{
  "type": "Feature",
  "properties": {
    "iso:country":"BE",
    "sg:address":"Dokter E. Rubbenslaan 5",
    "sg:city":"Lede",
    "sg:classifiers":[
        {
            "category":"Utilities",
            "subcategory":"Telephone",
            "type":"Services"
        }
    ],
    "sg:phone":"+32 53 80 00 38",
    "sg:postcode":"9340",
    "sg:province":"Oost-Vlaanderen",
    "sg:tags":[
        "-",
        "internet"
    ],
    "wof:name":"File Nv",
    "wof:placetype":"venue"
},
  "geometry": {"coordinates":[3.9877479076,50.9720954895],"type":"Point"}
}