{
  "type": "Feature",
  "properties": {
    "iso:country":"BE",
    "sg:address":"Grand Rue 25-123",
    "sg:city":"Ottignies-louvain-la-neuve (louvain-la-neuve)",
    "sg:classifiers":[
        {
            "category":"Health Services",
            "subcategory":"Dentist",
            "type":"Services"
        }
    ],
    "sg:phone":"+32 10 45 18 49",
    "sg:postcode":"1348",
    "sg:province":"Brabant Wallon",
    "wof:name":"Laal Riahi Christian",
    "wof:placetype":"venue"
},
  "geometry": {"coordinates":[4.614274025,50.6692466736],"type":"Point"}
}