{
  "type": "Feature",
  "properties": {
    "iso:country":"BE",
    "sg:address":"Rue Ortho 16",
    "sg:city":"La Roche-en-ardenne",
    "sg:classifiers":[
        {
            "category":"Cafe",
            "type":"Food & Drink"
        }
    ],
    "sg:phone":"+32 84 43 31 19",
    "sg:postcode":"6983",
    "sg:province":"Luxembourg",
    "sg:tags":[
        "caf\u00e9s"
    ],
    "wof:name":"Caf\u00c9 Des Sports",
    "wof:placetype":"venue"
},
  "geometry": {"coordinates":[5.6177611351,50.1462554932],"type":"Point"}
}