{
  "type": "Feature",
  "properties": {
    "iso:country":"BE",
    "sg:address":"Van Vlaanderenpln 7",
    "sg:city":"Gent",
    "sg:classifiers":[
        {
            "category":"Banks & Credit Unions",
            "subcategory":"Bank",
            "type":"Services"
        }
    ],
    "sg:phone":"+32 53 23 33 09",
    "sg:postcode":"9000",
    "sg:province":"Oost-Vlaanderen",
    "wof:name":"Banque Bruxelles Lambert Sa",
    "wof:placetype":"venue"
},
  "geometry": {"coordinates":[3.7320649624,51.0481872559],"type":"Point"}
}