{
  "type": "Feature",
  "properties": {
    "iso:country":"BE",
    "sg:address":"Bredestraat 90",
    "sg:city":"Lovendegem",
    "sg:classifiers":[
        {
            "category":"Cafe",
            "type":"Food & Drink"
        }
    ],
    "sg:phone":"+32 9 372 87 99",
    "sg:postcode":"9920",
    "sg:province":"Oost-Vlaanderen",
    "sg:tags":[
        "caf\u00e9s"
    ],
    "wof:name":"Anna Mestach",
    "wof:placetype":"venue"
},
  "geometry": {"coordinates":[3.6237709522,51.1106948853],"type":"Point"}
}