{
  "type": "Feature",
  "properties": {
    "iso:country":"BE",
    "sg:address":"Rue L\u00c9on Henrard 16",
    "sg:city":"Vresse-sur-semois",
    "sg:orig_category":"Location d'articles de sport, de sport nautique and de camping. Installations and terrains de sport ",
    "sg:phone":"+32 61 50 03 81",
    "sg:postcode":"5550",
    "sg:province":"Namur",
    "wof:name":"R\u00c9cr\u00c9alle-descente De La Semois",
    "wof:placetype":"venue"
},
  "geometry": {"coordinates":[4.9336900711,49.8729820251],"type":"Point"}
}