{
  "type": "Feature",
  "properties": {
    "iso:country":"BE",
    "sg:address":"Bruggesteenweg 117",
    "sg:city":"Middelkerke",
    "sg:orig_category":"Eleveurs and marchands de porcs. Eleveurs de bovins",
    "sg:phone":"+32 58 23 40 86",
    "sg:postcode":"8433",
    "sg:province":"West-Vlaanderen",
    "wof:name":"Gerard Logier",
    "wof:placetype":"venue"
},
  "geometry": {"coordinates":[2.8315300941,51.1189155579],"type":"Point"}
}