{
  "type": "Feature",
  "properties": {
    "addr:full":"Rue Z\u00e9nobe Gramme 21 Arlon Luxembourg 6700",
    "addr:housenumber":"21",
    "addr:postcode":"6700",
    "addr:street":"Rue Ze\u0301Nobe Gramme",
    "iso:country":"BE",
    "sg:address":"Rue Z\u00e9nobe Gramme 21",
    "sg:city":"Arlon",
    "sg:classifiers":[
        {
            "category":"Health Services",
            "subcategory":"Health Practitioner",
            "type":"Services"
        }
    ],
    "sg:phone":"+32 63 23 75 85",
    "sg:postcode":"6700",
    "sg:province":"Luxembourg",
    "sg:tags":[
        "psychologist"
    ],
    "wof:name":"Rongvaux B",
    "wof:placetype":"venue"
},
  "geometry": {"coordinates":[5.805475235,49.6798477173],"type":"Point"}
}