{
  "type": "Feature",
  "properties": {
    "iso:country":"BE",
    "sg:address":"Vivensteenweg 7",
    "sg:city":"Damme",
    "sg:orig_category":"Eleveurs de bovins",
    "sg:phone":"+32 50 35 39 02",
    "sg:postcode":"8340",
    "sg:province":"West-Vlaanderen",
    "wof:name":"Gustaaf Valcke",
    "wof:placetype":"venue"
},
  "geometry": {"coordinates":[3.2953810692,51.2380752563],"type":"Point"}
}