{
  "type": "Feature",
  "properties": {
    "iso:country":"BE",
    "sg:address":"Gelaagstraat 18",
    "sg:city":"Temse",
    "sg:classifiers":[
        {
            "category":"Arena",
            "subcategory":"Sports Club",
            "type":"Entertainment"
        }
    ],
    "sg:phone":"+32 3 774 31 51",
    "sg:postcode":"9140",
    "sg:province":"Oost-Vlaanderen",
    "sg:tags":[
        "de"
    ],
    "wof:name":"Aan Ons De Toekomst",
    "wof:placetype":"venue"
},
  "geometry": {"coordinates":[4.2722268105,51.1245765686],"type":"Point"}
}