{
  "type": "Feature",
  "properties": {
    "iso:country":"BE",
    "sg:address":"Churchilllaan 224",
    "sg:city":"Schoten",
    "sg:classifiers":[
        {
            "category":"Fast Food",
            "type":"Food & Drink"
        }
    ],
    "sg:phone":"+32 3 658 87 29",
    "sg:postcode":"2900",
    "sg:province":"Antwerpen",
    "sg:tags":[
        "meeneem",
        "restaurant"
    ],
    "wof:name":"Peking",
    "wof:placetype":"venue"
},
  "geometry": {"coordinates":[4.486120224,51.2499961853],"type":"Point"}
}