{
  "type": "Feature",
  "properties": {
    "addr:full":"Chauss\u00c9e De Haecht 1465 Brussel/bruxelles Bruxelles-Capitale 1130",
    "addr:postcode":"1465;/ bruxelles;1130",
    "addr:street":"Chausse\u0301E De Haecht",
    "iso:country":"BE",
    "sg:address":"Chauss\u00c9e De Haecht 1465",
    "sg:city":"Brussel/bruxelles",
    "sg:orig_category":"Rev\u00eatements pour sols and murs. Rev\u00eatements de sols and murs. Eclairage et \u00e9quipements du foyer",
    "sg:phone":"+32 2 245 10 50",
    "sg:postcode":"1130",
    "sg:province":"Bruxelles-Capitale",
    "wof:name":"Crombe",
    "wof:placetype":"venue"
},
  "geometry": {"coordinates":[4.4228749275,50.8864173889],"type":"Point"}
}