{
  "type": "Feature",
  "properties": {
    "addr:full":"Fabrieksstraat 41 Brussel/bruxelles Bruxelles-Capitale 1000",
    "addr:housenumber":"41",
    "addr:postcode":"1000",
    "addr:street":"Fabrieksstraat;/",
    "iso:country":"BE",
    "sg:address":"Fabrieksstraat 41",
    "sg:city":"Brussel/bruxelles",
    "sg:orig_category":"Geschenken and souvenirs Verlichting and huishoudartikelen",
    "sg:phone":"+32 2 512 41 13",
    "sg:postcode":"1000",
    "sg:province":"Bruxelles-Capitale",
    "wof:name":"Belgian Souvenirs",
    "wof:placetype":"venue"
},
  "geometry": {"coordinates":[4.3407578468,50.8489303589],"type":"Point"}
}