{
  "type": "Feature",
  "properties": {
    "iso:country":"BE",
    "sg:address":"Kapellestraat 90",
    "sg:city":"Mol",
    "sg:classifiers":[
        {
            "category":"Retail",
            "subcategory":"Event Space",
            "type":"Services"
        }
    ],
    "sg:phone":"+32 14 31 41 05",
    "sg:postcode":"2400",
    "sg:province":"Antwerpen",
    "sg:tags":[
        "rental",
        "-",
        "hall"
    ],
    "wof:name":"Parochie Centrum",
    "wof:placetype":"venue"
},
  "geometry": {"coordinates":[5.1290698051,51.1981201172],"type":"Point"}
}