{
  "type": "Feature",
  "properties": {
    "addr:full":"Rue Bureau 9 Fl\u00e9ron Li\u00e8ge 4620",
    "addr:housenumber":"9",
    "addr:postcode":"4620",
    "addr:street":"Rue Bureau",
    "iso:country":"BE",
    "sg:address":"Rue Bureau 9",
    "sg:city":"Fl\u00e9ron",
    "sg:classifiers":[
        {
            "category":"Personal",
            "subcategory":"Beauty Salon",
            "type":"Services"
        }
    ],
    "sg:phone":"+32 4 358 34 28",
    "sg:postcode":"4620",
    "sg:province":"Li\u00e8ge",
    "sg:tags":[
        "lady",
        "-",
        "hairdressing"
    ],
    "wof:name":"Camille Albane",
    "wof:placetype":"venue"
},
  "geometry": {"coordinates":[5.6895179749,50.6143608093],"type":"Point"}
}