{
  "type": "Feature",
  "properties": {
    "addr:full":"Kanaaldijk 6 Ravels Antwerpen 2380",
    "addr:housenumber":"6",
    "addr:postcode":"2380",
    "addr:street":"Kanaaldijk",
    "iso:country":"BE",
    "sg:address":"Kanaaldijk 6",
    "sg:city":"Ravels",
    "sg:orig_category":"Ramassage and traitement des d\u00e9chets m\u00e9nagers",
    "sg:phone":"+32 14 43 80 43",
    "sg:postcode":"2380",
    "sg:province":"Antwerpen",
    "wof:name":"Van De Sande",
    "wof:placetype":"venue"
},
  "geometry": {"coordinates":[4.9876742363,51.3595924377],"type":"Point"}
}