{
  "type": "Feature",
  "properties": {
    "iso:country":"BE",
    "sg:address":"Rode Dries 2",
    "sg:city":"Grobbendonk",
    "sg:orig_category":"Installatie van houten of kunststof schrijnwerk Installatie van metalen schrijnwerk",
    "sg:phone":"+32 14 51 77 38",
    "sg:postcode":"2288",
    "sg:province":"Antwerpen",
    "wof:name":"Windey",
    "wof:placetype":"venue"
},
  "geometry": {"coordinates":[4.7594227791,51.1613006592],"type":"Point"}
}