{
  "type": "Feature",
  "properties": {
    "iso:country":"BE",
    "sg:address":"Rue De Bologne 29",
    "sg:city":"Habay-la-neuve",
    "sg:classifiers":[
        {
            "category":"Professional",
            "type":"Services"
        }
    ],
    "sg:phone":"+32 63 42 30 66",
    "sg:postcode":"6720",
    "sg:province":"Luxembourg",
    "sg:tags":[
        "transport"
    ],
    "wof:name":"Transud S.p.r.l.",
    "wof:placetype":"venue"
},
  "geometry": {"coordinates":[5.6405739784,49.7295074463],"type":"Point"}
}