{
  "type": "Feature",
  "properties": {
    "iso:country":"BE",
    "sg:address":"36",
    "sg:city":"Rue Des Fripiers 1000 Bruxelles",
    "sg:classifiers":[
        {
            "category":"Manufacturing",
            "subcategory":"Jewelry",
            "type":"Manufacturing & Wholesale Goods"
        }
    ],
    "sg:phone":"+32 2 218 11 93",
    "sg:postcode":"36",
    "sg:tags":[
        "product",
        "miscellaneous",
        "jewellery"
    ],
    "wof:name":"G Tollet Sa",
    "wof:placetype":"venue"
},
  "geometry": {"coordinates":[4.3518648148,50.8484115601],"type":"Point"}
}