{
  "type": "Feature",
  "properties": {
    "addr:full":"Diestersteenweg 330 Maaseik Limburg 3680",
    "addr:housenumber":"330",
    "addr:postcode":"3680",
    "addr:street":"Diestersteenweg",
    "iso:country":"BE",
    "sg:address":"Diestersteenweg 330",
    "sg:city":"Maaseik",
    "sg:orig_category":"Artsen and specialisten",
    "sg:phone":"+32 89 56 56 50",
    "sg:postcode":"3680",
    "sg:province":"Limburg",
    "wof:name":"Anja Vermeulen",
    "wof:placetype":"venue"
},
  "geometry": {"coordinates":[5.7496099472,51.1019210815],"type":"Point"}
}