{
  "type": "Feature",
  "properties": {
    "iso:country":"BE",
    "sg:address":"Vredestraat 1",
    "sg:city":"Beerse",
    "sg:classifiers":[
        {
            "category":"Personal",
            "subcategory":"Beauty Salon",
            "type":"Services"
        }
    ],
    "sg:phone":"+32 14 61 37 51",
    "sg:postcode":"2340",
    "sg:province":"Antwerpen",
    "sg:tags":[
        "lady",
        "-",
        "hairdressing"
    ],
    "wof:name":"Hair Style",
    "wof:placetype":"venue"
},
  "geometry": {"coordinates":[4.85607481,51.319896698],"type":"Point"}
}