{
  "type": "Feature",
  "properties": {
    "iso:country":"BE",
    "sg:address":"Stationsstraat 71b6",
    "sg:city":"Tervuren",
    "sg:orig_category":"Koerierbedrijven",
    "sg:phone":"+32 2 767 08 63",
    "sg:postcode":"3080",
    "sg:province":"Vlaams-Brabant",
    "wof:name":"Patrice Charbonnier",
    "wof:placetype":"venue"
},
  "geometry": {"coordinates":[4.5544548035,50.8391876221],"type":"Point"}
}