{
  "type": "Feature",
  "properties": {
    "addr:full":"Rue De Dinant 112 Tinlot Li\u00e8ge 4557",
    "addr:housenumber":"112",
    "addr:postcode":"4557",
    "addr:street":"Rue De Dinant",
    "iso:country":"BE",
    "sg:address":"Rue De Dinant 112",
    "sg:city":"Tinlot",
    "sg:orig_category":"Fotografen and fotostudio's",
    "sg:phone":"+32 85 51 34 35",
    "sg:postcode":"4557",
    "sg:province":"Li\u00e8ge",
    "wof:name":"Fe. Aerobel",
    "wof:placetype":"venue"
},
  "geometry": {"coordinates":[5.3894300461,50.5045166016],"type":"Point"}
}