{
  "type": "Feature",
  "properties": {
    "iso:country":"BE",
    "sg:address":"Hoepertingenstraat 7",
    "sg:city":"Borgloon (hoepertingen)",
    "sg:classifiers":[
        {
            "category":"Professional",
            "subcategory":"Lawyer & Legal Services",
            "type":"Services"
        }
    ],
    "sg:phone":"+32 12 74 17 68",
    "sg:postcode":"3840",
    "sg:province":"Limburg",
    "wof:name":"De Brabander Jean",
    "wof:placetype":"venue"
},
  "geometry": {"coordinates":[5.3441700935,50.8012466431],"type":"Point"}
}