{
  "type": "Feature",
  "properties": {
    "iso:country":"BE",
    "sg:address":"Wijnegemsteenweg 116",
    "sg:city":"Schilde ('s Gravenwezel)",
    "sg:classifiers":[
        {
            "category":"Retail",
            "subcategory":"Laundry & Dry Cleaning",
            "type":"Services"
        }
    ],
    "sg:phone":"+32 3 658 84 47",
    "sg:postcode":"2970",
    "sg:province":"Antwerpen",
    "wof:name":"Wezelse Wasserij Bvba",
    "wof:placetype":"venue"
},
  "geometry": {"coordinates":[4.5479688644,51.2567710876],"type":"Point"}
}