{
  "type": "Feature",
  "properties": {
    "iso:country":"BE",
    "sg:address":"Lombardstraat 34-42",
    "sg:city":"Brussel/bruxelles",
    "sg:orig_category":"Beroepsorganisaties Krantenuitgeverijen Tijdschriftenuitgeverijen",
    "sg:phone":"+32 2 545 56 00",
    "sg:postcode":"1000",
    "sg:province":"Bruxelles-Capitale",
    "wof:name":"Nat. Confed. Bouw - Conf\u00c9d. Nat. Construction",
    "wof:placetype":"venue"
},
  "geometry": {"coordinates":[4.3510780334,50.8455467224],"type":"Point"}
}