{
  "type": "Feature",
  "properties": {
    "iso:country":"BE",
    "sg:address":"Rue Saint-martin 66",
    "sg:city":"Sambreville",
    "sg:orig_category":"Artsen and specialisten",
    "sg:phone":"+32 71 77 23 65",
    "sg:postcode":"5060",
    "sg:province":"Namur",
    "wof:name":"Ch. Koulos",
    "wof:placetype":"venue"
},
  "geometry": {"coordinates":[4.5933699608,50.4375991821],"type":"Point"}
}