{
  "type": "Feature",
  "properties": {
    "addr:full":"Rue Du March\u00e9-au-beurre 7 Arlon Luxembourg 6700",
    "addr:housenumber":"7",
    "addr:postcode":"6700",
    "addr:street":"Rue Du Marche\u0301-Au-Beurre",
    "iso:country":"BE",
    "sg:address":"Rue Du March\u00e9-au-beurre 7",
    "sg:city":"Arlon",
    "sg:classifiers":[
        {
            "category":"Recreation",
            "subcategory":"Fishing",
            "type":"Entertainment"
        }
    ],
    "sg:phone":"+32 63 22 03 36",
    "sg:postcode":"6700",
    "sg:province":"Luxembourg",
    "sg:tags":[
        "tackle"
    ],
    "wof:name":"Bernard P\u00eache",
    "wof:placetype":"venue"
},
  "geometry": {"coordinates":[5.814994812,49.6833724976],"type":"Point"}
}