{
  "type": "Feature",
  "properties": {
    "addr:full":"Paddenhoek 37 Sint-martens-latem Oost-Vlaanderen 9830",
    "addr:housenumber":"37",
    "addr:postcode":"9830",
    "addr:street":"Paddenhoek",
    "iso:country":"BE",
    "sg:address":"Paddenhoek 37",
    "sg:city":"Sint-martens-latem",
    "sg:classifiers":[
        {
            "category":"Communications",
            "subcategory":"Film & Video Production",
            "type":"Services"
        }
    ],
    "sg:phone":"+32 9 282 74 81",
    "sg:postcode":"9830",
    "sg:province":"Oost-Vlaanderen",
    "sg:tags":[
        "realisation",
        "-"
    ],
    "wof:name":"Van Coillie",
    "wof:placetype":"venue"
},
  "geometry": {"coordinates":[3.6386249065,51.0118675232],"type":"Point"}
}