{
  "type": "Feature",
  "properties": {
    "addr:full":"Overwinningstraat 21 Willebroek Antwerpen 2830",
    "addr:housenumber":"21",
    "addr:postcode":"2830",
    "addr:street":"Overwinningstraat",
    "iso:country":"BE",
    "sg:address":"Overwinningstraat 21",
    "sg:city":"Willebroek",
    "sg:classifiers":[
        {
            "category":"Shopping",
            "subcategory":"Clothing, Apparel, & Fashions",
            "type":"Retail Goods"
        }
    ],
    "sg:phone":"+32 3 866 09 77",
    "sg:postcode":"2830",
    "sg:province":"Antwerpen",
    "sg:tags":[
        "underwear",
        "lingerie",
        "-"
    ],
    "wof:name":"Linda",
    "wof:placetype":"venue"
},
  "geometry": {"coordinates":[4.3601360321,51.0593528748],"type":"Point"}
}