{
  "type": "Feature",
  "properties": {
    "addr:full":"Vogelwikkestraat 9 Evergem Oost-Vlaanderen 9940",
    "addr:housenumber":"9",
    "addr:postcode":"9940",
    "addr:street":"Vogelwikkestraat;Oost-Vlaanderen",
    "iso:country":"BE",
    "sg:address":"Vogelwikkestraat 9",
    "sg:city":"Evergem",
    "sg:orig_category":"Sportclubs",
    "sg:phone":"+32 9 253 98 44",
    "sg:postcode":"9940",
    "sg:province":"Oost-Vlaanderen",
    "wof:name":"Rap & Vrank Sleidinge",
    "wof:placetype":"venue"
},
  "geometry": {"coordinates":[3.7241799831,51.1129150391],"type":"Point"}
}