{
  "type": "Feature",
  "properties": {
    "iso:country":"BE",
    "sg:address":"Markt 4",
    "sg:city":"Sint-katelijne-waver",
    "sg:classifiers":[
        {
            "category":"Social Services",
            "subcategory":"Child Care",
            "type":"Services"
        }
    ],
    "sg:phone":"+32 15 31 75 11",
    "sg:postcode":"2860",
    "sg:province":"Antwerpen",
    "sg:tags":[
        "baby",
        "nursery",
        "day",
        "sitting"
    ],
    "wof:name":"Buitenschoolse Kinderopvang",
    "wof:placetype":"venue"
},
  "geometry": {"coordinates":[4.5338730812,51.0684928894],"type":"Point"}
}