{
  "type": "Feature",
  "properties": {
    "iso:country":"BE",
    "sg:address":"Bld Prince De Li\u00c8ge 40b2",
    "sg:city":"Anderlecht/anderlecht",
    "sg:orig_category":"M\u00e9decins and sp\u00e9cialistes",
    "sg:phone":"+32 2 523 43 86",
    "sg:postcode":"1070",
    "sg:province":"Bruxelles-Capitale",
    "wof:name":"Luc De Keyzer",
    "wof:placetype":"venue"
},
  "geometry": {"coordinates":[4.2998161316,50.8459320068],"type":"Point"}
}