{
  "type": "Feature",
  "properties": {
    "addr:full":"Rue De La Marjolaine 10 Brussel/bruxelles Bruxelles-Capitale 1120",
    "addr:housenumber":"10",
    "addr:postcode":"1120",
    "addr:street":"Rue De La Marjolaine;/",
    "iso:country":"BE",
    "sg:address":"Rue De La Marjolaine 10",
    "sg:city":"Brussel/bruxelles",
    "sg:orig_category":"Artistes ind\u00e9pendants",
    "sg:phone":"+32 2 216 67 48",
    "sg:postcode":"1120",
    "sg:province":"Bruxelles-Capitale",
    "wof:name":"Roland",
    "wof:placetype":"venue"
},
  "geometry": {"coordinates":[4.3871850967,50.8919487],"type":"Point"}
}