{
  "type": "Feature",
  "properties": {
    "iso:country":"BE",
    "sg:address":"Rue Des Corriers 14",
    "sg:city":"Tournai",
    "sg:orig_category":"Overheidsdiensten",
    "sg:phone":"+32 69 22 71 69",
    "sg:postcode":"7500",
    "sg:province":"Hainaut",
    "wof:name":"Admin. Contrib. Directes",
    "wof:placetype":"venue"
},
  "geometry": {"coordinates":[3.3854720592,50.6095046997],"type":"Point"}
}