{
  "type": "Feature",
  "properties": {
    "iso:country":"BE",
    "sg:address":"Steenputstraat 24",
    "sg:city":"Nevele",
    "sg:orig_category":"Rundveehouders Varkenskwekers",
    "sg:phone":"+32 9 371 59 24",
    "sg:postcode":"9850",
    "sg:province":"Oost-Vlaanderen",
    "wof:name":"Herve Sergeant",
    "wof:placetype":"venue"
},
  "geometry": {"coordinates":[3.55032897,51.0460586548],"type":"Point"}
}