{
  "type": "Feature",
  "properties": {
    "iso:country":"BE",
    "sg:address":"Rue De La Pompe 48",
    "sg:city":"Mettet",
    "sg:classifiers":[
        {
            "category":"Insurance",
            "subcategory":"Life Insurance",
            "type":"Services"
        }
    ],
    "sg:phone":"+32 71 72 96 91",
    "sg:postcode":"5640",
    "sg:province":"Namur",
    "sg:tags":[
        "assurance"
    ],
    "wof:name":"Portinvest",
    "wof:placetype":"venue"
},
  "geometry": {"coordinates":[4.6578397751,50.3198051453],"type":"Point"}
}