{
  "type": "Feature",
  "properties": {
    "iso:country":"BE",
    "sg:address":"Magerhoek 18",
    "sg:city":"Destelbergen",
    "sg:orig_category":"Drogueries",
    "sg:phone":"+32 9 232 12 72",
    "sg:postcode":"9070",
    "sg:province":"Oost-Vlaanderen",
    "wof:name":"Johan Leyman",
    "wof:placetype":"venue"
},
  "geometry": {"coordinates":[3.815778017,51.0246162415],"type":"Point"}
}