{
  "type": "Feature",
  "properties": {
    "addr:full":"Nieuwkerkenstraat 230 Sint-niklaas (nieuwkerken-waas) Oost-Vlaanderen 9100",
    "addr:housenumber":"230",
    "addr:postcode":"9100",
    "addr:street":"Nieuwkerkenstraat",
    "iso:country":"BE",
    "sg:address":"Nieuwkerkenstraat 230",
    "sg:city":"Sint-niklaas (nieuwkerken-waas)",
    "sg:classifiers":[
        {
            "category":"Personal",
            "subcategory":"Beauty Salon",
            "type":"Services"
        }
    ],
    "sg:phone":"+32 3 766 74 16",
    "sg:postcode":"9100",
    "sg:province":"Oost-Vlaanderen",
    "wof:name":"Carla",
    "wof:placetype":"venue"
},
  "geometry": {"coordinates":[4.1844358444,51.1862373352],"type":"Point"}
}