{
  "type": "Feature",
  "properties": {
    "iso:country":"BE",
    "sg:address":"Eksaarde Dorp 25",
    "sg:city":"Lokeren (eksaarde)",
    "sg:classifiers":[
        {
            "category":"Shopping",
            "subcategory":"Optician",
            "type":"Retail Goods"
        }
    ],
    "sg:phone":"+32 9 346 84 82",
    "sg:postcode":"9160",
    "sg:province":"Oost-Vlaanderen",
    "sg:tags":[
        "-"
    ],
    "wof:name":"Snel-optiek Bvba",
    "wof:placetype":"venue"
},
  "geometry": {"coordinates":[3.9627809525,51.1151809692],"type":"Point"}
}