{
  "type": "Feature",
  "properties": {
    "addr:full":"Schansstraat 40 Mol Antwerpen 2400",
    "addr:housenumber":"40",
    "addr:postcode":"2400",
    "addr:street":"Schansstraat",
    "iso:country":"BE",
    "sg:address":"Schansstraat 40",
    "sg:city":"Mol",
    "sg:orig_category":"Brandweer and civiele bescherming",
    "sg:phone":"+32 14 33 07 20",
    "sg:postcode":"2400",
    "sg:province":"Antwerpen",
    "wof:name":"Brandweerkazerne",
    "wof:placetype":"venue"
},
  "geometry": {"coordinates":[5.1157650948,51.186756134],"type":"Point"}
}