{
  "type": "Feature",
  "properties": {
    "addr:full":"Rue Alphonse Collette 24 Theux (polleur) Li\u00e8ge 4910",
    "addr:housenumber":"24",
    "addr:postcode":"4910",
    "addr:street":"Rue Alphonse Collette",
    "iso:country":"BE",
    "sg:address":"Rue Alphonse Collette 24",
    "sg:city":"Theux (polleur)",
    "sg:classifiers":[
        {
            "category":"Utilities",
            "subcategory":"Recycling",
            "type":"Services"
        }
    ],
    "sg:phone":"+32 87 22 45 85",
    "sg:postcode":"4910",
    "sg:province":"Li\u00e8ge",
    "sg:tags":[
        "rubbish",
        "removal"
    ],
    "wof:name":"Bollette Michel",
    "wof:placetype":"venue"
},
  "geometry": {"coordinates":[5.8130488396,50.5356216431],"type":"Point"}
}