{
  "type": "Feature",
  "properties": {
    "addr:full":"Constant Permekelaan 61 Jabbeke West-Vlaanderen 8490",
    "addr:housenumber":"61",
    "addr:postcode":"8490",
    "addr:street":"Constant Permekelaan",
    "iso:country":"BE",
    "sg:address":"Constant Permekelaan 61",
    "sg:city":"Jabbeke",
    "sg:orig_category":"Advocaten and juridische adviseurs",
    "sg:phone":"+32 50 81 52 58",
    "sg:postcode":"8490",
    "sg:province":"West-Vlaanderen",
    "wof:name":"Franky Baert",
    "wof:placetype":"venue"
},
  "geometry": {"coordinates":[3.0981431007,51.1809425354],"type":"Point"}
}