{
  "type": "Feature",
  "properties": {
    "addr:full":"Rue De Baudour 101 Jurbise Hainaut 7050",
    "addr:housenumber":"101",
    "addr:postcode":"7050",
    "addr:street":"Rue De Baudour",
    "iso:country":"BE",
    "sg:address":"Rue De Baudour 101",
    "sg:city":"Jurbise",
    "sg:orig_category":"Eleveurs de bovins. Eleveurs and marchands de porcs",
    "sg:phone":"+32 65 22 99 59",
    "sg:postcode":"7050",
    "sg:province":"Hainaut",
    "wof:name":"Bernard Galant",
    "wof:placetype":"venue"
},
  "geometry": {"coordinates":[3.8503990173,50.5197601318],"type":"Point"}
}