{
  "type": "Feature",
  "properties": {
    "iso:country":"BE",
    "sg:address":"Boulevard Paepsem 20a",
    "sg:city":"Anderlecht",
    "sg:orig_category":"Evaluation and estimation de biens immobiliers. Agences immobili\u00e8res",
    "sg:phone":"+32 2 521 46 46",
    "sg:postcode":"1070",
    "sg:province":"Bruxelles-Capitale",
    "wof:name":"Immeubles & Industries",
    "wof:placetype":"venue"
},
  "geometry": {"coordinates":[4.3128418922,50.8239364624],"type":"Point"}
}