{
  "type": "Feature",
  "properties": {
    "iso:country":"BE",
    "sg:address":"Potaardestraat 123",
    "sg:city":"Temse",
    "sg:orig_category":"Loodgieterij, verwarming and sanitaire installaties",
    "sg:phone":"+32 3 771 43 24",
    "sg:postcode":"9140",
    "sg:province":"Oost-Vlaanderen",
    "wof:name":"Van Cleemput Dirk",
    "wof:placetype":"venue"
},
  "geometry": {"coordinates":[4.2253541946,51.1381034851],"type":"Point"}
}