{
  "type": "Feature",
  "properties": {
    "iso:country":"BE",
    "sg:address":"Quai De L'industrie 170",
    "sg:city":"Anderlecht/anderlecht",
    "sg:orig_category":"Enseignement sup\u00e9rieur",
    "sg:phone":"+32 2 523 37 37",
    "sg:postcode":"1070",
    "sg:province":"Bruxelles-Capitale",
    "wof:name":"Erasmushogeschool",
    "wof:placetype":"venue"
},
  "geometry": {"coordinates":[4.3181500435,50.8375282288],"type":"Point"}
}