{
  "type": "Feature",
  "properties": {
    "iso:country":"BE",
    "sg:address":"Kluizenhof 33",
    "sg:city":"Sint-gillis-waas",
    "sg:classifiers":[
        {
            "category":"Wholesale",
            "subcategory":"Seafood",
            "type":"Manufacturing & Wholesale Goods"
        }
    ],
    "sg:phone":"+32 3 770 77 69",
    "sg:postcode":"9170",
    "sg:province":"Oost-Vlaanderen",
    "sg:tags":[
        "whol",
        "fish",
        "-",
        "shellfish"
    ],
    "wof:name":"Van Biesen-pieters Bvba",
    "wof:placetype":"venue"
},
  "geometry": {"coordinates":[4.0898981094,51.2282104492],"type":"Point"}
}