{
  "type": "Feature",
  "properties": {
    "iso:country":"BE",
    "sg:address":"Groeningerstraat 31",
    "sg:city":"Borsbeek",
    "sg:classifiers":[
        {
            "category":"Retail",
            "subcategory":"Auto Rental",
            "type":"Services"
        }
    ],
    "sg:phone":"+32 3 322 06 00",
    "sg:postcode":"2150",
    "sg:province":"Antwerpen",
    "sg:tags":[
        "mazda",
        "automobile",
        "v\u00e9hicules"
    ],
    "wof:name":"Garage Schelkens Bvba",
    "wof:placetype":"venue"
},
  "geometry": {"coordinates":[4.4773759842,51.1956939697],"type":"Point"}
}