{
  "type": "Feature",
  "properties": {
    "addr:full":"Rue A. France 115 La Louvi\u00c8re (groot) Hainaut 7100",
    "addr:housenumber":"115",
    "addr:postcode":"7100",
    "addr:street":"Rue A.;Hainaut",
    "iso:country":"BE",
    "sg:address":"Rue A. France 115",
    "sg:city":"La Louvi\u00c8re (groot)",
    "sg:classifiers":[
        {
            "category":"Personal",
            "subcategory":"Beauty Salon",
            "type":"Services"
        }
    ],
    "sg:phone":"+32 64 26 43 25",
    "sg:postcode":"7100",
    "sg:province":"Hainaut",
    "sg:tags":[
        "de",
        "coiffure"
    ],
    "wof:name":"L'uomo",
    "wof:placetype":"venue"
},
  "geometry": {"coordinates":[4.1913690567,50.4809112549],"type":"Point"}
}