{
  "type": "Feature",
  "properties": {
    "iso:country":"BE",
    "sg:address":"Van Humbeekstraat (pierre) 5",
    "sg:city":"Brussel",
    "sg:classifiers":[
        {
            "category":"Food & Beverages",
            "subcategory":"Liquor & Beverages",
            "type":"Retail Goods"
        }
    ],
    "sg:phone":"+32 2 410 47 47",
    "sg:postcode":"1080",
    "sg:province":"Bruxelles-Capitale",
    "sg:tags":[
        "champagne"
    ],
    "wof:name":"Cinoco S.a.",
    "wof:placetype":"venue"
},
  "geometry": {"coordinates":[4.324669838,50.8495025635],"type":"Point"}
}