{
  "type": "Feature",
  "properties": {
    "addr:full":"Amerikalei 197 Antwerpen Antwerpen 2000",
    "addr:housenumber":"197",
    "addr:postcode":"2000",
    "addr:street":"Amerikalei",
    "iso:country":"BE",
    "sg:address":"Amerikalei 197",
    "sg:city":"Antwerpen",
    "sg:classifiers":[
        {
            "category":"Shopping",
            "subcategory":"Pets & Pet Supplies",
            "type":"Retail Goods"
        }
    ],
    "sg:phone":"+32 3 238 97 14",
    "sg:postcode":"2000",
    "sg:province":"Antwerpen",
    "sg:tags":[
        "aquarium",
        "accessory"
    ],
    "wof:name":"Lotus",
    "wof:placetype":"venue"
},
  "geometry": {"coordinates":[4.3910808563,51.2048301697],"type":"Point"}
}