{
  "type": "Feature",
  "properties": {
    "iso:country":"BE",
    "sg:address":"Ch. De Roodebeek 451",
    "sg:city":"Brussel/bruxelles",
    "sg:orig_category":"Electrom\u00e9nager, t\u00e9l\u00e9visions and radios. Ordinateurs and \u00e9quipement informatique",
    "sg:phone":"+32 2 772 24 34",
    "sg:postcode":"1200",
    "sg:province":"Bruxelles-Capitale",
    "wof:name":"Multihard Sprl",
    "wof:placetype":"venue"
},
  "geometry": {"coordinates":[4.4161667824,50.8500022888],"type":"Point"}
}