{
  "type": "Feature",
  "properties": {
    "iso:country":"BE",
    "sg:address":"Rue Du Manypr\u00c9 79",
    "sg:city":"Chaumont-gistoux",
    "sg:classifiers":[
        {
            "category":"Restaurant",
            "type":"Food & Drink"
        }
    ],
    "sg:phone":"+32 10 68 08 42",
    "sg:postcode":"1325",
    "sg:province":"Brabant Wallon",
    "wof:name":"La Thaini\u00c8re",
    "wof:placetype":"venue"
},
  "geometry": {"coordinates":[4.6823129654,50.6698455811],"type":"Point"}
}