{
  "type": "Feature",
  "properties": {
    "iso:country":"BE",
    "sg:address":"Venstraat 153a",
    "sg:city":"Schoten",
    "sg:classifiers":[
        {
            "category":"Professional",
            "subcategory":"Lawyer & Legal Services",
            "type":"Services"
        }
    ],
    "sg:phone":"+32 3 685 00 73",
    "sg:postcode":"2900",
    "sg:province":"Antwerpen",
    "wof:name":"Janssens Philippe",
    "wof:placetype":"venue"
},
  "geometry": {"coordinates":[4.505947113,51.2507743835],"type":"Point"}
}