{
  "type": "Feature",
  "properties": {
    "iso:country":"BE",
    "sg:address":"Kleehofkensstraat 46",
    "sg:city":"Bilzen (mopertingen)",
    "sg:classifiers":[
        {
            "category":"Shopping",
            "subcategory":"Bicycles & Sporting Goods",
            "type":"Retail Goods"
        }
    ],
    "sg:phone":"+32 89 50 21 13",
    "sg:postcode":"3740",
    "sg:province":"Limburg",
    "sg:tags":[
        "-"
    ],
    "wof:name":"De Muynck",
    "wof:placetype":"venue"
},
  "geometry": {"coordinates":[5.578098774,50.8615951538],"type":"Point"}
}