{
  "type": "Feature",
  "properties": {
    "addr:full":"Gennevaux 7 Musson Luxembourg 6750",
    "addr:housenumber":"7",
    "addr:postcode":"6750",
    "addr:street":"Gennevaux",
    "iso:country":"BE",
    "sg:address":"Gennevaux 7",
    "sg:city":"Musson",
    "sg:orig_category":"Tuinen",
    "sg:phone":"+32 63 67 88 60",
    "sg:postcode":"6750",
    "sg:province":"Luxembourg",
    "wof:name":"Deaulmerie",
    "wof:placetype":"venue"
},
  "geometry": {"coordinates":[5.7003917694,49.5682640076],"type":"Point"}
}