{
  "type": "Feature",
  "properties": {
    "addr:full":"Rue Des Tongres 26ba Etterbeek/etterbeek Bruxelles-Capitale 1040",
    "addr:housenumber":"26ba",
    "addr:postcode":"1040",
    "addr:street":"Rue Des Tongres",
    "iso:country":"BE",
    "sg:address":"Rue Des Tongres 26ba",
    "sg:city":"Etterbeek/etterbeek",
    "sg:orig_category":"Maroquinerie and articles de voyage",
    "sg:phone":"+32 2 733 23 10",
    "sg:postcode":"1040",
    "sg:province":"Bruxelles-Capitale",
    "wof:name":"Passy",
    "wof:placetype":"venue"
},
  "geometry": {"coordinates":[4.3997211456,50.8399200439],"type":"Point"}
}