{
  "type": "Feature",
  "properties": {
    "iso:country":"BE",
    "sg:address":"Rue De Luxembourg 58",
    "sg:city":"Marche-en-famenne",
    "sg:classifiers":[
        {
            "category":"Fast Food",
            "type":"Food & Drink"
        }
    ],
    "sg:phone":"+32 84 31 56 07",
    "sg:postcode":"6900",
    "sg:province":"Luxembourg",
    "sg:tags":[
        "\u00c0",
        "emporter",
        "restaurants"
    ],
    "wof:name":"Pizza Akdeniz",
    "wof:placetype":"venue"
},
  "geometry": {"coordinates":[5.3453631401,50.2225608826],"type":"Point"}
}