{
  "type": "Feature",
  "properties": {
    "addr:full":"Kerkstraat 20 Oostrozebeke West-Vlaanderen 8780",
    "addr:housenumber":"20",
    "addr:postcode":"8780",
    "addr:street":"Kerkstraat",
    "iso:country":"BE",
    "sg:address":"Kerkstraat 20",
    "sg:city":"Oostrozebeke",
    "sg:orig_category":"Foto-uitrusting Fotografen and fotostudio's",
    "sg:phone":"+32 56 66 44 24",
    "sg:postcode":"8780",
    "sg:province":"West-Vlaanderen",
    "wof:name":"Foto Pollie",
    "wof:placetype":"venue"
},
  "geometry": {"coordinates":[3.3361189365,50.9211654663],"type":"Point"}
}