{
  "type": "Feature",
  "properties": {
    "iso:country":"BE",
    "sg:address":"Dokter Lemoinelaan 11b34",
    "sg:city":"Anderlecht",
    "sg:orig_category":"Woningbouw",
    "sg:phone":"+32 2 527 89 07",
    "sg:postcode":"1070",
    "sg:province":"Bruxelles-Capitale",
    "wof:name":"Build Belgian",
    "wof:placetype":"venue"
},
  "geometry": {"coordinates":[4.2844700813,50.8275604248],"type":"Point"}
}