{
  "type": "Feature",
  "properties": {
    "addr:full":"Neerloop 5b1 Lier Antwerpen 2500",
    "addr:housenumber":"5b1",
    "addr:postcode":"2500",
    "addr:street":"Neerloop",
    "iso:country":"BE",
    "sg:address":"Neerloop 5b1",
    "sg:city":"Lier",
    "sg:orig_category":"Groententeelt",
    "sg:phone":"+32 3 489 00 29",
    "sg:postcode":"2500",
    "sg:province":"Antwerpen",
    "wof:name":"Jos Ceulemans",
    "wof:placetype":"venue"
},
  "geometry": {"coordinates":[4.5977740288,51.1322822571],"type":"Point"}
}