{
  "type": "Feature",
  "properties": {
    "addr:full":"Schaapsdreef 27 Kortrijk West-Vlaanderen 8500",
    "addr:housenumber":"27",
    "addr:postcode":"8500",
    "addr:street":"Schaapsdreef",
    "iso:country":"BE",
    "sg:address":"Schaapsdreef 27",
    "sg:city":"Kortrijk",
    "sg:classifiers":[
        {
            "category":"Shopping",
            "subcategory":"Party Supplies",
            "type":"Retail Goods"
        }
    ],
    "sg:phone":"+32 56 22 83 17",
    "sg:postcode":"8500",
    "sg:province":"West-Vlaanderen",
    "sg:tags":[
        "technician",
        "equipment",
        "dental",
        "-",
        "dentist"
    ],
    "wof:name":"Codema Dental Materials Nv",
    "wof:placetype":"venue"
},
  "geometry": {"coordinates":[3.288711071,50.7997207642],"type":"Point"}
}