{
  "type": "Feature",
  "properties": {
    "addr:full":"Maexhofweg 10 Zonhoven Limburg 3520",
    "addr:housenumber":"10",
    "addr:postcode":"3520",
    "addr:street":"Maexhofweg",
    "iso:country":"BE",
    "sg:address":"Maexhofweg 10",
    "sg:city":"Zonhoven",
    "sg:classifiers":[
        {
            "category":"Arena",
            "subcategory":"Sports Club",
            "type":"Entertainment"
        }
    ],
    "sg:phone":"+32 11 82 31 56",
    "sg:postcode":"3520",
    "sg:province":"Limburg",
    "wof:name":"Bollen",
    "wof:placetype":"venue"
},
  "geometry": {"coordinates":[5.3916721344,50.9898719788],"type":"Point"}
}