{
  "type": "Feature",
  "properties": {
    "addr:full":"Rue Du N\u00e9ronry 1 Sprimont Li\u00e8ge 4140",
    "addr:housenumber":"1",
    "addr:postcode":"4140",
    "addr:street":"Rue Du Ne\u0301Ronry",
    "iso:country":"BE",
    "sg:address":"Rue Du N\u00e9ronry 1",
    "sg:city":"Sprimont",
    "sg:classifiers":[
        {
            "category":"Arena",
            "subcategory":"Sports Club",
            "type":"Entertainment"
        }
    ],
    "sg:phone":"+32 4 382 26 14",
    "sg:postcode":"4140",
    "sg:province":"Li\u00e8ge",
    "wof:name":"Tennis Club Tultay",
    "wof:placetype":"venue"
},
  "geometry": {"coordinates":[5.6607699394,50.5123786926],"type":"Point"}
}