{
  "type": "Feature",
  "properties": {
    "iso:country":"BE",
    "sg:address":"Stationsstraat 17",
    "sg:city":"Kluisbergen",
    "sg:orig_category":"Epiceries",
    "sg:phone":"+32 55 38 86 13",
    "sg:postcode":"9690",
    "sg:province":"Oost-Vlaanderen",
    "wof:name":"Huis Martens-moreel",
    "wof:placetype":"venue"
},
  "geometry": {"coordinates":[3.5096371174,50.7903747559],"type":"Point"}
}