{
  "type": "Feature",
  "properties": {
    "addr:full":"Rue Baudouin I 16 Anh\u00e9e Namur 5537",
    "addr:housenumber":"16",
    "addr:postcode":"5537",
    "addr:street":"Rue Baudouin I",
    "iso:country":"BE",
    "sg:address":"Rue Baudouin I 16",
    "sg:city":"Anh\u00e9e",
    "sg:classifiers":[
        {
            "category":"Banks & Credit Unions",
            "subcategory":"Bureau De Change",
            "type":"Services"
        }
    ],
    "sg:phone":"+32 82 61 46 58",
    "sg:postcode":"5537",
    "sg:province":"Namur",
    "sg:tags":[
        "-",
        "household",
        "gas"
    ],
    "wof:name":"Cassart R",
    "wof:placetype":"venue"
},
  "geometry": {"coordinates":[4.8833169937,50.3053207397],"type":"Point"}
}