{
  "type": "Feature",
  "properties": {
    "iso:country":"BE",
    "sg:address":"Rue Des Ecoles 50ba",
    "sg:city":"Ohey",
    "sg:orig_category":"Herstellingen and onderhoud van auto's",
    "sg:phone":"+32 85 61 10 39",
    "sg:postcode":"5351",
    "sg:province":"Namur",
    "wof:name":"Garage Verhest & Fils",
    "wof:placetype":"venue"
},
  "geometry": {"coordinates":[5.1507129669,50.4372367859],"type":"Point"}
}