{
  "type": "Feature",
  "properties": {
    "iso:country":"BE",
    "sg:address":"Ganzendries 19",
    "sg:city":"Gent-centrum",
    "sg:orig_category":"Balie van Gent. Avocats and conseillers juridiques",
    "sg:phone":"+32 9 222 09 75",
    "sg:postcode":"9000",
    "sg:province":"Oost-Vlaanderen",
    "wof:name":"Ruppel Dirk",
    "wof:placetype":"venue"
},
  "geometry": {"coordinates":[3.7125918865,51.0315170288],"type":"Point"}
}