{
  "type": "Feature",
  "properties": {
    "iso:country":"BE",
    "sg:address":"Dendermondse Steenweg 46",
    "sg:city":"Hamme",
    "sg:orig_category":"Quincailleries. Plomberie, chauffage and installations sanitaires. Charpentes and couvertures",
    "sg:phone":"+32 52 47 65 13",
    "sg:postcode":"9220",
    "sg:province":"Oost-Vlaanderen",
    "wof:name":"De Blende Jan",
    "wof:placetype":"venue"
},
  "geometry": {"coordinates":[4.1189680099,51.0697479248],"type":"Point"}
}