{
  "type": "Feature",
  "properties": {
    "addr:full":"Gistelse Steenweg 170 Brugge West-Vlaanderen 8200",
    "addr:housenumber":"170",
    "addr:postcode":"8200",
    "addr:street":"Gistelse Steenweg",
    "iso:country":"BE",
    "sg:address":"Gistelse Steenweg 170",
    "sg:city":"Brugge",
    "sg:orig_category":"Rundveehouders Slagers",
    "sg:phone":"+32 50 38 79 08",
    "sg:postcode":"8200",
    "sg:province":"West-Vlaanderen",
    "wof:name":"Paul Stubbe",
    "wof:placetype":"venue"
},
  "geometry": {"coordinates":[3.2001869678,51.2014389038],"type":"Point"}
}