{
  "type": "Feature",
  "properties": {
    "addr:full":"Joseph Stevensstraat 33 Brussel/bruxelles Bruxelles-Capitale 1000",
    "addr:housenumber":"33",
    "addr:postcode":"1000",
    "addr:street":"Joseph Stevensstraat;/",
    "iso:country":"BE",
    "sg:address":"Joseph Stevensstraat 33",
    "sg:city":"Brussel/bruxelles",
    "sg:orig_category":"Fotografen and fotostudio's",
    "sg:phone":"+32 2 502 87 62",
    "sg:postcode":"1000",
    "sg:province":"Bruxelles-Capitale",
    "wof:name":"Saskia Vanderstichele",
    "wof:placetype":"venue"
},
  "geometry": {"coordinates":[4.3532447815,50.8413162231],"type":"Point"}
}