{
  "type": "Feature",
  "properties": {
    "addr:full":"Halvemaanstraat 1a Damme (moerkerke) West-Vlaanderen 8340",
    "addr:housenumber":"1a",
    "addr:postcode":"8340",
    "addr:street":"Halvemaanstraat",
    "iso:country":"BE",
    "sg:address":"Halvemaanstraat 1a",
    "sg:city":"Damme (moerkerke)",
    "sg:classifiers":[
        {
            "category":"Banks & Credit Unions",
            "subcategory":"Investment Brokerage",
            "type":"Services"
        }
    ],
    "sg:phone":"+32 50 50 19 00",
    "sg:postcode":"8340",
    "sg:province":"West-Vlaanderen",
    "sg:tags":[
        "auditor"
    ],
    "wof:name":"Verminck J",
    "wof:placetype":"venue"
},
  "geometry": {"coordinates":[3.2815999985,51.2513160706],"type":"Point"}
}