{
  "type": "Feature",
  "properties": {
    "iso:country":"BE",
    "sg:address":"Alsembergse Steenweg 833",
    "sg:city":"Ukkel/uccle",
    "sg:orig_category":"Juwelen and horloges",
    "sg:phone":"+32 2 376 73 85",
    "sg:postcode":"1180",
    "sg:province":"Bruxelles-Capitale",
    "wof:name":"Joaillerie Tordeurs",
    "wof:placetype":"venue"
},
  "geometry": {"coordinates":[4.3363828659,50.8012733459],"type":"Point"}
}