{
  "type": "Feature",
  "properties": {
    "iso:country":"BE",
    "sg:address":"Veurtstraat 91",
    "sg:city":"Puurs (breendonk)",
    "sg:classifiers":[
        {
            "category":"Shopping",
            "subcategory":"Discount & Variety Stores",
            "type":"Retail Goods"
        }
    ],
    "sg:phone":"+32 52 38 11 11",
    "sg:postcode":"2870",
    "sg:province":"Antwerpen",
    "sg:tags":[
        "warehouse",
        "-",
        "merchandise"
    ],
    "wof:name":"Fiege Nv",
    "wof:placetype":"venue"
},
  "geometry": {"coordinates":[4.3236198425,51.0342254639],"type":"Point"}
}