{
  "type": "Feature",
  "properties": {
    "iso:country":"BE",
    "sg:address":"Tancremont 3",
    "sg:city":"Theux",
    "sg:classifiers":[
        {
            "category":"Tea Room",
            "subcategory":"None",
            "type":"Food & Drink"
        }
    ],
    "sg:phone":"+32 87 54 13 62",
    "sg:postcode":"4910",
    "sg:province":"Li\u00e8ge",
    "wof:name":"Tarterie De La Chapelle Sprl",
    "wof:placetype":"venue"
},
  "geometry": {"coordinates":[5.7952098846,50.548500061],"type":"Point"}
}