{
  "type": "Feature",
  "properties": {
    "iso:country":"BE",
    "sg:address":"Dokter Haubenlaan 34",
    "sg:city":"Maasmechelen",
    "sg:classifiers":[
        {
            "category":"Bars & Pubs",
            "type":"Food & Drink"
        }
    ],
    "sg:phone":"+32 89 76 04 11",
    "sg:postcode":"3630",
    "sg:province":"Limburg",
    "wof:name":"La Fete",
    "wof:placetype":"venue"
},
  "geometry": {"coordinates":[5.7017049789,50.9611053467],"type":"Point"}
}