{
  "type": "Feature",
  "properties": {
    "iso:country":"BE",
    "sg:address":"Nokerseweg 105b2",
    "sg:city":"Waregem",
    "sg:orig_category":"Antiquit\u00e9s",
    "sg:phone":"+32 56 60 90 86",
    "sg:postcode":"8790",
    "sg:province":"West-Vlaanderen",
    "wof:name":"Antiek Voltaire",
    "wof:placetype":"venue"
},
  "geometry": {"coordinates":[3.4579660892,50.8876495361],"type":"Point"}
}