{
  "type": "Feature",
  "properties": {
    "addr:full":"Zakstraat 9 Wellen Limburg 3830",
    "addr:housenumber":"9",
    "addr:postcode":"3830",
    "addr:street":"Zakstraat",
    "iso:country":"BE",
    "sg:address":"Zakstraat 9",
    "sg:city":"Wellen",
    "sg:orig_category":"Woningbouw",
    "sg:phone":"+32 12 74 52 15",
    "sg:postcode":"3830",
    "sg:province":"Limburg",
    "wof:name":"H En V",
    "wof:placetype":"venue"
},
  "geometry": {"coordinates":[5.3283948898,50.846118927],"type":"Point"}
}