{
  "type": "Feature",
  "properties": {
    "addr:full":"Rijselstraat 91 Brugge (sint-michiels) West-Vlaanderen 8200",
    "addr:housenumber":"91",
    "addr:postcode":"8200",
    "addr:street":"Rijselstraat",
    "iso:country":"BE",
    "sg:address":"Rijselstraat 91",
    "sg:city":"Brugge (sint-michiels)",
    "sg:classifiers":[
        {
            "category":"Shopping",
            "subcategory":"Clothing, Apparel, & Fashions",
            "type":"Retail Goods"
        }
    ],
    "sg:phone":"+32 50 38 38 25",
    "sg:postcode":"8200",
    "sg:province":"West-Vlaanderen",
    "sg:tags":[
        "clothing",
        "-",
        "gentleman"
    ],
    "wof:name":"Lava",
    "wof:placetype":"venue"
},
  "geometry": {"coordinates":[3.2113099098,51.1885986328],"type":"Point"}
}