{
  "type": "Feature",
  "properties": {
    "addr:full":"Europalaan 50 Genk Limburg 3600",
    "addr:housenumber":"50",
    "addr:postcode":"3600",
    "addr:street":"Europalaan",
    "iso:country":"BE",
    "sg:address":"Europalaan 50",
    "sg:city":"Genk",
    "sg:orig_category":"Avocats and conseillers juridiques",
    "sg:phone":"+32 89 35 55 64",
    "sg:postcode":"3600",
    "sg:province":"Limburg",
    "wof:name":"Anja Bijnens",
    "wof:placetype":"venue"
},
  "geometry": {"coordinates":[5.4977278709,50.9660224915],"type":"Point"}
}