{
  "type": "Feature",
  "properties": {
    "addr:full":"Groenebosdreef 4 Houthulst West-Vlaanderen 8650",
    "addr:housenumber":"4",
    "addr:postcode":"8650",
    "addr:street":"Groenebosdreef",
    "iso:country":"BE",
    "sg:address":"Groenebosdreef 4",
    "sg:city":"Houthulst",
    "sg:orig_category":"Eleveurs and marchands de porcs. Produits \u00e0 base de pommes de terre Fruits and l\u00e9gumes Gr",
    "sg:phone":"+32 51 54 40 85",
    "sg:postcode":"8650",
    "sg:province":"West-Vlaanderen",
    "wof:name":"Roger Desintebin",
    "wof:placetype":"venue"
},
  "geometry": {"coordinates":[2.9292800426,50.9583053589],"type":"Point"}
}