{
  "type": "Feature",
  "properties": {
    "iso:country":"BE",
    "sg:address":"Nieuwburcht 10",
    "sg:city":"Dendermonde",
    "sg:orig_category":"Maisons de repos and r\u00e9sidences",
    "sg:phone":"+32 52 21 90 69",
    "sg:postcode":"9200",
    "sg:province":"Oost-Vlaanderen",
    "wof:name":"Residentie Het Zilverpand",
    "wof:placetype":"venue"
},
  "geometry": {"coordinates":[4.090157032,51.0353126526],"type":"Point"}
}