{
  "type": "Feature",
  "properties": {
    "addr:full":"Barastraat 75 Anderlecht Bruxelles-Capitale 1070",
    "addr:housenumber":"75",
    "addr:postcode":"1070",
    "addr:street":"Barastraat",
    "iso:country":"BE",
    "sg:address":"Barastraat 75",
    "sg:city":"Anderlecht",
    "sg:orig_category":"Dameskledingzaken",
    "sg:phone":"+32 2 524 39 04",
    "sg:postcode":"1070",
    "sg:province":"Bruxelles-Capitale",
    "wof:name":"Couture H\u00c9l\u00c8ne",
    "wof:placetype":"venue"
},
  "geometry": {"coordinates":[4.3325390816,50.8369178772],"type":"Point"}
}