{
  "type": "Feature",
  "properties": {
    "iso:country":"BE",
    "sg:address":"Rue Baron Bouvier 14",
    "sg:city":"Incourt",
    "sg:orig_category":"Brood, gebak and snoepgoed",
    "sg:phone":"+32 10 88 80 88",
    "sg:postcode":"1315",
    "sg:province":"Brabant Wallon",
    "wof:name":"P\u00c2tisserie Benne",
    "wof:placetype":"venue"
},
  "geometry": {"coordinates":[4.8031859398,50.6918678284],"type":"Point"}
}