{
  "type": "Feature",
  "properties": {
    "addr:full":"Vijfwindgatenstraat 21 Gent Oost-Vlaanderen 9000",
    "addr:housenumber":"21",
    "addr:postcode":"9000",
    "addr:street":"Vijfwindgatenstraat;Oost-Vlaanderen",
    "iso:country":"BE",
    "sg:address":"Vijfwindgatenstraat 21",
    "sg:city":"Gent",
    "sg:classifiers":[
        {
            "category":"Professional",
            "subcategory":"Advertising",
            "type":"Services"
        }
    ],
    "sg:phone":"+32 9 268 27 11",
    "sg:postcode":"9000",
    "sg:province":"Oost-Vlaanderen",
    "sg:tags":[
        "telemarketing"
    ],
    "wof:name":"Mifratel",
    "wof:placetype":"venue"
},
  "geometry": {"coordinates":[3.7346150875,51.044467926],"type":"Point"}
}