{
  "type": "Feature",
  "properties": {
    "addr:full":"Westendelaan 231 Middelkerke West-Vlaanderen 8434",
    "addr:housenumber":"231",
    "addr:postcode":"8434",
    "addr:street":"Westendelaan",
    "iso:country":"BE",
    "sg:address":"Westendelaan 231",
    "sg:city":"Middelkerke",
    "sg:orig_category":"Installation \u00e9lectrique industrielle",
    "sg:phone":"+32 59 51 05 10",
    "sg:postcode":"8434",
    "sg:province":"West-Vlaanderen",
    "wof:name":"Thierry/eral",
    "wof:placetype":"venue"
},
  "geometry": {"coordinates":[2.7558889389,51.1391983032],"type":"Point"}
}