{
  "type": "Feature",
  "properties": {
    "addr:full":"Chauss\u00c9e De Bruxelles 340 Jumet Hainaut 6040",
    "addr:housenumber":"340",
    "addr:postcode":"6040",
    "addr:street":"Chausse\u0301E De Bruxelles",
    "iso:country":"BE",
    "sg:address":"Chauss\u00c9e De Bruxelles 340",
    "sg:city":"Jumet",
    "sg:orig_category":"Viessmann. Plomberie, chauffage and installations sanitaires",
    "sg:phone":"+32 71 35 75 27",
    "sg:postcode":"6040",
    "sg:province":"Hainaut",
    "wof:name":"Danczuk",
    "wof:placetype":"venue"
},
  "geometry": {"coordinates":[4.4347271919,50.448841095],"type":"Point"}
}