{
  "type": "Feature",
  "properties": {
    "addr:full":"Rue Des Deux Eglises 5 Neupr\u00e9 (rotheux-rimi\u00e8re) Li\u00e8ge 4120",
    "addr:housenumber":"5",
    "addr:postcode":"4120",
    "addr:street":"Rue Des Deux Eglises;Rotheux-Rimie\u0300Re",
    "iso:country":"BE",
    "sg:address":"Rue Des Deux Eglises 5",
    "sg:city":"Neupr\u00e9 (rotheux-rimi\u00e8re)",
    "sg:classifiers":[
        {
            "category":"Health Services",
            "subcategory":"Dentist",
            "type":"Services"
        }
    ],
    "sg:phone":"+32 4 371 26 20",
    "sg:postcode":"4120",
    "sg:province":"Li\u00e8ge",
    "wof:name":"Geys P",
    "wof:placetype":"venue"
},
  "geometry": {"coordinates":[5.4810872078,50.534538269],"type":"Point"}
}