{
  "type": "Feature",
  "properties": {
    "addr:full":"Halve Maanstraat 16 Sint-amands Antwerpen 2890",
    "addr:housenumber":"16",
    "addr:postcode":"2890",
    "addr:street":"Halve Maanstraat",
    "iso:country":"BE",
    "sg:address":"Halve Maanstraat 16",
    "sg:city":"Sint-amands",
    "sg:orig_category":"Imitation jewelry - Mfg.& Whol.",
    "sg:phone":"+32 52 39 70 15",
    "sg:postcode":"2890",
    "sg:province":"Antwerpen",
    "wof:name":"Sassafras Bvba",
    "wof:placetype":"venue"
},
  "geometry": {"coordinates":[4.2060351372,51.0605621338],"type":"Point"}
}