{
  "type": "Feature",
  "properties": {
    "addr:full":"Tramstraat 12 Wingene West-Vlaanderen 8750",
    "addr:housenumber":"12",
    "addr:postcode":"8750",
    "addr:street":"Tramstraat",
    "iso:country":"BE",
    "sg:address":"Tramstraat 12",
    "sg:city":"Wingene",
    "sg:orig_category":"Verplichte sociale verzekeringen",
    "sg:phone":"+32 51 61 32 68",
    "sg:postcode":"8750",
    "sg:province":"West-Vlaanderen",
    "wof:name":"Bond Moyson",
    "wof:placetype":"venue"
},
  "geometry": {"coordinates":[3.2134981155,51.0373497009],"type":"Point"}
}