{
  "type": "Feature",
  "properties": {
    "iso:country":"BE",
    "sg:address":"Statiestraat 67",
    "sg:city":"Lichtervelde",
    "sg:orig_category":"Supermarch\u00e9s",
    "sg:phone":"+32 51 72 56 70",
    "sg:postcode":"8810",
    "sg:province":"West-Vlaanderen",
    "wof:name":"Spar",
    "wof:placetype":"venue"
},
  "geometry": {"coordinates":[3.137720108,51.0256881714],"type":"Point"}
}