{
  "type": "Feature",
  "properties": {
    "addr:full":"Route De Mons 9 Charleroi Hainaut 6031",
    "addr:housenumber":"9",
    "addr:postcode":"6031",
    "addr:street":"Route De Mons;Hainaut",
    "iso:country":"BE",
    "sg:address":"Route De Mons 9",
    "sg:city":"Charleroi",
    "sg:orig_category":"V\u00e9hicules automobiles",
    "sg:phone":"+32 71 31 96 40",
    "sg:postcode":"6031",
    "sg:province":"Hainaut",
    "wof:name":"Citro\u00cbn S.i.a.",
    "wof:placetype":"venue"
},
  "geometry": {"coordinates":[4.4356851578,50.4121932983],"type":"Point"}
}