{
  "type": "Feature",
  "properties": {
    "iso:country":"BE",
    "sg:address":"Loystraat 139",
    "sg:city":"Hamme",
    "sg:classifiers":[
        {
            "category":"Health Services",
            "subcategory":"Health Practitioner",
            "type":"Services"
        }
    ],
    "sg:phone":"+32 52 48 06 11",
    "sg:postcode":"9220",
    "sg:province":"Oost-Vlaanderen",
    "sg:tags":[
        "physiotherapist"
    ],
    "wof:name":"Hobert Steven",
    "wof:placetype":"venue"
},
  "geometry": {"coordinates":[4.1417717934,51.0925216675],"type":"Point"}
}