{
  "type": "Feature",
  "properties": {
    "iso:country":"BE",
    "sg:address":"Clos De Hesbaye 42",
    "sg:city":"Waremme",
    "sg:orig_category":"Artsen and specialisten",
    "sg:phone":"+32 19 32 56 58",
    "sg:postcode":"4300",
    "sg:province":"Li\u00e8ge",
    "wof:name":"Pierre-philippe Delleuze",
    "wof:placetype":"venue"
},
  "geometry": {"coordinates":[5.2668662071,50.6971206665],"type":"Point"}
}