{
  "type": "Feature",
  "properties": {
    "iso:country":"BE",
    "sg:address":"Rue Grande Coyarde 14",
    "sg:city":"Ramillies",
    "sg:orig_category":"Elektrische installaties voor woningen Huishoudapparaten, televisies and radio's",
    "sg:phone":"+32 81 87 86 68",
    "sg:postcode":"1367",
    "sg:province":"Brabant Wallon",
    "wof:name":"Guy Gramme",
    "wof:placetype":"venue"
},
  "geometry": {"coordinates":[4.8673539162,50.6622657776],"type":"Point"}
}