{
  "type": "Feature",
  "properties": {
    "addr:full":"Moerkerkse Steenweg 228 Brugge (sint-kruis) West-Vlaanderen 8310",
    "addr:housenumber":"228",
    "addr:postcode":"8310",
    "addr:street":"Moerkerkse Steenweg",
    "iso:country":"BE",
    "sg:address":"Moerkerkse Steenweg 228",
    "sg:city":"Brugge (sint-kruis)",
    "sg:classifiers":[
        {
            "category":"Professional",
            "subcategory":"Testing Lab",
            "type":"Services"
        }
    ],
    "sg:phone":"+32 50 35 46 93",
    "sg:postcode":"8310",
    "sg:province":"West-Vlaanderen",
    "sg:tags":[
        "chemist"
    ],
    "wof:name":"Vandenbroeke D",
    "wof:placetype":"venue"
},
  "geometry": {"coordinates":[3.2537920475,51.2143135071],"type":"Point"}
}