{
  "type": "Feature",
  "properties": {
    "addr:full":"Bokhoutlaan 10 Aalter Oost-Vlaanderen 9880",
    "addr:housenumber":"10",
    "addr:postcode":"9880",
    "addr:street":"Bokhoutlaan",
    "iso:country":"BE",
    "sg:address":"Bokhoutlaan 10",
    "sg:city":"Aalter",
    "sg:classifiers":[
        {
            "category":"Banks & Credit Unions",
            "subcategory":"Investment Brokerage",
            "type":"Services"
        }
    ],
    "sg:phone":"+32 9 374 37 07",
    "sg:postcode":"9880",
    "sg:province":"Oost-Vlaanderen",
    "sg:tags":[
        "repair",
        "-",
        "installation",
        "sanitary",
        "article"
    ],
    "wof:name":"Rijckaert E",
    "wof:placetype":"venue"
},
  "geometry": {"coordinates":[3.385037899,51.1110916138],"type":"Point"}
}