{
  "type": "Feature",
  "properties": {
    "addr:full":"Adolf Buylstraat 45 Oostende West-Vlaanderen 8400",
    "addr:housenumber":"45",
    "addr:postcode":"8400",
    "addr:street":"Buylstraat",
    "iso:country":"BE",
    "sg:address":"Adolf Buylstraat 45",
    "sg:city":"Oostende",
    "sg:orig_category":"Epiceries",
    "sg:phone":"+32 59 70 27 44",
    "sg:postcode":"8400",
    "sg:province":"West-Vlaanderen",
    "wof:name":"Huis Marie-jos\u00c9",
    "wof:placetype":"venue"
},
  "geometry": {"coordinates":[2.9145579338,51.2312355042],"type":"Point"}
}