{
  "type": "Feature",
  "properties": {
    "addr:full":"Rue Bruy\u00c8re-saint-jean 52 Waterloo Brabant Wallon 1410",
    "addr:housenumber":"52",
    "addr:postcode":"1410",
    "addr:street":"Rue Bruye\u0300Re-Saint-Jean",
    "iso:country":"BE",
    "sg:address":"Rue Bruy\u00c8re-saint-jean 52",
    "sg:city":"Waterloo",
    "sg:orig_category":"M\u00e9decins and sp\u00e9cialistes",
    "sg:phone":"+32 2 354 74 39",
    "sg:postcode":"1410",
    "sg:province":"Brabant Wallon",
    "wof:name":"C. Van Der Linden",
    "wof:placetype":"venue"
},
  "geometry": {"coordinates":[4.3801898956,50.7148475647],"type":"Point"}
}