{
  "type": "Feature",
  "properties": {
    "iso:country":"BE",
    "sg:address":"Avenue Albert Ier 14",
    "sg:city":"Huy",
    "sg:orig_category":"Slagers",
    "sg:phone":"+32 85 21 79 28",
    "sg:postcode":"4500",
    "sg:province":"Li\u00e8ge",
    "wof:name":"Renmans",
    "wof:placetype":"venue"
},
  "geometry": {"coordinates":[5.2352790833,50.5246696472],"type":"Point"}
}