{
  "type": "Feature",
  "properties": {
    "addr:full":"Place Reine-astrid 12 Li\u00c8ge Li\u00e8ge 4000",
    "addr:housenumber":"12",
    "addr:postcode":"4000",
    "addr:street":"Place Reine-Astrid",
    "iso:country":"BE",
    "sg:address":"Place Reine-astrid 12",
    "sg:city":"Li\u00c8ge",
    "sg:orig_category":"Cr\u00e9dits divers",
    "sg:postcode":"4000",
    "sg:province":"Li\u00e8ge",
    "wof:name":"Bancontact-mister Cash",
    "wof:placetype":"venue"
},
  "geometry": {"coordinates":[5.5465331078,50.6762657166],"type":"Point"}
}