{
  "type": "Feature",
  "properties": {
    "iso:country":"BE",
    "sg:address":"Basse Lev\u00e9e 13",
    "sg:city":"Stavelot",
    "sg:classifiers":[
        {
            "category":"Health Services",
            "subcategory":"Doctor",
            "type":"Services"
        }
    ],
    "sg:phone":"+32 80 86 22 79",
    "sg:postcode":"4970",
    "sg:province":"Li\u00e8ge",
    "sg:tags":[
        "medicinephysicians",
        "surgeon"
    ],
    "wof:name":"Jacquerie B",
    "wof:placetype":"venue"
},
  "geometry": {"coordinates":[5.9358940125,50.3976974487],"type":"Point"}
}