{
  "type": "Feature",
  "properties": {
    "addr:full":"Gaarveldstraat 102 Hasselt Limburg 3500",
    "addr:housenumber":"102",
    "addr:postcode":"3500",
    "addr:street":"Gaarveldstraat",
    "iso:country":"BE",
    "sg:address":"Gaarveldstraat 102",
    "sg:city":"Hasselt",
    "sg:orig_category":"Alimentation sp\u00e9cialis\u00e9e",
    "sg:phone":"+32 11 28 40 33",
    "sg:postcode":"3500",
    "sg:province":"Limburg",
    "wof:name":"Het Kippenhuys",
    "wof:placetype":"venue"
},
  "geometry": {"coordinates":[5.327398777,50.9257392883],"type":"Point"}
}