{
  "type": "Feature",
  "properties": {
    "addr:full":"Aarschotsestraat 93 Vilvoorde Vlaams-Brabant 1800",
    "addr:housenumber":"93",
    "addr:postcode":"1800",
    "addr:street":"Aarschotsestraat",
    "iso:country":"BE",
    "sg:address":"Aarschotsestraat 93",
    "sg:city":"Vilvoorde",
    "sg:orig_category":"Kapsalons",
    "sg:phone":"+32 2 252 12 93",
    "sg:postcode":"1800",
    "sg:province":"Vlaams-Brabant",
    "wof:name":"Rosette Claes",
    "wof:placetype":"venue"
},
  "geometry": {"coordinates":[4.4552898407,50.9262084961],"type":"Point"}
}