{
  "type": "Feature",
  "properties": {
    "addr:full":"Lierseweg 230 Herentals Antwerpen 2200",
    "addr:housenumber":"230",
    "addr:postcode":"2200",
    "addr:street":"Lierseweg",
    "iso:country":"BE",
    "sg:address":"Lierseweg 230",
    "sg:city":"Herentals",
    "sg:orig_category":"Centres de fitness. Cours de danse",
    "sg:phone":"+32 14 23 11 50",
    "sg:postcode":"2200",
    "sg:province":"Antwerpen",
    "wof:name":"Dansstudio Inge",
    "wof:placetype":"venue"
},
  "geometry": {"coordinates":[4.8150701523,51.1743011475],"type":"Point"}
}