{
  "type": "Feature",
  "properties": {
    "addr:full":"Dijkstraat 50 Mechelen Antwerpen 2800",
    "addr:housenumber":"50",
    "addr:postcode":"2800",
    "addr:street":"Dijkstraat",
    "iso:country":"BE",
    "sg:address":"Dijkstraat 50",
    "sg:city":"Mechelen",
    "sg:classifiers":[
        {
            "category":"Real Estate",
            "subcategory":"Architect",
            "type":"Services"
        }
    ],
    "sg:phone":"+32 15 55 03 48",
    "sg:postcode":"2800",
    "sg:province":"Antwerpen",
    "wof:name":"Le Compte H",
    "wof:placetype":"venue"
},
  "geometry": {"coordinates":[4.4752697945,51.0167579651],"type":"Point"}
}