{
  "type": "Feature",
  "properties": {
    "addr:full":"Rue Du Blacet 3 Yvoir Namur 5530",
    "addr:housenumber":"3",
    "addr:postcode":"5530",
    "addr:street":"Rue Du Blacet",
    "iso:country":"BE",
    "sg:address":"Rue Du Blacet 3",
    "sg:city":"Yvoir",
    "sg:classifiers":[
        {
            "category":"Health Services",
            "subcategory":"Health Practitioner",
            "type":"Services"
        }
    ],
    "sg:phone":"+32 82 61 29 20",
    "sg:postcode":"5530",
    "sg:province":"Namur",
    "sg:tags":[
        "physiotherapist"
    ],
    "wof:name":"Bouv\u00e9 Christian",
    "wof:placetype":"venue"
},
  "geometry": {"coordinates":[4.8787350655,50.3275947571],"type":"Point"}
}