{
  "type": "Feature",
  "properties": {
    "iso:country":"BE",
    "sg:address":"Avenue Du G\u00c9n\u00c9ral-patton 1",
    "sg:city":"Arlon",
    "sg:classifiers":[
        {
            "category":"Restaurant",
            "type":"Food & Drink"
        }
    ],
    "sg:phone":"+32 63 21 66 10",
    "sg:postcode":"6700",
    "sg:province":"Luxembourg",
    "sg:tags":[
        "caf\u00e9s"
    ],
    "wof:name":"Taverne Le Patton",
    "wof:placetype":"venue"
},
  "geometry": {"coordinates":[5.8115510941,49.6774101257],"type":"Point"}
}