{
  "type": "Feature",
  "properties": {
    "iso:country":"BE",
    "sg:address":"Spoorweglaan 22",
    "sg:city":"Temse",
    "sg:classifiers":[
        {
            "category":"Personal",
            "subcategory":"Beauty Salon",
            "type":"Services"
        }
    ],
    "sg:phone":"+32 3 711 30 65",
    "sg:postcode":"9140",
    "sg:province":"Oost-Vlaanderen",
    "sg:tags":[
        "lady",
        "-",
        "hairdressing"
    ],
    "wof:name":"Coiffure Jo\u00eblle",
    "wof:placetype":"venue"
},
  "geometry": {"coordinates":[4.221309185,51.1300392151],"type":"Point"}
}