{
  "type": "Feature",
  "properties": {
    "iso:country":"BE",
    "sg:address":"Rue D' En Haut 24",
    "sg:city":"Beaumont",
    "sg:classifiers":[
        {
            "category":"Personal",
            "subcategory":"Beauty Salon",
            "type":"Services"
        }
    ],
    "sg:phone":"+32 71 58 89 61",
    "sg:postcode":"6500",
    "sg:province":"Hainaut",
    "sg:tags":[
        "de",
        "coiffure"
    ],
    "wof:name":"Coiffure Thierry",
    "wof:placetype":"venue"
},
  "geometry": {"coordinates":[4.2594871521,50.191444397],"type":"Point"}
}