{
  "type": "Feature",
  "properties": {
    "iso:country":"BE",
    "sg:address":"Rue Du Pansy 225",
    "sg:city":"Saint-nicolas",
    "sg:orig_category":"Kruideniers Voedingsspeciaalzaken",
    "sg:phone":"+32 4 231 31 47",
    "sg:postcode":"4420",
    "sg:province":"Li\u00e8ge",
    "wof:name":"Calogero Macaluso",
    "wof:placetype":"venue"
},
  "geometry": {"coordinates":[5.5195960999,50.6308135986],"type":"Point"}
}