{
  "type": "Feature",
  "properties": {
    "iso:country":"BE",
    "sg:address":"Rue Raymond No\u00cbl 28",
    "sg:city":"Profondeville",
    "sg:orig_category":"Bijouteries and horlogeries",
    "sg:phone":"+32 81 43 32 27",
    "sg:postcode":"5170",
    "sg:province":"Namur",
    "wof:name":"John Borbouse",
    "wof:placetype":"venue"
},
  "geometry": {"coordinates":[4.8093848228,50.389755249],"type":"Point"}
}