{
  "type": "Feature",
  "properties": {
    "iso:country":"BE",
    "sg:address":"3\u00e8me Avenue 19",
    "sg:city":"Herstal",
    "sg:classifiers":[
        {
            "category":"Professional",
            "subcategory":"Accounting & Tax Preparation",
            "type":"Services"
        }
    ],
    "sg:phone":"+32 4 264 01 30",
    "sg:postcode":"4040",
    "sg:province":"Li\u00e8ge",
    "sg:tags":[
        "bookkeeper"
    ],
    "wof:name":"Blaise E",
    "wof:placetype":"venue"
},
  "geometry": {"coordinates":[5.6244139671,50.6975440979],"type":"Point"}
}