{
  "type": "Feature",
  "properties": {
    "addr:full":"Quai Gloesener 5 Li\u00e8ge 1 (li\u00e8ge 2) Li\u00e8ge 4020",
    "addr:housenumber":"5;1;2",
    "addr:postcode":"4020",
    "addr:street":"Quai Gloesener",
    "iso:country":"BE",
    "sg:address":"Quai Gloesener 5",
    "sg:city":"Li\u00e8ge 1 (li\u00e8ge 2)",
    "sg:classifiers":[
        {
            "category":"Health Services",
            "subcategory":"Doctor",
            "type":"Services"
        }
    ],
    "sg:phone":"+32 4 342 06 92",
    "sg:postcode":"4020",
    "sg:province":"Li\u00e8ge",
    "sg:tags":[
        "medicinephysicians",
        "surgeon"
    ],
    "wof:name":"Bodson N",
    "wof:placetype":"venue"
},
  "geometry": {"coordinates":[5.5811891556,50.6205940247],"type":"Point"}
}