{
  "type": "Feature",
  "properties": {
    "iso:country":"BE",
    "sg:address":"Wildonkenstraat 9",
    "sg:city":"Deinze (meigem)",
    "sg:classifiers":[
        {
            "category":"Home & Garden",
            "subcategory":"Garden Supply",
            "type":"Retail Goods"
        }
    ],
    "sg:phone":"+32 9 386 16 58",
    "sg:postcode":"9800",
    "sg:province":"Oost-Vlaanderen",
    "wof:name":"Van De Velde-dobbelaere",
    "wof:placetype":"venue"
},
  "geometry": {"coordinates":[3.530174017,50.9863166809],"type":"Point"}
}