{
  "type": "Feature",
  "properties": {
    "addr:full":"Kerkstraat 25m Hamme Oost-Vlaanderen 9220",
    "addr:housenumber":"25m",
    "addr:postcode":"9220",
    "addr:street":"Kerkstraat",
    "iso:country":"BE",
    "sg:address":"Kerkstraat 25m",
    "sg:city":"Hamme",
    "sg:classifiers":[
        {
            "category":"Shopping",
            "subcategory":"Gifts & Souvenirs",
            "type":"Retail Goods"
        }
    ],
    "sg:phone":"+32 52 47 22 92",
    "sg:postcode":"9220",
    "sg:province":"Oost-Vlaanderen",
    "sg:tags":[
        "-"
    ],
    "wof:name":"Melrose",
    "wof:placetype":"venue"
},
  "geometry": {"coordinates":[4.1356229782,51.0980987549],"type":"Point"}
}