{
  "type": "Feature",
  "properties": {
    "addr:full":"Alsembergse Steenweg 1393 Ukkel/uccle Bruxelles-Capitale 1180",
    "addr:housenumber":"1393",
    "addr:postcode":"1180",
    "addr:street":"Alsembergse Steenweg;/",
    "iso:country":"BE",
    "sg:address":"Alsembergse Steenweg 1393",
    "sg:city":"Ukkel/uccle",
    "sg:orig_category":"Afbraak- and draineerwerken Beschutte werkplaatsen Boomkwekerijen Gespecialiseerde residenti\u00eble bouw",
    "sg:phone":"+32 2 332 15 30",
    "sg:postcode":"1180",
    "sg:province":"Bruxelles-Capitale",
    "wof:name":"Les Jeunes Jardiniers",
    "wof:placetype":"venue"
},
  "geometry": {"coordinates":[4.3260741234,50.7815170288],"type":"Point"}
}