{
  "type": "Feature",
  "properties": {
    "addr:full":"Rue De La Paix 30 Bruxelles (ixelles) Bruxelles-Capitale 1050",
    "addr:housenumber":"30",
    "addr:postcode":"1050",
    "addr:street":"Rue De La Paix",
    "iso:country":"BE",
    "sg:address":"Rue De La Paix 30",
    "sg:city":"Bruxelles (ixelles)",
    "sg:classifiers":[
        {
            "category":"Personal",
            "subcategory":"Barber",
            "type":"Services"
        }
    ],
    "sg:phone":"+32 2 511 25 77",
    "sg:postcode":"1050",
    "sg:province":"Bruxelles-Capitale",
    "sg:tags":[
        "gentleman",
        "salon",
        "-",
        "hairdressing"
    ],
    "wof:name":"Triptif",
    "wof:placetype":"venue"
},
  "geometry": {"coordinates":[4.3653712273,50.8361129761],"type":"Point"}
}