{
  "type": "Feature",
  "properties": {
    "addr:full":"Huttelaan 285 Leuven (heverlee) Vlaams-Brabant 3001",
    "addr:housenumber":"285",
    "addr:postcode":"3001",
    "addr:street":"Huttelaan",
    "iso:country":"BE",
    "sg:address":"Huttelaan 285",
    "sg:city":"Leuven (heverlee)",
    "sg:classifiers":[
        {
            "category":"Health Services",
            "subcategory":"Doctor",
            "type":"Services"
        }
    ],
    "sg:phone":"+32 16 40 76 33",
    "sg:postcode":"3001",
    "sg:province":"Vlaams-Brabant",
    "sg:tags":[
        "psychotherapist",
        "psychoanalyst"
    ],
    "wof:name":"Seynaeve P & Woertman E",
    "wof:placetype":"venue"
},
  "geometry": {"coordinates":[4.6940741539,50.8496437073],"type":"Point"}
}