{
  "type": "Feature",
  "properties": {
    "iso:country":"BE",
    "sg:address":"Place Roi Albert 15",
    "sg:city":"Houffalize",
    "sg:classifiers":[
        {
            "category":"Tea Room",
            "subcategory":"None",
            "type":"Food & Drink"
        }
    ],
    "sg:phone":"+32 61 28 81 27",
    "sg:postcode":"6660",
    "sg:province":"Luxembourg",
    "wof:name":"Alta Falisia",
    "wof:placetype":"venue"
},
  "geometry": {"coordinates":[5.790473938,50.129535675],"type":"Point"}
}