{
  "type": "Feature",
  "properties": {
    "iso:country":"BE",
    "sg:address":"Van Halewynstraat 1",
    "sg:city":"Zwevegem",
    "sg:orig_category":"M\u00e9decins and sp\u00e9cialistes",
    "sg:phone":"+32 56 75 93 43",
    "sg:postcode":"8550",
    "sg:province":"West-Vlaanderen",
    "wof:name":"Regine Florizoone",
    "wof:placetype":"venue"
},
  "geometry": {"coordinates":[3.3363370895,50.8033790588],"type":"Point"}
}