{
  "type": "Feature",
  "properties": {
    "iso:country":"BE",
    "sg:address":"Leopoldstraat 64",
    "sg:city":"Mechelen",
    "sg:orig_category":"Advocaten and juridische adviseurs",
    "sg:phone":"+32 15 44 64 80",
    "sg:postcode":"2800",
    "sg:province":"Antwerpen",
    "wof:name":"Ilse Arnouts",
    "wof:placetype":"venue"
},
  "geometry": {"coordinates":[4.4802107811,51.0187797546],"type":"Point"}
}