{
  "type": "Feature",
  "properties": {
    "iso:country":"BE",
    "sg:address":"Chemin Brimboriau 16",
    "sg:city":"Ath (meslin - L'ev\u00eaque)",
    "sg:classifiers":[
        {
            "category":"Retail",
            "subcategory":"Event Space",
            "type":"Services"
        }
    ],
    "sg:phone":"+32 68 55 26 43",
    "sg:postcode":"7822",
    "sg:province":"Hainaut",
    "sg:tags":[
        "rental",
        "-",
        "hall"
    ],
    "wof:name":"Altitude 48",
    "wof:placetype":"venue"
},
  "geometry": {"coordinates":[3.859400034,50.6526184082],"type":"Point"}
}