{
  "type": "Feature",
  "properties": {
    "addr:full":"Chaussee De Waterloo 255 Saint-gilles Bruxelles-Capitale 1060",
    "addr:housenumber":"255",
    "addr:postcode":"1060",
    "addr:street":"Chaussee De Waterloo",
    "iso:country":"BE",
    "sg:address":"Chaussee De Waterloo 255",
    "sg:city":"Saint-gilles",
    "sg:classifiers":[
        {
            "category":"Insurance",
            "subcategory":"Insurance Agent",
            "type":"Services"
        }
    ],
    "sg:phone":"+32 2 539 00 80",
    "sg:postcode":"1060",
    "sg:province":"Bruxelles-Capitale",
    "sg:tags":[
        "-",
        "representative"
    ],
    "wof:name":"Hiscox Belgium Sa",
    "wof:placetype":"venue"
},
  "geometry": {"coordinates":[4.3489189148,50.8248100281],"type":"Point"}
}