{
  "type": "Feature",
  "properties": {
    "iso:country":"BE",
    "sg:address":"Sint-jobsesteenweg 134",
    "sg:city":"Brasschaat",
    "sg:orig_category":"Autokeuringen",
    "sg:phone":"+32 3 663 11 15",
    "sg:postcode":"2930",
    "sg:province":"Antwerpen",
    "wof:name":"Autokeuring",
    "wof:placetype":"venue"
},
  "geometry": {"coordinates":[4.5568499565,51.3099708557],"type":"Point"}
}