{
  "type": "Feature",
  "properties": {
    "iso:country":"BE",
    "sg:address":"Rue De La Bichetour 17",
    "sg:city":"Bouillon",
    "sg:orig_category":"Installation \u00e9lectrique r\u00e9sidentielle",
    "sg:phone":"+32 61 46 76 35",
    "sg:postcode":"6832",
    "sg:province":"Luxembourg",
    "wof:name":"Thierry Denoncin",
    "wof:placetype":"venue"
},
  "geometry": {"coordinates":[5.0727958679,49.8251419067],"type":"Point"}
}