{
  "type": "Feature",
  "properties": {
    "iso:country":"BE",
    "sg:address":"Nukkerstraat 110",
    "sg:city":"Bredene",
    "sg:orig_category":"Rev\u00eatements de sols and murs. Installation de menuiserie en bois and plastique",
    "sg:phone":"+32 59 33 15 70",
    "sg:postcode":"8450",
    "sg:province":"West-Vlaanderen",
    "wof:name":"Franky Borny",
    "wof:placetype":"venue"
},
  "geometry": {"coordinates":[2.9592521191,51.2241172791],"type":"Point"}
}