{
  "type": "Feature",
  "properties": {
    "addr:full":"Chauss\u00c9e De Waterloo 602 Ixelles Bruxelles-Capitale 1050",
    "addr:housenumber":"602",
    "addr:postcode":"1050",
    "addr:street":"Chausse\u0301E De Waterloo",
    "iso:country":"BE",
    "sg:address":"Chauss\u00c9e De Waterloo 602",
    "sg:city":"Ixelles",
    "sg:classifiers":[
        {
            "category":"Travel",
            "subcategory":"Travel Agent",
            "type":"Entertainment"
        }
    ],
    "sg:phone":"+32 2 345 98 48",
    "sg:postcode":"1050",
    "sg:province":"Bruxelles-Capitale",
    "sg:tags":[
        "voyage",
        "de",
        "agences",
        "flash",
        "holidays",
        "plus"
    ],
    "wof:name":"Flash Travel",
    "wof:placetype":"venue"
},
  "geometry": {"coordinates":[4.3643932343,50.8181114197],"type":"Point"}
}