{
  "type": "Feature",
  "properties": {
    "addr:full":"Sentier P\u00eatre 2 Villers-la-ville Brabant Wallon 1495",
    "addr:housenumber":"2",
    "addr:postcode":"1495",
    "addr:street":"Sentier Pe\u0302Tre",
    "iso:country":"BE",
    "sg:address":"Sentier P\u00eatre 2",
    "sg:city":"Villers-la-ville",
    "sg:classifiers":[
        {
            "category":"Building & Trades",
            "subcategory":"Landscaping Services",
            "type":"Services"
        }
    ],
    "sg:phone":"+32 71 87 99 53",
    "sg:postcode":"1495",
    "sg:province":"Brabant Wallon",
    "sg:tags":[
        "-",
        "lopping",
        "work",
        "tree",
        "felling"
    ],
    "wof:name":"Bary J-m",
    "wof:placetype":"venue"
},
  "geometry": {"coordinates":[4.5312561989,50.5818557739],"type":"Point"}
}