{
  "type": "Feature",
  "properties": {
    "iso:country":"BE",
    "sg:address":"Poperingseweg 25",
    "sg:city":"Ieper",
    "sg:orig_category":"Goederenvervoer over de weg HUISBRANDOLIE",
    "sg:phone":"+32 57 20 16 94",
    "sg:postcode":"8900",
    "sg:province":"West-Vlaanderen",
    "wof:name":"Pierre Packet",
    "wof:placetype":"venue"
},
  "geometry": {"coordinates":[2.872576952,50.8497009277],"type":"Point"}
}