{
  "type": "Feature",
  "properties": {
    "iso:country":"BE",
    "sg:address":"Mechelsesteenweg 265b9",
    "sg:city":"Antwerpen",
    "sg:orig_category":"S\u00e9lection de personnel and placement",
    "sg:phone":"+32 3 230 28 59",
    "sg:postcode":"2018",
    "sg:province":"Antwerpen",
    "wof:name":"I.m.a.c.",
    "wof:placetype":"venue"
},
  "geometry": {"coordinates":[4.4141550064,51.2004623413],"type":"Point"}
}