{
  "type": "Feature",
  "properties": {
    "iso:country":"BE",
    "sg:address":"Wolvengrachtstraat 9bd",
    "sg:city":"Langemark-poelkapelle",
    "sg:orig_category":"Installation de menuiserie en bois and plastique",
    "sg:phone":"+32 57 48 94 46",
    "sg:postcode":"8920",
    "sg:province":"West-Vlaanderen",
    "wof:name":"Daniel Depuydt",
    "wof:placetype":"venue"
},
  "geometry": {"coordinates":[2.9280149937,50.9386825562],"type":"Point"}
}