{
  "type": "Feature",
  "properties": {
    "addr:full":"Nervi\u00ebrslei 22 Schoten Antwerpen 2900",
    "addr:housenumber":"22",
    "addr:postcode":"2900",
    "addr:street":"Nervie\u0308Rslei",
    "iso:country":"BE",
    "sg:address":"Nervi\u00ebrslei 22",
    "sg:city":"Schoten",
    "sg:classifiers":[
        {
            "category":"Professional",
            "subcategory":"Engineering",
            "type":"Services"
        }
    ],
    "sg:phone":"+32 3 658 63 40",
    "sg:postcode":"2900",
    "sg:province":"Antwerpen",
    "sg:tags":[
        "-"
    ],
    "wof:name":"Prokad Nv",
    "wof:placetype":"venue"
},
  "geometry": {"coordinates":[4.524438858,51.2689399719],"type":"Point"}
}