{
  "type": "Feature",
  "properties": {
    "iso:country":"BE",
    "sg:address":"Rue Du Village 45",
    "sg:city":"Sint-genesius-rode/rhode-saint-genese",
    "sg:orig_category":"S\u00e9curit\u00e9 sociale",
    "sg:phone":"+32 2 380 74 75",
    "sg:postcode":"1640",
    "sg:province":"Vlaams-Brabant",
    "wof:name":"St.michielsbond",
    "wof:placetype":"venue"
},
  "geometry": {"coordinates":[4.3453412056,50.745136261],"type":"Point"}
}