{
  "type": "Feature",
  "properties": {
    "addr:full":"Dorp 33 Bonheiden Antwerpen 2820",
    "addr:housenumber":"33",
    "addr:postcode":"2820",
    "addr:street":"Dorp",
    "iso:country":"BE",
    "sg:address":"Dorp 33",
    "sg:city":"Bonheiden",
    "sg:classifiers":[
        {
            "category":"Banks & Credit Unions",
            "subcategory":"Bank",
            "type":"Services"
        }
    ],
    "sg:phone":"+32 15 51 16 85",
    "sg:postcode":"2820",
    "sg:province":"Antwerpen",
    "wof:name":"Gemeentekrediet",
    "wof:placetype":"venue"
},
  "geometry": {"coordinates":[4.5479202271,51.0222206116],"type":"Point"}
}