{
  "type": "Feature",
  "properties": {
    "addr:full":"Koning Overwinnaarplein 12 Etterbeek Bruxelles-Capitale 1040",
    "addr:housenumber":"12",
    "addr:postcode":"1040",
    "addr:street":"Koning Overwinnaarplein",
    "iso:country":"BE",
    "sg:address":"Koning Overwinnaarplein 12",
    "sg:city":"Etterbeek",
    "sg:orig_category":"Boekhouders",
    "sg:phone":"+32 2 779 24 13",
    "sg:postcode":"1040",
    "sg:province":"Bruxelles-Capitale",
    "wof:name":"V\u00c9ronique Kuperblum",
    "wof:placetype":"venue"
},
  "geometry": {"coordinates":[4.3995537758,50.8328323364],"type":"Point"}
}