{
  "type": "Feature",
  "properties": {
    "iso:country":"BE",
    "sg:address":"Rue Jean Jaures 17",
    "sg:city":"La Louviere",
    "sg:orig_category":"Artsen and specialisten",
    "sg:phone":"+32 64 22 90 70",
    "sg:postcode":"7100",
    "sg:province":"Hainaut",
    "wof:name":"Michel Lefebvre",
    "wof:placetype":"venue"
},
  "geometry": {"coordinates":[4.1862359047,50.4799308777],"type":"Point"}
}