{
  "type": "Feature",
  "properties": {
    "iso:country":"BE",
    "sg:address":"Solleveld 30",
    "sg:city":"Herzele",
    "sg:orig_category":"Brood, gebak and snoepgoed",
    "sg:phone":"+32 53 62 24 17",
    "sg:postcode":"9550",
    "sg:province":"Oost-Vlaanderen",
    "wof:name":"Bakkerij Standaert",
    "wof:placetype":"venue"
},
  "geometry": {"coordinates":[3.8904719353,50.8827476501],"type":"Point"}
}