{
  "type": "Feature",
  "properties": {
    "iso:country":"BE",
    "sg:address":"Anspachlaan 54",
    "sg:city":"Brussel/bruxelles",
    "sg:orig_category":"Winkelinrichting and handelsuitrusting Gh",
    "sg:phone":"+32 2 219 71 98",
    "sg:postcode":"1000",
    "sg:province":"Bruxelles-Capitale",
    "wof:name":"New Las Vegas",
    "wof:placetype":"venue"
},
  "geometry": {"coordinates":[4.3507890701,50.8491973877],"type":"Point"}
}