{
  "type": "Feature",
  "properties": {
    "addr:full":"Rue Paul Leduc 26 La Louvi\u00e8re Hainaut 7100",
    "addr:housenumber":"26",
    "addr:postcode":"7100",
    "addr:street":"Rue Paul Leduc",
    "iso:country":"BE",
    "sg:address":"Rue Paul Leduc 26",
    "sg:city":"La Louvi\u00e8re",
    "sg:classifiers":[
        {
            "category":"Food & Beverages",
            "subcategory":"Fruits & Vegetables",
            "type":"Retail Goods"
        }
    ],
    "sg:phone":"+32 64 28 24 23",
    "sg:postcode":"7100",
    "sg:province":"Hainaut",
    "sg:tags":[
        "-"
    ],
    "wof:name":"Carabe Dor\u00e9 (le)",
    "wof:placetype":"venue"
},
  "geometry": {"coordinates":[4.185863018,50.47605896],"type":"Point"}
}