{
  "type": "Feature",
  "properties": {
    "addr:full":"Voie Mar\u00c9chal Grouchy 26 Wavre Brabant Wallon 1300",
    "addr:housenumber":"26;1300",
    "addr:street":"Voie Mare\u0301Chal Grouchy",
    "iso:country":"BE",
    "sg:address":"Voie Mar\u00c9chal Grouchy 26",
    "sg:city":"Wavre",
    "sg:orig_category":"M\u00e9decins and sp\u00e9cialistes",
    "sg:phone":"+32 10 45 49 90",
    "sg:postcode":"1300",
    "sg:province":"Brabant Wallon",
    "wof:name":"Daniel Hunin",
    "wof:placetype":"venue"
},
  "geometry": {"coordinates":[4.6221828461,50.6853981018],"type":"Point"}
}