{
  "type": "Feature",
  "properties": {
    "addr:full":"\u00b4t Angereelstraat 60 Ninove Oost-Vlaanderen 9400",
    "addr:housenumber":"60",
    "addr:postcode":"9400",
    "addr:street":"Angereelstraat",
    "iso:country":"BE",
    "sg:address":"\u00b4t Angereelstraat 60",
    "sg:city":"Ninove",
    "sg:orig_category":"D\u00e9molition d\u00b4immeubles and terrassements",
    "sg:phone":"+32 54 33 24 74",
    "sg:postcode":"9400",
    "sg:province":"Oost-Vlaanderen",
    "wof:name":"Christophe Ondernemingen",
    "wof:placetype":"venue"
},
  "geometry": {"coordinates":[4.0232000351,50.8349113464],"type":"Point"}
}