{
  "type": "Feature",
  "properties": {
    "iso:country":"BE",
    "sg:address":"Guido Gezellelaan 13",
    "sg:city":"Lier",
    "sg:classifiers":[
        {
            "category":"Education",
            "subcategory":"Special Training",
            "type":"Public Place"
        }
    ],
    "sg:phone":"+32 3 488 19 99",
    "sg:postcode":"2500",
    "sg:province":"Antwerpen",
    "sg:tags":[
        "school",
        "flying"
    ],
    "wof:name":"Antaser",
    "wof:placetype":"venue"
},
  "geometry": {"coordinates":[4.5385599136,51.1444358826],"type":"Point"}
}