{
  "type": "Feature",
  "properties": {
    "iso:country":"BE",
    "sg:address":"Kard Cardijnstraat 14",
    "sg:city":"Sint-katelijne-waver",
    "sg:orig_category":"Drukkerijen and copyshops",
    "sg:phone":"+32 15 31 27 23",
    "sg:postcode":"2860",
    "sg:province":"Antwerpen",
    "wof:name":"Drukkerij Paskruis",
    "wof:placetype":"venue"
},
  "geometry": {"coordinates":[4.5288801193,51.0644721985],"type":"Point"}
}