{
  "type": "Feature",
  "properties": {
    "addr:full":"Avenue Lambeau 78 Bruxelles (woluwe-saint-lambert) Bruxelles-Capitale 1200",
    "addr:housenumber":"78",
    "addr:postcode":"1200",
    "addr:street":"Avenue Lambeau",
    "iso:country":"BE",
    "sg:address":"Avenue Lambeau 78",
    "sg:city":"Bruxelles (woluwe-saint-lambert)",
    "sg:classifiers":[
        {
            "category":"Professional",
            "subcategory":"Management & Consulting",
            "type":"Services"
        }
    ],
    "sg:phone":"+32 2 732 81 71",
    "sg:postcode":"1200",
    "sg:province":"Bruxelles-Capitale",
    "sg:tags":[
        "-",
        "processing",
        "data",
        "consultant"
    ],
    "wof:name":"Mac Express",
    "wof:placetype":"venue"
},
  "geometry": {"coordinates":[4.4095568657,50.8455467224],"type":"Point"}
}