{
  "type": "Feature",
  "properties": {
    "addr:full":"Tennislaan 1 Maasmechelen Limburg 3630",
    "addr:housenumber":"1",
    "addr:postcode":"3630",
    "addr:street":"Tennislaan",
    "iso:country":"BE",
    "sg:address":"Tennislaan 1",
    "sg:city":"Maasmechelen",
    "sg:orig_category":"Sportterreinen and installaties behalve sportcentra",
    "sg:phone":"+32 89 76 08 49",
    "sg:postcode":"3630",
    "sg:province":"Limburg",
    "wof:name":"Openluchtzwembad Eisden",
    "wof:placetype":"venue"
},
  "geometry": {"coordinates":[5.6961350441,50.963848114],"type":"Point"}
}