{
  "type": "Feature",
  "properties": {
    "addr:full":"Hasseltsesteenweg 9 Tongeren Limburg 3700",
    "addr:housenumber":"9",
    "addr:postcode":"3700",
    "addr:street":"Hasseltsesteenweg",
    "iso:country":"BE",
    "sg:address":"Hasseltsesteenweg 9",
    "sg:city":"Tongeren",
    "sg:orig_category":"Articles non-alimentaires",
    "sg:phone":"+32 12 39 11 44",
    "sg:postcode":"3700",
    "sg:province":"Limburg",
    "wof:name":"Stock 2001",
    "wof:placetype":"venue"
},
  "geometry": {"coordinates":[5.4520640373,50.7890625],"type":"Point"}
}