{
  "type": "Feature",
  "properties": {
    "addr:full":"Rue D'italie 122 Box B Ans Li\u00e8ge 4430",
    "addr:housenumber":"122",
    "addr:postcode":"box;4430",
    "addr:street":"Rue D'Italie;B Ans",
    "iso:country":"BE",
    "sg:address":"Rue D'italie 122 Box B",
    "sg:city":"Ans",
    "sg:classifiers":[
        {
            "category":"Retail",
            "subcategory":"Event Space",
            "type":"Services"
        }
    ],
    "sg:phone":"+32 4 263 88 36",
    "sg:postcode":"4430",
    "sg:province":"Li\u00e8ge",
    "sg:tags":[
        "rental",
        "-",
        "hall"
    ],
    "wof:name":"Bonne Fortune",
    "wof:placetype":"venue"
},
  "geometry": {"coordinates":[5.5244889259,50.6528968811],"type":"Point"}
}