{
  "type": "Feature",
  "properties": {
    "addr:full":"Rue Des D\u00e9port\u00e9s 1 Estinnes (fauroeulx) Hainaut 7120",
    "addr:housenumber":"1",
    "addr:postcode":"7120",
    "addr:street":"Rue Des De\u0301Porte\u0301S",
    "iso:country":"BE",
    "sg:address":"Rue Des D\u00e9port\u00e9s 1",
    "sg:city":"Estinnes (fauroeulx)",
    "sg:classifiers":[
        {
            "category":"Real Estate",
            "subcategory":"Architect",
            "type":"Services"
        }
    ],
    "sg:phone":"+32 64 36 67 98",
    "sg:postcode":"7120",
    "sg:province":"Hainaut",
    "wof:name":"Marchetti B",
    "wof:placetype":"venue"
},
  "geometry": {"coordinates":[4.0999469757,50.3737068176],"type":"Point"}
}