{
  "type": "Feature",
  "properties": {
    "iso:country":"BE",
    "sg:address":"All\u00e9e De La Recherche 60",
    "sg:city":"Bruxelles (anderlecht)",
    "sg:classifiers":[
        {
            "category":"Government",
            "subcategory":"Office",
            "type":"Public Place"
        }
    ],
    "sg:phone":"+32 2 559 95 82",
    "sg:postcode":"1070",
    "sg:province":"Bruxelles-Capitale",
    "sg:tags":[
        "chamber",
        "industry",
        "commerce"
    ],
    "wof:name":"Chambre De Commerce Belgo-luxembourgeoise-polonaise",
    "wof:placetype":"venue"
},
  "geometry": {"coordinates":[4.2742171288,50.8167877197],"type":"Point"}
}