{
  "type": "Feature",
  "properties": {
    "addr:full":"Route Du Crois\u00c9 12bb Bouillon Luxembourg 6831",
    "addr:housenumber":"12bb",
    "addr:postcode":"6831",
    "addr:street":"Route Du Croise\u0301",
    "iso:country":"BE",
    "sg:address":"Route Du Crois\u00c9 12bb",
    "sg:city":"Bouillon",
    "sg:classifiers":[
        {
            "category":"Cafe",
            "type":"Food & Drink"
        }
    ],
    "sg:phone":"+32 61 46 63 42",
    "sg:postcode":"6831",
    "sg:province":"Luxembourg",
    "sg:tags":[
        "caf\u00e9s"
    ],
    "wof:name":"Caf\u00c9 Franco-belge",
    "wof:placetype":"venue"
},
  "geometry": {"coordinates":[5.0937948227,49.8202438354],"type":"Point"}
}