{
  "type": "Feature",
  "properties": {
    "iso:country":"BE",
    "sg:address":"Avenue Victor-tesch 69",
    "sg:city":"Arlon",
    "sg:orig_category":"Kinderopvang",
    "sg:phone":"+32 63 23 62 18",
    "sg:postcode":"6700",
    "sg:province":"Luxembourg",
    "wof:name":"A La Claire Fontaine",
    "wof:placetype":"venue"
},
  "geometry": {"coordinates":[5.816549778,49.6815490723],"type":"Point"}
}