{
  "type": "Feature",
  "properties": {
    "addr:full":"Rue Sainte-th\u00c9r\u00c8se 57 Erquelinnes Hainaut 6560",
    "addr:housenumber":"57",
    "addr:postcode":"6560",
    "addr:street":"Rue Sainte-The\u0301Re\u0300Se",
    "iso:country":"BE",
    "sg:address":"Rue Sainte-th\u00c9r\u00c8se 57",
    "sg:city":"Erquelinnes",
    "sg:orig_category":"Mat\u00e9riel m\u00e9dical and orthop\u00e9dique and proth\u00e8ses Fab",
    "sg:phone":"+32 71 55 89 47",
    "sg:postcode":"6560",
    "sg:province":"Hainaut",
    "wof:name":"Dolores Le Puil",
    "wof:placetype":"venue"
},
  "geometry": {"coordinates":[4.1130428314,50.3073043823],"type":"Point"}
}