{
  "type": "Feature",
  "properties": {
    "addr:full":"Molenweg 47 Brasschaat Antwerpen 2930",
    "addr:housenumber":"47",
    "addr:postcode":"2930",
    "addr:street":"Molenweg",
    "iso:country":"BE",
    "sg:address":"Molenweg 47",
    "sg:city":"Brasschaat",
    "sg:orig_category":"Immobili\u00ebnkantoren",
    "sg:phone":"+32 3 605 06 50",
    "sg:postcode":"2930",
    "sg:province":"Antwerpen",
    "wof:name":"Belgian Relocation Center",
    "wof:placetype":"venue"
},
  "geometry": {"coordinates":[4.449338913,51.2924804688],"type":"Point"}
}