{
  "type": "Feature",
  "properties": {
    "addr:full":"Rue De Haerne 183 Bruxelles (etterbeek) Bruxelles-Capitale 1040",
    "addr:housenumber":"183",
    "addr:postcode":"1040",
    "addr:street":"Rue De Haerne",
    "iso:country":"BE",
    "sg:address":"Rue De Haerne 183",
    "sg:city":"Bruxelles (etterbeek)",
    "sg:classifiers":[
        {
            "category":"Social Services",
            "subcategory":"Child Care",
            "type":"Services"
        }
    ],
    "sg:phone":"+32 2 649 49 11",
    "sg:postcode":"1040",
    "sg:province":"Bruxelles-Capitale",
    "sg:tags":[
        "baby",
        "nursery",
        "day",
        "sitting"
    ],
    "wof:name":"Base (la)",
    "wof:placetype":"venue"
},
  "geometry": {"coordinates":[4.3855690956,50.8280105591],"type":"Point"}
}