{
  "type": "Feature",
  "properties": {
    "addr:full":"All\u00e9e Centrale Z.i. Jumet Jumet Hainaut 6040",
    "addr:postcode":"6040",
    "addr:street":"Alle\u0301E Centrale",
    "iso:country":"BE",
    "sg:address":"All\u00e9e Centrale Z.i. Jumet",
    "sg:city":"Jumet",
    "sg:classifiers":[
        {
            "category":"Manufacturing",
            "subcategory":"Tools & Machinery",
            "type":"Manufacturing & Wholesale Goods"
        }
    ],
    "sg:phone":"+32 71 25 82 00",
    "sg:postcode":"6040",
    "sg:province":"Hainaut",
    "sg:tags":[
        "equipment",
        "measurement",
        "-",
        "precision",
        "instrument"
    ],
    "wof:name":"Sensy Sa",
    "wof:placetype":"venue"
},
  "geometry": {"coordinates":[4.4245052338,50.4448814392],"type":"Point"}
}