{
  "type": "Feature",
  "properties": {
    "addr:full":"Rue Ferdinand Nicolay 23 Saint-nicolas Li\u00e8ge 4420",
    "addr:housenumber":"23",
    "addr:postcode":"4420",
    "addr:street":"Rue Ferdinand Nicolay",
    "iso:country":"BE",
    "sg:address":"Rue Ferdinand Nicolay 23",
    "sg:city":"Saint-nicolas",
    "sg:orig_category":"Installation \u00e9lectrique r\u00e9sidentielle",
    "sg:phone":"+32 4 252 28 74",
    "sg:postcode":"4420",
    "sg:province":"Li\u00e8ge",
    "wof:name":"Michel Legros",
    "wof:placetype":"venue"
},
  "geometry": {"coordinates":[5.5459599495,50.6319274902],"type":"Point"}
}