{
  "type": "Feature",
  "properties": {
    "addr:full":"Rue De La For\u00cat 1 Marche-en-famenne Luxembourg 6900",
    "addr:housenumber":"1",
    "addr:postcode":"6900",
    "addr:street":"Rue De La Fore\u0302T",
    "iso:country":"BE",
    "sg:address":"Rue De La For\u00cat 1",
    "sg:city":"Marche-en-famenne",
    "sg:orig_category":"Rundveehouders",
    "sg:phone":"+32 84 31 33 87",
    "sg:postcode":"6900",
    "sg:province":"Luxembourg",
    "wof:name":"Henri Seron",
    "wof:placetype":"venue"
},
  "geometry": {"coordinates":[5.3728928566,50.2192878723],"type":"Point"}
}