{
  "type": "Feature",
  "properties": {
    "iso:country":"BE",
    "sg:address":"Rue De Sclessin 15",
    "sg:city":"Li\u00c8ge",
    "sg:orig_category":"Advocaten and juridische adviseurs",
    "sg:phone":"+32 4 254 14 02",
    "sg:postcode":"4000",
    "sg:province":"Li\u00e8ge",
    "wof:name":"Muriel Fr\u00c8re",
    "wof:placetype":"venue"
},
  "geometry": {"coordinates":[5.5696611404,50.62525177],"type":"Point"}
}