{
  "type": "Feature",
  "properties": {
    "addr:full":"Rue Du G\u00c9n\u00c9ral-molitor 2b10 Arlon Luxembourg 6700",
    "addr:housenumber":"2b10",
    "addr:postcode":"6700",
    "addr:street":"Rue Du Ge\u0301Ne\u0301Ral-Molitor",
    "iso:country":"BE",
    "sg:address":"Rue Du G\u00c9n\u00c9ral-molitor 2b10",
    "sg:city":"Arlon",
    "sg:orig_category":"Avocats and conseillers juridiques",
    "sg:phone":"+32 63 23 34 44",
    "sg:postcode":"6700",
    "sg:province":"Luxembourg",
    "wof:name":"Emmanuel Bosseler",
    "wof:placetype":"venue"
},
  "geometry": {"coordinates":[5.8122520447,49.682056427],"type":"Point"}
}