{
  "type": "Feature",
  "properties": {
    "iso:country":"BE",
    "sg:address":"Sportlaan 3",
    "sg:city":"Genk",
    "sg:orig_category":"Epiceries",
    "sg:phone":"+32 89 35 68 80",
    "sg:postcode":"3600",
    "sg:province":"Limburg",
    "wof:name":"Huis Deen",
    "wof:placetype":"venue"
},
  "geometry": {"coordinates":[5.4756450653,50.9749755859],"type":"Point"}
}