{
  "type": "Feature",
  "properties": {
    "addr:full":"Rue Kasterlinden 11 Bruxelles (berchem-sainte-agathe) Bruxelles-Capitale 1082",
    "addr:housenumber":"11",
    "addr:postcode":"1082",
    "addr:street":"Rue Kasterlinden",
    "iso:country":"BE",
    "sg:address":"Rue Kasterlinden 11",
    "sg:city":"Bruxelles (berchem-sainte-agathe)",
    "sg:orig_category":"Solar protection - Inside",
    "sg:phone":"+32 2 425 66 37",
    "sg:postcode":"1082",
    "sg:province":"Bruxelles-Capitale",
    "wof:name":"Delchevalerie Ets",
    "wof:placetype":"venue"
},
  "geometry": {"coordinates":[4.2953982353,50.859588623],"type":"Point"}
}