{
  "type": "Feature",
  "properties": {
    "iso:country":"BE",
    "sg:address":"Boorsemstraat 2",
    "sg:city":"Maasmechelen",
    "sg:orig_category":"Biens d'occasion",
    "sg:phone":"+32 89 77 92 92",
    "sg:postcode":"3630",
    "sg:province":"Limburg",
    "wof:name":"Kringloopcentrum Maasland",
    "wof:placetype":"venue"
},
  "geometry": {"coordinates":[5.6961350441,50.963848114],"type":"Point"}
}