{
  "type": "Feature",
  "properties": {
    "addr:full":"Rue Barbe D'or 4 Faimes Li\u00e8ge 4317",
    "addr:housenumber":"4",
    "addr:postcode":"4317",
    "addr:street":"Rue Barbe D'Or",
    "iso:country":"BE",
    "sg:address":"Rue Barbe D'or 4",
    "sg:city":"Faimes",
    "sg:orig_category":"Loodgieterij and centrale verwarming Gh",
    "sg:phone":"+32 19 56 72 96",
    "sg:postcode":"4317",
    "sg:province":"Li\u00e8ge",
    "wof:name":"Aqua Sertec",
    "wof:placetype":"venue"
},
  "geometry": {"coordinates":[5.2618899345,50.6657218933],"type":"Point"}
}