{
  "type": "Feature",
  "properties": {
    "iso:country":"BE",
    "sg:address":"Zilverbergstraat 100",
    "sg:city":"Waregem (desselgem)",
    "sg:classifiers":[
        {
            "category":"Bars & Pubs",
            "type":"Food & Drink"
        }
    ],
    "sg:phone":"+32 56 71 34 65",
    "sg:postcode":"8792",
    "sg:province":"West-Vlaanderen",
    "wof:name":"Klokkenhof",
    "wof:placetype":"venue"
},
  "geometry": {"coordinates":[3.3686790466,50.8850669861],"type":"Point"}
}