{
  "type": "Feature",
  "properties": {
    "iso:country":"BE",
    "sg:address":"Rue De L'eglise 37",
    "sg:city":"Vresse-sur-semois",
    "sg:classifiers":[
        {
            "category":"Restaurant",
            "type":"Food & Drink"
        }
    ],
    "sg:phone":"+32 61 50 09 94",
    "sg:postcode":"5550",
    "sg:province":"Namur",
    "sg:tags":[
        "caf\u00e9s"
    ],
    "wof:name":"Taverne Chez Dominique",
    "wof:placetype":"venue"
},
  "geometry": {"coordinates":[4.9336800575,49.8729782104],"type":"Point"}
}