{
  "type": "Feature",
  "properties": {
    "addr:full":"Palingstraat 27 Puurs Antwerpen 2870",
    "addr:housenumber":"27",
    "addr:postcode":"2870",
    "addr:street":"Palingstraat",
    "iso:country":"BE",
    "sg:address":"Palingstraat 27",
    "sg:city":"Puurs",
    "sg:classifiers":[
        {
            "category":"Bars & Pubs",
            "type":"Food & Drink"
        }
    ],
    "sg:phone":"+32 3 889 07 21",
    "sg:postcode":"2870",
    "sg:province":"Antwerpen",
    "wof:name":"Gulden Spoor",
    "wof:placetype":"venue"
},
  "geometry": {"coordinates":[4.2788310051,51.0751571655],"type":"Point"}
}