{
  "type": "Feature",
  "properties": {
    "addr:full":"Bijlokevest 93 Gent Oost-Vlaanderen 9000",
    "addr:housenumber":"93",
    "addr:postcode":"9000",
    "addr:street":"Bijlokevest;Oost-Vlaanderen",
    "iso:country":"BE",
    "sg:address":"Bijlokevest 93",
    "sg:city":"Gent",
    "sg:classifiers":[
        {
            "category":"Cafe",
            "type":"Food & Drink"
        }
    ],
    "sg:phone":"+32 9 225 68 13",
    "sg:postcode":"9000",
    "sg:province":"Oost-Vlaanderen",
    "sg:tags":[
        "caf\u00e9s"
    ],
    "wof:name":"Caf\u00c9 Sportvriend",
    "wof:placetype":"venue"
},
  "geometry": {"coordinates":[3.7119278908,51.0476341248],"type":"Point"}
}