{
  "type": "Feature",
  "properties": {
    "iso:country":"BE",
    "sg:address":"Rue Des Fabriques 9",
    "sg:city":"Saint-l\u00c9ger",
    "sg:orig_category":"Boekhouders",
    "sg:postcode":"6747",
    "sg:province":"Luxembourg",
    "wof:name":"Liliane Thomas",
    "wof:placetype":"venue"
},
  "geometry": {"coordinates":[5.6591219902,49.6115837097],"type":"Point"}
}