{
  "type": "Feature",
  "properties": {
    "addr:full":"Rue Marie-christine 101 Bruxelles-laeken Bruxelles-Capitale 1020",
    "addr:housenumber":"101",
    "addr:postcode":"1020",
    "addr:street":"Rue Marie-Christine",
    "iso:country":"BE",
    "sg:address":"Rue Marie-christine 101",
    "sg:city":"Bruxelles-laeken",
    "sg:classifiers":[
        {
            "category":"Shopping",
            "subcategory":"Computers & Home Electronics",
            "type":"Retail Goods"
        }
    ],
    "sg:phone":"+32 2 424 30 31",
    "sg:postcode":"1020",
    "sg:province":"Bruxelles-Capitale",
    "sg:tags":[
        "computerapparatuur",
        "microsoft"
    ],
    "wof:name":"Dekeuleneer-sematec",
    "wof:placetype":"venue"
},
  "geometry": {"coordinates":[4.3540101051,50.875453949],"type":"Point"}
}