{
  "type": "Feature",
  "properties": {
    "addr:full":"Lobbensestraat 43 Scherpenheuvel-zichem Vlaams-Brabant 3271",
    "addr:housenumber":"43",
    "addr:postcode":"3271",
    "addr:street":"Lobbensestraat",
    "iso:country":"BE",
    "sg:address":"Lobbensestraat 43",
    "sg:city":"Scherpenheuvel-zichem",
    "sg:orig_category":"Eleveurs and marchands de porcs",
    "sg:phone":"+32 13 77 23 65",
    "sg:postcode":"3271",
    "sg:province":"Vlaams-Brabant",
    "wof:name":"Petrus Goossens",
    "wof:placetype":"venue"
},
  "geometry": {"coordinates":[4.9651780128,50.9917678833],"type":"Point"}
}