{
  "type": "Feature",
  "properties": {
    "addr:full":"Grotestraat 243 Nieuwerkerken (wijer) Limburg 3850",
    "addr:housenumber":"243",
    "addr:postcode":"3850",
    "addr:street":"Grotestraat;Wijer Limburg",
    "iso:country":"BE",
    "sg:address":"Grotestraat 243",
    "sg:city":"Nieuwerkerken (wijer)",
    "sg:classifiers":[
        {
            "category":"Personal",
            "subcategory":"Beauty Salon",
            "type":"Services"
        }
    ],
    "sg:phone":"+32 11 31 66 55",
    "sg:postcode":"3850",
    "sg:province":"Limburg",
    "sg:tags":[
        "lady",
        "-",
        "hairdressing"
    ],
    "wof:name":"Marleen",
    "wof:placetype":"venue"
},
  "geometry": {"coordinates":[5.1931529045,50.8640937805],"type":"Point"}
}