{
  "type": "Feature",
  "properties": {
    "iso:country":"BE",
    "sg:address":"8",
    "sg:city":"Marktplatz 4750 Butgenbach",
    "sg:classifiers":[
        {
            "category":"Travel",
            "subcategory":"Hotels & Motels",
            "type":"Entertainment"
        }
    ],
    "sg:phone":"+32 80 44 42 12",
    "sg:postcode":"8",
    "sg:tags":[
        "hotels",
        "business",
        "restaurant"
    ],
    "wof:name":"Maraite Norbert Richard M.",
    "wof:placetype":"venue"
},
  "geometry": {"coordinates":[6.204595089,50.4256248474],"type":"Point"}
}