{
  "type": "Feature",
  "properties": {
    "iso:country":"BE",
    "sg:address":"Brusselseheerweg 69",
    "sg:city":"Neigem",
    "sg:classifiers":[
        {
            "category":"Food & Beverages",
            "subcategory":"Groceries & Convenience Stores",
            "type":"Retail Goods"
        }
    ],
    "sg:phone":"+32 54 32 81 28",
    "sg:postcode":"9403",
    "sg:province":"Oost-Vlaanderen",
    "sg:tags":[
        "product",
        "grain",
        "cereal",
        "related"
    ],
    "wof:name":"Watermolen Neigem Bvba",
    "wof:placetype":"venue"
},
  "geometry": {"coordinates":[4.0583410263,50.8023872375],"type":"Point"}
}