{
  "type": "Feature",
  "properties": {
    "addr:full":"Chemin Landaise 2b Tournai (orcq - Marquain - Lamain) Hainaut 7501",
    "addr:housenumber":"2b",
    "addr:postcode":"7501",
    "addr:street":"Chemin Landaise;Hainaut",
    "iso:country":"BE",
    "sg:address":"Chemin Landaise 2b",
    "sg:city":"Tournai (orcq - Marquain - Lamain)",
    "sg:classifiers":[
        {
            "category":"Health Services",
            "subcategory":"Doctor",
            "type":"Services"
        }
    ],
    "sg:phone":"+32 69 84 50 43",
    "sg:postcode":"7501",
    "sg:province":"Hainaut",
    "sg:tags":[
        "medicinephysicians",
        "surgeon"
    ],
    "wof:name":"Hoffreumon B",
    "wof:placetype":"venue"
},
  "geometry": {"coordinates":[3.3424310684,50.6014213562],"type":"Point"}
}