{
  "type": "Feature",
  "properties": {
    "addr:full":"Outerstraat 124 Ninove Oost-Vlaanderen 9406",
    "addr:housenumber":"124",
    "addr:postcode":"9406",
    "addr:street":"Outerstraat",
    "iso:country":"BE",
    "sg:address":"Outerstraat 124",
    "sg:city":"Ninove",
    "sg:orig_category":"Jardinage",
    "sg:phone":"+32 54 33 97 04",
    "sg:postcode":"9406",
    "sg:province":"Oost-Vlaanderen",
    "wof:name":"Vanderpoorten K",
    "wof:placetype":"venue"
},
  "geometry": {"coordinates":[4.0027251244,50.8381233215],"type":"Point"}
}