{
  "type": "Feature",
  "properties": {
    "addr:full":"Lange Ambachtstraat 4 Oosterzele Oost-Vlaanderen 9860",
    "addr:housenumber":"4",
    "addr:postcode":"9860",
    "addr:street":"Lange Ambachtstraat;Oost-Vlaanderen",
    "iso:country":"BE",
    "sg:address":"Lange Ambachtstraat 4",
    "sg:city":"Oosterzele",
    "sg:orig_category":"Kantoormateriaal",
    "sg:phone":"+32 9 362 93 56",
    "sg:postcode":"9860",
    "sg:province":"Oost-Vlaanderen",
    "wof:name":"Adico",
    "wof:placetype":"venue"
},
  "geometry": {"coordinates":[3.8136649132,50.9513244629],"type":"Point"}
}