{
  "type": "Feature",
  "properties": {
    "addr:full":"Mechelbaan 33 Meise Vlaams-Brabant 1860",
    "addr:housenumber":"33",
    "addr:postcode":"1860",
    "addr:street":"Mechelbaan",
    "iso:country":"BE",
    "sg:address":"Mechelbaan 33",
    "sg:city":"Meise",
    "sg:classifiers":[
        {
            "category":"Professional",
            "subcategory":"Accounting & Tax Preparation",
            "type":"Services"
        }
    ],
    "sg:phone":"+32 2 270 47 77",
    "sg:postcode":"1860",
    "sg:province":"Vlaams-Brabant",
    "sg:tags":[
        "bookkeeper"
    ],
    "wof:name":"Tax And Administration Office Bvba",
    "wof:placetype":"venue"
},
  "geometry": {"coordinates":[4.3325190544,50.9465408325],"type":"Point"}
}