{
  "type": "Feature",
  "properties": {
    "iso:country":"BE",
    "sg:address":"Givry 1205",
    "sg:city":"Bertogne",
    "sg:orig_category":"Enseignement maternel and primaire",
    "sg:phone":"+32 61 21 86 69",
    "sg:postcode":"6686",
    "sg:province":"Luxembourg",
    "wof:name":"Ecole Fond. Communale",
    "wof:placetype":"venue"
},
  "geometry": {"coordinates":[5.6022458076,50.0324134827],"type":"Point"}
}