{
  "type": "Feature",
  "properties": {
    "iso:country":"BE",
    "sg:address":"Tongersesteenweg 225",
    "sg:city":"Kortessem (vliermaal)",
    "sg:classifiers":[
        {
            "category":"Shopping",
            "subcategory":"Bicycles & Sporting Goods",
            "type":"Retail Goods"
        }
    ],
    "sg:phone":"+32 11 37 65 52",
    "sg:postcode":"3724",
    "sg:province":"Limburg",
    "sg:tags":[
        "tyre"
    ],
    "wof:name":"Beltys Nv Autobanden",
    "wof:placetype":"venue"
},
  "geometry": {"coordinates":[5.4092340469,50.826965332],"type":"Point"}
}