{
  "type": "Feature",
  "properties": {
    "iso:country":"BE",
    "sg:address":"Bloemisterijstraat 10",
    "sg:city":"Damme (sijsele)",
    "sg:classifiers":[
        {
            "category":"Home & Garden",
            "subcategory":"Garden Supply",
            "type":"Retail Goods"
        }
    ],
    "sg:phone":"+32 50 36 26 53",
    "sg:postcode":"8340",
    "sg:province":"West-Vlaanderen",
    "sg:tags":[
        "lawn",
        "mower"
    ],
    "wof:name":"Vanhoutte F",
    "wof:placetype":"venue"
},
  "geometry": {"coordinates":[3.31448102,51.2037467957],"type":"Point"}
}