{
  "type": "Feature",
  "properties": {
    "addr:full":"Locomotiefstraat 121 Mechelen Antwerpen 2800",
    "addr:housenumber":"121",
    "addr:postcode":"2800",
    "addr:street":"Locomotiefstraat",
    "iso:country":"BE",
    "sg:address":"Locomotiefstraat 121",
    "sg:city":"Mechelen",
    "sg:orig_category":"Etalage- and showroomontwerpers Film-, tv- and videoproductie",
    "sg:phone":"+32 15 42 37 33",
    "sg:postcode":"2800",
    "sg:province":"Antwerpen",
    "wof:name":"L.d.p.",
    "wof:placetype":"venue"
},
  "geometry": {"coordinates":[4.4958481789,51.0198249817],"type":"Point"}
}