{
  "type": "Feature",
  "properties": {
    "addr:full":"Rue Du Chemin De Fer Gosselies Hainaut 6041",
    "addr:postcode":"6041",
    "addr:street":"Rue Du Chemin De Fer;Hainaut",
    "iso:country":"BE",
    "sg:address":"Rue Du Chemin De Fer",
    "sg:city":"Gosselies",
    "sg:orig_category":"Meubles D\u00e9taillants, Am\u00e9nagement de B\u00e2timents et de Cuisines",
    "sg:phone":"+32 71 85 42 18",
    "sg:postcode":"6041",
    "sg:province":"Hainaut",
    "wof:name":"Maxim Home",
    "wof:placetype":"venue"
},
  "geometry": {"coordinates":[4.4391322136,50.4723167419],"type":"Point"}
}