{
  "type": "Feature",
  "properties": {
    "addr:full":"Kastanjebosstraat 2bb Jabbeke West-Vlaanderen 8490",
    "addr:housenumber":"2bb",
    "addr:postcode":"8490",
    "addr:street":"Kastanjebosstraat",
    "iso:country":"BE",
    "sg:address":"Kastanjebosstraat 2bb",
    "sg:city":"Jabbeke",
    "sg:orig_category":"Plaatsen van vloer- and muurbekleding",
    "sg:phone":"+32 50 81 29 69",
    "sg:postcode":"8490",
    "sg:province":"West-Vlaanderen",
    "wof:name":"Franky Devriendt",
    "wof:placetype":"venue"
},
  "geometry": {"coordinates":[3.0777640343,51.17735672],"type":"Point"}
}