{
  "type": "Feature",
  "properties": {
    "iso:country":"BE",
    "sg:address":"Izenbergestraat 131",
    "sg:city":"Alveringem",
    "sg:orig_category":"Gespecialiseerde niet-residenti\u00eble bouw Herstellingen and onderhoud van auto's",
    "sg:phone":"+32 58 29 91 67",
    "sg:postcode":"8691",
    "sg:province":"West-Vlaanderen",
    "wof:name":"Garage Clarys",
    "wof:placetype":"venue"
},
  "geometry": {"coordinates":[2.6480140686,50.9930610657],"type":"Point"}
}