{
  "type": "Feature",
  "properties": {
    "addr:full":"Keiberg 16 Lede Oost-Vlaanderen 9340",
    "addr:housenumber":"16",
    "addr:postcode":"9340",
    "addr:street":"Keiberg",
    "iso:country":"BE",
    "sg:address":"Keiberg 16",
    "sg:city":"Lede",
    "sg:classifiers":[
        {
            "category":"Cafe",
            "type":"Food & Drink"
        }
    ],
    "sg:phone":"+32 53 80 85 71",
    "sg:postcode":"9340",
    "sg:province":"Oost-Vlaanderen",
    "sg:tags":[
        "caf\u00e9s"
    ],
    "wof:name":"Caf\u00c9 Fonteintje",
    "wof:placetype":"venue"
},
  "geometry": {"coordinates":[3.9840860367,50.9568061829],"type":"Point"}
}