{
  "type": "Feature",
  "properties": {
    "iso:country":"BE",
    "sg:address":"Grand'place Wauthier-br. 1",
    "sg:city":"Braine-le-chateau",
    "sg:orig_category":"Openbare veiligheid",
    "sg:phone":"+32 2 366 92 67",
    "sg:postcode":"1440",
    "sg:province":"Brabant Wallon",
    "wof:name":"Police F\u00c9d\u00c9rale",
    "wof:placetype":"venue"
},
  "geometry": {"coordinates":[4.2669420242,50.6817054749],"type":"Point"}
}