{
  "type": "Feature",
  "properties": {
    "addr:full":"Churchilllaan 179 Schoten Antwerpen 2900",
    "addr:housenumber":"179",
    "addr:postcode":"2900",
    "addr:street":"Churchilllaan",
    "iso:country":"BE",
    "sg:address":"Churchilllaan 179",
    "sg:city":"Schoten",
    "sg:orig_category":"Slagers",
    "sg:phone":"+32 3 658 46 25",
    "sg:postcode":"2900",
    "sg:province":"Antwerpen",
    "wof:name":"Hubert Willemsen",
    "wof:placetype":"venue"
},
  "geometry": {"coordinates":[4.4866318703,51.249584198],"type":"Point"}
}