{
  "type": "Feature",
  "properties": {
    "iso:country":"BE",
    "sg:address":"Sluizeken 13",
    "sg:city":"Gent",
    "sg:classifiers":[
        {
            "category":"Communications",
            "subcategory":"Television Station",
            "type":"Services"
        }
    ],
    "sg:phone":"+32 50 42 47 92",
    "sg:postcode":"9000",
    "sg:province":"Oost-Vlaanderen",
    "sg:tags":[
        "array",
        "satellite",
        "aerial",
        "reception",
        "antenna"
    ],
    "wof:name":"Meyelec Ep",
    "wof:placetype":"venue"
},
  "geometry": {"coordinates":[3.0823609829,51.2976760864],"type":"Point"}
}