{
  "type": "Feature",
  "properties": {
    "addr:full":"Stationsstraat 48 Landen Vlaams-Brabant 3400",
    "addr:housenumber":"48",
    "addr:postcode":"3400",
    "addr:street":"Stationsstraat",
    "iso:country":"BE",
    "sg:address":"Stationsstraat 48",
    "sg:city":"Landen",
    "sg:classifiers":[
        {
            "category":"Food & Beverages",
            "subcategory":"Specialty",
            "type":"Retail Goods"
        }
    ],
    "sg:phone":"+32 11 88 35 33",
    "sg:postcode":"3400",
    "sg:province":"Vlaams-Brabant",
    "sg:tags":[
        "health",
        "dietary",
        "-",
        "biological"
    ],
    "wof:name":"Natuurwinkeltje (het)",
    "wof:placetype":"venue"
},
  "geometry": {"coordinates":[5.0806632042,50.7524223328],"type":"Point"}
}