{
  "type": "Feature",
  "properties": {
    "iso:country":"BE",
    "sg:address":"Neringenstraat 1 Box 5",
    "sg:city":"Tielt (aarsele)",
    "sg:classifiers":[
        {
            "category":"Building & Trades",
            "subcategory":"Electrical",
            "type":"Services"
        }
    ],
    "sg:phone":"+32 51 46 58 01",
    "sg:postcode":"8700",
    "sg:province":"West-Vlaanderen",
    "sg:tags":[
        "electric",
        "-",
        "housewiring",
        "contractor"
    ],
    "wof:name":"Domo Electro",
    "wof:placetype":"venue"
},
  "geometry": {"coordinates":[3.4039781094,51.0129814148],"type":"Point"}
}