{
  "type": "Feature",
  "properties": {
    "addr:full":". Limburg (groot) Li\u00e8ge 4830",
    "addr:postcode":"4830",
    "addr:street":"Groot Lie\u0300Ge",
    "iso:country":"BE",
    "sg:address":".",
    "sg:city":"Limburg (groot)",
    "sg:orig_category":"Apotheken",
    "sg:phone":"+32 900 10 500",
    "sg:postcode":"4830",
    "sg:province":"Li\u00e8ge",
    "wof:name":"Apothekers Van Wacht",
    "wof:placetype":"venue"
},
  "geometry": {"coordinates":[5.9407401085,50.6112518311],"type":"Point"}
}