{
  "type": "Feature",
  "properties": {
    "iso:country":"BE",
    "sg:address":"Rive De Meuse 28",
    "sg:city":"Profondeville",
    "sg:orig_category":"Catering and organisatie van feesten Fast food and meeneem restaurants Restaurants",
    "sg:phone":"+32 81 41 10 89",
    "sg:postcode":"5170",
    "sg:province":"Namur",
    "wof:name":"La Rh\u00c9torique",
    "wof:placetype":"venue"
},
  "geometry": {"coordinates":[4.8720002174,50.3783798218],"type":"Point"}
}