{
  "type": "Feature",
  "properties": {
    "addr:full":"Laan Op Heusden 59 Box 2 Beringen (koersel) Limburg 3582",
    "addr:housenumber":"59;2",
    "addr:postcode":"3582",
    "addr:street":"Laan Op Heusden;Box",
    "iso:country":"BE",
    "sg:address":"Laan Op Heusden 59 Box 2",
    "sg:city":"Beringen (koersel)",
    "sg:classifiers":[
        {
            "category":"Home & Garden",
            "subcategory":"Building Materials",
            "type":"Retail Goods"
        }
    ],
    "sg:phone":"+32 11 43 10 48",
    "sg:postcode":"3582",
    "sg:province":"Limburg",
    "sg:tags":[
        "veranda"
    ],
    "wof:name":"Amdega",
    "wof:placetype":"venue"
},
  "geometry": {"coordinates":[5.2708749771,51.0595359802],"type":"Point"}
}