{
  "type": "Feature",
  "properties": {
    "iso:country":"BE",
    "sg:address":"Rue De La Colline 283",
    "sg:city":"Seraing",
    "sg:orig_category":"Enseignement maternel and primaire",
    "sg:phone":"+32 4 336 45 46",
    "sg:postcode":"4100",
    "sg:province":"Li\u00e8ge",
    "wof:name":"Ecole Primaire Libre",
    "wof:placetype":"venue"
},
  "geometry": {"coordinates":[5.5060248375,50.587978363],"type":"Point"}
}