{
  "type": "Feature",
  "properties": {
    "addr:full":"Rue Pied De Vache 25c Gr\u00c2ce-hollogne Li\u00e8ge 4460",
    "addr:housenumber":"25c",
    "addr:postcode":"4460",
    "addr:street":"Rue Pied De Vache",
    "iso:country":"BE",
    "sg:address":"Rue Pied De Vache 25c",
    "sg:city":"Gr\u00c2ce-hollogne",
    "sg:orig_category":"Kapsalons",
    "sg:phone":"+32 476 32 08 45",
    "sg:postcode":"4460",
    "sg:province":"Li\u00e8ge",
    "wof:name":"Renson C",
    "wof:placetype":"venue"
},
  "geometry": {"coordinates":[5.3717999458,50.6298675537],"type":"Point"}
}