{
  "type": "Feature",
  "properties": {
    "iso:country":"BE",
    "sg:address":"Braamakkerstraat 91",
    "sg:city":"Deerlijk",
    "sg:orig_category":"Slagers",
    "sg:phone":"+32 56 77 75 62",
    "sg:postcode":"8540",
    "sg:province":"West-Vlaanderen",
    "wof:name":"Bernice Segaert",
    "wof:placetype":"venue"
},
  "geometry": {"coordinates":[3.3556139469,50.8476028442],"type":"Point"}
}