{
  "type": "Feature",
  "properties": {
    "iso:country":"BE",
    "sg:address":"Landwaartslaan 93",
    "sg:city":"Genk",
    "sg:orig_category":"Banken and kredietinstellingen",
    "sg:phone":"+32 89 35 89 93",
    "sg:postcode":"3600",
    "sg:province":"Limburg",
    "wof:name":"Fortis",
    "wof:placetype":"venue"
},
  "geometry": {"coordinates":[5.448788166,50.9682159424],"type":"Point"}
}