{
  "type": "Feature",
  "properties": {
    "iso:country":"BE",
    "sg:address":"Jan Palfijnlaan 9",
    "sg:city":"Hasselt",
    "sg:classifiers":[
        {
            "category":"Personal",
            "subcategory":"Beauty Salon",
            "type":"Services"
        }
    ],
    "sg:phone":"+32 11 22 72 70",
    "sg:postcode":"3500",
    "sg:province":"Limburg",
    "sg:tags":[
        "de",
        "coiffure"
    ],
    "wof:name":"Haarmode",
    "wof:placetype":"venue"
},
  "geometry": {"coordinates":[5.3506360054,50.9249801636],"type":"Point"}
}