{
  "type": "Feature",
  "properties": {
    "addr:full":"Terbeeksestraat 65ba Hoogstraten Antwerpen 2321",
    "addr:housenumber":"65ba",
    "addr:postcode":"2321",
    "addr:street":"Terbeeksestraat",
    "iso:country":"BE",
    "sg:address":"Terbeeksestraat 65ba",
    "sg:city":"Hoogstraten",
    "sg:orig_category":"Producteurs de fruits",
    "sg:phone":"+32 3 315 88 44",
    "sg:postcode":"2321",
    "sg:province":"Antwerpen",
    "wof:name":"Andre Sterkens",
    "wof:placetype":"venue"
},
  "geometry": {"coordinates":[4.7366099358,51.442325592],"type":"Point"}
}