{
  "type": "Feature",
  "properties": {
    "iso:country":"BE",
    "sg:address":"Schoubroek 27",
    "sg:city":"Gent (mariakerke)",
    "sg:classifiers":[
        {
            "category":"Wholesale",
            "subcategory":"Wine & Distilled Alcoholic Beverages",
            "type":"Manufacturing & Wholesale Goods"
        }
    ],
    "sg:phone":"+32 9 227 63 66",
    "sg:postcode":"9030",
    "sg:province":"Oost-Vlaanderen",
    "sg:tags":[
        "whol",
        "-",
        "spirit",
        "mfg"
    ],
    "wof:name":"Hodira Bvba",
    "wof:placetype":"venue"
},
  "geometry": {"coordinates":[3.6759450436,51.0819625854],"type":"Point"}
}