{
  "type": "Feature",
  "properties": {
    "iso:country":"BE",
    "sg:address":"Veurnestraat 10",
    "sg:city":"Poperinge",
    "sg:classifiers":[
        {
            "category":"Farming",
            "subcategory":"Fish & Marine Products",
            "type":"Manufacturing & Wholesale Goods"
        }
    ],
    "sg:phone":"+32 57 33 38 49",
    "sg:postcode":"8970",
    "sg:province":"West-Vlaanderen",
    "sg:tags":[
        "retail",
        "-",
        "shellfish"
    ],
    "wof:name":"Duyvejonck L",
    "wof:placetype":"venue"
},
  "geometry": {"coordinates":[2.7263669968,50.8562507629],"type":"Point"}
}