{
  "type": "Feature",
  "properties": {
    "addr:full":"Stationsplein 12 Hamont-achel Limburg 3930",
    "addr:housenumber":"12",
    "addr:postcode":"3930",
    "addr:street":"Stationsplein",
    "iso:country":"BE",
    "sg:address":"Stationsplein 12",
    "sg:city":"Hamont-achel",
    "sg:orig_category":"M\u00e9decins and sp\u00e9cialistes",
    "sg:phone":"+32 11 44 51 20",
    "sg:postcode":"3930",
    "sg:province":"Limburg",
    "wof:name":"H. Lammers",
    "wof:placetype":"venue"
},
  "geometry": {"coordinates":[5.5450549126,51.2511863708],"type":"Point"}
}