{
  "type": "Feature",
  "properties": {
    "iso:country":"BE",
    "sg:address":"Dr\u00c8ve Mar\u00c9chal Murat 7",
    "sg:city":"Genappe",
    "sg:orig_category":"M\u00e9decins and sp\u00e9cialistes",
    "sg:phone":"+32 67 78 09 26",
    "sg:postcode":"1470",
    "sg:province":"Brabant Wallon",
    "wof:name":"Marcel Delire",
    "wof:placetype":"venue"
},
  "geometry": {"coordinates":[4.455742836,50.5771560669],"type":"Point"}
}