{
  "type": "Feature",
  "properties": {
    "addr:full":"Rue De Roubaix 88 Mouscron Hainaut 7700",
    "addr:housenumber":"88",
    "addr:postcode":"7700",
    "addr:street":"Rue De Roubaix",
    "iso:country":"BE",
    "sg:address":"Rue De Roubaix 88",
    "sg:city":"Mouscron",
    "sg:classifiers":[
        {
            "category":"Health Services",
            "subcategory":"Dentist",
            "type":"Services"
        }
    ],
    "sg:phone":"+32 56 33 16 20",
    "sg:postcode":"7700",
    "sg:province":"Hainaut",
    "wof:name":"De Jonghe C",
    "wof:placetype":"venue"
},
  "geometry": {"coordinates":[3.208329916,50.7378349304],"type":"Point"}
}