{
  "type": "Feature",
  "properties": {
    "addr:full":"Olympialaan 18 Sint-truiden Limburg 3800",
    "addr:housenumber":"18",
    "addr:postcode":"3800",
    "addr:street":"Olympialaan",
    "iso:country":"BE",
    "sg:address":"Olympialaan 18",
    "sg:city":"Sint-truiden",
    "sg:orig_category":"M\u00e9decins and sp\u00e9cialistes",
    "sg:phone":"+32 11 68 94 70",
    "sg:postcode":"3800",
    "sg:province":"Limburg",
    "wof:name":"J. Sneyers",
    "wof:placetype":"venue"
},
  "geometry": {"coordinates":[5.1786389351,50.8125038147],"type":"Point"}
}