{
  "type": "Feature",
  "properties": {
    "iso:country":"BE",
    "sg:address":"Jan-van-gentstraat 15",
    "sg:city":"Oostende",
    "sg:orig_category":"Instituts de beaut\u00e9",
    "sg:phone":"+32 59 80 78 97",
    "sg:postcode":"8400",
    "sg:province":"West-Vlaanderen",
    "wof:name":"Pedicure Heyse",
    "wof:placetype":"venue"
},
  "geometry": {"coordinates":[2.9141099453,51.2248306274],"type":"Point"}
}