{
  "type": "Feature",
  "properties": {
    "iso:country":"BE",
    "sg:address":"Rue Des Dominicains 16",
    "sg:city":"Mons",
    "sg:orig_category":"Artsen and specialisten",
    "sg:phone":"+32 65 35 39 91",
    "sg:postcode":"7000",
    "sg:province":"Hainaut",
    "wof:name":"Robert Degreve",
    "wof:placetype":"venue"
},
  "geometry": {"coordinates":[3.950220108,50.4564743042],"type":"Point"}
}