{
  "type": "Feature",
  "properties": {
    "addr:full":"Boulevard L\u00c9opold Ii 130 Sint-jans-molenbeek/molenbeek-saint-jean Bruxelles-Capitale 1080",
    "addr:housenumber":"130",
    "addr:postcode":"1080",
    "addr:street":"Boulevard Le\u0301Opold Ii",
    "iso:country":"BE",
    "sg:address":"Boulevard L\u00c9opold Ii 130",
    "sg:city":"Sint-jans-molenbeek/molenbeek-saint-jean",
    "sg:orig_category":"Evaluation and estimation de biens immobiliers",
    "sg:phone":"+32 2 414 09 24",
    "sg:postcode":"1080",
    "sg:province":"Bruxelles-Capitale",
    "wof:name":"U.s.e.g./useg",
    "wof:placetype":"venue"
},
  "geometry": {"coordinates":[4.3387207985,50.8605728149],"type":"Point"}
}