{
  "type": "Feature",
  "properties": {
    "addr:full":"Leopold De Waelplaats 22 Box 21 Antwerpen Antwerpen 2000",
    "addr:housenumber":"22 box 21",
    "addr:postcode":"2000",
    "addr:street":"Leopold De Waelplaats",
    "iso:country":"BE",
    "sg:address":"Leopold De Waelplaats 22 Box 21",
    "sg:city":"Antwerpen",
    "sg:classifiers":[
        {
            "category":"Real Estate",
            "subcategory":"Architect",
            "type":"Services"
        }
    ],
    "sg:phone":"+32 475 57 67 32",
    "sg:postcode":"2000",
    "sg:province":"Antwerpen",
    "wof:name":"Smet E",
    "wof:placetype":"venue"
},
  "geometry": {"coordinates":[4.3930602074,51.2090568542],"type":"Point"}
}