{
  "type": "Feature",
  "properties": {
    "iso:country":"BE",
    "sg:address":"Rue C\u00c9sar Despretz 6",
    "sg:city":"Lessines",
    "sg:classifiers":[
        {
            "category":"Insurance",
            "subcategory":"Life Insurance",
            "type":"Services"
        }
    ],
    "sg:phone":"+32 68 33 59 15",
    "sg:postcode":"7860",
    "sg:province":"Hainaut",
    "sg:tags":[
        "assurance"
    ],
    "wof:name":"F. Counasse",
    "wof:placetype":"venue"
},
  "geometry": {"coordinates":[3.8285770416,50.7122154236],"type":"Point"}
}