{
  "type": "Feature",
  "properties": {
    "addr:full":"Rue Du Centre 15 Nassogne (grune) Luxembourg 6952",
    "addr:housenumber":"15",
    "addr:postcode":"6952",
    "addr:street":"Rue Du Centre",
    "iso:country":"BE",
    "sg:address":"Rue Du Centre 15",
    "sg:city":"Nassogne (grune)",
    "sg:classifiers":[
        {
            "category":"Education",
            "subcategory":"School",
            "type":"Public Place"
        }
    ],
    "sg:phone":"+32 84 34 44 30",
    "sg:postcode":"6952",
    "sg:province":"Luxembourg",
    "sg:tags":[
        "primary"
    ],
    "wof:name":"Ecole De La Wamme",
    "wof:placetype":"venue"
},
  "geometry": {"coordinates":[5.3817892075,50.1555366516],"type":"Point"}
}