{
  "type": "Feature",
  "properties": {
    "iso:country":"BE",
    "sg:address":"Lariksln. 1",
    "sg:city":"Kapellen",
    "sg:classifiers":[
        {
            "category":"Wholesale",
            "subcategory":"Chemicals & Plastics",
            "type":"Manufacturing & Wholesale Goods"
        }
    ],
    "sg:phone":"+32 3 666 01 01",
    "sg:postcode":"2950",
    "sg:province":"Antwerpen",
    "sg:tags":[
        "rubber",
        "pharmaceutical",
        "chemistry",
        "-",
        "by-product"
    ],
    "wof:name":"Corrocoat",
    "wof:placetype":"venue"
},
  "geometry": {"coordinates":[4.4289112091,51.3147735596],"type":"Point"}
}