{
  "type": "Feature",
  "properties": {
    "iso:country":"BE",
    "sg:address":"Rue Du M\u00e9tal 28",
    "sg:city":"Bruxelles (saint-gilles)",
    "sg:classifiers":[
        {
            "category":"Communications",
            "subcategory":"Film & Video Production",
            "type":"Services"
        }
    ],
    "sg:phone":"+32 2 534 35 83",
    "sg:postcode":"1060",
    "sg:province":"Bruxelles-Capitale",
    "sg:tags":[
        "sound",
        "installation",
        "material",
        "-",
        "recording",
        "studio"
    ],
    "wof:name":"C.c.s.",
    "wof:placetype":"venue"
},
  "geometry": {"coordinates":[4.349506855,50.8306541443],"type":"Point"}
}