{
  "type": "Feature",
  "properties": {
    "iso:country":"BE",
    "sg:address":"Vinkenlaan 35",
    "sg:city":"Bornem",
    "sg:orig_category":"Animations diverses",
    "sg:phone":"+32 3 889 11 33",
    "sg:postcode":"2880",
    "sg:province":"Antwerpen",
    "wof:name":"No Problem",
    "wof:placetype":"venue"
},
  "geometry": {"coordinates":[4.1989588737,51.0764122009],"type":"Point"}
}