{
  "type": "Feature",
  "properties": {
    "addr:full":"Nijverheidsstraat 6 Brussel/bruxelles Bruxelles-Capitale 1000",
    "addr:housenumber":"6",
    "addr:postcode":"1000",
    "addr:street":"Nijverheidsstraat;/",
    "iso:country":"BE",
    "sg:address":"Nijverheidsstraat 6",
    "sg:city":"Brussel/bruxelles",
    "sg:orig_category":"Overheidsdiensten",
    "sg:phone":"+32 2 506 51 11",
    "sg:postcode":"1000",
    "sg:province":"Bruxelles-Capitale",
    "wof:name":"Minist\u00c8re Des Affaires Economiques",
    "wof:placetype":"venue"
},
  "geometry": {"coordinates":[4.3690648079,50.8411598206],"type":"Point"}
}