{
  "type": "Feature",
  "properties": {
    "addr:full":"Golfbrekerslaan 2 Middelkerke West-Vlaanderen 8430",
    "addr:housenumber":"2",
    "addr:postcode":"8430",
    "addr:street":"Golfbrekerslaan",
    "iso:country":"BE",
    "sg:address":"Golfbrekerslaan 2",
    "sg:city":"Middelkerke",
    "sg:orig_category":"Charpentes and couvertures",
    "sg:phone":"+32 59 30 47 34",
    "sg:postcode":"8430",
    "sg:province":"West-Vlaanderen",
    "wof:name":"Vermote",
    "wof:placetype":"venue"
},
  "geometry": {"coordinates":[2.7992529869,51.174861908],"type":"Point"}
}