{
  "type": "Feature",
  "properties": {
    "iso:country":"BE",
    "sg:address":"Rue Fernand Henrotaux 19",
    "sg:city":"Dalhem",
    "sg:classifiers":[
        {
            "category":"Social Services",
            "subcategory":"Child Care",
            "type":"Services"
        }
    ],
    "sg:phone":"+32 4 379 09 41",
    "sg:postcode":"4607",
    "sg:province":"Li\u00e8ge",
    "sg:tags":[
        "baby",
        "nursery",
        "day",
        "sitting"
    ],
    "wof:name":"Maison D'enfants Petit \u00e0 Petit",
    "wof:placetype":"venue"
},
  "geometry": {"coordinates":[5.724779129,50.7066879272],"type":"Point"}
}