{
  "type": "Feature",
  "properties": {
    "iso:country":"BE",
    "sg:address":"Place A Bosch 34",
    "sg:city":"Wavre (grand)",
    "sg:orig_category":"Kapsalons",
    "sg:phone":"+32 81 22 15 97",
    "sg:postcode":"1300",
    "sg:province":"Brabant Wallon",
    "wof:name":"Loren",
    "wof:placetype":"venue"
},
  "geometry": {"coordinates":[4.6109080315,50.7136192322],"type":"Point"}
}