{
  "type": "Feature",
  "properties": {
    "iso:country":"BE",
    "sg:address":"Kalkstraat 23",
    "sg:city":"Sint-niklaas",
    "sg:orig_category":"Newspapers, magazines, periodicals - Publishers",
    "sg:phone":"+32 3 778 14 95",
    "sg:postcode":"9100",
    "sg:province":"Oost-Vlaanderen",
    "wof:name":"Release Bvba",
    "wof:placetype":"venue"
},
  "geometry": {"coordinates":[4.1447758675,51.1645011902],"type":"Point"}
}