{
  "type": "Feature",
  "properties": {
    "iso:country":"BE",
    "sg:address":"Steenhouwersvest 34",
    "sg:city":"Antwerpen",
    "sg:classifiers":[
        {
            "category":"Real Estate",
            "subcategory":"Real Estate Services",
            "type":"Services"
        }
    ],
    "sg:phone":"+32 3 232 76 59",
    "sg:postcode":"2000",
    "sg:province":"Antwerpen",
    "wof:name":"Van Praag G",
    "wof:placetype":"venue"
},
  "geometry": {"coordinates":[4.3987751007,51.2177391052],"type":"Point"}
}