{
  "type": "Feature",
  "properties": {
    "iso:country":"BE",
    "sg:address":"Sint-jorislaan 143",
    "sg:city":"Herk-de-stad",
    "sg:classifiers":[
        {
            "category":"Fast Food",
            "type":"Food & Drink"
        }
    ],
    "sg:phone":"+32 13 55 11 07",
    "sg:postcode":"3540",
    "sg:province":"Limburg",
    "sg:tags":[
        "\u00c0",
        "emporter",
        "restaurants"
    ],
    "wof:name":"Frituur St-joris",
    "wof:placetype":"venue"
},
  "geometry": {"coordinates":[5.1950278282,50.9526443481],"type":"Point"}
}