{
  "type": "Feature",
  "properties": {
    "addr:full":"Avenue Louis Bertrand 129 Brussel/bruxelles Bruxelles-Capitale 1030",
    "addr:housenumber":"129",
    "addr:postcode":"1030",
    "addr:street":"Avenue Louis Bertrand;/",
    "iso:country":"BE",
    "sg:address":"Avenue Louis Bertrand 129",
    "sg:city":"Brussel/bruxelles",
    "sg:classifiers":[
        {
            "category":"Restaurant",
            "type":"Food & Drink"
        }
    ],
    "sg:phone":"+32 2 216 37 29",
    "sg:postcode":"1030",
    "sg:province":"Bruxelles-Capitale",
    "sg:tags":[
        "caf\u00e9s"
    ],
    "wof:name":"Taverne New Horizon",
    "wof:placetype":"venue"
},
  "geometry": {"coordinates":[4.3800802231,50.8631706238],"type":"Point"}
}