{
  "type": "Feature",
  "properties": {
    "addr:full":"Rue Georges Emmanuel 22 Namur (flawinne) Namur 5020",
    "addr:housenumber":"22",
    "addr:postcode":"5020",
    "addr:street":"Rue Georges Emmanuel",
    "iso:country":"BE",
    "sg:address":"Rue Georges Emmanuel 22",
    "sg:city":"Namur (flawinne)",
    "sg:classifiers":[
        {
            "category":"Health Services",
            "subcategory":"Nursing And Care Facility",
            "type":"Services"
        }
    ],
    "sg:phone":"+32 81 74 14 53",
    "sg:postcode":"5020",
    "sg:province":"Namur",
    "sg:tags":[
        "home"
    ],
    "wof:name":"Tuteleers A",
    "wof:placetype":"venue"
},
  "geometry": {"coordinates":[4.7952418327,50.4352035522],"type":"Point"}
}