{
  "type": "Feature",
  "properties": {
    "addr:full":"Markt 7 Meerhout Antwerpen 2450",
    "addr:housenumber":"7",
    "addr:postcode":"2450",
    "addr:street":"Markt",
    "iso:country":"BE",
    "sg:address":"Markt 7",
    "sg:city":"Meerhout",
    "sg:classifiers":[
        {
            "category":"Insurance",
            "subcategory":"Insurance Agent",
            "type":"Services"
        }
    ],
    "sg:phone":"+32 14 30 46 55",
    "sg:postcode":"2450",
    "sg:province":"Antwerpen",
    "sg:tags":[
        "broker"
    ],
    "wof:name":"Verzekeringen Dan Van De Craen En Luc Thys Bvba",
    "wof:placetype":"venue"
},
  "geometry": {"coordinates":[5.0777950287,51.132648468],"type":"Point"}
}