{
  "type": "Feature",
  "properties": {
    "addr:full":"Bosstraat 18 Erpe-mere Oost-Vlaanderen 9420",
    "addr:housenumber":"18",
    "addr:postcode":"9420",
    "addr:street":"Bosstraat",
    "iso:country":"BE",
    "sg:address":"Bosstraat 18",
    "sg:city":"Erpe-mere",
    "sg:classifiers":[
        {
            "category":"Insurance",
            "subcategory":"Life Insurance",
            "type":"Services"
        }
    ],
    "sg:phone":"+32 53 83 18 18",
    "sg:postcode":"9420",
    "sg:province":"Oost-Vlaanderen",
    "sg:tags":[
        "assurance"
    ],
    "wof:name":"W. Hostens",
    "wof:placetype":"venue"
},
  "geometry": {"coordinates":[3.9665329456,50.92370224],"type":"Point"}
}