{
  "type": "Feature",
  "properties": {
    "iso:country":"BE",
    "sg:address":"Kerkhovensesteenweg 21",
    "sg:city":"Lommel",
    "sg:classifiers":[
        {
            "category":"Farming",
            "subcategory":"Livestock Farm",
            "type":"Manufacturing & Wholesale Goods"
        }
    ],
    "sg:phone":"+32 11 54 42 89",
    "sg:postcode":"3920",
    "sg:province":"Limburg",
    "sg:tags":[
        "horse"
    ],
    "wof:name":"Deferm Bart",
    "wof:placetype":"venue"
},
  "geometry": {"coordinates":[5.2991828918,51.185749054],"type":"Point"}
}