{
  "type": "Feature",
  "properties": {
    "addr:full":"Rue De Cerfontaine 94 Peruwelz Hainaut 7600",
    "addr:housenumber":"94",
    "addr:postcode":"7600",
    "addr:street":"Rue De Cerfontaine;Hainaut",
    "iso:country":"BE",
    "sg:address":"Rue De Cerfontaine 94",
    "sg:city":"Peruwelz",
    "sg:orig_category":"Artsen and specialisten",
    "sg:phone":"+32 69 77 44 91",
    "sg:postcode":"7600",
    "sg:province":"Hainaut",
    "wof:name":"Micheline Mareen",
    "wof:placetype":"venue"
},
  "geometry": {"coordinates":[3.5804800987,50.5034561157],"type":"Point"}
}