{
  "type": "Feature",
  "properties": {
    "addr:full":"Bulmolenweg 8 Dentergem West-Vlaanderen 8720",
    "addr:housenumber":"8",
    "addr:postcode":"8720",
    "addr:street":"Bulmolenweg",
    "iso:country":"BE",
    "sg:address":"Bulmolenweg 8",
    "sg:city":"Dentergem",
    "sg:orig_category":"Traitements param\u00e9dicaux",
    "sg:phone":"+32 51 63 54 04",
    "sg:postcode":"8720",
    "sg:province":"West-Vlaanderen",
    "wof:name":"Logosoft",
    "wof:placetype":"venue"
},
  "geometry": {"coordinates":[3.4000990391,50.94713974],"type":"Point"}
}