{
  "type": "Feature",
  "properties": {
    "addr:full":"Bierweg 24 Aalter Oost-Vlaanderen 9880",
    "addr:housenumber":"24",
    "addr:postcode":"9880",
    "addr:street":"Bierweg",
    "iso:country":"BE",
    "sg:address":"Bierweg 24",
    "sg:city":"Aalter",
    "sg:classifiers":[
        {
            "category":"Real Estate",
            "subcategory":"Real Estate Operator",
            "type":"Services"
        }
    ],
    "sg:phone":"+32 9 375 30 39",
    "sg:postcode":"9880",
    "sg:province":"Oost-Vlaanderen",
    "sg:tags":[
        "pump",
        "centrifugal"
    ],
    "wof:name":"Speck Pompen Belgi\u00eb Nv",
    "wof:placetype":"venue"
},
  "geometry": {"coordinates":[3.4416139126,51.0859336853],"type":"Point"}
}