{
  "type": "Feature",
  "properties": {
    "addr:full":"Baron Ruzettelaan 78 Box 8 Brugge (assebroek) West-Vlaanderen 8310",
    "addr:housenumber":"78;8",
    "addr:postcode":"8310",
    "addr:street":"Baron Ruzettelaan;Box",
    "iso:country":"BE",
    "sg:address":"Baron Ruzettelaan 78 Box 8",
    "sg:city":"Brugge (assebroek)",
    "sg:orig_category":"Fiduciairies",
    "sg:phone":"+32 50 35 74 51",
    "sg:postcode":"8310",
    "sg:province":"West-Vlaanderen",
    "wof:name":"Accountantskantoor Slabbinck R Bvba",
    "wof:placetype":"venue"
},
  "geometry": {"coordinates":[3.2313389778,51.1950378418],"type":"Point"}
}