{
  "type": "Feature",
  "properties": {
    "iso:country":"BE",
    "sg:address":"Assesteenweg 300",
    "sg:city":"Ternat",
    "sg:orig_category":"Woningbouw",
    "sg:phone":"+32 2 582 86 80",
    "sg:postcode":"1742",
    "sg:province":"Vlaams-Brabant",
    "wof:name":"David Dillens",
    "wof:placetype":"venue"
},
  "geometry": {"coordinates":[4.1620998383,50.8723297119],"type":"Point"}
}