{
  "type": "Feature",
  "properties": {
    "iso:country":"BE",
    "sg:address":"Pastorijstraat 11",
    "sg:city":"Houthalen-helchteren (houthalen)",
    "sg:classifiers":[
        {
            "category":"Organizations",
            "subcategory":"Community Association",
            "type":"Services"
        }
    ],
    "sg:phone":"+32 11 52 40 10",
    "sg:postcode":"3530",
    "sg:province":"Limburg",
    "sg:tags":[
        "cultural"
    ],
    "wof:name":"Parochiaal Cultureel Centrum",
    "wof:placetype":"venue"
},
  "geometry": {"coordinates":[5.3727631569,51.0297470093],"type":"Point"}
}