{
  "type": "Feature",
  "properties": {
    "addr:full":"Faubourg De Lille 69 Komen-waasten/comines-warneton Hainaut 7784",
    "addr:housenumber":"69;7784",
    "addr:street":"Faubourg De Lille",
    "iso:country":"BE",
    "sg:address":"Faubourg De Lille 69",
    "sg:city":"Komen-waasten/comines-warneton",
    "sg:classifiers":[
        {
            "category":"Food & Beverages",
            "subcategory":"Fruits & Vegetables",
            "type":"Retail Goods"
        }
    ],
    "sg:phone":"+32 56 58 92 54",
    "sg:postcode":"7784",
    "sg:province":"Hainaut",
    "sg:tags":[
        "l\u00e9gumes"
    ],
    "wof:name":"Maison D'hantschotter R.",
    "wof:placetype":"venue"
},
  "geometry": {"coordinates":[2.9414350986,50.7495651245],"type":"Point"}
}