{
  "type": "Feature",
  "properties": {
    "addr:full":"Mutsaardweg 35 Rijkevorsel Antwerpen 2310",
    "addr:housenumber":"35",
    "addr:postcode":"2310",
    "addr:street":"Mutsaardweg",
    "iso:country":"BE",
    "sg:address":"Mutsaardweg 35",
    "sg:city":"Rijkevorsel",
    "sg:orig_category":"Rev\u00eatements pour sols and murs",
    "sg:phone":"+32 3 314 48 57",
    "sg:postcode":"2310",
    "sg:province":"Antwerpen",
    "wof:name":"Roger Hoppenbrouwers",
    "wof:placetype":"venue"
},
  "geometry": {"coordinates":[4.7619290352,51.3396873474],"type":"Point"}
}