{
  "type": "Feature",
  "properties": {
    "iso:country":"BE",
    "sg:address":"Steenweg Op Rijsel 53",
    "sg:city":"Komen-waasten/comines-warneton",
    "sg:orig_category":"Benzinestations and brandstoffen",
    "sg:phone":"+32 56 58 88 15",
    "sg:postcode":"7784",
    "sg:province":"Hainaut",
    "wof:name":"Station Copain",
    "wof:placetype":"venue"
},
  "geometry": {"coordinates":[2.9404909611,50.7490615845],"type":"Point"}
}