{
  "type": "Feature",
  "properties": {
    "iso:country":"BE",
    "sg:address":"Gulledelle 94",
    "sg:city":"Bruxelles (woluwe-saint-lambert)",
    "sg:classifiers":[
        {
            "category":"Mining & Drilling",
            "type":"Manufacturing & Wholesale Goods"
        }
    ],
    "sg:phone":"+32 2 773 35 71",
    "sg:postcode":"1200",
    "sg:province":"Bruxelles-Capitale",
    "sg:tags":[
        "quarry"
    ],
    "wof:name":"Ucp (snc-vgn)",
    "wof:placetype":"venue"
},
  "geometry": {"coordinates":[4.4245529175,50.8558616638],"type":"Point"}
}