{
  "type": "Feature",
  "properties": {
    "addr:full":"Doornhof 6 Diest Vlaams-Brabant 3294",
    "addr:housenumber":"6",
    "addr:postcode":"3294",
    "addr:street":"Doornhof",
    "iso:country":"BE",
    "sg:address":"Doornhof 6",
    "sg:city":"Diest",
    "sg:orig_category":"Studios photographiques. Equipement photographique",
    "sg:phone":"+32 13 32 30 00",
    "sg:postcode":"3294",
    "sg:province":"Vlaams-Brabant",
    "wof:name":"Foto Atelier De 3 Kronen",
    "wof:placetype":"venue"
},
  "geometry": {"coordinates":[5.0133299828,51.0038795471],"type":"Point"}
}