{
  "type": "Feature",
  "properties": {
    "addr:full":"Norbert Gillelaan 87 Anderlecht/anderlecht Bruxelles-Capitale 1070",
    "addr:housenumber":"87",
    "addr:postcode":"1070",
    "addr:street":"Norbert Gillelaan",
    "iso:country":"BE",
    "sg:address":"Norbert Gillelaan 87",
    "sg:city":"Anderlecht/anderlecht",
    "sg:classifiers":[
        {
            "category":"Cafe",
            "type":"Food & Drink"
        }
    ],
    "sg:phone":"+32 2 520 57 94",
    "sg:postcode":"1070",
    "sg:province":"Bruxelles-Capitale",
    "sg:tags":[
        "caf\u00e9s"
    ],
    "wof:name":"Caf\u00c9 Lefi Muharem",
    "wof:placetype":"venue"
},
  "geometry": {"coordinates":[4.3142709732,50.8451347351],"type":"Point"}
}