{
  "type": "Feature",
  "properties": {
    "addr:full":"Waversebaan 51 Zemst Vlaams-Brabant 1982",
    "addr:housenumber":"51",
    "addr:postcode":"1982",
    "addr:street":"Waversebaan;Vlaams-Brabant",
    "iso:country":"BE",
    "sg:address":"Waversebaan 51",
    "sg:city":"Zemst",
    "sg:orig_category":"Gespecialiseerde residenti\u00eble bouw Plaatsen van vloer- and muurbekleding",
    "sg:phone":"+32 15 61 32 31",
    "sg:postcode":"1982",
    "sg:province":"Vlaams-Brabant",
    "wof:name":"Ronald Meysmans",
    "wof:placetype":"venue"
},
  "geometry": {"coordinates":[4.4943499565,50.9645042419],"type":"Point"}
}