{
  "type": "Feature",
  "properties": {
    "addr:full":"Zuiderdijk 9 Rijkevorsel Antwerpen 2310",
    "addr:housenumber":"9",
    "addr:postcode":"2310",
    "addr:street":"Zuiderdijk",
    "iso:country":"BE",
    "sg:address":"Zuiderdijk 9",
    "sg:city":"Rijkevorsel",
    "sg:orig_category":"Afval and schroot Gh",
    "sg:phone":"+32 3 311 56 49",
    "sg:postcode":"2310",
    "sg:province":"Antwerpen",
    "wof:name":"Colmetal",
    "wof:placetype":"venue"
},
  "geometry": {"coordinates":[4.7595419884,51.3500099182],"type":"Point"}
}