{
  "type": "Feature",
  "properties": {
    "addr:full":"Rue Paul Pastur 253 Charleroi (lodelinsart) Hainaut 6042",
    "addr:housenumber":"253",
    "addr:postcode":"6042",
    "addr:street":"Rue Paul Pastur",
    "iso:country":"BE",
    "sg:address":"Rue Paul Pastur 253",
    "sg:city":"Charleroi (lodelinsart)",
    "sg:classifiers":[
        {
            "category":"Sports & Exercise",
            "subcategory":"Stables",
            "type":"Entertainment"
        }
    ],
    "sg:phone":"+32 71 31 04 08",
    "sg:postcode":"6042",
    "sg:province":"Hainaut",
    "sg:tags":[
        "riding",
        "school"
    ],
    "wof:name":"Cercle Equestre L'amazone",
    "wof:placetype":"venue"
},
  "geometry": {"coordinates":[4.3600201607,50.4079208374],"type":"Point"}
}