{
  "type": "Feature",
  "properties": {
    "iso:country":"BE",
    "sg:address":"Avenue Bourgmestre Jean Herinckx 16 Box 7",
    "sg:city":"Bruxelles (uccle)",
    "sg:classifiers":[
        {
            "category":"Banks & Credit Unions",
            "subcategory":"Investment Brokerage",
            "type":"Services"
        }
    ],
    "sg:phone":"+32 2 343 83 88",
    "sg:postcode":"1180",
    "sg:province":"Bruxelles-Capitale",
    "sg:tags":[
        "distributor",
        "-",
        "distributors",
        "physical"
    ],
    "wof:name":"G.d.s. Sprl",
    "wof:placetype":"venue"
},
  "geometry": {"coordinates":[4.3493118286,50.8096160889],"type":"Point"}
}