{
  "type": "Feature",
  "properties": {
    "addr:full":"Rue Des Chasseurs Ardennais 25 Chiny (izel) Luxembourg 6810",
    "addr:housenumber":"25",
    "addr:postcode":"6810",
    "addr:street":"Rue Des Chasseurs Ardennais",
    "iso:country":"BE",
    "sg:address":"Rue Des Chasseurs Ardennais 25",
    "sg:city":"Chiny (izel)",
    "sg:classifiers":[
        {
            "category":"Building & Trades",
            "subcategory":"Plumbing",
            "type":"Services"
        }
    ],
    "sg:phone":"+32 61 32 84 87",
    "sg:postcode":"6810",
    "sg:province":"Luxembourg",
    "sg:tags":[
        "repair",
        "mainten",
        "-",
        "central",
        "heating"
    ],
    "wof:name":"Pecheur F",
    "wof:placetype":"venue"
},
  "geometry": {"coordinates":[5.3759570122,49.6953582764],"type":"Point"}
}