{
  "type": "Feature",
  "properties": {
    "iso:country":"BE",
    "sg:address":"Rue Ferrer 82",
    "sg:city":"Frameries",
    "sg:orig_category":"Pain, p\u00e2tisseries and confiseries",
    "sg:phone":"+32 65 67 77 26",
    "sg:postcode":"7080",
    "sg:province":"Hainaut",
    "wof:name":"La Bo\u00cete \u00c0 Pain",
    "wof:placetype":"venue"
},
  "geometry": {"coordinates":[3.8983550072,50.4054679871],"type":"Point"}
}