{
  "type": "Feature",
  "properties": {
    "addr:full":"Mechelsesteenweg 24 Kontich Antwerpen 2550",
    "addr:housenumber":"24",
    "addr:postcode":"2550",
    "addr:street":"Mechelsesteenweg",
    "iso:country":"BE",
    "sg:address":"Mechelsesteenweg 24",
    "sg:city":"Kontich",
    "sg:classifiers":[
        {
            "category":"Retail",
            "subcategory":"Repair Shop",
            "type":"Services"
        }
    ],
    "sg:phone":"+32 3 457 29 04",
    "sg:postcode":"2550",
    "sg:province":"Antwerpen",
    "sg:tags":[
        "photographic",
        "equipment",
        "-",
        "accessory"
    ],
    "wof:name":"Release Beeld & Geluid",
    "wof:placetype":"venue"
},
  "geometry": {"coordinates":[4.4451007843,51.134059906],"type":"Point"}
}