{
  "type": "Feature",
  "properties": {
    "addr:full":"Grotestraat 46 Maasmechelen (boorsem) Limburg 3631",
    "addr:housenumber":"46",
    "addr:postcode":"3631",
    "addr:street":"Grotestraat",
    "iso:country":"BE",
    "sg:address":"Grotestraat 46",
    "sg:city":"Maasmechelen (boorsem)",
    "sg:classifiers":[
        {
            "category":"Health Services",
            "subcategory":"Dentist",
            "type":"Services"
        }
    ],
    "sg:phone":"+32 89 76 55 74",
    "sg:postcode":"3631",
    "sg:province":"Limburg",
    "wof:name":"Sleypen D",
    "wof:placetype":"venue"
},
  "geometry": {"coordinates":[5.7239232063,50.9423713684],"type":"Point"}
}