{
  "type": "Feature",
  "properties": {
    "addr:full":"Jules Moretuslei 452 Antwerpen Antwerpen 2610",
    "addr:housenumber":"452",
    "addr:postcode":"2610",
    "addr:street":"Jules Moretuslei",
    "iso:country":"BE",
    "sg:address":"Jules Moretuslei 452",
    "sg:city":"Antwerpen",
    "sg:orig_category":"Begrafeniswezen",
    "sg:phone":"+32 3 827 11 04",
    "sg:postcode":"2610",
    "sg:province":"Antwerpen",
    "wof:name":"Jacobs",
    "wof:placetype":"venue"
},
  "geometry": {"coordinates":[4.3946051598,51.1691131592],"type":"Point"}
}