{
  "type": "Feature",
  "properties": {
    "addr:full":"Av. Eug\u00c8ne Mullendorff 2 Verviers Li\u00e8ge 4800",
    "addr:housenumber":"2",
    "addr:postcode":"4800",
    "addr:street":"Av. Euge\u0300Ne Mullendorff",
    "iso:country":"BE",
    "sg:address":"Av. Eug\u00c8ne Mullendorff 2",
    "sg:city":"Verviers",
    "sg:orig_category":"Tabac",
    "sg:phone":"+32 87 33 92 38",
    "sg:postcode":"4800",
    "sg:province":"Li\u00e8ge",
    "wof:name":"Georges Bertholet",
    "wof:placetype":"venue"
},
  "geometry": {"coordinates":[5.8671851158,50.5901260376],"type":"Point"}
}