{
  "type": "Feature",
  "properties": {
    "addr:full":"Mechelsesteenweg 232 Zaventem Vlaams-Brabant 1933",
    "addr:housenumber":"232",
    "addr:postcode":"1933",
    "addr:street":"Mechelsesteenweg",
    "iso:country":"BE",
    "sg:address":"Mechelsesteenweg 232",
    "sg:city":"Zaventem",
    "sg:orig_category":"Fotografen and fotostudio's",
    "sg:phone":"+32 2 731 27 80",
    "sg:postcode":"1933",
    "sg:province":"Vlaams-Brabant",
    "wof:name":"Baert-van De Waeyenberg",
    "wof:placetype":"venue"
},
  "geometry": {"coordinates":[4.5152211189,50.8626823425],"type":"Point"}
}