{
  "type": "Feature",
  "properties": {
    "addr:full":"Rue De Linthout 165 Bruxelles (woluwe-saint-lambert) Bruxelles-Capitale 1200",
    "addr:housenumber":"165",
    "addr:postcode":"1200",
    "addr:street":"Rue De Linthout",
    "iso:country":"BE",
    "sg:address":"Rue De Linthout 165",
    "sg:city":"Bruxelles (woluwe-saint-lambert)",
    "sg:classifiers":[
        {
            "category":"Personal",
            "subcategory":"Beauty Salon",
            "type":"Services"
        }
    ],
    "sg:phone":"+32 2 736 45 35",
    "sg:postcode":"1200",
    "sg:province":"Bruxelles-Capitale",
    "sg:tags":[
        "lady",
        "-",
        "hairdressing"
    ],
    "wof:name":"Anthony-and.",
    "wof:placetype":"venue"
},
  "geometry": {"coordinates":[4.401517868,50.8408508301],"type":"Point"}
}