{
  "type": "Feature",
  "properties": {
    "iso:country":"BE",
    "sg:address":"Tribomont 10",
    "sg:city":"Herve",
    "sg:orig_category":"Paramedische behandelingen",
    "sg:phone":"+32 87 31 18 27",
    "sg:postcode":"4650",
    "sg:province":"Li\u00e8ge",
    "wof:name":"Bodeux",
    "wof:placetype":"venue"
},
  "geometry": {"coordinates":[5.8207788467,50.6008796692],"type":"Point"}
}