{
  "type": "Feature",
  "properties": {
    "iso:country":"BE",
    "sg:address":"Markt 1",
    "sg:city":"De Panne",
    "sg:orig_category":"Slagers",
    "sg:phone":"+32 58 41 13 09",
    "sg:postcode":"8660",
    "sg:province":"West-Vlaanderen",
    "wof:name":"Noel Dequeecker",
    "wof:placetype":"venue"
},
  "geometry": {"coordinates":[2.594340086,51.0992698669],"type":"Point"}
}