{
  "type": "Feature",
  "properties": {
    "iso:country":"BE",
    "sg:address":"Vennen 30",
    "sg:city":"Herentals",
    "sg:classifiers":[
        {
            "category":"Personal",
            "subcategory":"Sauna",
            "type":"Services"
        }
    ],
    "sg:phone":"+32 13 67 61 75",
    "sg:postcode":"2200",
    "sg:province":"Antwerpen",
    "wof:name":"Ter Venne Bvba",
    "wof:placetype":"venue"
},
  "geometry": {"coordinates":[4.844933033,51.1653938293],"type":"Point"}
}