{
  "type": "Feature",
  "properties": {
    "addr:full":"Stintelaarstraat 4 Bilzen (martenslinde) Limburg 3742",
    "addr:housenumber":"4",
    "addr:postcode":"3742",
    "addr:street":"Stintelaarstraat",
    "iso:country":"BE",
    "sg:address":"Stintelaarstraat 4",
    "sg:city":"Bilzen (martenslinde)",
    "sg:classifiers":[
        {
            "category":"Professional",
            "subcategory":"Computer Services",
            "type":"Services"
        }
    ],
    "sg:phone":"+32 89 50 17 59",
    "sg:postcode":"3742",
    "sg:province":"Limburg",
    "sg:tags":[
        "-",
        "processing",
        "data"
    ],
    "wof:name":"Mardata",
    "wof:placetype":"venue"
},
  "geometry": {"coordinates":[5.5366449356,50.8542747498],"type":"Point"}
}