{
  "type": "Feature",
  "properties": {
    "iso:country":"BE",
    "sg:address":"Zilvermeerlaan 5",
    "sg:city":"Mol",
    "sg:classifiers":[
        {
            "category":"Banks & Credit Unions",
            "subcategory":"Investment Brokerage",
            "type":"Services"
        }
    ],
    "sg:phone":"+32 14 81 60 28",
    "sg:postcode":"2400",
    "sg:province":"Antwerpen",
    "sg:tags":[
        "rental",
        "-",
        "yacht",
        "boat",
        "pleasure"
    ],
    "wof:name":"Water-dreams Bvba",
    "wof:placetype":"venue"
},
  "geometry": {"coordinates":[5.1798357964,51.2299842834],"type":"Point"}
}