{
  "type": "Feature",
  "properties": {
    "addr:full":"Hoevelei 181 Aartselaar Antwerpen 2630",
    "addr:housenumber":"181",
    "addr:postcode":"2630",
    "addr:street":"Hoevelei",
    "iso:country":"BE",
    "sg:address":"Hoevelei 181",
    "sg:city":"Aartselaar",
    "sg:classifiers":[
        {
            "category":"Cafe",
            "type":"Food & Drink"
        }
    ],
    "sg:phone":"+32 3 887 32 44",
    "sg:postcode":"2630",
    "sg:province":"Antwerpen",
    "sg:tags":[
        "caf\u00e9s"
    ],
    "wof:name":"Kaffee Oo Deusjevoo",
    "wof:placetype":"venue"
},
  "geometry": {"coordinates":[4.3790831566,51.1396827698],"type":"Point"}
}