{
  "type": "Feature",
  "properties": {
    "addr:full":"Rue De Temploux 50 Jemeppe-sur-sambre Namur 5190",
    "addr:housenumber":"50",
    "addr:postcode":"5190",
    "addr:street":"Rue De Temploux",
    "iso:country":"BE",
    "sg:address":"Rue De Temploux 50",
    "sg:city":"Jemeppe-sur-sambre",
    "sg:orig_category":"Kapsalons",
    "sg:phone":"+32 71 78 03 61",
    "sg:postcode":"5190",
    "sg:province":"Namur",
    "wof:name":"Constructif-brigite Espreux",
    "wof:placetype":"venue"
},
  "geometry": {"coordinates":[4.7194471359,50.4818000793],"type":"Point"}
}