{
  "type": "Feature",
  "properties": {
    "iso:country":"BE",
    "sg:address":"Grote Steenweg 116",
    "sg:city":"Zulte (olsene)",
    "sg:classifiers":[
        {
            "category":"Professional",
            "subcategory":"Testing Lab",
            "type":"Services"
        }
    ],
    "sg:phone":"+32 9 388 82 53",
    "sg:postcode":"9870",
    "sg:province":"Oost-Vlaanderen",
    "sg:tags":[
        "chemist"
    ],
    "wof:name":"Vandermarliere M Nv",
    "wof:placetype":"venue"
},
  "geometry": {"coordinates":[3.4436409473,50.921661377],"type":"Point"}
}