{
  "type": "Feature",
  "properties": {
    "iso:country":"BE",
    "sg:address":"Rue Du Pont",
    "sg:city":"Pont-a-celles",
    "sg:orig_category":"Benzinestations and brandstoffen HUISBRANDOLIE Royal Canin",
    "sg:phone":"+32 71 84 53 78",
    "sg:postcode":"6230",
    "sg:province":"Hainaut",
    "wof:name":"Jurion Luc",
    "wof:placetype":"venue"
},
  "geometry": {"coordinates":[4.3553719521,50.5130767822],"type":"Point"}
}