{
  "type": "Feature",
  "properties": {
    "addr:full":"Bredabaan 424 Brasschaat Antwerpen 2930",
    "addr:housenumber":"424",
    "addr:postcode":"2930",
    "addr:street":"Bredabaan",
    "iso:country":"BE",
    "sg:address":"Bredabaan 424",
    "sg:city":"Brasschaat",
    "sg:classifiers":[
        {
            "category":"Structure",
            "subcategory":"Office Building",
            "type":"Public Place"
        }
    ],
    "sg:phone":"+32 3 650 15 25",
    "sg:postcode":"2930",
    "sg:province":"Antwerpen",
    "sg:tags":[
        "equipment",
        "alarm",
        "installation",
        "system"
    ],
    "wof:name":"Alarm & Veiligheid Vochten Nv",
    "wof:placetype":"venue"
},
  "geometry": {"coordinates":[4.4964399338,51.2952766418],"type":"Point"}
}