{
  "type": "Feature",
  "properties": {
    "addr:full":"Nieuwmoer Dorp 19 Kalmthout Antwerpen 2920",
    "addr:housenumber":"19",
    "addr:postcode":"2920",
    "addr:street":"Nieuwmoer Dorp",
    "iso:country":"BE",
    "sg:address":"Nieuwmoer Dorp 19",
    "sg:city":"Kalmthout",
    "sg:classifiers":[
        {
            "category":"Organizations",
            "subcategory":"Political Organization",
            "type":"Services"
        }
    ],
    "sg:phone":"+32 3 667 53 04",
    "sg:postcode":"2920",
    "sg:province":"Antwerpen",
    "sg:tags":[
        "owner",
        "ship"
    ],
    "wof:name":"Zadeko Shipping Nv",
    "wof:placetype":"venue"
},
  "geometry": {"coordinates":[4.5151000023,51.4325866699],"type":"Point"}
}