{
  "type": "Feature",
  "properties": {
    "iso:country":"BE",
    "sg:address":"Chemin De L'oasis 85",
    "sg:city":"Mons",
    "sg:orig_category":"Fairs, shows, exhibitions",
    "sg:phone":"+32 65 84 01 28",
    "sg:postcode":"7000",
    "sg:province":"Hainaut",
    "wof:name":"E.s.f.",
    "wof:placetype":"venue"
},
  "geometry": {"coordinates":[3.9848840237,50.4631080627],"type":"Point"}
}