{
  "type": "Feature",
  "properties": {
    "iso:country":"BE",
    "sg:address":"Antwerpsestraat 6",
    "sg:city":"Lier",
    "sg:orig_category":"Apotheken",
    "sg:phone":"+32 3 480 07 15",
    "sg:postcode":"2500",
    "sg:province":"Antwerpen",
    "wof:name":"De Voorzorg",
    "wof:placetype":"venue"
},
  "geometry": {"coordinates":[4.569258213,51.131942749],"type":"Point"}
}