{
  "type": "Feature",
  "properties": {
    "addr:full":"Leuvensestraat 62 Aarschot Vlaams-Brabant 3200",
    "addr:housenumber":"62",
    "addr:postcode":"3200",
    "addr:street":"Leuvensestraat",
    "iso:country":"BE",
    "sg:address":"Leuvensestraat 62",
    "sg:city":"Aarschot",
    "sg:classifiers":[
        {
            "category":"Restaurant",
            "type":"Food & Drink"
        }
    ],
    "sg:phone":"+32 16 56 64 64",
    "sg:postcode":"3200",
    "sg:province":"Vlaams-Brabant",
    "wof:name":"Keizershof",
    "wof:placetype":"venue"
},
  "geometry": {"coordinates":[4.831589222,50.9835395813],"type":"Point"}
}