{
  "type": "Feature",
  "properties": {
    "addr:full":"Rue Saint-l\u00e9onard 243 Li\u00e8ge 1 Li\u00e8ge 4000",
    "addr:housenumber":"243;1",
    "addr:postcode":"4000",
    "addr:street":"Rue Saint-Le\u0301Onard",
    "iso:country":"BE",
    "sg:address":"Rue Saint-l\u00e9onard 243",
    "sg:city":"Li\u00e8ge 1",
    "sg:classifiers":[
        {
            "category":"Health Services",
            "subcategory":"Doctor",
            "type":"Services"
        }
    ],
    "sg:phone":"+32 4 227 47 59",
    "sg:postcode":"4000",
    "sg:province":"Li\u00e8ge",
    "sg:tags":[
        "medicinephysicians",
        "surgeon"
    ],
    "wof:name":"Dethier Marc",
    "wof:placetype":"venue"
},
  "geometry": {"coordinates":[5.5959701538,50.650970459],"type":"Point"}
}