{
  "type": "Feature",
  "properties": {
    "iso:country":"BE",
    "sg:address":"Brusselsesteenweg 33",
    "sg:city":"Herent",
    "sg:orig_category":"Autombile concessionaires",
    "sg:phone":"+32 16 20 60 80",
    "sg:postcode":"3020",
    "sg:province":"Vlaams-Brabant",
    "wof:name":"Landeloos Nv",
    "wof:placetype":"venue"
},
  "geometry": {"coordinates":[4.6668691635,50.8869514465],"type":"Point"}
}