{
  "type": "Feature",
  "properties": {
    "addr:full":"Chauss\u00e9e De Louvain 454 Namur (bouge) Namur 5004",
    "addr:housenumber":"454",
    "addr:postcode":"5004",
    "addr:street":"Chausse\u0301E De Louvain",
    "iso:country":"BE",
    "sg:address":"Chauss\u00e9e De Louvain 454",
    "sg:city":"Namur (bouge)",
    "sg:classifiers":[
        {
            "category":"Home & Garden",
            "subcategory":"Home Furnishings",
            "type":"Retail Goods"
        }
    ],
    "sg:phone":"+32 81 21 41 01",
    "sg:postcode":"5004",
    "sg:province":"Namur",
    "sg:tags":[
        "curtain",
        "-",
        "fixture"
    ],
    "wof:name":"L & J Scrl",
    "wof:placetype":"venue"
},
  "geometry": {"coordinates":[4.8875179291,50.4838676453],"type":"Point"}
}