{
  "type": "Feature",
  "properties": {
    "iso:country":"BE",
    "sg:address":"Bankstraat 44",
    "sg:city":"Beveren (haasdonk)",
    "sg:classifiers":[
        {
            "category":"Wholesale",
            "subcategory":"Fruits & Vegetables",
            "type":"Manufacturing & Wholesale Goods"
        }
    ],
    "sg:phone":"+32 3 775 64 07",
    "sg:postcode":"9120",
    "sg:province":"Oost-Vlaanderen",
    "sg:tags":[
        "whol",
        "-",
        "potato"
    ],
    "wof:name":"De Clercq Luc & Zonen",
    "wof:placetype":"venue"
},
  "geometry": {"coordinates":[4.2262978554,51.1762428284],"type":"Point"}
}