{
  "type": "Feature",
  "properties": {
    "addr:full":"Rue Vandy 13 Flawinne 5720",
    "addr:housenumber":"13",
    "addr:postcode":"5720",
    "addr:street":"Rue Vandy",
    "iso:country":"BE",
    "sg:address":"Rue Vandy 13",
    "sg:city":"Flawinne",
    "sg:classifiers":[
        {
            "category":"Banks & Credit Unions",
            "subcategory":"Bank",
            "type":"Services"
        }
    ],
    "sg:phone":"+32 81 73 75 56",
    "sg:postcode":"5720",
    "wof:name":"G\u00e9n\u00e9rale De Banque Sa",
    "wof:placetype":"venue"
},
  "geometry": {"coordinates":[4.8119301796,50.4570884705],"type":"Point"}
}