{
  "type": "Feature",
  "properties": {
    "iso:country":"BE",
    "sg:address":"Geraardsbergenstraat 171",
    "sg:city":"Ronse/renaix",
    "sg:orig_category":"Elektrische installaties voor woningen",
    "sg:phone":"+32 55 21 51 80",
    "sg:postcode":"9600",
    "sg:province":"Oost-Vlaanderen",
    "wof:name":"Geert De Roissart",
    "wof:placetype":"venue"
},
  "geometry": {"coordinates":[3.621368885,50.749420166],"type":"Point"}
}