{
  "type": "Feature",
  "properties": {
    "iso:country":"BE",
    "sg:address":"Kampelaar 27-29",
    "sg:city":"Brasschaat",
    "sg:classifiers":[
        {
            "category":"Health Services",
            "subcategory":"Doctor",
            "type":"Services"
        }
    ],
    "sg:phone":"+32 3 646 93 33",
    "sg:postcode":"2930",
    "sg:province":"Antwerpen",
    "sg:tags":[
        "medicinephysicians",
        "surgeon"
    ],
    "wof:name":"Degroote Johan",
    "wof:placetype":"venue"
},
  "geometry": {"coordinates":[4.4592719078,51.2763061523],"type":"Point"}
}