{
  "type": "Feature",
  "properties": {
    "iso:country":"BE",
    "sg:address":"Lotuslaan 20",
    "sg:city":"Boortmeerbeek (hever)",
    "sg:classifiers":[
        {
            "category":"Personal",
            "subcategory":"Beauty Salon",
            "type":"Services"
        }
    ],
    "sg:phone":"+32 15 61 41 78",
    "sg:postcode":"3191",
    "sg:province":"Vlaams-Brabant",
    "wof:name":"De Lotus Beauty & Well Being Center",
    "wof:placetype":"venue"
},
  "geometry": {"coordinates":[4.554901123,50.9925537109],"type":"Point"}
}