{
  "type": "Feature",
  "properties": {
    "addr:full":"Rue De L'int\u00c9rieur 150 Perwez Brabant Wallon 1360",
    "addr:housenumber":"150",
    "addr:postcode":"1360",
    "addr:street":"Rue De L'Inte \u0301Rieur",
    "iso:country":"BE",
    "sg:address":"Rue De L'int\u00c9rieur 150",
    "sg:city":"Perwez",
    "sg:orig_category":"Eleveurs de bovins",
    "sg:phone":"+32 81 65 59 78",
    "sg:postcode":"1360",
    "sg:province":"Brabant Wallon",
    "wof:name":"Christian Wellems",
    "wof:placetype":"venue"
},
  "geometry": {"coordinates":[4.7735118866,50.6247138977],"type":"Point"}
}