{
  "type": "Feature",
  "properties": {
    "iso:country":"BE",
    "sg:address":"Lantroul 2",
    "sg:city":"Ferrieres",
    "sg:orig_category":"Afbraak- and draineerwerken Woningbouw",
    "sg:phone":"+32 86 40 03 82",
    "sg:postcode":"4190",
    "sg:province":"Li\u00e8ge",
    "wof:name":"Pierre Dethier",
    "wof:placetype":"venue"
},
  "geometry": {"coordinates":[5.6375727654,50.3973846436],"type":"Point"}
}