{
  "type": "Feature",
  "properties": {
    "iso:country":"BE",
    "sg:address":"Rue Des Coutures 231",
    "sg:city":"Charleroi",
    "sg:orig_category":"Entretien and r\u00e9parations de voitures",
    "sg:phone":"+32 71 41 12 24",
    "sg:postcode":"6042",
    "sg:province":"Hainaut",
    "wof:name":"Garage Botte",
    "wof:placetype":"venue"
},
  "geometry": {"coordinates":[4.4490199089,50.4293518066],"type":"Point"}
}