{
  "type": "Feature",
  "properties": {
    "iso:country":"BE",
    "sg:address":"Kolisheide 40",
    "sg:city":"Neerpelt",
    "sg:orig_category":"Rundveehouders",
    "sg:phone":"+32 11 64 60 14",
    "sg:postcode":"3910",
    "sg:province":"Limburg",
    "wof:name":"Daniels Marcel & Andre",
    "wof:placetype":"venue"
},
  "geometry": {"coordinates":[5.4617338181,51.1957168579],"type":"Point"}
}