{
  "type": "Feature",
  "properties": {
    "iso:country":"BE",
    "sg:address":"Kerklaan 30",
    "sg:city":"Machelen",
    "sg:classifiers":[
        {
            "category":"Organizations",
            "subcategory":"Community Association",
            "type":"Services"
        }
    ],
    "sg:phone":"+32 2 252 28 63",
    "sg:postcode":"1830",
    "sg:province":"Vlaams-Brabant",
    "sg:tags":[
        "organisation"
    ],
    "wof:name":"Sjaloom",
    "wof:placetype":"venue"
},
  "geometry": {"coordinates":[4.4321408272,50.9130249023],"type":"Point"}
}