{
  "type": "Feature",
  "properties": {
    "addr:full":"Boulevard Barth\u00c9l\u00c9my 17 Brussel/bruxelles Bruxelles-Capitale 1000",
    "addr:housenumber":"17",
    "addr:postcode":"1000",
    "addr:street":"Boulevard Barthe\u0301Le\u0301My;/",
    "iso:country":"BE",
    "sg:address":"Boulevard Barth\u00c9l\u00c9my 17",
    "sg:city":"Brussel/bruxelles",
    "sg:classifiers":[
        {
            "category":"Sports & Exercise",
            "subcategory":"Sports Center",
            "type":"Entertainment"
        }
    ],
    "sg:phone":"+32 2 512 51 33",
    "sg:postcode":"1000",
    "sg:province":"Bruxelles-Capitale",
    "sg:tags":[
        "terrain",
        "hors",
        "de",
        "installation",
        "sportifs"
    ],
    "wof:name":"Flanders Gate",
    "wof:placetype":"venue"
},
  "geometry": {"coordinates":[4.3407530785,50.852142334],"type":"Point"}
}