{
  "type": "Feature",
  "properties": {
    "addr:full":"Rue Du Pr\u00e9sident Allende 55 Chapelle-lez-herlaimont (godarville) Hainaut 7160",
    "addr:housenumber":"55",
    "addr:postcode":"7160",
    "addr:street":"Rue Du Pre\u0301Sident Allende",
    "iso:country":"BE",
    "sg:address":"Rue Du Pr\u00e9sident Allende 55",
    "sg:city":"Chapelle-lez-herlaimont (godarville)",
    "sg:classifiers":[
        {
            "category":"Retail",
            "subcategory":"Auto Repair",
            "type":"Services"
        }
    ],
    "sg:phone":"+32 64 44 98 34",
    "sg:postcode":"7160",
    "sg:province":"Hainaut",
    "sg:tags":[
        "automobile-body"
    ],
    "wof:name":"Auto Look Sprl",
    "wof:placetype":"venue"
},
  "geometry": {"coordinates":[4.2875790596,50.4942092896],"type":"Point"}
}