{
  "type": "Feature",
  "properties": {
    "addr:full":"Rue Louis Viatour 10 Profondeville Namur 5170",
    "addr:housenumber":"10",
    "addr:postcode":"5170",
    "addr:street":"Rue Louis Viatour",
    "iso:country":"BE",
    "sg:address":"Rue Louis Viatour 10",
    "sg:city":"Profondeville",
    "sg:orig_category":"Pleisterwerk",
    "sg:phone":"+32 81 41 15 79",
    "sg:postcode":"5170",
    "sg:province":"Namur",
    "wof:name":"Emile Thomas",
    "wof:placetype":"venue"
},
  "geometry": {"coordinates":[4.8702011108,50.3757591248],"type":"Point"}
}