{
  "type": "Feature",
  "properties": {
    "addr:full":"Jonkh.p. Coppietersdreef 17 Brugge West-Vlaanderen 8200",
    "addr:housenumber":"17",
    "addr:postcode":"8200",
    "iso:country":"BE",
    "sg:address":"Jonkh.p. Coppietersdreef 17",
    "sg:city":"Brugge",
    "sg:orig_category":"Schoonheidssalons",
    "sg:phone":"+32 50 39 17 30",
    "sg:postcode":"8200",
    "sg:province":"West-Vlaanderen",
    "wof:name":"Bernadette Baeyens",
    "wof:placetype":"venue"
},
  "geometry": {"coordinates":[3.1981990337,51.1954689026],"type":"Point"}
}