{
  "type": "Feature",
  "properties": {
    "iso:country":"BE",
    "sg:address":"Boulevard Du Roi Albert Ii 5",
    "sg:city":"Bruxelles (saint-josse-ten-noode)",
    "sg:classifiers":[
        {
            "category":"Organizations",
            "subcategory":"Professional Association",
            "type":"Services"
        }
    ],
    "sg:phone":"+32 2 224 02 11",
    "sg:postcode":"1210",
    "sg:province":"Bruxelles-Capitale",
    "sg:tags":[
        "trade-union",
        "federation"
    ],
    "wof:name":"Conf\u00e9d\u00e9ration Internationale Des Syndicats Libres",
    "wof:placetype":"venue"
},
  "geometry": {"coordinates":[4.3562707901,50.8571739197],"type":"Point"}
}