{
  "type": "Feature",
  "properties": {
    "iso:country":"BE",
    "sg:address":"Elisabethlaan 335",
    "sg:city":"Oostende",
    "sg:orig_category":"Cr\u00e9meries",
    "sg:phone":"+32 59 50 87 53",
    "sg:postcode":"8400",
    "sg:province":"West-Vlaanderen",
    "wof:name":"Jollijt",
    "wof:placetype":"venue"
},
  "geometry": {"coordinates":[2.9071149826,51.2144393921],"type":"Point"}
}