{
  "type": "Feature",
  "properties": {
    "iso:country":"BE",
    "sg:address":"Grand Route 6",
    "sg:city":"Fernelmont (hingeon)",
    "sg:classifiers":[
        {
            "category":"Building & Trades",
            "subcategory":"Construction",
            "type":"Services"
        }
    ],
    "sg:phone":"+32 81 83 40 42",
    "sg:postcode":"5380",
    "sg:province":"Namur",
    "sg:tags":[
        "installation",
        "-",
        "central",
        "heating"
    ],
    "wof:name":"Bougeois G",
    "wof:placetype":"venue"
},
  "geometry": {"coordinates":[5.0082240105,50.5289115906],"type":"Point"}
}