{
  "type": "Feature",
  "properties": {
    "iso:country":"BE",
    "sg:address":"Schelselei 15 E",
    "sg:city":"Aartselaar",
    "sg:orig_category":"Benzinestations and brandstoffen Onderdelen and accessoires voor auto's",
    "sg:phone":"+32 3 877 41 92",
    "sg:postcode":"2630",
    "sg:province":"Antwerpen",
    "wof:name":"Airco Systems",
    "wof:placetype":"venue"
},
  "geometry": {"coordinates":[4.387804985,51.1342391968],"type":"Point"}
}