{
  "type": "Feature",
  "properties": {
    "addr:full":"Nijverheidslaan 58 Deerlijk West-Vlaanderen 8540",
    "addr:housenumber":"58",
    "addr:postcode":"8540",
    "addr:street":"Nijverheidslaan",
    "iso:country":"BE",
    "sg:address":"Nijverheidslaan 58",
    "sg:city":"Deerlijk",
    "sg:classifiers":[
        {
            "category":"Manufacturing",
            "subcategory":"Textiles",
            "type":"Manufacturing & Wholesale Goods"
        }
    ],
    "sg:phone":"+32 56 77 48 10",
    "sg:postcode":"8540",
    "sg:province":"West-Vlaanderen",
    "sg:tags":[
        "finishing"
    ],
    "wof:name":"I & B Carpet Service Nv",
    "wof:placetype":"venue"
},
  "geometry": {"coordinates":[3.3871080875,50.855178833],"type":"Point"}
}