{
  "type": "Feature",
  "properties": {
    "iso:country":"BE",
    "sg:address":"Predikherenlei 2",
    "sg:city":"Belgium",
    "sg:classifiers":[
        {
            "category":"Travel",
            "subcategory":"Travel Agent",
            "type":"Entertainment"
        }
    ],
    "sg:postcode":"9000",
    "sg:province":"Oost-Vlaanderen",
    "wof:name":"Hotel De Orangerie",
    "wof:placetype":"venue"
},
  "geometry": {"coordinates":[3.2263960838,51.2069702148],"type":"Point"}
}