{
  "type": "Feature",
  "properties": {
    "addr:full":"Rue De Montroeul 115c Qui\u00e9vrain Hainaut 7380",
    "addr:housenumber":"115c",
    "addr:postcode":"7380",
    "addr:street":"Rue De Montroeul",
    "iso:country":"BE",
    "sg:address":"Rue De Montroeul 115c",
    "sg:city":"Qui\u00e9vrain",
    "sg:classifiers":[
        {
            "category":"Real Estate",
            "subcategory":"Architect",
            "type":"Services"
        }
    ],
    "sg:phone":"+32 65 45 70 26",
    "sg:postcode":"7380",
    "sg:province":"Hainaut",
    "wof:name":"Francois P",
    "wof:placetype":"venue"
},
  "geometry": {"coordinates":[3.6909279823,50.4131507874],"type":"Point"}
}