{
  "type": "Feature",
  "properties": {
    "addr:full":"Rue De Jodoigne 22 Huppaye Brabant Wallon 1367",
    "addr:housenumber":"22",
    "addr:postcode":"1367",
    "addr:street":"Rue De Jodoigne;Brabant Wallon",
    "iso:country":"BE",
    "sg:address":"Rue De Jodoigne 22",
    "sg:city":"Huppaye",
    "sg:orig_category":"Central Heating Boiler Brushes",
    "sg:phone":"+32 10 81 23 65",
    "sg:postcode":"1367",
    "sg:province":"Brabant Wallon",
    "wof:name":"Michel Heuvinck S.p.r.l.",
    "wof:placetype":"venue"
},
  "geometry": {"coordinates":[4.8970527649,50.6963424683],"type":"Point"}
}