{
  "type": "Feature",
  "properties": {
    "addr:full":"Reeckervelt 14 Riemst Limburg 3770",
    "addr:housenumber":"14",
    "addr:postcode":"3770",
    "addr:street":"Reeckervelt",
    "iso:country":"BE",
    "sg:address":"Reeckervelt 14",
    "sg:city":"Riemst",
    "sg:orig_category":"R\u00e9cup\u00e9ration de mati\u00e8res m\u00e9talliques recyclables and d\u00e9molisseurs de voitures. D\u00e9chets and d\u00e9bris Qu",
    "sg:phone":"+32 12 45 37 75",
    "sg:postcode":"3770",
    "sg:province":"Limburg",
    "wof:name":"Marcel Nijs",
    "wof:placetype":"venue"
},
  "geometry": {"coordinates":[5.5960831642,50.8171386719],"type":"Point"}
}