{
  "type": "Feature",
  "properties": {
    "addr:full":"Chemin De Perwez 16 Huy Li\u00e8ge 4500",
    "addr:housenumber":"16",
    "addr:postcode":"4500",
    "addr:street":"Chemin De Perwez",
    "iso:country":"BE",
    "sg:address":"Chemin De Perwez 16",
    "sg:city":"Huy",
    "sg:orig_category":"Algemeen secundair onderwijs",
    "sg:phone":"+32 85 61 26 70",
    "sg:postcode":"4500",
    "sg:province":"Li\u00e8ge",
    "wof:name":"E.s.e.s. L\u00b4heureux Abri",
    "wof:placetype":"venue"
},
  "geometry": {"coordinates":[5.1753921509,50.4738006592],"type":"Point"}
}