{
  "type": "Feature",
  "properties": {
    "addr:full":"Avenue Isidore Geyskens 124 Bruxelles (auderghem) Bruxelles-Capitale 1160",
    "addr:housenumber":"124",
    "addr:postcode":"1160",
    "addr:street":"Avenue Isidore Geyskens",
    "iso:country":"BE",
    "sg:address":"Avenue Isidore Geyskens 124",
    "sg:city":"Bruxelles (auderghem)",
    "sg:classifiers":[
        {
            "category":"Health Services",
            "subcategory":"Doctor",
            "type":"Services"
        }
    ],
    "sg:phone":"+32 2 675 12 12",
    "sg:postcode":"1160",
    "sg:province":"Bruxelles-Capitale",
    "sg:tags":[
        "medicinephysicians",
        "surgeon"
    ],
    "wof:name":"Hannesse M",
    "wof:placetype":"venue"
},
  "geometry": {"coordinates":[4.4230952263,50.8209571838],"type":"Point"}
}