{
  "type": "Feature",
  "properties": {
    "addr:full":"Avenue P. H\u00c9ger 22 Brussel/bruxelles Bruxelles-Capitale 1000",
    "addr:housenumber":"22",
    "addr:postcode":"1000",
    "addr:street":"Avenue P. He\u0301Ger;/",
    "iso:country":"BE",
    "sg:address":"Avenue P. H\u00c9ger 22",
    "sg:city":"Brussel/bruxelles",
    "sg:classifiers":[
        {
            "category":"Restaurant",
            "type":"Food & Drink"
        }
    ],
    "sg:phone":"+32 2 640 15 90",
    "sg:postcode":"1000",
    "sg:province":"Bruxelles-Capitale",
    "wof:name":"Petit Yoyo",
    "wof:placetype":"venue"
},
  "geometry": {"coordinates":[4.3817877769,50.8130607605],"type":"Point"}
}