{
  "type": "Feature",
  "properties": {
    "addr:full":"Neervenbaan 4 Brecht Antwerpen 2960",
    "addr:housenumber":"4",
    "addr:postcode":"2960",
    "addr:street":"Neervenbaan",
    "iso:country":"BE",
    "sg:address":"Neervenbaan 4",
    "sg:city":"Brecht",
    "sg:orig_category":"Rundveehouders",
    "sg:phone":"+32 3 313 85 87",
    "sg:postcode":"2960",
    "sg:province":"Antwerpen",
    "wof:name":"Marc De Ruysscher",
    "wof:placetype":"venue"
},
  "geometry": {"coordinates":[4.636952877,51.3635292053],"type":"Point"}
}