{
  "type": "Feature",
  "properties": {
    "addr:full":"Boulevard Emile Bockstael 285 Bruxelles Bruxelles-Capitale 1020",
    "addr:housenumber":"285",
    "addr:postcode":"1020",
    "addr:street":"Boulevard Emile Bockstael",
    "iso:country":"BE",
    "sg:address":"Boulevard Emile Bockstael 285",
    "sg:city":"Bruxelles",
    "sg:classifiers":[
        {
            "category":"Building & Trades",
            "subcategory":"Construction",
            "type":"Services"
        }
    ],
    "sg:phone":"+32 2 479 25 45",
    "sg:postcode":"1020",
    "sg:province":"Bruxelles-Capitale",
    "sg:tags":[
        "carpenter"
    ],
    "wof:name":"Esteves",
    "wof:placetype":"venue"
},
  "geometry": {"coordinates":[4.3478031158,50.8808403015],"type":"Point"}
}