{
  "type": "Feature",
  "properties": {
    "addr:full":"Blandenstraat 129 Oud-heverlee Vlaams-Brabant 3053",
    "addr:housenumber":"129",
    "addr:postcode":"3053",
    "addr:street":"Blandenstraat",
    "iso:country":"BE",
    "sg:address":"Blandenstraat 129",
    "sg:city":"Oud-heverlee",
    "sg:orig_category":"S\u00e9curit\u00e9 sociale",
    "sg:phone":"+32 16 40 33 40",
    "sg:postcode":"3053",
    "sg:province":"Vlaams-Brabant",
    "wof:name":"Euromut",
    "wof:placetype":"venue"
},
  "geometry": {"coordinates":[4.7239780426,50.8337783813],"type":"Point"}
}