{
  "type": "Feature",
  "properties": {
    "addr:full":"Rue Courte Saint-roch 5 Dinant Namur 5500",
    "addr:housenumber":"5",
    "addr:postcode":"5500",
    "addr:street":"Rue Courte Saint-Roch",
    "iso:country":"BE",
    "sg:address":"Rue Courte Saint-roch 5",
    "sg:city":"Dinant",
    "sg:classifiers":[
        {
            "category":"Social Services",
            "type":"Services"
        }
    ],
    "sg:phone":"+32 82 22 86 60",
    "sg:postcode":"5500",
    "sg:province":"Namur",
    "wof:name":"Famille D'accueil Odile Henri (la)",
    "wof:placetype":"venue"
},
  "geometry": {"coordinates":[4.9159560204,50.2551422119],"type":"Point"}
}