{
  "type": "Feature",
  "properties": {
    "addr:full":"Impasse Du Moulin 11 Havelange Namur 5370",
    "addr:housenumber":"11",
    "addr:postcode":"5370",
    "addr:street":"Impasse Du Moulin",
    "iso:country":"BE",
    "sg:address":"Impasse Du Moulin 11",
    "sg:city":"Havelange",
    "sg:classifiers":[
        {
            "category":"Arena",
            "subcategory":"Sports Club",
            "type":"Entertainment"
        }
    ],
    "sg:phone":"+32 83 63 32 75",
    "sg:postcode":"5370",
    "sg:province":"Namur",
    "sg:tags":[
        "installation",
        "sportifs",
        "de",
        "terrain",
        "hors",
        "caf\u00e9s"
    ],
    "wof:name":"R.c. Havelange",
    "wof:placetype":"venue"
},
  "geometry": {"coordinates":[5.2450370789,50.3869361877],"type":"Point"}
}