{
  "type": "Feature",
  "properties": {
    "iso:country":"BE",
    "sg:address":"Ingelmunstersteenweg 72",
    "sg:city":"Oostrozebeke",
    "sg:orig_category":"Huisdieren and benodigdheden Royal Canin",
    "sg:phone":"+32 56 66 55 44",
    "sg:postcode":"8780",
    "sg:province":"West-Vlaanderen",
    "wof:name":"Nv Vlaeminck Frans",
    "wof:placetype":"venue"
},
  "geometry": {"coordinates":[3.3143899441,50.9190101624],"type":"Point"}
}