{
  "type": "Feature",
  "properties": {
    "addr:full":"Overwinningstraat 71 Willebroek Antwerpen 2830",
    "addr:housenumber":"71",
    "addr:postcode":"2830",
    "addr:street":"Overwinningstraat",
    "iso:country":"BE",
    "sg:address":"Overwinningstraat 71",
    "sg:city":"Willebroek",
    "sg:orig_category":"Non-Classified Establishments",
    "sg:phone":"+32 3 886 25 13",
    "sg:postcode":"2830",
    "sg:province":"Antwerpen",
    "wof:name":"Cedeco",
    "wof:placetype":"venue"
},
  "geometry": {"coordinates":[4.3597297668,51.0587806702],"type":"Point"}
}