{
  "type": "Feature",
  "properties": {
    "addr:full":"Gilainstraat 33 Tienen Vlaams-Brabant 3300",
    "addr:housenumber":"33",
    "addr:postcode":"3300",
    "addr:street":"Gilainstraat",
    "iso:country":"BE",
    "sg:address":"Gilainstraat 33",
    "sg:city":"Tienen",
    "sg:orig_category":"Newspapers, magazines, periodicals - Distribution",
    "sg:phone":"+32 16 82 09 52",
    "sg:postcode":"3300",
    "sg:province":"Vlaams-Brabant",
    "wof:name":"Van A Tot Z Bvba",
    "wof:placetype":"venue"
},
  "geometry": {"coordinates":[4.9374399185,50.8094940186],"type":"Point"}
}