{
  "type": "Feature",
  "properties": {
    "addr:full":"Chauss\u00c9e De Louvain 275 Waterloo Brabant Wallon 1410",
    "addr:housenumber":"275",
    "addr:postcode":"1410",
    "addr:street":"Chausse\u0301E De Louvain",
    "iso:country":"BE",
    "sg:address":"Chauss\u00c9e De Louvain 275",
    "sg:city":"Waterloo",
    "sg:orig_category":"Woningbouw",
    "sg:phone":"+32 2 353 03 35",
    "sg:postcode":"1410",
    "sg:province":"Brabant Wallon",
    "wof:name":"Duro-home",
    "wof:placetype":"venue"
},
  "geometry": {"coordinates":[4.4257221222,50.7011642456],"type":"Point"}
}