{
  "type": "Feature",
  "properties": {
    "addr:full":"Zeypestraat 38 Sint-pieters-leeuw (vlezenbeek) Vlaams-Brabant 1602",
    "addr:housenumber":"38",
    "addr:postcode":"1602",
    "addr:street":"Zeypestraat",
    "iso:country":"BE",
    "sg:address":"Zeypestraat 38",
    "sg:city":"Sint-pieters-leeuw (vlezenbeek)",
    "sg:classifiers":[
        {
            "category":"Communications",
            "subcategory":"Film & Video Production",
            "type":"Services"
        }
    ],
    "sg:phone":"+32 2 532 22 35",
    "sg:postcode":"1602",
    "sg:province":"Vlaams-Brabant",
    "sg:tags":[
        "realisation",
        "-"
    ],
    "wof:name":"De Saegher R",
    "wof:placetype":"venue"
},
  "geometry": {"coordinates":[4.2390069962,50.8065948486],"type":"Point"}
}