{
  "type": "Feature",
  "properties": {
    "iso:country":"BE",
    "sg:address":"Boulevard Emile Bockstael 247",
    "sg:city":"Bruxelles",
    "sg:classifiers":[
        {
            "category":"Health Services",
            "subcategory":"Doctor",
            "type":"Services"
        }
    ],
    "sg:phone":"+32 2 426 11 83",
    "sg:postcode":"1020",
    "sg:province":"Bruxelles-Capitale",
    "sg:tags":[
        "orthopedist"
    ],
    "wof:name":"Balck H",
    "wof:placetype":"venue"
},
  "geometry": {"coordinates":[4.3480839729,50.8788604736],"type":"Point"}
}