{
  "type": "Feature",
  "properties": {
    "iso:country":"BE",
    "sg:address":"Rue Du Trois Juin 57",
    "sg:city":"Herstal",
    "sg:classifiers":[
        {
            "category":"Manufacturing",
            "subcategory":"Tools & Machinery",
            "type":"Manufacturing & Wholesale Goods"
        }
    ],
    "sg:phone":"+32 4 264 29 02",
    "sg:postcode":"4040",
    "sg:province":"Li\u00e8ge",
    "sg:tags":[
        "builder"
    ],
    "wof:name":"Bloom J",
    "wof:placetype":"venue"
},
  "geometry": {"coordinates":[5.630382061,50.6747627258],"type":"Point"}
}