{
  "type": "Feature",
  "properties": {
    "addr:full":"Oude Vichtestraat 21 Deerlijk West-Vlaanderen 8540",
    "addr:housenumber":"21",
    "addr:postcode":"8540",
    "addr:street":"Oude Vichtestraat",
    "iso:country":"BE",
    "sg:address":"Oude Vichtestraat 21",
    "sg:city":"Deerlijk",
    "sg:orig_category":"Installatie van houten of kunststof schrijnwerk",
    "sg:phone":"+32 56 77 51 58",
    "sg:postcode":"8540",
    "sg:province":"West-Vlaanderen",
    "wof:name":"Gerdy Biesbrouck",
    "wof:placetype":"venue"
},
  "geometry": {"coordinates":[3.382324934,50.8447952271],"type":"Point"}
}