{
  "type": "Feature",
  "properties": {
    "addr:full":"Rue Des P\u00eacheurs 2 Sprimont Li\u00e8ge 4140",
    "addr:housenumber":"2",
    "addr:postcode":"4140",
    "addr:street":"Rue Des Pe\u0302Cheurs",
    "iso:country":"BE",
    "sg:address":"Rue Des P\u00eacheurs 2",
    "sg:city":"Sprimont",
    "sg:classifiers":[
        {
            "category":"Professional",
            "subcategory":"Accounting & Tax Preparation",
            "type":"Services"
        }
    ],
    "sg:phone":"+32 4 369 14 39",
    "sg:postcode":"4140",
    "sg:province":"Li\u00e8ge",
    "sg:tags":[
        "bookkeeper"
    ],
    "wof:name":"Conrad H",
    "wof:placetype":"venue"
},
  "geometry": {"coordinates":[5.6597499847,50.5072059631],"type":"Point"}
}