{
  "type": "Feature",
  "properties": {
    "addr:full":"Alsembergsesteenweg 702 Brussel-ukkel Bruxelles-Capitale 1180",
    "addr:housenumber":"702",
    "addr:postcode":"1180",
    "addr:street":"Alsembergsesteenweg",
    "iso:country":"BE",
    "sg:address":"Alsembergsesteenweg 702",
    "sg:city":"Brussel-ukkel",
    "sg:classifiers":[
        {
            "category":"Shopping",
            "subcategory":"Computers & Home Electronics",
            "type":"Retail Goods"
        }
    ],
    "sg:phone":"+32 2 347 57 28",
    "sg:postcode":"1180",
    "sg:province":"Bruxelles-Capitale",
    "sg:tags":[
        "shop",
        "base",
        "telecommunicatieapparaten"
    ],
    "wof:name":"Base Uccle-ukkel",
    "wof:placetype":"venue"
},
  "geometry": {"coordinates":[4.3368878365,50.8023071289],"type":"Point"}
}