{
  "type": "Feature",
  "properties": {
    "iso:country":"BE",
    "sg:address":"Nijverheidsweg 20",
    "sg:city":"Merelbeke",
    "sg:classifiers":[
        {
            "category":"Manufacturing",
            "subcategory":"Metals",
            "type":"Manufacturing & Wholesale Goods"
        }
    ],
    "sg:phone":"+32 9 231 99 80",
    "sg:postcode":"9820",
    "sg:province":"Oost-Vlaanderen",
    "sg:tags":[
        "processing"
    ],
    "wof:name":"Almermetaal Nv",
    "wof:placetype":"venue"
},
  "geometry": {"coordinates":[3.7304809093,51.0020751953],"type":"Point"}
}