{
  "type": "Feature",
  "properties": {
    "addr:full":"Vismijnstraat 11 Brugge (zeebrugge - Lissewege) West-Vlaanderen 8380",
    "addr:housenumber":"11",
    "addr:postcode":"8380",
    "addr:street":"Vismijnstraat",
    "iso:country":"BE",
    "sg:address":"Vismijnstraat 11",
    "sg:city":"Brugge (zeebrugge - Lissewege)",
    "sg:classifiers":[
        {
            "category":"Landmark",
            "subcategory":"Tourist Attraction",
            "type":"Public Place"
        }
    ],
    "sg:phone":"+32 50 55 09 00",
    "sg:postcode":"8380",
    "sg:province":"West-Vlaanderen",
    "sg:tags":[
        "-",
        "tourism",
        "interest",
        "sight"
    ],
    "wof:name":"Rederij Euro-line Nv",
    "wof:placetype":"venue"
},
  "geometry": {"coordinates":[3.2288448811,51.2742958069],"type":"Point"}
}