{
  "type": "Feature",
  "properties": {
    "iso:country":"BE",
    "sg:address":"Rijksweg 768",
    "sg:city":"Dilsen-stokkem (rotem)",
    "sg:classifiers":[
        {
            "category":"Building & Trades",
            "subcategory":"Equipment Rental",
            "type":"Services"
        }
    ],
    "sg:phone":"+32 89 56 33 09",
    "sg:postcode":"3650",
    "sg:province":"Limburg",
    "sg:tags":[
        "sound",
        "-",
        "system"
    ],
    "wof:name":"Intersound",
    "wof:placetype":"venue"
},
  "geometry": {"coordinates":[5.7348308563,51.0439147949],"type":"Point"}
}