{
  "type": "Feature",
  "properties": {
    "iso:country":"BE",
    "sg:address":"Boulevard Z\u00e9nobe Gramme 16",
    "sg:city":"Herstal",
    "sg:orig_category":"Autombile concessionaires",
    "sg:phone":"+32 4 264 24 50",
    "sg:postcode":"4040",
    "sg:province":"Li\u00e8ge",
    "wof:name":"Gar Lana",
    "wof:placetype":"venue"
},
  "geometry": {"coordinates":[5.6346869469,50.6644592285],"type":"Point"}
}