{
  "type": "Feature",
  "properties": {
    "addr:full":"Noordstraat 4 Wevelgem (gullegem) West-Vlaanderen 8560",
    "addr:housenumber":"4",
    "addr:postcode":"8560",
    "addr:street":"Noordstraat",
    "iso:country":"BE",
    "sg:address":"Noordstraat 4",
    "sg:city":"Wevelgem (gullegem)",
    "sg:orig_category":"Non-Classified Establishments",
    "sg:phone":"+32 56 40 29 94",
    "sg:postcode":"8560",
    "sg:province":"West-Vlaanderen",
    "wof:name":"Textiel Chemicalien Kortrijk N Nv",
    "wof:placetype":"venue"
},
  "geometry": {"coordinates":[3.1799249649,50.808013916],"type":"Point"}
}