{
  "type": "Feature",
  "properties": {
    "iso:country":"BE",
    "sg:address":"Waterschransweg 8",
    "sg:city":"Lier",
    "sg:orig_category":"Agences de publicit\u00e9",
    "sg:phone":"+32 3 489 11 88",
    "sg:postcode":"2500",
    "sg:province":"Antwerpen",
    "wof:name":"Publivaria",
    "wof:placetype":"venue"
},
  "geometry": {"coordinates":[4.5481700897,51.1224136353],"type":"Point"}
}