{
  "type": "Feature",
  "properties": {
    "addr:full":"Koekoekstraat 106 Mol Antwerpen 2400",
    "addr:housenumber":"106",
    "addr:postcode":"2400",
    "addr:street":"Koekoekstraat",
    "iso:country":"BE",
    "sg:address":"Koekoekstraat 106",
    "sg:city":"Mol",
    "sg:orig_category":"Installation de menuiserie en bois and plastique",
    "sg:phone":"+32 14 31 53 32",
    "sg:postcode":"2400",
    "sg:province":"Antwerpen",
    "wof:name":"Marc Verwimp",
    "wof:placetype":"venue"
},
  "geometry": {"coordinates":[5.0510878563,51.1834373474],"type":"Point"}
}