{
  "type": "Feature",
  "properties": {
    "iso:country":"BE",
    "sg:address":"Dorpstraat 9",
    "sg:city":"Lierde",
    "sg:orig_category":"Installatie van houten of kunststof schrijnwerk",
    "sg:phone":"+32 55 42 85 08",
    "sg:postcode":"9570",
    "sg:province":"Oost-Vlaanderen",
    "wof:name":"Claes Gilbert",
    "wof:placetype":"venue"
},
  "geometry": {"coordinates":[3.8558080196,50.8197593689],"type":"Point"}
}