{
  "type": "Feature",
  "properties": {
    "addr:full":"Rue Du P\u00e9pin 48 Bruxelles Bruxelles-Capitale 1000",
    "addr:housenumber":"48",
    "addr:postcode":"1000",
    "addr:street":"Rue Du Pe\u0301Pin",
    "iso:country":"BE",
    "sg:address":"Rue Du P\u00e9pin 48",
    "sg:city":"Bruxelles",
    "sg:classifiers":[
        {
            "category":"Shopping",
            "subcategory":"Clothing, Apparel, & Fashions",
            "type":"Retail Goods"
        }
    ],
    "sg:phone":"+32 2 502 13 73",
    "sg:postcode":"1000",
    "sg:province":"Bruxelles-Capitale",
    "sg:tags":[
        "boutique"
    ],
    "wof:name":"Baines",
    "wof:placetype":"venue"
},
  "geometry": {"coordinates":[4.3604369164,50.8390312195],"type":"Point"}
}