{
  "type": "Feature",
  "properties": {
    "iso:country":"BE",
    "sg:address":"Geertruimoerstraat 8",
    "sg:city":"Tremelo",
    "sg:orig_category":"V\u00e9t\u00e9rinaires",
    "sg:phone":"+32 16 53 27 91",
    "sg:postcode":"3128",
    "sg:province":"Vlaams-Brabant",
    "wof:name":"Rudolf De Roover",
    "wof:placetype":"venue"
},
  "geometry": {"coordinates":[4.7408938408,51.0078430176],"type":"Point"}
}