{
  "type": "Feature",
  "properties": {
    "addr:full":"Ankerstraat 58 Sint-niklaas Oost-Vlaanderen 9100",
    "addr:housenumber":"58",
    "addr:postcode":"9100",
    "addr:street":"Ankerstraat",
    "iso:country":"BE",
    "sg:address":"Ankerstraat 58",
    "sg:city":"Sint-niklaas",
    "sg:classifiers":[
        {
            "category":"Cafe",
            "type":"Food & Drink"
        }
    ],
    "sg:phone":"+32 3 776 05 00",
    "sg:postcode":"9100",
    "sg:province":"Oost-Vlaanderen",
    "sg:tags":[
        "caf\u00e9s"
    ],
    "wof:name":"Jan Van Den Berghe",
    "wof:placetype":"venue"
},
  "geometry": {"coordinates":[4.146982193,51.1665000916],"type":"Point"}
}