{
  "type": "Feature",
  "properties": {
    "addr:full":"Kalvariestraat 5 Zele Oost-Vlaanderen 9240",
    "addr:housenumber":"5",
    "addr:postcode":"9240",
    "addr:street":"Kalvariestraat",
    "iso:country":"BE",
    "sg:address":"Kalvariestraat 5",
    "sg:city":"Zele",
    "sg:orig_category":"Software ontwikkeling and ontwerp",
    "sg:phone":"+32 477 38 82 76",
    "sg:postcode":"9240",
    "sg:province":"Oost-Vlaanderen",
    "wof:name":"Dvd-design",
    "wof:placetype":"venue"
},
  "geometry": {"coordinates":[4.0505270958,51.0548439026],"type":"Point"}
}