{
  "type": "Feature",
  "properties": {
    "iso:country":"BE",
    "sg:address":"Ave Gouv Bovesse 117/34",
    "sg:city":"Jambes",
    "sg:classifiers":[
        {
            "category":"Banks & Credit Unions",
            "subcategory":"Bank",
            "type":"Services"
        }
    ],
    "sg:phone":"+32 81 30 25 19",
    "sg:postcode":"5100",
    "sg:province":"Namur",
    "wof:name":"G\u00e9n\u00e9rale De Banque Sa",
    "wof:placetype":"venue"
},
  "geometry": {"coordinates":[4.8756117821,50.459728241],"type":"Point"}
}