{
  "type": "Feature",
  "properties": {
    "iso:country":"BE",
    "sg:address":"Rue De Mons 66",
    "sg:city":"Soignies",
    "sg:classifiers":[
        {
            "category":"Shopping",
            "subcategory":"Jewelry",
            "type":"Retail Goods"
        }
    ],
    "sg:phone":"+32 67 33 03 13",
    "sg:postcode":"7060",
    "sg:province":"Hainaut",
    "sg:tags":[
        "jeweller",
        "-"
    ],
    "wof:name":"Ramakers",
    "wof:placetype":"venue"
},
  "geometry": {"coordinates":[4.0718660355,50.5776557922],"type":"Point"}
}