{
  "type": "Feature",
  "properties": {
    "addr:full":"Rue Henri-vieuxtemps 76b15 Li\u00c8ge Li\u00e8ge 4000",
    "addr:housenumber":"76b15",
    "addr:postcode":"4000",
    "addr:street":"Rue Henri-Vieuxtemps",
    "iso:country":"BE",
    "sg:address":"Rue Henri-vieuxtemps 76b15",
    "sg:city":"Li\u00c8ge",
    "sg:orig_category":"M\u00e9decins and sp\u00e9cialistes",
    "sg:phone":"+32 4 224 12 37",
    "sg:postcode":"4000",
    "sg:province":"Li\u00e8ge",
    "wof:name":"V. Cannella",
    "wof:placetype":"venue"
},
  "geometry": {"coordinates":[5.5605559349,50.6474494934],"type":"Point"}
}