{
  "type": "Feature",
  "properties": {
    "addr:full":"Brigade Pironlaan 52b1 Sint-jans-molenbeek/molenbeek-saint-jean Bruxelles-Capitale 1080",
    "addr:housenumber":"52b1",
    "addr:postcode":"1080",
    "addr:street":"Brigade Pironlaan",
    "iso:country":"BE",
    "sg:address":"Brigade Pironlaan 52b1",
    "sg:city":"Sint-jans-molenbeek/molenbeek-saint-jean",
    "sg:orig_category":"Advocaten and juridische adviseurs",
    "sg:phone":"+32 2 396 06 00",
    "sg:postcode":"1080",
    "sg:province":"Bruxelles-Capitale",
    "wof:name":"Clarisse Sepulchre",
    "wof:placetype":"venue"
},
  "geometry": {"coordinates":[4.3164510727,50.8524589539],"type":"Point"}
}