{
  "type": "Feature",
  "properties": {
    "iso:country":"BE",
    "sg:address":"Kempestraat 108",
    "sg:city":"Diepenbeek",
    "sg:classifiers":[
        {
            "category":"Health Services",
            "subcategory":"Hospital",
            "type":"Services"
        }
    ],
    "sg:phone":"+32 11 32 31 67",
    "sg:postcode":"3590",
    "sg:province":"Limburg",
    "sg:tags":[
        "ambulance"
    ],
    "wof:name":"G. Martens",
    "wof:placetype":"venue"
},
  "geometry": {"coordinates":[5.4317889214,50.9256057739],"type":"Point"}
}