{
  "type": "Feature",
  "properties": {
    "iso:country":"BE",
    "sg:address":"Pelikaanstraat 26",
    "sg:city":"Oudenaarde",
    "sg:orig_category":"Bloemen and planten Boomkwekerijen",
    "sg:phone":"+32 55 30 24 80",
    "sg:postcode":"9700",
    "sg:province":"Oost-Vlaanderen",
    "wof:name":"De Bock",
    "wof:placetype":"venue"
},
  "geometry": {"coordinates":[3.634732008,50.8678398132],"type":"Point"}
}