{
  "type": "Feature",
  "properties": {
    "iso:country":"BE",
    "sg:address":"Weverstraat 81",
    "sg:city":"Zemst",
    "sg:orig_category":"Rundveehouders",
    "sg:phone":"+32 15 61 39 16",
    "sg:postcode":"1982",
    "sg:province":"Vlaams-Brabant",
    "wof:name":"Emma Ardies",
    "wof:placetype":"venue"
},
  "geometry": {"coordinates":[4.465569973,50.9712409973],"type":"Point"}
}