{
  "type": "Feature",
  "properties": {
    "addr:full":"Rue Leon Delacroix 30 Bruxelles Bruxelles-Capitale 1070",
    "addr:housenumber":"30",
    "addr:postcode":"1070",
    "addr:street":"Rue Leon Delacroix",
    "iso:country":"BE",
    "sg:address":"Rue Leon Delacroix 30",
    "sg:city":"Bruxelles",
    "sg:classifiers":[
        {
            "category":"Food & Beverages",
            "subcategory":"Meat & Fish",
            "type":"Retail Goods"
        }
    ],
    "sg:phone":"+32 2 413 10 10",
    "sg:postcode":"1070",
    "sg:province":"Bruxelles-Capitale",
    "sg:tags":[
        "sausage"
    ],
    "wof:name":"Ets A. Dewitte & Fils S.a.",
    "wof:placetype":"venue"
},
  "geometry": {"coordinates":[4.3257489204,50.8448944092],"type":"Point"}
}