{
  "type": "Feature",
  "properties": {
    "addr:full":"Avenue De Woluwe Saint-lambert 45 Bruxelles (woluwe-saint-lambert) Bruxelles-Capitale 1200",
    "addr:housenumber":"45",
    "addr:postcode":"1200",
    "addr:street":"Avenue De Woluwe Saint-Lambert",
    "iso:country":"BE",
    "sg:address":"Avenue De Woluwe Saint-lambert 45",
    "sg:city":"Bruxelles (woluwe-saint-lambert)",
    "sg:orig_category":"Non-Classified Establishments",
    "sg:phone":"+32 2 734 35 32",
    "sg:postcode":"1200",
    "sg:province":"Bruxelles-Capitale",
    "wof:name":"Quatermass Sprl",
    "wof:placetype":"venue"
},
  "geometry": {"coordinates":[4.4098110199,50.839641571],"type":"Point"}
}