{
  "type": "Feature",
  "properties": {
    "addr:full":"Louisestraat 39 Oostende West-Vlaanderen 8400",
    "addr:housenumber":"39",
    "addr:postcode":"8400",
    "addr:street":"Louisestraat",
    "iso:country":"BE",
    "sg:address":"Louisestraat 39",
    "sg:city":"Oostende",
    "sg:orig_category":"Vakantiehuizen",
    "sg:phone":"+32 59 50 27 93",
    "sg:postcode":"8400",
    "sg:province":"West-Vlaanderen",
    "wof:name":"Cobbaert Mon S\u00c9jour",
    "wof:placetype":"venue"
},
  "geometry": {"coordinates":[2.916009903,51.2343902588],"type":"Point"}
}