{
  "type": "Feature",
  "properties": {
    "addr:full":"Terliststraat 26 Antwerpen Antwerpen 2018",
    "addr:housenumber":"26",
    "addr:postcode":"2018",
    "addr:street":"Terliststraat",
    "iso:country":"BE",
    "sg:address":"Terliststraat 26",
    "sg:city":"Antwerpen",
    "sg:classifiers":[
        {
            "category":"Government",
            "subcategory":"Post Office",
            "type":"Public Place"
        }
    ],
    "sg:phone":"+32 3 226 45 78",
    "sg:postcode":"2018",
    "sg:province":"Antwerpen",
    "sg:tags":[
        "picture",
        "restoring"
    ],
    "wof:name":"De Ridder",
    "wof:placetype":"venue"
},
  "geometry": {"coordinates":[4.4190387726,51.2122344971],"type":"Point"}
}