{
  "type": "Feature",
  "properties": {
    "addr:full":"Rue De Marche 69 Bastogne Luxembourg 6600",
    "addr:housenumber":"69",
    "addr:postcode":"6600",
    "addr:street":"Rue De Marche",
    "iso:country":"BE",
    "sg:address":"Rue De Marche 69",
    "sg:city":"Bastogne",
    "sg:classifiers":[
        {
            "category":"Government",
            "subcategory":"Police Station",
            "type":"Public Place"
        }
    ],
    "sg:phone":"+32 61 24 12 11",
    "sg:postcode":"6600",
    "sg:province":"Luxembourg",
    "sg:tags":[
        "gendarmerie"
    ],
    "wof:name":"Police F\u00c9d\u00c9rale/federale Politie",
    "wof:placetype":"venue"
},
  "geometry": {"coordinates":[5.7093968391,50.0016098022],"type":"Point"}
}