{
  "type": "Feature",
  "properties": {
    "iso:country":"BE",
    "sg:address":"Rijksweg 245a",
    "sg:city":"Maasmechelen",
    "sg:orig_category":"Editeurs de revues and p\u00e9riodiques. Editeurs de journaux",
    "sg:phone":"+32 89 76 71 56",
    "sg:postcode":"3630",
    "sg:province":"Limburg",
    "wof:name":"Edith Krantenshop",
    "wof:placetype":"venue"
},
  "geometry": {"coordinates":[5.698679924,50.9718818665],"type":"Point"}
}