{
  "type": "Feature",
  "properties": {
    "addr:full":"Kapelaanstraat 30 Maldegem Oost-Vlaanderen 9990",
    "addr:housenumber":"30",
    "addr:postcode":"9990",
    "addr:street":"Kapelaanstraat",
    "iso:country":"BE",
    "sg:address":"Kapelaanstraat 30",
    "sg:city":"Maldegem",
    "sg:classifiers":[
        {
            "category":"Health Services",
            "subcategory":"Health Practitioner",
            "type":"Services"
        }
    ],
    "sg:phone":"+32 50 71 87 23",
    "sg:postcode":"9990",
    "sg:province":"Oost-Vlaanderen",
    "sg:tags":[
        "physiotherapist"
    ],
    "wof:name":"Van Rie K",
    "wof:placetype":"venue"
},
  "geometry": {"coordinates":[3.4531779289,51.2110023499],"type":"Point"}
}