{
  "type": "Feature",
  "properties": {
    "addr:full":"Stationsstraat 100 Merchtem Vlaams-Brabant 1785",
    "addr:housenumber":"100",
    "addr:postcode":"1785",
    "addr:street":"Stationsstraat",
    "iso:country":"BE",
    "sg:address":"Stationsstraat 100",
    "sg:city":"Merchtem",
    "sg:classifiers":[
        {
            "category":"Health Services",
            "subcategory":"Health Practitioner",
            "type":"Services"
        }
    ],
    "sg:phone":"+32 52 37 12 90",
    "sg:postcode":"1785",
    "sg:province":"Vlaams-Brabant",
    "sg:tags":[
        "physiotherapist"
    ],
    "wof:name":"Van Den Broeck M",
    "wof:placetype":"venue"
},
  "geometry": {"coordinates":[4.2260131836,50.9550628662],"type":"Point"}
}