{
  "type": "Feature",
  "properties": {
    "iso:country":"BE",
    "sg:address":"Avenue Rogier 131",
    "sg:city":"Brussel/bruxelles",
    "sg:orig_category":"Bloemen and planten",
    "sg:phone":"+32 2 242 77 75",
    "sg:postcode":"1030",
    "sg:province":"Bruxelles-Capitale",
    "wof:name":"Floral",
    "wof:placetype":"venue"
},
  "geometry": {"coordinates":[4.3778328896,50.8592185974],"type":"Point"}
}