{
  "type": "Feature",
  "properties": {
    "addr:full":"Rue De Namur 48 Wavre Brabant Wallon 1300",
    "addr:housenumber":"48;1300",
    "addr:street":"Rue De Namur",
    "iso:country":"BE",
    "sg:address":"Rue De Namur 48",
    "sg:city":"Wavre",
    "sg:classifiers":[
        {
            "category":"Personal",
            "subcategory":"Beauty Salon",
            "type":"Services"
        }
    ],
    "sg:phone":"+32 10 22 36 42",
    "sg:postcode":"1300",
    "sg:province":"Brabant Wallon",
    "sg:tags":[
        "lady",
        "-",
        "hairdressing"
    ],
    "wof:name":"Solange",
    "wof:placetype":"venue"
},
  "geometry": {"coordinates":[4.6126050949,50.7123298645],"type":"Point"}
}