{
  "type": "Feature",
  "properties": {
    "addr:full":"Clos Du Grand Sart 12 Dalhem Li\u00e8ge 4607",
    "addr:housenumber":"12",
    "addr:postcode":"4607",
    "addr:street":"Clos Du Grand Sart",
    "iso:country":"BE",
    "sg:address":"Clos Du Grand Sart 12",
    "sg:city":"Dalhem",
    "sg:classifiers":[
        {
            "category":"Personal",
            "subcategory":"Beauty Salon",
            "type":"Services"
        }
    ],
    "sg:phone":"+32 4 376 69 23",
    "sg:postcode":"4607",
    "sg:province":"Li\u00e8ge",
    "sg:tags":[
        "de",
        "coiffure"
    ],
    "wof:name":"Coiffure Beaut\u00c9",
    "wof:placetype":"venue"
},
  "geometry": {"coordinates":[5.7561850548,50.7103652954],"type":"Point"}
}