{
  "type": "Feature",
  "properties": {
    "addr:full":"Langestraat 175 Brugge West-Vlaanderen 8000",
    "addr:housenumber":"175",
    "addr:postcode":"8000",
    "addr:street":"Langestraat",
    "iso:country":"BE",
    "sg:address":"Langestraat 175",
    "sg:city":"Brugge",
    "sg:classifiers":[
        {
            "category":"Social Services",
            "type":"Services"
        }
    ],
    "sg:phone":"+32 50 33 27 57",
    "sg:postcode":"8000",
    "sg:province":"West-Vlaanderen",
    "wof:name":"Nat Inst Oorlogsinvaliden,oud-strijders En Oorlogsslachtoffers",
    "wof:placetype":"venue"
},
  "geometry": {"coordinates":[3.2391769886,51.2126350403],"type":"Point"}
}