{
  "type": "Feature",
  "properties": {
    "addr:full":"Oude Vaartstraat 35ba Ranst Antwerpen 2520",
    "addr:housenumber":"35ba",
    "addr:postcode":"2520",
    "addr:street":"Oude Vaartstraat",
    "iso:country":"BE",
    "sg:address":"Oude Vaartstraat 35ba",
    "sg:city":"Ranst",
    "sg:orig_category":"Installatie van houten of kunststof schrijnwerk Woningbouw",
    "sg:phone":"+32 3 475 10 58",
    "sg:postcode":"2520",
    "sg:province":"Antwerpen",
    "wof:name":"Verboven",
    "wof:placetype":"venue"
},
  "geometry": {"coordinates":[4.5787348747,51.2024688721],"type":"Point"}
}