{
  "type": "Feature",
  "properties": {
    "addr:full":"Rue Du March\u00e9 Aux Fromages 12 Bruxelles Bruxelles-Capitale 1000",
    "addr:housenumber":"12",
    "addr:postcode":"1000",
    "addr:street":"Rue Du Marche\u0301 Aux Fromages",
    "iso:country":"BE",
    "sg:address":"Rue Du March\u00e9 Aux Fromages 12",
    "sg:city":"Bruxelles",
    "sg:classifiers":[
        {
            "category":"Cafe",
            "type":"Food & Drink"
        }
    ],
    "sg:phone":"+32 2 511 56 21",
    "sg:postcode":"1000",
    "sg:province":"Bruxelles-Capitale",
    "sg:tags":[
        "snack-bars"
    ],
    "wof:name":"Ath\u00e8nes Snack",
    "wof:placetype":"venue"
},
  "geometry": {"coordinates":[4.3530979156,50.8457756042],"type":"Point"}
}