{
  "type": "Feature",
  "properties": {
    "addr:full":"Hoenderstraat 24 Wetteren Oost-Vlaanderen 9230",
    "addr:housenumber":"24",
    "addr:postcode":"9230",
    "addr:street":"Hoenderstraat",
    "iso:country":"BE",
    "sg:address":"Hoenderstraat 24",
    "sg:city":"Wetteren",
    "sg:classifiers":[
        {
            "category":"Taxi",
            "type":"Transportation"
        }
    ],
    "sg:phone":"+32 9 365 03 42",
    "sg:postcode":"9230",
    "sg:province":"Oost-Vlaanderen",
    "sg:tags":[
        "taxicab"
    ],
    "wof:name":"G'ethics",
    "wof:placetype":"venue"
},
  "geometry": {"coordinates":[3.8821570873,51.0041313171],"type":"Point"}
}