{
  "type": "Feature",
  "properties": {
    "iso:country":"BE",
    "sg:address":"Neerveld 15",
    "sg:city":"Kontich",
    "sg:orig_category":"Non-Classified Establishments",
    "sg:phone":"+32 3 457 79 85",
    "sg:postcode":"2550",
    "sg:province":"Antwerpen",
    "wof:name":"Selfmatic",
    "wof:placetype":"venue"
},
  "geometry": {"coordinates":[4.4517998695,51.1213607788],"type":"Point"}
}