{
  "type": "Feature",
  "properties": {
    "iso:country":"BE",
    "sg:address":"Neerlintersesteenweg 213",
    "sg:city":"Tienen",
    "sg:orig_category":"Producteurs de fruits",
    "sg:phone":"+32 11 78 42 65",
    "sg:postcode":"3300",
    "sg:province":"Vlaams-Brabant",
    "wof:name":"Jan Jorissen",
    "wof:placetype":"venue"
},
  "geometry": {"coordinates":[5.014070034,50.8367538452],"type":"Point"}
}