{
  "type": "Feature",
  "properties": {
    "iso:country":"BE",
    "sg:address":"Nieuwstraat 11",
    "sg:city":"Tienen",
    "sg:classifiers":[
        {
            "category":"Banks & Credit Unions",
            "subcategory":"Investment Brokerage",
            "type":"Services"
        }
    ],
    "sg:phone":"+32 16 82 29 14",
    "sg:postcode":"3300",
    "sg:province":"Vlaams-Brabant",
    "sg:tags":[
        "jean",
        "casual",
        "wear"
    ],
    "wof:name":"Broekenhuis Tienen Nv",
    "wof:placetype":"venue"
},
  "geometry": {"coordinates":[4.9386920929,50.8067741394],"type":"Point"}
}