{
  "type": "Feature",
  "properties": {
    "addr:full":"Turnhoutsebaan 259 Wijnegem Antwerpen 2110",
    "addr:housenumber":"259",
    "addr:postcode":"2110",
    "addr:street":"Turnhoutsebaan",
    "iso:country":"BE",
    "sg:address":"Turnhoutsebaan 259",
    "sg:city":"Wijnegem",
    "sg:orig_category":"Art and fournitures artistiques",
    "sg:phone":"+32 3 354 07 12",
    "sg:postcode":"2110",
    "sg:province":"Antwerpen",
    "wof:name":"Fa. Crimo",
    "wof:placetype":"venue"
},
  "geometry": {"coordinates":[4.5170311928,51.2265663147],"type":"Point"}
}