{
  "type": "Feature",
  "properties": {
    "iso:country":"BE",
    "sg:address":"Rue Ambiorix 78",
    "sg:city":"Li\u00e8ge 1",
    "sg:classifiers":[
        {
            "category":"Real Estate",
            "subcategory":"Architect",
            "type":"Services"
        }
    ],
    "sg:phone":"+32 4 252 07 77",
    "sg:postcode":"4000",
    "sg:province":"Li\u00e8ge",
    "wof:name":"Vandendriessche M",
    "wof:placetype":"venue"
},
  "geometry": {"coordinates":[5.5602030754,50.6297035217],"type":"Point"}
}