{
  "type": "Feature",
  "properties": {
    "addr:full":"Marcel Habetslaan 18bb Genk Limburg 3600",
    "addr:housenumber":"18bb",
    "addr:postcode":"3600",
    "addr:street":"Marcel Habetslaan",
    "iso:country":"BE",
    "sg:address":"Marcel Habetslaan 18bb",
    "sg:city":"Genk",
    "sg:orig_category":"Agences d'exp\u00e9dition",
    "sg:phone":"+32 89 38 00 26",
    "sg:postcode":"3600",
    "sg:province":"Limburg",
    "wof:name":"Malmendier Belgium",
    "wof:placetype":"venue"
},
  "geometry": {"coordinates":[5.5052580833,51.0101394653],"type":"Point"}
}