{
  "type": "Feature",
  "properties": {
    "addr:full":"Rue Albert Ier 73 Charleroi Hainaut 6043",
    "addr:housenumber":"73",
    "addr:postcode":"6043",
    "addr:street":"Rue Albert Ier;Hainaut",
    "iso:country":"BE",
    "sg:address":"Rue Albert Ier 73",
    "sg:city":"Charleroi",
    "sg:orig_category":"Advocaten and juridische adviseurs",
    "sg:phone":"+32 71 34 48 95",
    "sg:postcode":"6043",
    "sg:province":"Hainaut",
    "wof:name":"J. F. Dizier",
    "wof:placetype":"venue"
},
  "geometry": {"coordinates":[4.4839549065,50.4479637146],"type":"Point"}
}