{
  "type": "Feature",
  "properties": {
    "addr:full":"Acacialaan 11 Zaventem Vlaams-Brabant 1930",
    "addr:housenumber":"11",
    "addr:postcode":"1930",
    "addr:street":"Acacialaan",
    "iso:country":"BE",
    "sg:address":"Acacialaan 11",
    "sg:city":"Zaventem",
    "sg:classifiers":[
        {
            "category":"Shopping",
            "subcategory":"Gifts & Souvenirs",
            "type":"Retail Goods"
        }
    ],
    "sg:phone":"+32 2 245 21 61",
    "sg:postcode":"1930",
    "sg:province":"Vlaams-Brabant",
    "sg:tags":[
        "calendar"
    ],
    "wof:name":"Creart & Co Sa-nv",
    "wof:placetype":"venue"
},
  "geometry": {"coordinates":[4.447496891,50.8614387512],"type":"Point"}
}