{
  "type": "Feature",
  "properties": {
    "addr:full":"Fr\u00e8re-orbanstraat 53 Oostende West-Vlaanderen 8400",
    "addr:housenumber":"53",
    "addr:postcode":"8400",
    "addr:street":"Fre\u0300Re-Orbanstraat",
    "iso:country":"BE",
    "sg:address":"Fr\u00e8re-orbanstraat 53",
    "sg:city":"Oostende",
    "sg:classifiers":[
        {
            "category":"Banks & Credit Unions",
            "subcategory":"Financial Services",
            "type":"Services"
        }
    ],
    "sg:phone":"+32 59 51 36 57",
    "sg:postcode":"8400",
    "sg:province":"West-Vlaanderen",
    "sg:tags":[
        "debt",
        "recovery"
    ],
    "wof:name":"Van Litsenburgh J",
    "wof:placetype":"venue"
},
  "geometry": {"coordinates":[2.9105360508,51.2203178406],"type":"Point"}
}