{
  "type": "Feature",
  "properties": {
    "iso:country":"BE",
    "sg:address":"Gotestraat 1",
    "sg:city":"Gooik",
    "sg:classifiers":[
        {
            "category":"Professional",
            "subcategory":"Computer Services",
            "type":"Services"
        }
    ],
    "sg:phone":"+32 54 34 44 29",
    "sg:postcode":"1755",
    "sg:province":"Vlaams-Brabant",
    "sg:tags":[
        "-",
        "processing",
        "data"
    ],
    "wof:name":"Vdg-electro",
    "wof:placetype":"venue"
},
  "geometry": {"coordinates":[4.0704379082,50.8005447388],"type":"Point"}
}