{
  "type": "Feature",
  "properties": {
    "addr:full":"Rue Emile Cuvelier 29 Namur Namur 5000",
    "addr:housenumber":"29",
    "addr:postcode":"5000",
    "addr:street":"Rue Emile Cuvelier",
    "iso:country":"BE",
    "sg:address":"Rue Emile Cuvelier 29",
    "sg:city":"Namur",
    "sg:classifiers":[
        {
            "category":"Professional",
            "subcategory":"Printing & Photocopies",
            "type":"Services"
        }
    ],
    "sg:phone":"+32 81 22 77 16",
    "sg:postcode":"5000",
    "sg:province":"Namur",
    "sg:tags":[
        "occasional",
        "-"
    ],
    "wof:name":"Imprimerie Photoplan",
    "wof:placetype":"venue"
},
  "geometry": {"coordinates":[4.8667750359,50.4643058777],"type":"Point"}
}