{
  "type": "Feature",
  "properties": {
    "addr:full":"Aalstersestraat 77 Wieze Oost-Vlaanderen 9280",
    "addr:housenumber":"77",
    "addr:postcode":"9280",
    "addr:street":"Aalstersestraat;Oost-Vlaanderen",
    "iso:country":"BE",
    "sg:address":"Aalstersestraat 77",
    "sg:city":"Wieze",
    "sg:classifiers":[
        {
            "category":"Professional",
            "subcategory":"Advertising",
            "type":"Services"
        }
    ],
    "sg:phone":"+32 53 21 50 93",
    "sg:postcode":"9280",
    "sg:province":"Oost-Vlaanderen",
    "sg:tags":[
        "selling",
        "idea"
    ],
    "wof:name":"Publi Wieze B.v.b.a.",
    "wof:placetype":"venue"
},
  "geometry": {"coordinates":[4.0951981544,50.9817390442],"type":"Point"}
}