{
  "type": "Feature",
  "properties": {
    "addr:full":"Rue Jonet 138 Charleroi Hainaut 6000",
    "addr:housenumber":"138",
    "addr:postcode":"6000",
    "addr:street":"Rue Jonet;Hainaut",
    "iso:country":"BE",
    "sg:address":"Rue Jonet 138",
    "sg:city":"Charleroi",
    "sg:orig_category":"Traitements param\u00e9dicaux",
    "sg:phone":"+32 71 34 47 08",
    "sg:postcode":"6000",
    "sg:province":"Hainaut",
    "wof:name":"S. Berard",
    "wof:placetype":"venue"
},
  "geometry": {"coordinates":[4.4584569931,50.4251556396],"type":"Point"}
}