{
  "type": "Feature",
  "properties": {
    "iso:country":"BE",
    "sg:address":"Rue Colo-hughes 67",
    "sg:city":"Braine-l\u00b4alleud",
    "sg:orig_category":"Installatie van houten of kunststof schrijnwerk Installatie van metalen schrijnwerk",
    "sg:phone":"+32 2 387 28 29",
    "sg:postcode":"1420",
    "sg:province":"Brabant Wallon",
    "wof:name":"All Matic Doors",
    "wof:placetype":"venue"
},
  "geometry": {"coordinates":[4.3740029335,50.6817855835],"type":"Point"}
}