{
  "type": "Feature",
  "properties": {
    "iso:country":"BE",
    "sg:address":"Rue Des Wallons 29-405",
    "sg:city":"Ottignies-louvain-la-neuve (louvain-la-neuve)",
    "sg:classifiers":[
        {
            "category":"Transit Center",
            "subcategory":"Freight",
            "type":"Transportation"
        }
    ],
    "sg:phone":"+32 10 41 46 52",
    "sg:postcode":"1348",
    "sg:province":"Brabant Wallon",
    "sg:tags":[
        "import",
        "export",
        "-"
    ],
    "wof:name":"Veka Trading",
    "wof:placetype":"venue"
},
  "geometry": {"coordinates":[4.6167078018,50.6689033508],"type":"Point"}
}