{
  "type": "Feature",
  "properties": {
    "addr:full":"Rue Emile Montignies 3 Tournai Hainaut 7522",
    "addr:housenumber":"3",
    "addr:postcode":"7522",
    "addr:street":"Rue Emile Montignies",
    "iso:country":"BE",
    "sg:address":"Rue Emile Montignies 3",
    "sg:city":"Tournai",
    "sg:orig_category":"Rundveehouders",
    "sg:phone":"+32 69 35 26 42",
    "sg:postcode":"7522",
    "sg:province":"Hainaut",
    "wof:name":"Jean Bayart",
    "wof:placetype":"venue"
},
  "geometry": {"coordinates":[3.2876479626,50.6276130676],"type":"Point"}
}