{
  "type": "Feature",
  "properties": {
    "addr:full":"Hoveniersstraat 11b23 Antwerpen Antwerpen 2018",
    "addr:housenumber":"11b23",
    "addr:postcode":"2018",
    "addr:street":"Hoveniersstraat",
    "iso:country":"BE",
    "sg:address":"Hoveniersstraat 11b23",
    "sg:city":"Antwerpen",
    "sg:orig_category":"Diverse intermediaire producten Gh",
    "sg:phone":"+32 3 225 24 69",
    "sg:postcode":"2018",
    "sg:province":"Antwerpen",
    "wof:name":"Fa. Polymex",
    "wof:placetype":"venue"
},
  "geometry": {"coordinates":[4.4189128876,51.2155609131],"type":"Point"}
}