{
  "type": "Feature",
  "properties": {
    "addr:full":"Opperstebosstraat 51 Gooik Vlaams-Brabant 1755",
    "addr:housenumber":"51",
    "addr:postcode":"1755",
    "addr:street":"Opperstebosstraat",
    "iso:country":"BE",
    "sg:address":"Opperstebosstraat 51",
    "sg:city":"Gooik",
    "sg:orig_category":"Eleveurs de bovins",
    "sg:phone":"+32 54 56 67 43",
    "sg:postcode":"1755",
    "sg:province":"Vlaams-Brabant",
    "wof:name":"Herman Abbeloos",
    "wof:placetype":"venue"
},
  "geometry": {"coordinates":[4.0469098091,50.7817687988],"type":"Point"}
}