{
  "type": "Feature",
  "properties": {
    "iso:country":"BE",
    "sg:address":"Jasmijnlaan 6",
    "sg:city":"Retie",
    "sg:classifiers":[
        {
            "category":"Real Estate",
            "subcategory":"Architect",
            "type":"Services"
        }
    ],
    "sg:phone":"+32 14 37 82 86",
    "sg:postcode":"2470",
    "sg:province":"Antwerpen",
    "wof:name":"Loots H",
    "wof:placetype":"venue"
},
  "geometry": {"coordinates":[5.1432552338,51.2758140564],"type":"Point"}
}