{
  "type": "Feature",
  "properties": {
    "iso:country":"BE",
    "sg:address":"Lennikse Baan 806",
    "sg:city":"Anderlecht",
    "sg:orig_category":"Brood, gebak and snoepgoed",
    "sg:phone":"+32 2 522 41 27",
    "sg:postcode":"1070",
    "sg:province":"Bruxelles-Capitale",
    "wof:name":"Le Matin Fran\u00c7ais",
    "wof:placetype":"venue"
},
  "geometry": {"coordinates":[4.2656698227,50.81432724],"type":"Point"}
}