{
  "type": "Feature",
  "properties": {
    "iso:country":"BE",
    "sg:address":"Boterlaarbaan 18",
    "sg:city":"Schilde",
    "sg:orig_category":"Epiceries",
    "sg:phone":"+32 3 383 01 50",
    "sg:postcode":"2970",
    "sg:province":"Antwerpen",
    "wof:name":"K.m.k.",
    "wof:placetype":"venue"
},
  "geometry": {"coordinates":[4.5619120598,51.2476501465],"type":"Point"}
}