{
  "type": "Feature",
  "properties": {
    "addr:full":"Rue De Fenal 2ba Mettet Namur 5641",
    "addr:housenumber":"2ba",
    "addr:postcode":"5641",
    "addr:street":"Rue De Fenal",
    "iso:country":"BE",
    "sg:address":"Rue De Fenal 2ba",
    "sg:city":"Mettet",
    "sg:orig_category":"Installatie van houten of kunststof schrijnwerk",
    "sg:phone":"+32 71 72 63 86",
    "sg:postcode":"5641",
    "sg:province":"Namur",
    "wof:name":"Walbrecq Et Cie",
    "wof:placetype":"venue"
},
  "geometry": {"coordinates":[4.7038769722,50.3088493347],"type":"Point"}
}