{
  "type": "Feature",
  "properties": {
    "addr:full":"Wiesenbachstrasse 61 Sankt Vith/saint-vith Li\u00e8ge 4780",
    "addr:housenumber":"61",
    "addr:postcode":"4780",
    "addr:street":"Wiesenbachstrasse",
    "iso:country":"BE",
    "sg:address":"Wiesenbachstrasse 61",
    "sg:city":"Sankt Vith/saint-vith",
    "sg:orig_category":"Drukkerijen and copyshops",
    "sg:phone":"+32 80 22 78 02",
    "sg:postcode":"4780",
    "sg:province":"Li\u00e8ge",
    "wof:name":"Bernard Henkes",
    "wof:placetype":"venue"
},
  "geometry": {"coordinates":[6.0429549217,50.3349761963],"type":"Point"}
}