{
  "type": "Feature",
  "properties": {
    "iso:country":"BE",
    "sg:address":"Clos Stijn Streuvels 7",
    "sg:city":"Wezembeek-oppem",
    "sg:classifiers":[
        {
            "category":"Health Services",
            "subcategory":"Health Practitioner",
            "type":"Services"
        }
    ],
    "sg:phone":"+32 2 731 57 95",
    "sg:postcode":"1970",
    "sg:province":"Vlaams-Brabant",
    "sg:tags":[
        "physiotherapist"
    ],
    "wof:name":"Spegelaere Georges",
    "wof:placetype":"venue"
},
  "geometry": {"coordinates":[4.4962000847,50.8379745483],"type":"Point"}
}