{
  "type": "Feature",
  "properties": {
    "addr:full":"Turnhoutsebaan 5b24 Wijnegem Antwerpen 2110",
    "addr:housenumber":"5b24",
    "addr:postcode":"2110",
    "addr:street":"Turnhoutsebaan",
    "iso:country":"BE",
    "sg:address":"Turnhoutsebaan 5b24",
    "sg:city":"Wijnegem",
    "sg:orig_category":"V\u00eatements pour Hommes. V\u00eatements pour Dames",
    "sg:phone":"+32 3 353 16 37",
    "sg:postcode":"2110",
    "sg:province":"Antwerpen",
    "wof:name":"Naf-naf",
    "wof:placetype":"venue"
},
  "geometry": {"coordinates":[4.5043401718,51.2240219116],"type":"Point"}
}