{
  "type": "Feature",
  "properties": {
    "addr:full":"Nerviersstraat 25 Antwerpen Antwerpen 2018",
    "addr:housenumber":"25",
    "addr:postcode":"2018",
    "addr:street":"Nerviersstraat",
    "iso:country":"BE",
    "sg:address":"Nerviersstraat 25",
    "sg:city":"Antwerpen",
    "sg:orig_category":"Juwelen and edelstenen Fab",
    "sg:phone":"+32 3 281 12 55",
    "sg:postcode":"2018",
    "sg:province":"Antwerpen",
    "wof:name":"Fa. Ollech Bennaro",
    "wof:placetype":"venue"
},
  "geometry": {"coordinates":[4.4215831757,51.2059326172],"type":"Point"}
}