{
  "type": "Feature",
  "properties": {
    "addr:full":"Chauss\u00c9e De Bruxelles 18 Tournai Hainaut 7500",
    "addr:housenumber":"18",
    "addr:postcode":"7500",
    "addr:street":"Chausse\u0301E De Bruxelles",
    "iso:country":"BE",
    "sg:address":"Chauss\u00c9e De Bruxelles 18",
    "sg:city":"Tournai",
    "sg:orig_category":"Mat\u00e9riel m\u00e9dical and orthop\u00e9dique and proth\u00e8ses Fab",
    "sg:phone":"+32 69 23 28 84",
    "sg:postcode":"7500",
    "sg:province":"Hainaut",
    "wof:name":"Mario Hernandez",
    "wof:placetype":"venue"
},
  "geometry": {"coordinates":[3.4059660435,50.6054420471],"type":"Point"}
}