{
  "type": "Feature",
  "properties": {
    "addr:full":"Chauss\u00c9e De Renaix 155ba Lessines Hainaut 7860",
    "addr:postcode":"7860",
    "addr:street":"Chausse\u0301E De Renaix 155Ba;Hainaut",
    "iso:country":"BE",
    "sg:address":"Chauss\u00c9e De Renaix 155ba",
    "sg:city":"Lessines",
    "sg:classifiers":[
        {
            "category":"Insurance",
            "subcategory":"Life Insurance",
            "type":"Services"
        }
    ],
    "sg:phone":"+32 68 33 92 00",
    "sg:postcode":"7860",
    "sg:province":"Hainaut",
    "sg:tags":[
        "assurance"
    ],
    "wof:name":"Demeuldre Luc & Cie",
    "wof:placetype":"venue"
},
  "geometry": {"coordinates":[3.8125989437,50.7143363953],"type":"Point"}
}