{
  "type": "Feature",
  "properties": {
    "iso:country":"BE",
    "sg:address":"Chauss\u00e9e De Wavre 86",
    "sg:city":"H\u00e9ron",
    "sg:classifiers":[
        {
            "category":"Retail",
            "subcategory":"Auto Repair",
            "type":"Services"
        }
    ],
    "sg:phone":"+32 85 71 15 70",
    "sg:postcode":"4217",
    "sg:province":"Li\u00e8ge",
    "sg:tags":[
        "garage"
    ],
    "wof:name":"Hance Garage-carrosserie Sprl",
    "wof:placetype":"venue"
},
  "geometry": {"coordinates":[5.0955271721,50.5485801697],"type":"Point"}
}