{
  "type": "Feature",
  "properties": {
    "iso:country":"BE",
    "sg:address":"Generaal Tombeurstraat 71",
    "sg:city":"Etterbeek",
    "sg:orig_category":"Boekenuitgeverijen Film-, tv- and videoproductie Geluidsopnames",
    "sg:phone":"+32 2 735 20 26",
    "sg:postcode":"1040",
    "sg:province":"Bruxelles-Capitale",
    "wof:name":"Four Tunes",
    "wof:placetype":"venue"
},
  "geometry": {"coordinates":[4.3954691887,50.8348121643],"type":"Point"}
}