{
  "type": "Feature",
  "properties": {
    "iso:country":"BE",
    "sg:address":"Vinkstraat 6",
    "sg:city":"Oostrozebeke",
    "sg:orig_category":"Herstellingen and onderhoud van auto's",
    "sg:phone":"+32 56 66 99 58",
    "sg:postcode":"8780",
    "sg:province":"West-Vlaanderen",
    "wof:name":"Stefaan De Rijcke",
    "wof:placetype":"venue"
},
  "geometry": {"coordinates":[3.3249979019,50.9283218384],"type":"Point"}
}