{
  "type": "Feature",
  "properties": {
    "addr:full":"Place De Carni\u00c8res 8 Morlanwelz Hainaut 7141",
    "addr:housenumber":"8",
    "addr:postcode":"7141",
    "addr:street":"Place De Carnie\u0300Res",
    "iso:country":"BE",
    "sg:address":"Place De Carni\u00c8res 8",
    "sg:city":"Morlanwelz",
    "sg:orig_category":"Secretariaatsdiensten",
    "sg:phone":"+32 64 44 62 41",
    "sg:postcode":"7141",
    "sg:province":"Hainaut",
    "wof:name":"Lebeau",
    "wof:placetype":"venue"
},
  "geometry": {"coordinates":[4.2543048859,50.4436531067],"type":"Point"}
}