{
  "type": "Feature",
  "properties": {
    "iso:country":"BE",
    "sg:address":"Pastorijstraat 109",
    "sg:city":"Wingene",
    "sg:orig_category":"Reclamebureaus",
    "sg:phone":"+32 51 61 38 18",
    "sg:postcode":"8750",
    "sg:province":"West-Vlaanderen",
    "wof:name":"Id-touch\u00c9",
    "wof:placetype":"venue"
},
  "geometry": {"coordinates":[3.2222070694,51.0375556946],"type":"Point"}
}