{
  "type": "Feature",
  "properties": {
    "addr:full":"Brusselsesteenweg 336 Ninove (meerbeke) Oost-Vlaanderen 9402",
    "addr:housenumber":"336",
    "addr:postcode":"9402",
    "addr:street":"Brusselsesteenweg",
    "iso:country":"BE",
    "sg:address":"Brusselsesteenweg 336",
    "sg:city":"Ninove (meerbeke)",
    "sg:classifiers":[
        {
            "category":"Wholesale",
            "subcategory":"Vending Machines",
            "type":"Manufacturing & Wholesale Goods"
        }
    ],
    "sg:phone":"+32 54 33 88 31",
    "sg:postcode":"9402",
    "sg:province":"Oost-Vlaanderen",
    "sg:tags":[
        "automobile",
        "-",
        "radiator"
    ],
    "wof:name":"Dedoncker R",
    "wof:placetype":"venue"
},
  "geometry": {"coordinates":[4.0395750999,50.8249015808],"type":"Point"}
}