{
  "type": "Feature",
  "properties": {
    "addr:full":"Rue Sylvain Guyaux 45 La Louviere Hainaut 7100",
    "addr:housenumber":"45",
    "addr:postcode":"7100",
    "addr:street":"Rue Sylvain Guyaux",
    "iso:country":"BE",
    "sg:address":"Rue Sylvain Guyaux 45",
    "sg:city":"La Louviere",
    "sg:classifiers":[
        {
            "category":"Fast Food",
            "type":"Food & Drink"
        }
    ],
    "sg:phone":"+32 64 26 11 58",
    "sg:postcode":"7100",
    "sg:province":"Hainaut",
    "sg:tags":[
        "meeneem",
        "restaurant"
    ],
    "wof:name":"Portes D'asie",
    "wof:placetype":"venue"
},
  "geometry": {"coordinates":[4.1839270592,50.4755935669],"type":"Point"}
}