{
  "type": "Feature",
  "properties": {
    "addr:full":"Weverslaan 20a Lokeren Oost-Vlaanderen 9160",
    "addr:housenumber":"20a",
    "addr:postcode":"9160",
    "addr:street":"Weverslaan",
    "iso:country":"BE",
    "sg:address":"Weverslaan 20a",
    "sg:city":"Lokeren",
    "sg:orig_category":"Non-Classified Establishments",
    "sg:phone":"+32 9 348 81 19",
    "sg:postcode":"9160",
    "sg:province":"Oost-Vlaanderen",
    "wof:name":"St Paul",
    "wof:placetype":"venue"
},
  "geometry": {"coordinates":[4.0149488449,51.110206604],"type":"Point"}
}