{
  "type": "Feature",
  "properties": {
    "iso:country":"BE",
    "sg:address":"Rue Cache Lannoy 4",
    "sg:city":"Mont-de-l'enclus (amougies)",
    "sg:classifiers":[
        {
            "category":"Airline",
            "type":"Transportation"
        }
    ],
    "sg:phone":"+32 69 45 55 30",
    "sg:postcode":"7750",
    "sg:province":"Hainaut",
    "sg:tags":[
        "airport"
    ],
    "wof:name":"Airport Amougies",
    "wof:placetype":"venue"
},
  "geometry": {"coordinates":[6.4035139084,49.1109848022],"type":"Point"}
}