{
  "type": "Feature",
  "properties": {
    "addr:full":"Rue De La Vergette 26 Virton Luxembourg 6761",
    "addr:housenumber":"26",
    "addr:postcode":"6761",
    "addr:street":"Rue De La Vergette",
    "iso:country":"BE",
    "sg:address":"Rue De La Vergette 26",
    "sg:city":"Virton",
    "sg:orig_category":"Electrom\u00e9nager, t\u00e9l\u00e9visions and radios",
    "sg:phone":"+32 63 57 89 76",
    "sg:postcode":"6761",
    "sg:province":"Luxembourg",
    "wof:name":"Guy Abinet",
    "wof:placetype":"venue"
},
  "geometry": {"coordinates":[5.5587921143,49.5586280823],"type":"Point"}
}