{
  "type": "Feature",
  "properties": {
    "addr:full":"Rue De La Promenade 44 Bruxelles (anderlecht) Bruxelles-Capitale 1070",
    "addr:housenumber":"44",
    "addr:postcode":"1070",
    "addr:street":"Rue De La Promenade",
    "iso:country":"BE",
    "sg:address":"Rue De La Promenade 44",
    "sg:city":"Bruxelles (anderlecht)",
    "sg:orig_category":"Newspapers, magazines, periodicals - Distribution",
    "sg:phone":"+32 2 521 39 80",
    "sg:postcode":"1070",
    "sg:province":"Bruxelles-Capitale",
    "wof:name":"Van Nijkerk B",
    "wof:placetype":"venue"
},
  "geometry": {"coordinates":[4.2969632149,50.8259353638],"type":"Point"}
}