{
  "type": "Feature",
  "properties": {
    "iso:country":"BE",
    "sg:address":"Stasegemsesteenweg 1bl",
    "sg:city":"Kortrijk",
    "sg:orig_category":"Dakwerken Diverse bouwafwerking and reiniging",
    "sg:phone":"+32 56 25 69 96",
    "sg:postcode":"8500",
    "sg:province":"West-Vlaanderen",
    "wof:name":"Salembier",
    "wof:placetype":"venue"
},
  "geometry": {"coordinates":[3.2893440723,50.8310852051],"type":"Point"}
}