{
  "type": "Feature",
  "properties": {
    "addr:full":"Rue De Rome 11 Verviers Li\u00e8ge 4800",
    "addr:housenumber":"11",
    "addr:postcode":"4800",
    "addr:street":"Rue De Rome",
    "iso:country":"BE",
    "sg:address":"Rue De Rome 11",
    "sg:city":"Verviers",
    "sg:orig_category":"Motos. R\u00e9parations and entretien de motos",
    "sg:phone":"+32 87 35 31 00",
    "sg:postcode":"4800",
    "sg:province":"Li\u00e8ge",
    "wof:name":"Helios Mob",
    "wof:placetype":"venue"
},
  "geometry": {"coordinates":[5.8614487648,50.5916252136],"type":"Point"}
}