{
  "type": "Feature",
  "properties": {
    "iso:country":"BE",
    "sg:address":"Chauss\u00e9e De Warneton 377",
    "sg:city":"Comines-warneton (bas-warneton)",
    "sg:classifiers":[
        {
            "category":"Manufacturing",
            "subcategory":"Metals",
            "type":"Manufacturing & Wholesale Goods"
        }
    ],
    "sg:phone":"+32 56 55 78 79",
    "sg:postcode":"7784",
    "sg:province":"Hainaut",
    "sg:tags":[
        "alloy",
        "aluminium"
    ],
    "wof:name":"Alutrade Nv",
    "wof:placetype":"venue"
},
  "geometry": {"coordinates":[2.9706449509,50.76304245],"type":"Point"}
}