{
  "type": "Feature",
  "properties": {
    "addr:full":"Rue De L'ontario 6 Waterloo Brabant Wallon 1410",
    "addr:housenumber":"6",
    "addr:postcode":"1410",
    "addr:street":"Rue De L'Ontario",
    "iso:country":"BE",
    "sg:address":"Rue De L'ontario 6",
    "sg:city":"Waterloo",
    "sg:classifiers":[
        {
            "category":"Health Services",
            "subcategory":"Health Practitioner",
            "type":"Services"
        }
    ],
    "sg:phone":"+32 2 354 95 22",
    "sg:postcode":"1410",
    "sg:province":"Brabant Wallon",
    "sg:tags":[
        "therapist",
        "speech"
    ],
    "wof:name":"Wynant-hombroeckx",
    "wof:placetype":"venue"
},
  "geometry": {"coordinates":[4.3846869469,50.7254486084],"type":"Point"}
}