{
  "type": "Feature",
  "properties": {
    "iso:country":"BE",
    "sg:address":"Jasmijnstraat 45",
    "sg:city":"Lovendegem",
    "sg:orig_category":"Elektrische installaties voor woningen Loodgieterij, verwarming and sanitaire installaties Viessmann",
    "sg:phone":"+32 9 372 81 66",
    "sg:postcode":"9920",
    "sg:province":"Oost-Vlaanderen",
    "wof:name":"Gregoir Walter",
    "wof:placetype":"venue"
},
  "geometry": {"coordinates":[3.6346309185,51.1014976501],"type":"Point"}
}