{
  "type": "Feature",
  "properties": {
    "iso:country":"BE",
    "sg:address":"Chemin Des Pins 27",
    "sg:city":"Ukkel/uccle",
    "sg:orig_category":"Ambassades and consulats",
    "sg:phone":"+32 2 218 41 43",
    "sg:postcode":"1180",
    "sg:province":"Bruxelles-Capitale",
    "wof:name":"Ambassade Et Consulat Des Comores",
    "wof:placetype":"venue"
},
  "geometry": {"coordinates":[4.3799757957,50.7770271301],"type":"Point"}
}