{
  "type": "Feature",
  "properties": {
    "iso:country":"BE",
    "sg:address":"Sint-amandsstraat 105",
    "sg:city":"Grimbergen",
    "sg:orig_category":"Plomberie, chauffage and installations sanitaires",
    "sg:phone":"+32 2 267 16 97",
    "sg:postcode":"1853",
    "sg:province":"Vlaams-Brabant",
    "wof:name":"Europa Plomberie",
    "wof:placetype":"venue"
},
  "geometry": {"coordinates":[4.3602099419,50.905872345],"type":"Point"}
}