{
  "type": "Feature",
  "properties": {
    "addr:full":"Rue Michel Beckers 62 Vis\u00e9 (argenteau) Li\u00e8ge 4601",
    "addr:housenumber":"62",
    "addr:postcode":"4601",
    "addr:street":"Rue Michel Beckers;Argenteau",
    "iso:country":"BE",
    "sg:address":"Rue Michel Beckers 62",
    "sg:city":"Vis\u00e9 (argenteau)",
    "sg:classifiers":[
        {
            "category":"Utilities",
            "subcategory":"Telephone",
            "type":"Services"
        }
    ],
    "sg:phone":"+32 4 379 51 64",
    "sg:postcode":"4601",
    "sg:province":"Li\u00e8ge",
    "sg:tags":[
        "-",
        "internet"
    ],
    "wof:name":"Surf 2000",
    "wof:placetype":"venue"
},
  "geometry": {"coordinates":[5.6874017715,50.6957092285],"type":"Point"}
}