{
  "type": "Feature",
  "properties": {
    "iso:country":"BE",
    "sg:address":"Ossenwegstraat 111",
    "sg:city":"Zoutleeuw",
    "sg:classifiers":[
        {
            "category":"Cafe",
            "type":"Food & Drink"
        }
    ],
    "sg:phone":"+32 11 78 07 60",
    "sg:postcode":"3440",
    "sg:province":"Vlaams-Brabant",
    "sg:tags":[
        "caf\u00e9s"
    ],
    "wof:name":"Martine Hendrickx",
    "wof:placetype":"venue"
},
  "geometry": {"coordinates":[5.1351900101,50.8483352661],"type":"Point"}
}