{
  "type": "Feature",
  "properties": {
    "addr:full":"Rue De La Station 201 Charleroi (ransart) Hainaut 6043",
    "addr:housenumber":"201",
    "addr:postcode":"6043",
    "addr:street":"Rue De La Station",
    "iso:country":"BE",
    "sg:address":"Rue De La Station 201",
    "sg:city":"Charleroi (ransart)",
    "sg:classifiers":[
        {
            "category":"Health Services",
            "subcategory":"Dentist",
            "type":"Services"
        }
    ],
    "sg:phone":"+32 71 35 01 63",
    "sg:postcode":"6043",
    "sg:province":"Hainaut",
    "wof:name":"Hubert P",
    "wof:placetype":"venue"
},
  "geometry": {"coordinates":[4.4935002327,50.456703186],"type":"Point"}
}