{
  "type": "Feature",
  "properties": {
    "iso:country":"BE",
    "sg:address":"Oorloge 8",
    "sg:city":"Brakel",
    "sg:orig_category":"Artsen and specialisten",
    "sg:phone":"+32 55 42 25 59",
    "sg:postcode":"9660",
    "sg:province":"Oost-Vlaanderen",
    "wof:name":"Geert Vande Vijver",
    "wof:placetype":"venue"
},
  "geometry": {"coordinates":[3.7491691113,50.80701828],"type":"Point"}
}