{
  "type": "Feature",
  "properties": {
    "addr:full":"Rue De Royenne 44 Grez-doiceau Brabant Wallon 1390",
    "addr:housenumber":"44",
    "addr:postcode":"1390",
    "addr:street":"Rue De Royenne",
    "iso:country":"BE",
    "sg:address":"Rue De Royenne 44",
    "sg:city":"Grez-doiceau",
    "sg:classifiers":[
        {
            "category":"Professional",
            "subcategory":"Art Services",
            "type":"Services"
        }
    ],
    "sg:phone":"+32 10 84 02 10",
    "sg:postcode":"1390",
    "sg:province":"Brabant Wallon",
    "sg:tags":[
        "children's",
        "animation"
    ],
    "wof:name":"Les Doigts Sots Asbl",
    "wof:placetype":"venue"
},
  "geometry": {"coordinates":[4.6993160248,50.7183609009],"type":"Point"}
}