{
  "type": "Feature",
  "properties": {
    "iso:country":"BE",
    "sg:address":"Beekstraat 12",
    "sg:city":"Gingelom",
    "sg:classifiers":[
        {
            "category":"Manufacturing",
            "subcategory":"Textiles",
            "type":"Manufacturing & Wholesale Goods"
        }
    ],
    "sg:phone":"+32 11 88 17 51",
    "sg:postcode":"3890",
    "sg:province":"Limburg",
    "sg:tags":[
        "lingerie",
        "textiles",
        "sous-v\u00eatements"
    ],
    "wof:name":"Texmode",
    "wof:placetype":"venue"
},
  "geometry": {"coordinates":[5.1307911873,50.7209625244],"type":"Point"}
}