{
  "type": "Feature",
  "properties": {
    "iso:country":"BE",
    "sg:address":"Avenue Des Ardennes 59",
    "sg:city":"Esneux (tilff)",
    "sg:classifiers":[
        {
            "category":"Retail",
            "subcategory":"Repair Shop",
            "type":"Services"
        }
    ],
    "sg:phone":"+32 4 388 19 14",
    "sg:postcode":"4130",
    "sg:province":"Li\u00e8ge",
    "sg:tags":[
        "radio",
        "television",
        "-",
        "maintenance"
    ],
    "wof:name":"Chamberland",
    "wof:placetype":"venue"
},
  "geometry": {"coordinates":[5.5669360161,50.5327568054],"type":"Point"}
}