{
  "type": "Feature",
  "properties": {
    "addr:full":"Grote Weg 142 Menen (rekkem) West-Vlaanderen 8930",
    "addr:housenumber":"142",
    "addr:postcode":"8930",
    "addr:street":"Grote Weg",
    "iso:country":"BE",
    "sg:address":"Grote Weg 142",
    "sg:city":"Menen (rekkem)",
    "sg:classifiers":[
        {
            "category":"Home & Garden",
            "subcategory":"Hardware",
            "type":"Retail Goods"
        }
    ],
    "sg:phone":"+32 56 41 37 20",
    "sg:postcode":"8930",
    "sg:province":"West-Vlaanderen",
    "sg:tags":[
        "machine",
        "horticultural"
    ],
    "wof:name":"Christiaens Herve Nv",
    "wof:placetype":"venue"
},
  "geometry": {"coordinates":[3.1830179691,50.7670402527],"type":"Point"}
}