{
  "type": "Feature",
  "properties": {
    "addr:full":"Rue De Nieuport 51 Mouscron Hainaut 7700",
    "addr:housenumber":"51",
    "addr:postcode":"7700",
    "addr:street":"Rue De Nieuport",
    "iso:country":"BE",
    "sg:address":"Rue De Nieuport 51",
    "sg:city":"Mouscron",
    "sg:classifiers":[
        {
            "category":"Shopping",
            "subcategory":"Books",
            "type":"Retail Goods"
        }
    ],
    "sg:phone":"+32 56 33 16 94",
    "sg:postcode":"7700",
    "sg:province":"Hainaut",
    "sg:tags":[
        "bookseller"
    ],
    "wof:name":"Vandenbroucke (librairie)",
    "wof:placetype":"venue"
},
  "geometry": {"coordinates":[3.2032380104,50.7498817444],"type":"Point"}
}