{
  "type": "Feature",
  "properties": {
    "addr:full":"Driemastenbaan 68 Wommelgem Antwerpen 2160",
    "addr:housenumber":"68",
    "addr:postcode":"2160",
    "addr:street":"Driemastenbaan",
    "iso:country":"BE",
    "sg:address":"Driemastenbaan 68",
    "sg:city":"Wommelgem",
    "sg:orig_category":"Installation de menuiserie en bois and plastique",
    "sg:phone":"+32 3 354 08 39",
    "sg:postcode":"2160",
    "sg:province":"Antwerpen",
    "wof:name":"Herijgers Louis En Zoon",
    "wof:placetype":"venue"
},
  "geometry": {"coordinates":[4.5330290794,51.1942863464],"type":"Point"}
}