{
  "type": "Feature",
  "properties": {
    "iso:country":"BE",
    "sg:address":"Rue Albert I 84",
    "sg:city":"La Louvi\u00e8re",
    "sg:classifiers":[
        {
            "category":"Manufacturing",
            "subcategory":"Textiles",
            "type":"Manufacturing & Wholesale Goods"
        }
    ],
    "sg:phone":"+32 64 84 94 80",
    "sg:postcode":"7100",
    "sg:province":"Hainaut",
    "sg:tags":[
        "retail",
        "-"
    ],
    "wof:name":"Zeeman Textiel Supers",
    "wof:placetype":"venue"
},
  "geometry": {"coordinates":[4.1856532097,50.4756622314],"type":"Point"}
}