{
  "type": "Feature",
  "properties": {
    "iso:country":"BE",
    "sg:address":"Sint-romboutskerkhof",
    "sg:city":"Mechelen",
    "sg:orig_category":"Mus\u00e9es and patrimoine culturel",
    "sg:phone":"+32 15 21 87 06",
    "sg:postcode":"2800",
    "sg:province":"Antwerpen",
    "wof:name":"St. Romboutskathedraal",
    "wof:placetype":"venue"
},
  "geometry": {"coordinates":[4.4781098366,51.0292434692],"type":"Point"}
}