{
  "type": "Feature",
  "properties": {
    "addr:full":"28 Vaucampslaan 1654 Huizingen 28",
    "addr:housenumber":"28;28",
    "addr:postcode":"1654",
    "addr:street":"Vaucampslaan",
    "iso:country":"BE",
    "sg:address":"28",
    "sg:city":"Vaucampslaan 1654 Huizingen",
    "sg:classifiers":[
        {
            "category":"Professional",
            "subcategory":"Engineering",
            "type":"Services"
        }
    ],
    "sg:phone":"+32 2 360 14 15",
    "sg:postcode":"28",
    "sg:tags":[
        "machine",
        "-",
        "mechanical"
    ],
    "wof:name":"Dolmen Industrial Projects",
    "wof:placetype":"venue"
},
  "geometry": {"coordinates":[4.2630400658,50.752040863],"type":"Point"}
}