{
  "type": "Feature",
  "properties": {
    "addr:full":"Herenstraat 100/102 Waterschei-zwartberg Limburg 3600",
    "addr:housenumber":"100 / 102",
    "addr:postcode":"3600",
    "addr:street":"Herenstraat;Waterschei-Zwartberg Limburg",
    "iso:country":"BE",
    "sg:address":"Herenstraat 100/102",
    "sg:city":"Waterschei-zwartberg",
    "sg:orig_category":"Huisdieren and benodigdheden Royal Canin",
    "sg:phone":"+32 11 38 01 02",
    "sg:postcode":"3600",
    "sg:province":"Limburg",
    "wof:name":"Van Hengel-steyvers J.",
    "wof:placetype":"venue"
},
  "geometry": {"coordinates":[5.4990148544,50.9635848999],"type":"Point"}
}