{
  "type": "Feature",
  "properties": {
    "addr:full":"Rue D'harnoncourt 48 Virton Luxembourg 6762",
    "addr:housenumber":"48",
    "addr:postcode":"6762",
    "addr:street":"Rue D'Harnoncourt",
    "iso:country":"BE",
    "sg:address":"Rue D'harnoncourt 48",
    "sg:city":"Virton",
    "sg:orig_category":"Pharmaciens",
    "sg:phone":"+32 63 58 81 39",
    "sg:postcode":"6762",
    "sg:province":"Luxembourg",
    "wof:name":"Clinique Edm. Jacques",
    "wof:placetype":"venue"
},
  "geometry": {"coordinates":[5.5250229836,49.5530929565],"type":"Point"}
}