{
  "type": "Feature",
  "properties": {
    "addr:full":"Rue De La Roche 89 Rendeux Luxembourg 6987",
    "addr:housenumber":"89",
    "addr:postcode":"6987",
    "addr:street":"Rue De La",
    "iso:country":"BE",
    "sg:address":"Rue De La Roche 89",
    "sg:city":"Rendeux",
    "sg:classifiers":[
        {
            "category":"Recreation",
            "subcategory":"Campground",
            "type":"Entertainment"
        }
    ],
    "sg:phone":"+32 84 47 73 71",
    "sg:postcode":"6987",
    "sg:province":"Luxembourg",
    "sg:tags":[
        "site",
        "camping"
    ],
    "wof:name":"Festival (le)",
    "wof:placetype":"venue"
},
  "geometry": {"coordinates":[5.5241208076,50.2292709351],"type":"Point"}
}