{
  "type": "Feature",
  "properties": {
    "iso:country":"BE",
    "sg:address":"Heistraat 77",
    "sg:city":"Sint-niklaas",
    "sg:orig_category":"Biens d'occasion",
    "sg:phone":"+32 3 777 28 98",
    "sg:postcode":"9100",
    "sg:province":"Oost-Vlaanderen",
    "wof:name":"Huis Bozzel",
    "wof:placetype":"venue"
},
  "geometry": {"coordinates":[4.1282501221,51.1735420227],"type":"Point"}
}