{
  "type": "Feature",
  "properties": {
    "addr:full":"Rue De La Hav\u00e9e 8a Erez\u00e9e (soy) Luxembourg 6997",
    "addr:housenumber":"8a",
    "addr:postcode":"6997",
    "addr:street":"Rue De La Have\u0301E",
    "iso:country":"BE",
    "sg:address":"Rue De La Hav\u00e9e 8a",
    "sg:city":"Erez\u00e9e (soy)",
    "sg:classifiers":[
        {
            "category":"Manufacturing",
            "subcategory":"Metals",
            "type":"Manufacturing & Wholesale Goods"
        }
    ],
    "sg:phone":"+32 84 46 64 54",
    "sg:postcode":"6997",
    "sg:province":"Luxembourg",
    "sg:tags":[
        "ironwork"
    ],
    "wof:name":"Borlon Marcel",
    "wof:placetype":"venue"
},
  "geometry": {"coordinates":[5.5588469505,50.2911453247],"type":"Point"}
}