{
  "type": "Feature",
  "properties": {
    "iso:country":"BE",
    "sg:address":"Avenue Paul De Lorraine 17",
    "sg:city":"Waterloo",
    "sg:orig_category":"Non-Classified Establishments",
    "sg:phone":"+32 2 384 61 45",
    "sg:postcode":"1410",
    "sg:province":"Brabant Wallon",
    "wof:name":"Langsbel Sa",
    "wof:placetype":"venue"
},
  "geometry": {"coordinates":[4.3995838165,50.6961364746],"type":"Point"}
}