{
  "type": "Feature",
  "properties": {
    "iso:country":"BE",
    "sg:address":"Place Saint-georges 74",
    "sg:city":"Limbourg",
    "sg:classifiers":[
        {
            "category":"Shopping",
            "subcategory":"Crafts & Fabrics",
            "type":"Retail Goods"
        }
    ],
    "sg:phone":"+32 87 76 65 07",
    "sg:postcode":"4830",
    "sg:province":"Li\u00e8ge",
    "sg:tags":[
        "pleating",
        "embroidery"
    ],
    "wof:name":"Finck Jl & K",
    "wof:placetype":"venue"
},
  "geometry": {"coordinates":[5.9399728775,50.6122322083],"type":"Point"}
}