{
  "type": "Feature",
  "properties": {
    "addr:full":"Rue De Valenciennes 377 Boussu (hornu) Hainaut 7301",
    "addr:housenumber":"377",
    "addr:postcode":"7301",
    "addr:street":"Rue De Valenciennes",
    "iso:country":"BE",
    "sg:address":"Rue De Valenciennes 377",
    "sg:city":"Boussu (hornu)",
    "sg:classifiers":[
        {
            "category":"Food & Beverages",
            "subcategory":"Supermarket",
            "type":"Retail Goods"
        }
    ],
    "sg:phone":"+32 65 78 91 01",
    "sg:postcode":"7301",
    "sg:province":"Hainaut",
    "sg:tags":[
        "department",
        "store"
    ],
    "wof:name":"Battard",
    "wof:placetype":"venue"
},
  "geometry": {"coordinates":[3.8257451057,50.4362258911],"type":"Point"}
}