{
  "type": "Feature",
  "properties": {
    "iso:country":"BE",
    "sg:address":"Gemeenteplein 31",
    "sg:city":"Hoeilaart",
    "sg:orig_category":"Diverse kredietdiensten",
    "sg:postcode":"1560",
    "sg:province":"Vlaams-Brabant",
    "wof:name":"Bancontact-mister Cash",
    "wof:placetype":"venue"
},
  "geometry": {"coordinates":[4.4725551605,50.7685661316],"type":"Point"}
}