{
  "type": "Feature",
  "properties": {
    "addr:full":"Rue D'houdr\u00e9mont 64 Bi\u00e8vre Namur 5555",
    "addr:housenumber":"64",
    "addr:postcode":"5555",
    "addr:street":"Rue D'Houdre \u0301Mont",
    "iso:country":"BE",
    "sg:address":"Rue D'houdr\u00e9mont 64",
    "sg:city":"Bi\u00e8vre",
    "sg:classifiers":[
        {
            "category":"Health Services",
            "subcategory":"Doctor",
            "type":"Services"
        }
    ],
    "sg:phone":"+32 61 51 16 51",
    "sg:postcode":"5555",
    "sg:province":"Namur",
    "sg:tags":[
        "medicinephysicians",
        "surgeon"
    ],
    "wof:name":"Libouton J P",
    "wof:placetype":"venue"
},
  "geometry": {"coordinates":[5.0044760704,49.9400863647],"type":"Point"}
}