{
  "type": "Feature",
  "properties": {
    "addr:full":"Dorp 65 Haaltert (denderhoutem) Oost-Vlaanderen 9450",
    "addr:housenumber":"65",
    "addr:postcode":"9450",
    "addr:street":"Dorp",
    "iso:country":"BE",
    "sg:address":"Dorp 65",
    "sg:city":"Haaltert (denderhoutem)",
    "sg:classifiers":[
        {
            "category":"Health Services",
            "subcategory":"Health Practitioner",
            "type":"Services"
        }
    ],
    "sg:phone":"+32 54 33 34 35",
    "sg:postcode":"9450",
    "sg:province":"Oost-Vlaanderen",
    "sg:tags":[
        "physiotherapist"
    ],
    "wof:name":"Lievens Krista",
    "wof:placetype":"venue"
},
  "geometry": {"coordinates":[4.0180931091,50.8714828491],"type":"Point"}
}