{
  "type": "Feature",
  "properties": {
    "iso:country":"BE",
    "sg:address":"Constant Hansoulstraat 48",
    "sg:city":"Machelen",
    "sg:orig_category":"Jardinage",
    "sg:phone":"+32 2 251 89 29",
    "sg:postcode":"1830",
    "sg:province":"Vlaams-Brabant",
    "wof:name":"Blanpain",
    "wof:placetype":"venue"
},
  "geometry": {"coordinates":[4.4354968071,50.9104423523],"type":"Point"}
}