{
  "type": "Feature",
  "properties": {
    "addr:full":"Diesterbaan 27 Box 1 Herentals (noorderwijk) Antwerpen 2200",
    "addr:housenumber":"27;1",
    "addr:postcode":"2200",
    "addr:street":"Diesterbaan;Box",
    "iso:country":"BE",
    "sg:address":"Diesterbaan 27 Box 1",
    "sg:city":"Herentals (noorderwijk)",
    "sg:classifiers":[
        {
            "category":"Professional",
            "subcategory":"Accounting & Tax Preparation",
            "type":"Services"
        }
    ],
    "sg:phone":"+32 14 26 23 16",
    "sg:postcode":"2200",
    "sg:province":"Antwerpen",
    "sg:tags":[
        "bookkeeper"
    ],
    "wof:name":"Nuyts A",
    "wof:placetype":"venue"
},
  "geometry": {"coordinates":[4.8407402039,51.1371536255],"type":"Point"}
}