{
  "type": "Feature",
  "properties": {
    "iso:country":"BE",
    "sg:address":"H. Van Veldekesingel 5",
    "sg:city":"Hasselt",
    "sg:orig_category":"Bagage and lederwaren Schoenen",
    "sg:phone":"+32 11 27 42 82",
    "sg:postcode":"3500",
    "sg:province":"Limburg",
    "wof:name":"Scapino",
    "wof:placetype":"venue"
},
  "geometry": {"coordinates":[5.3143901825,50.92993927],"type":"Point"}
}