{
  "type": "Feature",
  "properties": {
    "iso:country":"BE",
    "sg:address":"Frederik De Merodestraat 26",
    "sg:city":"Mechelen",
    "sg:orig_category":"Fotografen and fotostudio's",
    "sg:phone":"+32 15 21 68 20",
    "sg:postcode":"2800",
    "sg:province":"Antwerpen",
    "wof:name":"Philippe Mathijs",
    "wof:placetype":"venue"
},
  "geometry": {"coordinates":[4.481607914,51.0299682617],"type":"Point"}
}