{
  "type": "Feature",
  "properties": {
    "addr:full":"Korte Bruggestraat 0 Poperinge West-Vlaanderen 8970",
    "addr:housenumber":"0",
    "addr:postcode":"8970",
    "addr:street":"Korte Bruggestraat",
    "iso:country":"BE",
    "sg:address":"Korte Bruggestraat 0",
    "sg:city":"Poperinge",
    "sg:orig_category":"Sportclubs Sportterreinen and installaties behalve sportcentra",
    "sg:phone":"+32 57 33 70 66",
    "sg:postcode":"8970",
    "sg:province":"West-Vlaanderen",
    "wof:name":"Tennis Club Poperinge",
    "wof:placetype":"venue"
},
  "geometry": {"coordinates":[2.7408649921,50.8572044373],"type":"Point"}
}