{
  "type": "Feature",
  "properties": {
    "addr:full":"Dorp 71 Haaltert Oost-Vlaanderen 9450",
    "addr:housenumber":"71",
    "addr:postcode":"9450",
    "addr:street":"Dorp",
    "iso:country":"BE",
    "sg:address":"Dorp 71",
    "sg:city":"Haaltert",
    "sg:orig_category":"R\u00e9parations d'appareils \u00e9lectrom\u00e9nagers. Electrom\u00e9nager, t\u00e9l\u00e9visions and radios",
    "sg:phone":"+32 54 33 17 76",
    "sg:postcode":"9450",
    "sg:province":"Oost-Vlaanderen",
    "wof:name":"Huis Goubert",
    "wof:placetype":"venue"
},
  "geometry": {"coordinates":[4.0180020332,50.8716201782],"type":"Point"}
}