{
  "type": "Feature",
  "properties": {
    "addr:full":"Rostynedreef 36a Aalter Oost-Vlaanderen 9880",
    "addr:housenumber":"36a",
    "addr:postcode":"9880",
    "addr:street":"Rostynedreef",
    "iso:country":"BE",
    "sg:address":"Rostynedreef 36a",
    "sg:city":"Aalter",
    "sg:classifiers":[
        {
            "category":"Professional",
            "subcategory":"Accounting & Tax Preparation",
            "type":"Services"
        }
    ],
    "sg:phone":"+32 9 374 14 78",
    "sg:postcode":"9880",
    "sg:province":"Oost-Vlaanderen",
    "sg:tags":[
        "bookkeeper"
    ],
    "wof:name":"Almey K",
    "wof:placetype":"venue"
},
  "geometry": {"coordinates":[3.4732310772,51.0765724182],"type":"Point"}
}