{
  "type": "Feature",
  "properties": {
    "addr:full":"Chauss\u00c9e De Stockel 482 Sint-pieters-woluwe/woluwe-saint-pierre Bruxelles-Capitale 1150",
    "addr:housenumber":"482",
    "addr:postcode":"1150",
    "addr:street":"Chausse\u0301E De Stockel;/",
    "iso:country":"BE",
    "sg:address":"Chauss\u00c9e De Stockel 482",
    "sg:city":"Sint-pieters-woluwe/woluwe-saint-pierre",
    "sg:orig_category":"M\u00e9decins and sp\u00e9cialistes",
    "sg:phone":"+32 2 721 24 32",
    "sg:postcode":"1150",
    "sg:province":"Bruxelles-Capitale",
    "wof:name":"Xavier Gillis",
    "wof:placetype":"venue"
},
  "geometry": {"coordinates":[4.4570198059,50.8419799805],"type":"Point"}
}