{
  "type": "Feature",
  "properties": {
    "addr:full":"Avenue Louise 120 Box 12 Bruxelles (ixelles) Bruxelles-Capitale 1050",
    "addr:housenumber":"120 box 12",
    "addr:postcode":"1050",
    "addr:street":"Avenue Louise",
    "iso:country":"BE",
    "sg:address":"Avenue Louise 120 Box 12",
    "sg:city":"Bruxelles (ixelles)",
    "sg:orig_category":"Railway Logistics",
    "sg:phone":"+32 50 55 99 99",
    "sg:postcode":"1050",
    "sg:province":"Bruxelles-Capitale",
    "wof:name":"Inter Ferry Boats Nv",
    "wof:placetype":"venue"
},
  "geometry": {"coordinates":[3.1914598942,51.3280792236],"type":"Point"}
}