{
  "type": "Feature",
  "properties": {
    "iso:country":"BE",
    "sg:address":"Avenue Paul Stroobant 46bb",
    "sg:city":"Ukkel/uccle",
    "sg:orig_category":"M\u00e9decins and sp\u00e9cialistes",
    "sg:phone":"+32 2 374 61 75",
    "sg:postcode":"1180",
    "sg:province":"Bruxelles-Capitale",
    "wof:name":"Dominique Biarent",
    "wof:placetype":"venue"
},
  "geometry": {"coordinates":[4.3483428955,50.7988014221],"type":"Point"}
}