{
  "type": "Feature",
  "properties": {
    "addr:full":"Rue Ferrer 73 Mons Hainaut 7033",
    "addr:housenumber":"73",
    "addr:postcode":"7033",
    "addr:street":"Rue Ferrer;Hainaut",
    "iso:country":"BE",
    "sg:address":"Rue Ferrer 73",
    "sg:city":"Mons",
    "sg:orig_category":"Plomberie, chauffage and installations sanitaires",
    "sg:phone":"+32 65 31 95 74",
    "sg:postcode":"7033",
    "sg:province":"Hainaut",
    "wof:name":"Cantagallo",
    "wof:placetype":"venue"
},
  "geometry": {"coordinates":[3.9253261089,50.4366378784],"type":"Point"}
}