{
  "type": "Feature",
  "properties": {
    "addr:full":"Bondgenotenlaan 56 Leuven Vlaams-Brabant 3000",
    "addr:housenumber":"56",
    "addr:postcode":"3000",
    "addr:street":"Bondgenotenlaan",
    "iso:country":"BE",
    "sg:address":"Bondgenotenlaan 56",
    "sg:city":"Leuven",
    "sg:classifiers":[
        {
            "category":"Shopping",
            "subcategory":"Clothing, Apparel, & Fashions",
            "type":"Retail Goods"
        }
    ],
    "sg:phone":"+32 16 29 18 85",
    "sg:postcode":"3000",
    "sg:province":"Vlaams-Brabant",
    "sg:tags":[
        "boutique"
    ],
    "wof:name":"Mexx Lifestyle",
    "wof:placetype":"venue"
},
  "geometry": {"coordinates":[4.7069587708,50.8797912598],"type":"Point"}
}