{
  "type": "Feature",
  "properties": {
    "addr:full":"Luikerstraat 5 Sint-truiden Limburg 3800",
    "addr:housenumber":"5",
    "addr:postcode":"3800",
    "addr:street":"Luikerstraat",
    "iso:country":"BE",
    "sg:address":"Luikerstraat 5",
    "sg:city":"Sint-truiden",
    "sg:classifiers":[
        {
            "category":"Shopping",
            "subcategory":"Clothing, Apparel, & Fashions",
            "type":"Retail Goods"
        }
    ],
    "sg:phone":"+32 11 70 72 88",
    "sg:postcode":"3800",
    "sg:province":"Limburg",
    "sg:tags":[
        "clothing",
        "-",
        "gentleman"
    ],
    "wof:name":"Cardelly",
    "wof:placetype":"venue"
},
  "geometry": {"coordinates":[5.1868519783,50.8150138855],"type":"Point"}
}