{
  "type": "Feature",
  "properties": {
    "iso:country":"BE",
    "sg:address":"Rue De La Chapelle 3",
    "sg:city":"Remicourt",
    "sg:orig_category":"Fabrication and montage de mobilier. D\u00e9corateurs d'int\u00e9rieur. Quincailleries. Installation de menuis",
    "sg:phone":"+32 19 54 53 19",
    "sg:postcode":"4351",
    "sg:province":"Li\u00e8ge",
    "wof:name":"Georges Serville",
    "wof:placetype":"venue"
},
  "geometry": {"coordinates":[5.3469061852,50.695602417],"type":"Point"}
}