{
  "type": "Feature",
  "properties": {
    "addr:full":"Avenue De Restauration 10 Dinant Namur 5500",
    "addr:housenumber":"10",
    "addr:postcode":"5500",
    "addr:street":"Avenue De Restauration",
    "iso:country":"BE",
    "sg:address":"Avenue De Restauration 10",
    "sg:city":"Dinant",
    "sg:orig_category":"Eleveurs de bovins",
    "sg:phone":"+32 82 74 42 17",
    "sg:postcode":"5500",
    "sg:province":"Namur",
    "wof:name":"Bernard Sinet",
    "wof:placetype":"venue"
},
  "geometry": {"coordinates":[4.8967700005,50.1997413635],"type":"Point"}
}