{
  "type": "Feature",
  "properties": {
    "addr:full":"Zwaluwenstraat 27 Geel Antwerpen 2440",
    "addr:housenumber":"27",
    "addr:postcode":"2440",
    "addr:street":"Zwaluwenstraat",
    "iso:country":"BE",
    "sg:address":"Zwaluwenstraat 27",
    "sg:city":"Geel",
    "sg:classifiers":[
        {
            "category":"Food & Beverages",
            "subcategory":"Groceries & Convenience Stores",
            "type":"Retail Goods"
        }
    ],
    "sg:phone":"+32 14 59 40 12",
    "sg:postcode":"2440",
    "sg:province":"Antwerpen",
    "sg:tags":[
        "grocer"
    ],
    "wof:name":"De Leunen",
    "wof:placetype":"venue"
},
  "geometry": {"coordinates":[4.9723520279,51.1727485657],"type":"Point"}
}