{
  "type": "Feature",
  "properties": {
    "iso:country":"BE",
    "sg:address":"Zavelstraat 27",
    "sg:city":"Wezembeek-oppem/wezembeek-oppem",
    "sg:classifiers":[
        {
            "category":"Professional",
            "subcategory":"Accounting & Tax Preparation",
            "type":"Services"
        }
    ],
    "sg:phone":"+32 2 731 17 65",
    "sg:postcode":"1970",
    "sg:province":"Vlaams-Brabant",
    "sg:tags":[
        "accountant"
    ],
    "wof:name":"Francoise Francq",
    "wof:placetype":"venue"
},
  "geometry": {"coordinates":[4.4943552017,50.8378143311],"type":"Point"}
}