{
  "type": "Feature",
  "properties": {
    "addr:full":"Avenue Des B\u00c9cassines 13 Oudergem/auderghem Bruxelles-Capitale 1160",
    "addr:housenumber":"13",
    "addr:postcode":"1160",
    "addr:street":"Avenue Des Be\u0301Cassines;/",
    "iso:country":"BE",
    "sg:address":"Avenue Des B\u00c9cassines 13",
    "sg:city":"Oudergem/auderghem",
    "sg:orig_category":"Agences immobili\u00e8res",
    "sg:phone":"+32 2 660 35 55",
    "sg:postcode":"1160",
    "sg:province":"Bruxelles-Capitale",
    "wof:name":"Top Real Estate",
    "wof:placetype":"venue"
},
  "geometry": {"coordinates":[4.4217801094,50.8206100464],"type":"Point"}
}