{
  "type": "Feature",
  "properties": {
    "addr:full":"Rue Paul Verlaine 24 Bouillon Luxembourg 6838",
    "addr:housenumber":"24",
    "addr:postcode":"6838",
    "addr:street":"Rue Paul Verlaine",
    "iso:country":"BE",
    "sg:address":"Rue Paul Verlaine 24",
    "sg:city":"Bouillon",
    "sg:orig_category":"Kruideniers Slagers",
    "sg:phone":"+32 61 46 69 19",
    "sg:postcode":"6838",
    "sg:province":"Luxembourg",
    "wof:name":"Uma",
    "wof:placetype":"venue"
},
  "geometry": {"coordinates":[5.0071702003,49.7973403931],"type":"Point"}
}