{
  "type": "Feature",
  "properties": {
    "iso:country":"BE",
    "sg:address":"Pont-de-pierre 124",
    "sg:city":"Dinant",
    "sg:orig_category":"Antiek",
    "sg:phone":"+32 82 22 52 02",
    "sg:postcode":"5500",
    "sg:province":"Namur",
    "wof:name":"La Licorne",
    "wof:placetype":"venue"
},
  "geometry": {"coordinates":[4.9431390762,50.2401542664],"type":"Point"}
}