{
  "type": "Feature",
  "properties": {
    "addr:full":"Rue De N\u00c8vremont 79 Fosses-la-ville Namur 5070",
    "addr:housenumber":"79",
    "addr:postcode":"5070",
    "addr:street":"Rue De Ne\u0300Vremont",
    "iso:country":"BE",
    "sg:address":"Rue De N\u00c8vremont 79",
    "sg:city":"Fosses-la-ville",
    "sg:orig_category":"Charpentes and couvertures",
    "sg:phone":"+32 71 71 25 40",
    "sg:postcode":"5070",
    "sg:province":"Namur",
    "wof:name":"Entreprises Gilson Fr\u00c8res",
    "wof:placetype":"venue"
},
  "geometry": {"coordinates":[4.6767292023,50.4069328308],"type":"Point"}
}