{
  "type": "Feature",
  "properties": {
    "addr:full":"Rue Neuve 6 Malmedy Li\u00e8ge 4960",
    "addr:housenumber":"6",
    "addr:postcode":"4960",
    "addr:street":"Rue Neuve",
    "iso:country":"BE",
    "sg:address":"Rue Neuve 6",
    "sg:city":"Malmedy",
    "sg:orig_category":"V\u00eatements, chaussures and accessoires Agences de publicit\u00e9",
    "sg:phone":"+32 80 77 08 06",
    "sg:postcode":"4960",
    "sg:province":"Li\u00e8ge",
    "wof:name":"Oh! Graphic",
    "wof:placetype":"venue"
},
  "geometry": {"coordinates":[6.0332422256,50.4249954224],"type":"Point"}
}