{
  "type": "Feature",
  "properties": {
    "addr:full":"Noord-brabantlaan 16 Turnhout Antwerpen 2300",
    "addr:housenumber":"16",
    "addr:postcode":"2300",
    "addr:street":"Noord-Brabantlaan",
    "iso:country":"BE",
    "sg:address":"Noord-brabantlaan 16",
    "sg:city":"Turnhout",
    "sg:orig_category":"Pi\u00e8ces and accessoires de v\u00e9hicules automobiles Gr",
    "sg:phone":"+32 14 45 37 96",
    "sg:postcode":"2300",
    "sg:province":"Antwerpen",
    "wof:name":"Janssens - Geerlinck",
    "wof:placetype":"venue"
},
  "geometry": {"coordinates":[4.9667639732,51.3261756897],"type":"Point"}
}