{
  "type": "Feature",
  "properties": {
    "iso:country":"BE",
    "sg:address":"Grote Heerweg 92",
    "sg:city":"Waregem",
    "sg:orig_category":"Sportclubs",
    "sg:phone":"+32 56 72 90 24",
    "sg:postcode":"8791",
    "sg:province":"West-Vlaanderen",
    "wof:name":"W.c. Sport Na Arbeid",
    "wof:placetype":"venue"
},
  "geometry": {"coordinates":[3.3323719501,50.8761672974],"type":"Point"}
}