{
  "type": "Feature",
  "properties": {
    "iso:country":"BE",
    "sg:address":"Kapelstraat 3b11",
    "sg:city":"Diepenbeek",
    "sg:classifiers":[
        {
            "category":"Sports & Exercise",
            "subcategory":"Sports Center",
            "type":"Entertainment"
        }
    ],
    "sg:phone":"+32 11 33 22 01",
    "sg:postcode":"3590",
    "sg:province":"Limburg",
    "sg:tags":[
        "de",
        "fitness"
    ],
    "wof:name":"Gino Renson",
    "wof:placetype":"venue"
},
  "geometry": {"coordinates":[5.4187002182,50.909198761],"type":"Point"}
}