{
  "type": "Feature",
  "properties": {
    "iso:country":"BE",
    "sg:address":"Teckenbusch 18",
    "sg:city":"Kelmis",
    "sg:classifiers":[
        {
            "category":"Home & Garden",
            "subcategory":"Carpets & Floor Coverings",
            "type":"Retail Goods"
        }
    ],
    "sg:phone":"+32 87 65 91 18",
    "sg:postcode":"4720",
    "sg:province":"Li\u00e8ge",
    "sg:tags":[
        "-"
    ],
    "wof:name":"Boursie J",
    "wof:placetype":"venue"
},
  "geometry": {"coordinates":[6.0117278099,50.7237815857],"type":"Point"}
}