{
  "type": "Feature",
  "properties": {
    "addr:full":"Zuidmoerstraat 188 Eeklo Oost-Vlaanderen 9900",
    "addr:housenumber":"188",
    "addr:postcode":"9900",
    "addr:street":"Zuidmoerstraat",
    "iso:country":"BE",
    "sg:address":"Zuidmoerstraat 188",
    "sg:city":"Eeklo",
    "sg:orig_category":"Souvenirs and objets artisanaux",
    "sg:phone":"+32 9 377 84 33",
    "sg:postcode":"9900",
    "sg:province":"Oost-Vlaanderen",
    "wof:name":"Annekes Creativiteitsatelier",
    "wof:placetype":"venue"
},
  "geometry": {"coordinates":[3.5619690418,51.1826324463],"type":"Point"}
}