{
  "type": "Feature",
  "properties": {
    "addr:full":"Lieven Bauwensstraat 15 Brugge (sint-andries) West-Vlaanderen 8200",
    "addr:housenumber":"15",
    "addr:postcode":"8200",
    "addr:street":"Lieven Bauwensstraat",
    "iso:country":"BE",
    "sg:address":"Lieven Bauwensstraat 15",
    "sg:city":"Brugge (sint-andries)",
    "sg:classifiers":[
        {
            "category":"Retail",
            "subcategory":"Auto Repair",
            "type":"Services"
        }
    ],
    "sg:phone":"+32 50 31 35 63",
    "sg:postcode":"8200",
    "sg:province":"West-Vlaanderen",
    "sg:tags":[
        "garage"
    ],
    "wof:name":"Service Center Vuylsteke",
    "wof:placetype":"venue"
},
  "geometry": {"coordinates":[3.1946899891,51.2132072449],"type":"Point"}
}