{
  "type": "Feature",
  "properties": {
    "addr:full":"Rue De L'abbaye 11\u00c01000 Brussel/bruxelles Bruxelles-Capitale 1000",
    "addr:postcode":"1000",
    "addr:street":"Rue De L'Abbaye 11A\u03001000",
    "iso:country":"BE",
    "sg:address":"Rue De L'abbaye 11\u00c01000",
    "sg:city":"Brussel/bruxelles",
    "sg:orig_category":"Bloemen and planten",
    "sg:phone":"+32 2 640 95 05",
    "sg:postcode":"1000",
    "sg:province":"Bruxelles-Capitale",
    "wof:name":"Arrosoir Du Prieur\u00c9",
    "wof:placetype":"venue"
},
  "geometry": {"coordinates":[4.3519678116,50.8579750061],"type":"Point"}
}