{
  "type": "Feature",
  "properties": {
    "addr:full":"Rue De La Poudrerie 2 Huy (ben-ahin) Li\u00e8ge 4500",
    "addr:housenumber":"2",
    "addr:postcode":"4500",
    "addr:street":"Rue De La Poudrerie",
    "iso:country":"BE",
    "sg:address":"Rue De La Poudrerie 2",
    "sg:city":"Huy (ben-ahin)",
    "sg:classifiers":[
        {
            "category":"Manufacturing",
            "subcategory":"Furniture",
            "type":"Manufacturing & Wholesale Goods"
        }
    ],
    "sg:phone":"+32 85 25 20 24",
    "sg:postcode":"4500",
    "sg:province":"Li\u00e8ge",
    "sg:tags":[
        "design",
        "-"
    ],
    "wof:name":"S.e.l.e.c.k.",
    "wof:placetype":"venue"
},
  "geometry": {"coordinates":[5.1946849823,50.51720047],"type":"Point"}
}