{
  "type": "Feature",
  "properties": {
    "addr:full":"Metzert 2 Attert Luxembourg 6717",
    "addr:housenumber":"2",
    "addr:postcode":"6717",
    "addr:street":"Metzert",
    "iso:country":"BE",
    "sg:address":"Metzert 2",
    "sg:city":"Attert",
    "sg:orig_category":"Sportclubs",
    "sg:phone":"+32 63 21 63 61",
    "sg:postcode":"6717",
    "sg:province":"Luxembourg",
    "wof:name":"T.c. Du Val D'attert",
    "wof:placetype":"venue"
},
  "geometry": {"coordinates":[5.7888741493,49.7506217957],"type":"Point"}
}