{
  "type": "Feature",
  "properties": {
    "addr:full":"Montjoielaan 3 Ukkel/uccle Bruxelles-Capitale 1180",
    "addr:housenumber":"3",
    "addr:postcode":"1180",
    "addr:street":"Montjoielaan;/",
    "iso:country":"BE",
    "sg:address":"Montjoielaan 3",
    "sg:city":"Ukkel/uccle",
    "sg:orig_category":"Artiesten and kunstenaars",
    "sg:phone":"+32 2 343 81 96",
    "sg:postcode":"1180",
    "sg:province":"Bruxelles-Capitale",
    "wof:name":"Tamara Diatchenko",
    "wof:placetype":"venue"
},
  "geometry": {"coordinates":[4.3684329987,50.8107147217],"type":"Point"}
}