{
  "type": "Feature",
  "properties": {
    "addr:full":"Chauss\u00c9e De Mont St.jean 120 Braine-l'alleud Brabant Wallon 1420",
    "addr:housenumber":"120",
    "addr:postcode":"1420",
    "addr:street":"Chausse\u0301E De Mont St.Jean",
    "iso:country":"BE",
    "sg:address":"Chauss\u00c9e De Mont St.jean 120",
    "sg:city":"Braine-l'alleud",
    "sg:orig_category":"Protection civile",
    "sg:phone":"+32 2 385 02 07",
    "sg:postcode":"1420",
    "sg:province":"Brabant Wallon",
    "wof:name":"Corps De Pompiers",
    "wof:placetype":"venue"
},
  "geometry": {"coordinates":[4.9165067673,50.3185577393],"type":"Point"}
}