{
  "type": "Feature",
  "properties": {
    "addr:full":"Luchthaven Gebouw 119b3 Steenokkerzeel Vlaams-Brabant 1820",
    "addr:postcode":"1820",
    "addr:street":"Vlaams-Brabant",
    "iso:country":"BE",
    "sg:address":"Luchthaven Gebouw 119b3",
    "sg:city":"Steenokkerzeel",
    "sg:orig_category":"Ecoles de pilotage de bateaux and d\u00b4avions",
    "sg:phone":"+32 2 752 94 30",
    "sg:postcode":"1820",
    "sg:province":"Vlaams-Brabant",
    "wof:name":"Schreiner Fsc Belgium",
    "wof:placetype":"venue"
},
  "geometry": {"coordinates":[4.5128650665,50.9095802307],"type":"Point"}
}