{
  "type": "Feature",
  "properties": {
    "iso:country":"BE",
    "sg:address":"Avenue De La Sarriette 88",
    "sg:city":"Brussel/bruxelles",
    "sg:orig_category":"Enseignement secondaire g\u00e9n\u00e9ral",
    "sg:phone":"+32 2 262 08 91",
    "sg:postcode":"1020",
    "sg:province":"Bruxelles-Capitale",
    "wof:name":"Atheneum Karel Buls",
    "wof:placetype":"venue"
},
  "geometry": {"coordinates":[4.3690581322,50.8964424133],"type":"Point"}
}