{
  "type": "Feature",
  "properties": {
    "iso:country":"BE",
    "sg:address":"Brugsestraat 62",
    "sg:city":"Oostkamp",
    "sg:classifiers":[
        {
            "category":"Home & Garden",
            "subcategory":"Carpets & Floor Coverings",
            "type":"Retail Goods"
        }
    ],
    "sg:phone":"+32 50 84 06 65",
    "sg:postcode":"8020",
    "sg:province":"West-Vlaanderen",
    "sg:tags":[
        "parquet"
    ],
    "wof:name":"Willton Bvba",
    "wof:placetype":"venue"
},
  "geometry": {"coordinates":[3.2359569073,51.1583175659],"type":"Point"}
}