{
  "type": "Feature",
  "properties": {
    "addr:full":"Doelstraat 13 Box 1 Herk-de-stad Limburg 3540",
    "addr:housenumber":"13;1",
    "addr:postcode":"3540",
    "addr:street":"Doelstraat;Box",
    "iso:country":"BE",
    "sg:address":"Doelstraat 13 Box 1",
    "sg:city":"Herk-de-stad",
    "sg:classifiers":[
        {
            "category":"Farming",
            "subcategory":"Fish & Marine Products",
            "type":"Manufacturing & Wholesale Goods"
        }
    ],
    "sg:phone":"+32 13 52 17 78",
    "sg:postcode":"3540",
    "sg:province":"Limburg",
    "sg:tags":[
        "equipment",
        "fishery"
    ],
    "wof:name":"Vissersclub Ter Doelen",
    "wof:placetype":"venue"
},
  "geometry": {"coordinates":[5.1722621918,50.9414978027],"type":"Point"}
}