{
  "type": "Feature",
  "properties": {
    "addr:full":"Ambachtstraat 3 Oud-turnhout Antwerpen 2360",
    "addr:housenumber":"3",
    "addr:postcode":"2360",
    "addr:street":"Ambachtstraat",
    "iso:country":"BE",
    "sg:address":"Ambachtstraat 3",
    "sg:city":"Oud-turnhout",
    "sg:classifiers":[
        {
            "category":"Home & Garden",
            "subcategory":"Hardware",
            "type":"Retail Goods"
        }
    ],
    "sg:phone":"+32 14 45 02 21",
    "sg:postcode":"2360",
    "sg:province":"Antwerpen",
    "sg:tags":[
        "equipment",
        "woodworking",
        "machinery"
    ],
    "wof:name":"Soethoudt Bvba",
    "wof:placetype":"venue"
},
  "geometry": {"coordinates":[4.9689397812,51.3257484436],"type":"Point"}
}