{
  "type": "Feature",
  "properties": {
    "iso:country":"BE",
    "sg:address":"Sint-jansplein 59",
    "sg:city":"Antwerpen",
    "sg:classifiers":[
        {
            "category":"Cafe",
            "type":"Food & Drink"
        }
    ],
    "sg:phone":"+32 3 232 01 50",
    "sg:postcode":"2060",
    "sg:province":"Antwerpen",
    "sg:tags":[
        "caf\u00e9s"
    ],
    "wof:name":"Caf\u00c9 't Wapperke",
    "wof:placetype":"venue"
},
  "geometry": {"coordinates":[4.4165868759,51.2254867554],"type":"Point"}
}