{
  "type": "Feature",
  "properties": {
    "addr:full":"Rue Des Chasseurs Ardennais Parc Scientifique Du Sart-tilman Angleur Li\u00e8ge 4031",
    "addr:postcode":"4031",
    "addr:street":"Rue Des Chasseurs Ardennais Parc Scientifique Du Sart-Tilman",
    "iso:country":"BE",
    "sg:address":"Rue Des Chasseurs Ardennais Parc Scientifique Du Sart-tilman",
    "sg:city":"Angleur",
    "sg:classifiers":[
        {
            "category":"Professional",
            "subcategory":"Computer Services",
            "type":"Services"
        }
    ],
    "sg:phone":"+32 4 361 81 11",
    "sg:postcode":"4031",
    "sg:province":"Li\u00e8ge",
    "sg:tags":[
        "information",
        "technology",
        "software"
    ],
    "wof:name":"Spacebel S.a.",
    "wof:placetype":"venue"
},
  "geometry": {"coordinates":[5.599583149,50.6115036011],"type":"Point"}
}