{
  "type": "Feature",
  "properties": {
    "addr:full":"Kortrijksesteenweg 59 Deinze (petegem-aan-de-leie) Oost-Vlaanderen 9800",
    "addr:housenumber":"59",
    "addr:postcode":"9800",
    "addr:street":"Kortrijksesteenweg;Oost-Vlaanderen",
    "iso:country":"BE",
    "sg:address":"Kortrijksesteenweg 59",
    "sg:city":"Deinze (petegem-aan-de-leie)",
    "sg:orig_category":"Non-Classified Establishments",
    "sg:phone":"+32 9 386 48 41",
    "sg:postcode":"9800",
    "sg:province":"Oost-Vlaanderen",
    "wof:name":"Chanterie Schaubroeck Nv",
    "wof:placetype":"venue"
},
  "geometry": {"coordinates":[3.5288000107,50.9781837463],"type":"Point"}
}