{
  "type": "Feature",
  "properties": {
    "addr:full":"Maarschalk Frenchlaan 21 Ieper West-Vlaanderen 8900",
    "addr:housenumber":"21",
    "addr:postcode":"8900",
    "addr:street":"Maarschalk Frenchlaan",
    "iso:country":"BE",
    "sg:address":"Maarschalk Frenchlaan 21",
    "sg:city":"Ieper",
    "sg:classifiers":[
        {
            "category":"Health Services",
            "subcategory":"Dentist",
            "type":"Services"
        }
    ],
    "sg:phone":"+32 57 21 94 18",
    "sg:postcode":"8900",
    "sg:province":"West-Vlaanderen",
    "wof:name":"Van Moer Carine",
    "wof:placetype":"venue"
},
  "geometry": {"coordinates":[2.8930668831,50.8527107239],"type":"Point"}
}