{
  "type": "Feature",
  "properties": {
    "addr:full":"Hoogveld 9 Avelgem West-Vlaanderen 8580",
    "addr:housenumber":"9",
    "addr:postcode":"8580",
    "addr:street":"Hoogveld",
    "iso:country":"BE",
    "sg:address":"Hoogveld 9",
    "sg:city":"Avelgem",
    "sg:classifiers":[
        {
            "category":"Arena",
            "subcategory":"Sports Club",
            "type":"Entertainment"
        }
    ],
    "sg:phone":"+32 56 64 72 40",
    "sg:postcode":"8580",
    "sg:province":"West-Vlaanderen",
    "sg:tags":[
        "de"
    ],
    "wof:name":"Bbc Scheldeburcht Avelgem",
    "wof:placetype":"venue"
},
  "geometry": {"coordinates":[3.4332449436,50.7771453857],"type":"Point"}
}