{
  "type": "Feature",
  "properties": {
    "addr:full":"Varendriesstraat 19 Gent Oost-Vlaanderen 9031",
    "addr:housenumber":"19",
    "addr:postcode":"9031",
    "addr:street":"Varendriesstraat;Oost-Vlaanderen",
    "iso:country":"BE",
    "sg:address":"Varendriesstraat 19",
    "sg:city":"Gent",
    "sg:orig_category":"Diverse persoonlijke diensten",
    "sg:phone":"+32 9 226 80 25",
    "sg:postcode":"9031",
    "sg:province":"Oost-Vlaanderen",
    "wof:name":"De Deyne-henderickx",
    "wof:placetype":"venue"
},
  "geometry": {"coordinates":[3.6300549507,51.0467147827],"type":"Point"}
}