{
  "type": "Feature",
  "properties": {
    "addr:full":"Rue Des Etangs Noirs 3 Sint-jans-molenbeek/molenbeek-saint-jean Bruxelles-Capitale 1080",
    "addr:housenumber":"3",
    "addr:postcode":"1080",
    "addr:street":"Rue Des Etangs Noirs",
    "iso:country":"BE",
    "sg:address":"Rue Des Etangs Noirs 3",
    "sg:city":"Sint-jans-molenbeek/molenbeek-saint-jean",
    "sg:orig_category":"Banques and organismes de cr\u00e9dit",
    "sg:phone":"+32 2 411 59 69",
    "sg:postcode":"1080",
    "sg:province":"Bruxelles-Capitale",
    "wof:name":"Dexia",
    "wof:placetype":"venue"
},
  "geometry": {"coordinates":[4.3324131966,50.85704422],"type":"Point"}
}