{
  "type": "Feature",
  "properties": {
    "iso:country":"BE",
    "sg:address":"Orbanlaan 73",
    "sg:city":"Sint-pieters-woluwe/woluwe-saint-pierre",
    "sg:orig_category":"Algemeen secundair onderwijs Kleuter- en basisonderwijs",
    "sg:phone":"+32 2 770 32 50",
    "sg:postcode":"1150",
    "sg:province":"Bruxelles-Capitale",
    "wof:name":"Ecole Fondamentale",
    "wof:placetype":"venue"
},
  "geometry": {"coordinates":[4.4559831619,50.8341293335],"type":"Point"}
}