{
  "type": "Feature",
  "properties": {
    "iso:country":"BE",
    "sg:address":"Stationsstraat 109ba",
    "sg:city":"Eeklo",
    "sg:classifiers":[
        {
            "category":"Fast Food",
            "type":"Food & Drink"
        }
    ],
    "sg:phone":"+32 9 377 80 02",
    "sg:postcode":"9900",
    "sg:province":"Oost-Vlaanderen",
    "sg:tags":[
        "\u00c0",
        "emporter",
        "restaurants"
    ],
    "wof:name":"Frituur Over D'ijzers",
    "wof:placetype":"venue"
},
  "geometry": {"coordinates":[3.5732140541,51.1821517944],"type":"Point"}
}