{
  "type": "Feature",
  "properties": {
    "iso:country":"BE",
    "sg:address":"Rue De Montainpr\u00c9 27-29",
    "sg:city":"Rochefort",
    "sg:classifiers":[
        {
            "category":"Travel",
            "subcategory":"Hotels & Motels",
            "type":"Entertainment"
        }
    ],
    "sg:phone":"+32 84 37 84 05",
    "sg:postcode":"5580",
    "sg:province":"Namur",
    "sg:tags":[
        "restaurant"
    ],
    "wof:name":"H\u00d4tel Chateau De Vign\u00c9e",
    "wof:placetype":"venue"
},
  "geometry": {"coordinates":[5.074406147,50.1585922241],"type":"Point"}
}