{
  "type": "Feature",
  "properties": {
    "addr:full":"Rue Des Alli\u00c9s 264 Vorst/forest Bruxelles-Capitale 1190",
    "addr:housenumber":"264",
    "addr:postcode":"1190",
    "addr:street":"Rue Des Allie\u0301S;/ Forest",
    "iso:country":"BE",
    "sg:address":"Rue Des Alli\u00c9s 264",
    "sg:city":"Vorst/forest",
    "sg:orig_category":"M\u00e9decins and sp\u00e9cialistes",
    "sg:phone":"+32 2 346 60 81",
    "sg:postcode":"1190",
    "sg:province":"Bruxelles-Capitale",
    "wof:name":"Kathia Zylberberg",
    "wof:placetype":"venue"
},
  "geometry": {"coordinates":[4.3272137642,50.8221702576],"type":"Point"}
}