{
  "type": "Feature",
  "properties": {
    "addr:full":"Wibertusstraat 6 Westerlo Antwerpen 2260",
    "addr:housenumber":"6",
    "addr:postcode":"2260",
    "addr:street":"Wibertusstraat",
    "iso:country":"BE",
    "sg:address":"Wibertusstraat 6",
    "sg:city":"Westerlo",
    "sg:classifiers":[
        {
            "category":"Manufacturing",
            "subcategory":"Soap",
            "type":"Manufacturing & Wholesale Goods"
        }
    ],
    "sg:phone":"+32 14 54 79 39",
    "sg:postcode":"2260",
    "sg:province":"Antwerpen",
    "sg:tags":[
        "product",
        "bath"
    ],
    "wof:name":"Bie Dauwen Cosmetics",
    "wof:placetype":"venue"
},
  "geometry": {"coordinates":[4.8990502357,51.1021537781],"type":"Point"}
}