{
  "type": "Feature",
  "properties": {
    "addr:full":"Grote Baan 525 Houthalen-helchteren (houthalen) Limburg 3530",
    "addr:housenumber":"525",
    "addr:postcode":"3530",
    "addr:street":"Grote Baan",
    "iso:country":"BE",
    "sg:address":"Grote Baan 525",
    "sg:city":"Houthalen-helchteren (houthalen)",
    "sg:classifiers":[
        {
            "category":"Professional",
            "subcategory":"Art Services",
            "type":"Services"
        }
    ],
    "sg:phone":"+32 475 24 13 98",
    "sg:postcode":"3530",
    "sg:province":"Limburg",
    "sg:tags":[
        "automobile",
        "transit",
        "-",
        "export",
        "import"
    ],
    "wof:name":"Inpra-cars Bvba",
    "wof:placetype":"venue"
},
  "geometry": {"coordinates":[5.3800802231,51.0446815491],"type":"Point"}
}