{
  "type": "Feature",
  "properties": {
    "addr:full":"Schali\u00ebnhoevedreef 1b Box 1 Mechelen Antwerpen 2800",
    "addr:housenumber":"1b;1",
    "addr:postcode":"2800",
    "addr:street":"Schalie\u0308Nhoevedreef;Box",
    "iso:country":"BE",
    "sg:address":"Schali\u00ebnhoevedreef 1b Box 1",
    "sg:city":"Mechelen",
    "sg:classifiers":[
        {
            "category":"Communications",
            "type":"Services"
        }
    ],
    "sg:phone":"+32 15 28 38 20",
    "sg:postcode":"2800",
    "sg:province":"Antwerpen",
    "sg:tags":[
        "radio",
        "television",
        "broadcasting",
        "-"
    ],
    "wof:name":"Tmf (the Music Factory)",
    "wof:placetype":"venue"
},
  "geometry": {"coordinates":[4.4625988007,51.0555458069],"type":"Point"}
}