{
  "type": "Feature",
  "properties": {
    "addr:full":"Rue Du Commerce 22 Bruxelles Bruxelles-Capitale 1000",
    "addr:housenumber":"22",
    "addr:postcode":"1000",
    "addr:street":"Rue Du Commerce",
    "iso:country":"BE",
    "sg:address":"Rue Du Commerce 22",
    "sg:city":"Bruxelles",
    "sg:classifiers":[
        {
            "category":"Organizations",
            "subcategory":"Non-profit Organization",
            "type":"Services"
        }
    ],
    "sg:phone":"+32 2 500 10 20",
    "sg:postcode":"1000",
    "sg:province":"Bruxelles-Capitale",
    "sg:tags":[
        "international",
        "organisation"
    ],
    "wof:name":"Solidar Association",
    "wof:placetype":"venue"
},
  "geometry": {"coordinates":[4.3673019409,50.8401374817],"type":"Point"}
}