{
  "type": "Feature",
  "properties": {
    "addr:full":"Steenweg 19 Asse Vlaams-Brabant 1730",
    "addr:housenumber":"19",
    "addr:postcode":"1730",
    "addr:street":"Steenweg",
    "iso:country":"BE",
    "sg:address":"Steenweg 19",
    "sg:city":"Asse",
    "sg:orig_category":"Agences de presse",
    "sg:phone":"+32 2 453 99 09",
    "sg:postcode":"1730",
    "sg:province":"Vlaams-Brabant",
    "wof:name":"Wim De Smet",
    "wof:placetype":"venue"
},
  "geometry": {"coordinates":[4.1981220245,50.9109268188],"type":"Point"}
}