{
  "type": "Feature",
  "properties": {
    "addr:full":"Rue Du Tienne De Mont 2 Yvoir (godinne) Namur 5530",
    "addr:housenumber":"2",
    "addr:postcode":"5530",
    "addr:street":"Rue Du Tienne De Mont",
    "iso:country":"BE",
    "sg:address":"Rue Du Tienne De Mont 2",
    "sg:city":"Yvoir (godinne)",
    "sg:classifiers":[
        {
            "category":"Building & Trades",
            "subcategory":"Landscaping Services",
            "type":"Services"
        }
    ],
    "sg:phone":"+32 81 41 13 57",
    "sg:postcode":"5530",
    "sg:province":"Namur",
    "sg:tags":[
        "gardening",
        "garden",
        "maintenance"
    ],
    "wof:name":"Boden G",
    "wof:placetype":"venue"
},
  "geometry": {"coordinates":[4.8832740784,50.3523368835],"type":"Point"}
}