{
  "type": "Feature",
  "properties": {
    "iso:country":"BE",
    "sg:address":"Kanaalstraat 9",
    "sg:city":"Lier",
    "sg:classifiers":[
        {
            "category":"Personal",
            "subcategory":"Beauty Salon",
            "type":"Services"
        }
    ],
    "sg:phone":"+32 3 480 71 29",
    "sg:postcode":"2500",
    "sg:province":"Antwerpen",
    "sg:tags":[
        "de",
        "coiffure"
    ],
    "wof:name":"Coiffure Myriam",
    "wof:placetype":"venue"
},
  "geometry": {"coordinates":[4.5888109207,51.1326789856],"type":"Point"}
}