{
  "type": "Feature",
  "properties": {
    "iso:country":"BE",
    "sg:address":"Turnhoutsebaan 37",
    "sg:city":"Malle (oostmalle)",
    "sg:classifiers":[
        {
            "category":"Shopping",
            "subcategory":"Crafts & Fabrics",
            "type":"Retail Goods"
        }
    ],
    "sg:phone":"+32 3 311 71 31",
    "sg:postcode":"2390",
    "sg:province":"Antwerpen",
    "sg:tags":[
        "silk",
        "-"
    ],
    "wof:name":"Kris Kras Kinderstoffen",
    "wof:placetype":"venue"
},
  "geometry": {"coordinates":[4.7356147766,51.3014526367],"type":"Point"}
}