{
  "type": "Feature",
  "properties": {
    "iso:country":"BE",
    "sg:address":"Truweelstraat 33",
    "sg:city":"Sint-niklaas",
    "sg:orig_category":"Boekhouders",
    "sg:phone":"+32 3 776 70 66",
    "sg:postcode":"9100",
    "sg:province":"Oost-Vlaanderen",
    "wof:name":"Romain Van Der Heyden",
    "wof:placetype":"venue"
},
  "geometry": {"coordinates":[4.1491241455,51.1692504883],"type":"Point"}
}