{
  "type": "Feature",
  "properties": {
    "iso:country":"BE",
    "sg:address":"Vlaschaardlaan 20",
    "sg:city":"Ledegem",
    "sg:orig_category":"Experts-comptables",
    "sg:phone":"+32 56 50 07 29",
    "sg:postcode":"8880",
    "sg:province":"West-Vlaanderen",
    "wof:name":"Jean-pierre Depoortere",
    "wof:placetype":"venue"
},
  "geometry": {"coordinates":[3.1781270504,50.8709869385],"type":"Point"}
}