{
  "type": "Feature",
  "properties": {
    "iso:country":"BE",
    "sg:address":"Nisramont 46",
    "sg:city":"La Roche-en-ardenne",
    "sg:classifiers":[
        {
            "category":"Fast Food",
            "type":"Food & Drink"
        }
    ],
    "sg:phone":"+32 84 43 34 23",
    "sg:postcode":"6983",
    "sg:province":"Luxembourg",
    "sg:tags":[
        "meeneem",
        "restaurant"
    ],
    "wof:name":"Friterie Du H\u00c9rou",
    "wof:placetype":"venue"
},
  "geometry": {"coordinates":[5.6033000946,50.1450004578],"type":"Point"}
}