{
  "type": "Feature",
  "properties": {
    "iso:country":"BE",
    "sg:address":"Rue Royale 65",
    "sg:city":"Peruwelz",
    "sg:orig_category":"Plaatsen van vloer- and muurbekleding Schilders",
    "sg:phone":"+32 69 77 40 61",
    "sg:postcode":"7603",
    "sg:province":"Hainaut",
    "wof:name":"Leimbach & Fils",
    "wof:placetype":"venue"
},
  "geometry": {"coordinates":[3.6134090424,50.5000991821],"type":"Point"}
}