{
  "type": "Feature",
  "properties": {
    "iso:country":"BE",
    "sg:address":"Rue Neuve 58",
    "sg:city":"Courcelles (souvret)",
    "sg:classifiers":[
        {
            "category":"Bakery",
            "type":"Food & Drink"
        }
    ],
    "sg:phone":"+32 71 45 29 58",
    "sg:postcode":"6182",
    "sg:province":"Hainaut",
    "sg:tags":[
        "confectioner",
        "baker"
    ],
    "wof:name":"Delattre Boulangerie",
    "wof:placetype":"venue"
},
  "geometry": {"coordinates":[4.3458662033,50.4440956116],"type":"Point"}
}