{
  "type": "Feature",
  "properties": {
    "iso:country":"BE",
    "sg:address":"Rue De Gosselies 1",
    "sg:city":"Courcelles (trazegnies)",
    "sg:classifiers":[
        {
            "category":"Shopping",
            "subcategory":"Florist",
            "type":"Retail Goods"
        }
    ],
    "sg:phone":"+32 71 46 33 13",
    "sg:postcode":"6183",
    "sg:province":"Hainaut",
    "wof:name":"Collard Jo\u00eblle",
    "wof:placetype":"venue"
},
  "geometry": {"coordinates":[4.3439102173,50.4629707336],"type":"Point"}
}