{
  "type": "Feature",
  "properties": {
    "iso:country":"BE",
    "sg:address":"Rue De La Passerelle 12-14",
    "sg:city":"Bouillon",
    "sg:orig_category":"Maisons de vacances",
    "sg:phone":"+32 2 453 91 38",
    "sg:postcode":"6830",
    "sg:province":"Luxembourg",
    "wof:name":"R.bresseleers",
    "wof:placetype":"venue"
},
  "geometry": {"coordinates":[5.0699849129,49.7954597473],"type":"Point"}
}