{
  "type": "Feature",
  "properties": {
    "iso:country":"BE",
    "sg:address":"Route Du Viroin 15",
    "sg:city":"Viroinval (olloy-sur-viroin)",
    "sg:classifiers":[
        {
            "category":"Building & Trades",
            "subcategory":"Electrical",
            "type":"Services"
        }
    ],
    "sg:phone":"+32 60 39 02 07",
    "sg:postcode":"5670",
    "sg:province":"Namur",
    "sg:tags":[
        "electric",
        "-",
        "housewiring",
        "contractor"
    ],
    "wof:name":"Michel J-p",
    "wof:placetype":"venue"
},
  "geometry": {"coordinates":[4.5839939117,50.0706100464],"type":"Point"}
}