{
  "type": "Feature",
  "properties": {
    "addr:full":"Kerkstraat 5 Lanaken Limburg 3620",
    "addr:housenumber":"5",
    "addr:postcode":"3620",
    "addr:street":"Kerkstraat",
    "iso:country":"BE",
    "sg:address":"Kerkstraat 5",
    "sg:city":"Lanaken",
    "sg:classifiers":[
        {
            "category":"Insurance",
            "subcategory":"Life Insurance",
            "type":"Services"
        }
    ],
    "sg:phone":"+32 89 72 23 88",
    "sg:postcode":"3620",
    "sg:province":"Limburg",
    "sg:tags":[
        "assurance"
    ],
    "wof:name":"Axa",
    "wof:placetype":"venue"
},
  "geometry": {"coordinates":[5.6336631775,50.8638496399],"type":"Point"}
}