{
  "type": "Feature",
  "properties": {
    "iso:country":"BE",
    "sg:address":"Vianderstraat 30",
    "sg:city":"Tienen",
    "sg:orig_category":"Drukkerijen and copyshops",
    "sg:phone":"+32 16 81 22 62",
    "sg:postcode":"3300",
    "sg:province":"Vlaams-Brabant",
    "wof:name":"Drukkerij Gova",
    "wof:placetype":"venue"
},
  "geometry": {"coordinates":[4.9449877739,50.8131065369],"type":"Point"}
}