{
  "type": "Feature",
  "properties": {
    "iso:country":"BE",
    "sg:address":"Rue De La Station 76",
    "sg:city":"Charleroi",
    "sg:orig_category":"Blanchisseries and teintureries",
    "sg:phone":"+32 71 35 29 44",
    "sg:postcode":"6040",
    "sg:province":"Hainaut",
    "wof:name":"Pressing De La Station",
    "wof:placetype":"venue"
},
  "geometry": {"coordinates":[4.4331159592,50.4408454895],"type":"Point"}
}