{
  "type": "Feature",
  "properties": {
    "iso:country":"BE",
    "sg:address":"Drapstraat 15",
    "sg:city":"Aalst (gijzegem)",
    "sg:classifiers":[
        {
            "category":"Building & Trades",
            "subcategory":"Construction",
            "type":"Services"
        }
    ],
    "sg:phone":"+32 53 78 62 89",
    "sg:postcode":"9308",
    "sg:province":"Oost-Vlaanderen",
    "sg:tags":[
        "installation",
        "-",
        "central",
        "heating"
    ],
    "wof:name":"All-round",
    "wof:placetype":"venue"
},
  "geometry": {"coordinates":[4.0378041267,50.9816398621],"type":"Point"}
}