{
  "type": "Feature",
  "properties": {
    "iso:country":"BE",
    "sg:address":"Solterweg 34",
    "sg:city":"Bree",
    "sg:orig_category":"Rundveehouders",
    "sg:phone":"+32 89 86 75 29",
    "sg:postcode":"3960",
    "sg:province":"Limburg",
    "wof:name":"Rudi Thaens",
    "wof:placetype":"venue"
},
  "geometry": {"coordinates":[5.6640901566,51.1222991943],"type":"Point"}
}