{
  "type": "Feature",
  "properties": {
    "iso:country":"BE",
    "sg:address":"Oud-strijderslaan 5bw2",
    "sg:city":"Lokeren",
    "sg:orig_category":"Herstellingen and onderhoud van auto's",
    "sg:phone":"+32 9 348 40 79",
    "sg:postcode":"9160",
    "sg:province":"Oost-Vlaanderen",
    "wof:name":"Carr. Van Puymbroeck",
    "wof:placetype":"venue"
},
  "geometry": {"coordinates":[3.9959468842,51.1036109924],"type":"Point"}
}