{
  "type": "Feature",
  "properties": {
    "iso:country":"BE",
    "sg:address":"Ter Stratenweg 14",
    "sg:city":"Ranst (oelegem)",
    "sg:classifiers":[
        {
            "category":"Manufacturing",
            "subcategory":"Rubber & Plastics",
            "type":"Manufacturing & Wholesale Goods"
        }
    ],
    "sg:phone":"+32 3 470 13 90",
    "sg:postcode":"2520",
    "sg:province":"Antwerpen",
    "sg:tags":[
        "hose"
    ],
    "wof:name":"Philippe Jans Nv",
    "wof:placetype":"venue"
},
  "geometry": {"coordinates":[4.5856342316,51.2073631287],"type":"Point"}
}