{
  "type": "Feature",
  "properties": {
    "iso:country":"BE",
    "sg:address":"Pottelberg 158",
    "sg:city":"Kortrijk (marke)",
    "sg:classifiers":[
        {
            "category":"Personal",
            "subcategory":"Beauty Salon",
            "type":"Services"
        }
    ],
    "sg:phone":"+32 56 21 36 97",
    "sg:postcode":"8510",
    "sg:province":"West-Vlaanderen",
    "sg:tags":[
        "lady",
        "-",
        "hairdressing"
    ],
    "wof:name":"Lutgart",
    "wof:placetype":"venue"
},
  "geometry": {"coordinates":[3.2333650589,50.8071060181],"type":"Point"}
}