{
  "type": "Feature",
  "properties": {
    "iso:country":"BE",
    "sg:address":"Rue Du Routy 8",
    "sg:city":"Florenville (lacuisine)",
    "sg:classifiers":[
        {
            "category":"Health Services",
            "subcategory":"Hospital",
            "type":"Services"
        }
    ],
    "sg:phone":"+32 61 31 50 80",
    "sg:postcode":"6821",
    "sg:province":"Luxembourg",
    "sg:tags":[
        "ambulance"
    ],
    "wof:name":"Vehicule Sanitaire Leger De La Croix Rouge",
    "wof:placetype":"venue"
},
  "geometry": {"coordinates":[5.314166069,49.723400116],"type":"Point"}
}