{
  "type": "Feature",
  "properties": {
    "addr:full":"Strooistraat 45 Meise Vlaams-Brabant 1860",
    "addr:housenumber":"45",
    "addr:postcode":"1860",
    "addr:street":"Strooistraat",
    "iso:country":"BE",
    "sg:address":"Strooistraat 45",
    "sg:city":"Meise",
    "sg:orig_category":"Producteurs de l\u00e9gumes",
    "sg:phone":"+32 2 269 23 28",
    "sg:postcode":"1860",
    "sg:province":"Vlaams-Brabant",
    "wof:name":"Jan Stallaert",
    "wof:placetype":"venue"
},
  "geometry": {"coordinates":[4.3056411743,50.9348678589],"type":"Point"}
}