{
  "type": "Feature",
  "properties": {
    "iso:country":"BE",
    "sg:address":"Place Du Man\u00e8ge 10",
    "sg:city":"Charleroi",
    "sg:classifiers":[
        {
            "category":"Fast Food",
            "type":"Food & Drink"
        }
    ],
    "sg:phone":"+32 71 31 54 32",
    "sg:postcode":"6000",
    "sg:province":"Hainaut",
    "sg:tags":[
        "fried",
        "stand",
        "potato"
    ],
    "wof:name":"Pippo (chez)",
    "wof:placetype":"venue"
},
  "geometry": {"coordinates":[4.4440331459,50.412853241],"type":"Point"}
}