{
  "type": "Feature",
  "properties": {
    "iso:country":"BE",
    "sg:address":"Rue Saint-antoine 76",
    "sg:city":"Pont-a-celles",
    "sg:classifiers":[
        {
            "category":"Autos & Motor Vehicles",
            "subcategory":"Fuel & Gas Station",
            "type":"Retail Goods"
        }
    ],
    "sg:phone":"+32 71 84 52 74",
    "sg:postcode":"6230",
    "sg:province":"Hainaut",
    "sg:tags":[
        "stations-service",
        "carburants"
    ],
    "wof:name":"Ets. Neirynck & Fils",
    "wof:placetype":"venue"
},
  "geometry": {"coordinates":[4.3441729546,50.5014648438],"type":"Point"}
}