{
  "type": "Feature",
  "properties": {
    "addr:full":"Val Du Ch\u00c2teau 9 Herstal Li\u00e8ge 4040",
    "addr:housenumber":"9",
    "addr:postcode":"4040",
    "addr:street":"Val Du Cha\u0302Teau",
    "iso:country":"BE",
    "sg:address":"Val Du Ch\u00c2teau 9",
    "sg:city":"Herstal",
    "sg:orig_category":"Promoteurs immobiliers. Evaluation and estimation de biens immobiliers. Agences immobili\u00e8res",
    "sg:phone":"+32 4 264 44 27",
    "sg:postcode":"4040",
    "sg:province":"Li\u00e8ge",
    "wof:name":"Indimmo",
    "wof:placetype":"venue"
},
  "geometry": {"coordinates":[5.6021389961,50.6706123352],"type":"Point"}
}