{
  "type": "Feature",
  "properties": {
    "iso:country":"BE",
    "sg:address":"Pieter Coeckestraat 56",
    "sg:city":"Aalst",
    "sg:orig_category":"Rainwear",
    "sg:phone":"+32 53 21 14 70",
    "sg:postcode":"9300",
    "sg:province":"Oost-Vlaanderen",
    "wof:name":"R.v. Camping",
    "wof:placetype":"venue"
},
  "geometry": {"coordinates":[4.032834053,50.9433517456],"type":"Point"}
}