{
  "type": "Feature",
  "properties": {
    "iso:country":"BE",
    "sg:address":"Oudergemselaan 124",
    "sg:city":"Etterbeek",
    "sg:orig_category":"Sportclubs",
    "sg:phone":"+32 2 640 17 30",
    "sg:postcode":"1040",
    "sg:province":"Bruxelles-Capitale",
    "wof:name":"Etterbeekse Tennisclub",
    "wof:placetype":"venue"
},
  "geometry": {"coordinates":[4.3868288994,50.8372612],"type":"Point"}
}