{
  "type": "Feature",
  "properties": {
    "addr:full":"Voorstraat 12 Kortrijk West-Vlaanderen 8500",
    "addr:housenumber":"12",
    "addr:postcode":"8500",
    "addr:street":"Voorstraat",
    "iso:country":"BE",
    "sg:address":"Voorstraat 12",
    "sg:city":"Kortrijk",
    "sg:orig_category":"Antiek",
    "sg:phone":"+32 56 21 01 02",
    "sg:postcode":"8500",
    "sg:province":"West-Vlaanderen",
    "wof:name":"Epoque Fine Jewels",
    "wof:placetype":"venue"
},
  "geometry": {"coordinates":[3.2711229324,50.827545166],"type":"Point"}
}