{
  "type": "Feature",
  "properties": {
    "addr:full":"Sint-guidostraat 7 Anderlecht Bruxelles-Capitale 1070",
    "addr:housenumber":"7",
    "addr:postcode":"1070",
    "addr:street":"Sint-Guidostraat",
    "iso:country":"BE",
    "sg:address":"Sint-guidostraat 7",
    "sg:city":"Anderlecht",
    "sg:orig_category":"Brood, gebak and snoepgoed",
    "sg:phone":"+32 2 523 25 25",
    "sg:postcode":"1070",
    "sg:province":"Bruxelles-Capitale",
    "wof:name":"Maison Aramis",
    "wof:placetype":"venue"
},
  "geometry": {"coordinates":[4.3058681488,50.8351135254],"type":"Point"}
}