{
  "type": "Feature",
  "properties": {
    "iso:country":"BE",
    "sg:address":"Oostvaartdijk 309",
    "sg:city":"Grimbergen (humbeek)",
    "sg:classifiers":[
        {
            "category":"Professional",
            "subcategory":"Employment Agencies",
            "type":"Services"
        }
    ],
    "sg:phone":"+32 2 306 30 30",
    "sg:postcode":"1851",
    "sg:province":"Vlaams-Brabant",
    "sg:tags":[
        "-",
        "processing",
        "data"
    ],
    "wof:name":"D-trix",
    "wof:placetype":"venue"
},
  "geometry": {"coordinates":[4.3950147629,50.9734916687],"type":"Point"}
}