{
  "type": "Feature",
  "properties": {
    "addr:full":"Rue De La Dr\u00e8ve 26 Mons (ghlin) Hainaut 7011",
    "addr:housenumber":"26",
    "addr:postcode":"7011",
    "addr:street":"Rue De La Dre\u0300Ve",
    "iso:country":"BE",
    "sg:address":"Rue De La Dr\u00e8ve 26",
    "sg:city":"Mons (ghlin)",
    "sg:classifiers":[
        {
            "category":"Health Services",
            "subcategory":"Health Practitioner",
            "type":"Services"
        }
    ],
    "sg:phone":"+32 65 31 61 41",
    "sg:postcode":"7011",
    "sg:province":"Hainaut",
    "sg:tags":[
        "therapist",
        "speech"
    ],
    "wof:name":"Caudron A",
    "wof:placetype":"venue"
},
  "geometry": {"coordinates":[3.912539959,50.4712982178],"type":"Point"}
}