{
  "type": "Feature",
  "properties": {
    "addr:full":"Stationsstraat 61 Aalter Oost-Vlaanderen 9880",
    "addr:housenumber":"61",
    "addr:postcode":"9880",
    "addr:street":"Stationsstraat",
    "iso:country":"BE",
    "sg:address":"Stationsstraat 61",
    "sg:city":"Aalter",
    "sg:orig_category":"Randstad",
    "sg:phone":"+32 9 325 77 90",
    "sg:postcode":"9880",
    "sg:province":"Oost-Vlaanderen",
    "wof:name":"Randstad",
    "wof:placetype":"venue"
},
  "geometry": {"coordinates":[3.4480500221,51.085899353],"type":"Point"}
}