{
  "type": "Feature",
  "properties": {
    "iso:country":"BE",
    "sg:address":"Avenue Provinciale 83-87",
    "sg:city":"Ceroux-mousty",
    "sg:classifiers":[
        {
            "category":"Parking",
            "subcategory":"Lot",
            "type":"Transportation"
        }
    ],
    "sg:phone":"+32 10 61 28 47",
    "sg:postcode":"1341",
    "sg:province":"Brabant Wallon",
    "sg:tags":[
        "parking-places",
        "laying-out"
    ],
    "wof:name":"Melin",
    "wof:placetype":"venue"
},
  "geometry": {"coordinates":[4.5630908012,50.6575469971],"type":"Point"}
}