{
  "type": "Feature",
  "properties": {
    "iso:country":"BE",
    "sg:address":"Chauss\u00c9e De Ninove 150",
    "sg:city":"Sint-jans-molenbeek",
    "sg:orig_category":"Forge, Moulage and Profilage des M\u00e9taux",
    "sg:phone":"+32 2 414 91 21",
    "sg:postcode":"1080",
    "sg:province":"Bruxelles-Capitale",
    "wof:name":"Ateliers Costermans",
    "wof:placetype":"venue"
},
  "geometry": {"coordinates":[4.3256669044,50.8490371704],"type":"Point"}
}