{
  "type": "Feature",
  "properties": {
    "addr:full":"Dr\u00c8ve De Waroux 57 Ans Li\u00e8ge 4432",
    "addr:housenumber":"57",
    "addr:postcode":"4432",
    "addr:street":"Dre\u0300Ve De Waroux",
    "iso:country":"BE",
    "sg:address":"Dr\u00c8ve De Waroux 57",
    "sg:city":"Ans",
    "sg:orig_category":"Experts-comptables",
    "sg:phone":"+32 4 263 37 98",
    "sg:postcode":"4432",
    "sg:province":"Li\u00e8ge",
    "wof:name":"Charles Lambotte",
    "wof:placetype":"venue"
},
  "geometry": {"coordinates":[5.4930419922,50.6798362732],"type":"Point"}
}