{
  "type": "Feature",
  "properties": {
    "iso:country":"BE",
    "sg:address":"Rue Jules Cornet 3",
    "sg:city":"Mons",
    "sg:orig_category":"V\u00eatements",
    "sg:phone":"+32 65 35 45 57",
    "sg:postcode":"7000",
    "sg:province":"Hainaut",
    "wof:name":"Maison Ruelle-neusy",
    "wof:placetype":"venue"
},
  "geometry": {"coordinates":[3.9581620693,50.4628639221],"type":"Point"}
}