{
  "type": "Feature",
  "properties": {
    "addr:full":"Liersesteenweg 224ba Mechelen Antwerpen 2800",
    "addr:housenumber":"224ba",
    "addr:postcode":"2800",
    "addr:street":"Liersesteenweg",
    "iso:country":"BE",
    "sg:address":"Liersesteenweg 224ba",
    "sg:city":"Mechelen",
    "sg:orig_category":"Banques and organismes de cr\u00e9dit",
    "sg:phone":"+32 15 20 35 09",
    "sg:postcode":"2800",
    "sg:province":"Antwerpen",
    "wof:name":"Kbc",
    "wof:placetype":"venue"
},
  "geometry": {"coordinates":[4.4783301353,51.0410766602],"type":"Point"}
}