{
  "type": "Feature",
  "properties": {
    "iso:country":"BE",
    "sg:address":"Rue Des Clercs 29",
    "sg:city":"Mons",
    "sg:classifiers":[
        {
            "category":"Professional",
            "subcategory":"Lawyer & Legal Services",
            "type":"Services"
        }
    ],
    "sg:phone":"+32 65 72 45 90",
    "sg:postcode":"7000",
    "sg:province":"Hainaut",
    "wof:name":"Blondiau Fran\u00e7ois",
    "wof:placetype":"venue"
},
  "geometry": {"coordinates":[3.9498300552,50.4534111023],"type":"Point"}
}