{
  "type": "Feature",
  "properties": {
    "addr:full":"Leuvensesteenweg 526 Zaventem Vlaams-Brabant 1930",
    "addr:housenumber":"526",
    "addr:postcode":"1930",
    "addr:street":"Leuvensesteenweg",
    "iso:country":"BE",
    "sg:address":"Leuvensesteenweg 526",
    "sg:city":"Zaventem",
    "sg:orig_category":"Rubber Bands, Tapes, Strands",
    "sg:phone":"+32 3 324 24 64",
    "sg:postcode":"1930",
    "sg:province":"Vlaams-Brabant",
    "wof:name":"Mutsaers Nv",
    "wof:placetype":"venue"
},
  "geometry": {"coordinates":[4.4711489677,51.2349662781],"type":"Point"}
}