{
  "type": "Feature",
  "properties": {
    "addr:full":"Watermolenstraat 45 Brakel Oost-Vlaanderen 9660",
    "addr:housenumber":"45",
    "addr:postcode":"9660",
    "addr:street":"Watermolenstraat",
    "iso:country":"BE",
    "sg:address":"Watermolenstraat 45",
    "sg:city":"Brakel",
    "sg:orig_category":"Diverse grafische activiteiten",
    "sg:phone":"+32 55 42 42 70",
    "sg:postcode":"9660",
    "sg:province":"Oost-Vlaanderen",
    "wof:name":"Ansfried De Vylder",
    "wof:placetype":"venue"
},
  "geometry": {"coordinates":[3.7702898979,50.808807373],"type":"Point"}
}