{
  "type": "Feature",
  "properties": {
    "iso:country":"BE",
    "sg:address":"Vieux March\u00e9 Aux Poteries 16",
    "sg:city":"Tournai",
    "sg:classifiers":[
        {
            "category":"Banks & Credit Unions",
            "subcategory":"Bank",
            "type":"Services"
        }
    ],
    "sg:phone":"+32 69 21 02 04",
    "sg:postcode":"7500",
    "sg:province":"Hainaut",
    "sg:tags":[
        "savings-banks"
    ],
    "wof:name":"Caisse D'epargne De La Ville De Tournai",
    "wof:placetype":"venue"
},
  "geometry": {"coordinates":[3.3885769844,50.6063232422],"type":"Point"}
}