{
  "type": "Feature",
  "properties": {
    "iso:country":"BE",
    "sg:address":"Oostveld Kouter 195",
    "sg:city":"Lovendegem",
    "sg:orig_category":"Imprimeries and copyshops. Composition and photogravure",
    "sg:phone":"+32 9 372 84 26",
    "sg:postcode":"9920",
    "sg:province":"Oost-Vlaanderen",
    "wof:name":"All Round Screen",
    "wof:placetype":"venue"
},
  "geometry": {"coordinates":[3.6356289387,51.1072273254],"type":"Point"}
}