{
  "type": "Feature",
  "properties": {
    "iso:country":"BE",
    "sg:address":"Rue Berckmans 34b",
    "sg:city":"Bruxelles (saint-gilles)",
    "sg:classifiers":[
        {
            "category":"Retail",
            "subcategory":"Auto Repair",
            "type":"Services"
        }
    ],
    "sg:phone":"+32 2 537 88 10",
    "sg:postcode":"1060",
    "sg:province":"Bruxelles-Capitale",
    "sg:tags":[
        "garage"
    ],
    "wof:name":"Glibert",
    "wof:placetype":"venue"
},
  "geometry": {"coordinates":[4.3557109833,50.8314361572],"type":"Point"}
}