{
  "type": "Feature",
  "properties": {
    "addr:full":"Rozenlaan 29 Zandhoven (pulderbos) Antwerpen 2242",
    "addr:housenumber":"29",
    "addr:postcode":"2242",
    "addr:street":"Rozenlaan",
    "iso:country":"BE",
    "sg:address":"Rozenlaan 29",
    "sg:city":"Zandhoven (pulderbos)",
    "sg:classifiers":[
        {
            "category":"Professional",
            "subcategory":"Computer Services",
            "type":"Services"
        }
    ],
    "sg:phone":"+32 3 297 51 58",
    "sg:postcode":"2242",
    "sg:province":"Antwerpen",
    "sg:tags":[
        "webdesign",
        "-",
        "internet"
    ],
    "wof:name":"Lieckens Web Projects",
    "wof:placetype":"venue"
},
  "geometry": {"coordinates":[4.6967577934,51.2214851379],"type":"Point"}
}