{
  "type": "Feature",
  "properties": {
    "addr:full":"Rue Marcel Cuvelier 6 Leuze-en-hainaut Hainaut 7904",
    "addr:housenumber":"6",
    "addr:postcode":"7904",
    "addr:street":"Rue Marcel Cuvelier",
    "iso:country":"BE",
    "sg:address":"Rue Marcel Cuvelier 6",
    "sg:city":"Leuze-en-hainaut",
    "sg:orig_category":"Apotheken",
    "sg:phone":"+32 69 66 47 97",
    "sg:postcode":"7904",
    "sg:province":"Hainaut",
    "wof:name":"Pharmacie De Pipaix",
    "wof:placetype":"venue"
},
  "geometry": {"coordinates":[3.5815010071,50.5835876465],"type":"Point"}
}