{
  "type": "Feature",
  "properties": {
    "iso:country":"BE",
    "sg:address":"Bruglaan 17",
    "sg:city":"Bree",
    "sg:classifiers":[
        {
            "category":"Insurance",
            "subcategory":"Insurance Agent",
            "type":"Services"
        }
    ],
    "sg:phone":"+32 89 47 37 45",
    "sg:postcode":"3960",
    "sg:province":"Limburg",
    "sg:tags":[
        "broker"
    ],
    "wof:name":"Colson Guy Nv",
    "wof:placetype":"venue"
},
  "geometry": {"coordinates":[5.6084780693,51.142250061],"type":"Point"}
}