{
  "type": "Feature",
  "properties": {
    "addr:full":"Veeweidestraat 111 Anderlecht/anderlecht Bruxelles-Capitale 1070",
    "addr:housenumber":"111",
    "addr:postcode":"1070",
    "addr:street":"Veeweidestraat",
    "iso:country":"BE",
    "sg:address":"Veeweidestraat 111",
    "sg:city":"Anderlecht/anderlecht",
    "sg:orig_category":"Dakwerken Gespecialiseerde residenti\u00eble bouw Industri\u00eble and commerci\u00eble bouw Loodgieterij, verwarmi",
    "sg:phone":"+32 2 520 49 94",
    "sg:postcode":"1070",
    "sg:province":"Bruxelles-Capitale",
    "wof:name":"Giacomo Patteri",
    "wof:placetype":"venue"
},
  "geometry": {"coordinates":[4.3047828674,50.8306121826],"type":"Point"}
}