{
  "type": "Feature",
  "properties": {
    "iso:country":"BE",
    "sg:address":"Boulevard Sainctelette 27",
    "sg:city":"Mons",
    "sg:orig_category":"Belastingconsulenten Diverse juridische dienstverlening",
    "sg:phone":"+32 65 36 11 13",
    "sg:postcode":"7000",
    "sg:province":"Hainaut",
    "wof:name":"Serv.gest. & Informatique",
    "wof:placetype":"venue"
},
  "geometry": {"coordinates":[3.9452280998,50.4466819763],"type":"Point"}
}