{
  "type": "Feature",
  "properties": {
    "addr:full":"Rodenbachstraat 118 Vorst/forest Bruxelles-Capitale 1190",
    "addr:housenumber":"118",
    "addr:postcode":"1190",
    "addr:street":"Rodenbachstraat;/ Forest",
    "iso:country":"BE",
    "sg:address":"Rodenbachstraat 118",
    "sg:city":"Vorst/forest",
    "sg:orig_category":"Fotografen and fotostudio's",
    "sg:phone":"+32 2 345 55 43",
    "sg:postcode":"1190",
    "sg:province":"Bruxelles-Capitale",
    "wof:name":"Alain Balthazart",
    "wof:placetype":"venue"
},
  "geometry": {"coordinates":[4.3445391655,50.8165740967],"type":"Point"}
}