{
  "type": "Feature",
  "properties": {
    "addr:full":"Lievevrouwestraat 3 Ranst Antwerpen 2520",
    "addr:housenumber":"3",
    "addr:postcode":"2520",
    "addr:street":"Lievevrouwestraat",
    "iso:country":"BE",
    "sg:address":"Lievevrouwestraat 3",
    "sg:city":"Ranst",
    "sg:orig_category":"Textiles. Souvenirs and objets artisanaux. Eclairage et \u00e9quipements du foyer",
    "sg:phone":"+32 3 485 73 33",
    "sg:postcode":"2520",
    "sg:province":"Antwerpen",
    "wof:name":"Huis Maxim",
    "wof:placetype":"venue"
},
  "geometry": {"coordinates":[4.5609898567,51.1899528503],"type":"Point"}
}