{
  "type": "Feature",
  "properties": {
    "addr:full":"Chauss\u00e9e De Saint-job 502 Bruxelles (uccle) Bruxelles-Capitale 1180",
    "addr:housenumber":"502",
    "addr:postcode":"1180",
    "addr:street":"Chausse\u0301E De Saint-Job",
    "iso:country":"BE",
    "sg:address":"Chauss\u00e9e De Saint-job 502",
    "sg:city":"Bruxelles (uccle)",
    "sg:classifiers":[
        {
            "category":"Building & Trades",
            "subcategory":"Landscaping Services",
            "type":"Services"
        }
    ],
    "sg:phone":"+32 477 52 91 83",
    "sg:postcode":"1180",
    "sg:province":"Bruxelles-Capitale",
    "sg:tags":[
        "gardening",
        "garden",
        "maintenance"
    ],
    "wof:name":"Geoff Garden Service",
    "wof:placetype":"venue"
},
  "geometry": {"coordinates":[4.3583087921,50.7920875549],"type":"Point"}
}