{
  "type": "Feature",
  "properties": {
    "addr:full":"Goorkensdreef 7 Hoogstraten Antwerpen 2322",
    "addr:housenumber":"7",
    "addr:postcode":"2322",
    "addr:street":"Goorkensdreef",
    "iso:country":"BE",
    "sg:address":"Goorkensdreef 7",
    "sg:city":"Hoogstraten",
    "sg:orig_category":"Eleveurs de bovins. Producteurs de fruits. Eleveurs and marchands de porcs",
    "sg:phone":"+32 3 315 80 46",
    "sg:postcode":"2322",
    "sg:province":"Antwerpen",
    "wof:name":"Adrianus De Bie",
    "wof:placetype":"venue"
},
  "geometry": {"coordinates":[4.763384819,51.4160041809],"type":"Point"}
}