{
  "type": "Feature",
  "properties": {
    "iso:country":"BE",
    "sg:address":"Rue Keyenveld 46",
    "sg:city":"Bruxelles (ixelles)",
    "sg:classifiers":[
        {
            "category":"Education",
            "subcategory":"Music School",
            "type":"Public Place"
        }
    ],
    "sg:phone":"+32 2 513 67 04",
    "sg:postcode":"1050",
    "sg:province":"Bruxelles-Capitale",
    "sg:tags":[
        "-",
        "teacher",
        "private"
    ],
    "wof:name":"Tchaikovsky",
    "wof:placetype":"venue"
},
  "geometry": {"coordinates":[4.3615159988,50.8348770142],"type":"Point"}
}