{
  "type": "Feature",
  "properties": {
    "addr:full":"Rue Grand-vin\u00c2ve 31 Seraing Li\u00e8ge 4101",
    "addr:housenumber":"31",
    "addr:postcode":"4101",
    "addr:street":"Rue Grand-Vina\u0302Ve",
    "iso:country":"BE",
    "sg:address":"Rue Grand-vin\u00c2ve 31",
    "sg:city":"Seraing",
    "sg:orig_category":"Grands magasins",
    "sg:phone":"+32 4 234 05 34",
    "sg:postcode":"4101",
    "sg:province":"Li\u00e8ge",
    "wof:name":"Trafic",
    "wof:placetype":"venue"
},
  "geometry": {"coordinates":[5.5054078102,50.616481781],"type":"Point"}
}