{
  "type": "Feature",
  "properties": {
    "addr:full":"Stationsstraat 5 Zwevegem 8552",
    "addr:housenumber":"5",
    "addr:postcode":"8552",
    "addr:street":"Stationsstraat",
    "iso:country":"BE",
    "sg:address":"Stationsstraat 5",
    "sg:city":"Zwevegem",
    "sg:orig_category":"Dameskledingzaken",
    "sg:phone":"+32 56 64 49 47",
    "sg:postcode":"8552",
    "wof:name":"Huis Tendens",
    "wof:placetype":"venue"
},
  "geometry": {"coordinates":[3.3970520496,50.770198822],"type":"Point"}
}