{
  "type": "Feature",
  "properties": {
    "iso:country":"BE",
    "sg:address":"Geistingen 88",
    "sg:city":"Kinrooi",
    "sg:orig_category":"Industri\u00eble and commerci\u00eble bouw Woningbouw",
    "sg:phone":"+32 89 56 21 94",
    "sg:postcode":"3640",
    "sg:province":"Limburg",
    "wof:name":"Rojega",
    "wof:placetype":"venue"
},
  "geometry": {"coordinates":[5.8145852089,51.1354942322],"type":"Point"}
}