{
  "type": "Feature",
  "properties": {
    "addr:full":"Acaciastraat 17 Neerpelt Limburg 3910",
    "addr:housenumber":"17",
    "addr:postcode":"3910",
    "addr:street":"Acaciastraat",
    "iso:country":"BE",
    "sg:address":"Acaciastraat 17",
    "sg:city":"Neerpelt",
    "sg:orig_category":"Elektrische installaties voor woningen",
    "sg:phone":"+32 11 80 24 40",
    "sg:postcode":"3910",
    "sg:province":"Limburg",
    "wof:name":"Theo Van Lit",
    "wof:placetype":"venue"
},
  "geometry": {"coordinates":[5.4453401566,51.2238807678],"type":"Point"}
}