{
  "type": "Feature",
  "properties": {
    "addr:full":"Kleine Katsweg 15ba Maldegem Oost-Vlaanderen 9990",
    "addr:postcode":"9990",
    "addr:street":"Oost-Vlaanderen",
    "iso:country":"BE",
    "sg:address":"Kleine Katsweg 15ba",
    "sg:city":"Maldegem",
    "sg:classifiers":[
        {
            "category":"Personal",
            "subcategory":"Beauty Salon",
            "type":"Services"
        }
    ],
    "sg:phone":"+32 50 71 81 31",
    "sg:postcode":"9990",
    "sg:province":"Oost-Vlaanderen",
    "sg:tags":[
        "de",
        "coiffure"
    ],
    "wof:name":"Kapsalon Lateste-style",
    "wof:placetype":"venue"
},
  "geometry": {"coordinates":[3.4588060379,51.2089118958],"type":"Point"}
}