{
  "type": "Feature",
  "properties": {
    "iso:country":"BE",
    "sg:address":"Rue Des B\u00c9guines 103",
    "sg:city":"Sint-jans-molenbeek/molenbeek-saint-jean",
    "sg:orig_category":"Biblioth\u00e8ques and archives publiques",
    "sg:phone":"+32 2 414 48 99",
    "sg:postcode":"1080",
    "sg:province":"Bruxelles-Capitale",
    "wof:name":"Biblioth\u00c8que Publique",
    "wof:placetype":"venue"
},
  "geometry": {"coordinates":[4.311934948,50.8577919006],"type":"Point"}
}