{
  "type": "Feature",
  "properties": {
    "addr:full":"Rijschoolstraat 12 Assenede Oost-Vlaanderen 9960",
    "addr:housenumber":"12",
    "addr:postcode":"9960",
    "addr:street":"Rijschoolstraat",
    "iso:country":"BE",
    "sg:address":"Rijschoolstraat 12",
    "sg:city":"Assenede",
    "sg:orig_category":"Bloemen and planten",
    "sg:phone":"+32 9 344 94 14",
    "sg:postcode":"9960",
    "sg:province":"Oost-Vlaanderen",
    "wof:name":"Verschaere",
    "wof:placetype":"venue"
},
  "geometry": {"coordinates":[3.7435491085,51.1930770874],"type":"Point"}
}