{
  "type": "Feature",
  "properties": {
    "iso:country":"BE",
    "sg:address":"Rue Des Combattants 35",
    "sg:city":"Bertrix",
    "sg:orig_category":"Artsen and specialisten",
    "sg:phone":"+32 61 41 20 27",
    "sg:postcode":"6880",
    "sg:province":"Luxembourg",
    "wof:name":"Jos\u00c9 Coppine",
    "wof:placetype":"venue"
},
  "geometry": {"coordinates":[5.2539100647,49.8569564819],"type":"Point"}
}