{
  "type": "Feature",
  "properties": {
    "addr:full":"Clos Des Puits 9 Mons (ghlin) Hainaut 7011",
    "addr:housenumber":"9",
    "addr:postcode":"7011",
    "addr:street":"Clos Des Puits",
    "iso:country":"BE",
    "sg:address":"Clos Des Puits 9",
    "sg:city":"Mons (ghlin)",
    "sg:classifiers":[
        {
            "category":"Health Services",
            "subcategory":"Doctor",
            "type":"Services"
        }
    ],
    "sg:phone":"+32 65 36 14 25",
    "sg:postcode":"7011",
    "sg:province":"Hainaut",
    "sg:tags":[
        "medicinephysicians",
        "surgeon"
    ],
    "wof:name":"Dutron Guy",
    "wof:placetype":"venue"
},
  "geometry": {"coordinates":[3.912539959,50.4712982178],"type":"Point"}
}