{
  "type": "Feature",
  "properties": {
    "iso:country":"BE",
    "sg:address":"Breendonkstraat 22b",
    "sg:city":"Willebroek",
    "sg:orig_category":"Installation de menuiserie en bois and plastique",
    "sg:phone":"+32 3 886 74 78",
    "sg:postcode":"2830",
    "sg:province":"Antwerpen",
    "wof:name":"Vanenco",
    "wof:placetype":"venue"
},
  "geometry": {"coordinates":[4.3524627686,51.0549736023],"type":"Point"}
}