{
  "type": "Feature",
  "properties": {
    "addr:full":"Paddeschootdreef 100 Sint-niklaas Oost-Vlaanderen 9100",
    "addr:housenumber":"100",
    "addr:postcode":"9100",
    "iso:country":"BE",
    "sg:address":"Paddeschootdreef 100",
    "sg:city":"Sint-niklaas",
    "sg:orig_category":"Newspapers, magazines, periodicals - Distribution",
    "sg:phone":"+32 3 777 97 32",
    "sg:postcode":"9100",
    "sg:province":"Oost-Vlaanderen",
    "wof:name":"Van Hove",
    "wof:placetype":"venue"
},
  "geometry": {"coordinates":[4.1264238358,51.1671218872],"type":"Point"}
}