{
  "type": "Feature",
  "properties": {
    "addr:full":"All\u00e9e Du Douaire 26 Florennes (morialm\u00e9) Namur 5621",
    "addr:housenumber":"26",
    "addr:postcode":"5621",
    "addr:street":"Alle\u0301E Du Douaire",
    "iso:country":"BE",
    "sg:address":"All\u00e9e Du Douaire 26",
    "sg:city":"Florennes (morialm\u00e9)",
    "sg:classifiers":[
        {
            "category":"Professional",
            "subcategory":"Accounting & Tax Preparation",
            "type":"Services"
        }
    ],
    "sg:phone":"+32 71 68 62 61",
    "sg:postcode":"5621",
    "sg:province":"Namur",
    "sg:tags":[
        "bookkeeper"
    ],
    "wof:name":"Massaux B",
    "wof:placetype":"venue"
},
  "geometry": {"coordinates":[4.5722708702,50.2684822083],"type":"Point"}
}