{
  "type": "Feature",
  "properties": {
    "addr:full":"Sliksteenvest 1 Tienen Vlaams-Brabant 3300",
    "addr:housenumber":"1",
    "addr:postcode":"3300",
    "addr:street":"Sliksteenvest",
    "iso:country":"BE",
    "sg:address":"Sliksteenvest 1",
    "sg:city":"Tienen",
    "sg:orig_category":"Enseignement maternel and primaire",
    "sg:phone":"+32 16 81 56 36",
    "sg:postcode":"3300",
    "sg:province":"Vlaams-Brabant",
    "wof:name":"Provinciale Basisschool",
    "wof:placetype":"venue"
},
  "geometry": {"coordinates":[4.942882061,50.8119544983],"type":"Point"}
}