{
  "type": "Feature",
  "properties": {
    "iso:country":"BE",
    "sg:address":"Place Loix 7b27",
    "sg:city":"Sint-gillis/saint-gilles",
    "sg:orig_category":"Avocats and conseillers juridiques",
    "sg:phone":"+32 2 538 93 93",
    "sg:postcode":"1060",
    "sg:province":"Bruxelles-Capitale",
    "wof:name":"A. Vermoortele",
    "wof:placetype":"venue"
},
  "geometry": {"coordinates":[4.3530640602,50.8316955566],"type":"Point"}
}