{
  "type": "Feature",
  "properties": {
    "iso:country":"BE",
    "sg:address":"Rue Raaff 153",
    "sg:city":"Raeren",
    "sg:orig_category":"Antiquit\u00e9s",
    "sg:phone":"+32 87 85 36 76",
    "sg:postcode":"4731",
    "sg:province":"Li\u00e8ge",
    "wof:name":"Andrea Maassen",
    "wof:placetype":"venue"
},
  "geometry": {"coordinates":[6.1114530563,50.693687439],"type":"Point"}
}