{
  "type": "Feature",
  "properties": {
    "addr:full":"Rue Des Raines 93-95 Verviers Li\u00e8ge 4800",
    "addr:postcode":"93-95;4800",
    "addr:street":"Rue Des Raines",
    "iso:country":"BE",
    "sg:address":"Rue Des Raines 93-95",
    "sg:city":"Verviers",
    "sg:classifiers":[
        {
            "category":"Building & Trades",
            "subcategory":"Landscaping Services",
            "type":"Services"
        }
    ],
    "sg:phone":"+32 87 31 21 55",
    "sg:postcode":"4800",
    "sg:province":"Li\u00e8ge",
    "sg:tags":[
        "handicraft"
    ],
    "wof:name":"La Lune Qui souris",
    "wof:placetype":"venue"
},
  "geometry": {"coordinates":[5.8661870956,50.5943527222],"type":"Point"}
}