{
  "type": "Feature",
  "properties": {
    "addr:full":"Rue Des Salinques 4 Le Roeulx Hainaut 7041",
    "addr:housenumber":"4",
    "addr:postcode":"7041",
    "addr:street":"Rue Des Salinques",
    "iso:country":"BE",
    "sg:address":"Rue Des Salinques 4",
    "sg:city":"Le Roeulx",
    "sg:orig_category":"Groententeelt",
    "sg:phone":"+32 64 67 54 12",
    "sg:postcode":"7041",
    "sg:province":"Hainaut",
    "wof:name":"Freddy Poliart",
    "wof:placetype":"venue"
},
  "geometry": {"coordinates":[4.0324649811,50.3790435791],"type":"Point"}
}