{
  "type": "Feature",
  "properties": {
    "addr:full":"Rue De Moorslede 149 Bruxelles Bruxelles-Capitale 1020",
    "addr:housenumber":"149",
    "addr:postcode":"1020",
    "addr:street":"Rue De Moorslede",
    "iso:country":"BE",
    "sg:address":"Rue De Moorslede 149",
    "sg:city":"Bruxelles",
    "sg:classifiers":[
        {
            "category":"Food & Beverages",
            "subcategory":"Groceries & Convenience Stores",
            "type":"Retail Goods"
        }
    ],
    "sg:phone":"+32 2 428 77 71",
    "sg:postcode":"1020",
    "sg:province":"Bruxelles-Capitale",
    "sg:tags":[
        "grocer"
    ],
    "wof:name":"Cles Shopping",
    "wof:placetype":"venue"
},
  "geometry": {"coordinates":[4.3481411934,50.8723907471],"type":"Point"}
}