{
  "type": "Feature",
  "properties": {
    "iso:country":"BE",
    "sg:address":"Rue C. Magnette 4/a",
    "sg:city":"Li\u00c8ge (grand)",
    "sg:orig_category":"Naai- and breimachines",
    "sg:phone":"+32 4 222 14 44",
    "sg:postcode":"4000",
    "sg:province":"Li\u00e8ge",
    "wof:name":"Singer",
    "wof:placetype":"venue"
},
  "geometry": {"coordinates":[5.574133873,50.6411247253],"type":"Point"}
}