{
  "type": "Feature",
  "properties": {
    "iso:country":"BE",
    "sg:address":"Frederik Burvenichstraat 83",
    "sg:city":"Gent",
    "sg:orig_category":"Apotheken",
    "sg:phone":"+32 9 230 24 40",
    "sg:postcode":"9050",
    "sg:province":"Oost-Vlaanderen",
    "wof:name":"K. De Nil",
    "wof:placetype":"venue"
},
  "geometry": {"coordinates":[3.7498469353,51.0397148132],"type":"Point"}
}