{
  "type": "Feature",
  "properties": {
    "addr:full":"Reservorenstraat 40 Beringen (beverlo) Limburg 3581",
    "addr:housenumber":"40",
    "addr:postcode":"3581",
    "addr:street":"Reservorenstraat",
    "iso:country":"BE",
    "sg:address":"Reservorenstraat 40",
    "sg:city":"Beringen (beverlo)",
    "sg:orig_category":"Non-Classified Establishments",
    "sg:phone":"+32 11 34 12 59",
    "sg:postcode":"3581",
    "sg:province":"Limburg",
    "wof:name":"Vanhamel Bvba",
    "wof:placetype":"venue"
},
  "geometry": {"coordinates":[5.2349181175,51.0938873291],"type":"Point"}
}