{
  "type": "Feature",
  "properties": {
    "iso:country":"BE",
    "sg:address":"Tribomont 14",
    "sg:city":"Herve",
    "sg:orig_category":"Experts-comptables",
    "sg:phone":"+32 87 31 36 30",
    "sg:postcode":"4650",
    "sg:province":"Li\u00e8ge",
    "wof:name":"J. Dome",
    "wof:placetype":"venue"
},
  "geometry": {"coordinates":[5.8207788467,50.6008796692],"type":"Point"}
}