{
  "type": "Feature",
  "properties": {
    "iso:country":"BE",
    "sg:address":"Vrerenstraat 35",
    "sg:city":"Tongeren",
    "sg:orig_category":"Installation \u00e9lectrique r\u00e9sidentielle",
    "sg:phone":"+32 12 23 55 04",
    "sg:postcode":"3700",
    "sg:province":"Limburg",
    "wof:name":"Jose Dieu",
    "wof:placetype":"venue"
},
  "geometry": {"coordinates":[5.4918189049,50.7529029846],"type":"Point"}
}