{
  "type": "Feature",
  "properties": {
    "addr:full":"Rijksweg 289 Maasmechelen Limburg 3630",
    "addr:housenumber":"289",
    "addr:postcode":"3630",
    "addr:street":"Rijksweg",
    "iso:country":"BE",
    "sg:address":"Rijksweg 289",
    "sg:city":"Maasmechelen",
    "sg:orig_category":"Non-Classified Establishments",
    "sg:phone":"+32 89 77 20 71",
    "sg:postcode":"3630",
    "sg:province":"Limburg",
    "wof:name":"B-art Chocolats Bvba",
    "wof:placetype":"venue"
},
  "geometry": {"coordinates":[5.6981391907,50.9714393616],"type":"Point"}
}