{
  "type": "Feature",
  "properties": {
    "addr:full":"Bree\u00ebrsteenweg 330 Kinrooi Limburg 3640",
    "addr:housenumber":"330",
    "addr:postcode":"3640",
    "addr:street":"Breee\u0308Rsteenweg",
    "iso:country":"BE",
    "sg:address":"Bree\u00ebrsteenweg 330",
    "sg:city":"Kinrooi",
    "sg:orig_category":"Non-Classified Establishments",
    "sg:phone":"+32 89 70 22 73",
    "sg:postcode":"3640",
    "sg:province":"Limburg",
    "wof:name":"Theybers-segers",
    "wof:placetype":"venue"
},
  "geometry": {"coordinates":[5.7335681915,51.1457252502],"type":"Point"}
}