{
  "type": "Feature",
  "properties": {
    "addr:full":"Rue De Rotheux 269 Seraing Li\u00e8ge 4100",
    "addr:housenumber":"269",
    "addr:postcode":"4100",
    "addr:street":"Rue De Rotheux",
    "iso:country":"BE",
    "sg:address":"Rue De Rotheux 269",
    "sg:city":"Seraing",
    "sg:orig_category":"R\u00e9parations d'appareils \u00e9lectrom\u00e9nagers. Electrom\u00e9nager, t\u00e9l\u00e9visions and radios. Ordinateurs Fab. In",
    "sg:phone":"+32 4 336 78 54",
    "sg:postcode":"4100",
    "sg:province":"Li\u00e8ge",
    "wof:name":"A. & Technotronics Engin.",
    "wof:placetype":"venue"
},
  "geometry": {"coordinates":[5.5031719208,50.5796394348],"type":"Point"}
}