{
  "type": "Feature",
  "properties": {
    "iso:country":"BE",
    "sg:address":"Rue Des Ormeaux 25",
    "sg:city":"Chimay",
    "sg:orig_category":"Fournitures de bureau. Librairies. Tabac. Journaux",
    "sg:phone":"+32 60 21 44 08",
    "sg:postcode":"6460",
    "sg:province":"Hainaut",
    "wof:name":"Le Furet",
    "wof:placetype":"venue"
},
  "geometry": {"coordinates":[4.3163380623,50.0477104187],"type":"Point"}
}