{
  "type": "Feature",
  "properties": {
    "addr:full":"Voldersstraat 13 Lochristi Oost-Vlaanderen 9080",
    "addr:housenumber":"13",
    "addr:postcode":"9080",
    "addr:street":"Voldersstraat",
    "iso:country":"BE",
    "sg:address":"Voldersstraat 13",
    "sg:city":"Lochristi",
    "sg:orig_category":"Rundveehouders",
    "sg:phone":"+32 9 355 61 38",
    "sg:postcode":"9080",
    "sg:province":"Oost-Vlaanderen",
    "wof:name":"Andre De Vos",
    "wof:placetype":"venue"
},
  "geometry": {"coordinates":[3.8961279392,51.0837478638],"type":"Point"}
}