{
  "type": "Feature",
  "properties": {
    "iso:country":"BE",
    "sg:address":"Wildonkenstraat 22",
    "sg:city":"Deinze",
    "sg:classifiers":[
        {
            "category":"Food & Beverages",
            "subcategory":"Fruits & Vegetables",
            "type":"Retail Goods"
        }
    ],
    "sg:phone":"+32 9 386 25 73",
    "sg:postcode":"9800",
    "sg:province":"Oost-Vlaanderen",
    "sg:tags":[
        "l\u00e9gumes"
    ],
    "wof:name":"G. Vlaemynck",
    "wof:placetype":"venue"
},
  "geometry": {"coordinates":[3.530174017,50.9863166809],"type":"Point"}
}