{
  "type": "Feature",
  "properties": {
    "iso:country":"BE",
    "sg:address":"Bolwerkstraat 16",
    "sg:city":"Vilvoorde",
    "sg:orig_category":"Meubles D\u00e9taillants, Am\u00e9nagement de B\u00e2timents et de Cuisines",
    "sg:phone":"+32 2 253 14 30",
    "sg:postcode":"1800",
    "sg:province":"Vlaams-Brabant",
    "wof:name":"Poot R Interieur",
    "wof:placetype":"venue"
},
  "geometry": {"coordinates":[4.432202816,50.9284553528],"type":"Point"}
}