{
  "type": "Feature",
  "properties": {
    "addr:full":"Lerrekensstraat 32a Heist-op-den-berg Antwerpen 2220",
    "addr:housenumber":"32a",
    "addr:postcode":"2220",
    "addr:street":"Lerrekensstraat",
    "iso:country":"BE",
    "sg:address":"Lerrekensstraat 32a",
    "sg:city":"Heist-op-den-berg",
    "sg:classifiers":[
        {
            "category":"Building & Trades",
            "subcategory":"Cleaning & Sanitation",
            "type":"Services"
        }
    ],
    "sg:phone":"+32 15 25 16 01",
    "sg:postcode":"2220",
    "sg:province":"Antwerpen",
    "sg:tags":[
        "transport",
        "mean"
    ],
    "wof:name":"Mobile Truck Cleaning Nv",
    "wof:placetype":"venue"
},
  "geometry": {"coordinates":[4.7044901848,51.0603027344],"type":"Point"}
}