{
  "type": "Feature",
  "properties": {
    "addr:full":"Rue F\u00c9lix Protin 9 Sambreville Namur 5060",
    "addr:housenumber":"9",
    "addr:postcode":"5060",
    "addr:street":"Rue Fe\u0301Lix Protin",
    "iso:country":"BE",
    "sg:address":"Rue F\u00c9lix Protin 9",
    "sg:city":"Sambreville",
    "sg:orig_category":"Art and fournitures artistiques. Souvenirs and objets artisanaux. Eclairage et \u00e9quipements du foyer",
    "sg:phone":"+32 71 74 22 75",
    "sg:postcode":"5060",
    "sg:province":"Namur",
    "wof:name":"C.e.s.",
    "wof:placetype":"venue"
},
  "geometry": {"coordinates":[4.6285200119,50.4448738098],"type":"Point"}
}