{
  "type": "Feature",
  "properties": {
    "addr:full":"Rue De Burhaimont 82 Bertrix Luxembourg 6880",
    "addr:housenumber":"82",
    "addr:postcode":"6880",
    "addr:street":"Rue De Burhaimont",
    "iso:country":"BE",
    "sg:address":"Rue De Burhaimont 82",
    "sg:city":"Bertrix",
    "sg:classifiers":[
        {
            "category":"Arts & Performance",
            "subcategory":"Symphony",
            "type":"Entertainment"
        }
    ],
    "sg:phone":"+32 61 41 19 52",
    "sg:postcode":"6880",
    "sg:province":"Luxembourg",
    "sg:tags":[
        "orchestra"
    ],
    "wof:name":"Hanssen F",
    "wof:placetype":"venue"
},
  "geometry": {"coordinates":[5.2517552376,49.8595466614],"type":"Point"}
}