{
  "type": "Feature",
  "properties": {
    "addr:full":"Hillarestraat 160 Lokeren Oost-Vlaanderen 9160",
    "addr:housenumber":"160",
    "addr:postcode":"9160",
    "addr:street":"Hillarestraat",
    "iso:country":"BE",
    "sg:address":"Hillarestraat 160",
    "sg:city":"Lokeren",
    "sg:orig_category":"Eleveurs de bovins",
    "sg:phone":"+32 9 348 74 37",
    "sg:postcode":"9160",
    "sg:province":"Oost-Vlaanderen",
    "wof:name":"Jozef Verdonck",
    "wof:placetype":"venue"
},
  "geometry": {"coordinates":[3.9634640217,51.0904884338],"type":"Point"}
}