{
  "type": "Feature",
  "properties": {
    "iso:country":"BE",
    "sg:address":"Quai Du Sud 0",
    "sg:city":"Charleroi",
    "sg:classifiers":[
        {
            "category":"Cafe",
            "type":"Food & Drink"
        }
    ],
    "sg:phone":"+32 71 51 66 62",
    "sg:postcode":"6030",
    "sg:province":"Hainaut",
    "sg:tags":[
        "caf\u00e9s"
    ],
    "wof:name":"Action Cathol. Batelier",
    "wof:placetype":"venue"
},
  "geometry": {"coordinates":[4.3956131935,50.4077453613],"type":"Point"}
}