{
  "type": "Feature",
  "properties": {
    "addr:full":"Wolvertemsesteenweg 359 Grimbergen Vlaams-Brabant 1850",
    "addr:housenumber":"359",
    "addr:postcode":"1850",
    "addr:street":"Wolvertemsesteenweg",
    "iso:country":"BE",
    "sg:address":"Wolvertemsesteenweg 359",
    "sg:city":"Grimbergen",
    "sg:classifiers":[
        {
            "category":"Retail",
            "subcategory":"Repair Shop",
            "type":"Services"
        }
    ],
    "sg:phone":"+32 2 270 06 31",
    "sg:postcode":"1850",
    "sg:province":"Vlaams-Brabant",
    "sg:tags":[
        "upholsterer"
    ],
    "wof:name":"Fryns S",
    "wof:placetype":"venue"
},
  "geometry": {"coordinates":[4.3471050262,50.9397239685],"type":"Point"}
}