{
  "type": "Feature",
  "properties": {
    "addr:full":"Rue Fran\u00c7ois Wachel 26 P\u00c9ruwelz Hainaut 7603",
    "addr:housenumber":"26",
    "addr:postcode":"7603",
    "addr:street":"Rue Franc\u0327Ois Wachel",
    "iso:country":"BE",
    "sg:address":"Rue Fran\u00c7ois Wachel 26",
    "sg:city":"P\u00c9ruwelz",
    "sg:orig_category":"Antiquit\u00e9s",
    "sg:phone":"+32 69 77 71 30",
    "sg:postcode":"7603",
    "sg:province":"Hainaut",
    "wof:name":"Patricia Duquin",
    "wof:placetype":"venue"
},
  "geometry": {"coordinates":[3.6173698902,50.5020713806],"type":"Point"}
}