{
  "type": "Feature",
  "properties": {
    "addr:full":"Pamelstraat 227 Ninove Oost-Vlaanderen 9400",
    "addr:housenumber":"227",
    "addr:postcode":"9400",
    "addr:street":"Pamelstraat",
    "iso:country":"BE",
    "sg:address":"Pamelstraat 227",
    "sg:city":"Ninove",
    "sg:classifiers":[
        {
            "category":"Personal",
            "subcategory":"Beauty Salon",
            "type":"Services"
        }
    ],
    "sg:phone":"+32 54 33 10 00",
    "sg:postcode":"9400",
    "sg:province":"Oost-Vlaanderen",
    "sg:tags":[
        "de",
        "coiffure"
    ],
    "wof:name":"Coiffure Micheline",
    "wof:placetype":"venue"
},
  "geometry": {"coordinates":[4.0332198143,50.8387832642],"type":"Point"}
}