{
  "type": "Feature",
  "properties": {
    "iso:country":"BE",
    "sg:address":"Moerstraat 66",
    "sg:city":"Hoogstraten",
    "sg:orig_category":"Eleveurs de bovins. Eleveurs and marchands de porcs",
    "sg:phone":"+32 3 314 76 83",
    "sg:postcode":"2320",
    "sg:province":"Antwerpen",
    "wof:name":"Jan Verheyen",
    "wof:placetype":"venue"
},
  "geometry": {"coordinates":[4.7528061867,51.4074707031],"type":"Point"}
}