{
  "type": "Feature",
  "properties": {
    "iso:country":"BE",
    "sg:address":"Chauss\u00e9e De Louvain 159",
    "sg:city":"Namur (bouge)",
    "sg:classifiers":[
        {
            "category":"Health Services",
            "subcategory":"Health Practitioner",
            "type":"Services"
        }
    ],
    "sg:phone":"+32 81 23 08 77",
    "sg:postcode":"5004",
    "sg:province":"Namur",
    "sg:tags":[
        "osteopath"
    ],
    "wof:name":"Verheyen M",
    "wof:placetype":"venue"
},
  "geometry": {"coordinates":[4.8751478195,50.4759140015],"type":"Point"}
}