{
  "type": "Feature",
  "properties": {
    "addr:full":"Zandstraat 77 Neerpelt Limburg 3910",
    "addr:housenumber":"77",
    "addr:postcode":"3910",
    "addr:street":"Zandstraat",
    "iso:country":"BE",
    "sg:address":"Zandstraat 77",
    "sg:city":"Neerpelt",
    "sg:orig_category":"Kapsalons",
    "sg:phone":"+32 11 64 71 69",
    "sg:postcode":"3910",
    "sg:province":"Limburg",
    "wof:name":"Coiffure Jeannine",
    "wof:placetype":"venue"
},
  "geometry": {"coordinates":[5.454969883,51.2153511047],"type":"Point"}
}