{
  "type": "Feature",
  "properties": {
    "addr:full":"Rue De Tournai 63 Leuze-en-hainaut Hainaut 7900",
    "addr:housenumber":"63",
    "addr:postcode":"7900",
    "addr:street":"Rue De Tournai",
    "iso:country":"BE",
    "sg:address":"Rue De Tournai 63",
    "sg:city":"Leuze-en-hainaut",
    "sg:orig_category":"V\u00e9t\u00e9rinaires",
    "sg:phone":"+32 69 66 13 31",
    "sg:postcode":"7900",
    "sg:province":"Hainaut",
    "wof:name":"Rene Antoine",
    "wof:placetype":"venue"
},
  "geometry": {"coordinates":[3.5964910984,50.5957984924],"type":"Point"}
}