{
  "type": "Feature",
  "properties": {
    "addr:full":"Nonnenstraat 27 Retie Antwerpen 2470",
    "addr:housenumber":"27",
    "addr:postcode":"2470",
    "addr:street":"Nonnenstraat",
    "iso:country":"BE",
    "sg:address":"Nonnenstraat 27",
    "sg:city":"Retie",
    "sg:classifiers":[
        {
            "category":"Shopping",
            "subcategory":"Clothing, Apparel, & Fashions",
            "type":"Retail Goods"
        }
    ],
    "sg:phone":"+32 14 67 19 39",
    "sg:postcode":"2470",
    "sg:province":"Antwerpen",
    "sg:tags":[
        "-",
        "clothing",
        "child"
    ],
    "wof:name":"Mes O",
    "wof:placetype":"venue"
},
  "geometry": {"coordinates":[5.0494499207,51.2905464172],"type":"Point"}
}