{
  "type": "Feature",
  "properties": {
    "iso:country":"BE",
    "sg:address":"Place Henri Hallet 27",
    "sg:city":"Hannut",
    "sg:classifiers":[
        {
            "category":"Social Services",
            "type":"Services"
        }
    ],
    "sg:phone":"+32 19 51 00 29",
    "sg:postcode":"4280",
    "sg:province":"Li\u00e8ge",
    "sg:tags":[
        "handicapped",
        "-"
    ],
    "wof:name":"Croisette (la) Asbl",
    "wof:placetype":"venue"
},
  "geometry": {"coordinates":[5.0793008804,50.6712760925],"type":"Point"}
}