{
  "type": "Feature",
  "properties": {
    "iso:country":"BE",
    "sg:address":"Rue Du Cur\u00e9 7",
    "sg:city":"Philippeville (villers-le-gambon)",
    "sg:classifiers":[
        {
            "category":"Professional",
            "subcategory":"Testing Lab",
            "type":"Services"
        }
    ],
    "sg:phone":"+32 71 66 63 54",
    "sg:postcode":"5600",
    "sg:province":"Namur",
    "sg:tags":[
        "chemist"
    ],
    "wof:name":"Scailteur L",
    "wof:placetype":"venue"
},
  "geometry": {"coordinates":[4.6099991798,50.1895713806],"type":"Point"}
}