{
  "type": "Feature",
  "properties": {
    "addr:full":"Opperstraat 128 Nieuwerkerken Limburg 3850",
    "addr:housenumber":"128",
    "addr:postcode":"3850",
    "addr:street":"Opperstraat",
    "iso:country":"BE",
    "sg:address":"Opperstraat 128",
    "sg:city":"Nieuwerkerken",
    "sg:orig_category":"Catering and organisatie van feesten",
    "sg:phone":"+32 11 59 19 70",
    "sg:postcode":"3850",
    "sg:province":"Limburg",
    "wof:name":"Traiteur Jean",
    "wof:placetype":"venue"
},
  "geometry": {"coordinates":[5.2124810219,50.895614624],"type":"Point"}
}