{
  "type": "Feature",
  "properties": {
    "iso:country":"BE",
    "sg:address":"Hultendries 17",
    "sg:city":"Mechelen",
    "sg:orig_category":"Dierenartsen",
    "sg:phone":"+32 15 42 21 42",
    "sg:postcode":"2811",
    "sg:province":"Antwerpen",
    "wof:name":"Karel De Wit",
    "wof:placetype":"venue"
},
  "geometry": {"coordinates":[4.4322299957,51.0027313232],"type":"Point"}
}