{
  "type": "Feature",
  "properties": {
    "iso:country":"BE",
    "sg:address":"Rue Du Prince Royal 33",
    "sg:city":"Bruxelles (ixelles)",
    "sg:classifiers":[
        {
            "category":"Banks & Credit Unions",
            "subcategory":"Financial Services",
            "type":"Services"
        }
    ],
    "sg:phone":"+32 2 513 31 39",
    "sg:postcode":"1050",
    "sg:province":"Bruxelles-Capitale",
    "sg:tags":[
        "financing"
    ],
    "wof:name":"Cr\u00e9dit Immobilier",
    "wof:placetype":"venue"
},
  "geometry": {"coordinates":[4.3623838425,50.8348617554],"type":"Point"}
}