{
  "type": "Feature",
  "properties": {
    "addr:full":"Stationsstraat 29 Izegem West-Vlaanderen 8870",
    "addr:housenumber":"29",
    "addr:postcode":"8870",
    "addr:street":"Stationsstraat",
    "iso:country":"BE",
    "sg:address":"Stationsstraat 29",
    "sg:city":"Izegem",
    "sg:orig_category":"Bouwmaterialen Gh Verzekeringsmakelaars and experts",
    "sg:phone":"+32 51 30 47 66",
    "sg:postcode":"8870",
    "sg:province":"West-Vlaanderen",
    "wof:name":"Joseph Lapeire",
    "wof:placetype":"venue"
},
  "geometry": {"coordinates":[3.2127718925,50.9205245972],"type":"Point"}
}