{
  "type": "Feature",
  "properties": {
    "addr:full":"Rue Florikosse 38 Verviers (heusy) Li\u00e8ge 4802",
    "addr:housenumber":"38",
    "addr:postcode":"4802",
    "addr:street":"Rue Florikosse",
    "iso:country":"BE",
    "sg:address":"Rue Florikosse 38",
    "sg:city":"Verviers (heusy)",
    "sg:classifiers":[
        {
            "category":"Social Services",
            "type":"Services"
        }
    ],
    "sg:phone":"+32 87 22 45 25",
    "sg:postcode":"4802",
    "sg:province":"Li\u00e8ge",
    "wof:name":"Oeuvre Des Aveugles De Verviers Et R\u00e9gion Asbl",
    "wof:placetype":"venue"
},
  "geometry": {"coordinates":[5.8671250343,50.5714111328],"type":"Point"}
}