{
  "type": "Feature",
  "properties": {
    "iso:country":"BE",
    "sg:address":"Avenue Ariane 27",
    "sg:city":"Bruxelles (woluwe-saint-lambert)",
    "sg:classifiers":[
        {
            "category":"Shopping",
            "subcategory":"Stationery & Office Supplies",
            "type":"Retail Goods"
        }
    ],
    "sg:phone":"+32 2 772 50 85",
    "sg:postcode":"1200",
    "sg:province":"Bruxelles-Capitale",
    "sg:tags":[
        "binder",
        "file"
    ],
    "wof:name":"Reich Frederic Sprl",
    "wof:placetype":"venue"
},
  "geometry": {"coordinates":[4.4341430664,50.8589363098],"type":"Point"}
}