{
  "type": "Feature",
  "properties": {
    "iso:country":"BE",
    "sg:address":"Industrieln 14",
    "sg:city":"Hoeselt",
    "sg:classifiers":[
        {
            "category":"Autos & Motor Vehicles",
            "subcategory":"Automobile Sales",
            "type":"Retail Goods"
        }
    ],
    "sg:phone":"+32 89 49 26 73",
    "sg:postcode":"3730",
    "sg:province":"Limburg",
    "sg:tags":[
        "equipment",
        "motor-cars",
        "transport"
    ],
    "wof:name":"Vos Nv",
    "wof:placetype":"venue"
},
  "geometry": {"coordinates":[5.491560936,50.8587265015],"type":"Point"}
}