{
  "type": "Feature",
  "properties": {
    "iso:country":"BE",
    "sg:address":"Naamsesteenweg 318",
    "sg:city":"Leuven (heverlee)",
    "sg:classifiers":[
        {
            "category":"Health Services",
            "subcategory":"Health Practitioner",
            "type":"Services"
        }
    ],
    "sg:phone":"+32 16 40 38 91",
    "sg:postcode":"3001",
    "sg:province":"Vlaams-Brabant",
    "sg:tags":[
        "physiotherapist"
    ],
    "wof:name":"Buchet Emmanuel",
    "wof:placetype":"venue"
},
  "geometry": {"coordinates":[4.6956977844,50.8577919006],"type":"Point"}
}