{
  "type": "Feature",
  "properties": {
    "addr:full":"Antwerpsesteenweg 123 Rumst Antwerpen 2840",
    "addr:housenumber":"123",
    "addr:postcode":"2840",
    "addr:street":"Antwerpsesteenweg",
    "iso:country":"BE",
    "sg:address":"Antwerpsesteenweg 123",
    "sg:city":"Rumst",
    "sg:classifiers":[
        {
            "category":"Shopping",
            "subcategory":"Party Supplies",
            "type":"Retail Goods"
        }
    ],
    "sg:phone":"+32 15 32 09 88",
    "sg:postcode":"2840",
    "sg:province":"Antwerpen",
    "wof:name":"Henderickx S",
    "wof:placetype":"venue"
},
  "geometry": {"coordinates":[4.4511198997,51.0977783203],"type":"Point"}
}