{
  "type": "Feature",
  "properties": {
    "iso:country":"BE",
    "sg:address":"Rue Vertes Feuilles 6-8",
    "sg:city":"Frasnes-lez-anvaing (saint-sauveur)",
    "sg:orig_category":"Non-Classified Establishments",
    "sg:phone":"+32 69 76 84 21",
    "sg:postcode":"7912",
    "sg:province":"Hainaut",
    "wof:name":"Moreau A-m",
    "wof:placetype":"venue"
},
  "geometry": {"coordinates":[3.6211299896,50.7116889954],"type":"Point"}
}