{
  "type": "Feature",
  "properties": {
    "iso:country":"BE",
    "sg:address":"Rue De La Station 28",
    "sg:city":"Beaumont (str\u00e9e)",
    "sg:classifiers":[
        {
            "category":"Real Estate",
            "subcategory":"Architect",
            "type":"Services"
        }
    ],
    "sg:phone":"+32 71 53 31 91",
    "sg:postcode":"6511",
    "sg:province":"Hainaut",
    "wof:name":"Denruyter P",
    "wof:placetype":"venue"
},
  "geometry": {"coordinates":[4.3018498421,50.273349762],"type":"Point"}
}