{
  "type": "Feature",
  "properties": {
    "iso:country":"BE",
    "sg:address":"Marktstraat 12",
    "sg:city":"Lichtervelde",
    "sg:classifiers":[
        {
            "category":"Health Services",
            "subcategory":"Dentist",
            "type":"Services"
        }
    ],
    "sg:phone":"+32 51 72 39 30",
    "sg:postcode":"8810",
    "sg:province":"West-Vlaanderen",
    "wof:name":"Jacquemin Myriam",
    "wof:placetype":"venue"
},
  "geometry": {"coordinates":[3.1389670372,51.0270843506],"type":"Point"}
}