{
  "type": "Feature",
  "properties": {
    "addr:full":"Rue Mab\u00ceme 75 Ans Li\u00e8ge 4432",
    "addr:housenumber":"75",
    "addr:postcode":"4432",
    "addr:street":"Rue Mabi\u0302Me",
    "iso:country":"BE",
    "sg:address":"Rue Mab\u00ceme 75",
    "sg:city":"Ans",
    "sg:orig_category":"D\u00e9molition d\u00b4immeubles and terrassements. Construction industrielle and commerciale. Construction de",
    "sg:phone":"+32 4 246 51 00",
    "sg:postcode":"4432",
    "sg:province":"Li\u00e8ge",
    "wof:name":"Dewalque Tony",
    "wof:placetype":"venue"
},
  "geometry": {"coordinates":[5.5244660378,50.6687088013],"type":"Point"}
}