{
  "type": "Feature",
  "properties": {
    "addr:full":"Brusselsesteenweg 438 Asse Vlaams-Brabant 1731",
    "addr:housenumber":"438",
    "addr:postcode":"1731",
    "addr:street":"Brusselsesteenweg",
    "iso:country":"BE",
    "sg:address":"Brusselsesteenweg 438",
    "sg:city":"Asse",
    "sg:orig_category":"Herstellingen and onderhoud van auto's",
    "sg:phone":"+32 2 462 43 94",
    "sg:postcode":"1731",
    "sg:province":"Vlaams-Brabant",
    "wof:name":"Garage Mira",
    "wof:placetype":"venue"
},
  "geometry": {"coordinates":[4.2455320358,50.8937339783],"type":"Point"}
}