{
  "type": "Feature",
  "properties": {
    "addr:full":"Chauss\u00e9e De Mons 71 Soignies Hainaut 7060",
    "addr:housenumber":"71",
    "addr:postcode":"7060",
    "addr:street":"Chausse\u0301E De Mons",
    "iso:country":"BE",
    "sg:address":"Chauss\u00e9e De Mons 71",
    "sg:city":"Soignies",
    "sg:classifiers":[
        {
            "category":"Retail",
            "subcategory":"Auto Repair",
            "type":"Services"
        }
    ],
    "sg:phone":"+32 67 33 35 45",
    "sg:postcode":"7060",
    "sg:province":"Hainaut",
    "sg:tags":[
        "automobile-body"
    ],
    "wof:name":"Ets O Bois D'enghien & Fils Sa",
    "wof:placetype":"venue"
},
  "geometry": {"coordinates":[4.0644598007,50.5689620972],"type":"Point"}
}