{
  "type": "Feature",
  "properties": {
    "iso:country":"BE",
    "sg:address":"Vlasstraat 7a",
    "sg:city":"Gent (mariakerke)",
    "sg:classifiers":[
        {
            "category":"Real Estate",
            "subcategory":"Architect",
            "type":"Services"
        }
    ],
    "sg:phone":"+32 9 227 84 26",
    "sg:postcode":"9030",
    "sg:province":"Oost-Vlaanderen",
    "wof:name":"Bertrand Y",
    "wof:placetype":"venue"
},
  "geometry": {"coordinates":[3.6880569458,51.0713729858],"type":"Point"}
}