{
  "type": "Feature",
  "properties": {
    "addr:full":"De Keyserlei 25 Antwerpen Antwerpen 2018",
    "addr:housenumber":"25",
    "addr:postcode":"2018",
    "addr:street":"De Keyserlei",
    "iso:country":"BE",
    "sg:address":"De Keyserlei 25",
    "sg:city":"Antwerpen",
    "sg:classifiers":[
        {
            "category":"Bars & Pubs",
            "type":"Food & Drink"
        }
    ],
    "sg:phone":"+32 3 231 30 94",
    "sg:postcode":"2018",
    "sg:province":"Antwerpen",
    "sg:tags":[
        "tavern"
    ],
    "wof:name":"Christian Andersen",
    "wof:placetype":"venue"
},
  "geometry": {"coordinates":[4.4180760384,51.2177352905],"type":"Point"}
}