{
  "type": "Feature",
  "properties": {
    "iso:country":"BE",
    "sg:address":"Bavikhoofsestraat 176",
    "sg:city":"Harelbeke (bavikhove)",
    "sg:classifiers":[
        {
            "category":"Building & Trades",
            "subcategory":"Construction",
            "type":"Services"
        }
    ],
    "sg:phone":"+32 56 70 39 73",
    "sg:postcode":"8531",
    "sg:province":"West-Vlaanderen",
    "sg:tags":[
        "carpenter"
    ],
    "wof:name":"Verheye D",
    "wof:placetype":"venue"
},
  "geometry": {"coordinates":[3.3099410534,50.8737640381],"type":"Point"}
}