{
  "type": "Feature",
  "properties": {
    "iso:country":"BE",
    "sg:address":"Pastorijstraat 67",
    "sg:city":"Beringen (koersel)",
    "sg:classifiers":[
        {
            "category":"Health Services",
            "subcategory":"Health Practitioner",
            "type":"Services"
        }
    ],
    "sg:phone":"+32 11 45 11 54",
    "sg:postcode":"3582",
    "sg:province":"Limburg",
    "sg:tags":[
        "osteopath"
    ],
    "wof:name":"Gheisar M D.o",
    "wof:placetype":"venue"
},
  "geometry": {"coordinates":[5.2708749771,51.0595359802],"type":"Point"}
}