{
  "type": "Feature",
  "properties": {
    "iso:country":"BE",
    "sg:address":"Prins Boudewijnstraat 44",
    "sg:city":"Roeselare",
    "sg:orig_category":"Installatie van metalen schrijnwerk Plaatsen van vloer- and muurbekleding Schilders Verlichting and ",
    "sg:phone":"+32 51 20 75 73",
    "sg:postcode":"8800",
    "sg:province":"West-Vlaanderen",
    "wof:name":"Dael Lieven",
    "wof:placetype":"venue"
},
  "geometry": {"coordinates":[3.1225249767,50.9586448669],"type":"Point"}
}