{
  "type": "Feature",
  "properties": {
    "addr:full":"Celestijnenlaan 11-12 Leuven (heverlee) Vlaams-Brabant 3001",
    "addr:postcode":"11-12;3001",
    "addr:street":"Celestijnenlaan",
    "iso:country":"BE",
    "sg:address":"Celestijnenlaan 11-12",
    "sg:city":"Leuven (heverlee)",
    "sg:classifiers":[
        {
            "category":"Manufacturing",
            "subcategory":"Musical Instruments",
            "type":"Manufacturing & Wholesale Goods"
        }
    ],
    "sg:phone":"+32 16 29 28 37",
    "sg:postcode":"3001",
    "sg:province":"Vlaams-Brabant",
    "sg:tags":[
        "scientific",
        "apparatus"
    ],
    "wof:name":"Meteopublic",
    "wof:placetype":"venue"
},
  "geometry": {"coordinates":[4.6746220589,50.8718528748],"type":"Point"}
}