{
  "type": "Feature",
  "properties": {
    "addr:full":"Ieperse Steenweg 175 Veurne West-Vlaanderen 8630",
    "addr:housenumber":"175",
    "addr:postcode":"8630",
    "addr:street":"Steenweg",
    "iso:country":"BE",
    "sg:address":"Ieperse Steenweg 175",
    "sg:city":"Veurne",
    "sg:orig_category":"Bouwmaterialen Gh",
    "sg:phone":"+32 58 29 94 57",
    "sg:postcode":"8630",
    "sg:province":"West-Vlaanderen",
    "wof:name":"Roger Mertens",
    "wof:placetype":"venue"
},
  "geometry": {"coordinates":[2.6674098969,51.0584754944],"type":"Point"}
}