{
  "type": "Feature",
  "properties": {
    "iso:country":"BE",
    "sg:address":"Achouffe 16",
    "sg:city":"Houffalize",
    "sg:orig_category":"Rundveehouders",
    "sg:phone":"+32 61 28 89 82",
    "sg:postcode":"6666",
    "sg:province":"Luxembourg",
    "wof:name":"Marcel Frenoy",
    "wof:placetype":"venue"
},
  "geometry": {"coordinates":[5.7208809853,50.1656913757],"type":"Point"}
}