{
  "type": "Feature",
  "properties": {
    "iso:country":"BE",
    "sg:address":"Dr\u00e8ve De La Curette 23",
    "sg:city":"Villers-la-ville",
    "sg:classifiers":[
        {
            "category":"Retail",
            "subcategory":"Auto Repair",
            "type":"Services"
        }
    ],
    "sg:phone":"+32 71 87 48 81",
    "sg:postcode":"1495",
    "sg:province":"Brabant Wallon",
    "sg:tags":[
        "garage"
    ],
    "wof:name":"Combecar Sa",
    "wof:placetype":"venue"
},
  "geometry": {"coordinates":[4.5425200462,50.5768966675],"type":"Point"}
}