{
  "type": "Feature",
  "properties": {
    "iso:country":"BE",
    "sg:address":"Rue De Huy 219",
    "sg:city":"Faimes",
    "sg:classifiers":[
        {
            "category":"Cafe",
            "type":"Food & Drink"
        }
    ],
    "sg:phone":"+32 19 32 79 40",
    "sg:postcode":"4317",
    "sg:province":"Li\u00e8ge",
    "sg:tags":[
        "caf\u00e9s"
    ],
    "wof:name":"Roger Joannes",
    "wof:placetype":"venue"
},
  "geometry": {"coordinates":[5.2543201447,50.6671295166],"type":"Point"}
}