{
  "type": "Feature",
  "properties": {
    "iso:country":"BE",
    "sg:address":"Rue De France 111",
    "sg:city":"Anderlecht",
    "sg:orig_category":"Levering aan huis restaurants Restaurants",
    "sg:phone":"+32 2 520 05 12",
    "sg:postcode":"1070",
    "sg:province":"Bruxelles-Capitale",
    "wof:name":"Chang",
    "wof:placetype":"venue"
},
  "geometry": {"coordinates":[4.3302598,50.8328399658],"type":"Point"}
}