{
  "type": "Feature",
  "properties": {
    "addr:full":"Vosseschijnstraat 98 Antwerpen Antwerpen 2030",
    "addr:housenumber":"98",
    "addr:postcode":"2030",
    "addr:street":"Vosseschijnstraat",
    "iso:country":"BE",
    "sg:address":"Vosseschijnstraat 98",
    "sg:city":"Antwerpen",
    "sg:classifiers":[
        {
            "category":"Building & Trades",
            "subcategory":"Construction",
            "type":"Services"
        }
    ],
    "sg:phone":"+32 3 546 45 00",
    "sg:postcode":"2030",
    "sg:province":"Antwerpen",
    "sg:tags":[
        "fork",
        "lift",
        "truck"
    ],
    "wof:name":"Noell Reggiane Belgium Nv",
    "wof:placetype":"venue"
},
  "geometry": {"coordinates":[4.3952641487,51.26379776],"type":"Point"}
}