{
  "type": "Feature",
  "properties": {
    "addr:full":"Staanijzerstraat 41 Heuvelland (wijtschate) West-Vlaanderen 8953",
    "addr:housenumber":"41",
    "addr:postcode":"8953",
    "addr:street":"Staanijzerstraat",
    "iso:country":"BE",
    "sg:address":"Staanijzerstraat 41",
    "sg:city":"Heuvelland (wijtschate)",
    "sg:classifiers":[
        {
            "category":"Banks & Credit Unions",
            "subcategory":"Investment Brokerage",
            "type":"Services"
        }
    ],
    "sg:phone":"+32 57 44 52 50",
    "sg:postcode":"8953",
    "sg:province":"West-Vlaanderen",
    "sg:tags":[
        "printing",
        "-"
    ],
    "wof:name":"Verscheure Drukkerij",
    "wof:placetype":"venue"
},
  "geometry": {"coordinates":[2.8860659599,50.7852401733],"type":"Point"}
}