{
  "type": "Feature",
  "properties": {
    "addr:full":"Rue Pierre Wathieu 26 Saint-nicolas (montegn\u00e9e) Li\u00e8ge 4420",
    "addr:housenumber":"26",
    "addr:postcode":"4420",
    "addr:street":"Rue Pierre Wathieu;Montegne\u0301E",
    "iso:country":"BE",
    "sg:address":"Rue Pierre Wathieu 26",
    "sg:city":"Saint-nicolas (montegn\u00e9e)",
    "sg:classifiers":[
        {
            "category":"Retail",
            "subcategory":"Auto Repair",
            "type":"Services"
        }
    ],
    "sg:phone":"+32 4 231 12 44",
    "sg:postcode":"4420",
    "sg:province":"Li\u00e8ge",
    "sg:tags":[
        "automobile-body"
    ],
    "wof:name":"Detrez Design Sprl",
    "wof:placetype":"venue"
},
  "geometry": {"coordinates":[5.5073971748,50.6301307678],"type":"Point"}
}