{
  "type": "Feature",
  "properties": {
    "iso:country":"BE",
    "sg:address":"Brandhoutkaai 39",
    "sg:city":"Brussel",
    "sg:classifiers":[
        {
            "category":"Farming",
            "subcategory":"Livestock Farm",
            "type":"Manufacturing & Wholesale Goods"
        }
    ],
    "sg:phone":"+32 2 218 25 02",
    "sg:postcode":"1000",
    "sg:province":"Bruxelles-Capitale",
    "sg:tags":[
        "breeding",
        "agriculture",
        "animal"
    ],
    "wof:name":"Nv Aalvis",
    "wof:placetype":"venue"
},
  "geometry": {"coordinates":[4.3481631279,50.8525390625],"type":"Point"}
}