{
  "type": "Feature",
  "properties": {
    "addr:full":"Wijshagerkiezel 106 Meeuwen-gruitrode (meeuwen) Limburg 3670",
    "addr:housenumber":"106",
    "addr:postcode":"3670",
    "addr:street":"Wijshagerkiezel",
    "iso:country":"BE",
    "sg:address":"Wijshagerkiezel 106",
    "sg:city":"Meeuwen-gruitrode (meeuwen)",
    "sg:classifiers":[
        {
            "category":"Autos & Motor Vehicles",
            "subcategory":"Motorcycle Sales",
            "type":"Retail Goods"
        }
    ],
    "sg:phone":"+32 89 46 32 48",
    "sg:postcode":"3670",
    "sg:province":"Limburg",
    "sg:tags":[
        "scooter",
        "-",
        "moped"
    ],
    "wof:name":"Timmers M",
    "wof:placetype":"venue"
},
  "geometry": {"coordinates":[5.5647549629,51.1056861877],"type":"Point"}
}