{
  "type": "Feature",
  "properties": {
    "iso:country":"BE",
    "sg:address":"Sint-bavostraat 20",
    "sg:city":"Antwerpen",
    "sg:orig_category":"Musea and historische gebouwen",
    "sg:phone":"+32 3 828 85 51",
    "sg:postcode":"2610",
    "sg:province":"Antwerpen",
    "wof:name":"Heemmuseum Wilrica",
    "wof:placetype":"venue"
},
  "geometry": {"coordinates":[4.3946051598,51.1691131592],"type":"Point"}
}