{
  "type": "Feature",
  "properties": {
    "addr:full":"Val Des Seigneurs 81 Sint-pieters-woluwe/woluwe-sai Bruxelles-Capitale 1150",
    "addr:housenumber":"81",
    "addr:postcode":"1150",
    "addr:street":"Val Des Seigneurs",
    "iso:country":"BE",
    "sg:address":"Val Des Seigneurs 81",
    "sg:city":"Sint-pieters-woluwe/woluwe-sai",
    "sg:classifiers":[
        {
            "category":"Restaurant",
            "type":"Food & Drink"
        }
    ],
    "sg:phone":"+32 2 771 14 47",
    "sg:postcode":"1150",
    "sg:province":"Bruxelles-Capitale",
    "wof:name":"Les Deux Maisons",
    "wof:placetype":"venue"
},
  "geometry": {"coordinates":[4.4598650932,50.8413162231],"type":"Point"}
}