{
  "type": "Feature",
  "properties": {
    "addr:full":"Avenue De Stalingrad 57 Bruxelles Bruxelles-Capitale 1000",
    "addr:housenumber":"57",
    "addr:postcode":"1000",
    "addr:street":"Avenue De Stalingrad",
    "iso:country":"BE",
    "sg:address":"Avenue De Stalingrad 57",
    "sg:city":"Bruxelles",
    "sg:classifiers":[
        {
            "category":"Home & Garden",
            "subcategory":"Building Materials",
            "type":"Retail Goods"
        }
    ],
    "sg:phone":"+32 2 502 46 00",
    "sg:postcode":"1000",
    "sg:province":"Bruxelles-Capitale",
    "sg:tags":[
        "article",
        "-",
        "do-it-yourself"
    ],
    "wof:name":"Midi Brico",
    "wof:placetype":"venue"
},
  "geometry": {"coordinates":[4.3431921005,50.8409805298],"type":"Point"}
}