{
  "type": "Feature",
  "properties": {
    "addr:full":"Kerkhovensesteenweg 84 Lommel Limburg 3920",
    "addr:housenumber":"84",
    "addr:postcode":"3920",
    "addr:street":"Kerkhovensesteenweg",
    "iso:country":"BE",
    "sg:address":"Kerkhovensesteenweg 84",
    "sg:city":"Lommel",
    "sg:orig_category":"Matelas Fab",
    "sg:phone":"+32 11 54 90 00",
    "sg:postcode":"3920",
    "sg:province":"Limburg",
    "wof:name":"Polypreen Belgi\u00cb",
    "wof:placetype":"venue"
},
  "geometry": {"coordinates":[5.2931070328,51.1791687012],"type":"Point"}
}