{
  "type": "Feature",
  "properties": {
    "iso:country":"BE",
    "sg:address":"Ninoofsesteenweg 359",
    "sg:city":"Dilbeek",
    "sg:classifiers":[
        {
            "category":"Retail",
            "subcategory":"Storage",
            "type":"Services"
        }
    ],
    "sg:phone":"+32 2 720 80 18",
    "sg:postcode":"1700",
    "sg:province":"Vlaams-Brabant",
    "sg:tags":[
        "rack",
        "system"
    ],
    "wof:name":"Tixit/marc Van Ackere",
    "wof:placetype":"venue"
},
  "geometry": {"coordinates":[4.2600841522,50.8437690735],"type":"Point"}
}