{
  "type": "Feature",
  "properties": {
    "addr:full":"Polderinstraat 16 Staden (oostnieuwkerke) West-Vlaanderen 8840",
    "addr:housenumber":"16",
    "addr:postcode":"8840",
    "addr:street":"Polderinstraat",
    "iso:country":"BE",
    "sg:address":"Polderinstraat 16",
    "sg:city":"Staden (oostnieuwkerke)",
    "sg:classifiers":[
        {
            "category":"Food & Beverages",
            "subcategory":"Fruits & Vegetables",
            "type":"Retail Goods"
        }
    ],
    "sg:phone":"+32 51 24 70 22",
    "sg:postcode":"8840",
    "sg:province":"West-Vlaanderen",
    "sg:tags":[
        "-"
    ],
    "wof:name":"Ceenaeme P",
    "wof:placetype":"venue"
},
  "geometry": {"coordinates":[3.0826640129,50.9491157532],"type":"Point"}
}