{
  "type": "Feature",
  "properties": {
    "iso:country":"BE",
    "sg:address":"Henri Devedeleerstraat 30",
    "sg:city":"Halle (buizingen)",
    "sg:classifiers":[
        {
            "category":"Communications",
            "subcategory":"Film & Video Production",
            "type":"Services"
        }
    ],
    "sg:phone":"+32 2 360 30 59",
    "sg:postcode":"1501",
    "sg:province":"Vlaams-Brabant",
    "sg:tags":[
        "realisation",
        "-"
    ],
    "wof:name":"S.p.f. Production",
    "wof:placetype":"venue"
},
  "geometry": {"coordinates":[4.2657418251,50.741809845],"type":"Point"}
}