{
  "type": "Feature",
  "properties": {
    "addr:full":"Avenue De La Chasse 195 Bruxelles (etterbeek) Bruxelles-Capitale 1040",
    "addr:housenumber":"195",
    "addr:postcode":"1040",
    "addr:street":"Avenue De La Chasse",
    "iso:country":"BE",
    "sg:address":"Avenue De La Chasse 195",
    "sg:city":"Bruxelles (etterbeek)",
    "sg:classifiers":[
        {
            "category":"Retail",
            "subcategory":"Event Space",
            "type":"Services"
        }
    ],
    "sg:phone":"+32 2 739 63 98",
    "sg:postcode":"1040",
    "sg:province":"Bruxelles-Capitale",
    "sg:tags":[
        "organisation"
    ],
    "wof:name":"K Par K Events & Communication",
    "wof:placetype":"venue"
},
  "geometry": {"coordinates":[4.3946151733,50.8355255127],"type":"Point"}
}