{
  "type": "Feature",
  "properties": {
    "iso:country":"BE",
    "sg:address":"Grondwetlaan 120",
    "sg:city":"Gent",
    "sg:orig_category":"Traitements param\u00e9dicaux",
    "sg:phone":"+32 9 251 83 43",
    "sg:postcode":"9040",
    "sg:province":"Oost-Vlaanderen",
    "wof:name":"I. Puttemans",
    "wof:placetype":"venue"
},
  "geometry": {"coordinates":[3.7503640652,51.0679130554],"type":"Point"}
}