{
  "type": "Feature",
  "properties": {
    "iso:country":"BE",
    "sg:address":"Rue F\u00c9tis 52",
    "sg:city":"Etterbeek",
    "sg:orig_category":"D\u00e9corateurs d'int\u00e9rieur",
    "sg:phone":"+32 2 640 02 62",
    "sg:postcode":"1040",
    "sg:province":"Bruxelles-Capitale",
    "wof:name":"Carr\u00c9-tiers",
    "wof:placetype":"venue"
},
  "geometry": {"coordinates":[4.3876309395,50.8342018127],"type":"Point"}
}