{
  "type": "Feature",
  "properties": {
    "iso:country":"BE",
    "sg:address":"Balgerhoeke 97",
    "sg:city":"Eeklo",
    "sg:classifiers":[
        {
            "category":"Cafe",
            "type":"Food & Drink"
        }
    ],
    "sg:phone":"+32 9 377 36 65",
    "sg:postcode":"9900",
    "sg:province":"Oost-Vlaanderen",
    "sg:tags":[
        "caf\u00e9s"
    ],
    "wof:name":"Caf\u00c9 Het Zotteke",
    "wof:placetype":"venue"
},
  "geometry": {"coordinates":[3.5163099766,51.2047729492],"type":"Point"}
}