{
  "type": "Feature",
  "properties": {
    "addr:full":"Rue Patenier 65 Namur Namur 5000",
    "addr:housenumber":"65",
    "addr:postcode":"5000",
    "addr:street":"Rue Patenier",
    "iso:country":"BE",
    "sg:address":"Rue Patenier 65",
    "sg:city":"Namur",
    "sg:classifiers":[
        {
            "category":"Home & Garden",
            "subcategory":"Carpets & Floor Coverings",
            "type":"Retail Goods"
        }
    ],
    "sg:phone":"+32 81 72 80 92",
    "sg:postcode":"5000",
    "sg:province":"Namur",
    "sg:tags":[
        "parquet"
    ],
    "wof:name":"Tout Parquet",
    "wof:placetype":"venue"
},
  "geometry": {"coordinates":[4.8461041451,50.4633789062],"type":"Point"}
}