{
  "type": "Feature",
  "properties": {
    "addr:full":"Rue De Warcoing 4bc Estaimpuis Hainaut 7730",
    "addr:housenumber":"4bc",
    "addr:postcode":"7730",
    "addr:street":"Rue De Warcoing;Hainaut",
    "iso:country":"BE",
    "sg:address":"Rue De Warcoing 4bc",
    "sg:city":"Estaimpuis",
    "sg:orig_category":"Sportclubs Sportterreinen and installaties behalve sportcentra",
    "sg:phone":"+32 56 48 67 69",
    "sg:postcode":"7730",
    "sg:province":"Hainaut",
    "wof:name":"S.c. Mont De L\u00b4enclus",
    "wof:placetype":"venue"
},
  "geometry": {"coordinates":[3.315351963,50.7056427002],"type":"Point"}
}