{
  "type": "Feature",
  "properties": {
    "iso:country":"BE",
    "sg:address":"Jol\u00c9laan 21",
    "sg:city":"Oudergem/auderghem",
    "sg:orig_category":"Rusthuizen and serviceflats",
    "sg:phone":"+32 2 673 28 04",
    "sg:postcode":"1160",
    "sg:province":"Bruxelles-Capitale",
    "wof:name":"Paule Buffin",
    "wof:placetype":"venue"
},
  "geometry": {"coordinates":[4.4340558052,50.8121337891],"type":"Point"}
}