{
  "type": "Feature",
  "properties": {
    "addr:full":"Daloensdelle 50 Overijse Vlaams-Brabant 3090",
    "addr:housenumber":"50",
    "addr:postcode":"3090",
    "addr:street":"Daloensdelle",
    "iso:country":"BE",
    "sg:address":"Daloensdelle 50",
    "sg:city":"Overijse",
    "sg:orig_category":"Non-Classified Establishments",
    "sg:phone":"+32 2 657 98 05",
    "sg:postcode":"3090",
    "sg:province":"Vlaams-Brabant",
    "wof:name":"R M G Fashion Frames Bvba",
    "wof:placetype":"venue"
},
  "geometry": {"coordinates":[4.5371460915,50.7635993958],"type":"Point"}
}