{
  "type": "Feature",
  "properties": {
    "iso:country":"BE",
    "sg:address":"Rue De Boussoit",
    "sg:city":"Maurage",
    "sg:orig_category":"Huisdieren and benodigdheden Royal Canin",
    "sg:phone":"+32 64 66 45 88",
    "sg:postcode":"7110",
    "sg:province":"Hainaut",
    "wof:name":"Rousseau",
    "wof:placetype":"venue"
},
  "geometry": {"coordinates":[4.0969810486,50.4567756653],"type":"Point"}
}