{
  "type": "Feature",
  "properties": {
    "addr:full":"Rue Emile Mazy 29 Profondeville Namur 5170",
    "addr:housenumber":"29",
    "addr:postcode":"5170",
    "addr:street":"Rue Emile Mazy",
    "iso:country":"BE",
    "sg:address":"Rue Emile Mazy 29",
    "sg:city":"Profondeville",
    "sg:orig_category":"Paramedische behandelingen",
    "sg:phone":"+32 81 43 37 09",
    "sg:postcode":"5170",
    "sg:province":"Namur",
    "wof:name":"A. Dannevoye",
    "wof:placetype":"venue"
},
  "geometry": {"coordinates":[4.8078570366,50.3897514343],"type":"Point"}
}