{
  "type": "Feature",
  "properties": {
    "iso:country":"BE",
    "sg:address":"Mechelse Steenweg 161",
    "sg:city":"Antwerpen",
    "sg:orig_category":"Non-Classified Establishments",
    "sg:phone":"+32 3 289 90 34",
    "sg:postcode":"2018",
    "sg:province":"Antwerpen",
    "wof:name":"Chris Janssens Bvba",
    "wof:placetype":"venue"
},
  "geometry": {"coordinates":[4.4110012054,51.2048377991],"type":"Point"}
}