{
  "type": "Feature",
  "properties": {
    "addr:full":"Place L'hotel-de-ville 17 Florennes Namur 5620",
    "addr:housenumber":"17",
    "addr:postcode":"5620",
    "addr:street":"Place L'Hotel-De-Ville",
    "iso:country":"BE",
    "sg:address":"Place L'hotel-de-ville 17",
    "sg:city":"Florennes",
    "sg:orig_category":"Banques and organismes de cr\u00e9dit",
    "sg:phone":"+32 71 68 96 14",
    "sg:postcode":"5620",
    "sg:province":"Namur",
    "wof:name":"Cr\u00c9dit Agricole",
    "wof:placetype":"venue"
},
  "geometry": {"coordinates":[4.6022891998,50.2510032654],"type":"Point"}
}