{
  "type": "Feature",
  "properties": {
    "iso:country":"BE",
    "sg:address":"Hoog Mosscher 80",
    "sg:city":"Kortrijk",
    "sg:classifiers":[
        {
            "category":"Real Estate",
            "subcategory":"Architect",
            "type":"Services"
        }
    ],
    "sg:phone":"+32 56 25 71 76",
    "sg:postcode":"8500",
    "sg:province":"West-Vlaanderen",
    "wof:name":"Vanheuverzwijn L",
    "wof:placetype":"venue"
},
  "geometry": {"coordinates":[3.256467104,50.8150405884],"type":"Point"}
}