{
  "type": "Feature",
  "properties": {
    "addr:full":"Grand-route 35 Bassenge Li\u00e8ge 4690",
    "addr:housenumber":"35",
    "addr:postcode":"4690",
    "addr:street":"Grand-Route",
    "iso:country":"BE",
    "sg:address":"Grand-route 35",
    "sg:city":"Bassenge",
    "sg:orig_category":"Boucheries",
    "sg:phone":"+32 4 286 41 25",
    "sg:postcode":"4690",
    "sg:province":"Li\u00e8ge",
    "wof:name":"Jean-marie Delince",
    "wof:placetype":"venue"
},
  "geometry": {"coordinates":[5.6048378944,50.7541503906],"type":"Point"}
}