{
  "type": "Feature",
  "properties": {
    "addr:full":"Ambachtstraat 16 Malle Antwerpen 2390",
    "addr:housenumber":"16",
    "addr:postcode":"2390",
    "addr:street":"Ambachtstraat",
    "iso:country":"BE",
    "sg:address":"Ambachtstraat 16",
    "sg:city":"Malle",
    "sg:classifiers":[
        {
            "category":"Building & Trades",
            "subcategory":"Plumbing",
            "type":"Services"
        }
    ],
    "sg:phone":"+32 3 309 25 26",
    "sg:postcode":"2390",
    "sg:province":"Antwerpen",
    "sg:tags":[
        "diver",
        "commerce",
        "gr",
        "pour",
        "equipement"
    ],
    "wof:name":"Morehouse-cowles Int Belgium",
    "wof:placetype":"venue"
},
  "geometry": {"coordinates":[4.7090167999,51.2922859192],"type":"Point"}
}