{
  "type": "Feature",
  "properties": {
    "iso:country":"BE",
    "sg:address":"Rue Saint-gilles 131",
    "sg:city":"Li\u00e8ge 1",
    "sg:classifiers":[
        {
            "category":"Shopping",
            "subcategory":"Clothing, Apparel, & Fashions",
            "type":"Retail Goods"
        }
    ],
    "sg:phone":"+32 4 223 69 58",
    "sg:postcode":"4000",
    "sg:province":"Li\u00e8ge",
    "sg:tags":[
        "clothing",
        "-",
        "gentleman"
    ],
    "wof:name":"L'ev\u00eaque R",
    "wof:placetype":"venue"
},
  "geometry": {"coordinates":[5.5631771088,50.6379051208],"type":"Point"}
}