{
  "type": "Feature",
  "properties": {
    "addr:full":"Rue De Chateaumont 12 Bouillon Luxembourg 6833",
    "addr:housenumber":"12",
    "addr:postcode":"6833",
    "addr:street":"Rue De Chateaumont",
    "iso:country":"BE",
    "sg:address":"Rue De Chateaumont 12",
    "sg:city":"Bouillon",
    "sg:orig_category":"Maisons de vacances. Mus\u00e9es and patrimoine culturel",
    "sg:phone":"+32 61 46 67 72",
    "sg:postcode":"6833",
    "sg:province":"Luxembourg",
    "wof:name":"Mus\u00c9e De La F\u00d4ret Des Lavandi\u00c8res",
    "wof:placetype":"venue"
},
  "geometry": {"coordinates":[5.0515799522,49.8228187561],"type":"Point"}
}