{
  "type": "Feature",
  "properties": {
    "iso:country":"BE",
    "sg:address":"Gierledreef 17",
    "sg:city":"Turnhout",
    "sg:classifiers":[
        {
            "category":"Real Estate",
            "subcategory":"Architect",
            "type":"Services"
        }
    ],
    "sg:phone":"+32 14 41 45 71",
    "sg:postcode":"2300",
    "sg:province":"Antwerpen",
    "wof:name":"Weyns S",
    "wof:placetype":"venue"
},
  "geometry": {"coordinates":[4.9257421494,51.318977356],"type":"Point"}
}