{
  "type": "Feature",
  "properties": {
    "addr:full":"Amerikaanse Straat 76 Elsene/ixelles Bruxelles-Capitale 1050",
    "addr:housenumber":"76",
    "addr:postcode":"1050",
    "addr:street":"Amerikaanse Straat",
    "iso:country":"BE",
    "sg:address":"Amerikaanse Straat 76",
    "sg:city":"Elsene/ixelles",
    "sg:orig_category":"Film-, tv- and videoproductie",
    "sg:phone":"+32 2 539 39 75",
    "sg:postcode":"1050",
    "sg:province":"Bruxelles-Capitale",
    "wof:name":"Zero Gravity",
    "wof:placetype":"venue"
},
  "geometry": {"coordinates":[4.3582458496,50.8236351013],"type":"Point"}
}