{
  "type": "Feature",
  "properties": {
    "iso:country":"BE",
    "sg:address":"Rue De La Station 22",
    "sg:city":"Braine-le-comte",
    "sg:classifiers":[
        {
            "category":"Professional",
            "subcategory":"Testing Lab",
            "type":"Services"
        }
    ],
    "sg:phone":"+32 67 55 21 37",
    "sg:postcode":"7090",
    "sg:province":"Hainaut",
    "sg:tags":[
        "chemist"
    ],
    "wof:name":"Fiasse-croquet Sa",
    "wof:placetype":"venue"
},
  "geometry": {"coordinates":[4.1372628212,50.6096916199],"type":"Point"}
}