{
  "type": "Feature",
  "properties": {
    "addr:full":"Rue D'utue 4 Gedinne Namur 5575",
    "addr:housenumber":"4",
    "addr:postcode":"5575",
    "addr:street":"Rue D'Utue",
    "iso:country":"BE",
    "sg:address":"Rue D'utue 4",
    "sg:city":"Gedinne",
    "sg:classifiers":[
        {
            "category":"Building & Trades",
            "subcategory":"Construction",
            "type":"Services"
        }
    ],
    "sg:phone":"+32 61 58 87 80",
    "sg:postcode":"5575",
    "sg:province":"Namur",
    "sg:tags":[
        "carpenter"
    ],
    "wof:name":"Leonard Ch",
    "wof:placetype":"venue"
},
  "geometry": {"coordinates":[4.9336481094,49.9803199768],"type":"Point"}
}