{
  "type": "Feature",
  "properties": {
    "addr:full":"Rue Des Chass. Ardennais 8 Leglise Luxembourg 6860",
    "addr:housenumber":"8",
    "addr:postcode":"6860",
    "addr:street":"Rue Des Chass. Ardennais",
    "iso:country":"BE",
    "sg:address":"Rue Des Chass. Ardennais 8",
    "sg:city":"Leglise",
    "sg:orig_category":"Rundveehouders",
    "sg:phone":"+32 63 60 06 72",
    "sg:postcode":"6860",
    "sg:province":"Luxembourg",
    "wof:name":"Bradfer Alphonse Roger",
    "wof:placetype":"venue"
},
  "geometry": {"coordinates":[5.5967988968,49.8555221558],"type":"Point"}
}