{
  "type": "Feature",
  "properties": {
    "addr:full":"Rue Des Foss\u00e9s Fleuris 44 Namur Namur 5000",
    "addr:housenumber":"44",
    "addr:postcode":"5000",
    "addr:street":"Rue Des Fosse\u0301S Fleuris",
    "iso:country":"BE",
    "sg:address":"Rue Des Foss\u00e9s Fleuris 44",
    "sg:city":"Namur",
    "sg:classifiers":[
        {
            "category":"Personal",
            "subcategory":"Beauty Salon",
            "type":"Services"
        }
    ],
    "sg:phone":"+32 81 24 12 14",
    "sg:postcode":"5000",
    "sg:province":"Namur",
    "wof:name":"Institut Fraicheur Marine",
    "wof:placetype":"venue"
},
  "geometry": {"coordinates":[4.8641281128,50.4625968933],"type":"Point"}
}