{
  "type": "Feature",
  "properties": {
    "addr:full":"Leuvensesteenweg 15 Tielt-winge Vlaams-Brabant 3390",
    "addr:housenumber":"15",
    "addr:postcode":"3390",
    "addr:street":"Leuvensesteenweg",
    "iso:country":"BE",
    "sg:address":"Leuvensesteenweg 15",
    "sg:city":"Tielt-winge",
    "sg:orig_category":"Elektrische installaties voor woningen Hout and afgeleiden Gh IJzerwaren, bouw- and verfmaterialen",
    "sg:phone":"+32 16 63 40 38",
    "sg:postcode":"3390",
    "sg:province":"Vlaams-Brabant",
    "wof:name":"Coekaerts",
    "wof:placetype":"venue"
},
  "geometry": {"coordinates":[4.9083800316,50.9250183105],"type":"Point"}
}