{
  "type": "Feature",
  "properties": {
    "addr:full":"Rue Des Ecoles 8 Bastogne Luxembourg 6600",
    "addr:housenumber":"8",
    "addr:postcode":"6600",
    "addr:street":"Rue Des Ecoles",
    "iso:country":"BE",
    "sg:address":"Rue Des Ecoles 8",
    "sg:city":"Bastogne",
    "sg:orig_category":"Enseignement secondaire g\u00e9n\u00e9ral",
    "sg:phone":"+32 61 21 22 14",
    "sg:postcode":"6600",
    "sg:province":"Luxembourg",
    "wof:name":"Institut Notre-dame",
    "wof:placetype":"venue"
},
  "geometry": {"coordinates":[5.715681076,50.0023117065],"type":"Point"}
}