{
  "type": "Feature",
  "properties": {
    "iso:country":"BE",
    "sg:address":"Rue Au Bois 212",
    "sg:city":"Sint-pieters-woluwe/woluwe-saint-pierre",
    "sg:orig_category":"Pharmaciens",
    "sg:phone":"+32 2 770 89 45",
    "sg:postcode":"1150",
    "sg:province":"Bruxelles-Capitale",
    "wof:name":"Multipharma",
    "wof:placetype":"venue"
},
  "geometry": {"coordinates":[4.4483380318,50.832901001],"type":"Point"}
}