{
  "type": "Feature",
  "properties": {
    "addr:full":"Dokter Haubenlaan 57 Maasmechelen Limburg 3630",
    "addr:housenumber":"57",
    "addr:postcode":"3630",
    "addr:street":"Dokter Haubenlaan",
    "iso:country":"BE",
    "sg:address":"Dokter Haubenlaan 57",
    "sg:city":"Maasmechelen",
    "sg:orig_category":"Begrafeniswezen Natuursteenbewerking",
    "sg:phone":"+32 89 76 41 15",
    "sg:postcode":"3630",
    "sg:province":"Limburg",
    "wof:name":"Leenders & Konings",
    "wof:placetype":"venue"
},
  "geometry": {"coordinates":[5.7003331184,50.9620132446],"type":"Point"}
}