{
  "type": "Feature",
  "properties": {
    "addr:full":"Place Cardinal-mercier 12 Dinant Namur 5500",
    "addr:housenumber":"12",
    "addr:postcode":"5500",
    "addr:street":"Place Cardinal-Mercier",
    "iso:country":"BE",
    "sg:address":"Place Cardinal-mercier 12",
    "sg:city":"Dinant",
    "sg:orig_category":"Supermarkten",
    "sg:phone":"+32 82 22 46 59",
    "sg:postcode":"5500",
    "sg:province":"Namur",
    "wof:name":"Delhaize",
    "wof:placetype":"venue"
},
  "geometry": {"coordinates":[4.8966798782,50.2709693909],"type":"Point"}
}