{
  "type": "Feature",
  "properties": {
    "addr:full":"Kanaalweg 20 Oostrozebeke West-Vlaanderen 8780",
    "addr:housenumber":"20",
    "addr:postcode":"8780",
    "addr:street":"Kanaalweg",
    "iso:country":"BE",
    "sg:address":"Kanaalweg 20",
    "sg:city":"Oostrozebeke",
    "sg:classifiers":[
        {
            "category":"Building & Trades",
            "subcategory":"Electrical",
            "type":"Services"
        }
    ],
    "sg:phone":"+32 497 41 05 99",
    "sg:postcode":"8780",
    "sg:province":"West-Vlaanderen",
    "sg:tags":[
        "electric",
        "-",
        "housewiring",
        "contractor"
    ],
    "wof:name":"Bs-electric",
    "wof:placetype":"venue"
},
  "geometry": {"coordinates":[3.3136730194,50.9062461853],"type":"Point"}
}