{
  "type": "Feature",
  "properties": {
    "iso:country":"BE",
    "sg:address":"Rue D'ascotte 41",
    "sg:city":"Braine-le-comte",
    "sg:orig_category":"Caf\u00e9s Kampeerterreinen",
    "sg:phone":"+32 67 45 83 12",
    "sg:postcode":"7090",
    "sg:province":"Hainaut",
    "wof:name":"Camping Les Acacias",
    "wof:placetype":"venue"
},
  "geometry": {"coordinates":[4.1355600357,50.610748291],"type":"Point"}
}