{
  "type": "Feature",
  "properties": {
    "iso:country":"BE",
    "sg:address":"Rue De Pailhe 4",
    "sg:city":"Marchin",
    "sg:orig_category":"Astrologen, grafologen and mediums",
    "sg:phone":"+32 85 41 24 20",
    "sg:postcode":"4570",
    "sg:province":"Li\u00e8ge",
    "wof:name":"Libris",
    "wof:placetype":"venue"
},
  "geometry": {"coordinates":[5.2686190605,50.4458427429],"type":"Point"}
}