{
  "type": "Feature",
  "properties": {
    "addr:full":"Krepelstraat 28a Ninove (denderwindeke) Oost-Vlaanderen 9400",
    "addr:housenumber":"28a",
    "addr:postcode":"9400",
    "addr:street":"Krepelstraat",
    "iso:country":"BE",
    "sg:address":"Krepelstraat 28a",
    "sg:city":"Ninove (denderwindeke)",
    "sg:classifiers":[
        {
            "category":"Real Estate",
            "subcategory":"Architect",
            "type":"Services"
        }
    ],
    "sg:phone":"+32 54 33 52 77",
    "sg:postcode":"9400",
    "sg:province":"Oost-Vlaanderen",
    "wof:name":"De Ro P",
    "wof:placetype":"venue"
},
  "geometry": {"coordinates":[4.0232000351,50.8349113464],"type":"Point"}
}