{
  "type": "Feature",
  "properties": {
    "iso:country":"BE",
    "sg:address":"Hoogstr 102",
    "sg:city":"Bavikhove",
    "sg:classifiers":[
        {
            "category":"Shopping",
            "subcategory":"Computers & Home Electronics",
            "type":"Retail Goods"
        }
    ],
    "sg:phone":"+32 56 65 09 00",
    "sg:postcode":"8531",
    "sg:province":"West-Vlaanderen",
    "sg:tags":[
        "electric",
        "electricity",
        "component",
        "equipment",
        "electrical",
        "electronic"
    ],
    "wof:name":"Callewaert Nv",
    "wof:placetype":"venue"
},
  "geometry": {"coordinates":[3.3158950806,50.8833961487],"type":"Point"}
}