{
  "type": "Feature",
  "properties": {
    "addr:full":"Chauss\u00c9e De Theux 76 Verviers Li\u00e8ge 4802",
    "addr:housenumber":"76",
    "addr:postcode":"4802",
    "addr:street":"Chausse\u0301E De Theux",
    "iso:country":"BE",
    "sg:address":"Chauss\u00c9e De Theux 76",
    "sg:city":"Verviers",
    "sg:classifiers":[
        {
            "category":"Insurance",
            "subcategory":"Life Insurance",
            "type":"Services"
        }
    ],
    "sg:phone":"+32 87 22 54 56",
    "sg:postcode":"4802",
    "sg:province":"Li\u00e8ge",
    "sg:tags":[
        "assurance"
    ],
    "wof:name":"Groupe Vervi\u00c9t. Assureurs",
    "wof:placetype":"venue"
},
  "geometry": {"coordinates":[5.8671250343,50.5714111328],"type":"Point"}
}