{
  "type": "Feature",
  "properties": {
    "iso:country":"BE",
    "sg:address":"Leemstraat 104",
    "sg:city":"Sint-katelijne-waver",
    "sg:classifiers":[
        {
            "category":"Insurance",
            "subcategory":"Life Insurance",
            "type":"Services"
        }
    ],
    "sg:phone":"+32 15 76 04 57",
    "sg:postcode":"2861",
    "sg:province":"Antwerpen",
    "sg:tags":[
        "assurance"
    ],
    "wof:name":"Hendrickx-de Bruyn",
    "wof:placetype":"venue"
},
  "geometry": {"coordinates":[4.590359211,51.0588226318],"type":"Point"}
}