{
  "type": "Feature",
  "properties": {
    "addr:full":"Schaarbeekstraat 4ba Zwijndrecht Antwerpen 2070",
    "addr:housenumber":"4ba",
    "addr:postcode":"2070",
    "addr:street":"Schaarbeekstraat",
    "iso:country":"BE",
    "sg:address":"Schaarbeekstraat 4ba",
    "sg:city":"Zwijndrecht",
    "sg:orig_category":"Producteurs de l\u00e9gumes. Producteurs de fruits",
    "sg:phone":"+32 3 252 81 91",
    "sg:postcode":"2070",
    "sg:province":"Antwerpen",
    "wof:name":"Omer Van Haute",
    "wof:placetype":"venue"
},
  "geometry": {"coordinates":[4.3228421211,51.2002449036],"type":"Point"}
}