{
  "type": "Feature",
  "properties": {
    "iso:country":"BE",
    "sg:address":"Place Du Roi Albert 5",
    "sg:city":"Remicourt",
    "sg:orig_category":"Epiceries",
    "sg:phone":"+32 19 54 42 51",
    "sg:postcode":"4350",
    "sg:province":"Li\u00e8ge",
    "wof:name":"Lucien Milisen",
    "wof:placetype":"venue"
},
  "geometry": {"coordinates":[5.3047251701,50.6945762634],"type":"Point"}
}