{
  "type": "Feature",
  "properties": {
    "iso:country":"BE",
    "sg:address":"Kroonlaan 104",
    "sg:city":"Elsene/ixelles",
    "sg:orig_category":"Kapsalons",
    "sg:phone":"+32 2 648 07 36",
    "sg:postcode":"1050",
    "sg:province":"Bruxelles-Capitale",
    "wof:name":"Coiffure Julie",
    "wof:placetype":"venue"
},
  "geometry": {"coordinates":[4.3789229393,50.8300018311],"type":"Point"}
}