{
  "type": "Feature",
  "properties": {
    "addr:full":"Grensstraat 5 Koksijde West-Vlaanderen 8670",
    "addr:housenumber":"5",
    "addr:postcode":"8670",
    "addr:street":"Grensstraat",
    "iso:country":"BE",
    "sg:address":"Grensstraat 5",
    "sg:city":"Koksijde",
    "sg:classifiers":[
        {
            "category":"Arts & Performance",
            "subcategory":"Art Gallery",
            "type":"Entertainment"
        }
    ],
    "sg:phone":"+32 58 51 61 97",
    "sg:postcode":"8670",
    "sg:province":"West-Vlaanderen",
    "wof:name":"Wijland-werner Ryckeboer",
    "wof:placetype":"venue"
},
  "geometry": {"coordinates":[2.6445829868,51.1164970398],"type":"Point"}
}