{
  "type": "Feature",
  "properties": {
    "iso:country":"BE",
    "sg:address":"Mechelsesteenweg 132",
    "sg:city":"Edegem",
    "sg:classifiers":[
        {
            "category":"Organizations",
            "subcategory":"Community Association",
            "type":"Services"
        }
    ],
    "sg:phone":"+32 3 455 53 24",
    "sg:postcode":"2650",
    "sg:province":"Antwerpen",
    "sg:tags":[
        "box",
        "cardboard"
    ],
    "wof:name":"Unit Nv",
    "wof:placetype":"venue"
},
  "geometry": {"coordinates":[4.4632902145,51.1492614746],"type":"Point"}
}