{
  "type": "Feature",
  "properties": {
    "iso:country":"BE",
    "sg:address":"Rue Du Fr\u00c8re Merantius 2",
    "sg:city":"Virton",
    "sg:orig_category":"Drukkerijen and copyshops Papierwaren Reclamebureaus",
    "sg:phone":"+32 63 57 66 93",
    "sg:postcode":"6760",
    "sg:province":"Luxembourg",
    "wof:name":"Sbn Screen",
    "wof:placetype":"venue"
},
  "geometry": {"coordinates":[5.5944848061,49.5368843079],"type":"Point"}
}