{
  "type": "Feature",
  "properties": {
    "iso:country":"BE",
    "sg:address":"Rue Du Panorama 26",
    "sg:city":"Rixensart",
    "sg:orig_category":"M\u00e9decins and sp\u00e9cialistes",
    "sg:phone":"+32 2 653 83 71",
    "sg:postcode":"1331",
    "sg:province":"Brabant Wallon",
    "wof:name":"G\u00c9rard Van Braekel",
    "wof:placetype":"venue"
},
  "geometry": {"coordinates":[4.5303668976,50.7299308777],"type":"Point"}
}