{
  "type": "Feature",
  "properties": {
    "iso:country":"BE",
    "sg:address":"Oudstrijdersstraat 15",
    "sg:city":"Ingelmunster",
    "sg:orig_category":"Entretien and r\u00e9parations de voitures",
    "sg:phone":"+32 51 30 76 91",
    "sg:postcode":"8770",
    "sg:province":"West-Vlaanderen",
    "wof:name":"Roland Uyttenhove",
    "wof:placetype":"venue"
},
  "geometry": {"coordinates":[3.2603940964,50.9142227173],"type":"Point"}
}