{
  "type": "Feature",
  "properties": {
    "iso:country":"BE",
    "sg:address":"Petite Rue Des Loups 7",
    "sg:city":"Anderlecht",
    "sg:orig_category":"Plaatsen van vloer- and muurbekleding Schilders",
    "sg:phone":"+32 2 521 29 45",
    "sg:postcode":"1070",
    "sg:province":"Bruxelles-Capitale",
    "wof:name":"De Schmidt",
    "wof:placetype":"venue"
},
  "geometry": {"coordinates":[4.2960958481,50.8237380981],"type":"Point"}
}