{
  "type": "Feature",
  "properties": {
    "addr:full":"Henry Fordlaan 8b21 Genk Limburg 3600",
    "addr:housenumber":"8b21",
    "addr:postcode":"3600",
    "addr:street":"Henry Fordlaan",
    "iso:country":"BE",
    "sg:address":"Henry Fordlaan 8b21",
    "sg:city":"Genk",
    "sg:orig_category":"Onderdelen and accessoires voertuigen Gh",
    "sg:phone":"+32 89 61 61 11",
    "sg:postcode":"3600",
    "sg:province":"Limburg",
    "wof:name":"Ford-werke A.g.",
    "wof:placetype":"venue"
},
  "geometry": {"coordinates":[5.5121808052,50.922794342],"type":"Point"}
}