{
  "type": "Feature",
  "properties": {
    "iso:country":"BE",
    "sg:address":"Rue Croisettes 36ba",
    "sg:city":"Ecaussinnes",
    "sg:orig_category":"Traitements param\u00e9dicaux",
    "sg:phone":"+32 67 49 00 92",
    "sg:postcode":"7190",
    "sg:province":"Hainaut",
    "wof:name":"Peeters",
    "wof:placetype":"venue"
},
  "geometry": {"coordinates":[4.1432051659,50.5520782471],"type":"Point"}
}