{
  "type": "Feature",
  "properties": {
    "iso:country":"BE",
    "sg:address":"Zemstbaan 55",
    "sg:city":"Mechelen",
    "sg:classifiers":[
        {
            "category":"Shopping",
            "subcategory":"Books",
            "type":"Retail Goods"
        }
    ],
    "sg:phone":"+32 15 41 27 99",
    "sg:postcode":"2800",
    "sg:province":"Antwerpen",
    "sg:tags":[
        "bookseller"
    ],
    "wof:name":"Max Stripzolder",
    "wof:placetype":"venue"
},
  "geometry": {"coordinates":[4.4722537994,51.000793457],"type":"Point"}
}