{
  "type": "Feature",
  "properties": {
    "iso:country":"BE",
    "sg:address":"Moerestraat 29",
    "sg:city":"Koekelare",
    "sg:orig_category":"Banken and kredietinstellingen",
    "sg:phone":"+32 51 58 93 58",
    "sg:postcode":"8680",
    "sg:province":"West-Vlaanderen",
    "wof:name":"Kbc",
    "wof:placetype":"venue"
},
  "geometry": {"coordinates":[2.9791820049,51.0923156738],"type":"Point"}
}