{
  "type": "Feature",
  "properties": {
    "addr:full":"Rue De Heuseux 67 Soumagne Li\u00e8ge 4630",
    "addr:housenumber":"67",
    "addr:postcode":"4630",
    "addr:street":"Rue De Heuseux",
    "iso:country":"BE",
    "sg:address":"Rue De Heuseux 67",
    "sg:city":"Soumagne",
    "sg:orig_category":"Bloemen and planten",
    "sg:phone":"+32 4 377 12 89",
    "sg:postcode":"4630",
    "sg:province":"Li\u00e8ge",
    "wof:name":"Fortemps-nyssen",
    "wof:placetype":"venue"
},
  "geometry": {"coordinates":[5.7230181694,50.6307487488],"type":"Point"}
}