{
  "type": "Feature",
  "properties": {
    "addr:full":"Ameler Strasse 103a Amel (born Zentrum) Li\u00e8ge 4770",
    "addr:housenumber":"103a",
    "addr:postcode":"4770",
    "addr:street":"Ameler Strasse;Born",
    "iso:country":"BE",
    "sg:address":"Ameler Strasse 103a",
    "sg:city":"Amel (born Zentrum)",
    "sg:classifiers":[
        {
            "category":"Building & Trades",
            "subcategory":"Equipment Rental",
            "type":"Services"
        }
    ],
    "sg:phone":"+32 80 22 77 77",
    "sg:postcode":"4770",
    "sg:province":"Li\u00e8ge",
    "sg:tags":[
        "lighting",
        "-",
        "fixture"
    ],
    "wof:name":"Charly's Musicshop",
    "wof:placetype":"venue"
},
  "geometry": {"coordinates":[6.1297230721,50.3405342102],"type":"Point"}
}