{
  "type": "Feature",
  "properties": {
    "iso:country":"BE",
    "sg:address":"Brusselsesteenweg 135",
    "sg:city":"Leuven",
    "sg:classifiers":[
        {
            "category":"Bars & Pubs",
            "type":"Food & Drink"
        }
    ],
    "sg:phone":"+32 16 29 08 87",
    "sg:postcode":"3000",
    "sg:province":"Vlaams-Brabant",
    "wof:name":"Blauwe Hoek",
    "wof:placetype":"venue"
},
  "geometry": {"coordinates":[4.6900959015,50.8811149597],"type":"Point"}
}