{
  "type": "Feature",
  "properties": {
    "iso:country":"BE",
    "sg:address":"Chauss\u00e9e De Mons 21b",
    "sg:city":"Tournai (barry - Maulde)",
    "sg:classifiers":[
        {
            "category":"Professional",
            "subcategory":"Testing Lab",
            "type":"Services"
        }
    ],
    "sg:phone":"+32 69 54 77 18",
    "sg:postcode":"7534",
    "sg:province":"Hainaut",
    "sg:tags":[
        "chemist"
    ],
    "wof:name":"Lacroix G",
    "wof:placetype":"venue"
},
  "geometry": {"coordinates":[3.5431599617,50.5869293213],"type":"Point"}
}