{
  "type": "Feature",
  "properties": {
    "iso:country":"BE",
    "sg:address":"Eekhoutstraat 16b",
    "sg:city":"Wortegem-petegem (petegem-aan-de-schelde)",
    "sg:classifiers":[
        {
            "category":"Building & Trades",
            "subcategory":"Electrical",
            "type":"Services"
        }
    ],
    "sg:phone":"+32 55 31 49 90",
    "sg:postcode":"9790",
    "sg:province":"Oost-Vlaanderen",
    "sg:tags":[
        "electric",
        "-",
        "housewiring",
        "contractor"
    ],
    "wof:name":"Baert L",
    "wof:placetype":"venue"
},
  "geometry": {"coordinates":[3.5624771118,50.8388404846],"type":"Point"}
}