{
  "type": "Feature",
  "properties": {
    "iso:country":"BE",
    "sg:address":"Kon. Albertstraat 33",
    "sg:city":"Turnhout",
    "sg:orig_category":"Huishoudapparaten, televisies and radio's Verlichting and huishoudartikelen",
    "sg:phone":"+32 14 41 83 23",
    "sg:postcode":"2300",
    "sg:province":"Antwerpen",
    "wof:name":"Prolight Systems",
    "wof:placetype":"venue"
},
  "geometry": {"coordinates":[4.946803093,51.3275337219],"type":"Point"}
}