{
  "type": "Feature",
  "properties": {
    "iso:country":"BE",
    "sg:address":"Boonhemstraat 1",
    "sg:city":"Sint-niklaas",
    "sg:orig_category":"Enseignement artistique",
    "sg:phone":"+32 3 776 33 00",
    "sg:postcode":"9100",
    "sg:province":"Oost-Vlaanderen",
    "wof:name":"Academie Schone Kunsten",
    "wof:placetype":"venue"
},
  "geometry": {"coordinates":[4.1385068893,51.1674804688],"type":"Point"}
}