{
  "type": "Feature",
  "properties": {
    "addr:full":"Avenue De La Libert\u00e9 5 Bruxelles (koekelberg) Bruxelles-Capitale 1081",
    "addr:housenumber":"5",
    "addr:postcode":"1081",
    "addr:street":"Avenue De La Liberte\u0301",
    "iso:country":"BE",
    "sg:address":"Avenue De La Libert\u00e9 5",
    "sg:city":"Bruxelles (koekelberg)",
    "sg:classifiers":[
        {
            "category":"Autos & Motor Vehicles",
            "subcategory":"Automobile Sales",
            "type":"Retail Goods"
        }
    ],
    "sg:phone":"+32 2 410 36 86",
    "sg:postcode":"1081",
    "sg:province":"Bruxelles-Capitale",
    "sg:tags":[
        "car",
        "used",
        "-"
    ],
    "wof:name":"A.m. Automobile",
    "wof:placetype":"venue"
},
  "geometry": {"coordinates":[4.3286948204,50.8631591797],"type":"Point"}
}