{
  "type": "Feature",
  "properties": {
    "addr:full":"Tabakstraat 66 Deinze Oost-Vlaanderen 9800",
    "addr:housenumber":"66",
    "addr:postcode":"9800",
    "addr:street":"Tabakstraat",
    "iso:country":"BE",
    "sg:address":"Tabakstraat 66",
    "sg:city":"Deinze",
    "sg:orig_category":"Eleveurs de bovins",
    "sg:phone":"+32 51 63 39 51",
    "sg:postcode":"9800",
    "sg:province":"Oost-Vlaanderen",
    "wof:name":"Pierre Frits",
    "wof:placetype":"venue"
},
  "geometry": {"coordinates":[3.4396979809,50.9804801941],"type":"Point"}
}