{
  "type": "Feature",
  "properties": {
    "iso:country":"BE",
    "sg:address":"Lierselei 126",
    "sg:city":"Malle",
    "sg:orig_category":"Meubles D\u00e9taillants, Am\u00e9nagement de B\u00e2timents et de Cuisines",
    "sg:phone":"+32 3 309 13 96",
    "sg:postcode":"2390",
    "sg:province":"Antwerpen",
    "wof:name":"Meubelen Inspiration",
    "wof:placetype":"venue"
},
  "geometry": {"coordinates":[4.7224121094,51.2833786011],"type":"Point"}
}