{
  "type": "Feature",
  "properties": {
    "addr:full":"Rue Cayauderie 63 Charleroi Hainaut 6000",
    "addr:housenumber":"63",
    "addr:postcode":"6000",
    "addr:street":"Rue Cayauderie;Hainaut",
    "iso:country":"BE",
    "sg:address":"Rue Cayauderie 63",
    "sg:city":"Charleroi",
    "sg:orig_category":"M\u00e9decines alternatives",
    "sg:phone":"+32 71 41 79 63",
    "sg:postcode":"6000",
    "sg:province":"Hainaut",
    "wof:name":"J. M. Wilmes",
    "wof:placetype":"venue"
},
  "geometry": {"coordinates":[4.4592370987,50.423084259],"type":"Point"}
}