{
  "type": "Feature",
  "properties": {
    "iso:country":"BE",
    "sg:address":"Assebroeklaan 37",
    "sg:city":"Brugge",
    "sg:orig_category":"Elektrische installaties voor woningen Huishoudapparaten, televisies and radio's",
    "sg:phone":"+32 50 35 80 83",
    "sg:postcode":"8310",
    "sg:province":"West-Vlaanderen",
    "wof:name":"Paul Dendooven",
    "wof:placetype":"venue"
},
  "geometry": {"coordinates":[3.2471280098,51.2090644836],"type":"Point"}
}