{
  "type": "Feature",
  "properties": {
    "iso:country":"BE",
    "sg:address":"Rue Guimard 19",
    "sg:city":"Bruxelles (etterbeek)",
    "sg:classifiers":[
        {
            "category":"Professional",
            "subcategory":"Printing & Photocopies",
            "type":"Services"
        }
    ],
    "sg:phone":"+32 2 512 29 49",
    "sg:postcode":"1040",
    "sg:province":"Bruxelles-Capitale",
    "sg:tags":[
        "silkscreen",
        "-"
    ],
    "wof:name":"Charte (la)",
    "wof:placetype":"venue"
},
  "geometry": {"coordinates":[4.3702960014,50.8435554504],"type":"Point"}
}