{
  "type": "Feature",
  "properties": {
    "iso:country":"BE",
    "sg:address":"Gauwerstraat 6",
    "sg:city":"Kortessem (vliermaalroot)",
    "sg:classifiers":[
        {
            "category":"Bars & Pubs",
            "type":"Food & Drink"
        }
    ],
    "sg:phone":"+32 11 37 80 88",
    "sg:postcode":"3721",
    "sg:province":"Limburg",
    "wof:name":"Schuurke ('t)",
    "wof:placetype":"venue"
},
  "geometry": {"coordinates":[5.4235877991,50.8622665405],"type":"Point"}
}