{
  "type": "Feature",
  "properties": {
    "addr:full":"Rue De Monsville 232 Quaregnon Hainaut 7390",
    "addr:housenumber":"232",
    "addr:postcode":"7390",
    "addr:street":"Rue De Monsville",
    "iso:country":"BE",
    "sg:address":"Rue De Monsville 232",
    "sg:city":"Quaregnon",
    "sg:classifiers":[
        {
            "category":"Personal",
            "subcategory":"Beauty Salon",
            "type":"Services"
        }
    ],
    "sg:phone":"+32 65 78 01 70",
    "sg:postcode":"7390",
    "sg:province":"Hainaut",
    "sg:tags":[
        "lady",
        "-",
        "hairdressing"
    ],
    "wof:name":"Galaxy 2000",
    "wof:placetype":"venue"
},
  "geometry": {"coordinates":[3.8642530441,50.4361991882],"type":"Point"}
}