{
  "type": "Feature",
  "properties": {
    "addr:full":"Sint-rijkersstraat 56 Alveringem West-Vlaanderen 8690",
    "addr:housenumber":"56",
    "addr:postcode":"8690",
    "addr:street":"Sint-Rijkersstraat",
    "iso:country":"BE",
    "sg:address":"Sint-rijkersstraat 56",
    "sg:city":"Alveringem",
    "sg:orig_category":"Rundveehouders",
    "sg:phone":"+32 58 28 87 34",
    "sg:postcode":"8690",
    "sg:province":"West-Vlaanderen",
    "wof:name":"Frank Dewaele",
    "wof:placetype":"venue"
},
  "geometry": {"coordinates":[2.6881999969,51.0084381104],"type":"Point"}
}