{
  "type": "Feature",
  "properties": {
    "iso:country":"BE",
    "sg:address":"Rue Du Berger 200",
    "sg:city":"Ohey",
    "sg:orig_category":"Advocaten and juridische adviseurs",
    "sg:phone":"+32 85 61 27 28",
    "sg:postcode":"5350",
    "sg:province":"Namur",
    "wof:name":"D. De Laveleye",
    "wof:placetype":"venue"
},
  "geometry": {"coordinates":[5.1252059937,50.4300727844],"type":"Point"}
}