{
  "type": "Feature",
  "properties": {
    "addr:full":"Rue D'aywaille 181 Comblain-au-pont Li\u00e8ge 4170",
    "addr:housenumber":"181",
    "addr:postcode":"4170",
    "addr:street":"Rue D'Aywaille",
    "iso:country":"BE",
    "sg:address":"Rue D'aywaille 181",
    "sg:city":"Comblain-au-pont",
    "sg:orig_category":"Installatie van houten of kunststof schrijnwerk",
    "sg:phone":"+32 4 369 30 93",
    "sg:postcode":"4170",
    "sg:province":"Li\u00e8ge",
    "wof:name":"Gavage M",
    "wof:placetype":"venue"
},
  "geometry": {"coordinates":[5.6128211021,50.4767570496],"type":"Point"}
}