{
  "type": "Feature",
  "properties": {
    "iso:country":"BE",
    "sg:address":"Rue Des Goutteaux 30",
    "sg:city":"Charleroi",
    "sg:orig_category":"M\u00e9decins and sp\u00e9cialistes",
    "sg:phone":"+32 71 37 00 98",
    "sg:postcode":"6043",
    "sg:province":"Hainaut",
    "wof:name":"Claude Hanet",
    "wof:placetype":"venue"
},
  "geometry": {"coordinates":[4.4095730782,50.4378356934],"type":"Point"}
}