{
  "type": "Feature",
  "properties": {
    "iso:country":"BE",
    "sg:address":"Chauss\u00e9e De Dottignies 10",
    "sg:city":"Estaimpuis",
    "sg:classifiers":[
        {
            "category":"Shopping",
            "subcategory":"Clothing, Apparel, & Fashions",
            "type":"Retail Goods"
        }
    ],
    "sg:phone":"+32 56 33 14 07",
    "sg:postcode":"7730",
    "sg:province":"Hainaut",
    "sg:tags":[
        "lady",
        "clothing",
        "-"
    ],
    "wof:name":"Demarke J",
    "wof:placetype":"venue"
},
  "geometry": {"coordinates":[3.2575879097,50.7151908875],"type":"Point"}
}