{
  "type": "Feature",
  "properties": {
    "iso:country":"BE",
    "sg:address":"Goedendaglaan 77ba",
    "sg:city":"Kortrijk",
    "sg:orig_category":"Sportclubs",
    "sg:phone":"+32 56 22 68 15",
    "sg:postcode":"8500",
    "sg:province":"West-Vlaanderen",
    "wof:name":"V.c. Stade-v.t.i.kortrijk",
    "wof:placetype":"venue"
},
  "geometry": {"coordinates":[3.2863080502,50.8275756836],"type":"Point"}
}