{
  "type": "Feature",
  "properties": {
    "iso:country":"BE",
    "sg:address":"Kapelsesteenweg 3",
    "sg:city":"Antwerpen",
    "sg:orig_category":"Fietsen Motorfietsen",
    "sg:phone":"+32 3 641 80 10",
    "sg:postcode":"2180",
    "sg:province":"Antwerpen",
    "wof:name":"A M S Antwerpen",
    "wof:placetype":"venue"
},
  "geometry": {"coordinates":[4.4606118202,51.2686538696],"type":"Point"}
}