{
  "type": "Feature",
  "properties": {
    "addr:full":"Waaienberg 31 Tervuren Vlaams-Brabant 3080",
    "addr:housenumber":"31",
    "addr:postcode":"3080",
    "addr:street":"Waaienberg",
    "iso:country":"BE",
    "sg:address":"Waaienberg 31",
    "sg:city":"Tervuren",
    "sg:orig_category":"Producteurs de fruits",
    "sg:phone":"+32 2 687 82 66",
    "sg:postcode":"3080",
    "sg:province":"Vlaams-Brabant",
    "wof:name":"Frans Foccaert",
    "wof:placetype":"venue"
},
  "geometry": {"coordinates":[4.535692215,50.8002319336],"type":"Point"}
}