{
  "type": "Feature",
  "properties": {
    "iso:country":"BE",
    "sg:address":"Rue Albert Ier 18",
    "sg:city":"Saint-georges-sur-meuse",
    "sg:orig_category":"Ruimtes voor conferenties, recepties and feesten Zalen voor culturele evenementen",
    "sg:phone":"+32 4 259 75 05",
    "sg:postcode":"4470",
    "sg:province":"Li\u00e8ge",
    "wof:name":"Foyer Culturel",
    "wof:placetype":"venue"
},
  "geometry": {"coordinates":[5.3556170464,50.6008682251],"type":"Point"}
}