{
  "type": "Feature",
  "properties": {
    "iso:country":"BE",
    "sg:address":"Alsembergse Steenweg 1059",
    "sg:city":"Ukkel/uccle",
    "sg:orig_category":"Slagers",
    "sg:phone":"+32 2 376 81 40",
    "sg:postcode":"1180",
    "sg:province":"Bruxelles-Capitale",
    "wof:name":"Discount Viandes",
    "wof:placetype":"venue"
},
  "geometry": {"coordinates":[4.3326258659,50.7919883728],"type":"Point"}
}