{
  "type": "Feature",
  "properties": {
    "addr:full":"Lindenlaan 19 Lille Antwerpen 2275",
    "addr:housenumber":"19",
    "addr:postcode":"2275",
    "addr:street":"Lindenlaan",
    "iso:country":"BE",
    "sg:address":"Lindenlaan 19",
    "sg:city":"Lille",
    "sg:classifiers":[
        {
            "category":"Arena",
            "subcategory":"Sports Club",
            "type":"Entertainment"
        }
    ],
    "sg:phone":"+32 3 312 30 24",
    "sg:postcode":"2275",
    "sg:province":"Antwerpen",
    "sg:tags":[
        "de"
    ],
    "wof:name":"Wandelclub Zandstappers",
    "wof:placetype":"venue"
},
  "geometry": {"coordinates":[4.7900252342,51.2632904053],"type":"Point"}
}