{
  "type": "Feature",
  "properties": {
    "addr:full":"Statielei 49 Mortsel Antwerpen 2640",
    "addr:housenumber":"49",
    "addr:postcode":"2640",
    "addr:street":"Statielei",
    "iso:country":"BE",
    "sg:address":"Statielei 49",
    "sg:city":"Mortsel",
    "sg:orig_category":"V\u00eatements. V\u00eatements pour Dames",
    "sg:phone":"+32 3 449 66 82",
    "sg:postcode":"2640",
    "sg:province":"Antwerpen",
    "wof:name":"Escada By Blok",
    "wof:placetype":"venue"
},
  "geometry": {"coordinates":[4.4516949654,51.1707382202],"type":"Point"}
}