{
  "type": "Feature",
  "properties": {
    "iso:country":"BE",
    "sg:address":"Eug\u00c8ne Ysayelaan 46",
    "sg:city":"Anderlecht",
    "sg:classifiers":[
        {
            "category":"Insurance",
            "subcategory":"Insurance Agent",
            "type":"Services"
        }
    ],
    "sg:phone":"+32 2 522 85 38",
    "sg:postcode":"1070",
    "sg:province":"Bruxelles-Capitale",
    "sg:tags":[
        "verzekeringsmakelaars",
        "expert"
    ],
    "wof:name":"Clever Invest Sa",
    "wof:placetype":"venue"
},
  "geometry": {"coordinates":[4.2974867821,50.8305664062],"type":"Point"}
}