{
  "type": "Feature",
  "properties": {
    "iso:country":"BE",
    "sg:address":"Nieuwstraat 13",
    "sg:city":"Aalst",
    "sg:orig_category":"Brood, gebak and snoepgoed Restaurants",
    "sg:phone":"+32 53 21 17 20",
    "sg:postcode":"9300",
    "sg:province":"Oost-Vlaanderen",
    "wof:name":"Tea-room Zwaenepoel",
    "wof:placetype":"venue"
},
  "geometry": {"coordinates":[4.0356211662,50.9373512268],"type":"Point"}
}