{
  "type": "Feature",
  "properties": {
    "iso:country":"BE",
    "sg:address":"Rempart Des Arquebusiers 12",
    "sg:city":"Vise",
    "sg:orig_category":"Kapsalons",
    "sg:phone":"+32 4 379 26 93",
    "sg:postcode":"4600",
    "sg:province":"Li\u00e8ge",
    "wof:name":"Coiffure Syst\u00c8me 21",
    "wof:placetype":"venue"
},
  "geometry": {"coordinates":[5.6960539818,50.7350769043],"type":"Point"}
}