{
  "type": "Feature",
  "properties": {
    "iso:country":"BE",
    "sg:address":"Place Sainte-v\u00c9ronique 2",
    "sg:city":"Li\u00c8ge",
    "sg:orig_category":"Journaux. Tabac",
    "sg:phone":"+32 4 252 23 63",
    "sg:postcode":"4000",
    "sg:province":"Li\u00e8ge",
    "wof:name":"St.v\u00c9ronique",
    "wof:placetype":"venue"
},
  "geometry": {"coordinates":[5.565571785,50.6317558289],"type":"Point"}
}