{
  "type": "Feature",
  "properties": {
    "addr:full":"Brugsesteenweg 11 Kortrijk West-Vlaanderen 8500",
    "addr:housenumber":"11",
    "addr:postcode":"8500",
    "addr:street":"Brugsesteenweg",
    "iso:country":"BE",
    "sg:address":"Brugsesteenweg 11",
    "sg:city":"Kortrijk",
    "sg:classifiers":[
        {
            "category":"Personal",
            "subcategory":"Beauty Salon",
            "type":"Services"
        }
    ],
    "sg:phone":"+32 56 35 26 20",
    "sg:postcode":"8500",
    "sg:province":"West-Vlaanderen",
    "sg:tags":[
        "de",
        "coiffure"
    ],
    "wof:name":"Gilbert Ameye",
    "wof:placetype":"venue"
},
  "geometry": {"coordinates":[3.2620310783,50.8358688354],"type":"Point"}
}