{
  "type": "Feature",
  "properties": {
    "addr:full":"Kleine Bruggeweg 2 Lichtervelde West-Vlaanderen 8810",
    "addr:housenumber":"2",
    "addr:postcode":"8810",
    "addr:street":"Kleine Bruggeweg",
    "iso:country":"BE",
    "sg:address":"Kleine Bruggeweg 2",
    "sg:city":"Lichtervelde",
    "sg:orig_category":"Jardinage",
    "sg:phone":"+32 51 72 67 09",
    "sg:postcode":"8810",
    "sg:province":"West-Vlaanderen",
    "wof:name":"Steve Van Bruwaene",
    "wof:placetype":"venue"
},
  "geometry": {"coordinates":[3.1546909809,51.0465316772],"type":"Point"}
}