{
  "type": "Feature",
  "properties": {
    "iso:country":"BE",
    "sg:address":"Cit\u00c9 De La Ferme 2",
    "sg:city":"Anderlues",
    "sg:orig_category":"RESTAURANTS: LIVRAISON \u00c0 DOMICILE",
    "sg:phone":"+32 71 52 25 56",
    "sg:postcode":"6150",
    "sg:province":"Hainaut",
    "wof:name":"Au Plaisir Du Palais",
    "wof:placetype":"venue"
},
  "geometry": {"coordinates":[4.2646389008,50.4047584534],"type":"Point"}
}