{
  "type": "Feature",
  "properties": {
    "iso:country":"BE",
    "sg:address":"Rue Du Bas 52",
    "sg:city":"Fleurus",
    "sg:orig_category":"Drukkerijen and copyshops",
    "sg:phone":"+32 71 85 23 70",
    "sg:postcode":"6220",
    "sg:province":"Hainaut",
    "wof:name":"Christian Meynaerts",
    "wof:placetype":"venue"
},
  "geometry": {"coordinates":[4.4924778938,50.4808311462],"type":"Point"}
}