{
  "type": "Feature",
  "properties": {
    "addr:full":"Place Du Ballon 6 Charleroi Hainaut 6040",
    "addr:housenumber":"6",
    "addr:postcode":"6040",
    "addr:street":"Place Du Ballon;Hainaut",
    "iso:country":"BE",
    "sg:address":"Place Du Ballon 6",
    "sg:city":"Charleroi",
    "sg:orig_category":"Eclairage et \u00e9quipements du foyer. Fleurs and plantes",
    "sg:phone":"+32 71 35 27 22",
    "sg:postcode":"6040",
    "sg:province":"Hainaut",
    "wof:name":"Art & Flor Passion",
    "wof:placetype":"venue"
},
  "geometry": {"coordinates":[4.4136137962,50.4339866638],"type":"Point"}
}