{
  "type": "Feature",
  "properties": {
    "iso:country":"BE",
    "sg:address":"Onderbos 12",
    "sg:city":"Oudenaarde",
    "sg:orig_category":"Boekhouders",
    "sg:phone":"+32 55 31 47 42",
    "sg:postcode":"9700",
    "sg:province":"Oost-Vlaanderen",
    "wof:name":"Els De Rooze",
    "wof:placetype":"venue"
},
  "geometry": {"coordinates":[3.594422102,50.8218688965],"type":"Point"}
}