{
  "type": "Feature",
  "properties": {
    "addr:full":"Rue D'havr\u00e9 131 Mons Hainaut 7000",
    "addr:housenumber":"131",
    "addr:postcode":"7000",
    "addr:street":"Rue D'Havre \u0301;Hainaut",
    "iso:country":"BE",
    "sg:address":"Rue D'havr\u00e9 131",
    "sg:city":"Mons",
    "sg:classifiers":[
        {
            "category":"Food & Beverages",
            "subcategory":"Groceries & Convenience Stores",
            "type":"Retail Goods"
        }
    ],
    "sg:phone":"+32 65 31 60 80",
    "sg:postcode":"7000",
    "sg:province":"Hainaut",
    "sg:tags":[
        "grocer"
    ],
    "wof:name":"Sette O",
    "wof:placetype":"venue"
},
  "geometry": {"coordinates":[3.9581680298,50.454044342],"type":"Point"}
}