{
  "type": "Feature",
  "properties": {
    "addr:full":"Rue Du Texas 25 Texasstraat Bruxelles/brussel Bruxelles-Capitale 1190",
    "addr:housenumber":"25",
    "addr:postcode":"1190",
    "addr:street":"Rue Du Texas;Texasstraat",
    "iso:country":"BE",
    "sg:address":"Rue Du Texas 25 Texasstraat",
    "sg:city":"Bruxelles/brussel",
    "sg:classifiers":[
        {
            "category":"Home & Garden",
            "subcategory":"Carpets & Floor Coverings",
            "type":"Retail Goods"
        }
    ],
    "sg:phone":"+32 2 344 23 21",
    "sg:postcode":"1190",
    "sg:province":"Bruxelles-Capitale",
    "sg:tags":[
        "polishing",
        "abrasive",
        "paste"
    ],
    "wof:name":"Renwart Sa/nv",
    "wof:placetype":"venue"
},
  "geometry": {"coordinates":[4.3210902214,50.8135299683],"type":"Point"}
}