{
  "type": "Feature",
  "properties": {
    "iso:country":"BE",
    "sg:address":"Rue Lat\u00e9rale 2",
    "sg:city":"Courcelles (trazegnies)",
    "sg:classifiers":[
        {
            "category":"Retail",
            "subcategory":"Auto Rental",
            "type":"Services"
        }
    ],
    "sg:phone":"+32 71 46 32 77",
    "sg:postcode":"6183",
    "sg:province":"Hainaut",
    "sg:tags":[
        "automobile",
        "-",
        "car",
        "self-drive"
    ],
    "wof:name":"Auto Mah Sprl",
    "wof:placetype":"venue"
},
  "geometry": {"coordinates":[4.336411953,50.458442688],"type":"Point"}
}