{
  "type": "Feature",
  "properties": {
    "iso:country":"BE",
    "sg:address":"Diestersteenweg 99",
    "sg:city":"Nieuwerkerken",
    "sg:orig_category":"Meubles D\u00e9taillants, Am\u00e9nagement de B\u00e2timents et de Cuisines. Fabrication and montage de mobilier",
    "sg:phone":"+32 11 68 33 34",
    "sg:postcode":"3850",
    "sg:province":"Limburg",
    "wof:name":"Meubelen Vranken",
    "wof:placetype":"venue"
},
  "geometry": {"coordinates":[5.1884169579,50.8635635376],"type":"Point"}
}