{
  "type": "Feature",
  "properties": {
    "addr:full":"Houtkaai 9-12 Brugge West-Vlaanderen 8000",
    "addr:housenumber":"9-12",
    "addr:postcode":"8000",
    "addr:street":"Houtkaai",
    "iso:country":"BE",
    "sg:address":"Houtkaai 9-12",
    "sg:city":"Brugge",
    "sg:classifiers":[
        {
            "category":"Manufacturing",
            "subcategory":"Motor Vehicles & Parts",
            "type":"Manufacturing & Wholesale Goods"
        }
    ],
    "sg:phone":"+32 50 31 48 14",
    "sg:postcode":"8000",
    "sg:province":"West-Vlaanderen",
    "sg:tags":[
        "machine",
        "-",
        "indivisible",
        "transport"
    ],
    "wof:name":"Gheysens Bvba",
    "wof:placetype":"venue"
},
  "geometry": {"coordinates":[3.2079019547,51.2179336548],"type":"Point"}
}