{
  "type": "Feature",
  "properties": {
    "addr:full":"Hinaumetz 1 Leuze-en-hainaut (thieulain) Hainaut 7901",
    "addr:housenumber":"1;7901",
    "addr:street":"Hinaumetz;Thieulain Hainaut",
    "iso:country":"BE",
    "sg:address":"Hinaumetz 1",
    "sg:city":"Leuze-en-hainaut (thieulain)",
    "sg:classifiers":[
        {
            "category":"Retail",
            "subcategory":"Auto Repair",
            "type":"Services"
        }
    ],
    "sg:phone":"+32 69 66 40 95",
    "sg:postcode":"7901",
    "sg:province":"Hainaut",
    "sg:tags":[
        "garage"
    ],
    "wof:name":"Verstraete W",
    "wof:placetype":"venue"
},
  "geometry": {"coordinates":[3.5988080502,50.6200485229],"type":"Point"}
}