{
  "type": "Feature",
  "properties": {
    "addr:full":"Baron De Gieylaan 53 De Pinte Oost-Vlaanderen 9840",
    "addr:housenumber":"53",
    "addr:postcode":"9840",
    "addr:street":"Baron De Gieylaan",
    "iso:country":"BE",
    "sg:address":"Baron De Gieylaan 53",
    "sg:city":"De Pinte",
    "sg:orig_category":"Pain, p\u00e2tisseries and confiseries",
    "sg:phone":"+32 9 282 61 43",
    "sg:postcode":"9840",
    "sg:province":"Oost-Vlaanderen",
    "wof:name":"Leonidas",
    "wof:placetype":"venue"
},
  "geometry": {"coordinates":[3.6546459198,50.9928321838],"type":"Point"}
}