{
  "type": "Feature",
  "properties": {
    "addr:full":"Rue Ville Basse 9 Silly Hainaut 7830",
    "addr:housenumber":"9",
    "addr:postcode":"7830",
    "addr:street":"Rue Ville Basse",
    "iso:country":"BE",
    "sg:address":"Rue Ville Basse 9",
    "sg:city":"Silly",
    "sg:classifiers":[
        {
            "category":"Shopping",
            "subcategory":"Clothing, Apparel, & Fashions",
            "type":"Retail Goods"
        }
    ],
    "sg:phone":"+32 68 55 10 65",
    "sg:postcode":"7830",
    "sg:province":"Hainaut",
    "sg:tags":[
        "underwear",
        "lingerie",
        "-"
    ],
    "wof:name":"Duprix C",
    "wof:placetype":"venue"
},
  "geometry": {"coordinates":[3.9250159264,50.6498680115],"type":"Point"}
}