{
  "type": "Feature",
  "properties": {
    "addr:full":"Rue Des Cloutiers 83 Fleron Li\u00e8ge 4621",
    "addr:housenumber":"83",
    "addr:postcode":"4621",
    "addr:street":"Rue Des Cloutiers",
    "iso:country":"BE",
    "sg:address":"Rue Des Cloutiers 83",
    "sg:city":"Fleron",
    "sg:orig_category":"Metaalafval, schrootrecyclage and sloperijen Onderdelen and accessoires voor auto's",
    "sg:phone":"+32 4 358 51 30",
    "sg:postcode":"4621",
    "sg:province":"Li\u00e8ge",
    "wof:name":"Fe. Joskin",
    "wof:placetype":"venue"
},
  "geometry": {"coordinates":[5.6991319656,50.6241416931],"type":"Point"}
}