{
  "type": "Feature",
  "properties": {
    "addr:full":"Rue Neuve 220 Colfontaine (p\u00e2turages) Hainaut 7340",
    "addr:housenumber":"220",
    "addr:postcode":"7340",
    "addr:street":"Rue Neuve",
    "iso:country":"BE",
    "sg:address":"Rue Neuve 220",
    "sg:city":"Colfontaine (p\u00e2turages)",
    "sg:classifiers":[
        {
            "category":"Home & Garden",
            "subcategory":"Kitchen Supply",
            "type":"Retail Goods"
        }
    ],
    "sg:phone":"+32 65 67 90 90",
    "sg:postcode":"7340",
    "sg:province":"Hainaut",
    "sg:tags":[
        "installation"
    ],
    "wof:name":"Venturi Giorgio",
    "wof:placetype":"venue"
},
  "geometry": {"coordinates":[3.8496201038,50.3996276855],"type":"Point"}
}