{
  "type": "Feature",
  "properties": {
    "iso:country":"BE",
    "sg:address":"Ancien-chemin-d\u00b4halma 30",
    "sg:city":"Wellin",
    "sg:orig_category":"S\u00e9curit\u00e9 sociale",
    "sg:phone":"+32 84 38 99 58",
    "sg:postcode":"6920",
    "sg:province":"Luxembourg",
    "wof:name":"Mutualit\u00c9 Socialiste",
    "wof:placetype":"venue"
},
  "geometry": {"coordinates":[5.1150951385,50.0813598633],"type":"Point"}
}