{
  "type": "Feature",
  "properties": {
    "addr:full":"Rue Du Ch\u00eane 184 Chapelle-lez-herlaimont Hainaut 7160",
    "addr:housenumber":"184",
    "addr:postcode":"7160",
    "addr:street":"Rue Du Che\u0302Ne",
    "iso:country":"BE",
    "sg:address":"Rue Du Ch\u00eane 184",
    "sg:city":"Chapelle-lez-herlaimont",
    "sg:classifiers":[
        {
            "category":"Health Services",
            "subcategory":"Health Practitioner",
            "type":"Services"
        }
    ],
    "sg:phone":"+32 64 45 11 60",
    "sg:postcode":"7160",
    "sg:province":"Hainaut",
    "sg:tags":[
        "psychologist"
    ],
    "wof:name":"Libotte J.p.",
    "wof:placetype":"venue"
},
  "geometry": {"coordinates":[4.2749872208,50.4773330688],"type":"Point"}
}