{
  "type": "Feature",
  "properties": {
    "addr:full":"Heidestraat Zuid 232 Kapellen Antwerpen 2950",
    "addr:housenumber":"232",
    "addr:postcode":"2950",
    "addr:street":"Heidestraat Zuid",
    "iso:country":"BE",
    "sg:address":"Heidestraat Zuid 232",
    "sg:city":"Kapellen",
    "sg:classifiers":[
        {
            "category":"Professional",
            "subcategory":"Engineering",
            "type":"Services"
        }
    ],
    "sg:phone":"+32 3 605 14 67",
    "sg:postcode":"2950",
    "sg:province":"Antwerpen",
    "sg:tags":[
        "industrial",
        "-",
        "automation"
    ],
    "wof:name":"Snoeijer W",
    "wof:placetype":"venue"
},
  "geometry": {"coordinates":[4.4525971413,51.3283920288],"type":"Point"}
}