{
  "type": "Feature",
  "properties": {
    "iso:country":"BE",
    "sg:address":"Zandstraat 106",
    "sg:city":"Herentals",
    "sg:classifiers":[
        {
            "category":"Manufacturing",
            "subcategory":"Textiles",
            "type":"Manufacturing & Wholesale Goods"
        }
    ],
    "sg:phone":"+32 14 21 12 01",
    "sg:postcode":"2200",
    "sg:province":"Antwerpen",
    "sg:tags":[
        "retail",
        "-"
    ],
    "wof:name":"De Herdt F",
    "wof:placetype":"venue"
},
  "geometry": {"coordinates":[4.830780983,51.1774864197],"type":"Point"}
}