{
  "type": "Feature",
  "properties": {
    "addr:full":"Distelstraat 59 Gent Oost-Vlaanderen 9000",
    "addr:housenumber":"59",
    "addr:postcode":"9000",
    "addr:street":"Distelstraat;Oost-Vlaanderen",
    "iso:country":"BE",
    "sg:address":"Distelstraat 59",
    "sg:city":"Gent",
    "sg:orig_category":"Kapsalons",
    "sg:phone":"+32 9 222 84 11",
    "sg:postcode":"9000",
    "sg:province":"Oost-Vlaanderen",
    "wof:name":"Coiffure Arlette",
    "wof:placetype":"venue"
},
  "geometry": {"coordinates":[3.7065970898,51.0388259888],"type":"Point"}
}