{
  "type": "Feature",
  "properties": {
    "addr:full":"Grotesteenweg 375 Berchem Antwerpen 2600",
    "addr:housenumber":"375",
    "addr:postcode":"2600",
    "addr:street":"Grotesteenweg;Antwerpen",
    "iso:country":"BE",
    "sg:address":"Grotesteenweg 375",
    "sg:city":"Berchem",
    "sg:classifiers":[
        {
            "category":"Wholesale",
            "subcategory":"Machinery & Supplies",
            "type":"Manufacturing & Wholesale Goods"
        }
    ],
    "sg:phone":"+32 3 230 81 04",
    "sg:postcode":"2600",
    "sg:province":"Antwerpen",
    "sg:tags":[
        "equipment",
        "optical",
        "precision",
        "instrument"
    ],
    "wof:name":"Metro-foto Bvba",
    "wof:placetype":"venue"
},
  "geometry": {"coordinates":[4.4292969704,51.1857147217],"type":"Point"}
}