{
  "type": "Feature",
  "properties": {
    "iso:country":"BE",
    "sg:address":"Avenue Victor-tesch 37",
    "sg:city":"Arlon",
    "sg:orig_category":"M\u00e9decins and sp\u00e9cialistes",
    "sg:phone":"+32 63 22 59 82",
    "sg:postcode":"6700",
    "sg:province":"Luxembourg",
    "wof:name":"Chantal Debaty",
    "wof:placetype":"venue"
},
  "geometry": {"coordinates":[5.8016247749,49.688419342],"type":"Point"}
}