{
  "type": "Feature",
  "properties": {
    "iso:country":"BE",
    "sg:address":"Prins Boudewijnstraat 106",
    "sg:city":"Ganshoren",
    "sg:orig_category":"Artsen and specialisten Medische and orthopedische apparaten",
    "sg:phone":"+32 2 463 02 80",
    "sg:postcode":"1083",
    "sg:province":"Bruxelles-Capitale",
    "wof:name":"Cebelor",
    "wof:placetype":"venue"
},
  "geometry": {"coordinates":[4.3197550774,50.8713874817],"type":"Point"}
}