{
  "type": "Feature",
  "properties": {
    "addr:full":"Dorp 38 Lommel Limburg 3920",
    "addr:housenumber":"38",
    "addr:postcode":"3920",
    "addr:street":"Dorp",
    "iso:country":"BE",
    "sg:address":"Dorp 38",
    "sg:city":"Lommel",
    "sg:orig_category":"Randstad",
    "sg:phone":"+32 11 54 55 66",
    "sg:postcode":"3920",
    "sg:province":"Limburg",
    "wof:name":"Randstad",
    "wof:placetype":"venue"
},
  "geometry": {"coordinates":[5.3089981079,51.2305793762],"type":"Point"}
}