{
  "type": "Feature",
  "properties": {
    "addr:full":"Rijksweg 378 Maasmechelen Limburg 3630",
    "addr:housenumber":"378",
    "addr:postcode":"3630",
    "addr:street":"Rijksweg",
    "iso:country":"BE",
    "sg:address":"Rijksweg 378",
    "sg:city":"Maasmechelen",
    "sg:orig_category":"Huishoudapparaten, televisies and radio's",
    "sg:phone":"+32 89 76 04 62",
    "sg:postcode":"3630",
    "sg:province":"Limburg",
    "wof:name":"Fa. Colee",
    "wof:placetype":"venue"
},
  "geometry": {"coordinates":[5.6961579323,50.9664039612],"type":"Point"}
}