{
  "type": "Feature",
  "properties": {
    "addr:full":"Rue De Lens Sur Geer 33 Remicourt Li\u00e8ge 4351",
    "addr:housenumber":"33",
    "addr:postcode":"4351",
    "addr:street":"Rue De Lens Sur Geer",
    "iso:country":"BE",
    "sg:address":"Rue De Lens Sur Geer 33",
    "sg:city":"Remicourt",
    "sg:classifiers":[
        {
            "category":"Arena",
            "subcategory":"Sports Club",
            "type":"Entertainment"
        }
    ],
    "sg:phone":"+32 19 54 47 13",
    "sg:postcode":"4351",
    "sg:province":"Li\u00e8ge",
    "sg:tags":[
        "de"
    ],
    "wof:name":"Hirondelle",
    "wof:placetype":"venue"
},
  "geometry": {"coordinates":[5.3438849449,50.697807312],"type":"Point"}
}