{
  "type": "Feature",
  "properties": {
    "iso:country":"BE",
    "sg:address":"Rue De L'eglise 29",
    "sg:city":"Pont-\u00e0-celles",
    "sg:classifiers":[
        {
            "category":"Shopping",
            "subcategory":"Optician",
            "type":"Retail Goods"
        }
    ],
    "sg:phone":"+32 71 84 47 14",
    "sg:postcode":"6230",
    "sg:province":"Hainaut",
    "sg:tags":[
        "-"
    ],
    "wof:name":"Haegeman Ph",
    "wof:placetype":"venue"
},
  "geometry": {"coordinates":[4.3633651733,50.5102462769],"type":"Point"}
}