{
  "type": "Feature",
  "properties": {
    "iso:country":"BE",
    "sg:address":"Emile Vandersteenenstraat 2",
    "sg:city":"Sint-pieters-leeuw",
    "sg:classifiers":[
        {
            "category":"Wholesale",
            "subcategory":"Scrap",
            "type":"Manufacturing & Wholesale Goods"
        }
    ],
    "sg:phone":"+32 2 377 64 47",
    "sg:postcode":"1600",
    "sg:province":"Vlaams-Brabant",
    "sg:tags":[
        "metal"
    ],
    "wof:name":"Legrand Louis",
    "wof:placetype":"venue"
},
  "geometry": {"coordinates":[4.2729058266,50.7812385559],"type":"Point"}
}