{
  "type": "Feature",
  "properties": {
    "addr:full":"Kasteeldreef 1 Ganshoren/ganshoren Bruxelles-Capitale 1083",
    "addr:housenumber":"1",
    "addr:postcode":"1083",
    "addr:street":"Kasteeldreef",
    "iso:country":"BE",
    "sg:address":"Kasteeldreef 1",
    "sg:city":"Ganshoren/ganshoren",
    "sg:orig_category":"Apotheken",
    "sg:phone":"+32 2 425 11 53",
    "sg:postcode":"1083",
    "sg:province":"Bruxelles-Capitale",
    "wof:name":"M.c. Meerschaut",
    "wof:placetype":"venue"
},
  "geometry": {"coordinates":[4.317358017,50.8759498596],"type":"Point"}
}