{
  "type": "Feature",
  "properties": {
    "iso:country":"BE",
    "sg:address":"Stationstraat 84",
    "sg:city":"Sint-katelijne-waver",
    "sg:orig_category":"Drukkerijen and copyshops",
    "sg:phone":"+32 15 31 10 85",
    "sg:postcode":"2860",
    "sg:province":"Antwerpen",
    "wof:name":"Drukkerij Hens Bvba",
    "wof:placetype":"venue"
},
  "geometry": {"coordinates":[4.5229878426,51.0705718994],"type":"Point"}
}