{
  "type": "Feature",
  "properties": {
    "iso:country":"BE",
    "sg:address":"Steenweg 67",
    "sg:city":"Diepenbeek",
    "sg:classifiers":[
        {
            "category":"Bars & Pubs",
            "type":"Food & Drink"
        }
    ],
    "sg:phone":"+32 11 32 31 74",
    "sg:postcode":"3590",
    "sg:province":"Limburg",
    "wof:name":"Bagatel Vzw",
    "wof:placetype":"venue"
},
  "geometry": {"coordinates":[5.402367115,50.9148750305],"type":"Point"}
}