{
  "type": "Feature",
  "properties": {
    "addr:full":"Nieuwenhovestraat 56 Waregem West-Vlaanderen 8790",
    "addr:housenumber":"56",
    "addr:postcode":"8790",
    "addr:street":"Nieuwenhovestraat",
    "iso:country":"BE",
    "sg:address":"Nieuwenhovestraat 56",
    "sg:city":"Waregem",
    "sg:orig_category":"Pain, p\u00e2tisseries and confiseries",
    "sg:phone":"+32 56 60 15 19",
    "sg:postcode":"8790",
    "sg:province":"West-Vlaanderen",
    "wof:name":"Bakkerij Francis",
    "wof:placetype":"venue"
},
  "geometry": {"coordinates":[3.3986949921,50.8643875122],"type":"Point"}
}