{
  "type": "Feature",
  "properties": {
    "addr:full":"Leopoldstraat 55 Zwevegem West-Vlaanderen 8550",
    "addr:housenumber":"55",
    "addr:postcode":"8550",
    "addr:street":"Leopoldstraat",
    "iso:country":"BE",
    "sg:address":"Leopoldstraat 55",
    "sg:city":"Zwevegem",
    "sg:classifiers":[
        {
            "category":"Professional",
            "subcategory":"Business Services",
            "type":"Services"
        }
    ],
    "sg:phone":"+32 56 75 75 84",
    "sg:postcode":"8550",
    "sg:province":"West-Vlaanderen",
    "sg:tags":[
        "bookmaker"
    ],
    "wof:name":"Ladbrokes - Eggermont D",
    "wof:placetype":"venue"
},
  "geometry": {"coordinates":[3.334856987,50.8108177185],"type":"Point"}
}