{
  "type": "Feature",
  "properties": {
    "addr:full":"Rue Fran\u00e7ois Hellinckx 49 Bruxelles (koekelberg) Bruxelles-Capitale 1081",
    "addr:housenumber":"49",
    "addr:postcode":"1081",
    "addr:street":"Rue Franc\u0327Ois Hellinckx",
    "iso:country":"BE",
    "sg:address":"Rue Fran\u00e7ois Hellinckx 49",
    "sg:city":"Bruxelles (koekelberg)",
    "sg:classifiers":[
        {
            "category":"Deli",
            "type":"Food & Drink"
        }
    ],
    "sg:phone":"+32 2 411 52 30",
    "sg:postcode":"1081",
    "sg:province":"Bruxelles-Capitale",
    "sg:tags":[
        "delicatessen"
    ],
    "wof:name":"Biarritz Bvba",
    "wof:placetype":"venue"
},
  "geometry": {"coordinates":[4.3270487785,50.858455658],"type":"Point"}
}