{
  "type": "Feature",
  "properties": {
    "iso:country":"BE",
    "sg:address":"Kerkstraat 60",
    "sg:city":"Ternat",
    "sg:orig_category":"Artistes ind\u00e9pendants",
    "sg:phone":"+32 2 582 56 39",
    "sg:postcode":"1742",
    "sg:province":"Vlaams-Brabant",
    "wof:name":"Stefaan Danhieux",
    "wof:placetype":"venue"
},
  "geometry": {"coordinates":[4.158826828,50.8710021973],"type":"Point"}
}