{
  "type": "Feature",
  "properties": {
    "addr:full":"Britselei 34 Antwerpen Antwerpen 2000",
    "addr:housenumber":"34",
    "addr:postcode":"2000",
    "addr:street":"Britselei",
    "iso:country":"BE",
    "sg:address":"Britselei 34",
    "sg:city":"Antwerpen",
    "sg:orig_category":"Belastingconsulenten Diverse juridische dienstverlening",
    "sg:phone":"+32 3 226 16 64",
    "sg:postcode":"2000",
    "sg:province":"Antwerpen",
    "wof:name":"Eurolux",
    "wof:placetype":"venue"
},
  "geometry": {"coordinates":[4.4056649208,51.2102851868],"type":"Point"}
}