{
  "type": "Feature",
  "properties": {
    "iso:country":"BE",
    "sg:address":"Helstraat 28",
    "sg:city":"Kortessem",
    "sg:orig_category":"Producteurs de l\u00e9gumes",
    "sg:phone":"+32 11 37 64 58",
    "sg:postcode":"3721",
    "sg:province":"Limburg",
    "wof:name":"Marc Appeltans",
    "wof:placetype":"venue"
},
  "geometry": {"coordinates":[5.4258799553,50.8713798523],"type":"Point"}
}