{
  "type": "Feature",
  "properties": {
    "addr:full":"Rue Haute 38-40 Plombieres Li\u00e8ge 4850",
    "addr:housenumber":"38-40",
    "addr:postcode":"4850",
    "addr:street":"Rue Haute;Plombieres Lie\u0300Ge",
    "iso:country":"BE",
    "sg:address":"Rue Haute 38-40",
    "sg:city":"Plombieres",
    "sg:orig_category":"Installatie van houten of kunststof schrijnwerk",
    "sg:phone":"+32 87 78 57 45",
    "sg:postcode":"4850",
    "sg:province":"Li\u00e8ge",
    "wof:name":"Oak House",
    "wof:placetype":"venue"
},
  "geometry": {"coordinates":[5.9694910049,50.7305335999],"type":"Point"}
}