{
  "type": "Feature",
  "properties": {
    "addr:full":"Avenue Du Progr\u00e8s 26 Seraing Li\u00e8ge 4100",
    "addr:housenumber":"26",
    "addr:postcode":"4100",
    "addr:street":"Avenue Du Progre\u0300S",
    "iso:country":"BE",
    "sg:address":"Avenue Du Progr\u00e8s 26",
    "sg:city":"Seraing",
    "sg:classifiers":[
        {
            "category":"Health Services",
            "subcategory":"Health Practitioner",
            "type":"Services"
        }
    ],
    "sg:phone":"+32 4 337 31 77",
    "sg:postcode":"4100",
    "sg:province":"Li\u00e8ge",
    "sg:tags":[
        "physiotherapist"
    ],
    "wof:name":"Schoemans-guillaume Marie-christine",
    "wof:placetype":"venue"
},
  "geometry": {"coordinates":[5.5048799515,50.5830726624],"type":"Point"}
}