{
  "type": "Feature",
  "properties": {
    "addr:full":"Nieuwe Wereldstraat 343 Moeskroen/mouscron Hainaut 7700",
    "addr:housenumber":"343",
    "addr:postcode":"7700",
    "addr:street":"Nieuwe Wereldstraat",
    "iso:country":"BE",
    "sg:address":"Nieuwe Wereldstraat 343",
    "sg:city":"Moeskroen/mouscron",
    "sg:orig_category":"Opvangtehuizen and vluchthuizen",
    "sg:phone":"+32 56 34 46 39",
    "sg:postcode":"7700",
    "sg:province":"Hainaut",
    "wof:name":"Maison Maternelle",
    "wof:placetype":"venue"
},
  "geometry": {"coordinates":[3.2323200703,50.7400932312],"type":"Point"}
}