{
  "type": "Feature",
  "properties": {
    "addr:full":"Rue De Soudromont 9a Manage Hainaut 7170",
    "addr:housenumber":"9a",
    "addr:postcode":"7170",
    "addr:street":"Rue De Soudromont",
    "iso:country":"BE",
    "sg:address":"Rue De Soudromont 9a",
    "sg:city":"Manage",
    "sg:classifiers":[
        {
            "category":"Retail",
            "subcategory":"Repair Shop",
            "type":"Services"
        }
    ],
    "sg:phone":"+32 64 55 86 15",
    "sg:postcode":"7170",
    "sg:province":"Hainaut",
    "sg:tags":[
        "denture"
    ],
    "wof:name":"Wauters",
    "wof:placetype":"venue"
},
  "geometry": {"coordinates":[4.258272171,50.5007286072],"type":"Point"}
}