{
  "type": "Feature",
  "properties": {
    "addr:full":"Rue Ovide Dieu 116 Frameries Hainaut 7080",
    "addr:housenumber":"116",
    "addr:postcode":"7080",
    "addr:street":"Rue Ovide Dieu",
    "iso:country":"BE",
    "sg:address":"Rue Ovide Dieu 116",
    "sg:city":"Frameries",
    "sg:orig_category":"Woningbouw",
    "sg:phone":"+32 65 66 79 57",
    "sg:postcode":"7080",
    "sg:province":"Hainaut",
    "wof:name":"G.l.b.",
    "wof:placetype":"venue"
},
  "geometry": {"coordinates":[3.8744080067,50.4081230164],"type":"Point"}
}