{
  "type": "Feature",
  "properties": {
    "addr:full":"Zur St\u00d6ck 5 B\u00dctgenbach/butgenbach Li\u00e8ge 4750",
    "addr:housenumber":"5",
    "addr:postcode":"4750",
    "addr:street":"Stoeck",
    "iso:country":"BE",
    "sg:address":"Zur St\u00d6ck 5",
    "sg:city":"B\u00dctgenbach/butgenbach",
    "sg:orig_category":"Alternatieve geneeskunde",
    "sg:phone":"+32 80 44 56 64",
    "sg:postcode":"4750",
    "sg:province":"Li\u00e8ge",
    "wof:name":"A. Fickers",
    "wof:placetype":"venue"
},
  "geometry": {"coordinates":[6.2206501961,50.457408905],"type":"Point"}
}