{
  "type": "Feature",
  "properties": {
    "iso:country":"BE",
    "sg:address":"De Bergen 74",
    "sg:city":"Kasterlee",
    "sg:orig_category":"D\u00e9taillants en pi\u00e8ces and accessoires de voitures",
    "sg:phone":"+32 14 55 26 08",
    "sg:postcode":"2460",
    "sg:province":"Antwerpen",
    "wof:name":"Andre Van De Water",
    "wof:placetype":"venue"
},
  "geometry": {"coordinates":[4.9671049118,51.2406616211],"type":"Point"}
}