{
  "type": "Feature",
  "properties": {
    "addr:full":"Pl St-pierre 2 Tournai Hainaut 7500",
    "addr:housenumber":"2",
    "addr:postcode":"7500",
    "addr:street":"Pl St-Pierre",
    "iso:country":"BE",
    "sg:address":"Pl St-pierre 2",
    "sg:city":"Tournai",
    "sg:classifiers":[
        {
            "category":"Travel",
            "subcategory":"Hotels & Motels",
            "type":"Entertainment"
        }
    ],
    "sg:phone":"+32 69 21 50 77",
    "sg:postcode":"7500",
    "sg:province":"Hainaut",
    "sg:tags":[
        "hotels",
        "business",
        "restaurant"
    ],
    "wof:name":"Hotel Cathedrale Sa",
    "wof:placetype":"venue"
},
  "geometry": {"coordinates":[3.3909270763,50.6070365906],"type":"Point"}
}