{
  "type": "Feature",
  "properties": {
    "iso:country":"BE",
    "sg:address":"Rue Michel-ham\u00e9lius 41",
    "sg:city":"Arlon",
    "sg:classifiers":[
        {
            "category":"Health Services",
            "subcategory":"Dentist",
            "type":"Services"
        }
    ],
    "sg:phone":"+32 63 22 47 00",
    "sg:postcode":"6700",
    "sg:province":"Luxembourg",
    "wof:name":"Cohrs M-c Mme",
    "wof:placetype":"venue"
},
  "geometry": {"coordinates":[5.8216748238,49.6839294434],"type":"Point"}
}