{
  "type": "Feature",
  "properties": {
    "addr:full":"Avenue Des Cerisiers 82 Brussel/bruxelles Bruxelles-Capitale 1030",
    "addr:housenumber":"82",
    "addr:postcode":"1030",
    "addr:street":"Avenue Des Cerisiers;/",
    "iso:country":"BE",
    "sg:address":"Avenue Des Cerisiers 82",
    "sg:city":"Brussel/bruxelles",
    "sg:orig_category":"Articles non-alimentaires",
    "sg:phone":"+32 2 733 22 02",
    "sg:postcode":"1030",
    "sg:province":"Bruxelles-Capitale",
    "wof:name":"Mostinckx C",
    "wof:placetype":"venue"
},
  "geometry": {"coordinates":[4.407430172,50.8482398987],"type":"Point"}
}