{
  "type": "Feature",
  "properties": {
    "addr:full":"Rue De Longpr\u00c9 16ba Incourt Brabant Wallon 1315",
    "addr:housenumber":"16ba",
    "addr:postcode":"1315",
    "addr:street":"Rue De Longpre\u0301",
    "iso:country":"BE",
    "sg:address":"Rue De Longpr\u00c9 16ba",
    "sg:city":"Incourt",
    "sg:orig_category":"Kapsalons Mobiele kappers",
    "sg:phone":"+32 10 88 03 52",
    "sg:postcode":"1315",
    "sg:province":"Brabant Wallon",
    "wof:name":"Isabelle Seghers",
    "wof:placetype":"venue"
},
  "geometry": {"coordinates":[4.7794971466,50.6936340332],"type":"Point"}
}