{
  "type": "Feature",
  "properties": {
    "iso:country":"BE",
    "sg:address":"Rue De La Station 38",
    "sg:city":"Fleurus",
    "sg:orig_category":"Caf\u00e9s Ruimtes voor conferenties, recepties and feesten",
    "sg:phone":"+32 71 81 33 41",
    "sg:postcode":"6220",
    "sg:province":"Hainaut",
    "wof:name":"Le Billard",
    "wof:placetype":"venue"
},
  "geometry": {"coordinates":[4.5483670235,50.4827651978],"type":"Point"}
}