{
  "type": "Feature",
  "properties": {
    "iso:country":"BE",
    "sg:address":"Buizegemlei 88",
    "sg:city":"Edegem",
    "sg:classifiers":[
        {
            "category":"Building & Trades",
            "subcategory":"Landscaping Services",
            "type":"Services"
        }
    ],
    "sg:phone":"+32 3 457 93 99",
    "sg:postcode":"2650",
    "sg:province":"Antwerpen",
    "sg:tags":[
        "gardening",
        "garden",
        "maintenance"
    ],
    "wof:name":"Oase Tuinatelier",
    "wof:placetype":"venue"
},
  "geometry": {"coordinates":[4.4565038681,51.1508369446],"type":"Point"}
}