{
  "type": "Feature",
  "properties": {
    "iso:country":"BE",
    "sg:address":"Rue Matt\u00c9otti 36",
    "sg:city":"Seraing",
    "sg:orig_category":"Kapsalons",
    "sg:phone":"+32 4 336 04 99",
    "sg:postcode":"4102",
    "sg:province":"Li\u00e8ge",
    "wof:name":"Studio Coiffure",
    "wof:placetype":"venue"
},
  "geometry": {"coordinates":[5.5411219597,50.5812454224],"type":"Point"}
}