{
  "type": "Feature",
  "properties": {
    "addr:full":"Genutstraat 8 Bilzen Limburg 3740",
    "addr:housenumber":"8",
    "addr:postcode":"3740",
    "addr:street":"Genutstraat",
    "iso:country":"BE",
    "sg:address":"Genutstraat 8",
    "sg:city":"Bilzen",
    "sg:orig_category":"Boekhandels Microsoft",
    "sg:phone":"+32 89 51 56 17",
    "sg:postcode":"3740",
    "sg:province":"Limburg",
    "wof:name":"Standaard Boekhandel Bilzen",
    "wof:placetype":"venue"
},
  "geometry": {"coordinates":[5.514977932,50.8711166382],"type":"Point"}
}