{
  "type": "Feature",
  "properties": {
    "addr:full":"Chemin De Tourneppe 6 Braine L'alleud (braine-l'alleud) Brabant Wallon 1420",
    "addr:housenumber":"6",
    "addr:postcode":"1420",
    "addr:street":"Chemin De Tourneppe",
    "iso:country":"BE",
    "sg:address":"Chemin De Tourneppe 6",
    "sg:city":"Braine L'alleud (braine-l'alleud)",
    "sg:classifiers":[
        {
            "category":"Professional",
            "subcategory":"Art Services",
            "type":"Services"
        }
    ],
    "sg:phone":"+32 2 385 08 15",
    "sg:postcode":"1420",
    "sg:province":"Brabant Wallon",
    "sg:tags":[
        "sculptor"
    ],
    "wof:name":"Monge Lasdislas (de)",
    "wof:placetype":"venue"
},
  "geometry": {"coordinates":[-0.8015390038,47.4095726013],"type":"Point"}
}