{
  "type": "Feature",
  "properties": {
    "addr:full":"Turnhoutsebaan 424 Wijnegem Antwerpen 2110",
    "addr:housenumber":"424",
    "addr:postcode":"2110",
    "addr:street":"Turnhoutsebaan",
    "iso:country":"BE",
    "sg:address":"Turnhoutsebaan 424",
    "sg:city":"Wijnegem",
    "sg:classifiers":[
        {
            "category":"Professional",
            "subcategory":"Art Services",
            "type":"Services"
        }
    ],
    "sg:phone":"+32 3 353 07 72",
    "sg:postcode":"2110",
    "sg:province":"Antwerpen",
    "sg:tags":[
        "photographer"
    ],
    "wof:name":"Studio Sandra",
    "wof:placetype":"venue"
},
  "geometry": {"coordinates":[4.5243110657,51.2279586792],"type":"Point"}
}