{
  "type": "Feature",
  "properties": {
    "iso:country":"BE",
    "sg:address":"Kerkstraat 4",
    "sg:city":"Damme",
    "sg:classifiers":[
        {
            "category":"Bars & Pubs",
            "type":"Food & Drink"
        }
    ],
    "sg:phone":"+32 50 37 29 45",
    "sg:postcode":"8340",
    "sg:province":"West-Vlaanderen",
    "sg:tags":[
        "tavern"
    ],
    "wof:name":"La Luna Bistro",
    "wof:placetype":"venue"
},
  "geometry": {"coordinates":[3.2806799412,51.2519493103],"type":"Point"}
}