{
  "type": "Feature",
  "properties": {
    "iso:country":"BE",
    "sg:address":"West Kapellestraat 493",
    "sg:city":"Knokke-heist",
    "sg:orig_category":"Electrom\u00e9nager, t\u00e9l\u00e9visions and radios",
    "sg:phone":"+32 50 60 30 96",
    "sg:postcode":"8300",
    "sg:province":"West-Vlaanderen",
    "wof:name":"Goethals Pieter Electrohandel",
    "wof:placetype":"venue"
},
  "geometry": {"coordinates":[3.287694931,51.3467254639],"type":"Point"}
}