{
  "type": "Feature",
  "properties": {
    "iso:country":"BE",
    "sg:address":"Heilig-hartplein 5",
    "sg:city":"Sint-truiden",
    "sg:classifiers":[
        {
            "category":"Bars & Pubs",
            "type":"Food & Drink"
        }
    ],
    "sg:phone":"+32 11 68 36 15",
    "sg:postcode":"3800",
    "sg:province":"Limburg",
    "wof:name":"Nieuwscaf\u00e9 ('t)",
    "wof:placetype":"venue"
},
  "geometry": {"coordinates":[5.1874141693,50.815372467],"type":"Point"}
}