{
  "type": "Feature",
  "properties": {
    "iso:country":"BE",
    "sg:address":"Avenue De Cointe 17",
    "sg:city":"Liege",
    "sg:orig_category":"Diverse bedrijfsbeheeradviesbureaus",
    "sg:phone":"+32 4 252 37 49",
    "sg:postcode":"4000",
    "sg:province":"Li\u00e8ge",
    "wof:name":"Erve Consulting",
    "wof:placetype":"venue"
},
  "geometry": {"coordinates":[5.5639371872,50.6186752319],"type":"Point"}
}