{
  "type": "Feature",
  "properties": {
    "iso:country":"BE",
    "sg:address":"Oude Beekstraat 24",
    "sg:city":"Bilzen (munsterbilzen)",
    "sg:classifiers":[
        {
            "category":"Health Services",
            "subcategory":"Health Practitioner",
            "type":"Services"
        }
    ],
    "sg:phone":"+32 89 41 29 20",
    "sg:postcode":"3740",
    "sg:province":"Limburg",
    "sg:tags":[
        "physiotherapist"
    ],
    "wof:name":"Van Droogenbroeck W",
    "wof:placetype":"venue"
},
  "geometry": {"coordinates":[5.5275530815,50.8935241699],"type":"Point"}
}