{
  "type": "Feature",
  "properties": {
    "iso:country":"BE",
    "sg:address":"Route De Huy 6a",
    "sg:city":"Ferri\u00e8res (werbomont)",
    "sg:classifiers":[
        {
            "category":"Professional",
            "subcategory":"Testing Lab",
            "type":"Services"
        }
    ],
    "sg:phone":"+32 86 43 43 33",
    "sg:postcode":"4190",
    "sg:province":"Li\u00e8ge",
    "sg:tags":[
        "chemist"
    ],
    "wof:name":"Pharmacie De Werbomont Sprl",
    "wof:placetype":"venue"
},
  "geometry": {"coordinates":[5.6792078018,50.3815345764],"type":"Point"}
}