{
  "type": "Feature",
  "properties": {
    "iso:country":"BE",
    "sg:address":"Neerstraat 11",
    "sg:city":"Lichtervelde",
    "sg:classifiers":[
        {
            "category":"Cinema",
            "subcategory":"Movie Theater",
            "type":"Entertainment"
        }
    ],
    "sg:phone":"+32 51 72 22 24",
    "sg:postcode":"8810",
    "sg:province":"West-Vlaanderen",
    "wof:name":"De Keizer",
    "wof:placetype":"venue"
},
  "geometry": {"coordinates":[3.1414039135,51.0267066956],"type":"Point"}
}