{
  "type": "Feature",
  "properties": {
    "iso:country":"BE",
    "sg:address":"Rue Des Marronniers 1ba",
    "sg:city":"Onhaye",
    "sg:orig_category":"Artsen and specialisten",
    "sg:phone":"+32 82 69 96 35",
    "sg:postcode":"5523",
    "sg:province":"Namur",
    "wof:name":"Philippe Dumont",
    "wof:placetype":"venue"
},
  "geometry": {"coordinates":[4.8271818161,50.260597229],"type":"Point"}
}