{
  "type": "Feature",
  "properties": {
    "iso:country":"BE",
    "sg:address":"De Rivierendreef 158",
    "sg:city":"Ganshoren",
    "sg:orig_category":"Elektrische installaties voor woningen",
    "sg:phone":"+32 2 426 71 24",
    "sg:postcode":"1083",
    "sg:province":"Bruxelles-Capitale",
    "wof:name":"Ciscom",
    "wof:placetype":"venue"
},
  "geometry": {"coordinates":[4.318210125,50.877986908],"type":"Point"}
}