{
  "type": "Feature",
  "properties": {
    "iso:country":"BE",
    "sg:address":"Kapellestraat 11",
    "sg:city":"Aartselaar",
    "sg:classifiers":[
        {
            "category":"Personal",
            "subcategory":"Shoe Repair & Shine",
            "type":"Services"
        }
    ],
    "sg:phone":"+32 3 877 07 62",
    "sg:postcode":"2630",
    "sg:province":"Antwerpen",
    "sg:tags":[
        "shoemaker"
    ],
    "wof:name":"Shoe-key",
    "wof:placetype":"venue"
},
  "geometry": {"coordinates":[4.3886299133,51.1331787109],"type":"Point"}
}