{
  "type": "Feature",
  "properties": {
    "addr:full":"Route De Mettet 59 Fosses-la-ville Namur 5070",
    "addr:housenumber":"59",
    "addr:postcode":"5070",
    "addr:street":"Route De Mettet",
    "iso:country":"BE",
    "sg:address":"Route De Mettet 59",
    "sg:city":"Fosses-la-ville",
    "sg:orig_category":"Serres and speciale beglazing",
    "sg:phone":"+32 71 71 13 51",
    "sg:postcode":"5070",
    "sg:province":"Namur",
    "wof:name":"Ets. Egon",
    "wof:placetype":"venue"
},
  "geometry": {"coordinates":[4.6769471169,50.384021759],"type":"Point"}
}