{
  "type": "Feature",
  "properties": {
    "iso:country":"BE",
    "sg:address":"Rue De Pintamont 54",
    "sg:city":"Ath",
    "sg:classifiers":[
        {
            "category":"Health Services",
            "subcategory":"Nursing And Care Facility",
            "type":"Services"
        }
    ],
    "sg:phone":"+32 68 26 91 00",
    "sg:postcode":"7800",
    "sg:province":"Hainaut",
    "sg:tags":[
        "public"
    ],
    "wof:name":"Administration Communale",
    "wof:placetype":"venue"
},
  "geometry": {"coordinates":[3.774285078,50.6286773682],"type":"Point"}
}