{
  "type": "Feature",
  "properties": {
    "iso:country":"BE",
    "sg:address":"Wijnstraat 83",
    "sg:city":"Ronse/renaix",
    "sg:orig_category":"Bloemen and planten",
    "sg:phone":"+32 55 21 84 97",
    "sg:postcode":"9600",
    "sg:province":"Oost-Vlaanderen",
    "wof:name":"D'hondt",
    "wof:placetype":"venue"
},
  "geometry": {"coordinates":[3.5971050262,50.7499084473],"type":"Point"}
}