{
  "type": "Feature",
  "properties": {
    "iso:country":"BE",
    "sg:address":"Kamiel Wautersstraat 9",
    "sg:city":"Temse",
    "sg:classifiers":[
        {
            "category":"Health Services",
            "subcategory":"Nursing And Care Facility",
            "type":"Services"
        }
    ],
    "sg:phone":"+32 3 710 12 12",
    "sg:postcode":"9140",
    "sg:province":"Oost-Vlaanderen",
    "sg:tags":[
        "public"
    ],
    "wof:name":"Gemeentebestuur",
    "wof:placetype":"venue"
},
  "geometry": {"coordinates":[4.2142829895,51.1246681213],"type":"Point"}
}