{
  "type": "Feature",
  "properties": {
    "addr:full":"Stationstraat 35 Kortenberg Vlaams-Brabant 3070",
    "addr:housenumber":"35",
    "addr:postcode":"3070",
    "addr:street":"Stationstraat;Vlaams-Brabant",
    "iso:country":"BE",
    "sg:address":"Stationstraat 35",
    "sg:city":"Kortenberg",
    "sg:classifiers":[
        {
            "category":"Personal",
            "subcategory":"Beauty Salon",
            "type":"Services"
        }
    ],
    "sg:phone":"+32 2 759 71 75",
    "sg:postcode":"3070",
    "sg:province":"Vlaams-Brabant",
    "sg:tags":[
        "de",
        "coiffure"
    ],
    "wof:name":"Up To Date",
    "wof:placetype":"venue"
},
  "geometry": {"coordinates":[4.5430321693,50.8899269104],"type":"Point"}
}