{
  "type": "Feature",
  "properties": {
    "iso:country":"BE",
    "sg:address":"Draaiboom 2",
    "sg:city":"Zandhoven",
    "sg:orig_category":"Artsen and specialisten",
    "sg:phone":"+32 3 484 41 84",
    "sg:postcode":"2242",
    "sg:province":"Antwerpen",
    "wof:name":"Patrick Moerman",
    "wof:placetype":"venue"
},
  "geometry": {"coordinates":[4.6916108131,51.2146644592],"type":"Point"}
}