{
  "type": "Feature",
  "properties": {
    "addr:full":"Kroonlaan 530 Elsene/ixelles Bruxelles-Capitale 1050",
    "addr:housenumber":"530",
    "addr:postcode":"1050",
    "addr:street":"Kroonlaan",
    "iso:country":"BE",
    "sg:address":"Kroonlaan 530",
    "sg:city":"Elsene/ixelles",
    "sg:orig_category":"Telecommunicatiesystemen",
    "sg:phone":"+32 2 643 42 42",
    "sg:postcode":"1050",
    "sg:province":"Bruxelles-Capitale",
    "wof:name":"Det O Partners",
    "wof:placetype":"venue"
},
  "geometry": {"coordinates":[4.3921380043,50.8189659119],"type":"Point"}
}