{
  "type": "Feature",
  "properties": {
    "addr:full":"Rue Mont De Solre 10 Erquelinnes Hainaut 6560",
    "addr:housenumber":"10",
    "addr:postcode":"6560",
    "addr:street":"Rue Mont De Solre",
    "iso:country":"BE",
    "sg:address":"Rue Mont De Solre 10",
    "sg:city":"Erquelinnes",
    "sg:orig_category":"Slagers",
    "sg:phone":"+32 71 55 54 76",
    "sg:postcode":"6560",
    "sg:province":"Hainaut",
    "wof:name":"Georges Detourbe",
    "wof:placetype":"venue"
},
  "geometry": {"coordinates":[4.1588401794,50.3061485291],"type":"Point"}
}