{
  "type": "Feature",
  "properties": {
    "iso:country":"BE",
    "sg:address":"Koning Leopold 1er 18",
    "sg:city":"Leuven",
    "sg:classifiers":[
        {
            "category":"Home & Garden",
            "subcategory":"Furniture",
            "type":"Retail Goods"
        }
    ],
    "sg:phone":"+32 16 29 44 55",
    "sg:postcode":"3000",
    "sg:province":"Vlaams-Brabant",
    "sg:tags":[
        "household",
        "wood"
    ],
    "wof:name":"Jan Nackaerts Bvba",
    "wof:placetype":"venue"
},
  "geometry": {"coordinates":[4.7086229324,50.879070282],"type":"Point"}
}