{
  "type": "Feature",
  "properties": {
    "addr:full":"Nieuwstraat 15 Kortemark West-Vlaanderen 8610",
    "addr:housenumber":"15",
    "addr:postcode":"8610",
    "addr:street":"Nieuwstraat",
    "iso:country":"BE",
    "sg:address":"Nieuwstraat 15",
    "sg:city":"Kortemark",
    "sg:classifiers":[
        {
            "category":"Retail",
            "subcategory":"Veterinary Services",
            "type":"Services"
        }
    ],
    "sg:phone":"+32 51 56 61 81",
    "sg:postcode":"8610",
    "sg:province":"West-Vlaanderen",
    "sg:tags":[
        "veterinarian"
    ],
    "wof:name":"Vulsteke G",
    "wof:placetype":"venue"
},
  "geometry": {"coordinates":[3.0441260338,51.0271835327],"type":"Point"}
}