{
  "type": "Feature",
  "properties": {
    "addr:full":"Kerkplein 3 Lokeren Oost-Vlaanderen 9160",
    "addr:housenumber":"3",
    "addr:postcode":"9160",
    "addr:street":"Kerkplein",
    "iso:country":"BE",
    "sg:address":"Kerkplein 3",
    "sg:city":"Lokeren",
    "sg:orig_category":"Biblioth\u00e8ques and archives publiques",
    "sg:phone":"+32 9 340 50 70",
    "sg:postcode":"9160",
    "sg:province":"Oost-Vlaanderen",
    "wof:name":"Openbare Bibliotheek",
    "wof:placetype":"venue"
},
  "geometry": {"coordinates":[3.9922609329,51.1045532227],"type":"Point"}
}