{
  "type": "Feature",
  "properties": {
    "iso:country":"BE",
    "sg:address":"Weggevoerdenlaan 2",
    "sg:city":"Kortrijk",
    "sg:orig_category":"Artsen and specialisten",
    "sg:phone":"+32 56 22 79 39",
    "sg:postcode":"8500",
    "sg:province":"West-Vlaanderen",
    "wof:name":"Yves Deltour",
    "wof:placetype":"venue"
},
  "geometry": {"coordinates":[3.2545330524,50.821056366],"type":"Point"}
}