{
  "type": "Feature",
  "properties": {
    "iso:country":"BE",
    "sg:address":"Kapellelaan 2",
    "sg:city":"Kraainem/kraainem",
    "sg:orig_category":"Artsen and specialisten",
    "sg:phone":"+32 2 720 36 01",
    "sg:postcode":"1950",
    "sg:province":"Vlaams-Brabant",
    "wof:name":"Thierry Vander Straeten",
    "wof:placetype":"venue"
},
  "geometry": {"coordinates":[4.4574480057,50.8615112305],"type":"Point"}
}