{
  "type": "Feature",
  "properties": {
    "iso:country":"BE",
    "sg:address":"Tongersesteenweg 8",
    "sg:city":"Riemst",
    "sg:orig_category":"Toeristische diensten",
    "sg:phone":"+32 12 45 19 30",
    "sg:postcode":"3770",
    "sg:province":"Limburg",
    "wof:name":"V.v.v. Riemst",
    "wof:placetype":"venue"
},
  "geometry": {"coordinates":[5.594645977,50.811756134],"type":"Point"}
}