{
  "type": "Feature",
  "properties": {
    "addr:full":"Berkenlaan 62 Grimbergen Vlaams-Brabant 1850",
    "addr:housenumber":"62",
    "addr:postcode":"1850",
    "addr:street":"Berkenlaan",
    "iso:country":"BE",
    "sg:address":"Berkenlaan 62",
    "sg:city":"Grimbergen",
    "sg:classifiers":[
        {
            "category":"Professional",
            "subcategory":"Accounting & Tax Preparation",
            "type":"Services"
        }
    ],
    "sg:phone":"+32 2 251 12 66",
    "sg:postcode":"1850",
    "sg:province":"Vlaams-Brabant",
    "sg:tags":[
        "accountant"
    ],
    "wof:name":"Daniel Draps",
    "wof:placetype":"venue"
},
  "geometry": {"coordinates":[4.3851461411,50.9202194214],"type":"Point"}
}