{
  "type": "Feature",
  "properties": {
    "iso:country":"BE",
    "sg:address":"Kasteelstraat 45",
    "sg:city":"Herzele",
    "sg:orig_category":"Installation de menuiserie en bois and plastique",
    "sg:phone":"+32 53 62 18 18",
    "sg:postcode":"9550",
    "sg:province":"Oost-Vlaanderen",
    "wof:name":"De Cock D",
    "wof:placetype":"venue"
},
  "geometry": {"coordinates":[3.9101951122,50.8710403442],"type":"Point"}
}