{
  "type": "Feature",
  "properties": {
    "iso:country":"BE",
    "sg:address":"Antwerpsesteenweg 76",
    "sg:city":"Vosselaar",
    "sg:classifiers":[
        {
            "category":"Personal",
            "subcategory":"Beauty Salon",
            "type":"Services"
        }
    ],
    "sg:phone":"+32 14 61 51 17",
    "sg:postcode":"2350",
    "sg:province":"Antwerpen",
    "sg:tags":[
        "de",
        "coiffure"
    ],
    "wof:name":"Coiffure Mario",
    "wof:placetype":"venue"
},
  "geometry": {"coordinates":[4.8886342049,51.3149299622],"type":"Point"}
}