{
  "type": "Feature",
  "properties": {
    "iso:country":"BE",
    "sg:address":"Rue Des Pr\u00c9s 38",
    "sg:city":"Leglise",
    "sg:orig_category":"Herstellingen and onderhoud van auto's",
    "sg:phone":"+32 63 60 03 23",
    "sg:postcode":"6860",
    "sg:province":"Luxembourg",
    "wof:name":"Garage Willemet",
    "wof:placetype":"venue"
},
  "geometry": {"coordinates":[5.6135911942,49.8739814758],"type":"Point"}
}