{
  "type": "Feature",
  "properties": {
    "iso:country":"BE",
    "sg:address":"Grote Markt 6",
    "sg:city":"Zoutleeuw",
    "sg:classifiers":[
        {
            "category":"Fast Food",
            "type":"Food & Drink"
        }
    ],
    "sg:phone":"+32 11 78 20 20",
    "sg:postcode":"3440",
    "sg:province":"Vlaams-Brabant",
    "sg:tags":[
        "fried",
        "stand",
        "potato"
    ],
    "wof:name":"Breughel",
    "wof:placetype":"venue"
},
  "geometry": {"coordinates":[5.1028909683,50.8328132629],"type":"Point"}
}