{
  "type": "Feature",
  "properties": {
    "iso:country":"BE",
    "sg:address":"Rue Supexhe 110",
    "sg:city":"Blegny",
    "sg:orig_category":"Eleveurs de bovins",
    "sg:phone":"+32 4 387 49 21",
    "sg:postcode":"4672",
    "sg:province":"Li\u00e8ge",
    "wof:name":"Prosper Biemar",
    "wof:placetype":"venue"
},
  "geometry": {"coordinates":[5.7018008232,50.6961021423],"type":"Point"}
}