{
  "type": "Feature",
  "properties": {
    "iso:country":"BE",
    "sg:address":"Domein Van Bouchout",
    "sg:city":"Meise",
    "sg:classifiers":[
        {
            "category":"Landmark",
            "subcategory":"Tourist Attraction",
            "type":"Public Place"
        }
    ],
    "sg:phone":"+32 2 269 39 05",
    "sg:postcode":"1860",
    "sg:province":"Vlaams-Brabant",
    "sg:tags":[
        "-",
        "tourism",
        "interest",
        "sight"
    ],
    "wof:name":"Nationale Plantentuin Van Belgi\u00eb",
    "wof:placetype":"venue"
},
  "geometry": {"coordinates":[4.3304052353,50.9334487915],"type":"Point"}
}