{
  "type": "Feature",
  "properties": {
    "iso:country":"BE",
    "sg:address":"Rue Nouvelle 16",
    "sg:city":"Mettet",
    "sg:orig_category":"Installation de menuiserie en bois and plastique. Meubles D\u00e9taillants, Am\u00e9nagement de B\u00e2timents et d",
    "sg:phone":"+32 71 72 77 26",
    "sg:postcode":"5640",
    "sg:province":"Namur",
    "wof:name":"Fe. Gillet P. & Fils",
    "wof:placetype":"venue"
},
  "geometry": {"coordinates":[4.6545100212,50.3391189575],"type":"Point"}
}