{
  "type": "Feature",
  "properties": {
    "addr:full":"Place Des Bienfaiteurs 7 Bruxelles (schaerbeek) Bruxelles-Capitale 1030",
    "addr:housenumber":"7",
    "addr:postcode":"1030",
    "addr:street":"Place Des Bienfaiteurs",
    "iso:country":"BE",
    "sg:address":"Place Des Bienfaiteurs 7",
    "sg:city":"Bruxelles (schaerbeek)",
    "sg:classifiers":[
        {
            "category":"Manufacturing",
            "subcategory":"Electronics",
            "type":"Manufacturing & Wholesale Goods"
        }
    ],
    "sg:phone":"+32 2 240 64 64",
    "sg:postcode":"1030",
    "sg:province":"Bruxelles-Capitale",
    "sg:tags":[
        "telecommunication",
        "system"
    ],
    "wof:name":"Bpt",
    "wof:placetype":"venue"
},
  "geometry": {"coordinates":[4.3836431503,50.8576812744],"type":"Point"}
}