{
  "type": "Feature",
  "properties": {
    "addr:full":"Het Schoemeken 19 Schilde Antwerpen 2970",
    "addr:housenumber":"19",
    "addr:postcode":"2970",
    "iso:country":"BE",
    "sg:address":"Het Schoemeken 19",
    "sg:city":"Schilde",
    "sg:classifiers":[
        {
            "category":"Building & Trades",
            "subcategory":"Cleaning & Sanitation",
            "type":"Services"
        }
    ],
    "sg:phone":"+32 3 383 39 23",
    "sg:postcode":"2970",
    "sg:province":"Antwerpen",
    "wof:name":"Drema",
    "wof:placetype":"venue"
},
  "geometry": {"coordinates":[4.5867900848,51.2385787964],"type":"Point"}
}