{
  "type": "Feature",
  "properties": {
    "addr:full":"Avenue Des Hirondelles 18 Waterloo Brabant Wallon 1410",
    "addr:housenumber":"18",
    "addr:postcode":"1410",
    "addr:street":"Avenue Des Hirondelles",
    "iso:country":"BE",
    "sg:address":"Avenue Des Hirondelles 18",
    "sg:city":"Waterloo",
    "sg:classifiers":[
        {
            "category":"Professional",
            "subcategory":"Accounting & Tax Preparation",
            "type":"Services"
        }
    ],
    "sg:phone":"+32 2 351 63 20",
    "sg:postcode":"1410",
    "sg:province":"Brabant Wallon",
    "sg:tags":[
        "bookkeeper"
    ],
    "wof:name":"Draguez Tripels De Hault D",
    "wof:placetype":"venue"
},
  "geometry": {"coordinates":[4.4004969597,50.7224960327],"type":"Point"}
}