{
  "type": "Feature",
  "properties": {
    "addr:full":"Handelslei 89 Zoersel Antwerpen 2980",
    "addr:housenumber":"89",
    "addr:postcode":"2980",
    "addr:street":"Handelslei",
    "iso:country":"BE",
    "sg:address":"Handelslei 89",
    "sg:city":"Zoersel",
    "sg:classifiers":[
        {
            "category":"Bus Station",
            "type":"Transportation"
        }
    ],
    "sg:phone":"+32 3 383 61 50",
    "sg:postcode":"2980",
    "sg:province":"Antwerpen",
    "sg:tags":[
        "navigation",
        "coastal",
        "-",
        "rhine",
        "shipping"
    ],
    "wof:name":"De Koning Scheepvaart Bvba",
    "wof:placetype":"venue"
},
  "geometry": {"coordinates":[4.645430088,51.2712097168],"type":"Point"}
}