{
  "type": "Feature",
  "properties": {
    "addr:full":"Chauss\u00c9e De Tongres 141 Juprelle Li\u00e8ge 4450",
    "addr:housenumber":"141",
    "addr:postcode":"4450",
    "addr:street":"Chausse\u0301E De Tongres",
    "iso:country":"BE",
    "sg:address":"Chauss\u00c9e De Tongres 141",
    "sg:city":"Juprelle",
    "sg:orig_category":"R\u00e9parations de chaussures and articles en cuir",
    "sg:phone":"+32 4 247 00 18",
    "sg:postcode":"4450",
    "sg:province":"Li\u00e8ge",
    "wof:name":"Laurent Noelmans",
    "wof:placetype":"venue"
},
  "geometry": {"coordinates":[5.5315198898,50.698299408],"type":"Point"}
}