{
  "type": "Feature",
  "properties": {
    "addr:full":"Chauss\u00e9e De La Hulpe 177 Box 10 Bruxelles (watermael-boitsfort) Bruxelles-Capitale 1170",
    "addr:housenumber":"177 box 10",
    "addr:postcode":"1170",
    "addr:street":"Chausse\u0301E De La Hulpe",
    "iso:country":"BE",
    "sg:address":"Chauss\u00e9e De La Hulpe 177 Box 10",
    "sg:city":"Bruxelles (watermael-boitsfort)",
    "sg:classifiers":[
        {
            "category":"Communications",
            "type":"Services"
        }
    ],
    "sg:phone":"+32 2 663 65 90",
    "sg:postcode":"1170",
    "sg:province":"Bruxelles-Capitale",
    "sg:tags":[
        "telecommunication"
    ],
    "wof:name":"Traff-x Sa",
    "wof:placetype":"venue"
},
  "geometry": {"coordinates":[4.4032540321,50.7958106995],"type":"Point"}
}