{
  "type": "Feature",
  "properties": {
    "iso:country":"BE",
    "sg:address":"Wijngaardstraat 89",
    "sg:city":"Gooik",
    "sg:orig_category":"Technische studies and ingenieursactiviteiten",
    "sg:phone":"+32 2 532 09 30",
    "sg:postcode":"1755",
    "sg:province":"Vlaams-Brabant",
    "wof:name":"Beetens En Persoons",
    "wof:placetype":"venue"
},
  "geometry": {"coordinates":[4.1264710426,50.7961654663],"type":"Point"}
}