{
  "type": "Feature",
  "properties": {
    "addr:full":"Hillarestraat 221 Lokeren Oost-Vlaanderen 9160",
    "addr:housenumber":"221",
    "addr:postcode":"9160",
    "addr:street":"Hillarestraat",
    "iso:country":"BE",
    "sg:address":"Hillarestraat 221",
    "sg:city":"Lokeren",
    "sg:classifiers":[
        {
            "category":"Health Services",
            "subcategory":"Health Practitioner",
            "type":"Services"
        }
    ],
    "sg:phone":"+32 9 348 45 87",
    "sg:postcode":"9160",
    "sg:province":"Oost-Vlaanderen",
    "sg:tags":[
        "physiotherapist"
    ],
    "wof:name":"Podevyn H",
    "wof:placetype":"venue"
},
  "geometry": {"coordinates":[3.9648559093,51.0916061401],"type":"Point"}
}