{
  "type": "Feature",
  "properties": {
    "addr:full":"Rue Du Plantis 4 Houyet (celles) Namur 5561",
    "addr:housenumber":"4",
    "addr:postcode":"5561",
    "addr:street":"Rue Du Plantis",
    "iso:country":"BE",
    "sg:address":"Rue Du Plantis 4",
    "sg:city":"Houyet (celles)",
    "sg:classifiers":[
        {
            "category":"Manufacturing",
            "subcategory":"Tools & Machinery",
            "type":"Manufacturing & Wholesale Goods"
        }
    ],
    "sg:phone":"+32 82 66 72 16",
    "sg:postcode":"5561",
    "sg:province":"Namur",
    "sg:tags":[
        "-"
    ],
    "wof:name":"Adnet D",
    "wof:placetype":"venue"
},
  "geometry": {"coordinates":[5.0096502304,50.229221344],"type":"Point"}
}