{
  "type": "Feature",
  "properties": {
    "addr:full":"Rue Abel Wart 233 Manage (fayt-lez-manage) Hainaut 7170",
    "addr:housenumber":"233",
    "addr:postcode":"7170",
    "addr:street":"Rue Abel Wart",
    "iso:country":"BE",
    "sg:address":"Rue Abel Wart 233",
    "sg:city":"Manage (fayt-lez-manage)",
    "sg:classifiers":[
        {
            "category":"Building & Trades",
            "subcategory":"Plumbing",
            "type":"Services"
        }
    ],
    "sg:phone":"+32 64 84 92 59",
    "sg:postcode":"7170",
    "sg:province":"Hainaut",
    "sg:tags":[
        "repair",
        "mainten",
        "-",
        "central",
        "heating"
    ],
    "wof:name":"Ronsin Chauffage",
    "wof:placetype":"venue"
},
  "geometry": {"coordinates":[4.2327899933,50.5008239746],"type":"Point"}
}