{
  "type": "Feature",
  "properties": {
    "addr:full":"Kloosterbaan 121a Arendonk Antwerpen 2370",
    "addr:housenumber":"121a",
    "addr:postcode":"2370",
    "addr:street":"Kloosterbaan",
    "iso:country":"BE",
    "sg:address":"Kloosterbaan 121a",
    "sg:city":"Arendonk",
    "sg:classifiers":[
        {
            "category":"Manufacturing",
            "subcategory":"Metals",
            "type":"Manufacturing & Wholesale Goods"
        }
    ],
    "sg:phone":"+32 14 67 12 42",
    "sg:postcode":"2370",
    "sg:province":"Antwerpen",
    "sg:tags":[
        "ornamental",
        "work",
        "-"
    ],
    "wof:name":"Slegers V",
    "wof:placetype":"venue"
},
  "geometry": {"coordinates":[5.0753679276,51.3271331787],"type":"Point"}
}