{
  "type": "Feature",
  "properties": {
    "iso:country":"BE",
    "sg:address":"Rue Du Pansy 312",
    "sg:city":"Saint-nicolas",
    "sg:classifiers":[
        {
            "category":"Retail",
            "subcategory":"Event Space",
            "type":"Services"
        }
    ],
    "sg:phone":"+32 4 233 33 82",
    "sg:postcode":"4420",
    "sg:province":"Li\u00e8ge",
    "sg:tags":[
        "rental",
        "-",
        "hall"
    ],
    "wof:name":"Capri (le)",
    "wof:placetype":"venue"
},
  "geometry": {"coordinates":[5.5217499733,50.6282691956],"type":"Point"}
}