{
  "type": "Feature",
  "properties": {
    "iso:country":"BE",
    "sg:address":"Scheldekaai 1bb",
    "sg:city":"Gent",
    "sg:orig_category":"Architecten",
    "sg:phone":"+32 9 232 18 50",
    "sg:postcode":"9050",
    "sg:province":"Oost-Vlaanderen",
    "wof:name":"Hugo Vanneste",
    "wof:placetype":"venue"
},
  "geometry": {"coordinates":[3.743252039,51.0433311462],"type":"Point"}
}