{
  "type": "Feature",
  "properties": {
    "addr:full":"Ringln 50 Eeklo Oost-Vlaanderen 9900",
    "addr:housenumber":"50",
    "addr:postcode":"9900",
    "addr:street":"Ringln",
    "iso:country":"BE",
    "sg:address":"Ringln 50",
    "sg:city":"Eeklo",
    "sg:classifiers":[
        {
            "category":"Manufacturing",
            "subcategory":"Building Materials",
            "type":"Manufacturing & Wholesale Goods"
        }
    ],
    "sg:phone":"+32 9 377 99 78",
    "sg:postcode":"9900",
    "sg:province":"Oost-Vlaanderen",
    "sg:tags":[
        "-",
        "machine",
        "raw",
        "engineering",
        "paper",
        "mechanical",
        "cardboard"
    ],
    "wof:name":"Avercon Nv",
    "wof:placetype":"venue"
},
  "geometry": {"coordinates":[3.564510107,51.1856040955],"type":"Point"}
}