{
  "type": "Feature",
  "properties": {
    "addr:full":"Keiberg 9 Tervuren Vlaams-Brabant 3080",
    "addr:housenumber":"9",
    "addr:postcode":"3080",
    "addr:street":"Keiberg",
    "iso:country":"BE",
    "sg:address":"Keiberg 9",
    "sg:city":"Tervuren",
    "sg:orig_category":"Elektrische installaties voor woningen",
    "sg:phone":"+32 2 767 17 05",
    "sg:postcode":"3080",
    "sg:province":"Vlaams-Brabant",
    "wof:name":"Luc Defraine",
    "wof:placetype":"venue"
},
  "geometry": {"coordinates":[4.5567932129,50.8401260376],"type":"Point"}
}