{
  "type": "Feature",
  "properties": {
    "addr:full":"Avenue Du Commerce 24a Braine L'alleud (braine-l'alleud) Brabant Wallon 1420",
    "addr:housenumber":"24a",
    "addr:postcode":"1420",
    "addr:street":"Avenue Du Commerce",
    "iso:country":"BE",
    "sg:address":"Avenue Du Commerce 24a",
    "sg:city":"Braine L'alleud (braine-l'alleud)",
    "sg:classifiers":[
        {
            "category":"Autos & Motor Vehicles",
            "subcategory":"Auto Supplies",
            "type":"Retail Goods"
        }
    ],
    "sg:phone":"+32 2 384 54 20",
    "sg:postcode":"1420",
    "sg:province":"Brabant Wallon",
    "sg:tags":[
        "access",
        "automobile",
        "part",
        "-"
    ],
    "wof:name":"Auto Braine Services Sprl",
    "wof:placetype":"venue"
},
  "geometry": {"coordinates":[-0.7004899979,47.369140625],"type":"Point"}
}