{
  "type": "Feature",
  "properties": {
    "iso:country":"BE",
    "sg:address":"Rue Jules Destr\u00e9e 147",
    "sg:city":"Anderlues",
    "sg:classifiers":[
        {
            "category":"Health Services",
            "subcategory":"Doctor",
            "type":"Services"
        }
    ],
    "sg:phone":"+32 71 52 73 69",
    "sg:postcode":"6150",
    "sg:province":"Hainaut",
    "sg:tags":[
        "medicinephysicians",
        "surgeon"
    ],
    "wof:name":"Lootvoet Louis",
    "wof:placetype":"venue"
},
  "geometry": {"coordinates":[4.2632842064,50.4241752625],"type":"Point"}
}