{
  "type": "Feature",
  "properties": {
    "iso:country":"BE",
    "sg:address":"Potaardestraat 35",
    "sg:city":"Sint-agatha-berchem",
    "sg:orig_category":"Elektrische installaties voor woningen Woningbouw",
    "sg:phone":"+32 2 468 22 94",
    "sg:postcode":"1082",
    "sg:province":"Bruxelles-Capitale",
    "wof:name":"Ruebens Marc",
    "wof:placetype":"venue"
},
  "geometry": {"coordinates":[4.2815151215,50.865814209],"type":"Point"}
}