{
  "type": "Feature",
  "properties": {
    "iso:country":"BE",
    "sg:address":"Roeselarestraat 109",
    "sg:city":"Wevelgem",
    "sg:orig_category":"Huishoudapparaten, televisies and radio's",
    "sg:phone":"+32 56 41 49 78",
    "sg:postcode":"8560",
    "sg:province":"West-Vlaanderen",
    "wof:name":"B. Breyne",
    "wof:placetype":"venue"
},
  "geometry": {"coordinates":[3.1802279949,50.8140487671],"type":"Point"}
}