{
  "type": "Feature",
  "properties": {
    "addr:full":"Duinberglaan 108 Leuven Vlaams-Brabant 3001",
    "addr:housenumber":"108",
    "addr:postcode":"3001",
    "addr:street":"Duinberglaan",
    "iso:country":"BE",
    "sg:address":"Duinberglaan 108",
    "sg:city":"Leuven",
    "sg:classifiers":[
        {
            "category":"Military Area",
            "subcategory":"Air Force Base",
            "type":"Public Place"
        }
    ],
    "sg:phone":"+32 16 40 80 58",
    "sg:postcode":"3001",
    "sg:province":"Vlaams-Brabant",
    "sg:tags":[
        "commerce",
        "gr",
        "equipement",
        "de",
        "\u00e9v\u00e9nements",
        "pour",
        "diver",
        "mat\u00e9riel",
        "location",
        "banquet"
    ],
    "wof:name":"Stein",
    "wof:placetype":"venue"
},
  "geometry": {"coordinates":[4.7037248611,50.861114502],"type":"Point"}
}