{
  "type": "Feature",
  "properties": {
    "addr:full":"Rue Roulette 11 Awans Li\u00e8ge 4340",
    "addr:housenumber":"11",
    "addr:postcode":"4340",
    "addr:street":"Rue Roulette",
    "iso:country":"BE",
    "sg:address":"Rue Roulette 11",
    "sg:city":"Awans",
    "sg:orig_category":"Peinture. Rev\u00eatements pour sols and murs",
    "sg:phone":"+32 4 257 42 23",
    "sg:postcode":"4340",
    "sg:province":"Li\u00e8ge",
    "wof:name":"Fernand Zilles",
    "wof:placetype":"venue"
},
  "geometry": {"coordinates":[5.4653058052,50.7127037048],"type":"Point"}
}