{
  "type": "Feature",
  "properties": {
    "addr:full":"Kortrijksteenweg 8 Wingene West-Vlaanderen 8750",
    "addr:housenumber":"8",
    "addr:postcode":"8750",
    "addr:street":"Kortrijksteenweg",
    "iso:country":"BE",
    "sg:address":"Kortrijksteenweg 8",
    "sg:city":"Wingene",
    "sg:orig_category":"Bouwwerktuigen Gh Elektrische installaties voor woningen Verhuur bouwmachines",
    "sg:phone":"+32 51 61 23 14",
    "sg:postcode":"8750",
    "sg:province":"West-Vlaanderen",
    "wof:name":"Geert Taeckens",
    "wof:placetype":"venue"
},
  "geometry": {"coordinates":[3.2291760445,51.0367698669],"type":"Point"}
}