{
  "type": "Feature",
  "properties": {
    "addr:full":"Nieuwe Steenweg 96 Zuienkerke West-Vlaanderen 8377",
    "addr:housenumber":"96",
    "addr:postcode":"8377",
    "addr:street":"Nieuwe Steenweg",
    "iso:country":"BE",
    "sg:address":"Nieuwe Steenweg 96",
    "sg:city":"Zuienkerke",
    "sg:orig_category":"Enseignement maternel and primaire",
    "sg:phone":"+32 50 42 65 29",
    "sg:postcode":"8377",
    "sg:province":"West-Vlaanderen",
    "wof:name":"Vrije Basisschool",
    "wof:placetype":"venue"
},
  "geometry": {"coordinates":[3.153345108,51.2646064758],"type":"Point"}
}