{
  "type": "Feature",
  "properties": {
    "iso:country":"BE",
    "sg:address":"Kerkplein 216",
    "sg:city":"\u00b4s Gravenvoeren",
    "sg:orig_category":"Offices du tourisme. Librairies",
    "sg:phone":"+32 4 381 07 36",
    "sg:postcode":"3798",
    "sg:province":"Limburg",
    "wof:name":"Toerisme Voerstreek",
    "wof:placetype":"venue"
},
  "geometry": {"coordinates":[5.7587299347,50.7593955994],"type":"Point"}
}