{
  "type": "Feature",
  "properties": {
    "addr:full":"Boulevard Gustave Roullier 1 Charleroi Hainaut 6000",
    "addr:housenumber":"1",
    "addr:postcode":"6000",
    "addr:street":"Boulevard Gustave Roullier;Hainaut",
    "iso:country":"BE",
    "sg:address":"Boulevard Gustave Roullier 1",
    "sg:city":"Charleroi",
    "sg:classifiers":[
        {
            "category":"Education",
            "subcategory":"School",
            "type":"Public Place"
        }
    ],
    "sg:phone":"+32 71 53 12 11",
    "sg:postcode":"6000",
    "sg:province":"Hainaut",
    "sg:tags":[
        "secondary"
    ],
    "wof:name":"Universit\u00e9 Du Travail De Charleroi",
    "wof:placetype":"venue"
},
  "geometry": {"coordinates":[4.4480810165,50.4173851013],"type":"Point"}
}