{
  "type": "Feature",
  "properties": {
    "addr:full":"Boulevard Initialis 5 Mons Hainaut 7000",
    "addr:housenumber":"5",
    "addr:postcode":"7000",
    "addr:street":"Boulevard Initialis;Hainaut",
    "iso:country":"BE",
    "sg:address":"Boulevard Initialis 5",
    "sg:city":"Mons",
    "sg:classifiers":[
        {
            "category":"Transit Center",
            "subcategory":"Freight",
            "type":"Transportation"
        }
    ],
    "sg:phone":"+32 65 40 16 76",
    "sg:postcode":"7000",
    "sg:province":"Hainaut",
    "sg:tags":[
        "enzyme"
    ],
    "wof:name":"Biochem-europe S.a.",
    "wof:placetype":"venue"
},
  "geometry": {"coordinates":[3.9267599583,50.4598045349],"type":"Point"}
}