{
  "type": "Feature",
  "properties": {
    "addr:full":"Langemunt 12 Gent Oost-Vlaanderen 9000",
    "addr:housenumber":"12",
    "addr:postcode":"9000",
    "addr:street":"Langemunt;Oost-Vlaanderen",
    "iso:country":"BE",
    "sg:address":"Langemunt 12",
    "sg:city":"Gent",
    "sg:orig_category":"HERSTELLING ELEKTRISCHE HUISHOUDAPPARATEN Huishoudapparaten, televisies and radio's",
    "sg:phone":"+32 9 223 69 24",
    "sg:postcode":"9000",
    "sg:province":"Oost-Vlaanderen",
    "wof:name":"Skala",
    "wof:placetype":"venue"
},
  "geometry": {"coordinates":[3.7227990627,51.0558204651],"type":"Point"}
}