{
  "type": "Feature",
  "properties": {
    "addr:full":"Het Lak 1 Hoogstraten Antwerpen 2321",
    "addr:housenumber":"1",
    "addr:postcode":"2321",
    "addr:street":"Het Lak",
    "iso:country":"BE",
    "sg:address":"Het Lak 1",
    "sg:city":"Hoogstraten",
    "sg:orig_category":"Drogueries",
    "sg:phone":"+32 3 315 08 51",
    "sg:postcode":"2321",
    "sg:province":"Antwerpen",
    "wof:name":"Maria Schoenmaekers",
    "wof:placetype":"venue"
},
  "geometry": {"coordinates":[4.7354521751,51.4419403076],"type":"Point"}
}