{
  "type": "Feature",
  "properties": {
    "iso:country":"BE",
    "sg:address":"Steenbeekstraat 30",
    "sg:city":"Houthulst (ronehoek - Nieuwe Stede)",
    "sg:classifiers":[
        {
            "category":"Wholesale",
            "subcategory":"Fruits & Vegetables",
            "type":"Manufacturing & Wholesale Goods"
        }
    ],
    "sg:phone":"+32 475 25 09 52",
    "sg:postcode":"8650",
    "sg:province":"West-Vlaanderen",
    "sg:tags":[
        "whol",
        "-",
        "potato"
    ],
    "wof:name":"Jonkers Patat Bvba",
    "wof:placetype":"venue"
},
  "geometry": {"coordinates":[2.9010798931,50.9748802185],"type":"Point"}
}