{
  "type": "Feature",
  "properties": {
    "addr:full":"Place De Saint-martin 92 Jemeppe-sur-sambre Namur 5190",
    "addr:housenumber":"92",
    "addr:postcode":"5190",
    "addr:street":"Place De Saint-Martin",
    "iso:country":"BE",
    "sg:address":"Place De Saint-martin 92",
    "sg:city":"Jemeppe-sur-sambre",
    "sg:orig_category":"V\u00e9t\u00e9rinaires",
    "sg:phone":"+32 81 63 45 46",
    "sg:postcode":"5190",
    "sg:province":"Namur",
    "wof:name":"Pascale Van Rijckevorsel",
    "wof:placetype":"venue"
},
  "geometry": {"coordinates":[4.6466140747,50.5012130737],"type":"Point"}
}