{
  "type": "Feature",
  "properties": {
    "iso:country":"BE",
    "sg:address":"Hogestraat 58",
    "sg:city":"Kortemark",
    "sg:orig_category":"Woningbouw",
    "sg:phone":"+32 51 56 66 82",
    "sg:postcode":"8610",
    "sg:province":"West-Vlaanderen",
    "wof:name":"Andre Deopere",
    "wof:placetype":"venue"
},
  "geometry": {"coordinates":[3.0078439713,51.0482139587],"type":"Point"}
}