{
  "type": "Feature",
  "properties": {
    "addr:full":"Rue De L'institut 48a Rixensart Brabant Wallon 1330",
    "addr:housenumber":"48a",
    "addr:postcode":"1330",
    "addr:street":"Rue De L'Institut;Wallon",
    "iso:country":"BE",
    "sg:address":"Rue De L'institut 48a",
    "sg:city":"Rixensart",
    "sg:classifiers":[
        {
            "category":"Building & Trades",
            "subcategory":"Electrical",
            "type":"Services"
        }
    ],
    "sg:phone":"+32 2 652 27 32",
    "sg:postcode":"1330",
    "sg:province":"Brabant Wallon",
    "sg:tags":[
        "electric",
        "-",
        "housewiring",
        "contractor"
    ],
    "wof:name":"Da Silva C Sprl",
    "wof:placetype":"venue"
},
  "geometry": {"coordinates":[4.5291118622,50.7189712524],"type":"Point"}
}