{
  "type": "Feature",
  "properties": {
    "iso:country":"BE",
    "sg:address":"Rue De Waremme 48",
    "sg:city":"Villers-le-bouillet",
    "sg:classifiers":[
        {
            "category":"Professional",
            "subcategory":"Detective & Security Services",
            "type":"Services"
        }
    ],
    "sg:phone":"+32 85 23 03 99",
    "sg:postcode":"4530",
    "sg:province":"Li\u00e8ge",
    "sg:tags":[
        "access-control",
        "system"
    ],
    "wof:name":"Afsluitingen Guisse",
    "wof:placetype":"venue"
},
  "geometry": {"coordinates":[5.266023159,50.5703964233],"type":"Point"}
}