{
  "type": "Feature",
  "properties": {
    "addr:full":"Square Marguerite 28 Bruxelles Bruxelles-Capitale 1000",
    "addr:housenumber":"28",
    "addr:postcode":"1000",
    "addr:street":"Square Marguerite",
    "iso:country":"BE",
    "sg:address":"Square Marguerite 28",
    "sg:city":"Bruxelles",
    "sg:classifiers":[
        {
            "category":"Food & Beverages",
            "subcategory":"Groceries & Convenience Stores",
            "type":"Retail Goods"
        }
    ],
    "sg:phone":"+32 2 734 11 56",
    "sg:postcode":"1000",
    "sg:province":"Bruxelles-Capitale",
    "sg:tags":[
        "grocer"
    ],
    "wof:name":"Apicius",
    "wof:placetype":"venue"
},
  "geometry": {"coordinates":[4.387114048,50.8468437195],"type":"Point"}
}