{
  "type": "Feature",
  "properties": {
    "iso:country":"BE",
    "sg:address":"Gemeentestraat 2",
    "sg:city":"Oud-heverlee",
    "sg:orig_category":"Werk and personeelsselectie",
    "sg:phone":"+32 16 40 12 55",
    "sg:postcode":"3054",
    "sg:province":"Vlaams-Brabant",
    "wof:name":"Pwa Oud-heverlee",
    "wof:placetype":"venue"
},
  "geometry": {"coordinates":[4.6899847984,50.8270301819],"type":"Point"}
}