{
  "type": "Feature",
  "properties": {
    "iso:country":"BE",
    "sg:address":"Rue De Devant-les-bois 34",
    "sg:city":"Mettet",
    "sg:orig_category":"Artsen and specialisten",
    "sg:phone":"+32 71 72 88 85",
    "sg:postcode":"5640",
    "sg:province":"Namur",
    "wof:name":"Pierre Roquet-gravy",
    "wof:placetype":"venue"
},
  "geometry": {"coordinates":[4.6408238411,50.347820282],"type":"Point"}
}