{
  "type": "Feature",
  "properties": {
    "iso:country":"BE",
    "sg:address":"Rue T. Toussaint 38",
    "sg:city":"Gembloux",
    "sg:classifiers":[
        {
            "category":"Sports & Exercise",
            "subcategory":"Sports Center",
            "type":"Entertainment"
        }
    ],
    "sg:phone":"+32 81 61 26 45",
    "sg:postcode":"5030",
    "sg:province":"Namur",
    "sg:tags":[
        "de",
        "fitness"
    ],
    "wof:name":"Olympic Gym",
    "wof:placetype":"venue"
},
  "geometry": {"coordinates":[4.6902542114,50.5592575073],"type":"Point"}
}