{
  "type": "Feature",
  "properties": {
    "addr:full":"Nati\u00ebnlaan 6 Damme (moerkerke) West-Vlaanderen 8340",
    "addr:housenumber":"6",
    "addr:postcode":"8340",
    "addr:street":"Natie\u0308Nlaan",
    "iso:country":"BE",
    "sg:address":"Nati\u00ebnlaan 6",
    "sg:city":"Damme (moerkerke)",
    "sg:classifiers":[
        {
            "category":"Autos & Motor Vehicles",
            "subcategory":"Automobile Sales",
            "type":"Retail Goods"
        }
    ],
    "sg:phone":"+32 50 60 98 76",
    "sg:postcode":"8340",
    "sg:province":"West-Vlaanderen",
    "sg:tags":[
        "car",
        "used",
        "-"
    ],
    "wof:name":"Stroo S",
    "wof:placetype":"venue"
},
  "geometry": {"coordinates":[3.330065012,51.299331665],"type":"Point"}
}