{
  "type": "Feature",
  "properties": {
    "iso:country":"BE",
    "sg:address":"Blerebergstraat 7",
    "sg:city":"Tielt-winge",
    "sg:classifiers":[
        {
            "category":"Cafe",
            "type":"Food & Drink"
        }
    ],
    "sg:phone":"+32 16 63 51 52",
    "sg:postcode":"3390",
    "sg:province":"Vlaams-Brabant",
    "sg:tags":[
        "caf\u00e9s"
    ],
    "wof:name":"Caf\u00c9 Berg & Dal",
    "wof:placetype":"venue"
},
  "geometry": {"coordinates":[4.9100298882,50.9277305603],"type":"Point"}
}