{
  "type": "Feature",
  "properties": {
    "addr:full":"Loten 9 Eupen Li\u00e8ge 4700",
    "addr:housenumber":"9",
    "addr:postcode":"4700",
    "addr:street":"Loten",
    "iso:country":"BE",
    "sg:address":"Loten 9",
    "sg:city":"Eupen",
    "sg:classifiers":[
        {
            "category":"Insurance",
            "subcategory":"Insurance Agent",
            "type":"Services"
        }
    ],
    "sg:phone":"+32 87 74 22 57",
    "sg:postcode":"4700",
    "sg:province":"Li\u00e8ge",
    "sg:tags":[
        "broker"
    ],
    "wof:name":"Frank W",
    "wof:placetype":"venue"
},
  "geometry": {"coordinates":[6.0297541618,50.6255645752],"type":"Point"}
}