{
  "type": "Feature",
  "properties": {
    "iso:country":"BE",
    "sg:address":"Rue De Booze 7",
    "sg:city":"Bl\u00e9gny (trembleur)",
    "sg:classifiers":[
        {
            "category":"Real Estate",
            "subcategory":"Real Estate Services",
            "type":"Services"
        }
    ],
    "sg:phone":"+32 4 387 40 89",
    "sg:postcode":"4670",
    "sg:province":"Li\u00e8ge",
    "wof:name":"B.g.c.i. Sprl",
    "wof:placetype":"venue"
},
  "geometry": {"coordinates":[5.7144122124,50.6765518188],"type":"Point"}
}