{
  "type": "Feature",
  "properties": {
    "addr:full":"Jan Blockxstraat 23 Antwerpen Antwerpen 2018",
    "addr:housenumber":"23",
    "addr:postcode":"2018",
    "addr:street":"Jan Blockxstraat",
    "iso:country":"BE",
    "sg:address":"Jan Blockxstraat 23",
    "sg:city":"Antwerpen",
    "sg:classifiers":[
        {
            "category":"Real Estate",
            "subcategory":"Architect",
            "type":"Services"
        }
    ],
    "sg:phone":"+32 3 237 88 91",
    "sg:postcode":"2018",
    "sg:province":"Antwerpen",
    "wof:name":"Nelis G Mevr",
    "wof:placetype":"venue"
},
  "geometry": {"coordinates":[4.4065999985,51.2040557861],"type":"Point"}
}