{
  "type": "Feature",
  "properties": {
    "iso:country":"BE",
    "sg:address":"Chauss\u00c9e De Redemont 111",
    "sg:city":"La Louviere",
    "sg:orig_category":"Mat\u00e9riaux de construction Produits chimiques Gr",
    "sg:phone":"+32 64 22 36 23",
    "sg:postcode":"7100",
    "sg:province":"Hainaut",
    "wof:name":"Coulon Pierre Ets",
    "wof:placetype":"venue"
},
  "geometry": {"coordinates":[4.2071900368,50.4667510986],"type":"Point"}
}