{
  "type": "Feature",
  "properties": {
    "iso:country":"BE",
    "sg:address":"Avenue De Tervueren 182",
    "sg:city":"Bruxelles (woluwe-saint-pierre)",
    "sg:classifiers":[
        {
            "category":"Insurance",
            "subcategory":"Life Insurance",
            "type":"Services"
        }
    ],
    "sg:phone":"+32 2 775 80 05",
    "sg:postcode":"1150",
    "sg:province":"Bruxelles-Capitale",
    "sg:tags":[
        "refinery",
        "-",
        "sugar"
    ],
    "wof:name":"Tiense Suikerraffinaderij",
    "wof:placetype":"venue"
},
  "geometry": {"coordinates":[4.4110479355,50.8370742798],"type":"Point"}
}