{
  "type": "Feature",
  "properties": {
    "iso:country":"BE",
    "sg:address":"Chauss\u00e9e De Louvain 837",
    "sg:city":"Bruxelles (evere)",
    "sg:classifiers":[
        {
            "category":"Home & Garden",
            "subcategory":"Kitchen Supply",
            "type":"Retail Goods"
        }
    ],
    "sg:phone":"+32 2 726 68 20",
    "sg:postcode":"1140",
    "sg:province":"Bruxelles-Capitale",
    "sg:tags":[
        "installation"
    ],
    "wof:name":"Maes Frank Sprl",
    "wof:placetype":"venue"
},
  "geometry": {"coordinates":[4.4154529572,50.8594703674],"type":"Point"}
}