{
  "type": "Feature",
  "properties": {
    "iso:country":"BE",
    "sg:address":"Noordzandstraat 26",
    "sg:city":"Brugge",
    "sg:orig_category":"Machines \u00e0 coudre and tricoter",
    "sg:phone":"+32 50 33 47 53",
    "sg:postcode":"8000",
    "sg:province":"West-Vlaanderen",
    "wof:name":"Lowyck",
    "wof:placetype":"venue"
},
  "geometry": {"coordinates":[3.220484972,51.2077713013],"type":"Point"}
}