{
  "type": "Feature",
  "properties": {
    "iso:country":"BE",
    "sg:address":"Rue Ernest Martel 61",
    "sg:city":"Ecaussinnes",
    "sg:orig_category":"S\u00e9curit\u00e9 sociale",
    "sg:phone":"+32 67 44 32 82",
    "sg:postcode":"7190",
    "sg:province":"Hainaut",
    "wof:name":"Mutualit\u00c9 Socialiste",
    "wof:placetype":"venue"
},
  "geometry": {"coordinates":[4.1639289856,50.5657348633],"type":"Point"}
}