{
  "type": "Feature",
  "properties": {
    "addr:full":"Rue De Maire 10 Tournai Hainaut 7503",
    "addr:housenumber":"10",
    "addr:postcode":"7503",
    "addr:street":"Rue De Maire",
    "iso:country":"BE",
    "sg:address":"Rue De Maire 10",
    "sg:city":"Tournai",
    "sg:orig_category":"Boissons",
    "sg:phone":"+32 69 84 56 66",
    "sg:postcode":"7503",
    "sg:province":"Hainaut",
    "wof:name":"Servi Drinks",
    "wof:placetype":"venue"
},
  "geometry": {"coordinates":[3.3721559048,50.6250534058],"type":"Point"}
}