{
  "type": "Feature",
  "properties": {
    "iso:country":"BE",
    "sg:address":"Gaarshof 3",
    "sg:city":"Hoogstraten",
    "sg:orig_category":"Rundveehouders Varkenskwekers",
    "sg:phone":"+32 3 315 71 77",
    "sg:postcode":"2321",
    "sg:province":"Antwerpen",
    "wof:name":"Jaak Goetschalckx",
    "wof:placetype":"venue"
},
  "geometry": {"coordinates":[4.7300047874,51.46118927],"type":"Point"}
}