{
  "type": "Feature",
  "properties": {
    "addr:full":". Hoegaarden (groot) Vlaams-Brabant 3320",
    "addr:postcode":"3320",
    "addr:street":"Groot Vlaams-Brabant",
    "iso:country":"BE",
    "sg:address":".",
    "sg:city":"Hoegaarden (groot)",
    "sg:orig_category":"Apotheken",
    "sg:phone":"+32 900 10 500",
    "sg:postcode":"3320",
    "sg:province":"Vlaams-Brabant",
    "wof:name":"Apothekers Van Wacht",
    "wof:placetype":"venue"
},
  "geometry": {"coordinates":[4.8881611824,50.7744941711],"type":"Point"}
}