{
  "type": "Feature",
  "properties": {
    "addr:full":"Kruisstraat 45 Sint-niklaas Oost-Vlaanderen 9111",
    "addr:housenumber":"45",
    "addr:postcode":"9111",
    "addr:street":"Kruisstraat",
    "iso:country":"BE",
    "sg:address":"Kruisstraat 45",
    "sg:city":"Sint-niklaas",
    "sg:orig_category":"Brood, gebak and snoepgoed",
    "sg:phone":"+32 3 772 30 81",
    "sg:postcode":"9111",
    "sg:province":"Oost-Vlaanderen",
    "wof:name":"De Koning-d'haese",
    "wof:placetype":"venue"
},
  "geometry": {"coordinates":[4.0661268234,51.1715698242],"type":"Point"}
}