{
  "type": "Feature",
  "properties": {
    "addr:full":"Rue De Neufch\u00c2teau 157 Bastogne Luxembourg 6600",
    "addr:housenumber":"157",
    "addr:postcode":"6600",
    "addr:street":"Rue De Neufcha\u0302Teau",
    "iso:country":"BE",
    "sg:address":"Rue De Neufch\u00c2teau 157",
    "sg:city":"Bastogne",
    "sg:orig_category":"Charpentes and couvertures",
    "sg:phone":"+32 61 21 45 83",
    "sg:postcode":"6600",
    "sg:province":"Luxembourg",
    "wof:name":"Toitures Bauvir",
    "wof:placetype":"venue"
},
  "geometry": {"coordinates":[5.7027831078,49.9929428101],"type":"Point"}
}