{
  "type": "Feature",
  "properties": {
    "addr:full":"Bosstraat 2a Pepingen Vlaams-Brabant 1670",
    "addr:housenumber":"2a",
    "addr:postcode":"1670",
    "addr:street":"Bosstraat",
    "iso:country":"BE",
    "sg:address":"Bosstraat 2a",
    "sg:city":"Pepingen",
    "sg:orig_category":"V\u00e9hicules automobiles. Entretien and r\u00e9parations de voitures",
    "sg:phone":"+32 2 396 10 06",
    "sg:postcode":"1670",
    "sg:province":"Vlaams-Brabant",
    "wof:name":"Garage Reygaerts",
    "wof:placetype":"venue"
},
  "geometry": {"coordinates":[4.0975928307,50.7266235352],"type":"Point"}
}