{
  "type": "Feature",
  "properties": {
    "iso:country":"BE",
    "sg:address":"Rue De La Basse Hestre 102",
    "sg:city":"Manage",
    "sg:orig_category":"Messageries",
    "sg:phone":"+32 64 55 92 29",
    "sg:postcode":"7170",
    "sg:province":"Hainaut",
    "wof:name":"T.j.p. Express",
    "wof:placetype":"venue"
},
  "geometry": {"coordinates":[4.2426009178,50.4837379456],"type":"Point"}
}