{
  "type": "Feature",
  "properties": {
    "iso:country":"BE",
    "sg:address":"Moerkerkse Steenweg 23",
    "sg:city":"Brugge (sint-kruis)",
    "sg:classifiers":[
        {
            "category":"Professional",
            "subcategory":"Testing Lab",
            "type":"Services"
        }
    ],
    "sg:phone":"+32 50 37 65 12",
    "sg:postcode":"8310",
    "sg:province":"West-Vlaanderen",
    "sg:tags":[
        "chemist"
    ],
    "wof:name":"Vandepitte L",
    "wof:placetype":"venue"
},
  "geometry": {"coordinates":[3.242855072,51.2127685547],"type":"Point"}
}