{
  "type": "Feature",
  "properties": {
    "addr:full":"Genthof 32 Brugge West-Vlaanderen 8000",
    "addr:housenumber":"32",
    "addr:postcode":"8000",
    "addr:street":"Genthof",
    "iso:country":"BE",
    "sg:address":"Genthof 32",
    "sg:city":"Brugge",
    "sg:classifiers":[
        {
            "category":"Professional",
            "subcategory":"Art Services",
            "type":"Services"
        }
    ],
    "sg:phone":"+32 50 61 37 46",
    "sg:postcode":"8000",
    "sg:province":"West-Vlaanderen",
    "sg:tags":[
        "-",
        "painter",
        "artist"
    ],
    "wof:name":"Kunstschilder/portretist",
    "wof:placetype":"venue"
},
  "geometry": {"coordinates":[3.2274289131,51.212688446],"type":"Point"}
}