{
  "type": "Feature",
  "properties": {
    "addr:full":"Sint-simonstraat 12 Gent (gentbrugge) Oost-Vlaanderen 9050",
    "addr:housenumber":"12",
    "addr:postcode":"9050",
    "addr:street":"Sint-Simonstraat",
    "iso:country":"BE",
    "sg:address":"Sint-simonstraat 12",
    "sg:city":"Gent (gentbrugge)",
    "sg:classifiers":[
        {
            "category":"Bars & Pubs",
            "type":"Food & Drink"
        }
    ],
    "sg:phone":"+32 9 230 26 38",
    "sg:postcode":"9050",
    "sg:province":"Oost-Vlaanderen",
    "wof:name":"Kring",
    "wof:placetype":"venue"
},
  "geometry": {"coordinates":[3.7578990459,51.0446281433],"type":"Point"}
}