{
  "type": "Feature",
  "properties": {
    "iso:country":"BE",
    "sg:address":"Pastoorsstraat 11",
    "sg:city":"Zutendaal",
    "sg:orig_category":"Eleveurs de bovins",
    "sg:phone":"+32 89 61 10 77",
    "sg:postcode":"3690",
    "sg:province":"Limburg",
    "wof:name":"Eddy Menten",
    "wof:placetype":"venue"
},
  "geometry": {"coordinates":[5.5690431595,50.9266166687],"type":"Point"}
}