{
  "type": "Feature",
  "properties": {
    "addr:full":"Wolstraat 24-31 Antwerpen Antwerpen 2000",
    "addr:postcode":"24-31;2000",
    "addr:street":"Wolstraat",
    "iso:country":"BE",
    "sg:address":"Wolstraat 24-31",
    "sg:city":"Antwerpen",
    "sg:classifiers":[
        {
            "category":"Professional",
            "subcategory":"Art Services",
            "type":"Services"
        }
    ],
    "sg:phone":"+32 3 213 33 94",
    "sg:postcode":"2000",
    "sg:province":"Antwerpen",
    "sg:tags":[
        "-",
        "valuer"
    ],
    "wof:name":"Van Dyck B",
    "wof:placetype":"venue"
},
  "geometry": {"coordinates":[4.403799057,51.2214431763],"type":"Point"}
}