{
  "type": "Feature",
  "properties": {
    "iso:country":"BE",
    "sg:address":"Avenue Georges Henri 481",
    "sg:city":"Bruxelles (woluwe-saint-lambert)",
    "sg:classifiers":[
        {
            "category":"Home & Garden",
            "subcategory":"Home Furnishings",
            "type":"Retail Goods"
        }
    ],
    "sg:phone":"+32 2 735 13 44",
    "sg:postcode":"1200",
    "sg:province":"Bruxelles-Capitale",
    "sg:tags":[
        "-",
        "furniture"
    ],
    "wof:name":"Envie De Bois",
    "wof:placetype":"venue"
},
  "geometry": {"coordinates":[4.404156208,50.8416519165],"type":"Point"}
}