{
  "type": "Feature",
  "properties": {
    "addr:full":"Kaaiplein 29 Hamme (groot) Oost-Vlaanderen 9220",
    "addr:housenumber":"29",
    "addr:postcode":"9220",
    "addr:street":"Kaaiplein;Groot Oost-Vlaanderen",
    "iso:country":"BE",
    "sg:address":"Kaaiplein 29",
    "sg:city":"Hamme (groot)",
    "sg:orig_category":"Maatschappelijke dienstverlening",
    "sg:phone":"+32 52 47 74 62",
    "sg:postcode":"9220",
    "sg:province":"Oost-Vlaanderen",
    "wof:name":"Clb",
    "wof:placetype":"venue"
},
  "geometry": {"coordinates":[4.1348900795,51.1028518677],"type":"Point"}
}