{
  "type": "Feature",
  "properties": {
    "addr:full":"Kortrijksestraat 170 Oostkamp West-Vlaanderen 8020",
    "addr:housenumber":"170",
    "addr:postcode":"8020",
    "addr:street":"Kortrijksestraat",
    "iso:country":"BE",
    "sg:address":"Kortrijksestraat 170",
    "sg:city":"Oostkamp",
    "sg:classifiers":[
        {
            "category":"Retail",
            "subcategory":"Auto Repair",
            "type":"Services"
        }
    ],
    "sg:phone":"+32 50 82 20 29",
    "sg:postcode":"8020",
    "sg:province":"West-Vlaanderen",
    "sg:tags":[
        "garage"
    ],
    "wof:name":"Vanquathem Bvba",
    "wof:placetype":"venue"
},
  "geometry": {"coordinates":[3.2318539619,51.1473197937],"type":"Point"}
}