{
  "type": "Feature",
  "properties": {
    "iso:country":"BE",
    "sg:address":"Rue De La Bruy\u00e8re Du Masy 12",
    "sg:city":"Ittre",
    "sg:classifiers":[
        {
            "category":"Professional",
            "subcategory":"Lawyer & Legal Services",
            "type":"Services"
        }
    ],
    "sg:phone":"+32 67 21 34 02",
    "sg:postcode":"1460",
    "sg:province":"Brabant Wallon",
    "wof:name":"Deramaix Cassandra",
    "wof:placetype":"venue"
},
  "geometry": {"coordinates":[4.2463412285,50.647644043],"type":"Point"}
}