{
  "type": "Feature",
  "properties": {
    "addr:full":"Rue Aux Fraises 21 Andenne Namur 5300",
    "addr:housenumber":"21",
    "addr:postcode":"5300",
    "addr:street":"Rue Aux Fraises",
    "iso:country":"BE",
    "sg:address":"Rue Aux Fraises 21",
    "sg:city":"Andenne",
    "sg:classifiers":[
        {
            "category":"Professional",
            "subcategory":"Accounting & Tax Preparation",
            "type":"Services"
        }
    ],
    "sg:phone":"+32 85 84 12 28",
    "sg:postcode":"5300",
    "sg:province":"Namur",
    "sg:tags":[
        "accountant"
    ],
    "wof:name":"Francis Docquier",
    "wof:placetype":"venue"
},
  "geometry": {"coordinates":[5.1056890488,50.4858932495],"type":"Point"}
}