{
  "type": "Feature",
  "properties": {
    "iso:country":"BE",
    "sg:address":"De Linden 21",
    "sg:city":"Zandhoven",
    "sg:orig_category":"Artsen and specialisten",
    "sg:phone":"+32 3 464 12 77",
    "sg:postcode":"2240",
    "sg:province":"Antwerpen",
    "wof:name":"Filip Bernaerts",
    "wof:placetype":"venue"
},
  "geometry": {"coordinates":[4.6619992256,51.2144241333],"type":"Point"}
}