{
  "type": "Feature",
  "properties": {
    "addr:full":"Sander De Vosstraat 120 Lier Antwerpen 2500",
    "addr:housenumber":"120",
    "addr:postcode":"2500",
    "addr:street":"Sander De Vosstraat",
    "iso:country":"BE",
    "sg:address":"Sander De Vosstraat 120",
    "sg:city":"Lier",
    "sg:orig_category":"Eleveurs de bovins",
    "sg:phone":"+32 3 482 13 33",
    "sg:postcode":"2500",
    "sg:province":"Antwerpen",
    "wof:name":"Andre Dillen",
    "wof:placetype":"venue"
},
  "geometry": {"coordinates":[4.6269521713,51.0875778198],"type":"Point"}
}