{
  "type": "Feature",
  "properties": {
    "addr:full":"Industristrasse 18 Eupen Li\u00e8ge 4700",
    "addr:housenumber":"18",
    "addr:postcode":"4700",
    "addr:street":"Industristrasse",
    "iso:country":"BE",
    "sg:address":"Industristrasse 18",
    "sg:city":"Eupen",
    "sg:orig_category":"Procesbesturingssystemen Fab",
    "sg:phone":"+32 87 59 53 00",
    "sg:postcode":"4700",
    "sg:province":"Li\u00e8ge",
    "wof:name":"Jumo Automation",
    "wof:placetype":"venue"
},
  "geometry": {"coordinates":[6.0075001717,50.6406707764],"type":"Point"}
}