{
  "type": "Feature",
  "properties": {
    "addr:full":"Waterloose Steenweg 216 Sint-gillis/saint-gilles Bruxelles-Capitale 1060",
    "addr:housenumber":"216",
    "addr:postcode":"1060",
    "addr:street":"Waterloose Steenweg",
    "iso:country":"BE",
    "sg:address":"Waterloose Steenweg 216",
    "sg:city":"Sint-gillis/saint-gilles",
    "sg:orig_category":"Banken and kredietinstellingen",
    "sg:phone":"+32 2 537 64 40",
    "sg:postcode":"1060",
    "sg:province":"Bruxelles-Capitale",
    "wof:name":"Dexia",
    "wof:placetype":"venue"
},
  "geometry": {"coordinates":[4.3455719948,50.8266448975],"type":"Point"}
}