{
  "type": "Feature",
  "properties": {
    "addr:full":"Kerkplein 3 Asse Vlaams-Brabant 1730",
    "addr:housenumber":"3",
    "addr:postcode":"1730",
    "addr:street":"Kerkplein",
    "iso:country":"BE",
    "sg:address":"Kerkplein 3",
    "sg:city":"Asse",
    "sg:classifiers":[
        {
            "category":"Bars & Pubs",
            "type":"Food & Drink"
        }
    ],
    "sg:phone":"+32 2 453 00 06",
    "sg:postcode":"1730",
    "sg:province":"Vlaams-Brabant",
    "wof:name":"Kerkuil (de)",
    "wof:placetype":"venue"
},
  "geometry": {"coordinates":[4.1955962181,50.9106369019],"type":"Point"}
}