{
  "type": "Feature",
  "properties": {
    "addr:full":"Rue Des Chinels 10b401 Ottignies-louvain-la-neuve Brabant Wallon 1348",
    "addr:housenumber":"10b401",
    "addr:postcode":"1348",
    "addr:street":"Rue Des Chinels",
    "iso:country":"BE",
    "sg:address":"Rue Des Chinels 10b401",
    "sg:city":"Ottignies-louvain-la-neuve",
    "sg:orig_category":"Artsen and specialisten",
    "sg:phone":"+32 10 45 77 33",
    "sg:postcode":"1348",
    "sg:province":"Brabant Wallon",
    "wof:name":"Benoit Symens",
    "wof:placetype":"venue"
},
  "geometry": {"coordinates":[4.6055150032,50.6708564758],"type":"Point"}
}