{
  "type": "Feature",
  "properties": {
    "addr:full":"Rue D'hyon 9 Mons (mesvin) Hainaut 7022",
    "addr:housenumber":"9",
    "addr:postcode":"7022",
    "addr:street":"Rue D'Hyon",
    "iso:country":"BE",
    "sg:address":"Rue D'hyon 9",
    "sg:city":"Mons (mesvin)",
    "sg:classifiers":[
        {
            "category":"Health Services",
            "subcategory":"Health Practitioner",
            "type":"Services"
        }
    ],
    "sg:phone":"+32 65 35 48 41",
    "sg:postcode":"7022",
    "sg:province":"Hainaut",
    "sg:tags":[
        "psychologist"
    ],
    "wof:name":"Dieu M-cl",
    "wof:placetype":"venue"
},
  "geometry": {"coordinates":[3.9610059261,50.4295692444],"type":"Point"}
}