{
  "type": "Feature",
  "properties": {
    "iso:country":"BE",
    "sg:address":"Pijphoekstraat 10 B",
    "sg:city":"Gent",
    "sg:orig_category":"Alimentation sp\u00e9cialis\u00e9e",
    "sg:phone":"+32 9 370 87 89",
    "sg:postcode":"9041",
    "sg:province":"Oost-Vlaanderen",
    "wof:name":"De Muizenval",
    "wof:placetype":"venue"
},
  "geometry": {"coordinates":[3.7659420967,51.1010665894],"type":"Point"}
}