{
  "type": "Feature",
  "properties": {
    "addr:full":"Amersveldestraat 60 Hooglede West-Vlaanderen 8830",
    "addr:housenumber":"60",
    "addr:postcode":"8830",
    "addr:street":"Amersveldestraat",
    "iso:country":"BE",
    "sg:address":"Amersveldestraat 60",
    "sg:city":"Hooglede",
    "sg:orig_category":"Producteurs de l\u00e9gumes",
    "sg:phone":"+32 51 70 16 64",
    "sg:postcode":"8830",
    "sg:province":"West-Vlaanderen",
    "wof:name":"Etienne Vandermarcke",
    "wof:placetype":"venue"
},
  "geometry": {"coordinates":[3.0544600487,51.0003204346],"type":"Point"}
}