{
  "type": "Feature",
  "properties": {
    "iso:country":"BE",
    "sg:address":"Laar 68",
    "sg:city":"Geel",
    "sg:orig_category":"HUISBRANDOLIE Loodgieterij, verwarming and sanitaire installaties",
    "sg:phone":"+32 14 59 08 20",
    "sg:postcode":"2440",
    "sg:province":"Antwerpen",
    "wof:name":"Caeyers Raf",
    "wof:placetype":"venue"
},
  "geometry": {"coordinates":[5.00477314,51.1586875916],"type":"Point"}
}