{
  "type": "Feature",
  "properties": {
    "addr:full":"Rue Emile-collard 20 Onhaye Namur 5520",
    "addr:housenumber":"20",
    "addr:postcode":"5520",
    "addr:street":"Rue Emile-Collard",
    "iso:country":"BE",
    "sg:address":"Rue Emile-collard 20",
    "sg:city":"Onhaye",
    "sg:orig_category":"Herstellingen and onderhoud van auto's",
    "sg:phone":"+32 82 68 92 88",
    "sg:postcode":"5520",
    "sg:province":"Namur",
    "wof:name":"Sport Line Cars",
    "wof:placetype":"venue"
},
  "geometry": {"coordinates":[4.8398251534,50.2400093079],"type":"Point"}
}