{
  "type": "Feature",
  "properties": {
    "addr:full":"Oudegemse Baan 66 Dendermonde Oost-Vlaanderen 9200",
    "addr:housenumber":"66",
    "addr:postcode":"9200",
    "addr:street":"Oudegemse Baan;Oost-Vlaanderen",
    "iso:country":"BE",
    "sg:address":"Oudegemse Baan 66",
    "sg:city":"Dendermonde",
    "sg:orig_category":"Pharmaciens",
    "sg:phone":"+32 52 21 23 33",
    "sg:postcode":"9200",
    "sg:province":"Oost-Vlaanderen",
    "wof:name":"Apotheek Vandewalle",
    "wof:placetype":"venue"
},
  "geometry": {"coordinates":[4.0983099937,51.0315208435],"type":"Point"}
}