{
  "type": "Feature",
  "properties": {
    "iso:country":"BE",
    "sg:address":"Nieuwstraat 25",
    "sg:city":"Geel",
    "sg:orig_category":"Eclairage et \u00e9quipements du foyer. Souvenirs and objets artisanaux. Jeux and jouets",
    "sg:phone":"+32 14 58 13 56",
    "sg:postcode":"2440",
    "sg:province":"Antwerpen",
    "wof:name":"Blokker",
    "wof:placetype":"venue"
},
  "geometry": {"coordinates":[4.9923849106,51.1627235413],"type":"Point"}
}