{
  "type": "Feature",
  "properties": {
    "addr:full":"Rue De La Paille 9 Bruxelles Bruxelles-Capitale 1000",
    "addr:housenumber":"9",
    "addr:postcode":"1000",
    "addr:street":"Rue De La Paille",
    "iso:country":"BE",
    "sg:address":"Rue De La Paille 9",
    "sg:city":"Bruxelles",
    "sg:classifiers":[
        {
            "category":"Shopping",
            "subcategory":"Hobbies, Toys, & Games",
            "type":"Retail Goods"
        }
    ],
    "sg:phone":"+32 2 511 35 80",
    "sg:postcode":"1000",
    "sg:province":"Bruxelles-Capitale",
    "sg:tags":[
        "product",
        "miscellaneous",
        "entertainment"
    ],
    "wof:name":"Crearte Sprl",
    "wof:placetype":"venue"
},
  "geometry": {"coordinates":[4.3545498848,50.8420906067],"type":"Point"}
}