{
  "type": "Feature",
  "properties": {
    "addr:full":"Moeskroenstraat 132 Menen West-Vlaanderen 8930",
    "addr:housenumber":"132",
    "addr:postcode":"8930",
    "addr:street":"Moeskroenstraat",
    "iso:country":"BE",
    "sg:address":"Moeskroenstraat 132",
    "sg:city":"Menen",
    "sg:classifiers":[
        {
            "category":"Shopping",
            "subcategory":"Bicycles & Sporting Goods",
            "type":"Retail Goods"
        }
    ],
    "sg:phone":"+32 56 51 78 53",
    "sg:postcode":"8930",
    "sg:province":"West-Vlaanderen",
    "sg:tags":[
        "article",
        "de",
        "sport",
        "camping"
    ],
    "wof:name":"Hengelsport Pasius",
    "wof:placetype":"venue"
},
  "geometry": {"coordinates":[3.132463932,50.7875366211],"type":"Point"}
}