{
  "type": "Feature",
  "properties": {
    "addr:full":"Boulevard Des Arbal\u00e9triers 104 Nivelles Brabant Wallon 1400",
    "addr:housenumber":"104",
    "addr:postcode":"1400",
    "addr:street":"Boulevard Des Arbale\u0301Triers",
    "iso:country":"BE",
    "sg:address":"Boulevard Des Arbal\u00e9triers 104",
    "sg:city":"Nivelles",
    "sg:classifiers":[
        {
            "category":"Professional",
            "subcategory":"Management & Consulting",
            "type":"Services"
        }
    ],
    "sg:phone":"+32 67 22 17 21",
    "sg:postcode":"1400",
    "sg:province":"Brabant Wallon",
    "sg:tags":[
        "marketing",
        "-",
        "consultant"
    ],
    "wof:name":"Bertholet Consulting Sprl",
    "wof:placetype":"venue"
},
  "geometry": {"coordinates":[4.3219380379,50.5991973877],"type":"Point"}
}