{
  "type": "Feature",
  "properties": {
    "addr:full":"Bruidsstraat 14 Brussel/bruxelles Bruxelles-Capitale 1000",
    "addr:housenumber":"14",
    "addr:postcode":"1000",
    "addr:street":"Bruidsstraat;/",
    "iso:country":"BE",
    "sg:address":"Bruidsstraat 14",
    "sg:city":"Brussel/bruxelles",
    "sg:orig_category":"Beheer onroerend goed",
    "sg:phone":"+32 2 220 14 97",
    "sg:postcode":"1000",
    "sg:province":"Bruxelles-Capitale",
    "wof:name":"Metropolitan Buildings",
    "wof:placetype":"venue"
},
  "geometry": {"coordinates":[4.3543400764,50.8534927368],"type":"Point"}
}