{
  "type": "Feature",
  "properties": {
    "addr:full":"Chaamseweg 34ba Hoogstraten Antwerpen 2328",
    "addr:housenumber":"34ba",
    "addr:postcode":"2328",
    "addr:street":"Chaamseweg",
    "iso:country":"BE",
    "sg:address":"Chaamseweg 34ba",
    "sg:city":"Hoogstraten",
    "sg:orig_category":"Banques and organismes de cr\u00e9dit",
    "sg:phone":"+32 3 315 70 09",
    "sg:postcode":"2328",
    "sg:province":"Antwerpen",
    "wof:name":"Landbouwkrediet",
    "wof:placetype":"venue"
},
  "geometry": {"coordinates":[4.8041949272,51.4741134644],"type":"Point"}
}