{
  "type": "Feature",
  "properties": {
    "addr:full":"Muizenvenstraat 5-7 Turnhout Antwerpen 2300",
    "addr:housenumber":"5-7",
    "addr:postcode":"2300",
    "addr:street":"Muizenvenstraat",
    "iso:country":"BE",
    "sg:address":"Muizenvenstraat 5-7",
    "sg:city":"Turnhout",
    "sg:orig_category":"Pre-press",
    "sg:phone":"+32 14 42 27 26",
    "sg:postcode":"2300",
    "sg:province":"Antwerpen",
    "wof:name":"Matthys-beccu Bvba",
    "wof:placetype":"venue"
},
  "geometry": {"coordinates":[4.9220671654,51.3063735962],"type":"Point"}
}