{
  "type": "Feature",
  "properties": {
    "addr:full":"Ruggekouterweg 35 Avelgem West-Vlaanderen 8580",
    "addr:housenumber":"35",
    "addr:postcode":"8580",
    "addr:street":"Ruggekouterweg",
    "iso:country":"BE",
    "sg:address":"Ruggekouterweg 35",
    "sg:city":"Avelgem",
    "sg:classifiers":[
        {
            "category":"Home & Garden",
            "subcategory":"Hardware",
            "type":"Retail Goods"
        }
    ],
    "sg:phone":"+32 56 64 98 44",
    "sg:postcode":"8580",
    "sg:province":"West-Vlaanderen",
    "sg:tags":[
        "battery",
        "dry"
    ],
    "wof:name":"Deknudt Bvba",
    "wof:placetype":"venue"
},
  "geometry": {"coordinates":[3.4620289803,50.7774658203],"type":"Point"}
}