{
  "type": "Feature",
  "properties": {
    "iso:country":"BE",
    "sg:address":"Rue Du Village 92",
    "sg:city":"Eghez\u00e9e (noville-sur-m\u00e9haigne)",
    "sg:classifiers":[
        {
            "category":"Personal",
            "subcategory":"Beauty Salon",
            "type":"Services"
        }
    ],
    "sg:phone":"+32 81 81 29 12",
    "sg:postcode":"5310",
    "sg:province":"Namur",
    "sg:tags":[
        "lady",
        "-",
        "hairdressing"
    ],
    "wof:name":"Captif Coiffure",
    "wof:placetype":"venue"
},
  "geometry": {"coordinates":[4.8813347816,50.6083221436],"type":"Point"}
}