{
  "type": "Feature",
  "properties": {
    "iso:country":"BE",
    "sg:address":"Rue Charles Bormans 55",
    "sg:city":"Wanze (bas-oha)",
    "sg:classifiers":[
        {
            "category":"Health Services",
            "subcategory":"Health Practitioner",
            "type":"Services"
        }
    ],
    "sg:phone":"+32 85 23 17 78",
    "sg:postcode":"4520",
    "sg:province":"Li\u00e8ge",
    "sg:tags":[
        "physiotherapist"
    ],
    "wof:name":"Thirion J-m",
    "wof:placetype":"venue"
},
  "geometry": {"coordinates":[5.1775798798,50.5246658325],"type":"Point"}
}