{
  "type": "Feature",
  "properties": {
    "iso:country":"BE",
    "sg:address":"Sint-stevensstraat 33",
    "sg:city":"Sint-pieters-leeuw",
    "sg:orig_category":"Kapsalons",
    "sg:phone":"+32 2 377 90 80",
    "sg:postcode":"1600",
    "sg:province":"Vlaams-Brabant",
    "wof:name":"Jean Devits",
    "wof:placetype":"venue"
},
  "geometry": {"coordinates":[4.2870430946,50.8047866821],"type":"Point"}
}