{
  "type": "Feature",
  "properties": {
    "iso:country":"BE",
    "sg:address":"Quellinstraat 42",
    "sg:city":"Antwerpen",
    "sg:classifiers":[
        {
            "category":"Utilities",
            "subcategory":"Water",
            "type":"Services"
        }
    ],
    "sg:phone":"+32 3 201 51 10",
    "sg:postcode":"2018",
    "sg:province":"Antwerpen",
    "sg:tags":[
        "mounting",
        "tyre",
        "equipment"
    ],
    "wof:name":"D.q.n. - Du Quesne B.v.b.a.",
    "wof:placetype":"venue"
},
  "geometry": {"coordinates":[4.4157891273,51.2158279419],"type":"Point"}
}