{
  "type": "Feature",
  "properties": {
    "iso:country":"BE",
    "sg:address":"Perenlaan 11",
    "sg:city":"Zandhoven",
    "sg:orig_category":"Jardinage",
    "sg:phone":"+32 3 484 55 46",
    "sg:postcode":"2240",
    "sg:province":"Antwerpen",
    "wof:name":"Vanleke",
    "wof:placetype":"venue"
},
  "geometry": {"coordinates":[4.6502699852,51.2093238831],"type":"Point"}
}