{
  "type": "Feature",
  "properties": {
    "addr:full":"Rue C\u00e9sar Franck 44 Plombi\u00e8res (gemmenich) Li\u00e8ge 4851",
    "addr:housenumber":"44",
    "addr:postcode":"4851",
    "addr:street":"Rue Ce\u0301Sar Franck",
    "iso:country":"BE",
    "sg:address":"Rue C\u00e9sar Franck 44",
    "sg:city":"Plombi\u00e8res (gemmenich)",
    "sg:classifiers":[
        {
            "category":"Insurance",
            "subcategory":"Insurance Agent",
            "type":"Services"
        }
    ],
    "sg:phone":"+32 87 78 65 50",
    "sg:postcode":"4851",
    "sg:province":"Li\u00e8ge",
    "sg:tags":[
        "broker"
    ],
    "wof:name":"Bureau Capocci Sa",
    "wof:placetype":"venue"
},
  "geometry": {"coordinates":[5.9946041107,50.7455978394],"type":"Point"}
}