{
  "type": "Feature",
  "properties": {
    "addr:full":"Eggebekstraat 8 Peer (wijchmaal) Limburg 3990",
    "addr:housenumber":"8",
    "addr:postcode":"3990",
    "addr:street":"Eggebekstraat",
    "iso:country":"BE",
    "sg:address":"Eggebekstraat 8",
    "sg:city":"Peer (wijchmaal)",
    "sg:classifiers":[
        {
            "category":"Professional",
            "subcategory":"Printing & Photocopies",
            "type":"Services"
        }
    ],
    "sg:phone":"+32 11 63 71 62",
    "sg:postcode":"3990",
    "sg:province":"Limburg",
    "sg:tags":[
        "silkscreen",
        "-"
    ],
    "wof:name":"Cribadruk",
    "wof:placetype":"venue"
},
  "geometry": {"coordinates":[5.418525219,51.1285362244],"type":"Point"}
}