{
  "type": "Feature",
  "properties": {
    "addr:full":"Bellegemsestraat 13 Kortrijk (bellegem) West-Vlaanderen 8510",
    "addr:housenumber":"13",
    "addr:postcode":"8510",
    "addr:street":"Bellegemsestraat",
    "iso:country":"BE",
    "sg:address":"Bellegemsestraat 13",
    "sg:city":"Kortrijk (bellegem)",
    "sg:classifiers":[
        {
            "category":"Banks & Credit Unions",
            "subcategory":"Investment Brokerage",
            "type":"Services"
        }
    ],
    "sg:phone":"+32 497 99 10 90",
    "sg:postcode":"8510",
    "sg:province":"West-Vlaanderen",
    "sg:tags":[
        "ladies'",
        "tailor",
        "tailoresses",
        "-",
        "clothing"
    ],
    "wof:name":"Braekeveld V",
    "wof:placetype":"venue"
},
  "geometry": {"coordinates":[3.2813360691,50.7778358459],"type":"Point"}
}