{
  "type": "Feature",
  "properties": {
    "addr:full":"Maastrichtersteenweg 149 Hasselt Limburg 3500",
    "addr:housenumber":"149",
    "addr:postcode":"3500",
    "addr:street":"Maastrichtersteenweg",
    "iso:country":"BE",
    "sg:address":"Maastrichtersteenweg 149",
    "sg:city":"Hasselt",
    "sg:orig_category":"Solariums",
    "sg:phone":"+32 11 22 50 24",
    "sg:postcode":"3500",
    "sg:province":"Limburg",
    "wof:name":"De Kleurenkapper",
    "wof:placetype":"venue"
},
  "geometry": {"coordinates":[5.3533229828,50.9287872314],"type":"Point"}
}