{
  "type": "Feature",
  "properties": {
    "addr:full":"Sprookjespad 1 Oostende West-Vlaanderen 8400",
    "addr:housenumber":"1",
    "addr:postcode":"8400",
    "addr:street":"Sprookjespad",
    "iso:country":"BE",
    "sg:address":"Sprookjespad 1",
    "sg:city":"Oostende",
    "sg:orig_category":"Activit\u00e9s diverses d'imprimerie",
    "sg:phone":"+32 59 50 41 97",
    "sg:postcode":"8400",
    "sg:province":"West-Vlaanderen",
    "wof:name":"Bureau Sloy Art Designs",
    "wof:placetype":"venue"
},
  "geometry": {"coordinates":[2.9126999378,51.2312583923],"type":"Point"}
}