{
  "type": "Feature",
  "properties": {
    "iso:country":"BE",
    "sg:address":"Boerenkrijglaan 14a",
    "sg:city":"Olen",
    "sg:classifiers":[
        {
            "category":"Manufacturing",
            "subcategory":"Metals",
            "type":"Manufacturing & Wholesale Goods"
        }
    ],
    "sg:phone":"+32 14 26 58 11",
    "sg:postcode":"2250",
    "sg:province":"Antwerpen",
    "sg:tags":[
        "blanking",
        "dy"
    ],
    "wof:name":"Centra-tech B.v.b.a.",
    "wof:placetype":"venue"
},
  "geometry": {"coordinates":[4.8633179665,51.1418876648],"type":"Point"}
}