{
  "type": "Feature",
  "properties": {
    "addr:full":"Sint-goriksplein 1 Haaltert Oost-Vlaanderen 9450",
    "addr:housenumber":"1",
    "addr:postcode":"9450",
    "addr:street":"Sint-Goriksplein",
    "iso:country":"BE",
    "sg:address":"Sint-goriksplein 1",
    "sg:city":"Haaltert",
    "sg:orig_category":"R\u00e9parations de chaussures and articles en cuir",
    "sg:phone":"+32 53 83 32 93",
    "sg:postcode":"9450",
    "sg:province":"Oost-Vlaanderen",
    "wof:name":"Schoenmakerij Andy",
    "wof:placetype":"venue"
},
  "geometry": {"coordinates":[4.0057902336,50.9014015198],"type":"Point"}
}