{
  "type": "Feature",
  "properties": {
    "iso:country":"BE",
    "sg:address":"Rue Paul Pastur 35",
    "sg:city":"Charleroi (ransart)",
    "sg:classifiers":[
        {
            "category":"Real Estate",
            "subcategory":"Real Estate Services",
            "type":"Services"
        }
    ],
    "sg:phone":"+32 71 35 82 83",
    "sg:postcode":"6043",
    "sg:province":"Hainaut",
    "wof:name":"Ludo Constructions Sprl",
    "wof:placetype":"venue"
},
  "geometry": {"coordinates":[4.4174618721,50.4417190552],"type":"Point"}
}