{
  "type": "Feature",
  "properties": {
    "addr:full":"Rue Charles-magnette 15 Li\u00c8ge Li\u00e8ge 4000",
    "addr:housenumber":"15",
    "addr:postcode":"4000",
    "addr:street":"Rue Charles-Magnette",
    "iso:country":"BE",
    "sg:address":"Rue Charles-magnette 15",
    "sg:city":"Li\u00c8ge",
    "sg:orig_category":"V\u00eatements pour Hommes",
    "sg:phone":"+32 4 223 31 40",
    "sg:postcode":"4000",
    "sg:province":"Li\u00e8ge",
    "wof:name":"Ars\u00c8ne Pirotte",
    "wof:placetype":"venue"
},
  "geometry": {"coordinates":[5.573015213,50.6406326294],"type":"Point"}
}