{
  "type": "Feature",
  "properties": {
    "iso:country":"BE",
    "sg:address":"Weg Naar As 121a Box 10",
    "sg:city":"Genk",
    "sg:classifiers":[
        {
            "category":"Education",
            "subcategory":"Library",
            "type":"Public Place"
        }
    ],
    "sg:phone":"+32 475 87 39 89",
    "sg:postcode":"3600",
    "sg:province":"Limburg",
    "sg:tags":[
        "equipment",
        "-"
    ],
    "wof:name":"Procos - Bomefa Bvba",
    "wof:placetype":"venue"
},
  "geometry": {"coordinates":[5.5123472214,50.9704780579],"type":"Point"}
}