{
  "type": "Feature",
  "properties": {
    "iso:country":"BE",
    "sg:address":"Koning Albertlaan 46b2",
    "sg:city":"Maaseik",
    "sg:classifiers":[
        {
            "category":"Personal",
            "subcategory":"Beauty Salon",
            "type":"Services"
        }
    ],
    "sg:phone":"+32 89 56 15 36",
    "sg:postcode":"3680",
    "sg:province":"Limburg",
    "sg:tags":[
        "de",
        "coiffure"
    ],
    "wof:name":"Mario Luyten",
    "wof:placetype":"venue"
},
  "geometry": {"coordinates":[5.7831921577,51.0970916748],"type":"Point"}
}