{
  "type": "Feature",
  "properties": {
    "addr:full":"Antoon Vander Plaetsestraat 8 Kortrijk West-Vlaanderen 8500",
    "addr:housenumber":"8",
    "addr:postcode":"8500",
    "addr:street":"Antoon Vander Plaetsestraat",
    "iso:country":"BE",
    "sg:address":"Antoon Vander Plaetsestraat 8",
    "sg:city":"Kortrijk",
    "sg:classifiers":[
        {
            "category":"Health Services",
            "subcategory":"Health Practitioner",
            "type":"Services"
        }
    ],
    "sg:phone":"+32 56 20 23 10",
    "sg:postcode":"8500",
    "sg:province":"West-Vlaanderen",
    "sg:tags":[
        "physiotherapist"
    ],
    "wof:name":"Demeulenaere M-h Mevr",
    "wof:placetype":"venue"
},
  "geometry": {"coordinates":[3.2674450874,50.8162498474],"type":"Point"}
}