{
  "type": "Feature",
  "properties": {
    "addr:full":"Norulle 7 Tintigny Luxembourg 6730",
    "addr:housenumber":"7",
    "addr:postcode":"6730",
    "addr:street":"Norulle",
    "iso:country":"BE",
    "sg:address":"Norulle 7",
    "sg:city":"Tintigny",
    "sg:classifiers":[
        {
            "category":"Cafe",
            "type":"Food & Drink"
        }
    ],
    "sg:phone":"+32 63 44 42 72",
    "sg:postcode":"6730",
    "sg:province":"Luxembourg",
    "sg:tags":[
        "caf\u00e9s"
    ],
    "wof:name":"Patrick Wala",
    "wof:placetype":"venue"
},
  "geometry": {"coordinates":[5.521176815,49.6835212708],"type":"Point"}
}