{
  "type": "Feature",
  "properties": {
    "iso:country":"BE",
    "sg:address":"Boonakker 41",
    "sg:city":"Temse",
    "sg:orig_category":"Kapsalons",
    "sg:phone":"+32 3 771 48 83",
    "sg:postcode":"9140",
    "sg:province":"Oost-Vlaanderen",
    "wof:name":"Coiffure Arlette",
    "wof:placetype":"venue"
},
  "geometry": {"coordinates":[4.2012600899,51.1332130432],"type":"Point"}
}