{
  "type": "Feature",
  "properties": {
    "addr:full":"Guido Gezellelaan 31 Duffel Antwerpen 2570",
    "addr:housenumber":"31",
    "addr:postcode":"2570",
    "addr:street":"Guido Gezellelaan",
    "iso:country":"BE",
    "sg:address":"Guido Gezellelaan 31",
    "sg:city":"Duffel",
    "sg:classifiers":[
        {
            "category":"Arena",
            "subcategory":"Sports Club",
            "type":"Entertainment"
        }
    ],
    "sg:phone":"+32 15 31 94 34",
    "sg:postcode":"2570",
    "sg:province":"Antwerpen",
    "wof:name":"Amor Cordis Wet Wheels",
    "wof:placetype":"venue"
},
  "geometry": {"coordinates":[4.5051569939,51.1040306091],"type":"Point"}
}