{
  "type": "Feature",
  "properties": {
    "iso:country":"BE",
    "sg:address":"Kerkstraat 21 Box 1",
    "sg:city":"Merksplas",
    "sg:classifiers":[
        {
            "category":"Personal",
            "subcategory":"Beauty Salon",
            "type":"Services"
        }
    ],
    "sg:phone":"+32 14 63 31 99",
    "sg:postcode":"2330",
    "sg:province":"Antwerpen",
    "sg:tags":[
        "lady",
        "-",
        "hairdressing"
    ],
    "wof:name":"Krols K",
    "wof:placetype":"venue"
},
  "geometry": {"coordinates":[4.8632240295,51.3595542908],"type":"Point"}
}