{
  "type": "Feature",
  "properties": {
    "addr:full":"Poederleeseweg 25 Lille Antwerpen 2275",
    "addr:housenumber":"25",
    "addr:postcode":"2275",
    "addr:street":"Poederleeseweg",
    "iso:country":"BE",
    "sg:address":"Poederleeseweg 25",
    "sg:city":"Lille",
    "sg:orig_category":"Warenhuizen",
    "sg:phone":"+32 14 88 01 38",
    "sg:postcode":"2275",
    "sg:province":"Antwerpen",
    "wof:name":"Cash Fresh",
    "wof:placetype":"venue"
},
  "geometry": {"coordinates":[4.825961113,51.2370605469],"type":"Point"}
}