{
  "type": "Feature",
  "properties": {
    "addr:full":"Mechelbaan 77 Lier (koningshooikt) Antwerpen 2500",
    "addr:housenumber":"77",
    "addr:postcode":"2500",
    "addr:street":"Mechelbaan",
    "iso:country":"BE",
    "sg:address":"Mechelbaan 77",
    "sg:city":"Lier (koningshooikt)",
    "sg:classifiers":[
        {
            "category":"Shopping",
            "subcategory":"Clothing, Apparel, & Fashions",
            "type":"Retail Goods"
        }
    ],
    "sg:phone":"+32 3 482 11 01",
    "sg:postcode":"2500",
    "sg:province":"Antwerpen",
    "sg:tags":[
        "lady",
        "clothing",
        "-"
    ],
    "wof:name":"E.e. Basics",
    "wof:placetype":"venue"
},
  "geometry": {"coordinates":[4.6092638969,51.0905227661],"type":"Point"}
}