{
  "type": "Feature",
  "properties": {
    "iso:country":"BE",
    "sg:address":"Ophovenstraat 13",
    "sg:city":"Meeuwen-gruitrode",
    "sg:orig_category":"Installatie van houten of kunststof schrijnwerk",
    "sg:phone":"+32 89 85 61 28",
    "sg:postcode":"3670",
    "sg:province":"Limburg",
    "wof:name":"Stienaers J.-stienaers M.",
    "wof:placetype":"venue"
},
  "geometry": {"coordinates":[5.5348110199,51.0683021545],"type":"Point"}
}