{
  "type": "Feature",
  "properties": {
    "addr:full":"Chauss\u00e9e De Li\u00e8ge 290 Gr\u00e2ce-hollogne (gr\u00e2ce-berleur) Li\u00e8ge 4460",
    "addr:housenumber":"290",
    "addr:postcode":"4460",
    "addr:street":"Chausse\u0301E De Lie\u0300Ge;Gra\u0302Ce-Berleur",
    "iso:country":"BE",
    "sg:address":"Chauss\u00e9e De Li\u00e8ge 290",
    "sg:city":"Gr\u00e2ce-hollogne (gr\u00e2ce-berleur)",
    "sg:classifiers":[
        {
            "category":"Cafe",
            "type":"Food & Drink"
        }
    ],
    "sg:phone":"+32 4 239 11 40",
    "sg:postcode":"4460",
    "sg:province":"Li\u00e8ge",
    "sg:tags":[
        "snack-bars"
    ],
    "wof:name":"Valentine",
    "wof:placetype":"venue"
},
  "geometry": {"coordinates":[5.4879860878,50.6470375061],"type":"Point"}
}