{
  "type": "Feature",
  "properties": {
    "addr:full":"Kazernelaan 108 Box 1 Houthalen-helchteren (helchteren) Limburg 3530",
    "addr:housenumber":"108;1",
    "addr:postcode":"3530",
    "addr:street":"Kazernelaan;Box",
    "iso:country":"BE",
    "sg:address":"Kazernelaan 108 Box 1",
    "sg:city":"Houthalen-helchteren (helchteren)",
    "sg:classifiers":[
        {
            "category":"Bars & Pubs",
            "type":"Food & Drink"
        }
    ],
    "sg:phone":"+32 11 81 24 60",
    "sg:postcode":"3530",
    "sg:province":"Limburg",
    "wof:name":"Paradiso Club",
    "wof:placetype":"venue"
},
  "geometry": {"coordinates":[5.3719201088,51.0310020447],"type":"Point"}
}