{
  "type": "Feature",
  "properties": {
    "addr:full":"Pollepelstraat 4 Maldegem Oost-Vlaanderen 9990",
    "addr:housenumber":"4",
    "addr:postcode":"9990",
    "addr:street":"Pollepelstraat",
    "iso:country":"BE",
    "sg:address":"Pollepelstraat 4",
    "sg:city":"Maldegem",
    "sg:orig_category":"Rundveehouders",
    "sg:phone":"+32 50 71 16 28",
    "sg:postcode":"9990",
    "sg:province":"Oost-Vlaanderen",
    "wof:name":"Jackie Van Kerschaver",
    "wof:placetype":"venue"
},
  "geometry": {"coordinates":[3.4220039845,51.1996307373],"type":"Point"}
}