{
  "type": "Feature",
  "properties": {
    "iso:country":"BE",
    "sg:address":"Boulevard Sainctelette 20",
    "sg:city":"Mons",
    "sg:orig_category":"M\u00e9decins and sp\u00e9cialistes",
    "sg:phone":"+32 65 84 45 56",
    "sg:postcode":"7000",
    "sg:province":"Hainaut",
    "wof:name":"Laurent Chapelle",
    "wof:placetype":"venue"
},
  "geometry": {"coordinates":[3.9464359283,50.4468231201],"type":"Point"}
}