{
  "type": "Feature",
  "properties": {
    "addr:full":"Rue Du Soleil 170 Ronse/renaix Oost-Vlaanderen 9600",
    "addr:housenumber":"170",
    "addr:postcode":"9600",
    "addr:street":"Rue Du Soleil",
    "iso:country":"BE",
    "sg:address":"Rue Du Soleil 170",
    "sg:city":"Ronse/renaix",
    "sg:orig_category":"M\u00e9decins and sp\u00e9cialistes",
    "sg:phone":"+32 55 21 22 15",
    "sg:postcode":"9600",
    "sg:province":"Oost-Vlaanderen",
    "wof:name":"Andr\u00c9 Lesenne",
    "wof:placetype":"venue"
},
  "geometry": {"coordinates":[3.5865459442,50.7489776611],"type":"Point"}
}