{
  "type": "Feature",
  "properties": {
    "iso:country":"BE",
    "sg:address":"Boulevard Emile De Laveleye 44",
    "sg:city":"Li\u00e8ge 1 (li\u00e8ge 2)",
    "sg:classifiers":[
        {
            "category":"Health Services",
            "subcategory":"Dentist",
            "type":"Services"
        }
    ],
    "sg:phone":"+32 4 343 44 33",
    "sg:postcode":"4020",
    "sg:province":"Li\u00e8ge",
    "wof:name":"Lambotte P",
    "wof:placetype":"venue"
},
  "geometry": {"coordinates":[5.5872421265,50.6238288879],"type":"Point"}
}