{
  "type": "Feature",
  "properties": {
    "iso:country":"BE",
    "sg:address":"Molenstraat 12",
    "sg:city":"Puurs",
    "sg:orig_category":"Binnenhuisarchitecten Immobili\u00ebnkantoren Projectontwikkelaars Woningbouw",
    "sg:phone":"+32 3 889 83 89",
    "sg:postcode":"2870",
    "sg:province":"Antwerpen",
    "wof:name":"Concept I",
    "wof:placetype":"venue"
},
  "geometry": {"coordinates":[4.2886891365,51.0736083984],"type":"Point"}
}