{
  "type": "Feature",
  "properties": {
    "addr:full":"Vandeveldestraat 114 Brussel-schaarbeek Bruxelles-Capitale 1030",
    "addr:housenumber":"114",
    "addr:postcode":"1030",
    "addr:street":"Vandeveldestraat",
    "iso:country":"BE",
    "sg:address":"Vandeveldestraat 114",
    "sg:city":"Brussel-schaarbeek",
    "sg:classifiers":[
        {
            "category":"Autos & Motor Vehicles",
            "subcategory":"Automobile Sales",
            "type":"Retail Goods"
        }
    ],
    "sg:phone":"+32 2 216 49 36",
    "sg:postcode":"1030",
    "sg:province":"Bruxelles-Capitale",
    "sg:tags":[
        "mazda"
    ],
    "wof:name":"Garage Saint-michel B.v.b.a.",
    "wof:placetype":"venue"
},
  "geometry": {"coordinates":[4.3917441368,50.8720169067],"type":"Point"}
}