{
  "type": "Feature",
  "properties": {
    "addr:full":"Fabriekstraat 1 Tessenderlo Limburg 3980",
    "addr:housenumber":"1",
    "addr:postcode":"3980",
    "addr:street":"Fabriekstraat",
    "iso:country":"BE",
    "sg:address":"Fabriekstraat 1",
    "sg:city":"Tessenderlo",
    "sg:orig_category":"Bouwmaterialen Gh Loodgieterij and centrale verwarming Gh Non-foodwinkels",
    "sg:phone":"+32 13 66 18 47",
    "sg:postcode":"3980",
    "sg:province":"Limburg",
    "wof:name":"Tankshop Verbeeck Jan",
    "wof:placetype":"venue"
},
  "geometry": {"coordinates":[5.1031579971,51.0655250549],"type":"Point"}
}