{
  "type": "Feature",
  "properties": {
    "iso:country":"BE",
    "sg:address":"Rue Lieutenant Cotton 27",
    "sg:city":"Flobecq",
    "sg:classifiers":[
        {
            "category":"Shopping",
            "subcategory":"Discount & Variety Stores",
            "type":"Retail Goods"
        }
    ],
    "sg:phone":"+32 68 44 70 35",
    "sg:postcode":"7880",
    "sg:province":"Hainaut",
    "sg:tags":[
        "shop",
        "clearers",
        "curiosity",
        "furniture"
    ],
    "wof:name":"Espace Brocante",
    "wof:placetype":"venue"
},
  "geometry": {"coordinates":[3.7405350208,50.7359046936],"type":"Point"}
}