{
  "type": "Feature",
  "properties": {
    "iso:country":"BE",
    "sg:address":"Rue De La Couturelle 3",
    "sg:city":"Doische",
    "sg:orig_category":"Installation \u00e9lectrique r\u00e9sidentielle",
    "sg:phone":"+32 60 39 95 99",
    "sg:postcode":"5680",
    "sg:province":"Namur",
    "wof:name":"Michel Pirson",
    "wof:placetype":"venue"
},
  "geometry": {"coordinates":[4.6138777733,50.1163101196],"type":"Point"}
}