{
  "type": "Feature",
  "properties": {
    "addr:full":"Epelteer 29 Hoogstraten Antwerpen 2320",
    "addr:housenumber":"29",
    "addr:postcode":"2320",
    "addr:street":"Epelteer",
    "iso:country":"BE",
    "sg:address":"Epelteer 29",
    "sg:city":"Hoogstraten",
    "sg:classifiers":[
        {
            "category":"Professional",
            "subcategory":"Management & Consulting",
            "type":"Services"
        }
    ],
    "sg:phone":"+32 3 314 84 47",
    "sg:postcode":"2320",
    "sg:province":"Antwerpen",
    "sg:tags":[
        "-",
        "processing",
        "data",
        "consultant"
    ],
    "wof:name":"It8",
    "wof:placetype":"venue"
},
  "geometry": {"coordinates":[4.7598280907,51.3917579651],"type":"Point"}
}