{
  "type": "Feature",
  "properties": {
    "addr:full":"Bld Anspach 145 Bruxelles Bruxelles-Capitale 1000",
    "addr:housenumber":"145",
    "addr:postcode":"1000",
    "addr:street":"Bld Anspach",
    "iso:country":"BE",
    "sg:address":"Bld Anspach 145",
    "sg:city":"Bruxelles",
    "sg:orig_category":"Disquaires",
    "sg:phone":"+32 2 513 32 42",
    "sg:postcode":"1000",
    "sg:province":"Bruxelles-Capitale",
    "wof:name":"Club Connection",
    "wof:placetype":"venue"
},
  "geometry": {"coordinates":[4.3472828865,50.846157074],"type":"Point"}
}