{
  "type": "Feature",
  "properties": {
    "iso:country":"BE",
    "sg:address":"Dorp 42",
    "sg:city":"Lille",
    "sg:orig_category":"V\u00eatements pour Dames. V\u00eatements pour Hommes. V\u00eatements sur mesure Fab",
    "sg:phone":"+32 14 88 28 28",
    "sg:postcode":"2275",
    "sg:province":"Antwerpen",
    "wof:name":"Van Peer",
    "wof:placetype":"venue"
},
  "geometry": {"coordinates":[4.8352527618,51.2290916443],"type":"Point"}
}