{
  "type": "Feature",
  "properties": {
    "iso:country":"BE",
    "sg:address":"De Haak 1",
    "sg:city":"Asse",
    "sg:orig_category":"Agences de marketing",
    "sg:phone":"+32 2 467 59 59",
    "sg:postcode":"1731",
    "sg:province":"Vlaams-Brabant",
    "wof:name":"Stichting Marketing",
    "wof:placetype":"venue"
},
  "geometry": {"coordinates":[4.2977781296,50.8801307678],"type":"Point"}
}