{
  "type": "Feature",
  "properties": {
    "addr:full":"Rue De L'enclos 17 Braives (tourinne) Li\u00e8ge 4263",
    "addr:housenumber":"17",
    "addr:postcode":"4263",
    "addr:street":"Rue De L'Enclos;Tourinne",
    "iso:country":"BE",
    "sg:address":"Rue De L'enclos 17",
    "sg:city":"Braives (tourinne)",
    "sg:classifiers":[
        {
            "category":"Manufacturing",
            "subcategory":"Glass & Minerals",
            "type":"Manufacturing & Wholesale Goods"
        }
    ],
    "sg:phone":"+32 475 32 41 82",
    "sg:postcode":"4263",
    "sg:province":"Li\u00e8ge",
    "sg:tags":[
        "stained",
        "glazier",
        "-"
    ],
    "wof:name":"Art Stained Glass-vitraux D'art",
    "wof:placetype":"venue"
},
  "geometry": {"coordinates":[5.1757659912,50.6399536133],"type":"Point"}
}