{
  "type": "Feature",
  "properties": {
    "iso:country":"BE",
    "sg:address":"Rode Kruislaan 54",
    "sg:city":"Bree",
    "sg:orig_category":"Non-Classified Establishments",
    "sg:phone":"+32 89 46 13 32",
    "sg:postcode":"3960",
    "sg:province":"Limburg",
    "wof:name":"Mobital Kantooruitrusting Nv",
    "wof:placetype":"venue"
},
  "geometry": {"coordinates":[5.6057062149,51.1376342773],"type":"Point"}
}