{
  "type": "Feature",
  "properties": {
    "addr:full":"Place Nicola\u00ef 15 Aubel Li\u00e8ge 4880",
    "addr:housenumber":"15",
    "addr:postcode":"4880",
    "addr:street":"Place Nicolai\u0308",
    "iso:country":"BE",
    "sg:address":"Place Nicola\u00ef 15",
    "sg:city":"Aubel",
    "sg:classifiers":[
        {
            "category":"Shopping",
            "subcategory":"Clothing, Apparel, & Fashions",
            "type":"Retail Goods"
        }
    ],
    "sg:phone":"+32 87 68 82 18",
    "sg:postcode":"4880",
    "sg:province":"Li\u00e8ge",
    "sg:tags":[
        "lady",
        "clothing",
        "-"
    ],
    "wof:name":"Joyce Boutique",
    "wof:placetype":"venue"
},
  "geometry": {"coordinates":[5.858232975,50.7054786682],"type":"Point"}
}