{
  "type": "Feature",
  "properties": {
    "addr:full":"Rue Hainchamps 57 Seraing Li\u00e8ge 4100",
    "addr:housenumber":"57",
    "addr:postcode":"4100",
    "addr:street":"Rue Hainchamps",
    "iso:country":"BE",
    "sg:address":"Rue Hainchamps 57",
    "sg:city":"Seraing",
    "sg:classifiers":[
        {
            "category":"Health Services",
            "subcategory":"Health Practitioner",
            "type":"Services"
        }
    ],
    "sg:phone":"+32 4 336 79 69",
    "sg:postcode":"4100",
    "sg:province":"Li\u00e8ge",
    "sg:tags":[
        "physiotherapist"
    ],
    "wof:name":"Palermini Claudia",
    "wof:placetype":"venue"
},
  "geometry": {"coordinates":[5.5089650154,50.6009216309],"type":"Point"}
}