{
  "type": "Feature",
  "properties": {
    "iso:country":"BE",
    "sg:address":"Henri Maubelstraat 59",
    "sg:city":"Vorst/forest",
    "sg:orig_category":"Herstellingen and onderhoud van auto's",
    "sg:phone":"+32 2 344 90 72",
    "sg:postcode":"1190",
    "sg:province":"Bruxelles-Capitale",
    "wof:name":"H. De Troy",
    "wof:placetype":"venue"
},
  "geometry": {"coordinates":[4.3347320557,50.8105010986],"type":"Point"}
}