{
  "type": "Feature",
  "properties": {
    "addr:full":"Gentsestraat 16 Harelbeke West-Vlaanderen 8530",
    "addr:housenumber":"16",
    "addr:postcode":"8530",
    "addr:street":"Gentsestraat",
    "iso:country":"BE",
    "sg:address":"Gentsestraat 16",
    "sg:city":"Harelbeke",
    "sg:orig_category":"Banques and organismes de cr\u00e9dit",
    "sg:phone":"+32 56 71 10 62",
    "sg:postcode":"8530",
    "sg:province":"West-Vlaanderen",
    "wof:name":"Kbc",
    "wof:placetype":"venue"
},
  "geometry": {"coordinates":[3.3132750988,50.8575820923],"type":"Point"}
}