{
  "type": "Feature",
  "properties": {
    "iso:country":"BE",
    "sg:address":"Rue Henri De Saegher 10",
    "sg:city":"Bruxelles (molenbeek-saint-jean)",
    "sg:classifiers":[
        {
            "category":"Banks & Credit Unions",
            "subcategory":"Investment Brokerage",
            "type":"Services"
        }
    ],
    "sg:phone":"+32 2 410 07 70",
    "sg:postcode":"1080",
    "sg:province":"Bruxelles-Capitale",
    "sg:tags":[
        "printing",
        "-"
    ],
    "wof:name":"Pieters",
    "wof:placetype":"venue"
},
  "geometry": {"coordinates":[4.3280849457,50.852596283],"type":"Point"}
}