{
  "type": "Feature",
  "properties": {
    "addr:full":"Watermolenstraat 22 Lede (wanzele) Oost-Vlaanderen 9340",
    "addr:housenumber":"22",
    "addr:postcode":"9340",
    "addr:street":"Watermolenstraat",
    "iso:country":"BE",
    "sg:address":"Watermolenstraat 22",
    "sg:city":"Lede (wanzele)",
    "sg:classifiers":[
        {
            "category":"Insurance",
            "subcategory":"Insurance Agent",
            "type":"Services"
        }
    ],
    "sg:phone":"+32 53 80 12 97",
    "sg:postcode":"9340",
    "sg:province":"Oost-Vlaanderen",
    "sg:tags":[
        "-",
        "representative"
    ],
    "wof:name":"Grepdon Dirk Bvba",
    "wof:placetype":"venue"
},
  "geometry": {"coordinates":[3.9609820843,50.9679832458],"type":"Point"}
}