{
  "type": "Feature",
  "properties": {
    "iso:country":"BE",
    "sg:address":"Heerbaan 8",
    "sg:city":"Zoutleeuw",
    "sg:orig_category":"Installation de menuiserie m\u00e9tallique. Travaux de finition and nettoyage de b\u00e2timents. Construction ",
    "sg:phone":"+32 11 58 99 85",
    "sg:postcode":"3440",
    "sg:province":"Vlaams-Brabant",
    "wof:name":"Driesmans Patrick",
    "wof:placetype":"venue"
},
  "geometry": {"coordinates":[5.0699319839,50.8615913391],"type":"Point"}
}