{
  "type": "Feature",
  "properties": {
    "iso:country":"BE",
    "sg:address":"Langerheide 30",
    "sg:city":"Haacht",
    "sg:orig_category":"Landmeters",
    "sg:phone":"+32 16 60 68 05",
    "sg:postcode":"3150",
    "sg:province":"Vlaams-Brabant",
    "wof:name":"Felix Stuyckens",
    "wof:placetype":"venue"
},
  "geometry": {"coordinates":[4.6213932037,50.9756889343],"type":"Point"}
}