{
  "type": "Feature",
  "properties": {
    "addr:full":"Goudstraat 24 Gent Oost-Vlaanderen 9000",
    "addr:housenumber":"24",
    "addr:postcode":"9000",
    "addr:street":"Goudstraat;Oost-Vlaanderen",
    "iso:country":"BE",
    "sg:address":"Goudstraat 24",
    "sg:city":"Gent",
    "sg:classifiers":[
        {
            "category":"Professional",
            "subcategory":"Art Services",
            "type":"Services"
        }
    ],
    "sg:phone":"+32 9 265 09 27",
    "sg:postcode":"9000",
    "sg:province":"Oost-Vlaanderen",
    "sg:tags":[
        "photographer"
    ],
    "wof:name":"De Witte A",
    "wof:placetype":"venue"
},
  "geometry": {"coordinates":[3.7277729511,51.0595664978],"type":"Point"}
}