{
  "type": "Feature",
  "properties": {
    "iso:country":"BE",
    "sg:address":"Rue Antoine-quintens 24",
    "sg:city":"Gembloux",
    "sg:orig_category":"Eleveurs de bovins",
    "sg:phone":"+32 81 63 33 92",
    "sg:postcode":"5032",
    "sg:province":"Namur",
    "wof:name":"Joseph Hance",
    "wof:placetype":"venue"
},
  "geometry": {"coordinates":[4.6657671928,50.5404129028],"type":"Point"}
}