{
  "type": "Feature",
  "properties": {
    "addr:full":"Rue Du Chapitre 18 Florennes Namur 5620",
    "addr:housenumber":"18",
    "addr:postcode":"5620",
    "addr:street":"Rue Du Chapitre",
    "iso:country":"BE",
    "sg:address":"Rue Du Chapitre 18",
    "sg:city":"Florennes",
    "sg:orig_category":"Boucheries",
    "sg:phone":"+32 71 68 88 77",
    "sg:postcode":"5620",
    "sg:province":"Namur",
    "wof:name":"Christian Pire",
    "wof:placetype":"venue"
},
  "geometry": {"coordinates":[4.604637146,50.2506828308],"type":"Point"}
}