{
  "type": "Feature",
  "properties": {
    "addr:full":"Chemin De Crapel 10 Lontzen/lontzen Li\u00e8ge 4711",
    "addr:housenumber":"10",
    "addr:postcode":"4711",
    "addr:street":"Chemin De Crapel",
    "iso:country":"BE",
    "sg:address":"Chemin De Crapel 10",
    "sg:city":"Lontzen/lontzen",
    "sg:orig_category":"Eleveurs de bovins",
    "sg:phone":"+32 87 88 02 26",
    "sg:postcode":"4711",
    "sg:province":"Li\u00e8ge",
    "wof:name":"Oswald Janssen",
    "wof:placetype":"venue"
},
  "geometry": {"coordinates":[6.047369957,50.6752853394],"type":"Point"}
}