{
  "type": "Feature",
  "properties": {
    "iso:country":"BE",
    "sg:address":"127-133 R Van Artevelde",
    "sg:city":"Bruxelles",
    "sg:classifiers":[
        {
            "category":"Manufacturing",
            "subcategory":"Wood Products",
            "type":"Manufacturing & Wholesale Goods"
        }
    ],
    "sg:phone":"+32 2 511 45 60",
    "sg:postcode":"1000",
    "sg:province":"Bruxelles-Capitale",
    "sg:tags":[
        "furniture"
    ],
    "wof:name":"Girbal Sa",
    "wof:placetype":"venue"
},
  "geometry": {"coordinates":[4.3450551033,50.8474235535],"type":"Point"}
}