{
  "type": "Feature",
  "properties": {
    "addr:full":"Sint-jans Gasthuisstraat 6 Gistel West-Vlaanderen 8470",
    "addr:housenumber":"6",
    "addr:postcode":"8470",
    "addr:street":"Sint-Jans Gasthuisstraat",
    "iso:country":"BE",
    "sg:address":"Sint-jans Gasthuisstraat 6",
    "sg:city":"Gistel",
    "sg:classifiers":[
        {
            "category":"Insurance",
            "subcategory":"Insurance Agent",
            "type":"Services"
        }
    ],
    "sg:phone":"+32 59 27 90 64",
    "sg:postcode":"8470",
    "sg:province":"West-Vlaanderen",
    "sg:tags":[
        "broker"
    ],
    "wof:name":"Ortmann Zakenkantoor",
    "wof:placetype":"venue"
},
  "geometry": {"coordinates":[2.968693018,51.1563339233],"type":"Point"}
}