{
  "type": "Feature",
  "properties": {
    "addr:full":"Hoksentstraat 35 Hechtel-eksel Limburg 3941",
    "addr:housenumber":"35",
    "addr:postcode":"3941",
    "addr:street":"Hoksentstraat",
    "iso:country":"BE",
    "sg:address":"Hoksentstraat 35",
    "sg:city":"Hechtel-eksel",
    "sg:orig_category":"Airconditioning and ventilatie Elektrische installaties voor woningen",
    "sg:phone":"+32 475 58 90 36",
    "sg:postcode":"3941",
    "sg:province":"Limburg",
    "wof:name":"Mike Geuns",
    "wof:placetype":"venue"
},
  "geometry": {"coordinates":[5.422118187,51.1573143005],"type":"Point"}
}