{
  "type": "Feature",
  "properties": {
    "addr:full":"Rue Van Eyck 52b02 Elsene Bruxelles-Capitale 1050",
    "addr:housenumber":"52b02",
    "addr:postcode":"1050",
    "addr:street":"Rue Van Eyck",
    "iso:country":"BE",
    "sg:address":"Rue Van Eyck 52b02",
    "sg:city":"Elsene",
    "sg:orig_category":"Agences d'exp\u00e9dition",
    "sg:phone":"+32 2 640 97 33",
    "sg:postcode":"1050",
    "sg:province":"Bruxelles-Capitale",
    "wof:name":"Sif Groupe",
    "wof:placetype":"venue"
},
  "geometry": {"coordinates":[4.3687901497,50.8277015686],"type":"Point"}
}