{
  "type": "Feature",
  "properties": {
    "addr:full":"Rue Du Fond 62 Anhee Namur 5537",
    "addr:housenumber":"62",
    "addr:postcode":"5537",
    "addr:street":"Rue Du Fond;Namur",
    "iso:country":"BE",
    "sg:address":"Rue Du Fond 62",
    "sg:city":"Anhee",
    "sg:orig_category":"Electrom\u00e9nager, t\u00e9l\u00e9visions and radios",
    "sg:phone":"+32 82 61 39 74",
    "sg:postcode":"5537",
    "sg:province":"Namur",
    "wof:name":"Michel Colin",
    "wof:placetype":"venue"
},
  "geometry": {"coordinates":[4.8300828934,50.3224983215],"type":"Point"}
}