{
  "type": "Feature",
  "properties": {
    "iso:country":"BE",
    "sg:address":"Route De Blaimont 105",
    "sg:city":"Hastiere",
    "sg:orig_category":"Drukkerijen and copyshops",
    "sg:phone":"+32 82 64 55 53",
    "sg:postcode":"5541",
    "sg:province":"Namur",
    "wof:name":"Jean-claude Godart",
    "wof:placetype":"venue"
},
  "geometry": {"coordinates":[4.8395800591,50.212310791],"type":"Point"}
}