{
  "type": "Feature",
  "properties": {
    "iso:country":"BE",
    "sg:address":"Maastrichterstraat 19",
    "sg:city":"Hasselt",
    "sg:orig_category":"Boekhandels Kantoormateriaal Krantenwinkels Microsoft",
    "sg:phone":"+32 11 22 75 59",
    "sg:postcode":"3500",
    "sg:province":"Limburg",
    "wof:name":"Standaard Boekhandel Hasselt",
    "wof:placetype":"venue"
},
  "geometry": {"coordinates":[5.3387231827,50.9290733337],"type":"Point"}
}