{
  "type": "Feature",
  "properties": {
    "addr:full":"Fotografielaan 37-39 Wilrijk Antwerpen 2610",
    "addr:postcode":"37-39;2610",
    "addr:street":"Fotografielaan;Antwerpen",
    "iso:country":"BE",
    "sg:address":"Fotografielaan 37-39",
    "sg:city":"Wilrijk",
    "sg:classifiers":[
        {
            "category":"Banks & Credit Unions",
            "subcategory":"Investment Brokerage",
            "type":"Services"
        }
    ],
    "sg:phone":"+32 3 825 15 15",
    "sg:postcode":"2610",
    "sg:province":"Antwerpen",
    "sg:tags":[
        "-",
        "transport",
        "related"
    ],
    "wof:name":"Sumitomo Warehouse 'europe' Gmbh",
    "wof:placetype":"venue"
},
  "geometry": {"coordinates":[4.3653459549,51.1571998596],"type":"Point"}
}