{
  "type": "Feature",
  "properties": {
    "iso:country":"BE",
    "sg:address":"Biezenstraat 21",
    "sg:city":"Berlare",
    "sg:classifiers":[
        {
            "category":"Arena",
            "subcategory":"Sports Club",
            "type":"Entertainment"
        }
    ],
    "sg:phone":"+32 52 42 22 69",
    "sg:postcode":"9290",
    "sg:province":"Oost-Vlaanderen",
    "sg:tags":[
        "de"
    ],
    "wof:name":"V.c. Berlare",
    "wof:placetype":"venue"
},
  "geometry": {"coordinates":[4.0013952255,51.0160598755],"type":"Point"}
}