{
  "type": "Feature",
  "properties": {
    "iso:country":"BE",
    "sg:address":"Schildpadstraat 8",
    "sg:city":"Grimbergen",
    "sg:orig_category":"Non-Classified Establishments",
    "sg:phone":"+32 2 269 94 72",
    "sg:postcode":"1850",
    "sg:province":"Vlaams-Brabant",
    "wof:name":"Rummens L Nv",
    "wof:placetype":"venue"
},
  "geometry": {"coordinates":[4.3719730377,50.9411392212],"type":"Point"}
}