{
  "type": "Feature",
  "properties": {
    "iso:country":"BE",
    "sg:address":"Rue Sainte- Genevi\u00c8ve 23",
    "sg:city":"Chimay",
    "sg:orig_category":"Passagiersvervoer over de weg",
    "sg:phone":"+32 60 21 13 31",
    "sg:postcode":"6460",
    "sg:province":"Hainaut",
    "wof:name":"Voyages Leleux",
    "wof:placetype":"venue"
},
  "geometry": {"coordinates":[4.3021922112,50.046836853],"type":"Point"}
}