{
  "type": "Feature",
  "properties": {
    "iso:country":"BE",
    "sg:address":"Rue Ferrer 252",
    "sg:city":"Seraing",
    "sg:orig_category":"Oil Lubrication Pumps",
    "sg:phone":"+32 4 338 06 02",
    "sg:postcode":"4100",
    "sg:province":"Li\u00e8ge",
    "wof:name":"Henning S.a.",
    "wof:placetype":"venue"
},
  "geometry": {"coordinates":[5.5028729439,50.6080970764],"type":"Point"}
}