{
  "type": "Feature",
  "properties": {
    "addr:full":"Korte Gasthuisstraat 32 Antwerpen Antwerpen 2000",
    "addr:housenumber":"32",
    "addr:postcode":"2000",
    "addr:street":"Korte Gasthuisstraat",
    "iso:country":"BE",
    "sg:address":"Korte Gasthuisstraat 32",
    "sg:city":"Antwerpen",
    "sg:orig_category":"Alimentation sp\u00e9cialis\u00e9e",
    "sg:phone":"+32 3 233 57 64",
    "sg:postcode":"2000",
    "sg:province":"Antwerpen",
    "wof:name":"Huis Breughel",
    "wof:placetype":"venue"
},
  "geometry": {"coordinates":[4.4042310715,51.2166938782],"type":"Point"}
}