{
  "type": "Feature",
  "properties": {
    "iso:country":"BE",
    "sg:address":"Rue Du Fort 51",
    "sg:city":"Juprelle (lantin)",
    "sg:classifiers":[
        {
            "category":"Health Services",
            "subcategory":"Health Practitioner",
            "type":"Services"
        }
    ],
    "sg:phone":"+32 4 263 78 12",
    "sg:postcode":"4450",
    "sg:province":"Li\u00e8ge",
    "sg:tags":[
        "physiotherapist"
    ],
    "wof:name":"Vinchent Bernard",
    "wof:placetype":"venue"
},
  "geometry": {"coordinates":[5.5243849754,50.6923065186],"type":"Point"}
}