{
  "type": "Feature",
  "properties": {
    "addr:full":"Wolvertemsesteenweg 196 Merchtem Vlaams-Brabant 1785",
    "addr:housenumber":"196",
    "addr:postcode":"1785",
    "addr:street":"Wolvertemsesteenweg",
    "iso:country":"BE",
    "sg:address":"Wolvertemsesteenweg 196",
    "sg:city":"Merchtem",
    "sg:classifiers":[
        {
            "category":"Arena",
            "subcategory":"Sports Club",
            "type":"Entertainment"
        }
    ],
    "sg:phone":"+32 52 37 18 56",
    "sg:postcode":"1785",
    "sg:province":"Vlaams-Brabant",
    "sg:tags":[
        "de"
    ],
    "wof:name":"Aikidoclub Merchtem",
    "wof:placetype":"venue"
},
  "geometry": {"coordinates":[4.2608761787,50.9535865784],"type":"Point"}
}