{
  "type": "Feature",
  "properties": {
    "iso:country":"BE",
    "sg:address":"Oosterring 9",
    "sg:city":"Genk",
    "sg:orig_category":"Mat\u00e9riel scientifique and technique Fab",
    "sg:phone":"+32 89 62 04 42",
    "sg:postcode":"3600",
    "sg:province":"Limburg",
    "wof:name":"G.p.s.",
    "wof:placetype":"venue"
},
  "geometry": {"coordinates":[5.5184497833,50.9423713684],"type":"Point"}
}