{
  "type": "Feature",
  "properties": {
    "iso:country":"BE",
    "sg:address":"Zijdeling 1",
    "sg:city":"Bredene",
    "sg:orig_category":"M\u00e9decins and sp\u00e9cialistes",
    "sg:phone":"+32 59 33 24 48",
    "sg:postcode":"8450",
    "sg:province":"West-Vlaanderen",
    "wof:name":"Erik Tratsaert",
    "wof:placetype":"venue"
},
  "geometry": {"coordinates":[2.9591999054,51.2410087585],"type":"Point"}
}