{
  "type": "Feature",
  "properties": {
    "iso:country":"BE",
    "sg:address":"Rue Du Vertbois 13b",
    "sg:city":"Li\u00e8ge 1",
    "sg:classifiers":[
        {
            "category":"Banks & Credit Unions",
            "subcategory":"Investment Brokerage",
            "type":"Services"
        }
    ],
    "sg:phone":"+32 4 221 62 20",
    "sg:postcode":"4000",
    "sg:province":"Li\u00e8ge",
    "wof:name":"Spinventure Sa",
    "wof:placetype":"venue"
},
  "geometry": {"coordinates":[5.5721750259,50.6378631592],"type":"Point"}
}