{
  "type": "Feature",
  "properties": {
    "iso:country":"BE",
    "sg:address":"Rechtestraat 16",
    "sg:city":"Lier",
    "sg:classifiers":[
        {
            "category":"Shopping",
            "subcategory":"Shoes",
            "type":"Retail Goods"
        }
    ],
    "sg:phone":"+32 3 488 00 10",
    "sg:postcode":"2500",
    "sg:province":"Antwerpen",
    "sg:tags":[
        "slipper",
        "-"
    ],
    "wof:name":"Zurich Special Shoe Bvba",
    "wof:placetype":"venue"
},
  "geometry": {"coordinates":[4.5719771385,51.1300926208],"type":"Point"}
}