{
  "type": "Feature",
  "properties": {
    "addr:full":"Rue Nouwen 26 Bassenge Li\u00e8ge 4690",
    "addr:housenumber":"26",
    "addr:postcode":"4690",
    "addr:street":"Rue Nouwen",
    "iso:country":"BE",
    "sg:address":"Rue Nouwen 26",
    "sg:city":"Bassenge",
    "sg:orig_category":"Kapsalons",
    "sg:phone":"+32 4 286 58 08",
    "sg:postcode":"4690",
    "sg:province":"Li\u00e8ge",
    "wof:name":"Coiffure Nancy",
    "wof:placetype":"venue"
},
  "geometry": {"coordinates":[5.6037278175,50.7609214783],"type":"Point"}
}