{
  "type": "Feature",
  "properties": {
    "addr:full":"Rue Picard 74 Molenbeek-saint-jean (bruxelles) Bruxelles-Capitale 1080",
    "addr:housenumber":"74",
    "addr:postcode":"1080",
    "addr:street":"Rue Picard",
    "iso:country":"BE",
    "sg:address":"Rue Picard 74",
    "sg:city":"Molenbeek-saint-jean (bruxelles)",
    "sg:classifiers":[
        {
            "category":"Restaurant",
            "type":"Food & Drink"
        }
    ],
    "sg:phone":"+32 2 376 10 56",
    "sg:postcode":"1080",
    "sg:province":"Bruxelles-Capitale",
    "wof:name":"Les Senteurs De Saint-tropez",
    "wof:placetype":"venue"
},
  "geometry": {"coordinates":[4.3450160027,50.8636054993],"type":"Point"}
}