{
  "type": "Feature",
  "properties": {
    "addr:full":"Oude Weg 11 Hoogstraten Antwerpen 2323",
    "addr:housenumber":"11",
    "addr:postcode":"2323",
    "addr:street":"Oude Weg",
    "iso:country":"BE",
    "sg:address":"Oude Weg 11",
    "sg:city":"Hoogstraten",
    "sg:orig_category":"MEUBELONTWERP AND -INSTALLATIE",
    "sg:phone":"+32 3 314 68 42",
    "sg:postcode":"2323",
    "sg:province":"Antwerpen",
    "wof:name":"Forsterkeukens",
    "wof:placetype":"venue"
},
  "geometry": {"coordinates":[4.7957539558,51.3966712952],"type":"Point"}
}