{
  "type": "Feature",
  "properties": {
    "iso:country":"BE",
    "sg:address":"Zeedijk 77-79",
    "sg:city":"Blankenberge",
    "sg:classifiers":[
        {
            "category":"Travel",
            "subcategory":"Hotels & Motels",
            "type":"Entertainment"
        }
    ],
    "sg:phone":"+32 50 42 96 64",
    "sg:postcode":"8370",
    "sg:province":"West-Vlaanderen",
    "sg:tags":[
        "fair",
        "business",
        "restaurant",
        "game",
        "professional",
        "sport",
        "hotels"
    ],
    "wof:name":"Beach Palace Bvba",
    "wof:placetype":"venue"
},
  "geometry": {"coordinates":[3.1215538979,51.3145599365],"type":"Point"}
}