{
  "type": "Feature",
  "properties": {
    "addr:full":"Rue De F\u00c9tinne 37 Li\u00c8ge Li\u00e8ge 4020",
    "addr:housenumber":"37",
    "addr:postcode":"4020",
    "addr:street":"Rue De Fe\u0301Tinne",
    "iso:country":"BE",
    "sg:address":"Rue De F\u00c9tinne 37",
    "sg:city":"Li\u00c8ge",
    "sg:orig_category":"Pain, p\u00e2tisseries and confiseries",
    "sg:phone":"+32 4 343 29 72",
    "sg:postcode":"4020",
    "sg:province":"Li\u00e8ge",
    "wof:name":"Jean-luc Keutgen",
    "wof:placetype":"venue"
},
  "geometry": {"coordinates":[5.5819721222,50.6270370483],"type":"Point"}
}