{
  "type": "Feature",
  "properties": {
    "iso:country":"BE",
    "sg:address":"Lar",
    "sg:city":"Menen (rekkem)",
    "sg:classifiers":[
        {
            "category":"Communications",
            "subcategory":"Film & Video Production",
            "type":"Services"
        }
    ],
    "sg:phone":"+32 56 42 82 36",
    "sg:postcode":"8930",
    "sg:province":"West-Vlaanderen",
    "sg:tags":[
        "warehouse",
        "storage",
        "cold",
        "-"
    ],
    "wof:name":"Larfrost",
    "wof:placetype":"venue"
},
  "geometry": {"coordinates":[3.1944880486,50.7747917175],"type":"Point"}
}