{
  "type": "Feature",
  "properties": {
    "addr:full":"Gauwelstraat 56 Zwevegem (heestert) West-Vlaanderen 8551",
    "addr:housenumber":"56",
    "addr:postcode":"8551",
    "addr:street":"Gauwelstraat",
    "iso:country":"BE",
    "sg:address":"Gauwelstraat 56",
    "sg:city":"Zwevegem (heestert)",
    "sg:orig_category":"Non-Classified Establishments",
    "sg:phone":"+32 56 64 50 32",
    "sg:postcode":"8551",
    "sg:province":"West-Vlaanderen",
    "wof:name":"Cattebeke J",
    "wof:placetype":"venue"
},
  "geometry": {"coordinates":[3.402121067,50.7801513672],"type":"Point"}
}