{
  "type": "Feature",
  "properties": {
    "addr:full":"Waregemseweg 131 Wortegem-petegem (wortegem) Oost-Vlaanderen 9790",
    "addr:housenumber":"131",
    "addr:postcode":"9790",
    "addr:street":"Wortegem-Petegem Wortegem Oost-Vlaanderen",
    "iso:country":"BE",
    "sg:address":"Waregemseweg 131",
    "sg:city":"Wortegem-petegem (wortegem)",
    "sg:classifiers":[
        {
            "category":"Home & Garden",
            "subcategory":"Building Materials",
            "type":"Retail Goods"
        }
    ],
    "sg:phone":"+32 56 68 93 59",
    "sg:postcode":"9790",
    "sg:province":"Oost-Vlaanderen",
    "sg:tags":[
        "granite",
        "stone",
        "natural",
        "marble"
    ],
    "wof:name":"Agra Nv",
    "wof:placetype":"venue"
},
  "geometry": {"coordinates":[3.4776229858,50.8648071289],"type":"Point"}
}