{
  "type": "Feature",
  "properties": {
    "iso:country":"BE",
    "sg:address":"Chinru 18",
    "sg:city":"Theux",
    "sg:orig_category":"Tuinen",
    "sg:phone":"+32 87 22 22 83",
    "sg:postcode":"4910",
    "sg:province":"Li\u00e8ge",
    "wof:name":"Mathieu Ph.",
    "wof:placetype":"venue"
},
  "geometry": {"coordinates":[5.8121237755,50.5359802246],"type":"Point"}
}