{
  "type": "Feature",
  "properties": {
    "addr:full":"Bellegemsestraat 35 Kortrijk (bellegem) West-Vlaanderen 8510",
    "addr:housenumber":"35",
    "addr:postcode":"8510",
    "addr:street":"Bellegemsestraat",
    "iso:country":"BE",
    "sg:address":"Bellegemsestraat 35",
    "sg:city":"Kortrijk (bellegem)",
    "sg:classifiers":[
        {
            "category":"Shopping",
            "subcategory":"Optician",
            "type":"Retail Goods"
        }
    ],
    "sg:phone":"+32 56 21 43 52",
    "sg:postcode":"8510",
    "sg:province":"West-Vlaanderen",
    "sg:tags":[
        "-"
    ],
    "wof:name":"Decraene J",
    "wof:placetype":"venue"
},
  "geometry": {"coordinates":[3.2825679779,50.7776794434],"type":"Point"}
}