{
  "type": "Feature",
  "properties": {
    "iso:country":"BE",
    "sg:address":"Dumonplein 1",
    "sg:city":"Sint-pieters-woluwe/woluwe-sai",
    "sg:orig_category":"Banken and kredietinstellingen",
    "sg:phone":"+32 2 779 20 60",
    "sg:postcode":"1150",
    "sg:province":"Bruxelles-Capitale",
    "wof:name":"Bbl",
    "wof:placetype":"venue"
},
  "geometry": {"coordinates":[4.4648599625,50.8392753601],"type":"Point"}
}