{
  "type": "Feature",
  "properties": {
    "iso:country":"BE",
    "sg:address":"Leestsesteenweg 161",
    "sg:city":"Mechelen",
    "sg:classifiers":[
        {
            "category":"Building & Trades",
            "subcategory":"Pest Control",
            "type":"Services"
        }
    ],
    "sg:phone":"+32 477 58 31 79",
    "sg:postcode":"2800",
    "sg:province":"Antwerpen",
    "sg:tags":[
        "painting",
        "contractor"
    ],
    "wof:name":"Mondeco",
    "wof:placetype":"venue"
},
  "geometry": {"coordinates":[4.4259262085,51.0364532471],"type":"Point"}
}