{
  "type": "Feature",
  "properties": {
    "iso:country":"BE",
    "sg:address":"Passage Wellington 165 Box 84",
    "sg:city":"Waterloo",
    "sg:classifiers":[
        {
            "category":"Shopping",
            "subcategory":"Clothing, Apparel, & Fashions",
            "type":"Retail Goods"
        }
    ],
    "sg:phone":"+32 2 353 00 18",
    "sg:postcode":"1410",
    "sg:province":"Brabant Wallon",
    "sg:tags":[
        "lady",
        "clothing",
        "-"
    ],
    "wof:name":"Saint Germain",
    "wof:placetype":"venue"
},
  "geometry": {"coordinates":[4.3995580673,50.7164573669],"type":"Point"}
}