{
  "type": "Feature",
  "properties": {
    "addr:full":"Rue P. Sauvenier Manage Hainaut 7170",
    "addr:postcode":"7170",
    "addr:street":"Rue P. Sauvenier;Hainaut",
    "iso:country":"BE",
    "sg:address":"Rue P. Sauvenier",
    "sg:city":"Manage",
    "sg:orig_category":"Loodgieterij, verwarming and sanitaire installaties",
    "sg:phone":"+32 64 54 08 96",
    "sg:postcode":"7170",
    "sg:province":"Hainaut",
    "wof:name":"Andr\u00c9 Y.",
    "wof:placetype":"venue"
},
  "geometry": {"coordinates":[4.2327899933,50.5008239746],"type":"Point"}
}