{
  "type": "Feature",
  "properties": {
    "iso:country":"BE",
    "sg:address":"Industriestraat 7",
    "sg:city":"Langemark-poelkapelle",
    "sg:orig_category":"Afval and schroot Gh",
    "sg:phone":"+32 57 48 71 93",
    "sg:postcode":"8920",
    "sg:province":"West-Vlaanderen",
    "wof:name":"Geert Beauprez",
    "wof:placetype":"venue"
},
  "geometry": {"coordinates":[2.919770956,50.9132423401],"type":"Point"}
}