{
  "type": "Feature",
  "properties": {
    "iso:country":"BE",
    "sg:address":"Triestraat 161",
    "sg:city":"Assenede",
    "sg:orig_category":"Sportclubs",
    "sg:phone":"+32 9 344 80 58",
    "sg:postcode":"9960",
    "sg:province":"Oost-Vlaanderen",
    "wof:name":"Wielertoeristenclub Blijf Jong Assenede",
    "wof:placetype":"venue"
},
  "geometry": {"coordinates":[3.7614889145,51.2133293152],"type":"Point"}
}