{
  "type": "Feature",
  "properties": {
    "addr:full":"Rue Delper\u00c9e 12ba Huy Li\u00e8ge 4500",
    "addr:housenumber":"12ba",
    "addr:postcode":"4500",
    "addr:street":"Rue Delpere\u0301E",
    "iso:country":"BE",
    "sg:address":"Rue Delper\u00c9e 12ba",
    "sg:city":"Huy",
    "sg:orig_category":"Activit\u00e9s r\u00e9cr\u00e9atives diverses",
    "sg:phone":"+32 85 21 57 49",
    "sg:postcode":"4500",
    "sg:province":"Li\u00e8ge",
    "wof:name":"Huy Espage-bridge",
    "wof:placetype":"venue"
},
  "geometry": {"coordinates":[5.2460451126,50.5259666443],"type":"Point"}
}