{
  "type": "Feature",
  "properties": {
    "iso:country":"BE",
    "sg:address":"Broechemsesteenweg 111",
    "sg:city":"Boechout (vremde)",
    "sg:classifiers":[
        {
            "category":"Building & Trades",
            "subcategory":"Landscaping Services",
            "type":"Services"
        }
    ],
    "sg:phone":"+32 3 485 76 13",
    "sg:postcode":"2531",
    "sg:province":"Antwerpen",
    "sg:tags":[
        "-",
        "lopping",
        "work",
        "tree",
        "felling"
    ],
    "wof:name":"Siebens P",
    "wof:placetype":"venue"
},
  "geometry": {"coordinates":[4.5362529755,51.174621582],"type":"Point"}
}