{
  "type": "Feature",
  "properties": {
    "addr:full":"Rue Du Parnasse 3 Elsene/ixelles Bruxelles-Capitale 1050",
    "addr:housenumber":"3",
    "addr:postcode":"1050",
    "addr:street":"Rue Du Parnasse",
    "iso:country":"BE",
    "sg:address":"Rue Du Parnasse 3",
    "sg:city":"Elsene/ixelles",
    "sg:classifiers":[
        {
            "category":"Professional",
            "subcategory":"Business Services",
            "type":"Services"
        }
    ],
    "sg:phone":"+32 2 511 54 15",
    "sg:postcode":"1050",
    "sg:province":"Bruxelles-Capitale",
    "sg:tags":[
        "aux",
        "diver",
        "entreprises"
    ],
    "wof:name":"Fran\u00c7ois Coosemans",
    "wof:placetype":"venue"
},
  "geometry": {"coordinates":[4.3707528114,50.8386955261],"type":"Point"}
}