{
  "type": "Feature",
  "properties": {
    "addr:full":"Rue Destafflers 29ba Doornik Hainaut 7520",
    "addr:housenumber":"29ba",
    "addr:postcode":"7520",
    "addr:street":"Rue Destafflers",
    "iso:country":"BE",
    "sg:address":"Rue Destafflers 29ba",
    "sg:city":"Doornik",
    "sg:orig_category":"Diensten voor huisdieren Diverse organisaties and verenigingen",
    "sg:phone":"+32 69 35 24 83",
    "sg:postcode":"7520",
    "sg:province":"Hainaut",
    "wof:name":"Lig. Roy. Belg. Protection Oiseaux",
    "wof:placetype":"venue"
},
  "geometry": {"coordinates":[3.2830650806,50.6447639465],"type":"Point"}
}