{
  "type": "Feature",
  "properties": {
    "iso:country":"BE",
    "sg:address":"Sint-lambertusstraat 16",
    "sg:city":"Leuven",
    "sg:orig_category":"Avocats and conseillers juridiques",
    "sg:phone":"+32 16 22 63 70",
    "sg:postcode":"3001",
    "sg:province":"Vlaams-Brabant",
    "wof:name":"J. Devos",
    "wof:placetype":"venue"
},
  "geometry": {"coordinates":[4.6943311691,50.863067627],"type":"Point"}
}