{
  "type": "Feature",
  "properties": {
    "iso:country":"BE",
    "sg:address":"Avenue Albert Ier 36",
    "sg:city":"Namur",
    "sg:orig_category":"Mat\u00e9riaux de construction Combustibles",
    "sg:phone":"+32 81 22 16 85",
    "sg:postcode":"5000",
    "sg:province":"Namur",
    "wof:name":"Houiller De La Meuse",
    "wof:placetype":"venue"
},
  "geometry": {"coordinates":[4.8809671402,50.4662361145],"type":"Point"}
}