{
  "type": "Feature",
  "properties": {
    "addr:full":"Avenue R\u00eave D'or 100 La Louvi\u00e8re Hainaut 7100",
    "addr:housenumber":"100",
    "addr:postcode":"7100",
    "addr:street":"Avenue Re\u0302Ve D'Or",
    "iso:country":"BE",
    "sg:address":"Avenue R\u00eave D'or 100",
    "sg:city":"La Louvi\u00e8re",
    "sg:classifiers":[
        {
            "category":"Health Services",
            "subcategory":"Health Practitioner",
            "type":"Services"
        }
    ],
    "sg:phone":"+32 64 28 27 89",
    "sg:postcode":"7100",
    "sg:province":"Hainaut",
    "sg:tags":[
        "therapist",
        "speech"
    ],
    "wof:name":"De Vleeschouwer A",
    "wof:placetype":"venue"
},
  "geometry": {"coordinates":[4.171020031,50.4790992737],"type":"Point"}
}