{
  "type": "Feature",
  "properties": {
    "addr:full":"Torhoutstraat 31bb Hooglede West-Vlaanderen 8830",
    "addr:housenumber":"31bb",
    "addr:postcode":"8830",
    "addr:street":"Torhoutstraat",
    "iso:country":"BE",
    "sg:address":"Torhoutstraat 31bb",
    "sg:city":"Hooglede",
    "sg:orig_category":"Sportclubs Sportterreinen and installaties behalve sportcentra",
    "sg:phone":"+32 51 22 88 37",
    "sg:postcode":"8830",
    "sg:province":"West-Vlaanderen",
    "wof:name":"V.k.p. Sadef",
    "wof:placetype":"venue"
},
  "geometry": {"coordinates":[3.0975449085,50.9983291626],"type":"Point"}
}