{
  "type": "Feature",
  "properties": {
    "iso:country":"BE",
    "sg:address":"Rue Du Vingt-deux Ao\u00fbt 34",
    "sg:city":"Morlanwelz (carni\u00e8res)",
    "sg:classifiers":[
        {
            "category":"Insurance",
            "subcategory":"Insurance Agent",
            "type":"Services"
        }
    ],
    "sg:phone":"+32 64 44 97 26",
    "sg:postcode":"7141",
    "sg:province":"Hainaut",
    "sg:tags":[
        "-",
        "representative"
    ],
    "wof:name":"Cbc Assurances - Morsiau V Sa",
    "wof:placetype":"venue"
},
  "geometry": {"coordinates":[4.2565331459,50.4287910461],"type":"Point"}
}