{
  "type": "Feature",
  "properties": {
    "addr:full":"Rue Du Centre 1 Leglise Luxembourg 6860",
    "addr:housenumber":"1",
    "addr:postcode":"6860",
    "addr:street":"Rue Du Centre",
    "iso:country":"BE",
    "sg:address":"Rue Du Centre 1",
    "sg:city":"Leglise",
    "sg:orig_category":"Eleveurs de bovins",
    "sg:phone":"+32 63 60 02 31",
    "sg:postcode":"6860",
    "sg:province":"Luxembourg",
    "wof:name":"Bernard Gruslin",
    "wof:placetype":"venue"
},
  "geometry": {"coordinates":[5.5349779129,49.7996826172],"type":"Point"}
}