{
  "type": "Feature",
  "properties": {
    "addr:full":"Westkapelse Steenweg 15 Brugge West-Vlaanderen 8380",
    "addr:housenumber":"15",
    "addr:postcode":"8380",
    "addr:street":"Steenweg",
    "iso:country":"BE",
    "sg:address":"Westkapelse Steenweg 15",
    "sg:city":"Brugge",
    "sg:orig_category":"Verhuur cateringmateriaal and evenementuitrusting Winkelinrichting and handelsuitrusting Gh",
    "sg:phone":"+32 50 59 92 66",
    "sg:postcode":"8380",
    "sg:province":"West-Vlaanderen",
    "wof:name":"Fa. Artidres",
    "wof:placetype":"venue"
},
  "geometry": {"coordinates":[3.2288448811,51.2742958069],"type":"Point"}
}