{
  "type": "Feature",
  "properties": {
    "addr:full":"Hongerstraat 9 Waregem West-Vlaanderen 8790",
    "addr:housenumber":"9",
    "addr:postcode":"8790",
    "addr:street":"Hongerstraat",
    "iso:country":"BE",
    "sg:address":"Hongerstraat 9",
    "sg:city":"Waregem",
    "sg:orig_category":"Boekhouders",
    "sg:phone":"+32 56 60 66 45",
    "sg:postcode":"8790",
    "sg:province":"West-Vlaanderen",
    "wof:name":"Krist Heyde",
    "wof:placetype":"venue"
},
  "geometry": {"coordinates":[3.445941925,50.8953056335],"type":"Point"}
}