{
  "type": "Feature",
  "properties": {
    "addr:full":"Patronagestrasse 53 Kelmis Li\u00e8ge 4720",
    "addr:housenumber":"53",
    "addr:postcode":"4720",
    "addr:street":"Patronagestrasse",
    "iso:country":"BE",
    "sg:address":"Patronagestrasse 53",
    "sg:city":"Kelmis",
    "sg:classifiers":[
        {
            "category":"Bars & Pubs",
            "type":"Food & Drink"
        }
    ],
    "sg:phone":"+32 87 65 87 06",
    "sg:postcode":"4720",
    "sg:province":"Li\u00e8ge",
    "wof:name":"Sportzentrum Kelmis",
    "wof:placetype":"venue"
},
  "geometry": {"coordinates":[6.0141482353,50.7193336487],"type":"Point"}
}