{
  "type": "Feature",
  "properties": {
    "addr:full":"Rue R. Sualem 6 Seraing (jemeppe-sur-meuse) Li\u00e8ge 4101",
    "addr:housenumber":"6",
    "addr:postcode":"4101",
    "addr:street":"Rue R. Sualem;Jemeppe-Sur-Meuse",
    "iso:country":"BE",
    "sg:address":"Rue R. Sualem 6",
    "sg:city":"Seraing (jemeppe-sur-meuse)",
    "sg:classifiers":[
        {
            "category":"Utilities",
            "subcategory":"Mobile Phone",
            "type":"Services"
        }
    ],
    "sg:phone":"+32 4 233 30 30",
    "sg:postcode":"4101",
    "sg:province":"Li\u00e8ge",
    "sg:tags":[
        "access",
        "gsm",
        "-",
        "apparatus"
    ],
    "wof:name":"Equip'auto Pneu Sa",
    "wof:placetype":"venue"
},
  "geometry": {"coordinates":[5.503921032,50.6160850525],"type":"Point"}
}