{
  "type": "Feature",
  "properties": {
    "iso:country":"BE",
    "sg:address":"Vrouwenboomstraat 37",
    "sg:city":"Tielt (schuiferskapelle)",
    "sg:classifiers":[
        {
            "category":"Building & Trades",
            "subcategory":"Equipment Rental",
            "type":"Services"
        }
    ],
    "sg:phone":"+32 51 40 62 26",
    "sg:postcode":"8700",
    "sg:province":"West-Vlaanderen",
    "sg:tags":[
        "safety",
        "collective",
        "individual",
        "-"
    ],
    "wof:name":"Metax",
    "wof:placetype":"venue"
},
  "geometry": {"coordinates":[3.3226089478,51.0193405151],"type":"Point"}
}