{
  "type": "Feature",
  "properties": {
    "addr:full":"Kempenstraat 1 Dilsen-stokkem (dilsen) Limburg 3650",
    "addr:housenumber":"1",
    "addr:postcode":"3650",
    "addr:street":"Kempenstraat",
    "iso:country":"BE",
    "sg:address":"Kempenstraat 1",
    "sg:city":"Dilsen-stokkem (dilsen)",
    "sg:classifiers":[
        {
            "category":"Transit Center",
            "subcategory":"Passenger",
            "type":"Transportation"
        }
    ],
    "sg:phone":"+32 89 79 09 30",
    "sg:postcode":"3650",
    "sg:province":"Limburg",
    "sg:tags":[
        "sand",
        "gravel"
    ],
    "wof:name":"Bichterweerd",
    "wof:placetype":"venue"
},
  "geometry": {"coordinates":[5.7379012108,51.0517425537],"type":"Point"}
}