{
  "type": "Feature",
  "properties": {
    "iso:country":"BE",
    "sg:address":"Moorsledestraat 34-36",
    "sg:city":"Zonnebeke",
    "sg:classifiers":[
        {
            "category":"Home & Garden",
            "subcategory":"Hardware",
            "type":"Retail Goods"
        }
    ],
    "sg:phone":"+32 51 77 75 29",
    "sg:postcode":"8980",
    "sg:province":"West-Vlaanderen",
    "sg:tags":[
        "machine",
        "horticultural"
    ],
    "wof:name":"Cruydt Tuinmachines",
    "wof:placetype":"venue"
},
  "geometry": {"coordinates":[3.0114700794,50.8758544922],"type":"Point"}
}