{
  "type": "Feature",
  "properties": {
    "addr:full":"Avenue De Roodebeek 41-43 Bruxelles Bruxelles-Capitale 1030",
    "addr:postcode":"41-43;1030",
    "addr:street":"Avenue De Roodebeek",
    "iso:country":"BE",
    "sg:address":"Avenue De Roodebeek 41-43",
    "sg:city":"Bruxelles",
    "sg:classifiers":[
        {
            "category":"Professional",
            "subcategory":"Business Services",
            "type":"Services"
        }
    ],
    "sg:phone":"+32 9 226 55 02",
    "sg:postcode":"1030",
    "sg:province":"Bruxelles-Capitale",
    "sg:tags":[
        "marketing",
        "consulting"
    ],
    "wof:name":"Belgian Senior Consultants V.z.w.",
    "wof:placetype":"venue"
},
  "geometry": {"coordinates":[3.6859340668,51.0792312622],"type":"Point"}
}