{
  "type": "Feature",
  "properties": {
    "addr:full":"Jacques Eggermontstraat 10 Gent (ledeberg) Oost-Vlaanderen 9050",
    "addr:housenumber":"10",
    "addr:postcode":"9050",
    "addr:street":"Eggermontstraat",
    "iso:country":"BE",
    "sg:address":"Jacques Eggermontstraat 10",
    "sg:city":"Gent (ledeberg)",
    "sg:classifiers":[
        {
            "category":"Professional",
            "subcategory":"Lawyer & Legal Services",
            "type":"Services"
        }
    ],
    "sg:phone":"+32 9 232 28 04",
    "sg:postcode":"9050",
    "sg:province":"Oost-Vlaanderen",
    "wof:name":"Haeseryn Ludo",
    "wof:placetype":"venue"
},
  "geometry": {"coordinates":[3.7411029339,51.0372543335],"type":"Point"}
}