{
  "type": "Feature",
  "properties": {
    "addr:full":"Rue Du Commandant-speesen 3 Li\u00e8ge 1 (jupille-sur-meuse) Li\u00e8ge 4020",
    "addr:housenumber":"3;1",
    "addr:postcode":"4020",
    "addr:street":"Rue Du Commandant-Speesen;Jupille-Sur-Meuse Lie\u0300Ge",
    "iso:country":"BE",
    "sg:address":"Rue Du Commandant-speesen 3",
    "sg:city":"Li\u00e8ge 1 (jupille-sur-meuse)",
    "sg:classifiers":[
        {
            "category":"Insurance",
            "subcategory":"Insurance Agent",
            "type":"Services"
        }
    ],
    "sg:phone":"+32 4 365 13 14",
    "sg:postcode":"4020",
    "sg:province":"Li\u00e8ge",
    "sg:tags":[
        "broker"
    ],
    "wof:name":"Butacide",
    "wof:placetype":"venue"
},
  "geometry": {"coordinates":[5.6281599998,50.636756897],"type":"Point"}
}