{
  "type": "Feature",
  "properties": {
    "iso:country":"BE",
    "sg:address":"Nieuwstraat 17ba",
    "sg:city":"Izegem",
    "sg:orig_category":"Installation \u00e9lectrique r\u00e9sidentielle",
    "sg:phone":"+32 51 31 01 37",
    "sg:postcode":"8870",
    "sg:province":"West-Vlaanderen",
    "wof:name":"Christiaan Debrouwere",
    "wof:placetype":"venue"
},
  "geometry": {"coordinates":[3.2134950161,50.9188766479],"type":"Point"}
}