{
  "type": "Feature",
  "properties": {
    "addr:full":"Borgwormsesteenweg 112 Sint-truiden Limburg 3800",
    "addr:housenumber":"112",
    "addr:postcode":"3800",
    "addr:street":"Borgwormsesteenweg",
    "iso:country":"BE",
    "sg:address":"Borgwormsesteenweg 112",
    "sg:city":"Sint-truiden",
    "sg:orig_category":"Pleisterwerk",
    "sg:phone":"+32 11 68 76 84",
    "sg:postcode":"3800",
    "sg:province":"Limburg",
    "wof:name":"Joseph Smolders",
    "wof:placetype":"venue"
},
  "geometry": {"coordinates":[5.2148199081,50.7904586792],"type":"Point"}
}