{
  "type": "Feature",
  "properties": {
    "iso:country":"BE",
    "sg:address":"Edith Cavelllaan 10",
    "sg:city":"Brecht",
    "sg:orig_category":"Dameskledingzaken",
    "sg:phone":"+32 3 636 16 77",
    "sg:postcode":"2960",
    "sg:province":"Antwerpen",
    "wof:name":"Boetiek Thea",
    "wof:placetype":"venue"
},
  "geometry": {"coordinates":[4.5733819008,51.2942276001],"type":"Point"}
}