{
  "type": "Feature",
  "properties": {
    "addr:full":"Achter De Wereld 12 Herselt Antwerpen 2230",
    "addr:housenumber":"12",
    "addr:postcode":"2230",
    "addr:street":"Achter De Wereld",
    "iso:country":"BE",
    "sg:address":"Achter De Wereld 12",
    "sg:city":"Herselt",
    "sg:classifiers":[
        {
            "category":"Banks & Credit Unions",
            "subcategory":"Investment Brokerage",
            "type":"Services"
        }
    ],
    "sg:phone":"+32 16 69 96 99",
    "sg:postcode":"2230",
    "sg:province":"Antwerpen",
    "sg:tags":[
        "repair",
        "-",
        "installation",
        "sanitary",
        "article"
    ],
    "wof:name":"Vervloessem Nv",
    "wof:placetype":"venue"
},
  "geometry": {"coordinates":[4.8514242172,51.0284690857],"type":"Point"}
}