{
  "type": "Feature",
  "properties": {
    "addr:full":"R De L' Azeille 3 Philippeville Namur 5600",
    "addr:housenumber":"3",
    "addr:postcode":"5600",
    "iso:country":"BE",
    "sg:address":"R De L' Azeille 3",
    "sg:city":"Philippeville",
    "sg:orig_category":"Installation de menuiserie m\u00e9tallique",
    "sg:phone":"+32 60 31 27 74",
    "sg:postcode":"5600",
    "sg:province":"Namur",
    "wof:name":"Plasti P.p.f",
    "wof:placetype":"venue"
},
  "geometry": {"coordinates":[4.5397567749,50.1357841492],"type":"Point"}
}