{
  "type": "Feature",
  "properties": {
    "addr:full":"Avenue D'uccle 31 Bruxelles (forest) Bruxelles-Capitale 1190",
    "addr:housenumber":"31",
    "addr:postcode":"1190",
    "addr:street":"Avenue D'Uccle",
    "iso:country":"BE",
    "sg:address":"Avenue D'uccle 31",
    "sg:city":"Bruxelles (forest)",
    "sg:classifiers":[
        {
            "category":"Health Services",
            "subcategory":"Health Practitioner",
            "type":"Services"
        }
    ],
    "sg:phone":"+32 2 347 04 22",
    "sg:postcode":"1190",
    "sg:province":"Bruxelles-Capitale",
    "sg:tags":[
        "physiotherapist"
    ],
    "wof:name":"Deridder W",
    "wof:placetype":"venue"
},
  "geometry": {"coordinates":[4.3254671097,50.8126373291],"type":"Point"}
}