{
  "type": "Feature",
  "properties": {
    "iso:country":"BE",
    "sg:address":"Bloklaan 48",
    "sg:city":"Asse",
    "sg:classifiers":[
        {
            "category":"Arena",
            "subcategory":"Sports Club",
            "type":"Entertainment"
        }
    ],
    "sg:phone":"+32 2 452 97 94",
    "sg:postcode":"1730",
    "sg:province":"Vlaams-Brabant",
    "sg:tags":[
        "de"
    ],
    "wof:name":"Gwsc Asse/groepering Van W&s-clubs",
    "wof:placetype":"venue"
},
  "geometry": {"coordinates":[4.196228981,50.9089355469],"type":"Point"}
}