{
  "type": "Feature",
  "properties": {
    "iso:country":"BE",
    "sg:address":"Schrieksesteenweg 118",
    "sg:city":"Heist-op-den-berg",
    "sg:orig_category":"Diverse bouwafwerking and reiniging Gespecialiseerde residenti\u00eble bouw",
    "sg:phone":"+32 15 22 36 93",
    "sg:postcode":"2221",
    "sg:province":"Antwerpen",
    "wof:name":"Paul Buelens",
    "wof:placetype":"venue"
},
  "geometry": {"coordinates":[4.7739758492,51.0512428284],"type":"Point"}
}