{
  "type": "Feature",
  "properties": {
    "addr:full":"Rue Du Tir 1 Charleroi (marcinelle) Hainaut 6001",
    "addr:housenumber":"1",
    "addr:postcode":"6001",
    "addr:street":"Rue Du Tir",
    "iso:country":"BE",
    "sg:address":"Rue Du Tir 1",
    "sg:city":"Charleroi (marcinelle)",
    "sg:classifiers":[
        {
            "category":"Professional",
            "subcategory":"Lawyer & Legal Services",
            "type":"Services"
        }
    ],
    "sg:phone":"+32 71 36 68 78",
    "sg:postcode":"6001",
    "sg:province":"Hainaut",
    "wof:name":"Degr\u00e8ve Ph",
    "wof:placetype":"venue"
},
  "geometry": {"coordinates":[4.4296898842,50.4008598328],"type":"Point"}
}