{
  "type": "Feature",
  "properties": {
    "iso:country":"BE",
    "sg:address":"Zwaaikomstraat 64",
    "sg:city":"Roeselare",
    "sg:classifiers":[
        {
            "category":"Shopping",
            "subcategory":"Crafts & Fabrics",
            "type":"Retail Goods"
        }
    ],
    "sg:phone":"+32 51 20 59 60",
    "sg:postcode":"8800",
    "sg:province":"West-Vlaanderen",
    "sg:tags":[
        "paints",
        "varnish",
        "-",
        "lacquers",
        "enamel"
    ],
    "wof:name":"Vergote Lakkerij Bvba",
    "wof:placetype":"venue"
},
  "geometry": {"coordinates":[3.1526401043,50.9537010193],"type":"Point"}
}