{
  "type": "Feature",
  "properties": {
    "addr:full":"Quai Des Ardennes 159 Li\u00e8ge 1 (ch\u00ean\u00e9e) Li\u00e8ge 4032",
    "addr:housenumber":"159;1",
    "addr:postcode":"4032",
    "addr:street":"Quai Des Ardennes",
    "iso:country":"BE",
    "sg:address":"Quai Des Ardennes 159",
    "sg:city":"Li\u00e8ge 1 (ch\u00ean\u00e9e)",
    "sg:classifiers":[
        {
            "category":"Autos & Motor Vehicles",
            "subcategory":"Auto Supplies",
            "type":"Retail Goods"
        }
    ],
    "sg:phone":"+32 4 365 88 64",
    "sg:postcode":"4032",
    "sg:province":"Li\u00e8ge",
    "sg:tags":[
        "access",
        "automobile",
        "part",
        "-"
    ],
    "wof:name":"Autoparts Paulus Sprl",
    "wof:placetype":"venue"
},
  "geometry": {"coordinates":[5.6102719307,50.6147537231],"type":"Point"}
}