{
  "type": "Feature",
  "properties": {
    "iso:country":"BE",
    "sg:address":"Nieuwstraat 77",
    "sg:city":"Brussel/bruxelles",
    "sg:orig_category":"Verbruikerskredietinstellingen",
    "sg:phone":"+32 2 226 38 00",
    "sg:postcode":"1000",
    "sg:province":"Bruxelles-Capitale",
    "wof:name":"Aurora",
    "wof:placetype":"venue"
},
  "geometry": {"coordinates":[4.3564071655,50.8531188965],"type":"Point"}
}