{
  "type": "Feature",
  "properties": {
    "iso:country":"BE",
    "sg:address":"Dorpsstraat 40",
    "sg:city":"Diepenbeek",
    "sg:orig_category":"Sportclubs",
    "sg:phone":"+32 11 33 31 60",
    "sg:postcode":"3590",
    "sg:province":"Limburg",
    "wof:name":"Limburgse Keverclub",
    "wof:placetype":"venue"
},
  "geometry": {"coordinates":[5.4187932014,50.9092292786],"type":"Point"}
}