{
  "type": "Feature",
  "properties": {
    "addr:full":"Stationsstraat 19 De Haan West-Vlaanderen 8420",
    "addr:housenumber":"19",
    "addr:postcode":"8420",
    "addr:street":"Stationsstraat",
    "iso:country":"BE",
    "sg:address":"Stationsstraat 19",
    "sg:city":"De Haan",
    "sg:orig_category":"Schoenen Sport- and kampeermateriaal",
    "sg:phone":"+32 59 23 95 69",
    "sg:postcode":"8420",
    "sg:province":"West-Vlaanderen",
    "wof:name":"Euro-sport",
    "wof:placetype":"venue"
},
  "geometry": {"coordinates":[3.0338630676,51.2715644836],"type":"Point"}
}