{
  "type": "Feature",
  "properties": {
    "iso:country":"BE",
    "sg:address":"Rue Provinciale 331",
    "sg:city":"Wavre (bierges)",
    "sg:classifiers":[
        {
            "category":"Retail",
            "subcategory":"Auto Repair",
            "type":"Services"
        }
    ],
    "sg:phone":"+32 10 41 89 19",
    "sg:postcode":"1301",
    "sg:province":"Brabant Wallon",
    "sg:tags":[
        "garage"
    ],
    "wof:name":"V.h. Automobiles",
    "wof:placetype":"venue"
},
  "geometry": {"coordinates":[4.5859899521,50.7042007446],"type":"Point"}
}