{
  "type": "Feature",
  "properties": {
    "iso:country":"BE",
    "sg:address":"Legendaledreef 58",
    "sg:city":"Oostkamp",
    "sg:orig_category":"Entretien and r\u00e9parations de machines de bureau and ordinateurs",
    "sg:phone":"+32 50 84 21 40",
    "sg:postcode":"8020",
    "sg:province":"West-Vlaanderen",
    "wof:name":"Pc Rescue",
    "wof:placetype":"venue"
},
  "geometry": {"coordinates":[3.2374510765,51.1433296204],"type":"Point"}
}