{
  "type": "Feature",
  "properties": {
    "iso:country":"BE",
    "sg:address":"P.o. Box 49",
    "sg:city":"Heverlee",
    "sg:classifiers":[
        {
            "category":"Shopping",
            "subcategory":"Mobile Phones",
            "type":"Retail Goods"
        }
    ],
    "sg:phone":"+32 16 40 25 26",
    "sg:postcode":"3001",
    "sg:province":"Vlaams-Brabant",
    "sg:tags":[
        "sound",
        "damping"
    ],
    "wof:name":"Sonogamma",
    "wof:placetype":"venue"
},
  "geometry": {"coordinates":[4.6959400177,50.8633499146],"type":"Point"}
}