{
  "type": "Feature",
  "properties": {
    "addr:full":"Melis Stokelaan 7c Antwerpen Antwerpen 2050",
    "addr:housenumber":"7c",
    "addr:postcode":"2050",
    "addr:street":"Melis Stokelaan",
    "iso:country":"BE",
    "sg:address":"Melis Stokelaan 7c",
    "sg:city":"Antwerpen",
    "sg:classifiers":[
        {
            "category":"Personal",
            "subcategory":"Beauty Salon",
            "type":"Services"
        }
    ],
    "sg:phone":"+32 3 219 02 82",
    "sg:postcode":"2050",
    "sg:province":"Antwerpen",
    "sg:tags":[
        "lady",
        "-",
        "hairdressing"
    ],
    "wof:name":"Christel",
    "wof:placetype":"venue"
},
  "geometry": {"coordinates":[4.3850851059,51.2309875488],"type":"Point"}
}