{
  "type": "Feature",
  "properties": {
    "addr:full":"Rue Albert Ier 22 Fleurus Hainaut 6220",
    "addr:housenumber":"22",
    "addr:postcode":"6220",
    "addr:street":"Rue Albert Ier",
    "iso:country":"BE",
    "sg:address":"Rue Albert Ier 22",
    "sg:city":"Fleurus",
    "sg:orig_category":"Artsen and specialisten",
    "sg:phone":"+32 71 81 12 94",
    "sg:postcode":"6220",
    "sg:province":"Hainaut",
    "wof:name":"Gaston Decerf",
    "wof:placetype":"venue"
},
  "geometry": {"coordinates":[4.5568342209,50.4602279663],"type":"Point"}
}