{
  "type": "Feature",
  "properties": {
    "addr:full":"Rue De Bray 93 La Louviere Hainaut 7110",
    "addr:housenumber":"93",
    "addr:postcode":"7110",
    "addr:street":"Rue De Bray",
    "iso:country":"BE",
    "sg:address":"Rue De Bray 93",
    "sg:city":"La Louviere",
    "sg:orig_category":"HUISBRANDOLIE",
    "sg:phone":"+32 64 66 29 46",
    "sg:postcode":"7110",
    "sg:province":"Hainaut",
    "wof:name":"Henri Valente",
    "wof:placetype":"venue"
},
  "geometry": {"coordinates":[4.0996761322,50.4494552612],"type":"Point"}
}