{
  "type": "Feature",
  "properties": {
    "iso:country":"BE",
    "sg:address":"Barsy 5",
    "sg:city":"Havelange (flostoy)",
    "sg:classifiers":[
        {
            "category":"Food & Beverages",
            "subcategory":"Specialty",
            "type":"Retail Goods"
        }
    ],
    "sg:phone":"+32 83 61 11 69",
    "sg:postcode":"5370",
    "sg:province":"Namur",
    "sg:tags":[
        "health",
        "dietary",
        "-",
        "biological"
    ],
    "wof:name":"Sepulchre I",
    "wof:placetype":"venue"
},
  "geometry": {"coordinates":[5.1521692276,50.3848838806],"type":"Point"}
}