{
  "type": "Feature",
  "properties": {
    "iso:country":"BE",
    "sg:address":"Bredabaan 1065",
    "sg:city":"Wuustwezel",
    "sg:classifiers":[
        {
            "category":"Retail",
            "subcategory":"Veterinary Services",
            "type":"Services"
        }
    ],
    "sg:phone":"+32 3 633 14 16",
    "sg:postcode":"2990",
    "sg:province":"Antwerpen",
    "sg:tags":[
        "veterinarian"
    ],
    "wof:name":"Peluso Ann Katrien",
    "wof:placetype":"venue"
},
  "geometry": {"coordinates":[4.5357441902,51.34425354],"type":"Point"}
}