{
  "type": "Feature",
  "properties": {
    "addr:full":"Lombaardstraat 79 Sint-katelijne-waver Antwerpen 2860",
    "addr:housenumber":"79",
    "addr:postcode":"2860",
    "addr:street":"Lombaardstraat",
    "iso:country":"BE",
    "sg:address":"Lombaardstraat 79",
    "sg:city":"Sint-katelijne-waver",
    "sg:classifiers":[
        {
            "category":"Professional",
            "subcategory":"Accounting & Tax Preparation",
            "type":"Services"
        }
    ],
    "sg:phone":"+32 15 23 73 89",
    "sg:postcode":"2860",
    "sg:province":"Antwerpen",
    "sg:tags":[
        "bookkeeper"
    ],
    "wof:name":"Hellemans E",
    "wof:placetype":"venue"
},
  "geometry": {"coordinates":[4.5379548073,51.0513038635],"type":"Point"}
}