{
  "type": "Feature",
  "properties": {
    "iso:country":"BE",
    "sg:address":"Rue De Bouttignies 26",
    "sg:city":"Erquelinnes (grand-reng)",
    "sg:classifiers":[
        {
            "category":"Building & Trades",
            "subcategory":"Landscaping Services",
            "type":"Services"
        }
    ],
    "sg:phone":"+32 64 77 23 94",
    "sg:postcode":"6560",
    "sg:province":"Hainaut",
    "sg:tags":[
        "nurseryman"
    ],
    "wof:name":"La Couture De L'orme",
    "wof:placetype":"venue"
},
  "geometry": {"coordinates":[4.0797791481,50.3330574036],"type":"Point"}
}