{
  "type": "Feature",
  "properties": {
    "iso:country":"BE",
    "sg:address":"Rue De L'eglise 72",
    "sg:city":"Raeren/raeren",
    "sg:orig_category":"Installation de menuiserie en bois and plastique",
    "sg:phone":"+32 87 63 07 64",
    "sg:postcode":"4730",
    "sg:province":"Li\u00e8ge",
    "wof:name":"Edgard Lauffs",
    "wof:placetype":"venue"
},
  "geometry": {"coordinates":[6.1511101723,50.650188446],"type":"Point"}
}