{
  "type": "Feature",
  "properties": {
    "addr:full":"Av. Du Ruisseau Du Godru 21 Wavre Brabant Wallon 1300",
    "addr:housenumber":"21;1300",
    "addr:street":"Av. Du Ruisseau Du Godru",
    "iso:country":"BE",
    "sg:address":"Av. Du Ruisseau Du Godru 21",
    "sg:city":"Wavre",
    "sg:orig_category":"Plomberie, chauffage and installations sanitaires",
    "sg:phone":"+32 10 22 48 94",
    "sg:postcode":"1300",
    "sg:province":"Brabant Wallon",
    "wof:name":"Chauffage Services",
    "wof:placetype":"venue"
},
  "geometry": {"coordinates":[4.6212029457,50.7143173218],"type":"Point"}
}