{
  "type": "Feature",
  "properties": {
    "addr:full":"Prins Boudewijnlaan 247 Edegem Antwerpen 2650",
    "addr:housenumber":"247",
    "addr:postcode":"2650",
    "addr:street":"Prins Boudewijnlaan",
    "iso:country":"BE",
    "sg:address":"Prins Boudewijnlaan 247",
    "sg:city":"Edegem",
    "sg:orig_category":"Immobili\u00ebnkantoren",
    "sg:phone":"+32 3 448 26 85",
    "sg:postcode":"2650",
    "sg:province":"Antwerpen",
    "wof:name":"Immo Flanders",
    "wof:placetype":"venue"
},
  "geometry": {"coordinates":[4.4296011925,51.1588249207],"type":"Point"}
}