{
  "type": "Feature",
  "properties": {
    "addr:full":"Noordstraat 27 Kortrijk West-Vlaanderen 8500",
    "addr:housenumber":"27",
    "addr:postcode":"8500",
    "addr:street":"Noordstraat",
    "iso:country":"BE",
    "sg:address":"Noordstraat 27",
    "sg:city":"Kortrijk",
    "sg:classifiers":[
        {
            "category":"Shopping",
            "subcategory":"Pets & Pet Supplies",
            "type":"Retail Goods"
        }
    ],
    "sg:phone":"+32 56 36 09 95",
    "sg:postcode":"8500",
    "sg:province":"West-Vlaanderen",
    "sg:tags":[
        "aquarium",
        "accessory"
    ],
    "wof:name":"Aquarium-center Kortrijk Bvba",
    "wof:placetype":"venue"
},
  "geometry": {"coordinates":[3.2554380894,50.8304290771],"type":"Point"}
}