{
  "type": "Feature",
  "properties": {
    "addr:full":"Stationsstraat 247 Herzele Oost-Vlaanderen 9550",
    "addr:housenumber":"247",
    "addr:postcode":"9550",
    "addr:street":"Stationsstraat;Oost-Vlaanderen",
    "iso:country":"BE",
    "sg:address":"Stationsstraat 247",
    "sg:city":"Herzele",
    "sg:orig_category":"Apotheken",
    "sg:phone":"+32 53 63 07 12",
    "sg:postcode":"9550",
    "sg:province":"Oost-Vlaanderen",
    "wof:name":"Van Bellinghen",
    "wof:placetype":"venue"
},
  "geometry": {"coordinates":[3.8802061081,50.8976097107],"type":"Point"}
}