{
  "type": "Feature",
  "properties": {
    "addr:full":"Planchestraat 19 Vloesberg/flobecq Hainaut 7880",
    "addr:housenumber":"19",
    "addr:postcode":"7880",
    "addr:street":"Planchestraat;Hainaut",
    "iso:country":"BE",
    "sg:address":"Planchestraat 19",
    "sg:city":"Vloesberg/flobecq",
    "sg:orig_category":"Kantoormateriaal",
    "sg:phone":"+32 68 44 79 07",
    "sg:postcode":"7880",
    "sg:province":"Hainaut",
    "wof:name":"Guy Marchal",
    "wof:placetype":"venue"
},
  "geometry": {"coordinates":[3.7247760296,50.7434196472],"type":"Point"}
}