{
  "type": "Feature",
  "properties": {
    "iso:country":"BE",
    "sg:address":"Koolmijnlaan 433",
    "sg:city":"Heusden-zolder",
    "sg:classifiers":[
        {
            "category":"Cafe",
            "type":"Food & Drink"
        }
    ],
    "sg:phone":"+32 11 57 38 91",
    "sg:postcode":"3550",
    "sg:province":"Limburg",
    "sg:tags":[
        "caf\u00e9s"
    ],
    "wof:name":"Rena Dancing",
    "wof:placetype":"venue"
},
  "geometry": {"coordinates":[5.3139648438,51.0231018066],"type":"Point"}
}