{
  "type": "Feature",
  "properties": {
    "addr:full":"Rue De Beaumont 45 Charleroi Hainaut 6030",
    "addr:housenumber":"45",
    "addr:postcode":"6030",
    "addr:street":"Rue De Beaumont;Hainaut",
    "iso:country":"BE",
    "sg:address":"Rue De Beaumont 45",
    "sg:city":"Charleroi",
    "sg:orig_category":"Banken and kredietinstellingen",
    "sg:phone":"+32 71 51 55 56",
    "sg:postcode":"6030",
    "sg:province":"Hainaut",
    "wof:name":"Fortis",
    "wof:placetype":"venue"
},
  "geometry": {"coordinates":[4.3958601952,50.4048919678],"type":"Point"}
}