{
  "type": "Feature",
  "properties": {
    "addr:full":"Wilgenbaan 73 Grimbergen Vlaams-Brabant 1850",
    "addr:housenumber":"73",
    "addr:postcode":"1850",
    "addr:street":"Wilgenbaan",
    "iso:country":"BE",
    "sg:address":"Wilgenbaan 73",
    "sg:city":"Grimbergen",
    "sg:classifiers":[
        {
            "category":"Military Area",
            "subcategory":"Air Force Base",
            "type":"Public Place"
        }
    ],
    "sg:phone":"+32 2 268 65 00",
    "sg:postcode":"1850",
    "sg:province":"Vlaams-Brabant",
    "sg:tags":[
        "water",
        "treatment"
    ],
    "wof:name":"Living Water Sprl",
    "wof:placetype":"venue"
},
  "geometry": {"coordinates":[4.364276886,50.9223861694],"type":"Point"}
}