{
  "type": "Feature",
  "properties": {
    "iso:country":"BE",
    "sg:address":"Rue De Malonne 6a",
    "sg:city":"Floreffe",
    "sg:classifiers":[
        {
            "category":"Professional",
            "subcategory":"Management & Consulting",
            "type":"Services"
        }
    ],
    "sg:phone":"+32 81 44 58 88",
    "sg:postcode":"5150",
    "sg:province":"Namur",
    "sg:tags":[
        "consultant"
    ],
    "wof:name":"Phil Management Sa",
    "wof:placetype":"venue"
},
  "geometry": {"coordinates":[4.78166008,50.4203262329],"type":"Point"}
}