{
  "type": "Feature",
  "properties": {
    "addr:full":"Rue Marie-delcourt 24 Arlon Luxembourg 6700",
    "addr:housenumber":"24",
    "addr:postcode":"6700",
    "addr:street":"Rue Marie-Delcourt",
    "iso:country":"BE",
    "sg:address":"Rue Marie-delcourt 24",
    "sg:city":"Arlon",
    "sg:orig_category":"Rundveehouders",
    "sg:phone":"+32 63 21 77 48",
    "sg:postcode":"6700",
    "sg:province":"Luxembourg",
    "wof:name":"Fernand Friob",
    "wof:placetype":"venue"
},
  "geometry": {"coordinates":[5.8071889877,49.6620635986],"type":"Point"}
}