{
  "type": "Feature",
  "properties": {
    "iso:country":"BE",
    "sg:address":"Pastorijstraat 58",
    "sg:city":"Tielt",
    "sg:orig_category":"Elektrische installaties voor woningen",
    "sg:phone":"+32 51 63 64 35",
    "sg:postcode":"8700",
    "sg:province":"West-Vlaanderen",
    "wof:name":"Gert Vandenheede",
    "wof:placetype":"venue"
},
  "geometry": {"coordinates":[3.4258589745,50.993434906],"type":"Point"}
}