{
  "type": "Feature",
  "properties": {
    "addr:full":"Rue De Crahiat 20 Ciney Namur 5590",
    "addr:housenumber":"20",
    "addr:postcode":"5590",
    "addr:street":"Rue De Crahiat",
    "iso:country":"BE",
    "sg:address":"Rue De Crahiat 20",
    "sg:city":"Ciney",
    "sg:classifiers":[
        {
            "category":"Bars & Pubs",
            "type":"Food & Drink"
        }
    ],
    "sg:phone":"+32 83 65 74 45",
    "sg:postcode":"5590",
    "sg:province":"Namur",
    "wof:name":"Rimbaud (le)",
    "wof:placetype":"venue"
},
  "geometry": {"coordinates":[5.0916061401,50.2895736694],"type":"Point"}
}