{
  "type": "Feature",
  "properties": {
    "iso:country":"BE",
    "sg:address":"Gildekamersstraat 2",
    "sg:city":"Antwerpen",
    "sg:orig_category":"Musea and historische gebouwen",
    "sg:phone":"+32 3 232 94 09",
    "sg:postcode":"2000",
    "sg:province":"Antwerpen",
    "wof:name":"Volkskundemuseum",
    "wof:placetype":"venue"
},
  "geometry": {"coordinates":[4.3988618851,51.2215919495],"type":"Point"}
}