{
  "type": "Feature",
  "properties": {
    "addr:full":"Schotensteenweg 93b Brecht Antwerpen 2960",
    "addr:housenumber":"93b",
    "addr:postcode":"2960",
    "addr:street":"Schotensteenweg",
    "iso:country":"BE",
    "sg:address":"Schotensteenweg 93b",
    "sg:city":"Brecht",
    "sg:classifiers":[
        {
            "category":"Banks & Credit Unions",
            "subcategory":"Investment Brokerage",
            "type":"Services"
        }
    ],
    "sg:phone":"+32 3 290 32 90",
    "sg:postcode":"2960",
    "sg:province":"Antwerpen",
    "sg:tags":[
        "auditor"
    ],
    "wof:name":"Van Elsacker L",
    "wof:placetype":"venue"
},
  "geometry": {"coordinates":[4.6124401093,51.3343200684],"type":"Point"}
}