{
  "type": "Feature",
  "properties": {
    "iso:country":"BE",
    "sg:address":"Rue De La Gare 49",
    "sg:city":"Komen-waasten/comines-warneton",
    "sg:classifiers":[
        {
            "category":"Shopping",
            "subcategory":"Clothing, Apparel, & Fashions",
            "type":"Retail Goods"
        }
    ],
    "sg:phone":"+32 56 55 50 79",
    "sg:postcode":"7780",
    "sg:province":"Hainaut",
    "sg:tags":[
        "lingerie",
        "sous-v\u00eatements"
    ],
    "wof:name":"Maison Agnes",
    "wof:placetype":"venue"
},
  "geometry": {"coordinates":[2.9971749783,50.7715950012],"type":"Point"}
}