{
  "type": "Feature",
  "properties": {
    "addr:full":"Pr\u00e9 Messire 12 Stavelot Li\u00e8ge 4970",
    "addr:housenumber":"12",
    "addr:postcode":"4970",
    "addr:street":"Pre\u0301 Messire",
    "iso:country":"BE",
    "sg:address":"Pr\u00e9 Messire 12",
    "sg:city":"Stavelot",
    "sg:classifiers":[
        {
            "category":"Building & Trades",
            "subcategory":"Electrical",
            "type":"Services"
        }
    ],
    "sg:phone":"+32 80 86 22 83",
    "sg:postcode":"4970",
    "sg:province":"Li\u00e8ge",
    "sg:tags":[
        "electric",
        "-",
        "housewiring",
        "contractor"
    ],
    "wof:name":"Delvaux Y",
    "wof:placetype":"venue"
},
  "geometry": {"coordinates":[5.938231945,50.3951683044],"type":"Point"}
}