{
  "type": "Feature",
  "properties": {
    "addr:full":"Broekstraat 29 Arendonk Antwerpen 2370",
    "addr:housenumber":"29",
    "addr:postcode":"2370",
    "addr:street":"Broekstraat",
    "iso:country":"BE",
    "sg:address":"Broekstraat 29",
    "sg:city":"Arendonk",
    "sg:orig_category":"Varkenskwekers",
    "sg:phone":"+32 14 67 97 03",
    "sg:postcode":"2370",
    "sg:province":"Antwerpen",
    "wof:name":"Ivo Van Olmen",
    "wof:placetype":"venue"
},
  "geometry": {"coordinates":[5.0737352371,51.3077468872],"type":"Point"}
}