{
  "type": "Feature",
  "properties": {
    "addr:full":"Antwerpsesteenweg 381 Lier Antwerpen 2500",
    "addr:housenumber":"381",
    "addr:postcode":"2500",
    "addr:street":"Antwerpsesteenweg",
    "iso:country":"BE",
    "sg:address":"Antwerpsesteenweg 381",
    "sg:city":"Lier",
    "sg:classifiers":[
        {
            "category":"Health Services",
            "subcategory":"Health Practitioner",
            "type":"Services"
        }
    ],
    "sg:phone":"+32 3 480 01 02",
    "sg:postcode":"2500",
    "sg:province":"Antwerpen",
    "sg:tags":[
        "physiotherapist"
    ],
    "wof:name":"Sels Jan",
    "wof:placetype":"venue"
},
  "geometry": {"coordinates":[4.5469532013,51.1431427002],"type":"Point"}
}