{
  "type": "Feature",
  "properties": {
    "addr:full":"Genieskensstraat 151 Maasmechelen Limburg 3630",
    "addr:housenumber":"151",
    "addr:postcode":"3630",
    "addr:street":"Genieskensstraat",
    "iso:country":"BE",
    "sg:address":"Genieskensstraat 151",
    "sg:city":"Maasmechelen",
    "sg:orig_category":"Offices du tourisme",
    "sg:phone":"+32 89 75 76 12",
    "sg:postcode":"3630",
    "sg:province":"Limburg",
    "wof:name":"Toerisme Maasland",
    "wof:placetype":"venue"
},
  "geometry": {"coordinates":[5.6961350441,50.963848114],"type":"Point"}
}