{
  "type": "Feature",
  "properties": {
    "iso:country":"BE",
    "sg:address":"Stoffezandstraat 16",
    "sg:city":"Wuustwezel",
    "sg:orig_category":"Banken and kredietinstellingen",
    "sg:phone":"+32 3 669 83 11",
    "sg:postcode":"2990",
    "sg:province":"Antwerpen",
    "wof:name":"Fortis",
    "wof:placetype":"venue"
},
  "geometry": {"coordinates":[4.6423559189,51.3991317749],"type":"Point"}
}