{
  "type": "Feature",
  "properties": {
    "iso:country":"BE",
    "sg:address":"Rue De La Pin\u00e8de 44",
    "sg:city":"Namur (w\u00e9pion)",
    "sg:classifiers":[
        {
            "category":"Wholesale",
            "subcategory":"Medical Equipment & Supplies",
            "type":"Manufacturing & Wholesale Goods"
        }
    ],
    "sg:phone":"+32 81 47 01 37",
    "sg:postcode":"5100",
    "sg:province":"Namur",
    "sg:tags":[
        "aid",
        "hearing"
    ],
    "wof:name":"Centre Auditif Leclerq",
    "wof:placetype":"venue"
},
  "geometry": {"coordinates":[4.8691620827,50.4218254089],"type":"Point"}
}