{
  "type": "Feature",
  "properties": {
    "iso:country":"BE",
    "sg:address":"Tulpenstraat 2",
    "sg:city":"Ledegem",
    "sg:classifiers":[
        {
            "category":"Fast Food",
            "type":"Food & Drink"
        }
    ],
    "sg:phone":"+32 56 50 24 16",
    "sg:postcode":"8880",
    "sg:province":"West-Vlaanderen",
    "sg:tags":[
        "meeneem",
        "restaurant"
    ],
    "wof:name":"Bogaert",
    "wof:placetype":"venue"
},
  "geometry": {"coordinates":[3.1450641155,50.8707389832],"type":"Point"}
}