{
  "type": "Feature",
  "properties": {
    "iso:country":"BE",
    "sg:address":"Rue Des Garennes 86",
    "sg:city":"Watermaal-bosvoorde/watermael-boitsfort",
    "sg:orig_category":"Parfumeries",
    "sg:phone":"+32 2 672 82 27",
    "sg:postcode":"1170",
    "sg:province":"Bruxelles-Capitale",
    "wof:name":"Fe. Karina",
    "wof:placetype":"venue"
},
  "geometry": {"coordinates":[4.4158530235,50.802154541],"type":"Point"}
}