{
  "type": "Feature",
  "properties": {
    "addr:full":"Varkensmarkt 22 Diepenbeek Limburg 3590",
    "addr:housenumber":"22",
    "addr:postcode":"3590",
    "addr:street":"Varkensmarkt",
    "iso:country":"BE",
    "sg:address":"Varkensmarkt 22",
    "sg:city":"Diepenbeek",
    "sg:classifiers":[
        {
            "category":"Food & Beverages",
            "subcategory":"Fruits & Vegetables",
            "type":"Retail Goods"
        }
    ],
    "sg:phone":"+32 11 33 25 69",
    "sg:postcode":"3590",
    "sg:province":"Limburg",
    "sg:tags":[
        "-"
    ],
    "wof:name":"Appeltje ('t)",
    "wof:placetype":"venue"
},
  "geometry": {"coordinates":[5.4183630943,50.9080581665],"type":"Point"}
}