{
  "type": "Feature",
  "properties": {
    "iso:country":"BE",
    "sg:address":"Onderdijke 28",
    "sg:city":"Maldegem",
    "sg:orig_category":"Rundveehouders",
    "sg:phone":"+32 50 71 48 20",
    "sg:postcode":"9991",
    "sg:province":"Oost-Vlaanderen",
    "wof:name":"Achiel Ryckaert",
    "wof:placetype":"venue"
},
  "geometry": {"coordinates":[3.4904639721,51.1728401184],"type":"Point"}
}