{
  "type": "Feature",
  "properties": {
    "addr:full":"Kuilstraat 1 Erpe-mere Oost-Vlaanderen 9420",
    "addr:housenumber":"1",
    "addr:postcode":"9420",
    "addr:street":"Kuilstraat",
    "iso:country":"BE",
    "sg:address":"Kuilstraat 1",
    "sg:city":"Erpe-mere",
    "sg:classifiers":[
        {
            "category":"Travel",
            "subcategory":"Hotels & Motels",
            "type":"Entertainment"
        }
    ],
    "sg:phone":"+32 53 80 53 66",
    "sg:postcode":"9420",
    "sg:province":"Oost-Vlaanderen",
    "sg:tags":[
        "restaurant"
    ],
    "wof:name":"Restaurant Bovendael",
    "wof:placetype":"venue"
},
  "geometry": {"coordinates":[3.9554889202,50.9407691956],"type":"Point"}
}