{
  "type": "Feature",
  "properties": {
    "addr:full":"Burchtlaan 16 Lubbeek Vlaams-Brabant 3210",
    "addr:housenumber":"16",
    "addr:postcode":"3210",
    "addr:street":"Burchtlaan",
    "iso:country":"BE",
    "sg:address":"Burchtlaan 16",
    "sg:city":"Lubbeek",
    "sg:orig_category":"Advocaten and juridische adviseurs",
    "sg:phone":"+32 16 26 00 03",
    "sg:postcode":"3210",
    "sg:province":"Vlaams-Brabant",
    "wof:name":"Robrecht Tas",
    "wof:placetype":"venue"
},
  "geometry": {"coordinates":[4.763657093,50.9040679932],"type":"Point"}
}