{
  "type": "Feature",
  "properties": {
    "iso:country":"BE",
    "sg:address":"Swinnenwijerweg 10",
    "sg:city":"Genk",
    "sg:orig_category":"Transports routiers de marchandises",
    "sg:phone":"+32 89 35 91 73",
    "sg:postcode":"3600",
    "sg:province":"Limburg",
    "wof:name":"Genker Transport",
    "wof:placetype":"venue"
},
  "geometry": {"coordinates":[5.5056190491,50.9391746521],"type":"Point"}
}