{
  "type": "Feature",
  "properties": {
    "addr:full":"Avenue Blonden 80b12 Li\u00c8ge Li\u00e8ge 4000",
    "addr:housenumber":"80b12",
    "addr:postcode":"4000",
    "addr:street":"Avenue Blonden",
    "iso:country":"BE",
    "sg:address":"Avenue Blonden 80b12",
    "sg:city":"Li\u00c8ge",
    "sg:orig_category":"M\u00e9decins and sp\u00e9cialistes",
    "sg:phone":"+32 4 387 44 52",
    "sg:postcode":"4000",
    "sg:province":"Li\u00e8ge",
    "wof:name":"Jean Lerusse",
    "wof:placetype":"venue"
},
  "geometry": {"coordinates":[5.5717110634,50.6277122498],"type":"Point"}
}