{
  "type": "Feature",
  "properties": {
    "addr:full":"Beverestraat 120 Oudenaarde Oost-Vlaanderen 9700",
    "addr:housenumber":"120",
    "addr:postcode":"9700",
    "addr:street":"Beverestraat",
    "iso:country":"BE",
    "sg:address":"Beverestraat 120",
    "sg:city":"Oudenaarde",
    "sg:classifiers":[
        {
            "category":"Real Estate",
            "subcategory":"Real Estate Services",
            "type":"Services"
        }
    ],
    "sg:phone":"+32 55 30 16 13",
    "sg:postcode":"9700",
    "sg:province":"Oost-Vlaanderen",
    "wof:name":"Vossimmo Nv",
    "wof:placetype":"venue"
},
  "geometry": {"coordinates":[3.5957760811,50.8509635925],"type":"Point"}
}