{
  "type": "Feature",
  "properties": {
    "addr:full":"Rue De Mons 25 Box 26 Charleroi Hainaut 6000",
    "addr:housenumber":"25 box 26",
    "addr:postcode":"6000",
    "addr:street":"Rue De Mons;Hainaut",
    "iso:country":"BE",
    "sg:address":"Rue De Mons 25 Box 26",
    "sg:city":"Charleroi",
    "sg:classifiers":[
        {
            "category":"Professional",
            "subcategory":"Business Services",
            "type":"Services"
        }
    ],
    "sg:phone":"+32 71 20 49 49",
    "sg:postcode":"6000",
    "sg:province":"Hainaut",
    "sg:tags":[
        "automobile",
        "-",
        "assessor"
    ],
    "wof:name":"Jacquet Bureau D'expertises Techniques Sa",
    "wof:placetype":"venue"
},
  "geometry": {"coordinates":[4.4352698326,50.4122581482],"type":"Point"}
}