{
  "type": "Feature",
  "properties": {
    "addr:full":"Doornikserijksweg 97 Kortrijk West-Vlaanderen 8510",
    "addr:housenumber":"97",
    "addr:postcode":"8510",
    "addr:street":"Doornikserijksweg",
    "iso:country":"BE",
    "sg:address":"Doornikserijksweg 97",
    "sg:city":"Kortrijk",
    "sg:orig_category":"HUISBRANDOLIE",
    "sg:phone":"+32 56 25 83 89",
    "sg:postcode":"8510",
    "sg:province":"West-Vlaanderen",
    "wof:name":"Verleye K.",
    "wof:placetype":"venue"
},
  "geometry": {"coordinates":[3.312292099,50.7570266724],"type":"Point"}
}