{
  "type": "Feature",
  "properties": {
    "addr:full":"Renier Sniedersstraat 9 Turnhout Antwerpen 2300",
    "addr:housenumber":"9",
    "addr:postcode":"2300",
    "addr:street":"Renier Sniedersstraat",
    "iso:country":"BE",
    "sg:address":"Renier Sniedersstraat 9",
    "sg:city":"Turnhout",
    "sg:orig_category":"Brood, gebak and snoepgoed",
    "sg:phone":"+32 14 41 27 10",
    "sg:postcode":"2300",
    "sg:province":"Antwerpen",
    "wof:name":"Josephus Van Der Moeren",
    "wof:placetype":"venue"
},
  "geometry": {"coordinates":[4.942688942,51.3226623535],"type":"Point"}
}