{
  "type": "Feature",
  "properties": {
    "iso:country":"BE",
    "sg:address":"Nieuwstraat 1",
    "sg:city":"Bilzen",
    "sg:orig_category":"Sportclubs",
    "sg:phone":"+32 89 50 28 49",
    "sg:postcode":"3740",
    "sg:province":"Limburg",
    "wof:name":"Fordvrienden Limburg",
    "wof:placetype":"venue"
},
  "geometry": {"coordinates":[5.5086240768,50.8675270081],"type":"Point"}
}