{
  "type": "Feature",
  "properties": {
    "addr:full":"Rue De Marbais 10 Villers-la-ville Brabant Wallon 1495",
    "addr:housenumber":"10",
    "addr:postcode":"1495",
    "addr:street":"Rue De Marbais",
    "iso:country":"BE",
    "sg:address":"Rue De Marbais 10",
    "sg:city":"Villers-la-ville",
    "sg:classifiers":[
        {
            "category":"Bakery",
            "type":"Food & Drink"
        }
    ],
    "sg:phone":"+32 71 87 52 65",
    "sg:postcode":"1495",
    "sg:province":"Brabant Wallon",
    "sg:tags":[
        "confectioner",
        "baker"
    ],
    "wof:name":"Lonbois J.l.",
    "wof:placetype":"venue"
},
  "geometry": {"coordinates":[4.5312547684,50.5762290955],"type":"Point"}
}