{
  "type": "Feature",
  "properties": {
    "addr:full":"Boulevard Emile Bockstael 10 Bruxelles Bruxelles-Capitale 1020",
    "addr:housenumber":"10",
    "addr:postcode":"1020",
    "addr:street":"Boulevard Emile Bockstael",
    "iso:country":"BE",
    "sg:address":"Boulevard Emile Bockstael 10",
    "sg:city":"Bruxelles",
    "sg:classifiers":[
        {
            "category":"Professional",
            "subcategory":"Business Services",
            "type":"Services"
        }
    ],
    "sg:phone":"+32 2 424 04 77",
    "sg:postcode":"1020",
    "sg:province":"Bruxelles-Capitale",
    "sg:tags":[
        "agency",
        "export"
    ],
    "wof:name":"Distri One S.a.",
    "wof:placetype":"venue"
},
  "geometry": {"coordinates":[4.3431649208,50.8705406189],"type":"Point"}
}