{
  "type": "Feature",
  "properties": {
    "iso:country":"BE",
    "sg:address":"Heilaakstraat 5b13",
    "sg:city":"Aarschot",
    "sg:orig_category":"Instellingen voor mindervalide volwassenen",
    "sg:phone":"+32 16 56 56 75",
    "sg:postcode":"3200",
    "sg:province":"Vlaams-Brabant",
    "wof:name":"Huize Eigen Haard",
    "wof:placetype":"venue"
},
  "geometry": {"coordinates":[4.8393201828,50.9933204651],"type":"Point"}
}