{
  "type": "Feature",
  "properties": {
    "addr:full":"Eden City 17 Bruxelles (forest) Bruxelles-Capitale 1190",
    "addr:housenumber":"17",
    "addr:postcode":"1190",
    "addr:street":"Eden City",
    "iso:country":"BE",
    "sg:address":"Eden City 17",
    "sg:city":"Bruxelles (forest)",
    "sg:classifiers":[
        {
            "category":"Real Estate",
            "subcategory":"Architect",
            "type":"Services"
        }
    ],
    "sg:phone":"+32 2 219 81 15",
    "sg:postcode":"1190",
    "sg:province":"Bruxelles-Capitale",
    "wof:name":"Claessens E",
    "wof:placetype":"venue"
},
  "geometry": {"coordinates":[4.3308238983,50.8213653564],"type":"Point"}
}