{
  "type": "Feature",
  "properties": {
    "iso:country":"BE",
    "sg:address":"Rue Verw\u00e9e 20",
    "sg:city":"Bruxelles (schaerbeek)",
    "sg:classifiers":[
        {
            "category":"Shopping",
            "subcategory":"Discount & Variety Stores",
            "type":"Retail Goods"
        }
    ],
    "sg:phone":"+32 2 215 24 45",
    "sg:postcode":"1030",
    "sg:province":"Bruxelles-Capitale",
    "sg:tags":[
        "shop",
        "clearers",
        "curiosity",
        "furniture"
    ],
    "wof:name":"Ghibeche",
    "wof:placetype":"venue"
},
  "geometry": {"coordinates":[4.3746209145,50.8665771484],"type":"Point"}
}