{
  "type": "Feature",
  "properties": {
    "iso:country":"BE",
    "sg:address":"Rue Louvrex 109",
    "sg:city":"Li\u00c8ge",
    "sg:orig_category":"Editeurs de journaux. Editeurs de revues and p\u00e9riodiques",
    "sg:phone":"+32 4 223 50 12",
    "sg:postcode":"4000",
    "sg:province":"Li\u00e8ge",
    "wof:name":"Bureau April",
    "wof:placetype":"venue"
},
  "geometry": {"coordinates":[5.5646867752,50.633190155],"type":"Point"}
}