{
  "type": "Feature",
  "properties": {
    "addr:full":"Chauss\u00c9e De Marche 790 Namur Namur 5100",
    "addr:housenumber":"790",
    "addr:postcode":"5100",
    "addr:street":"Chausse\u0301E De Marche",
    "iso:country":"BE",
    "sg:address":"Chauss\u00c9e De Marche 790",
    "sg:city":"Namur",
    "sg:orig_category":"Benzinestations and brandstoffen Herstellingen and onderhoud aan huis voor voertuigen Herstellingen ",
    "sg:phone":"+32 81 40 18 19",
    "sg:postcode":"5100",
    "sg:province":"Namur",
    "wof:name":"Comp\u00c8re Luc",
    "wof:placetype":"venue"
},
  "geometry": {"coordinates":[4.8713750839,50.4566345215],"type":"Point"}
}