{
  "type": "Feature",
  "properties": {
    "addr:full":"Route De Huy 85 Lincent Li\u00e8ge 4287",
    "addr:housenumber":"85",
    "addr:postcode":"4287",
    "addr:street":"Route De Huy",
    "iso:country":"BE",
    "sg:address":"Route De Huy 85",
    "sg:city":"Lincent",
    "sg:orig_category":"Banques and organismes de cr\u00e9dit",
    "sg:phone":"+32 19 63 47 61",
    "sg:postcode":"4287",
    "sg:province":"Li\u00e8ge",
    "wof:name":"Dexia",
    "wof:placetype":"venue"
},
  "geometry": {"coordinates":[5.0350809097,50.7136230469],"type":"Point"}
}