{
  "type": "Feature",
  "properties": {
    "addr:full":"Havermarkt 19 Hasselt Limburg 3500",
    "addr:housenumber":"19",
    "addr:postcode":"3500",
    "addr:street":"Havermarkt",
    "iso:country":"BE",
    "sg:address":"Havermarkt 19",
    "sg:city":"Hasselt",
    "sg:classifiers":[
        {
            "category":"Food & Beverages",
            "subcategory":"Fruits & Vegetables",
            "type":"Retail Goods"
        }
    ],
    "sg:phone":"+32 11 22 71 20",
    "sg:postcode":"3500",
    "sg:province":"Limburg",
    "sg:tags":[
        "-"
    ],
    "wof:name":"Vitamientje ('t)",
    "wof:placetype":"venue"
},
  "geometry": {"coordinates":[5.3355798721,50.9294242859],"type":"Point"}
}