{
  "type": "Feature",
  "properties": {
    "addr:full":"Sint-maartensstraat 23ba Olen Antwerpen 2250",
    "addr:housenumber":"23ba",
    "addr:postcode":"2250",
    "addr:street":"Sint-Maartensstraat",
    "iso:country":"BE",
    "sg:address":"Sint-maartensstraat 23ba",
    "sg:city":"Olen",
    "sg:orig_category":"Kinderopvang",
    "sg:phone":"+32 14 26 26 59",
    "sg:postcode":"2250",
    "sg:province":"Antwerpen",
    "wof:name":"Dienst Opvanggezinnen",
    "wof:placetype":"venue"
},
  "geometry": {"coordinates":[4.8575668335,51.1439361572],"type":"Point"}
}