{
  "type": "Feature",
  "properties": {
    "iso:country":"BE",
    "sg:address":"Avenue De La Faiencerie 2",
    "sg:city":"Mons",
    "sg:orig_category":"Meubles D\u00e9taillants, Am\u00e9nagement de B\u00e2timents et de Cuisines",
    "sg:phone":"+32 65 82 20 79",
    "sg:postcode":"7012",
    "sg:province":"Hainaut",
    "wof:name":"Meubles Lecomte",
    "wof:placetype":"venue"
},
  "geometry": {"coordinates":[3.9595210552,50.4641418457],"type":"Point"}
}