{
  "type": "Feature",
  "properties": {
    "addr:full":"Grote Markt 101 Zelzate Oost-Vlaanderen 9060",
    "addr:housenumber":"101",
    "addr:postcode":"9060",
    "addr:street":"Grote Markt",
    "iso:country":"BE",
    "sg:address":"Grote Markt 101",
    "sg:city":"Zelzate",
    "sg:orig_category":"Tabac",
    "sg:phone":"+32 9 345 79 25",
    "sg:postcode":"9060",
    "sg:province":"Oost-Vlaanderen",
    "wof:name":"Van Raemdonck En Co",
    "wof:placetype":"venue"
},
  "geometry": {"coordinates":[3.812212944,51.199344635],"type":"Point"}
}