{
  "type": "Feature",
  "properties": {
    "addr:full":"Lindenlaan 18 Evergem Oost-Vlaanderen 9940",
    "addr:housenumber":"18",
    "addr:postcode":"9940",
    "addr:street":"Lindenlaan;Oost-Vlaanderen",
    "iso:country":"BE",
    "sg:address":"Lindenlaan 18",
    "sg:city":"Evergem",
    "sg:orig_category":"Boucheries",
    "sg:phone":"+32 9 344 98 34",
    "sg:postcode":"9940",
    "sg:province":"Oost-Vlaanderen",
    "wof:name":"Beenhouwerij Geert",
    "wof:placetype":"venue"
},
  "geometry": {"coordinates":[3.7457180023,51.1773490906],"type":"Point"}
}