{
  "type": "Feature",
  "properties": {
    "iso:country":"BE",
    "sg:address":"Avenue Des Gaulois 3",
    "sg:city":"Etterbeek",
    "sg:orig_category":"Werk and personeelsselectie",
    "sg:phone":"+32 2 743 44 80",
    "sg:postcode":"1040",
    "sg:province":"Bruxelles-Capitale",
    "wof:name":"Beaufort",
    "wof:placetype":"venue"
},
  "geometry": {"coordinates":[4.3939390182,50.8381195068],"type":"Point"}
}