{
  "type": "Feature",
  "properties": {
    "addr:full":"Parnassusstraat 2ba Elsene/ixelles Bruxelles-Capitale 1050",
    "addr:housenumber":"2ba",
    "addr:postcode":"1050",
    "addr:street":"Parnassusstraat",
    "iso:country":"BE",
    "sg:address":"Parnassusstraat 2ba",
    "sg:city":"Elsene/ixelles",
    "sg:classifiers":[
        {
            "category":"Restaurant",
            "type":"Food & Drink"
        }
    ],
    "sg:phone":"+32 2 511 40 16",
    "sg:postcode":"1050",
    "sg:province":"Bruxelles-Capitale",
    "wof:name":"La Rose D'asie",
    "wof:placetype":"venue"
},
  "geometry": {"coordinates":[4.3698368073,50.8378067017],"type":"Point"}
}