{
  "type": "Feature",
  "properties": {
    "iso:country":"BE",
    "sg:address":"Eester 17",
    "sg:city":"Brecht",
    "sg:orig_category":"Eleveurs de bovins",
    "sg:phone":"+32 3 313 96 69",
    "sg:postcode":"2960",
    "sg:province":"Antwerpen",
    "wof:name":"Jan Sips",
    "wof:placetype":"venue"
},
  "geometry": {"coordinates":[4.5634040833,51.3149719238],"type":"Point"}
}