{
  "type": "Feature",
  "properties": {
    "addr:full":"Porte D'ogy 39 Lessines Hainaut 7860",
    "addr:housenumber":"39",
    "addr:postcode":"7860",
    "addr:street":"Hainaut",
    "iso:country":"BE",
    "sg:address":"Porte D'ogy 39",
    "sg:city":"Lessines",
    "sg:classifiers":[
        {
            "category":"Retail",
            "subcategory":"Funeral Services",
            "type":"Services"
        }
    ],
    "sg:phone":"+32 68 33 50 44",
    "sg:postcode":"7860",
    "sg:province":"Hainaut",
    "sg:tags":[
        "director"
    ],
    "wof:name":"Plume Claude",
    "wof:placetype":"venue"
},
  "geometry": {"coordinates":[3.8263149261,50.7125015259],"type":"Point"}
}