{
  "type": "Feature",
  "properties": {
    "iso:country":"BE",
    "sg:address":"Overheide 19",
    "sg:city":"Puurs",
    "sg:orig_category":"Producteurs de l\u00e9gumes",
    "sg:phone":"+32 3 889 55 54",
    "sg:postcode":"2870",
    "sg:province":"Antwerpen",
    "wof:name":"Ludovicus Tersago",
    "wof:placetype":"venue"
},
  "geometry": {"coordinates":[4.2728900909,51.0659713745],"type":"Point"}
}