{
  "type": "Feature",
  "properties": {
    "iso:country":"BE",
    "sg:address":"Zevenputtenstraat 5",
    "sg:city":"Zutendaal",
    "sg:classifiers":[
        {
            "category":"Structure",
            "subcategory":"Building",
            "type":"Public Place"
        }
    ],
    "sg:phone":"+32 89 61 27 62",
    "sg:postcode":"3690",
    "sg:province":"Limburg",
    "sg:tags":[
        "apartment"
    ],
    "wof:name":"Bouwbedrijf Wienen Nv",
    "wof:placetype":"venue"
},
  "geometry": {"coordinates":[5.5398440361,50.9203262329],"type":"Point"}
}