{
  "type": "Feature",
  "properties": {
    "addr:full":"Tentoonstellingslaan 86 Gent Oost-Vlaanderen 9000",
    "addr:housenumber":"86",
    "addr:postcode":"9000",
    "addr:street":"Tentoonstellingslaan;Oost-Vlaanderen",
    "iso:country":"BE",
    "sg:address":"Tentoonstellingslaan 86",
    "sg:city":"Gent",
    "sg:classifiers":[
        {
            "category":"Real Estate",
            "subcategory":"Architect",
            "type":"Services"
        }
    ],
    "sg:phone":"+32 9 223 67 67",
    "sg:postcode":"9000",
    "sg:province":"Oost-Vlaanderen",
    "wof:name":"De Langhe V",
    "wof:placetype":"venue"
},
  "geometry": {"coordinates":[3.7314350605,51.0392341614],"type":"Point"}
}