{
  "type": "Feature",
  "properties": {
    "iso:country":"BE",
    "sg:address":"Pontbeek 63",
    "sg:city":"Asse (zellik)",
    "sg:classifiers":[
        {
            "category":"Military Area",
            "subcategory":"Coast Guard Base",
            "type":"Public Place"
        }
    ],
    "sg:phone":"+32 3 325 25 15",
    "sg:postcode":"1731",
    "sg:province":"Vlaams-Brabant",
    "sg:tags":[
        "towers",
        "mast",
        "radio",
        "antenna"
    ],
    "wof:name":"Antwerp Building Consultants Nv",
    "wof:placetype":"venue"
},
  "geometry": {"coordinates":[4.463280201,51.2211112976],"type":"Point"}
}