{
  "type": "Feature",
  "properties": {
    "iso:country":"BE",
    "sg:address":"Antwerpsestraat 124 Box 1",
    "sg:city":"Boom",
    "sg:classifiers":[
        {
            "category":"Health Services",
            "subcategory":"Doctor",
            "type":"Services"
        }
    ],
    "sg:phone":"+32 3 844 74 64",
    "sg:postcode":"2850",
    "sg:province":"Antwerpen",
    "sg:tags":[
        "medicinephysicians",
        "surgeon"
    ],
    "wof:name":"Lambrecht A",
    "wof:placetype":"venue"
},
  "geometry": {"coordinates":[4.3654618263,51.0908966064],"type":"Point"}
}