{
  "type": "Feature",
  "properties": {
    "addr:full":"Leuvensestr 2 Tienen Vlaams-Brabant 3300",
    "addr:housenumber":"2",
    "addr:postcode":"3300",
    "addr:street":"Leuvensestr",
    "iso:country":"BE",
    "sg:address":"Leuvensestr 2",
    "sg:city":"Tienen",
    "sg:classifiers":[
        {
            "category":"Banks & Credit Unions",
            "subcategory":"Bank",
            "type":"Services"
        }
    ],
    "sg:phone":"+32 16 82 32 76",
    "sg:postcode":"3300",
    "sg:province":"Vlaams-Brabant",
    "wof:name":"Banque Bruxelles Lambert Sa",
    "wof:placetype":"venue"
},
  "geometry": {"coordinates":[4.9292068481,50.8096733093],"type":"Point"}
}