{
  "type": "Feature",
  "properties": {
    "iso:country":"BE",
    "sg:address":"Rue De Beauwelz 24",
    "sg:city":"Momignies",
    "sg:orig_category":"Herstelling horloges and juwelen Juwelen and horloges",
    "sg:phone":"+32 60 51 13 86",
    "sg:postcode":"6590",
    "sg:province":"Hainaut",
    "wof:name":"Maison Hosselet",
    "wof:placetype":"venue"
},
  "geometry": {"coordinates":[4.1576910019,50.0241317749],"type":"Point"}
}