{
  "type": "Feature",
  "properties": {
    "iso:country":"BE",
    "sg:address":"Quai De Brabant 37",
    "sg:city":"Charleroi",
    "sg:classifiers":[
        {
            "category":"Recreation",
            "subcategory":"Dance Hall",
            "type":"Entertainment"
        }
    ],
    "sg:phone":"+32 71 33 08 19",
    "sg:postcode":"6000",
    "sg:province":"Hainaut",
    "sg:tags":[
        "discotheque"
    ],
    "wof:name":"Pacha Club",
    "wof:placetype":"venue"
},
  "geometry": {"coordinates":[4.4455041885,50.4053497314],"type":"Point"}
}