{
  "type": "Feature",
  "properties": {
    "addr:full":"Kortrijksesteenweg 205 Box 2 Sint-martens-latem Oost-Vlaanderen 9830",
    "addr:housenumber":"205;2",
    "addr:postcode":"9830",
    "addr:street":"Kortrijksesteenweg;Box",
    "iso:country":"BE",
    "sg:address":"Kortrijksesteenweg 205 Box 2",
    "sg:city":"Sint-martens-latem",
    "sg:classifiers":[
        {
            "category":"Home & Garden",
            "subcategory":"Kitchen Supply",
            "type":"Retail Goods"
        }
    ],
    "sg:phone":"+32 9 383 07 21",
    "sg:postcode":"9830",
    "sg:province":"Oost-Vlaanderen",
    "sg:tags":[
        "installation"
    ],
    "wof:name":"Dl Keukeninterieur",
    "wof:placetype":"venue"
},
  "geometry": {"coordinates":[3.6301860809,51.0074501038],"type":"Point"}
}