{
  "type": "Feature",
  "properties": {
    "addr:full":"Heimolenhoek 3bc Sint-niklaas Oost-Vlaanderen 9100",
    "addr:postcode":"9100",
    "addr:street":"Oost-Vlaanderen",
    "iso:country":"BE",
    "sg:address":"Heimolenhoek 3bc",
    "sg:city":"Sint-niklaas",
    "sg:orig_category":"Production and transformation de viande",
    "sg:phone":"+32 3 776 27 98",
    "sg:postcode":"9100",
    "sg:province":"Oost-Vlaanderen",
    "wof:name":"Paul Van Gucht",
    "wof:placetype":"venue"
},
  "geometry": {"coordinates":[4.1310420036,51.1344299316],"type":"Point"}
}