{
  "type": "Feature",
  "properties": {
    "addr:full":"Rue De Nimy 117 Mons Hainaut 7000",
    "addr:housenumber":"117",
    "addr:postcode":"7000",
    "addr:street":"Rue De Nimy;Hainaut",
    "iso:country":"BE",
    "sg:address":"Rue De Nimy 117",
    "sg:city":"Mons",
    "sg:orig_category":"Supermarkten",
    "sg:phone":"+32 65 34 06 95",
    "sg:postcode":"7000",
    "sg:province":"Hainaut",
    "wof:name":"Ad Delhaize",
    "wof:placetype":"venue"
},
  "geometry": {"coordinates":[3.9554879665,50.4585952759],"type":"Point"}
}