{
  "type": "Feature",
  "properties": {
    "addr:full":"Avenue Richard Neybergh 166 Bruxelles Bruxelles-Capitale 1020",
    "addr:housenumber":"166",
    "addr:postcode":"1020",
    "addr:street":"Avenue Richard Neybergh",
    "iso:country":"BE",
    "sg:address":"Avenue Richard Neybergh 166",
    "sg:city":"Bruxelles",
    "sg:classifiers":[
        {
            "category":"Professional",
            "subcategory":"Computer Services",
            "type":"Services"
        }
    ],
    "sg:phone":"+32 2 420 95 88",
    "sg:postcode":"1020",
    "sg:province":"Bruxelles-Capitale",
    "sg:tags":[
        "-",
        "processing",
        "data",
        "software"
    ],
    "wof:name":"V.b.s.e. Sprl",
    "wof:placetype":"venue"
},
  "geometry": {"coordinates":[4.3426017761,50.8739471436],"type":"Point"}
}