{
  "type": "Feature",
  "properties": {
    "addr:full":"Rue Du Trieu 36 Chi\u00e8vres Hainaut 7950",
    "addr:housenumber":"36",
    "addr:postcode":"7950",
    "addr:street":"Rue Du Trieu;Hainaut",
    "iso:country":"BE",
    "sg:address":"Rue Du Trieu 36",
    "sg:city":"Chi\u00e8vres",
    "sg:classifiers":[
        {
            "category":"Building & Trades",
            "subcategory":"Electrical",
            "type":"Services"
        }
    ],
    "sg:phone":"+32 68 65 86 97",
    "sg:postcode":"7950",
    "sg:province":"Hainaut",
    "sg:tags":[
        "electric",
        "-",
        "housewiring",
        "contractor"
    ],
    "wof:name":"Handrieu Y",
    "wof:placetype":"venue"
},
  "geometry": {"coordinates":[3.8038809299,50.5535011292],"type":"Point"}
}