{
  "type": "Feature",
  "properties": {
    "addr:full":"Rue De Tongres 66 Oupeye Li\u00e8ge 4684",
    "addr:housenumber":"66",
    "addr:postcode":"4684",
    "addr:street":"Rue De Tongres",
    "iso:country":"BE",
    "sg:address":"Rue De Tongres 66",
    "sg:city":"Oupeye",
    "sg:orig_category":"Boekhouders",
    "sg:phone":"+32 4 379 58 58",
    "sg:postcode":"4684",
    "sg:province":"Li\u00e8ge",
    "wof:name":"Bureau Corman",
    "wof:placetype":"venue"
},
  "geometry": {"coordinates":[5.6692328453,50.740322113],"type":"Point"}
}