{
  "type": "Feature",
  "properties": {
    "iso:country":"BE",
    "sg:address":"Latemstraat 25",
    "sg:city":"Sint-martens-latem",
    "sg:orig_category":"Salles de conf\u00e9rences and de r\u00e9ceptions. Services divers aux personnes. Services fun\u00e9raires",
    "sg:phone":"+32 9 282 35 68",
    "sg:postcode":"9830",
    "sg:province":"Oost-Vlaanderen",
    "wof:name":"Leiensymfonie",
    "wof:placetype":"venue"
},
  "geometry": {"coordinates":[3.6371269226,51.0191879272],"type":"Point"}
}