{
  "type": "Feature",
  "properties": {
    "addr:full":"Winterslagstraat 20 Genk Limburg 3600",
    "addr:housenumber":"20",
    "addr:postcode":"3600",
    "addr:street":"Winterslagstraat",
    "iso:country":"BE",
    "sg:address":"Winterslagstraat 20",
    "sg:city":"Genk",
    "sg:classifiers":[
        {
            "category":"Personal",
            "subcategory":"Beauty Salon",
            "type":"Services"
        }
    ],
    "sg:phone":"+32 89 35 53 78",
    "sg:postcode":"3600",
    "sg:province":"Limburg",
    "wof:name":"Ega",
    "wof:placetype":"venue"
},
  "geometry": {"coordinates":[5.4987230301,50.9645195007],"type":"Point"}
}