{
  "type": "Feature",
  "properties": {
    "addr:full":"Rue Adolphe Mazy 94 Namur Namur 5001",
    "addr:housenumber":"94",
    "addr:postcode":"5001",
    "addr:street":"Rue Adolphe Mazy",
    "iso:country":"BE",
    "sg:address":"Rue Adolphe Mazy 94",
    "sg:city":"Namur",
    "sg:orig_category":"HERSTELLING ELEKTRISCHE HUISHOUDAPPARATEN Huishoudapparaten, televisies and radio's",
    "sg:phone":"+32 81 73 04 43",
    "sg:postcode":"5001",
    "sg:province":"Namur",
    "wof:name":"Claude Collart",
    "wof:placetype":"venue"
},
  "geometry": {"coordinates":[4.8257050514,50.4722557068],"type":"Point"}
}