{
  "type": "Feature",
  "properties": {
    "iso:country":"BE",
    "sg:address":"Rue Chanoine Scarmure 22",
    "sg:city":"Soignies",
    "sg:classifiers":[
        {
            "category":"Home & Garden",
            "subcategory":"Household Appliances",
            "type":"Retail Goods"
        }
    ],
    "sg:phone":"+32 67 33 31 02",
    "sg:postcode":"7060",
    "sg:province":"Hainaut",
    "sg:tags":[
        "repair",
        "stove",
        "-"
    ],
    "wof:name":"Michel L",
    "wof:placetype":"venue"
},
  "geometry": {"coordinates":[4.0724987984,50.5799407959],"type":"Point"}
}