{
  "type": "Feature",
  "properties": {
    "iso:country":"BE",
    "sg:address":"Rue D\u00e9sir\u00e9 Simonis 2",
    "sg:city":"Li\u00e8ge 1 (jupille-sur-meuse)",
    "sg:classifiers":[
        {
            "category":"Bars & Pubs",
            "type":"Food & Drink"
        }
    ],
    "sg:phone":"+32 4 370 61 71",
    "sg:postcode":"4020",
    "sg:province":"Li\u00e8ge",
    "wof:name":"Stade (le)",
    "wof:placetype":"venue"
},
  "geometry": {"coordinates":[5.6258468628,50.6455726624],"type":"Point"}
}