{
  "type": "Feature",
  "properties": {
    "addr:full":"Rue De France 16 Frameries Hainaut 7080",
    "addr:housenumber":"16",
    "addr:postcode":"7080",
    "addr:street":"Rue De France",
    "iso:country":"BE",
    "sg:address":"Rue De France 16",
    "sg:city":"Frameries",
    "sg:orig_category":"Artsen and specialisten",
    "sg:phone":"+32 65 67 47 56",
    "sg:postcode":"7080",
    "sg:province":"Hainaut",
    "wof:name":"Jos\u00c9 Renaux",
    "wof:placetype":"venue"
},
  "geometry": {"coordinates":[3.8919730186,50.4056091309],"type":"Point"}
}