{
  "type": "Feature",
  "properties": {
    "iso:country":"BE",
    "sg:address":"Herman Teirlinckstraat 20",
    "sg:city":"Vilvoorde",
    "sg:orig_category":"V\u00eatements de travail and protection Fab. Equipements divers pour l\u00b4industrie Gr",
    "sg:phone":"+32 2 251 25 07",
    "sg:postcode":"1800",
    "sg:province":"Vlaams-Brabant",
    "wof:name":"Gils",
    "wof:placetype":"venue"
},
  "geometry": {"coordinates":[4.4296951294,50.9382324219],"type":"Point"}
}