{
  "type": "Feature",
  "properties": {
    "addr:full":"Kortenberglaan 75 Brussel (brussel) Bruxelles-Capitale 1000",
    "addr:housenumber":"75",
    "addr:postcode":"1000",
    "addr:street":"Kortenberglaan",
    "iso:country":"BE",
    "sg:address":"Kortenberglaan 75",
    "sg:city":"Brussel (brussel)",
    "sg:orig_category":"Ambassades and consulaten",
    "sg:phone":"+32 2 737 57 00",
    "sg:postcode":"1000",
    "sg:province":"Bruxelles-Capitale",
    "wof:name":"Ambassade Luxembourg",
    "wof:placetype":"venue"
},
  "geometry": {"coordinates":[4.3894968033,50.8446846008],"type":"Point"}
}