{
  "type": "Feature",
  "properties": {
    "iso:country":"BE",
    "sg:address":"Meerstraat 59",
    "sg:city":"Oosterzele",
    "sg:orig_category":"Auto-\u00e9coles",
    "sg:phone":"+32 800 15 285",
    "sg:postcode":"9660",
    "sg:province":"Oost-Vlaanderen",
    "wof:name":"Autorijschool Baert",
    "wof:placetype":"venue"
},
  "geometry": {"coordinates":[3.8019831181,50.9536895752],"type":"Point"}
}