{
  "type": "Feature",
  "properties": {
    "iso:country":"BE",
    "sg:address":"Avenue Georges Lemaitre 15",
    "sg:city":"Charleroi (gosselies)",
    "sg:classifiers":[
        {
            "category":"Education",
            "subcategory":"Special Training",
            "type":"Public Place"
        }
    ],
    "sg:phone":"+32 71 25 61 70",
    "sg:postcode":"6041",
    "sg:province":"Hainaut",
    "sg:tags":[
        "professional"
    ],
    "wof:name":"Centre D'excellence En Maintenance Industrielle",
    "wof:placetype":"venue"
},
  "geometry": {"coordinates":[4.4795351028,50.4749755859],"type":"Point"}
}