{
  "type": "Feature",
  "properties": {
    "iso:country":"BE",
    "sg:address":"Rue Basse 12",
    "sg:city":"Hensies",
    "sg:orig_category":"Epiceries",
    "sg:phone":"+32 65 46 04 71",
    "sg:postcode":"7350",
    "sg:province":"Hainaut",
    "wof:name":"Dominique Duquenne",
    "wof:placetype":"venue"
},
  "geometry": {"coordinates":[3.6824419498,50.4362678528],"type":"Point"}
}