{
  "type": "Feature",
  "properties": {
    "addr:full":"Vliegplein 38 Herenthout Antwerpen 2270",
    "addr:housenumber":"38",
    "addr:postcode":"2270",
    "addr:street":"Vliegplein",
    "iso:country":"BE",
    "sg:address":"Vliegplein 38",
    "sg:city":"Herenthout",
    "sg:orig_category":"Pain, p\u00e2tisseries and confiseries",
    "sg:phone":"+32 14 51 63 52",
    "sg:postcode":"2270",
    "sg:province":"Antwerpen",
    "wof:name":"Huis Wilca",
    "wof:placetype":"venue"
},
  "geometry": {"coordinates":[4.7684559822,51.1398696899],"type":"Point"}
}