{
  "type": "Feature",
  "properties": {
    "addr:full":"Centre Commerc. Longdoz 56bb Li\u00c8ge Li\u00e8ge 4020",
    "addr:housenumber":"56bb",
    "addr:postcode":"4020",
    "iso:country":"BE",
    "sg:address":"Centre Commerc. Longdoz 56bb",
    "sg:city":"Li\u00c8ge",
    "sg:classifiers":[
        {
            "category":"Shopping",
            "subcategory":"Clothing, Apparel, & Fashions",
            "type":"Retail Goods"
        }
    ],
    "sg:phone":"+32 4 344 43 96",
    "sg:postcode":"4020",
    "sg:province":"Li\u00e8ge",
    "sg:tags":[
        "ondergoed",
        "lingerie"
    ],
    "wof:name":"Lingerie Celyne",
    "wof:placetype":"venue"
},
  "geometry": {"coordinates":[5.5819950104,50.6368713379],"type":"Point"}
}