{
  "type": "Feature",
  "properties": {
    "iso:country":"BE",
    "sg:address":"Deerlijksesteenweg 139a",
    "sg:city":"Harelbeke",
    "sg:classifiers":[
        {
            "category":"Building & Trades",
            "subcategory":"Landscaping Services",
            "type":"Services"
        }
    ],
    "sg:postcode":"8530",
    "sg:province":"West-Vlaanderen",
    "sg:tags":[
        "access",
        "pond",
        "laying-out",
        "-"
    ],
    "wof:name":"Het Koi Paradijs Bvba",
    "wof:placetype":"venue"
},
  "geometry": {"coordinates":[3.3293859959,50.8576011658],"type":"Point"}
}