{
  "type": "Feature",
  "properties": {
    "addr:full":"Rue Du Cheval Blanc 46 Pont-\u00e0-celles (luttre) Hainaut 6238",
    "addr:housenumber":"46",
    "addr:postcode":"6238",
    "addr:street":"Rue Du Cheval Blanc",
    "iso:country":"BE",
    "sg:address":"Rue Du Cheval Blanc 46",
    "sg:city":"Pont-\u00e0-celles (luttre)",
    "sg:classifiers":[
        {
            "category":"Communications",
            "type":"Services"
        }
    ],
    "sg:phone":"+32 71 84 29 31",
    "sg:postcode":"6238",
    "sg:province":"Hainaut",
    "sg:tags":[
        "translator"
    ],
    "wof:name":"Traductions",
    "wof:placetype":"venue"
},
  "geometry": {"coordinates":[4.3912329674,50.5042648315],"type":"Point"}
}