{
  "type": "Feature",
  "properties": {
    "addr:full":"Rue De La Banque 5 Seraing Li\u00e8ge 4100",
    "addr:housenumber":"5",
    "addr:postcode":"4100",
    "addr:street":"Rue De La Banque",
    "iso:country":"BE",
    "sg:address":"Rue De La Banque 5",
    "sg:city":"Seraing",
    "sg:orig_category":"S\u00e9curit\u00e9 sociale",
    "sg:phone":"+32 4 337 00 02",
    "sg:postcode":"4100",
    "sg:province":"Li\u00e8ge",
    "wof:name":"Mutualit\u00c9 Prof. & Libre",
    "wof:placetype":"venue"
},
  "geometry": {"coordinates":[5.5132279396,50.6095848083],"type":"Point"}
}