{
  "type": "Feature",
  "properties": {
    "addr:full":"Rue Tout-y-faut 84 La Louvi\u00c8re Hainaut 7110",
    "addr:housenumber":"84",
    "addr:postcode":"7110",
    "addr:street":"Rue Tout-Y-Faut",
    "iso:country":"BE",
    "sg:address":"Rue Tout-y-faut 84",
    "sg:city":"La Louvi\u00c8re",
    "sg:orig_category":"Agences immobili\u00e8res. Gestion de portefeuilles and fortunes, conseils en placements. Assurances",
    "sg:phone":"+32 64 26 41 11",
    "sg:postcode":"7110",
    "sg:province":"Hainaut",
    "wof:name":"Soci\u00c9t\u00c9 Immobili\u00c8re Europ\u00c9enne",
    "wof:placetype":"venue"
},
  "geometry": {"coordinates":[4.1505050659,50.4826698303],"type":"Point"}
}