{
  "type": "Feature",
  "properties": {
    "addr:full":"Gisseleire Vers\u00c9laan 23 Sint-agatha-berchem/berchem-sainte-agathe Bruxelles-Capitale 1082",
    "addr:housenumber":"23",
    "addr:postcode":"1082",
    "addr:street":"Gisseleire Verse\u0301Laan",
    "iso:country":"BE",
    "sg:address":"Gisseleire Vers\u00c9laan 23",
    "sg:city":"Sint-agatha-berchem/berchem-sainte-agathe",
    "sg:orig_category":"Rusthuizen and serviceflats",
    "sg:phone":"+32 2 465 67 15",
    "sg:postcode":"1082",
    "sg:province":"Bruxelles-Capitale",
    "wof:name":"Nouvelle R\u00c9sidence Le Saule",
    "wof:placetype":"venue"
},
  "geometry": {"coordinates":[4.2995758057,50.86095047],"type":"Point"}
}