{
  "type": "Feature",
  "properties": {
    "iso:country":"BE",
    "sg:address":"Nijverheidszone 'begijnenmeers' 24-26",
    "sg:city":"Liedekerke",
    "sg:classifiers":[
        {
            "category":"Retail",
            "subcategory":"Auto Repair",
            "type":"Services"
        }
    ],
    "sg:phone":"+32 53 66 22 66",
    "sg:postcode":"1770",
    "sg:province":"Vlaams-Brabant",
    "sg:tags":[
        "garage"
    ],
    "wof:name":"De Bolle",
    "wof:placetype":"venue"
},
  "geometry": {"coordinates":[4.0872688293,50.8854942322],"type":"Point"}
}