{
  "type": "Feature",
  "properties": {
    "iso:country":"BE",
    "sg:address":"Avenue Batonnier-thomas-braun 1",
    "sg:city":"Paliseul",
    "sg:orig_category":"DIVERSE RECREATIEVE ACTIVITEITEN Diverse zakelijke dienstverlening Hotels Pensions Restaurants Sport",
    "sg:phone":"+32 61 65 53 91",
    "sg:postcode":"6852",
    "sg:province":"Luxembourg",
    "wof:name":"Chalet Sur Lesse",
    "wof:placetype":"venue"
},
  "geometry": {"coordinates":[5.1872749329,49.9693183899],"type":"Point"}
}