{
  "type": "Feature",
  "properties": {
    "iso:country":"BE",
    "sg:address":"3 Rue De Tohogne",
    "sg:city":"Bomal",
    "sg:classifiers":[
        {
            "category":"Professional",
            "subcategory":"Printing & Photocopies",
            "type":"Services"
        }
    ],
    "sg:phone":"+32 2 386 42 50",
    "sg:postcode":"6941",
    "sg:province":"Luxembourg",
    "sg:tags":[
        "publishing"
    ],
    "wof:name":"Editions Panini Belgique Sa",
    "wof:placetype":"venue"
},
  "geometry": {"coordinates":[15.2195005417,40.783657074],"type":"Point"}
}