{
  "type": "Feature",
  "properties": {
    "addr:full":"Rechtestraat 1a Genk Limburg 3600",
    "addr:housenumber":"1a",
    "addr:postcode":"3600",
    "addr:street":"Rechtestraat",
    "iso:country":"BE",
    "sg:address":"Rechtestraat 1a",
    "sg:city":"Genk",
    "sg:classifiers":[
        {
            "category":"Personal",
            "subcategory":"Beauty Salon",
            "type":"Services"
        }
    ],
    "sg:phone":"+32 89 30 66 64",
    "sg:postcode":"3600",
    "sg:province":"Limburg",
    "sg:tags":[
        "lady",
        "-",
        "hairdressing"
    ],
    "wof:name":"Cathy",
    "wof:placetype":"venue"
},
  "geometry": {"coordinates":[5.446996212,50.9819412231],"type":"Point"}
}