{
  "type": "Feature",
  "properties": {
    "addr:full":"Molendreef 68a-80 Anzegem (vichte) West-Vlaanderen 8570",
    "addr:housenumber":"68a-80",
    "addr:postcode":"8570",
    "addr:street":"Molendreef",
    "iso:country":"BE",
    "sg:address":"Molendreef 68a-80",
    "sg:city":"Anzegem (vichte)",
    "sg:classifiers":[
        {
            "category":"Retail",
            "subcategory":"Auto Repair",
            "type":"Services"
        }
    ],
    "sg:phone":"+32 56 77 89 96",
    "sg:postcode":"8570",
    "sg:province":"West-Vlaanderen",
    "sg:tags":[
        "breakdown",
        "automobile",
        "-",
        "recovery"
    ],
    "wof:name":"Bekaert",
    "wof:placetype":"venue"
},
  "geometry": {"coordinates":[3.4000720978,50.8409767151],"type":"Point"}
}