{
  "type": "Feature",
  "properties": {
    "addr:full":"Leopoldstraat 11 Merksplas Antwerpen 2330",
    "addr:housenumber":"11",
    "addr:postcode":"2330",
    "addr:street":"Leopoldstraat",
    "iso:country":"BE",
    "sg:address":"Leopoldstraat 11",
    "sg:city":"Merksplas",
    "sg:orig_category":"Boucheries",
    "sg:phone":"+32 14 63 39 33",
    "sg:postcode":"2330",
    "sg:province":"Antwerpen",
    "wof:name":"Slagerij Hofkens-van Hees",
    "wof:placetype":"venue"
},
  "geometry": {"coordinates":[4.8641867638,51.3574905396],"type":"Point"}
}