{
  "type": "Feature",
  "properties": {
    "addr:full":"Maarschalk Fochstraat 26 Leopoldsburg Limburg 3970",
    "addr:housenumber":"26",
    "addr:postcode":"3970",
    "addr:street":"Maarschalk Fochstraat",
    "iso:country":"BE",
    "sg:address":"Maarschalk Fochstraat 26",
    "sg:city":"Leopoldsburg",
    "sg:classifiers":[
        {
            "category":"Personal",
            "subcategory":"Beauty Salon",
            "type":"Services"
        }
    ],
    "sg:phone":"+32 11 34 11 64",
    "sg:postcode":"3970",
    "sg:province":"Limburg",
    "sg:tags":[
        "lady",
        "-",
        "hairdressing"
    ],
    "wof:name":"Frans",
    "wof:placetype":"venue"
},
  "geometry": {"coordinates":[5.261138916,51.1171798706],"type":"Point"}
}