{
  "type": "Feature",
  "properties": {
    "addr:full":"Dorpsstraat 32 As Limburg 3665",
    "addr:housenumber":"32",
    "addr:postcode":"3665",
    "addr:street":"Dorpsstraat",
    "iso:country":"BE",
    "sg:address":"Dorpsstraat 32",
    "sg:city":"As",
    "sg:orig_category":"Glaszetten and glaswerk",
    "sg:phone":"+32 89 65 94 57",
    "sg:postcode":"3665",
    "sg:province":"Limburg",
    "wof:name":"Carrein",
    "wof:placetype":"venue"
},
  "geometry": {"coordinates":[5.5854082108,51.0077934265],"type":"Point"}
}