{
  "type": "Feature",
  "properties": {
    "addr:full":"Vennestraat 79 Genk Limburg 3600",
    "addr:housenumber":"79",
    "addr:postcode":"3600",
    "addr:street":"Vennestraat",
    "iso:country":"BE",
    "sg:address":"Vennestraat 79",
    "sg:city":"Genk",
    "sg:classifiers":[
        {
            "category":"Professional",
            "subcategory":"Accounting & Tax Preparation",
            "type":"Services"
        }
    ],
    "sg:phone":"+32 89 61 24 20",
    "sg:postcode":"3600",
    "sg:province":"Limburg",
    "sg:tags":[
        "bookkeeper"
    ],
    "wof:name":"Zakenkantoor Eddy Valee Bvba",
    "wof:placetype":"venue"
},
  "geometry": {"coordinates":[5.4904799461,50.9782218933],"type":"Point"}
}