{
  "type": "Feature",
  "properties": {
    "addr:full":"Hogeweg 245 Menen West-Vlaanderen 8930",
    "addr:housenumber":"245",
    "addr:postcode":"8930",
    "addr:street":"Hogeweg",
    "iso:country":"BE",
    "sg:address":"Hogeweg 245",
    "sg:city":"Menen",
    "sg:orig_category":"Rev\u00eatements de sols and murs",
    "sg:phone":"+32 56 52 88 40",
    "sg:postcode":"8930",
    "sg:province":"West-Vlaanderen",
    "wof:name":"Par-ky",
    "wof:placetype":"venue"
},
  "geometry": {"coordinates":[3.0953850746,50.795879364],"type":"Point"}
}