{
  "type": "Feature",
  "properties": {
    "iso:country":"BE",
    "sg:address":"Dennenstraat 12",
    "sg:city":"Mol",
    "sg:classifiers":[
        {
            "category":"Insurance",
            "subcategory":"Insurance Agent",
            "type":"Services"
        }
    ],
    "sg:phone":"+32 14 31 24 42",
    "sg:postcode":"2400",
    "sg:province":"Antwerpen",
    "sg:tags":[
        "verzekeringsmakelaars",
        "expert"
    ],
    "wof:name":"Linda Lauwers",
    "wof:placetype":"venue"
},
  "geometry": {"coordinates":[5.1350460052,51.2046203613],"type":"Point"}
}