{
  "type": "Feature",
  "properties": {
    "iso:country":"BE",
    "sg:address":"Rue Delvaux 2",
    "sg:city":"Awans",
    "sg:orig_category":"Eleveurs de bovins",
    "sg:phone":"+32 4 257 61 80",
    "sg:postcode":"4340",
    "sg:province":"Li\u00e8ge",
    "wof:name":"Louis Lombard",
    "wof:placetype":"venue"
},
  "geometry": {"coordinates":[5.4635682106,50.7128372192],"type":"Point"}
}