{
  "type": "Feature",
  "properties": {
    "addr:full":"Enclus Du Haut 30 Mont-de-l'enclus Hainaut 7750",
    "addr:housenumber":"30",
    "addr:postcode":"7750",
    "addr:street":"Mont-De-L'Enclus Hainaut",
    "iso:country":"BE",
    "sg:address":"Enclus Du Haut 30",
    "sg:city":"Mont-de-l'enclus",
    "sg:orig_category":"HUISBRANDOLIE",
    "sg:phone":"+32 69 45 55 44",
    "sg:postcode":"7750",
    "sg:province":"Hainaut",
    "wof:name":"Albert Hobsig",
    "wof:placetype":"venue"
},
  "geometry": {"coordinates":[5.7178230286,47.0204772949],"type":"Point"}
}