{
  "type": "Feature",
  "properties": {
    "iso:country":"BE",
    "sg:address":"Ten Bosse 106",
    "sg:city":"Deinze",
    "sg:orig_category":"Technische studies and ingenieursactiviteiten",
    "sg:phone":"+32 9 380 25 88",
    "sg:postcode":"9800",
    "sg:province":"Oost-Vlaanderen",
    "wof:name":"S E C",
    "wof:placetype":"venue"
},
  "geometry": {"coordinates":[3.5382139683,50.9896965027],"type":"Point"}
}