{
  "type": "Feature",
  "properties": {
    "addr:full":"Rue De Wand 122 Laken/laeken Bruxelles-Capitale 1020",
    "addr:housenumber":"122",
    "addr:postcode":"1020",
    "addr:street":"Rue De Wand",
    "iso:country":"BE",
    "sg:address":"Rue De Wand 122",
    "sg:city":"Laken/laeken",
    "sg:orig_category":"Fietsen Motorfietsen Sport- and kampeermateriaal",
    "sg:phone":"+32 2 268 53 41",
    "sg:postcode":"1020",
    "sg:province":"Bruxelles-Capitale",
    "wof:name":"Sport 2000",
    "wof:placetype":"venue"
},
  "geometry": {"coordinates":[4.3601269722,50.8999633789],"type":"Point"}
}