{
  "type": "Feature",
  "properties": {
    "iso:country":"BE",
    "sg:address":"Rue Henry Pastur 29",
    "sg:city":"Jodoigne",
    "sg:orig_category":"Rundveehouders",
    "sg:phone":"+32 10 81 11 66",
    "sg:postcode":"1370",
    "sg:province":"Brabant Wallon",
    "wof:name":"Ludo Wilmots",
    "wof:placetype":"venue"
},
  "geometry": {"coordinates":[4.831993103,50.7174072266],"type":"Point"}
}