{
  "type": "Feature",
  "properties": {
    "addr:full":"Monseigneur Lambrechtstraat 106 Oudenaarde (welden) Oost-Vlaanderen 9700",
    "addr:housenumber":"106",
    "addr:postcode":"9700",
    "addr:street":"Monseigneur Lambrechtstraat",
    "iso:country":"BE",
    "sg:address":"Monseigneur Lambrechtstraat 106",
    "sg:city":"Oudenaarde (welden)",
    "sg:classifiers":[
        {
            "category":"Building & Trades",
            "subcategory":"Landscaping Services",
            "type":"Services"
        }
    ],
    "sg:phone":"+32 55 49 78 76",
    "sg:postcode":"9700",
    "sg:province":"Oost-Vlaanderen",
    "sg:tags":[
        "gardening",
        "garden",
        "maintenance"
    ],
    "wof:name":"De Reebock",
    "wof:placetype":"venue"
},
  "geometry": {"coordinates":[3.6519730091,50.8802909851],"type":"Point"}
}