{
  "type": "Feature",
  "properties": {
    "iso:country":"BE",
    "sg:address":"Oudenaardsestraat 230",
    "sg:city":"Geraardsbergen",
    "sg:orig_category":"Agences de publicit\u00e9",
    "sg:phone":"+32 54 41 35 74",
    "sg:postcode":"9500",
    "sg:province":"Oost-Vlaanderen",
    "wof:name":"Fa. Grafido",
    "wof:placetype":"venue"
},
  "geometry": {"coordinates":[3.8688800335,50.7724113464],"type":"Point"}
}