{
  "type": "Feature",
  "properties": {
    "iso:country":"BE",
    "sg:address":"Rue D'asquillies 32",
    "sg:city":"Mons (nouvelles)",
    "sg:classifiers":[
        {
            "category":"Real Estate",
            "subcategory":"Architect",
            "type":"Services"
        }
    ],
    "sg:phone":"+32 65 33 87 38",
    "sg:postcode":"7022",
    "sg:province":"Hainaut",
    "wof:name":"Monniez J",
    "wof:placetype":"venue"
},
  "geometry": {"coordinates":[3.9619328976,50.4398155212],"type":"Point"}
}