{
  "type": "Feature",
  "properties": {
    "iso:country":"BE",
    "sg:address":"Ketelstraat 60",
    "sg:city":"Deinze",
    "sg:classifiers":[
        {
            "category":"Personal",
            "subcategory":"Beauty Salon",
            "type":"Services"
        }
    ],
    "sg:phone":"+32 9 386 88 46",
    "sg:postcode":"9800",
    "sg:province":"Oost-Vlaanderen",
    "sg:tags":[
        "de",
        "coiffure"
    ],
    "wof:name":"Coiffure Vera",
    "wof:placetype":"venue"
},
  "geometry": {"coordinates":[3.47727108,51.01537323],"type":"Point"}
}