{
  "type": "Feature",
  "properties": {
    "addr:full":"Rue Du Village 18 Quaregnon Hainaut 7390",
    "addr:housenumber":"18",
    "addr:postcode":"7390",
    "addr:street":"Rue Du Village",
    "iso:country":"BE",
    "sg:address":"Rue Du Village 18",
    "sg:city":"Quaregnon",
    "sg:orig_category":"Schoenen",
    "sg:phone":"+32 65 78 36 45",
    "sg:postcode":"7390",
    "sg:province":"Hainaut",
    "wof:name":"Shoes In The Box",
    "wof:placetype":"venue"
},
  "geometry": {"coordinates":[3.8652279377,50.4426689148],"type":"Point"}
}