{
  "type": "Feature",
  "properties": {
    "addr:full":"Kamperbaan 7 Hechtel-eksel Limburg 3940",
    "addr:housenumber":"7",
    "addr:postcode":"3940",
    "addr:street":"Kamperbaan",
    "iso:country":"BE",
    "sg:address":"Kamperbaan 7",
    "sg:city":"Hechtel-eksel",
    "sg:orig_category":"Boucheries",
    "sg:phone":"+32 11 73 41 64",
    "sg:postcode":"3940",
    "sg:province":"Limburg",
    "wof:name":"Mathieu Aerts",
    "wof:placetype":"venue"
},
  "geometry": {"coordinates":[5.364795208,51.1255340576],"type":"Point"}
}