{
  "type": "Feature",
  "properties": {
    "addr:full":"Avenue Des Martyrs 268 Fl\u00e9ron Li\u00e8ge 4620",
    "addr:housenumber":"268",
    "addr:postcode":"4620",
    "addr:street":"Avenue Des Martyrs",
    "iso:country":"BE",
    "sg:address":"Avenue Des Martyrs 268",
    "sg:city":"Fl\u00e9ron",
    "sg:classifiers":[
        {
            "category":"Shopping",
            "subcategory":"Clothing, Apparel, & Fashions",
            "type":"Retail Goods"
        }
    ],
    "sg:phone":"+32 4 358 57 95",
    "sg:postcode":"4620",
    "sg:province":"Li\u00e8ge",
    "sg:tags":[
        "boutique"
    ],
    "wof:name":"Indigo",
    "wof:placetype":"venue"
},
  "geometry": {"coordinates":[5.6849889755,50.6144180298],"type":"Point"}
}