{
  "type": "Feature",
  "properties": {
    "addr:full":"Magaret 5 De Pinte Oost-Vlaanderen 9840",
    "addr:housenumber":"5",
    "addr:postcode":"9840",
    "addr:street":"Magaret",
    "iso:country":"BE",
    "sg:address":"Magaret 5",
    "sg:city":"De Pinte",
    "sg:orig_category":"Artsen and specialisten",
    "sg:phone":"+32 9 282 21 38",
    "sg:postcode":"9840",
    "sg:province":"Oost-Vlaanderen",
    "wof:name":"G. Hollanders",
    "wof:placetype":"venue"
},
  "geometry": {"coordinates":[3.6630630493,50.9880027771],"type":"Point"}
}