{
  "type": "Feature",
  "properties": {
    "iso:country":"BE",
    "sg:address":"Oostmoerstraat 39",
    "sg:city":"Jabbeke",
    "sg:orig_category":"Banques and organismes de cr\u00e9dit",
    "sg:phone":"+32 50 81 44 28",
    "sg:postcode":"8490",
    "sg:province":"West-Vlaanderen",
    "wof:name":"Centea",
    "wof:placetype":"venue"
},
  "geometry": {"coordinates":[3.1341199875,51.1668014526],"type":"Point"}
}