{
  "type": "Feature",
  "properties": {
    "addr:full":"Meir 80-82 Antwerpen Antwerpen 2000",
    "addr:postcode":"80-82;2000",
    "addr:street":"Meir",
    "iso:country":"BE",
    "sg:address":"Meir 80-82",
    "sg:city":"Antwerpen",
    "sg:orig_category":"Eclairage et \u00e9quipements du foyer",
    "sg:phone":"+32 3 226 39 07",
    "sg:postcode":"2000",
    "sg:province":"Antwerpen",
    "wof:name":"Inno",
    "wof:placetype":"venue"
},
  "geometry": {"coordinates":[4.4118318558,51.2180023193],"type":"Point"}
}