{
  "type": "Feature",
  "properties": {
    "addr:full":"Rue Henri Deleers 82 Bruxelles (anderlecht) Bruxelles-Capitale 1070",
    "addr:housenumber":"82",
    "addr:postcode":"1070",
    "addr:street":"Rue Henri Deleers",
    "iso:country":"BE",
    "sg:address":"Rue Henri Deleers 82",
    "sg:city":"Bruxelles (anderlecht)",
    "sg:classifiers":[
        {
            "category":"Food & Beverages",
            "subcategory":"Groceries & Convenience Stores",
            "type":"Retail Goods"
        }
    ],
    "sg:phone":"+32 2 539 35 24",
    "sg:postcode":"1070",
    "sg:province":"Bruxelles-Capitale",
    "sg:tags":[
        "grocer"
    ],
    "wof:name":"Assucol Et Co",
    "wof:placetype":"venue"
},
  "geometry": {"coordinates":[4.3032598495,50.8260383606],"type":"Point"}
}