{
  "type": "Feature",
  "properties": {
    "addr:full":"Cit\u00c9 Du Moulin 4ba3 Li\u00c8ge Li\u00e8ge 4000",
    "addr:postcode":"4000",
    "addr:street":"Cite\u0301 Du Moulin 4Ba3",
    "iso:country":"BE",
    "sg:address":"Cit\u00c9 Du Moulin 4ba3",
    "sg:city":"Li\u00c8ge",
    "sg:classifiers":[
        {
            "category":"Insurance",
            "subcategory":"Insurance Agent",
            "type":"Services"
        }
    ],
    "sg:phone":"+32 4 226 49 43",
    "sg:postcode":"4000",
    "sg:province":"Li\u00e8ge",
    "sg:tags":[
        "verzekeringsmakelaars",
        "expert"
    ],
    "wof:name":"A. Aydogdu",
    "wof:placetype":"venue"
},
  "geometry": {"coordinates":[5.5480527878,50.6506767273],"type":"Point"}
}