{
  "type": "Feature",
  "properties": {
    "iso:country":"BE",
    "sg:address":"Huisdal 5",
    "sg:city":"Asse (relegem)",
    "sg:classifiers":[
        {
            "category":"Professional",
            "subcategory":"Management & Consulting",
            "type":"Services"
        }
    ],
    "sg:phone":"+32 2 460 11 95",
    "sg:postcode":"1731",
    "sg:province":"Vlaams-Brabant",
    "sg:tags":[
        "consultant"
    ],
    "wof:name":"Verstraeten P",
    "wof:placetype":"venue"
},
  "geometry": {"coordinates":[4.2764248848,50.9018745422],"type":"Point"}
}