{
  "type": "Feature",
  "properties": {
    "addr:full":"Grote Steenweg 395 Linter (drieslinter) Vlaams-Brabant 3350",
    "addr:housenumber":"395",
    "addr:postcode":"3350",
    "addr:street":"Grote Steenweg",
    "iso:country":"BE",
    "sg:address":"Grote Steenweg 395",
    "sg:city":"Linter (drieslinter)",
    "sg:classifiers":[
        {
            "category":"Health Services",
            "subcategory":"Dentist",
            "type":"Services"
        }
    ],
    "sg:phone":"+32 11 78 05 35",
    "sg:postcode":"3350",
    "sg:province":"Vlaams-Brabant",
    "wof:name":"Vanherwegen Ludo",
    "wof:placetype":"venue"
},
  "geometry": {"coordinates":[5.0574817657,50.8504905701],"type":"Point"}
}