{
  "type": "Feature",
  "properties": {
    "addr:full":"Sint-bernardusstraat 48 Sint-gillis/saint-gilles Bruxelles-Capitale 1060",
    "addr:housenumber":"48",
    "addr:postcode":"1060",
    "addr:street":"Sint-Bernardusstraat",
    "iso:country":"BE",
    "sg:address":"Sint-bernardusstraat 48",
    "sg:city":"Sint-gillis/saint-gilles",
    "sg:classifiers":[
        {
            "category":"Professional",
            "subcategory":"Art Services",
            "type":"Services"
        }
    ],
    "sg:phone":"+32 2 534 71 09",
    "sg:postcode":"1060",
    "sg:province":"Bruxelles-Capitale",
    "sg:tags":[
        "designer",
        "ontwerpers"
    ],
    "wof:name":"Union Pour Le Votement",
    "wof:placetype":"venue"
},
  "geometry": {"coordinates":[4.3541941643,50.8286247253],"type":"Point"}
}