{
  "type": "Feature",
  "properties": {
    "addr:full":"Rue Jean Not\u00e9 64 Bruxelles (anderlecht) Bruxelles-Capitale 1070",
    "addr:housenumber":"64",
    "addr:postcode":"1070",
    "addr:street":"Rue Jean Note\u0301",
    "iso:country":"BE",
    "sg:address":"Rue Jean Not\u00e9 64",
    "sg:city":"Bruxelles (anderlecht)",
    "sg:classifiers":[
        {
            "category":"Health Services",
            "subcategory":"Health Practitioner",
            "type":"Services"
        }
    ],
    "sg:phone":"+32 2 523 82 83",
    "sg:postcode":"1070",
    "sg:province":"Bruxelles-Capitale",
    "sg:tags":[
        "physiotherapist"
    ],
    "wof:name":"Geeraerts C",
    "wof:placetype":"venue"
},
  "geometry": {"coordinates":[4.2932357788,50.8258552551],"type":"Point"}
}