{
  "type": "Feature",
  "properties": {
    "addr:full":"Rode Kruisstraat 5 Heusden-zolder (heusden) Limburg 3550",
    "addr:housenumber":"5",
    "addr:postcode":"3550",
    "addr:street":"Rode Kruisstraat",
    "iso:country":"BE",
    "sg:address":"Rode Kruisstraat 5",
    "sg:city":"Heusden-zolder (heusden)",
    "sg:orig_category":"Non-Classified Establishments",
    "sg:phone":"+32 495 30 21 61",
    "sg:postcode":"3550",
    "sg:province":"Limburg",
    "wof:name":"Pyramisa Import",
    "wof:placetype":"venue"
},
  "geometry": {"coordinates":[5.3065400124,51.0395469666],"type":"Point"}
}