{
  "type": "Feature",
  "properties": {
    "addr:full":"Korte Vuldersstraat 12 Brugge West-Vlaanderen 8000",
    "addr:housenumber":"12",
    "addr:postcode":"8000",
    "addr:street":"Korte Vuldersstraat",
    "iso:country":"BE",
    "sg:address":"Korte Vuldersstraat 12",
    "sg:city":"Brugge",
    "sg:orig_category":"Non-Classified Establishments",
    "sg:phone":"+32 50 34 45 57",
    "sg:postcode":"8000",
    "sg:province":"West-Vlaanderen",
    "wof:name":"Speybrouck M & M",
    "wof:placetype":"venue"
},
  "geometry": {"coordinates":[3.2200410366,51.2049331665],"type":"Point"}
}