{
  "type": "Feature",
  "properties": {
    "iso:country":"BE",
    "sg:address":"Rue Rouveroy 2",
    "sg:city":"Li\u00e8ge 1",
    "sg:classifiers":[
        {
            "category":"Social Services",
            "type":"Services"
        }
    ],
    "sg:phone":"+32 4 223 54 36",
    "sg:postcode":"4000",
    "sg:province":"Li\u00e8ge",
    "wof:name":"Missio",
    "wof:placetype":"venue"
},
  "geometry": {"coordinates":[5.5721678734,50.6369781494],"type":"Point"}
}