{
  "type": "Feature",
  "properties": {
    "iso:country":"BE",
    "sg:address":"Allemansweg 36",
    "sg:city":"Dilsen-stokkem",
    "sg:orig_category":"Studios photographiques",
    "sg:phone":"+32 89 79 35 15",
    "sg:postcode":"3650",
    "sg:province":"Limburg",
    "wof:name":"Erie Ten Doesschate",
    "wof:placetype":"venue"
},
  "geometry": {"coordinates":[5.7289938927,51.0495986938],"type":"Point"}
}