{
  "type": "Feature",
  "properties": {
    "addr:full":"Rue Des Carmes 29 Namur Namur 5000",
    "addr:housenumber":"29",
    "addr:postcode":"5000",
    "addr:street":"Rue Des Carmes",
    "iso:country":"BE",
    "sg:address":"Rue Des Carmes 29",
    "sg:city":"Namur",
    "sg:orig_category":"Tijdelijke werkgelegenheid and uitzendkantoren",
    "sg:phone":"+32 81 22 19 46",
    "sg:postcode":"5000",
    "sg:province":"Namur",
    "wof:name":"T\u00c8nce Interim",
    "wof:placetype":"venue"
},
  "geometry": {"coordinates":[4.8635749817,50.465877533],"type":"Point"}
}