{
  "type": "Feature",
  "properties": {
    "addr:full":"Kaatstraat 54 Lommel Limburg 3920",
    "addr:housenumber":"54",
    "addr:postcode":"3920",
    "addr:street":"Kaatstraat",
    "iso:country":"BE",
    "sg:address":"Kaatstraat 54",
    "sg:city":"Lommel",
    "sg:classifiers":[
        {
            "category":"Parking",
            "subcategory":"Lot",
            "type":"Transportation"
        }
    ],
    "sg:phone":"+32 11 54 51 17",
    "sg:postcode":"3920",
    "sg:province":"Limburg",
    "sg:tags":[
        "parking-places",
        "laying-out"
    ],
    "wof:name":"Kuypers J",
    "wof:placetype":"venue"
},
  "geometry": {"coordinates":[5.2915768623,51.1848831177],"type":"Point"}
}