{
  "type": "Feature",
  "properties": {
    "addr:full":"Kortrijkstraat 360 Oudenaarde Oost-Vlaanderen 9700",
    "addr:housenumber":"360",
    "addr:postcode":"9700",
    "addr:street":"Kortrijkstraat",
    "iso:country":"BE",
    "sg:address":"Kortrijkstraat 360",
    "sg:city":"Oudenaarde",
    "sg:classifiers":[
        {
            "category":"Banks & Credit Unions",
            "subcategory":"Financial Services",
            "type":"Services"
        }
    ],
    "sg:phone":"+32 55 30 43 47",
    "sg:postcode":"9700",
    "sg:province":"Oost-Vlaanderen",
    "sg:tags":[
        "group"
    ],
    "wof:name":"Holda Nv",
    "wof:placetype":"venue"
},
  "geometry": {"coordinates":[3.5938498974,50.8505096436],"type":"Point"}
}