{
  "type": "Feature",
  "properties": {
    "addr:full":"Groenstraat 106-201 Leuven (heverlee) Vlaams-Brabant 3001",
    "addr:housenumber":"106-201",
    "addr:postcode":"3001",
    "addr:street":"Groenstraat",
    "iso:country":"BE",
    "sg:address":"Groenstraat 106-201",
    "sg:city":"Leuven (heverlee)",
    "sg:classifiers":[
        {
            "category":"Real Estate",
            "subcategory":"Architect",
            "type":"Services"
        }
    ],
    "sg:phone":"+32 16 40 45 70",
    "sg:postcode":"3001",
    "sg:province":"Vlaams-Brabant",
    "wof:name":"Werkplaats Voor Architectuur Architectenassociatie",
    "wof:placetype":"venue"
},
  "geometry": {"coordinates":[4.6843662262,50.8710327148],"type":"Point"}
}