{
  "type": "Feature",
  "properties": {
    "addr:full":"Kapelstraat 4 Hamont-achel Limburg 3930",
    "addr:housenumber":"4",
    "addr:postcode":"3930",
    "addr:street":"Kapelstraat",
    "iso:country":"BE",
    "sg:address":"Kapelstraat 4",
    "sg:city":"Hamont-achel",
    "sg:orig_category":"Binnenhuisarchitecten",
    "sg:phone":"+32 11 44 67 26",
    "sg:postcode":"3930",
    "sg:province":"Limburg",
    "wof:name":"Kathleen Simons",
    "wof:placetype":"venue"
},
  "geometry": {"coordinates":[5.5450549126,51.2511863708],"type":"Point"}
}