{
  "type": "Feature",
  "properties": {
    "iso:country":"BE",
    "sg:address":"Westlaan 263",
    "sg:city":"Roeselare",
    "sg:orig_category":"Boissons",
    "sg:phone":"+32 51 22 12 22",
    "sg:postcode":"8800",
    "sg:province":"West-Vlaanderen",
    "wof:name":"Vynckier",
    "wof:placetype":"venue"
},
  "geometry": {"coordinates":[3.1129860878,50.9452552795],"type":"Point"}
}