{
  "type": "Feature",
  "properties": {
    "iso:country":"BE",
    "sg:address":"Rechtestraat 26",
    "sg:city":"Lille",
    "sg:orig_category":"Brood, gebak and snoepgoed",
    "sg:phone":"+32 14 88 00 45",
    "sg:postcode":"2275",
    "sg:province":"Antwerpen",
    "wof:name":"Nifera",
    "wof:placetype":"venue"
},
  "geometry": {"coordinates":[4.8236098289,51.2395515442],"type":"Point"}
}