{
  "type": "Feature",
  "properties": {
    "iso:country":"BE",
    "sg:address":"Edingsesteenweg 251",
    "sg:city":"Ninove (denderwindeke)",
    "sg:classifiers":[
        {
            "category":"Bakery",
            "type":"Food & Drink"
        }
    ],
    "sg:phone":"+32 54 33 30 06",
    "sg:postcode":"9400",
    "sg:province":"Oost-Vlaanderen",
    "sg:tags":[
        "confectioner",
        "baker"
    ],
    "wof:name":"Bick\u00e9 M",
    "wof:placetype":"venue"
},
  "geometry": {"coordinates":[4.0263299942,50.8269996643],"type":"Point"}
}