{
  "type": "Feature",
  "properties": {
    "iso:country":"BE",
    "sg:address":"Goudenkruispunt",
    "sg:city":"Tielt-winge (sint-joris-winge)",
    "sg:classifiers":[
        {
            "category":"Shopping",
            "subcategory":"Crafts & Fabrics",
            "type":"Retail Goods"
        }
    ],
    "sg:phone":"+32 16 63 33 57",
    "sg:postcode":"3390",
    "sg:province":"Vlaams-Brabant",
    "sg:tags":[
        "silk",
        "-"
    ],
    "wof:name":"Rotexco Stoffen",
    "wof:placetype":"venue"
},
  "geometry": {"coordinates":[4.8715748787,50.9058761597],"type":"Point"}
}