{
  "type": "Feature",
  "properties": {
    "iso:country":"BE",
    "sg:address":"Tervuursesteenweg 203",
    "sg:city":"Leuven (heverlee)",
    "sg:classifiers":[
        {
            "category":"Retail",
            "subcategory":"Veterinary Services",
            "type":"Services"
        }
    ],
    "sg:phone":"+32 16 20 60 33",
    "sg:postcode":"3001",
    "sg:province":"Vlaams-Brabant",
    "sg:tags":[
        "veterinarian"
    ],
    "wof:name":"Laes A",
    "wof:placetype":"venue"
},
  "geometry": {"coordinates":[4.6758389473,50.8750114441],"type":"Point"}
}