{
  "type": "Feature",
  "properties": {
    "iso:country":"BE",
    "sg:address":"Nijverheidslaan 1",
    "sg:city":"Diest",
    "sg:classifiers":[
        {
            "category":"Community Center",
            "subcategory":"Ethnic",
            "type":"Public Place"
        }
    ],
    "sg:phone":"+32 13 32 31 91",
    "sg:postcode":"3290",
    "sg:province":"Vlaams-Brabant",
    "sg:tags":[
        "medium"
    ],
    "wof:name":"Mercatron Communication Nv",
    "wof:placetype":"venue"
},
  "geometry": {"coordinates":[5.0496058464,50.9899101257],"type":"Point"}
}