{
  "type": "Feature",
  "properties": {
    "addr:full":"Torhoutstraat 83 Kortemark West-Vlaanderen 8610",
    "addr:housenumber":"83",
    "addr:postcode":"8610",
    "addr:street":"Torhoutstraat",
    "iso:country":"BE",
    "sg:address":"Torhoutstraat 83",
    "sg:city":"Kortemark",
    "sg:orig_category":"Rundveehouders Varkenskwekers",
    "sg:phone":"+32 51 56 64 78",
    "sg:postcode":"8610",
    "sg:province":"West-Vlaanderen",
    "wof:name":"Gabriel Gunst",
    "wof:placetype":"venue"
},
  "geometry": {"coordinates":[3.0478379726,51.0354881287],"type":"Point"}
}