{
  "type": "Feature",
  "properties": {
    "addr:full":"Smisstraat 113 Sint-niklaas Oost-Vlaanderen 9100",
    "addr:housenumber":"113",
    "addr:postcode":"9100",
    "addr:street":"Smisstraat",
    "iso:country":"BE",
    "sg:address":"Smisstraat 113",
    "sg:city":"Sint-niklaas",
    "sg:classifiers":[
        {
            "category":"Building & Trades",
            "subcategory":"Construction",
            "type":"Services"
        }
    ],
    "sg:phone":"+32 3 776 59 07",
    "sg:postcode":"9100",
    "sg:province":"Oost-Vlaanderen",
    "sg:tags":[
        "carpenter"
    ],
    "wof:name":"Loeman T",
    "wof:placetype":"venue"
},
  "geometry": {"coordinates":[4.1354141235,51.1491165161],"type":"Point"}
}