{
  "type": "Feature",
  "properties": {
    "iso:country":"BE",
    "sg:address":"Basiliekstraat 14",
    "sg:city":"Halle",
    "sg:orig_category":"DIENSTEN VOOR TELECOMMUNICATIE Mobistar Centres Telecommunicatieapparaten Telecommunicatiesystemen",
    "sg:phone":"+32 2 356 82 98",
    "sg:postcode":"1500",
    "sg:province":"Vlaams-Brabant",
    "wof:name":"Mobistar Center Tofico",
    "wof:placetype":"venue"
},
  "geometry": {"coordinates":[4.2371277809,50.7356109619],"type":"Point"}
}