{
  "type": "Feature",
  "properties": {
    "iso:country":"BE",
    "sg:address":"Berthoudersplein 4",
    "sg:city":"Mechelen",
    "sg:classifiers":[
        {
            "category":"Building & Trades",
            "subcategory":"Construction",
            "type":"Services"
        }
    ],
    "sg:phone":"+32 15 71 07 58",
    "sg:postcode":"2800",
    "sg:province":"Antwerpen",
    "sg:tags":[
        "installation",
        "-",
        "central",
        "heating"
    ],
    "wof:name":"Perremans P",
    "wof:placetype":"venue"
},
  "geometry": {"coordinates":[4.4870381355,51.0260620117],"type":"Point"}
}