{
  "type": "Feature",
  "properties": {
    "addr:full":"Braban\u00c7onnelaan 64 Brussel/bruxelles Bruxelles-Capitale 1000",
    "addr:housenumber":"64",
    "addr:postcode":"1000",
    "addr:street":"Brabanc\u0327Onnelaan;/",
    "iso:country":"BE",
    "sg:address":"Braban\u00c7onnelaan 64",
    "sg:city":"Brussel/bruxelles",
    "sg:orig_category":"Elektrische installaties voor woningen",
    "sg:phone":"+32 2 735 31 59",
    "sg:postcode":"1000",
    "sg:province":"Bruxelles-Capitale",
    "wof:name":"Constant Hubert",
    "wof:placetype":"venue"
},
  "geometry": {"coordinates":[4.385846138,50.8498420715],"type":"Point"}
}