{
  "type": "Feature",
  "properties": {
    "iso:country":"BE",
    "sg:address":"Avenue Marius Renard 4b10",
    "sg:city":"Anderlecht",
    "sg:orig_category":"M\u00e9decins and sp\u00e9cialistes",
    "sg:phone":"+32 2 520 65 73",
    "sg:postcode":"1070",
    "sg:province":"Bruxelles-Capitale",
    "wof:name":"Jean-marc Verdebout",
    "wof:placetype":"venue"
},
  "geometry": {"coordinates":[4.2908439636,50.842502594],"type":"Point"}
}