{
  "type": "Feature",
  "properties": {
    "iso:country":"BE",
    "sg:address":"Meelstraat 8",
    "sg:city":"Gent",
    "sg:orig_category":"Meubles D\u00e9taillants, Am\u00e9nagement de B\u00e2timents et de Cuisines",
    "sg:phone":"+32 9 225 78 59",
    "sg:postcode":"9000",
    "sg:province":"Oost-Vlaanderen",
    "wof:name":"Andri-safe",
    "wof:placetype":"venue"
},
  "geometry": {"coordinates":[3.7178170681,51.0609931946],"type":"Point"}
}