{
  "type": "Feature",
  "properties": {
    "iso:country":"BE",
    "sg:address":"Blokstraat 70",
    "sg:city":"Boortmeerbeek",
    "sg:orig_category":"Artsen and specialisten",
    "sg:phone":"+32 15 61 79 61",
    "sg:postcode":"3191",
    "sg:province":"Vlaams-Brabant",
    "wof:name":"Frans Dhaenens",
    "wof:placetype":"venue"
},
  "geometry": {"coordinates":[4.5308218002,50.9752388],"type":"Point"}
}