{
  "type": "Feature",
  "properties": {
    "iso:country":"BE",
    "sg:address":"Square Marguerite 1b63",
    "sg:city":"Brussel/bruxelles",
    "sg:orig_category":"M\u00e9decins and sp\u00e9cialistes",
    "sg:phone":"+32 2 734 08 30",
    "sg:postcode":"1000",
    "sg:province":"Bruxelles-Capitale",
    "wof:name":"M. Hannes",
    "wof:placetype":"venue"
},
  "geometry": {"coordinates":[4.3851618767,50.8473625183],"type":"Point"}
}