{
  "type": "Feature",
  "properties": {
    "addr:full":"Rue Des Foss\u00c9s 28 Dinant Namur 5500",
    "addr:housenumber":"28",
    "addr:postcode":"5500",
    "addr:street":"Rue Des Fosse\u0301S",
    "iso:country":"BE",
    "sg:address":"Rue Des Foss\u00c9s 28",
    "sg:city":"Dinant",
    "sg:orig_category":"Bouwmaterialen Gh Serres and speciale beglazing Verlichting and huishoudartikelen",
    "sg:phone":"+32 82 22 28 57",
    "sg:postcode":"5500",
    "sg:province":"Namur",
    "wof:name":"Vitromeuse",
    "wof:placetype":"venue"
},
  "geometry": {"coordinates":[4.9146351814,50.2570114136],"type":"Point"}
}