{
  "type": "Feature",
  "properties": {
    "iso:country":"BE",
    "sg:address":"Hoogstraat 25-1",
    "sg:city":"Erpe-mere (erondegem)",
    "sg:classifiers":[
        {
            "category":"Shopping",
            "subcategory":"Clothing, Apparel, & Fashions",
            "type":"Retail Goods"
        }
    ],
    "sg:phone":"+32 53 80 75 99",
    "sg:postcode":"9420",
    "sg:province":"Oost-Vlaanderen",
    "sg:tags":[
        "clothing",
        "-",
        "gentleman"
    ],
    "wof:name":"Ben-jan-tom",
    "wof:placetype":"venue"
},
  "geometry": {"coordinates":[3.9569599628,50.9396629333],"type":"Point"}
}