{
  "type": "Feature",
  "properties": {
    "addr:full":"Nieuwelaan 41 Grimbergen (strombeek-bever) Vlaams-Brabant 1853",
    "addr:housenumber":"41",
    "addr:postcode":"1853",
    "addr:street":"Nieuwelaan",
    "iso:country":"BE",
    "sg:address":"Nieuwelaan 41",
    "sg:city":"Grimbergen (strombeek-bever)",
    "sg:orig_category":"Non-Classified Establishments",
    "sg:phone":"+32 2 267 29 91",
    "sg:postcode":"1853",
    "sg:province":"Vlaams-Brabant",
    "wof:name":"De Vogeleer Monique Bvba",
    "wof:placetype":"venue"
},
  "geometry": {"coordinates":[4.3509812355,50.9057579041],"type":"Point"}
}