{
  "type": "Feature",
  "properties": {
    "addr:full":"Vlazendaalstraat 25 Anderlecht Bruxelles-Capitale 1070",
    "addr:housenumber":"25",
    "addr:postcode":"1070",
    "addr:street":"Vlazendaalstraat",
    "iso:country":"BE",
    "sg:address":"Vlazendaalstraat 25",
    "sg:city":"Anderlecht",
    "sg:orig_category":"Werk and personeelsselectie",
    "sg:phone":"+32 2 527 03 09",
    "sg:postcode":"1070",
    "sg:province":"Bruxelles-Capitale",
    "wof:name":"Mottet & Associates",
    "wof:placetype":"venue"
},
  "geometry": {"coordinates":[4.2587881088,50.8342666626],"type":"Point"}
}