{
  "type": "Feature",
  "properties": {
    "addr:full":"Rue Du Gu\u00c9 43 Bl\u00c9gny Li\u00e8ge 4670",
    "addr:housenumber":"43",
    "addr:postcode":"4670",
    "addr:street":"Rue Du Gue\u0301",
    "iso:country":"BE",
    "sg:address":"Rue Du Gu\u00c9 43",
    "sg:city":"Bl\u00c9gny",
    "sg:orig_category":"Animaux domestiques and accessoires",
    "sg:phone":"+32 4 387 79 88",
    "sg:postcode":"4670",
    "sg:province":"Li\u00e8ge",
    "wof:name":"Premium Petfood Profess.",
    "wof:placetype":"venue"
},
  "geometry": {"coordinates":[5.7331418991,50.6866607666],"type":"Point"}
}