{
  "type": "Feature",
  "properties": {
    "iso:country":"BE",
    "sg:address":"Bredenakkerstraat 7",
    "sg:city":"Destelbergen",
    "sg:classifiers":[
        {
            "category":"Banks & Credit Unions",
            "subcategory":"Investment Brokerage",
            "type":"Services"
        }
    ],
    "sg:phone":"+32 9 229 22 13",
    "sg:postcode":"9070",
    "sg:province":"Oost-Vlaanderen",
    "sg:tags":[
        "repair",
        "-",
        "installation",
        "sanitary",
        "article"
    ],
    "wof:name":"Goossens P",
    "wof:placetype":"venue"
},
  "geometry": {"coordinates":[3.7639279366,51.0558357239],"type":"Point"}
}