{
  "type": "Feature",
  "properties": {
    "iso:country":"BE",
    "sg:address":"Attenrodestraat 10",
    "sg:city":"Tielt-winge",
    "sg:orig_category":"M\u00e9decins and sp\u00e9cialistes",
    "sg:phone":"+32 16 63 50 34",
    "sg:postcode":"3391",
    "sg:province":"Vlaams-Brabant",
    "wof:name":"H. Vandesande",
    "wof:placetype":"venue"
},
  "geometry": {"coordinates":[4.9229869843,50.8905563354],"type":"Point"}
}