{
  "type": "Feature",
  "properties": {
    "addr:full":"Molenstraat 31 Aalst Oost-Vlaanderen 9300",
    "addr:housenumber":"31",
    "addr:postcode":"9300",
    "addr:street":"Molenstraat",
    "iso:country":"BE",
    "sg:address":"Molenstraat 31",
    "sg:city":"Aalst",
    "sg:orig_category":"Cr\u00e9meries. Boissons",
    "sg:phone":"+32 53 70 05 29",
    "sg:postcode":"9300",
    "sg:province":"Oost-Vlaanderen",
    "wof:name":"Filliaert",
    "wof:placetype":"venue"
},
  "geometry": {"coordinates":[4.0412797928,50.9389457703],"type":"Point"}
}