{
  "type": "Feature",
  "properties": {
    "addr:full":"Rue Royale 163 Sint-joost-ten-node/saint-joss Bruxelles-Capitale 1210",
    "addr:housenumber":"163",
    "addr:postcode":"1210",
    "addr:street":"Rue Royale",
    "iso:country":"BE",
    "sg:address":"Rue Royale 163",
    "sg:city":"Sint-joost-ten-node/saint-joss",
    "sg:classifiers":[
        {
            "category":"Insurance",
            "subcategory":"Life Insurance",
            "type":"Services"
        }
    ],
    "sg:phone":"+32 2 219 02 50",
    "sg:postcode":"1210",
    "sg:province":"Bruxelles-Capitale",
    "sg:tags":[
        "assurance"
    ],
    "wof:name":"Pinel & Fils Assurances",
    "wof:placetype":"venue"
},
  "geometry": {"coordinates":[4.3663702011,50.8540229797],"type":"Point"}
}