{
  "type": "Feature",
  "properties": {
    "addr:full":"Rijn 117 Geel Antwerpen 2440",
    "addr:housenumber":"117",
    "addr:postcode":"2440",
    "addr:street":"Rijn",
    "iso:country":"BE",
    "sg:address":"Rijn 117",
    "sg:city":"Geel",
    "sg:classifiers":[
        {
            "category":"Personal",
            "subcategory":"Beauty Salon",
            "type":"Services"
        }
    ],
    "sg:phone":"+32 14 58 62 61",
    "sg:postcode":"2440",
    "sg:province":"Antwerpen",
    "sg:tags":[
        "de",
        "coiffure"
    ],
    "wof:name":"Coiffure Chantal",
    "wof:placetype":"venue"
},
  "geometry": {"coordinates":[5.0128569603,51.1633148193],"type":"Point"}
}