{
  "type": "Feature",
  "properties": {
    "iso:country":"BE",
    "sg:address":"Leuvensesteenweg 201ba3",
    "sg:city":"Tielt-winge",
    "sg:orig_category":"Advocaten and juridische adviseurs",
    "sg:phone":"+32 16 63 42 25",
    "sg:postcode":"3390",
    "sg:province":"Vlaams-Brabant",
    "wof:name":"F. Duerinckx",
    "wof:placetype":"venue"
},
  "geometry": {"coordinates":[4.8769779205,50.907623291],"type":"Point"}
}