{
  "type": "Feature",
  "properties": {
    "iso:country":"BE",
    "sg:address":"Nivez\u00c9 Bas 159",
    "sg:city":"Jalhay",
    "sg:orig_category":"Charpentes and couvertures",
    "sg:phone":"+32 87 77 10 62",
    "sg:postcode":"4845",
    "sg:province":"Li\u00e8ge",
    "wof:name":"Gerlaxhe P.",
    "wof:placetype":"venue"
},
  "geometry": {"coordinates":[5.8996210098,50.5005378723],"type":"Point"}
}