{
  "type": "Feature",
  "properties": {
    "addr:full":"Rue De Rosi\u00c8res 71 Rixensart Brabant Wallon 1332",
    "addr:housenumber":"71",
    "addr:postcode":"1332",
    "addr:street":"Rue De Rosie\u0300Res;Wallon",
    "iso:country":"BE",
    "sg:address":"Rue De Rosi\u00c8res 71",
    "sg:city":"Rixensart",
    "sg:orig_category":"Binnenhuisarchitecten Etalage- and showroomontwerpers Plaatsen van vloer- and muurbekleding Schilder",
    "sg:phone":"+32 2 653 41 26",
    "sg:postcode":"1332",
    "sg:province":"Brabant Wallon",
    "wof:name":"Carels Design Group",
    "wof:placetype":"venue"
},
  "geometry": {"coordinates":[4.52039814,50.7253608704],"type":"Point"}
}