{
  "type": "Feature",
  "properties": {
    "addr:full":"Avenue Louis Bertrand 6 Bruxelles (schaerbeek) Bruxelles-Capitale 1030",
    "addr:housenumber":"6",
    "addr:postcode":"1030",
    "addr:street":"Avenue Louis Bertrand",
    "iso:country":"BE",
    "sg:address":"Avenue Louis Bertrand 6",
    "sg:city":"Bruxelles (schaerbeek)",
    "sg:classifiers":[
        {
            "category":"Professional",
            "subcategory":"Engineering",
            "type":"Services"
        }
    ],
    "sg:phone":"+32 2 245 23 41",
    "sg:postcode":"1030",
    "sg:province":"Bruxelles-Capitale",
    "sg:tags":[
        "technical",
        "industrial",
        "-",
        "subcontracting"
    ],
    "wof:name":"Van Doorsselaere G",
    "wof:placetype":"venue"
},
  "geometry": {"coordinates":[4.3740592003,50.8642845154],"type":"Point"}
}