{
  "type": "Feature",
  "properties": {
    "addr:full":"Emile Beauduinstraat 11 Gingelom Limburg 3890",
    "addr:housenumber":"11",
    "addr:postcode":"3890",
    "addr:street":"Beauduinstraat",
    "iso:country":"BE",
    "sg:address":"Emile Beauduinstraat 11",
    "sg:city":"Gingelom",
    "sg:orig_category":"Industri\u00eble wasserijen and droogkuis",
    "sg:phone":"+32 11 48 56 92",
    "sg:postcode":"3890",
    "sg:province":"Limburg",
    "wof:name":"St-joris",
    "wof:placetype":"venue"
},
  "geometry": {"coordinates":[5.1873340607,50.7227287292],"type":"Point"}
}