{
  "type": "Feature",
  "properties": {
    "addr:full":"Nationalestraat 5 Antwerpen Antwerpen 2000",
    "addr:housenumber":"5",
    "addr:postcode":"2000",
    "addr:street":"Nationalestraat",
    "iso:country":"BE",
    "sg:address":"Nationalestraat 5",
    "sg:city":"Antwerpen",
    "sg:orig_category":"Enseignement sup\u00e9rieur",
    "sg:phone":"+32 3 205 18 00",
    "sg:postcode":"2000",
    "sg:province":"Antwerpen",
    "wof:name":"Kdg-campus Groenplaats",
    "wof:placetype":"venue"
},
  "geometry": {"coordinates":[4.4006509781,51.2179260254],"type":"Point"}
}