{
  "type": "Feature",
  "properties": {
    "iso:country":"BE",
    "sg:address":"Donksesteenweg 212",
    "sg:city":"Brasschaat",
    "sg:classifiers":[
        {
            "category":"Shopping",
            "subcategory":"Clothing, Apparel, & Fashions",
            "type":"Retail Goods"
        }
    ],
    "sg:phone":"+32 3 644 76 40",
    "sg:postcode":"2930",
    "sg:province":"Antwerpen",
    "sg:tags":[
        "underwear",
        "lingerie",
        "-"
    ],
    "wof:name":"New Dranabou",
    "wof:placetype":"venue"
},
  "geometry": {"coordinates":[4.4540362358,51.2810211182],"type":"Point"}
}