{
  "type": "Feature",
  "properties": {
    "addr:full":"Grote Markt 61b61 Sint-niklaas Oost-Vlaanderen 9100",
    "addr:housenumber":"61b61",
    "addr:postcode":"9100",
    "addr:street":"Grote Markt",
    "iso:country":"BE",
    "sg:address":"Grote Markt 61b61",
    "sg:city":"Sint-niklaas",
    "sg:orig_category":"Eclairage et \u00e9quipements du foyer",
    "sg:phone":"+32 3 766 85 67",
    "sg:postcode":"9100",
    "sg:province":"Oost-Vlaanderen",
    "wof:name":"Life Style",
    "wof:placetype":"venue"
},
  "geometry": {"coordinates":[4.1409869194,51.1650848389],"type":"Point"}
}