{
  "type": "Feature",
  "properties": {
    "iso:country":"BE",
    "sg:address":"Winterdreef 15",
    "sg:city":"Oud-turnhout",
    "sg:orig_category":"Pleisterwerk",
    "sg:phone":"+32 14 45 22 32",
    "sg:postcode":"2360",
    "sg:province":"Antwerpen",
    "wof:name":"Jan Theeuws",
    "wof:placetype":"venue"
},
  "geometry": {"coordinates":[5.0040359497,51.2999801636],"type":"Point"}
}