{
  "type": "Feature",
  "properties": {
    "iso:country":"BE",
    "sg:address":"Rue De Givet 26",
    "sg:city":"Beauraing",
    "sg:classifiers":[
        {
            "category":"Personal",
            "subcategory":"Nail Salon",
            "type":"Services"
        }
    ],
    "sg:phone":"+32 82 71 19 79",
    "sg:postcode":"5570",
    "sg:province":"Namur",
    "sg:tags":[
        "pedicure"
    ],
    "wof:name":"Verbelen S",
    "wof:placetype":"venue"
},
  "geometry": {"coordinates":[4.9539089203,50.111125946],"type":"Point"}
}