{
  "type": "Feature",
  "properties": {
    "iso:country":"BE",
    "sg:address":"Wilbroek 7",
    "sg:city":"Beringen",
    "sg:orig_category":"Installation de menuiserie en bois and plastique",
    "sg:phone":"+32 13 66 82 26",
    "sg:postcode":"3583",
    "sg:province":"Limburg",
    "wof:name":"Theo Moons",
    "wof:placetype":"venue"
},
  "geometry": {"coordinates":[5.1706700325,51.0389442444],"type":"Point"}
}