{
  "type": "Feature",
  "properties": {
    "iso:country":"BE",
    "sg:address":"Bergstraat 72",
    "sg:city":"Nieuwerkerken",
    "sg:orig_category":"Fruitteelt",
    "sg:phone":"+32 11 31 29 07",
    "sg:postcode":"3850",
    "sg:province":"Limburg",
    "wof:name":"Fernand Wanten",
    "wof:placetype":"venue"
},
  "geometry": {"coordinates":[5.2391471863,50.8690109253],"type":"Point"}
}