{
  "type": "Feature",
  "properties": {
    "addr:full":"Chauss\u00e9e De Waterloo 119 Rhode-saint-gen\u00e8se Vlaams-Brabant 1640",
    "addr:housenumber":"119",
    "addr:postcode":"rhode-saint-gene\u0300se;1640",
    "addr:street":"Chausse\u0301E De Waterloo",
    "iso:country":"BE",
    "sg:address":"Chauss\u00e9e De Waterloo 119",
    "sg:city":"Rhode-saint-gen\u00e8se",
    "sg:classifiers":[
        {
            "category":"Building & Trades",
            "subcategory":"Pest Control",
            "type":"Services"
        }
    ],
    "sg:phone":"+32 2 358 11 81",
    "sg:postcode":"1640",
    "sg:province":"Vlaams-Brabant",
    "sg:tags":[
        "painting",
        "contractor"
    ],
    "wof:name":"Fior",
    "wof:placetype":"venue"
},
  "geometry": {"coordinates":[4.3960881233,50.7352256775],"type":"Point"}
}