{
  "type": "Feature",
  "properties": {
    "addr:full":"Chauss\u00e9e De Willemeau 257 Tournai Hainaut 7500",
    "addr:housenumber":"257",
    "addr:postcode":"7500",
    "addr:street":"Chausse\u0301E De Willemeau",
    "iso:country":"BE",
    "sg:address":"Chauss\u00e9e De Willemeau 257",
    "sg:city":"Tournai",
    "sg:classifiers":[
        {
            "category":"Health Services",
            "subcategory":"Nursing And Care Facility",
            "type":"Services"
        }
    ],
    "sg:phone":"+32 477 20 95 44",
    "sg:postcode":"7500",
    "sg:province":"Hainaut",
    "sg:tags":[
        "home"
    ],
    "wof:name":"Vanderhaeghen Paulette",
    "wof:placetype":"venue"
},
  "geometry": {"coordinates":[3.3724069595,50.590801239],"type":"Point"}
}