{
  "type": "Feature",
  "properties": {
    "addr:full":"Norbertijnerlei 34 Duffel Antwerpen 2570",
    "addr:housenumber":"34",
    "addr:postcode":"2570",
    "addr:street":"Norbertijnerlei",
    "iso:country":"BE",
    "sg:address":"Norbertijnerlei 34",
    "sg:city":"Duffel",
    "sg:orig_category":"Protection civile",
    "sg:phone":"+32 15 31 12 02",
    "sg:postcode":"2570",
    "sg:province":"Antwerpen",
    "wof:name":"Brandweerkazerne",
    "wof:placetype":"venue"
},
  "geometry": {"coordinates":[4.4979019165,51.0887908936],"type":"Point"}
}