{
  "type": "Feature",
  "properties": {
    "addr:full":"Verdunstraat 459 Brussel/bruxelles Bruxelles-Capitale 1130",
    "addr:housenumber":"459",
    "addr:postcode":"1130",
    "addr:street":"Verdunstraat;/",
    "iso:country":"BE",
    "sg:address":"Verdunstraat 459",
    "sg:city":"Brussel/bruxelles",
    "sg:orig_category":"Elektrische installaties voor woningen MEUBELONTWERP AND -INSTALLATIE",
    "sg:phone":"+32 2 216 45 44",
    "sg:postcode":"1130",
    "sg:province":"Bruxelles-Capitale",
    "wof:name":"H.r.",
    "wof:placetype":"venue"
},
  "geometry": {"coordinates":[4.4184570312,50.8924255371],"type":"Point"}
}