{
  "type": "Feature",
  "properties": {
    "iso:country":"BE",
    "sg:address":"Rue De La Bach\u00e9e 53",
    "sg:city":"Lasne (plancenoit)",
    "sg:classifiers":[
        {
            "category":"Health Services",
            "subcategory":"Health Practitioner",
            "type":"Services"
        }
    ],
    "sg:phone":"+32 2 633 26 35",
    "sg:postcode":"1380",
    "sg:province":"Brabant Wallon",
    "sg:tags":[
        "physiotherapist"
    ],
    "wof:name":"Lechien Sylvie",
    "wof:placetype":"venue"
},
  "geometry": {"coordinates":[4.4259171486,50.6597671509],"type":"Point"}
}