{
  "type": "Feature",
  "properties": {
    "iso:country":"BE",
    "sg:address":"Avenue De Tervueren 412 Box 8",
    "sg:city":"Bruxelles (woluwe-saint-pierre)",
    "sg:classifiers":[
        {
            "category":"Insurance",
            "subcategory":"Insurance Agent",
            "type":"Services"
        }
    ],
    "sg:phone":"+32 2 776 32 11",
    "sg:postcode":"1150",
    "sg:province":"Bruxelles-Capitale",
    "sg:tags":[
        "-",
        "representative"
    ],
    "wof:name":"Civis G I E",
    "wof:placetype":"venue"
},
  "geometry": {"coordinates":[4.4450421333,50.8274459839],"type":"Point"}
}