{
  "type": "Feature",
  "properties": {
    "iso:country":"BE",
    "sg:address":"De Westakker 122",
    "sg:city":"Wevelgem",
    "sg:classifiers":[
        {
            "category":"Arena",
            "subcategory":"Sports Club",
            "type":"Entertainment"
        }
    ],
    "sg:phone":"+32 56 41 45 50",
    "sg:postcode":"8560",
    "sg:province":"West-Vlaanderen",
    "sg:tags":[
        "terrain",
        "hors",
        "de",
        "installation",
        "sportifs"
    ],
    "wof:name":"S.k. Gullegem",
    "wof:placetype":"venue"
},
  "geometry": {"coordinates":[3.2018198967,50.8496894836],"type":"Point"}
}