{
  "type": "Feature",
  "properties": {
    "iso:country":"BE",
    "sg:address":"Poststraat 4a",
    "sg:city":"Ham (kwaadmechelen)",
    "sg:classifiers":[
        {
            "category":"Insurance",
            "subcategory":"Insurance Agent",
            "type":"Services"
        }
    ],
    "sg:phone":"+32 13 67 15 64",
    "sg:postcode":"3945",
    "sg:province":"Limburg",
    "sg:tags":[
        "broker"
    ],
    "wof:name":"Theys P-govaerts & Co Bvba",
    "wof:placetype":"venue"
},
  "geometry": {"coordinates":[5.1776199341,51.1046104431],"type":"Point"}
}