{
  "type": "Feature",
  "properties": {
    "addr:full":"Gasthuisbosdreef 16 Tongeren Limburg 3700",
    "addr:housenumber":"16",
    "addr:postcode":"3700",
    "addr:street":"Gasthuisbosdreef",
    "iso:country":"BE",
    "sg:address":"Gasthuisbosdreef 16",
    "sg:city":"Tongeren",
    "sg:orig_category":"Installation de menuiserie m\u00e9tallique",
    "sg:phone":"+32 475 58 21 03",
    "sg:postcode":"3700",
    "sg:province":"Limburg",
    "wof:name":"Hendrix Tony",
    "wof:placetype":"venue"
},
  "geometry": {"coordinates":[5.4530239105,50.7917098999],"type":"Point"}
}