{
  "type": "Feature",
  "properties": {
    "iso:country":"BE",
    "sg:address":"Rue F\u00e9lix Protin 3",
    "sg:city":"Sambreville (auvelais)",
    "sg:classifiers":[
        {
            "category":"Retail",
            "subcategory":"Repair Shop",
            "type":"Services"
        }
    ],
    "sg:phone":"+32 71 77 34 06",
    "sg:postcode":"5060",
    "sg:province":"Namur",
    "sg:tags":[
        "machine",
        "sewing",
        "-"
    ],
    "wof:name":"Calomne Sprl",
    "wof:placetype":"venue"
},
  "geometry": {"coordinates":[4.6285200119,50.4448738098],"type":"Point"}
}