{
  "type": "Feature",
  "properties": {
    "iso:country":"BE",
    "sg:address":"Longvilly 27",
    "sg:city":"Bastogne",
    "sg:classifiers":[
        {
            "category":"Insurance",
            "subcategory":"Life Insurance",
            "type":"Services"
        }
    ],
    "sg:phone":"+32 61 21 84 11",
    "sg:postcode":"6600",
    "sg:province":"Luxembourg",
    "sg:tags":[
        "assurance"
    ],
    "wof:name":"B. Bouvy",
    "wof:placetype":"venue"
},
  "geometry": {"coordinates":[5.7148199081,50.0007820129],"type":"Point"}
}