{
  "type": "Feature",
  "properties": {
    "addr:full":"Kerkstraat 27 Middelkerke West-Vlaanderen 8430",
    "addr:housenumber":"27",
    "addr:postcode":"8430",
    "addr:street":"Kerkstraat",
    "iso:country":"BE",
    "sg:address":"Kerkstraat 27",
    "sg:city":"Middelkerke",
    "sg:classifiers":[
        {
            "category":"Tea Room",
            "subcategory":"None",
            "type":"Food & Drink"
        }
    ],
    "sg:phone":"+32 59 30 64 49",
    "sg:postcode":"8430",
    "sg:province":"West-Vlaanderen",
    "wof:name":"Mollebolle",
    "wof:placetype":"venue"
},
  "geometry": {"coordinates":[2.8203859329,51.18592453],"type":"Point"}
}