{
  "type": "Feature",
  "properties": {
    "iso:country":"BE",
    "sg:address":"Rue Remikette 37",
    "sg:city":"Faimes",
    "sg:orig_category":"Diensten voor huisdieren Huisdieren and benodigdheden",
    "sg:phone":"+32 19 56 91 05",
    "sg:postcode":"4317",
    "sg:province":"Li\u00e8ge",
    "wof:name":"Toilettage Teddy",
    "wof:placetype":"venue"
},
  "geometry": {"coordinates":[5.2116951942,50.6409568787],"type":"Point"}
}