{
  "type": "Feature",
  "properties": {
    "iso:country":"BE",
    "sg:address":"Schuddebeurzeweg 54",
    "sg:city":"Middelkerke",
    "sg:orig_category":"G\u00e9om\u00e8tres",
    "sg:phone":"+32 58 23 67 36",
    "sg:postcode":"8434",
    "sg:province":"West-Vlaanderen",
    "wof:name":"Michel Luyssen",
    "wof:placetype":"venue"
},
  "geometry": {"coordinates":[2.7569050789,51.1488685608],"type":"Point"}
}