{
  "type": "Feature",
  "properties": {
    "addr:full":"Parklaan 13b Aalst Oost-Vlaanderen 9300",
    "addr:housenumber":"13b",
    "addr:postcode":"9300",
    "addr:street":"Parklaan",
    "iso:country":"BE",
    "sg:address":"Parklaan 13b",
    "sg:city":"Aalst",
    "sg:classifiers":[
        {
            "category":"Health Services",
            "subcategory":"Doctor",
            "type":"Services"
        }
    ],
    "sg:phone":"+32 53 71 00 93",
    "sg:postcode":"9300",
    "sg:province":"Oost-Vlaanderen",
    "sg:tags":[
        "orthopedist"
    ],
    "wof:name":"Ortho-shop Aalst",
    "wof:placetype":"venue"
},
  "geometry": {"coordinates":[4.0453572273,50.9322547913],"type":"Point"}
}