{
  "type": "Feature",
  "properties": {
    "addr:full":"Rue Inchebroux 7 Chaumont-gistoux Brabant Wallon 1325",
    "addr:housenumber":"7",
    "addr:postcode":"1325",
    "addr:street":"Rue Inchebroux",
    "iso:country":"BE",
    "sg:address":"Rue Inchebroux 7",
    "sg:city":"Chaumont-gistoux",
    "sg:classifiers":[
        {
            "category":"Professional",
            "subcategory":"Accounting & Tax Preparation",
            "type":"Services"
        }
    ],
    "sg:phone":"+32 10 84 64 30",
    "sg:postcode":"1325",
    "sg:province":"Brabant Wallon",
    "sg:tags":[
        "accountant"
    ],
    "wof:name":"Monfils Chr",
    "wof:placetype":"venue"
},
  "geometry": {"coordinates":[4.6918358803,50.6894416809],"type":"Point"}
}