{
  "type": "Feature",
  "properties": {
    "iso:country":"BE",
    "sg:address":"Leihoekstraat 7",
    "sg:city":"Zulte",
    "sg:orig_category":"Enseignement maternel and primaire",
    "sg:phone":"+32 9 386 52 57",
    "sg:postcode":"9870",
    "sg:province":"Oost-Vlaanderen",
    "wof:name":"Vrije Basisschool",
    "wof:placetype":"venue"
},
  "geometry": {"coordinates":[3.4844579697,50.9607086182],"type":"Point"}
}