{
  "type": "Feature",
  "properties": {
    "addr:full":"Begonialaan 11 Affligem Vlaams-Brabant 1790",
    "addr:housenumber":"11",
    "addr:postcode":"1790",
    "addr:street":"Begonialaan",
    "iso:country":"BE",
    "sg:address":"Begonialaan 11",
    "sg:city":"Affligem",
    "sg:orig_category":"Verhuur televisie- and audiovisuele apparatuur",
    "sg:phone":"+32 53 66 10 15",
    "sg:postcode":"1790",
    "sg:province":"Vlaams-Brabant",
    "wof:name":"Jimmy Schelfhout",
    "wof:placetype":"venue"
},
  "geometry": {"coordinates":[4.0959839821,50.8908004761],"type":"Point"}
}