{
  "type": "Feature",
  "properties": {
    "addr:full":"Altenastraat 43 Heers Limburg 3870",
    "addr:housenumber":"43",
    "addr:postcode":"3870",
    "addr:street":"Altenastraat",
    "iso:country":"BE",
    "sg:address":"Altenastraat 43",
    "sg:city":"Heers",
    "sg:orig_category":"Eleveurs de bovins",
    "sg:phone":"+32 11 48 41 18",
    "sg:postcode":"3870",
    "sg:province":"Limburg",
    "wof:name":"Jean-marie Jadoul",
    "wof:placetype":"venue"
},
  "geometry": {"coordinates":[5.2493729591,50.7371139526],"type":"Point"}
}