{
  "type": "Feature",
  "properties": {
    "iso:country":"BE",
    "sg:address":"Molenlei 26",
    "sg:city":"Mortsel",
    "sg:classifiers":[
        {
            "category":"Fast Food",
            "type":"Food & Drink"
        }
    ],
    "sg:phone":"+32 3 449 68 16",
    "sg:postcode":"2640",
    "sg:province":"Antwerpen",
    "sg:tags":[
        "fried",
        "stand",
        "potato"
    ],
    "wof:name":"De Molenlei Cvba",
    "wof:placetype":"venue"
},
  "geometry": {"coordinates":[4.452144146,51.1626853943],"type":"Point"}
}