{
  "type": "Feature",
  "properties": {
    "addr:full":"Herent 85 Neerpelt Limburg 3910",
    "addr:housenumber":"85",
    "addr:postcode":"3910",
    "addr:street":"Herent",
    "iso:country":"BE",
    "sg:address":"Herent 85",
    "sg:city":"Neerpelt",
    "sg:orig_category":"Eleveurs de bovins",
    "sg:phone":"+32 11 64 32 03",
    "sg:postcode":"3910",
    "sg:province":"Limburg",
    "wof:name":"Emiel Fransen",
    "wof:placetype":"venue"
},
  "geometry": {"coordinates":[5.4444208145,51.2056465149],"type":"Point"}
}