{
  "type": "Feature",
  "properties": {
    "iso:country":"BE",
    "sg:address":"Hubert D'ydewallestraat 70 Box 2",
    "sg:city":"Beernem",
    "sg:classifiers":[
        {
            "category":"Arts & Performance",
            "subcategory":"Music",
            "type":"Entertainment"
        }
    ],
    "sg:phone":"+32 50 78 81 25",
    "sg:postcode":"8730",
    "sg:province":"West-Vlaanderen",
    "sg:tags":[
        "disc-jockeys"
    ],
    "wof:name":"Studio Dms",
    "wof:placetype":"venue"
},
  "geometry": {"coordinates":[3.3203160763,51.1297149658],"type":"Point"}
}