{
  "type": "Feature",
  "properties": {
    "addr:full":"Rubensstraat 120 Vilvoorde Vlaams-Brabant 1800",
    "addr:housenumber":"120",
    "addr:postcode":"1800",
    "addr:street":"Rubensstraat",
    "iso:country":"BE",
    "sg:address":"Rubensstraat 120",
    "sg:city":"Vilvoorde",
    "sg:orig_category":"Verhuur voertuigen behalve auto's",
    "sg:phone":"+32 800 16 666",
    "sg:postcode":"1800",
    "sg:province":"Vlaams-Brabant",
    "wof:name":"Trend-rent",
    "wof:placetype":"venue"
},
  "geometry": {"coordinates":[4.4052882195,50.9245796204],"type":"Point"}
}