{
  "type": "Feature",
  "properties": {
    "iso:country":"BE",
    "sg:address":"Eiland 5",
    "sg:city":"Sint-lievens-houtem",
    "sg:orig_category":"M\u00e9decins and sp\u00e9cialistes",
    "sg:phone":"+32 53 62 35 35",
    "sg:postcode":"9520",
    "sg:province":"Oost-Vlaanderen",
    "wof:name":"Walter Van Vaerenbergh",
    "wof:placetype":"venue"
},
  "geometry": {"coordinates":[3.8594470024,50.921497345],"type":"Point"}
}