{
  "type": "Feature",
  "properties": {
    "iso:country":"BE",
    "sg:address":"Vlasmarkt 28",
    "sg:city":"Antwerpen",
    "sg:classifiers":[
        {
            "category":"Real Estate",
            "subcategory":"Real Estate Services",
            "type":"Services"
        }
    ],
    "sg:phone":"+32 3 231 87 22",
    "sg:postcode":"2000",
    "sg:province":"Antwerpen",
    "sg:tags":[
        "boarding",
        "house"
    ],
    "wof:name":"Griekse Gemeenschap Van Antwerpen-grieks Zeemanshuis",
    "wof:placetype":"venue"
},
  "geometry": {"coordinates":[4.3975319862,51.2195549011],"type":"Point"}
}