{
  "type": "Feature",
  "properties": {
    "addr:full":"Roeselarestraat 275 Wevelgem West-Vlaanderen 8560",
    "addr:housenumber":"275",
    "addr:postcode":"8560",
    "addr:street":"Roeselarestraat",
    "iso:country":"BE",
    "sg:address":"Roeselarestraat 275",
    "sg:city":"Wevelgem",
    "sg:orig_category":"Catering and organisation de f\u00eates",
    "sg:phone":"+32 56 40 31 26",
    "sg:postcode":"8560",
    "sg:province":"West-Vlaanderen",
    "wof:name":"Katrien Stragier",
    "wof:placetype":"venue"
},
  "geometry": {"coordinates":[3.1773459911,50.8190689087],"type":"Point"}
}