{
  "type": "Feature",
  "properties": {
    "iso:country":"BE",
    "sg:address":"Kerkhoflei 39",
    "sg:city":"Mechelen",
    "sg:classifiers":[
        {
            "category":"Social Services",
            "type":"Services"
        }
    ],
    "sg:phone":"+32 15 20 19 99",
    "sg:postcode":"2800",
    "sg:province":"Antwerpen",
    "sg:tags":[
        "handicapped",
        "-"
    ],
    "wof:name":"Katholieke Vereniging Voor Gehandicapten",
    "wof:placetype":"venue"
},
  "geometry": {"coordinates":[4.4822850227,51.0381393433],"type":"Point"}
}