{
  "type": "Feature",
  "properties": {
    "addr:full":"Koning Albert I Laan 63 Roeselare West-Vlaanderen 8800",
    "addr:housenumber":"63",
    "addr:postcode":"8800",
    "addr:street":"Koning Albert I Laan",
    "iso:country":"BE",
    "sg:address":"Koning Albert I Laan 63",
    "sg:city":"Roeselare",
    "sg:classifiers":[
        {
            "category":"Autos & Motor Vehicles",
            "subcategory":"Automobile Sales",
            "type":"Retail Goods"
        }
    ],
    "sg:phone":"+32 51 20 84 14",
    "sg:postcode":"8800",
    "sg:province":"West-Vlaanderen",
    "sg:tags":[
        "car",
        "used",
        "-"
    ],
    "wof:name":"Callebert",
    "wof:placetype":"venue"
},
  "geometry": {"coordinates":[3.1308920383,50.9410743713],"type":"Point"}
}