{
  "type": "Feature",
  "properties": {
    "addr:full":"Rue Arnold Trillet 32 Soumagne Li\u00e8ge 4630",
    "addr:housenumber":"32",
    "addr:postcode":"4630",
    "addr:street":"Rue Arnold Trillet",
    "iso:country":"BE",
    "sg:address":"Rue Arnold Trillet 32",
    "sg:city":"Soumagne",
    "sg:classifiers":[
        {
            "category":"Farming",
            "subcategory":"Farm & Veterinary Services",
            "type":"Manufacturing & Wholesale Goods"
        }
    ],
    "sg:phone":"+32 4 377 40 49",
    "sg:postcode":"4630",
    "sg:province":"Li\u00e8ge",
    "sg:tags":[
        "agricultural",
        "contractor"
    ],
    "wof:name":"Deflandre J P",
    "wof:placetype":"venue"
},
  "geometry": {"coordinates":[5.7262601852,50.6223602295],"type":"Point"}
}