{
  "type": "Feature",
  "properties": {
    "iso:country":"BE",
    "sg:address":"Rue De Tubize 137",
    "sg:city":"Braine-le-chateau",
    "sg:orig_category":"Drukkerijen and copyshops",
    "sg:phone":"+32 2 366 99 60",
    "sg:postcode":"1440",
    "sg:province":"Brabant Wallon",
    "wof:name":"Meurice Printing",
    "wof:placetype":"venue"
},
  "geometry": {"coordinates":[4.2492070198,50.6804237366],"type":"Point"}
}