{
  "type": "Feature",
  "properties": {
    "addr:full":"Sint-ursmarusstraat 180 Dendermonde (baasrode) Oost-Vlaanderen 9200",
    "addr:housenumber":"180",
    "addr:postcode":"9200",
    "addr:street":"Sint-Ursmarusstraat",
    "iso:country":"BE",
    "sg:address":"Sint-ursmarusstraat 180",
    "sg:city":"Dendermonde (baasrode)",
    "sg:classifiers":[
        {
            "category":"Home & Garden",
            "subcategory":"Home Furnishings",
            "type":"Retail Goods"
        }
    ],
    "sg:phone":"+32 52 33 66 35",
    "sg:postcode":"9200",
    "sg:province":"Oost-Vlaanderen",
    "sg:tags":[
        "interior",
        "decoration"
    ],
    "wof:name":"Multiform Bvba",
    "wof:placetype":"venue"
},
  "geometry": {"coordinates":[4.0983099937,51.0315208435],"type":"Point"}
}