{
  "type": "Feature",
  "properties": {
    "addr:full":"Avenue Peltzer 8 Box 6 Verviers Li\u00e8ge 4800",
    "addr:housenumber":"8;6",
    "addr:postcode":"4800",
    "addr:street":"Avenue Peltzer;Box",
    "iso:country":"BE",
    "sg:address":"Avenue Peltzer 8 Box 6",
    "sg:city":"Verviers",
    "sg:classifiers":[
        {
            "category":"Health Services",
            "subcategory":"Health Practitioner",
            "type":"Services"
        }
    ],
    "sg:phone":"+32 87 22 01 78",
    "sg:postcode":"4800",
    "sg:province":"Li\u00e8ge",
    "sg:tags":[
        "physiotherapist"
    ],
    "wof:name":"Julemont St\u00e9phanie",
    "wof:placetype":"venue"
},
  "geometry": {"coordinates":[5.8586769104,50.5858573914],"type":"Point"}
}