{
  "type": "Feature",
  "properties": {
    "iso:country":"BE",
    "sg:address":"Rue L\u00b4eglise St.-etienne 3",
    "sg:city":"Lasne",
    "sg:orig_category":"Beheer onroerend goed",
    "sg:phone":"+32 2 633 68 53",
    "sg:postcode":"1380",
    "sg:province":"Brabant Wallon",
    "wof:name":"Soc.civ.immob.dieleghem",
    "wof:placetype":"venue"
},
  "geometry": {"coordinates":[4.470290184,50.6958351135],"type":"Point"}
}