{
  "type": "Feature",
  "properties": {
    "iso:country":"BE",
    "sg:address":"Rue Basse 14",
    "sg:city":"Mesen/messines",
    "sg:orig_category":"M\u00e9decins and sp\u00e9cialistes",
    "sg:phone":"+32 57 44 49 54",
    "sg:postcode":"8957",
    "sg:province":"West-Vlaanderen",
    "wof:name":"Paul Lambelin",
    "wof:placetype":"venue"
},
  "geometry": {"coordinates":[2.8981010914,50.7629203796],"type":"Point"}
}