{
  "type": "Feature",
  "properties": {
    "iso:country":"BE",
    "sg:address":"Rue Naniot 87",
    "sg:city":"Li\u00c8ge",
    "sg:orig_category":"Catering and organisatie van feesten",
    "sg:phone":"+32 4 224 05 33",
    "sg:postcode":"4000",
    "sg:province":"Li\u00e8ge",
    "wof:name":"Les Buffets De Sophie",
    "wof:placetype":"venue"
},
  "geometry": {"coordinates":[5.5546011925,50.6508636475],"type":"Point"}
}