{
  "type": "Feature",
  "properties": {
    "addr:full":"Vaartstraat 31 Brecht Antwerpen 2960",
    "addr:housenumber":"31",
    "addr:postcode":"2960",
    "addr:street":"Vaartstraat",
    "iso:country":"BE",
    "sg:address":"Vaartstraat 31",
    "sg:city":"Brecht",
    "sg:classifiers":[
        {
            "category":"Building & Trades",
            "subcategory":"Construction",
            "type":"Services"
        }
    ],
    "sg:phone":"+32 3 313 95 08",
    "sg:postcode":"2960",
    "sg:province":"Antwerpen",
    "sg:tags":[
        "paper",
        "hanger"
    ],
    "wof:name":"Heymans J & Zonen",
    "wof:placetype":"venue"
},
  "geometry": {"coordinates":[4.6442708969,51.3469963074],"type":"Point"}
}