{
  "type": "Feature",
  "properties": {
    "addr:full":"Ambachtenstraat 11 Eeklo Oost-Vlaanderen 9900",
    "addr:housenumber":"11",
    "addr:postcode":"9900",
    "addr:street":"Ambachtenstraat",
    "iso:country":"BE",
    "sg:address":"Ambachtenstraat 11",
    "sg:city":"Eeklo",
    "sg:classifiers":[
        {
            "category":"Community Center",
            "subcategory":"Ethnic",
            "type":"Public Place"
        }
    ],
    "sg:phone":"+32 9 378 28 44",
    "sg:postcode":"9900",
    "sg:province":"Oost-Vlaanderen",
    "sg:tags":[
        "fibre",
        "optical"
    ],
    "wof:name":"Electroteam Leloup & Co Nv",
    "wof:placetype":"venue"
},
  "geometry": {"coordinates":[3.546104908,51.177444458],"type":"Point"}
}