{
  "type": "Feature",
  "properties": {
    "addr:full":"Marktstr 36 Opwijk 1890",
    "addr:housenumber":"36",
    "addr:postcode":"1890",
    "addr:street":"Marktstr",
    "iso:country":"BE",
    "sg:address":"Marktstr 36",
    "sg:city":"Opwijk",
    "sg:classifiers":[
        {
            "category":"Banks & Credit Unions",
            "subcategory":"Bank",
            "type":"Services"
        }
    ],
    "sg:phone":"+32 52 35 70 61",
    "sg:postcode":"1890",
    "wof:name":"Banque Bruxelles Lambert Sa",
    "wof:placetype":"venue"
},
  "geometry": {"coordinates":[4.1886200905,50.9701271057],"type":"Point"}
}