{
  "type": "Feature",
  "properties": {
    "addr:full":"Burgstraat 22 Destelbergen Oost-Vlaanderen 9070",
    "addr:housenumber":"22",
    "addr:postcode":"9070",
    "addr:street":"Burgstraat",
    "iso:country":"BE",
    "sg:address":"Burgstraat 22",
    "sg:city":"Destelbergen",
    "sg:orig_category":"Entretien and r\u00e9parations de voitures",
    "sg:phone":"+32 9 355 90 23",
    "sg:postcode":"9070",
    "sg:province":"Oost-Vlaanderen",
    "wof:name":"Patrick Geiregat",
    "wof:placetype":"venue"
},
  "geometry": {"coordinates":[3.8362140656,51.0750579834],"type":"Point"}
}