{
  "type": "Feature",
  "properties": {
    "addr:full":"Rue Jules Lahaye 27 Bruxelles (jette) Bruxelles-Capitale 1090",
    "addr:housenumber":"27",
    "addr:postcode":"1090",
    "addr:street":"Rue Jules Lahaye",
    "iso:country":"BE",
    "sg:address":"Rue Jules Lahaye 27",
    "sg:city":"Bruxelles (jette)",
    "sg:classifiers":[
        {
            "category":"Bars & Pubs",
            "type":"Food & Drink"
        }
    ],
    "sg:phone":"+32 2 426 58 36",
    "sg:postcode":"1090",
    "sg:province":"Bruxelles-Capitale",
    "wof:name":"Gele Poraa (de)",
    "wof:placetype":"venue"
},
  "geometry": {"coordinates":[4.3305368423,50.8795013428],"type":"Point"}
}