{
  "type": "Feature",
  "properties": {
    "iso:country":"BE",
    "sg:address":"Demerstraat 1",
    "sg:city":"Hasselt",
    "sg:classifiers":[
        {
            "category":"Shopping",
            "subcategory":"Clothing, Apparel, & Fashions",
            "type":"Retail Goods"
        }
    ],
    "sg:phone":"+32 11 22 71 15",
    "sg:postcode":"3500",
    "sg:province":"Limburg",
    "sg:tags":[
        "lingerie",
        "sous-v\u00eatements"
    ],
    "wof:name":"Huis Maldoy",
    "wof:placetype":"venue"
},
  "geometry": {"coordinates":[5.3375601768,50.9306411743],"type":"Point"}
}