{
  "type": "Feature",
  "properties": {
    "addr:full":"Itegemse Steenweg 32 Herenthout Antwerpen 2270",
    "addr:housenumber":"32",
    "addr:postcode":"2270",
    "addr:street":"Itegemse Steenweg",
    "iso:country":"BE",
    "sg:address":"Itegemse Steenweg 32",
    "sg:city":"Herenthout",
    "sg:classifiers":[
        {
            "category":"Freight",
            "type":"Transportation"
        }
    ],
    "sg:phone":"+32 14 50 25 42",
    "sg:postcode":"2270",
    "sg:province":"Antwerpen",
    "sg:tags":[
        "-",
        "transport"
    ],
    "wof:name":"Unastra Bvba",
    "wof:placetype":"venue"
},
  "geometry": {"coordinates":[4.7610549927,51.1380004883],"type":"Point"}
}