{
  "type": "Feature",
  "properties": {
    "iso:country":"BE",
    "sg:address":"Oelegembaan 4",
    "sg:city":"Zandhoven",
    "sg:classifiers":[
        {
            "category":"Insurance",
            "subcategory":"Insurance Agent",
            "type":"Services"
        }
    ],
    "sg:phone":"+32 3 484 64 07",
    "sg:postcode":"2240",
    "sg:province":"Antwerpen",
    "sg:tags":[
        "-",
        "representative"
    ],
    "wof:name":"Dieleman Verzekeringen Bvba",
    "wof:placetype":"venue"
},
  "geometry": {"coordinates":[4.6558017731,51.2131958008],"type":"Point"}
}