{
  "type": "Feature",
  "properties": {
    "iso:country":"BE",
    "sg:address":"Oekensestraat 25",
    "sg:city":"Ledegem (sint-eloois-winkel)",
    "sg:classifiers":[
        {
            "category":"Insurance",
            "subcategory":"Insurance Agent",
            "type":"Services"
        }
    ],
    "sg:phone":"+32 56 50 34 58",
    "sg:postcode":"8880",
    "sg:province":"West-Vlaanderen",
    "sg:tags":[
        "broker"
    ],
    "wof:name":"Oost-van Den Bulcke Bvba",
    "wof:placetype":"venue"
},
  "geometry": {"coordinates":[3.1751129627,50.8796768188],"type":"Point"}
}