{
  "type": "Feature",
  "properties": {
    "addr:full":"Orbanlaan 127 Sint-pieters-woluwe/woluwe-saint-pierre Bruxelles-Capitale 1150",
    "addr:housenumber":"127",
    "addr:postcode":"1150",
    "addr:street":"Orbanlaan;/",
    "iso:country":"BE",
    "sg:address":"Orbanlaan 127",
    "sg:city":"Sint-pieters-woluwe/woluwe-saint-pierre",
    "sg:orig_category":"Alternatieve geneeskunde",
    "sg:phone":"+32 2 770 60 76",
    "sg:postcode":"1150",
    "sg:province":"Bruxelles-Capitale",
    "wof:name":"J.m. Philippart De Foy",
    "wof:placetype":"venue"
},
  "geometry": {"coordinates":[4.4589910507,50.8356552124],"type":"Point"}
}