{
  "type": "Feature",
  "properties": {
    "addr:full":"Rue Grand Pre 138 Namur Namur 5100",
    "addr:housenumber":"138",
    "addr:postcode":"5100",
    "addr:street":"Rue Grand Pre",
    "iso:country":"BE",
    "sg:address":"Rue Grand Pre 138",
    "sg:city":"Namur",
    "sg:orig_category":"Mat\u00e9riel m\u00e9dical and orthop\u00e9dique and proth\u00e8ses Fab",
    "sg:phone":"+32 81 40 13 58",
    "sg:postcode":"5100",
    "sg:province":"Namur",
    "wof:name":"Rodrigue Pollet",
    "wof:placetype":"venue"
},
  "geometry": {"coordinates":[4.9189238548,50.4156837463],"type":"Point"}
}