{
  "type": "Feature",
  "properties": {
    "addr:full":"Av Des Arts 2 Bte 8 Bruxelles Bruxelles-Capitale 1210",
    "addr:housenumber":"2;8",
    "addr:postcode":"1210",
    "addr:street":"Av Des Arts;Bte",
    "iso:country":"BE",
    "sg:address":"Av Des Arts 2 Bte 8",
    "sg:city":"Bruxelles",
    "sg:orig_category":"Miscellaneous Products",
    "sg:phone":"+32 2 219 06 20",
    "sg:postcode":"1210",
    "sg:province":"Bruxelles-Capitale",
    "wof:name":"Ste Des Marches Exterieurs Sa",
    "wof:placetype":"venue"
},
  "geometry": {"coordinates":[4.3695549965,50.8488845825],"type":"Point"}
}