{
  "type": "Feature",
  "properties": {
    "iso:country":"BE",
    "sg:address":"Rue Albert I 248-252",
    "sg:city":"Binche (leval-trahegnies)",
    "sg:classifiers":[
        {
            "category":"Building & Trades",
            "subcategory":"Pest Control",
            "type":"Services"
        }
    ],
    "sg:phone":"+32 475 96 93 03",
    "sg:postcode":"7134",
    "sg:province":"Hainaut",
    "sg:tags":[
        "painting",
        "contractor"
    ],
    "wof:name":"Jp Lambert Sprl",
    "wof:placetype":"venue"
},
  "geometry": {"coordinates":[4.2204451561,50.4262008667],"type":"Point"}
}