{
  "type": "Feature",
  "properties": {
    "addr:full":"Grand\u00b4rue 28 Antoing Hainaut 7640",
    "addr:housenumber":"28",
    "addr:postcode":"7640",
    "addr:street":"Grand\u00b4Rue",
    "iso:country":"BE",
    "sg:address":"Grand\u00b4rue 28",
    "sg:city":"Antoing",
    "sg:orig_category":"Avocats and conseillers juridiques",
    "sg:phone":"+32 69 44 53 00",
    "sg:postcode":"7640",
    "sg:province":"Hainaut",
    "wof:name":"Anne-sophie Vivier",
    "wof:placetype":"venue"
},
  "geometry": {"coordinates":[3.4466810226,50.5670280457],"type":"Point"}
}