{
  "type": "Feature",
  "properties": {
    "addr:full":"Rue De L'egalit\u00c9 36 Quaregnon Hainaut 7390",
    "addr:housenumber":"36",
    "addr:postcode":"7390",
    "addr:street":"Rue De L'Egalite \u0301",
    "iso:country":"BE",
    "sg:address":"Rue De L'egalit\u00c9 36",
    "sg:city":"Quaregnon",
    "sg:orig_category":"Quincailleries. Eclairage et \u00e9quipements du foyer. Magasins de r\u00e9parations d'articles personnels et ",
    "sg:phone":"+32 65 78 34 39",
    "sg:postcode":"7390",
    "sg:province":"Hainaut",
    "wof:name":"Michel Randour",
    "wof:placetype":"venue"
},
  "geometry": {"coordinates":[3.8630900383,50.4407539368],"type":"Point"}
}