{
  "type": "Feature",
  "properties": {
    "iso:country":"BE",
    "sg:address":"Tiensesteenweg 390",
    "sg:city":"Leuven",
    "sg:classifiers":[
        {
            "category":"Government",
            "subcategory":"Fire Station",
            "type":"Public Place"
        }
    ],
    "sg:phone":"+32 16 26 01 52",
    "sg:postcode":"3000",
    "sg:province":"Vlaams-Brabant",
    "sg:tags":[
        "packard",
        "nec",
        "bell"
    ],
    "wof:name":"Megapool Leuven",
    "wof:placetype":"venue"
},
  "geometry": {"coordinates":[4.7408051491,50.8674049377],"type":"Point"}
}