{
  "type": "Feature",
  "properties": {
    "iso:country":"BE",
    "sg:address":"Rue De Wallonie 3 - Z.i. Multimodale",
    "sg:city":"Ch\u00e2telineau",
    "sg:classifiers":[
        {
            "category":"Wholesale",
            "subcategory":"Construction Materials",
            "type":"Manufacturing & Wholesale Goods"
        }
    ],
    "sg:phone":"+32 71 42 06 75",
    "sg:postcode":"6200",
    "sg:province":"Hainaut",
    "sg:tags":[
        "profile",
        "aluminium",
        "ceiling"
    ],
    "wof:name":"Fa\u00e7ozinc-fa\u00e7ometal S.a.",
    "wof:placetype":"venue"
},
  "geometry": {"coordinates":[4.4880981445,50.4251937866],"type":"Point"}
}