{
  "type": "Feature",
  "properties": {
    "addr:full":"Avenue Frans Van Kalken 3 Box 104 Bruxelles (anderlecht) Bruxelles-Capitale 1070",
    "addr:housenumber":"3 box 104",
    "addr:postcode":"1070",
    "addr:street":"Avenue Frans Van Kalken",
    "iso:country":"BE",
    "sg:address":"Avenue Frans Van Kalken 3 Box 104",
    "sg:city":"Bruxelles (anderlecht)",
    "sg:classifiers":[
        {
            "category":"Professional",
            "subcategory":"Lawyer & Legal Services",
            "type":"Services"
        }
    ],
    "sg:phone":"+32 2 558 96 96",
    "sg:postcode":"1070",
    "sg:province":"Bruxelles-Capitale",
    "wof:name":"Leytens Elisabeth",
    "wof:placetype":"venue"
},
  "geometry": {"coordinates":[4.3045191765,50.8274002075],"type":"Point"}
}