{
  "type": "Feature",
  "properties": {
    "addr:full":"Rue Du Bonijoux 27 Eghezee Namur 5310",
    "addr:housenumber":"27",
    "addr:postcode":"5310",
    "addr:street":"Rue Du Bonijoux;Namur",
    "iso:country":"BE",
    "sg:address":"Rue Du Bonijoux 27",
    "sg:city":"Eghezee",
    "sg:classifiers":[
        {
            "category":"Autos & Motor Vehicles",
            "subcategory":"Fuel & Gas Station",
            "type":"Retail Goods"
        }
    ],
    "sg:phone":"+32 81 85 50 76",
    "sg:postcode":"5310",
    "sg:province":"Namur",
    "sg:tags":[
        "stations-service",
        "carburants"
    ],
    "wof:name":"Chantal Francois",
    "wof:placetype":"venue"
},
  "geometry": {"coordinates":[4.945248127,50.610824585],"type":"Point"}
}