{
  "type": "Feature",
  "properties": {
    "addr:full":"Avenue Du Sergent Cotton 39 Waterloo Brabant Wallon 1410",
    "addr:housenumber":"39",
    "addr:postcode":"1410",
    "addr:street":"Avenue Du Sergent Cotton",
    "iso:country":"BE",
    "sg:address":"Avenue Du Sergent Cotton 39",
    "sg:city":"Waterloo",
    "sg:classifiers":[
        {
            "category":"Health Services",
            "subcategory":"Doctor",
            "type":"Services"
        }
    ],
    "sg:phone":"+32 473 58 56 86",
    "sg:postcode":"1410",
    "sg:province":"Brabant Wallon",
    "sg:tags":[
        "psychotherapist",
        "psychoanalyst"
    ],
    "wof:name":"Breda C",
    "wof:placetype":"venue"
},
  "geometry": {"coordinates":[4.3937430382,50.6879043579],"type":"Point"}
}