{
  "type": "Feature",
  "properties": {
    "iso:country":"BE",
    "sg:address":"Vleminckstraat 5",
    "sg:city":"Antwerpen",
    "sg:classifiers":[
        {
            "category":"Professional",
            "subcategory":"Computer Services",
            "type":"Services"
        }
    ],
    "sg:phone":"+32 3 224 83 91",
    "sg:postcode":"2000",
    "sg:province":"Antwerpen",
    "sg:tags":[
        "-",
        "processing",
        "data",
        "software"
    ],
    "wof:name":"Smart Manager Bvba",
    "wof:placetype":"venue"
},
  "geometry": {"coordinates":[4.4033360481,51.220035553],"type":"Point"}
}