{
  "type": "Feature",
  "properties": {
    "iso:country":"BE",
    "sg:address":"Rue Bollinckx 254",
    "sg:city":"Bruxelles (anderlecht)",
    "sg:classifiers":[
        {
            "category":"Professional",
            "subcategory":"Art Services",
            "type":"Services"
        }
    ],
    "sg:phone":"+32 2 333 81 60",
    "sg:postcode":"1070",
    "sg:province":"Bruxelles-Capitale",
    "sg:tags":[
        "-",
        "mailing",
        "lettershops",
        "direct",
        "mail"
    ],
    "wof:name":"Mps",
    "wof:placetype":"venue"
},
  "geometry": {"coordinates":[4.3061499596,50.8150024414],"type":"Point"}
}