{
  "type": "Feature",
  "properties": {
    "iso:country":"BE",
    "sg:address":"Klein Antwerpenstraat 113",
    "sg:city":"Lebbeke",
    "sg:classifiers":[
        {
            "category":"Arena",
            "subcategory":"Sports Club",
            "type":"Entertainment"
        }
    ],
    "sg:phone":"+32 52 35 60 37",
    "sg:postcode":"9280",
    "sg:province":"Oost-Vlaanderen",
    "sg:tags":[
        "de"
    ],
    "wof:name":"V.c. Moderna Lebbeke",
    "wof:placetype":"venue"
},
  "geometry": {"coordinates":[4.1557998657,50.9904403687],"type":"Point"}
}