{
  "type": "Feature",
  "properties": {
    "iso:country":"BE",
    "sg:address":"Hoevenzavellaan 75",
    "sg:city":"Genk",
    "sg:orig_category":"Slagers",
    "sg:phone":"+32 89 84 56 27",
    "sg:postcode":"3600",
    "sg:province":"Limburg",
    "wof:name":"Budgetslager",
    "wof:placetype":"venue"
},
  "geometry": {"coordinates":[5.50704813,51.0009498596],"type":"Point"}
}