{
  "type": "Feature",
  "properties": {
    "iso:country":"BE",
    "sg:address":"Rue Du Coll\u00c8ge 6",
    "sg:city":"Wezet",
    "sg:orig_category":"V\u00eatements pour Dames. V\u00eatements pour Hommes. V\u00eatements pour b\u00e9b\u00e9s and enfants",
    "sg:phone":"+32 4 379 76 24",
    "sg:postcode":"4600",
    "sg:province":"Li\u00e8ge",
    "wof:name":"Benetton",
    "wof:placetype":"venue"
},
  "geometry": {"coordinates":[5.6947112083,50.7353591919],"type":"Point"}
}