{
  "type": "Feature",
  "properties": {
    "addr:full":"Prinses Jos.-charlotteln 28 Sint-niklaas Oost-Vlaanderen 9100",
    "addr:housenumber":"28",
    "addr:postcode":"9100",
    "addr:street":"Prinses Jos.-Charlotteln",
    "iso:country":"BE",
    "sg:address":"Prinses Jos.-charlotteln 28",
    "sg:city":"Sint-niklaas",
    "sg:orig_category":"Evaluation and estimation de biens immobiliers",
    "sg:phone":"+32 3 776 77 65",
    "sg:postcode":"9100",
    "sg:province":"Oost-Vlaanderen",
    "wof:name":"I. R. J. Vanwijck",
    "wof:placetype":"venue"
},
  "geometry": {"coordinates":[4.1453948021,51.1531906128],"type":"Point"}
}