{
  "type": "Feature",
  "properties": {
    "iso:country":"BE",
    "sg:address":"Rue T'serstevens 84",
    "sg:city":"Thuin",
    "sg:orig_category":"V\u00eatements",
    "sg:phone":"+32 71 59 45 19",
    "sg:postcode":"6530",
    "sg:province":"Hainaut",
    "wof:name":"Jery & Co",
    "wof:placetype":"venue"
},
  "geometry": {"coordinates":[4.2826051712,50.3414039612],"type":"Point"}
}