{
  "type": "Feature",
  "properties": {
    "addr:full":"Charleroisesteenweg 38 Elsene/ixelles Bruxelles-Capitale 1050",
    "addr:housenumber":"38",
    "addr:postcode":"1050",
    "addr:street":"Charleroisesteenweg",
    "iso:country":"BE",
    "sg:address":"Charleroisesteenweg 38",
    "sg:city":"Elsene/ixelles",
    "sg:orig_category":"Hotels Restaurants Ruimtes voor conferenties, recepties and feesten",
    "sg:phone":"+32 2 533 66 66",
    "sg:postcode":"1050",
    "sg:province":"Bruxelles-Capitale",
    "wof:name":"Holiday Inn",
    "wof:placetype":"venue"
},
  "geometry": {"coordinates":[4.3798799515,50.8206710815],"type":"Point"}
}