{
  "type": "Feature",
  "properties": {
    "iso:country":"BE",
    "sg:address":"Vosseslag 23",
    "sg:city":"De Haan",
    "sg:orig_category":"Eleveurs de bovins",
    "sg:phone":"+32 59 23 42 93",
    "sg:postcode":"8420",
    "sg:province":"West-Vlaanderen",
    "wof:name":"Agra Zwaenepoel",
    "wof:placetype":"venue"
},
  "geometry": {"coordinates":[3.0099380016,51.2522125244],"type":"Point"}
}