{
  "type": "Feature",
  "properties": {
    "addr:full":"Rue Des Grands-pr\u00e9s 283 Li\u00e8ge 1 (ch\u00ean\u00e9e) Li\u00e8ge 4032",
    "addr:housenumber":"283;1",
    "addr:postcode":"4032",
    "addr:street":"Rue Des Grands-Pre\u0301S",
    "iso:country":"BE",
    "sg:address":"Rue Des Grands-pr\u00e9s 283",
    "sg:city":"Li\u00e8ge 1 (ch\u00ean\u00e9e)",
    "sg:classifiers":[
        {
            "category":"Health Services",
            "subcategory":"Health Practitioner",
            "type":"Services"
        }
    ],
    "sg:phone":"+32 4 371 99 00",
    "sg:postcode":"4032",
    "sg:province":"Li\u00e8ge",
    "sg:tags":[
        "physiotherapist"
    ],
    "wof:name":"Bollaerts Martine",
    "wof:placetype":"venue"
},
  "geometry": {"coordinates":[5.6243882179,50.6049385071],"type":"Point"}
}