{
  "type": "Feature",
  "properties": {
    "addr:full":"Villerslei 93 Schoten Antwerpen 2900",
    "addr:housenumber":"93",
    "addr:postcode":"2900",
    "addr:street":"Villerslei",
    "iso:country":"BE",
    "sg:address":"Villerslei 93",
    "sg:city":"Schoten",
    "sg:orig_category":"Banques and organismes de cr\u00e9dit",
    "sg:phone":"+32 3 658 27 46",
    "sg:postcode":"2900",
    "sg:province":"Antwerpen",
    "wof:name":"Bacob",
    "wof:placetype":"venue"
},
  "geometry": {"coordinates":[4.5128660202,51.2523612976],"type":"Point"}
}