{
  "type": "Feature",
  "properties": {
    "addr:full":"Rue Vanderdussen 48 Sint-jans-molenbeek/molenbeek-saint-jean Bruxelles-Capitale 1080",
    "addr:housenumber":"48",
    "addr:postcode":"1080",
    "addr:street":"Rue Vanderdussen",
    "iso:country":"BE",
    "sg:address":"Rue Vanderdussen 48",
    "sg:city":"Sint-jans-molenbeek/molenbeek-saint-jean",
    "sg:orig_category":"Pain, p\u00e2tisseries and confiseries",
    "sg:phone":"+32 2 411 40 65",
    "sg:postcode":"1080",
    "sg:province":"Bruxelles-Capitale",
    "wof:name":"Sain Pain",
    "wof:placetype":"venue"
},
  "geometry": {"coordinates":[4.3299489021,50.855052948],"type":"Point"}
}