{
  "type": "Feature",
  "properties": {
    "addr:full":"Koning Leopoldlaan 20e Maldegem Oost-Vlaanderen 9990",
    "addr:housenumber":"20e",
    "addr:postcode":"9990",
    "addr:street":"Koning Leopoldlaan",
    "iso:country":"BE",
    "sg:address":"Koning Leopoldlaan 20e",
    "sg:city":"Maldegem",
    "sg:classifiers":[
        {
            "category":"Home & Garden",
            "subcategory":"Kitchen Supply",
            "type":"Retail Goods"
        }
    ],
    "sg:postcode":"9990",
    "sg:province":"Oost-Vlaanderen",
    "sg:tags":[
        "installation"
    ],
    "wof:name":"Eurokitchen Bvba",
    "wof:placetype":"venue"
},
  "geometry": {"coordinates":[3.4638059139,51.2042198181],"type":"Point"}
}