{
  "type": "Feature",
  "properties": {
    "iso:country":"BE",
    "sg:address":"Fred Wallecanlaan 8",
    "sg:city":"Koksijde",
    "sg:classifiers":[
        {
            "category":"Building & Trades",
            "subcategory":"Pest Control",
            "type":"Services"
        }
    ],
    "sg:phone":"+32 58 51 39 40",
    "sg:postcode":"8670",
    "sg:province":"West-Vlaanderen",
    "sg:tags":[
        "painting",
        "contractor"
    ],
    "wof:name":"Geeraert M",
    "wof:placetype":"venue"
},
  "geometry": {"coordinates":[2.6161339283,51.1044921875],"type":"Point"}
}