{
  "type": "Feature",
  "properties": {
    "addr:full":"Grote Baan 183 Hasselt Limburg 3511",
    "addr:housenumber":"183",
    "addr:postcode":"3511",
    "addr:street":"Grote Baan",
    "iso:country":"BE",
    "sg:address":"Grote Baan 183",
    "sg:city":"Hasselt",
    "sg:orig_category":"Meubelzaken, woning- and keukeninrichting",
    "sg:phone":"+32 11 25 40 73",
    "sg:postcode":"3511",
    "sg:province":"Limburg",
    "wof:name":"Old Pine Shop",
    "wof:placetype":"venue"
},
  "geometry": {"coordinates":[5.2954502106,50.9420585632],"type":"Point"}
}