{
  "type": "Feature",
  "properties": {
    "iso:country":"BE",
    "sg:address":"Rue Cesar De Paepe 92",
    "sg:city":"Charleroi",
    "sg:orig_category":"Boucheries",
    "sg:phone":"+32 71 35 35 30",
    "sg:postcode":"6040",
    "sg:province":"Hainaut",
    "wof:name":"Boucherie Laurent",
    "wof:placetype":"venue"
},
  "geometry": {"coordinates":[4.4128961563,50.4367599487],"type":"Point"}
}