{
  "type": "Feature",
  "properties": {
    "iso:country":"BE",
    "sg:address":"Veeweidestraat 10",
    "sg:city":"Tienen",
    "sg:orig_category":"Eleveurs and marchands de porcs",
    "sg:phone":"+32 16 77 75 13",
    "sg:postcode":"3300",
    "sg:province":"Vlaams-Brabant",
    "wof:name":"Henricus Rethy",
    "wof:placetype":"venue"
},
  "geometry": {"coordinates":[4.9718570709,50.8425674438],"type":"Point"}
}