{
  "type": "Feature",
  "properties": {
    "addr:full":"Schilsweg 11 Eupen/eupen Li\u00e8ge 4700",
    "addr:housenumber":"11",
    "addr:postcode":"4700",
    "addr:street":"Schilsweg",
    "iso:country":"BE",
    "sg:address":"Schilsweg 11",
    "sg:city":"Eupen/eupen",
    "sg:orig_category":"M\u00e9decins and sp\u00e9cialistes",
    "sg:phone":"+32 87 55 73 00",
    "sg:postcode":"4700",
    "sg:province":"Li\u00e8ge",
    "wof:name":"Oumar Sy",
    "wof:placetype":"venue"
},
  "geometry": {"coordinates":[6.0407810211,50.6215629578],"type":"Point"}
}