{
  "type": "Feature",
  "properties": {
    "iso:country":"BE",
    "sg:address":"Liersesteenweg 68",
    "sg:city":"Mortsel",
    "sg:classifiers":[
        {
            "category":"Personal",
            "subcategory":"Barber",
            "type":"Services"
        }
    ],
    "sg:phone":"+32 3 440 81 71",
    "sg:postcode":"2640",
    "sg:province":"Antwerpen",
    "sg:tags":[
        "gentleman",
        "salon",
        "-",
        "hairdressing"
    ],
    "wof:name":"Guido",
    "wof:placetype":"venue"
},
  "geometry": {"coordinates":[4.4612598419,51.1694526672],"type":"Point"}
}