{
  "type": "Feature",
  "properties": {
    "addr:full":"Marktstraat 22 Opwijk Vlaams-Brabant 1745",
    "addr:housenumber":"22",
    "addr:postcode":"1745",
    "addr:street":"Marktstraat",
    "iso:country":"BE",
    "sg:address":"Marktstraat 22",
    "sg:city":"Opwijk",
    "sg:orig_category":"Agences de voyages",
    "sg:phone":"+32 52 35 62 20",
    "sg:postcode":"1745",
    "sg:province":"Vlaams-Brabant",
    "wof:name":"Benitours",
    "wof:placetype":"venue"
},
  "geometry": {"coordinates":[4.188120842,50.9705238342],"type":"Point"}
}