{
  "type": "Feature",
  "properties": {
    "addr:full":"Boulevard Du Nord 21 Namur Namur 5000",
    "addr:housenumber":"21",
    "addr:postcode":"5000",
    "addr:street":"Boulevard Du Nord",
    "iso:country":"BE",
    "sg:address":"Boulevard Du Nord 21",
    "sg:city":"Namur",
    "sg:orig_category":"BMW Moto's",
    "sg:phone":"+32 81 22 36 04",
    "sg:postcode":"5000",
    "sg:province":"Namur",
    "wof:name":"Herpigny Motors",
    "wof:placetype":"venue"
},
  "geometry": {"coordinates":[4.863629818,50.4702339172],"type":"Point"}
}