{
  "type": "Feature",
  "properties": {
    "addr:full":"Nieuwe Steenweg 35 Heers Limburg 3870",
    "addr:housenumber":"35",
    "addr:postcode":"3870",
    "addr:street":"Nieuwe Steenweg",
    "iso:country":"BE",
    "sg:address":"Nieuwe Steenweg 35",
    "sg:city":"Heers",
    "sg:classifiers":[
        {
            "category":"Retail",
            "subcategory":"Event Space",
            "type":"Services"
        }
    ],
    "sg:phone":"+32 11 48 50 27",
    "sg:postcode":"3870",
    "sg:province":"Limburg",
    "sg:tags":[
        "rental",
        "-",
        "hall"
    ],
    "wof:name":"Pleintje ('t)",
    "wof:placetype":"venue"
},
  "geometry": {"coordinates":[5.3014931679,50.752166748],"type":"Point"}
}