{
  "type": "Feature",
  "properties": {
    "addr:full":"Koninklijke Baan 157 Koksijde West-Vlaanderen 8670",
    "addr:housenumber":"157",
    "addr:postcode":"8670",
    "addr:street":"Koninklijke Baan",
    "iso:country":"BE",
    "sg:address":"Koninklijke Baan 157",
    "sg:city":"Koksijde",
    "sg:classifiers":[
        {
            "category":"Travel",
            "subcategory":"Hotels & Motels",
            "type":"Entertainment"
        }
    ],
    "sg:phone":"+32 58 51 73 23",
    "sg:postcode":"8670",
    "sg:province":"West-Vlaanderen",
    "wof:name":"Penel",
    "wof:placetype":"venue"
},
  "geometry": {"coordinates":[2.6328129768,51.1192588806],"type":"Point"}
}