{
  "type": "Feature",
  "properties": {
    "iso:country":"BE",
    "sg:address":"Rue Sous-ghoy 22",
    "sg:city":"Merbes-le-chateau",
    "sg:classifiers":[
        {
            "category":"Arena",
            "subcategory":"Sports Club",
            "type":"Entertainment"
        }
    ],
    "sg:phone":"+32 71 55 89 05",
    "sg:postcode":"6567",
    "sg:province":"Hainaut",
    "sg:tags":[
        "de"
    ],
    "wof:name":"Archery Club Labuissi\u00c8re",
    "wof:placetype":"venue"
},
  "geometry": {"coordinates":[4.1872458458,50.314666748],"type":"Point"}
}