{
  "type": "Feature",
  "properties": {
    "iso:country":"BE",
    "sg:address":"Zoning Ouest 15",
    "sg:city":"Lessines",
    "sg:classifiers":[
        {
            "category":"Manufacturing",
            "subcategory":"Petroleum Products",
            "type":"Manufacturing & Wholesale Goods"
        }
    ],
    "sg:phone":"+32 68 33 86 86",
    "sg:postcode":"7860",
    "sg:province":"Hainaut",
    "sg:tags":[
        "production",
        "combustible",
        "de",
        "distribution",
        "gaz"
    ],
    "wof:name":"B.t.g.",
    "wof:placetype":"venue"
},
  "geometry": {"coordinates":[3.8221569061,50.7007675171],"type":"Point"}
}