{
  "type": "Feature",
  "properties": {
    "iso:country":"BE",
    "sg:address":"Rue Jean Jaur\u00c8s 18",
    "sg:city":"Gr\u00c2ce-hollogne",
    "sg:classifiers":[
        {
            "category":"Restaurant",
            "type":"Food & Drink"
        }
    ],
    "sg:phone":"+32 4 246 14 94",
    "sg:postcode":"4460",
    "sg:province":"Li\u00e8ge",
    "sg:tags":[
        "caf\u00e9s"
    ],
    "wof:name":"Taverne Chez Lucien",
    "wof:placetype":"venue"
},
  "geometry": {"coordinates":[5.5049958229,50.6440086365],"type":"Point"}
}