{
  "type": "Feature",
  "properties": {
    "addr:full":"Les Potales 41 Namur Namur 5020",
    "addr:housenumber":"41",
    "addr:postcode":"5020",
    "iso:country":"BE",
    "sg:address":"Les Potales 41",
    "sg:city":"Namur",
    "sg:orig_category":"Woningbouw",
    "sg:phone":"+32 81 44 41 35",
    "sg:postcode":"5020",
    "sg:province":"Namur",
    "wof:name":"Leon Lamotte",
    "wof:placetype":"venue"
},
  "geometry": {"coordinates":[4.7952418327,50.4352035522],"type":"Point"}
}