{
  "type": "Feature",
  "properties": {
    "iso:country":"BE",
    "sg:address":"Mechelsesteenweg 488",
    "sg:city":"Zaventem (nossegem)",
    "sg:classifiers":[
        {
            "category":"Bars & Pubs",
            "type":"Food & Drink"
        }
    ],
    "sg:phone":"+32 2 759 96 59",
    "sg:postcode":"1930",
    "sg:province":"Vlaams-Brabant",
    "wof:name":"Tinnen Pot (de)",
    "wof:placetype":"venue"
},
  "geometry": {"coordinates":[4.5068287849,50.8793907166],"type":"Point"}
}