{
  "type": "Feature",
  "properties": {
    "iso:country":"BE",
    "sg:address":"Rue D\u00b4anth\u00c9e 41",
    "sg:city":"Mettet",
    "sg:orig_category":"Artsen and specialisten",
    "sg:phone":"+32 71 72 72 06",
    "sg:postcode":"5644",
    "sg:province":"Namur",
    "wof:name":"Carole Maloteaux",
    "wof:placetype":"venue"
},
  "geometry": {"coordinates":[4.7193441391,50.2983093262],"type":"Point"}
}