{
  "type": "Feature",
  "properties": {
    "addr:full":"Dr.-van De Perrestraat 98 Geel Antwerpen 2440",
    "addr:housenumber":"98",
    "addr:postcode":"2440",
    "addr:street":"Dr.-Van De Perrestraat",
    "iso:country":"BE",
    "sg:address":"Dr.-van De Perrestraat 98",
    "sg:city":"Geel",
    "sg:orig_category":"Diverse kredietdiensten",
    "sg:postcode":"2440",
    "sg:province":"Antwerpen",
    "wof:name":"Bancontact-mister Cash",
    "wof:placetype":"venue"
},
  "geometry": {"coordinates":[4.9870991707,51.1726341248],"type":"Point"}
}