{
  "type": "Feature",
  "properties": {
    "iso:country":"BE",
    "sg:address":"Pioenenlaan 8",
    "sg:city":"Liedekerke",
    "sg:orig_category":"Diverse opleidingen and onderwijs",
    "sg:phone":"+32 53 68 05 38",
    "sg:postcode":"1770",
    "sg:province":"Vlaams-Brabant",
    "wof:name":"Moons",
    "wof:placetype":"venue"
},
  "geometry": {"coordinates":[4.1120610237,50.8585090637],"type":"Point"}
}