{
  "type": "Feature",
  "properties": {
    "addr:full":"Avenue De L'emeraude 59 Bruxelles (schaerbeek) Bruxelles-Capitale 1030",
    "addr:housenumber":"59",
    "addr:postcode":"1030",
    "addr:street":"Avenue De L'Emeraude",
    "iso:country":"BE",
    "sg:address":"Avenue De L'emeraude 59",
    "sg:city":"Bruxelles (schaerbeek)",
    "sg:classifiers":[
        {
            "category":"Organizations",
            "subcategory":"Community Association",
            "type":"Services"
        }
    ],
    "sg:phone":"+32 2 732 15 92",
    "sg:postcode":"1030",
    "sg:province":"Bruxelles-Capitale",
    "sg:tags":[
        "cultural"
    ],
    "wof:name":"Alliance Fran\u00e7aise",
    "wof:placetype":"venue"
},
  "geometry": {"coordinates":[4.3990240097,50.8525695801],"type":"Point"}
}