{
  "type": "Feature",
  "properties": {
    "iso:country":"BE",
    "sg:address":"Heilsborre 42",
    "sg:city":"Asse",
    "sg:orig_category":"Artiesten and kunstenaars",
    "sg:phone":"+32 2 452 84 87",
    "sg:postcode":"1730",
    "sg:province":"Vlaams-Brabant",
    "wof:name":"Armand Frits",
    "wof:placetype":"venue"
},
  "geometry": {"coordinates":[4.1630220413,50.9096870422],"type":"Point"}
}