{
  "type": "Feature",
  "properties": {
    "addr:full":"Dobbelenbergstraat 104 Brussel/bruxelles Bruxelles-Capitale 1130",
    "addr:housenumber":"104",
    "addr:postcode":"1130",
    "addr:street":"Dobbelenbergstraat;/",
    "iso:country":"BE",
    "sg:address":"Dobbelenbergstraat 104",
    "sg:city":"Brussel/bruxelles",
    "sg:classifiers":[
        {
            "category":"Restaurant",
            "type":"Food & Drink"
        }
    ],
    "sg:phone":"+32 2 245 23 62",
    "sg:postcode":"1130",
    "sg:province":"Bruxelles-Capitale",
    "sg:tags":[
        "caf\u00e9s"
    ],
    "wof:name":"Taverne The Rayan\u00b4s",
    "wof:placetype":"venue"
},
  "geometry": {"coordinates":[4.4196109772,50.903213501],"type":"Point"}
}