{
  "type": "Feature",
  "properties": {
    "iso:country":"BE",
    "sg:address":"Esenweg 67",
    "sg:city":"Diksmuide",
    "sg:orig_category":"Huisdieren and benodigdheden Royal Canin",
    "sg:phone":"+32 51 50 44 71",
    "sg:postcode":"8600",
    "sg:province":"West-Vlaanderen",
    "wof:name":"Defever-laplasse",
    "wof:placetype":"venue"
},
  "geometry": {"coordinates":[2.8756189346,51.0318260193],"type":"Point"}
}