{
  "type": "Feature",
  "properties": {
    "iso:country":"BE",
    "sg:address":"Chauss\u00c9e De Bruxelles 296",
    "sg:city":"Charleroi",
    "sg:orig_category":"Caravans, aanhangwagens and opleggers Herstellingen and onderhoud van auto's Verhuur voertuigen beha",
    "sg:phone":"+32 71 32 43 18",
    "sg:postcode":"6042",
    "sg:province":"Hainaut",
    "wof:name":"Hainaut Caravaning Center",
    "wof:placetype":"venue"
},
  "geometry": {"coordinates":[4.4352998734,50.4472618103],"type":"Point"}
}