{
  "type": "Feature",
  "properties": {
    "iso:country":"BE",
    "sg:address":"Lijsterbeslaan 6",
    "sg:city":"Brecht",
    "sg:classifiers":[
        {
            "category":"Military Area",
            "subcategory":"Air Force Base",
            "type":"Public Place"
        }
    ],
    "sg:phone":"+32 3 663 88 63",
    "sg:postcode":"2960",
    "sg:province":"Antwerpen",
    "sg:tags":[
        "wall",
        "painting"
    ],
    "wof:name":"Keutgens K",
    "wof:placetype":"venue"
},
  "geometry": {"coordinates":[4.6415200233,51.3512115479],"type":"Point"}
}