{
  "type": "Feature",
  "properties": {
    "iso:country":"BE",
    "sg:address":"Zwijnaardsesteenweg 20",
    "sg:city":"Gent",
    "sg:orig_category":"Opticiens",
    "sg:phone":"+32 9 221 75 74",
    "sg:postcode":"9000",
    "sg:province":"Oost-Vlaanderen",
    "wof:name":"Brilcenter",
    "wof:placetype":"venue"
},
  "geometry": {"coordinates":[3.7261209488,51.0363769531],"type":"Point"}
}