{
  "type": "Feature",
  "properties": {
    "addr:full":"Nieuwstraat 160 Diepenbeek Limburg 3590",
    "addr:housenumber":"160",
    "addr:postcode":"3590",
    "addr:street":"Nieuwstraat",
    "iso:country":"BE",
    "sg:address":"Nieuwstraat 160",
    "sg:city":"Diepenbeek",
    "sg:orig_category":"Herstellingen and onderhoud van auto's Onderdelen and accessoires voor auto's",
    "sg:phone":"+32 11 33 21 85",
    "sg:postcode":"3590",
    "sg:province":"Limburg",
    "wof:name":"Banden Johnny",
    "wof:placetype":"venue"
},
  "geometry": {"coordinates":[5.4537830353,50.9249458313],"type":"Point"}
}