{
  "type": "Feature",
  "properties": {
    "iso:country":"BE",
    "sg:address":"Bruulstraat 67",
    "sg:city":"Haaltert",
    "sg:classifiers":[
        {
            "category":"Building & Trades",
            "subcategory":"Plumbing",
            "type":"Services"
        }
    ],
    "sg:phone":"+32 53 84 81 96",
    "sg:postcode":"9450",
    "sg:province":"Oost-Vlaanderen",
    "sg:tags":[
        "contractor"
    ],
    "wof:name":"Lanckman",
    "wof:placetype":"venue"
},
  "geometry": {"coordinates":[3.9994618893,50.9062423706],"type":"Point"}
}