{
  "type": "Feature",
  "properties": {
    "iso:country":"BE",
    "sg:address":"Keverstraat 20",
    "sg:city":"Tongeren",
    "sg:orig_category":"Eclairage et \u00e9quipements du foyer",
    "sg:phone":"+32 12 23 65 72",
    "sg:postcode":"3700",
    "sg:province":"Limburg",
    "wof:name":"Plugers Interieur",
    "wof:placetype":"venue"
},
  "geometry": {"coordinates":[5.4609751701,50.7833442688],"type":"Point"}
}