{
  "type": "Feature",
  "properties": {
    "addr:full":"Brugse Steenweg 211 Veurne West-Vlaanderen 8630",
    "addr:housenumber":"211",
    "addr:postcode":"8630",
    "addr:street":"Brugse Steenweg",
    "iso:country":"BE",
    "sg:address":"Brugse Steenweg 211",
    "sg:city":"Veurne",
    "sg:orig_category":"Varkenskwekers",
    "sg:phone":"+32 58 31 15 42",
    "sg:postcode":"8630",
    "sg:province":"West-Vlaanderen",
    "wof:name":"Marc Huyghe",
    "wof:placetype":"venue"
},
  "geometry": {"coordinates":[2.687032938,51.0731925964],"type":"Point"}
}