{
  "type": "Feature",
  "properties": {
    "addr:full":"Avenue Brugmann 307 Ukkel/uccle Bruxelles-Capitale 1180",
    "addr:housenumber":"307",
    "addr:postcode":"1180",
    "addr:street":"Avenue Brugmann;/",
    "iso:country":"BE",
    "sg:address":"Avenue Brugmann 307",
    "sg:city":"Ukkel/uccle",
    "sg:orig_category":"Agences de publicit\u00e9",
    "sg:phone":"+32 2 344 03 83",
    "sg:postcode":"1180",
    "sg:province":"Bruxelles-Capitale",
    "wof:name":"Ine De Behr",
    "wof:placetype":"venue"
},
  "geometry": {"coordinates":[4.3461151123,50.8111419678],"type":"Point"}
}