{
  "type": "Feature",
  "properties": {
    "addr:full":"Gentseweg 31ba Knesselare Oost-Vlaanderen 9910",
    "addr:housenumber":"31ba",
    "addr:postcode":"9910",
    "addr:street":"Gentseweg;Oost-Vlaanderen",
    "iso:country":"BE",
    "sg:address":"Gentseweg 31ba",
    "sg:city":"Knesselare",
    "sg:orig_category":"D\u00e9molition d\u00b4immeubles and terrassements",
    "sg:phone":"+32 9 375 06 69",
    "sg:postcode":"9910",
    "sg:province":"Oost-Vlaanderen",
    "wof:name":"Ivo Casier",
    "wof:placetype":"venue"
},
  "geometry": {"coordinates":[3.5161418915,51.1221542358],"type":"Point"}
}