{
  "type": "Feature",
  "properties": {
    "addr:full":"Brusselsesteenweg 510 Halle Vlaams-Brabant 1500",
    "addr:housenumber":"510",
    "addr:postcode":"1500",
    "addr:street":"Brusselsesteenweg",
    "iso:country":"BE",
    "sg:address":"Brusselsesteenweg 510",
    "sg:city":"Halle",
    "sg:classifiers":[
        {
            "category":"Home & Garden",
            "subcategory":"Building Materials",
            "type":"Retail Goods"
        }
    ],
    "sg:phone":"+32 2 361 32 80",
    "sg:postcode":"1500",
    "sg:province":"Vlaams-Brabant",
    "sg:tags":[
        "window"
    ],
    "wof:name":"Lapeyre Sa",
    "wof:placetype":"venue"
},
  "geometry": {"coordinates":[4.2471661568,50.7524833679],"type":"Point"}
}