{
  "type": "Feature",
  "properties": {
    "addr:full":"Bronstraat 11a Beersel (alsemberg) Vlaams-Brabant 1652",
    "addr:housenumber":"11a",
    "addr:postcode":"1652",
    "addr:street":"Bronstraat",
    "iso:country":"BE",
    "sg:address":"Bronstraat 11a",
    "sg:city":"Beersel (alsemberg)",
    "sg:classifiers":[
        {
            "category":"Banks & Credit Unions",
            "subcategory":"Investment Brokerage",
            "type":"Services"
        }
    ],
    "sg:phone":"+32 2 381 01 50",
    "sg:postcode":"1652",
    "sg:province":"Vlaams-Brabant",
    "sg:tags":[
        "auditor"
    ],
    "wof:name":"Rousselle D",
    "wof:placetype":"venue"
},
  "geometry": {"coordinates":[4.3402371407,50.7478141785],"type":"Point"}
}