{
  "type": "Feature",
  "properties": {
    "addr:full":"Sint-maartenplein 70 Hasselt Limburg 3512",
    "addr:housenumber":"70",
    "addr:postcode":"3512",
    "addr:street":"Sint-Maartenplein",
    "iso:country":"BE",
    "sg:address":"Sint-maartenplein 70",
    "sg:city":"Hasselt",
    "sg:classifiers":[
        {
            "category":"Restaurant",
            "type":"Food & Drink"
        }
    ],
    "sg:phone":"+32 11 31 69 12",
    "sg:postcode":"3512",
    "sg:province":"Limburg",
    "wof:name":"Koffiehuisje",
    "wof:placetype":"venue"
},
  "geometry": {"coordinates":[5.2474980354,50.917011261],"type":"Point"}
}