{
  "type": "Feature",
  "properties": {
    "iso:country":"BE",
    "sg:address":"Edisonplein 5b8",
    "sg:city":"Schoten",
    "sg:orig_category":"Articles non-alimentaires",
    "sg:phone":"+32 3 685 13 44",
    "sg:postcode":"2900",
    "sg:province":"Antwerpen",
    "wof:name":"India Papa Sierra",
    "wof:placetype":"venue"
},
  "geometry": {"coordinates":[4.5007200241,51.2531356812],"type":"Point"}
}