{
  "type": "Feature",
  "properties": {
    "iso:country":"BE",
    "sg:address":"Antwerpsestraat 72",
    "sg:city":"Lier",
    "sg:classifiers":[
        {
            "category":"Shopping",
            "subcategory":"Shoes",
            "type":"Retail Goods"
        }
    ],
    "sg:phone":"+32 3 480 37 72",
    "sg:postcode":"2500",
    "sg:province":"Antwerpen",
    "sg:tags":[
        "slipper",
        "-"
    ],
    "wof:name":"Schoenen David",
    "wof:placetype":"venue"
},
  "geometry": {"coordinates":[4.5675139427,51.1335754395],"type":"Point"}
}