{
  "type": "Feature",
  "properties": {
    "addr:full":"Oosteinde 14 Box 2 Lochristi (zaffelare) Oost-Vlaanderen 9080",
    "addr:housenumber":"14;2",
    "addr:postcode":"9080",
    "addr:street":"Oosteinde;Box",
    "iso:country":"BE",
    "sg:address":"Oosteinde 14 Box 2",
    "sg:city":"Lochristi (zaffelare)",
    "sg:classifiers":[
        {
            "category":"Health Services",
            "subcategory":"Dentist",
            "type":"Services"
        }
    ],
    "sg:phone":"+32 9 356 64 47",
    "sg:postcode":"9080",
    "sg:province":"Oost-Vlaanderen",
    "wof:name":"Carlier Sofie",
    "wof:placetype":"venue"
},
  "geometry": {"coordinates":[3.8656790257,51.1340408325],"type":"Point"}
}