{
  "type": "Feature",
  "properties": {
    "iso:country":"BE",
    "sg:address":"Brabantdam 36",
    "sg:city":"Gent",
    "sg:orig_category":"Baby- and kinderkleding",
    "sg:phone":"+32 9 225 63 99",
    "sg:postcode":"9000",
    "sg:province":"Oost-Vlaanderen",
    "wof:name":"Huis Petit Boy",
    "wof:placetype":"venue"
},
  "geometry": {"coordinates":[3.7283599377,51.0504112244],"type":"Point"}
}