{
  "type": "Feature",
  "properties": {
    "iso:country":"BE",
    "sg:address":"Nijverheidsstraat 130",
    "sg:city":"Gavere (dikkelvenne)",
    "sg:classifiers":[
        {
            "category":"Shopping",
            "subcategory":"Florist",
            "type":"Retail Goods"
        }
    ],
    "sg:phone":"+32 9 384 57 36",
    "sg:postcode":"9890",
    "sg:province":"Oost-Vlaanderen",
    "wof:name":"Fiori Bloemen",
    "wof:placetype":"venue"
},
  "geometry": {"coordinates":[3.6782319546,50.9217414856],"type":"Point"}
}