{
  "type": "Feature",
  "properties": {
    "iso:country":"BE",
    "sg:address":"Roeselaarsestraat 92",
    "sg:city":"Ardooie",
    "sg:classifiers":[
        {
            "category":"Personal",
            "subcategory":"Beauty Salon",
            "type":"Services"
        }
    ],
    "sg:phone":"+32 51 20 45 28",
    "sg:postcode":"8850",
    "sg:province":"West-Vlaanderen",
    "sg:tags":[
        "lady",
        "-",
        "hairdressing"
    ],
    "wof:name":"Degrande K",
    "wof:placetype":"venue"
},
  "geometry": {"coordinates":[3.1850719452,50.9681663513],"type":"Point"}
}