{
  "type": "Feature",
  "properties": {
    "iso:country":"BE",
    "sg:address":"Vijfhuizenstraat 76",
    "sg:city":"Westerlo",
    "sg:orig_category":"Eleveurs and marchands de porcs",
    "sg:phone":"+32 14 54 92 73",
    "sg:postcode":"2260",
    "sg:province":"Antwerpen",
    "wof:name":"Gustaaf Maes",
    "wof:placetype":"venue"
},
  "geometry": {"coordinates":[4.884955883,51.0946006775],"type":"Point"}
}