{
  "type": "Feature",
  "properties": {
    "addr:full":"Rue D'ombret 264 Engis (clermont-sous-huy) Li\u00e8ge 4480",
    "addr:housenumber":"264",
    "addr:postcode":"4480",
    "addr:street":"Rue D'Ombret;Clermont-Sous-Huy",
    "iso:country":"BE",
    "sg:address":"Rue D'ombret 264",
    "sg:city":"Engis (clermont-sous-huy)",
    "sg:classifiers":[
        {
            "category":"Wholesale",
            "subcategory":"Machinery & Supplies",
            "type":"Manufacturing & Wholesale Goods"
        }
    ],
    "sg:phone":"+32 85 31 15 91",
    "sg:postcode":"4480",
    "sg:province":"Li\u00e8ge",
    "sg:tags":[
        "agricultural",
        "tractor"
    ],
    "wof:name":"Deville Ets Sa",
    "wof:placetype":"venue"
},
  "geometry": {"coordinates":[5.3381738663,50.5445404053],"type":"Point"}
}