{
  "type": "Feature",
  "properties": {
    "addr:full":"Stationlaan Bilzen Limburg 3740",
    "addr:postcode":"3740",
    "addr:street":"Stationlaan",
    "iso:country":"BE",
    "sg:address":"Stationlaan",
    "sg:city":"Bilzen",
    "sg:orig_category":"Treinen and spoorwegen",
    "sg:phone":"+32 89 41 12 28",
    "sg:postcode":"3740",
    "sg:province":"Limburg",
    "wof:name":"Station Bilzen",
    "wof:placetype":"venue"
},
  "geometry": {"coordinates":[5.5119190216,50.8694152832],"type":"Point"}
}