{
  "type": "Feature",
  "properties": {
    "addr:full":"Koningin Astridlaan 185 Gent Oost-Vlaanderen 9000",
    "addr:housenumber":"185",
    "addr:postcode":"9000",
    "addr:street":"Koningin Astridlaan;Oost-Vlaanderen",
    "iso:country":"BE",
    "sg:address":"Koningin Astridlaan 185",
    "sg:city":"Gent",
    "sg:classifiers":[
        {
            "category":"Insurance",
            "subcategory":"Life Insurance",
            "type":"Services"
        }
    ],
    "sg:phone":"+32 9 242 95 75",
    "sg:postcode":"9000",
    "sg:province":"Oost-Vlaanderen",
    "sg:tags":[
        "assurance"
    ],
    "wof:name":"Coris-belguim",
    "wof:placetype":"venue"
},
  "geometry": {"coordinates":[3.7133710384,51.0361595154],"type":"Point"}
}