{
  "type": "Feature",
  "properties": {
    "iso:country":"BE",
    "sg:address":"Kortewagenstraat 34",
    "sg:city":"Roeselare",
    "sg:classifiers":[
        {
            "category":"Food & Beverages",
            "subcategory":"Fruits & Vegetables",
            "type":"Retail Goods"
        }
    ],
    "sg:phone":"+32 56 50 03 55",
    "sg:postcode":"8800",
    "sg:province":"West-Vlaanderen",
    "sg:tags":[
        "l\u00e9gumes",
        "gr"
    ],
    "wof:name":"Mestdagh Joseph & Karel",
    "wof:placetype":"venue"
},
  "geometry": {"coordinates":[3.1221790314,50.8968315125],"type":"Point"}
}