{
  "type": "Feature",
  "properties": {
    "iso:country":"BE",
    "sg:address":"Bloemenhof 11",
    "sg:city":"Boechout",
    "sg:orig_category":"Groententeelt",
    "sg:phone":"+32 3 480 58 68",
    "sg:postcode":"2531",
    "sg:province":"Antwerpen",
    "wof:name":"Leopold Naenen",
    "wof:placetype":"venue"
},
  "geometry": {"coordinates":[4.5364727974,51.1633338928],"type":"Point"}
}