{
  "type": "Feature",
  "properties": {
    "addr:full":"Boomkensstraat 24 Mechelen (hombeek) Antwerpen 2811",
    "addr:housenumber":"24",
    "addr:postcode":"2811",
    "addr:street":"Boomkensstraat",
    "iso:country":"BE",
    "sg:address":"Boomkensstraat 24",
    "sg:city":"Mechelen (hombeek)",
    "sg:classifiers":[
        {
            "category":"Personal",
            "subcategory":"Beauty Salon",
            "type":"Services"
        }
    ],
    "sg:phone":"+32 15 61 63 21",
    "sg:postcode":"2811",
    "sg:province":"Antwerpen",
    "sg:tags":[
        "lady",
        "-",
        "hairdressing"
    ],
    "wof:name":"Katleen",
    "wof:placetype":"venue"
},
  "geometry": {"coordinates":[4.4062299728,51.003288269],"type":"Point"}
}