{
  "type": "Feature",
  "properties": {
    "addr:full":"Heirstraat 310 Maasmechelen Limburg 3630",
    "addr:housenumber":"310",
    "addr:postcode":"3630",
    "addr:street":"Heirstraat",
    "iso:country":"BE",
    "sg:address":"Heirstraat 310",
    "sg:city":"Maasmechelen",
    "sg:classifiers":[
        {
            "category":"Health Services",
            "subcategory":"Health Practitioner",
            "type":"Services"
        }
    ],
    "sg:phone":"+32 479 59 30 82",
    "sg:postcode":"3630",
    "sg:province":"Limburg",
    "sg:tags":[
        "alternative",
        "therapy",
        "treatment"
    ],
    "wof:name":"Jacobs S",
    "wof:placetype":"venue"
},
  "geometry": {"coordinates":[5.6900320053,50.9575691223],"type":"Point"}
}