{
  "type": "Feature",
  "properties": {
    "iso:country":"BE",
    "sg:address":"Pollaertstraat 5",
    "sg:city":"Kortemark",
    "sg:orig_category":"Varkenskwekers",
    "sg:phone":"+32 51 56 61 65",
    "sg:postcode":"8610",
    "sg:province":"West-Vlaanderen",
    "wof:name":"Michiel Waeyaert",
    "wof:placetype":"venue"
},
  "geometry": {"coordinates":[3.0067400932,51.055606842],"type":"Point"}
}