{
  "type": "Feature",
  "properties": {
    "iso:country":"BE",
    "sg:address":"Ninoofsesteenweg 44",
    "sg:city":"Haaltert",
    "sg:orig_category":"Charpentes and couvertures",
    "sg:phone":"+32 54 33 72 51",
    "sg:postcode":"9450",
    "sg:province":"Oost-Vlaanderen",
    "wof:name":"Ferge",
    "wof:placetype":"venue"
},
  "geometry": {"coordinates":[4.0187959671,50.8661880493],"type":"Point"}
}