{
  "type": "Feature",
  "properties": {
    "iso:country":"BE",
    "sg:address":"Jetse-laan 220",
    "sg:city":"Brussel",
    "sg:classifiers":[
        {
            "category":"Real Estate",
            "subcategory":"Architect",
            "type":"Services"
        }
    ],
    "sg:phone":"+32 2 426 07 04",
    "sg:postcode":"1090",
    "sg:province":"Bruxelles-Capitale",
    "sg:tags":[
        "textile",
        "clothing"
    ],
    "wof:name":"Vetrico Nv",
    "wof:placetype":"venue"
},
  "geometry": {"coordinates":[4.3252410889,50.8704719543],"type":"Point"}
}