{
  "type": "Feature",
  "properties": {
    "iso:country":"BE",
    "sg:address":"Scheldestraat 28",
    "sg:city":"Zwevegem",
    "sg:orig_category":"V\u00e9t\u00e9rinaires",
    "sg:phone":"+32 56 77 74 73",
    "sg:postcode":"8553",
    "sg:province":"West-Vlaanderen",
    "wof:name":"Ulysse Laverge",
    "wof:placetype":"venue"
},
  "geometry": {"coordinates":[3.4254140854,50.8058929443],"type":"Point"}
}