{
  "type": "Feature",
  "properties": {
    "addr:full":"Populierendreef 19b1 Mechelen Antwerpen 2800",
    "addr:housenumber":"19b1",
    "addr:postcode":"2800",
    "addr:street":"Populierendreef",
    "iso:country":"BE",
    "sg:address":"Populierendreef 19b1",
    "sg:city":"Mechelen",
    "sg:orig_category":"Traitements param\u00e9dicaux",
    "sg:phone":"+32 15 27 36 05",
    "sg:postcode":"2800",
    "sg:province":"Antwerpen",
    "wof:name":"M. Zwaan",
    "wof:placetype":"venue"
},
  "geometry": {"coordinates":[4.4862308502,51.0329742432],"type":"Point"}
}