{
  "type": "Feature",
  "properties": {
    "addr:full":"Groenedijkstraat 5a Oudenburg West-Vlaanderen 8460",
    "addr:housenumber":"5a",
    "addr:postcode":"8460",
    "addr:street":"Groenedijkstraat",
    "iso:country":"BE",
    "sg:address":"Groenedijkstraat 5a",
    "sg:city":"Oudenburg",
    "sg:classifiers":[
        {
            "category":"Travel",
            "subcategory":"Hotels & Motels",
            "type":"Entertainment"
        }
    ],
    "sg:phone":"+32 59 26 85 40",
    "sg:postcode":"8460",
    "sg:province":"West-Vlaanderen",
    "wof:name":"Motorloft Groenedijk",
    "wof:placetype":"venue"
},
  "geometry": {"coordinates":[2.9831080437,51.1926460266],"type":"Point"}
}