{
  "type": "Feature",
  "properties": {
    "iso:country":"BE",
    "sg:address":"Stationsstraat 16",
    "sg:city":"Balen",
    "sg:classifiers":[
        {
            "category":"Banks & Credit Unions",
            "subcategory":"Investment Brokerage",
            "type":"Services"
        }
    ],
    "sg:phone":"+32 14 81 35 00",
    "sg:postcode":"2490",
    "sg:province":"Antwerpen",
    "sg:tags":[
        "printing",
        "-"
    ],
    "wof:name":"Drukkerij Moons Bvba",
    "wof:placetype":"venue"
},
  "geometry": {"coordinates":[5.1655950546,51.1702156067],"type":"Point"}
}