{
  "type": "Feature",
  "properties": {
    "addr:full":"Petit Paris 0 Oostende West-Vlaanderen 8400",
    "addr:postcode":"8400",
    "iso:country":"BE",
    "sg:address":"Petit Paris 0",
    "sg:city":"Oostende",
    "sg:orig_category":"Voedingsspeciaalzaken",
    "sg:phone":"+32 59 70 14 50",
    "sg:postcode":"8400",
    "sg:province":"West-Vlaanderen",
    "wof:name":"Beuselinck",
    "wof:placetype":"venue"
},
  "geometry": {"coordinates":[2.9088850021,51.224521637],"type":"Point"}
}