{
  "type": "Feature",
  "properties": {
    "iso:country":"BE",
    "sg:address":"Hoogte 54",
    "sg:city":"Sint-laureins",
    "sg:orig_category":"Rundveehouders Varkenskwekers",
    "sg:phone":"+32 9 379 86 40",
    "sg:postcode":"9980",
    "sg:province":"Oost-Vlaanderen",
    "wof:name":"Johan Creytens",
    "wof:placetype":"venue"
},
  "geometry": {"coordinates":[3.5905499458,51.2333946228],"type":"Point"}
}