{
  "type": "Feature",
  "properties": {
    "addr:full":"Vilvoordelaan 20 Zaventem Vlaams-Brabant 1930",
    "addr:housenumber":"20",
    "addr:postcode":"1930",
    "addr:street":"Vilvoordelaan",
    "iso:country":"BE",
    "sg:address":"Vilvoordelaan 20",
    "sg:city":"Zaventem",
    "sg:orig_category":"Rechtbanken",
    "sg:phone":"+32 2 720 31 15",
    "sg:postcode":"1930",
    "sg:province":"Vlaams-Brabant",
    "wof:name":"Vredegerecht",
    "wof:placetype":"venue"
},
  "geometry": {"coordinates":[4.471075058,50.886516571],"type":"Point"}
}