{
  "type": "Feature",
  "properties": {
    "addr:full":"Pater Eudore Devroyestr. 53 Etterbeek Bruxelles-Capitale 1040",
    "addr:housenumber":"53",
    "addr:postcode":"1040",
    "addr:street":"Pater Eudore Devroyestr.",
    "iso:country":"BE",
    "sg:address":"Pater Eudore Devroyestr. 53",
    "sg:city":"Etterbeek",
    "sg:classifiers":[
        {
            "category":"Professional",
            "subcategory":"Accounting & Tax Preparation",
            "type":"Services"
        }
    ],
    "sg:phone":"+32 2 736 31 81",
    "sg:postcode":"1040",
    "sg:province":"Bruxelles-Capitale",
    "sg:tags":[
        "accountant"
    ],
    "wof:name":"Alain Cardon",
    "wof:placetype":"venue"
},
  "geometry": {"coordinates":[4.4090409279,50.833114624],"type":"Point"}
}