{
  "type": "Feature",
  "properties": {
    "iso:country":"BE",
    "sg:address":"Rue De La Warchenne 25",
    "sg:city":"Malmedy/malmedy",
    "sg:orig_category":"M\u00e9decins and sp\u00e9cialistes",
    "sg:phone":"+32 80 77 07 24",
    "sg:postcode":"4960",
    "sg:province":"Li\u00e8ge",
    "wof:name":"Martine Vanderveken",
    "wof:placetype":"venue"
},
  "geometry": {"coordinates":[6.0551772118,50.37657547],"type":"Point"}
}