{
  "type": "Feature",
  "properties": {
    "addr:full":"Oppuursesteenweg 34 Bornem Antwerpen 2880",
    "addr:housenumber":"34",
    "addr:postcode":"2880",
    "addr:street":"Oppuursesteenweg",
    "iso:country":"BE",
    "sg:address":"Oppuursesteenweg 34",
    "sg:city":"Bornem",
    "sg:orig_category":"Transports routiers de marchandises",
    "sg:phone":"+32 3 889 60 00",
    "sg:postcode":"2880",
    "sg:province":"Antwerpen",
    "wof:name":"De Smet",
    "wof:placetype":"venue"
},
  "geometry": {"coordinates":[4.2401371002,51.0779075623],"type":"Point"}
}