{
  "type": "Feature",
  "properties": {
    "iso:country":"BE",
    "sg:address":"Heeldstraat 10",
    "sg:city":"Genk",
    "sg:classifiers":[
        {
            "category":"Cafe",
            "type":"Food & Drink"
        }
    ],
    "sg:phone":"+32 89 30 32 90",
    "sg:postcode":"3600",
    "sg:province":"Limburg",
    "sg:tags":[
        "caf\u00e9s"
    ],
    "wof:name":"Caf\u00c9 Bret",
    "wof:placetype":"venue"
},
  "geometry": {"coordinates":[5.5232701302,50.9756011963],"type":"Point"}
}