{
  "type": "Feature",
  "properties": {
    "iso:country":"BE",
    "sg:address":"Brugstraat 45 Box 1",
    "sg:city":"Turnhout",
    "sg:classifiers":[
        {
            "category":"Utilities",
            "subcategory":"Natural Gas",
            "type":"Services"
        }
    ],
    "sg:phone":"+32 14 46 21 26",
    "sg:postcode":"2300",
    "sg:province":"Antwerpen",
    "sg:tags":[
        "industrial",
        "-"
    ],
    "wof:name":"Vandenborre Technologies Nv",
    "wof:placetype":"venue"
},
  "geometry": {"coordinates":[4.9279851913,51.3260040283],"type":"Point"}
}