{
  "type": "Feature",
  "properties": {
    "addr:full":"Donk 54 Lier Antwerpen 2500",
    "addr:housenumber":"54",
    "addr:postcode":"2500",
    "addr:street":"Donk",
    "iso:country":"BE",
    "sg:address":"Donk 54",
    "sg:city":"Lier",
    "sg:orig_category":"HERSTELLING ELEKTRISCHE HUISHOUDAPPARATEN Huishoudapparaten, televisies and radio's Telecommunicatie",
    "sg:phone":"+32 3 488 46 47",
    "sg:postcode":"2500",
    "sg:province":"Antwerpen",
    "wof:name":"Van Praag",
    "wof:placetype":"venue"
},
  "geometry": {"coordinates":[4.5707178116,51.1302833557],"type":"Point"}
}