{
  "type": "Feature",
  "properties": {
    "iso:country":"BE",
    "sg:address":"Rue Saint-mort 148",
    "sg:city":"Ohey",
    "sg:orig_category":"Sportclubs Sportterreinen and installaties behalve sportcentra",
    "sg:phone":"+32 85 61 12 95",
    "sg:postcode":"5351",
    "sg:province":"Namur",
    "wof:name":"R. Standard Club Oheytois",
    "wof:placetype":"venue"
},
  "geometry": {"coordinates":[5.1466321945,50.4483375549],"type":"Point"}
}