{
  "type": "Feature",
  "properties": {
    "iso:country":"BE",
    "sg:address":"Heiblok 58",
    "sg:city":"Essen",
    "sg:classifiers":[
        {
            "category":"Building & Trades",
            "subcategory":"Construction",
            "type":"Services"
        }
    ],
    "sg:phone":"+32 3 667 72 20",
    "sg:postcode":"2910",
    "sg:province":"Antwerpen",
    "sg:tags":[
        "installation",
        "-",
        "central",
        "heating"
    ],
    "wof:name":"Goossenaerts L",
    "wof:placetype":"venue"
},
  "geometry": {"coordinates":[4.505338192,51.4761314392],"type":"Point"}
}