{
  "type": "Feature",
  "properties": {
    "addr:full":"Oudebaan 225 Affligem (essene) Vlaams-Brabant 1790",
    "addr:housenumber":"225",
    "addr:postcode":"1790",
    "addr:street":"Oudebaan",
    "iso:country":"BE",
    "sg:address":"Oudebaan 225",
    "sg:city":"Affligem (essene)",
    "sg:classifiers":[
        {
            "category":"Health Services",
            "subcategory":"Doctor",
            "type":"Services"
        }
    ],
    "sg:phone":"+32 2 453 02 97",
    "sg:postcode":"1790",
    "sg:province":"Vlaams-Brabant",
    "sg:tags":[
        "medicinephysicians",
        "surgeon"
    ],
    "wof:name":"De Doncker V",
    "wof:placetype":"venue"
},
  "geometry": {"coordinates":[4.1276397705,50.909778595],"type":"Point"}
}