{
  "type": "Feature",
  "properties": {
    "iso:country":"BE",
    "sg:address":"Kirchstrasse 43",
    "sg:city":"Kelmis/la Calamine",
    "sg:orig_category":"Bloemen and planten",
    "sg:phone":"+32 87 65 65 75",
    "sg:postcode":"4720",
    "sg:province":"Li\u00e8ge",
    "wof:name":"Manuela's Blumenoase",
    "wof:placetype":"venue"
},
  "geometry": {"coordinates":[6.0124278069,50.7160682678],"type":"Point"}
}