{
  "type": "Feature",
  "properties": {
    "addr:full":"Rue Albert Ier 128 Dison Li\u00e8ge 4820",
    "addr:housenumber":"128",
    "addr:postcode":"4820",
    "addr:street":"Rue Albert Ier",
    "iso:country":"BE",
    "sg:address":"Rue Albert Ier 128",
    "sg:city":"Dison",
    "sg:orig_category":"Banques and organismes de cr\u00e9dit",
    "sg:phone":"+32 87 33 67 61",
    "sg:postcode":"4820",
    "sg:province":"Li\u00e8ge",
    "wof:name":"Cr\u00c9dit \u00c0 L\u00b4industrie",
    "wof:placetype":"venue"
},
  "geometry": {"coordinates":[5.8543801308,50.6090698242],"type":"Point"}
}