{
  "type": "Feature",
  "properties": {
    "iso:country":"BE",
    "sg:address":"Geneikenstraat 83",
    "sg:city":"Lummen",
    "sg:orig_category":"Textiel Verlichting and huishoudartikelen",
    "sg:phone":"+32 11 42 39 66",
    "sg:postcode":"3560",
    "sg:province":"Limburg",
    "wof:name":"Fa. Vanderaerden",
    "wof:placetype":"venue"
},
  "geometry": {"coordinates":[5.2181658745,51.0185012817],"type":"Point"}
}