{
  "type": "Feature",
  "properties": {
    "iso:country":"BE",
    "sg:address":"Basse-mouline 4c",
    "sg:city":"Libramont-chevigny (saint-pierre)",
    "sg:classifiers":[
        {
            "category":"Banks & Credit Unions",
            "subcategory":"Financial Services",
            "type":"Services"
        }
    ],
    "sg:phone":"+32 61 22 32 71",
    "sg:postcode":"6800",
    "sg:province":"Luxembourg",
    "sg:tags":[
        "loan",
        "mortgage"
    ],
    "wof:name":"La Maison Ardennaise",
    "wof:placetype":"venue"
},
  "geometry": {"coordinates":[5.3891119957,49.8920898438],"type":"Point"}
}