{
  "type": "Feature",
  "properties": {
    "iso:country":"BE",
    "sg:address":"Lindenstraat 18",
    "sg:city":"Aalst",
    "sg:orig_category":"Agences de presse",
    "sg:phone":"+32 53 70 55 42",
    "sg:postcode":"9300",
    "sg:province":"Oost-Vlaanderen",
    "wof:name":"Jos Gavel",
    "wof:placetype":"venue"
},
  "geometry": {"coordinates":[4.0177321434,50.9434165955],"type":"Point"}
}