{
  "type": "Feature",
  "properties": {
    "iso:country":"BE",
    "sg:address":"Rue Buraufosse 189",
    "sg:city":"Saint-nicolas",
    "sg:orig_category":"Epiceries",
    "sg:phone":"+32 4 233 64 77",
    "sg:postcode":"4420",
    "sg:province":"Li\u00e8ge",
    "wof:name":"Carmelina Benedetto",
    "wof:placetype":"venue"
},
  "geometry": {"coordinates":[5.5237498283,50.6250610352],"type":"Point"}
}