{
  "type": "Feature",
  "properties": {
    "iso:country":"BE",
    "sg:address":"Albertlaan 15",
    "sg:city":"Riemst",
    "sg:orig_category":"Huishoudapparaten, televisies and radio's",
    "sg:phone":"+32 12 45 36 41",
    "sg:postcode":"3770",
    "sg:province":"Limburg",
    "wof:name":"Johnny Stevens",
    "wof:placetype":"venue"
},
  "geometry": {"coordinates":[5.5738368034,50.8024673462],"type":"Point"}
}