{
  "type": "Feature",
  "properties": {
    "addr:full":"Parc Ind. Des Hauts Sarts 4e 66 Herstal Li\u00e8ge 4040",
    "addr:housenumber":"66",
    "addr:postcode":"4040",
    "addr:street":"Sarts 4E",
    "iso:country":"BE",
    "sg:address":"Parc Ind. Des Hauts Sarts 4e 66",
    "sg:city":"Herstal",
    "sg:classifiers":[
        {
            "category":"Professional",
            "type":"Services"
        }
    ],
    "sg:phone":"+32 4 240 70 40",
    "sg:postcode":"4040",
    "sg:province":"Li\u00e8ge",
    "sg:tags":[
        "transport"
    ],
    "wof:name":"Keulders S.a.",
    "wof:placetype":"venue"
},
  "geometry": {"coordinates":[5.6207761765,50.6997451782],"type":"Point"}
}