{
  "type": "Feature",
  "properties": {
    "iso:country":"BE",
    "sg:address":"Rue Du 25-ao\u00dbt 6",
    "sg:city":"Arlon",
    "sg:orig_category":"Industri\u00eble wasserijen and droogkuis",
    "sg:phone":"+32 63 22 44 66",
    "sg:postcode":"6700",
    "sg:province":"Luxembourg",
    "wof:name":"Nettoyage Edelweiss",
    "wof:placetype":"venue"
},
  "geometry": {"coordinates":[5.8115649223,49.6837844849],"type":"Point"}
}