{
  "type": "Feature",
  "properties": {
    "addr:full":"Chauss\u00c9e De Bruxelles 24 Charleroi Hainaut 6041",
    "addr:housenumber":"24",
    "addr:postcode":"6041",
    "addr:street":"Chausse\u0301E De Bruxelles;Hainaut",
    "iso:country":"BE",
    "sg:address":"Chauss\u00c9e De Bruxelles 24",
    "sg:city":"Charleroi",
    "sg:orig_category":"Herstellingen and onderhoud van auto's Voertuigen",
    "sg:phone":"+32 71 85 35 35",
    "sg:postcode":"6041",
    "sg:province":"Hainaut",
    "wof:name":"Garage Bouvy",
    "wof:placetype":"venue"
},
  "geometry": {"coordinates":[4.4402737617,50.4359855652],"type":"Point"}
}