{
  "type": "Feature",
  "properties": {
    "iso:country":"BE",
    "sg:address":"Rue De Lhonneux 13d",
    "sg:city":"Huy",
    "sg:classifiers":[
        {
            "category":"Manufacturing",
            "subcategory":"Motor Vehicles & Parts",
            "type":"Manufacturing & Wholesale Goods"
        }
    ],
    "sg:phone":"+32 85 25 03 01",
    "sg:postcode":"4500",
    "sg:province":"Li\u00e8ge",
    "sg:tags":[
        "automotive",
        "industry",
        "component",
        "plastic"
    ],
    "wof:name":"Plastic Works S.p.r.l.",
    "wof:placetype":"venue"
},
  "geometry": {"coordinates":[5.2388768196,50.528339386],"type":"Point"}
}