{
  "type": "Feature",
  "properties": {
    "addr:full":"Nederwijk 259 Ninove Oost-Vlaanderen 9400",
    "addr:housenumber":"259",
    "addr:postcode":"9400",
    "addr:street":"Nederwijk",
    "iso:country":"BE",
    "sg:address":"Nederwijk 259",
    "sg:city":"Ninove",
    "sg:orig_category":"Metaalbehandeling and -bekleding",
    "sg:phone":"+32 54 33 20 01",
    "sg:postcode":"9400",
    "sg:province":"Oost-Vlaanderen",
    "wof:name":"Fadani",
    "wof:placetype":"venue"
},
  "geometry": {"coordinates":[4.0368227959,50.8385925293],"type":"Point"}
}