{
  "type": "Feature",
  "properties": {
    "addr:full":"Heerstraat 34 Neerpelt Limburg 3910",
    "addr:housenumber":"34",
    "addr:postcode":"3910",
    "addr:street":"Heerstraat",
    "iso:country":"BE",
    "sg:address":"Heerstraat 34",
    "sg:city":"Neerpelt",
    "sg:classifiers":[
        {
            "category":"Restaurant",
            "type":"Food & Drink"
        }
    ],
    "sg:phone":"+32 11 66 31 17",
    "sg:postcode":"3910",
    "sg:province":"Limburg",
    "wof:name":"Au Bain Marie",
    "wof:placetype":"venue"
},
  "geometry": {"coordinates":[5.4368739128,51.2293128967],"type":"Point"}
}