{
  "type": "Feature",
  "properties": {
    "addr:full":"Rue Sainte-doroth\u00e9e 2 Mons Hainaut 7000",
    "addr:housenumber":"2",
    "addr:postcode":"7000",
    "addr:street":"Rue Sainte-Dorothe\u0301E;Hainaut",
    "iso:country":"BE",
    "sg:address":"Rue Sainte-doroth\u00e9e 2",
    "sg:city":"Mons",
    "sg:classifiers":[
        {
            "category":"Bars & Pubs",
            "type":"Food & Drink"
        }
    ],
    "sg:phone":"+32 65 84 53 66",
    "sg:postcode":"7000",
    "sg:province":"Hainaut",
    "wof:name":"Le B\u00e9guinage",
    "wof:placetype":"venue"
},
  "geometry": {"coordinates":[3.9444470406,50.4499893188],"type":"Point"}
}