{
  "type": "Feature",
  "properties": {
    "iso:country":"BE",
    "sg:address":"Rue Grande 3",
    "sg:city":"Tellin",
    "sg:classifiers":[
        {
            "category":"Cafe",
            "type":"Food & Drink"
        }
    ],
    "sg:phone":"+32 84 36 61 13",
    "sg:postcode":"6927",
    "sg:province":"Luxembourg",
    "sg:tags":[
        "caf\u00e9s"
    ],
    "wof:name":"Caf\u00c9 Gillain",
    "wof:placetype":"venue"
},
  "geometry": {"coordinates":[5.2174491882,50.0809288025],"type":"Point"}
}