{
  "type": "Feature",
  "properties": {
    "addr:full":"Rue Des Deux-ponts 20 Ottignies-louvain-la-neuve Brabant Wallon 1340",
    "addr:housenumber":"20",
    "addr:postcode":"1340",
    "addr:street":"Rue Des Deux-Ponts",
    "iso:country":"BE",
    "sg:address":"Rue Des Deux-ponts 20",
    "sg:city":"Ottignies-louvain-la-neuve",
    "sg:orig_category":"Banken and kredietinstellingen",
    "sg:phone":"+32 10 41 01 11",
    "sg:postcode":"1340",
    "sg:province":"Brabant Wallon",
    "wof:name":"Centea",
    "wof:placetype":"venue"
},
  "geometry": {"coordinates":[4.5720310211,50.6679267883],"type":"Point"}
}