{
  "type": "Feature",
  "properties": {
    "iso:country":"BE",
    "sg:address":"Rue Verte 56",
    "sg:city":"Herstal",
    "sg:orig_category":"G\u00e2teaux, p\u00e2tisserie and biscuits Fab",
    "sg:phone":"+32 4 264 89 44",
    "sg:postcode":"4040",
    "sg:province":"Li\u00e8ge",
    "wof:name":"Bruno Porta",
    "wof:placetype":"venue"
},
  "geometry": {"coordinates":[5.6080698967,50.6717224121],"type":"Point"}
}