{
  "type": "Feature",
  "properties": {
    "iso:country":"BE",
    "sg:address":"Barend Van Orlystraat 4",
    "sg:city":"Kortrijk (marke)",
    "sg:classifiers":[
        {
            "category":"Banks & Credit Unions",
            "subcategory":"Investment Brokerage",
            "type":"Services"
        }
    ],
    "sg:phone":"+32 56 22 31 70",
    "sg:postcode":"8510",
    "sg:province":"West-Vlaanderen",
    "sg:tags":[
        "auditor"
    ],
    "wof:name":"Indigne A",
    "wof:placetype":"venue"
},
  "geometry": {"coordinates":[3.2575340271,50.8042373657],"type":"Point"}
}