{
  "type": "Feature",
  "properties": {
    "addr:full":"Diestersteenweg 128 Nieuwerkerken Limburg 3850",
    "addr:housenumber":"128",
    "addr:postcode":"3850",
    "addr:street":"Diestersteenweg",
    "iso:country":"BE",
    "sg:address":"Diestersteenweg 128",
    "sg:city":"Nieuwerkerken",
    "sg:orig_category":"Herstelling horloges and juwelen Juwelen and horloges Opticiens",
    "sg:phone":"+32 11 68 35 51",
    "sg:postcode":"3850",
    "sg:province":"Limburg",
    "wof:name":"Huis Adriaens-vandijk",
    "wof:placetype":"venue"
},
  "geometry": {"coordinates":[5.1888408661,50.8637008667],"type":"Point"}
}