{
  "type": "Feature",
  "properties": {
    "addr:full":"Rue D'hoyaux 10 Peruwelz Hainaut 7602",
    "addr:housenumber":"10",
    "addr:postcode":"7602",
    "addr:street":"Rue D'Hoyaux;Hainaut",
    "iso:country":"BE",
    "sg:address":"Rue D'hoyaux 10",
    "sg:city":"Peruwelz",
    "sg:orig_category":"Eleveurs de bovins",
    "sg:phone":"+32 69 77 18 56",
    "sg:postcode":"7602",
    "sg:province":"Hainaut",
    "wof:name":"Jean-luc Debliquy",
    "wof:placetype":"venue"
},
  "geometry": {"coordinates":[3.5986979008,50.5477294922],"type":"Point"}
}