{
  "type": "Feature",
  "properties": {
    "addr:full":"Rue Du Commerce 24 Wavre Brabant Wallon 1300",
    "addr:housenumber":"24;1300",
    "addr:street":"Rue Du Commerce",
    "iso:country":"BE",
    "sg:address":"Rue Du Commerce 24",
    "sg:city":"Wavre",
    "sg:orig_category":"Parfumeries. Centres de relaxation and bien-\u00eatre. Instituts de beaut\u00e9",
    "sg:phone":"+32 10 22 55 22",
    "sg:postcode":"1300",
    "sg:province":"Brabant Wallon",
    "wof:name":"Moa",
    "wof:placetype":"venue"
},
  "geometry": {"coordinates":[4.6100897789,50.7163352966],"type":"Point"}
}