{
  "type": "Feature",
  "properties": {
    "addr:full":"Vis\u00e9 Voie 17 Li\u00e8ge 1 (rocourt) Li\u00e8ge 4000",
    "addr:housenumber":"17;1",
    "addr:postcode":"4000",
    "addr:street":"Voie",
    "iso:country":"BE",
    "sg:address":"Vis\u00e9 Voie 17",
    "sg:city":"Li\u00e8ge 1 (rocourt)",
    "sg:classifiers":[
        {
            "category":"Wholesale",
            "subcategory":"Medical Equipment & Supplies",
            "type":"Manufacturing & Wholesale Goods"
        }
    ],
    "sg:phone":"+32 4 224 10 51",
    "sg:postcode":"4000",
    "sg:province":"Li\u00e8ge",
    "sg:tags":[
        "-",
        "gas"
    ],
    "wof:name":"Trubbia Fr\u00e8res Et Fils Sprl",
    "wof:placetype":"venue"
},
  "geometry": {"coordinates":[5.5629339218,50.6644172668],"type":"Point"}
}