{
  "type": "Feature",
  "properties": {
    "iso:country":"BE",
    "sg:address":"Beernemsteenweg 56",
    "sg:city":"Wingene",
    "sg:orig_category":"Elektrische installaties voor woningen",
    "sg:phone":"+32 51 65 84 78",
    "sg:postcode":"8750",
    "sg:province":"West-Vlaanderen",
    "wof:name":"Fa. Van Hauwaert",
    "wof:placetype":"venue"
},
  "geometry": {"coordinates":[3.2784159184,51.0627975464],"type":"Point"}
}