{
  "type": "Feature",
  "properties": {
    "addr:full":"Rue Du Village 23 Leuze-en-hainaut Hainaut 7903",
    "addr:housenumber":"23",
    "addr:postcode":"7903",
    "addr:street":"Rue Du Village",
    "iso:country":"BE",
    "sg:address":"Rue Du Village 23",
    "sg:city":"Leuze-en-hainaut",
    "sg:orig_category":"Schoonheidssalons",
    "sg:phone":"+32 69 66 10 90",
    "sg:postcode":"7903",
    "sg:province":"Hainaut",
    "wof:name":"Chantal Legaix",
    "wof:placetype":"venue"
},
  "geometry": {"coordinates":[3.66654706,50.5950737],"type":"Point"}
}