{
  "type": "Feature",
  "properties": {
    "iso:country":"BE",
    "sg:address":"Cit\u00c9 Belle-vue 16",
    "sg:city":"Comblain-au-pont",
    "sg:orig_category":"Sportclubs",
    "sg:phone":"+32 4 380 32 62",
    "sg:postcode":"4170",
    "sg:province":"Li\u00e8ge",
    "wof:name":"T.c. Mont",
    "wof:placetype":"venue"
},
  "geometry": {"coordinates":[5.574696064,50.5036392212],"type":"Point"}
}