{
  "type": "Feature",
  "properties": {
    "addr:full":"Rue De La Clef-d'or 40 Sambreville Namur 5060",
    "addr:housenumber":"40",
    "addr:postcode":"5060",
    "addr:street":"Rue De La Clef-D'Or",
    "iso:country":"BE",
    "sg:address":"Rue De La Clef-d'or 40",
    "sg:city":"Sambreville",
    "sg:orig_category":"Rundveehouders",
    "sg:phone":"+32 71 77 19 46",
    "sg:postcode":"5060",
    "sg:province":"Namur",
    "wof:name":"Andre Therasse",
    "wof:placetype":"venue"
},
  "geometry": {"coordinates":[4.6219601631,50.4459686279],"type":"Point"}
}