{
  "type": "Feature",
  "properties": {
    "addr:full":"Beekstraat 55 Assenede Oost-Vlaanderen 9968",
    "addr:housenumber":"55",
    "addr:postcode":"9968",
    "addr:street":"Beekstraat",
    "iso:country":"BE",
    "sg:address":"Beekstraat 55",
    "sg:city":"Assenede",
    "sg:orig_category":"Traitements param\u00e9dicaux",
    "sg:phone":"+32 9 373 63 74",
    "sg:postcode":"9968",
    "sg:province":"Oost-Vlaanderen",
    "wof:name":"A. Van De Velde",
    "wof:placetype":"venue"
},
  "geometry": {"coordinates":[3.6887938976,51.1923027039],"type":"Point"}
}