{
  "type": "Feature",
  "properties": {
    "iso:country":"BE",
    "sg:address":"Rue All\u00c9e 12",
    "sg:city":"Charleroi",
    "sg:orig_category":"Rev\u00eatements de sols and murs",
    "sg:phone":"+32 71 70 28 93",
    "sg:postcode":"6001",
    "sg:province":"Hainaut",
    "wof:name":"Technosol Sa",
    "wof:placetype":"venue"
},
  "geometry": {"coordinates":[4.4448251724,50.3973655701],"type":"Point"}
}