{
  "type": "Feature",
  "properties": {
    "iso:country":"BE",
    "sg:address":"Diesterstraat 15",
    "sg:city":"Sint-truiden",
    "sg:orig_category":"Kapsalons",
    "sg:phone":"+32 11 69 24 64",
    "sg:postcode":"3800",
    "sg:province":"Limburg",
    "wof:name":"Coiffure Anne-mie",
    "wof:placetype":"venue"
},
  "geometry": {"coordinates":[5.1858839989,50.8172531128],"type":"Point"}
}