{
  "type": "Feature",
  "properties": {
    "addr:full":"Grote Steenweg 2 Laakdal (veerle) Antwerpen 2431",
    "addr:housenumber":"2",
    "addr:postcode":"2431",
    "addr:street":"Grote Steenweg",
    "iso:country":"BE",
    "sg:address":"Grote Steenweg 2",
    "sg:city":"Laakdal (veerle)",
    "sg:classifiers":[
        {
            "category":"Food & Beverages",
            "subcategory":"Groceries & Convenience Stores",
            "type":"Retail Goods"
        }
    ],
    "sg:phone":"+32 14 84 80 95",
    "sg:postcode":"2431",
    "sg:province":"Antwerpen",
    "sg:tags":[
        "baker",
        "-",
        "ingredient"
    ],
    "wof:name":"Bakhuisje ('t)",
    "wof:placetype":"venue"
},
  "geometry": {"coordinates":[4.9631619453,51.0741767883],"type":"Point"}
}