{
  "type": "Feature",
  "properties": {
    "iso:country":"BE",
    "sg:address":"Nieuwe Boekhoutestraat 27",
    "sg:city":"Assenede",
    "sg:orig_category":"Sportclubs Sportterreinen and installaties behalve sportcentra",
    "sg:phone":"+32 9 373 82 93",
    "sg:postcode":"9968",
    "sg:province":"Oost-Vlaanderen",
    "wof:name":"K.v.v. Kl. Bassevelde",
    "wof:placetype":"venue"
},
  "geometry": {"coordinates":[3.6940219402,51.2353401184],"type":"Point"}
}