{
  "type": "Feature",
  "properties": {
    "addr:full":"Parc M\u00e9nobu 546 Theux (la Reid) Li\u00e8ge 4910",
    "addr:housenumber":"546",
    "addr:postcode":"4910",
    "addr:street":"La Reid",
    "iso:country":"BE",
    "sg:address":"Parc M\u00e9nobu 546",
    "sg:city":"Theux (la Reid)",
    "sg:classifiers":[
        {
            "category":"Travel",
            "subcategory":"Hotels & Motels",
            "type":"Entertainment"
        }
    ],
    "sg:phone":"+32 87 37 60 42",
    "sg:postcode":"4910",
    "sg:province":"Li\u00e8ge",
    "wof:name":"Menobu (le)",
    "wof:placetype":"venue"
},
  "geometry": {"coordinates":[5.7673540115,50.5002479553],"type":"Point"}
}