{
  "type": "Feature",
  "properties": {
    "addr:full":"El Roue 5 Gesves Namur 5340",
    "addr:housenumber":"5",
    "addr:postcode":"5340",
    "addr:street":"Roue",
    "iso:country":"BE",
    "sg:address":"El Roue 5",
    "sg:city":"Gesves",
    "sg:orig_category":"Boucheries",
    "sg:phone":"+32 83 67 70 62",
    "sg:postcode":"5340",
    "sg:province":"Namur",
    "wof:name":"Maurice Michaux",
    "wof:placetype":"venue"
},
  "geometry": {"coordinates":[5.0685091019,50.4097976685],"type":"Point"}
}