{
  "type": "Feature",
  "properties": {
    "addr:full":"Avenue De Nancy 66 Li\u00e8ge 1 (li\u00e8ge 2) Li\u00e8ge 4020",
    "addr:housenumber":"66;1;2",
    "addr:postcode":"4020",
    "addr:street":"Avenue De Nancy",
    "iso:country":"BE",
    "sg:address":"Avenue De Nancy 66",
    "sg:city":"Li\u00e8ge 1 (li\u00e8ge 2)",
    "sg:classifiers":[
        {
            "category":"Health Services",
            "subcategory":"Dentist",
            "type":"Services"
        }
    ],
    "sg:phone":"+32 4 344 05 96",
    "sg:postcode":"4020",
    "sg:province":"Li\u00e8ge",
    "wof:name":"Deldinne Bernard",
    "wof:placetype":"venue"
},
  "geometry": {"coordinates":[5.6015758514,50.6447372437],"type":"Point"}
}