{
  "type": "Feature",
  "properties": {
    "iso:country":"BE",
    "sg:address":"Chemin De La Poudrerie 6",
    "sg:city":"Soignies",
    "sg:orig_category":"Jeux de hasard",
    "sg:phone":"+32 65 73 03 12",
    "sg:postcode":"7061",
    "sg:province":"Hainaut",
    "wof:name":"J Simon & Co",
    "wof:placetype":"venue"
},
  "geometry": {"coordinates":[4.0133500099,50.5159416199],"type":"Point"}
}