{
  "type": "Feature",
  "properties": {
    "iso:country":"BE",
    "sg:address":"Notelaarstraat 17",
    "sg:city":"Bonheiden",
    "sg:classifiers":[
        {
            "category":"Personal",
            "subcategory":"Beauty Salon",
            "type":"Services"
        }
    ],
    "sg:phone":"+32 15 55 11 83",
    "sg:postcode":"2820",
    "sg:province":"Antwerpen",
    "sg:tags":[
        "lady",
        "-",
        "hairdressing"
    ],
    "wof:name":"Van Der Seen I",
    "wof:placetype":"venue"
},
  "geometry": {"coordinates":[4.5251088142,51.036693573],"type":"Point"}
}