{
  "type": "Feature",
  "properties": {
    "iso:country":"BE",
    "sg:address":"Rue Wartonlieu 60",
    "sg:city":"Courcelles",
    "sg:classifiers":[
        {
            "category":"Shopping",
            "subcategory":"Books",
            "type":"Retail Goods"
        }
    ],
    "sg:phone":"+32 71 45 80 67",
    "sg:postcode":"6180",
    "sg:province":"Hainaut",
    "sg:tags":[
        "bookseller"
    ],
    "wof:name":"Piacentino",
    "wof:placetype":"venue"
},
  "geometry": {"coordinates":[4.3887610435,50.467540741],"type":"Point"}
}