{
  "type": "Feature",
  "properties": {
    "iso:country":"BE",
    "sg:address":"Rue Aux Pois 7",
    "sg:city":"Tournai",
    "sg:orig_category":"Maisons de repos and r\u00e9sidences",
    "sg:phone":"+32 69 35 25 73",
    "sg:postcode":"7520",
    "sg:province":"Hainaut",
    "wof:name":"Home Alphonse Marie",
    "wof:placetype":"venue"
},
  "geometry": {"coordinates":[3.2821800709,50.6415214539],"type":"Point"}
}