{
  "type": "Feature",
  "properties": {
    "addr:full":"Clemenceaustraat 171 Sint-katelijne-waver Antwerpen 2860",
    "addr:housenumber":"171",
    "addr:postcode":"2860",
    "addr:street":"Clemenceaustraat",
    "iso:country":"BE",
    "sg:address":"Clemenceaustraat 171",
    "sg:city":"Sint-katelijne-waver",
    "sg:classifiers":[
        {
            "category":"Health Services",
            "subcategory":"Dentist",
            "type":"Services"
        }
    ],
    "sg:phone":"+32 15 31 96 66",
    "sg:postcode":"2860",
    "sg:province":"Antwerpen",
    "wof:name":"De Wit K",
    "wof:placetype":"venue"
},
  "geometry": {"coordinates":[4.4899630547,51.0628356934],"type":"Point"}
}