{
  "type": "Feature",
  "properties": {
    "addr:full":"Statieplein 2 Lichtervelde West-Vlaanderen 8810",
    "addr:housenumber":"2",
    "addr:postcode":"8810",
    "addr:street":"Statieplein",
    "iso:country":"BE",
    "sg:address":"Statieplein 2",
    "sg:city":"Lichtervelde",
    "sg:classifiers":[
        {
            "category":"Personal",
            "subcategory":"Beauty Salon",
            "type":"Services"
        }
    ],
    "sg:phone":"+32 51 72 21 93",
    "sg:postcode":"8810",
    "sg:province":"West-Vlaanderen",
    "sg:tags":[
        "de",
        "coiffure"
    ],
    "wof:name":"Coiffure Andre",
    "wof:placetype":"venue"
},
  "geometry": {"coordinates":[3.1411089897,51.0263137817],"type":"Point"}
}