{
  "type": "Feature",
  "properties": {
    "addr:full":"Koolmijnlaan 201 Beringen Limburg 3580",
    "addr:housenumber":"201",
    "addr:postcode":"3580",
    "addr:street":"Koolmijnlaan",
    "iso:country":"BE",
    "sg:address":"Koolmijnlaan 201",
    "sg:city":"Beringen",
    "sg:classifiers":[
        {
            "category":"Retail",
            "subcategory":"Storage",
            "type":"Services"
        }
    ],
    "sg:phone":"+32 11 45 07 60",
    "sg:postcode":"3580",
    "sg:province":"Limburg",
    "sg:tags":[
        "dangerous",
        "material"
    ],
    "wof:name":"P.c.t. Nv",
    "wof:placetype":"venue"
},
  "geometry": {"coordinates":[5.2222099304,51.0599594116],"type":"Point"}
}