{
  "type": "Feature",
  "properties": {
    "iso:country":"BE",
    "sg:address":"Klein Lafeltstraat 33",
    "sg:city":"Riemst",
    "sg:orig_category":"Rundveehouders",
    "sg:phone":"+32 12 45 47 09",
    "sg:postcode":"3770",
    "sg:province":"Limburg",
    "wof:name":"Johannes Wouters",
    "wof:placetype":"venue"
},
  "geometry": {"coordinates":[5.6024160385,50.8125953674],"type":"Point"}
}