{
  "type": "Feature",
  "properties": {
    "addr:full":"Surister 6 Jalhay Li\u00e8ge 4845",
    "addr:housenumber":"6",
    "addr:postcode":"4845",
    "addr:street":"Surister",
    "iso:country":"BE",
    "sg:address":"Surister 6",
    "sg:city":"Jalhay",
    "sg:orig_category":"Computers and computerapparatuur Software ontwikkeling and ontwerp",
    "sg:phone":"+32 87 64 61 64",
    "sg:postcode":"4845",
    "sg:province":"Li\u00e8ge",
    "wof:name":"Epi International",
    "wof:placetype":"venue"
},
  "geometry": {"coordinates":[5.9230241776,50.542175293],"type":"Point"}
}