{
  "type": "Feature",
  "properties": {
    "addr:full":"Rue Vonck 19b3 Sint-joost-ten-node/saint-josse-ten-noode Bruxelles-Capitale 1210",
    "addr:housenumber":"19b3",
    "addr:postcode":"1210",
    "addr:street":"Rue Vonck",
    "iso:country":"BE",
    "sg:address":"Rue Vonck 19b3",
    "sg:city":"Sint-joost-ten-node/saint-josse-ten-noode",
    "sg:orig_category":"Parfumeries",
    "sg:phone":"+32 2 219 81 13",
    "sg:postcode":"1210",
    "sg:province":"Bruxelles-Capitale",
    "wof:name":"Ignazia Schifano",
    "wof:placetype":"venue"
},
  "geometry": {"coordinates":[4.3761320114,50.8535652161],"type":"Point"}
}