{
  "type": "Feature",
  "properties": {
    "addr:full":"Statiestraat 3 Staden West-Vlaanderen 8840",
    "addr:housenumber":"3",
    "addr:postcode":"8840",
    "addr:street":"Statiestraat",
    "iso:country":"BE",
    "sg:address":"Statiestraat 3",
    "sg:city":"Staden",
    "sg:orig_category":"Verplichte sociale verzekeringen",
    "sg:phone":"+32 51 70 18 57",
    "sg:postcode":"8840",
    "sg:province":"West-Vlaanderen",
    "wof:name":"Westvl. Liberaal Ziekenf.",
    "wof:placetype":"venue"
},
  "geometry": {"coordinates":[3.0140120983,50.9748878479],"type":"Point"}
}