{
  "type": "Feature",
  "properties": {
    "iso:country":"BE",
    "sg:address":"Avenue Georges Henri 265",
    "sg:city":"Bruxelles (woluwe-saint-lambert)",
    "sg:classifiers":[
        {
            "category":"Food & Beverages",
            "subcategory":"Groceries & Convenience Stores",
            "type":"Retail Goods"
        }
    ],
    "sg:phone":"+32 2 770 46 95",
    "sg:postcode":"1200",
    "sg:province":"Bruxelles-Capitale",
    "sg:tags":[
        "grocer"
    ],
    "wof:name":"Corbeille D'or (la)",
    "wof:placetype":"venue"
},
  "geometry": {"coordinates":[4.4141421318,50.8440666199],"type":"Point"}
}