{
  "type": "Feature",
  "properties": {
    "iso:country":"BE",
    "sg:address":"Chauss\u00c9e De Charleroi 29",
    "sg:city":"Jodoigne",
    "sg:orig_category":"Gespecialiseerde residenti\u00eble bouw Woningbouw",
    "sg:phone":"+32 10 81 40 58",
    "sg:postcode":"1370",
    "sg:province":"Brabant Wallon",
    "wof:name":"Schema Modul",
    "wof:placetype":"venue"
},
  "geometry": {"coordinates":[4.8430299759,50.6925392151],"type":"Point"}
}