{
  "type": "Feature",
  "properties": {
    "iso:country":"BE",
    "sg:address":"Jan Van Puyenbroecklaan 75",
    "sg:city":"Schoten",
    "sg:classifiers":[
        {
            "category":"Banks & Credit Unions",
            "subcategory":"Financial Services",
            "type":"Services"
        }
    ],
    "sg:phone":"+32 3 644 02 00",
    "sg:postcode":"2900",
    "sg:province":"Antwerpen",
    "sg:tags":[
        "debt",
        "recovery"
    ],
    "wof:name":"Juridisch Schuldvorderingskantoor",
    "wof:placetype":"venue"
},
  "geometry": {"coordinates":[4.4677419662,51.2617225647],"type":"Point"}
}