{
  "type": "Feature",
  "properties": {
    "addr:full":"Molenstraat 67 Aalst Oost-Vlaanderen 9300",
    "addr:housenumber":"67",
    "addr:postcode":"9300",
    "addr:street":"Molenstraat",
    "iso:country":"BE",
    "sg:address":"Molenstraat 67",
    "sg:city":"Aalst",
    "sg:classifiers":[
        {
            "category":"Fast Food",
            "type":"Food & Drink"
        }
    ],
    "sg:phone":"+32 53 21 10 92",
    "sg:postcode":"9300",
    "sg:province":"Oost-Vlaanderen",
    "sg:tags":[
        "meeneem",
        "restaurant"
    ],
    "wof:name":"Restaurant Shanghai",
    "wof:placetype":"venue"
},
  "geometry": {"coordinates":[4.0428891182,50.9395713806],"type":"Point"}
}