{
  "type": "Feature",
  "properties": {
    "iso:country":"BE",
    "sg:address":"Broekhuizenstraat 11",
    "sg:city":"Maldegem",
    "sg:orig_category":"Traitements param\u00e9dicaux",
    "sg:phone":"+32 50 71 81 66",
    "sg:postcode":"9990",
    "sg:province":"Oost-Vlaanderen",
    "wof:name":"Van Deursen Greta",
    "wof:placetype":"venue"
},
  "geometry": {"coordinates":[3.4601531029,51.2237014771],"type":"Point"}
}