{
  "type": "Feature",
  "properties": {
    "iso:country":"BE",
    "sg:address":"Rue De Bohan 91",
    "sg:city":"Vresse-sur-semois",
    "sg:orig_category":"Alimentation sp\u00e9cialis\u00e9e",
    "sg:phone":"+32 61 50 34 10",
    "sg:postcode":"5550",
    "sg:province":"Namur",
    "wof:name":"Le H\u00c9risson",
    "wof:placetype":"venue"
},
  "geometry": {"coordinates":[4.9336900711,49.8729820251],"type":"Point"}
}