{
  "type": "Feature",
  "properties": {
    "iso:country":"BE",
    "sg:address":"Rue De La Falloise 3",
    "sg:city":"Paliseul (offagne)",
    "sg:classifiers":[
        {
            "category":"Retail",
            "subcategory":"Auto Repair",
            "type":"Services"
        }
    ],
    "sg:phone":"+32 61 53 47 12",
    "sg:postcode":"6850",
    "sg:province":"Luxembourg",
    "sg:tags":[
        "automobile-body"
    ],
    "wof:name":"Cavelier J.m",
    "wof:placetype":"venue"
},
  "geometry": {"coordinates":[5.1349849701,49.9033889771],"type":"Point"}
}