{
  "type": "Feature",
  "properties": {
    "iso:country":"BE",
    "sg:address":"Lindelei 17",
    "sg:city":"Lint",
    "sg:orig_category":"M\u00e9decins and sp\u00e9cialistes",
    "sg:phone":"+32 3 455 25 31",
    "sg:postcode":"2547",
    "sg:province":"Antwerpen",
    "wof:name":"Mark Blyweert",
    "wof:placetype":"venue"
},
  "geometry": {"coordinates":[4.4984459877,51.1288833618],"type":"Point"}
}