{
  "type": "Feature",
  "properties": {
    "addr:full":"Rue Jonet 84-86 Charleroi Hainaut 6000",
    "addr:housenumber":"84-86",
    "addr:postcode":"6000",
    "addr:street":"Rue Jonet;Hainaut",
    "iso:country":"BE",
    "sg:address":"Rue Jonet 84-86",
    "sg:city":"Charleroi",
    "sg:classifiers":[
        {
            "category":"Manufacturing",
            "subcategory":"Metals",
            "type":"Manufacturing & Wholesale Goods"
        }
    ],
    "sg:phone":"+32 71 41 79 98",
    "sg:postcode":"6000",
    "sg:province":"Hainaut",
    "sg:tags":[
        "ironwork"
    ],
    "wof:name":"Ateliers Lenom Sprl",
    "wof:placetype":"venue"
},
  "geometry": {"coordinates":[4.4610648155,50.4241104126],"type":"Point"}
}