{
  "type": "Feature",
  "properties": {
    "addr:full":"Waalbrugstraat 3 Gent Oost-Vlaanderen 9032",
    "addr:housenumber":"3",
    "addr:postcode":"9032",
    "addr:street":"Waalbrugstraat;Oost-Vlaanderen",
    "iso:country":"BE",
    "sg:address":"Waalbrugstraat 3",
    "sg:city":"Gent",
    "sg:classifiers":[
        {
            "category":"Fast Food",
            "type":"Food & Drink"
        }
    ],
    "sg:phone":"+32 9 258 17 21",
    "sg:postcode":"9032",
    "sg:province":"Oost-Vlaanderen",
    "sg:tags":[
        "meeneem",
        "restaurant"
    ],
    "wof:name":"Mcdonald's",
    "wof:placetype":"venue"
},
  "geometry": {"coordinates":[3.7162549496,51.0900535583],"type":"Point"}
}