{
  "type": "Feature",
  "properties": {
    "addr:full":"Rue Fontaine St.-martin 99 Braine-l'alleud Brabant Wallon 1428",
    "addr:housenumber":"99",
    "addr:postcode":"1428",
    "addr:street":"Rue Fontaine St.-Martin",
    "iso:country":"BE",
    "sg:address":"Rue Fontaine St.-martin 99",
    "sg:city":"Braine-l'alleud",
    "sg:orig_category":"Woningbouw",
    "sg:phone":"+32 2 384 90 67",
    "sg:postcode":"1428",
    "sg:province":"Brabant Wallon",
    "wof:name":"Fe. Bulbo",
    "wof:placetype":"venue"
},
  "geometry": {"coordinates":[2.4406859875,47.157497406],"type":"Point"}
}