{
  "type": "Feature",
  "properties": {
    "iso:country":"BE",
    "sg:address":"Avenue De Bouillon 68",
    "sg:city":"Libramont-chevigny (recogne)",
    "sg:classifiers":[
        {
            "category":"Professional",
            "subcategory":"Art Services",
            "type":"Services"
        }
    ],
    "sg:phone":"+32 61 22 46 13",
    "sg:postcode":"6800",
    "sg:province":"Luxembourg",
    "sg:tags":[
        "photography",
        "reporting",
        "-"
    ],
    "wof:name":"Jlb Photo",
    "wof:placetype":"venue"
},
  "geometry": {"coordinates":[5.3597779274,49.9145126343],"type":"Point"}
}