{
  "type": "Feature",
  "properties": {
    "iso:country":"BE",
    "sg:address":"Balsakker 0",
    "sg:city":"Lille",
    "sg:classifiers":[
        {
            "category":"Cafe",
            "type":"Food & Drink"
        }
    ],
    "sg:phone":"+32 14 88 30 31",
    "sg:postcode":"2275",
    "sg:province":"Antwerpen",
    "sg:tags":[
        "caf\u00e9s"
    ],
    "wof:name":"Caf\u00c9 Balsakker",
    "wof:placetype":"venue"
},
  "geometry": {"coordinates":[4.8082580566,51.2386627197],"type":"Point"}
}