{
  "type": "Feature",
  "properties": {
    "iso:country":"BE",
    "sg:address":"Trieu Linglot 5",
    "sg:city":"Thuin",
    "sg:classifiers":[
        {
            "category":"Insurance",
            "subcategory":"Life Insurance",
            "type":"Services"
        }
    ],
    "sg:phone":"+32 71 59 00 64",
    "sg:postcode":"6531",
    "sg:province":"Hainaut",
    "sg:tags":[
        "assurance"
    ],
    "wof:name":"D. D\u00b4hotel",
    "wof:placetype":"venue"
},
  "geometry": {"coordinates":[4.30753088,50.3248672485],"type":"Point"}
}