{
  "type": "Feature",
  "properties": {
    "iso:country":"BE",
    "sg:address":"Rue Bois De Lahaut 15",
    "sg:city":"Namur (boninne - Gelbress\u00e9e)",
    "sg:classifiers":[
        {
            "category":"Building & Trades",
            "subcategory":"Landscaping Services",
            "type":"Services"
        }
    ],
    "sg:phone":"+32 81 20 03 21",
    "sg:postcode":"5021",
    "sg:province":"Namur",
    "sg:tags":[
        "architect",
        "landscape"
    ],
    "wof:name":"Tasiaux Fran\u00e7ois",
    "wof:placetype":"venue"
},
  "geometry": {"coordinates":[4.9194841385,50.4932327271],"type":"Point"}
}