{
  "type": "Feature",
  "properties": {
    "addr:full":"Avenue Eug\u00c8ne Ysaye 12b8 Chaudfontaine Li\u00e8ge 4053",
    "addr:housenumber":"12b8",
    "addr:postcode":"4053",
    "addr:street":"Avenue Euge\u0300Ne Ysaye",
    "iso:country":"BE",
    "sg:address":"Avenue Eug\u00c8ne Ysaye 12b8",
    "sg:city":"Chaudfontaine",
    "sg:orig_category":"Traitements param\u00e9dicaux",
    "sg:phone":"+32 4 365 74 78",
    "sg:postcode":"4053",
    "sg:province":"Li\u00e8ge",
    "wof:name":"A. Gillet",
    "wof:placetype":"venue"
},
  "geometry": {"coordinates":[5.6063599586,50.5931015015],"type":"Point"}
}