{
  "type": "Feature",
  "properties": {
    "iso:country":"BE",
    "sg:address":"De Smet De Naeyerlaan 245",
    "sg:city":"Jette",
    "sg:orig_category":"Kantoormateriaal Krantenwinkels Rookartikelen",
    "sg:phone":"+32 2 425 62 26",
    "sg:postcode":"1090",
    "sg:province":"Bruxelles-Capitale",
    "wof:name":"Librairie St.pierre",
    "wof:placetype":"venue"
},
  "geometry": {"coordinates":[4.3311238289,50.8770561218],"type":"Point"}
}