{
  "type": "Feature",
  "properties": {
    "iso:country":"BE",
    "sg:address":"Grote Baan 205",
    "sg:city":"Aalst (herdersem)",
    "sg:classifiers":[
        {
            "category":"Home & Garden",
            "subcategory":"Home Furnishings",
            "type":"Retail Goods"
        }
    ],
    "sg:phone":"+32 53 77 64 41",
    "sg:postcode":"9310",
    "sg:province":"Oost-Vlaanderen",
    "sg:tags":[
        "interior",
        "decoration"
    ],
    "wof:name":"Hendrickx M",
    "wof:placetype":"venue"
},
  "geometry": {"coordinates":[4.0665278435,50.9711112976],"type":"Point"}
}