{
  "type": "Feature",
  "properties": {
    "iso:country":"BE",
    "sg:address":"Rue Grande-louvi\u00c8re 64",
    "sg:city":"La Louviere",
    "sg:orig_category":"Rev\u00eatements pour sols and murs. Peinture",
    "sg:phone":"+32 64 22 68 84",
    "sg:postcode":"7100",
    "sg:province":"Hainaut",
    "wof:name":"Franco D\u00c9cor",
    "wof:placetype":"venue"
},
  "geometry": {"coordinates":[4.169547081,50.4780311584],"type":"Point"}
}