{
  "type": "Feature",
  "properties": {
    "addr:full":"Nerenbroekstraat 82 Erpe-mere Oost-Vlaanderen 9420",
    "addr:housenumber":"82",
    "addr:postcode":"9420",
    "addr:street":"Nerenbroekstraat",
    "iso:country":"BE",
    "sg:address":"Nerenbroekstraat 82",
    "sg:city":"Erpe-mere",
    "sg:orig_category":"Meubelzaken, woning- and keukeninrichting",
    "sg:phone":"+32 53 80 09 65",
    "sg:postcode":"9420",
    "sg:province":"Oost-Vlaanderen",
    "wof:name":"Di",
    "wof:placetype":"venue"
},
  "geometry": {"coordinates":[3.9762101173,50.9441757202],"type":"Point"}
}