{
  "type": "Feature",
  "properties": {
    "addr:full":"Gasthuisbosdreef 34 Tongeren Limburg 3700",
    "addr:housenumber":"34",
    "addr:postcode":"3700",
    "addr:street":"Gasthuisbosdreef",
    "iso:country":"BE",
    "sg:address":"Gasthuisbosdreef 34",
    "sg:city":"Tongeren",
    "sg:classifiers":[
        {
            "category":"Home & Garden",
            "subcategory":"Kitchen Supply",
            "type":"Retail Goods"
        }
    ],
    "sg:phone":"+32 12 23 75 59",
    "sg:postcode":"3700",
    "sg:province":"Limburg",
    "sg:tags":[
        "installation"
    ],
    "wof:name":"Rottiers Cuisines Cv",
    "wof:placetype":"venue"
},
  "geometry": {"coordinates":[5.4553351402,50.7927131653],"type":"Point"}
}