{
  "type": "Feature",
  "properties": {
    "addr:full":"Markt 20 Herzele Oost-Vlaanderen 9550",
    "addr:housenumber":"20",
    "addr:postcode":"9550",
    "addr:street":"Markt;Oost-Vlaanderen",
    "iso:country":"BE",
    "sg:address":"Markt 20",
    "sg:city":"Herzele",
    "sg:orig_category":"Overheidsdiensten",
    "sg:phone":"+32 53 60 70 70",
    "sg:postcode":"9550",
    "sg:province":"Oost-Vlaanderen",
    "wof:name":"Gemeentebestuur",
    "wof:placetype":"venue"
},
  "geometry": {"coordinates":[3.8930180073,50.8846168518],"type":"Point"}
}