{
  "type": "Feature",
  "properties": {
    "addr:full":"Koning Leopold Ii-laan 104 Gent Oost-Vlaanderen 9000",
    "addr:housenumber":"104",
    "addr:postcode":"9000",
    "addr:street":"Koning Leopold Ii-Laan;Oost-Vlaanderen",
    "iso:country":"BE",
    "sg:address":"Koning Leopold Ii-laan 104",
    "sg:city":"Gent",
    "sg:classifiers":[
        {
            "category":"Real Estate",
            "subcategory":"Architect",
            "type":"Services"
        }
    ],
    "sg:phone":"+32 9 245 03 01",
    "sg:postcode":"9000",
    "sg:province":"Oost-Vlaanderen",
    "wof:name":"Van Hecke-vanbossel",
    "wof:placetype":"venue"
},
  "geometry": {"coordinates":[3.7170040607,51.0378723145],"type":"Point"}
}