{
  "type": "Feature",
  "properties": {
    "addr:full":"Groetbacherweg 83 Lontzen (walhorn) Li\u00e8ge 4711",
    "addr:housenumber":"83",
    "addr:postcode":"4711",
    "addr:street":"Groetbacherweg",
    "iso:country":"BE",
    "sg:address":"Groetbacherweg 83",
    "sg:city":"Lontzen (walhorn)",
    "sg:classifiers":[
        {
            "category":"Shopping",
            "subcategory":"Florist",
            "type":"Retail Goods"
        }
    ],
    "sg:phone":"+32 87 65 70 36",
    "sg:postcode":"4711",
    "sg:province":"Li\u00e8ge",
    "wof:name":"Radermeker A & S\u00f6hne",
    "wof:placetype":"venue"
},
  "geometry": {"coordinates":[6.047369957,50.6752853394],"type":"Point"}
}