{
  "type": "Feature",
  "properties": {
    "addr:full":"Galerie Op\u00c9ra 14 Liege Li\u00e8ge 4000",
    "addr:housenumber":"14",
    "addr:postcode":"4000",
    "iso:country":"BE",
    "sg:address":"Galerie Op\u00c9ra 14",
    "sg:city":"Liege",
    "sg:orig_category":"Bijouteries and horlogeries. R\u00e9parations d'horloges, montres and bijoux. Bijoux Fab. Souvenirs and o",
    "sg:phone":"+32 4 222 45 14",
    "sg:postcode":"4000",
    "sg:province":"Li\u00e8ge",
    "wof:name":"Venizi",
    "wof:placetype":"venue"
},
  "geometry": {"coordinates":[5.57107687,50.6435165405],"type":"Point"}
}