{
  "type": "Feature",
  "properties": {
    "addr:full":"Oude Baan 94 Affligem Vlaams-Brabant 1790",
    "addr:housenumber":"94",
    "addr:postcode":"1790",
    "addr:street":"Oude Baan",
    "iso:country":"BE",
    "sg:address":"Oude Baan 94",
    "sg:city":"Affligem",
    "sg:orig_category":"Maatschappelijke dienstverlening",
    "sg:postcode":"1790",
    "sg:province":"Vlaams-Brabant",
    "wof:name":"Rode Kruis Affligem",
    "wof:placetype":"venue"
},
  "geometry": {"coordinates":[4.1159992218,50.9109916687],"type":"Point"}
}