{
  "type": "Feature",
  "properties": {
    "iso:country":"BE",
    "sg:address":"Rue De La Station 48",
    "sg:city":"Sambreville",
    "sg:orig_category":"Non-foodwinkels",
    "sg:phone":"+32 71 77 28 66",
    "sg:postcode":"5060",
    "sg:province":"Namur",
    "wof:name":"Articom",
    "wof:placetype":"venue"
},
  "geometry": {"coordinates":[4.6115899086,50.431640625],"type":"Point"}
}