{
  "type": "Feature",
  "properties": {
    "addr:full":"Molenweg 140 Willebroek Antwerpen 2830",
    "addr:housenumber":"140",
    "addr:postcode":"2830",
    "addr:street":"Molenweg",
    "iso:country":"BE",
    "sg:address":"Molenweg 140",
    "sg:city":"Willebroek",
    "sg:classifiers":[
        {
            "category":"Transit Center",
            "subcategory":"Freight",
            "type":"Transportation"
        }
    ],
    "sg:phone":"+32 3 866 35 63",
    "sg:postcode":"2830",
    "sg:province":"Antwerpen",
    "sg:tags":[
        "glue"
    ],
    "wof:name":"Verlijmingen Reyniers",
    "wof:placetype":"venue"
},
  "geometry": {"coordinates":[4.3638620377,51.0484695435],"type":"Point"}
}