{
  "type": "Feature",
  "properties": {
    "addr:full":"Rozenkranslaan 133 Genk Limburg 3600",
    "addr:housenumber":"133",
    "addr:postcode":"3600",
    "addr:street":"Rozenkranslaan",
    "iso:country":"BE",
    "sg:address":"Rozenkranslaan 133",
    "sg:city":"Genk",
    "sg:orig_category":"Epiceries",
    "sg:phone":"+32 89 35 66 63",
    "sg:postcode":"3600",
    "sg:province":"Limburg",
    "wof:name":"Discount Termien",
    "wof:placetype":"venue"
},
  "geometry": {"coordinates":[5.4841971397,50.9568138123],"type":"Point"}
}