{
  "type": "Feature",
  "properties": {
    "addr:full":"Boulevard Clovis 85 Brussel/bruxelles Bruxelles-Capitale 1000",
    "addr:housenumber":"85",
    "addr:postcode":"1000",
    "addr:street":"Boulevard Clovis;/",
    "iso:country":"BE",
    "sg:address":"Boulevard Clovis 85",
    "sg:city":"Brussel/bruxelles",
    "sg:orig_category":"Agences de publicit\u00e9",
    "sg:phone":"+32 2 282 49 70",
    "sg:postcode":"1000",
    "sg:province":"Bruxelles-Capitale",
    "wof:name":"Bureau B.d.d.p.",
    "wof:placetype":"venue"
},
  "geometry": {"coordinates":[4.3807711601,50.8500442505],"type":"Point"}
}