{
  "type": "Feature",
  "properties": {
    "iso:country":"BE",
    "sg:address":"Spanjestraat 55",
    "sg:city":"Roeselare",
    "sg:classifiers":[
        {
            "category":"Professional",
            "subcategory":"Engineering",
            "type":"Services"
        }
    ],
    "sg:phone":"+32 51 20 43 43",
    "sg:postcode":"8800",
    "sg:province":"West-Vlaanderen",
    "sg:tags":[
        "workshop"
    ],
    "wof:name":"Damman-croes Nv",
    "wof:placetype":"venue"
},
  "geometry": {"coordinates":[3.1346299648,50.9463996887],"type":"Point"}
}