{
  "type": "Feature",
  "properties": {
    "addr:full":"Rue Jean Stassart 1ba Crisnee Li\u00e8ge 4367",
    "addr:housenumber":"1ba",
    "addr:postcode":"4367",
    "addr:street":"Rue Jean Stassart",
    "iso:country":"BE",
    "sg:address":"Rue Jean Stassart 1ba",
    "sg:city":"Crisnee",
    "sg:classifiers":[
        {
            "category":"Insurance",
            "subcategory":"Insurance Agent",
            "type":"Services"
        }
    ],
    "sg:phone":"+32 19 67 74 80",
    "sg:postcode":"4367",
    "sg:province":"Li\u00e8ge",
    "sg:tags":[
        "verzekeringsmakelaars",
        "expert"
    ],
    "wof:name":"Bureau Dumont & Cie",
    "wof:placetype":"venue"
},
  "geometry": {"coordinates":[5.3920321465,50.7107887268],"type":"Point"}
}