{
  "type": "Feature",
  "properties": {
    "iso:country":"BE",
    "sg:address":"Rue De Botrange 66",
    "sg:city":"Waimes",
    "sg:orig_category":"Woningbouw",
    "sg:phone":"+32 80 44 64 31",
    "sg:postcode":"4950",
    "sg:province":"Li\u00e8ge",
    "wof:name":"Charles Paquay",
    "wof:placetype":"venue"
},
  "geometry": {"coordinates":[6.1145558357,50.4758682251],"type":"Point"}
}