{
  "type": "Feature",
  "properties": {
    "addr:full":"Rue Des Carri\u00c8res 90 Seneffe Hainaut 7181",
    "addr:housenumber":"90",
    "addr:postcode":"7181",
    "addr:street":"Rue Des Carrie\u0300Res",
    "iso:country":"BE",
    "sg:address":"Rue Des Carri\u00c8res 90",
    "sg:city":"Seneffe",
    "sg:orig_category":"Elektrische installaties voor woningen",
    "sg:phone":"+32 67 87 80 46",
    "sg:postcode":"7181",
    "sg:province":"Hainaut",
    "wof:name":"Luc Leclercq",
    "wof:placetype":"venue"
},
  "geometry": {"coordinates":[4.2709851265,50.5611000061],"type":"Point"}
}