{
  "type": "Feature",
  "properties": {
    "addr:full":"Mgr. Cardijnlaan 17 Moorslede West-Vlaanderen 8890",
    "addr:housenumber":"17",
    "addr:postcode":"8890",
    "addr:street":"Mgr. Cardijnlaan",
    "iso:country":"BE",
    "sg:address":"Mgr. Cardijnlaan 17",
    "sg:city":"Moorslede",
    "sg:orig_category":"Artsen and specialisten",
    "sg:phone":"+32 56 50 23 35",
    "sg:postcode":"8890",
    "sg:province":"West-Vlaanderen",
    "wof:name":"C. Nuyttens",
    "wof:placetype":"venue"
},
  "geometry": {"coordinates":[3.0637769699,50.891456604],"type":"Point"}
}