{
  "type": "Feature",
  "properties": {
    "iso:country":"BE",
    "sg:address":"Rue Godfroid Kurth 87",
    "sg:city":"Bruxelles (evere)",
    "sg:classifiers":[
        {
            "category":"Shopping",
            "subcategory":"Books",
            "type":"Retail Goods"
        }
    ],
    "sg:phone":"+32 2 216 56 31",
    "sg:postcode":"1140",
    "sg:province":"Bruxelles-Capitale",
    "sg:tags":[
        "bookseller"
    ],
    "wof:name":"Avenir (librairie De L')",
    "wof:placetype":"venue"
},
  "geometry": {"coordinates":[4.3997797966,50.8686828613],"type":"Point"}
}