{
  "type": "Feature",
  "properties": {
    "addr:full":"Rue Pierre Timmermans 63 Jette Bruxelles-Capitale 1090",
    "addr:housenumber":"63",
    "addr:postcode":"1090",
    "addr:street":"Rue Pierre Timmermans",
    "iso:country":"BE",
    "sg:address":"Rue Pierre Timmermans 63",
    "sg:city":"Jette",
    "sg:classifiers":[
        {
            "category":"Restaurant",
            "type":"Food & Drink"
        }
    ],
    "sg:phone":"+32 2 426 14 05",
    "sg:postcode":"1090",
    "sg:province":"Bruxelles-Capitale",
    "wof:name":"La Penisola",
    "wof:placetype":"venue"
},
  "geometry": {"coordinates":[4.3233919144,50.8739891052],"type":"Point"}
}