{
  "type": "Feature",
  "properties": {
    "iso:country":"BE",
    "sg:address":"E. Eylenboschstraat 23",
    "sg:city":"Dilbeek",
    "sg:orig_category":"Brood, gebak and snoepgoed",
    "sg:phone":"+32 2 567 05 72",
    "sg:postcode":"1703",
    "sg:province":"Vlaams-Brabant",
    "wof:name":"Schepdaals Taartje",
    "wof:placetype":"venue"
},
  "geometry": {"coordinates":[4.1926670074,50.8350372314],"type":"Point"}
}