{
  "type": "Feature",
  "properties": {
    "iso:country":"BE",
    "sg:address":"Gaverlandstraat 177",
    "sg:city":"Beveren (melsele)",
    "sg:classifiers":[
        {
            "category":"Home & Garden",
            "subcategory":"Carpets & Floor Coverings",
            "type":"Retail Goods"
        }
    ],
    "sg:phone":"+32 3 775 75 85",
    "sg:postcode":"9120",
    "sg:province":"Oost-Vlaanderen",
    "sg:tags":[
        "tile"
    ],
    "wof:name":"Van Moer Jerome",
    "wof:placetype":"venue"
},
  "geometry": {"coordinates":[4.2644720078,51.2279968262],"type":"Point"}
}