{
  "type": "Feature",
  "properties": {
    "addr:full":"Turnhoutsebaan 29 Antwerpen Antwerpen 2140",
    "addr:housenumber":"29",
    "addr:postcode":"2140",
    "addr:street":"Turnhoutsebaan",
    "iso:country":"BE",
    "sg:address":"Turnhoutsebaan 29",
    "sg:city":"Antwerpen",
    "sg:orig_category":"Meubles D\u00e9taillants, Am\u00e9nagement de B\u00e2timents et de Cuisines",
    "sg:phone":"+32 3 236 38 83",
    "sg:postcode":"2140",
    "sg:province":"Antwerpen",
    "wof:name":"Droomland",
    "wof:placetype":"venue"
},
  "geometry": {"coordinates":[4.4332199097,51.2137565613],"type":"Point"}
}