{
  "type": "Feature",
  "properties": {
    "addr:full":"Kerkstraat 7 Roosdaal (borchtlombeek) Vlaams-Brabant 1761",
    "addr:housenumber":"7",
    "addr:postcode":"1761",
    "addr:street":"Kerkstraat",
    "iso:country":"BE",
    "sg:address":"Kerkstraat 7",
    "sg:city":"Roosdaal (borchtlombeek)",
    "sg:classifiers":[
        {
            "category":"Professional",
            "subcategory":"Art Services",
            "type":"Services"
        }
    ],
    "sg:phone":"+32 2 582 68 39",
    "sg:postcode":"1761",
    "sg:province":"Vlaams-Brabant",
    "sg:tags":[
        "graphic",
        "designer"
    ],
    "wof:name":"Special Day",
    "wof:placetype":"venue"
},
  "geometry": {"coordinates":[4.136548996,50.848526001],"type":"Point"}
}