{
  "type": "Feature",
  "properties": {
    "iso:country":"BE",
    "sg:address":"Middelweg 101",
    "sg:city":"Bruxelles",
    "sg:classifiers":[
        {
            "category":"Professional",
            "subcategory":"Detective & Security Services",
            "type":"Services"
        }
    ],
    "sg:phone":"+32 2 245 40 84",
    "sg:postcode":"1130",
    "sg:province":"Bruxelles-Capitale",
    "sg:tags":[
        "guard"
    ],
    "wof:name":"Protector",
    "wof:placetype":"venue"
},
  "geometry": {"coordinates":[4.4226989746,50.8870201111],"type":"Point"}
}