{
  "type": "Feature",
  "properties": {
    "addr:full":"Vredesteinlaan 16 Bonheiden Antwerpen 2820",
    "addr:housenumber":"16",
    "addr:postcode":"2820",
    "addr:street":"Vredesteinlaan",
    "iso:country":"BE",
    "sg:address":"Vredesteinlaan 16",
    "sg:city":"Bonheiden",
    "sg:orig_category":"Bloemen and planten",
    "sg:phone":"+32 15 55 10 82",
    "sg:postcode":"2820",
    "sg:province":"Antwerpen",
    "wof:name":"Herman Hellemans",
    "wof:placetype":"venue"
},
  "geometry": {"coordinates":[4.5387392044,51.0371513367],"type":"Point"}
}