{
  "type": "Feature",
  "properties": {
    "addr:full":"Leenweg 1 Deinze Oost-Vlaanderen 9800",
    "addr:housenumber":"1",
    "addr:postcode":"9800",
    "addr:street":"Leenweg",
    "iso:country":"BE",
    "sg:address":"Leenweg 1",
    "sg:city":"Deinze",
    "sg:orig_category":"Plomberie, chauffage and installations sanitaires",
    "sg:phone":"+32 9 386 04 85",
    "sg:postcode":"9800",
    "sg:province":"Oost-Vlaanderen",
    "wof:name":"Nevejans",
    "wof:placetype":"venue"
},
  "geometry": {"coordinates":[3.5714728832,50.9781837463],"type":"Point"}
}