{
  "type": "Feature",
  "properties": {
    "addr:full":"Heilig Sacramentstraat 13 Wingene West-Vlaanderen 8750",
    "addr:housenumber":"13",
    "addr:postcode":"8750",
    "addr:street":"Heilig Sacramentstraat",
    "iso:country":"BE",
    "sg:address":"Heilig Sacramentstraat 13",
    "sg:city":"Wingene",
    "sg:orig_category":"Plaatsen van vloer- and muurbekleding Schilders",
    "sg:phone":"+32 51 65 55 32",
    "sg:postcode":"8750",
    "sg:province":"West-Vlaanderen",
    "wof:name":"Eric Lambrecht",
    "wof:placetype":"venue"
},
  "geometry": {"coordinates":[3.2838969231,51.0589065552],"type":"Point"}
}