{
  "type": "Feature",
  "properties": {
    "addr:full":"Rue Entre Deux Portes 75 Huy Li\u00e8ge 4500",
    "addr:housenumber":"75",
    "addr:postcode":"4500",
    "addr:street":"Rue Entre Deux Portes",
    "iso:country":"BE",
    "sg:address":"Rue Entre Deux Portes 75",
    "sg:city":"Huy",
    "sg:classifiers":[
        {
            "category":"Education",
            "subcategory":"School",
            "type":"Public Place"
        }
    ],
    "sg:phone":"+32 85 21 14 49",
    "sg:postcode":"4500",
    "sg:province":"Li\u00e8ge",
    "sg:tags":[
        "secondary"
    ],
    "wof:name":"Coll\u00e8ge St-quirin",
    "wof:placetype":"venue"
},
  "geometry": {"coordinates":[5.2306399345,50.524974823],"type":"Point"}
}