{
  "type": "Feature",
  "properties": {
    "addr:full":"Chauss\u00c9e De Li\u00c8ge 173 Grace-hollogne Li\u00e8ge 4460",
    "addr:housenumber":"173",
    "addr:postcode":"4460",
    "addr:street":"Chausse\u0301E De Lie\u0300Ge",
    "iso:country":"BE",
    "sg:address":"Chauss\u00c9e De Li\u00c8ge 173",
    "sg:city":"Grace-hollogne",
    "sg:orig_category":"Diverse bouwafwerking and reiniging Gespecialiseerde residenti\u00eble bouw Pleisterwerk Woningbouw",
    "sg:phone":"+32 4 263 21 20",
    "sg:postcode":"4460",
    "sg:province":"Li\u00e8ge",
    "wof:name":"Charles Meurisse",
    "wof:placetype":"venue"
},
  "geometry": {"coordinates":[5.4810380936,50.6484413147],"type":"Point"}
}