{
  "type": "Feature",
  "properties": {
    "iso:country":"BE",
    "sg:address":"Holstraat",
    "sg:city":"Waregem",
    "sg:classifiers":[
        {
            "category":"Arena",
            "subcategory":"Horse Racetrack",
            "type":"Entertainment"
        }
    ],
    "sg:phone":"+32 56 60 31 14",
    "sg:postcode":"8790",
    "sg:province":"West-Vlaanderen",
    "sg:tags":[
        "hippodrome"
    ],
    "wof:name":"Renbaan Van Waregem",
    "wof:placetype":"venue"
},
  "geometry": {"coordinates":[3.4338729382,50.8859672546],"type":"Point"}
}