{
  "type": "Feature",
  "properties": {
    "addr:full":"Rue Bollinckx 15 Bruxelles Bruxelles-Capitale 1070",
    "addr:housenumber":"15",
    "addr:postcode":"1070",
    "addr:street":"Rue Bollinckx",
    "iso:country":"BE",
    "sg:address":"Rue Bollinckx 15",
    "sg:city":"Bruxelles",
    "sg:classifiers":[
        {
            "category":"Shopping",
            "subcategory":"Bicycles & Sporting Goods",
            "type":"Retail Goods"
        }
    ],
    "sg:phone":"+32 2 522 51 20",
    "sg:postcode":"1070",
    "sg:province":"Bruxelles-Capitale",
    "wof:name":"Selcom Nv",
    "wof:placetype":"venue"
},
  "geometry": {"coordinates":[4.3051171303,50.820766449],"type":"Point"}
}