{
  "type": "Feature",
  "properties": {
    "addr:full":"Zeedijk-het Zoute 736 Knokke-heist West-Vlaanderen 8300",
    "addr:housenumber":"736",
    "addr:postcode":"8300",
    "addr:street":"Zoute",
    "iso:country":"BE",
    "sg:address":"Zeedijk-het Zoute 736",
    "sg:city":"Knokke-heist",
    "sg:orig_category":"Salles de spectacles",
    "sg:phone":"+32 50 60 71 27",
    "sg:postcode":"8300",
    "sg:province":"West-Vlaanderen",
    "wof:name":"Artes Art Gallery",
    "wof:placetype":"venue"
},
  "geometry": {"coordinates":[3.3267199993,51.3504714966],"type":"Point"}
}