{
  "type": "Feature",
  "properties": {
    "iso:country":"BE",
    "sg:address":"Kortestraat 7",
    "sg:city":"Lanaken",
    "sg:classifiers":[
        {
            "category":"Shopping",
            "subcategory":"Musical Instruments",
            "type":"Retail Goods"
        }
    ],
    "sg:phone":"+32 89 73 12 61",
    "sg:postcode":"3620",
    "sg:province":"Limburg",
    "sg:tags":[
        "piano",
        "-",
        "tuning"
    ],
    "wof:name":"Van Damme P",
    "wof:placetype":"venue"
},
  "geometry": {"coordinates":[5.6513738632,50.8915634155],"type":"Point"}
}