{
  "type": "Feature",
  "properties": {
    "iso:country":"BE",
    "sg:address":"C\u00e9r\u00e8sstraat 7",
    "sg:city":"Antwerpen (borgerhout)",
    "sg:classifiers":[
        {
            "category":"Arts & Performance",
            "subcategory":"Music",
            "type":"Entertainment"
        }
    ],
    "sg:phone":"+32 3 236 97 62",
    "sg:postcode":"2140",
    "sg:province":"Antwerpen",
    "sg:tags":[
        "freelance",
        "musician"
    ],
    "wof:name":"Claeys S",
    "wof:placetype":"venue"
},
  "geometry": {"coordinates":[4.4332199097,51.2137565613],"type":"Point"}
}