{
  "type": "Feature",
  "properties": {
    "addr:full":"Belegstraat 6 Antwerpen Antwerpen 2018",
    "addr:housenumber":"6",
    "addr:postcode":"2018",
    "addr:street":"Belegstraat",
    "iso:country":"BE",
    "sg:address":"Belegstraat 6",
    "sg:city":"Antwerpen",
    "sg:orig_category":"Boucheries",
    "sg:phone":"+32 3 237 73 22",
    "sg:postcode":"2018",
    "sg:province":"Antwerpen",
    "wof:name":"Jean Migom",
    "wof:placetype":"venue"
},
  "geometry": {"coordinates":[4.393737793,51.205619812],"type":"Point"}
}