{
  "type": "Feature",
  "properties": {
    "addr:full":"Kleine Hoogveld 1 Vilvoorde Vlaams-Brabant 1800",
    "addr:housenumber":"1",
    "addr:postcode":"1800",
    "addr:street":"Kleine Hoogveld",
    "iso:country":"BE",
    "sg:address":"Kleine Hoogveld 1",
    "sg:city":"Vilvoorde",
    "sg:orig_category":"Beheer van afvalopslag- and stortplaatsen",
    "sg:phone":"+32 2 267 55 18",
    "sg:postcode":"1800",
    "sg:province":"Vlaams-Brabant",
    "wof:name":"Containerpark Koningslo",
    "wof:placetype":"venue"
},
  "geometry": {"coordinates":[4.3972401619,50.9163894653],"type":"Point"}
}