{
  "type": "Feature",
  "properties": {
    "iso:country":"BE",
    "sg:address":"Dorpsstraat 5",
    "sg:city":"Wuustwezel",
    "sg:orig_category":"Enseignement maternel and primaire",
    "sg:phone":"+32 3 669 62 87",
    "sg:postcode":"2990",
    "sg:province":"Antwerpen",
    "wof:name":"Gemeentel. Lagere School",
    "wof:placetype":"venue"
},
  "geometry": {"coordinates":[4.5913529396,51.3891906738],"type":"Point"}
}