{
  "type": "Feature",
  "properties": {
    "addr:full":"Den Bremt 60 Herent Vlaams-Brabant 3020",
    "addr:housenumber":"60",
    "addr:postcode":"3020",
    "addr:street":"Den Bremt",
    "iso:country":"BE",
    "sg:address":"Den Bremt 60",
    "sg:city":"Herent",
    "sg:classifiers":[
        {
            "category":"Insurance",
            "subcategory":"Insurance Agent",
            "type":"Services"
        }
    ],
    "sg:phone":"+32 16 23 97 12",
    "sg:postcode":"3020",
    "sg:province":"Vlaams-Brabant",
    "sg:tags":[
        "verzekeringsmakelaars",
        "expert"
    ],
    "wof:name":"F. Vanden Bosch",
    "wof:placetype":"venue"
},
  "geometry": {"coordinates":[4.6631269455,50.9031829834],"type":"Point"}
}