{
  "type": "Feature",
  "properties": {
    "iso:country":"BE",
    "sg:address":"Avenue Du Sacr\u00e9 Coeur 45",
    "sg:city":"Bruxelles (jette)",
    "sg:classifiers":[
        {
            "category":"Health Services",
            "subcategory":"Dentist",
            "type":"Services"
        }
    ],
    "sg:phone":"+32 2 478 13 26",
    "sg:postcode":"1090",
    "sg:province":"Bruxelles-Capitale",
    "wof:name":"Van Bogaert Thierry",
    "wof:placetype":"venue"
},
  "geometry": {"coordinates":[4.3311319351,50.8833580017],"type":"Point"}
}