{
  "type": "Feature",
  "properties": {
    "iso:country":"BE",
    "sg:address":"Dampoortstraat 5",
    "sg:city":"Gent",
    "sg:classifiers":[
        {
            "category":"Fast Food",
            "type":"Food & Drink"
        }
    ],
    "sg:phone":"+32 9 233 31 31",
    "sg:postcode":"9000",
    "sg:province":"Oost-Vlaanderen",
    "sg:tags":[
        "de",
        "restaurant",
        "organisation",
        "\u00c0",
        "catering",
        "emporter",
        "f\u00cates",
        "restaurants"
    ],
    "wof:name":"Restaurant De Casserolle",
    "wof:placetype":"venue"
},
  "geometry": {"coordinates":[3.7339110374,51.0568199158],"type":"Point"}
}