{
  "type": "Feature",
  "properties": {
    "iso:country":"BE",
    "sg:address":"Place Colignon 27",
    "sg:city":"Schaarbeek/schaerbeek",
    "sg:orig_category":"Artistes ind\u00e9pendants",
    "sg:phone":"+32 2 215 42 08",
    "sg:postcode":"1030",
    "sg:province":"Bruxelles-Capitale",
    "wof:name":"Nelly Dartay",
    "wof:placetype":"venue"
},
  "geometry": {"coordinates":[4.3729200363,50.8676948547],"type":"Point"}
}