{
  "type": "Feature",
  "properties": {
    "iso:country":"BE",
    "sg:address":"Rue De Roubaix 98",
    "sg:city":"Tournai",
    "sg:orig_category":"V\u00e9t\u00e9rinaires",
    "sg:phone":"+32 69 35 23 29",
    "sg:postcode":"7520",
    "sg:province":"Hainaut",
    "wof:name":"Detavernier",
    "wof:placetype":"venue"
},
  "geometry": {"coordinates":[3.2713670731,50.6448554993],"type":"Point"}
}