{
  "type": "Feature",
  "properties": {
    "addr:full":"Bethanienlei 11 Brecht Antwerpen 2960",
    "addr:housenumber":"11",
    "addr:postcode":"2960",
    "addr:street":"Bethanienlei",
    "iso:country":"BE",
    "sg:address":"Bethanienlei 11",
    "sg:city":"Brecht",
    "sg:classifiers":[
        {
            "category":"Shopping",
            "subcategory":"Jewelry",
            "type":"Retail Goods"
        }
    ],
    "sg:phone":"+32 3 385 29 25",
    "sg:postcode":"2960",
    "sg:province":"Antwerpen",
    "sg:tags":[
        "fab",
        "bijou"
    ],
    "wof:name":"Jozef Bergen",
    "wof:placetype":"venue"
},
  "geometry": {"coordinates":[4.5943398476,51.2881355286],"type":"Point"}
}