{
  "type": "Feature",
  "properties": {
    "addr:full":"Karel Van Manderstraat 4 Oostkamp West-Vlaanderen 8020",
    "addr:housenumber":"4",
    "addr:postcode":"8020",
    "addr:street":"Karel Van Manderstraat",
    "iso:country":"BE",
    "sg:address":"Karel Van Manderstraat 4",
    "sg:city":"Oostkamp",
    "sg:orig_category":"Installation \u00e9lectrique r\u00e9sidentielle",
    "sg:phone":"+32 50 82 53 88",
    "sg:postcode":"8020",
    "sg:province":"West-Vlaanderen",
    "wof:name":"Yvan Truyaert",
    "wof:placetype":"venue"
},
  "geometry": {"coordinates":[3.234719038,51.14270401],"type":"Point"}
}