{
  "type": "Feature",
  "properties": {
    "iso:country":"BE",
    "sg:address":"Sassenhout 67",
    "sg:city":"Vorselaar",
    "sg:orig_category":"Afbraak- and draineerwerken",
    "sg:phone":"+32 14 21 87 27",
    "sg:postcode":"2290",
    "sg:province":"Antwerpen",
    "wof:name":"Paepen",
    "wof:placetype":"venue"
},
  "geometry": {"coordinates":[4.7962379456,51.2099876404],"type":"Point"}
}