{
  "type": "Feature",
  "properties": {
    "addr:full":"Museumstraat 26 Aalter (bellem) Oost-Vlaanderen 9881",
    "addr:housenumber":"26",
    "addr:postcode":"9881",
    "addr:street":"Museumstraat",
    "iso:country":"BE",
    "sg:address":"Museumstraat 26",
    "sg:city":"Aalter (bellem)",
    "sg:classifiers":[
        {
            "category":"Building & Trades",
            "subcategory":"Landscaping Services",
            "type":"Services"
        }
    ],
    "sg:phone":"+32 9 325 08 12",
    "sg:postcode":"9881",
    "sg:province":"Oost-Vlaanderen",
    "sg:tags":[
        "gardening",
        "garden",
        "maintenance"
    ],
    "wof:name":"Van Lantschoot D",
    "wof:placetype":"venue"
},
  "geometry": {"coordinates":[3.4910109043,51.0917205811],"type":"Point"}
}