{
  "type": "Feature",
  "properties": {
    "addr:full":"Sint-maternuswal 16 Tongeren Limburg 3700",
    "addr:housenumber":"16",
    "addr:postcode":"3700",
    "addr:street":"Sint-Maternuswal",
    "iso:country":"BE",
    "sg:address":"Sint-maternuswal 16",
    "sg:city":"Tongeren",
    "sg:classifiers":[
        {
            "category":"Social Services",
            "type":"Services"
        }
    ],
    "sg:phone":"+32 12 26 41 12",
    "sg:postcode":"3700",
    "sg:province":"Limburg",
    "wof:name":"Europees Centrum Voor Globale Kankerpreventie En -genezing",
    "wof:placetype":"venue"
},
  "geometry": {"coordinates":[5.4511590004,50.7757759094],"type":"Point"}
}