{
  "type": "Feature",
  "properties": {
    "addr:full":"Boswachterlaan 2 Tremelo Vlaams-Brabant 3120",
    "addr:housenumber":"2",
    "addr:postcode":"3120",
    "addr:street":"Boswachterlaan",
    "iso:country":"BE",
    "sg:address":"Boswachterlaan 2",
    "sg:city":"Tremelo",
    "sg:orig_category":"Dakwerken",
    "sg:phone":"+32 16 53 16 81",
    "sg:postcode":"3120",
    "sg:province":"Vlaams-Brabant",
    "wof:name":"Van Dijck En Co",
    "wof:placetype":"venue"
},
  "geometry": {"coordinates":[4.7310791016,50.9947624207],"type":"Point"}
}