{
  "type": "Feature",
  "properties": {
    "addr:full":"Muizeputweg 8 Ardooie West-Vlaanderen 8850",
    "addr:housenumber":"8",
    "addr:postcode":"8850",
    "addr:street":"Muizeputweg",
    "iso:country":"BE",
    "sg:address":"Muizeputweg 8",
    "sg:city":"Ardooie",
    "sg:classifiers":[
        {
            "category":"Manufacturing",
            "subcategory":"Tools & Machinery",
            "type":"Manufacturing & Wholesale Goods"
        }
    ],
    "sg:phone":"+32 475 51 49 18",
    "sg:postcode":"8850",
    "sg:province":"West-Vlaanderen",
    "sg:tags":[
        "-"
    ],
    "wof:name":"Facto Groep Nv",
    "wof:placetype":"venue"
},
  "geometry": {"coordinates":[3.2067089081,50.964931488],"type":"Point"}
}