{
  "type": "Feature",
  "properties": {
    "addr:full":"Rue Parapet 78 Anhee Namur 5537",
    "addr:housenumber":"78",
    "addr:postcode":"5537",
    "addr:street":"Rue Parapet;Namur",
    "iso:country":"BE",
    "sg:address":"Rue Parapet 78",
    "sg:city":"Anhee",
    "sg:orig_category":"Installation \u00e9lectrique r\u00e9sidentielle",
    "sg:phone":"+32 71 79 82 90",
    "sg:postcode":"5537",
    "sg:province":"Namur",
    "wof:name":"Daniel Jourdan",
    "wof:placetype":"venue"
},
  "geometry": {"coordinates":[4.817399025,50.340587616],"type":"Point"}
}