{
  "type": "Feature",
  "properties": {
    "addr:full":"Venecoweg 23 Nazareth Oost-Vlaanderen 9810",
    "addr:housenumber":"23",
    "addr:postcode":"9810",
    "addr:street":"Venecoweg",
    "iso:country":"BE",
    "sg:address":"Venecoweg 23",
    "sg:city":"Nazareth",
    "sg:classifiers":[
        {
            "category":"Manufacturing",
            "subcategory":"Rubber & Plastics",
            "type":"Manufacturing & Wholesale Goods"
        }
    ],
    "sg:phone":"+32 9 381 09 90",
    "sg:postcode":"9810",
    "sg:province":"Oost-Vlaanderen",
    "sg:tags":[
        "working"
    ],
    "wof:name":"Dakota Coatings Nv",
    "wof:placetype":"venue"
},
  "geometry": {"coordinates":[3.5542340279,50.953338623],"type":"Point"}
}