{
  "type": "Feature",
  "properties": {
    "addr:full":"Avenue G\u00c9n\u00c9ral De Gaulle 49 Elsene/ixelles Bruxelles-Capitale 1050",
    "addr:housenumber":"49",
    "addr:postcode":"1050",
    "addr:street":"Avenue Ge\u0301Ne\u0301Ral De Gaulle",
    "iso:country":"BE",
    "sg:address":"Avenue G\u00c9n\u00c9ral De Gaulle 49",
    "sg:city":"Elsene/ixelles",
    "sg:orig_category":"Databeheer and gegevensverwerking",
    "sg:phone":"+32 2 649 18 37",
    "sg:postcode":"1050",
    "sg:province":"Bruxelles-Capitale",
    "wof:name":"A.c.t.",
    "wof:placetype":"venue"
},
  "geometry": {"coordinates":[4.3730978966,50.8226394653],"type":"Point"}
}