{
  "type": "Feature",
  "properties": {
    "iso:country":"BE",
    "sg:address":"Leistraat 19",
    "sg:city":"Haaltert",
    "sg:classifiers":[
        {
            "category":"Arena",
            "subcategory":"Sports Club",
            "type":"Entertainment"
        }
    ],
    "sg:phone":"+32 53 62 21 26",
    "sg:postcode":"9450",
    "sg:province":"Oost-Vlaanderen",
    "sg:tags":[
        "de"
    ],
    "wof:name":"B.c. Vic Raes",
    "wof:placetype":"venue"
},
  "geometry": {"coordinates":[3.9635229111,50.8754310608],"type":"Point"}
}