{
  "type": "Feature",
  "properties": {
    "addr:full":"Naamsesteenweg 234 Sint-truiden Limburg 3800",
    "addr:housenumber":"234",
    "addr:postcode":"sint-truiden;3800",
    "addr:street":"Naamsesteenweg",
    "iso:country":"BE",
    "sg:address":"Naamsesteenweg 234",
    "sg:city":"Sint-truiden",
    "sg:classifiers":[
        {
            "category":"Health Services",
            "subcategory":"Health Practitioner",
            "type":"Services"
        }
    ],
    "sg:phone":"+32 11 68 02 71",
    "sg:postcode":"3800",
    "sg:province":"Limburg",
    "sg:tags":[
        "physiotherapist"
    ],
    "wof:name":"Kerkhofs M",
    "wof:placetype":"venue"
},
  "geometry": {"coordinates":[5.1850399971,50.812789917],"type":"Point"}
}