{
  "type": "Feature",
  "properties": {
    "iso:country":"BE",
    "sg:address":"Frambozenweg 2",
    "sg:city":"Staden",
    "sg:orig_category":"Installation \u00e9lectrique r\u00e9sidentielle",
    "sg:phone":"+32 51 78 07 89",
    "sg:postcode":"8840",
    "sg:province":"West-Vlaanderen",
    "wof:name":"Geert Eeckhout",
    "wof:placetype":"venue"
},
  "geometry": {"coordinates":[3.0127930641,50.9751815796],"type":"Point"}
}