{
  "type": "Feature",
  "properties": {
    "addr:full":"Rue Du Maitrank 78 Arlon Luxembourg 6700",
    "addr:housenumber":"78",
    "addr:postcode":"6700",
    "addr:street":"Rue Du Maitrank",
    "iso:country":"BE",
    "sg:address":"Rue Du Maitrank 78",
    "sg:city":"Arlon",
    "sg:classifiers":[
        {
            "category":"Taxi",
            "type":"Transportation"
        }
    ],
    "sg:phone":"+32 63 23 27 81",
    "sg:postcode":"6700",
    "sg:province":"Luxembourg",
    "sg:tags":[
        "taxi's"
    ],
    "wof:name":"Traveltaxi",
    "wof:placetype":"venue"
},
  "geometry": {"coordinates":[5.8170199394,49.6958618164],"type":"Point"}
}