{
  "type": "Feature",
  "properties": {
    "iso:country":"BE",
    "sg:address":"Brun Cornet 4",
    "sg:city":"Menen",
    "sg:orig_category":"Sportclubs",
    "sg:phone":"+32 56 41 58 58",
    "sg:postcode":"8930",
    "sg:province":"West-Vlaanderen",
    "wof:name":"V.t. Wevelgem-bissegem",
    "wof:placetype":"venue"
},
  "geometry": {"coordinates":[3.1800479889,50.7745819092],"type":"Point"}
}