{
  "type": "Feature",
  "properties": {
    "addr:full":"Liebaardstraat 274 Beveren-leie West-Vlaanderen 8791",
    "addr:housenumber":"274",
    "addr:postcode":"8791",
    "addr:street":"Liebaardstraat;West-Vlaanderen",
    "iso:country":"BE",
    "sg:address":"Liebaardstraat 274",
    "sg:city":"Beveren-leie",
    "sg:orig_category":"Opticiens",
    "sg:phone":"+32 56 70 26 67",
    "sg:postcode":"8791",
    "sg:province":"West-Vlaanderen",
    "wof:name":"Boury Optiek",
    "wof:placetype":"venue"
},
  "geometry": {"coordinates":[3.3590118885,50.8800125122],"type":"Point"}
}