{
  "type": "Feature",
  "properties": {
    "addr:full":"Stationsstraat 27 Lokeren Oost-Vlaanderen 9160",
    "addr:housenumber":"27",
    "addr:postcode":"9160",
    "addr:street":"Stationsstraat",
    "iso:country":"BE",
    "sg:address":"Stationsstraat 27",
    "sg:city":"Lokeren",
    "sg:classifiers":[
        {
            "category":"Insurance",
            "subcategory":"Life Insurance",
            "type":"Services"
        }
    ],
    "sg:phone":"+32 9 348 24 45",
    "sg:postcode":"9160",
    "sg:province":"Oost-Vlaanderen",
    "sg:tags":[
        "assurance"
    ],
    "wof:name":"Zakenkantoor Wiewauters",
    "wof:placetype":"venue"
},
  "geometry": {"coordinates":[3.9877181053,51.1064376831],"type":"Point"}
}