{
  "type": "Feature",
  "properties": {
    "addr:full":"Ruddervoordestraat 182 Torhout West-Vlaanderen 8820",
    "addr:housenumber":"182",
    "addr:postcode":"8820",
    "addr:street":"Ruddervoordestraat",
    "iso:country":"BE",
    "sg:address":"Ruddervoordestraat 182",
    "sg:city":"Torhout",
    "sg:orig_category":"Rundveehouders Varkenskwekers",
    "sg:phone":"+32 50 21 34 72",
    "sg:postcode":"8820",
    "sg:province":"West-Vlaanderen",
    "wof:name":"Jozef Vansteelant",
    "wof:placetype":"venue"
},
  "geometry": {"coordinates":[3.136674881,51.0616645813],"type":"Point"}
}