{
  "type": "Feature",
  "properties": {
    "addr:full":"Deinzestraat 60 Dentergem West-Vlaanderen 8720",
    "addr:housenumber":"60",
    "addr:postcode":"8720",
    "addr:street":"Deinzestraat",
    "iso:country":"BE",
    "sg:address":"Deinzestraat 60",
    "sg:city":"Dentergem",
    "sg:orig_category":"Entretien and r\u00e9parations de voitures",
    "sg:phone":"+32 9 388 85 04",
    "sg:postcode":"8720",
    "sg:province":"West-Vlaanderen",
    "wof:name":"Carrosserie Vanrijckegem",
    "wof:placetype":"venue"
},
  "geometry": {"coordinates":[3.4354639053,50.9390640259],"type":"Point"}
}