{
  "type": "Feature",
  "properties": {
    "iso:country":"BE",
    "sg:address":"Meensesteenweg 209",
    "sg:city":"Kortrijk",
    "sg:orig_category":"V\u00e9hicules automobiles. Entretien and r\u00e9parations de voitures. Combustibles",
    "sg:phone":"+32 56 35 44 58",
    "sg:postcode":"8501",
    "sg:province":"West-Vlaanderen",
    "wof:name":"Garage Decock",
    "wof:placetype":"venue"
},
  "geometry": {"coordinates":[3.2373969555,50.8257904053],"type":"Point"}
}