{
  "type": "Feature",
  "properties": {
    "addr:full":"Rue Du Chaunois 7 Gesves Namur 5340",
    "addr:housenumber":"7",
    "addr:postcode":"5340",
    "addr:street":"Rue Du Chaunois",
    "iso:country":"BE",
    "sg:address":"Rue Du Chaunois 7",
    "sg:city":"Gesves",
    "sg:orig_category":"Charpentes and couvertures. Plomberie, chauffage and installations sanitaires",
    "sg:phone":"+32 81 57 07 01",
    "sg:postcode":"5340",
    "sg:province":"Namur",
    "wof:name":"Isosanitoit",
    "wof:placetype":"venue"
},
  "geometry": {"coordinates":[5.0180702209,50.425945282],"type":"Point"}
}