{
  "type": "Feature",
  "properties": {
    "addr:full":"Leuvensesteenweg 284b4 Boortmeerbeek Vlaams-Brabant 3190",
    "addr:housenumber":"284b4",
    "addr:postcode":"3190",
    "addr:street":"Leuvensesteenweg",
    "iso:country":"BE",
    "sg:address":"Leuvensesteenweg 284b4",
    "sg:city":"Boortmeerbeek",
    "sg:orig_category":"Agences d'exp\u00e9dition",
    "sg:phone":"+32 15 51 14 20",
    "sg:postcode":"3190",
    "sg:province":"Vlaams-Brabant",
    "wof:name":"Van Dessel S",
    "wof:placetype":"venue"
},
  "geometry": {"coordinates":[4.5687952042,50.9709472656],"type":"Point"}
}