{
  "type": "Feature",
  "properties": {
    "iso:country":"BE",
    "sg:address":"Verboekt 49",
    "sg:city":"Laakdal (forest)",
    "sg:classifiers":[
        {
            "category":"Organizations",
            "subcategory":"Political Organization",
            "type":"Services"
        }
    ],
    "sg:phone":"+32 13 67 55 99",
    "sg:postcode":"2430",
    "sg:province":"Antwerpen",
    "sg:tags":[
        "charitable",
        "organisation"
    ],
    "wof:name":"Hulpverleningsgroep De Schakel Vzw",
    "wof:placetype":"venue"
},
  "geometry": {"coordinates":[5.0833601952,51.0951499939],"type":"Point"}
}