{
  "type": "Feature",
  "properties": {
    "addr:full":"Faubourg De Charleroi 14bb Charleroi Hainaut 6041",
    "addr:housenumber":"14bb",
    "addr:postcode":"6041",
    "addr:street":"Faubourg;Charleroi;Hainaut",
    "iso:country":"BE",
    "sg:address":"Faubourg De Charleroi 14bb",
    "sg:city":"Charleroi",
    "sg:orig_category":"Overheidsdiensten",
    "sg:phone":"+32 71 35 78 94",
    "sg:postcode":"6041",
    "sg:province":"Hainaut",
    "wof:name":"Admin. Contrib. Directes",
    "wof:placetype":"venue"
},
  "geometry": {"coordinates":[4.4314317703,50.4685935974],"type":"Point"}
}