{
  "type": "Feature",
  "properties": {
    "iso:country":"BE",
    "sg:address":"Avenue Arthur-tagnon 1",
    "sg:city":"Paliseul",
    "sg:orig_category":"Algemeen secundair onderwijs Technisch and beroeps secundair onderwijs",
    "sg:phone":"+32 61 53 01 02",
    "sg:postcode":"6850",
    "sg:province":"Luxembourg",
    "wof:name":"Institut St.joseph",
    "wof:placetype":"venue"
},
  "geometry": {"coordinates":[5.1349849701,49.9033889771],"type":"Point"}
}