{
  "type": "Feature",
  "properties": {
    "addr:full":"Rue De Purnode 8 Dinant (lisogne) Namur 5501",
    "addr:housenumber":"8",
    "addr:postcode":"5501",
    "addr:street":"Rue De Purnode",
    "iso:country":"BE",
    "sg:address":"Rue De Purnode 8",
    "sg:city":"Dinant (lisogne)",
    "sg:classifiers":[
        {
            "category":"Building & Trades",
            "subcategory":"Pest Control",
            "type":"Services"
        }
    ],
    "sg:phone":"+32 82 22 50 68",
    "sg:postcode":"5501",
    "sg:province":"Namur",
    "sg:tags":[
        "painting",
        "contractor"
    ],
    "wof:name":"Fondaire D",
    "wof:placetype":"venue"
},
  "geometry": {"coordinates":[4.9467449188,50.300567627],"type":"Point"}
}