{
  "type": "Feature",
  "properties": {
    "iso:country":"BE",
    "sg:address":"Ter Coutere 53",
    "sg:city":"Harelbeke",
    "sg:orig_category":"Paramedische behandelingen",
    "sg:phone":"+32 56 70 55 50",
    "sg:postcode":"8531",
    "sg:province":"West-Vlaanderen",
    "wof:name":"Ch. Derhore",
    "wof:placetype":"venue"
},
  "geometry": {"coordinates":[3.3017270565,50.8644256592],"type":"Point"}
}