{
  "type": "Feature",
  "properties": {
    "addr:full":"Van Eycklei 9 Antwerpen Antwerpen 2018",
    "addr:housenumber":"9",
    "addr:postcode":"2018",
    "addr:street":"Van Eycklei",
    "iso:country":"BE",
    "sg:address":"Van Eycklei 9",
    "sg:city":"Antwerpen",
    "sg:classifiers":[
        {
            "category":"Banks & Credit Unions",
            "subcategory":"Bureau De Change",
            "type":"Services"
        }
    ],
    "sg:phone":"+32 3 225 01 24",
    "sg:postcode":"2018",
    "sg:province":"Antwerpen",
    "sg:tags":[
        "foundation",
        "bored",
        "pile"
    ],
    "wof:name":"Fondedile Belgium Nv",
    "wof:placetype":"venue"
},
  "geometry": {"coordinates":[4.4121260643,51.2106170654],"type":"Point"}
}