{
  "type": "Feature",
  "properties": {
    "addr:full":"Klerkenstraat 170bb Langemark-poelkapelle West-Vlaanderen 8920",
    "addr:housenumber":"170bb",
    "addr:postcode":"8920",
    "addr:street":"Klerkenstraat",
    "iso:country":"BE",
    "sg:address":"Klerkenstraat 170bb",
    "sg:city":"Langemark-poelkapelle",
    "sg:orig_category":"Banques and organismes de cr\u00e9dit",
    "sg:phone":"+32 57 48 90 92",
    "sg:postcode":"8920",
    "sg:province":"West-Vlaanderen",
    "wof:name":"Centea",
    "wof:placetype":"venue"
},
  "geometry": {"coordinates":[2.934910059,50.9388313293],"type":"Point"}
}