{
  "type": "Feature",
  "properties": {
    "iso:country":"BE",
    "sg:address":"Sijselestraat 106",
    "sg:city":"Beernem",
    "sg:orig_category":"Eleveurs de bovins",
    "sg:phone":"+32 50 78 91 68",
    "sg:postcode":"8730",
    "sg:province":"West-Vlaanderen",
    "wof:name":"Luc Cloet",
    "wof:placetype":"venue"
},
  "geometry": {"coordinates":[3.3329229355,51.1838417053],"type":"Point"}
}