{
  "type": "Feature",
  "properties": {
    "iso:country":"BE",
    "sg:address":"Rue De La Grenouillette 2a",
    "sg:city":"Bruxelles",
    "sg:classifiers":[
        {
            "category":"Manufacturing",
            "subcategory":"Tools & Machinery",
            "type":"Manufacturing & Wholesale Goods"
        }
    ],
    "sg:phone":"+32 2 216 02 16",
    "sg:postcode":"1130",
    "sg:province":"Bruxelles-Capitale",
    "sg:tags":[
        "abrasive"
    ],
    "wof:name":"Pferd-r\u00fcggeberg S.p.r.l.",
    "wof:placetype":"venue"
},
  "geometry": {"coordinates":[4.4172420502,50.8834724426],"type":"Point"}
}