{
  "type": "Feature",
  "properties": {
    "iso:country":"BE",
    "sg:address":"De Zwaan 28",
    "sg:city":"Brasschaat",
    "sg:orig_category":"Non-Classified Establishments",
    "sg:phone":"+32 3 651 88 85",
    "sg:postcode":"2930",
    "sg:province":"Antwerpen",
    "wof:name":"Clb Voor- En Noorderkempen",
    "wof:placetype":"venue"
},
  "geometry": {"coordinates":[4.4926347733,51.2910995483],"type":"Point"}
}