{
  "type": "Feature",
  "properties": {
    "iso:country":"BE",
    "sg:address":"501",
    "sg:city":"Boomsesteenweg 2610 Wilrijk",
    "sg:classifiers":[
        {
            "category":"Professional",
            "subcategory":"Engineering",
            "type":"Services"
        }
    ],
    "sg:phone":"+32 3 830 30 80",
    "sg:postcode":"501",
    "sg:tags":[
        "machine",
        "-",
        "mechanical"
    ],
    "wof:name":"Markant Nv",
    "wof:placetype":"venue"
},
  "geometry": {"coordinates":[4.3816552162,51.1495361328],"type":"Point"}
}