{
  "type": "Feature",
  "properties": {
    "addr:full":"Lippenslaan 69 Knokke-heist West-Vlaanderen 8300",
    "addr:housenumber":"69",
    "addr:postcode":"8300",
    "addr:street":"Lippenslaan",
    "iso:country":"BE",
    "sg:address":"Lippenslaan 69",
    "sg:city":"Knokke-heist",
    "sg:orig_category":"Bloemen and planten",
    "sg:phone":"+32 50 60 72 65",
    "sg:postcode":"8300",
    "sg:province":"West-Vlaanderen",
    "wof:name":"Bloemen Crea",
    "wof:placetype":"venue"
},
  "geometry": {"coordinates":[3.2877368927,51.3435440063],"type":"Point"}
}