{
  "type": "Feature",
  "properties": {
    "addr:full":"Rue De Bastogne 469 Arlon Luxembourg 6700",
    "addr:housenumber":"469",
    "addr:postcode":"6700",
    "addr:street":"Rue De Bastogne",
    "iso:country":"BE",
    "sg:address":"Rue De Bastogne 469",
    "sg:city":"Arlon",
    "sg:classifiers":[
        {
            "category":"Retail",
            "subcategory":"Auto Repair",
            "type":"Services"
        }
    ],
    "sg:phone":"+32 63 23 03 03",
    "sg:postcode":"6700",
    "sg:province":"Luxembourg",
    "sg:tags":[
        "garage"
    ],
    "wof:name":"Schaus (garage)",
    "wof:placetype":"venue"
},
  "geometry": {"coordinates":[5.8098897934,49.695350647],"type":"Point"}
}