{
  "type": "Feature",
  "properties": {
    "iso:country":"BE",
    "sg:address":"Zegestraat 18b3",
    "sg:city":"Tienen",
    "sg:orig_category":"Agences de mannequins and h\u00f4tesses",
    "sg:phone":"+32 495 47 07 15",
    "sg:postcode":"3300",
    "sg:province":"Vlaams-Brabant",
    "wof:name":"Kina's Int. Models Agency",
    "wof:placetype":"venue"
},
  "geometry": {"coordinates":[4.9359211922,50.8121566772],"type":"Point"}
}