{
  "type": "Feature",
  "properties": {
    "iso:country":"BE",
    "sg:address":"Europaplein 12",
    "sg:city":"Maasmechelen",
    "sg:orig_category":"S\u00e9curit\u00e9 sociale. Secr\u00e9tariats sociaux",
    "sg:phone":"+32 89 76 03 84",
    "sg:postcode":"3630",
    "sg:province":"Limburg",
    "wof:name":"Partena",
    "wof:placetype":"venue"
},
  "geometry": {"coordinates":[5.6961350441,50.963848114],"type":"Point"}
}