{
  "type": "Feature",
  "properties": {
    "addr:full":"Klein Eind 28 Hamont-achel Limburg 3930",
    "addr:housenumber":"28",
    "addr:postcode":"3930",
    "addr:street":"Klein Eind",
    "iso:country":"BE",
    "sg:address":"Klein Eind 28",
    "sg:city":"Hamont-achel",
    "sg:classifiers":[
        {
            "category":"Food & Beverages",
            "subcategory":"Fruits & Vegetables",
            "type":"Retail Goods"
        }
    ],
    "sg:phone":"+32 11 64 90 72",
    "sg:postcode":"3930",
    "sg:province":"Limburg",
    "sg:tags":[
        "l\u00e9gumes"
    ],
    "wof:name":"Vercammen H. & M.",
    "wof:placetype":"venue"
},
  "geometry": {"coordinates":[5.4734420776,51.2663726807],"type":"Point"}
}