{
  "type": "Feature",
  "properties": {
    "iso:country":"BE",
    "sg:address":"Hazelereik 36",
    "sg:city":"Tongeren",
    "sg:classifiers":[
        {
            "category":"Home & Garden",
            "subcategory":"Household Appliances",
            "type":"Retail Goods"
        }
    ],
    "sg:phone":"+32 12 23 95 50",
    "sg:postcode":"3700",
    "sg:province":"Limburg",
    "sg:tags":[
        "repair",
        "mainten",
        "-",
        "electric"
    ],
    "wof:name":"Electro Deliever J",
    "wof:placetype":"venue"
},
  "geometry": {"coordinates":[5.4826331139,50.7873382568],"type":"Point"}
}