{
  "type": "Feature",
  "properties": {
    "addr:full":"Rue Du Horloz 26 Saint-nicolas Li\u00e8ge 4420",
    "addr:housenumber":"26",
    "addr:postcode":"4420",
    "addr:street":"Rue Du Horloz",
    "iso:country":"BE",
    "sg:address":"Rue Du Horloz 26",
    "sg:city":"Saint-nicolas",
    "sg:classifiers":[
        {
            "category":"Building & Trades",
            "subcategory":"Construction",
            "type":"Services"
        }
    ],
    "sg:phone":"+32 497 70 46 40",
    "sg:postcode":"4420",
    "sg:province":"Li\u00e8ge",
    "sg:tags":[
        "installation",
        "-",
        "central",
        "heating"
    ],
    "wof:name":"Brijjak Entreprise",
    "wof:placetype":"venue"
},
  "geometry": {"coordinates":[5.5313339233,50.629447937],"type":"Point"}
}