{
  "type": "Feature",
  "properties": {
    "addr:full":"Riet 66 Stekene Oost-Vlaanderen 9190",
    "addr:housenumber":"66",
    "addr:postcode":"9190",
    "addr:street":"Riet",
    "iso:country":"BE",
    "sg:address":"Riet 66",
    "sg:city":"Stekene",
    "sg:orig_category":"Peinture. Rev\u00eatements pour sols and murs",
    "sg:phone":"+32 3 789 07 62",
    "sg:postcode":"9190",
    "sg:province":"Oost-Vlaanderen",
    "wof:name":"De Saeger",
    "wof:placetype":"venue"
},
  "geometry": {"coordinates":[3.9980928898,51.2364273071],"type":"Point"}
}