{
  "type": "Feature",
  "properties": {
    "iso:country":"BE",
    "sg:address":"Rue Vlle Voie De Li\u00c8ge 20b1",
    "sg:city":"Sprimont",
    "sg:orig_category":"Landmeters",
    "sg:phone":"+32 4 382 18 08",
    "sg:postcode":"4140",
    "sg:province":"Li\u00e8ge",
    "wof:name":"Patrick Leduc",
    "wof:placetype":"venue"
},
  "geometry": {"coordinates":[5.6590099335,50.5073661804],"type":"Point"}
}