{
  "type": "Feature",
  "properties": {
    "iso:country":"BE",
    "sg:address":"Gen. De Krahestraat 112",
    "sg:city":"Leopoldsburg",
    "sg:orig_category":"Bloemen and planten Gh",
    "sg:phone":"+32 11 34 49 30",
    "sg:postcode":"3970",
    "sg:province":"Limburg",
    "wof:name":"Cash & Carry",
    "wof:placetype":"venue"
},
  "geometry": {"coordinates":[5.2594308853,51.1230773926],"type":"Point"}
}