{
  "type": "Feature",
  "properties": {
    "iso:country":"BE",
    "sg:address":"Chemin Des Fontaines 12a",
    "sg:city":"Soignies (casteau)",
    "sg:classifiers":[
        {
            "category":"Professional",
            "type":"Services"
        }
    ],
    "sg:phone":"+32 65 72 88 17",
    "sg:postcode":"7061",
    "sg:province":"Hainaut",
    "sg:tags":[
        "surveyor",
        "-",
        "valuer"
    ],
    "wof:name":"Massin-meremans",
    "wof:placetype":"venue"
},
  "geometry": {"coordinates":[4.0117030144,50.5142326355],"type":"Point"}
}