{
  "type": "Feature",
  "properties": {
    "addr:full":"Vliegplein 12 Maldegem (adegem) Oost-Vlaanderen 9991",
    "addr:housenumber":"12",
    "addr:postcode":"9991",
    "addr:street":"Vliegplein",
    "iso:country":"BE",
    "sg:address":"Vliegplein 12",
    "sg:city":"Maldegem (adegem)",
    "sg:classifiers":[
        {
            "category":"Airport",
            "subcategory":"International",
            "type":"Transportation"
        }
    ],
    "sg:phone":"+32 50 71 30 06",
    "sg:postcode":"9991",
    "sg:province":"Oost-Vlaanderen",
    "sg:tags":[
        "-",
        "transport"
    ],
    "wof:name":"Transhumal",
    "wof:placetype":"venue"
},
  "geometry": {"coordinates":[3.4779388905,51.1958274841],"type":"Point"}
}