{
  "type": "Feature",
  "properties": {
    "iso:country":"BE",
    "sg:address":"Heirweg Zuid 68ba",
    "sg:city":"Ingelmunster",
    "sg:orig_category":"Producteurs de l\u00e9gumes",
    "sg:phone":"+32 51 31 63 79",
    "sg:postcode":"8770",
    "sg:province":"West-Vlaanderen",
    "wof:name":"Maes-bruggeman",
    "wof:placetype":"venue"
},
  "geometry": {"coordinates":[3.2578439713,50.8988265991],"type":"Point"}
}