{
  "type": "Feature",
  "properties": {
    "addr:full":"Gentstraat 245 Ingelmunster West-Vlaanderen 8770",
    "addr:housenumber":"245",
    "addr:postcode":"8770",
    "addr:street":"Gentstraat",
    "iso:country":"BE",
    "sg:address":"Gentstraat 245",
    "sg:city":"Ingelmunster",
    "sg:orig_category":"Eleveurs and marchands de porcs",
    "sg:phone":"+32 56 66 62 17",
    "sg:postcode":"8770",
    "sg:province":"West-Vlaanderen",
    "wof:name":"Paul Bruneel",
    "wof:placetype":"venue"
},
  "geometry": {"coordinates":[3.2841699123,50.9116744995],"type":"Point"}
}