{
  "type": "Feature",
  "properties": {
    "addr:full":"Oudenaardestraat 36b2 Anzegem West-Vlaanderen 8570",
    "addr:housenumber":"36b2",
    "addr:postcode":"8570",
    "addr:street":"Oudenaardestraat",
    "iso:country":"BE",
    "sg:address":"Oudenaardestraat 36b2",
    "sg:city":"Anzegem",
    "sg:orig_category":"Bloemen and planten",
    "sg:phone":"+32 56 77 23 83",
    "sg:postcode":"8570",
    "sg:province":"West-Vlaanderen",
    "wof:name":"Pioen",
    "wof:placetype":"venue"
},
  "geometry": {"coordinates":[3.406719923,50.8387374878],"type":"Point"}
}