{
  "type": "Feature",
  "properties": {
    "iso:country":"BE",
    "sg:address":"Oude Geelsebaan 25",
    "sg:city":"Laakdal (veerle)",
    "sg:classifiers":[
        {
            "category":"Shopping",
            "subcategory":"Bicycles & Sporting Goods",
            "type":"Retail Goods"
        }
    ],
    "sg:phone":"+32 14 84 19 24",
    "sg:postcode":"2431",
    "sg:province":"Antwerpen",
    "sg:tags":[
        "-"
    ],
    "wof:name":"Dams K",
    "wof:placetype":"venue"
},
  "geometry": {"coordinates":[4.9774179459,51.0674324036],"type":"Point"}
}