{
  "type": "Feature",
  "properties": {
    "addr:full":"Broesveldstraat 57 Neerpelt Limburg 3910",
    "addr:housenumber":"57",
    "addr:postcode":"3910",
    "addr:street":"Broesveldstraat",
    "iso:country":"BE",
    "sg:address":"Broesveldstraat 57",
    "sg:city":"Neerpelt",
    "sg:classifiers":[
        {
            "category":"Insurance",
            "subcategory":"Insurance Agent",
            "type":"Services"
        }
    ],
    "sg:phone":"+32 11 64 46 13",
    "sg:postcode":"3910",
    "sg:province":"Limburg",
    "sg:tags":[
        "broker"
    ],
    "wof:name":"Plessers K",
    "wof:placetype":"venue"
},
  "geometry": {"coordinates":[5.428290844,51.2317619324],"type":"Point"}
}