{
  "type": "Feature",
  "properties": {
    "iso:country":"BE",
    "sg:address":"Kruisstr 85",
    "sg:city":"Dendermonde (groot)",
    "sg:classifiers":[
        {
            "category":"Personal",
            "subcategory":"Beauty Salon",
            "type":"Services"
        }
    ],
    "sg:phone":"+32 52 21 26 98",
    "sg:postcode":"9200",
    "sg:province":"Oost-Vlaanderen",
    "sg:tags":[
        "de",
        "coiffure"
    ],
    "wof:name":"Kinder-&tienerkapsalon",
    "wof:placetype":"venue"
},
  "geometry": {"coordinates":[4.1115927696,51.0102005005],"type":"Point"}
}