{
  "type": "Feature",
  "properties": {
    "addr:full":"Louizalaan 391 Brussel/bruxelles Bruxelles-Capitale 1050",
    "addr:housenumber":"391",
    "addr:postcode":"1050",
    "addr:street":"Louizalaan;/",
    "iso:country":"BE",
    "sg:address":"Louizalaan 391",
    "sg:city":"Brussel/bruxelles",
    "sg:orig_category":"Herstellingen and onderhoud van auto's Voertuigen",
    "sg:phone":"+32 2 640 00 87",
    "sg:postcode":"1050",
    "sg:province":"Bruxelles-Capitale",
    "wof:name":"Beherman Auto/beherman Retail",
    "wof:placetype":"venue"
},
  "geometry": {"coordinates":[4.356962204,50.8341941833],"type":"Point"}
}