{
  "type": "Feature",
  "properties": {
    "iso:country":"BE",
    "sg:address":"Loonsvijverstraat 1",
    "sg:city":"Zonnebeke",
    "sg:orig_category":"Rundveehouders",
    "sg:phone":"+32 51 77 70 74",
    "sg:postcode":"8980",
    "sg:province":"West-Vlaanderen",
    "wof:name":"Gilbert Vangheluwe",
    "wof:placetype":"venue"
},
  "geometry": {"coordinates":[2.9872550964,50.8730812073],"type":"Point"}
}