{
  "type": "Feature",
  "properties": {
    "iso:country":"BE",
    "sg:address":"Bruul 6b12",
    "sg:city":"Ronse/renaix",
    "sg:orig_category":"Informaticaconsulenten Software ontwikkeling and ontwerp",
    "sg:phone":"+32 55 21 35 01",
    "sg:postcode":"9600",
    "sg:province":"Oost-Vlaanderen",
    "wof:name":"G.j. Firmw. Cons.&softw.",
    "wof:placetype":"venue"
},
  "geometry": {"coordinates":[3.6034629345,50.7504920959],"type":"Point"}
}