{
  "type": "Feature",
  "properties": {
    "addr:full":"Rue Des D\u00c9port\u00c9s 60 Rixensart Brabant Wallon 1332",
    "addr:housenumber":"60",
    "addr:postcode":"1332",
    "addr:street":"Rue Des De\u0301Porte\u0301S;Wallon",
    "iso:country":"BE",
    "sg:address":"Rue Des D\u00c9port\u00c9s 60",
    "sg:city":"Rixensart",
    "sg:orig_category":"Drogueries. Peinture. Rev\u00eatements pour sols and murs",
    "sg:phone":"+32 2 653 42 11",
    "sg:postcode":"1332",
    "sg:province":"Brabant Wallon",
    "wof:name":"Libert - De Bruyne",
    "wof:placetype":"venue"
},
  "geometry": {"coordinates":[4.4935321808,50.7170982361],"type":"Point"}
}