{
  "type": "Feature",
  "properties": {
    "iso:country":"BE",
    "sg:address":"Leopoldplein 9",
    "sg:city":"Hasselt",
    "sg:classifiers":[
        {
            "category":"Arts & Performance",
            "subcategory":"Art Gallery",
            "type":"Entertainment"
        }
    ],
    "sg:phone":"+32 11 22 60 10",
    "sg:postcode":"3500",
    "sg:province":"Limburg",
    "wof:name":"Dessers Bvba",
    "wof:placetype":"venue"
},
  "geometry": {"coordinates":[5.3358058929,50.9277648926],"type":"Point"}
}