{
  "type": "Feature",
  "properties": {
    "iso:country":"BE",
    "sg:address":"Pierstraat 133",
    "sg:city":"Kontich",
    "sg:classifiers":[
        {
            "category":"Building & Trades",
            "subcategory":"Plumbing",
            "type":"Services"
        }
    ],
    "sg:phone":"+32 3 457 10 81",
    "sg:postcode":"2550",
    "sg:province":"Antwerpen",
    "sg:tags":[
        "repair",
        "mainten",
        "-",
        "central",
        "heating"
    ],
    "wof:name":"Van Herck Frans & Zonen Bvba",
    "wof:placetype":"venue"
},
  "geometry": {"coordinates":[4.4261331558,51.1306610107],"type":"Point"}
}