{
  "type": "Feature",
  "properties": {
    "iso:country":"BE",
    "sg:address":"Chauss\u00e9e De Charleroi 65",
    "sg:city":"Bruxelles (saint-gilles)",
    "sg:classifiers":[
        {
            "category":"Home & Garden",
            "subcategory":"Home Furnishings",
            "type":"Retail Goods"
        }
    ],
    "sg:phone":"+32 2 537 55 32",
    "sg:postcode":"1060",
    "sg:province":"Bruxelles-Capitale",
    "sg:tags":[
        "interior",
        "decoration"
    ],
    "wof:name":"Steenput & Wiame",
    "wof:placetype":"venue"
},
  "geometry": {"coordinates":[4.3561491966,50.8312072754],"type":"Point"}
}