{
  "type": "Feature",
  "properties": {
    "iso:country":"BE",
    "sg:address":"Kriekenhof 6",
    "sg:city":"Merelbeke",
    "sg:orig_category":"Verbruikerskredietinstellingen",
    "sg:phone":"+32 9 231 48 42",
    "sg:postcode":"9820",
    "sg:province":"Oost-Vlaanderen",
    "wof:name":"Mister Cr\u00c9dit",
    "wof:placetype":"venue"
},
  "geometry": {"coordinates":[3.7561058998,50.9878387451],"type":"Point"}
}