{
  "type": "Feature",
  "properties": {
    "addr:full":"Gelmelstraat 62 Hoogstraten Antwerpen 2320",
    "addr:housenumber":"62",
    "addr:postcode":"2320",
    "addr:street":"Gelmelstraat",
    "iso:country":"BE",
    "sg:address":"Gelmelstraat 62",
    "sg:city":"Hoogstraten",
    "sg:orig_category":"Algemeen secundair onderwijs",
    "sg:phone":"+32 3 314 50 11",
    "sg:postcode":"2320",
    "sg:province":"Antwerpen",
    "wof:name":"Internaat Spijker",
    "wof:placetype":"venue"
},
  "geometry": {"coordinates":[4.7688698769,51.4033126831],"type":"Point"}
}