{
  "type": "Feature",
  "properties": {
    "iso:country":"BE",
    "sg:address":"Rue De Philippeville 87",
    "sg:city":"Ham-sur-heure-nalinnes (nalinnes)",
    "sg:orig_category":"Terraces Horeca",
    "sg:phone":"+32 2 721 69 89",
    "sg:postcode":"6120",
    "sg:province":"Hainaut",
    "wof:name":"Baille J Ets Sprl",
    "wof:placetype":"venue"
},
  "geometry": {"coordinates":[4.4749622345,50.3360404968],"type":"Point"}
}