{
  "type": "Feature",
  "properties": {
    "addr:full":"Everaertsstraat 64 Antwerpen Antwerpen 2060",
    "addr:housenumber":"64",
    "addr:postcode":"2060",
    "addr:street":"Everaertsstraat",
    "iso:country":"BE",
    "sg:address":"Everaertsstraat 64",
    "sg:city":"Antwerpen",
    "sg:orig_category":"Installation \u00e9lectrique r\u00e9sidentielle",
    "sg:phone":"+32 3 226 93 96",
    "sg:postcode":"2060",
    "sg:province":"Antwerpen",
    "wof:name":"Marc Everaert",
    "wof:placetype":"venue"
},
  "geometry": {"coordinates":[4.4247488976,51.2269744873],"type":"Point"}
}