{
  "type": "Feature",
  "properties": {
    "addr:full":"Zandstraat 26 Retie Antwerpen 2470",
    "addr:housenumber":"26",
    "addr:postcode":"2470",
    "addr:street":"Zandstraat",
    "iso:country":"BE",
    "sg:address":"Zandstraat 26",
    "sg:city":"Retie",
    "sg:orig_category":"Plomberie, chauffage and installations sanitaires",
    "sg:phone":"+32 14 37 35 90",
    "sg:postcode":"2470",
    "sg:province":"Antwerpen",
    "wof:name":"Tim De Kock",
    "wof:placetype":"venue"
},
  "geometry": {"coordinates":[5.0905499458,51.2541885376],"type":"Point"}
}