{
  "type": "Feature",
  "properties": {
    "iso:country":"BE",
    "sg:address":"Rue Du Lombard 29-31",
    "sg:city":"Bruxelles",
    "sg:classifiers":[
        {
            "category":"Manufacturing",
            "subcategory":"Furniture",
            "type":"Manufacturing & Wholesale Goods"
        }
    ],
    "sg:phone":"+32 2 511 60 78",
    "sg:postcode":"1000",
    "sg:province":"Bruxelles-Capitale",
    "sg:tags":[
        "armchair",
        "-"
    ],
    "wof:name":"Sauvage D\u00e9cor Sa",
    "wof:placetype":"venue"
},
  "geometry": {"coordinates":[4.3500361443,50.8457183838],"type":"Point"}
}