{
  "type": "Feature",
  "properties": {
    "iso:country":"BE",
    "sg:address":"Rue Du Charron 77",
    "sg:city":"Braine-l\u00b4alleud",
    "sg:orig_category":"Plaatsen van vloer- and muurbekleding Schilders",
    "sg:phone":"+32 2 387 34 79",
    "sg:postcode":"1420",
    "sg:province":"Brabant Wallon",
    "wof:name":"Stordeur Freres",
    "wof:placetype":"venue"
},
  "geometry": {"coordinates":[4.3905029297,50.684928894],"type":"Point"}
}