{
  "type": "Feature",
  "properties": {
    "iso:country":"BE",
    "sg:address":"Rue Du Fr\u00e8re-m\u00e9rantius 2",
    "sg:city":"Virton (ruette)",
    "sg:classifiers":[
        {
            "category":"Real Estate",
            "subcategory":"Surveying",
            "type":"Services"
        }
    ],
    "sg:phone":"+32 63 57 66 93",
    "sg:postcode":"6760",
    "sg:province":"Luxembourg",
    "sg:tags":[
        "lettering",
        "letter"
    ],
    "wof:name":"Sbn Screen Sc",
    "wof:placetype":"venue"
},
  "geometry": {"coordinates":[5.5944848061,49.5368843079],"type":"Point"}
}