{
  "type": "Feature",
  "properties": {
    "addr:full":"Impasse Des Capucins 2b8 Namur Namur 5000",
    "addr:housenumber":"2b8",
    "addr:postcode":"5000",
    "addr:street":"Impasse Des Capucins",
    "iso:country":"BE",
    "sg:address":"Impasse Des Capucins 2b8",
    "sg:city":"Namur",
    "sg:orig_category":"Maatschappelijke dienstverlening",
    "sg:phone":"+32 81 22 08 72",
    "sg:postcode":"5000",
    "sg:province":"Namur",
    "wof:name":"Centre National Infor Jeunes",
    "wof:placetype":"venue"
},
  "geometry": {"coordinates":[4.866230011,50.4650001526],"type":"Point"}
}