{
  "type": "Feature",
  "properties": {
    "addr:full":"Subtropische Planten De Pinte Oost-Vlaanderen 9840",
    "addr:postcode":"9840",
    "addr:street":"Subtropische Planten",
    "iso:country":"BE",
    "sg:address":"Subtropische Planten",
    "sg:city":"De Pinte",
    "sg:orig_category":"Bloemen and planten Bloemen and planten Gh",
    "sg:phone":"+32 9 222 66 33",
    "sg:postcode":"9840",
    "sg:province":"Oost-Vlaanderen",
    "wof:name":"Plantimplex Ets.",
    "wof:placetype":"venue"
},
  "geometry": {"coordinates":[3.6517701149,50.9923439026],"type":"Point"}
}