{
  "type": "Feature",
  "properties": {
    "addr:full":"Heirbaan 30 Grobbendonk Antwerpen 2280",
    "addr:housenumber":"30",
    "addr:postcode":"2280",
    "addr:street":"Heirbaan",
    "iso:country":"BE",
    "sg:address":"Heirbaan 30",
    "sg:city":"Grobbendonk",
    "sg:classifiers":[
        {
            "category":"Utilities",
            "subcategory":"Fuel Oil & Lpg",
            "type":"Services"
        }
    ],
    "sg:phone":"+32 14 51 25 55",
    "sg:postcode":"2280",
    "sg:province":"Antwerpen",
    "wof:name":"Struyfs & Zn Bvba",
    "wof:placetype":"venue"
},
  "geometry": {"coordinates":[4.7340459824,51.2023544312],"type":"Point"}
}