{
  "type": "Feature",
  "properties": {
    "addr:full":"Leopoldstraat 17 Turnhout Antwerpen 2300",
    "addr:housenumber":"17",
    "addr:postcode":"2300",
    "addr:street":"Leopoldstraat",
    "iso:country":"BE",
    "sg:address":"Leopoldstraat 17",
    "sg:city":"Turnhout",
    "sg:orig_category":"Eclairage et \u00e9quipements du foyer",
    "sg:phone":"+32 14 42 70 55",
    "sg:postcode":"2300",
    "sg:province":"Antwerpen",
    "wof:name":"Nostalgie",
    "wof:placetype":"venue"
},
  "geometry": {"coordinates":[4.9443497658,51.3230667114],"type":"Point"}
}