{
  "type": "Feature",
  "properties": {
    "addr:full":"Nieuwpoortsesteenweg 20bb Oostende West-Vlaanderen 8400",
    "addr:housenumber":"20bb",
    "addr:postcode":"8400",
    "addr:street":"Nieuwpoortsesteenweg",
    "iso:country":"BE",
    "sg:address":"Nieuwpoortsesteenweg 20bb",
    "sg:city":"Oostende",
    "sg:orig_category":"Baby- and kinderkleding Babyspullen",
    "sg:phone":"+32 59 70 00 40",
    "sg:postcode":"8400",
    "sg:province":"West-Vlaanderen",
    "wof:name":"Huis Marie-o-bain",
    "wof:placetype":"venue"
},
  "geometry": {"coordinates":[2.9079010487,51.2242507935],"type":"Point"}
}