{
  "type": "Feature",
  "properties": {
    "addr:full":"Liebaardstraat 1 Waregem West-Vlaanderen 8792",
    "addr:housenumber":"1",
    "addr:postcode":"8792",
    "addr:street":"Liebaardstraat",
    "iso:country":"BE",
    "sg:address":"Liebaardstraat 1",
    "sg:city":"Waregem",
    "sg:classifiers":[
        {
            "category":"Cafe",
            "type":"Food & Drink"
        }
    ],
    "sg:phone":"+32 56 71 24 75",
    "sg:postcode":"8792",
    "sg:province":"West-Vlaanderen",
    "sg:tags":[
        "caf\u00e9s"
    ],
    "wof:name":"Dick Desmet",
    "wof:placetype":"venue"
},
  "geometry": {"coordinates":[3.3496799469,50.8867454529],"type":"Point"}
}