{
  "type": "Feature",
  "properties": {
    "iso:country":"BE",
    "sg:address":"Arkemolenstraat 27",
    "sg:city":"Moorslede",
    "sg:orig_category":"Groententeelt",
    "sg:phone":"+32 56 50 01 57",
    "sg:postcode":"8890",
    "sg:province":"West-Vlaanderen",
    "wof:name":"Fa. Masschelein",
    "wof:placetype":"venue"
},
  "geometry": {"coordinates":[3.0768909454,50.8469619751],"type":"Point"}
}