{
  "type": "Feature",
  "properties": {
    "addr:full":"Chauss\u00c9e D'alsemberg 76 Sint-gillis/saint-gilles Bruxelles-Capitale 1060",
    "addr:housenumber":"76",
    "addr:postcode":"1060",
    "addr:street":"Chausse\u0301E D'Alsemberg",
    "iso:country":"BE",
    "sg:address":"Chauss\u00c9e D'alsemberg 76",
    "sg:city":"Sint-gillis/saint-gilles",
    "sg:orig_category":"Jeux and jouets",
    "sg:phone":"+32 2 537 83 92",
    "sg:postcode":"1060",
    "sg:province":"Bruxelles-Capitale",
    "wof:name":"Casse Noisettes",
    "wof:placetype":"venue"
},
  "geometry": {"coordinates":[4.3435811996,50.8242645264],"type":"Point"}
}