{
  "type": "Feature",
  "properties": {
    "iso:country":"BE",
    "sg:address":"Rue Haut-vin\u00c2ve 40",
    "sg:city":"Ans",
    "sg:orig_category":"Instituts de beaut\u00e9. Combustibles",
    "sg:phone":"+32 4 257 60 89",
    "sg:postcode":"4432",
    "sg:province":"Li\u00e8ge",
    "wof:name":"P\u00c9dicure Fourre",
    "wof:placetype":"venue"
},
  "geometry": {"coordinates":[5.4771847725,50.7027702332],"type":"Point"}
}