{
  "type": "Feature",
  "properties": {
    "iso:country":"BE",
    "sg:address":"Langestraat 140",
    "sg:city":"Ternat (wambeek)",
    "sg:classifiers":[
        {
            "category":"Communications",
            "type":"Services"
        }
    ],
    "sg:phone":"+32 2 567 20 71",
    "sg:postcode":"1741",
    "sg:province":"Vlaams-Brabant",
    "sg:tags":[
        "translator"
    ],
    "wof:name":"Taelemans T",
    "wof:placetype":"venue"
},
  "geometry": {"coordinates":[4.1809091568,50.850402832],"type":"Point"}
}