{
  "type": "Feature",
  "properties": {
    "addr:full":"Oude Zandstraat 21b4 Beveren Oost-Vlaanderen 9120",
    "addr:housenumber":"21b4",
    "addr:postcode":"9120",
    "addr:street":"Oude Zandstraat",
    "iso:country":"BE",
    "sg:address":"Oude Zandstraat 21b4",
    "sg:city":"Beveren",
    "sg:orig_category":"Agences immobili\u00e8res. Assurances. Pr\u00eats hypoth\u00e9caires and cr\u00e9dits immobiliers",
    "sg:phone":"+32 3 775 17 26",
    "sg:postcode":"9120",
    "sg:province":"Oost-Vlaanderen",
    "wof:name":"Adviesburo Kwotum",
    "wof:placetype":"venue"
},
  "geometry": {"coordinates":[4.2542037964,51.2120323181],"type":"Point"}
}