{
  "type": "Feature",
  "properties": {
    "addr:full":"Brugsestraat 35 Oostkamp West-Vlaanderen 8020",
    "addr:housenumber":"35",
    "addr:postcode":"8020",
    "addr:street":"Brugsestraat",
    "iso:country":"BE",
    "sg:address":"Brugsestraat 35",
    "sg:city":"Oostkamp",
    "sg:classifiers":[
        {
            "category":"Retail",
            "subcategory":"Funeral Services",
            "type":"Services"
        }
    ],
    "sg:phone":"+32 50 82 40 48",
    "sg:postcode":"8020",
    "sg:province":"West-Vlaanderen",
    "sg:tags":[
        "director"
    ],
    "wof:name":"Timmerman Jos",
    "wof:placetype":"venue"
},
  "geometry": {"coordinates":[3.2354059219,51.1568946838],"type":"Point"}
}