{
  "type": "Feature",
  "properties": {
    "addr:full":"Baerdonckstraat 14 Wetteren Oost-Vlaanderen 9230",
    "addr:housenumber":"14",
    "addr:postcode":"9230",
    "addr:street":"Baerdonckstraat",
    "iso:country":"BE",
    "sg:address":"Baerdonckstraat 14",
    "sg:city":"Wetteren",
    "sg:orig_category":"Gespecialiseerde residenti\u00eble bouw Woningbouw",
    "sg:phone":"+32 9 369 57 37",
    "sg:postcode":"9230",
    "sg:province":"Oost-Vlaanderen",
    "wof:name":"Willy De Keulenaere",
    "wof:placetype":"venue"
},
  "geometry": {"coordinates":[3.8823039532,51.0124549866],"type":"Point"}
}