{
  "type": "Feature",
  "properties": {
    "iso:country":"BE",
    "sg:address":"Mexicostraat 16",
    "sg:city":"Ichtegem",
    "sg:orig_category":"Catering and organisatie van feesten Fast food and meeneem restaurants Levering aan huis restaurants",
    "sg:phone":"+32 51 58 31 71",
    "sg:postcode":"8480",
    "sg:province":"West-Vlaanderen",
    "wof:name":"In Den Plezanten Hof Restaurant",
    "wof:placetype":"venue"
},
  "geometry": {"coordinates":[3.0086979866,51.0904006958],"type":"Point"}
}