{
  "type": "Feature",
  "properties": {
    "addr:full":"Chaamseweg 2 Hoogstraten Antwerpen 2328",
    "addr:housenumber":"2",
    "addr:postcode":"2328",
    "addr:street":"Chaamseweg",
    "iso:country":"BE",
    "sg:address":"Chaamseweg 2",
    "sg:city":"Hoogstraten",
    "sg:classifiers":[
        {
            "category":"Personal",
            "subcategory":"Beauty Salon",
            "type":"Services"
        }
    ],
    "sg:phone":"+32 3 315 94 58",
    "sg:postcode":"2328",
    "sg:province":"Antwerpen",
    "sg:tags":[
        "de",
        "coiffure"
    ],
    "wof:name":"Coiffure Viviane",
    "wof:placetype":"venue"
},
  "geometry": {"coordinates":[4.8041949272,51.4741134644],"type":"Point"}
}