{
  "type": "Feature",
  "properties": {
    "addr:full":"Nieuwstraat 24 Hove Antwerpen 2540",
    "addr:housenumber":"24",
    "addr:postcode":"2540",
    "addr:street":"Nieuwstraat",
    "iso:country":"BE",
    "sg:address":"Nieuwstraat 24",
    "sg:city":"Hove",
    "sg:classifiers":[
        {
            "category":"Real Estate",
            "subcategory":"Architect",
            "type":"Services"
        }
    ],
    "sg:phone":"+32 3 454 34 50",
    "sg:postcode":"2540",
    "sg:province":"Antwerpen",
    "wof:name":"Jennen F",
    "wof:placetype":"venue"
},
  "geometry": {"coordinates":[4.467854023,51.152923584],"type":"Point"}
}