{
  "type": "Feature",
  "properties": {
    "iso:country":"BE",
    "sg:address":"Bosstraat 365bb",
    "sg:city":"Sint-pieters-woluwe/woluwe-saint-pierre",
    "sg:orig_category":"CD's, cassettes and platen Film-, tv- and videoproductie",
    "sg:phone":"+32 2 779 17 17",
    "sg:postcode":"1150",
    "sg:province":"Bruxelles-Capitale",
    "wof:name":"R.t.c.b.",
    "wof:placetype":"venue"
},
  "geometry": {"coordinates":[4.4561228752,50.8278045654],"type":"Point"}
}