{
  "type": "Feature",
  "properties": {
    "iso:country":"BE",
    "sg:address":"Pottestraat 99",
    "sg:city":"Poperinge",
    "sg:classifiers":[
        {
            "category":"Personal",
            "subcategory":"Beauty Salon",
            "type":"Services"
        }
    ],
    "sg:phone":"+32 57 33 65 21",
    "sg:postcode":"8970",
    "sg:province":"West-Vlaanderen",
    "sg:tags":[
        "de",
        "coiffure"
    ],
    "wof:name":"Coiffure Hans",
    "wof:placetype":"venue"
},
  "geometry": {"coordinates":[2.7226490974,50.8589057922],"type":"Point"}
}