{
  "type": "Feature",
  "properties": {
    "addr:full":"Rue Du Quatre Ao\u00dbt 54 Wavre Brabant Wallon 1300",
    "addr:housenumber":"54;1300",
    "addr:street":"Rue Du Quatre Aou\u0302T",
    "iso:country":"BE",
    "sg:address":"Rue Du Quatre Ao\u00dbt 54",
    "sg:city":"Wavre",
    "sg:orig_category":"Artsen and specialisten",
    "sg:phone":"+32 10 22 24 65",
    "sg:postcode":"1300",
    "sg:province":"Brabant Wallon",
    "wof:name":"Anne-c\u00c9cile Lovens",
    "wof:placetype":"venue"
},
  "geometry": {"coordinates":[4.6093711853,50.7185745239],"type":"Point"}
}