{
  "type": "Feature",
  "properties": {
    "iso:country":"BE",
    "sg:address":"Westeindestraat 145",
    "sg:city":"Maldegem",
    "sg:orig_category":"Artsen and specialisten",
    "sg:phone":"+32 50 71 31 68",
    "sg:postcode":"9990",
    "sg:province":"Oost-Vlaanderen",
    "wof:name":"Margriet Lippens",
    "wof:placetype":"venue"
},
  "geometry": {"coordinates":[3.4353430271,51.2082443237],"type":"Point"}
}