{
  "type": "Feature",
  "properties": {
    "iso:country":"BE",
    "sg:address":"Avenue Claire 37ba",
    "sg:city":"Waterloo",
    "sg:orig_category":"M\u00e9decins and sp\u00e9cialistes",
    "sg:phone":"+32 2 354 98 07",
    "sg:postcode":"1410",
    "sg:province":"Brabant Wallon",
    "wof:name":"Serge Wesel",
    "wof:placetype":"venue"
},
  "geometry": {"coordinates":[4.4013848305,50.7196960449],"type":"Point"}
}