{
  "type": "Feature",
  "properties": {
    "iso:country":"BE",
    "sg:address":"Oude Baan 6",
    "sg:city":"Lille",
    "sg:orig_category":"Epiceries",
    "sg:phone":"+32 14 55 75 77",
    "sg:postcode":"2275",
    "sg:province":"Antwerpen",
    "wof:name":"Frans Laurijssen",
    "wof:placetype":"venue"
},
  "geometry": {"coordinates":[4.8721518517,51.2690849304],"type":"Point"}
}