{
  "type": "Feature",
  "properties": {
    "addr:full":"Avenue Du Parc De Woluwe 50 Bruxelles (auderghem) Bruxelles-Capitale 1160",
    "addr:housenumber":"50",
    "addr:postcode":"1160",
    "addr:street":"Avenue Du Parc De Woluwe",
    "iso:country":"BE",
    "sg:address":"Avenue Du Parc De Woluwe 50",
    "sg:city":"Bruxelles (auderghem)",
    "sg:classifiers":[
        {
            "category":"Health Services",
            "subcategory":"Doctor",
            "type":"Services"
        }
    ],
    "sg:phone":"+32 2 673 03 92",
    "sg:postcode":"1160",
    "sg:province":"Bruxelles-Capitale",
    "sg:tags":[
        "medicinephysicians",
        "surgeon"
    ],
    "wof:name":"Marchand M",
    "wof:placetype":"venue"
},
  "geometry": {"coordinates":[4.4266619682,50.8219604492],"type":"Point"}
}