{
  "type": "Feature",
  "properties": {
    "iso:country":"BE",
    "sg:address":"Rue Bruy\u00e8re 94",
    "sg:city":"Ellezelles",
    "sg:classifiers":[
        {
            "category":"Health Services",
            "subcategory":"Dentist",
            "type":"Services"
        }
    ],
    "sg:phone":"+32 68 54 28 76",
    "sg:postcode":"7890",
    "sg:province":"Hainaut",
    "wof:name":"Vandenbossche M",
    "wof:placetype":"venue"
},
  "geometry": {"coordinates":[3.7021210194,50.7379264832],"type":"Point"}
}