{
  "type": "Feature",
  "properties": {
    "addr:full":"Hoevenzavellaan 68 Box 3a Genk (waterschei) Limburg 3600",
    "addr:housenumber":"68;3a",
    "addr:postcode":"3600",
    "addr:street":"Hoevenzavellaan;Box",
    "iso:country":"BE",
    "sg:address":"Hoevenzavellaan 68 Box 3a",
    "sg:city":"Genk (waterschei)",
    "sg:classifiers":[
        {
            "category":"Transit Center",
            "subcategory":"Freight",
            "type":"Transportation"
        }
    ],
    "sg:phone":"+32 89 46 70 24",
    "sg:postcode":"3600",
    "sg:province":"Limburg",
    "sg:tags":[
        "import",
        "export",
        "-"
    ],
    "wof:name":"Alexandria",
    "wof:placetype":"venue"
},
  "geometry": {"coordinates":[5.4990148544,50.9635848999],"type":"Point"}
}