{
  "type": "Feature",
  "properties": {
    "addr:full":"Oudenaardsesteenweg 828 Erpe-mere Oost-Vlaanderen 9420",
    "addr:housenumber":"828",
    "addr:postcode":"9420",
    "addr:street":"Oudenaardsesteenweg",
    "iso:country":"BE",
    "sg:address":"Oudenaardsesteenweg 828",
    "sg:city":"Erpe-mere",
    "sg:classifiers":[
        {
            "category":"Cafe",
            "type":"Food & Drink"
        }
    ],
    "sg:phone":"+32 53 63 12 58",
    "sg:postcode":"9420",
    "sg:province":"Oost-Vlaanderen",
    "sg:tags":[
        "caf\u00e9s"
    ],
    "wof:name":"Caf\u00c9 De Langen",
    "wof:placetype":"venue"
},
  "geometry": {"coordinates":[3.9181120396,50.9127731323],"type":"Point"}
}