{
  "type": "Feature",
  "properties": {
    "iso:country":"BE",
    "sg:address":"Huidenvettersplein 5",
    "sg:city":"Brugge",
    "sg:classifiers":[
        {
            "category":"Retail",
            "subcategory":"Event Space",
            "type":"Services"
        }
    ],
    "sg:phone":"+32 50 34 23 20",
    "sg:postcode":"8000",
    "sg:province":"West-Vlaanderen",
    "sg:tags":[
        "rental",
        "-",
        "hall"
    ],
    "wof:name":"Mosselkelder (de)",
    "wof:placetype":"venue"
},
  "geometry": {"coordinates":[3.2277190685,51.2077941895],"type":"Point"}
}