{
  "type": "Feature",
  "properties": {
    "iso:country":"BE",
    "sg:address":"Rue Du Houblon 61",
    "sg:city":"Brussel/bruxelles",
    "sg:orig_category":"Imprimeries and copyshops",
    "sg:phone":"+32 2 512 63 91",
    "sg:postcode":"1000",
    "sg:province":"Bruxelles-Capitale",
    "wof:name":"Myncke Fr\u00c8res",
    "wof:placetype":"venue"
},
  "geometry": {"coordinates":[4.3413410187,50.8512306213],"type":"Point"}
}