{
  "type": "Feature",
  "properties": {
    "addr:full":"Avenue De Haussy 1ba Manage Hainaut 7170",
    "addr:housenumber":"1ba",
    "addr:postcode":"7170",
    "addr:street":"Avenue De Haussy",
    "iso:country":"BE",
    "sg:address":"Avenue De Haussy 1ba",
    "sg:city":"Manage",
    "sg:orig_category":"Banken and kredietinstellingen",
    "sg:phone":"+32 64 54 84 92",
    "sg:postcode":"7170",
    "sg:province":"Hainaut",
    "wof:name":"Bbl",
    "wof:placetype":"venue"
},
  "geometry": {"coordinates":[4.2353701591,50.5030097961],"type":"Point"}
}