{
  "type": "Feature",
  "properties": {
    "iso:country":"BE",
    "sg:address":"Steenovenstraat 5",
    "sg:city":"Pittem",
    "sg:orig_category":"Eleveurs and marchands de porcs",
    "sg:phone":"+32 51 46 63 15",
    "sg:postcode":"8740",
    "sg:province":"West-Vlaanderen",
    "wof:name":"Raphael Heyndrickx",
    "wof:placetype":"venue"
},
  "geometry": {"coordinates":[3.252300024,50.9847183228],"type":"Point"}
}