{
  "type": "Feature",
  "properties": {
    "iso:country":"BE",
    "sg:address":"Dendermondse Steenweg 75",
    "sg:city":"Aalst",
    "sg:orig_category":"Non-Classified Establishments",
    "sg:phone":"+32 474 97 58 86",
    "sg:postcode":"9300",
    "sg:province":"Oost-Vlaanderen",
    "wof:name":"Flamant",
    "wof:placetype":"venue"
},
  "geometry": {"coordinates":[4.0465779305,50.9505729675],"type":"Point"}
}