{
  "type": "Feature",
  "properties": {
    "addr:full":"Parc Industriel Zone C Seneffe Hainaut 7180",
    "addr:postcode":"7180",
    "addr:street":"Parc Industriel;C;Hainaut",
    "iso:country":"BE",
    "sg:address":"Parc Industriel Zone C",
    "sg:city":"Seneffe",
    "sg:orig_category":"Apparatus, Containers, Boilers, And Tanks Of Steel",
    "sg:phone":"+32 64 23 26 11",
    "sg:postcode":"7180",
    "sg:province":"Hainaut",
    "wof:name":"Acv Manufacturing S.a.",
    "wof:placetype":"venue"
},
  "geometry": {"coordinates":[4.2591218948,50.5296554565],"type":"Point"}
}