{
  "type": "Feature",
  "properties": {
    "addr:full":"Halensebaan 151 Diest Vlaams-Brabant 3290",
    "addr:housenumber":"151",
    "addr:postcode":"3290",
    "addr:street":"Halensebaan",
    "iso:country":"BE",
    "sg:address":"Halensebaan 151",
    "sg:city":"Diest",
    "sg:classifiers":[
        {
            "category":"Manufacturing",
            "subcategory":"Metals",
            "type":"Manufacturing & Wholesale Goods"
        }
    ],
    "sg:phone":"+32 13 33 67 68",
    "sg:postcode":"3290",
    "sg:province":"Vlaams-Brabant",
    "sg:tags":[
        "ironwork"
    ],
    "wof:name":"Pacolet J",
    "wof:placetype":"venue"
},
  "geometry": {"coordinates":[5.0766720772,50.9669532776],"type":"Point"}
}