{
  "type": "Feature",
  "properties": {
    "iso:country":"BE",
    "sg:address":"Bruul 24",
    "sg:city":"Zwalm",
    "sg:orig_category":"Installation de menuiserie en bois and plastique",
    "sg:phone":"+32 55 49 82 13",
    "sg:postcode":"9630",
    "sg:province":"Oost-Vlaanderen",
    "wof:name":"Guy De Mulder",
    "wof:placetype":"venue"
},
  "geometry": {"coordinates":[3.7344350815,50.8828392029],"type":"Point"}
}