{
  "type": "Feature",
  "properties": {
    "addr:full":"Grand'place 35 Ath Hainaut 7800",
    "addr:housenumber":"35",
    "addr:postcode":"7800",
    "addr:street":"Grand'Place",
    "iso:country":"BE",
    "sg:address":"Grand'place 35",
    "sg:city":"Ath",
    "sg:orig_category":"Herstelling leer and schoeisel",
    "sg:phone":"+32 68 28 03 78",
    "sg:postcode":"7800",
    "sg:province":"Hainaut",
    "wof:name":"Philippe Verplancken",
    "wof:placetype":"venue"
},
  "geometry": {"coordinates":[3.7767679691,50.6313171387],"type":"Point"}
}