{
  "type": "Feature",
  "properties": {
    "iso:country":"BE",
    "sg:address":"Ridderstraat 6bb",
    "sg:city":"Bierbeek",
    "sg:orig_category":"Diepvriesproducten Gh",
    "sg:phone":"+32 16 46 12 60",
    "sg:postcode":"3360",
    "sg:province":"Vlaams-Brabant",
    "wof:name":"Covee",
    "wof:placetype":"venue"
},
  "geometry": {"coordinates":[4.7506041527,50.8648948669],"type":"Point"}
}