{
  "type": "Feature",
  "properties": {
    "addr:full":"Berkenlaan 10b Kaprijke (lembeke) Oost-Vlaanderen 9971",
    "addr:housenumber":"10b",
    "addr:postcode":"9971",
    "addr:street":"Berkenlaan",
    "iso:country":"BE",
    "sg:address":"Berkenlaan 10b",
    "sg:city":"Kaprijke (lembeke)",
    "sg:classifiers":[
        {
            "category":"Ice Cream",
            "type":"Food & Drink"
        }
    ],
    "sg:phone":"+32 9 377 59 25",
    "sg:postcode":"9971",
    "sg:province":"Oost-Vlaanderen",
    "wof:name":"Ijs-ster (de) Nv",
    "wof:placetype":"venue"
},
  "geometry": {"coordinates":[3.6324079037,51.1818504333],"type":"Point"}
}