{
  "type": "Feature",
  "properties": {
    "addr:full":"Kontichstraat 46 Edegem Antwerpen 2650",
    "addr:housenumber":"46",
    "addr:postcode":"2650",
    "addr:street":"Kontichstraat",
    "iso:country":"BE",
    "sg:address":"Kontichstraat 46",
    "sg:city":"Edegem",
    "sg:orig_category":"Overheidsdiensten",
    "sg:phone":"+32 3 457 75 50",
    "sg:postcode":"2650",
    "sg:province":"Antwerpen",
    "wof:name":"Admin. Directe Belast.",
    "wof:placetype":"venue"
},
  "geometry": {"coordinates":[4.4465761185,51.1525421143],"type":"Point"}
}