{
  "type": "Feature",
  "properties": {
    "addr:full":"Rue Provinciale 11 Wavre Brabant Wallon 1301",
    "addr:housenumber":"1301",
    "addr:street":"Rue Provinciale 11",
    "iso:country":"BE",
    "sg:address":"Rue Provinciale 11",
    "sg:city":"Wavre",
    "sg:orig_category":"Krantenuitgeverijen Tijdschriftenuitgeverijen",
    "sg:phone":"+32 10 40 19 67",
    "sg:postcode":"1301",
    "sg:province":"Brabant Wallon",
    "wof:name":"Editions Entre-vues",
    "wof:placetype":"venue"
},
  "geometry": {"coordinates":[4.6038880348,50.713508606],"type":"Point"}
}