{
  "type": "Feature",
  "properties": {
    "addr:full":"Kielenstraat 16 Tongeren Limburg 3700",
    "addr:housenumber":"16",
    "addr:postcode":"3700",
    "addr:street":"Kielenstraat",
    "iso:country":"BE",
    "sg:address":"Kielenstraat 16",
    "sg:city":"Tongeren",
    "sg:classifiers":[
        {
            "category":"Health Services",
            "subcategory":"Dentist",
            "type":"Services"
        }
    ],
    "sg:phone":"+32 12 23 47 13",
    "sg:postcode":"3700",
    "sg:province":"Limburg",
    "wof:name":"Hougaerts Claesen",
    "wof:placetype":"venue"
},
  "geometry": {"coordinates":[5.4659438133,50.7817192078],"type":"Point"}
}