{
  "type": "Feature",
  "properties": {
    "iso:country":"BE",
    "sg:address":"Pastoriestraat 92",
    "sg:city":"Boutersem",
    "sg:classifiers":[
        {
            "category":"Shopping",
            "subcategory":"Antiques",
            "type":"Retail Goods"
        }
    ],
    "sg:phone":"+32 16 73 52 90",
    "sg:postcode":"3370",
    "sg:province":"Vlaams-Brabant",
    "wof:name":"Buiten Verwachting",
    "wof:placetype":"venue"
},
  "geometry": {"coordinates":[4.8531699181,50.8421211243],"type":"Point"}
}