{
  "type": "Feature",
  "properties": {
    "iso:country":"BE",
    "sg:address":"Industrielaan 38",
    "sg:city":"Brakel (nederbrakel)",
    "sg:orig_category":"Metallizing",
    "sg:phone":"+32 55 42 56 97",
    "sg:postcode":"9660",
    "sg:province":"Oost-Vlaanderen",
    "wof:name":"Bramo",
    "wof:placetype":"venue"
},
  "geometry": {"coordinates":[3.7608599663,50.7957229614],"type":"Point"}
}