{
  "type": "Feature",
  "properties": {
    "iso:country":"BE",
    "sg:address":"De Ridderstraat 5",
    "sg:city":"Aalst",
    "sg:classifiers":[
        {
            "category":"Health Services",
            "subcategory":"Optometrist",
            "type":"Services"
        }
    ],
    "sg:phone":"+32 53 78 01 11",
    "sg:postcode":"9300",
    "sg:province":"Oost-Vlaanderen",
    "wof:name":"Optiek Pupil",
    "wof:placetype":"venue"
},
  "geometry": {"coordinates":[4.0365300179,50.9398384094],"type":"Point"}
}