{
  "type": "Feature",
  "properties": {
    "iso:country":"BE",
    "sg:address":"Burchtstraat 14",
    "sg:city":"Kruibeke",
    "sg:classifiers":[
        {
            "category":"Food & Beverages",
            "subcategory":"Specialty",
            "type":"Retail Goods"
        }
    ],
    "sg:phone":"+32 3 774 43 26",
    "sg:postcode":"9150",
    "sg:province":"Oost-Vlaanderen",
    "sg:tags":[
        "health",
        "dietary",
        "-",
        "biological"
    ],
    "wof:name":"Madeliefje ('t)",
    "wof:placetype":"venue"
},
  "geometry": {"coordinates":[4.3158621788,51.1769371033],"type":"Point"}
}