{
  "type": "Feature",
  "properties": {
    "iso:country":"BE",
    "sg:address":"Grand Route 598",
    "sg:city":"Flemalle",
    "sg:orig_category":"Herstellingen and onderhoud van auto's",
    "sg:phone":"+32 4 233 91 95",
    "sg:postcode":"4400",
    "sg:province":"Li\u00e8ge",
    "wof:name":"Tordoir Engineering",
    "wof:placetype":"venue"
},
  "geometry": {"coordinates":[5.4543910027,50.5927047729],"type":"Point"}
}