{
  "type": "Feature",
  "properties": {
    "addr:full":"Koerselsebaan 151b1 Heusden-zolder Limburg 3550",
    "addr:housenumber":"151b1",
    "addr:postcode":"3550",
    "addr:street":"Koerselsebaan",
    "iso:country":"BE",
    "sg:address":"Koerselsebaan 151b1",
    "sg:city":"Heusden-zolder",
    "sg:orig_category":"Artiesten and kunstenaars Decoratieve kunst and kunstbenodigdheden",
    "sg:phone":"+32 11 43 15 31",
    "sg:postcode":"3550",
    "sg:province":"Limburg",
    "wof:name":"Liliane Corvers",
    "wof:placetype":"venue"
},
  "geometry": {"coordinates":[5.2794499397,51.0456008911],"type":"Point"}
}