{
  "type": "Feature",
  "properties": {
    "addr:full":"Chauss\u00c9e De Tubize 93 Braine-l'alleud Brabant Wallon 1420",
    "addr:housenumber":"93",
    "addr:postcode":"1420",
    "addr:street":"Chausse\u0301E De Tubize",
    "iso:country":"BE",
    "sg:address":"Chauss\u00c9e De Tubize 93",
    "sg:city":"Braine-l'alleud",
    "sg:orig_category":"Pi\u00e8ces and accessoires de v\u00e9hicules automobiles Entretien and r\u00e9parations de voitures",
    "sg:phone":"+32 2 384 61 53",
    "sg:postcode":"1420",
    "sg:province":"Brabant Wallon",
    "wof:name":"Carrosserie Auto-fer",
    "wof:placetype":"venue"
},
  "geometry": {"coordinates":[4.1952600479,50.6840705872],"type":"Point"}
}