{
  "type": "Feature",
  "properties": {
    "iso:country":"BE",
    "sg:address":"Stationsstraat 83",
    "sg:city":"Boutersem",
    "sg:classifiers":[
        {
            "category":"Social Services",
            "subcategory":"Child Care",
            "type":"Services"
        }
    ],
    "sg:phone":"+32 16 73 30 98",
    "sg:postcode":"3370",
    "sg:province":"Vlaams-Brabant",
    "sg:tags":[
        "baby",
        "nursery",
        "day",
        "sitting"
    ],
    "wof:name":"Vlindertje ('t)",
    "wof:placetype":"venue"
},
  "geometry": {"coordinates":[4.8402237892,50.8376350403],"type":"Point"}
}