{
  "type": "Feature",
  "properties": {
    "iso:country":"BE",
    "sg:address":"Scheldestraat 57",
    "sg:city":"Temse",
    "sg:orig_category":"Alimentation sp\u00e9cialis\u00e9e",
    "sg:phone":"+32 3 771 13 94",
    "sg:postcode":"9140",
    "sg:province":"Oost-Vlaanderen",
    "wof:name":"Delicatessen Ann",
    "wof:placetype":"venue"
},
  "geometry": {"coordinates":[4.2163791656,51.1263008118],"type":"Point"}
}