{
  "type": "Feature",
  "properties": {
    "iso:country":"BE",
    "sg:address":"Burgweg 15",
    "sg:city":"Koksijde",
    "sg:orig_category":"Varkenskwekers",
    "sg:phone":"+32 58 31 23 83",
    "sg:postcode":"8670",
    "sg:province":"West-Vlaanderen",
    "wof:name":"Patrick Van Hyfte",
    "wof:placetype":"venue"
},
  "geometry": {"coordinates":[2.6660709381,51.0995826721],"type":"Point"}
}