{
  "type": "Feature",
  "properties": {
    "iso:country":"BE",
    "sg:address":"Route De Thuin 10",
    "sg:city":"Thuin",
    "sg:orig_category":"Juwelen and horloges",
    "sg:phone":"+32 71 21 77 90",
    "sg:postcode":"6534",
    "sg:province":"Hainaut",
    "wof:name":"Maison Deglimes Bruffaerts",
    "wof:placetype":"venue"
},
  "geometry": {"coordinates":[4.3502287865,50.3337020874],"type":"Point"}
}