{
  "type": "Feature",
  "properties": {
    "addr:full":"Grote Markt 1 Antwerpen Antwerpen 2000",
    "addr:housenumber":"1",
    "addr:postcode":"2000",
    "addr:street":"Grote Markt",
    "iso:country":"BE",
    "sg:address":"Grote Markt 1",
    "sg:city":"Antwerpen",
    "sg:classifiers":[
        {
            "category":"Health Services",
            "subcategory":"Nursing And Care Facility",
            "type":"Services"
        }
    ],
    "sg:phone":"+32 3 650 02 02",
    "sg:postcode":"2000",
    "sg:province":"Antwerpen",
    "sg:tags":[
        "public"
    ],
    "wof:name":"Financieringsintercomm.",
    "wof:placetype":"venue"
},
  "geometry": {"coordinates":[4.3992300034,51.2212677002],"type":"Point"}
}