{
  "type": "Feature",
  "properties": {
    "addr:full":"Galerie Du Roi 24-26 Bruxelles Bruxelles-Capitale 1000",
    "addr:postcode":"24-26;1000",
    "addr:street":"Galerie Du Roi",
    "iso:country":"BE",
    "sg:address":"Galerie Du Roi 24-26",
    "sg:city":"Bruxelles",
    "sg:classifiers":[
        {
            "category":"Food & Beverages",
            "subcategory":"Chocolate",
            "type":"Retail Goods"
        }
    ],
    "sg:phone":"+32 2 512 49 84",
    "sg:postcode":"1000",
    "sg:province":"Bruxelles-Capitale",
    "sg:tags":[
        "confectionery",
        "-"
    ],
    "wof:name":"Corn\u00e9 De La Toison D'or",
    "wof:placetype":"venue"
},
  "geometry": {"coordinates":[4.3335790634,50.8311538696],"type":"Point"}
}