{
  "type": "Feature",
  "properties": {
    "iso:country":"BE",
    "sg:address":"Keizersplein 47",
    "sg:city":"Aalst",
    "sg:orig_category":"Meubles D\u00e9taillants, Am\u00e9nagement de B\u00e2timents et de Cuisines",
    "sg:phone":"+32 53 21 59 99",
    "sg:postcode":"9300",
    "sg:province":"Oost-Vlaanderen",
    "wof:name":"Peter & De Wolf",
    "wof:placetype":"venue"
},
  "geometry": {"coordinates":[4.0366249084,50.9360351562],"type":"Point"}
}