{
  "type": "Feature",
  "properties": {
    "addr:full":"Rue Haute 61 Ottignies-louvain-la-neuve Brabant Wallon 1348",
    "addr:housenumber":"61",
    "addr:postcode":"1348",
    "addr:street":"Rue Haute",
    "iso:country":"BE",
    "sg:address":"Rue Haute 61",
    "sg:city":"Ottignies-louvain-la-neuve",
    "sg:orig_category":"M\u00e9decins and sp\u00e9cialistes",
    "sg:phone":"+32 10 45 03 98",
    "sg:postcode":"1348",
    "sg:province":"Brabant Wallon",
    "wof:name":"Didier Hue",
    "wof:placetype":"venue"
},
  "geometry": {"coordinates":[4.6032619476,50.6692848206],"type":"Point"}
}