{
  "type": "Feature",
  "properties": {
    "addr:full":"Rue Du Louvroy 45 Ham-sur-heure-nalinnes Hainaut 6120",
    "addr:housenumber":"45",
    "addr:postcode":"6120",
    "addr:street":"Rue Du Louvroy;Hainaut",
    "iso:country":"BE",
    "sg:address":"Rue Du Louvroy 45",
    "sg:city":"Ham-sur-heure-nalinnes",
    "sg:orig_category":"M\u00e9decins and sp\u00e9cialistes",
    "sg:phone":"+32 71 22 14 15",
    "sg:postcode":"6120",
    "sg:province":"Hainaut",
    "wof:name":"Marc Dandois",
    "wof:placetype":"venue"
},
  "geometry": {"coordinates":[4.4702401161,50.3204574585],"type":"Point"}
}