{
  "type": "Feature",
  "properties": {
    "addr:full":"Rue Saint-roch 8 Assesse Namur 5330",
    "addr:housenumber":"8",
    "addr:postcode":"5330",
    "addr:street":"Rue Saint-Roch",
    "iso:country":"BE",
    "sg:address":"Rue Saint-roch 8",
    "sg:city":"Assesse",
    "sg:orig_category":"HERSTELLING ELEKTRISCHE HUISHOUDAPPARATEN Huishoudapparaten, televisies and radio's",
    "sg:phone":"+32 83 65 52 35",
    "sg:postcode":"5330",
    "sg:province":"Namur",
    "wof:name":"Claude Morelle",
    "wof:placetype":"venue"
},
  "geometry": {"coordinates":[5.0246567726,50.3668899536],"type":"Point"}
}