{
  "type": "Feature",
  "properties": {
    "iso:country":"BE",
    "sg:address":"Dendermondsesteenweg 1",
    "sg:city":"Lebbeke",
    "sg:classifiers":[
        {
            "category":"Real Estate",
            "subcategory":"Architect",
            "type":"Services"
        }
    ],
    "sg:phone":"+32 52 41 51 61",
    "sg:postcode":"9280",
    "sg:province":"Oost-Vlaanderen",
    "wof:name":"Van De Voorde E",
    "wof:placetype":"venue"
},
  "geometry": {"coordinates":[4.1277599335,51.0013084412],"type":"Point"}
}