{
  "type": "Feature",
  "properties": {
    "addr:full":"Rue G\u00c9n\u00c9ral Modard 25 Ans Li\u00e8ge 4431",
    "addr:housenumber":"25",
    "addr:postcode":"4431",
    "addr:street":"Rue Ge\u0301Ne\u0301Ral Modard",
    "iso:country":"BE",
    "sg:address":"Rue G\u00c9n\u00c9ral Modard 25",
    "sg:city":"Ans",
    "sg:classifiers":[
        {
            "category":"Personal",
            "subcategory":"Beauty Salon",
            "type":"Services"
        }
    ],
    "sg:phone":"+32 4 263 79 02",
    "sg:postcode":"4431",
    "sg:province":"Li\u00e8ge",
    "sg:tags":[
        "de",
        "coiffure"
    ],
    "wof:name":"Coiffure Josiane",
    "wof:placetype":"venue"
},
  "geometry": {"coordinates":[5.5040779114,50.6631469727],"type":"Point"}
}