{
  "type": "Feature",
  "properties": {
    "iso:country":"BE",
    "sg:address":"Rue Bonne Haie 10",
    "sg:city":"Silly (graty)",
    "sg:classifiers":[
        {
            "category":"Farming",
            "subcategory":"Farm & Veterinary Services",
            "type":"Manufacturing & Wholesale Goods"
        }
    ],
    "sg:phone":"+32 67 45 89 50",
    "sg:postcode":"7830",
    "sg:province":"Hainaut",
    "sg:tags":[
        "agricultural",
        "contractor"
    ],
    "wof:name":"De Valckeneer G",
    "wof:placetype":"venue"
},
  "geometry": {"coordinates":[4.0122089386,50.6403579712],"type":"Point"}
}