{
  "type": "Feature",
  "properties": {
    "addr:full":"Moortelstraat 18ba Affligem Vlaams-Brabant 1790",
    "addr:postcode":"1790",
    "addr:street":"Moortelstraat;Vlaams-Brabant",
    "iso:country":"BE",
    "sg:address":"Moortelstraat 18ba",
    "sg:city":"Affligem",
    "sg:orig_category":"Kapsalons",
    "sg:phone":"+32 2 582 24 56",
    "sg:postcode":"1790",
    "sg:province":"Vlaams-Brabant",
    "wof:name":"Jeannine Moyson",
    "wof:placetype":"venue"
},
  "geometry": {"coordinates":[4.1347818375,50.8986167908],"type":"Point"}
}