{
  "type": "Feature",
  "properties": {
    "addr:full":"Meenseheirweg 41 Roeselare West-Vlaanderen 8800",
    "addr:housenumber":"41",
    "addr:postcode":"8800",
    "addr:street":"Meenseheirweg",
    "iso:country":"BE",
    "sg:address":"Meenseheirweg 41",
    "sg:city":"Roeselare",
    "sg:classifiers":[
        {
            "category":"Cafe",
            "type":"Food & Drink"
        }
    ],
    "sg:phone":"+32 51 22 62 83",
    "sg:postcode":"8800",
    "sg:province":"West-Vlaanderen",
    "sg:tags":[
        "caf\u00e9s"
    ],
    "wof:name":"Marc Goethals",
    "wof:placetype":"venue"
},
  "geometry": {"coordinates":[3.1259748936,50.9372215271],"type":"Point"}
}