{
  "type": "Feature",
  "properties": {
    "addr:full":"Chauss\u00c9e Moncheur 81 Andenne Namur 5300",
    "addr:housenumber":"81",
    "addr:postcode":"5300",
    "addr:street":"Chausse\u0301E Moncheur",
    "iso:country":"BE",
    "sg:address":"Chauss\u00c9e Moncheur 81",
    "sg:city":"Andenne",
    "sg:orig_category":"Tuinen",
    "sg:phone":"+32 85 84 34 71",
    "sg:postcode":"5300",
    "sg:province":"Namur",
    "wof:name":"Michaux & Righetti",
    "wof:placetype":"venue"
},
  "geometry": {"coordinates":[5.1201648712,50.4971122742],"type":"Point"}
}