{
  "type": "Feature",
  "properties": {
    "iso:country":"BE",
    "sg:address":"Rue De L'ancien V\u00e9lodrome 32",
    "sg:city":"Esneux (tilff)",
    "sg:classifiers":[
        {
            "category":"Professional",
            "subcategory":"Management & Consulting",
            "type":"Services"
        }
    ],
    "sg:phone":"+32 4 388 34 00",
    "sg:postcode":"4130",
    "sg:province":"Li\u00e8ge",
    "sg:tags":[
        "consultant"
    ],
    "wof:name":"Wagemans Jean-pierre Sprl",
    "wof:placetype":"venue"
},
  "geometry": {"coordinates":[5.5756249428,50.5611305237],"type":"Point"}
}