{
  "type": "Feature",
  "properties": {
    "addr:full":"Hoogstraat 114 Herzele Oost-Vlaanderen 9550",
    "addr:housenumber":"114",
    "addr:postcode":"9550",
    "addr:street":"Hoogstraat;Oost-Vlaanderen",
    "iso:country":"BE",
    "sg:address":"Hoogstraat 114",
    "sg:city":"Herzele",
    "sg:orig_category":"Rundveehouders Varkenskwekers",
    "sg:phone":"+32 53 62 22 82",
    "sg:postcode":"9550",
    "sg:province":"Oost-Vlaanderen",
    "wof:name":"Leo De Cock",
    "wof:placetype":"venue"
},
  "geometry": {"coordinates":[3.875674963,50.8808555603],"type":"Point"}
}