{
  "type": "Feature",
  "properties": {
    "iso:country":"BE",
    "sg:address":"Avenue Sti\u00c9non 76",
    "sg:city":"Brussel/bruxelles",
    "sg:orig_category":"Epiceries",
    "sg:phone":"+32 2 478 77 16",
    "sg:postcode":"1020",
    "sg:province":"Bruxelles-Capitale",
    "wof:name":"Maison Le R\u00c9gal",
    "wof:placetype":"venue"
},
  "geometry": {"coordinates":[4.3306732178,50.8909301758],"type":"Point"}
}