{
  "type": "Feature",
  "properties": {
    "addr:full":"Kloosterstraat 109 Voeren Limburg 3798",
    "addr:housenumber":"109",
    "addr:postcode":"3798",
    "addr:street":"Kloosterstraat",
    "iso:country":"BE",
    "sg:address":"Kloosterstraat 109",
    "sg:city":"Voeren",
    "sg:orig_category":"Vakantiehuizen",
    "sg:phone":"+32 4 381 01 70",
    "sg:postcode":"3798",
    "sg:province":"Limburg",
    "wof:name":"Hoeve Thienhof",
    "wof:placetype":"venue"
},
  "geometry": {"coordinates":[5.7594389915,50.7591896057],"type":"Point"}
}