{
  "type": "Feature",
  "properties": {
    "addr:full":"Halvemaanstraat 81 Vorst/forest Bruxelles-Capitale 1190",
    "addr:housenumber":"81",
    "addr:postcode":"1190",
    "addr:street":"Halvemaanstraat;/ Forest",
    "iso:country":"BE",
    "sg:address":"Halvemaanstraat 81",
    "sg:city":"Vorst/forest",
    "sg:orig_category":"Diverse grafische activiteiten",
    "sg:phone":"+32 2 539 05 09",
    "sg:postcode":"1190",
    "sg:province":"Bruxelles-Capitale",
    "wof:name":"Bureau Beeckman-thienpont",
    "wof:placetype":"venue"
},
  "geometry": {"coordinates":[4.3326129913,50.8268318176],"type":"Point"}
}