{
  "type": "Feature",
  "properties": {
    "addr:full":"Hannuitsesteenweg 231 Landen Vlaams-Brabant 3401",
    "addr:housenumber":"231",
    "addr:postcode":"3401",
    "addr:street":"Hannuitsesteenweg",
    "iso:country":"BE",
    "sg:address":"Hannuitsesteenweg 231",
    "sg:city":"Landen",
    "sg:orig_category":"V\u00e9t\u00e9rinaires",
    "sg:phone":"+32 11 88 59 72",
    "sg:postcode":"3401",
    "sg:province":"Vlaams-Brabant",
    "wof:name":"M. Despontin",
    "wof:placetype":"venue"
},
  "geometry": {"coordinates":[5.0814318657,50.7340164185],"type":"Point"}
}