{
  "type": "Feature",
  "properties": {
    "addr:full":"Chauss\u00e9e De Frasnes 78 Tournai (rumillies - Mourcourt) Hainaut 7540",
    "addr:housenumber":"78",
    "addr:postcode":"7540",
    "addr:street":"Chausse\u0301E De Frasnes;Hainaut",
    "iso:country":"BE",
    "sg:address":"Chauss\u00e9e De Frasnes 78",
    "sg:city":"Tournai (rumillies - Mourcourt)",
    "sg:classifiers":[
        {
            "category":"Professional",
            "subcategory":"Accounting & Tax Preparation",
            "type":"Services"
        }
    ],
    "sg:phone":"+32 69 22 70 79",
    "sg:postcode":"7540",
    "sg:province":"Hainaut",
    "sg:tags":[
        "bookkeeper"
    ],
    "wof:name":"Boccart C",
    "wof:placetype":"venue"
},
  "geometry": {"coordinates":[3.5063819885,50.6486129761],"type":"Point"}
}