{
  "type": "Feature",
  "properties": {
    "addr:full":"Chemin Du Bon Dieu 191 Quaregnon Hainaut 7390",
    "addr:housenumber":"191",
    "addr:postcode":"7390",
    "addr:street":"Chemin Du Bon Dieu",
    "iso:country":"BE",
    "sg:address":"Chemin Du Bon Dieu 191",
    "sg:city":"Quaregnon",
    "sg:orig_category":"Woningbouw",
    "sg:phone":"+32 476 99 26 37",
    "sg:postcode":"7390",
    "sg:province":"Hainaut",
    "wof:name":"Ets. Stoquart S.",
    "wof:placetype":"venue"
},
  "geometry": {"coordinates":[3.8695011139,50.4360961914],"type":"Point"}
}