{
  "type": "Feature",
  "properties": {
    "addr:full":"Rue Klipveld 51 Ukkel (brussel) Bruxelles-Capitale 1180",
    "addr:housenumber":"51",
    "addr:postcode":"1180",
    "addr:street":"Rue Klipveld",
    "iso:country":"BE",
    "sg:address":"Rue Klipveld 51",
    "sg:city":"Ukkel (brussel)",
    "sg:classifiers":[
        {
            "category":"Personal",
            "subcategory":"Beauty Salon",
            "type":"Services"
        }
    ],
    "sg:phone":"+32 2 374 32 14",
    "sg:postcode":"1180",
    "sg:province":"Bruxelles-Capitale",
    "sg:tags":[
        "de",
        "coiffure"
    ],
    "wof:name":"Trianon",
    "wof:placetype":"venue"
},
  "geometry": {"coordinates":[4.3415021896,50.7977867126],"type":"Point"}
}