{
  "type": "Feature",
  "properties": {
    "iso:country":"BE",
    "sg:address":"Kerkestraat 69",
    "sg:city":"Leopoldsburg",
    "sg:orig_category":"HUISBRANDOLIE",
    "sg:phone":"+32 11 34 10 28",
    "sg:postcode":"3971",
    "sg:province":"Limburg",
    "wof:name":"Frans Vanderheyden",
    "wof:placetype":"venue"
},
  "geometry": {"coordinates":[5.2261228561,51.1015625],"type":"Point"}
}