{
  "type": "Feature",
  "properties": {
    "addr:full":"Isidore Geyskenslaan 43 Oudergem/auderghem Bruxelles-Capitale 1160",
    "addr:housenumber":"43",
    "addr:postcode":"1160",
    "addr:street":"Isidore Geyskenslaan;/",
    "iso:country":"BE",
    "sg:address":"Isidore Geyskenslaan 43",
    "sg:city":"Oudergem/auderghem",
    "sg:orig_category":"Persagentschappen",
    "sg:phone":"+32 2 673 21 72",
    "sg:postcode":"1160",
    "sg:province":"Bruxelles-Capitale",
    "wof:name":"A\u00cfda Allouache",
    "wof:placetype":"venue"
},
  "geometry": {"coordinates":[4.4204602242,50.8188934326],"type":"Point"}
}