{
  "type": "Feature",
  "properties": {
    "iso:country":"BE",
    "sg:address":"Stationsstraat 27",
    "sg:city":"Oosterzele (scheldewindeke)",
    "sg:classifiers":[
        {
            "category":"Shopping",
            "subcategory":"Optician",
            "type":"Retail Goods"
        }
    ],
    "sg:phone":"+32 9 362 50 61",
    "sg:postcode":"9860",
    "sg:province":"Oost-Vlaanderen",
    "sg:tags":[
        "-"
    ],
    "wof:name":"Optiro",
    "wof:placetype":"venue"
},
  "geometry": {"coordinates":[3.7823309898,50.9377784729],"type":"Point"}
}