{
  "type": "Feature",
  "properties": {
    "addr:full":"Quai De L'industrie 121 Box 2 Bruxelles (molenbeek-saint-jean) Bruxelles-Capitale 1080",
    "addr:housenumber":"121;2",
    "addr:postcode":"1080",
    "addr:street":"Quai De L'Industrie;Box",
    "iso:country":"BE",
    "sg:address":"Quai De L'industrie 121 Box 2",
    "sg:city":"Bruxelles (molenbeek-saint-jean)",
    "sg:classifiers":[
        {
            "category":"Wholesale",
            "subcategory":"Furniture",
            "type":"Manufacturing & Wholesale Goods"
        }
    ],
    "sg:phone":"+32 2 524 00 24",
    "sg:postcode":"1080",
    "sg:province":"Bruxelles-Capitale",
    "sg:tags":[
        "-",
        "collectivities"
    ],
    "wof:name":"Frezza Belgium Sa",
    "wof:placetype":"venue"
},
  "geometry": {"coordinates":[4.3273668289,50.845500946],"type":"Point"}
}