{
  "type": "Feature",
  "properties": {
    "addr:full":"Houtweg 46 Bruxelles Bruxelles-Capitale 1140",
    "addr:housenumber":"46",
    "addr:postcode":"1140",
    "addr:street":"Houtweg",
    "iso:country":"BE",
    "sg:address":"Houtweg 46",
    "sg:city":"Bruxelles",
    "sg:classifiers":[
        {
            "category":"Shopping",
            "subcategory":"Gifts & Souvenirs",
            "type":"Retail Goods"
        }
    ],
    "sg:phone":"+32 2 240 03 70",
    "sg:postcode":"1140",
    "sg:province":"Bruxelles-Capitale",
    "sg:tags":[
        "product",
        "miscellaneous"
    ],
    "wof:name":"Gemaco Nv/sa",
    "wof:placetype":"venue"
},
  "geometry": {"coordinates":[4.4071269035,50.8820533752],"type":"Point"}
}