{
  "type": "Feature",
  "properties": {
    "iso:country":"BE",
    "sg:address":"Wervikstraat 367",
    "sg:city":"Menen",
    "sg:orig_category":"Entretien and r\u00e9parations de voitures",
    "sg:phone":"+32 56 51 64 32",
    "sg:postcode":"8930",
    "sg:province":"West-Vlaanderen",
    "wof:name":"Garage Pieters",
    "wof:placetype":"venue"
},
  "geometry": {"coordinates":[3.0988359451,50.7846794128],"type":"Point"}
}