{
  "type": "Feature",
  "properties": {
    "iso:country":"BE",
    "sg:address":"Diesterstraat 247",
    "sg:city":"Tessenderlo",
    "sg:classifiers":[
        {
            "category":"Personal",
            "subcategory":"Beauty Salon",
            "type":"Services"
        }
    ],
    "sg:phone":"+32 13 66 36 12",
    "sg:postcode":"3980",
    "sg:province":"Limburg",
    "sg:tags":[
        "de",
        "coiffure"
    ],
    "wof:name":"Coiffure Vera",
    "wof:placetype":"venue"
},
  "geometry": {"coordinates":[5.0882458687,51.0536117554],"type":"Point"}
}