{
  "type": "Feature",
  "properties": {
    "iso:country":"BE",
    "sg:address":"Chauss\u00e9e De Theux 39",
    "sg:city":"Verviers (heusy)",
    "sg:classifiers":[
        {
            "category":"Shopping",
            "subcategory":"Florist",
            "type":"Retail Goods"
        }
    ],
    "sg:phone":"+32 87 22 87 00",
    "sg:postcode":"4802",
    "sg:province":"Li\u00e8ge",
    "wof:name":"Fleurs Lelarge",
    "wof:placetype":"venue"
},
  "geometry": {"coordinates":[5.8671250343,50.5714111328],"type":"Point"}
}