{
  "type": "Feature",
  "properties": {
    "addr:full":"Meersel 17 Hoogstraten (meer) Antwerpen 2321",
    "addr:housenumber":"17",
    "addr:postcode":"2321",
    "addr:street":"Meersel;Meer",
    "iso:country":"BE",
    "sg:address":"Meersel 17",
    "sg:city":"Hoogstraten (meer)",
    "sg:classifiers":[
        {
            "category":"Building & Trades",
            "subcategory":"Landscaping Services",
            "type":"Services"
        }
    ],
    "sg:phone":"+32 3 315 91 12",
    "sg:postcode":"2321",
    "sg:province":"Antwerpen",
    "sg:tags":[
        "nurseryman"
    ],
    "wof:name":"Huijbregts Robert Bvba",
    "wof:placetype":"venue"
},
  "geometry": {"coordinates":[4.7366099358,51.442325592],"type":"Point"}
}