{
  "type": "Feature",
  "properties": {
    "addr:full":"Boulevard Albert Elisabeth 49-2 Mons Hainaut 7000",
    "addr:housenumber":"49-2",
    "addr:postcode":"7000",
    "addr:street":"Boulevard Albert Elisabeth;Hainaut",
    "iso:country":"BE",
    "sg:address":"Boulevard Albert Elisabeth 49-2",
    "sg:city":"Mons",
    "sg:classifiers":[
        {
            "category":"Building & Trades",
            "subcategory":"Cleaning & Sanitation",
            "type":"Services"
        }
    ],
    "sg:phone":"+32 65 31 20 18",
    "sg:postcode":"7000",
    "sg:province":"Hainaut",
    "sg:tags":[
        "blast"
    ],
    "wof:name":"Daniel M",
    "wof:placetype":"venue"
},
  "geometry": {"coordinates":[3.9527618885,50.4466552734],"type":"Point"}
}