{
  "type": "Feature",
  "properties": {
    "iso:country":"BE",
    "sg:address":"Terbeek 40",
    "sg:city":"Sint-truiden",
    "sg:orig_category":"Studios photographiques",
    "sg:phone":"+32 11 68 55 02",
    "sg:postcode":"3800",
    "sg:province":"Limburg",
    "wof:name":"Michel De Moortel",
    "wof:placetype":"venue"
},
  "geometry": {"coordinates":[5.1774959564,50.8458976746],"type":"Point"}
}