{
  "type": "Feature",
  "properties": {
    "iso:country":"BE",
    "sg:address":"Boulevard Des Invalides 224",
    "sg:city":"Bruxelles",
    "sg:orig_category":"Activit\u00e9s r\u00e9cr\u00e9atives diverses",
    "sg:phone":"+32 2 515 33 19",
    "sg:postcode":"1160",
    "sg:province":"Bruxelles-Capitale",
    "wof:name":"Tib\u00c9checs",
    "wof:placetype":"venue"
},
  "geometry": {"coordinates":[4.4049501419,50.8182792664],"type":"Point"}
}