{
  "type": "Feature",
  "properties": {
    "addr:full":"Zonder-naamstraat 79 Gent Oost-Vlaanderen 9000",
    "addr:housenumber":"79",
    "addr:postcode":"9000",
    "addr:street":"Zonder-Naamstraat;Oost-Vlaanderen",
    "iso:country":"BE",
    "sg:address":"Zonder-naamstraat 79",
    "sg:city":"Gent",
    "sg:orig_category":"Binnenhuisarchitecten",
    "sg:phone":"+32 9 223 69 44",
    "sg:postcode":"9000",
    "sg:province":"Oost-Vlaanderen",
    "wof:name":"Philippe Vermeersch",
    "wof:placetype":"venue"
},
  "geometry": {"coordinates":[3.7344241142,51.0590286255],"type":"Point"}
}