{
  "type": "Feature",
  "properties": {
    "iso:country":"BE",
    "sg:address":"Potteriestraat 13b15",
    "sg:city":"Lichtervelde",
    "sg:orig_category":"Artsen and specialisten",
    "sg:phone":"+32 51 72 42 79",
    "sg:postcode":"8810",
    "sg:province":"West-Vlaanderen",
    "wof:name":"Marc Pareit",
    "wof:placetype":"venue"
},
  "geometry": {"coordinates":[3.1429569721,51.0276870728],"type":"Point"}
}