{
  "type": "Feature",
  "properties": {
    "addr:full":"Klokke Roelandstraat 10a Roeselare West-Vlaanderen 8800",
    "addr:housenumber":"10a",
    "addr:postcode":"8800",
    "addr:street":"Klokke Roelandstraat",
    "iso:country":"BE",
    "sg:address":"Klokke Roelandstraat 10a",
    "sg:city":"Roeselare",
    "sg:classifiers":[
        {
            "category":"Personal",
            "subcategory":"Beauty Salon",
            "type":"Services"
        }
    ],
    "sg:phone":"+32 51 20 49 13",
    "sg:postcode":"8800",
    "sg:province":"West-Vlaanderen",
    "sg:tags":[
        "lady",
        "-",
        "hairdressing"
    ],
    "wof:name":"Gilberte",
    "wof:placetype":"venue"
},
  "geometry": {"coordinates":[3.1077039242,50.9397125244],"type":"Point"}
}