{
  "type": "Feature",
  "properties": {
    "iso:country":"BE",
    "sg:address":"Stationsstraat 62",
    "sg:city":"Lanaken",
    "sg:orig_category":"Microsoft. Librairies. Journaux",
    "sg:phone":"+32 89 71 30 19",
    "sg:postcode":"3620",
    "sg:province":"Limburg",
    "wof:name":"Standaard Boekhandel Lanaken",
    "wof:placetype":"venue"
},
  "geometry": {"coordinates":[5.64854002,50.8878593445],"type":"Point"}
}