{
  "type": "Feature",
  "properties": {
    "addr:full":"Chauss\u00e9e De Bruxelles 91 Charleroi (lodelinsart) Hainaut 6042",
    "addr:housenumber":"91",
    "addr:postcode":"6042",
    "addr:street":"Chausse\u0301E De Bruxelles",
    "iso:country":"BE",
    "sg:address":"Chauss\u00e9e De Bruxelles 91",
    "sg:city":"Charleroi (lodelinsart)",
    "sg:classifiers":[
        {
            "category":"Shopping",
            "subcategory":"Gifts & Souvenirs",
            "type":"Retail Goods"
        }
    ],
    "sg:phone":"+32 71 31 38 35",
    "sg:postcode":"6042",
    "sg:province":"Hainaut",
    "sg:tags":[
        "-"
    ],
    "wof:name":"Dereume Z",
    "wof:placetype":"venue"
},
  "geometry": {"coordinates":[4.4387431145,50.4381904602],"type":"Point"}
}