{
  "type": "Feature",
  "properties": {
    "addr:full":"Grotstraat 1 Peer Limburg 3990",
    "addr:housenumber":"1",
    "addr:postcode":"3990",
    "addr:street":"Grotstraat",
    "iso:country":"BE",
    "sg:address":"Grotstraat 1",
    "sg:city":"Peer",
    "sg:orig_category":"Woningbouw",
    "sg:phone":"+32 11 79 13 79",
    "sg:postcode":"3990",
    "sg:province":"Limburg",
    "wof:name":"Bouwwerken Loos",
    "wof:placetype":"venue"
},
  "geometry": {"coordinates":[5.4451370239,51.0966644287],"type":"Point"}
}