{
  "type": "Feature",
  "properties": {
    "iso:country":"BE",
    "sg:address":"Chauss\u00c9e De Fleurus 90-94",
    "sg:city":"Charleroi (grand)",
    "sg:orig_category":"V\u00eatements de mariage and c\u00e9r\u00e9monies",
    "sg:phone":"+32 71 41 46 80",
    "sg:postcode":"6060",
    "sg:province":"Hainaut",
    "wof:name":"Prestige Couture",
    "wof:placetype":"venue"
},
  "geometry": {"coordinates":[4.4728951454,50.440486908],"type":"Point"}
}