{
  "type": "Feature",
  "properties": {
    "addr:full":"Rue Des B\u00e9guines 7 Remicourt (momalle) Li\u00e8ge 4350",
    "addr:housenumber":"7",
    "addr:postcode":"4350",
    "addr:street":"Rue Des Be\u0301Guines",
    "iso:country":"BE",
    "sg:address":"Rue Des B\u00e9guines 7",
    "sg:city":"Remicourt (momalle)",
    "sg:classifiers":[
        {
            "category":"Personal",
            "subcategory":"Beauty Salon",
            "type":"Services"
        }
    ],
    "sg:phone":"+32 4 250 25 23",
    "sg:postcode":"4350",
    "sg:province":"Li\u00e8ge",
    "sg:tags":[
        "lady",
        "-",
        "hairdressing"
    ],
    "wof:name":"Laurette",
    "wof:placetype":"venue"
},
  "geometry": {"coordinates":[5.3720788956,50.6854171753],"type":"Point"}
}