{
  "type": "Feature",
  "properties": {
    "addr:full":"Avenue Ferdinand Nicolay 1 Stavelot Li\u00e8ge 4970",
    "addr:housenumber":"1",
    "addr:postcode":"4970",
    "addr:street":"Avenue Ferdinand Nicolay",
    "iso:country":"BE",
    "sg:address":"Avenue Ferdinand Nicolay 1",
    "sg:city":"Stavelot",
    "sg:orig_category":"Pharmaciens",
    "sg:phone":"+32 80 86 20 81",
    "sg:postcode":"4970",
    "sg:province":"Li\u00e8ge",
    "wof:name":"Pharmacie Populaire",
    "wof:placetype":"venue"
},
  "geometry": {"coordinates":[5.9305210114,50.3942184448],"type":"Point"}
}