{
  "type": "Feature",
  "properties": {
    "iso:country":"BE",
    "sg:address":"Grand Rue 13",
    "sg:city":"Pecq (obigies)",
    "sg:classifiers":[
        {
            "category":"Retail",
            "subcategory":"Auto Repair",
            "type":"Services"
        }
    ],
    "sg:phone":"+32 69 23 53 12",
    "sg:postcode":"7743",
    "sg:province":"Hainaut",
    "sg:tags":[
        "breakdown",
        "automobile",
        "-",
        "recovery"
    ],
    "wof:name":"J D D\u00e9pannage",
    "wof:placetype":"venue"
},
  "geometry": {"coordinates":[3.3636109829,50.6504631042],"type":"Point"}
}