{
  "type": "Feature",
  "properties": {
    "iso:country":"BE",
    "sg:address":"Rue Emile Vandervelde 7",
    "sg:city":"Herstal",
    "sg:orig_category":"Geschenken and souvenirs Industri\u00eble wasserijen and droogkuis Textiel",
    "sg:phone":"+32 4 227 78 24",
    "sg:postcode":"4041",
    "sg:province":"Li\u00e8ge",
    "wof:name":"Nettaneuf",
    "wof:placetype":"venue"
},
  "geometry": {"coordinates":[5.5832858086,50.6730728149],"type":"Point"}
}