{
  "type": "Feature",
  "properties": {
    "iso:country":"BE",
    "sg:address":"Rue Fran\u00c7ois Vekemans 48",
    "sg:city":"Brussel/bruxelles",
    "sg:orig_category":"Cr\u00e8ches and garderies d'enfants",
    "sg:phone":"+32 2 268 21 79",
    "sg:postcode":"1120",
    "sg:province":"Bruxelles-Capitale",
    "wof:name":"Gemeentelijke Kribbe/cr\u00c8che Commun. Bruxelles",
    "wof:placetype":"venue"
},
  "geometry": {"coordinates":[4.3899149895,50.8958091736],"type":"Point"}
}