{
  "type": "Feature",
  "properties": {
    "addr:full":"Rue De Verviers 12 Eupen (grand) Li\u00e8ge 4700",
    "addr:housenumber":"12",
    "addr:postcode":"4700",
    "addr:street":"Rue De Verviers;Grand Lie\u0300Ge",
    "iso:country":"BE",
    "sg:address":"Rue De Verviers 12",
    "sg:city":"Eupen (grand)",
    "sg:orig_category":"Overheidsdiensten",
    "sg:phone":"+32 87 56 09 40",
    "sg:postcode":"4700",
    "sg:province":"Li\u00e8ge",
    "wof:name":"C.a.p.a.c",
    "wof:placetype":"venue"
},
  "geometry": {"coordinates":[6.0271477699,50.6314926147],"type":"Point"}
}