{
  "type": "Feature",
  "properties": {
    "addr:full":"Stationsstraat 24 Neerpelt Limburg 3910",
    "addr:housenumber":"24",
    "addr:postcode":"3910",
    "addr:street":"Stationsstraat",
    "iso:country":"BE",
    "sg:address":"Stationsstraat 24",
    "sg:city":"Neerpelt",
    "sg:orig_category":"Bloemen and planten",
    "sg:phone":"+32 11 64 71 04",
    "sg:postcode":"3910",
    "sg:province":"Limburg",
    "wof:name":"Erides",
    "wof:placetype":"venue"
},
  "geometry": {"coordinates":[5.4354839325,51.2270393372],"type":"Point"}
}