{
  "type": "Feature",
  "properties": {
    "addr:full":"Rue Sauvegarde 2 Yvoir Namur 5530",
    "addr:housenumber":"2",
    "addr:postcode":"5530",
    "addr:street":"Rue Sauvegarde",
    "iso:country":"BE",
    "sg:address":"Rue Sauvegarde 2",
    "sg:city":"Yvoir",
    "sg:classifiers":[
        {
            "category":"Farming",
            "subcategory":"Livestock Farm",
            "type":"Manufacturing & Wholesale Goods"
        }
    ],
    "sg:phone":"+32 82 61 15 01",
    "sg:postcode":"5530",
    "sg:province":"Namur",
    "sg:tags":[
        "poultry",
        "rabbit"
    ],
    "wof:name":"Albert Y",
    "wof:placetype":"venue"
},
  "geometry": {"coordinates":[4.9119901657,50.320438385],"type":"Point"}
}