{
  "type": "Feature",
  "properties": {
    "addr:full":"Quai Des Ardennes 160 Li\u00e8ge 1 (ch\u00ean\u00e9e) Li\u00e8ge 4032",
    "addr:housenumber":"160;1",
    "addr:postcode":"4032",
    "addr:street":"Quai Des Ardennes",
    "iso:country":"BE",
    "sg:address":"Quai Des Ardennes 160",
    "sg:city":"Li\u00e8ge 1 (ch\u00ean\u00e9e)",
    "sg:classifiers":[
        {
            "category":"Banks & Credit Unions",
            "subcategory":"Financial Services",
            "type":"Services"
        }
    ],
    "sg:phone":"+32 4 371 97 77",
    "sg:postcode":"4032",
    "sg:province":"Li\u00e8ge",
    "sg:tags":[
        "loan",
        "mortgage"
    ],
    "wof:name":"Chapelier Philippe Techni",
    "wof:placetype":"venue"
},
  "geometry": {"coordinates":[5.6103401184,50.6147155762],"type":"Point"}
}