{
  "type": "Feature",
  "properties": {
    "iso:country":"BE",
    "sg:address":"Rue Stain 17",
    "sg:city":"Sombreffe",
    "sg:orig_category":"Rundveehouders",
    "sg:phone":"+32 71 88 83 74",
    "sg:postcode":"5140",
    "sg:province":"Namur",
    "wof:name":"Bernard Chaufouraux",
    "wof:placetype":"venue"
},
  "geometry": {"coordinates":[4.5962610245,50.5241661072],"type":"Point"}
}