{
  "type": "Feature",
  "properties": {
    "addr:full":"Vissenstraat 11 Erpe-mere Oost-Vlaanderen 9420",
    "addr:housenumber":"11",
    "addr:postcode":"9420",
    "addr:street":"Vissenstraat",
    "iso:country":"BE",
    "sg:address":"Vissenstraat 11",
    "sg:city":"Erpe-mere",
    "sg:orig_category":"Eleveurs de bovins",
    "sg:phone":"+32 53 80 56 35",
    "sg:postcode":"9420",
    "sg:province":"Oost-Vlaanderen",
    "wof:name":"Marcel De Rycke",
    "wof:placetype":"venue"
},
  "geometry": {"coordinates":[3.9324440956,50.9396324158],"type":"Point"}
}