{
  "type": "Feature",
  "properties": {
    "addr:full":"Tuyaertsstraat 77 Boom Antwerpen 2850",
    "addr:housenumber":"77",
    "addr:postcode":"2850",
    "addr:street":"Tuyaertsstraat",
    "iso:country":"BE",
    "sg:address":"Tuyaertsstraat 77",
    "sg:city":"Boom",
    "sg:classifiers":[
        {
            "category":"Shopping",
            "subcategory":"Baby Store",
            "type":"Retail Goods"
        }
    ],
    "sg:phone":"+32 3 843 30 05",
    "sg:postcode":"2850",
    "sg:province":"Antwerpen",
    "sg:tags":[
        "-",
        "accessory"
    ],
    "wof:name":"Het Land Van Ooit",
    "wof:placetype":"venue"
},
  "geometry": {"coordinates":[4.3696899414,51.0868415833],"type":"Point"}
}