{
  "type": "Feature",
  "properties": {
    "iso:country":"BE",
    "sg:address":"Hoogveld 3",
    "sg:city":"Dendermonde (sint-gillis-bij-dendermonde)",
    "sg:classifiers":[
        {
            "category":"Professional",
            "subcategory":"Accounting & Tax Preparation",
            "type":"Services"
        }
    ],
    "sg:phone":"+32 52 21 25 35",
    "sg:postcode":"9200",
    "sg:province":"Oost-Vlaanderen",
    "sg:tags":[
        "bookkeeper"
    ],
    "wof:name":"Fiscalcul Nv",
    "wof:placetype":"venue"
},
  "geometry": {"coordinates":[4.1313247681,51.0365867615],"type":"Point"}
}