{
  "type": "Feature",
  "properties": {
    "iso:country":"BE",
    "sg:address":"Kleine Wingerd 4",
    "sg:city":"Lanaken",
    "sg:classifiers":[
        {
            "category":"Health Services",
            "subcategory":"Health Practitioner",
            "type":"Services"
        }
    ],
    "sg:phone":"+32 89 71 42 02",
    "sg:postcode":"3620",
    "sg:province":"Limburg",
    "sg:tags":[
        "physiotherapist"
    ],
    "wof:name":"Willen Luc",
    "wof:placetype":"venue"
},
  "geometry": {"coordinates":[5.656689167,50.8956680298],"type":"Point"}
}