{
  "type": "Feature",
  "properties": {
    "addr:full":"Burg J Eerdekenstraat 35 Leuven Vlaams-Brabant 3001",
    "addr:housenumber":"35",
    "addr:postcode":"3001",
    "addr:street":"Burg;Eerdekenstraat",
    "iso:country":"BE",
    "sg:address":"Burg J Eerdekenstraat 35",
    "sg:city":"Leuven",
    "sg:orig_category":"Diverse bedrijfsbeheeradviesbureaus",
    "sg:phone":"+32 16 23 04 99",
    "sg:postcode":"3001",
    "sg:province":"Vlaams-Brabant",
    "wof:name":"Lammens Consulting & Marketing",
    "wof:placetype":"venue"
},
  "geometry": {"coordinates":[4.6959400177,50.8633499146],"type":"Point"}
}