{
  "type": "Feature",
  "properties": {
    "iso:country":"BE",
    "sg:address":"Meirestraat 18",
    "sg:city":"Kruishoutem",
    "sg:classifiers":[
        {
            "category":"Utilities",
            "subcategory":"Fuel Oil & Lpg",
            "type":"Services"
        }
    ],
    "sg:phone":"+32 9 388 87 50",
    "sg:postcode":"9770",
    "sg:province":"Oost-Vlaanderen",
    "wof:name":"Holvoet Lumato",
    "wof:placetype":"venue"
},
  "geometry": {"coordinates":[3.4691359997,50.9007072449],"type":"Point"}
}