{
  "type": "Feature",
  "properties": {
    "addr:full":"Generaal De Ceuninckstraat 85 Mechelen Antwerpen 2800",
    "addr:housenumber":"85",
    "addr:postcode":"2800",
    "addr:street":"Generaal De Ceuninckstraat",
    "iso:country":"BE",
    "sg:address":"Generaal De Ceuninckstraat 85",
    "sg:city":"Mechelen",
    "sg:classifiers":[
        {
            "category":"Professional",
            "subcategory":"Computer Services",
            "type":"Services"
        }
    ],
    "sg:phone":"+32 3 651 40 12",
    "sg:postcode":"2800",
    "sg:province":"Antwerpen",
    "sg:tags":[
        "-",
        "processing",
        "data",
        "software"
    ],
    "wof:name":"P J Engineering Bvba",
    "wof:placetype":"venue"
},
  "geometry": {"coordinates":[4.4790787697,51.0353431702],"type":"Point"}
}