{
  "type": "Feature",
  "properties": {
    "addr:full":"Mechelsesteenweg 1099 Herent Vlaams-Brabant 3020",
    "addr:housenumber":"1099",
    "addr:postcode":"3020",
    "addr:street":"Mechelsesteenweg",
    "iso:country":"BE",
    "sg:address":"Mechelsesteenweg 1099",
    "sg:city":"Herent",
    "sg:orig_category":"Stations-service and carburants. Combustibles. Entretien and r\u00e9parations de voitures",
    "sg:phone":"+32 16 49 00 25",
    "sg:postcode":"3020",
    "sg:province":"Vlaams-Brabant",
    "wof:name":"Esso",
    "wof:placetype":"venue"
},
  "geometry": {"coordinates":[4.64812994,50.9203414917],"type":"Point"}
}