{
  "type": "Feature",
  "properties": {
    "addr:full":"Papenaardekenstraat 241 Schoten Antwerpen 2900",
    "addr:housenumber":"241",
    "addr:postcode":"2900",
    "addr:street":"Papenaardekenstraat",
    "iso:country":"BE",
    "sg:address":"Papenaardekenstraat 241",
    "sg:city":"Schoten",
    "sg:orig_category":"Moteurs, transformateurs and groupes \u00e9lectrog\u00e8nes Fab",
    "sg:phone":"+32 3 685 13 09",
    "sg:postcode":"2900",
    "sg:province":"Antwerpen",
    "wof:name":"De Backer - Van Stappen",
    "wof:placetype":"venue"
},
  "geometry": {"coordinates":[4.484000206,51.2450294495],"type":"Point"}
}