{
  "type": "Feature",
  "properties": {
    "addr:full":"Wijnegemsteenweg 46 Wommelgem Antwerpen 2160",
    "addr:housenumber":"46",
    "addr:postcode":"2160",
    "addr:street":"Wijnegemsteenweg",
    "iso:country":"BE",
    "sg:address":"Wijnegemsteenweg 46",
    "sg:city":"Wommelgem",
    "sg:classifiers":[
        {
            "category":"Banks & Credit Unions",
            "subcategory":"Investment Brokerage",
            "type":"Services"
        }
    ],
    "sg:phone":"+32 3 353 12 68",
    "sg:postcode":"2160",
    "sg:province":"Antwerpen",
    "sg:tags":[
        "fence"
    ],
    "wof:name":"Van Winckel R",
    "wof:placetype":"venue"
},
  "geometry": {"coordinates":[4.5291872025,51.2102851868],"type":"Point"}
}