{
  "type": "Feature",
  "properties": {
    "addr:full":"H\u00dctte 79b3 Eupen Li\u00e8ge 4700",
    "addr:housenumber":"79b3",
    "addr:postcode":"4700",
    "addr:street":"Hu\u0308Tte",
    "iso:country":"BE",
    "sg:address":"H\u00dctte 79b3",
    "sg:city":"Eupen",
    "sg:orig_category":"Ordinateurs and \u00e9quipement informatique",
    "sg:phone":"+32 87 59 30 50",
    "sg:postcode":"4700",
    "sg:province":"Li\u00e8ge",
    "wof:name":"Fa. Albat Und Wirsam",
    "wof:placetype":"venue"
},
  "geometry": {"coordinates":[6.0449099541,50.6149787903],"type":"Point"}
}