{
  "type": "Feature",
  "properties": {
    "iso:country":"BE",
    "sg:address":"Rue De L'enseignement 27",
    "sg:city":"Fleurus",
    "sg:orig_category":"HUISBRANDOLIE",
    "sg:phone":"+32 71 81 76 86",
    "sg:postcode":"6220",
    "sg:province":"Hainaut",
    "wof:name":"Luc Genevrois",
    "wof:placetype":"venue"
},
  "geometry": {"coordinates":[4.5474638939,50.4793968201],"type":"Point"}
}