{
  "type": "Feature",
  "properties": {
    "addr:full":"Avenue Des Pruniers 3 Ans (alleur) Li\u00e8ge 4432",
    "addr:housenumber":"3",
    "addr:postcode":"4432",
    "addr:street":"Avenue Des Pruniers",
    "iso:country":"BE",
    "sg:address":"Avenue Des Pruniers 3",
    "sg:city":"Ans (alleur)",
    "sg:classifiers":[
        {
            "category":"Building & Trades",
            "subcategory":"Equipment Rental",
            "type":"Services"
        }
    ],
    "sg:phone":"+32 4 246 20 47",
    "sg:postcode":"4432",
    "sg:province":"Li\u00e8ge",
    "sg:tags":[
        "tableware",
        "-"
    ],
    "wof:name":"Remy R",
    "wof:placetype":"venue"
},
  "geometry": {"coordinates":[5.5090651512,50.6772613525],"type":"Point"}
}