{
  "type": "Feature",
  "properties": {
    "iso:country":"BE",
    "sg:address":"Brusselstraat 286",
    "sg:city":"Dilbeek",
    "sg:orig_category":"Traitements param\u00e9dicaux",
    "sg:phone":"+32 2 463 07 75",
    "sg:postcode":"1702",
    "sg:province":"Vlaams-Brabant",
    "wof:name":"Tineke Quaghebeur",
    "wof:placetype":"venue"
},
  "geometry": {"coordinates":[4.2598648071,50.8711357117],"type":"Point"}
}