{
  "type": "Feature",
  "properties": {
    "addr:full":"Mangelaarstraat 39 Langemark-poelkapelle (langemark) West-Vlaanderen 8920",
    "addr:housenumber":"39",
    "addr:postcode":"8920",
    "addr:street":"Mangelaarstraat",
    "iso:country":"BE",
    "sg:address":"Mangelaarstraat 39",
    "sg:city":"Langemark-poelkapelle (langemark)",
    "sg:classifiers":[
        {
            "category":"Wholesale",
            "subcategory":"Scrap",
            "type":"Manufacturing & Wholesale Goods"
        }
    ],
    "sg:phone":"+32 57 48 95 10",
    "sg:postcode":"8920",
    "sg:province":"West-Vlaanderen",
    "sg:tags":[
        "metal"
    ],
    "wof:name":"Noyelle D",
    "wof:placetype":"venue"
},
  "geometry": {"coordinates":[2.9094650745,50.9346923828],"type":"Point"}
}