{
  "type": "Feature",
  "properties": {
    "addr:full":"Spijkerlaan 98 Waregem West-Vlaanderen 8791",
    "addr:housenumber":"98",
    "addr:postcode":"8791",
    "addr:street":"Spijkerlaan",
    "iso:country":"BE",
    "sg:address":"Spijkerlaan 98",
    "sg:city":"Waregem",
    "sg:orig_category":"P\u00e9pini\u00e9ristes",
    "sg:phone":"+32 56 71 94 76",
    "sg:postcode":"8791",
    "sg:province":"West-Vlaanderen",
    "wof:name":"Kurth Viaene",
    "wof:placetype":"venue"
},
  "geometry": {"coordinates":[3.3449380398,50.863067627],"type":"Point"}
}