{
  "type": "Feature",
  "properties": {
    "addr:full":"Rue Henri Maus 156 Li\u00e8ge 1 Li\u00e8ge 4000",
    "addr:housenumber":"156;1",
    "addr:postcode":"4000",
    "addr:street":"Rue Henri Maus",
    "iso:country":"BE",
    "sg:address":"Rue Henri Maus 156",
    "sg:city":"Li\u00e8ge 1",
    "sg:classifiers":[
        {
            "category":"Health Services",
            "subcategory":"Health Practitioner",
            "type":"Services"
        }
    ],
    "sg:phone":"+32 496 85 26 92",
    "sg:postcode":"4000",
    "sg:province":"Li\u00e8ge",
    "sg:tags":[
        "psychologist"
    ],
    "wof:name":"Gutmacher",
    "wof:placetype":"venue"
},
  "geometry": {"coordinates":[5.5526452065,50.6314086914],"type":"Point"}
}