{
  "type": "Feature",
  "properties": {
    "addr:full":"Rue Du Jauviat 37 Yvoir Namur 5530",
    "addr:housenumber":"37",
    "addr:postcode":"5530",
    "addr:street":"Rue Du Jauviat",
    "iso:country":"BE",
    "sg:address":"Rue Du Jauviat 37",
    "sg:city":"Yvoir",
    "sg:classifiers":[
        {
            "category":"Building & Trades",
            "subcategory":"Electrical",
            "type":"Services"
        }
    ],
    "sg:phone":"+32 82 61 28 22",
    "sg:postcode":"5530",
    "sg:province":"Namur",
    "sg:tags":[
        "electric",
        "-",
        "housewiring",
        "contractor"
    ],
    "wof:name":"Louvet S",
    "wof:placetype":"venue"
},
  "geometry": {"coordinates":[4.9055871964,50.3210983276],"type":"Point"}
}