{
  "type": "Feature",
  "properties": {
    "addr:full":"Wersbeekstraat 25 Tielt-winge Vlaams-Brabant 3391",
    "addr:housenumber":"25",
    "addr:postcode":"3391",
    "addr:street":"Wersbeekstraat",
    "iso:country":"BE",
    "sg:address":"Wersbeekstraat 25",
    "sg:city":"Tielt-winge",
    "sg:orig_category":"Installation de menuiserie en bois and plastique",
    "sg:phone":"+32 16 63 18 09",
    "sg:postcode":"3391",
    "sg:province":"Vlaams-Brabant",
    "wof:name":"Houtcomfort",
    "wof:placetype":"venue"
},
  "geometry": {"coordinates":[4.9282550812,50.9001159668],"type":"Point"}
}