{
  "type": "Feature",
  "properties": {
    "addr:full":"Rue Adelin Colon 76-2 Wavre Brabant Wallon 1300",
    "addr:housenumber":"76-2;1300",
    "addr:street":"Rue Adelin Colon",
    "iso:country":"BE",
    "sg:address":"Rue Adelin Colon 76-2",
    "sg:city":"Wavre",
    "sg:classifiers":[
        {
            "category":"Professional",
            "subcategory":"Accounting & Tax Preparation",
            "type":"Services"
        }
    ],
    "sg:phone":"+32 10 22 71 06",
    "sg:postcode":"1300",
    "sg:province":"Brabant Wallon",
    "sg:tags":[
        "bookkeeper"
    ],
    "wof:name":"G\u00e9rard J",
    "wof:placetype":"venue"
},
  "geometry": {"coordinates":[4.6144919395,50.7211952209],"type":"Point"}
}