{
  "type": "Feature",
  "properties": {
    "addr:full":"Place Henri Hallet 3 Hannut Li\u00e8ge 4280",
    "addr:housenumber":"3",
    "addr:postcode":"4280",
    "addr:street":"Place Henri Hallet",
    "iso:country":"BE",
    "sg:address":"Place Henri Hallet 3",
    "sg:city":"Hannut",
    "sg:orig_category":"Bijouteries and horlogeries. Opticiens. R\u00e9parations d'horloges, montres and bijoux",
    "sg:phone":"+32 19 51 18 78",
    "sg:postcode":"4280",
    "sg:province":"Li\u00e8ge",
    "wof:name":"Hardenne Davin",
    "wof:placetype":"venue"
},
  "geometry": {"coordinates":[5.0788497925,50.6715431213],"type":"Point"}
}