{
  "type": "Feature",
  "properties": {
    "addr:full":"Avenue Du Pesage 81 Elsene/ixelles Bruxelles-Capitale 1050",
    "addr:housenumber":"81",
    "addr:postcode":"1050",
    "addr:street":"Avenue Du Pesage",
    "iso:country":"BE",
    "sg:address":"Avenue Du Pesage 81",
    "sg:city":"Elsene/ixelles",
    "sg:orig_category":"M\u00e9decins and sp\u00e9cialistes",
    "sg:phone":"+32 2 640 63 91",
    "sg:postcode":"1050",
    "sg:province":"Bruxelles-Capitale",
    "wof:name":"Lucien Fumi\u00c8re",
    "wof:placetype":"venue"
},
  "geometry": {"coordinates":[4.3873939514,50.8076896667],"type":"Point"}
}