{
  "type": "Feature",
  "properties": {
    "iso:country":"BE",
    "sg:address":"Waterpoort 2b11",
    "sg:city":"Kortrijk",
    "sg:orig_category":"Slagers",
    "sg:phone":"+32 56 20 18 10",
    "sg:postcode":"8500",
    "sg:province":"West-Vlaanderen",
    "wof:name":"Slagerij Demessemaeker",
    "wof:placetype":"venue"
},
  "geometry": {"coordinates":[3.2640039921,50.8263778687],"type":"Point"}
}