{
  "type": "Feature",
  "properties": {
    "iso:country":"BE",
    "sg:address":"Zeeweg 56",
    "sg:city":"Brugge",
    "sg:orig_category":"Quincailleries",
    "sg:phone":"+32 50 39 06 00",
    "sg:postcode":"8200",
    "sg:province":"West-Vlaanderen",
    "wof:name":"De Quant P",
    "wof:placetype":"venue"
},
  "geometry": {"coordinates":[3.1704800129,51.1675186157],"type":"Point"}
}