{
  "type": "Feature",
  "properties": {
    "iso:country":"BE",
    "sg:address":"Rue De Crespin 105b",
    "sg:city":"Hensies",
    "sg:classifiers":[
        {
            "category":"Food & Beverages",
            "subcategory":"Liquor & Beverages",
            "type":"Retail Goods"
        }
    ],
    "sg:phone":"+32 65 43 02 70",
    "sg:postcode":"7350",
    "sg:province":"Hainaut",
    "sg:tags":[
        "-",
        "spirit",
        "wine"
    ],
    "wof:name":"Delvaux-decrucq M-p",
    "wof:placetype":"venue"
},
  "geometry": {"coordinates":[3.6788918972,50.4252128601],"type":"Point"}
}