{
  "type": "Feature",
  "properties": {
    "iso:country":"BE",
    "sg:address":"Rue Du Petit Dra\u00e7on 3",
    "sg:city":"Namur (naninne)",
    "sg:classifiers":[
        {
            "category":"Professional",
            "subcategory":"Accounting & Tax Preparation",
            "type":"Services"
        }
    ],
    "sg:phone":"+32 81 40 15 65",
    "sg:postcode":"5100",
    "sg:province":"Namur",
    "sg:tags":[
        "bookkeeper"
    ],
    "wof:name":"Fidurec Sprl",
    "wof:placetype":"venue"
},
  "geometry": {"coordinates":[4.8713750839,50.4566345215],"type":"Point"}
}