{
  "type": "Feature",
  "properties": {
    "iso:country":"BE",
    "sg:address":"Hoogstraat 102",
    "sg:city":"Meise (wolvertem)",
    "sg:classifiers":[
        {
            "category":"Retail",
            "subcategory":"Auto Repair",
            "type":"Services"
        }
    ],
    "sg:phone":"+32 2 269 29 85",
    "sg:postcode":"1861",
    "sg:province":"Vlaams-Brabant",
    "sg:tags":[
        "garage"
    ],
    "wof:name":"Lucien De Mulder Bvba",
    "wof:placetype":"venue"
},
  "geometry": {"coordinates":[4.3142180443,50.9554367065],"type":"Point"}
}