{
  "type": "Feature",
  "properties": {
    "iso:country":"BE",
    "sg:address":"Jan Mahieustraat 13",
    "sg:city":"Roeselare",
    "sg:classifiers":[
        {
            "category":"Personal",
            "subcategory":"Nail Salon",
            "type":"Services"
        }
    ],
    "sg:phone":"+32 51 20 48 55",
    "sg:postcode":"8800",
    "sg:province":"West-Vlaanderen",
    "sg:tags":[
        "pedicure"
    ],
    "wof:name":"Sibelle Bvba",
    "wof:placetype":"venue"
},
  "geometry": {"coordinates":[3.1269319057,50.9471893311],"type":"Point"}
}