{
  "type": "Feature",
  "properties": {
    "addr:full":"Rue Hubin 2a Wavre (limal) Brabant Wallon 1300",
    "addr:housenumber":"2a",
    "addr:postcode":"1300",
    "addr:street":"Rue Hubin;Wallon",
    "iso:country":"BE",
    "sg:address":"Rue Hubin 2a",
    "sg:city":"Wavre (limal)",
    "sg:classifiers":[
        {
            "category":"Building & Trades",
            "subcategory":"Landscaping Services",
            "type":"Services"
        }
    ],
    "sg:phone":"+32 10 43 90 70",
    "sg:postcode":"1300",
    "sg:province":"Brabant Wallon",
    "sg:tags":[
        "access",
        "pond",
        "laying-out",
        "-"
    ],
    "wof:name":"Aquatic Design & Creation Sprl",
    "wof:placetype":"venue"
},
  "geometry": {"coordinates":[4.6116552353,50.7134132385],"type":"Point"}
}