{
  "type": "Feature",
  "properties": {
    "iso:country":"BE",
    "sg:address":"Place De La R\u00c9publique Fran\u00c7aise 31",
    "sg:city":"Li\u00c8ge",
    "sg:classifiers":[
        {
            "category":"Fast Food",
            "type":"Food & Drink"
        }
    ],
    "sg:phone":"+32 4 222 33 02",
    "sg:postcode":"4000",
    "sg:province":"Li\u00e8ge",
    "sg:tags":[
        "\u00c0",
        "emporter",
        "restaurants"
    ],
    "wof:name":"Mcdonald's",
    "wof:placetype":"venue"
},
  "geometry": {"coordinates":[5.5720849037,50.6430664062],"type":"Point"}
}