{
  "type": "Feature",
  "properties": {
    "addr:full":"Rozenlaan 29 Sint-katelijne-waver (onze-lieve-vrouw-waver) Antwerpen 2861",
    "addr:housenumber":"29",
    "addr:postcode":"2861",
    "addr:street":"Rozenlaan",
    "iso:country":"BE",
    "sg:address":"Rozenlaan 29",
    "sg:city":"Sint-katelijne-waver (onze-lieve-vrouw-waver)",
    "sg:classifiers":[
        {
            "category":"Health Services",
            "subcategory":"Health Practitioner",
            "type":"Services"
        }
    ],
    "sg:phone":"+32 15 55 18 39",
    "sg:postcode":"2861",
    "sg:province":"Antwerpen",
    "sg:tags":[
        "physiotherapist"
    ],
    "wof:name":"Van Den Broeck F",
    "wof:placetype":"venue"
},
  "geometry": {"coordinates":[4.5803399086,51.0623168945],"type":"Point"}
}