{
  "type": "Feature",
  "properties": {
    "addr:full":"Woudstraat 1 Genk Limburg 3600",
    "addr:housenumber":"1",
    "addr:postcode":"3600",
    "addr:street":"Woudstraat",
    "iso:country":"BE",
    "sg:address":"Woudstraat 1",
    "sg:city":"Genk",
    "sg:classifiers":[
        {
            "category":"Science Facility",
            "type":"Public Place"
        }
    ],
    "sg:phone":"+32 89 38 69 79",
    "sg:postcode":"3600",
    "sg:province":"Limburg",
    "sg:tags":[
        "commerce",
        "installation",
        "gr",
        "equipement",
        "pour",
        "r\u00e9sidentielle",
        "\u00e9lectrique",
        "diver"
    ],
    "wof:name":"Freskimo",
    "wof:placetype":"venue"
},
  "geometry": {"coordinates":[5.485060215,51.0081291199],"type":"Point"}
}