{
  "type": "Feature",
  "properties": {
    "iso:country":"BE",
    "sg:address":"Rodeweg 41",
    "sg:city":"Dendermonde",
    "sg:orig_category":"Producteurs de l\u00e9gumes",
    "sg:phone":"+32 52 22 34 35",
    "sg:postcode":"9200",
    "sg:province":"Oost-Vlaanderen",
    "wof:name":"Marc Vermeir",
    "wof:placetype":"venue"
},
  "geometry": {"coordinates":[4.0885691643,51.014415741],"type":"Point"}
}