{
  "type": "Feature",
  "properties": {
    "addr:full":"Torhoutsesteenweg 187 Zedelgem West-Vlaanderen 8210",
    "addr:housenumber":"187",
    "addr:postcode":"8210",
    "addr:street":"Torhoutsesteenweg",
    "iso:country":"BE",
    "sg:address":"Torhoutsesteenweg 187",
    "sg:city":"Zedelgem",
    "sg:orig_category":"Meubles D\u00e9taillants, Am\u00e9nagement de B\u00e2timents et de Cuisines. Articles pour b\u00e9b\u00e9s. V\u00eatements pour b\u00e9",
    "sg:phone":"+32 50 24 04 24",
    "sg:postcode":"8210",
    "sg:province":"West-Vlaanderen",
    "wof:name":"Knuffel",
    "wof:placetype":"venue"
},
  "geometry": {"coordinates":[3.1576468945,51.1365127563],"type":"Point"}
}