{
  "type": "Feature",
  "properties": {
    "iso:country":"BE",
    "sg:address":"Molenweg 29",
    "sg:city":"Linter",
    "sg:orig_category":"Fruitteelt",
    "sg:phone":"+32 11 78 26 89",
    "sg:postcode":"3350",
    "sg:province":"Vlaams-Brabant",
    "wof:name":"Bortholomeus Beelen",
    "wof:placetype":"venue"
},
  "geometry": {"coordinates":[5.0409579277,50.8457984924],"type":"Point"}
}