{
  "type": "Feature",
  "properties": {
    "addr:full":"Poincar\u00c9laan 50 Anderlecht Bruxelles-Capitale 1070",
    "addr:housenumber":"50",
    "addr:postcode":"1070",
    "addr:street":"Poincare\u0301Laan",
    "iso:country":"BE",
    "sg:address":"Poincar\u00c9laan 50",
    "sg:city":"Anderlecht",
    "sg:orig_category":"Voertuigen",
    "sg:phone":"+32 2 527 96 58",
    "sg:postcode":"1070",
    "sg:province":"Bruxelles-Capitale",
    "wof:name":"C.t.",
    "wof:placetype":"venue"
},
  "geometry": {"coordinates":[4.3390522003,50.8429374695],"type":"Point"}
}