{
  "type": "Feature",
  "properties": {
    "addr:full":"Rue Jules Destr\u00c9e 53 Aiseau-presles Hainaut 6250",
    "addr:housenumber":"53",
    "addr:postcode":"6250",
    "addr:street":"Rue Jules Destre\u0301E;Hainaut",
    "iso:country":"BE",
    "sg:address":"Rue Jules Destr\u00c9e 53",
    "sg:city":"Aiseau-presles",
    "sg:classifiers":[
        {
            "category":"Autos & Motor Vehicles",
            "subcategory":"Fuel & Gas Station",
            "type":"Retail Goods"
        }
    ],
    "sg:phone":"+32 71 77 73 24",
    "sg:postcode":"6250",
    "sg:province":"Hainaut",
    "sg:tags":[
        "stations-service",
        "carburants"
    ],
    "wof:name":"Joseph Alardo",
    "wof:placetype":"venue"
},
  "geometry": {"coordinates":[4.5720238686,50.4231338501],"type":"Point"}
}