{
  "type": "Feature",
  "properties": {
    "addr:full":"Harelbeekstraat 27 Zwevegem West-Vlaanderen 8550",
    "addr:housenumber":"27",
    "addr:postcode":"8550",
    "addr:street":"Harelbeekstraat",
    "iso:country":"BE",
    "sg:address":"Harelbeekstraat 27",
    "sg:city":"Zwevegem",
    "sg:orig_category":"Boucheries",
    "sg:phone":"+32 56 75 51 28",
    "sg:postcode":"8550",
    "sg:province":"West-Vlaanderen",
    "wof:name":"Peter Desmet",
    "wof:placetype":"venue"
},
  "geometry": {"coordinates":[3.331289053,50.814250946],"type":"Point"}
}