{
  "type": "Feature",
  "properties": {
    "iso:country":"BE",
    "sg:address":"Haantjen 41a",
    "sg:city":"Assenede (bassevelde)",
    "sg:classifiers":[
        {
            "category":"Professional",
            "subcategory":"Engineering",
            "type":"Services"
        }
    ],
    "sg:phone":"+32 9 373 52 47",
    "sg:postcode":"9968",
    "sg:province":"Oost-Vlaanderen",
    "sg:tags":[
        "workshop"
    ],
    "wof:name":"Ames Bvba",
    "wof:placetype":"venue"
},
  "geometry": {"coordinates":[3.6887938976,51.1923027039],"type":"Point"}
}