{
  "type": "Feature",
  "properties": {
    "iso:country":"BE",
    "sg:address":"Nijverheidsstraat 6",
    "sg:city":"Diksmuide",
    "sg:classifiers":[
        {
            "category":"Transit Center",
            "subcategory":"Freight",
            "type":"Transportation"
        }
    ],
    "sg:phone":"+32 51 50 44 05",
    "sg:postcode":"8600",
    "sg:province":"West-Vlaanderen",
    "sg:tags":[
        "import",
        "export",
        "-"
    ],
    "wof:name":"Angelique Industries Bvba",
    "wof:placetype":"venue"
},
  "geometry": {"coordinates":[2.861385107,51.0269088745],"type":"Point"}
}