{
  "type": "Feature",
  "properties": {
    "addr:full":"Rue St.-vincent De Paul 7 Namur Namur 5000",
    "addr:housenumber":"7",
    "addr:postcode":"5000",
    "addr:street":"Rue St.-Vincent De Paul",
    "iso:country":"BE",
    "sg:address":"Rue St.-vincent De Paul 7",
    "sg:city":"Namur",
    "sg:orig_category":"Kapsalons",
    "sg:phone":"+32 81 22 65 75",
    "sg:postcode":"5000",
    "sg:province":"Namur",
    "wof:name":"Coiffure Monique",
    "wof:placetype":"venue"
},
  "geometry": {"coordinates":[4.8617630005,50.4657287598],"type":"Point"}
}