{
  "type": "Feature",
  "properties": {
    "addr:full":"Av.des Pagodes 352 Bruxelles Bruxelles-Capitale 1020",
    "addr:housenumber":"352",
    "addr:postcode":"1020",
    "addr:street":"Pagodes",
    "iso:country":"BE",
    "sg:address":"Av.des Pagodes 352",
    "sg:city":"Bruxelles",
    "sg:orig_category":"Fleurs and plantes",
    "sg:phone":"+32 2 268 19 93",
    "sg:postcode":"1020",
    "sg:province":"Bruxelles-Capitale",
    "wof:name":"Fleurs Et Passion",
    "wof:placetype":"venue"
},
  "geometry": {"coordinates":[4.3626379967,50.8956832886],"type":"Point"}
}