{
  "type": "Feature",
  "properties": {
    "addr:full":"Antwerpsestraat 315 Boom Antwerpen 2850",
    "addr:housenumber":"315",
    "addr:postcode":"2850",
    "addr:street":"Antwerpsestraat",
    "iso:country":"BE",
    "sg:address":"Antwerpsestraat 315",
    "sg:city":"Boom",
    "sg:classifiers":[
        {
            "category":"Communications",
            "subcategory":"Film & Video Production",
            "type":"Services"
        }
    ],
    "sg:phone":"+32 3 844 40 89",
    "sg:postcode":"2850",
    "sg:province":"Antwerpen",
    "sg:tags":[
        "realisation",
        "-"
    ],
    "wof:name":"Weirdo Activity",
    "wof:placetype":"venue"
},
  "geometry": {"coordinates":[4.3672089577,51.1000747681],"type":"Point"}
}