{
  "type": "Feature",
  "properties": {
    "iso:country":"BE",
    "sg:address":"Dennenlaan 61",
    "sg:city":"Schilde",
    "sg:classifiers":[
        {
            "category":"Home & Garden",
            "subcategory":"Building Materials",
            "type":"Retail Goods"
        }
    ],
    "sg:phone":"+32 3 213 02 86",
    "sg:postcode":"2970",
    "sg:province":"Antwerpen",
    "sg:tags":[
        "wall",
        "cupboard"
    ],
    "wof:name":"Pr 7",
    "wof:placetype":"venue"
},
  "geometry": {"coordinates":[4.5821208954,51.2472724915],"type":"Point"}
}