{
  "type": "Feature",
  "properties": {
    "iso:country":"BE",
    "sg:address":"Weerterweg 1",
    "sg:city":"Bocholt",
    "sg:classifiers":[
        {
            "category":"Airport",
            "subcategory":"International",
            "type":"Transportation"
        }
    ],
    "sg:phone":"+32 89 46 49 51",
    "sg:postcode":"3950",
    "sg:province":"Limburg",
    "sg:tags":[
        "-",
        "transport"
    ],
    "wof:name":"Heynickx Leon Bvba",
    "wof:placetype":"venue"
},
  "geometry": {"coordinates":[5.5858311653,51.1801605225],"type":"Point"}
}