{
  "type": "Feature",
  "properties": {
    "iso:country":"BE",
    "sg:address":"Rue De La P\u00c9pini\u00c8re 13",
    "sg:city":"Eghez\u00c9e",
    "sg:orig_category":"Etalage- and showroomontwerpers",
    "sg:phone":"+32 81 81 31 10",
    "sg:postcode":"5310",
    "sg:province":"Namur",
    "wof:name":"Accipio",
    "wof:placetype":"venue"
},
  "geometry": {"coordinates":[4.9457578659,50.5908126831],"type":"Point"}
}