{
  "type": "Feature",
  "properties": {
    "iso:country":"BE",
    "sg:address":"Berghomstraat 2",
    "sg:city":"Gooik",
    "sg:orig_category":"Installation de menuiserie en bois and plastique",
    "sg:phone":"+32 54 56 82 58",
    "sg:postcode":"1755",
    "sg:province":"Vlaams-Brabant",
    "wof:name":"Marc Cochez",
    "wof:placetype":"venue"
},
  "geometry": {"coordinates":[4.1002349854,50.7679824829],"type":"Point"}
}