{
  "type": "Feature",
  "properties": {
    "iso:country":"BE",
    "sg:address":"Groenestraat 69",
    "sg:city":"Blankenberge",
    "sg:orig_category":"Enseignement maternel and primaire",
    "sg:phone":"+32 50 41 14 74",
    "sg:postcode":"8370",
    "sg:province":"West-Vlaanderen",
    "wof:name":"B.s.g.o. Zilvermeeuw",
    "wof:placetype":"venue"
},
  "geometry": {"coordinates":[3.1375129223,51.3142433167],"type":"Point"}
}