{
  "type": "Feature",
  "properties": {
    "addr:full":"Pastoor Cooremansstraat 5 Dilbeek Vlaams-Brabant 1702",
    "addr:housenumber":"5",
    "addr:postcode":"1702",
    "addr:street":"Pastoor Cooremansstraat",
    "iso:country":"BE",
    "sg:address":"Pastoor Cooremansstraat 5",
    "sg:city":"Dilbeek",
    "sg:orig_category":"Location de voitures. D\u00e9m\u00e9nagements. Location de v\u00e9hicules sauf voitures",
    "sg:phone":"+32 2 463 11 47",
    "sg:postcode":"1702",
    "sg:province":"Vlaams-Brabant",
    "wof:name":"Dockx",
    "wof:placetype":"venue"
},
  "geometry": {"coordinates":[4.2844200134,50.8748512268],"type":"Point"}
}