{
  "type": "Feature",
  "properties": {
    "iso:country":"BE",
    "sg:address":"Mechelsesteenweg 239 Box 10",
    "sg:city":"Lier",
    "sg:classifiers":[
        {
            "category":"Professional",
            "subcategory":"Engineering",
            "type":"Services"
        }
    ],
    "sg:phone":"+32 3 488 52 26",
    "sg:postcode":"2500",
    "sg:province":"Antwerpen",
    "sg:tags":[
        "technical",
        "industrial",
        "-",
        "subcontracting"
    ],
    "wof:name":"Tack Albert Bvba",
    "wof:placetype":"venue"
},
  "geometry": {"coordinates":[4.5481348038,51.1234397888],"type":"Point"}
}