{
  "type": "Feature",
  "properties": {
    "iso:country":"BE",
    "sg:address":"Hauptstrasse 75",
    "sg:city":"Raeren",
    "sg:classifiers":[
        {
            "category":"Insurance",
            "subcategory":"Insurance Agent",
            "type":"Services"
        }
    ],
    "sg:phone":"+32 87 85 19 59",
    "sg:postcode":"4730",
    "sg:province":"Li\u00e8ge",
    "sg:tags":[
        "verzekeringsmakelaars",
        "expert"
    ],
    "wof:name":"B\u00dcro Hellemans-thissen",
    "wof:placetype":"venue"
},
  "geometry": {"coordinates":[6.1129670143,50.6745872498],"type":"Point"}
}