{
  "type": "Feature",
  "properties": {
    "addr:full":"Blvd E Jacqmain 162 Bruxelles Bruxelles-Capitale 1210",
    "addr:housenumber":"162",
    "addr:postcode":"1210",
    "addr:street":"Blvd E Jacqmain",
    "iso:country":"BE",
    "sg:address":"Blvd E Jacqmain 162",
    "sg:city":"Bruxelles",
    "sg:classifiers":[
        {
            "category":"Banks & Credit Unions",
            "subcategory":"Bank",
            "type":"Services"
        }
    ],
    "sg:phone":"+32 11 22 69 41",
    "sg:postcode":"1210",
    "sg:province":"Bruxelles-Capitale",
    "wof:name":"Paribas Bank Belgie Nv, (banque Paribas Belgique Sa)",
    "wof:placetype":"venue"
},
  "geometry": {"coordinates":[5.3338909149,50.9284133911],"type":"Point"}
}