{
  "type": "Feature",
  "properties": {
    "iso:country":"BE",
    "sg:address":"Brugstraat 11",
    "sg:city":"Bilzen",
    "sg:classifiers":[
        {
            "category":"Cafe",
            "type":"Food & Drink"
        }
    ],
    "sg:phone":"+32 89 41 71 11",
    "sg:postcode":"3740",
    "sg:province":"Limburg",
    "sg:tags":[
        "caf\u00e9s"
    ],
    "wof:name":"De Kroeg",
    "wof:placetype":"venue"
},
  "geometry": {"coordinates":[5.5174651146,50.8692779541],"type":"Point"}
}