{
  "type": "Feature",
  "properties": {
    "addr:full":"Huidevettersstraat 36 Houthalen-helchteren (houthalen) Limburg 3530",
    "addr:housenumber":"36",
    "addr:postcode":"3530",
    "addr:street":"Huidevettersstraat",
    "iso:country":"BE",
    "sg:address":"Huidevettersstraat 36",
    "sg:city":"Houthalen-helchteren (houthalen)",
    "sg:classifiers":[
        {
            "category":"Government",
            "subcategory":"Office",
            "type":"Public Place"
        }
    ],
    "sg:phone":"+32 11 52 27 92",
    "sg:postcode":"3530",
    "sg:province":"Limburg",
    "sg:tags":[
        "-",
        "tourism",
        "federation"
    ],
    "wof:name":"Loeky Stek",
    "wof:placetype":"venue"
},
  "geometry": {"coordinates":[5.3965859413,51.0271568298],"type":"Point"}
}