{
  "type": "Feature",
  "properties": {
    "addr:full":"Witvenstr 163 Hoevenen Antwerpen 2940",
    "addr:housenumber":"163",
    "addr:postcode":"2940",
    "addr:street":"Hoevenen Antwerpen",
    "iso:country":"BE",
    "sg:address":"Witvenstr 163",
    "sg:city":"Hoevenen",
    "sg:classifiers":[
        {
            "category":"Manufacturing",
            "subcategory":"Building Materials",
            "type":"Manufacturing & Wholesale Goods"
        }
    ],
    "sg:phone":"+32 3 664 60 91",
    "sg:postcode":"2940",
    "sg:province":"Antwerpen",
    "sg:tags":[
        "glass",
        "ceramic"
    ],
    "wof:name":"Brouwers Bvba",
    "wof:placetype":"venue"
},
  "geometry": {"coordinates":[4.4095950127,51.3091468811],"type":"Point"}
}