{
  "type": "Feature",
  "properties": {
    "addr:full":"Gasthuisstraat 10 Ranst Antwerpen 2520",
    "addr:housenumber":"10",
    "addr:postcode":"2520",
    "addr:street":"Gasthuisstraat",
    "iso:country":"BE",
    "sg:address":"Gasthuisstraat 10",
    "sg:city":"Ranst",
    "sg:orig_category":"Woningbouw",
    "sg:phone":"+32 3 485 55 41",
    "sg:postcode":"2520",
    "sg:province":"Antwerpen",
    "wof:name":"G. Nagels",
    "wof:placetype":"venue"
},
  "geometry": {"coordinates":[4.5594129562,51.18983078],"type":"Point"}
}