{
  "type": "Feature",
  "properties": {
    "addr:full":"Beukenlaan 39 Herentals Antwerpen 2200",
    "addr:housenumber":"39",
    "addr:postcode":"2200",
    "addr:street":"Beukenlaan",
    "iso:country":"BE",
    "sg:address":"Beukenlaan 39",
    "sg:city":"Herentals",
    "sg:orig_category":"Installation de menuiserie en bois and plastique",
    "sg:phone":"+32 14 21 92 41",
    "sg:postcode":"2200",
    "sg:province":"Antwerpen",
    "wof:name":"Wipe Wood",
    "wof:placetype":"venue"
},
  "geometry": {"coordinates":[4.8295369148,51.1646575928],"type":"Point"}
}