{
  "type": "Feature",
  "properties": {
    "iso:country":"BE",
    "sg:address":"Rue De L'invasion 7",
    "sg:city":"Limbourg",
    "sg:orig_category":"Bouwmaterialen Gh Hout and afgeleiden Gh Houtbewerking and -behandeling IJzerwaren, bouw- and verfma",
    "sg:phone":"+32 87 76 31 11",
    "sg:postcode":"4834",
    "sg:province":"Li\u00e8ge",
    "wof:name":"E. Zimmermann",
    "wof:placetype":"venue"
},
  "geometry": {"coordinates":[5.9711608887,50.6022224426],"type":"Point"}
}