{
  "type": "Feature",
  "properties": {
    "addr:full":"Kokerstraat 13 Genk Limburg 3600",
    "addr:housenumber":"13",
    "addr:postcode":"3600",
    "addr:street":"Kokerstraat",
    "iso:country":"BE",
    "sg:address":"Kokerstraat 13",
    "sg:city":"Genk",
    "sg:orig_category":"M\u00e9decins and sp\u00e9cialistes",
    "sg:phone":"+32 89 35 24 69",
    "sg:postcode":"3600",
    "sg:province":"Limburg",
    "wof:name":"W. Van De Casseye",
    "wof:placetype":"venue"
},
  "geometry": {"coordinates":[5.5380129814,50.97448349],"type":"Point"}
}