{
  "type": "Feature",
  "properties": {
    "iso:country":"BE",
    "sg:address":"Chauss\u00c9e De Bruxelles 553",
    "sg:city":"Les Bons Villers",
    "sg:orig_category":"Notarissen",
    "sg:phone":"+32 71 85 24 44",
    "sg:postcode":"6210",
    "sg:province":"Hainaut",
    "wof:name":"Marie-france Meunier",
    "wof:placetype":"venue"
},
  "geometry": {"coordinates":[4.4511561394,50.5378227234],"type":"Point"}
}