{
  "type": "Feature",
  "properties": {
    "iso:country":"BE",
    "sg:address":"Rue De Fl\u00c9ron 20",
    "sg:city":"Fleron",
    "sg:orig_category":"Charpentes and couvertures. Installation de menuiserie en bois and plastique",
    "sg:phone":"+32 4 358 84 00",
    "sg:postcode":"4623",
    "sg:province":"Li\u00e8ge",
    "wof:name":"Robert Selles",
    "wof:placetype":"venue"
},
  "geometry": {"coordinates":[5.6799798012,50.6048316956],"type":"Point"}
}