{
  "type": "Feature",
  "properties": {
    "addr:full":"Kromveldstraatje 25 Evergem Oost-Vlaanderen 9940",
    "addr:housenumber":"25",
    "addr:postcode":"9940",
    "addr:street":"Kromveldstraatje;Oost-Vlaanderen",
    "iso:country":"BE",
    "sg:address":"Kromveldstraatje 25",
    "sg:city":"Evergem",
    "sg:orig_category":"Rundveehouders Varkenskwekers",
    "sg:phone":"+32 9 357 38 89",
    "sg:postcode":"9940",
    "sg:province":"Oost-Vlaanderen",
    "wof:name":"De Wispelaere E. & G.",
    "wof:placetype":"venue"
},
  "geometry": {"coordinates":[3.6743459702,51.1156387329],"type":"Point"}
}