{
  "type": "Feature",
  "properties": {
    "iso:country":"BE",
    "sg:address":"Heirweg 26",
    "sg:city":"Zulte (groot)",
    "sg:classifiers":[
        {
            "category":"Restaurant",
            "type":"Food & Drink"
        }
    ],
    "sg:phone":"+32 9 388 84 45",
    "sg:postcode":"9870",
    "sg:province":"Oost-Vlaanderen",
    "sg:tags":[
        "brasserie"
    ],
    "wof:name":"Brouwerij Damberd",
    "wof:placetype":"venue"
},
  "geometry": {"coordinates":[3.4654409885,50.9385871887],"type":"Point"}
}