{
  "type": "Feature",
  "properties": {
    "addr:full":"Rue Provinciale 244b7 Wavre Brabant Wallon 1301",
    "addr:housenumber":"1301",
    "addr:street":"Rue Provinciale 244B7",
    "iso:country":"BE",
    "sg:address":"Rue Provinciale 244b7",
    "sg:city":"Wavre",
    "sg:orig_category":"Secr\u00e9tariats. Composition and photogravure",
    "sg:phone":"+32 10 40 15 63",
    "sg:postcode":"1301",
    "sg:province":"Brabant Wallon",
    "wof:name":"D Finition X",
    "wof:placetype":"venue"
},
  "geometry": {"coordinates":[4.5893211365,50.7059822083],"type":"Point"}
}