{
  "type": "Feature",
  "properties": {
    "addr:full":"Chauss\u00c9e De Mons 199 Anderlecht Bruxelles-Capitale 1170",
    "addr:housenumber":"199",
    "addr:postcode":"1170",
    "addr:street":"Chausse\u0301E De Mons",
    "iso:country":"BE",
    "sg:address":"Chauss\u00c9e De Mons 199",
    "sg:city":"Anderlecht",
    "sg:orig_category":"Electrom\u00e9nager, t\u00e9l\u00e9visions and radios",
    "sg:phone":"+32 2 524 46 88",
    "sg:postcode":"1170",
    "sg:province":"Bruxelles-Capitale",
    "wof:name":"A.b. Electric",
    "wof:placetype":"venue"
},
  "geometry": {"coordinates":[4.3289561272,50.8414115906],"type":"Point"}
}