{
  "type": "Feature",
  "properties": {
    "iso:country":"BE",
    "sg:address":"Steenvoordedreef 106",
    "sg:city":"Destelbergen (heusden)",
    "sg:classifiers":[
        {
            "category":"Building & Trades",
            "subcategory":"Electrical",
            "type":"Services"
        }
    ],
    "sg:phone":"+32 9 230 26 76",
    "sg:postcode":"9070",
    "sg:province":"Oost-Vlaanderen",
    "sg:tags":[
        "-",
        "electric",
        "contractor"
    ],
    "wof:name":"Leytens Bvba",
    "wof:placetype":"venue"
},
  "geometry": {"coordinates":[3.8047471046,51.0238380432],"type":"Point"}
}