{
  "type": "Feature",
  "properties": {
    "addr:full":"Nijverheidslaan 19 Wevelgem West-Vlaanderen 8560",
    "addr:housenumber":"19",
    "addr:postcode":"8560",
    "addr:street":"Nijverheidslaan",
    "iso:country":"BE",
    "sg:address":"Nijverheidslaan 19",
    "sg:city":"Wevelgem",
    "sg:orig_category":"Fabrication and montage de mobilier",
    "sg:phone":"+32 56 42 51 59",
    "sg:postcode":"8560",
    "sg:province":"West-Vlaanderen",
    "wof:name":"Rifo",
    "wof:placetype":"venue"
},
  "geometry": {"coordinates":[3.1840379238,50.8496818542],"type":"Point"}
}