{
  "type": "Feature",
  "properties": {
    "iso:country":"BE",
    "sg:address":"Ledegemstraat 18b",
    "sg:city":"Moorslede (dadizele)",
    "sg:classifiers":[
        {
            "category":"Shopping",
            "subcategory":"Clothing, Apparel, & Fashions",
            "type":"Retail Goods"
        }
    ],
    "sg:phone":"+32 56 50 65 99",
    "sg:postcode":"8890",
    "sg:province":"West-Vlaanderen",
    "sg:tags":[
        "-",
        "clothing",
        "child"
    ],
    "wof:name":"Daddy's Baby",
    "wof:placetype":"venue"
},
  "geometry": {"coordinates":[3.0983989239,50.852230072],"type":"Point"}
}