{
  "type": "Feature",
  "properties": {
    "iso:country":"BE",
    "sg:address":"Avenue De La Gare 67",
    "sg:city":"Hotton",
    "sg:orig_category":"M\u00e9decins and sp\u00e9cialistes",
    "sg:phone":"+32 84 46 63 86",
    "sg:postcode":"6990",
    "sg:province":"Luxembourg",
    "wof:name":"Dominique Torbeyns",
    "wof:placetype":"venue"
},
  "geometry": {"coordinates":[5.439209938,50.2756614685],"type":"Point"}
}