{
  "type": "Feature",
  "properties": {
    "addr:full":"Rue J.b. Desmeth 44 Evere Bruxelles-Capitale 1140",
    "addr:housenumber":"44",
    "addr:postcode":"1140",
    "addr:street":"Rue J.B. Desmeth",
    "iso:country":"BE",
    "sg:address":"Rue J.b. Desmeth 44",
    "sg:city":"Evere",
    "sg:orig_category":"Installation de menuiserie m\u00e9tallique",
    "sg:phone":"+32 2 241 69 55",
    "sg:postcode":"1140",
    "sg:province":"Bruxelles-Capitale",
    "wof:name":"Heymbeeck",
    "wof:placetype":"venue"
},
  "geometry": {"coordinates":[4.4025449753,50.8722229004],"type":"Point"}
}