{
  "type": "Feature",
  "properties": {
    "addr:full":"Kortrijkse Poortstraat 207 Gent Oost-Vlaanderen 9000",
    "addr:housenumber":"207",
    "addr:postcode":"9000",
    "addr:street":"Kortrijkse Poortstraat;Oost-Vlaanderen",
    "iso:country":"BE",
    "sg:address":"Kortrijkse Poortstraat 207",
    "sg:city":"Gent",
    "sg:orig_category":"Epiceries",
    "sg:postcode":"9000",
    "sg:province":"Oost-Vlaanderen",
    "wof:name":"Automatische Muurwinkel",
    "wof:placetype":"venue"
},
  "geometry": {"coordinates":[3.7222790718,51.0448074341],"type":"Point"}
}