{
  "type": "Feature",
  "properties": {
    "addr:full":"Rue Mandart 48 Quaregnon Hainaut 7390",
    "addr:housenumber":"48",
    "addr:postcode":"7390",
    "addr:street":"Rue Mandart",
    "iso:country":"BE",
    "sg:address":"Rue Mandart 48",
    "sg:city":"Quaregnon",
    "sg:orig_category":"Slagers",
    "sg:phone":"+32 65 78 33 28",
    "sg:postcode":"7390",
    "sg:province":"Hainaut",
    "wof:name":"Gaston Roland",
    "wof:placetype":"venue"
},
  "geometry": {"coordinates":[3.8663799763,50.4374084473],"type":"Point"}
}