{
  "type": "Feature",
  "properties": {
    "addr:full":"Legrandlaan 76 Elsene/ixelles Bruxelles-Capitale 1050",
    "addr:housenumber":"76",
    "addr:postcode":"1050",
    "addr:street":"Legrandlaan",
    "iso:country":"BE",
    "sg:address":"Legrandlaan 76",
    "sg:city":"Elsene/ixelles",
    "sg:orig_category":"Artiesten and kunstenaars",
    "sg:phone":"+32 2 649 11 41",
    "sg:postcode":"1050",
    "sg:province":"Bruxelles-Capitale",
    "wof:name":"Albert Burns",
    "wof:placetype":"venue"
},
  "geometry": {"coordinates":[4.3685588837,50.8149337769],"type":"Point"}
}