{
  "type": "Feature",
  "properties": {
    "iso:country":"BE",
    "sg:address":"Rue De Mornimont 5",
    "sg:city":"Floreffe",
    "sg:orig_category":"Bloemen and planten",
    "sg:phone":"+32 81 44 40 53",
    "sg:postcode":"5150",
    "sg:province":"Namur",
    "wof:name":"F. Fleurs",
    "wof:placetype":"venue"
},
  "geometry": {"coordinates":[4.7309999466,50.440246582],"type":"Point"}
}