{
  "type": "Feature",
  "properties": {
    "addr:full":"Rue Constant Deraedt 18 Wavre Brabant Wallon 1300",
    "addr:housenumber":"18;1300",
    "addr:street":"Rue Constant Deraedt",
    "iso:country":"BE",
    "sg:address":"Rue Constant Deraedt 18",
    "sg:city":"Wavre",
    "sg:classifiers":[
        {
            "category":"Personal",
            "subcategory":"Shoe Repair & Shine",
            "type":"Services"
        }
    ],
    "sg:phone":"+32 10 22 61 90",
    "sg:postcode":"1300",
    "sg:province":"Brabant Wallon",
    "sg:tags":[
        "shoemaker"
    ],
    "wof:name":"Luc",
    "wof:placetype":"venue"
},
  "geometry": {"coordinates":[4.6108169556,50.715511322],"type":"Point"}
}