{
  "type": "Feature",
  "properties": {
    "addr:full":"De Zevenster 36 Schilde ('s Gravenwezel) Antwerpen 2970",
    "addr:housenumber":"36",
    "addr:postcode":"2970",
    "addr:street":"De Zevenster;S",
    "iso:country":"BE",
    "sg:address":"De Zevenster 36",
    "sg:city":"Schilde ('s Gravenwezel)",
    "sg:classifiers":[
        {
            "category":"Professional",
            "subcategory":"Engineering",
            "type":"Services"
        }
    ],
    "sg:phone":"+32 3 353 94 54",
    "sg:postcode":"2970",
    "sg:province":"Antwerpen",
    "sg:tags":[
        "-"
    ],
    "wof:name":"O.b.a.s.",
    "wof:placetype":"venue"
},
  "geometry": {"coordinates":[4.5528521538,51.2347488403],"type":"Point"}
}