{
  "type": "Feature",
  "properties": {
    "iso:country":"BE",
    "sg:address":"Rodter Strasse 49",
    "sg:city":"Sankt Vith",
    "sg:classifiers":[
        {
            "category":"Building & Trades",
            "subcategory":"Construction",
            "type":"Services"
        }
    ],
    "sg:phone":"+32 80 22 10 42",
    "sg:postcode":"4780",
    "sg:province":"Li\u00e8ge",
    "sg:tags":[
        "carpenter"
    ],
    "wof:name":"Lehnen",
    "wof:placetype":"venue"
},
  "geometry": {"coordinates":[6.1102972031,50.2816505432],"type":"Point"}
}