{
  "type": "Feature",
  "properties": {
    "iso:country":"BE",
    "sg:address":"Koninginnelaan 22",
    "sg:city":"Oostende",
    "sg:orig_category":"Newspapers, magazines, periodicals - Distribution",
    "sg:phone":"+32 59 51 33 20",
    "sg:postcode":"8400",
    "sg:province":"West-Vlaanderen",
    "wof:name":"John",
    "wof:placetype":"venue"
},
  "geometry": {"coordinates":[2.9068350792,51.2257804871],"type":"Point"}
}