{
  "type": "Feature",
  "properties": {
    "iso:country":"BE",
    "sg:address":"Pottebezemstraat 20",
    "sg:city":"Torhout",
    "sg:orig_category":"Loodgieterij, verwarming and sanitaire installaties",
    "sg:phone":"+32 50 21 25 64",
    "sg:postcode":"8820",
    "sg:province":"West-Vlaanderen",
    "wof:name":"Vandewalle H",
    "wof:placetype":"venue"
},
  "geometry": {"coordinates":[3.1187460423,51.0828170776],"type":"Point"}
}