{
  "type": "Feature",
  "properties": {
    "addr:full":"Rue De La Goffe 24 Liege-centre Li\u00e8ge 4000",
    "addr:housenumber":"24",
    "addr:postcode":"4000",
    "addr:street":"Rue De La Goffe",
    "iso:country":"BE",
    "sg:address":"Rue De La Goffe 24",
    "sg:city":"Liege-centre",
    "sg:orig_category":"Diensten voor huisdieren Huisdieren and benodigdheden Royal Canin",
    "sg:phone":"+32 4 223 43 79",
    "sg:postcode":"4000",
    "sg:province":"Li\u00e8ge",
    "wof:name":"Sprl Lagi",
    "wof:placetype":"venue"
},
  "geometry": {"coordinates":[6.2250900269,44.0888595581],"type":"Point"}
}