{
  "type": "Feature",
  "properties": {
    "addr:full":"Rue Monplaisir 22 Beloeil Hainaut 7972",
    "addr:housenumber":"22",
    "addr:postcode":"7972",
    "addr:street":"Rue Monplaisir",
    "iso:country":"BE",
    "sg:address":"Rue Monplaisir 22",
    "sg:city":"Beloeil",
    "sg:orig_category":"Pain, p\u00e2tisseries and confiseries",
    "sg:phone":"+32 69 68 83 69",
    "sg:postcode":"7972",
    "sg:province":"Hainaut",
    "wof:name":"Olivier Pitton",
    "wof:placetype":"venue"
},
  "geometry": {"coordinates":[3.6712739468,50.5593948364],"type":"Point"}
}