{
  "type": "Feature",
  "properties": {
    "iso:country":"BE",
    "sg:address":"Konkelstraat 155",
    "sg:city":"Sint-pieters-woluwe/woluwe-saint-pierre",
    "sg:orig_category":"Artsen and specialisten",
    "sg:phone":"+32 2 762 10 01",
    "sg:postcode":"1150",
    "sg:province":"Bruxelles-Capitale",
    "wof:name":"Mich\u00c8le Piron",
    "wof:placetype":"venue"
},
  "geometry": {"coordinates":[4.4475970268,50.8388900757],"type":"Point"}
}