{
  "type": "Feature",
  "properties": {
    "addr:full":"Boulevard Audent 58 Charleroi Hainaut 6000",
    "addr:housenumber":"58",
    "addr:postcode":"6000",
    "addr:street":"Boulevard Audent;Hainaut",
    "iso:country":"BE",
    "sg:address":"Boulevard Audent 58",
    "sg:city":"Charleroi",
    "sg:orig_category":"Openbare bibliotheken and archieven",
    "sg:phone":"+32 71 31 41 06",
    "sg:postcode":"6000",
    "sg:province":"Hainaut",
    "wof:name":"Biblioth\u00c8que E. Baussart",
    "wof:placetype":"venue"
},
  "geometry": {"coordinates":[4.447206974,50.4084243774],"type":"Point"}
}