{
  "type": "Feature",
  "properties": {
    "addr:full":"Vismarkt 20 Westerlo Antwerpen 2260",
    "addr:housenumber":"20",
    "addr:postcode":"2260",
    "addr:street":"Vismarkt",
    "iso:country":"BE",
    "sg:address":"Vismarkt 20",
    "sg:city":"Westerlo",
    "sg:orig_category":"Cr\u00e9dits divers",
    "sg:postcode":"2260",
    "sg:province":"Antwerpen",
    "wof:name":"Bancontact-mister Cash",
    "wof:placetype":"venue"
},
  "geometry": {"coordinates":[4.9156827927,51.0863265991],"type":"Point"}
}