{
  "type": "Feature",
  "properties": {
    "addr:full":"Grote Baan 94 Hulshout Antwerpen 2235",
    "addr:housenumber":"94",
    "addr:postcode":"2235",
    "addr:street":"Grote Baan",
    "iso:country":"BE",
    "sg:address":"Grote Baan 94",
    "sg:city":"Hulshout",
    "sg:classifiers":[
        {
            "category":"Insurance",
            "subcategory":"Life Insurance",
            "type":"Services"
        }
    ],
    "sg:phone":"+32 15 22 21 98",
    "sg:postcode":"2235",
    "sg:province":"Antwerpen",
    "sg:tags":[
        "assurance"
    ],
    "wof:name":"Kantoor Celen",
    "wof:placetype":"venue"
},
  "geometry": {"coordinates":[4.7876272202,51.0762367249],"type":"Point"}
}