{
  "type": "Feature",
  "properties": {
    "addr:full":"Koning Leopoldlaan 16 Westerlo Antwerpen 2260",
    "addr:housenumber":"16",
    "addr:postcode":"2260",
    "addr:street":"Koning Leopoldlaan",
    "iso:country":"BE",
    "sg:address":"Koning Leopoldlaan 16",
    "sg:city":"Westerlo",
    "sg:orig_category":"Biens d'occasion",
    "sg:phone":"+32 14 54 13 75",
    "sg:postcode":"2260",
    "sg:province":"Antwerpen",
    "wof:name":"Huis Tweede Handje",
    "wof:placetype":"venue"
},
  "geometry": {"coordinates":[4.9098920822,51.0857543945],"type":"Point"}
}