{
  "type": "Feature",
  "properties": {
    "addr:full":"Steenweg 231 Nazareth (eke) Oost-Vlaanderen 9810",
    "addr:housenumber":"231",
    "addr:postcode":"9810",
    "addr:street":"Steenweg",
    "iso:country":"BE",
    "sg:address":"Steenweg 231",
    "sg:city":"Nazareth (eke)",
    "sg:classifiers":[
        {
            "category":"Bars & Pubs",
            "type":"Food & Drink"
        }
    ],
    "sg:phone":"+32 9 385 54 74",
    "sg:postcode":"9810",
    "sg:province":"Oost-Vlaanderen",
    "sg:tags":[
        "tavern"
    ],
    "wof:name":"Bonaparte",
    "wof:placetype":"venue"
},
  "geometry": {"coordinates":[3.5967800617,50.9596405029],"type":"Point"}
}