{
  "type": "Feature",
  "properties": {
    "addr:full":"Omgangstraat 43 Zingem Oost-Vlaanderen 9750",
    "addr:housenumber":"43",
    "addr:postcode":"9750",
    "addr:street":"Omgangstraat",
    "iso:country":"BE",
    "sg:address":"Omgangstraat 43",
    "sg:city":"Zingem",
    "sg:classifiers":[
        {
            "category":"Banks & Credit Unions",
            "subcategory":"Investment Brokerage",
            "type":"Services"
        }
    ],
    "sg:phone":"+32 9 384 01 09",
    "sg:postcode":"9750",
    "sg:province":"Oost-Vlaanderen",
    "sg:tags":[
        "remediation",
        "soil",
        "protection"
    ],
    "wof:name":"Vandeputte L",
    "wof:placetype":"venue"
},
  "geometry": {"coordinates":[3.6619091034,50.9013252258],"type":"Point"}
}