{
  "type": "Feature",
  "properties": {
    "addr:full":"Zonnedauwlaan 6 Schoten Antwerpen 2900",
    "addr:housenumber":"6",
    "addr:postcode":"2900",
    "addr:street":"Zonnedauwlaan",
    "iso:country":"BE",
    "sg:address":"Zonnedauwlaan 6",
    "sg:city":"Schoten",
    "sg:orig_category":"Parfumeries",
    "sg:phone":"+32 3 685 13 98",
    "sg:postcode":"2900",
    "sg:province":"Antwerpen",
    "wof:name":"Nadine Theeus",
    "wof:placetype":"venue"
},
  "geometry": {"coordinates":[4.5086197853,51.2604637146],"type":"Point"}
}