{
  "type": "Feature",
  "properties": {
    "iso:country":"BE",
    "sg:address":"Rue Alphonse Jaumain 9",
    "sg:city":"Profondeville",
    "sg:orig_category":"Artsen and specialisten",
    "sg:phone":"+32 81 41 14 13",
    "sg:postcode":"5170",
    "sg:province":"Namur",
    "wof:name":"Louis Fronville",
    "wof:placetype":"venue"
},
  "geometry": {"coordinates":[4.8672041893,50.3769035339],"type":"Point"}
}