{
  "type": "Feature",
  "properties": {
    "addr:full":"Baron Ruzettelaan 102 Brugge (assebroek) West-Vlaanderen 8310",
    "addr:housenumber":"102",
    "addr:postcode":"8310",
    "addr:street":"Baron Ruzettelaan",
    "iso:country":"BE",
    "sg:address":"Baron Ruzettelaan 102",
    "sg:city":"Brugge (assebroek)",
    "sg:classifiers":[
        {
            "category":"Professional",
            "subcategory":"Computer Services",
            "type":"Services"
        }
    ],
    "sg:phone":"+32 50 67 06 58",
    "sg:postcode":"8310",
    "sg:province":"West-Vlaanderen",
    "sg:tags":[
        "webdesign",
        "-",
        "internet"
    ],
    "wof:name":"Digicreate.be Bvba",
    "wof:placetype":"venue"
},
  "geometry": {"coordinates":[3.2317109108,51.1935424805],"type":"Point"}
}