{
  "type": "Feature",
  "properties": {
    "addr:full":"Brechtsebaan 36 Schoten Antwerpen 2900",
    "addr:housenumber":"36",
    "addr:postcode":"2900",
    "addr:street":"Brechtsebaan",
    "iso:country":"BE",
    "sg:address":"Brechtsebaan 36",
    "sg:city":"Schoten",
    "sg:orig_category":"Canalisation",
    "sg:phone":"+32 3 658 39 00",
    "sg:postcode":"2900",
    "sg:province":"Antwerpen",
    "wof:name":"Vebor Nv",
    "wof:placetype":"venue"
},
  "geometry": {"coordinates":[4.5115399361,51.2656555176],"type":"Point"}
}