{
  "type": "Feature",
  "properties": {
    "iso:country":"BE",
    "sg:address":"Oudstrijdersstraat 23",
    "sg:city":"Ranst",
    "sg:orig_category":"Plaatsen van vloer- and muurbekleding",
    "sg:phone":"+32 3 383 31 29",
    "sg:postcode":"2520",
    "sg:province":"Antwerpen",
    "wof:name":"Marc Sebrechts",
    "wof:placetype":"venue"
},
  "geometry": {"coordinates":[4.5945820808,51.2117004395],"type":"Point"}
}