{
  "type": "Feature",
  "properties": {
    "iso:country":"BE",
    "sg:address":"Tollaan 87",
    "sg:city":"Zaventem (sint-stevens-woluwe)",
    "sg:classifiers":[
        {
            "category":"Manufacturing",
            "subcategory":"Signs",
            "type":"Manufacturing & Wholesale Goods"
        }
    ],
    "sg:phone":"+32 2 720 95 60",
    "sg:postcode":"1932",
    "sg:province":"Vlaams-Brabant",
    "sg:tags":[
        "sign-boards"
    ],
    "wof:name":"Burotex",
    "wof:placetype":"venue"
},
  "geometry": {"coordinates":[4.4311118126,50.860874176],"type":"Point"}
}