{
  "type": "Feature",
  "properties": {
    "addr:full":"Bruinbeekstraat 33 Bonheiden Antwerpen 2820",
    "addr:housenumber":"33",
    "addr:postcode":"2820",
    "addr:street":"Bruinbeekstraat",
    "iso:country":"BE",
    "sg:address":"Bruinbeekstraat 33",
    "sg:city":"Bonheiden",
    "sg:orig_category":"Grands magasins",
    "sg:phone":"+32 15 55 33 24",
    "sg:postcode":"2820",
    "sg:province":"Antwerpen",
    "wof:name":"Patrick Busschodts",
    "wof:placetype":"venue"
},
  "geometry": {"coordinates":[4.5282521248,51.0326957703],"type":"Point"}
}