{
  "type": "Feature",
  "properties": {
    "addr:full":"El Cw\u00c8ne 3 Durbuy Luxembourg 6941",
    "addr:housenumber":"3",
    "addr:postcode":"6941",
    "iso:country":"BE",
    "sg:address":"El Cw\u00c8ne 3",
    "sg:city":"Durbuy",
    "sg:classifiers":[
        {
            "category":"Restaurant",
            "type":"Food & Drink"
        }
    ],
    "sg:phone":"+32 86 49 94 62",
    "sg:postcode":"6941",
    "sg:province":"Luxembourg",
    "wof:name":"Le Grill L'etable",
    "wof:placetype":"venue"
},
  "geometry": {"coordinates":[5.5608057976,50.3466300964],"type":"Point"}
}