{
  "type": "Feature",
  "properties": {
    "iso:country":"BE",
    "sg:address":"Rue Du Chabus 2",
    "sg:city":"Virton",
    "sg:orig_category":"Mat\u00e9riaux de construction Travaux d'isolation",
    "sg:phone":"+32 63 58 25 48",
    "sg:postcode":"6760",
    "sg:province":"Luxembourg",
    "wof:name":"Seurisol",
    "wof:placetype":"venue"
},
  "geometry": {"coordinates":[5.5246829987,49.5732154846],"type":"Point"}
}