{
  "type": "Feature",
  "properties": {
    "iso:country":"BE",
    "sg:address":"Dorpsstraat 54",
    "sg:city":"Geetbets",
    "sg:classifiers":[
        {
            "category":"Bars & Pubs",
            "type":"Food & Drink"
        }
    ],
    "sg:phone":"+32 11 58 26 99",
    "sg:postcode":"3450",
    "sg:province":"Vlaams-Brabant",
    "wof:name":"Dorp ('t)",
    "wof:placetype":"venue"
},
  "geometry": {"coordinates":[5.1155247688,50.8897323608],"type":"Point"}
}