{
  "type": "Feature",
  "properties": {
    "addr:full":"Vredelaan 11 Torhout West-Vlaanderen 8820",
    "addr:housenumber":"11",
    "addr:postcode":"8820",
    "addr:street":"Vredelaan",
    "iso:country":"BE",
    "sg:address":"Vredelaan 11",
    "sg:city":"Torhout",
    "sg:classifiers":[
        {
            "category":"Retail",
            "subcategory":"Auto Repair",
            "type":"Services"
        }
    ],
    "sg:phone":"+32 50 21 24 13",
    "sg:postcode":"8820",
    "sg:province":"West-Vlaanderen",
    "sg:tags":[
        "automobile-body"
    ],
    "wof:name":"Goethals Bvba",
    "wof:placetype":"venue"
},
  "geometry": {"coordinates":[3.0920860767,51.066532135],"type":"Point"}
}