{
  "type": "Feature",
  "properties": {
    "iso:country":"BE",
    "sg:address":"Sint-bernardusstraat 6",
    "sg:city":"Hechtel-eksel",
    "sg:orig_category":"Elektrische installaties voor woningen",
    "sg:phone":"+32 11 73 29 17",
    "sg:postcode":"3941",
    "sg:province":"Limburg",
    "wof:name":"T. Mandiau",
    "wof:placetype":"venue"
},
  "geometry": {"coordinates":[5.3788671494,51.1383247375],"type":"Point"}
}