{
  "type": "Feature",
  "properties": {
    "addr:full":"Rue Albert I 4 Beyne-heusay Li\u00e8ge 4610",
    "addr:housenumber":"4",
    "addr:postcode":"4610",
    "addr:street":"Rue Albert I",
    "iso:country":"BE",
    "sg:address":"Rue Albert I 4",
    "sg:city":"Beyne-heusay",
    "sg:classifiers":[
        {
            "category":"Professional",
            "subcategory":"Lawyer & Legal Services",
            "type":"Services"
        }
    ],
    "sg:phone":"+32 4 367 60 01",
    "sg:postcode":"4610",
    "sg:province":"Li\u00e8ge",
    "sg:tags":[
        "notary"
    ],
    "wof:name":"Lahaye J Mme",
    "wof:placetype":"venue"
},
  "geometry": {"coordinates":[5.6518611908,50.6223983765],"type":"Point"}
}