{
  "type": "Feature",
  "properties": {
    "addr:full":"Borrekent 51 Haaltert (denderhoutem) Oost-Vlaanderen 9450",
    "addr:housenumber":"51",
    "addr:postcode":"9450",
    "addr:street":"Borrekent",
    "iso:country":"BE",
    "sg:address":"Borrekent 51",
    "sg:city":"Haaltert (denderhoutem)",
    "sg:classifiers":[
        {
            "category":"Health Services",
            "subcategory":"Doctor",
            "type":"Services"
        }
    ],
    "sg:phone":"+32 54 32 56 07",
    "sg:postcode":"9450",
    "sg:province":"Oost-Vlaanderen",
    "sg:tags":[
        "medicinephysicians",
        "surgeon"
    ],
    "wof:name":"De Sadeleer Carlos",
    "wof:placetype":"venue"
},
  "geometry": {"coordinates":[4.0108671188,50.8749427795],"type":"Point"}
}