{
  "type": "Feature",
  "properties": {
    "iso:country":"BE",
    "sg:address":"Nervi\u00cbrslei 20",
    "sg:city":"Schoten",
    "sg:orig_category":"Woningbouw",
    "sg:phone":"+32 3 658 72 06",
    "sg:postcode":"2900",
    "sg:province":"Antwerpen",
    "wof:name":"Hi-style",
    "wof:placetype":"venue"
},
  "geometry": {"coordinates":[4.5240859985,51.2687416077],"type":"Point"}
}