{
  "type": "Feature",
  "properties": {
    "addr:full":"Vogelhoekstraat 98 Gent (gentbrugge) Oost-Vlaanderen 9050",
    "addr:housenumber":"98",
    "addr:postcode":"9050",
    "addr:street":"Vogelhoekstraat",
    "iso:country":"BE",
    "sg:address":"Vogelhoekstraat 98",
    "sg:city":"Gent (gentbrugge)",
    "sg:classifiers":[
        {
            "category":"Organizations",
            "subcategory":"Professional Association",
            "type":"Services"
        }
    ],
    "sg:phone":"+32 9 231 00 60",
    "sg:postcode":"9050",
    "sg:province":"Oost-Vlaanderen",
    "sg:tags":[
        "artist",
        "make-up"
    ],
    "wof:name":"Declerck S",
    "wof:placetype":"venue"
},
  "geometry": {"coordinates":[3.765556097,51.0238952637],"type":"Point"}
}