{
  "type": "Feature",
  "properties": {
    "addr:full":"Rue Des D\u00c9port\u00c9s 17 Arlon Luxembourg 6700",
    "addr:housenumber":"17",
    "addr:postcode":"6700",
    "addr:street":"Rue Des De\u0301Porte\u0301S",
    "iso:country":"BE",
    "sg:address":"Rue Des D\u00c9port\u00c9s 17",
    "sg:city":"Arlon",
    "sg:orig_category":"Secr\u00e9tariats sociaux",
    "sg:phone":"+32 63 22 06 07",
    "sg:postcode":"6700",
    "sg:province":"Luxembourg",
    "wof:name":"Ucm",
    "wof:placetype":"venue"
},
  "geometry": {"coordinates":[5.8208508492,49.6791954041],"type":"Point"}
}