{
  "type": "Feature",
  "properties": {
    "addr:full":"Kreyelerstraat 38 Bocholt Limburg 3950",
    "addr:housenumber":"38",
    "addr:postcode":"3950",
    "addr:street":"Kreyelerstraat",
    "iso:country":"BE",
    "sg:address":"Kreyelerstraat 38",
    "sg:city":"Bocholt",
    "sg:orig_category":"Rundveehouders",
    "sg:phone":"+32 89 46 38 53",
    "sg:postcode":"3950",
    "sg:province":"Limburg",
    "wof:name":"Jaak Hillen",
    "wof:placetype":"venue"
},
  "geometry": {"coordinates":[5.6016778946,51.1716117859],"type":"Point"}
}