{
  "type": "Feature",
  "properties": {
    "addr:full":"Square De Quinaux 26 Namur (wierde) Namur 5100",
    "addr:housenumber":"26",
    "addr:postcode":"5100",
    "addr:street":"Square De Quinaux",
    "iso:country":"BE",
    "sg:address":"Square De Quinaux 26",
    "sg:city":"Namur (wierde)",
    "sg:classifiers":[
        {
            "category":"Retail",
            "subcategory":"Repair Shop",
            "type":"Services"
        }
    ],
    "sg:phone":"+32 496 31 91 92",
    "sg:postcode":"5100",
    "sg:province":"Namur",
    "sg:tags":[
        "-",
        "mainten",
        "watch",
        "clock"
    ],
    "wof:name":"Atelier D'horlogerie",
    "wof:placetype":"venue"
},
  "geometry": {"coordinates":[4.8713750839,50.4566345215],"type":"Point"}
}