{
  "type": "Feature",
  "properties": {
    "addr:full":"Molenstraat 10 Assenede Oost-Vlaanderen 9960",
    "addr:housenumber":"10",
    "addr:postcode":"9960",
    "addr:street":"Molenstraat",
    "iso:country":"BE",
    "sg:address":"Molenstraat 10",
    "sg:city":"Assenede",
    "sg:orig_category":"Diensten voor huisdieren Huisdieren and benodigdheden Royal Canin Sport- and kampeermateriaal",
    "sg:phone":"+32 9 344 70 36",
    "sg:postcode":"9960",
    "sg:province":"Oost-Vlaanderen",
    "wof:name":"Quality Animales",
    "wof:placetype":"venue"
},
  "geometry": {"coordinates":[3.7503430843,51.226184845],"type":"Point"}
}