{
  "type": "Feature",
  "properties": {
    "addr:full":"Rue De La Cloche 5 Amay Li\u00e8ge 4540",
    "addr:housenumber":"5",
    "addr:postcode":"4540",
    "addr:street":"Rue De La Cloche",
    "iso:country":"BE",
    "sg:address":"Rue De La Cloche 5",
    "sg:city":"Amay",
    "sg:orig_category":"Plomberie, chauffage and installations sanitaires. R\u00e9parations \u00e0 domicile d'articles divers. Quincai",
    "sg:phone":"+32 85 31 17 85",
    "sg:postcode":"4540",
    "sg:province":"Li\u00e8ge",
    "wof:name":"Pierre Chauffage",
    "wof:placetype":"venue"
},
  "geometry": {"coordinates":[5.323015213,50.5462417603],"type":"Point"}
}