{
  "type": "Feature",
  "properties": {
    "addr:full":"Veerledorp 8 Laakdal Antwerpen 2431",
    "addr:housenumber":"8",
    "addr:postcode":"2431",
    "addr:street":"Veerledorp",
    "iso:country":"BE",
    "sg:address":"Veerledorp 8",
    "sg:city":"Laakdal",
    "sg:classifiers":[
        {
            "category":"Restaurant",
            "type":"Food & Drink"
        }
    ],
    "sg:phone":"+32 14 84 12 94",
    "sg:postcode":"2431",
    "sg:province":"Antwerpen",
    "wof:name":"Chris",
    "wof:placetype":"venue"
},
  "geometry": {"coordinates":[4.983730793,51.0688858032],"type":"Point"}
}