{
  "type": "Feature",
  "properties": {
    "iso:country":"BE",
    "sg:address":"Rue Donveau 15ba",
    "sg:city":"Florennes",
    "sg:orig_category":"Artsen and specialisten",
    "sg:phone":"+32 71 68 90 11",
    "sg:postcode":"5621",
    "sg:province":"Namur",
    "wof:name":"Monique Selosse",
    "wof:placetype":"venue"
},
  "geometry": {"coordinates":[4.5651698112,50.282699585],"type":"Point"}
}