{
  "type": "Feature",
  "properties": {
    "iso:country":"BE",
    "sg:address":"Merksemsebaan 40",
    "sg:city":"Wijnegem",
    "sg:classifiers":[
        {
            "category":"Bars & Pubs",
            "type":"Food & Drink"
        }
    ],
    "sg:phone":"+32 3 354 09 15",
    "sg:postcode":"2110",
    "sg:province":"Antwerpen",
    "wof:name":"Dorp('t)",
    "wof:placetype":"venue"
},
  "geometry": {"coordinates":[4.5173568726,51.2284355164],"type":"Point"}
}