{
  "type": "Feature",
  "properties": {
    "addr:full":"Rue De La Religion 6 Nivelles Brabant Wallon 1400",
    "addr:housenumber":"6",
    "addr:postcode":"1400",
    "addr:street":"Rue De La Religion",
    "iso:country":"BE",
    "sg:address":"Rue De La Religion 6",
    "sg:city":"Nivelles",
    "sg:classifiers":[
        {
            "category":"Professional",
            "subcategory":"Lawyer & Legal Services",
            "type":"Services"
        }
    ],
    "sg:phone":"+32 67 21 45 41",
    "sg:postcode":"1400",
    "sg:province":"Brabant Wallon",
    "wof:name":"Lardinois Michel",
    "wof:placetype":"venue"
},
  "geometry": {"coordinates":[4.3259949684,50.5954284668],"type":"Point"}
}