{
  "type": "Feature",
  "properties": {
    "addr:full":"Ringlaan 126 Zandhoven Antwerpen 2240",
    "addr:housenumber":"126",
    "addr:postcode":"2240",
    "addr:street":"Ringlaan",
    "iso:country":"BE",
    "sg:address":"Ringlaan 126",
    "sg:city":"Zandhoven",
    "sg:classifiers":[
        {
            "category":"Home & Garden",
            "subcategory":"Carpets & Floor Coverings",
            "type":"Retail Goods"
        }
    ],
    "sg:phone":"+32 475 63 75 71",
    "sg:postcode":"2240",
    "sg:province":"Antwerpen",
    "sg:tags":[
        "oriental"
    ],
    "wof:name":"Coninckx O",
    "wof:placetype":"venue"
},
  "geometry": {"coordinates":[4.6655192375,51.2154006958],"type":"Point"}
}