{
  "type": "Feature",
  "properties": {
    "iso:country":"BE",
    "sg:address":"Zeedijk",
    "sg:city":"Middelkerke",
    "sg:classifiers":[
        {
            "category":"Casinos & Gambling",
            "type":"Entertainment"
        }
    ],
    "sg:phone":"+32 59 30 05 03",
    "sg:postcode":"8430",
    "sg:province":"West-Vlaanderen",
    "wof:name":"Casino Middelkerke",
    "wof:placetype":"venue"
},
  "geometry": {"coordinates":[2.8105099201,51.1863250732],"type":"Point"}
}