{
  "type": "Feature",
  "properties": {
    "addr:full":"Koning Albertlaan 2 Leuven (kessel-lo) Vlaams-Brabant 3010",
    "addr:housenumber":"2",
    "addr:postcode":"3010",
    "addr:street":"Koning Albertlaan",
    "iso:country":"BE",
    "sg:address":"Koning Albertlaan 2",
    "sg:city":"Leuven (kessel-lo)",
    "sg:classifiers":[
        {
            "category":"Government",
            "subcategory":"Court House",
            "type":"Public Place"
        }
    ],
    "sg:phone":"+32 16 35 05 79",
    "sg:postcode":"3010",
    "sg:province":"Vlaams-Brabant",
    "sg:tags":[
        "consultant",
        "outplacement"
    ],
    "wof:name":"Kompas Vzw",
    "wof:placetype":"venue"
},
  "geometry": {"coordinates":[4.7304501534,50.889755249],"type":"Point"}
}