{
  "type": "Feature",
  "properties": {
    "addr:full":"Victor Allardstraat 147 Ukkel/uccle Bruxelles-Capitale 1180",
    "addr:housenumber":"147",
    "addr:postcode":"1180",
    "addr:street":"Victor Allardstraat;/",
    "iso:country":"BE",
    "sg:address":"Victor Allardstraat 147",
    "sg:city":"Ukkel/uccle",
    "sg:orig_category":"Secretariaatsdiensten",
    "sg:phone":"+32 2 332 18 11",
    "sg:postcode":"1180",
    "sg:province":"Bruxelles-Capitale",
    "wof:name":"Flash +",
    "wof:placetype":"venue"
},
  "geometry": {"coordinates":[4.3307719231,50.8013763428],"type":"Point"}
}