{
  "type": "Feature",
  "properties": {
    "iso:country":"BE",
    "sg:address":"Galerie Kennedy",
    "sg:city":"Rixensart",
    "sg:classifiers":[
        {
            "category":"Food & Beverages",
            "subcategory":"Specialty",
            "type":"Retail Goods"
        }
    ],
    "sg:phone":"+32 2 653 02 01",
    "sg:postcode":"1330",
    "sg:province":"Brabant Wallon",
    "sg:tags":[
        "health",
        "dietary",
        "-",
        "biological"
    ],
    "wof:name":"Autre Chose Sprl",
    "wof:placetype":"venue"
},
  "geometry": {"coordinates":[4.5209498405,50.7110290527],"type":"Point"}
}