{
  "type": "Feature",
  "properties": {
    "iso:country":"BE",
    "sg:address":"Rue Joseph Toisoul 7",
    "sg:city":"La Louvi\u00c8re",
    "sg:orig_category":"V\u00eatements pour Hommes",
    "sg:phone":"+32 64 21 60 21",
    "sg:postcode":"7100",
    "sg:province":"Hainaut",
    "wof:name":"Maison Pour L\u00b4homme",
    "wof:placetype":"venue"
},
  "geometry": {"coordinates":[4.1895871162,50.4783363342],"type":"Point"}
}