{
  "type": "Feature",
  "properties": {
    "addr:full":"Graatakker 155b5 Turnhout Antwerpen 2300",
    "addr:housenumber":"155b5",
    "addr:postcode":"2300",
    "addr:street":"Graatakker",
    "iso:country":"BE",
    "sg:address":"Graatakker 155b5",
    "sg:city":"Turnhout",
    "sg:orig_category":"Etalage- and showroomontwerpers",
    "sg:phone":"+32 14 41 91 69",
    "sg:postcode":"2300",
    "sg:province":"Antwerpen",
    "wof:name":"Etalages Van",
    "wof:placetype":"venue"
},
  "geometry": {"coordinates":[4.9499192238,51.3145294189],"type":"Point"}
}