{
  "type": "Feature",
  "properties": {
    "addr:full":"Louis Van Craenstraat 15 Antwerpen (deurne) Antwerpen 2100",
    "addr:housenumber":"15",
    "addr:postcode":"2100",
    "addr:street":"Louis Van Craenstraat",
    "iso:country":"BE",
    "sg:address":"Louis Van Craenstraat 15",
    "sg:city":"Antwerpen (deurne)",
    "sg:classifiers":[
        {
            "category":"Real Estate",
            "subcategory":"Architect",
            "type":"Services"
        }
    ],
    "sg:phone":"+32 3 324 80 13",
    "sg:postcode":"2100",
    "sg:province":"Antwerpen",
    "wof:name":"Ceulemans J",
    "wof:placetype":"venue"
},
  "geometry": {"coordinates":[4.4586100578,51.2203941345],"type":"Point"}
}