{
  "type": "Feature",
  "properties": {
    "iso:country":"BE",
    "sg:address":"Place De La Wallonie 5",
    "sg:city":"Fontaine-l'ev\u00eaque",
    "sg:classifiers":[
        {
            "category":"Bars & Pubs",
            "type":"Food & Drink"
        }
    ],
    "sg:phone":"+32 71 52 56 37",
    "sg:postcode":"6140",
    "sg:province":"Hainaut",
    "wof:name":"Parc (du)",
    "wof:placetype":"venue"
},
  "geometry": {"coordinates":[4.3245301247,50.4105377197],"type":"Point"}
}