{
  "type": "Feature",
  "properties": {
    "addr:full":"Rue Gaston Bary 37 La Hulpe Brabant Wallon 1310",
    "addr:housenumber":"37",
    "addr:postcode":"1310",
    "addr:street":"Rue Gaston Bary",
    "iso:country":"BE",
    "sg:address":"Rue Gaston Bary 37",
    "sg:city":"La Hulpe",
    "sg:classifiers":[
        {
            "category":"Professional",
            "subcategory":"Accounting & Tax Preparation",
            "type":"Services"
        }
    ],
    "sg:phone":"+32 2 654 13 61",
    "sg:postcode":"1310",
    "sg:province":"Brabant Wallon",
    "sg:tags":[
        "accountant"
    ],
    "wof:name":"Jozef Galein",
    "wof:placetype":"venue"
},
  "geometry": {"coordinates":[4.4935040474,50.7392921448],"type":"Point"}
}