{
  "type": "Feature",
  "properties": {
    "iso:country":"BE",
    "sg:address":"Rue Des Tanneurs 158",
    "sg:city":"Bruxelles",
    "sg:classifiers":[
        {
            "category":"Food & Beverages",
            "subcategory":"Groceries & Convenience Stores",
            "type":"Retail Goods"
        }
    ],
    "sg:phone":"+32 2 513 94 84",
    "sg:postcode":"1000",
    "sg:province":"Bruxelles-Capitale",
    "sg:tags":[
        "grocer"
    ],
    "wof:name":"Panier Du Tanneur (le)",
    "wof:placetype":"venue"
},
  "geometry": {"coordinates":[4.3434271812,50.8375396729],"type":"Point"}
}