{
  "type": "Feature",
  "properties": {
    "addr:full":"Rue Haute Bruxelles Bruxelles-Capitale 1000",
    "addr:postcode":"1000",
    "addr:street":"Rue Haute",
    "iso:country":"BE",
    "sg:address":"Rue Haute",
    "sg:city":"Bruxelles",
    "sg:orig_category":"Mat\u00e9riel de T\u00e9l\u00e9communication",
    "sg:phone":"+32 2 513 61 71",
    "sg:postcode":"1000",
    "sg:province":"Bruxelles-Capitale",
    "wof:name":"Aidel(sablon)",
    "wof:placetype":"venue"
},
  "geometry": {"coordinates":[4.3512358665,50.8400230408],"type":"Point"}
}