{
  "type": "Feature",
  "properties": {
    "iso:country":"BE",
    "sg:address":"Alsembergsesteenweg 877",
    "sg:city":"Ukkel/uccle",
    "sg:orig_category":"Passagiersvervoer over de weg",
    "sg:phone":"+32 2 376 79 68",
    "sg:postcode":"1180",
    "sg:province":"Bruxelles-Capitale",
    "wof:name":"Autocars Feyaerts",
    "wof:placetype":"venue"
},
  "geometry": {"coordinates":[4.3363118172,50.7997817993],"type":"Point"}
}