{
  "type": "Feature",
  "properties": {
    "iso:country":"BE",
    "sg:address":"Chauss\u00c9e De Bruxelles 135",
    "sg:city":"Soignies",
    "sg:orig_category":"Catering and organisatie van feesten",
    "sg:phone":"+32 65 72 36 27",
    "sg:postcode":"7061",
    "sg:province":"Hainaut",
    "wof:name":"Lo-fo-tel",
    "wof:placetype":"venue"
},
  "geometry": {"coordinates":[4.0133500099,50.5159416199],"type":"Point"}
}