{
  "type": "Feature",
  "properties": {
    "iso:country":"BE",
    "sg:address":"Rue Des Bouleaux 21",
    "sg:city":"Amay",
    "sg:classifiers":[
        {
            "category":"Professional",
            "type":"Services"
        }
    ],
    "sg:phone":"+32 85 31 38 90",
    "sg:postcode":"4540",
    "sg:province":"Li\u00e8ge",
    "sg:tags":[
        "industrial",
        "work",
        "-",
        "maintenance"
    ],
    "wof:name":"Liziero Sdl",
    "wof:placetype":"venue"
},
  "geometry": {"coordinates":[5.3286337852,50.5492515564],"type":"Point"}
}