{
  "type": "Feature",
  "properties": {
    "iso:country":"BE",
    "sg:address":"Rue De La Croix Gabriel 24",
    "sg:city":"Nivelles",
    "sg:classifiers":[
        {
            "category":"Health Services",
            "subcategory":"Health Practitioner",
            "type":"Services"
        }
    ],
    "sg:phone":"+32 67 84 31 46",
    "sg:postcode":"1400",
    "sg:province":"Brabant Wallon",
    "sg:tags":[
        "therapist",
        "speech"
    ],
    "wof:name":"Etienne-hins A",
    "wof:placetype":"venue"
},
  "geometry": {"coordinates":[4.3482499123,50.5959663391],"type":"Point"}
}