{
  "type": "Feature",
  "properties": {
    "iso:country":"BE",
    "sg:address":"Avenue De L'emeraude 9",
    "sg:city":"Schaarbeek/schaerbeek",
    "sg:orig_category":"M\u00e9decins and sp\u00e9cialistes",
    "sg:phone":"+32 2 736 29 14",
    "sg:postcode":"1030",
    "sg:province":"Bruxelles-Capitale",
    "wof:name":"Consultations Nourrissons",
    "wof:placetype":"venue"
},
  "geometry": {"coordinates":[4.3742771149,50.8617973328],"type":"Point"}
}