{
  "type": "Feature",
  "properties": {
    "addr:full":"Voort 6 Neerpelt Limburg 3910",
    "addr:housenumber":"6",
    "addr:postcode":"3910",
    "addr:street":"Voort",
    "iso:country":"BE",
    "sg:address":"Voort 6",
    "sg:city":"Neerpelt",
    "sg:classifiers":[
        {
            "category":"Insurance",
            "subcategory":"Life Insurance",
            "type":"Services"
        }
    ],
    "sg:phone":"+32 11 64 35 04",
    "sg:postcode":"3910",
    "sg:province":"Limburg",
    "sg:tags":[
        "assurance"
    ],
    "wof:name":"L. Jansen",
    "wof:placetype":"venue"
},
  "geometry": {"coordinates":[5.4885811806,51.2227897644],"type":"Point"}
}