{
  "type": "Feature",
  "properties": {
    "iso:country":"BE",
    "sg:address":"Driekoningenstraat 20",
    "sg:city":"Sint-niklaas",
    "sg:orig_category":"Beautyfarms, relaxatie and lichamelijk welzijn",
    "sg:phone":"+32 3 776 73 38",
    "sg:postcode":"9100",
    "sg:province":"Oost-Vlaanderen",
    "wof:name":"Cosmo Sun",
    "wof:placetype":"venue"
},
  "geometry": {"coordinates":[4.1401920319,51.1718597412],"type":"Point"}
}