{
  "type": "Feature",
  "properties": {
    "addr:full":"Spinnersstraat 27 Roeselare West-Vlaanderen 8800",
    "addr:housenumber":"27",
    "addr:postcode":"8800",
    "addr:street":"Spinnersstraat",
    "iso:country":"BE",
    "sg:address":"Spinnersstraat 27",
    "sg:city":"Roeselare",
    "sg:orig_category":"Brood, gebak and snoepgoed",
    "sg:phone":"+32 51 21 10 72",
    "sg:postcode":"8800",
    "sg:province":"West-Vlaanderen",
    "wof:name":"Vandenbrande & Co.",
    "wof:placetype":"venue"
},
  "geometry": {"coordinates":[3.1344480515,50.9495582581],"type":"Point"}
}