{
  "type": "Feature",
  "properties": {
    "addr:full":"Rue Wayez 46 Bruxelles (anderlecht) Bruxelles-Capitale 1070",
    "addr:housenumber":"46",
    "addr:postcode":"1070",
    "addr:street":"Rue Wayez",
    "iso:country":"BE",
    "sg:address":"Rue Wayez 46",
    "sg:city":"Bruxelles (anderlecht)",
    "sg:classifiers":[
        {
            "category":"Cafe",
            "type":"Food & Drink"
        }
    ],
    "sg:phone":"+32 2 520 13 03",
    "sg:postcode":"1070",
    "sg:province":"Bruxelles-Capitale",
    "sg:tags":[
        "snack-bars"
    ],
    "wof:name":"La Corniche",
    "wof:placetype":"venue"
},
  "geometry": {"coordinates":[4.3154110909,50.8361206055],"type":"Point"}
}