{
  "type": "Feature",
  "properties": {
    "iso:country":"BE",
    "sg:address":"Chauss\u00c9e De Bruxelles 45",
    "sg:city":"Waterloo",
    "sg:orig_category":"Installatie van houten of kunststof schrijnwerk",
    "sg:phone":"+32 2 354 36 14",
    "sg:postcode":"1410",
    "sg:province":"Brabant Wallon",
    "wof:name":"B & M Trading",
    "wof:placetype":"venue"
},
  "geometry": {"coordinates":[4.3988847733,50.7284469604],"type":"Point"}
}