{
  "type": "Feature",
  "properties": {
    "addr:full":"Avenue Albert Ier. 12 Edingen/enghien Hainaut 7850",
    "addr:housenumber":"12",
    "addr:postcode":"7850",
    "addr:street":"Avenue Albert Ier.",
    "iso:country":"BE",
    "sg:address":"Avenue Albert Ier. 12",
    "sg:city":"Edingen/enghien",
    "sg:orig_category":"M\u00e9decins and sp\u00e9cialistes",
    "sg:phone":"+32 2 395 58 18",
    "sg:postcode":"7850",
    "sg:province":"Hainaut",
    "wof:name":"Florence Colart",
    "wof:placetype":"venue"
},
  "geometry": {"coordinates":[4.0409798622,50.6933822632],"type":"Point"}
}