{
  "type": "Feature",
  "properties": {
    "addr:full":"Rue G\u00c9n\u00c9ral Leman 7 Mons Hainaut 7012",
    "addr:housenumber":"7",
    "addr:postcode":"7012",
    "addr:street":"Rue Ge\u0301Ne\u0301Ral Leman;Hainaut",
    "iso:country":"BE",
    "sg:address":"Rue G\u00c9n\u00c9ral Leman 7",
    "sg:city":"Mons",
    "sg:orig_category":"Ordinateurs and \u00e9quipement informatique. Conseils en syst\u00e8mes informatiques",
    "sg:phone":"+32 65 88 66 88",
    "sg:postcode":"7012",
    "sg:province":"Hainaut",
    "wof:name":"Net Consult",
    "wof:placetype":"venue"
},
  "geometry": {"coordinates":[3.9500141144,50.4364242554],"type":"Point"}
}