{
  "type": "Feature",
  "properties": {
    "addr:full":"Groene Laan 6 Willebroek Antwerpen 2830",
    "addr:housenumber":"6",
    "addr:postcode":"2830",
    "addr:street":"Groene Laan",
    "iso:country":"BE",
    "sg:address":"Groene Laan 6",
    "sg:city":"Willebroek",
    "sg:classifiers":[
        {
            "category":"Professional",
            "subcategory":"Lawyer & Legal Services",
            "type":"Services"
        }
    ],
    "sg:phone":"+32 3 886 77 77",
    "sg:postcode":"2830",
    "sg:province":"Antwerpen",
    "wof:name":"Spiessens J",
    "wof:placetype":"venue"
},
  "geometry": {"coordinates":[4.3631801605,51.0610809326],"type":"Point"}
}