{
  "type": "Feature",
  "properties": {
    "addr:full":"Onledestraat 7 Hooglede West-Vlaanderen 8830",
    "addr:housenumber":"7",
    "addr:postcode":"8830",
    "addr:street":"Onledestraat",
    "iso:country":"BE",
    "sg:address":"Onledestraat 7",
    "sg:city":"Hooglede",
    "sg:orig_category":"Varkenskwekers",
    "sg:phone":"+32 51 72 26 50",
    "sg:postcode":"8830",
    "sg:province":"West-Vlaanderen",
    "wof:name":"Guido Ameye",
    "wof:placetype":"venue"
},
  "geometry": {"coordinates":[3.1285300255,51.0024719238],"type":"Point"}
}