{
  "type": "Feature",
  "properties": {
    "addr:full":"Chauss\u00e9e De Tournai 16 Leuze-en-hainaut (pipaix) Hainaut 7904",
    "addr:housenumber":"16",
    "addr:postcode":"7904",
    "addr:street":"Chausse\u0301E De Tournai;Hainaut",
    "iso:country":"BE",
    "sg:address":"Chauss\u00e9e De Tournai 16",
    "sg:city":"Leuze-en-hainaut (pipaix)",
    "sg:classifiers":[
        {
            "category":"Retail",
            "subcategory":"Auto Repair",
            "type":"Services"
        }
    ],
    "sg:phone":"+32 69 66 12 09",
    "sg:postcode":"7904",
    "sg:province":"Hainaut",
    "sg:tags":[
        "garage"
    ],
    "wof:name":"Merlot",
    "wof:placetype":"venue"
},
  "geometry": {"coordinates":[3.5772058964,50.5929946899],"type":"Point"}
}