{
  "type": "Feature",
  "properties": {
    "iso:country":"BE",
    "sg:address":"Damstraat 30",
    "sg:city":"Lede",
    "sg:orig_category":"Electrom\u00e9nager, t\u00e9l\u00e9visions and radios",
    "sg:phone":"+32 53 80 06 03",
    "sg:postcode":"9340",
    "sg:province":"Oost-Vlaanderen",
    "wof:name":"Renaat Henderickx",
    "wof:placetype":"venue"
},
  "geometry": {"coordinates":[3.967550993,50.9645996094],"type":"Point"}
}