{
  "type": "Feature",
  "properties": {
    "iso:country":"BE",
    "sg:address":"Thier De Hodimont",
    "sg:city":"Verviers (petit-rechain)",
    "sg:classifiers":[
        {
            "category":"Arena",
            "subcategory":"Sports Club",
            "type":"Entertainment"
        }
    ],
    "sg:phone":"+32 87 31 56 93",
    "sg:postcode":"4800",
    "sg:province":"Li\u00e8ge",
    "wof:name":"R.u.hodimontoise Terrain",
    "wof:placetype":"venue"
},
  "geometry": {"coordinates":[5.8673610687,50.5928611755],"type":"Point"}
}