{
  "type": "Feature",
  "properties": {
    "addr:full":"Ringlaan 24 Kuurne West-Vlaanderen 8520",
    "addr:housenumber":"24",
    "addr:postcode":"8520",
    "addr:street":"Ringlaan",
    "iso:country":"BE",
    "sg:address":"Ringlaan 24",
    "sg:city":"Kuurne",
    "sg:classifiers":[
        {
            "category":"Home & Garden",
            "subcategory":"Carpets & Floor Coverings",
            "type":"Retail Goods"
        }
    ],
    "sg:phone":"+32 56 36 96 11",
    "sg:postcode":"8520",
    "sg:province":"West-Vlaanderen",
    "sg:tags":[
        "carpeting"
    ],
    "wof:name":"Prado Rugs Nv",
    "wof:placetype":"venue"
},
  "geometry": {"coordinates":[3.2814209461,50.8413085938],"type":"Point"}
}