{
  "type": "Feature",
  "properties": {
    "addr:full":"60 Kapeldreef 3001 Leuven 60",
    "addr:housenumber":"60",
    "addr:postcode":"3001",
    "addr:street":"Kapeldreef",
    "iso:country":"BE",
    "sg:address":"60",
    "sg:city":"Kapeldreef 3001 Leuven",
    "sg:classifiers":[
        {
            "category":"Professional",
            "subcategory":"Computer Services",
            "type":"Services"
        }
    ],
    "sg:phone":"+32 16 40 14 20",
    "sg:postcode":"60",
    "sg:tags":[
        "information",
        "technology",
        "software"
    ],
    "wof:name":"Vom Nv",
    "wof:placetype":"venue"
},
  "geometry": {"coordinates":[4.6650252342,50.8611412048],"type":"Point"}
}