{
  "type": "Feature",
  "properties": {
    "addr:full":"Knaptandstraat 195-197 Sint-niklaas Oost-Vlaanderen 9100",
    "addr:housenumber":"195-197",
    "addr:postcode":"9100",
    "addr:street":"Knaptandstraat",
    "iso:country":"BE",
    "sg:address":"Knaptandstraat 195-197",
    "sg:city":"Sint-niklaas",
    "sg:classifiers":[
        {
            "category":"Retail",
            "subcategory":"Repair Shop",
            "type":"Services"
        }
    ],
    "sg:phone":"+32 3 776 41 65",
    "sg:postcode":"9100",
    "sg:province":"Oost-Vlaanderen",
    "sg:tags":[
        "-",
        "mainten",
        "watch",
        "clock"
    ],
    "wof:name":"Pevenage P",
    "wof:placetype":"venue"
},
  "geometry": {"coordinates":[4.1466321945,51.1569595337],"type":"Point"}
}