{
  "type": "Feature",
  "properties": {
    "addr:full":"Rue Verte 57 Bruxelles (saint-josse-ten-noode) Bruxelles-Capitale 1210",
    "addr:housenumber":"57",
    "addr:postcode":"1210",
    "addr:street":"Rue Verte",
    "iso:country":"BE",
    "sg:address":"Rue Verte 57",
    "sg:city":"Bruxelles (saint-josse-ten-noode)",
    "sg:classifiers":[
        {
            "category":"Shopping",
            "subcategory":"Bicycles & Sporting Goods",
            "type":"Retail Goods"
        }
    ],
    "sg:phone":"+32 2 217 78 61",
    "sg:postcode":"1210",
    "sg:province":"Bruxelles-Capitale",
    "sg:tags":[
        "tyre"
    ],
    "wof:name":"Sezer",
    "wof:placetype":"venue"
},
  "geometry": {"coordinates":[4.3642940521,50.8581161499],"type":"Point"}
}