{
  "type": "Feature",
  "properties": {
    "iso:country":"BE",
    "sg:address":"Rue G\u00c9ry Everaerts 59",
    "sg:city":"Wavre",
    "sg:orig_category":"Editeurs de livres. Graphologues, astrologues, voyants and radiesth\u00e9sistes",
    "sg:phone":"+32 10 41 31 35",
    "sg:postcode":"1300",
    "sg:province":"Brabant Wallon",
    "wof:name":"Litcom Services",
    "wof:placetype":"venue"
},
  "geometry": {"coordinates":[4.5831489563,50.6873435974],"type":"Point"}
}