{
  "type": "Feature",
  "properties": {
    "iso:country":"BE",
    "sg:address":"Monseigneur Broekxplein 6",
    "sg:city":"Hasselt",
    "sg:classifiers":[
        {
            "category":"Bars & Pubs",
            "type":"Food & Drink"
        }
    ],
    "sg:phone":"+32 11 22 44 56",
    "sg:postcode":"3500",
    "sg:province":"Limburg",
    "sg:tags":[
        "tavern"
    ],
    "wof:name":"Volksmacht (de)",
    "wof:placetype":"venue"
},
  "geometry": {"coordinates":[5.3264780045,50.931350708],"type":"Point"}
}