{
  "type": "Feature",
  "properties": {
    "iso:country":"BE",
    "sg:address":"Donklaan 124",
    "sg:city":"Berlare",
    "sg:classifiers":[
        {
            "category":"Cafe",
            "type":"Food & Drink"
        }
    ],
    "sg:phone":"+32 9 367 85 31",
    "sg:postcode":"9290",
    "sg:province":"Oost-Vlaanderen",
    "sg:tags":[
        "snack-bars"
    ],
    "wof:name":"Supersnack",
    "wof:placetype":"venue"
},
  "geometry": {"coordinates":[3.9814178944,51.0465431213],"type":"Point"}
}