{
  "type": "Feature",
  "properties": {
    "addr:full":"Vijfkampstraat 23 Antwerpen Antwerpen 2020",
    "addr:housenumber":"23",
    "addr:postcode":"2020",
    "addr:street":"Vijfkampstraat",
    "iso:country":"BE",
    "sg:address":"Vijfkampstraat 23",
    "sg:city":"Antwerpen",
    "sg:classifiers":[
        {
            "category":"Professional",
            "type":"Services"
        }
    ],
    "sg:phone":"+32 3 828 44 78",
    "sg:postcode":"2020",
    "sg:province":"Antwerpen",
    "sg:tags":[
        "surveyor",
        "-",
        "valuer"
    ],
    "wof:name":"Raats,nieman & Nieman",
    "wof:placetype":"venue"
},
  "geometry": {"coordinates":[4.3858251572,51.1817550659],"type":"Point"}
}