{
  "type": "Feature",
  "properties": {
    "iso:country":"BE",
    "sg:address":"De Wieken 16",
    "sg:city":"Edegem",
    "sg:orig_category":"Sportclubs",
    "sg:phone":"+32 3 458 22 78",
    "sg:postcode":"2650",
    "sg:province":"Antwerpen",
    "wof:name":"A.p.s.o.",
    "wof:placetype":"venue"
},
  "geometry": {"coordinates":[4.4466209412,51.1612167358],"type":"Point"}
}