{
  "type": "Feature",
  "properties": {
    "addr:full":"Dupontstraat (pieter) 167 Brussel Bruxelles-Capitale 1140",
    "addr:housenumber":"167",
    "addr:postcode":"1140",
    "addr:street":"Dupontstraat Pieter",
    "iso:country":"BE",
    "sg:address":"Dupontstraat (pieter) 167",
    "sg:city":"Brussel",
    "sg:classifiers":[
        {
            "category":"Wholesale",
            "subcategory":"Construction Materials",
            "type":"Manufacturing & Wholesale Goods"
        }
    ],
    "sg:phone":"+32 2 726 16 85",
    "sg:postcode":"1140",
    "sg:province":"Bruxelles-Capitale",
    "sg:tags":[
        "chemical",
        "product"
    ],
    "wof:name":"Sika Nv",
    "wof:placetype":"venue"
},
  "geometry": {"coordinates":[4.4124150276,50.8641777039],"type":"Point"}
}