{
  "type": "Feature",
  "properties": {
    "iso:country":"BE",
    "sg:address":"Rue Du Plagniau 50",
    "sg:city":"Rixensart",
    "sg:orig_category":"Diverse grafische activiteiten",
    "sg:phone":"+32 2 652 49 95",
    "sg:postcode":"1330",
    "sg:province":"Brabant Wallon",
    "wof:name":"N. Binart",
    "wof:placetype":"venue"
},
  "geometry": {"coordinates":[4.5358700752,50.7221412659],"type":"Point"}
}