{
  "type": "Feature",
  "properties": {
    "addr:full":"Rue De Berneau 30 Vise Li\u00e8ge 4600",
    "addr:housenumber":"30",
    "addr:postcode":"4600",
    "addr:street":"Rue De Berneau",
    "iso:country":"BE",
    "sg:address":"Rue De Berneau 30",
    "sg:city":"Vise",
    "sg:orig_category":"Sportclubs",
    "sg:phone":"+32 4 379 36 28",
    "sg:postcode":"4600",
    "sg:province":"Li\u00e8ge",
    "wof:name":"R.s.c. Vis\u00c9 Tennis De Table",
    "wof:placetype":"venue"
},
  "geometry": {"coordinates":[5.7071399689,50.7372741699],"type":"Point"}
}