{
  "type": "Feature",
  "properties": {
    "addr:full":"Geraardsbergsestraat 141 Dilbeek Vlaams-Brabant 1703",
    "addr:housenumber":"141",
    "addr:postcode":"1703",
    "addr:street":"Geraardsbergsestraat",
    "iso:country":"BE",
    "sg:address":"Geraardsbergsestraat 141",
    "sg:city":"Dilbeek",
    "sg:orig_category":"Eleveurs de bovins",
    "sg:phone":"+32 2 582 19 30",
    "sg:postcode":"1703",
    "sg:province":"Vlaams-Brabant",
    "wof:name":"Anne Taelemans",
    "wof:placetype":"venue"
},
  "geometry": {"coordinates":[4.1896390915,50.8323898315],"type":"Point"}
}