{
  "type": "Feature",
  "properties": {
    "iso:country":"BE",
    "sg:address":"Monseigneur Stillemansstraat 4",
    "sg:city":"Sint-niklaas",
    "sg:orig_category":"Mutualities",
    "sg:phone":"+32 3 776 51 12",
    "sg:postcode":"9100",
    "sg:province":"Oost-Vlaanderen",
    "wof:name":"Vlaams Onafhankelijk Ziekenfonds",
    "wof:placetype":"venue"
},
  "geometry": {"coordinates":[4.1420679092,51.1613883972],"type":"Point"}
}