{
  "type": "Feature",
  "properties": {
    "addr:full":"Veldmaarschalk Montgomerystraat 14 Box 2 Kuurne West-Vlaanderen 8520",
    "addr:housenumber":"14;2",
    "addr:postcode":"8520",
    "addr:street":"Veldmaarschalk Montgomerystraat;Box",
    "iso:country":"BE",
    "sg:address":"Veldmaarschalk Montgomerystraat 14 Box 2",
    "sg:city":"Kuurne",
    "sg:classifiers":[
        {
            "category":"Building & Trades",
            "subcategory":"Construction",
            "type":"Services"
        }
    ],
    "sg:phone":"+32 56 70 54 99",
    "sg:postcode":"8520",
    "sg:province":"West-Vlaanderen",
    "sg:tags":[
        "carpenter"
    ],
    "wof:name":"Eggermont Philippe",
    "wof:placetype":"venue"
},
  "geometry": {"coordinates":[3.2784249783,50.8533935547],"type":"Point"}
}