{
  "type": "Feature",
  "properties": {
    "addr:full":"Neermeerskaai 88 Gent Oost-Vlaanderen 9000",
    "addr:housenumber":"88",
    "addr:postcode":"9000",
    "addr:street":"Neermeerskaai;Oost-Vlaanderen",
    "iso:country":"BE",
    "sg:address":"Neermeerskaai 88",
    "sg:city":"Gent",
    "sg:orig_category":"Apotheken",
    "sg:phone":"+32 9 222 70 91",
    "sg:postcode":"9000",
    "sg:province":"Oost-Vlaanderen",
    "wof:name":"Apotheek Vooruit",
    "wof:placetype":"venue"
},
  "geometry": {"coordinates":[3.7046790123,51.0439491272],"type":"Point"}
}