{
  "type": "Feature",
  "properties": {
    "iso:country":"BE",
    "sg:address":"Brederodestraat 58",
    "sg:city":"Antwerpen",
    "sg:classifiers":[
        {
            "category":"Shopping",
            "subcategory":"Florist",
            "type":"Retail Goods"
        }
    ],
    "sg:phone":"+32 3 238 97 98",
    "sg:postcode":"2018",
    "sg:province":"Antwerpen",
    "wof:name":"Bloemerie (de)",
    "wof:placetype":"venue"
},
  "geometry": {"coordinates":[4.3954172134,51.2052688599],"type":"Point"}
}