{
  "type": "Feature",
  "properties": {
    "addr:full":"Mechelsesteenweg 38 Kontich Antwerpen 2550",
    "addr:housenumber":"38",
    "addr:postcode":"2550",
    "addr:street":"Mechelsesteenweg",
    "iso:country":"BE",
    "sg:address":"Mechelsesteenweg 38",
    "sg:city":"Kontich",
    "sg:classifiers":[
        {
            "category":"Professional",
            "subcategory":"Management & Consulting",
            "type":"Services"
        }
    ],
    "sg:phone":"+32 3 289 05 81",
    "sg:postcode":"2550",
    "sg:province":"Antwerpen",
    "sg:tags":[
        "-",
        "processing",
        "data",
        "consultant"
    ],
    "wof:name":"Cotrain Bvba",
    "wof:placetype":"venue"
},
  "geometry": {"coordinates":[4.4454331398,51.1334762573],"type":"Point"}
}