{
  "type": "Feature",
  "properties": {
    "addr:full":"Rue Du Chemin De Fer 20ba Charleroi Hainaut 6041",
    "addr:housenumber":"20ba",
    "addr:postcode":"6041",
    "addr:street":"Rue Du Chemin De Fer;Hainaut",
    "iso:country":"BE",
    "sg:address":"Rue Du Chemin De Fer 20ba",
    "sg:city":"Charleroi",
    "sg:orig_category":"Herstellingen motorfietsen",
    "sg:phone":"+32 71 37 37 82",
    "sg:postcode":"6041",
    "sg:province":"Hainaut",
    "wof:name":"Maison City Motor",
    "wof:placetype":"venue"
},
  "geometry": {"coordinates":[4.4237208366,50.4222984314],"type":"Point"}
}