{
  "type": "Feature",
  "properties": {
    "addr:full":"Rue Puccini 22 Bruxelles (anderlecht) Bruxelles-Capitale 1070",
    "addr:housenumber":"22",
    "addr:postcode":"1070",
    "addr:street":"Rue Puccini",
    "iso:country":"BE",
    "sg:address":"Rue Puccini 22",
    "sg:city":"Bruxelles (anderlecht)",
    "sg:classifiers":[
        {
            "category":"Health Services",
            "subcategory":"Nursing And Care Facility",
            "type":"Services"
        }
    ],
    "sg:phone":"+32 2 559 71 00",
    "sg:postcode":"1070",
    "sg:province":"Bruxelles-Capitale",
    "sg:tags":[
        "home",
        "rest"
    ],
    "wof:name":"Home J Vanhellemont",
    "wof:placetype":"venue"
},
  "geometry": {"coordinates":[4.3070578575,50.8459892273],"type":"Point"}
}