{
  "type": "Feature",
  "properties": {
    "iso:country":"BE",
    "sg:address":"Waversesteenweg 139",
    "sg:city":"Hoeilaart",
    "sg:classifiers":[
        {
            "category":"Retail",
            "subcategory":"Auto Repair",
            "type":"Services"
        }
    ],
    "sg:phone":"+32 2 657 28 45",
    "sg:postcode":"1560",
    "sg:province":"Vlaams-Brabant",
    "sg:tags":[
        "garage"
    ],
    "wof:name":"L'atelier",
    "wof:placetype":"venue"
},
  "geometry": {"coordinates":[4.4807829857,50.7564468384],"type":"Point"}
}