{
  "type": "Feature",
  "properties": {
    "addr:full":"Vosseschijnstraat 38 Antwerpen Antwerpen 2030",
    "addr:housenumber":"38",
    "addr:postcode":"2030",
    "addr:street":"Vosseschijnstraat",
    "iso:country":"BE",
    "sg:address":"Vosseschijnstraat 38",
    "sg:city":"Antwerpen",
    "sg:orig_category":"Decoratiestoffen and buitenhuistextiel Fab",
    "sg:phone":"+32 3 542 69 69",
    "sg:postcode":"2030",
    "sg:province":"Antwerpen",
    "wof:name":"Uvo",
    "wof:placetype":"venue"
},
  "geometry": {"coordinates":[4.4163517952,51.2556991577],"type":"Point"}
}