{
  "type": "Feature",
  "properties": {
    "addr:full":"Rue Cit\u00e9 Des Oiseaux 22 Fontaine-l'ev\u00eaque Hainaut 6140",
    "addr:housenumber":"22",
    "addr:postcode":"6140",
    "addr:street":"Rue Cite\u0301 Des Oiseaux;\u0302Que Hainaut",
    "iso:country":"BE",
    "sg:address":"Rue Cit\u00e9 Des Oiseaux 22",
    "sg:city":"Fontaine-l'ev\u00eaque",
    "sg:classifiers":[
        {
            "category":"Food & Beverages",
            "subcategory":"Groceries & Convenience Stores",
            "type":"Retail Goods"
        }
    ],
    "sg:phone":"+32 71 52 83 26",
    "sg:postcode":"6140",
    "sg:province":"Hainaut",
    "sg:tags":[
        "grocer"
    ],
    "wof:name":"Louis Delhaize",
    "wof:placetype":"venue"
},
  "geometry": {"coordinates":[-111.9644622803,46.2507972717],"type":"Point"}
}