{
  "type": "Feature",
  "properties": {
    "addr:full":"Vanderstichelenstraat 45 Blankenberge West-Vlaanderen 8370",
    "addr:housenumber":"45",
    "addr:postcode":"8370",
    "addr:street":"Vanderstichelenstraat",
    "iso:country":"BE",
    "sg:address":"Vanderstichelenstraat 45",
    "sg:city":"Blankenberge",
    "sg:orig_category":"V\u00e9los. Location d'articles de sport, de sport nautique and de camping",
    "sg:phone":"+32 50 41 75 08",
    "sg:postcode":"8370",
    "sg:province":"West-Vlaanderen",
    "wof:name":"M. Saelens",
    "wof:placetype":"venue"
},
  "geometry": {"coordinates":[3.1246349812,51.3146324158],"type":"Point"}
}