{
  "type": "Feature",
  "properties": {
    "addr:full":"Bochtlaan 34 Genk Limburg 3600",
    "addr:housenumber":"34",
    "addr:postcode":"3600",
    "addr:street":"Bochtlaan",
    "iso:country":"BE",
    "sg:address":"Bochtlaan 34",
    "sg:city":"Genk",
    "sg:classifiers":[
        {
            "category":"Health Services",
            "subcategory":"Health Practitioner",
            "type":"Services"
        }
    ],
    "sg:phone":"+32 486 83 09 06",
    "sg:postcode":"3600",
    "sg:province":"Limburg",
    "sg:tags":[
        "therapist",
        "speech"
    ],
    "wof:name":"Verbrugghe G",
    "wof:placetype":"venue"
},
  "geometry": {"coordinates":[5.502412796,50.969871521],"type":"Point"}
}