{
  "type": "Feature",
  "properties": {
    "iso:country":"BE",
    "sg:address":"Rue De La Cul\u00e9e 12",
    "sg:city":"Florenville",
    "sg:classifiers":[
        {
            "category":"Bars & Pubs",
            "type":"Food & Drink"
        }
    ],
    "sg:phone":"+32 61 31 36 50",
    "sg:postcode":"6820",
    "sg:province":"Luxembourg",
    "wof:name":"Taverne De La Semois",
    "wof:placetype":"venue"
},
  "geometry": {"coordinates":[5.3078799248,49.7007904053],"type":"Point"}
}