{
  "type": "Feature",
  "properties": {
    "iso:country":"BE",
    "sg:address":"St. Katelijnevest 25",
    "sg:city":"Antwerpen",
    "sg:orig_category":"Electrom\u00e9nager, t\u00e9l\u00e9visions and radios",
    "sg:phone":"+32 3 290 60 78",
    "sg:postcode":"2000",
    "sg:province":"Antwerpen",
    "wof:name":"T.s.c.",
    "wof:placetype":"venue"
},
  "geometry": {"coordinates":[4.405479908,51.2205314636],"type":"Point"}
}