{
  "type": "Feature",
  "properties": {
    "iso:country":"BE",
    "sg:address":"Chauss\u00e9e De Lodelinsart 56",
    "sg:city":"Charleroi (gilly)",
    "sg:classifiers":[
        {
            "category":"Banks & Credit Unions",
            "subcategory":"Financial Services",
            "type":"Services"
        }
    ],
    "sg:phone":"+32 71 41 12 96",
    "sg:postcode":"6060",
    "sg:province":"Hainaut",
    "sg:tags":[
        "financing"
    ],
    "wof:name":"Citibank Gilly",
    "wof:placetype":"venue"
},
  "geometry": {"coordinates":[4.4497418404,50.4203147888],"type":"Point"}
}