{
  "type": "Feature",
  "properties": {
    "addr:full":"Luikstraat 88 Lokeren Oost-Vlaanderen 9160",
    "addr:housenumber":"88",
    "addr:postcode":"9160",
    "addr:street":"Luikstraat",
    "iso:country":"BE",
    "sg:address":"Luikstraat 88",
    "sg:city":"Lokeren",
    "sg:classifiers":[
        {
            "category":"Professional",
            "subcategory":"Computer Services",
            "type":"Services"
        }
    ],
    "sg:phone":"+32 9 328 32 95",
    "sg:postcode":"9160",
    "sg:province":"Oost-Vlaanderen",
    "sg:tags":[
        "-",
        "processing",
        "data",
        "used"
    ],
    "wof:name":"Secintosh",
    "wof:placetype":"venue"
},
  "geometry": {"coordinates":[3.9900789261,51.1016921997],"type":"Point"}
}