{
  "type": "Feature",
  "properties": {
    "iso:country":"BE",
    "sg:address":"Mechelbaan 277",
    "sg:city":"Putte",
    "sg:orig_category":"Groententeelt",
    "sg:phone":"+32 15 75 63 32",
    "sg:postcode":"2580",
    "sg:province":"Antwerpen",
    "wof:name":"Paul Heylen",
    "wof:placetype":"venue"
},
  "geometry": {"coordinates":[4.6479620934,51.0593681335],"type":"Point"}
}