{
  "type": "Feature",
  "properties": {
    "addr:full":"Itali\u00cblaan 48 Mol Antwerpen 2400",
    "addr:housenumber":"48",
    "addr:postcode":"2400",
    "addr:street":"Italie\u0308Laan",
    "iso:country":"BE",
    "sg:address":"Itali\u00cblaan 48",
    "sg:city":"Mol",
    "sg:orig_category":"Ecoles de pilotage de bateaux and d\u00b4avions",
    "sg:phone":"+32 14 31 37 45",
    "sg:postcode":"2400",
    "sg:province":"Antwerpen",
    "wof:name":"Aero-kiewit",
    "wof:placetype":"venue"
},
  "geometry": {"coordinates":[5.1120052338,51.2148475647],"type":"Point"}
}