{
  "type": "Feature",
  "properties": {
    "iso:country":"BE",
    "sg:address":"Rue D'en Bas 5",
    "sg:city":"Leuze-en-hainaut",
    "sg:orig_category":"Kapsalons",
    "sg:phone":"+32 69 66 41 27",
    "sg:postcode":"7906",
    "sg:province":"Hainaut",
    "wof:name":"Coiff'extr\u00came Elle & Lui",
    "wof:placetype":"venue"
},
  "geometry": {"coordinates":[3.575553894,50.6065635681],"type":"Point"}
}