{
  "type": "Feature",
  "properties": {
    "iso:country":"BE",
    "sg:address":"Jozef De Blockstraat 28",
    "sg:city":"Willebroek",
    "sg:classifiers":[
        {
            "category":"Insurance",
            "subcategory":"Insurance Agent",
            "type":"Services"
        }
    ],
    "sg:phone":"+32 3 886 66 01",
    "sg:postcode":"2830",
    "sg:province":"Antwerpen",
    "sg:tags":[
        "verzekeringsmakelaars",
        "expert"
    ],
    "wof:name":"Rimez Lucien",
    "wof:placetype":"venue"
},
  "geometry": {"coordinates":[4.3538179398,51.0373649597],"type":"Point"}
}