{
  "type": "Feature",
  "properties": {
    "iso:country":"BE",
    "sg:address":"Rue Neuve 73",
    "sg:city":"Libin",
    "sg:orig_category":"Antiquit\u00e9s",
    "sg:phone":"+32 61 65 61 84",
    "sg:postcode":"6890",
    "sg:province":"Luxembourg",
    "wof:name":"Librairie Dailly P.",
    "wof:placetype":"venue"
},
  "geometry": {"coordinates":[5.2562999725,49.9827537537],"type":"Point"}
}