{
  "type": "Feature",
  "properties": {
    "iso:country":"BE",
    "sg:address":"Beverestraat 117",
    "sg:city":"Oudenaarde",
    "sg:orig_category":"M\u00e9decins and sp\u00e9cialistes",
    "sg:phone":"+32 55 31 24 09",
    "sg:postcode":"9700",
    "sg:province":"Oost-Vlaanderen",
    "wof:name":"Pierre De Vos",
    "wof:placetype":"venue"
},
  "geometry": {"coordinates":[3.5959990025,50.8512039185],"type":"Point"}
}