{
  "type": "Feature",
  "properties": {
    "addr:full":"Borgersteinlei 18 Sint-katelijne-waver Antwerpen 2860",
    "addr:housenumber":"18",
    "addr:postcode":"2860",
    "addr:street":"Borgersteinlei",
    "iso:country":"BE",
    "sg:address":"Borgersteinlei 18",
    "sg:city":"Sint-katelijne-waver",
    "sg:classifiers":[
        {
            "category":"Arena",
            "subcategory":"Sports Club",
            "type":"Entertainment"
        }
    ],
    "sg:phone":"+32 15 55 34 00",
    "sg:postcode":"2860",
    "sg:province":"Antwerpen",
    "sg:tags":[
        "de"
    ],
    "wof:name":"Kick Boxing Mechelen",
    "wof:placetype":"venue"
},
  "geometry": {"coordinates":[4.5077600479,51.0404090881],"type":"Point"}
}