{
  "type": "Feature",
  "properties": {
    "addr:full":"Rue G\u00c9n\u00c9ral De Gaulle 71 Courcelles Hainaut 6180",
    "addr:housenumber":"71",
    "addr:postcode":"6180",
    "addr:street":"Rue Ge\u0301Ne\u0301Ral De Gaulle",
    "iso:country":"BE",
    "sg:address":"Rue G\u00c9n\u00c9ral De Gaulle 71",
    "sg:city":"Courcelles",
    "sg:orig_category":"Kapsalons",
    "sg:phone":"+32 71 45 32 14",
    "sg:postcode":"6180",
    "sg:province":"Hainaut",
    "wof:name":"Harmonie",
    "wof:placetype":"venue"
},
  "geometry": {"coordinates":[4.381234169,50.4566268921],"type":"Point"}
}