{
  "type": "Feature",
  "properties": {
    "addr:full":"Pallieterlaan 5 De Haan (klemskerke) West-Vlaanderen 8420",
    "addr:housenumber":"5",
    "addr:postcode":"8420",
    "addr:street":"Pallieterlaan",
    "iso:country":"BE",
    "sg:address":"Pallieterlaan 5",
    "sg:city":"De Haan (klemskerke)",
    "sg:classifiers":[
        {
            "category":"Building & Trades",
            "subcategory":"Pest Control",
            "type":"Services"
        }
    ],
    "sg:phone":"+32 59 23 58 35",
    "sg:postcode":"8420",
    "sg:province":"West-Vlaanderen",
    "sg:tags":[
        "painting",
        "contractor"
    ],
    "wof:name":"Casier R",
    "wof:placetype":"venue"
},
  "geometry": {"coordinates":[3.0369069576,51.2692985535],"type":"Point"}
}