{
  "type": "Feature",
  "properties": {
    "iso:country":"BE",
    "sg:address":"Rue Sainte-gertrude 18",
    "sg:city":"Court-saint-etienne",
    "sg:orig_category":"Diverse bedrijfsbeheeradviesbureaus",
    "sg:phone":"+32 10 61 16 85",
    "sg:postcode":"1490",
    "sg:province":"Brabant Wallon",
    "wof:name":"Thienpont Et Associ\u00c9s",
    "wof:placetype":"venue"
},
  "geometry": {"coordinates":[4.5409607887,50.6092185974],"type":"Point"}
}