{
  "type": "Feature",
  "properties": {
    "addr:full":"Kapelstraat 28 Wuustwezel (loenhout) Antwerpen 2990",
    "addr:housenumber":"28",
    "addr:postcode":"2990",
    "addr:street":"Kapelstraat",
    "iso:country":"BE",
    "sg:address":"Kapelstraat 28",
    "sg:city":"Wuustwezel (loenhout)",
    "sg:orig_category":"Non-Classified Establishments",
    "sg:phone":"+32 3 669 61 45",
    "sg:postcode":"2990",
    "sg:province":"Antwerpen",
    "wof:name":"Kuypers Gebr Bvba",
    "wof:placetype":"venue"
},
  "geometry": {"coordinates":[4.645925045,51.399684906],"type":"Point"}
}