{
  "type": "Feature",
  "properties": {
    "addr:full":"Lindekensveld 31 Lummen Limburg 3560",
    "addr:housenumber":"31",
    "addr:postcode":"3560",
    "addr:street":"Lindekensveld",
    "iso:country":"BE",
    "sg:address":"Lindekensveld 31",
    "sg:city":"Lummen",
    "sg:classifiers":[
        {
            "category":"Personal",
            "type":"Services"
        }
    ],
    "sg:phone":"+32 13 52 16 59",
    "sg:postcode":"3560",
    "sg:province":"Limburg",
    "sg:tags":[
        "party",
        "planning"
    ],
    "wof:name":"Traiteur Gaston Bvba",
    "wof:placetype":"venue"
},
  "geometry": {"coordinates":[5.197414875,50.9953308105],"type":"Point"}
}