{
  "type": "Feature",
  "properties": {
    "addr:full":"Sint-petrus En Paulusstraat 2 Roeselare (rumbeke) West-Vlaanderen 8800",
    "addr:housenumber":"2",
    "addr:postcode":"8800",
    "addr:street":"Paulusstraat",
    "iso:country":"BE",
    "sg:address":"Sint-petrus En Paulusstraat 2",
    "sg:city":"Roeselare (rumbeke)",
    "sg:classifiers":[
        {
            "category":"Home & Garden",
            "subcategory":"Building Materials",
            "type":"Retail Goods"
        }
    ],
    "sg:phone":"+32 51 20 98 11",
    "sg:postcode":"8800",
    "sg:province":"West-Vlaanderen",
    "sg:tags":[
        "wall",
        "cupboard"
    ],
    "wof:name":"'t Casteelken",
    "wof:placetype":"venue"
},
  "geometry": {"coordinates":[3.1560809612,50.9335403442],"type":"Point"}
}