{
  "type": "Feature",
  "properties": {
    "addr:full":"Rue Saint-gilles 158 Li\u00c8ge Li\u00e8ge 4000",
    "addr:housenumber":"158",
    "addr:postcode":"4000",
    "addr:street":"Rue Saint-Gilles",
    "iso:country":"BE",
    "sg:address":"Rue Saint-gilles 158",
    "sg:city":"Li\u00c8ge",
    "sg:orig_category":"Binnenhuisarchitecten",
    "sg:phone":"+32 4 222 30 04",
    "sg:postcode":"4000",
    "sg:province":"Li\u00e8ge",
    "wof:name":"Sylviane Pintus",
    "wof:placetype":"venue"
},
  "geometry": {"coordinates":[5.5628800392,50.6380844116],"type":"Point"}
}