{
  "type": "Feature",
  "properties": {
    "addr:full":"Langeweg 171 Overijse Vlaams-Brabant 3090",
    "addr:housenumber":"171",
    "addr:postcode":"3090",
    "addr:street":"Langeweg",
    "iso:country":"BE",
    "sg:address":"Langeweg 171",
    "sg:city":"Overijse",
    "sg:orig_category":"Gespecialiseerde residenti\u00eble bouw",
    "sg:phone":"+32 2 687 37 59",
    "sg:postcode":"3090",
    "sg:province":"Vlaams-Brabant",
    "wof:name":"Monteiro",
    "wof:placetype":"venue"
},
  "geometry": {"coordinates":[4.5029702187,50.7447319031],"type":"Point"}
}