{
  "type": "Feature",
  "properties": {
    "addr:full":"Crilsplein 2 Westerlo Antwerpen 2260",
    "addr:housenumber":"2",
    "addr:postcode":"2260",
    "addr:street":"Crilsplein",
    "iso:country":"BE",
    "sg:address":"Crilsplein 2",
    "sg:city":"Westerlo",
    "sg:orig_category":"Enseignement maternel and primaire",
    "sg:phone":"+32 14 21 86 67",
    "sg:postcode":"2260",
    "sg:province":"Antwerpen",
    "wof:name":"K.s.g.o. Trienenkant",
    "wof:placetype":"venue"
},
  "geometry": {"coordinates":[4.9023160934,51.1259613037],"type":"Point"}
}