{
  "type": "Feature",
  "properties": {
    "iso:country":"BE",
    "sg:address":"Slachthuisstraat 0",
    "sg:city":"Tienen",
    "sg:orig_category":"Chaussures",
    "sg:phone":"+32 16 81 82 58",
    "sg:postcode":"3300",
    "sg:province":"Vlaams-Brabant",
    "wof:name":"Shoe Discount",
    "wof:placetype":"venue"
},
  "geometry": {"coordinates":[4.948018074,50.8053474426],"type":"Point"}
}