{
  "type": "Feature",
  "properties": {
    "addr:full":"Jevoumont 65 Theux Li\u00e8ge 4910",
    "addr:housenumber":"65",
    "addr:postcode":"4910",
    "addr:street":"Jevoumont",
    "iso:country":"BE",
    "sg:address":"Jevoumont 65",
    "sg:city":"Theux",
    "sg:orig_category":"M\u00e9decins and sp\u00e9cialistes",
    "sg:phone":"+32 87 54 24 43",
    "sg:postcode":"4910",
    "sg:province":"Li\u00e8ge",
    "wof:name":"Anne Ruelle",
    "wof:placetype":"venue"
},
  "geometry": {"coordinates":[5.8039050102,50.5217247009],"type":"Point"}
}