{
  "type": "Feature",
  "properties": {
    "addr:full":"Ninoofsesteenweg 132 Sint-jans-molenbeek/molenbeek-saint-jean Bruxelles-Capitale 1080",
    "addr:housenumber":"132",
    "addr:postcode":"1080",
    "addr:street":"Ninoofsesteenweg",
    "iso:country":"BE",
    "sg:address":"Ninoofsesteenweg 132",
    "sg:city":"Sint-jans-molenbeek/molenbeek-saint-jean",
    "sg:orig_category":"Algemeen secundair onderwijs Technisch and beroeps secundair onderwijs",
    "sg:phone":"+32 2 410 15 03",
    "sg:postcode":"1080",
    "sg:province":"Bruxelles-Capitale",
    "wof:name":"Imelda-instituut",
    "wof:placetype":"venue"
},
  "geometry": {"coordinates":[4.3266692162,50.8491325378],"type":"Point"}
}