{
  "type": "Feature",
  "properties": {
    "addr:full":"Hoogstraat 51 C Roeselare West-Vlaanderen 8800",
    "addr:housenumber":"51 c",
    "addr:postcode":"8800",
    "addr:street":"Hoogstraat",
    "iso:country":"BE",
    "sg:address":"Hoogstraat 51 C",
    "sg:city":"Roeselare",
    "sg:classifiers":[
        {
            "category":"Insurance",
            "subcategory":"Life Insurance",
            "type":"Services"
        }
    ],
    "sg:phone":"+32 51 22 40 43",
    "sg:postcode":"8800",
    "sg:province":"West-Vlaanderen",
    "sg:tags":[
        "assurance"
    ],
    "wof:name":"Nuytten Eric Verzekeringen",
    "wof:placetype":"venue"
},
  "geometry": {"coordinates":[3.1463499069,50.9309806824],"type":"Point"}
}