{
  "type": "Feature",
  "properties": {
    "addr:full":"Rue Des Vertes Feuilles 16 Frasnes-lez-anvaing Hainaut 7912",
    "addr:housenumber":"16",
    "addr:postcode":"7912",
    "addr:street":"Rue Des Vertes Feuilles",
    "iso:country":"BE",
    "sg:address":"Rue Des Vertes Feuilles 16",
    "sg:city":"Frasnes-lez-anvaing",
    "sg:orig_category":"Artistes ind\u00e9pendants",
    "sg:phone":"+32 69 76 84 59",
    "sg:postcode":"7912",
    "sg:province":"Hainaut",
    "wof:name":"Noel",
    "wof:placetype":"venue"
},
  "geometry": {"coordinates":[3.6226279736,50.7113418579],"type":"Point"}
}