{
  "type": "Feature",
  "properties": {
    "addr:full":"Meremweg 33 Bilzen Limburg 3740",
    "addr:housenumber":"33",
    "addr:postcode":"3740",
    "addr:street":"Meremweg",
    "iso:country":"BE",
    "sg:address":"Meremweg 33",
    "sg:city":"Bilzen",
    "sg:classifiers":[
        {
            "category":"Health Services",
            "subcategory":"Health Practitioner",
            "type":"Services"
        }
    ],
    "sg:phone":"+32 89 41 26 36",
    "sg:postcode":"3740",
    "sg:province":"Limburg",
    "sg:tags":[
        "physiotherapist"
    ],
    "wof:name":"Langenaken A-m",
    "wof:placetype":"venue"
},
  "geometry": {"coordinates":[5.5043621063,50.8677062988],"type":"Point"}
}