{
  "type": "Feature",
  "properties": {
    "iso:country":"BE",
    "sg:address":"Rue Barri\u00e8re Moye 28",
    "sg:city":"Wavre",
    "sg:classifiers":[
        {
            "category":"Health Services",
            "subcategory":"Doctor",
            "type":"Services"
        }
    ],
    "sg:phone":"+32 10 24 22 53",
    "sg:postcode":"1300",
    "sg:province":"Brabant Wallon",
    "sg:tags":[
        "medicinephysicians",
        "surgeon"
    ],
    "wof:name":"Corbeel L",
    "wof:placetype":"venue"
},
  "geometry": {"coordinates":[4.6154079437,50.7058792114],"type":"Point"}
}