{
  "type": "Feature",
  "properties": {
    "addr:full":"Avenue Armand Huysmans 54 Box 1 Bruxelles (ixelles) Bruxelles-Capitale 1050",
    "addr:housenumber":"54;1",
    "addr:postcode":"1050",
    "addr:street":"Avenue Armand Huysmans;Box",
    "iso:country":"BE",
    "sg:address":"Avenue Armand Huysmans 54 Box 1",
    "sg:city":"Bruxelles (ixelles)",
    "sg:classifiers":[
        {
            "category":"Professional",
            "subcategory":"Lawyer & Legal Services",
            "type":"Services"
        }
    ],
    "sg:phone":"+32 2 649 14 92",
    "sg:postcode":"1050",
    "sg:province":"Bruxelles-Capitale",
    "wof:name":"Du Jardin T",
    "wof:placetype":"venue"
},
  "geometry": {"coordinates":[4.3863430023,50.8136100769],"type":"Point"}
}