{
  "type": "Feature",
  "properties": {
    "iso:country":"BE",
    "sg:address":"Chauss\u00e9e De Namur 172",
    "sg:city":"Eghez\u00e9e (leuze)",
    "sg:classifiers":[
        {
            "category":"Real Estate",
            "subcategory":"Architect",
            "type":"Services"
        }
    ],
    "sg:phone":"+32 81 51 14 44",
    "sg:postcode":"5310",
    "sg:province":"Namur",
    "wof:name":"Dubois L",
    "wof:placetype":"venue"
},
  "geometry": {"coordinates":[4.9116740227,50.5860519409],"type":"Point"}
}