{
  "type": "Feature",
  "properties": {
    "addr:full":"Kemzekedorp 34 Stekene Oost-Vlaanderen 9190",
    "addr:housenumber":"34",
    "addr:postcode":"9190",
    "addr:street":"Kemzekedorp",
    "iso:country":"BE",
    "sg:address":"Kemzekedorp 34",
    "sg:city":"Stekene",
    "sg:orig_category":"Verplichte sociale verzekeringen",
    "sg:phone":"+32 3 779 60 03",
    "sg:postcode":"9190",
    "sg:province":"Oost-Vlaanderen",
    "wof:name":"Christelijke Mutualiteit",
    "wof:placetype":"venue"
},
  "geometry": {"coordinates":[4.0777111053,51.2069778442],"type":"Point"}
}