{
  "type": "Feature",
  "properties": {
    "addr:full":"Stationsstraat 14 Hooglede West-Vlaanderen 8830",
    "addr:housenumber":"14",
    "addr:postcode":"8830",
    "addr:street":"Stationsstraat",
    "iso:country":"BE",
    "sg:address":"Stationsstraat 14",
    "sg:city":"Hooglede",
    "sg:orig_category":"Apotheken",
    "sg:phone":"+32 51 22 71 19",
    "sg:postcode":"8830",
    "sg:province":"West-Vlaanderen",
    "wof:name":"Marc Delbeke",
    "wof:placetype":"venue"
},
  "geometry": {"coordinates":[3.0997579098,50.997089386],"type":"Point"}
}