{
  "type": "Feature",
  "properties": {
    "addr:full":"Rue Gustave-delperdange 12 Bastenaken Luxembourg 6600",
    "addr:housenumber":"12",
    "addr:postcode":"6600",
    "addr:street":"Rue Gustave-Delperdange",
    "iso:country":"BE",
    "sg:address":"Rue Gustave-delperdange 12",
    "sg:city":"Bastenaken",
    "sg:orig_category":"Formation permanente",
    "sg:phone":"+32 61 21 53 51",
    "sg:postcode":"6600",
    "sg:province":"Luxembourg",
    "wof:name":"Cefa",
    "wof:placetype":"venue"
},
  "geometry": {"coordinates":[5.745347023,50.0071411133],"type":"Point"}
}