{
  "type": "Feature",
  "properties": {
    "addr:full":"Rue Henri Dunant 166 Mons Hainaut 7000",
    "addr:housenumber":"166",
    "addr:postcode":"7000",
    "addr:street":"Rue Henri Dunant;Hainaut",
    "iso:country":"BE",
    "sg:address":"Rue Henri Dunant 166",
    "sg:city":"Mons",
    "sg:orig_category":"Eleveurs d'animaux divers",
    "sg:phone":"+32 65 31 46 11",
    "sg:postcode":"7000",
    "sg:province":"Hainaut",
    "wof:name":"Apiculture Du Monde",
    "wof:placetype":"venue"
},
  "geometry": {"coordinates":[3.9654510021,50.4689216614],"type":"Point"}
}