{
  "type": "Feature",
  "properties": {
    "addr:full":"Rue Xhav\u00c9e 11-13 Verviers Li\u00e8ge 4800",
    "addr:postcode":"11-13;4800",
    "addr:street":"Rue Xhave\u0301E",
    "iso:country":"BE",
    "sg:address":"Rue Xhav\u00c9e 11-13",
    "sg:city":"Verviers",
    "sg:orig_category":"Banken and kredietinstellingen",
    "sg:phone":"+32 87 33 21 75",
    "sg:postcode":"4800",
    "sg:province":"Li\u00e8ge",
    "wof:name":"Bacob",
    "wof:placetype":"venue"
},
  "geometry": {"coordinates":[5.8598461151,50.5917701721],"type":"Point"}
}