{
  "type": "Feature",
  "properties": {
    "iso:country":"BE",
    "sg:address":"Route De Mons 69",
    "sg:city":"Sivry-rance",
    "sg:orig_category":"V\u00e9hicules automobiles. Entretien and r\u00e9parations de voitures",
    "sg:phone":"+32 60 45 63 45",
    "sg:postcode":"6470",
    "sg:province":"Hainaut",
    "wof:name":"Garage Julien",
    "wof:placetype":"venue"
},
  "geometry": {"coordinates":[4.235159874,50.1711502075],"type":"Point"}
}