{
  "type": "Feature",
  "properties": {
    "iso:country":"BE",
    "sg:address":"Markt 45",
    "sg:city":"Zele",
    "sg:orig_category":"Banken and kredietinstellingen",
    "sg:phone":"+32 52 44 46 36",
    "sg:postcode":"9240",
    "sg:province":"Oost-Vlaanderen",
    "wof:name":"Kbc",
    "wof:placetype":"venue"
},
  "geometry": {"coordinates":[4.0374588966,51.0683822632],"type":"Point"}
}