{
  "type": "Feature",
  "properties": {
    "iso:country":"BE",
    "sg:address":"Wippelberg 86bb",
    "sg:city":"Arendonk",
    "sg:orig_category":"Etalage- and showroomontwerpers",
    "sg:phone":"+32 14 67 86 88",
    "sg:postcode":"2370",
    "sg:province":"Antwerpen",
    "wof:name":"Brouwers",
    "wof:placetype":"venue"
},
  "geometry": {"coordinates":[5.0980029106,51.319519043],"type":"Point"}
}