{
  "type": "Feature",
  "properties": {
    "iso:country":"BE",
    "sg:address":"Markt 20",
    "sg:city":"Ichtegem",
    "sg:classifiers":[
        {
            "category":"Retail",
            "subcategory":"Event Space",
            "type":"Services"
        }
    ],
    "sg:phone":"+32 51 58 13 13",
    "sg:postcode":"8480",
    "sg:province":"West-Vlaanderen",
    "sg:tags":[
        "rental",
        "-",
        "hall"
    ],
    "wof:name":"De Somme",
    "wof:placetype":"venue"
},
  "geometry": {"coordinates":[3.0101490021,51.0920677185],"type":"Point"}
}