{
  "type": "Feature",
  "properties": {
    "addr:full":"Avenue Capitaine Piret 21 Box 28 Bruxelles (woluwe-saint-pierre) Bruxelles-Capitale 1150",
    "addr:housenumber":"21 box 28",
    "addr:postcode":"1150",
    "addr:street":"Avenue Capitaine Piret",
    "iso:country":"BE",
    "sg:address":"Avenue Capitaine Piret 21 Box 28",
    "sg:city":"Bruxelles (woluwe-saint-pierre)",
    "sg:classifiers":[
        {
            "category":"Professional",
            "subcategory":"Accounting & Tax Preparation",
            "type":"Services"
        }
    ],
    "sg:phone":"+32 2 770 88 36",
    "sg:postcode":"1150",
    "sg:province":"Bruxelles-Capitale",
    "sg:tags":[
        "accountant"
    ],
    "wof:name":"Deli\u00e8ge Ch",
    "wof:placetype":"venue"
},
  "geometry": {"coordinates":[4.422082901,50.8382492065],"type":"Point"}
}