{
  "type": "Feature",
  "properties": {
    "addr:full":"Quai Aux Hu\u00eetres 22 Wavre Brabant Wallon 1300",
    "addr:housenumber":"22;1300",
    "addr:street":"Quai Aux Hui\u0302Tres",
    "iso:country":"BE",
    "sg:address":"Quai Aux Hu\u00eetres 22",
    "sg:city":"Wavre",
    "sg:classifiers":[
        {
            "category":"Home & Garden",
            "subcategory":"Household Appliances",
            "type":"Retail Goods"
        }
    ],
    "sg:phone":"+32 475 69 32 56",
    "sg:postcode":"1300",
    "sg:province":"Brabant Wallon",
    "sg:tags":[
        "repair",
        "mainten",
        "-",
        "electric"
    ],
    "wof:name":"Collart M",
    "wof:placetype":"venue"
},
  "geometry": {"coordinates":[4.6116380692,50.7152099609],"type":"Point"}
}