{
  "type": "Feature",
  "properties": {
    "iso:country":"BE",
    "sg:address":"Luikersteenweg 15",
    "sg:city":"Sint-truiden",
    "sg:orig_category":"Winkelinrichting and handelsuitrusting Gh",
    "sg:phone":"+32 11 68 32 60",
    "sg:postcode":"3800",
    "sg:province":"Limburg",
    "wof:name":"Kleykens En Koll",
    "wof:placetype":"venue"
},
  "geometry": {"coordinates":[5.1893410683,50.8120384216],"type":"Point"}
}