{
  "type": "Feature",
  "properties": {
    "addr:full":"Paul Hymanslaan 111b24 Sint-lambrechts-woluwe/woluwe-saint-lambert Bruxelles-Capitale 1200",
    "addr:housenumber":"111b24 sint-lambrechts-woluwe",
    "addr:postcode":"1200",
    "addr:street":"Hymanslaan",
    "iso:country":"BE",
    "sg:address":"Paul Hymanslaan 111b24",
    "sg:city":"Sint-lambrechts-woluwe/woluwe-saint-lambert",
    "sg:orig_category":"Artsen and specialisten",
    "sg:phone":"+32 2 770 13 49",
    "sg:postcode":"1200",
    "sg:province":"Bruxelles-Capitale",
    "wof:name":"Patrick Martiny",
    "wof:placetype":"venue"
},
  "geometry": {"coordinates":[4.4319138527,50.8470878601],"type":"Point"}
}