{
  "type": "Feature",
  "properties": {
    "addr:full":"Place Du Centenaire Flechet 14a Dalhem (warsage) Li\u00e8ge 4608",
    "addr:housenumber":"14a",
    "addr:postcode":"4608",
    "addr:street":"Place Du Centenaire Flechet",
    "iso:country":"BE",
    "sg:address":"Place Du Centenaire Flechet 14a",
    "sg:city":"Dalhem (warsage)",
    "sg:classifiers":[
        {
            "category":"Building & Trades",
            "subcategory":"Construction",
            "type":"Services"
        }
    ],
    "sg:phone":"+32 4 387 63 81",
    "sg:postcode":"4608",
    "sg:province":"Li\u00e8ge",
    "sg:tags":[
        "carpenter"
    ],
    "wof:name":"Lejeune E",
    "wof:placetype":"venue"
},
  "geometry": {"coordinates":[5.7779669762,50.7188148499],"type":"Point"}
}