{
  "type": "Feature",
  "properties": {
    "iso:country":"BE",
    "sg:address":"Vanden Tymplestraat 59 Box 2",
    "sg:city":"Leuven",
    "sg:classifiers":[
        {
            "category":"Professional",
            "subcategory":"Computer Services",
            "type":"Services"
        }
    ],
    "sg:phone":"+32 16 22 71 68",
    "sg:postcode":"3000",
    "sg:province":"Vlaams-Brabant",
    "sg:tags":[
        "-",
        "processing",
        "data",
        "software"
    ],
    "wof:name":"Trading And Consulting Company Bvba",
    "wof:placetype":"venue"
},
  "geometry": {"coordinates":[4.7101612091,50.8835639954],"type":"Point"}
}