{
  "type": "Feature",
  "properties": {
    "iso:country":"BE",
    "sg:address":"Ijzerstraat 16",
    "sg:city":"Alveringem",
    "sg:orig_category":"HUISBRANDOLIE Varkenskwekers",
    "sg:phone":"+32 57 30 04 73",
    "sg:postcode":"8691",
    "sg:province":"West-Vlaanderen",
    "wof:name":"Leo Baes",
    "wof:placetype":"venue"
},
  "geometry": {"coordinates":[2.6718599796,50.9428634644],"type":"Point"}
}