{
  "type": "Feature",
  "properties": {
    "iso:country":"BE",
    "sg:address":"Rue Rivi\u00e8re 42",
    "sg:city":"Estinnes (estinnes-au-mont)",
    "sg:classifiers":[
        {
            "category":"Health Services",
            "subcategory":"Doctor",
            "type":"Services"
        }
    ],
    "sg:phone":"+32 64 36 68 30",
    "sg:postcode":"7120",
    "sg:province":"Hainaut",
    "sg:tags":[
        "medicinephysicians",
        "surgeon"
    ],
    "wof:name":"Lacroix L",
    "wof:placetype":"venue"
},
  "geometry": {"coordinates":[4.1009688377,50.4021759033],"type":"Point"}
}