{
  "type": "Feature",
  "properties": {
    "addr:full":"Rue Omer Pierard 142 Gembloux Namur 5030",
    "addr:housenumber":"142",
    "addr:postcode":"5030",
    "addr:street":"Rue Omer Pierard;Namur",
    "iso:country":"BE",
    "sg:address":"Rue Omer Pierard 142",
    "sg:city":"Gembloux",
    "sg:orig_category":"Tuinen",
    "sg:phone":"+32 81 61 02 52",
    "sg:postcode":"5030",
    "sg:province":"Namur",
    "wof:name":"Wibert",
    "wof:placetype":"venue"
},
  "geometry": {"coordinates":[4.6625828743,50.5917320251],"type":"Point"}
}