{
  "type": "Feature",
  "properties": {
    "iso:country":"BE",
    "sg:address":"Nieuwelaan 3a",
    "sg:city":"Meise",
    "sg:classifiers":[
        {
            "category":"Retail",
            "subcategory":"Veterinary Services",
            "type":"Services"
        }
    ],
    "sg:phone":"+32 2 269 80 01",
    "sg:postcode":"1860",
    "sg:province":"Vlaams-Brabant",
    "sg:tags":[
        "veterinarian"
    ],
    "wof:name":"Lamont S",
    "wof:placetype":"venue"
},
  "geometry": {"coordinates":[4.3299298286,50.9358177185],"type":"Point"}
}