{
  "type": "Feature",
  "properties": {
    "iso:country":"BE",
    "sg:address":"Rue Mon Plaisir 53",
    "sg:city":"Morlanwelz",
    "sg:classifiers":[
        {
            "category":"Fast Food",
            "type":"Food & Drink"
        }
    ],
    "sg:phone":"+32 64 44 94 63",
    "sg:postcode":"7141",
    "sg:province":"Hainaut",
    "sg:tags":[
        "meeneem",
        "restaurant"
    ],
    "wof:name":"Friterie Stefanini",
    "wof:placetype":"venue"
},
  "geometry": {"coordinates":[4.264770031,50.4544525146],"type":"Point"}
}