{
  "type": "Feature",
  "properties": {
    "iso:country":"BE",
    "sg:address":"Rue De Goz\u00c9e 167",
    "sg:city":"Montigny-le-tilleul",
    "sg:orig_category":"Fleurs and plantes",
    "sg:phone":"+32 71 51 99 13",
    "sg:postcode":"6110",
    "sg:province":"Hainaut",
    "wof:name":"Vincent Dewever",
    "wof:placetype":"venue"
},
  "geometry": {"coordinates":[4.3812918663,50.3867530823],"type":"Point"}
}