{
  "type": "Feature",
  "properties": {
    "addr:full":"Boulevard Auguste Reyers 103 Box 18 Bruxelles (schaerbeek) Bruxelles-Capitale 1030",
    "addr:housenumber":"103 box 18",
    "addr:postcode":"1030",
    "addr:street":"Boulevard Auguste Reyers",
    "iso:country":"BE",
    "sg:address":"Boulevard Auguste Reyers 103 Box 18",
    "sg:city":"Bruxelles (schaerbeek)",
    "sg:classifiers":[
        {
            "category":"Health Services",
            "subcategory":"Doctor",
            "type":"Services"
        }
    ],
    "sg:phone":"+32 2 736 88 59",
    "sg:postcode":"1030",
    "sg:province":"Bruxelles-Capitale",
    "sg:tags":[
        "psychotherapist",
        "psychoanalyst"
    ],
    "wof:name":"Storm B",
    "wof:placetype":"venue"
},
  "geometry": {"coordinates":[4.400739193,50.8510169983],"type":"Point"}
}