{
  "type": "Feature",
  "properties": {
    "addr:full":"Rue Wattelar Maximilien 27 Charleroi (jumet) Hainaut 6040",
    "addr:housenumber":"27",
    "addr:postcode":"6040",
    "addr:street":"Rue Wattelar Maximilien",
    "iso:country":"BE",
    "sg:address":"Rue Wattelar Maximilien 27",
    "sg:city":"Charleroi (jumet)",
    "sg:classifiers":[
        {
            "category":"Insurance",
            "subcategory":"Insurance Agent",
            "type":"Services"
        }
    ],
    "sg:phone":"+32 71 35 91 56",
    "sg:postcode":"6040",
    "sg:province":"Hainaut",
    "sg:tags":[
        "broker"
    ],
    "wof:name":"Cofiscass Sprl",
    "wof:placetype":"venue"
},
  "geometry": {"coordinates":[4.4199209213,50.4442138672],"type":"Point"}
}