{
  "type": "Feature",
  "properties": {
    "addr:full":"Rue Paul Emile Janson 3a Box 10 Bruxelles (ixelles) Bruxelles-Capitale 1050",
    "addr:housenumber":"3a box 10",
    "addr:postcode":"1050",
    "addr:street":"Rue Paul Emile Janson",
    "iso:country":"BE",
    "sg:address":"Rue Paul Emile Janson 3a Box 10",
    "sg:city":"Bruxelles (ixelles)",
    "sg:classifiers":[
        {
            "category":"Professional",
            "subcategory":"Accounting & Tax Preparation",
            "type":"Services"
        }
    ],
    "sg:phone":"+32 2 538 70 16",
    "sg:postcode":"1050",
    "sg:province":"Bruxelles-Capitale",
    "sg:tags":[
        "bookkeeper"
    ],
    "wof:name":"Florani J-c",
    "wof:placetype":"venue"
},
  "geometry": {"coordinates":[4.3613300323,50.827709198],"type":"Point"}
}