{
  "type": "Feature",
  "properties": {
    "iso:country":"BE",
    "sg:address":"Edingsesteenweg 211",
    "sg:city":"Gooik (leerbeek)",
    "sg:classifiers":[
        {
            "category":"Food & Beverages",
            "subcategory":"Groceries & Convenience Stores",
            "type":"Retail Goods"
        }
    ],
    "sg:phone":"+32 2 532 29 47",
    "sg:postcode":"1755",
    "sg:province":"Vlaams-Brabant",
    "sg:tags":[
        "grocer"
    ],
    "wof:name":"Hoeksken ('t)",
    "wof:placetype":"venue"
},
  "geometry": {"coordinates":[4.1230998039,50.7871284485],"type":"Point"}
}