{
  "type": "Feature",
  "properties": {
    "addr:full":"Sint-annastraat 18 Waasmunster Oost-Vlaanderen 9250",
    "addr:housenumber":"18",
    "addr:postcode":"9250",
    "addr:street":"Sint-Annastraat",
    "iso:country":"BE",
    "sg:address":"Sint-annastraat 18",
    "sg:city":"Waasmunster",
    "sg:orig_category":"Voertuigen",
    "sg:phone":"+32 52 47 88 73",
    "sg:postcode":"9250",
    "sg:province":"Oost-Vlaanderen",
    "wof:name":"Viviane Van Eenaeme",
    "wof:placetype":"venue"
},
  "geometry": {"coordinates":[4.0859050751,51.095161438],"type":"Point"}
}