{
  "type": "Feature",
  "properties": {
    "addr:full":"Zeedijk 75 Blankenberge West-Vlaanderen 8370",
    "addr:housenumber":"75",
    "addr:postcode":"8370",
    "addr:street":"Zeedijk",
    "iso:country":"BE",
    "sg:address":"Zeedijk 75",
    "sg:city":"Blankenberge",
    "sg:classifiers":[
        {
            "category":"Bars & Pubs",
            "type":"Food & Drink"
        }
    ],
    "sg:phone":"+32 50 41 95 52",
    "sg:postcode":"8370",
    "sg:province":"West-Vlaanderen",
    "wof:name":"Caf\u00e9 Au Luxembourg",
    "wof:placetype":"venue"
},
  "geometry": {"coordinates":[3.1214039326,51.3145141602],"type":"Point"}
}