{
  "type": "Feature",
  "properties": {
    "addr:full":"Veldstraat 66 Gent Oost-Vlaanderen 9000",
    "addr:housenumber":"66",
    "addr:postcode":"9000",
    "addr:street":"Veldstraat;Oost-Vlaanderen",
    "iso:country":"BE",
    "sg:address":"Veldstraat 66",
    "sg:city":"Gent",
    "sg:orig_category":"Apotheken",
    "sg:phone":"+32 9 225 35 33",
    "sg:postcode":"9000",
    "sg:province":"Oost-Vlaanderen",
    "wof:name":"Apotheek Esco-farma",
    "wof:placetype":"venue"
},
  "geometry": {"coordinates":[3.721683979,51.0521316528],"type":"Point"}
}