{
  "type": "Feature",
  "properties": {
    "addr:full":"Rue Des Merles 3 Aubange Luxembourg 6790",
    "addr:housenumber":"3",
    "addr:postcode":"6790",
    "addr:street":"Rue Des Merles",
    "iso:country":"BE",
    "sg:address":"Rue Des Merles 3",
    "sg:city":"Aubange",
    "sg:orig_category":"Diverse bedrijfsbeheeradviesbureaus",
    "sg:phone":"+32 63 38 60 16",
    "sg:postcode":"6790",
    "sg:province":"Luxembourg",
    "wof:name":"Janabel",
    "wof:placetype":"venue"
},
  "geometry": {"coordinates":[5.814330101,49.5655288696],"type":"Point"}
}