{
  "type": "Feature",
  "properties": {
    "iso:country":"BE",
    "sg:address":"Assenedesteenweg 181",
    "sg:city":"Zelzate",
    "sg:orig_category":"Baby- and kinderkleding",
    "sg:phone":"+32 9 344 70 96",
    "sg:postcode":"9060",
    "sg:province":"Oost-Vlaanderen",
    "wof:name":"Huis Poesie",
    "wof:placetype":"venue"
},
  "geometry": {"coordinates":[3.786698103,51.2012939453],"type":"Point"}
}