{
  "type": "Feature",
  "properties": {
    "iso:country":"BE",
    "sg:address":"Boulevard Industriel 20",
    "sg:city":"Comines-warneton (comines)",
    "sg:classifiers":[
        {
            "category":"Banks & Credit Unions",
            "subcategory":"Investment Brokerage",
            "type":"Services"
        }
    ],
    "sg:phone":"+32 56 55 88 22",
    "sg:postcode":"7780",
    "sg:province":"Hainaut",
    "sg:tags":[
        "printing",
        "-"
    ],
    "wof:name":"Tanghe Printing Bvba",
    "wof:placetype":"venue"
},
  "geometry": {"coordinates":[3.0157558918,50.7767868042],"type":"Point"}
}