{
  "type": "Feature",
  "properties": {
    "addr:full":"Rue Du Couvent 26 Mouscron Hainaut 7700",
    "addr:housenumber":"26",
    "addr:postcode":"7700",
    "addr:street":"Rue Du Couvent",
    "iso:country":"BE",
    "sg:address":"Rue Du Couvent 26",
    "sg:city":"Mouscron",
    "sg:classifiers":[
        {
            "category":"Shopping",
            "subcategory":"Florist",
            "type":"Retail Goods"
        }
    ],
    "sg:phone":"+32 56 84 49 52",
    "sg:postcode":"7700",
    "sg:province":"Hainaut",
    "wof:name":"Orchidee (l')",
    "wof:placetype":"venue"
},
  "geometry": {"coordinates":[3.2003901005,50.7419281006],"type":"Point"}
}