{
  "type": "Feature",
  "properties": {
    "iso:country":"BE",
    "sg:address":"Place De Buissenal 30",
    "sg:city":"Frasnes-lez-anvaing",
    "sg:orig_category":"Kapsalons",
    "sg:phone":"+32 69 86 62 88",
    "sg:postcode":"7911",
    "sg:province":"Hainaut",
    "wof:name":"Coiffure Mille Coupes",
    "wof:placetype":"venue"
},
  "geometry": {"coordinates":[3.6559739113,50.6647148132],"type":"Point"}
}