{
  "type": "Feature",
  "properties": {
    "addr:full":"Hombeeksesteenweg 368 Mechelen Antwerpen 2800",
    "addr:housenumber":"368",
    "addr:postcode":"2800",
    "addr:street":"Hombeeksesteenweg",
    "iso:country":"BE",
    "sg:address":"Hombeeksesteenweg 368",
    "sg:city":"Mechelen",
    "sg:orig_category":"Fiduciairies",
    "sg:phone":"+32 15 42 36 71",
    "sg:postcode":"2800",
    "sg:province":"Antwerpen",
    "wof:name":"Typ-top",
    "wof:placetype":"venue"
},
  "geometry": {"coordinates":[4.4595251083,51.0159759521],"type":"Point"}
}