{
  "type": "Feature",
  "properties": {
    "iso:country":"BE",
    "sg:address":"Rue Des Chasseurs Ardennais 129",
    "sg:city":"Vresse-sur-semois (sugny)",
    "sg:classifiers":[
        {
            "category":"Building & Trades",
            "subcategory":"Landscaping Services",
            "type":"Services"
        }
    ],
    "sg:phone":"+32 61 50 09 73",
    "sg:postcode":"5550",
    "sg:province":"Namur",
    "sg:tags":[
        "forestry"
    ],
    "wof:name":"Zourane Fr\u00e8res Sa",
    "wof:placetype":"venue"
},
  "geometry": {"coordinates":[4.9030809402,49.8140602112],"type":"Point"}
}