{
  "type": "Feature",
  "properties": {
    "addr:full":"Place Georges Ista 24 Liege-centre Li\u00e8ge 4030",
    "addr:housenumber":"24",
    "addr:postcode":"4030",
    "addr:street":"Place Georges Ista",
    "iso:country":"BE",
    "sg:address":"Place Georges Ista 24",
    "sg:city":"Liege-centre",
    "sg:orig_category":"Auto-\u00e9coles",
    "sg:phone":"+32 87 27 00 18",
    "sg:postcode":"4030",
    "sg:province":"Li\u00e8ge",
    "wof:name":"Ecole De Conduite Plus Du R.a.c.b.",
    "wof:placetype":"venue"
},
  "geometry": {"coordinates":[2.4079089165,44.1636695862],"type":"Point"}
}