{
  "type": "Feature",
  "properties": {
    "iso:country":"BE",
    "sg:address":"Place Raymond Blyckaerts 6",
    "sg:city":"Elsene/ixelles",
    "sg:orig_category":"M\u00e9decins and sp\u00e9cialistes",
    "sg:phone":"+32 2 646 13 67",
    "sg:postcode":"1050",
    "sg:province":"Bruxelles-Capitale",
    "wof:name":"C. Adant",
    "wof:placetype":"venue"
},
  "geometry": {"coordinates":[4.3742260933,50.8328285217],"type":"Point"}
}