{
  "type": "Feature",
  "properties": {
    "addr:full":"Bourgetlaan 40 Brussel Bruxelles-Capitale 1130",
    "addr:housenumber":"40",
    "addr:postcode":"1130",
    "addr:street":"Bourgetlaan",
    "iso:country":"BE",
    "sg:address":"Bourgetlaan 40",
    "sg:city":"Brussel",
    "sg:classifiers":[
        {
            "category":"Organizations",
            "subcategory":"Community Association",
            "type":"Services"
        }
    ],
    "sg:phone":"+32 2 708 36 31",
    "sg:postcode":"1130",
    "sg:province":"Bruxelles-Capitale",
    "sg:tags":[
        "management",
        "public",
        "authority"
    ],
    "wof:name":"Kpmg Support Services E.s.v.",
    "wof:placetype":"venue"
},
  "geometry": {"coordinates":[4.4316191673,50.8777885437],"type":"Point"}
}