{
  "type": "Feature",
  "properties": {
    "iso:country":"BE",
    "sg:address":"Rue De Huy 224",
    "sg:city":"Faimes",
    "sg:orig_category":"Boucheries",
    "sg:phone":"+32 19 32 26 03",
    "sg:postcode":"4317",
    "sg:province":"Li\u00e8ge",
    "wof:name":"Fabrice Radoux",
    "wof:placetype":"venue"
},
  "geometry": {"coordinates":[5.2543201447,50.6671295166],"type":"Point"}
}