{
  "type": "Feature",
  "properties": {
    "addr:full":"Rue Fr\u00e9d\u00e9ric Pelletier 45 Bruxelles (schaerbeek) Bruxelles-Capitale 1030",
    "addr:housenumber":"45",
    "addr:postcode":"1030",
    "addr:street":"Rue Fre\u0301De\u0301Ric Pelletier",
    "iso:country":"BE",
    "sg:address":"Rue Fr\u00e9d\u00e9ric Pelletier 45",
    "sg:city":"Bruxelles (schaerbeek)",
    "sg:classifiers":[
        {
            "category":"Professional",
            "subcategory":"Lawyer & Legal Services",
            "type":"Services"
        }
    ],
    "sg:phone":"+32 2 735 16 60",
    "sg:postcode":"1030",
    "sg:province":"Bruxelles-Capitale",
    "wof:name":"Claes Robert",
    "wof:placetype":"venue"
},
  "geometry": {"coordinates":[4.4005651474,50.8454780579],"type":"Point"}
}