{
  "type": "Feature",
  "properties": {
    "iso:country":"BE",
    "sg:address":"Rue De Thoricourt 48",
    "sg:city":"Silly",
    "sg:classifiers":[
        {
            "category":"Cafe",
            "type":"Food & Drink"
        }
    ],
    "sg:phone":"+32 67 45 82 57",
    "sg:postcode":"7830",
    "sg:province":"Hainaut",
    "sg:tags":[
        "caf\u00e9s"
    ],
    "wof:name":"Caf\u00c9 Le Beau S\u00c9jour",
    "wof:placetype":"venue"
},
  "geometry": {"coordinates":[3.9305300713,50.6185340881],"type":"Point"}
}