{
  "type": "Feature",
  "properties": {
    "iso:country":"BE",
    "sg:address":"Rue Stroobants 48b",
    "sg:city":"Bruxelles (evere)",
    "sg:classifiers":[
        {
            "category":"Professional",
            "subcategory":"Printing & Photocopies",
            "type":"Services"
        }
    ],
    "sg:postcode":"1140",
    "sg:province":"Bruxelles-Capitale",
    "sg:tags":[
        "-",
        "offset"
    ],
    "wof:name":"Micrographex Sc",
    "wof:placetype":"venue"
},
  "geometry": {"coordinates":[4.3971171379,50.8794517517],"type":"Point"}
}