{
  "type": "Feature",
  "properties": {
    "addr:full":"Gorhez 275 Aubel Li\u00e8ge 4880",
    "addr:housenumber":"275",
    "addr:postcode":"4880",
    "addr:street":"Gorhez",
    "iso:country":"BE",
    "sg:address":"Gorhez 275",
    "sg:city":"Aubel",
    "sg:classifiers":[
        {
            "category":"Retail",
            "subcategory":"Animal Services",
            "type":"Services"
        }
    ],
    "sg:phone":"+32 87 68 79 27",
    "sg:postcode":"4880",
    "sg:province":"Li\u00e8ge",
    "sg:tags":[
        "grooming",
        "-",
        "dog"
    ],
    "wof:name":"Bo\u00eete \u00e0 Puces (la)",
    "wof:placetype":"venue"
},
  "geometry": {"coordinates":[5.8301229477,50.6986999512],"type":"Point"}
}