{
  "type": "Feature",
  "properties": {
    "addr:full":"Rue Du Ti\u00e8ge 116 Oupeye Li\u00e8ge 4680",
    "addr:housenumber":"116",
    "addr:postcode":"4680",
    "addr:street":"Rue Du Tie\u0300Ge",
    "iso:country":"BE",
    "sg:address":"Rue Du Ti\u00e8ge 116",
    "sg:city":"Oupeye",
    "sg:classifiers":[
        {
            "category":"Professional",
            "subcategory":"Lawyer & Legal Services",
            "type":"Services"
        }
    ],
    "sg:phone":"+32 4 264 31 27",
    "sg:postcode":"4680",
    "sg:province":"Li\u00e8ge",
    "wof:name":"Riga-corsale Maria",
    "wof:placetype":"venue"
},
  "geometry": {"coordinates":[5.6368608475,50.7116317749],"type":"Point"}
}