{
  "type": "Feature",
  "properties": {
    "iso:country":"BE",
    "sg:address":"De Plaats 18",
    "sg:city":"Knesselare",
    "sg:orig_category":"Boucheries",
    "sg:phone":"+32 9 374 14 15",
    "sg:postcode":"9910",
    "sg:province":"Oost-Vlaanderen",
    "wof:name":"Frank Stul",
    "wof:placetype":"venue"
},
  "geometry": {"coordinates":[3.4124610424,51.1390113831],"type":"Point"}
}