{
  "type": "Feature",
  "properties": {
    "addr:full":"Heieinde 18 Vosselaar Antwerpen 2350",
    "addr:housenumber":"18",
    "addr:postcode":"2350",
    "addr:street":"Heieinde",
    "iso:country":"BE",
    "sg:address":"Heieinde 18",
    "sg:city":"Vosselaar",
    "sg:classifiers":[
        {
            "category":"Cafe",
            "type":"Food & Drink"
        }
    ],
    "sg:phone":"+32 14 61 41 54",
    "sg:postcode":"2350",
    "sg:province":"Antwerpen",
    "sg:tags":[
        "caf\u00e9s"
    ],
    "wof:name":"Caf\u00c9 Calypso",
    "wof:placetype":"venue"
},
  "geometry": {"coordinates":[4.8854908943,51.3033790588],"type":"Point"}
}