{
  "type": "Feature",
  "properties": {
    "iso:country":"BE",
    "sg:address":"Neremstraat 2",
    "sg:city":"Borgloon",
    "sg:classifiers":[
        {
            "category":"Wholesale",
            "subcategory":"Fruits & Vegetables",
            "type":"Manufacturing & Wholesale Goods"
        }
    ],
    "sg:phone":"+32 12 74 21 48",
    "sg:postcode":"3840",
    "sg:province":"Limburg",
    "sg:tags":[
        "whol",
        "-"
    ],
    "wof:name":"Derwael Fruitbedrijf",
    "wof:placetype":"venue"
},
  "geometry": {"coordinates":[5.3341569901,50.7948646545],"type":"Point"}
}