{
  "type": "Feature",
  "properties": {
    "iso:country":"BE",
    "sg:address":"Aux Anciennes P\u00c2tures 9",
    "sg:city":"Chaudfontaine",
    "sg:orig_category":"Artsen and specialisten",
    "sg:phone":"+32 4 368 55 14",
    "sg:postcode":"4052",
    "sg:province":"Li\u00e8ge",
    "wof:name":"Pascale Eymael",
    "wof:placetype":"venue"
},
  "geometry": {"coordinates":[5.6288042068,50.5700340271],"type":"Point"}
}