{
  "type": "Feature",
  "properties": {
    "iso:country":"BE",
    "sg:address":"Rollegemstraat 164",
    "sg:city":"Ledegem",
    "sg:orig_category":"Installation de menuiserie en bois and plastique",
    "sg:phone":"+32 56 50 27 36",
    "sg:postcode":"8880",
    "sg:province":"West-Vlaanderen",
    "wof:name":"Antoine Dewitte",
    "wof:placetype":"venue"
},
  "geometry": {"coordinates":[3.1353259087,50.8613700867],"type":"Point"}
}