{
  "type": "Feature",
  "properties": {
    "addr:full":"Place De Bronckart 4 Li\u00e8ge 1 Li\u00e8ge 4000",
    "addr:housenumber":"4;1",
    "addr:postcode":"4000",
    "addr:street":"Place De Bronckart",
    "iso:country":"BE",
    "sg:address":"Place De Bronckart 4",
    "sg:city":"Li\u00e8ge 1",
    "sg:classifiers":[
        {
            "category":"Banks & Credit Unions",
            "subcategory":"Financial Services",
            "type":"Services"
        }
    ],
    "sg:phone":"+32 4 252 00 12",
    "sg:postcode":"4000",
    "sg:province":"Li\u00e8ge",
    "sg:tags":[
        "loan",
        "mortgage"
    ],
    "wof:name":"Omnium (l')",
    "wof:placetype":"venue"
},
  "geometry": {"coordinates":[5.5654258728,50.6299057007],"type":"Point"}
}