{
  "type": "Feature",
  "properties": {
    "addr:full":"Sint-laureisstraat 85 Antwerpen Antwerpen 2018",
    "addr:housenumber":"85",
    "addr:postcode":"2018",
    "addr:street":"Sint-Laureisstraat",
    "iso:country":"BE",
    "sg:address":"Sint-laureisstraat 85",
    "sg:city":"Antwerpen",
    "sg:classifiers":[
        {
            "category":"Cafe",
            "type":"Food & Drink"
        }
    ],
    "sg:phone":"+32 3 227 20 12",
    "sg:postcode":"2018",
    "sg:province":"Antwerpen",
    "sg:tags":[
        "caf\u00e9s"
    ],
    "wof:name":"Caf\u00c9 Modane",
    "wof:placetype":"venue"
},
  "geometry": {"coordinates":[4.3968038559,51.2023468018],"type":"Point"}
}