{
  "type": "Feature",
  "properties": {
    "iso:country":"BE",
    "sg:address":"Meersstraat 164b",
    "sg:city":"Liedekerke",
    "sg:classifiers":[
        {
            "category":"Farming",
            "subcategory":"Livestock Farm",
            "type":"Manufacturing & Wholesale Goods"
        }
    ],
    "sg:phone":"+32 53 66 64 18",
    "sg:postcode":"1770",
    "sg:province":"Vlaams-Brabant",
    "sg:tags":[
        "buyer"
    ],
    "wof:name":"Van Den Brande Jp",
    "wof:placetype":"venue"
},
  "geometry": {"coordinates":[4.0890250206,50.8783607483],"type":"Point"}
}