{
  "type": "Feature",
  "properties": {
    "addr:full":"Rue Des Fusill\u00e9s 20 Ottignies-louvain-la-neuve (ottignies) Brabant Wallon 1340",
    "addr:housenumber":"20",
    "addr:postcode":"ottignies-louvain-la-neuve;1340",
    "addr:street":"Rue Des Fusille\u0301S",
    "iso:country":"BE",
    "sg:address":"Rue Des Fusill\u00e9s 20",
    "sg:city":"Ottignies-louvain-la-neuve (ottignies)",
    "sg:classifiers":[
        {
            "category":"Community Center",
            "type":"Public Place"
        }
    ],
    "sg:phone":"+32 10 41 80 93",
    "sg:postcode":"1340",
    "sg:province":"Brabant Wallon",
    "sg:tags":[
        "medical"
    ],
    "wof:name":"Centre M\u00e9dico Psychoth\u00e9rapique",
    "wof:placetype":"venue"
},
  "geometry": {"coordinates":[4.5739212036,50.670135498],"type":"Point"}
}