{
  "type": "Feature",
  "properties": {
    "iso:country":"BE",
    "sg:address":"Rue Du Grenadier 37",
    "sg:city":"Frameries (eugies)",
    "sg:classifiers":[
        {
            "category":"Food & Beverages",
            "subcategory":"Cheese",
            "type":"Retail Goods"
        }
    ],
    "sg:phone":"+32 65 66 10 74",
    "sg:postcode":"7080",
    "sg:province":"Hainaut",
    "sg:tags":[
        "-"
    ],
    "wof:name":"Cattelan A",
    "wof:placetype":"venue"
},
  "geometry": {"coordinates":[3.867069006,50.38879776],"type":"Point"}
}