{
  "type": "Feature",
  "properties": {
    "iso:country":"BE",
    "sg:address":"Beverlosesteenweg 365",
    "sg:city":"Beringen",
    "sg:orig_category":"M\u00e9decins and sp\u00e9cialistes",
    "sg:phone":"+32 11 42 37 10",
    "sg:postcode":"3583",
    "sg:province":"Limburg",
    "wof:name":"Jozef Weckx",
    "wof:placetype":"venue"
},
  "geometry": {"coordinates":[5.2071199417,51.0680465698],"type":"Point"}
}