{
  "type": "Feature",
  "properties": {
    "addr:full":"Kuringersteenweg 154 Hasselt Limburg 3500",
    "addr:housenumber":"154",
    "addr:postcode":"3500",
    "addr:street":"Kuringersteenweg",
    "iso:country":"BE",
    "sg:address":"Kuringersteenweg 154",
    "sg:city":"Hasselt",
    "sg:orig_category":"Computers and computerapparatuur Diverse informatica-activiteiten Onderhoud van kantoor- and compute",
    "sg:phone":"+32 11 25 66 22",
    "sg:postcode":"3500",
    "sg:province":"Limburg",
    "wof:name":"Das Automatisering",
    "wof:placetype":"venue"
},
  "geometry": {"coordinates":[5.3193378448,50.9354934692],"type":"Point"}
}