{
  "type": "Feature",
  "properties": {
    "addr:full":"Rue Vanderkindere 352 Bruxelles (uccle) Bruxelles-Capitale 1180",
    "addr:housenumber":"352",
    "addr:postcode":"1180",
    "addr:street":"Rue Vanderkindere",
    "iso:country":"BE",
    "sg:address":"Rue Vanderkindere 352",
    "sg:city":"Bruxelles (uccle)",
    "sg:classifiers":[
        {
            "category":"Food & Beverages",
            "subcategory":"Specialty",
            "type":"Retail Goods"
        }
    ],
    "sg:phone":"+32 2 347 45 77",
    "sg:postcode":"1180",
    "sg:province":"Bruxelles-Capitale",
    "sg:tags":[
        "health",
        "dietary",
        "-",
        "biological"
    ],
    "wof:name":"La Table D'isis",
    "wof:placetype":"venue"
},
  "geometry": {"coordinates":[4.3557648659,50.8143157959],"type":"Point"}
}