{
  "type": "Feature",
  "properties": {
    "addr:full":"Wenduinse Steenweg 8 Blankenberge West-Vlaanderen 8370",
    "addr:housenumber":"8",
    "addr:postcode":"8370",
    "addr:street":"Steenweg",
    "iso:country":"BE",
    "sg:address":"Wenduinse Steenweg 8",
    "sg:city":"Blankenberge",
    "sg:classifiers":[
        {
            "category":"Retail",
            "subcategory":"Auto Rental",
            "type":"Services"
        }
    ],
    "sg:phone":"+32 50 41 20 06",
    "sg:postcode":"8370",
    "sg:province":"West-Vlaanderen",
    "sg:tags":[
        "engine",
        "diesel",
        "-"
    ],
    "wof:name":"North Sea Boating",
    "wof:placetype":"venue"
},
  "geometry": {"coordinates":[3.1139400005,51.3111915588],"type":"Point"}
}