{
  "type": "Feature",
  "properties": {
    "addr:full":"Kreeftstraat 29b3 Antwerpen Antwerpen 2018",
    "addr:housenumber":"29b3",
    "addr:postcode":"2018",
    "addr:street":"Kreeftstraat",
    "iso:country":"BE",
    "sg:address":"Kreeftstraat 29b3",
    "sg:city":"Antwerpen",
    "sg:orig_category":"Agences de presse",
    "sg:phone":"+32 3 271 04 35",
    "sg:postcode":"2018",
    "sg:province":"Antwerpen",
    "wof:name":"Saskia Stuurman",
    "wof:placetype":"venue"
},
  "geometry": {"coordinates":[4.4320931435,51.2077560425],"type":"Point"}
}