{
  "type": "Feature",
  "properties": {
    "addr:full":"Rollegemplaats 1 Kortrijk West-Vlaanderen 8510",
    "addr:housenumber":"1",
    "addr:postcode":"8510",
    "addr:street":"Rollegemplaats",
    "iso:country":"BE",
    "sg:address":"Rollegemplaats 1",
    "sg:city":"Kortrijk",
    "sg:orig_category":"Slagers",
    "sg:phone":"+32 56 21 50 44",
    "sg:postcode":"8510",
    "sg:province":"West-Vlaanderen",
    "wof:name":"Leon Decantere",
    "wof:placetype":"venue"
},
  "geometry": {"coordinates":[3.2625350952,50.7691001892],"type":"Point"}
}