{
  "type": "Feature",
  "properties": {
    "iso:country":"BE",
    "sg:address":"Kuringersteenweg 111",
    "sg:city":"Hasselt",
    "sg:classifiers":[
        {
            "category":"Cafe",
            "type":"Food & Drink"
        }
    ],
    "sg:phone":"+32 11 87 40 54",
    "sg:postcode":"3500",
    "sg:province":"Limburg",
    "sg:tags":[
        "snack-bars"
    ],
    "wof:name":"Georgie's",
    "wof:placetype":"venue"
},
  "geometry": {"coordinates":[5.3238101006,50.9340934753],"type":"Point"}
}