{
  "type": "Feature",
  "properties": {
    "addr:full":"Valerius De Saedeleerstraat 71 Aalst Oost-Vlaanderen 9300",
    "addr:housenumber":"71",
    "addr:postcode":"9300",
    "addr:street":"Valerius De Saedeleerstraat",
    "iso:country":"BE",
    "sg:address":"Valerius De Saedeleerstraat 71",
    "sg:city":"Aalst",
    "sg:classifiers":[
        {
            "category":"Professional",
            "subcategory":"Art Services",
            "type":"Services"
        }
    ],
    "sg:phone":"+32 53 70 63 09",
    "sg:postcode":"9300",
    "sg:province":"Oost-Vlaanderen",
    "sg:tags":[
        "graphic",
        "designer"
    ],
    "wof:name":"Forma",
    "wof:placetype":"venue"
},
  "geometry": {"coordinates":[4.0309228897,50.9442520142],"type":"Point"}
}