{
  "type": "Feature",
  "properties": {
    "iso:country":"BE",
    "sg:address":"Chauss\u00e9e D'audenarde 427",
    "sg:city":"Pecq (h\u00e9rinnes-lez-pecq)",
    "sg:classifiers":[
        {
            "category":"Bars & Pubs",
            "type":"Food & Drink"
        }
    ],
    "sg:phone":"+32 69 55 83 90",
    "sg:postcode":"7742",
    "sg:province":"Hainaut",
    "wof:name":"Escale (l')",
    "wof:placetype":"venue"
},
  "geometry": {"coordinates":[3.3638091087,50.7013778687],"type":"Point"}
}