{
  "type": "Feature",
  "properties": {
    "addr:full":"Boerenkrijglaan 33 Sint-gillis-waas (de Klinge) Oost-Vlaanderen 9170",
    "addr:housenumber":"33",
    "addr:postcode":"9170",
    "addr:street":"Boerenkrijglaan;Oost-Vlaanderen",
    "iso:country":"BE",
    "sg:address":"Boerenkrijglaan 33",
    "sg:city":"Sint-gillis-waas (de Klinge)",
    "sg:classifiers":[
        {
            "category":"Communications",
            "subcategory":"Film & Video Production",
            "type":"Services"
        }
    ],
    "sg:phone":"+32 3 770 75 03",
    "sg:postcode":"9170",
    "sg:province":"Oost-Vlaanderen",
    "sg:tags":[
        "sound",
        "recording",
        "studio"
    ],
    "wof:name":"Belgian Media Factory Gcv",
    "wof:placetype":"venue"
},
  "geometry": {"coordinates":[4.1072659492,51.2615661621],"type":"Point"}
}