{
  "type": "Feature",
  "properties": {
    "addr:full":"Nijlensesteenweg 101 Nijlen (bevel) Antwerpen 2560",
    "addr:housenumber":"101",
    "addr:postcode":"2560",
    "addr:street":"Nijlensesteenweg",
    "iso:country":"BE",
    "sg:address":"Nijlensesteenweg 101",
    "sg:city":"Nijlen (bevel)",
    "sg:classifiers":[
        {
            "category":"Personal",
            "subcategory":"Beauty Salon",
            "type":"Services"
        }
    ],
    "sg:phone":"+32 3 481 92 31",
    "sg:postcode":"2560",
    "sg:province":"Antwerpen",
    "sg:tags":[
        "lady",
        "-",
        "hairdressing"
    ],
    "wof:name":"Liliane",
    "wof:placetype":"venue"
},
  "geometry": {"coordinates":[4.6839251518,51.1427383423],"type":"Point"}
}