{
  "type": "Feature",
  "properties": {
    "iso:country":"BE",
    "sg:address":"Demerstraat 18",
    "sg:city":"Antwerpen",
    "sg:classifiers":[
        {
            "category":"Education",
            "subcategory":"School",
            "type":"Public Place"
        }
    ],
    "sg:phone":"+32 3 233 34 30",
    "sg:postcode":"2060",
    "sg:province":"Antwerpen",
    "sg:tags":[
        "primary"
    ],
    "wof:name":"Sint Lambertusschool",
    "wof:placetype":"venue"
},
  "geometry": {"coordinates":[4.42933321,51.2305412292],"type":"Point"}
}