{
  "type": "Feature",
  "properties": {
    "iso:country":"BE",
    "sg:address":"Steenweg Op Turnhout 160",
    "sg:city":"Oud-turnhout",
    "sg:orig_category":"Emballages en plastique Fab",
    "sg:phone":"+32 14 46 27 50",
    "sg:postcode":"2360",
    "sg:province":"Antwerpen",
    "wof:name":"Mpc-dg Plastics",
    "wof:placetype":"venue"
},
  "geometry": {"coordinates":[4.9716601372,51.3207015991],"type":"Point"}
}