{
  "type": "Feature",
  "properties": {
    "addr:full":"Oude Heirbaan 165 Deinze (gottem) Oost-Vlaanderen 9800",
    "addr:housenumber":"165",
    "addr:postcode":"9800",
    "addr:street":"Oude Heirbaan",
    "iso:country":"BE",
    "sg:address":"Oude Heirbaan 165",
    "sg:city":"Deinze (gottem)",
    "sg:orig_category":"Non-Classified Establishments",
    "sg:phone":"+32 51 63 65 10",
    "sg:postcode":"9800",
    "sg:province":"Oost-Vlaanderen",
    "wof:name":"Wavalin Cvba",
    "wof:placetype":"venue"
},
  "geometry": {"coordinates":[3.4825899601,50.9827575684],"type":"Point"}
}