{
  "type": "Feature",
  "properties": {
    "addr:full":"Rue De La Fontaine 7 Edingen/enghien Hainaut 7850",
    "addr:housenumber":"7",
    "addr:postcode":"7850",
    "addr:street":"Rue De La Fontaine",
    "iso:country":"BE",
    "sg:address":"Rue De La Fontaine 7",
    "sg:city":"Edingen/enghien",
    "sg:orig_category":"M\u00e9decins and sp\u00e9cialistes",
    "sg:phone":"+32 2 395 38 58",
    "sg:postcode":"7850",
    "sg:province":"Hainaut",
    "wof:name":"Bernard Gregoire",
    "wof:placetype":"venue"
},
  "geometry": {"coordinates":[4.0383729935,50.6924438477],"type":"Point"}
}