{
  "type": "Feature",
  "properties": {
    "addr:full":"Rue Du B\u00e9guinage 3 Ans (xhendremael) Li\u00e8ge 4432",
    "addr:housenumber":"3",
    "addr:postcode":"4432",
    "addr:street":"Rue Du Be\u0301Guinage;Xhendremael",
    "iso:country":"BE",
    "sg:address":"Rue Du B\u00e9guinage 3",
    "sg:city":"Ans (xhendremael)",
    "sg:classifiers":[
        {
            "category":"Health Services",
            "subcategory":"Hospital",
            "type":"Services"
        }
    ],
    "sg:phone":"+32 4 257 41 08",
    "sg:postcode":"4432",
    "sg:province":"Li\u00e8ge",
    "wof:name":"R\u00e9sidence Du B\u00e9guinage",
    "wof:placetype":"venue"
},
  "geometry": {"coordinates":[5.48188591,50.705078125],"type":"Point"}
}