{
  "type": "Feature",
  "properties": {
    "iso:country":"BE",
    "sg:address":"Rue De La Cath\u00c9drale 37",
    "sg:city":"Li\u00c8ge",
    "sg:orig_category":"Rev\u00eatements de sols and murs. Quincailleries. Eclairage et \u00e9quipements du foyer",
    "sg:phone":"+32 4 223 14 55",
    "sg:postcode":"4000",
    "sg:province":"Li\u00e8ge",
    "wof:name":"Gregoire",
    "wof:placetype":"venue"
},
  "geometry": {"coordinates":[5.5755472183,50.6427154541],"type":"Point"}
}