{
  "type": "Feature",
  "properties": {
    "addr:full":"Rijselsteenweg 48 Ieper West-Vlaanderen 8900",
    "addr:housenumber":"48",
    "addr:postcode":"8900",
    "addr:street":"Rijselsteenweg",
    "iso:country":"BE",
    "sg:address":"Rijselsteenweg 48",
    "sg:city":"Ieper",
    "sg:orig_category":"Benzinestations and brandstoffen Herstellingen and onderhoud van auto's Mazda Voertuigen",
    "sg:phone":"+32 57 20 06 85",
    "sg:postcode":"8900",
    "sg:province":"West-Vlaanderen",
    "wof:name":"Garage Demey",
    "wof:placetype":"venue"
},
  "geometry": {"coordinates":[2.8890008926,50.8421859741],"type":"Point"}
}