{
  "type": "Feature",
  "properties": {
    "addr:full":"Herentalsesteenweg 80 Kasterlee Antwerpen 2460",
    "addr:housenumber":"80",
    "addr:postcode":"2460",
    "addr:street":"Herentalsesteenweg",
    "iso:country":"BE",
    "sg:address":"Herentalsesteenweg 80",
    "sg:city":"Kasterlee",
    "sg:classifiers":[
        {
            "category":"Restaurant",
            "type":"Food & Drink"
        }
    ],
    "sg:phone":"+32 14 55 27 74",
    "sg:postcode":"2460",
    "sg:province":"Antwerpen",
    "wof:name":"Grill Carr\u00c9",
    "wof:placetype":"venue"
},
  "geometry": {"coordinates":[4.8979201317,51.2080879211],"type":"Point"}
}