{
  "type": "Feature",
  "properties": {
    "addr:full":"Onkerzelestraat 154 Geraardsbergen Oost-Vlaanderen 9500",
    "addr:housenumber":"154",
    "addr:postcode":"9500",
    "addr:street":"Onkerzelestraat",
    "iso:country":"BE",
    "sg:address":"Onkerzelestraat 154",
    "sg:city":"Geraardsbergen",
    "sg:orig_category":"Enseignement maternel and primaire",
    "sg:phone":"+32 54 41 00 34",
    "sg:postcode":"9500",
    "sg:province":"Oost-Vlaanderen",
    "wof:name":"Vrije Basisschool",
    "wof:placetype":"venue"
},
  "geometry": {"coordinates":[3.8943850994,50.7744750977],"type":"Point"}
}