{
  "type": "Feature",
  "properties": {
    "iso:country":"BE",
    "sg:address":"Place Joseph G\u00c9rard 11",
    "sg:city":"Theux",
    "sg:orig_category":"Gasproductie and -distributie",
    "sg:phone":"+32 87 22 18 02",
    "sg:postcode":"4910",
    "sg:province":"Li\u00e8ge",
    "wof:name":"Elisabeth Manguette",
    "wof:placetype":"venue"
},
  "geometry": {"coordinates":[5.8875250816,50.5426101685],"type":"Point"}
}