{
  "type": "Feature",
  "properties": {
    "addr:full":"Scheldestraat 41 Antwerpen Antwerpen 2000",
    "addr:housenumber":"41",
    "addr:postcode":"2000",
    "addr:street":"Scheldestraat",
    "iso:country":"BE",
    "sg:address":"Scheldestraat 41",
    "sg:city":"Antwerpen",
    "sg:classifiers":[
        {
            "category":"Building & Trades",
            "subcategory":"Pest Control",
            "type":"Services"
        }
    ],
    "sg:phone":"+32 3 216 20 63",
    "sg:postcode":"2000",
    "sg:province":"Antwerpen",
    "sg:tags":[
        "machine",
        "vending"
    ],
    "wof:name":"Nutstime",
    "wof:placetype":"venue"
},
  "geometry": {"coordinates":[4.3945398331,51.211933136],"type":"Point"}
}