{
  "type": "Feature",
  "properties": {
    "addr:full":"Trieux Des Mines 97 Namur Namur 5020",
    "addr:housenumber":"97",
    "addr:postcode":"5020",
    "addr:street":"Des Mines",
    "iso:country":"BE",
    "sg:address":"Trieux Des Mines 97",
    "sg:city":"Namur",
    "sg:orig_category":"Eleveurs de bovins",
    "sg:phone":"+32 81 21 08 23",
    "sg:postcode":"5020",
    "sg:province":"Namur",
    "wof:name":"Jean Ghys",
    "wof:placetype":"venue"
},
  "geometry": {"coordinates":[4.7952418327,50.4352035522],"type":"Point"}
}