{
  "type": "Feature",
  "properties": {
    "addr:full":"Nieuwstraat 63 Haaltert Oost-Vlaanderen 9450",
    "addr:housenumber":"63",
    "addr:postcode":"9450",
    "addr:street":"Nieuwstraat",
    "iso:country":"BE",
    "sg:address":"Nieuwstraat 63",
    "sg:city":"Haaltert",
    "sg:orig_category":"Alimentation sp\u00e9cialis\u00e9e",
    "sg:phone":"+32 54 33 87 22",
    "sg:postcode":"9450",
    "sg:province":"Oost-Vlaanderen",
    "wof:name":"Dirk Bulte",
    "wof:placetype":"venue"
},
  "geometry": {"coordinates":[4.0106239319,50.8692398071],"type":"Point"}
}