{
  "type": "Feature",
  "properties": {
    "iso:country":"BE",
    "sg:address":"Hoornstraat 22",
    "sg:city":"Beernem",
    "sg:orig_category":"Loodgieterij, verwarming and sanitaire installaties",
    "sg:phone":"+32 50 79 01 11",
    "sg:postcode":"8730",
    "sg:province":"West-Vlaanderen",
    "wof:name":"Gazel",
    "wof:placetype":"venue"
},
  "geometry": {"coordinates":[3.3504769802,51.1467247009],"type":"Point"}
}