{
  "type": "Feature",
  "properties": {
    "iso:country":"BE",
    "sg:address":"Heuveneideweg 74",
    "sg:city":"Zonhoven",
    "sg:orig_category":"Mat\u00e9riel de contr\u00f4le des processus industriels Fab",
    "sg:phone":"+32 11 82 18 96",
    "sg:postcode":"3520",
    "sg:province":"Limburg",
    "wof:name":"Cimax",
    "wof:placetype":"venue"
},
  "geometry": {"coordinates":[5.3608541489,50.9716720581],"type":"Point"}
}