{
  "type": "Feature",
  "properties": {
    "addr:full":"Veldstraat 42 Hechtel-eksel Limburg 3941",
    "addr:housenumber":"42",
    "addr:postcode":"3941",
    "addr:street":"Veldstraat",
    "iso:country":"BE",
    "sg:address":"Veldstraat 42",
    "sg:city":"Hechtel-eksel",
    "sg:orig_category":"Woningbouw",
    "sg:phone":"+32 11 73 64 66",
    "sg:postcode":"3941",
    "sg:province":"Limburg",
    "wof:name":"Ceunen",
    "wof:placetype":"venue"
},
  "geometry": {"coordinates":[5.3876810074,51.1530189514],"type":"Point"}
}