{
  "type": "Feature",
  "properties": {
    "addr:full":"Afrikalaan 20 Gent Oost-Vlaanderen 9000",
    "addr:housenumber":"20",
    "addr:postcode":"9000",
    "addr:street":"Afrikalaan;Oost-Vlaanderen",
    "iso:country":"BE",
    "sg:address":"Afrikalaan 20",
    "sg:city":"Gent",
    "sg:classifiers":[
        {
            "category":"Shopping Center",
            "type":"Public Place"
        }
    ],
    "sg:phone":"+32 9 225 40 05",
    "sg:postcode":"9000",
    "sg:province":"Oost-Vlaanderen",
    "sg:tags":[
        "aluminium",
        "section"
    ],
    "wof:name":"Dinac Benelux B.v.b.a.",
    "wof:placetype":"venue"
},
  "geometry": {"coordinates":[3.7393798828,51.0639457703],"type":"Point"}
}