{
  "type": "Feature",
  "properties": {
    "addr:full":"Welvaartstraat 3 Herentals Antwerpen 2200",
    "addr:housenumber":"3",
    "addr:postcode":"2200",
    "addr:street":"Welvaartstraat",
    "iso:country":"BE",
    "sg:address":"Welvaartstraat 3",
    "sg:city":"Herentals",
    "sg:orig_category":"Koekjes, gebak and taart Fab",
    "sg:phone":"+32 14 22 00 21",
    "sg:postcode":"2200",
    "sg:province":"Antwerpen",
    "wof:name":"Dryon Biscuits Internat.",
    "wof:placetype":"venue"
},
  "geometry": {"coordinates":[4.801158905,51.159286499],"type":"Point"}
}