{
  "type": "Feature",
  "properties": {
    "iso:country":"BE",
    "sg:address":"Rue Joseph Vrindt 2b14",
    "sg:city":"Grace-hollogne",
    "sg:orig_category":"Messageries",
    "sg:phone":"+32 475 73 80 22",
    "sg:postcode":"4460",
    "sg:province":"Li\u00e8ge",
    "wof:name":"Jacqueline De Bruin",
    "wof:placetype":"venue"
},
  "geometry": {"coordinates":[5.4919090271,50.6301116943],"type":"Point"}
}