{
  "type": "Feature",
  "properties": {
    "addr:full":"Moerkerkse Steenweg 451 Brugge (sint-kruis) West-Vlaanderen 8310",
    "addr:housenumber":"451",
    "addr:postcode":"8310",
    "addr:street":"Moerkerkse Steenweg",
    "iso:country":"BE",
    "sg:address":"Moerkerkse Steenweg 451",
    "sg:city":"Brugge (sint-kruis)",
    "sg:classifiers":[
        {
            "category":"Freight",
            "type":"Transportation"
        }
    ],
    "sg:phone":"+32 50 35 10 50",
    "sg:postcode":"8310",
    "sg:province":"West-Vlaanderen",
    "sg:tags":[
        "-",
        "transport"
    ],
    "wof:name":"Dezutter",
    "wof:placetype":"venue"
},
  "geometry": {"coordinates":[3.2627220154,51.2134895325],"type":"Point"}
}