{
  "type": "Feature",
  "properties": {
    "addr:full":"Ter Stratenweg 35 Oelegem Antwerpen 2520",
    "addr:housenumber":"35",
    "addr:postcode":"2520",
    "addr:street":"Ter Stratenweg",
    "iso:country":"BE",
    "sg:address":"Ter Stratenweg 35",
    "sg:city":"Oelegem",
    "sg:classifiers":[
        {
            "category":"Building & Trades",
            "subcategory":"Construction",
            "type":"Services"
        }
    ],
    "sg:phone":"+32 3 475 93 48",
    "sg:postcode":"2520",
    "sg:province":"Antwerpen",
    "sg:tags":[
        "en",
        "la",
        "el\u00e9ments",
        "pour",
        "fab",
        "b\u00e9ton"
    ],
    "wof:name":"Verhaert En Co",
    "wof:placetype":"venue"
},
  "geometry": {"coordinates":[4.5767421722,51.2127685547],"type":"Point"}
}