{
  "type": "Feature",
  "properties": {
    "addr:full":"Nieuwstraat 95 Vorselaar Antwerpen 2290",
    "addr:housenumber":"95",
    "addr:postcode":"2290",
    "addr:street":"Nieuwstraat",
    "iso:country":"BE",
    "sg:address":"Nieuwstraat 95",
    "sg:city":"Vorselaar",
    "sg:classifiers":[
        {
            "category":"Home & Garden",
            "subcategory":"Carpets & Floor Coverings",
            "type":"Retail Goods"
        }
    ],
    "sg:phone":"+32 14 51 78 69",
    "sg:postcode":"2290",
    "sg:province":"Antwerpen",
    "sg:tags":[
        "layer",
        "mosaicists"
    ],
    "wof:name":"Van Den Eynde",
    "wof:placetype":"venue"
},
  "geometry": {"coordinates":[4.786962986,51.2042350769],"type":"Point"}
}