{
  "type": "Feature",
  "properties": {
    "addr:full":"Chauss\u00c9e De Wavre 706 Etterbeek/etterbeek Bruxelles-Capitale 1040",
    "addr:housenumber":"706",
    "addr:postcode":"1040",
    "addr:street":"Chausse\u0301E De Wavre",
    "iso:country":"BE",
    "sg:address":"Chauss\u00c9e De Wavre 706",
    "sg:city":"Etterbeek/etterbeek",
    "sg:orig_category":"S\u00e9curit\u00e9 sociale",
    "sg:phone":"+32 2 647 71 12",
    "sg:postcode":"1040",
    "sg:province":"Bruxelles-Capitale",
    "wof:name":"Mutualit\u00c9 Socialiste",
    "wof:placetype":"venue"
},
  "geometry": {"coordinates":[4.3897509575,50.830909729],"type":"Point"}
}