{
  "type": "Feature",
  "properties": {
    "addr:full":"Holt 74 Bilzen (beverst) Limburg 3740",
    "addr:housenumber":"74",
    "addr:postcode":"3740",
    "addr:street":"Holt",
    "iso:country":"BE",
    "sg:address":"Holt 74",
    "sg:city":"Bilzen (beverst)",
    "sg:classifiers":[
        {
            "category":"Social Services",
            "subcategory":"Child Care",
            "type":"Services"
        }
    ],
    "sg:phone":"+32 89 41 35 63",
    "sg:postcode":"3740",
    "sg:province":"Limburg",
    "sg:tags":[
        "baby",
        "nursery",
        "day",
        "sitting"
    ],
    "wof:name":"Snoezepoes",
    "wof:placetype":"venue"
},
  "geometry": {"coordinates":[5.4804148674,50.8875541687],"type":"Point"}
}