{
  "type": "Feature",
  "properties": {
    "iso:country":"BE",
    "sg:address":"Marktstraat 98",
    "sg:city":"Kortrijk",
    "sg:orig_category":"Ordinateurs and \u00e9quipement informatique",
    "sg:phone":"+32 56 25 54 72",
    "sg:postcode":"8510",
    "sg:province":"West-Vlaanderen",
    "wof:name":"Fa. Up And Running",
    "wof:placetype":"venue"
},
  "geometry": {"coordinates":[3.234926939,50.8092956543],"type":"Point"}
}