{
  "type": "Feature",
  "properties": {
    "iso:country":"BE",
    "sg:address":"Kneuterlei 4",
    "sg:city":"Schoten",
    "sg:classifiers":[
        {
            "category":"Building & Trades",
            "subcategory":"Landscaping Services",
            "type":"Services"
        }
    ],
    "sg:phone":"+32 3 685 55 14",
    "sg:postcode":"2900",
    "sg:province":"Antwerpen",
    "sg:tags":[
        "gardening",
        "garden",
        "maintenance"
    ],
    "wof:name":"Baeyens S",
    "wof:placetype":"venue"
},
  "geometry": {"coordinates":[4.5215549469,51.2569122314],"type":"Point"}
}