{
  "type": "Feature",
  "properties": {
    "addr:full":"Rue Robert 26 Chapelle-lez-herlaimont Hainaut 7160",
    "addr:housenumber":"26",
    "addr:postcode":"7160",
    "addr:street":"Rue Robert",
    "iso:country":"BE",
    "sg:address":"Rue Robert 26",
    "sg:city":"Chapelle-lez-herlaimont",
    "sg:orig_category":"Pain, p\u00e2tisseries and confiseries",
    "sg:phone":"+32 64 44 59 53",
    "sg:postcode":"7160",
    "sg:province":"Hainaut",
    "wof:name":"Eric Baneton",
    "wof:placetype":"venue"
},
  "geometry": {"coordinates":[4.2828807831,50.4706840515],"type":"Point"}
}