{
  "type": "Feature",
  "properties": {
    "iso:country":"BE",
    "sg:address":"Keizerinlaan 3",
    "sg:city":"Brussel/bruxelles",
    "sg:orig_category":"Postkantoren Verzekeringsmakelaars and experts",
    "sg:phone":"+32 2 511 36 69",
    "sg:postcode":"1000",
    "sg:province":"Bruxelles-Capitale",
    "wof:name":"De Post",
    "wof:placetype":"venue"
},
  "geometry": {"coordinates":[4.3565368652,50.8451347351],"type":"Point"}
}