{
  "type": "Feature",
  "properties": {
    "addr:full":"Rue Martin-sandron 67 Doische Namur 5680",
    "addr:housenumber":"67",
    "addr:postcode":"5680",
    "addr:street":"Rue Martin-Sandron",
    "iso:country":"BE",
    "sg:address":"Rue Martin-sandron 67",
    "sg:city":"Doische",
    "sg:orig_category":"Installatie van houten of kunststof schrijnwerk",
    "sg:phone":"+32 82 67 76 05",
    "sg:postcode":"5680",
    "sg:province":"Namur",
    "wof:name":"R. Chabot",
    "wof:placetype":"venue"
},
  "geometry": {"coordinates":[4.752655983,50.1388511658],"type":"Point"}
}