{
  "type": "Feature",
  "properties": {
    "addr:full":"Chauss\u00c9e De Forest 83 Sint-gillis/saint-gilles Bruxelles-Capitale 1060",
    "addr:housenumber":"83",
    "addr:postcode":"1060",
    "addr:street":"Chausse\u0301E De Forest",
    "iso:country":"BE",
    "sg:address":"Chauss\u00c9e De Forest 83",
    "sg:city":"Sint-gillis/saint-gilles",
    "sg:orig_category":"Quincailleries",
    "sg:phone":"+32 2 538 62 14",
    "sg:postcode":"1060",
    "sg:province":"Bruxelles-Capitale",
    "wof:name":"Electro Akd",
    "wof:placetype":"venue"
},
  "geometry": {"coordinates":[4.3391489983,50.8312416077],"type":"Point"}
}