{
  "type": "Feature",
  "properties": {
    "addr:full":"Boulevard Maurice Lemonnier 15 Bruxelles Bruxelles-Capitale 1000",
    "addr:housenumber":"15",
    "addr:postcode":"1000",
    "addr:street":"Boulevard Maurice Lemonnier",
    "iso:country":"BE",
    "sg:address":"Boulevard Maurice Lemonnier 15",
    "sg:city":"Bruxelles",
    "sg:classifiers":[
        {
            "category":"Shopping",
            "subcategory":"Books",
            "type":"Retail Goods"
        }
    ],
    "sg:phone":"+32 2 513 46 70",
    "sg:postcode":"1000",
    "sg:province":"Bruxelles-Capitale",
    "sg:tags":[
        "bookseller"
    ],
    "wof:name":"Petits Papiers",
    "wof:placetype":"venue"
},
  "geometry": {"coordinates":[4.3457870483,50.8448638916],"type":"Point"}
}