{
  "type": "Feature",
  "properties": {
    "addr:full":"Kerkskendorp3 Haaltert Oost-Vlaanderen 9451",
    "addr:postcode":"9451",
    "addr:street":"Oost-Vlaanderen",
    "iso:country":"BE",
    "sg:address":"Kerkskendorp3",
    "sg:city":"Haaltert",
    "sg:orig_category":"Foto-uitrusting Fotografen and fotostudio's Telecommunicatieapparaten",
    "sg:phone":"+32 53 83 52 37",
    "sg:postcode":"9451",
    "sg:province":"Oost-Vlaanderen",
    "wof:name":"Top Camera De Rijck Marc Fotografie",
    "wof:placetype":"venue"
},
  "geometry": {"coordinates":[3.99208498,50.8902664185],"type":"Point"}
}