{
  "type": "Feature",
  "properties": {
    "iso:country":"BE",
    "sg:address":"Rooienberg 130",
    "sg:city":"Duffel",
    "sg:classifiers":[
        {
            "category":"Professional",
            "subcategory":"Lawyer & Legal Services",
            "type":"Services"
        }
    ],
    "sg:phone":"+32 15 31 52 62",
    "sg:postcode":"2570",
    "sg:province":"Antwerpen",
    "wof:name":"Torremans T",
    "wof:placetype":"venue"
},
  "geometry": {"coordinates":[4.4847788811,51.0987625122],"type":"Point"}
}