{
  "type": "Feature",
  "properties": {
    "iso:country":"BE",
    "sg:address":"Cathilleweg 104",
    "sg:city":"Jabbeke (stalhille)",
    "sg:classifiers":[
        {
            "category":"Personal",
            "subcategory":"Beauty Salon",
            "type":"Services"
        }
    ],
    "sg:phone":"+32 50 81 21 58",
    "sg:postcode":"8490",
    "sg:province":"West-Vlaanderen",
    "sg:tags":[
        "lady",
        "-",
        "hairdressing"
    ],
    "wof:name":"Hilde",
    "wof:placetype":"venue"
},
  "geometry": {"coordinates":[3.0717790127,51.2147827148],"type":"Point"}
}