{
  "type": "Feature",
  "properties": {
    "iso:country":"BE",
    "sg:address":"A. Pevernagestraat 105",
    "sg:city":"Harelbeke (groot)",
    "sg:orig_category":"Kapsalons",
    "sg:phone":"+32 56 72 44 19",
    "sg:postcode":"8530",
    "sg:province":"West-Vlaanderen",
    "wof:name":"Henk Kapsalon",
    "wof:placetype":"venue"
},
  "geometry": {"coordinates":[3.3088970184,50.8517723083],"type":"Point"}
}