{
  "type": "Feature",
  "properties": {
    "addr:full":"Markt 13 Oostkamp West-Vlaanderen 8020",
    "addr:housenumber":"13",
    "addr:postcode":"8020",
    "addr:street":"Markt",
    "iso:country":"BE",
    "sg:address":"Markt 13",
    "sg:city":"Oostkamp",
    "sg:orig_category":"Cr\u00e9dits divers",
    "sg:postcode":"8020",
    "sg:province":"West-Vlaanderen",
    "wof:name":"Bancontact-mister Cash",
    "wof:placetype":"venue"
},
  "geometry": {"coordinates":[3.2062408924,51.0961685181],"type":"Point"}
}