{
  "type": "Feature",
  "properties": {
    "iso:country":"BE",
    "sg:address":"Populierstraat 76",
    "sg:city":"Roeselare",
    "sg:orig_category":"Woningbouw",
    "sg:phone":"+32 51 20 95 47",
    "sg:postcode":"8800",
    "sg:province":"West-Vlaanderen",
    "wof:name":"Demeulenaere M.",
    "wof:placetype":"venue"
},
  "geometry": {"coordinates":[3.1590189934,50.948135376],"type":"Point"}
}