{
  "type": "Feature",
  "properties": {
    "iso:country":"BE",
    "sg:address":"Rue De La Charit\u00c9 15",
    "sg:city":"Sint-joost-ten-node/saint-joss",
    "sg:orig_category":"Installation \u00e9lectrique r\u00e9sidentielle",
    "sg:phone":"+32 2 223 35 14",
    "sg:postcode":"1210",
    "sg:province":"Bruxelles-Capitale",
    "wof:name":"Technimatic",
    "wof:placetype":"venue"
},
  "geometry": {"coordinates":[4.3707580566,50.848651886],"type":"Point"}
}