{
  "type": "Feature",
  "properties": {
    "addr:full":"Rue J Pirotte 1 Luik (groot) Li\u00e8ge 4000",
    "addr:housenumber":"1",
    "addr:postcode":"4000",
    "addr:street":"Rue J Pirotte;Luik Groot Lie\u0300Ge",
    "iso:country":"BE",
    "sg:address":"Rue J Pirotte 1",
    "sg:city":"Luik (groot)",
    "sg:orig_category":"Kapsalons",
    "sg:phone":"+32 4 247 58 77",
    "sg:postcode":"4000",
    "sg:province":"Li\u00e8ge",
    "wof:name":"Daphne",
    "wof:placetype":"venue"
},
  "geometry": {"coordinates":[5.5479240417,50.6459274292],"type":"Point"}
}