{
  "type": "Feature",
  "properties": {
    "addr:full":"Rue De Moorslede 33 Bruxelles Bruxelles-Capitale 1020",
    "addr:housenumber":"33",
    "addr:postcode":"1020",
    "addr:street":"Rue De Moorslede",
    "iso:country":"BE",
    "sg:address":"Rue De Moorslede 33",
    "sg:city":"Bruxelles",
    "sg:classifiers":[
        {
            "category":"Real Estate",
            "subcategory":"Real Estate Services",
            "type":"Services"
        }
    ],
    "sg:phone":"+32 2 427 45 80",
    "sg:postcode":"1020",
    "sg:province":"Bruxelles-Capitale",
    "wof:name":"Gepi",
    "wof:placetype":"venue"
},
  "geometry": {"coordinates":[4.3503689766,50.8764266968],"type":"Point"}
}