{
  "type": "Feature",
  "properties": {
    "iso:country":"BE",
    "sg:address":"Eppegemsesteenweg 26",
    "sg:city":"Grimbergen",
    "sg:classifiers":[
        {
            "category":"Professional",
            "subcategory":"Computer Services",
            "type":"Services"
        }
    ],
    "sg:phone":"+32 2 255 90 00",
    "sg:postcode":"1850",
    "sg:province":"Vlaams-Brabant",
    "sg:tags":[
        "-",
        "processing",
        "data",
        "software"
    ],
    "wof:name":"3 A C S",
    "wof:placetype":"venue"
},
  "geometry": {"coordinates":[4.4158639908,50.9485969543],"type":"Point"}
}