{
  "type": "Feature",
  "properties": {
    "iso:country":"BE",
    "sg:address":"Rue De Grammont 70",
    "sg:city":"Lessines",
    "sg:classifiers":[
        {
            "category":"Wholesale",
            "subcategory":"Wine & Distilled Alcoholic Beverages",
            "type":"Manufacturing & Wholesale Goods"
        }
    ],
    "sg:phone":"+32 68 33 20 91",
    "sg:postcode":"7860",
    "sg:province":"Hainaut",
    "sg:tags":[
        "whol",
        "-",
        "spirit",
        "mfg"
    ],
    "wof:name":"France Vigne",
    "wof:placetype":"venue"
},
  "geometry": {"coordinates":[3.8286569118,50.7152404785],"type":"Point"}
}