{
  "type": "Feature",
  "properties": {
    "addr:full":"Avenue Des Saisons 27 Bruxelles (ixelles) Bruxelles-Capitale 1050",
    "addr:housenumber":"27",
    "addr:postcode":"1050",
    "addr:street":"Avenue Des Saisons",
    "iso:country":"BE",
    "sg:address":"Avenue Des Saisons 27",
    "sg:city":"Bruxelles (ixelles)",
    "sg:classifiers":[
        {
            "category":"Shopping",
            "subcategory":"Books",
            "type":"Retail Goods"
        }
    ],
    "sg:phone":"+32 2 217 45 75",
    "sg:postcode":"1050",
    "sg:province":"Bruxelles-Capitale",
    "sg:tags":[
        "bookseller"
    ],
    "wof:name":"Livre D'enseignement (le) Sa",
    "wof:placetype":"venue"
},
  "geometry": {"coordinates":[4.3860812187,50.8196868896],"type":"Point"}
}