{
  "type": "Feature",
  "properties": {
    "iso:country":"BE",
    "sg:address":"Chaussee De Louvain 56",
    "sg:city":"Bruxelles",
    "sg:classifiers":[
        {
            "category":"Shopping",
            "subcategory":"Computers & Home Electronics",
            "type":"Retail Goods"
        }
    ],
    "sg:phone":"+32 2 211 02 90",
    "sg:postcode":"1210",
    "sg:province":"Bruxelles-Capitale",
    "sg:tags":[
        "telephone"
    ],
    "wof:name":"Happymany S.a.",
    "wof:placetype":"venue"
},
  "geometry": {"coordinates":[4.3720741272,50.8496208191],"type":"Point"}
}