{
  "type": "Feature",
  "properties": {
    "addr:full":"Muisbroeklaan 34 Antwerpen Antwerpen 2030",
    "addr:housenumber":"34",
    "addr:postcode":"2030",
    "addr:street":"Muisbroeklaan",
    "iso:country":"BE",
    "sg:address":"Muisbroeklaan 34",
    "sg:city":"Antwerpen",
    "sg:classifiers":[
        {
            "category":"Retail",
            "subcategory":"Repair Shop",
            "type":"Services"
        }
    ],
    "sg:phone":"+32 3 542 52 90",
    "sg:postcode":"2030",
    "sg:province":"Antwerpen",
    "sg:tags":[
        "container",
        "maintenance"
    ],
    "wof:name":"A.c.e. Nv",
    "wof:placetype":"venue"
},
  "geometry": {"coordinates":[4.347671032,51.2857208252],"type":"Point"}
}