{
  "type": "Feature",
  "properties": {
    "iso:country":"BE",
    "sg:address":"Rue Du Centenaire 113",
    "sg:city":"Boussu",
    "sg:classifiers":[
        {
            "category":"Parking",
            "subcategory":"Bicycle",
            "type":"Transportation"
        }
    ],
    "sg:phone":"+32 65 78 41 40",
    "sg:postcode":"7300",
    "sg:province":"Hainaut",
    "sg:tags":[
        "chiropodist"
    ],
    "wof:name":"Fissiaux L",
    "wof:placetype":"venue"
},
  "geometry": {"coordinates":[3.7971770763,50.4286880493],"type":"Point"}
}