{
  "type": "Feature",
  "properties": {
    "iso:country":"BE",
    "sg:address":"Langstraat 10",
    "sg:city":"Heers (groot)",
    "sg:orig_category":"Kapsalons",
    "sg:phone":"+32 11 48 50 79",
    "sg:postcode":"3870",
    "sg:province":"Limburg",
    "wof:name":"Velkeneers H",
    "wof:placetype":"venue"
},
  "geometry": {"coordinates":[5.3745012283,50.7629814148],"type":"Point"}
}