{
  "type": "Feature",
  "properties": {
    "iso:country":"BE",
    "sg:address":"Rue Des Goutteaux 105",
    "sg:city":"Charleroi",
    "sg:orig_category":"Voedingsspeciaalzaken",
    "sg:phone":"+32 71 34 54 67",
    "sg:postcode":"6043",
    "sg:province":"Hainaut",
    "wof:name":"La Jonqui\u00c8re",
    "wof:placetype":"venue"
},
  "geometry": {"coordinates":[4.408654213,50.3866043091],"type":"Point"}
}