{
  "type": "Feature",
  "properties": {
    "addr:full":"Avenue Emile Duray 64 Box 9 Bruxelles Bruxelles-Capitale 1000",
    "addr:housenumber":"64;9",
    "addr:postcode":"1000",
    "addr:street":"Avenue Emile Duray;Box",
    "iso:country":"BE",
    "sg:address":"Avenue Emile Duray 64 Box 9",
    "sg:city":"Bruxelles",
    "sg:classifiers":[
        {
            "category":"Professional",
            "subcategory":"Lawyer & Legal Services",
            "type":"Services"
        }
    ],
    "sg:phone":"+32 2 648 49 50",
    "sg:postcode":"1000",
    "sg:province":"Bruxelles-Capitale",
    "wof:name":"Knops E",
    "wof:placetype":"venue"
},
  "geometry": {"coordinates":[4.3762469292,50.8166542053],"type":"Point"}
}