{
  "type": "Feature",
  "properties": {
    "iso:country":"BE",
    "sg:address":"Past. Raeymaekersstraat 29",
    "sg:city":"Genk",
    "sg:orig_category":"M\u00e9decins and sp\u00e9cialistes",
    "sg:phone":"+32 89 30 71 62",
    "sg:postcode":"3600",
    "sg:province":"Limburg",
    "wof:name":"Guillaume Terwinghe",
    "wof:placetype":"venue"
},
  "geometry": {"coordinates":[5.5020542145,50.9676551819],"type":"Point"}
}