{
  "type": "Feature",
  "properties": {
    "addr:full":"Leuvensesteenweg 97 Diest (kaggevinne) Vlaams-Brabant 3293",
    "addr:housenumber":"97",
    "addr:postcode":"3293",
    "addr:street":"Leuvensesteenweg",
    "iso:country":"BE",
    "sg:address":"Leuvensesteenweg 97",
    "sg:city":"Diest (kaggevinne)",
    "sg:classifiers":[
        {
            "category":"Park",
            "subcategory":"National",
            "type":"Public Place"
        }
    ],
    "sg:phone":"+32 13 33 80 33",
    "sg:postcode":"3293",
    "sg:province":"Vlaams-Brabant",
    "sg:tags":[
        "recreation"
    ],
    "wof:name":"Speelfabriek",
    "wof:placetype":"venue"
},
  "geometry": {"coordinates":[5.0446949005,50.9781417847],"type":"Point"}
}