{
  "type": "Feature",
  "properties": {
    "addr:full":"Chauss\u00e9e De Namur 10 Beauvechain (hamme-mille) Brabant Wallon 1320",
    "addr:housenumber":"10",
    "addr:postcode":"1320",
    "addr:street":"Chausse\u0301E De Namur",
    "iso:country":"BE",
    "sg:address":"Chauss\u00e9e De Namur 10",
    "sg:city":"Beauvechain (hamme-mille)",
    "sg:classifiers":[
        {
            "category":"Health Services",
            "subcategory":"Doctor",
            "type":"Services"
        }
    ],
    "sg:phone":"+32 10 86 63 97",
    "sg:postcode":"1320",
    "sg:province":"Brabant Wallon",
    "sg:tags":[
        "medicinephysicians",
        "surgeon"
    ],
    "wof:name":"Algo\u00ebt J",
    "wof:placetype":"venue"
},
  "geometry": {"coordinates":[4.7186942101,50.7775154114],"type":"Point"}
}