{
  "type": "Feature",
  "properties": {
    "addr:full":"Monnikenwerve 43 Brugge West-Vlaanderen 8000",
    "addr:housenumber":"43",
    "addr:postcode":"8000",
    "addr:street":"Monnikenwerve",
    "iso:country":"BE",
    "sg:address":"Monnikenwerve 43",
    "sg:city":"Brugge",
    "sg:orig_category":"Surveying Instruments",
    "sg:phone":"+32 50 38 98 14",
    "sg:postcode":"8000",
    "sg:province":"West-Vlaanderen",
    "wof:name":"Couder\u00e9 Huis B.v.b.a.",
    "wof:placetype":"venue"
},
  "geometry": {"coordinates":[3.1976881027,51.2481422424],"type":"Point"}
}