{
  "type": "Feature",
  "properties": {
    "addr:full":"Rue De Vis\u00c9 137 Vise Li\u00e8ge 4602",
    "addr:housenumber":"137",
    "addr:postcode":"vise;4602",
    "addr:street":"Rue De Vise\u0301",
    "iso:country":"BE",
    "sg:address":"Rue De Vis\u00c9 137",
    "sg:city":"Vise",
    "sg:orig_category":"M\u00e9decins and sp\u00e9cialistes",
    "sg:phone":"+32 4 362 30 40",
    "sg:postcode":"4602",
    "sg:province":"Li\u00e8ge",
    "wof:name":"Paul Pev\u00c9e",
    "wof:placetype":"venue"
},
  "geometry": {"coordinates":[5.6702780724,50.6831855774],"type":"Point"}
}