{
  "type": "Feature",
  "properties": {
    "iso:country":"BE",
    "sg:address":"Rue Du Pel\u00e9mont 66",
    "sg:city":"Jemeppe-sur-sambre (bal\u00e2tre)",
    "sg:classifiers":[
        {
            "category":"Wholesale",
            "subcategory":"Books, Periodicals, & Newspapers",
            "type":"Manufacturing & Wholesale Goods"
        }
    ],
    "sg:phone":"+32 81 63 21 13",
    "sg:postcode":"5190",
    "sg:province":"Namur",
    "sg:tags":[
        "publisher"
    ],
    "wof:name":"Moreau P.c.e. Sa",
    "wof:placetype":"venue"
},
  "geometry": {"coordinates":[4.6703448296,50.4645042419],"type":"Point"}
}