{
  "type": "Feature",
  "properties": {
    "addr:full":"Azi\u00cblaan 19 Scherpenheuvel-zichem Vlaams-Brabant 3270",
    "addr:housenumber":"19",
    "addr:postcode":"3270",
    "addr:street":"Azie\u0308Laan",
    "iso:country":"BE",
    "sg:address":"Azi\u00cblaan 19",
    "sg:city":"Scherpenheuvel-zichem",
    "sg:orig_category":"Dakwerken Loodgieterij, verwarming and sanitaire installaties",
    "sg:phone":"+32 13 77 60 94",
    "sg:postcode":"3270",
    "sg:province":"Vlaams-Brabant",
    "wof:name":"De Berre",
    "wof:placetype":"venue"
},
  "geometry": {"coordinates":[4.9663162231,50.9696655273],"type":"Point"}
}