{
  "type": "Feature",
  "properties": {
    "iso:country":"BE",
    "sg:address":"Polenstraat 42a",
    "sg:city":"Evergem",
    "sg:orig_category":"Traitement and fa\u00e7onnage de la pierre",
    "sg:phone":"+32 9 357 34 02",
    "sg:postcode":"9940",
    "sg:province":"Oost-Vlaanderen",
    "wof:name":"Steenhouwerij Martens",
    "wof:placetype":"venue"
},
  "geometry": {"coordinates":[3.6793689728,51.1321258545],"type":"Point"}
}