{
  "type": "Feature",
  "properties": {
    "addr:full":"Dries 80 Watermaal-bosvoorde/watermael-boitsfort Bruxelles-Capitale 1170",
    "addr:housenumber":"80",
    "addr:postcode":"1170",
    "addr:street":"Dries",
    "iso:country":"BE",
    "sg:address":"Dries 80",
    "sg:city":"Watermaal-bosvoorde/watermael-boitsfort",
    "sg:orig_category":"Artiesten and kunstenaars",
    "sg:phone":"+32 2 673 13 87",
    "sg:postcode":"1170",
    "sg:province":"Bruxelles-Capitale",
    "wof:name":"Paul Boedts",
    "wof:placetype":"venue"
},
  "geometry": {"coordinates":[4.4002990723,50.8043670654],"type":"Point"}
}