{
  "type": "Feature",
  "properties": {
    "iso:country":"BE",
    "sg:address":"D'eslt 8",
    "sg:city":"Lebbeke",
    "sg:orig_category":"Herstellingen and onderhoud van auto's",
    "sg:phone":"+32 52 41 58 20",
    "sg:postcode":"9280",
    "sg:province":"Oost-Vlaanderen",
    "wof:name":"Booster Tuning",
    "wof:placetype":"venue"
},
  "geometry": {"coordinates":[4.1281099319,51.0004501343],"type":"Point"}
}