{
  "type": "Feature",
  "properties": {
    "addr:full":"Zeedijk De Panne West-Vlaanderen 8660",
    "addr:postcode":"8660",
    "addr:street":"Zeedijk",
    "iso:country":"BE",
    "sg:address":"Zeedijk",
    "sg:city":"De Panne",
    "sg:orig_category":"Articles de jardin",
    "sg:phone":"+32 55 23 23 18",
    "sg:postcode":"8660",
    "sg:province":"West-Vlaanderen",
    "wof:name":"Henry",
    "wof:placetype":"venue"
},
  "geometry": {"coordinates":[2.5814049244,51.1000213623],"type":"Point"}
}