{
  "type": "Feature",
  "properties": {
    "addr:full":"Erfkensstraat 9 Peer Limburg 3990",
    "addr:housenumber":"9",
    "addr:postcode":"3990",
    "addr:street":"Erfkensstraat",
    "iso:country":"BE",
    "sg:address":"Erfkensstraat 9",
    "sg:city":"Peer",
    "sg:classifiers":[
        {
            "category":"Building & Trades",
            "subcategory":"Pest Control",
            "type":"Services"
        }
    ],
    "sg:phone":"+32 11 79 15 82",
    "sg:postcode":"3990",
    "sg:province":"Limburg",
    "sg:tags":[
        "painting",
        "contractor"
    ],
    "wof:name":"Home Decor Bvba",
    "wof:placetype":"venue"
},
  "geometry": {"coordinates":[5.434636116,51.094959259],"type":"Point"}
}