{
  "type": "Feature",
  "properties": {
    "iso:country":"BE",
    "sg:address":"Pauwbroekstraat 15ba",
    "sg:city":"Ham",
    "sg:orig_category":"Artsen and specialisten",
    "sg:phone":"+32 11 34 72 82",
    "sg:postcode":"3945",
    "sg:province":"Limburg",
    "wof:name":"B. Van Coillie",
    "wof:placetype":"venue"
},
  "geometry": {"coordinates":[5.1776199341,51.1046104431],"type":"Point"}
}