{
  "type": "Feature",
  "properties": {
    "addr:full":"Chauss\u00c9e De Waterloo 198 Sint-genesius-rode/rhode-saint-genese Vlaams-Brabant 1640",
    "addr:housenumber":"198",
    "addr:postcode":"1640",
    "addr:street":"Chausse\u0301E De Waterloo",
    "iso:country":"BE",
    "sg:address":"Chauss\u00c9e De Waterloo 198",
    "sg:city":"Sint-genesius-rode/rhode-saint-genese",
    "sg:classifiers":[
        {
            "category":"Shopping Center",
            "type":"Public Place"
        }
    ],
    "sg:phone":"+32 2 359 96 90",
    "sg:postcode":"1640",
    "sg:province":"Vlaams-Brabant",
    "sg:tags":[
        "enseignement",
        "formation"
    ],
    "wof:name":"Krauthammer International/krauthammer Eric",
    "wof:placetype":"venue"
},
  "geometry": {"coordinates":[4.3945999146,50.7476196289],"type":"Point"}
}