{
  "type": "Feature",
  "properties": {
    "addr:full":"Hoogstraat 7 Oosterzele (gijzenzele) Oost-Vlaanderen 9860",
    "addr:housenumber":"7",
    "addr:postcode":"9860",
    "addr:street":"Hoogstraat",
    "iso:country":"BE",
    "sg:address":"Hoogstraat 7",
    "sg:city":"Oosterzele (gijzenzele)",
    "sg:classifiers":[
        {
            "category":"Building & Trades",
            "subcategory":"Construction",
            "type":"Services"
        }
    ],
    "sg:phone":"+32 9 362 67 86",
    "sg:postcode":"9860",
    "sg:province":"Oost-Vlaanderen",
    "sg:tags":[
        "carpenter"
    ],
    "wof:name":"Van De Vijver M",
    "wof:placetype":"venue"
},
  "geometry": {"coordinates":[3.8207120895,50.9710922241],"type":"Point"}
}