{
  "type": "Feature",
  "properties": {
    "addr:full":"Rue Busleyden 1b2 Arlon Luxembourg 6700",
    "addr:housenumber":"1b2",
    "addr:postcode":"6700",
    "addr:street":"Rue Busleyden",
    "iso:country":"BE",
    "sg:address":"Rue Busleyden 1b2",
    "sg:city":"Arlon",
    "sg:orig_category":"Meubles D\u00e9taillants, Am\u00e9nagement de B\u00e2timents et de Cuisines",
    "sg:phone":"+32 63 23 59 15",
    "sg:postcode":"6700",
    "sg:province":"Luxembourg",
    "wof:name":"Jean Warnimont",
    "wof:placetype":"venue"
},
  "geometry": {"coordinates":[5.8201260567,49.6847381592],"type":"Point"}
}