{
  "type": "Feature",
  "properties": {
    "iso:country":"BE",
    "sg:address":"Landsheerstraat 60",
    "sg:city":"Erpe-mere",
    "sg:orig_category":"Supermarkten",
    "sg:phone":"+32 53 62 23 36",
    "sg:postcode":"9420",
    "sg:province":"Oost-Vlaanderen",
    "wof:name":"Caro",
    "wof:placetype":"venue"
},
  "geometry": {"coordinates":[3.9287879467,50.92162323],"type":"Point"}
}