{
  "type": "Feature",
  "properties": {
    "iso:country":"BE",
    "sg:address":"Rue Des Faubourgs 1",
    "sg:city":"Arlon",
    "sg:orig_category":"Banques and organismes de cr\u00e9dit",
    "sg:phone":"+32 63 21 21 11",
    "sg:postcode":"6700",
    "sg:province":"Luxembourg",
    "wof:name":"Bbl",
    "wof:placetype":"venue"
},
  "geometry": {"coordinates":[5.8122301102,49.683921814],"type":"Point"}
}