{
  "type": "Feature",
  "properties": {
    "addr:full":"Peraltastraat 15 Brugge West-Vlaanderen 8000",
    "addr:housenumber":"15",
    "addr:postcode":"8000",
    "addr:street":"Peraltastraat",
    "iso:country":"BE",
    "sg:address":"Peraltastraat 15",
    "sg:city":"Brugge",
    "sg:orig_category":"Installation de menuiserie en bois and plastique",
    "sg:phone":"+32 50 31 09 13",
    "sg:postcode":"8000",
    "sg:province":"West-Vlaanderen",
    "wof:name":"J Van De Kerckhove",
    "wof:placetype":"venue"
},
  "geometry": {"coordinates":[3.2135438919,51.2433128357],"type":"Point"}
}