{
  "type": "Feature",
  "properties": {
    "addr:full":"Grand Route 49 Bassenge Li\u00e8ge 4690",
    "addr:postcode":"4690",
    "addr:street":"Grand Route 49",
    "iso:country":"BE",
    "sg:address":"Grand Route 49",
    "sg:city":"Bassenge",
    "sg:orig_category":"Genealogen",
    "sg:phone":"+32 4 286 24 58",
    "sg:postcode":"4690",
    "sg:province":"Li\u00e8ge",
    "wof:name":"Cabinet G\u00c9n\u00c9alogique Rocour",
    "wof:placetype":"venue"
},
  "geometry": {"coordinates":[5.6180701256,50.7608184814],"type":"Point"}
}