{
  "type": "Feature",
  "properties": {
    "addr:full":"Ostendaelstraat 6 Sint-jans-molenbeek/molenbeek-saint-jean Bruxelles-Capitale 1080",
    "addr:housenumber":"6",
    "addr:postcode":"1080",
    "addr:street":"Ostendaelstraat",
    "iso:country":"BE",
    "sg:address":"Ostendaelstraat 6",
    "sg:city":"Sint-jans-molenbeek/molenbeek-saint-jean",
    "sg:orig_category":"Diverse grafische activiteiten",
    "sg:phone":"+32 2 410 33 15",
    "sg:postcode":"1080",
    "sg:province":"Bruxelles-Capitale",
    "wof:name":"Artzoo Graphic",
    "wof:placetype":"venue"
},
  "geometry": {"coordinates":[4.3183851242,50.854057312],"type":"Point"}
}