{
  "type": "Feature",
  "properties": {
    "addr:full":"Sint-jobsstraat 119 Herentals Antwerpen 2200",
    "addr:housenumber":"119",
    "addr:postcode":"2200",
    "iso:country":"BE",
    "sg:address":"Sint-jobsstraat 119",
    "sg:city":"Herentals",
    "sg:orig_category":"Entretien and r\u00e9parations de voitures. Traitement and rev\u00eatement des m\u00e9taux",
    "sg:phone":"+32 14 21 16 10",
    "sg:postcode":"2200",
    "sg:province":"Antwerpen",
    "wof:name":"Hoeylaerts",
    "wof:placetype":"venue"
},
  "geometry": {"coordinates":[4.8479180336,51.1804122925],"type":"Point"}
}