{
  "type": "Feature",
  "properties": {
    "addr:full":"Rue Saint-fran\u00c7ois 1 Yvoir Namur 5530",
    "addr:housenumber":"1",
    "addr:postcode":"5530",
    "addr:street":"Rue Saint-Franc\u0327Ois",
    "iso:country":"BE",
    "sg:address":"Rue Saint-fran\u00c7ois 1",
    "sg:city":"Yvoir",
    "sg:classifiers":[
        {
            "category":"Insurance",
            "subcategory":"Insurance Agent",
            "type":"Services"
        }
    ],
    "sg:phone":"+32 83 69 04 43",
    "sg:postcode":"5530",
    "sg:province":"Namur",
    "sg:tags":[
        "verzekeringsmakelaars",
        "expert"
    ],
    "wof:name":"P.a.s.s.",
    "wof:placetype":"venue"
},
  "geometry": {"coordinates":[4.9828357697,50.3350410461],"type":"Point"}
}