{
  "type": "Feature",
  "properties": {
    "addr:full":"Rue Arnaud Fraiteur 28 Bruxelles Bruxelles-Capitale 1050",
    "addr:housenumber":"28",
    "addr:postcode":"1050",
    "addr:street":"Rue Arnaud Fraiteur",
    "iso:country":"BE",
    "sg:address":"Rue Arnaud Fraiteur 28",
    "sg:city":"Bruxelles",
    "sg:orig_category":"Bars Sportclubs",
    "sg:phone":"+32 2 646 69 82",
    "sg:postcode":"1050",
    "sg:province":"Bruxelles-Capitale",
    "wof:name":"Faculty",
    "wof:placetype":"venue"
},
  "geometry": {"coordinates":[4.3941898346,50.8175582886],"type":"Point"}
}