{
  "type": "Feature",
  "properties": {
    "addr:full":"Rue Pierre-joseph Antoine 79b Herstal Li\u00e8ge 4040",
    "addr:housenumber":"79b",
    "addr:postcode":"4040",
    "addr:street":"Rue Pierre-Joseph Antoine",
    "iso:country":"BE",
    "sg:address":"Rue Pierre-joseph Antoine 79b",
    "sg:city":"Herstal",
    "sg:classifiers":[
        {
            "category":"Manufacturing",
            "subcategory":"Tools & Machinery",
            "type":"Manufacturing & Wholesale Goods"
        }
    ],
    "sg:phone":"+32 4 227 67 53",
    "sg:postcode":"4040",
    "sg:province":"Li\u00e8ge",
    "sg:tags":[
        "machine"
    ],
    "wof:name":"Tisef Scrl",
    "wof:placetype":"venue"
},
  "geometry": {"coordinates":[5.6405339241,50.6795768738],"type":"Point"}
}