{
  "type": "Feature",
  "properties": {
    "addr:full":"Keizershoek 312 Kontich Antwerpen 2550",
    "addr:housenumber":"312",
    "addr:postcode":"2550",
    "addr:street":"Keizershoek",
    "iso:country":"BE",
    "sg:address":"Keizershoek 312",
    "sg:city":"Kontich",
    "sg:classifiers":[
        {
            "category":"Wholesale",
            "subcategory":"Plants",
            "type":"Manufacturing & Wholesale Goods"
        }
    ],
    "sg:phone":"+32 3 450 85 00",
    "sg:postcode":"2550",
    "sg:province":"Antwerpen",
    "sg:tags":[
        "whol",
        "flower",
        "-",
        "grower"
    ],
    "wof:name":"Aksent",
    "wof:placetype":"venue"
},
  "geometry": {"coordinates":[4.4238290787,51.1222648621],"type":"Point"}
}