{
  "type": "Feature",
  "properties": {
    "iso:country":"BE",
    "sg:address":"Keperenbergstraat 37b",
    "sg:city":"Dilbeek",
    "sg:orig_category":"Fitnesscentra Sportcentra",
    "sg:phone":"+32 2 569 00 48",
    "sg:postcode":"1701",
    "sg:province":"Vlaams-Brabant",
    "wof:name":"Sportzaal Recreatiecentr.",
    "wof:placetype":"venue"
},
  "geometry": {"coordinates":[4.2489171028,50.8360671997],"type":"Point"}
}