{
  "type": "Feature",
  "properties": {
    "iso:country":"BE",
    "sg:address":"Dendermondse Steenweg 23",
    "sg:city":"Aalst",
    "sg:classifiers":[
        {
            "category":"Insurance",
            "subcategory":"Insurance Agent",
            "type":"Services"
        }
    ],
    "sg:phone":"+32 53 78 01 10",
    "sg:postcode":"9300",
    "sg:province":"Oost-Vlaanderen",
    "sg:tags":[
        "broker"
    ],
    "wof:name":"Argenta Kantoor Aalst",
    "wof:placetype":"venue"
},
  "geometry": {"coordinates":[4.0351758003,50.9432754517],"type":"Point"}
}