{
  "type": "Feature",
  "properties": {
    "iso:country":"BE",
    "sg:address":"Acaciastraat 21",
    "sg:city":"Geel",
    "sg:classifiers":[
        {
            "category":"Food & Beverages",
            "subcategory":"Fruits & Vegetables",
            "type":"Retail Goods"
        }
    ],
    "sg:phone":"+32 14 86 61 01",
    "sg:postcode":"2440",
    "sg:province":"Antwerpen",
    "sg:tags":[
        "l\u00e9gumes",
        "gr"
    ],
    "wof:name":"Euro-gijbels",
    "wof:placetype":"venue"
},
  "geometry": {"coordinates":[5.0211420059,51.1172599792],"type":"Point"}
}