{
  "type": "Feature",
  "properties": {
    "iso:country":"BE",
    "sg:address":"Aarschotsesteenweg 87",
    "sg:city":"Leuven",
    "sg:orig_category":"Architecten",
    "sg:phone":"+32 16 73 43 60",
    "sg:postcode":"3012",
    "sg:province":"Vlaams-Brabant",
    "wof:name":"Jan Wijckmans",
    "wof:placetype":"venue"
},
  "geometry": {"coordinates":[4.7102122307,50.9036026001],"type":"Point"}
}