{
  "type": "Feature",
  "properties": {
    "addr:full":"Albert Biesmanslaan 10 Hoeilaart Vlaams-Brabant 1560",
    "addr:housenumber":"10",
    "addr:postcode":"1560",
    "addr:street":"Albert Biesmanslaan",
    "iso:country":"BE",
    "sg:address":"Albert Biesmanslaan 10",
    "sg:city":"Hoeilaart",
    "sg:orig_category":"Industri\u00eble wasserijen and droogkuis",
    "sg:phone":"+32 2 657 22 13",
    "sg:postcode":"1560",
    "sg:province":"Vlaams-Brabant",
    "wof:name":"Milleniclean",
    "wof:placetype":"venue"
},
  "geometry": {"coordinates":[4.4752988815,50.7677001953],"type":"Point"}
}