{
  "type": "Feature",
  "properties": {
    "addr:full":"Rue Du Vieux Ch\u00c2teau 11 Walhain Brabant Wallon 1457",
    "addr:housenumber":"11;1457",
    "addr:street":"Rue Du Vieux Cha\u0302Teau",
    "iso:country":"BE",
    "sg:address":"Rue Du Vieux Ch\u00c2teau 11",
    "sg:city":"Walhain",
    "sg:orig_category":"Dancings and bo\u00eetes de nuit",
    "sg:phone":"+32 10 65 03 98",
    "sg:postcode":"1457",
    "sg:province":"Brabant Wallon",
    "wof:name":"Ex-m",
    "wof:placetype":"venue"
},
  "geometry": {"coordinates":[4.6970200539,50.615447998],"type":"Point"}
}