{
  "type": "Feature",
  "properties": {
    "addr:full":"Baron A. Verhaegenln. 20 Merelbeke Oost-Vlaanderen 9820",
    "addr:housenumber":"20",
    "addr:postcode":"9820",
    "addr:street":"Baron A. Verhaegenln.",
    "iso:country":"BE",
    "sg:address":"Baron A. Verhaegenln. 20",
    "sg:city":"Merelbeke",
    "sg:orig_category":"Drogisterijen",
    "sg:phone":"+32 9 231 31 33",
    "sg:postcode":"9820",
    "sg:province":"Oost-Vlaanderen",
    "wof:name":"Sabine De Wulf",
    "wof:placetype":"venue"
},
  "geometry": {"coordinates":[3.7515850067,50.9990348816],"type":"Point"}
}