{
  "type": "Feature",
  "properties": {
    "addr:full":"Place Maurice S\u00e9bastien 4 Brugelette Hainaut 7940",
    "addr:housenumber":"4",
    "addr:postcode":"7940",
    "addr:street":"Place Maurice Se\u0301Bastien;Hainaut",
    "iso:country":"BE",
    "sg:address":"Place Maurice S\u00e9bastien 4",
    "sg:city":"Brugelette",
    "sg:classifiers":[
        {
            "category":"Health Services",
            "subcategory":"Dentist",
            "type":"Services"
        }
    ],
    "sg:phone":"+32 68 45 51 91",
    "sg:postcode":"7940",
    "sg:province":"Hainaut",
    "wof:name":"Danguy St\u00e9phanie",
    "wof:placetype":"venue"
},
  "geometry": {"coordinates":[3.8525779247,50.5945243835],"type":"Point"}
}