{
  "type": "Feature",
  "properties": {
    "addr:full":"Hogesteenweg 10 Grimbergen Vlaams-Brabant 1850",
    "addr:housenumber":"10",
    "addr:postcode":"1850",
    "addr:street":"Hogesteenweg",
    "iso:country":"BE",
    "sg:address":"Hogesteenweg 10",
    "sg:city":"Grimbergen",
    "sg:classifiers":[
        {
            "category":"Shopping",
            "subcategory":"Luggage & Leather Goods",
            "type":"Retail Goods"
        }
    ],
    "sg:phone":"+32 2 270 94 79",
    "sg:postcode":"1850",
    "sg:province":"Vlaams-Brabant",
    "sg:tags":[
        "-"
    ],
    "wof:name":"Zevensterre (de)",
    "wof:placetype":"venue"
},
  "geometry": {"coordinates":[4.3717808723,50.9330482483],"type":"Point"}
}