{
  "type": "Feature",
  "properties": {
    "iso:country":"BE",
    "sg:address":"Malpertuuslaan 13",
    "sg:city":"Schoten",
    "sg:orig_category":"Experts-comptables",
    "sg:phone":"+32 3 658 28 09",
    "sg:postcode":"2900",
    "sg:province":"Antwerpen",
    "wof:name":"Pierre Truyen",
    "wof:placetype":"venue"
},
  "geometry": {"coordinates":[4.5152988434,51.2640304565],"type":"Point"}
}