{
  "type": "Feature",
  "properties": {
    "addr:full":"Bohemen 21 Wichelen Oost-Vlaanderen 9260",
    "addr:housenumber":"21",
    "addr:postcode":"9260",
    "addr:street":"Bohemen",
    "iso:country":"BE",
    "sg:address":"Bohemen 21",
    "sg:city":"Wichelen",
    "sg:classifiers":[
        {
            "category":"Building & Trades",
            "subcategory":"Construction",
            "type":"Services"
        }
    ],
    "sg:phone":"+32 52 42 32 99",
    "sg:postcode":"9260",
    "sg:province":"Oost-Vlaanderen",
    "sg:tags":[
        "carpenter"
    ],
    "wof:name":"Schuddinck G",
    "wof:placetype":"venue"
},
  "geometry": {"coordinates":[3.9804170132,51.0038909912],"type":"Point"}
}