{
  "type": "Feature",
  "properties": {
    "addr:full":"Rue Saint-sauveur 2 La Bruyere Namur 5081",
    "addr:housenumber":"2",
    "addr:postcode":"5081",
    "addr:street":"Rue Saint-Sauveur;La Bruyere",
    "iso:country":"BE",
    "sg:address":"Rue Saint-sauveur 2",
    "sg:city":"La Bruyere",
    "sg:orig_category":"Herstellingen and onderhoud van auto's",
    "sg:phone":"+32 81 56 77 78",
    "sg:postcode":"5081",
    "sg:province":"Namur",
    "wof:name":"Emile Flamand",
    "wof:placetype":"venue"
},
  "geometry": {"coordinates":[4.8039960861,50.5503311157],"type":"Point"}
}