{
  "type": "Feature",
  "properties": {
    "addr:full":"Tervurenlaan 12b6 Etterbeek Bruxelles-Capitale 1040",
    "addr:housenumber":"12b6",
    "addr:postcode":"1040",
    "addr:street":"Tervurenlaan",
    "iso:country":"BE",
    "sg:address":"Tervurenlaan 12b6",
    "sg:city":"Etterbeek",
    "sg:classifiers":[
        {
            "category":"Insurance",
            "subcategory":"Insurance Agent",
            "type":"Services"
        }
    ],
    "sg:phone":"+32 2 736 01 70",
    "sg:postcode":"1040",
    "sg:province":"Bruxelles-Capitale",
    "sg:tags":[
        "verzekeringsmakelaars",
        "expert"
    ],
    "wof:name":"Coteca",
    "wof:placetype":"venue"
},
  "geometry": {"coordinates":[4.3987178802,50.8395881653],"type":"Point"}
}