{
  "type": "Feature",
  "properties": {
    "iso:country":"BE",
    "sg:address":"Rue De Namur 131",
    "sg:city":"Wavre",
    "sg:classifiers":[
        {
            "category":"Bakery",
            "type":"Food & Drink"
        }
    ],
    "sg:phone":"+32 10 22 24 74",
    "sg:postcode":"1300",
    "sg:province":"Brabant Wallon",
    "sg:tags":[
        "cake",
        "product",
        "related",
        "bread"
    ],
    "wof:name":"Boulangerie De La C\u00d4te Sa",
    "wof:placetype":"venue"
},
  "geometry": {"coordinates":[4.6142301559,50.7110328674],"type":"Point"}
}