{
  "type": "Feature",
  "properties": {
    "iso:country":"BE",
    "sg:address":"Hannekestraat 21c",
    "sg:city":"Dessel",
    "sg:classifiers":[
        {
            "category":"Education",
            "subcategory":"Dance Studio",
            "type":"Public Place"
        }
    ],
    "sg:phone":"+32 14 37 23 59",
    "sg:postcode":"2480",
    "sg:province":"Antwerpen",
    "sg:tags":[
        "school",
        "dancing"
    ],
    "wof:name":"Rock Fifty-5",
    "wof:placetype":"venue"
},
  "geometry": {"coordinates":[5.1098980904,51.2391052246],"type":"Point"}
}