{
  "type": "Feature",
  "properties": {
    "iso:country":"BE",
    "sg:address":"Gladiolenweg 5",
    "sg:city":"Tienen",
    "sg:orig_category":"Pleisterwerk",
    "sg:phone":"+32 16 60 05 47",
    "sg:postcode":"3300",
    "sg:province":"Vlaams-Brabant",
    "wof:name":"Frans Heymbeek",
    "wof:placetype":"venue"
},
  "geometry": {"coordinates":[4.952393055,50.8164558411],"type":"Point"}
}