{
  "type": "Feature",
  "properties": {
    "iso:country":"BE",
    "sg:address":"Rue Des Clarisses 14",
    "sg:city":"Tournai",
    "sg:classifiers":[
        {
            "category":"Government",
            "subcategory":"Fire Station",
            "type":"Public Place"
        }
    ],
    "sg:phone":"+32 69 84 36 22",
    "sg:postcode":"7500",
    "sg:province":"Hainaut",
    "sg:tags":[
        "packard",
        "nec",
        "bell"
    ],
    "wof:name":"Photo-hall Tournai",
    "wof:placetype":"venue"
},
  "geometry": {"coordinates":[3.3916258812,50.6054191589],"type":"Point"}
}