{
  "type": "Feature",
  "properties": {
    "addr:full":"Botestraat 14 Gent Oost-Vlaanderen 9032",
    "addr:housenumber":"14",
    "addr:postcode":"9032",
    "addr:street":"Botestraat;Oost-Vlaanderen",
    "iso:country":"BE",
    "sg:address":"Botestraat 14",
    "sg:city":"Gent",
    "sg:orig_category":"Chaussures",
    "sg:phone":"+32 9 258 03 67",
    "sg:postcode":"9032",
    "sg:province":"Oost-Vlaanderen",
    "wof:name":"Shoes In The Box",
    "wof:placetype":"venue"
},
  "geometry": {"coordinates":[3.7162549496,51.0900535583],"type":"Point"}
}