{
  "type": "Feature",
  "properties": {
    "addr:full":"Bruynstraat 1 Brussel/bruxelles Bruxelles-Capitale 1120",
    "addr:housenumber":"1",
    "addr:postcode":"1120",
    "addr:street":"Bruynstraat;/",
    "iso:country":"BE",
    "sg:address":"Bruynstraat 1",
    "sg:city":"Brussel/bruxelles",
    "sg:orig_category":"Opticiens",
    "sg:phone":"+32 2 264 45 42",
    "sg:postcode":"1120",
    "sg:province":"Bruxelles-Capitale",
    "wof:name":"Ctr.optiq.h\u00d4pit.militaire",
    "wof:placetype":"venue"
},
  "geometry": {"coordinates":[4.3891181946,50.9060745239],"type":"Point"}
}