{
  "type": "Feature",
  "properties": {
    "addr:full":"Groot-brittannielaan 51 Gent Oost-Vlaanderen 9000",
    "addr:housenumber":"51",
    "addr:postcode":"9000",
    "addr:street":"Groot-Brittannielaan;Oost-Vlaanderen",
    "iso:country":"BE",
    "sg:address":"Groot-brittannielaan 51",
    "sg:city":"Gent",
    "sg:orig_category":"Zalen voor culturele evenementen",
    "sg:phone":"+32 9 265 91 62",
    "sg:postcode":"9000",
    "sg:province":"Oost-Vlaanderen",
    "wof:name":"Gele Zaal",
    "wof:placetype":"venue"
},
  "geometry": {"coordinates":[3.7109630108,51.0429573059],"type":"Point"}
}