{
  "type": "Feature",
  "properties": {
    "addr:full":"Blanchestraat 42 Sint-gillis/saint-gilles Bruxelles-Capitale 1060",
    "addr:housenumber":"42",
    "addr:postcode":"1060",
    "addr:street":"Blanchestraat",
    "iso:country":"BE",
    "sg:address":"Blanchestraat 42",
    "sg:city":"Sint-gillis/saint-gilles",
    "sg:orig_category":"Diverse grafische activiteiten Marktonderzoekbureaus",
    "sg:phone":"+32 2 538 98 98",
    "sg:postcode":"1060",
    "sg:province":"Bruxelles-Capitale",
    "wof:name":"Bur. Ursini Strat.design",
    "wof:placetype":"venue"
},
  "geometry": {"coordinates":[4.3573198318,50.8296318054],"type":"Point"}
}