{
  "type": "Feature",
  "properties": {
    "iso:country":"BE",
    "sg:address":"Herentalsesteenweg 17",
    "sg:city":"Kasterlee (lichtaart)",
    "sg:classifiers":[
        {
            "category":"Autos & Motor Vehicles",
            "subcategory":"Fuel & Gas Station",
            "type":"Retail Goods"
        }
    ],
    "sg:phone":"+32 14 55 63 39",
    "sg:postcode":"2460",
    "sg:province":"Antwerpen",
    "wof:name":"Caeymaex Bvba",
    "wof:placetype":"venue"
},
  "geometry": {"coordinates":[4.894589901,51.2070617676],"type":"Point"}
}