{
  "type": "Feature",
  "properties": {
    "addr:full":"Hogeschoollaan 34 Elsene/ixelles Bruxelles-Capitale 1050",
    "addr:housenumber":"34",
    "addr:postcode":"1050",
    "addr:street":"Hogeschoollaan",
    "iso:country":"BE",
    "sg:address":"Hogeschoollaan 34",
    "sg:city":"Elsene/ixelles",
    "sg:orig_category":"Medische apparatuur, orthopedische artikelen and prothesen Fab",
    "sg:phone":"+32 2 649 57 33",
    "sg:postcode":"1050",
    "sg:province":"Bruxelles-Capitale",
    "wof:name":"Labo V.d.b.",
    "wof:placetype":"venue"
},
  "geometry": {"coordinates":[4.3883528709,50.8149719238],"type":"Point"}
}