{
  "type": "Feature",
  "properties": {
    "addr:full":"Av. Bourg. Jean Materne 89 Namur Namur 5100",
    "addr:housenumber":"89",
    "addr:postcode":"5100",
    "addr:street":"Av. Bourg. Jean Materne",
    "iso:country":"BE",
    "sg:address":"Av. Bourg. Jean Materne 89",
    "sg:city":"Namur",
    "sg:orig_category":"Alimentation sp\u00e9cialis\u00e9e",
    "sg:phone":"+32 81 30 06 22",
    "sg:postcode":"5100",
    "sg:province":"Namur",
    "wof:name":"Ets. Carabin",
    "wof:placetype":"venue"
},
  "geometry": {"coordinates":[4.8713750839,50.4566345215],"type":"Point"}
}