{
  "type": "Feature",
  "properties": {
    "iso:country":"BE",
    "sg:address":"Oordegemsesteenweg 169",
    "sg:city":"Wetteren",
    "sg:orig_category":"Woningbouw",
    "sg:phone":"+32 9 369 54 88",
    "sg:postcode":"9230",
    "sg:province":"Oost-Vlaanderen",
    "wof:name":"Roger Hebbelinck",
    "wof:placetype":"venue"
},
  "geometry": {"coordinates":[3.8863010406,50.9954452515],"type":"Point"}
}