{
  "type": "Feature",
  "properties": {
    "iso:country":"BE",
    "sg:address":"Stefaniastraat 161",
    "sg:city":"Brussel/bruxelles",
    "sg:orig_category":"Diensten voor huisdieren",
    "sg:phone":"+32 2 428 12 58",
    "sg:postcode":"1020",
    "sg:province":"Bruxelles-Capitale",
    "wof:name":"Le Cabotin",
    "wof:placetype":"venue"
},
  "geometry": {"coordinates":[4.3492717743,50.8774414062],"type":"Point"}
}