{
  "type": "Feature",
  "properties": {
    "addr:full":"Rue De La Florbecq 48 Lessines (ollignies) Hainaut 7866",
    "addr:housenumber":"48",
    "addr:postcode":"7866",
    "addr:street":"Rue De La Florbecq",
    "iso:country":"BE",
    "sg:address":"Rue De La Florbecq 48",
    "sg:city":"Lessines (ollignies)",
    "sg:classifiers":[
        {
            "category":"Retail",
            "subcategory":"Veterinary Services",
            "type":"Services"
        }
    ],
    "sg:phone":"+32 68 33 32 43",
    "sg:postcode":"7866",
    "sg:province":"Hainaut",
    "sg:tags":[
        "veterinarian"
    ],
    "wof:name":"H\u00eane R",
    "wof:placetype":"venue"
},
  "geometry": {"coordinates":[3.8493859768,50.6868934631],"type":"Point"}
}