{
  "type": "Feature",
  "properties": {
    "iso:country":"BE",
    "sg:address":"Hoof 122",
    "sg:city":"Welkenraedt/welkenraedt",
    "sg:orig_category":"Eleveurs and marchands de porcs. Eleveurs de bovins",
    "sg:phone":"+32 87 44 63 83",
    "sg:postcode":"4841",
    "sg:province":"Li\u00e8ge",
    "wof:name":"Vanderheyden A. & J.",
    "wof:placetype":"venue"
},
  "geometry": {"coordinates":[5.9195780754,50.6508865356],"type":"Point"}
}