{
  "type": "Feature",
  "properties": {
    "addr:full":"Hoogstraat 19 Antwerpen Antwerpen 2000",
    "addr:housenumber":"19",
    "addr:postcode":"2000",
    "addr:street":"Hoogstraat",
    "iso:country":"BE",
    "sg:address":"Hoogstraat 19",
    "sg:city":"Antwerpen",
    "sg:classifiers":[
        {
            "category":"Shopping",
            "subcategory":"Clothing, Apparel, & Fashions",
            "type":"Retail Goods"
        }
    ],
    "sg:phone":"+32 3 234 27 82",
    "sg:postcode":"2000",
    "sg:province":"Antwerpen",
    "sg:tags":[
        "v\u00eatements",
        "pour",
        "dame"
    ],
    "wof:name":"Boetiek Archipel",
    "wof:placetype":"venue"
},
  "geometry": {"coordinates":[4.3985881805,51.2199897766],"type":"Point"}
}