{
  "type": "Feature",
  "properties": {
    "iso:country":"BE",
    "sg:address":"Avenue Des V\u00ces Tchapias 1b6",
    "sg:city":"Ottignies-louvain-la-neuve",
    "sg:orig_category":"Schoonheidssalons",
    "sg:phone":"+32 10 41 88 88",
    "sg:postcode":"1340",
    "sg:province":"Brabant Wallon",
    "wof:name":"P\u00c9dicure Van Malder",
    "wof:placetype":"venue"
},
  "geometry": {"coordinates":[4.5849971771,50.6648979187],"type":"Point"}
}