{
  "type": "Feature",
  "properties": {
    "iso:country":"BE",
    "sg:address":"Rue Cavalier Fonck 5",
    "sg:city":"Thimister-clermont",
    "sg:orig_category":"Traducteurs and interpr\u00e8tes",
    "sg:phone":"+32 87 44 50 09",
    "sg:postcode":"4890",
    "sg:province":"Li\u00e8ge",
    "wof:name":"Notturni S. Cbtip/bkvtf",
    "wof:placetype":"venue"
},
  "geometry": {"coordinates":[5.8628058434,50.6488227844],"type":"Point"}
}