{
  "type": "Feature",
  "properties": {
    "addr:full":"Rue Auguste Scohy 97b4 Aiseau-presles Hainaut 6250",
    "addr:housenumber":"97b4",
    "addr:postcode":"6250",
    "addr:street":"Rue Auguste Scohy;Hainaut",
    "iso:country":"BE",
    "sg:address":"Rue Auguste Scohy 97b4",
    "sg:city":"Aiseau-presles",
    "sg:orig_category":"Charpentes and couvertures. Plomberie, chauffage and installations sanitaires",
    "sg:phone":"+32 71 39 33 48",
    "sg:postcode":"6250",
    "sg:province":"Hainaut",
    "wof:name":"Fabrice Camilliard",
    "wof:placetype":"venue"
},
  "geometry": {"coordinates":[4.5468659401,50.4110565186],"type":"Point"}
}