{
  "type": "Feature",
  "properties": {
    "addr:full":"Hendrik Consciencehof 7 Harelbeke West-Vlaanderen 8530",
    "addr:housenumber":"7",
    "addr:postcode":"8530",
    "addr:street":"Consciencehof",
    "iso:country":"BE",
    "sg:address":"Hendrik Consciencehof 7",
    "sg:city":"Harelbeke",
    "sg:classifiers":[
        {
            "category":"Personal",
            "subcategory":"Nail Salon",
            "type":"Services"
        }
    ],
    "sg:phone":"+32 56 72 87 88",
    "sg:postcode":"8530",
    "sg:province":"West-Vlaanderen",
    "sg:tags":[
        "pedicure"
    ],
    "wof:name":"Vanfleteren N",
    "wof:placetype":"venue"
},
  "geometry": {"coordinates":[3.3037080765,50.8493881226],"type":"Point"}
}