{
  "type": "Feature",
  "properties": {
    "addr:full":"Rue Du Vallon 15 Fl\u00e9ron Li\u00e8ge 4624",
    "addr:housenumber":"15",
    "addr:postcode":"4624",
    "addr:street":"Rue Du Vallon",
    "iso:country":"BE",
    "sg:address":"Rue Du Vallon 15",
    "sg:city":"Fl\u00e9ron",
    "sg:classifiers":[
        {
            "category":"Building & Trades",
            "subcategory":"Construction",
            "type":"Services"
        }
    ],
    "sg:phone":"+32 2 344 02 55",
    "sg:postcode":"4624",
    "sg:province":"Li\u00e8ge",
    "sg:tags":[
        "work",
        "public"
    ],
    "wof:name":"Asphalte Trojan Sa",
    "wof:placetype":"venue"
},
  "geometry": {"coordinates":[4.3070120811,50.8243103027],"type":"Point"}
}