{
  "type": "Feature",
  "properties": {
    "iso:country":"BE",
    "sg:address":"Place Colonel Peckham 4",
    "sg:city":"Plombieres",
    "sg:classifiers":[
        {
            "category":"Cafe",
            "type":"Food & Drink"
        }
    ],
    "sg:phone":"+32 87 78 67 55",
    "sg:postcode":"4851",
    "sg:province":"Li\u00e8ge",
    "sg:tags":[
        "caf\u00e9s"
    ],
    "wof:name":"Paul Steins",
    "wof:placetype":"venue"
},
  "geometry": {"coordinates":[5.9971208572,50.7460594177],"type":"Point"}
}