{
  "type": "Feature",
  "properties": {
    "iso:country":"BE",
    "sg:address":"Grand-rue 91",
    "sg:city":"Courcelles",
    "sg:classifiers":[
        {
            "category":"Cafe",
            "type":"Food & Drink"
        }
    ],
    "sg:phone":"+32 71 45 75 08",
    "sg:postcode":"6183",
    "sg:province":"Hainaut",
    "sg:tags":[
        "caf\u00e9s"
    ],
    "wof:name":"Caf\u00c9 Du Bon Coin",
    "wof:placetype":"venue"
},
  "geometry": {"coordinates":[4.3350520134,50.4609794617],"type":"Point"}
}