{
  "type": "Feature",
  "properties": {
    "addr:full":"Palingstraat 24 Meise Vlaams-Brabant 1861",
    "addr:housenumber":"24",
    "addr:postcode":"1861",
    "addr:street":"Palingstraat",
    "iso:country":"BE",
    "sg:address":"Palingstraat 24",
    "sg:city":"Meise",
    "sg:orig_category":"Produits \u00e0 base de pommes de terre Fruits and l\u00e9gumes Gr",
    "sg:phone":"+32 2 269 40 28",
    "sg:postcode":"1861",
    "sg:province":"Vlaams-Brabant",
    "wof:name":"Fa. Lathouwers & Co.",
    "wof:placetype":"venue"
},
  "geometry": {"coordinates":[4.2997069359,50.9591445923],"type":"Point"}
}