{
  "type": "Feature",
  "properties": {
    "iso:country":"BE",
    "sg:address":"Antoine Dansaertstraat 155",
    "sg:city":"Brussel/bruxelles",
    "sg:orig_category":"Industri\u00eble wasserijen and droogkuis",
    "sg:phone":"+32 2 219 05 62",
    "sg:postcode":"1000",
    "sg:province":"Bruxelles-Capitale",
    "wof:name":"Lav O Net",
    "wof:placetype":"venue"
},
  "geometry": {"coordinates":[4.3433251381,50.8525085449],"type":"Point"}
}