{
  "type": "Feature",
  "properties": {
    "addr:full":"Vinkenstraat 26 Grimbergen Vlaams-Brabant 1850",
    "addr:housenumber":"26",
    "addr:postcode":"1850",
    "addr:street":"Vinkenstraat",
    "iso:country":"BE",
    "sg:address":"Vinkenstraat 26",
    "sg:city":"Grimbergen",
    "sg:classifiers":[
        {
            "category":"Real Estate",
            "subcategory":"Architect",
            "type":"Services"
        }
    ],
    "sg:phone":"+32 2 251 52 61",
    "sg:postcode":"1850",
    "sg:province":"Vlaams-Brabant",
    "wof:name":"Buelens L",
    "wof:placetype":"venue"
},
  "geometry": {"coordinates":[4.3994379044,50.9297561646],"type":"Point"}
}