{
  "type": "Feature",
  "properties": {
    "addr:full":"Markt 24 Ruiselede West-Vlaanderen 8755",
    "addr:housenumber":"24",
    "addr:postcode":"8755",
    "addr:street":"Markt",
    "iso:country":"BE",
    "sg:address":"Markt 24",
    "sg:city":"Ruiselede",
    "sg:orig_category":"Banques and organismes de cr\u00e9dit",
    "sg:phone":"+32 51 68 92 19",
    "sg:postcode":"8755",
    "sg:province":"West-Vlaanderen",
    "wof:name":"Fortis",
    "wof:placetype":"venue"
},
  "geometry": {"coordinates":[3.3966720104,51.0416297913],"type":"Point"}
}