{
  "type": "Feature",
  "properties": {
    "iso:country":"BE",
    "sg:address":"Rue Du Faubourg 12",
    "sg:city":"Rebecq",
    "sg:classifiers":[
        {
            "category":"Government",
            "subcategory":"Police Station",
            "type":"Public Place"
        }
    ],
    "sg:phone":"+32 67 63 86 63",
    "sg:postcode":"1430",
    "sg:province":"Brabant Wallon",
    "sg:tags":[
        "gendarmerie"
    ],
    "wof:name":"Police F\u00c9d\u00c9rale/federale Politie",
    "wof:placetype":"venue"
},
  "geometry": {"coordinates":[4.1568112373,50.6695365906],"type":"Point"}
}