{
  "type": "Feature",
  "properties": {
    "iso:country":"BE",
    "sg:address":"Elsstraat 11",
    "sg:city":"Maarkedal",
    "sg:orig_category":"Rev\u00eatements de sols and murs. Magasins sp\u00e9cialis\u00e9s",
    "sg:phone":"+32 55 21 68 07",
    "sg:postcode":"9681",
    "sg:province":"Oost-Vlaanderen",
    "wof:name":"Vanalderwerelt Natuursteen",
    "wof:placetype":"venue"
},
  "geometry": {"coordinates":[3.5952050686,50.7969856262],"type":"Point"}
}