{
  "type": "Feature",
  "properties": {
    "addr:full":"Rue Tilleul Sambr\u00c9e 8 Perwez Brabant Wallon 1360",
    "addr:housenumber":"8",
    "addr:postcode":"1360",
    "addr:street":"Rue Tilleul Sambre\u0301E",
    "iso:country":"BE",
    "sg:address":"Rue Tilleul Sambr\u00c9e 8",
    "sg:city":"Perwez",
    "sg:orig_category":"Plomberie, chauffage and installations sanitaires",
    "sg:phone":"+32 81 65 74 27",
    "sg:postcode":"1360",
    "sg:province":"Brabant Wallon",
    "wof:name":"Fe. Sillien",
    "wof:placetype":"venue"
},
  "geometry": {"coordinates":[4.7644081116,50.6362342834],"type":"Point"}
}