{
  "type": "Feature",
  "properties": {
    "iso:country":"BE",
    "sg:address":"Rue Uyttenhove 39ba",
    "sg:city":"Jette/jette",
    "sg:orig_category":"Avocats and conseillers juridiques",
    "sg:phone":"+32 2 426 86 36",
    "sg:postcode":"1090",
    "sg:province":"Bruxelles-Capitale",
    "wof:name":"R. Baudewyn",
    "wof:placetype":"venue"
},
  "geometry": {"coordinates":[4.3364109993,50.8706130981],"type":"Point"}
}