{
  "type": "Feature",
  "properties": {
    "iso:country":"BE",
    "sg:address":"Chauss\u00c9e De Wavre 120",
    "sg:city":"Perwez",
    "sg:orig_category":"Boissons. Boissons Gr",
    "sg:phone":"+32 81 65 67 77",
    "sg:postcode":"1360",
    "sg:province":"Brabant Wallon",
    "wof:name":"Brasserie Baccus",
    "wof:placetype":"venue"
},
  "geometry": {"coordinates":[4.8033800125,50.6295204163],"type":"Point"}
}