{
  "type": "Feature",
  "properties": {
    "addr:full":"Rue De Fumay 11 Viroinval Namur 5670",
    "addr:housenumber":"11",
    "addr:postcode":"5670",
    "addr:street":"Rue De Fumay",
    "iso:country":"BE",
    "sg:address":"Rue De Fumay 11",
    "sg:city":"Viroinval",
    "sg:orig_category":"Offices du tourisme",
    "sg:phone":"+32 60 39 03 63",
    "sg:postcode":"5670",
    "sg:province":"Namur",
    "wof:name":"Syndicat D'initiative",
    "wof:placetype":"venue"
},
  "geometry": {"coordinates":[4.64164114,50.021522522],"type":"Point"}
}