{
  "type": "Feature",
  "properties": {
    "iso:country":"BE",
    "sg:address":"Rue De La Clef 48",
    "sg:city":"Mons",
    "sg:classifiers":[
        {
            "category":"Fast Food",
            "type":"Food & Drink"
        }
    ],
    "sg:phone":"+32 65 84 36 64",
    "sg:postcode":"7000",
    "sg:province":"Hainaut",
    "sg:tags":[
        "fried",
        "stand",
        "potato"
    ],
    "wof:name":"Arr\u00eat Du Temps (l')",
    "wof:placetype":"venue"
},
  "geometry": {"coordinates":[3.9533810616,50.4523696899],"type":"Point"}
}