{
  "type": "Feature",
  "properties": {
    "addr:full":"Chauss\u00e9e D'ixelles 284 Bruxelles (ixelles) Bruxelles-Capitale 1050",
    "addr:housenumber":"284",
    "addr:postcode":"1050",
    "addr:street":"Chausse\u0301E D'Ixelles",
    "iso:country":"BE",
    "sg:address":"Chauss\u00e9e D'ixelles 284",
    "sg:city":"Bruxelles (ixelles)",
    "sg:classifiers":[
        {
            "category":"Home & Garden",
            "subcategory":"Home Furnishings",
            "type":"Retail Goods"
        }
    ],
    "sg:phone":"+32 2 649 54 14",
    "sg:postcode":"1050",
    "sg:province":"Bruxelles-Capitale",
    "sg:tags":[
        "lampshade",
        "chandelier",
        "-"
    ],
    "wof:name":"Snacken (la Fille D'alex) Sprl",
    "wof:placetype":"venue"
},
  "geometry": {"coordinates":[4.3704981804,50.8292274475],"type":"Point"}
}