{
  "type": "Feature",
  "properties": {
    "addr:full":"Faliestraat 40 Zedelgem West-Vlaanderen 8210",
    "addr:housenumber":"40",
    "addr:postcode":"8210",
    "addr:street":"Faliestraat",
    "iso:country":"BE",
    "sg:address":"Faliestraat 40",
    "sg:city":"Zedelgem",
    "sg:classifiers":[
        {
            "category":"Government",
            "subcategory":"Fire Station",
            "type":"Public Place"
        }
    ],
    "sg:phone":"+31 495 493 212",
    "sg:postcode":"8210",
    "sg:province":"West-Vlaanderen",
    "sg:tags":[
        "installation",
        "-",
        "air conditioning"
    ],
    "wof:name":"Airflow Koeltechniek & Airconditioning V.o.f.",
    "wof:placetype":"venue"
},
  "geometry": {"coordinates":[5.5788660049,51.2669372559],"type":"Point"}
}