{
  "type": "Feature",
  "properties": {
    "addr:full":"Zeelaan 63 Koksijde West-Vlaanderen 8670",
    "addr:housenumber":"63",
    "addr:postcode":"8670",
    "addr:street":"Zeelaan",
    "iso:country":"BE",
    "sg:address":"Zeelaan 63",
    "sg:city":"Koksijde",
    "sg:classifiers":[
        {
            "category":"Insurance",
            "subcategory":"Insurance Agent",
            "type":"Services"
        }
    ],
    "sg:phone":"+32 58 51 58 87",
    "sg:postcode":"8670",
    "sg:province":"West-Vlaanderen",
    "sg:tags":[
        "verzekeringsmakelaars",
        "expert"
    ],
    "wof:name":"N.m.k.n.",
    "wof:placetype":"venue"
},
  "geometry": {"coordinates":[2.6485059261,51.1065979004],"type":"Point"}
}