{
  "type": "Feature",
  "properties": {
    "iso:country":"BE",
    "sg:address":"Sportstraat 434",
    "sg:city":"Gent",
    "sg:orig_category":"Artistes ind\u00e9pendants",
    "sg:phone":"+32 9 221 69 43",
    "sg:postcode":"9000",
    "sg:province":"Oost-Vlaanderen",
    "wof:name":"Mathias Sercu",
    "wof:placetype":"venue"
},
  "geometry": {"coordinates":[3.7018299103,51.0395545959],"type":"Point"}
}