{
  "type": "Feature",
  "properties": {
    "addr:full":"Rue Abb\u00c9 De L'ep\u00c9e 20 Sint-lambrechts-woluwe/woluwe-saint-lambert Bruxelles-Capitale 1200",
    "addr:housenumber":"20",
    "addr:postcode":"1200",
    "addr:street":"Rue Abbe\u0301 De L'Epe \u0301E",
    "iso:country":"BE",
    "sg:address":"Rue Abb\u00c9 De L'ep\u00c9e 20",
    "sg:city":"Sint-lambrechts-woluwe/woluwe-saint-lambert",
    "sg:orig_category":"M\u00e9decins and sp\u00e9cialistes",
    "sg:phone":"+32 2 735 89 79",
    "sg:postcode":"1200",
    "sg:province":"Bruxelles-Capitale",
    "wof:name":"Gilbert Paul",
    "wof:placetype":"venue"
},
  "geometry": {"coordinates":[4.4120078087,50.8427963257],"type":"Point"}
}