{
  "type": "Feature",
  "properties": {
    "addr:full":"Hooiweg 36 Heist-op-den-berg Antwerpen 2222",
    "addr:housenumber":"36",
    "addr:postcode":"2222",
    "addr:street":"Hooiweg",
    "iso:country":"BE",
    "sg:address":"Hooiweg 36",
    "sg:city":"Heist-op-den-berg",
    "sg:classifiers":[
        {
            "category":"Fast Food",
            "type":"Food & Drink"
        }
    ],
    "sg:phone":"+32 15 24 48 28",
    "sg:postcode":"2222",
    "sg:province":"Antwerpen",
    "sg:tags":[
        "\u00c0",
        "restaurants",
        "emporter",
        "restaurant"
    ],
    "wof:name":"Restaurant \u00b4t Spinnewiel",
    "wof:placetype":"venue"
},
  "geometry": {"coordinates":[4.7292399406,51.1032218933],"type":"Point"}
}