{
  "type": "Feature",
  "properties": {
    "iso:country":"BE",
    "sg:address":"Predikherenstraat 9",
    "sg:city":"Tongeren",
    "sg:classifiers":[
        {
            "category":"Health Services",
            "subcategory":"Dentist",
            "type":"Services"
        }
    ],
    "sg:phone":"+32 12 23 27 75",
    "sg:postcode":"3700",
    "sg:province":"Limburg",
    "wof:name":"Philips A",
    "wof:placetype":"venue"
},
  "geometry": {"coordinates":[5.4682002068,50.7811088562],"type":"Point"}
}