{
  "type": "Feature",
  "properties": {
    "addr:full":"Hulststraat 34 Lier Antwerpen 2500",
    "addr:housenumber":"34",
    "addr:postcode":"2500",
    "addr:street":"Hulststraat",
    "iso:country":"BE",
    "sg:address":"Hulststraat 34",
    "sg:city":"Lier",
    "sg:orig_category":"Artsen and specialisten",
    "sg:phone":"+32 3 480 05 34",
    "sg:postcode":"2500",
    "sg:province":"Antwerpen",
    "wof:name":"J. Bosmans",
    "wof:placetype":"venue"
},
  "geometry": {"coordinates":[4.5303349495,51.1251144409],"type":"Point"}
}