{
  "type": "Feature",
  "properties": {
    "addr:full":"Zuidlaan 14 Blankenberge West-Vlaanderen 8370",
    "addr:housenumber":"14",
    "addr:postcode":"8370",
    "addr:street":"Zuidlaan",
    "iso:country":"BE",
    "sg:address":"Zuidlaan 14",
    "sg:city":"Blankenberge",
    "sg:orig_category":"Advocaten and juridische adviseurs",
    "sg:phone":"+32 50 41 41 18",
    "sg:postcode":"8370",
    "sg:province":"West-Vlaanderen",
    "wof:name":"Eric De Ville",
    "wof:placetype":"venue"
},
  "geometry": {"coordinates":[3.1342740059,51.3099861145],"type":"Point"}
}