{
  "type": "Feature",
  "properties": {
    "addr:full":"Veluwestraat 24 Mechelen Antwerpen 2800",
    "addr:housenumber":"24",
    "addr:postcode":"2800",
    "addr:street":"Veluwestraat",
    "iso:country":"BE",
    "sg:address":"Veluwestraat 24",
    "sg:city":"Mechelen",
    "sg:orig_category":"Brood, gebak and snoepgoed",
    "sg:phone":"+32 15 20 48 68",
    "sg:postcode":"2800",
    "sg:province":"Antwerpen",
    "wof:name":"Bakkerij Verstraelen",
    "wof:placetype":"venue"
},
  "geometry": {"coordinates":[4.4733462334,51.0241470337],"type":"Point"}
}