{
  "type": "Feature",
  "properties": {
    "iso:country":"BE",
    "sg:address":"Avenue Des Celtes 46",
    "sg:city":"Bruxelles (etterbeek)",
    "sg:classifiers":[
        {
            "category":"Communications",
            "subcategory":"News Services",
            "type":"Services"
        }
    ],
    "sg:phone":"+32 2 736 90 36",
    "sg:postcode":"1040",
    "sg:province":"Bruxelles-Capitale",
    "sg:tags":[
        "illustrator"
    ],
    "wof:name":"Hendroz D",
    "wof:placetype":"venue"
},
  "geometry": {"coordinates":[4.3970527649,50.8378448486],"type":"Point"}
}