{
  "type": "Feature",
  "properties": {
    "addr:full":"Rue De La Victoire 31 Fernelmont Namur 5380",
    "addr:housenumber":"31",
    "addr:postcode":"5380",
    "addr:street":"Rue De La",
    "iso:country":"BE",
    "sg:address":"Rue De La Victoire 31",
    "sg:city":"Fernelmont",
    "sg:classifiers":[
        {
            "category":"Government",
            "subcategory":"Police Station",
            "type":"Public Place"
        }
    ],
    "sg:phone":"+32 81 83 34 01",
    "sg:postcode":"5380",
    "sg:province":"Namur",
    "sg:tags":[
        "gendarmerie"
    ],
    "wof:name":"Police F\u00c9d\u00c9rale",
    "wof:placetype":"venue"
},
  "geometry": {"coordinates":[4.9586200714,50.5488739014],"type":"Point"}
}