{
  "type": "Feature",
  "properties": {
    "addr:full":"Koning Albertstraat 146 Ravels Antwerpen 2381",
    "addr:housenumber":"146",
    "addr:postcode":"2381",
    "addr:street":"Koning Albertstraat",
    "iso:country":"BE",
    "sg:address":"Koning Albertstraat 146",
    "sg:city":"Ravels",
    "sg:orig_category":"Slagers",
    "sg:phone":"+32 14 65 99 85",
    "sg:postcode":"2381",
    "sg:province":"Antwerpen",
    "wof:name":"Weldse Vleeshal",
    "wof:placetype":"venue"
},
  "geometry": {"coordinates":[4.9977459908,51.4103355408],"type":"Point"}
}