{
  "type": "Feature",
  "properties": {
    "addr:full":"Rue De Ninove 127 Ronse/renaix Oost-Vlaanderen 9600",
    "addr:housenumber":"127",
    "addr:postcode":"9600",
    "addr:street":"Rue De Ninove",
    "iso:country":"BE",
    "sg:address":"Rue De Ninove 127",
    "sg:city":"Ronse/renaix",
    "sg:orig_category":"Caravanes and remorques",
    "sg:phone":"+32 55 21 31 26",
    "sg:postcode":"9600",
    "sg:province":"Oost-Vlaanderen",
    "wof:name":"Caravans Expo",
    "wof:placetype":"venue"
},
  "geometry": {"coordinates":[3.6108899117,50.7511558533],"type":"Point"}
}