{
  "type": "Feature",
  "properties": {
    "iso:country":"BE",
    "sg:address":"Sint-antoniuslei 40",
    "sg:city":"Brasschaat",
    "sg:classifiers":[
        {
            "category":"Real Estate",
            "subcategory":"Architect",
            "type":"Services"
        }
    ],
    "sg:phone":"+32 3 315 13 03",
    "sg:postcode":"2930",
    "sg:province":"Antwerpen",
    "wof:name":"Van Hove V",
    "wof:placetype":"venue"
},
  "geometry": {"coordinates":[4.4451208115,51.2934417725],"type":"Point"}
}