{
  "type": "Feature",
  "properties": {
    "iso:country":"BE",
    "sg:address":"Rittenweg 23",
    "sg:city":"Opglabbeek",
    "sg:classifiers":[
        {
            "category":"Utilities",
            "subcategory":"Natural Gas",
            "type":"Services"
        }
    ],
    "sg:postcode":"3660",
    "sg:province":"Limburg",
    "sg:tags":[
        "welding"
    ],
    "wof:name":"Vandeurzen Jolanda Vof",
    "wof:placetype":"venue"
},
  "geometry": {"coordinates":[5.6126508713,51.0496101379],"type":"Point"}
}