{
  "type": "Feature",
  "properties": {
    "addr:full":"Ommegang Oost 39 Staden West-Vlaanderen 8840",
    "addr:housenumber":"39",
    "addr:postcode":"8840",
    "addr:street":"Ommegang Oost",
    "iso:country":"BE",
    "sg:address":"Ommegang Oost 39",
    "sg:city":"Staden",
    "sg:orig_category":"WAPENS AND MUNITIE",
    "sg:phone":"+32 51 77 90 06",
    "sg:postcode":"8840",
    "sg:province":"West-Vlaanderen",
    "wof:name":"Marc Devreker",
    "wof:placetype":"venue"
},
  "geometry": {"coordinates":[3.0142650604,50.9304046631],"type":"Point"}
}