{
  "type": "Feature",
  "properties": {
    "iso:country":"BE",
    "sg:address":"Tolpoortstraat 77",
    "sg:city":"Deinze",
    "sg:classifiers":[
        {
            "category":"Tea Room",
            "subcategory":"None",
            "type":"Food & Drink"
        }
    ],
    "sg:phone":"+32 9 380 17 04",
    "sg:postcode":"9800",
    "sg:province":"Oost-Vlaanderen",
    "wof:name":"Fox",
    "wof:placetype":"venue"
},
  "geometry": {"coordinates":[3.5296180248,50.9801559448],"type":"Point"}
}