{
  "type": "Feature",
  "properties": {
    "addr:full":"Meensesteenweg 387 Kortrijk West-Vlaanderen 8501",
    "addr:housenumber":"387",
    "addr:postcode":"8501",
    "addr:street":"Meensesteenweg",
    "iso:country":"BE",
    "sg:address":"Meensesteenweg 387",
    "sg:city":"Kortrijk",
    "sg:orig_category":"Banques and organismes de cr\u00e9dit",
    "sg:phone":"+32 56 35 28 12",
    "sg:postcode":"8501",
    "sg:province":"West-Vlaanderen",
    "wof:name":"Fortis",
    "wof:placetype":"venue"
},
  "geometry": {"coordinates":[3.2277040482,50.8236961365],"type":"Point"}
}