{
  "type": "Feature",
  "properties": {
    "iso:country":"BE",
    "sg:address":"Grote Steenweg 75",
    "sg:city":"Zoutleeuw (halle-booienhoven)",
    "sg:classifiers":[
        {
            "category":"Autos & Motor Vehicles",
            "subcategory":"Recreational Vehicle Sales",
            "type":"Retail Goods"
        }
    ],
    "sg:phone":"+32 11 78 45 18",
    "sg:postcode":"3440",
    "sg:province":"Vlaams-Brabant",
    "sg:tags":[
        "caravan",
        "accessory"
    ],
    "wof:name":"Lefever",
    "wof:placetype":"venue"
},
  "geometry": {"coordinates":[5.1040768623,50.8079109192],"type":"Point"}
}