{
  "type": "Feature",
  "properties": {
    "addr:full":"Langemunte 62 Lierde Oost-Vlaanderen 9570",
    "addr:housenumber":"62",
    "addr:postcode":"9570",
    "addr:street":"Langemunte",
    "iso:country":"BE",
    "sg:address":"Langemunte 62",
    "sg:city":"Lierde",
    "sg:orig_category":"Loodgieterij, verwarming and sanitaire installaties",
    "sg:phone":"+32 55 42 54 51",
    "sg:postcode":"9570",
    "sg:province":"Oost-Vlaanderen",
    "wof:name":"Kurt Van Der Heyden",
    "wof:placetype":"venue"
},
  "geometry": {"coordinates":[3.8461771011,50.8108062744],"type":"Point"}
}