{
  "type": "Feature",
  "properties": {
    "addr:full":"Gravenstraat 26 Holsbeek (kortrijk-dutsel) Vlaams-Brabant 3220",
    "addr:housenumber":"26",
    "addr:postcode":"3220",
    "addr:street":"Gravenstraat",
    "iso:country":"BE",
    "sg:address":"Gravenstraat 26",
    "sg:city":"Holsbeek (kortrijk-dutsel)",
    "sg:classifiers":[
        {
            "category":"Home & Garden",
            "subcategory":"Building Materials",
            "type":"Retail Goods"
        }
    ],
    "sg:phone":"+32 16 62 14 84",
    "sg:postcode":"3220",
    "sg:province":"Vlaams-Brabant",
    "sg:tags":[
        "article",
        "-",
        "do-it-yourself"
    ],
    "wof:name":"Smets Home & Garden/ Super Do-it",
    "wof:placetype":"venue"
},
  "geometry": {"coordinates":[4.8166399002,50.9314002991],"type":"Point"}
}