{
  "type": "Feature",
  "properties": {
    "addr:full":"Generaal Lemanlaan 180 Brugge (assebroek) West-Vlaanderen 8310",
    "addr:housenumber":"180",
    "addr:postcode":"8310",
    "addr:street":"Generaal Lemanlaan",
    "iso:country":"BE",
    "sg:address":"Generaal Lemanlaan 180",
    "sg:city":"Brugge (assebroek)",
    "sg:classifiers":[
        {
            "category":"Bars & Pubs",
            "type":"Food & Drink"
        }
    ],
    "sg:phone":"+32 50 27 01 55",
    "sg:postcode":"8310",
    "sg:province":"West-Vlaanderen",
    "wof:name":"Pepe's Poolbar",
    "wof:placetype":"venue"
},
  "geometry": {"coordinates":[3.243940115,51.2010116577],"type":"Point"}
}