{
  "type": "Feature",
  "properties": {
    "addr:full":"Rue De La For\u00cat 16 Marche-en-famenne Luxembourg 6900",
    "addr:housenumber":"16",
    "addr:postcode":"6900",
    "addr:street":"Rue De La Fore\u0302T",
    "iso:country":"BE",
    "sg:address":"Rue De La For\u00cat 16",
    "sg:city":"Marche-en-famenne",
    "sg:classifiers":[
        {
            "category":"Recreation",
            "type":"Entertainment"
        }
    ],
    "sg:phone":"+32 84 32 19 07",
    "sg:postcode":"6900",
    "sg:province":"Luxembourg",
    "sg:tags":[
        "diver",
        "amusement"
    ],
    "wof:name":"D.j. Dance Blue",
    "wof:placetype":"venue"
},
  "geometry": {"coordinates":[5.3759651184,50.2180938721],"type":"Point"}
}