{
  "type": "Feature",
  "properties": {
    "addr:full":"Vichtesteenweg 46 Deerlijk West-Vlaanderen 8540",
    "addr:housenumber":"46",
    "addr:postcode":"8540",
    "addr:street":"Vichtesteenweg",
    "iso:country":"BE",
    "sg:address":"Vichtesteenweg 46",
    "sg:city":"Deerlijk",
    "sg:orig_category":"Boucheries",
    "sg:phone":"+32 56 72 55 06",
    "sg:postcode":"8540",
    "sg:province":"West-Vlaanderen",
    "wof:name":"Renmans",
    "wof:placetype":"venue"
},
  "geometry": {"coordinates":[3.3620729446,50.8520088196],"type":"Point"}
}