{
  "type": "Feature",
  "properties": {
    "addr:full":"Kortevest 12 Halle Vlaams-Brabant 1500",
    "addr:housenumber":"12",
    "addr:postcode":"1500",
    "addr:street":"Kortevest",
    "iso:country":"BE",
    "sg:address":"Kortevest 12",
    "sg:city":"Halle",
    "sg:orig_category":"Activit\u00e9s d\u00b4action sociale sans h\u00e9bergement",
    "sg:phone":"+32 2 356 53 36",
    "sg:postcode":"1500",
    "sg:province":"Vlaams-Brabant",
    "wof:name":"Rode Kruis Halle",
    "wof:placetype":"venue"
},
  "geometry": {"coordinates":[4.2348718643,50.7346382141],"type":"Point"}
}