{
  "type": "Feature",
  "properties": {
    "addr:full":"Rue Fusch 24 Li\u00c8ge Li\u00e8ge 4000",
    "addr:housenumber":"24",
    "addr:postcode":"4000",
    "addr:street":"Rue Fusch",
    "iso:country":"BE",
    "sg:address":"Rue Fusch 24",
    "sg:city":"Li\u00c8ge",
    "sg:orig_category":"Artistes ind\u00e9pendants",
    "sg:phone":"+32 4 232 34 70",
    "sg:postcode":"4000",
    "sg:province":"Li\u00e8ge",
    "wof:name":"Andr\u00c9 Lenaerts",
    "wof:placetype":"venue"
},
  "geometry": {"coordinates":[5.5622038841,50.6358108521],"type":"Point"}
}