{
  "type": "Feature",
  "properties": {
    "addr:full":"Rue Th\u00c9odore Verhaegen 172 Sint-gillis/saint-gilles Bruxelles-Capitale 1060",
    "addr:housenumber":"172",
    "addr:postcode":"1060",
    "addr:street":"Rue The\u0301Odore Verhaegen",
    "iso:country":"BE",
    "sg:address":"Rue Th\u00c9odore Verhaegen 172",
    "sg:city":"Sint-gillis/saint-gilles",
    "sg:orig_category":"Plomberie, chauffage and installations sanitaires",
    "sg:phone":"+32 2 537 32 82",
    "sg:postcode":"1060",
    "sg:province":"Bruxelles-Capitale",
    "wof:name":"Polo Construct",
    "wof:placetype":"venue"
},
  "geometry": {"coordinates":[4.336368084,50.8304519653],"type":"Point"}
}