{
  "type": "Feature",
  "properties": {
    "iso:country":"BE",
    "sg:address":"Hoogstraat 17",
    "sg:city":"Oudenburg",
    "sg:classifiers":[
        {
            "category":"Organizations",
            "subcategory":"Community Association",
            "type":"Services"
        }
    ],
    "sg:phone":"+32 59 26 74 28",
    "sg:postcode":"8460",
    "sg:province":"West-Vlaanderen",
    "sg:tags":[
        "organisation"
    ],
    "wof:name":"Joc \u00b4t Scharnier",
    "wof:placetype":"venue"
},
  "geometry": {"coordinates":[3.0010209084,51.1822357178],"type":"Point"}
}