{
  "type": "Feature",
  "properties": {
    "iso:country":"BE",
    "sg:address":"Antwerpsesteenweg 145",
    "sg:city":"Mechelen",
    "sg:orig_category":"Technisch and beroeps secundair onderwijs",
    "sg:phone":"+32 15 20 14 93",
    "sg:postcode":"2800",
    "sg:province":"Antwerpen",
    "wof:name":"Prov. Inst. Tuinbouwond.",
    "wof:placetype":"venue"
},
  "geometry": {"coordinates":[4.4700379372,51.0433731079],"type":"Point"}
}