{
  "type": "Feature",
  "properties": {
    "addr:full":"Paddestraat 146ba Zottegem Oost-Vlaanderen 9620",
    "addr:postcode":"9620",
    "addr:street":"Paddestraat;Oost-Vlaanderen",
    "iso:country":"BE",
    "sg:address":"Paddestraat 146ba",
    "sg:city":"Zottegem",
    "sg:orig_category":"Eleveurs de bovins",
    "sg:phone":"+32 9 361 26 28",
    "sg:postcode":"9620",
    "sg:province":"Oost-Vlaanderen",
    "wof:name":"Lieven Galle",
    "wof:placetype":"venue"
},
  "geometry": {"coordinates":[3.7625210285,50.8752593994],"type":"Point"}
}