{
  "type": "Feature",
  "properties": {
    "iso:country":"BE",
    "sg:address":"Chemin De Casteau 49",
    "sg:city":"Jurbise",
    "sg:orig_category":"Agences de publicit\u00e9",
    "sg:phone":"+32 65 73 04 77",
    "sg:postcode":"7050",
    "sg:province":"Hainaut",
    "wof:name":"Bureau Surfline",
    "wof:placetype":"venue"
},
  "geometry": {"coordinates":[3.9697570801,50.5239524841],"type":"Point"}
}