{
  "type": "Feature",
  "properties": {
    "addr:full":"Brechtsebaan 700 Schoten Antwerpen 2900",
    "addr:housenumber":"700",
    "addr:postcode":"2900",
    "addr:street":"Brechtsebaan",
    "iso:country":"BE",
    "sg:address":"Brechtsebaan 700",
    "sg:city":"Schoten",
    "sg:classifiers":[
        {
            "category":"Home & Garden",
            "subcategory":"Carpets & Floor Coverings",
            "type":"Retail Goods"
        }
    ],
    "sg:phone":"+32 3 290 81 65",
    "sg:postcode":"2900",
    "sg:province":"Antwerpen",
    "sg:tags":[
        "-"
    ],
    "wof:name":"Schollaerts M",
    "wof:placetype":"venue"
},
  "geometry": {"coordinates":[4.5120401382,51.2662391663],"type":"Point"}
}