{
  "type": "Feature",
  "properties": {
    "addr:full":"Kruisvindingsstraat 62 Tongeren Limburg 3700",
    "addr:housenumber":"62",
    "addr:postcode":"3700",
    "addr:street":"Kruisvindingsstraat",
    "iso:country":"BE",
    "sg:address":"Kruisvindingsstraat 62",
    "sg:city":"Tongeren",
    "sg:orig_category":"Travaux de pl\u00e2trage",
    "sg:phone":"+32 12 23 98 83",
    "sg:postcode":"3700",
    "sg:province":"Limburg",
    "wof:name":"A.p.s.",
    "wof:placetype":"venue"
},
  "geometry": {"coordinates":[5.4636240005,50.7807197571],"type":"Point"}
}