{
  "type": "Feature",
  "properties": {
    "iso:country":"BE",
    "sg:address":"Schuttershofstraat 16",
    "sg:city":"Antwerpen",
    "sg:orig_category":"Pain, p\u00e2tisseries and confiseries",
    "sg:phone":"+32 3 226 36 91",
    "sg:postcode":"2000",
    "sg:province":"Antwerpen",
    "wof:name":"Huis Sweertvaegher",
    "wof:placetype":"venue"
},
  "geometry": {"coordinates":[4.4070549011,51.2163200378],"type":"Point"}
}