{
  "type": "Feature",
  "properties": {
    "addr:full":"Sint-guidostraat 36 Anderlecht Bruxelles-Capitale 1070",
    "addr:housenumber":"36",
    "addr:postcode":"1070",
    "addr:street":"Sint-Guidostraat",
    "iso:country":"BE",
    "sg:address":"Sint-guidostraat 36",
    "sg:city":"Anderlecht",
    "sg:classifiers":[
        {
            "category":"Fast Food",
            "type":"Food & Drink"
        }
    ],
    "sg:phone":"+32 2 522 53 48",
    "sg:postcode":"1070",
    "sg:province":"Bruxelles-Capitale",
    "sg:tags":[
        "meeneem",
        "restaurant"
    ],
    "wof:name":"Hoo Mei",
    "wof:placetype":"venue"
},
  "geometry": {"coordinates":[4.3042697906,50.8356285095],"type":"Point"}
}