{
  "type": "Feature",
  "properties": {
    "addr:full":"Oudebaan 79 Antwerpen Antwerpen 2610",
    "addr:housenumber":"79",
    "addr:postcode":"2610",
    "addr:street":"Oudebaan",
    "iso:country":"BE",
    "sg:address":"Oudebaan 79",
    "sg:city":"Antwerpen",
    "sg:orig_category":"Quincailleries",
    "sg:phone":"+32 3 821 03 92",
    "sg:postcode":"2610",
    "sg:province":"Antwerpen",
    "wof:name":"Districenter",
    "wof:placetype":"venue"
},
  "geometry": {"coordinates":[4.4209218025,51.2266654968],"type":"Point"}
}