{
  "type": "Feature",
  "properties": {
    "addr:full":"De Pont 18 Schilde Antwerpen 2970",
    "addr:housenumber":"18",
    "addr:postcode":"2970",
    "addr:street":"De Pont",
    "iso:country":"BE",
    "sg:address":"De Pont 18",
    "sg:city":"Schilde",
    "sg:classifiers":[
        {
            "category":"Health Services",
            "subcategory":"Health Practitioner",
            "type":"Services"
        }
    ],
    "sg:phone":"+32 3 383 32 54",
    "sg:postcode":"2970",
    "sg:province":"Antwerpen",
    "sg:tags":[
        "physiotherapist"
    ],
    "wof:name":"Maes Jeroen",
    "wof:placetype":"venue"
},
  "geometry": {"coordinates":[4.5740299225,51.2247047424],"type":"Point"}
}