{
  "type": "Feature",
  "properties": {
    "addr:full":"Chauss\u00c9e De Fleurus 237 Gilly Hainaut 6060",
    "addr:housenumber":"237",
    "addr:postcode":"6060",
    "addr:street":"Chausse\u0301E De Fleurus",
    "iso:country":"BE",
    "sg:address":"Chauss\u00c9e De Fleurus 237",
    "sg:city":"Gilly",
    "sg:classifiers":[
        {
            "category":"Restaurant",
            "type":"Food & Drink"
        }
    ],
    "sg:phone":"+32 71 41 20 95",
    "sg:postcode":"6060",
    "sg:province":"Hainaut",
    "wof:name":"All ' Osteria",
    "wof:placetype":"venue"
},
  "geometry": {"coordinates":[4.4879112244,50.4252738953],"type":"Point"}
}