{
  "type": "Feature",
  "properties": {
    "addr:full":"Sint-jozefslaan 92 Mol Antwerpen 2400",
    "addr:housenumber":"92",
    "addr:postcode":"2400",
    "addr:street":"Sint-Jozefslaan",
    "iso:country":"BE",
    "sg:address":"Sint-jozefslaan 92",
    "sg:city":"Mol",
    "sg:classifiers":[
        {
            "category":"Cafe",
            "type":"Food & Drink"
        }
    ],
    "sg:phone":"+32 14 81 25 31",
    "sg:postcode":"2400",
    "sg:province":"Antwerpen",
    "sg:tags":[
        "caf\u00e9s"
    ],
    "wof:name":"Caf\u00c9 Manhattan",
    "wof:placetype":"venue"
},
  "geometry": {"coordinates":[5.2258758545,51.1961517334],"type":"Point"}
}