{
  "type": "Feature",
  "properties": {
    "iso:country":"BE",
    "sg:address":"Sluisvaartstraat 70",
    "sg:city":"Middelkerke",
    "sg:classifiers":[
        {
            "category":"Ice Cream",
            "type":"Food & Drink"
        }
    ],
    "sg:phone":"+32 59 31 00 31",
    "sg:postcode":"8430",
    "sg:province":"West-Vlaanderen",
    "wof:name":"Iglo-ola Kustdepot Nv Mid-freeze",
    "wof:placetype":"venue"
},
  "geometry": {"coordinates":[2.8296461105,51.1918983459],"type":"Point"}
}