{
  "type": "Feature",
  "properties": {
    "iso:country":"BE",
    "sg:address":"Avenue Des Marronniers 26b2",
    "sg:city":"Beyne-heusay",
    "sg:orig_category":"Bagage and lederwaren Herstelling leer and schoeisel",
    "sg:phone":"+32 4 358 77 60",
    "sg:postcode":"4610",
    "sg:province":"Li\u00e8ge",
    "wof:name":"Francesco Lo Giudice",
    "wof:placetype":"venue"
},
  "geometry": {"coordinates":[5.6528968811,50.6206550598],"type":"Point"}
}