{
  "type": "Feature",
  "properties": {
    "addr:full":"Rue Du Couvent 1 Hensies Hainaut 7350",
    "addr:housenumber":"1",
    "addr:postcode":"7350",
    "addr:street":"Rue Du Couvent",
    "iso:country":"BE",
    "sg:address":"Rue Du Couvent 1",
    "sg:city":"Hensies",
    "sg:orig_category":"Enseignement maternel and primaire",
    "sg:phone":"+32 65 63 26 26",
    "sg:postcode":"7350",
    "sg:province":"Hainaut",
    "wof:name":"Ecole Primaire Libre",
    "wof:placetype":"venue"
},
  "geometry": {"coordinates":[3.7396299839,50.4298095703],"type":"Point"}
}