{
  "type": "Feature",
  "properties": {
    "addr:full":"De Dreef Van Duyvendael 20 Schilde (groot) Antwerpen 2970",
    "addr:housenumber":"20",
    "addr:postcode":"2970",
    "addr:street":"De Dreef Van Duyvendael;Groot Antwerpen",
    "iso:country":"BE",
    "sg:address":"De Dreef Van Duyvendael 20",
    "sg:city":"Schilde (groot)",
    "sg:orig_category":"Immobili\u00ebnkantoren",
    "sg:phone":"+32 3 685 44 70",
    "sg:postcode":"2970",
    "sg:province":"Antwerpen",
    "wof:name":"Antwerps Vastgoed",
    "wof:placetype":"venue"
},
  "geometry": {"coordinates":[4.5653090477,51.2528495789],"type":"Point"}
}