{
  "type": "Feature",
  "properties": {
    "iso:country":"BE",
    "sg:address":"Chauss\u00e9e De Forest 46",
    "sg:city":"Bruxelles (saint-gilles)",
    "sg:classifiers":[
        {
            "category":"Building & Trades",
            "subcategory":"Cleaning & Sanitation",
            "type":"Services"
        }
    ],
    "sg:phone":"+32 2 537 11 36",
    "sg:postcode":"1060",
    "sg:province":"Bruxelles-Capitale",
    "sg:tags":[
        "janitor"
    ],
    "wof:name":"Lef\u00e8vre Sa",
    "wof:placetype":"venue"
},
  "geometry": {"coordinates":[4.3410902023,50.8319702148],"type":"Point"}
}