{
  "type": "Feature",
  "properties": {
    "addr:full":"Heirbaan 12 Mortsel Antwerpen 2640",
    "addr:housenumber":"12",
    "addr:postcode":"2640",
    "addr:street":"Heirbaan",
    "iso:country":"BE",
    "sg:address":"Heirbaan 12",
    "sg:city":"Mortsel",
    "sg:classifiers":[
        {
            "category":"Professional",
            "subcategory":"Printing & Photocopies",
            "type":"Services"
        }
    ],
    "sg:phone":"+32 3 827 17 98",
    "sg:postcode":"2640",
    "sg:province":"Antwerpen",
    "sg:tags":[
        "job"
    ],
    "wof:name":"Baskerville Nv",
    "wof:placetype":"venue"
},
  "geometry": {"coordinates":[4.4166941643,51.1738777161],"type":"Point"}
}