{
  "type": "Feature",
  "properties": {
    "iso:country":"BE",
    "sg:address":"Burg.g.van Landeghemstraat 12",
    "sg:city":"Sint-gillis-waas",
    "sg:orig_category":"Beautyfarms, relaxatie and lichamelijk welzijn Schoonheidssalons",
    "sg:phone":"+32 3 770 70 94",
    "sg:postcode":"9170",
    "sg:province":"Oost-Vlaanderen",
    "wof:name":"V. Van Der Heyden",
    "wof:placetype":"venue"
},
  "geometry": {"coordinates":[4.1242260933,51.2165756226],"type":"Point"}
}