{
  "type": "Feature",
  "properties": {
    "addr:full":"Legen Heirweg 75 Gavere Oost-Vlaanderen 9890",
    "addr:housenumber":"75",
    "addr:postcode":"9890",
    "addr:street":"Legen Heirweg",
    "iso:country":"BE",
    "sg:address":"Legen Heirweg 75",
    "sg:city":"Gavere",
    "sg:classifiers":[
        {
            "category":"Real Estate",
            "subcategory":"Developer",
            "type":"Services"
        }
    ],
    "sg:phone":"+32 9 384 87 36",
    "sg:postcode":"9890",
    "sg:province":"Oost-Vlaanderen",
    "sg:tags":[
        "plomberie",
        "chauffage",
        "mat\u00e9riel",
        "gr",
        "pour"
    ],
    "wof:name":"Waterworld",
    "wof:placetype":"venue"
},
  "geometry": {"coordinates":[3.6468539238,50.934627533],"type":"Point"}
}