{
  "type": "Feature",
  "properties": {
    "iso:country":"BE",
    "sg:address":"Kehrweg 1",
    "sg:city":"Eupen",
    "sg:orig_category":"Beheer van reclamemedia Computers and computerapparatuur Diverse informatica-activiteiten Diverse op",
    "sg:phone":"+32 87 56 11 77",
    "sg:postcode":"4700",
    "sg:province":"Li\u00e8ge",
    "wof:name":"Euregio. Net/euregio-net 080",
    "wof:placetype":"venue"
},
  "geometry": {"coordinates":[6.0429520607,50.6270675659],"type":"Point"}
}