{
  "type": "Feature",
  "properties": {
    "iso:country":"BE",
    "sg:address":"Bogaardestraat 49",
    "sg:city":"Antwerpen",
    "sg:classifiers":[
        {
            "category":"Communications",
            "subcategory":"Film & Video Production",
            "type":"Services"
        }
    ],
    "sg:phone":"+32 3 213 25 75",
    "sg:postcode":"2000",
    "sg:province":"Antwerpen",
    "sg:tags":[
        "producer",
        "realizators"
    ],
    "wof:name":"Hamelynck & Perez Productions",
    "wof:placetype":"venue"
},
  "geometry": {"coordinates":[4.400080204,51.2142868042],"type":"Point"}
}