{
  "type": "Feature",
  "properties": {
    "iso:country":"BE",
    "sg:address":"Beekstraat 5",
    "sg:city":"Wortegem-petegem",
    "sg:orig_category":"Rundveehouders",
    "sg:phone":"+32 56 68 88 32",
    "sg:postcode":"9790",
    "sg:province":"Oost-Vlaanderen",
    "wof:name":"Frans Detavernier",
    "wof:placetype":"venue"
},
  "geometry": {"coordinates":[3.5084280968,50.8529052734],"type":"Point"}
}