{
  "type": "Feature",
  "properties": {
    "iso:country":"BE",
    "sg:address":"Rue De La Station 150",
    "sg:city":"Les Bons Villers",
    "sg:orig_category":"Slagers",
    "sg:phone":"+32 71 84 27 48",
    "sg:postcode":"6210",
    "sg:province":"Hainaut",
    "wof:name":"Eddy Degreve",
    "wof:placetype":"venue"
},
  "geometry": {"coordinates":[4.412979126,50.5519485474],"type":"Point"}
}