{
  "type": "Feature",
  "properties": {
    "iso:country":"BE",
    "sg:address":"Eekstraat 20",
    "sg:city":"Lokeren",
    "sg:classifiers":[
        {
            "category":"Insurance",
            "subcategory":"Insurance Agent",
            "type":"Services"
        }
    ],
    "sg:phone":"+32 9 348 61 61",
    "sg:postcode":"9160",
    "sg:province":"Oost-Vlaanderen",
    "sg:tags":[
        "verzekeringsmakelaars",
        "expert"
    ],
    "wof:name":"Bureau De Munck",
    "wof:placetype":"venue"
},
  "geometry": {"coordinates":[3.9777460098,51.1025085449],"type":"Point"}
}