{
  "type": "Feature",
  "properties": {
    "addr:full":"Statiestraat 38 Ternat Vlaams-Brabant 1740",
    "addr:housenumber":"38",
    "addr:postcode":"1740",
    "addr:street":"Statiestraat",
    "iso:country":"BE",
    "sg:address":"Statiestraat 38",
    "sg:city":"Ternat",
    "sg:orig_category":"Advocaten and juridische adviseurs",
    "sg:phone":"+32 2 532 16 18",
    "sg:postcode":"1740",
    "sg:province":"Vlaams-Brabant",
    "wof:name":"A. Vandam",
    "wof:placetype":"venue"
},
  "geometry": {"coordinates":[4.1747279167,50.8705825806],"type":"Point"}
}