{
  "type": "Feature",
  "properties": {
    "addr:full":"Blarenberglaan 21a Mechelen Antwerpen 2800",
    "addr:housenumber":"21a",
    "addr:postcode":"2800",
    "addr:street":"Blarenberglaan",
    "iso:country":"BE",
    "sg:address":"Blarenberglaan 21a",
    "sg:city":"Mechelen",
    "sg:classifiers":[
        {
            "category":"Professional",
            "subcategory":"Advertising",
            "type":"Services"
        }
    ],
    "sg:phone":"+32 15 20 20 95",
    "sg:postcode":"2800",
    "sg:province":"Antwerpen",
    "sg:tags":[
        "gift"
    ],
    "wof:name":"Rivanco B.v.b.a.",
    "wof:placetype":"venue"
},
  "geometry": {"coordinates":[4.4509840012,51.0521621704],"type":"Point"}
}