{
  "type": "Feature",
  "properties": {
    "addr:full":"Bruggestraat 31 Menen West-Vlaanderen 8930",
    "addr:housenumber":"31",
    "addr:postcode":"8930",
    "addr:street":"Bruggestraat",
    "iso:country":"BE",
    "sg:address":"Bruggestraat 31",
    "sg:city":"Menen",
    "sg:classifiers":[
        {
            "category":"Travel",
            "subcategory":"Travel Agent",
            "type":"Entertainment"
        }
    ],
    "sg:phone":"+32 56 51 76 70",
    "sg:postcode":"8930",
    "sg:province":"West-Vlaanderen",
    "sg:tags":[
        "agency"
    ],
    "wof:name":"Dehaene Reizen",
    "wof:placetype":"venue"
},
  "geometry": {"coordinates":[3.1221139431,50.7972297668],"type":"Point"}
}