{
  "type": "Feature",
  "properties": {
    "addr:full":"Kapelstraat 48 Wuustwezel Antwerpen 2990",
    "addr:housenumber":"48",
    "addr:postcode":"2990",
    "addr:street":"Kapelstraat",
    "iso:country":"BE",
    "sg:address":"Kapelstraat 48",
    "sg:city":"Wuustwezel",
    "sg:orig_category":"Dameskledingzaken",
    "sg:phone":"+32 3 669 71 61",
    "sg:postcode":"2990",
    "sg:province":"Antwerpen",
    "wof:name":"Boetiek Fabiola",
    "wof:placetype":"venue"
},
  "geometry": {"coordinates":[4.6470341682,51.4000244141],"type":"Point"}
}