{
  "type": "Feature",
  "properties": {
    "addr:full":"Brouwerijstraat 117 Elsene/ixelles Bruxelles-Capitale 1050",
    "addr:housenumber":"117",
    "addr:postcode":"1050",
    "addr:street":"Brouwerijstraat",
    "iso:country":"BE",
    "sg:address":"Brouwerijstraat 117",
    "sg:city":"Elsene/ixelles",
    "sg:orig_category":"Levering aan huis restaurants",
    "sg:phone":"+32 2 648 37 37",
    "sg:postcode":"1050",
    "sg:province":"Bruxelles-Capitale",
    "wof:name":"Pizzaphone",
    "wof:placetype":"venue"
},
  "geometry": {"coordinates":[4.3741140366,50.8278846741],"type":"Point"}
}