{
  "type": "Feature",
  "properties": {
    "iso:country":"BE",
    "sg:address":"Maexhofweg 20",
    "sg:city":"Zonhoven",
    "sg:classifiers":[
        {
            "category":"Health Services",
            "subcategory":"Dentist",
            "type":"Services"
        }
    ],
    "sg:phone":"+32 11 82 26 50",
    "sg:postcode":"3520",
    "sg:province":"Limburg",
    "sg:tags":[
        "dental",
        "clinic"
    ],
    "wof:name":"Surgical Dental Services Bvba",
    "wof:placetype":"venue"
},
  "geometry": {"coordinates":[5.3922510147,50.9891548157],"type":"Point"}
}