{
  "type": "Feature",
  "properties": {
    "addr:full":"Stadsestraat 17 Olen Antwerpen 2250",
    "addr:housenumber":"17",
    "addr:postcode":"2250",
    "addr:street":"Stadsestraat",
    "iso:country":"BE",
    "sg:address":"Stadsestraat 17",
    "sg:city":"Olen",
    "sg:classifiers":[
        {
            "category":"Shopping",
            "subcategory":"Bicycles & Sporting Goods",
            "type":"Retail Goods"
        }
    ],
    "sg:phone":"+32 14 26 32 41",
    "sg:postcode":"2250",
    "sg:province":"Antwerpen",
    "wof:name":"Norta Nv",
    "wof:placetype":"venue"
},
  "geometry": {"coordinates":[4.8552880287,51.1494903564],"type":"Point"}
}