{
  "type": "Feature",
  "properties": {
    "iso:country":"BE",
    "sg:address":"Rue Henri Grenier 22",
    "sg:city":"Orp-jauche (orp-le-grand)",
    "sg:orig_category":"Non-Classified Establishments",
    "sg:phone":"+32 19 51 68 58",
    "sg:postcode":"1350",
    "sg:province":"Brabant Wallon",
    "wof:name":"Bbap Sprl M\u00e9dical Distribution",
    "wof:placetype":"venue"
},
  "geometry": {"coordinates":[4.9837789536,50.6927566528],"type":"Point"}
}