{
  "type": "Feature",
  "properties": {
    "iso:country":"BE",
    "sg:address":"Celestijnenlaan 35b11",
    "sg:city":"Leuven",
    "sg:orig_category":"M\u00e9decins and sp\u00e9cialistes",
    "sg:phone":"+32 16 22 33 94",
    "sg:postcode":"3001",
    "sg:province":"Vlaams-Brabant",
    "wof:name":"F. Vanstapel",
    "wof:placetype":"venue"
},
  "geometry": {"coordinates":[4.6759839058,50.8706626892],"type":"Point"}
}