{
  "type": "Feature",
  "properties": {
    "addr:full":"March\u00c9 Aux Chevaux 2 Jodoigne Brabant Wallon 1370",
    "addr:housenumber":"2",
    "addr:postcode":"1370",
    "addr:street":"Aux Chevaux",
    "iso:country":"BE",
    "sg:address":"March\u00c9 Aux Chevaux 2",
    "sg:city":"Jodoigne",
    "sg:classifiers":[
        {
            "category":"Health Services",
            "subcategory":"Nursing And Care Facility",
            "type":"Services"
        }
    ],
    "sg:phone":"+32 10 81 99 29",
    "sg:postcode":"1370",
    "sg:province":"Brabant Wallon",
    "sg:tags":[
        "public"
    ],
    "wof:name":"C.p.a.s.",
    "wof:placetype":"venue"
},
  "geometry": {"coordinates":[4.8686351776,50.725528717],"type":"Point"}
}