{
  "type": "Feature",
  "properties": {
    "addr:full":"Chauss\u00e9e De Gand 141 Bruxelles (molenbeek-saint-jean) Bruxelles-Capitale 1080",
    "addr:housenumber":"141",
    "addr:postcode":"1080",
    "addr:street":"Chausse\u0301E De Gand",
    "iso:country":"BE",
    "sg:address":"Chauss\u00e9e De Gand 141",
    "sg:city":"Bruxelles (molenbeek-saint-jean)",
    "sg:classifiers":[
        {
            "category":"Home & Garden",
            "subcategory":"Home Furnishings",
            "type":"Retail Goods"
        }
    ],
    "sg:phone":"+32 2 411 31 63",
    "sg:postcode":"1080",
    "sg:province":"Bruxelles-Capitale",
    "sg:tags":[
        "-",
        "furniture"
    ],
    "wof:name":"Delmoiti\u00e9 Fr\u00e8res & Fils",
    "wof:placetype":"venue"
},
  "geometry": {"coordinates":[4.3353390694,50.8559303284],"type":"Point"}
}