{
  "type": "Feature",
  "properties": {
    "iso:country":"BE",
    "sg:address":"Brusselstraat 242",
    "sg:city":"Dilbeek",
    "sg:orig_category":"Boucheries",
    "sg:phone":"+32 2 466 27 61",
    "sg:postcode":"1702",
    "sg:province":"Vlaams-Brabant",
    "wof:name":"Michael De Ridder",
    "wof:placetype":"venue"
},
  "geometry": {"coordinates":[4.2638077736,50.8713111877],"type":"Point"}
}