{
  "type": "Feature",
  "properties": {
    "addr:full":"Budastraat 30 Kortrijk West-Vlaanderen 8500",
    "addr:housenumber":"30",
    "addr:postcode":"8500",
    "addr:street":"Budastraat",
    "iso:country":"BE",
    "sg:address":"Budastraat 30",
    "sg:city":"Kortrijk",
    "sg:orig_category":"Cr\u00e8ches and garderies d'enfants",
    "sg:phone":"+32 56 22 01 51",
    "sg:postcode":"8500",
    "sg:province":"West-Vlaanderen",
    "wof:name":"Kinderresidentie H. Hart",
    "wof:placetype":"venue"
},
  "geometry": {"coordinates":[3.2634210587,50.8306541443],"type":"Point"}
}