{
  "type": "Feature",
  "properties": {
    "iso:country":"BE",
    "sg:address":"Kempenhof 38",
    "sg:city":"Hasselt",
    "sg:classifiers":[
        {
            "category":"Professional",
            "subcategory":"Accounting & Tax Preparation",
            "type":"Services"
        }
    ],
    "sg:phone":"+32 11 21 05 57",
    "sg:postcode":"3500",
    "sg:province":"Limburg",
    "sg:tags":[
        "bookkeeper"
    ],
    "wof:name":"Feytongs F",
    "wof:placetype":"venue"
},
  "geometry": {"coordinates":[5.3445129395,50.949596405],"type":"Point"}
}