{
  "type": "Feature",
  "properties": {
    "addr:full":"Geitestraat 86 Izegem West-Vlaanderen 8870",
    "addr:housenumber":"86",
    "addr:postcode":"8870",
    "addr:street":"Geitestraat",
    "iso:country":"BE",
    "sg:address":"Geitestraat 86",
    "sg:city":"Izegem",
    "sg:orig_category":"Woningbouw",
    "sg:phone":"+32 51 30 72 26",
    "sg:postcode":"8870",
    "sg:province":"West-Vlaanderen",
    "wof:name":"Hendrik Ghilgemijn",
    "wof:placetype":"venue"
},
  "geometry": {"coordinates":[3.1859989166,50.8970680237],"type":"Point"}
}