{
  "type": "Feature",
  "properties": {
    "addr:full":"Europark Zuid 7b Sint-niklaas Oost-Vlaanderen 9100",
    "addr:housenumber":"7b",
    "addr:postcode":"9100",
    "addr:street":"Europark Zuid",
    "iso:country":"BE",
    "sg:address":"Europark Zuid 7b",
    "sg:city":"Sint-niklaas",
    "sg:classifiers":[
        {
            "category":"Building & Trades",
            "subcategory":"Construction",
            "type":"Services"
        }
    ],
    "sg:phone":"+32 3 776 15 65",
    "sg:postcode":"9100",
    "sg:province":"Oost-Vlaanderen",
    "sg:tags":[
        "glazier"
    ],
    "wof:name":"Dresselaers & Zoon",
    "wof:placetype":"venue"
},
  "geometry": {"coordinates":[4.1709680557,51.1608200073],"type":"Point"}
}