{
  "type": "Feature",
  "properties": {
    "addr:full":"Kortrijkstraat 81b1 Tielt West-Vlaanderen 8700",
    "addr:housenumber":"81b1",
    "addr:postcode":"8700",
    "addr:street":"Kortrijkstraat",
    "iso:country":"BE",
    "sg:address":"Kortrijkstraat 81b1",
    "sg:city":"Tielt",
    "sg:orig_category":"Diverse kredietdiensten",
    "sg:postcode":"8700",
    "sg:province":"West-Vlaanderen",
    "wof:name":"Bancontact-mister Cash",
    "wof:placetype":"venue"
},
  "geometry": {"coordinates":[3.3257260323,50.9967079163],"type":"Point"}
}