{
  "type": "Feature",
  "properties": {
    "addr:full":"Hoogstraat 101 Deerlijk West-Vlaanderen 8540",
    "addr:housenumber":"101",
    "addr:postcode":"8540",
    "addr:street":"Hoogstraat",
    "iso:country":"BE",
    "sg:address":"Hoogstraat 101",
    "sg:city":"Deerlijk",
    "sg:orig_category":"Verlichting and huishoudartikelen",
    "sg:phone":"+32 56 71 05 34",
    "sg:postcode":"8540",
    "sg:province":"West-Vlaanderen",
    "wof:name":"Ygrek",
    "wof:placetype":"venue"
},
  "geometry": {"coordinates":[3.3528769016,50.8535003662],"type":"Point"}
}