{
  "type": "Feature",
  "properties": {
    "iso:country":"BE",
    "sg:address":"Chauss\u00e9e De Bruxelles 321",
    "sg:city":"Waterloo",
    "sg:classifiers":[
        {
            "category":"Arts & Performance",
            "subcategory":"Arts Center",
            "type":"Entertainment"
        }
    ],
    "sg:phone":"+32 2 352 07 40",
    "sg:postcode":"1410",
    "sg:province":"Brabant Wallon",
    "sg:tags":[
        "inspection",
        "automobile",
        "-",
        "examination"
    ],
    "wof:name":"Cta Sa Station D'inspection",
    "wof:placetype":"venue"
},
  "geometry": {"coordinates":[4.401889801,50.7059364319],"type":"Point"}
}