{
  "type": "Feature",
  "properties": {
    "iso:country":"BE",
    "sg:address":"Zeeptstraat 53",
    "sg:city":"Keerbergen",
    "sg:classifiers":[
        {
            "category":"Professional",
            "subcategory":"Management & Consulting",
            "type":"Services"
        }
    ],
    "sg:phone":"+32 15 51 65 52",
    "sg:postcode":"3140",
    "sg:province":"Vlaams-Brabant",
    "sg:tags":[
        "consultant"
    ],
    "wof:name":"Eom Consulting Bvba",
    "wof:placetype":"venue"
},
  "geometry": {"coordinates":[4.6040377617,50.9965667725],"type":"Point"}
}