{
  "type": "Feature",
  "properties": {
    "addr:full":"Jasmijnstraat 10 Ninove Oost-Vlaanderen 9400",
    "addr:housenumber":"10",
    "addr:postcode":"9400",
    "addr:street":"Jasmijnstraat",
    "iso:country":"BE",
    "sg:address":"Jasmijnstraat 10",
    "sg:city":"Ninove",
    "sg:orig_category":"Gespecialiseerde residenti\u00eble bouw",
    "sg:phone":"+32 54 33 17 70",
    "sg:postcode":"9400",
    "sg:province":"Oost-Vlaanderen",
    "wof:name":"Berloo Eric En Zoon",
    "wof:placetype":"venue"
},
  "geometry": {"coordinates":[4.0255270004,50.843952179],"type":"Point"}
}