{
  "type": "Feature",
  "properties": {
    "addr:full":"Rue Croix De Pierre 2 Braine-l\u00b4alleud Brabant Wallon 1428",
    "addr:housenumber":"2",
    "addr:postcode":"1428",
    "addr:street":"Rue Croix De Pierre;Brabant Wallon",
    "iso:country":"BE",
    "sg:address":"Rue Croix De Pierre 2",
    "sg:city":"Braine-l\u00b4alleud",
    "sg:orig_category":"Production de films, t\u00e9l\u00e9films and vid\u00e9os",
    "sg:phone":"+32 2 384 76 92",
    "sg:postcode":"1428",
    "sg:province":"Brabant Wallon",
    "wof:name":"Xavier Lechanteur",
    "wof:placetype":"venue"
},
  "geometry": {"coordinates":[4.357711792,50.6413383484],"type":"Point"}
}