{
  "type": "Feature",
  "properties": {
    "iso:country":"BE",
    "sg:address":"Oude Straat 119",
    "sg:city":"Aartselaar",
    "sg:orig_category":"Computers Fab Computers and computerapparatuur Informaticaconsulenten Microsoft",
    "sg:phone":"+32 3 877 29 22",
    "sg:postcode":"2630",
    "sg:province":"Antwerpen",
    "wof:name":"Interact",
    "wof:placetype":"venue"
},
  "geometry": {"coordinates":[4.388862133,51.144443512],"type":"Point"}
}