{
  "type": "Feature",
  "properties": {
    "iso:country":"BE",
    "sg:address":"Chauss\u00e9e De Lodelinsart 57",
    "sg:city":"Charleroi (gilly)",
    "sg:classifiers":[
        {
            "category":"Shopping",
            "subcategory":"Beauty & Cosmetics",
            "type":"Retail Goods"
        }
    ],
    "sg:phone":"+32 71 41 38 76",
    "sg:postcode":"6060",
    "sg:province":"Hainaut",
    "sg:tags":[
        "-",
        "perfumery"
    ],
    "wof:name":"Beauty Femina Sprl",
    "wof:placetype":"venue"
},
  "geometry": {"coordinates":[4.4880981445,50.4251937866],"type":"Point"}
}