{
  "type": "Feature",
  "properties": {
    "addr:full":"Statiestraat 118b Zulte Oost-Vlaanderen 9870",
    "addr:housenumber":"118b",
    "addr:postcode":"9870",
    "addr:street":"Statiestraat",
    "iso:country":"BE",
    "sg:address":"Statiestraat 118b",
    "sg:city":"Zulte",
    "sg:orig_category":"Woningbouw",
    "sg:phone":"+32 9 388 72 42",
    "sg:postcode":"9870",
    "sg:province":"Oost-Vlaanderen",
    "wof:name":"Brepal",
    "wof:placetype":"venue"
},
  "geometry": {"coordinates":[3.4471449852,50.9150733948],"type":"Point"}
}