{
  "type": "Feature",
  "properties": {
    "iso:country":"BE",
    "sg:address":"Sollevelden 26",
    "sg:city":"Berlaar",
    "sg:orig_category":"Artsen and specialisten",
    "sg:phone":"+32 3 482 17 37",
    "sg:postcode":"2590",
    "sg:province":"Antwerpen",
    "wof:name":"Anne Luyten",
    "wof:placetype":"venue"
},
  "geometry": {"coordinates":[4.6617479324,51.1177177429],"type":"Point"}
}