{
  "type": "Feature",
  "properties": {
    "iso:country":"BE",
    "sg:address":"Hogelaanstraat 15a",
    "sg:city":"Lichtervelde",
    "sg:classifiers":[
        {
            "category":"Building & Trades",
            "subcategory":"Construction",
            "type":"Services"
        }
    ],
    "sg:phone":"+32 50 21 23 62",
    "sg:postcode":"8810",
    "sg:province":"West-Vlaanderen",
    "sg:tags":[
        "carpenter"
    ],
    "wof:name":"Geert Vanbelle Bvba",
    "wof:placetype":"venue"
},
  "geometry": {"coordinates":[3.1409499645,51.0631637573],"type":"Point"}
}