{
  "type": "Feature",
  "properties": {
    "addr:full":"Avenue Charles-quint 225 Ganshoren/ganshoren Bruxelles-Capitale 1083",
    "addr:housenumber":"225",
    "addr:postcode":"1083",
    "addr:street":"Avenue Charles-Quint",
    "iso:country":"BE",
    "sg:address":"Avenue Charles-quint 225",
    "sg:city":"Ganshoren/ganshoren",
    "sg:orig_category":"Installation \u00e9lectrique r\u00e9sidentielle",
    "sg:phone":"+32 2 465 55 83",
    "sg:postcode":"1083",
    "sg:province":"Bruxelles-Capitale",
    "wof:name":"Magic-elec",
    "wof:placetype":"venue"
},
  "geometry": {"coordinates":[4.3062710762,50.8699913025],"type":"Point"}
}