{
  "type": "Feature",
  "properties": {
    "addr:full":"Klokkeput 3 Harelbeke West-Vlaanderen 8530",
    "addr:housenumber":"3",
    "addr:postcode":"8530",
    "addr:street":"Klokkeput",
    "iso:country":"BE",
    "sg:address":"Klokkeput 3",
    "sg:city":"Harelbeke",
    "sg:classifiers":[
        {
            "category":"Cafe",
            "type":"Food & Drink"
        }
    ],
    "sg:phone":"+32 56 22 55 84",
    "sg:postcode":"8530",
    "sg:province":"West-Vlaanderen",
    "sg:tags":[
        "caf\u00e9s"
    ],
    "wof:name":"Marcel Blondelle",
    "wof:placetype":"venue"
},
  "geometry": {"coordinates":[3.3151900768,50.8356590271],"type":"Point"}
}