{
  "type": "Feature",
  "properties": {
    "addr:full":"Grote Markt 15 Ronse/renaix Oost-Vlaanderen 9600",
    "addr:housenumber":"15",
    "addr:postcode":"9600",
    "addr:street":"Grote Markt",
    "iso:country":"BE",
    "sg:address":"Grote Markt 15",
    "sg:city":"Ronse/renaix",
    "sg:orig_category":"Werk and personeelsselectie",
    "sg:phone":"+32 55 23 53 11",
    "sg:postcode":"9600",
    "sg:province":"Oost-Vlaanderen",
    "wof:name":"Career Consult Securex",
    "wof:placetype":"venue"
},
  "geometry": {"coordinates":[3.6012349129,50.7473335266],"type":"Point"}
}