{
  "type": "Feature",
  "properties": {
    "iso:country":"BE",
    "sg:address":"Katelijnevest 15",
    "sg:city":"Brugge",
    "sg:classifiers":[
        {
            "category":"Social Services",
            "type":"Services"
        }
    ],
    "sg:phone":"+32 50 44 37 80",
    "sg:postcode":"8000",
    "sg:province":"West-Vlaanderen",
    "wof:name":"Crisisopvangcentrum",
    "wof:placetype":"venue"
},
  "geometry": {"coordinates":[3.2271258831,51.1992454529],"type":"Point"}
}