{
  "type": "Feature",
  "properties": {
    "addr:full":"Terhagelaan 20 Wommelgem Antwerpen 2160",
    "addr:housenumber":"20",
    "addr:postcode":"2160",
    "addr:street":"Terhagelaan",
    "iso:country":"BE",
    "sg:address":"Terhagelaan 20",
    "sg:city":"Wommelgem",
    "sg:orig_category":"Artsen and specialisten",
    "sg:phone":"+32 3 352 92 56",
    "sg:postcode":"2160",
    "sg:province":"Antwerpen",
    "wof:name":"C. Van De Put",
    "wof:placetype":"venue"
},
  "geometry": {"coordinates":[4.5296969414,51.2007865906],"type":"Point"}
}