{
  "type": "Feature",
  "properties": {
    "addr:full":"Steenstraat 41 Kortemark West-Vlaanderen 8610",
    "addr:housenumber":"41",
    "addr:postcode":"8610",
    "addr:street":"Steenstraat",
    "iso:country":"BE",
    "sg:address":"Steenstraat 41",
    "sg:city":"Kortemark",
    "sg:classifiers":[
        {
            "category":"Autos & Motor Vehicles",
            "subcategory":"Fuel & Gas Station",
            "type":"Retail Goods"
        }
    ],
    "sg:phone":"+32 51 56 73 44",
    "sg:postcode":"8610",
    "sg:province":"West-Vlaanderen",
    "sg:tags":[
        "stations-service",
        "carburants"
    ],
    "wof:name":"Lutgarda Vandevyver",
    "wof:placetype":"venue"
},
  "geometry": {"coordinates":[2.9595429897,51.0322952271],"type":"Point"}
}