{
  "type": "Feature",
  "properties": {
    "addr:full":"Waterloose Steenweg 893 Ukkel/uccle Bruxelles-Capitale 1180",
    "addr:housenumber":"893",
    "addr:postcode":"1180",
    "addr:street":"Waterloose Steenweg;/",
    "iso:country":"BE",
    "sg:address":"Waterloose Steenweg 893",
    "sg:city":"Ukkel/uccle",
    "sg:orig_category":"Apotheken",
    "sg:phone":"+32 2 374 97 44",
    "sg:postcode":"1180",
    "sg:province":"Bruxelles-Capitale",
    "wof:name":"Claudine Manhay",
    "wof:placetype":"venue"
},
  "geometry": {"coordinates":[4.3702220917,50.8082885742],"type":"Point"}
}