{
  "type": "Feature",
  "properties": {
    "addr:full":"Avenue Marcel Tilquin 5 Rixensart Brabant Wallon 1330",
    "addr:housenumber":"5",
    "addr:postcode":"1330",
    "addr:street":"Avenue Marcel Tilquin;Wallon",
    "iso:country":"BE",
    "sg:address":"Avenue Marcel Tilquin 5",
    "sg:city":"Rixensart",
    "sg:orig_category":"Installatie van metalen schrijnwerk Verlichting and huishoudartikelen",
    "sg:phone":"+32 2 653 84 51",
    "sg:postcode":"1330",
    "sg:province":"Brabant Wallon",
    "wof:name":"Habitat Concept",
    "wof:placetype":"venue"
},
  "geometry": {"coordinates":[4.5312371254,50.7121162415],"type":"Point"}
}