{
  "type": "Feature",
  "properties": {
    "iso:country":"BE",
    "sg:address":"Wipstraat 7",
    "sg:city":"Kontich",
    "sg:orig_category":"Installation de menuiserie en bois and plastique. Equipement divers pour commerces Gr",
    "sg:phone":"+32 3 457 20 00",
    "sg:postcode":"2550",
    "sg:province":"Antwerpen",
    "wof:name":"Jos Cleys",
    "wof:placetype":"venue"
},
  "geometry": {"coordinates":[4.4556241035,51.1393280029],"type":"Point"}
}