{
  "type": "Feature",
  "properties": {
    "addr:full":"Oneux 42 Theux Li\u00e8ge 4910",
    "addr:housenumber":"42",
    "addr:postcode":"4910",
    "addr:street":"Oneux",
    "iso:country":"BE",
    "sg:address":"Oneux 42",
    "sg:city":"Theux",
    "sg:orig_category":"Installatie van houten of kunststof schrijnwerk Installatie van metalen schrijnwerk",
    "sg:phone":"+32 87 54 17 97",
    "sg:postcode":"4910",
    "sg:province":"Li\u00e8ge",
    "wof:name":"Joseph Knaust",
    "wof:placetype":"venue"
},
  "geometry": {"coordinates":[5.8672819138,50.5664100647],"type":"Point"}
}