{
  "type": "Feature",
  "properties": {
    "iso:country":"BE",
    "sg:address":"Bornestraat 7ba",
    "sg:city":"Leuven",
    "sg:orig_category":"Bagage and lederwaren Fab",
    "sg:phone":"+32 16 23 71 21",
    "sg:postcode":"3012",
    "sg:province":"Vlaams-Brabant",
    "wof:name":"Puelinckx H.",
    "wof:placetype":"venue"
},
  "geometry": {"coordinates":[4.6992812157,50.9034996033],"type":"Point"}
}