{
  "type": "Feature",
  "properties": {
    "iso:country":"BE",
    "sg:address":"Herentalsebaan 638",
    "sg:city":"Wommelgem",
    "sg:classifiers":[
        {
            "category":"Landmark",
            "subcategory":"Scenic View",
            "type":"Public Place"
        }
    ],
    "sg:phone":"+32 3 354 41 72",
    "sg:postcode":"2160",
    "sg:province":"Antwerpen",
    "sg:tags":[
        "setting",
        "photographic"
    ],
    "wof:name":"Rg Bvba",
    "wof:placetype":"venue"
},
  "geometry": {"coordinates":[4.5200238228,51.197845459],"type":"Point"}
}