{
  "type": "Feature",
  "properties": {
    "addr:full":"Schoendalestraat 312-314 Waregem (desselgem) West-Vlaanderen 8792",
    "addr:housenumber":"312-314",
    "addr:postcode":"8792",
    "addr:street":"Schoendalestraat",
    "iso:country":"BE",
    "sg:address":"Schoendalestraat 312-314",
    "sg:city":"Waregem (desselgem)",
    "sg:classifiers":[
        {
            "category":"Home & Garden",
            "subcategory":"Carpets & Floor Coverings",
            "type":"Retail Goods"
        }
    ],
    "sg:phone":"+32 56 71 98 49",
    "sg:postcode":"8792",
    "sg:province":"West-Vlaanderen",
    "sg:tags":[
        "industrial",
        "-"
    ],
    "wof:name":"Extra Beton Nv",
    "wof:placetype":"venue"
},
  "geometry": {"coordinates":[3.3749389648,50.8936042786],"type":"Point"}
}