{
  "type": "Feature",
  "properties": {
    "iso:country":"BE",
    "sg:address":"Avenue Du Pont De Luttre 9",
    "sg:city":"Vorst/forest",
    "sg:orig_category":"Installation de menuiserie en bois and plastique. Conception d'\u00e9talages and de showrooms. Meubles D\u00e9",
    "sg:phone":"+32 2 347 30 24",
    "sg:postcode":"1190",
    "sg:province":"Bruxelles-Capitale",
    "wof:name":"Vendredi",
    "wof:placetype":"venue"
},
  "geometry": {"coordinates":[4.3214631081,50.8206443787],"type":"Point"}
}