{
  "type": "Feature",
  "properties": {
    "iso:country":"BE",
    "sg:address":"Turnhoutsebaan 200",
    "sg:city":"Malle (oostmalle)",
    "sg:classifiers":[
        {
            "category":"Airport",
            "subcategory":"International",
            "type":"Transportation"
        }
    ],
    "sg:phone":"+32 3 311 55 27",
    "sg:postcode":"2390",
    "sg:province":"Antwerpen",
    "sg:tags":[
        "-",
        "transport"
    ],
    "wof:name":"Daritrans Nv",
    "wof:placetype":"venue"
},
  "geometry": {"coordinates":[4.7733001709,51.3016815186],"type":"Point"}
}