{
  "type": "Feature",
  "properties": {
    "addr:full":"Rue Neuve 19 Charleroi Hainaut 6061",
    "addr:housenumber":"19",
    "addr:postcode":"6061",
    "addr:street":"Rue Neuve;Hainaut",
    "iso:country":"BE",
    "sg:address":"Rue Neuve 19",
    "sg:city":"Charleroi",
    "sg:orig_category":"Boekhouders",
    "sg:phone":"+32 71 31 55 60",
    "sg:postcode":"6061",
    "sg:province":"Hainaut",
    "wof:name":"Marie-rose Baye",
    "wof:placetype":"venue"
},
  "geometry": {"coordinates":[4.4574270248,50.4107627869],"type":"Point"}
}