{
  "type": "Feature",
  "properties": {
    "addr:full":"Molenhuisstraat 36 Deinze (bachte-maria-leerne) Oost-Vlaanderen 9800",
    "addr:housenumber":"36",
    "addr:postcode":"9800",
    "addr:street":"Molenhuisstraat",
    "iso:country":"BE",
    "sg:address":"Molenhuisstraat 36",
    "sg:city":"Deinze (bachte-maria-leerne)",
    "sg:classifiers":[
        {
            "category":"Building & Trades",
            "subcategory":"Landscaping Services",
            "type":"Services"
        }
    ],
    "sg:phone":"+32 9 281 14 59",
    "sg:postcode":"9800",
    "sg:province":"Oost-Vlaanderen",
    "sg:tags":[
        "architect",
        "landscape"
    ],
    "wof:name":"Suda J",
    "wof:placetype":"venue"
},
  "geometry": {"coordinates":[3.5736870766,51.0163269043],"type":"Point"}
}