{
  "type": "Feature",
  "properties": {
    "addr:full":"Hoveniersstraat 20 Aalst Oost-Vlaanderen 9300",
    "addr:housenumber":"20",
    "addr:postcode":"9300",
    "addr:street":"Hoveniersstraat",
    "iso:country":"BE",
    "sg:address":"Hoveniersstraat 20",
    "sg:city":"Aalst",
    "sg:orig_category":"Supermarkten",
    "sg:phone":"+32 53 77 74 61",
    "sg:postcode":"9300",
    "sg:province":"Oost-Vlaanderen",
    "wof:name":"Gb Contact",
    "wof:placetype":"venue"
},
  "geometry": {"coordinates":[4.0457019806,50.9418716431],"type":"Point"}
}