{
  "type": "Feature",
  "properties": {
    "addr:full":"Nederkouter 9 Gent Oost-Vlaanderen 9000",
    "addr:housenumber":"9",
    "addr:postcode":"9000",
    "addr:street":"Nederkouter;Oost-Vlaanderen",
    "iso:country":"BE",
    "sg:address":"Nederkouter 9",
    "sg:city":"Gent",
    "sg:orig_category":"Epiceries",
    "sg:phone":"+32 9 225 97 37",
    "sg:postcode":"9000",
    "sg:province":"Oost-Vlaanderen",
    "wof:name":"\u00b4t Toemaatje",
    "wof:placetype":"venue"
},
  "geometry": {"coordinates":[3.7214291096,51.0486412048],"type":"Point"}
}