{
  "type": "Feature",
  "properties": {
    "addr:full":"Langedonkstr 3 Knesselare Oost-Vlaanderen 9910",
    "addr:housenumber":"3",
    "addr:postcode":"9910",
    "addr:street":"Langedonkstr;Oost-Vlaanderen",
    "iso:country":"BE",
    "sg:address":"Langedonkstr 3",
    "sg:city":"Knesselare",
    "sg:classifiers":[
        {
            "category":"Home & Garden",
            "subcategory":"Furniture",
            "type":"Retail Goods"
        }
    ],
    "sg:phone":"+32 9 374 14 09",
    "sg:postcode":"9910",
    "sg:province":"Oost-Vlaanderen",
    "sg:tags":[
        "household",
        "wood"
    ],
    "wof:name":"Stoellux Nv",
    "wof:placetype":"venue"
},
  "geometry": {"coordinates":[3.4014229774,51.1285133362],"type":"Point"}
}