{
  "type": "Feature",
  "properties": {
    "iso:country":"BE",
    "sg:address":"Rue Provinciale 3",
    "sg:city":"Celles",
    "sg:orig_category":"Eleveurs de bovins",
    "sg:phone":"+32 69 45 51 62",
    "sg:postcode":"7760",
    "sg:province":"Hainaut",
    "wof:name":"Albert Fraichefond",
    "wof:placetype":"venue"
},
  "geometry": {"coordinates":[3.4746260643,50.7044715881],"type":"Point"}
}