{
  "type": "Feature",
  "properties": {
    "addr:full":"Landsdijk 40 Assenede (bassevelde) Oost-Vlaanderen 9968",
    "addr:housenumber":"40",
    "addr:postcode":"9968",
    "addr:street":"Landsdijk",
    "iso:country":"BE",
    "sg:address":"Landsdijk 40",
    "sg:city":"Assenede (bassevelde)",
    "sg:classifiers":[
        {
            "category":"Building & Trades",
            "subcategory":"Construction",
            "type":"Services"
        }
    ],
    "sg:phone":"+32 9 373 71 28",
    "sg:postcode":"9968",
    "sg:province":"Oost-Vlaanderen",
    "sg:tags":[
        "carpenter"
    ],
    "wof:name":"Dmv Bouw Bvba",
    "wof:placetype":"venue"
},
  "geometry": {"coordinates":[3.6558148861,51.253200531],"type":"Point"}
}