{
  "type": "Feature",
  "properties": {
    "addr:full":"Avenue Saint-job 47 Wavre Brabant Wallon 1300",
    "addr:housenumber":"47;1300",
    "addr:street":"Avenue Saint-Job",
    "iso:country":"BE",
    "sg:address":"Avenue Saint-job 47",
    "sg:city":"Wavre",
    "sg:orig_category":"Installation de menuiserie en bois and plastique",
    "sg:phone":"+32 10 22 31 28",
    "sg:postcode":"1300",
    "sg:province":"Brabant Wallon",
    "wof:name":"Manuel Galea Saura",
    "wof:placetype":"venue"
},
  "geometry": {"coordinates":[4.6271982193,50.7203559875],"type":"Point"}
}