{
  "type": "Feature",
  "properties": {
    "iso:country":"BE",
    "sg:address":"Tentoonstellingslaan 370b41",
    "sg:city":"Jette",
    "sg:orig_category":"Serres and speciale beglazing",
    "sg:phone":"+32 2 479 24 36",
    "sg:postcode":"1090",
    "sg:province":"Bruxelles-Capitale",
    "wof:name":"Moreau",
    "wof:placetype":"venue"
},
  "geometry": {"coordinates":[4.3167362213,50.887172699],"type":"Point"}
}