{
  "type": "Feature",
  "properties": {
    "addr:full":"Avenue Jos\u00e9phine-charlotte 60 Rixensart Brabant Wallon 1330",
    "addr:housenumber":"60",
    "addr:postcode":"1330",
    "addr:street":"Avenue Jose\u0301Phine-Charlotte;Wallon",
    "iso:country":"BE",
    "sg:address":"Avenue Jos\u00e9phine-charlotte 60",
    "sg:city":"Rixensart",
    "sg:classifiers":[
        {
            "category":"Real Estate",
            "subcategory":"Architect",
            "type":"Services"
        }
    ],
    "sg:phone":"+32 2 653 45 95",
    "sg:postcode":"1330",
    "sg:province":"Brabant Wallon",
    "wof:name":"Stassen Y",
    "wof:placetype":"venue"
},
  "geometry": {"coordinates":[4.542798996,50.7067871094],"type":"Point"}
}