{
  "type": "Feature",
  "properties": {
    "addr:full":"Oude Wetterstraat 49 Wetteren Oost-Vlaanderen 9230",
    "addr:housenumber":"49",
    "addr:postcode":"9230",
    "addr:street":"Oude Wetterstraat",
    "iso:country":"BE",
    "sg:address":"Oude Wetterstraat 49",
    "sg:city":"Wetteren",
    "sg:classifiers":[
        {
            "category":"Retail",
            "subcategory":"Auto Repair",
            "type":"Services"
        }
    ],
    "sg:phone":"+32 9 369 45 54",
    "sg:postcode":"9230",
    "sg:province":"Oost-Vlaanderen",
    "sg:tags":[
        "garage"
    ],
    "wof:name":"V.d.s. Motors Nv",
    "wof:placetype":"venue"
},
  "geometry": {"coordinates":[3.8485610485,50.9875297546],"type":"Point"}
}