{
  "type": "Feature",
  "properties": {
    "iso:country":"BE",
    "sg:address":"Rue Du Buverniat 4",
    "sg:city":"Walcourt",
    "sg:orig_category":"M\u00e9decins and sp\u00e9cialistes. M\u00e9decines alternatives",
    "sg:phone":"+32 71 53 41 51",
    "sg:postcode":"5650",
    "sg:province":"Namur",
    "wof:name":"L\u00c9otard Nadine",
    "wof:placetype":"venue"
},
  "geometry": {"coordinates":[4.3233828545,50.2577323914],"type":"Point"}
}