{
  "type": "Feature",
  "properties": {
    "iso:country":"BE",
    "sg:address":"G. De Stuersstraat",
    "sg:city":"Ieper",
    "sg:orig_category":"Musea and historische gebouwen",
    "sg:phone":"+32 57 20 58 36",
    "sg:postcode":"8900",
    "sg:province":"West-Vlaanderen",
    "wof:name":"Stedelijk Onderwijsmuseum",
    "wof:placetype":"venue"
},
  "geometry": {"coordinates":[2.8782429695,50.8494186401],"type":"Point"}
}