{
  "type": "Feature",
  "properties": {
    "iso:country":"BE",
    "sg:address":"Av. De La Joyeuse Entree 13",
    "sg:city":"Mons",
    "sg:orig_category":"Restaurants Ruimtes voor conferenties, recepties and feesten",
    "sg:phone":"+32 65 34 07 34",
    "sg:postcode":"7020",
    "sg:province":"Hainaut",
    "wof:name":"Le Coral Grill",
    "wof:placetype":"venue"
},
  "geometry": {"coordinates":[3.9553449154,50.4761772156],"type":"Point"}
}