{
  "type": "Feature",
  "properties": {
    "addr:full":"Rue Hubert Halet 22 Pepinster Li\u00e8ge 4860",
    "addr:housenumber":"22",
    "addr:postcode":"4860",
    "addr:street":"Rue Hubert Halet",
    "iso:country":"BE",
    "sg:address":"Rue Hubert Halet 22",
    "sg:city":"Pepinster",
    "sg:classifiers":[
        {
            "category":"Cafe",
            "type":"Food & Drink"
        }
    ],
    "sg:phone":"+32 87 46 02 24",
    "sg:postcode":"4860",
    "sg:province":"Li\u00e8ge",
    "sg:tags":[
        "caf\u00e9s"
    ],
    "wof:name":"Mireille Voss",
    "wof:placetype":"venue"
},
  "geometry": {"coordinates":[5.8073921204,50.5700149536],"type":"Point"}
}