{
  "type": "Feature",
  "properties": {
    "iso:country":"BE",
    "sg:address":"Petite Rue 17",
    "sg:city":"Mouscron",
    "sg:classifiers":[
        {
            "category":"Shopping",
            "subcategory":"Clothing, Apparel, & Fashions",
            "type":"Retail Goods"
        }
    ],
    "sg:phone":"+32 56 33 32 86",
    "sg:postcode":"7700",
    "sg:province":"Hainaut",
    "sg:tags":[
        "lady",
        "clothing",
        "-"
    ],
    "wof:name":"Bo-wear",
    "wof:placetype":"venue"
},
  "geometry": {"coordinates":[3.2133998871,50.7440757751],"type":"Point"}
}