{
  "type": "Feature",
  "properties": {
    "addr:full":"Rue De Diekirch 62 Arlon Luxembourg 6700",
    "addr:housenumber":"62",
    "addr:postcode":"6700",
    "addr:street":"Rue De Diekirch",
    "iso:country":"BE",
    "sg:address":"Rue De Diekirch 62",
    "sg:city":"Arlon",
    "sg:orig_category":"Ambassades and consulats",
    "sg:phone":"+32 63 23 60 20",
    "sg:postcode":"6700",
    "sg:province":"Luxembourg",
    "wof:name":"Consulat De France",
    "wof:placetype":"venue"
},
  "geometry": {"coordinates":[5.8149991035,49.6861457825],"type":"Point"}
}