{
  "type": "Feature",
  "properties": {
    "addr:full":"Langestraat 156-115 Brugge West-Vlaanderen 8000",
    "addr:housenumber":"156-115",
    "addr:postcode":"8000",
    "addr:street":"Langestraat",
    "iso:country":"BE",
    "sg:address":"Langestraat 156-115",
    "sg:city":"Brugge",
    "sg:classifiers":[
        {
            "category":"Professional",
            "subcategory":"Art Services",
            "type":"Services"
        }
    ],
    "sg:phone":"+32 50 33 60 75",
    "sg:postcode":"8000",
    "sg:province":"West-Vlaanderen",
    "sg:tags":[
        "picture",
        "framer"
    ],
    "wof:name":"Noteboom Bvba",
    "wof:placetype":"venue"
},
  "geometry": {"coordinates":[3.2396669388,51.2124519348],"type":"Point"}
}