{
  "type": "Feature",
  "properties": {
    "addr:full":"Wulfhoek 10 Nevele Oost-Vlaanderen 9850",
    "addr:housenumber":"10",
    "addr:postcode":"9850",
    "addr:street":"Wulfhoek",
    "iso:country":"BE",
    "sg:address":"Wulfhoek 10",
    "sg:city":"Nevele",
    "sg:orig_category":"Eleveurs and marchands de porcs. Eleveurs de bovins. Producteurs de fruits",
    "sg:phone":"+32 9 371 62 58",
    "sg:postcode":"9850",
    "sg:province":"Oost-Vlaanderen",
    "wof:name":"Aurele De Vreese",
    "wof:placetype":"venue"
},
  "geometry": {"coordinates":[3.5522708893,51.052066803],"type":"Point"}
}