{
  "type": "Feature",
  "properties": {
    "addr:full":"Quai De Maestricht 6 Li\u00e8ge 1 Li\u00e8ge 4000",
    "addr:housenumber":"6;1",
    "addr:postcode":"4000",
    "addr:street":"Quai De Maestricht",
    "iso:country":"BE",
    "sg:address":"Quai De Maestricht 6",
    "sg:city":"Li\u00e8ge 1",
    "sg:classifiers":[
        {
            "category":"Home & Garden",
            "subcategory":"Furniture",
            "type":"Retail Goods"
        }
    ],
    "sg:phone":"+32 4 222 05 59",
    "sg:postcode":"4000",
    "sg:province":"Li\u00e8ge",
    "sg:tags":[
        "bamboo",
        "cane",
        "wickerwork"
    ],
    "wof:name":"Caroline",
    "wof:placetype":"venue"
},
  "geometry": {"coordinates":[5.5829949379,50.64686203],"type":"Point"}
}