{
  "type": "Feature",
  "properties": {
    "iso:country":"BE",
    "sg:address":"Avenue De Broqueville 32",
    "sg:city":"Bruxelles (woluwe-saint-lambert)",
    "sg:classifiers":[
        {
            "category":"Education",
            "subcategory":"Music School",
            "type":"Public Place"
        }
    ],
    "sg:phone":"+32 2 763 09 37",
    "sg:postcode":"1200",
    "sg:province":"Bruxelles-Capitale",
    "sg:tags":[
        "-",
        "teacher",
        "private"
    ],
    "wof:name":"Poss",
    "wof:placetype":"venue"
},
  "geometry": {"coordinates":[4.4102401733,50.8382453918],"type":"Point"}
}