{
  "type": "Feature",
  "properties": {
    "addr:full":"Avenue Wellington 3 Ukkel/uccle Bruxelles-Capitale 1180",
    "addr:housenumber":"3",
    "addr:postcode":"1180",
    "addr:street":"Avenue Wellington;/",
    "iso:country":"BE",
    "sg:address":"Avenue Wellington 3",
    "sg:city":"Ukkel/uccle",
    "sg:orig_category":"Agences immobili\u00e8res",
    "sg:phone":"+32 2 375 01 82",
    "sg:postcode":"1180",
    "sg:province":"Bruxelles-Capitale",
    "wof:name":"Pergal",
    "wof:placetype":"venue"
},
  "geometry": {"coordinates":[4.3701968193,50.7867164612],"type":"Point"}
}