{
  "type": "Feature",
  "properties": {
    "addr:full":"Tramstraat 27 Oosterzele Oost-Vlaanderen 9860",
    "addr:housenumber":"27",
    "addr:postcode":"9860",
    "addr:street":"Tramstraat;Oost-Vlaanderen",
    "iso:country":"BE",
    "sg:address":"Tramstraat 27",
    "sg:city":"Oosterzele",
    "sg:orig_category":"Artsen and specialisten",
    "sg:phone":"+32 9 362 73 14",
    "sg:postcode":"9860",
    "sg:province":"Oost-Vlaanderen",
    "wof:name":"S. Tanghe",
    "wof:placetype":"venue"
},
  "geometry": {"coordinates":[3.775001049,50.9553947449],"type":"Point"}
}