{
  "type": "Feature",
  "properties": {
    "iso:country":"BE",
    "sg:address":"Rue Emile No\u00cbl 54",
    "sg:city":"Couvin",
    "sg:orig_category":"Diverse bouwafwerking and reiniging Woningbouw",
    "sg:phone":"+32 60 34 54 70",
    "sg:postcode":"5660",
    "sg:province":"Namur",
    "wof:name":"Vincent Regnier",
    "wof:placetype":"venue"
},
  "geometry": {"coordinates":[4.420841217,50.032245636],"type":"Point"}
}