{
  "type": "Feature",
  "properties": {
    "addr:full":"Rue Du Parc 13 Manage Hainaut 7170",
    "addr:housenumber":"13",
    "addr:postcode":"7170",
    "addr:street":"Rue Du Parc",
    "iso:country":"BE",
    "sg:address":"Rue Du Parc 13",
    "sg:city":"Manage",
    "sg:orig_category":"V\u00e9t\u00e9rinaires",
    "sg:phone":"+32 64 28 04 94",
    "sg:postcode":"7170",
    "sg:province":"Hainaut",
    "wof:name":"Thierry Delvaux",
    "wof:placetype":"venue"
},
  "geometry": {"coordinates":[4.2333111763,50.4715690613],"type":"Point"}
}