{
  "type": "Feature",
  "properties": {
    "iso:country":"BE",
    "sg:address":"Klameerstraat 32",
    "sg:city":"Alken",
    "sg:orig_category":"Producteurs de fruits. Eleveurs de bovins",
    "sg:phone":"+32 11 31 29 51",
    "sg:postcode":"3570",
    "sg:province":"Limburg",
    "wof:name":"Jozef Martens",
    "wof:placetype":"venue"
},
  "geometry": {"coordinates":[5.3040938377,50.8623886108],"type":"Point"}
}