{
  "type": "Feature",
  "properties": {
    "iso:country":"BE",
    "sg:address":"O Verschuerestraat 40",
    "sg:city":"Waregem",
    "sg:orig_category":"Imprimeries and copyshops",
    "sg:phone":"+32 56 60 46 68",
    "sg:postcode":"8790",
    "sg:province":"West-Vlaanderen",
    "wof:name":"Copy-lux",
    "wof:placetype":"venue"
},
  "geometry": {"coordinates":[3.4292020798,50.8867759705],"type":"Point"}
}