{
  "type": "Feature",
  "properties": {
    "iso:country":"BE",
    "sg:address":"Rue Wattimez-haut 50",
    "sg:city":"Les Bons Villers",
    "sg:classifiers":[
        {
            "category":"Food & Beverages",
            "subcategory":"Fruits & Vegetables",
            "type":"Retail Goods"
        }
    ],
    "sg:phone":"+32 71 84 55 33",
    "sg:postcode":"6210",
    "sg:province":"Hainaut",
    "sg:tags":[
        "l\u00e9gumes"
    ],
    "wof:name":"Servi-culture",
    "wof:placetype":"venue"
},
  "geometry": {"coordinates":[4.484855175,50.5268325806],"type":"Point"}
}