{
  "type": "Feature",
  "properties": {
    "addr:full":"Rue Jean-d'outremeuse 23 Li\u00c8ge Li\u00e8ge 4020",
    "addr:housenumber":"23",
    "addr:postcode":"4020",
    "addr:street":"Rue Jean-D'Outremeuse",
    "iso:country":"BE",
    "sg:address":"Rue Jean-d'outremeuse 23",
    "sg:city":"Li\u00c8ge",
    "sg:orig_category":"Cr\u00e9meries. Restaurants",
    "sg:phone":"+32 4 343 99 32",
    "sg:postcode":"4020",
    "sg:province":"Li\u00e8ge",
    "wof:name":"Glacier Elisa",
    "wof:placetype":"venue"
},
  "geometry": {"coordinates":[5.5828461647,50.6393585205],"type":"Point"}
}