{
  "type": "Feature",
  "properties": {
    "addr:full":"Sportlaan 2 De Panne West-Vlaanderen 8660",
    "addr:housenumber":"2",
    "addr:postcode":"8660",
    "addr:street":"Sportlaan",
    "iso:country":"BE",
    "sg:address":"Sportlaan 2",
    "sg:city":"De Panne",
    "sg:orig_category":"Fitnesscentra Sportcentra Sportclubs Sportterreinen and installaties behalve sportcentra",
    "sg:phone":"+32 58 42 18 20",
    "sg:postcode":"8660",
    "sg:province":"West-Vlaanderen",
    "wof:name":"Gemeentelijk Sportcomplex",
    "wof:placetype":"venue"
},
  "geometry": {"coordinates":[2.6110880375,51.0931053162],"type":"Point"}
}