{
  "type": "Feature",
  "properties": {
    "addr:full":"Victor Braeckmanlaan 91-93 Gent (sint-amandsberg) Oost-Vlaanderen 9040",
    "addr:housenumber":"91-93",
    "addr:postcode":"9040",
    "addr:street":"Victor Braeckmanlaan",
    "iso:country":"BE",
    "sg:address":"Victor Braeckmanlaan 91-93",
    "sg:city":"Gent (sint-amandsberg)",
    "sg:classifiers":[
        {
            "category":"Professional",
            "subcategory":"Art Services",
            "type":"Services"
        }
    ],
    "sg:phone":"+32 9 228 90 01",
    "sg:postcode":"9040",
    "sg:province":"Oost-Vlaanderen",
    "sg:tags":[
        "interior",
        "designer"
    ],
    "wof:name":"Heads",
    "wof:placetype":"venue"
},
  "geometry": {"coordinates":[3.7526330948,51.0598602295],"type":"Point"}
}