{
  "type": "Feature",
  "properties": {
    "iso:country":"BE",
    "sg:address":"Grand-rue 72",
    "sg:city":"Mons",
    "sg:orig_category":"Journaux. Tabac",
    "sg:phone":"+32 65 35 36 57",
    "sg:postcode":"7000",
    "sg:province":"Hainaut",
    "wof:name":"Le Nouveau Point Du Jour",
    "wof:placetype":"venue"
},
  "geometry": {"coordinates":[3.949213028,50.450466156],"type":"Point"}
}