{
  "type": "Feature",
  "properties": {
    "addr:full":"Hugo Verrieststraat 46 Roeselare West-Vlaanderen 8800",
    "addr:housenumber":"46",
    "addr:postcode":"8800",
    "addr:street":"Hugo Verrieststraat",
    "iso:country":"BE",
    "sg:address":"Hugo Verrieststraat 46",
    "sg:city":"Roeselare",
    "sg:orig_category":"Kinderopvang",
    "sg:phone":"+32 51 24 02 36",
    "sg:postcode":"8800",
    "sg:province":"West-Vlaanderen",
    "wof:name":"'t Bolhoedje",
    "wof:placetype":"venue"
},
  "geometry": {"coordinates":[3.1242489815,50.9504165649],"type":"Point"}
}