{
  "type": "Feature",
  "properties": {
    "iso:country":"BE",
    "sg:address":"Koningin Astridplein 34",
    "sg:city":"Antwerpen",
    "sg:classifiers":[
        {
            "category":"Travel",
            "subcategory":"Hotels & Motels",
            "type":"Entertainment"
        }
    ],
    "sg:phone":"+32 3 225 00 93",
    "sg:postcode":"2018",
    "sg:province":"Antwerpen",
    "wof:name":"Monico",
    "wof:placetype":"venue"
},
  "geometry": {"coordinates":[4.4205980301,51.2177467346],"type":"Point"}
}