{
  "type": "Feature",
  "properties": {
    "iso:country":"BE",
    "sg:address":"Rue De La Chapelle 1",
    "sg:city":"Prouvy",
    "sg:classifiers":[
        {
            "category":"Structure",
            "subcategory":"Building",
            "type":"Public Place"
        }
    ],
    "sg:phone":"+32 61 32 92 24",
    "sg:postcode":"6810",
    "sg:province":"Luxembourg",
    "sg:tags":[
        "apartment"
    ],
    "wof:name":"L\u00e9on Homel Entreprises S.a.",
    "wof:placetype":"venue"
},
  "geometry": {"coordinates":[5.4372801781,49.6862792969],"type":"Point"}
}