{
  "type": "Feature",
  "properties": {
    "addr:full":"Fonteinstraat 75 Box 87 Leuven Vlaams-Brabant 3000",
    "addr:housenumber":"75 box 87",
    "addr:postcode":"3000",
    "addr:street":"Fonteinstraat",
    "iso:country":"BE",
    "sg:address":"Fonteinstraat 75 Box 87",
    "sg:city":"Leuven",
    "sg:classifiers":[
        {
            "category":"Professional",
            "subcategory":"Accounting & Tax Preparation",
            "type":"Services"
        }
    ],
    "sg:phone":"+32 16 50 35 22",
    "sg:postcode":"3000",
    "sg:province":"Vlaams-Brabant",
    "sg:tags":[
        "bookkeeper"
    ],
    "wof:name":"Goris K",
    "wof:placetype":"venue"
},
  "geometry": {"coordinates":[4.6937851906,50.8834609985],"type":"Point"}
}