{
  "type": "Feature",
  "properties": {
    "addr:full":"Bree\u00ebrsteenweg 348 Kinrooi Limburg 3640",
    "addr:housenumber":"348",
    "addr:postcode":"3640",
    "addr:street":"Breee\u0308Rsteenweg",
    "iso:country":"BE",
    "sg:address":"Bree\u00ebrsteenweg 348",
    "sg:city":"Kinrooi",
    "sg:classifiers":[
        {
            "category":"Home & Garden",
            "subcategory":"Kitchen Supply",
            "type":"Retail Goods"
        }
    ],
    "sg:phone":"+32 89 70 30 62",
    "sg:postcode":"3640",
    "sg:province":"Limburg",
    "sg:tags":[
        "installation"
    ],
    "wof:name":"Morgana",
    "wof:placetype":"venue"
},
  "geometry": {"coordinates":[5.7309007645,51.1457901001],"type":"Point"}
}