{
  "type": "Feature",
  "properties": {
    "iso:country":"BE",
    "sg:address":"Antwerpsesteenweg 64",
    "sg:city":"Hoboken",
    "sg:classifiers":[
        {
            "category":"Manufacturing",
            "subcategory":"Chemicals & Compounds",
            "type":"Manufacturing & Wholesale Goods"
        }
    ],
    "sg:phone":"+32 3 825 27 68",
    "sg:postcode":"2660",
    "sg:province":"Antwerpen",
    "sg:tags":[
        "pharmaceutical",
        "chemistry",
        "-",
        "by-product"
    ],
    "wof:name":"De Ruiter Decor Bvba",
    "wof:placetype":"venue"
},
  "geometry": {"coordinates":[4.3543319702,51.1779785156],"type":"Point"}
}