{
  "type": "Feature",
  "properties": {
    "addr:full":"Gebroeders Naudtslaan 12 Wachtebeke Oost-Vlaanderen 9185",
    "addr:housenumber":"12",
    "addr:postcode":"9185",
    "addr:street":"Gebroeders Naudtslaan",
    "iso:country":"BE",
    "sg:address":"Gebroeders Naudtslaan 12",
    "sg:city":"Wachtebeke",
    "sg:classifiers":[
        {
            "category":"Shopping",
            "subcategory":"Discount & Variety Stores",
            "type":"Retail Goods"
        }
    ],
    "sg:phone":"+32 9 345 75 33",
    "sg:postcode":"9185",
    "sg:province":"Oost-Vlaanderen",
    "sg:tags":[
        "warehouse",
        "-",
        "merchandise"
    ],
    "wof:name":"Flandid Nv",
    "wof:placetype":"venue"
},
  "geometry": {"coordinates":[3.8340420723,51.1922035217],"type":"Point"}
}