{
  "type": "Feature",
  "properties": {
    "addr:full":"Bruynstraat 200 Brussel/bruxelles Bruxelles-Capitale 1120",
    "addr:housenumber":"200",
    "addr:postcode":"1120",
    "addr:street":"Bruynstraat;/",
    "iso:country":"BE",
    "sg:address":"Bruynstraat 200",
    "sg:city":"Brussel/bruxelles",
    "sg:orig_category":"Artsen and specialisten",
    "sg:phone":"+32 2 264 44 67",
    "sg:postcode":"1120",
    "sg:province":"Bruxelles-Capitale",
    "wof:name":"Philippe Huysegoms",
    "wof:placetype":"venue"
},
  "geometry": {"coordinates":[4.3866701126,50.9033203125],"type":"Point"}
}