{
  "type": "Feature",
  "properties": {
    "addr:full":"Rijsseveldstraat 53 Staden West-Vlaanderen 8840",
    "addr:housenumber":"53",
    "addr:postcode":"8840",
    "addr:street":"Rijsseveldstraat",
    "iso:country":"BE",
    "sg:address":"Rijsseveldstraat 53",
    "sg:city":"Staden",
    "sg:orig_category":"D\u00e9molition d\u00b4immeubles and terrassements",
    "sg:phone":"+32 51 70 38 48",
    "sg:postcode":"8840",
    "sg:province":"West-Vlaanderen",
    "wof:name":"Hans Masschelein",
    "wof:placetype":"venue"
},
  "geometry": {"coordinates":[3.0127930641,50.9751815796],"type":"Point"}
}