{
  "type": "Feature",
  "properties": {
    "iso:country":"BE",
    "sg:address":"Liersesteenweg 203a",
    "sg:city":"Mortsel",
    "sg:classifiers":[
        {
            "category":"Professional",
            "subcategory":"Advertising",
            "type":"Services"
        }
    ],
    "sg:phone":"+32 3 460 30 44",
    "sg:postcode":"2640",
    "sg:province":"Antwerpen",
    "sg:tags":[
        "item",
        "-",
        "business",
        "gift",
        "promotional"
    ],
    "wof:name":"Cadis Bag 2 Business",
    "wof:placetype":"venue"
},
  "geometry": {"coordinates":[4.4703550339,51.1689376831],"type":"Point"}
}