{
  "type": "Feature",
  "properties": {
    "addr:full":"Tienpondstraat 24 Wuustwezel Antwerpen 2990",
    "addr:housenumber":"24",
    "addr:postcode":"2990",
    "addr:street":"Tienpondstraat",
    "iso:country":"BE",
    "sg:address":"Tienpondstraat 24",
    "sg:city":"Wuustwezel",
    "sg:orig_category":"Rundveehouders",
    "sg:phone":"+32 3 669 63 24",
    "sg:postcode":"2990",
    "sg:province":"Antwerpen",
    "wof:name":"Constant Stes",
    "wof:placetype":"venue"
},
  "geometry": {"coordinates":[4.6474289894,51.3995399475],"type":"Point"}
}