{
  "type": "Feature",
  "properties": {
    "iso:country":"BE",
    "sg:address":"Rue Albert Ier 438",
    "sg:city":"Erquelinnes",
    "sg:orig_category":"Textiles. Eclairage et \u00e9quipements du foyer",
    "sg:phone":"+32 71 55 64 14",
    "sg:postcode":"6560",
    "sg:province":"Hainaut",
    "wof:name":"A La Cloche",
    "wof:placetype":"venue"
},
  "geometry": {"coordinates":[4.1091871262,50.3033752441],"type":"Point"}
}