{
  "type": "Feature",
  "properties": {
    "iso:country":"BE",
    "sg:address":"Vijfwegestraat 205 B",
    "sg:city":"Roeselare",
    "sg:orig_category":"Services de Nettoyage and de D\u00e9sinfection",
    "sg:phone":"+32 477 60 11 52",
    "sg:postcode":"8800",
    "sg:province":"West-Vlaanderen",
    "wof:name":"Rs Cleaning",
    "wof:placetype":"venue"
},
  "geometry": {"coordinates":[3.1311030388,50.9356155396],"type":"Point"}
}