{
  "type": "Feature",
  "properties": {
    "iso:country":"BE",
    "sg:address":"Bollestraat 15b",
    "sg:city":"Hooglede (gits)",
    "sg:classifiers":[
        {
            "category":"Farming",
            "subcategory":"Crops",
            "type":"Manufacturing & Wholesale Goods"
        }
    ],
    "sg:phone":"+32 51 72 28 57",
    "sg:postcode":"8830",
    "sg:province":"West-Vlaanderen",
    "sg:tags":[
        "vegetable",
        "fruit",
        "-",
        "grower"
    ],
    "wof:name":"Defevere E",
    "wof:placetype":"venue"
},
  "geometry": {"coordinates":[3.121516943,51.0005455017],"type":"Point"}
}