{
  "type": "Feature",
  "properties": {
    "iso:country":"BE",
    "sg:address":"Chauss\u00e9e De Mons 1",
    "sg:city":"Nivelles",
    "sg:classifiers":[
        {
            "category":"Retail",
            "subcategory":"Auto Repair",
            "type":"Services"
        }
    ],
    "sg:phone":"+32 67 89 02 11",
    "sg:postcode":"1400",
    "sg:province":"Brabant Wallon",
    "sg:tags":[
        "garage"
    ],
    "wof:name":"Aviation (garage De L') Sprl",
    "wof:placetype":"venue"
},
  "geometry": {"coordinates":[4.3147611618,50.5904388428],"type":"Point"}
}