{
  "type": "Feature",
  "properties": {
    "iso:country":"BE",
    "sg:address":"Kachtemsestraat 5",
    "sg:city":"Izegem",
    "sg:classifiers":[
        {
            "category":"Cafe",
            "type":"Food & Drink"
        }
    ],
    "sg:phone":"+32 51 30 05 51",
    "sg:postcode":"8870",
    "sg:province":"West-Vlaanderen",
    "sg:tags":[
        "caf\u00e9s"
    ],
    "wof:name":"Georges Vanacker",
    "wof:placetype":"venue"
},
  "geometry": {"coordinates":[3.2140829563,50.9277915955],"type":"Point"}
}