{
  "type": "Feature",
  "properties": {
    "iso:country":"BE",
    "sg:address":"Rue Dolimont 8",
    "sg:city":"Wavre",
    "sg:orig_category":"Diverse bedrijfsbeheeradviesbureaus",
    "sg:phone":"+32 2 654 12 31",
    "sg:postcode":"1301",
    "sg:province":"Brabant Wallon",
    "wof:name":"Cksb Benelux",
    "wof:placetype":"venue"
},
  "geometry": {"coordinates":[4.562128067,50.7327156067],"type":"Point"}
}