{
  "type": "Feature",
  "properties": {
    "addr:full":"Rue Adelson Castiaux 225 Quaregnon Hainaut 7390",
    "addr:housenumber":"225",
    "addr:postcode":"7390",
    "addr:street":"Rue Adelson Castiaux",
    "iso:country":"BE",
    "sg:address":"Rue Adelson Castiaux 225",
    "sg:city":"Quaregnon",
    "sg:classifiers":[
        {
            "category":"Banks & Credit Unions",
            "subcategory":"Investment Brokerage",
            "type":"Services"
        }
    ],
    "sg:phone":"+32 65 77 83 89",
    "sg:postcode":"7390",
    "sg:province":"Hainaut",
    "sg:tags":[
        "repair",
        "-",
        "installation",
        "sanitary",
        "article"
    ],
    "wof:name":"Joly Freddy & Fils",
    "wof:placetype":"venue"
},
  "geometry": {"coordinates":[3.8622720242,50.4371871948],"type":"Point"}
}