{
  "type": "Feature",
  "properties": {
    "iso:country":"BE",
    "sg:address":"Gaversesteenweg 733",
    "sg:city":"Merelbeke",
    "sg:orig_category":"Plantes and fleurs Gr",
    "sg:phone":"+32 9 362 08 17",
    "sg:postcode":"9820",
    "sg:province":"Oost-Vlaanderen",
    "wof:name":"Volckaert-thienpondt",
    "wof:placetype":"venue"
},
  "geometry": {"coordinates":[3.719219923,50.9737091064],"type":"Point"}
}