{
  "type": "Feature",
  "properties": {
    "addr:full":"Tien Geboden 23 Brugge West-Vlaanderen 8200",
    "addr:housenumber":"23",
    "addr:postcode":"8200",
    "iso:country":"BE",
    "sg:address":"Tien Geboden 23",
    "sg:city":"Brugge",
    "sg:classifiers":[
        {
            "category":"Arena",
            "subcategory":"Sports Club",
            "type":"Entertainment"
        }
    ],
    "sg:phone":"+32 50 31 96 48",
    "sg:postcode":"8200",
    "sg:province":"West-Vlaanderen",
    "sg:tags":[
        "de"
    ],
    "wof:name":"B.b.c. Concordia Brugge",
    "wof:placetype":"venue"
},
  "geometry": {"coordinates":[3.2047760487,51.2053527832],"type":"Point"}
}