{
  "type": "Feature",
  "properties": {
    "addr:full":"Avenue Du Pois De Senteur 62 Bruxelles Bruxelles-Capitale 1020",
    "addr:housenumber":"62",
    "addr:postcode":"1020",
    "addr:street":"Avenue Du Pois De Senteur",
    "iso:country":"BE",
    "sg:address":"Avenue Du Pois De Senteur 62",
    "sg:city":"Bruxelles",
    "sg:classifiers":[
        {
            "category":"Health Services",
            "subcategory":"Health Practitioner",
            "type":"Services"
        }
    ],
    "sg:phone":"+32 2 268 57 24",
    "sg:postcode":"1020",
    "sg:province":"Bruxelles-Capitale",
    "sg:tags":[
        "physiotherapist"
    ],
    "wof:name":"Tieleman L",
    "wof:placetype":"venue"
},
  "geometry": {"coordinates":[4.3695201874,50.8932304382],"type":"Point"}
}