{
  "type": "Feature",
  "properties": {
    "iso:country":"BE",
    "sg:address":"Dorpsstraat 37b",
    "sg:city":"Zonhoven",
    "sg:orig_category":"Kapsalons",
    "sg:phone":"+32 11 81 89 74",
    "sg:postcode":"3520",
    "sg:province":"Limburg",
    "wof:name":"Coiffure A",
    "wof:placetype":"venue"
},
  "geometry": {"coordinates":[5.3676381111,50.9933319092],"type":"Point"}
}