{
  "type": "Feature",
  "properties": {
    "addr:full":"Koningin Astridlaan 145 Mechelen Antwerpen 2800",
    "addr:housenumber":"145",
    "addr:postcode":"2800",
    "addr:street":"Koningin Astridlaan",
    "iso:country":"BE",
    "sg:address":"Koningin Astridlaan 145",
    "sg:city":"Mechelen",
    "sg:orig_category":"Avocats and conseillers juridiques",
    "sg:phone":"+32 15 41 37 26",
    "sg:postcode":"2800",
    "sg:province":"Antwerpen",
    "wof:name":"Frans Meulemans",
    "wof:placetype":"venue"
},
  "geometry": {"coordinates":[4.4717478752,51.0239295959],"type":"Point"}
}