{
  "type": "Feature",
  "properties": {
    "iso:country":"BE",
    "sg:address":"Statieplaats 2",
    "sg:city":"Komen-waasten/comines-warneton",
    "sg:orig_category":"Kapsalons",
    "sg:phone":"+32 56 55 75 06",
    "sg:postcode":"7784",
    "sg:province":"Hainaut",
    "wof:name":"Coiffure Hawai",
    "wof:placetype":"venue"
},
  "geometry": {"coordinates":[2.9385099411,50.738319397],"type":"Point"}
}