{
  "type": "Feature",
  "properties": {
    "addr:full":"Dr\u00e8ve De Touraine 21 Bruxelles (uccle) Bruxelles-Capitale 1180",
    "addr:housenumber":"21",
    "addr:postcode":"1180",
    "addr:street":"Dre\u0300Ve De Touraine",
    "iso:country":"BE",
    "sg:address":"Dr\u00e8ve De Touraine 21",
    "sg:city":"Bruxelles (uccle)",
    "sg:classifiers":[
        {
            "category":"Health Services",
            "subcategory":"Health Practitioner",
            "type":"Services"
        }
    ],
    "sg:phone":"+32 2 376 31 90",
    "sg:postcode":"1180",
    "sg:province":"Bruxelles-Capitale",
    "sg:tags":[
        "therapist",
        "speech"
    ],
    "wof:name":"Dubois C",
    "wof:placetype":"venue"
},
  "geometry": {"coordinates":[4.326862812,50.8048782349],"type":"Point"}
}