{
  "type": "Feature",
  "properties": {
    "addr:full":"Rue L\u00c9on Hachez 44 Soignies Hainaut 7060",
    "addr:housenumber":"44",
    "addr:postcode":"7060",
    "addr:street":"Rue Le\u0301On Hachez",
    "iso:country":"BE",
    "sg:address":"Rue L\u00c9on Hachez 44",
    "sg:city":"Soignies",
    "sg:classifiers":[
        {
            "category":"Shopping",
            "subcategory":"Bicycles & Sporting Goods",
            "type":"Retail Goods"
        }
    ],
    "sg:phone":"+32 67 33 58 90",
    "sg:postcode":"7060",
    "sg:province":"Hainaut",
    "sg:tags":[
        "article",
        "de",
        "sport",
        "camping"
    ],
    "wof:name":"Algo-sports",
    "wof:placetype":"venue"
},
  "geometry": {"coordinates":[4.0688838959,50.5813713074],"type":"Point"}
}