{
  "type": "Feature",
  "properties": {
    "iso:country":"BE",
    "sg:address":"Eksaarde Dorp 52",
    "sg:city":"Lokeren (eksaarde)",
    "sg:classifiers":[
        {
            "category":"Personal",
            "type":"Services"
        }
    ],
    "sg:phone":"+32 9 346 85 99",
    "sg:postcode":"9160",
    "sg:province":"Oost-Vlaanderen",
    "sg:tags":[
        "clothing",
        "men's",
        "tailor",
        "-"
    ],
    "wof:name":"Bauwens M",
    "wof:placetype":"venue"
},
  "geometry": {"coordinates":[3.9624640942,51.1158332825],"type":"Point"}
}