{
  "type": "Feature",
  "properties": {
    "iso:country":"BE",
    "sg:address":"Merelstraat 7b2",
    "sg:city":"Asse",
    "sg:orig_category":"Paramedische behandelingen",
    "sg:phone":"+32 2 463 30 90",
    "sg:postcode":"1731",
    "sg:province":"Vlaams-Brabant",
    "wof:name":"K. Vanderhasselt",
    "wof:placetype":"venue"
},
  "geometry": {"coordinates":[4.2742218971,50.885345459],"type":"Point"}
}