{
  "type": "Feature",
  "properties": {
    "iso:country":"BE",
    "sg:address":"Chauss\u00e9e De Namur 200",
    "sg:city":"Eghez\u00e9e (leuze)",
    "sg:classifiers":[
        {
            "category":"Personal",
            "subcategory":"Barber",
            "type":"Services"
        }
    ],
    "sg:phone":"+32 81 51 33 00",
    "sg:postcode":"5310",
    "sg:province":"Namur",
    "sg:tags":[
        "gentleman",
        "salon",
        "-",
        "hairdressing"
    ],
    "wof:name":"Nolmans G",
    "wof:placetype":"venue"
},
  "geometry": {"coordinates":[4.9116740227,50.5860519409],"type":"Point"}
}