{
  "type": "Feature",
  "properties": {
    "iso:country":"BE",
    "sg:address":"Maasstraat 38b",
    "sg:city":"Antwerpen",
    "sg:classifiers":[
        {
            "category":"Shopping",
            "subcategory":"Stationery & Office Supplies",
            "type":"Retail Goods"
        }
    ],
    "sg:phone":"+32 3 825 57 97",
    "sg:postcode":"2060",
    "sg:province":"Antwerpen",
    "sg:tags":[
        "partition"
    ],
    "wof:name":"P.s.m.",
    "wof:placetype":"venue"
},
  "geometry": {"coordinates":[4.4275169373,51.2345161438],"type":"Point"}
}