{
  "type": "Feature",
  "properties": {
    "addr:full":"Avenue Guillaume Gilbert 28 Bruxelles (ixelles) Bruxelles-Capitale 1050",
    "addr:housenumber":"28",
    "addr:postcode":"1050",
    "addr:street":"Avenue Guillaume Gilbert",
    "iso:country":"BE",
    "sg:address":"Avenue Guillaume Gilbert 28",
    "sg:city":"Bruxelles (ixelles)",
    "sg:classifiers":[
        {
            "category":"Home & Garden",
            "subcategory":"Carpets & Floor Coverings",
            "type":"Retail Goods"
        }
    ],
    "sg:phone":"+32 2 672 76 89",
    "sg:postcode":"1050",
    "sg:province":"Bruxelles-Capitale",
    "sg:tags":[
        "material",
        "waterproofing"
    ],
    "wof:name":"Product Service Sa",
    "wof:placetype":"venue"
},
  "geometry": {"coordinates":[4.3912491798,50.8113059998],"type":"Point"}
}