{
  "type": "Feature",
  "properties": {
    "addr:full":"Palmstraat 1 Kapellen Antwerpen 2950",
    "addr:housenumber":"1",
    "addr:postcode":"2950",
    "addr:street":"Palmstraat",
    "iso:country":"BE",
    "sg:address":"Palmstraat 1",
    "sg:city":"Kapellen",
    "sg:classifiers":[
        {
            "category":"Professional",
            "subcategory":"Accounting & Tax Preparation",
            "type":"Services"
        }
    ],
    "sg:phone":"+32 3 605 94 28",
    "sg:postcode":"2950",
    "sg:province":"Antwerpen",
    "sg:tags":[
        "bookkeeper"
    ],
    "wof:name":"Anthonissen G",
    "wof:placetype":"venue"
},
  "geometry": {"coordinates":[4.4194178581,51.3076477051],"type":"Point"}
}