{
  "type": "Feature",
  "properties": {
    "iso:country":"BE",
    "sg:address":"Basilieklaan 22ba",
    "sg:city":"Scherpenheuvel-zichem",
    "sg:orig_category":"Pharmaciens",
    "sg:phone":"+32 13 77 14 16",
    "sg:postcode":"3270",
    "sg:province":"Vlaams-Brabant",
    "wof:name":"Apotheek Dassen Jos",
    "wof:placetype":"venue"
},
  "geometry": {"coordinates":[4.9756960869,50.9800415039],"type":"Point"}
}