{
  "type": "Feature",
  "properties": {
    "iso:country":"BE",
    "sg:address":"Chemin De La Prairie 77",
    "sg:city":"Hellebecq",
    "sg:classifiers":[
        {
            "category":"Manufacturing",
            "subcategory":"Paper Products",
            "type":"Manufacturing & Wholesale Goods"
        }
    ],
    "sg:phone":"+32 68 55 29 41",
    "sg:postcode":"7830",
    "sg:province":"Hainaut",
    "sg:tags":[
        "hygiene",
        "animal"
    ],
    "wof:name":"Marc Gemers",
    "wof:placetype":"venue"
},
  "geometry": {"coordinates":[3.8947598934,50.6678619385],"type":"Point"}
}