{
  "type": "Feature",
  "properties": {
    "iso:country":"BE",
    "sg:address":"Lodorp 34",
    "sg:city":"Aalter",
    "sg:orig_category":"Slagers",
    "sg:phone":"+32 51 68 82 07",
    "sg:postcode":"9880",
    "sg:province":"Oost-Vlaanderen",
    "wof:name":"Marc Wyckstandt",
    "wof:placetype":"venue"
},
  "geometry": {"coordinates":[3.4628639221,51.0490226746],"type":"Point"}
}