{
  "type": "Feature",
  "properties": {
    "iso:country":"BE",
    "sg:address":"Wilgenlaan 13",
    "sg:city":"Scherpenheuvel-zichem",
    "sg:orig_category":"Dakwerken",
    "sg:phone":"+32 13 77 76 75",
    "sg:postcode":"3271",
    "sg:province":"Vlaams-Brabant",
    "wof:name":"Davy Jacobs",
    "wof:placetype":"venue"
},
  "geometry": {"coordinates":[4.9584841728,50.9800796509],"type":"Point"}
}