{
  "type": "Feature",
  "properties": {
    "addr:full":"Ketschehoef 10 Vosselaar Antwerpen 2350",
    "addr:housenumber":"10",
    "addr:postcode":"2350",
    "addr:street":"Ketschehoef",
    "iso:country":"BE",
    "sg:address":"Ketschehoef 10",
    "sg:city":"Vosselaar",
    "sg:orig_category":"Boekhouders",
    "sg:phone":"+32 14 41 55 24",
    "sg:postcode":"2350",
    "sg:province":"Antwerpen",
    "wof:name":"Vromans Belgie",
    "wof:placetype":"venue"
},
  "geometry": {"coordinates":[4.9010062218,51.3025627136],"type":"Point"}
}