{
  "type": "Feature",
  "properties": {
    "iso:country":"BE",
    "sg:address":"Bootdijkstraat 96",
    "sg:city":"Hamme",
    "sg:orig_category":"Groententeelt",
    "sg:phone":"+32 52 47 66 56",
    "sg:postcode":"9220",
    "sg:province":"Oost-Vlaanderen",
    "wof:name":"Karine Colman",
    "wof:placetype":"venue"
},
  "geometry": {"coordinates":[4.165391922,51.0779342651],"type":"Point"}
}