{
  "type": "Feature",
  "properties": {
    "iso:country":"BE",
    "sg:address":"Sint-christianastraat 18ba",
    "sg:city":"Dendermonde",
    "sg:orig_category":"M\u00e9decins and sp\u00e9cialistes",
    "sg:phone":"+32 52 20 34 24",
    "sg:postcode":"9200",
    "sg:province":"Oost-Vlaanderen",
    "wof:name":"J. Decloedt",
    "wof:placetype":"venue"
},
  "geometry": {"coordinates":[4.0900998116,51.0323867798],"type":"Point"}
}