{
  "type": "Feature",
  "properties": {
    "addr:full":"Rue Du Ch\u00e9ra 79b Li\u00e8ge 1 Li\u00e8ge 4000",
    "addr:housenumber":"79b;1",
    "addr:postcode":"4000",
    "addr:street":"Rue Du Che\u0301Ra",
    "iso:country":"BE",
    "sg:address":"Rue Du Ch\u00e9ra 79b",
    "sg:city":"Li\u00e8ge 1",
    "sg:classifiers":[
        {
            "category":"Arena",
            "subcategory":"Sports Club",
            "type":"Entertainment"
        }
    ],
    "sg:phone":"+32 4 254 17 64",
    "sg:postcode":"4000",
    "sg:province":"Li\u00e8ge",
    "wof:name":"Daring Club De Cointe (royal)",
    "wof:placetype":"venue"
},
  "geometry": {"coordinates":[5.5675559044,50.6166152954],"type":"Point"}
}