{
  "type": "Feature",
  "properties": {
    "iso:country":"BE",
    "sg:address":"Kortrijksesteenweg 329",
    "sg:city":"Harelbeke",
    "sg:orig_category":"Sportcentra",
    "sg:phone":"+32 56 72 95 95",
    "sg:postcode":"8530",
    "sg:province":"West-Vlaanderen",
    "wof:name":"Flits Fitness Centrum",
    "wof:placetype":"venue"
},
  "geometry": {"coordinates":[3.2911119461,50.842300415],"type":"Point"}
}