{
  "type": "Feature",
  "properties": {
    "iso:country":"BE",
    "sg:address":"Zoning Industriel Des Cahottes",
    "sg:city":"Flemalle",
    "sg:orig_category":"Rev\u00eatements de sols and murs",
    "sg:phone":"+32 4 250 47 93",
    "sg:postcode":"4400",
    "sg:province":"Li\u00e8ge",
    "wof:name":"Solidbeton",
    "wof:placetype":"venue"
},
  "geometry": {"coordinates":[5.434276104,50.6219558716],"type":"Point"}
}