{
  "type": "Feature",
  "properties": {
    "addr:full":"Processieweg 16 Buggenhout Oost-Vlaanderen 9255",
    "addr:housenumber":"16",
    "addr:postcode":"9255",
    "addr:street":"Processieweg",
    "iso:country":"BE",
    "sg:address":"Processieweg 16",
    "sg:city":"Buggenhout",
    "sg:classifiers":[
        {
            "category":"Professional",
            "subcategory":"Accounting & Tax Preparation",
            "type":"Services"
        }
    ],
    "sg:phone":"+32 52 35 10 51",
    "sg:postcode":"9255",
    "sg:province":"Oost-Vlaanderen",
    "sg:tags":[
        "accountant"
    ],
    "wof:name":"Decofis Bvba",
    "wof:placetype":"venue"
},
  "geometry": {"coordinates":[4.1705579758,50.9931678772],"type":"Point"}
}