{
  "type": "Feature",
  "properties": {
    "iso:country":"BE",
    "sg:address":"Chemin De La Rosi\u00e8re 4",
    "sg:city":"Neufch\u00e2teau (tournay)",
    "sg:classifiers":[
        {
            "category":"Farming",
            "subcategory":"Fish & Marine Products",
            "type":"Manufacturing & Wholesale Goods"
        }
    ],
    "sg:phone":"+32 61 27 00 56",
    "sg:postcode":"6840",
    "sg:province":"Luxembourg",
    "sg:tags":[
        "breeding"
    ],
    "wof:name":"Pisciculture Des Faussies",
    "wof:placetype":"venue"
},
  "geometry": {"coordinates":[5.4346451759,49.8411598206],"type":"Point"}
}