{
  "type": "Feature",
  "properties": {
    "iso:country":"BE",
    "sg:address":"Roemeni\u00cbstraat 38",
    "sg:city":"Sint-gillis/saint-gilles",
    "sg:orig_category":"Artsen and specialisten",
    "sg:phone":"+32 2 534 72 27",
    "sg:postcode":"1060",
    "sg:province":"Bruxelles-Capitale",
    "wof:name":"A. Cloquet",
    "wof:placetype":"venue"
},
  "geometry": {"coordinates":[4.3503489494,50.8274879456],"type":"Point"}
}