{
  "type": "Feature",
  "properties": {
    "addr:full":"Eikenlaan 9 Liedekerke Vlaams-Brabant 1770",
    "addr:housenumber":"9",
    "addr:postcode":"1770",
    "addr:street":"Eikenlaan;Vlaams-Brabant",
    "iso:country":"BE",
    "sg:address":"Eikenlaan 9",
    "sg:city":"Liedekerke",
    "sg:classifiers":[
        {
            "category":"Structure",
            "subcategory":"Office Building",
            "type":"Public Place"
        }
    ],
    "sg:phone":"+32 53 66 59 51",
    "sg:postcode":"1770",
    "sg:province":"Vlaams-Brabant",
    "sg:tags":[
        "roofing",
        "slate"
    ],
    "wof:name":"Van Den Brande R",
    "wof:placetype":"venue"
},
  "geometry": {"coordinates":[4.1011800766,50.8643074036],"type":"Point"}
}