{
  "type": "Feature",
  "properties": {
    "addr:full":"40 Weg Naar Meeuwen 3660 Opglabbeek 40",
    "addr:housenumber":"40",
    "addr:postcode":"3660",
    "addr:street":"40 Weg Naar Meeuwen",
    "iso:country":"BE",
    "sg:address":"40",
    "sg:city":"Weg Naar Meeuwen 3660 Opglabbeek",
    "sg:classifiers":[
        {
            "category":"Professional",
            "type":"Services"
        }
    ],
    "sg:phone":"+32 89 85 50 44",
    "sg:postcode":"40",
    "sg:tags":[
        "transport",
        "road"
    ],
    "wof:name":"Jos Siborgs Int Transport Bvba",
    "wof:placetype":"venue"
},
  "geometry": {"coordinates":[5.5271449089,51.0398139954],"type":"Point"}
}