{
  "type": "Feature",
  "properties": {
    "iso:country":"BE",
    "sg:address":"Rue Des Ecoles 4",
    "sg:city":"Comblain-au-pont",
    "sg:orig_category":"Boucheries",
    "sg:phone":"+32 4 380 15 73",
    "sg:postcode":"4171",
    "sg:province":"Li\u00e8ge",
    "wof:name":"Jean-marie Michel",
    "wof:placetype":"venue"
},
  "geometry": {"coordinates":[5.5796041489,50.5086021423],"type":"Point"}
}