{
  "type": "Feature",
  "properties": {
    "addr:full":"Houthalenseweg 6a Zonhoven Limburg 3520",
    "addr:housenumber":"6a",
    "addr:postcode":"3520",
    "addr:street":"Houthalenseweg",
    "iso:country":"BE",
    "sg:address":"Houthalenseweg 6a",
    "sg:city":"Zonhoven",
    "sg:classifiers":[
        {
            "category":"Wholesale",
            "subcategory":"Beer",
            "type":"Manufacturing & Wholesale Goods"
        }
    ],
    "sg:phone":"+32 11 81 58 32",
    "sg:postcode":"3520",
    "sg:province":"Limburg",
    "sg:tags":[
        "ale",
        "-"
    ],
    "wof:name":"Drink-service Indeherberg Bvba",
    "wof:placetype":"venue"
},
  "geometry": {"coordinates":[5.3695402145,50.9968795776],"type":"Point"}
}