{
  "type": "Feature",
  "properties": {
    "addr:full":"Koninksemstraat 73 Tongeren Limburg 3700",
    "addr:housenumber":"73",
    "addr:postcode":"3700",
    "addr:street":"Koninksemstraat",
    "iso:country":"BE",
    "sg:address":"Koninksemstraat 73",
    "sg:city":"Tongeren",
    "sg:classifiers":[
        {
            "category":"Personal",
            "subcategory":"Beauty Salon",
            "type":"Services"
        }
    ],
    "sg:phone":"+32 12 23 89 41",
    "sg:postcode":"3700",
    "sg:province":"Limburg",
    "sg:tags":[
        "de",
        "coiffure"
    ],
    "wof:name":"Raf Princen",
    "wof:placetype":"venue"
},
  "geometry": {"coordinates":[5.4570708275,50.7769241333],"type":"Point"}
}