{
  "type": "Feature",
  "properties": {
    "iso:country":"BE",
    "sg:address":"Chemin De La Fontaine 15",
    "sg:city":"Sart-lez-spa",
    "sg:classifiers":[
        {
            "category":"Building & Trades",
            "subcategory":"Construction",
            "type":"Services"
        }
    ],
    "sg:phone":"+32 87 77 21 84",
    "sg:postcode":"4845",
    "sg:province":"Li\u00e8ge",
    "sg:tags":[
        "carpenter"
    ],
    "wof:name":"J\u00e9r\u00f4me & Fils Sprl",
    "wof:placetype":"venue"
},
  "geometry": {"coordinates":[5.8976831436,50.5031013489],"type":"Point"}
}