{
  "type": "Feature",
  "properties": {
    "addr:full":"Scheldestraat 82 Gent Oost-Vlaanderen 9040",
    "addr:housenumber":"82",
    "addr:postcode":"9040",
    "addr:street":"Scheldestraat;Oost-Vlaanderen",
    "iso:country":"BE",
    "sg:address":"Scheldestraat 82",
    "sg:city":"Gent",
    "sg:orig_category":"Paramedische behandelingen",
    "sg:phone":"+32 9 228 66 04",
    "sg:postcode":"9040",
    "sg:province":"Oost-Vlaanderen",
    "wof:name":"B. Petit",
    "wof:placetype":"venue"
},
  "geometry": {"coordinates":[3.7501630783,51.0500793457],"type":"Point"}
}