{
  "type": "Feature",
  "properties": {
    "iso:country":"BE",
    "sg:address":"Nieuwstraat 4",
    "sg:city":"Brussel/bruxelles",
    "sg:orig_category":"Dameskledingzaken",
    "sg:phone":"+32 2 219 57 68",
    "sg:postcode":"1000",
    "sg:province":"Bruxelles-Capitale",
    "wof:name":"Jennyfer - Belgique",
    "wof:placetype":"venue"
},
  "geometry": {"coordinates":[4.3523869514,50.854637146],"type":"Point"}
}