{
  "type": "Feature",
  "properties": {
    "addr:full":"Moorselbaan 562 Aalst Oost-Vlaanderen 9300",
    "addr:housenumber":"562",
    "addr:postcode":"9300",
    "addr:street":"Moorselbaan",
    "iso:country":"BE",
    "sg:address":"Moorselbaan 562",
    "sg:city":"Aalst",
    "sg:orig_category":"Newspapers, magazines, periodicals - Distribution",
    "sg:phone":"+32 53 70 32 34",
    "sg:postcode":"9300",
    "sg:province":"Oost-Vlaanderen",
    "wof:name":"Dagbladhandel Chris",
    "wof:placetype":"venue"
},
  "geometry": {"coordinates":[4.0813498497,50.9454193115],"type":"Point"}
}