{
  "type": "Feature",
  "properties": {
    "addr:full":"Beheerstraat 41 Kortrijk West-Vlaanderen 8500",
    "addr:housenumber":"41",
    "addr:postcode":"8500",
    "addr:street":"Beheerstraat",
    "iso:country":"BE",
    "sg:address":"Beheerstraat 41",
    "sg:city":"Kortrijk",
    "sg:orig_category":"Enseignement maternel and primaire",
    "sg:phone":"+32 56 21 51 54",
    "sg:postcode":"8500",
    "sg:province":"West-Vlaanderen",
    "wof:name":"Vrije Basisschool",
    "wof:placetype":"venue"
},
  "geometry": {"coordinates":[3.2574470043,50.8271446228],"type":"Point"}
}