{
  "type": "Feature",
  "properties": {
    "addr:full":"Luitenant Lippenslaan 12 Antwerpen Antwerpen 2140",
    "addr:housenumber":"12",
    "addr:postcode":"2140",
    "addr:street":"Luitenant Lippenslaan",
    "iso:country":"BE",
    "sg:address":"Luitenant Lippenslaan 12",
    "sg:city":"Antwerpen",
    "sg:orig_category":"Banken and kredietinstellingen",
    "sg:phone":"+32 3 236 48 06",
    "sg:postcode":"2140",
    "sg:province":"Antwerpen",
    "wof:name":"Fortis",
    "wof:placetype":"venue"
},
  "geometry": {"coordinates":[4.4332199097,51.2137565613],"type":"Point"}
}