{
  "type": "Feature",
  "properties": {
    "iso:country":"BE",
    "sg:address":"Burg. Heymansplein 48",
    "sg:city":"Beringen",
    "sg:orig_category":"Banques and organismes de cr\u00e9dit",
    "sg:phone":"+32 11 34 21 28",
    "sg:postcode":"3581",
    "sg:province":"Limburg",
    "wof:name":"Fortis",
    "wof:placetype":"venue"
},
  "geometry": {"coordinates":[5.2228298187,51.0881996155],"type":"Point"}
}