{
  "type": "Feature",
  "properties": {
    "iso:country":"BE",
    "sg:address":"Pingeren 19",
    "sg:city":"Baelen",
    "sg:classifiers":[
        {
            "category":"Retail",
            "subcategory":"Auto Repair",
            "type":"Services"
        }
    ],
    "sg:phone":"+32 87 88 27 12",
    "sg:postcode":"4837",
    "sg:province":"Li\u00e8ge",
    "sg:tags":[
        "automobile-body"
    ],
    "wof:name":"Koop P",
    "wof:placetype":"venue"
},
  "geometry": {"coordinates":[5.9603619576,50.6380996704],"type":"Point"}
}