{
  "type": "Feature",
  "properties": {
    "addr:full":"Bd Du Souverain 360 Auderghem Bruxelles-Capitale 1160",
    "addr:housenumber":"360",
    "addr:postcode":"1160",
    "addr:street":"Bd Du Souverain",
    "iso:country":"BE",
    "sg:address":"Bd Du Souverain 360",
    "sg:city":"Auderghem",
    "sg:classifiers":[
        {
            "category":"Banks & Credit Unions",
            "subcategory":"Financial Services",
            "type":"Services"
        }
    ],
    "sg:phone":"+32 2 673 80 30",
    "sg:postcode":"1160",
    "sg:province":"Bruxelles-Capitale",
    "sg:tags":[
        "banking",
        "finance",
        "insurance"
    ],
    "wof:name":"Partners Assurances Verzekeringen Sa",
    "wof:placetype":"venue"
},
  "geometry": {"coordinates":[4.4304890633,50.8215522766],"type":"Point"}
}