{
  "type": "Feature",
  "properties": {
    "iso:country":"BE",
    "sg:address":"Waterloose Steenweg 198",
    "sg:city":"Sint-genesius-rode/rhode-saint-genese",
    "sg:orig_category":"Diverse meubelen Fab MEUBELONTWERP AND -INSTALLATIE",
    "sg:phone":"+32 2 359 95 65",
    "sg:postcode":"1640",
    "sg:province":"Vlaams-Brabant",
    "wof:name":"Bruynzeel Keukens",
    "wof:placetype":"venue"
},
  "geometry": {"coordinates":[4.3945999146,50.7476196289],"type":"Point"}
}