{
  "type": "Feature",
  "properties": {
    "addr:full":"Zelemsebaan 21 Lummen (meldert) Limburg 3560",
    "addr:housenumber":"21",
    "addr:postcode":"3560",
    "addr:street":"Zelemsebaan",
    "iso:country":"BE",
    "sg:address":"Zelemsebaan 21",
    "sg:city":"Lummen (meldert)",
    "sg:classifiers":[
        {
            "category":"Wholesale",
            "subcategory":"Beer",
            "type":"Manufacturing & Wholesale Goods"
        }
    ],
    "sg:phone":"+32 13 31 18 46",
    "sg:postcode":"3560",
    "sg:province":"Limburg",
    "sg:tags":[
        "ale",
        "-"
    ],
    "wof:name":"Dranken Bukkers",
    "wof:placetype":"venue"
},
  "geometry": {"coordinates":[5.1928048134,50.9866790771],"type":"Point"}
}