{
  "type": "Feature",
  "properties": {
    "addr:full":"Frankrijklei 37 Antwerpen Antwerpen 2000",
    "addr:housenumber":"37",
    "addr:postcode":"2000",
    "addr:street":"Frankrijklei",
    "iso:country":"BE",
    "sg:address":"Frankrijklei 37",
    "sg:city":"Antwerpen",
    "sg:orig_category":"Advocaten and juridische adviseurs",
    "sg:phone":"+32 3 213 39 44",
    "sg:postcode":"2000",
    "sg:province":"Antwerpen",
    "wof:name":"P. Boelens",
    "wof:placetype":"venue"
},
  "geometry": {"coordinates":[4.4150729179,51.2166748047],"type":"Point"}
}