{
  "type": "Feature",
  "properties": {
    "iso:country":"BE",
    "sg:address":"Steenweg Op Blaasveld 56a",
    "sg:city":"Mechelen (heffen)",
    "sg:classifiers":[
        {
            "category":"Real Estate",
            "subcategory":"Real Estate Services",
            "type":"Services"
        }
    ],
    "sg:phone":"+32 15 27 70 36",
    "sg:postcode":"2801",
    "sg:province":"Antwerpen",
    "wof:name":"Investpro Nv",
    "wof:placetype":"venue"
},
  "geometry": {"coordinates":[4.4142742157,51.0467910767],"type":"Point"}
}