{
  "type": "Feature",
  "properties": {
    "iso:country":"BE",
    "sg:address":"Antwerpsesteenweg 309 Box 1",
    "sg:city":"Malle (westmalle)",
    "sg:classifiers":[
        {
            "category":"Personal",
            "subcategory":"Beauty Salon",
            "type":"Services"
        }
    ],
    "sg:phone":"+32 3 309 44 17",
    "sg:postcode":"2390",
    "sg:province":"Antwerpen",
    "sg:tags":[
        "lady",
        "-",
        "hairdressing"
    ],
    "wof:name":"Threesom",
    "wof:placetype":"venue"
},
  "geometry": {"coordinates":[4.6889400482,51.2971076965],"type":"Point"}
}