{
  "type": "Feature",
  "properties": {
    "iso:country":"BE",
    "sg:address":"Rue Du March\u00e9 Au Charbon 60",
    "sg:city":"Bruxelles",
    "sg:classifiers":[
        {
            "category":"Bars & Pubs",
            "type":"Food & Drink"
        }
    ],
    "sg:phone":"+32 2 514 51 49",
    "sg:postcode":"1000",
    "sg:province":"Bruxelles-Capitale",
    "wof:name":"Pablo Disco Bar",
    "wof:placetype":"venue"
},
  "geometry": {"coordinates":[4.348900795,50.8462562561],"type":"Point"}
}