{
  "type": "Feature",
  "properties": {
    "addr:full":"Mussenpad 4 Knokke-heist (knokke) West-Vlaanderen 8300",
    "addr:housenumber":"4",
    "addr:postcode":"8300",
    "addr:street":"Mussenpad",
    "iso:country":"BE",
    "sg:address":"Mussenpad 4",
    "sg:city":"Knokke-heist (knokke)",
    "sg:classifiers":[
        {
            "category":"Farming",
            "subcategory":"Fish & Marine Products",
            "type":"Manufacturing & Wholesale Goods"
        }
    ],
    "sg:phone":"+32 50 62 71 81",
    "sg:postcode":"8300",
    "sg:province":"West-Vlaanderen",
    "sg:tags":[
        "retail",
        "-",
        "shellfish"
    ],
    "wof:name":"Fastfish",
    "wof:placetype":"venue"
},
  "geometry": {"coordinates":[3.291934967,51.3491210938],"type":"Point"}
}