{
  "type": "Feature",
  "properties": {
    "addr:full":"Middelweg 11 Knesselare Oost-Vlaanderen 9910",
    "addr:housenumber":"11",
    "addr:postcode":"9910",
    "addr:street":"Middelweg;Oost-Vlaanderen",
    "iso:country":"BE",
    "sg:address":"Middelweg 11",
    "sg:city":"Knesselare",
    "sg:orig_category":"Entretien and r\u00e9parations de voitures",
    "sg:phone":"+32 9 375 06 45",
    "sg:postcode":"9910",
    "sg:province":"Oost-Vlaanderen",
    "wof:name":"Jan Dhooge",
    "wof:placetype":"venue"
},
  "geometry": {"coordinates":[3.4823338985,51.1283874512],"type":"Point"}
}