{
  "type": "Feature",
  "properties": {
    "addr:full":"Geneinde 1 Westerlo Antwerpen 2260",
    "addr:housenumber":"1",
    "addr:postcode":"2260",
    "addr:street":"Geneinde",
    "iso:country":"BE",
    "sg:address":"Geneinde 1",
    "sg:city":"Westerlo",
    "sg:classifiers":[
        {
            "category":"Personal",
            "type":"Services"
        }
    ],
    "sg:phone":"+32 14 54 43 91",
    "sg:postcode":"2260",
    "sg:province":"Antwerpen",
    "sg:tags":[
        "party",
        "planning"
    ],
    "wof:name":"Torenhof",
    "wof:placetype":"venue"
},
  "geometry": {"coordinates":[4.9055371284,51.1028251648],"type":"Point"}
}