{
  "type": "Feature",
  "properties": {
    "addr:full":"Chauss\u00e9e De Saint-amand 105 Tournai Hainaut 7500",
    "addr:housenumber":"105",
    "addr:postcode":"7500",
    "addr:street":"Chausse\u0301E De Saint-Amand",
    "iso:country":"BE",
    "sg:address":"Chauss\u00e9e De Saint-amand 105",
    "sg:city":"Tournai",
    "sg:classifiers":[
        {
            "category":"Shopping",
            "subcategory":"Books",
            "type":"Retail Goods"
        }
    ],
    "sg:phone":"+32 69 23 55 23",
    "sg:postcode":"7500",
    "sg:province":"Hainaut",
    "sg:tags":[
        "bookseller"
    ],
    "wof:name":"Parchemin (le)",
    "wof:placetype":"venue"
},
  "geometry": {"coordinates":[3.4004070759,50.5957641602],"type":"Point"}
}