{
  "type": "Feature",
  "properties": {
    "addr:full":"Rue Jules Lahaye 282b13 Jette Bruxelles-Capitale 1090",
    "addr:housenumber":"282b13",
    "addr:postcode":"1090",
    "addr:street":"Rue Jules Lahaye",
    "iso:country":"BE",
    "sg:address":"Rue Jules Lahaye 282b13",
    "sg:city":"Jette",
    "sg:orig_category":"Vertalers and tolken",
    "sg:phone":"+32 2 424 20 40",
    "sg:postcode":"1090",
    "sg:province":"Bruxelles-Capitale",
    "wof:name":"Halevy J. Cbtip/bkvtf",
    "wof:placetype":"venue"
},
  "geometry": {"coordinates":[4.3372688293,50.87915802],"type":"Point"}
}