{
  "type": "Feature",
  "properties": {
    "addr:full":"Eedstraat 7 Nazareth Oost-Vlaanderen 9810",
    "addr:housenumber":"7",
    "addr:postcode":"9810",
    "addr:street":"Eedstraat",
    "iso:country":"BE",
    "sg:address":"Eedstraat 7",
    "sg:city":"Nazareth",
    "sg:orig_category":"Installatie van houten of kunststof schrijnwerk Pleisterwerk",
    "sg:phone":"+32 9 385 70 82",
    "sg:postcode":"9810",
    "sg:province":"Oost-Vlaanderen",
    "wof:name":"Baudouin Wyloeck",
    "wof:placetype":"venue"
},
  "geometry": {"coordinates":[3.6622068882,50.9702377319],"type":"Point"}
}