{
  "type": "Feature",
  "properties": {
    "iso:country":"BE",
    "sg:address":"Sint-truidersteenweg 94",
    "sg:city":"Hasselt",
    "sg:orig_category":"Artsen and specialisten",
    "sg:phone":"+32 11 27 07 25",
    "sg:postcode":"3500",
    "sg:province":"Limburg",
    "wof:name":"G. Waerzeggers",
    "wof:placetype":"venue"
},
  "geometry": {"coordinates":[5.3327951431,50.923625946],"type":"Point"}
}