{
  "type": "Feature",
  "properties": {
    "addr:full":"Turnhoutsebaan 292 Wijnegem Antwerpen 2110",
    "addr:housenumber":"292",
    "addr:postcode":"2110",
    "addr:street":"Turnhoutsebaan",
    "iso:country":"BE",
    "sg:address":"Turnhoutsebaan 292",
    "sg:city":"Wijnegem",
    "sg:classifiers":[
        {
            "category":"Bakery",
            "type":"Food & Drink"
        }
    ],
    "sg:phone":"+32 3 353 67 97",
    "sg:postcode":"2110",
    "sg:province":"Antwerpen",
    "sg:tags":[
        "confectioner",
        "baker"
    ],
    "wof:name":"Van Riel-priem Bvba",
    "wof:placetype":"venue"
},
  "geometry": {"coordinates":[4.5157260895,51.2266387939],"type":"Point"}
}