{
  "type": "Feature",
  "properties": {
    "addr:full":"Bellemdorpweg 16 Aalter Oost-Vlaanderen 9881",
    "addr:housenumber":"16",
    "addr:postcode":"9881",
    "addr:street":"Bellemdorpweg",
    "iso:country":"BE",
    "sg:address":"Bellemdorpweg 16",
    "sg:city":"Aalter",
    "sg:classifiers":[
        {
            "category":"Restaurant",
            "type":"Food & Drink"
        }
    ],
    "sg:phone":"+32 9 374 31 03",
    "sg:postcode":"9881",
    "sg:province":"Oost-Vlaanderen",
    "wof:name":"Gasthof Grill Ter Linden",
    "wof:placetype":"venue"
},
  "geometry": {"coordinates":[3.4908380508,51.0885391235],"type":"Point"}
}