{
  "type": "Feature",
  "properties": {
    "iso:country":"BE",
    "sg:address":"Rue De Houffalize 11",
    "sg:city":"Houffalize",
    "sg:orig_category":"R\u00e9parations de chaussures and articles en cuir. Chaussures",
    "sg:phone":"+32 84 44 42 50",
    "sg:postcode":"6660",
    "sg:province":"Luxembourg",
    "wof:name":"Joseph Mawet",
    "wof:placetype":"venue"
},
  "geometry": {"coordinates":[5.7902050018,50.1322784424],"type":"Point"}
}