{
  "type": "Feature",
  "properties": {
    "iso:country":"BE",
    "sg:address":"Meulebekestraat 21",
    "sg:city":"Dentergem",
    "sg:orig_category":"Rundveehouders Varkenskwekers",
    "sg:phone":"+32 51 63 51 60",
    "sg:postcode":"8720",
    "sg:province":"West-Vlaanderen",
    "wof:name":"Daniel Bouckhout",
    "wof:placetype":"venue"
},
  "geometry": {"coordinates":[3.3787178993,50.9614448547],"type":"Point"}
}