{
  "type": "Feature",
  "properties": {
    "iso:country":"BE",
    "sg:address":"A. Tirelirenstraat 6",
    "sg:city":"Essen",
    "sg:orig_category":"Sportclubs",
    "sg:phone":"+32 3 667 65 95",
    "sg:postcode":"2910",
    "sg:province":"Antwerpen",
    "wof:name":"Shotokan",
    "wof:placetype":"venue"
},
  "geometry": {"coordinates":[4.461160183,51.4604988098],"type":"Point"}
}