{
  "type": "Feature",
  "properties": {
    "iso:country":"BE",
    "sg:address":"Dr\u00c8ve Olympique 15b12",
    "sg:city":"Anderlecht",
    "sg:classifiers":[
        {
            "category":"Shopping",
            "subcategory":"Clothing, Apparel, & Fashions",
            "type":"Retail Goods"
        }
    ],
    "sg:phone":"+32 2 521 12 29",
    "sg:postcode":"1070",
    "sg:province":"Bruxelles-Capitale",
    "sg:tags":[
        "lingerie",
        "sous-v\u00eatements"
    ],
    "wof:name":"Hunkem\u00d6ller",
    "wof:placetype":"venue"
},
  "geometry": {"coordinates":[4.2767281532,50.8199539185],"type":"Point"}
}