{
  "type": "Feature",
  "properties": {
    "addr:full":"Vrasenestraat 42 Beveren Oost-Vlaanderen 9120",
    "addr:housenumber":"42",
    "addr:postcode":"9120",
    "addr:street":"Vrasenestraat",
    "iso:country":"BE",
    "sg:address":"Vrasenestraat 42",
    "sg:city":"Beveren",
    "sg:classifiers":[
        {
            "category":"Shopping",
            "subcategory":"Bicycles & Sporting Goods",
            "type":"Retail Goods"
        }
    ],
    "sg:phone":"+32 3 775 19 61",
    "sg:postcode":"9120",
    "sg:province":"Oost-Vlaanderen",
    "sg:tags":[
        "article",
        "de",
        "sport",
        "camping"
    ],
    "wof:name":"Sportline",
    "wof:placetype":"venue"
},
  "geometry": {"coordinates":[4.2544322014,51.2137565613],"type":"Point"}
}