{
  "type": "Feature",
  "properties": {
    "addr:full":"Chaumont 5 Vaux-sur-s\u00fbre (hompr\u00e9) Luxembourg 6640",
    "addr:housenumber":"5",
    "addr:postcode":"6640",
    "addr:street":"Chaumont",
    "iso:country":"BE",
    "sg:address":"Chaumont 5",
    "sg:city":"Vaux-sur-s\u00fbre (hompr\u00e9)",
    "sg:classifiers":[
        {
            "category":"Home & Garden",
            "subcategory":"Garden Supply",
            "type":"Retail Goods"
        }
    ],
    "sg:phone":"+32 61 26 61 79",
    "sg:postcode":"6640",
    "sg:province":"Luxembourg",
    "sg:tags":[
        "machine",
        "agricultural",
        "-"
    ],
    "wof:name":"Belche F Ets",
    "wof:placetype":"venue"
},
  "geometry": {"coordinates":[5.5671000481,49.91065979],"type":"Point"}
}