{
  "type": "Feature",
  "properties": {
    "addr:full":"Ukkelse Laan 25 Vorst/forest Bruxelles-Capitale 1190",
    "addr:housenumber":"25",
    "addr:postcode":"1190",
    "addr:street":"Ukkelse Laan;/ Forest",
    "iso:country":"BE",
    "sg:address":"Ukkelse Laan 25",
    "sg:city":"Vorst/forest",
    "sg:orig_category":"Artsen and specialisten",
    "sg:phone":"+32 2 346 57 70",
    "sg:postcode":"1190",
    "sg:province":"Bruxelles-Capitale",
    "wof:name":"Ch. Dubois",
    "wof:placetype":"venue"
},
  "geometry": {"coordinates":[4.3254189491,50.8127059937],"type":"Point"}
}