{
  "type": "Feature",
  "properties": {
    "addr:full":"Heuvelstraat 8 Hoogstraten Antwerpen 2320",
    "addr:housenumber":"8",
    "addr:postcode":"2320",
    "addr:street":"Heuvelstraat",
    "iso:country":"BE",
    "sg:address":"Heuvelstraat 8",
    "sg:city":"Hoogstraten",
    "sg:orig_category":"Eleveurs and marchands de porcs. Eleveurs de bovins",
    "sg:phone":"+32 3 314 66 31",
    "sg:postcode":"2320",
    "sg:province":"Antwerpen",
    "wof:name":"Miechielsen Alf & J.",
    "wof:placetype":"venue"
},
  "geometry": {"coordinates":[4.7464199066,51.3941917419],"type":"Point"}
}