{
  "type": "Feature",
  "properties": {
    "addr:full":"Industrieterrein 1114 Kanaal Noord Bree Limburg 3960",
    "addr:housenumber":"1114",
    "addr:postcode":"3960",
    "addr:street":"Industrieterrein;Kanaal Noord Bree Limburg",
    "iso:country":"BE",
    "sg:address":"Industrieterrein 1114 Kanaal Noord",
    "sg:city":"Bree",
    "sg:orig_category":"Betonnen bouwelementen Fab",
    "sg:phone":"+32 89 47 22 16",
    "sg:postcode":"3960",
    "sg:province":"Limburg",
    "wof:name":"Kunnen Betonproducten",
    "wof:placetype":"venue"
},
  "geometry": {"coordinates":[5.6175317764,51.1431541443],"type":"Point"}
}