{
  "type": "Feature",
  "properties": {
    "addr:full":"Mechelsesteenweg 89b Kampenhout Vlaams-Brabant 1910",
    "addr:housenumber":"89b",
    "addr:postcode":"1910",
    "addr:street":"Mechelsesteenweg",
    "iso:country":"BE",
    "sg:address":"Mechelsesteenweg 89b",
    "sg:city":"Kampenhout",
    "sg:classifiers":[
        {
            "category":"Shopping",
            "subcategory":"Clothing, Apparel, & Fashions",
            "type":"Retail Goods"
        }
    ],
    "sg:phone":"+32 16 60 90 06",
    "sg:postcode":"1910",
    "sg:province":"Vlaams-Brabant",
    "sg:tags":[
        "lady",
        "clothing",
        "-"
    ],
    "wof:name":"Noa Woman",
    "wof:placetype":"venue"
},
  "geometry": {"coordinates":[4.5842909813,50.9611740112],"type":"Point"}
}