{
  "type": "Feature",
  "properties": {
    "iso:country":"BE",
    "sg:address":"Rue Du Crucifix 108",
    "sg:city":"Herstal",
    "sg:orig_category":"Plomberie, chauffage and installations sanitaires. Charpentes and couvertures",
    "sg:phone":"+32 4 240 18 88",
    "sg:postcode":"4040",
    "sg:province":"Li\u00e8ge",
    "wof:name":"Brondoit",
    "wof:placetype":"venue"
},
  "geometry": {"coordinates":[5.640335083,50.676990509],"type":"Point"}
}