{
  "type": "Feature",
  "properties": {
    "iso:country":"BE",
    "sg:address":"Kriktestraat 9",
    "sg:city":"Lokeren",
    "sg:classifiers":[
        {
            "category":"Home & Garden",
            "subcategory":"Home Furnishings",
            "type":"Retail Goods"
        }
    ],
    "sg:phone":"+32 9 348 25 87",
    "sg:postcode":"9160",
    "sg:province":"Oost-Vlaanderen",
    "sg:tags":[
        "fitting"
    ],
    "wof:name":"Buisgro Bvba",
    "wof:placetype":"venue"
},
  "geometry": {"coordinates":[3.9981799126,51.1256713867],"type":"Point"}
}