{
  "type": "Feature",
  "properties": {
    "addr:full":"Breughelstraat 18 Neerpelt Limburg 3910",
    "addr:housenumber":"18",
    "addr:postcode":"3910",
    "addr:street":"Breughelstraat",
    "iso:country":"BE",
    "sg:address":"Breughelstraat 18",
    "sg:city":"Neerpelt",
    "sg:orig_category":"Metaalbehandeling and -bekleding",
    "sg:phone":"+32 11 66 29 90",
    "sg:postcode":"3910",
    "sg:province":"Limburg",
    "wof:name":"Van Lindt M",
    "wof:placetype":"venue"
},
  "geometry": {"coordinates":[5.4431500435,51.1920700073],"type":"Point"}
}