{
  "type": "Feature",
  "properties": {
    "addr:full":"Burgemeester Henrylaan 24 Dilsen-stokkem (elen) Limburg 3650",
    "addr:housenumber":"24",
    "addr:postcode":"3650",
    "addr:street":"Burgemeester Henrylaan;Elen Limburg",
    "iso:country":"BE",
    "sg:address":"Burgemeester Henrylaan 24",
    "sg:city":"Dilsen-stokkem (elen)",
    "sg:classifiers":[
        {
            "category":"Bars & Pubs",
            "type":"Food & Drink"
        }
    ],
    "sg:phone":"+32 89 75 52 42",
    "sg:postcode":"3650",
    "sg:province":"Limburg",
    "wof:name":"Fort (het)",
    "wof:placetype":"venue"
},
  "geometry": {"coordinates":[5.7337231636,51.0554046631],"type":"Point"}
}