{
  "type": "Feature",
  "properties": {
    "addr:full":"Leeuwkensweg 18 Schilde Antwerpen 2970",
    "addr:housenumber":"18",
    "addr:postcode":"2970",
    "addr:street":"Leeuwkensweg",
    "iso:country":"BE",
    "sg:address":"Leeuwkensweg 18",
    "sg:city":"Schilde",
    "sg:orig_category":"Sportterreinen and installaties behalve sportcentra",
    "sg:phone":"+32 3 385 85 72",
    "sg:postcode":"2970",
    "sg:province":"Antwerpen",
    "wof:name":"Pony Club",
    "wof:placetype":"venue"
},
  "geometry": {"coordinates":[4.5997419357,51.2292976379],"type":"Point"}
}