{
  "type": "Feature",
  "properties": {
    "addr:full":"Rue Du Sablon 13 Bastogne Luxembourg 6600",
    "addr:housenumber":"13",
    "addr:postcode":"6600",
    "addr:street":"Rue Du Sablon",
    "iso:country":"BE",
    "sg:address":"Rue Du Sablon 13",
    "sg:city":"Bastogne",
    "sg:orig_category":"Dameskledingzaken Herenkledingzaken",
    "sg:phone":"+32 61 21 11 25",
    "sg:postcode":"6600",
    "sg:province":"Luxembourg",
    "wof:name":"Maison Damas",
    "wof:placetype":"venue"
},
  "geometry": {"coordinates":[5.7159972191,50.0011749268],"type":"Point"}
}