{
  "type": "Feature",
  "properties": {
    "iso:country":"BE",
    "sg:address":"Rue 3 Villes 70",
    "sg:city":"La Roche-en-ardenne",
    "sg:orig_category":"Diverse voedingsmiddelen Gh",
    "sg:phone":"+32 84 43 31 34",
    "sg:postcode":"6980",
    "sg:province":"Luxembourg",
    "wof:name":"Le Val D'herlin",
    "wof:placetype":"venue"
},
  "geometry": {"coordinates":[5.5757198334,50.1831130981],"type":"Point"}
}