{
  "type": "Feature",
  "properties": {
    "iso:country":"BE",
    "sg:address":"Rue Du Voisin 75",
    "sg:city":"Sambreville",
    "sg:orig_category":"Paramedische behandelingen",
    "sg:phone":"+32 71 76 06 26",
    "sg:postcode":"5060",
    "sg:province":"Namur",
    "wof:name":"P. Debaty",
    "wof:placetype":"venue"
},
  "geometry": {"coordinates":[4.6285200119,50.4448738098],"type":"Point"}
}