{
  "type": "Feature",
  "properties": {
    "addr:full":"Anna Bijnslaan 20 Kortrijk West-Vlaanderen 8500",
    "addr:housenumber":"20",
    "addr:postcode":"8500",
    "addr:street":"Anna Bijnslaan",
    "iso:country":"BE",
    "sg:address":"Anna Bijnslaan 20",
    "sg:city":"Kortrijk",
    "sg:classifiers":[
        {
            "category":"Manufacturing",
            "subcategory":"Chemicals & Compounds",
            "type":"Manufacturing & Wholesale Goods"
        }
    ],
    "sg:phone":"+32 56 20 45 66",
    "sg:postcode":"8500",
    "sg:province":"West-Vlaanderen",
    "sg:tags":[
        "pharmaceutical",
        "product"
    ],
    "wof:name":"R & D Nv",
    "wof:placetype":"venue"
},
  "geometry": {"coordinates":[3.2968900204,50.7973327637],"type":"Point"}
}