{
  "type": "Feature",
  "properties": {
    "addr:full":"Holt 91 Bilzen (beverst) Limburg 3740",
    "addr:housenumber":"91",
    "addr:postcode":"3740",
    "addr:street":"Holt",
    "iso:country":"BE",
    "sg:address":"Holt 91",
    "sg:city":"Bilzen (beverst)",
    "sg:classifiers":[
        {
            "category":"Bars & Pubs",
            "type":"Food & Drink"
        }
    ],
    "sg:phone":"+32 89 41 27 66",
    "sg:postcode":"3740",
    "sg:province":"Limburg",
    "sg:tags":[
        "tavern"
    ],
    "wof:name":"De Kleyne Laer",
    "wof:placetype":"venue"
},
  "geometry": {"coordinates":[5.4801621437,50.8878669739],"type":"Point"}
}