{
  "type": "Feature",
  "properties": {
    "iso:country":"BE",
    "sg:address":"Rue De Tawes 53",
    "sg:city":"Li\u00c8ge",
    "sg:orig_category":"Dansscholen",
    "sg:phone":"+32 4 226 75 54",
    "sg:postcode":"4000",
    "sg:province":"Li\u00e8ge",
    "wof:name":"Chantal Camus",
    "wof:placetype":"venue"
},
  "geometry": {"coordinates":[5.5725669861,50.6572303772],"type":"Point"}
}