{
  "type": "Feature",
  "properties": {
    "addr:full":"Nobelstraat 105 Tremelo Vlaams-Brabant 3128",
    "addr:housenumber":"105",
    "addr:postcode":"3128",
    "addr:street":"Nobelstraat",
    "iso:country":"BE",
    "sg:address":"Nobelstraat 105",
    "sg:city":"Tremelo",
    "sg:orig_category":"Film-, tv- and videoproductie",
    "sg:phone":"+32 16 52 01 89",
    "sg:postcode":"3128",
    "sg:province":"Vlaams-Brabant",
    "wof:name":"Marc Convents",
    "wof:placetype":"venue"
},
  "geometry": {"coordinates":[4.7461929321,51.0046386719],"type":"Point"}
}