{
  "type": "Feature",
  "properties": {
    "iso:country":"BE",
    "sg:address":"Geurtsestraat 5",
    "sg:city":"Malle",
    "sg:orig_category":"Installation de menuiserie en bois and plastique",
    "sg:phone":"+32 3 312 44 82",
    "sg:postcode":"2390",
    "sg:province":"Antwerpen",
    "wof:name":"Georges De Bie",
    "wof:placetype":"venue"
},
  "geometry": {"coordinates":[4.7420978546,51.3078536987],"type":"Point"}
}