{
  "type": "Feature",
  "properties": {
    "addr:full":"Neerwindenstraat 52 Landen (neerwinden) Vlaams-Brabant 3400",
    "addr:housenumber":"52",
    "addr:postcode":"3400",
    "addr:street":"Neerwindenstraat",
    "iso:country":"BE",
    "sg:address":"Neerwindenstraat 52",
    "sg:city":"Landen (neerwinden)",
    "sg:classifiers":[
        {
            "category":"Retail",
            "subcategory":"Auto Repair",
            "type":"Services"
        }
    ],
    "sg:phone":"+32 16 78 80 93",
    "sg:postcode":"3400",
    "sg:province":"Vlaams-Brabant",
    "sg:tags":[
        "garage"
    ],
    "wof:name":"Opel Garage Soers Bvba",
    "wof:placetype":"venue"
},
  "geometry": {"coordinates":[5.0393280983,50.7669868469],"type":"Point"}
}