{
  "type": "Feature",
  "properties": {
    "addr:full":"Roeselaarsestraat 354 Izegem West-Vlaanderen 8870",
    "addr:housenumber":"354",
    "addr:postcode":"8870",
    "addr:street":"Roeselaarsestraat",
    "iso:country":"BE",
    "sg:address":"Roeselaarsestraat 354",
    "sg:city":"Izegem",
    "sg:orig_category":"Non-Classified Establishments",
    "sg:phone":"+32 51 30 40 29",
    "sg:postcode":"8870",
    "sg:province":"West-Vlaanderen",
    "wof:name":"Verfaillie M",
    "wof:placetype":"venue"
},
  "geometry": {"coordinates":[3.1975069046,50.9223899841],"type":"Point"}
}