{
  "type": "Feature",
  "properties": {
    "iso:country":"BE",
    "sg:address":"Rijnrode 17a",
    "sg:city":"Bekkevoort",
    "sg:orig_category":"Erotische- and Escortediensten",
    "sg:phone":"+32 494 04 66 79",
    "sg:postcode":"3460",
    "sg:province":"Vlaams-Brabant",
    "wof:name":"Hans",
    "wof:placetype":"venue"
},
  "geometry": {"coordinates":[5.0407600403,50.933719635],"type":"Point"}
}