{
  "type": "Feature",
  "properties": {
    "iso:country":"BE",
    "sg:address":"Rue De Hotton 2",
    "sg:city":"Rendeux",
    "sg:orig_category":"Fietsen Tuinbenodigdheden",
    "sg:phone":"+32 84 47 72 77",
    "sg:postcode":"6987",
    "sg:province":"Luxembourg",
    "wof:name":"Daniel Verdin",
    "wof:placetype":"venue"
},
  "geometry": {"coordinates":[5.507900238,50.2360610962],"type":"Point"}
}