{
  "type": "Feature",
  "properties": {
    "addr:full":"Lambroekstraat 25 Wetteren Oost-Vlaanderen 9230",
    "addr:housenumber":"25",
    "addr:postcode":"9230",
    "addr:street":"Lambroekstraat",
    "iso:country":"BE",
    "sg:address":"Lambroekstraat 25",
    "sg:city":"Wetteren",
    "sg:orig_category":"Plaatsen van vloer- and muurbekleding",
    "sg:phone":"+32 9 369 57 03",
    "sg:postcode":"9230",
    "sg:province":"Oost-Vlaanderen",
    "wof:name":"Willy Lievens",
    "wof:placetype":"venue"
},
  "geometry": {"coordinates":[3.8855400085,51.0070304871],"type":"Point"}
}