{
  "type": "Feature",
  "properties": {
    "iso:country":"BE",
    "sg:address":"Rue De L'eau Noire 33",
    "sg:city":"Chimay",
    "sg:orig_category":"Loodgieterij, verwarming and sanitaire installaties",
    "sg:phone":"+32 60 37 75 01",
    "sg:postcode":"6464",
    "sg:province":"Hainaut",
    "wof:name":"Ets. Fran\u00c7ois",
    "wof:placetype":"venue"
},
  "geometry": {"coordinates":[4.4201798439,49.9481506348],"type":"Point"}
}