{
  "type": "Feature",
  "properties": {
    "iso:country":"BE",
    "sg:address":"Place De L\u00b4equerre 33",
    "sg:city":"Ottignies-louvain-la-neuve",
    "sg:orig_category":"Epiceries",
    "sg:phone":"+32 10 45 47 24",
    "sg:postcode":"1348",
    "sg:province":"Brabant Wallon",
    "wof:name":"E. Lamya",
    "wof:placetype":"venue"
},
  "geometry": {"coordinates":[4.6097669601,50.6640777588],"type":"Point"}
}