{
  "type": "Feature",
  "properties": {
    "iso:country":"BE",
    "sg:address":"Hengelhoefseweg 9",
    "sg:city":"Zonhoven",
    "sg:orig_category":"Kampeerterreinen",
    "sg:phone":"+32 11 81 71 40",
    "sg:postcode":"3520",
    "sg:province":"Limburg",
    "wof:name":"Camping holsteenbron",
    "wof:placetype":"venue"
},
  "geometry": {"coordinates":[5.4259052277,50.9980010986],"type":"Point"}
}