{
  "type": "Feature",
  "properties": {
    "iso:country":"BE",
    "sg:address":"Chauss\u00e9e De Charleroi 92",
    "sg:city":"Genappe (loupoigne)",
    "sg:classifiers":[
        {
            "category":"Building & Trades",
            "subcategory":"Landscaping Services",
            "type":"Services"
        }
    ],
    "sg:phone":"+32 67 77 39 84",
    "sg:postcode":"1471",
    "sg:province":"Brabant Wallon",
    "sg:tags":[
        "-",
        "lopping",
        "work",
        "tree",
        "felling"
    ],
    "wof:name":"Emanuele T",
    "wof:placetype":"venue"
},
  "geometry": {"coordinates":[4.453783989,50.6014175415],"type":"Point"}
}