{
  "type": "Feature",
  "properties": {
    "addr:full":"Rue Long Pr\u00e9at 2a Charleroi (gosselies) Hainaut 6041",
    "addr:housenumber":"2a",
    "addr:postcode":"6041",
    "addr:street":"Rue Long Pre\u0301At",
    "iso:country":"BE",
    "sg:address":"Rue Long Pr\u00e9at 2a",
    "sg:city":"Charleroi (gosselies)",
    "sg:classifiers":[
        {
            "category":"Retail",
            "subcategory":"Auto Repair",
            "type":"Services"
        }
    ],
    "sg:phone":"+32 71 37 15 93",
    "sg:postcode":"6041",
    "sg:province":"Hainaut",
    "sg:tags":[
        "automobile-body"
    ],
    "wof:name":"Gabriel Sport Cars",
    "wof:placetype":"venue"
},
  "geometry": {"coordinates":[4.44535923,50.4697761536],"type":"Point"}
}