{
  "type": "Feature",
  "properties": {
    "iso:country":"BE",
    "sg:address":"Rue Des Forgerons 102",
    "sg:city":"Charleroi",
    "sg:orig_category":"Emballages en plastique Fab. Emballages en papier and carton Fab",
    "sg:phone":"+32 71 36 76 75",
    "sg:postcode":"6001",
    "sg:province":"Hainaut",
    "wof:name":"Papershop",
    "wof:placetype":"venue"
},
  "geometry": {"coordinates":[4.4531960487,50.3923377991],"type":"Point"}
}