{
  "type": "Feature",
  "properties": {
    "iso:country":"BE",
    "sg:address":"Pluime 12",
    "sg:city":"Beernem",
    "sg:classifiers":[
        {
            "category":"Utilities",
            "subcategory":"Natural Gas",
            "type":"Services"
        }
    ],
    "sg:phone":"+32 50 78 00 98",
    "sg:postcode":"8730",
    "sg:province":"West-Vlaanderen",
    "sg:tags":[
        "blacksmith"
    ],
    "wof:name":"Baute",
    "wof:placetype":"venue"
},
  "geometry": {"coordinates":[3.3740210533,51.1402015686],"type":"Point"}
}