{
  "type": "Feature",
  "properties": {
    "addr:full":"Maastrichtersteenweg 220 Riemst Limburg 3770",
    "addr:housenumber":"220",
    "addr:postcode":"3770",
    "addr:street":"Maastrichtersteenweg",
    "iso:country":"BE",
    "sg:address":"Maastrichtersteenweg 220",
    "sg:city":"Riemst",
    "sg:orig_category":"Banken and kredietinstellingen",
    "sg:phone":"+32 12 45 18 49",
    "sg:postcode":"3770",
    "sg:province":"Limburg",
    "wof:name":"Kbc",
    "wof:placetype":"venue"
},
  "geometry": {"coordinates":[5.612569809,50.8188209534],"type":"Point"}
}