{
  "type": "Feature",
  "properties": {
    "iso:country":"BE",
    "sg:address":"Rue Louis Pasteur 95",
    "sg:city":"Li\u00e8ge 1 (grivegn\u00e9e)",
    "sg:classifiers":[
        {
            "category":"Building & Trades",
            "subcategory":"Construction",
            "type":"Services"
        }
    ],
    "sg:phone":"+32 4 365 66 50",
    "sg:postcode":"4030",
    "sg:province":"Li\u00e8ge",
    "sg:tags":[
        "surveyor",
        "-"
    ],
    "wof:name":"Lassance R",
    "wof:placetype":"venue"
},
  "geometry": {"coordinates":[5.6436281204,50.6265144348],"type":"Point"}
}