{
  "type": "Feature",
  "properties": {
    "iso:country":"BE",
    "sg:address":"Zandhovensteenweg 98",
    "sg:city":"Ranst",
    "sg:orig_category":"Imprimeries and copyshops",
    "sg:phone":"+32 3 383 14 02",
    "sg:postcode":"2520",
    "sg:province":"Antwerpen",
    "wof:name":"Petrus Tibos",
    "wof:placetype":"venue"
},
  "geometry": {"coordinates":[4.6125478745,51.2116241455],"type":"Point"}
}