{
  "type": "Feature",
  "properties": {
    "iso:country":"BE",
    "sg:address":"Otterstraat 92",
    "sg:city":"Turnhout",
    "sg:orig_category":"Herstelling aan huis van huishoudartikelen Herstelling leer and schoeisel Herstellingswinkels voor d",
    "sg:phone":"+32 14 42 38 23",
    "sg:postcode":"2300",
    "sg:province":"Antwerpen",
    "wof:name":"Guns",
    "wof:placetype":"venue"
},
  "geometry": {"coordinates":[4.9534502029,51.32213974],"type":"Point"}
}