{
  "type": "Feature",
  "properties": {
    "iso:country":"BE",
    "sg:address":"Groenestraat 51",
    "sg:city":"Ruiselede",
    "sg:orig_category":"Woningbouw",
    "sg:phone":"+32 51 68 76 26",
    "sg:postcode":"8755",
    "sg:province":"West-Vlaanderen",
    "wof:name":"Geert De Graeve",
    "wof:placetype":"venue"
},
  "geometry": {"coordinates":[3.3939089775,51.0342102051],"type":"Point"}
}