{
  "type": "Feature",
  "properties": {
    "iso:country":"BE",
    "sg:address":"Avenue J Mermoz 1",
    "sg:city":"Charleroi",
    "sg:orig_category":"Jardinage",
    "sg:phone":"+32 71 25 60 36",
    "sg:postcode":"6041",
    "sg:province":"Hainaut",
    "wof:name":"Geoter Sa",
    "wof:placetype":"venue"
},
  "geometry": {"coordinates":[4.4788680077,50.475276947],"type":"Point"}
}