{
  "type": "Feature",
  "properties": {
    "addr:full":"Hofveldstraat 13 Maarkedal (schorisse) Oost-Vlaanderen 9688",
    "addr:housenumber":"13",
    "addr:postcode":"9688",
    "addr:street":"Hofveldstraat",
    "iso:country":"BE",
    "sg:address":"Hofveldstraat 13",
    "sg:city":"Maarkedal (schorisse)",
    "sg:classifiers":[
        {
            "category":"Banks & Credit Unions",
            "subcategory":"Financial Services",
            "type":"Services"
        }
    ],
    "sg:phone":"+32 55 45 53 83",
    "sg:postcode":"9688",
    "sg:province":"Oost-Vlaanderen",
    "sg:tags":[
        "loan",
        "mortgage"
    ],
    "wof:name":"Clement C",
    "wof:placetype":"venue"
},
  "geometry": {"coordinates":[3.6776850224,50.8049926758],"type":"Point"}
}