{
  "type": "Feature",
  "properties": {
    "iso:country":"BE",
    "sg:address":"R. Borremansstraat 21",
    "sg:city":"Huldenberg",
    "sg:orig_category":"Fotografen and fotostudio's",
    "sg:phone":"+32 2 687 51 17",
    "sg:postcode":"3040",
    "sg:province":"Vlaams-Brabant",
    "wof:name":"Agneessens Light Art",
    "wof:placetype":"venue"
},
  "geometry": {"coordinates":[4.5889220238,50.7899551392],"type":"Point"}
}