{
  "type": "Feature",
  "properties": {
    "addr:full":"Stokstormestraat 12 Deinze Oost-Vlaanderen 9800",
    "addr:housenumber":"12",
    "addr:postcode":"9800",
    "addr:street":"Stokstormestraat",
    "iso:country":"BE",
    "sg:address":"Stokstormestraat 12",
    "sg:city":"Deinze",
    "sg:orig_category":"Varkenskwekers",
    "sg:phone":"+32 9 386 11 01",
    "sg:postcode":"9800",
    "sg:province":"Oost-Vlaanderen",
    "wof:name":"Kestens Gunther & Liliana",
    "wof:placetype":"venue"
},
  "geometry": {"coordinates":[3.530174017,50.9863166809],"type":"Point"}
}