{
  "type": "Feature",
  "properties": {
    "addr:full":"Misweg 22 Oudenaarde Oost-Vlaanderen 9700",
    "addr:housenumber":"22",
    "addr:postcode":"9700",
    "addr:street":"Misweg",
    "iso:country":"BE",
    "sg:address":"Misweg 22",
    "sg:city":"Oudenaarde",
    "sg:classifiers":[
        {
            "category":"Professional",
            "subcategory":"Art Services",
            "type":"Services"
        }
    ],
    "sg:phone":"+32 55 31 08 18",
    "sg:postcode":"9700",
    "sg:province":"Oost-Vlaanderen",
    "sg:tags":[
        "children's",
        "animation"
    ],
    "wof:name":"Prijzenpot (de)",
    "wof:placetype":"venue"
},
  "geometry": {"coordinates":[3.6242570877,50.8717155457],"type":"Point"}
}