{
  "type": "Feature",
  "properties": {
    "iso:country":"BE",
    "sg:address":"Rue Destr\u00c9e 154",
    "sg:city":"Florennes",
    "sg:orig_category":"V\u00e9hicules automobiles. Entretien and r\u00e9parations de voitures",
    "sg:phone":"+32 71 74 40 92",
    "sg:postcode":"6250",
    "sg:province":"Hainaut",
    "wof:name":"Bauraing J",
    "wof:placetype":"venue"
},
  "geometry": {"coordinates":[4.5706348419,50.4195671082],"type":"Point"}
}