{
  "type": "Feature",
  "properties": {
    "iso:country":"BE",
    "sg:address":"Chauss\u00e9e De Nivelles 52",
    "sg:city":"Ittre (haut-ittre)",
    "sg:orig_category":"Non-Classified Establishments",
    "sg:phone":"+32 2 366 02 69",
    "sg:postcode":"1461",
    "sg:province":"Brabant Wallon",
    "wof:name":"Baptista",
    "wof:placetype":"venue"
},
  "geometry": {"coordinates":[4.3013467789,50.659538269],"type":"Point"}
}