{
  "type": "Feature",
  "properties": {
    "addr:full":"Dijkstraat 14 Zandhoven Antwerpen 2240",
    "addr:housenumber":"14",
    "addr:postcode":"2240",
    "addr:street":"Dijkstraat",
    "iso:country":"BE",
    "sg:address":"Dijkstraat 14",
    "sg:city":"Zandhoven",
    "sg:classifiers":[
        {
            "category":"Fast Food",
            "type":"Food & Drink"
        }
    ],
    "sg:phone":"+32 3 464 04 33",
    "sg:postcode":"2240",
    "sg:province":"Antwerpen",
    "sg:tags":[
        "\u00c0",
        "restaurants",
        "emporter",
        "restaurant"
    ],
    "wof:name":"'t Renteniershuis",
    "wof:placetype":"venue"
},
  "geometry": {"coordinates":[4.6640591621,51.1925125122],"type":"Point"}
}