{
  "type": "Feature",
  "properties": {
    "addr:full":"Rue De La Station De La Sambre 6 Mont-sur-marchienne Hainaut 6032",
    "addr:housenumber":"6",
    "addr:postcode":"6032",
    "addr:street":"Rue De La Station De La Sambre",
    "iso:country":"BE",
    "sg:address":"Rue De La Station De La Sambre 6",
    "sg:city":"Mont-sur-marchienne",
    "sg:classifiers":[
        {
            "category":"Wholesale",
            "subcategory":"Music Publishers",
            "type":"Manufacturing & Wholesale Goods"
        }
    ],
    "sg:phone":"+32 71 36 26 72",
    "sg:postcode":"6032",
    "sg:province":"Hainaut",
    "sg:tags":[
        "finishing",
        "paper",
        "processing"
    ],
    "wof:name":"Emile Sanglier S.a.",
    "wof:placetype":"venue"
},
  "geometry": {"coordinates":[4.403854847,50.3877906799],"type":"Point"}
}