{
  "type": "Feature",
  "properties": {
    "addr:full":"Kattestaartstraat 40 Zutendaal Limburg 3690",
    "addr:housenumber":"40",
    "addr:postcode":"3690",
    "addr:street":"Kattestaartstraat",
    "iso:country":"BE",
    "sg:address":"Kattestaartstraat 40",
    "sg:city":"Zutendaal",
    "sg:classifiers":[
        {
            "category":"Building & Trades",
            "subcategory":"Construction",
            "type":"Services"
        }
    ],
    "sg:phone":"+32 89 61 28 73",
    "sg:postcode":"3690",
    "sg:province":"Limburg",
    "sg:tags":[
        "carpenter"
    ],
    "wof:name":"Hansen R",
    "wof:placetype":"venue"
},
  "geometry": {"coordinates":[5.5698738098,50.9362030029],"type":"Point"}
}