{
  "type": "Feature",
  "properties": {
    "addr:full":"Oplintersesteenweg 20 Glabbeek Vlaams-Brabant 3380",
    "addr:housenumber":"20",
    "addr:postcode":"3380",
    "addr:street":"Oplintersesteenweg",
    "iso:country":"BE",
    "sg:address":"Oplintersesteenweg 20",
    "sg:city":"Glabbeek",
    "sg:orig_category":"Fruitteelt",
    "sg:phone":"+32 16 77 11 45",
    "sg:postcode":"3380",
    "sg:province":"Vlaams-Brabant",
    "wof:name":"Andre Vanherwegen",
    "wof:placetype":"venue"
},
  "geometry": {"coordinates":[4.9657549858,50.8473243713],"type":"Point"}
}