{
  "type": "Feature",
  "properties": {
    "iso:country":"BE",
    "sg:address":"Heidebaan 52",
    "sg:city":"Sint-niklaas",
    "sg:classifiers":[
        {
            "category":"Food & Beverages",
            "subcategory":"Dairy",
            "type":"Retail Goods"
        }
    ],
    "sg:phone":"+32 3 777 50 88",
    "sg:postcode":"9100",
    "sg:province":"Oost-Vlaanderen",
    "sg:tags":[
        "product",
        "-"
    ],
    "wof:name":"De Ryck R",
    "wof:placetype":"venue"
},
  "geometry": {"coordinates":[4.1781420708,51.1693344116],"type":"Point"}
}