{
  "type": "Feature",
  "properties": {
    "addr:full":"Zultseweg 234 Waregem West-Vlaanderen 8790",
    "addr:housenumber":"234",
    "addr:postcode":"8790",
    "iso:country":"BE",
    "sg:address":"Zultseweg 234",
    "sg:city":"Waregem",
    "sg:classifiers":[
        {
            "category":"Food & Beverages",
            "subcategory":"Groceries & Convenience Stores",
            "type":"Retail Goods"
        }
    ],
    "sg:phone":"+32 56 60 29 77",
    "sg:postcode":"8790",
    "sg:province":"West-Vlaanderen",
    "sg:tags":[
        "product",
        "related"
    ],
    "wof:name":"Recutex Nv",
    "wof:placetype":"venue"
},
  "geometry": {"coordinates":[3.4466660023,50.9022369385],"type":"Point"}
}