{
  "type": "Feature",
  "properties": {
    "iso:country":"BE",
    "sg:address":"Korte Begijnenstraat 23",
    "sg:city":"Turnhout",
    "sg:classifiers":[
        {
            "category":"Shopping",
            "subcategory":"Clothing, Apparel, & Fashions",
            "type":"Retail Goods"
        }
    ],
    "sg:phone":"+32 14 42 32 74",
    "sg:postcode":"2300",
    "sg:province":"Antwerpen",
    "sg:tags":[
        "purchase",
        "clothing",
        "-",
        "sale",
        "second-hand"
    ],
    "wof:name":"Harlekyn (de)",
    "wof:placetype":"venue"
},
  "geometry": {"coordinates":[4.9483180046,51.3261451721],"type":"Point"}
}