{
  "type": "Feature",
  "properties": {
    "iso:country":"BE",
    "sg:address":"Brusselsesteenweg 57-59",
    "sg:city":"Ledeberg",
    "sg:orig_category":"Advocaten and juridische adviseurs Balie van Gent",
    "sg:phone":"+32 9 231 21 25",
    "sg:postcode":"9050",
    "sg:province":"Oost-Vlaanderen",
    "wof:name":"Schepens Danny",
    "wof:placetype":"venue"
},
  "geometry": {"coordinates":[3.7423679829,51.0410766602],"type":"Point"}
}