{
  "type": "Feature",
  "properties": {
    "iso:country":"BE",
    "sg:address":"Rue Lamberts 57",
    "sg:city":"Welkenraedt",
    "sg:classifiers":[
        {
            "category":"Shopping",
            "subcategory":"Clothing, Apparel, & Fashions",
            "type":"Retail Goods"
        }
    ],
    "sg:phone":"+32 87 89 00 67",
    "sg:postcode":"4840",
    "sg:province":"Li\u00e8ge",
    "sg:tags":[
        "-",
        "haberdashery"
    ],
    "wof:name":"Fil Dore (le)",
    "wof:placetype":"venue"
},
  "geometry": {"coordinates":[5.9763679504,50.6606254578],"type":"Point"}
}