{
  "type": "Feature",
  "properties": {
    "addr:full":"Brugsesteenweg 12 Kortrijk West-Vlaanderen 8500",
    "addr:housenumber":"12",
    "addr:postcode":"8500",
    "addr:street":"Brugsesteenweg",
    "iso:country":"BE",
    "sg:address":"Brugsesteenweg 12",
    "sg:city":"Kortrijk",
    "sg:classifiers":[
        {
            "category":"Restaurant",
            "type":"Food & Drink"
        }
    ],
    "sg:phone":"+32 56 35 00 55",
    "sg:postcode":"8500",
    "sg:province":"West-Vlaanderen",
    "sg:tags":[
        "de",
        "organisation",
        "\u00e0",
        "fast",
        "catering",
        "emporter",
        "f\u00eates",
        "restaurants"
    ],
    "wof:name":"Jachthuis",
    "wof:placetype":"venue"
},
  "geometry": {"coordinates":[3.2623169422,50.8366203308],"type":"Point"}
}