{
  "type": "Feature",
  "properties": {
    "iso:country":"BE",
    "sg:address":"Hasseltsebaan 185",
    "sg:city":"Hechtel-eksel (hechtel)",
    "sg:classifiers":[
        {
            "category":"Wholesale",
            "subcategory":"Meat",
            "type":"Manufacturing & Wholesale Goods"
        }
    ],
    "sg:phone":"+32 11 73 17 34",
    "sg:postcode":"3940",
    "sg:province":"Limburg",
    "sg:tags":[
        "whol",
        "-"
    ],
    "wof:name":"Carmans Bvba",
    "wof:placetype":"venue"
},
  "geometry": {"coordinates":[5.3750371933,51.0968093872],"type":"Point"}
}