{
  "type": "Feature",
  "properties": {
    "iso:country":"BE",
    "sg:address":"Turnhoutsebaan 204",
    "sg:city":"Dessel",
    "sg:classifiers":[
        {
            "category":"Retail",
            "subcategory":"Auto Repair",
            "type":"Services"
        }
    ],
    "sg:phone":"+32 14 37 75 66",
    "sg:postcode":"2480",
    "sg:province":"Antwerpen",
    "sg:tags":[
        "garage"
    ],
    "wof:name":"Van De Pol R",
    "wof:placetype":"venue"
},
  "geometry": {"coordinates":[5.104118824,51.2544555664],"type":"Point"}
}