{
  "type": "Feature",
  "properties": {
    "addr:full":"Diestsesteenweg 311 Kessel-lo Vlaams-Brabant 3010",
    "addr:housenumber":"311",
    "addr:postcode":"3010",
    "addr:street":"Diestsesteenweg",
    "iso:country":"BE",
    "sg:address":"Diestsesteenweg 311",
    "sg:city":"Kessel-lo",
    "sg:orig_category":"Beautyfarms, relaxatie and lichamelijk welzijn Schoonheidssalons",
    "sg:phone":"+32 16 25 90 54",
    "sg:postcode":"3010",
    "sg:province":"Vlaams-Brabant",
    "wof:name":"Schoonheidssalon Carmen",
    "wof:placetype":"venue"
},
  "geometry": {"coordinates":[4.7286992073,50.8846702576],"type":"Point"}
}