{
  "type": "Feature",
  "properties": {
    "addr:full":"Rue G\u00c9n\u00c9ral-borlon 26 Erezee Luxembourg 6997",
    "addr:housenumber":"26",
    "addr:postcode":"6997",
    "addr:street":"Rue Ge\u0301Ne\u0301Ral-Borlon",
    "iso:country":"BE",
    "sg:address":"Rue G\u00c9n\u00c9ral-borlon 26",
    "sg:city":"Erezee",
    "sg:orig_category":"V\u00e9hicules automobiles. Entretien and r\u00e9parations de voitures",
    "sg:phone":"+32 86 47 77 35",
    "sg:postcode":"6997",
    "sg:province":"Luxembourg",
    "wof:name":"Garage Collard Pol",
    "wof:placetype":"venue"
},
  "geometry": {"coordinates":[5.562016964,50.2894973755],"type":"Point"}
}