{
  "type": "Feature",
  "properties": {
    "addr:full":"Nieuwstraat 50 Maldegem Oost-Vlaanderen 9990",
    "addr:housenumber":"50",
    "addr:postcode":"9990",
    "addr:street":"Nieuwstraat",
    "iso:country":"BE",
    "sg:address":"Nieuwstraat 50",
    "sg:city":"Maldegem",
    "sg:orig_category":"V\u00eatements pour b\u00e9b\u00e9s and enfants. V\u00eatements pour Dames. Articles pour b\u00e9b\u00e9s",
    "sg:phone":"+32 50 71 28 88",
    "sg:postcode":"9990",
    "sg:province":"Oost-Vlaanderen",
    "wof:name":"Pr\u00c9maman",
    "wof:placetype":"venue"
},
  "geometry": {"coordinates":[3.4465000629,51.2070503235],"type":"Point"}
}