{
  "type": "Feature",
  "properties": {
    "addr:full":"Parijsstr 52 Leuven Vlaams-Brabant 3000",
    "addr:housenumber":"52",
    "addr:postcode":"3000",
    "addr:street":"Parijsstr",
    "iso:country":"BE",
    "sg:address":"Parijsstr 52",
    "sg:city":"Leuven",
    "sg:classifiers":[
        {
            "category":"Banks & Credit Unions",
            "subcategory":"Bank",
            "type":"Services"
        }
    ],
    "sg:postcode":"3000",
    "sg:province":"Vlaams-Brabant",
    "wof:name":"Cerafund Management Nv",
    "wof:placetype":"venue"
},
  "geometry": {"coordinates":[4.6956720352,50.8805732727],"type":"Point"}
}