{
  "type": "Feature",
  "properties": {
    "addr:full":"Grand Rue 46 Mons Hainaut 7000",
    "addr:housenumber":"46",
    "addr:postcode":"7000",
    "addr:street":"Grand Rue;Hainaut",
    "iso:country":"BE",
    "sg:address":"Grand Rue 46",
    "sg:city":"Mons",
    "sg:classifiers":[
        {
            "category":"Bars & Pubs",
            "type":"Food & Drink"
        }
    ],
    "sg:phone":"+32 65 84 55 24",
    "sg:postcode":"7000",
    "sg:province":"Hainaut",
    "wof:name":"Tube (le)",
    "wof:placetype":"venue"
},
  "geometry": {"coordinates":[3.9492590427,50.4511756897],"type":"Point"}
}