{
  "type": "Feature",
  "properties": {
    "iso:country":"BE",
    "sg:address":"Place Albert I 22",
    "sg:city":"Florenville",
    "sg:classifiers":[
        {
            "category":"Bars & Pubs",
            "type":"Food & Drink"
        }
    ],
    "sg:phone":"+32 61 32 96 40",
    "sg:postcode":"6820",
    "sg:province":"Luxembourg",
    "wof:name":"Actuel (l')",
    "wof:placetype":"venue"
},
  "geometry": {"coordinates":[5.3102898598,49.6983985901],"type":"Point"}
}