{
  "type": "Feature",
  "properties": {
    "addr:full":"Romeinsedijk 70 Neerpelt Limburg 3910",
    "addr:housenumber":"70",
    "addr:postcode":"3910",
    "addr:street":"Romeinsedijk",
    "iso:country":"BE",
    "sg:address":"Romeinsedijk 70",
    "sg:city":"Neerpelt",
    "sg:orig_category":"Ordinateurs and \u00e9quipement informatique",
    "sg:phone":"+32 495 25 15 36",
    "sg:postcode":"3910",
    "sg:province":"Limburg",
    "wof:name":"Pascal Verspeek",
    "wof:placetype":"venue"
},
  "geometry": {"coordinates":[5.4589529037,51.2115478516],"type":"Point"}
}