{
  "type": "Feature",
  "properties": {
    "addr:full":"Helmetsesteenweg 380 Schaarbeek/schaerbeek Bruxelles-Capitale 1030",
    "addr:housenumber":"380",
    "addr:postcode":"1030",
    "addr:street":"Helmetsesteenweg",
    "iso:country":"BE",
    "sg:address":"Helmetsesteenweg 380",
    "sg:city":"Schaarbeek/schaerbeek",
    "sg:orig_category":"Maatkleding Fab",
    "sg:phone":"+32 2 216 56 65",
    "sg:postcode":"1030",
    "sg:province":"Bruxelles-Capitale",
    "wof:name":"M Alfano",
    "wof:placetype":"venue"
},
  "geometry": {"coordinates":[4.3921031952,50.8756217957],"type":"Point"}
}