{
  "type": "Feature",
  "properties": {
    "addr:full":"Rue De Beauvechain 43j Beauvechain (tourinnes-la-grosse) Brabant Wallon 1320",
    "addr:housenumber":"43j",
    "addr:postcode":"1320",
    "addr:street":"Rue De Beauvechain;Wallon",
    "iso:country":"BE",
    "sg:address":"Rue De Beauvechain 43j",
    "sg:city":"Beauvechain (tourinnes-la-grosse)",
    "sg:classifiers":[
        {
            "category":"Health Services",
            "subcategory":"Doctor",
            "type":"Services"
        }
    ],
    "sg:phone":"+32 10 86 68 96",
    "sg:postcode":"1320",
    "sg:province":"Brabant Wallon",
    "sg:tags":[
        "medicinephysicians",
        "surgeon"
    ],
    "wof:name":"De Smedt M",
    "wof:placetype":"venue"
},
  "geometry": {"coordinates":[4.7572388649,50.7787055969],"type":"Point"}
}