{
  "type": "Feature",
  "properties": {
    "iso:country":"BE",
    "sg:address":"Heirbaan 109",
    "sg:city":"Lanaken (neerharen)",
    "sg:classifiers":[
        {
            "category":"Home & Garden",
            "subcategory":"Kitchen Supply",
            "type":"Retail Goods"
        }
    ],
    "sg:phone":"+32 89 72 38 76",
    "sg:postcode":"3620",
    "sg:province":"Limburg",
    "sg:tags":[
        "installation"
    ],
    "wof:name":"Beckers L",
    "wof:placetype":"venue"
},
  "geometry": {"coordinates":[5.6850380898,50.9112854004],"type":"Point"}
}