{
  "type": "Feature",
  "properties": {
    "addr:full":"Dendermondsesteenweg 7 Lochristi Oost-Vlaanderen 9080",
    "addr:housenumber":"7",
    "addr:postcode":"9080",
    "addr:street":"Dendermondsesteenweg",
    "iso:country":"BE",
    "sg:address":"Dendermondsesteenweg 7",
    "sg:city":"Lochristi",
    "sg:orig_category":"Plantes and fleurs Gr",
    "sg:phone":"+32 9 355 30 11",
    "sg:postcode":"9080",
    "sg:province":"Oost-Vlaanderen",
    "wof:name":"Goossens Jan",
    "wof:placetype":"venue"
},
  "geometry": {"coordinates":[3.8539719582,51.0523757935],"type":"Point"}
}