{
  "type": "Feature",
  "properties": {
    "addr:full":"Rue De Montigny 66 Charleroi Hainaut 6000",
    "addr:housenumber":"66",
    "addr:postcode":"6000",
    "addr:street":"Rue De Montigny;Hainaut",
    "iso:country":"BE",
    "sg:address":"Rue De Montigny 66",
    "sg:city":"Charleroi",
    "sg:orig_category":"V\u00eatements. Textiles",
    "sg:phone":"+32 71 31 37 44",
    "sg:postcode":"6000",
    "sg:province":"Hainaut",
    "wof:name":"Maison Philippart",
    "wof:placetype":"venue"
},
  "geometry": {"coordinates":[4.4467601776,50.4078216553],"type":"Point"}
}