{
  "type": "Feature",
  "properties": {
    "addr:full":"Rue Xhav\u00e9e 21 Theux (polleur) Li\u00e8ge 4910",
    "addr:housenumber":"21",
    "addr:postcode":"4910",
    "addr:street":"Rue Xhave\u0301E",
    "iso:country":"BE",
    "sg:address":"Rue Xhav\u00e9e 21",
    "sg:city":"Theux (polleur)",
    "sg:classifiers":[
        {
            "category":"Health Services",
            "subcategory":"Health Practitioner",
            "type":"Services"
        }
    ],
    "sg:phone":"+32 87 23 24 95",
    "sg:postcode":"4910",
    "sg:province":"Li\u00e8ge",
    "sg:tags":[
        "physiotherapist"
    ],
    "wof:name":"Wertz Philippe",
    "wof:placetype":"venue"
},
  "geometry": {"coordinates":[5.8130488396,50.5356216431],"type":"Point"}
}