{
  "type": "Feature",
  "properties": {
    "addr:full":"Jozef Van Bogaertstraat 60 Dendermonde (sint-gillis-bij-dendermonde) Oost-Vlaanderen 9200",
    "addr:housenumber":"60",
    "addr:postcode":"9200",
    "addr:street":"Jozef Van Bogaertstraat",
    "iso:country":"BE",
    "sg:address":"Jozef Van Bogaertstraat 60",
    "sg:city":"Dendermonde (sint-gillis-bij-dendermonde)",
    "sg:orig_category":"Non-Classified Establishments",
    "sg:phone":"+32 52 21 55 38",
    "sg:postcode":"9200",
    "sg:province":"Oost-Vlaanderen",
    "wof:name":"Interhealth",
    "wof:placetype":"venue"
},
  "geometry": {"coordinates":[4.1023898125,51.0318984985],"type":"Point"}
}