{
  "type": "Feature",
  "properties": {
    "iso:country":"BE",
    "sg:address":"Waversebaan 35",
    "sg:city":"Oud-heverlee",
    "sg:orig_category":"Woningbouw",
    "sg:phone":"+32 16 40 47 88",
    "sg:postcode":"3050",
    "sg:province":"Vlaams-Brabant",
    "wof:name":"Vandezande Louis",
    "wof:placetype":"venue"
},
  "geometry": {"coordinates":[4.6698861122,50.8426399231],"type":"Point"}
}