{
  "type": "Feature",
  "properties": {
    "addr:full":"Werchtersesteenweg 118 Haacht Vlaams-Brabant 3150",
    "addr:housenumber":"118",
    "addr:postcode":"3150",
    "addr:street":"Werchtersesteenweg",
    "iso:country":"BE",
    "sg:address":"Werchtersesteenweg 118",
    "sg:city":"Haacht",
    "sg:orig_category":"Bouwmaterialen Gh IJzerwaren, bouw- and verfmaterialen",
    "sg:phone":"+32 16 60 34 36",
    "sg:postcode":"3150",
    "sg:province":"Vlaams-Brabant",
    "wof:name":"Van Den Broeck",
    "wof:placetype":"venue"
},
  "geometry": {"coordinates":[4.6502819061,50.9734649658],"type":"Point"}
}