{
  "type": "Feature",
  "properties": {
    "addr:full":"Leopoldstraat 44 Halle Vlaams-Brabant 1500",
    "addr:housenumber":"44",
    "addr:postcode":"1500",
    "addr:street":"Leopoldstraat",
    "iso:country":"BE",
    "sg:address":"Leopoldstraat 44",
    "sg:city":"Halle",
    "sg:orig_category":"Plomberie, chauffage and installations sanitaires",
    "sg:phone":"+32 2 356 99 01",
    "sg:postcode":"1500",
    "sg:province":"Vlaams-Brabant",
    "wof:name":"Standaert A.",
    "wof:placetype":"venue"
},
  "geometry": {"coordinates":[4.2469611168,50.7270736694],"type":"Point"}
}