{
  "type": "Feature",
  "properties": {
    "addr:full":"Pollarebaan 29 Ninove Oost-Vlaanderen 9400",
    "addr:housenumber":"29",
    "addr:postcode":"9400",
    "addr:street":"Pollarebaan",
    "iso:country":"BE",
    "sg:address":"Pollarebaan 29",
    "sg:city":"Ninove",
    "sg:orig_category":"Dakwerken",
    "sg:phone":"+32 479 30 16 23",
    "sg:postcode":"9400",
    "sg:province":"Oost-Vlaanderen",
    "wof:name":"Petrus De Vos En Zoon",
    "wof:placetype":"venue"
},
  "geometry": {"coordinates":[4.0229167938,50.8285675049],"type":"Point"}
}