{
  "type": "Feature",
  "properties": {
    "addr:full":"Industrieweg-noord 1150 Opglabbeek Limburg 3660",
    "addr:postcode":"1150 opglabbeek;3660",
    "iso:country":"BE",
    "sg:address":"Industrieweg-noord 1150",
    "sg:city":"Opglabbeek",
    "sg:classifiers":[
        {
            "category":"Utilities",
            "subcategory":"Telephone",
            "type":"Services"
        }
    ],
    "sg:phone":"+32 89 65 13 70",
    "sg:postcode":"3660",
    "sg:province":"Limburg",
    "sg:tags":[
        "device",
        "electromechanical",
        "assembly",
        "electronic"
    ],
    "wof:name":"Gebroeders De Rijk Belgi\u00eb Nv",
    "wof:placetype":"venue"
},
  "geometry": {"coordinates":[5.5429549217,51.0373573303],"type":"Point"}
}