{
  "type": "Feature",
  "properties": {
    "iso:country":"BE",
    "sg:address":"Gemeenteplein 2",
    "sg:city":"Linkebeek/linkebeek",
    "sg:orig_category":"Overheidsdiensten",
    "sg:phone":"+32 2 380 62 15",
    "sg:postcode":"1630",
    "sg:province":"Vlaams-Brabant",
    "wof:name":"Gemeentebestuur",
    "wof:placetype":"venue"
},
  "geometry": {"coordinates":[4.3362197876,50.7724838257],"type":"Point"}
}