{
  "type": "Feature",
  "properties": {
    "iso:country":"BE",
    "sg:address":"Grande Rue Au Bois 17",
    "sg:city":"Bruxelles (schaerbeek)",
    "sg:classifiers":[
        {
            "category":"Shopping",
            "subcategory":"Crafts & Fabrics",
            "type":"Retail Goods"
        }
    ],
    "sg:phone":"+32 2 245 06 26",
    "sg:postcode":"1030",
    "sg:province":"Bruxelles-Capitale",
    "sg:tags":[
        "ceramic"
    ],
    "wof:name":"Atelier Argile",
    "wof:placetype":"venue"
},
  "geometry": {"coordinates":[4.3848338127,50.8570327759],"type":"Point"}
}