{
  "type": "Feature",
  "properties": {
    "iso:country":"BE",
    "sg:address":"Hendrik Kuijpersstraat 18",
    "sg:city":"Mortsel",
    "sg:classifiers":[
        {
            "category":"Retail",
            "subcategory":"Repair Shop",
            "type":"Services"
        }
    ],
    "sg:phone":"+32 3 480 50 99",
    "sg:postcode":"2640",
    "sg:province":"Antwerpen",
    "sg:tags":[
        "-",
        "clothing",
        "alteration"
    ],
    "wof:name":"Alfaserv",
    "wof:placetype":"venue"
},
  "geometry": {"coordinates":[4.4375767708,51.1768760681],"type":"Point"}
}