{
  "type": "Feature",
  "properties": {
    "addr:full":"Torhoutsesteenweg 172 Oostende West-Vlaanderen 8400",
    "addr:housenumber":"172",
    "addr:postcode":"8400",
    "addr:street":"Torhoutsesteenweg",
    "iso:country":"BE",
    "sg:address":"Torhoutsesteenweg 172",
    "sg:city":"Oostende",
    "sg:classifiers":[
        {
            "category":"Food & Beverages",
            "subcategory":"Groceries & Convenience Stores",
            "type":"Retail Goods"
        }
    ],
    "sg:phone":"+32 59 50 33 31",
    "sg:postcode":"8400",
    "sg:province":"West-Vlaanderen",
    "sg:tags":[
        "grocer"
    ],
    "wof:name":"Top Service",
    "wof:placetype":"venue"
},
  "geometry": {"coordinates":[2.9080839157,51.2200927734],"type":"Point"}
}