{
  "type": "Feature",
  "properties": {
    "iso:country":"BE",
    "sg:address":"Leopold Ii Laan 43",
    "sg:city":"Sint-jans-molenbeek/molenbeek-saint-jean",
    "sg:orig_category":"Volwassenenonderwijs",
    "sg:phone":"+32 2 428 52 49",
    "sg:postcode":"1080",
    "sg:province":"Bruxelles-Capitale",
    "wof:name":"C.e.s.o.a.",
    "wof:placetype":"venue"
},
  "geometry": {"coordinates":[4.3436870575,50.8597488403],"type":"Point"}
}