{
  "type": "Feature",
  "properties": {
    "iso:country":"BE",
    "sg:address":"Monseigneur Heylenstraat 2",
    "sg:city":"Kasterlee",
    "sg:classifiers":[
        {
            "category":"Professional",
            "subcategory":"Testing Lab",
            "type":"Services"
        }
    ],
    "sg:phone":"+32 14 85 01 03",
    "sg:postcode":"2460",
    "sg:province":"Antwerpen",
    "sg:tags":[
        "chemist"
    ],
    "wof:name":"Van Ballaer W",
    "wof:placetype":"venue"
},
  "geometry": {"coordinates":[4.9659109116,51.2400588989],"type":"Point"}
}