{
  "type": "Feature",
  "properties": {
    "addr:full":"Abdijstraat 13ba Assenede Oost-Vlaanderen 9968",
    "addr:housenumber":"13ba",
    "addr:postcode":"9968",
    "addr:street":"Abdijstraat",
    "iso:country":"BE",
    "sg:address":"Abdijstraat 13ba",
    "sg:city":"Assenede",
    "sg:orig_category":"Artsen and specialisten",
    "sg:phone":"+32 9 373 66 05",
    "sg:postcode":"9968",
    "sg:province":"Oost-Vlaanderen",
    "wof:name":"A. De Vos",
    "wof:placetype":"venue"
},
  "geometry": {"coordinates":[3.6828179359,51.1863708496],"type":"Point"}
}