{
  "type": "Feature",
  "properties": {
    "iso:country":"BE",
    "sg:address":"Molsesteenweg 77",
    "sg:city":"Balen",
    "sg:classifiers":[
        {
            "category":"Retail",
            "subcategory":"Auto Repair",
            "type":"Services"
        }
    ],
    "sg:phone":"+32 14 31 96 96",
    "sg:postcode":"2490",
    "sg:province":"Antwerpen",
    "sg:tags":[
        "garage"
    ],
    "wof:name":"Lievens Paul",
    "wof:placetype":"venue"
},
  "geometry": {"coordinates":[5.1435570717,51.173538208],"type":"Point"}
}