{
  "type": "Feature",
  "properties": {
    "iso:country":"BE",
    "sg:address":"Steenbrugstraat 192 Box 2",
    "sg:city":"Harelbeke",
    "sg:classifiers":[
        {
            "category":"Building & Trades",
            "subcategory":"Construction",
            "type":"Services"
        }
    ],
    "sg:phone":"+32 56 20 04 56",
    "sg:postcode":"8530",
    "sg:province":"West-Vlaanderen",
    "sg:tags":[
        "asphalt",
        "contractor"
    ],
    "wof:name":"Vantieghem Johan & Co Bvba",
    "wof:placetype":"venue"
},
  "geometry": {"coordinates":[3.3325710297,50.8351554871],"type":"Point"}
}