{
  "type": "Feature",
  "properties": {
    "addr:full":"Rue Albert I 68 Hannut Li\u00e8ge 4280",
    "addr:housenumber":"68",
    "addr:postcode":"4280",
    "addr:street":"Rue Albert I",
    "iso:country":"BE",
    "sg:address":"Rue Albert I 68",
    "sg:city":"Hannut",
    "sg:classifiers":[
        {
            "category":"Retail",
            "subcategory":"Laundry & Dry Cleaning",
            "type":"Services"
        }
    ],
    "sg:phone":"+32 19 51 32 78",
    "sg:postcode":"4280",
    "sg:province":"Li\u00e8ge",
    "sg:tags":[
        "dyer",
        "cleaner"
    ],
    "wof:name":"Lavoir Du Centre",
    "wof:placetype":"venue"
},
  "geometry": {"coordinates":[5.0834321976,50.6692504883],"type":"Point"}
}