{
  "type": "Feature",
  "properties": {
    "iso:country":"BE",
    "sg:address":"Rue Du Chainia 34",
    "sg:city":"La Bruy\u00e8re (meux)",
    "sg:classifiers":[
        {
            "category":"Building & Trades",
            "subcategory":"Landscaping Services",
            "type":"Services"
        }
    ],
    "sg:phone":"+32 81 56 78 86",
    "sg:postcode":"5081",
    "sg:province":"Namur",
    "sg:tags":[
        "gardening",
        "garden",
        "maintenance"
    ],
    "wof:name":"Wilgos J",
    "wof:placetype":"venue"
},
  "geometry": {"coordinates":[4.7987561226,50.5548934937],"type":"Point"}
}