{
  "type": "Feature",
  "properties": {
    "iso:country":"BE",
    "sg:address":"Rue Ronqui\u00c8res 4",
    "sg:city":"Ecaussinnes",
    "sg:orig_category":"Installatie van houten of kunststof schrijnwerk",
    "sg:phone":"+32 67 48 55 18",
    "sg:postcode":"7191",
    "sg:province":"Hainaut",
    "wof:name":"Menuiserie Guerard",
    "wof:placetype":"venue"
},
  "geometry": {"coordinates":[4.1993308067,50.5865211487],"type":"Point"}
}