{
  "type": "Feature",
  "properties": {
    "iso:country":"BE",
    "sg:address":"Steenbakkersdam 2b2",
    "sg:city":"Beerse",
    "sg:orig_category":"Gespecialiseerde niet-residenti\u00eble bouw Installatie van metalen schrijnwerk SMEEDWERK, METAALBEWERKI",
    "sg:phone":"+32 14 61 64 06",
    "sg:postcode":"2340",
    "sg:province":"Antwerpen",
    "wof:name":"De Visscher W.",
    "wof:placetype":"venue"
},
  "geometry": {"coordinates":[4.8628091812,51.3289909363],"type":"Point"}
}