{
  "type": "Feature",
  "properties": {
    "addr:full":"Dampoortstraat 74 Gent Oost-Vlaanderen 9000",
    "addr:housenumber":"74",
    "addr:postcode":"9000",
    "addr:street":"Dampoortstraat;Oost-Vlaanderen",
    "iso:country":"BE",
    "sg:address":"Dampoortstraat 74",
    "sg:city":"Gent",
    "sg:classifiers":[
        {
            "category":"Bakery",
            "type":"Food & Drink"
        }
    ],
    "sg:phone":"+32 9 225 53 62",
    "sg:postcode":"9000",
    "sg:province":"Oost-Vlaanderen",
    "sg:tags":[
        "confectioner",
        "baker"
    ],
    "wof:name":"Elif",
    "wof:placetype":"venue"
},
  "geometry": {"coordinates":[3.7368400097,51.0568809509],"type":"Point"}
}