{
  "type": "Feature",
  "properties": {
    "addr:full":"Rue Fond Thirion 8 Waterloo Brabant Wallon 1410",
    "addr:housenumber":"8",
    "addr:postcode":"1410",
    "addr:street":"Rue Fond Thirion",
    "iso:country":"BE",
    "sg:address":"Rue Fond Thirion 8",
    "sg:city":"Waterloo",
    "sg:orig_category":"Artsen and specialisten",
    "sg:phone":"+32 2 354 05 39",
    "sg:postcode":"1410",
    "sg:province":"Brabant Wallon",
    "wof:name":"J. Mgoyi",
    "wof:placetype":"venue"
},
  "geometry": {"coordinates":[4.3773560524,50.7093238831],"type":"Point"}
}