{
  "type": "Feature",
  "properties": {
    "addr:full":"Terhulpsesteenweg 401 Watermaal-bosvoorde/watermael-boitsfort Bruxelles-Capitale 1170",
    "addr:housenumber":"401",
    "addr:postcode":"1170",
    "addr:street":"Terhulpsesteenweg",
    "iso:country":"BE",
    "sg:address":"Terhulpsesteenweg 401",
    "sg:city":"Watermaal-bosvoorde/watermael-boitsfort",
    "sg:orig_category":"Kapsalons",
    "sg:phone":"+32 2 672 46 58",
    "sg:postcode":"1170",
    "sg:province":"Bruxelles-Capitale",
    "wof:name":"Coiffure Lucienne",
    "wof:placetype":"venue"
},
  "geometry": {"coordinates":[4.422191143,50.7905960083],"type":"Point"}
}