{
  "type": "Feature",
  "properties": {
    "addr:full":"Wijerdriesstraat 44 Genk Limburg 3600",
    "addr:housenumber":"44",
    "addr:postcode":"3600",
    "addr:street":"Wijerdriesstraat",
    "iso:country":"BE",
    "sg:address":"Wijerdriesstraat 44",
    "sg:city":"Genk",
    "sg:orig_category":"M\u00e9decines alternatives",
    "sg:phone":"+32 89 36 71 11",
    "sg:postcode":"3600",
    "sg:province":"Limburg",
    "wof:name":"Axelle",
    "wof:placetype":"venue"
},
  "geometry": {"coordinates":[5.5520181656,50.9728355408],"type":"Point"}
}