{
  "type": "Feature",
  "properties": {
    "iso:country":"BE",
    "sg:address":"Zonneweelde 6",
    "sg:city":"Schilde",
    "sg:orig_category":"Installatie van metalen schrijnwerk",
    "sg:phone":"+32 3 685 58 83",
    "sg:postcode":"2970",
    "sg:province":"Antwerpen",
    "wof:name":"Barvac",
    "wof:placetype":"venue"
},
  "geometry": {"coordinates":[4.5628628731,51.2711677551],"type":"Point"}
}