{
  "type": "Feature",
  "properties": {
    "addr:full":"Stationsstraat 34 Sint-niklaas Oost-Vlaanderen 9100",
    "addr:housenumber":"34",
    "addr:postcode":"9100",
    "addr:street":"Stationsstraat",
    "iso:country":"BE",
    "sg:address":"Stationsstraat 34",
    "sg:city":"Sint-niklaas",
    "sg:classifiers":[
        {
            "category":"Shopping",
            "subcategory":"Jewelry",
            "type":"Retail Goods"
        }
    ],
    "sg:phone":"+32 3 766 01 72",
    "sg:postcode":"9100",
    "sg:province":"Oost-Vlaanderen",
    "sg:tags":[
        "-",
        "imitation"
    ],
    "wof:name":"Choice Modejuwelen Nv",
    "wof:placetype":"venue"
},
  "geometry": {"coordinates":[4.1413869858,51.1661338806],"type":"Point"}
}