{
  "type": "Feature",
  "properties": {
    "iso:country":"BE",
    "sg:address":"Karel De Goedelaan 38",
    "sg:city":"Izegem",
    "sg:orig_category":"Kapsalons",
    "sg:phone":"+32 51 30 29 04",
    "sg:postcode":"8870",
    "sg:province":"West-Vlaanderen",
    "wof:name":"Coiffure Rika",
    "wof:placetype":"venue"
},
  "geometry": {"coordinates":[3.195483923,50.901599884],"type":"Point"}
}