{
  "type": "Feature",
  "properties": {
    "addr:full":"Houthulstseweg 63 Langemark-poelkapelle West-Vlaanderen 8920",
    "addr:housenumber":"63",
    "addr:postcode":"8920",
    "addr:street":"Houthulstseweg",
    "iso:country":"BE",
    "sg:address":"Houthulstseweg 63",
    "sg:city":"Langemark-poelkapelle",
    "sg:orig_category":"Eleveurs and marchands de porcs",
    "sg:phone":"+32 57 48 83 03",
    "sg:postcode":"8920",
    "sg:province":"West-Vlaanderen",
    "wof:name":"Ameel",
    "wof:placetype":"venue"
},
  "geometry": {"coordinates":[2.9435329437,50.9305801392],"type":"Point"}
}