{
  "type": "Feature",
  "properties": {
    "iso:country":"BE",
    "sg:address":"Petit Halleux 19",
    "sg:city":"Vielsalm (grand-halleux)",
    "sg:classifiers":[
        {
            "category":"Building & Trades",
            "subcategory":"Plumbing",
            "type":"Services"
        }
    ],
    "sg:phone":"+32 80 21 58 71",
    "sg:postcode":"6698",
    "sg:province":"Luxembourg",
    "sg:tags":[
        "repair",
        "mainten",
        "-",
        "central",
        "heating"
    ],
    "wof:name":"Close F",
    "wof:placetype":"venue"
},
  "geometry": {"coordinates":[5.9034662247,50.3227233887],"type":"Point"}
}