{
  "type": "Feature",
  "properties": {
    "iso:country":"BE",
    "sg:address":"Brakelsesteenweg 167",
    "sg:city":"Ninove",
    "sg:orig_category":"Fabrication and montage de mobilier. Quincailleries",
    "sg:phone":"+32 54 34 18 84",
    "sg:postcode":"9406",
    "sg:province":"Oost-Vlaanderen",
    "wof:name":"D. M. K.",
    "wof:placetype":"venue"
},
  "geometry": {"coordinates":[4.0010199547,50.8352165222],"type":"Point"}
}