{
  "type": "Feature",
  "properties": {
    "iso:country":"BE",
    "sg:address":"Eichemstraat 116",
    "sg:city":"Ninove",
    "sg:orig_category":"Plaatsen van vloer- and muurbekleding Schilders",
    "sg:phone":"+32 54 33 42 30",
    "sg:postcode":"9400",
    "sg:province":"Oost-Vlaanderen",
    "wof:name":"Vergalle-decor",
    "wof:placetype":"venue"
},
  "geometry": {"coordinates":[4.0232000351,50.8349113464],"type":"Point"}
}