{
  "type": "Feature",
  "properties": {
    "addr:full":"Broekstraat 2 Dessel Antwerpen 2480",
    "addr:housenumber":"2",
    "addr:postcode":"2480",
    "addr:street":"Broekstraat",
    "iso:country":"BE",
    "sg:address":"Broekstraat 2",
    "sg:city":"Dessel",
    "sg:classifiers":[
        {
            "category":"Personal",
            "subcategory":"Beauty Salon",
            "type":"Services"
        }
    ],
    "sg:phone":"+32 14 37 17 03",
    "sg:postcode":"2480",
    "sg:province":"Antwerpen",
    "sg:tags":[
        "de",
        "coiffure"
    ],
    "wof:name":"Gustaaf Van Gompel",
    "wof:placetype":"venue"
},
  "geometry": {"coordinates":[5.1080851555,51.2396202087],"type":"Point"}
}