{
  "type": "Feature",
  "properties": {
    "iso:country":"BE",
    "sg:address":"Place Palais De Justice 1",
    "sg:city":"Namur",
    "sg:orig_category":"Installatie van houten of kunststof schrijnwerk",
    "sg:phone":"+32 81 22 09 10",
    "sg:postcode":"5000",
    "sg:province":"Namur",
    "wof:name":"S\u00c9bastien Harmel",
    "wof:placetype":"venue"
},
  "geometry": {"coordinates":[4.8606100082,50.4651374817],"type":"Point"}
}