{
  "type": "Feature",
  "properties": {
    "addr:full":"Merelstraat 87 Heusden-zolder Limburg 3550",
    "addr:housenumber":"87",
    "addr:postcode":"3550",
    "addr:street":"Merelstraat",
    "iso:country":"BE",
    "sg:address":"Merelstraat 87",
    "sg:city":"Heusden-zolder",
    "sg:orig_category":"Dakwerken",
    "sg:phone":"+32 11 42 06 76",
    "sg:postcode":"3550",
    "sg:province":"Limburg",
    "wof:name":"Vamo",
    "wof:placetype":"venue"
},
  "geometry": {"coordinates":[5.2689862251,51.0337257385],"type":"Point"}
}