{
  "type": "Feature",
  "properties": {
    "addr:full":"Place Crombez 1 Tournai Hainaut 7500",
    "addr:housenumber":"1",
    "addr:postcode":"7500",
    "addr:street":"Place Crombez",
    "iso:country":"BE",
    "sg:address":"Place Crombez 1",
    "sg:city":"Tournai",
    "sg:classifiers":[
        {
            "category":"Personal",
            "subcategory":"Beauty Salon",
            "type":"Services"
        }
    ],
    "sg:phone":"+32 69 23 25 19",
    "sg:postcode":"7500",
    "sg:province":"Hainaut",
    "wof:name":"Salens J",
    "wof:placetype":"venue"
},
  "geometry": {"coordinates":[3.3952450752,50.6119041443],"type":"Point"}
}