{
  "type": "Feature",
  "properties": {
    "iso:country":"BE",
    "sg:address":"R De La Melopee 38",
    "sg:city":"Molenbeek-saint-jean (bruxelles)",
    "sg:orig_category":"Kapsalons",
    "sg:phone":"+32 2 410 16 42",
    "sg:postcode":"1080",
    "sg:province":"Bruxelles-Capitale",
    "wof:name":"Alix Coiffure",
    "wof:placetype":"venue"
},
  "geometry": {"coordinates":[4.31483078,50.8534355164],"type":"Point"}
}