{
  "type": "Feature",
  "properties": {
    "iso:country":"BE",
    "sg:address":"Rue Aux Communes 25",
    "sg:city":"Vis\u00e9 (cheratte)",
    "sg:classifiers":[
        {
            "category":"Home & Garden",
            "subcategory":"Carpets & Floor Coverings",
            "type":"Retail Goods"
        }
    ],
    "sg:phone":"+32 4 370 67 00",
    "sg:postcode":"4602",
    "sg:province":"Li\u00e8ge",
    "sg:tags":[
        "armoring"
    ],
    "wof:name":"Akgun Vedat",
    "wof:placetype":"venue"
},
  "geometry": {"coordinates":[5.6778979301,50.6836242676],"type":"Point"}
}