{
  "type": "Feature",
  "properties": {
    "iso:country":"BE",
    "sg:address":"Grobbendonkseweg 58",
    "sg:city":"Nijlen",
    "sg:orig_category":"Woningbouw",
    "sg:phone":"+32 3 411 05 16",
    "sg:postcode":"2560",
    "sg:province":"Antwerpen",
    "wof:name":"Breugelmans Bruno",
    "wof:placetype":"venue"
},
  "geometry": {"coordinates":[4.6913781166,51.1665802002],"type":"Point"}
}