{
  "type": "Feature",
  "properties": {
    "addr:full":"Kennedylaan 8 Box 2 Sint-truiden Limburg 3800",
    "addr:housenumber":"8;2",
    "addr:postcode":"3800",
    "addr:street":"Kennedylaan;Box",
    "iso:country":"BE",
    "sg:address":"Kennedylaan 8 Box 2",
    "sg:city":"Sint-truiden",
    "sg:classifiers":[
        {
            "category":"Health Services",
            "subcategory":"Doctor",
            "type":"Services"
        }
    ],
    "sg:phone":"+32 11 69 48 41",
    "sg:postcode":"3800",
    "sg:province":"Limburg",
    "sg:tags":[
        "medicinephysicians",
        "surgeon"
    ],
    "wof:name":"Koopmans E",
    "wof:placetype":"venue"
},
  "geometry": {"coordinates":[5.1932082176,50.8109779358],"type":"Point"}
}