{
  "type": "Feature",
  "properties": {
    "iso:country":"BE",
    "sg:address":"Grand Rue 22",
    "sg:city":"Bouillon",
    "sg:classifiers":[
        {
            "category":"Brewery",
            "type":"Food & Drink"
        }
    ],
    "sg:phone":"+32 61 46 89 40",
    "sg:postcode":"6830",
    "sg:province":"Luxembourg",
    "wof:name":"Bouillon (brasserie De)",
    "wof:placetype":"venue"
},
  "geometry": {"coordinates":[5.0692481995,49.7954788208],"type":"Point"}
}