{
  "type": "Feature",
  "properties": {
    "iso:country":"BE",
    "sg:address":"Place De Bernissart 13",
    "sg:city":"Bernissart",
    "sg:classifiers":[
        {
            "category":"Food & Beverages",
            "subcategory":"Groceries & Convenience Stores",
            "type":"Retail Goods"
        }
    ],
    "sg:phone":"+32 69 56 24 08",
    "sg:postcode":"7320",
    "sg:province":"Hainaut",
    "sg:tags":[
        "grocer"
    ],
    "wof:name":"Superette De La Place",
    "wof:placetype":"venue"
},
  "geometry": {"coordinates":[3.6495399475,50.4748306274],"type":"Point"}
}