{
  "type": "Feature",
  "properties": {
    "iso:country":"BE",
    "sg:address":"Krepelstraat 3ba",
    "sg:city":"Ninove",
    "sg:orig_category":"Boucheries",
    "sg:phone":"+32 54 33 28 04",
    "sg:postcode":"9400",
    "sg:province":"Oost-Vlaanderen",
    "wof:name":"Slagerij De Cleer",
    "wof:placetype":"venue"
},
  "geometry": {"coordinates":[4.0227351189,50.7973747253],"type":"Point"}
}