{
  "type": "Feature",
  "properties": {
    "iso:country":"BE",
    "sg:address":"Boulevard Georges Deryck 49",
    "sg:city":"Tubize",
    "sg:orig_category":"Rechtbanken",
    "sg:phone":"+32 2 355 86 06",
    "sg:postcode":"1480",
    "sg:province":"Brabant Wallon",
    "wof:name":"Justice De Paix",
    "wof:placetype":"venue"
},
  "geometry": {"coordinates":[4.2017860413,50.6936912537],"type":"Point"}
}