{
  "type": "Feature",
  "properties": {
    "iso:country":"BE",
    "sg:address":"Aalsterweg 26",
    "sg:city":"Sint-truiden",
    "sg:orig_category":"Installatie van houten of kunststof schrijnwerk",
    "sg:phone":"+32 11 68 00 91",
    "sg:postcode":"3800",
    "sg:province":"Limburg",
    "wof:name":"Koen Celis",
    "wof:placetype":"venue"
},
  "geometry": {"coordinates":[5.1914348602,50.8078536987],"type":"Point"}
}