{
  "type": "Feature",
  "properties": {
    "iso:country":"BE",
    "sg:address":"Boulevard Cauchy 19",
    "sg:city":"Namur (grand)",
    "sg:orig_category":"Formation permanente",
    "sg:phone":"+32 81 74 32 00",
    "sg:postcode":"5000",
    "sg:province":"Namur",
    "wof:name":"Interf\u00c9d\u00c9ration Des Organismes De Formation",
    "wof:placetype":"venue"
},
  "geometry": {"coordinates":[4.8715848923,50.4683685303],"type":"Point"}
}