{
  "type": "Feature",
  "properties": {
    "addr:full":"Beverlaai 1 Kortrijk West-Vlaanderen 8500",
    "addr:housenumber":"1",
    "addr:postcode":"8500",
    "addr:street":"Beverlaai",
    "iso:country":"BE",
    "sg:address":"Beverlaai 1",
    "sg:city":"Kortrijk",
    "sg:orig_category":"Fietsen Motorfietsen",
    "sg:phone":"+32 56 22 52 50",
    "sg:postcode":"8500",
    "sg:province":"West-Vlaanderen",
    "wof:name":"Vanneste D & Zoon",
    "wof:placetype":"venue"
},
  "geometry": {"coordinates":[3.268034935,50.8223304749],"type":"Point"}
}