{
  "type": "Feature",
  "properties": {
    "iso:country":"BE",
    "sg:address":"Rue D'anderlues 44",
    "sg:city":"Binche",
    "sg:classifiers":[
        {
            "category":"Insurance",
            "subcategory":"Life Insurance",
            "type":"Services"
        }
    ],
    "sg:phone":"+32 64 34 05 27",
    "sg:postcode":"7134",
    "sg:province":"Hainaut",
    "sg:tags":[
        "assurance"
    ],
    "wof:name":"Assurances Cocco",
    "wof:placetype":"venue"
},
  "geometry": {"coordinates":[4.2237710953,50.422668457],"type":"Point"}
}