{
  "type": "Feature",
  "properties": {
    "iso:country":"BE",
    "sg:address":"Robbroekstraat 11",
    "sg:city":"Steenhuffel",
    "sg:classifiers":[
        {
            "category":"Autos & Motor Vehicles",
            "subcategory":"Automobile Sales",
            "type":"Retail Goods"
        }
    ],
    "sg:phone":"+32 52 30 99 06",
    "sg:postcode":"1840",
    "sg:province":"Vlaams-Brabant",
    "sg:tags":[
        "equipment",
        "motor-cars",
        "transport"
    ],
    "wof:name":"Garage De Plecker-pauwels Nv",
    "wof:placetype":"venue"
},
  "geometry": {"coordinates":[4.2632517815,50.9902153015],"type":"Point"}
}