{
  "type": "Feature",
  "properties": {
    "iso:country":"BE",
    "sg:address":"Avenue Des Perdrix 5",
    "sg:city":"Waterloo",
    "sg:classifiers":[
        {
            "category":"Parking",
            "subcategory":"Bicycle",
            "type":"Transportation"
        }
    ],
    "sg:phone":"+32 2 354 28 69",
    "sg:postcode":"1410",
    "sg:province":"Brabant Wallon",
    "sg:tags":[
        "chiropodist"
    ],
    "wof:name":"Beuselinck A",
    "wof:placetype":"venue"
},
  "geometry": {"coordinates":[4.3956251144,50.7347068787],"type":"Point"}
}