{
  "type": "Feature",
  "properties": {
    "addr:full":"Mechelsestraat 147 Leuven Vlaams-Brabant 3000",
    "addr:housenumber":"147",
    "addr:postcode":"3000",
    "addr:street":"Mechelsestraat",
    "iso:country":"BE",
    "sg:address":"Mechelsestraat 147",
    "sg:city":"Leuven",
    "sg:orig_category":"Agences immobili\u00e8res",
    "sg:phone":"+32 16 23 80 40",
    "sg:postcode":"3000",
    "sg:province":"Vlaams-Brabant",
    "wof:name":"Bureau Boogaerts & Partn.",
    "wof:placetype":"venue"
},
  "geometry": {"coordinates":[4.6982388496,50.8832321167],"type":"Point"}
}