{
  "type": "Feature",
  "properties": {
    "addr:full":"Rue Du Chainia 55 La Bruy\u00e8re (meux) Namur 5081",
    "addr:housenumber":"55",
    "addr:postcode":"5081",
    "addr:street":"Rue Du Chainia",
    "iso:country":"BE",
    "sg:address":"Rue Du Chainia 55",
    "sg:city":"La Bruy\u00e8re (meux)",
    "sg:classifiers":[
        {
            "category":"Organizations",
            "subcategory":"Professional Association",
            "type":"Services"
        }
    ],
    "sg:phone":"+32 81 56 02 28",
    "sg:postcode":"5081",
    "sg:province":"Namur",
    "sg:tags":[
        "organisation",
        "seminar"
    ],
    "wof:name":"Lefranc S",
    "wof:placetype":"venue"
},
  "geometry": {"coordinates":[4.8025398254,50.551197052],"type":"Point"}
}