{
  "type": "Feature",
  "properties": {
    "addr:full":"Oude Brusselseweg 244 Gent Oost-Vlaanderen 9050",
    "addr:housenumber":"244",
    "addr:postcode":"9050",
    "addr:street":"Oude Brusselseweg;Oost-Vlaanderen",
    "iso:country":"BE",
    "sg:address":"Oude Brusselseweg 244",
    "sg:city":"Gent",
    "sg:orig_category":"Production de films, t\u00e9l\u00e9films and vid\u00e9os",
    "sg:phone":"+32 9 232 50 00",
    "sg:postcode":"9050",
    "sg:province":"Oost-Vlaanderen",
    "wof:name":"Cast And Crew",
    "wof:placetype":"venue"
},
  "geometry": {"coordinates":[3.7540049553,51.0377044678],"type":"Point"}
}