{
  "type": "Feature",
  "properties": {
    "iso:country":"BE",
    "sg:address":"Rue Paul Janson 6",
    "sg:city":"Amay",
    "sg:orig_category":"Drogisterijen Plaatsen van vloer- and muurbekleding Schilders Textiel Verlichting and huishoudartike",
    "sg:phone":"+32 85 31 12 51",
    "sg:postcode":"4540",
    "sg:province":"Li\u00e8ge",
    "wof:name":"D\u00c9coration Lambotte",
    "wof:placetype":"venue"
},
  "geometry": {"coordinates":[5.3171367645,50.5479316711],"type":"Point"}
}