{
  "type": "Feature",
  "properties": {
    "addr:full":"Mechelsesteenweg 588d Vilvoorde Vlaams-Brabant 1800",
    "addr:housenumber":"588d",
    "addr:postcode":"1800",
    "addr:street":"Mechelsesteenweg",
    "iso:country":"BE",
    "sg:address":"Mechelsesteenweg 588d",
    "sg:city":"Vilvoorde",
    "sg:orig_category":"Herstellingen and onderhoud van auto's Voertuigen",
    "sg:phone":"+32 2 254 75 60",
    "sg:postcode":"1800",
    "sg:province":"Vlaams-Brabant",
    "wof:name":"Subaru",
    "wof:placetype":"venue"
},
  "geometry": {"coordinates":[4.4433917999,50.9450721741],"type":"Point"}
}