{
  "type": "Feature",
  "properties": {
    "addr:full":"De Bormanlaan 40 Hoeselt Limburg 3730",
    "addr:housenumber":"40",
    "addr:postcode":"3730",
    "addr:street":"Bormanlaan",
    "iso:country":"BE",
    "sg:address":"De Bormanlaan 40",
    "sg:city":"Hoeselt",
    "sg:orig_category":"Diverse bedrijfsbeheeradviesbureaus",
    "sg:phone":"+32 89 51 45 86",
    "sg:postcode":"3730",
    "sg:province":"Limburg",
    "wof:name":"Arias",
    "wof:placetype":"venue"
},
  "geometry": {"coordinates":[5.4809980392,50.8470077515],"type":"Point"}
}