{
  "type": "Feature",
  "properties": {
    "iso:country":"BE",
    "sg:address":"Handelsstraat 44",
    "sg:city":"Mol",
    "sg:classifiers":[
        {
            "category":"Communications",
            "subcategory":"Film & Video Production",
            "type":"Services"
        }
    ],
    "sg:phone":"+32 14 81 45 67",
    "sg:postcode":"2400",
    "sg:province":"Antwerpen",
    "sg:tags":[
        "adhesive"
    ],
    "wof:name":"M-n International Nv",
    "wof:placetype":"venue"
},
  "geometry": {"coordinates":[5.210436821,51.1895523071],"type":"Point"}
}