{
  "type": "Feature",
  "properties": {
    "iso:country":"BE",
    "sg:address":"Lenniksesteenweg 621",
    "sg:city":"Halle",
    "sg:orig_category":"Enseignement maternel and primaire",
    "sg:phone":"+32 2 356 14 71",
    "sg:postcode":"1500",
    "sg:province":"Vlaams-Brabant",
    "wof:name":"Vrije Kleuterschool",
    "wof:placetype":"venue"
},
  "geometry": {"coordinates":[4.2134699821,50.748008728],"type":"Point"}
}