{
  "type": "Feature",
  "properties": {
    "iso:country":"BE",
    "sg:address":"Kapitein M. Cuypersstraat 34",
    "sg:city":"Scherpenheuvel-zichem (zichem)",
    "sg:classifiers":[
        {
            "category":"Personal",
            "subcategory":"Barber",
            "type":"Services"
        }
    ],
    "sg:phone":"+32 13 77 58 63",
    "sg:postcode":"3271",
    "sg:province":"Vlaams-Brabant",
    "sg:tags":[
        "gentleman",
        "salon",
        "-",
        "hairdressing"
    ],
    "wof:name":"Danny Haarmode",
    "wof:placetype":"venue"
},
  "geometry": {"coordinates":[4.9861989021,50.9997787476],"type":"Point"}
}