{
  "type": "Feature",
  "properties": {
    "iso:country":"BE",
    "sg:address":"Doornenlaan 6",
    "sg:city":"Oostende",
    "sg:orig_category":"Experts-comptables",
    "sg:phone":"+32 59 51 49 01",
    "sg:postcode":"8400",
    "sg:province":"West-Vlaanderen",
    "wof:name":"Luc Coene",
    "wof:placetype":"venue"
},
  "geometry": {"coordinates":[2.9028859138,51.2095718384],"type":"Point"}
}