{
  "type": "Feature",
  "properties": {
    "iso:country":"BE",
    "sg:address":"Heikant 35",
    "sg:city":"Lille",
    "sg:orig_category":"Eclairage et \u00e9quipements du foyer. Installation \u00e9lectrique industrielle. Electrom\u00e9nager, t\u00e9l\u00e9visions",
    "sg:phone":"+32 14 88 21 75",
    "sg:postcode":"2275",
    "sg:province":"Antwerpen",
    "wof:name":"Electro Jacobs",
    "wof:placetype":"venue"
},
  "geometry": {"coordinates":[4.8301229477,51.2297782898],"type":"Point"}
}