{
  "type": "Feature",
  "properties": {
    "iso:country":"BE",
    "sg:address":"Stationsstraat 100",
    "sg:city":"Nevele",
    "sg:classifiers":[
        {
            "category":"Restaurant",
            "type":"Food & Drink"
        }
    ],
    "sg:phone":"+32 9 371 90 78",
    "sg:postcode":"9850",
    "sg:province":"Oost-Vlaanderen",
    "sg:tags":[
        "caf\u00e9s"
    ],
    "wof:name":"Taverne De Pelgrim",
    "wof:placetype":"venue"
},
  "geometry": {"coordinates":[3.5494019985,51.0329589844],"type":"Point"}
}