{
  "type": "Feature",
  "properties": {
    "addr:full":"Steenbeekstraat 25 Beveren Oost-Vlaanderen 9120",
    "addr:housenumber":"25",
    "addr:postcode":"9120",
    "addr:street":"Steenbeekstraat",
    "iso:country":"BE",
    "sg:address":"Steenbeekstraat 25",
    "sg:city":"Beveren",
    "sg:orig_category":"Boomkwekerijen Groenten and fruit Gh",
    "sg:phone":"+32 3 775 91 27",
    "sg:postcode":"9120",
    "sg:province":"Oost-Vlaanderen",
    "wof:name":"No-bo",
    "wof:placetype":"venue"
},
  "geometry": {"coordinates":[4.1690468788,51.2135047913],"type":"Point"}
}