{
  "type": "Feature",
  "properties": {
    "iso:country":"BE",
    "sg:address":"Avenue De La Ros\u00c9e 8",
    "sg:city":"Sint-genesius-rode/rhode-saint-gen\u00c8se",
    "sg:orig_category":"M\u00e9decins and sp\u00e9cialistes",
    "sg:phone":"+32 2 358 40 24",
    "sg:postcode":"1640",
    "sg:province":"Vlaams-Brabant",
    "wof:name":"Marie-france Vaes",
    "wof:placetype":"venue"
},
  "geometry": {"coordinates":[4.3919668198,50.7400131226],"type":"Point"}
}