{
  "type": "Feature",
  "properties": {
    "iso:country":"BE",
    "sg:address":"Assesteenweg 65",
    "sg:city":"Ternat",
    "sg:orig_category":"Mat\u00e9riel scientifique and technique Fab",
    "sg:phone":"+32 2 583 09 99",
    "sg:postcode":"1740",
    "sg:province":"Vlaams-Brabant",
    "wof:name":"Interflex Belgium",
    "wof:placetype":"venue"
},
  "geometry": {"coordinates":[4.1669659615,50.8823661804],"type":"Point"}
}