{
  "type": "Feature",
  "properties": {
    "iso:country":"BE",
    "sg:address":"Kaulillerdorp 18",
    "sg:city":"Bocholt (kaulille)",
    "sg:classifiers":[
        {
            "category":"Manufacturing",
            "subcategory":"Textiles",
            "type":"Manufacturing & Wholesale Goods"
        }
    ],
    "sg:phone":"+32 11 44 50 82",
    "sg:postcode":"3950",
    "sg:province":"Limburg",
    "sg:tags":[
        "retail",
        "-"
    ],
    "wof:name":"Schabon P",
    "wof:placetype":"venue"
},
  "geometry": {"coordinates":[5.5160279274,51.190158844],"type":"Point"}
}