{
  "type": "Feature",
  "properties": {
    "addr:full":"8660 De Panne West-Vlaanderen 8660",
    "addr:housenumber":"8660",
    "addr:postcode":"8660",
    "iso:country":"BE",
    "sg:address":"8660",
    "sg:city":"De Panne",
    "sg:orig_category":"Erotische Etablissementen Schoonheidsbehandelingen aan huis",
    "sg:phone":"+32 478 51 28 86",
    "sg:postcode":"8660",
    "sg:province":"West-Vlaanderen",
    "wof:name":"Wally",
    "wof:placetype":"venue"
},
  "geometry": {"coordinates":[2.5873849392,51.0955162048],"type":"Point"}
}