{
  "type": "Feature",
  "properties": {
    "addr:full":"Rue D'albanie 117 Sint-gillis/saint-gilles Bruxelles-Capitale 1060",
    "addr:housenumber":"117",
    "addr:postcode":"1060",
    "addr:street":"Rue D'Albanie",
    "iso:country":"BE",
    "sg:address":"Rue D'albanie 117",
    "sg:city":"Sint-gillis/saint-gilles",
    "sg:orig_category":"Databeheer and gegevensverwerking",
    "sg:phone":"+32 2 538 55 65",
    "sg:postcode":"1060",
    "sg:province":"Bruxelles-Capitale",
    "wof:name":"European Law Office",
    "wof:placetype":"venue"
},
  "geometry": {"coordinates":[4.3507061005,50.8233680725],"type":"Point"}
}