{
  "type": "Feature",
  "properties": {
    "iso:country":"BE",
    "sg:address":"Rue De La Colline 126",
    "sg:city":"Frameries",
    "sg:orig_category":"Epiceries",
    "sg:phone":"+32 65 67 29 92",
    "sg:postcode":"7080",
    "sg:province":"Hainaut",
    "wof:name":"Superette De La Colline",
    "wof:placetype":"venue"
},
  "geometry": {"coordinates":[3.8776578903,50.4034042358],"type":"Point"}
}