{
  "type": "Feature",
  "properties": {
    "iso:country":"BE",
    "sg:address":"Michielssendreef 24",
    "sg:city":"Brasschaat",
    "sg:classifiers":[
        {
            "category":"Health Services",
            "subcategory":"Hospital",
            "type":"Services"
        }
    ],
    "sg:phone":"+32 3 653 09 11",
    "sg:postcode":"2930",
    "sg:province":"Antwerpen",
    "wof:name":"Autodialyse Azca C Stuivenberg",
    "wof:placetype":"venue"
},
  "geometry": {"coordinates":[4.4825181961,51.2891616821],"type":"Point"}
}