{
  "type": "Feature",
  "properties": {
    "addr:full":"Hoveniersstraat 30 Antwerpen Antwerpen 2018",
    "addr:housenumber":"30",
    "addr:postcode":"2018",
    "addr:street":"Hoveniersstraat",
    "iso:country":"BE",
    "sg:address":"Hoveniersstraat 30",
    "sg:city":"Antwerpen",
    "sg:classifiers":[
        {
            "category":"Shopping",
            "subcategory":"Jewelry",
            "type":"Retail Goods"
        }
    ],
    "sg:phone":"+32 3 231 73 77",
    "sg:postcode":"2018",
    "sg:province":"Antwerpen",
    "sg:tags":[
        "diamond"
    ],
    "wof:name":"Intralcor Nv",
    "wof:placetype":"venue"
},
  "geometry": {"coordinates":[4.4185500145,51.2151031494],"type":"Point"}
}