{
  "type": "Feature",
  "properties": {
    "iso:country":"BE",
    "sg:address":"Avenue De La Closeraie 7-9",
    "sg:city":"Li\u00e8ge 1 (rocourt)",
    "sg:classifiers":[
        {
            "category":"Communications",
            "subcategory":"Film & Video Production",
            "type":"Services"
        }
    ],
    "sg:phone":"+32 4 224 70 78",
    "sg:postcode":"4000",
    "sg:province":"Li\u00e8ge",
    "sg:tags":[
        "hiring",
        "-"
    ],
    "wof:name":"Vid\u00e9o Cool",
    "wof:placetype":"venue"
},
  "geometry": {"coordinates":[5.5557179451,50.667098999],"type":"Point"}
}