{
  "type": "Feature",
  "properties": {
    "iso:country":"BE",
    "sg:address":"Amand Thi\u00e9rylaan 27",
    "sg:city":"Leuven (heverlee)",
    "sg:classifiers":[
        {
            "category":"Personal",
            "subcategory":"Nail Salon",
            "type":"Services"
        }
    ],
    "sg:phone":"+32 16 40 50 19",
    "sg:postcode":"3001",
    "sg:province":"Vlaams-Brabant",
    "sg:tags":[
        "pedicure"
    ],
    "wof:name":"Griffes-tobback",
    "wof:placetype":"venue"
},
  "geometry": {"coordinates":[4.7093291283,50.860496521],"type":"Point"}
}