{
  "type": "Feature",
  "properties": {
    "addr:full":"Uilevelden 3 Putte Antwerpen 2580",
    "addr:housenumber":"3",
    "addr:postcode":"2580",
    "addr:street":"Uilevelden",
    "iso:country":"BE",
    "sg:address":"Uilevelden 3",
    "sg:city":"Putte",
    "sg:orig_category":"Groententeelt",
    "sg:phone":"+32 15 23 38 90",
    "sg:postcode":"2580",
    "sg:province":"Antwerpen",
    "wof:name":"Edward Lambaerts",
    "wof:placetype":"venue"
},
  "geometry": {"coordinates":[4.6790800095,51.0232391357],"type":"Point"}
}