{
  "type": "Feature",
  "properties": {
    "addr:full":"Rue De Caraman 3 Boussu Hainaut 7300",
    "addr:housenumber":"3",
    "addr:postcode":"7300",
    "addr:street":"Rue De Caraman",
    "iso:country":"BE",
    "sg:address":"Rue De Caraman 3",
    "sg:city":"Boussu",
    "sg:classifiers":[
        {
            "category":"Retail",
            "subcategory":"Auto Repair",
            "type":"Services"
        }
    ],
    "sg:phone":"+32 475 59 83 38",
    "sg:postcode":"7300",
    "sg:province":"Hainaut",
    "sg:tags":[
        "automobile-body"
    ],
    "wof:name":"Motown Cars",
    "wof:placetype":"venue"
},
  "geometry": {"coordinates":[3.795101881,50.4340705872],"type":"Point"}
}