{
  "type": "Feature",
  "properties": {
    "addr:full":"Rue De Linthout 65 Bruxelles (schaerbeek) Bruxelles-Capitale 1030",
    "addr:housenumber":"65",
    "addr:postcode":"1030",
    "addr:street":"Rue De Linthout",
    "iso:country":"BE",
    "sg:address":"Rue De Linthout 65",
    "sg:city":"Bruxelles (schaerbeek)",
    "sg:classifiers":[
        {
            "category":"Health Services",
            "subcategory":"Nursing And Care Facility",
            "type":"Services"
        }
    ],
    "sg:phone":"+32 2 735 08 40",
    "sg:postcode":"1030",
    "sg:province":"Bruxelles-Capitale",
    "sg:tags":[
        "home",
        "rest"
    ],
    "wof:name":"Seniorie Linthout",
    "wof:placetype":"venue"
},
  "geometry": {"coordinates":[4.3982667923,50.8455467224],"type":"Point"}
}