{
  "type": "Feature",
  "properties": {
    "iso:country":"BE",
    "sg:address":"Nieuwmoerdorp 52",
    "sg:city":"Kalmthout",
    "sg:orig_category":"Epiceries",
    "sg:phone":"+32 3 667 22 94",
    "sg:postcode":"2920",
    "sg:province":"Antwerpen",
    "wof:name":"Spar",
    "wof:placetype":"venue"
},
  "geometry": {"coordinates":[4.5171837807,51.4325904846],"type":"Point"}
}