{
  "type": "Feature",
  "properties": {
    "addr:full":"Rue Delhasse 36 Spa Li\u00e8ge 4900",
    "addr:housenumber":"36",
    "addr:postcode":"4900",
    "addr:street":"Rue Delhasse",
    "iso:country":"BE",
    "sg:address":"Rue Delhasse 36",
    "sg:city":"Spa",
    "sg:classifiers":[
        {
            "category":"Personal",
            "subcategory":"Beauty Salon",
            "type":"Services"
        }
    ],
    "sg:phone":"+32 87 77 09 18",
    "sg:postcode":"4900",
    "sg:province":"Li\u00e8ge",
    "sg:tags":[
        "de",
        "coiffure"
    ],
    "wof:name":"Coiffure Ma\u00cft\u00c9's Cr\u00c9ation",
    "wof:placetype":"venue"
},
  "geometry": {"coordinates":[5.8654031754,50.4926452637],"type":"Point"}
}