{
  "type": "Feature",
  "properties": {
    "iso:country":"BE",
    "sg:address":"Marienheide 15",
    "sg:city":"Kelmis/la Calamine",
    "sg:orig_category":"Activit\u00e9s diverses d'imprimerie",
    "sg:phone":"+32 87 63 01 45",
    "sg:postcode":"4728",
    "sg:province":"Li\u00e8ge",
    "wof:name":"Pascal Hendrik",
    "wof:placetype":"venue"
},
  "geometry": {"coordinates":[6.0438699722,50.7164764404],"type":"Point"}
}