{
  "type": "Feature",
  "properties": {
    "addr:full":"Schoolstraat 226 Sint-niklaas Oost-Vlaanderen 9100",
    "addr:housenumber":"226",
    "addr:postcode":"9100",
    "addr:street":"Schoolstraat",
    "iso:country":"BE",
    "sg:address":"Schoolstraat 226",
    "sg:city":"Sint-niklaas",
    "sg:orig_category":"Producteurs de l\u00e9gumes",
    "sg:phone":"+32 3 776 50 51",
    "sg:postcode":"9100",
    "sg:province":"Oost-Vlaanderen",
    "wof:name":"August De Smedt",
    "wof:placetype":"venue"
},
  "geometry": {"coordinates":[4.1497898102,51.1562576294],"type":"Point"}
}