{
  "type": "Feature",
  "properties": {
    "addr:full":"Appelstraat 47 Aalst Oost-Vlaanderen 9300",
    "addr:housenumber":"47",
    "addr:postcode":"9300",
    "addr:street":"Appelstraat",
    "iso:country":"BE",
    "sg:address":"Appelstraat 47",
    "sg:city":"Aalst",
    "sg:orig_category":"Bloemen and planten",
    "sg:phone":"+32 53 78 19 10",
    "sg:postcode":"9300",
    "sg:province":"Oost-Vlaanderen",
    "wof:name":"Van Acker - De Buyser",
    "wof:placetype":"venue"
},
  "geometry": {"coordinates":[4.0519390106,50.9412841797],"type":"Point"}
}