{
  "type": "Feature",
  "properties": {
    "iso:country":"BE",
    "sg:address":"Av. De For\u00cat De Soignes 324",
    "sg:city":"Sint-genesius-rode/rhode-saint-genese",
    "sg:orig_category":"M\u00e9decins and sp\u00e9cialistes",
    "sg:phone":"+32 2 358 33 99",
    "sg:postcode":"1640",
    "sg:province":"Vlaams-Brabant",
    "wof:name":"J.m. Crokaerts",
    "wof:placetype":"venue"
},
  "geometry": {"coordinates":[4.3802671432,50.7572517395],"type":"Point"}
}