{
  "type": "Feature",
  "properties": {
    "iso:country":"BE",
    "sg:address":"Ortolanenlaan 56",
    "sg:city":"Watermaal-bosvoorde/watermael-boitsfort",
    "sg:orig_category":"Paramedische behandelingen",
    "sg:phone":"+32 2 660 84 94",
    "sg:postcode":"1170",
    "sg:province":"Bruxelles-Capitale",
    "wof:name":"C. Lef\u00c8bvre",
    "wof:placetype":"venue"
},
  "geometry": {"coordinates":[4.4071087837,50.8030967712],"type":"Point"}
}