{
  "type": "Feature",
  "properties": {
    "iso:country":"BE",
    "sg:address":"Chauss\u00c9e De Lodelinsart 100",
    "sg:city":"Charleroi",
    "sg:orig_category":"Verplichte sociale verzekeringen",
    "sg:phone":"+32 71 20 88 47",
    "sg:postcode":"6060",
    "sg:province":"Hainaut",
    "wof:name":"Mutualit\u00c9 Socialiste",
    "wof:placetype":"venue"
},
  "geometry": {"coordinates":[4.4880981445,50.4251937866],"type":"Point"}
}