{
  "type": "Feature",
  "properties": {
    "iso:country":"BE",
    "sg:address":"Rue Du Centre 13",
    "sg:city":"Gedinne (louette-saint-pierre)",
    "sg:orig_category":"Non-Classified Establishments",
    "sg:phone":"+32 61 58 82 85",
    "sg:postcode":"5575",
    "sg:province":"Namur",
    "wof:name":"Lejeune Ch\u00e8vrerie",
    "wof:placetype":"venue"
},
  "geometry": {"coordinates":[4.926554203,49.9601783752],"type":"Point"}
}