{
  "type": "Feature",
  "properties": {
    "addr:full":"Chauss\u00e9e Victor Lampe 106 Lessines (ollignies) Hainaut 7866",
    "addr:housenumber":"106",
    "addr:postcode":"7866",
    "addr:street":"Chausse\u0301E Victor Lampe",
    "iso:country":"BE",
    "sg:address":"Chauss\u00e9e Victor Lampe 106",
    "sg:city":"Lessines (ollignies)",
    "sg:classifiers":[
        {
            "category":"Autos & Motor Vehicles",
            "subcategory":"Automobile Sales",
            "type":"Retail Goods"
        }
    ],
    "sg:phone":"+32 68 33 23 40",
    "sg:postcode":"7866",
    "sg:province":"Hainaut",
    "sg:tags":[
        "car",
        "used",
        "-"
    ],
    "wof:name":"Baudoux-pelders Sprl",
    "wof:placetype":"venue"
},
  "geometry": {"coordinates":[3.8607370853,50.6822395325],"type":"Point"}
}