{
  "type": "Feature",
  "properties": {
    "iso:country":"BE",
    "sg:address":"Eendrachtstraat 4",
    "sg:city":"Aalst",
    "sg:classifiers":[
        {
            "category":"Arena",
            "subcategory":"Auto Racetrack",
            "type":"Entertainment"
        }
    ],
    "sg:phone":"+32 53 76 90 00",
    "sg:postcode":"9300",
    "sg:province":"Oost-Vlaanderen",
    "sg:tags":[
        "voyage",
        "de",
        "bmw",
        "autos",
        "agences"
    ],
    "wof:name":"Romein",
    "wof:placetype":"venue"
},
  "geometry": {"coordinates":[4.0393261909,50.9501724243],"type":"Point"}
}