{
  "type": "Feature",
  "properties": {
    "iso:country":"BE",
    "sg:address":"Avenue De Burlet 11",
    "sg:city":"Nivelles",
    "sg:classifiers":[
        {
            "category":"Bakery",
            "type":"Food & Drink"
        }
    ],
    "sg:phone":"+32 67 22 03 59",
    "sg:postcode":"1400",
    "sg:province":"Brabant Wallon",
    "sg:tags":[
        "confectioner",
        "baker"
    ],
    "wof:name":"Capricornes (les)",
    "wof:placetype":"venue"
},
  "geometry": {"coordinates":[4.3340888023,50.5998878479],"type":"Point"}
}