{
  "type": "Feature",
  "properties": {
    "addr:full":"Grand'rue 6 Aubange Luxembourg 6791",
    "addr:housenumber":"6",
    "addr:postcode":"6791",
    "addr:street":"Grand'Rue",
    "iso:country":"BE",
    "sg:address":"Grand'rue 6",
    "sg:city":"Aubange",
    "sg:orig_category":"Brood, gebak and snoepgoed",
    "sg:phone":"+32 63 38 88 08",
    "sg:postcode":"6791",
    "sg:province":"Luxembourg",
    "wof:name":"Jean Renard",
    "wof:placetype":"venue"
},
  "geometry": {"coordinates":[5.8356189728,49.5628623962],"type":"Point"}
}