{
  "type": "Feature",
  "properties": {
    "addr:full":"Plantenstraat 38 Hasselt Limburg 3500",
    "addr:housenumber":"38",
    "addr:postcode":"3500",
    "addr:street":"Plantenstraat",
    "iso:country":"BE",
    "sg:address":"Plantenstraat 38",
    "sg:city":"Hasselt",
    "sg:orig_category":"Sportcentra",
    "sg:phone":"+32 11 25 38 44",
    "sg:postcode":"3500",
    "sg:province":"Limburg",
    "wof:name":"Hatha Yoga",
    "wof:placetype":"venue"
},
  "geometry": {"coordinates":[5.3253779411,50.9351806641],"type":"Point"}
}