{
  "type": "Feature",
  "properties": {
    "addr:full":"Rue De La P\u00e9pini\u00e8re 19 Namur Namur 5000",
    "addr:housenumber":"19",
    "addr:postcode":"5000",
    "addr:street":"Rue De La Pe\u0301Pinie\u0300Re",
    "iso:country":"BE",
    "sg:address":"Rue De La P\u00e9pini\u00e8re 19",
    "sg:city":"Namur",
    "sg:classifiers":[
        {
            "category":"Communications",
            "subcategory":"Film & Video Production",
            "type":"Services"
        }
    ],
    "sg:phone":"+32 81 22 81 18",
    "sg:postcode":"5000",
    "sg:province":"Namur",
    "sg:tags":[
        "realisation",
        "-"
    ],
    "wof:name":"Phi Sprl",
    "wof:placetype":"venue"
},
  "geometry": {"coordinates":[4.8627271652,50.4709663391],"type":"Point"}
}