{
  "type": "Feature",
  "properties": {
    "addr:full":"Rue Voie De Li\u00e8ge 144 Herstal Li\u00e8ge 4040",
    "addr:housenumber":"144",
    "addr:postcode":"4040",
    "addr:street":"Rue Voie De Lie\u0300Ge",
    "iso:country":"BE",
    "sg:address":"Rue Voie De Li\u00e8ge 144",
    "sg:city":"Herstal",
    "sg:classifiers":[
        {
            "category":"Shopping",
            "subcategory":"Books",
            "type":"Retail Goods"
        }
    ],
    "sg:phone":"+32 4 264 38 29",
    "sg:postcode":"4040",
    "sg:province":"Li\u00e8ge",
    "sg:tags":[
        "bookseller"
    ],
    "wof:name":"Librairie Du 144",
    "wof:placetype":"venue"
},
  "geometry": {"coordinates":[5.6310281754,50.6682319641],"type":"Point"}
}