{
  "type": "Feature",
  "properties": {
    "iso:country":"BE",
    "sg:address":"Rue Des Mal\u00c8zes 3",
    "sg:city":"Elsene/ixelles",
    "sg:orig_category":"Architectes",
    "sg:phone":"+32 2 646 14 48",
    "sg:postcode":"1050",
    "sg:province":"Bruxelles-Capitale",
    "wof:name":"Kamar Sami",
    "wof:placetype":"venue"
},
  "geometry": {"coordinates":[4.3647561073,50.8213768005],"type":"Point"}
}