{
  "type": "Feature",
  "properties": {
    "addr:full":"Putstraat 2 Lubbeek Vlaams-Brabant 3212",
    "addr:housenumber":"2",
    "addr:postcode":"3212",
    "addr:street":"Putstraat",
    "iso:country":"BE",
    "sg:address":"Putstraat 2",
    "sg:city":"Lubbeek",
    "sg:orig_category":"Eleveurs de bovins",
    "sg:phone":"+32 16 62 04 05",
    "sg:postcode":"3212",
    "sg:province":"Vlaams-Brabant",
    "wof:name":"Georges Tombeur",
    "wof:placetype":"venue"
},
  "geometry": {"coordinates":[4.7956662178,50.8834114075],"type":"Point"}
}