{
  "type": "Feature",
  "properties": {
    "addr:full":"Woutersstraat 46 Hasselt Limburg 3500",
    "addr:housenumber":"46",
    "addr:postcode":"3500",
    "addr:street":"Woutersstraat",
    "iso:country":"BE",
    "sg:address":"Woutersstraat 46",
    "sg:city":"Hasselt",
    "sg:classifiers":[
        {
            "category":"Real Estate",
            "subcategory":"Architect",
            "type":"Services"
        }
    ],
    "sg:phone":"+32 11 28 11 16",
    "sg:postcode":"3500",
    "sg:province":"Limburg",
    "wof:name":"Woutermaertens W",
    "wof:placetype":"venue"
},
  "geometry": {"coordinates":[5.3313097954,50.9284095764],"type":"Point"}
}