{
  "type": "Feature",
  "properties": {
    "iso:country":"BE",
    "sg:address":"Avenue Du Parc 21",
    "sg:city":"Herve (chaineux)",
    "sg:classifiers":[
        {
            "category":"Retail",
            "subcategory":"Auto Repair",
            "type":"Services"
        }
    ],
    "sg:phone":"+32 87 39 45 45",
    "sg:postcode":"4650",
    "sg:province":"Li\u00e8ge",
    "sg:tags":[
        "automobile-body"
    ],
    "wof:name":"Carrosserie Leruth Sprl",
    "wof:placetype":"venue"
},
  "geometry": {"coordinates":[5.8422279358,50.6266021729],"type":"Point"}
}