{
  "type": "Feature",
  "properties": {
    "iso:country":"BE",
    "sg:address":"Zeelaan 143",
    "sg:city":"De Panne",
    "sg:orig_category":"Parfumeries",
    "sg:phone":"+32 58 41 25 35",
    "sg:postcode":"8660",
    "sg:province":"West-Vlaanderen",
    "wof:name":"Parfumerie Nefertiti",
    "wof:placetype":"venue"
},
  "geometry": {"coordinates":[2.5911939144,51.1021385193],"type":"Point"}
}