{
  "type": "Feature",
  "properties": {
    "addr:full":"Toekomstlaan 52 Herentals Antwerpen 2200",
    "addr:housenumber":"52",
    "addr:postcode":"2200",
    "addr:street":"Toekomstlaan",
    "iso:country":"BE",
    "sg:address":"Toekomstlaan 52",
    "sg:city":"Herentals",
    "sg:orig_category":"Gereedschapswerktuigen Gh",
    "sg:phone":"+32 14 21 00 31",
    "sg:postcode":"2200",
    "sg:province":"Antwerpen",
    "wof:name":"Fike Europe",
    "wof:placetype":"venue"
},
  "geometry": {"coordinates":[4.7922787666,51.1680870056],"type":"Point"}
}