{
  "type": "Feature",
  "properties": {
    "iso:country":"BE",
    "sg:address":"Hoogstraat 27",
    "sg:city":"Brugge",
    "sg:orig_category":"Antiquit\u00e9s. Art and fournitures artistiques",
    "sg:phone":"+32 50 33 14 50",
    "sg:postcode":"8000",
    "sg:province":"West-Vlaanderen",
    "wof:name":"Brugs Antiekhuis",
    "wof:placetype":"venue"
},
  "geometry": {"coordinates":[3.2296969891,51.2099075317],"type":"Point"}
}