{
  "type": "Feature",
  "properties": {
    "iso:country":"BE",
    "sg:address":"Rue De La R\u00c9sistance 7",
    "sg:city":"La Louviere",
    "sg:orig_category":"Schoonheidssalons",
    "sg:phone":"+32 64 22 94 22",
    "sg:postcode":"7100",
    "sg:province":"Hainaut",
    "wof:name":"Pierre Sapart",
    "wof:placetype":"venue"
},
  "geometry": {"coordinates":[4.1918292046,50.472782135],"type":"Point"}
}