{
  "type": "Feature",
  "properties": {
    "iso:country":"BE",
    "sg:address":"Nieuwstraat 52",
    "sg:city":"Essen",
    "sg:classifiers":[
        {
            "category":"Bars & Pubs",
            "type":"Food & Drink"
        }
    ],
    "sg:phone":"+32 3 677 00 58",
    "sg:postcode":"2910",
    "sg:province":"Antwerpen",
    "sg:tags":[
        "tavern"
    ],
    "wof:name":"Torenhof",
    "wof:placetype":"venue"
},
  "geometry": {"coordinates":[4.4684739113,51.4679756165],"type":"Point"}
}