{
  "type": "Feature",
  "properties": {
    "addr:full":"Rue Berckmans 154 Bruxelles (saint-gilles) Bruxelles-Capitale 1060",
    "addr:housenumber":"154",
    "addr:postcode":"1060",
    "addr:street":"Rue Berckmans",
    "iso:country":"BE",
    "sg:address":"Rue Berckmans 154",
    "sg:city":"Bruxelles (saint-gilles)",
    "sg:classifiers":[
        {
            "category":"Health Services",
            "subcategory":"Nursing And Care Facility",
            "type":"Services"
        }
    ],
    "sg:phone":"+32 2 534 32 17",
    "sg:postcode":"1060",
    "sg:province":"Bruxelles-Capitale",
    "sg:tags":[
        "home"
    ],
    "wof:name":"Rochtus",
    "wof:placetype":"venue"
},
  "geometry": {"coordinates":[4.3486862183,50.8325157166],"type":"Point"}
}