{
  "type": "Feature",
  "properties": {
    "iso:country":"BE",
    "sg:address":"Bogaerdstraat 13",
    "sg:city":"Merchtem",
    "sg:classifiers":[
        {
            "category":"Arena",
            "subcategory":"Sports Club",
            "type":"Entertainment"
        }
    ],
    "sg:phone":"+32 52 37 11 54",
    "sg:postcode":"1785",
    "sg:province":"Vlaams-Brabant",
    "wof:name":"Schietstand-trefpunt",
    "wof:placetype":"venue"
},
  "geometry": {"coordinates":[4.2326450348,50.958152771],"type":"Point"}
}