{
  "type": "Feature",
  "properties": {
    "addr:full":"Rue Du Village 24b Beauvechain Brabant Wallon 1320",
    "addr:housenumber":"24b",
    "addr:postcode":"1320",
    "addr:street":"Rue Du Village",
    "iso:country":"BE",
    "sg:address":"Rue Du Village 24b",
    "sg:city":"Beauvechain",
    "sg:classifiers":[
        {
            "category":"Professional",
            "subcategory":"Management & Consulting",
            "type":"Services"
        }
    ],
    "sg:phone":"+32 10 86 11 99",
    "sg:postcode":"1320",
    "sg:province":"Brabant Wallon",
    "sg:tags":[
        "-",
        "processing",
        "data",
        "consultant"
    ],
    "wof:name":"Overstijns Network Consultants",
    "wof:placetype":"venue"
},
  "geometry": {"coordinates":[4.7747120857,50.7852973938],"type":"Point"}
}