{
  "type": "Feature",
  "properties": {
    "addr:full":"Rue De La Rtgence 1 Baelen/baelen Li\u00e8ge 4837",
    "addr:housenumber":"1",
    "addr:postcode":"4837",
    "addr:street":"Rue De La Rtgence",
    "iso:country":"BE",
    "sg:address":"Rue De La Rtgence 1",
    "sg:city":"Baelen/baelen",
    "sg:orig_category":"Overheidsdiensten",
    "sg:phone":"+32 87 76 01 13",
    "sg:postcode":"4837",
    "sg:province":"Li\u00e8ge",
    "wof:name":"C.p.a.s.",
    "wof:placetype":"venue"
},
  "geometry": {"coordinates":[5.9713401794,50.6319007874],"type":"Point"}
}