{
  "type": "Feature",
  "properties": {
    "iso:country":"BE",
    "sg:address":"Chaussee D'antoing 55",
    "sg:city":"Tournai",
    "sg:classifiers":[
        {
            "category":"Manufacturing",
            "subcategory":"Building Materials",
            "type":"Manufacturing & Wholesale Goods"
        }
    ],
    "sg:phone":"+32 69 88 41 41",
    "sg:postcode":"7500",
    "sg:province":"Hainaut",
    "sg:tags":[
        "cement"
    ],
    "wof:name":"Ateliers Louis Carton S.a.",
    "wof:placetype":"venue"
},
  "geometry": {"coordinates":[3.4049310684,50.5968208313],"type":"Point"}
}