{
  "type": "Feature",
  "properties": {
    "addr:full":"Wijtschaatsestraat 24 Ieper West-Vlaanderen 8902",
    "addr:housenumber":"24",
    "addr:postcode":"8902",
    "addr:street":"Wijtschaatsestraat",
    "iso:country":"BE",
    "sg:address":"Wijtschaatsestraat 24",
    "sg:city":"Ieper",
    "sg:orig_category":"Rundveehouders",
    "sg:phone":"+32 57 20 57 21",
    "sg:postcode":"8902",
    "sg:province":"West-Vlaanderen",
    "wof:name":"Delanote Luc",
    "wof:placetype":"venue"
},
  "geometry": {"coordinates":[2.8731570244,50.812664032],"type":"Point"}
}