{
  "type": "Feature",
  "properties": {
    "addr:full":"Rue De La Montagne 6 Bruxelles Bruxelles-Capitale 1000",
    "addr:housenumber":"6",
    "addr:postcode":"1000",
    "addr:street":"Rue De La Montagne",
    "iso:country":"BE",
    "sg:address":"Rue De La Montagne 6",
    "sg:city":"Bruxelles",
    "sg:classifiers":[
        {
            "category":"Shopping",
            "subcategory":"Stationery & Office Supplies",
            "type":"Retail Goods"
        }
    ],
    "sg:phone":"+32 2 503 31 38",
    "sg:postcode":"1000",
    "sg:province":"Bruxelles-Capitale",
    "sg:tags":[
        "exchange"
    ],
    "wof:name":"Travelex Global & Financial Services",
    "wof:placetype":"venue"
},
  "geometry": {"coordinates":[4.3543801308,50.8467826843],"type":"Point"}
}