{
  "type": "Feature",
  "properties": {
    "iso:country":"BE",
    "sg:address":"Heegstraat 43",
    "sg:city":"Dessel",
    "sg:orig_category":"Eleveurs de volaille. Cr\u00e9meries",
    "sg:phone":"+32 14 37 80 05",
    "sg:postcode":"2480",
    "sg:province":"Antwerpen",
    "wof:name":"Claes-stessens",
    "wof:placetype":"venue"
},
  "geometry": {"coordinates":[5.1200752258,51.2454986572],"type":"Point"}
}