{
  "type": "Feature",
  "properties": {
    "addr:full":"Rue De La Grande Marli\u00e8re 20 Fontaine-l'ev\u00eaque (leernes) Hainaut 6142",
    "addr:housenumber":"20",
    "addr:postcode":"6142",
    "addr:street":"Rue De La Grande Marlie\u0300Re;Hainaut",
    "iso:country":"BE",
    "sg:address":"Rue De La Grande Marli\u00e8re 20",
    "sg:city":"Fontaine-l'ev\u00eaque (leernes)",
    "sg:classifiers":[
        {
            "category":"Building & Trades",
            "subcategory":"Electrical",
            "type":"Services"
        }
    ],
    "sg:phone":"+32 477 87 41 58",
    "sg:postcode":"6142",
    "sg:province":"Hainaut",
    "sg:tags":[
        "electric",
        "-",
        "housewiring",
        "contractor"
    ],
    "wof:name":"Noirfalise M",
    "wof:placetype":"venue"
},
  "geometry": {"coordinates":[-111.9644622803,46.2507972717],"type":"Point"}
}