{
  "type": "Feature",
  "properties": {
    "iso:country":"BE",
    "sg:address":"Bleumerstraat 44",
    "sg:city":"Maaseik",
    "sg:classifiers":[
        {
            "category":"Shopping",
            "subcategory":"Clothing, Apparel, & Fashions",
            "type":"Retail Goods"
        }
    ],
    "sg:phone":"+32 89 65 03 45",
    "sg:postcode":"3680",
    "sg:province":"Limburg",
    "sg:tags":[
        "lady",
        "clothing",
        "-"
    ],
    "wof:name":"Christel",
    "wof:placetype":"venue"
},
  "geometry": {"coordinates":[5.794260025,51.0942764282],"type":"Point"}
}