{
  "type": "Feature",
  "properties": {
    "addr:full":"Oudesteenweg 4bb Heist-op-den-berg Antwerpen 2222",
    "addr:housenumber":"4bb",
    "addr:postcode":"2222",
    "addr:street":"Oudesteenweg",
    "iso:country":"BE",
    "sg:address":"Oudesteenweg 4bb",
    "sg:city":"Heist-op-den-berg",
    "sg:orig_category":"Artsen and specialisten",
    "sg:phone":"+32 15 24 76 85",
    "sg:postcode":"2222",
    "sg:province":"Antwerpen",
    "wof:name":"Edwig Royberghs",
    "wof:placetype":"venue"
},
  "geometry": {"coordinates":[4.7191638947,51.103553772],"type":"Point"}
}