{
  "type": "Feature",
  "properties": {
    "iso:country":"BE",
    "sg:address":"Rue De Rosi\u00c8res 19",
    "sg:city":"Rixensart",
    "sg:classifiers":[
        {
            "category":"Insurance",
            "subcategory":"Insurance Agent",
            "type":"Services"
        }
    ],
    "sg:phone":"+32 2 655 05 50",
    "sg:postcode":"1332",
    "sg:province":"Brabant Wallon",
    "sg:tags":[
        "verzekeringsmakelaars",
        "expert"
    ],
    "wof:name":"Jp Proost Gestion Et Controle",
    "wof:placetype":"venue"
},
  "geometry": {"coordinates":[4.5162849426,50.7246322632],"type":"Point"}
}