{
  "type": "Feature",
  "properties": {
    "addr:full":"Rue De Monin 93 Hamois (achet) Namur 5362",
    "addr:housenumber":"93",
    "addr:postcode":"5362",
    "addr:street":"Rue De Monin",
    "iso:country":"BE",
    "sg:address":"Rue De Monin 93",
    "sg:city":"Hamois (achet)",
    "sg:orig_category":"Non-Classified Establishments",
    "sg:phone":"+32 83 61 16 60",
    "sg:postcode":"5362",
    "sg:province":"Namur",
    "wof:name":"Toussaint L Bv",
    "wof:placetype":"venue"
},
  "geometry": {"coordinates":[5.1476168633,50.3135948181],"type":"Point"}
}