{
  "type": "Feature",
  "properties": {
    "iso:country":"BE",
    "sg:address":"Sint-pauluslaan 21",
    "sg:city":"Tervuren",
    "sg:orig_category":"M\u00e9decins and sp\u00e9cialistes",
    "sg:phone":"+32 2 767 50 09",
    "sg:postcode":"3080",
    "sg:province":"Vlaams-Brabant",
    "wof:name":"Guido Anckaert",
    "wof:placetype":"venue"
},
  "geometry": {"coordinates":[4.5544900894,50.8358001709],"type":"Point"}
}