{
  "type": "Feature",
  "properties": {
    "iso:country":"BE",
    "sg:address":"Sur Le Gibet De Harz\u00c9 10",
    "sg:city":"Aywaille",
    "sg:orig_category":"Diensten voor huisdieren",
    "sg:phone":"+32 4 384 58 02",
    "sg:postcode":"4920",
    "sg:province":"Li\u00e8ge",
    "wof:name":"L'hermitrie-harze Aywaille",
    "wof:placetype":"venue"
},
  "geometry": {"coordinates":[5.6677598953,50.4542503357],"type":"Point"}
}