{
  "type": "Feature",
  "properties": {
    "iso:country":"BE",
    "sg:address":"Kwadeplasstraat 44a",
    "sg:city":"Linter (neerlinter)",
    "sg:classifiers":[
        {
            "category":"Professional",
            "subcategory":"Lawyer & Legal Services",
            "type":"Services"
        }
    ],
    "sg:phone":"+32 11 78 30 83",
    "sg:postcode":"3350",
    "sg:province":"Vlaams-Brabant",
    "wof:name":"Spiritus Kristien",
    "wof:placetype":"venue"
},
  "geometry": {"coordinates":[5.0643911362,50.8061676025],"type":"Point"}
}