{
  "type": "Feature",
  "properties": {
    "iso:country":"BE",
    "sg:address":"Vondelparklaan 12",
    "sg:city":"Dendermonde",
    "sg:orig_category":"DIVERSE RECREATIEVE ACTIVITEITEN",
    "sg:phone":"+32 52 21 66 46",
    "sg:postcode":"9200",
    "sg:province":"Oost-Vlaanderen",
    "wof:name":"Filatelistische Kring",
    "wof:placetype":"venue"
},
  "geometry": {"coordinates":[4.1042780876,51.0203857422],"type":"Point"}
}