{
  "type": "Feature",
  "properties": {
    "addr:full":"Rue Du Midi 4b Renaix Oost-Vlaanderen 9600",
    "addr:housenumber":"4b",
    "addr:postcode":"9600",
    "addr:street":"Rue Du Midi",
    "iso:country":"BE",
    "sg:address":"Rue Du Midi 4b",
    "sg:city":"Renaix",
    "sg:classifiers":[
        {
            "category":"Banks & Credit Unions",
            "subcategory":"Financial Services",
            "type":"Services"
        }
    ],
    "sg:phone":"+32 55 20 94 65",
    "sg:postcode":"9600",
    "sg:province":"Oost-Vlaanderen",
    "sg:tags":[
        "loan",
        "mortgage"
    ],
    "wof:name":"Vercruysse Bvba",
    "wof:placetype":"venue"
},
  "geometry": {"coordinates":[3.6034491062,50.746925354],"type":"Point"}
}