{
  "type": "Feature",
  "properties": {
    "iso:country":"BE",
    "sg:address":"Rupelmondestraat 99",
    "sg:city":"Kruibeke (bazel)",
    "sg:classifiers":[
        {
            "category":"Food & Beverages",
            "subcategory":"Groceries & Convenience Stores",
            "type":"Retail Goods"
        }
    ],
    "sg:phone":"+32 3 774 10 41",
    "sg:postcode":"9150",
    "sg:province":"Oost-Vlaanderen",
    "sg:tags":[
        "grocer"
    ],
    "wof:name":"Van Hul K",
    "wof:placetype":"venue"
},
  "geometry": {"coordinates":[4.2968978882,51.1443061829],"type":"Point"}
}