{
  "type": "Feature",
  "properties": {
    "iso:country":"BE",
    "sg:address":"Chemin Close 15",
    "sg:city":"Malmedy (bellevaux-lignueville)",
    "sg:classifiers":[
        {
            "category":"Professional",
            "subcategory":"Lawyer & Legal Services",
            "type":"Services"
        }
    ],
    "sg:phone":"+32 80 33 78 03",
    "sg:postcode":"4960",
    "sg:province":"Li\u00e8ge",
    "wof:name":"Baumel A",
    "wof:placetype":"venue"
},
  "geometry": {"coordinates":[6.0531868935,50.3719902039],"type":"Point"}
}