{
  "type": "Feature",
  "properties": {
    "addr:full":"Vandenboogaerdestraat 108 Sint-jans-molenbeek/molenbeek-saint-jean Bruxelles-Capitale 1080",
    "addr:housenumber":"108",
    "addr:postcode":"1080",
    "addr:street":"Vandenboogaerdestraat",
    "iso:country":"BE",
    "sg:address":"Vandenboogaerdestraat 108",
    "sg:city":"Sint-jans-molenbeek/molenbeek-saint-jean",
    "sg:orig_category":"Gedistilleerde dranken and aperitieven Fab Wijnen Fab",
    "sg:phone":"+32 2 423 48 11",
    "sg:postcode":"1080",
    "sg:province":"Bruxelles-Capitale",
    "wof:name":"Bacardi-martini Belgium/bacardi-martini",
    "wof:placetype":"venue"
},
  "geometry": {"coordinates":[4.3418622017,50.8637580872],"type":"Point"}
}