{
  "type": "Feature",
  "properties": {
    "iso:country":"BE",
    "sg:address":"Esenplein 4",
    "sg:city":"Diksmuide",
    "sg:orig_category":"Brood, gebak and snoepgoed",
    "sg:phone":"+32 51 50 10 99",
    "sg:postcode":"8600",
    "sg:province":"West-Vlaanderen",
    "wof:name":"R. Veryser",
    "wof:placetype":"venue"
},
  "geometry": {"coordinates":[2.8690049648,51.0319023132],"type":"Point"}
}