{
  "type": "Feature",
  "properties": {
    "addr:full":"Gemeenteplein 1 Hoegaarden Vlaams-Brabant 3320",
    "addr:housenumber":"1",
    "addr:postcode":"3320",
    "addr:street":"Gemeenteplein",
    "iso:country":"BE",
    "sg:address":"Gemeenteplein 1",
    "sg:city":"Hoegaarden",
    "sg:orig_category":"Offices du tourisme",
    "sg:phone":"+32 16 76 81 86",
    "sg:postcode":"3320",
    "sg:province":"Vlaams-Brabant",
    "wof:name":"Dienst Voor Toerisme",
    "wof:placetype":"venue"
},
  "geometry": {"coordinates":[4.8877401352,50.773765564],"type":"Point"}
}