{
  "type": "Feature",
  "properties": {
    "addr:full":"Lippenslaan 74 Knokke-heist West-Vlaanderen 8300",
    "addr:housenumber":"74",
    "addr:postcode":"8300",
    "addr:street":"Lippenslaan",
    "iso:country":"BE",
    "sg:address":"Lippenslaan 74",
    "sg:city":"Knokke-heist",
    "sg:orig_category":"Banques and organismes de cr\u00e9dit",
    "sg:phone":"+32 50 60 53 24",
    "sg:postcode":"8300",
    "sg:province":"West-Vlaanderen",
    "wof:name":"Dexia",
    "wof:placetype":"venue"
},
  "geometry": {"coordinates":[3.2882590294,51.3440933228],"type":"Point"}
}