{
  "type": "Feature",
  "properties": {
    "iso:country":"BE",
    "sg:address":"Sint-lambertusstraat 33",
    "sg:city":"Westerlo",
    "sg:classifiers":[
        {
            "category":"Arts & Performance",
            "subcategory":"Theater",
            "type":"Entertainment"
        }
    ],
    "sg:phone":"+32 14 54 97 75",
    "sg:postcode":"2260",
    "sg:province":"Antwerpen",
    "sg:tags":[
        "concert-halls",
        "theatre"
    ],
    "wof:name":"Krekke (de)",
    "wof:placetype":"venue"
},
  "geometry": {"coordinates":[4.919025898,51.0902481079],"type":"Point"}
}