{
  "type": "Feature",
  "properties": {
    "iso:country":"BE",
    "sg:address":"Rue De Martilly 20",
    "sg:city":"Herbeumont",
    "sg:orig_category":"Eleveurs de bovins",
    "sg:phone":"+32 61 27 98 55",
    "sg:postcode":"6887",
    "sg:province":"Luxembourg",
    "wof:name":"Raymond Maboge",
    "wof:placetype":"venue"
},
  "geometry": {"coordinates":[5.23706007,49.7813262939],"type":"Point"}
}