{
  "type": "Feature",
  "properties": {
    "addr:full":"Chauss\u00c9e De Verviers 18 Theux Li\u00e8ge 4910",
    "addr:housenumber":"18",
    "addr:postcode":"4910",
    "addr:street":"Chausse\u0301E De Verviers",
    "iso:country":"BE",
    "sg:address":"Chauss\u00c9e De Verviers 18",
    "sg:city":"Theux",
    "sg:orig_category":"Artsen and specialisten",
    "sg:phone":"+32 87 54 24 35",
    "sg:postcode":"4910",
    "sg:province":"Li\u00e8ge",
    "wof:name":"Psychoth\u00c9r. Robinson B.",
    "wof:placetype":"venue"
},
  "geometry": {"coordinates":[5.8166351318,50.5386734009],"type":"Point"}
}