{
  "type": "Feature",
  "properties": {
    "iso:country":"BE",
    "sg:address":"Wouwerstraat 6",
    "sg:city":"Turnhout",
    "sg:orig_category":"Vertalers and tolken",
    "sg:phone":"+32 14 43 94 89",
    "sg:postcode":"2300",
    "sg:province":"Antwerpen",
    "wof:name":"Vertalingen Dice",
    "wof:placetype":"venue"
},
  "geometry": {"coordinates":[4.9461269379,51.3277511597],"type":"Point"}
}