{
  "type": "Feature",
  "properties": {
    "iso:country":"BE",
    "sg:address":"Rue De Genville 90",
    "sg:city":"Orp-jauche (jandrain-jandrenouille)",
    "sg:classifiers":[
        {
            "category":"Wholesale",
            "subcategory":"Wine & Distilled Alcoholic Beverages",
            "type":"Manufacturing & Wholesale Goods"
        }
    ],
    "sg:phone":"+32 19 63 55 58",
    "sg:postcode":"1350",
    "sg:province":"Brabant Wallon",
    "sg:tags":[
        "whol",
        "-",
        "spirit",
        "mfg"
    ],
    "wof:name":"Bonne Bouteille (la)",
    "wof:placetype":"venue"
},
  "geometry": {"coordinates":[4.9813990593,50.6833534241],"type":"Point"}
}