{
  "type": "Feature",
  "properties": {
    "addr:full":"Rue Ernest Gilot 46 Wanze Li\u00e8ge 4520",
    "addr:housenumber":"46",
    "addr:postcode":"4520",
    "addr:street":"Rue Ernest Gilot",
    "iso:country":"BE",
    "sg:address":"Rue Ernest Gilot 46",
    "sg:city":"Wanze",
    "sg:orig_category":"Dierenartsen",
    "sg:phone":"+32 85 23 05 29",
    "sg:postcode":"4520",
    "sg:province":"Li\u00e8ge",
    "wof:name":"Eric Petit",
    "wof:placetype":"venue"
},
  "geometry": {"coordinates":[5.2321920395,50.5401649475],"type":"Point"}
}