{
  "type": "Feature",
  "properties": {
    "addr:full":"All\u00c9e De Fanson 9 Ferrieres Li\u00e8ge 4190",
    "addr:housenumber":"9",
    "addr:postcode":"4190",
    "addr:street":"Alle\u0301E De Fanson",
    "iso:country":"BE",
    "sg:address":"All\u00c9e De Fanson 9",
    "sg:city":"Ferrieres",
    "sg:orig_category":"Ordinateurs and \u00e9quipement informatique",
    "sg:phone":"+32 4 369 30 32",
    "sg:postcode":"4190",
    "sg:province":"Li\u00e8ge",
    "wof:name":"C.p.c.",
    "wof:placetype":"venue"
},
  "geometry": {"coordinates":[5.6009960175,50.4515686035],"type":"Point"}
}