{
  "type": "Feature",
  "properties": {
    "addr:full":"Lindenlaan 18 Beerse Antwerpen 2340",
    "addr:housenumber":"18",
    "addr:postcode":"2340",
    "addr:street":"Lindenlaan",
    "iso:country":"BE",
    "sg:address":"Lindenlaan 18",
    "sg:city":"Beerse",
    "sg:orig_category":"Artsen and specialisten",
    "sg:phone":"+32 14 61 88 18",
    "sg:postcode":"2340",
    "sg:province":"Antwerpen",
    "wof:name":"L. Mylemans",
    "wof:placetype":"venue"
},
  "geometry": {"coordinates":[4.8535108566,51.3193664551],"type":"Point"}
}