{
  "type": "Feature",
  "properties": {
    "iso:country":"BE",
    "sg:address":"Verheyleweghenstraat 30b1",
    "sg:city":"Sint-lambrechts-woluwe/woluwe-saint-lambert",
    "sg:orig_category":"Boekhouders",
    "sg:postcode":"1200",
    "sg:province":"Bruxelles-Capitale",
    "wof:name":"Thierry Rigolet",
    "wof:placetype":"venue"
},
  "geometry": {"coordinates":[4.4256978035,50.8479194641],"type":"Point"}
}