{
  "type": "Feature",
  "properties": {
    "addr:full":"Turnhoutsebaan 116 Malle (oostmalle) Antwerpen 2390",
    "addr:housenumber":"116",
    "addr:postcode":"2390",
    "addr:street":"Turnhoutsebaan",
    "iso:country":"BE",
    "sg:address":"Turnhoutsebaan 116",
    "sg:city":"Malle (oostmalle)",
    "sg:classifiers":[
        {
            "category":"Professional",
            "subcategory":"Detective & Security Services",
            "type":"Services"
        }
    ],
    "sg:phone":"+32 3 311 68 72",
    "sg:postcode":"2390",
    "sg:province":"Antwerpen",
    "sg:tags":[
        "installation",
        "alarm",
        "-",
        "system"
    ],
    "wof:name":"Sterkens Alarmsystemen Nv",
    "wof:placetype":"venue"
},
  "geometry": {"coordinates":[4.747025013,51.3012161255],"type":"Point"}
}