{
  "type": "Feature",
  "properties": {
    "iso:country":"BE",
    "sg:address":"Haachtsesteenweg 4",
    "sg:city":"Steenokkerzeel",
    "sg:orig_category":"Slagers",
    "sg:phone":"+32 16 65 19 38",
    "sg:postcode":"1820",
    "sg:province":"Vlaams-Brabant",
    "wof:name":"Dega",
    "wof:placetype":"venue"
},
  "geometry": {"coordinates":[4.5209841728,50.9266662598],"type":"Point"}
}