{
  "type": "Feature",
  "properties": {
    "iso:country":"BE",
    "sg:address":"Bulskampstraat 98",
    "sg:city":"Veurne",
    "sg:classifiers":[
        {
            "category":"Building & Trades",
            "subcategory":"Pest Control",
            "type":"Services"
        }
    ],
    "sg:phone":"+32 58 31 14 58",
    "sg:postcode":"8630",
    "sg:province":"West-Vlaanderen",
    "sg:tags":[
        "painting",
        "contractor"
    ],
    "wof:name":"Jonckheere P",
    "wof:placetype":"venue"
},
  "geometry": {"coordinates":[2.6489899158,51.0528793335],"type":"Point"}
}