{
  "type": "Feature",
  "properties": {
    "addr:full":"Dorpspln 5 Ledegem 8768",
    "addr:housenumber":"5",
    "addr:postcode":"8768",
    "addr:street":"Dorpspln",
    "iso:country":"BE",
    "sg:address":"Dorpspln 5",
    "sg:city":"Ledegem",
    "sg:classifiers":[
        {
            "category":"Banks & Credit Unions",
            "subcategory":"Bank",
            "type":"Services"
        }
    ],
    "sg:phone":"+32 56 50 90 67",
    "sg:postcode":"8768",
    "wof:name":"Bank Van Roeselare",
    "wof:placetype":"venue"
},
  "geometry": {"coordinates":[3.1787199974,50.8758811951],"type":"Point"}
}