{
  "type": "Feature",
  "properties": {
    "addr:full":"Zavelstraat 48 Dilbeek Vlaams-Brabant 1700",
    "addr:housenumber":"48",
    "addr:postcode":"1700",
    "addr:street":"Zavelstraat",
    "iso:country":"BE",
    "sg:address":"Zavelstraat 48",
    "sg:city":"Dilbeek",
    "sg:orig_category":"Producteurs de fruits",
    "sg:phone":"+32 2 453 94 70",
    "sg:postcode":"1700",
    "sg:province":"Vlaams-Brabant",
    "wof:name":"Joanna Tirry",
    "wof:placetype":"venue"
},
  "geometry": {"coordinates":[4.223282814,50.8737258911],"type":"Point"}
}