{
  "type": "Feature",
  "properties": {
    "addr:full":"Rue Du Ch\u00c2teau 15 Les Bons Villers Hainaut 6210",
    "addr:housenumber":"15",
    "addr:postcode":"6210",
    "addr:street":"Rue Du Cha\u0302Teau",
    "iso:country":"BE",
    "sg:address":"Rue Du Ch\u00c2teau 15",
    "sg:city":"Les Bons Villers",
    "sg:orig_category":"Loodgieterij, verwarming and sanitaire installaties",
    "sg:phone":"+32 71 85 02 62",
    "sg:postcode":"6210",
    "sg:province":"Hainaut",
    "wof:name":"Lagneaux Daniel",
    "wof:placetype":"venue"
},
  "geometry": {"coordinates":[4.4511561394,50.5378227234],"type":"Point"}
}