{
  "type": "Feature",
  "properties": {
    "addr:full":"Chauss\u00e9e De Louvain 231 Bruxelles (saint-josse-ten-noode) Bruxelles-Capitale 1210",
    "addr:housenumber":"231",
    "addr:postcode":"1210",
    "addr:street":"Chausse\u0301E De Louvain",
    "iso:country":"BE",
    "sg:address":"Chauss\u00e9e De Louvain 231",
    "sg:city":"Bruxelles (saint-josse-ten-noode)",
    "sg:classifiers":[
        {
            "category":"Cinema",
            "subcategory":"Movie Rental",
            "type":"Entertainment"
        }
    ],
    "sg:phone":"+32 2 735 38 78",
    "sg:postcode":"1210",
    "sg:province":"Bruxelles-Capitale",
    "sg:tags":[
        "-",
        "supply"
    ],
    "wof:name":"Acz Cin\u00e9 Vid\u00e9o Son",
    "wof:placetype":"venue"
},
  "geometry": {"coordinates":[4.3825278282,50.8511581421],"type":"Point"}
}