{
  "type": "Feature",
  "properties": {
    "iso:country":"BE",
    "sg:address":"Franklin Rooseveltlaan 64",
    "sg:city":"Waregem",
    "sg:classifiers":[
        {
            "category":"Professional",
            "subcategory":"Lawyer & Legal Services",
            "type":"Services"
        }
    ],
    "sg:phone":"+32 56 32 30 97",
    "sg:postcode":"8790",
    "sg:province":"West-Vlaanderen",
    "wof:name":"Couvreur C",
    "wof:placetype":"venue"
},
  "geometry": {"coordinates":[3.4385259151,50.8798370361],"type":"Point"}
}