{
  "type": "Feature",
  "properties": {
    "addr:full":"J.f. Kennedystraat 1 As Limburg 3668",
    "addr:housenumber":"1 as",
    "addr:postcode":"3668",
    "addr:street":"J.F. Kennedystraat;Limburg",
    "iso:country":"BE",
    "sg:address":"J.f. Kennedystraat 1",
    "sg:city":"As",
    "sg:orig_category":"Kapsalons",
    "sg:phone":"+32 89 65 73 60",
    "sg:postcode":"3668",
    "sg:province":"Limburg",
    "wof:name":"Coiffure Elly",
    "wof:placetype":"venue"
},
  "geometry": {"coordinates":[5.6172537804,51.0309181213],"type":"Point"}
}