{
  "type": "Feature",
  "properties": {
    "iso:country":"BE",
    "sg:address":"Kuurnsestraat 10",
    "sg:city":"Harelbeke",
    "sg:classifiers":[
        {
            "category":"Insurance",
            "subcategory":"Life Insurance",
            "type":"Services"
        }
    ],
    "sg:phone":"+32 56 71 30 41",
    "sg:postcode":"8531",
    "sg:province":"West-Vlaanderen",
    "sg:tags":[
        "assurance"
    ],
    "wof:name":"N.m.k.n.",
    "wof:placetype":"venue"
},
  "geometry": {"coordinates":[3.2985351086,50.8808670044],"type":"Point"}
}