{
  "type": "Feature",
  "properties": {
    "addr:full":"Tempelstraat 16 Ieper West-Vlaanderen 8900",
    "addr:housenumber":"16",
    "addr:postcode":"8900",
    "addr:street":"Tempelstraat",
    "iso:country":"BE",
    "sg:address":"Tempelstraat 16",
    "sg:city":"Ieper",
    "sg:classifiers":[
        {
            "category":"Shopping",
            "subcategory":"Clothing, Apparel, & Fashions",
            "type":"Retail Goods"
        }
    ],
    "sg:phone":"+32 57 21 67 01",
    "sg:postcode":"8900",
    "sg:province":"West-Vlaanderen",
    "sg:tags":[
        "lady",
        "clothing",
        "-"
    ],
    "wof:name":"Senso",
    "wof:placetype":"venue"
},
  "geometry": {"coordinates":[2.8815100193,50.8496284485],"type":"Point"}
}