{
  "type": "Feature",
  "properties": {
    "iso:country":"BE",
    "sg:address":"Rue Maurice Canon 5ba",
    "sg:city":"Ecaussinnes",
    "sg:orig_category":"Dameskledingzaken",
    "sg:phone":"+32 67 49 07 20",
    "sg:postcode":"7190",
    "sg:province":"Hainaut",
    "wof:name":"La Solderie",
    "wof:placetype":"venue"
},
  "geometry": {"coordinates":[4.1752362251,50.5700759888],"type":"Point"}
}