{
  "type": "Feature",
  "properties": {
    "iso:country":"BE",
    "sg:address":"Rue De La Burdinale 24",
    "sg:city":"Heron",
    "sg:orig_category":"Computers and computerapparatuur Software ontwikkeling and ontwerp",
    "sg:phone":"+32 85 71 26 65",
    "sg:postcode":"4217",
    "sg:province":"Li\u00e8ge",
    "wof:name":"R.v.c.",
    "wof:placetype":"venue"
},
  "geometry": {"coordinates":[5.0667290688,50.5544815063],"type":"Point"}
}