{
  "type": "Feature",
  "properties": {
    "addr:full":"Rue De La Montagne 47 Sambreville (falisolle) Namur 5060",
    "addr:housenumber":"47",
    "addr:postcode":"5060",
    "addr:street":"Rue De La Montagne",
    "iso:country":"BE",
    "sg:address":"Rue De La Montagne 47",
    "sg:city":"Sambreville (falisolle)",
    "sg:classifiers":[
        {
            "category":"Retail",
            "subcategory":"Event Space",
            "type":"Services"
        }
    ],
    "sg:phone":"+32 71 77 38 23",
    "sg:postcode":"5060",
    "sg:province":"Namur",
    "sg:tags":[
        "rental",
        "-",
        "hall"
    ],
    "wof:name":"Salle Du Petit Fond",
    "wof:placetype":"venue"
},
  "geometry": {"coordinates":[4.6285200119,50.4448738098],"type":"Point"}
}