{
  "type": "Feature",
  "properties": {
    "addr:full":"Chauss\u00e9e De Wavre 1044 Bruxelles (auderghem) Bruxelles-Capitale 1160",
    "addr:postcode":"1044;1160",
    "addr:street":"Chausse\u0301E De Wavre",
    "iso:country":"BE",
    "sg:address":"Chauss\u00e9e De Wavre 1044",
    "sg:city":"Bruxelles (auderghem)",
    "sg:classifiers":[
        {
            "category":"Autos & Motor Vehicles",
            "subcategory":"Auto Supplies",
            "type":"Retail Goods"
        }
    ],
    "sg:phone":"+32 2 733 86 09",
    "sg:postcode":"1160",
    "sg:province":"Bruxelles-Capitale",
    "sg:tags":[
        "access",
        "automobile",
        "part",
        "-"
    ],
    "wof:name":"Guiot A",
    "wof:placetype":"venue"
},
  "geometry": {"coordinates":[4.40061903,50.8242149353],"type":"Point"}
}