{
  "type": "Feature",
  "properties": {
    "iso:country":"BE",
    "sg:address":"Grote Baan 193",
    "sg:city":"Beveren",
    "sg:orig_category":"Fietsen Watersport-, Sport- and Kampeerbenodigdheden Verhuur",
    "sg:phone":"+32 3 775 14 41",
    "sg:postcode":"9120",
    "sg:province":"Oost-Vlaanderen",
    "wof:name":"Koen De Rijck",
    "wof:placetype":"venue"
},
  "geometry": {"coordinates":[4.2840771675,51.2202262878],"type":"Point"}
}