{
  "type": "Feature",
  "properties": {
    "iso:country":"BE",
    "sg:address":"Stationsstraat 32",
    "sg:city":"Waarschoot",
    "sg:orig_category":"Pain, p\u00e2tisseries and confiseries",
    "sg:phone":"+32 9 377 97 10",
    "sg:postcode":"9950",
    "sg:province":"Oost-Vlaanderen",
    "wof:name":"Caroline De Spiegelaere",
    "wof:placetype":"venue"
},
  "geometry": {"coordinates":[3.6089890003,51.1516418457],"type":"Point"}
}