{
  "type": "Feature",
  "properties": {
    "iso:country":"BE",
    "sg:address":"Mandellaan 377-379",
    "sg:city":"Roeselare",
    "sg:orig_category":"Fietsen",
    "sg:phone":"+32 51 22 50 50",
    "sg:postcode":"8800",
    "sg:province":"West-Vlaanderen",
    "wof:name":"Antoon Rambout",
    "wof:placetype":"venue"
},
  "geometry": {"coordinates":[3.1465120316,50.9441757202],"type":"Point"}
}