{
  "type": "Feature",
  "properties": {
    "iso:country":"BE",
    "sg:address":"Quartier De La Gare 17",
    "sg:city":"Bernissart (blaton)",
    "sg:classifiers":[
        {
            "category":"Real Estate",
            "subcategory":"Architect",
            "type":"Services"
        }
    ],
    "sg:phone":"+32 69 57 64 87",
    "sg:postcode":"7321",
    "sg:province":"Hainaut",
    "wof:name":"Moureau F",
    "wof:placetype":"venue"
},
  "geometry": {"coordinates":[3.6650850773,50.5054092407],"type":"Point"}
}