{
  "type": "Feature",
  "properties": {
    "addr:full":". Brussel Bruxelles-Capitale 1030",
    "addr:postcode":"1030",
    "iso:country":"BE",
    "sg:address":".",
    "sg:city":"Brussel",
    "sg:orig_category":"Sportclubs",
    "sg:phone":"+32 2 215 43 09",
    "sg:postcode":"1030",
    "sg:province":"Bruxelles-Capitale",
    "wof:name":"Basket Brabant",
    "wof:placetype":"venue"
},
  "geometry": {"coordinates":[4.3749351501,50.8680000305],"type":"Point"}
}