{
  "type": "Feature",
  "properties": {
    "iso:country":"BE",
    "sg:address":"Rue Du Moulin D'en Haut 31",
    "sg:city":"Mons",
    "sg:orig_category":"Alimentation sp\u00e9cialis\u00e9e. Epiceries",
    "sg:phone":"+32 65 88 58 60",
    "sg:postcode":"7012",
    "sg:province":"Hainaut",
    "wof:name":"Ceccilia Atzeni",
    "wof:placetype":"venue"
},
  "geometry": {"coordinates":[3.8994269371,50.438911438],"type":"Point"}
}