{
  "type": "Feature",
  "properties": {
    "iso:country":"BE",
    "sg:address":"Rue Des Sports 6bd",
    "sg:city":"La Louvi\u00c8re",
    "sg:orig_category":"Sportclubs",
    "sg:phone":"+32 496 21 49 22",
    "sg:postcode":"7110",
    "sg:province":"Hainaut",
    "wof:name":"B.b.c. Baudets Maurage",
    "wof:placetype":"venue"
},
  "geometry": {"coordinates":[4.1505050659,50.4826698303],"type":"Point"}
}