{
  "type": "Feature",
  "properties": {
    "addr:full":"Rue Alphonse-j\u00c9rouville 120 Libin Luxembourg 6890",
    "addr:housenumber":"120",
    "addr:postcode":"6890",
    "addr:street":"Rue Alphonse-Je\u0301Rouville",
    "iso:country":"BE",
    "sg:address":"Rue Alphonse-j\u00c9rouville 120",
    "sg:city":"Libin",
    "sg:orig_category":"Rundveehouders",
    "sg:phone":"+32 61 22 28 76",
    "sg:postcode":"6890",
    "sg:province":"Luxembourg",
    "wof:name":"Marcel Plennevaux",
    "wof:placetype":"venue"
},
  "geometry": {"coordinates":[5.278096199,49.9224700928],"type":"Point"}
}