{
  "type": "Feature",
  "properties": {
    "addr:full":"Bredabaan 948a Brasschaat Antwerpen 2930",
    "addr:housenumber":"948a",
    "addr:postcode":"2930",
    "addr:street":"Bredabaan",
    "iso:country":"BE",
    "sg:address":"Bredabaan 948a",
    "sg:city":"Brasschaat",
    "sg:orig_category":"Dansscholen",
    "sg:phone":"+32 3 653 18 82",
    "sg:postcode":"2930",
    "sg:province":"Antwerpen",
    "wof:name":"Spillemaeckers M.",
    "wof:placetype":"venue"
},
  "geometry": {"coordinates":[4.5278449059,51.3382835388],"type":"Point"}
}