{
  "type": "Feature",
  "properties": {
    "iso:country":"BE",
    "sg:address":"Rerum Novarumlaan 39",
    "sg:city":"Malle",
    "sg:orig_category":"Gespecialiseerde residenti\u00eble bouw",
    "sg:phone":"+32 3 312 44 10",
    "sg:postcode":"2390",
    "sg:province":"Antwerpen",
    "wof:name":"Jozef Nicolai",
    "wof:placetype":"venue"
},
  "geometry": {"coordinates":[4.6859078407,51.3002700806],"type":"Point"}
}