{
  "type": "Feature",
  "properties": {
    "iso:country":"BE",
    "sg:address":"Rue Du Pays-bas 20",
    "sg:city":"Charleroi",
    "sg:classifiers":[
        {
            "category":"Shopping",
            "subcategory":"Computers & Home Electronics",
            "type":"Retail Goods"
        }
    ],
    "sg:phone":"+32 71 30 77 27",
    "sg:postcode":"6061",
    "sg:province":"Hainaut",
    "sg:tags":[
        "equipment",
        "household",
        "electrical",
        "appliance",
        "electronic"
    ],
    "wof:name":"Melerva Sa",
    "wof:placetype":"venue"
},
  "geometry": {"coordinates":[4.4867758751,50.3964881897],"type":"Point"}
}