{
  "type": "Feature",
  "properties": {
    "iso:country":"BE",
    "sg:address":"Rue De La Bovi\u00c8re 9",
    "sg:city":"Aywaille",
    "sg:orig_category":"Boekhouders",
    "sg:phone":"+32 4 384 52 63",
    "sg:postcode":"4920",
    "sg:province":"Li\u00e8ge",
    "wof:name":"Christiane Gilles",
    "wof:placetype":"venue"
},
  "geometry": {"coordinates":[5.6702589989,50.473651886],"type":"Point"}
}