{
  "type": "Feature",
  "properties": {
    "addr:full":". Blankenberge (groot) West-Vlaanderen 8370",
    "addr:postcode":"8370",
    "addr:street":"Groot West-Vlaanderen",
    "iso:country":"BE",
    "sg:address":".",
    "sg:city":"Blankenberge (groot)",
    "sg:orig_category":"Apotheken",
    "sg:phone":"+32 900 10 500",
    "sg:postcode":"8370",
    "sg:province":"West-Vlaanderen",
    "wof:name":"Apothekers Van Wacht",
    "wof:placetype":"venue"
},
  "geometry": {"coordinates":[3.1343250275,51.3109512329],"type":"Point"}
}