{
  "type": "Feature",
  "properties": {
    "iso:country":"BE",
    "sg:address":"Hanswijckvaart 77",
    "sg:city":"Mechelen",
    "sg:orig_category":"Metaalbehandeling and -bekleding",
    "sg:phone":"+32 15 41 69 11",
    "sg:postcode":"2800",
    "sg:province":"Antwerpen",
    "wof:name":"Belgium Forge",
    "wof:placetype":"venue"
},
  "geometry": {"coordinates":[4.4903979301,51.0105171204],"type":"Point"}
}