{
  "type": "Feature",
  "properties": {
    "iso:country":"BE",
    "sg:address":"Dorpsstraat 25",
    "sg:city":"Bocholt",
    "sg:classifiers":[
        {
            "category":"Personal",
            "subcategory":"Beauty Salon",
            "type":"Services"
        }
    ],
    "sg:phone":"+32 89 46 53 84",
    "sg:postcode":"3950",
    "sg:province":"Limburg",
    "sg:tags":[
        "de",
        "coiffure"
    ],
    "wof:name":"Kapsalon Christine",
    "wof:placetype":"venue"
},
  "geometry": {"coordinates":[5.5793390274,51.1731567383],"type":"Point"}
}