{
  "type": "Feature",
  "properties": {
    "iso:country":"BE",
    "sg:address":"Potteriehoek 22",
    "sg:city":"Harelbeke",
    "sg:orig_category":"Woningbouw",
    "sg:phone":"+32 56 66 56 49",
    "sg:postcode":"8531",
    "sg:province":"West-Vlaanderen",
    "wof:name":"Vlieghe Eric",
    "wof:placetype":"venue"
},
  "geometry": {"coordinates":[3.2871301174,50.9032478333],"type":"Point"}
}