{
  "type": "Feature",
  "properties": {
    "iso:country":"BE",
    "sg:address":"Antwerpsesteenweg 16",
    "sg:city":"Kontich",
    "sg:orig_category":"M\u00e9decins and sp\u00e9cialistes",
    "sg:phone":"+32 3 457 88 71",
    "sg:postcode":"2550",
    "sg:province":"Antwerpen",
    "wof:name":"J.w.d. Van Doorn",
    "wof:placetype":"venue"
},
  "geometry": {"coordinates":[4.4468212128,51.1358718872],"type":"Point"}
}