{
  "type": "Feature",
  "properties": {
    "addr:full":"Van Frachenlaan 64 Steenokkerzeel Vlaams-Brabant 1820",
    "addr:housenumber":"64",
    "addr:postcode":"1820",
    "addr:street":"Van Frachenlaan",
    "iso:country":"BE",
    "sg:address":"Van Frachenlaan 64",
    "sg:city":"Steenokkerzeel",
    "sg:orig_category":"Banques and organismes de cr\u00e9dit",
    "sg:phone":"+32 2 751 87 35",
    "sg:postcode":"1820",
    "sg:province":"Vlaams-Brabant",
    "wof:name":"Bbl",
    "wof:placetype":"venue"
},
  "geometry": {"coordinates":[4.5084462166,50.913772583],"type":"Point"}
}