{
  "type": "Feature",
  "properties": {
    "iso:country":"BE",
    "sg:address":"Rue Joseph Wettinck 72",
    "sg:city":"Seraing",
    "sg:orig_category":"Pharmaciens",
    "sg:phone":"+32 4 233 93 95",
    "sg:postcode":"4101",
    "sg:province":"Li\u00e8ge",
    "wof:name":"Pharmacie Du Peuple",
    "wof:placetype":"venue"
},
  "geometry": {"coordinates":[5.5011048317,50.6149787903],"type":"Point"}
}