{
  "type": "Feature",
  "properties": {
    "iso:country":"BE",
    "sg:address":"Rue Du T\u00e9nimont 19",
    "sg:city":"Durbuy (barvaux-sur-ourthe)",
    "sg:classifiers":[
        {
            "category":"Building & Trades",
            "subcategory":"Pest Control",
            "type":"Services"
        }
    ],
    "sg:phone":"+32 86 21 11 73",
    "sg:postcode":"6940",
    "sg:province":"Luxembourg",
    "sg:tags":[
        "painting",
        "contractor"
    ],
    "wof:name":"Sougn\u00e9 & Fils Sprl",
    "wof:placetype":"venue"
},
  "geometry": {"coordinates":[5.4543361664,50.3515777588],"type":"Point"}
}