{
  "type": "Feature",
  "properties": {
    "iso:country":"BE",
    "sg:address":"Hovestraat 11",
    "sg:city":"Edegem",
    "sg:classifiers":[
        {
            "category":"Deli",
            "type":"Food & Drink"
        }
    ],
    "sg:phone":"+32 3 288 50 26",
    "sg:postcode":"2650",
    "sg:province":"Antwerpen",
    "sg:tags":[
        "delicatessen"
    ],
    "wof:name":"Filet D'anvers",
    "wof:placetype":"venue"
},
  "geometry": {"coordinates":[4.4471077919,51.1555480957],"type":"Point"}
}