{
  "type": "Feature",
  "properties": {
    "iso:country":"BE",
    "sg:address":"Rue Du Progr\u00c8s 8",
    "sg:city":"Chapelle-lez-herlaimont",
    "sg:orig_category":"Boekhouders",
    "sg:phone":"+32 64 44 47 79",
    "sg:postcode":"7160",
    "sg:province":"Hainaut",
    "wof:name":"Paul Lambert",
    "wof:placetype":"venue"
},
  "geometry": {"coordinates":[4.2809171677,50.4687271118],"type":"Point"}
}