{
  "type": "Feature",
  "properties": {
    "addr:full":"Rue Saint-pierre 4 Burdinne (lamontz\u00e9e) Li\u00e8ge 4210",
    "addr:housenumber":"4",
    "addr:postcode":"4210",
    "addr:street":"Rue Saint-Pierre;Lamontze\u0301E",
    "iso:country":"BE",
    "sg:address":"Rue Saint-pierre 4",
    "sg:city":"Burdinne (lamontz\u00e9e)",
    "sg:classifiers":[
        {
            "category":"Arena",
            "subcategory":"Sports Club",
            "type":"Entertainment"
        }
    ],
    "sg:phone":"+32 85 71 22 43",
    "sg:postcode":"4210",
    "sg:province":"Li\u00e8ge",
    "wof:name":"Derclaye J",
    "wof:placetype":"venue"
},
  "geometry": {"coordinates":[5.089304924,50.5844917297],"type":"Point"}
}