{
  "type": "Feature",
  "properties": {
    "iso:country":"BE",
    "sg:address":"Rue Saint-nicolas 309",
    "sg:city":"Li\u00e8ge 1",
    "sg:classifiers":[
        {
            "category":"Bars & Pubs",
            "type":"Food & Drink"
        }
    ],
    "sg:phone":"+32 4 225 09 29",
    "sg:postcode":"4000",
    "sg:province":"Li\u00e8ge",
    "wof:name":"Geoffrey (le)",
    "wof:placetype":"venue"
},
  "geometry": {"coordinates":[5.5397219658,50.6390647888],"type":"Point"}
}