{
  "type": "Feature",
  "properties": {
    "iso:country":"BE",
    "sg:address":"Knokkestraat 626",
    "sg:city":"Knokke-heist",
    "sg:orig_category":"Installation \u00e9lectrique r\u00e9sidentielle",
    "sg:phone":"+32 50 60 97 42",
    "sg:postcode":"8300",
    "sg:province":"West-Vlaanderen",
    "wof:name":"E.m.s.",
    "wof:placetype":"venue"
},
  "geometry": {"coordinates":[3.2714550495,51.3401412964],"type":"Point"}
}