{
  "type": "Feature",
  "properties": {
    "addr:full":"Dorp 35 Zandhoven (pulderbos) Antwerpen 2242",
    "addr:housenumber":"35",
    "addr:postcode":"2242",
    "addr:street":"Dorp",
    "iso:country":"BE",
    "sg:address":"Dorp 35",
    "sg:city":"Zandhoven (pulderbos)",
    "sg:classifiers":[
        {
            "category":"Bars & Pubs",
            "type":"Food & Drink"
        }
    ],
    "sg:phone":"+32 3 484 32 79",
    "sg:postcode":"2242",
    "sg:province":"Antwerpen",
    "wof:name":"Klok (in De)",
    "wof:placetype":"venue"
},
  "geometry": {"coordinates":[4.6916651726,51.2182121277],"type":"Point"}
}