{
  "type": "Feature",
  "properties": {
    "iso:country":"BE",
    "sg:address":"Avenue Jules Destr\u00c9e 34",
    "sg:city":"Charleroi",
    "sg:classifiers":[
        {
            "category":"Restaurant",
            "type":"Food & Drink"
        }
    ],
    "sg:phone":"+32 71 31 57 09",
    "sg:postcode":"6031",
    "sg:province":"Hainaut",
    "wof:name":"Il Peccato",
    "wof:placetype":"venue"
},
  "geometry": {"coordinates":[4.4510297775,50.4195365906],"type":"Point"}
}