{
  "type": "Feature",
  "properties": {
    "iso:country":"BE",
    "sg:address":"Rue Brogniez 47",
    "sg:city":"Bruxelles (anderlecht)",
    "sg:orig_category":"Non-Classified Establishments",
    "sg:phone":"+32 2 527 17 81",
    "sg:postcode":"1070",
    "sg:province":"Bruxelles-Capitale",
    "wof:name":"Bivan Sprl",
    "wof:placetype":"venue"
},
  "geometry": {"coordinates":[4.3371191025,50.8419189453],"type":"Point"}
}