{
  "type": "Feature",
  "properties": {
    "addr:full":"Romeinse Kassei 26 Tongeren Limburg 3700",
    "addr:housenumber":"26",
    "addr:postcode":"3700",
    "addr:street":"Romeinse Kassei",
    "iso:country":"BE",
    "sg:address":"Romeinse Kassei 26",
    "sg:city":"Tongeren",
    "sg:classifiers":[
        {
            "category":"Social Services",
            "subcategory":"Job Training",
            "type":"Services"
        }
    ],
    "sg:phone":"+32 12 67 14 83",
    "sg:postcode":"3700",
    "sg:province":"Limburg",
    "sg:tags":[
        "coordinator",
        "safety"
    ],
    "wof:name":"Avc Bvba",
    "wof:placetype":"venue"
},
  "geometry": {"coordinates":[5.4533848763,50.7781105042],"type":"Point"}
}