{
  "type": "Feature",
  "properties": {
    "addr:full":"Onze-lieve-vrouwstraat 156 Heusden-zolder (zolder) Limburg 3550",
    "addr:housenumber":"156",
    "addr:postcode":"3550",
    "addr:street":"Onze-Lieve-Vrouwstraat",
    "iso:country":"BE",
    "sg:address":"Onze-lieve-vrouwstraat 156",
    "sg:city":"Heusden-zolder (zolder)",
    "sg:classifiers":[
        {
            "category":"Insurance",
            "subcategory":"Insurance Agent",
            "type":"Services"
        }
    ],
    "sg:phone":"+32 11 53 75 75",
    "sg:postcode":"3550",
    "sg:province":"Limburg",
    "sg:tags":[
        "broker"
    ],
    "wof:name":"Houbrechts Zakenkantoor",
    "wof:placetype":"venue"
},
  "geometry": {"coordinates":[5.2720417976,51.011428833],"type":"Point"}
}