{
  "type": "Feature",
  "properties": {
    "iso:country":"BE",
    "sg:address":"Astridstraat 17",
    "sg:city":"Rotselaar",
    "sg:orig_category":"Boekhouders",
    "sg:phone":"+32 16 44 90 34",
    "sg:postcode":"3110",
    "sg:province":"Vlaams-Brabant",
    "wof:name":"Felix Stuyckens",
    "wof:placetype":"venue"
},
  "geometry": {"coordinates":[4.7236318588,50.9417304993],"type":"Point"}
}