{
  "type": "Feature",
  "properties": {
    "addr:full":"Steenbakkerijen 32 Niel Antwerpen 2845",
    "addr:housenumber":"32",
    "addr:postcode":"2845",
    "addr:street":"Steenbakkerijen",
    "iso:country":"BE",
    "sg:address":"Steenbakkerijen 32",
    "sg:city":"Niel",
    "sg:orig_category":"Briques and tuiles Fab",
    "sg:phone":"+32 3 888 00 46",
    "sg:postcode":"2845",
    "sg:province":"Antwerpen",
    "wof:name":"Steenbakkerijen Damman",
    "wof:placetype":"venue"
},
  "geometry": {"coordinates":[4.3329749107,51.1000823975],"type":"Point"}
}