{
  "type": "Feature",
  "properties": {
    "addr:full":"Startelstraat 16 Sint-truiden Limburg 3800",
    "addr:housenumber":"16",
    "addr:postcode":"3800",
    "addr:street":"Startelstraat",
    "iso:country":"BE",
    "sg:address":"Startelstraat 16",
    "sg:city":"Sint-truiden",
    "sg:orig_category":"Fruitteelt",
    "sg:phone":"+32 11 31 25 54",
    "sg:postcode":"3800",
    "sg:province":"Limburg",
    "wof:name":"Vanderstraeten G. & R.",
    "wof:placetype":"venue"
},
  "geometry": {"coordinates":[5.2590517998,50.8436012268],"type":"Point"}
}