{
  "type": "Feature",
  "properties": {
    "addr:full":"Sint-nicolaasplaats 3-4 Antwerpen Antwerpen 2000",
    "addr:housenumber":"3-4",
    "addr:postcode":"2000",
    "addr:street":"Sint-Nicolaasplaats",
    "iso:country":"BE",
    "sg:address":"Sint-nicolaasplaats 3-4",
    "sg:city":"Antwerpen",
    "sg:orig_category":"Reisbureaus",
    "sg:phone":"+32 3 231 59 94",
    "sg:postcode":"2000",
    "sg:province":"Antwerpen",
    "wof:name":"Reizen Eurocult",
    "wof:placetype":"venue"
},
  "geometry": {"coordinates":[4.4056339264,51.220161438],"type":"Point"}
}