{
  "type": "Feature",
  "properties": {
    "iso:country":"BE",
    "sg:address":"Lindelaan 80",
    "sg:city":"Zwevegem",
    "sg:classifiers":[
        {
            "category":"Professional",
            "subcategory":"Computer Services",
            "type":"Services"
        }
    ],
    "sg:phone":"+32 56 75 70 08",
    "sg:postcode":"8550",
    "sg:province":"West-Vlaanderen",
    "sg:tags":[
        "-",
        "processing",
        "data"
    ],
    "wof:name":"L.n.c.-nuytten",
    "wof:placetype":"venue"
},
  "geometry": {"coordinates":[3.3277909756,50.8105926514],"type":"Point"}
}