{
  "type": "Feature",
  "properties": {
    "addr:full":"Grote Steenweg 408b4e Antwerpen Antwerpen 2600",
    "addr:housenumber":"408b4e",
    "addr:postcode":"2600",
    "addr:street":"Grote Steenweg",
    "iso:country":"BE",
    "sg:address":"Grote Steenweg 408b4e",
    "sg:city":"Antwerpen",
    "sg:orig_category":"Avocats and conseillers juridiques",
    "sg:phone":"+32 3 281 09 01",
    "sg:postcode":"2600",
    "sg:province":"Antwerpen",
    "wof:name":"Guy Cambr\u00c9",
    "wof:placetype":"venue"
},
  "geometry": {"coordinates":[4.4174151421,51.1974411011],"type":"Point"}
}