{
  "type": "Feature",
  "properties": {
    "addr:full":"Chemin Du Gros Tienne 1 La Hulpe Brabant Wallon 1310",
    "addr:housenumber":"1",
    "addr:postcode":"1310",
    "addr:street":"Chemin Du Gros Tienne",
    "iso:country":"BE",
    "sg:address":"Chemin Du Gros Tienne 1",
    "sg:city":"La Hulpe",
    "sg:classifiers":[
        {
            "category":"Professional",
            "subcategory":"Accounting & Tax Preparation",
            "type":"Services"
        }
    ],
    "sg:phone":"+32 2 654 15 21",
    "sg:postcode":"1310",
    "sg:province":"Brabant Wallon",
    "sg:tags":[
        "accountant"
    ],
    "wof:name":"De Ganck P",
    "wof:placetype":"venue"
},
  "geometry": {"coordinates":[4.4688577652,50.7207756042],"type":"Point"}
}