{
  "type": "Feature",
  "properties": {
    "addr:full":"Theet 42 Hamme Oost-Vlaanderen 9220",
    "addr:housenumber":"42",
    "addr:postcode":"9220",
    "addr:street":"Theet",
    "iso:country":"BE",
    "sg:address":"Theet 42",
    "sg:city":"Hamme",
    "sg:orig_category":"Installation \u00e9lectrique r\u00e9sidentielle",
    "sg:phone":"+32 52 48 01 43",
    "sg:postcode":"9220",
    "sg:province":"Oost-Vlaanderen",
    "wof:name":"Electro De Roover",
    "wof:placetype":"venue"
},
  "geometry": {"coordinates":[4.1299548149,51.0797996521],"type":"Point"}
}