{
  "type": "Feature",
  "properties": {
    "addr:full":"Avenue Des Sapins 1 Tournai Hainaut 7500",
    "addr:housenumber":"1",
    "addr:postcode":"7500",
    "addr:street":"Avenue Des Sapins",
    "iso:country":"BE",
    "sg:address":"Avenue Des Sapins 1",
    "sg:city":"Tournai",
    "sg:orig_category":"Location de logements sociaux",
    "sg:phone":"+32 69 22 27 41",
    "sg:postcode":"7500",
    "sg:province":"Hainaut",
    "wof:name":"Le Logis Tournaisien",
    "wof:placetype":"venue"
},
  "geometry": {"coordinates":[3.3752400875,50.6082191467],"type":"Point"}
}