{
  "type": "Feature",
  "properties": {
    "addr:full":"Rue Des B\u00c9guines 38 Sint-jans-molenbeek/molenbeek-saint-jean Bruxelles-Capitale 1080",
    "addr:housenumber":"38",
    "addr:postcode":"1080",
    "addr:street":"Rue Des Be\u0301Guines",
    "iso:country":"BE",
    "sg:address":"Rue Des B\u00c9guines 38",
    "sg:city":"Sint-jans-molenbeek/molenbeek-saint-jean",
    "sg:orig_category":"M\u00e9decins and sp\u00e9cialistes",
    "sg:phone":"+32 2 414 57 67",
    "sg:postcode":"1080",
    "sg:province":"Bruxelles-Capitale",
    "wof:name":"Marcel Lamonte",
    "wof:placetype":"venue"
},
  "geometry": {"coordinates":[4.3171467781,50.8574829102],"type":"Point"}
}