{
  "type": "Feature",
  "properties": {
    "addr:full":"Rue Du Vivier 124 Bastogne Luxembourg 6600",
    "addr:housenumber":"124",
    "addr:postcode":"6600",
    "addr:street":"Rue Du Vivier",
    "iso:country":"BE",
    "sg:address":"Rue Du Vivier 124",
    "sg:city":"Bastogne",
    "sg:classifiers":[
        {
            "category":"Shopping",
            "subcategory":"Luggage & Leather Goods",
            "type":"Retail Goods"
        }
    ],
    "sg:phone":"+32 61 21 37 03",
    "sg:postcode":"6600",
    "sg:province":"Luxembourg",
    "sg:tags":[
        "-"
    ],
    "wof:name":"Sabrina Maroquinerie",
    "wof:placetype":"venue"
},
  "geometry": {"coordinates":[5.7173857689,50.0019989014],"type":"Point"}
}