{
  "type": "Feature",
  "properties": {
    "addr:full":"Avenue Du Bourgmestre Jean Materne 32 Namur (jambes) Namur 5100",
    "addr:housenumber":"32",
    "addr:postcode":"5100",
    "addr:street":"Avenue Du Bourgmestre Jean Materne",
    "iso:country":"BE",
    "sg:address":"Avenue Du Bourgmestre Jean Materne 32",
    "sg:city":"Namur (jambes)",
    "sg:classifiers":[
        {
            "category":"Shopping",
            "subcategory":"Clothing, Apparel, & Fashions",
            "type":"Retail Goods"
        }
    ],
    "sg:phone":"+32 81 30 26 04",
    "sg:postcode":"5100",
    "sg:province":"Namur",
    "sg:tags":[
        "lady",
        "clothing",
        "-"
    ],
    "wof:name":"Ivoire",
    "wof:placetype":"venue"
},
  "geometry": {"coordinates":[4.8713750839,50.4566345215],"type":"Point"}
}