{
  "type": "Feature",
  "properties": {
    "iso:country":"BE",
    "sg:address":"Halensestraat 34",
    "sg:city":"Halen (zelem)",
    "sg:classifiers":[
        {
            "category":"Food & Beverages",
            "subcategory":"Groceries & Convenience Stores",
            "type":"Retail Goods"
        }
    ],
    "sg:phone":"+32 13 46 13 28",
    "sg:postcode":"3545",
    "sg:province":"Limburg",
    "sg:tags":[
        "grocer"
    ],
    "wof:name":"Superette Heidi",
    "wof:placetype":"venue"
},
  "geometry": {"coordinates":[5.1164269447,50.9724578857],"type":"Point"}
}