{
  "type": "Feature",
  "properties": {
    "addr:full":"Boulevard Edmond Machtens 83 Bruxelles (molenbeek-saint-jean) Bruxelles-Capitale 1080",
    "addr:housenumber":"83",
    "addr:postcode":"1080",
    "addr:street":"Boulevard Edmond Machtens",
    "iso:country":"BE",
    "sg:address":"Boulevard Edmond Machtens 83",
    "sg:city":"Bruxelles (molenbeek-saint-jean)",
    "sg:classifiers":[
        {
            "category":"Organizations",
            "subcategory":"Professional Association",
            "type":"Services"
        }
    ],
    "sg:phone":"+32 2 410 33 47",
    "sg:postcode":"1080",
    "sg:province":"Bruxelles-Capitale",
    "sg:tags":[
        "trade-union",
        "federation"
    ],
    "wof:name":"Fed.nation.negociants Bieres & Eaux De Boisson",
    "wof:placetype":"venue"
},
  "geometry": {"coordinates":[4.3131341934,50.8517532349],"type":"Point"}
}