{
  "type": "Feature",
  "properties": {
    "iso:country":"BE",
    "sg:address":"Hauwaart 69",
    "sg:city":"Oudenaarde (mater)",
    "sg:classifiers":[
        {
            "category":"Home & Garden",
            "subcategory":"Carpets & Floor Coverings",
            "type":"Retail Goods"
        }
    ],
    "sg:phone":"+32 55 45 69 28",
    "sg:postcode":"9700",
    "sg:province":"Oost-Vlaanderen",
    "sg:tags":[
        "layer",
        "mosaicists"
    ],
    "wof:name":"Hen Ruan Toul",
    "wof:placetype":"venue"
},
  "geometry": {"coordinates":[3.6643459797,50.8308906555],"type":"Point"}
}