{
  "type": "Feature",
  "properties": {
    "addr:full":"Rue L. Gilles 46 Fontaine-l'ev\u00eaque (leernes) Hainaut 6142",
    "addr:housenumber":"46",
    "addr:postcode":"6142",
    "addr:street":"Rue L. Gilles;Hainaut",
    "iso:country":"BE",
    "sg:address":"Rue L. Gilles 46",
    "sg:city":"Fontaine-l'ev\u00eaque (leernes)",
    "sg:classifiers":[
        {
            "category":"Sports & Exercise",
            "subcategory":"Stables",
            "type":"Entertainment"
        }
    ],
    "sg:phone":"+32 71 54 53 63",
    "sg:postcode":"6142",
    "sg:province":"Hainaut",
    "sg:tags":[
        "riding",
        "school"
    ],
    "wof:name":"Chevauchoire (la)",
    "wof:placetype":"venue"
},
  "geometry": {"coordinates":[-111.9644622803,46.2507972717],"type":"Point"}
}