{
  "type": "Feature",
  "properties": {
    "addr:full":"Zarrenplein 1 Kortemark West-Vlaanderen 8610",
    "addr:housenumber":"1",
    "addr:postcode":"8610",
    "addr:street":"Zarrenplein",
    "iso:country":"BE",
    "sg:address":"Zarrenplein 1",
    "sg:city":"Kortemark",
    "sg:orig_category":"Overheidsdiensten",
    "sg:phone":"+32 51 56 60 32",
    "sg:postcode":"8610",
    "sg:province":"West-Vlaanderen",
    "wof:name":"Gemeentehuis",
    "wof:placetype":"venue"
},
  "geometry": {"coordinates":[2.9586670399,51.0185127258],"type":"Point"}
}