{
  "type": "Feature",
  "properties": {
    "iso:country":"BE",
    "sg:address":"Dr.-van De Perrestraat 255",
    "sg:city":"Geel",
    "sg:orig_category":"Centres de fitness. Centres de relaxation and bien-\u00eatre",
    "sg:phone":"+32 14 58 11 37",
    "sg:postcode":"2440",
    "sg:province":"Antwerpen",
    "wof:name":"Solarium Super Fit",
    "wof:placetype":"venue"
},
  "geometry": {"coordinates":[4.9858269691,51.1791954041],"type":"Point"}
}