{
  "type": "Feature",
  "properties": {
    "iso:country":"BE",
    "sg:address":"Engelsdorfer Strasse 2",
    "sg:city":"Amel (born Zentrum)",
    "sg:classifiers":[
        {
            "category":"Manufacturing",
            "subcategory":"Tools & Machinery",
            "type":"Manufacturing & Wholesale Goods"
        }
    ],
    "sg:phone":"+32 80 57 03 67",
    "sg:postcode":"4770",
    "sg:province":"Li\u00e8ge",
    "sg:tags":[
        "builder"
    ],
    "wof:name":"Hugo Karl Sa",
    "wof:placetype":"venue"
},
  "geometry": {"coordinates":[6.0711231232,50.3498764038],"type":"Point"}
}