{
  "type": "Feature",
  "properties": {
    "iso:country":"BE",
    "sg:address":"Leuvenselaan 172 Box 24",
    "sg:city":"Tienen",
    "sg:classifiers":[
        {
            "category":"Professional",
            "subcategory":"Accounting & Tax Preparation",
            "type":"Services"
        }
    ],
    "sg:phone":"+32 16 82 36 73",
    "sg:postcode":"3300",
    "sg:province":"Vlaams-Brabant",
    "sg:tags":[
        "cupola",
        "-",
        "skylight"
    ],
    "wof:name":"Velopa",
    "wof:placetype":"venue"
},
  "geometry": {"coordinates":[4.9303297997,50.8096694946],"type":"Point"}
}