{
  "type": "Feature",
  "properties": {
    "iso:country":"BE",
    "sg:address":"Beekstraat 4",
    "sg:city":"Zemst (eppegem)",
    "sg:classifiers":[
        {
            "category":"Real Estate",
            "subcategory":"Real Estate Services",
            "type":"Services"
        }
    ],
    "sg:phone":"+32 15 62 35 89",
    "sg:postcode":"1980",
    "sg:province":"Vlaams-Brabant",
    "wof:name":"Patgo Nv",
    "wof:placetype":"venue"
},
  "geometry": {"coordinates":[4.4462862015,50.9688034058],"type":"Point"}
}