{
  "type": "Feature",
  "properties": {
    "iso:country":"BE",
    "sg:address":"Chauss\u00c9e Roosevelt 184",
    "sg:city":"Saint-nicolas",
    "sg:classifiers":[
        {
            "category":"Autos & Motor Vehicles",
            "subcategory":"Fuel & Gas Station",
            "type":"Retail Goods"
        }
    ],
    "sg:phone":"+32 4 263 59 75",
    "sg:postcode":"4420",
    "sg:province":"Li\u00e8ge",
    "sg:tags":[
        "stations-service",
        "carburants"
    ],
    "wof:name":"A.c.t.i.f.s.",
    "wof:placetype":"venue"
},
  "geometry": {"coordinates":[5.5197920799,50.6465415955],"type":"Point"}
}