{
  "type": "Feature",
  "properties": {
    "iso:country":"BE",
    "sg:address":"Rue De L'ange 22",
    "sg:city":"Fleurus",
    "sg:orig_category":"Installation de menuiserie en bois and plastique",
    "sg:phone":"+32 71 81 80 39",
    "sg:postcode":"6222",
    "sg:province":"Hainaut",
    "wof:name":"Osman Gencoglu",
    "wof:placetype":"venue"
},
  "geometry": {"coordinates":[4.555161953,50.5228424072],"type":"Point"}
}