{
  "type": "Feature",
  "properties": {
    "iso:country":"BE",
    "sg:address":"Stationsstraat 12",
    "sg:city":"Herselt",
    "sg:classifiers":[
        {
            "category":"Insurance",
            "subcategory":"Life Insurance",
            "type":"Services"
        }
    ],
    "sg:phone":"+32 16 69 66 66",
    "sg:postcode":"2230",
    "sg:province":"Antwerpen",
    "sg:tags":[
        "assurance"
    ],
    "wof:name":"Cootmans Marcel",
    "wof:placetype":"venue"
},
  "geometry": {"coordinates":[4.8321208954,51.0321006775],"type":"Point"}
}