{
  "type": "Feature",
  "properties": {
    "addr:full":"Kruisstraat 21 Kalmthout Antwerpen 2920",
    "addr:housenumber":"21",
    "addr:postcode":"2920",
    "addr:street":"Kruisstraat",
    "iso:country":"BE",
    "sg:address":"Kruisstraat 21",
    "sg:city":"Kalmthout",
    "sg:orig_category":"Eleveurs de bovins",
    "sg:phone":"+32 3 666 63 89",
    "sg:postcode":"2920",
    "sg:province":"Antwerpen",
    "wof:name":"Josephus Van Gestel",
    "wof:placetype":"venue"
},
  "geometry": {"coordinates":[4.5116620064,51.3740577698],"type":"Point"}
}