{
  "type": "Feature",
  "properties": {
    "addr:full":"Heistraat 105 Oosterzele Oost-Vlaanderen 9860",
    "addr:housenumber":"105",
    "addr:postcode":"9860",
    "addr:street":"Heistraat;Oost-Vlaanderen",
    "iso:country":"BE",
    "sg:address":"Heistraat 105",
    "sg:city":"Oosterzele",
    "sg:orig_category":"Fotografen and fotostudio's",
    "sg:phone":"+32 9 362 20 50",
    "sg:postcode":"9860",
    "sg:province":"Oost-Vlaanderen",
    "wof:name":"Reprorent",
    "wof:placetype":"venue"
},
  "geometry": {"coordinates":[3.8385720253,50.9509849548],"type":"Point"}
}