{
  "type": "Feature",
  "properties": {
    "addr:full":"Heuvenstraat 29 Zonhoven Limburg 3520",
    "addr:housenumber":"29",
    "addr:postcode":"3520",
    "addr:street":"Heuvenstraat",
    "iso:country":"BE",
    "sg:address":"Heuvenstraat 29",
    "sg:city":"Zonhoven",
    "sg:classifiers":[
        {
            "category":"Wholesale",
            "subcategory":"Fruits & Vegetables",
            "type":"Manufacturing & Wholesale Goods"
        }
    ],
    "sg:phone":"+32 11 81 37 13",
    "sg:postcode":"3520",
    "sg:province":"Limburg",
    "sg:tags":[
        "whol",
        "-"
    ],
    "wof:name":"Fruit-central",
    "wof:placetype":"venue"
},
  "geometry": {"coordinates":[5.3675298691,50.9893455505],"type":"Point"}
}