{
  "type": "Feature",
  "properties": {
    "addr:full":"Veldstraat 70 Gent Oost-Vlaanderen 9000",
    "addr:housenumber":"70",
    "addr:postcode":"9000",
    "addr:street":"Veldstraat;Oost-Vlaanderen",
    "iso:country":"BE",
    "sg:address":"Veldstraat 70",
    "sg:city":"Gent",
    "sg:orig_category":"Cosmetica and toiletartikelen Drogisterijen",
    "sg:phone":"+32 9 233 82 18",
    "sg:postcode":"9000",
    "sg:province":"Oost-Vlaanderen",
    "wof:name":"Kruidvat",
    "wof:placetype":"venue"
},
  "geometry": {"coordinates":[3.7215468884,51.0520439148],"type":"Point"}
}