{
  "type": "Feature",
  "properties": {
    "addr:full":"Molenstraat 16 Brecht Antwerpen 2960",
    "addr:housenumber":"16",
    "addr:postcode":"2960",
    "addr:street":"Molenstraat",
    "iso:country":"BE",
    "sg:address":"Molenstraat 16",
    "sg:city":"Brecht",
    "sg:classifiers":[
        {
            "category":"Airport",
            "subcategory":"International",
            "type":"Transportation"
        }
    ],
    "sg:phone":"+32 3 313 00 57",
    "sg:postcode":"2960",
    "sg:province":"Antwerpen",
    "sg:tags":[
        "-",
        "transport"
    ],
    "wof:name":"Servi-trans Belgium Bvba",
    "wof:placetype":"venue"
},
  "geometry": {"coordinates":[4.6356601715,51.3466148376],"type":"Point"}
}