{
  "type": "Feature",
  "properties": {
    "iso:country":"BE",
    "sg:address":"Rue De La Goette 18",
    "sg:city":"Florennes (saint-aubin)",
    "sg:classifiers":[
        {
            "category":"Health Services",
            "subcategory":"Doctor",
            "type":"Services"
        }
    ],
    "sg:phone":"+32 71 68 96 56",
    "sg:postcode":"5620",
    "sg:province":"Namur",
    "sg:tags":[
        "medicinephysicians",
        "surgeon"
    ],
    "wof:name":"Jacquemin M",
    "wof:placetype":"venue"
},
  "geometry": {"coordinates":[4.5808129311,50.2459487915],"type":"Point"}
}