{
  "type": "Feature",
  "properties": {
    "addr:full":"Rue Des Bouchers 70 Bruxelles Bruxelles-Capitale 1000",
    "addr:housenumber":"70",
    "addr:postcode":"1000",
    "addr:street":"Rue Des Bouchers",
    "iso:country":"BE",
    "sg:address":"Rue Des Bouchers 70",
    "sg:city":"Bruxelles",
    "sg:classifiers":[
        {
            "category":"Shopping",
            "subcategory":"Books",
            "type":"Retail Goods"
        }
    ],
    "sg:phone":"+32 2 511 35 91",
    "sg:postcode":"1000",
    "sg:province":"Bruxelles-Capitale",
    "sg:tags":[
        "antiquarian",
        "trade"
    ],
    "wof:name":"De Haen",
    "wof:placetype":"venue"
},
  "geometry": {"coordinates":[4.3560137749,50.8473320007],"type":"Point"}
}