{
  "type": "Feature",
  "properties": {
    "addr:full":"Smishoek 3 Wachtebeke Oost-Vlaanderen 9185",
    "addr:housenumber":"3",
    "addr:postcode":"9185",
    "addr:street":"Smishoek",
    "iso:country":"BE",
    "sg:address":"Smishoek 3",
    "sg:city":"Wachtebeke",
    "sg:orig_category":"Journaux. Tabac",
    "sg:phone":"+32 9 345 00 30",
    "sg:postcode":"9185",
    "sg:province":"Oost-Vlaanderen",
    "wof:name":"Noi-quattroro",
    "wof:placetype":"venue"
},
  "geometry": {"coordinates":[3.8601748943,51.1702041626],"type":"Point"}
}