{
  "type": "Feature",
  "properties": {
    "addr:full":"Avenue De La Grande Arm\u00e9e 41 Braine L'alleud (braine-l'alleud) Brabant Wallon 1420",
    "addr:housenumber":"41",
    "addr:postcode":"1420",
    "addr:street":"Avenue De La Grande Arme\u0301E",
    "iso:country":"BE",
    "sg:address":"Avenue De La Grande Arm\u00e9e 41",
    "sg:city":"Braine L'alleud (braine-l'alleud)",
    "sg:classifiers":[
        {
            "category":"Health Services",
            "subcategory":"Doctor",
            "type":"Services"
        }
    ],
    "sg:phone":"+32 2 384 88 62",
    "sg:postcode":"1420",
    "sg:province":"Brabant Wallon",
    "sg:tags":[
        "medicinephysicians",
        "surgeon"
    ],
    "wof:name":"Defourny Adrienne",
    "wof:placetype":"venue"
},
  "geometry": {"coordinates":[-118.0959396362,45.3295402527],"type":"Point"}
}