{
  "type": "Feature",
  "properties": {
    "iso:country":"BE",
    "sg:address":"Rue Du Calvaire 5",
    "sg:city":"Tubize",
    "sg:orig_category":"Dansscholen",
    "sg:phone":"+32 67 64 65 69",
    "sg:postcode":"1480",
    "sg:province":"Brabant Wallon",
    "wof:name":"Georgette Debusscher",
    "wof:placetype":"venue"
},
  "geometry": {"coordinates":[4.2310328484,50.662322998],"type":"Point"}
}