{
  "type": "Feature",
  "properties": {
    "addr:full":"Rue Du Jardinier 30 Sint-jans-molenbeek/molenbeek- Bruxelles-Capitale 1080",
    "addr:housenumber":"30",
    "addr:postcode":"1080",
    "addr:street":"Rue Du Jardinier",
    "iso:country":"BE",
    "sg:address":"Rue Du Jardinier 30",
    "sg:city":"Sint-jans-molenbeek/molenbeek-",
    "sg:orig_category":"Bloemen and planten",
    "sg:phone":"+32 2 414 10 19",
    "sg:postcode":"1080",
    "sg:province":"Bruxelles-Capitale",
    "wof:name":"Ryntjens",
    "wof:placetype":"venue"
},
  "geometry": {"coordinates":[4.339193821,50.8580474854],"type":"Point"}
}