{
  "type": "Feature",
  "properties": {
    "addr:full":"Jan Baptist Tassynsstr. 42 Zwijndrecht Antwerpen 2070",
    "addr:housenumber":"42",
    "addr:postcode":"2070",
    "addr:street":"Jan Baptist Tassynsstr.",
    "iso:country":"BE",
    "sg:address":"Jan Baptist Tassynsstr. 42",
    "sg:city":"Zwijndrecht",
    "sg:classifiers":[
        {
            "category":"Arena",
            "subcategory":"Sports Club",
            "type":"Entertainment"
        }
    ],
    "sg:phone":"+32 3 252 97 43",
    "sg:postcode":"2070",
    "sg:province":"Antwerpen",
    "sg:tags":[
        "terrain",
        "hors",
        "de",
        "installation",
        "sportifs"
    ],
    "wof:name":"K.f.c. Gerda St.-niklaas",
    "wof:placetype":"venue"
},
  "geometry": {"coordinates":[4.3311839104,51.2165641785],"type":"Point"}
}