{
  "type": "Feature",
  "properties": {
    "addr:full":"Rue Des Forgerons 102 Charleroi Hainaut 6001",
    "addr:housenumber":"102",
    "addr:postcode":"6001",
    "addr:street":"Rue Des Forgerons;Hainaut",
    "iso:country":"BE",
    "sg:address":"Rue Des Forgerons 102",
    "sg:city":"Charleroi",
    "sg:orig_category":"Groenten and fruit Gh",
    "sg:phone":"+32 71 36 45 15",
    "sg:postcode":"6001",
    "sg:province":"Hainaut",
    "wof:name":"Van Laethem",
    "wof:placetype":"venue"
},
  "geometry": {"coordinates":[4.4531960487,50.3923377991],"type":"Point"}
}