{
  "type": "Feature",
  "properties": {
    "addr:full":"Tongersesteenweg 7b1 Hoeselt Limburg 3730",
    "addr:housenumber":"7b1",
    "addr:postcode":"3730",
    "addr:street":"Tongersesteenweg",
    "iso:country":"BE",
    "sg:address":"Tongersesteenweg 7b1",
    "sg:city":"Hoeselt",
    "sg:orig_category":"Disneyland Paris. Agences de voyages",
    "sg:phone":"+32 89 49 21 40",
    "sg:postcode":"3730",
    "sg:province":"Limburg",
    "wof:name":"Maxi Holidays",
    "wof:placetype":"venue"
},
  "geometry": {"coordinates":[5.4910020828,50.8494567871],"type":"Point"}
}