{
  "type": "Feature",
  "properties": {
    "addr:full":"Noordbroek 20 Gent Oost-Vlaanderen 9030",
    "addr:housenumber":"20",
    "addr:postcode":"9030",
    "addr:street":"Noordbroek;Oost-Vlaanderen",
    "iso:country":"BE",
    "sg:address":"Noordbroek 20",
    "sg:city":"Gent",
    "sg:orig_category":"Kapsalons Mobiele kappers",
    "sg:phone":"+32 9 236 41 03",
    "sg:postcode":"9030",
    "sg:province":"Oost-Vlaanderen",
    "wof:name":"Coiffure Gerda",
    "wof:placetype":"venue"
},
  "geometry": {"coordinates":[3.6742119789,51.0826416016],"type":"Point"}
}