{
  "type": "Feature",
  "properties": {
    "iso:country":"BE",
    "sg:address":"Pastoor Dergentstraat 2",
    "sg:city":"Aarschot",
    "sg:orig_category":"M\u00e9decins and sp\u00e9cialistes",
    "sg:phone":"+32 16 56 74 86",
    "sg:postcode":"3200",
    "sg:province":"Vlaams-Brabant",
    "wof:name":"Bart Schoolmeesters",
    "wof:placetype":"venue"
},
  "geometry": {"coordinates":[4.8319921494,50.9868087769],"type":"Point"}
}