{
  "type": "Feature",
  "properties": {
    "iso:country":"BE",
    "sg:address":"Berlarij 10",
    "sg:city":"Lier",
    "sg:orig_category":"Apotheken",
    "sg:phone":"+32 3 491 05 90",
    "sg:postcode":"2500",
    "sg:province":"Antwerpen",
    "wof:name":"Apotheek Van Look",
    "wof:placetype":"venue"
},
  "geometry": {"coordinates":[4.5776438713,51.1289520264],"type":"Point"}
}