{
  "type": "Feature",
  "properties": {
    "addr:full":"Avenue De La Fauconnerie 89 Bruxelles (watermael-boitsfort) Bruxelles-Capitale 1170",
    "addr:housenumber":"89",
    "addr:postcode":"1170",
    "addr:street":"Avenue De La Fauconnerie",
    "iso:country":"BE",
    "sg:address":"Avenue De La Fauconnerie 89",
    "sg:city":"Bruxelles (watermael-boitsfort)",
    "sg:classifiers":[
        {
            "category":"Professional",
            "subcategory":"Lawyer & Legal Services",
            "type":"Services"
        }
    ],
    "sg:phone":"+32 2 673 08 10",
    "sg:postcode":"1170",
    "sg:province":"Bruxelles-Capitale",
    "wof:name":"Gilon M",
    "wof:placetype":"venue"
},
  "geometry": {"coordinates":[4.4182391167,50.8026695251],"type":"Point"}
}