{
  "type": "Feature",
  "properties": {
    "iso:country":"BE",
    "sg:address":"Oostakkerdorp 41",
    "sg:city":"Oostakker",
    "sg:classifiers":[
        {
            "category":"Banks & Credit Unions",
            "subcategory":"Bank",
            "type":"Services"
        }
    ],
    "sg:phone":"+32 54 51 03 80",
    "sg:postcode":"9040",
    "sg:province":"Oost-Vlaanderen",
    "wof:name":"G\u00e9n\u00e9rale De Banque Sa",
    "wof:placetype":"venue"
},
  "geometry": {"coordinates":[3.7638869286,51.0996551514],"type":"Point"}
}