{
  "type": "Feature",
  "properties": {
    "iso:country":"BE",
    "sg:address":"Chauss\u00e9e De Marche 53",
    "sg:city":"Assesse",
    "sg:classifiers":[
        {
            "category":"Real Estate",
            "subcategory":"Real Estate Services",
            "type":"Services"
        }
    ],
    "sg:phone":"+32 83 65 62 08",
    "sg:postcode":"5330",
    "sg:province":"Namur",
    "sg:tags":[
        "-",
        "abroad"
    ],
    "wof:name":"Lecomte Bureau Sc",
    "wof:placetype":"venue"
},
  "geometry": {"coordinates":[5.0226421356,50.3709182739],"type":"Point"}
}