{
  "type": "Feature",
  "properties": {
    "iso:country":"BE",
    "sg:address":"Venlosesteenweg 165",
    "sg:city":"Maaseik",
    "sg:classifiers":[
        {
            "category":"Banks & Credit Unions",
            "subcategory":"Investment Brokerage",
            "type":"Services"
        }
    ],
    "sg:phone":"+32 89 56 74 81",
    "sg:postcode":"3680",
    "sg:province":"Limburg",
    "sg:tags":[
        "repair",
        "-",
        "installation",
        "sanitary",
        "article"
    ],
    "wof:name":"Smeets Nico",
    "wof:placetype":"venue"
},
  "geometry": {"coordinates":[5.7999420166,51.1155776978],"type":"Point"}
}