{
  "type": "Feature",
  "properties": {
    "addr:full":"Gentsestraat 70 Harelbeke West-Vlaanderen 8530",
    "addr:housenumber":"70",
    "addr:postcode":"8530",
    "addr:street":"Gentsestraat",
    "iso:country":"BE",
    "sg:address":"Gentsestraat 70",
    "sg:city":"Harelbeke",
    "sg:classifiers":[
        {
            "category":"Bakery",
            "type":"Food & Drink"
        }
    ],
    "sg:phone":"+32 56 71 16 05",
    "sg:postcode":"8530",
    "sg:province":"West-Vlaanderen",
    "sg:tags":[
        "confectioner",
        "baker"
    ],
    "wof:name":"Noppe Banketbakkerij",
    "wof:placetype":"venue"
},
  "geometry": {"coordinates":[3.3194959164,50.860824585],"type":"Point"}
}