{
  "type": "Feature",
  "properties": {
    "addr:full":"Rue Du Condroz 12 Ciney Namur 5590",
    "addr:housenumber":"12",
    "addr:postcode":"5590",
    "addr:street":"Rue Du Condroz",
    "iso:country":"BE",
    "sg:address":"Rue Du Condroz 12",
    "sg:city":"Ciney",
    "sg:orig_category":"Schoenen",
    "sg:phone":"+32 83 21 77 86",
    "sg:postcode":"5590",
    "sg:province":"Namur",
    "wof:name":"diff\u00c9rent Chaussures",
    "wof:placetype":"venue"
},
  "geometry": {"coordinates":[5.1030259132,50.2967758179],"type":"Point"}
}