{
  "type": "Feature",
  "properties": {
    "iso:country":"BE",
    "sg:address":"Zavelstraat 29",
    "sg:city":"Stekene",
    "sg:classifiers":[
        {
            "category":"Manufacturing",
            "subcategory":"Metals",
            "type":"Manufacturing & Wholesale Goods"
        }
    ],
    "sg:phone":"+32 3 779 99 47",
    "sg:postcode":"9190",
    "sg:province":"Oost-Vlaanderen",
    "sg:tags":[
        "working"
    ],
    "wof:name":"Vematec",
    "wof:placetype":"venue"
},
  "geometry": {"coordinates":[4.0520310402,51.2100334167],"type":"Point"}
}