{
  "type": "Feature",
  "properties": {
    "addr:full":"Derri\u00c8re Les Courtils 13 Durbuy Luxembourg 6940",
    "addr:housenumber":"13",
    "addr:postcode":"6940",
    "addr:street":"Derrie\u0300Re Les Courtils",
    "iso:country":"BE",
    "sg:address":"Derri\u00c8re Les Courtils 13",
    "sg:city":"Durbuy",
    "sg:classifiers":[
        {
            "category":"Restaurant",
            "type":"Food & Drink"
        }
    ],
    "sg:phone":"+32 84 46 60 21",
    "sg:postcode":"6940",
    "sg:province":"Luxembourg",
    "wof:name":"Les Mign\u00c9es",
    "wof:placetype":"venue"
},
  "geometry": {"coordinates":[5.4543361664,50.3515777588],"type":"Point"}
}