{
  "type": "Feature",
  "properties": {
    "iso:country":"BE",
    "sg:address":"Oude Veurnestraat 5",
    "sg:city":"Ieper",
    "sg:orig_category":"Epiceries",
    "sg:phone":"+32 57 20 75 25",
    "sg:postcode":"8900",
    "sg:province":"West-Vlaanderen",
    "wof:name":"Huis Pic-nic",
    "wof:placetype":"venue"
},
  "geometry": {"coordinates":[2.8769330978,50.8586845398],"type":"Point"}
}