{
  "type": "Feature",
  "properties": {
    "addr:full":"Heuvel 95 Aalst Oost-Vlaanderen 9320",
    "addr:housenumber":"95",
    "addr:postcode":"9320",
    "addr:street":"Heuvel",
    "iso:country":"BE",
    "sg:address":"Heuvel 95",
    "sg:city":"Aalst",
    "sg:orig_category":"D\u00e9corateurs d'int\u00e9rieur. Jardinage",
    "sg:phone":"+32 53 78 31 10",
    "sg:postcode":"9320",
    "sg:province":"Oost-Vlaanderen",
    "wof:name":"Johan De Backer",
    "wof:placetype":"venue"
},
  "geometry": {"coordinates":[4.0553851128,50.9209976196],"type":"Point"}
}