{
  "type": "Feature",
  "properties": {
    "iso:country":"BE",
    "sg:address":"Ruitersdreef 2",
    "sg:city":"Sint-martens-latem",
    "sg:orig_category":"Binnenhuisarchitecten",
    "sg:phone":"+32 9 282 72 32",
    "sg:postcode":"9831",
    "sg:province":"Oost-Vlaanderen",
    "wof:name":"Hedwig Deschagt",
    "wof:placetype":"venue"
},
  "geometry": {"coordinates":[3.6065649986,51.0152359009],"type":"Point"}
}