{
  "type": "Feature",
  "properties": {
    "iso:country":"BE",
    "sg:address":"Boekakker 4",
    "sg:city":"Wetteren",
    "sg:classifiers":[
        {
            "category":"Professional",
            "subcategory":"Employment Agencies",
            "type":"Services"
        }
    ],
    "sg:phone":"+32 478 88 14 66",
    "sg:postcode":"9230",
    "sg:province":"Oost-Vlaanderen",
    "sg:tags":[
        "pr",
        "relation",
        "public"
    ],
    "wof:name":"Pit Pr -partners In Thinking",
    "wof:placetype":"venue"
},
  "geometry": {"coordinates":[3.8624498844,50.9983253479],"type":"Point"}
}