{
  "type": "Feature",
  "properties": {
    "addr:full":"Boektsestraat 71 Steenokkerzeel Vlaams-Brabant 1820",
    "addr:housenumber":"71",
    "addr:postcode":"1820",
    "addr:street":"Boektsestraat",
    "iso:country":"BE",
    "sg:address":"Boektsestraat 71",
    "sg:city":"Steenokkerzeel",
    "sg:orig_category":"Kapsalons",
    "sg:phone":"+32 15 61 37 82",
    "sg:postcode":"1820",
    "sg:province":"Vlaams-Brabant",
    "wof:name":"Jeannine Breban",
    "wof:placetype":"venue"
},
  "geometry": {"coordinates":[4.5113320351,50.9456596375],"type":"Point"}
}