{
  "type": "Feature",
  "properties": {
    "iso:country":"BE",
    "sg:address":"Hemelrijkstraat 2",
    "sg:city":"Ieper",
    "sg:orig_category":"Producteurs de fruits",
    "sg:phone":"+32 57 48 87 08",
    "sg:postcode":"8904",
    "sg:province":"West-Vlaanderen",
    "wof:name":"Marc Cools",
    "wof:placetype":"venue"
},
  "geometry": {"coordinates":[2.9059948921,50.8874664307],"type":"Point"}
}