{
  "type": "Feature",
  "properties": {
    "iso:country":"BE",
    "sg:address":"Leopoldplein 11",
    "sg:city":"Lier",
    "sg:classifiers":[
        {
            "category":"Bakery",
            "type":"Food & Drink"
        }
    ],
    "sg:phone":"+32 3 480 05 23",
    "sg:postcode":"2500",
    "sg:province":"Antwerpen",
    "sg:tags":[
        "confectioner",
        "baker"
    ],
    "wof:name":"Sleeckx",
    "wof:placetype":"venue"
},
  "geometry": {"coordinates":[4.5640301704,51.1352539062],"type":"Point"}
}