{
  "type": "Feature",
  "properties": {
    "iso:country":"BE",
    "sg:address":"Rue De Fafchamps 63",
    "sg:city":"Blegny",
    "sg:orig_category":"Entretien and r\u00e9parations de voitures",
    "sg:phone":"+32 4 387 72 96",
    "sg:postcode":"4670",
    "sg:province":"Li\u00e8ge",
    "wof:name":"Garage V.d.g.",
    "wof:placetype":"venue"
},
  "geometry": {"coordinates":[5.7284460068,50.668510437],"type":"Point"}
}