{
  "type": "Feature",
  "properties": {
    "iso:country":"BE",
    "sg:address":"Dorp 50",
    "sg:city":"Olen",
    "sg:orig_category":"Pain, p\u00e2tisseries and confiseries",
    "sg:phone":"+32 14 26 34 34",
    "sg:postcode":"2250",
    "sg:province":"Antwerpen",
    "wof:name":"Ignace Vanspringel",
    "wof:placetype":"venue"
},
  "geometry": {"coordinates":[4.8600430489,51.1434440613],"type":"Point"}
}