{
  "type": "Feature",
  "properties": {
    "addr:full":"Avenue Des Combattants 87 Rixensart (genval) Brabant Wallon 1332",
    "addr:housenumber":"87",
    "addr:postcode":"1332",
    "addr:street":"Avenue Des Combattants",
    "iso:country":"BE",
    "sg:address":"Avenue Des Combattants 87",
    "sg:city":"Rixensart (genval)",
    "sg:classifiers":[
        {
            "category":"Shopping",
            "subcategory":"Crafts & Fabrics",
            "type":"Retail Goods"
        }
    ],
    "sg:phone":"+32 2 653 60 76",
    "sg:postcode":"1332",
    "sg:province":"Brabant Wallon",
    "sg:tags":[
        "plant",
        "flower",
        "artificial"
    ],
    "wof:name":"Boon J Fun\u00e9railles",
    "wof:placetype":"venue"
},
  "geometry": {"coordinates":[4.5031218529,50.7193031311],"type":"Point"}
}