{
  "type": "Feature",
  "properties": {
    "iso:country":"BE",
    "sg:address":"Arendsstraat 84",
    "sg:city":"Harelbeke",
    "sg:orig_category":"Apotheken",
    "sg:phone":"+32 56 71 26 57",
    "sg:postcode":"8530",
    "sg:province":"West-Vlaanderen",
    "wof:name":"Apotheek Callewaert",
    "wof:placetype":"venue"
},
  "geometry": {"coordinates":[3.3217790127,50.8544082642],"type":"Point"}
}