{
  "type": "Feature",
  "properties": {
    "addr:full":"Clos Du Buley 13 Namur (w\u00e9pion) Namur 5100",
    "addr:housenumber":"13",
    "addr:postcode":"5100",
    "addr:street":"Clos Du Buley",
    "iso:country":"BE",
    "sg:address":"Clos Du Buley 13",
    "sg:city":"Namur (w\u00e9pion)",
    "sg:classifiers":[
        {
            "category":"Health Services",
            "subcategory":"Doctor",
            "type":"Services"
        }
    ],
    "sg:phone":"+32 81 46 23 61",
    "sg:postcode":"5100",
    "sg:province":"Namur",
    "sg:tags":[
        "medicinephysicians",
        "surgeon"
    ],
    "wof:name":"Laloux P",
    "wof:placetype":"venue"
},
  "geometry": {"coordinates":[4.8595280647,50.423740387],"type":"Point"}
}