{
  "type": "Feature",
  "properties": {
    "iso:country":"BE",
    "sg:address":"Eedstraat 40",
    "sg:city":"Anderlecht",
    "sg:classifiers":[
        {
            "category":"Insurance",
            "subcategory":"Insurance Agent",
            "type":"Services"
        }
    ],
    "sg:phone":"+32 2 524 02 33",
    "sg:postcode":"1070",
    "sg:province":"Bruxelles-Capitale",
    "sg:tags":[
        "verzekeringsmakelaars",
        "expert"
    ],
    "wof:name":"Bureau Pleckspaen",
    "wof:placetype":"venue"
},
  "geometry": {"coordinates":[4.3056721687,50.8383026123],"type":"Point"}
}