{
  "type": "Feature",
  "properties": {
    "iso:country":"BE",
    "sg:address":"Toekomstlaan 15b2",
    "sg:city":"Herentals",
    "sg:orig_category":"Elektrische installaties voor woningen",
    "sg:phone":"+32 14 21 05 43",
    "sg:postcode":"2200",
    "sg:province":"Antwerpen",
    "wof:name":"Indian\u00b432",
    "wof:placetype":"venue"
},
  "geometry": {"coordinates":[4.8096618652,51.160861969],"type":"Point"}
}