{
  "type": "Feature",
  "properties": {
    "addr:full":"Hamontweg 42 Maaseik Limburg 3680",
    "addr:housenumber":"42",
    "addr:postcode":"3680",
    "addr:street":"Hamontweg",
    "iso:country":"BE",
    "sg:address":"Hamontweg 42",
    "sg:city":"Maaseik",
    "sg:classifiers":[
        {
            "category":"Shopping",
            "subcategory":"Clothing, Apparel, & Fashions",
            "type":"Retail Goods"
        }
    ],
    "sg:phone":"+32 89 56 21 91",
    "sg:postcode":"3680",
    "sg:province":"Limburg",
    "sg:tags":[
        "-",
        "clothing",
        "child"
    ],
    "wof:name":"Cartoon & Co Bvba",
    "wof:placetype":"venue"
},
  "geometry": {"coordinates":[5.798104763,51.1011199951],"type":"Point"}
}