{
  "type": "Feature",
  "properties": {
    "iso:country":"BE",
    "sg:address":"Steenweg 138",
    "sg:city":"Opwijk (mazenzele)",
    "sg:classifiers":[
        {
            "category":"Health Services",
            "subcategory":"Health Practitioner",
            "type":"Services"
        }
    ],
    "sg:postcode":"1745",
    "sg:province":"Vlaams-Brabant",
    "sg:tags":[
        "physiotherapist"
    ],
    "wof:name":"De Boeck-van Der Elst",
    "wof:placetype":"venue"
},
  "geometry": {"coordinates":[4.1673789024,50.9460296631],"type":"Point"}
}