{
  "type": "Feature",
  "properties": {
    "iso:country":"BE",
    "sg:address":"Kapellekouter 16",
    "sg:city":"Sint-lievens-houtem",
    "sg:orig_category":"Groenten and fruit Gh",
    "sg:phone":"+32 53 63 05 37",
    "sg:postcode":"9520",
    "sg:province":"Oost-Vlaanderen",
    "wof:name":"Chantale De Smet",
    "wof:placetype":"venue"
},
  "geometry": {"coordinates":[3.8639938831,50.9174118042],"type":"Point"}
}