{
  "type": "Feature",
  "properties": {
    "iso:country":"BE",
    "sg:address":"Hongerstraat 13",
    "sg:city":"Zottegem",
    "sg:orig_category":"Alimentation sp\u00e9cialis\u00e9e",
    "sg:phone":"+32 55 42 63 12",
    "sg:postcode":"9620",
    "sg:province":"Oost-Vlaanderen",
    "wof:name":"Kesteleyn Marnic",
    "wof:placetype":"venue"
},
  "geometry": {"coordinates":[3.8112111092,50.871181488],"type":"Point"}
}