{
  "type": "Feature",
  "properties": {
    "iso:country":"BE",
    "sg:address":"Koning Leopold Iii-laan 2",
    "sg:city":"Kortrijk",
    "sg:classifiers":[
        {
            "category":"Real Estate",
            "subcategory":"Architect",
            "type":"Services"
        }
    ],
    "sg:phone":"+32 56 35 81 78",
    "sg:postcode":"8500",
    "sg:province":"West-Vlaanderen",
    "wof:name":"Missiaen En Degroote Bvba",
    "wof:placetype":"venue"
},
  "geometry": {"coordinates":[3.2695889473,50.8358650208],"type":"Point"}
}