{
  "type": "Feature",
  "properties": {
    "iso:country":"BE",
    "sg:address":"Lauwbergstraat 110",
    "sg:city":"Menen (lauwe)",
    "sg:classifiers":[
        {
            "category":"Professional",
            "subcategory":"Lawyer & Legal Services",
            "type":"Services"
        }
    ],
    "sg:phone":"+32 56 41 83 00",
    "sg:postcode":"8930",
    "sg:province":"West-Vlaanderen",
    "wof:name":"Huysentruyt Randall",
    "wof:placetype":"venue"
},
  "geometry": {"coordinates":[3.1209149361,50.7961845398],"type":"Point"}
}