{
  "type": "Feature",
  "properties": {
    "iso:country":"BE",
    "sg:address":"Rue Du Ham 99",
    "sg:city":"Bruxelles (uccle)",
    "sg:classifiers":[
        {
            "category":"Health Services",
            "subcategory":"Nursing And Care Facility",
            "type":"Services"
        }
    ],
    "sg:phone":"+32 2 374 99 40",
    "sg:postcode":"1180",
    "sg:province":"Bruxelles-Capitale",
    "sg:tags":[
        "handwriting",
        "-",
        "expert"
    ],
    "wof:name":"Stevens E",
    "wof:placetype":"venue"
},
  "geometry": {"coordinates":[4.3689627647,50.7909011841],"type":"Point"}
}