{
  "type": "Feature",
  "properties": {
    "iso:country":"BE",
    "sg:address":"Herentalslaan 12",
    "sg:city":"Roeselare",
    "sg:orig_category":"Woningbouw",
    "sg:phone":"+32 51 24 08 45",
    "sg:postcode":"8800",
    "sg:province":"West-Vlaanderen",
    "wof:name":"Renzo Gunst",
    "wof:placetype":"venue"
},
  "geometry": {"coordinates":[3.1321179867,50.9546127319],"type":"Point"}
}