{
  "type": "Feature",
  "properties": {
    "addr:full":"Rue Des Moissons 6 Sint-joost-ten-node/saint-josse-ten-noode Bruxelles-Capitale 1210",
    "addr:housenumber":"6",
    "addr:postcode":"1210",
    "addr:street":"Rue Des Moissons",
    "iso:country":"BE",
    "sg:address":"Rue Des Moissons 6",
    "sg:city":"Sint-joost-ten-node/saint-josse-ten-noode",
    "sg:orig_category":"Articles m\u00e9dicaux and orthop\u00e9diques",
    "sg:phone":"+32 2 219 66 16",
    "sg:postcode":"1210",
    "sg:province":"Bruxelles-Capitale",
    "wof:name":"Cordonnerie Ateco-rogge",
    "wof:placetype":"venue"
},
  "geometry": {"coordinates":[4.3745298386,50.8528709412],"type":"Point"}
}