{
  "type": "Feature",
  "properties": {
    "iso:country":"BE",
    "sg:address":"Jozef Duthoystraat 1",
    "sg:city":"Waregem",
    "sg:classifiers":[
        {
            "category":"Cafe",
            "type":"Food & Drink"
        }
    ],
    "sg:phone":"+32 56 61 39 20",
    "sg:postcode":"8790",
    "sg:province":"West-Vlaanderen",
    "sg:tags":[
        "caf\u00e9s"
    ],
    "wof:name":"Caf\u00c9 Louis Xiv",
    "wof:placetype":"venue"
},
  "geometry": {"coordinates":[3.4255239964,50.8839492798],"type":"Point"}
}