{
  "type": "Feature",
  "properties": {
    "addr:full":"Gemeenteplein 10 Meise Vlaams-Brabant 1861",
    "addr:housenumber":"10",
    "addr:postcode":"1861",
    "addr:street":"Gemeenteplein",
    "iso:country":"BE",
    "sg:address":"Gemeenteplein 10",
    "sg:city":"Meise",
    "sg:classifiers":[
        {
            "category":"Cafe",
            "type":"Food & Drink"
        }
    ],
    "sg:phone":"+32 2 269 72 87",
    "sg:postcode":"1861",
    "sg:province":"Vlaams-Brabant",
    "sg:tags":[
        "caf\u00e9s"
    ],
    "wof:name":"Taverne Cambrinusludo Willems",
    "wof:placetype":"venue"
},
  "geometry": {"coordinates":[4.3091049194,50.9506645203],"type":"Point"}
}