{
  "type": "Feature",
  "properties": {
    "iso:country":"BE",
    "sg:address":"Sint-antoniusstraat 5",
    "sg:city":"Sint-lievens-houtem",
    "sg:classifiers":[
        {
            "category":"Cafe",
            "type":"Food & Drink"
        }
    ],
    "sg:phone":"+32 9 362 80 52",
    "sg:postcode":"9520",
    "sg:province":"Oost-Vlaanderen",
    "sg:tags":[
        "caf\u00e9s"
    ],
    "wof:name":"Filip Van Den Bossche",
    "wof:placetype":"venue"
},
  "geometry": {"coordinates":[3.8642859459,50.9426002502],"type":"Point"}
}