{
  "type": "Feature",
  "properties": {
    "addr:full":"Dr.adriaan Martenslaan 55 Deinze Oost-Vlaanderen 9800",
    "addr:housenumber":"55",
    "addr:postcode":"9800",
    "addr:street":"Dr.Adriaan Martenslaan",
    "iso:country":"BE",
    "sg:address":"Dr.adriaan Martenslaan 55",
    "sg:city":"Deinze",
    "sg:classifiers":[
        {
            "category":"Shopping",
            "subcategory":"Stationery & Office Supplies",
            "type":"Retail Goods"
        }
    ],
    "sg:phone":"+32 9 386 77 14",
    "sg:postcode":"9800",
    "sg:province":"Oost-Vlaanderen",
    "sg:tags":[
        "furniture"
    ],
    "wof:name":"S.a.r.a. Nv",
    "wof:placetype":"venue"
},
  "geometry": {"coordinates":[3.5206100941,50.9896316528],"type":"Point"}
}