{
  "type": "Feature",
  "properties": {
    "iso:country":"BE",
    "sg:address":"Monnikenwerve 135",
    "sg:city":"Brugge",
    "sg:classifiers":[
        {
            "category":"Wholesale",
            "subcategory":"Construction Materials",
            "type":"Manufacturing & Wholesale Goods"
        }
    ],
    "sg:phone":"+32 50 45 04 50",
    "sg:postcode":"8000",
    "sg:province":"West-Vlaanderen",
    "sg:tags":[
        "la",
        "de",
        "\u00e9quipement",
        "pour",
        "machine",
        "entretie",
        "location",
        "equipements"
    ],
    "wof:name":"Garage Euro-forklifts",
    "wof:placetype":"venue"
},
  "geometry": {"coordinates":[3.2037129402,51.2472343445],"type":"Point"}
}