{
  "type": "Feature",
  "properties": {
    "iso:country":"BE",
    "sg:address":"Pr\u00c9 Messire 22",
    "sg:city":"Stavelot",
    "sg:classifiers":[
        {
            "category":"Health Services",
            "subcategory":"Nursing And Care Facility",
            "type":"Services"
        }
    ],
    "sg:phone":"+32 80 86 57 58",
    "sg:postcode":"4970",
    "sg:province":"Li\u00e8ge",
    "sg:tags":[
        "public"
    ],
    "wof:name":"C.p.a.s.",
    "wof:placetype":"venue"
},
  "geometry": {"coordinates":[5.9344549179,50.3950195312],"type":"Point"}
}