{
  "type": "Feature",
  "properties": {
    "addr:full":"Berendrechtstraat 45-47 Antwerpen Antwerpen 2020",
    "addr:postcode":"45-47;2020",
    "addr:street":"Berendrechtstraat",
    "iso:country":"BE",
    "sg:address":"Berendrechtstraat 45-47",
    "sg:city":"Antwerpen",
    "sg:classifiers":[
        {
            "category":"Retail",
            "subcategory":"Auto Repair",
            "type":"Services"
        }
    ],
    "sg:phone":"+32 3 238 96 60",
    "sg:postcode":"2020",
    "sg:province":"Antwerpen",
    "sg:tags":[
        "garage"
    ],
    "wof:name":"Opel/boodts",
    "wof:placetype":"venue"
},
  "geometry": {"coordinates":[4.3862781525,51.1871299744],"type":"Point"}
}