{
  "type": "Feature",
  "properties": {
    "addr:full":"Kerkstraat 5 Hoeselt Limburg 3730",
    "addr:housenumber":"5",
    "addr:postcode":"3730",
    "addr:street":"Kerkstraat",
    "iso:country":"BE",
    "sg:address":"Kerkstraat 5",
    "sg:city":"Hoeselt",
    "sg:orig_category":"Producteurs de fruits. V\u00eatements pour b\u00e9b\u00e9s and enfants",
    "sg:phone":"+32 89 41 11 85",
    "sg:postcode":"3730",
    "sg:province":"Limburg",
    "wof:name":"Jacques Vandersanden",
    "wof:placetype":"venue"
},
  "geometry": {"coordinates":[5.4889349937,50.8502044678],"type":"Point"}
}