{
  "type": "Feature",
  "properties": {
    "iso:country":"BE",
    "sg:address":"Everdongenlaan 37",
    "sg:city":"Turnhout",
    "sg:classifiers":[
        {
            "category":"Home & Garden",
            "subcategory":"Furniture",
            "type":"Retail Goods"
        }
    ],
    "sg:phone":"+32 14 43 76 52",
    "sg:postcode":"2300",
    "sg:province":"Antwerpen",
    "sg:tags":[
        "bathroom"
    ],
    "wof:name":"Aform Nv",
    "wof:placetype":"venue"
},
  "geometry": {"coordinates":[4.9343490601,51.2998580933],"type":"Point"}
}