{
  "type": "Feature",
  "properties": {
    "addr:full":"Duinkerkestraat 151 Poperinge West-Vlaanderen 8970",
    "addr:housenumber":"151",
    "addr:postcode":"8970",
    "addr:street":"Duinkerkestraat",
    "iso:country":"BE",
    "sg:address":"Duinkerkestraat 151",
    "sg:city":"Poperinge",
    "sg:orig_category":"Gespecialiseerde residenti\u00eble bouw",
    "sg:phone":"+32 57 33 49 92",
    "sg:postcode":"8970",
    "sg:province":"West-Vlaanderen",
    "wof:name":"Benny Heughebaert",
    "wof:placetype":"venue"
},
  "geometry": {"coordinates":[2.7106420994,50.8564224243],"type":"Point"}
}