{
  "type": "Feature",
  "properties": {
    "addr:full":"Abdijstraat 46 Oudenaarde Oost-Vlaanderen 9700",
    "addr:housenumber":"46",
    "addr:postcode":"9700",
    "addr:street":"Abdijstraat",
    "iso:country":"BE",
    "sg:address":"Abdijstraat 46",
    "sg:city":"Oudenaarde",
    "sg:classifiers":[
        {
            "category":"Home & Garden",
            "subcategory":"Furniture",
            "type":"Retail Goods"
        }
    ],
    "sg:phone":"+32 55 31 32 92",
    "sg:postcode":"9700",
    "sg:province":"Oost-Vlaanderen",
    "sg:tags":[
        "fab",
        "meubelen",
        "diverse"
    ],
    "wof:name":"Dermaut",
    "wof:placetype":"venue"
},
  "geometry": {"coordinates":[3.6323399544,50.8572540283],"type":"Point"}
}