{
  "type": "Feature",
  "properties": {
    "iso:country":"BE",
    "sg:address":"Rue Du Commerce 1",
    "sg:city":"Charleroi",
    "sg:classifiers":[
        {
            "category":"Health Services",
            "subcategory":"Doctor",
            "type":"Services"
        }
    ],
    "sg:phone":"+32 71 31 58 90",
    "sg:postcode":"6000",
    "sg:province":"Hainaut",
    "sg:tags":[
        "medicinephysicians",
        "surgeon"
    ],
    "wof:name":"Huberlant G",
    "wof:placetype":"venue"
},
  "geometry": {"coordinates":[4.4392261505,50.4068412781],"type":"Point"}
}