{
  "type": "Feature",
  "properties": {
    "iso:country":"BE",
    "sg:address":"Hoornstraat 3",
    "sg:city":"Gent",
    "sg:orig_category":"V\u00eatements pour Hommes",
    "sg:phone":"+32 9 233 28 21",
    "sg:postcode":"9000",
    "sg:province":"Oost-Vlaanderen",
    "wof:name":"Laundry Industry",
    "wof:placetype":"venue"
},
  "geometry": {"coordinates":[3.7214450836,51.0520057678],"type":"Point"}
}