{
  "type": "Feature",
  "properties": {
    "iso:country":"BE",
    "sg:address":"Linkesstraat 4",
    "sg:city":"Zutendaal",
    "sg:orig_category":"Loodgieterij, verwarming and sanitaire installaties",
    "sg:phone":"+32 89 62 24 70",
    "sg:postcode":"3690",
    "sg:province":"Limburg",
    "wof:name":"Wilhelmus Maastr. Holdi",
    "wof:placetype":"venue"
},
  "geometry": {"coordinates":[5.5852332115,50.9365615845],"type":"Point"}
}