{
  "type": "Feature",
  "properties": {
    "addr:full":"Schupstraat 9-11 Blok B Antwerpen Antwerpen 2018",
    "addr:housenumber":"9-11",
    "addr:postcode":"2018",
    "addr:street":"Schupstraat;B",
    "iso:country":"BE",
    "sg:address":"Schupstraat 9-11 Blok B",
    "sg:city":"Antwerpen",
    "sg:classifiers":[
        {
            "category":"Manufacturing",
            "subcategory":"Jewelry",
            "type":"Manufacturing & Wholesale Goods"
        }
    ],
    "sg:phone":"+32 3 231 46 10",
    "sg:postcode":"2018",
    "sg:province":"Antwerpen",
    "sg:tags":[
        "product",
        "miscellaneous",
        "jewellery"
    ],
    "wof:name":"Dd Manufacturing Nv",
    "wof:placetype":"venue"
},
  "geometry": {"coordinates":[4.4045801163,51.294593811],"type":"Point"}
}