{
  "type": "Feature",
  "properties": {
    "iso:country":"BE",
    "sg:address":"Peter Benoitstraat 10",
    "sg:city":"Antwerpen",
    "sg:classifiers":[
        {
            "category":"Professional",
            "subcategory":"Lawyer & Legal Services",
            "type":"Services"
        }
    ],
    "sg:phone":"+32 3 238 10 46",
    "sg:postcode":"2018",
    "sg:province":"Antwerpen",
    "wof:name":"Us\u00e9 H",
    "wof:placetype":"venue"
},
  "geometry": {"coordinates":[4.4080371857,51.2050743103],"type":"Point"}
}