{
  "type": "Feature",
  "properties": {
    "iso:country":"BE",
    "sg:address":"Van Regenmortelstraat 27",
    "sg:city":"Tremelo (baal)",
    "sg:orig_category":"Ergotherapists",
    "sg:phone":"+32 16 60 10 07",
    "sg:postcode":"3128",
    "sg:province":"Vlaams-Brabant",
    "wof:name":"Bauweraerts K",
    "wof:placetype":"venue"
},
  "geometry": {"coordinates":[4.7491230965,50.9966239929],"type":"Point"}
}