{
  "type": "Feature",
  "properties": {
    "iso:country":"BE",
    "sg:address":"Coige-steenweg 19",
    "sg:city":"Bertem",
    "sg:orig_category":"Instituts pour adultes moins valides",
    "sg:phone":"+32 2 767 47 05",
    "sg:postcode":"3061",
    "sg:province":"Vlaams-Brabant",
    "wof:name":"Centrum De Eglantier",
    "wof:placetype":"venue"
},
  "geometry": {"coordinates":[4.5536899567,50.8501281738],"type":"Point"}
}