{
  "type": "Feature",
  "properties": {
    "iso:country":"BE",
    "sg:address":"Pastorijstraat 26",
    "sg:city":"Kasterlee",
    "sg:classifiers":[
        {
            "category":"Health Services",
            "subcategory":"Health Practitioner",
            "type":"Services"
        }
    ],
    "sg:phone":"+32 14 85 17 79",
    "sg:postcode":"2460",
    "sg:province":"Antwerpen",
    "sg:tags":[
        "physiotherapist"
    ],
    "wof:name":"Pauwels Mieke",
    "wof:placetype":"venue"
},
  "geometry": {"coordinates":[4.9630651474,51.2400360107],"type":"Point"}
}