{
  "type": "Feature",
  "properties": {
    "iso:country":"BE",
    "sg:address":"Rue De Stassart 117",
    "sg:city":"Bruxelles (ixelles)",
    "sg:classifiers":[
        {
            "category":"Sports & Exercise",
            "subcategory":"Sports Center",
            "type":"Entertainment"
        }
    ],
    "sg:phone":"+32 2 513 30 30",
    "sg:postcode":"1050",
    "sg:province":"Bruxelles-Capitale",
    "sg:tags":[
        "holiday",
        "language"
    ],
    "wof:name":"E.f. Centres Internationaux De Langues/ E.f. Internationale Talenscholen",
    "wof:placetype":"venue"
},
  "geometry": {"coordinates":[4.3586268425,50.834274292],"type":"Point"}
}