{
  "type": "Feature",
  "properties": {
    "addr:full":"Rue De La Ferme 2 Antoing (fontenoy) Hainaut 7643",
    "addr:housenumber":"2",
    "addr:postcode":"7643",
    "addr:street":"Rue De La Ferme",
    "iso:country":"BE",
    "sg:address":"Rue De La Ferme 2",
    "sg:city":"Antoing (fontenoy)",
    "sg:classifiers":[
        {
            "category":"Farming",
            "subcategory":"Livestock Farm",
            "type":"Manufacturing & Wholesale Goods"
        }
    ],
    "sg:phone":"+32 69 44 24 03",
    "sg:postcode":"7643",
    "sg:province":"Hainaut",
    "sg:tags":[
        "buyer"
    ],
    "wof:name":"Lietaer M",
    "wof:placetype":"venue"
},
  "geometry": {"coordinates":[3.4726090431,50.5684051514],"type":"Point"}
}