{
  "type": "Feature",
  "properties": {
    "addr:full":"Polderstraat 29 Hamme Oost-Vlaanderen 9220",
    "addr:housenumber":"29",
    "addr:postcode":"9220",
    "addr:street":"Polderstraat",
    "iso:country":"BE",
    "sg:address":"Polderstraat 29",
    "sg:city":"Hamme",
    "sg:orig_category":"Landmeters",
    "sg:phone":"+32 52 47 01 97",
    "sg:postcode":"9220",
    "sg:province":"Oost-Vlaanderen",
    "wof:name":"Marcel Van Mele",
    "wof:placetype":"venue"
},
  "geometry": {"coordinates":[4.1615371704,51.0965766907],"type":"Point"}
}