{
  "type": "Feature",
  "properties": {
    "addr:full":"4040 Herstal Li\u00e8ge 4040",
    "addr:postcode":"4040;4040",
    "iso:country":"BE",
    "sg:address":"4040",
    "sg:city":"Herstal",
    "sg:orig_category":"Quincailleries",
    "sg:phone":"+32 4 240 05 06",
    "sg:postcode":"4040",
    "sg:province":"Li\u00e8ge",
    "wof:name":"Elce",
    "wof:placetype":"venue"
},
  "geometry": {"coordinates":[5.6231198311,50.678150177],"type":"Point"}
}