{
  "type": "Feature",
  "properties": {
    "addr:full":"Schoolstraat 1bc Sint-genesius-rode/rhode-saint-genese Vlaams-Brabant 1640",
    "addr:housenumber":"1bc",
    "addr:postcode":"1640",
    "addr:street":"Schoolstraat",
    "iso:country":"BE",
    "sg:address":"Schoolstraat 1bc",
    "sg:city":"Sint-genesius-rode/rhode-saint-genese",
    "sg:orig_category":"Installatie van houten of kunststof schrijnwerk",
    "sg:phone":"+32 2 358 23 37",
    "sg:postcode":"1640",
    "sg:province":"Vlaams-Brabant",
    "wof:name":"Ren\u00c9 Vankeerberghen",
    "wof:placetype":"venue"
},
  "geometry": {"coordinates":[4.3725318909,50.739200592],"type":"Point"}
}