{
  "type": "Feature",
  "properties": {
    "iso:country":"BE",
    "sg:address":"Grand Rue 54",
    "sg:city":"Ch\u00e2telet",
    "sg:classifiers":[
        {
            "category":"Utilities",
            "subcategory":"Cable",
            "type":"Services"
        }
    ],
    "sg:phone":"+32 71 88 53 00",
    "sg:postcode":"6200",
    "sg:province":"Hainaut",
    "sg:tags":[
        "rope",
        "twine"
    ],
    "wof:name":"La Becasse",
    "wof:placetype":"venue"
},
  "geometry": {"coordinates":[4.5285210609,50.4024276733],"type":"Point"}
}