{
  "type": "Feature",
  "properties": {
    "addr:full":"Rue De La Levure 38 Bruxelles (ixelles) Bruxelles-Capitale 1050",
    "addr:housenumber":"38",
    "addr:postcode":"1050",
    "addr:street":"Rue De La Levure",
    "iso:country":"BE",
    "sg:address":"Rue De La Levure 38",
    "sg:city":"Bruxelles (ixelles)",
    "sg:classifiers":[
        {
            "category":"Building & Trades",
            "subcategory":"Cleaning & Sanitation",
            "type":"Services"
        }
    ],
    "sg:phone":"+32 2 640 12 13",
    "sg:postcode":"1050",
    "sg:province":"Bruxelles-Capitale",
    "sg:tags":[
        "janitor"
    ],
    "wof:name":"Gaveta",
    "wof:placetype":"venue"
},
  "geometry": {"coordinates":[4.3765058517,50.8280944824],"type":"Point"}
}