{
  "type": "Feature",
  "properties": {
    "iso:country":"BE",
    "sg:address":"Hertogstraat 167",
    "sg:city":"Leuven",
    "sg:orig_category":"Services de Nettoyage and de D\u00e9sinfection",
    "sg:phone":"+32 16 40 54 49",
    "sg:postcode":"3001",
    "sg:province":"Vlaams-Brabant",
    "wof:name":"General Clean",
    "wof:placetype":"venue"
},
  "geometry": {"coordinates":[4.7006177902,50.8590011597],"type":"Point"}
}