{
  "type": "Feature",
  "properties": {
    "iso:country":"BE",
    "sg:address":"Terbiest 8",
    "sg:city":"Herzele",
    "sg:orig_category":"Ramassage and traitement des d\u00e9chets m\u00e9nagers",
    "sg:phone":"+32 54 32 50 36",
    "sg:postcode":"9550",
    "sg:province":"Oost-Vlaanderen",
    "wof:name":"De Wever Geon",
    "wof:placetype":"venue"
},
  "geometry": {"coordinates":[3.8826320171,50.8588409424],"type":"Point"}
}