{
  "type": "Feature",
  "properties": {
    "addr:full":"Rue Child\u00c9ric 16 Tournai Hainaut 7500",
    "addr:housenumber":"16",
    "addr:postcode":"7500",
    "addr:street":"Rue Childe\u0301Ric",
    "iso:country":"BE",
    "sg:address":"Rue Child\u00c9ric 16",
    "sg:city":"Tournai",
    "sg:orig_category":"Belastingconsulenten Boekhouders Diverse juridische dienstverlening",
    "sg:phone":"+32 69 21 38 69",
    "sg:postcode":"7500",
    "sg:province":"Hainaut",
    "wof:name":"Martial Seghers",
    "wof:placetype":"venue"
},
  "geometry": {"coordinates":[3.39417696,50.6096611023],"type":"Point"}
}