{
  "type": "Feature",
  "properties": {
    "iso:country":"BE",
    "sg:address":"Oleanderstraat 12",
    "sg:city":"Wevelgem",
    "sg:orig_category":"M\u00e9decins and sp\u00e9cialistes",
    "sg:phone":"+32 56 41 34 04",
    "sg:postcode":"8560",
    "sg:province":"West-Vlaanderen",
    "wof:name":"Luc Van Laere",
    "wof:placetype":"venue"
},
  "geometry": {"coordinates":[3.1766149998,50.8162956238],"type":"Point"}
}