{
  "type": "Feature",
  "properties": {
    "addr:full":"Weg Naar As 19b15 Genk Limburg 3600",
    "addr:housenumber":"19b15",
    "addr:postcode":"3600",
    "addr:street":"Weg Naar As",
    "iso:country":"BE",
    "sg:address":"Weg Naar As 19b15",
    "sg:city":"Genk",
    "sg:orig_category":"Avocats and conseillers juridiques",
    "sg:phone":"+32 89 35 22 23",
    "sg:postcode":"3600",
    "sg:province":"Limburg",
    "wof:name":"P. Panis",
    "wof:placetype":"venue"
},
  "geometry": {"coordinates":[5.5340800285,50.982219696],"type":"Point"}
}