{
  "type": "Feature",
  "properties": {
    "addr:full":"Vaaltweg 14 Herent Vlaams-Brabant 3020",
    "addr:housenumber":"14",
    "addr:postcode":"3020",
    "addr:street":"Vaaltweg",
    "iso:country":"BE",
    "sg:address":"Vaaltweg 14",
    "sg:city":"Herent",
    "sg:classifiers":[
        {
            "category":"Health Services",
            "subcategory":"Dentist",
            "type":"Services"
        }
    ],
    "sg:phone":"+32 16 29 13 03",
    "sg:postcode":"3020",
    "sg:province":"Vlaams-Brabant",
    "wof:name":"Everaert Katia",
    "wof:placetype":"venue"
},
  "geometry": {"coordinates":[4.6856708527,50.8992424011],"type":"Point"}
}