{
  "type": "Feature",
  "properties": {
    "iso:country":"BE",
    "sg:address":"Aven Ackers 1",
    "sg:city":"Beveren",
    "sg:orig_category":"Location de mat\u00e9riel pour banquets and \u00e9v\u00e9nements. Locations de machines and \u00e9quipement pour la cons",
    "sg:phone":"+32 3 210 99 70",
    "sg:postcode":"9130",
    "sg:province":"Oost-Vlaanderen",
    "wof:name":"Scaffyco",
    "wof:placetype":"venue"
},
  "geometry": {"coordinates":[4.1907539368,51.2505264282],"type":"Point"}
}