{
  "type": "Feature",
  "properties": {
    "addr:full":"Oostmalsesteenweg 14 Rijkevorsel Antwerpen 2310",
    "addr:housenumber":"14",
    "addr:postcode":"2310",
    "addr:street":"Oostmalsesteenweg",
    "iso:country":"BE",
    "sg:address":"Oostmalsesteenweg 14",
    "sg:city":"Rijkevorsel",
    "sg:orig_category":"Slagers",
    "sg:phone":"+32 3 314 60 51",
    "sg:postcode":"2310",
    "sg:province":"Antwerpen",
    "wof:name":"Jan Storms",
    "wof:placetype":"venue"
},
  "geometry": {"coordinates":[4.7584810257,51.3462982178],"type":"Point"}
}