{
  "type": "Feature",
  "properties": {
    "addr:full":"Lange Kievitstraat 87 Antwerpen Antwerpen 2018",
    "addr:housenumber":"87",
    "addr:postcode":"2018",
    "addr:street":"Lange Kievitstraat",
    "iso:country":"BE",
    "sg:address":"Lange Kievitstraat 87",
    "sg:city":"Antwerpen",
    "sg:orig_category":"Epiceries",
    "sg:phone":"+32 3 233 76 17",
    "sg:postcode":"2018",
    "sg:province":"Antwerpen",
    "wof:name":"Steinmetz",
    "wof:placetype":"venue"
},
  "geometry": {"coordinates":[4.4205951691,51.2130088806],"type":"Point"}
}