{
  "type": "Feature",
  "properties": {
    "iso:country":"BE",
    "sg:address":"Rue Des Jardins 36 Box 6",
    "sg:city":"Bastogne",
    "sg:classifiers":[
        {
            "category":"Freight",
            "type":"Transportation"
        }
    ],
    "sg:phone":"+32 477 47 80 84",
    "sg:postcode":"6600",
    "sg:province":"Luxembourg",
    "sg:tags":[
        "express",
        "transport"
    ],
    "wof:name":"Kaiser A",
    "wof:placetype":"venue"
},
  "geometry": {"coordinates":[5.7207708359,50.004032135],"type":"Point"}
}