{
  "type": "Feature",
  "properties": {
    "iso:country":"BE",
    "sg:address":"Rue De La Gare 22",
    "sg:city":"Gouvy",
    "sg:orig_category":"Transports ferroviaires",
    "sg:phone":"+32 80 51 74 02",
    "sg:postcode":"6670",
    "sg:province":"Luxembourg",
    "wof:name":"Gare De Gouvy",
    "wof:placetype":"venue"
},
  "geometry": {"coordinates":[5.9546999931,50.1896934509],"type":"Point"}
}