{
  "type": "Feature",
  "properties": {
    "iso:country":"BE",
    "sg:address":"Rue G Magnee 92bte 6",
    "sg:city":"Ans",
    "sg:classifiers":[
        {
            "category":"Structure",
            "subcategory":"Office Building",
            "type":"Public Place"
        }
    ],
    "sg:phone":"+32 4 239 78 80",
    "sg:postcode":"4430",
    "sg:province":"Li\u00e8ge",
    "sg:tags":[
        "engineering",
        "electrical"
    ],
    "wof:name":"Deltatec S.a.",
    "wof:placetype":"venue"
},
  "geometry": {"coordinates":[5.5293679237,50.6607818604],"type":"Point"}
}