{
  "type": "Feature",
  "properties": {
    "iso:country":"BE",
    "sg:address":"Engsbergseweg 69",
    "sg:city":"Tessenderlo",
    "sg:orig_category":"Apotheken",
    "sg:phone":"+32 13 33 62 59",
    "sg:postcode":"3980",
    "sg:province":"Limburg",
    "wof:name":"Apoteek Engsbergen",
    "wof:placetype":"venue"
},
  "geometry": {"coordinates":[5.066450119,51.0323104858],"type":"Point"}
}