{
  "type": "Feature",
  "properties": {
    "addr:full":"Reitstraat 11 Ham Limburg 3945",
    "addr:housenumber":"11",
    "addr:postcode":"3945",
    "addr:street":"Reitstraat",
    "iso:country":"BE",
    "sg:address":"Reitstraat 11",
    "sg:city":"Ham",
    "sg:classifiers":[
        {
            "category":"Sports & Exercise",
            "subcategory":"Sports Center",
            "type":"Entertainment"
        }
    ],
    "sg:phone":"+32 11 40 25 81",
    "sg:postcode":"3945",
    "sg:province":"Limburg",
    "sg:tags":[
        "de",
        "fitness"
    ],
    "wof:name":"Nevyna Gym",
    "wof:placetype":"venue"
},
  "geometry": {"coordinates":[5.1776199341,51.1046104431],"type":"Point"}
}