{
  "type": "Feature",
  "properties": {
    "addr:full":"Rue Basse 19 Quevy Hainaut 7040",
    "addr:housenumber":"19",
    "addr:postcode":"7040",
    "addr:street":"Rue Basse;Hainaut",
    "iso:country":"BE",
    "sg:address":"Rue Basse 19",
    "sg:city":"Quevy",
    "sg:orig_category":"Enseignement maternel and primaire",
    "sg:phone":"+32 65 56 97 81",
    "sg:postcode":"7040",
    "sg:province":"Hainaut",
    "wof:name":"E.m.l. St.brice",
    "wof:placetype":"venue"
},
  "geometry": {"coordinates":[3.9018409252,50.3377838135],"type":"Point"}
}