{
  "type": "Feature",
  "properties": {
    "addr:full":"Victor Dumonlaan 12 Willebroek Antwerpen 2830",
    "addr:housenumber":"12",
    "addr:postcode":"2830",
    "addr:street":"Victor Dumonlaan",
    "iso:country":"BE",
    "sg:address":"Victor Dumonlaan 12",
    "sg:city":"Willebroek",
    "sg:classifiers":[
        {
            "category":"Freight",
            "type":"Transportation"
        }
    ],
    "sg:phone":"+32 3 880 27 00",
    "sg:postcode":"2830",
    "sg:province":"Antwerpen",
    "sg:tags":[
        "container",
        "-",
        "transport"
    ],
    "wof:name":"Tct Belgium Nv",
    "wof:placetype":"venue"
},
  "geometry": {"coordinates":[4.3669800758,51.0741615295],"type":"Point"}
}