{
  "type": "Feature",
  "properties": {
    "iso:country":"BE",
    "sg:address":"Notelarestraat 6",
    "sg:city":"Wellen",
    "sg:orig_category":"Banques and organismes de cr\u00e9dit",
    "sg:phone":"+32 12 74 19 95",
    "sg:postcode":"3830",
    "sg:province":"Limburg",
    "wof:name":"Bbl",
    "wof:placetype":"venue"
},
  "geometry": {"coordinates":[5.3387351036,50.8402481079],"type":"Point"}
}