{
  "type": "Feature",
  "properties": {
    "addr:full":"Place Des Braban\u00c7ons 1ba Ottignies-louvain-la-neuve Brabant Wallon 1348",
    "addr:housenumber":"1ba",
    "addr:postcode":"1348",
    "addr:street":"Place Des Brabanc\u0327Ons",
    "iso:country":"BE",
    "sg:address":"Place Des Braban\u00c7ons 1ba",
    "sg:city":"Ottignies-louvain-la-neuve",
    "sg:classifiers":[
        {
            "category":"Restaurant",
            "type":"Food & Drink"
        }
    ],
    "sg:phone":"+32 10 45 15 85",
    "sg:postcode":"1348",
    "sg:province":"Brabant Wallon",
    "wof:name":"Le Cr\u00caperie Bretonne",
    "wof:placetype":"venue"
},
  "geometry": {"coordinates":[4.616256237,50.6686515808],"type":"Point"}
}