{
  "type": "Feature",
  "properties": {
    "addr:full":"Koekelbergstraat 4 Sint-agatha-berchem/berchem-sa Bruxelles-Capitale 1082",
    "addr:housenumber":"4",
    "addr:postcode":"1082",
    "addr:street":"Koekelbergstraat",
    "iso:country":"BE",
    "sg:address":"Koekelbergstraat 4",
    "sg:city":"Sint-agatha-berchem/berchem-sa",
    "sg:orig_category":"Fleurs and plantes",
    "sg:phone":"+32 2 513 86 97",
    "sg:postcode":"1082",
    "sg:province":"Bruxelles-Capitale",
    "wof:name":"Beevex Import",
    "wof:placetype":"venue"
},
  "geometry": {"coordinates":[4.3023691177,50.8620681763],"type":"Point"}
}