{
  "type": "Feature",
  "properties": {
    "iso:country":"BE",
    "sg:address":"Rue Du Longtry 66",
    "sg:city":"Charleroi",
    "sg:orig_category":"Pain, p\u00e2tisseries and confiseries. Equipement divers pour commerces Gr",
    "sg:phone":"+32 71 43 64 22",
    "sg:postcode":"6032",
    "sg:province":"Hainaut",
    "wof:name":"Fe. Super Cool",
    "wof:placetype":"venue"
},
  "geometry": {"coordinates":[4.4070467949,50.3728370667],"type":"Point"}
}