{
  "type": "Feature",
  "properties": {
    "iso:country":"BE",
    "sg:address":"Rozendaal 78",
    "sg:city":"Geel",
    "sg:orig_category":"Avocats and conseillers juridiques",
    "sg:phone":"+32 14 58 91 72",
    "sg:postcode":"2440",
    "sg:province":"Antwerpen",
    "wof:name":"T. Vandecruys",
    "wof:placetype":"venue"
},
  "geometry": {"coordinates":[4.9933080673,51.1656837463],"type":"Point"}
}