{
  "type": "Feature",
  "properties": {
    "addr:full":"Marktstraat 35 Maldegem Oost-Vlaanderen 9990",
    "addr:housenumber":"35",
    "addr:postcode":"9990",
    "addr:street":"Marktstraat",
    "iso:country":"BE",
    "sg:address":"Marktstraat 35",
    "sg:city":"Maldegem",
    "sg:orig_category":"Diverse kredietdiensten",
    "sg:postcode":"9990",
    "sg:province":"Oost-Vlaanderen",
    "wof:name":"Bancontact-mister Cash",
    "wof:placetype":"venue"
},
  "geometry": {"coordinates":[3.4463219643,51.2088508606],"type":"Point"}
}