{
  "type": "Feature",
  "properties": {
    "addr:full":"Kopstraat 346-348 Schoten Antwerpen 2900",
    "addr:housenumber":"346-348",
    "addr:postcode":"2900",
    "addr:street":"Kopstraat",
    "iso:country":"BE",
    "sg:address":"Kopstraat 346-348",
    "sg:city":"Schoten",
    "sg:classifiers":[
        {
            "category":"Transit Center",
            "subcategory":"Passenger",
            "type":"Transportation"
        }
    ],
    "sg:phone":"+32 3 658 14 80",
    "sg:postcode":"2900",
    "sg:province":"Antwerpen",
    "sg:tags":[
        "car",
        "trailer"
    ],
    "wof:name":"Gonnissen-wijckmans Poortencentrale Nv",
    "wof:placetype":"venue"
},
  "geometry": {"coordinates":[4.5045409203,51.2616424561],"type":"Point"}
}