{
  "type": "Feature",
  "properties": {
    "iso:country":"BE",
    "sg:address":"Dr\u00c8ve Dom Placide 1",
    "sg:city":"Genappe",
    "sg:orig_category":"M\u00e9decins and sp\u00e9cialistes",
    "sg:phone":"+32 10 61 33 75",
    "sg:postcode":"1470",
    "sg:province":"Brabant Wallon",
    "wof:name":"Chantal Duyckaerts",
    "wof:placetype":"venue"
},
  "geometry": {"coordinates":[4.5282402039,50.641708374],"type":"Point"}
}