{
  "type": "Feature",
  "properties": {
    "addr:full":"Rue Emile-kirsch 51 Messancy Luxembourg 6780",
    "addr:housenumber":"51",
    "addr:postcode":"6780",
    "addr:street":"Rue Emile-Kirsch",
    "iso:country":"BE",
    "sg:address":"Rue Emile-kirsch 51",
    "sg:city":"Messancy",
    "sg:orig_category":"Paramedische behandelingen",
    "sg:phone":"+32 63 38 81 40",
    "sg:postcode":"6780",
    "sg:province":"Luxembourg",
    "wof:name":"Hugo's",
    "wof:placetype":"venue"
},
  "geometry": {"coordinates":[5.8173398972,49.5863189697],"type":"Point"}
}