{
  "type": "Feature",
  "properties": {
    "iso:country":"BE",
    "sg:address":"Rue Des Sports 33",
    "sg:city":"Charleroi",
    "sg:orig_category":"Artsen and specialisten",
    "sg:phone":"+32 71 31 63 50",
    "sg:postcode":"6000",
    "sg:province":"Hainaut",
    "wof:name":"Jean-pierre Duch\u00c2teau",
    "wof:placetype":"venue"
},
  "geometry": {"coordinates":[4.4550299644,50.4143218994],"type":"Point"}
}