{
  "type": "Feature",
  "properties": {
    "iso:country":"BE",
    "sg:address":"Vital Decosterstraat 2",
    "sg:city":"Leuven",
    "sg:classifiers":[
        {
            "category":"Personal",
            "subcategory":"Beauty Salon",
            "type":"Services"
        }
    ],
    "sg:phone":"+32 16 22 81 36",
    "sg:postcode":"3000",
    "sg:province":"Vlaams-Brabant",
    "sg:tags":[
        "de",
        "coiffure"
    ],
    "wof:name":"Coiffure Martin",
    "wof:placetype":"venue"
},
  "geometry": {"coordinates":[4.706319809,50.8792686462],"type":"Point"}
}