{
  "type": "Feature",
  "properties": {
    "iso:country":"BE",
    "sg:address":"Hoogboomsteenweg 46",
    "sg:city":"Brasschaat",
    "sg:classifiers":[
        {
            "category":"Building & Trades",
            "subcategory":"Electrical",
            "type":"Services"
        }
    ],
    "sg:phone":"+32 3 651 46 35",
    "sg:postcode":"2930",
    "sg:province":"Antwerpen",
    "sg:tags":[
        "electric",
        "-",
        "housewiring",
        "contractor"
    ],
    "wof:name":"E S V Van Den Eede",
    "wof:placetype":"venue"
},
  "geometry": {"coordinates":[4.4851207733,51.3056869507],"type":"Point"}
}