{
  "type": "Feature",
  "properties": {
    "iso:country":"BE",
    "sg:address":"Chauss\u00e9e De Dinant 139",
    "sg:city":"Anh\u00e9e",
    "sg:classifiers":[
        {
            "category":"Professional",
            "subcategory":"Employment Agencies",
            "type":"Services"
        }
    ],
    "sg:phone":"+32 82 61 36 63",
    "sg:postcode":"5537",
    "sg:province":"Namur",
    "sg:tags":[
        "model",
        "modelling"
    ],
    "wof:name":"Pub Magic Light",
    "wof:placetype":"venue"
},
  "geometry": {"coordinates":[4.893488884,50.2963218689],"type":"Point"}
}