{
  "type": "Feature",
  "properties": {
    "iso:country":"BE",
    "sg:address":"Pastorijstraat 52",
    "sg:city":"Lille",
    "sg:orig_category":"Dranken Gh",
    "sg:phone":"+32 3 312 03 23",
    "sg:postcode":"2275",
    "sg:province":"Antwerpen",
    "wof:name":"Daems & Zoon",
    "wof:placetype":"venue"
},
  "geometry": {"coordinates":[4.792386055,51.2668113708],"type":"Point"}
}