{
  "type": "Feature",
  "properties": {
    "addr:full":"Rich. Van Britsomstraat 16 Sint-niklaas Oost-Vlaanderen 9100",
    "addr:housenumber":"16",
    "addr:postcode":"9100",
    "addr:street":"Rich.;Britsomstraat",
    "iso:country":"BE",
    "sg:address":"Rich. Van Britsomstraat 16",
    "sg:city":"Sint-niklaas",
    "sg:orig_category":"Pain, p\u00e2tisseries and confiseries",
    "sg:phone":"+32 3 766 40 41",
    "sg:postcode":"9100",
    "sg:province":"Oost-Vlaanderen",
    "wof:name":"Huis Snoepie",
    "wof:placetype":"venue"
},
  "geometry": {"coordinates":[4.1398568153,51.1679954529],"type":"Point"}
}