{
  "type": "Feature",
  "properties": {
    "addr:full":"Oosteinde 2 Lochristi Oost-Vlaanderen 9080",
    "addr:housenumber":"2",
    "addr:postcode":"9080",
    "addr:street":"Oosteinde",
    "iso:country":"BE",
    "sg:address":"Oosteinde 2",
    "sg:city":"Lochristi",
    "sg:orig_category":"Boucheries",
    "sg:phone":"+32 9 355 52 63",
    "sg:postcode":"9080",
    "sg:province":"Oost-Vlaanderen",
    "wof:name":"Roland De Vliegher",
    "wof:placetype":"venue"
},
  "geometry": {"coordinates":[3.8644359112,51.1335716248],"type":"Point"}
}