{
  "type": "Feature",
  "properties": {
    "iso:country":"BE",
    "sg:address":"Rue De Haut-vent 9",
    "sg:city":"Mettet (biesme)",
    "sg:classifiers":[
        {
            "category":"Personal",
            "subcategory":"Nail Salon",
            "type":"Services"
        }
    ],
    "sg:phone":"+32 71 72 61 84",
    "sg:postcode":"5640",
    "sg:province":"Namur",
    "sg:tags":[
        "pedicure"
    ],
    "wof:name":"Lebrun V",
    "wof:placetype":"venue"
},
  "geometry": {"coordinates":[4.6047887802,50.3379898071],"type":"Point"}
}