{
  "type": "Feature",
  "properties": {
    "addr:full":"Gravin Margaretalaan 5 Kruibeke (rupelmonde) Oost-Vlaanderen 9150",
    "addr:housenumber":"5",
    "addr:postcode":"9150",
    "addr:street":"Gravin Margaretalaan",
    "iso:country":"BE",
    "sg:address":"Gravin Margaretalaan 5",
    "sg:city":"Kruibeke (rupelmonde)",
    "sg:classifiers":[
        {
            "category":"Autos & Motor Vehicles",
            "subcategory":"Automobile Sales",
            "type":"Retail Goods"
        }
    ],
    "sg:phone":"+32 3 774 30 22",
    "sg:postcode":"9150",
    "sg:province":"Oost-Vlaanderen",
    "sg:tags":[
        "distributor",
        "independent",
        "-"
    ],
    "wof:name":"Raemdonck V",
    "wof:placetype":"venue"
},
  "geometry": {"coordinates":[4.2907891273,51.1304283142],"type":"Point"}
}