{
  "type": "Feature",
  "properties": {
    "addr:full":"Pilkemseweg 134 Ieper West-Vlaanderen 8904",
    "addr:housenumber":"134",
    "addr:postcode":"8904",
    "iso:country":"BE",
    "sg:address":"Pilkemseweg 134",
    "sg:city":"Ieper",
    "sg:orig_category":"Eleveurs de bovins",
    "sg:phone":"+32 57 48 72 84",
    "sg:postcode":"8904",
    "sg:province":"West-Vlaanderen",
    "wof:name":"Emile Lemahieu",
    "wof:placetype":"venue"
},
  "geometry": {"coordinates":[2.8885140419,50.8853416443],"type":"Point"}
}