{
  "type": "Feature",
  "properties": {
    "iso:country":"BE",
    "sg:address":"Steenweg Op Vilvoorde 15",
    "sg:city":"Opwijk",
    "sg:classifiers":[
        {
            "category":"Food & Beverages",
            "subcategory":"Fruits & Vegetables",
            "type":"Retail Goods"
        }
    ],
    "sg:phone":"+32 52 37 29 20",
    "sg:postcode":"1745",
    "sg:province":"Vlaams-Brabant",
    "sg:tags":[
        "-"
    ],
    "wof:name":"Het Marktje Bvba",
    "wof:placetype":"venue"
},
  "geometry": {"coordinates":[4.2011098862,50.960231781],"type":"Point"}
}