{
  "type": "Feature",
  "properties": {
    "addr:full":"Martelarenlaan 17 Hasselt Limburg 3500",
    "addr:housenumber":"17",
    "addr:postcode":"3500",
    "addr:street":"Martelarenlaan",
    "iso:country":"BE",
    "sg:address":"Martelarenlaan 17",
    "sg:city":"Hasselt",
    "sg:orig_category":"Biblioth\u00e8ques and archives publiques",
    "sg:phone":"+32 11 29 59 00",
    "sg:postcode":"3500",
    "sg:province":"Limburg",
    "wof:name":"Prov.cent.openb.biblioth.",
    "wof:placetype":"venue"
},
  "geometry": {"coordinates":[5.3420100212,50.9327735901],"type":"Point"}
}