{
  "type": "Feature",
  "properties": {
    "addr:full":"Rue De Sendrogne 45 Sprimont Li\u00e8ge 4141",
    "addr:housenumber":"45",
    "addr:postcode":"4141",
    "addr:street":"Rue De Sendrogne",
    "iso:country":"BE",
    "sg:address":"Rue De Sendrogne 45",
    "sg:city":"Sprimont",
    "sg:orig_category":"Woningbouw",
    "sg:phone":"+32 4 360 85 51",
    "sg:postcode":"4141",
    "sg:province":"Li\u00e8ge",
    "wof:name":"Malherbe",
    "wof:placetype":"venue"
},
  "geometry": {"coordinates":[5.7102560997,50.5312538147],"type":"Point"}
}