{
  "type": "Feature",
  "properties": {
    "iso:country":"BE",
    "sg:address":"Lentestraat 45",
    "sg:city":"Elsene (brussel)",
    "sg:orig_category":"Advocaten and juridische adviseurs",
    "sg:phone":"+32 2 649 47 10",
    "sg:postcode":"1050",
    "sg:province":"Bruxelles-Capitale",
    "wof:name":"Bosquet Serge",
    "wof:placetype":"venue"
},
  "geometry": {"coordinates":[4.3887929916,50.8203697205],"type":"Point"}
}