{
  "type": "Feature",
  "properties": {
    "iso:country":"BE",
    "sg:address":"Rue Vaux Toultia 18",
    "sg:city":"Villers-le-bouillet",
    "sg:classifiers":[
        {
            "category":"Arena",
            "subcategory":"Sports Club",
            "type":"Entertainment"
        }
    ],
    "sg:phone":"+32 19 56 62 61",
    "sg:postcode":"4530",
    "sg:province":"Li\u00e8ge",
    "sg:tags":[
        "terrain",
        "hors",
        "de",
        "installation",
        "sportifs"
    ],
    "wof:name":"F.c. Vaux-borset",
    "wof:placetype":"venue"
},
  "geometry": {"coordinates":[5.227118969,50.6118507385],"type":"Point"}
}