{
  "type": "Feature",
  "properties": {
    "addr:full":"Izegemstraat 124 Ingelmunster West-Vlaanderen 8770",
    "addr:housenumber":"124",
    "addr:postcode":"8770",
    "addr:street":"Izegemstraat",
    "iso:country":"BE",
    "sg:address":"Izegemstraat 124",
    "sg:city":"Ingelmunster",
    "sg:classifiers":[
        {
            "category":"Personal",
            "subcategory":"Beauty Salon",
            "type":"Services"
        }
    ],
    "sg:phone":"+32 51 31 12 79",
    "sg:postcode":"8770",
    "sg:province":"West-Vlaanderen",
    "sg:tags":[
        "de",
        "coiffure"
    ],
    "wof:name":"Annick Everaedt",
    "wof:placetype":"venue"
},
  "geometry": {"coordinates":[3.2475950718,50.915687561],"type":"Point"}
}