{
  "type": "Feature",
  "properties": {
    "iso:country":"BE",
    "sg:address":"Avenue De L'araucaria 48-50",
    "sg:city":"Brussel/bruxelles",
    "sg:orig_category":"Opticiens",
    "sg:phone":"+32 2 268 18 43",
    "sg:postcode":"1020",
    "sg:province":"Bruxelles-Capitale",
    "wof:name":"Optique Michel s",
    "wof:placetype":"venue"
},
  "geometry": {"coordinates":[4.363284111,50.8954620361],"type":"Point"}
}