{
  "type": "Feature",
  "properties": {
    "iso:country":"BE",
    "sg:address":"Sint-truidersteenweg 209",
    "sg:city":"Tongeren",
    "sg:orig_category":"Mat\u00e9riel m\u00e9dical and orthop\u00e9dique and proth\u00e8ses Fab",
    "sg:phone":"+32 12 23 18 14",
    "sg:postcode":"3700",
    "sg:province":"Limburg",
    "wof:name":"Albert Ruiters",
    "wof:placetype":"venue"
},
  "geometry": {"coordinates":[5.4437098503,50.7770805359],"type":"Point"}
}