{
  "type": "Feature",
  "properties": {
    "iso:country":"BE",
    "sg:address":"Achtste Liniestraat 11",
    "sg:city":"Diksmuide (keiem)",
    "sg:classifiers":[
        {
            "category":"Personal",
            "subcategory":"Beauty Salon",
            "type":"Services"
        }
    ],
    "sg:phone":"+32 51 51 06 38",
    "sg:postcode":"8600",
    "sg:province":"West-Vlaanderen",
    "sg:tags":[
        "lady",
        "-",
        "hairdressing"
    ],
    "wof:name":"Nancy Coiffure",
    "wof:placetype":"venue"
},
  "geometry": {"coordinates":[2.8770520687,51.0805778503],"type":"Point"}
}