{
  "type": "Feature",
  "properties": {
    "iso:country":"BE",
    "sg:address":"Zavelstraat 8",
    "sg:city":"Puurs",
    "sg:classifiers":[
        {
            "category":"Arena",
            "subcategory":"Sports Club",
            "type":"Entertainment"
        }
    ],
    "sg:phone":"+32 3 889 30 05",
    "sg:postcode":"2870",
    "sg:province":"Antwerpen",
    "sg:tags":[
        "de"
    ],
    "wof:name":"Het Noorden",
    "wof:placetype":"venue"
},
  "geometry": {"coordinates":[4.3032197952,51.0441398621],"type":"Point"}
}