{
  "type": "Feature",
  "properties": {
    "iso:country":"BE",
    "sg:address":"Molenstraat 19be",
    "sg:city":"Maldegem",
    "sg:orig_category":"Slagers",
    "sg:phone":"+32 50 71 84 10",
    "sg:postcode":"9991",
    "sg:province":"Oost-Vlaanderen",
    "wof:name":"Crispyn",
    "wof:placetype":"venue"
},
  "geometry": {"coordinates":[3.4974191189,51.1984405518],"type":"Point"}
}