{
  "type": "Feature",
  "properties": {
    "iso:country":"BE",
    "sg:address":"Chauss\u00c9e De Nivelles 612",
    "sg:city":"Pont-a-celles",
    "sg:orig_category":"Woningbouw",
    "sg:phone":"+32 71 84 37 79",
    "sg:postcode":"6230",
    "sg:province":"Hainaut",
    "wof:name":"Gilbert Bizet",
    "wof:placetype":"venue"
},
  "geometry": {"coordinates":[4.3707361221,50.507106781],"type":"Point"}
}