{
  "type": "Feature",
  "properties": {
    "iso:country":"BE",
    "sg:address":"Kerkstraat 51",
    "sg:city":"Blankenberge",
    "sg:orig_category":"Voedingsspeciaalzaken",
    "sg:phone":"+32 50 41 22 37",
    "sg:postcode":"8370",
    "sg:province":"West-Vlaanderen",
    "wof:name":"Traiteur Saint-hubert",
    "wof:placetype":"venue"
},
  "geometry": {"coordinates":[3.1292569637,51.3148994446],"type":"Point"}
}