{
  "type": "Feature",
  "properties": {
    "iso:country":"BE",
    "sg:address":"Vissegatstraat 57",
    "sg:city":"Sint-truiden",
    "sg:orig_category":"Sportclubs",
    "sg:phone":"+32 11 67 35 95",
    "sg:postcode":"3800",
    "sg:province":"Limburg",
    "wof:name":"Ito Okita Jiu Jiutsu",
    "wof:placetype":"venue"
},
  "geometry": {"coordinates":[5.1912779808,50.8191337585],"type":"Point"}
}