{
  "type": "Feature",
  "properties": {
    "addr:full":"Chauss\u00e9e De Ninove 364 Bruxelles (anderlecht) Bruxelles-Capitale 1070",
    "addr:housenumber":"364",
    "addr:postcode":"1070",
    "addr:street":"Chausse\u0301E De Ninove",
    "iso:country":"BE",
    "sg:address":"Chauss\u00e9e De Ninove 364",
    "sg:city":"Bruxelles (anderlecht)",
    "sg:classifiers":[
        {
            "category":"Retail",
            "subcategory":"Funeral Services",
            "type":"Services"
        }
    ],
    "sg:phone":"+32 2 521 79 52",
    "sg:postcode":"1070",
    "sg:province":"Bruxelles-Capitale",
    "sg:tags":[
        "director"
    ],
    "wof:name":"Pellet",
    "wof:placetype":"venue"
},
  "geometry": {"coordinates":[4.3126349449,50.8479309082],"type":"Point"}
}