{
  "type": "Feature",
  "properties": {
    "iso:country":"BE",
    "sg:address":"Bosstraat 55",
    "sg:city":"Maaseik",
    "sg:classifiers":[
        {
            "category":"Government",
            "subcategory":"Department Of Motor Vehicles",
            "type":"Public Place"
        }
    ],
    "sg:phone":"+32 89 56 75 84",
    "sg:postcode":"3680",
    "sg:province":"Limburg",
    "sg:tags":[
        "painting",
        "picture",
        "-",
        "sale",
        "purchase"
    ],
    "wof:name":"Art Deco",
    "wof:placetype":"venue"
},
  "geometry": {"coordinates":[5.7875781059,51.0958976746],"type":"Point"}
}