{
  "type": "Feature",
  "properties": {
    "iso:country":"BE",
    "sg:address":"Chemin Des Moulyniers 19",
    "sg:city":"Dalhem (feneur)",
    "sg:classifiers":[
        {
            "category":"Real Estate",
            "subcategory":"Real Estate Services",
            "type":"Services"
        }
    ],
    "sg:phone":"+32 4 379 55 53",
    "sg:postcode":"4607",
    "sg:province":"Li\u00e8ge",
    "wof:name":"Immo Ang\u00e9ma Sprl",
    "wof:placetype":"venue"
},
  "geometry": {"coordinates":[5.7099409103,50.7035369873],"type":"Point"}
}