{
  "type": "Feature",
  "properties": {
    "addr:full":"Rue Du Plein Vent 5 Weismes Li\u00e8ge 4950",
    "addr:housenumber":"5",
    "addr:postcode":"4950",
    "addr:street":"Rue Du Plein Vent",
    "iso:country":"BE",
    "sg:address":"Rue Du Plein Vent 5",
    "sg:city":"Weismes",
    "sg:orig_category":"Sportclubs",
    "sg:phone":"+32 80 44 48 31",
    "sg:postcode":"4950",
    "sg:province":"Li\u00e8ge",
    "wof:name":"Vs St. Vith",
    "wof:placetype":"venue"
},
  "geometry": {"coordinates":[6.1296448708,50.4646911621],"type":"Point"}
}