{
  "type": "Feature",
  "properties": {
    "iso:country":"BE",
    "sg:address":"Kruisveld 48",
    "sg:city":"Sint-amands (oppuurs)",
    "sg:classifiers":[
        {
            "category":"Building & Trades",
            "subcategory":"Construction",
            "type":"Services"
        }
    ],
    "sg:phone":"+32 3 889 79 55",
    "sg:postcode":"2890",
    "sg:province":"Antwerpen",
    "sg:tags":[
        "installation",
        "-",
        "central",
        "heating"
    ],
    "wof:name":"Reynaert I",
    "wof:placetype":"venue"
},
  "geometry": {"coordinates":[4.2419099808,51.0651016235],"type":"Point"}
}