{
  "type": "Feature",
  "properties": {
    "addr:full":"Aarschotsesteenweg 854 Wilsele Vlaams-Brabant 3012",
    "addr:housenumber":"854",
    "addr:postcode":"3012",
    "addr:street":"Aarschotsesteenweg",
    "iso:country":"BE",
    "sg:address":"Aarschotsesteenweg 854",
    "sg:city":"Wilsele",
    "sg:orig_category":"Foto-uitrusting Fotografen and fotostudio's Fotolaboratoria Sport- and kampeermateriaal",
    "sg:phone":"+32 16 44 78 44",
    "sg:postcode":"3012",
    "sg:province":"Vlaams-Brabant",
    "wof:name":"Ab&d",
    "wof:placetype":"venue"
},
  "geometry": {"coordinates":[4.7166199684,50.9159889221],"type":"Point"}
}