{
  "type": "Feature",
  "properties": {
    "addr:full":"Roeselarestraat 92ba Hooglede West-Vlaanderen 8830",
    "addr:housenumber":"92ba",
    "addr:postcode":"8830",
    "addr:street":"Roeselarestraat",
    "iso:country":"BE",
    "sg:address":"Roeselarestraat 92ba",
    "sg:city":"Hooglede",
    "sg:orig_category":"Rundveehouders Varkenskwekers",
    "sg:phone":"+32 51 24 64 80",
    "sg:postcode":"8830",
    "sg:province":"West-Vlaanderen",
    "wof:name":"Marc Valcke",
    "wof:placetype":"venue"
},
  "geometry": {"coordinates":[3.0868270397,50.9711647034],"type":"Point"}
}