{
  "type": "Feature",
  "properties": {
    "addr:full":"Rue Du Trone 14/15 Bruxelles Bruxelles-Capitale 1000",
    "addr:housenumber":"14 / 15",
    "addr:postcode":"1000",
    "addr:street":"Rue Du Trone",
    "iso:country":"BE",
    "sg:address":"Rue Du Trone 14/15",
    "sg:city":"Bruxelles",
    "sg:classifiers":[
        {
            "category":"Banks & Credit Unions",
            "subcategory":"Bank",
            "type":"Services"
        }
    ],
    "sg:phone":"+32 2 511 91 85",
    "sg:postcode":"1000",
    "sg:province":"Bruxelles-Capitale",
    "wof:name":"Banco Do Brasil Europe",
    "wof:placetype":"venue"
},
  "geometry": {"coordinates":[4.3667387962,50.8398666382],"type":"Point"}
}