{
  "type": "Feature",
  "properties": {
    "iso:country":"BE",
    "sg:address":"Europaweg 10",
    "sg:city":"Zottegem (grotenberge)",
    "sg:classifiers":[
        {
            "category":"Manufacturing",
            "subcategory":"Building Materials",
            "type":"Manufacturing & Wholesale Goods"
        }
    ],
    "sg:phone":"+32 9 360 67 63",
    "sg:postcode":"9620",
    "sg:province":"Oost-Vlaanderen",
    "sg:tags":[
        "boiler",
        "manufacturer"
    ],
    "wof:name":"Aerts Tankbouw Bvba",
    "wof:placetype":"venue"
},
  "geometry": {"coordinates":[3.8112111092,50.871181488],"type":"Point"}
}