{
  "type": "Feature",
  "properties": {
    "addr:full":"Rue Des Muguets 19 Mons (baudour) Hainaut 7331",
    "addr:housenumber":"19",
    "addr:postcode":"7331",
    "addr:street":"Rue Des Muguets",
    "iso:country":"BE",
    "sg:address":"Rue Des Muguets 19",
    "sg:city":"Mons (baudour)",
    "sg:classifiers":[
        {
            "category":"Recreation",
            "subcategory":"Arcade",
            "type":"Entertainment"
        }
    ],
    "sg:phone":"+32 65 64 11 85",
    "sg:postcode":"7331",
    "sg:province":"Hainaut",
    "sg:tags":[
        "machine",
        "amusement"
    ],
    "wof:name":"Electronic Amusement Sprl",
    "wof:placetype":"venue"
},
  "geometry": {"coordinates":[3.832367897,50.4841804504],"type":"Point"}
}