{
  "type": "Feature",
  "properties": {
    "addr:full":"Vrijheidsstraat 16 Duffel Antwerpen 2570",
    "addr:housenumber":"16",
    "addr:postcode":"2570",
    "addr:street":"Vrijheidsstraat",
    "iso:country":"BE",
    "sg:address":"Vrijheidsstraat 16",
    "sg:city":"Duffel",
    "sg:orig_category":"Artsen and specialisten",
    "sg:phone":"+32 15 31 85 55",
    "sg:postcode":"2570",
    "sg:province":"Antwerpen",
    "wof:name":"M. Vandenbroucke",
    "wof:placetype":"venue"
},
  "geometry": {"coordinates":[4.5125107765,51.0935668945],"type":"Point"}
}