{
  "type": "Feature",
  "properties": {
    "iso:country":"BE",
    "sg:address":"Quartier Haynol",
    "sg:city":"Libramont-chevigny",
    "sg:classifiers":[
        {
            "category":"Building & Trades",
            "subcategory":"Landscaping Services",
            "type":"Services"
        }
    ],
    "sg:phone":"+32 61 23 03 40",
    "sg:postcode":"6800",
    "sg:province":"Luxembourg",
    "sg:tags":[
        "earth",
        "moving"
    ],
    "wof:name":"J\u00e9rouville Entreprises S.a.",
    "wof:placetype":"venue"
},
  "geometry": {"coordinates":[5.3761348724,49.9199943542],"type":"Point"}
}