{
  "type": "Feature",
  "properties": {
    "iso:country":"BE",
    "sg:address":"Vromondstraat 55a",
    "sg:city":"Laarne (kalken)",
    "sg:classifiers":[
        {
            "category":"Professional",
            "subcategory":"Art Services",
            "type":"Services"
        }
    ],
    "sg:phone":"+32 9 367 93 53",
    "sg:postcode":"9270",
    "sg:province":"Oost-Vlaanderen",
    "sg:tags":[
        "photography",
        "reporting",
        "-"
    ],
    "wof:name":"Eeraerts H",
    "wof:placetype":"venue"
},
  "geometry": {"coordinates":[3.921900034,51.0413703918],"type":"Point"}
}