{
  "type": "Feature",
  "properties": {
    "addr:full":"Nicolaylaan 105 Box 1 Leopoldsburg Limburg 3970",
    "addr:housenumber":"105;1",
    "addr:postcode":"3970",
    "addr:street":"Nicolaylaan;Box",
    "iso:country":"BE",
    "sg:address":"Nicolaylaan 105 Box 1",
    "sg:city":"Leopoldsburg",
    "sg:classifiers":[
        {
            "category":"Social Services",
            "subcategory":"Child Care",
            "type":"Services"
        }
    ],
    "sg:phone":"+32 11 34 83 91",
    "sg:postcode":"3970",
    "sg:province":"Limburg",
    "sg:tags":[
        "baby",
        "nursery",
        "day",
        "sitting"
    ],
    "wof:name":"Dienst Voor Onthaalgezinnen",
    "wof:placetype":"venue"
},
  "geometry": {"coordinates":[5.2582101822,51.119052887],"type":"Point"}
}