{
  "type": "Feature",
  "properties": {
    "addr:full":"Rue Des Panneries 49 Saint-ghislain (sirault) Hainaut 7332",
    "addr:housenumber":"49",
    "addr:postcode":"7332",
    "addr:street":"Rue Des Panneries",
    "iso:country":"BE",
    "sg:address":"Rue Des Panneries 49",
    "sg:city":"Saint-ghislain (sirault)",
    "sg:classifiers":[
        {
            "category":"Retail",
            "subcategory":"Auto Repair",
            "type":"Services"
        }
    ],
    "sg:phone":"+32 65 62 39 96",
    "sg:postcode":"7332",
    "sg:province":"Hainaut",
    "sg:tags":[
        "garage"
    ],
    "wof:name":"Glineur F",
    "wof:placetype":"venue"
},
  "geometry": {"coordinates":[3.786839962,50.5054969788],"type":"Point"}
}