{
  "type": "Feature",
  "properties": {
    "addr:full":"Berlion 8 Celles Hainaut 7760",
    "addr:housenumber":"8",
    "addr:postcode":"7760",
    "addr:street":"Berlion",
    "iso:country":"BE",
    "sg:address":"Berlion 8",
    "sg:city":"Celles",
    "sg:orig_category":"Eleveurs de bovins",
    "sg:phone":"+32 69 85 91 07",
    "sg:postcode":"7760",
    "sg:province":"Hainaut",
    "wof:name":"Lucien Deschepper",
    "wof:placetype":"venue"
},
  "geometry": {"coordinates":[3.4686439037,50.6759262085],"type":"Point"}
}