{
  "type": "Feature",
  "properties": {
    "iso:country":"BE",
    "sg:address":"Heirweg 47bb",
    "sg:city":"Maldegem",
    "sg:orig_category":"Diverse bouwafwerking and reiniging Gespecialiseerde residenti\u00eble bouw",
    "sg:phone":"+32 50 71 49 09",
    "sg:postcode":"9990",
    "sg:province":"Oost-Vlaanderen",
    "wof:name":"Voegwerken Roels",
    "wof:placetype":"venue"
},
  "geometry": {"coordinates":[3.4036400318,51.212020874],"type":"Point"}
}