{
  "type": "Feature",
  "properties": {
    "addr:full":"Beukendreef 8 Knokke-heist West-Vlaanderen 8300",
    "addr:housenumber":"8",
    "addr:postcode":"8300",
    "addr:street":"Beukendreef",
    "iso:country":"BE",
    "sg:address":"Beukendreef 8",
    "sg:city":"Knokke-heist",
    "sg:orig_category":"Experts-comptables",
    "sg:phone":"+32 50 60 45 15",
    "sg:postcode":"8300",
    "sg:province":"West-Vlaanderen",
    "wof:name":"Emiel Boussy",
    "wof:placetype":"venue"
},
  "geometry": {"coordinates":[3.287694931,51.3467254639],"type":"Point"}
}