{
  "type": "Feature",
  "properties": {
    "addr:full":"Rue Du Travail 9 Namur Namur 5000",
    "addr:housenumber":"9",
    "addr:postcode":"5000",
    "addr:street":"Rue Du Travail",
    "iso:country":"BE",
    "sg:address":"Rue Du Travail 9",
    "sg:city":"Namur",
    "sg:classifiers":[
        {
            "category":"Health Services",
            "subcategory":"Health Practitioner",
            "type":"Services"
        }
    ],
    "sg:phone":"+32 81 74 28 40",
    "sg:postcode":"5000",
    "sg:province":"Namur",
    "sg:tags":[
        "physiotherapist"
    ],
    "wof:name":"Binon P",
    "wof:placetype":"venue"
},
  "geometry": {"coordinates":[4.8430099487,50.4597587585],"type":"Point"}
}