{
  "type": "Feature",
  "properties": {
    "iso:country":"BE",
    "sg:address":"Leo Steelstraat 6",
    "sg:city":"Evergem",
    "sg:orig_category":"M\u00e9decins and sp\u00e9cialistes",
    "sg:phone":"+32 9 358 20 09",
    "sg:postcode":"9940",
    "sg:province":"Oost-Vlaanderen",
    "wof:name":"Carine Van Den Bossche",
    "wof:placetype":"venue"
},
  "geometry": {"coordinates":[3.6715550423,51.1308135986],"type":"Point"}
}