{
  "type": "Feature",
  "properties": {
    "addr:full":"Kapelstraat 66 Brecht Antwerpen 2960",
    "addr:housenumber":"66",
    "addr:postcode":"2960",
    "addr:street":"Kapelstraat",
    "iso:country":"BE",
    "sg:address":"Kapelstraat 66",
    "sg:city":"Brecht",
    "sg:orig_category":"Banken and kredietinstellingen",
    "sg:phone":"+32 3 313 74 74",
    "sg:postcode":"2960",
    "sg:province":"Antwerpen",
    "wof:name":"Kbc",
    "wof:placetype":"venue"
},
  "geometry": {"coordinates":[4.6072659492,51.3424377441],"type":"Point"}
}