{
  "type": "Feature",
  "properties": {
    "addr:full":"Nitsemstraat 22 Hasselt Limburg 3512",
    "addr:housenumber":"22",
    "addr:postcode":"3512",
    "addr:street":"Nitsemstraat",
    "iso:country":"BE",
    "sg:address":"Nitsemstraat 22",
    "sg:city":"Hasselt",
    "sg:orig_category":"Varkenskwekers",
    "sg:phone":"+32 11 31 28 94",
    "sg:postcode":"3512",
    "sg:province":"Limburg",
    "wof:name":"Jozef Schreurs",
    "wof:placetype":"venue"
},
  "geometry": {"coordinates":[5.2391319275,50.894821167],"type":"Point"}
}