{
  "type": "Feature",
  "properties": {
    "addr:full":"Edmond Laponstraat 33 Oostende West-Vlaanderen 8400",
    "addr:housenumber":"33",
    "addr:postcode":"8400",
    "addr:street":"Edmond Laponstraat",
    "iso:country":"BE",
    "sg:address":"Edmond Laponstraat 33",
    "sg:city":"Oostende",
    "sg:classifiers":[
        {
            "category":"Insurance",
            "subcategory":"Insurance Agent",
            "type":"Services"
        }
    ],
    "sg:phone":"+32 59 80 24 52",
    "sg:postcode":"8400",
    "sg:province":"West-Vlaanderen",
    "sg:tags":[
        "broker"
    ],
    "wof:name":"Batsleer G",
    "wof:placetype":"venue"
},
  "geometry": {"coordinates":[2.9081339836,51.2256889343],"type":"Point"}
}