{
  "type": "Feature",
  "properties": {
    "addr:full":"Stationsplein 3 Denderleeuw Oost-Vlaanderen 9470",
    "addr:housenumber":"3",
    "addr:postcode":"9470",
    "addr:street":"Stationsplein",
    "iso:country":"BE",
    "sg:address":"Stationsplein 3",
    "sg:city":"Denderleeuw",
    "sg:classifiers":[
        {
            "category":"Fast Food",
            "type":"Food & Drink"
        }
    ],
    "sg:phone":"+32 53 66 96 00",
    "sg:postcode":"9470",
    "sg:province":"Oost-Vlaanderen",
    "sg:tags":[
        "fried",
        "stand",
        "potato"
    ],
    "wof:name":"Antoine",
    "wof:placetype":"venue"
},
  "geometry": {"coordinates":[4.0727391243,50.8918571472],"type":"Point"}
}