{
  "type": "Feature",
  "properties": {
    "iso:country":"BE",
    "sg:address":"Avenue Nekkersgat 17",
    "sg:city":"Ukkel/uccle",
    "sg:orig_category":"Enseignement secondaire g\u00e9n\u00e9ral. Enseignement secondaire technique and professionnel",
    "sg:phone":"+32 2 376 61 55",
    "sg:postcode":"1180",
    "sg:province":"Bruxelles-Capitale",
    "wof:name":"Koninklijk Atheneum",
    "wof:placetype":"venue"
},
  "geometry": {"coordinates":[4.3272018433,50.7922859192],"type":"Point"}
}