{
  "type": "Feature",
  "properties": {
    "addr:full":"Clos Du Bo\u00c9 3 Hamoir Li\u00e8ge 4180",
    "addr:housenumber":"3",
    "addr:postcode":"4180",
    "addr:street":"Clos Du Boe\u0301",
    "iso:country":"BE",
    "sg:address":"Clos Du Bo\u00c9 3",
    "sg:city":"Hamoir",
    "sg:orig_category":"Boekhouders",
    "sg:phone":"+32 4 369 16 90",
    "sg:postcode":"4180",
    "sg:province":"Li\u00e8ge",
    "wof:name":"Courtage Ourthe Ambl\u00c8ve",
    "wof:placetype":"venue"
},
  "geometry": {"coordinates":[5.5741410255,50.4565887451],"type":"Point"}
}