{
  "type": "Feature",
  "properties": {
    "iso:country":"BE",
    "sg:address":"Dreve 79",
    "sg:city":"Dentergem",
    "sg:classifiers":[
        {
            "category":"Insurance",
            "subcategory":"Life Insurance",
            "type":"Services"
        }
    ],
    "sg:phone":"+32 51 63 52 41",
    "sg:postcode":"8720",
    "sg:province":"West-Vlaanderen",
    "sg:tags":[
        "assurance"
    ],
    "wof:name":"M. Vandewalle",
    "wof:placetype":"venue"
},
  "geometry": {"coordinates":[3.4133501053,50.9638290405],"type":"Point"}
}