{
  "type": "Feature",
  "properties": {
    "iso:country":"BE",
    "sg:address":"Rue De La Station 20",
    "sg:city":"Berloz (corswarem)",
    "sg:classifiers":[
        {
            "category":"Building & Trades",
            "subcategory":"Pest Control",
            "type":"Services"
        }
    ],
    "sg:phone":"+32 19 33 16 80",
    "sg:postcode":"4257",
    "sg:province":"Li\u00e8ge",
    "sg:tags":[
        "painting",
        "contractor"
    ],
    "wof:name":"Cb D\u00e9co",
    "wof:placetype":"venue"
},
  "geometry": {"coordinates":[5.2106699944,50.7057571411],"type":"Point"}
}