{
  "type": "Feature",
  "properties": {
    "iso:country":"BE",
    "sg:address":"Rue Des Douaniers 98",
    "sg:city":"Hastiere",
    "sg:orig_category":"Elektrische installaties voor woningen Huishoudapparaten, televisies and radio's",
    "sg:phone":"+32 82 64 55 36",
    "sg:postcode":"5543",
    "sg:province":"Namur",
    "wof:name":"Ereti Sonorisation",
    "wof:placetype":"venue"
},
  "geometry": {"coordinates":[4.8300671577,50.1596717834],"type":"Point"}
}