{
  "type": "Feature",
  "properties": {
    "iso:country":"BE",
    "sg:address":"Egide Van Ophemstraat 143",
    "sg:city":"Ukkel/uccle",
    "sg:orig_category":"Kapsalons",
    "sg:phone":"+32 2 376 57 12",
    "sg:postcode":"1180",
    "sg:province":"Bruxelles-Capitale",
    "wof:name":"Jean Destryker",
    "wof:placetype":"venue"
},
  "geometry": {"coordinates":[4.3252668381,50.7952232361],"type":"Point"}
}