{
  "type": "Feature",
  "properties": {
    "addr:full":"Stationsstraat 31b2 Londerzeel Vlaams-Brabant 1840",
    "addr:housenumber":"31b2",
    "addr:postcode":"1840",
    "addr:street":"Stationsstraat",
    "iso:country":"BE",
    "sg:address":"Stationsstraat 31b2",
    "sg:city":"Londerzeel",
    "sg:orig_category":"Drukkerijen and copyshops Geschenken and souvenirs Kantoormateriaal",
    "sg:phone":"+32 52 30 50 86",
    "sg:postcode":"1840",
    "sg:province":"Vlaams-Brabant",
    "wof:name":"Hilde Cools",
    "wof:placetype":"venue"
},
  "geometry": {"coordinates":[4.3019042015,51.0060653687],"type":"Point"}
}