{
  "type": "Feature",
  "properties": {
    "iso:country":"BE",
    "sg:address":"Rue Du Lombard 39",
    "sg:city":"Bruxelles",
    "sg:orig_category":"Newspapers, magazines, periodicals - Distribution",
    "sg:phone":"+32 2 511 94 93",
    "sg:postcode":"1000",
    "sg:province":"Bruxelles-Capitale",
    "wof:name":"Librairie Du Lombard",
    "wof:placetype":"venue"
},
  "geometry": {"coordinates":[4.3505249023,50.8455581665],"type":"Point"}
}