{
  "type": "Feature",
  "properties": {
    "iso:country":"BE",
    "sg:address":"Rue Lug\u00e9a 30",
    "sg:city":"Ans (alleur)",
    "sg:classifiers":[
        {
            "category":"Personal",
            "subcategory":"Beauty Salon",
            "type":"Services"
        }
    ],
    "sg:phone":"+32 4 263 92 38",
    "sg:postcode":"4432",
    "sg:province":"Li\u00e8ge",
    "sg:tags":[
        "lady",
        "-",
        "hairdressing"
    ],
    "wof:name":"Alice Coiffure",
    "wof:placetype":"venue"
},
  "geometry": {"coordinates":[5.5192408562,50.6737556458],"type":"Point"}
}