{
  "type": "Feature",
  "properties": {
    "addr:full":"Rue De Villers 306 Charleroi (couillet) Hainaut 6010",
    "addr:housenumber":"306",
    "addr:postcode":"6010",
    "addr:street":"Rue De Villers",
    "iso:country":"BE",
    "sg:address":"Rue De Villers 306",
    "sg:city":"Charleroi (couillet)",
    "sg:classifiers":[
        {
            "category":"Health Services",
            "subcategory":"Nursing And Care Facility",
            "type":"Services"
        }
    ],
    "sg:phone":"+32 71 43 69 38",
    "sg:postcode":"6010",
    "sg:province":"Hainaut",
    "sg:tags":[
        "home"
    ],
    "wof:name":"Genard M",
    "wof:placetype":"venue"
},
  "geometry": {"coordinates":[4.4790420532,50.3838310242],"type":"Point"}
}