{
  "type": "Feature",
  "properties": {
    "iso:country":"BE",
    "sg:address":"Av. De L` Hippodrome 152",
    "sg:city":"Elsene/ixelles",
    "sg:orig_category":"Mat\u00e9riel de T\u00e9l\u00e9communication",
    "sg:phone":"+32 2 646 58 69",
    "sg:postcode":"1050",
    "sg:province":"Bruxelles-Capitale",
    "wof:name":"Informelec",
    "wof:placetype":"venue"
},
  "geometry": {"coordinates":[4.3777008057,50.8199462891],"type":"Point"}
}