{
  "type": "Feature",
  "properties": {
    "iso:country":"BE",
    "sg:address":"Brusselsesteenweg 386",
    "sg:city":"Herent (veltem-beisem)",
    "sg:classifiers":[
        {
            "category":"Professional",
            "subcategory":"Computer Services",
            "type":"Services"
        }
    ],
    "sg:phone":"+32 16 48 85 56",
    "sg:postcode":"3020",
    "sg:province":"Vlaams-Brabant",
    "sg:tags":[
        "-",
        "processing",
        "data",
        "software"
    ],
    "wof:name":"M.c.s.c.",
    "wof:placetype":"venue"
},
  "geometry": {"coordinates":[4.6591420174,50.888584137],"type":"Point"}
}