{
  "type": "Feature",
  "properties": {
    "addr:full":"Au-chemin 52 Hasti\u00e8re (blaimont) Namur 5542",
    "addr:housenumber":"52",
    "addr:postcode":"5542",
    "addr:street":"Au-Chemin",
    "iso:country":"BE",
    "sg:address":"Au-chemin 52",
    "sg:city":"Hasti\u00e8re (blaimont)",
    "sg:classifiers":[
        {
            "category":"Retail",
            "subcategory":"Animal Services",
            "type":"Services"
        }
    ],
    "sg:phone":"+32 82 64 72 36",
    "sg:postcode":"5542",
    "sg:province":"Namur",
    "sg:tags":[
        "farrier"
    ],
    "wof:name":"Pirson S",
    "wof:placetype":"venue"
},
  "geometry": {"coordinates":[4.8407201767,50.19323349],"type":"Point"}
}