{
  "type": "Feature",
  "properties": {
    "iso:country":"BE",
    "sg:address":"Boulevard Sainte-beuve 26",
    "sg:city":"Li\u00e8ge 1",
    "sg:classifiers":[
        {
            "category":"Education",
            "subcategory":"Special Training",
            "type":"Public Place"
        }
    ],
    "sg:phone":"+32 4 252 64 05",
    "sg:postcode":"4000",
    "sg:province":"Li\u00e8ge",
    "sg:tags":[
        "school",
        "language"
    ],
    "wof:name":"B.d. Comes",
    "wof:placetype":"venue"
},
  "geometry": {"coordinates":[5.5487518311,50.6333274841],"type":"Point"}
}