{
  "type": "Feature",
  "properties": {
    "addr:full":"Oude Rondelaan 76-78 Leuven Vlaams-Brabant 3000",
    "addr:housenumber":"76-78",
    "addr:postcode":"3000",
    "addr:street":"Oude Rondelaan",
    "iso:country":"BE",
    "sg:address":"Oude Rondelaan 76-78",
    "sg:city":"Leuven",
    "sg:classifiers":[
        {
            "category":"Professional",
            "subcategory":"Accounting & Tax Preparation",
            "type":"Services"
        }
    ],
    "sg:phone":"+32 16 22 94 40",
    "sg:postcode":"3000",
    "sg:province":"Vlaams-Brabant",
    "sg:tags":[
        "bookkeeper"
    ],
    "wof:name":"Aaiko Consult Nv",
    "wof:placetype":"venue"
},
  "geometry": {"coordinates":[4.687994957,50.8876838684],"type":"Point"}
}