{
  "type": "Feature",
  "properties": {
    "addr:full":"Zwevegemsestraat 20 Kortrijk West-Vlaanderen 8500",
    "addr:housenumber":"20",
    "addr:postcode":"8500",
    "addr:street":"Zwevegemsestraat",
    "iso:country":"BE",
    "sg:address":"Zwevegemsestraat 20",
    "sg:city":"Kortrijk",
    "sg:classifiers":[
        {
            "category":"Shopping",
            "subcategory":"Bicycles & Sporting Goods",
            "type":"Retail Goods"
        }
    ],
    "sg:phone":"+32 56 21 01 74",
    "sg:postcode":"8500",
    "sg:province":"West-Vlaanderen",
    "sg:tags":[
        "article",
        "de",
        "sport",
        "camping"
    ],
    "wof:name":"D'amazone",
    "wof:placetype":"venue"
},
  "geometry": {"coordinates":[3.2718300819,50.8258323669],"type":"Point"}
}