{
  "type": "Feature",
  "properties": {
    "addr:full":"Rue Jean Jaur\u00e8s 160 La Louvi\u00e8re Hainaut 7100",
    "addr:housenumber":"160",
    "addr:postcode":"7100",
    "addr:street":"Rue Jean Jaure\u0300S",
    "iso:country":"BE",
    "sg:address":"Rue Jean Jaur\u00e8s 160",
    "sg:city":"La Louvi\u00e8re",
    "sg:classifiers":[
        {
            "category":"Airport",
            "subcategory":"International",
            "type":"Transportation"
        }
    ],
    "sg:phone":"+32 64 22 57 48",
    "sg:postcode":"7100",
    "sg:province":"Hainaut",
    "sg:tags":[
        "-",
        "transport"
    ],
    "wof:name":"Jeremie-lef\u00e8vre Sprl",
    "wof:placetype":"venue"
},
  "geometry": {"coordinates":[4.190964222,50.4836959839],"type":"Point"}
}