{
  "type": "Feature",
  "properties": {
    "iso:country":"BE",
    "sg:address":"Rue Emile Vandervelde 78",
    "sg:city":"Ecaussinnes",
    "sg:orig_category":"Rundveehouders",
    "sg:phone":"+32 67 44 21 99",
    "sg:postcode":"7190",
    "sg:province":"Hainaut",
    "wof:name":"Nestor Bastenier",
    "wof:placetype":"venue"
},
  "geometry": {"coordinates":[4.1710209846,50.540222168],"type":"Point"}
}