{
  "type": "Feature",
  "properties": {
    "iso:country":"BE",
    "sg:address":"Iepersteenweg 28",
    "sg:city":"Diksmuide (woumen)",
    "sg:classifiers":[
        {
            "category":"Farming",
            "subcategory":"Livestock Farm",
            "type":"Manufacturing & Wholesale Goods"
        }
    ],
    "sg:phone":"+32 51 50 20 15",
    "sg:postcode":"8600",
    "sg:province":"West-Vlaanderen",
    "sg:tags":[
        "buyer"
    ],
    "wof:name":"Jonckheere G & W",
    "wof:placetype":"venue"
},
  "geometry": {"coordinates":[2.8688099384,50.9905204773],"type":"Point"}
}