{
  "type": "Feature",
  "properties": {
    "addr:full":"Voldersstraat 33 Mechelen Antwerpen 2800",
    "addr:housenumber":"33",
    "addr:postcode":"2800",
    "addr:street":"Voldersstraat",
    "iso:country":"BE",
    "sg:address":"Voldersstraat 33",
    "sg:city":"Mechelen",
    "sg:orig_category":"M\u00e9decins and sp\u00e9cialistes",
    "sg:phone":"+32 15 55 60 16",
    "sg:postcode":"2800",
    "sg:province":"Antwerpen",
    "wof:name":"Yvon Van Elslander",
    "wof:placetype":"venue"
},
  "geometry": {"coordinates":[4.4986147881,51.0310173035],"type":"Point"}
}