{
  "type": "Feature",
  "properties": {
    "addr:full":"Hoveniersstraat 2b206 Antwerpen Antwerpen 2018",
    "addr:housenumber":"2b206",
    "addr:postcode":"2018",
    "addr:street":"Hoveniersstraat",
    "iso:country":"BE",
    "sg:address":"Hoveniersstraat 2b206",
    "sg:city":"Antwerpen",
    "sg:orig_category":"Produits interm\u00e9diaires Gr",
    "sg:phone":"+32 3 232 97 46",
    "sg:postcode":"2018",
    "sg:province":"Antwerpen",
    "wof:name":"Golconda",
    "wof:placetype":"venue"
},
  "geometry": {"coordinates":[4.418451786,51.2157592773],"type":"Point"}
}