{
  "type": "Feature",
  "properties": {
    "iso:country":"BE",
    "sg:address":"Chauss\u00c9e De La Croix 57",
    "sg:city":"Ottignies-louvain-la-neuve",
    "sg:orig_category":"Herstellingen and onderhoud van auto's",
    "sg:phone":"+32 10 41 43 22",
    "sg:postcode":"1340",
    "sg:province":"Brabant Wallon",
    "wof:name":"Garage Renard Et Fils",
    "wof:placetype":"venue"
},
  "geometry": {"coordinates":[4.5774121284,50.6688461304],"type":"Point"}
}