{
  "type": "Feature",
  "properties": {
    "iso:country":"BE",
    "sg:address":"Stationsstraat 31",
    "sg:city":"Geel",
    "sg:classifiers":[
        {
            "category":"Shopping",
            "subcategory":"Antiques",
            "type":"Retail Goods"
        }
    ],
    "sg:phone":"+32 14 59 04 52",
    "sg:postcode":"2440",
    "sg:province":"Antwerpen",
    "wof:name":"Geels Restauratie Atelier",
    "wof:placetype":"venue"
},
  "geometry": {"coordinates":[4.990380764,51.1638031006],"type":"Point"}
}