{
  "type": "Feature",
  "properties": {
    "addr:full":"Belv\u00c9d\u00c8reweg 249 Gent Oost-Vlaanderen 9000",
    "addr:housenumber":"249",
    "addr:postcode":"9000",
    "addr:street":"Belve\u0301De\u0300Reweg;Oost-Vlaanderen",
    "iso:country":"BE",
    "sg:address":"Belv\u00c9d\u00c8reweg 249",
    "sg:city":"Gent",
    "sg:orig_category":"Afval and schroot Gh",
    "sg:phone":"+32 9 220 74 72",
    "sg:postcode":"9000",
    "sg:province":"Oost-Vlaanderen",
    "wof:name":"Johan Mettepenningen",
    "wof:placetype":"venue"
},
  "geometry": {"coordinates":[3.6954009533,51.0470504761],"type":"Point"}
}