{
  "type": "Feature",
  "properties": {
    "addr:full":"Grote Markt 16 Blankenberge West-Vlaanderen 8370",
    "addr:housenumber":"16",
    "addr:postcode":"8370",
    "addr:street":"Grote Markt",
    "iso:country":"BE",
    "sg:address":"Grote Markt 16",
    "sg:city":"Blankenberge",
    "sg:orig_category":"Rusthuizen and serviceflats",
    "sg:phone":"+32 50 41 82 64",
    "sg:postcode":"8370",
    "sg:province":"West-Vlaanderen",
    "wof:name":"Residentie Grasduinen",
    "wof:placetype":"venue"
},
  "geometry": {"coordinates":[3.1253700256,51.3134689331],"type":"Point"}
}