{
  "type": "Feature",
  "properties": {
    "iso:country":"BE",
    "sg:address":"Taxanderlei 14",
    "sg:city":"Schoten",
    "sg:classifiers":[
        {
            "category":"Home & Garden",
            "subcategory":"Home Furnishings",
            "type":"Retail Goods"
        }
    ],
    "sg:phone":"+32 3 680 28 20",
    "sg:postcode":"2900",
    "sg:province":"Antwerpen",
    "sg:tags":[
        "decoration"
    ],
    "wof:name":"U.t.p. International Nv",
    "wof:placetype":"venue"
},
  "geometry": {"coordinates":[4.5169429779,51.2521743774],"type":"Point"}
}