{
  "type": "Feature",
  "properties": {
    "iso:country":"BE",
    "sg:address":"Maalse Steenweg 113",
    "sg:city":"Brugge (sint-kruis)",
    "sg:classifiers":[
        {
            "category":"Food & Beverages",
            "subcategory":"Fruits & Vegetables",
            "type":"Retail Goods"
        }
    ],
    "sg:phone":"+32 50 35 67 54",
    "sg:postcode":"8310",
    "sg:province":"West-Vlaanderen",
    "sg:tags":[
        "-"
    ],
    "wof:name":"Lampaert J",
    "wof:placetype":"venue"
},
  "geometry": {"coordinates":[3.2474040985,51.2101821899],"type":"Point"}
}