{
  "type": "Feature",
  "properties": {
    "addr:full":"Van Den Heckestraat 71 Gent (ledeberg) Oost-Vlaanderen 9050",
    "addr:housenumber":"71",
    "addr:postcode":"9050",
    "addr:street":"Van Den Heckestraat",
    "iso:country":"BE",
    "sg:address":"Van Den Heckestraat 71",
    "sg:city":"Gent (ledeberg)",
    "sg:classifiers":[
        {
            "category":"Autos & Motor Vehicles",
            "subcategory":"Automobile Sales",
            "type":"Retail Goods"
        }
    ],
    "sg:phone":"+32 9 330 35 78",
    "sg:postcode":"9050",
    "sg:province":"Oost-Vlaanderen",
    "sg:tags":[
        "car",
        "used",
        "-"
    ],
    "wof:name":"Dc Car Service Center",
    "wof:placetype":"venue"
},
  "geometry": {"coordinates":[3.7456820011,51.0358085632],"type":"Point"}
}