{
  "type": "Feature",
  "properties": {
    "addr:full":"Breeweg 4 Brugge West-Vlaanderen 8310",
    "addr:housenumber":"4",
    "addr:postcode":"8310",
    "addr:street":"Breeweg",
    "iso:country":"BE",
    "sg:address":"Breeweg 4",
    "sg:city":"Brugge",
    "sg:classifiers":[
        {
            "category":"Building & Trades",
            "subcategory":"Equipment Rental",
            "type":"Services"
        }
    ],
    "sg:phone":"+32 50 36 09 54",
    "sg:postcode":"8310",
    "sg:province":"West-Vlaanderen",
    "sg:tags":[
        "de",
        "\u00e9v\u00e9nements",
        "pour",
        "mat\u00e9riel",
        "location",
        "banquet"
    ],
    "wof:name":"Adhara",
    "wof:placetype":"venue"
},
  "geometry": {"coordinates":[3.2796599865,51.2128486633],"type":"Point"}
}