{
  "type": "Feature",
  "properties": {
    "iso:country":"BE",
    "sg:address":"Place Xavier Neujean 13bd",
    "sg:city":"Li\u00c8ge",
    "sg:orig_category":"Apotheken",
    "sg:phone":"+32 4 223 28 16",
    "sg:postcode":"4000",
    "sg:province":"Li\u00e8ge",
    "wof:name":"Pharm. Bayard A.m. & M.h.",
    "wof:placetype":"venue"
},
  "geometry": {"coordinates":[5.5681228638,50.6430702209],"type":"Point"}
}