{
  "type": "Feature",
  "properties": {
    "addr:full":"Boterhoek 23 Sint-katelijne-waver (onze-lieve-vrouw-waver) Antwerpen 2861",
    "addr:housenumber":"23",
    "addr:postcode":"2861",
    "addr:street":"Boterhoek",
    "iso:country":"BE",
    "sg:address":"Boterhoek 23",
    "sg:city":"Sint-katelijne-waver (onze-lieve-vrouw-waver)",
    "sg:classifiers":[
        {
            "category":"Farming",
            "subcategory":"Nursery",
            "type":"Manufacturing & Wholesale Goods"
        }
    ],
    "sg:phone":"+32 15 76 07 60",
    "sg:postcode":"2861",
    "sg:province":"Antwerpen",
    "sg:tags":[
        "horticultural",
        "automation"
    ],
    "wof:name":"Heylen R",
    "wof:placetype":"venue"
},
  "geometry": {"coordinates":[4.5921797752,51.0756759644],"type":"Point"}
}