{
  "type": "Feature",
  "properties": {
    "iso:country":"BE",
    "sg:address":"Klein Rootstraat 12",
    "sg:city":"Maaseik (neeroeteren)",
    "sg:classifiers":[
        {
            "category":"Home & Garden",
            "subcategory":"Building Materials",
            "type":"Retail Goods"
        }
    ],
    "sg:phone":"+32 89 62 32 00",
    "sg:postcode":"3680",
    "sg:province":"Limburg",
    "sg:tags":[
        "aluminium",
        "construction",
        "-"
    ],
    "wof:name":"Alugeveltechniek Technic & Service Bvba",
    "wof:placetype":"venue"
},
  "geometry": {"coordinates":[5.7066459656,51.0956306458],"type":"Point"}
}