{
  "type": "Feature",
  "properties": {
    "iso:country":"BE",
    "sg:address":"Venneheideweg 12a",
    "sg:city":"Aarschot",
    "sg:orig_category":"Informaticaconsulenten",
    "sg:phone":"+32 16 57 08 20",
    "sg:postcode":"3201",
    "sg:province":"Vlaams-Brabant",
    "wof:name":"K En R Medical Systems",
    "wof:placetype":"venue"
},
  "geometry": {"coordinates":[4.8662080765,51.0108947754],"type":"Point"}
}