{
  "type": "Feature",
  "properties": {
    "addr:full":"Heidestatiestraat 22b6 Kalmthout Antwerpen 2920",
    "addr:housenumber":"22b6",
    "addr:postcode":"2920",
    "addr:street":"Heidestatiestraat",
    "iso:country":"BE",
    "sg:address":"Heidestatiestraat 22b6",
    "sg:city":"Kalmthout",
    "sg:classifiers":[
        {
            "category":"Insurance",
            "subcategory":"Life Insurance",
            "type":"Services"
        }
    ],
    "sg:phone":"+32 3 666 84 81",
    "sg:postcode":"2920",
    "sg:province":"Antwerpen",
    "sg:tags":[
        "assurance"
    ],
    "wof:name":"Verzekeringen Kalmthout",
    "wof:placetype":"venue"
},
  "geometry": {"coordinates":[4.4643411636,51.365688324],"type":"Point"}
}