{
  "type": "Feature",
  "properties": {
    "iso:country":"BE",
    "sg:address":"Leopoldstraat 34-4",
    "sg:city":"Zwevegem",
    "sg:classifiers":[
        {
            "category":"Professional",
            "subcategory":"Lawyer & Legal Services",
            "type":"Services"
        }
    ],
    "sg:phone":"+32 56 75 68 88",
    "sg:postcode":"8550",
    "sg:province":"West-Vlaanderen",
    "wof:name":"Van Welden Claude",
    "wof:placetype":"venue"
},
  "geometry": {"coordinates":[3.3359839916,50.8114013672],"type":"Point"}
}