{
  "type": "Feature",
  "properties": {
    "iso:country":"BE",
    "sg:address":"Bovenberg 120ba",
    "sg:city":"Sint-pieters-woluwe/woluwe-saint-pierre",
    "sg:orig_category":"Artistes ind\u00e9pendants",
    "sg:phone":"+32 2 772 35 87",
    "sg:postcode":"1150",
    "sg:province":"Bruxelles-Capitale",
    "wof:name":"Larissa Ickx",
    "wof:placetype":"venue"
},
  "geometry": {"coordinates":[4.4334211349,50.8329429626],"type":"Point"}
}