{
  "type": "Feature",
  "properties": {
    "addr:full":"Chauss\u00c9e De Houffalize 3 Bastogne Luxembourg 6600",
    "addr:housenumber":"3",
    "addr:postcode":"6600",
    "addr:street":"Chausse\u0301E De Houffalize",
    "iso:country":"BE",
    "sg:address":"Chauss\u00c9e De Houffalize 3",
    "sg:city":"Bastogne",
    "sg:orig_category":"Kinderopvang",
    "sg:phone":"+32 61 21 31 14",
    "sg:postcode":"6600",
    "sg:province":"Luxembourg",
    "wof:name":"Ile Aux Bambins",
    "wof:placetype":"venue"
},
  "geometry": {"coordinates":[5.7235889435,50.0132637024],"type":"Point"}
}