{
  "type": "Feature",
  "properties": {
    "iso:country":"BE",
    "sg:address":"Heuvelstraat 33",
    "sg:city":"Hemiksem",
    "sg:orig_category":"Pain, p\u00e2tisseries and confiseries",
    "sg:phone":"+32 3 887 44 09",
    "sg:postcode":"2620",
    "sg:province":"Antwerpen",
    "wof:name":"Roger Van Loock",
    "wof:placetype":"venue"
},
  "geometry": {"coordinates":[4.3373880386,51.1398620605],"type":"Point"}
}