{
  "type": "Feature",
  "properties": {
    "iso:country":"BE",
    "sg:address":"Achterstraat 10",
    "sg:city":"Stekene",
    "sg:orig_category":"Eleveurs de bovins",
    "sg:phone":"+32 3 779 76 88",
    "sg:postcode":"9190",
    "sg:province":"Oost-Vlaanderen",
    "wof:name":"Paul Martens",
    "wof:placetype":"venue"
},
  "geometry": {"coordinates":[4.0011777878,51.1906547546],"type":"Point"}
}