{
  "type": "Feature",
  "properties": {
    "addr:full":"Markt 126b1 Deinze Oost-Vlaanderen 9800",
    "addr:housenumber":"126b1",
    "addr:postcode":"9800",
    "addr:street":"Markt",
    "iso:country":"BE",
    "sg:address":"Markt 126b1",
    "sg:city":"Deinze",
    "sg:orig_category":"Opticiens",
    "sg:phone":"+32 9 380 09 03",
    "sg:postcode":"9800",
    "sg:province":"Oost-Vlaanderen",
    "wof:name":"Optiek Tavernier",
    "wof:placetype":"venue"
},
  "geometry": {"coordinates":[3.5240609646,50.9867515564],"type":"Point"}
}