{
  "type": "Feature",
  "properties": {
    "addr:full":"Rue D'italie 81 Ans Li\u00e8ge 4430",
    "addr:housenumber":"81",
    "addr:postcode":"4430",
    "addr:street":"Rue D'Italie",
    "iso:country":"BE",
    "sg:address":"Rue D'italie 81",
    "sg:city":"Ans",
    "sg:orig_category":"Instituts de beaut\u00e9",
    "sg:phone":"+32 4 263 33 93",
    "sg:postcode":"4430",
    "sg:province":"Li\u00e8ge",
    "wof:name":"Josiane Geurts",
    "wof:placetype":"venue"
},
  "geometry": {"coordinates":[5.5259490013,50.6525764465],"type":"Point"}
}