{
  "type": "Feature",
  "properties": {
    "iso:country":"BE",
    "sg:address":"Halstraat 111",
    "sg:city":"Heusden-zolder",
    "sg:orig_category":"Installatie van houten of kunststof schrijnwerk MEUBELONTWERP AND -INSTALLATIE",
    "sg:phone":"+32 11 57 31 69",
    "sg:postcode":"3550",
    "sg:province":"Limburg",
    "wof:name":"Vangrieken Gebrs",
    "wof:placetype":"venue"
},
  "geometry": {"coordinates":[5.3122901917,51.0500793457],"type":"Point"}
}