{
  "type": "Feature",
  "properties": {
    "iso:country":"BE",
    "sg:address":"Smalle Heerweg 52",
    "sg:city":"Lochristi",
    "sg:orig_category":"Begrafeniswezen",
    "sg:phone":"+32 9 355 51 78",
    "sg:postcode":"9080",
    "sg:province":"Oost-Vlaanderen",
    "wof:name":"Crematorium Van Gent",
    "wof:placetype":"venue"
},
  "geometry": {"coordinates":[3.8133320808,51.0933456421],"type":"Point"}
}