{
  "type": "Feature",
  "properties": {
    "iso:country":"BE",
    "sg:address":"Weststraat 104",
    "sg:city":"Waarschoot",
    "sg:classifiers":[
        {
            "category":"Home & Garden",
            "subcategory":"Hardware",
            "type":"Retail Goods"
        }
    ],
    "sg:phone":"+32 9 377 60 75",
    "sg:postcode":"9950",
    "sg:province":"Oost-Vlaanderen",
    "sg:tags":[
        "battery",
        "dry"
    ],
    "wof:name":"App",
    "wof:placetype":"venue"
},
  "geometry": {"coordinates":[3.588504076,51.1529273987],"type":"Point"}
}