{
  "type": "Feature",
  "properties": {
    "iso:country":"BE",
    "sg:address":"Rue De La Gohiette 20",
    "sg:city":"Fernelmont",
    "sg:classifiers":[
        {
            "category":"Arena",
            "subcategory":"Sports Club",
            "type":"Entertainment"
        }
    ],
    "sg:phone":"+32 81 85 56 04",
    "sg:postcode":"5380",
    "sg:province":"Namur",
    "sg:tags":[
        "terrain",
        "hors",
        "de",
        "installation",
        "sportifs"
    ],
    "wof:name":"J.s. Anseremmoise",
    "wof:placetype":"venue"
},
  "geometry": {"coordinates":[4.9861078262,50.5531463623],"type":"Point"}
}