{
  "type": "Feature",
  "properties": {
    "addr:full":"Heuvellaan 10ba Dilbeek Vlaams-Brabant 1700",
    "addr:housenumber":"10ba",
    "addr:postcode":"1700",
    "addr:street":"Heuvellaan",
    "iso:country":"BE",
    "sg:address":"Heuvellaan 10ba",
    "sg:city":"Dilbeek",
    "sg:orig_category":"Dranken Gh",
    "sg:phone":"+32 2 569 05 19",
    "sg:postcode":"1700",
    "sg:province":"Vlaams-Brabant",
    "wof:name":"Bierhandel Schoentjes",
    "wof:placetype":"venue"
},
  "geometry": {"coordinates":[4.2582111359,50.8420562744],"type":"Point"}
}