{
  "type": "Feature",
  "properties": {
    "addr:full":"Rue Vall\u00e9e 20 Fl\u00e9ron (roms\u00e9e) Li\u00e8ge 4624",
    "addr:housenumber":"20",
    "addr:postcode":"4624",
    "addr:street":"Rue Valle\u0301E",
    "iso:country":"BE",
    "sg:address":"Rue Vall\u00e9e 20",
    "sg:city":"Fl\u00e9ron (roms\u00e9e)",
    "sg:classifiers":[
        {
            "category":"Wholesale",
            "subcategory":"Medical Equipment & Supplies",
            "type":"Manufacturing & Wholesale Goods"
        }
    ],
    "sg:phone":"+32 4 355 11 45",
    "sg:postcode":"4624",
    "sg:province":"Li\u00e8ge",
    "sg:tags":[
        "instrument",
        "apparatus"
    ],
    "wof:name":"A J M",
    "wof:placetype":"venue"
},
  "geometry": {"coordinates":[5.6583900452,50.6063995361],"type":"Point"}
}