{
  "type": "Feature",
  "properties": {
    "addr:full":"Chemin Du Raideu 16 Malmedy (beverc\u00e9) Li\u00e8ge 4960",
    "addr:housenumber":"16",
    "addr:postcode":"4960",
    "addr:street":"Chemin Du Raideu",
    "iso:country":"BE",
    "sg:address":"Chemin Du Raideu 16",
    "sg:city":"Malmedy (beverc\u00e9)",
    "sg:classifiers":[
        {
            "category":"Real Estate",
            "subcategory":"Architect",
            "type":"Services"
        }
    ],
    "sg:phone":"+32 80 77 09 46",
    "sg:postcode":"4960",
    "sg:province":"Li\u00e8ge",
    "wof:name":"Nelles L",
    "wof:placetype":"venue"
},
  "geometry": {"coordinates":[6.068292141,50.452331543],"type":"Point"}
}