{
  "type": "Feature",
  "properties": {
    "iso:country":"BE",
    "sg:address":"Route De Macquenoise 5",
    "sg:city":"Momignies",
    "sg:orig_category":"Fietsen Motorfietsen Watersport-, Sport- and Kampeerbenodigdheden Verhuur",
    "sg:phone":"+32 60 51 14 08",
    "sg:postcode":"6596",
    "sg:province":"Hainaut",
    "wof:name":"Leon Guillain",
    "wof:placetype":"venue"
},
  "geometry": {"coordinates":[4.2524051666,50.0097198486],"type":"Point"}
}