{
  "type": "Feature",
  "properties": {
    "iso:country":"BE",
    "sg:address":"Rueselarestr 305",
    "sg:city":"Wevelgem",
    "sg:orig_category":"Rev\u00eatements de sols and murs",
    "sg:phone":"+32 56 41 60 65",
    "sg:postcode":"8560",
    "sg:province":"West-Vlaanderen",
    "wof:name":"Vanackere",
    "wof:placetype":"venue"
},
  "geometry": {"coordinates":[3.1768701077,50.8198318481],"type":"Point"}
}