{
  "type": "Feature",
  "properties": {
    "addr:full":"Kerkstraat 22 Neerpelt Limburg 3910",
    "addr:housenumber":"22",
    "addr:postcode":"3910",
    "addr:street":"Kerkstraat",
    "iso:country":"BE",
    "sg:address":"Kerkstraat 22",
    "sg:city":"Neerpelt",
    "sg:orig_category":"Mat\u00e9riel de T\u00e9l\u00e9communication",
    "sg:phone":"+32 800 22 800",
    "sg:postcode":"3910",
    "sg:province":"Limburg",
    "wof:name":"Teleboetiek",
    "wof:placetype":"venue"
},
  "geometry": {"coordinates":[5.43247509,51.2287445068],"type":"Point"}
}