{
  "type": "Feature",
  "properties": {
    "iso:country":"BE",
    "sg:address":"Harelbeekstraat 176",
    "sg:city":"Zwevegem",
    "sg:orig_category":"V\u00e9hicules automobiles. Entretien and r\u00e9parations de voitures",
    "sg:phone":"+32 56 75 43 09",
    "sg:postcode":"8550",
    "sg:province":"West-Vlaanderen",
    "wof:name":"Garage Deconinck",
    "wof:placetype":"venue"
},
  "geometry": {"coordinates":[3.3253130913,50.8216819763],"type":"Point"}
}