{
  "type": "Feature",
  "properties": {
    "addr:full":"Karabiniersstraat 14 Ieper (zuidschote) West-Vlaanderen 8904",
    "addr:housenumber":"14",
    "addr:postcode":"8904",
    "addr:street":"Karabiniersstraat",
    "iso:country":"BE",
    "sg:address":"Karabiniersstraat 14",
    "sg:city":"Ieper (zuidschote)",
    "sg:classifiers":[
        {
            "category":"Farming",
            "subcategory":"Livestock Farm",
            "type":"Manufacturing & Wholesale Goods"
        }
    ],
    "sg:phone":"+32 57 42 21 08",
    "sg:postcode":"8904",
    "sg:province":"West-Vlaanderen",
    "sg:tags":[
        "poultry",
        "rabbit"
    ],
    "wof:name":"Arteel M",
    "wof:placetype":"venue"
},
  "geometry": {"coordinates":[2.8297879696,50.9210929871],"type":"Point"}
}