{
  "type": "Feature",
  "properties": {
    "addr:full":"Rue Du Progr\u00e8s 57 Bi\u00e8vre (graide) Namur 5555",
    "addr:housenumber":"57",
    "addr:postcode":"5555",
    "addr:street":"Rue Du Progre\u0300S",
    "iso:country":"BE",
    "sg:address":"Rue Du Progr\u00e8s 57",
    "sg:city":"Bi\u00e8vre (graide)",
    "sg:classifiers":[
        {
            "category":"Shopping",
            "subcategory":"Clothing, Apparel, & Fashions",
            "type":"Retail Goods"
        }
    ],
    "sg:phone":"+32 61 51 10 21",
    "sg:postcode":"5555",
    "sg:province":"Namur",
    "sg:tags":[
        "boutique"
    ],
    "wof:name":"Evy Couture",
    "wof:placetype":"venue"
},
  "geometry": {"coordinates":[5.049120903,49.9381523132],"type":"Point"}
}