{
  "type": "Feature",
  "properties": {
    "iso:country":"BE",
    "sg:address":"Rue Colonel Balaince 6",
    "sg:city":"Saint-ghislain",
    "sg:orig_category":"M\u00e9decins and sp\u00e9cialistes",
    "sg:phone":"+32 65 62 21 47",
    "sg:postcode":"7332",
    "sg:province":"Hainaut",
    "wof:name":"G. Verteneuil",
    "wof:placetype":"venue"
},
  "geometry": {"coordinates":[3.786839962,50.5054969788],"type":"Point"}
}