{
  "type": "Feature",
  "properties": {
    "iso:country":"BE",
    "sg:address":"Kardinaal Cardijnstraat 7",
    "sg:city":"Halle",
    "sg:orig_category":"Mus\u00e9es and patrimoine culturel",
    "sg:phone":"+32 2 361 31 56",
    "sg:postcode":"1500",
    "sg:province":"Vlaams-Brabant",
    "wof:name":"Zuidwest-brabants Museum",
    "wof:placetype":"venue"
},
  "geometry": {"coordinates":[4.2375259399,50.7365341187],"type":"Point"}
}