{
  "type": "Feature",
  "properties": {
    "addr:full":"Place De L'universit\u00c9 25 Ottignies-louvain-la-neuve Brabant Wallon 1348",
    "addr:housenumber":"25",
    "addr:postcode":"1348",
    "addr:street":"Place De L'Universite \u0301",
    "iso:country":"BE",
    "sg:address":"Place De L'universit\u00c9 25",
    "sg:city":"Ottignies-louvain-la-neuve",
    "sg:orig_category":"Overheidsdiensten",
    "sg:phone":"+32 10 45 62 51",
    "sg:postcode":"1348",
    "sg:province":"Brabant Wallon",
    "wof:name":"Admin. Contrib. Directes",
    "wof:placetype":"venue"
},
  "geometry": {"coordinates":[4.6155920029,50.6702461243],"type":"Point"}
}