{
  "type": "Feature",
  "properties": {
    "addr:full":"Groenestraat 37 Kortemark West-Vlaanderen 8610",
    "addr:housenumber":"37",
    "addr:postcode":"8610",
    "addr:street":"Groenestraat",
    "iso:country":"BE",
    "sg:address":"Groenestraat 37",
    "sg:city":"Kortemark",
    "sg:orig_category":"Rundveehouders",
    "sg:phone":"+32 51 56 66 22",
    "sg:postcode":"8610",
    "sg:province":"West-Vlaanderen",
    "wof:name":"Karel Boone",
    "wof:placetype":"venue"
},
  "geometry": {"coordinates":[3.0203509331,51.0032920837],"type":"Point"}
}