{
  "type": "Feature",
  "properties": {
    "iso:country":"BE",
    "sg:address":"Euster 26",
    "sg:city":"Duffel",
    "sg:orig_category":"Eleveurs de bovins",
    "sg:phone":"+32 3 488 12 65",
    "sg:postcode":"2570",
    "sg:province":"Antwerpen",
    "wof:name":"Herman Ceulemans",
    "wof:placetype":"venue"
},
  "geometry": {"coordinates":[4.5583958626,51.1065940857],"type":"Point"}
}