{
  "type": "Feature",
  "properties": {
    "addr:full":"Rue De Namur 85 Nivelles Brabant Wallon 1400",
    "addr:housenumber":"85",
    "addr:postcode":"1400",
    "addr:street":"Rue De Namur",
    "iso:country":"BE",
    "sg:address":"Rue De Namur 85",
    "sg:city":"Nivelles",
    "sg:orig_category":"Journaux. Tabac",
    "sg:phone":"+32 67 21 52 67",
    "sg:postcode":"1400",
    "sg:province":"Brabant Wallon",
    "wof:name":"Librairie Leduc",
    "wof:placetype":"venue"
},
  "geometry": {"coordinates":[4.3284621239,50.599445343],"type":"Point"}
}