{
  "type": "Feature",
  "properties": {
    "addr:full":"Markt 57 Zele Oost-Vlaanderen 9240",
    "addr:housenumber":"57",
    "addr:postcode":"9240",
    "addr:street":"Markt",
    "iso:country":"BE",
    "sg:address":"Markt 57",
    "sg:city":"Zele",
    "sg:classifiers":[
        {
            "category":"Shopping",
            "subcategory":"Luggage & Leather Goods",
            "type":"Retail Goods"
        }
    ],
    "sg:phone":"+32 52 52 09 80",
    "sg:postcode":"9240",
    "sg:province":"Oost-Vlaanderen",
    "sg:tags":[
        "-"
    ],
    "wof:name":"Aura",
    "wof:placetype":"venue"
},
  "geometry": {"coordinates":[4.037776947,51.0686302185],"type":"Point"}
}