{
  "type": "Feature",
  "properties": {
    "iso:country":"BE",
    "sg:address":"Koning Leopold Iii-laan 10",
    "sg:city":"Brugge (sint-andries)",
    "sg:classifiers":[
        {
            "category":"Health Services",
            "subcategory":"Dentist",
            "type":"Services"
        }
    ],
    "sg:phone":"+32 50 38 77 62",
    "sg:postcode":"8200",
    "sg:province":"West-Vlaanderen",
    "wof:name":"Jouret P",
    "wof:placetype":"venue"
},
  "geometry": {"coordinates":[3.2056040764,51.2055244446],"type":"Point"}
}