{
  "type": "Feature",
  "properties": {
    "addr:full":"Stoktmolenstraat 32 Box 3 Tielt West-Vlaanderen 8700",
    "addr:housenumber":"32;3",
    "addr:postcode":"8700",
    "addr:street":"Stoktmolenstraat;Box",
    "iso:country":"BE",
    "sg:address":"Stoktmolenstraat 32 Box 3",
    "sg:city":"Tielt",
    "sg:classifiers":[
        {
            "category":"Communications",
            "type":"Services"
        }
    ],
    "sg:phone":"+32 51 40 18 38",
    "sg:postcode":"8700",
    "sg:province":"West-Vlaanderen",
    "sg:tags":[
        "translator"
    ],
    "wof:name":"De Gryse Philippe",
    "wof:placetype":"venue"
},
  "geometry": {"coordinates":[3.3291840553,50.9941139221],"type":"Point"}
}