{
  "type": "Feature",
  "properties": {
    "iso:country":"BE",
    "sg:address":"Dorp 65",
    "sg:city":"Lommel",
    "sg:classifiers":[
        {
            "category":"Bars & Pubs",
            "type":"Food & Drink"
        }
    ],
    "sg:phone":"+32 11 55 34 86",
    "sg:postcode":"3920",
    "sg:province":"Limburg",
    "sg:tags":[
        "bars",
        "caf\u00e9s"
    ],
    "wof:name":"Caf\u00c9 The Screen",
    "wof:placetype":"venue"
},
  "geometry": {"coordinates":[5.3067698479,51.2311782837],"type":"Point"}
}