{
  "type": "Feature",
  "properties": {
    "iso:country":"BE",
    "sg:address":"De Haveskerckelaan 14",
    "sg:city":"Vorst/forest",
    "sg:orig_category":"Artsen and specialisten",
    "sg:phone":"+32 2 376 25 60",
    "sg:postcode":"1190",
    "sg:province":"Bruxelles-Capitale",
    "wof:name":"Benoit Claessens",
    "wof:placetype":"venue"
},
  "geometry": {"coordinates":[4.3235750198,50.8055686951],"type":"Point"}
}