{
  "type": "Feature",
  "properties": {
    "addr:full":"Chauss\u00e9e De Mons 427 Bruxelles (anderlecht) Bruxelles-Capitale 1070",
    "addr:housenumber":"427",
    "addr:postcode":"1070",
    "addr:street":"Chausse\u0301E De Mons",
    "iso:country":"BE",
    "sg:address":"Chauss\u00e9e De Mons 427",
    "sg:city":"Bruxelles (anderlecht)",
    "sg:orig_category":"Fiduciairies",
    "sg:phone":"+32 2 520 09 20",
    "sg:postcode":"1070",
    "sg:province":"Bruxelles-Capitale",
    "wof:name":"A.c.c.a.",
    "wof:placetype":"venue"
},
  "geometry": {"coordinates":[4.3192439079,50.8377571106],"type":"Point"}
}