{
  "type": "Feature",
  "properties": {
    "iso:country":"BE",
    "sg:address":"Blankenbergsedijk 90",
    "sg:city":"Brugge",
    "sg:orig_category":"Varkenskwekers",
    "sg:phone":"+32 50 31 36 39",
    "sg:postcode":"8000",
    "sg:province":"West-Vlaanderen",
    "wof:name":"Georges Mortier",
    "wof:placetype":"venue"
},
  "geometry": {"coordinates":[3.2002699375,51.2329025269],"type":"Point"}
}