{
  "type": "Feature",
  "properties": {
    "addr:full":"Geraardsbergse Steenweg 92 Oosterzele Oost-Vlaanderen 9860",
    "addr:housenumber":"92",
    "addr:postcode":"9860",
    "addr:street":"Steenweg;Oost-Vlaanderen",
    "iso:country":"BE",
    "sg:address":"Geraardsbergse Steenweg 92",
    "sg:city":"Oosterzele",
    "sg:classifiers":[
        {
            "category":"Professional",
            "subcategory":"Accounting & Tax Preparation",
            "type":"Services"
        }
    ],
    "sg:phone":"+32 9 362 01 83",
    "sg:postcode":"9860",
    "sg:province":"Oost-Vlaanderen",
    "sg:tags":[
        "bookkeeper"
    ],
    "wof:name":"Van De Vijver A",
    "wof:placetype":"venue"
},
  "geometry": {"coordinates":[3.8102519512,50.9528579712],"type":"Point"}
}