{
  "type": "Feature",
  "properties": {
    "iso:country":"BE",
    "sg:address":"Oostlaan 53",
    "sg:city":"Genk",
    "sg:classifiers":[
        {
            "category":"Education",
            "subcategory":"School",
            "type":"Public Place"
        }
    ],
    "sg:phone":"+32 89 30 89 60",
    "sg:postcode":"3600",
    "sg:province":"Limburg",
    "sg:tags":[
        "-",
        "private"
    ],
    "wof:name":"E.r. Com. Europe Bvba",
    "wof:placetype":"venue"
},
  "geometry": {"coordinates":[5.4847102165,50.9712905884],"type":"Point"}
}