{
  "type": "Feature",
  "properties": {
    "addr:full":"R De L'eglise 26 Brussel Bruxelles-Capitale 1082",
    "addr:housenumber":"26",
    "addr:postcode":"1082",
    "addr:street":"Brussel",
    "iso:country":"BE",
    "sg:address":"R De L'eglise 26",
    "sg:city":"Brussel",
    "sg:classifiers":[
        {
            "category":"Health Services",
            "subcategory":"Medical Lab",
            "type":"Services"
        }
    ],
    "sg:phone":"+32 2 465 53 50",
    "sg:postcode":"1082",
    "sg:province":"Bruxelles-Capitale",
    "sg:tags":[
        "chemical",
        "pharmaceutical",
        "pharmacy"
    ],
    "wof:name":"Apotheek Vanschelvergem Sprl",
    "wof:placetype":"venue"
},
  "geometry": {"coordinates":[4.2968797684,50.8651618958],"type":"Point"}
}