{
  "type": "Feature",
  "properties": {
    "addr:full":"Villerslei 103 Schoten Antwerpen 2900",
    "addr:housenumber":"103",
    "addr:postcode":"2900",
    "addr:street":"Villerslei",
    "iso:country":"BE",
    "sg:address":"Villerslei 103",
    "sg:city":"Schoten",
    "sg:orig_category":"M\u00e9decins and sp\u00e9cialistes",
    "sg:phone":"+32 3 658 54 38",
    "sg:postcode":"2900",
    "sg:province":"Antwerpen",
    "wof:name":"Louis Janssens",
    "wof:placetype":"venue"
},
  "geometry": {"coordinates":[4.51329422,51.2522506714],"type":"Point"}
}