{
  "type": "Feature",
  "properties": {
    "addr:full":"Rue Du Vivier 17 La Louviere Hainaut 7110",
    "addr:housenumber":"17",
    "addr:postcode":"7110",
    "addr:street":"Rue Du Vivier",
    "iso:country":"BE",
    "sg:address":"Rue Du Vivier 17",
    "sg:city":"La Louviere",
    "sg:orig_category":"Woningbouw",
    "sg:phone":"+32 64 26 68 01",
    "sg:postcode":"7110",
    "sg:province":"Hainaut",
    "wof:name":"Annalisa",
    "wof:placetype":"venue"
},
  "geometry": {"coordinates":[4.1505050659,50.4826698303],"type":"Point"}
}