{
  "type": "Feature",
  "properties": {
    "iso:country":"BE",
    "sg:address":"Rue Saint-martin 56",
    "sg:city":"Leuze-en-hainaut",
    "sg:orig_category":"Location d'appareils audio-visuels",
    "sg:phone":"+32 69 66 31 30",
    "sg:postcode":"7900",
    "sg:province":"Hainaut",
    "wof:name":"Fe. Light Matic",
    "wof:placetype":"venue"
},
  "geometry": {"coordinates":[3.6261160374,50.5972480774],"type":"Point"}
}