{
  "type": "Feature",
  "properties": {
    "addr:full":"Beilen 11 Olen Antwerpen 2250",
    "addr:housenumber":"11",
    "addr:postcode":"2250",
    "addr:street":"Beilen",
    "iso:country":"BE",
    "sg:address":"Beilen 11",
    "sg:city":"Olen",
    "sg:orig_category":"Banken and kredietinstellingen",
    "sg:phone":"+32 14 21 29 49",
    "sg:postcode":"2250",
    "sg:province":"Antwerpen",
    "wof:name":"Kbc",
    "wof:placetype":"venue"
},
  "geometry": {"coordinates":[4.8984718323,51.1673240662],"type":"Point"}
}