{
  "type": "Feature",
  "properties": {
    "addr:full":"Karel Van Manderstraat 206 Brugge (sint-kruis) West-Vlaanderen 8310",
    "addr:housenumber":"206",
    "addr:postcode":"8310",
    "addr:street":"Karel Van Manderstraat",
    "iso:country":"BE",
    "sg:address":"Karel Van Manderstraat 206",
    "sg:city":"Brugge (sint-kruis)",
    "sg:classifiers":[
        {
            "category":"Farming",
            "subcategory":"Berry Farm",
            "type":"Manufacturing & Wholesale Goods"
        }
    ],
    "sg:phone":"+32 50 31 51 61",
    "sg:postcode":"8310",
    "sg:province":"West-Vlaanderen",
    "sg:tags":[
        "horticulture",
        "-",
        "broker",
        "whol",
        "seed",
        "grain",
        "agriculture"
    ],
    "wof:name":"Maisadour Belgium",
    "wof:placetype":"venue"
},
  "geometry": {"coordinates":[3.241134882,51.2234802246],"type":"Point"}
}