{
  "type": "Feature",
  "properties": {
    "addr:full":"Rue De L\u00b4eglise 12 Ouffet Li\u00e8ge 4590",
    "addr:housenumber":"12",
    "addr:postcode":"4590",
    "addr:street":"Rue De L\u00b4Eglise",
    "iso:country":"BE",
    "sg:address":"Rue De L\u00b4eglise 12",
    "sg:city":"Ouffet",
    "sg:orig_category":"Sportclubs",
    "sg:phone":"+32 86 36 61 57",
    "sg:postcode":"4590",
    "sg:province":"Li\u00e8ge",
    "wof:name":"V.c. Ouffet",
    "wof:placetype":"venue"
},
  "geometry": {"coordinates":[5.4298529625,50.4506988525],"type":"Point"}
}