{
  "type": "Feature",
  "properties": {
    "addr:full":"Rue De Namur 1a Philippeville Namur 5600",
    "addr:housenumber":"1a",
    "addr:postcode":"5600",
    "addr:street":"Rue De Namur",
    "iso:country":"BE",
    "sg:address":"Rue De Namur 1a",
    "sg:city":"Philippeville",
    "sg:classifiers":[
        {
            "category":"Social Services",
            "type":"Services"
        }
    ],
    "sg:phone":"+32 71 66 64 88",
    "sg:postcode":"5600",
    "sg:province":"Namur",
    "wof:name":"A.l.e.",
    "wof:placetype":"venue"
},
  "geometry": {"coordinates":[4.5441408157,50.1964836121],"type":"Point"}
}