{
  "type": "Feature",
  "properties": {
    "addr:full":"Place Saint-arnould 7 Bouillon Luxembourg 6830",
    "addr:housenumber":"7",
    "addr:postcode":"6830",
    "addr:street":"Place Saint-Arnould",
    "iso:country":"BE",
    "sg:address":"Place Saint-arnould 7",
    "sg:city":"Bouillon",
    "sg:orig_category":"Boucheries",
    "sg:phone":"+32 61 46 60 95",
    "sg:postcode":"6830",
    "sg:province":"Luxembourg",
    "wof:name":"Benoit Hennon",
    "wof:placetype":"venue"
},
  "geometry": {"coordinates":[5.0704917908,49.7945289612],"type":"Point"}
}