{
  "type": "Feature",
  "properties": {
    "addr:full":"Route Des Xhawirs 83 Herve Li\u00e8ge 4652",
    "addr:housenumber":"83",
    "addr:postcode":"4652",
    "addr:street":"Route Des Xhawirs",
    "iso:country":"BE",
    "sg:address":"Route Des Xhawirs 83",
    "sg:city":"Herve",
    "sg:orig_category":"Antiquit\u00e9s",
    "sg:phone":"+32 87 67 87 41",
    "sg:postcode":"4652",
    "sg:province":"Li\u00e8ge",
    "wof:name":"Antiquit\u00c9s Nicolas",
    "wof:placetype":"venue"
},
  "geometry": {"coordinates":[5.7804818153,50.6042518616],"type":"Point"}
}