{
  "type": "Feature",
  "properties": {
    "addr:full":"Rue Edouard Deknoop 71 Box 3 Bruxelles (evere) Bruxelles-Capitale 1140",
    "addr:housenumber":"71;3",
    "addr:postcode":"1140",
    "addr:street":"Rue Edouard Deknoop;Box",
    "iso:country":"BE",
    "sg:address":"Rue Edouard Deknoop 71 Box 3",
    "sg:city":"Bruxelles (evere)",
    "sg:classifiers":[
        {
            "category":"Home & Garden",
            "subcategory":"Home Furnishings",
            "type":"Retail Goods"
        }
    ],
    "sg:phone":"+32 2 215 10 03",
    "sg:postcode":"1140",
    "sg:province":"Bruxelles-Capitale",
    "sg:tags":[
        "-",
        "bed",
        "mattress"
    ],
    "wof:name":"Medilux - Literie Orthopedique",
    "wof:placetype":"venue"
},
  "geometry": {"coordinates":[4.3991532326,50.8721008301],"type":"Point"}
}