{
  "type": "Feature",
  "properties": {
    "iso:country":"BE",
    "sg:address":"Rue Longue 32",
    "sg:city":"Baelen",
    "sg:orig_category":"Diverse bouwinstallaties Elektrische installaties voor woningen Reclamebureaus Verlichtingsapparaten",
    "sg:phone":"+32 87 76 46 74",
    "sg:postcode":"4837",
    "sg:province":"Li\u00e8ge",
    "wof:name":"Bestn\u00c9on",
    "wof:placetype":"venue"
},
  "geometry": {"coordinates":[5.9681539536,50.6300315857],"type":"Point"}
}