{
  "type": "Feature",
  "properties": {
    "addr:full":"Rue Des Ecoles 21 Rixensart Brabant Wallon 1330",
    "addr:housenumber":"21",
    "addr:postcode":"1330",
    "addr:street":"Rue Des Ecoles;Wallon",
    "iso:country":"BE",
    "sg:address":"Rue Des Ecoles 21",
    "sg:city":"Rixensart",
    "sg:orig_category":"Loodgieterij, verwarming and sanitaire installaties",
    "sg:phone":"+32 2 653 81 75",
    "sg:postcode":"1330",
    "sg:province":"Brabant Wallon",
    "wof:name":"Tagnon Entreprise",
    "wof:placetype":"venue"
},
  "geometry": {"coordinates":[4.5332350731,50.7145805359],"type":"Point"}
}