{
  "type": "Feature",
  "properties": {
    "iso:country":"BE",
    "sg:address":"Rue Des Grives 7",
    "sg:city":"Aubange",
    "sg:classifiers":[
        {
            "category":"Autos & Motor Vehicles",
            "subcategory":"Auto Supplies",
            "type":"Retail Goods"
        }
    ],
    "sg:phone":"+32 63 37 08 06",
    "sg:postcode":"6790",
    "sg:province":"Luxembourg",
    "sg:tags":[
        "access",
        "automobile",
        "part",
        "-"
    ],
    "wof:name":"Lorraine 4 X 4 Shop",
    "wof:placetype":"venue"
},
  "geometry": {"coordinates":[5.7954788208,49.5586013794],"type":"Point"}
}