{
  "type": "Feature",
  "properties": {
    "addr:full":"Bredepleinstraat 65 Boortmeerbeek Vlaams-Brabant 3190",
    "addr:housenumber":"65",
    "addr:postcode":"3190",
    "addr:street":"Bredepleinstraat",
    "iso:country":"BE",
    "sg:address":"Bredepleinstraat 65",
    "sg:city":"Boortmeerbeek",
    "sg:classifiers":[
        {
            "category":"Arena",
            "subcategory":"Sports Club",
            "type":"Entertainment"
        }
    ],
    "sg:phone":"+32 15 51 77 54",
    "sg:postcode":"3190",
    "sg:province":"Vlaams-Brabant",
    "sg:tags":[
        "de"
    ],
    "wof:name":"Turnkring Excelsior Haacht",
    "wof:placetype":"venue"
},
  "geometry": {"coordinates":[4.5759320259,50.9741973877],"type":"Point"}
}