{
  "type": "Feature",
  "properties": {
    "iso:country":"BE",
    "sg:address":"Waterloose Steenweg 1210",
    "sg:city":"Ukkel/uccle",
    "sg:orig_category":"Diverse grafische activiteiten",
    "sg:phone":"+32 2 374 42 86",
    "sg:postcode":"1180",
    "sg:province":"Bruxelles-Capitale",
    "wof:name":"Annie Sliwka",
    "wof:placetype":"venue"
},
  "geometry": {"coordinates":[4.3738021851,50.7947883606],"type":"Point"}
}