{
  "type": "Feature",
  "properties": {
    "iso:country":"BE",
    "sg:address":"Rue De La Hestre 164",
    "sg:city":"Chapelle-lez-herlaimont",
    "sg:orig_category":"Antiquit\u00e9s",
    "sg:phone":"+32 64 44 62 31",
    "sg:postcode":"7160",
    "sg:province":"Hainaut",
    "wof:name":"Int\u00c9rieur D\u00b4antan",
    "wof:placetype":"venue"
},
  "geometry": {"coordinates":[4.2695631981,50.4680366516],"type":"Point"}
}