{
  "type": "Feature",
  "properties": {
    "addr:full":"Ninoofsesteenweg 230 B1 Dilbeek Vlaams-Brabant 1700",
    "addr:housenumber":"230 b1",
    "addr:postcode":"1700",
    "addr:street":"Ninoofsesteenweg",
    "iso:country":"BE",
    "sg:address":"Ninoofsesteenweg 230 B1",
    "sg:city":"Dilbeek",
    "sg:orig_category":"Banques and organismes de cr\u00e9dit",
    "sg:phone":"+32 2 569 46 46",
    "sg:postcode":"1700",
    "sg:province":"Vlaams-Brabant",
    "wof:name":"Artesia",
    "wof:placetype":"venue"
},
  "geometry": {"coordinates":[4.2624697685,50.8459358215],"type":"Point"}
}