{
  "type": "Feature",
  "properties": {
    "iso:country":"BE",
    "sg:address":"Rue De L\u00b4eglise 16",
    "sg:city":"Leuze-en-hainaut",
    "sg:orig_category":"Paramedische behandelingen",
    "sg:phone":"+32 69 66 18 79",
    "sg:postcode":"7904",
    "sg:province":"Hainaut",
    "wof:name":"D. Dedriche",
    "wof:placetype":"venue"
},
  "geometry": {"coordinates":[3.5759270191,50.5829544067],"type":"Point"}
}