{
  "type": "Feature",
  "properties": {
    "iso:country":"BE",
    "sg:address":"Chauss\u00c9e Saint-pierre 101",
    "sg:city":"Etterbeek",
    "sg:orig_category":"Mat\u00e9riel m\u00e9dical and orthop\u00e9dique and proth\u00e8ses Fab",
    "sg:phone":"+32 2 644 13 59",
    "sg:postcode":"1040",
    "sg:province":"Bruxelles-Capitale",
    "wof:name":"Frederic Seynaeve",
    "wof:placetype":"venue"
},
  "geometry": {"coordinates":[4.3849730492,50.8358078003],"type":"Point"}
}