{
  "type": "Feature",
  "properties": {
    "addr:full":"Kerzelare 102 Oudenaarde Oost-Vlaanderen 9700",
    "addr:housenumber":"102",
    "addr:postcode":"9700",
    "iso:country":"BE",
    "sg:address":"Kerzelare 102",
    "sg:city":"Oudenaarde",
    "sg:classifiers":[
        {
            "category":"Sports & Exercise",
            "subcategory":"Stables",
            "type":"Entertainment"
        }
    ],
    "sg:phone":"+32 55 31 39 68",
    "sg:postcode":"9700",
    "sg:province":"Oost-Vlaanderen",
    "sg:tags":[
        "riding",
        "school"
    ],
    "wof:name":"Kerselare Manege-ruitershop",
    "wof:placetype":"venue"
},
  "geometry": {"coordinates":[3.6329300404,50.8292999268],"type":"Point"}
}