{
  "type": "Feature",
  "properties": {
    "addr:full":"Rue Du Roi Chevalier 11 Moeskroen/mouscron Hainaut 7700",
    "addr:housenumber":"11",
    "addr:postcode":"7700",
    "addr:street":"Rue Du Roi Chevalier",
    "iso:country":"BE",
    "sg:address":"Rue Du Roi Chevalier 11",
    "sg:city":"Moeskroen/mouscron",
    "sg:orig_category":"D\u00e9taillants en pi\u00e8ces and accessoires de voitures",
    "sg:phone":"+32 56 33 30 35",
    "sg:postcode":"7700",
    "sg:province":"Hainaut",
    "wof:name":"Centrale Du Pneu",
    "wof:placetype":"venue"
},
  "geometry": {"coordinates":[3.2323200703,50.7400932312],"type":"Point"}
}