{
  "type": "Feature",
  "properties": {
    "addr:full":"Diestsebaan 121 Diest (groot) Vlaams-Brabant 3290",
    "addr:housenumber":"121",
    "addr:postcode":"3290",
    "addr:street":"Diestsebaan;Groot Vlaams-Brabant",
    "iso:country":"BE",
    "sg:address":"Diestsebaan 121",
    "sg:city":"Diest (groot)",
    "sg:classifiers":[
        {
            "category":"Personal",
            "subcategory":"Beauty Salon",
            "type":"Services"
        }
    ],
    "sg:phone":"+32 13 31 29 74",
    "sg:postcode":"3290",
    "sg:province":"Vlaams-Brabant",
    "sg:tags":[
        "de",
        "coiffure"
    ],
    "wof:name":"Coiffure Marc",
    "wof:placetype":"venue"
},
  "geometry": {"coordinates":[5.0742759705,50.9969444275],"type":"Point"}
}