{
  "type": "Feature",
  "properties": {
    "addr:full":"Elsendonkstraat 85 Nijlen Antwerpen 2560",
    "addr:housenumber":"85",
    "addr:postcode":"2560",
    "addr:street":"Elsendonkstraat",
    "iso:country":"BE",
    "sg:address":"Elsendonkstraat 85",
    "sg:city":"Nijlen",
    "sg:orig_category":"Drukkerijen and copyshops",
    "sg:phone":"+32 3 481 87 48",
    "sg:postcode":"2560",
    "sg:province":"Antwerpen",
    "wof:name":"Robert Van Tendeloo",
    "wof:placetype":"venue"
},
  "geometry": {"coordinates":[4.6829171181,51.1688461304],"type":"Point"}
}