{
  "type": "Feature",
  "properties": {
    "iso:country":"BE",
    "sg:address":"Watertorenstraat 25",
    "sg:city":"Hamont-achel",
    "sg:orig_category":"Groententeelt",
    "sg:phone":"+32 11 44 53 54",
    "sg:postcode":"3930",
    "sg:province":"Limburg",
    "wof:name":"Jan Lipkens",
    "wof:placetype":"venue"
},
  "geometry": {"coordinates":[5.5450549126,51.2511863708],"type":"Point"}
}