{
  "type": "Feature",
  "properties": {
    "addr:full":"Milcampslaan 86 Schaarbeek/schaerbeek Bruxelles-Capitale 1030",
    "addr:housenumber":"86",
    "addr:postcode":"1030",
    "addr:street":"Milcampslaan",
    "iso:country":"BE",
    "sg:address":"Milcampslaan 86",
    "sg:city":"Schaarbeek/schaerbeek",
    "sg:classifiers":[
        {
            "category":"Cafe",
            "type":"Food & Drink"
        }
    ],
    "sg:phone":"+32 2 733 04 80",
    "sg:postcode":"1030",
    "sg:province":"Bruxelles-Capitale",
    "sg:tags":[
        "caf\u00e9s"
    ],
    "wof:name":"L'imper",
    "wof:placetype":"venue"
},
  "geometry": {"coordinates":[4.3942742348,50.8505859375],"type":"Point"}
}