{
  "type": "Feature",
  "properties": {
    "addr:full":"Rue Fran\u00c7ois Reconnu 25 Charleroi Hainaut 6061",
    "addr:housenumber":"25",
    "addr:postcode":"6061",
    "addr:street":"Rue Franc\u0327Ois Reconnu;Hainaut",
    "iso:country":"BE",
    "sg:address":"Rue Fran\u00c7ois Reconnu 25",
    "sg:city":"Charleroi",
    "sg:orig_category":"Artsen and specialisten",
    "sg:phone":"+32 71 32 07 50",
    "sg:postcode":"6061",
    "sg:province":"Hainaut",
    "wof:name":"Nicole Vandemaele",
    "wof:placetype":"venue"
},
  "geometry": {"coordinates":[4.4774670601,50.4077606201],"type":"Point"}
}