{
  "type": "Feature",
  "properties": {
    "iso:country":"BE",
    "sg:address":"Rue De Pepinster 54b60",
    "sg:city":"Verviers",
    "sg:orig_category":"Meubles D\u00e9taillants, Am\u00e9nagement de B\u00e2timents et de Cuisines",
    "sg:phone":"+32 87 33 23 00",
    "sg:postcode":"4800",
    "sg:province":"Li\u00e8ge",
    "wof:name":"Arpad Asztalos",
    "wof:placetype":"venue"
},
  "geometry": {"coordinates":[5.8594508171,50.5917663574],"type":"Point"}
}