{
  "type": "Feature",
  "properties": {
    "iso:country":"BE",
    "sg:address":"Klerkenstraat 114a",
    "sg:city":"Houthulst",
    "sg:orig_category":"Herstellingen and onderhoud van auto's Voertuigen",
    "sg:phone":"+32 51 50 00 77",
    "sg:postcode":"8650",
    "sg:province":"West-Vlaanderen",
    "wof:name":"Carrosserie Hindryckx",
    "wof:placetype":"venue"
},
  "geometry": {"coordinates":[2.9370999336,50.9833984375],"type":"Point"}
}