{
  "type": "Feature",
  "properties": {
    "addr:full":"Schoterweg 22 Tessenderlo Limburg 3980",
    "addr:housenumber":"22",
    "addr:postcode":"3980",
    "addr:street":"Schoterweg",
    "iso:country":"BE",
    "sg:address":"Schoterweg 22",
    "sg:city":"Tessenderlo",
    "sg:classifiers":[
        {
            "category":"Building & Trades",
            "subcategory":"Landscaping Services",
            "type":"Services"
        }
    ],
    "sg:phone":"+32 13 66 30 74",
    "sg:postcode":"3980",
    "sg:province":"Limburg",
    "sg:tags":[
        "architect",
        "landscape"
    ],
    "wof:name":"Nand Klinkers Bvba",
    "wof:placetype":"venue"
},
  "geometry": {"coordinates":[5.0822029114,51.0674781799],"type":"Point"}
}