{
  "type": "Feature",
  "properties": {
    "addr:full":"Rue De Saint-ghislain 13 Chievres Hainaut 7950",
    "addr:housenumber":"13",
    "addr:postcode":"7950",
    "addr:street":"Rue De Saint-Ghislain;Hainaut",
    "iso:country":"BE",
    "sg:address":"Rue De Saint-ghislain 13",
    "sg:city":"Chievres",
    "sg:orig_category":"Banken and kredietinstellingen",
    "sg:phone":"+32 68 65 76 73",
    "sg:postcode":"7950",
    "sg:province":"Hainaut",
    "wof:name":"Cbc",
    "wof:placetype":"venue"
},
  "geometry": {"coordinates":[3.805793047,50.5845794678],"type":"Point"}
}