{
  "type": "Feature",
  "properties": {
    "addr:full":"Molenhoek 131 Lede (smetlede) Oost-Vlaanderen 9340",
    "addr:housenumber":"131",
    "addr:postcode":"9340",
    "addr:street":"Molenhoek",
    "iso:country":"BE",
    "sg:address":"Molenhoek 131",
    "sg:city":"Lede (smetlede)",
    "sg:classifiers":[
        {
            "category":"Building & Trades",
            "subcategory":"Construction",
            "type":"Services"
        }
    ],
    "sg:phone":"+32 9 368 16 35",
    "sg:postcode":"9340",
    "sg:province":"Oost-Vlaanderen",
    "sg:tags":[
        "stucco",
        "contractor"
    ],
    "wof:name":"De Smet Nv",
    "wof:placetype":"venue"
},
  "geometry": {"coordinates":[3.9158670902,50.9635238647],"type":"Point"}
}