{
  "type": "Feature",
  "properties": {
    "iso:country":"BE",
    "sg:address":"Rue Du Trieu Du Loup 69",
    "sg:city":"Cerfontaine",
    "sg:orig_category":"Quincailleries. Instituts de beaut\u00e9",
    "sg:phone":"+32 71 64 44 12",
    "sg:postcode":"5630",
    "sg:province":"Namur",
    "wof:name":"Maison Bruaux-gigot",
    "wof:placetype":"venue"
},
  "geometry": {"coordinates":[4.4700598717,50.1738624573],"type":"Point"}
}