{
  "type": "Feature",
  "properties": {
    "addr:full":"Bergensesteenweg 411 Sint-pieters-leeuw Vlaams-Brabant 1600",
    "addr:housenumber":"411",
    "addr:postcode":"1600",
    "addr:street":"Bergensesteenweg",
    "iso:country":"BE",
    "sg:address":"Bergensesteenweg 411",
    "sg:city":"Sint-pieters-leeuw",
    "sg:orig_category":"Apotheken",
    "sg:phone":"+32 2 377 41 03",
    "sg:postcode":"1600",
    "sg:province":"Vlaams-Brabant",
    "wof:name":"Apoth. Graste-dessomviele",
    "wof:placetype":"venue"
},
  "geometry": {"coordinates":[4.278553009,50.7873039246],"type":"Point"}
}