{
  "type": "Feature",
  "properties": {
    "iso:country":"BE",
    "sg:address":"Steenoven 18",
    "sg:city":"Beernem",
    "sg:orig_category":"Rundveehouders Varkenskwekers",
    "sg:phone":"+32 50 78 92 11",
    "sg:postcode":"8730",
    "sg:province":"West-Vlaanderen",
    "wof:name":"Gilbert Desmet",
    "wof:placetype":"venue"
},
  "geometry": {"coordinates":[3.3764328957,51.1624412537],"type":"Point"}
}