{
  "type": "Feature",
  "properties": {
    "iso:country":"BE",
    "sg:address":"Chauss\u00c9e De Malines 114",
    "sg:city":"Wezembeek-oppem",
    "sg:orig_category":"D\u00e9taillants en pi\u00e8ces and accessoires de voitures",
    "sg:phone":"+32 2 782 20 05",
    "sg:postcode":"1970",
    "sg:province":"Vlaams-Brabant",
    "wof:name":"Oppem Pneus",
    "wof:placetype":"venue"
},
  "geometry": {"coordinates":[4.4941658974,50.8401412964],"type":"Point"}
}