{
  "type": "Feature",
  "properties": {
    "addr:full":"Stationsstraat 164 Wichelen Oost-Vlaanderen 9260",
    "addr:housenumber":"164",
    "addr:postcode":"9260",
    "addr:street":"Stationsstraat",
    "iso:country":"BE",
    "sg:address":"Stationsstraat 164",
    "sg:city":"Wichelen",
    "sg:orig_category":"Sportclubs",
    "sg:phone":"+32 9 369 31 19",
    "sg:postcode":"9260",
    "sg:province":"Oost-Vlaanderen",
    "wof:name":"T.c. Standaard Wetteren",
    "wof:placetype":"venue"
},
  "geometry": {"coordinates":[3.9224550724,51.0010223389],"type":"Point"}
}