{
  "type": "Feature",
  "properties": {
    "addr:full":"Rue Spintay 21 Verviers Li\u00e8ge 4800",
    "addr:housenumber":"21",
    "addr:postcode":"4800",
    "addr:street":"Rue Spintay",
    "iso:country":"BE",
    "sg:address":"Rue Spintay 21",
    "sg:city":"Verviers",
    "sg:classifiers":[
        {
            "category":"Social Services",
            "type":"Services"
        }
    ],
    "sg:phone":"+32 87 33 18 76",
    "sg:postcode":"4800",
    "sg:province":"Li\u00e8ge",
    "wof:name":"Centre Femmes Verviers",
    "wof:placetype":"venue"
},
  "geometry": {"coordinates":[5.8594508171,50.5917663574],"type":"Point"}
}