{
  "type": "Feature",
  "properties": {
    "iso:country":"BE",
    "sg:address":"Pasbrugstr. 33",
    "sg:city":"Hoesselt",
    "sg:classifiers":[
        {
            "category":"Health Services",
            "subcategory":"Medical Lab",
            "type":"Services"
        }
    ],
    "sg:phone":"+32 89 61 17 91",
    "sg:postcode":"3730",
    "sg:province":"Limburg",
    "sg:tags":[
        "chemical",
        "pharmaceutical",
        "pharmacy"
    ],
    "wof:name":"Dhr Rema Hendrik",
    "wof:placetype":"venue"
},
  "geometry": {"coordinates":[5.4977550507,50.8489112854],"type":"Point"}
}