{
  "type": "Feature",
  "properties": {
    "iso:country":"BE",
    "sg:address":"Alfons Sifferstraat 5b",
    "sg:city":"Zomergem",
    "sg:classifiers":[
        {
            "category":"Shopping",
            "subcategory":"Clothing, Apparel, & Fashions",
            "type":"Retail Goods"
        }
    ],
    "sg:phone":"+32 9 372 72 01",
    "sg:postcode":"9930",
    "sg:province":"Oost-Vlaanderen",
    "sg:tags":[
        "lady",
        "clothing",
        "-"
    ],
    "wof:name":"Van Hoorebeke",
    "wof:placetype":"venue"
},
  "geometry": {"coordinates":[3.5596439838,51.1172981262],"type":"Point"}
}