{
  "type": "Feature",
  "properties": {
    "iso:country":"BE",
    "sg:address":"Vleurgatsesteenweg 30",
    "sg:city":"Elsene/ixelles",
    "sg:orig_category":"Notarissen",
    "sg:phone":"+32 2 648 08 30",
    "sg:postcode":"1050",
    "sg:province":"Bruxelles-Capitale",
    "wof:name":"Xavier Carly",
    "wof:placetype":"venue"
},
  "geometry": {"coordinates":[4.3707070351,50.8267097473],"type":"Point"}
}