{
  "type": "Feature",
  "properties": {
    "addr:full":"Rue Wauters 195 Beloeil (quevaucamps) Hainaut 7972",
    "addr:housenumber":"195",
    "addr:postcode":"7972",
    "addr:street":"Rue Wauters",
    "iso:country":"BE",
    "sg:address":"Rue Wauters 195",
    "sg:city":"Beloeil (quevaucamps)",
    "sg:classifiers":[
        {
            "category":"Insurance",
            "subcategory":"Insurance Agent",
            "type":"Services"
        }
    ],
    "sg:phone":"+32 69 57 61 57",
    "sg:postcode":"7972",
    "sg:province":"Hainaut",
    "sg:tags":[
        "broker"
    ],
    "wof:name":"Quintin (assurances) Sprl",
    "wof:placetype":"venue"
},
  "geometry": {"coordinates":[3.6921050549,50.5274238586],"type":"Point"}
}