{
  "type": "Feature",
  "properties": {
    "addr:full":"Zandstr 41 Zomergem Oost-Vlaanderen 9930",
    "addr:housenumber":"41",
    "addr:postcode":"9930",
    "addr:street":"Zandstr",
    "iso:country":"BE",
    "sg:address":"Zandstr 41",
    "sg:city":"Zomergem",
    "sg:classifiers":[
        {
            "category":"Building & Trades",
            "subcategory":"Construction",
            "type":"Services"
        }
    ],
    "sg:phone":"+32 9 372 78 01",
    "sg:postcode":"9930",
    "sg:province":"Oost-Vlaanderen",
    "sg:tags":[
        "work",
        "public"
    ],
    "wof:name":"Rene Claeys Nv",
    "wof:placetype":"venue"
},
  "geometry": {"coordinates":[3.5680809021,51.117275238],"type":"Point"}
}