{
  "type": "Feature",
  "properties": {
    "addr:full":"Rue Albert I 35 Fleurus (lambusart) Hainaut 6220",
    "addr:housenumber":"35",
    "addr:postcode":"6220",
    "addr:street":"Rue Albert I",
    "iso:country":"BE",
    "sg:address":"Rue Albert I 35",
    "sg:city":"Fleurus (lambusart)",
    "sg:classifiers":[
        {
            "category":"Home & Garden",
            "subcategory":"Furniture",
            "type":"Retail Goods"
        }
    ],
    "sg:phone":"+32 477 55 69 87",
    "sg:postcode":"6220",
    "sg:province":"Hainaut",
    "sg:tags":[
        "-"
    ],
    "wof:name":"Esico Sprl",
    "wof:placetype":"venue"
},
  "geometry": {"coordinates":[4.5003662109,50.4472122192],"type":"Point"}
}