{
  "type": "Feature",
  "properties": {
    "iso:country":"BE",
    "sg:address":"Aux Allieux 8",
    "sg:city":"Libramont-chevigny (libramont)",
    "sg:classifiers":[
        {
            "category":"Taxi",
            "type":"Transportation"
        }
    ],
    "sg:phone":"+32 61 23 29 00",
    "sg:postcode":"6800",
    "sg:province":"Luxembourg",
    "sg:tags":[
        "taxicab"
    ],
    "wof:name":"Taxilux Libramont Sprl",
    "wof:placetype":"venue"
},
  "geometry": {"coordinates":[5.3761348724,49.9199943542],"type":"Point"}
}