{
  "type": "Feature",
  "properties": {
    "iso:country":"BE",
    "sg:address":"Stationsplein 0",
    "sg:city":"Hasselt",
    "sg:classifiers":[
        {
            "category":"Cafe",
            "type":"Food & Drink"
        }
    ],
    "sg:phone":"+32 11 22 60 40",
    "sg:postcode":"3500",
    "sg:province":"Limburg",
    "sg:tags":[
        "caf\u00e9s"
    ],
    "wof:name":"Buffet",
    "wof:placetype":"venue"
},
  "geometry": {"coordinates":[5.327023983,50.9310493469],"type":"Point"}
}