{
  "type": "Feature",
  "properties": {
    "iso:country":"BE",
    "sg:address":"Stationsstraat 22-24",
    "sg:city":"Opwijk",
    "sg:orig_category":"Installatie van houten of kunststof schrijnwerk",
    "sg:phone":"+32 52 35 15 43",
    "sg:postcode":"1745",
    "sg:province":"Vlaams-Brabant",
    "wof:name":"De Donder F.",
    "wof:placetype":"venue"
},
  "geometry": {"coordinates":[4.1870260239,50.9726982117],"type":"Point"}
}