{
  "type": "Feature",
  "properties": {
    "addr:full":"Graaf Van Hoornestraat 15 Antwerpen Antwerpen 2000",
    "addr:housenumber":"15",
    "addr:postcode":"2000",
    "addr:street":"Graaf Van Hoornestraat",
    "iso:country":"BE",
    "sg:address":"Graaf Van Hoornestraat 15",
    "sg:city":"Antwerpen",
    "sg:orig_category":"Avocats and conseillers juridiques",
    "sg:phone":"+32 3 216 08 47",
    "sg:postcode":"2000",
    "sg:province":"Antwerpen",
    "wof:name":"J. Coesemans",
    "wof:placetype":"venue"
},
  "geometry": {"coordinates":[4.393032074,51.2075767517],"type":"Point"}
}