{
  "type": "Feature",
  "properties": {
    "iso:country":"BE",
    "sg:address":"Rue De L'yser 44",
    "sg:city":"Awans",
    "sg:orig_category":"Benzinestations and brandstoffen HUISBRANDOLIE",
    "sg:phone":"+32 4 257 41 04",
    "sg:postcode":"4340",
    "sg:province":"Li\u00e8ge",
    "wof:name":"Fe. Charbomeuse",
    "wof:placetype":"venue"
},
  "geometry": {"coordinates":[5.4384331703,50.7060890198],"type":"Point"}
}