{
  "type": "Feature",
  "properties": {
    "addr:full":"Leuvestraat 2 Aalst Oost-Vlaanderen 9320",
    "addr:housenumber":"2",
    "addr:postcode":"9320",
    "addr:street":"Leuvestraat",
    "iso:country":"BE",
    "sg:address":"Leuvestraat 2",
    "sg:city":"Aalst",
    "sg:orig_category":"Industri\u00eble wasserijen and droogkuis",
    "sg:phone":"+32 53 77 90 29",
    "sg:postcode":"9320",
    "sg:province":"Oost-Vlaanderen",
    "wof:name":"White Shop",
    "wof:placetype":"venue"
},
  "geometry": {"coordinates":[4.0553851128,50.9209976196],"type":"Point"}
}