{
  "type": "Feature",
  "properties": {
    "addr:full":"Warandestraat 1 Oostkamp West-Vlaanderen 8020",
    "addr:housenumber":"1",
    "addr:postcode":"8020",
    "addr:street":"Warandestraat",
    "iso:country":"BE",
    "sg:address":"Warandestraat 1",
    "sg:city":"Oostkamp",
    "sg:orig_category":"Eleveurs d'\u00e9quid\u00e9s",
    "sg:phone":"+32 50 39 27 31",
    "sg:postcode":"8020",
    "sg:province":"West-Vlaanderen",
    "wof:name":"H.t.c.",
    "wof:placetype":"venue"
},
  "geometry": {"coordinates":[3.2344601154,51.1709289551],"type":"Point"}
}