{
  "type": "Feature",
  "properties": {
    "addr:full":"Rue Jean-d'outremeuse 20 Li\u00c8ge Li\u00e8ge 4020",
    "addr:housenumber":"20",
    "addr:postcode":"4020",
    "addr:street":"Rue Jean-D'Outremeuse",
    "iso:country":"BE",
    "sg:address":"Rue Jean-d'outremeuse 20",
    "sg:city":"Li\u00c8ge",
    "sg:orig_category":"Fleurs and plantes. Location de biens divers",
    "sg:phone":"+32 4 341 54 03",
    "sg:postcode":"4020",
    "sg:province":"Li\u00e8ge",
    "wof:name":"Aux Fleurs D'outremeuse",
    "wof:placetype":"venue"
},
  "geometry": {"coordinates":[5.5835189819,50.6393852234],"type":"Point"}
}