{
  "type": "Feature",
  "properties": {
    "iso:country":"BE",
    "sg:address":"Stuiverstraat 57",
    "sg:city":"Oostende",
    "sg:orig_category":"Pain, p\u00e2tisseries and confiseries",
    "sg:phone":"+32 59 51 03 42",
    "sg:postcode":"8400",
    "sg:province":"West-Vlaanderen",
    "wof:name":"Wim Van Craeynest",
    "wof:placetype":"venue"
},
  "geometry": {"coordinates":[2.9017810822,51.2191123962],"type":"Point"}
}