{
  "type": "Feature",
  "properties": {
    "addr:full":"Rerum-novarumplein 188 Gent Oost-Vlaanderen 9000",
    "addr:housenumber":"188",
    "addr:postcode":"9000",
    "addr:street":"Oost-Vlaanderen",
    "iso:country":"BE",
    "sg:address":"Rerum-novarumplein 188",
    "sg:city":"Gent",
    "sg:orig_category":"Enseignement maternel and primaire",
    "sg:phone":"+32 9 221 54 75",
    "sg:postcode":"9000",
    "sg:province":"Oost-Vlaanderen",
    "wof:name":"Vrije Basisschool",
    "wof:placetype":"venue"
},
  "geometry": {"coordinates":[3.7185499668,51.0238609314],"type":"Point"}
}