{
  "type": "Feature",
  "properties": {
    "addr:full":"Torhoutse Steenweg 455 Brugge West-Vlaanderen 8200",
    "addr:housenumber":"455",
    "addr:postcode":"8200",
    "addr:street":"Torhoutse Steenweg",
    "iso:country":"BE",
    "sg:address":"Torhoutse Steenweg 455",
    "sg:city":"Brugge",
    "sg:classifiers":[
        {
            "category":"Cafe",
            "type":"Food & Drink"
        }
    ],
    "sg:phone":"+32 50 38 03 95",
    "sg:postcode":"8200",
    "sg:province":"West-Vlaanderen",
    "sg:tags":[
        "caf\u00e9s"
    ],
    "wof:name":"Caf\u00c9 Den Tijl",
    "wof:placetype":"venue"
},
  "geometry": {"coordinates":[3.1783308983,51.1732139587],"type":"Point"}
}