{
  "type": "Feature",
  "properties": {
    "addr:full":"'s Gravenstraat 61 Nazareth Oost-Vlaanderen 9810",
    "addr:housenumber":"61",
    "addr:postcode":"9810",
    "addr:street":"' S Gravenstraat",
    "iso:country":"BE",
    "sg:address":"'s Gravenstraat 61",
    "sg:city":"Nazareth",
    "sg:orig_category":"Artsen and specialisten",
    "sg:phone":"+32 9 385 56 90",
    "sg:postcode":"9810",
    "sg:province":"Oost-Vlaanderen",
    "wof:name":"Andreas Van Poucke",
    "wof:placetype":"venue"
},
  "geometry": {"coordinates":[3.5957829952,50.9612007141],"type":"Point"}
}