{
  "type": "Feature",
  "properties": {
    "iso:country":"BE",
    "sg:address":"Avenue Des Criquets 23",
    "sg:city":"Watermaal-bosvoorde",
    "sg:orig_category":"R\u00e9alisation de programmes and logiciels",
    "sg:phone":"+32 2 675 14 25",
    "sg:postcode":"1170",
    "sg:province":"Bruxelles-Capitale",
    "wof:name":"Hdb Communication",
    "wof:placetype":"venue"
},
  "geometry": {"coordinates":[4.4024147987,50.7998847961],"type":"Point"}
}