{
  "type": "Feature",
  "properties": {
    "addr:full":"Rue De La Prale 38 Hannut Li\u00e8ge 4280",
    "addr:housenumber":"38",
    "addr:postcode":"4280",
    "addr:street":"Rue De La Prale",
    "iso:country":"BE",
    "sg:address":"Rue De La Prale 38",
    "sg:city":"Hannut",
    "sg:orig_category":"Mazda. Entretien and r\u00e9parations de voitures",
    "sg:phone":"+32 19 51 14 27",
    "sg:postcode":"4280",
    "sg:province":"Li\u00e8ge",
    "wof:name":"Garage Marchal Motor",
    "wof:placetype":"venue"
},
  "geometry": {"coordinates":[5.1001048088,50.6604347229],"type":"Point"}
}