{
  "type": "Feature",
  "properties": {
    "addr:full":"Rue Purgatoire 2 Pepinster Li\u00e8ge 4860",
    "addr:housenumber":"2",
    "addr:postcode":"4860",
    "addr:street":"Rue Purgatoire",
    "iso:country":"BE",
    "sg:address":"Rue Purgatoire 2",
    "sg:city":"Pepinster",
    "sg:orig_category":"Installatie van houten of kunststof schrijnwerk",
    "sg:phone":"+32 87 33 15 94",
    "sg:postcode":"4860",
    "sg:province":"Li\u00e8ge",
    "wof:name":"Quoidbach Fr\u00c9d\u00c9ric",
    "wof:placetype":"venue"
},
  "geometry": {"coordinates":[5.8348097801,50.5769271851],"type":"Point"}
}