{
  "type": "Feature",
  "properties": {
    "addr:full":"Lakenmakerstraat 126 Mechelen Antwerpen 2800",
    "addr:housenumber":"126",
    "addr:postcode":"2800",
    "addr:street":"Lakenmakerstraat",
    "iso:country":"BE",
    "sg:address":"Lakenmakerstraat 126",
    "sg:city":"Mechelen",
    "sg:orig_category":"Metaalbehandeling and -bekleding",
    "sg:phone":"+32 15 55 62 83",
    "sg:postcode":"2800",
    "sg:province":"Antwerpen",
    "wof:name":"Brabantchrom Cv",
    "wof:placetype":"venue"
},
  "geometry": {"coordinates":[4.5017080307,51.0309143066],"type":"Point"}
}