{
  "type": "Feature",
  "properties": {
    "addr:full":"Rue Jean-baptiste Lepage 26-28 Bruxelles (woluwe-saint-pierre) Bruxelles-Capitale 1150",
    "addr:housenumber":"26-28",
    "addr:postcode":"1150",
    "addr:street":"Rue Jean-Baptiste Lepage",
    "iso:country":"BE",
    "sg:address":"Rue Jean-baptiste Lepage 26-28",
    "sg:city":"Bruxelles (woluwe-saint-pierre)",
    "sg:classifiers":[
        {
            "category":"Retail",
            "subcategory":"Auto Repair",
            "type":"Services"
        }
    ],
    "sg:phone":"+32 2 762 29 00",
    "sg:postcode":"1150",
    "sg:province":"Bruxelles-Capitale",
    "sg:tags":[
        "automobile-body"
    ],
    "wof:name":"Carosserie De Stockel",
    "wof:placetype":"venue"
},
  "geometry": {"coordinates":[4.4606070518,50.8418693542],"type":"Point"}
}