{
  "type": "Feature",
  "properties": {
    "addr:full":"Domaine Du Lac 29 Weismes Li\u00e8ge 4950",
    "addr:housenumber":"29",
    "addr:postcode":"4950",
    "addr:street":"Domaine Du Lac",
    "iso:country":"BE",
    "sg:address":"Domaine Du Lac 29",
    "sg:city":"Weismes",
    "sg:classifiers":[
        {
            "category":"Food & Beverages",
            "subcategory":"Meat & Fish",
            "type":"Retail Goods"
        }
    ],
    "sg:phone":"+32 80 44 62 60",
    "sg:postcode":"4950",
    "sg:province":"Li\u00e8ge",
    "sg:tags":[
        "poultry",
        "whol",
        "game",
        "-"
    ],
    "wof:name":"Fagnarde (la)",
    "wof:placetype":"venue"
},
  "geometry": {"coordinates":[6.1078591347,50.4457473755],"type":"Point"}
}