{
  "type": "Feature",
  "properties": {
    "addr:full":"Rue Du Vignoble 32 Vorst/forest Bruxelles-Capitale 1190",
    "addr:housenumber":"32",
    "addr:postcode":"1190",
    "addr:street":"Rue Du Vignoble;/ Forest",
    "iso:country":"BE",
    "sg:address":"Rue Du Vignoble 32",
    "sg:city":"Vorst/forest",
    "sg:orig_category":"M\u00e9decins and sp\u00e9cialistes",
    "sg:phone":"+32 2 343 70 98",
    "sg:postcode":"1190",
    "sg:province":"Bruxelles-Capitale",
    "wof:name":"Erlich",
    "wof:placetype":"venue"
},
  "geometry": {"coordinates":[4.3264598846,50.813419342],"type":"Point"}
}