{
  "type": "Feature",
  "properties": {
    "iso:country":"BE",
    "sg:address":"Molenstraat 38",
    "sg:city":"Haaltert",
    "sg:classifiers":[
        {
            "category":"Insurance",
            "subcategory":"Life Insurance",
            "type":"Services"
        }
    ],
    "sg:phone":"+32 54 33 63 25",
    "sg:postcode":"9450",
    "sg:province":"Oost-Vlaanderen",
    "sg:tags":[
        "assurance"
    ],
    "wof:name":"Van Weyenberg",
    "wof:placetype":"venue"
},
  "geometry": {"coordinates":[4.0176091194,50.8729057312],"type":"Point"}
}