{
  "type": "Feature",
  "properties": {
    "addr:full":"Oudenaardsesteenweg 341 Erpe-mere Oost-Vlaanderen 9420",
    "addr:housenumber":"341",
    "addr:postcode":"9420",
    "addr:street":"Oudenaardsesteenweg",
    "iso:country":"BE",
    "sg:address":"Oudenaardsesteenweg 341",
    "sg:city":"Erpe-mere",
    "sg:classifiers":[
        {
            "category":"Personal",
            "subcategory":"Beauty Salon",
            "type":"Services"
        }
    ],
    "sg:phone":"+32 53 80 49 87",
    "sg:postcode":"9420",
    "sg:province":"Oost-Vlaanderen",
    "sg:tags":[
        "de",
        "coiffure"
    ],
    "wof:name":"Haarstudio Nancy",
    "wof:placetype":"venue"
},
  "geometry": {"coordinates":[3.9613289833,50.9287376404],"type":"Point"}
}