{
  "type": "Feature",
  "properties": {
    "addr:full":"Chemin Du Bon Dieu 64 Quaregnon Hainaut 7390",
    "addr:housenumber":"64",
    "addr:postcode":"7390",
    "addr:street":"Chemin Du Bon Dieu",
    "iso:country":"BE",
    "sg:address":"Chemin Du Bon Dieu 64",
    "sg:city":"Quaregnon",
    "sg:orig_category":"Dakwerken Diverse bouwafwerking and reiniging Woningbouw",
    "sg:phone":"+32 65 79 29 85",
    "sg:postcode":"7390",
    "sg:province":"Hainaut",
    "wof:name":"Batisant",
    "wof:placetype":"venue"
},
  "geometry": {"coordinates":[3.8692610264,50.4395904541],"type":"Point"}
}