{
  "type": "Feature",
  "properties": {
    "iso:country":"BE",
    "sg:address":"Gistelsesteenweg 123c",
    "sg:city":"Varsenare",
    "sg:orig_category":"Royal Canin. Animaux domestiques and accessoires",
    "sg:phone":"+32 50 38 93 95",
    "sg:postcode":"8490",
    "sg:province":"West-Vlaanderen",
    "wof:name":"Dhr.schollier Maurice",
    "wof:placetype":"venue"
},
  "geometry": {"coordinates":[3.1467180252,51.1866416931],"type":"Point"}
}