{
  "type": "Feature",
  "properties": {
    "addr:full":"Nieuwstraat 6 Geel Antwerpen 2440",
    "addr:housenumber":"6",
    "addr:postcode":"2440",
    "addr:street":"Nieuwstraat",
    "iso:country":"BE",
    "sg:address":"Nieuwstraat 6",
    "sg:city":"Geel",
    "sg:orig_category":"Services de t\u00e9l\u00e9communications. Syst\u00e8mes de t\u00e9l\u00e9communications. Mat\u00e9riel de T\u00e9l\u00e9communication",
    "sg:phone":"+32 14 59 44 90",
    "sg:postcode":"2440",
    "sg:province":"Antwerpen",
    "wof:name":"Mobistar Center Telecom Systems",
    "wof:placetype":"venue"
},
  "geometry": {"coordinates":[4.9912657738,51.1627502441],"type":"Point"}
}