{
  "type": "Feature",
  "properties": {
    "addr:full":"Oudenaardsesteenweg 460 Erpe-mere Oost-Vlaanderen 9420",
    "addr:housenumber":"460",
    "addr:postcode":"9420",
    "addr:street":"Oudenaardsesteenweg",
    "iso:country":"BE",
    "sg:address":"Oudenaardsesteenweg 460",
    "sg:city":"Erpe-mere",
    "sg:orig_category":"Benzinestations and brandstoffen",
    "sg:phone":"+32 53 83 30 88",
    "sg:postcode":"9420",
    "sg:province":"Oost-Vlaanderen",
    "wof:name":"Fina",
    "wof:placetype":"venue"
},
  "geometry": {"coordinates":[3.9472439289,50.9225082397],"type":"Point"}
}