{
  "type": "Feature",
  "properties": {
    "addr:full":"Rue De La Digue 0 Rumes Hainaut 7618",
    "addr:housenumber":"0",
    "addr:postcode":"7618",
    "addr:street":"Rue De La Digue",
    "iso:country":"BE",
    "sg:address":"Rue De La Digue 0",
    "sg:city":"Rumes",
    "sg:orig_category":"Beheer van afvalopslag- and stortplaatsen",
    "sg:phone":"+32 69 64 73 02",
    "sg:postcode":"7618",
    "sg:province":"Hainaut",
    "wof:name":"Parcs A Conteneurs Rumes",
    "wof:placetype":"venue"
},
  "geometry": {"coordinates":[3.3312199116,50.5416259766],"type":"Point"}
}