{
  "type": "Feature",
  "properties": {
    "addr:full":"Handelstraat 19 Antwerpen Antwerpen 2060",
    "addr:housenumber":"19",
    "addr:postcode":"2060",
    "addr:street":"Handelstraat",
    "iso:country":"BE",
    "sg:address":"Handelstraat 19",
    "sg:city":"Antwerpen",
    "sg:orig_category":"Assistances juridiques. Biens d'occasion",
    "sg:phone":"+32 3 236 38 64",
    "sg:postcode":"2060",
    "sg:province":"Antwerpen",
    "wof:name":"Dixy",
    "wof:placetype":"venue"
},
  "geometry": {"coordinates":[4.4282450676,51.2235336304],"type":"Point"}
}