{
  "type": "Feature",
  "properties": {
    "iso:country":"BE",
    "sg:address":"Frans Beirenslaan 69",
    "sg:city":"Borsbeek",
    "sg:classifiers":[
        {
            "category":"Home & Garden",
            "subcategory":"Household Appliances",
            "type":"Retail Goods"
        }
    ],
    "sg:phone":"+32 3 321 04 63",
    "sg:postcode":"2150",
    "sg:province":"Antwerpen",
    "sg:tags":[
        "repair",
        "mainten",
        "-",
        "electric"
    ],
    "wof:name":"Algemene Elektro Service",
    "wof:placetype":"venue"
},
  "geometry": {"coordinates":[4.479195118,51.1950645447],"type":"Point"}
}