{
  "type": "Feature",
  "properties": {
    "iso:country":"BE",
    "sg:address":"Rue Fief 17",
    "sg:city":"Olne",
    "sg:classifiers":[
        {
            "category":"Real Estate",
            "subcategory":"Architect",
            "type":"Services"
        }
    ],
    "sg:phone":"+32 4 358 43 99",
    "sg:postcode":"4877",
    "sg:province":"Li\u00e8ge",
    "wof:name":"Godart J",
    "wof:placetype":"venue"
},
  "geometry": {"coordinates":[5.7211060524,50.5932579041],"type":"Point"}
}