{
  "type": "Feature",
  "properties": {
    "iso:country":"BE",
    "sg:address":"Building",
    "sg:city":"Gent",
    "sg:classifiers":[
        {
            "category":"Shopping",
            "subcategory":"Computers & Home Electronics",
            "type":"Retail Goods"
        }
    ],
    "sg:phone":"+32 9 266 14 40",
    "sg:postcode":"9000",
    "sg:province":"Oost-Vlaanderen",
    "sg:tags":[
        "chamber",
        "commerce"
    ],
    "wof:name":"Gent Area Chamber Of Commerce And Industry",
    "wof:placetype":"venue"
},
  "geometry": {"coordinates":[3.7109489441,51.0467834473],"type":"Point"}
}