{
  "type": "Feature",
  "properties": {
    "addr:full":"Kerkvoetweg 9 Aarschot Vlaams-Brabant 3200",
    "addr:housenumber":"9",
    "addr:postcode":"3200",
    "addr:street":"Kerkvoetweg",
    "iso:country":"BE",
    "sg:address":"Kerkvoetweg 9",
    "sg:city":"Aarschot",
    "sg:orig_category":"Sportclubs Sportterreinen and installaties behalve sportcentra",
    "sg:phone":"+32 16 57 15 99",
    "sg:postcode":"3200",
    "sg:province":"Vlaams-Brabant",
    "wof:name":"V.v. Gelrode",
    "wof:placetype":"venue"
},
  "geometry": {"coordinates":[4.8315200806,50.9838638306],"type":"Point"}
}