{
  "type": "Feature",
  "properties": {
    "addr:full":"Rue Francisco Ferrer 19 Saint-nicolas Li\u00e8ge 4420",
    "addr:housenumber":"19",
    "addr:postcode":"4420",
    "addr:street":"Rue Francisco Ferrer",
    "iso:country":"BE",
    "sg:address":"Rue Francisco Ferrer 19",
    "sg:city":"Saint-nicolas",
    "sg:orig_category":"Bloemen and planten",
    "sg:phone":"+32 4 226 51 11",
    "sg:postcode":"4420",
    "sg:province":"Li\u00e8ge",
    "wof:name":"Fabienne Fleurs",
    "wof:placetype":"venue"
},
  "geometry": {"coordinates":[5.5328168869,50.6348571777],"type":"Point"}
}