{
  "type": "Feature",
  "properties": {
    "addr:full":"Golettes 23 Pepinster Li\u00e8ge 4860",
    "addr:housenumber":"23",
    "addr:postcode":"4860",
    "addr:street":"Golettes",
    "iso:country":"BE",
    "sg:address":"Golettes 23",
    "sg:city":"Pepinster",
    "sg:orig_category":"Woningbouw",
    "sg:phone":"+32 87 46 14 49",
    "sg:postcode":"4860",
    "sg:province":"Li\u00e8ge",
    "wof:name":"Charles Van Roy",
    "wof:placetype":"venue"
},
  "geometry": {"coordinates":[5.8082499504,50.5728797913],"type":"Point"}
}