{
  "type": "Feature",
  "properties": {
    "iso:country":"BE",
    "sg:address":"Rue De Pintamont 64",
    "sg:city":"Ath",
    "sg:orig_category":"Auto-\u00e9coles",
    "sg:phone":"+32 68 28 08 88",
    "sg:postcode":"7800",
    "sg:province":"Hainaut",
    "wof:name":"Auto-ecole Bara-tournai",
    "wof:placetype":"venue"
},
  "geometry": {"coordinates":[3.7740030289,50.6285438538],"type":"Point"}
}