{
  "type": "Feature",
  "properties": {
    "iso:country":"BE",
    "sg:address":"Beverlosesteenweg 139",
    "sg:city":"Beringen",
    "sg:orig_category":"Binnenhuisarchitecten",
    "sg:phone":"+32 11 42 12 98",
    "sg:postcode":"3583",
    "sg:province":"Limburg",
    "wof:name":"Firmin Reyckers",
    "wof:placetype":"venue"
},
  "geometry": {"coordinates":[5.2027769089,51.0647468567],"type":"Point"}
}