{
  "type": "Feature",
  "properties": {
    "iso:country":"BE",
    "sg:address":"Broodstraat 3-7",
    "sg:city":"Oudenaarde",
    "sg:classifiers":[
        {
            "category":"Shopping",
            "subcategory":"Clothing, Apparel, & Fashions",
            "type":"Retail Goods"
        }
    ],
    "sg:phone":"+32 55 31 18 41",
    "sg:postcode":"9700",
    "sg:province":"Oost-Vlaanderen",
    "sg:tags":[
        "clothing",
        "-",
        "gentleman"
    ],
    "wof:name":"New Dc Boetiek",
    "wof:placetype":"venue"
},
  "geometry": {"coordinates":[3.6052150726,50.8427276611],"type":"Point"}
}