{
  "type": "Feature",
  "properties": {
    "addr:full":"Rue G\u00e9n\u00e9ral Henry 101 Bruxelles (etterbeek) Bruxelles-Capitale 1040",
    "addr:housenumber":"101",
    "addr:postcode":"1040",
    "addr:street":"Rue Ge\u0301Ne\u0301Ral Henry",
    "iso:country":"BE",
    "sg:address":"Rue G\u00e9n\u00e9ral Henry 101",
    "sg:city":"Bruxelles (etterbeek)",
    "sg:classifiers":[
        {
            "category":"Building & Trades",
            "subcategory":"Plumbing",
            "type":"Services"
        }
    ],
    "sg:phone":"+32 2 647 83 54",
    "sg:postcode":"1040",
    "sg:province":"Bruxelles-Capitale",
    "sg:tags":[
        "contractor"
    ],
    "wof:name":"Vieuxtemps Sprl",
    "wof:placetype":"venue"
},
  "geometry": {"coordinates":[4.3942570686,50.8299751282],"type":"Point"}
}