{
  "type": "Feature",
  "properties": {
    "iso:country":"BE",
    "sg:address":"Chemin Malplaquet 2 (zon. Indus.)",
    "sg:city":"Ath",
    "sg:orig_category":"Entretien and r\u00e9parations de voitures",
    "sg:phone":"+32 68 55 20 75",
    "sg:postcode":"7822",
    "sg:province":"Hainaut",
    "wof:name":"Carrosserie Car Auto",
    "wof:placetype":"venue"
},
  "geometry": {"coordinates":[3.8608989716,50.6506652832],"type":"Point"}
}