{
  "type": "Feature",
  "properties": {
    "addr:full":"Kerkwegelakker 16 Lochristi Oost-Vlaanderen 9080",
    "addr:housenumber":"16",
    "addr:postcode":"9080",
    "addr:street":"Kerkwegelakker",
    "iso:country":"BE",
    "sg:address":"Kerkwegelakker 16",
    "sg:city":"Lochristi",
    "sg:orig_category":"Bloemen and planten Gh",
    "sg:phone":"+32 9 355 60 64",
    "sg:postcode":"9080",
    "sg:province":"Oost-Vlaanderen",
    "wof:name":"De Graeve",
    "wof:placetype":"venue"
},
  "geometry": {"coordinates":[3.8352029324,51.093585968],"type":"Point"}
}