{
  "type": "Feature",
  "properties": {
    "iso:country":"BE",
    "sg:address":"Hazegewoud 7",
    "sg:city":"Arendonk",
    "sg:orig_category":"Boekbinderijen and afwerking",
    "sg:phone":"+32 14 67 04 13",
    "sg:postcode":"2370",
    "sg:province":"Antwerpen",
    "wof:name":"Fa. Tuytelaars",
    "wof:placetype":"venue"
},
  "geometry": {"coordinates":[5.0972771645,51.3360519409],"type":"Point"}
}