{
  "type": "Feature",
  "properties": {
    "iso:country":"BE",
    "sg:address":"Baliestraat 18",
    "sg:city":"Brugge",
    "sg:orig_category":"M\u00e9decins and sp\u00e9cialistes",
    "sg:phone":"+32 50 34 25 81",
    "sg:postcode":"8000",
    "sg:province":"West-Vlaanderen",
    "wof:name":"Patrizia Morotti",
    "wof:placetype":"venue"
},
  "geometry": {"coordinates":[3.2265200615,51.2156219482],"type":"Point"}
}