{
  "type": "Feature",
  "properties": {
    "addr:full":"Kapelstraat 22 Puurs Antwerpen 2870",
    "addr:housenumber":"22",
    "addr:postcode":"2870",
    "addr:street":"Kapelstraat",
    "iso:country":"BE",
    "sg:address":"Kapelstraat 22",
    "sg:city":"Puurs",
    "sg:orig_category":"Hout and afgeleiden Gh IJzerwaren, bouw- and verfmaterialen",
    "sg:phone":"+32 3 889 77 82",
    "sg:postcode":"2870",
    "sg:province":"Antwerpen",
    "wof:name":"Amerhout",
    "wof:placetype":"venue"
},
  "geometry": {"coordinates":[4.3132948875,51.0830078125],"type":"Point"}
}