{
  "type": "Feature",
  "properties": {
    "addr:full":"Rue Jules Destr\u00e9e 5 Quaregnon Hainaut 7390",
    "addr:housenumber":"5",
    "addr:postcode":"7390",
    "addr:street":"Rue Jules Destre\u0301E",
    "iso:country":"BE",
    "sg:address":"Rue Jules Destr\u00e9e 5",
    "sg:city":"Quaregnon",
    "sg:classifiers":[
        {
            "category":"Travel",
            "subcategory":"Hotels & Motels",
            "type":"Entertainment"
        }
    ],
    "sg:phone":"+32 65 79 15 65",
    "sg:postcode":"7390",
    "sg:province":"Hainaut",
    "sg:tags":[
        "hotels",
        "business",
        "restaurant"
    ],
    "wof:name":"Cola Sprl",
    "wof:placetype":"venue"
},
  "geometry": {"coordinates":[3.8720960617,50.4461364746],"type":"Point"}
}