{
  "type": "Feature",
  "properties": {
    "iso:country":"BE",
    "sg:address":"Meerdegatstraat 82",
    "sg:city":"Alken",
    "sg:classifiers":[
        {
            "category":"Professional",
            "subcategory":"Printing & Photocopies",
            "type":"Services"
        }
    ],
    "sg:phone":"+32 11 27 34 10",
    "sg:postcode":"3570",
    "sg:province":"Limburg",
    "sg:tags":[
        "-",
        "offset"
    ],
    "wof:name":"Martens L",
    "wof:placetype":"venue"
},
  "geometry": {"coordinates":[5.3139081001,50.8843841553],"type":"Point"}
}