{
  "type": "Feature",
  "properties": {
    "iso:country":"BE",
    "sg:address":"Assestraat 42",
    "sg:city":"Herzele (steenhuize-wijnhuize)",
    "sg:classifiers":[
        {
            "category":"Professional",
            "subcategory":"Lawyer & Legal Services",
            "type":"Services"
        }
    ],
    "sg:phone":"+32 54 50 11 70",
    "sg:postcode":"9550",
    "sg:province":"Oost-Vlaanderen",
    "wof:name":"Van De Putte Silvie",
    "wof:placetype":"venue"
},
  "geometry": {"coordinates":[3.8597540855,50.8384628296],"type":"Point"}
}