{
  "type": "Feature",
  "properties": {
    "iso:country":"BE",
    "sg:address":"Neerstraat 44",
    "sg:city":"Haacht",
    "sg:orig_category":"Travaux de pl\u00e2trage",
    "sg:phone":"+32 16 60 25 67",
    "sg:postcode":"3150",
    "sg:province":"Vlaams-Brabant",
    "wof:name":"Aerts",
    "wof:placetype":"venue"
},
  "geometry": {"coordinates":[4.6286978722,50.9612693787],"type":"Point"}
}