{
  "type": "Feature",
  "properties": {
    "addr:full":"Avenue Du Globe 16 Vorst/forest Bruxelles-Capitale 1190",
    "addr:housenumber":"16",
    "addr:postcode":"1190",
    "addr:street":"Avenue Du Globe;/ Forest",
    "iso:country":"BE",
    "sg:address":"Avenue Du Globe 16",
    "sg:city":"Vorst/forest",
    "sg:orig_category":"Imprimeries and copyshops",
    "sg:phone":"+32 2 343 57 87",
    "sg:postcode":"1190",
    "sg:province":"Bruxelles-Capitale",
    "wof:name":"Copy Service Center",
    "wof:placetype":"venue"
},
  "geometry": {"coordinates":[4.3251948357,50.8096237183],"type":"Point"}
}