{
  "type": "Feature",
  "properties": {
    "addr:full":"Torense Weg 1 Stabroek Antwerpen 2940",
    "addr:housenumber":"1",
    "addr:postcode":"2940",
    "addr:street":"Torense Weg",
    "iso:country":"BE",
    "sg:address":"Torense Weg 1",
    "sg:city":"Stabroek",
    "sg:classifiers":[
        {
            "category":"Building & Trades",
            "subcategory":"Landscaping Services",
            "type":"Services"
        }
    ],
    "sg:phone":"+32 3 568 97 50",
    "sg:postcode":"2940",
    "sg:province":"Antwerpen",
    "sg:tags":[
        "gardening",
        "garden",
        "maintenance"
    ],
    "wof:name":"Eyking Jan",
    "wof:placetype":"venue"
},
  "geometry": {"coordinates":[4.3440070152,51.3410758972],"type":"Point"}
}