{
  "type": "Feature",
  "properties": {
    "iso:country":"BE",
    "sg:address":"Bostsestraat 49 Box 1",
    "sg:city":"Tienen",
    "sg:classifiers":[
        {
            "category":"Health Services",
            "subcategory":"Doctor",
            "type":"Services"
        }
    ],
    "sg:phone":"+32 16 82 04 44",
    "sg:postcode":"3300",
    "sg:province":"Vlaams-Brabant",
    "sg:tags":[
        "medicinephysicians",
        "surgeon"
    ],
    "wof:name":"Dewit C",
    "wof:placetype":"venue"
},
  "geometry": {"coordinates":[4.9401659966,50.8018569946],"type":"Point"}
}