{
  "type": "Feature",
  "properties": {
    "iso:country":"BE",
    "sg:address":"Avenue Comte De Namur 22",
    "sg:city":"Wavre",
    "sg:classifiers":[
        {
            "category":"Cafe",
            "type":"Food & Drink"
        }
    ],
    "sg:phone":"+32 10 22 88 28",
    "sg:postcode":"1300",
    "sg:province":"Brabant Wallon",
    "sg:tags":[
        "caf\u00e9s"
    ],
    "wof:name":"Roger Sleutel",
    "wof:placetype":"venue"
},
  "geometry": {"coordinates":[4.6287121773,50.7161865234],"type":"Point"}
}