{
  "type": "Feature",
  "properties": {
    "iso:country":"BE",
    "sg:address":"Oostendestraat 80",
    "sg:city":"Diksmuide",
    "sg:orig_category":"Herstellingen and onderhoud van auto's",
    "sg:phone":"+32 51 50 40 82",
    "sg:postcode":"8600",
    "sg:province":"West-Vlaanderen",
    "wof:name":"Garage Geert Delanghe",
    "wof:placetype":"venue"
},
  "geometry": {"coordinates":[2.865983963,51.0381965637],"type":"Point"}
}