{
  "type": "Feature",
  "properties": {
    "addr:full":"Schoolstraat 14 Kortenaken Vlaams-Brabant 3470",
    "addr:housenumber":"14",
    "addr:postcode":"3470",
    "addr:street":"Schoolstraat",
    "iso:country":"BE",
    "sg:address":"Schoolstraat 14",
    "sg:city":"Kortenaken",
    "sg:orig_category":"Enseignement maternel and primaire",
    "sg:phone":"+32 11 58 84 79",
    "sg:postcode":"3470",
    "sg:province":"Vlaams-Brabant",
    "wof:name":"Vrije Kleuterschool",
    "wof:placetype":"venue"
},
  "geometry": {"coordinates":[5.0607018471,50.9075279236],"type":"Point"}
}