{
  "type": "Feature",
  "properties": {
    "addr:full":"Philipslaan 32 Leuven Vlaams-Brabant 3000",
    "addr:housenumber":"32",
    "addr:postcode":"3000",
    "addr:street":"Philipslaan",
    "iso:country":"BE",
    "sg:address":"Philipslaan 32",
    "sg:city":"Leuven",
    "sg:classifiers":[
        {
            "category":"Health Services",
            "subcategory":"Medical Lab",
            "type":"Services"
        }
    ],
    "sg:phone":"+32 16 25 68 95",
    "sg:postcode":"3000",
    "sg:province":"Vlaams-Brabant",
    "sg:tags":[
        "laboratory",
        "dental"
    ],
    "wof:name":"Ortho Labo J Billen",
    "wof:placetype":"venue"
},
  "geometry": {"coordinates":[4.7300319672,50.8665809631],"type":"Point"}
}