{
  "type": "Feature",
  "properties": {
    "addr:full":"Brechtsesteenweg 200 Malle Antwerpen 2390",
    "addr:housenumber":"200",
    "addr:postcode":"2390",
    "addr:street":"Brechtsesteenweg",
    "iso:country":"BE",
    "sg:address":"Brechtsesteenweg 200",
    "sg:city":"Malle",
    "sg:orig_category":"Eleveurs de bovins",
    "sg:phone":"+32 3 312 12 88",
    "sg:postcode":"2390",
    "sg:province":"Antwerpen",
    "wof:name":"Frans Haest",
    "wof:placetype":"venue"
},
  "geometry": {"coordinates":[4.6826510429,51.3120727539],"type":"Point"}
}