{
  "type": "Feature",
  "properties": {
    "addr:full":"De Judestraat 3 Knokke-heist West-Vlaanderen 8300",
    "addr:housenumber":"3",
    "addr:postcode":"8300",
    "addr:street":"Judestraat",
    "iso:country":"BE",
    "sg:address":"De Judestraat 3",
    "sg:city":"Knokke-heist",
    "sg:orig_category":"Kapsalons",
    "sg:phone":"+32 50 60 35 61",
    "sg:postcode":"8300",
    "sg:province":"West-Vlaanderen",
    "wof:name":"Coiffure Willy",
    "wof:placetype":"venue"
},
  "geometry": {"coordinates":[3.2903790474,51.3413696289],"type":"Point"}
}