{
  "type": "Feature",
  "properties": {
    "addr:full":"Pastorijstraat 18 Hoeselt Limburg 3730",
    "addr:housenumber":"18",
    "addr:postcode":"3730",
    "addr:street":"Pastorijstraat",
    "iso:country":"BE",
    "sg:address":"Pastorijstraat 18",
    "sg:city":"Hoeselt",
    "sg:classifiers":[
        {
            "category":"Professional",
            "subcategory":"Art Services",
            "type":"Services"
        }
    ],
    "sg:phone":"+32 12 23 29 85",
    "sg:postcode":"3730",
    "sg:province":"Limburg",
    "sg:tags":[
        "designer",
        "display"
    ],
    "wof:name":"Vanlessen J",
    "wof:placetype":"venue"
},
  "geometry": {"coordinates":[5.4925289154,50.8298187256],"type":"Point"}
}