{
  "type": "Feature",
  "properties": {
    "addr:full":"Schoolstraat 5 Kontich Antwerpen 2550",
    "addr:housenumber":"5",
    "addr:postcode":"2550",
    "addr:street":"Schoolstraat",
    "iso:country":"BE",
    "sg:address":"Schoolstraat 5",
    "sg:city":"Kontich",
    "sg:classifiers":[
        {
            "category":"Personal",
            "subcategory":"Beauty Salon",
            "type":"Services"
        }
    ],
    "sg:phone":"+32 3 457 24 67",
    "sg:postcode":"2550",
    "sg:province":"Antwerpen",
    "sg:tags":[
        "lady",
        "-",
        "hairdressing"
    ],
    "wof:name":"Yves",
    "wof:placetype":"venue"
},
  "geometry": {"coordinates":[4.4444241524,51.1365280151],"type":"Point"}
}