{
  "type": "Feature",
  "properties": {
    "addr:full":"Luikersteenweg 86 Hasselt Limburg 3500",
    "addr:housenumber":"86",
    "addr:postcode":"3500",
    "addr:street":"Luikersteenweg",
    "iso:country":"BE",
    "sg:address":"Luikersteenweg 86",
    "sg:city":"Hasselt",
    "sg:classifiers":[
        {
            "category":"Bakery",
            "type":"Food & Drink"
        }
    ],
    "sg:phone":"+32 11 22 12 76",
    "sg:postcode":"3500",
    "sg:province":"Limburg",
    "sg:tags":[
        "confectioner",
        "baker"
    ],
    "wof:name":"Hermans H",
    "wof:placetype":"venue"
},
  "geometry": {"coordinates":[5.3390088081,50.923992157],"type":"Point"}
}