{
  "type": "Feature",
  "properties": {
    "addr:full":"Route De Perwez 62 Eghez\u00e9e (liernu) Namur 5310",
    "addr:housenumber":"62",
    "addr:postcode":"5310",
    "addr:street":"Route De Perwez;Liernu",
    "iso:country":"BE",
    "sg:address":"Route De Perwez 62",
    "sg:city":"Eghez\u00e9e (liernu)",
    "sg:classifiers":[
        {
            "category":"Home & Garden",
            "subcategory":"Carpets & Floor Coverings",
            "type":"Retail Goods"
        }
    ],
    "sg:phone":"+32 81 65 71 69",
    "sg:postcode":"5310",
    "sg:province":"Namur",
    "sg:tags":[
        "tile"
    ],
    "wof:name":"Simon J",
    "wof:placetype":"venue"
},
  "geometry": {"coordinates":[4.8344950676,50.5816955566],"type":"Point"}
}