{
  "type": "Feature",
  "properties": {
    "iso:country":"BE",
    "sg:address":"Vredelaan 21-5",
    "sg:city":"Houthalen-helchteren (houthalen)",
    "sg:classifiers":[
        {
            "category":"Health Services",
            "subcategory":"Doctor",
            "type":"Services"
        }
    ],
    "sg:phone":"+32 11 60 13 64",
    "sg:postcode":"3530",
    "sg:province":"Limburg",
    "sg:tags":[
        "psychotherapist",
        "psychoanalyst"
    ],
    "wof:name":"Nizhoni",
    "wof:placetype":"venue"
},
  "geometry": {"coordinates":[5.3729820251,51.0319824219],"type":"Point"}
}