{
  "type": "Feature",
  "properties": {
    "addr:full":"Chauss\u00c9e D\u00b4alsemberg 85 Linkebeek Vlaams-Brabant 1630",
    "addr:housenumber":"85",
    "addr:postcode":"1630",
    "addr:street":"Chausse\u0301E D\u00b4Alsemberg",
    "iso:country":"BE",
    "sg:address":"Chauss\u00c9e D\u00b4alsemberg 85",
    "sg:city":"Linkebeek",
    "sg:orig_category":"Centres sportifs. Agences de voyages. Clubs de sport",
    "sg:phone":"+32 2 381 22 98",
    "sg:postcode":"1630",
    "sg:province":"Vlaams-Brabant",
    "wof:name":"Espace Sport",
    "wof:placetype":"venue"
},
  "geometry": {"coordinates":[4.3281621933,50.7731971741],"type":"Point"}
}