{
  "type": "Feature",
  "properties": {
    "addr:full":"Rue G\u00c9n\u00c9ral Leman 87 Charleroi Hainaut 6044",
    "addr:housenumber":"87",
    "addr:postcode":"6044",
    "addr:street":"Rue Ge\u0301Ne\u0301Ral Leman;Hainaut",
    "iso:country":"BE",
    "sg:address":"Rue G\u00c9n\u00c9ral Leman 87",
    "sg:city":"Charleroi",
    "sg:orig_category":"Instituts de beaut\u00e9",
    "sg:phone":"+32 71 45 06 27",
    "sg:postcode":"6044",
    "sg:province":"Hainaut",
    "wof:name":"Carole Spinelli",
    "wof:placetype":"venue"
},
  "geometry": {"coordinates":[4.3866591454,50.444278717],"type":"Point"}
}