{
  "type": "Feature",
  "properties": {
    "iso:country":"BE",
    "sg:address":"Turnhoutsebaan 161",
    "sg:city":"Kasterlee",
    "sg:classifiers":[
        {
            "category":"Shopping",
            "subcategory":"Clothing, Apparel, & Fashions",
            "type":"Retail Goods"
        }
    ],
    "sg:phone":"+32 14 85 90 71",
    "sg:postcode":"2460",
    "sg:province":"Antwerpen",
    "sg:tags":[
        "clothing",
        "-",
        "motorbike",
        "equipment"
    ],
    "wof:name":"Apex Racing",
    "wof:placetype":"venue"
},
  "geometry": {"coordinates":[4.9626970291,51.2530250549],"type":"Point"}
}