{
  "type": "Feature",
  "properties": {
    "addr:full":"Provinciestraat 62 Antwerpen Antwerpen 2018",
    "addr:housenumber":"62",
    "addr:postcode":"2018",
    "addr:street":"Provinciestraat",
    "iso:country":"BE",
    "sg:address":"Provinciestraat 62",
    "sg:city":"Antwerpen",
    "sg:classifiers":[
        {
            "category":"Professional",
            "subcategory":"Art Services",
            "type":"Services"
        }
    ],
    "sg:phone":"+32 3 295 02 31",
    "sg:postcode":"2018",
    "sg:province":"Antwerpen",
    "sg:tags":[
        "photographer"
    ],
    "wof:name":"Studio 62",
    "wof:placetype":"venue"
},
  "geometry": {"coordinates":[4.4260010719,51.2160453796],"type":"Point"}
}