{
  "type": "Feature",
  "properties": {
    "addr:full":"Chemin-sur-le-foy 6 Nassogne Luxembourg 6950",
    "addr:housenumber":"6",
    "addr:postcode":"6950",
    "addr:street":"Chemin-Sur-Le-Foy",
    "iso:country":"BE",
    "sg:address":"Chemin-sur-le-foy 6",
    "sg:city":"Nassogne",
    "sg:orig_category":"Dakwerken Installatie van houten of kunststof schrijnwerk MEUBELONTWERP AND -INSTALLATIE Meubelzaken",
    "sg:phone":"+32 84 34 44 66",
    "sg:postcode":"6950",
    "sg:province":"Luxembourg",
    "wof:name":"Cherbai",
    "wof:placetype":"venue"
},
  "geometry": {"coordinates":[5.341301918,50.1289215088],"type":"Point"}
}