{
  "type": "Feature",
  "properties": {
    "addr:full":"Aldringen 38 Burg-reuland/burg-reuland Li\u00e8ge 4791",
    "addr:housenumber":"38",
    "addr:postcode":"4791",
    "addr:street":"Aldringen",
    "iso:country":"BE",
    "sg:address":"Aldringen 38",
    "sg:city":"Burg-reuland/burg-reuland",
    "sg:orig_category":"Rundveehouders",
    "sg:phone":"+32 80 22 80 44",
    "sg:postcode":"4791",
    "sg:province":"Li\u00e8ge",
    "wof:name":"Ramscheidt",
    "wof:placetype":"venue"
},
  "geometry": {"coordinates":[6.0771751404,50.2173156738],"type":"Point"}
}