{
  "type": "Feature",
  "properties": {
    "addr:full":"Avenue Du Castel 58 Bruxelles (woluwe-saint-lambert) Bruxelles-Capitale 1200",
    "addr:housenumber":"58",
    "addr:postcode":"1200",
    "addr:street":"Avenue Du Castel",
    "iso:country":"BE",
    "sg:address":"Avenue Du Castel 58",
    "sg:city":"Bruxelles (woluwe-saint-lambert)",
    "sg:classifiers":[
        {
            "category":"Professional",
            "subcategory":"Accounting & Tax Preparation",
            "type":"Services"
        }
    ],
    "sg:phone":"+32 2 732 35 10",
    "sg:postcode":"1200",
    "sg:province":"Bruxelles-Capitale",
    "sg:tags":[
        "bookkeeper"
    ],
    "wof:name":"El Aissaoui A",
    "wof:placetype":"venue"
},
  "geometry": {"coordinates":[4.4117069244,50.8414993286],"type":"Point"}
}