{
  "type": "Feature",
  "properties": {
    "iso:country":"BE",
    "sg:address":"M Scheperslaan 165",
    "sg:city":"Heusden-zolder",
    "sg:orig_category":"Plantes and fleurs Gr",
    "sg:phone":"+32 11 53 33 47",
    "sg:postcode":"3550",
    "sg:province":"Limburg",
    "wof:name":"Cuppens J-l",
    "wof:placetype":"venue"
},
  "geometry": {"coordinates":[5.3470730782,51.0237159729],"type":"Point"}
}