{
  "type": "Feature",
  "properties": {
    "addr:full":"Hollange 14 Fauvillers Luxembourg 6637",
    "addr:housenumber":"14",
    "addr:postcode":"6637",
    "addr:street":"Hollange",
    "iso:country":"BE",
    "sg:address":"Hollange 14",
    "sg:city":"Fauvillers",
    "sg:orig_category":"Eleveurs de bovins",
    "sg:phone":"+32 61 26 68 78",
    "sg:postcode":"6637",
    "sg:province":"Luxembourg",
    "wof:name":"Gerard Francois-cornette",
    "wof:placetype":"venue"
},
  "geometry": {"coordinates":[5.6893129349,49.9086761475],"type":"Point"}
}