{
  "type": "Feature",
  "properties": {
    "addr:full":"Oranjestraat 44 Antwerpen Antwerpen 2060",
    "addr:housenumber":"44",
    "addr:postcode":"2060",
    "addr:street":"Oranjestraat",
    "iso:country":"BE",
    "sg:address":"Oranjestraat 44",
    "sg:city":"Antwerpen",
    "sg:classifiers":[
        {
            "category":"Real Estate",
            "subcategory":"Architect",
            "type":"Services"
        }
    ],
    "sg:phone":"+32 3 233 83 51",
    "sg:postcode":"2060",
    "sg:province":"Antwerpen",
    "wof:name":"Verdickt & Verdickt Architecten Bvba",
    "wof:placetype":"venue"
},
  "geometry": {"coordinates":[4.4206271172,51.2273178101],"type":"Point"}
}