{
  "type": "Feature",
  "properties": {
    "iso:country":"BE",
    "sg:address":"Nieuw Zeelandersstraat 13",
    "sg:city":"Mesen/messines",
    "sg:orig_category":"Plaatsen van vloer- and muurbekleding Schilders",
    "sg:phone":"+32 57 44 65 16",
    "sg:postcode":"8957",
    "sg:province":"West-Vlaanderen",
    "wof:name":"Frankie Slegers",
    "wof:placetype":"venue"
},
  "geometry": {"coordinates":[2.893996954,50.7616920471],"type":"Point"}
}