{
  "type": "Feature",
  "properties": {
    "iso:country":"BE",
    "sg:address":"Baron R. De Vironlaan 2",
    "sg:city":"Dilbeek",
    "sg:orig_category":"Artsen and specialisten",
    "sg:phone":"+32 2 463 22 66",
    "sg:postcode":"1700",
    "sg:province":"Vlaams-Brabant",
    "wof:name":"H. Opdebeeck",
    "wof:placetype":"venue"
},
  "geometry": {"coordinates":[4.2660207748,50.8480110168],"type":"Point"}
}