{
  "type": "Feature",
  "properties": {
    "iso:country":"BE",
    "sg:address":"August Michielsstraat 8",
    "sg:city":"Antwerpen",
    "sg:orig_category":"Centres de relaxation and bien-\u00eatre",
    "sg:phone":"+32 3 232 65 66",
    "sg:postcode":"2000",
    "sg:province":"Antwerpen",
    "wof:name":"Action Club \u00b4 T Eilandje",
    "wof:placetype":"venue"
},
  "geometry": {"coordinates":[4.4099478722,51.2314605713],"type":"Point"}
}