{
  "type": "Feature",
  "properties": {
    "iso:country":"BE",
    "sg:address":"Rue Haute 18",
    "sg:city":"Anhee",
    "sg:orig_category":"Installatie van houten of kunststof schrijnwerk",
    "sg:phone":"+32 71 79 60 66",
    "sg:postcode":"5537",
    "sg:province":"Namur",
    "wof:name":"Roger Collart",
    "wof:placetype":"venue"
},
  "geometry": {"coordinates":[4.7497940063,50.3186416626],"type":"Point"}
}