{
  "type": "Feature",
  "properties": {
    "addr:full":"Avenue De L'arm\u00c9e 63 Etterbeek Bruxelles-Capitale 1040",
    "addr:housenumber":"63",
    "addr:postcode":"1040",
    "addr:street":"Avenue De L'Arme \u0301E",
    "iso:country":"BE",
    "sg:address":"Avenue De L'arm\u00c9e 63",
    "sg:city":"Etterbeek",
    "sg:orig_category":"S\u00e9lection de personnel and placement",
    "sg:phone":"+32 2 735 81 40",
    "sg:postcode":"1040",
    "sg:province":"Bruxelles-Capitale",
    "wof:name":"Bureau Secretary Trust",
    "wof:placetype":"venue"
},
  "geometry": {"coordinates":[4.403441906,50.8357162476],"type":"Point"}
}