{
  "type": "Feature",
  "properties": {
    "addr:full":"Leeglandstraat 20 Zuienkerke West-Vlaanderen 8377",
    "addr:housenumber":"20",
    "addr:postcode":"8377",
    "addr:street":"Leeglandstraat",
    "iso:country":"BE",
    "sg:address":"Leeglandstraat 20",
    "sg:city":"Zuienkerke",
    "sg:classifiers":[
        {
            "category":"Building & Trades",
            "subcategory":"Landscaping Services",
            "type":"Services"
        }
    ],
    "sg:phone":"+32 50 31 16 50",
    "sg:postcode":"8377",
    "sg:province":"West-Vlaanderen",
    "sg:tags":[
        "gardening",
        "garden",
        "maintenance"
    ],
    "wof:name":"Van Ryckeghem F",
    "wof:placetype":"venue"
},
  "geometry": {"coordinates":[3.1868550777,51.2568359375],"type":"Point"}
}