{
  "type": "Feature",
  "properties": {
    "addr:full":"Meensesteenweg 330 Kortrijk West-Vlaanderen 8501",
    "addr:housenumber":"330",
    "addr:postcode":"8501",
    "addr:street":"Meensesteenweg",
    "iso:country":"BE",
    "sg:address":"Meensesteenweg 330",
    "sg:city":"Kortrijk",
    "sg:classifiers":[
        {
            "category":"Cafe",
            "type":"Food & Drink"
        }
    ],
    "sg:phone":"+32 56 37 49 42",
    "sg:postcode":"8501",
    "sg:province":"West-Vlaanderen",
    "sg:tags":[
        "caf\u00e9s"
    ],
    "wof:name":"Caf\u00c9 Au Centre",
    "wof:placetype":"venue"
},
  "geometry": {"coordinates":[3.2262780666,50.8232727051],"type":"Point"}
}