{
  "type": "Feature",
  "properties": {
    "addr:full":"Postbaan 22 Diest Vlaams-Brabant 3290",
    "addr:housenumber":"22",
    "addr:postcode":"3290",
    "addr:street":"Postbaan",
    "iso:country":"BE",
    "sg:address":"Postbaan 22",
    "sg:city":"Diest",
    "sg:orig_category":"Artsen and specialisten",
    "sg:phone":"+32 13 33 47 62",
    "sg:postcode":"3290",
    "sg:province":"Vlaams-Brabant",
    "wof:name":"Jean-pierre Gaekens",
    "wof:placetype":"venue"
},
  "geometry": {"coordinates":[5.0751261711,50.9962425232],"type":"Point"}
}