{
  "type": "Feature",
  "properties": {
    "addr:full":"Audenhovenlaan 36 Boortmeerbeek Vlaams-Brabant 3190",
    "addr:housenumber":"36",
    "addr:postcode":"3190",
    "addr:street":"Audenhovenlaan",
    "iso:country":"BE",
    "sg:address":"Audenhovenlaan 36",
    "sg:city":"Boortmeerbeek",
    "sg:orig_category":"Travaux de pl\u00e2trage",
    "sg:phone":"+32 15 51 59 37",
    "sg:postcode":"3190",
    "sg:province":"Vlaams-Brabant",
    "wof:name":"Oldyck En Zoon",
    "wof:placetype":"venue"
},
  "geometry": {"coordinates":[4.567471981,50.9800872803],"type":"Point"}
}