{
  "type": "Feature",
  "properties": {
    "addr:full":"Grote Markt 41 Sint-niklaas Oost-Vlaanderen 9100",
    "addr:housenumber":"41",
    "addr:postcode":"9100",
    "addr:street":"Grote Markt",
    "iso:country":"BE",
    "sg:address":"Grote Markt 41",
    "sg:city":"Sint-niklaas",
    "sg:classifiers":[
        {
            "category":"Cafe",
            "type":"Food & Drink"
        }
    ],
    "sg:phone":"+32 3 777 06 36",
    "sg:postcode":"9100",
    "sg:province":"Oost-Vlaanderen",
    "sg:tags":[
        "caf\u00e9s"
    ],
    "wof:name":"Muziek- En Theatercaf\u00c9 Hemelrijk",
    "wof:placetype":"venue"
},
  "geometry": {"coordinates":[4.1416501999,51.1638793945],"type":"Point"}
}