{
  "type": "Feature",
  "properties": {
    "iso:country":"BE",
    "sg:address":"Rue Jennay 112",
    "sg:city":"Gembloux-sur-orneau (isnes)",
    "sg:classifiers":[
        {
            "category":"Health Services",
            "subcategory":"Health Practitioner",
            "type":"Services"
        }
    ],
    "sg:phone":"+32 81 56 96 95",
    "sg:postcode":"5032",
    "sg:province":"Namur",
    "sg:tags":[
        "physiotherapist"
    ],
    "wof:name":"Demoulin A",
    "wof:placetype":"venue"
},
  "geometry": {"coordinates":[4.7385630608,50.5093421936],"type":"Point"}
}