{
  "type": "Feature",
  "properties": {
    "addr:full":"Avenue Winston Churchill 247 Bruxelles (uccle) Bruxelles-Capitale 1180",
    "addr:housenumber":"247",
    "addr:postcode":"1180",
    "addr:street":"Avenue Winston Churchill",
    "iso:country":"BE",
    "sg:address":"Avenue Winston Churchill 247",
    "sg:city":"Bruxelles (uccle)",
    "sg:classifiers":[
        {
            "category":"Real Estate",
            "subcategory":"Real Estate Services",
            "type":"Services"
        }
    ],
    "sg:phone":"+32 2 644 35 80",
    "sg:postcode":"1180",
    "sg:province":"Bruxelles-Capitale",
    "wof:name":"Bxl Foncier-paquet",
    "wof:placetype":"venue"
},
  "geometry": {"coordinates":[4.3669948578,50.8116836548],"type":"Point"}
}