{
  "type": "Feature",
  "properties": {
    "addr:full":"Zeedijk-duinbergen 197 Knokke-heist (heist-aan-zee) West-Vlaanderen 8301",
    "addr:housenumber":"197",
    "addr:postcode":"8301",
    "addr:street":"Knokke-Heist Heist-Aan-Zee West-Vlaanderen",
    "iso:country":"BE",
    "sg:address":"Zeedijk-duinbergen 197",
    "sg:city":"Knokke-heist (heist-aan-zee)",
    "sg:classifiers":[
        {
            "category":"Banks & Credit Unions",
            "subcategory":"Investment Brokerage",
            "type":"Services"
        }
    ],
    "sg:phone":"+32 50 51 51 13",
    "sg:postcode":"8301",
    "sg:province":"West-Vlaanderen",
    "sg:tags":[
        "-",
        "sale",
        "yachts",
        "accessory",
        "pleasure",
        "boat"
    ],
    "wof:name":"Sail 4 U",
    "wof:placetype":"venue"
},
  "geometry": {"coordinates":[3.2583398819,51.3447189331],"type":"Point"}
}