{
  "type": "Feature",
  "properties": {
    "addr:full":"Zeedijk-albertstrand 523 Knokke-heist West-Vlaanderen 8300",
    "addr:housenumber":"523",
    "addr:postcode":"8300",
    "addr:street":"Knokke-Heist West-Vlaanderen",
    "iso:country":"BE",
    "sg:address":"Zeedijk-albertstrand 523",
    "sg:city":"Knokke-heist",
    "sg:classifiers":[
        {
            "category":"Restaurant",
            "type":"Food & Drink"
        }
    ],
    "sg:phone":"+32 50 61 02 68",
    "sg:postcode":"8300",
    "sg:province":"West-Vlaanderen",
    "wof:name":"Calypso",
    "wof:placetype":"venue"
},
  "geometry": {"coordinates":[3.287694931,51.3467254639],"type":"Point"}
}