{
  "type": "Feature",
  "properties": {
    "addr:full":"Blockmansstraat 45-47 Kortenberg Vlaams-Brabant 3070",
    "addr:postcode":"45-47;3070",
    "addr:street":"Blockmansstraat",
    "iso:country":"BE",
    "sg:address":"Blockmansstraat 45-47",
    "sg:city":"Kortenberg",
    "sg:classifiers":[
        {
            "category":"Retail",
            "subcategory":"Auto Repair",
            "type":"Services"
        }
    ],
    "sg:phone":"+32 2 759 70 58",
    "sg:postcode":"3070",
    "sg:province":"Vlaams-Brabant",
    "sg:tags":[
        "garage"
    ],
    "wof:name":"Salens M. & Zn",
    "wof:placetype":"venue"
},
  "geometry": {"coordinates":[4.5404458046,50.8892173767],"type":"Point"}
}