{
  "type": "Feature",
  "properties": {
    "addr:full":"Kortrijkstraat 82 Box 1 Deinze Oost-Vlaanderen 9800",
    "addr:housenumber":"82;1",
    "addr:postcode":"9800",
    "addr:street":"Kortrijkstraat;Box",
    "iso:country":"BE",
    "sg:address":"Kortrijkstraat 82 Box 1",
    "sg:city":"Deinze",
    "sg:classifiers":[
        {
            "category":"Professional",
            "subcategory":"Credit Reporting & Collection",
            "type":"Services"
        }
    ],
    "sg:phone":"+32 9 386 56 99",
    "sg:postcode":"9800",
    "sg:province":"Oost-Vlaanderen",
    "sg:tags":[
        "bailiff"
    ],
    "wof:name":"Groffils I",
    "wof:placetype":"venue"
},
  "geometry": {"coordinates":[3.5275769234,50.9770278931],"type":"Point"}
}