{
  "type": "Feature",
  "properties": {
    "addr:full":"Avenue De La Basilique 15 P\u00e9ruwelz (bon-secours) Hainaut 7603",
    "addr:housenumber":"15",
    "addr:postcode":"7603",
    "addr:street":"Avenue De La Basilique",
    "iso:country":"BE",
    "sg:address":"Avenue De La Basilique 15",
    "sg:city":"P\u00e9ruwelz (bon-secours)",
    "sg:classifiers":[
        {
            "category":"Bakery",
            "type":"Food & Drink"
        }
    ],
    "sg:phone":"+32 69 77 40 10",
    "sg:postcode":"7603",
    "sg:province":"Hainaut",
    "sg:tags":[
        "confectioner",
        "baker"
    ],
    "wof:name":"Ovidias Pralines",
    "wof:placetype":"venue"
},
  "geometry": {"coordinates":[3.6060919762,50.4979629517],"type":"Point"}
}