{
  "type": "Feature",
  "properties": {
    "addr:full":"Gotemstraat 30 Borgloon Limburg 3840",
    "addr:housenumber":"30",
    "addr:postcode":"3840",
    "addr:street":"Gotemstraat",
    "iso:country":"BE",
    "sg:address":"Gotemstraat 30",
    "sg:city":"Borgloon",
    "sg:orig_category":"Fruitteelt",
    "sg:phone":"+32 12 74 67 78",
    "sg:postcode":"3840",
    "sg:province":"Limburg",
    "wof:name":"Bert Claessens",
    "wof:placetype":"venue"
},
  "geometry": {"coordinates":[5.3441700935,50.8012466431],"type":"Point"}
}