{
  "type": "Feature",
  "properties": {
    "iso:country":"BE",
    "sg:address":"Chauss\u00e9e De Wavre 541",
    "sg:city":"Grez-doiceau",
    "sg:classifiers":[
        {
            "category":"Professional",
            "subcategory":"Employment Agencies",
            "type":"Services"
        }
    ],
    "sg:phone":"+32 10 84 05 62",
    "sg:postcode":"1390",
    "sg:province":"Brabant Wallon",
    "sg:tags":[
        "market",
        "research"
    ],
    "wof:name":"Dixit Informations",
    "wof:placetype":"venue"
},
  "geometry": {"coordinates":[4.6452860832,50.7300567627],"type":"Point"}
}