{
  "type": "Feature",
  "properties": {
    "addr:full":"Pieter Breughelstraat 30 Roeselare (rumbeke) West-Vlaanderen 8800",
    "addr:housenumber":"30",
    "addr:postcode":"8800",
    "addr:street":"Pieter Breughelstraat",
    "iso:country":"BE",
    "sg:address":"Pieter Breughelstraat 30",
    "sg:city":"Roeselare (rumbeke)",
    "sg:classifiers":[
        {
            "category":"Social Services",
            "subcategory":"Job Training",
            "type":"Services"
        }
    ],
    "sg:phone":"+32 56 57 90 37",
    "sg:postcode":"8800",
    "sg:province":"West-Vlaanderen",
    "sg:tags":[
        "personnel"
    ],
    "wof:name":"Paramedical Assistance",
    "wof:placetype":"venue"
},
  "geometry": {"coordinates":[3.1643741131,50.9264640808],"type":"Point"}
}