{
  "type": "Feature",
  "properties": {
    "addr:full":"Braamakkerstraat 93 Deerlijk West-Vlaanderen 8540",
    "addr:housenumber":"93",
    "addr:postcode":"8540",
    "addr:street":"Braamakkerstraat",
    "iso:country":"BE",
    "sg:address":"Braamakkerstraat 93",
    "sg:city":"Deerlijk",
    "sg:orig_category":"Sportclubs",
    "sg:phone":"+32 56 77 89 81",
    "sg:postcode":"8540",
    "sg:province":"West-Vlaanderen",
    "wof:name":"J.c. Deerlijk",
    "wof:placetype":"venue"
},
  "geometry": {"coordinates":[3.355686903,50.8475227356],"type":"Point"}
}