{
  "type": "Feature",
  "properties": {
    "addr:full":"Rue De Z\u00f4ne 130 Charleroi (marchienne-au-pont) Hainaut 6030",
    "addr:housenumber":"130",
    "addr:postcode":"6030",
    "addr:street":"Rue De Zo\u0302Ne",
    "iso:country":"BE",
    "sg:address":"Rue De Z\u00f4ne 130",
    "sg:city":"Charleroi (marchienne-au-pont)",
    "sg:classifiers":[
        {
            "category":"Communications",
            "subcategory":"Television Station",
            "type":"Services"
        }
    ],
    "sg:phone":"+32 71 51 10 02",
    "sg:postcode":"6030",
    "sg:province":"Hainaut",
    "sg:tags":[
        "report",
        "video"
    ],
    "wof:name":"Cine Dream",
    "wof:placetype":"venue"
},
  "geometry": {"coordinates":[4.3978500366,50.3973999023],"type":"Point"}
}