{
  "type": "Feature",
  "properties": {
    "iso:country":"BE",
    "sg:address":"Kontichsesteenweg 47",
    "sg:city":"Aartselaar",
    "sg:classifiers":[
        {
            "category":"Cafe",
            "type":"Food & Drink"
        }
    ],
    "sg:phone":"+32 3 877 25 75",
    "sg:postcode":"2630",
    "sg:province":"Antwerpen",
    "sg:tags":[
        "snack-bars"
    ],
    "wof:name":"De Snack",
    "wof:placetype":"venue"
},
  "geometry": {"coordinates":[4.389649868,51.1441726685],"type":"Point"}
}