{
  "type": "Feature",
  "properties": {
    "addr:full":"Rue De Lausanne 41 Bruxelles (saint-gilles) Bruxelles-Capitale 1060",
    "addr:housenumber":"41",
    "addr:postcode":"1060",
    "addr:street":"Rue De Lausanne",
    "iso:country":"BE",
    "sg:address":"Rue De Lausanne 41",
    "sg:city":"Bruxelles (saint-gilles)",
    "sg:classifiers":[
        {
            "category":"Real Estate",
            "subcategory":"Architect",
            "type":"Services"
        }
    ],
    "sg:phone":"+32 2 538 08 05",
    "sg:postcode":"1060",
    "sg:province":"Bruxelles-Capitale",
    "wof:name":"Hollevoet N",
    "wof:placetype":"venue"
},
  "geometry": {"coordinates":[4.3522200584,50.8294830322],"type":"Point"}
}