{
  "type": "Feature",
  "properties": {
    "iso:country":"BE",
    "sg:address":"Fonteinstraat 23",
    "sg:city":"Sint-genesius-rode/rhode-saint-genese",
    "sg:orig_category":"Baby- and kinderkleding",
    "sg:phone":"+32 2 380 09 65",
    "sg:postcode":"1640",
    "sg:province":"Vlaams-Brabant",
    "wof:name":"Huis Caramel",
    "wof:placetype":"venue"
},
  "geometry": {"coordinates":[4.3461799622,50.7439079285],"type":"Point"}
}