{
  "type": "Feature",
  "properties": {
    "addr:full":"Ruiterslaan 29 Zoersel (halle) Antwerpen 2980",
    "addr:housenumber":"29",
    "addr:postcode":"2980",
    "addr:street":"Ruiterslaan",
    "iso:country":"BE",
    "sg:address":"Ruiterslaan 29",
    "sg:city":"Zoersel (halle)",
    "sg:classifiers":[
        {
            "category":"Professional",
            "subcategory":"Testing Lab",
            "type":"Services"
        }
    ],
    "sg:phone":"+32 3 385 36 85",
    "sg:postcode":"2980",
    "sg:province":"Antwerpen",
    "sg:tags":[
        "laboratory",
        "-",
        "machines",
        "apparatus",
        "supply"
    ],
    "wof:name":"Immunosource Bvba",
    "wof:placetype":"venue"
},
  "geometry": {"coordinates":[4.713435173,51.269985199],"type":"Point"}
}