{
  "type": "Feature",
  "properties": {
    "iso:country":"BE",
    "sg:address":"Kleine Bogaardestraat 13",
    "sg:city":"Maldegem",
    "sg:orig_category":"Woningbouw",
    "sg:phone":"+32 50 71 46 51",
    "sg:postcode":"9990",
    "sg:province":"Oost-Vlaanderen",
    "wof:name":"Danny Van Hecke",
    "wof:placetype":"venue"
},
  "geometry": {"coordinates":[3.4413659573,51.2084388733],"type":"Point"}
}