{
  "type": "Feature",
  "properties": {
    "iso:country":"BE",
    "sg:address":"Lichterveldestraat 37",
    "sg:city":"Wingene",
    "sg:orig_category":"Boekhouders",
    "sg:phone":"+32 51 61 39 93",
    "sg:postcode":"8750",
    "sg:province":"West-Vlaanderen",
    "wof:name":"Pol Van Tieghem",
    "wof:placetype":"venue"
},
  "geometry": {"coordinates":[3.2074019909,51.0371856689],"type":"Point"}
}