{
  "type": "Feature",
  "properties": {
    "iso:country":"BE",
    "sg:address":"Gentseheerweg 77-79",
    "sg:city":"Izegem",
    "sg:classifiers":[
        {
            "category":"Travel",
            "subcategory":"Bed & Breakfast",
            "type":"Entertainment"
        }
    ],
    "sg:phone":"+32 51 30 10 77",
    "sg:postcode":"8870",
    "sg:province":"West-Vlaanderen",
    "sg:tags":[
        "ladder"
    ],
    "wof:name":"Martin Ladderfabriek Nv",
    "wof:placetype":"venue"
},
  "geometry": {"coordinates":[3.2332201004,50.9170455933],"type":"Point"}
}