{
  "type": "Feature",
  "properties": {
    "iso:country":"BE",
    "sg:address":"Wingene Steenweg 12",
    "sg:city":"Beernem",
    "sg:orig_category":"Fitnesscentra",
    "sg:phone":"+32 50 79 13 87",
    "sg:postcode":"8730",
    "sg:province":"West-Vlaanderen",
    "wof:name":"Life Style",
    "wof:placetype":"venue"
},
  "geometry": {"coordinates":[3.3277211189,51.1262588501],"type":"Point"}
}