{
  "type": "Feature",
  "properties": {
    "addr:full":"Donk 1 Lier Antwerpen 2500",
    "addr:housenumber":"1",
    "addr:postcode":"2500",
    "addr:street":"Donk",
    "iso:country":"BE",
    "sg:address":"Donk 1",
    "sg:city":"Lier",
    "sg:classifiers":[
        {
            "category":"Retail",
            "subcategory":"Repair Shop",
            "type":"Services"
        }
    ],
    "sg:phone":"+32 3 488 16 39",
    "sg:postcode":"2500",
    "sg:province":"Antwerpen",
    "wof:name":"H Abdel Aziz",
    "wof:placetype":"venue"
},
  "geometry": {"coordinates":[4.5539178848,51.140171051],"type":"Point"}
}