{
  "type": "Feature",
  "properties": {
    "addr:full":"Oorlogskruisenlaan 238b5 Brussel/bruxelles Bruxelles-Capitale 1120",
    "addr:housenumber":"238b5",
    "addr:postcode":"1120",
    "addr:street":"Oorlogskruisenlaan;/",
    "iso:country":"BE",
    "sg:address":"Oorlogskruisenlaan 238b5",
    "sg:city":"Brussel/bruxelles",
    "sg:orig_category":"Beheer onroerend goed",
    "sg:phone":"+32 2 262 13 05",
    "sg:postcode":"1120",
    "sg:province":"Bruxelles-Capitale",
    "wof:name":"Marcel Donkerwolcke",
    "wof:placetype":"venue"
},
  "geometry": {"coordinates":[4.3869628906,50.8927955627],"type":"Point"}
}