{
  "type": "Feature",
  "properties": {
    "addr:full":"Avenue Coghen 214 Ukkel/uccle Bruxelles-Capitale 1180",
    "addr:housenumber":"214",
    "addr:postcode":"1180",
    "addr:street":"Avenue Coghen;/",
    "iso:country":"BE",
    "sg:address":"Avenue Coghen 214",
    "sg:city":"Ukkel/uccle",
    "sg:orig_category":"Avocats and conseillers juridiques",
    "sg:phone":"+32 2 345 92 62",
    "sg:postcode":"1180",
    "sg:province":"Bruxelles-Capitale",
    "wof:name":"Lieve Minten",
    "wof:placetype":"venue"
},
  "geometry": {"coordinates":[4.3407459259,50.8068504333],"type":"Point"}
}