{
  "type": "Feature",
  "properties": {
    "addr:full":"Gorsemweg 50 Sint-truiden Limburg 3800",
    "addr:housenumber":"50",
    "addr:postcode":"3800",
    "addr:street":"Gorsemweg",
    "iso:country":"BE",
    "sg:address":"Gorsemweg 50",
    "sg:city":"Sint-truiden",
    "sg:classifiers":[
        {
            "category":"Health Services",
            "subcategory":"Doctor",
            "type":"Services"
        }
    ],
    "sg:phone":"+32 11 68 56 18",
    "sg:postcode":"3800",
    "sg:province":"Limburg",
    "sg:tags":[
        "medicinephysicians",
        "surgeon"
    ],
    "wof:name":"Colson M",
    "wof:placetype":"venue"
},
  "geometry": {"coordinates":[5.1790747643,50.819858551],"type":"Point"}
}