{
  "type": "Feature",
  "properties": {
    "iso:country":"BE",
    "sg:address":"Rue De Naugimont 6",
    "sg:city":"Floreffe",
    "sg:orig_category":"Pisciculture",
    "sg:phone":"+32 81 44 61 74",
    "sg:postcode":"5150",
    "sg:province":"Namur",
    "wof:name":"Sonia Loardi",
    "wof:placetype":"venue"
},
  "geometry": {"coordinates":[4.7556171417,50.4205741882],"type":"Point"}
}