{
  "type": "Feature",
  "properties": {
    "addr:full":"Rue De La Gayolle 116 Dour Hainaut 7370",
    "addr:housenumber":"116",
    "addr:postcode":"7370",
    "addr:street":"Rue De La Gayolle;Hainaut",
    "iso:country":"BE",
    "sg:address":"Rue De La Gayolle 116",
    "sg:city":"Dour",
    "sg:orig_category":"Diverse bouwafwerking and reiniging",
    "sg:phone":"+32 65 65 28 20",
    "sg:postcode":"7370",
    "sg:province":"Hainaut",
    "wof:name":"Angelo D'arcangelo",
    "wof:placetype":"venue"
},
  "geometry": {"coordinates":[3.7915511131,50.3908958435],"type":"Point"}
}