{
  "type": "Feature",
  "properties": {
    "iso:country":"BE",
    "sg:address":"Rue L\u00e9opold Courouble 26",
    "sg:city":"Bruxelles (schaerbeek)",
    "sg:orig_category":"Non-Classified Establishments",
    "sg:phone":"+32 2 241 93 54",
    "sg:postcode":"1030",
    "sg:province":"Bruxelles-Capitale",
    "wof:name":"Delta Vogue",
    "wof:placetype":"venue"
},
  "geometry": {"coordinates":[4.3795590401,50.8714332581],"type":"Point"}
}