{
  "type": "Feature",
  "properties": {
    "addr:full":"Stationsstraat 1 Deinze Oost-Vlaanderen 9800",
    "addr:housenumber":"1",
    "addr:postcode":"9800",
    "addr:street":"Stationsstraat",
    "iso:country":"BE",
    "sg:address":"Stationsstraat 1",
    "sg:city":"Deinze",
    "sg:orig_category":"Textiel Verlichting and huishoudartikelen",
    "sg:phone":"+32 9 386 13 56",
    "sg:postcode":"9800",
    "sg:province":"Oost-Vlaanderen",
    "wof:name":"Huis Robbens",
    "wof:placetype":"venue"
},
  "geometry": {"coordinates":[3.5309119225,50.9790153503],"type":"Point"}
}