{
  "type": "Feature",
  "properties": {
    "iso:country":"BE",
    "sg:address":"Bochtenstraat 26",
    "sg:city":"Rijkevorsel",
    "sg:orig_category":"Agences de publicit\u00e9",
    "sg:phone":"+32 3 314 92 82",
    "sg:postcode":"2310",
    "sg:province":"Antwerpen",
    "wof:name":"Sign Design",
    "wof:placetype":"venue"
},
  "geometry": {"coordinates":[4.7628221512,51.3475112915],"type":"Point"}
}