{
  "type": "Feature",
  "properties": {
    "iso:country":"BE",
    "sg:address":"Lattenklieversstraat 93",
    "sg:city":"Beernem (sint-joris)",
    "sg:classifiers":[
        {
            "category":"Health Services",
            "subcategory":"Health Practitioner",
            "type":"Services"
        }
    ],
    "sg:phone":"+32 50 78 12 13",
    "sg:postcode":"8730",
    "sg:province":"West-Vlaanderen",
    "sg:tags":[
        "physiotherapist"
    ],
    "wof:name":"De Vooght Jan",
    "wof:placetype":"venue"
},
  "geometry": {"coordinates":[3.3638269901,51.1274223328],"type":"Point"}
}