{
  "type": "Feature",
  "properties": {
    "iso:country":"BE",
    "sg:address":"Aarschotsestraat 67",
    "sg:city":"Vilvoorde",
    "sg:orig_category":"Vertalers and tolken",
    "sg:phone":"+32 2 252 23 40",
    "sg:postcode":"1800",
    "sg:province":"Vlaams-Brabant",
    "wof:name":"Vertalingen Kathleen Kempeneers",
    "wof:placetype":"venue"
},
  "geometry": {"coordinates":[4.4523777962,50.9250564575],"type":"Point"}
}