{
  "type": "Feature",
  "properties": {
    "iso:country":"BE",
    "sg:address":"Herentalse Steenweg 78",
    "sg:city":"Herenthout",
    "sg:classifiers":[
        {
            "category":"Wholesale",
            "subcategory":"Medical Equipment & Supplies",
            "type":"Manufacturing & Wholesale Goods"
        }
    ],
    "sg:phone":"+32 14 50 19 54",
    "sg:postcode":"2270",
    "sg:province":"Antwerpen",
    "sg:tags":[
        "theatrical"
    ],
    "wof:name":"Lestacon Bvba",
    "wof:placetype":"venue"
},
  "geometry": {"coordinates":[4.7865548134,51.1456184387],"type":"Point"}
}