{
  "type": "Feature",
  "properties": {
    "addr:full":"Acacialaan 79 Lochristi Oost-Vlaanderen 9080",
    "addr:housenumber":"79",
    "addr:postcode":"9080",
    "addr:street":"Acacialaan",
    "iso:country":"BE",
    "sg:address":"Acacialaan 79",
    "sg:city":"Lochristi",
    "sg:classifiers":[
        {
            "category":"Manufacturing",
            "subcategory":"Textiles",
            "type":"Manufacturing & Wholesale Goods"
        }
    ],
    "sg:phone":"+32 9 356 90 57",
    "sg:postcode":"9080",
    "sg:province":"Oost-Vlaanderen",
    "wof:name":"Christine Geerardyn",
    "wof:placetype":"venue"
},
  "geometry": {"coordinates":[3.8224411011,51.0859565735],"type":"Point"}
}