{
  "type": "Feature",
  "properties": {
    "addr:full":"Generaal Henrystraat 2 Etterbeek/etterbeek Bruxelles-Capitale 1040",
    "addr:housenumber":"2",
    "addr:postcode":"1040",
    "addr:street":"Generaal Henrystraat",
    "iso:country":"BE",
    "sg:address":"Generaal Henrystraat 2",
    "sg:city":"Etterbeek/etterbeek",
    "sg:orig_category":"Herstellingswinkels voor diverse persoonlijke and huishoudartikelen Installatie van metalen schrijnw",
    "sg:phone":"+32 2 735 57 26",
    "sg:postcode":"1040",
    "sg:province":"Bruxelles-Capitale",
    "wof:name":"Legr\u00c8ve & Fils",
    "wof:placetype":"venue"
},
  "geometry": {"coordinates":[4.3944621086,50.831943512],"type":"Point"}
}