{
  "type": "Feature",
  "properties": {
    "iso:country":"BE",
    "sg:address":"Guilleminlaan 40",
    "sg:city":"Geraardsbergen",
    "sg:orig_category":"Landmeters",
    "sg:phone":"+32 54 41 87 33",
    "sg:postcode":"9500",
    "sg:province":"Oost-Vlaanderen",
    "wof:name":"Marc Van Der Putten",
    "wof:placetype":"venue"
},
  "geometry": {"coordinates":[3.8906700611,50.7684440613],"type":"Point"}
}