{
  "type": "Feature",
  "properties": {
    "addr:full":"Cantersteen 7b24 Brussel/bruxelles Bruxelles-Capitale 1000",
    "addr:housenumber":"7b24",
    "addr:postcode":"1000",
    "addr:street":"Cantersteen;/",
    "iso:country":"BE",
    "sg:address":"Cantersteen 7b24",
    "sg:city":"Brussel/bruxelles",
    "sg:classifiers":[
        {
            "category":"Restaurant",
            "type":"Food & Drink"
        }
    ],
    "sg:phone":"+32 2 527 44 60",
    "sg:postcode":"1000",
    "sg:province":"Bruxelles-Capitale",
    "wof:name":"Tearoom Sunday",
    "wof:placetype":"venue"
},
  "geometry": {"coordinates":[4.3573942184,50.8450126648],"type":"Point"}
}