{
  "type": "Feature",
  "properties": {
    "iso:country":"BE",
    "sg:address":"Liege Airport",
    "sg:city":"Grace-hollogne",
    "sg:orig_category":"Location de voitures",
    "sg:phone":"+32 4 234 23 30",
    "sg:postcode":"4460",
    "sg:province":"Li\u00e8ge",
    "wof:name":"Royal Tours",
    "wof:placetype":"venue"
},
  "geometry": {"coordinates":[5.4639701843,50.6461410522],"type":"Point"}
}