{
  "type": "Feature",
  "properties": {
    "addr:full":"Avenue De Messidor 298 Ukkel/uccle Bruxelles-Capitale 1180",
    "addr:housenumber":"298",
    "addr:postcode":"1180",
    "addr:street":"Avenue De Messidor;/",
    "iso:country":"BE",
    "sg:address":"Avenue De Messidor 298",
    "sg:city":"Ukkel/uccle",
    "sg:orig_category":"Avocats and conseillers juridiques",
    "sg:phone":"+32 2 343 44 93",
    "sg:postcode":"1180",
    "sg:province":"Bruxelles-Capitale",
    "wof:name":"J.j. Verhulsel",
    "wof:placetype":"venue"
},
  "geometry": {"coordinates":[4.351785183,50.8115768433],"type":"Point"}
}