{
  "type": "Feature",
  "properties": {
    "addr:full":"Iveldingen 39 Amel Li\u00e8ge 4770",
    "addr:housenumber":"39",
    "addr:postcode":"4770",
    "addr:street":"Iveldingen",
    "iso:country":"BE",
    "sg:address":"Iveldingen 39",
    "sg:city":"Amel",
    "sg:classifiers":[
        {
            "category":"Home & Garden",
            "subcategory":"Garden Supply",
            "type":"Retail Goods"
        }
    ],
    "sg:phone":"+32 80 34 08 24",
    "sg:postcode":"4770",
    "sg:province":"Li\u00e8ge",
    "sg:tags":[
        "machine",
        "agricultural",
        "-"
    ],
    "wof:name":"Michels Sprl",
    "wof:placetype":"venue"
},
  "geometry": {"coordinates":[6.1689629555,50.3543167114],"type":"Point"}
}