{
  "type": "Feature",
  "properties": {
    "addr:full":"Place Albert Ier 42 Froidchapelle Hainaut 6440",
    "addr:housenumber":"42",
    "addr:postcode":"6440",
    "addr:street":"Place Albert Ier",
    "iso:country":"BE",
    "sg:address":"Place Albert Ier 42",
    "sg:city":"Froidchapelle",
    "sg:orig_category":"R\u00e9parations d'appareils \u00e9lectrom\u00e9nagers. Electrom\u00e9nager, t\u00e9l\u00e9visions and radios",
    "sg:phone":"+32 60 41 10 16",
    "sg:postcode":"6440",
    "sg:province":"Hainaut",
    "wof:name":"Jacquemain",
    "wof:placetype":"venue"
},
  "geometry": {"coordinates":[4.329679966,50.15102005],"type":"Point"}
}