{
  "type": "Feature",
  "properties": {
    "addr:full":"Rue D'erbaut 32 Lens Hainaut 7870",
    "addr:housenumber":"32",
    "addr:postcode":"7870",
    "addr:street":"Rue D'Erbaut",
    "iso:country":"BE",
    "sg:address":"Rue D'erbaut 32",
    "sg:city":"Lens",
    "sg:classifiers":[
        {
            "category":"Health Services",
            "subcategory":"Doctor",
            "type":"Services"
        }
    ],
    "sg:phone":"+32 65 22 94 86",
    "sg:postcode":"7870",
    "sg:province":"Hainaut",
    "sg:tags":[
        "psychotherapist",
        "psychoanalyst"
    ],
    "wof:name":"Penasse M-a",
    "wof:placetype":"venue"
},
  "geometry": {"coordinates":[3.8828990459,50.5455436707],"type":"Point"}
}