{
  "type": "Feature",
  "properties": {
    "iso:country":"BE",
    "sg:address":"Kortrijksesteenweg 707",
    "sg:city":"Gent",
    "sg:orig_category":"V\u00e9t\u00e9rinaires",
    "sg:phone":"+32 9 222 33 22",
    "sg:postcode":"9000",
    "sg:province":"Oost-Vlaanderen",
    "wof:name":"Chantal Finjaer",
    "wof:placetype":"venue"
},
  "geometry": {"coordinates":[3.7123351097,51.0293731689],"type":"Point"}
}