{
  "type": "Feature",
  "properties": {
    "addr:full":"Schapenstraat 98 Leuven Vlaams-Brabant 3000",
    "addr:housenumber":"98",
    "addr:postcode":"3000",
    "addr:street":"Schapenstraat",
    "iso:country":"BE",
    "sg:address":"Schapenstraat 98",
    "sg:city":"Leuven",
    "sg:classifiers":[
        {
            "category":"Education",
            "subcategory":"School",
            "type":"Public Place"
        }
    ],
    "sg:phone":"+32 16 22 79 69",
    "sg:postcode":"3000",
    "sg:province":"Vlaams-Brabant",
    "sg:tags":[
        "secondary"
    ],
    "wof:name":"Windekind B.u.s.o.",
    "wof:placetype":"venue"
},
  "geometry": {"coordinates":[4.6978421211,50.8703346252],"type":"Point"}
}