{
  "type": "Feature",
  "properties": {
    "addr:full":"Spokenhofstraat 10 Boechout Antwerpen 2530",
    "addr:housenumber":"10",
    "addr:postcode":"2530",
    "addr:street":"Spokenhofstraat",
    "iso:country":"BE",
    "sg:address":"Spokenhofstraat 10",
    "sg:city":"Boechout",
    "sg:orig_category":"Activit\u00e9s diverses d'imprimerie",
    "sg:phone":"+32 3 455 32 11",
    "sg:postcode":"2530",
    "sg:province":"Antwerpen",
    "wof:name":"Geert Crollet",
    "wof:placetype":"venue"
},
  "geometry": {"coordinates":[4.4919919968,51.1768760681],"type":"Point"}
}