{
  "type": "Feature",
  "properties": {
    "addr:full":"Rue Du Martyr 41 Li\u00e8ge 1 (bressoux) Li\u00e8ge 4020",
    "addr:housenumber":"41;1",
    "addr:postcode":"4020",
    "addr:street":"Rue Du Martyr",
    "iso:country":"BE",
    "sg:address":"Rue Du Martyr 41",
    "sg:city":"Li\u00e8ge 1 (bressoux)",
    "sg:classifiers":[
        {
            "category":"Banks & Credit Unions",
            "subcategory":"Investment Brokerage",
            "type":"Services"
        }
    ],
    "sg:phone":"+32 4 343 33 86",
    "sg:postcode":"4020",
    "sg:province":"Li\u00e8ge",
    "sg:tags":[
        "printing",
        "-"
    ],
    "wof:name":"Vervinckt R",
    "wof:placetype":"venue"
},
  "geometry": {"coordinates":[5.6004509926,50.6432037354],"type":"Point"}
}