{
  "type": "Feature",
  "properties": {
    "iso:country":"BE",
    "sg:address":"De Smet De Naeyerlaan 12b12",
    "sg:city":"Jette/jette",
    "sg:orig_category":"Artsen and specialisten",
    "sg:phone":"+32 2 420 25 42",
    "sg:postcode":"1090",
    "sg:province":"Bruxelles-Capitale",
    "wof:name":"R. Dricot",
    "wof:placetype":"venue"
},
  "geometry": {"coordinates":[4.3264279366,50.8718528748],"type":"Point"}
}