{
  "type": "Feature",
  "properties": {
    "addr:full":"Alpenroosstraat 26 Berlaar Antwerpen 2590",
    "addr:housenumber":"26",
    "addr:postcode":"2590",
    "addr:street":"Alpenroosstraat",
    "iso:country":"BE",
    "sg:address":"Alpenroosstraat 26",
    "sg:city":"Berlaar",
    "sg:orig_category":"Sportclubs",
    "sg:phone":"+32 3 422 51 52",
    "sg:postcode":"2590",
    "sg:province":"Antwerpen",
    "wof:name":"Tafeltennisclub Berlaar",
    "wof:placetype":"venue"
},
  "geometry": {"coordinates":[4.6532440186,51.1188316345],"type":"Point"}
}