{
  "type": "Feature",
  "properties": {
    "addr:full":"Chauss\u00c9e De Dinant 753 Namur Namur 5100",
    "addr:housenumber":"753",
    "addr:postcode":"5100",
    "addr:street":"Chausse\u0301E De Dinant",
    "iso:country":"BE",
    "sg:address":"Chauss\u00c9e De Dinant 753",
    "sg:city":"Namur",
    "sg:orig_category":"Avocats and conseillers juridiques",
    "sg:phone":"+32 81 46 02 59",
    "sg:postcode":"5100",
    "sg:province":"Namur",
    "wof:name":"Y. De Backer",
    "wof:placetype":"venue"
},
  "geometry": {"coordinates":[4.8683619499,50.4275054932],"type":"Point"}
}