{
  "type": "Feature",
  "properties": {
    "addr:full":"Rue Des Bollandistes 67 Bruxelles (etterbeek) Bruxelles-Capitale 1040",
    "addr:housenumber":"67",
    "addr:postcode":"1040",
    "addr:street":"Rue Des Bollandistes",
    "iso:country":"BE",
    "sg:address":"Rue Des Bollandistes 67",
    "sg:city":"Bruxelles (etterbeek)",
    "sg:classifiers":[
        {
            "category":"Professional",
            "subcategory":"Art Services",
            "type":"Services"
        }
    ],
    "sg:phone":"+32 2 732 10 20",
    "sg:postcode":"1040",
    "sg:province":"Bruxelles-Capitale",
    "sg:tags":[
        "graphic",
        "designer"
    ],
    "wof:name":"Eloi Sprl",
    "wof:placetype":"venue"
},
  "geometry": {"coordinates":[4.4055747986,50.8350219727],"type":"Point"}
}