{
  "type": "Feature",
  "properties": {
    "iso:country":"BE",
    "sg:address":"Molenveldstraat 26",
    "sg:city":"Lebbeke",
    "sg:orig_category":"M\u00e9decins and sp\u00e9cialistes",
    "sg:phone":"+32 52 41 02 74",
    "sg:postcode":"9280",
    "sg:province":"Oost-Vlaanderen",
    "wof:name":"Guido Halsberghe",
    "wof:placetype":"venue"
},
  "geometry": {"coordinates":[4.0947771072,50.9991455078],"type":"Point"}
}