{
  "type": "Feature",
  "properties": {
    "iso:country":"BE",
    "sg:address":"Quai Du Halage 268",
    "sg:city":"Flemalle",
    "sg:orig_category":"Artsen and specialisten",
    "sg:phone":"+32 4 275 17 30",
    "sg:postcode":"4400",
    "sg:province":"Li\u00e8ge",
    "wof:name":"I. Porignon",
    "wof:placetype":"venue"
},
  "geometry": {"coordinates":[5.4785251617,50.5973167419],"type":"Point"}
}