{
  "type": "Feature",
  "properties": {
    "iso:country":"BE",
    "sg:address":"Rue Maurice Brossius 47",
    "sg:city":"Flawinne",
    "sg:classifiers":[
        {
            "category":"Building & Trades",
            "subcategory":"Construction",
            "type":"Services"
        }
    ],
    "sg:phone":"+32 81 71 14 09",
    "sg:postcode":"5020",
    "sg:province":"Namur",
    "sg:tags":[
        "binding",
        "road",
        "agent"
    ],
    "wof:name":"Hydrocar Industrie S.a.",
    "wof:placetype":"venue"
},
  "geometry": {"coordinates":[4.8052339554,50.4549369812],"type":"Point"}
}