{
  "type": "Feature",
  "properties": {
    "addr:full":"Place Nicola\u00cf 21 Aubel Li\u00e8ge 4880",
    "addr:housenumber":"21",
    "addr:postcode":"4880",
    "addr:street":"Place Nicolai\u0308",
    "iso:country":"BE",
    "sg:address":"Place Nicola\u00cf 21",
    "sg:city":"Aubel",
    "sg:orig_category":"Foto-uitrusting Fotografen and fotostudio's Telecommunicatieapparaten",
    "sg:phone":"+32 87 68 77 57",
    "sg:postcode":"4880",
    "sg:province":"Li\u00e8ge",
    "wof:name":"Photo Gilman",
    "wof:placetype":"venue"
},
  "geometry": {"coordinates":[5.858232975,50.7054786682],"type":"Point"}
}