{
  "type": "Feature",
  "properties": {
    "iso:country":"BE",
    "sg:address":"Ruelle Des Bois 27",
    "sg:city":"Chaumont-gistoux",
    "sg:orig_category":"Secretariaatsdiensten",
    "sg:phone":"+32 10 88 03 95",
    "sg:postcode":"1325",
    "sg:province":"Brabant Wallon",
    "wof:name":"B.i.l. International",
    "wof:placetype":"venue"
},
  "geometry": {"coordinates":[4.7417421341,50.7080039978],"type":"Point"}
}