{
  "type": "Feature",
  "properties": {
    "addr:full":"Rue Du Noyer 299 Bruxelles Bruxelles-Capitale 1000",
    "addr:housenumber":"299",
    "addr:postcode":"1000",
    "addr:street":"Rue Du Noyer",
    "iso:country":"BE",
    "sg:address":"Rue Du Noyer 299",
    "sg:city":"Bruxelles",
    "sg:classifiers":[
        {
            "category":"Retail",
            "subcategory":"Repair Shop",
            "type":"Services"
        }
    ],
    "sg:phone":"+32 2 733 66 13",
    "sg:postcode":"1000",
    "sg:province":"Bruxelles-Capitale",
    "sg:tags":[
        "-",
        "clothing",
        "alteration"
    ],
    "wof:name":"Mi-ange",
    "wof:placetype":"venue"
},
  "geometry": {"coordinates":[4.3959088326,50.8434791565],"type":"Point"}
}