{
  "type": "Feature",
  "properties": {
    "addr:full":"Stationsstraat 45b52 Deerlijk West-Vlaanderen 8540",
    "addr:housenumber":"45b52",
    "addr:postcode":"8540",
    "addr:street":"Stationsstraat",
    "iso:country":"BE",
    "sg:address":"Stationsstraat 45b52",
    "sg:city":"Deerlijk",
    "sg:orig_category":"V\u00e9hicules automobiles. D\u00e9taillants en pi\u00e8ces and accessoires de voitures",
    "sg:phone":"+32 56 71 39 10",
    "sg:postcode":"8540",
    "sg:province":"West-Vlaanderen",
    "wof:name":"Garage Vandenberghe",
    "wof:placetype":"venue"
},
  "geometry": {"coordinates":[3.3513600826,50.8499145508],"type":"Point"}
}