{
  "type": "Feature",
  "properties": {
    "addr:full":"Grand-rue 99 Paliseul Luxembourg 6850",
    "addr:housenumber":"99",
    "addr:postcode":"6850",
    "addr:street":"Grand-Rue",
    "iso:country":"BE",
    "sg:address":"Grand-rue 99",
    "sg:city":"Paliseul",
    "sg:orig_category":"Enseignement maternel and primaire",
    "sg:phone":"+32 61 53 49 91",
    "sg:postcode":"6850",
    "sg:province":"Luxembourg",
    "wof:name":"Ecole Prim. Communale",
    "wof:placetype":"venue"
},
  "geometry": {"coordinates":[5.0989460945,49.9009666443],"type":"Point"}
}