{
  "type": "Feature",
  "properties": {
    "iso:country":"BE",
    "sg:address":"Avenue Du Travail 71",
    "sg:city":"Quaregnon",
    "sg:orig_category":"Woningbouw",
    "sg:phone":"+32 65 79 31 42",
    "sg:postcode":"7390",
    "sg:province":"Hainaut",
    "wof:name":"Entreprise G\u00c9n\u00c9rale",
    "wof:placetype":"venue"
},
  "geometry": {"coordinates":[3.8539218903,50.4397773743],"type":"Point"}
}