{
  "type": "Feature",
  "properties": {
    "addr:full":"Rotterdamstraat 52 Antwerpen Antwerpen 2060",
    "addr:housenumber":"52",
    "addr:postcode":"2060",
    "addr:street":"Rotterdamstraat",
    "iso:country":"BE",
    "sg:address":"Rotterdamstraat 52",
    "sg:city":"Antwerpen",
    "sg:orig_category":"Agences d'exp\u00e9dition. Caf\u00e9s",
    "sg:phone":"+32 3 232 49 38",
    "sg:postcode":"2060",
    "sg:province":"Antwerpen",
    "wof:name":"Guisabi Lda Belgica",
    "wof:placetype":"venue"
},
  "geometry": {"coordinates":[4.4193100929,51.2235603333],"type":"Point"}
}