{
  "type": "Feature",
  "properties": {
    "addr:full":"Daalstraat 4 Affligem Vlaams-Brabant 1790",
    "addr:housenumber":"4",
    "addr:postcode":"1790",
    "addr:street":"Daalstraat",
    "iso:country":"BE",
    "sg:address":"Daalstraat 4",
    "sg:city":"Affligem",
    "sg:orig_category":"Epiceries",
    "sg:phone":"+32 53 68 48 98",
    "sg:postcode":"1790",
    "sg:province":"Vlaams-Brabant",
    "wof:name":"A.v.b.",
    "wof:placetype":"venue"
},
  "geometry": {"coordinates":[4.0977330208,50.8924026489],"type":"Point"}
}