{
  "type": "Feature",
  "properties": {
    "iso:country":"BE",
    "sg:address":"Cour De La Sarriette 25-29",
    "sg:city":"Ottignies-louvain-la-neuve (louvain-la-neuve)",
    "sg:classifiers":[
        {
            "category":"Social Services",
            "subcategory":"Child Care",
            "type":"Services"
        }
    ],
    "sg:phone":"+32 10 45 02 43",
    "sg:postcode":"1348",
    "sg:province":"Brabant Wallon",
    "sg:tags":[
        "baby",
        "nursery",
        "day",
        "sitting"
    ],
    "wof:name":"Cigalons (cr\u00e8che Les) Asbl",
    "wof:placetype":"venue"
},
  "geometry": {"coordinates":[4.6188001633,50.6636962891],"type":"Point"}
}