{
  "type": "Feature",
  "properties": {
    "addr:full":"Rue De La Bruy\u00e8re 8 Rixensart (genval) Brabant Wallon 1332",
    "addr:housenumber":"8",
    "addr:postcode":"1332",
    "addr:street":"Rue De La Bruye\u0300Re",
    "iso:country":"BE",
    "sg:address":"Rue De La Bruy\u00e8re 8",
    "sg:city":"Rixensart (genval)",
    "sg:classifiers":[
        {
            "category":"Shopping",
            "subcategory":"Florist",
            "type":"Retail Goods"
        }
    ],
    "sg:phone":"+32 2 653 76 46",
    "sg:postcode":"1332",
    "sg:province":"Brabant Wallon",
    "wof:name":"Leloup & Fils",
    "wof:placetype":"venue"
},
  "geometry": {"coordinates":[4.4931049347,50.7177886963],"type":"Point"}
}