{
  "type": "Feature",
  "properties": {
    "iso:country":"BE",
    "sg:address":"Grand-rue 32",
    "sg:city":"Libramont-chevigny",
    "sg:orig_category":"Paramedische behandelingen",
    "sg:phone":"+32 61 22 48 09",
    "sg:postcode":"6800",
    "sg:province":"Luxembourg",
    "wof:name":"C. Noirot",
    "wof:placetype":"venue"
},
  "geometry": {"coordinates":[5.4576530457,49.9803771973],"type":"Point"}
}