{
  "type": "Feature",
  "properties": {
    "iso:country":"BE",
    "sg:address":"Jubileumlaan 2",
    "sg:city":"Turnhout",
    "sg:classifiers":[
        {
            "category":"Utilities",
            "subcategory":"Natural Gas",
            "type":"Services"
        }
    ],
    "sg:phone":"+32 14 42 26 97",
    "sg:postcode":"2300",
    "sg:province":"Antwerpen",
    "sg:tags":[
        "welding"
    ],
    "wof:name":"Alulas",
    "wof:placetype":"venue"
},
  "geometry": {"coordinates":[4.9617619514,51.3310928345],"type":"Point"}
}