{
  "type": "Feature",
  "properties": {
    "iso:country":"BE",
    "sg:address":"Pastoor Dergentlaan 75",
    "sg:city":"Aarschot",
    "sg:classifiers":[
        {
            "category":"Professional",
            "subcategory":"Printing & Photocopies",
            "type":"Services"
        }
    ],
    "sg:phone":"+32 16 56 71 47",
    "sg:postcode":"3200",
    "sg:province":"Vlaams-Brabant",
    "sg:tags":[
        "-",
        "publishing",
        "desktop"
    ],
    "wof:name":"Goovaerts J",
    "wof:placetype":"venue"
},
  "geometry": {"coordinates":[4.8369421959,50.9907569885],"type":"Point"}
}