{
  "type": "Feature",
  "properties": {
    "addr:full":"Kortedagsteeg 4 Gent Oost-Vlaanderen 9000",
    "addr:housenumber":"4",
    "addr:postcode":"9000",
    "addr:street":"Kortedagsteeg;Oost-Vlaanderen",
    "iso:country":"BE",
    "sg:address":"Kortedagsteeg 4",
    "sg:city":"Gent",
    "sg:orig_category":"Slagers",
    "sg:phone":"+32 9 223 30 72",
    "sg:postcode":"9000",
    "sg:province":"Oost-Vlaanderen",
    "wof:name":"Slagerij Guy",
    "wof:placetype":"venue"
},
  "geometry": {"coordinates":[3.7262010574,51.0504074097],"type":"Point"}
}