{
  "type": "Feature",
  "properties": {
    "iso:country":"BE",
    "sg:address":"Rue Achille Detienne 18",
    "sg:city":"Bruxelles",
    "sg:orig_category":"V\u00eatements",
    "sg:phone":"+32 2 248 22 48",
    "sg:postcode":"1030",
    "sg:province":"Bruxelles-Capitale",
    "wof:name":"Uni-style",
    "wof:placetype":"venue"
},
  "geometry": {"coordinates":[4.3889307976,50.8714294434],"type":"Point"}
}