{
  "type": "Feature",
  "properties": {
    "iso:country":"BE",
    "sg:address":"Chemin Des Fours 11",
    "sg:city":"Dour",
    "sg:orig_category":"Bouwmaterialen Gh Goederenvervoer over de weg",
    "sg:phone":"+32 65 63 28 35",
    "sg:postcode":"7370",
    "sg:province":"Hainaut",
    "wof:name":"Delhaye Mat\u00c9riaux",
    "wof:placetype":"venue"
},
  "geometry": {"coordinates":[3.7753100395,50.4030990601],"type":"Point"}
}