{
  "type": "Feature",
  "properties": {
    "iso:country":"BE",
    "sg:address":"Moerstraat 92",
    "sg:city":"Schilde ('s Gravenwezel)",
    "sg:orig_category":"Non-Classified Establishments",
    "sg:phone":"+32 3 325 60 12",
    "sg:postcode":"2970",
    "sg:province":"Antwerpen",
    "wof:name":"Eurasteel Co Bvba",
    "wof:placetype":"venue"
},
  "geometry": {"coordinates":[4.5619111061,51.2703971863],"type":"Point"}
}