{
  "type": "Feature",
  "properties": {
    "addr:full":"Avenue Jules C\u00e9sar 14 Bruxelles (woluwe-saint-pierre) Bruxelles-Capitale 1150",
    "addr:housenumber":"14",
    "addr:postcode":"1150",
    "addr:street":"Avenue Jules Ce\u0301Sar",
    "iso:country":"BE",
    "sg:address":"Avenue Jules C\u00e9sar 14",
    "sg:city":"Bruxelles (woluwe-saint-pierre)",
    "sg:classifiers":[
        {
            "category":"Retail",
            "subcategory":"Event Space",
            "type":"Services"
        }
    ],
    "sg:phone":"+32 2 762 01 42",
    "sg:postcode":"1150",
    "sg:province":"Bruxelles-Capitale",
    "sg:tags":[
        "organisation"
    ],
    "wof:name":"City 7 Belgium Sa",
    "wof:placetype":"venue"
},
  "geometry": {"coordinates":[4.4205322266,50.8334960938],"type":"Point"}
}