{
  "type": "Feature",
  "properties": {
    "addr:full":"Zavel 15 Zottegem Oost-Vlaanderen 9620",
    "addr:housenumber":"15",
    "addr:postcode":"9620",
    "addr:street":"Zavel",
    "iso:country":"BE",
    "sg:address":"Zavel 15",
    "sg:city":"Zottegem",
    "sg:classifiers":[
        {
            "category":"Education",
            "subcategory":"School",
            "type":"Public Place"
        }
    ],
    "sg:phone":"+32 9 360 12 29",
    "sg:postcode":"9620",
    "sg:province":"Oost-Vlaanderen",
    "sg:tags":[
        "secondary"
    ],
    "wof:name":"Sint-barbarainstituut",
    "wof:placetype":"venue"
},
  "geometry": {"coordinates":[3.8108251095,50.8689117432],"type":"Point"}
}