{
  "type": "Feature",
  "properties": {
    "addr:full":"Avenue Winston Churchill 59b9 Ukkel/uccle Bruxelles-Capitale 1180",
    "addr:housenumber":"59b9",
    "addr:postcode":"1180",
    "addr:street":"Avenue Winston Churchill;/",
    "iso:country":"BE",
    "sg:address":"Avenue Winston Churchill 59b9",
    "sg:city":"Ukkel/uccle",
    "sg:orig_category":"Architectes",
    "sg:phone":"+32 2 346 46 01",
    "sg:postcode":"1180",
    "sg:province":"Bruxelles-Capitale",
    "wof:name":"Boris Goldenberg",
    "wof:placetype":"venue"
},
  "geometry": {"coordinates":[4.3520169258,50.8120346069],"type":"Point"}
}