{
  "type": "Feature",
  "properties": {
    "addr:full":"Arthur Scheirisstraat 16 Box 9 Zottegem Oost-Vlaanderen 9620",
    "addr:housenumber":"16;9",
    "addr:postcode":"9620",
    "addr:street":"Scheirisstraat;Box",
    "iso:country":"BE",
    "sg:address":"Arthur Scheirisstraat 16 Box 9",
    "sg:city":"Zottegem",
    "sg:classifiers":[
        {
            "category":"Health Services",
            "subcategory":"Health Practitioner",
            "type":"Services"
        }
    ],
    "sg:phone":"+32 498 24 19 40",
    "sg:postcode":"9620",
    "sg:province":"Oost-Vlaanderen",
    "sg:tags":[
        "therapist",
        "speech"
    ],
    "wof:name":"Vercruysse S",
    "wof:placetype":"venue"
},
  "geometry": {"coordinates":[3.8096420765,50.8694725037],"type":"Point"}
}