{
  "type": "Feature",
  "properties": {
    "addr:full":"Binnenstraat 311 Aalst Oost-Vlaanderen 9300",
    "addr:housenumber":"311",
    "addr:postcode":"9300",
    "addr:street":"Binnenstraat",
    "iso:country":"BE",
    "sg:address":"Binnenstraat 311",
    "sg:city":"Aalst",
    "sg:classifiers":[
        {
            "category":"Shopping",
            "subcategory":"Florist",
            "type":"Retail Goods"
        }
    ],
    "sg:phone":"+32 53 78 73 49",
    "sg:postcode":"9300",
    "sg:province":"Oost-Vlaanderen",
    "sg:tags":[
        "-",
        "supply"
    ],
    "wof:name":"G.v.k.",
    "wof:placetype":"venue"
},
  "geometry": {"coordinates":[4.0559940338,50.9503326416],"type":"Point"}
}