{
  "type": "Feature",
  "properties": {
    "addr:full":"Rue De L'industrie 11 Tubize Brabant Wallon 1480",
    "addr:housenumber":"11",
    "addr:postcode":"1480",
    "addr:street":"Rue De L'Industrie;Wallon",
    "iso:country":"BE",
    "sg:address":"Rue De L'industrie 11",
    "sg:city":"Tubize",
    "sg:orig_category":"Assurances. Bureaux de poste",
    "sg:phone":"+32 2 355 62 65",
    "sg:postcode":"1480",
    "sg:province":"Brabant Wallon",
    "wof:name":"La Poste",
    "wof:placetype":"venue"
},
  "geometry": {"coordinates":[4.2038698196,50.6905822754],"type":"Point"}
}