{
  "type": "Feature",
  "properties": {
    "iso:country":"BE",
    "sg:address":"Rue La Basse 16",
    "sg:city":"Nandrin",
    "sg:classifiers":[
        {
            "category":"Building & Trades",
            "subcategory":"Pest Control",
            "type":"Services"
        }
    ],
    "sg:phone":"+32 85 51 20 03",
    "sg:postcode":"4550",
    "sg:province":"Li\u00e8ge",
    "sg:tags":[
        "painting",
        "contractor"
    ],
    "wof:name":"Collin J-l",
    "wof:placetype":"venue"
},
  "geometry": {"coordinates":[5.4230399132,50.501663208],"type":"Point"}
}