{
  "type": "Feature",
  "properties": {
    "iso:country":"BE",
    "sg:address":"Rue Des Casernes 14",
    "sg:city":"Florenville (villers-devant-orval)",
    "sg:classifiers":[
        {
            "category":"Home & Garden",
            "subcategory":"Household Appliances",
            "type":"Retail Goods"
        }
    ],
    "sg:phone":"+32 61 31 42 77",
    "sg:postcode":"6823",
    "sg:province":"Luxembourg",
    "sg:tags":[
        "repair",
        "mainten",
        "-",
        "electric"
    ],
    "wof:name":"Beguin P",
    "wof:placetype":"venue"
},
  "geometry": {"coordinates":[5.3309431076,49.620639801],"type":"Point"}
}