{
  "type": "Feature",
  "properties": {
    "iso:country":"BE",
    "sg:address":"Kempenlaan 8",
    "sg:city":"Genk",
    "sg:orig_category":"Woningbouw",
    "sg:phone":"+32 89 36 34 24",
    "sg:postcode":"3600",
    "sg:province":"Limburg",
    "wof:name":"Antonino Saraniti",
    "wof:placetype":"venue"
},
  "geometry": {"coordinates":[5.5004620552,50.9617919922],"type":"Point"}
}