{
  "type": "Feature",
  "properties": {
    "addr:full":"Rue De La Providence 17 Charleroi Hainaut 6030",
    "addr:housenumber":"17",
    "addr:postcode":"6030",
    "addr:street":"Rue De La Providence;Hainaut",
    "iso:country":"BE",
    "sg:address":"Rue De La Providence 17",
    "sg:city":"Charleroi",
    "sg:orig_category":"V\u00e9hicules automobiles",
    "sg:phone":"+32 71 31 45 50",
    "sg:postcode":"6030",
    "sg:province":"Hainaut",
    "wof:name":"Garage Bullman",
    "wof:placetype":"venue"
},
  "geometry": {"coordinates":[4.3974108696,50.411529541],"type":"Point"}
}