{
  "type": "Feature",
  "properties": {
    "iso:country":"BE",
    "sg:address":"Keistraat 21",
    "sg:city":"Bilzen (kleine-spouwen)",
    "sg:classifiers":[
        {
            "category":"Building & Trades",
            "subcategory":"Pest Control",
            "type":"Services"
        }
    ],
    "sg:phone":"+32 89 49 12 73",
    "sg:postcode":"3740",
    "sg:province":"Limburg",
    "sg:tags":[
        "painting",
        "contractor"
    ],
    "wof:name":"Erna M",
    "wof:placetype":"venue"
},
  "geometry": {"coordinates":[5.4725527763,50.8848457336],"type":"Point"}
}