{
  "type": "Feature",
  "properties": {
    "addr:full":"Rue Moirivay 1b Olne Li\u00e8ge 4877",
    "addr:housenumber":"1b",
    "addr:postcode":"4877",
    "addr:street":"Rue Moirivay",
    "iso:country":"BE",
    "sg:address":"Rue Moirivay 1b",
    "sg:city":"Olne",
    "sg:orig_category":"Entretien and r\u00e9parations de voitures",
    "sg:phone":"+32 87 26 86 71",
    "sg:postcode":"4877",
    "sg:province":"Li\u00e8ge",
    "wof:name":"J.m. Donneau",
    "wof:placetype":"venue"
},
  "geometry": {"coordinates":[5.732460022,50.5666618347],"type":"Point"}
}