{
  "type": "Feature",
  "properties": {
    "addr:full":"Sint-jozefstraat 30 Aalst Oost-Vlaanderen 9300",
    "addr:housenumber":"30",
    "addr:postcode":"9300",
    "addr:street":"Sint-Jozefstraat",
    "iso:country":"BE",
    "sg:address":"Sint-jozefstraat 30",
    "sg:city":"Aalst",
    "sg:classifiers":[
        {
            "category":"Shopping",
            "subcategory":"Discount & Variety Stores",
            "type":"Retail Goods"
        }
    ],
    "sg:phone":"+32 53 77 82 69",
    "sg:postcode":"9300",
    "sg:province":"Oost-Vlaanderen",
    "sg:tags":[
        "shop",
        "clearers",
        "curiosity",
        "furniture"
    ],
    "wof:name":"Verkoopzaal St-jozef",
    "wof:placetype":"venue"
},
  "geometry": {"coordinates":[4.0322341919,50.9413986206],"type":"Point"}
}