{
  "type": "Feature",
  "properties": {
    "addr:full":"Nieuwbrugstraat 4 Aalst Oost-Vlaanderen 9300",
    "addr:housenumber":"4",
    "addr:postcode":"9300",
    "addr:street":"Nieuwbrugstraat",
    "iso:country":"BE",
    "sg:address":"Nieuwbrugstraat 4",
    "sg:city":"Aalst",
    "sg:orig_category":"Journaux. Tabac",
    "sg:phone":"+32 53 70 59 99",
    "sg:postcode":"9300",
    "sg:province":"Oost-Vlaanderen",
    "wof:name":"De Zwarte Hoekbrug",
    "wof:placetype":"venue"
},
  "geometry": {"coordinates":[4.0395131111,50.945930481],"type":"Point"}
}