{
  "type": "Feature",
  "properties": {
    "addr:full":"Kapelsesteenweg 258 Brasschaat Antwerpen 2930",
    "addr:housenumber":"258",
    "addr:postcode":"2930",
    "addr:street":"Kapelsesteenweg",
    "iso:country":"BE",
    "sg:address":"Kapelsesteenweg 258",
    "sg:city":"Brasschaat",
    "sg:classifiers":[
        {
            "category":"Retail",
            "subcategory":"Event Space",
            "type":"Services"
        }
    ],
    "sg:phone":"+32 3 646 80 20",
    "sg:postcode":"2930",
    "sg:province":"Antwerpen",
    "sg:tags":[
        "organisation"
    ],
    "wof:name":"Lou Roman Band En Producties",
    "wof:placetype":"venue"
},
  "geometry": {"coordinates":[4.4487061501,51.286190033],"type":"Point"}
}