{
  "type": "Feature",
  "properties": {
    "iso:country":"BE",
    "sg:address":"Genkerbaan 61",
    "sg:city":"Meeuwen-gruitrode",
    "sg:orig_category":"Sportclubs",
    "sg:phone":"+32 11 79 27 63",
    "sg:postcode":"3670",
    "sg:province":"Limburg",
    "wof:name":"B.b.c. Meeuwen Gruitrode",
    "wof:placetype":"venue"
},
  "geometry": {"coordinates":[5.5269241333,51.0850067139],"type":"Point"}
}