{
  "type": "Feature",
  "properties": {
    "addr:full":"Sanderusstraat 50 Antwerpen Antwerpen 2018",
    "addr:housenumber":"50",
    "addr:postcode":"2018",
    "addr:street":"Sanderusstraat",
    "iso:country":"BE",
    "sg:address":"Sanderusstraat 50",
    "sg:city":"Antwerpen",
    "sg:orig_category":"Loodgieterij, verwarming and sanitaire installaties",
    "sg:phone":"+32 3 216 14 00",
    "sg:postcode":"2018",
    "sg:province":"Antwerpen",
    "wof:name":"Bockstal",
    "wof:placetype":"venue"
},
  "geometry": {"coordinates":[4.4042139053,51.2074928284],"type":"Point"}
}