{
  "type": "Feature",
  "properties": {
    "addr:full":"Schuiterstraat 41 Gent Oost-Vlaanderen 9031",
    "addr:housenumber":"41",
    "addr:postcode":"9031",
    "addr:street":"Schuiterstraat;Oost-Vlaanderen",
    "iso:country":"BE",
    "sg:address":"Schuiterstraat 41",
    "sg:city":"Gent",
    "sg:orig_category":"Dakwerken",
    "sg:phone":"+32 9 236 57 52",
    "sg:postcode":"9031",
    "sg:province":"Oost-Vlaanderen",
    "wof:name":"De Somer",
    "wof:placetype":"venue"
},
  "geometry": {"coordinates":[3.6486620903,51.046787262],"type":"Point"}
}