{
  "type": "Feature",
  "properties": {
    "addr:full":"Rue Grand Vin\u00c2ve Seraing 4104",
    "addr:postcode":"4104",
    "addr:street":"Rue Grand Vina\u0302Ve",
    "iso:country":"BE",
    "sg:address":"Rue Grand Vin\u00c2ve",
    "sg:city":"Seraing",
    "sg:orig_category":"Jeux de hasard",
    "sg:phone":"+32 4 233 36 33",
    "sg:postcode":"4104",
    "wof:name":"Tierce Franco Belge",
    "wof:placetype":"venue"
},
  "geometry": {"coordinates":[5.5066452026,50.6169204712],"type":"Point"}
}