{
  "type": "Feature",
  "properties": {
    "iso:country":"BE",
    "sg:address":"Rue Des Criquets 4",
    "sg:city":"Rochefort (wavreille)",
    "sg:classifiers":[
        {
            "category":"Banks & Credit Unions",
            "subcategory":"Bureau De Change",
            "type":"Services"
        }
    ],
    "sg:phone":"+32 84 21 00 22",
    "sg:postcode":"5580",
    "sg:province":"Namur",
    "sg:tags":[
        "-",
        "household",
        "gas"
    ],
    "wof:name":"Marchal M",
    "wof:placetype":"venue"
},
  "geometry": {"coordinates":[5.25704813,50.1184005737],"type":"Point"}
}