{
  "type": "Feature",
  "properties": {
    "addr:full":"Dorpsstraat 2 Stekene Oost-Vlaanderen 9190",
    "addr:housenumber":"2",
    "addr:postcode":"9190",
    "addr:street":"Dorpsstraat",
    "iso:country":"BE",
    "sg:address":"Dorpsstraat 2",
    "sg:city":"Stekene",
    "sg:classifiers":[
        {
            "category":"Cafe",
            "type":"Food & Drink"
        }
    ],
    "sg:phone":"+32 3 789 13 33",
    "sg:postcode":"9190",
    "sg:province":"Oost-Vlaanderen",
    "sg:tags":[
        "caf\u00e9s"
    ],
    "wof:name":"Herman Janssens",
    "wof:placetype":"venue"
},
  "geometry": {"coordinates":[4.0405430794,51.2060470581],"type":"Point"}
}