{
  "type": "Feature",
  "properties": {
    "iso:country":"BE",
    "sg:address":"Grote Leiestraat 147",
    "sg:city":"Anzegem",
    "sg:classifiers":[
        {
            "category":"Retail",
            "subcategory":"Auto Repair",
            "type":"Services"
        }
    ],
    "sg:phone":"+32 56 68 84 98",
    "sg:postcode":"8570",
    "sg:province":"West-Vlaanderen",
    "sg:tags":[
        "garage"
    ],
    "wof:name":"Dubrunfaut F",
    "wof:placetype":"venue"
},
  "geometry": {"coordinates":[3.4561491013,50.8559036255],"type":"Point"}
}