{
  "type": "Feature",
  "properties": {
    "addr:full":"Rue Du Vicinal 22 Blegny Li\u00e8ge 4670",
    "addr:housenumber":"22",
    "addr:postcode":"4670",
    "addr:street":"Rue Du Vicinal",
    "iso:country":"BE",
    "sg:address":"Rue Du Vicinal 22",
    "sg:city":"Blegny",
    "sg:orig_category":"Brood, gebak and snoepgoed",
    "sg:phone":"+32 4 387 40 77",
    "sg:postcode":"4670",
    "sg:province":"Li\u00e8ge",
    "wof:name":"Francis Petit",
    "wof:placetype":"venue"
},
  "geometry": {"coordinates":[5.7215051651,50.6760253906],"type":"Point"}
}