{
  "type": "Feature",
  "properties": {
    "addr:full":"Moerstraat 5 Zuienkerke West-Vlaanderen 8377",
    "addr:housenumber":"5",
    "addr:postcode":"8377",
    "addr:street":"Moerstraat",
    "iso:country":"BE",
    "sg:address":"Moerstraat 5",
    "sg:city":"Zuienkerke",
    "sg:orig_category":"Rundveehouders Varkenskwekers",
    "sg:phone":"+32 50 31 48 58",
    "sg:postcode":"8377",
    "sg:province":"West-Vlaanderen",
    "wof:name":"Marcel Devos",
    "wof:placetype":"venue"
},
  "geometry": {"coordinates":[3.160063982,51.2253494263],"type":"Point"}
}