{
  "type": "Feature",
  "properties": {
    "iso:country":"BE",
    "sg:address":"Koning Albertlaan 15bk",
    "sg:city":"Maldegem",
    "sg:orig_category":"Installation \u00e9lectrique r\u00e9sidentielle",
    "sg:phone":"+32 50 71 67 50",
    "sg:postcode":"9990",
    "sg:province":"Oost-Vlaanderen",
    "wof:name":"Geert De Roose",
    "wof:placetype":"venue"
},
  "geometry": {"coordinates":[3.4218659401,51.2113685608],"type":"Point"}
}