{
  "type": "Feature",
  "properties": {
    "addr:full":"Kleine Remerstraat 7 Tremelo (baal) Vlaams-Brabant 3128",
    "addr:housenumber":"7",
    "addr:postcode":"3128",
    "addr:street":"Kleine Remerstraat",
    "iso:country":"BE",
    "sg:address":"Kleine Remerstraat 7",
    "sg:city":"Tremelo (baal)",
    "sg:classifiers":[
        {
            "category":"Professional",
            "subcategory":"Art Services",
            "type":"Services"
        }
    ],
    "sg:phone":"+32 16 53 85 77",
    "sg:postcode":"3128",
    "sg:province":"Vlaams-Brabant",
    "sg:tags":[
        "graphic",
        "designer"
    ],
    "wof:name":"Lambaerts G",
    "wof:placetype":"venue"
},
  "geometry": {"coordinates":[4.7530770302,51.0057945251],"type":"Point"}
}