{
  "type": "Feature",
  "properties": {
    "iso:country":"BE",
    "sg:address":"Chauss\u00e9e De Jolimont 25",
    "sg:city":"La Louvi\u00e8re (haine-saint-pierre)",
    "sg:classifiers":[
        {
            "category":"Home & Garden",
            "subcategory":"Home Furnishings",
            "type":"Retail Goods"
        }
    ],
    "sg:phone":"+32 64 22 53 48",
    "sg:postcode":"7100",
    "sg:province":"Hainaut",
    "sg:tags":[
        "curtain",
        "-",
        "fixture"
    ],
    "wof:name":"Tapiclub",
    "wof:placetype":"venue"
},
  "geometry": {"coordinates":[4.2157001495,50.4721488953],"type":"Point"}
}