{
  "type": "Feature",
  "properties": {
    "iso:country":"BE",
    "sg:address":"Rue De Reppe 0",
    "sg:city":"Ohey",
    "sg:orig_category":"Enseignement maternel and primaire",
    "sg:phone":"+32 85 61 12 89",
    "sg:postcode":"5350",
    "sg:province":"Namur",
    "wof:name":"Ecole Fond. Communale",
    "wof:placetype":"venue"
},
  "geometry": {"coordinates":[5.0883698463,50.4253425598],"type":"Point"}
}