{
  "type": "Feature",
  "properties": {
    "addr:full":"Staatsbaan 85 Lanaken Limburg 3620",
    "addr:housenumber":"85",
    "addr:postcode":"3620",
    "addr:street":"Staatsbaan",
    "iso:country":"BE",
    "sg:address":"Staatsbaan 85",
    "sg:city":"Lanaken",
    "sg:orig_category":"Antiquit\u00e9s",
    "sg:phone":"+32 89 71 36 19",
    "sg:postcode":"3620",
    "sg:province":"Limburg",
    "wof:name":"Henri Nelissen",
    "wof:placetype":"venue"
},
  "geometry": {"coordinates":[5.6814289093,50.9115447998],"type":"Point"}
}