{
  "type": "Feature",
  "properties": {
    "addr:full":"Obberg 1 Wemmel Vlaams-Brabant 1780",
    "addr:housenumber":"1",
    "addr:postcode":"1780",
    "addr:street":"Obberg;Vlaams-Brabant",
    "iso:country":"BE",
    "sg:address":"Obberg 1",
    "sg:city":"Wemmel",
    "sg:orig_category":"Herstelling aan huis van huishoudartikelen Herstelling leer and schoeisel Herstellingswinkels voor d",
    "sg:phone":"+32 2 460 42 90",
    "sg:postcode":"1780",
    "sg:province":"Vlaams-Brabant",
    "wof:name":"Collier Stefaan Security",
    "wof:placetype":"venue"
},
  "geometry": {"coordinates":[4.3038330078,50.9042854309],"type":"Point"}
}