{
  "type": "Feature",
  "properties": {
    "addr:full":"Avenue Edouard B\u00e9n\u00e8s 111 Bruxelles (molenbeek-saint-jean) Bruxelles-Capitale 1080",
    "addr:housenumber":"111",
    "addr:postcode":"1080",
    "addr:street":"Avenue Edouard Be\u0301Ne\u0300S",
    "iso:country":"BE",
    "sg:address":"Avenue Edouard B\u00e9n\u00e8s 111",
    "sg:city":"Bruxelles (molenbeek-saint-jean)",
    "sg:classifiers":[
        {
            "category":"Professional",
            "subcategory":"Testing Lab",
            "type":"Services"
        }
    ],
    "sg:phone":"+32 2 465 07 04",
    "sg:postcode":"1080",
    "sg:province":"Bruxelles-Capitale",
    "sg:tags":[
        "laboratory",
        "photographic",
        "film"
    ],
    "wof:name":"Inprint Sa",
    "wof:placetype":"venue"
},
  "geometry": {"coordinates":[4.3073291779,50.8627586365],"type":"Point"}
}