{
  "type": "Feature",
  "properties": {
    "addr:full":"Nieuwkerkenstraat 10-12 Sint-niklaas (nieuwkerken-waas) Oost-Vlaanderen 9100",
    "addr:postcode":"10-12;9100",
    "addr:street":"Nieuwkerkenstraat",
    "iso:country":"BE",
    "sg:address":"Nieuwkerkenstraat 10-12",
    "sg:city":"Sint-niklaas (nieuwkerken-waas)",
    "sg:classifiers":[
        {
            "category":"Professional",
            "subcategory":"Testing Lab",
            "type":"Services"
        }
    ],
    "sg:phone":"+32 3 766 23 80",
    "sg:postcode":"9100",
    "sg:province":"Oost-Vlaanderen",
    "sg:tags":[
        "chemist"
    ],
    "wof:name":"Farma Bovan Nv",
    "wof:placetype":"venue"
},
  "geometry": {"coordinates":[4.178319931,51.1927604675],"type":"Point"}
}