{
  "type": "Feature",
  "properties": {
    "addr:full":"Legeweg 163 Oostkamp West-Vlaanderen 8020",
    "addr:housenumber":"163",
    "addr:postcode":"8020",
    "addr:street":"Legeweg",
    "iso:country":"BE",
    "sg:address":"Legeweg 163",
    "sg:city":"Oostkamp",
    "sg:classifiers":[
        {
            "category":"Manufacturing",
            "subcategory":"Petroleum Products",
            "type":"Manufacturing & Wholesale Goods"
        }
    ],
    "sg:phone":"+32 50 37 05 00",
    "sg:postcode":"8020",
    "sg:province":"West-Vlaanderen",
    "sg:tags":[
        "barrel",
        "cask"
    ],
    "wof:name":"Dumon Bvba",
    "wof:placetype":"venue"
},
  "geometry": {"coordinates":[3.2463619709,51.1732635498],"type":"Point"}
}