{
  "type": "Feature",
  "properties": {
    "iso:country":"BE",
    "sg:address":"Emile Vanderveldestraat 98",
    "sg:city":"Diest",
    "sg:orig_category":"Parfumeries",
    "sg:phone":"+32 13 31 32 20",
    "sg:postcode":"3290",
    "sg:province":"Vlaams-Brabant",
    "wof:name":"Georges Lemmens",
    "wof:placetype":"venue"
},
  "geometry": {"coordinates":[5.0503587723,50.9787979126],"type":"Point"}
}