{
  "type": "Feature",
  "properties": {
    "addr:full":"Place Cardinal Mercier 25 Bruxelles (jette) Bruxelles-Capitale 1090",
    "addr:housenumber":"25",
    "addr:postcode":"1090",
    "addr:street":"Place Cardinal Mercier",
    "iso:country":"BE",
    "sg:address":"Place Cardinal Mercier 25",
    "sg:city":"Bruxelles (jette)",
    "sg:classifiers":[
        {
            "category":"Bars & Pubs",
            "type":"Food & Drink"
        }
    ],
    "sg:phone":"+32 2 425 94 78",
    "sg:postcode":"1090",
    "sg:province":"Bruxelles-Capitale",
    "wof:name":"Barapaat",
    "wof:placetype":"venue"
},
  "geometry": {"coordinates":[4.3290557861,50.880065918],"type":"Point"}
}