{
  "type": "Feature",
  "properties": {
    "iso:country":"BE",
    "sg:address":"Hoogstraat 96a",
    "sg:city":"Lede",
    "sg:orig_category":"Banques de donn\u00e9es",
    "sg:phone":"+32 53 80 32 40",
    "sg:postcode":"9340",
    "sg:province":"Oost-Vlaanderen",
    "wof:name":"Euroscan Technologies",
    "wof:placetype":"venue"
},
  "geometry": {"coordinates":[3.9767420292,50.9600753784],"type":"Point"}
}