{
  "type": "Feature",
  "properties": {
    "addr:full":"Rue Fontenelle 33 Farciennes Hainaut 6240",
    "addr:housenumber":"33",
    "addr:postcode":"6240",
    "addr:street":"Rue Fontenelle",
    "iso:country":"BE",
    "sg:address":"Rue Fontenelle 33",
    "sg:city":"Farciennes",
    "sg:orig_category":"Airconditioning and ventilatie Bouwmaterialen Gh Loodgieterij, verwarming and sanitaire installaties",
    "sg:phone":"+32 71 81 71 61",
    "sg:postcode":"6240",
    "sg:province":"Hainaut",
    "wof:name":"Techno-confort",
    "wof:placetype":"venue"
},
  "geometry": {"coordinates":[4.5318698883,50.4505996704],"type":"Point"}
}