{
  "type": "Feature",
  "properties": {
    "iso:country":"BE",
    "sg:address":"Reepstraat 97",
    "sg:city":"Sint-gillis-waas",
    "sg:orig_category":"Plantes and fleurs Producteurs de l\u00e9gumes",
    "sg:phone":"+32 3 770 52 00",
    "sg:postcode":"9170",
    "sg:province":"Oost-Vlaanderen",
    "wof:name":"Patrick Van Guyse",
    "wof:placetype":"venue"
},
  "geometry": {"coordinates":[4.1035819054,51.227684021],"type":"Point"}
}