{
  "type": "Feature",
  "properties": {
    "addr:full":"Koninginnelaan 20a Oostende West-Vlaanderen 8400",
    "addr:housenumber":"20a",
    "addr:postcode":"8400",
    "addr:street":"Koninginnelaan",
    "iso:country":"BE",
    "sg:address":"Koninginnelaan 20a",
    "sg:city":"Oostende",
    "sg:orig_category":"Immobili\u00ebnkantoren Vakantiehuizen",
    "sg:phone":"+32 59 80 11 11",
    "sg:postcode":"8400",
    "sg:province":"West-Vlaanderen",
    "wof:name":"Broker",
    "wof:placetype":"venue"
},
  "geometry": {"coordinates":[2.9067339897,51.2257957458],"type":"Point"}
}