{
  "type": "Feature",
  "properties": {
    "iso:country":"BE",
    "sg:address":"Meidoornlaan 29",
    "sg:city":"Kapellen",
    "sg:orig_category":"Instituts de beaut\u00e9",
    "sg:phone":"+32 3 664 66 65",
    "sg:postcode":"2950",
    "sg:province":"Antwerpen",
    "wof:name":"Theodor Ludewigs",
    "wof:placetype":"venue"
},
  "geometry": {"coordinates":[4.4345760345,51.3230819702],"type":"Point"}
}