{
  "type": "Feature",
  "properties": {
    "addr:full":"Brusselstraat 310 Dilbeek Vlaams-Brabant 1702",
    "addr:housenumber":"310",
    "addr:postcode":"1702",
    "addr:street":"Brusselstraat",
    "iso:country":"BE",
    "sg:address":"Brusselstraat 310",
    "sg:city":"Dilbeek",
    "sg:orig_category":"Postkantoren Verzekeringsmakelaars and experts",
    "sg:phone":"+32 2 466 61 24",
    "sg:postcode":"1702",
    "sg:province":"Vlaams-Brabant",
    "wof:name":"De Post",
    "wof:placetype":"venue"
},
  "geometry": {"coordinates":[4.2583250999,50.870880127],"type":"Point"}
}