{
  "type": "Feature",
  "properties": {
    "iso:country":"BE",
    "sg:address":"Rue Gustave Demanet 8",
    "sg:city":"Brussel/bruxelles",
    "sg:orig_category":"V\u00eatements",
    "sg:phone":"+32 2 268 80 25",
    "sg:postcode":"1020",
    "sg:province":"Bruxelles-Capitale",
    "wof:name":"La Coque",
    "wof:placetype":"venue"
},
  "geometry": {"coordinates":[4.358399868,50.898021698],"type":"Point"}
}