{
  "type": "Feature",
  "properties": {
    "iso:country":"BE",
    "sg:address":"Karel De Roosestraat 15",
    "sg:city":"Merelbeke",
    "sg:orig_category":"Air conditionn\u00e9 and ventilation. Installation \u00e9lectrique industrielle",
    "sg:phone":"+32 9 210 04 11",
    "sg:postcode":"9820",
    "sg:province":"Oost-Vlaanderen",
    "wof:name":"A.t.s. Technics-bosteels",
    "wof:placetype":"venue"
},
  "geometry": {"coordinates":[3.7484099865,51.0054931641],"type":"Point"}
}