{
  "type": "Feature",
  "properties": {
    "iso:country":"BE",
    "sg:address":"Annegijsboslaan 20",
    "sg:city":"Overijse",
    "sg:classifiers":[
        {
            "category":"Home & Garden",
            "subcategory":"Carpets & Floor Coverings",
            "type":"Retail Goods"
        }
    ],
    "sg:phone":"+32 2 687 31 16",
    "sg:postcode":"3090",
    "sg:province":"Vlaams-Brabant",
    "sg:tags":[
        "-"
    ],
    "wof:name":"Josis Pablo",
    "wof:placetype":"venue"
},
  "geometry": {"coordinates":[4.5432338715,50.7650299072],"type":"Point"}
}