{
  "type": "Feature",
  "properties": {
    "addr:full":"Avenue De Messidor 316b3 Ukkel/uccle Bruxelles-Capitale 1180",
    "addr:housenumber":"316b3",
    "addr:postcode":"1180",
    "addr:street":"Avenue De Messidor;/",
    "iso:country":"BE",
    "sg:address":"Avenue De Messidor 316b3",
    "sg:city":"Ukkel/uccle",
    "sg:orig_category":"Avocats and conseillers juridiques",
    "sg:phone":"+32 2 343 19 66",
    "sg:postcode":"1180",
    "sg:province":"Bruxelles-Capitale",
    "wof:name":"C. Gilon",
    "wof:placetype":"venue"
},
  "geometry": {"coordinates":[4.3522539139,50.8116874695],"type":"Point"}
}