{
  "type": "Feature",
  "properties": {
    "addr:full":"Rue Th\u00e9odore Verhaegen 59-42 Bruxelles (saint-gilles) Bruxelles-Capitale 1060",
    "addr:postcode":"59-42;saint-gilles;1060",
    "addr:street":"Rue The\u0301Odore Verhaegen",
    "iso:country":"BE",
    "sg:address":"Rue Th\u00e9odore Verhaegen 59-42",
    "sg:city":"Bruxelles (saint-gilles)",
    "sg:classifiers":[
        {
            "category":"Professional",
            "subcategory":"Art Services",
            "type":"Services"
        }
    ],
    "sg:phone":"+32 2 537 80 64",
    "sg:postcode":"1060",
    "sg:province":"Bruxelles-Capitale",
    "sg:tags":[
        "sculptor"
    ],
    "wof:name":"Guelfi A",
    "wof:placetype":"venue"
},
  "geometry": {"coordinates":[4.3419017792,50.8282814026],"type":"Point"}
}