{
  "type": "Feature",
  "properties": {
    "iso:country":"BE",
    "sg:address":"Rue Des Bayards 22-24",
    "sg:city":"Li\u00e8ge 1",
    "sg:classifiers":[
        {
            "category":"Community Center",
            "type":"Public Place"
        }
    ],
    "sg:phone":"+32 4 227 19 80",
    "sg:postcode":"4000",
    "sg:province":"Li\u00e8ge",
    "sg:tags":[
        "box",
        "juke"
    ],
    "wof:name":"Bally Inter Sa",
    "wof:placetype":"venue"
},
  "geometry": {"coordinates":[5.601295948,50.6521644592],"type":"Point"}
}