{
  "type": "Feature",
  "properties": {
    "addr:full":"Kloosterstraat 90-92 Bornem Antwerpen 2880",
    "addr:postcode":"90-92;2880",
    "addr:street":"Kloosterstraat",
    "iso:country":"BE",
    "sg:address":"Kloosterstraat 90-92",
    "sg:city":"Bornem",
    "sg:classifiers":[
        {
            "category":"Fast Food",
            "type":"Food & Drink"
        }
    ],
    "sg:phone":"+32 3 889 06 26",
    "sg:postcode":"2880",
    "sg:province":"Antwerpen",
    "sg:tags":[
        "fried",
        "stand",
        "potato"
    ],
    "wof:name":"De Spar",
    "wof:placetype":"venue"
},
  "geometry": {"coordinates":[4.2243928909,51.093875885],"type":"Point"}
}