{
  "type": "Feature",
  "properties": {
    "addr:full":"Rue De Roloux 40bb Fexhe-le-haut-clocher Li\u00e8ge 4347",
    "addr:housenumber":"40bb",
    "addr:postcode":"4347",
    "addr:street":"Rue De Roloux",
    "iso:country":"BE",
    "sg:address":"Rue De Roloux 40bb",
    "sg:city":"Fexhe-le-haut-clocher",
    "sg:orig_category":"Binnenhuisarchitecten",
    "sg:phone":"+32 4 250 26 77",
    "sg:postcode":"4347",
    "sg:province":"Li\u00e8ge",
    "wof:name":"Jean-francois Thoma",
    "wof:placetype":"venue"
},
  "geometry": {"coordinates":[5.3988108635,50.6604270935],"type":"Point"}
}