{
  "type": "Feature",
  "properties": {
    "addr:full":"Stationsstraat 44 Zottegem Oost-Vlaanderen 9620",
    "addr:housenumber":"44",
    "addr:postcode":"9620",
    "addr:street":"Stationsstraat",
    "iso:country":"BE",
    "sg:address":"Stationsstraat 44",
    "sg:city":"Zottegem",
    "sg:orig_category":"Banken and kredietinstellingen",
    "sg:phone":"+32 9 360 14 91",
    "sg:postcode":"9620",
    "sg:province":"Oost-Vlaanderen",
    "wof:name":"Fortis",
    "wof:placetype":"venue"
},
  "geometry": {"coordinates":[3.813503027,50.8692016602],"type":"Point"}
}