{
  "type": "Feature",
  "properties": {
    "iso:country":"BE",
    "sg:address":"Place Albert Ier 46",
    "sg:city":"Charleroi",
    "sg:orig_category":"Assurances. Bureaux de poste",
    "sg:phone":"+32 71 31 47 59",
    "sg:postcode":"6061",
    "sg:province":"Hainaut",
    "wof:name":"La Poste",
    "wof:placetype":"venue"
},
  "geometry": {"coordinates":[4.4793901443,50.400390625],"type":"Point"}
}