{
  "type": "Feature",
  "properties": {
    "iso:country":"BE",
    "sg:address":"Grettouheid 118",
    "sg:city":"Pepinster",
    "sg:orig_category":"Traitements param\u00e9dicaux",
    "sg:phone":"+32 87 46 25 28",
    "sg:postcode":"4860",
    "sg:province":"Li\u00e8ge",
    "wof:name":"Ch. Karls",
    "wof:placetype":"venue"
},
  "geometry": {"coordinates":[5.7991089821,50.5735473633],"type":"Point"}
}