{
  "type": "Feature",
  "properties": {
    "addr:full":"Avenue Roi Albert 4 Andenne Namur 5300",
    "addr:housenumber":"4",
    "addr:postcode":"5300",
    "addr:street":"Avenue Roi Albert",
    "iso:country":"BE",
    "sg:address":"Avenue Roi Albert 4",
    "sg:city":"Andenne",
    "sg:classifiers":[
        {
            "category":"Shopping",
            "subcategory":"Books",
            "type":"Retail Goods"
        }
    ],
    "sg:phone":"+32 85 84 20 55",
    "sg:postcode":"5300",
    "sg:province":"Namur",
    "sg:tags":[
        "bookseller"
    ],
    "wof:name":"Bob Et Bobette",
    "wof:placetype":"venue"
},
  "geometry": {"coordinates":[5.0968060493,50.4910812378],"type":"Point"}
}