{
  "type": "Feature",
  "properties": {
    "addr:full":"Meerlaarstraat 14 Laakdal (forest) Antwerpen 2430",
    "addr:housenumber":"14",
    "addr:postcode":"2430",
    "addr:street":"Meerlaarstraat",
    "iso:country":"BE",
    "sg:address":"Meerlaarstraat 14",
    "sg:city":"Laakdal (forest)",
    "sg:classifiers":[
        {
            "category":"Building & Trades",
            "subcategory":"Landscaping Services",
            "type":"Services"
        }
    ],
    "sg:phone":"+32 13 66 42 39",
    "sg:postcode":"2430",
    "sg:province":"Antwerpen",
    "sg:tags":[
        "nurseryman"
    ],
    "wof:name":"Geeraerts M & Zn",
    "wof:placetype":"venue"
},
  "geometry": {"coordinates":[5.0522890091,51.0825157166],"type":"Point"}
}