{
  "type": "Feature",
  "properties": {
    "iso:country":"BE",
    "sg:address":"Kerkhoflaan 28",
    "sg:city":"Kortenberg",
    "sg:classifiers":[
        {
            "category":"Social Services",
            "subcategory":"Child Care",
            "type":"Services"
        }
    ],
    "sg:phone":"+32 2 757 00 05",
    "sg:postcode":"3070",
    "sg:province":"Vlaams-Brabant",
    "sg:tags":[
        "baby",
        "nursery",
        "day",
        "sitting"
    ],
    "wof:name":"Kapoentje ('t)",
    "wof:placetype":"venue"
},
  "geometry": {"coordinates":[4.5360450745,50.8892593384],"type":"Point"}
}