{
  "type": "Feature",
  "properties": {
    "iso:country":"BE",
    "sg:address":"Klosterstrasse 42",
    "sg:city":"Eupen",
    "sg:classifiers":[
        {
            "category":"Food & Beverages",
            "subcategory":"Groceries & Convenience Stores",
            "type":"Retail Goods"
        }
    ],
    "sg:phone":"+32 87 55 30 09",
    "sg:postcode":"4700",
    "sg:province":"Li\u00e8ge",
    "sg:tags":[
        "grocer"
    ],
    "wof:name":"Wertz K",
    "wof:placetype":"venue"
},
  "geometry": {"coordinates":[6.0316419601,50.6312026978],"type":"Point"}
}