{
  "type": "Feature",
  "properties": {
    "iso:country":"BE",
    "sg:address":"Rue De La Vall\u00e9e 63",
    "sg:city":"Ch\u00e2telet (ch\u00e2telineau)",
    "sg:classifiers":[
        {
            "category":"Shopping",
            "subcategory":"Florist",
            "type":"Retail Goods"
        }
    ],
    "sg:phone":"+32 71 39 33 76",
    "sg:postcode":"6200",
    "sg:province":"Hainaut",
    "wof:name":"Deco Flore",
    "wof:placetype":"venue"
},
  "geometry": {"coordinates":[4.5183868408,50.412815094],"type":"Point"}
}