{
  "type": "Feature",
  "properties": {
    "iso:country":"BE",
    "sg:address":"Blekerijstraat 22",
    "sg:city":"Gent",
    "sg:orig_category":"Architectes",
    "sg:phone":"+32 9 234 35 25",
    "sg:postcode":"9000",
    "sg:province":"Oost-Vlaanderen",
    "wof:name":"Ilse Degerickx",
    "wof:placetype":"venue"
},
  "geometry": {"coordinates":[3.7311620712,51.0597076416],"type":"Point"}
}