{
  "type": "Feature",
  "properties": {
    "iso:country":"BE",
    "sg:address":"Rue D\u00b4horue 91",
    "sg:city":"Braine-le-comte",
    "sg:orig_category":"Gespecialiseerde residenti\u00eble bouw Woningbouw",
    "sg:phone":"+32 67 55 35 98",
    "sg:postcode":"7090",
    "sg:province":"Hainaut",
    "wof:name":"Les Compagnons Entreprise",
    "wof:placetype":"venue"
},
  "geometry": {"coordinates":[4.1315641403,50.611038208],"type":"Point"}
}