{
  "type": "Feature",
  "properties": {
    "iso:country":"BE",
    "sg:address":"Centrum Zuid 3059",
    "sg:city":"Houthalen-helchteren (houthalen)",
    "sg:classifiers":[
        {
            "category":"Professional",
            "type":"Services"
        }
    ],
    "sg:phone":"+32 11 60 90 20",
    "sg:postcode":"3530",
    "sg:province":"Limburg",
    "sg:tags":[
        "industrial",
        "work",
        "-",
        "maintenance"
    ],
    "wof:name":"T.b.l.",
    "wof:placetype":"venue"
},
  "geometry": {"coordinates":[5.3600940704,51.0201454163],"type":"Point"}
}