{
  "type": "Feature",
  "properties": {
    "addr:full":"Rue Vanderborght 20 Bruxelles (koekelberg) Bruxelles-Capitale 1081",
    "addr:housenumber":"20",
    "addr:postcode":"1081",
    "addr:street":"Rue Vanderborght",
    "iso:country":"BE",
    "sg:address":"Rue Vanderborght 20",
    "sg:city":"Bruxelles (koekelberg)",
    "sg:classifiers":[
        {
            "category":"Professional",
            "subcategory":"Accounting & Tax Preparation",
            "type":"Services"
        }
    ],
    "sg:phone":"+32 2 426 42 19",
    "sg:postcode":"1081",
    "sg:province":"Bruxelles-Capitale",
    "sg:tags":[
        "accountant"
    ],
    "wof:name":"Parfait P",
    "wof:placetype":"venue"
},
  "geometry": {"coordinates":[4.3263201714,50.8662796021],"type":"Point"}
}