{
  "type": "Feature",
  "properties": {
    "addr:full":"Zoning Industriel De Bray Peronnes Binche Hainaut 7130",
    "addr:postcode":"7130",
    "addr:street":"Zoning Industriel De Bray Peronnes;Hainaut",
    "iso:country":"BE",
    "sg:address":"Zoning Industriel De Bray Peronnes",
    "sg:city":"Binche",
    "sg:classifiers":[
        {
            "category":"Building & Trades",
            "subcategory":"Construction",
            "type":"Services"
        }
    ],
    "sg:phone":"+32 64 33 18 44",
    "sg:postcode":"7130",
    "sg:province":"Hainaut",
    "sg:tags":[
        "duct",
        "underground",
        "ducting"
    ],
    "wof:name":"Sowal 92 Sa",
    "wof:placetype":"venue"
},
  "geometry": {"coordinates":[4.1660728455,50.412311554],"type":"Point"}
}