{
  "type": "Feature",
  "properties": {
    "iso:country":"BE",
    "sg:address":"Florimond Leirensstraat 24",
    "sg:city":"Wetteren",
    "sg:orig_category":"Opticiens",
    "sg:phone":"+32 9 369 52 88",
    "sg:postcode":"9230",
    "sg:province":"Oost-Vlaanderen",
    "wof:name":"Optimar",
    "wof:placetype":"venue"
},
  "geometry": {"coordinates":[3.8840389252,51.0056304932],"type":"Point"}
}