{
  "type": "Feature",
  "properties": {
    "iso:country":"BE",
    "sg:address":"Staatsbaan 215b2",
    "sg:city":"Bekkevoort",
    "sg:classifiers":[
        {
            "category":"Insurance",
            "subcategory":"Insurance Agent",
            "type":"Services"
        }
    ],
    "sg:phone":"+32 13 32 35 76",
    "sg:postcode":"3460",
    "sg:province":"Vlaams-Brabant",
    "sg:tags":[
        "verzekeringsmakelaars",
        "expert"
    ],
    "wof:name":"Marschou",
    "wof:placetype":"venue"
},
  "geometry": {"coordinates":[4.9718742371,50.9440689087],"type":"Point"}
}