{
  "type": "Feature",
  "properties": {
    "iso:country":"BE",
    "sg:address":"Rue De La Croix 18",
    "sg:city":"Welkenraedt",
    "sg:classifiers":[
        {
            "category":"Professional",
            "subcategory":"Management & Consulting",
            "type":"Services"
        }
    ],
    "sg:phone":"+32 87 66 24 09",
    "sg:postcode":"4840",
    "sg:province":"Li\u00e8ge",
    "sg:tags":[
        "consultant"
    ],
    "wof:name":"Baltus L",
    "wof:placetype":"venue"
},
  "geometry": {"coordinates":[5.9758648872,50.6633605957],"type":"Point"}
}