{
  "type": "Feature",
  "properties": {
    "addr:full":"Ieperstraat 70 Poperinge West-Vlaanderen 8970",
    "addr:housenumber":"70",
    "addr:postcode":"8970",
    "addr:street":"Ieperstraat",
    "iso:country":"BE",
    "sg:address":"Ieperstraat 70",
    "sg:city":"Poperinge",
    "sg:orig_category":"Boekhouders Verzekeringsmakelaars and experts",
    "sg:phone":"+32 57 33 57 35",
    "sg:postcode":"8970",
    "sg:province":"West-Vlaanderen",
    "wof:name":"De Leeuw",
    "wof:placetype":"venue"
},
  "geometry": {"coordinates":[2.7304189205,50.8544502258],"type":"Point"}
}