{
  "type": "Feature",
  "properties": {
    "iso:country":"BE",
    "sg:address":"Kapelstraat 16",
    "sg:city":"Hasselt",
    "sg:classifiers":[
        {
            "category":"Home & Garden",
            "subcategory":"Home Furnishings",
            "type":"Retail Goods"
        }
    ],
    "sg:phone":"+32 11 23 67 61",
    "sg:postcode":"3500",
    "sg:province":"Limburg",
    "sg:tags":[
        "linen",
        "household",
        "-"
    ],
    "wof:name":"Pastorie (de)",
    "wof:placetype":"venue"
},
  "geometry": {"coordinates":[5.3356080055,50.9297599792],"type":"Point"}
}