{
  "type": "Feature",
  "properties": {
    "addr:full":"Sint-bernardsesteenweg 77 Hemiksem Antwerpen 2620",
    "addr:housenumber":"77",
    "addr:postcode":"2620",
    "addr:street":"Sint-Bernardsesteenweg",
    "iso:country":"BE",
    "sg:address":"Sint-bernardsesteenweg 77",
    "sg:city":"Hemiksem",
    "sg:orig_category":"Plaatsen van vloer- and muurbekleding Schilders",
    "sg:phone":"+32 3 887 30 28",
    "sg:postcode":"2620",
    "sg:province":"Antwerpen",
    "wof:name":"Brits-clerbaut En Zn",
    "wof:placetype":"venue"
},
  "geometry": {"coordinates":[4.3355979919,51.1320381165],"type":"Point"}
}