{
  "type": "Feature",
  "properties": {
    "iso:country":"BE",
    "sg:address":"Rijksweg 11",
    "sg:city":"Bornem",
    "sg:orig_category":"Gelatine Capsules",
    "sg:phone":"+32 3 236 23 64",
    "sg:postcode":"2880",
    "sg:province":"Antwerpen",
    "wof:name":"Lambo Laboratoria Nv",
    "wof:placetype":"venue"
},
  "geometry": {"coordinates":[4.4536662102,51.214050293],"type":"Point"}
}