{
  "type": "Feature",
  "properties": {
    "iso:country":"BE",
    "sg:address":"Dambruggestraat 11-13",
    "sg:city":"Antwerpen",
    "sg:classifiers":[
        {
            "category":"Personal",
            "subcategory":"Beauty Salon",
            "type":"Services"
        }
    ],
    "sg:phone":"+32 3 232 42 24",
    "sg:postcode":"2060",
    "sg:province":"Antwerpen",
    "sg:tags":[
        "lady",
        "-",
        "hairdressing"
    ],
    "wof:name":"Gustaaf",
    "wof:placetype":"venue"
},
  "geometry": {"coordinates":[4.4233179092,51.2190551758],"type":"Point"}
}