{
  "type": "Feature",
  "properties": {
    "addr:full":"Schoolstraat 35 Waregem West-Vlaanderen 8791",
    "addr:housenumber":"35",
    "addr:postcode":"8791",
    "addr:street":"Schoolstraat",
    "iso:country":"BE",
    "sg:address":"Schoolstraat 35",
    "sg:city":"Waregem",
    "sg:orig_category":"Goederenvervoer over de weg",
    "sg:phone":"+32 56 71 86 43",
    "sg:postcode":"8791",
    "sg:province":"West-Vlaanderen",
    "wof:name":"Bouquet",
    "wof:placetype":"venue"
},
  "geometry": {"coordinates":[3.3373320103,50.8721923828],"type":"Point"}
}