{
  "type": "Feature",
  "properties": {
    "iso:country":"BE",
    "sg:address":"Lange Boomgaardstraat 21",
    "sg:city":"Gent",
    "sg:classifiers":[
        {
            "category":"Professional",
            "subcategory":"Art Services",
            "type":"Services"
        }
    ],
    "sg:phone":"+32 9 225 99 16",
    "sg:postcode":"9000",
    "sg:province":"Oost-Vlaanderen",
    "sg:tags":[
        "photographer"
    ],
    "wof:name":"Incognito",
    "wof:placetype":"venue"
},
  "geometry": {"coordinates":[3.7313489914,51.0512390137],"type":"Point"}
}