{
  "type": "Feature",
  "properties": {
    "addr:full":"Place Des Etangs 1 Anthisnes Li\u00e8ge 4160",
    "addr:housenumber":"1",
    "addr:postcode":"4160",
    "addr:street":"Place Des Etangs",
    "iso:country":"BE",
    "sg:address":"Place Des Etangs 1",
    "sg:city":"Anthisnes",
    "sg:classifiers":[
        {
            "category":"Health Services",
            "subcategory":"Health Practitioner",
            "type":"Services"
        }
    ],
    "sg:phone":"+32 4 383 66 52",
    "sg:postcode":"4160",
    "sg:province":"Li\u00e8ge",
    "sg:tags":[
        "physiotherapist"
    ],
    "wof:name":"Mossoux P",
    "wof:placetype":"venue"
},
  "geometry": {"coordinates":[5.5054020882,50.4741744995],"type":"Point"}
}