{
  "type": "Feature",
  "properties": {
    "addr:full":"Thier Du Goreu 12 Li\u00e8ge 1 (jupille-sur-meuse) Li\u00e8ge 4020",
    "addr:housenumber":"12;1",
    "addr:postcode":"4020",
    "addr:street":"Thier Du Goreu;Jupille-Sur-Meuse Lie\u0300Ge",
    "iso:country":"BE",
    "sg:address":"Thier Du Goreu 12",
    "sg:city":"Li\u00e8ge 1 (jupille-sur-meuse)",
    "sg:classifiers":[
        {
            "category":"Real Estate",
            "subcategory":"Surveying",
            "type":"Services"
        }
    ],
    "sg:phone":"+32 4 367 09 36",
    "sg:postcode":"4020",
    "sg:province":"Li\u00e8ge",
    "sg:tags":[
        "surveyor",
        "land"
    ],
    "wof:name":"Mahy F",
    "wof:placetype":"venue"
},
  "geometry": {"coordinates":[5.6336741447,50.6334838867],"type":"Point"}
}