{
  "type": "Feature",
  "properties": {
    "addr:full":"Leuvensestraat 63 Vilvoorde Vlaams-Brabant 1800",
    "addr:housenumber":"63",
    "addr:postcode":"1800",
    "addr:street":"Leuvensestraat",
    "iso:country":"BE",
    "sg:address":"Leuvensestraat 63",
    "sg:city":"Vilvoorde",
    "sg:orig_category":"Disquaires",
    "sg:phone":"+32 2 252 21 52",
    "sg:postcode":"1800",
    "sg:province":"Vlaams-Brabant",
    "wof:name":"Free Record Shop",
    "wof:placetype":"venue"
},
  "geometry": {"coordinates":[4.4276351929,50.9280509949],"type":"Point"}
}