{
  "type": "Feature",
  "properties": {
    "iso:country":"BE",
    "sg:address":"Belgi\u00eblei 105",
    "sg:city":"Antwerpen",
    "sg:classifiers":[
        {
            "category":"Health Services",
            "subcategory":"Doctor",
            "type":"Services"
        }
    ],
    "sg:phone":"+32 3 218 88 50",
    "sg:postcode":"2018",
    "sg:province":"Antwerpen",
    "sg:tags":[
        "medicinephysicians",
        "surgeon"
    ],
    "wof:name":"Kornitzer Marcel",
    "wof:placetype":"venue"
},
  "geometry": {"coordinates":[4.4180808067,51.2054634094],"type":"Point"}
}