{
  "type": "Feature",
  "properties": {
    "iso:country":"BE",
    "sg:address":"Kwerpseweg 10",
    "sg:city":"Kampenhout",
    "sg:orig_category":"Producteurs de l\u00e9gumes",
    "sg:phone":"+32 16 65 63 14",
    "sg:postcode":"1910",
    "sg:province":"Vlaams-Brabant",
    "wof:name":"Rene Verbist",
    "wof:placetype":"venue"
},
  "geometry": {"coordinates":[4.5635180473,50.9169616699],"type":"Point"}
}