{
  "type": "Feature",
  "properties": {
    "addr:full":"Rue Albert Meunier 75 Bruxelles (auderghem) Bruxelles-Capitale 1160",
    "addr:housenumber":"75",
    "addr:postcode":"1160",
    "addr:street":"Rue Albert Meunier",
    "iso:country":"BE",
    "sg:address":"Rue Albert Meunier 75",
    "sg:city":"Bruxelles (auderghem)",
    "sg:classifiers":[
        {
            "category":"Health Services",
            "subcategory":"Health Practitioner",
            "type":"Services"
        }
    ],
    "sg:phone":"+32 2 673 18 81",
    "sg:postcode":"1160",
    "sg:province":"Bruxelles-Capitale",
    "sg:tags":[
        "physiotherapist"
    ],
    "wof:name":"Wardavoir Helyett",
    "wof:placetype":"venue"
},
  "geometry": {"coordinates":[4.4371361732,50.8104820251],"type":"Point"}
}