{
  "type": "Feature",
  "properties": {
    "addr:full":"Avenue Henri De Brouck\u00e8re 43 Bruxelles (auderghem) Bruxelles-Capitale 1160",
    "addr:housenumber":"43",
    "addr:postcode":"1160",
    "addr:street":"Avenue Henri De Broucke\u0300Re",
    "iso:country":"BE",
    "sg:address":"Avenue Henri De Brouck\u00e8re 43",
    "sg:city":"Bruxelles (auderghem)",
    "sg:classifiers":[
        {
            "category":"Health Services",
            "subcategory":"Health Practitioner",
            "type":"Services"
        }
    ],
    "sg:phone":"+32 495 54 52 19",
    "sg:postcode":"1160",
    "sg:province":"Bruxelles-Capitale",
    "sg:tags":[
        "therapist",
        "speech"
    ],
    "wof:name":"Delplan Patricia",
    "wof:placetype":"venue"
},
  "geometry": {"coordinates":[4.4223389626,50.8178443909],"type":"Point"}
}