{
  "type": "Feature",
  "properties": {
    "iso:country":"BE",
    "sg:address":"Kwaremontplein 28",
    "sg:city":"Kluisbergen",
    "sg:orig_category":"Instituts de beaut\u00e9",
    "sg:phone":"+32 55 38 64 08",
    "sg:postcode":"9690",
    "sg:province":"Oost-Vlaanderen",
    "wof:name":"Instituut L'artisane",
    "wof:placetype":"venue"
},
  "geometry": {"coordinates":[3.5245831013,50.776512146],"type":"Point"}
}