{
  "type": "Feature",
  "properties": {
    "addr:full":"Avenue Du Cimeti\u00c8re 0 Sambreville Namur 5060",
    "addr:housenumber":"0",
    "addr:postcode":"5060",
    "addr:street":"Avenue Du Cimetie\u0300Re",
    "iso:country":"BE",
    "sg:address":"Avenue Du Cimeti\u00c8re 0",
    "sg:city":"Sambreville",
    "sg:orig_category":"Enseignement maternel and primaire",
    "sg:phone":"+32 71 77 47 49",
    "sg:postcode":"5060",
    "sg:province":"Namur",
    "wof:name":"Ecole Fondamentale",
    "wof:placetype":"venue"
},
  "geometry": {"coordinates":[4.6285200119,50.4448738098],"type":"Point"}
}