{
  "type": "Feature",
  "properties": {
    "addr:full":"Leenakkerstraat 35 Waregem (beveren-leie) West-Vlaanderen 8791",
    "addr:housenumber":"35",
    "addr:postcode":"8791",
    "addr:street":"Leenakkerstraat",
    "iso:country":"BE",
    "sg:address":"Leenakkerstraat 35",
    "sg:city":"Waregem (beveren-leie)",
    "sg:classifiers":[
        {
            "category":"Home & Garden",
            "subcategory":"Kitchen Supply",
            "type":"Retail Goods"
        }
    ],
    "sg:phone":"+32 56 71 20 96",
    "sg:postcode":"8791",
    "sg:province":"West-Vlaanderen",
    "sg:tags":[
        "installation"
    ],
    "wof:name":"Depoortere O & Zn",
    "wof:placetype":"venue"
},
  "geometry": {"coordinates":[3.3395659924,50.8677330017],"type":"Point"}
}