{
  "type": "Feature",
  "properties": {
    "addr:full":"Jetteselaan 392 Ganshoren Bruxelles-Capitale 1083",
    "addr:housenumber":"392",
    "addr:postcode":"1083",
    "addr:street":"Jetteselaan",
    "iso:country":"BE",
    "sg:address":"Jetteselaan 392",
    "sg:city":"Ganshoren",
    "sg:orig_category":"Kapsalons",
    "sg:phone":"+32 2 428 58 19",
    "sg:postcode":"1083",
    "sg:province":"Bruxelles-Capitale",
    "wof:name":"New Wave Hair",
    "wof:placetype":"venue"
},
  "geometry": {"coordinates":[4.3203921318,50.8754272461],"type":"Point"}
}