{
  "type": "Feature",
  "properties": {
    "addr:full":"Tieltsteenweg 6 Oostrozebeke West-Vlaanderen 8780",
    "addr:housenumber":"6",
    "addr:postcode":"8780",
    "addr:street":"Tieltsteenweg",
    "iso:country":"BE",
    "sg:address":"Tieltsteenweg 6",
    "sg:city":"Oostrozebeke",
    "sg:orig_category":"RESTAURANTS: ALIMENTATION SP\u00c9CIALIS\u00c9E",
    "sg:phone":"+32 56 66 76 57",
    "sg:postcode":"8780",
    "sg:province":"West-Vlaanderen",
    "wof:name":"Mistral",
    "wof:placetype":"venue"
},
  "geometry": {"coordinates":[3.3363280296,50.9219207764],"type":"Point"}
}