{
  "type": "Feature",
  "properties": {
    "iso:country":"BE",
    "sg:address":"Veerstraat 1",
    "sg:city":"Kluisbergen (ruien)",
    "sg:classifiers":[
        {
            "category":"Retail",
            "subcategory":"Event Space",
            "type":"Services"
        }
    ],
    "sg:phone":"+32 55 30 58 05",
    "sg:postcode":"9690",
    "sg:province":"Oost-Vlaanderen",
    "sg:tags":[
        "organisation"
    ],
    "wof:name":"B.b.o. Bvba",
    "wof:placetype":"venue"
},
  "geometry": {"coordinates":[3.475372076,50.7678031921],"type":"Point"}
}