{
  "type": "Feature",
  "properties": {
    "addr:full":"Haachtsesteenweg 111 Brussel Bruxelles-Capitale 1030",
    "addr:housenumber":"111",
    "addr:postcode":"1030",
    "addr:street":"Haachtsesteenweg",
    "iso:country":"BE",
    "sg:address":"Haachtsesteenweg 111",
    "sg:city":"Brussel",
    "sg:orig_category":"Kruideniers Rookartikelen",
    "sg:phone":"+32 2 217 96 30",
    "sg:postcode":"1030",
    "sg:province":"Bruxelles-Capitale",
    "wof:name":"Vizyon",
    "wof:placetype":"venue"
},
  "geometry": {"coordinates":[4.3698382378,50.8580245972],"type":"Point"}
}