{
  "type": "Feature",
  "properties": {
    "iso:country":"BE",
    "sg:address":"Stoktevijver 50",
    "sg:city":"Zomergem",
    "sg:classifiers":[
        {
            "category":"Retail",
            "subcategory":"Veterinary Services",
            "type":"Services"
        }
    ],
    "sg:phone":"+32 9 372 81 10",
    "sg:postcode":"9930",
    "sg:province":"Oost-Vlaanderen",
    "sg:tags":[
        "veterinarian"
    ],
    "wof:name":"De Neve G",
    "wof:placetype":"venue"
},
  "geometry": {"coordinates":[3.5596969128,51.1409797668],"type":"Point"}
}