{
  "type": "Feature",
  "properties": {
    "addr:full":"Generaal Baron Jacquesstraat 53 Diksmuide West-Vlaanderen 8600",
    "addr:housenumber":"53",
    "addr:postcode":"8600",
    "addr:street":"Generaal Baron Jacquesstraat",
    "iso:country":"BE",
    "sg:address":"Generaal Baron Jacquesstraat 53",
    "sg:city":"Diksmuide",
    "sg:classifiers":[
        {
            "category":"Home & Garden",
            "subcategory":"Carpets & Floor Coverings",
            "type":"Retail Goods"
        }
    ],
    "sg:phone":"+32 51 51 08 01",
    "sg:postcode":"8600",
    "sg:province":"West-Vlaanderen",
    "sg:tags":[
        "material",
        "waterproofing"
    ],
    "wof:name":"Joan Products Bvba",
    "wof:placetype":"venue"
},
  "geometry": {"coordinates":[2.8605918884,51.0335426331],"type":"Point"}
}