{
  "type": "Feature",
  "properties": {
    "iso:country":"BE",
    "sg:address":"Diksmuidseweg 367",
    "sg:city":"Ieper",
    "sg:orig_category":"Experts-comptables",
    "sg:phone":"+32 57 42 33 93",
    "sg:postcode":"8904",
    "sg:province":"West-Vlaanderen",
    "wof:name":"Marc Benoot",
    "wof:placetype":"venue"
},
  "geometry": {"coordinates":[2.8613901138,50.8924255371],"type":"Point"}
}