{
  "type": "Feature",
  "properties": {
    "iso:country":"BE",
    "sg:address":"Dennenlaan 52",
    "sg:city":"Beveren",
    "sg:orig_category":"Landmeters",
    "sg:phone":"+32 3 775 67 54",
    "sg:postcode":"9120",
    "sg:province":"Oost-Vlaanderen",
    "wof:name":"Le Fevere De Ten Hove",
    "wof:placetype":"venue"
},
  "geometry": {"coordinates":[4.2115130424,51.1845817566],"type":"Point"}
}