{
  "type": "Feature",
  "properties": {
    "addr:full":"Maasstraat 65 Antwerpen Antwerpen 2060",
    "addr:housenumber":"65",
    "addr:postcode":"2060",
    "addr:street":"Maasstraat",
    "iso:country":"BE",
    "sg:address":"Maasstraat 65",
    "sg:city":"Antwerpen",
    "sg:classifiers":[
        {
            "category":"Shopping",
            "subcategory":"Clothing, Apparel, & Fashions",
            "type":"Retail Goods"
        }
    ],
    "sg:phone":"+32 3 233 84 17",
    "sg:postcode":"2060",
    "sg:province":"Antwerpen",
    "sg:tags":[
        "lingerie",
        "sous-v\u00eatements"
    ],
    "wof:name":"Auwers Gebrs & Zn",
    "wof:placetype":"venue"
},
  "geometry": {"coordinates":[4.4270977974,51.2346229553],"type":"Point"}
}