{
  "type": "Feature",
  "properties": {
    "iso:country":"BE",
    "sg:address":"Bruggestraat 45",
    "sg:city":"Hooglede",
    "sg:classifiers":[
        {
            "category":"Education",
            "subcategory":"Special Training",
            "type":"Public Place"
        }
    ],
    "sg:phone":"+32 51 20 36 65",
    "sg:postcode":"8830",
    "sg:province":"West-Vlaanderen",
    "sg:tags":[
        "bread"
    ],
    "wof:name":"Vermaut's Boerenbrood Nv",
    "wof:placetype":"venue"
},
  "geometry": {"coordinates":[3.087045908,50.9798088074],"type":"Point"}
}