{
  "type": "Feature",
  "properties": {
    "addr:full":"Gehuchtstraat 7 Sint-genesius-rode Vlaams-Brabant 1640",
    "addr:housenumber":"7",
    "addr:postcode":"1640",
    "addr:street":"Gehuchtstraat",
    "iso:country":"BE",
    "sg:address":"Gehuchtstraat 7",
    "sg:city":"Sint-genesius-rode",
    "sg:orig_category":"Decoratieve kunst and kunstbenodigdheden Tuinen",
    "sg:phone":"+32 2 380 74 31",
    "sg:postcode":"1640",
    "sg:province":"Vlaams-Brabant",
    "wof:name":"Ideal Garden",
    "wof:placetype":"venue"
},
  "geometry": {"coordinates":[4.3608598709,50.7388191223],"type":"Point"}
}