{
  "type": "Feature",
  "properties": {
    "iso:country":"BE",
    "sg:address":"Sint Jansstraat 15",
    "sg:city":"Koksijde",
    "sg:orig_category":"Sportclubs",
    "sg:phone":"+32 58 23 58 85",
    "sg:postcode":"8670",
    "sg:province":"West-Vlaanderen",
    "wof:name":"West Aviation Club",
    "wof:placetype":"venue"
},
  "geometry": {"coordinates":[2.6492800713,51.1061401367],"type":"Point"}
}