{
  "type": "Feature",
  "properties": {
    "addr:full":"Place Du Petit Sablon 5 Bruxelles Bruxelles-Capitale 1000",
    "addr:housenumber":"5",
    "addr:postcode":"1000",
    "addr:street":"Place Du Petit Sablon",
    "iso:country":"BE",
    "sg:address":"Place Du Petit Sablon 5",
    "sg:city":"Bruxelles",
    "sg:classifiers":[
        {
            "category":"Shopping",
            "subcategory":"Musical Instruments",
            "type":"Retail Goods"
        }
    ],
    "sg:phone":"+32 2 511 66 74",
    "sg:postcode":"1000",
    "sg:province":"Bruxelles-Capitale",
    "sg:tags":[
        "-"
    ],
    "wof:name":"Meuwissen T",
    "wof:placetype":"venue"
},
  "geometry": {"coordinates":[4.3545198441,50.8415298462],"type":"Point"}
}