{
  "type": "Feature",
  "properties": {
    "addr:full":"Terhulpsesteenweg 219 Watermaal-bosvoorde/watermael-boitsfort Bruxelles-Capitale 1170",
    "addr:housenumber":"219",
    "addr:postcode":"1170",
    "addr:street":"Terhulpsesteenweg",
    "iso:country":"BE",
    "sg:address":"Terhulpsesteenweg 219",
    "sg:city":"Watermaal-bosvoorde/watermael-boitsfort",
    "sg:orig_category":"Secretariaatsdiensten",
    "sg:phone":"+32 2 663 14 19",
    "sg:postcode":"1170",
    "sg:province":"Bruxelles-Capitale",
    "wof:name":"Fe. Fisa",
    "wof:placetype":"venue"
},
  "geometry": {"coordinates":[4.4165930748,50.7942771912],"type":"Point"}
}