{
  "type": "Feature",
  "properties": {
    "iso:country":"BE",
    "sg:address":"J. Van Rijswijcklaan 100",
    "sg:city":"Antwerpen",
    "sg:orig_category":"Vertalers and tolken",
    "sg:phone":"+32 3 237 22 09",
    "sg:postcode":"2018",
    "sg:province":"Antwerpen",
    "wof:name":"Seidenberg A. Cbtip/bkvtf",
    "wof:placetype":"venue"
},
  "geometry": {"coordinates":[4.4025530815,51.1946678162],"type":"Point"}
}