{
  "type": "Feature",
  "properties": {
    "addr:full":"Veldbrugstraat 45 Zelzate Oost-Vlaanderen 9060",
    "addr:housenumber":"45",
    "addr:postcode":"9060",
    "addr:street":"Veldbrugstraat",
    "iso:country":"BE",
    "sg:address":"Veldbrugstraat 45",
    "sg:city":"Zelzate",
    "sg:classifiers":[
        {
            "category":"Retail",
            "subcategory":"Event Space",
            "type":"Services"
        }
    ],
    "sg:phone":"+32 9 344 86 78",
    "sg:postcode":"9060",
    "sg:province":"Oost-Vlaanderen",
    "sg:tags":[
        "pipeline"
    ],
    "wof:name":"Cosnefroy Vof",
    "wof:placetype":"venue"
},
  "geometry": {"coordinates":[3.797013998,51.1959915161],"type":"Point"}
}