{
  "type": "Feature",
  "properties": {
    "iso:country":"BE",
    "sg:address":"Antwerpsesteenweg 116",
    "sg:city":"Lier",
    "sg:classifiers":[
        {
            "category":"Fast Food",
            "type":"Food & Drink"
        }
    ],
    "sg:phone":"+32 3 489 05 72",
    "sg:postcode":"2500",
    "sg:province":"Antwerpen",
    "sg:tags":[
        "\u00c0",
        "emporter",
        "restaurants"
    ],
    "wof:name":"Frituur Kelly",
    "wof:placetype":"venue"
},
  "geometry": {"coordinates":[4.5567479134,51.1391487122],"type":"Point"}
}