{
  "type": "Feature",
  "properties": {
    "addr:full":"Klapstraat 9 Sint-martens-latem Oost-Vlaanderen 9831",
    "addr:housenumber":"9",
    "addr:postcode":"9831",
    "addr:street":"Klapstraat",
    "iso:country":"BE",
    "sg:address":"Klapstraat 9",
    "sg:city":"Sint-martens-latem",
    "sg:orig_category":"Production and transformation de viande",
    "sg:phone":"+32 9 282 31 89",
    "sg:postcode":"9831",
    "sg:province":"Oost-Vlaanderen",
    "wof:name":"S. Covent",
    "wof:placetype":"venue"
},
  "geometry": {"coordinates":[3.6072690487,50.9965591431],"type":"Point"}
}