{
  "type": "Feature",
  "properties": {
    "iso:country":"BE",
    "sg:address":"Rue Paul D\u00b4andrimont 47",
    "sg:city":"Micheroux",
    "sg:orig_category":"V\u00e9hicules automobiles",
    "sg:phone":"+32 4 377 50 83",
    "sg:postcode":"4630",
    "sg:province":"Li\u00e8ge",
    "wof:name":"Deby Car Service",
    "wof:placetype":"venue"
},
  "geometry": {"coordinates":[5.7151842117,50.625667572],"type":"Point"}
}