{
  "type": "Feature",
  "properties": {
    "iso:country":"BE",
    "sg:address":"Route Charlemagne 21",
    "sg:city":"Couvin",
    "sg:classifiers":[
        {
            "category":"Home & Garden",
            "subcategory":"Carpets & Floor Coverings",
            "type":"Retail Goods"
        }
    ],
    "sg:phone":"+32 60 34 40 04",
    "sg:postcode":"5660",
    "sg:province":"Namur",
    "sg:tags":[
        "-",
        "rug"
    ],
    "wof:name":"Atelier Couvinois Du Tapis",
    "wof:placetype":"venue"
},
  "geometry": {"coordinates":[4.4950699806,50.0608406067],"type":"Point"}
}