{
  "type": "Feature",
  "properties": {
    "addr:full":"Moleneinde 22 Ravels (weelde) Antwerpen 2381",
    "addr:housenumber":"22",
    "addr:postcode":"2381",
    "addr:street":"Moleneinde",
    "iso:country":"BE",
    "sg:address":"Moleneinde 22",
    "sg:city":"Ravels (weelde)",
    "sg:classifiers":[
        {
            "category":"Home & Garden",
            "subcategory":"Hardware",
            "type":"Retail Goods"
        }
    ],
    "sg:phone":"+32 14 65 00 84",
    "sg:postcode":"2381",
    "sg:province":"Antwerpen",
    "sg:tags":[
        "fixing",
        "material"
    ],
    "wof:name":"Cargo Control Plus Bv",
    "wof:placetype":"venue"
},
  "geometry": {"coordinates":[5.012196064,51.4026412964],"type":"Point"}
}