{
  "type": "Feature",
  "properties": {
    "addr:full":"Gentpoortstraat 33 Brugge West-Vlaanderen 8000",
    "addr:housenumber":"33",
    "addr:postcode":"8000",
    "addr:street":"Gentpoortstraat",
    "iso:country":"BE",
    "sg:address":"Gentpoortstraat 33",
    "sg:city":"Brugge",
    "sg:classifiers":[
        {
            "category":"Health Services",
            "subcategory":"Doctor",
            "type":"Services"
        }
    ],
    "sg:phone":"+32 50 34 26 26",
    "sg:postcode":"8000",
    "sg:province":"West-Vlaanderen",
    "sg:tags":[
        "medicinephysicians",
        "surgeon"
    ],
    "wof:name":"Balli\u00e8re P",
    "wof:placetype":"venue"
},
  "geometry": {"coordinates":[3.2326469421,51.2038421631],"type":"Point"}
}