{
  "type": "Feature",
  "properties": {
    "addr:full":"Rue Du Roi Albert 113 Seraing Li\u00e8ge 4102",
    "addr:housenumber":"113",
    "addr:postcode":"4102",
    "addr:street":"Rue Du Roi Albert",
    "iso:country":"BE",
    "sg:address":"Rue Du Roi Albert 113",
    "sg:city":"Seraing",
    "sg:orig_category":"Artsen and specialisten",
    "sg:phone":"+32 4 337 44 92",
    "sg:postcode":"4102",
    "sg:province":"Li\u00e8ge",
    "wof:name":"Albert Morsa",
    "wof:placetype":"venue"
},
  "geometry": {"coordinates":[5.5381140709,50.6008987427],"type":"Point"}
}