{
  "type": "Feature",
  "properties": {
    "iso:country":"BE",
    "sg:address":"Donkvijverstraat 13",
    "sg:city":"Beveren",
    "sg:orig_category":"D\u00e9taillants en pi\u00e8ces and accessoires de voitures",
    "sg:phone":"+32 3 775 16 86",
    "sg:postcode":"9120",
    "sg:province":"Oost-Vlaanderen",
    "wof:name":"Wb Autocenter",
    "wof:placetype":"venue"
},
  "geometry": {"coordinates":[4.2525429726,51.2147827148],"type":"Point"}
}