{
  "type": "Feature",
  "properties": {
    "addr:full":"Quartier Saint-amand 12 Espierres-helchin (espierres) West-Vlaanderen 8587",
    "addr:housenumber":"12",
    "addr:postcode":"8587",
    "addr:street":"Quartier Saint-Amand;Espierres",
    "iso:country":"BE",
    "sg:address":"Quartier Saint-amand 12",
    "sg:city":"Espierres-helchin (espierres)",
    "sg:classifiers":[
        {
            "category":"Professional",
            "subcategory":"Computer Services",
            "type":"Services"
        }
    ],
    "sg:phone":"+32 56 45 55 20",
    "sg:postcode":"8587",
    "sg:province":"West-Vlaanderen",
    "sg:tags":[
        "-",
        "processing",
        "data"
    ],
    "wof:name":"E.r. Computers",
    "wof:placetype":"venue"
},
  "geometry": {"coordinates":[3.3560020924,50.7193183899],"type":"Point"}
}