{
  "type": "Feature",
  "properties": {
    "iso:country":"BE",
    "sg:address":"Rue Roc Saint-nicaise 18",
    "sg:city":"Doornik",
    "sg:orig_category":"Eclairage et \u00e9quipements du foyer",
    "sg:phone":"+32 69 84 24 12",
    "sg:postcode":"7500",
    "sg:province":"Hainaut",
    "wof:name":"Spiridon",
    "wof:placetype":"venue"
},
  "geometry": {"coordinates":[3.383769989,50.6055183411],"type":"Point"}
}