{
  "type": "Feature",
  "properties": {
    "iso:country":"BE",
    "sg:address":"Ind. Park Brechtsebaan 18b1",
    "sg:city":"Schoten",
    "sg:orig_category":"Installation de menuiserie m\u00e9tallique",
    "sg:phone":"+32 3 685 47 43",
    "sg:postcode":"2900",
    "sg:province":"Antwerpen",
    "wof:name":"T.m.c.",
    "wof:placetype":"venue"
},
  "geometry": {"coordinates":[4.5107097626,51.2652397156],"type":"Point"}
}