{
  "type": "Feature",
  "properties": {
    "iso:country":"BE",
    "sg:address":"Avenue Kersbeek 241",
    "sg:city":"Vorst/forest",
    "sg:orig_category":"M\u00e9decins and sp\u00e9cialistes",
    "sg:phone":"+32 2 376 54 03",
    "sg:postcode":"1190",
    "sg:province":"Bruxelles-Capitale",
    "wof:name":"Jean-paul Darte",
    "wof:placetype":"venue"
},
  "geometry": {"coordinates":[4.3203988075,50.8023376465],"type":"Point"}
}