{
  "type": "Feature",
  "properties": {
    "addr:full":"Olmstraat 31 Vilvoorde Vlaams-Brabant 1800",
    "addr:housenumber":"31",
    "addr:postcode":"1800",
    "addr:street":"Olmstraat",
    "iso:country":"BE",
    "sg:address":"Olmstraat 31",
    "sg:city":"Vilvoorde",
    "sg:classifiers":[
        {
            "category":"Community Center",
            "type":"Public Place"
        }
    ],
    "sg:phone":"+32 2 251 43 70",
    "sg:postcode":"1800",
    "sg:province":"Vlaams-Brabant",
    "sg:tags":[
        "medical"
    ],
    "wof:name":"Premed Vzw",
    "wof:placetype":"venue"
},
  "geometry": {"coordinates":[4.4333691597,50.9288749695],"type":"Point"}
}