{
  "type": "Feature",
  "properties": {
    "addr:full":"Gr.l.de Lichterveldestr. 15 Gavere Oost-Vlaanderen 9890",
    "addr:housenumber":"15",
    "addr:postcode":"9890",
    "iso:country":"BE",
    "sg:address":"Gr.l.de Lichterveldestr. 15",
    "sg:city":"Gavere",
    "sg:classifiers":[
        {
            "category":"Personal",
            "subcategory":"Beauty Salon",
            "type":"Services"
        }
    ],
    "sg:phone":"+32 9 384 32 67",
    "sg:postcode":"9890",
    "sg:province":"Oost-Vlaanderen",
    "sg:tags":[
        "de",
        "coiffure"
    ],
    "wof:name":"Coiffure Marleen",
    "wof:placetype":"venue"
},
  "geometry": {"coordinates":[3.6953780651,50.9171600342],"type":"Point"}
}