{
  "type": "Feature",
  "properties": {
    "iso:country":"BE",
    "sg:address":"Rue Robert Boisacq 1",
    "sg:city":"Rixensart",
    "sg:classifiers":[
        {
            "category":"Home & Garden",
            "subcategory":"Home Furnishings",
            "type":"Retail Goods"
        }
    ],
    "sg:phone":"+32 2 654 17 71",
    "sg:postcode":"1330",
    "sg:province":"Brabant Wallon",
    "sg:tags":[
        "interior",
        "decoration"
    ],
    "wof:name":"Atelier (l')",
    "wof:placetype":"venue"
},
  "geometry": {"coordinates":[4.530298233,50.7127342224],"type":"Point"}
}