{
  "type": "Feature",
  "properties": {
    "addr:full":"Horzelstraat 92 Ukkel/uccle Bruxelles-Capitale 1180",
    "addr:housenumber":"92",
    "addr:postcode":"1180",
    "addr:street":"Horzelstraat;/",
    "iso:country":"BE",
    "sg:address":"Horzelstraat 92",
    "sg:city":"Ukkel/uccle",
    "sg:orig_category":"Benzinestations and brandstoffen Herstellingen and onderhoud van auto's Voertuigen",
    "sg:phone":"+32 2 376 01 69",
    "sg:postcode":"1180",
    "sg:province":"Bruxelles-Capitale",
    "wof:name":"L.s. Car",
    "wof:placetype":"venue"
},
  "geometry": {"coordinates":[4.3319897652,50.7855834961],"type":"Point"}
}