{
  "type": "Feature",
  "properties": {
    "addr:full":"Chauss\u00e9e De Louvain 975 Namur (cognel\u00e9e) Namur 5022",
    "addr:housenumber":"975",
    "addr:postcode":"5022",
    "addr:street":"Chausse\u0301E De Louvain",
    "iso:country":"BE",
    "sg:address":"Chauss\u00e9e De Louvain 975",
    "sg:city":"Namur (cognel\u00e9e)",
    "sg:classifiers":[
        {
            "category":"Wholesale",
            "subcategory":"Fruits & Vegetables",
            "type":"Manufacturing & Wholesale Goods"
        }
    ],
    "sg:phone":"+32 81 21 44 87",
    "sg:postcode":"5022",
    "sg:province":"Namur",
    "sg:tags":[
        "whol",
        "-"
    ],
    "wof:name":"P\u00e8re Cl\u00e9ment (au)",
    "wof:placetype":"venue"
},
  "geometry": {"coordinates":[4.902985096,50.513671875],"type":"Point"}
}