{
  "type": "Feature",
  "properties": {
    "addr:full":"Valleilaan 49 Diest Vlaams-Brabant 3290",
    "addr:housenumber":"49",
    "addr:postcode":"3290",
    "addr:street":"Valleilaan",
    "iso:country":"BE",
    "sg:address":"Valleilaan 49",
    "sg:city":"Diest",
    "sg:classifiers":[
        {
            "category":"Health Services",
            "subcategory":"Dentist",
            "type":"Services"
        }
    ],
    "sg:phone":"+32 13 31 47 07",
    "sg:postcode":"3290",
    "sg:province":"Vlaams-Brabant",
    "wof:name":"Drijvers Francis",
    "wof:placetype":"venue"
},
  "geometry": {"coordinates":[5.0473709106,50.9869384766],"type":"Point"}
}