{
  "type": "Feature",
  "properties": {
    "addr:full":"Weidestraat 3 Torhout West-Vlaanderen 8820",
    "addr:housenumber":"3",
    "addr:postcode":"8820",
    "addr:street":"Weidestraat",
    "iso:country":"BE",
    "sg:address":"Weidestraat 3",
    "sg:city":"Torhout",
    "sg:classifiers":[
        {
            "category":"Banks & Credit Unions",
            "subcategory":"Investment Brokerage",
            "type":"Services"
        }
    ],
    "sg:phone":"+32 50 21 59 30",
    "sg:postcode":"8820",
    "sg:province":"West-Vlaanderen",
    "sg:tags":[
        "repair",
        "-",
        "installation",
        "sanitary",
        "article"
    ],
    "wof:name":"Mortier",
    "wof:placetype":"venue"
},
  "geometry": {"coordinates":[3.0942149162,51.0858192444],"type":"Point"}
}