{
  "type": "Feature",
  "properties": {
    "addr:full":"Paalstraat 4 Schoten Antwerpen 2900",
    "addr:housenumber":"4",
    "addr:postcode":"2900",
    "addr:street":"Paalstraat",
    "iso:country":"BE",
    "sg:address":"Paalstraat 4",
    "sg:city":"Schoten",
    "sg:classifiers":[
        {
            "category":"Insurance",
            "subcategory":"Insurance Agent",
            "type":"Services"
        }
    ],
    "sg:phone":"+32 3 658 12 00",
    "sg:postcode":"2900",
    "sg:province":"Antwerpen",
    "sg:tags":[
        "broker"
    ],
    "wof:name":"Fidelia Bvba",
    "wof:placetype":"venue"
},
  "geometry": {"coordinates":[4.4989161491,51.2512550354],"type":"Point"}
}