{
  "type": "Feature",
  "properties": {
    "addr:full":"Dokter Haekstraat 33b Dendermonde Oost-Vlaanderen 9200",
    "addr:housenumber":"33b",
    "addr:postcode":"9200",
    "addr:street":"Dokter Haekstraat;Oost-Vlaanderen",
    "iso:country":"BE",
    "sg:address":"Dokter Haekstraat 33b",
    "sg:city":"Dendermonde",
    "sg:orig_category":"Postkantoren Verzekeringsmakelaars and experts",
    "sg:phone":"+32 52 25 04 79",
    "sg:postcode":"9200",
    "sg:province":"Oost-Vlaanderen",
    "wof:name":"De Post",
    "wof:placetype":"venue"
},
  "geometry": {"coordinates":[4.1070251465,51.0517654419],"type":"Point"}
}