{
  "type": "Feature",
  "properties": {
    "iso:country":"BE",
    "sg:address":"Rue Du Trieu P\u00e9rilleux 54",
    "sg:city":"Ath",
    "sg:classifiers":[
        {
            "category":"Real Estate",
            "subcategory":"Surveying",
            "type":"Services"
        }
    ],
    "sg:phone":"+32 68 28 42 52",
    "sg:postcode":"7800",
    "sg:province":"Hainaut",
    "sg:tags":[
        "surveyor",
        "land"
    ],
    "wof:name":"Colinet A",
    "wof:placetype":"venue"
},
  "geometry": {"coordinates":[3.8041200638,50.6275291443],"type":"Point"}
}