{
  "type": "Feature",
  "properties": {
    "iso:country":"BE",
    "sg:address":"Rue De L'instruction 121",
    "sg:city":"Bruxelles (anderlecht)",
    "sg:classifiers":[
        {
            "category":"Shopping",
            "subcategory":"Clothing, Apparel, & Fashions",
            "type":"Retail Goods"
        }
    ],
    "sg:phone":"+32 2 522 81 28",
    "sg:postcode":"1070",
    "sg:province":"Bruxelles-Capitale",
    "sg:tags":[
        "leather",
        "-",
        "buckskin",
        "clothing"
    ],
    "wof:name":"Isaco",
    "wof:placetype":"venue"
},
  "geometry": {"coordinates":[4.3307561874,50.8367881775],"type":"Point"}
}