{
  "type": "Feature",
  "properties": {
    "iso:country":"BE",
    "sg:address":"Chauss\u00c9e De Tongres 8",
    "sg:city":"Amay",
    "sg:orig_category":"M\u00e9decins and sp\u00e9cialistes",
    "sg:phone":"+32 85 31 38 87",
    "sg:postcode":"4540",
    "sg:province":"Li\u00e8ge",
    "wof:name":"Serge Dony",
    "wof:placetype":"venue"
},
  "geometry": {"coordinates":[5.3163838387,50.5476875305],"type":"Point"}
}