{
  "type": "Feature",
  "properties": {
    "iso:country":"BE",
    "sg:address":"Posterijlaan 24",
    "sg:city":"Pittem",
    "sg:orig_category":"Eleveurs and marchands de porcs",
    "sg:phone":"+32 51 46 61 82",
    "sg:postcode":"8740",
    "sg:province":"West-Vlaanderen",
    "wof:name":"Noel Schoonbaert",
    "wof:placetype":"venue"
},
  "geometry": {"coordinates":[3.2405350208,50.9888038635],"type":"Point"}
}