{
  "type": "Feature",
  "properties": {
    "addr:full":"6567 Merbes-le-ch\u00c2teau (groot) Hainaut 6567",
    "addr:housenumber":"6567",
    "addr:postcode":"6567",
    "addr:street":"Merbes-Le-Cha\u0302Teau Groot Hainaut",
    "iso:country":"BE",
    "sg:address":"6567",
    "sg:city":"Merbes-le-ch\u00c2teau (groot)",
    "sg:orig_category":"Pharmaciens",
    "sg:phone":"+32 900 10 500",
    "sg:postcode":"6567",
    "sg:province":"Hainaut",
    "wof:name":"Pharmacies De Garde",
    "wof:placetype":"venue"
},
  "geometry": {"coordinates":[4.16537714,50.3236999512],"type":"Point"}
}