{
  "type": "Feature",
  "properties": {
    "iso:country":"BE",
    "sg:address":"Rue De La Haute Folie 21",
    "sg:city":"Soignies (naast)",
    "sg:classifiers":[
        {
            "category":"Health Services",
            "subcategory":"Doctor",
            "type":"Services"
        }
    ],
    "sg:phone":"+32 67 33 59 71",
    "sg:postcode":"7062",
    "sg:province":"Hainaut",
    "sg:tags":[
        "medicinephysicians",
        "surgeon"
    ],
    "wof:name":"Brabant Annie",
    "wof:placetype":"venue"
},
  "geometry": {"coordinates":[4.097784996,50.5528373718],"type":"Point"}
}