{
  "type": "Feature",
  "properties": {
    "addr:full":"Vlijtstraat 14 Oudergem/auderghem Bruxelles-Capitale 1160",
    "addr:housenumber":"14",
    "addr:postcode":"1160",
    "addr:street":"Vlijtstraat;/",
    "iso:country":"BE",
    "sg:address":"Vlijtstraat 14",
    "sg:city":"Oudergem/auderghem",
    "sg:orig_category":"Persagentschappen",
    "sg:phone":"+32 2 673 20 68",
    "sg:postcode":"1160",
    "sg:province":"Bruxelles-Capitale",
    "wof:name":"Philippe Hereng",
    "wof:placetype":"venue"
},
  "geometry": {"coordinates":[4.4213600159,50.8169937134],"type":"Point"}
}