{
  "type": "Feature",
  "properties": {
    "addr:full":"Paleputstraat 24 Torhout West-Vlaanderen 8820",
    "addr:housenumber":"24",
    "addr:postcode":"8820",
    "addr:street":"Paleputstraat",
    "iso:country":"BE",
    "sg:address":"Paleputstraat 24",
    "sg:city":"Torhout",
    "sg:classifiers":[
        {
            "category":"Home & Garden",
            "subcategory":"Carpets & Floor Coverings",
            "type":"Retail Goods"
        }
    ],
    "sg:phone":"+32 51 72 35 06",
    "sg:postcode":"8820",
    "sg:province":"West-Vlaanderen",
    "sg:tags":[
        "layer",
        "mosaicists"
    ],
    "wof:name":"Aannemersbedrijf Willaert Peter",
    "wof:placetype":"venue"
},
  "geometry": {"coordinates":[3.0819098949,51.0277099609],"type":"Point"}
}