{
  "type": "Feature",
  "properties": {
    "addr:full":"Rue Gaston Bary 52 La Hulpe Brabant Wallon 1310",
    "addr:housenumber":"52",
    "addr:postcode":"1310",
    "addr:street":"Rue Gaston Bary",
    "iso:country":"BE",
    "sg:address":"Rue Gaston Bary 52",
    "sg:city":"La Hulpe",
    "sg:orig_category":"Enseignement maternel and primaire",
    "sg:phone":"+32 2 653 50 15",
    "sg:postcode":"1310",
    "sg:province":"Brabant Wallon",
    "wof:name":"E.m.c. Les Lupins",
    "wof:placetype":"venue"
},
  "geometry": {"coordinates":[4.4926447868,50.7406768799],"type":"Point"}
}