{
  "type": "Feature",
  "properties": {
    "addr:full":"Rue Du Nord 101 Courcelles Hainaut 6180",
    "addr:housenumber":"101",
    "addr:postcode":"6180",
    "addr:street":"Rue Du Nord",
    "iso:country":"BE",
    "sg:address":"Rue Du Nord 101",
    "sg:city":"Courcelles",
    "sg:orig_category":"Artsen and specialisten",
    "sg:phone":"+32 71 46 05 04",
    "sg:postcode":"6180",
    "sg:province":"Hainaut",
    "wof:name":"Genevi\u00c8ve Van Overbeke",
    "wof:placetype":"venue"
},
  "geometry": {"coordinates":[4.3597421646,50.4672393799],"type":"Point"}
}