{
  "type": "Feature",
  "properties": {
    "addr:full":"Ninoofsesteenweg 150 Halle Vlaams-Brabant 1500",
    "addr:housenumber":"150",
    "addr:postcode":"1500",
    "addr:street":"Ninoofsesteenweg",
    "iso:country":"BE",
    "sg:address":"Ninoofsesteenweg 150",
    "sg:city":"Halle",
    "sg:orig_category":"Waffle-Baking Machines, Waffle-Producing Plants",
    "sg:phone":"+32 2 356 67 82",
    "sg:postcode":"1500",
    "sg:province":"Vlaams-Brabant",
    "wof:name":"Acemal Nv",
    "wof:placetype":"venue"
},
  "geometry": {"coordinates":[4.2289562225,50.7396583557],"type":"Point"}
}