{
  "type": "Feature",
  "properties": {
    "iso:country":"BE",
    "sg:address":"Rue Du Val D\u00b4or 8",
    "sg:city":"Havelange",
    "sg:orig_category":"Maisons de repos and r\u00e9sidences",
    "sg:phone":"+32 86 32 24 03",
    "sg:postcode":"5374",
    "sg:province":"Namur",
    "wof:name":"Les Amandiers",
    "wof:placetype":"venue"
},
  "geometry": {"coordinates":[5.3126621246,50.3512229919],"type":"Point"}
}