{
  "type": "Feature",
  "properties": {
    "addr:full":"Gen.dos. De St.georgeslaan 11 Elsene/ixelles Bruxelles-Capitale 1050",
    "addr:housenumber":"11",
    "addr:postcode":"1050",
    "addr:street":"St.Georgeslaan",
    "iso:country":"BE",
    "sg:address":"Gen.dos. De St.georgeslaan 11",
    "sg:city":"Elsene/ixelles",
    "sg:orig_category":"Kapsalons Schoonheidssalons",
    "sg:phone":"+32 2 648 33 71",
    "sg:postcode":"1050",
    "sg:province":"Bruxelles-Capitale",
    "wof:name":"Coiffure C.m.",
    "wof:placetype":"venue"
},
  "geometry": {"coordinates":[4.369052887,50.818939209],"type":"Point"}
}