{
  "type": "Feature",
  "properties": {
    "addr:full":"Dorpsstraat 144b1 Damme West-Vlaanderen 8340",
    "addr:housenumber":"144b1",
    "addr:postcode":"8340",
    "addr:street":"Dorpsstraat",
    "iso:country":"BE",
    "sg:address":"Dorpsstraat 144b1",
    "sg:city":"Damme",
    "sg:orig_category":"Slagers",
    "sg:phone":"+32 50 35 31 28",
    "sg:postcode":"8340",
    "sg:province":"West-Vlaanderen",
    "wof:name":"Cyriel Kerkaert",
    "wof:placetype":"venue"
},
  "geometry": {"coordinates":[3.3204910755,51.2015533447],"type":"Point"}
}