{
  "type": "Feature",
  "properties": {
    "iso:country":"BE",
    "sg:address":"Heirweg 47",
    "sg:city":"Maldegem",
    "sg:classifiers":[
        {
            "category":"Parking",
            "subcategory":"Lot",
            "type":"Transportation"
        }
    ],
    "sg:phone":"+32 50 71 16 04",
    "sg:postcode":"9990",
    "sg:province":"Oost-Vlaanderen",
    "sg:tags":[
        "armoured",
        "door",
        "fireproof"
    ],
    "wof:name":"De Schepper R",
    "wof:placetype":"venue"
},
  "geometry": {"coordinates":[3.4036400318,51.212020874],"type":"Point"}
}