{
  "type": "Feature",
  "properties": {
    "addr:full":"Fabiolalaan 6 Ieper West-Vlaanderen 8900",
    "addr:housenumber":"6",
    "addr:postcode":"8900",
    "addr:street":"Fabiolalaan",
    "iso:country":"BE",
    "sg:address":"Fabiolalaan 6",
    "sg:city":"Ieper",
    "sg:classifiers":[
        {
            "category":"Wholesale",
            "subcategory":"Fruits & Vegetables",
            "type":"Manufacturing & Wholesale Goods"
        }
    ],
    "sg:phone":"+32 57 20 16 23",
    "sg:postcode":"8900",
    "sg:province":"West-Vlaanderen",
    "sg:tags":[
        "whol",
        "-"
    ],
    "wof:name":"Demuynck Nv",
    "wof:placetype":"venue"
},
  "geometry": {"coordinates":[2.863699913,50.8544998169],"type":"Point"}
}