{
  "type": "Feature",
  "properties": {
    "addr:full":"Rue Jules Besme 122 Bruxelles (koekelberg) Bruxelles-Capitale 1081",
    "addr:housenumber":"122",
    "addr:postcode":"1081",
    "addr:street":"Rue Jules Besme",
    "iso:country":"BE",
    "sg:address":"Rue Jules Besme 122",
    "sg:city":"Bruxelles (koekelberg)",
    "sg:classifiers":[
        {
            "category":"Personal",
            "subcategory":"Beauty Salon",
            "type":"Services"
        }
    ],
    "sg:phone":"+32 2 411 53 53",
    "sg:postcode":"1081",
    "sg:province":"Bruxelles-Capitale",
    "sg:tags":[
        "product",
        "-",
        "apparatus"
    ],
    "wof:name":"N.b.c. Nv",
    "wof:placetype":"venue"
},
  "geometry": {"coordinates":[4.3194627762,50.8624191284],"type":"Point"}
}