{
  "type": "Feature",
  "properties": {
    "iso:country":"BE",
    "sg:address":"Maalderijstraat 25",
    "sg:city":"Mortsel",
    "sg:classifiers":[
        {
            "category":"Personal",
            "subcategory":"Beauty Salon",
            "type":"Services"
        }
    ],
    "sg:phone":"+32 3 440 73 08",
    "sg:postcode":"2640",
    "sg:province":"Antwerpen",
    "sg:tags":[
        "de",
        "coiffure"
    ],
    "wof:name":"Coiffure Simonne",
    "wof:placetype":"venue"
},
  "geometry": {"coordinates":[4.4588208199,51.1640892029],"type":"Point"}
}