{
  "type": "Feature",
  "properties": {
    "iso:country":"BE",
    "sg:address":"Rue Du Pr\u00c9sident 9",
    "sg:city":"Namur",
    "sg:orig_category":"Verlichting and huishoudartikelen",
    "sg:phone":"+32 81 22 71 10",
    "sg:postcode":"5000",
    "sg:province":"Namur",
    "wof:name":"Le Voleur D\u00b4ombres",
    "wof:placetype":"venue"
},
  "geometry": {"coordinates":[4.8640179634,50.4634399414],"type":"Point"}
}