{
  "type": "Feature",
  "properties": {
    "addr:full":"Burrelstraat 4 Sint-niklaas Oost-Vlaanderen 9100",
    "addr:housenumber":"4",
    "addr:postcode":"9100",
    "addr:street":"Burrelstraat",
    "iso:country":"BE",
    "sg:address":"Burrelstraat 4",
    "sg:city":"Sint-niklaas",
    "sg:classifiers":[
        {
            "category":"Parking",
            "subcategory":"Garage",
            "type":"Transportation"
        }
    ],
    "sg:phone":"+32 3 777 84 95",
    "sg:postcode":"9100",
    "sg:province":"Oost-Vlaanderen",
    "sg:tags":[
        "truck",
        "-",
        "dump",
        "transport"
    ],
    "wof:name":"Tmt",
    "wof:placetype":"venue"
},
  "geometry": {"coordinates":[4.1414990425,51.1445426941],"type":"Point"}
}