{
  "type": "Feature",
  "properties": {
    "iso:country":"BE",
    "sg:address":"Vieux Chemin Du Poete 23",
    "sg:city":"Wavre",
    "sg:orig_category":"Produits chimiques Gr",
    "sg:phone":"+32 10 41 35 56",
    "sg:postcode":"1301",
    "sg:province":"Brabant Wallon",
    "wof:name":"Melibio",
    "wof:placetype":"venue"
},
  "geometry": {"coordinates":[4.5869660378,50.7059936523],"type":"Point"}
}