{
  "type": "Feature",
  "properties": {
    "addr:full":"Kruisstraat 41 Tremelo Vlaams-Brabant 3120",
    "addr:housenumber":"41",
    "addr:postcode":"3120",
    "addr:street":"Kruisstraat",
    "iso:country":"BE",
    "sg:address":"Kruisstraat 41",
    "sg:city":"Tremelo",
    "sg:orig_category":"Installation de piscines. Plomberie, chauffage and installations sanitaires",
    "sg:phone":"+32 16 53 03 05",
    "sg:postcode":"3120",
    "sg:province":"Vlaams-Brabant",
    "wof:name":"Avipool Zwembadenbouw",
    "wof:placetype":"venue"
},
  "geometry": {"coordinates":[4.7016820908,50.9934692383],"type":"Point"}
}