{
  "type": "Feature",
  "properties": {
    "iso:country":"BE",
    "sg:address":"Katelijnestr 65a",
    "sg:city":"Brugge",
    "sg:classifiers":[
        {
            "category":"Travel",
            "subcategory":"Hotels & Motels",
            "type":"Entertainment"
        }
    ],
    "sg:phone":"+32 50 33 75 75",
    "sg:postcode":"8000",
    "sg:province":"West-Vlaanderen",
    "sg:tags":[
        "hotels",
        "business",
        "restaurant"
    ],
    "wof:name":"Hotel Ibis",
    "wof:placetype":"venue"
},
  "geometry": {"coordinates":[3.2266418934,51.2023048401],"type":"Point"}
}