{
  "type": "Feature",
  "properties": {
    "addr:full":"Rue De L'hospice 1 Pepinster Li\u00e8ge 4860",
    "addr:housenumber":"1",
    "addr:postcode":"4860",
    "addr:street":"Rue De L'Hospice",
    "iso:country":"BE",
    "sg:address":"Rue De L'hospice 1",
    "sg:city":"Pepinster",
    "sg:orig_category":"Rusthuizen and serviceflats",
    "sg:phone":"+32 87 46 04 16",
    "sg:postcode":"4860",
    "sg:province":"Li\u00e8ge",
    "wof:name":"Maison De Retraite",
    "wof:placetype":"venue"
},
  "geometry": {"coordinates":[5.8096618652,50.5675697327],"type":"Point"}
}