{
  "type": "Feature",
  "properties": {
    "iso:country":"BE",
    "sg:address":"Champs De Foyr 77",
    "sg:city":"Jalhay",
    "sg:orig_category":"Jardinage",
    "sg:phone":"+32 87 64 73 77",
    "sg:postcode":"4845",
    "sg:province":"Li\u00e8ge",
    "wof:name":"Defraiture",
    "wof:placetype":"venue"
},
  "geometry": {"coordinates":[5.9364957809,50.5687675476],"type":"Point"}
}