{
  "type": "Feature",
  "properties": {
    "iso:country":"BE",
    "sg:address":"Gemeenteplaats 1",
    "sg:city":"Hemiksem",
    "sg:classifiers":[
        {
            "category":"Social Services",
            "type":"Services"
        }
    ],
    "sg:phone":"+32 3 877 70 18",
    "sg:postcode":"2620",
    "sg:province":"Antwerpen",
    "wof:name":"Akoshem Vzw",
    "wof:placetype":"venue"
},
  "geometry": {"coordinates":[4.3457779884,51.1442527771],"type":"Point"}
}