{
  "type": "Feature",
  "properties": {
    "iso:country":"BE",
    "sg:address":"Bergstraat 16",
    "sg:city":"Machelen",
    "sg:orig_category":"Immobili\u00ebnkantoren Landmeters",
    "sg:phone":"+32 2 253 33 90",
    "sg:postcode":"1830",
    "sg:province":"Vlaams-Brabant",
    "wof:name":"Bruno Vanbinst",
    "wof:placetype":"venue"
},
  "geometry": {"coordinates":[4.4293541908,50.9025688171],"type":"Point"}
}