{
  "type": "Feature",
  "properties": {
    "iso:country":"BE",
    "sg:address":"Rue De L'ancienne Grange 1",
    "sg:city":"Malmedy",
    "sg:classifiers":[
        {
            "category":"Professional",
            "subcategory":"Accounting & Tax Preparation",
            "type":"Services"
        }
    ],
    "sg:phone":"+32 80 79 99 61",
    "sg:postcode":"4960",
    "sg:province":"Li\u00e8ge",
    "sg:tags":[
        "accountant"
    ],
    "wof:name":"Braibant B",
    "wof:placetype":"venue"
},
  "geometry": {"coordinates":[6.0252990723,50.4229011536],"type":"Point"}
}