{
  "type": "Feature",
  "properties": {
    "iso:country":"BE",
    "sg:address":"Meulebeeksesteenweg 61",
    "sg:city":"Tielt",
    "sg:orig_category":"Herstellingen and onderhoud aan huis voor voertuigen Herstellingen and onderhoud van auto's",
    "sg:phone":"+32 51 40 31 77",
    "sg:postcode":"8700",
    "sg:province":"West-Vlaanderen",
    "wof:name":"Buyck Carrosserie & Depannage",
    "wof:placetype":"venue"
},
  "geometry": {"coordinates":[3.3116569519,50.9786071777],"type":"Point"}
}