{
  "type": "Feature",
  "properties": {
    "iso:country":"BE",
    "sg:address":"Fonteinstraat 14",
    "sg:city":"Haaltert",
    "sg:classifiers":[
        {
            "category":"Taxi",
            "type":"Transportation"
        }
    ],
    "sg:phone":"+32 53 83 31 13",
    "sg:postcode":"9450",
    "sg:province":"Oost-Vlaanderen",
    "sg:tags":[
        "sp\u00e9ciaux",
        "taxis"
    ],
    "wof:name":"Taxi Marc",
    "wof:placetype":"venue"
},
  "geometry": {"coordinates":[4.0100870132,50.8964042664],"type":"Point"}
}