{
  "type": "Feature",
  "properties": {
    "iso:country":"BE",
    "sg:address":"Gevaertlaan 49",
    "sg:city":"Westerlo",
    "sg:orig_category":"Informaticaconsulenten",
    "sg:phone":"+32 14 54 61 58",
    "sg:postcode":"2260",
    "sg:province":"Antwerpen",
    "wof:name":"Gvm I.t. Consultancy",
    "wof:placetype":"venue"
},
  "geometry": {"coordinates":[4.8619451523,51.0881729126],"type":"Point"}
}