{
  "type": "Feature",
  "properties": {
    "iso:country":"BE",
    "sg:address":"Slakweidestraat 42",
    "sg:city":"Maasmechelen",
    "sg:classifiers":[
        {
            "category":"Banks & Credit Unions",
            "subcategory":"Investment Brokerage",
            "type":"Services"
        }
    ],
    "sg:phone":"+32 89 77 55 00",
    "sg:postcode":"3630",
    "sg:province":"Limburg",
    "sg:tags":[
        "slat",
        "bed"
    ],
    "wof:name":"Elsach Nv",
    "wof:placetype":"venue"
},
  "geometry": {"coordinates":[5.7029619217,50.950428009],"type":"Point"}
}