{
  "type": "Feature",
  "properties": {
    "addr:full":"Rue Du Ri Des Corbeaux 2 Nivelles (monstreux) Brabant Wallon 1400",
    "addr:housenumber":"2",
    "addr:postcode":"1400",
    "addr:street":"Rue Du Ri Des Corbeaux;Wallon",
    "iso:country":"BE",
    "sg:address":"Rue Du Ri Des Corbeaux 2",
    "sg:city":"Nivelles (monstreux)",
    "sg:classifiers":[
        {
            "category":"Health Services",
            "subcategory":"Doctor",
            "type":"Services"
        }
    ],
    "sg:phone":"+32 67 84 12 16",
    "sg:postcode":"1400",
    "sg:province":"Brabant Wallon",
    "sg:tags":[
        "medicinephysicians",
        "surgeon"
    ],
    "wof:name":"Declaye X",
    "wof:placetype":"venue"
},
  "geometry": {"coordinates":[4.2889690399,50.5982437134],"type":"Point"}
}