{
  "type": "Feature",
  "properties": {
    "iso:country":"BE",
    "sg:address":"Rue Du Pont 11",
    "sg:city":"Seraing (jemeppe-sur-meuse)",
    "sg:classifiers":[
        {
            "category":"Retail",
            "subcategory":"Animal Services",
            "type":"Services"
        }
    ],
    "sg:phone":"+32 4 233 29 84",
    "sg:postcode":"4101",
    "sg:province":"Li\u00e8ge",
    "sg:tags":[
        "grooming",
        "-",
        "dog"
    ],
    "wof:name":"Ouaf-ouaf (beauty)",
    "wof:placetype":"venue"
},
  "geometry": {"coordinates":[5.5082211494,50.6176338196],"type":"Point"}
}