{
  "type": "Feature",
  "properties": {
    "addr:full":"Rue Des Combattants 125 Oreye Li\u00e8ge 4360",
    "addr:housenumber":"125",
    "addr:postcode":"4360",
    "addr:street":"Rue Des Combattants",
    "iso:country":"BE",
    "sg:address":"Rue Des Combattants 125",
    "sg:city":"Oreye",
    "sg:orig_category":"Kapsalons",
    "sg:phone":"+32 19 67 70 23",
    "sg:postcode":"4360",
    "sg:province":"Li\u00e8ge",
    "wof:name":"Marthe Warnier",
    "wof:placetype":"venue"
},
  "geometry": {"coordinates":[5.3742280006,50.7336006165],"type":"Point"}
}