{
  "type": "Feature",
  "properties": {
    "addr:full":"Schaveystraat 27 Huldenberg (neerijse) Vlaams-Brabant 3040",
    "addr:housenumber":"27",
    "addr:postcode":"3040",
    "addr:street":"Schaveystraat",
    "iso:country":"BE",
    "sg:address":"Schaveystraat 27",
    "sg:city":"Huldenberg (neerijse)",
    "sg:classifiers":[
        {
            "category":"Travel",
            "subcategory":"Travel Agent",
            "type":"Entertainment"
        }
    ],
    "sg:phone":"+32 16 47 25 63",
    "sg:postcode":"3040",
    "sg:province":"Vlaams-Brabant",
    "sg:tags":[
        "agency"
    ],
    "wof:name":"A.d.r. Services",
    "wof:placetype":"venue"
},
  "geometry": {"coordinates":[4.6211481094,50.8154907227],"type":"Point"}
}