{
  "type": "Feature",
  "properties": {
    "addr:full":"Kerkstraat 36 Tielt-winge Vlaams-Brabant 3391",
    "addr:housenumber":"36",
    "addr:postcode":"3391",
    "addr:street":"Kerkstraat",
    "iso:country":"BE",
    "sg:address":"Kerkstraat 36",
    "sg:city":"Tielt-winge",
    "sg:classifiers":[
        {
            "category":"Organizations",
            "subcategory":"Community Association",
            "type":"Services"
        }
    ],
    "sg:phone":"+32 16 63 35 22",
    "sg:postcode":"3391",
    "sg:province":"Vlaams-Brabant",
    "sg:tags":[
        "organisation"
    ],
    "wof:name":"Klj-kiezegem",
    "wof:placetype":"venue"
},
  "geometry": {"coordinates":[4.9045090675,50.8907203674],"type":"Point"}
}