{
  "type": "Feature",
  "properties": {
    "iso:country":"BE",
    "sg:address":"Sint-eloois Winkelstraat 95",
    "sg:city":"Ledegem",
    "sg:orig_category":"Non-Classified Establishments",
    "sg:phone":"+32 56 50 91 28",
    "sg:postcode":"8880",
    "sg:province":"West-Vlaanderen",
    "wof:name":"Vandenbulcke R",
    "wof:placetype":"venue"
},
  "geometry": {"coordinates":[3.1328530312,50.8576431274],"type":"Point"}
}