{
  "type": "Feature",
  "properties": {
    "addr:full":"Weyerstraat 5b Hoeselt Limburg 3730",
    "addr:housenumber":"5b",
    "addr:postcode":"3730",
    "addr:street":"Weyerstraat",
    "iso:country":"BE",
    "sg:address":"Weyerstraat 5b",
    "sg:city":"Hoeselt",
    "sg:classifiers":[
        {
            "category":"Health Services",
            "subcategory":"Doctor",
            "type":"Services"
        }
    ],
    "sg:phone":"+32 89 41 80 00",
    "sg:postcode":"3730",
    "sg:province":"Limburg",
    "sg:tags":[
        "medicinephysicians",
        "surgeon"
    ],
    "wof:name":"Maene Yasmine",
    "wof:placetype":"venue"
},
  "geometry": {"coordinates":[5.4939842224,50.8519706726],"type":"Point"}
}