{
  "type": "Feature",
  "properties": {
    "addr:full":"Kortekeer 1 Vleteren West-Vlaanderen 8640",
    "addr:housenumber":"1",
    "addr:postcode":"8640",
    "addr:street":"Kortekeer",
    "iso:country":"BE",
    "sg:address":"Kortekeer 1",
    "sg:city":"Vleteren",
    "sg:classifiers":[
        {
            "category":"Cafe",
            "type":"Food & Drink"
        }
    ],
    "sg:phone":"+32 57 40 12 28",
    "sg:postcode":"8640",
    "sg:province":"West-Vlaanderen",
    "sg:tags":[
        "caf\u00e9s"
    ],
    "wof:name":"Veronique Vandevoorde",
    "wof:placetype":"venue"
},
  "geometry": {"coordinates":[2.7371990681,50.9313316345],"type":"Point"}
}