{
  "type": "Feature",
  "properties": {
    "iso:country":"BE",
    "sg:address":"Tieltsesteenweg 21",
    "sg:city":"Deinze",
    "sg:orig_category":"Groententeelt",
    "sg:phone":"+32 51 63 57 77",
    "sg:postcode":"9800",
    "sg:province":"Oost-Vlaanderen",
    "wof:name":"Herve Van Vynckt",
    "wof:placetype":"venue"
},
  "geometry": {"coordinates":[3.4534220695,50.9893074036],"type":"Point"}
}