{
  "type": "Feature",
  "properties": {
    "iso:country":"BE",
    "sg:address":"Gijmelsesteenweg 264",
    "sg:city":"Aarschot",
    "sg:orig_category":"Souvenirs and objets artisanaux. Fournitures de bureau. Librairies. Journaux. Imprimeries and copysh",
    "sg:phone":"+32 16 56 75 99",
    "sg:postcode":"3201",
    "sg:province":"Vlaams-Brabant",
    "wof:name":"Krantenwinkel Myriam",
    "wof:placetype":"venue"
},
  "geometry": {"coordinates":[4.8598861694,51.0088768005],"type":"Point"}
}