{
  "type": "Feature",
  "properties": {
    "addr:full":"Prinsenweg 11 Tongeren Limburg 3700",
    "addr:housenumber":"11",
    "addr:postcode":"3700",
    "addr:street":"Prinsenweg",
    "iso:country":"BE",
    "sg:address":"Prinsenweg 11",
    "sg:city":"Tongeren",
    "sg:orig_category":"Verhuisdiensten",
    "sg:phone":"+32 12 23 14 58",
    "sg:postcode":"3700",
    "sg:province":"Limburg",
    "wof:name":"Vandenreydt",
    "wof:placetype":"venue"
},
  "geometry": {"coordinates":[5.4827260971,50.7683258057],"type":"Point"}
}