{
  "type": "Feature",
  "properties": {
    "addr:full":"Boulevard Edmond Machtens 61 Box 13 Bruxelles (molenbeek-saint-jean) Bruxelles-Capitale 1080",
    "addr:housenumber":"61 box 13",
    "addr:postcode":"1080",
    "addr:street":"Boulevard Edmond Machtens",
    "iso:country":"BE",
    "sg:address":"Boulevard Edmond Machtens 61 Box 13",
    "sg:city":"Bruxelles (molenbeek-saint-jean)",
    "sg:classifiers":[
        {
            "category":"Health Services",
            "subcategory":"Doctor",
            "type":"Services"
        }
    ],
    "sg:phone":"+32 2 410 72 60",
    "sg:postcode":"1080",
    "sg:province":"Bruxelles-Capitale",
    "sg:tags":[
        "medicinephysicians",
        "surgeon"
    ],
    "wof:name":"Lenaers Mich\u00e8le",
    "wof:placetype":"venue"
},
  "geometry": {"coordinates":[4.3152871132,50.8520812988],"type":"Point"}
}