{
  "type": "Feature",
  "properties": {
    "addr:full":"Brugsestraat 159 Oostkamp West-Vlaanderen 8020",
    "addr:housenumber":"159",
    "addr:postcode":"8020",
    "addr:street":"Brugsestraat",
    "iso:country":"BE",
    "sg:address":"Brugsestraat 159",
    "sg:city":"Oostkamp",
    "sg:classifiers":[
        {
            "category":"Food & Beverages",
            "subcategory":"Fruits & Vegetables",
            "type":"Retail Goods"
        }
    ],
    "sg:phone":"+32 50 82 55 26",
    "sg:postcode":"8020",
    "sg:province":"West-Vlaanderen",
    "sg:tags":[
        "groenten"
    ],
    "wof:name":"Fruitmarktje",
    "wof:placetype":"venue"
},
  "geometry": {"coordinates":[3.2343039513,51.1635627747],"type":"Point"}
}