{
  "type": "Feature",
  "properties": {
    "addr:full":"Korte Ridderstraat 15 Merchtem Vlaams-Brabant 1785",
    "addr:housenumber":"15",
    "addr:postcode":"1785",
    "addr:street":"Korte Ridderstraat",
    "iso:country":"BE",
    "sg:address":"Korte Ridderstraat 15",
    "sg:city":"Merchtem",
    "sg:classifiers":[
        {
            "category":"Arena",
            "subcategory":"Sports Club",
            "type":"Entertainment"
        }
    ],
    "sg:phone":"+32 52 37 11 62",
    "sg:postcode":"1785",
    "sg:province":"Vlaams-Brabant",
    "sg:tags":[
        "martial art",
        "accessory"
    ],
    "wof:name":"V P S International Nv",
    "wof:placetype":"venue"
},
  "geometry": {"coordinates":[4.2323470116,50.9595069885],"type":"Point"}
}