{
  "type": "Feature",
  "properties": {
    "addr:full":"Avenue Brugmann 43 Sint-gillis/saint-gilles Bruxelles-Capitale 1060",
    "addr:housenumber":"43",
    "addr:postcode":"1060",
    "addr:street":"Avenue Brugmann",
    "iso:country":"BE",
    "sg:address":"Avenue Brugmann 43",
    "sg:city":"Sint-gillis/saint-gilles",
    "sg:orig_category":"M\u00e9decins and sp\u00e9cialistes",
    "sg:phone":"+32 2 534 53 30",
    "sg:postcode":"1060",
    "sg:province":"Bruxelles-Capitale",
    "wof:name":"Claire Vuylsteke",
    "wof:placetype":"venue"
},
  "geometry": {"coordinates":[4.3526768684,50.8215255737],"type":"Point"}
}