{
  "type": "Feature",
  "properties": {
    "addr:full":"Aarschotsesteenweg 114 Leuven (wilsele) Vlaams-Brabant 3012",
    "addr:housenumber":"114",
    "addr:postcode":"3012",
    "addr:street":"Aarschotsesteenweg",
    "iso:country":"BE",
    "sg:address":"Aarschotsesteenweg 114",
    "sg:city":"Leuven (wilsele)",
    "sg:classifiers":[
        {
            "category":"Professional",
            "type":"Services"
        }
    ],
    "sg:phone":"+32 16 30 13 01",
    "sg:postcode":"3012",
    "sg:province":"Vlaams-Brabant",
    "sg:tags":[
        "packing",
        "-"
    ],
    "wof:name":"Varia-pack Nv",
    "wof:placetype":"venue"
},
  "geometry": {"coordinates":[4.7072558403,50.8978614807],"type":"Point"}
}