{
  "type": "Feature",
  "properties": {
    "iso:country":"BE",
    "sg:address":"Grotstraat 100",
    "sg:city":"Aarschot",
    "sg:orig_category":"Artsen and specialisten",
    "sg:phone":"+32 16 56 53 35",
    "sg:postcode":"3200",
    "sg:province":"Vlaams-Brabant",
    "wof:name":"Frans Depestele",
    "wof:placetype":"venue"
},
  "geometry": {"coordinates":[4.8117637634,51.0001602173],"type":"Point"}
}