{
  "type": "Feature",
  "properties": {
    "addr:full":"Dutselstraat 40 Holsbeek Vlaams-Brabant 3220",
    "addr:housenumber":"40",
    "addr:postcode":"3220",
    "addr:street":"Dutselstraat",
    "iso:country":"BE",
    "sg:address":"Dutselstraat 40",
    "sg:city":"Holsbeek",
    "sg:orig_category":"Fruitteelt",
    "sg:phone":"+32 16 62 22 21",
    "sg:postcode":"3220",
    "sg:province":"Vlaams-Brabant",
    "wof:name":"Marcel Elsen",
    "wof:placetype":"venue"
},
  "geometry": {"coordinates":[4.7841567993,50.9167823792],"type":"Point"}
}