{
  "type": "Feature",
  "properties": {
    "addr:full":"Chauss\u00e9e De Charleroi 167 Bruxelles (saint-gilles) Bruxelles-Capitale 1060",
    "addr:housenumber":"167",
    "addr:postcode":"1060",
    "addr:street":"Chausse\u0301E De Charleroi",
    "iso:country":"BE",
    "sg:address":"Chauss\u00e9e De Charleroi 167",
    "sg:city":"Bruxelles (saint-gilles)",
    "sg:classifiers":[
        {
            "category":"Shopping",
            "subcategory":"Antiques",
            "type":"Retail Goods"
        }
    ],
    "sg:phone":"+32 2 537 58 62",
    "sg:postcode":"1060",
    "sg:province":"Bruxelles-Capitale",
    "wof:name":"Galeries Roosens Scrl",
    "wof:placetype":"venue"
},
  "geometry": {"coordinates":[4.3548769951,50.827167511],"type":"Point"}
}