{
  "type": "Feature",
  "properties": {
    "addr:full":"Pre Wigi Herstal Li\u00e8ge 4040",
    "addr:postcode":"4040",
    "iso:country":"BE",
    "sg:address":"Pre Wigi",
    "sg:city":"Herstal",
    "sg:classifiers":[
        {
            "category":"Government",
            "subcategory":"Post Office",
            "type":"Public Place"
        }
    ],
    "sg:phone":"+32 4 240 74 74",
    "sg:postcode":"4040",
    "sg:province":"Li\u00e8ge",
    "sg:tags":[
        "disposal",
        "recycling",
        "treatment",
        "analysis",
        "waste"
    ],
    "wof:name":"Intradel S.c.r.l.",
    "wof:placetype":"venue"
},
  "geometry": {"coordinates":[5.6418199539,50.68019104],"type":"Point"}
}