{
  "type": "Feature",
  "properties": {
    "iso:country":"BE",
    "sg:address":"Lange Lozanastraat 101",
    "sg:city":"Antwerpen",
    "sg:orig_category":"R\u00e9parations d'appareils \u00e9lectrom\u00e9nagers. Electrom\u00e9nager, t\u00e9l\u00e9visions and radios",
    "sg:phone":"+32 3 237 85 02",
    "sg:postcode":"2018",
    "sg:province":"Antwerpen",
    "wof:name":"Studio 4",
    "wof:placetype":"venue"
},
  "geometry": {"coordinates":[4.4050908089,51.2036819458],"type":"Point"}
}