{
  "type": "Feature",
  "properties": {
    "iso:country":"BE",
    "sg:address":"Waaibergstraat 121",
    "sg:city":"Tienen",
    "sg:orig_category":"Artsen and specialisten",
    "sg:phone":"+32 16 81 18 60",
    "sg:postcode":"3300",
    "sg:province":"Vlaams-Brabant",
    "wof:name":"J. Jansen",
    "wof:placetype":"venue"
},
  "geometry": {"coordinates":[4.9420747757,50.8115692139],"type":"Point"}
}