{
  "type": "Feature",
  "properties": {
    "iso:country":"BE",
    "sg:address":"Avenue Du G\u00c9n\u00c9ral-patton 52",
    "sg:city":"Arlon",
    "sg:orig_category":"Belastingconsulenten Diverse bedrijfsbeheeradviesbureaus Diverse juridische dienstverlening",
    "sg:phone":"+32 63 24 21 00",
    "sg:postcode":"6700",
    "sg:province":"Luxembourg",
    "wof:name":"Sud Fiduciaire",
    "wof:placetype":"venue"
},
  "geometry": {"coordinates":[5.812666893,49.6763648987],"type":"Point"}
}