{
  "type": "Feature",
  "properties": {
    "iso:country":"BE",
    "sg:address":"Br\u00fcckberg 40",
    "sg:city":"B\u00fcllingen",
    "sg:orig_category":"Non-Classified Establishments",
    "sg:phone":"+32 80 64 70 49",
    "sg:postcode":"4760",
    "sg:province":"Li\u00e8ge",
    "wof:name":"Mertens H Sa",
    "wof:placetype":"venue"
},
  "geometry": {"coordinates":[6.2601599693,50.4087982178],"type":"Point"}
}