{
  "type": "Feature",
  "properties": {
    "iso:country":"BE",
    "sg:address":"Rue Du Bosquet 10",
    "sg:city":"Ottignies-louvain-la-neuve",
    "sg:orig_category":"Plomberie, chauffage and installations sanitaires. Location de mat\u00e9riel pour banquets and \u00e9v\u00e9nements",
    "sg:phone":"+32 10 45 11 96",
    "sg:postcode":"1348",
    "sg:province":"Brabant Wallon",
    "wof:name":"Satellite Industries Europe",
    "wof:placetype":"venue"
},
  "geometry": {"coordinates":[4.6321730614,50.6606636047],"type":"Point"}
}