{
  "type": "Feature",
  "properties": {
    "iso:country":"BE",
    "sg:address":"Broelkaai 1f",
    "sg:city":"Kortrijk",
    "sg:orig_category":"Herstellingen and onderhoud van auto's Onderdelen and accessoires voor auto's",
    "sg:phone":"+32 56 20 52 85",
    "sg:postcode":"8500",
    "sg:province":"West-Vlaanderen",
    "wof:name":"Ludwig Dupon",
    "wof:placetype":"venue"
},
  "geometry": {"coordinates":[3.2648129463,50.8300895691],"type":"Point"}
}