{
  "type": "Feature",
  "properties": {
    "addr:full":"Avenue Newton 4 Wavre Brabant Wallon 1300",
    "addr:housenumber":"4;1300",
    "addr:street":"Avenue Newton",
    "iso:country":"BE",
    "sg:address":"Avenue Newton 4",
    "sg:city":"Wavre",
    "sg:orig_category":"Non-Classified Establishments",
    "sg:phone":"+32 10 24 26 08",
    "sg:postcode":"1300",
    "sg:province":"Brabant Wallon",
    "wof:name":"Anita",
    "wof:placetype":"venue"
},
  "geometry": {"coordinates":[4.5877318382,50.7369232178],"type":"Point"}
}