{
  "type": "Feature",
  "properties": {
    "iso:country":"BE",
    "sg:address":"Avenue Des Sept-bonniers 144b2",
    "sg:city":"Vorst/forest",
    "sg:orig_category":"R\u00e9cup\u00e9ration de mati\u00e8res m\u00e9talliques recyclables and d\u00e9molisseurs de voitures",
    "sg:phone":"+32 2 345 64 35",
    "sg:postcode":"1190",
    "sg:province":"Bruxelles-Capitale",
    "wof:name":"Nicolas Samartzis",
    "wof:placetype":"venue"
},
  "geometry": {"coordinates":[4.3339858055,50.8118438721],"type":"Point"}
}