{
  "type": "Feature",
  "properties": {
    "addr:full":"Avenue Des D\u00c9port\u00c9s 10 Fosses-la-ville Namur 5070",
    "addr:housenumber":"10",
    "addr:postcode":"5070",
    "addr:street":"Avenue Des De\u0301Porte\u0301S",
    "iso:country":"BE",
    "sg:address":"Avenue Des D\u00c9port\u00c9s 10",
    "sg:city":"Fosses-la-ville",
    "sg:orig_category":"Elektrische installaties voor woningen Loodgieterij, verwarming and sanitaire installaties",
    "sg:phone":"+32 71 71 25 75",
    "sg:postcode":"5070",
    "sg:province":"Namur",
    "wof:name":"Biot",
    "wof:placetype":"venue"
},
  "geometry": {"coordinates":[4.6852588654,50.394077301],"type":"Point"}
}