{
  "type": "Feature",
  "properties": {
    "iso:country":"BE",
    "sg:address":"Biezenstraat 2",
    "sg:city":"Roeselare",
    "sg:classifiers":[
        {
            "category":"Health Services",
            "subcategory":"Health Practitioner",
            "type":"Services"
        }
    ],
    "sg:phone":"+32 51 24 17 01",
    "sg:postcode":"8800",
    "sg:province":"West-Vlaanderen",
    "sg:tags":[
        "physiotherapist"
    ],
    "wof:name":"Vanden Eynde K",
    "wof:placetype":"venue"
},
  "geometry": {"coordinates":[3.1052029133,50.9589805603],"type":"Point"}
}