{
  "type": "Feature",
  "properties": {
    "addr:full":"Steenweg 239b10 Lanaken Limburg 3621",
    "addr:housenumber":"239b10",
    "addr:postcode":"3621",
    "addr:street":"Steenweg",
    "iso:country":"BE",
    "sg:address":"Steenweg 239b10",
    "sg:city":"Lanaken",
    "sg:classifiers":[
        {
            "category":"Personal",
            "subcategory":"Beauty Salon",
            "type":"Services"
        }
    ],
    "sg:phone":"+32 89 71 56 39",
    "sg:postcode":"3621",
    "sg:province":"Limburg",
    "sg:tags":[
        "de",
        "coiffure"
    ],
    "wof:name":"Coiffure Jacky",
    "wof:placetype":"venue"
},
  "geometry": {"coordinates":[5.6871671677,50.9268188477],"type":"Point"}
}