{
  "type": "Feature",
  "properties": {
    "addr:full":"Kouterbaan 57 Ninove Oost-Vlaanderen 9400",
    "addr:housenumber":"57",
    "addr:postcode":"9400",
    "addr:street":"Kouterbaan",
    "iso:country":"BE",
    "sg:address":"Kouterbaan 57",
    "sg:city":"Ninove",
    "sg:orig_category":"M\u00e9decins and sp\u00e9cialistes",
    "sg:phone":"+32 54 33 94 48",
    "sg:postcode":"9400",
    "sg:province":"Oost-Vlaanderen",
    "wof:name":"F. Meert",
    "wof:placetype":"venue"
},
  "geometry": {"coordinates":[4.0565462112,50.8571205139],"type":"Point"}
}