{
  "type": "Feature",
  "properties": {
    "iso:country":"BE",
    "sg:address":"Nijverheidsstraat 113",
    "sg:city":"Erpe-mere",
    "sg:orig_category":"Avocats and conseillers juridiques",
    "sg:phone":"+32 53 83 28 36",
    "sg:postcode":"9420",
    "sg:province":"Oost-Vlaanderen",
    "wof:name":"P. Raes",
    "wof:placetype":"venue"
},
  "geometry": {"coordinates":[3.964979887,50.9195899963],"type":"Point"}
}