{
  "type": "Feature",
  "properties": {
    "addr:full":"Sint-katriensteenweg 33 Kuurne West-Vlaanderen 8520",
    "addr:housenumber":"33",
    "addr:postcode":"8520",
    "addr:street":"Sint-Katriensteenweg",
    "iso:country":"BE",
    "sg:address":"Sint-katriensteenweg 33",
    "sg:city":"Kuurne",
    "sg:orig_category":"Brood, gebak and snoepgoed",
    "sg:phone":"+32 56 37 00 04",
    "sg:postcode":"8520",
    "sg:province":"West-Vlaanderen",
    "wof:name":"Chantal Moerman",
    "wof:placetype":"venue"
},
  "geometry": {"coordinates":[3.2537119389,50.8671417236],"type":"Point"}
}