{
  "type": "Feature",
  "properties": {
    "addr:full":"Biekenshei 11a Schilde ('s Gravenwezel) Antwerpen 2970",
    "addr:housenumber":"11a",
    "addr:postcode":"2970",
    "addr:street":"Biekenshei;S",
    "iso:country":"BE",
    "sg:address":"Biekenshei 11a",
    "sg:city":"Schilde ('s Gravenwezel)",
    "sg:classifiers":[
        {
            "category":"Building & Trades",
            "subcategory":"Landscaping Services",
            "type":"Services"
        }
    ],
    "sg:phone":"+32 3 685 42 76",
    "sg:postcode":"2970",
    "sg:province":"Antwerpen",
    "sg:tags":[
        "gardening",
        "garden",
        "maintenance"
    ],
    "wof:name":"Marien M",
    "wof:placetype":"venue"
},
  "geometry": {"coordinates":[4.5779418945,51.2636451721],"type":"Point"}
}