{
  "type": "Feature",
  "properties": {
    "addr:full":"Sint-hubrechtsstraat 41 Roeselare West-Vlaanderen 8800",
    "addr:housenumber":"41",
    "addr:postcode":"8800",
    "addr:street":"Sint-Hubrechtsstraat",
    "iso:country":"BE",
    "sg:address":"Sint-hubrechtsstraat 41",
    "sg:city":"Roeselare",
    "sg:classifiers":[
        {
            "category":"Bars & Pubs",
            "type":"Food & Drink"
        }
    ],
    "sg:phone":"+32 51 20 26 45",
    "sg:postcode":"8800",
    "sg:province":"West-Vlaanderen",
    "wof:name":"Salonske",
    "wof:placetype":"venue"
},
  "geometry": {"coordinates":[3.1331989765,50.9475326538],"type":"Point"}
}