{
  "type": "Feature",
  "properties": {
    "addr:full":"Torsinplein 28 Tienen Vlaams-Brabant 3300",
    "addr:housenumber":"28",
    "addr:postcode":"3300",
    "addr:street":"Torsinplein",
    "iso:country":"BE",
    "sg:address":"Torsinplein 28",
    "sg:city":"Tienen",
    "sg:orig_category":"Pain, p\u00e2tisseries and confiseries",
    "sg:phone":"+32 16 82 44 24",
    "sg:postcode":"3300",
    "sg:province":"Vlaams-Brabant",
    "wof:name":"Bakkerij Poncelet-bosmans",
    "wof:placetype":"venue"
},
  "geometry": {"coordinates":[4.9399900436,50.8038787842],"type":"Point"}
}