{
  "type": "Feature",
  "properties": {
    "iso:country":"BE",
    "sg:address":"Klossestraat 4",
    "sg:city":"Zwijnaarde",
    "sg:classifiers":[
        {
            "category":"Building & Trades",
            "subcategory":"Construction",
            "type":"Services"
        }
    ],
    "sg:phone":"+32 9 221 32 13",
    "sg:postcode":"9052",
    "sg:province":"Oost-Vlaanderen",
    "sg:tags":[
        "installation",
        "air-conditioning",
        "system"
    ],
    "wof:name":"Klimaver B.v.b.a.",
    "wof:placetype":"venue"
},
  "geometry": {"coordinates":[3.6858038902,50.9969787598],"type":"Point"}
}