{
  "type": "Feature",
  "properties": {
    "addr:full":"Ijzerhandstraat 4 Kortrijk West-Vlaanderen 8510",
    "addr:housenumber":"4",
    "addr:postcode":"8510",
    "addr:street":"Ijzerhandstraat",
    "iso:country":"BE",
    "sg:address":"Ijzerhandstraat 4",
    "sg:city":"Kortrijk",
    "sg:orig_category":"Studios photographiques",
    "sg:phone":"+32 56 20 15 47",
    "sg:postcode":"8510",
    "sg:province":"West-Vlaanderen",
    "wof:name":"Studio Een Ind.& Com.foto",
    "wof:placetype":"venue"
},
  "geometry": {"coordinates":[3.2927310467,50.7626457214],"type":"Point"}
}