{
  "type": "Feature",
  "properties": {
    "addr:full":"Stappersestraat 3 Diest Vlaams-Brabant 3290",
    "addr:housenumber":"3",
    "addr:postcode":"3290",
    "addr:street":"Stappersestraat",
    "iso:country":"BE",
    "sg:address":"Stappersestraat 3",
    "sg:city":"Diest",
    "sg:orig_category":"Woningbouw",
    "sg:phone":"+32 13 32 31 36",
    "sg:postcode":"3290",
    "sg:province":"Vlaams-Brabant",
    "wof:name":"Mineur",
    "wof:placetype":"venue"
},
  "geometry": {"coordinates":[5.1052970886,51.0137634277],"type":"Point"}
}