{
  "type": "Feature",
  "properties": {
    "addr:full":"Rue De L'harmonie 58 Verviers Li\u00e8ge 4800",
    "addr:housenumber":"58",
    "addr:postcode":"4800",
    "addr:street":"Rue De L'Harmonie",
    "iso:country":"BE",
    "sg:address":"Rue De L'harmonie 58",
    "sg:city":"Verviers",
    "sg:classifiers":[
        {
            "category":"Place Of Worship",
            "subcategory":"Church",
            "type":"Public Place"
        }
    ],
    "sg:phone":"+32 87 31 68 94",
    "sg:postcode":"4800",
    "sg:province":"Li\u00e8ge",
    "sg:tags":[
        "article",
        "baptismal"
    ],
    "wof:name":"Gourmandise (la)",
    "wof:placetype":"venue"
},
  "geometry": {"coordinates":[5.8755340576,50.5953216553],"type":"Point"}
}