{
  "type": "Feature",
  "properties": {
    "addr:full":"Oude Kuringerbaan 41 Hasselt Limburg 3500",
    "addr:housenumber":"41",
    "addr:postcode":"3500",
    "addr:street":"Oude Kuringerbaan",
    "iso:country":"BE",
    "sg:address":"Oude Kuringerbaan 41",
    "sg:city":"Hasselt",
    "sg:classifiers":[
        {
            "category":"Professional",
            "subcategory":"Business Services",
            "type":"Services"
        }
    ],
    "sg:phone":"+32 11 22 52 53",
    "sg:postcode":"3500",
    "sg:province":"Limburg",
    "sg:tags":[
        "bookkeeping"
    ],
    "wof:name":"Tschoschia M",
    "wof:placetype":"venue"
},
  "geometry": {"coordinates":[5.3251137733,50.9344711304],"type":"Point"}
}