{
  "type": "Feature",
  "properties": {
    "addr:full":"Rue Du Tilleul 304 Schaarbeek/schaerbeek Bruxelles-Capitale 1030",
    "addr:housenumber":"304",
    "addr:postcode":"1030",
    "addr:street":"Rue Du Tilleul",
    "iso:country":"BE",
    "sg:address":"Rue Du Tilleul 304",
    "sg:city":"Schaarbeek/schaerbeek",
    "sg:classifiers":[
        {
            "category":"Arena",
            "subcategory":"Sports Club",
            "type":"Entertainment"
        }
    ],
    "sg:phone":"+32 2 241 28 65",
    "sg:postcode":"1030",
    "sg:province":"Bruxelles-Capitale",
    "sg:tags":[
        "de"
    ],
    "wof:name":"B.b.c. Royal Anciens 13",
    "wof:placetype":"venue"
},
  "geometry": {"coordinates":[4.3954792023,50.8696784973],"type":"Point"}
}