{
  "type": "Feature",
  "properties": {
    "addr:full":"Rue Du Gouty 14 Froidchapelle Hainaut 6440",
    "addr:housenumber":"14",
    "addr:postcode":"6440",
    "addr:street":"Rue Du Gouty",
    "iso:country":"BE",
    "sg:address":"Rue Du Gouty 14",
    "sg:city":"Froidchapelle",
    "sg:orig_category":"Sportclubs",
    "sg:phone":"+32 60 41 17 26",
    "sg:postcode":"6440",
    "sg:province":"Hainaut",
    "wof:name":"T.c. Froidchapelle Smash",
    "wof:placetype":"venue"
},
  "geometry": {"coordinates":[4.3307042122,50.1512794495],"type":"Point"}
}