{
  "type": "Feature",
  "properties": {
    "addr:full":"Kleistraat 2 Malle Antwerpen 2390",
    "addr:housenumber":"2",
    "addr:postcode":"2390",
    "addr:street":"Kleistraat",
    "iso:country":"BE",
    "sg:address":"Kleistraat 2",
    "sg:city":"Malle",
    "sg:orig_category":"Eleveurs de bovins",
    "sg:phone":"+32 3 312 49 70",
    "sg:postcode":"2390",
    "sg:province":"Antwerpen",
    "wof:name":"Jan Hofkens",
    "wof:placetype":"venue"
},
  "geometry": {"coordinates":[4.6847720146,51.3141212463],"type":"Point"}
}