{
  "type": "Feature",
  "properties": {
    "iso:country":"BE",
    "sg:address":"Halewijnstraat 24a",
    "sg:city":"Gent",
    "sg:orig_category":"Elektrische installaties voor woningen Loodgieterij, verwarming and sanitaire installaties",
    "sg:phone":"+32 9 227 95 62",
    "sg:postcode":"9031",
    "sg:province":"Oost-Vlaanderen",
    "wof:name":"Van Haver",
    "wof:placetype":"venue"
},
  "geometry": {"coordinates":[3.6260890961,51.0488739014],"type":"Point"}
}