{
  "type": "Feature",
  "properties": {
    "addr:full":"Vis\u00e9weg 398 Tongeren Limburg 3700",
    "addr:housenumber":"398",
    "addr:postcode":"3700",
    "addr:street":"Vise\u0301Weg",
    "iso:country":"BE",
    "sg:address":"Vis\u00e9weg 398",
    "sg:city":"Tongeren",
    "sg:classifiers":[
        {
            "category":"Building & Trades",
            "subcategory":"Construction",
            "type":"Services"
        }
    ],
    "sg:phone":"+32 12 23 99 99",
    "sg:postcode":"3700",
    "sg:province":"Limburg",
    "sg:tags":[
        "carpenter"
    ],
    "wof:name":"Daenen L",
    "wof:placetype":"venue"
},
  "geometry": {"coordinates":[5.5108981133,50.7843208313],"type":"Point"}
}