{
  "type": "Feature",
  "properties": {
    "iso:country":"BE",
    "sg:address":"Leuvensesteenweg 354",
    "sg:city":"Mechelen",
    "sg:orig_category":"Fleurs and plantes",
    "sg:phone":"+32 15 41 52 30",
    "sg:postcode":"2812",
    "sg:province":"Antwerpen",
    "wof:name":"Iris",
    "wof:placetype":"venue"
},
  "geometry": {"coordinates":[4.5150761604,51.0108947754],"type":"Point"}
}