{
  "type": "Feature",
  "properties": {
    "addr:full":"Rue De Paris 12 Silly (bassilly) Hainaut 7830",
    "addr:housenumber":"12",
    "addr:postcode":"7830",
    "addr:street":"Rue De Paris",
    "iso:country":"BE",
    "sg:address":"Rue De Paris 12",
    "sg:city":"Silly (bassilly)",
    "sg:classifiers":[
        {
            "category":"Building & Trades",
            "subcategory":"Electrical",
            "type":"Services"
        }
    ],
    "sg:phone":"+32 68 55 25 93",
    "sg:postcode":"7830",
    "sg:province":"Hainaut",
    "sg:tags":[
        "electric",
        "-",
        "housewiring",
        "contractor"
    ],
    "wof:name":"Dumortier (ets)",
    "wof:placetype":"venue"
},
  "geometry": {"coordinates":[3.9194788933,50.6833152771],"type":"Point"}
}