{
  "type": "Feature",
  "properties": {
    "addr:full":"Rue Duhainaut 76 Box 4 Namur (jambes) Namur 5100",
    "addr:housenumber":"76;4",
    "addr:postcode":"5100",
    "addr:street":"Rue Duhainaut;Box",
    "iso:country":"BE",
    "sg:address":"Rue Duhainaut 76 Box 4",
    "sg:city":"Namur (jambes)",
    "sg:classifiers":[
        {
            "category":"Personal",
            "subcategory":"Nail Salon",
            "type":"Services"
        }
    ],
    "sg:phone":"+32 81 32 21 59",
    "sg:postcode":"5100",
    "sg:province":"Namur",
    "sg:tags":[
        "pedicure"
    ],
    "wof:name":"Bultot C",
    "wof:placetype":"venue"
},
  "geometry": {"coordinates":[4.8713750839,50.4566345215],"type":"Point"}
}