{
  "type": "Feature",
  "properties": {
    "addr:full":"Coebergerstraat 35-37 Antwerpen Antwerpen 2018",
    "addr:postcode":"35-37;2018",
    "addr:street":"Coebergerstraat",
    "iso:country":"BE",
    "sg:address":"Coebergerstraat 35-37",
    "sg:city":"Antwerpen",
    "sg:classifiers":[
        {
            "category":"Social Services",
            "type":"Services"
        }
    ],
    "sg:phone":"+32 3 248 90 08",
    "sg:postcode":"2018",
    "sg:province":"Antwerpen",
    "wof:name":"Kids Antwerpen Zuid Vzw",
    "wof:placetype":"venue"
},
  "geometry": {"coordinates":[4.3956069946,51.2000770569],"type":"Point"}
}