{
  "type": "Feature",
  "properties": {
    "addr:full":"Boulevard G\u00c9n. Wahis 242 Brussel/bruxelles Bruxelles-Capitale 1030",
    "addr:housenumber":"242",
    "addr:postcode":"1030",
    "addr:street":"Boulevard Ge\u0301N Wahis;/",
    "iso:country":"BE",
    "sg:address":"Boulevard G\u00c9n. Wahis 242",
    "sg:city":"Brussel/bruxelles",
    "sg:orig_category":"Technische studies and ingenieursactiviteiten",
    "sg:phone":"+32 2 705 34 49",
    "sg:postcode":"1030",
    "sg:province":"Bruxelles-Capitale",
    "wof:name":"Corden Robot",
    "wof:placetype":"venue"
},
  "geometry": {"coordinates":[4.3984360695,50.8563804626],"type":"Point"}
}