{
  "type": "Feature",
  "properties": {
    "addr:full":"Waterstraat 33 Aalst (gijzegem) Oost-Vlaanderen 9308",
    "addr:housenumber":"33",
    "addr:postcode":"9308",
    "addr:street":"Waterstraat",
    "iso:country":"BE",
    "sg:address":"Waterstraat 33",
    "sg:city":"Aalst (gijzegem)",
    "sg:classifiers":[
        {
            "category":"Utilities",
            "subcategory":"Refuse",
            "type":"Services"
        }
    ],
    "sg:phone":"+32 53 21 28 90",
    "sg:postcode":"9308",
    "sg:province":"Oost-Vlaanderen",
    "sg:tags":[
        "miller"
    ],
    "wof:name":"Michiels P",
    "wof:placetype":"venue"
},
  "geometry": {"coordinates":[4.0338511467,50.9863967896],"type":"Point"}
}