{
  "type": "Feature",
  "properties": {
    "iso:country":"BE",
    "sg:address":"Rue D' Oha 21",
    "sg:city":"Wanze",
    "sg:classifiers":[
        {
            "category":"Arena",
            "subcategory":"Sports Club",
            "type":"Entertainment"
        }
    ],
    "sg:phone":"+32 85 23 02 25",
    "sg:postcode":"4520",
    "sg:province":"Li\u00e8ge",
    "sg:tags":[
        "terrain",
        "hors",
        "de",
        "installation",
        "sportifs"
    ],
    "wof:name":"R.j.s. Bas-oha",
    "wof:placetype":"venue"
},
  "geometry": {"coordinates":[5.1655631065,50.5663757324],"type":"Point"}
}