{
  "type": "Feature",
  "properties": {
    "iso:country":"BE",
    "sg:address":"Populierenstraat 33",
    "sg:city":"Hasselt",
    "sg:orig_category":"Boekhouders",
    "sg:phone":"+32 11 22 58 92",
    "sg:postcode":"3511",
    "sg:province":"Limburg",
    "wof:name":"Catherine Devries",
    "wof:placetype":"venue"
},
  "geometry": {"coordinates":[5.3308539391,50.9488105774],"type":"Point"}
}