{
  "type": "Feature",
  "properties": {
    "iso:country":"BE",
    "sg:address":"Ijzerlei 21",
    "sg:city":"Leopoldsburg",
    "sg:classifiers":[
        {
            "category":"Freight",
            "type":"Transportation"
        }
    ],
    "sg:phone":"+32 11 40 33 94",
    "sg:postcode":"3970",
    "sg:province":"Limburg",
    "sg:tags":[
        "-",
        "transport"
    ],
    "wof:name":"D-trans",
    "wof:placetype":"venue"
},
  "geometry": {"coordinates":[5.2565178871,51.1175575256],"type":"Point"}
}