{
  "type": "Feature",
  "properties": {
    "iso:country":"BE",
    "sg:address":"Tilburgseweg 124",
    "sg:city":"Ravels (poppel)",
    "sg:classifiers":[
        {
            "category":"Banks & Credit Unions",
            "subcategory":"Investment Brokerage",
            "type":"Services"
        }
    ],
    "sg:phone":"+32 14 65 64 31",
    "sg:postcode":"2382",
    "sg:province":"Antwerpen",
    "sg:tags":[
        "repair",
        "-",
        "installation",
        "sanitary",
        "article"
    ],
    "wof:name":"Moeskops K Bvba",
    "wof:placetype":"venue"
},
  "geometry": {"coordinates":[5.041768074,51.4469108582],"type":"Point"}
}