{
  "type": "Feature",
  "properties": {
    "addr:full":"Nieuwstad 4 Antwerpen Antwerpen 2000",
    "addr:housenumber":"4",
    "addr:postcode":"2000",
    "addr:street":"Nieuwstad",
    "iso:country":"BE",
    "sg:address":"Nieuwstad 4",
    "sg:city":"Antwerpen",
    "sg:classifiers":[
        {
            "category":"Bars & Pubs",
            "type":"Food & Drink"
        }
    ],
    "sg:phone":"+32 3 225 18 98",
    "sg:postcode":"2000",
    "sg:province":"Antwerpen",
    "wof:name":"Groote Comedie (de)",
    "wof:placetype":"venue"
},
  "geometry": {"coordinates":[4.4095788002,51.2140388489],"type":"Point"}
}