{
  "type": "Feature",
  "properties": {
    "iso:country":"BE",
    "sg:address":"Trichterweg 55",
    "sg:city":"Zutendaal",
    "sg:classifiers":[
        {
            "category":"Utilities",
            "subcategory":"Fuel Oil & Lpg",
            "type":"Services"
        }
    ],
    "sg:phone":"+32 89 73 26 79",
    "sg:postcode":"3690",
    "sg:province":"Limburg",
    "wof:name":"Lemmens-meesters Nv Nv",
    "wof:placetype":"venue"
},
  "geometry": {"coordinates":[5.5989279747,50.9278335571],"type":"Point"}
}