{
  "type": "Feature",
  "properties": {
    "addr:full":"Leuvensestraat 184 Vilvoorde Vlaams-Brabant 1800",
    "addr:housenumber":"184",
    "addr:postcode":"1800",
    "addr:street":"Leuvensestraat",
    "iso:country":"BE",
    "sg:address":"Leuvensestraat 184",
    "sg:city":"Vilvoorde",
    "sg:classifiers":[
        {
            "category":"Fast Food",
            "type":"Food & Drink"
        }
    ],
    "sg:phone":"+32 2 253 97 77",
    "sg:postcode":"1800",
    "sg:province":"Vlaams-Brabant",
    "sg:tags":[
        "meeneem",
        "restaurant"
    ],
    "wof:name":"Pizza Scarabee",
    "wof:placetype":"venue"
},
  "geometry": {"coordinates":[4.4341578484,50.9276199341],"type":"Point"}
}