{
  "type": "Feature",
  "properties": {
    "iso:country":"BE",
    "sg:address":"August Beernaertstraat 5",
    "sg:city":"De Haan (klemskerke)",
    "sg:classifiers":[
        {
            "category":"Food & Beverages",
            "subcategory":"Groceries & Convenience Stores",
            "type":"Retail Goods"
        }
    ],
    "sg:phone":"+32 59 23 43 79",
    "sg:postcode":"8420",
    "sg:province":"West-Vlaanderen",
    "sg:tags":[
        "grocer"
    ],
    "wof:name":"Fruitkorf (de)",
    "wof:placetype":"venue"
},
  "geometry": {"coordinates":[3.0345220566,51.2714653015],"type":"Point"}
}