{
  "type": "Feature",
  "properties": {
    "iso:country":"BE",
    "sg:address":"Grensstraat 170",
    "sg:city":"Kapellen",
    "sg:orig_category":"Articles de jardin",
    "sg:phone":"+32 3 664 32 70",
    "sg:postcode":"2950",
    "sg:province":"Antwerpen",
    "wof:name":"Fa. Van Bouwel",
    "wof:placetype":"venue"
},
  "geometry": {"coordinates":[4.4193367958,51.3618850708],"type":"Point"}
}