{
  "type": "Feature",
  "properties": {
    "iso:country":"BE",
    "sg:address":"Krimeestraat 1",
    "sg:city":"Bonheiden (rijmenam)",
    "sg:classifiers":[
        {
            "category":"Health Services",
            "subcategory":"Medical Lab",
            "type":"Services"
        }
    ],
    "sg:phone":"+32 15 51 34 12",
    "sg:postcode":"2820",
    "sg:province":"Antwerpen",
    "sg:tags":[
        "laboratory",
        "dental"
    ],
    "wof:name":"Strubbe Luc",
    "wof:placetype":"venue"
},
  "geometry": {"coordinates":[4.5496602058,51.0218009949],"type":"Point"}
}