{
  "type": "Feature",
  "properties": {
    "addr:full":"Heuvelstraat 28 Bocholt Limburg 3950",
    "addr:housenumber":"28",
    "addr:postcode":"3950",
    "addr:street":"Heuvelstraat",
    "iso:country":"BE",
    "sg:address":"Heuvelstraat 28",
    "sg:city":"Bocholt",
    "sg:classifiers":[
        {
            "category":"Personal",
            "type":"Services"
        }
    ],
    "sg:phone":"+32 89 46 14 02",
    "sg:postcode":"3950",
    "sg:province":"Limburg",
    "sg:tags":[
        "party",
        "planning"
    ],
    "wof:name":"Heuvelheem-feestzaal",
    "wof:placetype":"venue"
},
  "geometry": {"coordinates":[5.5818071365,51.1757888794],"type":"Point"}
}