{
  "type": "Feature",
  "properties": {
    "addr:full":"Sentier Du Pairoux 2-6 Li\u00e8ge 1 (rocourt) Li\u00e8ge 4000",
    "addr:housenumber":"2-6;1",
    "addr:postcode":"4000",
    "addr:street":"Sentier Du Pairoux",
    "iso:country":"BE",
    "sg:address":"Sentier Du Pairoux 2-6",
    "sg:city":"Li\u00e8ge 1 (rocourt)",
    "sg:classifiers":[
        {
            "category":"Train Station",
            "subcategory":"Rail",
            "type":"Transportation"
        }
    ],
    "sg:phone":"+32 4 263 35 18",
    "sg:postcode":"4000",
    "sg:province":"Li\u00e8ge",
    "sg:tags":[
        "bulk",
        "good",
        "-",
        "transport"
    ],
    "wof:name":"S C T R Sa",
    "wof:placetype":"venue"
},
  "geometry": {"coordinates":[5.5524859428,50.6835670471],"type":"Point"}
}