{
  "type": "Feature",
  "properties": {
    "addr:full":"Ardooisestraat 124 Izegem West-Vlaanderen 8870",
    "addr:housenumber":"124",
    "addr:postcode":"8870",
    "addr:street":"Ardooisestraat",
    "iso:country":"BE",
    "sg:address":"Ardooisestraat 124",
    "sg:city":"Izegem",
    "sg:orig_category":"Jardinage. Plantes and fleurs Gr",
    "sg:phone":"+32 51 30 73 95",
    "sg:postcode":"8870",
    "sg:province":"West-Vlaanderen",
    "wof:name":"Het Vijverteam",
    "wof:placetype":"venue"
},
  "geometry": {"coordinates":[3.2057080269,50.938041687],"type":"Point"}
}