{
  "type": "Feature",
  "properties": {
    "addr:full":"Kortemarkstraat 71 Ichtegem West-Vlaanderen 8480",
    "addr:housenumber":"71",
    "addr:postcode":"8480",
    "addr:street":"Kortemarkstraat",
    "iso:country":"BE",
    "sg:address":"Kortemarkstraat 71",
    "sg:city":"Ichtegem",
    "sg:orig_category":"Dierenartsen",
    "sg:phone":"+32 51 58 97 20",
    "sg:postcode":"8480",
    "sg:province":"West-Vlaanderen",
    "wof:name":"Jacques Vandecasteele",
    "wof:placetype":"venue"
},
  "geometry": {"coordinates":[3.0278968811,51.0739326477],"type":"Point"}
}