{
  "type": "Feature",
  "properties": {
    "iso:country":"BE",
    "sg:address":"Heislag 36",
    "sg:city":"Brasschaat",
    "sg:classifiers":[
        {
            "category":"Government",
            "subcategory":"Office",
            "type":"Public Place"
        }
    ],
    "sg:phone":"+32 3 652 05 00",
    "sg:postcode":"2930",
    "sg:province":"Antwerpen",
    "sg:tags":[
        "environmental",
        "contro",
        "pollution"
    ],
    "wof:name":"Arivic Bvba",
    "wof:placetype":"venue"
},
  "geometry": {"coordinates":[4.5090918541,51.3004760742],"type":"Point"}
}