{
  "type": "Feature",
  "properties": {
    "iso:country":"BE",
    "sg:address":"Morgensterpad 3",
    "sg:city":"Knokke-heist",
    "sg:orig_category":"Marktonderzoekbureaus",
    "sg:phone":"+32 50 62 81 49",
    "sg:postcode":"8300",
    "sg:province":"West-Vlaanderen",
    "wof:name":"Bureau 2-sigma",
    "wof:placetype":"venue"
},
  "geometry": {"coordinates":[3.2766439915,51.3452568054],"type":"Point"}
}