{
  "type": "Feature",
  "properties": {
    "iso:country":"BE",
    "sg:address":"Rue Bonne Fortune 6",
    "sg:city":"Luik",
    "sg:orig_category":"Musea and historische gebouwen",
    "sg:phone":"+32 4 232 61 30",
    "sg:postcode":"4000",
    "sg:province":"Li\u00e8ge",
    "wof:name":"Cath\u00c9drale De Li\u00c8ge",
    "wof:placetype":"venue"
},
  "geometry": {"coordinates":[5.57162714,50.6398658752],"type":"Point"}
}