{
  "type": "Feature",
  "properties": {
    "iso:country":"BE",
    "sg:address":"Kerkstraat 114",
    "sg:city":"Antwerpen",
    "sg:classifiers":[
        {
            "category":"Home & Garden",
            "subcategory":"Home Furnishings",
            "type":"Retail Goods"
        }
    ],
    "sg:phone":"+32 3 235 78 74",
    "sg:postcode":"2060",
    "sg:province":"Antwerpen",
    "sg:tags":[
        "-",
        "furniture"
    ],
    "wof:name":"Prijzenkoning (de)",
    "wof:placetype":"venue"
},
  "geometry": {"coordinates":[4.4330778122,51.2190856934],"type":"Point"}
}