{
  "type": "Feature",
  "properties": {
    "addr:full":"Baerdonckstraat 33 Wetteren Oost-Vlaanderen 9230",
    "addr:housenumber":"33",
    "addr:postcode":"9230",
    "addr:street":"Baerdonckstraat",
    "iso:country":"BE",
    "sg:address":"Baerdonckstraat 33",
    "sg:city":"Wetteren",
    "sg:orig_category":"Boucheries",
    "sg:phone":"+32 9 368 10 78",
    "sg:postcode":"9230",
    "sg:province":"Oost-Vlaanderen",
    "wof:name":"Erik Stalpaert",
    "wof:placetype":"venue"
},
  "geometry": {"coordinates":[3.88270998,51.0128135681],"type":"Point"}
}