{
  "type": "Feature",
  "properties": {
    "addr:full":"Rue D'argent 15 Enghien Hainaut 7850",
    "addr:housenumber":"15",
    "addr:postcode":"7850",
    "addr:street":"Rue D'Argent",
    "iso:country":"BE",
    "sg:address":"Rue D'argent 15",
    "sg:city":"Enghien",
    "sg:classifiers":[
        {
            "category":"Health Services",
            "subcategory":"Doctor",
            "type":"Services"
        }
    ],
    "sg:phone":"+32 2 395 92 80",
    "sg:postcode":"7850",
    "sg:province":"Hainaut",
    "sg:tags":[
        "psychotherapist",
        "psychoanalyst"
    ],
    "wof:name":"Petit R",
    "wof:placetype":"venue"
},
  "geometry": {"coordinates":[4.0381817818,50.6940727234],"type":"Point"}
}