{
  "type": "Feature",
  "properties": {
    "addr:full":"Jan Breydelstraat 30 Gent Oost-Vlaanderen 9000",
    "addr:housenumber":"30",
    "addr:postcode":"9000",
    "addr:street":"Jan Breydelstraat;Oost-Vlaanderen",
    "iso:country":"BE",
    "sg:address":"Jan Breydelstraat 30",
    "sg:city":"Gent",
    "sg:orig_category":"Artiesten and kunstenaars Zalen voor culturele evenementen",
    "sg:phone":"+32 9 233 08 85",
    "sg:postcode":"9000",
    "sg:province":"Oost-Vlaanderen",
    "wof:name":"Galerij Myriel",
    "wof:placetype":"venue"
},
  "geometry": {"coordinates":[3.7201099396,51.0564422607],"type":"Point"}
}