{
  "type": "Feature",
  "properties": {
    "addr:full":"Vaarnewijkstraat 7 Harelbeke West-Vlaanderen 8530",
    "addr:housenumber":"7",
    "addr:postcode":"8530",
    "addr:street":"Vaarnewijkstraat",
    "iso:country":"BE",
    "sg:address":"Vaarnewijkstraat 7",
    "sg:city":"Harelbeke",
    "sg:orig_category":"Entretien and r\u00e9parations de voitures",
    "sg:phone":"+32 56 71 23 90",
    "sg:postcode":"8530",
    "sg:province":"West-Vlaanderen",
    "wof:name":"Noel Bekaert",
    "wof:placetype":"venue"
},
  "geometry": {"coordinates":[3.3087580204,50.8659515381],"type":"Point"}
}