{
  "type": "Feature",
  "properties": {
    "iso:country":"BE",
    "sg:address":"Rue Des Meuniers 11",
    "sg:city":"Hannut (thisnes)",
    "sg:classifiers":[
        {
            "category":"Communications",
            "subcategory":"Film & Video Production",
            "type":"Services"
        }
    ],
    "sg:phone":"+32 19 51 35 45",
    "sg:postcode":"4280",
    "sg:province":"Li\u00e8ge",
    "sg:tags":[
        "sound",
        "recording",
        "studio"
    ],
    "wof:name":"Impact Music",
    "wof:placetype":"venue"
},
  "geometry": {"coordinates":[5.0425491333,50.6696052551],"type":"Point"}
}