{
  "type": "Feature",
  "properties": {
    "iso:country":"BE",
    "sg:address":"Rue Des Israelites 62",
    "sg:city":"Frameries",
    "sg:orig_category":"Herstellingen and onderhoud van auto's",
    "sg:phone":"+32 65 66 12 59",
    "sg:postcode":"7080",
    "sg:province":"Hainaut",
    "wof:name":"E. Lienard",
    "wof:placetype":"venue"
},
  "geometry": {"coordinates":[3.8695580959,50.3984794617],"type":"Point"}
}