{
  "type": "Feature",
  "properties": {
    "addr:full":"Leo Kempenaersstraat 106 Heist-op-den-berg Antwerpen 2223",
    "addr:housenumber":"106",
    "addr:postcode":"2223",
    "addr:street":"Leo Kempenaersstraat",
    "iso:country":"BE",
    "sg:address":"Leo Kempenaersstraat 106",
    "sg:city":"Heist-op-den-berg",
    "sg:classifiers":[
        {
            "category":"Insurance",
            "subcategory":"Life Insurance",
            "type":"Services"
        }
    ],
    "sg:phone":"+32 15 23 40 60",
    "sg:postcode":"2223",
    "sg:province":"Antwerpen",
    "sg:tags":[
        "assurance"
    ],
    "wof:name":"M. Verdyck",
    "wof:placetype":"venue"
},
  "geometry": {"coordinates":[4.6935648918,51.0282707214],"type":"Point"}
}