{
  "type": "Feature",
  "properties": {
    "addr:full":"Avenue Des Commandants Borl\u00e9e 33 Jodoigne Brabant Wallon 1370",
    "addr:housenumber":"33",
    "addr:postcode":"1370",
    "addr:street":"Avenue Des Commandants Borle\u0301E",
    "iso:country":"BE",
    "sg:address":"Avenue Des Commandants Borl\u00e9e 33",
    "sg:city":"Jodoigne",
    "sg:classifiers":[
        {
            "category":"Shopping",
            "subcategory":"Optician",
            "type":"Retail Goods"
        }
    ],
    "sg:phone":"+32 10 81 61 95",
    "sg:postcode":"1370",
    "sg:province":"Brabant Wallon",
    "sg:tags":[
        "-"
    ],
    "wof:name":"Point De Mire",
    "wof:placetype":"venue"
},
  "geometry": {"coordinates":[4.8742752075,50.7219619751],"type":"Point"}
}