{
  "type": "Feature",
  "properties": {
    "addr:full":"Paleizenstraat 301 Bruxelles Bruxelles-Capitale 1000",
    "addr:housenumber":"301",
    "addr:postcode":"1000",
    "addr:street":"Paleizenstraat",
    "iso:country":"BE",
    "sg:address":"Paleizenstraat 301",
    "sg:city":"Bruxelles",
    "sg:orig_category":"Non-Classified Establishments",
    "sg:phone":"+32 2 203 51 30",
    "sg:postcode":"1000",
    "sg:province":"Bruxelles-Capitale",
    "wof:name":"Simop Belgium Sa",
    "wof:placetype":"venue"
},
  "geometry": {"coordinates":[4.3627791405,50.871383667],"type":"Point"}
}