{
  "type": "Feature",
  "properties": {
    "addr:full":"Route De Habay 88 Attert (nobressart) Luxembourg 6717",
    "addr:housenumber":"88",
    "addr:postcode":"6717",
    "addr:street":"Route De Habay",
    "iso:country":"BE",
    "sg:address":"Route De Habay 88",
    "sg:city":"Attert (nobressart)",
    "sg:classifiers":[
        {
            "category":"Building & Trades",
            "subcategory":"Electrical",
            "type":"Services"
        }
    ],
    "sg:phone":"+32 63 22 56 61",
    "sg:postcode":"6717",
    "sg:province":"Luxembourg",
    "sg:tags":[
        "electric",
        "-",
        "housewiring",
        "contractor"
    ],
    "wof:name":"Boegen A",
    "wof:placetype":"venue"
},
  "geometry": {"coordinates":[5.7389187813,49.7748374939],"type":"Point"}
}