{
  "type": "Feature",
  "properties": {
    "addr:full":"Rue De L'abondance 22 Bruxelles (saint-josse-ten-noode) Bruxelles-Capitale 1210",
    "addr:housenumber":"22",
    "addr:postcode":"1210",
    "addr:street":"Rue De L'Abondance",
    "iso:country":"BE",
    "sg:address":"Rue De L'abondance 22",
    "sg:city":"Bruxelles (saint-josse-ten-noode)",
    "sg:classifiers":[
        {
            "category":"Shopping",
            "subcategory":"Bicycles & Sporting Goods",
            "type":"Retail Goods"
        }
    ],
    "sg:phone":"+32 2 217 70 60",
    "sg:postcode":"1210",
    "sg:province":"Bruxelles-Capitale",
    "sg:tags":[
        "tyre"
    ],
    "wof:name":"Fidcar Sprl K.s.k.",
    "wof:placetype":"venue"
},
  "geometry": {"coordinates":[4.3695449829,50.8529968262],"type":"Point"}
}