{
  "type": "Feature",
  "properties": {
    "addr:full":"Avenue De L' Europe 34 Courcelles Hainaut 6183",
    "addr:housenumber":"34",
    "addr:postcode":"6183",
    "addr:street":"Avenue De L ' Europe",
    "iso:country":"BE",
    "sg:address":"Avenue De L' Europe 34",
    "sg:city":"Courcelles",
    "sg:classifiers":[
        {
            "category":"Personal",
            "subcategory":"Beauty Salon",
            "type":"Services"
        }
    ],
    "sg:phone":"+32 71 45 29 26",
    "sg:postcode":"6183",
    "sg:province":"Hainaut",
    "sg:tags":[
        "de",
        "coiffure"
    ],
    "wof:name":"Marie De Mangeleire",
    "wof:placetype":"venue"
},
  "geometry": {"coordinates":[4.3333468437,50.4646034241],"type":"Point"}
}