{
  "type": "Feature",
  "properties": {
    "addr:full":"Andler 1ba Sankt Vith/saint-vith Li\u00e8ge 4782",
    "addr:housenumber":"1ba",
    "addr:postcode":"4782",
    "addr:street":"Andler",
    "iso:country":"BE",
    "sg:address":"Andler 1ba",
    "sg:city":"Sankt Vith/saint-vith",
    "sg:orig_category":"Eleveurs de bovins",
    "sg:phone":"+32 80 54 87 08",
    "sg:postcode":"4782",
    "sg:province":"Li\u00e8ge",
    "wof:name":"Leo Brodel",
    "wof:placetype":"venue"
},
  "geometry": {"coordinates":[6.2829198837,50.306060791],"type":"Point"}
}