{
  "type": "Feature",
  "properties": {
    "addr:full":"Molenstraat 24 Sint-niklaas Oost-Vlaanderen 9112",
    "addr:housenumber":"24",
    "addr:postcode":"9112",
    "addr:street":"Molenstraat",
    "iso:country":"BE",
    "sg:address":"Molenstraat 24",
    "sg:city":"Sint-niklaas",
    "sg:orig_category":"Artsen and specialisten",
    "sg:phone":"+32 3 772 25 26",
    "sg:postcode":"9112",
    "sg:province":"Oost-Vlaanderen",
    "wof:name":"R. Segers",
    "wof:placetype":"venue"
},
  "geometry": {"coordinates":[4.0522837639,51.1633453369],"type":"Point"}
}