{
  "type": "Feature",
  "properties": {
    "addr:full":"Chauss\u00e9e De Charleroi 307 Fleurus Hainaut 6220",
    "addr:housenumber":"307",
    "addr:postcode":"6220",
    "addr:street":"Chausse\u0301E De Charleroi",
    "iso:country":"BE",
    "sg:address":"Chauss\u00e9e De Charleroi 307",
    "sg:city":"Fleurus",
    "sg:classifiers":[
        {
            "category":"Insurance",
            "subcategory":"Insurance Agent",
            "type":"Services"
        }
    ],
    "sg:phone":"+32 71 81 77 87",
    "sg:postcode":"6220",
    "sg:province":"Hainaut",
    "sg:tags":[
        "broker"
    ],
    "wof:name":"D'arcangelo",
    "wof:placetype":"venue"
},
  "geometry": {"coordinates":[4.5485610962,50.479598999],"type":"Point"}
}