{
  "type": "Feature",
  "properties": {
    "addr:full":"Rootjensweg 44b1 Dendermonde Oost-Vlaanderen 9200",
    "addr:housenumber":"44b1",
    "addr:postcode":"9200",
    "addr:street":"Rootjensweg;Oost-Vlaanderen",
    "iso:country":"BE",
    "sg:address":"Rootjensweg 44b1",
    "sg:city":"Dendermonde",
    "sg:orig_category":"Installatie van houten of kunststof schrijnwerk Plaatsen van vloer- and muurbekleding Woningbouw",
    "sg:phone":"+32 52 22 50 74",
    "sg:postcode":"9200",
    "sg:province":"Oost-Vlaanderen",
    "wof:name":"Agabo",
    "wof:placetype":"venue"
},
  "geometry": {"coordinates":[4.1051411629,51.0546112061],"type":"Point"}
}