{
  "type": "Feature",
  "properties": {
    "iso:country":"BE",
    "sg:address":"Rue De La Gare 17",
    "sg:city":"Kelmis/la Calamine",
    "sg:orig_category":"Offices du tourisme",
    "sg:phone":"+32 87 65 82 13",
    "sg:postcode":"4728",
    "sg:province":"Li\u00e8ge",
    "wof:name":"Verkehrsverein",
    "wof:placetype":"venue"
},
  "geometry": {"coordinates":[6.0357689857,50.7088088989],"type":"Point"}
}