{
  "type": "Feature",
  "properties": {
    "addr:full":"Paul Parmentierlaan 41/43 Knokke-heist West-Vlaanderen 8300",
    "addr:housenumber":"41 / 43",
    "addr:postcode":"8300",
    "addr:street":"Paul Parmentierlaan",
    "iso:country":"BE",
    "sg:address":"Paul Parmentierlaan 41/43",
    "sg:city":"Knokke-heist",
    "sg:orig_category":"Zuivelproducten and spijsolie Gh",
    "sg:phone":"+32 50 60 66 42",
    "sg:postcode":"8300",
    "sg:province":"West-Vlaanderen",
    "wof:name":"Vermeersch Catering",
    "wof:placetype":"venue"
},
  "geometry": {"coordinates":[3.2854731083,51.3433761597],"type":"Point"}
}