{
  "type": "Feature",
  "properties": {
    "addr:full":"Franz Merjaystraat 28 Elsene/ixelles Bruxelles-Capitale 1050",
    "addr:housenumber":"28",
    "addr:postcode":"1050",
    "addr:street":"Franz Merjaystraat",
    "iso:country":"BE",
    "sg:address":"Franz Merjaystraat 28",
    "sg:city":"Elsene/ixelles",
    "sg:orig_category":"Etalage- and showroomontwerpers Fotografen and fotostudio's",
    "sg:phone":"+32 2 347 41 79",
    "sg:postcode":"1050",
    "sg:province":"Bruxelles-Capitale",
    "wof:name":"Gilles Batz",
    "wof:placetype":"venue"
},
  "geometry": {"coordinates":[4.3549098969,50.8211174011],"type":"Point"}
}