{
  "type": "Feature",
  "properties": {
    "addr:full":"Grand-rue 9 Bouillon Luxembourg 6830",
    "addr:housenumber":"9",
    "addr:postcode":"6830",
    "addr:street":"Grand-Rue",
    "iso:country":"BE",
    "sg:address":"Grand-rue 9",
    "sg:city":"Bouillon",
    "sg:classifiers":[
        {
            "category":"Restaurant",
            "type":"Food & Drink"
        }
    ],
    "sg:phone":"+32 61 46 62 77",
    "sg:postcode":"6830",
    "sg:province":"Luxembourg",
    "wof:name":"La Vieille Ardenne",
    "wof:placetype":"venue"
},
  "geometry": {"coordinates":[5.0694742203,49.7953987122],"type":"Point"}
}