{
  "type": "Feature",
  "properties": {
    "addr:full":"Grote Steenweg 81 De Pinte Oost-Vlaanderen 9840",
    "addr:housenumber":"81",
    "addr:postcode":"9840",
    "addr:street":"Grote Steenweg",
    "iso:country":"BE",
    "sg:address":"Grote Steenweg 81",
    "sg:city":"De Pinte",
    "sg:orig_category":"Eleveurs and marchands de porcs. Eleveurs de bovins",
    "sg:phone":"+32 9 222 76 10",
    "sg:postcode":"9840",
    "sg:province":"Oost-Vlaanderen",
    "wof:name":"Firmin Lampens",
    "wof:placetype":"venue"
},
  "geometry": {"coordinates":[3.6819489002,50.9878234863],"type":"Point"}
}