{
  "type": "Feature",
  "properties": {
    "addr:full":"Waalbeekstraat 29 Zulte Oost-Vlaanderen 9870",
    "addr:housenumber":"29",
    "addr:postcode":"9870",
    "addr:street":"Waalbeekstraat",
    "iso:country":"BE",
    "sg:address":"Waalbeekstraat 29",
    "sg:city":"Zulte",
    "sg:classifiers":[
        {
            "category":"Personal",
            "subcategory":"Beauty Salon",
            "type":"Services"
        }
    ],
    "sg:phone":"+32 9 388 44 40",
    "sg:postcode":"9870",
    "sg:province":"Oost-Vlaanderen",
    "sg:tags":[
        "lady",
        "-",
        "hairdressing"
    ],
    "wof:name":"Isabelle",
    "wof:placetype":"venue"
},
  "geometry": {"coordinates":[3.4641489983,50.919708252],"type":"Point"}
}