{
  "type": "Feature",
  "properties": {
    "iso:country":"BE",
    "sg:address":"Chauss\u00c9e De Binche 50bb",
    "sg:city":"Mons",
    "sg:orig_category":"Boucheries",
    "sg:phone":"+32 65 33 90 64",
    "sg:postcode":"7000",
    "sg:province":"Hainaut",
    "wof:name":"Boucherie La Toison D'or",
    "wof:placetype":"venue"
},
  "geometry": {"coordinates":[3.9824941158,50.4512825012],"type":"Point"}
}