{
  "type": "Feature",
  "properties": {
    "addr:full":"Haute Wegge 34 Waremme Li\u00e8ge 4300",
    "addr:housenumber":"34",
    "addr:postcode":"4300",
    "iso:country":"BE",
    "sg:address":"Haute Wegge 34",
    "sg:city":"Waremme",
    "sg:classifiers":[
        {
            "category":"Health Services",
            "subcategory":"Health Practitioner",
            "type":"Services"
        }
    ],
    "sg:phone":"+32 19 32 40 92",
    "sg:postcode":"4300",
    "sg:province":"Li\u00e8ge",
    "sg:tags":[
        "physiotherapist"
    ],
    "wof:name":"Guffens Carine",
    "wof:placetype":"venue"
},
  "geometry": {"coordinates":[5.247824192,50.7014884949],"type":"Point"}
}