{
  "type": "Feature",
  "properties": {
    "addr:full":"Rue Des Fourches 21 Leuze-en-hainaut (pipaix) Hainaut 7904",
    "addr:housenumber":"21",
    "addr:postcode":"7904",
    "addr:street":"Rue Des Fourches;Hainaut",
    "iso:country":"BE",
    "sg:address":"Rue Des Fourches 21",
    "sg:city":"Leuze-en-hainaut (pipaix)",
    "sg:classifiers":[
        {
            "category":"Health Services",
            "subcategory":"Health Practitioner",
            "type":"Services"
        }
    ],
    "sg:phone":"+32 69 66 11 73",
    "sg:postcode":"7904",
    "sg:province":"Hainaut",
    "sg:tags":[
        "physiotherapist"
    ],
    "wof:name":"Laho Roger",
    "wof:placetype":"venue"
},
  "geometry": {"coordinates":[3.5770459175,50.5797996521],"type":"Point"}
}