{
  "type": "Feature",
  "properties": {
    "addr:full":"Ondernemingsstraat 4 Veurne West-Vlaanderen 8630",
    "addr:housenumber":"4",
    "addr:postcode":"8630",
    "addr:street":"Ondernemingsstraat",
    "iso:country":"BE",
    "sg:address":"Ondernemingsstraat 4",
    "sg:city":"Veurne",
    "sg:orig_category":"Fietsen Fab",
    "sg:phone":"+32 58 31 11 22",
    "sg:postcode":"8630",
    "sg:province":"West-Vlaanderen",
    "wof:name":"Bonaventure J",
    "wof:placetype":"venue"
},
  "geometry": {"coordinates":[2.677850008,51.0620689392],"type":"Point"}
}