{
  "type": "Feature",
  "properties": {
    "iso:country":"BE",
    "sg:address":"Avenue De La Wallonie 6",
    "sg:city":"Leuze-en-hainaut",
    "sg:classifiers":[
        {
            "category":"Fast Food",
            "type":"Food & Drink"
        }
    ],
    "sg:phone":"+32 69 66 54 82",
    "sg:postcode":"7900",
    "sg:province":"Hainaut",
    "sg:tags":[
        "fried",
        "stand",
        "potato"
    ],
    "wof:name":"Friterie Du Centre",
    "wof:placetype":"venue"
},
  "geometry": {"coordinates":[3.6259829998,50.5963401794],"type":"Point"}
}