{
  "type": "Feature",
  "properties": {
    "iso:country":"BE",
    "sg:address":"Meensesteenweg 390",
    "sg:city":"Kortrijk",
    "sg:orig_category":"Loodgieterij, verwarming and sanitaire installaties",
    "sg:phone":"+32 56 55 87 15",
    "sg:postcode":"8501",
    "sg:province":"West-Vlaanderen",
    "wof:name":"Fa. Valcke J.p.",
    "wof:placetype":"venue"
},
  "geometry": {"coordinates":[3.2228019238,50.821144104],"type":"Point"}
}