{
  "type": "Feature",
  "properties": {
    "addr:full":"Rue Charleville 15 Gedinne Namur 5575",
    "addr:housenumber":"15",
    "addr:postcode":"5575",
    "addr:street":"Rue Charleville",
    "iso:country":"BE",
    "sg:address":"Rue Charleville 15",
    "sg:city":"Gedinne",
    "sg:orig_category":"Offices du tourisme",
    "sg:phone":"+32 61 58 82 32",
    "sg:postcode":"5575",
    "sg:province":"Namur",
    "wof:name":"Syndicat D'initiative",
    "wof:placetype":"venue"
},
  "geometry": {"coordinates":[4.9366922379,49.9796028137],"type":"Point"}
}