{
  "type": "Feature",
  "properties": {
    "addr:full":"Legeweg 157 Oostkamp West-Vlaanderen 8020",
    "addr:housenumber":"157",
    "addr:postcode":"8020",
    "addr:street":"Legeweg",
    "iso:country":"BE",
    "sg:address":"Legeweg 157",
    "sg:city":"Oostkamp",
    "sg:orig_category":"Rev\u00eatements de sols and murs. Construction industrielle and commerciale",
    "sg:phone":"+32 50 36 80 80",
    "sg:postcode":"8020",
    "sg:province":"West-Vlaanderen",
    "wof:name":"Beke",
    "wof:placetype":"venue"
},
  "geometry": {"coordinates":[3.2486140728,51.1724052429],"type":"Point"}
}