{
  "type": "Feature",
  "properties": {
    "addr:full":"Moeskouterlaan 7 Dendermonde (sint-gillis-bij-dendermonde) Oost-Vlaanderen 9200",
    "addr:housenumber":"7",
    "addr:postcode":"9200",
    "addr:street":"Moeskouterlaan",
    "iso:country":"BE",
    "sg:address":"Moeskouterlaan 7",
    "sg:city":"Dendermonde (sint-gillis-bij-dendermonde)",
    "sg:classifiers":[
        {
            "category":"Professional",
            "subcategory":"Management & Consulting",
            "type":"Services"
        }
    ],
    "sg:phone":"+32 52 22 15 28",
    "sg:postcode":"9200",
    "sg:province":"Oost-Vlaanderen",
    "sg:tags":[
        "-",
        "engineering",
        "electrical",
        "consultant"
    ],
    "wof:name":"Bergman Electronics",
    "wof:placetype":"venue"
},
  "geometry": {"coordinates":[4.1103758812,51.0131492615],"type":"Point"}
}