{
  "type": "Feature",
  "properties": {
    "addr:full":"Krijkelberg 1 Bierbeek Vlaams-Brabant 3360",
    "addr:housenumber":"1",
    "addr:postcode":"3360",
    "addr:street":"Krijkelberg",
    "iso:country":"BE",
    "sg:address":"Krijkelberg 1",
    "sg:city":"Bierbeek",
    "sg:classifiers":[
        {
            "category":"Health Services",
            "subcategory":"Hospital",
            "type":"Services"
        }
    ],
    "sg:phone":"+32 16 45 26 11",
    "sg:postcode":"3360",
    "sg:province":"Vlaams-Brabant",
    "wof:name":"Universitair Psychiatrisch Centrum St-kamillus",
    "wof:placetype":"venue"
},
  "geometry": {"coordinates":[4.7541489601,50.8509941101],"type":"Point"}
}