{
  "type": "Feature",
  "properties": {
    "addr:full":"Bouwenstraat 36 Lint Antwerpen 2547",
    "addr:housenumber":"36",
    "addr:postcode":"2547",
    "addr:street":"Bouwenstraat",
    "iso:country":"BE",
    "sg:address":"Bouwenstraat 36",
    "sg:city":"Lint",
    "sg:classifiers":[
        {
            "category":"Home & Garden",
            "subcategory":"Household Appliances",
            "type":"Retail Goods"
        }
    ],
    "sg:phone":"+32 3 829 15 48",
    "sg:postcode":"2547",
    "sg:province":"Antwerpen",
    "sg:tags":[
        "housewares",
        "-"
    ],
    "wof:name":"Rena Ware Service",
    "wof:placetype":"venue"
},
  "geometry": {"coordinates":[4.5030298233,51.1246528625],"type":"Point"}
}