{
  "type": "Feature",
  "properties": {
    "addr:full":"Rue De L'etang 93 Bruxelles (etterbeek) Bruxelles-Capitale 1040",
    "addr:housenumber":"93",
    "addr:postcode":"1040",
    "addr:street":"Rue De L'Etang",
    "iso:country":"BE",
    "sg:address":"Rue De L'etang 93",
    "sg:city":"Bruxelles (etterbeek)",
    "sg:classifiers":[
        {
            "category":"Utilities",
            "subcategory":"Natural Gas",
            "type":"Services"
        }
    ],
    "sg:phone":"+32 2 647 78 14",
    "sg:postcode":"1040",
    "sg:province":"Bruxelles-Capitale",
    "sg:tags":[
        "apiculture",
        "accessory"
    ],
    "wof:name":"Pique R",
    "wof:placetype":"venue"
},
  "geometry": {"coordinates":[4.3519678116,50.8579750061],"type":"Point"}
}