{
  "type": "Feature",
  "properties": {
    "iso:country":"BE",
    "sg:address":"Les Couturelles 3",
    "sg:city":"Walcourt",
    "sg:classifiers":[
        {
            "category":"Sports & Exercise",
            "subcategory":"Sports Center",
            "type":"Entertainment"
        }
    ],
    "sg:phone":"+32 71 22 05 02",
    "sg:postcode":"5651",
    "sg:province":"Namur",
    "sg:tags":[
        "de",
        "fitness"
    ],
    "wof:name":"Toni Vital Center",
    "wof:placetype":"venue"
},
  "geometry": {"coordinates":[4.4262080193,50.2824401855],"type":"Point"}
}