{
  "type": "Feature",
  "properties": {
    "addr:full":"Molenstraat 26 Gavere Oost-Vlaanderen 9890",
    "addr:housenumber":"26",
    "addr:postcode":"9890",
    "addr:street":"Molenstraat",
    "iso:country":"BE",
    "sg:address":"Molenstraat 26",
    "sg:city":"Gavere",
    "sg:classifiers":[
        {
            "category":"Cafe",
            "type":"Food & Drink"
        }
    ],
    "sg:phone":"+32 9 384 23 99",
    "sg:postcode":"9890",
    "sg:province":"Oost-Vlaanderen",
    "sg:tags":[
        "caf\u00e9s"
    ],
    "wof:name":"Cafe Kroonvogel",
    "wof:placetype":"venue"
},
  "geometry": {"coordinates":[3.6643190384,50.9281311035],"type":"Point"}
}