{
  "type": "Feature",
  "properties": {
    "iso:country":"BE",
    "sg:address":"Rue Archim\u00c8de 71",
    "sg:city":"Bruxelles",
    "sg:orig_category":"Levering aan huis restaurants",
    "sg:phone":"+32 2 734 24 84",
    "sg:postcode":"1000",
    "sg:province":"Bruxelles-Capitale",
    "wof:name":"Mi-figue Mi-raisin",
    "wof:placetype":"venue"
},
  "geometry": {"coordinates":[4.3839240074,50.8454017639],"type":"Point"}
}