{
  "type": "Feature",
  "properties": {
    "addr:full":"Rue Des M\u00e9sanges 16 Charleroi (marcinelle) Hainaut 6001",
    "addr:housenumber":"16",
    "addr:postcode":"6001",
    "addr:street":"Rue Des Me\u0301Sanges",
    "iso:country":"BE",
    "sg:address":"Rue Des M\u00e9sanges 16",
    "sg:city":"Charleroi (marcinelle)",
    "sg:classifiers":[
        {
            "category":"Health Services",
            "subcategory":"Doctor",
            "type":"Services"
        }
    ],
    "sg:phone":"+32 71 36 23 50",
    "sg:postcode":"6001",
    "sg:province":"Hainaut",
    "sg:tags":[
        "medicinephysicians",
        "surgeon"
    ],
    "wof:name":"Hens P",
    "wof:placetype":"venue"
},
  "geometry": {"coordinates":[4.4310121536,50.3699035645],"type":"Point"}
}