{
  "type": "Feature",
  "properties": {
    "addr:full":"Smarre 5a Oudenaarde (mater) Oost-Vlaanderen 9700",
    "addr:housenumber":"5a",
    "addr:postcode":"9700",
    "addr:street":"Smarre;Mater Oost-Vlaanderen",
    "iso:country":"BE",
    "sg:address":"Smarre 5a",
    "sg:city":"Oudenaarde (mater)",
    "sg:classifiers":[
        {
            "category":"Home & Garden",
            "subcategory":"Carpets & Floor Coverings",
            "type":"Retail Goods"
        }
    ],
    "sg:phone":"+32 55 23 96 44",
    "sg:postcode":"9700",
    "sg:province":"Oost-Vlaanderen",
    "sg:tags":[
        "tile"
    ],
    "wof:name":"Ceralux",
    "wof:placetype":"venue"
},
  "geometry": {"coordinates":[3.6940999031,50.8636741638],"type":"Point"}
}