{
  "type": "Feature",
  "properties": {
    "addr:full":"Neutralstrasse 322 Lontzen/lontzen Li\u00e8ge 4710",
    "addr:housenumber":"322",
    "addr:postcode":"4710",
    "addr:street":"Neutralstrasse",
    "iso:country":"BE",
    "sg:address":"Neutralstrasse 322",
    "sg:city":"Lontzen/lontzen",
    "sg:orig_category":"Pleisterwerk",
    "sg:phone":"+32 87 89 03 17",
    "sg:postcode":"4710",
    "sg:province":"Li\u00e8ge",
    "wof:name":"Jean-pierre Houben",
    "wof:placetype":"venue"
},
  "geometry": {"coordinates":[5.99229002,50.6763191223],"type":"Point"}
}