{
  "type": "Feature",
  "properties": {
    "iso:country":"BE",
    "sg:address":"Rue De Bailin 9",
    "sg:city":"Namur",
    "sg:orig_category":"Traitements param\u00e9dicaux",
    "sg:phone":"+32 81 46 29 67",
    "sg:postcode":"5100",
    "sg:province":"Namur",
    "wof:name":"M. Ryckaert",
    "wof:placetype":"venue"
},
  "geometry": {"coordinates":[4.8598060608,50.4182815552],"type":"Point"}
}