{
  "type": "Feature",
  "properties": {
    "iso:country":"BE",
    "sg:address":"Oevelenberg 14",
    "sg:city":"Lille",
    "sg:orig_category":"Eleveurs and marchands de porcs",
    "sg:phone":"+32 14 88 09 06",
    "sg:postcode":"2275",
    "sg:province":"Antwerpen",
    "wof:name":"Ludo Van Den Broeck",
    "wof:placetype":"venue"
},
  "geometry": {"coordinates":[4.8195347786,51.256603241],"type":"Point"}
}