{
  "type": "Feature",
  "properties": {
    "iso:country":"BE",
    "sg:address":"Grand'route 97",
    "sg:city":"Hamoir (filot)",
    "sg:classifiers":[
        {
            "category":"Structure",
            "subcategory":"Office Building",
            "type":"Public Place"
        }
    ],
    "sg:phone":"+32 86 38 84 55",
    "sg:postcode":"4181",
    "sg:province":"Li\u00e8ge",
    "sg:tags":[
        "roofing",
        "slate"
    ],
    "wof:name":"Meunier J-l",
    "wof:placetype":"venue"
},
  "geometry": {"coordinates":[5.5839800835,50.4247016907],"type":"Point"}
}