{
  "type": "Feature",
  "properties": {
    "iso:country":"BE",
    "sg:address":"Gelembekestraat 7",
    "sg:city":"Geraardsbergen",
    "sg:orig_category":"Rundveehouders",
    "sg:phone":"+32 54 41 60 55",
    "sg:postcode":"9500",
    "sg:province":"Oost-Vlaanderen",
    "wof:name":"Raphael Vincke",
    "wof:placetype":"venue"
},
  "geometry": {"coordinates":[3.8843801022,50.7716445923],"type":"Point"}
}