{
  "type": "Feature",
  "properties": {
    "addr:full":"Rue Reper Vreven 53 Bruxelles Bruxelles-Capitale 1020",
    "addr:housenumber":"53",
    "addr:postcode":"1020",
    "addr:street":"Rue Reper Vreven",
    "iso:country":"BE",
    "sg:address":"Rue Reper Vreven 53",
    "sg:city":"Bruxelles",
    "sg:classifiers":[
        {
            "category":"Autos & Motor Vehicles",
            "subcategory":"Auto Supplies",
            "type":"Retail Goods"
        }
    ],
    "sg:phone":"+32 2 478 46 39",
    "sg:postcode":"1020",
    "sg:province":"Bruxelles-Capitale",
    "sg:tags":[
        "access",
        "automobile",
        "part",
        "-"
    ],
    "wof:name":"W.w. Sprl",
    "wof:placetype":"venue"
},
  "geometry": {"coordinates":[4.341354847,50.8906402588],"type":"Point"}
}