{
  "type": "Feature",
  "properties": {
    "addr:full":"Industrieweg 1303 Herk-de-stad Limburg 3540",
    "addr:postcode":"1303;3540",
    "addr:street":"Industrieweg",
    "iso:country":"BE",
    "sg:address":"Industrieweg 1303",
    "sg:city":"Herk-de-stad",
    "sg:orig_category":"Non-Classified Establishments",
    "sg:phone":"+32 13 55 59 12",
    "sg:postcode":"3540",
    "sg:province":"Limburg",
    "wof:name":"Pontos Nv",
    "wof:placetype":"venue"
},
  "geometry": {"coordinates":[5.1707901955,50.9454612732],"type":"Point"}
}