{
  "type": "Feature",
  "properties": {
    "addr:full":"Rue De Heembeek 103 Bruxelles Bruxelles-Capitale 1120",
    "addr:housenumber":"103",
    "addr:postcode":"1120",
    "addr:street":"Rue De Heembeek",
    "iso:country":"BE",
    "sg:address":"Rue De Heembeek 103",
    "sg:city":"Bruxelles",
    "sg:classifiers":[
        {
            "category":"Building & Trades",
            "subcategory":"Plumbing",
            "type":"Services"
        }
    ],
    "sg:phone":"+32 2 245 80 92",
    "sg:postcode":"1120",
    "sg:province":"Bruxelles-Capitale",
    "sg:tags":[
        "contractor"
    ],
    "wof:name":"Plombi-services Sprl",
    "wof:placetype":"venue"
},
  "geometry": {"coordinates":[4.3781471252,50.8904151917],"type":"Point"}
}