{
  "type": "Feature",
  "properties": {
    "iso:country":"BE",
    "sg:address":"Dorpsstraat 22",
    "sg:city":"Diepenbeek",
    "sg:classifiers":[
        {
            "category":"Recreation",
            "subcategory":"Arcade",
            "type":"Entertainment"
        }
    ],
    "sg:phone":"+32 11 32 33 78",
    "sg:postcode":"3590",
    "sg:province":"Limburg",
    "sg:tags":[
        "machine",
        "amusement"
    ],
    "wof:name":"Philips H",
    "wof:placetype":"venue"
},
  "geometry": {"coordinates":[5.4206829071,50.9083786011],"type":"Point"}
}