{
  "type": "Feature",
  "properties": {
    "addr:full":"Dorpsstraat 81 Erpe-mere (erpe) Oost-Vlaanderen 9420",
    "addr:housenumber":"81",
    "addr:postcode":"9420",
    "addr:street":"Dorpsstraat",
    "iso:country":"BE",
    "sg:address":"Dorpsstraat 81",
    "sg:city":"Erpe-mere (erpe)",
    "sg:classifiers":[
        {
            "category":"Health Services",
            "subcategory":"Health Practitioner",
            "type":"Services"
        }
    ],
    "sg:phone":"+32 53 80 30 05",
    "sg:postcode":"9420",
    "sg:province":"Oost-Vlaanderen",
    "sg:tags":[
        "physiotherapist"
    ],
    "wof:name":"Bogaert Patrick",
    "wof:placetype":"venue"
},
  "geometry": {"coordinates":[3.9775409698,50.9343299866],"type":"Point"}
}