{
  "type": "Feature",
  "properties": {
    "iso:country":"BE",
    "sg:address":"Beukenlaan 13",
    "sg:city":"Kaprijke (lembeke)",
    "sg:classifiers":[
        {
            "category":"Professional",
            "subcategory":"Management & Consulting",
            "type":"Services"
        }
    ],
    "sg:phone":"+32 9 378 01 97",
    "sg:postcode":"9971",
    "sg:province":"Oost-Vlaanderen",
    "sg:tags":[
        "consultant"
    ],
    "wof:name":"Struyf Bedrijfsadvies",
    "wof:placetype":"venue"
},
  "geometry": {"coordinates":[3.6287689209,51.1847114563],"type":"Point"}
}