{
  "type": "Feature",
  "properties": {
    "iso:country":"BE",
    "sg:address":"Rue De La Longue Haie 23",
    "sg:city":"Bruxelles",
    "sg:classifiers":[
        {
            "category":"Cafe",
            "type":"Food & Drink"
        }
    ],
    "sg:phone":"+32 2 646 09 07",
    "sg:postcode":"1000",
    "sg:province":"Bruxelles-Capitale",
    "sg:tags":[
        "snack-bars"
    ],
    "wof:name":"Ile Au Tr\u00e9sor (l')",
    "wof:placetype":"venue"
},
  "geometry": {"coordinates":[4.3614139557,50.8308486938],"type":"Point"}
}