{
  "type": "Feature",
  "properties": {
    "iso:country":"BE",
    "sg:address":"Grand'place 51 Box 4",
    "sg:city":"Nivelles",
    "sg:classifiers":[
        {
            "category":"Professional",
            "subcategory":"Lawyer & Legal Services",
            "type":"Services"
        }
    ],
    "sg:phone":"+32 67 21 68 56",
    "sg:postcode":"1400",
    "sg:province":"Brabant Wallon",
    "wof:name":"Auquier Benjamin",
    "wof:placetype":"venue"
},
  "geometry": {"coordinates":[4.3232650757,50.596786499],"type":"Point"}
}