{
  "type": "Feature",
  "properties": {
    "iso:country":"BE",
    "sg:address":"Diesterstraat 162",
    "sg:city":"Tessenderlo",
    "sg:orig_category":"Voertuigen",
    "sg:phone":"+32 13 66 27 22",
    "sg:postcode":"3980",
    "sg:province":"Limburg",
    "wof:name":"Garage Exelmans",
    "wof:placetype":"venue"
},
  "geometry": {"coordinates":[5.0887341499,51.0570793152],"type":"Point"}
}