{
  "type": "Feature",
  "properties": {
    "addr:full":"Bissegemstraat 185 Wevelgem (gullegem) West-Vlaanderen 8560",
    "addr:housenumber":"185",
    "addr:postcode":"8560",
    "addr:street":"Bissegemstraat",
    "iso:country":"BE",
    "sg:address":"Bissegemstraat 185",
    "sg:city":"Wevelgem (gullegem)",
    "sg:classifiers":[
        {
            "category":"Parking",
            "subcategory":"Lot",
            "type":"Transportation"
        }
    ],
    "sg:phone":"+32 56 41 98 22",
    "sg:postcode":"8560",
    "sg:province":"West-Vlaanderen",
    "sg:tags":[
        "parking-places",
        "laying-out"
    ],
    "wof:name":"Hugelier Henri",
    "wof:placetype":"venue"
},
  "geometry": {"coordinates":[3.2114539146,50.8364982605],"type":"Point"}
}