{
  "type": "Feature",
  "properties": {
    "addr:full":"Mechelsestraat 49 Vilvoorde Vlaams-Brabant 1800",
    "addr:housenumber":"49",
    "addr:postcode":"1800",
    "addr:street":"Mechelsestraat",
    "iso:country":"BE",
    "sg:address":"Mechelsestraat 49",
    "sg:city":"Vilvoorde",
    "sg:orig_category":"Slagers",
    "sg:phone":"+32 2 251 18 40",
    "sg:postcode":"1800",
    "sg:province":"Vlaams-Brabant",
    "wof:name":"Ivan De Win",
    "wof:placetype":"venue"
},
  "geometry": {"coordinates":[4.4227590561,50.9309501648],"type":"Point"}
}