{
  "type": "Feature",
  "properties": {
    "addr:full":"Boulevard G\u00e9n\u00e9ral Wahis 16d Bruxelles (schaerbeek) Bruxelles-Capitale 1030",
    "addr:housenumber":"16d",
    "addr:postcode":"1030",
    "addr:street":"Boulevard Ge\u0301Ne\u0301Ral Wahis",
    "iso:country":"BE",
    "sg:address":"Boulevard G\u00e9n\u00e9ral Wahis 16d",
    "sg:city":"Bruxelles (schaerbeek)",
    "sg:classifiers":[
        {
            "category":"Transit Center",
            "subcategory":"Freight",
            "type":"Transportation"
        }
    ],
    "sg:phone":"+32 2 705 48 10",
    "sg:postcode":"1030",
    "sg:province":"Bruxelles-Capitale",
    "sg:tags":[
        "-",
        "tape",
        "adhesive"
    ],
    "wof:name":"Coenraets Nv-sa",
    "wof:placetype":"venue"
},
  "geometry": {"coordinates":[4.394411087,50.8601799011],"type":"Point"}
}