{
  "type": "Feature",
  "properties": {
    "iso:country":"BE",
    "sg:address":"Kouterstraat 53-2",
    "sg:city":"Zele",
    "sg:classifiers":[
        {
            "category":"Parking",
            "subcategory":"Bicycle",
            "type":"Transportation"
        }
    ],
    "sg:phone":"+32 52 44 61 92",
    "sg:postcode":"9240",
    "sg:province":"Oost-Vlaanderen",
    "sg:tags":[
        "chiropodist"
    ],
    "wof:name":"De Caluw\u00e9 I",
    "wof:placetype":"venue"
},
  "geometry": {"coordinates":[4.0310111046,51.0655784607],"type":"Point"}
}