{
  "type": "Feature",
  "properties": {
    "addr:full":"Landmolenstraat 13 Temse Oost-Vlaanderen 9140",
    "addr:housenumber":"13",
    "addr:postcode":"9140",
    "addr:street":"Landmolenstraat",
    "iso:country":"BE",
    "sg:address":"Landmolenstraat 13",
    "sg:city":"Temse",
    "sg:classifiers":[
        {
            "category":"Home & Garden",
            "subcategory":"Building Materials",
            "type":"Retail Goods"
        }
    ],
    "sg:phone":"+32 3 771 49 28",
    "sg:postcode":"9140",
    "sg:province":"Oost-Vlaanderen",
    "sg:tags":[
        "testing"
    ],
    "wof:name":"Gijko Bvba",
    "wof:placetype":"venue"
},
  "geometry": {"coordinates":[4.2421021461,51.1443328857],"type":"Point"}
}