{
  "type": "Feature",
  "properties": {
    "addr:full":"Burgemeester Bollenstr. 20 Hasselt Limburg 3500",
    "addr:housenumber":"20",
    "addr:postcode":"3500",
    "addr:street":"Burgemeester Bollenstr.",
    "iso:country":"BE",
    "sg:address":"Burgemeester Bollenstr. 20",
    "sg:city":"Hasselt",
    "sg:classifiers":[
        {
            "category":"Personal",
            "subcategory":"Beauty Salon",
            "type":"Services"
        }
    ],
    "sg:phone":"+32 11 22 26 42",
    "sg:postcode":"3500",
    "sg:province":"Limburg",
    "sg:tags":[
        "de",
        "coiffure"
    ],
    "wof:name":"Coiffure Jos\u00c9e",
    "wof:placetype":"venue"
},
  "geometry": {"coordinates":[5.3322668076,50.9317321777],"type":"Point"}
}