{
  "type": "Feature",
  "properties": {
    "iso:country":"BE",
    "sg:address":"Rue Marais \u00e0 Scailles 27",
    "sg:city":"Rebecq (rebecq-rognon)",
    "sg:classifiers":[
        {
            "category":"Arts & Performance",
            "subcategory":"Symphony",
            "type":"Entertainment"
        }
    ],
    "sg:phone":"+32 67 63 87 58",
    "sg:postcode":"1430",
    "sg:province":"Brabant Wallon",
    "sg:tags":[
        "orchestra"
    ],
    "wof:name":"Peter Welch Rhythm & Blues Band",
    "wof:placetype":"venue"
},
  "geometry": {"coordinates":[4.1307859421,50.6614532471],"type":"Point"}
}