{
  "type": "Feature",
  "properties": {
    "addr:full":"Heilig Hartlaan 26 Tessenderlo Limburg 3980",
    "addr:housenumber":"26",
    "addr:postcode":"3980",
    "addr:street":"Hartlaan",
    "iso:country":"BE",
    "sg:address":"Heilig Hartlaan 26",
    "sg:city":"Tessenderlo",
    "sg:classifiers":[
        {
            "category":"Military Area",
            "subcategory":"Bunker",
            "type":"Public Place"
        }
    ],
    "sg:phone":"+32 13 67 23 08",
    "sg:postcode":"3980",
    "sg:province":"Limburg",
    "sg:tags":[
        "equipment",
        "explosion",
        "proof"
    ],
    "wof:name":"Bartec Nv",
    "wof:placetype":"venue"
},
  "geometry": {"coordinates":[5.0924577713,51.0571212769],"type":"Point"}
}