{
  "type": "Feature",
  "properties": {
    "iso:country":"BE",
    "sg:address":"Route D'obourg 40",
    "sg:city":"Mons",
    "sg:orig_category":"Maisons de repos and r\u00e9sidences",
    "sg:phone":"+32 65 84 41 41",
    "sg:postcode":"7000",
    "sg:province":"Hainaut",
    "wof:name":"R\u00c9sidence Bon Pasteur",
    "wof:placetype":"venue"
},
  "geometry": {"coordinates":[3.9864530563,50.4582214355],"type":"Point"}
}