{
  "type": "Feature",
  "properties": {
    "iso:country":"BE",
    "sg:address":"Avenue Charles Woeste 296",
    "sg:city":"Jette",
    "sg:classifiers":[
        {
            "category":"Arena",
            "subcategory":"Sports Club",
            "type":"Entertainment"
        }
    ],
    "sg:phone":"+32 495 46 18 09",
    "sg:postcode":"1090",
    "sg:province":"Bruxelles-Capitale",
    "sg:tags":[
        "de"
    ],
    "wof:name":"Vc C.e.p.m. Moortebeek",
    "wof:placetype":"venue"
},
  "geometry": {"coordinates":[4.3355407715,50.8682403564],"type":"Point"}
}