{
  "type": "Feature",
  "properties": {
    "addr:full":"Boomsesteenweg 524 Antwerpen Antwerpen 2610",
    "addr:housenumber":"524",
    "addr:postcode":"2610",
    "addr:street":"Boomsesteenweg",
    "iso:country":"BE",
    "sg:address":"Boomsesteenweg 524",
    "sg:city":"Antwerpen",
    "sg:orig_category":"Produits pharmaceutiques Gr",
    "sg:phone":"+32 3 830 18 16",
    "sg:postcode":"2610",
    "sg:province":"Antwerpen",
    "wof:name":"Medata",
    "wof:placetype":"venue"
},
  "geometry": {"coordinates":[4.3898210526,51.182056427],"type":"Point"}
}