{
  "type": "Feature",
  "properties": {
    "iso:country":"BE",
    "sg:address":"Zeelaan 75",
    "sg:city":"Koksijde",
    "sg:classifiers":[
        {
            "category":"Restaurant",
            "type":"Food & Drink"
        }
    ],
    "sg:phone":"+32 58 51 56 03",
    "sg:postcode":"8670",
    "sg:province":"West-Vlaanderen",
    "wof:name":"Bistro Le Jardin",
    "wof:placetype":"venue"
},
  "geometry": {"coordinates":[2.6478259563,51.107208252],"type":"Point"}
}