{
  "type": "Feature",
  "properties": {
    "iso:country":"BE",
    "sg:address":"Proosdijstraat 78",
    "sg:city":"Oostkamp (ruddervoorde)",
    "sg:classifiers":[
        {
            "category":"Wholesale",
            "subcategory":"Machinery & Supplies",
            "type":"Manufacturing & Wholesale Goods"
        }
    ],
    "sg:phone":"+32 50 27 72 91",
    "sg:postcode":"8020",
    "sg:province":"West-Vlaanderen",
    "sg:tags":[
        "agricultural",
        "tractor"
    ],
    "wof:name":"Vanneste G & Zn Bvba",
    "wof:placetype":"venue"
},
  "geometry": {"coordinates":[3.2704930305,51.1078224182],"type":"Point"}
}