{
  "type": "Feature",
  "properties": {
    "addr:full":"Graaf Van Vlaanderenstr. 45 Sint-jans-molenbeek/molenbeek-saint-jean Bruxelles-Capitale 1080",
    "addr:housenumber":"45",
    "addr:postcode":"1080",
    "addr:street":"Graaf Van Vlaanderenstr.",
    "iso:country":"BE",
    "sg:address":"Graaf Van Vlaanderenstr. 45",
    "sg:city":"Sint-jans-molenbeek/molenbeek-saint-jean",
    "sg:orig_category":"HERSTELLING ELEKTRISCHE HUISHOUDAPPARATEN Huishoudapparaten, televisies and radio's IJzerwaren, bouw",
    "sg:phone":"+32 2 411 38 82",
    "sg:postcode":"1080",
    "sg:province":"Bruxelles-Capitale",
    "wof:name":"L'auxiliaire Du Chauffage",
    "wof:placetype":"venue"
},
  "geometry": {"coordinates":[4.3394360542,50.8556785583],"type":"Point"}
}