{
  "type": "Feature",
  "properties": {
    "addr:full":"Sluisstraat 65ba Knokke-heist West-Vlaanderen 8300",
    "addr:housenumber":"65ba",
    "addr:postcode":"8300",
    "addr:street":"Sluisstraat",
    "iso:country":"BE",
    "sg:address":"Sluisstraat 65ba",
    "sg:city":"Knokke-heist",
    "sg:orig_category":"Rev\u00eatements pour sols and murs. Peinture",
    "sg:phone":"+32 50 61 58 21",
    "sg:postcode":"8300",
    "sg:province":"West-Vlaanderen",
    "wof:name":"L. Callant",
    "wof:placetype":"venue"
},
  "geometry": {"coordinates":[3.287694931,51.3467254639],"type":"Point"}
}