{
  "type": "Feature",
  "properties": {
    "addr:full":"Bookmolenstraat 2 Zele Oost-Vlaanderen 9240",
    "addr:housenumber":"2",
    "addr:postcode":"9240",
    "addr:street":"Bookmolenstraat",
    "iso:country":"BE",
    "sg:address":"Bookmolenstraat 2",
    "sg:city":"Zele",
    "sg:orig_category":"Enseignement maternel and primaire",
    "sg:phone":"+32 52 44 52 23",
    "sg:postcode":"9240",
    "sg:province":"Oost-Vlaanderen",
    "wof:name":"Gemeentelijke Basisschool",
    "wof:placetype":"venue"
},
  "geometry": {"coordinates":[4.0411820412,51.0693817139],"type":"Point"}
}