{
  "type": "Feature",
  "properties": {
    "iso:country":"BE",
    "sg:address":"Blijveldstraat 17",
    "sg:city":"Hoegaarden",
    "sg:orig_category":"Non-Classified Establishments",
    "sg:phone":"+32 16 76 80 10",
    "sg:postcode":"3320",
    "sg:province":"Vlaams-Brabant",
    "wof:name":"Astrio's Nv",
    "wof:placetype":"venue"
},
  "geometry": {"coordinates":[4.8881611824,50.7744941711],"type":"Point"}
}