{
  "type": "Feature",
  "properties": {
    "iso:country":"BE",
    "sg:address":"Hammestraat 36",
    "sg:city":"Aalst",
    "sg:classifiers":[
        {
            "category":"Building & Trades",
            "subcategory":"Construction",
            "type":"Services"
        }
    ],
    "sg:phone":"+32 53 77 81 01",
    "sg:postcode":"9300",
    "sg:province":"Oost-Vlaanderen",
    "sg:tags":[
        "installation",
        "-",
        "central",
        "heating"
    ],
    "wof:name":"Gits Bvba",
    "wof:placetype":"venue"
},
  "geometry": {"coordinates":[4.0480751991,50.962020874],"type":"Point"}
}