{
  "type": "Feature",
  "properties": {
    "addr:full":"Wolvenstraat 31 Sint-katelijne-waver Antwerpen 2861",
    "addr:housenumber":"31",
    "addr:postcode":"2861",
    "addr:street":"Wolvenstraat",
    "iso:country":"BE",
    "sg:address":"Wolvenstraat 31",
    "sg:city":"Sint-katelijne-waver",
    "sg:orig_category":"Groententeelt",
    "sg:phone":"+32 15 31 42 47",
    "sg:postcode":"2861",
    "sg:province":"Antwerpen",
    "wof:name":"Julia Verschueren",
    "wof:placetype":"venue"
},
  "geometry": {"coordinates":[4.5579400063,51.0584602356],"type":"Point"}
}