{
  "type": "Feature",
  "properties": {
    "addr:full":"Kerkstraat 77 Blankenberge West-Vlaanderen 8370",
    "addr:housenumber":"77",
    "addr:postcode":"8370",
    "addr:street":"Kerkstraat",
    "iso:country":"BE",
    "sg:address":"Kerkstraat 77",
    "sg:city":"Blankenberge",
    "sg:orig_category":"Bagage and lederwaren",
    "sg:phone":"+32 50 42 74 51",
    "sg:postcode":"8370",
    "sg:province":"West-Vlaanderen",
    "wof:name":"Huis Vaudeville",
    "wof:placetype":"venue"
},
  "geometry": {"coordinates":[3.130022049,51.3142585754],"type":"Point"}
}