{
  "type": "Feature",
  "properties": {
    "iso:country":"BE",
    "sg:address":"All\u00c9es De Provence 65",
    "sg:city":"Evere/evere",
    "sg:orig_category":"M\u00e9decins and sp\u00e9cialistes",
    "sg:phone":"+32 2 215 69 89",
    "sg:postcode":"1140",
    "sg:province":"Bruxelles-Capitale",
    "wof:name":"Philippe Burton",
    "wof:placetype":"venue"
},
  "geometry": {"coordinates":[4.4046387672,50.8702964783],"type":"Point"}
}