{
  "type": "Feature",
  "properties": {
    "addr:full":"Mahoux 7 Houyet Namur 5560",
    "addr:housenumber":"7",
    "addr:postcode":"5560",
    "addr:street":"Mahoux",
    "iso:country":"BE",
    "sg:address":"Mahoux 7",
    "sg:city":"Houyet",
    "sg:orig_category":"Rundveehouders",
    "sg:phone":"+32 82 74 40 53",
    "sg:postcode":"5560",
    "sg:province":"Namur",
    "wof:name":"Claudine Marchal",
    "wof:placetype":"venue"
},
  "geometry": {"coordinates":[4.9260010719,50.1683883667],"type":"Point"}
}