{
  "type": "Feature",
  "properties": {
    "addr:full":"Ambachtstraat 11 Houthalen-helchteren Limburg 3530",
    "addr:housenumber":"11",
    "addr:postcode":"3530",
    "addr:street":"Ambachtstraat",
    "iso:country":"BE",
    "sg:address":"Ambachtstraat 11",
    "sg:city":"Houthalen-helchteren",
    "sg:orig_category":"Artsen and specialisten",
    "sg:phone":"+32 11 52 18 12",
    "sg:postcode":"3530",
    "sg:province":"Limburg",
    "wof:name":"A. Nouwen",
    "wof:placetype":"venue"
},
  "geometry": {"coordinates":[5.3719201088,51.0310020447],"type":"Point"}
}