{
  "type": "Feature",
  "properties": {
    "iso:country":"BE",
    "sg:address":"Centrum Zuid 2053",
    "sg:city":"Houthalen-helchteren (houthalen)",
    "sg:classifiers":[
        {
            "category":"Building & Trades",
            "subcategory":"Pest Control",
            "type":"Services"
        }
    ],
    "sg:phone":"+32 11 60 29 78",
    "sg:postcode":"3530",
    "sg:province":"Limburg",
    "sg:tags":[
        "disinfectant",
        "insecticide"
    ],
    "wof:name":"Roam Chemie Huwa-san Nv",
    "wof:placetype":"venue"
},
  "geometry": {"coordinates":[5.3647789955,51.0148925781],"type":"Point"}
}