{
  "type": "Feature",
  "properties": {
    "iso:country":"BE",
    "sg:address":"Rue Adolphe Marbotin 114",
    "sg:city":"Schaarbeek/schaerbeek",
    "sg:orig_category":"Agences d'exp\u00e9dition",
    "sg:phone":"+32 2 215 25 19",
    "sg:postcode":"1030",
    "sg:province":"Bruxelles-Capitale",
    "wof:name":"Spazio Events",
    "wof:placetype":"venue"
},
  "geometry": {"coordinates":[4.3945069313,50.8706130981],"type":"Point"}
}