{
  "type": "Feature",
  "properties": {
    "addr:full":"Rijmenamsesteenweg 23 Mechelen Antwerpen 2812",
    "addr:housenumber":"23",
    "addr:postcode":"2812",
    "addr:street":"Rijmenamsesteenweg",
    "iso:country":"BE",
    "sg:address":"Rijmenamsesteenweg 23",
    "sg:city":"Mechelen",
    "sg:orig_category":"Eleveurs de bovins",
    "sg:phone":"+32 15 51 20 94",
    "sg:postcode":"2812",
    "sg:province":"Antwerpen",
    "wof:name":"Jan Verschoren",
    "wof:placetype":"venue"
},
  "geometry": {"coordinates":[4.5150761604,51.0108947754],"type":"Point"}
}