{
  "type": "Feature",
  "properties": {
    "addr:full":"Steenweg Linde 17 Peer Limburg 3990",
    "addr:housenumber":"17",
    "addr:postcode":"3990",
    "addr:street":"Steenweg Linde",
    "iso:country":"BE",
    "sg:address":"Steenweg Linde 17",
    "sg:city":"Peer",
    "sg:orig_category":"Eleveurs and marchands de porcs",
    "sg:phone":"+32 11 79 14 63",
    "sg:postcode":"3990",
    "sg:province":"Limburg",
    "wof:name":"Elisa Winters",
    "wof:placetype":"venue"
},
  "geometry": {"coordinates":[5.4501228333,51.1066741943],"type":"Point"}
}