{
  "type": "Feature",
  "properties": {
    "addr:full":"Ijsbroekstraat 15 Aalst (groot) Oost-Vlaanderen 9308",
    "addr:housenumber":"15",
    "addr:postcode":"9308",
    "addr:street":"Ijsbroekstraat;Groot Oost-Vlaanderen",
    "iso:country":"BE",
    "sg:address":"Ijsbroekstraat 15",
    "sg:city":"Aalst (groot)",
    "sg:orig_category":"Kapsalons",
    "sg:phone":"+32 53 21 32 00",
    "sg:postcode":"9308",
    "sg:province":"Oost-Vlaanderen",
    "wof:name":"Coiffure Daisy",
    "wof:placetype":"venue"
},
  "geometry": {"coordinates":[4.0466709137,50.9832420349],"type":"Point"}
}