{
  "type": "Feature",
  "properties": {
    "iso:country":"BE",
    "sg:address":"Rue Jean Jaures 20",
    "sg:city":"Grace-hollogne",
    "sg:orig_category":"Mat\u00e9riel de T\u00e9l\u00e9communication. Electrom\u00e9nager, t\u00e9l\u00e9visions and radios. R\u00e9parations d'appareils \u00e9lect",
    "sg:phone":"+32 4 263 55 99",
    "sg:postcode":"4460",
    "sg:province":"Li\u00e8ge",
    "wof:name":"Electro Perou",
    "wof:placetype":"venue"
},
  "geometry": {"coordinates":[5.5048818588,50.6441268921],"type":"Point"}
}