{
  "type": "Feature",
  "properties": {
    "iso:country":"BE",
    "sg:address":"Kloosterstraat 86",
    "sg:city":"Lommel",
    "sg:classifiers":[
        {
            "category":"Bakery",
            "type":"Food & Drink"
        }
    ],
    "sg:phone":"+32 11 54 15 61",
    "sg:postcode":"3920",
    "sg:province":"Limburg",
    "sg:tags":[
        "confectioner",
        "baker"
    ],
    "wof:name":"Geudens",
    "wof:placetype":"venue"
},
  "geometry": {"coordinates":[5.3178281784,51.2304344177],"type":"Point"}
}