{
  "type": "Feature",
  "properties": {
    "addr:full":"Turnhoutsebaan 5b212 Wijnegem Antwerpen 2110",
    "addr:housenumber":"5b212",
    "addr:postcode":"2110",
    "addr:street":"Turnhoutsebaan",
    "iso:country":"BE",
    "sg:address":"Turnhoutsebaan 5b212",
    "sg:city":"Wijnegem",
    "sg:classifiers":[
        {
            "category":"Shopping",
            "subcategory":"Clothing, Apparel, & Fashions",
            "type":"Retail Goods"
        }
    ],
    "sg:phone":"+32 3 353 86 60",
    "sg:postcode":"2110",
    "sg:province":"Antwerpen",
    "sg:tags":[
        "v\u00eatements",
        "pour",
        "dame"
    ],
    "wof:name":"We Women",
    "wof:placetype":"venue"
},
  "geometry": {"coordinates":[4.5043401718,51.2240219116],"type":"Point"}
}