{
  "type": "Feature",
  "properties": {
    "iso:country":"BE",
    "sg:address":"Rue Guimard 9",
    "sg:city":"Bruxelles (etterbeek)",
    "sg:classifiers":[
        {
            "category":"Utilities",
            "subcategory":"Refuse",
            "type":"Services"
        }
    ],
    "sg:phone":"+32 2 502 87 08",
    "sg:postcode":"1040",
    "sg:province":"Bruxelles-Capitale",
    "sg:tags":[
        "catering"
    ],
    "wof:name":"Horeservi Catering Nv",
    "wof:placetype":"venue"
},
  "geometry": {"coordinates":[4.3695559502,50.8437080383],"type":"Point"}
}