{
  "type": "Feature",
  "properties": {
    "addr:full":"Avenue Docteur Terwagne 46 La Hulpe Brabant Wallon 1310",
    "addr:housenumber":"46",
    "addr:postcode":"1310",
    "addr:street":"Avenue Docteur Terwagne",
    "iso:country":"BE",
    "sg:address":"Avenue Docteur Terwagne 46",
    "sg:city":"La Hulpe",
    "sg:orig_category":"Sportclubs",
    "sg:phone":"+32 2 653 95 71",
    "sg:postcode":"1310",
    "sg:province":"Brabant Wallon",
    "wof:name":"U.l.b Sports Section Plong\u00c9e",
    "wof:placetype":"venue"
},
  "geometry": {"coordinates":[4.4766578674,50.7314414978],"type":"Point"}
}