{
  "type": "Feature",
  "properties": {
    "addr:full":"Avenue Dieudonn\u00e9-lambrecht 9 Li\u00e8ge 1 Li\u00e8ge 4000",
    "addr:housenumber":"9;1",
    "addr:postcode":"4000",
    "addr:street":"Avenue Dieudonne\u0301-Lambrecht",
    "iso:country":"BE",
    "sg:address":"Avenue Dieudonn\u00e9-lambrecht 9",
    "sg:city":"Li\u00e8ge 1",
    "sg:classifiers":[
        {
            "category":"Health Services",
            "subcategory":"Doctor",
            "type":"Services"
        }
    ],
    "sg:phone":"+32 4 227 09 71",
    "sg:postcode":"4000",
    "sg:province":"Li\u00e8ge",
    "sg:tags":[
        "medicinephysicians",
        "surgeon"
    ],
    "wof:name":"D'or Ghislaine",
    "wof:placetype":"venue"
},
  "geometry": {"coordinates":[5.5938529968,50.6632614136],"type":"Point"}
}