{
  "type": "Feature",
  "properties": {
    "addr:full":"Sint-pietersnieuwstraat 226 Gent Oost-Vlaanderen 9000",
    "addr:housenumber":"226",
    "addr:postcode":"9000",
    "addr:street":"Sint-Pietersnieuwstraat;Oost-Vlaanderen",
    "iso:country":"BE",
    "sg:address":"Sint-pietersnieuwstraat 226",
    "sg:city":"Gent",
    "sg:classifiers":[
        {
            "category":"Bars & Pubs",
            "type":"Food & Drink"
        }
    ],
    "sg:phone":"+32 9 224 41 20",
    "sg:postcode":"9000",
    "sg:province":"Oost-Vlaanderen",
    "wof:name":"De Sloef",
    "wof:placetype":"venue"
},
  "geometry": {"coordinates":[3.7259149551,51.0437049866],"type":"Point"}
}