{
  "type": "Feature",
  "properties": {
    "addr:full":"Chauss\u00c9e Du Pont Rouge 57 Komen-waasten/comines-warneton Hainaut 7784",
    "addr:housenumber":"57;7784",
    "addr:street":"Chausse\u0301E Du Pont Rouge",
    "iso:country":"BE",
    "sg:address":"Chauss\u00c9e Du Pont Rouge 57",
    "sg:city":"Komen-waasten/comines-warneton",
    "sg:orig_category":"Mat\u00e9riaux de construction Gr",
    "sg:phone":"+32 56 58 88 10",
    "sg:postcode":"7784",
    "sg:province":"Hainaut",
    "wof:name":"Briqueteries De Warneton",
    "wof:placetype":"venue"
},
  "geometry": {"coordinates":[2.9322679043,50.7382240295],"type":"Point"}
}