{
  "type": "Feature",
  "properties": {
    "iso:country":"BE",
    "sg:address":"Avenue Paola 33",
    "sg:city":"Rixensart",
    "sg:classifiers":[
        {
            "category":"Real Estate",
            "subcategory":"Real Estate Services",
            "type":"Services"
        }
    ],
    "sg:phone":"+32 2 653 23 69",
    "sg:postcode":"1330",
    "sg:province":"Brabant Wallon",
    "wof:name":"Bradem Consult Sc",
    "wof:placetype":"venue"
},
  "geometry": {"coordinates":[4.5398979187,50.7066001892],"type":"Point"}
}