{
  "type": "Feature",
  "properties": {
    "addr:full":"Grote Baan 115 Herdersem Oost-Vlaanderen 9310",
    "addr:housenumber":"115",
    "addr:postcode":"9310",
    "addr:street":"Grote Baan;Oost-Vlaanderen",
    "iso:country":"BE",
    "sg:address":"Grote Baan 115",
    "sg:city":"Herdersem",
    "sg:classifiers":[
        {
            "category":"Food & Beverages",
            "subcategory":"Dairy",
            "type":"Retail Goods"
        }
    ],
    "sg:phone":"+32 53 21 45 48",
    "sg:postcode":"9310",
    "sg:province":"Oost-Vlaanderen",
    "sg:tags":[
        "product",
        "related"
    ],
    "wof:name":"Lambrecht Gebroeders Bvba",
    "wof:placetype":"venue"
},
  "geometry": {"coordinates":[4.0631809235,50.9664611816],"type":"Point"}
}