{
  "type": "Feature",
  "properties": {
    "iso:country":"BE",
    "sg:address":"Balegemstraat 20",
    "sg:city":"Oosterzele",
    "sg:classifiers":[
        {
            "category":"Insurance",
            "subcategory":"Insurance Agent",
            "type":"Services"
        }
    ],
    "sg:phone":"+32 9 362 57 50",
    "sg:postcode":"9860",
    "sg:province":"Oost-Vlaanderen",
    "sg:tags":[
        "verzekeringsmakelaars",
        "expert"
    ],
    "wof:name":"Daeselaire",
    "wof:placetype":"venue"
},
  "geometry": {"coordinates":[3.7924339771,50.9227142334],"type":"Point"}
}