{
  "type": "Feature",
  "properties": {
    "iso:country":"BE",
    "sg:address":"Kortrijksepoortstraat 180",
    "sg:city":"Gent",
    "sg:classifiers":[
        {
            "category":"Utilities",
            "subcategory":"Telephone",
            "type":"Services"
        }
    ],
    "sg:phone":"+32 9 269 08 60",
    "sg:postcode":"9000",
    "sg:province":"Oost-Vlaanderen",
    "sg:tags":[
        "-",
        "internet"
    ],
    "wof:name":"Globetrotter (the)",
    "wof:placetype":"venue"
},
  "geometry": {"coordinates":[3.7218339443,51.0447540283],"type":"Point"}
}