{
  "type": "Feature",
  "properties": {
    "addr:full":"Rue Saint-eloi 19 Li\u00c8ge Li\u00e8ge 4020",
    "addr:housenumber":"19",
    "addr:postcode":"4020",
    "addr:street":"Rue Saint-Eloi",
    "iso:country":"BE",
    "sg:address":"Rue Saint-eloi 19",
    "sg:city":"Li\u00c8ge",
    "sg:orig_category":"Artsen and specialisten",
    "sg:phone":"+32 4 342 52 39",
    "sg:postcode":"4020",
    "sg:province":"Li\u00e8ge",
    "wof:name":"Roland Haquet",
    "wof:placetype":"venue"
},
  "geometry": {"coordinates":[5.5801491737,50.6414070129],"type":"Point"}
}