{
  "type": "Feature",
  "properties": {
    "iso:country":"BE",
    "sg:address":"Rue G\u00c9n\u00c9ral Leman 28",
    "sg:city":"Charleroi",
    "sg:orig_category":"M\u00e9decins and sp\u00e9cialistes",
    "sg:phone":"+32 71 45 38 54",
    "sg:postcode":"6044",
    "sg:province":"Hainaut",
    "wof:name":"L. Vauthier",
    "wof:placetype":"venue"
},
  "geometry": {"coordinates":[4.3907608986,50.4453010559],"type":"Point"}
}