{
  "type": "Feature",
  "properties": {
    "iso:country":"BE",
    "sg:address":"Alcyonstraat 28",
    "sg:city":"Sint-agatha-berchem/berchem-sainte-agathe",
    "sg:orig_category":"Artsen and specialisten",
    "sg:phone":"+32 2 465 66 35",
    "sg:postcode":"1082",
    "sg:province":"Bruxelles-Capitale",
    "wof:name":"Consultatiebur.jonge Kind",
    "wof:placetype":"venue"
},
  "geometry": {"coordinates":[4.2928161621,50.867099762],"type":"Point"}
}