{
  "type": "Feature",
  "properties": {
    "addr:full":"Vijversweg 7 Rijkevorsel Antwerpen 2310",
    "addr:housenumber":"7",
    "addr:postcode":"2310",
    "addr:street":"Vijversweg",
    "iso:country":"BE",
    "sg:address":"Vijversweg 7",
    "sg:city":"Rijkevorsel",
    "sg:classifiers":[
        {
            "category":"Manufacturing",
            "subcategory":"Metals",
            "type":"Manufacturing & Wholesale Goods"
        }
    ],
    "sg:phone":"+32 3 314 79 18",
    "sg:postcode":"2310",
    "sg:province":"Antwerpen",
    "sg:tags":[
        "working"
    ],
    "wof:name":"Stubbe P",
    "wof:placetype":"venue"
},
  "geometry": {"coordinates":[4.7862038612,51.3428649902],"type":"Point"}
}