{
  "type": "Feature",
  "properties": {
    "iso:country":"BE",
    "sg:address":"Motstraat 72",
    "sg:city":"Mechelen",
    "sg:classifiers":[
        {
            "category":"Home & Garden",
            "subcategory":"Carpets & Floor Coverings",
            "type":"Retail Goods"
        }
    ],
    "sg:phone":"+32 15 41 18 29",
    "sg:postcode":"2800",
    "sg:province":"Antwerpen",
    "sg:tags":[
        "industrial",
        "-"
    ],
    "wof:name":"Solastra Bvba",
    "wof:placetype":"venue"
},
  "geometry": {"coordinates":[4.4880218506,51.0147018433],"type":"Point"}
}