{
  "type": "Feature",
  "properties": {
    "addr:full":"La-nawe 79 Libin Luxembourg 6890",
    "addr:housenumber":"79",
    "addr:postcode":"6890",
    "addr:street":"La-Nawe",
    "iso:country":"BE",
    "sg:address":"La-nawe 79",
    "sg:city":"Libin",
    "sg:orig_category":"D\u00e9m\u00e9nagements",
    "sg:phone":"+32 61 65 61 02",
    "sg:postcode":"6890",
    "sg:province":"Luxembourg",
    "wof:name":"Transport Golinvaux J.l.",
    "wof:placetype":"venue"
},
  "geometry": {"coordinates":[5.166041851,50.0097465515],"type":"Point"}
}