{
  "type": "Feature",
  "properties": {
    "addr:full":"Wallenstraat 36 Roeselare West-Vlaanderen 8800",
    "addr:housenumber":"36",
    "addr:postcode":"8800",
    "addr:street":"Wallenstraat",
    "iso:country":"BE",
    "sg:address":"Wallenstraat 36",
    "sg:city":"Roeselare",
    "sg:orig_category":"Artiesten and kunstenaars",
    "sg:phone":"+32 51 20 17 56",
    "sg:postcode":"8800",
    "sg:province":"West-Vlaanderen",
    "wof:name":"Dejonckheere",
    "wof:placetype":"venue"
},
  "geometry": {"coordinates":[3.1209599972,50.9449958801],"type":"Point"}
}