{
  "type": "Feature",
  "properties": {
    "iso:country":"BE",
    "sg:address":"Brakelstraat 109",
    "sg:city":"Zottegem (sint-maria-oudenhove)",
    "sg:classifiers":[
        {
            "category":"Health Services",
            "subcategory":"Health Practitioner",
            "type":"Services"
        }
    ],
    "sg:phone":"+32 55 42 82 72",
    "sg:postcode":"9620",
    "sg:province":"Oost-Vlaanderen",
    "sg:tags":[
        "alternative",
        "therapy",
        "treatment"
    ],
    "wof:name":"Medi-fit Bvba",
    "wof:placetype":"venue"
},
  "geometry": {"coordinates":[3.8112111092,50.871181488],"type":"Point"}
}