{
  "type": "Feature",
  "properties": {
    "iso:country":"BE",
    "sg:address":"Rue Du Ch\u00c2teau D\u00b4eau 50",
    "sg:city":"Estaimpuis ( Saint-l\u00c9ger )",
    "sg:orig_category":"Speciaalzaken",
    "sg:phone":"+32 56 48 47 41",
    "sg:postcode":"7730",
    "sg:province":"Hainaut",
    "wof:name":"Chemin\u00c9es Et Style",
    "wof:placetype":"venue"
},
  "geometry": {"coordinates":[3.316945076,50.7120475769],"type":"Point"}
}