{
  "type": "Feature",
  "properties": {
    "iso:country":"BE",
    "sg:address":"Rubensstraat 54",
    "sg:city":"Mechelen (muizen)",
    "sg:classifiers":[
        {
            "category":"Personal",
            "subcategory":"Beauty Salon",
            "type":"Services"
        }
    ],
    "sg:phone":"+32 15 41 44 23",
    "sg:postcode":"2812",
    "sg:province":"Antwerpen",
    "sg:tags":[
        "lady",
        "-",
        "hairdressing"
    ],
    "wof:name":"Gilbert",
    "wof:placetype":"venue"
},
  "geometry": {"coordinates":[4.5170722008,51.0077934265],"type":"Point"}
}