{
  "type": "Feature",
  "properties": {
    "iso:country":"BE",
    "sg:address":"Rue De Marchienne 3",
    "sg:city":"Charleroi",
    "sg:orig_category":"Parfumeries",
    "sg:phone":"+32 71 32 15 11",
    "sg:postcode":"6000",
    "sg:province":"Hainaut",
    "wof:name":"Parfumerie Trifaux",
    "wof:placetype":"venue"
},
  "geometry": {"coordinates":[4.4407629967,50.407951355],"type":"Point"}
}