{
  "type": "Feature",
  "properties": {
    "addr:full":"Rue De La For\u00cat 14 Rendeux Luxembourg 6987",
    "addr:housenumber":"14",
    "addr:postcode":"6987",
    "addr:street":"Rue De La Fore\u0302T",
    "iso:country":"BE",
    "sg:address":"Rue De La For\u00cat 14",
    "sg:city":"Rendeux",
    "sg:orig_category":"Rundveehouders",
    "sg:phone":"+32 84 47 73 08",
    "sg:postcode":"6987",
    "sg:province":"Luxembourg",
    "wof:name":"Roger Collin",
    "wof:placetype":"venue"
},
  "geometry": {"coordinates":[5.5489640236,50.2143859863],"type":"Point"}
}