{
  "type": "Feature",
  "properties": {
    "addr:full":"Rue Des R\u00e9sistants 2 Mouscron Hainaut 7700",
    "addr:housenumber":"2",
    "addr:postcode":"7700",
    "addr:street":"Rue Des Re\u0301Sistants",
    "iso:country":"BE",
    "sg:address":"Rue Des R\u00e9sistants 2",
    "sg:city":"Mouscron",
    "sg:classifiers":[
        {
            "category":"Bars & Pubs",
            "type":"Food & Drink"
        }
    ],
    "sg:phone":"+32 56 34 50 03",
    "sg:postcode":"7700",
    "sg:province":"Hainaut",
    "wof:name":"Batchu (le)",
    "wof:placetype":"venue"
},
  "geometry": {"coordinates":[3.2136769295,50.7436103821],"type":"Point"}
}