{
  "type": "Feature",
  "properties": {
    "iso:country":"BE",
    "sg:address":"Werkplaatsen 43",
    "sg:city":"Lommel",
    "sg:orig_category":"Charpentes and couvertures",
    "sg:phone":"+32 11 54 54 99",
    "sg:postcode":"3920",
    "sg:province":"Limburg",
    "wof:name":"Jozef Cornelis",
    "wof:placetype":"venue"
},
  "geometry": {"coordinates":[5.2580718994,51.2282485962],"type":"Point"}
}