{
  "type": "Feature",
  "properties": {
    "iso:country":"BE",
    "sg:address":"Chauss\u00c9e De Binche 50",
    "sg:city":"Mons",
    "sg:orig_category":"Quincailleries",
    "sg:phone":"+32 65 84 45 57",
    "sg:postcode":"7000",
    "sg:province":"Hainaut",
    "wof:name":"Prestige Bain",
    "wof:placetype":"venue"
},
  "geometry": {"coordinates":[3.9824941158,50.4512825012],"type":"Point"}
}