{
  "type": "Feature",
  "properties": {
    "iso:country":"BE",
    "sg:address":"Rue Emmanuel Lutte 5",
    "sg:city":"Genappe",
    "sg:classifiers":[
        {
            "category":"Professional",
            "subcategory":"Testing Lab",
            "type":"Services"
        }
    ],
    "sg:phone":"+32 67 77 20 20",
    "sg:postcode":"1470",
    "sg:province":"Brabant Wallon",
    "sg:tags":[
        "chemist"
    ],
    "wof:name":"Depouhon A",
    "wof:placetype":"venue"
},
  "geometry": {"coordinates":[4.4514780045,50.6110877991],"type":"Point"}
}