{
  "type": "Feature",
  "properties": {
    "iso:country":"BE",
    "sg:address":"Mechelbaan 771",
    "sg:city":"Putte",
    "sg:orig_category":"Loodgieterij, verwarming and sanitaire installaties",
    "sg:phone":"+32 15 75 55 90",
    "sg:postcode":"2580",
    "sg:province":"Antwerpen",
    "wof:name":"Frans Portael",
    "wof:placetype":"venue"
},
  "geometry": {"coordinates":[4.5784840584,51.0381202698],"type":"Point"}
}