{
  "type": "Feature",
  "properties": {
    "addr:full":"Korte Gasthuisstraat 33 Antwerpen Antwerpen 2000",
    "addr:housenumber":"33",
    "addr:postcode":"2000",
    "addr:street":"Korte Gasthuisstraat",
    "iso:country":"BE",
    "sg:address":"Korte Gasthuisstraat 33",
    "sg:city":"Antwerpen",
    "sg:orig_category":"V\u00eatements. Accessoires vestimentaires. Sous-v\u00eatements and lingerie",
    "sg:phone":"+32 3 201 16 70",
    "sg:postcode":"2000",
    "sg:province":"Antwerpen",
    "wof:name":"Kousencenter",
    "wof:placetype":"venue"
},
  "geometry": {"coordinates":[4.4046320915,51.216545105],"type":"Point"}
}