{
  "type": "Feature",
  "properties": {
    "iso:country":"BE",
    "sg:address":"Sint-jacobstraat 47",
    "sg:city":"Dendermonde",
    "sg:orig_category":"Sportclubs Sportterreinen and installaties behalve sportcentra",
    "sg:phone":"+32 52 22 44 36",
    "sg:postcode":"9200",
    "sg:province":"Oost-Vlaanderen",
    "wof:name":"K.a.v. Dendermonde",
    "wof:placetype":"venue"
},
  "geometry": {"coordinates":[4.104927063,51.0302238464],"type":"Point"}
}