{
  "type": "Feature",
  "properties": {
    "addr:full":"Tige Del'vau 14 Fernelmont (forville) Namur 5380",
    "addr:housenumber":"14",
    "addr:postcode":"5380",
    "iso:country":"BE",
    "sg:address":"Tige Del'vau 14",
    "sg:city":"Fernelmont (forville)",
    "sg:classifiers":[
        {
            "category":"Food & Beverages",
            "subcategory":"Fruits & Vegetables",
            "type":"Retail Goods"
        }
    ],
    "sg:phone":"+32 81 83 52 34",
    "sg:postcode":"5380",
    "sg:province":"Namur",
    "sg:tags":[
        "-"
    ],
    "wof:name":"Creffier M",
    "wof:placetype":"venue"
},
  "geometry": {"coordinates":[5.0068640709,50.585773468],"type":"Point"}
}