{
  "type": "Feature",
  "properties": {
    "iso:country":"BE",
    "sg:address":"Moleneinde 16",
    "sg:city":"Evergem",
    "sg:orig_category":"Sportclubs",
    "sg:phone":"+32 9 357 32 28",
    "sg:postcode":"9940",
    "sg:province":"Oost-Vlaanderen",
    "wof:name":"De Eerste De Beste",
    "wof:placetype":"venue"
},
  "geometry": {"coordinates":[3.6733469963,51.1029891968],"type":"Point"}
}