{
  "type": "Feature",
  "properties": {
    "iso:country":"BE",
    "sg:address":"Filips Van De Elzaslaan 5",
    "sg:city":"Kortrijk",
    "sg:classifiers":[
        {
            "category":"Professional",
            "subcategory":"Art Services",
            "type":"Services"
        }
    ],
    "sg:phone":"+32 56 21 58 09",
    "sg:postcode":"8500",
    "sg:province":"West-Vlaanderen",
    "sg:tags":[
        "photographer"
    ],
    "wof:name":"Honore L",
    "wof:placetype":"venue"
},
  "geometry": {"coordinates":[3.2734971046,50.8218955994],"type":"Point"}
}