{
  "type": "Feature",
  "properties": {
    "iso:country":"BE",
    "sg:address":"Advocaat De Backerstraat 16",
    "sg:city":"Haaltert",
    "sg:orig_category":"Effectenmakelaars and vermogensbeheer Hypotheken and hypotheekbanken Verbruikerskredietinstellingen ",
    "sg:phone":"+32 54 34 34 64",
    "sg:postcode":"9450",
    "sg:province":"Oost-Vlaanderen",
    "wof:name":"Euro Consult",
    "wof:placetype":"venue"
},
  "geometry": {"coordinates":[4.0186128616,50.8728675842],"type":"Point"}
}