{
  "type": "Feature",
  "properties": {
    "addr:full":"Ten Bos 1 Aalst Oost-Vlaanderen 9320",
    "addr:housenumber":"1",
    "addr:postcode":"9320",
    "addr:street":"Ten Bos",
    "iso:country":"BE",
    "sg:address":"Ten Bos 1",
    "sg:city":"Aalst",
    "sg:orig_category":"Alimentation sp\u00e9cialis\u00e9e",
    "sg:phone":"+32 53 77 86 96",
    "sg:postcode":"9320",
    "sg:province":"Oost-Vlaanderen",
    "wof:name":"Linda Boel",
    "wof:placetype":"venue"
},
  "geometry": {"coordinates":[4.0852179527,50.9079551697],"type":"Point"}
}