{
  "type": "Feature",
  "properties": {
    "addr:full":"Alfred Van Campenhoutlaan 1 Meise Vlaams-Brabant 1860",
    "addr:housenumber":"1",
    "addr:postcode":"1860",
    "addr:street":"Alfred Van Campenhoutlaan",
    "iso:country":"BE",
    "sg:address":"Alfred Van Campenhoutlaan 1",
    "sg:city":"Meise",
    "sg:classifiers":[
        {
            "category":"Bakery",
            "type":"Food & Drink"
        }
    ],
    "sg:phone":"+32 2 269 88 88",
    "sg:postcode":"1860",
    "sg:province":"Vlaams-Brabant",
    "sg:tags":[
        "confectioner",
        "baker"
    ],
    "wof:name":"Chris",
    "wof:placetype":"venue"
},
  "geometry": {"coordinates":[4.3414101601,50.9585609436],"type":"Point"}
}