{
  "type": "Feature",
  "properties": {
    "addr:full":"Rue Vanderkindere 493 Ukkel/uccle Bruxelles-Capitale 1180",
    "addr:housenumber":"493",
    "addr:postcode":"1180",
    "addr:street":"Rue Vanderkindere;/",
    "iso:country":"BE",
    "sg:address":"Rue Vanderkindere 493",
    "sg:city":"Ukkel/uccle",
    "sg:orig_category":"Kansspelen",
    "sg:phone":"+32 2 345 42 69",
    "sg:postcode":"1180",
    "sg:province":"Bruxelles-Capitale",
    "wof:name":"Tierce Franco-belge",
    "wof:placetype":"venue"
},
  "geometry": {"coordinates":[4.3668351173,50.8144645691],"type":"Point"}
}