{
  "type": "Feature",
  "properties": {
    "addr:full":"Vogelenzang 4 Borsbeek Antwerpen 2150",
    "addr:housenumber":"4",
    "addr:postcode":"2150",
    "addr:street":"Vogelenzang",
    "iso:country":"BE",
    "sg:address":"Vogelenzang 4",
    "sg:city":"Borsbeek",
    "sg:classifiers":[
        {
            "category":"Wholesale",
            "subcategory":"Scrap",
            "type":"Manufacturing & Wholesale Goods"
        }
    ],
    "sg:phone":"+32 3 297 10 11",
    "sg:postcode":"2150",
    "sg:province":"Antwerpen",
    "sg:tags":[
        "metal"
    ],
    "wof:name":"A.b.a.d",
    "wof:placetype":"venue"
},
  "geometry": {"coordinates":[4.4959812164,51.1968002319],"type":"Point"}
}