{
  "type": "Feature",
  "properties": {
    "addr:full":"Fregatstraat 4 Oostende West-Vlaanderen 8400",
    "addr:housenumber":"4",
    "addr:postcode":"8400",
    "addr:street":"Fregatstraat",
    "iso:country":"BE",
    "sg:address":"Fregatstraat 4",
    "sg:city":"Oostende",
    "sg:classifiers":[
        {
            "category":"Food & Beverages",
            "subcategory":"Meat & Fish",
            "type":"Retail Goods"
        }
    ],
    "sg:phone":"+32 59 50 21 14",
    "sg:postcode":"8400",
    "sg:province":"West-Vlaanderen",
    "sg:tags":[
        "vi",
        "zeevruchten"
    ],
    "wof:name":"Ivan Fonteyne",
    "wof:placetype":"venue"
},
  "geometry": {"coordinates":[2.924806118,51.2263526917],"type":"Point"}
}