{
  "type": "Feature",
  "properties": {
    "iso:country":"BE",
    "sg:address":"Rue Sainte-marguerite 325",
    "sg:city":"Li\u00c8ge",
    "sg:orig_category":"Artsen and specialisten",
    "sg:phone":"+32 4 226 47 63",
    "sg:postcode":"4000",
    "sg:province":"Li\u00e8ge",
    "wof:name":"Jean-marie Yerna",
    "wof:placetype":"venue"
},
  "geometry": {"coordinates":[5.5521111488,50.6477050781],"type":"Point"}
}