{
  "type": "Feature",
  "properties": {
    "addr:full":"Rue De Laeken 24 Bruxelles Bruxelles-Capitale 1000",
    "addr:housenumber":"24",
    "addr:postcode":"1000",
    "addr:street":"Rue De Laeken",
    "iso:country":"BE",
    "sg:address":"Rue De Laeken 24",
    "sg:city":"Bruxelles",
    "sg:classifiers":[
        {
            "category":"Food & Beverages",
            "subcategory":"Groceries & Convenience Stores",
            "type":"Retail Goods"
        }
    ],
    "sg:phone":"+32 2 218 48 18",
    "sg:postcode":"1000",
    "sg:province":"Bruxelles-Capitale",
    "sg:tags":[
        "grocer"
    ],
    "wof:name":"Oasis (l')",
    "wof:placetype":"venue"
},
  "geometry": {"coordinates":[4.3506999016,50.8518257141],"type":"Point"}
}