{
  "type": "Feature",
  "properties": {
    "addr:full":"Offerandestraat 23 Antwerpen Antwerpen 2060",
    "addr:housenumber":"23",
    "addr:postcode":"2060",
    "addr:street":"Offerandestraat",
    "iso:country":"BE",
    "sg:address":"Offerandestraat 23",
    "sg:city":"Antwerpen",
    "sg:classifiers":[
        {
            "category":"Restaurant",
            "type":"Food & Drink"
        }
    ],
    "sg:phone":"+32 3 231 02 51",
    "sg:postcode":"2060",
    "sg:province":"Antwerpen",
    "wof:name":"\u00b4t Snoepke",
    "wof:placetype":"venue"
},
  "geometry": {"coordinates":[4.4247369766,51.2201728821],"type":"Point"}
}