{
  "type": "Feature",
  "properties": {
    "iso:country":"BE",
    "sg:address":"Van Campenhoutstraat 14",
    "sg:city":"Brussel/bruxelles",
    "sg:orig_category":"Artsen and specialisten",
    "sg:phone":"+32 2 732 64 16",
    "sg:postcode":"1000",
    "sg:province":"Bruxelles-Capitale",
    "wof:name":"Robert Glasroth",
    "wof:placetype":"venue"
},
  "geometry": {"coordinates":[4.3856430054,50.8476600647],"type":"Point"}
}