{
  "type": "Feature",
  "properties": {
    "iso:country":"BE",
    "sg:address":"Hooiestraat 21",
    "sg:city":"Wielsbeke",
    "sg:orig_category":"Eleveurs de bovins",
    "sg:phone":"+32 56 60 22 05",
    "sg:postcode":"8710",
    "sg:province":"West-Vlaanderen",
    "wof:name":"Carl Van Melle",
    "wof:placetype":"venue"
},
  "geometry": {"coordinates":[3.4125680923,50.9200553894],"type":"Point"}
}