{
  "type": "Feature",
  "properties": {
    "iso:country":"BE",
    "sg:address":"Chemin Du Ry 5",
    "sg:city":"Rebecq",
    "sg:orig_category":"Rundveehouders Varkenskwekers",
    "sg:phone":"+32 67 63 65 79",
    "sg:postcode":"1430",
    "sg:province":"Brabant Wallon",
    "wof:name":"Roger Cautaers",
    "wof:placetype":"venue"
},
  "geometry": {"coordinates":[4.1303219795,50.645740509],"type":"Point"}
}