{
  "type": "Feature",
  "properties": {
    "iso:country":"BE",
    "sg:address":"Kapellestraat 15a",
    "sg:city":"Laarne (kalken)",
    "sg:classifiers":[
        {
            "category":"Building & Trades",
            "subcategory":"Landscaping Services",
            "type":"Services"
        }
    ],
    "sg:phone":"+32 9 366 38 52",
    "sg:postcode":"9270",
    "sg:province":"Oost-Vlaanderen",
    "sg:tags":[
        "nurseryman"
    ],
    "wof:name":"Coppens G",
    "wof:placetype":"venue"
},
  "geometry": {"coordinates":[3.8828570843,51.0334396362],"type":"Point"}
}