{
  "type": "Feature",
  "properties": {
    "addr:full":"Windmolenstraat 34 Jabbeke West-Vlaanderen 8490",
    "addr:housenumber":"34",
    "addr:postcode":"8490",
    "addr:street":"Windmolenstraat",
    "iso:country":"BE",
    "sg:address":"Windmolenstraat 34",
    "sg:city":"Jabbeke",
    "sg:classifiers":[
        {
            "category":"Arts & Performance",
            "subcategory":"Symphony",
            "type":"Entertainment"
        }
    ],
    "sg:phone":"+32 50 81 20 87",
    "sg:postcode":"8490",
    "sg:province":"West-Vlaanderen",
    "sg:tags":[
        "orchestra"
    ],
    "wof:name":"Collegium Instrumentale Brugense",
    "wof:placetype":"venue"
},
  "geometry": {"coordinates":[3.0801000595,51.1834373474],"type":"Point"}
}