{
  "type": "Feature",
  "properties": {
    "addr:full":"Rue Des Fr\u00c8res Lefort 386 Tubize Brabant Wallon 1480",
    "addr:housenumber":"386",
    "addr:postcode":"1480",
    "addr:street":"Rue Des Fre\u0300Res Lefort;Wallon",
    "iso:country":"BE",
    "sg:address":"Rue Des Fr\u00c8res Lefort 386",
    "sg:city":"Tubize",
    "sg:orig_category":"Eclairage et \u00e9quipements du foyer",
    "sg:phone":"+32 475 72 91 13",
    "sg:postcode":"1480",
    "sg:province":"Brabant Wallon",
    "wof:name":"D\u00c9coration Preumont",
    "wof:placetype":"venue"
},
  "geometry": {"coordinates":[4.1986670494,50.6738204956],"type":"Point"}
}