{
  "type": "Feature",
  "properties": {
    "addr:full":"Avenue Du Parc 153 Vorst/forest Bruxelles-Capitale 1190",
    "addr:housenumber":"153",
    "addr:postcode":"1190",
    "addr:street":"Avenue Du Parc;/ Forest",
    "iso:country":"BE",
    "sg:address":"Avenue Du Parc 153",
    "sg:city":"Vorst/forest",
    "sg:classifiers":[
        {
            "category":"Personal",
            "subcategory":"Beauty Salon",
            "type":"Services"
        }
    ],
    "sg:phone":"+32 2 537 97 68",
    "sg:postcode":"1190",
    "sg:province":"Bruxelles-Capitale",
    "sg:tags":[
        "de",
        "coiffure"
    ],
    "wof:name":"Parc (du)",
    "wof:placetype":"venue"
},
  "geometry": {"coordinates":[4.3363780975,50.8248291016],"type":"Point"}
}