{
  "type": "Feature",
  "properties": {
    "iso:country":"BE",
    "sg:address":"Rue De Cugnon 10",
    "sg:city":"Florenville",
    "sg:orig_category":"Epiceries",
    "sg:phone":"+32 61 31 33 02",
    "sg:postcode":"6820",
    "sg:province":"Luxembourg",
    "wof:name":"Courtheoux",
    "wof:placetype":"venue"
},
  "geometry": {"coordinates":[5.1747031212,49.7174491882],"type":"Point"}
}