{
  "type": "Feature",
  "properties": {
    "addr:full":"Lijsterlaan 32 Liedekerke Vlaams-Brabant 1770",
    "addr:housenumber":"32",
    "addr:postcode":"1770",
    "addr:street":"Lijsterlaan;Vlaams-Brabant",
    "iso:country":"BE",
    "sg:address":"Lijsterlaan 32",
    "sg:city":"Liedekerke",
    "sg:orig_category":"Installation \u00e9lectrique r\u00e9sidentielle",
    "sg:phone":"+32 53 66 20 00",
    "sg:postcode":"1770",
    "sg:province":"Vlaams-Brabant",
    "wof:name":"Jan Lannoy",
    "wof:placetype":"venue"
},
  "geometry": {"coordinates":[4.1164622307,50.8589515686],"type":"Point"}
}