{
  "type": "Feature",
  "properties": {
    "addr:full":"Torhoutsesteenweg 303 Oostende West-Vlaanderen 8400",
    "addr:housenumber":"303",
    "addr:postcode":"8400",
    "addr:street":"Torhoutsesteenweg",
    "iso:country":"BE",
    "sg:address":"Torhoutsesteenweg 303",
    "sg:city":"Oostende",
    "sg:orig_category":"Jeux de hasard",
    "sg:phone":"+32 59 50 09 84",
    "sg:postcode":"8400",
    "sg:province":"West-Vlaanderen",
    "wof:name":"Ladbroke",
    "wof:placetype":"venue"
},
  "geometry": {"coordinates":[2.9067230225,51.2161865234],"type":"Point"}
}