{
  "type": "Feature",
  "properties": {
    "iso:country":"BE",
    "sg:address":"Mudakkers 95",
    "sg:city":"Lommel",
    "sg:orig_category":"M\u00e9decins and sp\u00e9cialistes",
    "sg:phone":"+32 11 54 41 27",
    "sg:postcode":"3920",
    "sg:province":"Limburg",
    "wof:name":"Petronella Vermeulen",
    "wof:placetype":"venue"
},
  "geometry": {"coordinates":[5.3216881752,51.232460022],"type":"Point"}
}