{
  "type": "Feature",
  "properties": {
    "addr:full":"Rue De La Banque Verviers Li\u00e8ge 4800",
    "addr:postcode":"4800",
    "addr:street":"Rue De La Banque",
    "iso:country":"BE",
    "sg:address":"Rue De La Banque",
    "sg:city":"Verviers",
    "sg:classifiers":[
        {
            "category":"Fast Food",
            "type":"Food & Drink"
        }
    ],
    "sg:phone":"+32 87 31 49 03",
    "sg:postcode":"4800",
    "sg:province":"Li\u00e8ge",
    "sg:tags":[
        "meeneem",
        "restaurant"
    ],
    "wof:name":"La Storia",
    "wof:placetype":"venue"
},
  "geometry": {"coordinates":[5.8656821251,50.5910835266],"type":"Point"}
}