{
  "type": "Feature",
  "properties": {
    "addr:full":"Warotveld 112 Herent Vlaams-Brabant 3020",
    "addr:housenumber":"112",
    "addr:postcode":"3020",
    "iso:country":"BE",
    "sg:address":"Warotveld 112",
    "sg:city":"Herent",
    "sg:orig_category":"Agences d'exp\u00e9dition",
    "sg:phone":"+32 16 49 05 22",
    "sg:postcode":"3020",
    "sg:province":"Vlaams-Brabant",
    "wof:name":"Phenicia Trading Agency",
    "wof:placetype":"venue"
},
  "geometry": {"coordinates":[4.6749200821,50.9079055786],"type":"Point"}
}