{
  "type": "Feature",
  "properties": {
    "iso:country":"BE",
    "sg:address":"Chauss\u00c9e De Fleurus 72",
    "sg:city":"Charleroi",
    "sg:orig_category":"Avocats and conseillers juridiques",
    "sg:phone":"+32 71 48 98 53",
    "sg:postcode":"6060",
    "sg:province":"Hainaut",
    "wof:name":"B. Parmentier",
    "wof:placetype":"venue"
},
  "geometry": {"coordinates":[4.4725241661,50.4411888123],"type":"Point"}
}