{
  "type": "Feature",
  "properties": {
    "addr:full":"Rue Henri Debeaume 24c Charleroi (goutroux) Hainaut 6030",
    "addr:housenumber":"24c",
    "addr:postcode":"6030",
    "addr:street":"Rue Henri Debeaume",
    "iso:country":"BE",
    "sg:address":"Rue Henri Debeaume 24c",
    "sg:city":"Charleroi (goutroux)",
    "sg:classifiers":[
        {
            "category":"Utilities",
            "subcategory":"Natural Gas",
            "type":"Services"
        }
    ],
    "sg:phone":"+32 71 52 86 05",
    "sg:postcode":"6030",
    "sg:province":"Hainaut",
    "sg:tags":[
        "welding"
    ],
    "wof:name":"Vp Soudure",
    "wof:placetype":"venue"
},
  "geometry": {"coordinates":[4.3603281975,50.4225845337],"type":"Point"}
}