{
  "type": "Feature",
  "properties": {
    "addr:full":"Avenue Am\u00e9d\u00e9e Hesse 13 Spa Li\u00e8ge 4900",
    "addr:housenumber":"13",
    "addr:postcode":"4900",
    "addr:street":"Avenue Ame\u0301De\u0301E Hesse",
    "iso:country":"BE",
    "sg:address":"Avenue Am\u00e9d\u00e9e Hesse 13",
    "sg:city":"Spa",
    "sg:classifiers":[
        {
            "category":"Arena",
            "subcategory":"Sports Club",
            "type":"Entertainment"
        }
    ],
    "sg:phone":"+32 87 77 32 36",
    "sg:postcode":"4900",
    "sg:province":"Li\u00e8ge",
    "wof:name":"Adeps-r\u00e9sidence Olympic",
    "wof:placetype":"venue"
},
  "geometry": {"coordinates":[5.8747811317,50.4957885742],"type":"Point"}
}