{
  "type": "Feature",
  "properties": {
    "addr:full":"Lavendelstraat 14 Ninove Oost-Vlaanderen 9400",
    "addr:housenumber":"14",
    "addr:postcode":"9400",
    "addr:street":"Lavendelstraat",
    "iso:country":"BE",
    "sg:address":"Lavendelstraat 14",
    "sg:city":"Ninove",
    "sg:orig_category":"Brood, gebak and snoepgoed",
    "sg:phone":"+32 54 33 13 22",
    "sg:postcode":"9400",
    "sg:province":"Oost-Vlaanderen",
    "wof:name":"Wilfried Van Keymeulen",
    "wof:placetype":"venue"
},
  "geometry": {"coordinates":[4.0204348564,50.8366661072],"type":"Point"}
}