{
  "type": "Feature",
  "properties": {
    "iso:country":"BE",
    "sg:address":"Plein 5",
    "sg:city":"Kaprijke",
    "sg:classifiers":[
        {
            "category":"Professional",
            "subcategory":"Testing Lab",
            "type":"Services"
        }
    ],
    "sg:phone":"+32 9 373 94 03",
    "sg:postcode":"9970",
    "sg:province":"Oost-Vlaanderen",
    "sg:tags":[
        "chemist"
    ],
    "wof:name":"Van Landschoot K",
    "wof:placetype":"venue"
},
  "geometry": {"coordinates":[3.6183750629,51.2189788818],"type":"Point"}
}