{
  "type": "Feature",
  "properties": {
    "addr:full":"Steinebruck 4 Sankt Vith/saint-vith Li\u00e8ge 4783",
    "addr:housenumber":"4",
    "addr:postcode":"4783",
    "addr:street":"Steinebruck",
    "iso:country":"BE",
    "sg:address":"Steinebruck 4",
    "sg:city":"Sankt Vith/saint-vith",
    "sg:classifiers":[
        {
            "category":"Cafe",
            "type":"Food & Drink"
        }
    ],
    "sg:phone":"+32 80 22 81 40",
    "sg:postcode":"4783",
    "sg:province":"Li\u00e8ge",
    "sg:tags":[
        "caf\u00e9s"
    ],
    "wof:name":"Gastst\u00c4tte Str\u00dcck Gebr.",
    "wof:placetype":"venue"
},
  "geometry": {"coordinates":[6.1624388695,50.2378196716],"type":"Point"}
}