{
  "type": "Feature",
  "properties": {
    "addr:full":"Rue Wirtz 7 Li\u00c8ge Li\u00e8ge 4000",
    "addr:housenumber":"7",
    "addr:postcode":"4000",
    "addr:street":"Rue Wirtz",
    "iso:country":"BE",
    "sg:address":"Rue Wirtz 7",
    "sg:city":"Li\u00c8ge",
    "sg:orig_category":"Instituts de beaut\u00e9",
    "sg:phone":"+32 4 226 84 81",
    "sg:postcode":"4000",
    "sg:province":"Li\u00e8ge",
    "wof:name":"Institut Bois De Santal",
    "wof:placetype":"venue"
},
  "geometry": {"coordinates":[5.5552120209,50.6408424377],"type":"Point"}
}