{
  "type": "Feature",
  "properties": {
    "addr:full":"Vrijheidstraat 75 Aalst Oost-Vlaanderen 9300",
    "addr:housenumber":"75",
    "addr:postcode":"9300",
    "addr:street":"Vrijheidstraat",
    "iso:country":"BE",
    "sg:address":"Vrijheidstraat 75",
    "sg:city":"Aalst",
    "sg:classifiers":[
        {
            "category":"Personal",
            "subcategory":"Beauty Salon",
            "type":"Services"
        }
    ],
    "sg:phone":"+32 53 21 55 75",
    "sg:postcode":"9300",
    "sg:province":"Oost-Vlaanderen",
    "sg:tags":[
        "lady",
        "-",
        "hairdressing"
    ],
    "wof:name":"Belicima",
    "wof:placetype":"venue"
},
  "geometry": {"coordinates":[4.0333600044,50.9391708374],"type":"Point"}
}