{
  "type": "Feature",
  "properties": {
    "iso:country":"BE",
    "sg:address":"Rue Fran\u00e7ois Libert 18",
    "sg:city":"Waterloo",
    "sg:classifiers":[
        {
            "category":"Personal",
            "subcategory":"Beauty Salon",
            "type":"Services"
        }
    ],
    "sg:phone":"+32 2 353 27 70",
    "sg:postcode":"1410",
    "sg:province":"Brabant Wallon",
    "wof:name":"Virginails",
    "wof:placetype":"venue"
},
  "geometry": {"coordinates":[4.3966259956,50.71667099],"type":"Point"}
}