{
  "type": "Feature",
  "properties": {
    "iso:country":"BE",
    "sg:address":"Driepaalhoeveweg 1",
    "sg:city":"Dilsen-stokkem",
    "sg:orig_category":"Rundveehouders",
    "sg:phone":"+32 89 75 53 77",
    "sg:postcode":"3650",
    "sg:province":"Limburg",
    "wof:name":"Andre Coolen",
    "wof:placetype":"venue"
},
  "geometry": {"coordinates":[5.703458786,51.0358200073],"type":"Point"}
}