{
  "type": "Feature",
  "properties": {
    "addr:full":"Rue Du Trixhe Barr\u00c9 3 Chaudfontaine Li\u00e8ge 4052",
    "addr:housenumber":"3",
    "addr:postcode":"4052",
    "addr:street":"Rue Du Trixhe Barre\u0301",
    "iso:country":"BE",
    "sg:address":"Rue Du Trixhe Barr\u00c9 3",
    "sg:city":"Chaudfontaine",
    "sg:classifiers":[
        {
            "category":"Arena",
            "subcategory":"Sports Club",
            "type":"Entertainment"
        }
    ],
    "sg:phone":"+32 4 368 70 45",
    "sg:postcode":"4052",
    "sg:province":"Li\u00e8ge",
    "sg:tags":[
        "de"
    ],
    "wof:name":"Beaufays T.c.",
    "wof:placetype":"venue"
},
  "geometry": {"coordinates":[5.6353411674,50.5643386841],"type":"Point"}
}