{
  "type": "Feature",
  "properties": {
    "addr:full":"Bilzersteenweg 71b1 Tongeren Limburg 3700",
    "addr:housenumber":"71b1",
    "addr:postcode":"3700",
    "addr:street":"Bilzersteenweg",
    "iso:country":"BE",
    "sg:address":"Bilzersteenweg 71b1",
    "sg:city":"Tongeren",
    "sg:orig_category":"Belastingconsulenten Diverse juridische dienstverlening Immobili\u00ebnkantoren Verzekeringsmakelaars and",
    "sg:phone":"+32 12 23 72 57",
    "sg:postcode":"3700",
    "sg:province":"Limburg",
    "wof:name":"Immo-bouw",
    "wof:placetype":"venue"
},
  "geometry": {"coordinates":[5.4628858566,50.7855682373],"type":"Point"}
}