{
  "type": "Feature",
  "properties": {
    "iso:country":"BE",
    "sg:address":"Bd Pire Lef. Desnouettes 1",
    "sg:city":"Braine-l\u00b4alleud",
    "sg:orig_category":"M\u00e9decins and sp\u00e9cialistes",
    "sg:phone":"+32 2 387 11 00",
    "sg:postcode":"1420",
    "sg:province":"Brabant Wallon",
    "wof:name":"Isabelle Schiepers",
    "wof:placetype":"venue"
},
  "geometry": {"coordinates":[4.3885731697,50.6766433716],"type":"Point"}
}