{
  "type": "Feature",
  "properties": {
    "iso:country":"BE",
    "sg:address":"Koksijdesteenweg 31",
    "sg:city":"Koksijde",
    "sg:orig_category":"Souvenirs and objets artisanaux. Fleurs and plantes. Quincailleries. Articles de jardin",
    "sg:phone":"+32 58 51 10 21",
    "sg:postcode":"8670",
    "sg:province":"West-Vlaanderen",
    "wof:name":"Tuincenter Lamote",
    "wof:placetype":"venue"
},
  "geometry": {"coordinates":[2.669121027,51.1102867126],"type":"Point"}
}