{
  "type": "Feature",
  "properties": {
    "addr:full":"Dorpsstraat 22 Deinze Oost-Vlaanderen 9800",
    "addr:housenumber":"22",
    "addr:postcode":"9800",
    "addr:street":"Dorpsstraat",
    "iso:country":"BE",
    "sg:address":"Dorpsstraat 22",
    "sg:city":"Deinze",
    "sg:orig_category":"Fotografen and fotostudio's",
    "sg:phone":"+32 9 386 74 14",
    "sg:postcode":"9800",
    "sg:province":"Oost-Vlaanderen",
    "wof:name":"Erik Vanderlinden",
    "wof:placetype":"venue"
},
  "geometry": {"coordinates":[3.530174017,50.9863166809],"type":"Point"}
}