{
  "type": "Feature",
  "properties": {
    "iso:country":"BE",
    "sg:address":"Grand'route 125a",
    "sg:city":"Flemalle",
    "sg:orig_category":"Biblioth\u00e8ques and archives publiques",
    "sg:phone":"+32 4 233 93 68",
    "sg:postcode":"4400",
    "sg:province":"Li\u00e8ge",
    "wof:name":"Biblioth\u00c8que Communal",
    "wof:placetype":"venue"
},
  "geometry": {"coordinates":[5.4492239952,50.5986442566],"type":"Point"}
}