{
  "type": "Feature",
  "properties": {
    "iso:country":"BE",
    "sg:address":"Rue Du Tram 12",
    "sg:city":"Soignies",
    "sg:orig_category":"Plaatsen van vloer- and muurbekleding Schilders",
    "sg:phone":"+32 67 33 28 72",
    "sg:postcode":"7060",
    "sg:province":"Hainaut",
    "wof:name":"Belot Marc & Fils",
    "wof:placetype":"venue"
},
  "geometry": {"coordinates":[4.0724000931,50.5779037476],"type":"Point"}
}