{
  "type": "Feature",
  "properties": {
    "addr:full":"Softplaats 29 Berendrecht Antwerpen 2040",
    "addr:housenumber":"29",
    "addr:postcode":"2040",
    "addr:street":"Softplaats",
    "iso:country":"BE",
    "sg:address":"Softplaats 29",
    "sg:city":"Berendrecht",
    "sg:orig_category":"Huisdieren and benodigdheden Royal Canin",
    "sg:phone":"+32 3568005",
    "sg:postcode":"2040",
    "sg:province":"Antwerpen",
    "wof:name":"Verhaert",
    "wof:placetype":"venue"
},
  "geometry": {"coordinates":[4.3147201538,51.3430671692],"type":"Point"}
}