{
  "type": "Feature",
  "properties": {
    "addr:full":"Berkenlaan 11 Ranst Antwerpen 2520",
    "addr:housenumber":"11",
    "addr:postcode":"2520",
    "addr:street":"Berkenlaan",
    "iso:country":"BE",
    "sg:address":"Berkenlaan 11",
    "sg:city":"Ranst",
    "sg:classifiers":[
        {
            "category":"Health Services",
            "subcategory":"Dentist",
            "type":"Services"
        }
    ],
    "sg:phone":"+32 3 485 76 00",
    "sg:postcode":"2520",
    "sg:province":"Antwerpen",
    "wof:name":"Van Huffelen J (mevr)",
    "wof:placetype":"venue"
},
  "geometry": {"coordinates":[4.5560059547,51.1911468506],"type":"Point"}
}