{
  "type": "Feature",
  "properties": {
    "addr:full":"Veldstraat 34 Oud-turnhout Antwerpen 2360",
    "addr:housenumber":"34",
    "addr:postcode":"2360",
    "addr:street":"Veldstraat",
    "iso:country":"BE",
    "sg:address":"Veldstraat 34",
    "sg:city":"Oud-turnhout",
    "sg:classifiers":[
        {
            "category":"Professional",
            "subcategory":"Management & Consulting",
            "type":"Services"
        }
    ],
    "sg:phone":"+32 14 43 65 02",
    "sg:postcode":"2360",
    "sg:province":"Antwerpen",
    "sg:tags":[
        "consultant"
    ],
    "wof:name":"Bioscan Bvba",
    "wof:placetype":"venue"
},
  "geometry": {"coordinates":[4.9705090523,51.3428497314],"type":"Point"}
}