{
  "type": "Feature",
  "properties": {
    "addr:full":"Liersebaan 45 Lier Antwerpen 2500",
    "addr:housenumber":"45",
    "addr:postcode":"2500",
    "addr:street":"Liersebaan",
    "iso:country":"BE",
    "sg:address":"Liersebaan 45",
    "sg:city":"Lier",
    "sg:orig_category":"Boucheries",
    "sg:phone":"+32 3 422 51 33",
    "sg:postcode":"2500",
    "sg:province":"Antwerpen",
    "wof:name":"'t Kippewinkeltje",
    "wof:placetype":"venue"
},
  "geometry": {"coordinates":[4.6070671082,51.099407196],"type":"Point"}
}