{
  "type": "Feature",
  "properties": {
    "addr:full":"Place Communal 7 Les Bons Villers Hainaut 6210",
    "addr:housenumber":"7",
    "addr:postcode":"6210",
    "addr:street":"Place Communal",
    "iso:country":"BE",
    "sg:address":"Place Communal 7",
    "sg:city":"Les Bons Villers",
    "sg:orig_category":"Werk and personeelsselectie",
    "sg:phone":"+32 71 85 02 46",
    "sg:postcode":"6210",
    "sg:province":"Hainaut",
    "wof:name":"S.l.a.i.e. Les Bons Villers",
    "wof:placetype":"venue"
},
  "geometry": {"coordinates":[4.4511561394,50.5378227234],"type":"Point"}
}