{
  "type": "Feature",
  "properties": {
    "addr:full":"Hauptstrasse 85 Raeren Li\u00e8ge 4730",
    "addr:housenumber":"85",
    "addr:postcode":"4730",
    "addr:street":"Hauptstrasse",
    "iso:country":"BE",
    "sg:address":"Hauptstrasse 85",
    "sg:city":"Raeren",
    "sg:orig_category":"Winkelinrichting and handelsuitrusting Gh",
    "sg:phone":"+32 87 85 15 27",
    "sg:postcode":"4730",
    "sg:province":"Li\u00e8ge",
    "wof:name":"Havenith",
    "wof:placetype":"venue"
},
  "geometry": {"coordinates":[6.1133389473,50.6738319397],"type":"Point"}
}