{
  "type": "Feature",
  "properties": {
    "addr:full":"Mechelbaan 495 Putte Antwerpen 2580",
    "addr:housenumber":"495",
    "addr:postcode":"2580",
    "addr:street":"Mechelbaan",
    "iso:country":"BE",
    "sg:address":"Mechelbaan 495",
    "sg:city":"Putte",
    "sg:orig_category":"Pain, p\u00e2tisseries and confiseries",
    "sg:phone":"+32 15 75 56 07",
    "sg:postcode":"2580",
    "sg:province":"Antwerpen",
    "wof:name":"Dijck - Vergauwen",
    "wof:placetype":"venue"
},
  "geometry": {"coordinates":[4.6296072006,51.0550994873],"type":"Point"}
}