{
  "type": "Feature",
  "properties": {
    "addr:full":"Nijverheidsstraat 1 Meulebeke West-Vlaanderen 8760",
    "addr:housenumber":"1",
    "addr:postcode":"8760",
    "addr:street":"Nijverheidsstraat",
    "iso:country":"BE",
    "sg:address":"Nijverheidsstraat 1",
    "sg:city":"Meulebeke",
    "sg:classifiers":[
        {
            "category":"Wholesale",
            "subcategory":"Beer",
            "type":"Manufacturing & Wholesale Goods"
        }
    ],
    "sg:phone":"+32 51 48 66 76",
    "sg:postcode":"8760",
    "sg:province":"West-Vlaanderen",
    "sg:tags":[
        "ale",
        "-"
    ],
    "wof:name":"Drinkmarket",
    "wof:placetype":"venue"
},
  "geometry": {"coordinates":[3.2989599705,50.9590492249],"type":"Point"}
}