{
  "type": "Feature",
  "properties": {
    "addr:full":"Rue Pont D'avroy 21 Liege Li\u00e8ge 4000",
    "addr:housenumber":"21",
    "addr:postcode":"4000",
    "addr:street":"Rue Pont D'Avroy",
    "iso:country":"BE",
    "sg:address":"Rue Pont D'avroy 21",
    "sg:city":"Liege",
    "sg:orig_category":"Cin\u00e9mas",
    "sg:phone":"+32 4 223 30 54",
    "sg:postcode":"4000",
    "sg:province":"Li\u00e8ge",
    "wof:name":"Le Palace",
    "wof:placetype":"venue"
},
  "geometry": {"coordinates":[5.5699968338,50.6404838562],"type":"Point"}
}