{
  "type": "Feature",
  "properties": {
    "addr:full":"Poelbergstraat 11 Scherpenheuvel-zichem Vlaams-Brabant 3270",
    "addr:housenumber":"11",
    "addr:postcode":"3270",
    "addr:street":"Poelbergstraat",
    "iso:country":"BE",
    "sg:address":"Poelbergstraat 11",
    "sg:city":"Scherpenheuvel-zichem",
    "sg:classifiers":[
        {
            "category":"Food & Beverages",
            "subcategory":"Fruits & Vegetables",
            "type":"Retail Goods"
        }
    ],
    "sg:phone":"+32 13 77 55 54",
    "sg:postcode":"3270",
    "sg:province":"Vlaams-Brabant",
    "sg:tags":[
        "l\u00e9gumes"
    ],
    "wof:name":"Irene Beynaerts",
    "wof:placetype":"venue"
},
  "geometry": {"coordinates":[4.9441819191,50.9639511108],"type":"Point"}
}