{
  "type": "Feature",
  "properties": {
    "iso:country":"BE",
    "sg:address":"Wijngaardstraat 16",
    "sg:city":"Antwerpen",
    "sg:orig_category":"Agences d'exp\u00e9dition",
    "sg:phone":"+32 3 226 84 06",
    "sg:postcode":"2000",
    "sg:province":"Antwerpen",
    "wof:name":"Cbc Belgium",
    "wof:placetype":"venue"
},
  "geometry": {"coordinates":[4.4048910141,51.2212257385],"type":"Point"}
}