{
  "type": "Feature",
  "properties": {
    "iso:country":"BE",
    "sg:address":"Hoogstraat 23",
    "sg:city":"Wachtebeke",
    "sg:classifiers":[
        {
            "category":"Building & Trades",
            "subcategory":"Landscaping Services",
            "type":"Services"
        }
    ],
    "sg:phone":"+32 478 47 52 55",
    "sg:postcode":"9185",
    "sg:province":"Oost-Vlaanderen",
    "sg:tags":[
        "gardening",
        "garden",
        "maintenance"
    ],
    "wof:name":"Eurogarden Center Bvba",
    "wof:placetype":"venue"
},
  "geometry": {"coordinates":[3.8994760513,51.1873779297],"type":"Point"}
}