{
  "type": "Feature",
  "properties": {
    "iso:country":"BE",
    "sg:address":"'t Hasseltkiezel 30a",
    "sg:city":"Bree",
    "sg:classifiers":[
        {
            "category":"Autos & Motor Vehicles",
            "subcategory":"Fuel & Gas Station",
            "type":"Retail Goods"
        }
    ],
    "sg:phone":"+32 89 46 18 41",
    "sg:postcode":"3960",
    "sg:province":"Limburg",
    "wof:name":"Q8-service Station",
    "wof:placetype":"venue"
},
  "geometry": {"coordinates":[5.6637887955,51.1423072815],"type":"Point"}
}