{
  "type": "Feature",
  "properties": {
    "addr:full":"Antwerpsesteenweg 48 Kapellen Antwerpen 2950",
    "addr:housenumber":"48",
    "addr:postcode":"2950",
    "addr:street":"Antwerpsesteenweg",
    "iso:country":"BE",
    "sg:address":"Antwerpsesteenweg 48",
    "sg:city":"Kapellen",
    "sg:classifiers":[
        {
            "category":"Restaurant",
            "type":"Food & Drink"
        }
    ],
    "sg:phone":"+32 3 664 22 82",
    "sg:postcode":"2950",
    "sg:province":"Antwerpen",
    "wof:name":"De Pauw",
    "wof:placetype":"venue"
},
  "geometry": {"coordinates":[4.4292850494,51.3123664856],"type":"Point"}
}