{
  "type": "Feature",
  "properties": {
    "iso:country":"BE",
    "sg:address":"Bessenstraat 6",
    "sg:city":"Ardooie",
    "sg:orig_category":"Elektrische installaties voor woningen",
    "sg:phone":"+32 51 74 68 40",
    "sg:postcode":"8850",
    "sg:province":"West-Vlaanderen",
    "wof:name":"F Vandenheede",
    "wof:placetype":"venue"
},
  "geometry": {"coordinates":[3.1921060085,50.9803466797],"type":"Point"}
}