{
  "type": "Feature",
  "properties": {
    "iso:country":"BE",
    "sg:address":"7170",
    "sg:city":"Manage (groot)",
    "sg:orig_category":"Pharmaciens",
    "sg:phone":"+32 900 10 500",
    "sg:postcode":"7170",
    "sg:province":"Hainaut",
    "wof:name":"Pharmacies De Garde",
    "wof:placetype":"venue"
},
  "geometry": {"coordinates":[4.2327899933,50.5008239746],"type":"Point"}
}