{
  "type": "Feature",
  "properties": {
    "addr:full":"Rue Marcel-moreau 11 Couvin Namur 5660",
    "addr:housenumber":"11",
    "addr:postcode":"5660",
    "addr:street":"Rue Marcel-Moreau",
    "iso:country":"BE",
    "sg:address":"Rue Marcel-moreau 11",
    "sg:city":"Couvin",
    "sg:orig_category":"Artsen and specialisten",
    "sg:phone":"+32 60 34 61 14",
    "sg:postcode":"5660",
    "sg:province":"Namur",
    "wof:name":"Pierre Ballat",
    "wof:placetype":"venue"
},
  "geometry": {"coordinates":[4.4820637703,50.0536766052],"type":"Point"}
}