{
  "type": "Feature",
  "properties": {
    "addr:full":"Rue De Liboichant Alle Namur 5550",
    "addr:postcode":"5550",
    "addr:street":"Rue De Liboichant Alle",
    "iso:country":"BE",
    "sg:address":"Rue De Liboichant",
    "sg:city":"Alle",
    "sg:orig_category":"Animaux domestiques and accessoires",
    "sg:phone":"+32 61 50 05 20",
    "sg:postcode":"5550",
    "sg:province":"Namur",
    "wof:name":"Ets Halleux-manil",
    "wof:placetype":"venue"
},
  "geometry": {"coordinates":[4.9698419571,49.8513145447],"type":"Point"}
}