{
  "type": "Feature",
  "properties": {
    "addr:full":"Sint-lambertusstraat 19 Westerlo Antwerpen 2260",
    "addr:housenumber":"19",
    "addr:postcode":"2260",
    "addr:street":"Sint-Lambertusstraat",
    "iso:country":"BE",
    "sg:address":"Sint-lambertusstraat 19",
    "sg:city":"Westerlo",
    "sg:classifiers":[
        {
            "category":"Manufacturing",
            "subcategory":"Glass & Minerals",
            "type":"Manufacturing & Wholesale Goods"
        }
    ],
    "sg:phone":"+32 14 54 08 20",
    "sg:postcode":"2260",
    "sg:province":"Antwerpen",
    "sg:tags":[
        "stained",
        "glazier",
        "-"
    ],
    "wof:name":"Atelier Transparant",
    "wof:placetype":"venue"
},
  "geometry": {"coordinates":[4.9190950394,51.0895233154],"type":"Point"}
}