{
  "type": "Feature",
  "properties": {
    "addr:full":"Lamorini\u00c8restraat 25 Antwerpen Antwerpen 2018",
    "addr:housenumber":"25",
    "addr:postcode":"2018",
    "addr:street":"Lamorinie\u0300Restraat",
    "iso:country":"BE",
    "sg:address":"Lamorini\u00c8restraat 25",
    "sg:city":"Antwerpen",
    "sg:orig_category":"Kunststofrecipi\u00ebnten and -verpakkingen Fab Papier- and kartonverpakkingen Fab",
    "sg:phone":"+32 3 281 29 32",
    "sg:postcode":"2018",
    "sg:province":"Antwerpen",
    "wof:name":"Antwerp Plastics",
    "wof:placetype":"venue"
},
  "geometry": {"coordinates":[4.4235649109,51.2070007324],"type":"Point"}
}