{
  "type": "Feature",
  "properties": {
    "addr:full":"Schoppen 39 Amel/ambleve Li\u00e8ge 4770",
    "addr:housenumber":"39",
    "addr:postcode":"4770",
    "addr:street":"Schoppen",
    "iso:country":"BE",
    "sg:address":"Schoppen 39",
    "sg:city":"Amel/ambleve",
    "sg:orig_category":"Rundveehouders",
    "sg:phone":"+32 80 34 95 58",
    "sg:postcode":"4770",
    "sg:province":"Li\u00e8ge",
    "wof:name":"Paul Kohnen",
    "wof:placetype":"venue"
},
  "geometry": {"coordinates":[6.1876211166,50.3251914978],"type":"Point"}
}