{
  "type": "Feature",
  "properties": {
    "iso:country":"BE",
    "sg:address":"Rue M\u00c9morial Am\u00c9ricain 381",
    "sg:city":"Plombieres/plombieres",
    "sg:orig_category":"Eleveurs de bovins",
    "sg:phone":"+32 87 88 10 18",
    "sg:postcode":"4850",
    "sg:province":"Li\u00e8ge",
    "wof:name":"Jean Wintgens",
    "wof:placetype":"venue"
},
  "geometry": {"coordinates":[5.9626002312,50.7068138123],"type":"Point"}
}