{
  "type": "Feature",
  "properties": {
    "iso:country":"BE",
    "sg:address":"Rue De La Station 61a",
    "sg:city":"Waterloo",
    "sg:classifiers":[
        {
            "category":"Professional",
            "subcategory":"Lawyer & Legal Services",
            "type":"Services"
        }
    ],
    "sg:phone":"+32 2 351 65 73",
    "sg:postcode":"1410",
    "sg:province":"Brabant Wallon",
    "wof:name":"Jantea Mihaela",
    "wof:placetype":"venue"
},
  "geometry": {"coordinates":[4.3885030746,50.7156181335],"type":"Point"}
}