{
  "type": "Feature",
  "properties": {
    "addr:full":"Nijverheidsstraat 60 Waarschoot Oost-Vlaanderen 9950",
    "addr:housenumber":"60",
    "addr:postcode":"9950",
    "addr:street":"Nijverheidsstraat",
    "iso:country":"BE",
    "sg:address":"Nijverheidsstraat 60",
    "sg:city":"Waarschoot",
    "sg:classifiers":[
        {
            "category":"Personal",
            "subcategory":"Beauty Salon",
            "type":"Services"
        }
    ],
    "sg:phone":"+32 9 378 18 10",
    "sg:postcode":"9950",
    "sg:province":"Oost-Vlaanderen",
    "sg:tags":[
        "de",
        "coiffure"
    ],
    "wof:name":"Steven Van De Velde",
    "wof:placetype":"venue"
},
  "geometry": {"coordinates":[3.6101191044,51.1533164978],"type":"Point"}
}