{
  "type": "Feature",
  "properties": {
    "iso:country":"BE",
    "sg:address":"Rue Hom\u00e8re 3",
    "sg:city":"Bruxelles (anderlecht)",
    "sg:classifiers":[
        {
            "category":"Health Services",
            "subcategory":"Health Practitioner",
            "type":"Services"
        }
    ],
    "sg:phone":"+32 2 521 06 11",
    "sg:postcode":"1070",
    "sg:province":"Bruxelles-Capitale",
    "sg:tags":[
        "dietitian"
    ],
    "wof:name":"Van Aelst C",
    "wof:placetype":"venue"
},
  "geometry": {"coordinates":[4.2863168716,50.8448944092],"type":"Point"}
}