{
  "type": "Feature",
  "properties": {
    "iso:country":"BE",
    "sg:address":"Avenue Des Celtes 42",
    "sg:city":"Etterbeek",
    "sg:classifiers":[
        {
            "category":"Bars & Pubs",
            "subcategory":"Sports Bar",
            "type":"Food & Drink"
        }
    ],
    "sg:phone":"+32 2 734 81 04",
    "sg:postcode":"1040",
    "sg:province":"Bruxelles-Capitale",
    "sg:tags":[
        "bars",
        "restaurant"
    ],
    "wof:name":"Europub",
    "wof:placetype":"venue"
},
  "geometry": {"coordinates":[4.3972520828,50.8380432129],"type":"Point"}
}