{
  "type": "Feature",
  "properties": {
    "iso:country":"BE",
    "sg:address":"Dorpsstraat 118",
    "sg:city":"Linter",
    "sg:orig_category":"Epiceries. D\u00e9molition d\u00b4immeubles and terrassements",
    "sg:phone":"+32 11 78 11 50",
    "sg:postcode":"3350",
    "sg:province":"Vlaams-Brabant",
    "wof:name":"Dewil R",
    "wof:placetype":"venue"
},
  "geometry": {"coordinates":[5.0616288185,50.8252983093],"type":"Point"}
}