{
  "type": "Feature",
  "properties": {
    "addr:full":"Rue Royale 227 Florennes Namur 5621",
    "addr:housenumber":"227",
    "addr:postcode":"5621",
    "addr:street":"Rue Royale",
    "iso:country":"BE",
    "sg:address":"Rue Royale 227",
    "sg:city":"Florennes",
    "sg:orig_category":"Artsen and specialisten",
    "sg:phone":"+32 71 68 96 48",
    "sg:postcode":"5621",
    "sg:province":"Namur",
    "wof:name":"D. Cuypers",
    "wof:placetype":"venue"
},
  "geometry": {"coordinates":[4.5658240318,50.2755355835],"type":"Point"}
}