{
  "type": "Feature",
  "properties": {
    "addr:full":"Avenue Eug\u00c8ne Mascaux 54 Charleroi Hainaut 6001",
    "addr:housenumber":"54",
    "addr:postcode":"6001",
    "addr:street":"Avenue Euge\u0300Ne Mascaux;Hainaut",
    "iso:country":"BE",
    "sg:address":"Avenue Eug\u00c8ne Mascaux 54",
    "sg:city":"Charleroi",
    "sg:classifiers":[
        {
            "category":"Cafe",
            "type":"Food & Drink"
        }
    ],
    "sg:phone":"+32 71 36 73 39",
    "sg:postcode":"6001",
    "sg:province":"Hainaut",
    "sg:tags":[
        "caf\u00e9s"
    ],
    "wof:name":"Caf\u00c9 Le Central",
    "wof:placetype":"venue"
},
  "geometry": {"coordinates":[4.4462981224,50.3988609314],"type":"Point"}
}