{
  "type": "Feature",
  "properties": {
    "addr:full":"Carri\u00e8re Du Parrain 37 Couvin (pesche) Namur 5660",
    "addr:housenumber":"37",
    "addr:postcode":"5660",
    "iso:country":"BE",
    "sg:address":"Carri\u00e8re Du Parrain 37",
    "sg:city":"Couvin (pesche)",
    "sg:classifiers":[
        {
            "category":"Personal",
            "subcategory":"Nail Salon",
            "type":"Services"
        }
    ],
    "sg:phone":"+32 477 68 75 55",
    "sg:postcode":"5660",
    "sg:province":"Namur",
    "sg:tags":[
        "pedicure"
    ],
    "wof:name":"Baudet F",
    "wof:placetype":"venue"
},
  "geometry": {"coordinates":[4.4616408348,50.0594444275],"type":"Point"}
}