{
  "type": "Feature",
  "properties": {
    "iso:country":"BE",
    "sg:address":"Square Cr\u00c9pin 2",
    "sg:city":"Rochefort",
    "sg:orig_category":"Notarissen",
    "sg:phone":"+32 84 21 10 10",
    "sg:postcode":"5580",
    "sg:province":"Namur",
    "wof:name":"Jacques Doicesco",
    "wof:placetype":"venue"
},
  "geometry": {"coordinates":[5.2202558517,50.1576156616],"type":"Point"}
}