{
  "type": "Feature",
  "properties": {
    "addr:full":"Avenue De Monte Carlo 9 Vorst/forest Bruxelles-Capitale 1190",
    "addr:housenumber":"9",
    "addr:postcode":"1190",
    "addr:street":"Avenue De Monte Carlo;/ Forest",
    "iso:country":"BE",
    "sg:address":"Avenue De Monte Carlo 9",
    "sg:city":"Vorst/forest",
    "sg:orig_category":"Plomberie, chauffage and installations sanitaires",
    "sg:phone":"+32 2 343 83 01",
    "sg:postcode":"1190",
    "sg:province":"Bruxelles-Capitale",
    "wof:name":"Alphamulti",
    "wof:placetype":"venue"
},
  "geometry": {"coordinates":[4.3216891289,50.8094329834],"type":"Point"}
}