{
  "type": "Feature",
  "properties": {
    "addr:full":"Rue De Gourdinne 2 Ham-sur-heure-nalinnes Hainaut 6120",
    "addr:housenumber":"2",
    "addr:postcode":"6120",
    "addr:street":"Rue De Gourdinne;Hainaut",
    "iso:country":"BE",
    "sg:address":"Rue De Gourdinne 2",
    "sg:city":"Ham-sur-heure-nalinnes",
    "sg:classifiers":[
        {
            "category":"Personal",
            "subcategory":"Beauty Salon",
            "type":"Services"
        }
    ],
    "sg:phone":"+32 71 21 66 03",
    "sg:postcode":"6120",
    "sg:province":"Hainaut",
    "sg:tags":[
        "de",
        "coiffure"
    ],
    "wof:name":"Alaifinitif",
    "wof:placetype":"venue"
},
  "geometry": {"coordinates":[4.445098877,50.3231811523],"type":"Point"}
}