{
  "type": "Feature",
  "properties": {
    "iso:country":"BE",
    "sg:address":"Rue Du Petit Harvengt 5",
    "sg:city":"Mons",
    "sg:orig_category":"Landbouwmachines Gh",
    "sg:phone":"+32 65 58 66 45",
    "sg:postcode":"7022",
    "sg:province":"Hainaut",
    "wof:name":"Danhiez",
    "wof:placetype":"venue"
},
  "geometry": {"coordinates":[4.0181078911,50.4045410156],"type":"Point"}
}