{
  "type": "Feature",
  "properties": {
    "addr:full":"Industriepark-zwijnaarde 3a Gent (zwijnaarde) Oost-Vlaanderen 9052",
    "addr:housenumber":"3a",
    "addr:postcode":"9052",
    "addr:street":"Industriepark-Zwijnaarde",
    "iso:country":"BE",
    "sg:address":"Industriepark-zwijnaarde 3a",
    "sg:city":"Gent (zwijnaarde)",
    "sg:classifiers":[
        {
            "category":"Professional",
            "subcategory":"Computer Services",
            "type":"Services"
        }
    ],
    "sg:phone":"+32 9 220 23 21",
    "sg:postcode":"9052",
    "sg:province":"Oost-Vlaanderen",
    "sg:tags":[
        "-",
        "processing",
        "data",
        "software"
    ],
    "wof:name":"Mips Nv",
    "wof:placetype":"venue"
},
  "geometry": {"coordinates":[3.7167270184,51.0002937317],"type":"Point"}
}