{
  "type": "Feature",
  "properties": {
    "addr:full":"Rue De Roucourt 108 P\u00e9ruwelz Hainaut 7600",
    "addr:housenumber":"108",
    "addr:postcode":"7600",
    "addr:street":"Rue De Roucourt",
    "iso:country":"BE",
    "sg:address":"Rue De Roucourt 108",
    "sg:city":"P\u00e9ruwelz",
    "sg:classifiers":[
        {
            "category":"Health Services",
            "subcategory":"Health Practitioner",
            "type":"Services"
        }
    ],
    "sg:phone":"+32 69 78 15 65",
    "sg:postcode":"7600",
    "sg:province":"Hainaut",
    "sg:tags":[
        "physiotherapist"
    ],
    "wof:name":"Desablin Bernard",
    "wof:placetype":"venue"
},
  "geometry": {"coordinates":[3.5879819393,50.5122947693],"type":"Point"}
}