{
  "type": "Feature",
  "properties": {
    "addr:full":"Rue Des Chasseurs A Pieds (bp5) 44 La Longueville 59570",
    "addr:housenumber":"44",
    "addr:postcode":"59570",
    "addr:street":"Rue Des Chasseurs A Pieds Bp5;La Longueville",
    "iso:country":"BE",
    "sg:address":"Rue Des Chasseurs A Pieds (bp5) 44",
    "sg:city":"La Longueville",
    "sg:classifiers":[
        {
            "category":"Utilities",
            "subcategory":"Refuse",
            "type":"Services"
        }
    ],
    "sg:postcode":"59570",
    "sg:tags":[
        "removal"
    ],
    "wof:name":"Demenagement Williame Sarl",
    "wof:placetype":"venue"
},
  "geometry": {"coordinates":[3.876914978,50.2842941284],"type":"Point"}
}