{
  "type": "Feature",
  "properties": {
    "iso:country":"BE",
    "sg:address":"Rue Sur Le Puits 10",
    "sg:city":"Oreye",
    "sg:orig_category":"Eleveurs and marchands de porcs. Eleveurs de bovins",
    "sg:phone":"+32 19 67 74 83",
    "sg:postcode":"4360",
    "sg:province":"Li\u00e8ge",
    "wof:name":"Clement Budo",
    "wof:placetype":"venue"
},
  "geometry": {"coordinates":[5.3249430656,50.7110595703],"type":"Point"}
}