{
  "type": "Feature",
  "properties": {
    "iso:country":"BE",
    "sg:address":"Moorselbaan 122",
    "sg:city":"Aalst",
    "sg:classifiers":[
        {
            "category":"Communications",
            "subcategory":"Television Station",
            "type":"Services"
        }
    ],
    "sg:phone":"+32 53 21 37 29",
    "sg:postcode":"9300",
    "sg:province":"Oost-Vlaanderen",
    "sg:tags":[
        "organ"
    ],
    "wof:name":"Muziekhandel Van De Moer-orgelmelodie",
    "wof:placetype":"venue"
},
  "geometry": {"coordinates":[4.0516381264,50.9422035217],"type":"Point"}
}