{
  "type": "Feature",
  "properties": {
    "iso:country":"BE",
    "sg:address":"Rue Lambillotte Joseph 9",
    "sg:city":"Charleroi (jumet)",
    "sg:classifiers":[
        {
            "category":"Retail",
            "subcategory":"Auto Repair",
            "type":"Services"
        }
    ],
    "sg:phone":"+32 71 34 32 23",
    "sg:postcode":"6040",
    "sg:province":"Hainaut",
    "sg:tags":[
        "automobile-body"
    ],
    "wof:name":"Topcars Sprl",
    "wof:placetype":"venue"
},
  "geometry": {"coordinates":[4.4361791611,50.4378051758],"type":"Point"}
}