{
  "type": "Feature",
  "properties": {
    "addr:full":"De Horeman 15 Arendonk Antwerpen 2370",
    "addr:housenumber":"15",
    "addr:postcode":"2370",
    "addr:street":"De Horeman",
    "iso:country":"BE",
    "sg:address":"De Horeman 15",
    "sg:city":"Arendonk",
    "sg:orig_category":"Meubelzaken, woning- and keukeninrichting Verlichting and huishoudartikelen",
    "sg:phone":"+32 14 67 76 70",
    "sg:postcode":"2370",
    "sg:province":"Antwerpen",
    "wof:name":"Bert Van Loon",
    "wof:placetype":"venue"
},
  "geometry": {"coordinates":[5.0929670334,51.3234291077],"type":"Point"}
}