{
  "type": "Feature",
  "properties": {
    "addr:full":"Architect Vanhoornelaan 31 Wevelgem West-Vlaanderen 8560",
    "addr:housenumber":"31",
    "addr:postcode":"8560",
    "addr:street":"Vanhoornelaan",
    "iso:country":"BE",
    "sg:address":"Architect Vanhoornelaan 31",
    "sg:city":"Wevelgem",
    "sg:orig_category":"Divers amusement Verhuur televisie- and audiovisuele apparatuur",
    "sg:phone":"+32 78 16 22 57",
    "sg:postcode":"8560",
    "sg:province":"West-Vlaanderen",
    "wof:name":"Marino",
    "wof:placetype":"venue"
},
  "geometry": {"coordinates":[3.1643741131,50.8354682922],"type":"Point"}
}