{
  "type": "Feature",
  "properties": {
    "iso:country":"BE",
    "sg:address":"Rue 't Serstevens 60",
    "sg:city":"Thuin",
    "sg:classifiers":[
        {
            "category":"Shopping",
            "subcategory":"Optician",
            "type":"Retail Goods"
        }
    ],
    "sg:phone":"+32 71 59 15 17",
    "sg:postcode":"6530",
    "sg:province":"Hainaut",
    "sg:tags":[
        "-"
    ],
    "wof:name":"Debienne Optique",
    "wof:placetype":"venue"
},
  "geometry": {"coordinates":[4.2838349342,50.341342926],"type":"Point"}
}