{
  "type": "Feature",
  "properties": {
    "addr:full":"Kustweg 101 Nieuwpoort West-Vlaanderen 8620",
    "addr:housenumber":"101",
    "addr:postcode":"8620",
    "addr:street":"Kustweg",
    "iso:country":"BE",
    "sg:address":"Kustweg 101",
    "sg:city":"Nieuwpoort",
    "sg:classifiers":[
        {
            "category":"Travel",
            "subcategory":"Resort",
            "type":"Entertainment"
        }
    ],
    "sg:phone":"+32 58 23 38 75",
    "sg:postcode":"8620",
    "sg:province":"West-Vlaanderen",
    "sg:tags":[
        "vacation"
    ],
    "wof:name":"Cdsca Lomb",
    "wof:placetype":"venue"
},
  "geometry": {"coordinates":[2.7486619949,51.1581764221],"type":"Point"}
}