{
  "type": "Feature",
  "properties": {
    "iso:country":"BE",
    "sg:address":"Chemin-rue 51",
    "sg:city":"Malmedy/malmedy",
    "sg:orig_category":"Poissonniers and \u00e9caillers",
    "sg:phone":"+32 80 77 00 20",
    "sg:postcode":"4960",
    "sg:province":"Li\u00e8ge",
    "wof:name":"Poisson. Petit P\u00cacheur",
    "wof:placetype":"venue"
},
  "geometry": {"coordinates":[6.0551772118,50.37657547],"type":"Point"}
}