{
  "type": "Feature",
  "properties": {
    "addr:full":"Zwaluwlaan 64 Wachtebeke Oost-Vlaanderen 9185",
    "addr:housenumber":"64",
    "addr:postcode":"9185",
    "addr:street":"Zwaluwlaan",
    "iso:country":"BE",
    "sg:address":"Zwaluwlaan 64",
    "sg:city":"Wachtebeke",
    "sg:orig_category":"Enseignement maternel and primaire",
    "sg:phone":"+32 9 345 90 20",
    "sg:postcode":"9185",
    "sg:province":"Oost-Vlaanderen",
    "wof:name":"B.s.g.o. 't Zwaluwnest",
    "wof:placetype":"venue"
},
  "geometry": {"coordinates":[3.8471400738,51.1647911072],"type":"Point"}
}