{
  "type": "Feature",
  "properties": {
    "addr:full":"Meersbloem Leupegem 21 Oudenaarde Oost-Vlaanderen 9700",
    "addr:housenumber":"21",
    "addr:postcode":"9700",
    "addr:street":"Leupegem",
    "iso:country":"BE",
    "sg:address":"Meersbloem Leupegem 21",
    "sg:city":"Oudenaarde",
    "sg:classifiers":[
        {
            "category":"Home & Garden",
            "subcategory":"Building Materials",
            "type":"Retail Goods"
        }
    ],
    "sg:phone":"+32 55 31 78 70",
    "sg:postcode":"9700",
    "sg:province":"Oost-Vlaanderen",
    "sg:tags":[
        "article",
        "-",
        "do-it-yourself"
    ],
    "wof:name":"Ottevaere Bouwmarkt Orga",
    "wof:placetype":"venue"
},
  "geometry": {"coordinates":[3.5996088982,50.8353042603],"type":"Point"}
}