{
  "type": "Feature",
  "properties": {
    "addr:full":"Waterstraat 18 Geel Antwerpen 2440",
    "addr:housenumber":"18",
    "addr:postcode":"2440",
    "addr:street":"Waterstraat",
    "iso:country":"BE",
    "sg:address":"Waterstraat 18",
    "sg:city":"Geel",
    "sg:orig_category":"M\u00e9decins and sp\u00e9cialistes",
    "sg:phone":"+32 14 58 93 23",
    "sg:postcode":"2440",
    "sg:province":"Antwerpen",
    "wof:name":"R. Mertens",
    "wof:placetype":"venue"
},
  "geometry": {"coordinates":[4.988202095,51.156917572],"type":"Point"}
}