{
  "type": "Feature",
  "properties": {
    "addr:full":"Avenue Fran\u00c7ois Cornesse 35 Aywaille Li\u00e8ge 4920",
    "addr:housenumber":"35",
    "addr:postcode":"4920",
    "addr:street":"Avenue Franc\u0327Ois Cornesse",
    "iso:country":"BE",
    "sg:address":"Avenue Fran\u00c7ois Cornesse 35",
    "sg:city":"Aywaille",
    "sg:orig_category":"Begrafeniswezen",
    "sg:phone":"+32 4 384 41 90",
    "sg:postcode":"4920",
    "sg:province":"Li\u00e8ge",
    "wof:name":"Pompes Fun\u00c8bres Lawarr\u00c9e",
    "wof:placetype":"venue"
},
  "geometry": {"coordinates":[5.6736149788,50.4744873047],"type":"Point"}
}