{
  "type": "Feature",
  "properties": {
    "addr:full":"Rue Kessels 34 Schaarbeek/schaerbeek Bruxelles-Capitale 1030",
    "addr:housenumber":"34",
    "addr:postcode":"1030",
    "addr:street":"Rue Kessels",
    "iso:country":"BE",
    "sg:address":"Rue Kessels 34",
    "sg:city":"Schaarbeek/schaerbeek",
    "sg:orig_category":"Studios photographiques",
    "sg:phone":"+32 2 215 19 62",
    "sg:postcode":"1030",
    "sg:province":"Bruxelles-Capitale",
    "wof:name":"Studio Pascal Lebrun",
    "wof:placetype":"venue"
},
  "geometry": {"coordinates":[4.3777618408,50.8618202209],"type":"Point"}
}