{
  "type": "Feature",
  "properties": {
    "addr:full":"Avenue Des Roses 4 Sint-genesius-rode Vlaams-Brabant 1640",
    "addr:housenumber":"4",
    "addr:postcode":"1640",
    "addr:street":"Avenue Des Roses",
    "iso:country":"BE",
    "sg:address":"Avenue Des Roses 4",
    "sg:city":"Sint-genesius-rode",
    "sg:orig_category":"Animations diverses",
    "sg:phone":"+32 2 358 12 69",
    "sg:postcode":"1640",
    "sg:province":"Vlaams-Brabant",
    "wof:name":"Bamba Festive Agency",
    "wof:placetype":"venue"
},
  "geometry": {"coordinates":[4.3898978233,50.747467041],"type":"Point"}
}