{
  "type": "Feature",
  "properties": {
    "iso:country":"BE",
    "sg:address":"Zepstraat 49",
    "sg:city":"Mechelen (hombeek)",
    "sg:classifiers":[
        {
            "category":"Health Services",
            "subcategory":"Health Practitioner",
            "type":"Services"
        }
    ],
    "sg:phone":"+32 15 41 39 83",
    "sg:postcode":"2811",
    "sg:province":"Antwerpen",
    "sg:tags":[
        "alternative",
        "therapy",
        "treatment"
    ],
    "wof:name":"Corbeel M",
    "wof:placetype":"venue"
},
  "geometry": {"coordinates":[4.4262771606,51.0097579956],"type":"Point"}
}