{
  "type": "Feature",
  "properties": {
    "addr:full":"Grote Bosstraat 109 Schaarbeek/schaerbeek Bruxelles-Capitale 1030",
    "addr:housenumber":"109",
    "addr:postcode":"1030",
    "addr:street":"Grote Bosstraat",
    "iso:country":"BE",
    "sg:address":"Grote Bosstraat 109",
    "sg:city":"Schaarbeek/schaerbeek",
    "sg:orig_category":"Bouwmaterialen Gh IJzerwaren, bouw- and verfmaterialen Verlichting and huishoudartikelen",
    "sg:phone":"+32 2 736 25 59",
    "sg:postcode":"1030",
    "sg:province":"Bruxelles-Capitale",
    "wof:name":"Van Caenegem",
    "wof:placetype":"venue"
},
  "geometry": {"coordinates":[4.3870940208,50.8546333313],"type":"Point"}
}