{
  "type": "Feature",
  "properties": {
    "iso:country":"BE",
    "sg:address":"Rue Du Wainage 213",
    "sg:city":"Farciennes",
    "sg:orig_category":"Boekhouders",
    "sg:postcode":"6240",
    "sg:province":"Hainaut",
    "wof:name":"Gian Franc Portinari",
    "wof:placetype":"venue"
},
  "geometry": {"coordinates":[4.5241208076,50.4338722229],"type":"Point"}
}