{
  "type": "Feature",
  "properties": {
    "addr:full":"Julien Mulliestraat 3 Moeskroen/mouscron Hainaut 7711",
    "addr:housenumber":"3",
    "addr:postcode":"7711",
    "addr:street":"Mulliestraat",
    "iso:country":"BE",
    "sg:address":"Julien Mulliestraat 3",
    "sg:city":"Moeskroen/mouscron",
    "sg:orig_category":"Dameskledingzaken",
    "sg:phone":"+32 56 48 55 85",
    "sg:postcode":"7711",
    "sg:province":"Hainaut",
    "wof:name":"Brigitte Nuttin",
    "wof:placetype":"venue"
},
  "geometry": {"coordinates":[3.3032488823,50.729221344],"type":"Point"}
}