{
  "type": "Feature",
  "properties": {
    "addr:full":"Chauss\u00e9e De Louvain 495 Wavre Brabant Wallon 1300",
    "addr:housenumber":"495;1300",
    "addr:street":"Chausse\u0301E De Louvain",
    "iso:country":"BE",
    "sg:address":"Chauss\u00e9e De Louvain 495",
    "sg:city":"Wavre",
    "sg:classifiers":[
        {
            "category":"Building & Trades",
            "subcategory":"Construction",
            "type":"Services"
        }
    ],
    "sg:phone":"+32 10 24 14 22",
    "sg:postcode":"1300",
    "sg:province":"Brabant Wallon",
    "sg:tags":[
        "flue"
    ],
    "wof:name":"Chemin\u00e9es & Feux",
    "wof:placetype":"venue"
},
  "geometry": {"coordinates":[4.6293740273,50.723274231],"type":"Point"}
}