{
  "type": "Feature",
  "properties": {
    "iso:country":"BE",
    "sg:address":"Rue Saint-gilles 48",
    "sg:city":"Li\u00c8ge",
    "sg:orig_category":"Blanchisseries and teintureries",
    "sg:phone":"+32 4 223 25 33",
    "sg:postcode":"4000",
    "sg:province":"Li\u00e8ge",
    "wof:name":"Jules Piel",
    "wof:placetype":"venue"
},
  "geometry": {"coordinates":[5.5663948059,50.6394004822],"type":"Point"}
}