{
  "type": "Feature",
  "properties": {
    "iso:country":"BE",
    "sg:address":"De Wulfstraat 4",
    "sg:city":"Assenede",
    "sg:orig_category":"Installation de serres, double vitrage and fen\u00eatres. Peinture. Rev\u00eatements pour sols and murs",
    "sg:phone":"+32 9 344 51 75",
    "sg:postcode":"9960",
    "sg:province":"Oost-Vlaanderen",
    "wof:name":"Dirk De Roo",
    "wof:placetype":"venue"
},
  "geometry": {"coordinates":[3.749161005,51.2259902954],"type":"Point"}
}