{
  "type": "Feature",
  "properties": {
    "iso:country":"BE",
    "sg:address":"Limbosbaan 7",
    "sg:city":"Grimbergen",
    "sg:orig_category":"Industri\u00eble and commerci\u00eble bouw",
    "sg:phone":"+32 2 269 79 27",
    "sg:postcode":"1852",
    "sg:province":"Vlaams-Brabant",
    "wof:name":"Gilbert Goossens",
    "wof:placetype":"venue"
},
  "geometry": {"coordinates":[4.3604388237,50.9516677856],"type":"Point"}
}