{
  "type": "Feature",
  "properties": {
    "iso:country":"BE",
    "sg:address":"Boulevard Dolez 67",
    "sg:city":"Mons",
    "sg:orig_category":"Avocats and conseillers juridiques",
    "sg:phone":"+32 65 34 63 46",
    "sg:postcode":"7000",
    "sg:province":"Hainaut",
    "wof:name":"B. Compagnion",
    "wof:placetype":"venue"
},
  "geometry": {"coordinates":[3.9549260139,50.4483680725],"type":"Point"}
}