{
  "type": "Feature",
  "properties": {
    "iso:country":"BE",
    "sg:address":"Rue Long Pont 18",
    "sg:city":"Lens",
    "sg:classifiers":[
        {
            "category":"Arena",
            "subcategory":"Sports Club",
            "type":"Entertainment"
        }
    ],
    "sg:phone":"+32 65 22 82 38",
    "sg:postcode":"7870",
    "sg:province":"Hainaut",
    "sg:tags":[
        "de"
    ],
    "wof:name":"J.c. Molenbeek",
    "wof:placetype":"venue"
},
  "geometry": {"coordinates":[3.9263920784,50.562412262],"type":"Point"}
}