{
  "type": "Feature",
  "properties": {
    "addr:full":"Steenweg Op Mol 81 Turnhout Antwerpen 2300",
    "addr:housenumber":"81",
    "addr:postcode":"2300",
    "addr:street":"Steenweg Op Mol",
    "iso:country":"BE",
    "sg:address":"Steenweg Op Mol 81",
    "sg:city":"Turnhout",
    "sg:classifiers":[
        {
            "category":"Personal",
            "subcategory":"Beauty Salon",
            "type":"Services"
        }
    ],
    "sg:phone":"+32 14 43 95 29",
    "sg:postcode":"2300",
    "sg:province":"Antwerpen",
    "wof:name":"Mireille",
    "wof:placetype":"venue"
},
  "geometry": {"coordinates":[4.9626188278,51.3216018677],"type":"Point"}
}