{
  "type": "Feature",
  "properties": {
    "addr:full":"Amersveldestraat 122 Hooglede West-Vlaanderen 8830",
    "addr:housenumber":"122",
    "addr:postcode":"8830",
    "addr:street":"Amersveldestraat",
    "iso:country":"BE",
    "sg:address":"Amersveldestraat 122",
    "sg:city":"Hooglede",
    "sg:classifiers":[
        {
            "category":"Bars & Pubs",
            "type":"Food & Drink"
        }
    ],
    "sg:phone":"+32 51 70 00 88",
    "sg:postcode":"8830",
    "sg:province":"West-Vlaanderen",
    "wof:name":"Hof Van Commerce",
    "wof:placetype":"venue"
},
  "geometry": {"coordinates":[3.0287599564,51.0031204224],"type":"Point"}
}