{
  "type": "Feature",
  "properties": {
    "iso:country":"BE",
    "sg:address":"Avenue Du Premier Empire 2-4",
    "sg:city":"Fleurus",
    "sg:classifiers":[
        {
            "category":"Organizations",
            "subcategory":"Professional Association",
            "type":"Services"
        }
    ],
    "sg:phone":"+32 71 38 81 93",
    "sg:postcode":"6220",
    "sg:province":"Hainaut",
    "sg:tags":[
        "organisation",
        "seminar"
    ],
    "wof:name":"Business Class Sa",
    "wof:placetype":"venue"
},
  "geometry": {"coordinates":[4.50025177,50.4469566345],"type":"Point"}
}