{
  "type": "Feature",
  "properties": {
    "iso:country":"BE",
    "sg:address":"Rue Des Mini\u00c8res 56",
    "sg:city":"Verviers",
    "sg:orig_category":"Apotheken",
    "sg:phone":"+32 87 22 92 38",
    "sg:postcode":"4800",
    "sg:province":"Li\u00e8ge",
    "wof:name":"Pharmacie Bellefontaine",
    "wof:placetype":"venue"
},
  "geometry": {"coordinates":[5.8586559296,50.5875740051],"type":"Point"}
}