{
  "type": "Feature",
  "properties": {
    "iso:country":"BE",
    "sg:address":"Avenue Marcel Thiry 216",
    "sg:city":"Brussel/bruxelles",
    "sg:orig_category":"Informaticaconsulenten",
    "sg:phone":"+32 2 774 42 11",
    "sg:postcode":"1200",
    "sg:province":"Bruxelles-Capitale",
    "wof:name":"Price Waterhouse Coopers",
    "wof:placetype":"venue"
},
  "geometry": {"coordinates":[4.4321532249,50.8567886353],"type":"Point"}
}