{
  "type": "Feature",
  "properties": {
    "addr:full":"Stientjesstraat 68 Anzegem West-Vlaanderen 8570",
    "addr:housenumber":"68",
    "addr:postcode":"8570",
    "addr:street":"Stientjesstraat",
    "iso:country":"BE",
    "sg:address":"Stientjesstraat 68",
    "sg:city":"Anzegem",
    "sg:orig_category":"Installation \u00e9lectrique industrielle",
    "sg:phone":"+32 56 69 40 10",
    "sg:postcode":"8570",
    "sg:province":"West-Vlaanderen",
    "wof:name":"Db Electronics",
    "wof:placetype":"venue"
},
  "geometry": {"coordinates":[3.452892065,50.8393707275],"type":"Point"}
}