{
  "type": "Feature",
  "properties": {
    "addr:full":"Rue D\u00c9sir\u00c9 Maroille 27b Frameries Hainaut 7080",
    "addr:housenumber":"27b",
    "addr:postcode":"7080",
    "addr:street":"Rue De\u0301Sire\u0301 Maroille",
    "iso:country":"BE",
    "sg:address":"Rue D\u00c9sir\u00c9 Maroille 27b",
    "sg:city":"Frameries",
    "sg:classifiers":[
        {
            "category":"Fast Food",
            "type":"Food & Drink"
        }
    ],
    "sg:phone":"+32 65 66 12 37",
    "sg:postcode":"7080",
    "sg:province":"Hainaut",
    "sg:tags":[
        "huis",
        "aan",
        "levering",
        "meeneem",
        "restaurant"
    ],
    "wof:name":"Restaurant Marco Polo",
    "wof:placetype":"venue"
},
  "geometry": {"coordinates":[3.8959159851,50.4093399048],"type":"Point"}
}