{
  "type": "Feature",
  "properties": {
    "iso:country":"BE",
    "sg:address":"Dikkebusstraat 140",
    "sg:city":"Heuvelland",
    "sg:orig_category":"Zalen voor culturele evenementen",
    "sg:phone":"+32 57 44 68 86",
    "sg:postcode":"8958",
    "sg:province":"West-Vlaanderen",
    "wof:name":"Galerij De Queeste",
    "wof:placetype":"venue"
},
  "geometry": {"coordinates":[2.7723040581,50.7892684937],"type":"Point"}
}