{
  "type": "Feature",
  "properties": {
    "iso:country":"BE",
    "sg:address":"Poekstraat 7",
    "sg:city":"Gent",
    "sg:orig_category":"Rundveehouders",
    "sg:phone":"+32 9 226 91 92",
    "sg:postcode":"9031",
    "sg:province":"Oost-Vlaanderen",
    "wof:name":"Valere Cocquyt",
    "wof:placetype":"venue"
},
  "geometry": {"coordinates":[3.6114630699,51.0707435608],"type":"Point"}
}