{
  "type": "Feature",
  "properties": {
    "iso:country":"BE",
    "sg:address":"Kuringersteenweg 283 Box 1",
    "sg:city":"Hasselt",
    "sg:classifiers":[
        {
            "category":"Professional",
            "subcategory":"Advertising",
            "type":"Services"
        }
    ],
    "sg:phone":"+32 11 35 25 67",
    "sg:postcode":"3500",
    "sg:province":"Limburg",
    "sg:tags":[
        "item",
        "-",
        "business",
        "gift",
        "promotional"
    ],
    "wof:name":"Ch\u00e2teau Du Monde",
    "wof:placetype":"venue"
},
  "geometry": {"coordinates":[5.31417799,50.9376411438],"type":"Point"}
}