{
  "type": "Feature",
  "properties": {
    "addr:full":"Chauss\u00c9e De Louvain 78 Sint-joost-ten-node/saint-josse-ten-noode Bruxelles-Capitale 1210",
    "addr:housenumber":"78",
    "addr:postcode":"1210",
    "addr:street":"Chausse\u0301E De Louvain",
    "iso:country":"BE",
    "sg:address":"Chauss\u00c9e De Louvain 78",
    "sg:city":"Sint-joost-ten-node/saint-josse-ten-noode",
    "sg:orig_category":"Epiceries",
    "sg:phone":"+32 2 217 09 34",
    "sg:postcode":"1210",
    "sg:province":"Bruxelles-Capitale",
    "wof:name":"Maison Dilan",
    "wof:placetype":"venue"
},
  "geometry": {"coordinates":[4.372882843,50.8497886658],"type":"Point"}
}