{
  "type": "Feature",
  "properties": {
    "iso:country":"BE",
    "sg:address":"Rue De L'egalit\u00c9 8",
    "sg:city":"Frameries",
    "sg:orig_category":"Herstellingen and onderhoud van auto's Voertuigen",
    "sg:phone":"+32 65 66 38 73",
    "sg:postcode":"7080",
    "sg:province":"Hainaut",
    "wof:name":"Garage Laiche",
    "wof:placetype":"venue"
},
  "geometry": {"coordinates":[3.8879680634,50.3912467957],"type":"Point"}
}