{
  "type": "Feature",
  "properties": {
    "iso:country":"BE",
    "sg:address":"Ida Vermeulenstraat 21",
    "sg:city":"Boortmeerbeek (hever)",
    "sg:classifiers":[
        {
            "category":"Professional",
            "subcategory":"Detective & Security Services",
            "type":"Services"
        }
    ],
    "sg:phone":"+32 15 50 99 99",
    "sg:postcode":"3191",
    "sg:province":"Vlaams-Brabant",
    "sg:tags":[
        "door",
        "videophones",
        "operating",
        "equipment"
    ],
    "wof:name":"@comittel Bvba",
    "wof:placetype":"venue"
},
  "geometry": {"coordinates":[4.553123951,50.9828987122],"type":"Point"}
}