{
  "type": "Feature",
  "properties": {
    "iso:country":"BE",
    "sg:address":"Gentsesteenweg 262",
    "sg:city":"Sint-jans-molenbeek/molenbeek-saint-jean",
    "sg:orig_category":"Diensten voor huisdieren",
    "sg:phone":"+32 2 410 39 14",
    "sg:postcode":"1080",
    "sg:province":"Bruxelles-Capitale",
    "wof:name":"Toutoutif",
    "wof:placetype":"venue"
},
  "geometry": {"coordinates":[4.3157501221,50.8577919006],"type":"Point"}
}