{
  "type": "Feature",
  "properties": {
    "iso:country":"BE",
    "sg:address":"Stationstraat 196",
    "sg:city":"Oostende (zandvoorde)",
    "sg:classifiers":[
        {
            "category":"Building & Trades",
            "subcategory":"Equipment Rental",
            "type":"Services"
        }
    ],
    "sg:phone":"+32 59 50 56 77",
    "sg:postcode":"8400",
    "sg:province":"West-Vlaanderen",
    "sg:tags":[
        "crane",
        "-"
    ],
    "wof:name":"Veryser G",
    "wof:placetype":"venue"
},
  "geometry": {"coordinates":[2.9780099392,51.2105255127],"type":"Point"}
}