{
  "type": "Feature",
  "properties": {
    "addr:full":"Rue St. Donas 5 Mettet Namur 5640",
    "addr:housenumber":"5",
    "addr:postcode":"5640",
    "addr:street":"Rue St. Donas",
    "iso:country":"BE",
    "sg:address":"Rue St. Donas 5",
    "sg:city":"Mettet",
    "sg:orig_category":"Installation de menuiserie en bois and plastique. Travaux de finition and nettoyage de b\u00e2timents",
    "sg:phone":"+32 71 72 87 35",
    "sg:postcode":"5640",
    "sg:province":"Namur",
    "wof:name":"Fabrich\u00c2let Groupe Oliwood",
    "wof:placetype":"venue"
},
  "geometry": {"coordinates":[4.6537299156,50.3033409119],"type":"Point"}
}