{
  "type": "Feature",
  "properties": {
    "addr:full":"Varsenareweg 29 Jabbeke West-Vlaanderen 8490",
    "addr:housenumber":"29",
    "addr:postcode":"8490",
    "addr:street":"Varsenareweg",
    "iso:country":"BE",
    "sg:address":"Varsenareweg 29",
    "sg:city":"Jabbeke",
    "sg:classifiers":[
        {
            "category":"Fast Food",
            "type":"Food & Drink"
        }
    ],
    "sg:phone":"+32 50 81 43 10",
    "sg:postcode":"8490",
    "sg:province":"West-Vlaanderen",
    "sg:tags":[
        "meeneem",
        "restaurant"
    ],
    "wof:name":"New China",
    "wof:placetype":"venue"
},
  "geometry": {"coordinates":[3.1087789536,51.1838111877],"type":"Point"}
}