{
  "type": "Feature",
  "properties": {
    "iso:country":"BE",
    "sg:address":"Rue Hautes Calenges 62",
    "sg:city":"Namur",
    "sg:orig_category":"Mobiele kappers",
    "sg:phone":"+32 81 44 66 19",
    "sg:postcode":"5020",
    "sg:province":"Namur",
    "wof:name":"Thibaut Val\u00c9rie",
    "wof:placetype":"venue"
},
  "geometry": {"coordinates":[4.7952418327,50.4352035522],"type":"Point"}
}