{
  "type": "Feature",
  "properties": {
    "iso:country":"BE",
    "sg:address":"Pourrain 11",
    "sg:city":"Gesves",
    "sg:classifiers":[
        {
            "category":"Airport",
            "subcategory":"General Aviation",
            "type":"Transportation"
        }
    ],
    "sg:phone":"+32 83 67 85 67",
    "sg:postcode":"5340",
    "sg:province":"Namur",
    "sg:tags":[
        "transport"
    ],
    "wof:name":"Condroz Airport Service Sprl",
    "wof:placetype":"venue"
},
  "geometry": {"coordinates":[5.0593519211,50.3936691284],"type":"Point"}
}