{
  "type": "Feature",
  "properties": {
    "iso:country":"BE",
    "sg:address":"Rue Saint-eloi 13",
    "sg:city":"Waremme",
    "sg:orig_category":"Instituts de beaut\u00e9",
    "sg:phone":"+32 19 32 83 21",
    "sg:postcode":"4300",
    "sg:province":"Li\u00e8ge",
    "wof:name":"Sabine Ebroin",
    "wof:placetype":"venue"
},
  "geometry": {"coordinates":[5.2656607628,50.6966552734],"type":"Point"}
}