{
  "type": "Feature",
  "properties": {
    "addr:full":"Noordzandstraat 1bis Brugge West-Vlaanderen 8000",
    "addr:housenumber":"1bis",
    "addr:postcode":"8000",
    "addr:street":"Noordzandstraat",
    "iso:country":"BE",
    "sg:address":"Noordzandstraat 1bis",
    "sg:city":"Brugge",
    "sg:classifiers":[
        {
            "category":"Food & Beverages",
            "subcategory":"Chocolate",
            "type":"Retail Goods"
        }
    ],
    "sg:phone":"+32 50 33 59 04",
    "sg:postcode":"8000",
    "sg:province":"West-Vlaanderen",
    "sg:tags":[
        "confectionery",
        "-"
    ],
    "wof:name":"Van Tilborgh",
    "wof:placetype":"venue"
},
  "geometry": {"coordinates":[3.221198082,51.2083053589],"type":"Point"}
}