{
  "type": "Feature",
  "properties": {
    "iso:country":"BE",
    "sg:address":"Ressegemstraat 54",
    "sg:city":"Herzele",
    "sg:orig_category":"Woningbouw",
    "sg:phone":"+32 53 62 23 12",
    "sg:postcode":"9551",
    "sg:province":"Oost-Vlaanderen",
    "wof:name":"Noel Van Herreweghe",
    "wof:placetype":"venue"
},
  "geometry": {"coordinates":[3.9059419632,50.8906097412],"type":"Point"}
}