{
  "type": "Feature",
  "properties": {
    "iso:country":"BE",
    "sg:address":"Grote Baan 201",
    "sg:city":"Beveren",
    "sg:orig_category":"Lingerie and ondergoed Textiel",
    "sg:phone":"+32 3 775 26 19",
    "sg:postcode":"9120",
    "sg:province":"Oost-Vlaanderen",
    "wof:name":"Huis Romantica",
    "wof:placetype":"venue"
},
  "geometry": {"coordinates":[4.2815608978,51.2200508118],"type":"Point"}
}