{
  "type": "Feature",
  "properties": {
    "addr:full":"Burg. Jos. Lievensstraat 14 Zedelgem West-Vlaanderen 8210",
    "addr:housenumber":"14",
    "addr:postcode":"8210",
    "addr:street":"Burg.;Lievensstraat",
    "iso:country":"BE",
    "sg:address":"Burg. Jos. Lievensstraat 14",
    "sg:city":"Zedelgem",
    "sg:orig_category":"Dierenartsen",
    "sg:phone":"+32 50 20 07 97",
    "sg:postcode":"8210",
    "sg:province":"West-Vlaanderen",
    "wof:name":"Paul Snauwaert",
    "wof:placetype":"venue"
},
  "geometry": {"coordinates":[3.1350231171,51.1412200928],"type":"Point"}
}