{
  "type": "Feature",
  "properties": {
    "addr:full":"Rue De Savoie 18 Bruxelles (saint-gilles) Bruxelles-Capitale 1060",
    "addr:housenumber":"18",
    "addr:postcode":"1060",
    "addr:street":"Rue De Savoie",
    "iso:country":"BE",
    "sg:address":"Rue De Savoie 18",
    "sg:city":"Bruxelles (saint-gilles)",
    "sg:classifiers":[
        {
            "category":"Professional",
            "subcategory":"Lawyer & Legal Services",
            "type":"Services"
        }
    ],
    "sg:phone":"+32 2 543 08 90",
    "sg:postcode":"1060",
    "sg:province":"Bruxelles-Capitale",
    "wof:name":"Jeanray P",
    "wof:placetype":"venue"
},
  "geometry": {"coordinates":[4.3475828171,50.8244094849],"type":"Point"}
}