{
  "type": "Feature",
  "properties": {
    "iso:country":"BE",
    "sg:address":"Putteveld 61",
    "sg:city":"Meise",
    "sg:orig_category":"Sportclubs",
    "sg:phone":"+32 2 269 03 92",
    "sg:postcode":"1860",
    "sg:province":"Vlaams-Brabant",
    "wof:name":"Stadium Badminton Brussel",
    "wof:placetype":"venue"
},
  "geometry": {"coordinates":[4.3359460831,50.957244873],"type":"Point"}
}