{
  "type": "Feature",
  "properties": {
    "iso:country":"BE",
    "sg:address":"Turnhoutsebaan 181",
    "sg:city":"Kasterlee",
    "sg:orig_category":"Catering and organisatie van feesten Fast food and meeneem restaurants Organisatie van beurzen, cong",
    "sg:phone":"+32 14 85 02 24",
    "sg:postcode":"2460",
    "sg:province":"Antwerpen",
    "wof:name":"Hof Ter Rielen",
    "wof:placetype":"venue"
},
  "geometry": {"coordinates":[4.9617948532,51.256652832],"type":"Point"}
}