{
  "type": "Feature",
  "properties": {
    "addr:full":"Kerkstraat 114 Nieuwerkerken Limburg 3850",
    "addr:housenumber":"114",
    "addr:postcode":"3850",
    "addr:street":"Kerkstraat",
    "iso:country":"BE",
    "sg:address":"Kerkstraat 114",
    "sg:city":"Nieuwerkerken",
    "sg:classifiers":[
        {
            "category":"Banks & Credit Unions",
            "subcategory":"Investment Brokerage",
            "type":"Services"
        }
    ],
    "sg:phone":"+32 11 68 14 35",
    "sg:postcode":"3850",
    "sg:province":"Limburg",
    "sg:tags":[
        "lottery",
        "pool"
    ],
    "wof:name":"D.r.-shop Bvba",
    "wof:placetype":"venue"
},
  "geometry": {"coordinates":[5.1933140755,50.8653068542],"type":"Point"}
}