{
  "type": "Feature",
  "properties": {
    "addr:full":"Rue Monfort 108 Ans Li\u00e8ge 4430",
    "addr:housenumber":"108",
    "addr:postcode":"4430",
    "addr:street":"Rue Monfort",
    "iso:country":"BE",
    "sg:address":"Rue Monfort 108",
    "sg:city":"Ans",
    "sg:classifiers":[
        {
            "category":"Structure",
            "subcategory":"Building",
            "type":"Public Place"
        }
    ],
    "sg:phone":"+32 9 231 31 31",
    "sg:postcode":"4430",
    "sg:province":"Li\u00e8ge",
    "sg:tags":[
        "apartment"
    ],
    "wof:name":"Eric De Winter B.v.b.a.",
    "wof:placetype":"venue"
},
  "geometry": {"coordinates":[3.7476680279,51.0383148193],"type":"Point"}
}