{
  "type": "Feature",
  "properties": {
    "addr:full":"Vitsstraat 91 Buggenhout Oost-Vlaanderen 9255",
    "addr:housenumber":"91",
    "addr:postcode":"9255",
    "addr:street":"Vitsstraat",
    "iso:country":"BE",
    "sg:address":"Vitsstraat 91",
    "sg:city":"Buggenhout",
    "sg:classifiers":[
        {
            "category":"Health Services",
            "subcategory":"Doctor",
            "type":"Services"
        }
    ],
    "sg:phone":"+32 52 34 06 68",
    "sg:postcode":"9255",
    "sg:province":"Oost-Vlaanderen",
    "sg:tags":[
        "medicinephysicians",
        "surgeon"
    ],
    "wof:name":"Bellon J",
    "wof:placetype":"venue"
},
  "geometry": {"coordinates":[4.2085800171,51.0189208984],"type":"Point"}
}