{
  "type": "Feature",
  "properties": {
    "iso:country":"BE",
    "sg:address":"Place Communale 21",
    "sg:city":"Rixensart (genval)",
    "sg:classifiers":[
        {
            "category":"Professional",
            "subcategory":"Testing Lab",
            "type":"Services"
        }
    ],
    "sg:phone":"+32 2 653 80 52",
    "sg:postcode":"1332",
    "sg:province":"Brabant Wallon",
    "sg:tags":[
        "chemist"
    ],
    "wof:name":"Pacco",
    "wof:placetype":"venue"
},
  "geometry": {"coordinates":[4.4990930557,50.7158737183],"type":"Point"}
}