{
  "type": "Feature",
  "properties": {
    "addr:full":"Place Des Martyrs 11 Dour Hainaut 7370",
    "addr:housenumber":"11",
    "addr:postcode":"7370",
    "addr:street":"Place Des Martyrs;Hainaut",
    "iso:country":"BE",
    "sg:address":"Place Des Martyrs 11",
    "sg:city":"Dour",
    "sg:classifiers":[
        {
            "category":"Cafe",
            "type":"Food & Drink"
        }
    ],
    "sg:phone":"+32 65 65 31 68",
    "sg:postcode":"7370",
    "sg:province":"Hainaut",
    "sg:tags":[
        "caf\u00e9s"
    ],
    "wof:name":"Caf\u00c9 Le Grand Dour",
    "wof:placetype":"venue"
},
  "geometry": {"coordinates":[3.7818500996,50.4009094238],"type":"Point"}
}