{
  "type": "Feature",
  "properties": {
    "addr:full":"Rue Du Chaufour 6 Meix-devant-virton (villers-la-loue) Luxembourg 6769",
    "addr:housenumber":"6",
    "addr:postcode":"6769",
    "addr:street":"Rue Du Chaufour",
    "iso:country":"BE",
    "sg:address":"Rue Du Chaufour 6",
    "sg:city":"Meix-devant-virton (villers-la-loue)",
    "sg:classifiers":[
        {
            "category":"Arts & Performance",
            "subcategory":"Art Gallery",
            "type":"Entertainment"
        }
    ],
    "sg:phone":"+32 63 57 75 77",
    "sg:postcode":"6769",
    "sg:province":"Luxembourg",
    "wof:name":"Jacob J.e.l.",
    "wof:placetype":"venue"
},
  "geometry": {"coordinates":[5.4861831665,49.5852470398],"type":"Point"}
}