{
  "type": "Feature",
  "properties": {
    "iso:country":"BE",
    "sg:address":"Haardstraat 8",
    "sg:city":"Moeskroen/mouscron",
    "sg:orig_category":"Installatie van houten of kunststof schrijnwerk",
    "sg:phone":"+32 56 34 59 58",
    "sg:postcode":"7700",
    "sg:province":"Hainaut",
    "wof:name":"Thierry Boitte",
    "wof:placetype":"venue"
},
  "geometry": {"coordinates":[3.2323200703,50.7400932312],"type":"Point"}
}