{
  "type": "Feature",
  "properties": {
    "addr:full":"Rue Antoine Cuvelier 20 Chaudfontaine (embourg) Li\u00e8ge 4053",
    "addr:housenumber":"20",
    "addr:postcode":"4053",
    "addr:street":"Rue Antoine Cuvelier",
    "iso:country":"BE",
    "sg:address":"Rue Antoine Cuvelier 20",
    "sg:city":"Chaudfontaine (embourg)",
    "sg:classifiers":[
        {
            "category":"Building & Trades",
            "subcategory":"Landscaping Services",
            "type":"Services"
        }
    ],
    "sg:phone":"+32 477 53 58 01",
    "sg:postcode":"4053",
    "sg:province":"Li\u00e8ge",
    "sg:tags":[
        "gardening",
        "garden",
        "maintenance"
    ],
    "wof:name":"Madenspacher B",
    "wof:placetype":"venue"
},
  "geometry": {"coordinates":[5.6093797684,50.590473175],"type":"Point"}
}