{
  "type": "Feature",
  "properties": {
    "addr:full":"Nieuwbrugstraat 75 Machelen Vlaams-Brabant 1830",
    "addr:housenumber":"75",
    "addr:postcode":"1830",
    "addr:street":"Nieuwbrugstraat",
    "iso:country":"BE",
    "sg:address":"Nieuwbrugstraat 75",
    "sg:city":"Machelen",
    "sg:classifiers":[
        {
            "category":"Military Area",
            "subcategory":"Air Force Base",
            "type":"Public Place"
        }
    ],
    "sg:phone":"+32 2 251 31 76",
    "sg:postcode":"1830",
    "sg:province":"Vlaams-Brabant",
    "sg:tags":[
        "fire",
        "protection"
    ],
    "wof:name":"Jean Muselle Nv",
    "wof:placetype":"venue"
},
  "geometry": {"coordinates":[4.4267058372,50.9098358154],"type":"Point"}
}