{
  "type": "Feature",
  "properties": {
    "addr:full":"Rue Emile Baudrux 4 Habay (habay-la-neuve) Luxembourg 6720",
    "addr:housenumber":"4",
    "addr:postcode":"6720",
    "addr:street":"Rue Emile Baudrux",
    "iso:country":"BE",
    "sg:address":"Rue Emile Baudrux 4",
    "sg:city":"Habay (habay-la-neuve)",
    "sg:classifiers":[
        {
            "category":"Building & Trades",
            "subcategory":"Pest Control",
            "type":"Services"
        }
    ],
    "sg:phone":"+32 63 42 28 75",
    "sg:postcode":"6720",
    "sg:province":"Luxembourg",
    "sg:tags":[
        "painting",
        "contractor"
    ],
    "wof:name":"Moraux-gr\u00e9visse Sprl",
    "wof:placetype":"venue"
},
  "geometry": {"coordinates":[5.6468100548,49.7278633118],"type":"Point"}
}