{
  "type": "Feature",
  "properties": {
    "iso:country":"BE",
    "sg:address":"Rue Florikosse 37",
    "sg:city":"Verviers",
    "sg:orig_category":"Installation \u00e9lectrique r\u00e9sidentielle",
    "sg:phone":"+32 87 22 18 59",
    "sg:postcode":"4802",
    "sg:province":"Li\u00e8ge",
    "wof:name":"Didier Prickartz",
    "wof:placetype":"venue"
},
  "geometry": {"coordinates":[5.8671250343,50.5714111328],"type":"Point"}
}