{
  "type": "Feature",
  "properties": {
    "addr:full":"Rue De La V\u00e9nerie 22 Bruxelles (watermael-boitsfort) Bruxelles-Capitale 1170",
    "addr:housenumber":"22",
    "addr:postcode":"1170",
    "addr:street":"Rue De La Ve\u0301Nerie",
    "iso:country":"BE",
    "sg:address":"Rue De La V\u00e9nerie 22",
    "sg:city":"Bruxelles (watermael-boitsfort)",
    "sg:classifiers":[
        {
            "category":"Utilities",
            "subcategory":"Telephone",
            "type":"Services"
        }
    ],
    "sg:phone":"+32 2 663 81 00",
    "sg:postcode":"1170",
    "sg:province":"Bruxelles-Capitale",
    "sg:tags":[
        "-",
        "internet"
    ],
    "wof:name":"Kjerag",
    "wof:placetype":"venue"
},
  "geometry": {"coordinates":[4.4188981056,50.7974662781],"type":"Point"}
}