{
  "type": "Feature",
  "properties": {
    "addr:full":"Lepelstraat 18b101 Sint-truiden Limburg 3800",
    "addr:housenumber":"18b101",
    "addr:postcode":"3800",
    "addr:street":"Lepelstraat",
    "iso:country":"BE",
    "sg:address":"Lepelstraat 18b101",
    "sg:city":"Sint-truiden",
    "sg:orig_category":"Informaticaconsulenten",
    "sg:phone":"+32 11 70 78 96",
    "sg:postcode":"3800",
    "sg:province":"Limburg",
    "wof:name":"I.l.s.automatisering",
    "wof:placetype":"venue"
},
  "geometry": {"coordinates":[5.1847047806,50.8115310669],"type":"Point"}
}