{
  "type": "Feature",
  "properties": {
    "iso:country":"BE",
    "sg:address":"Rue De La Gare 5",
    "sg:city":"Eghez\u00e9e",
    "sg:classifiers":[
        {
            "category":"Retail",
            "subcategory":"Event Space",
            "type":"Services"
        }
    ],
    "sg:phone":"+32 81 51 06 46",
    "sg:postcode":"5310",
    "sg:province":"Namur",
    "sg:tags":[
        "rental",
        "-",
        "hall"
    ],
    "wof:name":"Coges Asbl",
    "wof:placetype":"venue"
},
  "geometry": {"coordinates":[4.9102640152,50.5942230225],"type":"Point"}
}