{
  "type": "Feature",
  "properties": {
    "iso:country":"BE",
    "sg:address":"Francis De Meeuslaan 4",
    "sg:city":"Maldegem",
    "sg:classifiers":[
        {
            "category":"Shopping",
            "subcategory":"Bicycles & Sporting Goods",
            "type":"Retail Goods"
        }
    ],
    "sg:phone":"+32 50 71 48 75",
    "sg:postcode":"9990",
    "sg:province":"Oost-Vlaanderen",
    "sg:tags":[
        "-"
    ],
    "wof:name":"De Vogelaere M",
    "wof:placetype":"venue"
},
  "geometry": {"coordinates":[3.4166839123,51.1935653687],"type":"Point"}
}