{
  "type": "Feature",
  "properties": {
    "iso:country":"BE",
    "sg:address":"Veerledorp 52",
    "sg:city":"Laakdal (veerle)",
    "sg:classifiers":[
        {
            "category":"Juice Bar",
            "subcategory":"None",
            "type":"Food & Drink"
        }
    ],
    "sg:phone":"+32 14 84 13 67",
    "sg:postcode":"2431",
    "sg:province":"Antwerpen",
    "sg:tags":[
        "water",
        "soft"
    ],
    "wof:name":"Rens Voeding Nv",
    "wof:placetype":"venue"
},
  "geometry": {"coordinates":[4.9876461029,51.0701713562],"type":"Point"}
}