{
  "type": "Feature",
  "properties": {
    "addr:full":"Geelseweg 30a Olen Antwerpen 2250",
    "addr:housenumber":"30a",
    "addr:postcode":"2250",
    "addr:street":"Geelseweg",
    "iso:country":"BE",
    "sg:address":"Geelseweg 30a",
    "sg:city":"Olen",
    "sg:classifiers":[
        {
            "category":"Utilities",
            "subcategory":"Water",
            "type":"Services"
        }
    ],
    "sg:phone":"+32 14 25 70 80",
    "sg:postcode":"2250",
    "sg:province":"Antwerpen",
    "sg:tags":[
        "filter",
        "treatment"
    ],
    "wof:name":"Ecowater Systems Europe Nv",
    "wof:placetype":"venue"
},
  "geometry": {"coordinates":[4.9086499214,51.1534614563],"type":"Point"}
}