{
  "type": "Feature",
  "properties": {
    "iso:country":"BE",
    "sg:address":"Beatrijslaan 56",
    "sg:city":"Rotselaar",
    "sg:classifiers":[
        {
            "category":"Insurance",
            "subcategory":"Insurance Agent",
            "type":"Services"
        }
    ],
    "sg:phone":"+32 16 58 14 63",
    "sg:postcode":"3110",
    "sg:province":"Vlaams-Brabant",
    "sg:tags":[
        "verzekeringsmakelaars",
        "expert"
    ],
    "wof:name":"Johan Vos",
    "wof:placetype":"venue"
},
  "geometry": {"coordinates":[4.7606091499,50.9594230652],"type":"Point"}
}