{
  "type": "Feature",
  "properties": {
    "addr:full":"Sint-truidensesteenweg 289 Tienen Vlaams-Brabant 3300",
    "addr:housenumber":"289",
    "addr:postcode":"3300",
    "addr:street":"Sint-Truidensesteenweg",
    "iso:country":"BE",
    "sg:address":"Sint-truidensesteenweg 289",
    "sg:city":"Tienen",
    "sg:orig_category":"Articles de jardin",
    "sg:phone":"+32 16 82 19 11",
    "sg:postcode":"3300",
    "sg:province":"Vlaams-Brabant",
    "wof:name":"Tuincentrum Niclaes",
    "wof:placetype":"venue"
},
  "geometry": {"coordinates":[4.9679031372,50.7995223999],"type":"Point"}
}