{
  "type": "Feature",
  "properties": {
    "iso:country":"BE",
    "sg:address":"Place Loriaux Aim\u00e9 3",
    "sg:city":"Charleroi (jumet)",
    "sg:classifiers":[
        {
            "category":"Health Services",
            "subcategory":"Health Practitioner",
            "type":"Services"
        }
    ],
    "sg:phone":"+32 71 35 99 57",
    "sg:postcode":"6040",
    "sg:province":"Hainaut",
    "sg:tags":[
        "physiotherapist"
    ],
    "wof:name":"Dupierreux M",
    "wof:placetype":"venue"
},
  "geometry": {"coordinates":[4.4245052338,50.4448814392],"type":"Point"}
}