{
  "type": "Feature",
  "properties": {
    "addr:full":"Zomerweg 41 Lendelede West-Vlaanderen 8860",
    "addr:housenumber":"41",
    "addr:postcode":"8860",
    "addr:street":"Zomerweg",
    "iso:country":"BE",
    "sg:address":"Zomerweg 41",
    "sg:city":"Lendelede",
    "sg:orig_category":"Installation \u00e9lectrique r\u00e9sidentielle",
    "sg:phone":"+32 51 31 93 14",
    "sg:postcode":"8860",
    "sg:province":"West-Vlaanderen",
    "wof:name":"Jean Vermeersch",
    "wof:placetype":"venue"
},
  "geometry": {"coordinates":[3.253827095,50.8864784241],"type":"Point"}
}