{
  "type": "Feature",
  "properties": {
    "iso:country":"BE",
    "sg:address":"Rietmusweg 99",
    "sg:city":"Tongeren",
    "sg:classifiers":[
        {
            "category":"Shopping",
            "subcategory":"Clothing, Apparel, & Fashions",
            "type":"Retail Goods"
        }
    ],
    "sg:phone":"+32 12 23 29 66",
    "sg:postcode":"3700",
    "sg:province":"Limburg",
    "sg:tags":[
        "clothing",
        "-",
        "motorbike",
        "equipment"
    ],
    "wof:name":"Levior-menten Sa",
    "wof:placetype":"venue"
},
  "geometry": {"coordinates":[5.4763269424,50.7695541382],"type":"Point"}
}