{
  "type": "Feature",
  "properties": {
    "iso:country":"BE",
    "sg:address":"Boulevard Belgica 37",
    "sg:city":"Sint-jans-molenbeek/molenbeek-saint-jean",
    "sg:orig_category":"Agences immobili\u00e8res. Administration d'immeubles",
    "sg:phone":"+32 2 426 49 71",
    "sg:postcode":"1080",
    "sg:province":"Bruxelles-Capitale",
    "wof:name":"Immobili\u00c8re Delachasse",
    "wof:placetype":"venue"
},
  "geometry": {"coordinates":[4.3376350403,50.8668899536],"type":"Point"}
}