{
  "type": "Feature",
  "properties": {
    "addr:full":"Oudekouter 34 Gent (gentbrugge) Oost-Vlaanderen 9050",
    "addr:housenumber":"34",
    "addr:postcode":"9050",
    "addr:street":"Oudekouter",
    "iso:country":"BE",
    "sg:address":"Oudekouter 34",
    "sg:city":"Gent (gentbrugge)",
    "sg:classifiers":[
        {
            "category":"Building & Trades",
            "subcategory":"Electrical",
            "type":"Services"
        }
    ],
    "sg:phone":"+32 9 231 29 05",
    "sg:postcode":"9050",
    "sg:province":"Oost-Vlaanderen",
    "sg:tags":[
        "electric",
        "-",
        "housewiring",
        "contractor"
    ],
    "wof:name":"Depoorter P",
    "wof:placetype":"venue"
},
  "geometry": {"coordinates":[3.7712740898,51.0470848083],"type":"Point"}
}