{
  "type": "Feature",
  "properties": {
    "addr:full":"Fosse Du Loup 10 Ferri\u00e8res Li\u00e8ge 4190",
    "addr:housenumber":"10",
    "addr:postcode":"4190",
    "addr:street":"Fosse Du Loup",
    "iso:country":"BE",
    "sg:address":"Fosse Du Loup 10",
    "sg:city":"Ferri\u00e8res",
    "sg:classifiers":[
        {
            "category":"Manufacturing",
            "subcategory":"Furniture",
            "type":"Manufacturing & Wholesale Goods"
        }
    ],
    "sg:phone":"+32 86 43 34 57",
    "sg:postcode":"4190",
    "sg:province":"Li\u00e8ge",
    "sg:tags":[
        "made",
        "-",
        "custom"
    ],
    "wof:name":"Gerardy",
    "wof:placetype":"venue"
},
  "geometry": {"coordinates":[5.6424441338,50.3827438354],"type":"Point"}
}