{
  "type": "Feature",
  "properties": {
    "addr:full":"Albrecht Rodenbachlaan 75 Kortrijk (heule) West-Vlaanderen 8501",
    "addr:housenumber":"75",
    "addr:postcode":"8501",
    "addr:street":"Albrecht Rodenbachlaan",
    "iso:country":"BE",
    "sg:address":"Albrecht Rodenbachlaan 75",
    "sg:city":"Kortrijk (heule)",
    "sg:classifiers":[
        {
            "category":"Social Services",
            "subcategory":"Child Care",
            "type":"Services"
        }
    ],
    "sg:phone":"+32 56 35 80 19",
    "sg:postcode":"8501",
    "sg:province":"West-Vlaanderen",
    "sg:tags":[
        "baby",
        "nursery",
        "day",
        "sitting"
    ],
    "wof:name":"Tinneke",
    "wof:placetype":"venue"
},
  "geometry": {"coordinates":[3.2361009121,50.8371429443],"type":"Point"}
}