{
  "type": "Feature",
  "properties": {
    "iso:country":"BE",
    "sg:address":"Charlierhelling 6",
    "sg:city":"Blankenberge",
    "sg:classifiers":[
        {
            "category":"Travel",
            "subcategory":"Hotels & Motels",
            "type":"Entertainment"
        }
    ],
    "sg:phone":"+32 50 41 13 17",
    "sg:postcode":"8370",
    "sg:province":"West-Vlaanderen",
    "sg:tags":[
        "restaurant"
    ],
    "wof:name":"Hotel Marcel",
    "wof:placetype":"venue"
},
  "geometry": {"coordinates":[3.13154006,51.316696167],"type":"Point"}
}