{
  "type": "Feature",
  "properties": {
    "addr:full":"Rue Saint-sauveur 298ba Wanze Li\u00e8ge 4520",
    "addr:postcode":"4520",
    "addr:street":"Rue Saint-Sauveur 298Ba",
    "iso:country":"BE",
    "sg:address":"Rue Saint-sauveur 298ba",
    "sg:city":"Wanze",
    "sg:classifiers":[
        {
            "category":"Wholesale",
            "subcategory":"Farm Supplies",
            "type":"Manufacturing & Wholesale Goods"
        }
    ],
    "sg:phone":"+32 85 25 49 35",
    "sg:postcode":"4520",
    "sg:province":"Li\u00e8ge",
    "sg:tags":[
        "machine",
        "agricoles",
        "mat\u00e9riel",
        "gr"
    ],
    "wof:name":"Melotte Farming",
    "wof:placetype":"venue"
},
  "geometry": {"coordinates":[5.1698799133,50.5446739197],"type":"Point"}
}