{
  "type": "Feature",
  "properties": {
    "iso:country":"BE",
    "sg:address":"Berlaarsestraat 13",
    "sg:city":"Lier",
    "sg:orig_category":"Solariums",
    "sg:phone":"+32 3 480 76 05",
    "sg:postcode":"2500",
    "sg:province":"Antwerpen",
    "wof:name":"Apollo Zonnecenter",
    "wof:placetype":"venue"
},
  "geometry": {"coordinates":[4.5759458542,51.1300506592],"type":"Point"}
}