{
  "type": "Feature",
  "properties": {
    "addr:full":"Chauss\u00e9e De Louvain 23 Eghez\u00e9e Namur 5310",
    "addr:housenumber":"23",
    "addr:postcode":"5310",
    "addr:street":"Chausse\u0301E De Louvain;Namur",
    "iso:country":"BE",
    "sg:address":"Chauss\u00e9e De Louvain 23",
    "sg:city":"Eghez\u00e9e",
    "sg:classifiers":[
        {
            "category":"Real Estate",
            "subcategory":"Real Estate Services",
            "type":"Services"
        }
    ],
    "sg:phone":"+32 81 81 00 06",
    "sg:postcode":"5310",
    "sg:province":"Namur",
    "wof:name":"Williquet",
    "wof:placetype":"venue"
},
  "geometry": {"coordinates":[4.9104218483,50.5933074951],"type":"Point"}
}