{
  "type": "Feature",
  "properties": {
    "iso:country":"BE",
    "sg:address":"Grote Herreweg 227",
    "sg:city":"Kluisbergen",
    "sg:orig_category":"Architecten",
    "sg:phone":"+32 55 38 89 33",
    "sg:postcode":"9690",
    "sg:province":"Oost-Vlaanderen",
    "wof:name":"Wim Desloovere",
    "wof:placetype":"venue"
},
  "geometry": {"coordinates":[3.4936830997,50.7790107727],"type":"Point"}
}