{
  "type": "Feature",
  "properties": {
    "iso:country":"BE",
    "sg:address":"Rue Simon Martin 16",
    "sg:city":"Namur",
    "sg:orig_category":"Banken and kredietinstellingen Verbruikerskredietinstellingen Verzekeringsmakelaars and experts",
    "sg:phone":"+32 81 20 07 25",
    "sg:postcode":"5020",
    "sg:province":"Namur",
    "wof:name":"C.p.m. Bureau Service",
    "wof:placetype":"venue"
},
  "geometry": {"coordinates":[4.9032421112,50.4950866699],"type":"Point"}
}