{
  "type": "Feature",
  "properties": {
    "addr:full":"Diesterstraat 107b Tessenderlo Limburg 3980",
    "addr:housenumber":"107b",
    "addr:postcode":"3980",
    "addr:street":"Diesterstraat",
    "iso:country":"BE",
    "sg:address":"Diesterstraat 107b",
    "sg:city":"Tessenderlo",
    "sg:classifiers":[
        {
            "category":"Health Services",
            "subcategory":"Dentist",
            "type":"Services"
        }
    ],
    "sg:phone":"+32 13 67 37 60",
    "sg:postcode":"3980",
    "sg:province":"Limburg",
    "wof:name":"Putman Olivia",
    "wof:placetype":"venue"
},
  "geometry": {"coordinates":[5.0891480446,51.0619163513],"type":"Point"}
}