{
  "type": "Feature",
  "properties": {
    "addr:full":"Maria Van Hongarijestraat 18 Turnhout Antwerpen 2300",
    "addr:housenumber":"18",
    "addr:postcode":"2300",
    "addr:street":"Maria Van Hongarijestraat",
    "iso:country":"BE",
    "sg:address":"Maria Van Hongarijestraat 18",
    "sg:city":"Turnhout",
    "sg:classifiers":[
        {
            "category":"Professional",
            "subcategory":"Accounting & Tax Preparation",
            "type":"Services"
        }
    ],
    "sg:phone":"+32 14 41 19 97",
    "sg:postcode":"2300",
    "sg:province":"Antwerpen",
    "sg:tags":[
        "accountant"
    ],
    "wof:name":"Van Laeken F",
    "wof:placetype":"venue"
},
  "geometry": {"coordinates":[4.9625458717,51.3349761963],"type":"Point"}
}