{
  "type": "Feature",
  "properties": {
    "addr:full":"Rue Griange 10 Huy Li\u00e8ge 4500",
    "addr:housenumber":"10",
    "addr:postcode":"4500",
    "addr:street":"Rue Griange",
    "iso:country":"BE",
    "sg:address":"Rue Griange 10",
    "sg:city":"Huy",
    "sg:classifiers":[
        {
            "category":"Personal",
            "subcategory":"Beauty Salon",
            "type":"Services"
        }
    ],
    "sg:phone":"+32 85 23 67 93",
    "sg:postcode":"4500",
    "sg:province":"Li\u00e8ge",
    "wof:name":"Carezza Institut",
    "wof:placetype":"venue"
},
  "geometry": {"coordinates":[5.2414250374,50.5175590515],"type":"Point"}
}