{
  "type": "Feature",
  "properties": {
    "addr:full":"Savooistr 106 Ronse Oost-Vlaanderen 9600",
    "addr:housenumber":"106",
    "addr:postcode":"9600",
    "iso:country":"BE",
    "sg:address":"Savooistr 106",
    "sg:city":"Ronse",
    "sg:orig_category":"Salons de coiffure. Centres de relaxation and bien-\u00eatre",
    "sg:phone":"+32 55 20 93 87",
    "sg:postcode":"9600",
    "sg:province":"Oost-Vlaanderen",
    "wof:name":"Fidjo",
    "wof:placetype":"venue"
},
  "geometry": {"coordinates":[3.6256790161,50.7601203918],"type":"Point"}
}