{
  "type": "Feature",
  "properties": {
    "iso:country":"BE",
    "sg:address":"Rue De Namur 36",
    "sg:city":"Wavre",
    "sg:classifiers":[
        {
            "category":"Professional",
            "subcategory":"Art Services",
            "type":"Services"
        }
    ],
    "sg:phone":"+32 10 24 62 52",
    "sg:postcode":"1300",
    "sg:province":"Brabant Wallon",
    "sg:tags":[
        "picture",
        "framer"
    ],
    "wof:name":"D\u00e9clic (le Studio Photographique)",
    "wof:placetype":"venue"
},
  "geometry": {"coordinates":[4.6123418808,50.7124824524],"type":"Point"}
}