{
  "type": "Feature",
  "properties": {
    "addr:full":"Rue Chapuis 1 Sprimont Li\u00e8ge 4140",
    "addr:housenumber":"1",
    "addr:postcode":"4140",
    "addr:street":"Rue Chapuis",
    "iso:country":"BE",
    "sg:address":"Rue Chapuis 1",
    "sg:city":"Sprimont",
    "sg:orig_category":"Banques and organismes de cr\u00e9dit",
    "sg:phone":"+32 4 382 10 14",
    "sg:postcode":"4140",
    "sg:province":"Li\u00e8ge",
    "wof:name":"Bbl",
    "wof:placetype":"venue"
},
  "geometry": {"coordinates":[5.6635937691,50.5022087097],"type":"Point"}
}