{
  "type": "Feature",
  "properties": {
    "iso:country":"BE",
    "sg:address":"Kmo-zone Klein Boom",
    "sg:city":"Putte",
    "sg:orig_category":"Beheer van afvalopslag- and stortplaatsen",
    "sg:phone":"+32 15 75 47 66",
    "sg:postcode":"2580",
    "sg:province":"Antwerpen",
    "wof:name":"Containerpark Igemo",
    "wof:placetype":"venue"
},
  "geometry": {"coordinates":[4.609773159,51.0501213074],"type":"Point"}
}