{
  "type": "Feature",
  "properties": {
    "addr:full":"Rue Edouard Dinot 57 Ciney Namur 5590",
    "addr:housenumber":"57",
    "addr:postcode":"5590",
    "addr:street":"Rue Edouard Dinot",
    "iso:country":"BE",
    "sg:address":"Rue Edouard Dinot 57",
    "sg:city":"Ciney",
    "sg:orig_category":"Traitements param\u00e9dicaux",
    "sg:phone":"+32 83 21 22 73",
    "sg:postcode":"5590",
    "sg:province":"Namur",
    "wof:name":"Y. Collin",
    "wof:placetype":"venue"
},
  "geometry": {"coordinates":[5.1007962227,50.2924308777],"type":"Point"}
}