{
  "type": "Feature",
  "properties": {
    "iso:country":"BE",
    "sg:address":"Luipaardstraat 54",
    "sg:city":"Zwevegem",
    "sg:classifiers":[
        {
            "category":"Personal",
            "subcategory":"Nail Salon",
            "type":"Services"
        }
    ],
    "sg:phone":"+32 56 75 66 32",
    "sg:postcode":"8550",
    "sg:province":"West-Vlaanderen",
    "sg:tags":[
        "pedicure"
    ],
    "wof:name":"Duhem M",
    "wof:placetype":"venue"
},
  "geometry": {"coordinates":[3.3153500557,50.8169441223],"type":"Point"}
}