{
  "type": "Feature",
  "properties": {
    "addr:full":"Avenue De La Sarriette 52 Bruxelles Bruxelles-Capitale 1020",
    "addr:housenumber":"52",
    "addr:postcode":"1020",
    "addr:street":"Avenue De La Sarriette",
    "iso:country":"BE",
    "sg:address":"Avenue De La Sarriette 52",
    "sg:city":"Bruxelles",
    "sg:classifiers":[
        {
            "category":"Arena",
            "subcategory":"Sports Club",
            "type":"Entertainment"
        }
    ],
    "sg:phone":"+32 2 268 54 88",
    "sg:postcode":"1020",
    "sg:province":"Bruxelles-Capitale",
    "sg:tags":[
        "de"
    ],
    "wof:name":"Bruxelles 521",
    "wof:placetype":"venue"
},
  "geometry": {"coordinates":[4.3653697968,50.8967590332],"type":"Point"}
}