{
  "type": "Feature",
  "properties": {
    "iso:country":"BE",
    "sg:address":"Theo De Deckerlaan 7",
    "sg:city":"Temse",
    "sg:classifiers":[
        {
            "category":"Arena",
            "subcategory":"Sports Club",
            "type":"Entertainment"
        }
    ],
    "sg:phone":"+32 3 771 24 03",
    "sg:postcode":"9140",
    "sg:province":"Oost-Vlaanderen",
    "sg:tags":[
        "de"
    ],
    "wof:name":"Rust Roest Sint-niklaas",
    "wof:placetype":"venue"
},
  "geometry": {"coordinates":[4.20829916,51.1312637329],"type":"Point"}
}