{
  "type": "Feature",
  "properties": {
    "iso:country":"BE",
    "sg:address":"Kerkstraat 6",
    "sg:city":"Duffel",
    "sg:classifiers":[
        {
            "category":"Restaurant",
            "type":"Food & Drink"
        }
    ],
    "sg:phone":"+32 15 31 16 83",
    "sg:postcode":"2570",
    "sg:province":"Antwerpen",
    "wof:name":"De Strooien Hoed",
    "wof:placetype":"venue"
},
  "geometry": {"coordinates":[4.5009069443,51.0952415466],"type":"Point"}
}