{
  "type": "Feature",
  "properties": {
    "addr:full":"Rue De Li\u00e8ge 94 Li\u00e8ge 1 (jupille-sur-meuse) Li\u00e8ge 4020",
    "addr:housenumber":"94;1",
    "addr:postcode":"4020",
    "addr:street":"Rue De Lie\u0300Ge;Jupille-Sur-Meuse Lie\u0300Ge",
    "iso:country":"BE",
    "sg:address":"Rue De Li\u00e8ge 94",
    "sg:city":"Li\u00e8ge 1 (jupille-sur-meuse)",
    "sg:classifiers":[
        {
            "category":"Home & Garden",
            "subcategory":"Carpets & Floor Coverings",
            "type":"Retail Goods"
        }
    ],
    "sg:phone":"+32 4 362 94 23",
    "sg:postcode":"4020",
    "sg:province":"Li\u00e8ge",
    "sg:tags":[
        "material",
        "waterproofing"
    ],
    "wof:name":"Lebens",
    "wof:placetype":"venue"
},
  "geometry": {"coordinates":[5.6159038544,50.6428871155],"type":"Point"}
}