{
  "type": "Feature",
  "properties": {
    "iso:country":"BE",
    "sg:address":"Assesteenweg 391",
    "sg:city":"Ternat",
    "sg:orig_category":"Bloemen and planten",
    "sg:phone":"+32 2 582 48 85",
    "sg:postcode":"1741",
    "sg:province":"Vlaams-Brabant",
    "wof:name":"Paul Pernet",
    "wof:placetype":"venue"
},
  "geometry": {"coordinates":[4.1552600861,50.8572387695],"type":"Point"}
}