{
  "type": "Feature",
  "properties": {
    "addr:full":"Tempelsstraat 19 Beringen Limburg 3583",
    "addr:housenumber":"19",
    "addr:postcode":"3583",
    "addr:street":"Tempelsstraat",
    "iso:country":"BE",
    "sg:address":"Tempelsstraat 19",
    "sg:city":"Beringen",
    "sg:orig_category":"Cr\u00e9meries. Jardins botaniques, zoologiques, observatoires and r\u00e9serves naturelles",
    "sg:phone":"+32 13 66 60 09",
    "sg:postcode":"3583",
    "sg:province":"Limburg",
    "wof:name":"De Mekkerbek",
    "wof:placetype":"venue"
},
  "geometry": {"coordinates":[5.1706700325,51.0389442444],"type":"Point"}
}