{
  "type": "Feature",
  "properties": {
    "addr:full":"Loenhoutseweg 135ba Hoogstraten Antwerpen 2320",
    "addr:postcode":"2320",
    "addr:street":"Loenhoutseweg",
    "iso:country":"BE",
    "sg:address":"Loenhoutseweg 135ba",
    "sg:city":"Hoogstraten",
    "sg:orig_category":"Producteurs de l\u00e9gumes",
    "sg:phone":"+32 3 314 80 47",
    "sg:postcode":"2320",
    "sg:province":"Antwerpen",
    "wof:name":"Luc Sprangers",
    "wof:placetype":"venue"
},
  "geometry": {"coordinates":[4.7208800316,51.3937416077],"type":"Point"}
}