{
  "type": "Feature",
  "properties": {
    "addr:full":"Houtemsestw 2 Vilvoorde Vlaams-Brabant 1800",
    "addr:housenumber":"2",
    "addr:postcode":"1800",
    "addr:street":"Houtemsestw",
    "iso:country":"BE",
    "sg:address":"Houtemsestw 2",
    "sg:city":"Vilvoorde",
    "sg:classifiers":[
        {
            "category":"Food & Beverages",
            "subcategory":"Groceries & Convenience Stores",
            "type":"Retail Goods"
        }
    ],
    "sg:phone":"+32 2 251 02 57",
    "sg:postcode":"1800",
    "sg:province":"Vlaams-Brabant",
    "sg:tags":[
        "product",
        "related"
    ],
    "wof:name":"Van Reet Nv",
    "wof:placetype":"venue"
},
  "geometry": {"coordinates":[4.458591938,50.9413719177],"type":"Point"}
}