{
  "type": "Feature",
  "properties": {
    "iso:country":"BE",
    "sg:address":"Rode Kruislaan 29",
    "sg:city":"Zaventem",
    "sg:classifiers":[
        {
            "category":"Real Estate",
            "subcategory":"Architect",
            "type":"Services"
        }
    ],
    "sg:phone":"+32 2 725 84 90",
    "sg:postcode":"1930",
    "sg:province":"Vlaams-Brabant",
    "wof:name":"Heirman M",
    "wof:placetype":"venue"
},
  "geometry": {"coordinates":[4.4685211182,50.8884048462],"type":"Point"}
}