{
  "type": "Feature",
  "properties": {
    "iso:country":"BE",
    "sg:address":"Place Joseph-dejardin 10",
    "sg:city":"Li\u00e8ge 1 (grivegn\u00e9e)",
    "sg:classifiers":[
        {
            "category":"Personal",
            "subcategory":"Beauty Salon",
            "type":"Services"
        }
    ],
    "sg:phone":"+32 4 344 13 51",
    "sg:postcode":"4030",
    "sg:province":"Li\u00e8ge",
    "wof:name":"Dng",
    "wof:placetype":"venue"
},
  "geometry": {"coordinates":[5.6097459793,50.6183815002],"type":"Point"}
}