{
  "type": "Feature",
  "properties": {
    "iso:country":"BE",
    "sg:address":"Avenue Gevaert 107",
    "sg:city":"Rixensart",
    "sg:orig_category":"Landmeters and schatters",
    "sg:phone":"+32 2 653 31 16",
    "sg:postcode":"1332",
    "sg:province":"Brabant Wallon",
    "wof:name":"Viviane Bourguignon",
    "wof:placetype":"venue"
},
  "geometry": {"coordinates":[4.4992160797,50.7194137573],"type":"Point"}
}