{
  "type": "Feature",
  "properties": {
    "addr:full":"Broekstraat 3 Tervuren Vlaams-Brabant 3080",
    "addr:housenumber":"3",
    "addr:postcode":"3080",
    "addr:street":"Broekstraat",
    "iso:country":"BE",
    "sg:address":"Broekstraat 3",
    "sg:city":"Tervuren",
    "sg:orig_category":"Instituts de beaut\u00e9",
    "sg:phone":"+32 2 767 14 41",
    "sg:postcode":"3080",
    "sg:province":"Vlaams-Brabant",
    "wof:name":"Lutgarde Swalus",
    "wof:placetype":"venue"
},
  "geometry": {"coordinates":[4.5125441551,50.8256721497],"type":"Point"}
}