{
  "type": "Feature",
  "properties": {
    "iso:country":"BE",
    "sg:address":"Statiestraat 2",
    "sg:city":"Ternat",
    "sg:classifiers":[
        {
            "category":"Shopping",
            "subcategory":"Florist",
            "type":"Retail Goods"
        }
    ],
    "sg:phone":"+32 2 582 28 82",
    "sg:postcode":"1740",
    "sg:province":"Vlaams-Brabant",
    "wof:name":"Linea Verde",
    "wof:placetype":"venue"
},
  "geometry": {"coordinates":[4.1778049469,50.8712501526],"type":"Point"}
}