{
  "type": "Feature",
  "properties": {
    "addr:full":"Weldoenstraat 36 Watermaal-bosvoorde/watermael-boitsfort Bruxelles-Capitale 1170",
    "addr:housenumber":"36",
    "addr:postcode":"1170",
    "addr:street":"Weldoenstraat",
    "iso:country":"BE",
    "sg:address":"Weldoenstraat 36",
    "sg:city":"Watermaal-bosvoorde/watermael-boitsfort",
    "sg:orig_category":"Herstellingen and onderhoud van auto's",
    "sg:phone":"+32 2 673 57 84",
    "sg:postcode":"1170",
    "sg:province":"Bruxelles-Capitale",
    "wof:name":"Garage Watermael-boisfort",
    "wof:placetype":"venue"
},
  "geometry": {"coordinates":[4.431429863,50.7936401367],"type":"Point"}
}