{
  "type": "Feature",
  "properties": {
    "iso:country":"BE",
    "sg:address":"Place D'audregnies 68",
    "sg:city":"Quievrain",
    "sg:orig_category":"Enseignement maternel and primaire",
    "sg:phone":"+32 65 43 09 50",
    "sg:postcode":"7382",
    "sg:province":"Hainaut",
    "wof:name":"Ecole Fond. Communale",
    "wof:placetype":"venue"
},
  "geometry": {"coordinates":[3.7204289436,50.38438797],"type":"Point"}
}