{
  "type": "Feature",
  "properties": {
    "addr:full":"Heldenlaan 41 Beringen Limburg 3583",
    "addr:housenumber":"41",
    "addr:postcode":"3583",
    "addr:street":"Heldenlaan",
    "iso:country":"BE",
    "sg:address":"Heldenlaan 41",
    "sg:city":"Beringen",
    "sg:orig_category":"Verlichting and huishoudartikelen",
    "sg:phone":"+32 11 42 51 71",
    "sg:postcode":"3583",
    "sg:province":"Limburg",
    "wof:name":"Caerts C",
    "wof:placetype":"venue"
},
  "geometry": {"coordinates":[5.1706700325,51.0389442444],"type":"Point"}
}