{
  "type": "Feature",
  "properties": {
    "addr:full":"Rue Emile Feron 176 Bruxelles (saint-gilles) Bruxelles-Capitale 1060",
    "addr:housenumber":"176",
    "addr:postcode":"1060",
    "addr:street":"Rue Emile Feron",
    "iso:country":"BE",
    "sg:address":"Rue Emile Feron 176",
    "sg:city":"Bruxelles (saint-gilles)",
    "sg:classifiers":[
        {
            "category":"Health Services",
            "subcategory":"Doctor",
            "type":"Services"
        }
    ],
    "sg:phone":"+32 2 538 72 44",
    "sg:postcode":"1060",
    "sg:province":"Bruxelles-Capitale",
    "sg:tags":[
        "medicinephysicians",
        "surgeon"
    ],
    "wof:name":"Hildebrand Marc",
    "wof:placetype":"venue"
},
  "geometry": {"coordinates":[4.3343691826,50.8294258118],"type":"Point"}
}