{
  "type": "Feature",
  "properties": {
    "addr:full":"All\u00e9e Des Foug\u00e8res 3 Neupr\u00e9 (neuville-en-condroz) Li\u00e8ge 4121",
    "addr:housenumber":"3",
    "addr:postcode":"4121",
    "addr:street":"Alle\u0301E Des Fouge\u0300Res",
    "iso:country":"BE",
    "sg:address":"All\u00e9e Des Foug\u00e8res 3",
    "sg:city":"Neupr\u00e9 (neuville-en-condroz)",
    "sg:classifiers":[
        {
            "category":"Food & Beverages",
            "subcategory":"Groceries & Convenience Stores",
            "type":"Retail Goods"
        }
    ],
    "sg:phone":"+32 4 361 67 31",
    "sg:postcode":"4121",
    "sg:province":"Li\u00e8ge",
    "sg:tags":[
        "baker",
        "-",
        "ingredient"
    ],
    "wof:name":"Roch'coco",
    "wof:placetype":"venue"
},
  "geometry": {"coordinates":[5.4720540047,50.5487823486],"type":"Point"}
}