{
  "type": "Feature",
  "properties": {
    "addr:full":"Brasschaatsebaan 79 Schilde Antwerpen 2970",
    "addr:housenumber":"79",
    "addr:postcode":"2970",
    "addr:street":"Brasschaatsebaan",
    "iso:country":"BE",
    "sg:address":"Brasschaatsebaan 79",
    "sg:city":"Schilde",
    "sg:orig_category":"Schoonheidssalons",
    "sg:phone":"+32 3 383 04 77",
    "sg:postcode":"2970",
    "sg:province":"Antwerpen",
    "wof:name":"Patrick Fimmers",
    "wof:placetype":"venue"
},
  "geometry": {"coordinates":[4.5746068954,51.2436103821],"type":"Point"}
}