{
  "type": "Feature",
  "properties": {
    "addr:full":"Colline Du Glain 8 Rixensart Brabant Wallon 1330",
    "addr:housenumber":"8",
    "addr:postcode":"1330",
    "addr:street":"Colline Du Glain;Wallon",
    "iso:country":"BE",
    "sg:address":"Colline Du Glain 8",
    "sg:city":"Rixensart",
    "sg:classifiers":[
        {
            "category":"Professional",
            "subcategory":"Management & Consulting",
            "type":"Services"
        }
    ],
    "sg:phone":"+32 2 652 35 62",
    "sg:postcode":"1330",
    "sg:province":"Brabant Wallon",
    "sg:tags":[
        "-",
        "processing",
        "data",
        "consultant"
    ],
    "wof:name":"Y2k",
    "wof:placetype":"venue"
},
  "geometry": {"coordinates":[4.5165448189,50.7192420959],"type":"Point"}
}