{
  "type": "Feature",
  "properties": {
    "iso:country":"BE",
    "sg:address":"Kannunnik Puissantstraat",
    "sg:city":"Ronse",
    "sg:orig_category":"Beheer van afvalopslag- and stortplaatsen",
    "sg:phone":"+32 55 23 27 56",
    "sg:postcode":"9600",
    "sg:province":"Oost-Vlaanderen",
    "wof:name":"Containerpark Ronse",
    "wof:placetype":"venue"
},
  "geometry": {"coordinates":[3.589099884,50.7461547852],"type":"Point"}
}