{
  "type": "Feature",
  "properties": {
    "iso:country":"BE",
    "sg:address":"Rue Evariste Debroux 5",
    "sg:city":"Genappe (ways)",
    "sg:classifiers":[
        {
            "category":"Parking",
            "subcategory":"Bicycle",
            "type":"Transportation"
        }
    ],
    "sg:phone":"+32 67 77 10 91",
    "sg:postcode":"1474",
    "sg:province":"Brabant Wallon",
    "sg:tags":[
        "chiropodist"
    ],
    "wof:name":"Nanou",
    "wof:placetype":"venue"
},
  "geometry": {"coordinates":[4.4630827904,50.6126594543],"type":"Point"}
}