{
  "type": "Feature",
  "properties": {
    "addr:full":"Felix Timmermansstraat 22 Zele Oost-Vlaanderen 9240",
    "addr:housenumber":"22",
    "addr:postcode":"9240",
    "addr:street":"Felix Timmermansstraat",
    "iso:country":"BE",
    "sg:address":"Felix Timmermansstraat 22",
    "sg:city":"Zele",
    "sg:orig_category":"Installation de menuiserie en bois and plastique. Installation de menuiserie m\u00e9tallique",
    "sg:phone":"+32 52 44 60 84",
    "sg:postcode":"9240",
    "sg:province":"Oost-Vlaanderen",
    "wof:name":"Nicola Gelorini",
    "wof:placetype":"venue"
},
  "geometry": {"coordinates":[4.0336837769,51.0593910217],"type":"Point"}
}