{
  "type": "Feature",
  "properties": {
    "iso:country":"BE",
    "sg:address":"Rue Cote D\u00b4or 311",
    "sg:city":"Li\u00c8ge",
    "sg:orig_category":"HUISBRANDOLIE",
    "sg:phone":"+32 4 252 50 39",
    "sg:postcode":"4000",
    "sg:province":"Li\u00e8ge",
    "wof:name":"Transp. Bouharmont Fr\u00c8res",
    "wof:placetype":"venue"
},
  "geometry": {"coordinates":[5.5685949326,50.6123313904],"type":"Point"}
}