{
  "type": "Feature",
  "properties": {
    "addr:full":"Vis\u00e9steenweg 113 Riemst Limburg 3770",
    "addr:housenumber":"113",
    "addr:postcode":"3770",
    "addr:street":"Vise\u0301Steenweg",
    "iso:country":"BE",
    "sg:address":"Vis\u00e9steenweg 113",
    "sg:city":"Riemst",
    "sg:classifiers":[
        {
            "category":"Real Estate",
            "subcategory":"Architect",
            "type":"Services"
        }
    ],
    "sg:phone":"+32 12 45 44 43",
    "sg:postcode":"3770",
    "sg:province":"Limburg",
    "wof:name":"Oben J",
    "wof:placetype":"venue"
},
  "geometry": {"coordinates":[5.6054201126,50.8047485352],"type":"Point"}
}