{
  "type": "Feature",
  "properties": {
    "addr:full":"Pl De L'h\u00f4tel De Ville 16 Florennes 6388",
    "addr:housenumber":"16",
    "addr:postcode":"6388",
    "addr:street":"Pl",
    "iso:country":"BE",
    "sg:address":"Pl De L'h\u00f4tel De Ville 16",
    "sg:city":"Florennes",
    "sg:classifiers":[
        {
            "category":"Banks & Credit Unions",
            "subcategory":"Bank",
            "type":"Services"
        }
    ],
    "sg:phone":"+32 81 68 80 60",
    "sg:postcode":"6388",
    "wof:name":"G\u00e9n\u00e9rale De Banque Sa",
    "wof:placetype":"venue"
},
  "geometry": {"coordinates":[4.6046600342,50.2513809204],"type":"Point"}
}