{
  "type": "Feature",
  "properties": {
    "addr:full":"Rue Antoine Nys 40 Bruxelles (anderlecht) Bruxelles-Capitale 1070",
    "addr:housenumber":"40",
    "addr:postcode":"1070",
    "addr:street":"Rue Antoine Nys",
    "iso:country":"BE",
    "sg:address":"Rue Antoine Nys 40",
    "sg:city":"Bruxelles (anderlecht)",
    "sg:classifiers":[
        {
            "category":"Professional",
            "subcategory":"Accounting & Tax Preparation",
            "type":"Services"
        }
    ],
    "sg:phone":"+32 2 411 99 22",
    "sg:postcode":"1070",
    "sg:province":"Bruxelles-Capitale",
    "sg:tags":[
        "bookkeeper"
    ],
    "wof:name":"Lamourette C",
    "wof:placetype":"venue"
},
  "geometry": {"coordinates":[4.2877621651,50.8286323547],"type":"Point"}
}