{
  "type": "Feature",
  "properties": {
    "addr:full":"Tassijnslaan 8 Sint-niklaas Oost-Vlaanderen 9100",
    "addr:housenumber":"8",
    "addr:postcode":"9100",
    "addr:street":"Tassijnslaan",
    "iso:country":"BE",
    "sg:address":"Tassijnslaan 8",
    "sg:city":"Sint-niklaas",
    "sg:classifiers":[
        {
            "category":"Personal",
            "subcategory":"Beauty Salon",
            "type":"Services"
        }
    ],
    "sg:phone":"+32 3 755 37 75",
    "sg:postcode":"9100",
    "sg:province":"Oost-Vlaanderen",
    "sg:tags":[
        "lady",
        "-",
        "hairdressing"
    ],
    "wof:name":"Haarmode Linda",
    "wof:placetype":"venue"
},
  "geometry": {"coordinates":[4.2134661674,51.1751823425],"type":"Point"}
}