{
  "type": "Feature",
  "properties": {
    "addr:full":"Tir Aux Pigeons 89 Bruxelles (woluwe-saint-pierre) Bruxelles-Capitale 1150",
    "addr:housenumber":"89",
    "addr:postcode":"1150",
    "addr:street":"Tir Aux Pigeons",
    "iso:country":"BE",
    "sg:address":"Tir Aux Pigeons 89",
    "sg:city":"Bruxelles (woluwe-saint-pierre)",
    "sg:classifiers":[
        {
            "category":"Professional",
            "subcategory":"Accounting & Tax Preparation",
            "type":"Services"
        }
    ],
    "sg:phone":"+32 2 771 59 72",
    "sg:postcode":"1150",
    "sg:province":"Bruxelles-Capitale",
    "sg:tags":[
        "accountant"
    ],
    "wof:name":"Therasse A",
    "wof:placetype":"venue"
},
  "geometry": {"coordinates":[4.4651670456,50.8301048279],"type":"Point"}
}