{
  "type": "Feature",
  "properties": {
    "iso:country":"BE",
    "sg:address":"Augustijnslei 196",
    "sg:city":"Brasschaat",
    "sg:classifiers":[
        {
            "category":"Health Services",
            "subcategory":"Health Practitioner",
            "type":"Services"
        }
    ],
    "sg:phone":"+32 3 651 83 46",
    "sg:postcode":"2930",
    "sg:province":"Antwerpen",
    "sg:tags":[
        "psychologist"
    ],
    "wof:name":"Pauwels N",
    "wof:placetype":"venue"
},
  "geometry": {"coordinates":[4.4866018295,51.3024520874],"type":"Point"}
}