{
  "type": "Feature",
  "properties": {
    "addr:full":"Van Schoonbekestraat 79 Antwerpen Antwerpen 2018",
    "addr:housenumber":"79",
    "addr:postcode":"2018",
    "addr:street":"Van Schoonbekestraat",
    "iso:country":"BE",
    "sg:address":"Van Schoonbekestraat 79",
    "sg:city":"Antwerpen",
    "sg:classifiers":[
        {
            "category":"Real Estate",
            "subcategory":"Architect",
            "type":"Services"
        }
    ],
    "sg:phone":"+32 3 237 89 96",
    "sg:postcode":"2018",
    "sg:province":"Antwerpen",
    "wof:name":"Dalemans F",
    "wof:placetype":"venue"
},
  "geometry": {"coordinates":[4.406730175,51.2016944885],"type":"Point"}
}