{
  "type": "Feature",
  "properties": {
    "iso:country":"BE",
    "sg:address":"Rodendijk 52",
    "sg:city":"Zoersel",
    "sg:classifiers":[
        {
            "category":"Home & Garden",
            "subcategory":"Furniture",
            "type":"Retail Goods"
        }
    ],
    "sg:phone":"+32 3 312 05 48",
    "sg:postcode":"2980",
    "sg:province":"Antwerpen",
    "sg:tags":[
        "small",
        "item",
        "-"
    ],
    "wof:name":"Interlamp Bvba",
    "wof:placetype":"venue"
},
  "geometry": {"coordinates":[4.7055859566,51.2492675781],"type":"Point"}
}