{
  "type": "Feature",
  "properties": {
    "addr:full":"Marktplein 9 Kuurne West-Vlaanderen 8520",
    "addr:housenumber":"9",
    "addr:postcode":"8520",
    "addr:street":"Marktplein",
    "iso:country":"BE",
    "sg:address":"Marktplein 9",
    "sg:city":"Kuurne",
    "sg:classifiers":[
        {
            "category":"Health Services",
            "subcategory":"Nursing And Care Facility",
            "type":"Services"
        }
    ],
    "sg:phone":"+32 56 73 71 21",
    "sg:postcode":"8520",
    "sg:province":"West-Vlaanderen",
    "sg:tags":[
        "public"
    ],
    "wof:name":"Gemeentebestuur",
    "wof:placetype":"venue"
},
  "geometry": {"coordinates":[3.2872600555,50.8502311707],"type":"Point"}
}