{
  "type": "Feature",
  "properties": {
    "addr:full":"Rue Blanche Borne 79 Ch\u00e2telet (bouffioulx) Hainaut 6200",
    "addr:housenumber":"79",
    "addr:postcode":"6200",
    "addr:street":"Rue Blanche Borne",
    "iso:country":"BE",
    "sg:address":"Rue Blanche Borne 79",
    "sg:city":"Ch\u00e2telet (bouffioulx)",
    "sg:classifiers":[
        {
            "category":"Professional",
            "subcategory":"Testing Lab",
            "type":"Services"
        }
    ],
    "sg:phone":"+32 71 38 04 40",
    "sg:postcode":"6200",
    "sg:province":"Hainaut",
    "sg:tags":[
        "chemist"
    ],
    "wof:name":"Willame",
    "wof:placetype":"venue"
},
  "geometry": {"coordinates":[4.4979381561,50.3908653259],"type":"Point"}
}