{
  "type": "Feature",
  "properties": {
    "addr:full":"Drabstraat 10 Mortsel Antwerpen 2640",
    "addr:housenumber":"10",
    "addr:postcode":"2640",
    "addr:street":"Drabstraat",
    "iso:country":"BE",
    "sg:address":"Drabstraat 10",
    "sg:city":"Mortsel",
    "sg:orig_category":"Agences de voyages",
    "sg:phone":"+32 3 440 18 00",
    "sg:postcode":"2640",
    "sg:province":"Antwerpen",
    "wof:name":"Recrea",
    "wof:placetype":"venue"
},
  "geometry": {"coordinates":[4.4629449844,51.1700973511],"type":"Point"}
}