{
  "type": "Feature",
  "properties": {
    "addr:full":"Chauss\u00c9e De Fleurus 19bd Charleroi Hainaut 6040",
    "addr:housenumber":"19bd",
    "addr:postcode":"6040",
    "addr:street":"Chausse\u0301E De Fleurus;Hainaut",
    "iso:country":"BE",
    "sg:address":"Chauss\u00c9e De Fleurus 19bd",
    "sg:city":"Charleroi",
    "sg:orig_category":"Epiceries",
    "sg:phone":"+32 71 41 53 80",
    "sg:postcode":"6040",
    "sg:province":"Hainaut",
    "wof:name":"Spar",
    "wof:placetype":"venue"
},
  "geometry": {"coordinates":[4.4724640846,50.4434127808],"type":"Point"}
}