{
  "type": "Feature",
  "properties": {
    "iso:country":"BE",
    "sg:address":"Rue De La Gare 27",
    "sg:city":"Beauraing",
    "sg:orig_category":"Tabac. Journaux",
    "sg:phone":"+32 82 71 13 56",
    "sg:postcode":"5570",
    "sg:province":"Namur",
    "wof:name":"Librairie De Gare",
    "wof:placetype":"venue"
},
  "geometry": {"coordinates":[4.9565768242,50.1143608093],"type":"Point"}
}