{
  "type": "Feature",
  "properties": {
    "iso:country":"BE",
    "sg:address":"Rue Fr\u00e8re Orban 2",
    "sg:city":"Charleroi (jumet)",
    "sg:classifiers":[
        {
            "category":"Health Services",
            "subcategory":"Doctor",
            "type":"Services"
        }
    ],
    "sg:phone":"+32 71 35 77 53",
    "sg:postcode":"6040",
    "sg:province":"Hainaut",
    "sg:tags":[
        "medicinephysicians",
        "surgeon"
    ],
    "wof:name":"Colassin R",
    "wof:placetype":"venue"
},
  "geometry": {"coordinates":[4.4206271172,50.4390335083],"type":"Point"}
}