{
  "type": "Feature",
  "properties": {
    "iso:country":"BE",
    "sg:address":"Leedsesteenweg 96",
    "sg:city":"Erpe-mere",
    "sg:orig_category":"Instruments de musique",
    "sg:phone":"+32 478 39 11 96",
    "sg:postcode":"9420",
    "sg:province":"Oost-Vlaanderen",
    "wof:name":"Pianos Carlier",
    "wof:placetype":"venue"
},
  "geometry": {"coordinates":[3.9851429462,50.949005127],"type":"Point"}
}