{
  "type": "Feature",
  "properties": {
    "iso:country":"BE",
    "sg:address":"Bergstraat 26-28",
    "sg:city":"Nieuwerkerken",
    "sg:orig_category":"Plaatsen van vloer- and muurbekleding Schilders Verlichting and huishoudartikelen",
    "sg:phone":"+32 11 31 45 31",
    "sg:postcode":"3850",
    "sg:province":"Limburg",
    "wof:name":"Aber",
    "wof:placetype":"venue"
},
  "geometry": {"coordinates":[5.2403697968,50.8730964661],"type":"Point"}
}