{
  "type": "Feature",
  "properties": {
    "iso:country":"BE",
    "sg:address":"Koolaerdstraat 74",
    "sg:city":"Gistel",
    "sg:orig_category":"Instituts de beaut\u00e9",
    "sg:phone":"+32 59 27 61 36",
    "sg:postcode":"8470",
    "sg:province":"West-Vlaanderen",
    "wof:name":"Bart Vanhoutte",
    "wof:placetype":"venue"
},
  "geometry": {"coordinates":[2.9564878941,51.1551322937],"type":"Point"}
}