{
  "type": "Feature",
  "properties": {
    "addr:full":"Desmedtstraat 84 Hoogstraten (minderhout) Antwerpen 2322",
    "addr:housenumber":"84",
    "addr:postcode":"2322",
    "addr:street":"Desmedtstraat",
    "iso:country":"BE",
    "sg:address":"Desmedtstraat 84",
    "sg:city":"Hoogstraten (minderhout)",
    "sg:classifiers":[
        {
            "category":"Government",
            "subcategory":"Fire Station",
            "type":"Public Place"
        }
    ],
    "sg:phone":"+32 3 314 96 89",
    "sg:postcode":"2322",
    "sg:province":"Antwerpen",
    "sg:tags":[
        "installation",
        "-",
        "air conditioning"
    ],
    "wof:name":"Airnic Van Den Heuvel Bvba",
    "wof:placetype":"venue"
},
  "geometry": {"coordinates":[4.763384819,51.4160041809],"type":"Point"}
}