{
  "type": "Feature",
  "properties": {
    "addr:full":"Edward Vlietinckstraat 4a Oostende (stene) West-Vlaanderen 8400",
    "addr:housenumber":"4a",
    "addr:postcode":"8400",
    "addr:street":"Vlietinckstraat",
    "iso:country":"BE",
    "sg:address":"Edward Vlietinckstraat 4a",
    "sg:city":"Oostende (stene)",
    "sg:orig_category":"Non-Classified Establishments",
    "sg:phone":"+32 59 80 25 64",
    "sg:postcode":"8400",
    "sg:province":"West-Vlaanderen",
    "wof:name":"Herman",
    "wof:placetype":"venue"
},
  "geometry": {"coordinates":[2.9367740154,51.2063484192],"type":"Point"}
}