{
  "type": "Feature",
  "properties": {
    "addr:full":"Rue Les Golettes 243 Ohey Namur 5351",
    "addr:housenumber":"243",
    "addr:postcode":"5351",
    "addr:street":"Rue Les Golettes",
    "iso:country":"BE",
    "sg:address":"Rue Les Golettes 243",
    "sg:city":"Ohey",
    "sg:orig_category":"Rundveehouders",
    "sg:phone":"+32 85 61 12 26",
    "sg:postcode":"5351",
    "sg:province":"Namur",
    "wof:name":"Jean Sambon",
    "wof:placetype":"venue"
},
  "geometry": {"coordinates":[5.1467618942,50.4541015625],"type":"Point"}
}