{
  "type": "Feature",
  "properties": {
    "iso:country":"BE",
    "sg:address":"Koning-albertstraat 100",
    "sg:city":"Geel",
    "sg:orig_category":"Eleveurs and marchands de porcs. Eleveurs de volaille",
    "sg:phone":"+32 14 58 74 79",
    "sg:postcode":"2440",
    "sg:province":"Antwerpen",
    "wof:name":"Viktor Renders",
    "wof:placetype":"venue"
},
  "geometry": {"coordinates":[4.97955513,51.1354141235],"type":"Point"}
}