{
  "type": "Feature",
  "properties": {
    "iso:country":"BE",
    "sg:address":"Havenlaan 33 A",
    "sg:city":"Diepenbeek",
    "sg:orig_category":"Travaux de pl\u00e2trage. Construction de maisons",
    "sg:phone":"+32 11 24 13 41",
    "sg:postcode":"3590",
    "sg:province":"Limburg",
    "wof:name":"Hanssen",
    "wof:placetype":"venue"
},
  "geometry": {"coordinates":[5.4309301376,50.9406204224],"type":"Point"}
}