{
  "type": "Feature",
  "properties": {
    "addr:full":"Rue M Creusiaux 40 Charleroi Hainaut 6041",
    "addr:housenumber":"40",
    "addr:postcode":"6041",
    "addr:street":"Rue M Creusiaux;Hainaut",
    "iso:country":"BE",
    "sg:address":"Rue M Creusiaux 40",
    "sg:city":"Charleroi",
    "sg:orig_category":"Plantes and fleurs Gr",
    "sg:phone":"+32 71 37 38 52",
    "sg:postcode":"6041",
    "sg:province":"Hainaut",
    "wof:name":"Adam",
    "wof:placetype":"venue"
},
  "geometry": {"coordinates":[4.4314317703,50.4685935974],"type":"Point"}
}