{
  "type": "Feature",
  "properties": {
    "addr:full":"Turnhoutsebaan 151 Dessel Antwerpen 2480",
    "addr:housenumber":"151",
    "addr:postcode":"2480",
    "addr:street":"Turnhoutsebaan",
    "iso:country":"BE",
    "sg:address":"Turnhoutsebaan 151",
    "sg:city":"Dessel",
    "sg:orig_category":"Herstellingen and onderhoud van auto's Onderdelen and accessoires voor auto's Telecommunicatieappara",
    "sg:phone":"+32 14 37 33 11",
    "sg:postcode":"2480",
    "sg:province":"Antwerpen",
    "wof:name":"Cmc",
    "wof:placetype":"venue"
},
  "geometry": {"coordinates":[5.1081671715,51.2489471436],"type":"Point"}
}