{
  "type": "Feature",
  "properties": {
    "addr:full":"Gounodstraat 3 Antwerpen Antwerpen 2018",
    "addr:housenumber":"3",
    "addr:postcode":"2018",
    "addr:street":"Gounodstraat",
    "iso:country":"BE",
    "sg:address":"Gounodstraat 3",
    "sg:city":"Antwerpen",
    "sg:orig_category":"M\u00e9decins and sp\u00e9cialistes",
    "sg:phone":"+32 3 237 80 41",
    "sg:postcode":"2018",
    "sg:province":"Antwerpen",
    "wof:name":"Marc Daenen",
    "wof:placetype":"venue"
},
  "geometry": {"coordinates":[4.4095849991,51.2057342529],"type":"Point"}
}