{
  "type": "Feature",
  "properties": {
    "iso:country":"BE",
    "sg:address":"Chemin Maurice Bouvette 26",
    "sg:city":"Rebecq",
    "sg:orig_category":"Installation \u00e9lectrique r\u00e9sidentielle",
    "sg:phone":"+32 67 67 09 32",
    "sg:postcode":"1430",
    "sg:province":"Brabant Wallon",
    "wof:name":"Jean Claes",
    "wof:placetype":"venue"
},
  "geometry": {"coordinates":[4.1078391075,50.6470794678],"type":"Point"}
}