{
  "type": "Feature",
  "properties": {
    "addr:full":"Steenwagenstraat 35 Steenokkerzeel Vlaams-Brabant 1820",
    "addr:housenumber":"35",
    "addr:postcode":"1820",
    "addr:street":"Steenwagenstraat",
    "iso:country":"BE",
    "sg:address":"Steenwagenstraat 35",
    "sg:city":"Steenokkerzeel",
    "sg:orig_category":"Sportclubs",
    "sg:phone":"+32 2 751 44 11",
    "sg:postcode":"1820",
    "sg:province":"Vlaams-Brabant",
    "wof:name":"Sjaloom-luvok Etterbeek",
    "wof:placetype":"venue"
},
  "geometry": {"coordinates":[4.4682030678,50.9113731384],"type":"Point"}
}