{
  "type": "Feature",
  "properties": {
    "addr:full":"Haachtsesteenweg 132 Kampenhout (berg) Vlaams-Brabant 1910",
    "addr:housenumber":"132",
    "addr:postcode":"1910",
    "addr:street":"Haachtsesteenweg",
    "iso:country":"BE",
    "sg:address":"Haachtsesteenweg 132",
    "sg:city":"Kampenhout (berg)",
    "sg:classifiers":[
        {
            "category":"Sports & Exercise",
            "subcategory":"Tennis Court",
            "type":"Entertainment"
        }
    ],
    "sg:phone":"+32 16 65 05 86",
    "sg:postcode":"1910",
    "sg:province":"Vlaams-Brabant",
    "sg:tags":[
        "shoe"
    ],
    "wof:name":"Running Mate",
    "wof:placetype":"venue"
},
  "geometry": {"coordinates":[4.5492501259,50.9375],"type":"Point"}
}