{
  "type": "Feature",
  "properties": {
    "iso:country":"BE",
    "sg:address":"Chauss\u00c9e De Wavre 1265",
    "sg:city":"Oudergem/auderghem",
    "sg:orig_category":"M\u00e9decins and sp\u00e9cialistes",
    "sg:phone":"+32 2 672 28 75",
    "sg:postcode":"1160",
    "sg:province":"Bruxelles-Capitale",
    "wof:name":"Axel Hermans",
    "wof:placetype":"venue"
},
  "geometry": {"coordinates":[4.4071149826,50.821182251],"type":"Point"}
}