{
  "type": "Feature",
  "properties": {
    "addr:full":"Dorsweg 15 Lovendegem Oost-Vlaanderen 9921",
    "addr:housenumber":"15",
    "addr:postcode":"9921",
    "addr:street":"Dorsweg",
    "iso:country":"BE",
    "sg:address":"Dorsweg 15",
    "sg:city":"Lovendegem",
    "sg:classifiers":[
        {
            "category":"Fast Food",
            "type":"Food & Drink"
        }
    ],
    "sg:phone":"+32 9 226 20 53",
    "sg:postcode":"9921",
    "sg:province":"Oost-Vlaanderen",
    "sg:tags":[
        "meeneem",
        "restaurant"
    ],
    "wof:name":"Restaurant 't Baafken",
    "wof:placetype":"venue"
},
  "geometry": {"coordinates":[3.6413509846,51.0867500305],"type":"Point"}
}