{
  "type": "Feature",
  "properties": {
    "addr:full":"Hooidonkstraat 66 Nijlen Antwerpen 2560",
    "addr:housenumber":"66",
    "addr:postcode":"2560",
    "addr:street":"Hooidonkstraat",
    "iso:country":"BE",
    "sg:address":"Hooidonkstraat 66",
    "sg:city":"Nijlen",
    "sg:classifiers":[
        {
            "category":"Retail",
            "subcategory":"Auto Repair",
            "type":"Services"
        }
    ],
    "sg:phone":"+32 3 411 23 37",
    "sg:postcode":"2560",
    "sg:province":"Antwerpen",
    "sg:tags":[
        "lpg",
        "automobile",
        "-",
        "system"
    ],
    "wof:name":"Friane Bvba",
    "wof:placetype":"venue"
},
  "geometry": {"coordinates":[4.6917848587,51.170009613],"type":"Point"}
}