{
  "type": "Feature",
  "properties": {
    "addr:full":"Industrieterrein kolmen 1226 Alken Limburg 3570",
    "addr:housenumber":"1226",
    "addr:postcode":"3570",
    "addr:street":"Industrieterrein Kolmen",
    "iso:country":"BE",
    "sg:address":"Industrieterrein kolmen 1226",
    "sg:city":"Alken",
    "sg:classifiers":[
        {
            "category":"Retail",
            "subcategory":"Car Wash",
            "type":"Services"
        }
    ],
    "sg:phone":"+32 11 31 44 72",
    "sg:postcode":"3570",
    "sg:province":"Limburg",
    "sg:tags":[
        "elevator"
    ],
    "wof:name":"Renu Liften Nv",
    "wof:placetype":"venue"
},
  "geometry": {"coordinates":[5.3073601723,50.8763618469],"type":"Point"}
}