{
  "type": "Feature",
  "properties": {
    "addr:full":"Honegemstraat 107 Erpe-mere (erpe) Oost-Vlaanderen 9420",
    "addr:housenumber":"107",
    "addr:postcode":"9420",
    "addr:street":"Honegemstraat",
    "iso:country":"BE",
    "sg:address":"Honegemstraat 107",
    "sg:city":"Erpe-mere (erpe)",
    "sg:classifiers":[
        {
            "category":"Professional",
            "subcategory":"Lawyer & Legal Services",
            "type":"Services"
        }
    ],
    "sg:phone":"+32 53 80 55 46",
    "sg:postcode":"9420",
    "sg:province":"Oost-Vlaanderen",
    "wof:name":"Meert S",
    "wof:placetype":"venue"
},
  "geometry": {"coordinates":[3.9970180988,50.9510803223],"type":"Point"}
}