{
  "type": "Feature",
  "properties": {
    "addr:full":"Mechelsesteenweg 167 Sint-katelijne-waver Antwerpen 2860",
    "addr:housenumber":"167",
    "addr:postcode":"2860",
    "addr:street":"Mechelsesteenweg",
    "iso:country":"BE",
    "sg:address":"Mechelsesteenweg 167",
    "sg:city":"Sint-katelijne-waver",
    "sg:orig_category":"Meubles D\u00e9taillants, Am\u00e9nagement de B\u00e2timents et de Cuisines",
    "sg:phone":"+32 15 55 38 63",
    "sg:postcode":"2860",
    "sg:province":"Antwerpen",
    "wof:name":"Super Star",
    "wof:placetype":"venue"
},
  "geometry": {"coordinates":[4.5203099251,51.0525512695],"type":"Point"}
}