{
  "type": "Feature",
  "properties": {
    "addr:full":"Tienne-jean-pierre 31 Floreffe Namur 5150",
    "addr:housenumber":"31",
    "addr:postcode":"5150",
    "addr:street":"Tienne-Jean-Pierre",
    "iso:country":"BE",
    "sg:address":"Tienne-jean-pierre 31",
    "sg:city":"Floreffe",
    "sg:orig_category":"Plaatsen van vloer- and muurbekleding",
    "sg:phone":"+32 81 44 53 01",
    "sg:postcode":"5150",
    "sg:province":"Namur",
    "wof:name":"Michel Bodson",
    "wof:placetype":"venue"
},
  "geometry": {"coordinates":[4.7570519447,50.4175109863],"type":"Point"}
}