{
  "type": "Feature",
  "properties": {
    "addr:full":"Veldeken 5 Waarschoot Oost-Vlaanderen 9950",
    "addr:housenumber":"5",
    "addr:postcode":"9950",
    "addr:street":"Veldeken",
    "iso:country":"BE",
    "sg:address":"Veldeken 5",
    "sg:city":"Waarschoot",
    "sg:classifiers":[
        {
            "category":"Arena",
            "subcategory":"Sports Club",
            "type":"Entertainment"
        }
    ],
    "sg:phone":"+32 9 372 66 65",
    "sg:postcode":"9950",
    "sg:province":"Oost-Vlaanderen",
    "sg:tags":[
        "terrain",
        "hors",
        "de",
        "installation",
        "sportifs"
    ],
    "wof:name":"Ksk De Jeugd Lovendegem",
    "wof:placetype":"venue"
},
  "geometry": {"coordinates":[3.6107079983,51.1238212585],"type":"Point"}
}