{
  "type": "Feature",
  "properties": {
    "iso:country":"BE",
    "sg:address":"Dijkstraat 24",
    "sg:city":"Dessel",
    "sg:classifiers":[
        {
            "category":"Farming",
            "subcategory":"Farm & Veterinary Services",
            "type":"Manufacturing & Wholesale Goods"
        }
    ],
    "sg:phone":"+32 14 37 96 25",
    "sg:postcode":"2480",
    "sg:province":"Antwerpen",
    "sg:tags":[
        "agricultural",
        "contractor"
    ],
    "wof:name":"Bogaerts L",
    "wof:placetype":"venue"
},
  "geometry": {"coordinates":[5.1221141815,51.2355422974],"type":"Point"}
}