{
  "type": "Feature",
  "properties": {
    "iso:country":"BE",
    "sg:address":"Dorp 90",
    "sg:city":"Lille (poederlee)",
    "sg:classifiers":[
        {
            "category":"Health Services",
            "subcategory":"Health Practitioner",
            "type":"Services"
        }
    ],
    "sg:phone":"+32 14 88 25 09",
    "sg:postcode":"2275",
    "sg:province":"Antwerpen",
    "sg:tags":[
        "physiotherapist"
    ],
    "wof:name":"Verellen Ann",
    "wof:placetype":"venue"
},
  "geometry": {"coordinates":[4.8347101212,51.2293815613],"type":"Point"}
}