{
  "type": "Feature",
  "properties": {
    "addr:full":"Verhoevenlei 140 Brasschaat Antwerpen 2930",
    "addr:housenumber":"140",
    "addr:postcode":"2930",
    "iso:country":"BE",
    "sg:address":"Verhoevenlei 140",
    "sg:city":"Brasschaat",
    "sg:classifiers":[
        {
            "category":"Fast Food",
            "type":"Food & Drink"
        }
    ],
    "sg:phone":"+32 3 651 47 21",
    "sg:postcode":"2930",
    "sg:province":"Antwerpen",
    "sg:tags":[
        "fried",
        "stand",
        "potato"
    ],
    "wof:name":"Centrum",
    "wof:placetype":"venue"
},
  "geometry": {"coordinates":[4.4830307961,51.2914581299],"type":"Point"}
}