{
  "type": "Feature",
  "properties": {
    "addr:full":"Dorpsstraat 255 Kortenberg (meerbeek) Vlaams-Brabant 3078",
    "addr:housenumber":"255",
    "addr:postcode":"3078",
    "addr:street":"Dorpsstraat",
    "iso:country":"BE",
    "sg:address":"Dorpsstraat 255",
    "sg:city":"Kortenberg (meerbeek)",
    "sg:classifiers":[
        {
            "category":"Health Services",
            "subcategory":"Doctor",
            "type":"Services"
        }
    ],
    "sg:phone":"+32 2 757 08 10",
    "sg:postcode":"3078",
    "sg:province":"Vlaams-Brabant",
    "sg:tags":[
        "medicinephysicians",
        "surgeon"
    ],
    "wof:name":"Lambrechts Magdalena",
    "wof:placetype":"venue"
},
  "geometry": {"coordinates":[4.5838689804,50.8779449463],"type":"Point"}
}