{
  "type": "Feature",
  "properties": {
    "addr:full":"Astridlaan 406 Brugge West-Vlaanderen 8310",
    "addr:housenumber":"406",
    "addr:postcode":"8310",
    "addr:street":"Astridlaan",
    "iso:country":"BE",
    "sg:address":"Astridlaan 406",
    "sg:city":"Brugge",
    "sg:orig_category":"Sportclubs",
    "sg:phone":"+32 50 35 04 07",
    "sg:postcode":"8310",
    "sg:province":"West-Vlaanderen",
    "wof:name":"Families Helpen Families",
    "wof:placetype":"venue"
},
  "geometry": {"coordinates":[3.2573299408,51.1949081421],"type":"Point"}
}