{
  "type": "Feature",
  "properties": {
    "addr:full":"Rue Du Foss\u00c9 Aux Loups 26 Brussel/bruxelles Bruxelles-Capitale 1000",
    "addr:housenumber":"26",
    "addr:postcode":"1000",
    "addr:street":"Rue Du Fosse\u0301 Aux Loups;/",
    "iso:country":"BE",
    "sg:address":"Rue Du Foss\u00c9 Aux Loups 26",
    "sg:city":"Brussel/bruxelles",
    "sg:orig_category":"Agences d\u00b4interim and personnel temporaire",
    "sg:phone":"+32 2 219 72 00",
    "sg:postcode":"1000",
    "sg:province":"Bruxelles-Capitale",
    "wof:name":"Assoc-int\u00c9rim",
    "wof:placetype":"venue"
},
  "geometry": {"coordinates":[4.3539090157,50.8505477905],"type":"Point"}
}