{
  "type": "Feature",
  "properties": {
    "addr:full":"Place Josse Goffin 19 Tubize Brabant Wallon 1480",
    "addr:housenumber":"19",
    "addr:postcode":"1480",
    "addr:street":"Place Josse Goffin;Wallon",
    "iso:country":"BE",
    "sg:address":"Place Josse Goffin 19",
    "sg:city":"Tubize",
    "sg:orig_category":"Entretien and r\u00e9parations de voitures",
    "sg:phone":"+32 2 355 87 53",
    "sg:postcode":"1480",
    "sg:province":"Brabant Wallon",
    "wof:name":"Garage Rompato",
    "wof:placetype":"venue"
},
  "geometry": {"coordinates":[4.2213959694,50.6893234253],"type":"Point"}
}