{
  "type": "Feature",
  "properties": {
    "addr:full":"Avenue Du Val St.georges 96 Namur Namur 5000",
    "addr:housenumber":"96",
    "addr:postcode":"5000",
    "addr:street":"Avenue Du Val St.Georges",
    "iso:country":"BE",
    "sg:address":"Avenue Du Val St.georges 96",
    "sg:city":"Namur",
    "sg:orig_category":"Plomberie, chauffage and installations sanitaires",
    "sg:phone":"+32 81 73 62 90",
    "sg:postcode":"5000",
    "sg:province":"Namur",
    "wof:name":"Chauffage Ren\u00c9 Janssen",
    "wof:placetype":"venue"
},
  "geometry": {"coordinates":[4.8401079178,50.4647941589],"type":"Point"}
}