{
  "type": "Feature",
  "properties": {
    "addr:full":"Haachtsesteenweg 506 Kampenhout Vlaams-Brabant 1910",
    "addr:housenumber":"506",
    "addr:postcode":"1910",
    "addr:street":"Haachtsesteenweg",
    "iso:country":"BE",
    "sg:address":"Haachtsesteenweg 506",
    "sg:city":"Kampenhout",
    "sg:orig_category":"Pain, p\u00e2tisseries and confiseries",
    "sg:phone":"+32 16 65 13 90",
    "sg:postcode":"1910",
    "sg:province":"Vlaams-Brabant",
    "wof:name":"Bakkerij Croissy",
    "wof:placetype":"venue"
},
  "geometry": {"coordinates":[4.5703101158,50.9455909729],"type":"Point"}
}