{
  "type": "Feature",
  "properties": {
    "addr:full":"Rue Des Coudriers 1 Aywaille Li\u00e8ge 4920",
    "addr:housenumber":"1",
    "addr:postcode":"4920",
    "addr:street":"Rue Des Coudriers",
    "iso:country":"BE",
    "sg:address":"Rue Des Coudriers 1",
    "sg:city":"Aywaille",
    "sg:orig_category":"Services divers aux entreprises. Antiquit\u00e9s",
    "sg:phone":"+32 476 94 93 70",
    "sg:postcode":"4920",
    "sg:province":"Li\u00e8ge",
    "wof:name":"Arts & Antiques",
    "wof:placetype":"venue"
},
  "geometry": {"coordinates":[-6.2555279732,53.3624305725],"type":"Point"}
}