{
  "type": "Feature",
  "properties": {
    "iso:country":"BE",
    "sg:address":"22 B Avenue Franklin Roosvelt -",
    "sg:city":"Brussels",
    "sg:classifiers":[
        {
            "category":"Professional",
            "subcategory":"Art Services",
            "type":"Services"
        }
    ],
    "sg:phone":"+32 2 640 11 69",
    "sg:postcode":"1050",
    "sg:province":"Bruxelles-Capitale",
    "sg:tags":[
        "export-import"
    ],
    "wof:name":"Uruguay Embassy",
    "wof:placetype":"venue"
},
  "geometry": {"coordinates":[4.3963398933,50.7970123291],"type":"Point"}
}