{
  "type": "Feature",
  "properties": {
    "iso:country":"BE",
    "sg:address":"Rue De La Gendarmerie 50",
    "sg:city":"Philippeville",
    "sg:orig_category":"Installation de menuiserie en bois and plastique",
    "sg:phone":"+32 71 66 88 06",
    "sg:postcode":"5600",
    "sg:province":"Namur",
    "wof:name":"Fabribois",
    "wof:placetype":"venue"
},
  "geometry": {"coordinates":[4.5551600456,50.1990509033],"type":"Point"}
}