{
  "type": "Feature",
  "properties": {
    "addr:full":"Emiel Van Dorenlaan 120 Genk Limburg 3600",
    "addr:housenumber":"120",
    "addr:postcode":"3600",
    "addr:street":"Emiel Van Dorenlaan",
    "iso:country":"BE",
    "sg:address":"Emiel Van Dorenlaan 120",
    "sg:city":"Genk",
    "sg:classifiers":[
        {
            "category":"Professional",
            "subcategory":"Detective & Security Services",
            "type":"Services"
        }
    ],
    "sg:phone":"+32 89 77 88 50",
    "sg:postcode":"3600",
    "sg:province":"Limburg",
    "sg:tags":[
        "guard"
    ],
    "wof:name":"Dog Master Security Bvba",
    "wof:placetype":"venue"
},
  "geometry": {"coordinates":[5.5092849731,50.9907608032],"type":"Point"}
}