{
  "type": "Feature",
  "properties": {
    "iso:country":"BE",
    "sg:address":"Rue De Von\u00e8che 156",
    "sg:city":"Daverdisse (haut-fays)",
    "sg:classifiers":[
        {
            "category":"Bakery",
            "type":"Food & Drink"
        }
    ],
    "sg:phone":"+32 61 58 82 25",
    "sg:postcode":"6929",
    "sg:province":"Luxembourg",
    "sg:tags":[
        "confectioner",
        "baker"
    ],
    "wof:name":"Gilet M",
    "wof:placetype":"venue"
},
  "geometry": {"coordinates":[5.0165438652,50.0030899048],"type":"Point"}
}