{
  "type": "Feature",
  "properties": {
    "iso:country":"BE",
    "sg:address":"Rue Sur Le Bois 60",
    "sg:city":"Vis\u00e9 (argenteau)",
    "sg:classifiers":[
        {
            "category":"Health Services",
            "subcategory":"Health Practitioner",
            "type":"Services"
        }
    ],
    "sg:phone":"+32 4 379 18 20",
    "sg:postcode":"4601",
    "sg:province":"Li\u00e8ge",
    "sg:tags":[
        "physiotherapist"
    ],
    "wof:name":"Gasc Virginie",
    "wof:placetype":"venue"
},
  "geometry": {"coordinates":[5.6797041893,50.6951828003],"type":"Point"}
}