{
  "type": "Feature",
  "properties": {
    "iso:country":"BE",
    "sg:address":"Bois Des Chevreuils 17",
    "sg:city":"Esneux (tilff)",
    "sg:classifiers":[
        {
            "category":"Real Estate",
            "subcategory":"Surveying",
            "type":"Services"
        }
    ],
    "sg:phone":"+32 4 368 61 94",
    "sg:postcode":"4130",
    "sg:province":"Li\u00e8ge",
    "sg:tags":[
        "lettering",
        "letter"
    ],
    "wof:name":"Ciarlan D",
    "wof:placetype":"venue"
},
  "geometry": {"coordinates":[5.6085639,50.5643005371],"type":"Point"}
}