{
  "type": "Feature",
  "properties": {
    "addr:full":"Rue De Comines 7 Mouscron Hainaut 7700",
    "addr:housenumber":"7",
    "addr:postcode":"7700",
    "addr:street":"Rue De Comines",
    "iso:country":"BE",
    "sg:address":"Rue De Comines 7",
    "sg:city":"Mouscron",
    "sg:classifiers":[
        {
            "category":"Shopping",
            "subcategory":"Pets & Pet Supplies",
            "type":"Retail Goods"
        }
    ],
    "sg:phone":"+32 56 84 68 62",
    "sg:postcode":"7700",
    "sg:province":"Hainaut",
    "sg:tags":[
        "aquarium",
        "accessory"
    ],
    "wof:name":"Poisson D'or",
    "wof:placetype":"venue"
},
  "geometry": {"coordinates":[3.2049629688,50.7532272339],"type":"Point"}
}