{
  "type": "Feature",
  "properties": {
    "addr:full":"Rivierstraat 90 Turnhout Antwerpen 2300",
    "addr:housenumber":"90",
    "addr:postcode":"2300",
    "addr:street":"Rivierstraat",
    "iso:country":"BE",
    "sg:address":"Rivierstraat 90",
    "sg:city":"Turnhout",
    "sg:classifiers":[
        {
            "category":"Health Services",
            "subcategory":"Health Practitioner",
            "type":"Services"
        }
    ],
    "sg:phone":"+32 14 42 72 05",
    "sg:postcode":"2300",
    "sg:province":"Antwerpen",
    "sg:tags":[
        "physiotherapist"
    ],
    "wof:name":"Van Dijck Denise",
    "wof:placetype":"venue"
},
  "geometry": {"coordinates":[4.9375090599,51.3156929016],"type":"Point"}
}