{
  "type": "Feature",
  "properties": {
    "iso:country":"BE",
    "sg:address":"Place De Plancenoit 21a",
    "sg:city":"Lasne (plancenoit)",
    "sg:classifiers":[
        {
            "category":"Organizations",
            "subcategory":"Community Association",
            "type":"Services"
        }
    ],
    "sg:phone":"+32 2 478 94 18",
    "sg:postcode":"1380",
    "sg:province":"Brabant Wallon",
    "sg:tags":[
        "purchasing"
    ],
    "wof:name":"Best Deal",
    "wof:placetype":"venue"
},
  "geometry": {"coordinates":[4.4307742119,50.6605453491],"type":"Point"}
}