{
  "type": "Feature",
  "properties": {
    "iso:country":"BE",
    "sg:address":"Driehuizen 17",
    "sg:city":"Buggenhout",
    "sg:orig_category":"Artistes ind\u00e9pendants",
    "sg:phone":"+32 52 33 54 80",
    "sg:postcode":"9255",
    "sg:province":"Oost-Vlaanderen",
    "wof:name":"Eddy Asselbergs",
    "wof:placetype":"venue"
},
  "geometry": {"coordinates":[4.2390961647,51.0364685059],"type":"Point"}
}