{
  "type": "Feature",
  "properties": {
    "addr:full":"Boulevard De La Cambre 40 Box 14 Bruxelles Bruxelles-Capitale 1000",
    "addr:housenumber":"40 box 14",
    "addr:postcode":"1000",
    "addr:street":"Boulevard De La Cambre",
    "iso:country":"BE",
    "sg:address":"Boulevard De La Cambre 40 Box 14",
    "sg:city":"Bruxelles",
    "sg:classifiers":[
        {
            "category":"Banks & Credit Unions",
            "subcategory":"Investment Brokerage",
            "type":"Services"
        }
    ],
    "sg:phone":"+32 2 647 80 16",
    "sg:postcode":"1000",
    "sg:province":"Bruxelles-Capitale",
    "sg:tags":[
        "aid",
        "rehabiliation",
        "apparatus"
    ],
    "wof:name":"'r Go Dynamic Consulting",
    "wof:placetype":"venue"
},
  "geometry": {"coordinates":[4.3747091293,50.8159370422],"type":"Point"}
}