{
  "type": "Feature",
  "properties": {
    "iso:country":"BE",
    "sg:address":"Rue Pisseroule 137-139",
    "sg:city":"Dison",
    "sg:classifiers":[
        {
            "category":"Retail",
            "subcategory":"Auto Repair",
            "type":"Services"
        }
    ],
    "sg:phone":"+32 87 33 39 80",
    "sg:postcode":"4820",
    "sg:province":"Li\u00e8ge",
    "sg:tags":[
        "automobile-body"
    ],
    "wof:name":"Peters S",
    "wof:placetype":"venue"
},
  "geometry": {"coordinates":[5.8544697762,50.6027107239],"type":"Point"}
}