{
  "type": "Feature",
  "properties": {
    "iso:country":"BE",
    "sg:address":"Wiekenstraat 9",
    "sg:city":"Oostkamp",
    "sg:orig_category":"Installation de menuiserie en bois and plastique",
    "sg:phone":"+32 50 27 77 20",
    "sg:postcode":"8020",
    "sg:province":"West-Vlaanderen",
    "wof:name":"Alexander Warnier",
    "wof:placetype":"venue"
},
  "geometry": {"coordinates":[3.2046449184,51.0914649963],"type":"Point"}
}