{
  "type": "Feature",
  "properties": {
    "iso:country":"BE",
    "sg:address":"Rue Royale 58",
    "sg:city":"Tournai",
    "sg:orig_category":"Slagers",
    "sg:phone":"+32 69 21 42 95",
    "sg:postcode":"7500",
    "sg:province":"Hainaut",
    "wof:name":"Boucherie Christian",
    "wof:placetype":"venue"
},
  "geometry": {"coordinates":[3.3929929733,50.6100692749],"type":"Point"}
}