{
  "type": "Feature",
  "properties": {
    "addr:full":"Villastraat 3 Moeskroen Hainaut 7700",
    "addr:housenumber":"3",
    "addr:postcode":"7700",
    "addr:street":"Villastraat;Hainaut",
    "iso:country":"BE",
    "sg:address":"Villastraat 3",
    "sg:city":"Moeskroen",
    "sg:orig_category":"Articles textiles and tissus de d\u00e9coration Fab. Articles de f\u00eate, farces and attrapes",
    "sg:phone":"+32 56 34 40 06",
    "sg:postcode":"7700",
    "sg:province":"Hainaut",
    "wof:name":"Concerti",
    "wof:placetype":"venue"
},
  "geometry": {"coordinates":[3.2097630501,50.7439308167],"type":"Point"}
}