{
  "type": "Feature",
  "properties": {
    "addr:full":"Motstraat 72 Mechelen Antwerpen 2800",
    "addr:housenumber":"72",
    "addr:postcode":"2800",
    "addr:street":"Motstraat",
    "iso:country":"BE",
    "sg:address":"Motstraat 72",
    "sg:city":"Mechelen",
    "sg:classifiers":[
        {
            "category":"Home & Garden",
            "subcategory":"Home Furnishings",
            "type":"Retail Goods"
        }
    ],
    "sg:phone":"+32 15 41 30 49",
    "sg:postcode":"2800",
    "sg:province":"Antwerpen",
    "sg:tags":[
        "interior",
        "decoration"
    ],
    "wof:name":"Kiebooms E",
    "wof:placetype":"venue"
},
  "geometry": {"coordinates":[4.4880218506,51.0147018433],"type":"Point"}
}