{
  "type": "Feature",
  "properties": {
    "iso:country":"BE",
    "sg:address":"Wortegemseweg 37",
    "sg:city":"Waregem",
    "sg:orig_category":"M\u00e9decins and sp\u00e9cialistes",
    "sg:phone":"+32 56 61 39 39",
    "sg:postcode":"8790",
    "sg:province":"West-Vlaanderen",
    "wof:name":"Lieve Van Eeckhoutte",
    "wof:placetype":"venue"
},
  "geometry": {"coordinates":[3.4440860748,50.8761405945],"type":"Point"}
}