{
  "type": "Feature",
  "properties": {
    "iso:country":"BE",
    "sg:address":"Sint-rochusstraat 29",
    "sg:city":"Antwerpen",
    "sg:orig_category":"Voedingsspeciaalzaken",
    "sg:phone":"+32 3 321 48 98",
    "sg:postcode":"2100",
    "sg:province":"Antwerpen",
    "wof:name":"Huis Regiform",
    "wof:placetype":"venue"
},
  "geometry": {"coordinates":[4.4000759125,51.2124633789],"type":"Point"}
}