{
  "type": "Feature",
  "properties": {
    "addr:full":"Rue Bergenblok 21 Wezembeek-oppem Vlaams-Brabant 1970",
    "addr:housenumber":"21",
    "addr:postcode":"1970",
    "addr:street":"Rue Bergenblok",
    "iso:country":"BE",
    "sg:address":"Rue Bergenblok 21",
    "sg:city":"Wezembeek-oppem",
    "sg:classifiers":[
        {
            "category":"Home & Garden",
            "subcategory":"Garden Supply",
            "type":"Retail Goods"
        }
    ],
    "sg:phone":"+32 2 731 56 99",
    "sg:postcode":"1970",
    "sg:province":"Vlaams-Brabant",
    "wof:name":"Floralies Garden",
    "wof:placetype":"venue"
},
  "geometry": {"coordinates":[4.4876499176,50.8532104492],"type":"Point"}
}