{
  "type": "Feature",
  "properties": {
    "addr:full":"Oosteindeken 39 Lokeren Oost-Vlaanderen 9160",
    "addr:housenumber":"39",
    "addr:postcode":"9160",
    "addr:street":"Oosteindeken",
    "iso:country":"BE",
    "sg:address":"Oosteindeken 39",
    "sg:city":"Lokeren",
    "sg:classifiers":[
        {
            "category":"Arena",
            "subcategory":"Sports Club",
            "type":"Entertainment"
        }
    ],
    "sg:phone":"+32 9 346 79 47",
    "sg:postcode":"9160",
    "sg:province":"Oost-Vlaanderen",
    "sg:tags":[
        "de"
    ],
    "wof:name":"Elk Zijn Recht",
    "wof:placetype":"venue"
},
  "geometry": {"coordinates":[4.0112500191,51.0890197754],"type":"Point"}
}