{
  "type": "Feature",
  "properties": {
    "addr:full":"Avenue Jean Monnet 12 Sint-lambrechts-woluwe/woluwe-saint-lambert Bruxelles-Capitale 1200",
    "addr:housenumber":"12",
    "addr:postcode":"1200",
    "addr:street":"Avenue Jean Monnet",
    "iso:country":"BE",
    "sg:address":"Avenue Jean Monnet 12",
    "sg:city":"Sint-lambrechts-woluwe/woluwe-saint-lambert",
    "sg:classifiers":[
        {
            "category":"Insurance",
            "subcategory":"Life Insurance",
            "type":"Services"
        }
    ],
    "sg:phone":"+32 2 779 26 26",
    "sg:postcode":"1200",
    "sg:province":"Bruxelles-Capitale",
    "sg:tags":[
        "assurance"
    ],
    "wof:name":"Brufimas",
    "wof:placetype":"venue"
},
  "geometry": {"coordinates":[4.4315881729,50.855430603],"type":"Point"}
}