{
  "type": "Feature",
  "properties": {
    "iso:country":"BE",
    "sg:address":"Elzendreef 6",
    "sg:city":"Essen",
    "sg:orig_category":"Diverse zakelijke dienstverlening",
    "sg:phone":"+32 3 677 36 65",
    "sg:postcode":"2910",
    "sg:province":"Antwerpen",
    "wof:name":"Van Der Mast",
    "wof:placetype":"venue"
},
  "geometry": {"coordinates":[4.4399662018,51.4551010132],"type":"Point"}
}