{
  "type": "Feature",
  "properties": {
    "addr:full":"Drieshoek 7ba Harelbeke West-Vlaanderen 8531",
    "addr:postcode":"8531",
    "addr:street":"Drieshoek",
    "iso:country":"BE",
    "sg:address":"Drieshoek 7ba",
    "sg:city":"Harelbeke",
    "sg:orig_category":"Paramedische behandelingen",
    "sg:phone":"+32 56 72 93 25",
    "sg:postcode":"8531",
    "sg:province":"West-Vlaanderen",
    "wof:name":"H. Dewaele",
    "wof:placetype":"venue"
},
  "geometry": {"coordinates":[3.2956910133,50.8678779602],"type":"Point"}
}