{
  "type": "Feature",
  "properties": {
    "iso:country":"BE",
    "sg:address":"Rue Er\u00c8ne 1",
    "sg:city":"Marche-en-famenne",
    "sg:orig_category":"Activit\u00e9s d\u00b4action sociale sans h\u00e9bergement",
    "sg:phone":"+32 84 31 23 18",
    "sg:postcode":"6900",
    "sg:province":"Luxembourg",
    "wof:name":"Centre P.m.s.",
    "wof:placetype":"venue"
},
  "geometry": {"coordinates":[5.3469481468,50.2308616638],"type":"Point"}
}