{
  "type": "Feature",
  "properties": {
    "iso:country":"BE",
    "sg:address":"Rue Cambier Dupret 37",
    "sg:city":"Charleroi",
    "sg:orig_category":"Travaux de finition and nettoyage de b\u00e2timents. Installation de menuiserie en bois and plastique. Lo",
    "sg:phone":"+32 71 47 85 78",
    "sg:postcode":"6001",
    "sg:province":"Hainaut",
    "wof:name":"A.p.",
    "wof:placetype":"venue"
},
  "geometry": {"coordinates":[4.445939064,50.4045753479],"type":"Point"}
}