{
  "type": "Feature",
  "properties": {
    "iso:country":"BE",
    "sg:address":"Rue Du Cardinal Mercier 35",
    "sg:city":"Brussel/bruxelles",
    "sg:orig_category":"Activit\u00e9s diverses d'imprimerie. Imprimeries and copyshops",
    "sg:phone":"+32 2 545 66 66",
    "sg:postcode":"1000",
    "sg:province":"Bruxelles-Capitale",
    "wof:name":"Production +",
    "wof:placetype":"venue"
},
  "geometry": {"coordinates":[4.3571882248,50.8463516235],"type":"Point"}
}