{
  "type": "Feature",
  "properties": {
    "addr:full":"Kapucijnenvest 11ba Lier Antwerpen 2500",
    "addr:housenumber":"11ba",
    "addr:postcode":"2500",
    "addr:street":"Kapucijnenvest",
    "iso:country":"BE",
    "sg:address":"Kapucijnenvest 11ba",
    "sg:city":"Lier",
    "sg:orig_category":"Pretparken, kermissen and recreatiedomeinen",
    "sg:phone":"+32 3 480 93 88",
    "sg:postcode":"2500",
    "sg:province":"Antwerpen",
    "wof:name":"Toerist Tram",
    "wof:placetype":"venue"
},
  "geometry": {"coordinates":[4.5669260025,51.1306228638],"type":"Point"}
}