{
  "type": "Feature",
  "properties": {
    "iso:country":"BE",
    "sg:address":"R Des M\u00fbriers 34",
    "sg:city":"Jambes",
    "sg:classifiers":[
        {
            "category":"Wholesale",
            "subcategory":"Machinery & Supplies",
            "type":"Manufacturing & Wholesale Goods"
        }
    ],
    "sg:phone":"+32 4 370 91 01",
    "sg:postcode":"5100",
    "sg:province":"Namur",
    "sg:tags":[
        "equipment",
        "precision"
    ],
    "wof:name":"Medical Lux Sprl",
    "wof:placetype":"venue"
},
  "geometry": {"coordinates":[5.6446208954,50.6428184509],"type":"Point"}
}