{
  "type": "Feature",
  "properties": {
    "addr:full":"Philippe Baucqstraat 33 Etterbeek/etterbeek Bruxelles-Capitale 1040",
    "addr:housenumber":"33",
    "addr:postcode":"1040",
    "addr:street":"Baucqstraat",
    "iso:country":"BE",
    "sg:address":"Philippe Baucqstraat 33",
    "sg:city":"Etterbeek/etterbeek",
    "sg:orig_category":"Diverse grafische activiteiten",
    "sg:phone":"+32 2 647 89 07",
    "sg:postcode":"1040",
    "sg:province":"Bruxelles-Capitale",
    "wof:name":"Comics Cartoons Corp.",
    "wof:placetype":"venue"
},
  "geometry": {"coordinates":[4.3861131668,50.8318519592],"type":"Point"}
}