{
  "type": "Feature",
  "properties": {
    "addr:full":"Margrietstraat 65 Sint-gillis-waas Oost-Vlaanderen 9170",
    "addr:housenumber":"65",
    "addr:postcode":"9170",
    "addr:street":"Margrietstraat",
    "iso:country":"BE",
    "sg:address":"Margrietstraat 65",
    "sg:city":"Sint-gillis-waas",
    "sg:orig_category":"Installation \u00e9lectrique r\u00e9sidentielle. Electrom\u00e9nager, t\u00e9l\u00e9visions and radios. R\u00e9parations d'apparei",
    "sg:phone":"+32 3 773 40 94",
    "sg:postcode":"9170",
    "sg:province":"Oost-Vlaanderen",
    "wof:name":"Roger De Meulenaer",
    "wof:placetype":"venue"
},
  "geometry": {"coordinates":[4.1501030922,51.2574272156],"type":"Point"}
}