{
  "type": "Feature",
  "properties": {
    "iso:country":"BE",
    "sg:address":"Rue L\u00c9on Fr\u00c9d\u00c9ric 31",
    "sg:city":"Brussel/bruxelles",
    "sg:orig_category":"Vertalers and tolken",
    "sg:phone":"+32 2 732 44 27",
    "sg:postcode":"1030",
    "sg:province":"Bruxelles-Capitale",
    "wof:name":"Teran-larraguibel L. Cbtip/bkvtf",
    "wof:placetype":"venue"
},
  "geometry": {"coordinates":[4.3972878456,50.849697113],"type":"Point"}
}