{
  "type": "Feature",
  "properties": {
    "addr:full":"Marktplein 82 Sint-lievens-houtem Oost-Vlaanderen 9520",
    "addr:housenumber":"82",
    "addr:postcode":"9520",
    "addr:street":"Marktplein",
    "iso:country":"BE",
    "sg:address":"Marktplein 82",
    "sg:city":"Sint-lievens-houtem",
    "sg:orig_category":"Postkantoren Verzekeringsmakelaars and experts",
    "sg:phone":"+32 53 60 54 10",
    "sg:postcode":"9520",
    "sg:province":"Oost-Vlaanderen",
    "wof:name":"De Post",
    "wof:placetype":"venue"
},
  "geometry": {"coordinates":[3.854528904,50.9208641052],"type":"Point"}
}