{
  "type": "Feature",
  "properties": {
    "addr:full":"Holvenstraat 209 Overpelt Limburg 3900",
    "addr:housenumber":"209",
    "addr:postcode":"3900",
    "addr:street":"Holvenstraat",
    "iso:country":"BE",
    "sg:address":"Holvenstraat 209",
    "sg:city":"Overpelt",
    "sg:classifiers":[
        {
            "category":"Building & Trades",
            "subcategory":"Construction",
            "type":"Services"
        }
    ],
    "sg:phone":"+32 11 66 76 22",
    "sg:postcode":"3900",
    "sg:province":"Limburg",
    "sg:tags":[
        "stucco",
        "contractor"
    ],
    "wof:name":"Kums",
    "wof:placetype":"venue"
},
  "geometry": {"coordinates":[5.3669610023,51.2023010254],"type":"Point"}
}