{
  "type": "Feature",
  "properties": {
    "iso:country":"BE",
    "sg:address":"Otegemstraat 81",
    "sg:city":"Zwevegem",
    "sg:classifiers":[
        {
            "category":"Bars & Pubs",
            "type":"Food & Drink"
        }
    ],
    "sg:phone":"+32 56 75 83 10",
    "sg:postcode":"8550",
    "sg:province":"West-Vlaanderen",
    "wof:name":"Hof Van Brabant",
    "wof:placetype":"venue"
},
  "geometry": {"coordinates":[3.3395380974,50.8136444092],"type":"Point"}
}