{
  "type": "Feature",
  "properties": {
    "iso:country":"BE",
    "sg:address":"Winkelaar 1",
    "sg:city":"Zandhoven",
    "sg:orig_category":"Travaux d'isolation",
    "sg:phone":"+32 14 22 15 91",
    "sg:postcode":"2240",
    "sg:province":"Antwerpen",
    "wof:name":"Bofa",
    "wof:placetype":"venue"
},
  "geometry": {"coordinates":[4.6615819931,51.2029380798],"type":"Point"}
}