{
  "type": "Feature",
  "properties": {
    "addr:full":"Groene Dreef 32 Kortrijk (rollegem) West-Vlaanderen 8510",
    "addr:housenumber":"32",
    "addr:postcode":"8510",
    "addr:street":"Groene Dreef",
    "iso:country":"BE",
    "sg:address":"Groene Dreef 32",
    "sg:city":"Kortrijk (rollegem)",
    "sg:classifiers":[
        {
            "category":"Real Estate",
            "subcategory":"Real Estate Services",
            "type":"Services"
        }
    ],
    "sg:phone":"+32 56 20 30 27",
    "sg:postcode":"8510",
    "sg:province":"West-Vlaanderen",
    "wof:name":"Patco",
    "wof:placetype":"venue"
},
  "geometry": {"coordinates":[3.2622981071,50.7877655029],"type":"Point"}
}