{
  "type": "Feature",
  "properties": {
    "iso:country":"BE",
    "sg:address":"Alfons Pieterslaan 102",
    "sg:city":"Oostende",
    "sg:orig_category":"Mat\u00e9riel de T\u00e9l\u00e9communication. Equipement photographique. Electrom\u00e9nager, t\u00e9l\u00e9visions and radios. St",
    "sg:phone":"+32 59 80 28 48",
    "sg:postcode":"8400",
    "sg:province":"West-Vlaanderen",
    "wof:name":"Tuyttens",
    "wof:placetype":"venue"
},
  "geometry": {"coordinates":[2.9107570648,51.22498703],"type":"Point"}
}