{
  "type": "Feature",
  "properties": {
    "iso:country":"BE",
    "sg:address":"Laarstraat 113-115",
    "sg:city":"Zwijndrecht",
    "sg:classifiers":[
        {
            "category":"Food & Beverages",
            "subcategory":"Groceries & Convenience Stores",
            "type":"Retail Goods"
        }
    ],
    "sg:phone":"+32 3 252 74 11",
    "sg:postcode":"2070",
    "sg:province":"Antwerpen",
    "sg:tags":[
        "grocer"
    ],
    "wof:name":"Prima Heyrman-vermeulen",
    "wof:placetype":"venue"
},
  "geometry": {"coordinates":[4.3391518593,51.2163162231],"type":"Point"}
}