{
  "type": "Feature",
  "properties": {
    "addr:full":"Cijnshofstraat 3 Heusden-zolder Limburg 3550",
    "addr:housenumber":"3",
    "addr:postcode":"3550",
    "addr:street":"Cijnshofstraat",
    "iso:country":"BE",
    "sg:address":"Cijnshofstraat 3",
    "sg:city":"Heusden-zolder",
    "sg:orig_category":"Cr\u00e9dits divers",
    "sg:postcode":"3550",
    "sg:province":"Limburg",
    "wof:name":"Bancontact-mister Cash",
    "wof:placetype":"venue"
},
  "geometry": {"coordinates":[5.2809109688,51.0326919556],"type":"Point"}
}