{
  "type": "Feature",
  "properties": {
    "addr:full":"Avenue Des Tilleuls Chimay Hainaut 6460",
    "addr:postcode":"6460",
    "addr:street":"Avenue Des Tilleuls;Hainaut",
    "iso:country":"BE",
    "sg:address":"Avenue Des Tilleuls",
    "sg:city":"Chimay",
    "sg:classifiers":[
        {
            "category":"Professional",
            "subcategory":"Advertising",
            "type":"Services"
        }
    ],
    "sg:phone":"+32 60 21 29 85",
    "sg:postcode":"6460",
    "sg:province":"Hainaut",
    "sg:tags":[
        "item",
        "-",
        "business",
        "gift",
        "promotional"
    ],
    "wof:name":"Coene-marcoux",
    "wof:placetype":"venue"
},
  "geometry": {"coordinates":[4.3077697754,50.0458831787],"type":"Point"}
}