{
  "type": "Feature",
  "properties": {
    "iso:country":"BE",
    "sg:address":"Rue Alfred Rousseaux 3",
    "sg:city":"Beaumont",
    "sg:orig_category":"Rundveehouders",
    "sg:phone":"+32 71 58 81 68",
    "sg:postcode":"6500",
    "sg:province":"Hainaut",
    "wof:name":"Jean-claude Dupuis",
    "wof:placetype":"venue"
},
  "geometry": {"coordinates":[4.1935868263,50.2197380066],"type":"Point"}
}