{
  "type": "Feature",
  "properties": {
    "addr:full":"Rue De Sendrogne 160 Sprimont (louveign\u00e9) Li\u00e8ge 4141",
    "addr:housenumber":"160",
    "addr:postcode":"4141",
    "addr:street":"Rue De Sendrogne",
    "iso:country":"BE",
    "sg:address":"Rue De Sendrogne 160",
    "sg:city":"Sprimont (louveign\u00e9)",
    "sg:classifiers":[
        {
            "category":"Organizations",
            "subcategory":"Labor Organization",
            "type":"Services"
        }
    ],
    "sg:phone":"+32 4 360 91 88",
    "sg:postcode":"4141",
    "sg:province":"Li\u00e8ge",
    "sg:tags":[
        "harness",
        "maker",
        "saddler"
    ],
    "wof:name":"De Henne Sellerie (sdh)",
    "wof:placetype":"venue"
},
  "geometry": {"coordinates":[5.7102560997,50.5312538147],"type":"Point"}
}