{
  "type": "Feature",
  "properties": {
    "iso:country":"BE",
    "sg:address":"Bergensesteenweg 585",
    "sg:city":"Halle (lembeek)",
    "sg:classifiers":[
        {
            "category":"Home & Garden",
            "subcategory":"Carpets & Floor Coverings",
            "type":"Retail Goods"
        }
    ],
    "sg:phone":"+32 2 356 73 95",
    "sg:postcode":"1502",
    "sg:province":"Vlaams-Brabant",
    "sg:tags":[
        "industrial",
        "-"
    ],
    "wof:name":"Intilla Vincenzo",
    "wof:placetype":"venue"
},
  "geometry": {"coordinates":[4.2224087715,50.7174339294],"type":"Point"}
}