{
  "type": "Feature",
  "properties": {
    "iso:country":"BE",
    "sg:address":"Schapenstraat 89",
    "sg:city":"Ukkel/uccle",
    "sg:orig_category":"Landmeters and schatters",
    "sg:phone":"+32 2 374 03 82",
    "sg:postcode":"1180",
    "sg:province":"Bruxelles-Capitale",
    "wof:name":"Arbres Bois Eaux Forest",
    "wof:placetype":"venue"
},
  "geometry": {"coordinates":[4.3387560844,50.7939872742],"type":"Point"}
}