{
  "type": "Feature",
  "properties": {
    "addr:full":"Kerkweg 5 Ieper West-Vlaanderen 8900",
    "addr:housenumber":"5",
    "addr:postcode":"8900",
    "addr:street":"Kerkweg",
    "iso:country":"BE",
    "sg:address":"Kerkweg 5",
    "sg:city":"Ieper",
    "sg:classifiers":[
        {
            "category":"Personal",
            "subcategory":"Beauty Salon",
            "type":"Services"
        }
    ],
    "sg:phone":"+32 57 20 30 08",
    "sg:postcode":"8900",
    "sg:province":"West-Vlaanderen",
    "sg:tags":[
        "de",
        "coiffure"
    ],
    "wof:name":"Coiffure Christiane",
    "wof:placetype":"venue"
},
  "geometry": {"coordinates":[2.8492290974,50.8678970337],"type":"Point"}
}