{
  "type": "Feature",
  "properties": {
    "iso:country":"BE",
    "sg:address":"Geeraard De Cremerstraat 101",
    "sg:city":"Kruibeke",
    "sg:classifiers":[
        {
            "category":"Cafe",
            "type":"Food & Drink"
        }
    ],
    "sg:phone":"+32 3 774 46 47",
    "sg:postcode":"9150",
    "sg:province":"Oost-Vlaanderen",
    "sg:tags":[
        "caf\u00e9s"
    ],
    "wof:name":"Caf\u00c9 't Cremerke",
    "wof:placetype":"venue"
},
  "geometry": {"coordinates":[4.2930688858,51.1323204041],"type":"Point"}
}