{
  "type": "Feature",
  "properties": {
    "addr:full":"Biezeweg 9 Wetteren Oost-Vlaanderen 9230",
    "addr:housenumber":"9",
    "addr:postcode":"9230",
    "addr:street":"Biezeweg",
    "iso:country":"BE",
    "sg:address":"Biezeweg 9",
    "sg:city":"Wetteren",
    "sg:classifiers":[
        {
            "category":"Manufacturing",
            "subcategory":"Metals",
            "type":"Manufacturing & Wholesale Goods"
        }
    ],
    "sg:phone":"+32 9 252 18 45",
    "sg:postcode":"9230",
    "sg:province":"Oost-Vlaanderen",
    "sg:tags":[
        "foundry"
    ],
    "wof:name":"Van Londen Gieterij Nv",
    "wof:placetype":"venue"
},
  "geometry": {"coordinates":[3.8460628986,50.9887237549],"type":"Point"}
}