{
  "type": "Feature",
  "properties": {
    "iso:country":"BE",
    "sg:address":"Elizabetlaan 50",
    "sg:city":"Knokke-heist (knokke)",
    "sg:classifiers":[
        {
            "category":"Travel",
            "subcategory":"Hotels & Motels",
            "type":"Entertainment"
        }
    ],
    "sg:phone":"+32 50 60 10 73",
    "sg:postcode":"8300",
    "sg:province":"West-Vlaanderen",
    "wof:name":"Arcades (les)",
    "wof:placetype":"venue"
},
  "geometry": {"coordinates":[3.2955029011,51.3499183655],"type":"Point"}
}