{
  "type": "Feature",
  "properties": {
    "iso:country":"BE",
    "sg:address":"Panoramalaan 11",
    "sg:city":"Bierbeek (korbeek-lo)",
    "sg:classifiers":[
        {
            "category":"Real Estate",
            "subcategory":"Architect",
            "type":"Services"
        }
    ],
    "sg:phone":"+32 16 46 27 27",
    "sg:postcode":"3360",
    "sg:province":"Vlaams-Brabant",
    "wof:name":"Minnoye S",
    "wof:placetype":"venue"
},
  "geometry": {"coordinates":[4.7608289719,50.8719902039],"type":"Point"}
}