{
  "type": "Feature",
  "properties": {
    "addr:full":"Rijn 198 Geel Antwerpen 2440",
    "addr:housenumber":"198",
    "addr:postcode":"2440",
    "addr:street":"Rijn",
    "iso:country":"BE",
    "sg:address":"Rijn 198",
    "sg:city":"Geel",
    "sg:classifiers":[
        {
            "category":"Home & Garden",
            "subcategory":"Household Appliances",
            "type":"Retail Goods"
        }
    ],
    "sg:phone":"+32 14 58 83 75",
    "sg:postcode":"2440",
    "sg:province":"Antwerpen",
    "sg:tags":[
        "repair",
        "mainten",
        "-",
        "electric"
    ],
    "wof:name":"Vangeel J",
    "wof:placetype":"venue"
},
  "geometry": {"coordinates":[5.0190048218,51.1639213562],"type":"Point"}
}