{
  "type": "Feature",
  "properties": {
    "addr:full":"Chauss\u00e9e Paul Houtart 337 La Louvi\u00e8re (houdeng-goegnies) Hainaut 7110",
    "addr:housenumber":"337",
    "addr:postcode":"7110",
    "addr:street":"Chausse\u0301E Paul Houtart",
    "iso:country":"BE",
    "sg:address":"Chauss\u00e9e Paul Houtart 337",
    "sg:city":"La Louvi\u00e8re (houdeng-goegnies)",
    "sg:classifiers":[
        {
            "category":"Food & Beverages",
            "subcategory":"Fruits & Vegetables",
            "type":"Retail Goods"
        }
    ],
    "sg:phone":"+32 64 22 90 80",
    "sg:postcode":"7110",
    "sg:province":"Hainaut",
    "sg:tags":[
        "-"
    ],
    "wof:name":"Super Fruits",
    "wof:placetype":"venue"
},
  "geometry": {"coordinates":[4.1545357704,50.4879608154],"type":"Point"}
}