{
  "type": "Feature",
  "properties": {
    "iso:country":"BE",
    "sg:address":"Krekel 12",
    "sg:city":"Temse",
    "sg:orig_category":"Woningbouw",
    "sg:phone":"+32 3 775 58 86",
    "sg:postcode":"9140",
    "sg:province":"Oost-Vlaanderen",
    "wof:name":"Marcel Cole",
    "wof:placetype":"venue"
},
  "geometry": {"coordinates":[4.2145848274,51.1716880798],"type":"Point"}
}