{
  "type": "Feature",
  "properties": {
    "iso:country":"BE",
    "sg:address":"Diestsesteenweg 8",
    "sg:city":"Herk-de-stad",
    "sg:orig_category":"Cliniques and h\u00f4pitaux. Ambulances",
    "sg:phone":"+32 13 55 17 11",
    "sg:postcode":"3540",
    "sg:province":"Limburg",
    "wof:name":"Alg. Ziekenhuis Salvator",
    "wof:placetype":"venue"
},
  "geometry": {"coordinates":[5.16294384,50.9406509399],"type":"Point"}
}