{
  "type": "Feature",
  "properties": {
    "addr:full":"Place Des Combattants 7 Lessines Hainaut 7862",
    "addr:housenumber":"7",
    "addr:postcode":"7862",
    "addr:street":"Place Des Combattants;Hainaut",
    "iso:country":"BE",
    "sg:address":"Place Des Combattants 7",
    "sg:city":"Lessines",
    "sg:classifiers":[
        {
            "category":"Cafe",
            "type":"Food & Drink"
        }
    ],
    "sg:phone":"+32 68 44 92 77",
    "sg:postcode":"7862",
    "sg:province":"Hainaut",
    "sg:tags":[
        "caf\u00e9s"
    ],
    "wof:name":"Patrick Denis",
    "wof:placetype":"venue"
},
  "geometry": {"coordinates":[3.7807478905,50.7209777832],"type":"Point"}
}