{
  "type": "Feature",
  "properties": {
    "addr:full":"Schavelarestraat 53 Torhout West-Vlaanderen 8820",
    "addr:housenumber":"53",
    "addr:postcode":"8820",
    "addr:street":"Schavelarestraat",
    "iso:country":"BE",
    "sg:address":"Schavelarestraat 53",
    "sg:city":"Torhout",
    "sg:orig_category":"Epiceries",
    "sg:phone":"+32 50 21 65 00",
    "sg:postcode":"8820",
    "sg:province":"West-Vlaanderen",
    "wof:name":"Spar",
    "wof:placetype":"venue"
},
  "geometry": {"coordinates":[3.1154060364,51.0558433533],"type":"Point"}
}