{
  "type": "Feature",
  "properties": {
    "iso:country":"BE",
    "sg:address":"Avenue A.j. Slegers 67",
    "sg:city":"Bruxelles (woluwe-saint-lambert)",
    "sg:classifiers":[
        {
            "category":"Health Services",
            "subcategory":"Dentist",
            "type":"Services"
        }
    ],
    "sg:phone":"+32 2 771 89 76",
    "sg:postcode":"1200",
    "sg:province":"Bruxelles-Capitale",
    "wof:name":"Anton Michel",
    "wof:placetype":"venue"
},
  "geometry": {"coordinates":[4.4280061722,50.8408851624],"type":"Point"}
}