{
  "type": "Feature",
  "properties": {
    "addr:full":"Brusselsesteenweg 732c Waterloo Brabant Wallon 1410",
    "addr:housenumber":"732c",
    "addr:postcode":"1410",
    "addr:street":"Brusselsesteenweg",
    "iso:country":"BE",
    "sg:address":"Brusselsesteenweg 732c",
    "sg:city":"Waterloo",
    "sg:orig_category":"Rev\u00eatements de sols and murs",
    "sg:phone":"+32 2 380 64 00",
    "sg:postcode":"1410",
    "sg:province":"Brabant Wallon",
    "wof:name":"Poxy Belgium",
    "wof:placetype":"venue"
},
  "geometry": {"coordinates":[4.3958420753,50.7346763611],"type":"Point"}
}