{
  "type": "Feature",
  "properties": {
    "iso:country":"BE",
    "sg:address":"Zeelaan 131",
    "sg:city":"Koksijde",
    "sg:orig_category":"Stations-service and carburants. V\u00e9hicules automobiles",
    "sg:phone":"+32 58 51 17 06",
    "sg:postcode":"8670",
    "sg:province":"West-Vlaanderen",
    "wof:name":"Garage Declerck",
    "wof:placetype":"venue"
},
  "geometry": {"coordinates":[2.644630909,51.1101074219],"type":"Point"}
}