{
  "type": "Feature",
  "properties": {
    "iso:country":"BE",
    "sg:address":"Weststraat 19",
    "sg:city":"Jabbeke",
    "sg:orig_category":"Installation de menuiserie en bois and plastique",
    "sg:phone":"+32 50 81 17 30",
    "sg:postcode":"8490",
    "sg:province":"West-Vlaanderen",
    "wof:name":"Henk Deschacht",
    "wof:placetype":"venue"
},
  "geometry": {"coordinates":[3.0886619091,51.186580658],"type":"Point"}
}