{
  "type": "Feature",
  "properties": {
    "addr:full":"Bloklaan 24 Asse Vlaams-Brabant 1730",
    "addr:housenumber":"24",
    "addr:postcode":"1730",
    "addr:street":"Bloklaan",
    "iso:country":"BE",
    "sg:address":"Bloklaan 24",
    "sg:city":"Asse",
    "sg:classifiers":[
        {
            "category":"Food & Beverages",
            "subcategory":"Groceries & Convenience Stores",
            "type":"Retail Goods"
        }
    ],
    "sg:phone":"+32 2 452 69 31",
    "sg:postcode":"1730",
    "sg:province":"Vlaams-Brabant",
    "sg:tags":[
        "grocer"
    ],
    "wof:name":"Denijs G",
    "wof:placetype":"venue"
},
  "geometry": {"coordinates":[4.1951880455,50.9096031189],"type":"Point"}
}