{
  "type": "Feature",
  "properties": {
    "addr:full":"Tervurenlaan 402 Sint-pieters-woluwe/woluwe-saint-pierre Bruxelles-Capitale 1150",
    "addr:housenumber":"402",
    "addr:postcode":"1150",
    "addr:street":"Tervurenlaan;/",
    "iso:country":"BE",
    "sg:address":"Tervurenlaan 402",
    "sg:city":"Sint-pieters-woluwe/woluwe-saint-pierre",
    "sg:orig_category":"Public-relationsbureaus",
    "sg:phone":"+32 2 761 66 14",
    "sg:postcode":"1150",
    "sg:province":"Bruxelles-Capitale",
    "wof:name":"Overath D. & Partners",
    "wof:placetype":"venue"
},
  "geometry": {"coordinates":[4.4438309669,50.8279647827],"type":"Point"}
}