{
  "type": "Feature",
  "properties": {
    "addr:full":"Boldriesstraat 87 Menen West-Vlaanderen 8930",
    "addr:housenumber":"87",
    "addr:postcode":"8930",
    "addr:street":"Boldriesstraat",
    "iso:country":"BE",
    "sg:address":"Boldriesstraat 87",
    "sg:city":"Menen",
    "sg:orig_category":"R\u00e9parations de chaussures and articles en cuir",
    "sg:phone":"+32 56 41 14 35",
    "sg:postcode":"8930",
    "sg:province":"West-Vlaanderen",
    "wof:name":"Wim Suffys",
    "wof:placetype":"venue"
},
  "geometry": {"coordinates":[3.1209149361,50.7961845398],"type":"Point"}
}