{
  "type": "Feature",
  "properties": {
    "iso:country":"BE",
    "sg:address":"Hipp. Spilleboutdreef 2",
    "sg:city":"Roeselare",
    "sg:classifiers":[
        {
            "category":"Insurance",
            "subcategory":"Life Insurance",
            "type":"Services"
        }
    ],
    "sg:phone":"+32 51 24 82 11",
    "sg:postcode":"8800",
    "sg:province":"West-Vlaanderen",
    "sg:tags":[
        "assurance"
    ],
    "wof:name":"Priem Johan",
    "wof:placetype":"venue"
},
  "geometry": {"coordinates":[3.1248600483,50.9384498596],"type":"Point"}
}