{
  "type": "Feature",
  "properties": {
    "addr:full":"Hoogstraat 109a Lierde (sint-martens-lierde) Oost-Vlaanderen 9572",
    "addr:housenumber":"109a",
    "addr:postcode":"9572",
    "addr:street":"Hoogstraat",
    "iso:country":"BE",
    "sg:address":"Hoogstraat 109a",
    "sg:city":"Lierde (sint-martens-lierde)",
    "sg:classifiers":[
        {
            "category":"Real Estate",
            "subcategory":"Surveying",
            "type":"Services"
        }
    ],
    "sg:phone":"+32 55 42 84 72",
    "sg:postcode":"9572",
    "sg:province":"Oost-Vlaanderen",
    "sg:tags":[
        "surveyor",
        "land"
    ],
    "wof:name":"De Prez J",
    "wof:placetype":"venue"
},
  "geometry": {"coordinates":[3.8102090359,50.8092422485],"type":"Point"}
}