{
  "type": "Feature",
  "properties": {
    "iso:country":"BE",
    "sg:address":"Heide 108",
    "sg:city":"Lommel",
    "sg:classifiers":[
        {
            "category":"Food & Beverages",
            "subcategory":"Groceries & Convenience Stores",
            "type":"Retail Goods"
        }
    ],
    "sg:phone":"+32 11 54 43 44",
    "sg:postcode":"3920",
    "sg:province":"Limburg",
    "sg:tags":[
        "grocer"
    ],
    "wof:name":"Berghmans F",
    "wof:placetype":"venue"
},
  "geometry": {"coordinates":[5.3203220367,51.2411613464],"type":"Point"}
}