{
  "type": "Feature",
  "properties": {
    "iso:country":"BE",
    "sg:address":"Broechemsesteenweg 44",
    "sg:city":"Nijlen",
    "sg:classifiers":[
        {
            "category":"Cafe",
            "type":"Food & Drink"
        }
    ],
    "sg:phone":"+32 3 411 02 32",
    "sg:postcode":"2560",
    "sg:province":"Antwerpen",
    "sg:tags":[
        "caf\u00e9s"
    ],
    "wof:name":"Marc Heylen",
    "wof:placetype":"venue"
},
  "geometry": {"coordinates":[4.6652212143,51.1631011963],"type":"Point"}
}