{
  "type": "Feature",
  "properties": {
    "addr:full":"Koninginnelaan 115 Maasmechelen (eisden) Limburg 3630",
    "addr:housenumber":"115",
    "addr:postcode":"3630",
    "addr:street":"Koninginnelaan",
    "iso:country":"BE",
    "sg:address":"Koninginnelaan 115",
    "sg:city":"Maasmechelen (eisden)",
    "sg:classifiers":[
        {
            "category":"Shopping",
            "subcategory":"Clothing, Apparel, & Fashions",
            "type":"Retail Goods"
        }
    ],
    "sg:phone":"+32 89 70 21 98",
    "sg:postcode":"3630",
    "sg:province":"Limburg",
    "sg:tags":[
        "lady",
        "clothing",
        "-"
    ],
    "wof:name":"Cassis",
    "wof:placetype":"venue"
},
  "geometry": {"coordinates":[5.7009902,50.9814796448],"type":"Point"}
}