{
  "type": "Feature",
  "properties": {
    "addr:full":"Nati\u00cbnlaan 35 Maasmechelen Limburg 3630",
    "addr:housenumber":"35",
    "addr:postcode":"3630",
    "addr:street":"Natie\u0308Nlaan",
    "iso:country":"BE",
    "sg:address":"Nati\u00cbnlaan 35",
    "sg:city":"Maasmechelen",
    "sg:classifiers":[
        {
            "category":"Taxi",
            "type":"Transportation"
        }
    ],
    "sg:phone":"+32 89 77 22 22",
    "sg:postcode":"3630",
    "sg:province":"Limburg",
    "wof:name":"Kellens Taxi's Maaskant",
    "wof:placetype":"venue"
},
  "geometry": {"coordinates":[5.6961350441,50.963848114],"type":"Point"}
}