{
  "type": "Feature",
  "properties": {
    "addr:full":"Sint-antoniusplein 2 Oostende West-Vlaanderen 8400",
    "addr:housenumber":"2",
    "addr:postcode":"8400",
    "addr:street":"Sint-Antoniusplein",
    "iso:country":"BE",
    "sg:address":"Sint-antoniusplein 2",
    "sg:city":"Oostende",
    "sg:orig_category":"Banken and kredietinstellingen",
    "sg:phone":"+32 59 32 25 93",
    "sg:postcode":"8400",
    "sg:province":"West-Vlaanderen",
    "wof:name":"Bacob",
    "wof:placetype":"venue"
},
  "geometry": {"coordinates":[2.9431490898,51.2311401367],"type":"Point"}
}