{
  "type": "Feature",
  "properties": {
    "iso:country":"BE",
    "sg:address":"Boulevard G\u00c9n\u00c9ral Jacques 126",
    "sg:city":"Elsene/ixelles",
    "sg:orig_category":"Editeurs de journaux. Editeurs de revues and p\u00e9riodiques",
    "sg:phone":"+32 2 640 31 07",
    "sg:postcode":"1050",
    "sg:province":"Bruxelles-Capitale",
    "wof:name":"Revue Nouvelle",
    "wof:placetype":"venue"
},
  "geometry": {"coordinates":[4.3825821877,50.8200645447],"type":"Point"}
}