{
  "type": "Feature",
  "properties": {
    "addr:full":"Liersebaan 251 Zandhoven (massenhoven) Antwerpen 2240",
    "addr:housenumber":"251",
    "addr:postcode":"2240",
    "addr:street":"Liersebaan",
    "iso:country":"BE",
    "sg:address":"Liersebaan 251",
    "sg:city":"Zandhoven (massenhoven)",
    "sg:classifiers":[
        {
            "category":"Retail",
            "subcategory":"Auto Repair",
            "type":"Services"
        }
    ],
    "sg:phone":"+32 3 485 51 56",
    "sg:postcode":"2240",
    "sg:province":"Antwerpen",
    "sg:tags":[
        "garage"
    ],
    "wof:name":"Verboven",
    "wof:placetype":"venue"
},
  "geometry": {"coordinates":[4.6530098915,51.2075691223],"type":"Point"}
}