{
  "type": "Feature",
  "properties": {
    "iso:country":"BE",
    "sg:address":"Rue Branche Planchard 340",
    "sg:city":"Ans",
    "sg:classifiers":[
        {
            "category":"Home & Garden",
            "subcategory":"Carpets & Floor Coverings",
            "type":"Retail Goods"
        }
    ],
    "sg:phone":"+32 4 246 07 29",
    "sg:postcode":"4430",
    "sg:province":"Li\u00e8ge",
    "sg:tags":[
        "tile"
    ],
    "wof:name":"European Maison Sprl",
    "wof:placetype":"venue"
},
  "geometry": {"coordinates":[5.52293396,50.6505279541],"type":"Point"}
}