{
  "type": "Feature",
  "properties": {
    "addr:full":"Priesterstraat 41 Poperinge West-Vlaanderen 8970",
    "addr:housenumber":"41",
    "addr:postcode":"8970",
    "addr:street":"Priesterstraat",
    "iso:country":"BE",
    "sg:address":"Priesterstraat 41",
    "sg:city":"Poperinge",
    "sg:classifiers":[
        {
            "category":"Insurance",
            "subcategory":"Insurance Agent",
            "type":"Services"
        }
    ],
    "sg:phone":"+32 57 33 49 68",
    "sg:postcode":"8970",
    "sg:province":"West-Vlaanderen",
    "sg:tags":[
        "verzekeringsmakelaars",
        "expert"
    ],
    "wof:name":"Bertin Maerten",
    "wof:placetype":"venue"
},
  "geometry": {"coordinates":[2.7247140408,50.8548812866],"type":"Point"}
}