{
  "type": "Feature",
  "properties": {
    "addr:full":"Rue De La Colline 39 Namur Namur 5000",
    "addr:housenumber":"39",
    "addr:postcode":"5000",
    "addr:street":"Rue De La Colline",
    "iso:country":"BE",
    "sg:address":"Rue De La Colline 39",
    "sg:city":"Namur",
    "sg:orig_category":"Artsen and specialisten",
    "sg:phone":"+32 81 73 71 88",
    "sg:postcode":"5000",
    "sg:province":"Namur",
    "wof:name":"T. Biset",
    "wof:placetype":"venue"
},
  "geometry": {"coordinates":[4.8473711014,50.4621772766],"type":"Point"}
}