{
  "type": "Feature",
  "properties": {
    "addr:full":"Zuidstraat 6 Kortemark West-Vlaanderen 8610",
    "addr:housenumber":"6",
    "addr:postcode":"8610",
    "addr:street":"Zuidstraat",
    "iso:country":"BE",
    "sg:address":"Zuidstraat 6",
    "sg:city":"Kortemark",
    "sg:orig_category":"Eleveurs and marchands de porcs. Producteurs de l\u00e9gumes. Fruits and l\u00e9gumes Gr",
    "sg:phone":"+32 51 56 84 47",
    "sg:postcode":"8610",
    "sg:province":"West-Vlaanderen",
    "wof:name":"Marc Trybou",
    "wof:placetype":"venue"
},
  "geometry": {"coordinates":[3.0011980534,51.0035362244],"type":"Point"}
}