{
  "type": "Feature",
  "properties": {
    "iso:country":"BE",
    "sg:address":"Rue Edmond Lengrand 1",
    "sg:city":"Merbes-le-ch\u00c2teau",
    "sg:orig_category":"Traitements param\u00e9dicaux",
    "sg:phone":"+32 71 55 40 11",
    "sg:postcode":"6567",
    "sg:province":"Hainaut",
    "wof:name":"A. Eeckhaut",
    "wof:placetype":"venue"
},
  "geometry": {"coordinates":[4.1623921394,50.3257789612],"type":"Point"}
}