{
  "type": "Feature",
  "properties": {
    "iso:country":"BE",
    "sg:address":"Rue Fran\u00e7ois Hittelet 141",
    "sg:city":"Jemeppe-sur-sambre",
    "sg:classifiers":[
        {
            "category":"Retail",
            "subcategory":"Repair Shop",
            "type":"Services"
        }
    ],
    "sg:phone":"+32 71 78 06 33",
    "sg:postcode":"5190",
    "sg:province":"Namur",
    "sg:tags":[
        "radio",
        "television",
        "-",
        "maintenance"
    ],
    "wof:name":"Lejeune G",
    "wof:placetype":"venue"
},
  "geometry": {"coordinates":[4.6629700661,50.4599113464],"type":"Point"}
}