{
  "type": "Feature",
  "properties": {
    "addr:full":"Boulevard De L'humanit\u00c9 114 Anderlecht/anderlecht Bruxelles-Capitale 1070",
    "addr:housenumber":"114",
    "addr:postcode":"1070",
    "addr:street":"Boulevard De L'Humanite \u0301",
    "iso:country":"BE",
    "sg:address":"Boulevard De L'humanit\u00c9 114",
    "sg:city":"Anderlecht/anderlecht",
    "sg:orig_category":"Syst\u00e8mes de t\u00e9l\u00e9communications",
    "sg:phone":"+32 2 558 14 00",
    "sg:postcode":"1070",
    "sg:province":"Bruxelles-Capitale",
    "wof:name":"Which Belgium",
    "wof:placetype":"venue"
},
  "geometry": {"coordinates":[4.3092007637,50.8194198608],"type":"Point"}
}