{
  "type": "Feature",
  "properties": {
    "addr:full":"Rue Des Fripiers 34 Mons Hainaut 7000",
    "addr:housenumber":"34",
    "addr:postcode":"7000",
    "addr:street":"Rue Des Fripiers;Hainaut",
    "iso:country":"BE",
    "sg:address":"Rue Des Fripiers 34",
    "sg:city":"Mons",
    "sg:orig_category":"Dameskledingzaken",
    "sg:phone":"+32 65 84 63 73",
    "sg:postcode":"7000",
    "sg:province":"Hainaut",
    "wof:name":"Maison Encore Elle",
    "wof:placetype":"venue"
},
  "geometry": {"coordinates":[3.9514160156,50.4519348145],"type":"Point"}
}