{
  "type": "Feature",
  "properties": {
    "addr:full":"Rue Fernand Louis 6 Profondeville (bois-de-villers) Namur 5170",
    "addr:housenumber":"6",
    "addr:postcode":"5170",
    "addr:street":"Rue Fernand Louis",
    "iso:country":"BE",
    "sg:address":"Rue Fernand Louis 6",
    "sg:city":"Profondeville (bois-de-villers)",
    "sg:classifiers":[
        {
            "category":"Health Services",
            "subcategory":"Health Practitioner",
            "type":"Services"
        }
    ],
    "sg:phone":"+32 81 43 41 37",
    "sg:postcode":"5170",
    "sg:province":"Namur",
    "sg:tags":[
        "physiotherapist"
    ],
    "wof:name":"Rigaux Val\u00e9rie",
    "wof:placetype":"venue"
},
  "geometry": {"coordinates":[4.8128948212,50.3925666809],"type":"Point"}
}