{
  "type": "Feature",
  "properties": {
    "addr:full":"Lillo Steenweg 3 Houthalen-helchteren Limburg 3530",
    "addr:housenumber":"3",
    "addr:postcode":"3530",
    "addr:street":"Lillo Steenweg",
    "iso:country":"BE",
    "sg:address":"Lillo Steenweg 3",
    "sg:city":"Houthalen-helchteren",
    "sg:orig_category":"Avocats and conseillers juridiques",
    "sg:phone":"+32 11 57 48 26",
    "sg:postcode":"3530",
    "sg:province":"Limburg",
    "wof:name":"J. Ulenaers",
    "wof:placetype":"venue"
},
  "geometry": {"coordinates":[5.3534350395,51.0437507629],"type":"Point"}
}