{
  "type": "Feature",
  "properties": {
    "iso:country":"BE",
    "sg:address":"Rue Sanseau 4",
    "sg:city":"Hamois (achet)",
    "sg:classifiers":[
        {
            "category":"Travel",
            "subcategory":"Hotels & Motels",
            "type":"Entertainment"
        }
    ],
    "sg:phone":"+32 83 61 12 64",
    "sg:postcode":"5362",
    "sg:province":"Namur",
    "wof:name":"Repos Des Touristes",
    "wof:placetype":"venue"
},
  "geometry": {"coordinates":[5.1742448807,50.3328666687],"type":"Point"}
}