{
  "type": "Feature",
  "properties": {
    "addr:full":"Staatsbaan 8 Halen Limburg 3545",
    "addr:housenumber":"8",
    "addr:postcode":"3545",
    "addr:street":"Staatsbaan",
    "iso:country":"BE",
    "sg:address":"Staatsbaan 8",
    "sg:city":"Halen",
    "sg:classifiers":[
        {
            "category":"Shopping",
            "subcategory":"Clothing, Apparel, & Fashions",
            "type":"Retail Goods"
        }
    ],
    "sg:phone":"+32 13 55 65 75",
    "sg:postcode":"3545",
    "sg:province":"Limburg",
    "sg:tags":[
        "clothing",
        "-",
        "gentleman"
    ],
    "wof:name":"Touch\u00e9",
    "wof:placetype":"venue"
},
  "geometry": {"coordinates":[5.1137771606,50.9500274658],"type":"Point"}
}