{
  "type": "Feature",
  "properties": {
    "iso:country":"BE",
    "sg:address":"Ommegang Noord 15",
    "sg:city":"Staden (westrozebeke)",
    "sg:classifiers":[
        {
            "category":"Education",
            "subcategory":"Dance Studio",
            "type":"Public Place"
        }
    ],
    "sg:phone":"+32 51 24 86 91",
    "sg:postcode":"8840",
    "sg:province":"West-Vlaanderen",
    "sg:tags":[
        "school",
        "dancing"
    ],
    "wof:name":"Funky-dance M.c.",
    "wof:placetype":"venue"
},
  "geometry": {"coordinates":[3.0109870434,50.9340744019],"type":"Point"}
}