{
  "type": "Feature",
  "properties": {
    "addr:full":"Grote Steenweg 331 Linter Vlaams-Brabant 3350",
    "addr:housenumber":"331",
    "addr:postcode":"3350",
    "addr:street":"Grote Steenweg;Vlaams-Brabant",
    "iso:country":"BE",
    "sg:address":"Grote Steenweg 331",
    "sg:city":"Linter",
    "sg:orig_category":"Schoonheidssalons",
    "sg:phone":"+32 11 78 06 60",
    "sg:postcode":"3350",
    "sg:province":"Vlaams-Brabant",
    "wof:name":"Instituut Visage",
    "wof:placetype":"venue"
},
  "geometry": {"coordinates":[5.0493102074,50.8456459045],"type":"Point"}
}