{
  "type": "Feature",
  "properties": {
    "iso:country":"BE",
    "sg:address":"Avenue Du Bois De La Cambre 212",
    "sg:city":"Bruxelles (ixelles)",
    "sg:classifiers":[
        {
            "category":"Professional",
            "subcategory":"Credit Reporting & Collection",
            "type":"Services"
        }
    ],
    "sg:phone":"+32 2 646 40 93",
    "sg:postcode":"1050",
    "sg:province":"Bruxelles-Capitale",
    "sg:tags":[
        "bailiff"
    ],
    "wof:name":"Mormal Ph",
    "wof:placetype":"venue"
},
  "geometry": {"coordinates":[4.3890271187,50.806137085],"type":"Point"}
}