{
  "type": "Feature",
  "properties": {
    "addr:full":"Dasstraat 14 Wommelgem Antwerpen 2160",
    "addr:housenumber":"14",
    "addr:postcode":"2160",
    "addr:street":"Dasstraat",
    "iso:country":"BE",
    "sg:address":"Dasstraat 14",
    "sg:city":"Wommelgem",
    "sg:classifiers":[
        {
            "category":"Building & Trades",
            "subcategory":"Cleaning & Sanitation",
            "type":"Services"
        }
    ],
    "sg:phone":"+32 476 53 46 23",
    "sg:postcode":"2160",
    "sg:province":"Antwerpen",
    "sg:tags":[
        "cleaner",
        "window"
    ],
    "wof:name":"Wassertje ('t)",
    "wof:placetype":"venue"
},
  "geometry": {"coordinates":[4.5216870308,51.2041625977],"type":"Point"}
}