{
  "type": "Feature",
  "properties": {
    "iso:country":"BE",
    "sg:address":"Kortemunt 6",
    "sg:city":"Nevele",
    "sg:classifiers":[
        {
            "category":"Bakery",
            "type":"Food & Drink"
        }
    ],
    "sg:phone":"+32 9 371 55 20",
    "sg:postcode":"9850",
    "sg:province":"Oost-Vlaanderen",
    "sg:tags":[
        "confectioner",
        "baker"
    ],
    "wof:name":"Welvaert L",
    "wof:placetype":"venue"
},
  "geometry": {"coordinates":[3.5498869419,51.0325317383],"type":"Point"}
}