{
  "type": "Feature",
  "properties": {
    "iso:country":"BE",
    "sg:address":"Avenue Marius Renard 27 Box 129",
    "sg:city":"Bruxelles (anderlecht)",
    "sg:classifiers":[
        {
            "category":"Building & Trades",
            "subcategory":"Construction",
            "type":"Services"
        }
    ],
    "sg:phone":"+32 497 50 00 05",
    "sg:postcode":"1070",
    "sg:province":"Bruxelles-Capitale",
    "sg:tags":[
        "paper",
        "hanger"
    ],
    "wof:name":"Ravi-net Sprl",
    "wof:placetype":"venue"
},
  "geometry": {"coordinates":[4.2871899605,50.8267288208],"type":"Point"}
}