{
  "type": "Feature",
  "properties": {
    "iso:country":"BE",
    "sg:address":"Mechelsesteenweg 609",
    "sg:city":"Herent",
    "sg:orig_category":"Artsen and specialisten",
    "sg:phone":"+32 16 23 77 37",
    "sg:postcode":"3020",
    "sg:province":"Vlaams-Brabant",
    "wof:name":"Sophie Opsomer",
    "wof:placetype":"venue"
},
  "geometry": {"coordinates":[4.6632299423,50.9108123779],"type":"Point"}
}