{
  "type": "Feature",
  "properties": {
    "iso:country":"BE",
    "sg:address":"Rue Du Ch\u00c2teau 93",
    "sg:city":"Genappe",
    "sg:orig_category":"Boissons",
    "sg:phone":"+32 10 61 60 04",
    "sg:postcode":"1470",
    "sg:province":"Brabant Wallon",
    "wof:name":"Entr. Vinicoles P. Leloup",
    "wof:placetype":"venue"
},
  "geometry": {"coordinates":[4.4490060806,50.610458374],"type":"Point"}
}