{
  "type": "Feature",
  "properties": {
    "iso:country":"BE",
    "sg:address":"Avenue Charles Deli\u00c8ge 14",
    "sg:city":"Binche",
    "sg:orig_category":"Instituts de beaut\u00e9. Centres de relaxation and bien-\u00eatre",
    "sg:phone":"+32 64 33 34 74",
    "sg:postcode":"7130",
    "sg:province":"Hainaut",
    "wof:name":"Institut Isayake",
    "wof:placetype":"venue"
},
  "geometry": {"coordinates":[4.1673789024,50.4151611328],"type":"Point"}
}