{
  "type": "Feature",
  "properties": {
    "addr:full":"Koningin Astridlaan 130 Turnhout Antwerpen 2300",
    "addr:housenumber":"130",
    "addr:postcode":"2300",
    "addr:street":"Koningin Astridlaan",
    "iso:country":"BE",
    "sg:address":"Koningin Astridlaan 130",
    "sg:city":"Turnhout",
    "sg:orig_category":"Woningbouw",
    "sg:phone":"+32 14 42 45 70",
    "sg:postcode":"2300",
    "sg:province":"Antwerpen",
    "wof:name":"Van Heuckelom Gebroeders",
    "wof:placetype":"venue"
},
  "geometry": {"coordinates":[4.9206361771,51.325012207],"type":"Point"}
}