{
  "type": "Feature",
  "properties": {
    "addr:full":"Kermtstraat 118 Hasselt Limburg 3512",
    "addr:housenumber":"118",
    "addr:postcode":"3512",
    "addr:street":"Kermtstraat",
    "iso:country":"BE",
    "sg:address":"Kermtstraat 118",
    "sg:city":"Hasselt",
    "sg:orig_category":"Art and fournitures artistiques. Salles de spectacles",
    "sg:phone":"+32 11 85 12 24",
    "sg:postcode":"3512",
    "sg:province":"Limburg",
    "wof:name":"A. & A. Kunst Integratie",
    "wof:placetype":"venue"
},
  "geometry": {"coordinates":[5.2474632263,50.9172058105],"type":"Point"}
}