{
  "type": "Feature",
  "properties": {
    "addr:full":"Wildendries 23 Ninove Oost-Vlaanderen 9404",
    "addr:housenumber":"23",
    "addr:postcode":"9404",
    "addr:street":"Wildendries",
    "iso:country":"BE",
    "sg:address":"Wildendries 23",
    "sg:city":"Ninove",
    "sg:orig_category":"Rundveehouders",
    "sg:phone":"+32 54 33 10 80",
    "sg:postcode":"9404",
    "sg:province":"Oost-Vlaanderen",
    "wof:name":"Hubert Soens",
    "wof:placetype":"venue"
},
  "geometry": {"coordinates":[3.9570000172,50.8419036865],"type":"Point"}
}