{
  "type": "Feature",
  "properties": {
    "addr:full":"Volpenswege 41b Evergem (sleidinge) Oost-Vlaanderen 9940",
    "addr:housenumber":"41b",
    "addr:postcode":"9940",
    "addr:street":"Volpenswege",
    "iso:country":"BE",
    "sg:address":"Volpenswege 41b",
    "sg:city":"Evergem (sleidinge)",
    "sg:classifiers":[
        {
            "category":"Shopping",
            "subcategory":"Florist",
            "type":"Retail Goods"
        }
    ],
    "sg:phone":"+32 9 357 56 90",
    "sg:postcode":"9940",
    "sg:province":"Oost-Vlaanderen",
    "sg:tags":[
        "-",
        "supply"
    ],
    "wof:name":"Euroflor Cv",
    "wof:placetype":"venue"
},
  "geometry": {"coordinates":[3.6936790943,51.1507797241],"type":"Point"}
}