{
  "type": "Feature",
  "properties": {
    "iso:country":"BE",
    "sg:address":"Ledebergstraat 9",
    "sg:city":"Gent (ledeberg)",
    "sg:classifiers":[
        {
            "category":"Shopping",
            "subcategory":"Crafts & Fabrics",
            "type":"Retail Goods"
        }
    ],
    "sg:phone":"+32 9 231 27 62",
    "sg:postcode":"9050",
    "sg:province":"Oost-Vlaanderen",
    "sg:tags":[
        "needlework",
        "lady"
    ],
    "wof:name":"Handwerkmandje ('t)",
    "wof:placetype":"venue"
},
  "geometry": {"coordinates":[3.7414660454,51.0367431641],"type":"Point"}
}