{
  "type": "Feature",
  "properties": {
    "addr:full":"Sint-alenalaan 43 Dilbeek Vlaams-Brabant 1700",
    "addr:housenumber":"43",
    "addr:postcode":"1700",
    "addr:street":"Sint-Alenalaan",
    "iso:country":"BE",
    "sg:address":"Sint-alenalaan 43",
    "sg:city":"Dilbeek",
    "sg:orig_category":"Boucheries",
    "sg:phone":"+32 2 569 41 38",
    "sg:postcode":"1700",
    "sg:province":"Vlaams-Brabant",
    "wof:name":"Depril",
    "wof:placetype":"venue"
},
  "geometry": {"coordinates":[4.2643318176,50.8467597961],"type":"Point"}
}