{
  "type": "Feature",
  "properties": {
    "addr:full":"Papestraat 3 Aalst (nieuwerkerken) Oost-Vlaanderen 9320",
    "addr:housenumber":"3",
    "addr:postcode":"9320",
    "addr:street":"Papestraat",
    "iso:country":"BE",
    "sg:address":"Papestraat 3",
    "sg:city":"Aalst (nieuwerkerken)",
    "sg:orig_category":"Non-Classified Establishments",
    "sg:phone":"+32 53 83 42 00",
    "sg:postcode":"9320",
    "sg:province":"Oost-Vlaanderen",
    "wof:name":"De Saedeleer Myriam Bvba",
    "wof:placetype":"venue"
},
  "geometry": {"coordinates":[4.0553851128,50.9209976196],"type":"Point"}
}