{
  "type": "Feature",
  "properties": {
    "addr:full":"Rietstraat 7 Bornem Antwerpen 2880",
    "addr:housenumber":"7",
    "addr:postcode":"2880",
    "addr:street":"Rietstraat",
    "iso:country":"BE",
    "sg:address":"Rietstraat 7",
    "sg:city":"Bornem",
    "sg:classifiers":[
        {
            "category":"Cafe",
            "type":"Food & Drink"
        }
    ],
    "sg:phone":"+32 3 889 26 05",
    "sg:postcode":"2880",
    "sg:province":"Antwerpen",
    "sg:tags":[
        "caf\u00e9s"
    ],
    "wof:name":"K.v.k. Hingene",
    "wof:placetype":"venue"
},
  "geometry": {"coordinates":[4.2371749878,51.1003456116],"type":"Point"}
}