{
  "type": "Feature",
  "properties": {
    "iso:country":"BE",
    "sg:address":"Rue Quew\u00e9e 5",
    "sg:city":"Pont-\u00e0-celles",
    "sg:orig_category":"Non-Classified Establishments",
    "sg:phone":"+32 71 84 57 97",
    "sg:postcode":"6230",
    "sg:province":"Hainaut",
    "wof:name":"Multipap",
    "wof:placetype":"venue"
},
  "geometry": {"coordinates":[4.3433470726,50.5138893127],"type":"Point"}
}