{
  "type": "Feature",
  "properties": {
    "iso:country":"BE",
    "sg:address":"Grand Place 7b18",
    "sg:city":"Flemalle",
    "sg:classifiers":[
        {
            "category":"Fast Food",
            "type":"Food & Drink"
        }
    ],
    "sg:phone":"+32 4 275 59 31",
    "sg:postcode":"4400",
    "sg:province":"Li\u00e8ge",
    "sg:tags":[
        "\u00c0",
        "emporter",
        "restaurants"
    ],
    "wof:name":"Jean-marc Vander Velde",
    "wof:placetype":"venue"
},
  "geometry": {"coordinates":[5.4488148689,50.5988082886],"type":"Point"}
}