{
  "type": "Feature",
  "properties": {
    "iso:country":"BE",
    "sg:address":"Melegemstraat 10-12",
    "sg:city":"Zingem",
    "sg:classifiers":[
        {
            "category":"Banks & Credit Unions",
            "subcategory":"Investment Brokerage",
            "type":"Services"
        }
    ],
    "sg:phone":"+32 9 384 20 50",
    "sg:postcode":"9750",
    "sg:province":"Oost-Vlaanderen",
    "sg:tags":[
        "machine",
        "-",
        "waste",
        "installation",
        "treatment"
    ],
    "wof:name":"Efas",
    "wof:placetype":"venue"
},
  "geometry": {"coordinates":[3.6500999928,50.9028358459],"type":"Point"}
}