{
  "type": "Feature",
  "properties": {
    "iso:country":"BE",
    "sg:address":"Rue Des Quatre Abias 36",
    "sg:city":"Waremme",
    "sg:classifiers":[
        {
            "category":"Insurance",
            "subcategory":"Insurance Agent",
            "type":"Services"
        }
    ],
    "sg:phone":"+32 19 32 82 34",
    "sg:postcode":"4300",
    "sg:province":"Li\u00e8ge",
    "sg:tags":[
        "verzekeringsmakelaars",
        "expert"
    ],
    "wof:name":"Vinciane Nyssen",
    "wof:placetype":"venue"
},
  "geometry": {"coordinates":[5.2923178673,50.7060241699],"type":"Point"}
}