{
  "type": "Feature",
  "properties": {
    "addr:full":"Avenue Du Douaire 20-38 Ottignies-louvain-la-neuve Brabant Wallon 1340",
    "addr:housenumber":"20-38",
    "addr:postcode":"1340",
    "addr:street":"Avenue Du Douaire",
    "iso:country":"BE",
    "sg:address":"Avenue Du Douaire 20-38",
    "sg:city":"Ottignies-louvain-la-neuve",
    "sg:orig_category":"Supermarch\u00e9s",
    "sg:phone":"+32 10 41 79 30",
    "sg:postcode":"1340",
    "sg:province":"Brabant Wallon",
    "wof:name":"Colruyt",
    "wof:placetype":"venue"
},
  "geometry": {"coordinates":[4.5672249794,50.6636390686],"type":"Point"}
}