{
  "type": "Feature",
  "properties": {
    "addr:full":"Demerstraat 30 Hasselt Limburg 3500",
    "addr:housenumber":"30",
    "addr:postcode":"3500",
    "addr:street":"Demerstraat",
    "iso:country":"BE",
    "sg:address":"Demerstraat 30",
    "sg:city":"Hasselt",
    "sg:classifiers":[
        {
            "category":"Utilities",
            "subcategory":"Telephone",
            "type":"Services"
        }
    ],
    "sg:phone":"+32 11 35 06 80",
    "sg:postcode":"3500",
    "sg:province":"Limburg",
    "sg:tags":[
        "house",
        "phone",
        "telecommunicatieapparaten"
    ],
    "wof:name":"The Phone House",
    "wof:placetype":"venue"
},
  "geometry": {"coordinates":[5.3376698494,50.9318161011],"type":"Point"}
}