{
  "type": "Feature",
  "properties": {
    "addr:full":"Grand-rue 32 Martelange Luxembourg 6630",
    "addr:housenumber":"32",
    "addr:postcode":"6630",
    "addr:street":"Grand-Rue",
    "iso:country":"BE",
    "sg:address":"Grand-rue 32",
    "sg:city":"Martelange",
    "sg:orig_category":"Artsen and specialisten",
    "sg:phone":"+32 63 60 17 77",
    "sg:postcode":"6630",
    "sg:province":"Luxembourg",
    "wof:name":"Tania Chidiac",
    "wof:placetype":"venue"
},
  "geometry": {"coordinates":[5.7386841774,49.8317871094],"type":"Point"}
}