{
  "type": "Feature",
  "properties": {
    "iso:country":"BE",
    "sg:address":"Stuikberg 123",
    "sg:city":"Londerzeel",
    "sg:classifiers":[
        {
            "category":"Farming",
            "subcategory":"Poultry Farm",
            "type":"Manufacturing & Wholesale Goods"
        }
    ],
    "sg:phone":"+32 52 30 90 46",
    "sg:postcode":"1840",
    "sg:province":"Vlaams-Brabant",
    "sg:tags":[
        "rabbit",
        "slaughterhouse"
    ],
    "wof:name":"Van Den Brande F",
    "wof:placetype":"venue"
},
  "geometry": {"coordinates":[4.3132410049,51.029548645],"type":"Point"}
}