{
  "type": "Feature",
  "properties": {
    "iso:country":"BE",
    "sg:address":"Jules Moretuslei 157",
    "sg:city":"Wilrijk",
    "sg:classifiers":[
        {
            "category":"Home & Garden",
            "subcategory":"Furniture",
            "type":"Retail Goods"
        }
    ],
    "sg:phone":"+32 3 828 83 33",
    "sg:postcode":"2610",
    "sg:province":"Antwerpen",
    "sg:tags":[
        "used",
        "-"
    ],
    "wof:name":"Oxfam Solidarit\u00e9",
    "wof:placetype":"venue"
},
  "geometry": {"coordinates":[4.3893470764,51.1724395752],"type":"Point"}
}