{
  "type": "Feature",
  "properties": {
    "addr:full":"Rue Du Calvaire 52 Fleurus (wagnel\u00e9e) Hainaut 6223",
    "addr:housenumber":"52",
    "addr:postcode":"6223",
    "addr:street":"Rue Du Calvaire",
    "iso:country":"BE",
    "sg:address":"Rue Du Calvaire 52",
    "sg:city":"Fleurus (wagnel\u00e9e)",
    "sg:classifiers":[
        {
            "category":"Building & Trades",
            "subcategory":"Construction",
            "type":"Services"
        }
    ],
    "sg:phone":"+32 71 81 38 20",
    "sg:postcode":"6223",
    "sg:province":"Hainaut",
    "sg:tags":[
        "stucco",
        "contractor"
    ],
    "wof:name":"Fontaine L",
    "wof:placetype":"venue"
},
  "geometry": {"coordinates":[4.5345578194,50.5196075439],"type":"Point"}
}