{
  "type": "Feature",
  "properties": {
    "iso:country":"BE",
    "sg:address":"Rue De Tergn\u00c9e 227",
    "sg:city":"Farciennes",
    "sg:orig_category":"Articles de jardin",
    "sg:phone":"+32 71 38 80 13",
    "sg:postcode":"6240",
    "sg:province":"Hainaut",
    "wof:name":"M.g Jardins",
    "wof:placetype":"venue"
},
  "geometry": {"coordinates":[4.5664319992,50.4333572388],"type":"Point"}
}