{
  "type": "Feature",
  "properties": {
    "addr:full":"Rue Des Ardennes 32 Durbuy Luxembourg 6941",
    "addr:housenumber":"32",
    "addr:postcode":"6941",
    "addr:street":"Rue Des Ardennes",
    "iso:country":"BE",
    "sg:address":"Rue Des Ardennes 32",
    "sg:city":"Durbuy",
    "sg:orig_category":"M\u00e9decins and sp\u00e9cialistes. Chaussures",
    "sg:phone":"+32 86 21 17 32",
    "sg:postcode":"6941",
    "sg:province":"Luxembourg",
    "wof:name":"Joseph Bodson",
    "wof:placetype":"venue"
},
  "geometry": {"coordinates":[5.5263361931,50.3763084412],"type":"Point"}
}