{
  "type": "Feature",
  "properties": {
    "addr:full":"Rue De Ville-en-waret 58 Andenne Namur 5300",
    "addr:housenumber":"58",
    "addr:postcode":"5300",
    "addr:street":"Rue De Ville-En-Waret",
    "iso:country":"BE",
    "sg:address":"Rue De Ville-en-waret 58",
    "sg:city":"Andenne",
    "sg:orig_category":"Enseignement maternel and primaire",
    "sg:phone":"+32 81 58 04 17",
    "sg:postcode":"5300",
    "sg:province":"Namur",
    "wof:name":"Ecole Matern. Communale",
    "wof:placetype":"venue"
},
  "geometry": {"coordinates":[4.972700119,50.5071296692],"type":"Point"}
}