{
  "type": "Feature",
  "properties": {
    "iso:country":"BE",
    "sg:address":"Place Du Ch\u00c2telet 1",
    "sg:city":"Malmedy",
    "sg:orig_category":"Mat\u00e9riel de T\u00e9l\u00e9communication",
    "sg:phone":"+32 800 33 800",
    "sg:postcode":"4960",
    "sg:province":"Li\u00e8ge",
    "wof:name":"T\u00c9l\u00c9boutique",
    "wof:placetype":"venue"
},
  "geometry": {"coordinates":[6.0265460014,50.4271812439],"type":"Point"}
}