{
  "type": "Feature",
  "properties": {
    "addr:full":"Fabrieksstraat 1 Tessenderlo Limburg 3980",
    "addr:housenumber":"1",
    "addr:postcode":"3980",
    "addr:street":"Fabrieksstraat",
    "iso:country":"BE",
    "sg:address":"Fabrieksstraat 1",
    "sg:city":"Tessenderlo",
    "sg:classifiers":[
        {
            "category":"Building & Trades",
            "subcategory":"Plumbing",
            "type":"Services"
        }
    ],
    "sg:phone":"+32 13 66 18 47",
    "sg:postcode":"3980",
    "sg:province":"Limburg",
    "sg:tags":[
        "tank"
    ],
    "wof:name":"Tanks Shop",
    "wof:placetype":"venue"
},
  "geometry": {"coordinates":[5.1031579971,51.0655250549],"type":"Point"}
}