{
  "type": "Feature",
  "properties": {
    "addr:full":"Avenue Du Panth\u00c9on 101 Koekelberg Bruxelles-Capitale 1081",
    "addr:housenumber":"101",
    "addr:postcode":"1081",
    "addr:street":"Avenue Du Panthe\u0301On",
    "iso:country":"BE",
    "sg:address":"Avenue Du Panth\u00c9on 101",
    "sg:city":"Koekelberg",
    "sg:orig_category":"Epiceries. Fleurs and plantes",
    "sg:phone":"+32 2 426 47 03",
    "sg:postcode":"1081",
    "sg:province":"Bruxelles-Capitale",
    "wof:name":"Christian Corijn",
    "wof:placetype":"venue"
},
  "geometry": {"coordinates":[4.3147091866,50.8664627075],"type":"Point"}
}