{
  "type": "Feature",
  "properties": {
    "addr:full":"Industrieweg 8 Boom Antwerpen 2850",
    "addr:housenumber":"8",
    "addr:postcode":"2850",
    "addr:street":"Industrieweg",
    "iso:country":"BE",
    "sg:address":"Industrieweg 8",
    "sg:city":"Boom",
    "sg:classifiers":[
        {
            "category":"Professional",
            "type":"Services"
        }
    ],
    "sg:phone":"+32 3 880 13 00",
    "sg:postcode":"2850",
    "sg:province":"Antwerpen",
    "sg:tags":[
        "forwarding",
        "agency"
    ],
    "wof:name":"Dfds Transport Nv",
    "wof:placetype":"venue"
},
  "geometry": {"coordinates":[4.3537688255,51.0996360779],"type":"Point"}
}