{
  "type": "Feature",
  "properties": {
    "iso:country":"BE",
    "sg:address":"R.d.weert-saint-georges 155",
    "sg:city":"Grez-doiceau",
    "sg:orig_category":"Woningbouw",
    "sg:phone":"+32 10 86 10 93",
    "sg:postcode":"1390",
    "sg:province":"Brabant Wallon",
    "wof:name":"Robert Gijsegom",
    "wof:placetype":"venue"
},
  "geometry": {"coordinates":[4.6964898109,50.7374687195],"type":"Point"}
}