{
  "type": "Feature",
  "properties": {
    "iso:country":"BE",
    "sg:address":"Rue Winston Churchill 310",
    "sg:city":"Courcelles",
    "sg:orig_category":"V\u00e9t\u00e9rinaires",
    "sg:phone":"+32 71 45 84 52",
    "sg:postcode":"6180",
    "sg:province":"Hainaut",
    "wof:name":"Patrick Godissart",
    "wof:placetype":"venue"
},
  "geometry": {"coordinates":[4.3952898979,50.4631347656],"type":"Point"}
}