{
  "type": "Feature",
  "properties": {
    "addr:full":"Chauss\u00c9e De Bruxelles 139 Waterloo Brabant Wallon 1410",
    "addr:housenumber":"139",
    "addr:postcode":"1410",
    "addr:street":"Chausse\u0301E De Bruxelles",
    "iso:country":"BE",
    "sg:address":"Chauss\u00c9e De Bruxelles 139",
    "sg:city":"Waterloo",
    "sg:classifiers":[
        {
            "category":"Fast Food",
            "type":"Food & Drink"
        }
    ],
    "sg:phone":"+32 2 351 20 55",
    "sg:postcode":"1410",
    "sg:province":"Brabant Wallon",
    "sg:tags":[
        "meeneem",
        "restaurant"
    ],
    "wof:name":"Touch & Go",
    "wof:placetype":"venue"
},
  "geometry": {"coordinates":[4.3981099129,50.7180595398],"type":"Point"}
}