{
  "type": "Feature",
  "properties": {
    "iso:country":"BE",
    "sg:address":"Prolongement De L'abbaye 80",
    "sg:city":"Herstal",
    "sg:classifiers":[
        {
            "category":"Professional",
            "subcategory":"Engineering",
            "type":"Services"
        }
    ],
    "sg:phone":"+32 4 264 33 41",
    "sg:postcode":"4040",
    "sg:province":"Li\u00e8ge",
    "sg:tags":[
        "precision"
    ],
    "wof:name":"R.m.a.",
    "wof:placetype":"venue"
},
  "geometry": {"coordinates":[5.6372709274,50.6898040771],"type":"Point"}
}