{
  "type": "Feature",
  "properties": {
    "iso:country":"BE",
    "sg:address":"Rue De L'eglise 31",
    "sg:city":"Chievres",
    "sg:classifiers":[
        {
            "category":"Cafe",
            "type":"Food & Drink"
        }
    ],
    "sg:phone":"+32 69 68 98 59",
    "sg:postcode":"7950",
    "sg:province":"Hainaut",
    "sg:tags":[
        "caf\u00e9s"
    ],
    "wof:name":"Taverne Le Barbizon",
    "wof:placetype":"venue"
},
  "geometry": {"coordinates":[3.7548930645,50.5657539368],"type":"Point"}
}