{
  "type": "Feature",
  "properties": {
    "addr:full":"Vossaardestraat 62 Wervik West-Vlaanderen 8940",
    "addr:housenumber":"62",
    "addr:postcode":"8940",
    "addr:street":"Vossaardestraat",
    "iso:country":"BE",
    "sg:address":"Vossaardestraat 62",
    "sg:city":"Wervik",
    "sg:classifiers":[
        {
            "category":"Real Estate",
            "subcategory":"Surveying",
            "type":"Services"
        }
    ],
    "sg:phone":"+32 56 31 21 39",
    "sg:postcode":"8940",
    "sg:province":"West-Vlaanderen",
    "sg:tags":[
        "surveyor",
        "land"
    ],
    "wof:name":"Vangheluwe C",
    "wof:placetype":"venue"
},
  "geometry": {"coordinates":[3.0143859386,50.8118743896],"type":"Point"}
}