{
  "type": "Feature",
  "properties": {
    "addr:full":"Schonefelderweg 92 Eupen/eupen Li\u00e8ge 4700",
    "addr:housenumber":"92",
    "addr:postcode":"4700",
    "addr:street":"Schonefelderweg",
    "iso:country":"BE",
    "sg:address":"Schonefelderweg 92",
    "sg:city":"Eupen/eupen",
    "sg:orig_category":"Paramedische behandelingen",
    "sg:phone":"+32 87 74 28 98",
    "sg:postcode":"4700",
    "sg:province":"Li\u00e8ge",
    "wof:name":"Niessen",
    "wof:placetype":"venue"
},
  "geometry": {"coordinates":[6.0518388748,50.626411438],"type":"Point"}
}