{
  "type": "Feature",
  "properties": {
    "addr:full":"Vroonwegel 3 Kapelle-op-den-bos (nieuwenrode) Vlaams-Brabant 1880",
    "addr:housenumber":"3",
    "addr:postcode":"1880",
    "addr:street":"Vroonwegel",
    "iso:country":"BE",
    "sg:address":"Vroonwegel 3",
    "sg:city":"Kapelle-op-den-bos (nieuwenrode)",
    "sg:classifiers":[
        {
            "category":"Arena",
            "subcategory":"Sports Club",
            "type":"Entertainment"
        }
    ],
    "sg:phone":"+32 15 71 02 85",
    "sg:postcode":"1880",
    "sg:province":"Vlaams-Brabant",
    "wof:name":"Petanqueclub Nikaro Vzw",
    "wof:placetype":"venue"
},
  "geometry": {"coordinates":[4.3529539108,50.9810791016],"type":"Point"}
}