{
  "type": "Feature",
  "properties": {
    "addr:full":"Rue De Bomer\u00c9e 54ba Charleroi Hainaut 6032",
    "addr:housenumber":"54ba",
    "addr:postcode":"6032",
    "addr:street":"Rue De Bomere\u0301E;Hainaut",
    "iso:country":"BE",
    "sg:address":"Rue De Bomer\u00c9e 54ba",
    "sg:city":"Charleroi",
    "sg:orig_category":"Stations-service and carburants. Entretien and r\u00e9parations de voitures",
    "sg:phone":"+32 71 43 14 25",
    "sg:postcode":"6032",
    "sg:province":"Hainaut",
    "wof:name":"Shell",
    "wof:placetype":"venue"
},
  "geometry": {"coordinates":[4.4021511078,50.3839759827],"type":"Point"}
}