{
  "type": "Feature",
  "properties": {
    "iso:country":"BE",
    "sg:address":"Kon Astridlaan 55",
    "sg:city":"Wetteren",
    "sg:classifiers":[
        {
            "category":"Autos & Motor Vehicles",
            "subcategory":"Automobile Sales",
            "type":"Retail Goods"
        }
    ],
    "sg:phone":"+32 9 369 14 14",
    "sg:postcode":"9230",
    "sg:province":"Oost-Vlaanderen",
    "sg:tags":[
        "equipment",
        "motor-cars",
        "transport"
    ],
    "wof:name":"Auto-palace (garage) Bvba",
    "wof:placetype":"venue"
},
  "geometry": {"coordinates":[3.8782510757,51.0051269531],"type":"Point"}
}