{
  "type": "Feature",
  "properties": {
    "iso:country":"BE",
    "sg:address":"Rue Collin Leloup 30",
    "sg:city":"Spa",
    "sg:classifiers":[
        {
            "category":"Building & Trades",
            "subcategory":"Pest Control",
            "type":"Services"
        }
    ],
    "sg:phone":"+32 87 77 52 09",
    "sg:postcode":"4900",
    "sg:province":"Li\u00e8ge",
    "sg:tags":[
        "painting",
        "contractor"
    ],
    "wof:name":"Lousberg G",
    "wof:placetype":"venue"
},
  "geometry": {"coordinates":[5.8626141548,50.4898262024],"type":"Point"}
}