{
  "type": "Feature",
  "properties": {
    "addr:full":"Marcel Gr\u00dcnerstraat 9b37 Sint-jans-molenbeek/molenbeek-saint-jean Bruxelles-Capitale 1080",
    "addr:housenumber":"9b37 sint-jans-molenbeek",
    "addr:postcode":"1080",
    "addr:street":"Gru\u0308Nerstraat",
    "iso:country":"BE",
    "sg:address":"Marcel Gr\u00dcnerstraat 9b37",
    "sg:city":"Sint-jans-molenbeek/molenbeek-saint-jean",
    "sg:orig_category":"Artsen and specialisten",
    "sg:phone":"+32 2 411 44 13",
    "sg:postcode":"1080",
    "sg:province":"Bruxelles-Capitale",
    "wof:name":"Guy Hannecart",
    "wof:placetype":"venue"
},
  "geometry": {"coordinates":[4.3168520927,50.8588790894],"type":"Point"}
}