{
  "type": "Feature",
  "properties": {
    "addr:full":"Damse Vaart-zuid 26 Damme West-Vlaanderen 8340",
    "addr:housenumber":"26",
    "addr:postcode":"8340",
    "addr:street":"Damse Vaart-Zuid",
    "iso:country":"BE",
    "sg:address":"Damse Vaart-zuid 26",
    "sg:city":"Damme",
    "sg:classifiers":[
        {
            "category":"Restaurant",
            "type":"Food & Drink"
        }
    ],
    "sg:phone":"+32 50 50 18 66",
    "sg:postcode":"8340",
    "sg:province":"West-Vlaanderen",
    "wof:name":"Breughel",
    "wof:placetype":"venue"
},
  "geometry": {"coordinates":[3.3189098835,51.2500801086],"type":"Point"}
}