{
  "type": "Feature",
  "properties": {
    "iso:country":"BE",
    "sg:address":"Grote Baan 7",
    "sg:city":"Haacht (wespelaar)",
    "sg:classifiers":[
        {
            "category":"Real Estate",
            "subcategory":"Architect",
            "type":"Services"
        }
    ],
    "sg:phone":"+32 16 60 92 70",
    "sg:postcode":"3150",
    "sg:province":"Vlaams-Brabant",
    "wof:name":"Verplancke H",
    "wof:placetype":"venue"
},
  "geometry": {"coordinates":[4.6386470795,50.9577789307],"type":"Point"}
}