{
  "type": "Feature",
  "properties": {
    "addr:full":"Rue De Commerce 3 Andenne Namur 5300",
    "addr:housenumber":"3",
    "addr:postcode":"5300",
    "addr:street":"Rue De Commerce",
    "iso:country":"BE",
    "sg:address":"Rue De Commerce 3",
    "sg:city":"Andenne",
    "sg:orig_category":"Cr\u00e9dits divers",
    "sg:postcode":"5300",
    "sg:province":"Namur",
    "wof:name":"Postomat Andenne",
    "wof:placetype":"venue"
},
  "geometry": {"coordinates":[5.0966510773,50.4899330139],"type":"Point"}
}