{
  "type": "Feature",
  "properties": {
    "iso:country":"BE",
    "sg:address":"Rue Du Fisch Club 6",
    "sg:city":"Mons",
    "sg:classifiers":[
        {
            "category":"Professional",
            "subcategory":"Computer Services",
            "type":"Services"
        }
    ],
    "sg:phone":"+32 65 37 42 68",
    "sg:postcode":"7000",
    "sg:province":"Hainaut",
    "sg:tags":[
        "-",
        "processing",
        "data",
        "used"
    ],
    "wof:name":"Droit Et Devoir Asbl",
    "wof:placetype":"venue"
},
  "geometry": {"coordinates":[3.9616639614,50.4528045654],"type":"Point"}
}