{
  "type": "Feature",
  "properties": {
    "addr:full":"Wezel 4 Herselt Antwerpen 2230",
    "addr:housenumber":"4",
    "addr:postcode":"2230",
    "addr:street":"Wezel",
    "iso:country":"BE",
    "sg:address":"Wezel 4",
    "sg:city":"Herselt",
    "sg:classifiers":[
        {
            "category":"Professional",
            "type":"Services"
        }
    ],
    "sg:phone":"+32 14 54 52 04",
    "sg:postcode":"2230",
    "sg:province":"Antwerpen",
    "sg:tags":[
        "industrial",
        "work",
        "-",
        "maintenance"
    ],
    "wof:name":"Bos",
    "wof:placetype":"venue"
},
  "geometry": {"coordinates":[4.9134178162,51.0374755859],"type":"Point"}
}