{
  "type": "Feature",
  "properties": {
    "addr:full":"9060 Zelzate Oost-Vlaanderen 9060",
    "addr:postcode":"9060;9060",
    "iso:country":"BE",
    "sg:address":"9060",
    "sg:city":"Zelzate",
    "sg:orig_category":"Pharmaciens",
    "sg:phone":"+32 900 10 500",
    "sg:postcode":"9060",
    "sg:province":"Oost-Vlaanderen",
    "wof:name":"Pharmacies De Garde",
    "wof:placetype":"venue"
},
  "geometry": {"coordinates":[3.8146300316,51.1975364685],"type":"Point"}
}