{
  "type": "Feature",
  "properties": {
    "iso:country":"BE",
    "sg:address":"4 Augustusplein 5b11",
    "sg:city":"Etterbeek/etterbeek",
    "sg:orig_category":"Artsen and specialisten",
    "sg:phone":"+32 2 734 29 68",
    "sg:postcode":"1040",
    "sg:province":"Bruxelles-Capitale",
    "wof:name":"Andr\u00c9 Dachy",
    "wof:placetype":"venue"
},
  "geometry": {"coordinates":[4.401362896,50.832660675],"type":"Point"}
}