{
  "type": "Feature",
  "properties": {
    "iso:country":"BE",
    "sg:address":"Rue De Boussu 216",
    "sg:city":"Saint-ghislain (hautrage)",
    "sg:classifiers":[
        {
            "category":"Building & Trades",
            "subcategory":"Cleaning & Sanitation",
            "type":"Services"
        }
    ],
    "sg:phone":"+32 475 75 39 67",
    "sg:postcode":"7334",
    "sg:province":"Hainaut",
    "sg:tags":[
        "janitor"
    ],
    "wof:name":"Clean Service",
    "wof:placetype":"venue"
},
  "geometry": {"coordinates":[3.7779951096,50.4636955261],"type":"Point"}
}