{
  "type": "Feature",
  "properties": {
    "addr:full":"Avenue Du Douaire 64 Ottignies-louvain-la-neuve (ottignies) Brabant Wallon 1340",
    "addr:housenumber":"64",
    "addr:postcode":"1340",
    "addr:street":"Avenue Du Douaire",
    "iso:country":"BE",
    "sg:address":"Avenue Du Douaire 64",
    "sg:city":"Ottignies-louvain-la-neuve (ottignies)",
    "sg:classifiers":[
        {
            "category":"Shopping",
            "subcategory":"Books",
            "type":"Retail Goods"
        }
    ],
    "sg:phone":"+32 10 41 70 46",
    "sg:postcode":"1340",
    "sg:province":"Brabant Wallon",
    "sg:tags":[
        "bookseller"
    ],
    "wof:name":"Janus Librairie",
    "wof:placetype":"venue"
},
  "geometry": {"coordinates":[4.5672249794,50.6636390686],"type":"Point"}
}