{
  "type": "Feature",
  "properties": {
    "addr:full":"Sint-maartensstraat 19 Ardooie West-Vlaanderen 8851",
    "addr:housenumber":"19",
    "addr:postcode":"8851",
    "addr:street":"Sint-Maartensstraat",
    "iso:country":"BE",
    "sg:address":"Sint-maartensstraat 19",
    "sg:city":"Ardooie",
    "sg:orig_category":"Varkenskwekers",
    "sg:phone":"+32 51 74 46 19",
    "sg:postcode":"8851",
    "sg:province":"West-Vlaanderen",
    "wof:name":"Frans Dewulf",
    "wof:placetype":"venue"
},
  "geometry": {"coordinates":[3.2113389969,50.9953193665],"type":"Point"}
}