{
  "type": "Feature",
  "properties": {
    "addr:full":"Quai D'arona 3a Huy Li\u00e8ge 4500",
    "addr:housenumber":"3a",
    "addr:postcode":"4500",
    "addr:street":"Quai D'Arona",
    "iso:country":"BE",
    "sg:address":"Quai D'arona 3a",
    "sg:city":"Huy",
    "sg:classifiers":[
        {
            "category":"Professional",
            "subcategory":"Credit Reporting & Collection",
            "type":"Services"
        }
    ],
    "sg:phone":"+32 477 88 71 79",
    "sg:postcode":"4500",
    "sg:province":"Li\u00e8ge",
    "sg:tags":[
        "bailiff"
    ],
    "wof:name":"Verpoorten J",
    "wof:placetype":"venue"
},
  "geometry": {"coordinates":[5.2429351807,50.5282783508],"type":"Point"}
}