{
  "type": "Feature",
  "properties": {
    "addr:full":"Rue G\u00e9n\u00e9ral De Gaulle 182 Li\u00e8ge 1 (li\u00e8ge 2) Li\u00e8ge 4020",
    "addr:housenumber":"182;1;2",
    "addr:postcode":"4020",
    "addr:street":"Rue Ge\u0301Ne\u0301Ral De Gaulle",
    "iso:country":"BE",
    "sg:address":"Rue G\u00e9n\u00e9ral De Gaulle 182",
    "sg:city":"Li\u00e8ge 1 (li\u00e8ge 2)",
    "sg:classifiers":[
        {
            "category":"Utilities",
            "subcategory":"Refuse",
            "type":"Services"
        }
    ],
    "sg:phone":"+32 4 343 64 33",
    "sg:postcode":"4020",
    "sg:province":"Li\u00e8ge",
    "sg:tags":[
        "removal"
    ],
    "wof:name":"Spiroux J-c",
    "wof:placetype":"venue"
},
  "geometry": {"coordinates":[5.597507,50.6426467896],"type":"Point"}
}