{
  "type": "Feature",
  "properties": {
    "iso:country":"BE",
    "sg:address":"Kalkhoevestraat 1",
    "sg:city":"Waregem",
    "sg:orig_category":"Diverse bedrijfsbeheeradviesbureaus",
    "sg:phone":"+32 56 62 02 66",
    "sg:postcode":"8790",
    "sg:province":"West-Vlaanderen",
    "wof:name":"Industry Associates 'indas'",
    "wof:placetype":"venue"
},
  "geometry": {"coordinates":[3.4481890202,50.8727493286],"type":"Point"}
}