{
  "type": "Feature",
  "properties": {
    "addr:full":"K. Albertlaan 9 Neerpelt Limburg 3910",
    "addr:housenumber":"9",
    "addr:postcode":"3910",
    "addr:street":"K. Albertlaan",
    "iso:country":"BE",
    "sg:address":"K. Albertlaan 9",
    "sg:city":"Neerpelt",
    "sg:classifiers":[
        {
            "category":"Insurance",
            "subcategory":"Life Insurance",
            "type":"Services"
        }
    ],
    "sg:phone":"+32 11 64 12 04",
    "sg:postcode":"3910",
    "sg:province":"Limburg",
    "sg:tags":[
        "assurance"
    ],
    "wof:name":"Verzekeringskantoor Mortelmans",
    "wof:placetype":"venue"
},
  "geometry": {"coordinates":[5.4315428734,51.2268409729],"type":"Point"}
}