{
  "type": "Feature",
  "properties": {
    "addr:full":"Schriekstraat 123 Heist-op-den-berg (schriek) Antwerpen 2223",
    "addr:housenumber":"123",
    "addr:postcode":"2223",
    "addr:street":"Schriekstraat",
    "iso:country":"BE",
    "sg:address":"Schriekstraat 123",
    "sg:city":"Heist-op-den-berg (schriek)",
    "sg:classifiers":[
        {
            "category":"Bars & Pubs",
            "type":"Food & Drink"
        }
    ],
    "sg:phone":"+32 15 76 14 69",
    "sg:postcode":"2223",
    "sg:province":"Antwerpen",
    "wof:name":"Racerke ('t)",
    "wof:placetype":"venue"
},
  "geometry": {"coordinates":[4.6935648918,51.0282707214],"type":"Point"}
}