{
  "type": "Feature",
  "properties": {
    "addr:full":"Waterloose Steenweg 64 Elsene (brussel) Bruxelles-Capitale 1050",
    "addr:housenumber":"64",
    "addr:postcode":"1050",
    "addr:street":"Waterloose Steenweg",
    "iso:country":"BE",
    "sg:address":"Waterloose Steenweg 64",
    "sg:city":"Elsene (brussel)",
    "sg:orig_category":"Sociale secretariaten Verplichte sociale verzekeringen",
    "sg:phone":"+32 2 538 20 92",
    "sg:postcode":"1050",
    "sg:province":"Bruxelles-Capitale",
    "wof:name":"Partena",
    "wof:placetype":"venue"
},
  "geometry": {"coordinates":[4.3552598953,50.8220481873],"type":"Point"}
}