{
  "type": "Feature",
  "properties": {
    "iso:country":"BE",
    "sg:address":"Veldstraat 2",
    "sg:city":"Hulshout",
    "sg:orig_category":"Sportclubs Sportterreinen and installaties behalve sportcentra",
    "sg:phone":"+32 16 69 93 44",
    "sg:postcode":"2235",
    "sg:province":"Antwerpen",
    "wof:name":"Kvc Zw.duiv.westmeerbeek",
    "wof:placetype":"venue"
},
  "geometry": {"coordinates":[4.8316731453,51.0541534424],"type":"Point"}
}