{
  "type": "Feature",
  "properties": {
    "addr:full":"Molenstraat 11 Ruiselede West-Vlaanderen 8755",
    "addr:housenumber":"11",
    "addr:postcode":"8755",
    "addr:street":"Molenstraat",
    "iso:country":"BE",
    "sg:address":"Molenstraat 11",
    "sg:city":"Ruiselede",
    "sg:orig_category":"Sportclubs",
    "sg:phone":"+32 51 68 81 19",
    "sg:postcode":"8755",
    "sg:province":"West-Vlaanderen",
    "wof:name":"Shooting Team Molendorp",
    "wof:placetype":"venue"
},
  "geometry": {"coordinates":[3.3930859566,51.0385704041],"type":"Point"}
}