{
  "type": "Feature",
  "properties": {
    "iso:country":"BE",
    "sg:address":"Stationstraat 172",
    "sg:city":"Waregem",
    "sg:orig_category":"GROENTEN AND FRUIT Groenten and fruit Gh",
    "sg:phone":"+32 56 60 56 05",
    "sg:postcode":"8790",
    "sg:province":"West-Vlaanderen",
    "wof:name":"Fruitstation",
    "wof:placetype":"venue"
},
  "geometry": {"coordinates":[3.426956892,50.8926010132],"type":"Point"}
}