{
  "type": "Feature",
  "properties": {
    "addr:full":"Hippoliet Van Peenestraat 24 Kaprijke Oost-Vlaanderen 9970",
    "addr:housenumber":"24",
    "addr:postcode":"9970",
    "addr:street":"Hippoliet Van Peenestraat",
    "iso:country":"BE",
    "sg:address":"Hippoliet Van Peenestraat 24",
    "sg:city":"Kaprijke",
    "sg:classifiers":[
        {
            "category":"Education",
            "subcategory":"Music School",
            "type":"Public Place"
        }
    ],
    "sg:phone":"+32 9 373 58 23",
    "sg:postcode":"9970",
    "sg:province":"Oost-Vlaanderen",
    "sg:tags":[
        "-",
        "teacher",
        "private"
    ],
    "wof:name":"De Groff H",
    "wof:placetype":"venue"
},
  "geometry": {"coordinates":[3.6135699749,51.215877533],"type":"Point"}
}