{
  "type": "Feature",
  "properties": {
    "addr:full":"Rue Delannay 13 Tournai Hainaut 7504",
    "addr:housenumber":"13",
    "addr:postcode":"7504",
    "addr:street":"Rue Delannay",
    "iso:country":"BE",
    "sg:address":"Rue Delannay 13",
    "sg:city":"Tournai",
    "sg:orig_category":"Eleveurs de bovins",
    "sg:phone":"+32 69 64 80 73",
    "sg:postcode":"7504",
    "sg:province":"Hainaut",
    "wof:name":"Rene Vandenheeren",
    "wof:placetype":"venue"
},
  "geometry": {"coordinates":[3.320524931,50.5782394409],"type":"Point"}
}