{
  "type": "Feature",
  "properties": {
    "addr:full":"Ramskapellestraat 6 Nieuwpoort (ramskapelle) West-Vlaanderen 8620",
    "addr:housenumber":"6",
    "addr:postcode":"8620",
    "addr:street":"Ramskapellestraat",
    "iso:country":"BE",
    "sg:address":"Ramskapellestraat 6",
    "sg:city":"Nieuwpoort (ramskapelle)",
    "sg:classifiers":[
        {
            "category":"Restaurant",
            "type":"Food & Drink"
        }
    ],
    "sg:phone":"+32 58 23 60 38",
    "sg:postcode":"8620",
    "sg:province":"West-Vlaanderen",
    "sg:tags":[
        "industrial",
        "kitchen",
        "catering"
    ],
    "wof:name":"Nieuwpoorts Vleesbedrijf",
    "wof:placetype":"venue"
},
  "geometry": {"coordinates":[2.7669389248,51.1247177124],"type":"Point"}
}