{
  "type": "Feature",
  "properties": {
    "addr:full":"Lourdesstraat Gent Oost-Vlaanderen 9041",
    "addr:postcode":"9041",
    "addr:street":"Lourdesstraat",
    "iso:country":"BE",
    "sg:address":"Lourdesstraat",
    "sg:city":"Gent",
    "sg:orig_category":"Beheer van afvalopslag- and stortplaatsen Overheidsdiensten",
    "sg:phone":"+32 9 240 81 11",
    "sg:postcode":"9041",
    "sg:province":"Oost-Vlaanderen",
    "wof:name":"Ivago Containerpark Oostakker",
    "wof:placetype":"venue"
},
  "geometry": {"coordinates":[3.7521820068,51.0774993896],"type":"Point"}
}