{
  "type": "Feature",
  "properties": {
    "addr:full":"Dompel 32 Zingem Oost-Vlaanderen 9750",
    "addr:housenumber":"32",
    "addr:postcode":"9750",
    "addr:street":"Dompel",
    "iso:country":"BE",
    "sg:address":"Dompel 32",
    "sg:city":"Zingem",
    "sg:orig_category":"Supermarch\u00e9s",
    "sg:phone":"+32 9 384 48 41",
    "sg:postcode":"9750",
    "sg:province":"Oost-Vlaanderen",
    "wof:name":"Unic",
    "wof:placetype":"venue"
},
  "geometry": {"coordinates":[3.6569099426,50.9044685364],"type":"Point"}
}