{
  "type": "Feature",
  "properties": {
    "addr:full":"Henegouwenstraat 91 Gent Oost-Vlaanderen 9000",
    "addr:housenumber":"91",
    "addr:postcode":"9000",
    "addr:street":"Henegouwenstraat;Oost-Vlaanderen",
    "iso:country":"BE",
    "sg:address":"Henegouwenstraat 91",
    "sg:city":"Gent",
    "sg:orig_category":"V\u00eatements. V\u00eatements pour Dames",
    "sg:phone":"+32 9 225 84 76",
    "sg:postcode":"9000",
    "sg:province":"Oost-Vlaanderen",
    "wof:name":"Huis Maxwell's",
    "wof:placetype":"venue"
},
  "geometry": {"coordinates":[3.7268519402,51.0520591736],"type":"Point"}
}