{
  "type": "Feature",
  "properties": {
    "addr:full":"Radestraat 3 Maldegem Oost-Vlaanderen 9990",
    "addr:housenumber":"3",
    "addr:postcode":"9990",
    "addr:street":"Radestraat",
    "iso:country":"BE",
    "sg:address":"Radestraat 3",
    "sg:city":"Maldegem",
    "sg:classifiers":[
        {
            "category":"Restaurant",
            "type":"Food & Drink"
        }
    ],
    "sg:phone":"+32 50 71 84 34",
    "sg:postcode":"9990",
    "sg:province":"Oost-Vlaanderen",
    "wof:name":"De Veldbloem",
    "wof:placetype":"venue"
},
  "geometry": {"coordinates":[3.4663169384,51.2081069946],"type":"Point"}
}