{
  "type": "Feature",
  "properties": {
    "addr:full":"Rue De Mons 24 Braine-le-comte Hainaut 7090",
    "addr:housenumber":"24",
    "addr:postcode":"7090",
    "addr:street":"Rue De Mons",
    "iso:country":"BE",
    "sg:address":"Rue De Mons 24",
    "sg:city":"Braine-le-comte",
    "sg:orig_category":"M\u00e9decins and sp\u00e9cialistes",
    "sg:phone":"+32 67 56 06 67",
    "sg:postcode":"7090",
    "sg:province":"Hainaut",
    "wof:name":"Richard Mauroy",
    "wof:placetype":"venue"
},
  "geometry": {"coordinates":[4.1350312233,50.6094207764],"type":"Point"}
}