{
  "type": "Feature",
  "properties": {
    "iso:country":"BE",
    "sg:address":"Leie 23",
    "sg:city":"Lokeren (groot)",
    "sg:orig_category":"Diverse bedrijfsbeheeradviesbureaus",
    "sg:postcode":"9160",
    "sg:province":"Oost-Vlaanderen",
    "wof:name":"Vector Acces Control Solutions",
    "wof:placetype":"venue"
},
  "geometry": {"coordinates":[4.0027389526,51.0962486267],"type":"Point"}
}