{
  "type": "Feature",
  "properties": {
    "iso:country":"BE",
    "sg:address":"Rue De Namur 153a",
    "sg:city":"Nijvel",
    "sg:orig_category":"Kapsalons",
    "sg:phone":"+32 67 21 53 92",
    "sg:postcode":"1400",
    "sg:province":"Brabant Wallon",
    "wof:name":"Dept J-f",
    "wof:placetype":"venue"
},
  "geometry": {"coordinates":[4.3323178291,50.5996284485],"type":"Point"}
}