{
  "type": "Feature",
  "properties": {
    "iso:country":"BE",
    "sg:address":"Hulstbaan 68",
    "sg:city":"Sint-niklaas",
    "sg:orig_category":"Kapsalons",
    "sg:phone":"+32 3 772 48 04",
    "sg:postcode":"9112",
    "sg:province":"Oost-Vlaanderen",
    "wof:name":"Ferdinand Van Bocxlaer",
    "wof:placetype":"venue"
},
  "geometry": {"coordinates":[4.039949894,51.1514587402],"type":"Point"}
}