{
  "type": "Feature",
  "properties": {
    "iso:country":"BE",
    "sg:address":"Rue Des M\u00e9l\u00e8zes 2",
    "sg:city":"Bruxelles (ixelles)",
    "sg:classifiers":[
        {
            "category":"Health Services",
            "subcategory":"Dentist",
            "type":"Services"
        }
    ],
    "sg:phone":"+32 2 646 47 02",
    "sg:postcode":"1050",
    "sg:province":"Bruxelles-Capitale",
    "wof:name":"Delbrouck C",
    "wof:placetype":"venue"
},
  "geometry": {"coordinates":[4.3649468422,50.8212242126],"type":"Point"}
}