{
  "type": "Feature",
  "properties": {
    "iso:country":"BE",
    "sg:address":"Mandellaan 283",
    "sg:city":"Roeselare",
    "sg:orig_category":"Installation \u00e9lectrique r\u00e9sidentielle",
    "sg:phone":"+32 51 24 58 62",
    "sg:postcode":"8800",
    "sg:province":"West-Vlaanderen",
    "wof:name":"Rik Vandenbroucke",
    "wof:placetype":"venue"
},
  "geometry": {"coordinates":[3.1420359612,50.9477043152],"type":"Point"}
}