{
  "type": "Feature",
  "properties": {
    "addr:full":"Rue Dejoncker 54 Bruxelles (saint-gilles) Bruxelles-Capitale 1060",
    "addr:housenumber":"54",
    "addr:postcode":"1060",
    "addr:street":"Rue Dejoncker",
    "iso:country":"BE",
    "sg:address":"Rue Dejoncker 54",
    "sg:city":"Bruxelles (saint-gilles)",
    "sg:classifiers":[
        {
            "category":"Shopping",
            "subcategory":"Florist",
            "type":"Retail Goods"
        }
    ],
    "sg:phone":"+32 2 538 11 07",
    "sg:postcode":"1060",
    "sg:province":"Bruxelles-Capitale",
    "wof:name":"Fleurs De Louise (les)",
    "wof:placetype":"venue"
},
  "geometry": {"coordinates":[4.3564610481,50.8333625793],"type":"Point"}
}