{
  "type": "Feature",
  "properties": {
    "addr:full":"Grand'rue 31 Thuin Hainaut 6530",
    "addr:housenumber":"31",
    "addr:postcode":"6530",
    "addr:street":"Grand'Rue",
    "iso:country":"BE",
    "sg:address":"Grand'rue 31",
    "sg:city":"Thuin",
    "sg:orig_category":"Postkantoren Verzekeringsmakelaars and experts",
    "sg:phone":"+32 71 59 00 11",
    "sg:postcode":"6530",
    "sg:province":"Hainaut",
    "wof:name":"La Poste",
    "wof:placetype":"venue"
},
  "geometry": {"coordinates":[4.2896828651,50.3388442993],"type":"Point"}
}