{
  "type": "Feature",
  "properties": {
    "addr:full":"Rue Ren\u00c9 Jurdant 19 Wavre Brabant Wallon 1301",
    "addr:housenumber":"19;1301",
    "addr:street":"Rue Rene\u0301 Jurdant",
    "iso:country":"BE",
    "sg:address":"Rue Ren\u00c9 Jurdant 19",
    "sg:city":"Wavre",
    "sg:orig_category":"Epiceries",
    "sg:phone":"+32 10 41 46 73",
    "sg:postcode":"1301",
    "sg:province":"Brabant Wallon",
    "wof:name":"Anne Neyens",
    "wof:placetype":"venue"
},
  "geometry": {"coordinates":[4.585064888,50.7047538757],"type":"Point"}
}