{
  "type": "Feature",
  "properties": {
    "addr:full":"Grand\u00b4rue 6 Trooz Li\u00e8ge 4870",
    "addr:housenumber":"6",
    "addr:postcode":"4870",
    "addr:street":"Grand\u00b4Rue",
    "iso:country":"BE",
    "sg:address":"Grand\u00b4rue 6",
    "sg:city":"Trooz",
    "sg:orig_category":"Onderhoud van kantoor- and computeruitrusting",
    "sg:phone":"+32 4 351 88 81",
    "sg:postcode":"4870",
    "sg:province":"Li\u00e8ge",
    "wof:name":"Fe. Sistema",
    "wof:placetype":"venue"
},
  "geometry": {"coordinates":[5.6750769615,50.5780487061],"type":"Point"}
}