{
  "type": "Feature",
  "properties": {
    "addr:full":"Scouselestraat 40 Temse (steendorp) Oost-Vlaanderen 9140",
    "addr:housenumber":"40",
    "addr:postcode":"9140",
    "addr:street":"Scouselestraat",
    "iso:country":"BE",
    "sg:address":"Scouselestraat 40",
    "sg:city":"Temse (steendorp)",
    "sg:classifiers":[
        {
            "category":"Real Estate",
            "subcategory":"Architect",
            "type":"Services"
        }
    ],
    "sg:phone":"+32 3 774 47 30",
    "sg:postcode":"9140",
    "sg:province":"Oost-Vlaanderen",
    "wof:name":"Goossens Jackie",
    "wof:placetype":"venue"
},
  "geometry": {"coordinates":[4.2559719086,51.1228523254],"type":"Point"}
}