{
  "type": "Feature",
  "properties": {
    "addr:full":"Generaal Baron Jacquesstraat 72 Diksmuide West-Vlaanderen 8600",
    "addr:housenumber":"72",
    "addr:postcode":"8600",
    "addr:street":"Generaal Baron Jacquesstraat",
    "iso:country":"BE",
    "sg:address":"Generaal Baron Jacquesstraat 72",
    "sg:city":"Diksmuide",
    "sg:classifiers":[
        {
            "category":"Professional",
            "subcategory":"Accounting & Tax Preparation",
            "type":"Services"
        }
    ],
    "sg:phone":"+32 51 50 10 66",
    "sg:postcode":"8600",
    "sg:province":"West-Vlaanderen",
    "sg:tags":[
        "accountant"
    ],
    "wof:name":"Accountantskantoor Colaert J & Co Bvba",
    "wof:placetype":"venue"
},
  "geometry": {"coordinates":[2.860172987,51.0332221985],"type":"Point"}
}