{
  "type": "Feature",
  "properties": {
    "addr:full":"Rue Schoonbroodt 7a Herve Li\u00e8ge 4650",
    "addr:housenumber":"7a",
    "addr:postcode":"4650",
    "addr:street":"Rue Schoonbroodt",
    "iso:country":"BE",
    "sg:address":"Rue Schoonbroodt 7a",
    "sg:city":"Herve",
    "sg:classifiers":[
        {
            "category":"Wholesale",
            "subcategory":"Beer",
            "type":"Manufacturing & Wholesale Goods"
        }
    ],
    "sg:phone":"+32 87 67 47 57",
    "sg:postcode":"4650",
    "sg:province":"Li\u00e8ge",
    "sg:tags":[
        "ale",
        "-"
    ],
    "wof:name":"Pev\u00e9e H",
    "wof:placetype":"venue"
},
  "geometry": {"coordinates":[5.796230793,50.639919281],"type":"Point"}
}