{
  "type": "Feature",
  "properties": {
    "iso:country":"BE",
    "sg:address":"Avenue Winston Churchill 165bd60",
    "sg:city":"Ukkel/uccle",
    "sg:orig_category":"M\u00e9decins and sp\u00e9cialistes",
    "sg:phone":"+32 2 344 55 00",
    "sg:postcode":"1180",
    "sg:province":"Bruxelles-Capitale",
    "wof:name":"Raymond-jean Lenoble",
    "wof:placetype":"venue"
},
  "geometry": {"coordinates":[4.360874176,50.811214447],"type":"Point"}
}