{
  "type": "Feature",
  "properties": {
    "iso:country":"BE",
    "sg:address":"Begijnhof 24",
    "sg:city":"Sint-truiden",
    "sg:classifiers":[
        {
            "category":"Landmark",
            "subcategory":"Tourist Attraction",
            "type":"Public Place"
        }
    ],
    "sg:phone":"+32 11 68 87 52",
    "sg:postcode":"3800",
    "sg:province":"Limburg",
    "sg:tags":[
        "-",
        "tourism",
        "interest",
        "sight"
    ],
    "wof:name":"Festraets Studio",
    "wof:placetype":"venue"
},
  "geometry": {"coordinates":[5.1931858063,50.8215560913],"type":"Point"}
}