{
  "type": "Feature",
  "properties": {
    "iso:country":"BE",
    "sg:address":"Hamerstraat 2",
    "sg:city":"Mechelen",
    "sg:orig_category":"Installation de menuiserie en bois and plastique",
    "sg:phone":"+32 15 41 16 93",
    "sg:postcode":"2800",
    "sg:province":"Antwerpen",
    "wof:name":"Oger",
    "wof:placetype":"venue"
},
  "geometry": {"coordinates":[4.4924697876,51.0199317932],"type":"Point"}
}