{
  "type": "Feature",
  "properties": {
    "iso:country":"BE",
    "sg:address":"Driftweg 3",
    "sg:city":"De Haan",
    "sg:orig_category":"V\u00eatements pour b\u00e9b\u00e9s and enfants",
    "sg:phone":"+32 59 23 66 10",
    "sg:postcode":"8420",
    "sg:province":"West-Vlaanderen",
    "wof:name":"Huis Guapi Kids",
    "wof:placetype":"venue"
},
  "geometry": {"coordinates":[3.0333840847,51.2721481323],"type":"Point"}
}