{
  "type": "Feature",
  "properties": {
    "addr:full":"Vieux Chemin D'ath 23c Tournai Hainaut 7531",
    "addr:housenumber":"23c",
    "addr:postcode":"7531",
    "addr:street":"Vieux Chemin D'Ath",
    "iso:country":"BE",
    "sg:address":"Vieux Chemin D'ath 23c",
    "sg:city":"Tournai",
    "sg:orig_category":"Rev\u00eatements de sols and murs. Rev\u00eatements pour sols and murs. Eclairage et \u00e9quipements du foyer. Pei",
    "sg:phone":"+32 69 54 73 38",
    "sg:postcode":"7531",
    "sg:province":"Hainaut",
    "wof:name":"Didier Decor Et Fils",
    "wof:placetype":"venue"
},
  "geometry": {"coordinates":[3.4714920521,50.6165924072],"type":"Point"}
}