{
  "type": "Feature",
  "properties": {
    "iso:country":"BE",
    "sg:address":"Sint-jacobstraat 1",
    "sg:city":"Stabroek (hoevenen)",
    "sg:classifiers":[
        {
            "category":"Professional",
            "type":"Services"
        }
    ],
    "sg:phone":"+32 3 568 86 23",
    "sg:postcode":"2940",
    "sg:province":"Antwerpen",
    "sg:tags":[
        "industrial",
        "work",
        "-",
        "maintenance"
    ],
    "wof:name":"D M Service",
    "wof:placetype":"venue"
},
  "geometry": {"coordinates":[4.3763451576,51.3226966858],"type":"Point"}
}