{
  "type": "Feature",
  "properties": {
    "addr:full":"Stationsstraat 76 Oosterzele Oost-Vlaanderen 9860",
    "addr:housenumber":"76",
    "addr:postcode":"9860",
    "addr:street":"Stationsstraat;Oost-Vlaanderen",
    "iso:country":"BE",
    "sg:address":"Stationsstraat 76",
    "sg:city":"Oosterzele",
    "sg:orig_category":"Banques and organismes de cr\u00e9dit",
    "sg:phone":"+32 9 362 93 84",
    "sg:postcode":"9860",
    "sg:province":"Oost-Vlaanderen",
    "wof:name":"Ippa",
    "wof:placetype":"venue"
},
  "geometry": {"coordinates":[3.7757370472,50.9363555908],"type":"Point"}
}