{
  "type": "Feature",
  "properties": {
    "addr:full":"Chauss\u00c9e De Bruxelles 401 Ath Hainaut 7822",
    "addr:housenumber":"401",
    "addr:postcode":"7822",
    "addr:street":"Chausse\u0301E De Bruxelles",
    "iso:country":"BE",
    "sg:address":"Chauss\u00c9e De Bruxelles 401",
    "sg:city":"Ath",
    "sg:classifiers":[
        {
            "category":"Restaurant",
            "type":"Food & Drink"
        }
    ],
    "sg:phone":"+32 68 55 12 41",
    "sg:postcode":"7822",
    "sg:province":"Hainaut",
    "sg:tags":[
        "organisation",
        "de",
        "f\u00eates",
        "catering"
    ],
    "wof:name":"Le Relais De La Diligence",
    "wof:placetype":"venue"
},
  "geometry": {"coordinates":[3.8858850002,50.6560249329],"type":"Point"}
}