{
  "type": "Feature",
  "properties": {
    "addr:full":"Rue Docteur Jacquerye 85 Mons (jemappes) Hainaut 7012",
    "addr:housenumber":"85",
    "addr:postcode":"7012",
    "addr:street":"Rue Docteur Jacquerye",
    "iso:country":"BE",
    "sg:address":"Rue Docteur Jacquerye 85",
    "sg:city":"Mons (jemappes)",
    "sg:classifiers":[
        {
            "category":"Bakery",
            "type":"Food & Drink"
        }
    ],
    "sg:phone":"+32 65 82 25 92",
    "sg:postcode":"7012",
    "sg:province":"Hainaut",
    "sg:tags":[
        "confectioner",
        "baker"
    ],
    "wof:name":"Moulart M",
    "wof:placetype":"venue"
},
  "geometry": {"coordinates":[3.8894600868,50.4481964111],"type":"Point"}
}