{
  "type": "Feature",
  "properties": {
    "iso:country":"BE",
    "sg:address":"Klinkestraat 10",
    "sg:city":"Lichtervelde",
    "sg:orig_category":"Varkenskwekers",
    "sg:phone":"+32 51 72 33 38",
    "sg:postcode":"8810",
    "sg:province":"West-Vlaanderen",
    "wof:name":"Dirk Bouckaert",
    "wof:placetype":"venue"
},
  "geometry": {"coordinates":[3.140818119,51.0070266724],"type":"Point"}
}