{
  "type": "Feature",
  "properties": {
    "addr:full":"Terploeg 58 Tessenderlo Limburg 3980",
    "addr:housenumber":"58",
    "addr:postcode":"3980",
    "addr:street":"Terploeg",
    "iso:country":"BE",
    "sg:address":"Terploeg 58",
    "sg:city":"Tessenderlo",
    "sg:classifiers":[
        {
            "category":"Utilities",
            "subcategory":"Water",
            "type":"Services"
        }
    ],
    "sg:phone":"+32 13 67 55 49",
    "sg:postcode":"3980",
    "sg:province":"Limburg",
    "sg:tags":[
        "purification"
    ],
    "wof:name":"Axtron Milieutechniek Nv",
    "wof:placetype":"venue"
},
  "geometry": {"coordinates":[5.0875849724,51.0672340393],"type":"Point"}
}