{
  "type": "Feature",
  "properties": {
    "addr:full":"Teniersstraat 49 Vilvoorde Vlaams-Brabant 1800",
    "addr:housenumber":"49",
    "addr:postcode":"1800",
    "addr:street":"Teniersstraat",
    "iso:country":"BE",
    "sg:address":"Teniersstraat 49",
    "sg:city":"Vilvoorde",
    "sg:orig_category":"M\u00e9decins and sp\u00e9cialistes",
    "sg:phone":"+32 2 252 19 02",
    "sg:postcode":"1800",
    "sg:province":"Vlaams-Brabant",
    "wof:name":"Herwig Van Lint",
    "wof:placetype":"venue"
},
  "geometry": {"coordinates":[4.414375782,50.9241065979],"type":"Point"}
}