{
  "type": "Feature",
  "properties": {
    "iso:country":"BE",
    "sg:address":"Albert I Laan 88",
    "sg:city":"Koksijde",
    "sg:classifiers":[
        {
            "category":"Restaurant",
            "type":"Food & Drink"
        }
    ],
    "sg:phone":"+32 58 51 68 43",
    "sg:postcode":"8670",
    "sg:province":"West-Vlaanderen",
    "wof:name":"Rest. De Spelleplekke",
    "wof:placetype":"venue"
},
  "geometry": {"coordinates":[2.6733579636,51.1324424744],"type":"Point"}
}