{
  "type": "Feature",
  "properties": {
    "addr:full":"Rue Sainte-catherine 24 Tournai Hainaut 7500",
    "addr:housenumber":"24",
    "addr:postcode":"7500",
    "addr:street":"Rue Sainte-Catherine",
    "iso:country":"BE",
    "sg:address":"Rue Sainte-catherine 24",
    "sg:city":"Tournai",
    "sg:classifiers":[
        {
            "category":"Cafe",
            "type":"Food & Drink"
        }
    ],
    "sg:phone":"+32 69 23 25 32",
    "sg:postcode":"7500",
    "sg:province":"Hainaut",
    "sg:tags":[
        "caf\u00e9s"
    ],
    "wof:name":"Caf\u00c9 As De Carreau",
    "wof:placetype":"venue"
},
  "geometry": {"coordinates":[3.3959128857,50.6029701233],"type":"Point"}
}