{
  "type": "Feature",
  "properties": {
    "iso:country":"BE",
    "sg:address":"Veldstraat 28",
    "sg:city":"Wevelgem",
    "sg:classifiers":[
        {
            "category":"Manufacturing",
            "subcategory":"Tools & Machinery",
            "type":"Manufacturing & Wholesale Goods"
        }
    ],
    "sg:phone":"+32 56 41 73 23",
    "sg:postcode":"8560",
    "sg:province":"West-Vlaanderen",
    "sg:tags":[
        "solid",
        "carbide"
    ],
    "wof:name":"Dick Maintenance C.v.",
    "wof:placetype":"venue"
},
  "geometry": {"coordinates":[3.1870520115,50.8191833496],"type":"Point"}
}