{
  "type": "Feature",
  "properties": {
    "addr:full":"Hillarestraat 254 Lokeren Oost-Vlaanderen 9160",
    "addr:housenumber":"254",
    "addr:postcode":"9160",
    "addr:street":"Hillarestraat",
    "iso:country":"BE",
    "sg:address":"Hillarestraat 254",
    "sg:city":"Lokeren",
    "sg:orig_category":"Banques and organismes de cr\u00e9dit",
    "sg:phone":"+32 9 348 98 77",
    "sg:postcode":"9160",
    "sg:province":"Oost-Vlaanderen",
    "wof:name":"Kbc",
    "wof:placetype":"venue"
},
  "geometry": {"coordinates":[3.9652268887,51.091468811],"type":"Point"}
}