{
  "type": "Feature",
  "properties": {
    "addr:full":"Sint-stevensstraat 66 Sint-pieters-leeuw Vlaams-Brabant 1600",
    "addr:housenumber":"66",
    "addr:postcode":"1600",
    "addr:street":"Sint-Stevensstraat",
    "iso:country":"BE",
    "sg:address":"Sint-stevensstraat 66",
    "sg:city":"Sint-pieters-leeuw",
    "sg:orig_category":"Banken and kredietinstellingen",
    "sg:phone":"+32 2 377 57 25",
    "sg:postcode":"1600",
    "sg:province":"Vlaams-Brabant",
    "wof:name":"Fortis",
    "wof:placetype":"venue"
},
  "geometry": {"coordinates":[4.2857217789,50.8048706055],"type":"Point"}
}