{
  "type": "Feature",
  "properties": {
    "addr:full":"De Merodelei Turnhout Antwerpen 2300",
    "addr:postcode":"2300",
    "addr:street":"De Merodelei",
    "iso:country":"BE",
    "sg:address":"De Merodelei",
    "sg:city":"Turnhout",
    "sg:classifiers":[
        {
            "category":"Banks & Credit Unions",
            "subcategory":"Bank",
            "type":"Services"
        }
    ],
    "sg:phone":"+32 14 43 62 96",
    "sg:postcode":"2300",
    "sg:province":"Antwerpen",
    "wof:name":"Aslk-cger Bank",
    "wof:placetype":"venue"
},
  "geometry": {"coordinates":[4.9378099442,51.3216743469],"type":"Point"}
}