{
  "type": "Feature",
  "properties": {
    "addr:full":"Rue De Gramptinne 7 Andenne (thon) Namur 5300",
    "addr:housenumber":"7",
    "addr:postcode":"5300",
    "addr:street":"Rue De Gramptinne",
    "iso:country":"BE",
    "sg:address":"Rue De Gramptinne 7",
    "sg:city":"Andenne (thon)",
    "sg:classifiers":[
        {
            "category":"Professional",
            "subcategory":"Testing Lab",
            "type":"Services"
        }
    ],
    "sg:phone":"+32 81 58 81 11",
    "sg:postcode":"5300",
    "sg:province":"Namur",
    "sg:tags":[
        "chemist"
    ],
    "wof:name":"Dozot E Sprl",
    "wof:placetype":"venue"
},
  "geometry": {"coordinates":[4.9937038422,50.4660797119],"type":"Point"}
}