{
  "type": "Feature",
  "properties": {
    "addr:full":"Petites Tailles 6 Vielsalm Luxembourg 6690",
    "addr:housenumber":"6",
    "addr:postcode":"6690",
    "addr:street":"Petites Tailles",
    "iso:country":"BE",
    "sg:address":"Petites Tailles 6",
    "sg:city":"Vielsalm",
    "sg:orig_category":"Maisons de vacances",
    "sg:phone":"+32 3 888 06 81",
    "sg:postcode":"6690",
    "sg:province":"Luxembourg",
    "wof:name":"Valerie Blomme",
    "wof:placetype":"venue"
},
  "geometry": {"coordinates":[5.7692089081,50.2359428406],"type":"Point"}
}