{
  "type": "Feature",
  "properties": {
    "addr:full":"P Verhaertstraat 40 Koksijde West-Vlaanderen 8670",
    "addr:housenumber":"40",
    "addr:postcode":"8670",
    "addr:street":"P Verhaertstraat",
    "iso:country":"BE",
    "sg:address":"P Verhaertstraat 40",
    "sg:city":"Koksijde",
    "sg:orig_category":"Jardinage",
    "sg:phone":"+32 58 51 74 69",
    "sg:postcode":"8670",
    "sg:province":"West-Vlaanderen",
    "wof:name":"Kreatuin Oost",
    "wof:placetype":"venue"
},
  "geometry": {"coordinates":[2.6851170063,51.1215667725],"type":"Point"}
}