{
  "type": "Feature",
  "properties": {
    "iso:country":"BE",
    "sg:address":"Jourdanstraat 45b55",
    "sg:city":"Sint-gillis/saint-gilles",
    "sg:orig_category":"Sociale huisvestingsmaatschappijen",
    "sg:phone":"+32 2 533 19 11",
    "sg:postcode":"1060",
    "sg:province":"Bruxelles-Capitale",
    "wof:name":"S.l.r.b.",
    "wof:placetype":"venue"
},
  "geometry": {"coordinates":[4.3537168503,50.8341369629],"type":"Point"}
}