{
  "type": "Feature",
  "properties": {
    "iso:country":"BE",
    "sg:address":"Everaertsstraat 78",
    "sg:city":"Antwerpen",
    "sg:classifiers":[
        {
            "category":"Building & Trades",
            "subcategory":"Construction",
            "type":"Services"
        }
    ],
    "sg:phone":"+32 3 272 06 87",
    "sg:postcode":"2060",
    "sg:province":"Antwerpen",
    "sg:tags":[
        "asphalt",
        "contractor"
    ],
    "wof:name":"Roofing Service",
    "wof:placetype":"venue"
},
  "geometry": {"coordinates":[4.4256567955,51.2271270752],"type":"Point"}
}