{
  "type": "Feature",
  "properties": {
    "iso:country":"BE",
    "sg:address":"Kardinaal Cardijnlaan 1ba",
    "sg:city":"Willebroek",
    "sg:orig_category":"Enseignement maternel and primaire",
    "sg:phone":"+32 3 886 42 58",
    "sg:postcode":"2830",
    "sg:province":"Antwerpen",
    "wof:name":"Vrije Basisschool",
    "wof:placetype":"venue"
},
  "geometry": {"coordinates":[4.3548970222,51.0326080322],"type":"Point"}
}