{
  "type": "Feature",
  "properties": {
    "iso:country":"BE",
    "sg:address":"Rue Du Beau Site 3b Box 14",
    "sg:city":"Bruxelles",
    "sg:classifiers":[
        {
            "category":"Education",
            "subcategory":"Special Training",
            "type":"Public Place"
        }
    ],
    "sg:phone":"+32 2 647 79 44",
    "sg:postcode":"1000",
    "sg:province":"Bruxelles-Capitale",
    "sg:tags":[
        "professional"
    ],
    "wof:name":"Auxilia",
    "wof:placetype":"venue"
},
  "geometry": {"coordinates":[4.3635430336,50.8297538757],"type":"Point"}
}