{
  "type": "Feature",
  "properties": {
    "addr:full":"Rue De La M\u00c9tallurgie 33 Villers-le-bouillet Li\u00e8ge 4530",
    "addr:housenumber":"33",
    "addr:postcode":"4530",
    "addr:street":"Rue De La Me\u0301Tallurgie",
    "iso:country":"BE",
    "sg:address":"Rue De La M\u00c9tallurgie 33",
    "sg:city":"Villers-le-bouillet",
    "sg:orig_category":"Mat\u00e9riel \u00e9lectrique and \u00e9lectronique Gr",
    "sg:phone":"+32 4 259 92 00",
    "sg:postcode":"4530",
    "sg:province":"Li\u00e8ge",
    "wof:name":"Agemat",
    "wof:placetype":"venue"
},
  "geometry": {"coordinates":[5.2622499466,50.5809020996],"type":"Point"}
}