{
  "type": "Feature",
  "properties": {
    "iso:country":"BE",
    "sg:address":"Chemin Du Stocquoy 1-3",
    "sg:city":"Wavre",
    "sg:classifiers":[
        {
            "category":"Professional",
            "subcategory":"Lawyer & Legal Services",
            "type":"Services"
        }
    ],
    "sg:phone":"+32 10 45 46 00",
    "sg:postcode":"1300",
    "sg:province":"Brabant Wallon",
    "wof:name":"Malotaux Denis",
    "wof:placetype":"venue"
},
  "geometry": {"coordinates":[4.6157569885,50.6898498535],"type":"Point"}
}