{
  "type": "Feature",
  "properties": {
    "addr:full":"Industrieln. 17a Derde Industriezone Erembodegem Oost-Vlaanderen 9320",
    "addr:housenumber":"17a",
    "addr:postcode":"9320",
    "addr:street":"Industrieln.;Industriezone",
    "iso:country":"BE",
    "sg:address":"Industrieln. 17a Derde Industriezone",
    "sg:city":"Erembodegem",
    "sg:classifiers":[
        {
            "category":"Shopping",
            "subcategory":"Clothing, Apparel, & Fashions",
            "type":"Retail Goods"
        }
    ],
    "sg:phone":"+32 53 83 16 16",
    "sg:postcode":"9320",
    "sg:province":"Oost-Vlaanderen",
    "sg:tags":[
        "textile",
        "clothing",
        "clothes"
    ],
    "wof:name":"Somati Equipement Nv",
    "wof:placetype":"venue"
},
  "geometry": {"coordinates":[4.0358181,50.9130821228],"type":"Point"}
}