{
  "type": "Feature",
  "properties": {
    "iso:country":"BE",
    "sg:address":"'s Gravenmolenstraat 10c",
    "sg:city":"Grimbergen",
    "sg:orig_category":"Non-Classified Establishments",
    "sg:phone":"+32 2 270 43 21",
    "sg:postcode":"1850",
    "sg:province":"Vlaams-Brabant",
    "wof:name":"Dbl Bvba",
    "wof:placetype":"venue"
},
  "geometry": {"coordinates":[4.3636670113,50.9342727661],"type":"Point"}
}