{
  "type": "Feature",
  "properties": {
    "iso:country":"BE",
    "sg:address":"Rue Des Charmes 141",
    "sg:city":"Andenne",
    "sg:orig_category":"Rusthuizen and serviceflats",
    "sg:phone":"+32 85 61 13 30",
    "sg:postcode":"5300",
    "sg:province":"Namur",
    "wof:name":"Home Monjoie",
    "wof:placetype":"venue"
},
  "geometry": {"coordinates":[5.1154742241,50.4614028931],"type":"Point"}
}