{
  "type": "Feature",
  "properties": {
    "iso:country":"BE",
    "sg:address":"Roomstraat 20",
    "sg:city":"Lokeren",
    "sg:classifiers":[
        {
            "category":"Professional",
            "subcategory":"Management & Consulting",
            "type":"Services"
        }
    ],
    "sg:phone":"+32 9 222 13 92",
    "sg:postcode":"9160",
    "sg:province":"Oost-Vlaanderen",
    "sg:tags":[
        "consultant"
    ],
    "wof:name":"Connexus Bvba",
    "wof:placetype":"venue"
},
  "geometry": {"coordinates":[3.9880080223,51.1027259827],"type":"Point"}
}