{
  "type": "Feature",
  "properties": {
    "addr:full":"Koninklijke Prinsstraat 6 Elsene/ixelles Bruxelles-Capitale 1050",
    "addr:housenumber":"6",
    "addr:postcode":"1050",
    "addr:street":"Koninklijke Prinsstraat",
    "iso:country":"BE",
    "sg:address":"Koninklijke Prinsstraat 6",
    "sg:city":"Elsene/ixelles",
    "sg:orig_category":"Installatie van houten of kunststof schrijnwerk",
    "sg:phone":"+32 2 514 03 13",
    "sg:postcode":"1050",
    "sg:province":"Bruxelles-Capitale",
    "wof:name":"Vue Sur Mer",
    "wof:placetype":"venue"
},
  "geometry": {"coordinates":[4.3633160591,50.8350830078],"type":"Point"}
}