{
  "type": "Feature",
  "properties": {
    "iso:country":"BE",
    "sg:address":"Rue De Barvaux 160",
    "sg:city":"Ciney",
    "sg:orig_category":"Herstellingen and onderhoud van auto's",
    "sg:phone":"+32 83 68 86 91",
    "sg:postcode":"5590",
    "sg:province":"Namur",
    "wof:name":"Garage Meunier",
    "wof:placetype":"venue"
},
  "geometry": {"coordinates":[5.1022520065,50.297088623],"type":"Point"}
}