{
  "type": "Feature",
  "properties": {
    "addr:full":"Petite-hour 8 Houyet Namur 5563",
    "addr:housenumber":"8",
    "addr:postcode":"5563",
    "addr:street":"Petite-Hour",
    "iso:country":"BE",
    "sg:address":"Petite-hour 8",
    "sg:city":"Houyet",
    "sg:orig_category":"Eleveurs de bovins",
    "sg:phone":"+32 82 66 71 64",
    "sg:postcode":"5563",
    "sg:province":"Namur",
    "wof:name":"Didier Janot",
    "wof:placetype":"venue"
},
  "geometry": {"coordinates":[5.0318422318,50.1662750244],"type":"Point"}
}