{
  "type": "Feature",
  "properties": {
    "addr:full":"Kortrijkstraat 274 Oudenaarde Oost-Vlaanderen 9700",
    "addr:housenumber":"274",
    "addr:postcode":"9700",
    "addr:street":"Kortrijkstraat",
    "iso:country":"BE",
    "sg:address":"Kortrijkstraat 274",
    "sg:city":"Oudenaarde",
    "sg:classifiers":[
        {
            "category":"Bars & Pubs",
            "type":"Food & Drink"
        }
    ],
    "sg:phone":"+32 55 31 69 92",
    "sg:postcode":"9700",
    "sg:province":"Oost-Vlaanderen",
    "wof:name":"De Hert",
    "wof:placetype":"venue"
},
  "geometry": {"coordinates":[3.5938498974,50.8505096436],"type":"Point"}
}