{
  "type": "Feature",
  "properties": {
    "addr:full":"Buisson-la-fleur 91 Verlaine Li\u00e8ge 4537",
    "addr:housenumber":"91",
    "addr:postcode":"4537",
    "addr:street":"Buisson-La-Fleur",
    "iso:country":"BE",
    "sg:address":"Buisson-la-fleur 91",
    "sg:city":"Verlaine",
    "sg:classifiers":[
        {
            "category":"Wholesale",
            "subcategory":"Plants",
            "type":"Manufacturing & Wholesale Goods"
        }
    ],
    "sg:phone":"+32 4 259 45 55",
    "sg:postcode":"4537",
    "sg:province":"Li\u00e8ge",
    "sg:tags":[
        "whol",
        "flower",
        "-",
        "grower"
    ],
    "wof:name":"Kousen Fleurs",
    "wof:placetype":"venue"
},
  "geometry": {"coordinates":[5.3110179901,50.6088104248],"type":"Point"}
}