{
  "type": "Feature",
  "properties": {
    "iso:country":"BE",
    "sg:address":"Waregemstraat 461",
    "sg:city":"Deerlijk",
    "sg:classifiers":[
        {
            "category":"Professional",
            "subcategory":"Art Services",
            "type":"Services"
        }
    ],
    "sg:phone":"+32 56 71 64 59",
    "sg:postcode":"8540",
    "sg:province":"West-Vlaanderen",
    "sg:tags":[
        "designer",
        "display"
    ],
    "wof:name":"Christiaens R",
    "wof:placetype":"venue"
},
  "geometry": {"coordinates":[3.3797779083,50.8604431152],"type":"Point"}
}