{
  "type": "Feature",
  "properties": {
    "iso:country":"BE",
    "sg:address":"1840",
    "sg:city":"Londerzeel (groot)",
    "sg:orig_category":"Pharmaciens",
    "sg:phone":"+32 900 10 500",
    "sg:postcode":"1840",
    "sg:province":"Vlaams-Brabant",
    "wof:name":"Pharmacies De Garde",
    "wof:placetype":"venue"
},
  "geometry": {"coordinates":[4.3011660576,51.0014343262],"type":"Point"}
}