{
  "type": "Feature",
  "properties": {
    "addr:full":"Siberiastraat 20 Antwerpen Antwerpen 2030",
    "addr:housenumber":"20",
    "addr:postcode":"2030",
    "addr:street":"Siberiastraat",
    "iso:country":"BE",
    "sg:address":"Siberiastraat 20",
    "sg:city":"Antwerpen",
    "sg:orig_category":"Elektriciteitsproductie and -distributie",
    "sg:phone":"+32 3 205 24 25",
    "sg:postcode":"2030",
    "sg:province":"Antwerpen",
    "wof:name":"Techn.dienst Havenbedrijf",
    "wof:placetype":"venue"
},
  "geometry": {"coordinates":[4.4053401947,51.2416725159],"type":"Point"}
}