{
  "type": "Feature",
  "properties": {
    "iso:country":"BE",
    "sg:address":"Chauss\u00c9e De Monbeuge 506",
    "sg:city":"Mons",
    "sg:orig_category":"Entretien and r\u00e9parations de voitures",
    "sg:phone":"+32 65 35 23 20",
    "sg:postcode":"7022",
    "sg:province":"Hainaut",
    "wof:name":"Garage Cousin & Fils",
    "wof:placetype":"venue"
},
  "geometry": {"coordinates":[4.0181078911,50.4045410156],"type":"Point"}
}