{
  "type": "Feature",
  "properties": {
    "iso:country":"BE",
    "sg:address":"Chauss\u00e9e De Wavre 303",
    "sg:city":"Grez-doiceau (archennes)",
    "sg:classifiers":[
        {
            "category":"Government",
            "subcategory":"Fire Station",
            "type":"Public Place"
        }
    ],
    "sg:phone":"+32 10 81 82 83",
    "sg:postcode":"1390",
    "sg:province":"Brabant Wallon",
    "sg:tags":[
        "installation",
        "-",
        "air conditioning"
    ],
    "wof:name":"Ihd Sa",
    "wof:placetype":"venue"
},
  "geometry": {"coordinates":[4.6626000404,50.7380981445],"type":"Point"}
}