{
  "type": "Feature",
  "properties": {
    "iso:country":"BE",
    "sg:address":"Hoogstraatsesteenweg 6",
    "sg:city":"Rijkevorsel",
    "sg:classifiers":[
        {
            "category":"Professional",
            "subcategory":"Art Services",
            "type":"Services"
        }
    ],
    "sg:phone":"+32 3 314 72 29",
    "sg:postcode":"2310",
    "sg:province":"Antwerpen",
    "sg:tags":[
        "photographer"
    ],
    "wof:name":"Studio Bild",
    "wof:placetype":"venue"
},
  "geometry": {"coordinates":[4.7604298592,51.3506698608],"type":"Point"}
}