{
  "type": "Feature",
  "properties": {
    "iso:country":"BE",
    "sg:address":"Kruisstraat 52",
    "sg:city":"Zomergem",
    "sg:orig_category":"Installation \u00e9lectrique r\u00e9sidentielle",
    "sg:phone":"+32 9 372 83 22",
    "sg:postcode":"9930",
    "sg:province":"Oost-Vlaanderen",
    "wof:name":"Geert Van Acker",
    "wof:placetype":"venue"
},
  "geometry": {"coordinates":[3.5921559334,51.1063537598],"type":"Point"}
}