{
  "type": "Feature",
  "properties": {
    "iso:country":"BE",
    "sg:address":"Rue Auguste Meilleur 1",
    "sg:city":"Sambreville",
    "sg:orig_category":"Fleurs and plantes",
    "sg:phone":"+32 71 77 22 12",
    "sg:postcode":"5060",
    "sg:province":"Namur",
    "wof:name":"Annflor",
    "wof:placetype":"venue"
},
  "geometry": {"coordinates":[4.5876641273,50.4373588562],"type":"Point"}
}