{
  "type": "Feature",
  "properties": {
    "addr:full":"Minervalaan 5 Vorst/forest Bruxelles-Capitale 1190",
    "addr:housenumber":"5",
    "addr:postcode":"1190",
    "addr:street":"Minervalaan;/ Forest",
    "iso:country":"BE",
    "sg:address":"Minervalaan 5",
    "sg:city":"Vorst/forest",
    "sg:classifiers":[
        {
            "category":"Professional",
            "subcategory":"Art Services",
            "type":"Services"
        }
    ],
    "sg:phone":"+32 2 343 28 46",
    "sg:postcode":"1190",
    "sg:province":"Bruxelles-Capitale",
    "sg:tags":[
        "designer",
        "ontwerpers"
    ],
    "wof:name":"L'atelier Retouche",
    "wof:placetype":"venue"
},
  "geometry": {"coordinates":[4.3297610283,50.8108177185],"type":"Point"}
}