{
  "type": "Feature",
  "properties": {
    "addr:full":"Karrestraat 2 Lommel Limburg 3920",
    "addr:housenumber":"2",
    "addr:postcode":"3920",
    "addr:street":"Karrestraat",
    "iso:country":"BE",
    "sg:address":"Karrestraat 2",
    "sg:city":"Lommel",
    "sg:orig_category":"HUISBRANDOLIE",
    "sg:phone":"+32 11 54 47 49",
    "sg:postcode":"3920",
    "sg:province":"Limburg",
    "wof:name":"Jansen & Zn",
    "wof:placetype":"venue"
},
  "geometry": {"coordinates":[5.320291996,51.223236084],"type":"Point"}
}