{
  "type": "Feature",
  "properties": {
    "iso:country":"BE",
    "sg:address":"Rue Du L\u00e9ry 72",
    "sg:city":"L\u00e9glise",
    "sg:classifiers":[
        {
            "category":"Health Services",
            "subcategory":"Nursing And Care Facility",
            "type":"Services"
        }
    ],
    "sg:phone":"+32 63 43 39 21",
    "sg:postcode":"6860",
    "sg:province":"Luxembourg",
    "sg:tags":[
        "home"
    ],
    "wof:name":"L\u00e9onard-guebs",
    "wof:placetype":"venue"
},
  "geometry": {"coordinates":[5.5414681435,49.8094291687],"type":"Point"}
}