{
  "type": "Feature",
  "properties": {
    "addr:full":"Kuringenstraat 11 Hasselt (kuringen) Limburg 3511",
    "addr:housenumber":"11",
    "addr:postcode":"3511",
    "addr:street":"Kuringenstraat",
    "iso:country":"BE",
    "sg:address":"Kuringenstraat 11",
    "sg:city":"Hasselt (kuringen)",
    "sg:classifiers":[
        {
            "category":"Professional",
            "subcategory":"Lawyer & Legal Services",
            "type":"Services"
        }
    ],
    "sg:phone":"+32 11 85 09 90",
    "sg:postcode":"3511",
    "sg:province":"Limburg",
    "wof:name":"Corthouts Andre",
    "wof:placetype":"venue"
},
  "geometry": {"coordinates":[5.29829216,50.9385414124],"type":"Point"}
}