{
  "type": "Feature",
  "properties": {
    "iso:country":"BE",
    "sg:address":"Muylebeekstraat 44",
    "sg:city":"Galmaarden",
    "sg:orig_category":"Dierenartsen",
    "sg:phone":"+32 54 58 75 00",
    "sg:postcode":"1570",
    "sg:province":"Vlaams-Brabant",
    "wof:name":"Werner Serteels",
    "wof:placetype":"venue"
},
  "geometry": {"coordinates":[3.9896130562,50.7374038696],"type":"Point"}
}