{
  "type": "Feature",
  "properties": {
    "iso:country":"BE",
    "sg:address":"Ooststraat 77",
    "sg:city":"Roeselare",
    "sg:classifiers":[
        {
            "category":"Insurance",
            "subcategory":"Life Insurance",
            "type":"Services"
        }
    ],
    "sg:phone":"+32 51 20 34 99",
    "sg:postcode":"8800",
    "sg:province":"West-Vlaanderen",
    "sg:tags":[
        "assurance"
    ],
    "wof:name":"Bur. Wyckhuys-deceuninck",
    "wof:placetype":"venue"
},
  "geometry": {"coordinates":[3.1275720596,50.9472007751],"type":"Point"}
}