{
  "type": "Feature",
  "properties": {
    "iso:country":"BE",
    "sg:address":"Heuvelerweg 3",
    "sg:city":"Neerpelt",
    "sg:orig_category":"Eleveurs de bovins",
    "sg:phone":"+32 11 64 39 97",
    "sg:postcode":"3910",
    "sg:province":"Limburg",
    "wof:name":"Jos Kenis",
    "wof:placetype":"venue"
},
  "geometry": {"coordinates":[5.4808712006,51.2346611023],"type":"Point"}
}