{
  "type": "Feature",
  "properties": {
    "addr:full":"Bloemendaelelaan 10 Maldegem Oost-Vlaanderen 9990",
    "addr:housenumber":"10",
    "addr:postcode":"9990",
    "addr:street":"Bloemendaelelaan",
    "iso:country":"BE",
    "sg:address":"Bloemendaelelaan 10",
    "sg:city":"Maldegem",
    "sg:orig_category":"Artiesten and kunstenaars",
    "sg:phone":"+32 50 71 69 22",
    "sg:postcode":"9990",
    "sg:province":"Oost-Vlaanderen",
    "wof:name":"Geert Verstrynge",
    "wof:placetype":"venue"
},
  "geometry": {"coordinates":[3.4527649879,51.2122344971],"type":"Point"}
}