{
  "type": "Feature",
  "properties": {
    "iso:country":"BE",
    "sg:address":"Rue Du Ramponneau 44",
    "sg:city":"Frasnes-lez-anvaing",
    "sg:orig_category":"Loodgieterij, verwarming and sanitaire installaties",
    "sg:phone":"+32 69 86 72 93",
    "sg:postcode":"7911",
    "sg:province":"Hainaut",
    "wof:name":"Ets Mahieu Serge",
    "wof:placetype":"venue"
},
  "geometry": {"coordinates":[3.620002985,50.6728210449],"type":"Point"}
}