{
  "type": "Feature",
  "properties": {
    "addr:full":"Hoekstraat 9bb Neerpelt Limburg 3910",
    "addr:housenumber":"9bb",
    "addr:postcode":"3910",
    "addr:street":"Hoekstraat",
    "iso:country":"BE",
    "sg:address":"Hoekstraat 9bb",
    "sg:city":"Neerpelt",
    "sg:orig_category":"M\u00e9decins and sp\u00e9cialistes",
    "sg:phone":"+32 11 64 82 24",
    "sg:postcode":"3910",
    "sg:province":"Limburg",
    "wof:name":"Maria Hendrix",
    "wof:placetype":"venue"
},
  "geometry": {"coordinates":[5.4291229248,51.2284851074],"type":"Point"}
}