{
  "type": "Feature",
  "properties": {
    "iso:country":"BE",
    "sg:address":"Corneel Smitslei 61",
    "sg:city":"Borsbeek",
    "sg:classifiers":[
        {
            "category":"Personal",
            "subcategory":"Beauty Salon",
            "type":"Services"
        }
    ],
    "sg:phone":"+32 3 321 43 50",
    "sg:postcode":"2150",
    "sg:province":"Antwerpen",
    "sg:tags":[
        "de",
        "coiffure"
    ],
    "wof:name":"Trendy",
    "wof:placetype":"venue"
},
  "geometry": {"coordinates":[4.4856448174,51.1965141296],"type":"Point"}
}