{
  "type": "Feature",
  "properties": {
    "iso:country":"BE",
    "sg:address":"Torenstraat",
    "sg:city":"Zandhoven",
    "sg:classifiers":[
        {
            "category":"Fast Food",
            "type":"Food & Drink"
        }
    ],
    "sg:phone":"+32 14 51 61 80",
    "sg:postcode":"2280",
    "sg:province":"Antwerpen",
    "sg:tags":[
        "meeneem",
        "restaurant"
    ],
    "wof:name":"Frituur Greet",
    "wof:placetype":"venue"
},
  "geometry": {"coordinates":[4.7386469841,51.188659668],"type":"Point"}
}