{
  "type": "Feature",
  "properties": {
    "addr:full":"Bellestr 58 Heuvelland West-Vlaanderen 8954",
    "addr:housenumber":"58",
    "addr:postcode":"8954",
    "addr:street":"Bellestr",
    "iso:country":"BE",
    "sg:address":"Bellestr 58",
    "sg:city":"Heuvelland",
    "sg:classifiers":[
        {
            "category":"Autos & Motor Vehicles",
            "subcategory":"Automobile Sales",
            "type":"Retail Goods"
        }
    ],
    "sg:phone":"+32 57 44 45 46",
    "sg:postcode":"8954",
    "sg:province":"West-Vlaanderen",
    "sg:tags":[
        "equipment",
        "industrial",
        "transport"
    ],
    "wof:name":"Douve Bvba",
    "wof:placetype":"venue"
},
  "geometry": {"coordinates":[2.7476201057,50.7867088318],"type":"Point"}
}