{
  "type": "Feature",
  "properties": {
    "iso:country":"BE",
    "sg:address":"Rue Edouard Vaillant 79",
    "sg:city":"Quaregnon",
    "sg:orig_category":"Boucheries",
    "sg:phone":"+32 65 66 60 32",
    "sg:postcode":"7390",
    "sg:province":"Hainaut",
    "wof:name":"Pierre Boucart",
    "wof:placetype":"venue"
},
  "geometry": {"coordinates":[3.8644878864,50.4180335999],"type":"Point"}
}