{
  "type": "Feature",
  "properties": {
    "iso:country":"BE",
    "sg:address":"Rue Fransman 53",
    "sg:city":"Brussel/bruxelles",
    "sg:orig_category":"Boucheries",
    "sg:phone":"+32 2 426 03 25",
    "sg:postcode":"1020",
    "sg:province":"Bruxelles-Capitale",
    "wof:name":"Marc Cautaerts",
    "wof:placetype":"venue"
},
  "geometry": {"coordinates":[4.3456158638,50.878692627],"type":"Point"}
}