{
  "type": "Feature",
  "properties": {
    "addr:full":"Oostmolenstraat 129 Aalter Oost-Vlaanderen 9880",
    "addr:housenumber":"129",
    "addr:postcode":"9880",
    "addr:street":"Oostmolenstraat",
    "iso:country":"BE",
    "sg:address":"Oostmolenstraat 129",
    "sg:city":"Aalter",
    "sg:orig_category":"Gespecialiseerde residenti\u00eble bouw",
    "sg:phone":"+32 9 374 31 83",
    "sg:postcode":"9880",
    "sg:province":"Oost-Vlaanderen",
    "wof:name":"Luc Sierens",
    "wof:placetype":"venue"
},
  "geometry": {"coordinates":[3.4521450996,51.0993003845],"type":"Point"}
}