{
  "type": "Feature",
  "properties": {
    "addr:full":"Zuidstraat 12 Koekelare West-Vlaanderen 8680",
    "addr:housenumber":"12",
    "addr:postcode":"8680",
    "addr:street":"Zuidstraat",
    "iso:country":"BE",
    "sg:address":"Zuidstraat 12",
    "sg:city":"Koekelare",
    "sg:classifiers":[
        {
            "category":"Building & Trades",
            "subcategory":"Construction",
            "type":"Services"
        }
    ],
    "sg:phone":"+32 51 58 09 10",
    "sg:postcode":"8680",
    "sg:province":"West-Vlaanderen",
    "sg:tags":[
        "installation",
        "-",
        "central",
        "heating"
    ],
    "wof:name":"Depreitere L",
    "wof:placetype":"venue"
},
  "geometry": {"coordinates":[2.9745910168,51.0887565613],"type":"Point"}
}