{
  "type": "Feature",
  "properties": {
    "addr:full":"Rue De Huy 129b2 Hannut Li\u00e8ge 4280",
    "addr:housenumber":"129b2",
    "addr:postcode":"4280",
    "addr:street":"Rue De Huy",
    "iso:country":"BE",
    "sg:address":"Rue De Huy 129b2",
    "sg:city":"Hannut",
    "sg:orig_category":"Boekhouders",
    "sg:phone":"+32 19 51 90 88",
    "sg:postcode":"4280",
    "sg:province":"Li\u00e8ge",
    "wof:name":"Jean-marie Conter",
    "wof:placetype":"venue"
},
  "geometry": {"coordinates":[5.0926198959,50.6642913818],"type":"Point"}
}