{
  "type": "Feature",
  "properties": {
    "iso:country":"BE",
    "sg:address":"Egenhovenstraat 93",
    "sg:city":"Bertem",
    "sg:classifiers":[
        {
            "category":"Real Estate",
            "subcategory":"Real Estate Services",
            "type":"Services"
        }
    ],
    "sg:phone":"+32 16 48 97 90",
    "sg:postcode":"3060",
    "sg:province":"Vlaams-Brabant",
    "wof:name":"Geeraerts Integrale Vastgoedservice",
    "wof:placetype":"venue"
},
  "geometry": {"coordinates":[4.6381611824,50.8626708984],"type":"Point"}
}