{
  "type": "Feature",
  "properties": {
    "addr:full":"Rue Du Pan 45 A Bernissart Hainaut 7321",
    "addr:housenumber":"45 a",
    "addr:postcode":"7321",
    "addr:street":"Rue Du Pan",
    "iso:country":"BE",
    "sg:address":"Rue Du Pan 45 A",
    "sg:city":"Bernissart",
    "sg:orig_category":"Herstellingen and onderhoud van auto's",
    "sg:phone":"+32 69 57 64 68",
    "sg:postcode":"7321",
    "sg:province":"Hainaut",
    "wof:name":"Salvatore",
    "wof:placetype":"venue"
},
  "geometry": {"coordinates":[3.6649000645,50.4902114868],"type":"Point"}
}