{
  "type": "Feature",
  "properties": {
    "iso:country":"BE",
    "sg:address":"Rue K\u00c9ramis 61",
    "sg:city":"La Louvi\u00c8re",
    "sg:classifiers":[
        {
            "category":"Wholesale",
            "subcategory":"Sporting Goods",
            "type":"Manufacturing & Wholesale Goods"
        }
    ],
    "sg:phone":"+32 64 28 59 30",
    "sg:postcode":"7100",
    "sg:province":"Hainaut",
    "sg:tags":[
        "sport-",
        "kampeermateriaal"
    ],
    "wof:name":"O.s. Sport",
    "wof:placetype":"venue"
},
  "geometry": {"coordinates":[4.1844949722,50.476474762],"type":"Point"}
}