{
  "type": "Feature",
  "properties": {
    "addr:full":"De Burletlaan 177 Edegem Antwerpen 2650",
    "addr:housenumber":"177",
    "addr:postcode":"2650",
    "addr:street":"De Burletlaan",
    "iso:country":"BE",
    "sg:address":"De Burletlaan 177",
    "sg:city":"Edegem",
    "sg:classifiers":[
        {
            "category":"Bakery",
            "type":"Food & Drink"
        }
    ],
    "sg:phone":"+32 3 448 19 06",
    "sg:postcode":"2650",
    "sg:province":"Antwerpen",
    "sg:tags":[
        "confectioner",
        "baker"
    ],
    "wof:name":"Van Den Eynde-voets Bvba",
    "wof:placetype":"venue"
},
  "geometry": {"coordinates":[4.4321269989,51.1710472107],"type":"Point"}
}