{
  "type": "Feature",
  "properties": {
    "iso:country":"BE",
    "sg:address":"Oudburgstraat 41",
    "sg:city":"Zele",
    "sg:classifiers":[
        {
            "category":"Shopping",
            "subcategory":"Clothing, Apparel, & Fashions",
            "type":"Retail Goods"
        }
    ],
    "sg:phone":"+32 52 44 98 47",
    "sg:postcode":"9240",
    "sg:province":"Oost-Vlaanderen",
    "sg:tags":[
        "lady",
        "clothing",
        "-"
    ],
    "wof:name":"Purly Trading Bvba",
    "wof:placetype":"venue"
},
  "geometry": {"coordinates":[4.0343990326,51.0662956238],"type":"Point"}
}