{
  "type": "Feature",
  "properties": {
    "iso:country":"BE",
    "sg:address":"Rue Middelbourg 1",
    "sg:city":"Watermaal-bosvoorde/watermael-",
    "sg:orig_category":"Huishoudapparaten, televisies and radio's",
    "sg:phone":"+32 2 672 27 12",
    "sg:postcode":"1170",
    "sg:province":"Bruxelles-Capitale",
    "wof:name":"Cordenier",
    "wof:placetype":"venue"
},
  "geometry": {"coordinates":[4.4174928665,50.7959938049],"type":"Point"}
}