{
  "type": "Feature",
  "properties": {
    "addr:full":"Gasmeterstraat 41 Sint-niklaas Oost-Vlaanderen 9100",
    "addr:housenumber":"41",
    "addr:postcode":"9100",
    "addr:street":"Gasmeterstraat",
    "iso:country":"BE",
    "sg:address":"Gasmeterstraat 41",
    "sg:city":"Sint-niklaas",
    "sg:classifiers":[
        {
            "category":"Health Services",
            "subcategory":"Health Practitioner",
            "type":"Services"
        }
    ],
    "sg:phone":"+32 3 776 93 23",
    "sg:postcode":"9100",
    "sg:province":"Oost-Vlaanderen",
    "sg:tags":[
        "physiotherapist"
    ],
    "wof:name":"Meireleire Wim",
    "wof:placetype":"venue"
},
  "geometry": {"coordinates":[4.1374812126,51.1703186035],"type":"Point"}
}