{
  "type": "Feature",
  "properties": {
    "addr:full":"Trichterweg 50 Zutendaal Limburg 3690",
    "addr:housenumber":"50",
    "addr:postcode":"3690",
    "addr:street":"Trichterweg",
    "iso:country":"BE",
    "sg:address":"Trichterweg 50",
    "sg:city":"Zutendaal",
    "sg:classifiers":[
        {
            "category":"Utilities",
            "subcategory":"Telephone",
            "type":"Services"
        }
    ],
    "sg:phone":"+32 89 71 48 36",
    "sg:postcode":"3690",
    "sg:province":"Limburg",
    "sg:tags":[
        "-",
        "internet"
    ],
    "wof:name":"E-com Consult Bvba",
    "wof:placetype":"venue"
},
  "geometry": {"coordinates":[5.5979738235,50.9280433655],"type":"Point"}
}