{
  "type": "Feature",
  "properties": {
    "iso:country":"BE",
    "sg:address":"Boudewijnstraat 5",
    "sg:city":"Grobbendonk",
    "sg:orig_category":"M\u00e9decins and sp\u00e9cialistes",
    "sg:phone":"+32 14 51 64 06",
    "sg:postcode":"2280",
    "sg:province":"Antwerpen",
    "wof:name":"Kristiaan Verhaegen",
    "wof:placetype":"venue"
},
  "geometry": {"coordinates":[4.7388310432,51.1897544861],"type":"Point"}
}