{
  "type": "Feature",
  "properties": {
    "iso:country":"BE",
    "sg:address":"Schrijnwerkersstraat 13",
    "sg:city":"Hasselt",
    "sg:orig_category":"Persagentschappen",
    "sg:phone":"+32 495 99 13 11",
    "sg:postcode":"3500",
    "sg:province":"Limburg",
    "wof:name":"Bart Franssen",
    "wof:placetype":"venue"
},
  "geometry": {"coordinates":[5.3362269402,50.9317855835],"type":"Point"}
}