{
  "type": "Feature",
  "properties": {
    "iso:country":"BE",
    "sg:address":"Gelmelstraat 21",
    "sg:city":"Hoogstraten",
    "sg:orig_category":"S\u00e9curit\u00e9 sociale",
    "sg:phone":"+32 3 314 51 00",
    "sg:postcode":"2320",
    "sg:province":"Antwerpen",
    "wof:name":"Onafhankelijk Ziekenfonds",
    "wof:placetype":"venue"
},
  "geometry": {"coordinates":[4.7636151314,51.4020843506],"type":"Point"}
}