{
  "type": "Feature",
  "properties": {
    "iso:country":"BE",
    "sg:address":"Zennestraat 78",
    "sg:city":"Brussel/bruxelles",
    "sg:orig_category":"Opvangtehuizen and vluchthuizen",
    "sg:phone":"+32 2 512 72 04",
    "sg:postcode":"1000",
    "sg:province":"Bruxelles-Capitale",
    "wof:name":"Maison D'accueil Source",
    "wof:placetype":"venue"
},
  "geometry": {"coordinates":[4.3399801254,50.8465156555],"type":"Point"}
}