{
  "type": "Feature",
  "properties": {
    "addr:full":"Rue Robert Delange 7 Ath Hainaut 7812",
    "addr:housenumber":"7",
    "addr:postcode":"7812",
    "addr:street":"Rue Robert Delange",
    "iso:country":"BE",
    "sg:address":"Rue Robert Delange 7",
    "sg:city":"Ath",
    "sg:orig_category":"Sportclubs",
    "sg:phone":"+32 68 84 17 52",
    "sg:postcode":"7812",
    "sg:province":"Hainaut",
    "wof:name":"Moto Club Athois",
    "wof:placetype":"venue"
},
  "geometry": {"coordinates":[3.7476489544,50.6220054626],"type":"Point"}
}