{
  "type": "Feature",
  "properties": {
    "iso:country":"BE",
    "sg:address":"Koolskampstraat 44ba",
    "sg:city":"Hooglede",
    "sg:orig_category":"Installation \u00e9lectrique r\u00e9sidentielle",
    "sg:phone":"+32 51 57 00 02",
    "sg:postcode":"8830",
    "sg:province":"West-Vlaanderen",
    "wof:name":"Elektro Ralco",
    "wof:placetype":"venue"
},
  "geometry": {"coordinates":[3.1342999935,50.9988479614],"type":"Point"}
}