{
  "type": "Feature",
  "properties": {
    "iso:country":"BE",
    "sg:address":"Constant De Rouxstraat 61",
    "sg:city":"Hasselt",
    "sg:classifiers":[
        {
            "category":"Arts & Performance",
            "subcategory":"Theater",
            "type":"Entertainment"
        }
    ],
    "sg:phone":"+32 11 72 54 70",
    "sg:postcode":"3500",
    "sg:province":"Limburg",
    "sg:tags":[
        "group",
        "theatre"
    ],
    "wof:name":"Limburgs Toneelverbond Vzw",
    "wof:placetype":"venue"
},
  "geometry": {"coordinates":[5.3242988586,50.9092636108],"type":"Point"}
}