{
  "type": "Feature",
  "properties": {
    "addr:full":"Antoon Van Dyckstraat 6 Grobbendonk Antwerpen 2280",
    "addr:housenumber":"6",
    "addr:postcode":"2280",
    "addr:street":"Antoon Van Dyckstraat",
    "iso:country":"BE",
    "sg:address":"Antoon Van Dyckstraat 6",
    "sg:city":"Grobbendonk",
    "sg:orig_category":"Electrom\u00e9nager, t\u00e9l\u00e9visions and radios",
    "sg:phone":"+32 14 51 34 55",
    "sg:postcode":"2280",
    "sg:province":"Antwerpen",
    "wof:name":"Huis Boeckx",
    "wof:placetype":"venue"
},
  "geometry": {"coordinates":[4.7433261871,51.1903419495],"type":"Point"}
}