{
  "type": "Feature",
  "properties": {
    "iso:country":"BE",
    "sg:address":"Hoog-brabantlaan 7",
    "sg:city":"Brugge",
    "sg:orig_category":"Quincailleries. Bois Gr",
    "sg:phone":"+32 50 38 33 48",
    "sg:postcode":"8200",
    "sg:province":"West-Vlaanderen",
    "wof:name":"Eric Sybout",
    "wof:placetype":"venue"
},
  "geometry": {"coordinates":[3.2056028843,51.1997146606],"type":"Point"}
}