{
  "type": "Feature",
  "properties": {
    "addr:full":"Rue L'apleit 9 Huy Li\u00e8ge 4500",
    "addr:housenumber":"9",
    "addr:postcode":"4500",
    "addr:street":"Rue L'Apleit",
    "iso:country":"BE",
    "sg:address":"Rue L'apleit 9",
    "sg:city":"Huy",
    "sg:classifiers":[
        {
            "category":"Home & Garden",
            "subcategory":"Furniture",
            "type":"Retail Goods"
        }
    ],
    "sg:phone":"+32 85 25 53 93",
    "sg:postcode":"4500",
    "sg:province":"Li\u00e8ge",
    "sg:tags":[
        "-"
    ],
    "wof:name":"Buro Light",
    "wof:placetype":"venue"
},
  "geometry": {"coordinates":[5.2400631905,50.5196418762],"type":"Point"}
}