{
  "type": "Feature",
  "properties": {
    "addr:full":"Ravensteinstraat 60bus 18 Brussel Bruxelles-Capitale 1000",
    "addr:housenumber":"18",
    "addr:postcode":"1000",
    "addr:street":"Ravensteinstraat;Brussel",
    "iso:country":"BE",
    "sg:address":"Ravensteinstraat 60bus 18",
    "sg:city":"Brussel",
    "sg:classifiers":[
        {
            "category":"Railroad",
            "type":"Transportation"
        }
    ],
    "sg:phone":"+32 2 548 53 11",
    "sg:postcode":"1000",
    "sg:province":"Bruxelles-Capitale",
    "sg:tags":[
        "railway",
        "planning",
        "technology"
    ],
    "wof:name":"Transurb Technirail Nv",
    "wof:placetype":"venue"
},
  "geometry": {"coordinates":[4.3590707779,50.8455238342],"type":"Point"}
}