{
  "type": "Feature",
  "properties": {
    "iso:country":"BE",
    "sg:address":"Meerbos 4",
    "sg:city":"Wichelen",
    "sg:classifiers":[
        {
            "category":"Home & Garden",
            "subcategory":"Building Materials",
            "type":"Retail Goods"
        }
    ],
    "sg:phone":"+32 52 42 54 45",
    "sg:postcode":"9260",
    "sg:province":"Oost-Vlaanderen",
    "sg:tags":[
        "aluminium",
        "construction",
        "-"
    ],
    "wof:name":"Radeca Nv",
    "wof:placetype":"venue"
},
  "geometry": {"coordinates":[3.9576430321,51.0078277588],"type":"Point"}
}