{
  "type": "Feature",
  "properties": {
    "iso:country":"BE",
    "sg:address":"Rue Du Saule 30",
    "sg:city":"Bruxelles (jette)",
    "sg:classifiers":[
        {
            "category":"Professional",
            "subcategory":"Testing Lab",
            "type":"Services"
        }
    ],
    "sg:phone":"+32 2 420 02 01",
    "sg:postcode":"1090",
    "sg:province":"Bruxelles-Capitale",
    "sg:tags":[
        "laboratory",
        "-",
        "machines",
        "apparatus",
        "supply"
    ],
    "wof:name":"Labas Bvba",
    "wof:placetype":"venue"
},
  "geometry": {"coordinates":[4.3200922012,50.8782463074],"type":"Point"}
}