{
  "type": "Feature",
  "properties": {
    "iso:country":"BE",
    "sg:address":"Chauss\u00e9e De Nivelles 4",
    "sg:city":"Gembloux-sur-orneau (mazy)",
    "sg:classifiers":[
        {
            "category":"Professional",
            "subcategory":"Credit Reporting & Collection",
            "type":"Services"
        }
    ],
    "sg:phone":"+32 81 63 35 50",
    "sg:postcode":"5032",
    "sg:province":"Namur",
    "sg:tags":[
        "bailiff"
    ],
    "wof:name":"Raty A",
    "wof:placetype":"venue"
},
  "geometry": {"coordinates":[4.6774249077,50.5116271973],"type":"Point"}
}