{
  "type": "Feature",
  "properties": {
    "iso:country":"BE",
    "sg:address":"Rue De Belle T\u00eate 36",
    "sg:city":"Ecaussinnes (ecaussinnes-d'enghien)",
    "sg:classifiers":[
        {
            "category":"Social Services",
            "subcategory":"Child Care",
            "type":"Services"
        }
    ],
    "sg:phone":"+32 67 44 36 44",
    "sg:postcode":"7190",
    "sg:province":"Hainaut",
    "sg:tags":[
        "baby",
        "nursery",
        "day",
        "sitting"
    ],
    "wof:name":"Marguerite (la)",
    "wof:placetype":"venue"
},
  "geometry": {"coordinates":[4.1512560844,50.5661964417],"type":"Point"}
}