{
  "type": "Feature",
  "properties": {
    "iso:country":"BE",
    "sg:address":"Rue De La Verrerie 4",
    "sg:city":"Sivry-rance",
    "sg:orig_category":"Slagers",
    "sg:phone":"+32 60 41 21 08",
    "sg:postcode":"6470",
    "sg:province":"Hainaut",
    "wof:name":"Chez Manu",
    "wof:placetype":"venue"
},
  "geometry": {"coordinates":[4.2668590546,50.1448707581],"type":"Point"}
}