{
  "type": "Feature",
  "properties": {
    "addr:full":"Avenue Air Marshal Coningham 1 Box 17 Bruxelles Bruxelles-Capitale 1000",
    "addr:housenumber":"1 box 17",
    "addr:postcode":"1000",
    "addr:street":"Avenue Air Marshal Coningham",
    "iso:country":"BE",
    "sg:address":"Avenue Air Marshal Coningham 1 Box 17",
    "sg:city":"Bruxelles",
    "sg:classifiers":[
        {
            "category":"Professional",
            "subcategory":"Lawyer & Legal Services",
            "type":"Services"
        }
    ],
    "sg:phone":"+32 2 640 18 30",
    "sg:postcode":"1000",
    "sg:province":"Bruxelles-Capitale",
    "wof:name":"Belva Genevi\u00e8ve",
    "wof:placetype":"venue"
},
  "geometry": {"coordinates":[4.3864917755,50.8056945801],"type":"Point"}
}