{
  "type": "Feature",
  "properties": {
    "iso:country":"BE",
    "sg:address":"Dorpsstraat 43",
    "sg:city":"Diepenbeek",
    "sg:orig_category":"Slagers",
    "sg:phone":"+32 11 32 32 23",
    "sg:postcode":"3590",
    "sg:province":"Limburg",
    "wof:name":"Romain Vanaken",
    "wof:placetype":"venue"
},
  "geometry": {"coordinates":[5.4187669754,50.9091491699],"type":"Point"}
}