{
  "type": "Feature",
  "properties": {
    "iso:country":"BE",
    "sg:address":"Cielle 75",
    "sg:city":"La Roche-en-ardenne",
    "sg:classifiers":[
        {
            "category":"Cafe",
            "type":"Food & Drink"
        }
    ],
    "sg:phone":"+32 84 41 17 22",
    "sg:postcode":"6980",
    "sg:province":"Luxembourg",
    "sg:tags":[
        "caf\u00e9s"
    ],
    "wof:name":"Bastin",
    "wof:placetype":"venue"
},
  "geometry": {"coordinates":[5.5568399429,50.1901550293],"type":"Point"}
}