{
  "type": "Feature",
  "properties": {
    "addr:full":"Havermarkt 33 Hasselt Limburg 3500",
    "addr:housenumber":"33",
    "addr:postcode":"3500",
    "addr:street":"Havermarkt",
    "iso:country":"BE",
    "sg:address":"Havermarkt 33",
    "sg:city":"Hasselt",
    "sg:orig_category":"Diverse kredietdiensten",
    "sg:postcode":"3500",
    "sg:province":"Limburg",
    "wof:name":"Postomat Hasselt",
    "wof:placetype":"venue"
},
  "geometry": {"coordinates":[5.3348431587,50.9294052124],"type":"Point"}
}