{
  "type": "Feature",
  "properties": {
    "iso:country":"BE",
    "sg:address":"Herkkantstraat 27",
    "sg:city":"Hasselt",
    "sg:orig_category":"Woningbouw",
    "sg:phone":"+32 11 31 45 01",
    "sg:postcode":"3512",
    "sg:province":"Limburg",
    "wof:name":"Romain Dethier",
    "wof:placetype":"venue"
},
  "geometry": {"coordinates":[5.2426218987,50.9200553894],"type":"Point"}
}