{
  "type": "Feature",
  "properties": {
    "iso:country":"BE",
    "sg:address":"Vakenstraat 92",
    "sg:city":"Rotselaar",
    "sg:orig_category":"Sportclubs Sportterreinen and installaties behalve sportcentra",
    "sg:phone":"+32 16 58 20 32",
    "sg:postcode":"3110",
    "sg:province":"Vlaams-Brabant",
    "wof:name":"F.c. Werchter",
    "wof:placetype":"venue"
},
  "geometry": {"coordinates":[4.7313728333,50.9640846252],"type":"Point"}
}