{
  "type": "Feature",
  "properties": {
    "iso:country":"BE",
    "sg:address":"Rue Albert Mille 19",
    "sg:city":"Pecq",
    "sg:classifiers":[
        {
            "category":"Building & Trades",
            "subcategory":"Construction",
            "type":"Services"
        }
    ],
    "sg:phone":"+32 69 55 34 37",
    "sg:postcode":"7740",
    "sg:province":"Hainaut",
    "sg:tags":[
        "roofing",
        "material",
        "-"
    ],
    "wof:name":"S T M C",
    "wof:placetype":"venue"
},
  "geometry": {"coordinates":[3.3407990932,50.6827812195],"type":"Point"}
}