{
  "type": "Feature",
  "properties": {
    "addr:full":"Ommegangsdreef 63 Waasmunster Oost-Vlaanderen 9250",
    "addr:housenumber":"63",
    "addr:postcode":"9250",
    "addr:street":"Ommegangsdreef",
    "iso:country":"BE",
    "sg:address":"Ommegangsdreef 63",
    "sg:city":"Waasmunster",
    "sg:orig_category":"Vakantiedorpen",
    "sg:phone":"+32 52 46 00 73",
    "sg:postcode":"9250",
    "sg:province":"Oost-Vlaanderen",
    "wof:name":"Heidepark",
    "wof:placetype":"venue"
},
  "geometry": {"coordinates":[4.0997052193,51.1223335266],"type":"Point"}
}