{
  "type": "Feature",
  "properties": {
    "iso:country":"BE",
    "sg:address":"Oude Markt 20",
    "sg:city":"Leuven",
    "sg:orig_category":"Caf\u00e9s Sportclubs",
    "sg:phone":"+32 16 20 06 22",
    "sg:postcode":"3000",
    "sg:province":"Vlaams-Brabant",
    "wof:name":"D.c. De Colff",
    "wof:placetype":"venue"
},
  "geometry": {"coordinates":[4.7443299294,50.8633918762],"type":"Point"}
}