{
  "type": "Feature",
  "properties": {
    "iso:country":"BE",
    "sg:address":"Groenstraat 5b",
    "sg:city":"Sint-pieters-leeuw",
    "sg:orig_category":"Groenten and fruit Gh",
    "sg:phone":"+32 2 569 39 75",
    "sg:postcode":"1602",
    "sg:province":"Vlaams-Brabant",
    "wof:name":"Berckmans-vranckx",
    "wof:placetype":"venue"
},
  "geometry": {"coordinates":[4.2469511032,50.8121910095],"type":"Point"}
}