{
  "type": "Feature",
  "properties": {
    "iso:country":"BE",
    "sg:address":"Hoogbrugstraat 15",
    "sg:city":"Bilzen",
    "sg:classifiers":[
        {
            "category":"Retail",
            "subcategory":"Auto Repair",
            "type":"Services"
        }
    ],
    "sg:phone":"+32 89 41 21 61",
    "sg:postcode":"3740",
    "sg:province":"Limburg",
    "sg:tags":[
        "automobile-body"
    ],
    "wof:name":"Brepoels Carrosseriebedrijf Nv",
    "wof:placetype":"venue"
},
  "geometry": {"coordinates":[5.5037641525,50.8865089417],"type":"Point"}
}