{
  "type": "Feature",
  "properties": {
    "iso:country":"BE",
    "sg:address":"Rue Des Champs Elys\u00c9es 7",
    "sg:city":"Elsene/ixelles",
    "sg:orig_category":"Eclairage et \u00e9quipements du foyer",
    "sg:phone":"+32 2 513 89 28",
    "sg:postcode":"1050",
    "sg:province":"Bruxelles-Capitale",
    "wof:name":"A.b.c.z.",
    "wof:placetype":"venue"
},
  "geometry": {"coordinates":[4.3656640053,50.8320198059],"type":"Point"}
}