{
  "type": "Feature",
  "properties": {
    "addr:full":"Rue Grande 120 Dinant Namur 5500",
    "addr:housenumber":"120",
    "addr:postcode":"5500",
    "addr:street":"Rue Grande",
    "iso:country":"BE",
    "sg:address":"Rue Grande 120",
    "sg:city":"Dinant",
    "sg:classifiers":[
        {
            "category":"Shopping",
            "subcategory":"Clothing, Apparel, & Fashions",
            "type":"Retail Goods"
        }
    ],
    "sg:phone":"+32 82 22 30 11",
    "sg:postcode":"5500",
    "sg:province":"Namur",
    "sg:tags":[
        "boutique"
    ],
    "wof:name":"Avalanche",
    "wof:placetype":"venue"
},
  "geometry": {"coordinates":[4.9130182266,50.259563446],"type":"Point"}
}