{
  "type": "Feature",
  "properties": {
    "addr:full":"Rue Du Gh\u00cate 42 Court-saint-etienne Brabant Wallon 1490",
    "addr:housenumber":"42;1490",
    "addr:street":"Rue Du Ghe\u0302Te",
    "iso:country":"BE",
    "sg:address":"Rue Du Gh\u00cate 42",
    "sg:city":"Court-saint-etienne",
    "sg:orig_category":"Plaatsen van vloer- and muurbekleding Schilders Verlichting and huishoudartikelen",
    "sg:phone":"+32 10 61 13 44",
    "sg:postcode":"1490",
    "sg:province":"Brabant Wallon",
    "wof:name":"Jacques Delangen",
    "wof:placetype":"venue"
},
  "geometry": {"coordinates":[4.5308709145,50.6034355164],"type":"Point"}
}