{
  "type": "Feature",
  "properties": {
    "iso:country":"BE",
    "sg:address":"Rue Du Roptai 4",
    "sg:city":"Rochefort",
    "sg:orig_category":"Woningbouw",
    "sg:phone":"+32 84 38 81 11",
    "sg:postcode":"5580",
    "sg:province":"Namur",
    "wof:name":"Henri Motet",
    "wof:placetype":"venue"
},
  "geometry": {"coordinates":[5.2231431007,50.1608505249],"type":"Point"}
}