{
  "type": "Feature",
  "properties": {
    "addr:full":"Douglaslaan 12 Essen Antwerpen 2910",
    "addr:housenumber":"12",
    "addr:postcode":"2910",
    "addr:street":"Douglaslaan",
    "iso:country":"BE",
    "sg:address":"Douglaslaan 12",
    "sg:city":"Essen",
    "sg:classifiers":[
        {
            "category":"Professional",
            "subcategory":"Management & Consulting",
            "type":"Services"
        }
    ],
    "sg:phone":"+32 3 667 63 83",
    "sg:postcode":"2910",
    "sg:province":"Antwerpen",
    "sg:tags":[
        "consultant"
    ],
    "wof:name":"Corfin Bvba",
    "wof:placetype":"venue"
},
  "geometry": {"coordinates":[4.5285611153,51.4621505737],"type":"Point"}
}