{
  "type": "Feature",
  "properties": {
    "addr:full":"Merestraat 33 Aalst Oost-Vlaanderen 9300",
    "addr:housenumber":"33",
    "addr:postcode":"9300",
    "addr:street":"Merestraat",
    "iso:country":"BE",
    "sg:address":"Merestraat 33",
    "sg:city":"Aalst",
    "sg:orig_category":"Artiesten and kunstenaars",
    "sg:phone":"+32 53 77 40 57",
    "sg:postcode":"9300",
    "sg:province":"Oost-Vlaanderen",
    "wof:name":"Fran\u00c7ois Van De Velde",
    "wof:placetype":"venue"
},
  "geometry": {"coordinates":[4.0230350494,50.9375610352],"type":"Point"}
}