{
  "type": "Feature",
  "properties": {
    "iso:country":"BE",
    "sg:address":"Place Maurice Servais 1",
    "sg:city":"Namur",
    "sg:orig_category":"Brood, gebak and snoepgoed",
    "sg:phone":"+32 81 22 30 69",
    "sg:postcode":"5060",
    "sg:province":"Namur",
    "wof:name":"P\u00c2tisserie Nemann",
    "wof:placetype":"venue"
},
  "geometry": {"coordinates":[4.8652281761,50.462474823],"type":"Point"}
}