{
  "type": "Feature",
  "properties": {
    "iso:country":"BE",
    "sg:address":"Stationsstraat 7",
    "sg:city":"Temse",
    "sg:orig_category":"Paramedische behandelingen",
    "sg:phone":"+32 3 771 24 50",
    "sg:postcode":"9140",
    "sg:province":"Oost-Vlaanderen",
    "wof:name":"Martine Van De Velde",
    "wof:placetype":"venue"
},
  "geometry": {"coordinates":[4.2210998535,51.125541687],"type":"Point"}
}