{
  "type": "Feature",
  "properties": {
    "addr:full":"Val De La Berwinne 6c Dalhem (mortroux) Li\u00e8ge 4607",
    "addr:housenumber":"6c",
    "addr:postcode":"4607",
    "addr:street":"Val De La Berwinne",
    "iso:country":"BE",
    "sg:address":"Val De La Berwinne 6c",
    "sg:city":"Dalhem (mortroux)",
    "sg:classifiers":[
        {
            "category":"Arts & Performance",
            "subcategory":"Symphony",
            "type":"Entertainment"
        }
    ],
    "sg:phone":"+32 4 376 73 37",
    "sg:postcode":"4607",
    "sg:province":"Li\u00e8ge",
    "sg:tags":[
        "orchestra"
    ],
    "wof:name":"Lina",
    "wof:placetype":"venue"
},
  "geometry": {"coordinates":[5.7471299171,50.7169952393],"type":"Point"}
}