{
  "type": "Feature",
  "properties": {
    "iso:country":"BE",
    "sg:address":"Antwerpsesteenweg 10",
    "sg:city":"Malle (oostmalle)",
    "sg:classifiers":[
        {
            "category":"Retail",
            "subcategory":"Auto Repair",
            "type":"Services"
        }
    ],
    "sg:phone":"+32 3 309 40 21",
    "sg:postcode":"2390",
    "sg:province":"Antwerpen",
    "sg:tags":[
        "automobile",
        "servic",
        "electrical",
        "-"
    ],
    "wof:name":"Vanaerschot Guy Nv",
    "wof:placetype":"venue"
},
  "geometry": {"coordinates":[4.7321147919,51.3013648987],"type":"Point"}
}