{
  "type": "Feature",
  "properties": {
    "iso:country":"BE",
    "sg:address":"Rue De L\u00b4aisne 28 Bis",
    "sg:city":"Erezee",
    "sg:orig_category":"Herstellingen and onderhoud van auto's Voertuigen",
    "sg:phone":"+32 86 49 95 43",
    "sg:postcode":"6997",
    "sg:province":"Luxembourg",
    "wof:name":"Garage Delvaux",
    "wof:placetype":"venue"
},
  "geometry": {"coordinates":[5.5681190491,50.321346283],"type":"Point"}
}