{
  "type": "Feature",
  "properties": {
    "addr:full":"A. Van Bockxstaelestraat 26 Gent Oost-Vlaanderen 9050",
    "addr:housenumber":"26",
    "addr:postcode":"9050",
    "addr:street":"A. Van Bockxstaelestraat;Oost-Vlaanderen",
    "iso:country":"BE",
    "sg:address":"A. Van Bockxstaelestraat 26",
    "sg:city":"Gent",
    "sg:orig_category":"Alternatieve geneeskunde",
    "sg:phone":"+32 9 230 47 69",
    "sg:postcode":"9050",
    "sg:province":"Oost-Vlaanderen",
    "wof:name":"Marianne Duquet - Baf",
    "wof:placetype":"venue"
},
  "geometry": {"coordinates":[3.7589480877,51.0448532104],"type":"Point"}
}