{
  "type": "Feature",
  "properties": {
    "iso:country":"BE",
    "sg:address":"Winterslagstraat 5",
    "sg:city":"Genk",
    "sg:orig_category":"Banken and kredietinstellingen",
    "sg:phone":"+32 89 35 07 69",
    "sg:postcode":"3600",
    "sg:province":"Limburg",
    "wof:name":"Dexia",
    "wof:placetype":"venue"
},
  "geometry": {"coordinates":[5.4983139038,50.963848114],"type":"Point"}
}