{
  "type": "Feature",
  "properties": {
    "addr:full":"Torhoutsesteenweg 639 Oostende West-Vlaanderen 8400",
    "addr:housenumber":"639",
    "addr:postcode":"8400",
    "addr:street":"Torhoutsesteenweg",
    "iso:country":"BE",
    "sg:address":"Torhoutsesteenweg 639",
    "sg:city":"Oostende",
    "sg:orig_category":"Herstellingen and onderhoud van auto's Huishoudapparaten, televisies and radio's Onderdelen and acce",
    "sg:phone":"+32 59 50 08 16",
    "sg:postcode":"8400",
    "sg:province":"West-Vlaanderen",
    "wof:name":"Coppin A",
    "wof:placetype":"venue"
},
  "geometry": {"coordinates":[2.9048330784,51.2084617615],"type":"Point"}
}