{
  "type": "Feature",
  "properties": {
    "addr:full":"Rue Comte De Flandre 48 Molenbeek-saint-jean Bruxelles-Capitale 1080",
    "addr:housenumber":"48",
    "addr:postcode":"1080",
    "addr:street":"Rue Comte De Flandre",
    "iso:country":"BE",
    "sg:address":"Rue Comte De Flandre 48",
    "sg:city":"Molenbeek-saint-jean",
    "sg:orig_category":"Juwelen and horloges",
    "sg:phone":"+32 2 414 24 63",
    "sg:postcode":"1080",
    "sg:province":"Bruxelles-Capitale",
    "wof:name":"Bijouterie Ahmed",
    "wof:placetype":"venue"
},
  "geometry": {"coordinates":[4.3393177986,50.8561515808],"type":"Point"}
}