{
  "type": "Feature",
  "properties": {
    "addr:full":"Wijngaardveld 14 Aalst Oost-Vlaanderen 9300",
    "addr:housenumber":"14",
    "addr:postcode":"9300",
    "addr:street":"Wijngaardveld",
    "iso:country":"BE",
    "sg:address":"Wijngaardveld 14",
    "sg:city":"Aalst",
    "sg:orig_category":"Non-Classified Establishments",
    "sg:phone":"+32 53 77 77 55",
    "sg:postcode":"9300",
    "sg:province":"Oost-Vlaanderen",
    "wof:name":"Van Haute Nv",
    "wof:placetype":"venue"
},
  "geometry": {"coordinates":[4.0615148544,50.9397926331],"type":"Point"}
}