{
  "type": "Feature",
  "properties": {
    "addr:full":"Bld De Smet De Naeyer 216 Jette/jette Bruxelles-Capitale 1090",
    "addr:housenumber":"216",
    "addr:postcode":"1090",
    "addr:street":"Bld De Smet De Naeyer",
    "iso:country":"BE",
    "sg:address":"Bld De Smet De Naeyer 216",
    "sg:city":"Jette/jette",
    "sg:orig_category":"Agences immobili\u00e8res",
    "sg:phone":"+32 2 426 25 43",
    "sg:postcode":"1090",
    "sg:province":"Bruxelles-Capitale",
    "wof:name":"Pim-immo",
    "wof:placetype":"venue"
},
  "geometry": {"coordinates":[4.3311061859,50.8764572144],"type":"Point"}
}