{
  "type": "Feature",
  "properties": {
    "iso:country":"BE",
    "sg:address":"Steenhuffelstraat 34b2",
    "sg:city":"Londerzeel",
    "sg:classifiers":[
        {
            "category":"Insurance",
            "subcategory":"Insurance Agent",
            "type":"Services"
        }
    ],
    "sg:phone":"+32 52 34 06 04",
    "sg:postcode":"1840",
    "sg:province":"Vlaams-Brabant",
    "sg:tags":[
        "verzekeringsmakelaars",
        "expert"
    ],
    "wof:name":"Bureau Segers-de Witte",
    "wof:placetype":"venue"
},
  "geometry": {"coordinates":[4.2459950447,51.0170478821],"type":"Point"}
}