{
  "type": "Feature",
  "properties": {
    "addr:full":"Rue Haute 5 Sombreffe Namur 5140",
    "addr:housenumber":"5",
    "addr:postcode":"5140",
    "addr:street":"Rue Haute",
    "iso:country":"BE",
    "sg:address":"Rue Haute 5",
    "sg:city":"Sombreffe",
    "sg:orig_category":"Salles de spectacles",
    "sg:phone":"+32 71 88 78 20",
    "sg:postcode":"5140",
    "sg:province":"Namur",
    "wof:name":"Samaravia",
    "wof:placetype":"venue"
},
  "geometry": {"coordinates":[4.575056076,50.5110740662],"type":"Point"}
}