{
  "type": "Feature",
  "properties": {
    "iso:country":"BE",
    "sg:address":"Smeyskensstraat 13",
    "sg:city":"Dendermonde (baasrode)",
    "sg:classifiers":[
        {
            "category":"Manufacturing",
            "subcategory":"Glass & Minerals",
            "type":"Manufacturing & Wholesale Goods"
        }
    ],
    "sg:phone":"+32 52 33 03 48",
    "sg:postcode":"9200",
    "sg:province":"Oost-Vlaanderen",
    "sg:tags":[
        "blower"
    ],
    "wof:name":"Glamart",
    "wof:placetype":"venue"
},
  "geometry": {"coordinates":[4.0983099937,51.0315208435],"type":"Point"}
}