{
  "type": "Feature",
  "properties": {
    "addr:full":"Rue De Herm\u00e9e 225 - P.i.hauts-sarts Herstal Li\u00e8ge 4040",
    "addr:housenumber":"225",
    "addr:postcode":"4040",
    "addr:street":"Rue De Herme\u0301E",
    "iso:country":"BE",
    "sg:address":"Rue De Herm\u00e9e 225 - P.i.hauts-sarts",
    "sg:city":"Herstal",
    "sg:classifiers":[
        {
            "category":"Manufacturing",
            "subcategory":"Chemicals & Compounds",
            "type":"Manufacturing & Wholesale Goods"
        }
    ],
    "sg:phone":"+32 3 640 93 02",
    "sg:postcode":"4040",
    "sg:province":"Li\u00e8ge",
    "sg:tags":[
        "cosmetic"
    ],
    "wof:name":"Manuchar Nv",
    "wof:placetype":"venue"
},
  "geometry": {"coordinates":[4.4287090302,51.2472076416],"type":"Point"}
}