{
  "type": "Feature",
  "properties": {
    "iso:country":"BE",
    "sg:address":"Schouteerpark 4",
    "sg:city":"Destelbergen",
    "sg:orig_category":"Landmeters",
    "sg:phone":"+32 9 228 39 83",
    "sg:postcode":"9070",
    "sg:province":"Oost-Vlaanderen",
    "wof:name":"Eline Revis",
    "wof:placetype":"venue"
},
  "geometry": {"coordinates":[3.7744429111,51.0568161011],"type":"Point"}
}