{
  "type": "Feature",
  "properties": {
    "iso:country":"BE",
    "sg:address":"Krelstraat 12",
    "sg:city":"Genk",
    "sg:classifiers":[
        {
            "category":"Home & Garden",
            "subcategory":"Garden Supply",
            "type":"Retail Goods"
        }
    ],
    "sg:phone":"+32 89 61 23 91",
    "sg:postcode":"3600",
    "sg:province":"Limburg",
    "wof:name":"Bollen F",
    "wof:placetype":"venue"
},
  "geometry": {"coordinates":[5.5186219215,50.937122345],"type":"Point"}
}