{
  "type": "Feature",
  "properties": {
    "addr:full":"Oude Zandstraat 12 Beveren Oost-Vlaanderen 9120",
    "addr:housenumber":"12",
    "addr:postcode":"9120",
    "addr:street":"Oude Zandstraat",
    "iso:country":"BE",
    "sg:address":"Oude Zandstraat 12",
    "sg:city":"Beveren",
    "sg:orig_category":"Tijdelijke werkgelegenheid and uitzendkantoren",
    "sg:phone":"+32 3 750 95 60",
    "sg:postcode":"9120",
    "sg:province":"Oost-Vlaanderen",
    "wof:name":"Creyf\u00b4s Interim",
    "wof:placetype":"venue"
},
  "geometry": {"coordinates":[4.2544560432,51.2124633789],"type":"Point"}
}