{
  "type": "Feature",
  "properties": {
    "addr:full":"Rue Adolphe Rectem 55 Courcelles (trazegnies) Hainaut 6183",
    "addr:housenumber":"55",
    "addr:postcode":"6183",
    "addr:street":"Rue Adolphe Rectem",
    "iso:country":"BE",
    "sg:address":"Rue Adolphe Rectem 55",
    "sg:city":"Courcelles (trazegnies)",
    "sg:classifiers":[
        {
            "category":"Professional",
            "subcategory":"Testing Lab",
            "type":"Services"
        }
    ],
    "sg:phone":"+32 71 45 10 73",
    "sg:postcode":"6183",
    "sg:province":"Hainaut",
    "sg:tags":[
        "chemist"
    ],
    "wof:name":"Willame M",
    "wof:placetype":"venue"
},
  "geometry": {"coordinates":[4.3319401741,50.465423584],"type":"Point"}
}