{
  "type": "Feature",
  "properties": {
    "addr:full":"Cauwerburg 113 Temse Oost-Vlaanderen 9140",
    "addr:housenumber":"113",
    "addr:postcode":"9140",
    "iso:country":"BE",
    "sg:address":"Cauwerburg 113",
    "sg:city":"Temse",
    "sg:orig_category":"Diverse bedrijfsbeheeradviesbureaus",
    "sg:phone":"+32 3 771 42 09",
    "sg:postcode":"9140",
    "sg:province":"Oost-Vlaanderen",
    "wof:name":"Cauwerburg",
    "wof:placetype":"venue"
},
  "geometry": {"coordinates":[4.1953868866,51.1202278137],"type":"Point"}
}