{
  "type": "Feature",
  "properties": {
    "addr:full":"Hansbekedorp 35 Nevele Oost-Vlaanderen 9850",
    "addr:housenumber":"35",
    "addr:postcode":"9850",
    "addr:street":"Hansbekedorp",
    "iso:country":"BE",
    "sg:address":"Hansbekedorp 35",
    "sg:city":"Nevele",
    "sg:orig_category":"Enseignement maternel and primaire",
    "sg:phone":"+32 9 371 73 64",
    "sg:postcode":"9850",
    "sg:province":"Oost-Vlaanderen",
    "wof:name":"Vrije Lagere School",
    "wof:placetype":"venue"
},
  "geometry": {"coordinates":[3.535132885,51.0762138367],"type":"Point"}
}