{
  "type": "Feature",
  "properties": {
    "iso:country":"BE",
    "sg:address":"Stationstraat",
    "sg:city":"Ham",
    "sg:orig_category":"Gestion des d\u00e9charges and sites d\u00e9finitifs de stockage",
    "sg:phone":"+32 11 39 14 32",
    "sg:postcode":"3945",
    "sg:province":"Limburg",
    "wof:name":"Containerpark Ham",
    "wof:placetype":"venue"
},
  "geometry": {"coordinates":[5.1776199341,51.1046104431],"type":"Point"}
}