{
  "type": "Feature",
  "properties": {
    "addr:full":"Olsensesteenweg 41a Kruishoutem Oost-Vlaanderen 9770",
    "addr:housenumber":"41a",
    "addr:postcode":"9770",
    "addr:street":"Olsensesteenweg",
    "iso:country":"BE",
    "sg:address":"Olsensesteenweg 41a",
    "sg:city":"Kruishoutem",
    "sg:classifiers":[
        {
            "category":"Wholesale",
            "subcategory":"Meat",
            "type":"Manufacturing & Wholesale Goods"
        }
    ],
    "sg:phone":"+32 9 383 00 84",
    "sg:postcode":"9770",
    "sg:province":"Oost-Vlaanderen",
    "sg:tags":[
        "whol",
        "-"
    ],
    "wof:name":"Meat Service Nv-sa",
    "wof:placetype":"venue"
},
  "geometry": {"coordinates":[3.5150868893,50.9073524475],"type":"Point"}
}