{
  "type": "Feature",
  "properties": {
    "addr:full":"Rue Des Guillemins 37 Li\u00c8ge Li\u00e8ge 4000",
    "addr:housenumber":"37",
    "addr:postcode":"4000",
    "addr:street":"Rue Des Guillemins",
    "iso:country":"BE",
    "sg:address":"Rue Des Guillemins 37",
    "sg:city":"Li\u00c8ge",
    "sg:orig_category":"Beautyfarms, relaxatie and lichamelijk welzijn",
    "sg:phone":"+32 4 229 33 66",
    "sg:postcode":"4000",
    "sg:province":"Li\u00e8ge",
    "wof:name":"Sun 2000",
    "wof:placetype":"venue"
},
  "geometry": {"coordinates":[5.5677452087,50.6285514832],"type":"Point"}
}