{
  "type": "Feature",
  "properties": {
    "addr:full":"Place Jean Jaur\u00c8s 6 Herstal Li\u00e8ge 4040",
    "addr:housenumber":"6",
    "addr:postcode":"4040",
    "addr:street":"Place Jean Jaure\u0300S",
    "iso:country":"BE",
    "sg:address":"Place Jean Jaur\u00c8s 6",
    "sg:city":"Herstal",
    "sg:orig_category":"Diverse kredietdiensten",
    "sg:postcode":"4040",
    "sg:province":"Li\u00e8ge",
    "wof:name":"Bancontact-mister Cash",
    "wof:placetype":"venue"
},
  "geometry": {"coordinates":[5.6301851273,50.6654167175],"type":"Point"}
}