{
  "type": "Feature",
  "properties": {
    "iso:country":"BE",
    "sg:address":"Markt 16",
    "sg:city":"Bree",
    "sg:classifiers":[
        {
            "category":"Shopping",
            "subcategory":"Clothing, Apparel, & Fashions",
            "type":"Retail Goods"
        }
    ],
    "sg:phone":"+32 89 47 28 87",
    "sg:postcode":"3960",
    "sg:province":"Limburg",
    "sg:tags":[
        "boutique"
    ],
    "wof:name":"Chinook",
    "wof:placetype":"venue"
},
  "geometry": {"coordinates":[5.5963158607,51.141456604],"type":"Point"}
}