{
  "type": "Feature",
  "properties": {
    "iso:country":"BE",
    "sg:address":"Boulevard De Smet De Naeyer 277 Box 6",
    "sg:city":"Bruxelles (jette)",
    "sg:classifiers":[
        {
            "category":"Professional",
            "subcategory":"Lawyer & Legal Services",
            "type":"Services"
        }
    ],
    "sg:phone":"+32 2 420 91 86",
    "sg:postcode":"1090",
    "sg:province":"Bruxelles-Capitale",
    "wof:name":"Van Den Nest H",
    "wof:placetype":"venue"
},
  "geometry": {"coordinates":[4.3324780464,50.878200531],"type":"Point"}
}