{
  "type": "Feature",
  "properties": {
    "addr:full":"Mussestraat 6 Oosterzele Oost-Vlaanderen 9860",
    "addr:housenumber":"6",
    "addr:postcode":"9860",
    "addr:street":"Mussestraat;Oost-Vlaanderen",
    "iso:country":"BE",
    "sg:address":"Mussestraat 6",
    "sg:city":"Oosterzele",
    "sg:orig_category":"Rundveehouders",
    "sg:phone":"+32 9 362 89 59",
    "sg:postcode":"9860",
    "sg:province":"Oost-Vlaanderen",
    "wof:name":"Marc Crommelinck",
    "wof:placetype":"venue"
},
  "geometry": {"coordinates":[3.8095860481,50.9639968872],"type":"Point"}
}