{
  "type": "Feature",
  "properties": {
    "addr:full":"Opperstraat 71 Liedekerke Vlaams-Brabant 1770",
    "addr:housenumber":"71",
    "addr:postcode":"1770",
    "addr:street":"Opperstraat;Vlaams-Brabant",
    "iso:country":"BE",
    "sg:address":"Opperstraat 71",
    "sg:city":"Liedekerke",
    "sg:classifiers":[
        {
            "category":"Fast Food",
            "type":"Food & Drink"
        }
    ],
    "sg:phone":"+32 53 66 00 09",
    "sg:postcode":"1770",
    "sg:province":"Vlaams-Brabant",
    "sg:tags":[
        "\u00c0",
        "emporter",
        "restaurants"
    ],
    "wof:name":"Jade Garden",
    "wof:placetype":"venue"
},
  "geometry": {"coordinates":[4.0872659683,50.86926651],"type":"Point"}
}