{
  "type": "Feature",
  "properties": {
    "addr:full":"Rue Louis Burteau 48 Gembloux-sur-orneau (bothey) Namur 5032",
    "addr:housenumber":"48",
    "addr:postcode":"5032",
    "addr:street":"Rue Louis Burteau;Namur",
    "iso:country":"BE",
    "sg:address":"Rue Louis Burteau 48",
    "sg:city":"Gembloux-sur-orneau (bothey)",
    "sg:classifiers":[
        {
            "category":"Social Services",
            "type":"Services"
        }
    ],
    "sg:phone":"+32 81 63 30 24",
    "sg:postcode":"5032",
    "sg:province":"Namur",
    "sg:tags":[
        "handicapped",
        "-"
    ],
    "wof:name":"Foyer (le)",
    "wof:placetype":"venue"
},
  "geometry": {"coordinates":[4.6525769234,50.521232605],"type":"Point"}
}