{
  "type": "Feature",
  "properties": {
    "addr:full":"Route De Bastogne 13 Tenneville Luxembourg 6970",
    "addr:housenumber":"13",
    "addr:postcode":"6970",
    "addr:street":"Route De Bastogne",
    "iso:country":"BE",
    "sg:address":"Route De Bastogne 13",
    "sg:city":"Tenneville",
    "sg:classifiers":[
        {
            "category":"Professional",
            "subcategory":"Testing Lab",
            "type":"Services"
        }
    ],
    "sg:phone":"+32 84 45 54 81",
    "sg:postcode":"6970",
    "sg:province":"Luxembourg",
    "sg:tags":[
        "chemist"
    ],
    "wof:name":"No\u00ebl C",
    "wof:placetype":"venue"
},
  "geometry": {"coordinates":[5.5237488747,50.0920715332],"type":"Point"}
}