{
  "type": "Feature",
  "properties": {
    "iso:country":"BE",
    "sg:address":"Maastrichterstw 347",
    "sg:city":"Tongeren",
    "sg:classifiers":[
        {
            "category":"Autos & Motor Vehicles",
            "subcategory":"Automobile Sales",
            "type":"Retail Goods"
        }
    ],
    "sg:phone":"+32 12 26 02 10",
    "sg:postcode":"3700",
    "sg:province":"Limburg",
    "sg:tags":[
        "equipment",
        "motor-cars",
        "transport"
    ],
    "wof:name":"Etablissement J. Timmermans Autobedrijf Nv",
    "wof:placetype":"venue"
},
  "geometry": {"coordinates":[5.4848799706,50.7846603394],"type":"Point"}
}