{
  "type": "Feature",
  "properties": {
    "addr:full":"Beselarestraat 267 Zonnebeke West-Vlaanderen 8980",
    "addr:housenumber":"267",
    "addr:postcode":"8980",
    "addr:street":"Beselarestraat",
    "iso:country":"BE",
    "sg:address":"Beselarestraat 267",
    "sg:city":"Zonnebeke",
    "sg:classifiers":[
        {
            "category":"Cafe",
            "type":"Food & Drink"
        }
    ],
    "sg:phone":"+32 57 46 87 74",
    "sg:postcode":"8980",
    "sg:province":"West-Vlaanderen",
    "sg:tags":[
        "caf\u00e9s"
    ],
    "wof:name":"Brouwershof",
    "wof:placetype":"venue"
},
  "geometry": {"coordinates":[3.0097019672,50.8606758118],"type":"Point"}
}