{
  "type": "Feature",
  "properties": {
    "iso:country":"BE",
    "sg:address":"Marktplein 23",
    "sg:city":"Sint-lievens-houtem",
    "sg:orig_category":"Electrom\u00e9nager, t\u00e9l\u00e9visions and radios. R\u00e9parations d'appareils \u00e9lectrom\u00e9nagers",
    "sg:phone":"+32 53 62 41 28",
    "sg:postcode":"9520",
    "sg:province":"Oost-Vlaanderen",
    "wof:name":"Huis De Clercq",
    "wof:placetype":"venue"
},
  "geometry": {"coordinates":[3.8572940826,50.9201278687],"type":"Point"}
}