{
  "type": "Feature",
  "properties": {
    "addr:full":"Dumontlaan 3 Koksijde West-Vlaanderen 8670",
    "addr:housenumber":"3",
    "addr:postcode":"8670",
    "addr:street":"Dumontlaan",
    "iso:country":"BE",
    "sg:address":"Dumontlaan 3",
    "sg:city":"Koksijde",
    "sg:classifiers":[
        {
            "category":"Travel",
            "subcategory":"Resort",
            "type":"Entertainment"
        }
    ],
    "sg:phone":"+32 475 86 03 66",
    "sg:postcode":"8670",
    "sg:province":"West-Vlaanderen",
    "sg:tags":[
        "rental",
        "accomodation",
        "holiday",
        "-"
    ],
    "wof:name":"Eglantine B & B",
    "wof:placetype":"venue"
},
  "geometry": {"coordinates":[2.6081650257,51.1095352173],"type":"Point"}
}