{
  "type": "Feature",
  "properties": {
    "iso:country":"BE",
    "sg:address":"Miksebeekstraat 111",
    "sg:city":"Brasschaat",
    "sg:classifiers":[
        {
            "category":"Real Estate",
            "subcategory":"Architect",
            "type":"Services"
        }
    ],
    "sg:phone":"+32 3 651 30 92",
    "sg:postcode":"2930",
    "sg:province":"Antwerpen",
    "wof:name":"Delbaen W",
    "wof:placetype":"venue"
},
  "geometry": {"coordinates":[4.5113921165,51.2969398499],"type":"Point"}
}