{
  "type": "Feature",
  "properties": {
    "iso:country":"BE",
    "sg:address":"Chauss\u00e9e De Wavre 212",
    "sg:city":"Perwez (thorembais-saint-trond)",
    "sg:classifiers":[
        {
            "category":"Professional",
            "subcategory":"Accounting & Tax Preparation",
            "type":"Services"
        }
    ],
    "sg:phone":"+32 81 22 77 31",
    "sg:postcode":"1360",
    "sg:province":"Brabant Wallon",
    "sg:tags":[
        "bookkeeper"
    ],
    "wof:name":"F\u00e9d\u00e9ration Wallonne De Services Brabant-nanur",
    "wof:placetype":"venue"
},
  "geometry": {"coordinates":[4.8033800125,50.6295204163],"type":"Point"}
}