{
  "type": "Feature",
  "properties": {
    "iso:country":"BE",
    "sg:address":"Industriestraat 36",
    "sg:city":"Ichtegem",
    "sg:orig_category":"Non-Classified Establishments",
    "sg:phone":"+32 51 58 89 12",
    "sg:postcode":"8480",
    "sg:province":"West-Vlaanderen",
    "wof:name":"Dupon Biscuits",
    "wof:placetype":"venue"
},
  "geometry": {"coordinates":[3.0262880325,51.0999755859],"type":"Point"}
}