{
  "type": "Feature",
  "properties": {
    "addr:full":"Sportlaan 22 Hechtel-eksel Limburg 3941",
    "addr:housenumber":"22",
    "addr:postcode":"3941",
    "addr:street":"Sportlaan",
    "iso:country":"BE",
    "sg:address":"Sportlaan 22",
    "sg:city":"Hechtel-eksel",
    "sg:orig_category":"Architecten",
    "sg:phone":"+32 11 73 21 65",
    "sg:postcode":"3941",
    "sg:province":"Limburg",
    "wof:name":"Marthe Reumers",
    "wof:placetype":"venue"
},
  "geometry": {"coordinates":[5.3756670952,51.1559181213],"type":"Point"}
}