{
  "type": "Feature",
  "properties": {
    "addr:full":"Avenue Gouverneur Bovesse 177 - B7 Jambes-lez-namur Namur 5100",
    "addr:housenumber":"177 b7",
    "addr:postcode":"5100",
    "addr:street":"Avenue;Bovesse;Jambes-Lez-Namur Namur",
    "iso:country":"BE",
    "sg:address":"Avenue Gouverneur Bovesse 177 - B7",
    "sg:city":"Jambes-lez-namur",
    "sg:classifiers":[
        {
            "category":"Shopping",
            "subcategory":"Computers & Home Electronics",
            "type":"Retail Goods"
        }
    ],
    "sg:phone":"+32 81 32 05 50",
    "sg:postcode":"5100",
    "sg:province":"Namur",
    "sg:tags":[
        "chamber",
        "commerce"
    ],
    "wof:name":"Chambre De Commerce Et D'industrie De La Province De Namur",
    "wof:placetype":"venue"
},
  "geometry": {"coordinates":[4.8713750839,50.4566345215],"type":"Point"}
}