{
  "type": "Feature",
  "properties": {
    "iso:country":"BE",
    "sg:address":"Meileveld 58",
    "sg:city":"Zottegem",
    "sg:orig_category":"Installatie van metalen schrijnwerk",
    "sg:phone":"+32 9 360 16 65",
    "sg:postcode":"9620",
    "sg:province":"Oost-Vlaanderen",
    "wof:name":"Lieven De Ruyver",
    "wof:placetype":"venue"
},
  "geometry": {"coordinates":[3.7992730141,50.8638839722],"type":"Point"}
}