{
  "type": "Feature",
  "properties": {
    "addr:full":"Dr\u00e8ve De Linkebeek 49a Rhode-saint-gen\u00e8se Vlaams-Brabant 1640",
    "addr:housenumber":"49a",
    "addr:postcode":"1640",
    "addr:street":"Dre\u0300Ve De Linkebeek",
    "iso:country":"BE",
    "sg:address":"Dr\u00e8ve De Linkebeek 49a",
    "sg:city":"Rhode-saint-gen\u00e8se",
    "sg:classifiers":[
        {
            "category":"Real Estate",
            "subcategory":"Surveying",
            "type":"Services"
        }
    ],
    "sg:phone":"+32 2 358 17 87",
    "sg:postcode":"1640",
    "sg:province":"Vlaams-Brabant",
    "sg:tags":[
        "surveyor",
        "land"
    ],
    "wof:name":"Vanderlinden A",
    "wof:placetype":"venue"
},
  "geometry": {"coordinates":[4.3714418411,50.7600860596],"type":"Point"}
}