{
  "type": "Feature",
  "properties": {
    "iso:country":"BE",
    "sg:address":"Pater Damiaanstraat 6",
    "sg:city":"Niel",
    "sg:classifiers":[
        {
            "category":"Professional",
            "subcategory":"Engineering",
            "type":"Services"
        }
    ],
    "sg:phone":"+32 3 844 71 10",
    "sg:postcode":"2845",
    "sg:province":"Antwerpen",
    "sg:tags":[
        "technical",
        "equipment",
        "offices-"
    ],
    "wof:name":"Stetec",
    "wof:placetype":"venue"
},
  "geometry": {"coordinates":[4.3479480743,51.1090927124],"type":"Point"}
}