{
  "type": "Feature",
  "properties": {
    "iso:country":"BE",
    "sg:address":"Dranouterstraat 42",
    "sg:city":"Heuvelland",
    "sg:orig_category":"Rundveehouders Varkenskwekers",
    "sg:phone":"+32 57 44 47 14",
    "sg:postcode":"8950",
    "sg:province":"West-Vlaanderen",
    "wof:name":"Eric Heughebaert",
    "wof:placetype":"venue"
},
  "geometry": {"coordinates":[2.8055870533,50.7523956299],"type":"Point"}
}