{
  "type": "Feature",
  "properties": {
    "addr:full":"Rue Saint-michel 11 Li\u00c8ge Li\u00e8ge 4000",
    "addr:housenumber":"11",
    "addr:postcode":"4000",
    "addr:street":"Rue Saint-Michel",
    "iso:country":"BE",
    "sg:address":"Rue Saint-michel 11",
    "sg:city":"Li\u00c8ge",
    "sg:classifiers":[
        {
            "category":"Shopping",
            "subcategory":"Clothing, Apparel, & Fashions",
            "type":"Retail Goods"
        }
    ],
    "sg:phone":"+32 4 223 76 27",
    "sg:postcode":"4000",
    "sg:province":"Li\u00e8ge",
    "sg:tags":[
        "v\u00eatements",
        "pour",
        "dame"
    ],
    "wof:name":"Etam",
    "wof:placetype":"venue"
},
  "geometry": {"coordinates":[5.5721149445,50.6445350647],"type":"Point"}
}