{
  "type": "Feature",
  "properties": {
    "addr:full":"Cosijnstraat 14 Bree Limburg 3960",
    "addr:housenumber":"14",
    "addr:postcode":"3960",
    "addr:street":"Cosijnstraat",
    "iso:country":"BE",
    "sg:address":"Cosijnstraat 14",
    "sg:city":"Bree",
    "sg:orig_category":"Quincailleries. Fabrication and montage de mobilier",
    "sg:phone":"+32 89 46 56 08",
    "sg:postcode":"3960",
    "sg:province":"Limburg",
    "wof:name":"Joseph Soons",
    "wof:placetype":"venue"
},
  "geometry": {"coordinates":[5.5942549706,51.1397857666],"type":"Point"}
}