{
  "type": "Feature",
  "properties": {
    "addr:full":"Hoogte Honderdplein 34 Vorst/forest Bruxelles-Capitale 1190",
    "addr:housenumber":"34",
    "addr:postcode":"1190",
    "addr:street":"Hoogte Honderdplein;/ Forest",
    "iso:country":"BE",
    "sg:address":"Hoogte Honderdplein 34",
    "sg:city":"Vorst/forest",
    "sg:orig_category":"Diverse kredietdiensten",
    "sg:postcode":"1190",
    "sg:province":"Bruxelles-Capitale",
    "wof:name":"Bancontact-mister Cash",
    "wof:placetype":"venue"
},
  "geometry": {"coordinates":[4.3362932205,50.8161430359],"type":"Point"}
}