{
  "type": "Feature",
  "properties": {
    "addr:full":"Overhaamlaan 40 Tongeren Limburg 3700",
    "addr:housenumber":"40",
    "addr:postcode":"3700",
    "addr:street":"Overhaamlaan",
    "iso:country":"BE",
    "sg:address":"Overhaamlaan 40",
    "sg:city":"Tongeren",
    "sg:classifiers":[
        {
            "category":"Shopping",
            "subcategory":"Computers & Home Electronics",
            "type":"Retail Goods"
        }
    ],
    "sg:phone":"+32 12 39 04 00",
    "sg:postcode":"3700",
    "sg:province":"Limburg",
    "sg:tags":[
        "electric",
        "electricity",
        "component",
        "equipment",
        "electrical",
        "electronic"
    ],
    "wof:name":"G\u00dcnther Belgium Nv",
    "wof:placetype":"venue"
},
  "geometry": {"coordinates":[5.4752202034,50.7681503296],"type":"Point"}
}