{
  "type": "Feature",
  "properties": {
    "addr:full":"Kokstraat 33 Nieuwpoort West-Vlaanderen 8620",
    "addr:housenumber":"33",
    "addr:postcode":"8620",
    "addr:street":"Kokstraat",
    "iso:country":"BE",
    "sg:address":"Kokstraat 33",
    "sg:city":"Nieuwpoort",
    "sg:orig_category":"Banken and kredietinstellingen",
    "sg:phone":"+32 58 24 07 07",
    "sg:postcode":"8620",
    "sg:province":"West-Vlaanderen",
    "wof:name":"Centea",
    "wof:placetype":"venue"
},
  "geometry": {"coordinates":[2.7484149933,51.1312065125],"type":"Point"}
}