{
  "type": "Feature",
  "properties": {
    "iso:country":"BE",
    "sg:address":"Portweg 6",
    "sg:city":"Diksmuide",
    "sg:orig_category":"Eleveurs and marchands de porcs. Eleveurs de bovins",
    "sg:phone":"+32 51 50 03 13",
    "sg:postcode":"8600",
    "sg:province":"West-Vlaanderen",
    "wof:name":"Andre Verstegen",
    "wof:placetype":"venue"
},
  "geometry": {"coordinates":[2.9409410954,51.0430870056],"type":"Point"}
}