{
  "type": "Feature",
  "properties": {
    "addr:full":"Middenlaan 36 Leopoldsburg Limburg 3971",
    "addr:housenumber":"36",
    "addr:postcode":"3971",
    "addr:street":"Middenlaan",
    "iso:country":"BE",
    "sg:address":"Middenlaan 36",
    "sg:city":"Leopoldsburg",
    "sg:classifiers":[
        {
            "category":"Arena",
            "subcategory":"Sports Club",
            "type":"Entertainment"
        }
    ],
    "sg:phone":"+32 11 34 17 37",
    "sg:postcode":"3971",
    "sg:province":"Limburg",
    "sg:tags":[
        "de"
    ],
    "wof:name":"J.c. Ham",
    "wof:placetype":"venue"
},
  "geometry": {"coordinates":[5.2314500809,51.1209907532],"type":"Point"}
}