{
  "type": "Feature",
  "properties": {
    "iso:country":"BE",
    "sg:address":"Rue Pr\u00e9sident Wilson 28",
    "sg:city":"Ans",
    "sg:classifiers":[
        {
            "category":"Building & Trades",
            "subcategory":"Equipment Rental",
            "type":"Services"
        }
    ],
    "sg:phone":"+32 4 226 42 60",
    "sg:postcode":"4430",
    "sg:province":"Li\u00e8ge",
    "sg:tags":[
        "sound",
        "-",
        "system"
    ],
    "wof:name":"Sandvoice Sprl",
    "wof:placetype":"venue"
},
  "geometry": {"coordinates":[5.536752224,50.6528587341],"type":"Point"}
}