{
  "type": "Feature",
  "properties": {
    "addr:full":"Turcksinstraat 19 Machelen Vlaams-Brabant 1830",
    "addr:housenumber":"19",
    "addr:postcode":"1830",
    "addr:street":"Turcksinstraat",
    "iso:country":"BE",
    "sg:address":"Turcksinstraat 19",
    "sg:city":"Machelen",
    "sg:classifiers":[
        {
            "category":"Professional",
            "subcategory":"Accounting & Tax Preparation",
            "type":"Services"
        }
    ],
    "sg:phone":"+32 2 253 23 29",
    "sg:postcode":"1830",
    "sg:province":"Vlaams-Brabant",
    "sg:tags":[
        "bookkeeper"
    ],
    "wof:name":"Milbo Bvba",
    "wof:placetype":"venue"
},
  "geometry": {"coordinates":[4.4381408691,50.9141921997],"type":"Point"}
}