{
  "type": "Feature",
  "properties": {
    "iso:country":"BE",
    "sg:address":"Grensstraat 136",
    "sg:city":"Kapellen",
    "sg:orig_category":"Oldtimers",
    "sg:phone":"+32 3 665 30 97",
    "sg:postcode":"2950",
    "sg:province":"Antwerpen",
    "wof:name":"Ceremonie Rousseau Nv",
    "wof:placetype":"venue"
},
  "geometry": {"coordinates":[4.4193367958,51.3618850708],"type":"Point"}
}