{
  "type": "Feature",
  "properties": {
    "addr:full":"Vlasmarkt 8-10 Antwerpen Antwerpen 2000",
    "addr:housenumber":"8-10",
    "addr:postcode":"2000",
    "addr:street":"Vlasmarkt",
    "iso:country":"BE",
    "sg:address":"Vlasmarkt 8-10",
    "sg:city":"Antwerpen",
    "sg:classifiers":[
        {
            "category":"Restaurant",
            "type":"Food & Drink"
        }
    ],
    "sg:phone":"+32 3 231 90 86",
    "sg:postcode":"2000",
    "sg:province":"Antwerpen",
    "wof:name":"Nonkel Guy",
    "wof:placetype":"venue"
},
  "geometry": {"coordinates":[4.3967242241,51.2198028564],"type":"Point"}
}