{
  "type": "Feature",
  "properties": {
    "iso:country":"BE",
    "sg:address":"Oude Maria's Lindestraat 4",
    "sg:city":"Roeselare (rumbeke)",
    "sg:classifiers":[
        {
            "category":"Cafe",
            "type":"Food & Drink"
        }
    ],
    "sg:phone":"+32 51 69 45 15",
    "sg:postcode":"8800",
    "sg:province":"West-Vlaanderen",
    "sg:tags":[
        "snack-bars"
    ],
    "wof:name":"Het Oude Hof Ter Linden",
    "wof:placetype":"venue"
},
  "geometry": {"coordinates":[3.1357529163,50.9216918945],"type":"Point"}
}