{
  "type": "Feature",
  "properties": {
    "iso:country":"BE",
    "sg:address":"Industriepark De Bruwaan 16",
    "sg:city":"Oudenaarde",
    "sg:classifiers":[
        {
            "category":"Home & Garden",
            "subcategory":"Furniture",
            "type":"Retail Goods"
        }
    ],
    "sg:phone":"+32 55 31 45 75",
    "sg:postcode":"9700",
    "sg:province":"Oost-Vlaanderen",
    "sg:tags":[
        "household",
        "wood"
    ],
    "wof:name":"De Kito Nv",
    "wof:placetype":"venue"
},
  "geometry": {"coordinates":[3.5975739956,50.8644599915],"type":"Point"}
}