{
  "type": "Feature",
  "properties": {
    "iso:country":"BE",
    "sg:address":"Bakkerstraat 64",
    "sg:city":"Dendermonde",
    "sg:orig_category":"Immobili\u00ebnkantoren",
    "sg:phone":"+32 52 21 02 56",
    "sg:postcode":"9200",
    "sg:province":"Oost-Vlaanderen",
    "wof:name":"All Immo Redant",
    "wof:placetype":"venue"
},
  "geometry": {"coordinates":[4.1023831367,51.0446243286],"type":"Point"}
}