{
  "type": "Feature",
  "properties": {
    "iso:country":"BE",
    "sg:address":"Zandpoortstraat 11",
    "sg:city":"Gent",
    "sg:orig_category":"Herstellingen and onderhoud van auto's",
    "sg:phone":"+32 9 225 77 51",
    "sg:postcode":"9000",
    "sg:province":"Oost-Vlaanderen",
    "wof:name":"Frederic Cardon De Lichtbuer",
    "wof:placetype":"venue"
},
  "geometry": {"coordinates":[3.7189369202,51.0495262146],"type":"Point"}
}