{
  "type": "Feature",
  "properties": {
    "addr:full":"Chauss\u00c9e De Mons 1303 Anderlecht Bruxelles-Capitale 1070",
    "addr:postcode":"1303;1070",
    "addr:street":"Chausse\u0301E De Mons",
    "iso:country":"BE",
    "sg:address":"Chauss\u00c9e De Mons 1303",
    "sg:city":"Anderlecht",
    "sg:classifiers":[
        {
            "category":"Government",
            "subcategory":"Police Station",
            "type":"Public Place"
        }
    ],
    "sg:phone":"+32 2 521 10 10",
    "sg:postcode":"1070",
    "sg:province":"Bruxelles-Capitale",
    "sg:tags":[
        "gendarmerie"
    ],
    "wof:name":"Police F\u00c9d\u00c9rale",
    "wof:placetype":"venue"
},
  "geometry": {"coordinates":[4.2909059525,50.8161811829],"type":"Point"}
}