{
  "type": "Feature",
  "properties": {
    "addr:full":"Rue Alphonse Jaumain 56 Profondeville Namur 5170",
    "addr:housenumber":"56",
    "addr:postcode":"5170",
    "addr:street":"Rue Alphonse Jaumain",
    "iso:country":"BE",
    "sg:address":"Rue Alphonse Jaumain 56",
    "sg:city":"Profondeville",
    "sg:orig_category":"Airconditioning and ventilatie Elektrische installaties voor woningen Installatie van houten of kuns",
    "sg:phone":"+32 81 41 31 36",
    "sg:postcode":"5170",
    "sg:province":"Namur",
    "wof:name":"Henin A",
    "wof:placetype":"venue"
},
  "geometry": {"coordinates":[4.8585319519,50.3760261536],"type":"Point"}
}