{
  "type": "Feature",
  "properties": {
    "addr:full":"Halensebaan 17 Tielt-winge (sint-joris-winge) Vlaams-Brabant 3390",
    "addr:housenumber":"17",
    "addr:postcode":"3390",
    "addr:street":"Halensebaan",
    "iso:country":"BE",
    "sg:address":"Halensebaan 17",
    "sg:city":"Tielt-winge (sint-joris-winge)",
    "sg:classifiers":[
        {
            "category":"Personal",
            "subcategory":"Beauty Salon",
            "type":"Services"
        }
    ],
    "sg:phone":"+32 16 63 47 44",
    "sg:postcode":"3390",
    "sg:province":"Vlaams-Brabant",
    "sg:tags":[
        "lady",
        "-",
        "hairdressing"
    ],
    "wof:name":"Patricia",
    "wof:placetype":"venue"
},
  "geometry": {"coordinates":[4.8834939003,50.9084815979],"type":"Point"}
}