{
  "type": "Feature",
  "properties": {
    "addr:full":"Rue La Ringe 20 Vresse-sur-semois Namur 5550",
    "addr:housenumber":"20",
    "addr:postcode":"vresse-sur-semois;5550",
    "addr:street":"Rue La Ringe",
    "iso:country":"BE",
    "sg:address":"Rue La Ringe 20",
    "sg:city":"Vresse-sur-semois",
    "sg:orig_category":"Instellingen voor mindervalide volwassenen",
    "sg:phone":"+32 61 50 04 88",
    "sg:postcode":"5550",
    "sg:province":"Namur",
    "wof:name":"Home L\u00c9on Henrard",
    "wof:placetype":"venue"
},
  "geometry": {"coordinates":[4.9336900711,49.8729820251],"type":"Point"}
}