{
  "type": "Feature",
  "properties": {
    "addr:full":"Chauss\u00e9e De Ninove 991 Bruxelles (molenbeek-saint-jean) Bruxelles-Capitale 1080",
    "addr:housenumber":"991",
    "addr:postcode":"1080",
    "addr:street":"Chausse\u0301E De Ninove",
    "iso:country":"BE",
    "sg:address":"Chauss\u00e9e De Ninove 991",
    "sg:city":"Bruxelles (molenbeek-saint-jean)",
    "sg:classifiers":[
        {
            "category":"Professional",
            "subcategory":"Printing & Photocopies",
            "type":"Services"
        }
    ],
    "sg:phone":"+32 2 521 91 23",
    "sg:postcode":"1080",
    "sg:province":"Bruxelles-Capitale",
    "sg:tags":[
        "digital"
    ],
    "wof:name":"Mortier R",
    "wof:placetype":"venue"
},
  "geometry": {"coordinates":[4.29165411,50.8464508057],"type":"Point"}
}