{
  "type": "Feature",
  "properties": {
    "addr:full":"Avenue Des Thermes 61 Chaudfontaine Li\u00e8ge 4050",
    "addr:housenumber":"61",
    "addr:postcode":"4050",
    "addr:street":"Avenue Des Thermes",
    "iso:country":"BE",
    "sg:address":"Avenue Des Thermes 61",
    "sg:city":"Chaudfontaine",
    "sg:classifiers":[
        {
            "category":"Fast Food",
            "type":"Food & Drink"
        }
    ],
    "sg:phone":"+32 4 367 72 84",
    "sg:postcode":"4050",
    "sg:province":"Li\u00e8ge",
    "sg:tags":[
        "meeneem",
        "restaurant"
    ],
    "wof:name":"La Nonna",
    "wof:placetype":"venue"
},
  "geometry": {"coordinates":[5.6418890953,50.5862617493],"type":"Point"}
}