{
  "type": "Feature",
  "properties": {
    "addr:full":"Chemin Du Prince 20 Jurbise Hainaut 7050",
    "addr:housenumber":"20",
    "addr:postcode":"7050",
    "addr:street":"Chemin Du Prince",
    "iso:country":"BE",
    "sg:address":"Chemin Du Prince 20",
    "sg:city":"Jurbise",
    "sg:orig_category":"Artsen and specialisten",
    "sg:phone":"+32 65 22 77 26",
    "sg:postcode":"7050",
    "sg:province":"Hainaut",
    "wof:name":"J.p. Hubert",
    "wof:placetype":"venue"
},
  "geometry": {"coordinates":[3.9260599613,50.5102386475],"type":"Point"}
}