{
  "type": "Feature",
  "properties": {
    "addr:full":"Grote Weg 146 Menen (rekkem) West-Vlaanderen 8930",
    "addr:housenumber":"146",
    "addr:postcode":"8930",
    "addr:street":"Grote Weg",
    "iso:country":"BE",
    "sg:address":"Grote Weg 146",
    "sg:city":"Menen (rekkem)",
    "sg:classifiers":[
        {
            "category":"Food & Beverages",
            "subcategory":"Supermarket",
            "type":"Retail Goods"
        }
    ],
    "sg:phone":"+32 56 40 34 18",
    "sg:postcode":"8930",
    "sg:province":"West-Vlaanderen",
    "sg:tags":[
        "department",
        "store"
    ],
    "wof:name":"Delhaize",
    "wof:placetype":"venue"
},
  "geometry": {"coordinates":[3.1839399338,50.7666397095],"type":"Point"}
}