{
  "type": "Feature",
  "properties": {
    "iso:country":"BE",
    "sg:address":"Rue De La Station 49",
    "sg:city":"Pont-a-celles",
    "sg:orig_category":"Apotheken",
    "sg:phone":"+32 71 84 43 88",
    "sg:postcode":"6230",
    "sg:province":"Hainaut",
    "wof:name":"Marie-therese Hols",
    "wof:placetype":"venue"
},
  "geometry": {"coordinates":[4.3669190407,50.5324707031],"type":"Point"}
}