{
  "type": "Feature",
  "properties": {
    "addr:full":"Heilig-hartstraat 11 Gent Oost-Vlaanderen 9040",
    "addr:housenumber":"11",
    "addr:postcode":"9040",
    "addr:street":"Heilig-Hartstraat;Oost-Vlaanderen",
    "iso:country":"BE",
    "sg:address":"Heilig-hartstraat 11",
    "sg:city":"Gent",
    "sg:classifiers":[
        {
            "category":"Food & Beverages",
            "subcategory":"Fruits & Vegetables",
            "type":"Retail Goods"
        }
    ],
    "sg:phone":"+32 9 228 42 20",
    "sg:postcode":"9040",
    "sg:province":"Oost-Vlaanderen",
    "sg:tags":[
        "groenten"
    ],
    "wof:name":"Dimitri Knobbe",
    "wof:placetype":"venue"
},
  "geometry": {"coordinates":[3.7483069897,51.0538253784],"type":"Point"}
}