{
  "type": "Feature",
  "properties": {
    "iso:country":"BE",
    "sg:address":"Onze-lieve-vrouwstraat 57",
    "sg:city":"Ingelmunster",
    "sg:classifiers":[
        {
            "category":"Building & Trades",
            "subcategory":"Landscaping Services",
            "type":"Services"
        }
    ],
    "sg:phone":"+32 51 30 19 51",
    "sg:postcode":"8770",
    "sg:province":"West-Vlaanderen",
    "sg:tags":[
        "gardening",
        "garden",
        "maintenance"
    ],
    "wof:name":"Deruyter G",
    "wof:placetype":"venue"
},
  "geometry": {"coordinates":[3.2632269859,50.9050865173],"type":"Point"}
}