{
  "type": "Feature",
  "properties": {
    "addr:full":"Rue Du Delta 100 Bruxelles (forest) Bruxelles-Capitale 1190",
    "addr:housenumber":"100",
    "addr:postcode":"1190",
    "addr:street":"Rue Du Delta",
    "iso:country":"BE",
    "sg:address":"Rue Du Delta 100",
    "sg:city":"Bruxelles (forest)",
    "sg:classifiers":[
        {
            "category":"Professional",
            "subcategory":"Engineering",
            "type":"Services"
        }
    ],
    "sg:phone":"+32 2 345 59 70",
    "sg:postcode":"1190",
    "sg:province":"Bruxelles-Capitale",
    "sg:tags":[
        "-"
    ],
    "wof:name":"Sogeim",
    "wof:placetype":"venue"
},
  "geometry": {"coordinates":[4.3241510391,50.8172721863],"type":"Point"}
}