{
  "type": "Feature",
  "properties": {
    "addr:full":"Alt. Hoeseltweg 16 Bilzen Limburg 3740",
    "addr:housenumber":"16",
    "addr:postcode":"3740",
    "addr:street":"Alt.",
    "iso:country":"BE",
    "sg:address":"Alt. Hoeseltweg 16",
    "sg:city":"Bilzen",
    "sg:orig_category":"Quincailleries. Mat\u00e9riaux de construction Gr",
    "sg:phone":"+32 89 41 17 18",
    "sg:postcode":"3740",
    "sg:province":"Limburg",
    "wof:name":"Jorissen",
    "wof:placetype":"venue"
},
  "geometry": {"coordinates":[5.5115132332,50.8297462463],"type":"Point"}
}