{
  "type": "Feature",
  "properties": {
    "addr:full":"Avenue Jean Dubrucq 175 Box 1 Bruxelles (molenbeek-saint-jean) Bruxelles-Capitale 1080",
    "addr:housenumber":"175;1",
    "addr:postcode":"1080",
    "addr:street":"Avenue Jean Dubrucq;Box",
    "iso:country":"BE",
    "sg:address":"Avenue Jean Dubrucq 175 Box 1",
    "sg:city":"Bruxelles (molenbeek-saint-jean)",
    "sg:classifiers":[
        {
            "category":"Real Estate",
            "subcategory":"Developer",
            "type":"Services"
        }
    ],
    "sg:phone":"+32 2 422 53 11",
    "sg:postcode":"1080",
    "sg:province":"Bruxelles-Capitale",
    "sg:tags":[
        "project"
    ],
    "wof:name":"Compagnie Immobili\u00e8re De Belgique Sa",
    "wof:placetype":"venue"
},
  "geometry": {"coordinates":[4.3385930061,50.8682518005],"type":"Point"}
}