{
  "type": "Feature",
  "properties": {
    "iso:country":"BE",
    "sg:address":"Industriezone Roosveld 9",
    "sg:city":"Landen",
    "sg:orig_category":"Dakwerken Gespecialiseerde residenti\u00eble bouw Loodgieterij, verwarming and sanitaire installaties",
    "sg:phone":"+32 11 83 27 18",
    "sg:postcode":"3400",
    "sg:province":"Vlaams-Brabant",
    "wof:name":"Bens",
    "wof:placetype":"venue"
},
  "geometry": {"coordinates":[5.0648112297,50.7502212524],"type":"Point"}
}