{
  "type": "Feature",
  "properties": {
    "addr:full":"Industriepark De Bruwaan 14a Oudenaarde Oost-Vlaanderen 9700",
    "addr:housenumber":"14a",
    "addr:postcode":"9700",
    "addr:street":"Industriepark;Bruwaan",
    "iso:country":"BE",
    "sg:address":"Industriepark De Bruwaan 14a",
    "sg:city":"Oudenaarde",
    "sg:classifiers":[
        {
            "category":"Home & Garden",
            "subcategory":"Building Materials",
            "type":"Retail Goods"
        }
    ],
    "sg:phone":"+32 55 31 27 95",
    "sg:postcode":"9700",
    "sg:province":"Oost-Vlaanderen",
    "sg:tags":[
        "window"
    ],
    "wof:name":"Sonobo Nv",
    "wof:placetype":"venue"
},
  "geometry": {"coordinates":[3.5969190598,50.8640136719],"type":"Point"}
}