{
  "type": "Feature",
  "properties": {
    "addr:full":"Olmensebaan 121 Balen Antwerpen 2490",
    "addr:housenumber":"121",
    "addr:postcode":"2490",
    "addr:street":"Olmensebaan",
    "iso:country":"BE",
    "sg:address":"Olmensebaan 121",
    "sg:city":"Balen",
    "sg:orig_category":"Services pour animaux domestiques. Eleveurs d'animaux domestiques",
    "sg:phone":"+32 14 31 19 70",
    "sg:postcode":"2490",
    "sg:province":"Antwerpen",
    "wof:name":"De Blokhoeve Hondenpension",
    "wof:placetype":"venue"
},
  "geometry": {"coordinates":[5.1411828995,51.1612281799],"type":"Point"}
}