{
  "type": "Feature",
  "properties": {
    "iso:country":"BE",
    "sg:address":"66",
    "sg:city":"Aartshertogstraat 8400 Oostende",
    "sg:classifiers":[
        {
            "category":"Bakery",
            "type":"Food & Drink"
        }
    ],
    "sg:phone":"+32 59 80 18 89",
    "sg:postcode":"66",
    "sg:tags":[
        "cake",
        "product",
        "related",
        "bread"
    ],
    "wof:name":"Gheysen Ignace M.",
    "wof:placetype":"venue"
},
  "geometry": {"coordinates":[2.9168219566,51.2302780151],"type":"Point"}
}