{
  "type": "Feature",
  "properties": {
    "addr:full":"Avenue Prince De Li\u00c8ge 195 Namur Namur 5100",
    "addr:housenumber":"195",
    "addr:postcode":"5100",
    "addr:street":"Avenue Prince De Lie\u0300Ge",
    "iso:country":"BE",
    "sg:address":"Avenue Prince De Li\u00c8ge 195",
    "sg:city":"Namur",
    "sg:orig_category":"Entretien and r\u00e9parations de voitures. D\u00e9taillants en pi\u00e8ces and accessoires de voitures",
    "sg:phone":"+32 81 30 14 88",
    "sg:postcode":"5100",
    "sg:province":"Namur",
    "wof:name":"Midas",
    "wof:placetype":"venue"
},
  "geometry": {"coordinates":[4.8713750839,50.4566345215],"type":"Point"}
}