{
  "type": "Feature",
  "properties": {
    "addr:full":"Av De La Chasse 68 Bruxelles Bruxelles-Capitale 1040",
    "addr:housenumber":"68",
    "addr:postcode":"1040",
    "addr:street":"Av De La Chasse",
    "iso:country":"BE",
    "sg:address":"Av De La Chasse 68",
    "sg:city":"Bruxelles",
    "sg:classifiers":[
        {
            "category":"Home & Garden",
            "subcategory":"Furniture",
            "type":"Retail Goods"
        }
    ],
    "sg:phone":"+32 2 732 21 40",
    "sg:postcode":"1040",
    "sg:province":"Bruxelles-Capitale",
    "sg:tags":[
        "household",
        "wood"
    ],
    "wof:name":"Cadr'art Sprl",
    "wof:placetype":"venue"
},
  "geometry": {"coordinates":[4.3913960457,50.8323860168],"type":"Point"}
}