{
  "type": "Feature",
  "properties": {
    "iso:country":"BE",
    "sg:address":"Lillo Steenweg 3ba",
    "sg:city":"Houthalen-helchteren",
    "sg:orig_category":"Artsen and specialisten",
    "sg:phone":"+32 11 57 36 71",
    "sg:postcode":"3530",
    "sg:province":"Limburg",
    "wof:name":"Anita Achten",
    "wof:placetype":"venue"
},
  "geometry": {"coordinates":[5.3534350395,51.0437507629],"type":"Point"}
}