{
  "type": "Feature",
  "properties": {
    "iso:country":"BE",
    "sg:address":"Honthem 25",
    "sg:city":"Baelen/baelen",
    "sg:orig_category":"Rundveehouders",
    "sg:phone":"+32 87 76 48 77",
    "sg:postcode":"4837",
    "sg:province":"Li\u00e8ge",
    "wof:name":"Alain Mullender",
    "wof:placetype":"venue"
},
  "geometry": {"coordinates":[5.9491271973,50.6296730042],"type":"Point"}
}