{
  "type": "Feature",
  "properties": {
    "iso:country":"BE",
    "sg:address":"Grand'rue 80",
    "sg:city":"Antoing",
    "sg:orig_category":"Slagers",
    "sg:phone":"+32 69 44 25 12",
    "sg:postcode":"7640",
    "sg:province":"Hainaut",
    "wof:name":"Blondiau",
    "wof:placetype":"venue"
},
  "geometry": {"coordinates":[3.5038220882,50.5419311523],"type":"Point"}
}