{
  "type": "Feature",
  "properties": {
    "addr:full":"Pullaarsteenweg 91 Puurs Antwerpen 2870",
    "addr:housenumber":"91",
    "addr:postcode":"2870",
    "addr:street":"Pullaarsteenweg",
    "iso:country":"BE",
    "sg:address":"Pullaarsteenweg 91",
    "sg:city":"Puurs",
    "sg:orig_category":"Instituts de beaut\u00e9. Centres de relaxation and bien-\u00eatre",
    "sg:phone":"+32 3 886 49 78",
    "sg:postcode":"2870",
    "sg:province":"Antwerpen",
    "wof:name":"Instituut Marina",
    "wof:placetype":"venue"
},
  "geometry": {"coordinates":[4.3238677979,51.070980072],"type":"Point"}
}