{
  "type": "Feature",
  "properties": {
    "iso:country":"BE",
    "sg:address":"Kardinaal Cardijnlaan 28",
    "sg:city":"Lendelede",
    "sg:orig_category":"Charpentes and couvertures",
    "sg:phone":"+32 51 30 74 89",
    "sg:postcode":"8860",
    "sg:province":"West-Vlaanderen",
    "wof:name":"Dakwerken Delaere",
    "wof:placetype":"venue"
},
  "geometry": {"coordinates":[3.2343759537,50.8881912231],"type":"Point"}
}