{
  "type": "Feature",
  "properties": {
    "addr:full":"Tweekapellenstraat 4 Gent Oost-Vlaanderen 9050",
    "addr:housenumber":"4",
    "addr:postcode":"9050",
    "addr:street":"Tweekapellenstraat;Oost-Vlaanderen",
    "iso:country":"BE",
    "sg:address":"Tweekapellenstraat 4",
    "sg:city":"Gent",
    "sg:classifiers":[
        {
            "category":"Fast Food",
            "type":"Food & Drink"
        }
    ],
    "sg:phone":"+32 9 231 92 13",
    "sg:postcode":"9050",
    "sg:province":"Oost-Vlaanderen",
    "sg:tags":[
        "\u00c0",
        "restaurants",
        "emporter",
        "restaurant"
    ],
    "wof:name":"Frietshop",
    "wof:placetype":"venue"
},
  "geometry": {"coordinates":[3.7525401115,51.0442199707],"type":"Point"}
}