{
  "type": "Feature",
  "properties": {
    "iso:country":"BE",
    "sg:address":"Lakense Laan 50",
    "sg:city":"Jette",
    "sg:orig_category":"Artsen and specialisten",
    "sg:phone":"+32 2 428 70 60",
    "sg:postcode":"1090",
    "sg:province":"Bruxelles-Capitale",
    "wof:name":"P. Bruderer",
    "wof:placetype":"venue"
},
  "geometry": {"coordinates":[4.3233780861,50.8707199097],"type":"Point"}
}