{
  "type": "Feature",
  "properties": {
    "iso:country":"BE",
    "sg:address":"Stuurboordstraat 12",
    "sg:city":"Oostende",
    "sg:orig_category":"Isolatiewerk",
    "sg:phone":"+32 59 32 04 59",
    "sg:postcode":"8400",
    "sg:province":"West-Vlaanderen",
    "wof:name":"Isowan",
    "wof:placetype":"venue"
},
  "geometry": {"coordinates":[2.9126999378,51.2312583923],"type":"Point"}
}