{
  "type": "Feature",
  "properties": {
    "addr:full":"Kloosterstraat 25b1 Gooik Vlaams-Brabant 1755",
    "addr:housenumber":"25b1",
    "addr:postcode":"1755",
    "addr:street":"Kloosterstraat",
    "iso:country":"BE",
    "sg:address":"Kloosterstraat 25b1",
    "sg:city":"Gooik",
    "sg:orig_category":"Kapsalons",
    "sg:phone":"+32 54 56 93 50",
    "sg:postcode":"1755",
    "sg:province":"Vlaams-Brabant",
    "wof:name":"Coiffure Thierry",
    "wof:placetype":"venue"
},
  "geometry": {"coordinates":[4.0607891083,50.773601532],"type":"Point"}
}