{
  "type": "Feature",
  "properties": {
    "iso:country":"BE",
    "sg:address":"Leuvensesteenweg 545",
    "sg:city":"Kortenberg",
    "sg:classifiers":[
        {
            "category":"Food & Beverages",
            "subcategory":"Chocolate",
            "type":"Retail Goods"
        }
    ],
    "sg:phone":"+32 2 759 69 60",
    "sg:postcode":"3070",
    "sg:province":"Vlaams-Brabant",
    "sg:tags":[
        "confectionery",
        "-"
    ],
    "wof:name":"Amandine Chocolaterie",
    "wof:placetype":"venue"
},
  "geometry": {"coordinates":[4.556388855,50.890247345],"type":"Point"}
}