{
  "type": "Feature",
  "properties": {
    "addr:full":"Oud Termienstraat 22 Genk Limburg 3600",
    "addr:housenumber":"22",
    "addr:postcode":"3600",
    "addr:street":"Oud Termienstraat",
    "iso:country":"BE",
    "sg:address":"Oud Termienstraat 22",
    "sg:city":"Genk",
    "sg:classifiers":[
        {
            "category":"Home & Garden",
            "subcategory":"Kitchen Supply",
            "type":"Retail Goods"
        }
    ],
    "sg:phone":"+32 89 32 94 94",
    "sg:postcode":"3600",
    "sg:province":"Limburg",
    "sg:tags":[
        "installation"
    ],
    "wof:name":"V S K Supertegel",
    "wof:placetype":"venue"
},
  "geometry": {"coordinates":[5.4665341377,50.9412193298],"type":"Point"}
}