{
  "type": "Feature",
  "properties": {
    "addr:full":"Lemmenskuilstraat 1 Kinrooi Limburg 3640",
    "addr:housenumber":"1",
    "addr:postcode":"3640",
    "addr:street":"Lemmenskuilstraat",
    "iso:country":"BE",
    "sg:address":"Lemmenskuilstraat 1",
    "sg:city":"Kinrooi",
    "sg:orig_category":"Installation de menuiserie en bois and plastique",
    "sg:phone":"+32 89 70 31 46",
    "sg:postcode":"3640",
    "sg:province":"Limburg",
    "wof:name":"Patrick Steensels",
    "wof:placetype":"venue"
},
  "geometry": {"coordinates":[5.7294669151,51.1446380615],"type":"Point"}
}