{
  "type": "Feature",
  "properties": {
    "addr:full":"Avenue Baron Louis Huart 31 Namur Namur 5000",
    "addr:housenumber":"31",
    "addr:postcode":"5000",
    "addr:street":"Avenue Baron Louis Huart",
    "iso:country":"BE",
    "sg:address":"Avenue Baron Louis Huart 31",
    "sg:city":"Namur",
    "sg:orig_category":"Benzinestations and brandstoffen Herstellingen and onderhoud van auto's Onderdelen and accessoires v",
    "sg:phone":"+32 81 22 23 33",
    "sg:postcode":"5000",
    "sg:province":"Namur",
    "wof:name":"Garage Libion",
    "wof:placetype":"venue"
},
  "geometry": {"coordinates":[4.8655238152,50.4592018127],"type":"Point"}
}