{
  "type": "Feature",
  "properties": {
    "addr:full":"Boulevard D'herseaux 131 Moeskroen/mouscron Hainaut 7711",
    "addr:housenumber":"131",
    "addr:postcode":"7711",
    "addr:street":"Boulevard D'Herseaux",
    "iso:country":"BE",
    "sg:address":"Boulevard D'herseaux 131",
    "sg:city":"Moeskroen/mouscron",
    "sg:orig_category":"Pain, p\u00e2tisseries and confiseries",
    "sg:phone":"+32 56 48 59 45",
    "sg:postcode":"7711",
    "sg:province":"Hainaut",
    "wof:name":"Delberghe Ph. & S.",
    "wof:placetype":"venue"
},
  "geometry": {"coordinates":[3.277766943,50.7186355591],"type":"Point"}
}