{
  "type": "Feature",
  "properties": {
    "iso:country":"BE",
    "sg:address":"Beursstr 4",
    "sg:city":"Wellen",
    "sg:classifiers":[
        {
            "category":"Food & Beverages",
            "subcategory":"Dairy",
            "type":"Retail Goods"
        }
    ],
    "sg:phone":"+32 12 74 16 27",
    "sg:postcode":"3832",
    "sg:province":"Limburg",
    "sg:tags":[
        "product",
        "related"
    ],
    "wof:name":"Voerke Ijs Nv",
    "wof:placetype":"venue"
},
  "geometry": {"coordinates":[5.276884079,50.841381073],"type":"Point"}
}