{
  "type": "Feature",
  "properties": {
    "addr:full":"Heesterbos Ranst (oelegem) Antwerpen 2520",
    "addr:postcode":"2520",
    "addr:street":"Heesterbos",
    "iso:country":"BE",
    "sg:address":"Heesterbos",
    "sg:city":"Ranst (oelegem)",
    "sg:classifiers":[
        {
            "category":"Arena",
            "subcategory":"Sports Club",
            "type":"Entertainment"
        }
    ],
    "sg:phone":"+32 3 384 00 65",
    "sg:postcode":"2520",
    "sg:province":"Antwerpen",
    "wof:name":"J C Oelegem",
    "wof:placetype":"venue"
},
  "geometry": {"coordinates":[4.6185398102,51.2110061646],"type":"Point"}
}