{
  "type": "Feature",
  "properties": {
    "iso:country":"BE",
    "sg:address":"E. Eylenboschstraat 62",
    "sg:city":"Dilbeek",
    "sg:orig_category":"Pain, p\u00e2tisseries and confiseries",
    "sg:phone":"+32 2 569 78 65",
    "sg:postcode":"1703",
    "sg:province":"Vlaams-Brabant",
    "wof:name":"Bakkerij Van Strombeek",
    "wof:placetype":"venue"
},
  "geometry": {"coordinates":[4.1954288483,50.8376731873],"type":"Point"}
}