{
  "type": "Feature",
  "properties": {
    "addr:full":"Route De Mettet 67 Florennes Namur 5620",
    "addr:housenumber":"67",
    "addr:postcode":"5620",
    "addr:street":"Route De Mettet",
    "iso:country":"BE",
    "sg:address":"Route De Mettet 67",
    "sg:city":"Florennes",
    "sg:orig_category":"Traitement and fa\u00e7onnage de la pierre",
    "sg:phone":"+32 71 68 84 25",
    "sg:postcode":"5620",
    "sg:province":"Namur",
    "wof:name":"Marbreries De Florennes",
    "wof:placetype":"venue"
},
  "geometry": {"coordinates":[4.606883049,50.2543869019],"type":"Point"}
}