{
  "type": "Feature",
  "properties": {
    "addr:full":"Reningheersdijkstraat 7 Veurne West-Vlaanderen 8630",
    "addr:housenumber":"7",
    "addr:postcode":"8630",
    "addr:street":"Reningheersdijkstraat",
    "iso:country":"BE",
    "sg:address":"Reningheersdijkstraat 7",
    "sg:city":"Veurne",
    "sg:orig_category":"Eleveurs de bovins",
    "sg:phone":"+32 58 29 83 56",
    "sg:postcode":"8630",
    "sg:province":"West-Vlaanderen",
    "wof:name":"Marcel Vandecasserie",
    "wof:placetype":"venue"
},
  "geometry": {"coordinates":[2.6617588997,51.072681427],"type":"Point"}
}