{
  "type": "Feature",
  "properties": {
    "addr:full":"Rue Louis De Brouck\u00e8re 5 La Louvi\u00e8re Hainaut 7100",
    "addr:housenumber":"5",
    "addr:postcode":"7100",
    "addr:street":"Rue Louis De Broucke\u0300Re",
    "iso:country":"BE",
    "sg:address":"Rue Louis De Brouck\u00e8re 5",
    "sg:city":"La Louvi\u00e8re",
    "sg:classifiers":[
        {
            "category":"Retail",
            "subcategory":"Repair Shop",
            "type":"Services"
        }
    ],
    "sg:phone":"+32 64 22 13 91",
    "sg:postcode":"7100",
    "sg:province":"Hainaut",
    "sg:tags":[
        "radio",
        "television",
        "-",
        "maintenance"
    ],
    "wof:name":"Flamme",
    "wof:placetype":"venue"
},
  "geometry": {"coordinates":[4.189499855,50.4786376953],"type":"Point"}
}