{
  "type": "Feature",
  "properties": {
    "iso:country":"BE",
    "sg:address":"Kuitegemstraat 67",
    "sg:city":"Sint-amands",
    "sg:classifiers":[
        {
            "category":"Home & Garden",
            "subcategory":"Carpets & Floor Coverings",
            "type":"Retail Goods"
        }
    ],
    "sg:phone":"+32 52 33 19 02",
    "sg:postcode":"2890",
    "sg:province":"Antwerpen",
    "sg:tags":[
        "-",
        "rug"
    ],
    "wof:name":"Vermeir",
    "wof:placetype":"venue"
},
  "geometry": {"coordinates":[4.1940732002,51.04114151],"type":"Point"}
}