{
  "type": "Feature",
  "properties": {
    "addr:full":"Rue Achille Delattre 423 Quaregnon Hainaut 7390",
    "addr:housenumber":"423",
    "addr:postcode":"7390",
    "addr:street":"Rue Achille Delattre",
    "iso:country":"BE",
    "sg:address":"Rue Achille Delattre 423",
    "sg:city":"Quaregnon",
    "sg:orig_category":"Pain, p\u00e2tisseries and confiseries",
    "sg:phone":"+32 65 79 13 51",
    "sg:postcode":"7390",
    "sg:province":"Hainaut",
    "wof:name":"Beatrice De Pauw",
    "wof:placetype":"venue"
},
  "geometry": {"coordinates":[3.8496110439,50.4286422729],"type":"Point"}
}