{
  "type": "Feature",
  "properties": {
    "iso:country":"BE",
    "sg:address":"Rue De Marche 40",
    "sg:city":"Aywaille",
    "sg:orig_category":"Jardinage",
    "sg:phone":"+32 4 384 55 73",
    "sg:postcode":"4920",
    "sg:province":"Li\u00e8ge",
    "wof:name":"Fe. Lagasse",
    "wof:placetype":"venue"
},
  "geometry": {"coordinates":[5.6673960686,50.4598007202],"type":"Point"}
}