{
  "type": "Feature",
  "properties": {
    "iso:country":"BE",
    "sg:address":"Hallestraat 4",
    "sg:city":"Brugge",
    "sg:orig_category":"Verhuur voertuigen behalve auto's Watersport-, Sport- and Kampeerbenodigdheden Verhuur",
    "sg:phone":"+32 50 33 80 27",
    "sg:postcode":"8000",
    "sg:province":"West-Vlaanderen",
    "wof:name":"Adventure Scooter Renting",
    "wof:placetype":"venue"
},
  "geometry": {"coordinates":[3.2242839336,51.2080345154],"type":"Point"}
}