{
  "type": "Feature",
  "properties": {
    "addr:full":"Rue Des Salmons 7 Hannut (lens-saint-remy) Li\u00e8ge 4280",
    "addr:housenumber":"7",
    "addr:postcode":"4280",
    "addr:street":"Rue Des Salmons;Lens-Saint-Remy",
    "iso:country":"BE",
    "sg:address":"Rue Des Salmons 7",
    "sg:city":"Hannut (lens-saint-remy)",
    "sg:classifiers":[
        {
            "category":"Retail",
            "subcategory":"Auto Rental",
            "type":"Services"
        }
    ],
    "sg:phone":"+32 19 51 43 95",
    "sg:postcode":"4280",
    "sg:province":"Li\u00e8ge",
    "sg:tags":[
        "van",
        "hire",
        "-",
        "truck"
    ],
    "wof:name":"Schouffler",
    "wof:placetype":"venue"
},
  "geometry": {"coordinates":[5.1274957657,50.6537895203],"type":"Point"}
}