{
  "type": "Feature",
  "properties": {
    "iso:country":"BE",
    "sg:address":"Plezantstraat 56",
    "sg:city":"Sint-niklaas",
    "sg:orig_category":"Secr\u00e9tariats sociaux",
    "sg:phone":"+32 3 777 78 80",
    "sg:postcode":"9100",
    "sg:province":"Oost-Vlaanderen",
    "wof:name":"Kinderbijslagfonds Acvw",
    "wof:placetype":"venue"
},
  "geometry": {"coordinates":[4.1339349747,51.1667480469],"type":"Point"}
}