{
  "type": "Feature",
  "properties": {
    "addr:full":"Waversesteenweg 1617 Brussel-audergem Bruxelles-Capitale 1160",
    "addr:housenumber":"1617",
    "addr:postcode":"1160",
    "addr:street":"Waversesteenweg",
    "iso:country":"BE",
    "sg:address":"Waversesteenweg 1617",
    "sg:city":"Brussel-audergem",
    "sg:orig_category":"Huisdieren and benodigdheden Royal Canin",
    "sg:phone":"+32 2 673 21 19",
    "sg:postcode":"1160",
    "sg:province":"Bruxelles-Capitale",
    "wof:name":"Aqua Cichlid",
    "wof:placetype":"venue"
},
  "geometry": {"coordinates":[4.4212350845,50.8173065186],"type":"Point"}
}