{
  "type": "Feature",
  "properties": {
    "iso:country":"BE",
    "sg:address":"Place Du Vingt-ao\u00dbt 42",
    "sg:city":"Li\u00c8ge",
    "sg:orig_category":"Geschenken and souvenirs Meubelzaken, woning- and keukeninrichting Verlichting and huishoudartikelen",
    "sg:phone":"+32 4 223 49 77",
    "sg:postcode":"4000",
    "sg:province":"Li\u00e8ge",
    "wof:name":"Ex-centric",
    "wof:placetype":"venue"
},
  "geometry": {"coordinates":[5.5759239197,50.6394119263],"type":"Point"}
}