{
  "type": "Feature",
  "properties": {
    "iso:country":"BE",
    "sg:address":"Ommegangstraat 62",
    "sg:city":"Lochristi",
    "sg:classifiers":[
        {
            "category":"Health Services",
            "subcategory":"Dentist",
            "type":"Services"
        }
    ],
    "sg:phone":"+32 9 355 04 31",
    "sg:postcode":"9080",
    "sg:province":"Oost-Vlaanderen",
    "wof:name":"Timbremont Barbara",
    "wof:placetype":"venue"
},
  "geometry": {"coordinates":[3.8502318859,51.0858268738],"type":"Point"}
}