{
  "type": "Feature",
  "properties": {
    "iso:country":"BE",
    "sg:address":"Viide Olympiadelaan 38",
    "sg:city":"Antwerpen",
    "sg:classifiers":[
        {
            "category":"Health Services",
            "subcategory":"Doctor",
            "type":"Services"
        }
    ],
    "sg:phone":"+32 3 237 36 37",
    "sg:postcode":"2020",
    "sg:province":"Antwerpen",
    "sg:tags":[
        "medicinephysicians",
        "surgeon"
    ],
    "wof:name":"Florens L",
    "wof:placetype":"venue"
},
  "geometry": {"coordinates":[4.3871197701,51.1838912964],"type":"Point"}
}