{
  "type": "Feature",
  "properties": {
    "addr:full":"Rue De La Bach\u00e9e 84 Lasne (plancenoit) Brabant Wallon 1380",
    "addr:housenumber":"84",
    "addr:postcode":"1380",
    "addr:street":"Rue De La Bache\u0301E",
    "iso:country":"BE",
    "sg:address":"Rue De La Bach\u00e9e 84",
    "sg:city":"Lasne (plancenoit)",
    "sg:classifiers":[
        {
            "category":"Professional",
            "subcategory":"Testing Lab",
            "type":"Services"
        }
    ],
    "sg:phone":"+32 2 633 31 95",
    "sg:postcode":"1380",
    "sg:province":"Brabant Wallon",
    "sg:tags":[
        "chemist"
    ],
    "wof:name":"Taminiau C",
    "wof:placetype":"venue"
},
  "geometry": {"coordinates":[4.4228668213,50.6609039307],"type":"Point"}
}