{
  "type": "Feature",
  "properties": {
    "addr:full":"Rue De Roms\u00c9e 54 Fleron Li\u00e8ge 4620",
    "addr:housenumber":"54",
    "addr:postcode":"4620",
    "addr:street":"Rue De Romse\u0301E",
    "iso:country":"BE",
    "sg:address":"Rue De Roms\u00c9e 54",
    "sg:city":"Fleron",
    "sg:orig_category":"Kapsalons",
    "sg:phone":"+32 4 358 36 49",
    "sg:postcode":"4620",
    "sg:province":"Li\u00e8ge",
    "wof:name":"Coiffure Mar\u00c9chal",
    "wof:placetype":"venue"
},
  "geometry": {"coordinates":[5.6742720604,50.6128196716],"type":"Point"}
}