{
  "type": "Feature",
  "properties": {
    "iso:country":"BE",
    "sg:address":"Rue Xhov\u00e9mont 26",
    "sg:city":"Li\u00e8ge 1",
    "sg:classifiers":[
        {
            "category":"Real Estate",
            "subcategory":"Real Estate Services",
            "type":"Services"
        }
    ],
    "sg:phone":"+32 4 226 31 08",
    "sg:postcode":"4000",
    "sg:province":"Li\u00e8ge",
    "wof:name":"Citadelle (la)",
    "wof:placetype":"venue"
},
  "geometry": {"coordinates":[5.5653829575,50.6500396729],"type":"Point"}
}