{
  "type": "Feature",
  "properties": {
    "iso:country":"BE",
    "sg:address":"Beaulieu 11",
    "sg:city":"Tenneville",
    "sg:orig_category":"Rundveehouders",
    "sg:phone":"+32 84 45 56 84",
    "sg:postcode":"6972",
    "sg:province":"Luxembourg",
    "wof:name":"Jose Poncin",
    "wof:placetype":"venue"
},
  "geometry": {"coordinates":[5.5690231323,50.1207275391],"type":"Point"}
}