{
  "type": "Feature",
  "properties": {
    "addr:full":"Rue Du Calvaire 11 Leuze-en-hainaut Hainaut 7903",
    "addr:housenumber":"11",
    "addr:postcode":"7903",
    "addr:street":"Rue Du Calvaire",
    "iso:country":"BE",
    "sg:address":"Rue Du Calvaire 11",
    "sg:city":"Leuze-en-hainaut",
    "sg:orig_category":"Epiceries",
    "sg:phone":"+32 69 66 71 89",
    "sg:postcode":"7903",
    "sg:province":"Hainaut",
    "wof:name":"Isabelle Dubois",
    "wof:placetype":"venue"
},
  "geometry": {"coordinates":[3.6455359459,50.6161003113],"type":"Point"}
}