{
  "type": "Feature",
  "properties": {
    "addr:full":"4920 Aywaille (groot) Li\u00e8ge 4920",
    "addr:postcode":"4920;4920",
    "addr:street":"Groot Lie\u0300Ge",
    "iso:country":"BE",
    "sg:address":"4920",
    "sg:city":"Aywaille (groot)",
    "sg:orig_category":"Pharmaciens",
    "sg:phone":"+32 900 10 500",
    "sg:postcode":"4920",
    "sg:province":"Li\u00e8ge",
    "wof:name":"Pharmacies De Garde",
    "wof:placetype":"venue"
},
  "geometry": {"coordinates":[5.6782069206,50.4738540649],"type":"Point"}
}