{
  "type": "Feature",
  "properties": {
    "iso:country":"BE",
    "sg:address":"Sympathiestraat 49",
    "sg:city":"Anderlecht/anderlecht",
    "sg:orig_category":"Drukkerijen and copyshops",
    "sg:phone":"+32 2 521 09 15",
    "sg:postcode":"1070",
    "sg:province":"Bruxelles-Capitale",
    "wof:name":"Impr. Wyckmans L. & Cie",
    "wof:placetype":"venue"
},
  "geometry": {"coordinates":[4.3010601997,50.8229103088],"type":"Point"}
}