{
  "type": "Feature",
  "properties": {
    "addr:full":"Puursesteenweg 391 Bornem Antwerpen 2880",
    "addr:housenumber":"391",
    "addr:postcode":"2880",
    "addr:street":"Puursesteenweg",
    "iso:country":"BE",
    "sg:address":"Puursesteenweg 391",
    "sg:city":"Bornem",
    "sg:classifiers":[
        {
            "category":"Manufacturing",
            "subcategory":"Wood Products",
            "type":"Manufacturing & Wholesale Goods"
        }
    ],
    "sg:phone":"+32 3 889 01 27",
    "sg:postcode":"2880",
    "sg:province":"Antwerpen",
    "sg:tags":[
        "gate",
        "made",
        "door"
    ],
    "wof:name":"Theo Segers & Zoon Nv",
    "wof:placetype":"venue"
},
  "geometry": {"coordinates":[4.2628259659,51.0858612061],"type":"Point"}
}