{
  "type": "Feature",
  "properties": {
    "iso:country":"BE",
    "sg:address":"Sint-pauluslaan 95",
    "sg:city":"Tervuren",
    "sg:classifiers":[
        {
            "category":"Insurance",
            "subcategory":"Life Insurance",
            "type":"Services"
        }
    ],
    "sg:phone":"+32 2 767 80 74",
    "sg:postcode":"3080",
    "sg:province":"Vlaams-Brabant",
    "sg:tags":[
        "assurance"
    ],
    "wof:name":"Verz. Ach\u00c9-van Hellemont",
    "wof:placetype":"venue"
},
  "geometry": {"coordinates":[4.5454621315,50.8370666504],"type":"Point"}
}