{
  "type": "Feature",
  "properties": {
    "iso:country":"BE",
    "sg:address":"Rue De Burenville 110",
    "sg:city":"Li\u00c8ge",
    "sg:orig_category":"Ordinateurs and \u00e9quipement informatique",
    "sg:phone":"+32 4 225 93 33",
    "sg:postcode":"4000",
    "sg:province":"Li\u00e8ge",
    "wof:name":"All Tech Info",
    "wof:placetype":"venue"
},
  "geometry": {"coordinates":[5.5413761139,50.6398010254],"type":"Point"}
}