{
  "type": "Feature",
  "properties": {
    "addr:full":"Place Du Jeu De Balle 15 Brussel/bruxelles Bruxelles-Capitale 1000",
    "addr:housenumber":"15",
    "addr:postcode":"1000",
    "addr:street":"Place Du Jeu De Balle;/",
    "iso:country":"BE",
    "sg:address":"Place Du Jeu De Balle 15",
    "sg:city":"Brussel/bruxelles",
    "sg:orig_category":"RESTAURANTS: H\u00d4TELS",
    "sg:phone":"+32 2 502 42 43",
    "sg:postcode":"1000",
    "sg:province":"Bruxelles-Capitale",
    "wof:name":"H\u00d4tel R\u00c9sidence Galia",
    "wof:placetype":"venue"
},
  "geometry": {"coordinates":[4.346244812,50.837688446],"type":"Point"}
}