{
  "type": "Feature",
  "properties": {
    "addr:full":"Bierbeekstraat 116 Bierbeek Vlaams-Brabant 3360",
    "addr:housenumber":"116",
    "addr:postcode":"3360",
    "addr:street":"Bierbeekstraat",
    "iso:country":"BE",
    "sg:address":"Bierbeekstraat 116",
    "sg:city":"Bierbeek",
    "sg:orig_category":"M\u00e9decins and sp\u00e9cialistes",
    "sg:phone":"+32 16 46 10 68",
    "sg:postcode":"3360",
    "sg:province":"Vlaams-Brabant",
    "wof:name":"J. Nijs",
    "wof:placetype":"venue"
},
  "geometry": {"coordinates":[4.7611188889,50.857334137],"type":"Point"}
}