{
  "type": "Feature",
  "properties": {
    "addr:full":"Jagerstraat 1 Temse Oost-Vlaanderen 9140",
    "addr:housenumber":"1",
    "addr:postcode":"9140",
    "addr:street":"Jagerstraat",
    "iso:country":"BE",
    "sg:address":"Jagerstraat 1",
    "sg:city":"Temse",
    "sg:orig_category":"Rundveehouders",
    "sg:phone":"+32 3 771 22 63",
    "sg:postcode":"9140",
    "sg:province":"Oost-Vlaanderen",
    "wof:name":"Karel Lambers",
    "wof:placetype":"venue"
},
  "geometry": {"coordinates":[4.1797471046,51.1251945496],"type":"Point"}
}