{
  "type": "Feature",
  "properties": {
    "addr:full":"Rue De Mons 93 Tubize Brabant Wallon 1480",
    "addr:housenumber":"93",
    "addr:postcode":"1480",
    "addr:street":"Rue De Mons;Wallon",
    "iso:country":"BE",
    "sg:address":"Rue De Mons 93",
    "sg:city":"Tubize",
    "sg:orig_category":"Vakbonden",
    "sg:phone":"+32 2 355 69 60",
    "sg:postcode":"1480",
    "sg:province":"Brabant Wallon",
    "wof:name":"F.g.t.b.-alimentation",
    "wof:placetype":"venue"
},
  "geometry": {"coordinates":[4.2017869949,50.6900177002],"type":"Point"}
}