{
  "type": "Feature",
  "properties": {
    "iso:country":"BE",
    "sg:address":"Rue L\u00e9opold Et Victorien Barr\u00e9 6",
    "sg:city":"Dinant",
    "sg:classifiers":[
        {
            "category":"Arena",
            "subcategory":"Sports Club",
            "type":"Entertainment"
        }
    ],
    "sg:phone":"+32 82 22 59 45",
    "sg:postcode":"5500",
    "sg:province":"Namur",
    "wof:name":"Bala'tya",
    "wof:placetype":"venue"
},
  "geometry": {"coordinates":[4.9093489647,50.2634048462],"type":"Point"}
}