{
  "type": "Feature",
  "properties": {
    "iso:country":"BE",
    "sg:address":"Maastrichterstraat 117",
    "sg:city":"Tongeren",
    "sg:classifiers":[
        {
            "category":"Shopping",
            "subcategory":"Jewelry",
            "type":"Retail Goods"
        }
    ],
    "sg:phone":"+32 12 23 19 16",
    "sg:postcode":"3700",
    "sg:province":"Limburg",
    "sg:tags":[
        "jeweller",
        "-"
    ],
    "wof:name":"Houbrechts",
    "wof:placetype":"venue"
},
  "geometry": {"coordinates":[5.469037056,50.7826881409],"type":"Point"}
}