{
  "type": "Feature",
  "properties": {
    "iso:country":"BE",
    "sg:address":"Zuidburgweg 14",
    "sg:city":"Veurne",
    "sg:classifiers":[
        {
            "category":"Professional",
            "subcategory":"Computer Services",
            "type":"Services"
        }
    ],
    "sg:phone":"+32 58 31 20 14",
    "sg:postcode":"8630",
    "sg:province":"West-Vlaanderen",
    "sg:tags":[
        "-",
        "processing",
        "data",
        "software"
    ],
    "wof:name":"Soft@work Com V",
    "wof:placetype":"venue"
},
  "geometry": {"coordinates":[2.6688990593,51.0686531067],"type":"Point"}
}