{
  "type": "Feature",
  "properties": {
    "iso:country":"BE",
    "sg:address":"Boetendaellaan 72",
    "sg:city":"Ukkel/uccle",
    "sg:orig_category":"Advocaten and juridische adviseurs",
    "sg:phone":"+32 2 344 03 91",
    "sg:postcode":"1180",
    "sg:province":"Bruxelles-Capitale",
    "wof:name":"Y. Strypstein",
    "wof:placetype":"venue"
},
  "geometry": {"coordinates":[4.3446121216,50.8059196472],"type":"Point"}
}