{
  "type": "Feature",
  "properties": {
    "addr:full":"Veldstraat 61 Lochristi Oost-Vlaanderen 9080",
    "addr:housenumber":"61",
    "addr:postcode":"9080",
    "addr:street":"Veldstraat",
    "iso:country":"BE",
    "sg:address":"Veldstraat 61",
    "sg:city":"Lochristi",
    "sg:classifiers":[
        {
            "category":"Wholesale",
            "subcategory":"Plants",
            "type":"Manufacturing & Wholesale Goods"
        }
    ],
    "sg:phone":"+32 9 355 76 30",
    "sg:postcode":"9080",
    "sg:province":"Oost-Vlaanderen",
    "sg:tags":[
        "whol",
        "flower",
        "-",
        "grower"
    ],
    "wof:name":"De Schoenmacker J",
    "wof:placetype":"venue"
},
  "geometry": {"coordinates":[3.7951769829,51.1015586853],"type":"Point"}
}