{
  "type": "Feature",
  "properties": {
    "iso:country":"BE",
    "sg:address":"Boulevard Edmond Machtens 57 Box 17",
    "sg:city":"Bruxelles (molenbeek-saint-jean)",
    "sg:classifiers":[
        {
            "category":"Professional",
            "subcategory":"Lawyer & Legal Services",
            "type":"Services"
        }
    ],
    "sg:phone":"+32 2 410 20 05",
    "sg:postcode":"1080",
    "sg:province":"Bruxelles-Capitale",
    "sg:tags":[
        "notary"
    ],
    "wof:name":"Vermeulen P",
    "wof:placetype":"venue"
},
  "geometry": {"coordinates":[4.3156352043,50.8521347046],"type":"Point"}
}