{
  "type": "Feature",
  "properties": {
    "addr:full":"Reimenhof 35 Houthalen-helchteren Limburg 3530",
    "addr:housenumber":"35",
    "addr:postcode":"3530",
    "addr:street":"Reimenhof",
    "iso:country":"BE",
    "sg:address":"Reimenhof 35",
    "sg:city":"Houthalen-helchteren",
    "sg:orig_category":"Fabrication and montage de mobilier. Electrom\u00e9nager, t\u00e9l\u00e9visions and radios",
    "sg:phone":"+32 11 52 37 91",
    "sg:postcode":"3530",
    "sg:province":"Limburg",
    "wof:name":"Jean Coppieters",
    "wof:placetype":"venue"
},
  "geometry": {"coordinates":[5.3768768311,51.0269737244],"type":"Point"}
}