{
  "type": "Feature",
  "properties": {
    "addr:full":"Gaarshof 30 Hoogstraten Antwerpen 2321",
    "addr:housenumber":"30",
    "addr:postcode":"2321",
    "addr:street":"Gaarshof",
    "iso:country":"BE",
    "sg:address":"Gaarshof 30",
    "sg:city":"Hoogstraten",
    "sg:orig_category":"Producteurs de fruits",
    "sg:phone":"+32 3 315 92 36",
    "sg:postcode":"2321",
    "sg:province":"Antwerpen",
    "wof:name":"Sebastiaan Pluym",
    "wof:placetype":"venue"
},
  "geometry": {"coordinates":[4.7311000824,51.4617652893],"type":"Point"}
}