{
  "type": "Feature",
  "properties": {
    "addr:full":"Noordstraat 2 Gent Oost-Vlaanderen 9000",
    "addr:housenumber":"2",
    "addr:postcode":"9000",
    "addr:street":"Noordstraat;Oost-Vlaanderen",
    "iso:country":"BE",
    "sg:address":"Noordstraat 2",
    "sg:city":"Gent",
    "sg:orig_category":"HERSTELLING ELEKTRISCHE HUISHOUDAPPARATEN Telecommunicatieapparaten",
    "sg:phone":"+32 9 223 03 73",
    "sg:postcode":"9000",
    "sg:province":"Oost-Vlaanderen",
    "wof:name":"Devi",
    "wof:placetype":"venue"
},
  "geometry": {"coordinates":[3.7096459866,51.0568847656],"type":"Point"}
}