{
  "type": "Feature",
  "properties": {
    "iso:country":"BE",
    "sg:address":"Torhoutbaan 152",
    "sg:city":"Ichtegem",
    "sg:classifiers":[
        {
            "category":"Banks & Credit Unions",
            "subcategory":"Investment Brokerage",
            "type":"Services"
        }
    ],
    "sg:phone":"+32 50 22 12 25",
    "sg:postcode":"8480",
    "sg:province":"West-Vlaanderen",
    "sg:tags":[
        "printing",
        "-"
    ],
    "wof:name":"Cyber Press",
    "wof:placetype":"venue"
},
  "geometry": {"coordinates":[3.0495100021,51.0903663635],"type":"Point"}
}