{
  "type": "Feature",
  "properties": {
    "addr:full":"Jacob De Roorestraat 2 Edegem Antwerpen 2650",
    "addr:housenumber":"2",
    "addr:postcode":"2650",
    "addr:street":"Jacob De Roorestraat",
    "iso:country":"BE",
    "sg:address":"Jacob De Roorestraat 2",
    "sg:city":"Edegem",
    "sg:classifiers":[
        {
            "category":"Arena",
            "subcategory":"Sports Club",
            "type":"Entertainment"
        }
    ],
    "sg:phone":"+32 3 449 90 38",
    "sg:postcode":"2650",
    "sg:province":"Antwerpen",
    "wof:name":"Voorwaarts Kc",
    "wof:placetype":"venue"
},
  "geometry": {"coordinates":[4.4366998672,51.1692581177],"type":"Point"}
}