{
  "type": "Feature",
  "properties": {
    "addr:full":"Ottergemsesteenweg 439 Gent Oost-Vlaanderen 9000",
    "addr:housenumber":"439",
    "addr:postcode":"9000",
    "addr:street":"Ottergemsesteenweg;Oost-Vlaanderen",
    "iso:country":"BE",
    "sg:address":"Ottergemsesteenweg 439",
    "sg:city":"Gent",
    "sg:orig_category":"Non-Classified Establishments",
    "sg:phone":"+32 9 282 97 00",
    "sg:postcode":"9000",
    "sg:province":"Oost-Vlaanderen",
    "wof:name":"Data Papier",
    "wof:placetype":"venue"
},
  "geometry": {"coordinates":[3.7334580421,51.0267562866],"type":"Point"}
}