{
  "type": "Feature",
  "properties": {
    "iso:country":"BE",
    "sg:address":"Place Albert I 24",
    "sg:city":"Charleroi (monceau-sur-sambre)",
    "sg:classifiers":[
        {
            "category":"Bars & Pubs",
            "type":"Food & Drink"
        }
    ],
    "sg:phone":"+32 71 70 18 28",
    "sg:postcode":"6031",
    "sg:province":"Hainaut",
    "wof:name":"Ancienne Fanfare",
    "wof:placetype":"venue"
},
  "geometry": {"coordinates":[4.38022995,50.4121742249],"type":"Point"}
}