{
  "type": "Feature",
  "properties": {
    "addr:full":"Rue Des Messes 38 Ans Li\u00e8ge 4432",
    "addr:housenumber":"38",
    "addr:postcode":"4432",
    "addr:street":"Rue Des Messes",
    "iso:country":"BE",
    "sg:address":"Rue Des Messes 38",
    "sg:city":"Ans",
    "sg:classifiers":[
        {
            "category":"Fast Food",
            "type":"Food & Drink"
        }
    ],
    "sg:phone":"+32 4 263 80 62",
    "sg:postcode":"4432",
    "sg:province":"Li\u00e8ge",
    "sg:tags":[
        "meeneem",
        "restaurant"
    ],
    "wof:name":"Friterie Chez Matt",
    "wof:placetype":"venue"
},
  "geometry": {"coordinates":[5.5143899918,50.6740608215],"type":"Point"}
}