{
  "type": "Feature",
  "properties": {
    "addr:full":"Route Provinciale 18 Wavre Brabant Wallon 1300",
    "addr:housenumber":"1300",
    "addr:street":"Route Provinciale 18",
    "iso:country":"BE",
    "sg:address":"Route Provinciale 18",
    "sg:city":"Wavre",
    "sg:orig_category":"Kapsalons",
    "sg:phone":"+32 10 22 27 45",
    "sg:postcode":"1300",
    "sg:province":"Brabant Wallon",
    "wof:name":"Marc Delcroix",
    "wof:placetype":"venue"
},
  "geometry": {"coordinates":[4.6041297913,50.7136688232],"type":"Point"}
}