{
  "type": "Feature",
  "properties": {
    "addr:full":"Kerkstraat 2 Beveren Oost-Vlaanderen 9120",
    "addr:housenumber":"2",
    "addr:postcode":"9120",
    "addr:street":"Kerkstraat",
    "iso:country":"BE",
    "sg:address":"Kerkstraat 2",
    "sg:city":"Beveren",
    "sg:classifiers":[
        {
            "category":"Cafe",
            "type":"Food & Drink"
        }
    ],
    "sg:phone":"+32 3 775 88 71",
    "sg:postcode":"9120",
    "sg:province":"Oost-Vlaanderen",
    "sg:tags":[
        "caf\u00e9s"
    ],
    "wof:name":"Brouwershuis",
    "wof:placetype":"venue"
},
  "geometry": {"coordinates":[4.1945128441,51.2191581726],"type":"Point"}
}