{
  "type": "Feature",
  "properties": {
    "addr:full":"Nonnenbosstraat 55 Lede Oost-Vlaanderen 9340",
    "addr:housenumber":"55",
    "addr:postcode":"9340",
    "addr:street":"Nonnenbosstraat",
    "iso:country":"BE",
    "sg:address":"Nonnenbosstraat 55",
    "sg:city":"Lede",
    "sg:orig_category":"Artiesten and kunstenaars",
    "sg:phone":"+32 53 80 22 58",
    "sg:postcode":"9340",
    "sg:province":"Oost-Vlaanderen",
    "wof:name":"Melckenbeek",
    "wof:placetype":"venue"
},
  "geometry": {"coordinates":[3.9568350315,50.9781150818],"type":"Point"}
}