{
  "type": "Feature",
  "properties": {
    "iso:country":"BE",
    "sg:address":"Windmolenstraat 64",
    "sg:city":"Mol",
    "sg:classifiers":[
        {
            "category":"Professional",
            "subcategory":"Engineering",
            "type":"Services"
        }
    ],
    "sg:phone":"+32 14 31 67 81",
    "sg:postcode":"2400",
    "sg:province":"Antwerpen",
    "sg:tags":[
        "civil",
        "offices-"
    ],
    "wof:name":"Studiebureel Ir Luysterborg",
    "wof:placetype":"venue"
},
  "geometry": {"coordinates":[5.0892071724,51.1692581177],"type":"Point"}
}