{
  "type": "Feature",
  "properties": {
    "iso:country":"BE",
    "sg:address":"Dorpsplaats 0",
    "sg:city":"Malle",
    "sg:classifiers":[
        {
            "category":"Fast Food",
            "type":"Food & Drink"
        }
    ],
    "sg:phone":"+32 3 309 16 96",
    "sg:postcode":"2390",
    "sg:province":"Antwerpen",
    "sg:tags":[
        "\u00c0",
        "emporter",
        "restaurants"
    ],
    "wof:name":"\u00b4t Kruispunt",
    "wof:placetype":"venue"
},
  "geometry": {"coordinates":[4.7343788147,51.302570343],"type":"Point"}
}