{
  "type": "Feature",
  "properties": {
    "addr:full":"Chauss\u00e9e De Neufch\u00e2teau 52 Vaux-sur-s\u00fbre (vaux-lez-rosi\u00e8res) Luxembourg 6640",
    "addr:housenumber":"52",
    "addr:postcode":"6640",
    "addr:street":"Chausse\u0301E De Neufcha\u0302Teau",
    "iso:country":"BE",
    "sg:address":"Chauss\u00e9e De Neufch\u00e2teau 52",
    "sg:city":"Vaux-sur-s\u00fbre (vaux-lez-rosi\u00e8res)",
    "sg:classifiers":[
        {
            "category":"Professional",
            "subcategory":"Art Services",
            "type":"Services"
        }
    ],
    "sg:phone":"+32 61 25 52 62",
    "sg:postcode":"6640",
    "sg:province":"Luxembourg",
    "sg:tags":[
        "interior",
        "designer"
    ],
    "wof:name":"Arch\u00e9type",
    "wof:placetype":"venue"
},
  "geometry": {"coordinates":[5.559720993,49.9088745117],"type":"Point"}
}