{
  "type": "Feature",
  "properties": {
    "addr:full":"Rue Van Opr\u00c9 97 Namur Namur 5100",
    "addr:housenumber":"97",
    "addr:postcode":"5100",
    "addr:street":"Rue Van Opre\u0301",
    "iso:country":"BE",
    "sg:address":"Rue Van Opr\u00c9 97",
    "sg:city":"Namur",
    "sg:orig_category":"Artsen and specialisten",
    "sg:phone":"+32 81 30 02 61",
    "sg:postcode":"5100",
    "sg:province":"Namur",
    "wof:name":"Jo\u00cblle Sarot",
    "wof:placetype":"venue"
},
  "geometry": {"coordinates":[4.8759670258,50.4609184265],"type":"Point"}
}