{
  "type": "Feature",
  "properties": {
    "addr:full":"Avenue Joseph Van Genegen 14 Bruxelles (woluwe-saint-pierre) Bruxelles-Capitale 1150",
    "addr:housenumber":"14",
    "addr:postcode":"1150",
    "addr:street":"Avenue Joseph Van Genegen",
    "iso:country":"BE",
    "sg:address":"Avenue Joseph Van Genegen 14",
    "sg:city":"Bruxelles (woluwe-saint-pierre)",
    "sg:classifiers":[
        {
            "category":"Professional",
            "subcategory":"Management & Consulting",
            "type":"Services"
        }
    ],
    "sg:phone":"+32 2 762 28 68",
    "sg:postcode":"1150",
    "sg:province":"Bruxelles-Capitale",
    "sg:tags":[
        "consultant"
    ],
    "wof:name":"Coris",
    "wof:placetype":"venue"
},
  "geometry": {"coordinates":[4.4499611855,50.8329467773],"type":"Point"}
}