{
  "type": "Feature",
  "properties": {
    "addr:full":"Brugsesteenweg 363 Roeselare West-Vlaanderen 8400",
    "addr:housenumber":"363",
    "addr:postcode":"8400",
    "addr:street":"Brugsesteenweg",
    "iso:country":"BE",
    "sg:address":"Brugsesteenweg 363",
    "sg:city":"Roeselare",
    "sg:orig_category":"Chaussures",
    "sg:phone":"+32 51 24 49 99",
    "sg:postcode":"8400",
    "sg:province":"West-Vlaanderen",
    "wof:name":"Super Shoe",
    "wof:placetype":"venue"
},
  "geometry": {"coordinates":[3.1204900742,50.9635124207],"type":"Point"}
}