{
  "type": "Feature",
  "properties": {
    "addr:full":"Kruiskedreef 1 Moorslede West-Vlaanderen 8890",
    "addr:housenumber":"1",
    "addr:postcode":"8890",
    "addr:street":"Kruiskedreef",
    "iso:country":"BE",
    "sg:address":"Kruiskedreef 1",
    "sg:city":"Moorslede",
    "sg:orig_category":"Rundveehouders",
    "sg:phone":"+32 51 77 70 87",
    "sg:postcode":"8890",
    "sg:province":"West-Vlaanderen",
    "wof:name":"Luc Hemeryck",
    "wof:placetype":"venue"
},
  "geometry": {"coordinates":[3.0730578899,50.9109649658],"type":"Point"}
}