{
  "type": "Feature",
  "properties": {
    "iso:country":"BE",
    "sg:address":"Chauss\u00c9e De Louvain 205",
    "sg:city":"Waterloo",
    "sg:orig_category":"Installation de menuiserie en bois and plastique",
    "sg:phone":"+32 2 351 45 59",
    "sg:postcode":"1410",
    "sg:province":"Brabant Wallon",
    "wof:name":"Fe. Denys-palissandre",
    "wof:placetype":"venue"
},
  "geometry": {"coordinates":[4.4209990501,50.6970024109],"type":"Point"}
}