{
  "type": "Feature",
  "properties": {
    "addr:full":"Avenue Des Princes 30-32 Wavre Brabant Wallon 1300",
    "addr:housenumber":"1300",
    "addr:postcode":"30-32",
    "addr:street":"Avenue Des Princes",
    "iso:country":"BE",
    "sg:address":"Avenue Des Princes 30-32",
    "sg:city":"Wavre",
    "sg:classifiers":[
        {
            "category":"Home & Garden",
            "subcategory":"Household Appliances",
            "type":"Retail Goods"
        }
    ],
    "sg:phone":"+32 10 22 36 11",
    "sg:postcode":"1300",
    "sg:province":"Brabant Wallon",
    "sg:tags":[
        "housewares",
        "-"
    ],
    "wof:name":"Lenaerts",
    "wof:placetype":"venue"
},
  "geometry": {"coordinates":[4.6161999702,50.7162742615],"type":"Point"}
}