{
  "type": "Feature",
  "properties": {
    "addr:full":"Rue De La Poste 91-93 Bruxelles (schaerbeek) Bruxelles-Capitale 1030",
    "addr:postcode":"91-93;1030",
    "addr:street":"Rue De La Poste",
    "iso:country":"BE",
    "sg:address":"Rue De La Poste 91-93",
    "sg:city":"Bruxelles (schaerbeek)",
    "sg:classifiers":[
        {
            "category":"Education",
            "subcategory":"School",
            "type":"Public Place"
        }
    ],
    "sg:phone":"+32 2 218 78 49",
    "sg:postcode":"1030",
    "sg:province":"Bruxelles-Capitale",
    "sg:tags":[
        "secondary"
    ],
    "wof:name":"St Jean Et Nicolas",
    "wof:placetype":"venue"
},
  "geometry": {"coordinates":[4.3672099113,50.8581008911],"type":"Point"}
}