{
  "type": "Feature",
  "properties": {
    "addr:full":"Beukenhofstraat 77 Anzegem (vichte) West-Vlaanderen 8570",
    "addr:housenumber":"77",
    "addr:postcode":"8570",
    "addr:street":"Beukenhofstraat",
    "iso:country":"BE",
    "sg:address":"Beukenhofstraat 77",
    "sg:city":"Anzegem (vichte)",
    "sg:classifiers":[
        {
            "category":"Manufacturing",
            "subcategory":"Textiles",
            "type":"Manufacturing & Wholesale Goods"
        }
    ],
    "sg:phone":"+32 56 78 26 20",
    "sg:postcode":"8570",
    "sg:province":"West-Vlaanderen",
    "sg:tags":[
        "technical"
    ],
    "wof:name":"Steverlynck Stukverf",
    "wof:placetype":"venue"
},
  "geometry": {"coordinates":[3.3903169632,50.8329772949],"type":"Point"}
}