{
  "type": "Feature",
  "properties": {
    "iso:country":"BE",
    "sg:address":"Kaaiplein 3",
    "sg:city":"Zwijndrecht (burcht)",
    "sg:classifiers":[
        {
            "category":"Bars & Pubs",
            "type":"Food & Drink"
        }
    ],
    "sg:phone":"+32 3 254 04 39",
    "sg:postcode":"2070",
    "sg:province":"Antwerpen",
    "wof:name":"Violetta",
    "wof:placetype":"venue"
},
  "geometry": {"coordinates":[4.3498930931,51.2021369934],"type":"Point"}
}