{
  "type": "Feature",
  "properties": {
    "iso:country":"BE",
    "sg:address":"Rue Des Aises 66",
    "sg:city":"Charleroi (gilly)",
    "sg:classifiers":[
        {
            "category":"Shopping",
            "subcategory":"Discount & Variety Stores",
            "type":"Retail Goods"
        }
    ],
    "sg:phone":"+32 71 48 98 13",
    "sg:postcode":"6060",
    "sg:province":"Hainaut",
    "sg:tags":[
        "warehouse",
        "-",
        "merchandise"
    ],
    "wof:name":"Soditra Logistic",
    "wof:placetype":"venue"
},
  "geometry": {"coordinates":[4.4880981445,50.4251937866],"type":"Point"}
}