{
  "type": "Feature",
  "properties": {
    "iso:country":"BE",
    "sg:address":"Kleine Marktstraat 4",
    "sg:city":"Kortrijk (marke)",
    "sg:classifiers":[
        {
            "category":"Community Center",
            "subcategory":"Youth",
            "type":"Public Place"
        }
    ],
    "sg:phone":"+32 56 22 41 28",
    "sg:postcode":"8510",
    "sg:province":"West-Vlaanderen",
    "sg:tags":[
        "club"
    ],
    "wof:name":"Verblijfshoeve Marke",
    "wof:placetype":"venue"
},
  "geometry": {"coordinates":[3.2374858856,50.8120079041],"type":"Point"}
}