{
  "type": "Feature",
  "properties": {
    "iso:country":"BE",
    "sg:address":"Chauss\u00c9e De Gilly 375",
    "sg:city":"Fleurus",
    "sg:orig_category":"Plomberie, chauffage and installations sanitaires",
    "sg:phone":"+32 71 39 29 25",
    "sg:postcode":"6220",
    "sg:province":"Hainaut",
    "wof:name":"Angelo Fanara",
    "wof:placetype":"venue"
},
  "geometry": {"coordinates":[4.5166969299,50.4441490173],"type":"Point"}
}