{
  "type": "Feature",
  "properties": {
    "iso:country":"BE",
    "sg:address":"Rue Plaine Des Sports 64",
    "sg:city":"Wezembeek-oppem",
    "sg:classifiers":[
        {
            "category":"Professional",
            "subcategory":"Management & Consulting",
            "type":"Services"
        }
    ],
    "sg:phone":"+32 2 782 18 91",
    "sg:postcode":"1970",
    "sg:province":"Vlaams-Brabant",
    "sg:tags":[
        "consultant"
    ],
    "wof:name":"Alpha Management & Consulting Services Bvba",
    "wof:placetype":"venue"
},
  "geometry": {"coordinates":[4.4865398407,50.8424987793],"type":"Point"}
}