{
  "type": "Feature",
  "properties": {
    "iso:country":"BE",
    "sg:address":"Chrysantenlaan 31",
    "sg:city":"Mol",
    "sg:classifiers":[
        {
            "category":"Real Estate",
            "subcategory":"Architect",
            "type":"Services"
        }
    ],
    "sg:phone":"+32 14 31 62 87",
    "sg:postcode":"2400",
    "sg:province":"Antwerpen",
    "wof:name":"Verbist J",
    "wof:placetype":"venue"
},
  "geometry": {"coordinates":[5.1176919937,51.195022583],"type":"Point"}
}