{
  "type": "Feature",
  "properties": {
    "iso:country":"BE",
    "sg:address":"Quai De L'escaut 5",
    "sg:city":"Espierres-helchin (helchin)",
    "sg:classifiers":[
        {
            "category":"Manufacturing",
            "subcategory":"Tobacco Products",
            "type":"Manufacturing & Wholesale Goods"
        }
    ],
    "sg:phone":"+32 56 45 50 28",
    "sg:postcode":"8587",
    "sg:province":"West-Vlaanderen",
    "sg:tags":[
        "fertilizer",
        "merchant",
        "-"
    ],
    "wof:name":"Delbecque F & Zn Bvba",
    "wof:placetype":"venue"
},
  "geometry": {"coordinates":[3.3765869141,50.7291641235],"type":"Point"}
}