{
  "type": "Feature",
  "properties": {
    "iso:country":"BE",
    "sg:address":"Keiheuvelstraat 4a",
    "sg:city":"Mol",
    "sg:classifiers":[
        {
            "category":"Health Services",
            "subcategory":"Health Practitioner",
            "type":"Services"
        }
    ],
    "sg:phone":"+32 14 81 03 89",
    "sg:postcode":"2400",
    "sg:province":"Antwerpen",
    "sg:tags":[
        "physiotherapist"
    ],
    "wof:name":"Vos Margot",
    "wof:placetype":"venue"
},
  "geometry": {"coordinates":[5.2166910172,51.1925239563],"type":"Point"}
}