{
  "type": "Feature",
  "properties": {
    "iso:country":"BE",
    "sg:address":"Rue Monulphe 29",
    "sg:city":"Li\u00e8ge 1",
    "sg:classifiers":[
        {
            "category":"Arts & Performance",
            "subcategory":"Music",
            "type":"Entertainment"
        }
    ],
    "sg:phone":"+32 4 223 61 57",
    "sg:postcode":"4000",
    "sg:province":"Li\u00e8ge",
    "sg:tags":[
        "freelance",
        "musician"
    ],
    "wof:name":"Delhaye A",
    "wof:placetype":"venue"
},
  "geometry": {"coordinates":[5.5607662201,50.6394271851],"type":"Point"}
}