{
  "type": "Feature",
  "properties": {
    "iso:country":"BE",
    "sg:address":"Kasteelkaai 5",
    "sg:city":"Kortrijk",
    "sg:classifiers":[
        {
            "category":"Cafe",
            "type":"Food & Drink"
        }
    ],
    "sg:phone":"+32 56 21 96 74",
    "sg:postcode":"8500",
    "sg:province":"West-Vlaanderen",
    "sg:tags":[
        "caf\u00e9s"
    ],
    "wof:name":"Renault & Vandaele",
    "wof:placetype":"venue"
},
  "geometry": {"coordinates":[3.2618699074,50.8291778564],"type":"Point"}
}