{
  "type": "Feature",
  "properties": {
    "iso:country":"BE",
    "sg:address":"Stationsstraat 46",
    "sg:city":"Oudenaarde",
    "sg:orig_category":"Boucheries",
    "sg:phone":"+32 55 31 15 80",
    "sg:postcode":"9700",
    "sg:province":"Oost-Vlaanderen",
    "wof:name":"Beenhouwerij De Sloover",
    "wof:placetype":"venue"
},
  "geometry": {"coordinates":[3.6009349823,50.8491172791],"type":"Point"}
}