{
  "type": "Feature",
  "properties": {
    "addr:full":"Driftweg 19 De Haan West-Vlaanderen 8420",
    "addr:housenumber":"19",
    "addr:postcode":"8420",
    "addr:street":"Driftweg",
    "iso:country":"BE",
    "sg:address":"Driftweg 19",
    "sg:city":"De Haan",
    "sg:orig_category":"Fleurs and plantes. Eclairage et \u00e9quipements du foyer",
    "sg:phone":"+32 59 23 37 98",
    "sg:postcode":"8420",
    "sg:province":"West-Vlaanderen",
    "wof:name":"Huis Godri",
    "wof:placetype":"venue"
},
  "geometry": {"coordinates":[3.0320770741,51.2718544006],"type":"Point"}
}