{
  "type": "Feature",
  "properties": {
    "iso:country":"BE",
    "sg:address":"Pastoor Moernautstraat 4",
    "sg:city":"Lovendegem",
    "sg:orig_category":"Pain, p\u00e2tisseries and confiseries",
    "sg:phone":"+32 9 227 80 01",
    "sg:postcode":"9921",
    "sg:province":"Oost-Vlaanderen",
    "wof:name":"Bakkerij De Dapper",
    "wof:placetype":"venue"
},
  "geometry": {"coordinates":[3.6424849033,51.0870246887],"type":"Point"}
}