{
  "type": "Feature",
  "properties": {
    "addr:full":"Ch De Mons 93 Bruxelles Bruxelles-Capitale 1070",
    "addr:housenumber":"93",
    "addr:postcode":"1070",
    "addr:street":"Ch De Mons",
    "iso:country":"BE",
    "sg:address":"Ch De Mons 93",
    "sg:city":"Bruxelles",
    "sg:classifiers":[
        {
            "category":"Professional",
            "subcategory":"Engineering",
            "type":"Services"
        }
    ],
    "sg:phone":"+32 2 521 05 19",
    "sg:postcode":"1070",
    "sg:province":"Bruxelles-Capitale",
    "sg:tags":[
        "machine",
        "-",
        "mechanical"
    ],
    "wof:name":"Liverpool Carrosserie Sprl",
    "wof:placetype":"venue"
},
  "geometry": {"coordinates":[4.3338007927,50.8435249329],"type":"Point"}
}