{
  "type": "Feature",
  "properties": {
    "addr:full":"Max Havelaarlaan 8 Grimbergen Vlaams-Brabant 1850",
    "addr:housenumber":"8",
    "addr:postcode":"1850",
    "addr:street":"Max Havelaarlaan",
    "iso:country":"BE",
    "sg:address":"Max Havelaarlaan 8",
    "sg:city":"Grimbergen",
    "sg:classifiers":[
        {
            "category":"Health Services",
            "subcategory":"Health Practitioner",
            "type":"Services"
        }
    ],
    "sg:phone":"+32 2 270 84 20",
    "sg:postcode":"1850",
    "sg:province":"Vlaams-Brabant",
    "sg:tags":[
        "physiotherapist"
    ],
    "wof:name":"De Cuyper Jan & Pieter",
    "wof:placetype":"venue"
},
  "geometry": {"coordinates":[4.3743958473,50.9407997131],"type":"Point"}
}