{
  "type": "Feature",
  "properties": {
    "addr:full":"Rue Neuve Cour 16 Tubize Brabant Wallon 1480",
    "addr:housenumber":"16",
    "addr:postcode":"1480",
    "addr:street":"Rue Neuve Cour;Wallon",
    "iso:country":"BE",
    "sg:address":"Rue Neuve Cour 16",
    "sg:city":"Tubize",
    "sg:classifiers":[
        {
            "category":"Bakery",
            "type":"Food & Drink"
        }
    ],
    "sg:phone":"+32 2 355 45 68",
    "sg:postcode":"1480",
    "sg:province":"Brabant Wallon",
    "sg:tags":[
        "confectioner",
        "baker"
    ],
    "wof:name":"Langendries",
    "wof:placetype":"venue"
},
  "geometry": {"coordinates":[4.2021579742,50.6967544556],"type":"Point"}
}