{
  "type": "Feature",
  "properties": {
    "addr:full":"Boulevard Zenobe Gramme 96 Herstal Li\u00e8ge 4040",
    "addr:housenumber":"96",
    "addr:postcode":"4040",
    "addr:street":"Boulevard Zenobe Gramme",
    "iso:country":"BE",
    "sg:address":"Boulevard Zenobe Gramme 96",
    "sg:city":"Herstal",
    "sg:orig_category":"Entretien and r\u00e9parations de voitures",
    "sg:phone":"+32 4 264 04 00",
    "sg:postcode":"4040",
    "sg:province":"Li\u00e8ge",
    "wof:name":"Automobiles Martec",
    "wof:placetype":"venue"
},
  "geometry": {"coordinates":[5.6294898987,50.6607208252],"type":"Point"}
}