{
  "type": "Feature",
  "properties": {
    "iso:country":"BE",
    "sg:address":"Kriekelsheuvelstraat 76",
    "sg:city":"Maaseik",
    "sg:classifiers":[
        {
            "category":"Professional",
            "subcategory":"Accounting & Tax Preparation",
            "type":"Services"
        }
    ],
    "sg:phone":"+32 89 56 62 56",
    "sg:postcode":"3680",
    "sg:province":"Limburg",
    "sg:tags":[
        "bookkeeper"
    ],
    "wof:name":"Smolders E",
    "wof:placetype":"venue"
},
  "geometry": {"coordinates":[5.7713727951,51.1044960022],"type":"Point"}
}