{
  "type": "Feature",
  "properties": {
    "addr:full":"Rue De B\u00e9tissart 13 Ath (ormeignies) Hainaut 7802",
    "addr:housenumber":"13",
    "addr:postcode":"7802",
    "addr:street":"Rue De Be\u0301Tissart",
    "iso:country":"BE",
    "sg:address":"Rue De B\u00e9tissart 13",
    "sg:city":"Ath (ormeignies)",
    "sg:classifiers":[
        {
            "category":"Professional",
            "subcategory":"Lawyer & Legal Services",
            "type":"Services"
        }
    ],
    "sg:phone":"+32 68 28 20 80",
    "sg:postcode":"7802",
    "sg:province":"Hainaut",
    "sg:tags":[
        "notary"
    ],
    "wof:name":"Rose J",
    "wof:placetype":"venue"
},
  "geometry": {"coordinates":[3.7527279854,50.5938110352],"type":"Point"}
}