{
  "type": "Feature",
  "properties": {
    "iso:country":"BE",
    "sg:address":"Leemkuilstraat 21",
    "sg:city":"Alken",
    "sg:classifiers":[
        {
            "category":"Personal",
            "subcategory":"Beauty Salon",
            "type":"Services"
        }
    ],
    "sg:phone":"+32 11 59 38 90",
    "sg:postcode":"3570",
    "sg:province":"Limburg",
    "sg:tags":[
        "de",
        "coiffure"
    ],
    "wof:name":"Jochem Vanvoorden",
    "wof:placetype":"venue"
},
  "geometry": {"coordinates":[5.3230581284,50.8756828308],"type":"Point"}
}