{
  "type": "Feature",
  "properties": {
    "iso:country":"BE",
    "sg:address":"Rue De Vis\u00c9 273",
    "sg:city":"Voeren/fourons",
    "sg:classifiers":[
        {
            "category":"Arena",
            "subcategory":"Sports Club",
            "type":"Entertainment"
        }
    ],
    "sg:phone":"+32 4 381 01 29",
    "sg:postcode":"3790",
    "sg:province":"Limburg",
    "sg:tags":[
        "terrain",
        "hors",
        "de",
        "installation",
        "sportifs"
    ],
    "wof:name":"S.k. Moelingen",
    "wof:placetype":"venue"
},
  "geometry": {"coordinates":[5.8454608917,50.7517814636],"type":"Point"}
}