{
  "type": "Feature",
  "properties": {
    "addr:full":"Leopoldstadplein 17 Etterbeek Bruxelles-Capitale 1040",
    "addr:housenumber":"17",
    "addr:postcode":"1040",
    "addr:street":"Leopoldstadplein",
    "iso:country":"BE",
    "sg:address":"Leopoldstadplein 17",
    "sg:city":"Etterbeek",
    "sg:orig_category":"Artsen and specialisten",
    "sg:phone":"+32 2 649 00 01",
    "sg:postcode":"1040",
    "sg:province":"Bruxelles-Capitale",
    "wof:name":"Elisabeth Dugas",
    "wof:placetype":"venue"
},
  "geometry": {"coordinates":[4.3836731911,50.8283157349],"type":"Point"}
}