{
  "type": "Feature",
  "properties": {
    "iso:country":"BE",
    "sg:address":"Bredabaan 437",
    "sg:city":"Wuustwezel",
    "sg:orig_category":"V\u00eatements pour b\u00e9b\u00e9s and enfants",
    "sg:phone":"+32 3 669 56 43",
    "sg:postcode":"2990",
    "sg:province":"Antwerpen",
    "wof:name":"Swiggy's",
    "wof:placetype":"venue"
},
  "geometry": {"coordinates":[4.5923891068,51.3904495239],"type":"Point"}
}