{
  "type": "Feature",
  "properties": {
    "addr:full":"Vuurstraat 53 Vorst/forest Bruxelles-Capitale 1190",
    "addr:housenumber":"53",
    "addr:postcode":"1190",
    "addr:street":"Vuurstraat;/ Forest",
    "iso:country":"BE",
    "sg:address":"Vuurstraat 53",
    "sg:city":"Vorst/forest",
    "sg:orig_category":"Boekbinderijen and afwerking Drukkerijen and copyshops",
    "sg:phone":"+32 2 344 56 25",
    "sg:postcode":"1190",
    "sg:province":"Bruxelles-Capitale",
    "wof:name":"Euro Print Concept",
    "wof:placetype":"venue"
},
  "geometry": {"coordinates":[4.3232698441,50.8197288513],"type":"Point"}
}