{
  "type": "Feature",
  "properties": {
    "iso:country":"BE",
    "sg:address":"Rue Des Foulons 12",
    "sg:city":"Huy",
    "sg:classifiers":[
        {
            "category":"Utilities",
            "subcategory":"Natural Gas",
            "type":"Services"
        }
    ],
    "sg:phone":"+32 85 27 05 40",
    "sg:postcode":"4500",
    "sg:province":"Li\u00e8ge",
    "sg:tags":[
        "aerosol"
    ],
    "wof:name":"Medi-meuse",
    "wof:placetype":"venue"
},
  "geometry": {"coordinates":[5.2392311096,50.51612854],"type":"Point"}
}