{
  "type": "Feature",
  "properties": {
    "addr:full":"Eikstraat 45 Pepingen Vlaams-Brabant 1673",
    "addr:housenumber":"45",
    "addr:postcode":"1673",
    "addr:street":"Eikstraat",
    "iso:country":"BE",
    "sg:address":"Eikstraat 45",
    "sg:city":"Pepingen",
    "sg:orig_category":"Woningbouw",
    "sg:phone":"+32 2 361 14 78",
    "sg:postcode":"1673",
    "sg:province":"Vlaams-Brabant",
    "wof:name":"Bruno Vogeleer",
    "wof:placetype":"venue"
},
  "geometry": {"coordinates":[4.1828150749,50.7391242981],"type":"Point"}
}