{
  "type": "Feature",
  "properties": {
    "addr:full":"Sledderloweg 46 Genk Limburg 3600",
    "addr:housenumber":"46",
    "addr:postcode":"3600",
    "addr:street":"Sledderloweg",
    "iso:country":"BE",
    "sg:address":"Sledderloweg 46",
    "sg:city":"Genk",
    "sg:orig_category":"Pharmaciens",
    "sg:phone":"+32 89 35 32 50",
    "sg:postcode":"3600",
    "sg:province":"Limburg",
    "wof:name":"E. Bollen",
    "wof:placetype":"venue"
},
  "geometry": {"coordinates":[5.513338089,50.9503059387],"type":"Point"}
}