{
  "type": "Feature",
  "properties": {
    "addr:full":"Torhoutsesteenweg 90 Oostende West-Vlaanderen 8400",
    "addr:housenumber":"90",
    "addr:postcode":"8400",
    "addr:street":"Torhoutsesteenweg",
    "iso:country":"BE",
    "sg:address":"Torhoutsesteenweg 90",
    "sg:city":"Oostende",
    "sg:orig_category":"Swatch. Bijouteries and horlogeries",
    "sg:phone":"+32 59 70 49 55",
    "sg:postcode":"8400",
    "sg:province":"West-Vlaanderen",
    "wof:name":"'t Gouden Schip",
    "wof:placetype":"venue"
},
  "geometry": {"coordinates":[2.9088830948,51.2231559753],"type":"Point"}
}