{
  "type": "Feature",
  "properties": {
    "iso:country":"BE",
    "sg:address":"Rue De La Maye 9",
    "sg:city":"Herve",
    "sg:orig_category":"Eleveurs and marchands de porcs",
    "sg:phone":"+32 87 31 15 23",
    "sg:postcode":"4650",
    "sg:province":"Li\u00e8ge",
    "wof:name":"Jacqueline Brandt",
    "wof:placetype":"venue"
},
  "geometry": {"coordinates":[5.7942972183,50.6407928467],"type":"Point"}
}