{
  "type": "Feature",
  "properties": {
    "addr:full":"Rue Grande 83 Dinant Namur 5500",
    "addr:housenumber":"83",
    "addr:postcode":"5500",
    "addr:street":"Rue Grande",
    "iso:country":"BE",
    "sg:address":"Rue Grande 83",
    "sg:city":"Dinant",
    "sg:classifiers":[
        {
            "category":"Food & Beverages",
            "subcategory":"Chocolate",
            "type":"Retail Goods"
        }
    ],
    "sg:phone":"+32 82 22 63 44",
    "sg:postcode":"5500",
    "sg:province":"Namur",
    "sg:tags":[
        "confectionery",
        "-"
    ],
    "wof:name":"Amandine",
    "wof:placetype":"venue"
},
  "geometry": {"coordinates":[4.9143939018,50.2582435608],"type":"Point"}
}