{
  "type": "Feature",
  "properties": {
    "addr:full":"Place Des Franchises 4 Li\u00c8ge Li\u00e8ge 4000",
    "addr:housenumber":"4",
    "addr:postcode":"4000",
    "addr:street":"Place Des Franchises",
    "iso:country":"BE",
    "sg:address":"Place Des Franchises 4",
    "sg:city":"Li\u00c8ge",
    "sg:orig_category":"Artsen and specialisten",
    "sg:phone":"+32 4 252 12 35",
    "sg:postcode":"4000",
    "sg:province":"Li\u00e8ge",
    "wof:name":"Fabienne Lambert",
    "wof:placetype":"venue"
},
  "geometry": {"coordinates":[5.5705289841,50.6237449646],"type":"Point"}
}