{
  "type": "Feature",
  "properties": {
    "addr:full":"Steenweg Op Aalst 92 Zottegem Oost-Vlaanderen 9620",
    "addr:housenumber":"92",
    "addr:postcode":"9620",
    "addr:street":"Steenweg Op Aalst",
    "iso:country":"BE",
    "sg:address":"Steenweg Op Aalst 92",
    "sg:city":"Zottegem",
    "sg:orig_category":"Benzinestations and brandstoffen",
    "sg:phone":"+32 9 361 07 26",
    "sg:postcode":"9620",
    "sg:province":"Oost-Vlaanderen",
    "wof:name":"Fina",
    "wof:placetype":"venue"
},
  "geometry": {"coordinates":[3.8112111092,50.871181488],"type":"Point"}
}