{
  "type": "Feature",
  "properties": {
    "iso:country":"BE",
    "sg:address":"Avenue De Paepedelle 91",
    "sg:city":"Oudergem/auderghem",
    "sg:orig_category":"Filosofische and religieuze organisaties",
    "sg:phone":"+32 2 675 38 05",
    "sg:postcode":"1160",
    "sg:province":"Bruxelles-Capitale",
    "wof:name":"Institut Tib\u00c9tain",
    "wof:placetype":"venue"
},
  "geometry": {"coordinates":[4.4064202309,50.8220252991],"type":"Point"}
}