{
  "type": "Feature",
  "properties": {
    "addr:full":"Weverslaan 30 Lokeren Oost-Vlaanderen 9160",
    "addr:housenumber":"30",
    "addr:postcode":"9160",
    "addr:street":"Weverslaan",
    "iso:country":"BE",
    "sg:address":"Weverslaan 30",
    "sg:city":"Lokeren",
    "sg:classifiers":[
        {
            "category":"Shopping",
            "subcategory":"Gifts & Souvenirs",
            "type":"Retail Goods"
        }
    ],
    "sg:phone":"+32 9 349 17 43",
    "sg:postcode":"9160",
    "sg:province":"Oost-Vlaanderen",
    "sg:tags":[
        "geschenken"
    ],
    "wof:name":"Santa Land",
    "wof:placetype":"venue"
},
  "geometry": {"coordinates":[4.0143990517,51.1111717224],"type":"Point"}
}