{
  "type": "Feature",
  "properties": {
    "iso:country":"BE",
    "sg:address":"Rte De Luxembourg 1",
    "sg:city":"Malmedy",
    "sg:classifiers":[
        {
            "category":"Autos & Motor Vehicles",
            "subcategory":"Automobile Sales",
            "type":"Retail Goods"
        }
    ],
    "sg:phone":"+32 80 33 85 06",
    "sg:postcode":"4960",
    "sg:province":"Li\u00e8ge",
    "sg:tags":[
        "equipment",
        "motor-cars",
        "transport"
    ],
    "wof:name":"Breuer Antoine Sa",
    "wof:placetype":"venue"
},
  "geometry": {"coordinates":[6.0666742325,50.4031028748],"type":"Point"}
}