{
  "type": "Feature",
  "properties": {
    "addr:full":"Avenue Vanderaey 7 Ukkel/uccle Bruxelles-Capitale 1180",
    "addr:housenumber":"7",
    "addr:postcode":"1180",
    "addr:street":"Avenue Vanderaey;/",
    "iso:country":"BE",
    "sg:address":"Avenue Vanderaey 7",
    "sg:city":"Ukkel/uccle",
    "sg:orig_category":"M\u00e9decins and sp\u00e9cialistes",
    "sg:phone":"+32 2 376 49 66",
    "sg:postcode":"1180",
    "sg:province":"Bruxelles-Capitale",
    "wof:name":"Marcelle Doyen",
    "wof:placetype":"venue"
},
  "geometry": {"coordinates":[4.3364129066,50.7974853516],"type":"Point"}
}