{
  "type": "Feature",
  "properties": {
    "iso:country":"BE",
    "sg:address":"Langstraat 23",
    "sg:city":"Bilzen",
    "sg:orig_category":"Producteurs de fruits",
    "sg:phone":"+32 89 41 40 49",
    "sg:postcode":"3740",
    "sg:province":"Limburg",
    "wof:name":"Jan Duelen",
    "wof:placetype":"venue"
},
  "geometry": {"coordinates":[5.5083680153,50.8425865173],"type":"Point"}
}