{
  "type": "Feature",
  "properties": {
    "iso:country":"BE",
    "sg:address":"Kerkskenhoek 87",
    "sg:city":"Haaltert",
    "sg:classifiers":[
        {
            "category":"Restaurant",
            "type":"Food & Drink"
        }
    ],
    "sg:phone":"+32 53 83 32 86",
    "sg:postcode":"9450",
    "sg:province":"Oost-Vlaanderen",
    "sg:tags":[
        "caf\u00e9s"
    ],
    "wof:name":"In De Witten Hoek",
    "wof:placetype":"venue"
},
  "geometry": {"coordinates":[3.9952099323,50.8923110962],"type":"Point"}
}