{
  "type": "Feature",
  "properties": {
    "addr:full":"Franklin Rooseveltlaan 106 Vilvoorde Vlaams-Brabant 1800",
    "addr:housenumber":"106",
    "addr:postcode":"1800",
    "addr:street":"Franklin Rooseveltlaan",
    "iso:country":"BE",
    "sg:address":"Franklin Rooseveltlaan 106",
    "sg:city":"Vilvoorde",
    "sg:orig_category":"Kapsalons",
    "sg:phone":"+32 2 253 68 88",
    "sg:postcode":"1800",
    "sg:province":"Vlaams-Brabant",
    "wof:name":"Kappersteam Guy",
    "wof:placetype":"venue"
},
  "geometry": {"coordinates":[4.4246912003,50.9311637878],"type":"Point"}
}