{
  "type": "Feature",
  "properties": {
    "iso:country":"BE",
    "sg:address":"Rue Arille Laurent 1",
    "sg:city":"Chapelle-lez-herlaimont",
    "sg:orig_category":"Tweedehandsgoederen",
    "sg:phone":"+32 71 52 90 48",
    "sg:postcode":"7160",
    "sg:province":"Hainaut",
    "wof:name":"Ets. Ferro",
    "wof:placetype":"venue"
},
  "geometry": {"coordinates":[4.298140049,50.4431533813],"type":"Point"}
}