{
  "type": "Feature",
  "properties": {
    "iso:country":"BE",
    "sg:address":"Langestraat 96",
    "sg:city":"Nieuwpoort",
    "sg:classifiers":[
        {
            "category":"Shopping",
            "subcategory":"Florist",
            "type":"Retail Goods"
        }
    ],
    "sg:phone":"+32 58 23 64 01",
    "sg:postcode":"8620",
    "sg:province":"West-Vlaanderen",
    "wof:name":"Cinderella",
    "wof:placetype":"venue"
},
  "geometry": {"coordinates":[2.7517399788,51.1322975159],"type":"Point"}
}