{
  "type": "Feature",
  "properties": {
    "addr:full":"Bld Des G\u00c9rardchamps 157-158 B8 Verviers Li\u00e8ge 4800",
    "addr:postcode":"157-158 b8 verviers;4800",
    "addr:street":"Bld Des Ge\u0301Rardchamps",
    "iso:country":"BE",
    "sg:address":"Bld Des G\u00c9rardchamps 157-158 B8",
    "sg:city":"Verviers",
    "sg:orig_category":"Installation \u00e9lectrique r\u00e9sidentielle",
    "sg:phone":"+32 87 32 59 47",
    "sg:postcode":"4800",
    "sg:province":"Li\u00e8ge",
    "wof:name":"Netsys",
    "wof:placetype":"venue"
},
  "geometry": {"coordinates":[5.8594508171,50.5917663574],"type":"Point"}
}