{
  "type": "Feature",
  "properties": {
    "addr:full":"Ribaucourtstraat 146-152 Sint-jans-molenbeek/molenbeek- Bruxelles-Capitale 1080",
    "addr:housenumber":"146-152",
    "addr:postcode":"1080",
    "addr:street":"Ribaucourtstraat",
    "iso:country":"BE",
    "sg:address":"Ribaucourtstraat 146-152",
    "sg:city":"Sint-jans-molenbeek/molenbeek-",
    "sg:orig_category":"Diverse producten Gh Vrachtvervoer",
    "sg:phone":"+32 2 426 61 00",
    "sg:postcode":"1080",
    "sg:province":"Bruxelles-Capitale",
    "wof:name":"Catulle Yves",
    "wof:placetype":"venue"
},
  "geometry": {"coordinates":[4.3428258896,50.8617973328],"type":"Point"}
}