{
  "type": "Feature",
  "properties": {
    "iso:country":"BE",
    "sg:address":"Rue De Lexhy 18",
    "sg:city":"Fexhe-le-haut-clocher",
    "sg:orig_category":"Kapsalons",
    "sg:phone":"+32 4 250 12 12",
    "sg:postcode":"4347",
    "sg:province":"Li\u00e8ge",
    "wof:name":"Georgette Delathuy",
    "wof:placetype":"venue"
},
  "geometry": {"coordinates":[5.4012308121,50.651348114],"type":"Point"}
}