{
  "type": "Feature",
  "properties": {
    "addr:full":"Lippenslaan 22b5 Knokke-heist West-Vlaanderen 8300",
    "addr:housenumber":"22b5",
    "addr:postcode":"8300",
    "addr:street":"Lippenslaan",
    "iso:country":"BE",
    "sg:address":"Lippenslaan 22b5",
    "sg:city":"Knokke-heist",
    "sg:orig_category":"Erotische Etablissementen Erotische- and Escortediensten",
    "sg:phone":"+32 50 62 54 30",
    "sg:postcode":"8300",
    "sg:province":"West-Vlaanderen",
    "wof:name":"Alles Kan Alles Mag",
    "wof:placetype":"venue"
},
  "geometry": {"coordinates":[3.2876429558,51.3417739868],"type":"Point"}
}