{
  "type": "Feature",
  "properties": {
    "iso:country":"BE",
    "sg:address":"Place De Carni\u00c8res 26",
    "sg:city":"Morlanwelz",
    "sg:orig_category":"Maisons de repos and r\u00e9sidences",
    "sg:phone":"+32 64 44 22 95",
    "sg:postcode":"7141",
    "sg:province":"Hainaut",
    "wof:name":"Maison Du Sacr\u00c9 Coeur",
    "wof:placetype":"venue"
},
  "geometry": {"coordinates":[4.2544999123,50.442150116],"type":"Point"}
}