{
  "type": "Feature",
  "properties": {
    "iso:country":"BE",
    "sg:address":"Puttestraat 77",
    "sg:city":"Tervuren",
    "sg:orig_category":"Cr\u00e8ches and garderies d'enfants",
    "sg:phone":"+32 2 768 00 58",
    "sg:postcode":"3080",
    "sg:province":"Vlaams-Brabant",
    "wof:name":"Garderie Ptimoun",
    "wof:placetype":"venue"
},
  "geometry": {"coordinates":[4.5050091743,50.8221664429],"type":"Point"}
}