{
  "type": "Feature",
  "properties": {
    "iso:country":"BE",
    "sg:address":"Chemin Des Charbonniers 58",
    "sg:city":"Jurbise (masnuy-saint-jean)",
    "sg:classifiers":[
        {
            "category":"Sports & Exercise",
            "subcategory":"Stables",
            "type":"Entertainment"
        }
    ],
    "sg:phone":"+32 65 22 57 31",
    "sg:postcode":"7050",
    "sg:province":"Hainaut",
    "sg:tags":[
        "riding",
        "school"
    ],
    "wof:name":"Man\u00e8ge Des Bruy\u00e8res",
    "wof:placetype":"venue"
},
  "geometry": {"coordinates":[3.9249999523,50.5210227966],"type":"Point"}
}