{
  "type": "Feature",
  "properties": {
    "addr:full":"Route De L'etat 36 Wanze (huccorgne) Li\u00e8ge 4520",
    "addr:housenumber":"36",
    "addr:postcode":"4520",
    "addr:street":"Route De L'Etat",
    "iso:country":"BE",
    "sg:address":"Route De L'etat 36",
    "sg:city":"Wanze (huccorgne)",
    "sg:classifiers":[
        {
            "category":"Health Services",
            "subcategory":"Doctor",
            "type":"Services"
        }
    ],
    "sg:phone":"+32 85 71 29 72",
    "sg:postcode":"4520",
    "sg:province":"Li\u00e8ge",
    "sg:tags":[
        "medicinephysicians",
        "surgeon"
    ],
    "wof:name":"G\u00e9rard Fran\u00e7oise",
    "wof:placetype":"venue"
},
  "geometry": {"coordinates":[5.1647620201,50.5683403015],"type":"Point"}
}