{
  "type": "Feature",
  "properties": {
    "iso:country":"BE",
    "sg:address":"Rue D'arbre 3",
    "sg:city":"Anh\u00e9e (bioul)",
    "sg:classifiers":[
        {
            "category":"Personal",
            "subcategory":"Beauty Salon",
            "type":"Services"
        }
    ],
    "sg:phone":"+32 71 79 98 37",
    "sg:postcode":"5537",
    "sg:province":"Namur",
    "sg:tags":[
        "child",
        "-",
        "hairdressing"
    ],
    "wof:name":"Elle, Lui Et Les Petits",
    "wof:placetype":"venue"
},
  "geometry": {"coordinates":[4.796807766,50.3340988159],"type":"Point"}
}