{
  "type": "Feature",
  "properties": {
    "iso:country":"BE",
    "sg:address":"Place Ernest Rongvaux 3",
    "sg:city":"Waremme",
    "sg:orig_category":"Voedingsspeciaalzaken",
    "sg:phone":"+32 19 32 52 22",
    "sg:postcode":"4300",
    "sg:province":"Li\u00e8ge",
    "wof:name":"Traiteur Tian-tian",
    "wof:placetype":"venue"
},
  "geometry": {"coordinates":[5.2496080399,50.6951904297],"type":"Point"}
}