{
  "type": "Feature",
  "properties": {
    "addr:full":"Rue De L\u00b4aise 57 Jemeppe-sur-sambre Namur 5190",
    "addr:housenumber":"57",
    "addr:postcode":"5190",
    "addr:street":"Rue De L\u00b4Aise",
    "iso:country":"BE",
    "sg:address":"Rue De L\u00b4aise 57",
    "sg:city":"Jemeppe-sur-sambre",
    "sg:orig_category":"Traitements param\u00e9dicaux",
    "sg:phone":"+32 71 78 66 45",
    "sg:postcode":"5190",
    "sg:province":"Namur",
    "wof:name":"Doumont",
    "wof:placetype":"venue"
},
  "geometry": {"coordinates":[4.6677861214,50.4678611755],"type":"Point"}
}