{
  "type": "Feature",
  "properties": {
    "addr:full":"Rue De Livourne 97 Elsene/ixelles Bruxelles-Capitale 1050",
    "addr:housenumber":"97",
    "addr:postcode":"1050",
    "addr:street":"Rue De Livourne",
    "iso:country":"BE",
    "sg:address":"Rue De Livourne 97",
    "sg:city":"Elsene/ixelles",
    "sg:orig_category":"Avocats and conseillers juridiques",
    "sg:phone":"+32 2 647 50 25",
    "sg:postcode":"1050",
    "sg:province":"Bruxelles-Capitale",
    "wof:name":"Breitenstein G.",
    "wof:placetype":"venue"
},
  "geometry": {"coordinates":[4.3613009453,50.827545166],"type":"Point"}
}