{
  "type": "Feature",
  "properties": {
    "iso:country":"BE",
    "sg:address":"Verbindingsstraat 10b",
    "sg:city":"Grobbendonk (bouwel)",
    "sg:classifiers":[
        {
            "category":"Personal",
            "subcategory":"Beauty Salon",
            "type":"Services"
        }
    ],
    "sg:phone":"+32 14 50 15 25",
    "sg:postcode":"2288",
    "sg:province":"Antwerpen",
    "sg:tags":[
        "equipment",
        "hairdressing",
        "-",
        "supply"
    ],
    "wof:name":"Sfeo-art",
    "wof:placetype":"venue"
},
  "geometry": {"coordinates":[4.7555799484,51.1647644043],"type":"Point"}
}