{
  "type": "Feature",
  "properties": {
    "iso:country":"BE",
    "sg:address":"Neuville 8",
    "sg:city":"Vielsalm",
    "sg:classifiers":[
        {
            "category":"Home & Garden",
            "subcategory":"Carpets & Floor Coverings",
            "type":"Retail Goods"
        }
    ],
    "sg:phone":"+32 80 21 46 13",
    "sg:postcode":"6690",
    "sg:province":"Luxembourg",
    "sg:tags":[
        "layer",
        "mosaicists"
    ],
    "wof:name":"Fiume G",
    "wof:placetype":"venue"
},
  "geometry": {"coordinates":[5.930311203,50.2809524536],"type":"Point"}
}