{
  "type": "Feature",
  "properties": {
    "iso:country":"BE",
    "sg:address":"Langdorpsesteenweg 185",
    "sg:city":"Aarschot",
    "sg:orig_category":"Apotheken",
    "sg:phone":"+32 16 56 79 07",
    "sg:postcode":"3201",
    "sg:province":"Vlaams-Brabant",
    "wof:name":"J. Smeys",
    "wof:placetype":"venue"
},
  "geometry": {"coordinates":[4.8548250198,50.9929771423],"type":"Point"}
}