{
  "type": "Feature",
  "properties": {
    "addr:full":"Rue Louis De Brouck\u00c8re 56 Charleroi Hainaut 6044",
    "addr:housenumber":"56",
    "addr:postcode":"6044",
    "addr:street":"Rue Louis De Broucke\u0300Re;Hainaut",
    "iso:country":"BE",
    "sg:address":"Rue Louis De Brouck\u00c8re 56",
    "sg:city":"Charleroi",
    "sg:orig_category":"Parfumeries",
    "sg:phone":"+32 71 46 32 99",
    "sg:postcode":"6044",
    "sg:province":"Hainaut",
    "wof:name":"V\u00c9ronique Ma\u00c7on",
    "wof:placetype":"venue"
},
  "geometry": {"coordinates":[4.3900289536,50.4444046021],"type":"Point"}
}