{
  "type": "Feature",
  "properties": {
    "addr:full":"Processieweg 93 Lede (wanzele) Oost-Vlaanderen 9340",
    "addr:housenumber":"93",
    "addr:postcode":"9340",
    "addr:street":"Processieweg",
    "iso:country":"BE",
    "sg:address":"Processieweg 93",
    "sg:city":"Lede (wanzele)",
    "sg:classifiers":[
        {
            "category":"Freight",
            "type":"Transportation"
        }
    ],
    "sg:phone":"+32 53 80 20 81",
    "sg:postcode":"9340",
    "sg:province":"Oost-Vlaanderen",
    "sg:tags":[
        "-",
        "transport"
    ],
    "wof:name":"De Taey",
    "wof:placetype":"venue"
},
  "geometry": {"coordinates":[3.959829092,50.9715576172],"type":"Point"}
}