{
  "type": "Feature",
  "properties": {
    "iso:country":"BE",
    "sg:address":"Bisschopstraat 57",
    "sg:city":"Antwerpen",
    "sg:orig_category":"Werk and personeelsselectie",
    "sg:phone":"+32 3 227 08 70",
    "sg:postcode":"2060",
    "sg:province":"Antwerpen",
    "wof:name":"Curriculum Plus",
    "wof:placetype":"venue"
},
  "geometry": {"coordinates":[4.4259052277,51.2196807861],"type":"Point"}
}