{
  "type": "Feature",
  "properties": {
    "iso:country":"BE",
    "sg:address":"Rue C\u00c9sar Franck 36",
    "sg:city":"Elsene/ixelles",
    "sg:orig_category":"Ordinateurs and \u00e9quipement informatique",
    "sg:phone":"+32 2 644 17 62",
    "sg:postcode":"1050",
    "sg:province":"Bruxelles-Capitale",
    "wof:name":"Hard & Soft Development",
    "wof:placetype":"venue"
},
  "geometry": {"coordinates":[4.3906779289,50.8187522888],"type":"Point"}
}