{
  "type": "Feature",
  "properties": {
    "iso:country":"BE",
    "sg:address":"Rue Charles Magnette 2",
    "sg:city":"Li\u00e8ge 1",
    "sg:classifiers":[
        {
            "category":"Shopping",
            "subcategory":"Crafts & Fabrics",
            "type":"Retail Goods"
        }
    ],
    "sg:phone":"+32 4 221 05 20",
    "sg:postcode":"4000",
    "sg:province":"Li\u00e8ge",
    "sg:tags":[
        "upholstery",
        "-"
    ],
    "wof:name":"Darden's D\u00e9cors",
    "wof:placetype":"venue"
},
  "geometry": {"coordinates":[5.5743021965,50.6411514282],"type":"Point"}
}