{
  "type": "Feature",
  "properties": {
    "addr:full":"Rue Henri-vieuxtemps 76-32 Li\u00e8ge 1 Li\u00e8ge 4000",
    "addr:postcode":"76-32;4000",
    "addr:street":"Rue Henri-Vieuxtemps",
    "iso:country":"BE",
    "sg:address":"Rue Henri-vieuxtemps 76-32",
    "sg:city":"Li\u00e8ge 1",
    "sg:classifiers":[
        {
            "category":"Professional",
            "subcategory":"Accounting & Tax Preparation",
            "type":"Services"
        }
    ],
    "sg:phone":"+32 4 226 34 17",
    "sg:postcode":"4000",
    "sg:province":"Li\u00e8ge",
    "sg:tags":[
        "accountant"
    ],
    "wof:name":"Houbrechts H",
    "wof:placetype":"venue"
},
  "geometry": {"coordinates":[5.5606331825,50.6475143433],"type":"Point"}
}