{
  "type": "Feature",
  "properties": {
    "addr:full":"Place De Beloeil 18 Beloeil Hainaut 7970",
    "addr:housenumber":"18",
    "addr:postcode":"7970",
    "addr:street":"Place De Beloeil",
    "iso:country":"BE",
    "sg:address":"Place De Beloeil 18",
    "sg:city":"Beloeil",
    "sg:orig_category":"Banques and organismes de cr\u00e9dit",
    "sg:phone":"+32 69 68 95 78",
    "sg:postcode":"7970",
    "sg:province":"Hainaut",
    "wof:name":"Fortis",
    "wof:placetype":"venue"
},
  "geometry": {"coordinates":[3.7354249954,50.5487861633],"type":"Point"}
}