{
  "type": "Feature",
  "properties": {
    "iso:country":"BE",
    "sg:address":"Rue Bois De Graux 30",
    "sg:city":"Profondeville (lesve)",
    "sg:classifiers":[
        {
            "category":"Building & Trades",
            "subcategory":"Landscaping Services",
            "type":"Services"
        }
    ],
    "sg:phone":"+32 81 26 14 30",
    "sg:postcode":"5170",
    "sg:province":"Namur",
    "sg:tags":[
        "architect",
        "landscape"
    ],
    "wof:name":"Ducarme J-b",
    "wof:placetype":"venue"
},
  "geometry": {"coordinates":[4.7689118385,50.3772544861],"type":"Point"}
}