{
  "type": "Feature",
  "properties": {
    "iso:country":"BE",
    "sg:address":"Rue Osseghem 208",
    "sg:city":"Sint-jans-molenbeek/molenbeek-saint-jean",
    "sg:classifiers":[
        {
            "category":"Cafe",
            "type":"Food & Drink"
        }
    ],
    "sg:phone":"+32 2 410 39 22",
    "sg:postcode":"1080",
    "sg:province":"Bruxelles-Capitale",
    "sg:tags":[
        "caf\u00e9s"
    ],
    "wof:name":"Caf\u00c9 Stella Sport",
    "wof:placetype":"venue"
},
  "geometry": {"coordinates":[4.3107419014,50.8520698547],"type":"Point"}
}