{
  "type": "Feature",
  "properties": {
    "addr:full":"Broechemsesteenweg 121d Ranst (emblem) Antwerpen 2520",
    "addr:housenumber":"121d",
    "addr:postcode":"2520",
    "addr:street":"Broechemsesteenweg",
    "iso:country":"BE",
    "sg:address":"Broechemsesteenweg 121d",
    "sg:city":"Ranst (emblem)",
    "sg:orig_category":"Accumulators",
    "sg:phone":"+32 3 488 50 71",
    "sg:postcode":"2520",
    "sg:province":"Antwerpen",
    "wof:name":"Ruben Power Bvba",
    "wof:placetype":"venue"
},
  "geometry": {"coordinates":[4.5925297737,51.1659164429],"type":"Point"}
}