{
  "type": "Feature",
  "properties": {
    "iso:country":"BE",
    "sg:address":"Rue De La Gare 68",
    "sg:city":"Frasnes-lez-anvaing (anvaing)",
    "sg:classifiers":[
        {
            "category":"Health Services",
            "subcategory":"Dentist",
            "type":"Services"
        }
    ],
    "sg:phone":"+32 69 86 77 31",
    "sg:postcode":"7910",
    "sg:province":"Hainaut",
    "wof:name":"Olivier C",
    "wof:placetype":"venue"
},
  "geometry": {"coordinates":[3.5768198967,50.6884613037],"type":"Point"}
}