{
  "type": "Feature",
  "properties": {
    "addr:full":"Rue De Bastogne 67 Arlon Luxembourg 6700",
    "addr:housenumber":"67",
    "addr:postcode":"6700",
    "addr:street":"Rue De Bastogne",
    "iso:country":"BE",
    "sg:address":"Rue De Bastogne 67",
    "sg:city":"Arlon",
    "sg:orig_category":"Belastingconsulenten Boekhouders Diverse juridische dienstverlening",
    "sg:phone":"+32 63 22 79 58",
    "sg:postcode":"6700",
    "sg:province":"Luxembourg",
    "wof:name":"Jean-marie Nicolay",
    "wof:placetype":"venue"
},
  "geometry": {"coordinates":[5.8105549812,49.688999176],"type":"Point"}
}