{
  "type": "Feature",
  "properties": {
    "addr:full":"Frankrijkstraat 2 Moeskroen/mouscron Hainaut 7711",
    "addr:housenumber":"2",
    "addr:postcode":"7711",
    "addr:street":"Frankrijkstraat",
    "iso:country":"BE",
    "sg:address":"Frankrijkstraat 2",
    "sg:city":"Moeskroen/mouscron",
    "sg:orig_category":"Banken and kredietinstellingen",
    "sg:phone":"+32 56 48 98 88",
    "sg:postcode":"7711",
    "sg:province":"Hainaut",
    "wof:name":"Dexia",
    "wof:placetype":"venue"
},
  "geometry": {"coordinates":[3.3030340672,50.7274932861],"type":"Point"}
}