{
  "type": "Feature",
  "properties": {
    "addr:full":"Kruisstraat 17ba Hoeselt Limburg 3730",
    "addr:housenumber":"17ba",
    "addr:postcode":"3730",
    "addr:street":"Kruisstraat",
    "iso:country":"BE",
    "sg:address":"Kruisstraat 17ba",
    "sg:city":"Hoeselt",
    "sg:orig_category":"Artsen and specialisten",
    "sg:phone":"+32 89 51 14 37",
    "sg:postcode":"3730",
    "sg:province":"Limburg",
    "wof:name":"Erwin Bruninx",
    "wof:placetype":"venue"
},
  "geometry": {"coordinates":[5.4774708748,50.8468399048],"type":"Point"}
}