{
  "type": "Feature",
  "properties": {
    "addr:full":"Nieuwstraat 211 Diepenbeek Limburg 3590",
    "addr:housenumber":"211",
    "addr:postcode":"3590",
    "addr:street":"Nieuwstraat",
    "iso:country":"BE",
    "sg:address":"Nieuwstraat 211",
    "sg:city":"Diepenbeek",
    "sg:classifiers":[
        {
            "category":"Cafe",
            "type":"Food & Drink"
        }
    ],
    "sg:phone":"+32 11 33 12 52",
    "sg:postcode":"3590",
    "sg:province":"Limburg",
    "sg:tags":[
        "caf\u00e9s"
    ],
    "wof:name":"Corinne Henon",
    "wof:placetype":"venue"
},
  "geometry": {"coordinates":[5.4577050209,50.9273452759],"type":"Point"}
}