{
  "type": "Feature",
  "properties": {
    "iso:country":"BE",
    "sg:address":"Bld G\u00c9n\u00c9ral Jacques 202b2",
    "sg:city":"Elsene/ixelles",
    "sg:orig_category":"Activit\u00e9s r\u00e9cr\u00e9atives diverses",
    "sg:phone":"+32 2 640 46 13",
    "sg:postcode":"1050",
    "sg:province":"Bruxelles-Capitale",
    "wof:name":"Roy. Bourse Timbres-poste",
    "wof:placetype":"venue"
},
  "geometry": {"coordinates":[4.3861618042,50.8211708069],"type":"Point"}
}