{
  "type": "Feature",
  "properties": {
    "addr:full":"Naamsesteenweg 355 Leuven Vlaams-Brabant 3001",
    "addr:housenumber":"355",
    "addr:postcode":"3001",
    "addr:street":"Naamsesteenweg",
    "iso:country":"BE",
    "sg:address":"Naamsesteenweg 355",
    "sg:city":"Leuven",
    "sg:orig_category":"Enseignement secondaire technique and professionnel. Enseignement secondaire g\u00e9n\u00e9ral",
    "sg:phone":"+32 16 39 90 65",
    "sg:postcode":"3001",
    "sg:province":"Vlaams-Brabant",
    "wof:name":"Humaniora H.hartinstituut",
    "wof:placetype":"venue"
},
  "geometry": {"coordinates":[4.6964211464,50.8582878113],"type":"Point"}
}