{
  "type": "Feature",
  "properties": {
    "iso:country":"BE",
    "sg:address":"Rue Des Martyrs 15",
    "sg:city":"Verviers",
    "sg:orig_category":"Artsen and specialisten",
    "sg:phone":"+32 87 35 01 03",
    "sg:postcode":"4800",
    "sg:province":"Li\u00e8ge",
    "wof:name":"Quang-hiep Tran",
    "wof:placetype":"venue"
},
  "geometry": {"coordinates":[5.862883091,50.5920143127],"type":"Point"}
}