{
  "type": "Feature",
  "properties": {
    "iso:country":"BE",
    "sg:address":"Hoek 56",
    "sg:city":"Boom",
    "sg:orig_category":"Herstelling and restauratie van meubelen Meubelzaken, woning- and keukeninrichting",
    "sg:phone":"+32 3 844 18 13",
    "sg:postcode":"2850",
    "sg:province":"Antwerpen",
    "wof:name":"Kristof Bossaer",
    "wof:placetype":"venue"
},
  "geometry": {"coordinates":[4.3776321411,51.0851707458],"type":"Point"}
}