{
  "type": "Feature",
  "properties": {
    "addr:full":"Antwerpsesteenweg 55 Vosselaar Antwerpen 2350",
    "addr:housenumber":"55",
    "addr:postcode":"2350",
    "addr:street":"Antwerpsesteenweg",
    "iso:country":"BE",
    "sg:address":"Antwerpsesteenweg 55",
    "sg:city":"Vosselaar",
    "sg:orig_category":"Jeux and jouets",
    "sg:phone":"+32 14 61 90 21",
    "sg:postcode":"2350",
    "sg:province":"Antwerpen",
    "wof:name":"Agora",
    "wof:placetype":"venue"
},
  "geometry": {"coordinates":[4.8954210281,51.3156509399],"type":"Point"}
}