{
  "type": "Feature",
  "properties": {
    "addr:full":"Mechelsesteenweg 130 Dendermonde Oost-Vlaanderen 9200",
    "addr:housenumber":"130",
    "addr:postcode":"9200",
    "addr:street":"Mechelsesteenweg;Oost-Vlaanderen",
    "iso:country":"BE",
    "sg:address":"Mechelsesteenweg 130",
    "sg:city":"Dendermonde",
    "sg:orig_category":"Herstellingen and onderhoud van auto's Onderdelen and accessoires voor auto's",
    "sg:phone":"+32 52 21 42 20",
    "sg:postcode":"9200",
    "sg:province":"Oost-Vlaanderen",
    "wof:name":"Midas",
    "wof:placetype":"venue"
},
  "geometry": {"coordinates":[4.1156721115,51.0349655151],"type":"Point"}
}