{
  "type": "Feature",
  "properties": {
    "addr:full":"Langeveldstraat 12 Erpe-mere Oost-Vlaanderen 9420",
    "addr:housenumber":"12",
    "addr:postcode":"9420",
    "addr:street":"Langeveldstraat",
    "iso:country":"BE",
    "sg:address":"Langeveldstraat 12",
    "sg:city":"Erpe-mere",
    "sg:orig_category":"Travaux de pl\u00e2trage",
    "sg:phone":"+32 53 62 49 09",
    "sg:postcode":"9420",
    "sg:province":"Oost-Vlaanderen",
    "wof:name":"Verbraekel W. & Zn",
    "wof:placetype":"venue"
},
  "geometry": {"coordinates":[3.9251630306,50.9107971191],"type":"Point"}
}