{
  "type": "Feature",
  "properties": {
    "addr:full":"Rodestraat 19 Ternat Vlaams-Brabant 1742",
    "addr:housenumber":"19",
    "addr:postcode":"1742",
    "addr:street":"Rodestraat",
    "iso:country":"BE",
    "sg:address":"Rodestraat 19",
    "sg:city":"Ternat",
    "sg:classifiers":[
        {
            "category":"Personal",
            "subcategory":"Beauty Salon",
            "type":"Services"
        }
    ],
    "sg:phone":"+32 2 582 71 21",
    "sg:postcode":"1742",
    "sg:province":"Vlaams-Brabant",
    "sg:tags":[
        "de",
        "coiffure"
    ],
    "wof:name":"An Demaegd",
    "wof:placetype":"venue"
},
  "geometry": {"coordinates":[4.1537981033,50.8729858398],"type":"Point"}
}