{
  "type": "Feature",
  "properties": {
    "addr:full":"Koningin Elisabethplein 4 Sint-niklaas Oost-Vlaanderen 9100",
    "addr:housenumber":"4",
    "addr:postcode":"9100",
    "addr:street":"Koningin Elisabethplein",
    "iso:country":"BE",
    "sg:address":"Koningin Elisabethplein 4",
    "sg:city":"Sint-niklaas",
    "sg:classifiers":[
        {
            "category":"Professional",
            "subcategory":"Art Services",
            "type":"Services"
        }
    ],
    "sg:phone":"+32 3 776 97 82",
    "sg:postcode":"9100",
    "sg:province":"Oost-Vlaanderen",
    "sg:tags":[
        "photographer"
    ],
    "wof:name":"Huys H",
    "wof:placetype":"venue"
},
  "geometry": {"coordinates":[4.1537928581,51.1706581116],"type":"Point"}
}