{
  "type": "Feature",
  "properties": {
    "iso:country":"BE",
    "sg:address":"Vieux Chemin De Hal 44",
    "sg:city":"Braine-le-ch\u00e2teau",
    "sg:classifiers":[
        {
            "category":"Transit Center",
            "subcategory":"Passenger",
            "type":"Transportation"
        }
    ],
    "sg:phone":"+32 2 366 99 50",
    "sg:postcode":"1440",
    "sg:province":"Brabant Wallon",
    "sg:tags":[
        "sand",
        "gravel"
    ],
    "wof:name":"Sabli\u00e8re De Wauthier Braine S.a.",
    "wof:placetype":"venue"
},
  "geometry": {"coordinates":[4.2691302299,50.691947937],"type":"Point"}
}