{
  "type": "Feature",
  "properties": {
    "addr:full":"Hoeksken 9 Knesselare Oost-Vlaanderen 9910",
    "addr:housenumber":"9",
    "addr:postcode":"9910",
    "addr:street":"Hoeksken;Oost-Vlaanderen",
    "iso:country":"BE",
    "sg:address":"Hoeksken 9",
    "sg:city":"Knesselare",
    "sg:orig_category":"Elektrische installaties voor woningen Loodgieterij, verwarming and sanitaire installaties",
    "sg:phone":"+32 9 374 77 70",
    "sg:postcode":"9910",
    "sg:province":"Oost-Vlaanderen",
    "wof:name":"Johan Hautekier",
    "wof:placetype":"venue"
},
  "geometry": {"coordinates":[3.4736070633,51.1147346497],"type":"Point"}
}