{
  "type": "Feature",
  "properties": {
    "iso:country":"BE",
    "sg:address":"Kapelstraat 18 Box 2",
    "sg:city":"Hasselt",
    "sg:classifiers":[
        {
            "category":"Real Estate",
            "subcategory":"Architect",
            "type":"Services"
        }
    ],
    "sg:phone":"+32 11 24 30 31",
    "sg:postcode":"3500",
    "sg:province":"Limburg",
    "wof:name":"Gielen I",
    "wof:placetype":"venue"
},
  "geometry": {"coordinates":[5.3355407715,50.9297065735],"type":"Point"}
}