{
  "type": "Feature",
  "properties": {
    "addr:full":"Chemin De Saint-ghislain 17 Chi\u00e8vres Hainaut 7950",
    "addr:housenumber":"17",
    "addr:postcode":"7950",
    "addr:street":"Chemin De Saint-Ghislain;Hainaut",
    "iso:country":"BE",
    "sg:address":"Chemin De Saint-ghislain 17",
    "sg:city":"Chi\u00e8vres",
    "sg:classifiers":[
        {
            "category":"Food & Beverages",
            "subcategory":"Dairy",
            "type":"Retail Goods"
        }
    ],
    "sg:phone":"+32 68 65 70 19",
    "sg:postcode":"7950",
    "sg:province":"Hainaut",
    "sg:tags":[
        "product",
        "-"
    ],
    "wof:name":"Dupont J-m",
    "wof:placetype":"venue"
},
  "geometry": {"coordinates":[3.8058080673,50.5842247009],"type":"Point"}
}