{
  "type": "Feature",
  "properties": {
    "addr:full":"Rue Jean-mathieu-nisen 1 Box 1 Li\u00e8ge 1 (li\u00e8ge 2) Li\u00e8ge 4020",
    "addr:housenumber":"1;1;1;2",
    "addr:postcode":"4020",
    "addr:street":"Rue Jean-Mathieu-Nisen;Box",
    "iso:country":"BE",
    "sg:address":"Rue Jean-mathieu-nisen 1 Box 1",
    "sg:city":"Li\u00e8ge 1 (li\u00e8ge 2)",
    "sg:classifiers":[
        {
            "category":"Retail",
            "subcategory":"Repair Shop",
            "type":"Services"
        }
    ],
    "sg:phone":"+32 4 264 73 53",
    "sg:postcode":"4020",
    "sg:province":"Li\u00e8ge",
    "sg:tags":[
        "denture"
    ],
    "wof:name":"Serafini Laboratoire",
    "wof:placetype":"venue"
},
  "geometry": {"coordinates":[5.6016330719,50.6465950012],"type":"Point"}
}