{
  "type": "Feature",
  "properties": {
    "iso:country":"BE",
    "sg:address":"Mechelse Steenweg 77",
    "sg:city":"Antwerpen",
    "sg:classifiers":[
        {
            "category":"Home & Garden",
            "subcategory":"Home Furnishings",
            "type":"Retail Goods"
        }
    ],
    "sg:phone":"+32 3 232 14 81",
    "sg:postcode":"2018",
    "sg:province":"Antwerpen",
    "sg:tags":[
        "interior",
        "decoration"
    ],
    "wof:name":"Ilse De Meulemeester Interieur",
    "wof:placetype":"venue"
},
  "geometry": {"coordinates":[4.4097819328,51.2072563171],"type":"Point"}
}