{
  "type": "Feature",
  "properties": {
    "iso:country":"BE",
    "sg:address":"Kleine Markt 19a",
    "sg:city":"Herentals",
    "sg:classifiers":[
        {
            "category":"Professional",
            "subcategory":"Accounting & Tax Preparation",
            "type":"Services"
        }
    ],
    "sg:phone":"+32 14 21 32 40",
    "sg:postcode":"2200",
    "sg:province":"Antwerpen",
    "sg:tags":[
        "accountant"
    ],
    "wof:name":"Raymond M",
    "wof:placetype":"venue"
},
  "geometry": {"coordinates":[4.8271842003,51.1784286499],"type":"Point"}
}