{
  "type": "Feature",
  "properties": {
    "iso:country":"BE",
    "sg:address":"Wolvengrachtstraat 7",
    "sg:city":"Langemark-poelkapelle (langemark)",
    "sg:classifiers":[
        {
            "category":"Wholesale",
            "subcategory":"Scrap",
            "type":"Manufacturing & Wholesale Goods"
        }
    ],
    "sg:phone":"+32 57 48 85 90",
    "sg:postcode":"8920",
    "sg:province":"West-Vlaanderen",
    "sg:tags":[
        "metal"
    ],
    "wof:name":"Debruyne M",
    "wof:placetype":"venue"
},
  "geometry": {"coordinates":[2.927947998,50.9384155273],"type":"Point"}
}