{
  "type": "Feature",
  "properties": {
    "iso:country":"BE",
    "sg:address":"Stationsstraat 3",
    "sg:city":"Oostkamp",
    "sg:classifiers":[
        {
            "category":"Tea Room",
            "subcategory":"None",
            "type":"Food & Drink"
        }
    ],
    "sg:phone":"+32 50 82 42 21",
    "sg:postcode":"8020",
    "sg:province":"West-Vlaanderen",
    "wof:name":"La Siesta",
    "wof:placetype":"venue"
},
  "geometry": {"coordinates":[3.2357540131,51.1546173096],"type":"Point"}
}