{
  "type": "Feature",
  "properties": {
    "addr:full":"Reningelststraat 73 Heuvelland (kemmel) West-Vlaanderen 8956",
    "addr:housenumber":"73",
    "addr:postcode":"8956",
    "addr:street":"Reningelststraat",
    "iso:country":"BE",
    "sg:address":"Reningelststraat 73",
    "sg:city":"Heuvelland (kemmel)",
    "sg:classifiers":[
        {
            "category":"Banks & Credit Unions",
            "subcategory":"Bank",
            "type":"Services"
        }
    ],
    "sg:phone":"+32 57 44 60 11",
    "sg:postcode":"8956",
    "sg:province":"West-Vlaanderen",
    "sg:tags":[
        "savings-banks"
    ],
    "wof:name":"De Visschere M",
    "wof:placetype":"venue"
},
  "geometry": {"coordinates":[2.8227729797,50.7860794067],"type":"Point"}
}