{
  "type": "Feature",
  "properties": {
    "iso:country":"BE",
    "sg:address":"Sportstraat 61",
    "sg:city":"Bredene",
    "sg:orig_category":"Dakwerken IJzerwaren, bouw- and verfmaterialen Installatie van houten of kunststof schrijnwerk Plaat",
    "sg:phone":"+32 59 32 50 27",
    "sg:postcode":"8450",
    "sg:province":"West-Vlaanderen",
    "wof:name":"Algemene Bouwwerken Neyt",
    "wof:placetype":"venue"
},
  "geometry": {"coordinates":[2.9648199081,51.2282485962],"type":"Point"}
}