{
  "type": "Feature",
  "properties": {
    "addr:full":"Rue Du Centre 3 Waimes/waimes Li\u00e8ge 4950",
    "addr:housenumber":"3",
    "addr:postcode":"4950",
    "addr:street":"Rue Du Centre",
    "iso:country":"BE",
    "sg:address":"Rue Du Centre 3",
    "sg:city":"Waimes/waimes",
    "sg:orig_category":"Plaatsen van vloer- and muurbekleding Vloer- and muurbekleding",
    "sg:phone":"+32 80 67 90 44",
    "sg:postcode":"4950",
    "sg:province":"Li\u00e8ge",
    "wof:name":"Caromat",
    "wof:placetype":"venue"
},
  "geometry": {"coordinates":[6.1406908035,50.4036178589],"type":"Point"}
}