{
  "type": "Feature",
  "properties": {
    "iso:country":"BE",
    "sg:address":"Rue De Soignies 274",
    "sg:city":"Ath",
    "sg:classifiers":[
        {
            "category":"Building & Trades",
            "subcategory":"Plumbing",
            "type":"Services"
        }
    ],
    "sg:phone":"+32 68 28 54 57",
    "sg:postcode":"7800",
    "sg:province":"Hainaut",
    "sg:tags":[
        "contractor"
    ],
    "wof:name":"Fourdin Y",
    "wof:placetype":"venue"
},
  "geometry": {"coordinates":[3.7978799343,50.6222000122],"type":"Point"}
}