{
  "type": "Feature",
  "properties": {
    "iso:country":"BE",
    "sg:address":"Raverschootstraat 158",
    "sg:city":"Eeklo",
    "sg:classifiers":[
        {
            "category":"Social Services",
            "subcategory":"Child Care",
            "type":"Services"
        }
    ],
    "sg:phone":"+32 9 378 43 17",
    "sg:postcode":"9900",
    "sg:province":"Oost-Vlaanderen",
    "sg:tags":[
        "baby",
        "nursery",
        "day",
        "sitting"
    ],
    "wof:name":"Kinderopvang Claartje",
    "wof:placetype":"venue"
},
  "geometry": {"coordinates":[3.5510339737,51.1882171631],"type":"Point"}
}