{
  "type": "Feature",
  "properties": {
    "iso:country":"BE",
    "sg:address":"Magere Schorre 17",
    "sg:city":"Knokke-heist",
    "sg:orig_category":"Beheer onroerend goed",
    "sg:phone":"+32 50 61 01 03",
    "sg:postcode":"8300",
    "sg:province":"West-Vlaanderen",
    "wof:name":"Immobili\u00c8re Tavernier",
    "wof:placetype":"venue"
},
  "geometry": {"coordinates":[3.298156023,51.3406028748],"type":"Point"}
}