{
  "type": "Feature",
  "properties": {
    "iso:country":"BE",
    "sg:address":"Ooststraat 90",
    "sg:city":"Wervik",
    "sg:orig_category":"Installatie van houten of kunststof schrijnwerk",
    "sg:phone":"+32 56 31 42 51",
    "sg:postcode":"8940",
    "sg:province":"West-Vlaanderen",
    "wof:name":"Michel Claeys",
    "wof:placetype":"venue"
},
  "geometry": {"coordinates":[3.0520780087,50.7848129272],"type":"Point"}
}