{
  "type": "Feature",
  "properties": {
    "iso:country":"BE",
    "sg:address":"Sint-antoniusstraat 27",
    "sg:city":"Turnhout",
    "sg:classifiers":[
        {
            "category":"Transit Center",
            "subcategory":"Freight",
            "type":"Transportation"
        }
    ],
    "sg:phone":"+32 14 43 59 37",
    "sg:postcode":"2300",
    "sg:province":"Antwerpen",
    "sg:tags":[
        "import",
        "export",
        "-"
    ],
    "wof:name":"Btc Bvba",
    "wof:placetype":"venue"
},
  "geometry": {"coordinates":[4.9441242218,51.3235092163],"type":"Point"}
}