{
  "type": "Feature",
  "properties": {
    "iso:country":"BE",
    "sg:address":"Place Royale 38",
    "sg:city":"Rhode-saint-gen\u00e8se",
    "sg:classifiers":[
        {
            "category":"Health Services",
            "subcategory":"Dentist",
            "type":"Services"
        }
    ],
    "sg:phone":"+32 2 381 20 11",
    "sg:postcode":"1640",
    "sg:province":"Vlaams-Brabant",
    "wof:name":"De Saeger A",
    "wof:placetype":"venue"
},
  "geometry": {"coordinates":[4.3533501625,50.7396583557],"type":"Point"}
}