{
  "type": "Feature",
  "properties": {
    "iso:country":"BE",
    "sg:address":"Groenlaan 58",
    "sg:city":"Herzele",
    "sg:orig_category":"S\u00e9curit\u00e9 sociale",
    "sg:phone":"+32 53 62 22 00",
    "sg:postcode":"9550",
    "sg:province":"Oost-Vlaanderen",
    "wof:name":"Christelijke Mutualiteit",
    "wof:placetype":"venue"
},
  "geometry": {"coordinates":[3.8907339573,50.8841362],"type":"Point"}
}