{
  "type": "Feature",
  "properties": {
    "iso:country":"BE",
    "sg:address":"Rode Kruisstraat 5",
    "sg:city":"Heusden-zolder (heusden)",
    "sg:classifiers":[
        {
            "category":"Personal",
            "subcategory":"Beauty Salon",
            "type":"Services"
        }
    ],
    "sg:phone":"+32 11 57 14 71",
    "sg:postcode":"3550",
    "sg:province":"Limburg",
    "sg:tags":[
        "lady",
        "-",
        "hairdressing"
    ],
    "wof:name":"Cardienne",
    "wof:placetype":"venue"
},
  "geometry": {"coordinates":[5.3065400124,51.0395469666],"type":"Point"}
}