{
  "type": "Feature",
  "properties": {
    "iso:country":"BE",
    "sg:address":"Voie De Messe 22",
    "sg:city":"Oupeye",
    "sg:orig_category":"Voertuigen",
    "sg:phone":"+32 4 278 52 39",
    "sg:postcode":"4680",
    "sg:province":"Li\u00e8ge",
    "wof:name":"Garage Paque",
    "wof:placetype":"venue"
},
  "geometry": {"coordinates":[5.6444120407,50.7089729309],"type":"Point"}
}