{
  "type": "Feature",
  "properties": {
    "iso:country":"BE",
    "sg:address":"Tweekerkenstraat 101",
    "sg:city":"Sint-joost-ten-node/saint-josse-ten-noode",
    "sg:classifiers":[
        {
            "category":"Restaurant",
            "type":"Food & Drink"
        }
    ],
    "sg:phone":"+32 2 230 07 12",
    "sg:postcode":"1210",
    "sg:province":"Bruxelles-Capitale",
    "wof:name":"Chez Tartine",
    "wof:placetype":"venue"
},
  "geometry": {"coordinates":[4.3741979599,50.8487663269],"type":"Point"}
}