{
  "type": "Feature",
  "properties": {
    "addr:full":"Hameau De Maisoncelles 42 Beauraing Namur 5571",
    "addr:housenumber":"42",
    "addr:postcode":"5571",
    "addr:street":"Hameau De Maisoncelles",
    "iso:country":"BE",
    "sg:address":"Hameau De Maisoncelles 42",
    "sg:city":"Beauraing",
    "sg:orig_category":"Boissons",
    "sg:phone":"+32 82 71 33 58",
    "sg:postcode":"5571",
    "sg:province":"Namur",
    "wof:name":"Christine Hallet",
    "wof:placetype":"venue"
},
  "geometry": {"coordinates":[4.9769701958,50.1485595703],"type":"Point"}
}