{
  "type": "Feature",
  "properties": {
    "addr:full":"Claessensdreef 128 Kapellen (mariaburg) Antwerpen 2950",
    "addr:housenumber":"128",
    "addr:postcode":"2950",
    "addr:street":"Claessensdreef",
    "iso:country":"BE",
    "sg:address":"Claessensdreef 128",
    "sg:city":"Kapellen (mariaburg)",
    "sg:classifiers":[
        {
            "category":"Health Services",
            "subcategory":"Doctor",
            "type":"Services"
        }
    ],
    "sg:phone":"+32 3 295 60 95",
    "sg:postcode":"2950",
    "sg:province":"Antwerpen",
    "sg:tags":[
        "psychotherapist",
        "psychoanalyst"
    ],
    "wof:name":"Theys Agnes",
    "wof:placetype":"venue"
},
  "geometry": {"coordinates":[4.4619750977,51.3096504211],"type":"Point"}
}