{
  "type": "Feature",
  "properties": {
    "addr:full":"Dorpsstraat 96 Staden West-Vlaanderen 8840",
    "addr:housenumber":"96",
    "addr:postcode":"8840",
    "addr:street":"Dorpsstraat",
    "iso:country":"BE",
    "sg:address":"Dorpsstraat 96",
    "sg:city":"Staden",
    "sg:orig_category":"Slagers",
    "sg:phone":"+32 51 77 76 16",
    "sg:postcode":"8840",
    "sg:province":"West-Vlaanderen",
    "wof:name":"Erik Denys",
    "wof:placetype":"venue"
},
  "geometry": {"coordinates":[3.0124030113,50.932849884],"type":"Point"}
}