{
  "type": "Feature",
  "properties": {
    "addr:full":"Rue De La Villette 2a Rendeux Luxembourg 6987",
    "addr:housenumber":"2a",
    "addr:postcode":"6987",
    "addr:street":"Rue De La Villette",
    "iso:country":"BE",
    "sg:address":"Rue De La Villette 2a",
    "sg:city":"Rendeux",
    "sg:orig_category":"Brood, gebak and snoepgoed",
    "sg:phone":"+32 84 46 72 36",
    "sg:postcode":"6987",
    "sg:province":"Luxembourg",
    "wof:name":"Boulangerie David",
    "wof:placetype":"venue"
},
  "geometry": {"coordinates":[5.503636837,50.2335166931],"type":"Point"}
}