{
  "type": "Feature",
  "properties": {
    "addr:full":"Hoogstraat 61b Evergem (ertvelde) Oost-Vlaanderen 9940",
    "addr:housenumber":"61b",
    "addr:postcode":"9940",
    "addr:street":"Hoogstraat;Ertvelde Oost-Vlaanderen",
    "iso:country":"BE",
    "sg:address":"Hoogstraat 61b",
    "sg:city":"Evergem (ertvelde)",
    "sg:classifiers":[
        {
            "category":"Manufacturing",
            "subcategory":"Metals",
            "type":"Manufacturing & Wholesale Goods"
        }
    ],
    "sg:phone":"+32 495 32 41 94",
    "sg:postcode":"9940",
    "sg:province":"Oost-Vlaanderen",
    "sg:tags":[
        "turning"
    ],
    "wof:name":"Ltd Bvba",
    "wof:placetype":"venue"
},
  "geometry": {"coordinates":[3.7367401123,51.157699585],"type":"Point"}
}