{
  "type": "Feature",
  "properties": {
    "addr:full":"Stationstraat 42 Moeskroen/mouscron Hainaut 7700",
    "addr:housenumber":"42",
    "addr:postcode":"7700",
    "addr:street":"Stationstraat",
    "iso:country":"BE",
    "sg:address":"Stationstraat 42",
    "sg:city":"Moeskroen/mouscron",
    "sg:orig_category":"Artsen and specialisten",
    "sg:phone":"+32 56 33 09 14",
    "sg:postcode":"7700",
    "sg:province":"Hainaut",
    "wof:name":"M. Lenoir",
    "wof:placetype":"venue"
},
  "geometry": {"coordinates":[3.2323200703,50.7400932312],"type":"Point"}
}