{
  "type": "Feature",
  "properties": {
    "addr:full":"Rue Haute 207 Bruxelles Bruxelles-Capitale 1000",
    "addr:housenumber":"207",
    "addr:postcode":"1000",
    "addr:street":"Rue Haute",
    "iso:country":"BE",
    "sg:address":"Rue Haute 207",
    "sg:city":"Bruxelles",
    "sg:classifiers":[
        {
            "category":"Shopping",
            "subcategory":"Antiques",
            "type":"Retail Goods"
        }
    ],
    "sg:phone":"+32 2 649 80 50",
    "sg:postcode":"1000",
    "sg:province":"Bruxelles-Capitale",
    "wof:name":"Uselding S Sprl",
    "wof:placetype":"venue"
},
  "geometry": {"coordinates":[4.3486061096,50.8372917175],"type":"Point"}
}