{
  "type": "Feature",
  "properties": {
    "iso:country":"BE",
    "sg:address":"Nederkouter 123",
    "sg:city":"Gent",
    "sg:orig_category":"Apotheken",
    "sg:phone":"+32 9 225 39 48",
    "sg:postcode":"9000",
    "sg:province":"Oost-Vlaanderen",
    "wof:name":"Catherine De Cuyper",
    "wof:placetype":"venue"
},
  "geometry": {"coordinates":[3.7222840786,51.0466651917],"type":"Point"}
}