{
  "type": "Feature",
  "properties": {
    "addr:full":"Pierlapont 10 Zedelgem West-Vlaanderen 8210",
    "addr:housenumber":"10",
    "addr:postcode":"8210",
    "addr:street":"Pierlapont",
    "iso:country":"BE",
    "sg:address":"Pierlapont 10",
    "sg:city":"Zedelgem",
    "sg:classifiers":[
        {
            "category":"Building & Trades",
            "subcategory":"Construction",
            "type":"Services"
        }
    ],
    "sg:phone":"+32 50 20 05 55",
    "sg:postcode":"8210",
    "sg:province":"West-Vlaanderen",
    "sg:tags":[
        "installation",
        "-",
        "central",
        "heating"
    ],
    "wof:name":"Van De Putte W",
    "wof:placetype":"venue"
},
  "geometry": {"coordinates":[3.1458399296,51.1376457214],"type":"Point"}
}