{
  "type": "Feature",
  "properties": {
    "addr:full":"Avenue Du Castel 75 Sint-lambrechts-woluwe/woluwe-saint-lambert Bruxelles-Capitale 1200",
    "addr:housenumber":"75",
    "addr:postcode":"1200",
    "addr:street":"Avenue Du Castel",
    "iso:country":"BE",
    "sg:address":"Avenue Du Castel 75",
    "sg:city":"Sint-lambrechts-woluwe/woluwe-saint-lambert",
    "sg:orig_category":"D\u00e9corateurs d'int\u00e9rieur",
    "sg:phone":"+32 2 735 94 03",
    "sg:postcode":"1200",
    "sg:province":"Bruxelles-Capitale",
    "wof:name":"Brigitte Boitte",
    "wof:placetype":"venue"
},
  "geometry": {"coordinates":[4.4106860161,50.8409843445],"type":"Point"}
}