{
  "type": "Feature",
  "properties": {
    "addr:full":"Korenstraat 2 Oostkamp West-Vlaanderen 8020",
    "addr:housenumber":"2",
    "addr:postcode":"8020",
    "addr:street":"Korenstraat",
    "iso:country":"BE",
    "sg:address":"Korenstraat 2",
    "sg:city":"Oostkamp",
    "sg:classifiers":[
        {
            "category":"Arena",
            "subcategory":"Sports Club",
            "type":"Entertainment"
        }
    ],
    "sg:phone":"+32 50 82 38 05",
    "sg:postcode":"8020",
    "sg:province":"West-Vlaanderen",
    "sg:tags":[
        "de"
    ],
    "wof:name":"De Nacht",
    "wof:placetype":"venue"
},
  "geometry": {"coordinates":[3.2285349369,51.1561813354],"type":"Point"}
}