{
  "type": "Feature",
  "properties": {
    "iso:country":"BE",
    "sg:address":"Zeedijk Centrum 471",
    "sg:city":"Koksijde (oostduinkerke)",
    "sg:classifiers":[
        {
            "category":"Tea Room",
            "subcategory":"None",
            "type":"Food & Drink"
        }
    ],
    "sg:phone":"+32 58 51 51 30",
    "sg:postcode":"8670",
    "sg:province":"West-Vlaanderen",
    "wof:name":"De Verbeelding Bvba",
    "wof:placetype":"venue"
},
  "geometry": {"coordinates":[2.6742999554,51.1335334778],"type":"Point"}
}