{
  "type": "Feature",
  "properties": {
    "iso:country":"BE",
    "sg:address":"Chauss\u00e9e Du Roeulx 368",
    "sg:city":"Mons",
    "sg:classifiers":[
        {
            "category":"Retail",
            "subcategory":"Repair Shop",
            "type":"Services"
        }
    ],
    "sg:phone":"+32 65 82 51 36",
    "sg:postcode":"7000",
    "sg:province":"Hainaut",
    "sg:tags":[
        "denture"
    ],
    "wof:name":"Defrise O",
    "wof:placetype":"venue"
},
  "geometry": {"coordinates":[3.9939060211,50.4578933716],"type":"Point"}
}