{
  "type": "Feature",
  "properties": {
    "addr:full":"Aardseweg 114 Geel Antwerpen 2440",
    "addr:housenumber":"114",
    "addr:postcode":"2440",
    "addr:street":"Aardseweg",
    "iso:country":"BE",
    "sg:address":"Aardseweg 114",
    "sg:city":"Geel",
    "sg:orig_category":"Dierenartsen",
    "sg:phone":"+32 14 85 25 92",
    "sg:postcode":"2440",
    "sg:province":"Antwerpen",
    "wof:name":"Danny Coomans",
    "wof:placetype":"venue"
},
  "geometry": {"coordinates":[5.0080361366,51.2130889893],"type":"Point"}
}