{
  "type": "Feature",
  "properties": {
    "addr:full":"Rue De L'ancienne Poste 1a Marche-en-famenne Luxembourg 6900",
    "addr:housenumber":"1a",
    "addr:postcode":"6900",
    "addr:street":"Rue De L'Ancienne Poste",
    "iso:country":"BE",
    "sg:address":"Rue De L'ancienne Poste 1a",
    "sg:city":"Marche-en-famenne",
    "sg:orig_category":"Plaatsen van vloer- and muurbekleding Vloer- and muurbekleding",
    "sg:phone":"+32 84 31 20 37",
    "sg:postcode":"6900",
    "sg:province":"Luxembourg",
    "wof:name":"Poncin M",
    "wof:placetype":"venue"
},
  "geometry": {"coordinates":[5.3188261986,50.2025604248],"type":"Point"}
}