{
  "type": "Feature",
  "properties": {
    "addr:full":"Kapelsesteenweg 310 Brasschaat Antwerpen 2930",
    "addr:housenumber":"310",
    "addr:postcode":"2930",
    "addr:street":"Kapelsesteenweg",
    "iso:country":"BE",
    "sg:address":"Kapelsesteenweg 310",
    "sg:city":"Brasschaat",
    "sg:classifiers":[
        {
            "category":"Personal",
            "subcategory":"Beauty Salon",
            "type":"Services"
        }
    ],
    "sg:phone":"+32 3 664 60 05",
    "sg:postcode":"2930",
    "sg:province":"Antwerpen",
    "sg:tags":[
        "de",
        "coiffure"
    ],
    "wof:name":"Coiffure Mary-lou",
    "wof:placetype":"venue"
},
  "geometry": {"coordinates":[4.4457321167,51.2903900146],"type":"Point"}
}