{
  "type": "Feature",
  "properties": {
    "iso:country":"BE",
    "sg:address":"Alsteen 3",
    "sg:city":"Waregem (desselgem)",
    "sg:classifiers":[
        {
            "category":"Building & Trades",
            "subcategory":"Pest Control",
            "type":"Services"
        }
    ],
    "sg:phone":"+32 56 32 47 06",
    "sg:postcode":"8792",
    "sg:province":"West-Vlaanderen",
    "sg:tags":[
        "painting",
        "contractor"
    ],
    "wof:name":"Demeyer L",
    "wof:placetype":"venue"
},
  "geometry": {"coordinates":[3.3661279678,50.889591217],"type":"Point"}
}