{
  "type": "Feature",
  "properties": {
    "addr:full":"Schoolstraat 1 Tervuren Vlaams-Brabant 3080",
    "addr:housenumber":"1",
    "addr:postcode":"3080",
    "addr:street":"Schoolstraat",
    "iso:country":"BE",
    "sg:address":"Schoolstraat 1",
    "sg:city":"Tervuren",
    "sg:orig_category":"Banques and organismes de cr\u00e9dit",
    "sg:phone":"+32 2 767 42 96",
    "sg:postcode":"3080",
    "sg:province":"Vlaams-Brabant",
    "wof:name":"Fortis",
    "wof:placetype":"venue"
},
  "geometry": {"coordinates":[4.5347709656,50.8563804626],"type":"Point"}
}