{
  "type": "Feature",
  "properties": {
    "addr:full":"Beeldstraat 10 Sint-niklaas Oost-Vlaanderen 9100",
    "addr:housenumber":"10",
    "addr:postcode":"9100",
    "addr:street":"Beeldstraat",
    "iso:country":"BE",
    "sg:address":"Beeldstraat 10",
    "sg:city":"Sint-niklaas",
    "sg:classifiers":[
        {
            "category":"Bars & Pubs",
            "subcategory":"Lounge",
            "type":"Food & Drink"
        }
    ],
    "sg:phone":"+32 3 776 73 44",
    "sg:postcode":"9100",
    "sg:province":"Oost-Vlaanderen",
    "sg:tags":[
        "d",
        "restaurant",
        "organisation",
        "\u00c0",
        "domicile",
        "fast",
        "catering",
        "emporter",
        "livraison",
        "restaurants"
    ],
    "wof:name":"Gasthof Malpertus",
    "wof:placetype":"venue"
},
  "geometry": {"coordinates":[4.1964488029,51.168712616],"type":"Point"}
}