{
  "type": "Feature",
  "properties": {
    "iso:country":"BE",
    "sg:address":"Rue De Rotheux 39",
    "sg:city":"Seraing",
    "sg:classifiers":[
        {
            "category":"Professional",
            "subcategory":"Lawyer & Legal Services",
            "type":"Services"
        }
    ],
    "sg:phone":"+32 4 337 82 99",
    "sg:postcode":"4100",
    "sg:province":"Li\u00e8ge",
    "wof:name":"Omari Fatima",
    "wof:placetype":"venue"
},
  "geometry": {"coordinates":[5.5055379868,50.5871162415],"type":"Point"}
}