{
  "type": "Feature",
  "properties": {
    "addr:full":"Rue De Gr\u00e2ce 7 Gr\u00e2ce-hollogne (gr\u00e2ce-berleur) Li\u00e8ge 4460",
    "addr:housenumber":"7",
    "addr:postcode":"4460",
    "addr:street":"Rue De Gra\u0302Ce;Gra\u0302Ce-Berleur",
    "iso:country":"BE",
    "sg:address":"Rue De Gr\u00e2ce 7",
    "sg:city":"Gr\u00e2ce-hollogne (gr\u00e2ce-berleur)",
    "sg:classifiers":[
        {
            "category":"Building & Trades",
            "subcategory":"Construction",
            "type":"Services"
        }
    ],
    "sg:phone":"+32 4 233 95 13",
    "sg:postcode":"4460",
    "sg:province":"Li\u00e8ge",
    "sg:tags":[
        "installation",
        "-",
        "central",
        "heating"
    ],
    "wof:name":"Lamotte Sprl",
    "wof:placetype":"venue"
},
  "geometry": {"coordinates":[5.4859600067,50.6373634338],"type":"Point"}
}