{
  "type": "Feature",
  "properties": {
    "addr:full":"Quai Industrie 153 Bruxelles (anderlecht) Bruxelles-Capitale 1070",
    "addr:housenumber":"153",
    "addr:postcode":"1070",
    "addr:street":"Quai Industrie",
    "iso:country":"BE",
    "sg:address":"Quai Industrie 153",
    "sg:city":"Bruxelles (anderlecht)",
    "sg:classifiers":[
        {
            "category":"Autos & Motor Vehicles",
            "subcategory":"Automobile Sales",
            "type":"Retail Goods"
        }
    ],
    "sg:phone":"+32 2 527 33 33",
    "sg:postcode":"1070",
    "sg:province":"Bruxelles-Capitale",
    "sg:tags":[
        "car",
        "used",
        "-"
    ],
    "wof:name":"Auto Verdoba Sa",
    "wof:placetype":"venue"
},
  "geometry": {"coordinates":[4.3360548019,50.8485374451],"type":"Point"}
}