{
  "type": "Feature",
  "properties": {
    "addr:full":"Noordgijzelstraat 43 Gent Oost-Vlaanderen 9031",
    "addr:housenumber":"43",
    "addr:postcode":"9031",
    "addr:street":"Noordgijzelstraat;Oost-Vlaanderen",
    "iso:country":"BE",
    "sg:address":"Noordgijzelstraat 43",
    "sg:city":"Gent",
    "sg:orig_category":"Woningbouw",
    "sg:phone":"+32 9 226 70 39",
    "sg:postcode":"9031",
    "sg:province":"Oost-Vlaanderen",
    "wof:name":"Van De Cappelle & Zoon",
    "wof:placetype":"venue"
},
  "geometry": {"coordinates":[3.6310899258,51.0709915161],"type":"Point"}
}