{
  "type": "Feature",
  "properties": {
    "iso:country":"BE",
    "sg:address":"Oostwinkeldorp 3",
    "sg:city":"Zomergem",
    "sg:orig_category":"Kapsalons",
    "sg:phone":"+32 9 378 36 68",
    "sg:postcode":"9931",
    "sg:province":"Oost-Vlaanderen",
    "wof:name":"Sabine Van De Walle",
    "wof:placetype":"venue"
},
  "geometry": {"coordinates":[3.5235459805,51.1513214111],"type":"Point"}
}