{
  "type": "Feature",
  "properties": {
    "addr:full":"Zenobe Grammestraat 53 Gent (sint-amandsberg) Oost-Vlaanderen 9040",
    "addr:housenumber":"53",
    "addr:postcode":"9040",
    "addr:street":"Grammestraat",
    "iso:country":"BE",
    "sg:address":"Zenobe Grammestraat 53",
    "sg:city":"Gent (sint-amandsberg)",
    "sg:classifiers":[
        {
            "category":"Freight",
            "type":"Transportation"
        }
    ],
    "sg:phone":"+32 9 228 35 45",
    "sg:postcode":"9040",
    "sg:province":"Oost-Vlaanderen",
    "sg:tags":[
        "-",
        "transport"
    ],
    "wof:name":"Transport De Winter-de Raedemaeker",
    "wof:placetype":"venue"
},
  "geometry": {"coordinates":[3.7832069397,51.075630188],"type":"Point"}
}