{
  "type": "Feature",
  "properties": {
    "addr:full":"Lostraat 20 Aalter Oost-Vlaanderen 9880",
    "addr:housenumber":"20",
    "addr:postcode":"9880",
    "addr:street":"Lostraat",
    "iso:country":"BE",
    "sg:address":"Lostraat 20",
    "sg:city":"Aalter",
    "sg:orig_category":"Traitements param\u00e9dicaux",
    "sg:phone":"+32 9 375 30 50",
    "sg:postcode":"9880",
    "sg:province":"Oost-Vlaanderen",
    "wof:name":"Wit-gele Kruis",
    "wof:placetype":"venue"
},
  "geometry": {"coordinates":[3.4502649307,51.0822906494],"type":"Point"}
}