{
  "type": "Feature",
  "properties": {
    "iso:country":"BE",
    "sg:address":"Groenstraat 54",
    "sg:city":"Destelbergen",
    "sg:orig_category":"Woningbouw",
    "sg:phone":"+32 9 355 16 72",
    "sg:postcode":"9070",
    "sg:province":"Oost-Vlaanderen",
    "wof:name":"Gino Van De Velde",
    "wof:placetype":"venue"
},
  "geometry": {"coordinates":[3.8319370747,51.0697517395],"type":"Point"}
}