{
  "type": "Feature",
  "properties": {
    "addr:full":"Hoogstraat 101 Brussel/bruxelles Bruxelles-Capitale 1000",
    "addr:housenumber":"101",
    "addr:postcode":"1000",
    "addr:street":"Hoogstraat;/",
    "iso:country":"BE",
    "sg:address":"Hoogstraat 101",
    "sg:city":"Brussel/bruxelles",
    "sg:orig_category":"Verlichting and huishoudartikelen",
    "sg:phone":"+32 2 502 15 75",
    "sg:postcode":"1000",
    "sg:province":"Bruxelles-Capitale",
    "wof:name":"Maison Sortil\u00c8ges",
    "wof:placetype":"venue"
},
  "geometry": {"coordinates":[4.35060215,50.8394432068],"type":"Point"}
}