{
  "type": "Feature",
  "properties": {
    "iso:country":"BE",
    "sg:address":"March\u00e9 12",
    "sg:city":"Theux",
    "sg:classifiers":[
        {
            "category":"Education",
            "subcategory":"University",
            "type":"Public Place"
        }
    ],
    "sg:phone":"+32 87 54 29 70",
    "sg:postcode":"4910",
    "sg:province":"Li\u00e8ge",
    "sg:tags":[
        "higher"
    ],
    "wof:name":"Isell-st-roch",
    "wof:placetype":"venue"
},
  "geometry": {"coordinates":[5.8130488396,50.5356216431],"type":"Point"}
}