{
  "type": "Feature",
  "properties": {
    "iso:country":"BE",
    "sg:address":"Rue Al'vaulx 41",
    "sg:city":"Walcourt",
    "sg:classifiers":[
        {
            "category":"Health Services",
            "subcategory":"Doctor",
            "type":"Services"
        }
    ],
    "sg:phone":"+32 71 61 28 50",
    "sg:postcode":"5650",
    "sg:province":"Namur",
    "sg:tags":[
        "medicinephysicians",
        "surgeon"
    ],
    "wof:name":"Henrard G",
    "wof:placetype":"venue"
},
  "geometry": {"coordinates":[4.4327788353,50.2533721924],"type":"Point"}
}