{
  "type": "Feature",
  "properties": {
    "addr:full":"Sint-laureinsesteenweg 4 Eeklo Oost-Vlaanderen 9900",
    "addr:housenumber":"4",
    "addr:postcode":"9900",
    "addr:street":"Sint-Laureinsesteenweg",
    "iso:country":"BE",
    "sg:address":"Sint-laureinsesteenweg 4",
    "sg:city":"Eeklo",
    "sg:orig_category":"Woningbouw",
    "sg:phone":"+32 9 378 28 18",
    "sg:postcode":"9900",
    "sg:province":"Oost-Vlaanderen",
    "wof:name":"Marc Grammens",
    "wof:placetype":"venue"
},
  "geometry": {"coordinates":[3.5169610977,51.2081871033],"type":"Point"}
}