{
  "type": "Feature",
  "properties": {
    "iso:country":"BE",
    "sg:address":"Fauvillers-centre 45a",
    "sg:city":"Fauvillers",
    "sg:orig_category":"Installation de menuiserie en bois and plastique",
    "sg:phone":"+32 63 60 04 51",
    "sg:postcode":"6637",
    "sg:province":"Luxembourg",
    "wof:name":"Joseph Asselborn",
    "wof:placetype":"venue"
},
  "geometry": {"coordinates":[5.6666798592,49.8505592346],"type":"Point"}
}