{
  "type": "Feature",
  "properties": {
    "iso:country":"BE",
    "sg:address":"Margarethalaan 19",
    "sg:city":"Genk",
    "sg:classifiers":[
        {
            "category":"Retail",
            "subcategory":"Laundry & Dry Cleaning",
            "type":"Services"
        }
    ],
    "sg:phone":"+32 89 35 49 61",
    "sg:postcode":"3600",
    "sg:province":"Limburg",
    "sg:tags":[
        "self",
        "-"
    ],
    "wof:name":"Gima",
    "wof:placetype":"venue"
},
  "geometry": {"coordinates":[5.4805440903,50.9766654968],"type":"Point"}
}