{
  "type": "Feature",
  "properties": {
    "iso:country":"BE",
    "sg:address":"Kapelhofstraat 24",
    "sg:city":"Hasselt",
    "sg:orig_category":"Afbraak- and draineerwerken",
    "sg:phone":"+32 11 59 13 41",
    "sg:postcode":"3500",
    "sg:province":"Limburg",
    "wof:name":"Ballet",
    "wof:placetype":"venue"
},
  "geometry": {"coordinates":[5.3104529381,50.9047775269],"type":"Point"}
}