{
  "type": "Feature",
  "properties": {
    "iso:country":"BE",
    "sg:address":"Rue De Flemalle 40",
    "sg:city":"Jemeppe-sur-meuse",
    "sg:classifiers":[
        {
            "category":"Exhibition Hall",
            "type":"Public Place"
        }
    ],
    "sg:phone":"+32 4 234 14 15",
    "sg:postcode":"4101",
    "sg:province":"Li\u00e8ge",
    "sg:tags":[
        "steel"
    ],
    "wof:name":"Bl Construct S.c.r.l.",
    "wof:placetype":"venue"
},
  "geometry": {"coordinates":[5.4924969673,50.6096076965],"type":"Point"}
}