{
  "type": "Feature",
  "properties": {
    "iso:country":"BE",
    "sg:address":"Place March\u00e9 Aux L\u00e9gumes 12",
    "sg:city":"Namur",
    "sg:classifiers":[
        {
            "category":"Bars & Pubs",
            "type":"Food & Drink"
        }
    ],
    "sg:phone":"+32 81 23 19 39",
    "sg:postcode":"5000",
    "sg:province":"Namur",
    "sg:tags":[
        "tavern"
    ],
    "wof:name":"Vieille Fontaine (la)",
    "wof:placetype":"venue"
},
  "geometry": {"coordinates":[4.864136219,50.4633255005],"type":"Point"}
}