{
  "type": "Feature",
  "properties": {
    "iso:country":"BE",
    "sg:address":"Dorpsstraat 128",
    "sg:city":"Tielt-winge",
    "sg:orig_category":"Installatie van houten of kunststof schrijnwerk",
    "sg:phone":"+32 16 50 17 18",
    "sg:postcode":"3390",
    "sg:province":"Vlaams-Brabant",
    "wof:name":"Vounckx W",
    "wof:placetype":"venue"
},
  "geometry": {"coordinates":[4.9159798622,50.9429397583],"type":"Point"}
}