{
  "type": "Feature",
  "properties": {
    "addr:full":"Rue De La Fleur D'oranger 29 Box 231 Bruxelles (woluwe-saint-pierre) Bruxelles-Capitale 1150",
    "addr:housenumber":"29",
    "addr:postcode":"1150",
    "addr:street":"Rue De La Fleur D'Oranger;Box 231",
    "iso:country":"BE",
    "sg:address":"Rue De La Fleur D'oranger 29 Box 231",
    "sg:city":"Bruxelles (woluwe-saint-pierre)",
    "sg:classifiers":[
        {
            "category":"Communications",
            "type":"Services"
        }
    ],
    "sg:phone":"+32 2 772 38 64",
    "sg:postcode":"1150",
    "sg:province":"Bruxelles-Capitale",
    "sg:tags":[
        "translator"
    ],
    "wof:name":"Van Reijsen I",
    "wof:placetype":"venue"
},
  "geometry": {"coordinates":[4.4626970291,50.8458786011],"type":"Point"}
}