{
  "type": "Feature",
  "properties": {
    "iso:country":"BE",
    "sg:address":"Heistr",
    "sg:city":"St. Niklaas",
    "sg:classifiers":[
        {
            "category":"Banks & Credit Unions",
            "subcategory":"Bank",
            "type":"Services"
        }
    ],
    "sg:phone":"+32 3 766 32 63",
    "sg:postcode":"9100",
    "sg:province":"Oost-Vlaanderen",
    "wof:name":"Aslk-cger Bank",
    "wof:placetype":"venue"
},
  "geometry": {"coordinates":[4.1257348061,51.1729316711],"type":"Point"}
}