{
  "type": "Feature",
  "properties": {
    "addr:full":"Rue Mosty 2bbis Blegny Li\u00e8ge 4671",
    "addr:housenumber":"2bbis",
    "addr:postcode":"4671",
    "addr:street":"Rue Mosty",
    "iso:country":"BE",
    "sg:address":"Rue Mosty 2bbis",
    "sg:city":"Blegny",
    "sg:classifiers":[
        {
            "category":"Personal",
            "subcategory":"Beauty Salon",
            "type":"Services"
        }
    ],
    "sg:phone":"+32 4 362 61 62",
    "sg:postcode":"4671",
    "sg:province":"Li\u00e8ge",
    "sg:tags":[
        "de",
        "coiffure"
    ],
    "wof:name":"Sylvie Roujob",
    "wof:placetype":"venue"
},
  "geometry": {"coordinates":[5.6820588112,50.6480712891],"type":"Point"}
}