{
  "type": "Feature",
  "properties": {
    "iso:country":"BE",
    "sg:address":"Vierscharestraat 54",
    "sg:city":"Damme",
    "sg:orig_category":"Boucheries",
    "sg:phone":"+32 50 36 30 88",
    "sg:postcode":"8340",
    "sg:province":"West-Vlaanderen",
    "wof:name":"Dany Dhaens",
    "wof:placetype":"venue"
},
  "geometry": {"coordinates":[3.2968950272,51.2262687683],"type":"Point"}
}