{
  "type": "Feature",
  "properties": {
    "addr:full":"Kempische Steenweg 272 Hasselt Limburg 3500",
    "addr:housenumber":"272",
    "addr:postcode":"3500",
    "addr:street":"Kempische Steenweg",
    "iso:country":"BE",
    "sg:address":"Kempische Steenweg 272",
    "sg:city":"Hasselt",
    "sg:classifiers":[
        {
            "category":"Bars & Pubs",
            "type":"Food & Drink"
        }
    ],
    "sg:phone":"+32 11 21 46 75",
    "sg:postcode":"3500",
    "sg:province":"Limburg",
    "wof:name":"Myred",
    "wof:placetype":"venue"
},
  "geometry": {"coordinates":[5.3410902023,50.9396095276],"type":"Point"}
}