{
  "type": "Feature",
  "properties": {
    "addr:full":"Heirweg 28 Zemst Vlaams-Brabant 1982",
    "addr:housenumber":"28",
    "addr:postcode":"1982",
    "addr:street":"Heirweg;Vlaams-Brabant",
    "iso:country":"BE",
    "sg:address":"Heirweg 28",
    "sg:city":"Zemst",
    "sg:classifiers":[
        {
            "category":"Cafe",
            "type":"Food & Drink"
        }
    ],
    "sg:phone":"+32 15 61 08 01",
    "sg:postcode":"1982",
    "sg:province":"Vlaams-Brabant",
    "sg:tags":[
        "caf\u00e9s"
    ],
    "wof:name":"Fernande Van Den Haute",
    "wof:placetype":"venue"
},
  "geometry": {"coordinates":[4.4945502281,50.9746704102],"type":"Point"}
}