{
  "type": "Feature",
  "properties": {
    "iso:country":"BE",
    "sg:address":"Diesterstraat 188",
    "sg:city":"Tessenderlo",
    "sg:classifiers":[
        {
            "category":"Retail",
            "subcategory":"Veterinary Services",
            "type":"Services"
        }
    ],
    "sg:phone":"+32 13 66 78 90",
    "sg:postcode":"3980",
    "sg:province":"Limburg",
    "sg:tags":[
        "veterinarian"
    ],
    "wof:name":"Van Hove E",
    "wof:placetype":"venue"
},
  "geometry": {"coordinates":[5.0881409645,51.0547485352],"type":"Point"}
}