{
  "type": "Feature",
  "properties": {
    "iso:country":"BE",
    "sg:address":"Statiestraat 10",
    "sg:city":"Dentergem",
    "sg:orig_category":"Entretien and r\u00e9parations de voitures",
    "sg:phone":"+32 51 63 36 55",
    "sg:postcode":"8720",
    "sg:province":"West-Vlaanderen",
    "wof:name":"Garage Neirinck",
    "wof:placetype":"venue"
},
  "geometry": {"coordinates":[3.4157180786,50.9660263062],"type":"Point"}
}