{
  "type": "Feature",
  "properties": {
    "iso:country":"BE",
    "sg:address":"Bosstraat 25ba",
    "sg:city":"Bree",
    "sg:classifiers":[
        {
            "category":"Cafe",
            "type":"Food & Drink"
        }
    ],
    "sg:phone":"+32 89 86 84 70",
    "sg:postcode":"3960",
    "sg:province":"Limburg",
    "sg:tags":[
        "caf\u00e9s"
    ],
    "wof:name":"Caf\u00c9 De Stal",
    "wof:placetype":"venue"
},
  "geometry": {"coordinates":[5.6615891457,51.1287879944],"type":"Point"}
}