{
  "type": "Feature",
  "properties": {
    "iso:country":"BE",
    "sg:address":"Avenue Du Ch\u00cane 199",
    "sg:city":"Verviers",
    "sg:orig_category":"Pharmaciens",
    "sg:phone":"+32 87 22 33 75",
    "sg:postcode":"4802",
    "sg:province":"Li\u00e8ge",
    "wof:name":"Guy Evrard",
    "wof:placetype":"venue"
},
  "geometry": {"coordinates":[5.8668670654,50.5723495483],"type":"Point"}
}