{
  "type": "Feature",
  "properties": {
    "iso:country":"BE",
    "sg:address":"Industrieweg 12",
    "sg:city":"Grobbendonk",
    "sg:classifiers":[
        {
            "category":"Government",
            "subcategory":"Post Office",
            "type":"Public Place"
        }
    ],
    "sg:phone":"+32 14 50 79 10",
    "sg:postcode":"2280",
    "sg:province":"Antwerpen",
    "sg:tags":[
        "stamp",
        "dating",
        "-",
        "name"
    ],
    "wof:name":"Mauquoy Medal Company",
    "wof:placetype":"venue"
},
  "geometry": {"coordinates":[4.7361121178,51.1788406372],"type":"Point"}
}