{
  "type": "Feature",
  "properties": {
    "addr:full":"Weg Naar Opitter 44 Meeuwen-gruitrode Limburg 3670",
    "addr:housenumber":"44",
    "addr:postcode":"3670",
    "addr:street":"Weg Naar Opitter",
    "iso:country":"BE",
    "sg:address":"Weg Naar Opitter 44",
    "sg:city":"Meeuwen-gruitrode",
    "sg:orig_category":"Afbraak- and draineerwerken Bouwmaterialen Gh Bouwwerktuigen Gh Goederenvervoer over de weg Huisvuil",
    "sg:phone":"+32 89 85 41 15",
    "sg:postcode":"3670",
    "sg:province":"Limburg",
    "wof:name":"Vermeulen",
    "wof:placetype":"venue"
},
  "geometry": {"coordinates":[5.6203351021,51.094783783],"type":"Point"}
}