{
  "type": "Feature",
  "properties": {
    "addr:full":"Platteput 1 Buggenhout Oost-Vlaanderen 9255",
    "addr:housenumber":"1",
    "addr:postcode":"9255",
    "addr:street":"Platteput",
    "iso:country":"BE",
    "sg:address":"Platteput 1",
    "sg:city":"Buggenhout",
    "sg:orig_category":"Fitnesscentra",
    "sg:phone":"+32 52 33 10 01",
    "sg:postcode":"9255",
    "sg:province":"Oost-Vlaanderen",
    "wof:name":"Cossaer",
    "wof:placetype":"venue"
},
  "geometry": {"coordinates":[4.1934890747,51.013168335],"type":"Point"}
}