{
  "type": "Feature",
  "properties": {
    "iso:country":"BE",
    "sg:address":"Westouterstraat 28",
    "sg:city":"Poperinge",
    "sg:orig_category":"Gespecialiseerde residenti\u00eble bouw",
    "sg:phone":"+32 57 33 84 59",
    "sg:postcode":"8970",
    "sg:province":"West-Vlaanderen",
    "wof:name":"Serge Cuvelier",
    "wof:placetype":"venue"
},
  "geometry": {"coordinates":[2.7260620594,50.8499641418],"type":"Point"}
}