{
  "type": "Feature",
  "properties": {
    "addr:full":"Rue Du Gravier 21 Wavre Brabant Wallon 1300",
    "addr:housenumber":"21;1300",
    "addr:street":"Rue Du Gravier",
    "iso:country":"BE",
    "sg:address":"Rue Du Gravier 21",
    "sg:city":"Wavre",
    "sg:classifiers":[
        {
            "category":"Health Services",
            "subcategory":"Doctor",
            "type":"Services"
        }
    ],
    "sg:phone":"+32 10 22 58 99",
    "sg:postcode":"1300",
    "sg:province":"Brabant Wallon",
    "sg:tags":[
        "medicinephysicians",
        "surgeon"
    ],
    "wof:name":"Costy F",
    "wof:placetype":"venue"
},
  "geometry": {"coordinates":[4.6068677902,50.7141723633],"type":"Point"}
}