{
  "type": "Feature",
  "properties": {
    "iso:country":"BE",
    "sg:address":"Rue Hambursin 22",
    "sg:city":"Gembloux-sur-orneau (gembloux)",
    "sg:classifiers":[
        {
            "category":"Building & Trades",
            "subcategory":"Equipment Rental",
            "type":"Services"
        }
    ],
    "sg:phone":"+32 81 61 41 95",
    "sg:postcode":"5030",
    "sg:province":"Namur",
    "sg:tags":[
        "lighting",
        "-",
        "fixture"
    ],
    "wof:name":"Triline Location",
    "wof:placetype":"venue"
},
  "geometry": {"coordinates":[4.6877307892,50.5621795654],"type":"Point"}
}