{
  "type": "Feature",
  "properties": {
    "addr:full":"Italielei 179 Antwerpen Antwerpen 2000",
    "addr:housenumber":"179",
    "addr:postcode":"2000",
    "addr:street":"Italielei",
    "iso:country":"BE",
    "sg:address":"Italielei 179",
    "sg:city":"Antwerpen",
    "sg:orig_category":"Cliniques and h\u00f4pitaux. Instituts de beaut\u00e9",
    "sg:phone":"+32 3 231 30 65",
    "sg:postcode":"2000",
    "sg:province":"Antwerpen",
    "wof:name":"F.c.a.",
    "wof:placetype":"venue"
},
  "geometry": {"coordinates":[4.4163899422,51.2230796814],"type":"Point"}
}