{
  "type": "Feature",
  "properties": {
    "addr:full":"R. Jacq.-pieter Ballings 11 Jette Bruxelles-Capitale 1090",
    "addr:housenumber":"11",
    "addr:postcode":"1090",
    "addr:street":"Ballings",
    "iso:country":"BE",
    "sg:address":"R. Jacq.-pieter Ballings 11",
    "sg:city":"Jette",
    "sg:classifiers":[
        {
            "category":"Personal",
            "subcategory":"Beauty Salon",
            "type":"Services"
        }
    ],
    "sg:phone":"+32 2 478 83 80",
    "sg:postcode":"1090",
    "sg:province":"Bruxelles-Capitale",
    "sg:tags":[
        "de",
        "coiffure"
    ],
    "wof:name":"Coiffure Sandra",
    "wof:placetype":"venue"
},
  "geometry": {"coordinates":[4.3191227913,50.8869667053],"type":"Point"}
}