{
  "type": "Feature",
  "properties": {
    "addr:full":"Mgr. Raeymaekersstraat 13 Hulshout Antwerpen 2235",
    "addr:housenumber":"13",
    "addr:postcode":"2235",
    "addr:street":"Mgr. Raeymaekersstraat",
    "iso:country":"BE",
    "sg:address":"Mgr. Raeymaekersstraat 13",
    "sg:city":"Hulshout",
    "sg:orig_category":"Enseignement maternel and primaire",
    "sg:phone":"+32 16 69 93 33",
    "sg:postcode":"2235",
    "sg:province":"Antwerpen",
    "wof:name":"Vrije Basisschool",
    "wof:placetype":"venue"
},
  "geometry": {"coordinates":[4.78875494,51.0758056641],"type":"Point"}
}