{
  "type": "Feature",
  "properties": {
    "addr:full":"Koning Albertlaan 114 Brussel/bruxelles Bruxelles-Capitale 1120",
    "addr:housenumber":"114",
    "addr:postcode":"1120",
    "addr:street":"Koning Albertlaan;/",
    "iso:country":"BE",
    "sg:address":"Koning Albertlaan 114",
    "sg:city":"Brussel/bruxelles",
    "sg:orig_category":"Zalen voor culturele evenementen",
    "sg:phone":"+32 2 262 08 84",
    "sg:postcode":"1120",
    "sg:province":"Bruxelles-Capitale",
    "wof:name":"Collectif 1984",
    "wof:placetype":"venue"
},
  "geometry": {"coordinates":[4.3982248306,50.9002685547],"type":"Point"}
}