{
  "type": "Feature",
  "properties": {
    "addr:full":"Nijverheidspark 7 Beringen Limburg 3580",
    "addr:housenumber":"7",
    "addr:postcode":"3580",
    "addr:street":"Nijverheidspark",
    "iso:country":"BE",
    "sg:address":"Nijverheidspark 7",
    "sg:city":"Beringen",
    "sg:classifiers":[
        {
            "category":"Autos & Motor Vehicles",
            "subcategory":"Motorcycle Sales",
            "type":"Retail Goods"
        }
    ],
    "sg:phone":"+32 11 42 39 86",
    "sg:postcode":"3580",
    "sg:province":"Limburg",
    "sg:tags":[
        "motorbike"
    ],
    "wof:name":"Aixam/moons J",
    "wof:placetype":"venue"
},
  "geometry": {"coordinates":[5.2172307968,51.052898407],"type":"Point"}
}