{
  "type": "Feature",
  "properties": {
    "addr:full":"Slingerstraat 2 Torhout West-Vlaanderen 8820",
    "addr:housenumber":"2",
    "addr:postcode":"8820",
    "addr:street":"Slingerstraat",
    "iso:country":"BE",
    "sg:address":"Slingerstraat 2",
    "sg:city":"Torhout",
    "sg:classifiers":[
        {
            "category":"Building & Trades",
            "subcategory":"Landscaping Services",
            "type":"Services"
        }
    ],
    "sg:phone":"+32 51 72 38 09",
    "sg:postcode":"8820",
    "sg:province":"West-Vlaanderen",
    "sg:tags":[
        "gardening",
        "garden",
        "maintenance"
    ],
    "wof:name":"Voorspoels",
    "wof:placetype":"venue"
},
  "geometry": {"coordinates":[3.1066539288,51.0365219116],"type":"Point"}
}