{
  "type": "Feature",
  "properties": {
    "addr:full":"Rue G\u00c9rardrie 31 Li\u00c8ge Li\u00e8ge 4000",
    "addr:housenumber":"31",
    "addr:postcode":"4000",
    "addr:street":"Rue Ge\u0301Rardrie",
    "iso:country":"BE",
    "sg:address":"Rue G\u00c9rardrie 31",
    "sg:city":"Li\u00c8ge",
    "sg:orig_category":"Instituts de beaut\u00e9. Mobilier and \u00e9quipement m\u00e9nager Gr",
    "sg:phone":"+32 4 223 00 91",
    "sg:postcode":"4000",
    "sg:province":"Li\u00e8ge",
    "wof:name":"Anne Andr\u00c9",
    "wof:placetype":"venue"
},
  "geometry": {"coordinates":[5.5743141174,50.6441612244],"type":"Point"}
}