{
  "type": "Feature",
  "properties": {
    "iso:country":"BE",
    "sg:address":"Stationsstraat 3",
    "sg:city":"Koekelare",
    "sg:classifiers":[
        {
            "category":"Manufacturing",
            "subcategory":"Textiles",
            "type":"Manufacturing & Wholesale Goods"
        }
    ],
    "sg:phone":"+32 51 58 96 45",
    "sg:postcode":"8680",
    "sg:province":"West-Vlaanderen",
    "sg:tags":[
        "retail",
        "-"
    ],
    "wof:name":"De Duytsche W",
    "wof:placetype":"venue"
},
  "geometry": {"coordinates":[2.9736270905,51.090133667],"type":"Point"}
}