{
  "type": "Feature",
  "properties": {
    "iso:country":"BE",
    "sg:address":"Rue Emile Vandervelde 39",
    "sg:city":"Ittre (virginal-samme)",
    "sg:classifiers":[
        {
            "category":"Recreation",
            "subcategory":"Arcade",
            "type":"Entertainment"
        }
    ],
    "sg:phone":"+32 67 34 20 90",
    "sg:postcode":"1460",
    "sg:province":"Brabant Wallon",
    "sg:tags":[
        "machine",
        "amusement"
    ],
    "wof:name":"Lecrignier P",
    "wof:placetype":"venue"
},
  "geometry": {"coordinates":[4.2075209618,50.6401405334],"type":"Point"}
}