{
  "type": "Feature",
  "properties": {
    "iso:country":"BE",
    "sg:address":"Rue Du Biat Bouquet 19",
    "sg:city":"Grez-doiceau",
    "sg:orig_category":"Peinture. Rev\u00eatements pour sols and murs",
    "sg:phone":"+32 10 84 14 18",
    "sg:postcode":"1390",
    "sg:province":"Brabant Wallon",
    "wof:name":"Georges Dumoulin",
    "wof:placetype":"venue"
},
  "geometry": {"coordinates":[4.7040309906,50.7396774292],"type":"Point"}
}