{
  "type": "Feature",
  "properties": {
    "addr:full":"Middelwindenstraat 16 Landen Vlaams-Brabant 3400",
    "addr:housenumber":"16",
    "addr:postcode":"3400",
    "addr:street":"Middelwindenstraat",
    "iso:country":"BE",
    "sg:address":"Middelwindenstraat 16",
    "sg:city":"Landen",
    "sg:orig_category":"Rev\u00eatements pour sols and murs",
    "sg:phone":"+32 16 78 82 39",
    "sg:postcode":"3400",
    "sg:province":"Vlaams-Brabant",
    "wof:name":"Georges Engels",
    "wof:placetype":"venue"
},
  "geometry": {"coordinates":[5.0390582085,50.7634620667],"type":"Point"}
}