{
  "type": "Feature",
  "properties": {
    "iso:country":"BE",
    "sg:address":"Avenue Des Martyrs 161",
    "sg:city":"Fleron",
    "sg:classifiers":[
        {
            "category":"Fast Food",
            "type":"Food & Drink"
        }
    ],
    "sg:phone":"+32 4 355 25 88",
    "sg:postcode":"4620",
    "sg:province":"Li\u00e8ge",
    "sg:tags":[
        "\u00c0",
        "emporter",
        "restaurants"
    ],
    "wof:name":"Traiteur Thanh Thuy",
    "wof:placetype":"venue"
},
  "geometry": {"coordinates":[5.6779551506,50.6150283813],"type":"Point"}
}