{
  "type": "Feature",
  "properties": {
    "addr:full":"Jules De Saint-genoisstraat 55 Gent (gentbrugge) Oost-Vlaanderen 9050",
    "addr:housenumber":"55",
    "addr:postcode":"9050",
    "addr:street":"Jules De Saint-Genoisstraat",
    "iso:country":"BE",
    "sg:address":"Jules De Saint-genoisstraat 55",
    "sg:city":"Gent (gentbrugge)",
    "sg:classifiers":[
        {
            "category":"Professional",
            "subcategory":"Management & Consulting",
            "type":"Services"
        }
    ],
    "sg:phone":"+32 9 231 20 05",
    "sg:postcode":"9050",
    "sg:province":"Oost-Vlaanderen",
    "sg:tags":[
        "consultant"
    ],
    "wof:name":"Incoman Consult",
    "wof:placetype":"venue"
},
  "geometry": {"coordinates":[3.7592830658,51.0300636292],"type":"Point"}
}