{
  "type": "Feature",
  "properties": {
    "addr:full":"Rue Willy Brogneaux 26 Ham-sur-heure-nalinnes Hainaut 6120",
    "addr:housenumber":"26",
    "addr:postcode":"6120",
    "addr:street":"Rue Willy Brogneaux;Hainaut",
    "iso:country":"BE",
    "sg:address":"Rue Willy Brogneaux 26",
    "sg:city":"Ham-sur-heure-nalinnes",
    "sg:orig_category":"M\u00e9decins and sp\u00e9cialistes",
    "sg:phone":"+32 71 21 45 52",
    "sg:postcode":"6120",
    "sg:province":"Hainaut",
    "wof:name":"N. Boulanger",
    "wof:placetype":"venue"
},
  "geometry": {"coordinates":[4.4146871567,50.3556594849],"type":"Point"}
}