{
  "type": "Feature",
  "properties": {
    "iso:country":"BE",
    "sg:address":"Holstraat 43-45",
    "sg:city":"Heusden-zolder (zolder)",
    "sg:classifiers":[
        {
            "category":"Bars & Pubs",
            "type":"Food & Drink"
        }
    ],
    "sg:phone":"+32 11 53 31 26",
    "sg:postcode":"3550",
    "sg:province":"Limburg",
    "wof:name":"Bierhandel Beerten",
    "wof:placetype":"venue"
},
  "geometry": {"coordinates":[5.3158669472,51.020904541],"type":"Point"}
}