{
  "type": "Feature",
  "properties": {
    "addr:full":"Rue Coliche 2 Viroinval Namur 5670",
    "addr:housenumber":"2",
    "addr:postcode":"5670",
    "addr:street":"Rue Coliche",
    "iso:country":"BE",
    "sg:address":"Rue Coliche 2",
    "sg:city":"Viroinval",
    "sg:classifiers":[
        {
            "category":"Cafe",
            "type":"Food & Drink"
        }
    ],
    "sg:phone":"+32 60 39 02 41",
    "sg:postcode":"5670",
    "sg:province":"Namur",
    "sg:tags":[
        "caf\u00e9s"
    ],
    "wof:name":"Marc Collin",
    "wof:placetype":"venue"
},
  "geometry": {"coordinates":[4.6069750786,50.0740852356],"type":"Point"}
}