{
  "type": "Feature",
  "properties": {
    "iso:country":"BE",
    "sg:address":"Grote Markt 33",
    "sg:city":"Ieper",
    "sg:classifiers":[
        {
            "category":"Travel",
            "subcategory":"Hotels & Motels",
            "type":"Entertainment"
        }
    ],
    "sg:phone":"+32 57 20 01 93",
    "sg:postcode":"8900",
    "sg:province":"West-Vlaanderen",
    "sg:tags":[
        "restaurant"
    ],
    "wof:name":"Hotel De Sultan",
    "wof:placetype":"venue"
},
  "geometry": {"coordinates":[2.8865380287,50.850856781],"type":"Point"}
}