{
  "type": "Feature",
  "properties": {
    "addr:full":"Westlaan 57 Roeselare West-Vlaanderen 8800",
    "addr:housenumber":"57",
    "addr:postcode":"8800",
    "addr:street":"Westlaan",
    "iso:country":"BE",
    "sg:address":"Westlaan 57",
    "sg:city":"Roeselare",
    "sg:classifiers":[
        {
            "category":"Bakery",
            "type":"Food & Drink"
        }
    ],
    "sg:phone":"+32 51 20 32 47",
    "sg:postcode":"8800",
    "sg:province":"West-Vlaanderen",
    "sg:tags":[
        "confectioner",
        "baker"
    ],
    "wof:name":"Verbrugghe P",
    "wof:placetype":"venue"
},
  "geometry": {"coordinates":[3.1184780598,50.9373512268],"type":"Point"}
}