{
  "type": "Feature",
  "properties": {
    "iso:country":"BE",
    "sg:address":"Place R\u00c9publique-fran\u00c7aise 25",
    "sg:city":"Li\u00c8ge",
    "sg:classifiers":[
        {
            "category":"Fast Food",
            "type":"Food & Drink"
        }
    ],
    "sg:phone":"+32 4 223 33 03",
    "sg:postcode":"4000",
    "sg:province":"Li\u00e8ge",
    "sg:tags":[
        "\u00c0",
        "emporter",
        "restaurants"
    ],
    "wof:name":"Snack-bar Gide",
    "wof:placetype":"venue"
},
  "geometry": {"coordinates":[5.572655201,50.6430664062],"type":"Point"}
}