{
  "type": "Feature",
  "properties": {
    "addr:full":"Komedieplaats 15 Antwerpen Antwerpen 2000",
    "addr:housenumber":"15",
    "addr:postcode":"2000",
    "addr:street":"Komedieplaats",
    "iso:country":"BE",
    "sg:address":"Komedieplaats 15",
    "sg:city":"Antwerpen",
    "sg:classifiers":[
        {
            "category":"Shopping",
            "subcategory":"Clothing, Apparel, & Fashions",
            "type":"Retail Goods"
        }
    ],
    "sg:phone":"+32 3 226 84 24",
    "sg:postcode":"2000",
    "sg:province":"Antwerpen",
    "sg:tags":[
        "lady",
        "clothing",
        "-"
    ],
    "wof:name":"College",
    "wof:placetype":"venue"
},
  "geometry": {"coordinates":[4.4064922333,51.2163505554],"type":"Point"}
}