{
  "type": "Feature",
  "properties": {
    "iso:country":"BE",
    "sg:address":"Rue Hector Denis 29",
    "sg:city":"Gr\u00e2ce-hollogne (gr\u00e2ce-berleur)",
    "sg:classifiers":[
        {
            "category":"Education",
            "subcategory":"Music School",
            "type":"Public Place"
        }
    ],
    "sg:phone":"+32 4 246 09 37",
    "sg:postcode":"4460",
    "sg:province":"Li\u00e8ge",
    "sg:tags":[
        "rental",
        "grandstand",
        "stage",
        "-",
        "mfg"
    ],
    "wof:name":"Studio Phenix",
    "wof:placetype":"venue"
},
  "geometry": {"coordinates":[5.498857975,50.6450424194],"type":"Point"}
}