{
  "type": "Feature",
  "properties": {
    "addr:full":"Rue De Claire Fontaine 199 Chapelle-lez-herlaimont Hainaut 7160",
    "addr:housenumber":"199",
    "addr:postcode":"7160",
    "addr:street":"Rue De Claire Fontaine",
    "iso:country":"BE",
    "sg:address":"Rue De Claire Fontaine 199",
    "sg:city":"Chapelle-lez-herlaimont",
    "sg:orig_category":"Boekhouders",
    "sg:phone":"+32 64 44 62 68",
    "sg:postcode":"7160",
    "sg:province":"Hainaut",
    "wof:name":"Luc Treutens",
    "wof:placetype":"venue"
},
  "geometry": {"coordinates":[4.2815651894,50.4882545471],"type":"Point"}
}