{
  "type": "Feature",
  "properties": {
    "iso:country":"BE",
    "sg:address":"Wielewaalstraat 6",
    "sg:city":"Geel",
    "sg:orig_category":"Herstellingen and onderhoud van auto's",
    "sg:phone":"+32 14 58 23 13",
    "sg:postcode":"2440",
    "sg:province":"Antwerpen",
    "wof:name":"Garage Van Pelt",
    "wof:placetype":"venue"
},
  "geometry": {"coordinates":[4.9689621925,51.1734848022],"type":"Point"}
}