{
  "type": "Feature",
  "properties": {
    "addr:full":"Rue Gustave Gilson 178 Bruxelles Bruxelles-Capitale 1020",
    "addr:housenumber":"178",
    "addr:postcode":"1020",
    "addr:street":"Rue Gustave Gilson",
    "iso:country":"BE",
    "sg:address":"Rue Gustave Gilson 178",
    "sg:city":"Bruxelles",
    "sg:classifiers":[
        {
            "category":"Education",
            "subcategory":"Special Training",
            "type":"Public Place"
        }
    ],
    "sg:phone":"+32 479 46 93 64",
    "sg:postcode":"1020",
    "sg:province":"Bruxelles-Capitale",
    "sg:tags":[
        "school",
        "sailing"
    ],
    "wof:name":"Navistop",
    "wof:placetype":"venue"
},
  "geometry": {"coordinates":[4.3379020691,50.8860626221],"type":"Point"}
}