{
  "type": "Feature",
  "properties": {
    "iso:country":"BE",
    "sg:address":"159 Bld E Jacqmain",
    "sg:city":"Bruxelles",
    "sg:classifiers":[
        {
            "category":"Banks & Credit Unions",
            "subcategory":"Financial Services",
            "type":"Services"
        }
    ],
    "sg:phone":"+32 2 205 81 11",
    "sg:postcode":"1000",
    "sg:province":"Bruxelles-Capitale",
    "sg:tags":[
        "banking",
        "finance",
        "insurance"
    ],
    "wof:name":"Bank Card Company Sa",
    "wof:placetype":"venue"
},
  "geometry": {"coordinates":[4.354364872,50.8543663025],"type":"Point"}
}