{
  "type": "Feature",
  "properties": {
    "addr:full":"Rue Maurice Bertrand 528 Andenne Namur 5300",
    "addr:housenumber":"528",
    "addr:postcode":"5300",
    "addr:street":"Rue Maurice Bertrand",
    "iso:country":"BE",
    "sg:address":"Rue Maurice Bertrand 528",
    "sg:city":"Andenne",
    "sg:orig_category":"Rundveehouders",
    "sg:phone":"+32 85 82 56 93",
    "sg:postcode":"5300",
    "sg:province":"Namur",
    "wof:name":"Etienne Ryckaert",
    "wof:placetype":"venue"
},
  "geometry": {"coordinates":[5.0953598022,50.4872207642],"type":"Point"}
}