{
  "type": "Feature",
  "properties": {
    "addr:full":"Hooeind 64 Mol Antwerpen 2400",
    "addr:housenumber":"64",
    "addr:postcode":"2400",
    "addr:street":"Hooeind",
    "iso:country":"BE",
    "sg:address":"Hooeind 64",
    "sg:city":"Mol",
    "sg:classifiers":[
        {
            "category":"Organizations",
            "subcategory":"Community Association",
            "type":"Services"
        }
    ],
    "sg:phone":"+32 14 31 04 70",
    "sg:postcode":"2400",
    "sg:province":"Antwerpen",
    "sg:tags":[
        "organisation"
    ],
    "wof:name":"Vvkm",
    "wof:placetype":"venue"
},
  "geometry": {"coordinates":[5.072291851,51.1757507324],"type":"Point"}
}