{
  "type": "Feature",
  "properties": {
    "iso:country":"BE",
    "sg:address":"Baan Naar Helchteren 15",
    "sg:city":"Peer",
    "sg:classifiers":[
        {
            "category":"Building & Trades",
            "subcategory":"Construction",
            "type":"Services"
        }
    ],
    "sg:phone":"+32 11 79 34 00",
    "sg:postcode":"3990",
    "sg:province":"Limburg",
    "sg:tags":[
        "stucco",
        "contractor"
    ],
    "wof:name":"Dhr Jozef Soors",
    "wof:placetype":"venue"
},
  "geometry": {"coordinates":[5.4372768402,51.0764427185],"type":"Point"}
}