{
  "type": "Feature",
  "properties": {
    "addr:full":"Sadzot 4 Erezee Luxembourg 6997",
    "addr:housenumber":"4",
    "addr:postcode":"6997",
    "addr:street":"Sadzot",
    "iso:country":"BE",
    "sg:address":"Sadzot 4",
    "sg:city":"Erezee",
    "sg:orig_category":"Rundveehouders",
    "sg:phone":"+32 86 47 71 88",
    "sg:postcode":"6997",
    "sg:province":"Luxembourg",
    "wof:name":"Roger Sepult",
    "wof:placetype":"venue"
},
  "geometry": {"coordinates":[5.5977602005,50.2840614319],"type":"Point"}
}