{
  "type": "Feature",
  "properties": {
    "iso:country":"BE",
    "sg:address":"Rue M\u00c9an 23",
    "sg:city":"Li\u00c8ge",
    "sg:classifiers":[
        {
            "category":"Restaurant",
            "type":"Food & Drink"
        }
    ],
    "sg:phone":"+32 4 349 02 20",
    "sg:postcode":"4020",
    "sg:province":"Li\u00e8ge",
    "wof:name":"Le Maquis D'abidjan",
    "wof:placetype":"venue"
},
  "geometry": {"coordinates":[5.5805058479,50.6376495361],"type":"Point"}
}