{
  "type": "Feature",
  "properties": {
    "iso:country":"BE",
    "sg:address":"Molenbaan 78",
    "sg:city":"Vorselaar",
    "sg:orig_category":"Rundveehouders",
    "sg:phone":"+32 14 51 52 65",
    "sg:postcode":"2290",
    "sg:province":"Antwerpen",
    "wof:name":"Patrick Van Der Donck",
    "wof:placetype":"venue"
},
  "geometry": {"coordinates":[4.7608108521,51.2101554871],"type":"Point"}
}