{
  "type": "Feature",
  "properties": {
    "addr:full":"Ernest Allardstraat 33 Brussel/bruxelles Bruxelles-Capitale 1000",
    "addr:housenumber":"33",
    "addr:postcode":"1000",
    "addr:street":"Ernest Allardstraat;/",
    "iso:country":"BE",
    "sg:address":"Ernest Allardstraat 33",
    "sg:city":"Brussel/bruxelles",
    "sg:orig_category":"Antiek Diverse zakelijke dienstverlening",
    "sg:phone":"+32 2 512 25 23",
    "sg:postcode":"1000",
    "sg:province":"Bruxelles-Capitale",
    "wof:name":"Galery Ph Serck Xx",
    "wof:placetype":"venue"
},
  "geometry": {"coordinates":[4.3538651466,50.8397140503],"type":"Point"}
}