{
  "type": "Feature",
  "properties": {
    "addr:full":"Holt 25 Bilzen Limburg 3740",
    "addr:housenumber":"25",
    "addr:postcode":"3740",
    "addr:street":"Holt",
    "iso:country":"BE",
    "sg:address":"Holt 25",
    "sg:city":"Bilzen",
    "sg:classifiers":[
        {
            "category":"Utilities",
            "subcategory":"Natural Gas",
            "type":"Services"
        }
    ],
    "sg:phone":"+32 496 10 26 58",
    "sg:postcode":"3740",
    "sg:province":"Limburg",
    "sg:tags":[
        "welding"
    ],
    "wof:name":"Oyen G",
    "wof:placetype":"venue"
},
  "geometry": {"coordinates":[5.4852089882,50.8845367432],"type":"Point"}
}