{
  "type": "Feature",
  "properties": {
    "iso:country":"BE",
    "sg:address":"Boulevard Albert Elisabeth 34 Box 1",
    "sg:city":"Mons",
    "sg:classifiers":[
        {
            "category":"Professional",
            "subcategory":"Accounting & Tax Preparation",
            "type":"Services"
        }
    ],
    "sg:phone":"+32 65 76 00 17",
    "sg:postcode":"7000",
    "sg:province":"Hainaut",
    "sg:tags":[
        "bookkeeper"
    ],
    "wof:name":"Nutile F",
    "wof:placetype":"venue"
},
  "geometry": {"coordinates":[3.9518280029,50.446762085],"type":"Point"}
}