{
  "type": "Feature",
  "properties": {
    "addr:full":"Lar Menen (rekkem) West-Vlaanderen 8930",
    "addr:postcode":"8930",
    "iso:country":"BE",
    "sg:address":"Lar",
    "sg:city":"Menen (rekkem)",
    "sg:classifiers":[
        {
            "category":"Airport",
            "subcategory":"International",
            "type":"Transportation"
        }
    ],
    "sg:phone":"+32 56 42 06 40",
    "sg:postcode":"8930",
    "sg:province":"West-Vlaanderen",
    "sg:tags":[
        "-",
        "transport"
    ],
    "wof:name":"G.d.l.",
    "wof:placetype":"venue"
},
  "geometry": {"coordinates":[3.1944880486,50.7747917175],"type":"Point"}
}