{
  "type": "Feature",
  "properties": {
    "iso:country":"BE",
    "sg:address":"Groenestraat 3",
    "sg:city":"Alveringem",
    "sg:orig_category":"Caf\u00e9s Ruimtes voor conferenties, recepties and feesten",
    "sg:phone":"+32 58 29 96 69",
    "sg:postcode":"8691",
    "sg:province":"West-Vlaanderen",
    "wof:name":"'t Vlasblomtje",
    "wof:placetype":"venue"
},
  "geometry": {"coordinates":[2.6652519703,50.9701004028],"type":"Point"}
}