{
  "type": "Feature",
  "properties": {
    "addr:full":"Leopold Sabbestraat 70 Menen West-Vlaanderen 8930",
    "addr:housenumber":"70",
    "addr:postcode":"8930",
    "addr:street":"Leopold Sabbestraat",
    "iso:country":"BE",
    "sg:address":"Leopold Sabbestraat 70",
    "sg:city":"Menen",
    "sg:orig_category":"Installation de menuiserie en bois and plastique",
    "sg:phone":"+32 56 41 21 33",
    "sg:postcode":"8930",
    "sg:province":"West-Vlaanderen",
    "wof:name":"Gilbert Kind",
    "wof:placetype":"venue"
},
  "geometry": {"coordinates":[3.1282699108,50.7988700867],"type":"Point"}
}