{
  "type": "Feature",
  "properties": {
    "iso:country":"BE",
    "sg:address":"Rue Pisonchamps 38",
    "sg:city":"Fl\u00e9malle",
    "sg:classifiers":[
        {
            "category":"Retail",
            "subcategory":"Animal Services",
            "type":"Services"
        }
    ],
    "sg:phone":"+32 4 233 97 19",
    "sg:postcode":"4400",
    "sg:province":"Li\u00e8ge",
    "sg:tags":[
        "breeding",
        "selling",
        "-",
        "dog"
    ],
    "wof:name":"Les P'tits Ponpons",
    "wof:placetype":"venue"
},
  "geometry": {"coordinates":[5.4667749405,50.6175384521],"type":"Point"}
}