{
  "type": "Feature",
  "properties": {
    "addr:full":"Rue De Mons 54 Soignies Hainaut 7060",
    "addr:housenumber":"54",
    "addr:postcode":"7060",
    "addr:street":"Rue De Mons",
    "iso:country":"BE",
    "sg:address":"Rue De Mons 54",
    "sg:city":"Soignies",
    "sg:classifiers":[
        {
            "category":"Shopping",
            "subcategory":"Clothing, Apparel, & Fashions",
            "type":"Retail Goods"
        }
    ],
    "sg:phone":"+32 67 33 32 29",
    "sg:postcode":"7060",
    "sg:province":"Hainaut",
    "sg:tags":[
        "boutique"
    ],
    "wof:name":"Cachemire",
    "wof:placetype":"venue"
},
  "geometry": {"coordinates":[4.0717349052,50.5779647827],"type":"Point"}
}