{
  "type": "Feature",
  "properties": {
    "iso:country":"BE",
    "sg:address":"Paradijsstraat 8",
    "sg:city":"Herentals",
    "sg:orig_category":"V\u00eatements, chaussures and accessoires Gr",
    "sg:phone":"+32 14 26 76 51",
    "sg:postcode":"2200",
    "sg:province":"Antwerpen",
    "wof:name":"Wouters-van Hoochten",
    "wof:placetype":"venue"
},
  "geometry": {"coordinates":[4.848279953,51.1585502625],"type":"Point"}
}