{
  "type": "Feature",
  "properties": {
    "addr:full":"Rue De Recogne 42 Libin Luxembourg 6890",
    "addr:housenumber":"42",
    "addr:postcode":"6890",
    "addr:street":"Rue De Recogne",
    "iso:country":"BE",
    "sg:address":"Rue De Recogne 42",
    "sg:city":"Libin",
    "sg:orig_category":"Elektrische installaties voor woningen",
    "sg:phone":"+32 61 65 61 54",
    "sg:postcode":"6890",
    "sg:province":"Luxembourg",
    "wof:name":"Patrick Gerard",
    "wof:placetype":"venue"
},
  "geometry": {"coordinates":[5.2658061981,49.9760551453],"type":"Point"}
}