{
  "type": "Feature",
  "properties": {
    "addr:full":"Heidestraat 157 Diepenbeek Limburg 3590",
    "addr:housenumber":"157",
    "addr:postcode":"3590",
    "addr:street":"Heidestraat",
    "iso:country":"BE",
    "sg:address":"Heidestraat 157",
    "sg:city":"Diepenbeek",
    "sg:orig_category":"Enseignement maternel and primaire",
    "sg:phone":"+32 11 32 19 48",
    "sg:postcode":"3590",
    "sg:province":"Limburg",
    "wof:name":"Vrije Lagere School",
    "wof:placetype":"venue"
},
  "geometry": {"coordinates":[5.4201397896,50.9327697754],"type":"Point"}
}