{
  "type": "Feature",
  "properties": {
    "addr:full":"Ter Elst 3 Wevelgem West-Vlaanderen 8560",
    "addr:housenumber":"3",
    "addr:postcode":"8560",
    "addr:street":"Ter Elst",
    "iso:country":"BE",
    "sg:address":"Ter Elst 3",
    "sg:city":"Wevelgem",
    "sg:orig_category":"Traitements param\u00e9dicaux",
    "sg:phone":"+32 56 42 09 35",
    "sg:postcode":"8560",
    "sg:province":"West-Vlaanderen",
    "wof:name":"Caroline Lapauw",
    "wof:placetype":"venue"
},
  "geometry": {"coordinates":[3.2118659019,50.8421936035],"type":"Point"}
}