{
  "type": "Feature",
  "properties": {
    "iso:country":"BE",
    "sg:address":"Kouterweg 85",
    "sg:city":"Izegem",
    "sg:orig_category":"Slagers",
    "sg:phone":"+32 51 30 19 96",
    "sg:postcode":"8870",
    "sg:province":"West-Vlaanderen",
    "wof:name":"Nicolaas Vanlandeghem",
    "wof:placetype":"venue"
},
  "geometry": {"coordinates":[3.2223010063,50.9246520996],"type":"Point"}
}