{
  "type": "Feature",
  "properties": {
    "iso:country":"BE",
    "sg:address":"Jules Van Praetstraat 13",
    "sg:city":"Brussel/bruxelles",
    "sg:classifiers":[
        {
            "category":"Fast Food",
            "type":"Food & Drink"
        }
    ],
    "sg:phone":"+32 2 502 29 51",
    "sg:postcode":"1000",
    "sg:province":"Bruxelles-Capitale",
    "sg:tags":[
        "meeneem",
        "restaurant"
    ],
    "wof:name":"Au Bambou Fleur",
    "wof:placetype":"venue"
},
  "geometry": {"coordinates":[4.3482599258,50.8483695984],"type":"Point"}
}