{
  "type": "Feature",
  "properties": {
    "addr:full":"Rue De La Filature 2 Mouscron (herseaux) Hainaut 7712",
    "addr:housenumber":"2",
    "addr:postcode":"7712",
    "addr:street":"Rue De La Filature",
    "iso:country":"BE",
    "sg:address":"Rue De La Filature 2",
    "sg:city":"Mouscron (herseaux)",
    "sg:classifiers":[
        {
            "category":"Shopping",
            "subcategory":"Pets & Pet Supplies",
            "type":"Retail Goods"
        }
    ],
    "sg:phone":"+32 56 84 30 39",
    "sg:postcode":"7712",
    "sg:province":"Hainaut",
    "sg:tags":[
        "shop",
        "-"
    ],
    "wof:name":"Animalerie De La Gare",
    "wof:placetype":"venue"
},
  "geometry": {"coordinates":[3.2486140728,50.7140235901],"type":"Point"}
}