{
  "type": "Feature",
  "properties": {
    "iso:country":"BE",
    "sg:address":"Ginderoverstraat 71",
    "sg:city":"Diepenbeek",
    "sg:classifiers":[
        {
            "category":"Cafe",
            "type":"Food & Drink"
        }
    ],
    "sg:phone":"+32 11 32 17 50",
    "sg:postcode":"3590",
    "sg:province":"Limburg",
    "sg:tags":[
        "caf\u00e9s"
    ],
    "wof:name":"Caf\u00c9 Borly",
    "wof:placetype":"venue"
},
  "geometry": {"coordinates":[5.3973698616,50.9275398254],"type":"Point"}
}