{
  "type": "Feature",
  "properties": {
    "iso:country":"BE",
    "sg:address":"Zwaluwstraat 132",
    "sg:city":"Londerzeel",
    "sg:orig_category":"Advocaten and juridische adviseurs",
    "sg:phone":"+32 52 34 10 79",
    "sg:postcode":"1840",
    "sg:province":"Vlaams-Brabant",
    "wof:name":"Luc Van Litsenborg",
    "wof:placetype":"venue"
},
  "geometry": {"coordinates":[4.2375388145,51.0113487244],"type":"Point"}
}