{
  "type": "Feature",
  "properties": {
    "addr:full":"Kortrijksesteenweg 1040 Gent Oost-Vlaanderen 9051",
    "addr:postcode":"1040;9051",
    "addr:street":"Kortrijksesteenweg",
    "iso:country":"BE",
    "sg:address":"Kortrijksesteenweg 1040",
    "sg:city":"Gent",
    "sg:orig_category":"D\u00e9m\u00e9nagements",
    "sg:phone":"+32 9 242 80 20",
    "sg:postcode":"9051",
    "sg:province":"Oost-Vlaanderen",
    "wof:name":"Shurgard Self-storage",
    "wof:placetype":"venue"
},
  "geometry": {"coordinates":[3.6514649391,51.0148277283],"type":"Point"}
}