{
  "type": "Feature",
  "properties": {
    "addr:full":"Av. Des Longues Waides 6 Verviers Li\u00e8ge 4802",
    "addr:housenumber":"6",
    "addr:postcode":"4802",
    "addr:street":"Av. Des Longues Waides",
    "iso:country":"BE",
    "sg:address":"Av. Des Longues Waides 6",
    "sg:city":"Verviers",
    "sg:orig_category":"Kapsalons",
    "sg:phone":"+32 87 22 77 84",
    "sg:postcode":"4802",
    "sg:province":"Li\u00e8ge",
    "wof:name":"Coiffure Dany",
    "wof:placetype":"venue"
},
  "geometry": {"coordinates":[5.8841571808,50.5802459717],"type":"Point"}
}