{
  "type": "Feature",
  "properties": {
    "addr:full":"Lieven Bauwensstraat 18 Brugge West-Vlaanderen 8200",
    "addr:housenumber":"18",
    "addr:postcode":"8200",
    "addr:street":"Lieven Bauwensstraat",
    "iso:country":"BE",
    "sg:address":"Lieven Bauwensstraat 18",
    "sg:city":"Brugge",
    "sg:orig_category":"Articles textiles and tissus de d\u00e9coration Fab. Grossistes divers. Articles de f\u00eate, farces and attr",
    "sg:phone":"+32 50 31 82 23",
    "sg:postcode":"8200",
    "sg:province":"West-Vlaanderen",
    "wof:name":"Insignia",
    "wof:placetype":"venue"
},
  "geometry": {"coordinates":[3.1964700222,51.2147598267],"type":"Point"}
}