{
  "type": "Feature",
  "properties": {
    "addr:full":"Provinciesteenweg 496 Boechout Antwerpen 2530",
    "addr:housenumber":"496",
    "addr:postcode":"2530",
    "addr:street":"Provinciesteenweg",
    "iso:country":"BE",
    "sg:address":"Provinciesteenweg 496",
    "sg:city":"Boechout",
    "sg:classifiers":[
        {
            "category":"Autos & Motor Vehicles",
            "subcategory":"Automobile Sales",
            "type":"Retail Goods"
        }
    ],
    "sg:phone":"+32 3 455 26 24",
    "sg:postcode":"2530",
    "sg:province":"Antwerpen",
    "sg:tags":[
        "equipment",
        "transport"
    ],
    "wof:name":"Ch Smout Nv",
    "wof:placetype":"venue"
},
  "geometry": {"coordinates":[4.5106492043,51.1594467163],"type":"Point"}
}