{
  "type": "Feature",
  "properties": {
    "iso:country":"BE",
    "sg:address":"Amedeus Stockmanslei 109",
    "sg:city":"Mortsel",
    "sg:classifiers":[
        {
            "category":"Building & Trades",
            "subcategory":"Pest Control",
            "type":"Services"
        }
    ],
    "sg:phone":"+32 3 440 65 10",
    "sg:postcode":"2640",
    "sg:province":"Antwerpen",
    "sg:tags":[
        "painting",
        "contractor"
    ],
    "wof:name":"J.o.c.k. Bvba",
    "wof:placetype":"venue"
},
  "geometry": {"coordinates":[4.4529891014,51.1763534546],"type":"Point"}
}