{
  "type": "Feature",
  "properties": {
    "iso:country":"BE",
    "sg:address":"Everdongenlaan 9",
    "sg:city":"Turnhout",
    "sg:orig_category":"Pleisterwerk",
    "sg:phone":"+32 14 43 01 34",
    "sg:postcode":"2300",
    "sg:province":"Antwerpen",
    "wof:name":"Jozef Aerts",
    "wof:placetype":"venue"
},
  "geometry": {"coordinates":[4.9439711571,51.3001022339],"type":"Point"}
}