{
  "type": "Feature",
  "properties": {
    "addr:full":"Rue Des Ellebores 15 Watermael-boitsfort Bruxelles-Capitale 1170",
    "addr:housenumber":"15",
    "addr:postcode":"1170",
    "addr:street":"Rue Des Ellebores",
    "iso:country":"BE",
    "sg:address":"Rue Des Ellebores 15",
    "sg:city":"Watermael-boitsfort",
    "sg:orig_category":"Diverse bedrijfsbeheeradviesbureaus",
    "sg:phone":"+32 2 660 07 26",
    "sg:postcode":"1170",
    "sg:province":"Bruxelles-Capitale",
    "wof:name":"Price Consult",
    "wof:placetype":"venue"
},
  "geometry": {"coordinates":[4.4189491272,50.809715271],"type":"Point"}
}