{
  "type": "Feature",
  "properties": {
    "addr:full":"Acacialaan 40 Beveren (kieldrecht) Oost-Vlaanderen 9130",
    "addr:housenumber":"40",
    "addr:postcode":"9130",
    "addr:street":"Acacialaan",
    "iso:country":"BE",
    "sg:address":"Acacialaan 40",
    "sg:city":"Beveren (kieldrecht)",
    "sg:classifiers":[
        {
            "category":"Building & Trades",
            "subcategory":"Landscaping Services",
            "type":"Services"
        }
    ],
    "sg:phone":"+32 3 773 26 43",
    "sg:postcode":"9130",
    "sg:province":"Oost-Vlaanderen",
    "sg:tags":[
        "access",
        "pond",
        "laying-out",
        "-"
    ],
    "wof:name":"Dimitri J",
    "wof:placetype":"venue"
},
  "geometry": {"coordinates":[4.1760501862,51.2937202454],"type":"Point"}
}