{
  "type": "Feature",
  "properties": {
    "addr:full":"Sint-pietersmolenstraat 23-25 Brugge West-Vlaanderen 8000",
    "addr:postcode":"23-25;8000",
    "iso:country":"BE",
    "sg:address":"Sint-pietersmolenstraat 23-25",
    "sg:city":"Brugge",
    "sg:classifiers":[
        {
            "category":"Building & Trades",
            "subcategory":"Equipment Rental",
            "type":"Services"
        }
    ],
    "sg:phone":"+32 50 31 30 83",
    "sg:postcode":"8000",
    "sg:province":"West-Vlaanderen",
    "sg:tags":[
        "machine",
        "industrial",
        "dishwashing"
    ],
    "wof:name":"Decomac Nv",
    "wof:placetype":"venue"
},
  "geometry": {"coordinates":[3.2012059689,51.2328567505],"type":"Point"}
}