{
  "type": "Feature",
  "properties": {
    "iso:country":"BE",
    "sg:address":"Rue Watteeu 16",
    "sg:city":"Brussel/bruxelles",
    "sg:classifiers":[
        {
            "category":"Manufacturing",
            "subcategory":"Textiles",
            "type":"Manufacturing & Wholesale Goods"
        }
    ],
    "sg:phone":"+32 2 511 04 44",
    "sg:postcode":"1000",
    "sg:province":"Bruxelles-Capitale",
    "wof:name":"Maison Verschueren",
    "wof:placetype":"venue"
},
  "geometry": {"coordinates":[4.3538651466,50.8399391174],"type":"Point"}
}