{
  "type": "Feature",
  "properties": {
    "addr:full":"Fran\u00c7ois Stroobantstraat 14 Elsene/ixelles Bruxelles-Capitale 1050",
    "addr:housenumber":"14",
    "addr:postcode":"1050",
    "addr:street":"Franc\u0327Ois Stroobantstraat",
    "iso:country":"BE",
    "sg:address":"Fran\u00c7ois Stroobantstraat 14",
    "sg:city":"Elsene/ixelles",
    "sg:orig_category":"Herstelling leer and schoeisel Schoenen",
    "sg:phone":"+32 2 345 34 70",
    "sg:postcode":"1050",
    "sg:province":"Bruxelles-Capitale",
    "wof:name":"Cordonnerie Artisanale",
    "wof:placetype":"venue"
},
  "geometry": {"coordinates":[4.3549079895,50.8191871643],"type":"Point"}
}