{
  "type": "Feature",
  "properties": {
    "iso:country":"BE",
    "sg:address":"Dadizelestraat 52",
    "sg:city":"Wervik",
    "sg:orig_category":"D\u00e9molition d\u00b4immeubles and terrassements",
    "sg:phone":"+32 56 50 21 19",
    "sg:postcode":"8940",
    "sg:province":"West-Vlaanderen",
    "wof:name":"Cawegro",
    "wof:placetype":"venue"
},
  "geometry": {"coordinates":[3.0882430077,50.8338050842],"type":"Point"}
}