{
  "type": "Feature",
  "properties": {
    "iso:country":"BE",
    "sg:address":"Bourcy 121",
    "sg:city":"Bastogne (longvilly)",
    "sg:classifiers":[
        {
            "category":"Professional",
            "subcategory":"Testing Lab",
            "type":"Services"
        }
    ],
    "sg:phone":"+32 61 21 94 40",
    "sg:postcode":"6600",
    "sg:province":"Luxembourg",
    "sg:tags":[
        "chemist"
    ],
    "wof:name":"Pharmacie Pirotte J-l",
    "wof:placetype":"venue"
},
  "geometry": {"coordinates":[5.8130178452,50.0587768555],"type":"Point"}
}