{
  "type": "Feature",
  "properties": {
    "iso:country":"BE",
    "sg:address":"Guldenstraat 29",
    "sg:city":"Mechelen",
    "sg:orig_category":"Plomberie, chauffage and installations sanitaires",
    "sg:phone":"+32 15 61 27 18",
    "sg:postcode":"2800",
    "sg:province":"Antwerpen",
    "wof:name":"Flam Technic. Habo",
    "wof:placetype":"venue"
},
  "geometry": {"coordinates":[4.4769182205,51.025177002],"type":"Point"}
}