{
  "type": "Feature",
  "properties": {
    "iso:country":"BE",
    "sg:address":"Stationsstraat 129",
    "sg:city":"Sint-niklaas",
    "sg:orig_category":"HERSTELLING ELEKTRISCHE HUISHOUDAPPARATEN Huishoudapparaten, televisies and radio's",
    "sg:phone":"+32 3 777 74 06",
    "sg:postcode":"9100",
    "sg:province":"Oost-Vlaanderen",
    "wof:name":"Best-sellers",
    "wof:placetype":"venue"
},
  "geometry": {"coordinates":[4.1426830292,51.1697502136],"type":"Point"}
}