{
  "type": "Feature",
  "properties": {
    "iso:country":"BE",
    "sg:address":"Brielstraat 10",
    "sg:city":"Maldegem",
    "sg:classifiers":[
        {
            "category":"Organizations",
            "subcategory":"Labor Organization",
            "type":"Services"
        }
    ],
    "sg:phone":"+32 50 71 31 11",
    "sg:postcode":"9990",
    "sg:province":"Oost-Vlaanderen",
    "sg:tags":[
        "harness",
        "maker",
        "saddler"
    ],
    "wof:name":"Verhoestraete C & N",
    "wof:placetype":"venue"
},
  "geometry": {"coordinates":[3.4477250576,51.20652771],"type":"Point"}
}