{
  "type": "Feature",
  "properties": {
    "addr:full":"Chemin Du Champ Mahay 27 Durbuy Luxembourg 6941",
    "addr:housenumber":"27",
    "addr:postcode":"6941",
    "addr:street":"Chemin Du Champ Mahay",
    "iso:country":"BE",
    "sg:address":"Chemin Du Champ Mahay 27",
    "sg:city":"Durbuy",
    "sg:orig_category":"Rundveehouders",
    "sg:phone":"+32 86 34 41 68",
    "sg:postcode":"6941",
    "sg:province":"Luxembourg",
    "wof:name":"Leonie Collard",
    "wof:placetype":"venue"
},
  "geometry": {"coordinates":[5.4135389328,50.3780860901],"type":"Point"}
}