{
  "type": "Feature",
  "properties": {
    "iso:country":"BE",
    "sg:address":"Kapellestraat 13",
    "sg:city":"Aalst",
    "sg:orig_category":"Avocats and conseillers juridiques",
    "sg:phone":"+32 53 77 41 66",
    "sg:postcode":"9300",
    "sg:province":"Oost-Vlaanderen",
    "wof:name":"Val\u00c9rie Werbrouck",
    "wof:placetype":"venue"
},
  "geometry": {"coordinates":[4.0429601669,50.9359741211],"type":"Point"}
}