{
  "type": "Feature",
  "properties": {
    "iso:country":"BE",
    "sg:address":"Molenstraat 7",
    "sg:city":"Holsbeek",
    "sg:orig_category":"Woningbouw",
    "sg:phone":"+32 16 62 21 21",
    "sg:postcode":"3220",
    "sg:province":"Vlaams-Brabant",
    "wof:name":"Desiron M.",
    "wof:placetype":"venue"
},
  "geometry": {"coordinates":[4.8214688301,50.9316482544],"type":"Point"}
}