{
  "type": "Feature",
  "properties": {
    "iso:country":"BE",
    "sg:address":"'s-herenthagestraat 2",
    "sg:city":"Ieper (zillebeke)",
    "sg:classifiers":[
        {
            "category":"Retail",
            "subcategory":"Animal Services",
            "type":"Services"
        }
    ],
    "sg:phone":"+32 475 61 33 37",
    "sg:postcode":"8902",
    "sg:province":"West-Vlaanderen",
    "sg:tags":[
        "farrier"
    ],
    "wof:name":"Huys T",
    "wof:placetype":"venue"
},
  "geometry": {"coordinates":[2.9588749409,50.8362693787],"type":"Point"}
}