{
  "type": "Feature",
  "properties": {
    "addr:full":"Neerwindenstraat 22 Landen (neerwinden) Vlaams-Brabant 3400",
    "addr:housenumber":"22",
    "addr:postcode":"3400",
    "addr:street":"Neerwindenstraat",
    "iso:country":"BE",
    "sg:address":"Neerwindenstraat 22",
    "sg:city":"Landen (neerwinden)",
    "sg:classifiers":[
        {
            "category":"Health Services",
            "subcategory":"Dentist",
            "type":"Services"
        }
    ],
    "sg:phone":"+32 16 78 89 88",
    "sg:postcode":"3400",
    "sg:province":"Vlaams-Brabant",
    "wof:name":"Lefevre M",
    "wof:placetype":"venue"
},
  "geometry": {"coordinates":[5.0383138657,50.7655906677],"type":"Point"}
}