{
  "type": "Feature",
  "properties": {
    "iso:country":"BE",
    "sg:address":"Energielaan 11",
    "sg:city":"Kapellen",
    "sg:orig_category":"Meubles Fab. Meubles D\u00e9taillants, Am\u00e9nagement de B\u00e2timents et de Cuisines",
    "sg:phone":"+32 3 666 06 00",
    "sg:postcode":"2950",
    "sg:province":"Antwerpen",
    "wof:name":"Tillo M - Trading",
    "wof:placetype":"venue"
},
  "geometry": {"coordinates":[4.502726078,51.3553237915],"type":"Point"}
}