{
  "type": "Feature",
  "properties": {
    "addr:full":"Damberdstraat 29 Wevelgem West-Vlaanderen 8560",
    "addr:housenumber":"29",
    "addr:postcode":"8560",
    "addr:street":"Damberdstraat",
    "iso:country":"BE",
    "sg:address":"Damberdstraat 29",
    "sg:city":"Wevelgem",
    "sg:orig_category":"Notaires",
    "sg:phone":"+32 56 41 14 48",
    "sg:postcode":"8560",
    "sg:province":"West-Vlaanderen",
    "wof:name":"P. Vander Stichele",
    "wof:placetype":"venue"
},
  "geometry": {"coordinates":[3.1629340649,50.839263916],"type":"Point"}
}