{
  "type": "Feature",
  "properties": {
    "addr:full":"Rue Roger Salengro 49 Mouscron Hainaut 7700",
    "addr:housenumber":"49",
    "addr:postcode":"7700",
    "addr:street":"Rue Roger Salengro",
    "iso:country":"BE",
    "sg:address":"Rue Roger Salengro 49",
    "sg:city":"Mouscron",
    "sg:classifiers":[
        {
            "category":"Health Services",
            "subcategory":"Health Practitioner",
            "type":"Services"
        }
    ],
    "sg:phone":"+32 56 34 55 43",
    "sg:postcode":"7700",
    "sg:province":"Hainaut",
    "sg:tags":[
        "physiotherapist"
    ],
    "wof:name":"De Jonghe Sylvianne",
    "wof:placetype":"venue"
},
  "geometry": {"coordinates":[3.2071890831,50.7472686768],"type":"Point"}
}