{
  "type": "Feature",
  "properties": {
    "addr:full":"Van Campenhoutstraat 22 Bruxelles Bruxelles-Capitale 1000",
    "addr:housenumber":"22",
    "addr:postcode":"1000",
    "addr:street":"Van Campenhoutstraat",
    "iso:country":"BE",
    "sg:address":"Van Campenhoutstraat 22",
    "sg:city":"Bruxelles",
    "sg:orig_category":"Diverse bedrijfsbeheeradviesbureaus",
    "sg:phone":"+32 2 742 16 70",
    "sg:postcode":"1000",
    "sg:province":"Bruxelles-Capitale",
    "wof:name":"Eppa Belgium",
    "wof:placetype":"venue"
},
  "geometry": {"coordinates":[4.3857979774,50.8478736877],"type":"Point"}
}