{
  "type": "Feature",
  "properties": {
    "addr:full":"Tieltstraat 40 Pittem West-Vlaanderen 8740",
    "addr:housenumber":"40",
    "addr:postcode":"8740",
    "addr:street":"Tieltstraat",
    "iso:country":"BE",
    "sg:address":"Tieltstraat 40",
    "sg:city":"Pittem",
    "sg:orig_category":"Banques and organismes de cr\u00e9dit",
    "sg:phone":"+32 51 46 63 55",
    "sg:postcode":"8740",
    "sg:province":"West-Vlaanderen",
    "wof:name":"Fortis",
    "wof:placetype":"venue"
},
  "geometry": {"coordinates":[3.2663140297,50.9932250977],"type":"Point"}
}