{
  "type": "Feature",
  "properties": {
    "iso:country":"BE",
    "sg:address":"Gloriantlaan 59",
    "sg:city":"Antwerpen",
    "sg:classifiers":[
        {
            "category":"Health Services",
            "subcategory":"Health Practitioner",
            "type":"Services"
        }
    ],
    "sg:phone":"+32 3 219 20 24",
    "sg:postcode":"2050",
    "sg:province":"Antwerpen",
    "sg:tags":[
        "physiotherapist"
    ],
    "wof:name":"Lemense-de Brabanter",
    "wof:placetype":"venue"
},
  "geometry": {"coordinates":[4.3857941628,51.2245559692],"type":"Point"}
}