{
  "type": "Feature",
  "properties": {
    "iso:country":"BE",
    "sg:address":"Oudstrijdersstraat 71",
    "sg:city":"Leopoldsburg (heppen)",
    "sg:classifiers":[
        {
            "category":"Personal",
            "subcategory":"Beauty Salon",
            "type":"Services"
        }
    ],
    "sg:phone":"+32 11 34 36 72",
    "sg:postcode":"3971",
    "sg:province":"Limburg",
    "sg:tags":[
        "lady",
        "-",
        "hairdressing"
    ],
    "wof:name":"Ria",
    "wof:placetype":"venue"
},
  "geometry": {"coordinates":[5.2330088615,51.1118469238],"type":"Point"}
}