{
  "type": "Feature",
  "properties": {
    "iso:country":"BE",
    "sg:address":"Goethalsplaats 9",
    "sg:city":"Meulebeke",
    "sg:orig_category":"Entretien and r\u00e9parations de voitures. V\u00e9hicules automobiles",
    "sg:phone":"+32 51 48 82 09",
    "sg:postcode":"8760",
    "sg:province":"West-Vlaanderen",
    "wof:name":"Garage Van Iseghem",
    "wof:placetype":"venue"
},
  "geometry": {"coordinates":[3.2870628834,50.9504737854],"type":"Point"}
}