{
  "type": "Feature",
  "properties": {
    "iso:country":"BE",
    "sg:address":"Avenue De Fr\u00e9 44",
    "sg:city":"Bruxelles (uccle)",
    "sg:classifiers":[
        {
            "category":"Retail",
            "subcategory":"Event Space",
            "type":"Services"
        }
    ],
    "sg:phone":"+32 2 375 89 27",
    "sg:postcode":"1180",
    "sg:province":"Bruxelles-Capitale",
    "sg:tags":[
        "rental",
        "-",
        "hall"
    ],
    "wof:name":"Ferme Rose (la)",
    "wof:placetype":"venue"
},
  "geometry": {"coordinates":[4.347867012,50.8038406372],"type":"Point"}
}