{
  "type": "Feature",
  "properties": {
    "iso:country":"BE",
    "sg:address":"Chemin Du Moulin \u00e0 Vent 1",
    "sg:city":"Welkenraedt (henri-chapelle)",
    "sg:classifiers":[
        {
            "category":"Communications",
            "type":"Services"
        }
    ],
    "sg:phone":"+32 87 44 84 59",
    "sg:postcode":"4841",
    "sg:province":"Li\u00e8ge",
    "sg:tags":[
        "translator"
    ],
    "wof:name":"A L T C",
    "wof:placetype":"venue"
},
  "geometry": {"coordinates":[5.9202480316,50.6762008667],"type":"Point"}
}