{
  "type": "Feature",
  "properties": {
    "iso:country":"BE",
    "sg:address":"Kortrijksestr 59",
    "sg:city":"Izegem",
    "sg:classifiers":[
        {
            "category":"Professional",
            "subcategory":"Engineering",
            "type":"Services"
        }
    ],
    "sg:phone":"+32 51 31 62 06",
    "sg:postcode":"8870",
    "sg:province":"West-Vlaanderen",
    "sg:tags":[
        "machine",
        "-",
        "mechanical"
    ],
    "wof:name":"Alpaco Nv",
    "wof:placetype":"venue"
},
  "geometry": {"coordinates":[3.2156889439,50.9148025513],"type":"Point"}
}