{
  "type": "Feature",
  "properties": {
    "iso:country":"BE",
    "sg:address":"Scandinaviestraat 228",
    "sg:city":"Gent",
    "sg:orig_category":"Rusthuizen and serviceflats",
    "sg:phone":"+32 9 251 40 28",
    "sg:postcode":"9000",
    "sg:province":"Oost-Vlaanderen",
    "wof:name":"Home Finland",
    "wof:placetype":"venue"
},
  "geometry": {"coordinates":[3.7385089397,51.0697555542],"type":"Point"}
}