{
  "type": "Feature",
  "properties": {
    "iso:country":"BE",
    "sg:address":"Stationsstraat 3",
    "sg:city":"Wachtebeke",
    "sg:classifiers":[
        {
            "category":"Health Services",
            "subcategory":"Doctor",
            "type":"Services"
        }
    ],
    "sg:phone":"+32 9 345 01 20",
    "sg:postcode":"9185",
    "sg:province":"Oost-Vlaanderen",
    "sg:tags":[
        "medicinephysicians",
        "surgeon"
    ],
    "wof:name":"De Sonville L",
    "wof:placetype":"venue"
},
  "geometry": {"coordinates":[3.8611021042,51.1712341309],"type":"Point"}
}