{
  "type": "Feature",
  "properties": {
    "iso:country":"BE",
    "sg:address":"Edward Claessenslaan 32",
    "sg:city":"Niel",
    "sg:orig_category":"Epiceries",
    "sg:phone":"+32 3 888 32 32",
    "sg:postcode":"2845",
    "sg:province":"Antwerpen",
    "wof:name":"Maria Van Damme",
    "wof:placetype":"venue"
},
  "geometry": {"coordinates":[4.3274149895,51.1131858826],"type":"Point"}
}