{
  "type": "Feature",
  "properties": {
    "addr:full":"Grote Markt 64 Zelzate Oost-Vlaanderen 9060",
    "addr:housenumber":"64",
    "addr:postcode":"9060",
    "addr:street":"Grote Markt",
    "iso:country":"BE",
    "sg:address":"Grote Markt 64",
    "sg:city":"Zelzate",
    "sg:classifiers":[
        {
            "category":"Shopping",
            "subcategory":"Clothing, Apparel, & Fashions",
            "type":"Retail Goods"
        }
    ],
    "sg:phone":"+32 9 345 85 62",
    "sg:postcode":"9060",
    "sg:province":"Oost-Vlaanderen",
    "sg:tags":[
        "clothing",
        "-",
        "gentleman"
    ],
    "wof:name":"De Decker R",
    "wof:placetype":"venue"
},
  "geometry": {"coordinates":[3.8104870319,51.2003974915],"type":"Point"}
}