{
  "type": "Feature",
  "properties": {
    "iso:country":"BE",
    "sg:address":"Rue De L'invasion 11",
    "sg:city":"Ottignies-louvain-la-neuve",
    "sg:orig_category":"Installatie van metalen schrijnwerk SMEEDWERK, METAALBEWERKING AND POEDERMETALLURGIE",
    "sg:phone":"+32 10 41 87 28",
    "sg:postcode":"1340",
    "sg:province":"Brabant Wallon",
    "wof:name":"Ottim\u00c9tal Ferronnerie",
    "wof:placetype":"venue"
},
  "geometry": {"coordinates":[4.5841159821,50.669593811],"type":"Point"}
}