{
  "type": "Feature",
  "properties": {
    "iso:country":"BE",
    "sg:address":"Rue Des Clos Champs 3",
    "sg:city":"Rochefort",
    "sg:orig_category":"Travail and traitement du bois",
    "sg:phone":"+32 83 68 89 40",
    "sg:postcode":"5580",
    "sg:province":"Namur",
    "wof:name":"Fe. Kuypers Jean",
    "wof:placetype":"venue"
},
  "geometry": {"coordinates":[5.1370868683,50.2119407654],"type":"Point"}
}