{
  "type": "Feature",
  "properties": {
    "iso:country":"BE",
    "sg:address":"Route De Lessines 23",
    "sg:city":"Frasnes-lez-anvaing",
    "sg:orig_category":"Elektrische installaties voor woningen",
    "sg:phone":"+32 69 86 68 48",
    "sg:postcode":"7911",
    "sg:province":"Hainaut",
    "wof:name":"A. Decleve",
    "wof:placetype":"venue"
},
  "geometry": {"coordinates":[3.6265408993,50.6710548401],"type":"Point"}
}