{
  "type": "Feature",
  "properties": {
    "addr:full":"Rue Paul Pastur 77 Quaregnon Hainaut 7390",
    "addr:housenumber":"77",
    "addr:postcode":"7390",
    "addr:street":"Rue Paul Pastur",
    "iso:country":"BE",
    "sg:address":"Rue Paul Pastur 77",
    "sg:city":"Quaregnon",
    "sg:classifiers":[
        {
            "category":"Retail",
            "subcategory":"Auto Repair",
            "type":"Services"
        }
    ],
    "sg:phone":"+32 65 78 33 54",
    "sg:postcode":"7390",
    "sg:province":"Hainaut",
    "sg:tags":[
        "automobile-body"
    ],
    "wof:name":"Spadaro & Fils Sprl",
    "wof:placetype":"venue"
},
  "geometry": {"coordinates":[3.8622829914,50.4456520081],"type":"Point"}
}