{
  "type": "Feature",
  "properties": {
    "addr:full":"Broekstraat 56 Brussels Bruxelles-Capitale 1000",
    "addr:housenumber":"56",
    "addr:postcode":"1000",
    "addr:street":"Broekstraat",
    "iso:country":"BE",
    "sg:address":"Broekstraat 56",
    "sg:city":"Brussels",
    "sg:classifiers":[
        {
            "category":"Banks & Credit Unions",
            "subcategory":"Bank",
            "type":"Services"
        }
    ],
    "sg:phone":"+32 2 204 39 99",
    "sg:postcode":"1000",
    "sg:province":"Bruxelles-Capitale",
    "wof:name":"Eural Sa/nv",
    "wof:placetype":"venue"
},
  "geometry": {"coordinates":[4.3577327728,50.8619728088],"type":"Point"}
}