{
  "type": "Feature",
  "properties": {
    "iso:country":"BE",
    "sg:address":"Avenue Du Parc 31z",
    "sg:city":"Verviers",
    "sg:orig_category":"Pompes and compresseurs Fab",
    "sg:phone":"+32 87 32 14 11",
    "sg:postcode":"4800",
    "sg:province":"Li\u00e8ge",
    "wof:name":"Durco Europe",
    "wof:placetype":"venue"
},
  "geometry": {"coordinates":[5.8568301201,50.5819396973],"type":"Point"}
}