{
  "type": "Feature",
  "properties": {
    "addr:full":"Oude Ieperweg 30 Zedelgem West-Vlaanderen 8210",
    "addr:housenumber":"30",
    "addr:postcode":"8210",
    "addr:street":"Oude Ieperweg",
    "iso:country":"BE",
    "sg:address":"Oude Ieperweg 30",
    "sg:city":"Zedelgem",
    "sg:orig_category":"Eleveurs de bovins",
    "sg:phone":"+32 50 82 26 83",
    "sg:postcode":"8210",
    "sg:province":"West-Vlaanderen",
    "wof:name":"Andre De Splentere",
    "wof:placetype":"venue"
},
  "geometry": {"coordinates":[3.1458399296,51.1376457214],"type":"Point"}
}