{
  "type": "Feature",
  "properties": {
    "addr:full":"Fabriekstraat 339 Sint-pieters-leeuw Vlaams-Brabant 1601",
    "addr:housenumber":"339",
    "addr:postcode":"1601",
    "addr:street":"Fabriekstraat",
    "iso:country":"BE",
    "sg:address":"Fabriekstraat 339",
    "sg:city":"Sint-pieters-leeuw",
    "sg:classifiers":[
        {
            "category":"Restaurant",
            "type":"Food & Drink"
        }
    ],
    "sg:phone":"+32 2 331 52 61",
    "sg:postcode":"1601",
    "sg:province":"Vlaams-Brabant",
    "wof:name":"De Mayeur",
    "wof:placetype":"venue"
},
  "geometry": {"coordinates":[4.2848467827,50.7781791687],"type":"Point"}
}