{
  "type": "Feature",
  "properties": {
    "addr:full":"Steenweg Op Wetteren 20 Dendermonde Oost-Vlaanderen 9200",
    "addr:housenumber":"20",
    "addr:postcode":"9200",
    "addr:street":"Steenweg Op Wetteren;Oost-Vlaanderen",
    "iso:country":"BE",
    "sg:address":"Steenweg Op Wetteren 20",
    "sg:city":"Dendermonde",
    "sg:orig_category":"Produits chimiques Gr",
    "sg:phone":"+32 52 42 31 74",
    "sg:postcode":"9200",
    "sg:province":"Oost-Vlaanderen",
    "wof:name":"Ucb",
    "wof:placetype":"venue"
},
  "geometry": {"coordinates":[4.0066242218,51.002948761],"type":"Point"}
}