{
  "type": "Feature",
  "properties": {
    "addr:full":"Sint-goriksstraat 16 Asse (kobbegem) Vlaams-Brabant 1730",
    "addr:housenumber":"16",
    "addr:postcode":"1730",
    "addr:street":"Sint-Goriksstraat",
    "iso:country":"BE",
    "sg:address":"Sint-goriksstraat 16",
    "sg:city":"Asse (kobbegem)",
    "sg:classifiers":[
        {
            "category":"Health Services",
            "subcategory":"Nursing And Care Facility",
            "type":"Services"
        }
    ],
    "sg:phone":"+32 2 452 20 59",
    "sg:postcode":"1730",
    "sg:province":"Vlaams-Brabant",
    "sg:tags":[
        "home"
    ],
    "wof:name":"Michiels E Bvba",
    "wof:placetype":"venue"
},
  "geometry": {"coordinates":[4.2509908676,50.906452179],"type":"Point"}
}