{
  "type": "Feature",
  "properties": {
    "iso:country":"BE",
    "sg:address":"P. Delannoyplaats 82",
    "sg:city":"Edingen/enghien",
    "sg:orig_category":"Advocaten and juridische adviseurs",
    "sg:phone":"+32 2 395 69 40",
    "sg:postcode":"7850",
    "sg:province":"Hainaut",
    "wof:name":"Martine De Smet/m. De Smet",
    "wof:placetype":"venue"
},
  "geometry": {"coordinates":[4.0334601402,50.6914787292],"type":"Point"}
}