{
  "type": "Feature",
  "properties": {
    "addr:full":"Laan Op Heusden 10 Beringen (koersel) Limburg 3582",
    "addr:housenumber":"10",
    "addr:postcode":"3582",
    "addr:street":"Laan Op Heusden",
    "iso:country":"BE",
    "sg:address":"Laan Op Heusden 10",
    "sg:city":"Beringen (koersel)",
    "sg:classifiers":[
        {
            "category":"Health Services",
            "subcategory":"Health Practitioner",
            "type":"Services"
        }
    ],
    "sg:phone":"+32 11 42 41 88",
    "sg:postcode":"3582",
    "sg:province":"Limburg",
    "sg:tags":[
        "physiotherapist"
    ],
    "wof:name":"Leyssens Rita",
    "wof:placetype":"venue"
},
  "geometry": {"coordinates":[5.2708749771,51.0595359802],"type":"Point"}
}