{
  "type": "Feature",
  "properties": {
    "addr:full":"Rue Bouhette 92-32 Saint-nicolas (montegn\u00e9e) Li\u00e8ge 4420",
    "addr:housenumber":"92-32",
    "addr:postcode":"4420",
    "addr:street":"Rue Bouhette;Montegne\u0301E",
    "iso:country":"BE",
    "sg:address":"Rue Bouhette 92-32",
    "sg:city":"Saint-nicolas (montegn\u00e9e)",
    "sg:classifiers":[
        {
            "category":"Professional",
            "subcategory":"Art Services",
            "type":"Services"
        }
    ],
    "sg:phone":"+32 4 234 50 98",
    "sg:postcode":"4420",
    "sg:province":"Li\u00e8ge",
    "sg:tags":[
        "photographer"
    ],
    "wof:name":"Presse Jc",
    "wof:placetype":"venue"
},
  "geometry": {"coordinates":[5.5090661049,50.630695343],"type":"Point"}
}