{
  "type": "Feature",
  "properties": {
    "iso:country":"BE",
    "sg:address":"Sint-antoonplein 9",
    "sg:city":"Etterbeek",
    "sg:orig_category":"Artsen and specialisten",
    "sg:phone":"+32 2 640 32 10",
    "sg:postcode":"1040",
    "sg:province":"Bruxelles-Capitale",
    "wof:name":"Consultation Nourrissons",
    "wof:placetype":"venue"
},
  "geometry": {"coordinates":[4.3866930008,50.8287353516],"type":"Point"}
}