{
  "type": "Feature",
  "properties": {
    "iso:country":"BE",
    "sg:address":"Alfons Verdijckstraat 8",
    "sg:city":"Schoten",
    "sg:classifiers":[
        {
            "category":"Food & Beverages",
            "subcategory":"Chocolate",
            "type":"Retail Goods"
        }
    ],
    "sg:phone":"+32 3 658 74 49",
    "sg:postcode":"2900",
    "sg:province":"Antwerpen",
    "sg:tags":[
        "confectionery",
        "-"
    ],
    "wof:name":"Pralin\u00e9 Louis Van Oppen",
    "wof:placetype":"venue"
},
  "geometry": {"coordinates":[4.5048851967,51.2486114502],"type":"Point"}
}