{
  "type": "Feature",
  "properties": {
    "iso:country":"BE",
    "sg:address":"Rue Des Cinq Etoiles 1",
    "sg:city":"Perwez",
    "sg:orig_category":"Rundveehouders",
    "sg:phone":"+32 81 64 02 50",
    "sg:postcode":"1360",
    "sg:province":"Brabant Wallon",
    "wof:name":"Auguste Daube",
    "wof:placetype":"venue"
},
  "geometry": {"coordinates":[4.7544808388,50.6038398743],"type":"Point"}
}