{
  "type": "Feature",
  "properties": {
    "addr:full":"Rozenbosstraat 89 Nieuwerkerken Limburg 3850",
    "addr:housenumber":"89",
    "addr:postcode":"3850",
    "addr:street":"Rozenbosstraat",
    "iso:country":"BE",
    "sg:address":"Rozenbosstraat 89",
    "sg:city":"Nieuwerkerken",
    "sg:orig_category":"Producteurs de fruits",
    "sg:phone":"+32 11 68 36 99",
    "sg:postcode":"3850",
    "sg:province":"Limburg",
    "wof:name":"Andre Esselen",
    "wof:placetype":"venue"
},
  "geometry": {"coordinates":[5.2013010979,50.8790855408],"type":"Point"}
}