{
  "type": "Feature",
  "properties": {
    "iso:country":"BE",
    "sg:address":"Chauss\u00c9e De Gand 1214",
    "sg:city":"Sint-agatha-berchem/berchem-sainte-agathe",
    "sg:orig_category":"Art and fournitures artistiques",
    "sg:phone":"+32 2 465 31 57",
    "sg:postcode":"1082",
    "sg:province":"Bruxelles-Capitale",
    "wof:name":"Atelier Vercruysse",
    "wof:placetype":"venue"
},
  "geometry": {"coordinates":[4.2957148552,50.8656005859],"type":"Point"}
}