{
  "type": "Feature",
  "properties": {
    "iso:country":"BE",
    "sg:address":"Wezelstraat 81",
    "sg:city":"Grimbergen",
    "sg:classifiers":[
        {
            "category":"Communications",
            "subcategory":"Film & Video Production",
            "type":"Services"
        }
    ],
    "sg:phone":"+32 2 267 65 27",
    "sg:postcode":"1850",
    "sg:province":"Vlaams-Brabant",
    "sg:tags":[
        "realisation",
        "-"
    ],
    "wof:name":"Fux E",
    "wof:placetype":"venue"
},
  "geometry": {"coordinates":[4.3689570427,50.9441833496],"type":"Point"}
}