{
  "type": "Feature",
  "properties": {
    "addr:full":"Rue De Liverpool 82 Anderlecht Bruxelles-Capitale 1070",
    "addr:housenumber":"82",
    "addr:postcode":"1070",
    "addr:street":"Rue De Liverpool",
    "iso:country":"BE",
    "sg:address":"Rue De Liverpool 82",
    "sg:city":"Anderlecht",
    "sg:orig_category":"Pain, p\u00e2tisseries and confiseries",
    "sg:phone":"+32 2 523 55 01",
    "sg:postcode":"1070",
    "sg:province":"Bruxelles-Capitale",
    "wof:name":"Ankona",
    "wof:placetype":"venue"
},
  "geometry": {"coordinates":[4.3325481415,50.8451805115],"type":"Point"}
}