{
  "type": "Feature",
  "properties": {
    "addr:full":"Vierselbaan 12c Zandhoven Antwerpen 2240",
    "addr:housenumber":"12c",
    "addr:postcode":"2240",
    "addr:street":"Vierselbaan",
    "iso:country":"BE",
    "sg:address":"Vierselbaan 12c",
    "sg:city":"Zandhoven",
    "sg:classifiers":[
        {
            "category":"Wholesale",
            "subcategory":"Beer",
            "type":"Manufacturing & Wholesale Goods"
        }
    ],
    "sg:phone":"+32 3 484 31 12",
    "sg:postcode":"2240",
    "sg:province":"Antwerpen",
    "sg:tags":[
        "ale",
        "-"
    ],
    "wof:name":"Drankenarsenaal Bvba",
    "wof:placetype":"venue"
},
  "geometry": {"coordinates":[4.6583909988,51.2092323303],"type":"Point"}
}