{
  "type": "Feature",
  "properties": {
    "addr:full":"Broekstraat 19 Asse Vlaams-Brabant 1730",
    "addr:housenumber":"19",
    "addr:postcode":"1730",
    "addr:street":"Broekstraat",
    "iso:country":"BE",
    "sg:address":"Broekstraat 19",
    "sg:city":"Asse",
    "sg:classifiers":[
        {
            "category":"Building & Trades",
            "subcategory":"Electrical",
            "type":"Services"
        }
    ],
    "sg:phone":"+32 2 453 23 66",
    "sg:postcode":"1730",
    "sg:province":"Vlaams-Brabant",
    "sg:tags":[
        "electric",
        "-",
        "housewiring",
        "contractor"
    ],
    "wof:name":"Vds Services",
    "wof:placetype":"venue"
},
  "geometry": {"coordinates":[4.244328022,50.9104995728],"type":"Point"}
}