{
  "type": "Feature",
  "properties": {
    "iso:country":"BE",
    "sg:address":"Ardooisesteenweg 345",
    "sg:city":"Roeselare",
    "sg:classifiers":[
        {
            "category":"Arena",
            "subcategory":"Sports Club",
            "type":"Entertainment"
        }
    ],
    "sg:phone":"+32 51 21 04 21",
    "sg:postcode":"8800",
    "sg:province":"West-Vlaanderen",
    "sg:tags":[
        "de"
    ],
    "wof:name":"Besch. Tegen Roofvogels",
    "wof:placetype":"venue"
},
  "geometry": {"coordinates":[3.1562709808,50.9564094543],"type":"Point"}
}