{
  "type": "Feature",
  "properties": {
    "addr:full":"Rue Jean-baptiste Dekeyser 17 Renaix Oost-Vlaanderen 9600",
    "addr:housenumber":"17",
    "addr:postcode":"9600",
    "addr:street":"Rue Jean-Baptiste Dekeyser",
    "iso:country":"BE",
    "sg:address":"Rue Jean-baptiste Dekeyser 17",
    "sg:city":"Renaix",
    "sg:classifiers":[
        {
            "category":"Personal",
            "subcategory":"Beauty Salon",
            "type":"Services"
        }
    ],
    "sg:phone":"+32 55 21 77 05",
    "sg:postcode":"9600",
    "sg:province":"Oost-Vlaanderen",
    "sg:tags":[
        "lady",
        "-",
        "hairdressing"
    ],
    "wof:name":"Veronique",
    "wof:placetype":"venue"
},
  "geometry": {"coordinates":[3.6014249325,50.7449569702],"type":"Point"}
}