{
  "type": "Feature",
  "properties": {
    "addr:full":"Rue Du Culot 15 Couvin (aublain) Namur 5660",
    "addr:housenumber":"15",
    "addr:postcode":"5660",
    "addr:street":"Rue Du Culot",
    "iso:country":"BE",
    "sg:address":"Rue Du Culot 15",
    "sg:city":"Couvin (aublain)",
    "sg:classifiers":[
        {
            "category":"Health Services",
            "subcategory":"Nursing And Care Facility",
            "type":"Services"
        }
    ],
    "sg:phone":"+32 60 34 67 61",
    "sg:postcode":"5660",
    "sg:province":"Namur",
    "sg:tags":[
        "home"
    ],
    "wof:name":"Van Alfaene M-c",
    "wof:placetype":"venue"
},
  "geometry": {"coordinates":[4.4088549614,50.0655212402],"type":"Point"}
}