{
  "type": "Feature",
  "properties": {
    "iso:country":"BE",
    "sg:address":"Kaai 33",
    "sg:city":"Nieuwpoort",
    "sg:classifiers":[
        {
            "category":"Food & Beverages",
            "subcategory":"Meat & Fish",
            "type":"Retail Goods"
        }
    ],
    "sg:phone":"+32 58 23 44 76",
    "sg:postcode":"8620",
    "sg:province":"West-Vlaanderen",
    "sg:tags":[
        "vi",
        "zeevruchten"
    ],
    "wof:name":"Huis Romeo",
    "wof:placetype":"venue"
},
  "geometry": {"coordinates":[2.7495920658,51.1331329346],"type":"Point"}
}