{
  "type": "Feature",
  "properties": {
    "addr:full":"Ijzerstraat 16 Alveringem (stavele) West-Vlaanderen 8691",
    "addr:housenumber":"16",
    "addr:postcode":"8691",
    "addr:street":"Ijzerstraat",
    "iso:country":"BE",
    "sg:address":"Ijzerstraat 16",
    "sg:city":"Alveringem (stavele)",
    "sg:classifiers":[
        {
            "category":"Bars & Pubs",
            "type":"Food & Drink"
        }
    ],
    "sg:phone":"+32 57 30 01 12",
    "sg:postcode":"8691",
    "sg:province":"West-Vlaanderen",
    "sg:tags":[
        "tavern"
    ],
    "wof:name":"Hof Van Commerce('t)",
    "wof:placetype":"venue"
},
  "geometry": {"coordinates":[2.6718599796,50.9428634644],"type":"Point"}
}