{
  "type": "Feature",
  "properties": {
    "addr:full":"Avenue De La Sauge 20 Namur (jambes) Namur 5100",
    "addr:housenumber":"20",
    "addr:postcode":"5100",
    "addr:street":"Avenue De La Sauge",
    "iso:country":"BE",
    "sg:address":"Avenue De La Sauge 20",
    "sg:city":"Namur (jambes)",
    "sg:classifiers":[
        {
            "category":"Organizations",
            "subcategory":"Professional Association",
            "type":"Services"
        }
    ],
    "sg:phone":"+32 81 30 63 61",
    "sg:postcode":"5100",
    "sg:province":"Namur",
    "sg:tags":[
        "trade-union",
        "federation"
    ],
    "wof:name":"F.e.d.a.g.e.",
    "wof:placetype":"venue"
},
  "geometry": {"coordinates":[4.8713750839,50.4566345215],"type":"Point"}
}