{
  "type": "Feature",
  "properties": {
    "addr:full":"Nieuwstraat 1 Gavere Oost-Vlaanderen 9890",
    "addr:housenumber":"1",
    "addr:postcode":"9890",
    "addr:street":"Nieuwstraat",
    "iso:country":"BE",
    "sg:address":"Nieuwstraat 1",
    "sg:city":"Gavere",
    "sg:classifiers":[
        {
            "category":"Health Services",
            "subcategory":"Doctor",
            "type":"Services"
        }
    ],
    "sg:phone":"+32 9 390 81 52",
    "sg:postcode":"9890",
    "sg:province":"Oost-Vlaanderen",
    "sg:tags":[
        "orthopedist"
    ],
    "wof:name":"Van Holsbeeck E",
    "wof:placetype":"venue"
},
  "geometry": {"coordinates":[3.6591789722,50.9293441772],"type":"Point"}
}