{
  "type": "Feature",
  "properties": {
    "addr:full":"Avenue Charles Deli\u00e8ge 48 Binche Hainaut 7130",
    "addr:housenumber":"48",
    "addr:postcode":"7130",
    "addr:street":"Avenue Charles Delie\u0300Ge",
    "iso:country":"BE",
    "sg:address":"Avenue Charles Deli\u00e8ge 48",
    "sg:city":"Binche",
    "sg:classifiers":[
        {
            "category":"Real Estate",
            "subcategory":"Real Estate Services",
            "type":"Services"
        }
    ],
    "sg:phone":"+32 64 34 20 20",
    "sg:postcode":"7130",
    "sg:province":"Hainaut",
    "wof:name":"B.i.s. (bureau Immobilier Serv",
    "wof:placetype":"venue"
},
  "geometry": {"coordinates":[4.1661720276,50.4127655029],"type":"Point"}
}