{
  "type": "Feature",
  "properties": {
    "addr:full":"Sur Les Mini\u00c8res 5 Ferri\u00c8res Li\u00e8ge 4190",
    "addr:housenumber":"5",
    "addr:postcode":"4190",
    "addr:street":"Sur Les Minie\u0300Res",
    "iso:country":"BE",
    "sg:address":"Sur Les Mini\u00c8res 5",
    "sg:city":"Ferri\u00c8res",
    "sg:orig_category":"Pleisterwerk",
    "sg:phone":"+32 4 369 16 56",
    "sg:postcode":"4190",
    "sg:province":"Li\u00e8ge",
    "wof:name":"M. Maquinay",
    "wof:placetype":"venue"
},
  "geometry": {"coordinates":[5.6227741241,50.443649292],"type":"Point"}
}