{
  "type": "Feature",
  "properties": {
    "iso:country":"BE",
    "sg:address":"Lenclos 76",
    "sg:city":"Etalle",
    "sg:orig_category":"S\u00e9curit\u00e9 sociale",
    "sg:phone":"+32 63 45 56 89",
    "sg:postcode":"6740",
    "sg:province":"Luxembourg",
    "wof:name":"Mutualit\u00c9 Socialiste",
    "wof:placetype":"venue"
},
  "geometry": {"coordinates":[5.6059298515,49.6743545532],"type":"Point"}
}