{
  "type": "Feature",
  "properties": {
    "iso:country":"BE",
    "sg:address":"Route De Marche 9",
    "sg:city":"Somme-leuze (baillonville)",
    "sg:classifiers":[
        {
            "category":"Fast Food",
            "type":"Food & Drink"
        }
    ],
    "sg:phone":"+32 84 32 22 59",
    "sg:postcode":"5377",
    "sg:province":"Namur",
    "sg:tags":[
        "fried",
        "stand",
        "potato"
    ],
    "wof:name":"P'tit Creux (au)",
    "wof:placetype":"venue"
},
  "geometry": {"coordinates":[5.3641400337,50.3391952515],"type":"Point"}
}