{
  "type": "Feature",
  "properties": {
    "iso:country":"BE",
    "sg:address":"Rue Albert I 138",
    "sg:city":"Farciennes",
    "sg:orig_category":"Autombile concessionaires",
    "sg:phone":"+32 71 38 07 04",
    "sg:postcode":"6240",
    "sg:province":"Hainaut",
    "wof:name":"Gar Hublet & Fils",
    "wof:placetype":"venue"
},
  "geometry": {"coordinates":[4.5416688919,50.4249191284],"type":"Point"}
}