{
  "type": "Feature",
  "properties": {
    "addr:full":"Avenue Z\u00e9nobe Gramme 12 Wavre Brabant Wallon 1300",
    "addr:housenumber":"12;1300",
    "addr:street":"Avenue Ze\u0301Nobe Gramme",
    "iso:country":"BE",
    "sg:address":"Avenue Z\u00e9nobe Gramme 12",
    "sg:city":"Wavre",
    "sg:classifiers":[
        {
            "category":"Utilities",
            "subcategory":"Recycling",
            "type":"Services"
        }
    ],
    "sg:phone":"+32 10 24 17 33",
    "sg:postcode":"1300",
    "sg:province":"Brabant Wallon",
    "sg:tags":[
        "rubbish",
        "removal"
    ],
    "wof:name":"Efficace Vidange Scrl",
    "wof:placetype":"venue"
},
  "geometry": {"coordinates":[4.5811028481,50.7373199463],"type":"Point"}
}