{
  "type": "Feature",
  "properties": {
    "addr:full":"Rue De La Tonne 38 Ans Li\u00e8ge 4430",
    "addr:housenumber":"38",
    "addr:postcode":"4430",
    "addr:street":"Rue De La Tonne",
    "iso:country":"BE",
    "sg:address":"Rue De La Tonne 38",
    "sg:city":"Ans",
    "sg:classifiers":[
        {
            "category":"Shopping",
            "subcategory":"Books",
            "type":"Retail Goods"
        }
    ],
    "sg:phone":"+32 4 246 32 71",
    "sg:postcode":"4430",
    "sg:province":"Li\u00e8ge",
    "sg:tags":[
        "bookseller"
    ],
    "wof:name":"Morreale",
    "wof:placetype":"venue"
},
  "geometry": {"coordinates":[5.5426039696,50.6601257324],"type":"Point"}
}