{
  "type": "Feature",
  "properties": {
    "addr:full":"Lindekensveld 8 Lummen Limburg 3560",
    "addr:housenumber":"8",
    "addr:postcode":"3560",
    "addr:street":"Lindekensveld",
    "iso:country":"BE",
    "sg:address":"Lindekensveld 8",
    "sg:city":"Lummen",
    "sg:classifiers":[
        {
            "category":"Food & Beverages",
            "subcategory":"Specialty",
            "type":"Retail Goods"
        }
    ],
    "sg:phone":"+32 11 81 70 74",
    "sg:postcode":"3560",
    "sg:province":"Limburg",
    "sg:tags":[
        "sinking",
        "groundwater"
    ],
    "wof:name":"Rain Bird Watering Systems",
    "wof:placetype":"venue"
},
  "geometry": {"coordinates":[5.1960659027,50.9926490784],"type":"Point"}
}