{
  "type": "Feature",
  "properties": {
    "addr:full":"Sint-gittersplein 1 Landen Vlaams-Brabant 3400",
    "addr:housenumber":"1",
    "addr:postcode":"3400",
    "addr:street":"Sint-Gittersplein",
    "iso:country":"BE",
    "sg:address":"Sint-gittersplein 1",
    "sg:city":"Landen",
    "sg:orig_category":"Eleveurs de bovins",
    "sg:phone":"+32 11 88 27 31",
    "sg:postcode":"3400",
    "sg:province":"Vlaams-Brabant",
    "wof:name":"Emile Wauters",
    "wof:placetype":"venue"
},
  "geometry": {"coordinates":[5.0637111664,50.7461700439],"type":"Point"}
}