{
  "type": "Feature",
  "properties": {
    "addr:full":"Dennenlaan 59 Brecht Antwerpen 2960",
    "addr:housenumber":"59",
    "addr:postcode":"2960",
    "addr:street":"Dennenlaan",
    "iso:country":"BE",
    "sg:address":"Dennenlaan 59",
    "sg:city":"Brecht",
    "sg:classifiers":[
        {
            "category":"Building & Trades",
            "subcategory":"Construction",
            "type":"Services"
        }
    ],
    "sg:phone":"+32 3 636 04 16",
    "sg:postcode":"2960",
    "sg:province":"Antwerpen",
    "sg:tags":[
        "installation",
        "-",
        "central",
        "heating"
    ],
    "wof:name":"Vermeiren Bvba",
    "wof:placetype":"venue"
},
  "geometry": {"coordinates":[4.5839290619,51.300239563],"type":"Point"}
}