{
  "type": "Feature",
  "properties": {
    "addr:full":"Rooigemlaan 184 Gent Oost-Vlaanderen 9000",
    "addr:housenumber":"184",
    "addr:postcode":"9000",
    "addr:street":"Rooigemlaan;Oost-Vlaanderen",
    "iso:country":"BE",
    "sg:address":"Rooigemlaan 184",
    "sg:city":"Gent",
    "sg:orig_category":"Pharmaciens",
    "sg:phone":"+32 9 226 23 16",
    "sg:postcode":"9000",
    "sg:province":"Oost-Vlaanderen",
    "wof:name":"Johan Malfet",
    "wof:placetype":"venue"
},
  "geometry": {"coordinates":[3.6932721138,51.0579719543],"type":"Point"}
}