{
  "type": "Feature",
  "properties": {
    "addr:full":"Prins Boudewijnlaan 29 Maldegem Oost-Vlaanderen 9991",
    "addr:housenumber":"29",
    "addr:postcode":"9991",
    "addr:street":"Prins Boudewijnlaan",
    "iso:country":"BE",
    "sg:address":"Prins Boudewijnlaan 29",
    "sg:city":"Maldegem",
    "sg:orig_category":"Elektrische installaties voor woningen",
    "sg:phone":"+32 50 71 90 94",
    "sg:postcode":"9991",
    "sg:province":"Oost-Vlaanderen",
    "wof:name":"Filip D'have",
    "wof:placetype":"venue"
},
  "geometry": {"coordinates":[3.4996750355,51.2035865784],"type":"Point"}
}