{
  "type": "Feature",
  "properties": {
    "addr:full":"Strijpenplein 15 Zottegem Oost-Vlaanderen 9620",
    "addr:housenumber":"15",
    "addr:postcode":"9620",
    "addr:street":"Strijpenplein",
    "iso:country":"BE",
    "sg:address":"Strijpenplein 15",
    "sg:city":"Zottegem",
    "sg:orig_category":"Lampes and appareils \u00e9lectriques Fab. Travaux d\u00b4installation divers. Agences de publicit\u00e9",
    "sg:phone":"+32 9 361 23 48",
    "sg:postcode":"9620",
    "sg:province":"Oost-Vlaanderen",
    "wof:name":"Wim Coessens",
    "wof:placetype":"venue"
},
  "geometry": {"coordinates":[3.8112111092,50.871181488],"type":"Point"}
}