{
  "type": "Feature",
  "properties": {
    "iso:country":"BE",
    "sg:address":"Potbergstraat 46",
    "sg:city":"Rijkevorsel",
    "sg:classifiers":[
        {
            "category":"Fast Food",
            "type":"Food & Drink"
        }
    ],
    "sg:phone":"+32 3 314 59 04",
    "sg:postcode":"2310",
    "sg:province":"Antwerpen",
    "sg:tags":[
        "\u00c0",
        "emporter",
        "restaurants"
    ],
    "wof:name":"F. Van Bladel",
    "wof:placetype":"venue"
},
  "geometry": {"coordinates":[4.7623229027,51.3430404663],"type":"Point"}
}