{
  "type": "Feature",
  "properties": {
    "addr:full":"Rue Du Vingt-deux Ao\u00dbt 13 Morlanwelz Hainaut 7141",
    "addr:housenumber":"13",
    "addr:postcode":"7141",
    "addr:street":"Rue Du Vingt-Deux Aou\u0302T",
    "iso:country":"BE",
    "sg:address":"Rue Du Vingt-deux Ao\u00dbt 13",
    "sg:city":"Morlanwelz",
    "sg:orig_category":"Plomberie, chauffage and installations sanitaires",
    "sg:phone":"+32 64 45 02 77",
    "sg:postcode":"7141",
    "sg:province":"Hainaut",
    "wof:name":"Fe. Climachaud",
    "wof:placetype":"venue"
},
  "geometry": {"coordinates":[4.2556900978,50.42993927],"type":"Point"}
}