{
  "type": "Feature",
  "properties": {
    "iso:country":"BE",
    "sg:address":"Smoutebos 19",
    "sg:city":"Essen",
    "sg:classifiers":[
        {
            "category":"Building & Trades",
            "subcategory":"Construction",
            "type":"Services"
        }
    ],
    "sg:phone":"+32 3 677 03 71",
    "sg:postcode":"2910",
    "sg:province":"Antwerpen",
    "sg:tags":[
        "installation",
        "-",
        "central",
        "heating"
    ],
    "wof:name":"Haers F",
    "wof:placetype":"venue"
},
  "geometry": {"coordinates":[4.4494810104,51.4565963745],"type":"Point"}
}