{
  "type": "Feature",
  "properties": {
    "addr:full":"Stationsstraat 175 Duffel Antwerpen 2570",
    "addr:housenumber":"175",
    "addr:postcode":"2570",
    "addr:street":"Stationsstraat",
    "iso:country":"BE",
    "sg:address":"Stationsstraat 175",
    "sg:city":"Duffel",
    "sg:classifiers":[
        {
            "category":"Cafe",
            "type":"Food & Drink"
        }
    ],
    "sg:phone":"+32 15 31 76 17",
    "sg:postcode":"2570",
    "sg:province":"Antwerpen",
    "sg:tags":[
        "caf\u00e9s"
    ],
    "wof:name":"Philomena Coomans",
    "wof:placetype":"venue"
},
  "geometry": {"coordinates":[4.4943499565,51.0909004211],"type":"Point"}
}