{
  "type": "Feature",
  "properties": {
    "iso:country":"BE",
    "sg:address":"Driegotenkouter 100",
    "sg:city":"Hamme",
    "sg:orig_category":"Travaux de finition and nettoyage de b\u00e2timents. Constructions r\u00e9sidentielles sp\u00e9cifiques",
    "sg:phone":"+32 52 47 32 41",
    "sg:postcode":"9220",
    "sg:province":"Oost-Vlaanderen",
    "wof:name":"Franky Apers",
    "wof:placetype":"venue"
},
  "geometry": {"coordinates":[4.1559739113,51.0947189331],"type":"Point"}
}