{
  "type": "Feature",
  "properties": {
    "addr:full":"Avenue Du Fond Marie Monseu 64 Rixensart Brabant Wallon 1330",
    "addr:housenumber":"64",
    "addr:postcode":"1330",
    "addr:street":"Avenue Du Fond Marie Monseu;Wallon",
    "iso:country":"BE",
    "sg:address":"Avenue Du Fond Marie Monseu 64",
    "sg:city":"Rixensart",
    "sg:classifiers":[
        {
            "category":"Real Estate",
            "subcategory":"Real Estate Services",
            "type":"Services"
        }
    ],
    "sg:phone":"+32 2 736 98 38",
    "sg:postcode":"1330",
    "sg:province":"Brabant Wallon",
    "wof:name":"De Wilde D'estmael T",
    "wof:placetype":"venue"
},
  "geometry": {"coordinates":[4.5443749428,50.7066917419],"type":"Point"}
}