{
  "type": "Feature",
  "properties": {
    "iso:country":"BE",
    "sg:address":"38",
    "sg:city":"Esplanade Du Heysel B 1020 Bruxelles",
    "sg:classifiers":[
        {
            "category":"Professional",
            "subcategory":"Computer Services",
            "type":"Services"
        }
    ],
    "sg:phone":"+32 2 474 03 60",
    "sg:postcode":"38",
    "sg:tags":[
        "information",
        "technology",
        "software"
    ],
    "wof:name":"Showcase Benelux Sa",
    "wof:placetype":"venue"
},
  "geometry": {"coordinates":[4.341627121,50.8912887573],"type":"Point"}
}