{
  "type": "Feature",
  "properties": {
    "addr:full":"Zilverberkenlaan 1 Kortrijk West-Vlaanderen 8501",
    "addr:housenumber":"1",
    "addr:postcode":"8501",
    "addr:street":"Zilverberkenlaan",
    "iso:country":"BE",
    "sg:address":"Zilverberkenlaan 1",
    "sg:city":"Kortrijk",
    "sg:orig_category":"Experts-comptables",
    "sg:phone":"+32 56 41 13 69",
    "sg:postcode":"8501",
    "sg:province":"West-Vlaanderen",
    "wof:name":"Philippe Bisschop",
    "wof:placetype":"venue"
},
  "geometry": {"coordinates":[3.2142620087,50.8263168335],"type":"Point"}
}