{
  "type": "Feature",
  "properties": {
    "iso:country":"BE",
    "sg:address":"Avenue De Maire 28",
    "sg:city":"Tournai",
    "sg:orig_category":"Pompes and compresseurs Fab",
    "sg:phone":"+32 69 22 81 52",
    "sg:postcode":"7500",
    "sg:province":"Hainaut",
    "wof:name":"Deplechin",
    "wof:placetype":"venue"
},
  "geometry": {"coordinates":[3.3774929047,50.6133613586],"type":"Point"}
}