{
  "type": "Feature",
  "properties": {
    "addr:full":"Nieuwstraat 55 Waregem (desselgem) West-Vlaanderen 8792",
    "addr:housenumber":"55",
    "addr:postcode":"8792",
    "addr:street":"Nieuwstraat",
    "iso:country":"BE",
    "sg:address":"Nieuwstraat 55",
    "sg:city":"Waregem (desselgem)",
    "sg:classifiers":[
        {
            "category":"Professional",
            "subcategory":"Detective & Security Services",
            "type":"Services"
        }
    ],
    "sg:phone":"+32 56 71 26 66",
    "sg:postcode":"8792",
    "sg:province":"West-Vlaanderen",
    "sg:tags":[
        "installation",
        "alarm",
        "-",
        "system"
    ],
    "wof:name":"Devotec",
    "wof:placetype":"venue"
},
  "geometry": {"coordinates":[3.3534140587,50.8877563477],"type":"Point"}
}