{
  "type": "Feature",
  "properties": {
    "iso:country":"BE",
    "sg:address":"Wipstraat 2",
    "sg:city":"Berlaar",
    "sg:orig_category":"Schoonmaakbedrijven and ongediertebestrijding",
    "sg:phone":"+32 3 422 59 01",
    "sg:postcode":"2590",
    "sg:province":"Antwerpen",
    "wof:name":"Etienne Crauwels",
    "wof:placetype":"venue"
},
  "geometry": {"coordinates":[4.6418218613,51.1139717102],"type":"Point"}
}