{
  "type": "Feature",
  "properties": {
    "addr:full":"Suikerkaai 22 Halle Vlaams-Brabant 1500",
    "addr:housenumber":"22",
    "addr:postcode":"1500",
    "addr:street":"Suikerkaai",
    "iso:country":"BE",
    "sg:address":"Suikerkaai 22",
    "sg:city":"Halle",
    "sg:classifiers":[
        {
            "category":"Cafe",
            "type":"Food & Drink"
        }
    ],
    "sg:phone":"+32 2 360 03 30",
    "sg:postcode":"1500",
    "sg:province":"Vlaams-Brabant",
    "sg:tags":[
        "caf\u00e9s"
    ],
    "wof:name":"Caf\u00c9 Het Kanaal",
    "wof:placetype":"venue"
},
  "geometry": {"coordinates":[4.2353467941,50.7311859131],"type":"Point"}
}