{
  "type": "Feature",
  "properties": {
    "iso:country":"BE",
    "sg:address":"Roeselarestraat 2601a",
    "sg:city":"Diksmuide",
    "sg:classifiers":[
        {
            "category":"Banks & Credit Unions",
            "subcategory":"Bank",
            "type":"Services"
        }
    ],
    "sg:phone":"+32 51 50 33 11",
    "sg:postcode":"8600",
    "sg:province":"West-Vlaanderen",
    "sg:tags":[
        "savings-banks"
    ],
    "wof:name":"Vanbiervliet Zakenkantoor",
    "wof:placetype":"venue"
},
  "geometry": {"coordinates":[2.942358017,51.0190200806],"type":"Point"}
}