{
  "type": "Feature",
  "properties": {
    "addr:full":"Avenue John-fitzgerald Kennedy 21 Rixensart Brabant Wallon 1330",
    "addr:housenumber":"21",
    "addr:postcode":"1330",
    "addr:street":"Avenue John-Fitzgerald Kennedy;Wallon",
    "iso:country":"BE",
    "sg:address":"Avenue John-fitzgerald Kennedy 21",
    "sg:city":"Rixensart",
    "sg:classifiers":[
        {
            "category":"Health Services",
            "subcategory":"Health Practitioner",
            "type":"Services"
        }
    ],
    "sg:phone":"+32 2 653 81 99",
    "sg:postcode":"1330",
    "sg:province":"Brabant Wallon",
    "sg:tags":[
        "physiotherapist"
    ],
    "wof:name":"Gouti\u00e8re Andr\u00e9",
    "wof:placetype":"venue"
},
  "geometry": {"coordinates":[4.521007061,50.7089157104],"type":"Point"}
}