{
  "type": "Feature",
  "properties": {
    "addr:full":"Rijselsestraat 27 Zedelgem West-Vlaanderen 8210",
    "addr:housenumber":"27",
    "addr:postcode":"8210",
    "addr:street":"Rijselsestraat",
    "iso:country":"BE",
    "sg:address":"Rijselsestraat 27",
    "sg:city":"Zedelgem",
    "sg:orig_category":"Boucheries",
    "sg:phone":"+32 50 84 00 48",
    "sg:postcode":"8210",
    "sg:province":"West-Vlaanderen",
    "wof:name":"Johan Maertens",
    "wof:placetype":"venue"
},
  "geometry": {"coordinates":[3.1458399296,51.1376457214],"type":"Point"}
}