{
  "type": "Feature",
  "properties": {
    "addr:full":"Turnhoutsebaan 299 Antwerpen Antwerpen 2140",
    "addr:housenumber":"299",
    "addr:postcode":"2140",
    "addr:street":"Turnhoutsebaan",
    "iso:country":"BE",
    "sg:address":"Turnhoutsebaan 299",
    "sg:city":"Antwerpen",
    "sg:classifiers":[
        {
            "category":"Shopping",
            "subcategory":"Clothing, Apparel, & Fashions",
            "type":"Retail Goods"
        }
    ],
    "sg:phone":"+32 3 236 15 32",
    "sg:postcode":"2140",
    "sg:province":"Antwerpen",
    "sg:tags":[
        "ondergoed",
        "lingerie"
    ],
    "wof:name":"Berty De Wit",
    "wof:placetype":"venue"
},
  "geometry": {"coordinates":[4.4332199097,51.2137565613],"type":"Point"}
}