{
  "type": "Feature",
  "properties": {
    "addr:full":"Kruiskensstraat 2 Torhout West-Vlaanderen 8820",
    "addr:housenumber":"2",
    "addr:postcode":"8820",
    "addr:street":"Kruiskensstraat",
    "iso:country":"BE",
    "sg:address":"Kruiskensstraat 2",
    "sg:city":"Torhout",
    "sg:orig_category":"Rev\u00eatements de sols and murs",
    "sg:phone":"+32 50 21 51 75",
    "sg:postcode":"8820",
    "sg:province":"West-Vlaanderen",
    "wof:name":"Marc Decock",
    "wof:placetype":"venue"
},
  "geometry": {"coordinates":[3.0810449123,51.0555076599],"type":"Point"}
}