{
  "type": "Feature",
  "properties": {
    "iso:country":"BE",
    "sg:address":"Avenue Des Alli\u00c9s 28",
    "sg:city":"Malmedy (grand)",
    "sg:orig_category":"Secr\u00e9tariats sociaux",
    "sg:phone":"+32 80 79 13 00",
    "sg:postcode":"4960",
    "sg:province":"Li\u00e8ge",
    "wof:name":"Office National Des Pensions",
    "wof:placetype":"venue"
},
  "geometry": {"coordinates":[6.0208678246,50.4244766235],"type":"Point"}
}