{
  "type": "Feature",
  "properties": {
    "iso:country":"BE",
    "sg:address":"Buizemontstraat 26b4",
    "sg:city":"Geraardsbergen",
    "sg:orig_category":"Artsen and specialisten",
    "sg:phone":"+32 495 51 78 37",
    "sg:postcode":"9500",
    "sg:province":"Oost-Vlaanderen",
    "wof:name":"I. Willems",
    "wof:placetype":"venue"
},
  "geometry": {"coordinates":[3.8831028938,50.7703590393],"type":"Point"}
}