{
  "type": "Feature",
  "properties": {
    "iso:country":"BE",
    "sg:address":"Westakker 33",
    "sg:city":"Evergem",
    "sg:orig_category":"Schoonheidssalons",
    "sg:phone":"+32 9 258 02 46",
    "sg:postcode":"9940",
    "sg:province":"Oost-Vlaanderen",
    "wof:name":"Pedicure Patricia",
    "wof:placetype":"venue"
},
  "geometry": {"coordinates":[3.6751339436,51.103313446],"type":"Point"}
}