{
  "type": "Feature",
  "properties": {
    "iso:country":"BE",
    "sg:address":"Rue Pauline Hubert 10",
    "sg:city":"Sivry-rance",
    "sg:orig_category":"Bloemen and planten",
    "sg:phone":"+32 60 41 14 35",
    "sg:postcode":"6470",
    "sg:province":"Hainaut",
    "wof:name":"Maison Floril\u00c8ge",
    "wof:placetype":"venue"
},
  "geometry": {"coordinates":[4.2784252167,50.1424484253],"type":"Point"}
}