{
  "type": "Feature",
  "properties": {
    "addr:full":"Rue Albert I 124-130 Farciennes Hainaut 6240",
    "addr:postcode":"124-130;6240",
    "addr:street":"Rue Albert I;Hainaut",
    "iso:country":"BE",
    "sg:address":"Rue Albert I 124-130",
    "sg:city":"Farciennes",
    "sg:classifiers":[
        {
            "category":"Autos & Motor Vehicles",
            "subcategory":"Motorcycle Sales",
            "type":"Retail Goods"
        }
    ],
    "sg:phone":"+32 71 38 17 78",
    "sg:postcode":"6240",
    "sg:province":"Hainaut",
    "sg:tags":[
        "automobile",
        "brake",
        "-",
        "truck"
    ],
    "wof:name":"Evrard Georges Et Fils Sa",
    "wof:placetype":"venue"
},
  "geometry": {"coordinates":[4.542591095,50.4251594543],"type":"Point"}
}