{
  "type": "Feature",
  "properties": {
    "iso:country":"BE",
    "sg:address":"Rue D` Acoz 4",
    "sg:city":"Ham-sur-heure-nalinnes",
    "sg:orig_category":"HERSTELLING ELEKTRISCHE HUISHOUDAPPARATEN Huishoudapparaten, televisies and radio's Telecommunicatie",
    "sg:phone":"+32 71 21 79 57",
    "sg:postcode":"6120",
    "sg:province":"Hainaut",
    "wof:name":"Electro Video Roland",
    "wof:placetype":"venue"
},
  "geometry": {"coordinates":[4.4725461006,50.3431282043],"type":"Point"}
}