{
  "type": "Feature",
  "properties": {
    "iso:country":"BE",
    "sg:address":"Avenue De La Roche Foucald 6",
    "sg:city":"Rixensart",
    "sg:orig_category":"Sportactiviteiten en -evenementen",
    "sg:phone":"+32 2 653 33 01",
    "sg:postcode":"1330",
    "sg:province":"Brabant Wallon",
    "wof:name":"Ballons De C\u00c9roux",
    "wof:placetype":"venue"
},
  "geometry": {"coordinates":[4.5334229469,50.7169151306],"type":"Point"}
}