{
  "type": "Feature",
  "properties": {
    "iso:country":"BE",
    "sg:address":"Chemin Du Pont De Pierre 2",
    "sg:city":"Braine-le-comte",
    "sg:classifiers":[
        {
            "category":"Health Services",
            "subcategory":"Doctor",
            "type":"Services"
        }
    ],
    "sg:phone":"+32 67 33 56 00",
    "sg:postcode":"7090",
    "sg:province":"Hainaut",
    "sg:tags":[
        "medicinephysicians",
        "surgeon"
    ],
    "wof:name":"Cheron P",
    "wof:placetype":"venue"
},
  "geometry": {"coordinates":[4.0913882256,50.6066703796],"type":"Point"}
}