{
  "type": "Feature",
  "properties": {
    "iso:country":"BE",
    "sg:address":"Hoevenzavellaan 55",
    "sg:city":"Genk (waterschei)",
    "sg:classifiers":[
        {
            "category":"Manufacturing",
            "subcategory":"Textiles",
            "type":"Manufacturing & Wholesale Goods"
        }
    ],
    "sg:phone":"+32 89 38 25 84",
    "sg:postcode":"3600",
    "sg:province":"Limburg",
    "sg:tags":[
        "retail",
        "-"
    ],
    "wof:name":"Novotex",
    "wof:placetype":"venue"
},
  "geometry": {"coordinates":[5.5071239471,51.0008239746],"type":"Point"}
}