{
  "type": "Feature",
  "properties": {
    "addr:full":"Terhulpensesteenweg 200 Overijse Vlaams-Brabant 3090",
    "addr:housenumber":"200",
    "addr:postcode":"3090",
    "addr:street":"Terhulpensesteenweg",
    "iso:country":"BE",
    "sg:address":"Terhulpensesteenweg 200",
    "sg:city":"Overijse",
    "sg:classifiers":[
        {
            "category":"Insurance",
            "subcategory":"Insurance Agent",
            "type":"Services"
        }
    ],
    "sg:phone":"+32 2 687 83 57",
    "sg:postcode":"3090",
    "sg:province":"Vlaams-Brabant",
    "sg:tags":[
        "broker"
    ],
    "wof:name":"Doignies P",
    "wof:placetype":"venue"
},
  "geometry": {"coordinates":[4.5348291397,50.7606201172],"type":"Point"}
}