{
  "type": "Feature",
  "properties": {
    "addr:full":"Place Loix 12 Sint-gillis/saint-gilles Bruxelles-Capitale 1060",
    "addr:housenumber":"12",
    "addr:postcode":"1060",
    "addr:street":"Place Loix",
    "iso:country":"BE",
    "sg:address":"Place Loix 12",
    "sg:city":"Sint-gillis/saint-gilles",
    "sg:orig_category":"M\u00e9decins and sp\u00e9cialistes",
    "sg:phone":"+32 2 534 41 60",
    "sg:postcode":"1060",
    "sg:province":"Bruxelles-Capitale",
    "wof:name":"Titus Mebara",
    "wof:placetype":"venue"
},
  "geometry": {"coordinates":[4.3536581993,50.8314285278],"type":"Point"}
}