{
  "type": "Feature",
  "properties": {
    "addr:full":"Zonnestraat 235 Ronse Oost-Vlaanderen 9600",
    "addr:housenumber":"235",
    "addr:postcode":"9600",
    "addr:street":"Zonnestraat",
    "iso:country":"BE",
    "sg:address":"Zonnestraat 235",
    "sg:city":"Ronse",
    "sg:orig_category":"V\u00eatements",
    "sg:phone":"+32 55 23 71 98",
    "sg:postcode":"9600",
    "sg:province":"Oost-Vlaanderen",
    "wof:name":"Alsi-shop",
    "wof:placetype":"venue"
},
  "geometry": {"coordinates":[3.581897974,50.7494506836],"type":"Point"}
}