{
  "type": "Feature",
  "properties": {
    "iso:country":"BE",
    "sg:address":"Oude Stationstraat 110",
    "sg:city":"Tielt",
    "sg:classifiers":[
        {
            "category":"Personal",
            "subcategory":"Beauty Salon",
            "type":"Services"
        }
    ],
    "sg:phone":"+32 51 40 31 63",
    "sg:postcode":"8700",
    "sg:province":"West-Vlaanderen",
    "sg:tags":[
        "lady",
        "-",
        "hairdressing"
    ],
    "wof:name":"Kathelijne",
    "wof:placetype":"venue"
},
  "geometry": {"coordinates":[3.3301169872,50.9928283691],"type":"Point"}
}