{
  "type": "Feature",
  "properties": {
    "iso:country":"BE",
    "sg:address":"Avenue Braban\u00c7onne 82",
    "sg:city":"Bruxelles",
    "sg:orig_category":"Eclairage et \u00e9quipements du foyer",
    "sg:phone":"+32 2 732 69 10",
    "sg:postcode":"1030",
    "sg:province":"Bruxelles-Capitale",
    "wof:name":"Insolite",
    "wof:placetype":"venue"
},
  "geometry": {"coordinates":[4.3866591454,50.8510742188],"type":"Point"}
}