{
  "type": "Feature",
  "properties": {
    "addr:full":"Zeepziederijstraat 5 Diksmuide West-Vlaanderen 8600",
    "addr:housenumber":"5",
    "addr:postcode":"8600",
    "addr:street":"Zeepziederijstraat",
    "iso:country":"BE",
    "sg:address":"Zeepziederijstraat 5",
    "sg:city":"Diksmuide",
    "sg:classifiers":[
        {
            "category":"Organizations",
            "subcategory":"Labor Organization",
            "type":"Services"
        }
    ],
    "sg:phone":"+32 51 50 01 17",
    "sg:postcode":"8600",
    "sg:province":"West-Vlaanderen",
    "sg:tags":[
        "draining",
        "work"
    ],
    "wof:name":"Vandezande",
    "wof:placetype":"venue"
},
  "geometry": {"coordinates":[2.8332300186,51.0347290039],"type":"Point"}
}