{
  "type": "Feature",
  "properties": {
    "iso:country":"BE",
    "sg:address":"Rue Cav\u00c9e 30",
    "sg:city":"Silly",
    "sg:orig_category":"M\u00e9decins and sp\u00e9cialistes",
    "sg:phone":"+32 68 55 17 07",
    "sg:postcode":"7830",
    "sg:province":"Hainaut",
    "wof:name":"J. Dubois",
    "wof:placetype":"venue"
},
  "geometry": {"coordinates":[3.9329369068,50.6772003174],"type":"Point"}
}