{
  "type": "Feature",
  "properties": {
    "addr:full":"Rue D\u00b4ypres 4 Tournai Hainaut 7538",
    "addr:housenumber":"4",
    "addr:postcode":"7538",
    "addr:street":"Rue D\u00b4Ypres",
    "iso:country":"BE",
    "sg:address":"Rue D\u00b4ypres 4",
    "sg:city":"Tournai",
    "sg:orig_category":"Fleurs and plantes",
    "sg:phone":"+32 69 44 44 74",
    "sg:postcode":"7538",
    "sg:province":"Hainaut",
    "wof:name":"Gerflor",
    "wof:placetype":"venue"
},
  "geometry": {"coordinates":[3.5083200932,50.5687904358],"type":"Point"}
}