{
  "type": "Feature",
  "properties": {
    "addr:full":"Luikerstraat 77 Sint-truiden Limburg 3800",
    "addr:housenumber":"77",
    "addr:postcode":"3800",
    "addr:street":"Luikerstraat",
    "iso:country":"BE",
    "sg:address":"Luikerstraat 77",
    "sg:city":"Sint-truiden",
    "sg:classifiers":[
        {
            "category":"Shopping",
            "subcategory":"Clothing, Apparel, & Fashions",
            "type":"Retail Goods"
        }
    ],
    "sg:phone":"+32 11 69 56 80",
    "sg:postcode":"3800",
    "sg:province":"Limburg",
    "sg:tags":[
        "boutique"
    ],
    "wof:name":"Vert Vert",
    "wof:placetype":"venue"
},
  "geometry": {"coordinates":[5.192512989,50.8096160889],"type":"Point"}
}