{
  "type": "Feature",
  "properties": {
    "iso:country":"BE",
    "sg:address":"Statiestraat 50",
    "sg:city":"Lint",
    "sg:classifiers":[
        {
            "category":"Professional",
            "subcategory":"Management & Consulting",
            "type":"Services"
        }
    ],
    "sg:phone":"+32 3 288 95 28",
    "sg:postcode":"2547",
    "sg:province":"Antwerpen",
    "sg:tags":[
        "consultant",
        "agency",
        "advertising"
    ],
    "wof:name":"Z-verplaetse",
    "wof:placetype":"venue"
},
  "geometry": {"coordinates":[4.497300148,51.1292228699],"type":"Point"}
}