{
  "type": "Feature",
  "properties": {
    "addr:full":"Tervuursesteenweg 254 Mechelen Antwerpen 2800",
    "addr:housenumber":"254",
    "addr:postcode":"2800",
    "addr:street":"Tervuursesteenweg",
    "iso:country":"BE",
    "sg:address":"Tervuursesteenweg 254",
    "sg:city":"Mechelen",
    "sg:orig_category":"HERSTELLING ELEKTRISCHE HUISHOUDAPPARATEN Huishoudapparaten, televisies and radio's",
    "sg:phone":"+32 15 42 16 16",
    "sg:postcode":"2800",
    "sg:province":"Antwerpen",
    "wof:name":"Roger Van Der Goten",
    "wof:placetype":"venue"
},
  "geometry": {"coordinates":[4.4856362343,51.0069923401],"type":"Point"}
}