{
  "type": "Feature",
  "properties": {
    "addr:full":"Koning Ridderdijk 36 Middelkerke West-Vlaanderen 8434",
    "addr:housenumber":"36",
    "addr:postcode":"8434",
    "addr:street":"Koning Ridderdijk",
    "iso:country":"BE",
    "sg:address":"Koning Ridderdijk 36",
    "sg:city":"Middelkerke",
    "sg:orig_category":"Dameskledingzaken Herenkledingzaken",
    "sg:phone":"+32 59 30 63 89",
    "sg:postcode":"8434",
    "sg:province":"West-Vlaanderen",
    "wof:name":"Huis Stella-maris",
    "wof:placetype":"venue"
},
  "geometry": {"coordinates":[2.7569050789,51.1488685608],"type":"Point"}
}