{
  "type": "Feature",
  "properties": {
    "addr:full":"Sint-livinusstraat 59 Ieper (elverdinge) West-Vlaanderen 8906",
    "addr:housenumber":"59",
    "addr:postcode":"8906",
    "addr:street":"Sint-Livinusstraat",
    "iso:country":"BE",
    "sg:address":"Sint-livinusstraat 59",
    "sg:city":"Ieper (elverdinge)",
    "sg:classifiers":[
        {
            "category":"Health Services",
            "subcategory":"Health Practitioner",
            "type":"Services"
        }
    ],
    "sg:phone":"+32 57 42 25 04",
    "sg:postcode":"8906",
    "sg:province":"West-Vlaanderen",
    "sg:tags":[
        "therapist",
        "speech"
    ],
    "wof:name":"Malfait I",
    "wof:placetype":"venue"
},
  "geometry": {"coordinates":[2.8229300976,50.8812217712],"type":"Point"}
}