{
  "type": "Feature",
  "properties": {
    "addr:full":"Halledorp 100 Zoersel Antwerpen 2980",
    "addr:housenumber":"100",
    "addr:postcode":"2980",
    "addr:street":"Halledorp",
    "iso:country":"BE",
    "sg:address":"Halledorp 100",
    "sg:city":"Zoersel",
    "sg:orig_category":"M\u00e9decins and sp\u00e9cialistes",
    "sg:phone":"+32 3 385 41 42",
    "sg:postcode":"2980",
    "sg:province":"Antwerpen",
    "wof:name":"Paul Rabijns",
    "wof:placetype":"venue"
},
  "geometry": {"coordinates":[4.6434659958,51.2401847839],"type":"Point"}
}