{
  "type": "Feature",
  "properties": {
    "iso:country":"BE",
    "sg:address":"Quai Des Vennes 1 Box 33",
    "sg:city":"Li\u00e8ge 1 (li\u00e8ge 2)",
    "sg:classifiers":[
        {
            "category":"Shopping",
            "subcategory":"Jewelry",
            "type":"Retail Goods"
        }
    ],
    "sg:phone":"+32 4 349 08 85",
    "sg:postcode":"4020",
    "sg:province":"Li\u00e8ge",
    "sg:tags":[
        "jeweller",
        "-"
    ],
    "wof:name":"Lacher",
    "wof:placetype":"venue"
},
  "geometry": {"coordinates":[5.5939102173,50.616394043],"type":"Point"}
}