{
  "type": "Feature",
  "properties": {
    "addr:full":"Provinciebaan 21 Staden (westrozebeke) West-Vlaanderen 8840",
    "addr:housenumber":"21",
    "addr:postcode":"8840",
    "addr:street":"Provinciebaan",
    "iso:country":"BE",
    "sg:address":"Provinciebaan 21",
    "sg:city":"Staden (westrozebeke)",
    "sg:classifiers":[
        {
            "category":"Arena",
            "subcategory":"Sports Club",
            "type":"Entertainment"
        }
    ],
    "sg:phone":"+32 51 77 05 10",
    "sg:postcode":"8840",
    "sg:province":"West-Vlaanderen",
    "wof:name":"Sportcentrum De Boskant",
    "wof:placetype":"venue"
},
  "geometry": {"coordinates":[3.0457150936,50.9539299011],"type":"Point"}
}