{
  "type": "Feature",
  "properties": {
    "addr:full":"Avenue D'itterbeek 390 Bruxelles (anderlecht) Bruxelles-Capitale 1070",
    "addr:housenumber":"390",
    "addr:postcode":"1070",
    "addr:street":"Avenue D'Itterbeek",
    "iso:country":"BE",
    "sg:address":"Avenue D'itterbeek 390",
    "sg:city":"Bruxelles (anderlecht)",
    "sg:classifiers":[
        {
            "category":"Bars & Pubs",
            "type":"Food & Drink"
        }
    ],
    "sg:phone":"+32 2 522 56 88",
    "sg:postcode":"1070",
    "sg:province":"Bruxelles-Capitale",
    "wof:name":"Bij Alene & Prosper",
    "wof:placetype":"venue"
},
  "geometry": {"coordinates":[4.2782740593,50.8351211548],"type":"Point"}
}