{
  "type": "Feature",
  "properties": {
    "iso:country":"BE",
    "sg:address":"Baaigemstraat 237",
    "sg:city":"Gavere",
    "sg:classifiers":[
        {
            "category":"Wholesale",
            "subcategory":"Meat",
            "type":"Manufacturing & Wholesale Goods"
        }
    ],
    "sg:phone":"+32 9 362 16 00",
    "sg:postcode":"9890",
    "sg:province":"Oost-Vlaanderen",
    "sg:tags":[
        "machine",
        "product",
        "-",
        "supply"
    ],
    "wof:name":"A.d.s. Food Technology",
    "wof:placetype":"venue"
},
  "geometry": {"coordinates":[3.6904220581,50.9325790405],"type":"Point"}
}