{
  "type": "Feature",
  "properties": {
    "iso:country":"BE",
    "sg:address":"Rue Des Dominicains 4",
    "sg:city":"Li\u00c8ge",
    "sg:orig_category":"R\u00e9parations d'horloges, montres and bijoux. Bijouteries and horlogeries",
    "sg:phone":"+32 4 223 41 78",
    "sg:postcode":"4000",
    "sg:province":"Li\u00e8ge",
    "wof:name":"Maison Piron Georges",
    "wof:placetype":"venue"
},
  "geometry": {"coordinates":[5.5697550774,50.6430358887],"type":"Point"}
}