{
  "type": "Feature",
  "properties": {
    "iso:country":"BE",
    "sg:address":"Donksesteenweg 212",
    "sg:city":"Brasschaat",
    "sg:classifiers":[
        {
            "category":"Restaurant",
            "type":"Food & Drink"
        }
    ],
    "sg:phone":"+32 3 646 60 63",
    "sg:postcode":"2930",
    "sg:province":"Antwerpen",
    "sg:tags":[
        "caf\u00e9s"
    ],
    "wof:name":"Taverne Madouce",
    "wof:placetype":"venue"
},
  "geometry": {"coordinates":[4.4540362358,51.2810211182],"type":"Point"}
}