{
  "type": "Feature",
  "properties": {
    "addr:full":"Rue De Bruxelles 45 Wavre Brabant Wallon 1300",
    "addr:housenumber":"45;1300",
    "addr:street":"Rue De Bruxelles",
    "iso:country":"BE",
    "sg:address":"Rue De Bruxelles 45",
    "sg:city":"Wavre",
    "sg:orig_category":"Enseignement maternel and primaire",
    "sg:phone":"+32 10 22 97 77",
    "sg:postcode":"1300",
    "sg:province":"Brabant Wallon",
    "wof:name":"Ecole Fondamentale Libre",
    "wof:placetype":"venue"
},
  "geometry": {"coordinates":[4.6131591797,50.7185821533],"type":"Point"}
}