{
  "type": "Feature",
  "properties": {
    "addr:full":"Rue De L'h\u00f4tel Communal 90 Saint-nicolas Li\u00e8ge 4420",
    "addr:housenumber":"90",
    "addr:postcode":"4420",
    "addr:street":"Rue De L'Ho \u0302Tel Communal",
    "iso:country":"BE",
    "sg:address":"Rue De L'h\u00f4tel Communal 90",
    "sg:city":"Saint-nicolas",
    "sg:classifiers":[
        {
            "category":"Manufacturing",
            "subcategory":"Metals",
            "type":"Manufacturing & Wholesale Goods"
        }
    ],
    "sg:phone":"+32 475 51 35 81",
    "sg:postcode":"4420",
    "sg:province":"Li\u00e8ge",
    "sg:tags":[
        "working"
    ],
    "wof:name":"Betam-bellicano Sprl",
    "wof:placetype":"venue"
},
  "geometry": {"coordinates":[5.5395269394,50.6329956055],"type":"Point"}
}