{
  "type": "Feature",
  "properties": {
    "iso:country":"BE",
    "sg:address":"Herentalsebaan 141",
    "sg:city":"Borsbeek",
    "sg:classifiers":[
        {
            "category":"Professional",
            "subcategory":"Engineering",
            "type":"Services"
        }
    ],
    "sg:phone":"+32 3 366 42 42",
    "sg:postcode":"2150",
    "sg:province":"Antwerpen",
    "sg:tags":[
        "industrial",
        "-",
        "automation"
    ],
    "wof:name":"Bw Procestechniek Nv",
    "wof:placetype":"venue"
},
  "geometry": {"coordinates":[4.4893488884,51.2000083923],"type":"Point"}
}