{
  "type": "Feature",
  "properties": {
    "addr:full":"M\u00fchlenbachstrasse 14 Sankt Vith Li\u00e8ge 4780",
    "addr:housenumber":"14",
    "addr:postcode":"4780",
    "addr:street":"Muehlenbachstrasse",
    "iso:country":"BE",
    "sg:address":"M\u00fchlenbachstrasse 14",
    "sg:city":"Sankt Vith",
    "sg:classifiers":[
        {
            "category":"Building & Trades",
            "subcategory":"Equipment Rental",
            "type":"Services"
        }
    ],
    "sg:phone":"+32 80 22 64 22",
    "sg:postcode":"4780",
    "sg:province":"Li\u00e8ge",
    "sg:tags":[
        "machine",
        "industrial",
        "dishwashing"
    ],
    "wof:name":"Sch\u00fctz Elektro Sprlu",
    "wof:placetype":"venue"
},
  "geometry": {"coordinates":[6.1273479462,50.2810554504],"type":"Point"}
}