{
  "type": "Feature",
  "properties": {
    "addr:full":"Oude Brugsepoort 34 Deinze Oost-Vlaanderen 9800",
    "addr:housenumber":"34",
    "addr:postcode":"9800",
    "addr:street":"Oude Brugsepoort",
    "iso:country":"BE",
    "sg:address":"Oude Brugsepoort 34",
    "sg:city":"Deinze",
    "sg:classifiers":[
        {
            "category":"Real Estate",
            "subcategory":"Surveying",
            "type":"Services"
        }
    ],
    "sg:phone":"+32 9 380 36 82",
    "sg:postcode":"9800",
    "sg:province":"Oost-Vlaanderen",
    "sg:tags":[
        "surveyor",
        "land"
    ],
    "wof:name":"K.d.v. Nv",
    "wof:placetype":"venue"
},
  "geometry": {"coordinates":[3.521310091,50.9890060425],"type":"Point"}
}