{
  "type": "Feature",
  "properties": {
    "addr:full":"Rue De Buresse 54 Hamois Namur 5360",
    "addr:housenumber":"54",
    "addr:postcode":"5360",
    "addr:street":"Rue De Buresse",
    "iso:country":"BE",
    "sg:address":"Rue De Buresse 54",
    "sg:city":"Hamois",
    "sg:orig_category":"Rundveehouders",
    "sg:phone":"+32 83 61 10 54",
    "sg:postcode":"5360",
    "sg:province":"Namur",
    "wof:name":"Pierre Devaux",
    "wof:placetype":"venue"
},
  "geometry": {"coordinates":[5.1542420387,50.3611984253],"type":"Point"}
}