{
  "type": "Feature",
  "properties": {
    "addr:full":"Gr. De Smet De Naeyerln 46 Oostende West-Vlaanderen 8400",
    "addr:housenumber":"46",
    "addr:postcode":"8400",
    "addr:street":"Gr. De Smet De Naeyerln",
    "iso:country":"BE",
    "sg:address":"Gr. De Smet De Naeyerln 46",
    "sg:city":"Oostende",
    "sg:orig_category":"Animations diverses. Services divers aux entreprises. Agents artistiques",
    "sg:phone":"+32 59 70 57 09",
    "sg:postcode":"8400",
    "sg:province":"West-Vlaanderen",
    "wof:name":"Jean-pierre Bras",
    "wof:placetype":"venue"
},
  "geometry": {"coordinates":[2.9249279499,51.2248420715],"type":"Point"}
}