{
  "type": "Feature",
  "properties": {
    "addr:full":"Hoefstraat 12 Haaltert Oost-Vlaanderen 9450",
    "addr:housenumber":"12",
    "addr:postcode":"9450",
    "addr:street":"Hoefstraat",
    "iso:country":"BE",
    "sg:address":"Hoefstraat 12",
    "sg:city":"Haaltert",
    "sg:orig_category":"Woningbouw",
    "sg:phone":"+32 53 83 69 28",
    "sg:postcode":"9450",
    "sg:province":"Oost-Vlaanderen",
    "wof:name":"Roger Braem",
    "wof:placetype":"venue"
},
  "geometry": {"coordinates":[3.9752390385,50.8970336914],"type":"Point"}
}