{
  "type": "Feature",
  "properties": {
    "iso:country":"BE",
    "sg:address":"Cauwerburg 103",
    "sg:city":"Temse",
    "sg:orig_category":"Brood, gebak and snoepgoed",
    "sg:phone":"+32 3 771 93 17",
    "sg:postcode":"9140",
    "sg:province":"Oost-Vlaanderen",
    "wof:name":"Bakkerij Cathy",
    "wof:placetype":"venue"
},
  "geometry": {"coordinates":[4.1966500282,51.1212387085],"type":"Point"}
}