{
  "type": "Feature",
  "properties": {
    "iso:country":"BE",
    "sg:address":"Veldstraat 14",
    "sg:city":"Lovendegem",
    "sg:classifiers":[
        {
            "category":"Building & Trades",
            "subcategory":"Plumbing",
            "type":"Services"
        }
    ],
    "sg:phone":"+32 475 82 60 09",
    "sg:postcode":"9920",
    "sg:province":"Oost-Vlaanderen",
    "sg:tags":[
        "contractor"
    ],
    "wof:name":"Dasalo Bvba",
    "wof:placetype":"venue"
},
  "geometry": {"coordinates":[3.6146090031,51.1176528931],"type":"Point"}
}