{
  "type": "Feature",
  "properties": {
    "addr:full":"Soerveldweg 32 Dilsen-stokkem Limburg 3650",
    "addr:housenumber":"32",
    "addr:postcode":"3650",
    "addr:street":"Soerveldweg",
    "iso:country":"BE",
    "sg:address":"Soerveldweg 32",
    "sg:city":"Dilsen-stokkem",
    "sg:orig_category":"Eleveurs and marchands de porcs",
    "sg:phone":"+32 89 75 58 32",
    "sg:postcode":"3650",
    "sg:province":"Limburg",
    "wof:name":"Werner Gonnissen",
    "wof:placetype":"venue"
},
  "geometry": {"coordinates":[5.7242832184,51.026599884],"type":"Point"}
}