{
  "type": "Feature",
  "properties": {
    "addr:full":"Rue Du Corbeau 21 Dison Li\u00e8ge 4820",
    "addr:housenumber":"21",
    "addr:postcode":"4820",
    "addr:street":"Rue Du Corbeau",
    "iso:country":"BE",
    "sg:address":"Rue Du Corbeau 21",
    "sg:city":"Dison",
    "sg:orig_category":"Entretien and r\u00e9parations de voitures",
    "sg:phone":"+32 87 33 11 46",
    "sg:postcode":"4820",
    "sg:province":"Li\u00e8ge",
    "wof:name":"Carrosserie Delhez",
    "wof:placetype":"venue"
},
  "geometry": {"coordinates":[5.8558487892,50.6157608032],"type":"Point"}
}