{
  "type": "Feature",
  "properties": {
    "iso:country":"BE",
    "sg:address":"Coupure Rechts 952",
    "sg:city":"Gent",
    "sg:classifiers":[
        {
            "category":"Health Services",
            "subcategory":"Doctor",
            "type":"Services"
        }
    ],
    "sg:phone":"+32 9 223 62 22",
    "sg:postcode":"9000",
    "sg:province":"Oost-Vlaanderen",
    "sg:tags":[
        "medicinephysicians",
        "surgeon"
    ],
    "wof:name":"Gobert Ann",
    "wof:placetype":"venue"
},
  "geometry": {"coordinates":[3.7089970112,51.0562019348],"type":"Point"}
}