{
  "type": "Feature",
  "properties": {
    "iso:country":"BE",
    "sg:address":"Duffelsesteenweg 82",
    "sg:city":"Kontich",
    "sg:orig_category":"Supermarch\u00e9s",
    "sg:phone":"+32 3 458 34 70",
    "sg:postcode":"2550",
    "sg:province":"Antwerpen",
    "wof:name":"Brandt - Food",
    "wof:placetype":"venue"
},
  "geometry": {"coordinates":[4.4502849579,51.1299552917],"type":"Point"}
}