{
  "type": "Feature",
  "properties": {
    "addr:full":"Rue March\u00c9 Aux Herbes 14 Brussel/bruxelles Bruxelles-Capitale 1000",
    "addr:housenumber":"14",
    "addr:postcode":"1000",
    "addr:street":"Rue Marche\u0301 Aux Herbes;/",
    "iso:country":"BE",
    "sg:address":"Rue March\u00c9 Aux Herbes 14",
    "sg:city":"Brussel/bruxelles",
    "sg:orig_category":"Mat\u00e9riel de T\u00e9l\u00e9communication",
    "sg:phone":"+32 2 223 29 29",
    "sg:postcode":"1000",
    "sg:province":"Bruxelles-Capitale",
    "wof:name":"Mobistar Center All-com",
    "wof:placetype":"venue"
},
  "geometry": {"coordinates":[4.3521881104,50.8481216431],"type":"Point"}
}