{
  "type": "Feature",
  "properties": {
    "iso:country":"BE",
    "sg:address":"Pastorijstraat 25",
    "sg:city":"Lubbeek",
    "sg:orig_category":"Banken and kredietinstellingen",
    "sg:phone":"+32 16 62 09 68",
    "sg:postcode":"3210",
    "sg:province":"Vlaams-Brabant",
    "wof:name":"Centea",
    "wof:placetype":"venue"
},
  "geometry": {"coordinates":[4.7695741653,50.8967781067],"type":"Point"}
}