{
  "type": "Feature",
  "properties": {
    "iso:country":"BE",
    "sg:address":"Place De Bronckart 22",
    "sg:city":"Li\u00c8ge",
    "sg:orig_category":"Services annexes des transports terrestres",
    "sg:phone":"+32 4 252 88 89",
    "sg:postcode":"4000",
    "sg:province":"Li\u00e8ge",
    "wof:name":"Parking Cath\u00c9drale",
    "wof:placetype":"venue"
},
  "geometry": {"coordinates":[5.5655012131,50.6290054321],"type":"Point"}
}