{
  "type": "Feature",
  "properties": {
    "addr:full":"Rue Des H\u00catres 82 Bastogne Luxembourg 6600",
    "addr:housenumber":"82",
    "addr:postcode":"6600",
    "addr:street":"Rue Des He\u0302Tres",
    "iso:country":"BE",
    "sg:address":"Rue Des H\u00catres 82",
    "sg:city":"Bastogne",
    "sg:orig_category":"M\u00e9decins and sp\u00e9cialistes",
    "sg:phone":"+32 61 21 21 46",
    "sg:postcode":"6600",
    "sg:province":"Luxembourg",
    "wof:name":"Jacques Leclercq",
    "wof:placetype":"venue"
},
  "geometry": {"coordinates":[5.7306132317,50.0045852661],"type":"Point"}
}