{
  "type": "Feature",
  "properties": {
    "addr:full":"Gasthuisstraat 6 Nijlen Antwerpen 2560",
    "addr:housenumber":"6",
    "addr:postcode":"2560",
    "addr:street":"Gasthuisstraat",
    "iso:country":"BE",
    "sg:address":"Gasthuisstraat 6",
    "sg:city":"Nijlen",
    "sg:orig_category":"S\u00e9curit\u00e9 sociale",
    "sg:phone":"+32 3 480 55 65",
    "sg:postcode":"2560",
    "sg:province":"Antwerpen",
    "wof:name":"Christelijke Mutualiteit",
    "wof:placetype":"venue"
},
  "geometry": {"coordinates":[4.6288790703,51.1381835938],"type":"Point"}
}