{
  "type": "Feature",
  "properties": {
    "addr:full":"Zeeptstraat 65 Keerbergen Vlaams-Brabant 3140",
    "addr:housenumber":"65",
    "addr:postcode":"3140",
    "addr:street":"Zeeptstraat",
    "iso:country":"BE",
    "sg:address":"Zeeptstraat 65",
    "sg:city":"Keerbergen",
    "sg:orig_category":"Forge, Moulage and Profilage des M\u00e9taux",
    "sg:phone":"+32 15 51 67 84",
    "sg:postcode":"3140",
    "sg:province":"Vlaams-Brabant",
    "wof:name":"Verreth",
    "wof:placetype":"venue"
},
  "geometry": {"coordinates":[4.6029009819,50.9950027466],"type":"Point"}
}