{
  "type": "Feature",
  "properties": {
    "addr:full":"Rue Ferrer 28bb Chapelle-lez-herlaimont Hainaut 7160",
    "addr:housenumber":"28bb",
    "addr:postcode":"7160",
    "addr:street":"Rue Ferrer",
    "iso:country":"BE",
    "sg:address":"Rue Ferrer 28bb",
    "sg:city":"Chapelle-lez-herlaimont",
    "sg:orig_category":"Plomberie, chauffage and installations sanitaires",
    "sg:phone":"+32 64 44 35 19",
    "sg:postcode":"7160",
    "sg:province":"Hainaut",
    "wof:name":"Eric De Mol",
    "wof:placetype":"venue"
},
  "geometry": {"coordinates":[4.2812700272,50.4893264771],"type":"Point"}
}