{
  "type": "Feature",
  "properties": {
    "addr:full":"Heibaan 209 Hulshout Antwerpen 2235",
    "addr:housenumber":"209",
    "addr:postcode":"2235",
    "addr:street":"Heibaan",
    "iso:country":"BE",
    "sg:address":"Heibaan 209",
    "sg:city":"Hulshout",
    "sg:orig_category":"Fotografen and fotostudio's",
    "sg:phone":"+32 16 69 76 70",
    "sg:postcode":"2235",
    "sg:province":"Antwerpen",
    "wof:name":"Joris Roothooft",
    "wof:placetype":"venue"
},
  "geometry": {"coordinates":[4.822286129,51.0731925964],"type":"Point"}
}