{
  "type": "Feature",
  "properties": {
    "addr:full":"Avenue Du Panth\u00c9on 54 Koekelberg/koekelberg Bruxelles-Capitale 1081",
    "addr:housenumber":"54",
    "addr:postcode":"1081",
    "addr:street":"Avenue Du Panthe\u0301On",
    "iso:country":"BE",
    "sg:address":"Avenue Du Panth\u00c9on 54",
    "sg:city":"Koekelberg/koekelberg",
    "sg:classifiers":[
        {
            "category":"Building & Trades",
            "subcategory":"Plumbing",
            "type":"Services"
        }
    ],
    "sg:phone":"+32 2 414 71 95",
    "sg:postcode":"1081",
    "sg:province":"Bruxelles-Capitale",
    "sg:tags":[
        "diver",
        "commerce",
        "gr",
        "pour",
        "equipement"
    ],
    "wof:name":"Inter Beauty Cosmetique",
    "wof:placetype":"venue"
},
  "geometry": {"coordinates":[4.3212709427,50.8646507263],"type":"Point"}
}