{
  "type": "Feature",
  "properties": {
    "addr:full":"Oude Katsei 94b Gingelom Limburg 3890",
    "addr:housenumber":"94b",
    "addr:postcode":"3890",
    "addr:street":"Oude Katsei",
    "iso:country":"BE",
    "sg:address":"Oude Katsei 94b",
    "sg:city":"Gingelom",
    "sg:classifiers":[
        {
            "category":"Retail",
            "subcategory":"Veterinary Services",
            "type":"Services"
        }
    ],
    "sg:phone":"+32 11 88 79 59",
    "sg:postcode":"3890",
    "sg:province":"Limburg",
    "sg:tags":[
        "veterinarian"
    ],
    "wof:name":"Blum A",
    "wof:placetype":"venue"
},
  "geometry": {"coordinates":[5.1347198486,50.7442512512],"type":"Point"}
}