{
  "type": "Feature",
  "properties": {
    "iso:country":"BE",
    "sg:address":"Veldstraat 7",
    "sg:city":"Kinrooi",
    "sg:orig_category":"Rundveehouders",
    "sg:phone":"+32 89 56 59 24",
    "sg:postcode":"3640",
    "sg:province":"Limburg",
    "wof:name":"Laurentius Stakenborg",
    "wof:placetype":"venue"
},
  "geometry": {"coordinates":[5.819340229,51.1526412964],"type":"Point"}
}