{
  "type": "Feature",
  "properties": {
    "addr:full":"Boulevard De Waterloo 38 Bruxelles Bruxelles-Capitale 1000",
    "addr:housenumber":"38",
    "addr:postcode":"1000",
    "addr:street":"Boulevard De Waterloo",
    "iso:country":"BE",
    "sg:address":"Boulevard De Waterloo 38",
    "sg:city":"Bruxelles",
    "sg:classifiers":[
        {
            "category":"Community Center",
            "subcategory":"Social",
            "type":"Public Place"
        }
    ],
    "sg:phone":"+32 2 512 86 99",
    "sg:postcode":"1000",
    "sg:province":"Bruxelles-Capitale",
    "sg:tags":[
        "pencil",
        "pen"
    ],
    "wof:name":"Gilson",
    "wof:placetype":"venue"
},
  "geometry": {"coordinates":[4.3575940132,50.8372879028],"type":"Point"}
}