{
  "type": "Feature",
  "properties": {
    "iso:country":"BE",
    "sg:address":"Koersel Dorp 26",
    "sg:city":"Beringen (koersel)",
    "sg:classifiers":[
        {
            "category":"Bars & Pubs",
            "type":"Food & Drink"
        }
    ],
    "sg:phone":"+32 11 42 52 57",
    "sg:postcode":"3582",
    "sg:province":"Limburg",
    "wof:name":"Duivenlokaal De Toekomst",
    "wof:placetype":"venue"
},
  "geometry": {"coordinates":[5.2708749771,51.0595359802],"type":"Point"}
}