{
  "type": "Feature",
  "properties": {
    "iso:country":"BE",
    "sg:address":"Rijksweg 584",
    "sg:city":"Maasmechelen",
    "sg:classifiers":[
        {
            "category":"Manufacturing",
            "subcategory":"Tobacco Products",
            "type":"Manufacturing & Wholesale Goods"
        }
    ],
    "sg:phone":"+32 89 76 02 88",
    "sg:postcode":"3630",
    "sg:province":"Limburg",
    "sg:tags":[
        "soil",
        "peat"
    ],
    "wof:name":"Warson H",
    "wof:placetype":"venue"
},
  "geometry": {"coordinates":[5.6942400932,50.956161499],"type":"Point"}
}