{
  "type": "Feature",
  "properties": {
    "iso:country":"BE",
    "sg:address":"Rue Cesar De Paepe 120",
    "sg:city":"Charleroi",
    "sg:orig_category":"Kapsalons",
    "sg:phone":"+32 71 34 27 44",
    "sg:postcode":"6040",
    "sg:province":"Hainaut",
    "wof:name":"New Coiff Michel",
    "wof:placetype":"venue"
},
  "geometry": {"coordinates":[4.413312912,50.4357223511],"type":"Point"}
}