{
  "type": "Feature",
  "properties": {
    "iso:country":"BE",
    "sg:address":"Amerikalei 7",
    "sg:city":"Antwerpen",
    "sg:orig_category":"Artsen and specialisten",
    "sg:phone":"+32 3 238 20 86",
    "sg:postcode":"2000",
    "sg:province":"Antwerpen",
    "wof:name":"A. Croket",
    "wof:placetype":"venue"
},
  "geometry": {"coordinates":[4.4017419815,51.2082633972],"type":"Point"}
}