{
  "type": "Feature",
  "properties": {
    "addr:full":"Obberg 107 Wemmel/wemmel Vlaams-Brabant 1780",
    "addr:housenumber":"107",
    "addr:postcode":"1780",
    "addr:street":"Obberg",
    "iso:country":"BE",
    "sg:address":"Obberg 107",
    "sg:city":"Wemmel/wemmel",
    "sg:orig_category":"R\u00e9parations d'appareils \u00e9lectrom\u00e9nagers. Electrom\u00e9nager, t\u00e9l\u00e9visions and radios",
    "sg:phone":"+32 2 461 06 60",
    "sg:postcode":"1780",
    "sg:province":"Vlaams-Brabant",
    "wof:name":"Tv Video Technique",
    "wof:placetype":"venue"
},
  "geometry": {"coordinates":[4.3002791405,50.900352478],"type":"Point"}
}