{
  "type": "Feature",
  "properties": {
    "addr:full":"Rue De La Station 22 Havelange Namur 5370",
    "addr:housenumber":"22",
    "addr:postcode":"5370",
    "addr:street":"Rue De La Station",
    "iso:country":"BE",
    "sg:address":"Rue De La Station 22",
    "sg:city":"Havelange",
    "sg:classifiers":[
        {
            "category":"Building & Trades",
            "subcategory":"Electrical",
            "type":"Services"
        }
    ],
    "sg:phone":"+32 83 63 33 31",
    "sg:postcode":"5370",
    "sg:province":"Namur",
    "sg:tags":[
        "electric",
        "-",
        "housewiring",
        "contractor"
    ],
    "wof:name":"Lizen Sprl",
    "wof:placetype":"venue"
},
  "geometry": {"coordinates":[5.2405519485,50.3886146545],"type":"Point"}
}