{
  "type": "Feature",
  "properties": {
    "iso:country":"BE",
    "sg:address":"Rue Moris 33",
    "sg:city":"Bruxelles (saint-gilles)",
    "sg:classifiers":[
        {
            "category":"Building & Trades",
            "subcategory":"Construction",
            "type":"Services"
        }
    ],
    "sg:phone":"+32 2 544 04 00",
    "sg:postcode":"1060",
    "sg:province":"Bruxelles-Capitale",
    "sg:tags":[
        "work",
        "waterproofing"
    ],
    "wof:name":"Maintenance-travaux",
    "wof:placetype":"venue"
},
  "geometry": {"coordinates":[4.3515129089,50.8246841431],"type":"Point"}
}