{
  "type": "Feature",
  "properties": {
    "iso:country":"BE",
    "sg:address":"Robert Scottstraat 40",
    "sg:city":"Ukkel/uccle",
    "sg:orig_category":"Architecten",
    "sg:phone":"+32 2 375 22 12",
    "sg:postcode":"1180",
    "sg:province":"Bruxelles-Capitale",
    "wof:name":"Pierre Lemaire",
    "wof:placetype":"venue"
},
  "geometry": {"coordinates":[4.339015007,50.79920578],"type":"Point"}
}