{
  "type": "Feature",
  "properties": {
    "addr:full":"Hoekstraat 51 Wichelen Oost-Vlaanderen 9260",
    "addr:housenumber":"51",
    "addr:postcode":"9260",
    "addr:street":"Hoekstraat",
    "iso:country":"BE",
    "sg:address":"Hoekstraat 51",
    "sg:city":"Wichelen",
    "sg:orig_category":"Diverse voedingsmiddelen Gh Vis and zeevruchten",
    "sg:phone":"+32 9 369 82 51",
    "sg:postcode":"9260",
    "sg:province":"Oost-Vlaanderen",
    "wof:name":"De Coninck-van Hoecke",
    "wof:placetype":"venue"
},
  "geometry": {"coordinates":[3.935131073,51.0037460327],"type":"Point"}
}