{
  "type": "Feature",
  "properties": {
    "addr:full":"Turnhoutsebaan 5b131 Wijnegem Antwerpen 2110",
    "addr:housenumber":"5b131",
    "addr:postcode":"2110",
    "addr:street":"Turnhoutsebaan",
    "iso:country":"BE",
    "sg:address":"Turnhoutsebaan 5b131",
    "sg:city":"Wijnegem",
    "sg:orig_category":"Juwelen and horloges",
    "sg:phone":"+32 3 354 09 04",
    "sg:postcode":"2110",
    "sg:province":"Antwerpen",
    "wof:name":"Huis Vendi",
    "wof:placetype":"venue"
},
  "geometry": {"coordinates":[4.5043401718,51.2240219116],"type":"Point"}
}