{
  "type": "Feature",
  "properties": {
    "iso:country":"BE",
    "sg:address":"Rue De L'haisette 34",
    "sg:city":"Quaregnon",
    "sg:orig_category":"Plaatsen van vloer- and muurbekleding Schilders Verlichting and huishoudartikelen",
    "sg:phone":"+32 65 77 84 84",
    "sg:postcode":"7390",
    "sg:province":"Hainaut",
    "wof:name":"Dino Mattucci",
    "wof:placetype":"venue"
},
  "geometry": {"coordinates":[3.8598608971,50.4443397522],"type":"Point"}
}