{
  "type": "Feature",
  "properties": {
    "iso:country":"BE",
    "sg:address":"Brugsesteenweg 133",
    "sg:city":"Pittem",
    "sg:orig_category":"Rundveehouders Varkenskwekers",
    "sg:phone":"+32 51 46 60 71",
    "sg:postcode":"8740",
    "sg:province":"West-Vlaanderen",
    "wof:name":"Joost Lannoo",
    "wof:placetype":"venue"
},
  "geometry": {"coordinates":[3.2386798859,50.9919815063],"type":"Point"}
}