{
  "type": "Feature",
  "properties": {
    "addr:full":"Avenue De Bouillon 50 Libramont-chevigny Luxembourg 6800",
    "addr:housenumber":"50",
    "addr:postcode":"6800",
    "addr:street":"Avenue De Bouillon",
    "iso:country":"BE",
    "sg:address":"Avenue De Bouillon 50",
    "sg:city":"Libramont-chevigny",
    "sg:orig_category":"Maroquinerie and articles de voyage. V\u00eatements. Chaussures",
    "sg:phone":"+32 61 22 58 90",
    "sg:postcode":"6800",
    "sg:province":"Luxembourg",
    "wof:name":"Pronti",
    "wof:placetype":"venue"
},
  "geometry": {"coordinates":[5.368103981,49.9166679382],"type":"Point"}
}