{
  "type": "Feature",
  "properties": {
    "addr:full":"Avenue Brugmann 324 Ukkel/uccle Bruxelles-Capitale 1180",
    "addr:housenumber":"324",
    "addr:postcode":"1180",
    "addr:street":"Avenue Brugmann;/",
    "iso:country":"BE",
    "sg:address":"Avenue Brugmann 324",
    "sg:city":"Ukkel/uccle",
    "sg:orig_category":"Entretien and r\u00e9parations de voitures",
    "sg:phone":"+32 2 344 93 16",
    "sg:postcode":"1180",
    "sg:province":"Bruxelles-Capitale",
    "wof:name":"D. Wallemacq",
    "wof:placetype":"venue"
},
  "geometry": {"coordinates":[4.3444070816,50.8077011108],"type":"Point"}
}