{
  "type": "Feature",
  "properties": {
    "iso:country":"BE",
    "sg:address":"Route De Mirwart 47",
    "sg:city":"Saint-hubert",
    "sg:orig_category":"Vakantiehuizen",
    "sg:phone":"+32 84 37 77 24",
    "sg:postcode":"6870",
    "sg:province":"Luxembourg",
    "wof:name":"Le Sartay",
    "wof:placetype":"venue"
},
  "geometry": {"coordinates":[5.373360157,50.0256156921],"type":"Point"}
}