{
  "type": "Feature",
  "properties": {
    "addr:full":"Rue Du Ch\u00c2teau 11 Soignies Hainaut 7061",
    "addr:housenumber":"11",
    "addr:postcode":"7061",
    "addr:street":"Rue Du Cha\u0302Teau",
    "iso:country":"BE",
    "sg:address":"Rue Du Ch\u00c2teau 11",
    "sg:city":"Soignies",
    "sg:orig_category":"Plaatsen van vloer- and muurbekleding Schilders",
    "sg:phone":"+32 65 72 30 40",
    "sg:postcode":"7061",
    "sg:province":"Hainaut",
    "wof:name":"All-paints",
    "wof:placetype":"venue"
},
  "geometry": {"coordinates":[4.0133500099,50.5159416199],"type":"Point"}
}