{
  "type": "Feature",
  "properties": {
    "addr:full":"Clos Des Trois Couleurs 4 Bruxelles (woluwe-saint-pierre) Bruxelles-Capitale 1150",
    "addr:housenumber":"4",
    "addr:postcode":"1150",
    "addr:street":"Clos Des Trois Couleurs",
    "iso:country":"BE",
    "sg:address":"Clos Des Trois Couleurs 4",
    "sg:city":"Bruxelles (woluwe-saint-pierre)",
    "sg:classifiers":[
        {
            "category":"Professional",
            "subcategory":"Accounting & Tax Preparation",
            "type":"Services"
        }
    ],
    "sg:phone":"+32 2 772 19 71",
    "sg:postcode":"1150",
    "sg:province":"Bruxelles-Capitale",
    "sg:tags":[
        "accountant"
    ],
    "wof:name":"Druart P",
    "wof:placetype":"venue"
},
  "geometry": {"coordinates":[4.4492459297,50.8376846313],"type":"Point"}
}