{
  "type": "Feature",
  "properties": {
    "iso:country":"BE",
    "sg:address":"Place Lodewijckx 5",
    "sg:city":"Jodoigne",
    "sg:orig_category":"Fietsen Motorfietsen",
    "sg:phone":"+32 10 81 13 15",
    "sg:postcode":"1370",
    "sg:province":"Brabant Wallon",
    "wof:name":"La Maison Du Velo",
    "wof:placetype":"venue"
},
  "geometry": {"coordinates":[4.8679351807,50.7248001099],"type":"Point"}
}