{
  "type": "Feature",
  "properties": {
    "iso:country":"BE",
    "sg:address":"Sint-jobsesteenweg 594",
    "sg:city":"Ukkel/uccle",
    "sg:orig_category":"Warenhuizen",
    "sg:phone":"+32 2 374 69 09",
    "sg:postcode":"1180",
    "sg:province":"Bruxelles-Capitale",
    "wof:name":"Hobby-center Multibois",
    "wof:placetype":"venue"
},
  "geometry": {"coordinates":[4.3616328239,50.7931175232],"type":"Point"}
}