{
  "type": "Feature",
  "properties": {
    "addr:full":"Rondplein 7 Brakel (nederbrakel) Oost-Vlaanderen 9660",
    "addr:housenumber":"7",
    "addr:postcode":"9660",
    "addr:street":"Rondplein",
    "iso:country":"BE",
    "sg:address":"Rondplein 7",
    "sg:city":"Brakel (nederbrakel)",
    "sg:classifiers":[
        {
            "category":"Retail",
            "subcategory":"Auto Repair",
            "type":"Services"
        }
    ],
    "sg:phone":"+32 55 42 32 31",
    "sg:postcode":"9660",
    "sg:province":"Oost-Vlaanderen",
    "sg:tags":[
        "garage"
    ],
    "wof:name":"Van Der Linden",
    "wof:placetype":"venue"
},
  "geometry": {"coordinates":[3.7589130402,50.7985076904],"type":"Point"}
}