{
  "type": "Feature",
  "properties": {
    "addr:full":"Avenue Sluysmans 2 Li\u00e8ge 1 (grivegn\u00e9e) Li\u00e8ge 4030",
    "addr:housenumber":"2;1",
    "addr:postcode":"4030",
    "addr:street":"Avenue Sluysmans",
    "iso:country":"BE",
    "sg:address":"Avenue Sluysmans 2",
    "sg:city":"Li\u00e8ge 1 (grivegn\u00e9e)",
    "sg:classifiers":[
        {
            "category":"Shopping",
            "type":"Retail Goods"
        }
    ],
    "sg:phone":"+32 4 344 35 39",
    "sg:postcode":"4030",
    "sg:province":"Li\u00e8ge",
    "sg:tags":[
        "product",
        "cleaning",
        "maintenance"
    ],
    "wof:name":"S.l.d. 2000",
    "wof:placetype":"venue"
},
  "geometry": {"coordinates":[5.6003580093,50.6241493225],"type":"Point"}
}