{
  "type": "Feature",
  "properties": {
    "iso:country":"BE",
    "sg:address":"Rue Haie Du Loup 14",
    "sg:city":"Namur (gelbress\u00e9e)",
    "sg:classifiers":[
        {
            "category":"Home & Garden",
            "subcategory":"Carpets & Floor Coverings",
            "type":"Retail Goods"
        }
    ],
    "sg:phone":"+32 476 21 30 31",
    "sg:postcode":"5024",
    "sg:province":"Namur",
    "sg:tags":[
        "layer",
        "mosaicists"
    ],
    "wof:name":"Vg Bat",
    "wof:placetype":"venue"
},
  "geometry": {"coordinates":[4.9740638733,50.4963531494],"type":"Point"}
}