{
  "type": "Feature",
  "properties": {
    "iso:country":"BE",
    "sg:address":"Regn\u00c9 14",
    "sg:city":"Vielsalm",
    "sg:orig_category":"Eleveurs de bovins",
    "sg:phone":"+32 80 41 88 79",
    "sg:postcode":"6690",
    "sg:province":"Luxembourg",
    "wof:name":"Maurice Boulange",
    "wof:placetype":"venue"
},
  "geometry": {"coordinates":[5.7855319977,50.2552642822],"type":"Point"}
}