{
  "type": "Feature",
  "properties": {
    "addr:full":"Rue Des Forges 74 Aiseau-presles (aiseau) Hainaut 6250",
    "addr:housenumber":"74",
    "addr:postcode":"6250",
    "addr:street":"Rue Des Forges",
    "iso:country":"BE",
    "sg:address":"Rue Des Forges 74",
    "sg:city":"Aiseau-presles (aiseau)",
    "sg:classifiers":[
        {
            "category":"Farming",
            "subcategory":"Fish & Marine Products",
            "type":"Manufacturing & Wholesale Goods"
        }
    ],
    "sg:phone":"+32 71 74 13 12",
    "sg:postcode":"6250",
    "sg:province":"Hainaut",
    "sg:tags":[
        "equipment",
        "fishery"
    ],
    "wof:name":"Etangs Des Forges Sprl",
    "wof:placetype":"venue"
},
  "geometry": {"coordinates":[4.5846757889,50.4049835205],"type":"Point"}
}