{
  "type": "Feature",
  "properties": {
    "addr:full":"Puursesteenweg 363 Bornem Antwerpen 2880",
    "addr:housenumber":"363",
    "addr:postcode":"2880",
    "addr:street":"Puursesteenweg",
    "iso:country":"BE",
    "sg:address":"Puursesteenweg 363",
    "sg:city":"Bornem",
    "sg:classifiers":[
        {
            "category":"Military Area",
            "subcategory":"Air Force Base",
            "type":"Public Place"
        }
    ],
    "sg:phone":"+32 3 899 40 40",
    "sg:postcode":"2880",
    "sg:province":"Antwerpen",
    "sg:tags":[
        "electrical",
        "component",
        "electronic"
    ],
    "wof:name":"Plastic Color Nv",
    "wof:placetype":"venue"
},
  "geometry": {"coordinates":[4.2611460686,51.0858421326],"type":"Point"}
}