{
  "type": "Feature",
  "properties": {
    "iso:country":"BE",
    "sg:address":"Pacificatiestraat 56",
    "sg:city":"Antwerpen",
    "sg:classifiers":[
        {
            "category":"Professional",
            "subcategory":"Art Services",
            "type":"Services"
        }
    ],
    "sg:phone":"+32 3 248 30 78",
    "sg:postcode":"2000",
    "sg:province":"Antwerpen",
    "sg:tags":[
        "interior",
        "designer"
    ],
    "wof:name":"Corman C",
    "wof:placetype":"venue"
},
  "geometry": {"coordinates":[4.3914031982,51.2059860229],"type":"Point"}
}