{
  "type": "Feature",
  "properties": {
    "addr:full":"Pekelharing 35-37 Gent Oost-Vlaanderen 9000",
    "addr:housenumber":"35-37",
    "addr:postcode":"9000",
    "addr:street":"Oost-Vlaanderen",
    "iso:country":"BE",
    "sg:address":"Pekelharing 35-37",
    "sg:city":"Gent",
    "sg:classifiers":[
        {
            "category":"Manufacturing",
            "subcategory":"Chemicals & Compounds",
            "type":"Manufacturing & Wholesale Goods"
        }
    ],
    "sg:phone":"+32 9 225 37 51",
    "sg:postcode":"9000",
    "sg:province":"Oost-Vlaanderen",
    "sg:tags":[
        "pharmaceutical",
        "chemistry"
    ],
    "wof:name":"Geber-plastics Bvba",
    "wof:placetype":"venue"
},
  "geometry": {"coordinates":[3.718100071,51.048915863],"type":"Point"}
}