{
  "type": "Feature",
  "properties": {
    "iso:country":"BE",
    "sg:address":"Polletstraat 10",
    "sg:city":"Kortemark",
    "sg:orig_category":"Rundveehouders",
    "sg:phone":"+32 51 56 64 99",
    "sg:postcode":"8610",
    "sg:province":"West-Vlaanderen",
    "wof:name":"Gery Tyvaert",
    "wof:placetype":"venue"
},
  "geometry": {"coordinates":[3.0536739826,51.0482711792],"type":"Point"}
}