{
  "type": "Feature",
  "properties": {
    "iso:country":"BE",
    "sg:address":"Stationstraat 13",
    "sg:city":"Vloesberg/flobecq",
    "sg:orig_category":"Sportclubs Sportterreinen and installaties behalve sportcentra",
    "sg:phone":"+32 68 44 78 13",
    "sg:postcode":"7880",
    "sg:province":"Hainaut",
    "wof:name":"R.u.s. Flobecquoise",
    "wof:placetype":"venue"
},
  "geometry": {"coordinates":[3.7384300232,50.7368011475],"type":"Point"}
}