{
  "type": "Feature",
  "properties": {
    "addr:full":"Overbroekstraat 10 Wellen Limburg 3830",
    "addr:housenumber":"10",
    "addr:postcode":"3830",
    "addr:street":"Overbroekstraat",
    "iso:country":"BE",
    "sg:address":"Overbroekstraat 10",
    "sg:city":"Wellen",
    "sg:classifiers":[
        {
            "category":"Cinema",
            "subcategory":"Movie Rental",
            "type":"Entertainment"
        }
    ],
    "sg:phone":"+32 12 74 71 71",
    "sg:postcode":"3830",
    "sg:province":"Limburg",
    "sg:tags":[
        "de",
        "cassette",
        "location",
        "vid\u00e9o",
        "audio"
    ],
    "wof:name":"Bruno's Videoclub",
    "wof:placetype":"venue"
},
  "geometry": {"coordinates":[5.3217802048,50.8348617554],"type":"Point"}
}