{
  "type": "Feature",
  "properties": {
    "iso:country":"BE",
    "sg:address":"Kapenbergstraat 67",
    "sg:city":"Mortsel",
    "sg:classifiers":[
        {
            "category":"Education",
            "subcategory":"University",
            "type":"Public Place"
        }
    ],
    "sg:phone":"+32 3 454 18 95",
    "sg:postcode":"2640",
    "sg:province":"Antwerpen",
    "sg:tags":[
        "adult"
    ],
    "wof:name":"Spiegelpaleis",
    "wof:placetype":"venue"
},
  "geometry": {"coordinates":[4.4662599564,51.1639556885],"type":"Point"}
}