{
  "type": "Feature",
  "properties": {
    "iso:country":"BE",
    "sg:address":"Aarschotsebaan 81",
    "sg:city":"Kampenhout",
    "sg:orig_category":"Groententeelt",
    "sg:phone":"+32 16 65 51 84",
    "sg:postcode":"1910",
    "sg:province":"Vlaams-Brabant",
    "wof:name":"August Leaerts",
    "wof:placetype":"venue"
},
  "geometry": {"coordinates":[4.5837931633,50.9445075989],"type":"Point"}
}