{
  "type": "Feature",
  "properties": {
    "addr:full":"Avenue Charles Deli\u00c8ge 57 Binche Hainaut 7130",
    "addr:housenumber":"57",
    "addr:postcode":"7130",
    "addr:street":"Avenue Charles Delie\u0300Ge",
    "iso:country":"BE",
    "sg:address":"Avenue Charles Deli\u00c8ge 57",
    "sg:city":"Binche",
    "sg:classifiers":[
        {
            "category":"Cafe",
            "type":"Food & Drink"
        }
    ],
    "sg:phone":"+32 64 33 14 24",
    "sg:postcode":"7130",
    "sg:province":"Hainaut",
    "sg:tags":[
        "caf\u00e9s"
    ],
    "wof:name":"Caf\u00c9 L'excelsior",
    "wof:placetype":"venue"
},
  "geometry": {"coordinates":[4.166806221,50.4130172729],"type":"Point"}
}