{
  "type": "Feature",
  "properties": {
    "iso:country":"BE",
    "sg:address":"Mareydestraat 29",
    "sg:city":"Sint-pieters-woluwe/woluwe-saint-pierre",
    "sg:orig_category":"Diverse zakelijke dienstverlening",
    "sg:phone":"+32 2 772 26 19",
    "sg:postcode":"1150",
    "sg:province":"Bruxelles-Capitale",
    "wof:name":"Propel Seminar & Events",
    "wof:placetype":"venue"
},
  "geometry": {"coordinates":[4.4475989342,50.8313713074],"type":"Point"}
}