{
  "type": "Feature",
  "properties": {
    "iso:country":"BE",
    "sg:address":"Rue Robert Boisacq 9b2",
    "sg:city":"Rixensart",
    "sg:classifiers":[
        {
            "category":"Personal",
            "subcategory":"Beauty Salon",
            "type":"Services"
        }
    ],
    "sg:phone":"+32 2 653 03 13",
    "sg:postcode":"1330",
    "sg:province":"Brabant Wallon",
    "sg:tags":[
        "de",
        "coiffure"
    ],
    "wof:name":"Ondul'hair",
    "wof:placetype":"venue"
},
  "geometry": {"coordinates":[4.5303068161,50.7133865356],"type":"Point"}
}