{
  "type": "Feature",
  "properties": {
    "iso:country":"BE",
    "sg:address":"Malpertuusstraat 15",
    "sg:city":"Lommel",
    "sg:orig_category":"D\u00e9molition d\u00b4immeubles and terrassements",
    "sg:phone":"+32 11 66 18 33",
    "sg:postcode":"3920",
    "sg:province":"Limburg",
    "wof:name":"Joco",
    "wof:placetype":"venue"
},
  "geometry": {"coordinates":[5.3773570061,51.2415657043],"type":"Point"}
}