{
  "type": "Feature",
  "properties": {
    "addr:full":"Prins Boudewijnlaan 188 Edegem Antwerpen 2650",
    "addr:housenumber":"188",
    "addr:postcode":"2650",
    "addr:street":"Prins Boudewijnlaan",
    "iso:country":"BE",
    "sg:address":"Prins Boudewijnlaan 188",
    "sg:city":"Edegem",
    "sg:orig_category":"Plaatsen van vloer- and muurbekleding Schilders",
    "sg:phone":"+32 3 457 24 00",
    "sg:postcode":"2650",
    "sg:province":"Antwerpen",
    "wof:name":"Paul De Weert",
    "wof:placetype":"venue"
},
  "geometry": {"coordinates":[4.4341611862,51.151512146],"type":"Point"}
}