{
  "type": "Feature",
  "properties": {
    "addr:full":"Warandestraat 9 Nevele Oost-Vlaanderen 9850",
    "addr:housenumber":"9",
    "addr:postcode":"9850",
    "addr:street":"Warandestraat",
    "iso:country":"BE",
    "sg:address":"Warandestraat 9",
    "sg:city":"Nevele",
    "sg:orig_category":"Eleveurs de bovins",
    "sg:phone":"+32 9 371 54 12",
    "sg:postcode":"9850",
    "sg:province":"Oost-Vlaanderen",
    "wof:name":"De Bousies",
    "wof:placetype":"venue"
},
  "geometry": {"coordinates":[3.5249819756,51.0834083557],"type":"Point"}
}