{
  "type": "Feature",
  "properties": {
    "iso:country":"BE",
    "sg:address":"March\u00c9-aux-l\u00c9gumes 15",
    "sg:city":"Arlon",
    "sg:orig_category":"V\u00eatements pour b\u00e9b\u00e9s and enfants",
    "sg:phone":"+32 63 22 47 53",
    "sg:postcode":"6700",
    "sg:province":"Luxembourg",
    "wof:name":"Les Aristomomes",
    "wof:placetype":"venue"
},
  "geometry": {"coordinates":[5.8130202293,49.6839790344],"type":"Point"}
}