{
  "type": "Feature",
  "properties": {
    "addr:full":"Liebiglaan 11 Schoten Antwerpen 2900",
    "addr:housenumber":"11",
    "addr:postcode":"2900",
    "addr:street":"Liebiglaan",
    "iso:country":"BE",
    "sg:address":"Liebiglaan 11",
    "sg:city":"Schoten",
    "sg:classifiers":[
        {
            "category":"Manufacturing",
            "subcategory":"Food",
            "type":"Manufacturing & Wholesale Goods"
        }
    ],
    "sg:phone":"+32 3 641 95 00",
    "sg:postcode":"2900",
    "sg:province":"Antwerpen",
    "sg:tags":[
        "industry",
        "-",
        "ingredient"
    ],
    "wof:name":"Robertet Savoury",
    "wof:placetype":"venue"
},
  "geometry": {"coordinates":[4.4817800522,51.2430763245],"type":"Point"}
}