{
  "type": "Feature",
  "properties": {
    "addr:full":"Rue F\u00c9licien Mosray 7 Wavre Brabant Wallon 1300",
    "addr:housenumber":"7;1300",
    "addr:street":"Rue Fe\u0301Licien Mosray",
    "iso:country":"BE",
    "sg:address":"Rue F\u00c9licien Mosray 7",
    "sg:city":"Wavre",
    "sg:orig_category":"M\u00e9decins and sp\u00e9cialistes",
    "sg:phone":"+32 10 41 64 74",
    "sg:postcode":"1300",
    "sg:province":"Brabant Wallon",
    "wof:name":"Y. Sibille",
    "wof:placetype":"venue"
},
  "geometry": {"coordinates":[4.6116552353,50.7134132385],"type":"Point"}
}