{
  "type": "Feature",
  "properties": {
    "addr:full":"Brouwersstraat 6 Leuven Vlaams-Brabant 3000",
    "addr:housenumber":"6",
    "addr:postcode":"3000",
    "addr:street":"Brouwersstraat",
    "iso:country":"BE",
    "sg:address":"Brouwersstraat 6",
    "sg:city":"Leuven",
    "sg:orig_category":"Ramassage and traitement des d\u00e9chets m\u00e9nagers. Services publics",
    "sg:phone":"+32 16 23 58 36",
    "sg:postcode":"3000",
    "sg:province":"Vlaams-Brabant",
    "wof:name":"Interleuven",
    "wof:placetype":"venue"
},
  "geometry": {"coordinates":[4.6958360672,50.8827896118],"type":"Point"}
}