{
  "type": "Feature",
  "properties": {
    "iso:country":"BE",
    "sg:address":"Smidsestraat 9",
    "sg:city":"Dendermonde",
    "sg:orig_category":"Verplichte sociale verzekeringen",
    "sg:phone":"+32 52 21 49 08",
    "sg:postcode":"9200",
    "sg:province":"Oost-Vlaanderen",
    "wof:name":"Kristelijk Ziekenfonds",
    "wof:placetype":"venue"
},
  "geometry": {"coordinates":[4.0983099937,51.0315208435],"type":"Point"}
}