{
  "type": "Feature",
  "properties": {
    "addr:full":"Gentsesteenweg 174-176 Kortrijk West-Vlaanderen 8500",
    "addr:housenumber":"174-176",
    "addr:postcode":"8500",
    "addr:street":"Gentsesteenweg",
    "iso:country":"BE",
    "sg:address":"Gentsesteenweg 174-176",
    "sg:city":"Kortrijk",
    "sg:classifiers":[
        {
            "category":"Shopping",
            "type":"Retail Goods"
        }
    ],
    "sg:phone":"+32 56 21 12 81",
    "sg:postcode":"8500",
    "sg:province":"West-Vlaanderen",
    "sg:tags":[
        "metallurgy",
        "finished",
        "-",
        "metalworking",
        "metallic"
    ],
    "wof:name":"Industrim Nv",
    "wof:placetype":"venue"
},
  "geometry": {"coordinates":[3.2820959091,50.8362045288],"type":"Point"}
}