{
  "type": "Feature",
  "properties": {
    "addr:full":"Rue For\u00cat De Meerdael 10 Beauvechain Brabant Wallon 1320",
    "addr:housenumber":"10",
    "addr:postcode":"1320",
    "addr:street":"Rue Fore\u0302T De Meerdael",
    "iso:country":"BE",
    "sg:address":"Rue For\u00cat De Meerdael 10",
    "sg:city":"Beauvechain",
    "sg:classifiers":[
        {
            "category":"Insurance",
            "subcategory":"Life Insurance",
            "type":"Services"
        }
    ],
    "sg:phone":"+32 10 86 01 21",
    "sg:postcode":"1320",
    "sg:province":"Brabant Wallon",
    "sg:tags":[
        "assurance"
    ],
    "wof:name":"Ibis 4",
    "wof:placetype":"venue"
},
  "geometry": {"coordinates":[4.7126169205,50.7774963379],"type":"Point"}
}