{
  "type": "Feature",
  "properties": {
    "iso:country":"BE",
    "sg:address":"Quai Dautrebande 1b1",
    "sg:city":"Huy",
    "sg:classifiers":[
        {
            "category":"Fast Food",
            "type":"Food & Drink"
        }
    ],
    "sg:phone":"+32 85 21 41 88",
    "sg:postcode":"4500",
    "sg:province":"Li\u00e8ge",
    "sg:tags":[
        "\u00c0",
        "restaurants",
        "emporter",
        "restaurant"
    ],
    "wof:name":"Le Sorgho Rouge",
    "wof:placetype":"venue"
},
  "geometry": {"coordinates":[5.2386617661,50.5197563171],"type":"Point"}
}