{
  "type": "Feature",
  "properties": {
    "iso:country":"BE",
    "sg:address":"Kortemunt 1",
    "sg:city":"Nevele",
    "sg:classifiers":[
        {
            "category":"Shopping",
            "subcategory":"Optician",
            "type":"Retail Goods"
        }
    ],
    "sg:phone":"+32 9 371 77 70",
    "sg:postcode":"9850",
    "sg:province":"Oost-Vlaanderen",
    "sg:tags":[
        "-"
    ],
    "wof:name":"Taghon",
    "wof:placetype":"venue"
},
  "geometry": {"coordinates":[3.549916029,51.0327033997],"type":"Point"}
}