{
  "type": "Feature",
  "properties": {
    "iso:country":"BE",
    "sg:address":"Limburgstraat 58",
    "sg:city":"Gent",
    "sg:classifiers":[
        {
            "category":"Professional",
            "subcategory":"Art Services",
            "type":"Services"
        }
    ],
    "sg:phone":"+32 9 234 00 73",
    "sg:postcode":"9000",
    "sg:province":"Oost-Vlaanderen",
    "sg:tags":[
        "picture",
        "framer"
    ],
    "wof:name":"J&c Segers Atelier",
    "wof:placetype":"venue"
},
  "geometry": {"coordinates":[3.7275559902,51.0521430969],"type":"Point"}
}