{
  "type": "Feature",
  "properties": {
    "addr:full":"Lokerenstraat 72 Turnhout Antwerpen 2300",
    "addr:housenumber":"72",
    "addr:postcode":"2300",
    "addr:street":"Lokerenstraat",
    "iso:country":"BE",
    "sg:address":"Lokerenstraat 72",
    "sg:city":"Turnhout",
    "sg:orig_category":"Schoenen",
    "sg:phone":"+32 14 42 50 57",
    "sg:postcode":"2300",
    "sg:province":"Antwerpen",
    "wof:name":"Godelieve Hendrickx",
    "wof:placetype":"venue"
},
  "geometry": {"coordinates":[4.9273629189,51.3178405762],"type":"Point"}
}