{
  "type": "Feature",
  "properties": {
    "addr:full":"Staatsbaan 140a Bekkevoort 3260",
    "addr:housenumber":"140a",
    "addr:postcode":"3260",
    "addr:street":"Staatsbaan",
    "iso:country":"BE",
    "sg:address":"Staatsbaan 140a",
    "sg:city":"Bekkevoort",
    "sg:classifiers":[
        {
            "category":"Banks & Credit Unions",
            "subcategory":"Bank",
            "type":"Services"
        }
    ],
    "sg:phone":"+32 13 33 69 29",
    "sg:postcode":"3260",
    "wof:name":"Gemeentekrediet",
    "wof:placetype":"venue"
},
  "geometry": {"coordinates":[4.975230217,50.9448394775],"type":"Point"}
}