{
  "type": "Feature",
  "properties": {
    "iso:country":"BE",
    "sg:address":"Lostraat 1",
    "sg:city":"Aalter",
    "sg:orig_category":"Dameskledingzaken",
    "sg:phone":"+32 9 374 12 88",
    "sg:postcode":"9880",
    "sg:province":"Oost-Vlaanderen",
    "wof:name":"Kleding Pluba",
    "wof:placetype":"venue"
},
  "geometry": {"coordinates":[3.4492800236,51.083568573],"type":"Point"}
}