{
  "type": "Feature",
  "properties": {
    "addr:full":"Bochtenstraat 33 Laarne Oost-Vlaanderen 9270",
    "addr:housenumber":"33",
    "addr:postcode":"9270",
    "addr:street":"Bochtenstraat",
    "iso:country":"BE",
    "sg:address":"Bochtenstraat 33",
    "sg:city":"Laarne",
    "sg:orig_category":"Installation de menuiserie m\u00e9tallique",
    "sg:phone":"+32 9 369 59 27",
    "sg:postcode":"9270",
    "sg:province":"Oost-Vlaanderen",
    "wof:name":"Christiaens Techniek",
    "wof:placetype":"venue"
},
  "geometry": {"coordinates":[3.8594100475,51.0327987671],"type":"Point"}
}