{
  "type": "Feature",
  "properties": {
    "addr:full":"Frankrijkstraat 92 Moeskroen/mouscron Hainaut 7711",
    "addr:housenumber":"92",
    "addr:postcode":"7711",
    "addr:street":"Frankrijkstraat",
    "iso:country":"BE",
    "sg:address":"Frankrijkstraat 92",
    "sg:city":"Moeskroen/mouscron",
    "sg:orig_category":"Plaatsen van vloer- and muurbekleding Schilders",
    "sg:phone":"+32 56 48 96 07",
    "sg:postcode":"7711",
    "sg:province":"Hainaut",
    "wof:name":"Alex Carrette",
    "wof:placetype":"venue"
},
  "geometry": {"coordinates":[3.2979030609,50.7254295349],"type":"Point"}
}