{
  "type": "Feature",
  "properties": {
    "iso:country":"BE",
    "sg:address":"Calvariestraat 53",
    "sg:city":"Genk",
    "sg:orig_category":"V\u00eatements pour b\u00e9b\u00e9s and enfants",
    "sg:phone":"+32 89 35 50 26",
    "sg:postcode":"3600",
    "sg:province":"Limburg",
    "wof:name":"Huis Billy'o",
    "wof:placetype":"venue"
},
  "geometry": {"coordinates":[5.4870109558,50.9626083374],"type":"Point"}
}