{
  "type": "Feature",
  "properties": {
    "iso:country":"BE",
    "sg:address":"Manaihant 10",
    "sg:city":"Herve (battice)",
    "sg:classifiers":[
        {
            "category":"Shopping",
            "subcategory":"Stationery & Office Supplies",
            "type":"Retail Goods"
        }
    ],
    "sg:phone":"+32 87 67 88 93",
    "sg:postcode":"4651",
    "sg:province":"Li\u00e8ge",
    "sg:tags":[
        "partition"
    ],
    "wof:name":"Sequoia",
    "wof:placetype":"venue"
},
  "geometry": {"coordinates":[5.8163299561,50.6241493225],"type":"Point"}
}