{
  "type": "Feature",
  "properties": {
    "addr:full":"Avenue De La Gare 48 Neufch\u00e2teau Luxembourg 6840",
    "addr:housenumber":"48",
    "addr:postcode":"6840",
    "addr:street":"Avenue De La Gare",
    "iso:country":"BE",
    "sg:address":"Avenue De La Gare 48",
    "sg:city":"Neufch\u00e2teau",
    "sg:classifiers":[
        {
            "category":"Health Services",
            "subcategory":"Dentist",
            "type":"Services"
        }
    ],
    "sg:phone":"+32 61 27 81 85",
    "sg:postcode":"6840",
    "sg:province":"Luxembourg",
    "wof:name":"Parisse Jean-claude",
    "wof:placetype":"venue"
},
  "geometry": {"coordinates":[5.4402241707,49.8453330994],"type":"Point"}
}