{
  "type": "Feature",
  "properties": {
    "iso:country":"BE",
    "sg:address":"Poeldendries 32",
    "sg:city":"Nevele",
    "sg:orig_category":"Algemeen secundair onderwijs Kleuter- en basisonderwijs",
    "sg:phone":"+32 9 371 60 66",
    "sg:postcode":"9850",
    "sg:province":"Oost-Vlaanderen",
    "wof:name":"Bubao Ten Dries",
    "wof:placetype":"venue"
},
  "geometry": {"coordinates":[3.5792069435,51.0599594116],"type":"Point"}
}