{
  "type": "Feature",
  "properties": {
    "addr:full":"Rue Caporal Tr\u00e9signies 6 Bruxelles Bruxelles-Capitale 1190",
    "addr:housenumber":"6",
    "addr:postcode":"1190",
    "addr:street":"Rue Caporal Tre\u0301Signies",
    "iso:country":"BE",
    "sg:address":"Rue Caporal Tr\u00e9signies 6",
    "sg:city":"Bruxelles",
    "sg:classifiers":[
        {
            "category":"Building & Trades",
            "subcategory":"Construction",
            "type":"Services"
        }
    ],
    "sg:phone":"+32 2 332 09 02",
    "sg:postcode":"1190",
    "sg:province":"Bruxelles-Capitale",
    "sg:tags":[
        "assembly",
        "customized",
        "machine",
        "equipment",
        "electronics",
        "jointing"
    ],
    "wof:name":"Dvc S.a.",
    "wof:placetype":"venue"
},
  "geometry": {"coordinates":[4.3155388832,50.8090667725],"type":"Point"}
}