{
  "type": "Feature",
  "properties": {
    "iso:country":"BE",
    "sg:address":"Chauss\u00e9e De Bruxelles 62a",
    "sg:city":"Mons",
    "sg:classifiers":[
        {
            "category":"Home & Garden",
            "subcategory":"Carpets & Floor Coverings",
            "type":"Retail Goods"
        }
    ],
    "sg:phone":"+32 65 33 85 74",
    "sg:postcode":"7000",
    "sg:province":"Hainaut",
    "sg:tags":[
        "tile"
    ],
    "wof:name":"Clirrame Sa",
    "wof:placetype":"venue"
},
  "geometry": {"coordinates":[3.9578518867,50.4663505554],"type":"Point"}
}