{
  "type": "Feature",
  "properties": {
    "addr:full":"Rue Henri-vieuxtemps 98 Li\u00c8ge Li\u00e8ge 4000",
    "addr:housenumber":"98",
    "addr:postcode":"4000",
    "addr:street":"Rue Henri-Vieuxtemps",
    "iso:country":"BE",
    "sg:address":"Rue Henri-vieuxtemps 98",
    "sg:city":"Li\u00c8ge",
    "sg:orig_category":"Artistes ind\u00e9pendants",
    "sg:phone":"+32 4 226 06 20",
    "sg:postcode":"4000",
    "sg:province":"Li\u00e8ge",
    "wof:name":"Philippe Leclercq",
    "wof:placetype":"venue"
},
  "geometry": {"coordinates":[5.5602798462,50.6476211548],"type":"Point"}
}