{
  "type": "Feature",
  "properties": {
    "addr:full":"Tiensesteenweg 24 Sint-truiden Limburg 3800",
    "addr:housenumber":"24",
    "addr:postcode":"3800",
    "addr:street":"Tiensesteenweg",
    "iso:country":"BE",
    "sg:address":"Tiensesteenweg 24",
    "sg:city":"Sint-truiden",
    "sg:orig_category":"Banques and organismes de cr\u00e9dit",
    "sg:phone":"+32 11 68 59 63",
    "sg:postcode":"3800",
    "sg:province":"Limburg",
    "wof:name":"Fortis",
    "wof:placetype":"venue"
},
  "geometry": {"coordinates":[5.179913044,50.8152160645],"type":"Point"}
}