{
  "type": "Feature",
  "properties": {
    "addr:full":"Rue Du Witloof 111 Bruxelles Bruxelles-Capitale 1130",
    "addr:housenumber":"111",
    "addr:postcode":"1130",
    "addr:street":"Rue Du Witloof",
    "iso:country":"BE",
    "sg:address":"Rue Du Witloof 111",
    "sg:city":"Bruxelles",
    "sg:classifiers":[
        {
            "category":"Utilities",
            "subcategory":"Natural Gas",
            "type":"Services"
        }
    ],
    "sg:phone":"+32 2 215 18 25",
    "sg:postcode":"1130",
    "sg:province":"Bruxelles-Capitale",
    "sg:tags":[
        "industrial",
        "heating"
    ],
    "wof:name":"Stordy Combustion Engineering",
    "wof:placetype":"venue"
},
  "geometry": {"coordinates":[4.4237298965,50.9001464844],"type":"Point"}
}