{
  "type": "Feature",
  "properties": {
    "iso:country":"BE",
    "sg:address":"Rue Du Cheval Blanc 39",
    "sg:city":"Herstal (liers)",
    "sg:classifiers":[
        {
            "category":"Professional",
            "subcategory":"Art Services",
            "type":"Services"
        }
    ],
    "sg:phone":"+32 4 278 64 70",
    "sg:postcode":"4042",
    "sg:province":"Li\u00e8ge",
    "sg:tags":[
        "photography",
        "reporting",
        "-"
    ],
    "wof:name":"Roman F",
    "wof:placetype":"venue"
},
  "geometry": {"coordinates":[5.5661010742,50.6869468689],"type":"Point"}
}