{
  "type": "Feature",
  "properties": {
    "addr:full":"Rue Martin-luther King 23 Gr\u00e2ce-hollogne (gr\u00e2ce-berleur) Li\u00e8ge 4460",
    "addr:housenumber":"23",
    "addr:postcode":"4460",
    "addr:street":"Rue Martin-Luther King;Gra\u0302Ce-Berleur",
    "iso:country":"BE",
    "sg:address":"Rue Martin-luther King 23",
    "sg:city":"Gr\u00e2ce-hollogne (gr\u00e2ce-berleur)",
    "sg:classifiers":[
        {
            "category":"Building & Trades",
            "subcategory":"Electrical",
            "type":"Services"
        }
    ],
    "sg:phone":"+32 4 235 97 92",
    "sg:postcode":"4460",
    "sg:province":"Li\u00e8ge",
    "sg:tags":[
        "-",
        "electric",
        "contractor"
    ],
    "wof:name":"Electr@tech",
    "wof:placetype":"venue"
},
  "geometry": {"coordinates":[5.5009870529,50.6356887817],"type":"Point"}
}