{
  "type": "Feature",
  "properties": {
    "iso:country":"BE",
    "sg:address":"Lindenstraat 36",
    "sg:city":"Keerbergen",
    "sg:orig_category":"Industri\u00eble wasserijen and droogkuis",
    "sg:phone":"+32 15 51 72 92",
    "sg:postcode":"3140",
    "sg:province":"Vlaams-Brabant",
    "wof:name":"Wassalon Wagner",
    "wof:placetype":"venue"
},
  "geometry": {"coordinates":[4.6333489418,51.001789093],"type":"Point"}
}