{
  "type": "Feature",
  "properties": {
    "iso:country":"BE",
    "sg:address":"Excelsiorlaan 20",
    "sg:city":"Zaventem",
    "sg:orig_category":"Autoverhuur",
    "sg:phone":"+32 2 716 92 30",
    "sg:postcode":"1930",
    "sg:province":"Vlaams-Brabant",
    "wof:name":"Hertz",
    "wof:placetype":"venue"
},
  "geometry": {"coordinates":[4.4572439194,50.8851165771],"type":"Point"}
}