{
  "type": "Feature",
  "properties": {
    "iso:country":"BE",
    "sg:address":"Donderheide 3",
    "sg:city":"Lier (koningshooikt)",
    "sg:classifiers":[
        {
            "category":"Bars & Pubs",
            "type":"Food & Drink"
        }
    ],
    "sg:phone":"+32 15 32 12 39",
    "sg:postcode":"2500",
    "sg:province":"Antwerpen",
    "sg:tags":[
        "tavern"
    ],
    "wof:name":"Het Fort",
    "wof:placetype":"venue"
},
  "geometry": {"coordinates":[4.5676631927,51.0847511292],"type":"Point"}
}