{
  "type": "Feature",
  "properties": {
    "addr:full":"Chauss\u00e9e De Tongres 452 Li\u00e8ge 1 (rocourt) Li\u00e8ge 4000",
    "addr:housenumber":"452;1",
    "addr:postcode":"4000",
    "addr:street":"Chausse\u0301E De Tongres",
    "iso:country":"BE",
    "sg:address":"Chauss\u00e9e De Tongres 452",
    "sg:city":"Li\u00e8ge 1 (rocourt)",
    "sg:classifiers":[
        {
            "category":"Personal",
            "subcategory":"Tattoo Parlor",
            "type":"Services"
        }
    ],
    "sg:phone":"+32 4 247 52 22",
    "sg:postcode":"4000",
    "sg:province":"Li\u00e8ge",
    "sg:tags":[
        "tattooists"
    ],
    "wof:name":"Graffiti Studio",
    "wof:placetype":"venue"
},
  "geometry": {"coordinates":[5.5456337929,50.6767807007],"type":"Point"}
}