{
  "type": "Feature",
  "properties": {
    "addr:full":"Moli\u00c8relaan 296 Ukkel/uccle Bruxelles-Capitale 1180",
    "addr:housenumber":"296",
    "addr:postcode":"1180",
    "addr:street":"Molie\u0300Relaan;/",
    "iso:country":"BE",
    "sg:address":"Moli\u00c8relaan 296",
    "sg:city":"Ukkel/uccle",
    "sg:orig_category":"Dierenartsen",
    "sg:phone":"+32 2 344 84 15",
    "sg:postcode":"1180",
    "sg:province":"Bruxelles-Capitale",
    "wof:name":"Serge Garreyn",
    "wof:placetype":"venue"
},
  "geometry": {"coordinates":[4.3622097969,50.8159332275],"type":"Point"}
}