{
  "type": "Feature",
  "properties": {
    "iso:country":"BE",
    "sg:address":"Lutlommel 158",
    "sg:city":"Lommel",
    "sg:orig_category":"V\u00e9los",
    "sg:phone":"+32 11 54 62 63",
    "sg:postcode":"3920",
    "sg:province":"Limburg",
    "wof:name":"Fietsen Bleyen",
    "wof:placetype":"venue"
},
  "geometry": {"coordinates":[5.348511219,51.2320556641],"type":"Point"}
}