{
  "type": "Feature",
  "properties": {
    "iso:country":"BE",
    "sg:address":"Ruitersweg 76",
    "sg:city":"Kuurne",
    "sg:orig_category":"Belastingconsulenten Diverse juridische dienstverlening",
    "sg:phone":"+32 56 37 13 51",
    "sg:postcode":"8520",
    "sg:province":"West-Vlaanderen",
    "wof:name":"Gevimar",
    "wof:placetype":"venue"
},
  "geometry": {"coordinates":[3.2720890045,50.8566894531],"type":"Point"}
}