{
  "type": "Feature",
  "properties": {
    "iso:country":"BE",
    "sg:address":"Colomastraat 47",
    "sg:city":"Mechelen",
    "sg:orig_category":"Non-Classified Establishments",
    "sg:phone":"+32 15 43 12 91",
    "sg:postcode":"2800",
    "sg:province":"Antwerpen",
    "wof:name":"Baerlocher Benelux Nv",
    "wof:placetype":"venue"
},
  "geometry": {"coordinates":[4.4805951118,51.0189857483],"type":"Point"}
}