{
  "type": "Feature",
  "properties": {
    "iso:country":"BE",
    "sg:address":"Kermtstraat 155",
    "sg:city":"Hasselt",
    "sg:orig_category":"Woningbouw",
    "sg:phone":"+32 11 31 65 94",
    "sg:postcode":"3512",
    "sg:province":"Limburg",
    "wof:name":"Ronny Vangeel",
    "wof:placetype":"venue"
},
  "geometry": {"coordinates":[5.2505412102,50.9325027466],"type":"Point"}
}