{
  "type": "Feature",
  "properties": {
    "addr:full":"Koningin Fabiolapark 383 Sint-niklaas Oost-Vlaanderen 9100",
    "addr:housenumber":"383",
    "addr:postcode":"9100",
    "addr:street":"Koningin Fabiolapark",
    "iso:country":"BE",
    "sg:address":"Koningin Fabiolapark 383",
    "sg:city":"Sint-niklaas",
    "sg:classifiers":[
        {
            "category":"Professional",
            "type":"Services"
        }
    ],
    "sg:phone":"+32 3 777 66 24",
    "sg:postcode":"9100",
    "sg:province":"Oost-Vlaanderen",
    "sg:tags":[
        "ceremony",
        "master"
    ],
    "wof:name":"Van Bogaert D",
    "wof:placetype":"venue"
},
  "geometry": {"coordinates":[4.1575651169,51.1544494629],"type":"Point"}
}