{
  "type": "Feature",
  "properties": {
    "addr:full":"Groendreef 225 Gent Oost-Vlaanderen 9000",
    "addr:housenumber":"225",
    "addr:postcode":"9000",
    "addr:street":"Groendreef;Oost-Vlaanderen",
    "iso:country":"BE",
    "sg:address":"Groendreef 225",
    "sg:city":"Gent",
    "sg:classifiers":[
        {
            "category":"Building & Trades",
            "subcategory":"Construction",
            "type":"Services"
        }
    ],
    "sg:phone":"+32 9 236 56 31",
    "sg:postcode":"9000",
    "sg:province":"Oost-Vlaanderen",
    "sg:tags":[
        "work",
        "waterproofing"
    ],
    "wof:name":"Durieux Bvba",
    "wof:placetype":"venue"
},
  "geometry": {"coordinates":[3.6934709549,51.0692901611],"type":"Point"}
}