{
  "type": "Feature",
  "properties": {
    "addr:full":"Place Du 12\u00c8me De Ligne 6 Herstal Li\u00e8ge 4040",
    "addr:housenumber":"6",
    "addr:postcode":"4040",
    "addr:street":"Place Du 12E\u0300Me De Ligne",
    "iso:country":"BE",
    "sg:address":"Place Du 12\u00c8me De Ligne 6",
    "sg:city":"Herstal",
    "sg:orig_category":"Immobili\u00ebnkantoren Projectontwikkelaars",
    "sg:phone":"+32 4 240 08 04",
    "sg:postcode":"4040",
    "sg:province":"Li\u00e8ge",
    "wof:name":"Joly-home",
    "wof:placetype":"venue"
},
  "geometry": {"coordinates":[5.640581131,50.6734848022],"type":"Point"}
}