{
  "type": "Feature",
  "properties": {
    "addr:full":"Jaune Voie 67 Namur Namur 5100",
    "addr:housenumber":"67",
    "addr:postcode":"5100",
    "addr:street":"Voie",
    "iso:country":"BE",
    "sg:address":"Jaune Voie 67",
    "sg:city":"Namur",
    "sg:orig_category":"Parfumeries",
    "sg:phone":"+32 81 46 12 98",
    "sg:postcode":"5100",
    "sg:province":"Namur",
    "wof:name":"Martine Fasbender",
    "wof:placetype":"venue"
},
  "geometry": {"coordinates":[4.8653459549,50.4132270813],"type":"Point"}
}