{
  "type": "Feature",
  "properties": {
    "iso:country":"BE",
    "sg:address":"Moeskroenstraat 786",
    "sg:city":"Menen",
    "sg:orig_category":"Installatie van houten of kunststof schrijnwerk",
    "sg:phone":"+32 56 41 09 20",
    "sg:postcode":"8930",
    "sg:province":"West-Vlaanderen",
    "wof:name":"R Pype Lecointre",
    "wof:placetype":"venue"
},
  "geometry": {"coordinates":[3.1548678875,50.7887992859],"type":"Point"}
}