{
  "type": "Feature",
  "properties": {
    "addr:full":"Rue Maurice Duchene 52b Oth\u00e9e Li\u00e8ge 4340",
    "addr:housenumber":"52b",
    "addr:postcode":"4340",
    "addr:street":"Rue Maurice Duchene",
    "iso:country":"BE",
    "sg:address":"Rue Maurice Duchene 52b",
    "sg:city":"Oth\u00e9e",
    "sg:classifiers":[
        {
            "category":"Banks & Credit Unions",
            "subcategory":"Atm",
            "type":"Services"
        }
    ],
    "sg:phone":"+32 4 257 42 74",
    "sg:postcode":"4340",
    "sg:province":"Li\u00e8ge",
    "sg:tags":[
        "screed",
        "floor"
    ],
    "wof:name":"Leduc-malaise S.a.",
    "wof:placetype":"venue"
},
  "geometry": {"coordinates":[5.4653391838,50.7208442688],"type":"Point"}
}