{
  "type": "Feature",
  "properties": {
    "addr:full":"Ronseweg 15 Oudenaarde Oost-Vlaanderen 9700",
    "addr:housenumber":"15",
    "addr:postcode":"9700",
    "addr:street":"Ronseweg",
    "iso:country":"BE",
    "sg:address":"Ronseweg 15",
    "sg:city":"Oudenaarde",
    "sg:orig_category":"Entretien and r\u00e9parations de voitures. V\u00e9hicules automobiles",
    "sg:phone":"+32 55 31 91 96",
    "sg:postcode":"9700",
    "sg:province":"Oost-Vlaanderen",
    "wof:name":"Garage Cnockaert",
    "wof:placetype":"venue"
},
  "geometry": {"coordinates":[3.5994939804,50.8089752197],"type":"Point"}
}