{
  "type": "Feature",
  "properties": {
    "iso:country":"BE",
    "sg:address":"Rodekruisstraat 20",
    "sg:city":"Lommel",
    "sg:classifiers":[
        {
            "category":"Social Services",
            "subcategory":"Job Training",
            "type":"Services"
        }
    ],
    "sg:phone":"+32 11 66 75 96",
    "sg:postcode":"3920",
    "sg:province":"Limburg",
    "sg:tags":[
        "coordinator",
        "safety"
    ],
    "wof:name":"Ante",
    "wof:placetype":"venue"
},
  "geometry": {"coordinates":[5.3112611771,51.2293357849],"type":"Point"}
}