{
  "type": "Feature",
  "properties": {
    "addr:full":"Rue Des Combattants 2 Esneux Li\u00e8ge 4130",
    "addr:housenumber":"2",
    "addr:postcode":"4130",
    "addr:street":"Rue Des Combattants",
    "iso:country":"BE",
    "sg:address":"Rue Des Combattants 2",
    "sg:city":"Esneux",
    "sg:orig_category":"Sportclubs",
    "sg:phone":"+32 4 380 54 60",
    "sg:postcode":"4130",
    "sg:province":"Li\u00e8ge",
    "wof:name":"P.h.c. Ser\u00c9sien",
    "wof:placetype":"venue"
},
  "geometry": {"coordinates":[5.5685801506,50.5338897705],"type":"Point"}
}