{
  "type": "Feature",
  "properties": {
    "addr:full":"Rue Du Bosquet 2 Louvain-la-neuve Brabant Wallon 1348",
    "addr:housenumber":"2",
    "addr:postcode":"1348",
    "addr:street":"Rue Du Bosquet",
    "iso:country":"BE",
    "sg:address":"Rue Du Bosquet 2",
    "sg:city":"Louvain-la-neuve",
    "sg:classifiers":[
        {
            "category":"Health Services",
            "subcategory":"Medical Lab",
            "type":"Services"
        }
    ],
    "sg:phone":"+32 53 72 02 11",
    "sg:postcode":"1348",
    "sg:province":"Brabant Wallon",
    "sg:tags":[
        "product",
        "diagnostic"
    ],
    "wof:name":"Becton Dickinson Benelux Nv",
    "wof:placetype":"venue"
},
  "geometry": {"coordinates":[4.0553851128,50.9209976196],"type":"Point"}
}