{
  "type": "Feature",
  "properties": {
    "iso:country":"BE",
    "sg:address":"Maigre Cense 70ba",
    "sg:city":"Herve",
    "sg:orig_category":"Imprimeries and copyshops",
    "sg:phone":"+32 4 387 46 72",
    "sg:postcode":"4650",
    "sg:province":"Li\u00e8ge",
    "wof:name":"Agnes Lardinois",
    "wof:placetype":"venue"
},
  "geometry": {"coordinates":[5.7779188156,50.6923675537],"type":"Point"}
}