{
  "type": "Feature",
  "properties": {
    "addr:full":"Paardenmarkt 8 Antwerpen Antwerpen 2000",
    "addr:housenumber":"8",
    "addr:postcode":"2000",
    "addr:street":"Paardenmarkt",
    "iso:country":"BE",
    "sg:address":"Paardenmarkt 8",
    "sg:city":"Antwerpen",
    "sg:orig_category":"Diensten voor huisdieren Huisdieren and benodigdheden Royal Canin",
    "sg:phone":"+32 3 233 37 65",
    "sg:postcode":"2000",
    "sg:province":"Antwerpen",
    "wof:name":"De Pauw",
    "wof:placetype":"venue"
},
  "geometry": {"coordinates":[4.4077329636,51.2249221802],"type":"Point"}
}