{
  "type": "Feature",
  "properties": {
    "iso:country":"BE",
    "sg:address":"Brusselstraat 25",
    "sg:city":"Gooik",
    "sg:orig_category":"Meubelzaken, woning- and keukeninrichting",
    "sg:phone":"+32 2 532 49 46",
    "sg:postcode":"1755",
    "sg:province":"Vlaams-Brabant",
    "wof:name":"Heim Polle",
    "wof:placetype":"venue"
},
  "geometry": {"coordinates":[4.1311807632,50.7900543213],"type":"Point"}
}