{
  "type": "Feature",
  "properties": {
    "iso:country":"BE",
    "sg:address":"Chauss\u00c9e De Vleurgat 195",
    "sg:city":"Elsene/ixelles",
    "sg:orig_category":"Salons de coiffure. Instituts de beaut\u00e9",
    "sg:phone":"+32 2 644 61 44",
    "sg:postcode":"1050",
    "sg:province":"Bruxelles-Capitale",
    "wof:name":"Jean-claude Biguine",
    "wof:placetype":"venue"
},
  "geometry": {"coordinates":[4.366355896,50.8208618164],"type":"Point"}
}