{
  "type": "Feature",
  "properties": {
    "iso:country":"BE",
    "sg:address":"Oude Vaartstraat 31",
    "sg:city":"Ieper",
    "sg:classifiers":[
        {
            "category":"Health Services",
            "subcategory":"Nursing And Care Facility",
            "type":"Services"
        }
    ],
    "sg:phone":"+32 475 61 77 11",
    "sg:postcode":"8900",
    "sg:province":"West-Vlaanderen",
    "sg:tags":[
        "home"
    ],
    "wof:name":"Vervaeke Hilde Bvba",
    "wof:placetype":"venue"
},
  "geometry": {"coordinates":[2.8740100861,50.8509216309],"type":"Point"}
}