{
  "type": "Feature",
  "properties": {
    "addr:full":"Avenue Du Harnois 2 Evere Bruxelles-Capitale 1140",
    "addr:housenumber":"2",
    "addr:postcode":"1140",
    "addr:street":"Avenue Du Harnois",
    "iso:country":"BE",
    "sg:address":"Avenue Du Harnois 2",
    "sg:city":"Evere",
    "sg:classifiers":[
        {
            "category":"Cafe",
            "type":"Food & Drink"
        }
    ],
    "sg:phone":"+32 2 705 39 21",
    "sg:postcode":"1140",
    "sg:province":"Bruxelles-Capitale",
    "sg:tags":[
        "caf\u00e9s"
    ],
    "wof:name":"Betu Kalukumbi",
    "wof:placetype":"venue"
},
  "geometry": {"coordinates":[4.410449028,50.8593292236],"type":"Point"}
}