{
  "type": "Feature",
  "properties": {
    "iso:country":"BE",
    "sg:address":"Amelerstrasse 46",
    "sg:city":"Amel/ambleve",
    "sg:orig_category":"Rundveehouders",
    "sg:phone":"+32 80 34 01 30",
    "sg:postcode":"4770",
    "sg:province":"Li\u00e8ge",
    "wof:name":"Irene Mertes",
    "wof:placetype":"venue"
},
  "geometry": {"coordinates":[6.1238632202,50.3359794617],"type":"Point"}
}