{
  "type": "Feature",
  "properties": {
    "iso:country":"BE",
    "sg:address":"Avenue Emile Max 22",
    "sg:city":"Bruxelles (schaerbeek)",
    "sg:classifiers":[
        {
            "category":"Professional",
            "subcategory":"Art Services",
            "type":"Services"
        }
    ],
    "sg:phone":"+32 2 733 53 35",
    "sg:postcode":"1030",
    "sg:province":"Bruxelles-Capitale",
    "sg:tags":[
        "interior",
        "designer"
    ],
    "wof:name":"Pepin M",
    "wof:placetype":"venue"
},
  "geometry": {"coordinates":[4.3915328979,50.8497695923],"type":"Point"}
}