{
  "type": "Feature",
  "properties": {
    "addr:full":"Nieuwstraat 15 Torhout West-Vlaanderen 8820",
    "addr:housenumber":"15",
    "addr:postcode":"8820",
    "addr:street":"Nieuwstraat",
    "iso:country":"BE",
    "sg:address":"Nieuwstraat 15",
    "sg:city":"Torhout",
    "sg:orig_category":"Bagage and lederwaren Schoenen",
    "sg:phone":"+32 50 22 24 14",
    "sg:postcode":"8820",
    "sg:province":"West-Vlaanderen",
    "wof:name":"Huis Theas",
    "wof:placetype":"venue"
},
  "geometry": {"coordinates":[3.0999269485,51.0649604797],"type":"Point"}
}