{
  "type": "Feature",
  "properties": {
    "iso:country":"BE",
    "sg:address":"Pl Roi-albert-1er 21-23",
    "sg:city":"Rochefort",
    "sg:classifiers":[
        {
            "category":"Travel",
            "subcategory":"Hotels & Motels",
            "type":"Entertainment"
        }
    ],
    "sg:phone":"+32 84 21 10 36",
    "sg:postcode":"5580",
    "sg:province":"Namur",
    "sg:tags":[
        "hotels",
        "business",
        "restaurant"
    ],
    "wof:name":"H\u00d4tel Limbourg",
    "wof:placetype":"venue"
},
  "geometry": {"coordinates":[5.2231411934,50.1583595276],"type":"Point"}
}