{
  "type": "Feature",
  "properties": {
    "iso:country":"BE",
    "sg:address":"Tuinwijk 18",
    "sg:city":"Zulte",
    "sg:classifiers":[
        {
            "category":"Arena",
            "subcategory":"Sports Club",
            "type":"Entertainment"
        }
    ],
    "sg:phone":"+32 9 380 33 22",
    "sg:postcode":"9870",
    "sg:province":"Oost-Vlaanderen",
    "sg:tags":[
        "installation",
        "sportifs",
        "de",
        "terrain",
        "hors",
        "caf\u00e9s"
    ],
    "wof:name":"Fc Standard Deinze",
    "wof:placetype":"venue"
},
  "geometry": {"coordinates":[3.4923129082,50.9614295959],"type":"Point"}
}