{
  "type": "Feature",
  "properties": {
    "addr:full":"Rue Canal 37 Wanze Li\u00e8ge 4520",
    "addr:housenumber":"37",
    "addr:postcode":"4520",
    "addr:street":"Rue Canal",
    "iso:country":"BE",
    "sg:address":"Rue Canal 37",
    "sg:city":"Wanze",
    "sg:orig_category":"Plomberie, chauffage and installations sanitaires",
    "sg:phone":"+32 85 24 39 78",
    "sg:postcode":"4520",
    "sg:province":"Li\u00e8ge",
    "wof:name":"Marcel Wolk",
    "wof:placetype":"venue"
},
  "geometry": {"coordinates":[5.1907501221,50.5560798645],"type":"Point"}
}