{
  "type": "Feature",
  "properties": {
    "iso:country":"BE",
    "sg:address":"Place L'ilon 17",
    "sg:city":"Namur",
    "sg:orig_category":"Mutualities",
    "sg:phone":"+32 81 24 92 81",
    "sg:postcode":"5000",
    "sg:province":"Namur",
    "wof:name":"Centre Informatique R\u00e9gion",
    "wof:placetype":"venue"
},
  "geometry": {"coordinates":[4.8704371452,50.4637794495],"type":"Point"}
}