{
  "type": "Feature",
  "properties": {
    "iso:country":"BE",
    "sg:address":"Pastorijstraat 40b2",
    "sg:city":"Houthalen-helchteren",
    "sg:orig_category":"Formation permanente",
    "sg:phone":"+32 11 52 39 99",
    "sg:postcode":"3530",
    "sg:province":"Limburg",
    "wof:name":"Techn.inst.kempens Bekken",
    "wof:placetype":"venue"
},
  "geometry": {"coordinates":[5.3745150566,51.026802063],"type":"Point"}
}