{
  "type": "Feature",
  "properties": {
    "addr:full":"Schoolstraat 26 Middelkerke (lombardsijde) West-Vlaanderen 8434",
    "addr:housenumber":"26",
    "addr:postcode":"8434",
    "addr:street":"Schoolstraat",
    "iso:country":"BE",
    "sg:address":"Schoolstraat 26",
    "sg:city":"Middelkerke (lombardsijde)",
    "sg:classifiers":[
        {
            "category":"Bars & Pubs",
            "type":"Food & Drink"
        }
    ],
    "sg:phone":"+32 58 24 11 27",
    "sg:postcode":"8434",
    "sg:province":"West-Vlaanderen",
    "wof:name":"De Jol",
    "wof:placetype":"venue"
},
  "geometry": {"coordinates":[2.7549879551,51.1488876343],"type":"Point"}
}