{
  "type": "Feature",
  "properties": {
    "addr:full":"Rue De La Station 37c Ath Hainaut 7800",
    "addr:housenumber":"37c",
    "addr:postcode":"7800",
    "addr:street":"Rue De La Station",
    "iso:country":"BE",
    "sg:address":"Rue De La Station 37c",
    "sg:city":"Ath",
    "sg:classifiers":[
        {
            "category":"Cafe",
            "type":"Food & Drink"
        }
    ],
    "sg:phone":"+32 68 28 01 95",
    "sg:postcode":"7800",
    "sg:province":"Hainaut",
    "sg:tags":[
        "snack-bars"
    ],
    "wof:name":"Gourmet (le) Sprl",
    "wof:placetype":"venue"
},
  "geometry": {"coordinates":[3.7800168991,50.6273803711],"type":"Point"}
}