{
  "type": "Feature",
  "properties": {
    "iso:country":"BE",
    "sg:address":"Rue Ville Basse 2",
    "sg:city":"Silly",
    "sg:classifiers":[
        {
            "category":"Wholesale",
            "subcategory":"Beer",
            "type":"Manufacturing & Wholesale Goods"
        }
    ],
    "sg:phone":"+32 68 55 16 95",
    "sg:postcode":"7830",
    "sg:province":"Hainaut",
    "sg:tags":[
        "regional"
    ],
    "wof:name":"Brasserie De Silly S.a.",
    "wof:placetype":"venue"
},
  "geometry": {"coordinates":[3.9248399734,50.6494903564],"type":"Point"}
}