{
  "type": "Feature",
  "properties": {
    "addr:full":"Avenue De La Gare 71 Neufch\u00e2teau Luxembourg 6840",
    "addr:housenumber":"71",
    "addr:postcode":"6840",
    "addr:street":"Avenue De La Gare",
    "iso:country":"BE",
    "sg:address":"Avenue De La Gare 71",
    "sg:city":"Neufch\u00e2teau",
    "sg:classifiers":[
        {
            "category":"Health Services",
            "subcategory":"Dentist",
            "type":"Services"
        }
    ],
    "sg:phone":"+32 61 27 84 70",
    "sg:postcode":"6840",
    "sg:province":"Luxembourg",
    "wof:name":"Borlee G",
    "wof:placetype":"venue"
},
  "geometry": {"coordinates":[5.4404420853,49.8463363647],"type":"Point"}
}