{
  "type": "Feature",
  "properties": {
    "iso:country":"BE",
    "sg:address":"Duribreustraat 48",
    "sg:city":"Komen-waasten/comines-warneton",
    "sg:orig_category":"Elektrische installaties voor woningen",
    "sg:phone":"+32 56 58 82 88",
    "sg:postcode":"7783",
    "sg:province":"Hainaut",
    "wof:name":"Emmanuel Soenen",
    "wof:placetype":"venue"
},
  "geometry": {"coordinates":[2.8828949928,50.7069244385],"type":"Point"}
}