{
  "type": "Feature",
  "properties": {
    "addr:full":"Stationsstraat 93 Brakel Oost-Vlaanderen 9660",
    "addr:housenumber":"93",
    "addr:postcode":"9660",
    "addr:street":"Stationsstraat",
    "iso:country":"BE",
    "sg:address":"Stationsstraat 93",
    "sg:city":"Brakel",
    "sg:orig_category":"Apotheken",
    "sg:phone":"+32 55 42 32 94",
    "sg:postcode":"9660",
    "sg:province":"Oost-Vlaanderen",
    "wof:name":"Martine De Croo",
    "wof:placetype":"venue"
},
  "geometry": {"coordinates":[3.7642350197,50.8025398254],"type":"Point"}
}