{
  "type": "Feature",
  "properties": {
    "addr:full":"Rue Breydel 37 Bruxelles (etterbeek) Bruxelles-Capitale 1040",
    "addr:housenumber":"37",
    "addr:postcode":"1040",
    "addr:street":"Rue Breydel",
    "iso:country":"BE",
    "sg:address":"Rue Breydel 37",
    "sg:city":"Bruxelles (etterbeek)",
    "sg:classifiers":[
        {
            "category":"Health Services",
            "subcategory":"Health Practitioner",
            "type":"Services"
        }
    ],
    "sg:phone":"+32 2 230 28 50",
    "sg:postcode":"1040",
    "sg:province":"Bruxelles-Capitale",
    "sg:tags":[
        "physiotherapist"
    ],
    "wof:name":"Waeterloos Ann-catherine",
    "wof:placetype":"venue"
},
  "geometry": {"coordinates":[4.3843789101,50.8413162231],"type":"Point"}
}