{
  "type": "Feature",
  "properties": {
    "addr:full":"Rue Arthur Blairon 12 Namur (boninne - Gelbress\u00e9e) Namur 5021",
    "addr:housenumber":"12",
    "addr:postcode":"5021",
    "addr:street":"Rue Arthur Blairon",
    "iso:country":"BE",
    "sg:address":"Rue Arthur Blairon 12",
    "sg:city":"Namur (boninne - Gelbress\u00e9e)",
    "sg:classifiers":[
        {
            "category":"Building & Trades",
            "subcategory":"Landscaping Services",
            "type":"Services"
        }
    ],
    "sg:phone":"+32 81 21 52 22",
    "sg:postcode":"5021",
    "sg:province":"Namur",
    "sg:tags":[
        "gardening",
        "garden",
        "maintenance"
    ],
    "wof:name":"Binon G",
    "wof:placetype":"venue"
},
  "geometry": {"coordinates":[4.9334101677,50.4948120117],"type":"Point"}
}