{
  "type": "Feature",
  "properties": {
    "iso:country":"BE",
    "sg:address":"Pastorijstraat 46",
    "sg:city":"Herk-de-stad",
    "sg:classifiers":[
        {
            "category":"Insurance",
            "subcategory":"Life Insurance",
            "type":"Services"
        }
    ],
    "sg:phone":"+32 13 44 26 68",
    "sg:postcode":"3540",
    "sg:province":"Limburg",
    "sg:tags":[
        "assurance"
    ],
    "wof:name":"Nicole Windmolders",
    "wof:placetype":"venue"
},
  "geometry": {"coordinates":[5.134221077,50.942401886],"type":"Point"}
}