{
  "type": "Feature",
  "properties": {
    "iso:country":"BE",
    "sg:address":"Beversesteenweg 261",
    "sg:city":"Roeselare",
    "sg:classifiers":[
        {
            "category":"Retail",
            "subcategory":"Repair Shop",
            "type":"Services"
        }
    ],
    "sg:phone":"+32 51 20 11 47",
    "sg:postcode":"8800",
    "sg:province":"West-Vlaanderen",
    "wof:name":"Baert G",
    "wof:placetype":"venue"
},
  "geometry": {"coordinates":[3.1334240437,50.9612312317],"type":"Point"}
}