{
  "type": "Feature",
  "properties": {
    "iso:country":"BE",
    "sg:address":"Tommestraat 34",
    "sg:city":"Lo-reninge",
    "sg:orig_category":"Varkenskwekers",
    "sg:phone":"+32 58 28 85 81",
    "sg:postcode":"8647",
    "sg:province":"West-Vlaanderen",
    "wof:name":"Jos\u00c9 Ketelers",
    "wof:placetype":"venue"
},
  "geometry": {"coordinates":[2.7178249359,50.9683990479],"type":"Point"}
}