{
  "type": "Feature",
  "properties": {
    "addr:full":"Rue Du Conseil 4 Bruxelles (ixelles) Bruxelles-Capitale 1050",
    "addr:housenumber":"4",
    "addr:postcode":"1050",
    "addr:street":"Rue Du Conseil",
    "iso:country":"BE",
    "sg:address":"Rue Du Conseil 4",
    "sg:city":"Bruxelles (ixelles)",
    "sg:classifiers":[
        {
            "category":"Professional",
            "subcategory":"Accounting & Tax Preparation",
            "type":"Services"
        }
    ],
    "sg:phone":"+32 2 503 07 72",
    "sg:postcode":"1050",
    "sg:province":"Bruxelles-Capitale",
    "sg:tags":[
        "bookkeeper"
    ],
    "wof:name":"Cauchie J-m",
    "wof:placetype":"venue"
},
  "geometry": {"coordinates":[4.3671789169,50.8335342407],"type":"Point"}
}