{
  "type": "Feature",
  "properties": {
    "addr:full":"Leiestraat 8 Wervik West-Vlaanderen 8940",
    "addr:housenumber":"8",
    "addr:postcode":"8940",
    "addr:street":"Leiestraat",
    "iso:country":"BE",
    "sg:address":"Leiestraat 8",
    "sg:city":"Wervik",
    "sg:classifiers":[
        {
            "category":"Shopping",
            "subcategory":"Shoes",
            "type":"Retail Goods"
        }
    ],
    "sg:phone":"+32 56 31 17 84",
    "sg:postcode":"8940",
    "sg:province":"West-Vlaanderen",
    "sg:tags":[
        "slipper",
        "-"
    ],
    "wof:name":"De Brouwer R",
    "wof:placetype":"venue"
},
  "geometry": {"coordinates":[3.043184042,50.777141571],"type":"Point"}
}