{
  "type": "Feature",
  "properties": {
    "iso:country":"BE",
    "sg:address":"Lambroeckstraat 117",
    "sg:city":"Dendermonde",
    "sg:orig_category":"Rundveehouders",
    "sg:phone":"+32 52 21 10 31",
    "sg:postcode":"9200",
    "sg:province":"Oost-Vlaanderen",
    "wof:name":"Michel Cool",
    "wof:placetype":"venue"
},
  "geometry": {"coordinates":[4.0983099937,51.0315208435],"type":"Point"}
}