{
  "type": "Feature",
  "properties": {
    "iso:country":"BE",
    "sg:address":"Bethovenstraat 87",
    "sg:city":"Brecht",
    "sg:orig_category":"Farmaceutische producten Gh",
    "sg:phone":"+32 3 313 64 58",
    "sg:postcode":"2960",
    "sg:province":"Antwerpen",
    "wof:name":"Appeco",
    "wof:placetype":"venue"
},
  "geometry": {"coordinates":[4.6333050728,51.3526382446],"type":"Point"}
}