{
  "type": "Feature",
  "properties": {
    "iso:country":"BE",
    "sg:address":"Lijsterstraat 10bb",
    "sg:city":"Duffel",
    "sg:orig_category":"Fleurs and plantes",
    "sg:phone":"+32 15 31 93 58",
    "sg:postcode":"2570",
    "sg:province":"Antwerpen",
    "wof:name":"Maria De Laet",
    "wof:placetype":"venue"
},
  "geometry": {"coordinates":[4.4868350029,51.074760437],"type":"Point"}
}