{
  "type": "Feature",
  "properties": {
    "addr:full":"Diksmuidsesteenweg 285 Roeselare West-Vlaanderen 8800",
    "addr:housenumber":"285",
    "addr:postcode":"8800",
    "addr:street":"Diksmuidsesteenweg",
    "iso:country":"BE",
    "sg:address":"Diksmuidsesteenweg 285",
    "sg:city":"Roeselare",
    "sg:orig_category":"Non-Classified Establishments",
    "sg:phone":"+32 51 24 26 99",
    "sg:postcode":"8800",
    "sg:province":"West-Vlaanderen",
    "wof:name":"Doritex",
    "wof:placetype":"venue"
},
  "geometry": {"coordinates":[3.1093719006,50.9479484558],"type":"Point"}
}