{
  "type": "Feature",
  "properties": {
    "addr:full":"Molenstraat 32 Kontich Antwerpen 2550",
    "addr:housenumber":"32",
    "addr:postcode":"2550",
    "addr:street":"Molenstraat",
    "iso:country":"BE",
    "sg:address":"Molenstraat 32",
    "sg:city":"Kontich",
    "sg:classifiers":[
        {
            "category":"Education",
            "subcategory":"School",
            "type":"Public Place"
        }
    ],
    "sg:phone":"+32 3 457 06 04",
    "sg:postcode":"2550",
    "sg:province":"Antwerpen",
    "sg:tags":[
        "primary"
    ],
    "wof:name":"Gemeentelijke Basisschool A. Hans",
    "wof:placetype":"venue"
},
  "geometry": {"coordinates":[4.442961216,51.136051178],"type":"Point"}
}