{
  "type": "Feature",
  "properties": {
    "iso:country":"BE",
    "sg:address":"Boulevard L\u00c9opold Ii 180",
    "sg:city":"Sint-jans-molenbeek/molenbeek-saint-jean",
    "sg:orig_category":"Avocats and conseillers juridiques",
    "sg:phone":"+32 2 410 65 86",
    "sg:postcode":"1080",
    "sg:province":"Bruxelles-Capitale",
    "wof:name":"Stijn Butenaerts",
    "wof:placetype":"venue"
},
  "geometry": {"coordinates":[4.3359918594,50.8613204956],"type":"Point"}
}