{
  "type": "Feature",
  "properties": {
    "addr:full":"Herkkantstraat 13 Hasselt Limburg 3512",
    "addr:housenumber":"13",
    "addr:postcode":"3512",
    "addr:street":"Herkkantstraat",
    "iso:country":"BE",
    "sg:address":"Herkkantstraat 13",
    "sg:city":"Hasselt",
    "sg:orig_category":"Producteurs de fruits",
    "sg:phone":"+32 11 31 56 26",
    "sg:postcode":"3512",
    "sg:province":"Limburg",
    "wof:name":"Pierre Reniers",
    "wof:placetype":"venue"
},
  "geometry": {"coordinates":[5.2465701103,50.9198493958],"type":"Point"}
}