{
  "type": "Feature",
  "properties": {
    "addr:full":"Rue E Solvay 25 Herstal Li\u00e8ge 4040",
    "addr:housenumber":"25",
    "addr:postcode":"4040",
    "addr:street":"Rue E Solvay",
    "iso:country":"BE",
    "sg:address":"Rue E Solvay 25",
    "sg:city":"Herstal",
    "sg:orig_category":"Informaticaconsulenten",
    "sg:phone":"+32 4 240 23 70",
    "sg:postcode":"4040",
    "sg:province":"Li\u00e8ge",
    "wof:name":"Bcm",
    "wof:placetype":"venue"
},
  "geometry": {"coordinates":[5.6239299774,50.6598167419],"type":"Point"}
}