{
  "type": "Feature",
  "properties": {
    "addr:full":"Steenweg Op Weelde 2ba Merksplas Antwerpen 2330",
    "addr:housenumber":"2ba",
    "addr:postcode":"2330",
    "addr:street":"Steenweg Op Weelde",
    "iso:country":"BE",
    "sg:address":"Steenweg Op Weelde 2ba",
    "sg:city":"Merksplas",
    "sg:orig_category":"Protection civile",
    "sg:phone":"+32 14 63 41 07",
    "sg:postcode":"2330",
    "sg:province":"Antwerpen",
    "wof:name":"Brandweerkazerne",
    "wof:placetype":"venue"
},
  "geometry": {"coordinates":[4.865983963,51.365234375],"type":"Point"}
}