{
  "type": "Feature",
  "properties": {
    "addr:full":"Schoebroekstraat 34-36 Beringen Limburg 3583",
    "addr:postcode":"34-36 beringen;3583",
    "addr:street":"Schoebroekstraat",
    "iso:country":"BE",
    "sg:address":"Schoebroekstraat 34-36",
    "sg:city":"Beringen",
    "sg:orig_category":"Verhuur diverse uitrustingen",
    "sg:phone":"+32 11 45 72 11",
    "sg:postcode":"3583",
    "sg:province":"Limburg",
    "wof:name":"Ge Cms",
    "wof:placetype":"venue"
},
  "geometry": {"coordinates":[5.1706700325,51.0389442444],"type":"Point"}
}