{
  "type": "Feature",
  "properties": {
    "iso:country":"BE",
    "sg:address":"Gustave Royersln 12",
    "sg:city":"Ronse",
    "sg:classifiers":[
        {
            "category":"Shopping",
            "subcategory":"Clothing, Apparel, & Fashions",
            "type":"Retail Goods"
        }
    ],
    "sg:phone":"+32 55 21 48 35",
    "sg:postcode":"9600",
    "sg:province":"Oost-Vlaanderen",
    "sg:tags":[
        "textile",
        "clothing",
        "clothes"
    ],
    "wof:name":"L. Foulon Nv",
    "wof:placetype":"venue"
},
  "geometry": {"coordinates":[3.5929069519,50.7424087524],"type":"Point"}
}