{
  "type": "Feature",
  "properties": {
    "addr:full":"Venlosesteenweg 373 Kinrooi Limburg 3640",
    "addr:housenumber":"373",
    "addr:postcode":"3640",
    "addr:street":"Venlosesteenweg",
    "iso:country":"BE",
    "sg:address":"Venlosesteenweg 373",
    "sg:city":"Kinrooi",
    "sg:classifiers":[
        {
            "category":"Autos & Motor Vehicles",
            "subcategory":"Fuel & Gas Station",
            "type":"Retail Goods"
        }
    ],
    "sg:phone":"+32 89 56 43 46",
    "sg:postcode":"3640",
    "sg:province":"Limburg",
    "sg:tags":[
        "stations-service",
        "carburants"
    ],
    "wof:name":"Jacobus Arits",
    "wof:placetype":"venue"
},
  "geometry": {"coordinates":[5.8054800034,51.1356201172],"type":"Point"}
}