{
  "type": "Feature",
  "properties": {
    "addr:full":"Rue Pierre Baily 14 Charleroi (marcinelle) Hainaut 6001",
    "addr:housenumber":"14",
    "addr:postcode":"6001",
    "addr:street":"Rue Pierre Baily",
    "iso:country":"BE",
    "sg:address":"Rue Pierre Baily 14",
    "sg:city":"Charleroi (marcinelle)",
    "sg:classifiers":[
        {
            "category":"Real Estate",
            "subcategory":"Architect",
            "type":"Services"
        }
    ],
    "sg:phone":"+32 71 36 34 36",
    "sg:postcode":"6001",
    "sg:province":"Hainaut",
    "wof:name":"Gailly M-a Mme",
    "wof:placetype":"venue"
},
  "geometry": {"coordinates":[4.4518837929,50.3990020752],"type":"Point"}
}