{
  "type": "Feature",
  "properties": {
    "addr:full":"Trou Renard 34 Gesves (faulx-les-tombes) Namur 5340",
    "addr:housenumber":"34",
    "addr:postcode":"5340",
    "addr:street":"Trou Renard",
    "iso:country":"BE",
    "sg:address":"Trou Renard 34",
    "sg:city":"Gesves (faulx-les-tombes)",
    "sg:classifiers":[
        {
            "category":"Professional",
            "subcategory":"Accounting & Tax Preparation",
            "type":"Services"
        }
    ],
    "sg:phone":"+32 81 57 00 30",
    "sg:postcode":"5340",
    "sg:province":"Namur",
    "sg:tags":[
        "bookkeeper"
    ],
    "wof:name":"Libois N",
    "wof:placetype":"venue"
},
  "geometry": {"coordinates":[5.0755457878,50.4024353027],"type":"Point"}
}