{
  "type": "Feature",
  "properties": {
    "addr:full":"Avenue De La Closeraie 5 Li\u00e8ge 1 (rocourt) Li\u00e8ge 4000",
    "addr:housenumber":"5;1",
    "addr:postcode":"4000",
    "addr:street":"Avenue De La Closeraie",
    "iso:country":"BE",
    "sg:address":"Avenue De La Closeraie 5",
    "sg:city":"Li\u00e8ge 1 (rocourt)",
    "sg:classifiers":[
        {
            "category":"Professional",
            "subcategory":"Computer Services",
            "type":"Services"
        }
    ],
    "sg:phone":"+32 4 224 94 10",
    "sg:postcode":"4000",
    "sg:province":"Li\u00e8ge",
    "sg:tags":[
        "-",
        "processing",
        "data",
        "software"
    ],
    "wof:name":"M.b.c.",
    "wof:placetype":"venue"
},
  "geometry": {"coordinates":[5.5558381081,50.6671409607],"type":"Point"}
}