{
  "type": "Feature",
  "properties": {
    "iso:country":"BE",
    "sg:address":"Schoolstraat 33",
    "sg:city":"Waarschoot",
    "sg:orig_category":"Enseignement maternel and primaire",
    "sg:phone":"+32 9 378 43 26",
    "sg:postcode":"9950",
    "sg:province":"Oost-Vlaanderen",
    "wof:name":"Vrije Kleuterschool",
    "wof:placetype":"venue"
},
  "geometry": {"coordinates":[3.6048591137,51.1521377563],"type":"Point"}
}