{
  "type": "Feature",
  "properties": {
    "addr:full":"Evelandweg 6 Oosterzele Oost-Vlaanderen 9860",
    "addr:housenumber":"6",
    "addr:postcode":"9860",
    "addr:street":"Evelandweg;Oost-Vlaanderen",
    "iso:country":"BE",
    "sg:address":"Evelandweg 6",
    "sg:city":"Oosterzele",
    "sg:orig_category":"Rundveehouders",
    "sg:phone":"+32 9 360 12 66",
    "sg:postcode":"9860",
    "sg:province":"Oost-Vlaanderen",
    "wof:name":"Robert Baudewijns",
    "wof:placetype":"venue"
},
  "geometry": {"coordinates":[3.7877271175,50.9091072083],"type":"Point"}
}