{
  "type": "Feature",
  "properties": {
    "addr:full":"Beerlegemsebaan 57 Zwalm (beerlegem) Oost-Vlaanderen 9630",
    "addr:housenumber":"57",
    "addr:postcode":"9630",
    "addr:street":"Beerlegemsebaan;Beerlegem Oost-Vlaanderen",
    "iso:country":"BE",
    "sg:address":"Beerlegemsebaan 57",
    "sg:city":"Zwalm (beerlegem)",
    "sg:classifiers":[
        {
            "category":"Real Estate",
            "subcategory":"Developer",
            "type":"Services"
        }
    ],
    "sg:phone":"+32 495 30 59 99",
    "sg:postcode":"9630",
    "sg:province":"Oost-Vlaanderen",
    "sg:tags":[
        "project"
    ],
    "wof:name":"Duprez K",
    "wof:placetype":"venue"
},
  "geometry": {"coordinates":[3.7171080112,50.9063034058],"type":"Point"}
}