{
  "type": "Feature",
  "properties": {
    "iso:country":"BE",
    "sg:address":"Hitsveldlaan 34",
    "sg:city":"Hamont-achel",
    "sg:orig_category":"Entretien and r\u00e9parations de voitures",
    "sg:phone":"+32 11 64 92 10",
    "sg:postcode":"3930",
    "sg:province":"Limburg",
    "wof:name":"Robert Baeken",
    "wof:placetype":"venue"
},
  "geometry": {"coordinates":[5.4732761383,51.2514915466],"type":"Point"}
}