{
  "type": "Feature",
  "properties": {
    "iso:country":"BE",
    "sg:address":"Avenue Reine Elisabeth 41",
    "sg:city":"Andenne",
    "sg:orig_category":"Krantenuitgeverijen Reclamebureaus Tijdschriftenuitgeverijen",
    "sg:phone":"+32 85 84 47 53",
    "sg:postcode":"5300",
    "sg:province":"Namur",
    "wof:name":"Andenne Potins",
    "wof:placetype":"venue"
},
  "geometry": {"coordinates":[5.0939760208,50.4910316467],"type":"Point"}
}