{
  "type": "Feature",
  "properties": {
    "addr:full":"Rue De L'expansion 16d Ans (alleur) Li\u00e8ge 4432",
    "addr:housenumber":"16d",
    "addr:postcode":"4432",
    "addr:street":"Rue De L'Expansion",
    "iso:country":"BE",
    "sg:address":"Rue De L'expansion 16d",
    "sg:city":"Ans (alleur)",
    "sg:orig_category":"Non-Classified Establishments",
    "sg:phone":"+32 4 247 03 00",
    "sg:postcode":"4432",
    "sg:province":"Li\u00e8ge",
    "wof:name":"Notifier Benelux Sa",
    "wof:placetype":"venue"
},
  "geometry": {"coordinates":[5.5291252136,50.6798400879],"type":"Point"}
}