{
  "type": "Feature",
  "properties": {
    "addr:full":"Oplintersesteenweg 499 Tienen Vlaams-Brabant 3300",
    "addr:housenumber":"499",
    "addr:postcode":"3300",
    "addr:street":"Oplintersesteenweg",
    "iso:country":"BE",
    "sg:address":"Oplintersesteenweg 499",
    "sg:city":"Tienen",
    "sg:orig_category":"Boekhouders",
    "sg:phone":"+32 16 81 96 53",
    "sg:postcode":"3300",
    "sg:province":"Vlaams-Brabant",
    "wof:name":"Roland Smets",
    "wof:placetype":"venue"
},
  "geometry": {"coordinates":[4.9575099945,50.8213996887],"type":"Point"}
}