{
  "type": "Feature",
  "properties": {
    "iso:country":"BE",
    "sg:address":"Kasteelstraat 47",
    "sg:city":"Halle",
    "sg:orig_category":"Bloemen and planten",
    "sg:phone":"+32 2 356 73 05",
    "sg:postcode":"1500",
    "sg:province":"Vlaams-Brabant",
    "wof:name":"Huis De Boeketterie",
    "wof:placetype":"venue"
},
  "geometry": {"coordinates":[4.2542219162,50.7197227478],"type":"Point"}
}