{
  "type": "Feature",
  "properties": {
    "addr:full":"Rue De Fer 45 Namur Namur 5000",
    "addr:housenumber":"45",
    "addr:postcode":"5000",
    "addr:street":"Rue De Fer",
    "iso:country":"BE",
    "sg:address":"Rue De Fer 45",
    "sg:city":"Namur",
    "sg:classifiers":[
        {
            "category":"Shopping",
            "subcategory":"Clothing, Apparel, & Fashions",
            "type":"Retail Goods"
        }
    ],
    "sg:phone":"+32 81 22 19 07",
    "sg:postcode":"5000",
    "sg:province":"Namur",
    "sg:tags":[
        "-",
        "clothing",
        "child"
    ],
    "wof:name":"Cool Concept",
    "wof:placetype":"venue"
},
  "geometry": {"coordinates":[4.8650407791,50.4657669067],"type":"Point"}
}