{
  "type": "Feature",
  "properties": {
    "addr:full":"Nieuwstraat 6 Knokke-heist West-Vlaanderen 8300",
    "addr:housenumber":"6",
    "addr:postcode":"8300",
    "addr:street":"Nieuwstraat",
    "iso:country":"BE",
    "sg:address":"Nieuwstraat 6",
    "sg:city":"Knokke-heist",
    "sg:orig_category":"Rev\u00eatements de sols and murs",
    "sg:phone":"+32 50 62 25 71",
    "sg:postcode":"8300",
    "sg:province":"West-Vlaanderen",
    "wof:name":"Peter Vereyken",
    "wof:placetype":"venue"
},
  "geometry": {"coordinates":[3.2873859406,51.3383216858],"type":"Point"}
}