{
  "type": "Feature",
  "properties": {
    "addr:full":"Rue Th\u00e9odore Verhaegen 136 Bruxelles (saint-gilles) Bruxelles-Capitale 1060",
    "addr:housenumber":"136",
    "addr:postcode":"1060",
    "addr:street":"Rue The\u0301Odore Verhaegen",
    "iso:country":"BE",
    "sg:address":"Rue Th\u00e9odore Verhaegen 136",
    "sg:city":"Bruxelles (saint-gilles)",
    "sg:classifiers":[
        {
            "category":"Shopping",
            "subcategory":"Books",
            "type":"Retail Goods"
        }
    ],
    "sg:phone":"+32 2 537 00 36",
    "sg:postcode":"1060",
    "sg:province":"Bruxelles-Capitale",
    "sg:tags":[
        "bookseller"
    ],
    "wof:name":"Anna Librairie",
    "wof:placetype":"venue"
},
  "geometry": {"coordinates":[4.337706089,50.8299484253],"type":"Point"}
}