{
  "type": "Feature",
  "properties": {
    "addr:full":"Huttestraat 10 Berlaar Antwerpen 2590",
    "addr:housenumber":"10",
    "addr:postcode":"2590",
    "addr:street":"Huttestraat",
    "iso:country":"BE",
    "sg:address":"Huttestraat 10",
    "sg:city":"Berlaar",
    "sg:classifiers":[
        {
            "category":"Farming",
            "subcategory":"Crops",
            "type":"Manufacturing & Wholesale Goods"
        }
    ],
    "sg:phone":"+32 3 482 46 20",
    "sg:postcode":"2590",
    "sg:province":"Antwerpen",
    "sg:tags":[
        "vegetable",
        "fruit",
        "-",
        "grower"
    ],
    "wof:name":"Beltomex Bvba",
    "wof:placetype":"venue"
},
  "geometry": {"coordinates":[4.6386380196,51.08959198],"type":"Point"}
}