{
  "type": "Feature",
  "properties": {
    "iso:country":"BE",
    "sg:address":"Bampstraat 2",
    "sg:city":"Riemst",
    "sg:classifiers":[
        {
            "category":"Fast Food",
            "type":"Food & Drink"
        }
    ],
    "sg:phone":"+32 12 45 76 56",
    "sg:postcode":"3770",
    "sg:province":"Limburg",
    "sg:tags":[
        "\u00c0",
        "emporter",
        "restaurants"
    ],
    "wof:name":"Frituur 't Pleintje",
    "wof:placetype":"venue"
},
  "geometry": {"coordinates":[5.596159935,50.7861595154],"type":"Point"}
}