{
  "type": "Feature",
  "properties": {
    "addr:full":"Spanjeberg 4 Dilbeek Vlaams-Brabant 1700",
    "addr:housenumber":"4",
    "addr:postcode":"1700",
    "addr:street":"Spanjeberg",
    "iso:country":"BE",
    "sg:address":"Spanjeberg 4",
    "sg:city":"Dilbeek",
    "sg:orig_category":"Tweedehandsgoederen",
    "sg:phone":"+32 2 567 10 33",
    "sg:postcode":"1700",
    "sg:province":"Vlaams-Brabant",
    "wof:name":"Televil",
    "wof:placetype":"venue"
},
  "geometry": {"coordinates":[4.2646570206,50.8450927734],"type":"Point"}
}