{
  "type": "Feature",
  "properties": {
    "addr:full":"Avenue Emile Vandervelde 236 Ch\u00c2telet Hainaut 6200",
    "addr:housenumber":"236",
    "addr:postcode":"6200",
    "addr:street":"Avenue Emile Vandervelde",
    "iso:country":"BE",
    "sg:address":"Avenue Emile Vandervelde 236",
    "sg:city":"Ch\u00c2telet",
    "sg:orig_category":"Installatie van houten of kunststof schrijnwerk Installatie van metalen schrijnwerk",
    "sg:phone":"+32 71 38 31 61",
    "sg:postcode":"6200",
    "sg:province":"Hainaut",
    "wof:name":"Eco-ch\u00c2ssis",
    "wof:placetype":"venue"
},
  "geometry": {"coordinates":[4.5211410522,50.3973655701],"type":"Point"}
}