{
  "type": "Feature",
  "properties": {
    "addr:full":"Kiwilaan 7 Zoersel Antwerpen 2980",
    "addr:housenumber":"7",
    "addr:postcode":"2980",
    "addr:street":"Kiwilaan",
    "iso:country":"BE",
    "sg:address":"Kiwilaan 7",
    "sg:city":"Zoersel",
    "sg:classifiers":[
        {
            "category":"Health Services",
            "subcategory":"Health Practitioner",
            "type":"Services"
        }
    ],
    "sg:phone":"+32 3 384 14 72",
    "sg:postcode":"2980",
    "sg:province":"Antwerpen",
    "sg:tags":[
        "physiotherapist"
    ],
    "wof:name":"De Bruycker S",
    "wof:placetype":"venue"
},
  "geometry": {"coordinates":[4.6670408249,51.2692527771],"type":"Point"}
}