{
  "type": "Feature",
  "properties": {
    "addr:full":"De Spildoren 77 Schilde Antwerpen 2970",
    "addr:housenumber":"77",
    "addr:postcode":"2970",
    "iso:country":"BE",
    "sg:address":"De Spildoren 77",
    "sg:city":"Schilde",
    "sg:orig_category":"Experts-comptables",
    "sg:phone":"+32 3 322 82 10",
    "sg:postcode":"2970",
    "sg:province":"Antwerpen",
    "wof:name":"Jozef Dils",
    "wof:placetype":"venue"
},
  "geometry": {"coordinates":[4.5929632187,51.2393760681],"type":"Point"}
}