{
  "type": "Feature",
  "properties": {
    "addr:full":"Stationsstraat 34 Box 12 Alken Limburg 3570",
    "addr:housenumber":"34 box 12",
    "addr:postcode":"3570",
    "addr:street":"Stationsstraat",
    "iso:country":"BE",
    "sg:address":"Stationsstraat 34 Box 12",
    "sg:city":"Alken",
    "sg:classifiers":[
        {
            "category":"Wholesale",
            "subcategory":"Painting Supplies",
            "type":"Manufacturing & Wholesale Goods"
        }
    ],
    "sg:phone":"+32 11 31 68 20",
    "sg:postcode":"3570",
    "sg:province":"Limburg",
    "sg:tags":[
        "industrial",
        "-"
    ],
    "wof:name":"A.s.v.d. Nv",
    "wof:placetype":"venue"
},
  "geometry": {"coordinates":[5.3024258614,50.8816795349],"type":"Point"}
}