{
  "type": "Feature",
  "properties": {
    "addr:full":"Redingenstraat 86b2 Leuven Vlaams-Brabant 3000",
    "addr:housenumber":"86b2",
    "addr:postcode":"3000",
    "addr:street":"Redingenstraat",
    "iso:country":"BE",
    "sg:address":"Redingenstraat 86b2",
    "sg:city":"Leuven",
    "sg:orig_category":"Activit\u00e9s d\u00b4action sociale sans h\u00e9bergement",
    "sg:phone":"+32 16 22 81 95",
    "sg:postcode":"3000",
    "sg:province":"Vlaams-Brabant",
    "wof:name":"Vclb-centrum",
    "wof:placetype":"venue"
},
  "geometry": {"coordinates":[4.6959338188,50.8729743958],"type":"Point"}
}