{
  "type": "Feature",
  "properties": {
    "iso:country":"BE",
    "sg:address":"Rue Du Paradis 65",
    "sg:city":"Ath",
    "sg:orig_category":"Enseignement maternel and primaire",
    "sg:phone":"+32 68 84 10 75",
    "sg:postcode":"7800",
    "sg:province":"Hainaut",
    "wof:name":"Ecole Matern. Communale",
    "wof:placetype":"venue"
},
  "geometry": {"coordinates":[3.7711238861,50.6367111206],"type":"Point"}
}