{
  "type": "Feature",
  "properties": {
    "iso:country":"BE",
    "sg:address":"Grote Steenweg 139",
    "sg:city":"Kontich (waarloos)",
    "sg:classifiers":[
        {
            "category":"Professional",
            "subcategory":"Art Services",
            "type":"Services"
        }
    ],
    "sg:phone":"+32 15 31 28 14",
    "sg:postcode":"2550",
    "sg:province":"Antwerpen",
    "sg:tags":[
        "children's",
        "animation"
    ],
    "wof:name":"Peter Pocus",
    "wof:placetype":"venue"
},
  "geometry": {"coordinates":[4.4513659477,51.1014175415],"type":"Point"}
}