{
  "type": "Feature",
  "properties": {
    "addr:full":"Hoeilaartsesteenweg 80 Overijse Vlaams-Brabant 3090",
    "addr:housenumber":"80",
    "addr:postcode":"3090",
    "addr:street":"Hoeilaartsesteenweg",
    "iso:country":"BE",
    "sg:address":"Hoeilaartsesteenweg 80",
    "sg:city":"Overijse",
    "sg:classifiers":[
        {
            "category":"Professional",
            "subcategory":"Management & Consulting",
            "type":"Services"
        }
    ],
    "sg:phone":"+32 2 657 05 93",
    "sg:postcode":"3090",
    "sg:province":"Vlaams-Brabant",
    "sg:tags":[
        "consultant",
        "agency",
        "advertising"
    ],
    "wof:name":"Modem Communications",
    "wof:placetype":"venue"
},
  "geometry": {"coordinates":[4.5149898529,50.7500686646],"type":"Point"}
}