{
  "type": "Feature",
  "properties": {
    "addr:full":"Stationsstraat 3 Aalst (gijzegem) Oost-Vlaanderen 9308",
    "addr:housenumber":"3",
    "addr:postcode":"9308",
    "addr:street":"Stationsstraat",
    "iso:country":"BE",
    "sg:address":"Stationsstraat 3",
    "sg:city":"Aalst (gijzegem)",
    "sg:classifiers":[
        {
            "category":"Education",
            "subcategory":"School",
            "type":"Public Place"
        }
    ],
    "sg:phone":"+32 53 72 93 40",
    "sg:postcode":"9308",
    "sg:province":"Oost-Vlaanderen",
    "sg:tags":[
        "secondary"
    ],
    "wof:name":"Instituut St-vincentius",
    "wof:placetype":"venue"
},
  "geometry": {"coordinates":[4.0371718407,50.9413452148],"type":"Point"}
}