{
  "type": "Feature",
  "properties": {
    "addr:full":"Lijsterbessenstraat 17 Maaseik Limburg 3680",
    "addr:housenumber":"17",
    "addr:postcode":"3680",
    "addr:street":"Lijsterbessenstraat",
    "iso:country":"BE",
    "sg:address":"Lijsterbessenstraat 17",
    "sg:city":"Maaseik",
    "sg:orig_category":"Artsen and specialisten",
    "sg:phone":"+32 89 86 32 66",
    "sg:postcode":"3680",
    "sg:province":"Limburg",
    "wof:name":"Robert Brusten",
    "wof:placetype":"venue"
},
  "geometry": {"coordinates":[5.791285038,51.0954208374],"type":"Point"}
}