{
  "type": "Feature",
  "properties": {
    "iso:country":"BE",
    "sg:address":"Kerkstraat 16",
    "sg:city":"Pepingen",
    "sg:classifiers":[
        {
            "category":"Health Services",
            "subcategory":"Health Practitioner",
            "type":"Services"
        }
    ],
    "sg:phone":"+32 2 360 10 42",
    "sg:postcode":"1670",
    "sg:province":"Vlaams-Brabant",
    "sg:tags":[
        "physiotherapist"
    ],
    "wof:name":"Bruyeer J",
    "wof:placetype":"venue"
},
  "geometry": {"coordinates":[4.1597890854,50.7583236694],"type":"Point"}
}