{
  "type": "Feature",
  "properties": {
    "addr:full":"Avenue Jean Pochet 112 Namur Namur 5001",
    "addr:housenumber":"112",
    "addr:postcode":"5001",
    "addr:street":"Avenue Jean Pochet",
    "iso:country":"BE",
    "sg:address":"Avenue Jean Pochet 112",
    "sg:city":"Namur",
    "sg:orig_category":"Maisons de repos and r\u00e9sidences",
    "sg:phone":"+32 81 72 37 00",
    "sg:postcode":"5001",
    "sg:province":"Namur",
    "wof:name":"Le Fontiloy",
    "wof:placetype":"venue"
},
  "geometry": {"coordinates":[4.812830925,50.472442627],"type":"Point"}
}