{
  "type": "Feature",
  "properties": {
    "iso:country":"BE",
    "sg:address":"Rue Try Des Rudes 37",
    "sg:city":"Chastre (cortil-noirmont)",
    "sg:classifiers":[
        {
            "category":"Health Services",
            "subcategory":"Nursing And Care Facility",
            "type":"Services"
        }
    ],
    "sg:phone":"+32 81 61 06 19",
    "sg:postcode":"1450",
    "sg:province":"Brabant Wallon",
    "sg:tags":[
        "access",
        "equipment",
        "hospital",
        "-"
    ],
    "wof:name":"Excotramed Sprl",
    "wof:placetype":"venue"
},
  "geometry": {"coordinates":[4.6517510414,50.5718803406],"type":"Point"}
}