{
  "type": "Feature",
  "properties": {
    "addr:full":"Rue Des Combattants 10 Houyet (hour) Namur 5563",
    "addr:housenumber":"10",
    "addr:postcode":"5563",
    "addr:street":"Rue Des Combattants",
    "iso:country":"BE",
    "sg:address":"Rue Des Combattants 10",
    "sg:city":"Houyet (hour)",
    "sg:classifiers":[
        {
            "category":"Health Services",
            "subcategory":"Health Practitioner",
            "type":"Services"
        }
    ],
    "sg:phone":"+32 82 66 70 66",
    "sg:postcode":"5563",
    "sg:province":"Namur",
    "sg:tags":[
        "physiotherapist"
    ],
    "wof:name":"Cartiaux M",
    "wof:placetype":"venue"
},
  "geometry": {"coordinates":[5.0386381149,50.1619758606],"type":"Point"}
}