{
  "type": "Feature",
  "properties": {
    "addr:full":"Stippelstraat 34 Sint-truiden Limburg 3800",
    "addr:housenumber":"34",
    "addr:postcode":"3800",
    "addr:street":"Stippelstraat",
    "iso:country":"BE",
    "sg:address":"Stippelstraat 34",
    "sg:city":"Sint-truiden",
    "sg:orig_category":"Paramedische behandelingen",
    "sg:phone":"+32 11 59 18 79",
    "sg:postcode":"3800",
    "sg:province":"Limburg",
    "wof:name":"N. Boiten",
    "wof:placetype":"venue"
},
  "geometry": {"coordinates":[5.2570209503,50.8428077698],"type":"Point"}
}