{
  "type": "Feature",
  "properties": {
    "addr:full":"March\u00c9 Aux Herbes 24 Mons Hainaut 7000",
    "addr:housenumber":"24",
    "addr:postcode":"7000",
    "addr:street":"Herbes;Hainaut",
    "iso:country":"BE",
    "sg:address":"March\u00c9 Aux Herbes 24",
    "sg:city":"Mons",
    "sg:classifiers":[
        {
            "category":"Restaurant",
            "type":"Food & Drink"
        }
    ],
    "sg:phone":"+32 65 84 68 33",
    "sg:postcode":"7000",
    "sg:province":"Hainaut",
    "wof:name":"Caf\u00c9 Manitek",
    "wof:placetype":"venue"
},
  "geometry": {"coordinates":[3.9526219368,50.4529914856],"type":"Point"}
}