{
  "type": "Feature",
  "properties": {
    "iso:country":"BE",
    "sg:address":"Rue De La Colline 6",
    "sg:city":"Bruxelles",
    "sg:classifiers":[
        {
            "category":"Professional",
            "subcategory":"Advertising",
            "type":"Services"
        }
    ],
    "sg:phone":"+32 2 503 09 36",
    "sg:postcode":"1000",
    "sg:province":"Bruxelles-Capitale",
    "sg:tags":[
        "item",
        "-",
        "business",
        "gift",
        "promotional"
    ],
    "wof:name":"Euro House",
    "wof:placetype":"venue"
},
  "geometry": {"coordinates":[4.3538961411,50.8466873169],"type":"Point"}
}