{
  "type": "Feature",
  "properties": {
    "addr:full":"Rue Georges Martin 6 Tertre Hainaut 7333",
    "addr:housenumber":"6",
    "addr:postcode":"7333",
    "addr:street":"Rue Georges Martin;Hainaut",
    "iso:country":"BE",
    "sg:address":"Rue Georges Martin 6",
    "sg:city":"Tertre",
    "sg:orig_category":"Fire-Proofing And Fire Protection Work",
    "sg:phone":"+32 3 829 00 99",
    "sg:postcode":"7333",
    "sg:province":"Hainaut",
    "wof:name":"Ajax Fsp",
    "wof:placetype":"venue"
},
  "geometry": {"coordinates":[4.3931632042,51.1677894592],"type":"Point"}
}