{
  "type": "Feature",
  "properties": {
    "iso:country":"BE",
    "sg:address":"De Kleetlaan 14",
    "sg:city":"Machelen (groot)",
    "sg:orig_category":"H\u00f4tels. Restaurants",
    "sg:phone":"+32 2 203 92 52",
    "sg:postcode":"1831",
    "sg:province":"Vlaams-Brabant",
    "wof:name":"Nh Airport",
    "wof:placetype":"venue"
},
  "geometry": {"coordinates":[4.4473237991,50.8892173767],"type":"Point"}
}