{
  "type": "Feature",
  "properties": {
    "iso:country":"BE",
    "sg:address":"Kalmthoutse Steenweg 120ba",
    "sg:city":"Wuustwezel",
    "sg:orig_category":"Entretien and r\u00e9parations de voitures",
    "sg:phone":"+32 3 669 64 79",
    "sg:postcode":"2990",
    "sg:province":"Antwerpen",
    "wof:name":"Frank Palinckx",
    "wof:placetype":"venue"
},
  "geometry": {"coordinates":[4.5797848701,51.3904266357],"type":"Point"}
}