{
  "type": "Feature",
  "properties": {
    "iso:country":"BE",
    "sg:address":"Rue Des Bl\u00c9s 111",
    "sg:city":"Li\u00c8ge",
    "sg:orig_category":"Drogueries",
    "sg:phone":"+32 4 229 51 71",
    "sg:postcode":"4000",
    "sg:province":"Li\u00e8ge",
    "wof:name":"Jean-pol Hertigers",
    "wof:placetype":"venue"
},
  "geometry": {"coordinates":[5.5450692177,50.6324081421],"type":"Point"}
}