{
  "type": "Feature",
  "properties": {
    "iso:country":"BE",
    "sg:address":"Vliegtuigln 10",
    "sg:city":"Gent",
    "sg:classifiers":[
        {
            "category":"Home & Garden",
            "subcategory":"Furniture",
            "type":"Retail Goods"
        }
    ],
    "sg:phone":"+32 69 76 84 96",
    "sg:postcode":"9000",
    "sg:province":"Oost-Vlaanderen",
    "sg:tags":[
        "household",
        "wood"
    ],
    "wof:name":"Selection Meubles Sprl",
    "wof:placetype":"venue"
},
  "geometry": {"coordinates":[3.5057549477,50.7436904907],"type":"Point"}
}