{
  "type": "Feature",
  "properties": {
    "iso:country":"BE",
    "sg:address":"Avenue De L'hippodrome 75",
    "sg:city":"Elsene/ixelles",
    "sg:orig_category":"Pain, p\u00e2tisseries and confiseries",
    "sg:phone":"+32 2 648 41 02",
    "sg:postcode":"1050",
    "sg:province":"Bruxelles-Capitale",
    "wof:name":"L'amandine",
    "wof:placetype":"venue"
},
  "geometry": {"coordinates":[4.3767299652,50.8204841614],"type":"Point"}
}