{
  "type": "Feature",
  "properties": {
    "iso:country":"BE",
    "sg:address":"Ivo Van Den Berghlaan 4",
    "sg:city":"Kapellen",
    "sg:classifiers":[
        {
            "category":"Professional",
            "subcategory":"Accounting & Tax Preparation",
            "type":"Services"
        }
    ],
    "sg:phone":"+32 3 665 21 94",
    "sg:postcode":"2950",
    "sg:province":"Antwerpen",
    "sg:tags":[
        "accountant"
    ],
    "wof:name":"Reyniers E",
    "wof:placetype":"venue"
},
  "geometry": {"coordinates":[4.4240708351,51.3133850098],"type":"Point"}
}