{
  "type": "Feature",
  "properties": {
    "iso:country":"BE",
    "sg:address":"Don Boscostraat 54",
    "sg:city":"Hechtel-eksel (hechtel)",
    "sg:classifiers":[
        {
            "category":"Shopping",
            "subcategory":"Florist",
            "type":"Retail Goods"
        }
    ],
    "sg:phone":"+32 11 73 25 16",
    "sg:postcode":"3940",
    "sg:province":"Limburg",
    "wof:name":"Meiklokje('t)",
    "wof:placetype":"venue"
},
  "geometry": {"coordinates":[5.364795208,51.1255340576],"type":"Point"}
}