{
  "type": "Feature",
  "properties": {
    "iso:country":"BE",
    "sg:address":"Rue Simon 50",
    "sg:city":"Hotton",
    "sg:classifiers":[
        {
            "category":"Restaurant",
            "type":"Food & Drink"
        }
    ],
    "sg:phone":"+32 84 46 61 86",
    "sg:postcode":"6990",
    "sg:province":"Luxembourg",
    "wof:name":"Le Vieille Demeure",
    "wof:placetype":"venue"
},
  "geometry": {"coordinates":[5.4526572227,50.2657432556],"type":"Point"}
}