{
  "type": "Feature",
  "properties": {
    "iso:country":"BE",
    "sg:address":"Moerdijkbeek West 21",
    "sg:city":"Koekelare",
    "sg:orig_category":"Immobili\u00ebnkantoren",
    "sg:phone":"+32 59 27 36 86",
    "sg:postcode":"8680",
    "sg:province":"West-Vlaanderen",
    "wof:name":"Victoire",
    "wof:placetype":"venue"
},
  "geometry": {"coordinates":[2.9579610825,51.1131095886],"type":"Point"}
}