{
  "type": "Feature",
  "properties": {
    "iso:country":"BE",
    "sg:address":"Rassel 125",
    "sg:city":"Wemmel",
    "sg:orig_category":"Non-Classified Establishments",
    "sg:phone":"+32 2 460 08 94",
    "sg:postcode":"1780",
    "sg:province":"Vlaams-Brabant",
    "wof:name":"Hugo Vleeswaren Bvba",
    "wof:placetype":"venue"
},
  "geometry": {"coordinates":[4.2913899422,50.9085235596],"type":"Point"}
}