{
  "type": "Feature",
  "properties": {
    "iso:country":"BE",
    "sg:address":"Rue Du M\u00e9ridien 80",
    "sg:city":"Bruxelles (saint-josse-ten-noode)",
    "sg:classifiers":[
        {
            "category":"Shopping",
            "subcategory":"Jewelry",
            "type":"Retail Goods"
        }
    ],
    "sg:phone":"+32 2 219 19 29",
    "sg:postcode":"1210",
    "sg:province":"Bruxelles-Capitale",
    "sg:tags":[
        "jeweller",
        "-"
    ],
    "wof:name":"Sinar",
    "wof:placetype":"venue"
},
  "geometry": {"coordinates":[4.3689980507,50.855682373],"type":"Point"}
}