{
  "type": "Feature",
  "properties": {
    "iso:country":"BE",
    "sg:address":"Rue De L'universit\u00e9 45",
    "sg:city":"Li\u00e8ge 1",
    "sg:classifiers":[
        {
            "category":"Professional",
            "subcategory":"Art Services",
            "type":"Services"
        }
    ],
    "sg:phone":"+32 4 223 27 41",
    "sg:postcode":"4000",
    "sg:province":"Li\u00e8ge",
    "sg:tags":[
        "-",
        "valuer"
    ],
    "wof:name":"Bellartes (galerie)",
    "wof:placetype":"venue"
},
  "geometry": {"coordinates":[5.5746068954,50.641330719],"type":"Point"}
}