{
  "type": "Feature",
  "properties": {
    "iso:country":"BE",
    "sg:address":"Chauss\u00c9e De Thuin 171",
    "sg:city":"Anderlues",
    "sg:classifiers":[
        {
            "category":"Personal",
            "subcategory":"Beauty Salon",
            "type":"Services"
        }
    ],
    "sg:phone":"+32 71 52 19 29",
    "sg:postcode":"6150",
    "sg:province":"Hainaut",
    "sg:tags":[
        "de",
        "coiffure"
    ],
    "wof:name":"Coiffure Diminu-tif",
    "wof:placetype":"venue"
},
  "geometry": {"coordinates":[4.284922123,50.3972091675],"type":"Point"}
}