{
  "type": "Feature",
  "properties": {
    "iso:country":"BE",
    "sg:address":"Bredabaan 568",
    "sg:city":"Brasschaat",
    "sg:orig_category":"Alimentation sp\u00e9cialis\u00e9e. Catering and organisation de f\u00eates",
    "sg:phone":"+32 3 653 27 27",
    "sg:postcode":"2930",
    "sg:province":"Antwerpen",
    "wof:name":"Traiteur Lucullus",
    "wof:placetype":"venue"
},
  "geometry": {"coordinates":[4.5050301552,51.3054161072],"type":"Point"}
}