{
  "type": "Feature",
  "properties": {
    "addr:full":"Kwalijkstraat 8 Scherpenheuvel-zichem (zichem) Vlaams-Brabant 3271",
    "addr:housenumber":"8",
    "addr:postcode":"3271",
    "addr:street":"Kwalijkstraat",
    "iso:country":"BE",
    "sg:address":"Kwalijkstraat 8",
    "sg:city":"Scherpenheuvel-zichem (zichem)",
    "sg:orig_category":"Non-Classified Establishments",
    "sg:phone":"+32 13 77 84 84",
    "sg:postcode":"3271",
    "sg:province":"Vlaams-Brabant",
    "wof:name":"E.a.s.",
    "wof:placetype":"venue"
},
  "geometry": {"coordinates":[4.9865460396,50.9946365356],"type":"Point"}
}