{
  "type": "Feature",
  "properties": {
    "addr:full":"Rijmenamsesteenweg 99 Haacht Vlaams-Brabant 3150",
    "addr:housenumber":"99",
    "addr:postcode":"3150",
    "addr:street":"Rijmenamsesteenweg",
    "iso:country":"BE",
    "sg:address":"Rijmenamsesteenweg 99",
    "sg:city":"Haacht",
    "sg:classifiers":[
        {
            "category":"Professional",
            "subcategory":"Management & Consulting",
            "type":"Services"
        }
    ],
    "sg:phone":"+32 16 60 09 41",
    "sg:postcode":"3150",
    "sg:province":"Vlaams-Brabant",
    "sg:tags":[
        "consultant"
    ],
    "wof:name":"Evec Consulting Bvba",
    "wof:placetype":"venue"
},
  "geometry": {"coordinates":[4.6207380295,50.9803085327],"type":"Point"}
}