{
  "type": "Feature",
  "properties": {
    "iso:country":"BE",
    "sg:address":"Wittewalle 71",
    "sg:city":"Gent",
    "sg:orig_category":"Zuivelproducten",
    "sg:phone":"+32 9 251 21 07",
    "sg:postcode":"9000",
    "sg:province":"Oost-Vlaanderen",
    "wof:name":"Gerard Lammens",
    "wof:placetype":"venue"
},
  "geometry": {"coordinates":[3.7846300602,51.1087303162],"type":"Point"}
}