{
  "type": "Feature",
  "properties": {
    "iso:country":"BE",
    "sg:address":"De Hoek 12",
    "sg:city":"Ravels",
    "sg:orig_category":"Woningbouw",
    "sg:phone":"+32 14 65 87 88",
    "sg:postcode":"2381",
    "sg:province":"Antwerpen",
    "wof:name":"Marc Van Den Ackerveken",
    "wof:placetype":"venue"
},
  "geometry": {"coordinates":[4.9934921265,51.4052009583],"type":"Point"}
}