{
  "type": "Feature",
  "properties": {
    "iso:country":"BE",
    "sg:address":"Antoine Br\u00e9artstraat 13-15",
    "sg:city":"Knokke-heist (knokke)",
    "sg:classifiers":[
        {
            "category":"Arts & Performance",
            "subcategory":"Art Gallery",
            "type":"Entertainment"
        }
    ],
    "sg:phone":"+32 50 60 29 62",
    "sg:postcode":"8300",
    "sg:province":"West-Vlaanderen",
    "wof:name":"Multipel 13 Bvba",
    "wof:placetype":"venue"
},
  "geometry": {"coordinates":[3.287694931,51.3467254639],"type":"Point"}
}