{
  "type": "Feature",
  "properties": {
    "iso:country":"BE",
    "sg:address":"Gasthuisstraat 14",
    "sg:city":"Geel",
    "sg:classifiers":[
        {
            "category":"Restaurant",
            "type":"Food & Drink"
        }
    ],
    "sg:phone":"+32 14 58 93 42",
    "sg:postcode":"2440",
    "sg:province":"Antwerpen",
    "wof:name":"T Hofke",
    "wof:placetype":"venue"
},
  "geometry": {"coordinates":[4.9966011047,51.1592521667],"type":"Point"}
}