{
  "type": "Feature",
  "properties": {
    "iso:country":"BE",
    "sg:address":"Hoogstraat 9",
    "sg:city":"Assenede",
    "sg:classifiers":[
        {
            "category":"Professional",
            "subcategory":"Testing Lab",
            "type":"Services"
        }
    ],
    "sg:phone":"+32 9 344 67 78",
    "sg:postcode":"9960",
    "sg:province":"Oost-Vlaanderen",
    "sg:tags":[
        "chemist"
    ],
    "wof:name":"Dhanens A",
    "wof:placetype":"venue"
},
  "geometry": {"coordinates":[3.7541470528,51.2281532288],"type":"Point"}
}