{
  "type": "Feature",
  "properties": {
    "addr:full":"Zwembadstraat 84 Gent Oost-Vlaanderen 9032",
    "addr:housenumber":"84",
    "addr:postcode":"9032",
    "addr:street":"Zwembadstraat;Oost-Vlaanderen",
    "iso:country":"BE",
    "sg:address":"Zwembadstraat 84",
    "sg:city":"Gent",
    "sg:orig_category":"Landmeters",
    "sg:phone":"+32 9 253 58 21",
    "sg:postcode":"9032",
    "sg:province":"Oost-Vlaanderen",
    "wof:name":"Herman D'hondt",
    "wof:placetype":"venue"
},
  "geometry": {"coordinates":[3.7057299614,51.0896453857],"type":"Point"}
}