{
  "type": "Feature",
  "properties": {
    "addr:full":"Kauwekijnstraat 19 Ieper West-Vlaanderen 8900",
    "addr:housenumber":"19",
    "addr:postcode":"8900",
    "addr:street":"Kauwekijnstraat",
    "iso:country":"BE",
    "sg:address":"Kauwekijnstraat 19",
    "sg:city":"Ieper",
    "sg:classifiers":[
        {
            "category":"Cafe",
            "type":"Food & Drink"
        }
    ],
    "sg:phone":"+32 57 21 96 43",
    "sg:postcode":"8900",
    "sg:province":"West-Vlaanderen",
    "sg:tags":[
        "caf\u00e9s"
    ],
    "wof:name":"Marleen Maerten",
    "wof:placetype":"venue"
},
  "geometry": {"coordinates":[2.8899619579,50.8528518677],"type":"Point"}
}