{
  "type": "Feature",
  "properties": {
    "addr:full":"Industrielaan 1a Torhout Bruxelles-Capitale 1120",
    "addr:housenumber":"1a",
    "addr:postcode":"1120",
    "addr:street":"Industrielaan",
    "iso:country":"BE",
    "sg:address":"Industrielaan 1a",
    "sg:city":"Torhout",
    "sg:orig_category":"Bloemen and planten Bloemen and planten Gh",
    "sg:phone":"+32 50 22 22 98",
    "sg:postcode":"1120",
    "sg:province":"Bruxelles-Capitale",
    "wof:name":"Het Groenatelier",
    "wof:placetype":"venue"
},
  "geometry": {"coordinates":[3.1043949127,51.0698928833],"type":"Point"}
}