{
  "type": "Feature",
  "properties": {
    "addr:full":"Sint-hubertstraat 327 Deinze (petegem-aan-de-leie) Oost-Vlaanderen 9800",
    "addr:housenumber":"327",
    "addr:postcode":"9800",
    "addr:street":"Oost-Vlaanderen",
    "iso:country":"BE",
    "sg:address":"Sint-hubertstraat 327",
    "sg:city":"Deinze (petegem-aan-de-leie)",
    "sg:classifiers":[
        {
            "category":"Retail",
            "subcategory":"Animal Services",
            "type":"Services"
        }
    ],
    "sg:phone":"+32 473 63 99 98",
    "sg:postcode":"9800",
    "sg:province":"Oost-Vlaanderen",
    "sg:tags":[
        "grooming",
        "-",
        "dog"
    ],
    "wof:name":"Pascandy",
    "wof:placetype":"venue"
},
  "geometry": {"coordinates":[3.5132799149,50.9624443054],"type":"Point"}
}