{
  "type": "Feature",
  "properties": {
    "iso:country":"BE",
    "sg:address":"Adolf Buylstraat 33",
    "sg:city":"Oostende",
    "sg:orig_category":"Journaux. Fournitures de bureau. Souvenirs and objets artisanaux. Tabac. Librairies",
    "sg:phone":"+32 59 70 27 23",
    "sg:postcode":"8400",
    "sg:province":"West-Vlaanderen",
    "wof:name":"Press Shop",
    "wof:placetype":"venue"
},
  "geometry": {"coordinates":[2.9150021076,51.2313194275],"type":"Point"}
}