{
  "type": "Feature",
  "properties": {
    "addr:full":"Nekkerspoelstraat 449 Mechelen Antwerpen 2800",
    "addr:housenumber":"449",
    "addr:postcode":"2800",
    "addr:street":"Nekkerspoelstraat",
    "iso:country":"BE",
    "sg:address":"Nekkerspoelstraat 449",
    "sg:city":"Mechelen",
    "sg:orig_category":"Electrom\u00e9nager, t\u00e9l\u00e9visions and radios",
    "sg:phone":"+32 15 55 62 73",
    "sg:postcode":"2800",
    "sg:province":"Antwerpen",
    "wof:name":"Huis Television",
    "wof:placetype":"venue"
},
  "geometry": {"coordinates":[4.5067000389,51.0334014893],"type":"Point"}
}