{
  "type": "Feature",
  "properties": {
    "iso:country":"BE",
    "sg:address":"Kerkstraat 30",
    "sg:city":"Vosselaar",
    "sg:orig_category":"Traitements param\u00e9dicaux",
    "sg:phone":"+32 14 61 31 01",
    "sg:postcode":"2350",
    "sg:province":"Antwerpen",
    "wof:name":"A. Hendrickx",
    "wof:placetype":"venue"
},
  "geometry": {"coordinates":[4.890542984,51.3135490417],"type":"Point"}
}