{
  "type": "Feature",
  "properties": {
    "addr:full":"Rue Marionsonnet 5 Donceel (haneffe) Li\u00e8ge 4357",
    "addr:housenumber":"5",
    "addr:postcode":"4357",
    "addr:street":"Rue Marionsonnet;Haneffe",
    "iso:country":"BE",
    "sg:address":"Rue Marionsonnet 5",
    "sg:city":"Donceel (haneffe)",
    "sg:classifiers":[
        {
            "category":"Health Services",
            "subcategory":"Nursing And Care Facility",
            "type":"Services"
        }
    ],
    "sg:phone":"+32 4 259 59 50",
    "sg:postcode":"4357",
    "sg:province":"Li\u00e8ge",
    "sg:tags":[
        "home"
    ],
    "wof:name":"Delcommune S",
    "wof:placetype":"venue"
},
  "geometry": {"coordinates":[5.3245491982,50.6378135681],"type":"Point"}
}