{
  "type": "Feature",
  "properties": {
    "addr:full":"Avenue Van Volxem 204 Vorst Bruxelles-Capitale 1190",
    "addr:housenumber":"204",
    "addr:postcode":"1190",
    "addr:street":"Avenue Van Volxem",
    "iso:country":"BE",
    "sg:address":"Avenue Van Volxem 204",
    "sg:city":"Vorst",
    "sg:orig_category":"M\u00e9decins and sp\u00e9cialistes",
    "sg:phone":"+32 2 343 09 64",
    "sg:postcode":"1190",
    "sg:province":"Bruxelles-Capitale",
    "wof:name":"Van Lul L",
    "wof:placetype":"venue"
},
  "geometry": {"coordinates":[4.3259367943,50.8197517395],"type":"Point"}
}