{
  "type": "Feature",
  "properties": {
    "addr:full":"Sint-sebastiaanstraat 23 Oostende West-Vlaanderen 8400",
    "addr:housenumber":"23",
    "addr:postcode":"8400",
    "addr:street":"Sint-Sebastiaanstraat",
    "iso:country":"BE",
    "sg:address":"Sint-sebastiaanstraat 23",
    "sg:city":"Oostende",
    "sg:classifiers":[
        {
            "category":"Wholesale",
            "subcategory":"Sporting Goods",
            "type":"Manufacturing & Wholesale Goods"
        }
    ],
    "sg:phone":"+32 59 80 55 26",
    "sg:postcode":"8400",
    "sg:province":"West-Vlaanderen",
    "sg:tags":[
        "sport-",
        "kampeermateriaal"
    ],
    "wof:name":"Ghyselen H.",
    "wof:placetype":"venue"
},
  "geometry": {"coordinates":[2.9160509109,51.231300354],"type":"Point"}
}