{
  "type": "Feature",
  "properties": {
    "iso:country":"BE",
    "sg:address":"Esdoornlaan 1",
    "sg:city":"Affligem",
    "sg:orig_category":"Artistes ind\u00e9pendants",
    "sg:phone":"+32 53 67 32 65",
    "sg:postcode":"1790",
    "sg:province":"Vlaams-Brabant",
    "wof:name":"Patrick Van Craenenbroeck",
    "wof:placetype":"venue"
},
  "geometry": {"coordinates":[4.1079821587,50.8902168274],"type":"Point"}
}