{
  "type": "Feature",
  "properties": {
    "iso:country":"BE",
    "sg:address":"Avenue Des Casernes 41",
    "sg:city":"Etterbeek",
    "sg:orig_category":"Editeurs de journaux. Editeurs de revues and p\u00e9riodiques",
    "sg:phone":"+32 2 646 27 40",
    "sg:postcode":"1040",
    "sg:province":"Bruxelles-Capitale",
    "wof:name":"Alain Renier & Cie",
    "wof:placetype":"venue"
},
  "geometry": {"coordinates":[4.3900880814,50.8278694153],"type":"Point"}
}