{
  "type": "Feature",
  "properties": {
    "addr:full":"Place Coronmeuse 3-31 Herstal Li\u00e8ge 4040",
    "addr:housenumber":"3-31",
    "addr:postcode":"4040",
    "addr:street":"Place Coronmeuse",
    "iso:country":"BE",
    "sg:address":"Place Coronmeuse 3-31",
    "sg:city":"Herstal",
    "sg:classifiers":[
        {
            "category":"Health Services",
            "subcategory":"Health Practitioner",
            "type":"Services"
        }
    ],
    "sg:phone":"+32 4 264 50 06",
    "sg:postcode":"4040",
    "sg:province":"Li\u00e8ge",
    "sg:tags":[
        "physiotherapist"
    ],
    "wof:name":"Lambrecht Leopold",
    "wof:placetype":"venue"
},
  "geometry": {"coordinates":[5.6127200127,50.6552696228],"type":"Point"}
}