{
  "type": "Feature",
  "properties": {
    "iso:country":"BE",
    "sg:address":"Sentier De La Limite 80",
    "sg:city":"Charleroi",
    "sg:orig_category":"Woningbouw",
    "sg:phone":"+32 71 41 86 92",
    "sg:postcode":"6060",
    "sg:province":"Hainaut",
    "wof:name":"Sarty & Fils",
    "wof:placetype":"venue"
},
  "geometry": {"coordinates":[4.4880981445,50.4251937866],"type":"Point"}
}