{
  "type": "Feature",
  "properties": {
    "iso:country":"BE",
    "sg:address":"Koning Albertstraat 24",
    "sg:city":"Dendermonde (sint-gillis-bij-dendermonde)",
    "sg:classifiers":[
        {
            "category":"Autos & Motor Vehicles",
            "subcategory":"Auto Supplies",
            "type":"Retail Goods"
        }
    ],
    "sg:phone":"+32 52 21 24 23",
    "sg:postcode":"9200",
    "sg:province":"Oost-Vlaanderen",
    "sg:tags":[
        "automobile",
        "-",
        "radio"
    ],
    "wof:name":"Verougstraete Autoparts",
    "wof:placetype":"venue"
},
  "geometry": {"coordinates":[4.1137981415,51.0178413391],"type":"Point"}
}