{
  "type": "Feature",
  "properties": {
    "iso:country":"BE",
    "sg:address":"Rue Verbist 66",
    "sg:city":"Sint-joost-ten-node/saint-josse-ten-noode",
    "sg:orig_category":"Pain, p\u00e2tisseries and confiseries",
    "sg:phone":"+32 2 218 74 46",
    "sg:postcode":"1210",
    "sg:province":"Bruxelles-Capitale",
    "wof:name":"P\u00c2tisserie No\u00cbl",
    "wof:placetype":"venue"
},
  "geometry": {"coordinates":[4.3786802292,50.851360321],"type":"Point"}
}