{
  "type": "Feature",
  "properties": {
    "iso:country":"BE",
    "sg:address":"Hooiweg 89",
    "sg:city":"Genk",
    "sg:classifiers":[
        {
            "category":"Personal",
            "subcategory":"Beauty Salon",
            "type":"Services"
        }
    ],
    "sg:phone":"+32 89 35 76 43",
    "sg:postcode":"3600",
    "sg:province":"Limburg",
    "sg:tags":[
        "child",
        "-",
        "hairdressing"
    ],
    "wof:name":"Teresa",
    "wof:placetype":"venue"
},
  "geometry": {"coordinates":[5.5042471886,50.9512405396],"type":"Point"}
}