{
  "type": "Feature",
  "properties": {
    "iso:country":"BE",
    "sg:address":"Hofkwartier 3",
    "sg:city":"Buggenhout",
    "sg:orig_category":"Fruitteelt Groenten and fruit Gh",
    "sg:phone":"+32 52 35 66 42",
    "sg:postcode":"9255",
    "sg:province":"Oost-Vlaanderen",
    "wof:name":"Fa. De Ridder",
    "wof:placetype":"venue"
},
  "geometry": {"coordinates":[4.1865701675,51.0030288696],"type":"Point"}
}