{
  "type": "Feature",
  "properties": {
    "iso:country":"BE",
    "sg:address":"Eikelstraat 10",
    "sg:city":"Lier",
    "sg:classifiers":[
        {
            "category":"Bars & Pubs",
            "type":"Food & Drink"
        }
    ],
    "sg:phone":"+32 3 480 74 83",
    "sg:postcode":"2500",
    "sg:province":"Antwerpen",
    "wof:name":"Caf\u00c9 Bananas",
    "wof:placetype":"venue"
},
  "geometry": {"coordinates":[4.569275856,51.1305084229],"type":"Point"}
}