{
  "type": "Feature",
  "properties": {
    "addr:full":"Neerheide 8 Destelbergen Oost-Vlaanderen 9070",
    "addr:housenumber":"8",
    "addr:postcode":"9070",
    "addr:street":"Neerheide",
    "iso:country":"BE",
    "sg:address":"Neerheide 8",
    "sg:city":"Destelbergen",
    "sg:orig_category":"Agences de publicit\u00e9",
    "sg:phone":"+32 9 231 40 91",
    "sg:postcode":"9070",
    "sg:province":"Oost-Vlaanderen",
    "wof:name":"Freelance Taaldienst",
    "wof:placetype":"venue"
},
  "geometry": {"coordinates":[3.8094029427,51.0266304016],"type":"Point"}
}