{
  "type": "Feature",
  "properties": {
    "iso:country":"BE",
    "sg:address":"Pr\u00c9 Lorette 1",
    "sg:city":"Malmedy",
    "sg:classifiers":[
        {
            "category":"Farming",
            "subcategory":"Fish & Marine Products",
            "type":"Manufacturing & Wholesale Goods"
        }
    ],
    "sg:phone":"+32 80 57 02 85",
    "sg:postcode":"4960",
    "sg:province":"Li\u00e8ge",
    "sg:tags":[
        "schaaldierenkwekers",
        "vis-"
    ],
    "wof:name":"Simon-reuter",
    "wof:placetype":"venue"
},
  "geometry": {"coordinates":[6.0583162308,50.3773918152],"type":"Point"}
}