{
  "type": "Feature",
  "properties": {
    "addr:full":"Rue De France 29 Charleroi Hainaut 6000",
    "addr:housenumber":"29",
    "addr:postcode":"6000",
    "addr:street":"Rue De France;Hainaut",
    "iso:country":"BE",
    "sg:address":"Rue De France 29",
    "sg:city":"Charleroi",
    "sg:orig_category":"Sportclubs Sportterreinen and installaties behalve sportcentra Technisch and beroeps secundair onder",
    "sg:phone":"+32 71 31 31 03",
    "sg:postcode":"6000",
    "sg:province":"Hainaut",
    "wof:name":"Epseco",
    "wof:placetype":"venue"
},
  "geometry": {"coordinates":[4.4416761398,50.4108314514],"type":"Point"}
}