{
  "type": "Feature",
  "properties": {
    "addr:full":"Voetbalstraat 25 Zoersel Antwerpen 2980",
    "addr:housenumber":"25",
    "addr:postcode":"2980",
    "addr:street":"Voetbalstraat",
    "iso:country":"BE",
    "sg:address":"Voetbalstraat 25",
    "sg:city":"Zoersel",
    "sg:orig_category":"Schoonmaakbedrijven and ongediertebestrijding",
    "sg:phone":"+32 3 312 45 35",
    "sg:postcode":"2980",
    "sg:province":"Antwerpen",
    "wof:name":"Nicolas Van Ingelghem",
    "wof:placetype":"venue"
},
  "geometry": {"coordinates":[4.7138471603,51.2755126953],"type":"Point"}
}