{
  "type": "Feature",
  "properties": {
    "addr:full":"Rue Du Ch\u00e2teau 64 Courcelles (trazegnies) Hainaut 6183",
    "addr:housenumber":"64",
    "addr:postcode":"6183",
    "addr:street":"Rue Du Cha\u0302Teau",
    "iso:country":"BE",
    "sg:address":"Rue Du Ch\u00e2teau 64",
    "sg:city":"Courcelles (trazegnies)",
    "sg:classifiers":[
        {
            "category":"Autos & Motor Vehicles",
            "subcategory":"Auto Supplies",
            "type":"Retail Goods"
        }
    ],
    "sg:phone":"+32 71 45 56 11",
    "sg:postcode":"6183",
    "sg:province":"Hainaut",
    "sg:tags":[
        "cylinder",
        "jack"
    ],
    "wof:name":"Ateliers Marcel Vilain & Fils",
    "wof:placetype":"venue"
},
  "geometry": {"coordinates":[4.3289499283,50.4606895447],"type":"Point"}
}