{
  "type": "Feature",
  "properties": {
    "iso:country":"BE",
    "sg:address":"Avenue Eug\u00e8ne Mascaux 134",
    "sg:city":"Charleroi (marcinelle)",
    "sg:classifiers":[
        {
            "category":"Home & Garden",
            "subcategory":"Home Furnishings",
            "type":"Retail Goods"
        }
    ],
    "sg:phone":"+32 71 36 18 50",
    "sg:postcode":"6001",
    "sg:province":"Hainaut",
    "sg:tags":[
        "curtain",
        "-",
        "fixture"
    ],
    "wof:name":"Galeries Masset Sprl",
    "wof:placetype":"venue"
},
  "geometry": {"coordinates":[4.4436569214,50.3964996338],"type":"Point"}
}