{
  "type": "Feature",
  "properties": {
    "iso:country":"BE",
    "sg:address":"Koekelarestraat 95",
    "sg:city":"Kortemark",
    "sg:orig_category":"Woningbouw",
    "sg:phone":"+32 51 58 07 00",
    "sg:postcode":"8610",
    "sg:province":"West-Vlaanderen",
    "wof:name":"Patrick Bolle",
    "wof:placetype":"venue"
},
  "geometry": {"coordinates":[3.0178599358,51.0503807068],"type":"Point"}
}