{
  "type": "Feature",
  "properties": {
    "iso:country":"BE",
    "sg:address":"Albrecht Ardevelstraat 9",
    "sg:city":"Halle",
    "sg:orig_category":"R\u00e9alisation de programmes and logiciels",
    "sg:phone":"+32 2 360 11 78",
    "sg:postcode":"1500",
    "sg:province":"Vlaams-Brabant",
    "wof:name":"Novartsoft",
    "wof:placetype":"venue"
},
  "geometry": {"coordinates":[4.2312750816,50.7346801758],"type":"Point"}
}