{
  "type": "Feature",
  "properties": {
    "addr:full":"Kasteeldreef 16 Sint-amands Antwerpen 2890",
    "addr:housenumber":"16",
    "addr:postcode":"2890",
    "addr:street":"Kasteeldreef",
    "iso:country":"BE",
    "sg:address":"Kasteeldreef 16",
    "sg:city":"Sint-amands",
    "sg:orig_category":"Fleurs and plantes",
    "sg:phone":"+32 52 33 31 44",
    "sg:postcode":"2890",
    "sg:province":"Antwerpen",
    "wof:name":"Huis Vleminckx",
    "wof:placetype":"venue"
},
  "geometry": {"coordinates":[4.2594819069,51.0431289673],"type":"Point"}
}