{
  "type": "Feature",
  "properties": {
    "addr:full":"Gransveldestraat 37 Wetteren Oost-Vlaanderen 9230",
    "addr:housenumber":"37",
    "addr:postcode":"9230",
    "addr:street":"Gransveldestraat",
    "iso:country":"BE",
    "sg:address":"Gransveldestraat 37",
    "sg:city":"Wetteren",
    "sg:classifiers":[
        {
            "category":"Professional",
            "subcategory":"Management & Consulting",
            "type":"Services"
        }
    ],
    "sg:phone":"+32 9 324 01 03",
    "sg:postcode":"9230",
    "sg:province":"Oost-Vlaanderen",
    "sg:tags":[
        "-",
        "processing",
        "data",
        "consultant"
    ],
    "wof:name":"Pc Tech",
    "wof:placetype":"venue"
},
  "geometry": {"coordinates":[3.8719170094,51.0151939392],"type":"Point"}
}