{
  "type": "Feature",
  "properties": {
    "addr:full":"Bessemerstraat 258 Lanaken Limburg 3620",
    "addr:housenumber":"258",
    "addr:postcode":"3620",
    "addr:street":"Bessemerstraat",
    "iso:country":"BE",
    "sg:address":"Bessemerstraat 258",
    "sg:city":"Lanaken",
    "sg:classifiers":[
        {
            "category":"Bakery",
            "type":"Food & Drink"
        }
    ],
    "sg:phone":"+32 89 71 31 40",
    "sg:postcode":"3620",
    "sg:province":"Limburg",
    "sg:tags":[
        "confectioner",
        "baker"
    ],
    "wof:name":"L'espoir",
    "wof:placetype":"venue"
},
  "geometry": {"coordinates":[5.6421079636,50.8965454102],"type":"Point"}
}