{
  "type": "Feature",
  "properties": {
    "addr:full":"Kerkplein 17 Wingene West-Vlaanderen 8750",
    "addr:housenumber":"17",
    "addr:postcode":"8750",
    "addr:street":"Kerkplein",
    "iso:country":"BE",
    "sg:address":"Kerkplein 17",
    "sg:city":"Wingene",
    "sg:orig_category":"Diverse kredietdiensten",
    "sg:postcode":"8750",
    "sg:province":"West-Vlaanderen",
    "wof:name":"Bancontact-mister Cash",
    "wof:placetype":"venue"
},
  "geometry": {"coordinates":[3.2777199745,51.057888031],"type":"Point"}
}