{
  "type": "Feature",
  "properties": {
    "iso:country":"BE",
    "sg:address":"Poperingestraat 38",
    "sg:city":"Heuvelland",
    "sg:orig_category":"Eleveurs de bovins",
    "sg:phone":"+32 57 44 46 41",
    "sg:postcode":"8954",
    "sg:province":"West-Vlaanderen",
    "wof:name":"Joseph Rousere",
    "wof:placetype":"venue"
},
  "geometry": {"coordinates":[2.7313148975,50.8226890564],"type":"Point"}
}