{
  "type": "Feature",
  "properties": {
    "addr:full":"Kapelwijk 69 Waasmunster Oost-Vlaanderen 9250",
    "addr:housenumber":"69",
    "addr:postcode":"9250",
    "addr:street":"Kapelwijk",
    "iso:country":"BE",
    "sg:address":"Kapelwijk 69",
    "sg:city":"Waasmunster",
    "sg:classifiers":[
        {
            "category":"Health Services",
            "subcategory":"Nursing And Care Facility",
            "type":"Services"
        }
    ],
    "sg:phone":"+32 52 46 09 34",
    "sg:postcode":"9250",
    "sg:province":"Oost-Vlaanderen",
    "sg:tags":[
        "home"
    ],
    "wof:name":"H.u.c.h. Bvba",
    "wof:placetype":"venue"
},
  "geometry": {"coordinates":[4.129983902,51.1165542603],"type":"Point"}
}