{
  "type": "Feature",
  "properties": {
    "iso:country":"BE",
    "sg:address":"Prolongement De L'abbaye",
    "sg:city":"Herstal",
    "sg:classifiers":[
        {
            "category":"Wholesale",
            "subcategory":"Construction Materials",
            "type":"Manufacturing & Wholesale Goods"
        }
    ],
    "sg:postcode":"4040",
    "sg:province":"Li\u00e8ge",
    "sg:tags":[
        "insulation",
        "acoustical"
    ],
    "wof:name":"Plastiques Manufactures Sa",
    "wof:placetype":"venue"
},
  "geometry": {"coordinates":[5.6317949295,50.6926651001],"type":"Point"}
}