{
  "type": "Feature",
  "properties": {
    "addr:full":"Avenue De La Croix Du Sud 27 Waterloo Brabant Wallon 1410",
    "addr:housenumber":"27",
    "addr:postcode":"1410",
    "addr:street":"Avenue De La Croix Du Sud",
    "iso:country":"BE",
    "sg:address":"Avenue De La Croix Du Sud 27",
    "sg:city":"Waterloo",
    "sg:classifiers":[
        {
            "category":"Insurance",
            "subcategory":"Insurance Agent",
            "type":"Services"
        }
    ],
    "sg:phone":"+32 2 354 11 76",
    "sg:postcode":"1410",
    "sg:province":"Brabant Wallon",
    "sg:tags":[
        "broker"
    ],
    "wof:name":"Verniers Assureurs Conseils Sprl",
    "wof:placetype":"venue"
},
  "geometry": {"coordinates":[4.41959095,50.7007827759],"type":"Point"}
}