{
  "type": "Feature",
  "properties": {
    "addr:full":"Rue G\u00c9n\u00c9ral Wangerm\u00c9e 22 Etterbeek Bruxelles-Capitale 1040",
    "addr:housenumber":"22",
    "addr:postcode":"1040",
    "addr:street":"Rue Ge\u0301Ne\u0301Ral Wangerme\u0301E",
    "iso:country":"BE",
    "sg:address":"Rue G\u00c9n\u00c9ral Wangerm\u00c9e 22",
    "sg:city":"Etterbeek",
    "sg:orig_category":"Travaux de finition and nettoyage de b\u00e2timents. Constructions r\u00e9sidentielles sp\u00e9cifiques",
    "sg:phone":"+32 2 734 81 03",
    "sg:postcode":"1040",
    "sg:province":"Bruxelles-Capitale",
    "wof:name":"Colymit",
    "wof:placetype":"venue"
},
  "geometry": {"coordinates":[4.3938231468,50.8335075378],"type":"Point"}
}