{
  "type": "Feature",
  "properties": {
    "iso:country":"BE",
    "sg:address":"Landbeekstraat 32",
    "sg:city":"Meise",
    "sg:orig_category":"Mutualities",
    "sg:phone":"+32 2 269 79 64",
    "sg:postcode":"1860",
    "sg:province":"Vlaams-Brabant",
    "wof:name":"Vlaams Neutraal Ziekenfonds",
    "wof:placetype":"venue"
},
  "geometry": {"coordinates":[4.3220901489,50.9381904602],"type":"Point"}
}