{
  "type": "Feature",
  "properties": {
    "iso:country":"BE",
    "sg:address":"Avenue Montjoie 62",
    "sg:city":"Ukkel/uccle",
    "sg:orig_category":"M\u00e9decins and sp\u00e9cialistes",
    "sg:phone":"+32 2 374 72 31",
    "sg:postcode":"1180",
    "sg:province":"Bruxelles-Capitale",
    "wof:name":"Michel Marin",
    "wof:placetype":"venue"
},
  "geometry": {"coordinates":[4.3646969795,50.8098640442],"type":"Point"}
}