{
  "type": "Feature",
  "properties": {
    "iso:country":"BE",
    "sg:address":"Rue Du Progr\u00e8s 7 Box 7",
    "sg:city":"Wavre",
    "sg:classifiers":[
        {
            "category":"Professional",
            "subcategory":"Lawyer & Legal Services",
            "type":"Services"
        }
    ],
    "sg:phone":"+32 10 24 81 03",
    "sg:postcode":"1300",
    "sg:province":"Brabant Wallon",
    "wof:name":"Marghem Fabienne",
    "wof:placetype":"venue"
},
  "geometry": {"coordinates":[4.6103568077,50.7148895264],"type":"Point"}
}