{
  "type": "Feature",
  "properties": {
    "addr:full":"Burg Reuland 128 Burg-reuland Li\u00e8ge 4790",
    "addr:housenumber":"128",
    "addr:postcode":"4790",
    "addr:street":"Burg Reuland",
    "iso:country":"BE",
    "sg:address":"Burg Reuland 128",
    "sg:city":"Burg-reuland",
    "sg:classifiers":[
        {
            "category":"Bakery",
            "type":"Food & Drink"
        }
    ],
    "sg:phone":"+32 80 32 91 40",
    "sg:postcode":"4790",
    "sg:province":"Li\u00e8ge",
    "sg:tags":[
        "confectioner",
        "baker"
    ],
    "wof:name":"Richter H-g",
    "wof:placetype":"venue"
},
  "geometry": {"coordinates":[6.1315770149,50.1943702698],"type":"Point"}
}