{
  "type": "Feature",
  "properties": {
    "iso:country":"BE",
    "sg:address":"Tollaan 77",
    "sg:city":"Zaventem",
    "sg:orig_category":"Mat\u00e9riaux de construction Gr",
    "sg:phone":"+32 2 725 55 20",
    "sg:postcode":"1932",
    "sg:province":"Vlaams-Brabant",
    "wof:name":"Sphinx Gustavsberg Belgium",
    "wof:placetype":"venue"
},
  "geometry": {"coordinates":[4.4307599068,50.8610038757],"type":"Point"}
}