{
  "type": "Feature",
  "properties": {
    "addr:full":"Driesstraat 17 Avelgem West-Vlaanderen 8580",
    "addr:housenumber":"17",
    "addr:postcode":"8580",
    "addr:street":"Driesstraat",
    "iso:country":"BE",
    "sg:address":"Driesstraat 17",
    "sg:city":"Avelgem",
    "sg:classifiers":[
        {
            "category":"Arena",
            "subcategory":"Sports Club",
            "type":"Entertainment"
        }
    ],
    "sg:phone":"+32 56 64 83 31",
    "sg:postcode":"8580",
    "sg:province":"West-Vlaanderen",
    "sg:tags":[
        "de"
    ],
    "wof:name":"Karat\u00c9 Do",
    "wof:placetype":"venue"
},
  "geometry": {"coordinates":[3.4410181046,50.7782669067],"type":"Point"}
}