{
  "type": "Feature",
  "properties": {
    "addr:full":"Avenue A.j. Slegers 158b4 Sint-lambrechts-woluwe/woluwe-saint-lambert Bruxelles-Capitale 1200",
    "addr:housenumber":"158b4",
    "addr:postcode":"1200",
    "addr:street":"Avenue A.J. Slegers",
    "iso:country":"BE",
    "sg:address":"Avenue A.j. Slegers 158b4",
    "sg:city":"Sint-lambrechts-woluwe/woluwe-saint-lambert",
    "sg:orig_category":"Experts-comptables",
    "sg:phone":"+32 2 762 23 11",
    "sg:postcode":"1200",
    "sg:province":"Bruxelles-Capitale",
    "wof:name":"Louise Allegoet",
    "wof:placetype":"venue"
},
  "geometry": {"coordinates":[4.4220981598,50.8407669067],"type":"Point"}
}