{
  "type": "Feature",
  "properties": {
    "addr:full":"Sint-truidersteenweg 212 Tongeren Limburg 3700",
    "addr:housenumber":"212",
    "addr:postcode":"3700",
    "addr:street":"Sint-Truidersteenweg",
    "iso:country":"BE",
    "sg:address":"Sint-truidersteenweg 212",
    "sg:city":"Tongeren",
    "sg:orig_category":"Stations-service and carburants. D\u00e9taillants en pi\u00e8ces and accessoires de voitures",
    "sg:phone":"+32 12 23 44 54",
    "sg:postcode":"3700",
    "sg:province":"Limburg",
    "wof:name":"Jet",
    "wof:placetype":"venue"
},
  "geometry": {"coordinates":[5.4416999817,50.77684021],"type":"Point"}
}