{
  "type": "Feature",
  "properties": {
    "iso:country":"BE",
    "sg:address":"Rue Des Armuriers 31",
    "sg:city":"Li\u00c8ge",
    "sg:orig_category":"Openbare veiligheid",
    "sg:phone":"+32 4 227 34 75",
    "sg:postcode":"4000",
    "sg:province":"Li\u00e8ge",
    "wof:name":"Police F\u00c9d\u00c9rale",
    "wof:placetype":"venue"
},
  "geometry": {"coordinates":[5.5963349342,50.6497116089],"type":"Point"}
}