{
  "type": "Feature",
  "properties": {
    "addr:full":"Boterbloemlaan 17 Zoersel Antwerpen 2980",
    "addr:housenumber":"17",
    "addr:postcode":"2980",
    "addr:street":"Boterbloemlaan",
    "iso:country":"BE",
    "sg:address":"Boterbloemlaan 17",
    "sg:city":"Zoersel",
    "sg:orig_category":"Instituts de beaut\u00e9",
    "sg:phone":"+32 3 383 26 94",
    "sg:postcode":"2980",
    "sg:province":"Antwerpen",
    "wof:name":"Bob Van Beemen",
    "wof:placetype":"venue"
},
  "geometry": {"coordinates":[4.713435173,51.269985199],"type":"Point"}
}