{
  "type": "Feature",
  "properties": {
    "iso:country":"BE",
    "sg:address":"Koningsbergweg 81",
    "sg:city":"Zonhoven",
    "sg:orig_category":"M\u00e9decines alternatives",
    "sg:phone":"+32 11 81 21 61",
    "sg:postcode":"3520",
    "sg:province":"Limburg",
    "wof:name":"J. Moors",
    "wof:placetype":"venue"
},
  "geometry": {"coordinates":[5.4129161835,50.9971504211],"type":"Point"}
}