{
  "type": "Feature",
  "properties": {
    "addr:full":"Industriepark-west 75 Sint-niklaas Oost-Vlaanderen 9100",
    "addr:housenumber":"75",
    "addr:postcode":"9100",
    "addr:street":"Industriepark-West",
    "iso:country":"BE",
    "sg:address":"Industriepark-west 75",
    "sg:city":"Sint-niklaas",
    "sg:classifiers":[
        {
            "category":"Professional",
            "subcategory":"Computer Services",
            "type":"Services"
        }
    ],
    "sg:phone":"+32 3 780 30 02",
    "sg:postcode":"9100",
    "sg:province":"Oost-Vlaanderen",
    "sg:tags":[
        "-",
        "processing",
        "data",
        "software"
    ],
    "wof:name":"Invenso",
    "wof:placetype":"venue"
},
  "geometry": {"coordinates":[4.1614232063,51.1419754028],"type":"Point"}
}