{
  "type": "Feature",
  "properties": {
    "iso:country":"BE",
    "sg:address":"Lobelialaan 2",
    "sg:city":"Wachtebeke",
    "sg:classifiers":[
        {
            "category":"Personal",
            "subcategory":"Nail Salon",
            "type":"Services"
        }
    ],
    "sg:phone":"+32 9 345 82 47",
    "sg:postcode":"9185",
    "sg:province":"Oost-Vlaanderen",
    "sg:tags":[
        "pedicure"
    ],
    "wof:name":"Guldstrand B",
    "wof:placetype":"venue"
},
  "geometry": {"coordinates":[3.8522520065,51.174156189],"type":"Point"}
}