{
  "type": "Feature",
  "properties": {
    "addr:full":"Bld Prince De Li\u00c8ge 7 Anderlecht/anderlecht Bruxelles-Capitale 1070",
    "addr:housenumber":"7",
    "addr:postcode":"1070",
    "addr:street":"Bld Prince De Lie\u0300Ge",
    "iso:country":"BE",
    "sg:address":"Bld Prince De Li\u00c8ge 7",
    "sg:city":"Anderlecht/anderlecht",
    "sg:orig_category":"M\u00e9decins and sp\u00e9cialistes",
    "sg:phone":"+32 2 523 67 40",
    "sg:postcode":"1070",
    "sg:province":"Bruxelles-Capitale",
    "wof:name":"Maryl\u00c8ne Putzeys",
    "wof:placetype":"venue"
},
  "geometry": {"coordinates":[4.2992959023,50.8455200195],"type":"Point"}
}