{
  "type": "Feature",
  "properties": {
    "iso:country":"BE",
    "sg:address":"Rue De La Place 11",
    "sg:city":"Honnelles",
    "sg:orig_category":"Epiceries",
    "sg:phone":"+32 65 75 99 00",
    "sg:postcode":"7387",
    "sg:province":"Hainaut",
    "wof:name":"Superette De La Place",
    "wof:placetype":"venue"
},
  "geometry": {"coordinates":[3.6959199905,50.3683853149],"type":"Point"}
}