{
  "type": "Feature",
  "properties": {
    "addr:full":"Quai Godefroid Kurth 100 Li\u00c8ge Li\u00e8ge 4020",
    "addr:housenumber":"100",
    "addr:postcode":"4020",
    "addr:street":"Quai Godefroid Kurth",
    "iso:country":"BE",
    "sg:address":"Quai Godefroid Kurth 100",
    "sg:city":"Li\u00c8ge",
    "sg:classifiers":[
        {
            "category":"Manufacturing",
            "subcategory":"Petroleum Products",
            "type":"Manufacturing & Wholesale Goods"
        }
    ],
    "sg:phone":"+32 4 341 92 11",
    "sg:postcode":"4020",
    "sg:province":"Li\u00e8ge",
    "sg:tags":[
        "production",
        "combustible",
        "de",
        "distribution",
        "gaz"
    ],
    "wof:name":"Intermosane",
    "wof:placetype":"venue"
},
  "geometry": {"coordinates":[5.6009931564,50.6482467651],"type":"Point"}
}