{
  "type": "Feature",
  "properties": {
    "addr:full":"Maurits Sacr\u00e9straat 17 Merchtem Vlaams-Brabant 1785",
    "addr:housenumber":"17",
    "addr:postcode":"1785",
    "addr:street":"Sacre\u0301Straat",
    "iso:country":"BE",
    "sg:address":"Maurits Sacr\u00e9straat 17",
    "sg:city":"Merchtem",
    "sg:classifiers":[
        {
            "category":"Bakery",
            "type":"Food & Drink"
        }
    ],
    "sg:phone":"+32 52 37 45 34",
    "sg:postcode":"1785",
    "sg:province":"Vlaams-Brabant",
    "sg:tags":[
        "confectioner",
        "baker"
    ],
    "wof:name":"Biologische Bakkerij Jowan",
    "wof:placetype":"venue"
},
  "geometry": {"coordinates":[4.2356910706,50.954914093],"type":"Point"}
}