{
  "type": "Feature",
  "properties": {
    "addr:full":"Reservorenstraat 11 Beringen (beverlo) Limburg 3581",
    "addr:housenumber":"11",
    "addr:postcode":"3581",
    "addr:street":"Reservorenstraat",
    "iso:country":"BE",
    "sg:address":"Reservorenstraat 11",
    "sg:city":"Beringen (beverlo)",
    "sg:classifiers":[
        {
            "category":"Real Estate",
            "subcategory":"Real Estate Services",
            "type":"Services"
        }
    ],
    "sg:phone":"+32 11 45 45 35",
    "sg:postcode":"3581",
    "sg:province":"Limburg",
    "wof:name":"Jordens' Vastgoed",
    "wof:placetype":"venue"
},
  "geometry": {"coordinates":[5.2268509865,51.0922241211],"type":"Point"}
}