{
  "type": "Feature",
  "properties": {
    "addr:full":"Mispelaarstraat 35 Genk Limburg 3600",
    "addr:housenumber":"35",
    "addr:postcode":"3600",
    "addr:street":"Mispelaarstraat",
    "iso:country":"BE",
    "sg:address":"Mispelaarstraat 35",
    "sg:city":"Genk",
    "sg:orig_category":"Kapsalons",
    "sg:phone":"+32 89 36 23 63",
    "sg:postcode":"3600",
    "sg:province":"Limburg",
    "wof:name":"Sandra Kinable",
    "wof:placetype":"venue"
},
  "geometry": {"coordinates":[5.5286312103,50.9743690491],"type":"Point"}
}