{
  "type": "Feature",
  "properties": {
    "addr:full":"Dagmoedstraat 117 Geraardsbergen (schendelbeke) Oost-Vlaanderen 9506",
    "addr:housenumber":"117",
    "addr:postcode":"9506",
    "addr:street":"Dagmoedstraat",
    "iso:country":"BE",
    "sg:address":"Dagmoedstraat 117",
    "sg:city":"Geraardsbergen (schendelbeke)",
    "sg:classifiers":[
        {
            "category":"Personal",
            "subcategory":"Beauty Salon",
            "type":"Services"
        }
    ],
    "sg:phone":"+32 54 41 46 16",
    "sg:postcode":"9506",
    "sg:province":"Oost-Vlaanderen",
    "sg:tags":[
        "equipment",
        "hairdressing",
        "-",
        "supply"
    ],
    "wof:name":"Sebastian - Trucco - Opi",
    "wof:placetype":"venue"
},
  "geometry": {"coordinates":[3.8985300064,50.7987060547],"type":"Point"}
}