{
  "type": "Feature",
  "properties": {
    "addr:full":"Tieltstraat 54 Wingene West-Vlaanderen 8750",
    "addr:housenumber":"54",
    "addr:postcode":"8750",
    "addr:street":"Tieltstraat",
    "iso:country":"BE",
    "sg:address":"Tieltstraat 54",
    "sg:city":"Wingene",
    "sg:orig_category":"Banken and kredietinstellingen",
    "sg:phone":"+32 51 65 58 28",
    "sg:postcode":"8750",
    "sg:province":"West-Vlaanderen",
    "wof:name":"Groep Argenta",
    "wof:placetype":"venue"
},
  "geometry": {"coordinates":[3.283162117,51.056388855],"type":"Point"}
}