{
  "type": "Feature",
  "properties": {
    "addr:full":"Kapel Ter Bede 40 Kortrijk West-Vlaanderen 8500",
    "addr:housenumber":"40",
    "addr:postcode":"8500",
    "addr:street":"Bede",
    "iso:country":"BE",
    "sg:address":"Kapel Ter Bede 40",
    "sg:city":"Kortrijk",
    "sg:orig_category":"Dakwerken HUISBRANDOLIE",
    "sg:phone":"+32 56 21 00 84",
    "sg:postcode":"8500",
    "sg:province":"West-Vlaanderen",
    "wof:name":"Dakmos",
    "wof:placetype":"venue"
},
  "geometry": {"coordinates":[3.2934100628,50.8217735291],"type":"Point"}
}