{
  "type": "Feature",
  "properties": {
    "iso:country":"BE",
    "sg:address":"Grand'route 101",
    "sg:city":"Walcourt (laneffe)",
    "sg:classifiers":[
        {
            "category":"Retail",
            "subcategory":"Car Wash",
            "type":"Services"
        }
    ],
    "sg:phone":"+32 478 64 27 22",
    "sg:postcode":"5651",
    "sg:province":"Namur",
    "sg:tags":[
        "automobile",
        "washing",
        "-",
        "truck"
    ],
    "wof:name":"Mobil Wash",
    "wof:placetype":"venue"
},
  "geometry": {"coordinates":[4.4332799911,50.2857818604],"type":"Point"}
}