{
  "type": "Feature",
  "properties": {
    "iso:country":"BE",
    "sg:address":"Zuidkapelweg 15",
    "sg:city":"Veurne",
    "sg:orig_category":"Enseignement maternel and primaire",
    "sg:phone":"+32 58 31 27 35",
    "sg:postcode":"8630",
    "sg:province":"West-Vlaanderen",
    "wof:name":"Vrije Kleuterschool",
    "wof:placetype":"venue"
},
  "geometry": {"coordinates":[2.6645700932,51.0635414124],"type":"Point"}
}