{
  "type": "Feature",
  "properties": {
    "addr:full":"Anjelierstraat 111 Gent Oost-Vlaanderen 9000",
    "addr:housenumber":"111",
    "addr:postcode":"9000",
    "addr:street":"Anjelierstraat;Oost-Vlaanderen",
    "iso:country":"BE",
    "sg:address":"Anjelierstraat 111",
    "sg:city":"Gent",
    "sg:orig_category":"Kapsalons",
    "sg:phone":"+32 9 236 51 51",
    "sg:postcode":"9000",
    "sg:province":"Oost-Vlaanderen",
    "wof:name":"Coiffure Katia",
    "wof:placetype":"venue"
},
  "geometry": {"coordinates":[3.7134099007,51.0745582581],"type":"Point"}
}