{
  "type": "Feature",
  "properties": {
    "addr:full":"Keizersplein 15 Aalst Oost-Vlaanderen 9300",
    "addr:housenumber":"15",
    "addr:postcode":"9300",
    "addr:street":"Keizersplein",
    "iso:country":"BE",
    "sg:address":"Keizersplein 15",
    "sg:city":"Aalst",
    "sg:classifiers":[
        {
            "category":"Professional",
            "subcategory":"Art Services",
            "type":"Services"
        }
    ],
    "sg:phone":"+32 53 79 09 78",
    "sg:postcode":"9300",
    "sg:province":"Oost-Vlaanderen",
    "sg:tags":[
        "photographer"
    ],
    "wof:name":"Kokken G",
    "wof:placetype":"venue"
},
  "geometry": {"coordinates":[4.0346441269,50.9373016357],"type":"Point"}
}