{
  "type": "Feature",
  "properties": {
    "iso:country":"BE",
    "sg:address":"Blinde-rodenbachstraat 62a",
    "sg:city":"Roeselare (rumbeke)",
    "sg:classifiers":[
        {
            "category":"Professional",
            "subcategory":"Printing & Photocopies",
            "type":"Services"
        }
    ],
    "sg:phone":"+32 51 20 03 84",
    "sg:postcode":"8800",
    "sg:province":"West-Vlaanderen",
    "sg:tags":[
        "-",
        "offset"
    ],
    "wof:name":"Drukkerij Verduyn Bvba",
    "wof:placetype":"venue"
},
  "geometry": {"coordinates":[3.1421070099,50.9326324463],"type":"Point"}
}