{
  "type": "Feature",
  "properties": {
    "addr:full":"Hoevenstraat 8 Herselt Antwerpen 2230",
    "addr:housenumber":"8",
    "addr:postcode":"2230",
    "addr:street":"Hoevenstraat",
    "iso:country":"BE",
    "sg:address":"Hoevenstraat 8",
    "sg:city":"Herselt",
    "sg:orig_category":"Motorfietsen",
    "sg:phone":"+32 16 69 91 85",
    "sg:postcode":"2230",
    "sg:province":"Antwerpen",
    "wof:name":"De Peuter Omer",
    "wof:placetype":"venue"
},
  "geometry": {"coordinates":[4.8206877708,51.0296173096],"type":"Point"}
}