{
  "type": "Feature",
  "properties": {
    "iso:country":"BE",
    "sg:address":"Vieille Rue Du Moulin 247",
    "sg:city":"Bruxelles (uccle)",
    "sg:classifiers":[
        {
            "category":"Health Services",
            "subcategory":"Dentist",
            "type":"Services"
        }
    ],
    "sg:phone":"+32 2 374 63 63",
    "sg:postcode":"1180",
    "sg:province":"Bruxelles-Capitale",
    "wof:name":"Philippe Strykowski Mich\u00e8le",
    "wof:placetype":"venue"
},
  "geometry": {"coordinates":[4.3697900772,50.7898483276],"type":"Point"}
}