{
  "type": "Feature",
  "properties": {
    "iso:country":"BE",
    "sg:address":"Looierijstraat 138",
    "sg:city":"Zulte",
    "sg:orig_category":"Producteurs de l\u00e9gumes",
    "sg:phone":"+32 56 61 37 23",
    "sg:postcode":"9870",
    "sg:province":"Oost-Vlaanderen",
    "wof:name":"Chris Van Colenberghe",
    "wof:placetype":"venue"
},
  "geometry": {"coordinates":[3.4303719997,50.9054450989],"type":"Point"}
}