{
  "type": "Feature",
  "properties": {
    "iso:country":"BE",
    "sg:address":"Antwerpsesteenweg 10",
    "sg:city":"Lochristi",
    "sg:orig_category":"Bloemen and planten Gh",
    "sg:phone":"+32 9 355 51 62",
    "sg:postcode":"9080",
    "sg:province":"Oost-Vlaanderen",
    "wof:name":"De Cleene Azalea",
    "wof:placetype":"venue"
},
  "geometry": {"coordinates":[3.8207879066,51.0930595398],"type":"Point"}
}