{
  "type": "Feature",
  "properties": {
    "addr:full":"Dr. Verdurmenstraat 2 Sint-niklaas Oost-Vlaanderen 9100",
    "addr:housenumber":"2",
    "addr:postcode":"9100",
    "addr:street":"Verdurmenstraat",
    "iso:country":"BE",
    "sg:address":"Dr. Verdurmenstraat 2",
    "sg:city":"Sint-niklaas",
    "sg:orig_category":"Activit\u00e9s d\u00b4action sociale sans h\u00e9bergement",
    "sg:phone":"+32 3 776 37 98",
    "sg:postcode":"9100",
    "sg:province":"Oost-Vlaanderen",
    "wof:name":"Vclb-centrum",
    "wof:placetype":"venue"
},
  "geometry": {"coordinates":[4.1442742348,51.1674499512],"type":"Point"}
}