{
  "type": "Feature",
  "properties": {
    "addr:full":"Vroonstraat 27 Waregem (desselgem) West-Vlaanderen 8792",
    "addr:housenumber":"27",
    "addr:postcode":"8792",
    "addr:street":"Vroonstraat",
    "iso:country":"BE",
    "sg:address":"Vroonstraat 27",
    "sg:city":"Waregem (desselgem)",
    "sg:classifiers":[
        {
            "category":"Manufacturing",
            "subcategory":"Tools & Machinery",
            "type":"Manufacturing & Wholesale Goods"
        }
    ],
    "sg:phone":"+32 56 71 75 15",
    "sg:postcode":"8792",
    "sg:province":"West-Vlaanderen",
    "sg:tags":[
        "-"
    ],
    "wof:name":"Vanden Berghe J",
    "wof:placetype":"venue"
},
  "geometry": {"coordinates":[3.3605949879,50.8880386353],"type":"Point"}
}