{
  "type": "Feature",
  "properties": {
    "iso:country":"BE",
    "sg:address":"Cyriel Buyssestraat 39",
    "sg:city":"Nevele",
    "sg:orig_category":"Non-Classified Establishments",
    "sg:phone":"+32 9 371 51 21",
    "sg:postcode":"9850",
    "sg:province":"Oost-Vlaanderen",
    "wof:name":"Mipa",
    "wof:placetype":"venue"
},
  "geometry": {"coordinates":[3.5462009907,51.0319519043],"type":"Point"}
}