{
  "type": "Feature",
  "properties": {
    "addr:full":"Rue Arbre St Pierre Ellezelles Hainaut 7890",
    "addr:postcode":"7890",
    "addr:street":"Rue Arbre St;Hainaut",
    "iso:country":"BE",
    "sg:address":"Rue Arbre St Pierre",
    "sg:city":"Ellezelles",
    "sg:orig_category":"Installatie van houten of kunststof schrijnwerk",
    "sg:phone":"+32 68 54 22 34",
    "sg:postcode":"7890",
    "sg:province":"Hainaut",
    "wof:name":"Nachez P",
    "wof:placetype":"venue"
},
  "geometry": {"coordinates":[3.6823210716,50.7216567993],"type":"Point"}
}