{
  "type": "Feature",
  "properties": {
    "addr:full":"Zwijgershoek 14 Sint-niklaas Oost-Vlaanderen 9100",
    "addr:housenumber":"14",
    "addr:postcode":"9100",
    "addr:street":"Zwijgershoek",
    "iso:country":"BE",
    "sg:address":"Zwijgershoek 14",
    "sg:city":"Sint-niklaas",
    "sg:classifiers":[
        {
            "category":"Museum",
            "type":"Entertainment"
        }
    ],
    "sg:phone":"+32 3 777 29 42",
    "sg:postcode":"9100",
    "sg:province":"Oost-Vlaanderen",
    "wof:name":"Internationaal Exlibriscentrum",
    "wof:placetype":"venue"
},
  "geometry": {"coordinates":[4.1449642181,51.1661720276],"type":"Point"}
}