{
  "type": "Feature",
  "properties": {
    "addr:full":"Lange Beeldekensstraat 193 Antwerpen Antwerpen 2060",
    "addr:housenumber":"193",
    "addr:postcode":"2060",
    "addr:street":"Lange Beeldekensstraat",
    "iso:country":"BE",
    "sg:address":"Lange Beeldekensstraat 193",
    "sg:city":"Antwerpen",
    "sg:orig_category":"Eclairage et \u00e9quipements du foyer",
    "sg:phone":"+32 3 235 45 88",
    "sg:postcode":"2060",
    "sg:province":"Antwerpen",
    "wof:name":"Huis Elias",
    "wof:placetype":"venue"
},
  "geometry": {"coordinates":[4.4301590919,51.2213745117],"type":"Point"}
}