{
  "type": "Feature",
  "properties": {
    "addr:full":"Sint-martinusplein 11-11b Genk Limburg 3600",
    "addr:housenumber":"11-11b",
    "addr:postcode":"3600",
    "addr:street":"Genk Limburg",
    "iso:country":"BE",
    "sg:address":"Sint-martinusplein 11-11b",
    "sg:city":"Genk",
    "sg:classifiers":[
        {
            "category":"Shopping",
            "subcategory":"Clothing, Apparel, & Fashions",
            "type":"Retail Goods"
        }
    ],
    "sg:phone":"+32 89 30 36 27",
    "sg:postcode":"3600",
    "sg:province":"Limburg",
    "sg:tags":[
        "boutique"
    ],
    "wof:name":"Sharivari",
    "wof:placetype":"venue"
},
  "geometry": {"coordinates":[5.4979271889,50.9649467468],"type":"Point"}
}