{
  "type": "Feature",
  "properties": {
    "iso:country":"BE",
    "sg:address":"Ninoofsesteenweg 890",
    "sg:city":"Dilbeek",
    "sg:orig_category":"Peinture. Rev\u00eatements pour sols and murs",
    "sg:phone":"+32 2 569 77 89",
    "sg:postcode":"1703",
    "sg:province":"Vlaams-Brabant",
    "wof:name":"Marcel Lannoo",
    "wof:placetype":"venue"
},
  "geometry": {"coordinates":[4.2036099434,50.8387527466],"type":"Point"}
}