{
  "type": "Feature",
  "properties": {
    "addr:full":"Coq-anglaisstraat 42 Moeskroen/mouscron Hainaut 7700",
    "addr:housenumber":"42",
    "addr:postcode":"7700",
    "addr:street":"Coq-Anglaisstraat",
    "iso:country":"BE",
    "sg:address":"Coq-anglaisstraat 42",
    "sg:city":"Moeskroen/mouscron",
    "sg:orig_category":"Boekenuitgeverijen",
    "sg:phone":"+32 56 33 69 76",
    "sg:postcode":"7700",
    "sg:province":"Hainaut",
    "wof:name":"Corine Dernoncourt",
    "wof:placetype":"venue"
},
  "geometry": {"coordinates":[3.2323200703,50.7400932312],"type":"Point"}
}