{
  "type": "Feature",
  "properties": {
    "addr:full":"Albert Vanlaethemstraat 14ba Hoeilaart Vlaams-Brabant 1560",
    "addr:housenumber":"14ba",
    "addr:postcode":"1560",
    "addr:street":"Albert Vanlaethemstraat",
    "iso:country":"BE",
    "sg:address":"Albert Vanlaethemstraat 14ba",
    "sg:city":"Hoeilaart",
    "sg:orig_category":"Artistes ind\u00e9pendants",
    "sg:phone":"+32 2 657 96 96",
    "sg:postcode":"1560",
    "sg:province":"Vlaams-Brabant",
    "wof:name":"Th\u00c9r\u00c8se-marie Hunger",
    "wof:placetype":"venue"
},
  "geometry": {"coordinates":[4.467634201,50.7588920593],"type":"Point"}
}