{
  "type": "Feature",
  "properties": {
    "iso:country":"BE",
    "sg:address":"Wervenstraat 10",
    "sg:city":"As",
    "sg:classifiers":[
        {
            "category":"Farming",
            "subcategory":"Livestock Farm",
            "type":"Manufacturing & Wholesale Goods"
        }
    ],
    "sg:phone":"+32 89 61 32 50",
    "sg:postcode":"3665",
    "sg:province":"Limburg",
    "sg:tags":[
        "horse"
    ],
    "wof:name":"Immabel",
    "wof:placetype":"venue"
},
  "geometry": {"coordinates":[5.6101751328,51.022151947],"type":"Point"}
}