{
  "type": "Feature",
  "properties": {
    "addr:full":"Maandagmarkt 9 Halle Vlaams-Brabant 1500",
    "addr:housenumber":"9",
    "addr:postcode":"1500",
    "addr:street":"Maandagmarkt",
    "iso:country":"BE",
    "sg:address":"Maandagmarkt 9",
    "sg:city":"Halle",
    "sg:orig_category":"Mat\u00e9riel de T\u00e9l\u00e9communication",
    "sg:phone":"+32 2 361 30 61",
    "sg:postcode":"1500",
    "sg:province":"Vlaams-Brabant",
    "wof:name":"Optimum",
    "wof:placetype":"venue"
},
  "geometry": {"coordinates":[4.2364768982,50.7357711792],"type":"Point"}
}