{
  "type": "Feature",
  "properties": {
    "iso:country":"BE",
    "sg:address":"Kloosterstraat 1",
    "sg:city":"Lommel",
    "sg:orig_category":"Tabac. Journaux",
    "sg:phone":"+32 11 54 42 53",
    "sg:postcode":"3920",
    "sg:province":"Limburg",
    "wof:name":"Wielickx",
    "wof:placetype":"venue"
},
  "geometry": {"coordinates":[5.312816143,51.2297286987],"type":"Point"}
}