{
  "type": "Feature",
  "properties": {
    "iso:country":"BE",
    "sg:address":"Rue Joseph Wauters 136",
    "sg:city":"Charleroi",
    "sg:classifiers":[
        {
            "category":"Food & Beverages",
            "subcategory":"Groceries & Convenience Stores",
            "type":"Retail Goods"
        }
    ],
    "sg:phone":"+32 71 41 73 82",
    "sg:postcode":"6000",
    "sg:province":"Hainaut",
    "sg:tags":[
        "grocer"
    ],
    "wof:name":"Alouettes (les)",
    "wof:placetype":"venue"
},
  "geometry": {"coordinates":[4.4613242149,50.4265480042],"type":"Point"}
}