{
  "type": "Feature",
  "properties": {
    "addr:full":"Collegestraat 7 Mol Antwerpen 2400",
    "addr:housenumber":"7",
    "addr:postcode":"2400",
    "addr:street":"Collegestraat",
    "iso:country":"BE",
    "sg:address":"Collegestraat 7",
    "sg:city":"Mol",
    "sg:classifiers":[
        {
            "category":"Health Services",
            "subcategory":"Health Practitioner",
            "type":"Services"
        }
    ],
    "sg:phone":"+32 14 31 23 84",
    "sg:postcode":"2400",
    "sg:province":"Antwerpen",
    "sg:tags":[
        "physiotherapist"
    ],
    "wof:name":"Van Bael Bob",
    "wof:placetype":"venue"
},
  "geometry": {"coordinates":[5.1124930382,51.1866760254],"type":"Point"}
}