{
  "type": "Feature",
  "properties": {
    "addr:full":"Hasseltsestraat 1 Bilzen Limburg 3740",
    "addr:housenumber":"1",
    "addr:postcode":"3740",
    "addr:street":"Hasseltsestraat",
    "iso:country":"BE",
    "sg:address":"Hasseltsestraat 1",
    "sg:city":"Bilzen",
    "sg:orig_category":"Fruitteelt",
    "sg:phone":"+32 89 41 74 37",
    "sg:postcode":"3740",
    "sg:province":"Limburg",
    "wof:name":"Emmanuel Gielen",
    "wof:placetype":"venue"
},
  "geometry": {"coordinates":[5.4899978638,50.8823013306],"type":"Point"}
}