{
  "type": "Feature",
  "properties": {
    "addr:full":"Rue Des Chavees 31 Doische Namur 5680",
    "addr:housenumber":"31",
    "addr:postcode":"5680",
    "addr:street":"Rue Des Chavees",
    "iso:country":"BE",
    "sg:address":"Rue Des Chavees 31",
    "sg:city":"Doische",
    "sg:orig_category":"Woningbouw",
    "sg:phone":"+32 82 67 70 45",
    "sg:postcode":"5680",
    "sg:province":"Namur",
    "wof:name":"Claude Soumoy",
    "wof:placetype":"venue"
},
  "geometry": {"coordinates":[4.7154111862,50.1306228638],"type":"Point"}
}