{
  "type": "Feature",
  "properties": {
    "addr:full":"Nachtegaaldreef 17 Zandhoven (pulderbos) Antwerpen 2242",
    "addr:housenumber":"17",
    "addr:postcode":"2242",
    "addr:street":"Nachtegaaldreef",
    "iso:country":"BE",
    "sg:address":"Nachtegaaldreef 17",
    "sg:city":"Zandhoven (pulderbos)",
    "sg:classifiers":[
        {
            "category":"Health Services",
            "subcategory":"Dentist",
            "type":"Services"
        }
    ],
    "sg:phone":"+32 3 464 08 94",
    "sg:postcode":"2242",
    "sg:province":"Antwerpen",
    "wof:name":"Brignola G",
    "wof:placetype":"venue"
},
  "geometry": {"coordinates":[4.7208781242,51.23828125],"type":"Point"}
}