{
  "type": "Feature",
  "properties": {
    "addr:full":"Rue Hocheporte 11 Li\u00e8ge 1 Li\u00e8ge 4000",
    "addr:housenumber":"11;1",
    "addr:postcode":"4000",
    "addr:street":"Rue Hocheporte",
    "iso:country":"BE",
    "sg:address":"Rue Hocheporte 11",
    "sg:city":"Li\u00e8ge 1",
    "sg:classifiers":[
        {
            "category":"Education",
            "subcategory":"School",
            "type":"Public Place"
        }
    ],
    "sg:phone":"+32 4 222 20 83",
    "sg:postcode":"4000",
    "sg:province":"Li\u00e8ge",
    "sg:tags":[
        "-",
        "private"
    ],
    "wof:name":"Centre Feldenkrais D'education Somatique",
    "wof:placetype":"venue"
},
  "geometry": {"coordinates":[5.5654602051,50.645980835],"type":"Point"}
}