{
  "type": "Feature",
  "properties": {
    "iso:country":"BE",
    "sg:address":"Knaptandstraat 117",
    "sg:city":"Sint-niklaas",
    "sg:orig_category":"Slagers",
    "sg:phone":"+32 3 778 09 64",
    "sg:postcode":"9100",
    "sg:province":"Oost-Vlaanderen",
    "wof:name":"Dirk D'hooghe",
    "wof:placetype":"venue"
},
  "geometry": {"coordinates":[4.1445498466,51.1583786011],"type":"Point"}
}