{
  "type": "Feature",
  "properties": {
    "addr:full":"Kolmstraat 61 Zingem Oost-Vlaanderen 9750",
    "addr:housenumber":"61",
    "addr:postcode":"9750",
    "addr:street":"Kolmstraat",
    "iso:country":"BE",
    "sg:address":"Kolmstraat 61",
    "sg:city":"Zingem",
    "sg:orig_category":"Pluimveekwekers",
    "sg:phone":"+32 9 384 24 57",
    "sg:postcode":"9750",
    "sg:province":"Oost-Vlaanderen",
    "wof:name":"Gilbert Moerman",
    "wof:placetype":"venue"
},
  "geometry": {"coordinates":[3.6342840195,50.9111824036],"type":"Point"}
}