{
  "type": "Feature",
  "properties": {
    "addr:full":"Rue De Fafchamps Bl\u00e9gny (mortier) Li\u00e8ge 4670",
    "addr:postcode":"4670",
    "addr:street":"Rue De Fafchamps",
    "iso:country":"BE",
    "sg:address":"Rue De Fafchamps",
    "sg:city":"Bl\u00e9gny (mortier)",
    "sg:classifiers":[
        {
            "category":"Real Estate",
            "subcategory":"Architect",
            "type":"Services"
        }
    ],
    "sg:phone":"+32 4 387 48 77",
    "sg:postcode":"4670",
    "sg:province":"Li\u00e8ge",
    "wof:name":"Dumoulin M",
    "wof:placetype":"venue"
},
  "geometry": {"coordinates":[5.7201251984,50.6691474915],"type":"Point"}
}