{
  "type": "Feature",
  "properties": {
    "addr:full":"Pittemstraat 33 Aalter (lotenhulle) Oost-Vlaanderen 9880",
    "addr:housenumber":"33",
    "addr:postcode":"9880",
    "addr:street":"Pittemstraat",
    "iso:country":"BE",
    "sg:address":"Pittemstraat 33",
    "sg:city":"Aalter (lotenhulle)",
    "sg:classifiers":[
        {
            "category":"Health Services",
            "subcategory":"Health Practitioner",
            "type":"Services"
        }
    ],
    "sg:phone":"+32 51 68 76 33",
    "sg:postcode":"9880",
    "sg:province":"Oost-Vlaanderen",
    "sg:tags":[
        "physiotherapist"
    ],
    "wof:name":"Pelfrene Luc",
    "wof:placetype":"venue"
},
  "geometry": {"coordinates":[3.4612340927,51.0529785156],"type":"Point"}
}