{
  "type": "Feature",
  "properties": {
    "iso:country":"BE",
    "sg:address":"Leuvenselaan 758",
    "sg:city":"Tienen",
    "sg:orig_category":"Woningbouw",
    "sg:phone":"+32 16 82 12 51",
    "sg:postcode":"3300",
    "sg:province":"Vlaams-Brabant",
    "wof:name":"Pascal Roskams",
    "wof:placetype":"venue"
},
  "geometry": {"coordinates":[4.9037599564,50.8178901672],"type":"Point"}
}