{
  "type": "Feature",
  "properties": {
    "iso:country":"BE",
    "sg:address":"Rue Salvador 31",
    "sg:city":"Li\u00e8ge 1 (grivegn\u00e9e)",
    "sg:classifiers":[
        {
            "category":"Building & Trades",
            "subcategory":"Cleaning & Sanitation",
            "type":"Services"
        }
    ],
    "sg:phone":"+32 4 341 33 37",
    "sg:postcode":"4030",
    "sg:province":"Li\u00e8ge",
    "sg:tags":[
        "janitor"
    ],
    "wof:name":"Andrien Piscitello & Cie Scs",
    "wof:placetype":"venue"
},
  "geometry": {"coordinates":[5.6015071869,50.621799469],"type":"Point"}
}