{
  "type": "Feature",
  "properties": {
    "addr:full":"Rue Du Progres 35 Saint-ghislain Hainaut 7333",
    "addr:housenumber":"35",
    "addr:postcode":"7333",
    "addr:street":"Rue Du Progres;Hainaut",
    "iso:country":"BE",
    "sg:address":"Rue Du Progres 35",
    "sg:city":"Saint-ghislain",
    "sg:orig_category":"Installation de menuiserie en bois and plastique",
    "sg:phone":"+32 65 62 33 68",
    "sg:postcode":"7333",
    "sg:province":"Hainaut",
    "wof:name":"Gualandi",
    "wof:placetype":"venue"
},
  "geometry": {"coordinates":[3.7775599957,50.4584884644],"type":"Point"}
}