{
  "type": "Feature",
  "properties": {
    "addr:full":"Rue Du Houblon 47 Brussel/bruxelles Bruxelles-Capitale 1000",
    "addr:housenumber":"47",
    "addr:postcode":"1000",
    "addr:street":"Rue Du Houblon;/",
    "iso:country":"BE",
    "sg:address":"Rue Du Houblon 47",
    "sg:city":"Brussel/bruxelles",
    "sg:orig_category":"Imprimeries and copyshops",
    "sg:phone":"+32 2 511 66 38",
    "sg:postcode":"1000",
    "sg:province":"Bruxelles-Capitale",
    "wof:name":"Switch On Color",
    "wof:placetype":"venue"
},
  "geometry": {"coordinates":[4.3420791626,50.8512115479],"type":"Point"}
}