{
  "type": "Feature",
  "properties": {
    "iso:country":"BE",
    "sg:address":"Achterstraat 33",
    "sg:city":"Aalst (meldert)",
    "sg:classifiers":[
        {
            "category":"Health Services",
            "subcategory":"Health Practitioner",
            "type":"Services"
        }
    ],
    "sg:phone":"+32 53 71 10 19",
    "sg:postcode":"9310",
    "sg:province":"Oost-Vlaanderen",
    "sg:tags":[
        "physiotherapist"
    ],
    "wof:name":"Boschmans F",
    "wof:placetype":"venue"
},
  "geometry": {"coordinates":[4.1221909523,50.9462127686],"type":"Point"}
}