{
  "type": "Feature",
  "properties": {
    "iso:country":"BE",
    "sg:address":"Rue Willy Ernst 27",
    "sg:city":"Charleroi",
    "sg:orig_category":"M\u00e9decins and sp\u00e9cialistes",
    "sg:phone":"+32 71 31 21 69",
    "sg:postcode":"6000",
    "sg:province":"Hainaut",
    "wof:name":"Jacques Minet",
    "wof:placetype":"venue"
},
  "geometry": {"coordinates":[4.4492630959,50.4093437195],"type":"Point"}
}