{
  "type": "Feature",
  "properties": {
    "iso:country":"BE",
    "sg:address":"Watermolenstraat 56",
    "sg:city":"Lierde",
    "sg:orig_category":"Onderdelen and accessoires voor auto's",
    "sg:phone":"+32 54 41 47 17",
    "sg:postcode":"9570",
    "sg:province":"Oost-Vlaanderen",
    "wof:name":"Paul De Cubber",
    "wof:placetype":"venue"
},
  "geometry": {"coordinates":[3.8481009007,50.793586731],"type":"Point"}
}