{
  "type": "Feature",
  "properties": {
    "iso:country":"BE",
    "sg:address":"Alphonse Asselbergsstr. 34",
    "sg:city":"Ukkel/uccle",
    "sg:orig_category":"Fotogravure and zetwerk Secretariaatsdiensten",
    "sg:phone":"+32 2 347 52 05",
    "sg:postcode":"1180",
    "sg:province":"Bruxelles-Capitale",
    "wof:name":"Graphic Print Reset",
    "wof:placetype":"venue"
},
  "geometry": {"coordinates":[4.3352079391,50.8053359985],"type":"Point"}
}