{
  "type": "Feature",
  "properties": {
    "iso:country":"BE",
    "sg:address":"Eind 40",
    "sg:city":"Hamont-achel (achel)",
    "sg:classifiers":[
        {
            "category":"Professional",
            "subcategory":"Testing Lab",
            "type":"Services"
        }
    ],
    "sg:phone":"+32 11 80 57 57",
    "sg:postcode":"3930",
    "sg:province":"Limburg",
    "sg:tags":[
        "chemist"
    ],
    "wof:name":"Thijs C",
    "wof:placetype":"venue"
},
  "geometry": {"coordinates":[5.4770278931,51.2631072998],"type":"Point"}
}