{
  "type": "Feature",
  "properties": {
    "iso:country":"BE",
    "sg:address":"Rue Leman 11",
    "sg:city":"Mons (jemappes)",
    "sg:classifiers":[
        {
            "category":"Professional",
            "subcategory":"Testing Lab",
            "type":"Services"
        }
    ],
    "sg:phone":"+32 65 82 57 24",
    "sg:postcode":"7012",
    "sg:province":"Hainaut",
    "sg:tags":[
        "chemist"
    ],
    "wof:name":"Bouillon Sa",
    "wof:placetype":"venue"
},
  "geometry": {"coordinates":[3.8894600868,50.4481964111],"type":"Point"}
}