{
  "type": "Feature",
  "properties": {
    "addr:full":"Rue De La Ga\u00cet\u00c9 102 Anderlecht Bruxelles-Capitale 1070",
    "addr:housenumber":"102",
    "addr:postcode":"1070",
    "addr:street":"Rue De La Gai\u0302Te\u0301",
    "iso:country":"BE",
    "sg:address":"Rue De La Ga\u00cet\u00c9 102",
    "sg:city":"Anderlecht",
    "sg:orig_category":"Charpentes and couvertures",
    "sg:phone":"+32 2 523 26 65",
    "sg:postcode":"1070",
    "sg:province":"Bruxelles-Capitale",
    "wof:name":"J.m. Moisson & Fils",
    "wof:placetype":"venue"
},
  "geometry": {"coordinates":[4.3120617867,50.8334007263],"type":"Point"}
}