{
  "type": "Feature",
  "properties": {
    "iso:country":"BE",
    "sg:address":"Ferdinand Verstraetenlaan 9",
    "sg:city":"Kampenhout",
    "sg:classifiers":[
        {
            "category":"Organizations",
            "subcategory":"Community Association",
            "type":"Services"
        }
    ],
    "sg:phone":"+32 16 65 51 36",
    "sg:postcode":"1910",
    "sg:province":"Vlaams-Brabant",
    "sg:tags":[
        "box",
        "cardboard"
    ],
    "wof:name":"Kartonnage Van Kampenhout Nv",
    "wof:placetype":"venue"
},
  "geometry": {"coordinates":[4.5505199432,50.9399681091],"type":"Point"}
}