{
  "type": "Feature",
  "properties": {
    "addr:full":"Asterstraat 16 Opglabbeek Limburg 3660",
    "addr:housenumber":"16",
    "addr:postcode":"3660",
    "addr:street":"Asterstraat",
    "iso:country":"BE",
    "sg:address":"Asterstraat 16",
    "sg:city":"Opglabbeek",
    "sg:orig_category":"Pain, p\u00e2tisseries and confiseries",
    "sg:phone":"+32 89 38 25 84",
    "sg:postcode":"3660",
    "sg:province":"Limburg",
    "wof:name":"Huis Novotex",
    "wof:placetype":"venue"
},
  "geometry": {"coordinates":[5.5381760597,51.0312156677],"type":"Point"}
}