{
  "type": "Feature",
  "properties": {
    "addr:full":"Edestraat 17 Erpe-mere (mere) Oost-Vlaanderen 9420",
    "addr:housenumber":"17",
    "addr:postcode":"9420",
    "addr:street":"Edestraat;Mere Oost-Vlaanderen",
    "iso:country":"BE",
    "sg:address":"Edestraat 17",
    "sg:city":"Erpe-mere (mere)",
    "sg:classifiers":[
        {
            "category":"Health Services",
            "subcategory":"Health Practitioner",
            "type":"Services"
        }
    ],
    "sg:phone":"+32 477 37 58 61",
    "sg:postcode":"9420",
    "sg:province":"Oost-Vlaanderen",
    "sg:tags":[
        "physiotherapist"
    ],
    "wof:name":"De Pauw Bart",
    "wof:placetype":"venue"
},
  "geometry": {"coordinates":[3.9806959629,50.9127616882],"type":"Point"}
}