{
  "type": "Feature",
  "properties": {
    "addr:full":"Avenue G\u00c9n\u00c9ral De Gaulle 30 Elsene Bruxelles-Capitale 1050",
    "addr:housenumber":"30",
    "addr:postcode":"1050",
    "addr:street":"Avenue Ge\u0301Ne\u0301Ral De Gaulle",
    "iso:country":"BE",
    "sg:address":"Avenue G\u00c9n\u00c9ral De Gaulle 30",
    "sg:city":"Elsene",
    "sg:orig_category":"Bouwmaterialen Gh",
    "sg:phone":"+32 2 649 22 11",
    "sg:postcode":"1050",
    "sg:province":"Bruxelles-Capitale",
    "wof:name":"Euro-bati-concept",
    "wof:placetype":"venue"
},
  "geometry": {"coordinates":[4.3716278076,50.8246269226],"type":"Point"}
}