{
  "type": "Feature",
  "properties": {
    "addr:full":"Georges Lobertstraat 34 Oudenaarde Oost-Vlaanderen 9700",
    "addr:housenumber":"34",
    "addr:postcode":"9700",
    "addr:street":"Lobertstraat",
    "iso:country":"BE",
    "sg:address":"Georges Lobertstraat 34",
    "sg:city":"Oudenaarde",
    "sg:orig_category":"Installatie van houten of kunststof schrijnwerk",
    "sg:phone":"+32 55 30 24 00",
    "sg:postcode":"9700",
    "sg:province":"Oost-Vlaanderen",
    "wof:name":"Koen Ghyselinck",
    "wof:placetype":"venue"
},
  "geometry": {"coordinates":[3.6003439426,50.8312568665],"type":"Point"}
}