{
  "type": "Feature",
  "properties": {
    "addr:full":"Rue Du Samson 17 Andenne Namur 5300",
    "addr:housenumber":"17",
    "addr:postcode":"5300",
    "addr:street":"Rue Du Samson",
    "iso:country":"BE",
    "sg:address":"Rue Du Samson 17",
    "sg:city":"Andenne",
    "sg:orig_category":"Toeristische diensten",
    "sg:phone":"+32 81 58 90 57",
    "sg:postcode":"5300",
    "sg:province":"Namur",
    "wof:name":"Syndicat D\u00b4initiative",
    "wof:placetype":"venue"
},
  "geometry": {"coordinates":[4.9974207878,50.4647750854],"type":"Point"}
}