{
  "type": "Feature",
  "properties": {
    "iso:country":"BE",
    "sg:address":"Dapperensquare 16",
    "sg:city":"Linkebeek/linkebeek",
    "sg:orig_category":"Banken and kredietinstellingen",
    "sg:phone":"+32 2 380 76 27",
    "sg:postcode":"1630",
    "sg:province":"Vlaams-Brabant",
    "wof:name":"Fortis",
    "wof:placetype":"venue"
},
  "geometry": {"coordinates":[4.3360700607,50.7737159729],"type":"Point"}
}