{
  "type": "Feature",
  "properties": {
    "iso:country":"BE",
    "sg:address":"Riemsterweg 242",
    "sg:city":"Bilzen",
    "sg:classifiers":[
        {
            "category":"Home & Garden",
            "subcategory":"Garden Supply",
            "type":"Retail Goods"
        }
    ],
    "sg:phone":"+32 89 41 19 25",
    "sg:postcode":"3740",
    "sg:province":"Limburg",
    "sg:tags":[
        "machine",
        "agricultural",
        "-"
    ],
    "wof:name":"Geurts H & Zn Nv",
    "wof:placetype":"venue"
},
  "geometry": {"coordinates":[5.5292901993,50.8601989746],"type":"Point"}
}