{
  "type": "Feature",
  "properties": {
    "addr:full":"Oosteeklodorp 92 Assenede Oost-Vlaanderen 9968",
    "addr:housenumber":"92",
    "addr:postcode":"9968",
    "addr:street":"Oosteeklodorp",
    "iso:country":"BE",
    "sg:address":"Oosteeklodorp 92",
    "sg:city":"Assenede",
    "sg:classifiers":[
        {
            "category":"Insurance",
            "subcategory":"Life Insurance",
            "type":"Services"
        }
    ],
    "sg:phone":"+32 9 373 67 22",
    "sg:postcode":"9968",
    "sg:province":"Oost-Vlaanderen",
    "sg:tags":[
        "assurance"
    ],
    "wof:name":"Wauters Dienstengroep",
    "wof:placetype":"venue"
},
  "geometry": {"coordinates":[3.6853539944,51.1895866394],"type":"Point"}
}