{
  "type": "Feature",
  "properties": {
    "addr:full":"Oostveldstraat 197 Eeklo Oost-Vlaanderen 9900",
    "addr:housenumber":"197",
    "addr:postcode":"9900",
    "addr:street":"Oostveldstraat",
    "iso:country":"BE",
    "sg:address":"Oostveldstraat 197",
    "sg:city":"Eeklo",
    "sg:classifiers":[
        {
            "category":"Building & Trades",
            "subcategory":"Landscaping Services",
            "type":"Services"
        }
    ],
    "sg:phone":"+32 9 377 16 44",
    "sg:postcode":"9900",
    "sg:province":"Oost-Vlaanderen",
    "sg:tags":[
        "gardening",
        "garden",
        "maintenance"
    ],
    "wof:name":"De Clercq Marnix",
    "wof:placetype":"venue"
},
  "geometry": {"coordinates":[3.5935380459,51.1823806763],"type":"Point"}
}