{
  "type": "Feature",
  "properties": {
    "iso:country":"BE",
    "sg:address":"Rue De L'abbaye 24",
    "sg:city":"Assesse (courri\u00e8re)",
    "sg:classifiers":[
        {
            "category":"Professional",
            "subcategory":"Computer Services",
            "type":"Services"
        }
    ],
    "sg:phone":"+32 83 65 64 32",
    "sg:postcode":"5336",
    "sg:province":"Namur",
    "sg:tags":[
        "-",
        "processing",
        "data"
    ],
    "wof:name":"I.b.w.",
    "wof:placetype":"venue"
},
  "geometry": {"coordinates":[4.9978299141,50.3937606812],"type":"Point"}
}