{
  "type": "Feature",
  "properties": {
    "iso:country":"BE",
    "sg:address":"Vossenlo 13",
    "sg:city":"Destelbergen (heusden)",
    "sg:classifiers":[
        {
            "category":"Shopping",
            "subcategory":"Jewelry",
            "type":"Retail Goods"
        }
    ],
    "sg:phone":"+32 9 231 83 35",
    "sg:postcode":"9070",
    "sg:province":"Oost-Vlaanderen",
    "sg:tags":[
        "-",
        "imitation"
    ],
    "wof:name":"De Raes",
    "wof:placetype":"venue"
},
  "geometry": {"coordinates":[3.8180780411,51.0390167236],"type":"Point"}
}