{
  "type": "Feature",
  "properties": {
    "iso:country":"BE",
    "sg:address":"Steenweg Op Ravels 12",
    "sg:city":"Oud-turnhout",
    "sg:classifiers":[
        {
            "category":"Health Services",
            "subcategory":"Dentist",
            "type":"Services"
        }
    ],
    "sg:phone":"+32 14 42 51 60",
    "sg:postcode":"2360",
    "sg:province":"Antwerpen",
    "wof:name":"Madrid Y",
    "wof:placetype":"venue"
},
  "geometry": {"coordinates":[4.9677991867,51.3360519409],"type":"Point"}
}