{
  "type": "Feature",
  "properties": {
    "iso:country":"BE",
    "sg:address":"Avenue De La Lib\u00e9ration 9",
    "sg:city":"Leuze-en-hainaut",
    "sg:classifiers":[
        {
            "category":"Personal",
            "subcategory":"Nail Salon",
            "type":"Services"
        }
    ],
    "sg:phone":"+32 496 60 22 48",
    "sg:postcode":"7900",
    "sg:province":"Hainaut",
    "sg:tags":[
        "pedicure"
    ],
    "wof:name":"Lechevin C",
    "wof:placetype":"venue"
},
  "geometry": {"coordinates":[3.6096560955,50.5974578857],"type":"Point"}
}