{
  "type": "Feature",
  "properties": {
    "iso:country":"BE",
    "sg:address":"Ruitersweg 5",
    "sg:city":"Kortrijk",
    "sg:orig_category":"M\u00e9decins and sp\u00e9cialistes",
    "sg:phone":"+32 56 21 77 71",
    "sg:postcode":"8500",
    "sg:province":"West-Vlaanderen",
    "wof:name":"Fran\u00c7oise Laverge",
    "wof:placetype":"venue"
},
  "geometry": {"coordinates":[3.2745161057,50.8349113464],"type":"Point"}
}