{
  "type": "Feature",
  "properties": {
    "addr:full":"Ave Des Ardennes 18 Huy 5200",
    "addr:housenumber":"18",
    "addr:postcode":"5200",
    "addr:street":"Ave Des Ardennes",
    "iso:country":"BE",
    "sg:address":"Ave Des Ardennes 18",
    "sg:city":"Huy",
    "sg:classifiers":[
        {
            "category":"Banks & Credit Unions",
            "subcategory":"Bank",
            "type":"Services"
        }
    ],
    "sg:phone":"+32 85 21 14 08",
    "sg:postcode":"5200",
    "wof:name":"Banque Nagelmackers",
    "wof:placetype":"venue"
},
  "geometry": {"coordinates":[6.4994702339,44.5464782715],"type":"Point"}
}