{
  "type": "Feature",
  "properties": {
    "addr:full":"Middelstraat 8 Ieper West-Vlaanderen 8904",
    "addr:housenumber":"8",
    "addr:postcode":"8904",
    "addr:street":"Middelstraat",
    "iso:country":"BE",
    "sg:address":"Middelstraat 8",
    "sg:city":"Ieper",
    "sg:orig_category":"Rundveehouders",
    "sg:phone":"+32 51 54 40 39",
    "sg:postcode":"8904",
    "sg:province":"West-Vlaanderen",
    "wof:name":"Jose Veramme",
    "wof:placetype":"venue"
},
  "geometry": {"coordinates":[2.8281290531,50.9289627075],"type":"Point"}
}