{
  "type": "Feature",
  "properties": {
    "addr:full":"Sprinkelestraat 78e Zutendaal Limburg 3690",
    "addr:housenumber":"78e",
    "addr:postcode":"3690",
    "addr:street":"Sprinkelestraat",
    "iso:country":"BE",
    "sg:address":"Sprinkelestraat 78e",
    "sg:city":"Zutendaal",
    "sg:classifiers":[
        {
            "category":"Health Services",
            "subcategory":"Nursing And Care Facility",
            "type":"Services"
        }
    ],
    "sg:phone":"+32 89 61 50 58",
    "sg:postcode":"3690",
    "sg:province":"Limburg",
    "sg:tags":[
        "home"
    ],
    "wof:name":"Staes A",
    "wof:placetype":"venue"
},
  "geometry": {"coordinates":[5.5817980766,50.9351959229],"type":"Point"}
}