{
  "type": "Feature",
  "properties": {
    "iso:country":"BE",
    "sg:address":"Rue G\u00c9n\u00c9ral De Gaulle 61",
    "sg:city":"Li\u00c8ge",
    "sg:orig_category":"HUISBRANDOLIE",
    "sg:phone":"+32 4 343 41 37",
    "sg:postcode":"4020",
    "sg:province":"Li\u00e8ge",
    "wof:name":"Hebrans & Fils",
    "wof:placetype":"venue"
},
  "geometry": {"coordinates":[5.5788297653,50.6410903931],"type":"Point"}
}