{
  "type": "Feature",
  "properties": {
    "iso:country":"BE",
    "sg:address":"Pieter Dierckxlaan 83",
    "sg:city":"Temse",
    "sg:classifiers":[
        {
            "category":"Fast Food",
            "type":"Food & Drink"
        }
    ],
    "sg:phone":"+32 3 711 26 85",
    "sg:postcode":"9140",
    "sg:province":"Oost-Vlaanderen",
    "sg:tags":[
        "\u00c0",
        "emporter",
        "restaurants"
    ],
    "wof:name":"Frituur Sompershoek",
    "wof:placetype":"venue"
},
  "geometry": {"coordinates":[4.2019128799,51.1295280457],"type":"Point"}
}