{
  "type": "Feature",
  "properties": {
    "iso:country":"BE",
    "sg:address":"Wielemans Ceuppenslaan 112",
    "sg:city":"Vorst/forest",
    "sg:orig_category":"Artsen and specialisten",
    "sg:phone":"+32 2 538 54 53",
    "sg:postcode":"1190",
    "sg:province":"Bruxelles-Capitale",
    "wof:name":"Anders Magnusson",
    "wof:placetype":"venue"
},
  "geometry": {"coordinates":[4.3311371803,50.8244476318],"type":"Point"}
}