{
  "type": "Feature",
  "properties": {
    "addr:full":"Hikstraat 29 Herentals Antwerpen 2200",
    "addr:housenumber":"29",
    "addr:postcode":"2200",
    "addr:street":"Hikstraat",
    "iso:country":"BE",
    "sg:address":"Hikstraat 29",
    "sg:city":"Herentals",
    "sg:orig_category":"M\u00e9decins and sp\u00e9cialistes",
    "sg:phone":"+32 14 22 31 05",
    "sg:postcode":"2200",
    "sg:province":"Antwerpen",
    "wof:name":"C. De Reze",
    "wof:placetype":"venue"
},
  "geometry": {"coordinates":[4.8335018158,51.1814346313],"type":"Point"}
}