{
  "type": "Feature",
  "properties": {
    "addr:full":"Bruullos 8 Audenarde Oost-Vlaanderen 9700",
    "addr:housenumber":"8",
    "addr:postcode":"9700",
    "addr:street":"Bruullos;Oost-Vlaanderen",
    "iso:country":"BE",
    "sg:address":"Bruullos 8",
    "sg:city":"Audenarde",
    "sg:orig_category":"Architectes",
    "sg:phone":"+32 55 49 59 33",
    "sg:postcode":"9700",
    "sg:province":"Oost-Vlaanderen",
    "wof:name":"Baert Dirk",
    "wof:placetype":"venue"
},
  "geometry": {"coordinates":[3.6777169704,50.8551177979],"type":"Point"}
}