{
  "type": "Feature",
  "properties": {
    "iso:country":"BE",
    "sg:address":"Rijksweg 618",
    "sg:city":"Maasmechelen",
    "sg:orig_category":"Ice-cream parlours",
    "sg:phone":"+32 89 77 50 55",
    "sg:postcode":"3630",
    "sg:province":"Limburg",
    "wof:name":"Pralientje ('t)",
    "wof:placetype":"venue"
},
  "geometry": {"coordinates":[5.6942400932,50.956161499],"type":"Point"}
}