{
  "type": "Feature",
  "properties": {
    "iso:country":"BE",
    "sg:address":"Baron Van Caloenlaan 12",
    "sg:city":"De Haan",
    "sg:orig_category":"Installation de menuiserie en bois and plastique",
    "sg:phone":"+32 59 23 32 01",
    "sg:postcode":"8420",
    "sg:province":"West-Vlaanderen",
    "wof:name":"Wooninrichting Casier",
    "wof:placetype":"venue"
},
  "geometry": {"coordinates":[3.0368421078,51.2719650269],"type":"Point"}
}