{
  "type": "Feature",
  "properties": {
    "iso:country":"BE",
    "sg:address":"Van Breestraat 29",
    "sg:city":"Antwerpen",
    "sg:classifiers":[
        {
            "category":"Shopping",
            "subcategory":"Clothing, Apparel, & Fashions",
            "type":"Retail Goods"
        }
    ],
    "sg:phone":"+32 3 257 16 82",
    "sg:postcode":"2018",
    "sg:province":"Antwerpen",
    "sg:tags":[
        "-",
        "clothing",
        "child"
    ],
    "wof:name":"Simple Kids",
    "wof:placetype":"venue"
},
  "geometry": {"coordinates":[4.4089818001,51.2099609375],"type":"Point"}
}