{
  "type": "Feature",
  "properties": {
    "iso:country":"BE",
    "sg:address":"Rue Ren\u00c9-gobert 6",
    "sg:city":"Sombreffe",
    "sg:orig_category":"M\u00e9decins and sp\u00e9cialistes",
    "sg:phone":"+32 71 88 88 50",
    "sg:postcode":"5140",
    "sg:province":"Namur",
    "wof:name":"D. Gilbert",
    "wof:placetype":"venue"
},
  "geometry": {"coordinates":[4.5775408745,50.5150794983],"type":"Point"}
}