{
  "type": "Feature",
  "properties": {
    "iso:country":"BE",
    "sg:address":"Dikkebusseweg 344ba",
    "sg:city":"Ieper",
    "sg:orig_category":"Installatie van houten of kunststof schrijnwerk",
    "sg:phone":"+32 57 21 86 58",
    "sg:postcode":"8908",
    "sg:province":"West-Vlaanderen",
    "wof:name":"Vitse Rudy",
    "wof:placetype":"venue"
},
  "geometry": {"coordinates":[2.8475339413,50.8267745972],"type":"Point"}
}