{
  "type": "Feature",
  "properties": {
    "iso:country":"BE",
    "sg:address":"Hoeverbergweg 26",
    "sg:city":"Opglabbeek",
    "sg:classifiers":[
        {
            "category":"Personal",
            "subcategory":"Beauty Salon",
            "type":"Services"
        }
    ],
    "sg:phone":"+32 89 85 53 19",
    "sg:postcode":"3660",
    "sg:province":"Limburg",
    "sg:tags":[
        "de",
        "coiffure"
    ],
    "wof:name":"Kapsalon Martine",
    "wof:placetype":"venue"
},
  "geometry": {"coordinates":[5.5915951729,51.0323524475],"type":"Point"}
}