{
  "type": "Feature",
  "properties": {
    "iso:country":"BE",
    "sg:address":"Rue De La Station 2",
    "sg:city":"Dinant",
    "sg:orig_category":"Installatie van houten of kunststof schrijnwerk Installatie van metalen schrijnwerk Woningbouw",
    "sg:phone":"+32 82 21 95 12",
    "sg:postcode":"5500",
    "sg:province":"Namur",
    "wof:name":"Ts Bati",
    "wof:placetype":"venue"
},
  "geometry": {"coordinates":[4.9103012085,50.2602386475],"type":"Point"}
}