{
  "type": "Feature",
  "properties": {
    "addr:full":"Rue D'ab\u00c9e 25 Tinlot Li\u00e8ge 4557",
    "addr:housenumber":"25",
    "addr:postcode":"4557",
    "addr:street":"Rue D'Abe \u0301E",
    "iso:country":"BE",
    "sg:address":"Rue D'ab\u00c9e 25",
    "sg:city":"Tinlot",
    "sg:orig_category":"Eleveurs de bovins",
    "sg:phone":"+32 85 51 21 76",
    "sg:postcode":"4557",
    "sg:province":"Li\u00e8ge",
    "wof:name":"Emile Collinge",
    "wof:placetype":"venue"
},
  "geometry": {"coordinates":[5.3560509682,50.4726104736],"type":"Point"}
}