{
  "type": "Feature",
  "properties": {
    "addr:full":"Bakelaarstraat 22 Mechelen Antwerpen 2800",
    "addr:housenumber":"22",
    "addr:postcode":"2800",
    "addr:street":"Bakelaarstraat",
    "iso:country":"BE",
    "sg:address":"Bakelaarstraat 22",
    "sg:city":"Mechelen",
    "sg:classifiers":[
        {
            "category":"Communications",
            "type":"Services"
        }
    ],
    "sg:phone":"+32 15 28 70 56",
    "sg:postcode":"2800",
    "sg:province":"Antwerpen",
    "sg:tags":[
        "telecommunication"
    ],
    "wof:name":"P.c. Service",
    "wof:placetype":"venue"
},
  "geometry": {"coordinates":[4.488535881,51.0308609009],"type":"Point"}
}