{
  "type": "Feature",
  "properties": {
    "iso:country":"BE",
    "sg:address":"Avenue Bourg J. Materne 264",
    "sg:city":"Namur",
    "sg:orig_category":"Mat\u00e9riaux de construction Gr",
    "sg:phone":"+32 81 30 09 42",
    "sg:postcode":"5100",
    "sg:province":"Namur",
    "wof:name":"Lambert & F-d",
    "wof:placetype":"venue"
},
  "geometry": {"coordinates":[4.8713750839,50.4566345215],"type":"Point"}
}