{
  "type": "Feature",
  "properties": {
    "iso:country":"BE",
    "sg:address":"Koolsveldlaan 118",
    "sg:city":"Wijnegem",
    "sg:orig_category":"Schoonheidssalons",
    "sg:phone":"+32 3 354 01 42",
    "sg:postcode":"2110",
    "sg:province":"Antwerpen",
    "wof:name":"Rita Bos",
    "wof:placetype":"venue"
},
  "geometry": {"coordinates":[4.511785984,51.2226600647],"type":"Point"}
}