{
  "type": "Feature",
  "properties": {
    "iso:country":"BE",
    "sg:address":"Stationsstraat 16",
    "sg:city":"Waregem",
    "sg:orig_category":"Artsen and specialisten Medische and orthopedische apparaten",
    "sg:phone":"+32 56 60 63 30",
    "sg:postcode":"8790",
    "sg:province":"West-Vlaanderen",
    "wof:name":"Bandawar",
    "wof:placetype":"venue"
},
  "geometry": {"coordinates":[3.4316830635,50.8873977661],"type":"Point"}
}