{
  "type": "Feature",
  "properties": {
    "addr:full":"Piers De Raveschootlaan 91b2 Knokke-heist West-Vlaanderen 8300",
    "addr:housenumber":"91b2",
    "addr:postcode":"8300",
    "addr:street":"Piers;Raveschootlaan",
    "iso:country":"BE",
    "sg:address":"Piers De Raveschootlaan 91b2",
    "sg:city":"Knokke-heist",
    "sg:orig_category":"Etalage- and showroomontwerpers",
    "sg:phone":"+32 50 60 93 77",
    "sg:postcode":"8300",
    "sg:province":"West-Vlaanderen",
    "wof:name":"Patsy Stepman",
    "wof:placetype":"venue"
},
  "geometry": {"coordinates":[3.28905797,51.3453483582],"type":"Point"}
}