{
  "type": "Feature",
  "properties": {
    "iso:country":"BE",
    "sg:address":"Brouwersvliet 23",
    "sg:city":"Antwerpen",
    "sg:classifiers":[
        {
            "category":"Arena",
            "subcategory":"Sports Club",
            "type":"Entertainment"
        }
    ],
    "sg:phone":"+32 3 233 80 71",
    "sg:postcode":"2000",
    "sg:province":"Antwerpen",
    "sg:tags":[
        "graphite"
    ],
    "wof:name":"Schunk Benelux Nv",
    "wof:placetype":"venue"
},
  "geometry": {"coordinates":[4.4030132294,51.2272415161],"type":"Point"}
}