{
  "type": "Feature",
  "properties": {
    "addr:full":"Rue Saint-roch 26 Neufch\u00e2teau Luxembourg 6840",
    "addr:housenumber":"26",
    "addr:postcode":"6840",
    "addr:street":"Rue Saint-Roch",
    "iso:country":"BE",
    "sg:address":"Rue Saint-roch 26",
    "sg:city":"Neufch\u00e2teau",
    "sg:classifiers":[
        {
            "category":"Shopping",
            "subcategory":"Books",
            "type":"Retail Goods"
        }
    ],
    "sg:phone":"+32 61 27 15 12",
    "sg:postcode":"6840",
    "sg:province":"Luxembourg",
    "sg:tags":[
        "bookseller"
    ],
    "wof:name":"Oxyg\u00e8ne (librairie)",
    "wof:placetype":"venue"
},
  "geometry": {"coordinates":[5.4343662262,49.8429832458],"type":"Point"}
}