{
  "type": "Feature",
  "properties": {
    "addr:full":"Rue De Marcasse 20 Colfontaine Hainaut 7340",
    "addr:housenumber":"20",
    "addr:postcode":"7340",
    "addr:street":"Rue De Marcasse",
    "iso:country":"BE",
    "sg:address":"Rue De Marcasse 20",
    "sg:city":"Colfontaine",
    "sg:orig_category":"Slagers",
    "sg:phone":"+32 65 67 27 51",
    "sg:postcode":"7340",
    "sg:province":"Hainaut",
    "wof:name":"Baudouin Baland",
    "wof:placetype":"venue"
},
  "geometry": {"coordinates":[3.8366758823,50.4091644287],"type":"Point"}
}