{
  "type": "Feature",
  "properties": {
    "addr:full":"Eikenstraat 74 Rumst (reet) Antwerpen 2840",
    "addr:housenumber":"74",
    "addr:postcode":"2840",
    "addr:street":"Eikenstraat",
    "iso:country":"BE",
    "sg:address":"Eikenstraat 74",
    "sg:city":"Rumst (reet)",
    "sg:classifiers":[
        {
            "category":"Home & Garden",
            "subcategory":"Furniture",
            "type":"Retail Goods"
        }
    ],
    "sg:phone":"+32 3 844 75 05",
    "sg:postcode":"2840",
    "sg:province":"Antwerpen",
    "sg:tags":[
        "-"
    ],
    "wof:name":"Structures Bvba Bvba",
    "wof:placetype":"venue"
},
  "geometry": {"coordinates":[4.4111790657,51.1047096252],"type":"Point"}
}