{
  "type": "Feature",
  "properties": {
    "iso:country":"BE",
    "sg:address":"Rue Dr. Henri Schaltin 47",
    "sg:city":"Spa",
    "sg:classifiers":[
        {
            "category":"Cafe",
            "type":"Food & Drink"
        }
    ],
    "sg:phone":"+32 87 77 40 51",
    "sg:postcode":"4900",
    "sg:province":"Li\u00e8ge",
    "sg:tags":[
        "caf\u00e9s"
    ],
    "wof:name":"Caf\u00c9 Des Sportifs",
    "wof:placetype":"venue"
},
  "geometry": {"coordinates":[5.8662471771,50.4910736084],"type":"Point"}
}