{
  "type": "Feature",
  "properties": {
    "iso:country":"BE",
    "sg:address":"Rue De Spa 176",
    "sg:city":"Stavelot (francorchamps)",
    "sg:classifiers":[
        {
            "category":"Personal",
            "subcategory":"Beauty Salon",
            "type":"Services"
        }
    ],
    "sg:phone":"+32 87 27 50 40",
    "sg:postcode":"4970",
    "sg:province":"Li\u00e8ge",
    "sg:tags":[
        "lady",
        "-",
        "hairdressing"
    ],
    "wof:name":"Elly Coiffure",
    "wof:placetype":"venue"
},
  "geometry": {"coordinates":[5.9528617859,50.4591445923],"type":"Point"}
}