{
  "type": "Feature",
  "properties": {
    "iso:country":"BE",
    "sg:address":"Rue Scailquin 37 Box 6",
    "sg:city":"Bruxelles (saint-josse-ten-noode)",
    "sg:classifiers":[
        {
            "category":"Personal",
            "subcategory":"Beauty Salon",
            "type":"Services"
        }
    ],
    "sg:phone":"+32 2 223 06 00",
    "sg:postcode":"1210",
    "sg:province":"Bruxelles-Capitale",
    "wof:name":"Albert V",
    "wof:placetype":"venue"
},
  "geometry": {"coordinates":[4.370516777,50.8500823975],"type":"Point"}
}