{
  "type": "Feature",
  "properties": {
    "addr:full":"Rue Petit Avin 54 Clavier Li\u00e8ge 4560",
    "addr:housenumber":"54",
    "addr:postcode":"4560",
    "addr:street":"Rue Petit Avin",
    "iso:country":"BE",
    "sg:address":"Rue Petit Avin 54",
    "sg:city":"Clavier",
    "sg:orig_category":"Rundveehouders",
    "sg:phone":"+32 83 63 31 32",
    "sg:postcode":"4560",
    "sg:province":"Li\u00e8ge",
    "wof:name":"Neufcoeur Joseph & Didier",
    "wof:placetype":"venue"
},
  "geometry": {"coordinates":[5.2889199257,50.3984260559],"type":"Point"}
}