{
  "type": "Feature",
  "properties": {
    "addr:full":"Rue De La Plume 14 Bruxelles Bruxelles-Capitale 1000",
    "addr:housenumber":"14",
    "addr:postcode":"1000",
    "addr:street":"Rue De La Plume",
    "iso:country":"BE",
    "sg:address":"Rue De La Plume 14",
    "sg:city":"Bruxelles",
    "sg:classifiers":[
        {
            "category":"Professional",
            "subcategory":"Art Services",
            "type":"Services"
        }
    ],
    "sg:phone":"+32 2 513 25 75",
    "sg:postcode":"1000",
    "sg:province":"Bruxelles-Capitale",
    "sg:tags":[
        "graphic",
        "designer"
    ],
    "wof:name":"Daplincourt D",
    "wof:placetype":"venue"
},
  "geometry": {"coordinates":[4.3451390266,50.8361701965],"type":"Point"}
}