{
  "type": "Feature",
  "properties": {
    "iso:country":"BE",
    "sg:address":"Rue No\u00ebl 44",
    "sg:city":"Waterloo",
    "sg:classifiers":[
        {
            "category":"Building & Trades",
            "subcategory":"Landscaping Services",
            "type":"Services"
        }
    ],
    "sg:phone":"+32 2 384 93 46",
    "sg:postcode":"1410",
    "sg:province":"Brabant Wallon",
    "sg:tags":[
        "gardening",
        "garden",
        "maintenance"
    ],
    "wof:name":"Musette R",
    "wof:placetype":"venue"
},
  "geometry": {"coordinates":[4.3684439659,50.7054023743],"type":"Point"}
}