{
  "type": "Feature",
  "properties": {
    "addr:full":"Prins Boudewijnlaan 228 Edegem Antwerpen 2650",
    "addr:housenumber":"228",
    "addr:postcode":"2650",
    "addr:street":"Prins Boudewijnlaan",
    "iso:country":"BE",
    "sg:address":"Prins Boudewijnlaan 228",
    "sg:city":"Edegem",
    "sg:classifiers":[
        {
            "category":"Health Services",
            "subcategory":"Doctor",
            "type":"Services"
        }
    ],
    "sg:phone":"+32 3 449 14 03",
    "sg:postcode":"2650",
    "sg:province":"Antwerpen",
    "sg:tags":[
        "medicinephysicians",
        "surgeon"
    ],
    "wof:name":"Dr Huyghe Marc",
    "wof:placetype":"venue"
},
  "geometry": {"coordinates":[4.4303569794,51.1573028564],"type":"Point"}
}