{
  "type": "Feature",
  "properties": {
    "addr:full":"Route De Dieupart 41 Aywaille Li\u00e8ge 4920",
    "addr:housenumber":"41",
    "addr:postcode":"4920",
    "addr:street":"Route De Dieupart",
    "iso:country":"BE",
    "sg:address":"Route De Dieupart 41",
    "sg:city":"Aywaille",
    "sg:classifiers":[
        {
            "category":"Home & Garden",
            "subcategory":"Carpets & Floor Coverings",
            "type":"Retail Goods"
        }
    ],
    "sg:phone":"+32 4 384 41 41",
    "sg:postcode":"4920",
    "sg:province":"Li\u00e8ge",
    "sg:tags":[
        "houses",
        "shed"
    ],
    "wof:name":"Outil Leloup S.a.",
    "wof:placetype":"venue"
},
  "geometry": {"coordinates":[5.6915960312,50.4767913818],"type":"Point"}
}