{
  "type": "Feature",
  "properties": {
    "addr:full":"Eksterdreef 9 Schilde Antwerpen 2970",
    "addr:housenumber":"9",
    "addr:postcode":"2970",
    "addr:street":"Eksterdreef",
    "iso:country":"BE",
    "sg:address":"Eksterdreef 9",
    "sg:city":"Schilde",
    "sg:classifiers":[
        {
            "category":"Real Estate",
            "subcategory":"Real Estate Services",
            "type":"Services"
        }
    ],
    "sg:phone":"+32 3 385 99 44",
    "sg:postcode":"2970",
    "sg:province":"Antwerpen",
    "wof:name":"Real Estate Management Nv",
    "wof:placetype":"venue"
},
  "geometry": {"coordinates":[4.6145401001,51.2487754822],"type":"Point"}
}