{
  "type": "Feature",
  "properties": {
    "iso:country":"BE",
    "sg:address":"Grotstraat 42",
    "sg:city":"Oostrozebeke",
    "sg:orig_category":"Plaatsen van vloer- and muurbekleding Schilders",
    "sg:phone":"+32 51 40 37 18",
    "sg:postcode":"8780",
    "sg:province":"West-Vlaanderen",
    "wof:name":"Devaere",
    "wof:placetype":"venue"
},
  "geometry": {"coordinates":[3.3539810181,50.9469604492],"type":"Point"}
}