{
  "type": "Feature",
  "properties": {
    "iso:country":"BE",
    "sg:address":"Rue Monplaisir 2",
    "sg:city":"Beloeil",
    "sg:orig_category":"RESTAURANTS: CAF\u00c9S",
    "sg:phone":"+32 69 68 88 89",
    "sg:postcode":"7972",
    "sg:province":"Hainaut",
    "wof:name":"Taverne Le Fournil",
    "wof:placetype":"venue"
},
  "geometry": {"coordinates":[3.6740939617,50.5614471436],"type":"Point"}
}