{
  "type": "Feature",
  "properties": {
    "addr:full":"Grand'rue 10 Manage Hainaut 7170",
    "addr:housenumber":"10",
    "addr:postcode":"7170",
    "addr:street":"Grand'Rue",
    "iso:country":"BE",
    "sg:address":"Grand'rue 10",
    "sg:city":"Manage",
    "sg:classifiers":[
        {
            "category":"Shopping",
            "subcategory":"Clothing, Apparel, & Fashions",
            "type":"Retail Goods"
        }
    ],
    "sg:phone":"+32 64 55 66 31",
    "sg:postcode":"7170",
    "sg:province":"Hainaut",
    "sg:tags":[
        "-",
        "clothing",
        "child"
    ],
    "wof:name":"Maryd\u00e9e",
    "wof:placetype":"venue"
},
  "geometry": {"coordinates":[4.2365279198,50.5037574768],"type":"Point"}
}