{
  "type": "Feature",
  "properties": {
    "addr:full":"Rodebeukendreef 4a Gent (gentbrugge) Oost-Vlaanderen 9050",
    "addr:housenumber":"4a",
    "addr:postcode":"9050",
    "addr:street":"Rodebeukendreef",
    "iso:country":"BE",
    "sg:address":"Rodebeukendreef 4a",
    "sg:city":"Gent (gentbrugge)",
    "sg:classifiers":[
        {
            "category":"Personal",
            "subcategory":"Beauty Salon",
            "type":"Services"
        }
    ],
    "sg:phone":"+32 9 232 50 35",
    "sg:postcode":"9050",
    "sg:province":"Oost-Vlaanderen",
    "wof:name":"Acucha Blancquaert Chantal",
    "wof:placetype":"venue"
},
  "geometry": {"coordinates":[3.7632091045,51.0461158752],"type":"Point"}
}