{
  "type": "Feature",
  "properties": {
    "addr:full":"Meeuwenlaan 13 Oostende West-Vlaanderen 8400",
    "addr:housenumber":"13",
    "addr:postcode":"8400",
    "addr:street":"Meeuwenlaan",
    "iso:country":"BE",
    "sg:address":"Meeuwenlaan 13",
    "sg:city":"Oostende",
    "sg:orig_category":"M\u00e9decins and sp\u00e9cialistes. M\u00e9decines alternatives",
    "sg:phone":"+32 59 70 62 11",
    "sg:postcode":"8400",
    "sg:province":"West-Vlaanderen",
    "wof:name":"Pierre Schramme",
    "wof:placetype":"venue"
},
  "geometry": {"coordinates":[2.9166400433,51.2153930664],"type":"Point"}
}