{
  "type": "Feature",
  "properties": {
    "addr:full":"Dreef 23 Zomergem Oost-Vlaanderen 9930",
    "addr:housenumber":"23",
    "addr:postcode":"9930",
    "addr:street":"Dreef",
    "iso:country":"BE",
    "sg:address":"Dreef 23",
    "sg:city":"Zomergem",
    "sg:classifiers":[
        {
            "category":"Banks & Credit Unions",
            "subcategory":"Bank",
            "type":"Services"
        }
    ],
    "sg:phone":"+32 91725663",
    "sg:postcode":"9930",
    "sg:province":"Oost-Vlaanderen",
    "wof:name":"Caisse Nationale De, Cr\u00e9dit Professionnel",
    "wof:placetype":"venue"
},
  "geometry": {"coordinates":[3.5626559258,51.1189804077],"type":"Point"}
}