{
  "type": "Feature",
  "properties": {
    "addr:full":"Voorstadstraat 2ba Komen-waasten/comines-warneton Hainaut 7780",
    "addr:housenumber":"7780",
    "addr:street":"Voorstadstraat",
    "iso:country":"BE",
    "sg:address":"Voorstadstraat 2ba",
    "sg:city":"Komen-waasten/comines-warneton",
    "sg:orig_category":"Zalen voor culturele evenementen",
    "sg:phone":"+32 56 55 65 39",
    "sg:postcode":"7780",
    "sg:province":"Hainaut",
    "wof:name":"Centre Culturel",
    "wof:placetype":"venue"
},
  "geometry": {"coordinates":[2.9984300137,50.7863311768],"type":"Point"}
}