{
  "type": "Feature",
  "properties": {
    "addr:full":"Stationsstraat 125 Landen Vlaams-Brabant 3400",
    "addr:housenumber":"125",
    "addr:postcode":"3400",
    "addr:street":"Stationsstraat",
    "iso:country":"BE",
    "sg:address":"Stationsstraat 125",
    "sg:city":"Landen",
    "sg:classifiers":[
        {
            "category":"Building & Trades",
            "subcategory":"Electrical",
            "type":"Services"
        }
    ],
    "sg:phone":"+32 11 88 10 32",
    "sg:postcode":"3400",
    "sg:province":"Vlaams-Brabant",
    "sg:tags":[
        "electric",
        "-",
        "housewiring",
        "contractor"
    ],
    "wof:name":"All Electric",
    "wof:placetype":"venue"
},
  "geometry": {"coordinates":[5.0811100006,50.7489776611],"type":"Point"}
}