{
  "type": "Feature",
  "properties": {
    "addr:full":"Rue Pierre-joseph Dum\u00e9nil 1 Mons Hainaut 7000",
    "addr:housenumber":"1",
    "addr:postcode":"7000",
    "addr:street":"Rue Pierre-Joseph Dume\u0301Nil;Hainaut",
    "iso:country":"BE",
    "sg:address":"Rue Pierre-joseph Dum\u00e9nil 1",
    "sg:city":"Mons",
    "sg:classifiers":[
        {
            "category":"Personal",
            "subcategory":"Beauty Salon",
            "type":"Services"
        }
    ],
    "sg:phone":"+32 64 36 62 98",
    "sg:postcode":"7000",
    "sg:province":"Hainaut",
    "sg:tags":[
        "slimming"
    ],
    "wof:name":"Eve-line",
    "wof:placetype":"venue"
},
  "geometry": {"coordinates":[3.9558980465,50.4596252441],"type":"Point"}
}