{
  "type": "Feature",
  "properties": {
    "iso:country":"BE",
    "sg:address":"Remp. Des Arbalestriers 1",
    "sg:city":"Le Roeulx",
    "sg:classifiers":[
        {
            "category":"Cafe",
            "type":"Food & Drink"
        }
    ],
    "sg:phone":"+32 64 66 38 20",
    "sg:postcode":"7070",
    "sg:province":"Hainaut",
    "sg:tags":[
        "caf\u00e9s"
    ],
    "wof:name":"Athl\u00c9tique Club Le Roeulx",
    "wof:placetype":"venue"
},
  "geometry": {"coordinates":[4.1133651733,50.5023193359],"type":"Point"}
}