{
  "type": "Feature",
  "properties": {
    "iso:country":"BE",
    "sg:address":"Rue Des Deux Eglises 14b16",
    "sg:city":"Brussel/bruxelles",
    "sg:classifiers":[
        {
            "category":"Insurance",
            "subcategory":"Life Insurance",
            "type":"Services"
        }
    ],
    "sg:phone":"+32 2 220 32 11",
    "sg:postcode":"1000",
    "sg:province":"Bruxelles-Capitale",
    "sg:tags":[
        "compagnies",
        "habitation",
        "assurance",
        "vie"
    ],
    "wof:name":"Nationale Suisse",
    "wof:placetype":"venue"
},
  "geometry": {"coordinates":[4.3722939491,50.8459777832],"type":"Point"}
}