{
  "type": "Feature",
  "properties": {
    "iso:country":"BE",
    "sg:address":"Dr\u00e8ve Richelle 102",
    "sg:city":"Waterloo",
    "sg:classifiers":[
        {
            "category":"Shopping",
            "subcategory":"Clothing, Apparel, & Fashions",
            "type":"Retail Goods"
        }
    ],
    "sg:phone":"+32 2 354 80 19",
    "sg:postcode":"1410",
    "sg:province":"Brabant Wallon",
    "sg:tags":[
        "leather",
        "-",
        "buckskin",
        "clothing"
    ],
    "wof:name":"Gyma (ex)",
    "wof:placetype":"venue"
},
  "geometry": {"coordinates":[4.4099531174,50.7075386047],"type":"Point"}
}