{
  "type": "Feature",
  "properties": {
    "addr:full":"Rue Bordiau 24 Brussel (brussel) Bruxelles-Capitale 1000",
    "addr:housenumber":"24",
    "addr:postcode":"1000",
    "addr:street":"Rue Bordiau",
    "iso:country":"BE",
    "sg:address":"Rue Bordiau 24",
    "sg:city":"Brussel (brussel)",
    "sg:orig_category":"Kapsalons",
    "sg:phone":"+32 2 734 57 36",
    "sg:postcode":"1000",
    "sg:province":"Bruxelles-Capitale",
    "wof:name":"Elisabeth",
    "wof:placetype":"venue"
},
  "geometry": {"coordinates":[4.388548851,50.847869873],"type":"Point"}
}