{
  "type": "Feature",
  "properties": {
    "iso:country":"BE",
    "sg:address":"Rue Joseph Maisin 12",
    "sg:city":"Grez-doiceau (nethen)",
    "sg:classifiers":[
        {
            "category":"Bars & Pubs",
            "type":"Food & Drink"
        }
    ],
    "sg:phone":"+32 10 86 07 84",
    "sg:postcode":"1390",
    "sg:province":"Brabant Wallon",
    "sg:tags":[
        "tavern"
    ],
    "wof:name":"Taverne De La Vall\u00e9e",
    "wof:placetype":"venue"
},
  "geometry": {"coordinates":[4.6787848473,50.7838172913],"type":"Point"}
}