{
  "type": "Feature",
  "properties": {
    "addr:full":"Rue Des Brasseurs 11 Chatelet Hainaut 6200",
    "addr:housenumber":"11",
    "addr:postcode":"6200",
    "addr:street":"Rue Des Brasseurs;Hainaut",
    "iso:country":"BE",
    "sg:address":"Rue Des Brasseurs 11",
    "sg:city":"Chatelet",
    "sg:orig_category":"Bagage and lederwaren",
    "sg:phone":"+32 71 38 23 05",
    "sg:postcode":"6200",
    "sg:province":"Hainaut",
    "wof:name":"Les Ma\u00cetres Maroquiniers",
    "wof:placetype":"venue"
},
  "geometry": {"coordinates":[4.5195159912,50.4039535522],"type":"Point"}
}