{
  "type": "Feature",
  "properties": {
    "addr:full":"Rue Lahaut 7 Box 4 Chaumont-gistoux Brabant Wallon 1325",
    "addr:housenumber":"7;4",
    "addr:postcode":"1325",
    "addr:street":"Rue Lahaut;Box",
    "iso:country":"BE",
    "sg:address":"Rue Lahaut 7 Box 4",
    "sg:city":"Chaumont-gistoux",
    "sg:classifiers":[
        {
            "category":"Real Estate",
            "subcategory":"Surveying",
            "type":"Services"
        }
    ],
    "sg:phone":"+32 10 68 94 70",
    "sg:postcode":"1325",
    "sg:province":"Brabant Wallon",
    "sg:tags":[
        "lettering",
        "letter"
    ],
    "wof:name":"Texto",
    "wof:placetype":"venue"
},
  "geometry": {"coordinates":[4.7225818634,50.6777076721],"type":"Point"}
}