{
  "type": "Feature",
  "properties": {
    "addr:full":"Swimmenweyerweg 14 Genk Limburg 3600",
    "addr:housenumber":"14",
    "addr:postcode":"3600",
    "addr:street":"Swimmenweyerweg",
    "iso:country":"BE",
    "sg:address":"Swimmenweyerweg 14",
    "sg:city":"Genk",
    "sg:classifiers":[
        {
            "category":"Military Area",
            "subcategory":"Air Force Base",
            "type":"Public Place"
        }
    ],
    "sg:phone":"+32 89 36 19 55",
    "sg:postcode":"3600",
    "sg:province":"Limburg",
    "sg:tags":[
        "installation",
        "assembly"
    ],
    "wof:name":"Isolair-engineering Systems Nv",
    "wof:placetype":"venue"
},
  "geometry": {"coordinates":[5.4990148544,50.9635848999],"type":"Point"}
}