{
  "type": "Feature",
  "properties": {
    "addr:full":"Schomveld 13 Essen Antwerpen 2910",
    "addr:housenumber":"13",
    "addr:postcode":"2910",
    "addr:street":"Schomveld",
    "iso:country":"BE",
    "sg:address":"Schomveld 13",
    "sg:city":"Essen",
    "sg:classifiers":[
        {
            "category":"Home & Garden",
            "subcategory":"Carpets & Floor Coverings",
            "type":"Retail Goods"
        }
    ],
    "sg:phone":"+32 3 677 31 68",
    "sg:postcode":"2910",
    "sg:province":"Antwerpen",
    "sg:tags":[
        "tile"
    ],
    "wof:name":"Peeters L",
    "wof:placetype":"venue"
},
  "geometry": {"coordinates":[4.4512248039,51.4495849609],"type":"Point"}
}