{
  "type": "Feature",
  "properties": {
    "addr:full":"Rue De Stache 5ba Mettet Namur 5644",
    "addr:housenumber":"5ba",
    "addr:postcode":"5644",
    "addr:street":"Rue De Stache",
    "iso:country":"BE",
    "sg:address":"Rue De Stache 5ba",
    "sg:city":"Mettet",
    "sg:classifiers":[
        {
            "category":"Personal",
            "subcategory":"Beauty Salon",
            "type":"Services"
        }
    ],
    "sg:phone":"+32 71 72 94 44",
    "sg:postcode":"5644",
    "sg:province":"Namur",
    "sg:tags":[
        "de",
        "coiffure"
    ],
    "wof:name":"Coiffure Christine",
    "wof:placetype":"venue"
},
  "geometry": {"coordinates":[4.7235269547,50.2952842712],"type":"Point"}
}