{
  "type": "Feature",
  "properties": {
    "iso:country":"BE",
    "sg:address":"Kanaalstraat 8",
    "sg:city":"Lummen",
    "sg:classifiers":[
        {
            "category":"Transit Center",
            "subcategory":"Freight",
            "type":"Transportation"
        }
    ],
    "sg:phone":"+32 11 42 10 33",
    "sg:postcode":"3560",
    "sg:province":"Limburg",
    "sg:tags":[
        "tanker",
        "-",
        "transport"
    ],
    "wof:name":"Limburgs Tanktransport",
    "wof:placetype":"venue"
},
  "geometry": {"coordinates":[5.2278242111,51.0219192505],"type":"Point"}
}