{
  "type": "Feature",
  "properties": {
    "iso:country":"BE",
    "sg:address":"Route Du Fawetay 6",
    "sg:city":"Jalhay",
    "sg:classifiers":[
        {
            "category":"Arena",
            "subcategory":"Sports Club",
            "type":"Entertainment"
        }
    ],
    "sg:phone":"+32 87 64 61 14",
    "sg:postcode":"4845",
    "sg:province":"Li\u00e8ge",
    "sg:tags":[
        "de"
    ],
    "wof:name":"Automob.cl.hautes Fagnes",
    "wof:placetype":"venue"
},
  "geometry": {"coordinates":[5.9691720009,50.5544815063],"type":"Point"}
}