{
  "type": "Feature",
  "properties": {
    "addr:full":"Gentse Steenweg 316 Lokeren Oost-Vlaanderen 9160",
    "addr:housenumber":"316",
    "addr:postcode":"9160",
    "addr:street":"Gentse Steenweg",
    "iso:country":"BE",
    "sg:address":"Gentse Steenweg 316",
    "sg:city":"Lokeren",
    "sg:orig_category":"Bloemen and planten Geschenken and souvenirs Tuinbenodigdheden",
    "sg:phone":"+32 9 348 26 66",
    "sg:postcode":"9160",
    "sg:province":"Oost-Vlaanderen",
    "wof:name":"Bloemencenter Raman",
    "wof:placetype":"venue"
},
  "geometry": {"coordinates":[3.922107935,51.1108779907],"type":"Point"}
}