{
  "type": "Feature",
  "properties": {
    "addr:full":"Rue Jean-charles De Hugo 61 Tintigny Luxembourg 6730",
    "addr:housenumber":"61",
    "addr:postcode":"6730",
    "addr:street":"Rue Jean-Charles De Hugo",
    "iso:country":"BE",
    "sg:address":"Rue Jean-charles De Hugo 61",
    "sg:city":"Tintigny",
    "sg:orig_category":"Artsen and specialisten",
    "sg:phone":"+32 63 44 47 59",
    "sg:postcode":"6730",
    "sg:province":"Luxembourg",
    "wof:name":"B. Gadisseux",
    "wof:placetype":"venue"
},
  "geometry": {"coordinates":[5.4964671135,49.6644973755],"type":"Point"}
}