{
  "type": "Feature",
  "properties": {
    "addr:full":"Volkershouw 11 Wetteren Oost-Vlaanderen 9230",
    "addr:housenumber":"11",
    "addr:postcode":"9230",
    "addr:street":"Volkershouw",
    "iso:country":"BE",
    "sg:address":"Volkershouw 11",
    "sg:city":"Wetteren",
    "sg:orig_category":"Woningbouw",
    "sg:phone":"+32 9 369 54 83",
    "sg:postcode":"9230",
    "sg:province":"Oost-Vlaanderen",
    "wof:name":"Demo Home",
    "wof:placetype":"venue"
},
  "geometry": {"coordinates":[3.8529839516,50.970489502],"type":"Point"}
}