{
  "type": "Feature",
  "properties": {
    "addr:full":"Bld De La Constitution 40 Li\u00c8ge Li\u00e8ge 4020",
    "addr:housenumber":"40",
    "addr:postcode":"4020",
    "addr:street":"Bld De La Constitution",
    "iso:country":"BE",
    "sg:address":"Bld De La Constitution 40",
    "sg:city":"Li\u00c8ge",
    "sg:classifiers":[
        {
            "category":"Personal",
            "subcategory":"Beauty Salon",
            "type":"Services"
        }
    ],
    "sg:phone":"+32 4 344 14 43",
    "sg:postcode":"4020",
    "sg:province":"Li\u00e8ge",
    "sg:tags":[
        "de",
        "coiffure"
    ],
    "wof:name":"Coiffure Dimension",
    "wof:placetype":"venue"
},
  "geometry": {"coordinates":[5.5856361389,50.6432571411],"type":"Point"}
}