{
  "type": "Feature",
  "properties": {
    "addr:full":"Chauss\u00c9e De Beaumont 346 Mons Hainaut 7022",
    "addr:housenumber":"346",
    "addr:postcode":"7022",
    "addr:street":"Chausse\u0301E De Beaumont;Hainaut",
    "iso:country":"BE",
    "sg:address":"Chauss\u00c9e De Beaumont 346",
    "sg:city":"Mons",
    "sg:orig_category":"Huishoudapparaten, televisies and radio's IJzerwaren, bouw- and verfmaterialen Winkelinrichting and ",
    "sg:phone":"+32 65 58 64 36",
    "sg:postcode":"7022",
    "sg:province":"Hainaut",
    "wof:name":"Dutrieux Michel",
    "wof:placetype":"venue"
},
  "geometry": {"coordinates":[4.0181078911,50.4045410156],"type":"Point"}
}