{
  "type": "Feature",
  "properties": {
    "addr:full":"Rue Marcel Louis 34 Incourt (pi\u00e8trebais) Brabant Wallon 1315",
    "addr:housenumber":"34;1315",
    "addr:street":"Rue Marcel Louis;Brabant Wallon",
    "iso:country":"BE",
    "sg:address":"Rue Marcel Louis 34",
    "sg:city":"Incourt (pi\u00e8trebais)",
    "sg:classifiers":[
        {
            "category":"Professional",
            "subcategory":"Computer Services",
            "type":"Services"
        }
    ],
    "sg:phone":"+32 10 84 40 81",
    "sg:postcode":"1315",
    "sg:province":"Brabant Wallon",
    "sg:tags":[
        "-",
        "processing",
        "data"
    ],
    "wof:name":"Lacroix Electricit\u00e9",
    "wof:placetype":"venue"
},
  "geometry": {"coordinates":[4.799115181,50.6915283203],"type":"Point"}
}