{
  "type": "Feature",
  "properties": {
    "addr:full":"Tongersestraat 94 Bilzen Limburg 3740",
    "addr:housenumber":"94",
    "addr:postcode":"3740",
    "addr:street":"Tongersestraat",
    "iso:country":"BE",
    "sg:address":"Tongersestraat 94",
    "sg:city":"Bilzen",
    "sg:classifiers":[
        {
            "category":"Building & Trades",
            "subcategory":"Equipment Rental",
            "type":"Services"
        }
    ],
    "sg:phone":"+32 89 50 17 75",
    "sg:postcode":"3740",
    "sg:province":"Limburg",
    "sg:tags":[
        "use",
        "apparatus",
        "tool",
        "-",
        "professional",
        "machines"
    ],
    "wof:name":"Bilzen Verhuur",
    "wof:placetype":"venue"
},
  "geometry": {"coordinates":[5.5045099258,50.8632698059],"type":"Point"}
}