{
  "type": "Feature",
  "properties": {
    "iso:country":"BE",
    "sg:address":"Diksmuidelaan 211",
    "sg:city":"Berchem",
    "sg:orig_category":"Imprimeries and copyshops",
    "sg:phone":"+32 3 239 68 14",
    "sg:postcode":"2600",
    "sg:province":"Antwerpen",
    "wof:name":"Copymatic",
    "wof:placetype":"venue"
},
  "geometry": {"coordinates":[4.443857193,51.195438385],"type":"Point"}
}