{
  "type": "Feature",
  "properties": {
    "addr:full":"Place De La Victoire 11 Chatelet Hainaut 6200",
    "addr:housenumber":"11",
    "addr:postcode":"6200",
    "addr:street":"Place De La;Chatelet Hainaut",
    "iso:country":"BE",
    "sg:address":"Place De La Victoire 11",
    "sg:city":"Chatelet",
    "sg:classifiers":[
        {
            "category":"Restaurant",
            "type":"Food & Drink"
        }
    ],
    "sg:phone":"+32 71 39 54 70",
    "sg:postcode":"6200",
    "sg:province":"Hainaut",
    "wof:name":"China Garden",
    "wof:placetype":"venue"
},
  "geometry": {"coordinates":[4.5179800987,50.4041481018],"type":"Point"}
}