{
  "type": "Feature",
  "properties": {
    "addr:full":"Avenue Wilmart 18 Perwez Brabant Wallon 1360",
    "addr:housenumber":"18",
    "addr:postcode":"1360",
    "addr:street":"Avenue Wilmart",
    "iso:country":"BE",
    "sg:address":"Avenue Wilmart 18",
    "sg:city":"Perwez",
    "sg:orig_category":"Kansspelen",
    "sg:phone":"+32 81 65 69 69",
    "sg:postcode":"1360",
    "sg:province":"Brabant Wallon",
    "wof:name":"Ladbrokes",
    "wof:placetype":"venue"
},
  "geometry": {"coordinates":[4.8159527779,50.62449646],"type":"Point"}
}