{
  "type": "Feature",
  "properties": {
    "iso:country":"BE",
    "sg:address":"Genkerbaan 95",
    "sg:city":"Zonhoven",
    "sg:orig_category":"Kapsalons",
    "sg:phone":"+32 11 81 30 64",
    "sg:postcode":"3520",
    "sg:province":"Limburg",
    "wof:name":"Lea Claes",
    "wof:placetype":"venue"
},
  "geometry": {"coordinates":[5.3811731339,50.9915924072],"type":"Point"}
}