{
  "type": "Feature",
  "properties": {
    "iso:country":"BE",
    "sg:address":"Rue Des Brasseurs 8",
    "sg:city":"Bastogne",
    "sg:orig_category":"Agences d\u00b4interim and personnel temporaire",
    "sg:phone":"+32 61 21 41 40",
    "sg:postcode":"6600",
    "sg:province":"Luxembourg",
    "wof:name":"Adecco",
    "wof:placetype":"venue"
},
  "geometry": {"coordinates":[5.718670845,50.0038261414],"type":"Point"}
}