{
  "type": "Feature",
  "properties": {
    "iso:country":"BE",
    "sg:address":"Place Du Grand Sablon 5",
    "sg:city":"Bruxelles",
    "sg:classifiers":[
        {
            "category":"Manufacturing",
            "subcategory":"Metals",
            "type":"Manufacturing & Wholesale Goods"
        }
    ],
    "sg:phone":"+32 2 512 21 33",
    "sg:postcode":"1000",
    "sg:province":"Bruxelles-Capitale",
    "sg:tags":[
        "ornamental",
        "work",
        "-"
    ],
    "wof:name":"Costermans Sprl",
    "wof:placetype":"venue"
},
  "geometry": {"coordinates":[4.3545198441,50.8415298462],"type":"Point"}
}