{
  "type": "Feature",
  "properties": {
    "iso:country":"BE",
    "sg:address":"Rue Du Centre 39",
    "sg:city":"Li\u00c8ge",
    "sg:orig_category":"Diverse machines voor de nijverheid Gh",
    "sg:phone":"+32 4 229 52 99",
    "sg:postcode":"4000",
    "sg:province":"Li\u00e8ge",
    "wof:name":"Fumibat",
    "wof:placetype":"venue"
},
  "geometry": {"coordinates":[5.5520119667,50.6108283997],"type":"Point"}
}