{
  "type": "Feature",
  "properties": {
    "iso:country":"BE",
    "sg:address":"All\u00c9e Des Hortensias 0",
    "sg:city":"Waremme",
    "sg:orig_category":"Enseignement maternel and primaire",
    "sg:phone":"+32 19 32 67 77",
    "sg:postcode":"4300",
    "sg:province":"Li\u00e8ge",
    "wof:name":"Ecole Fond. Communale",
    "wof:placetype":"venue"
},
  "geometry": {"coordinates":[5.2616238594,50.6995887756],"type":"Point"}
}