{
  "type": "Feature",
  "properties": {
    "addr:full":"Rue Saint-georges 2 Tournai Hainaut 7500",
    "addr:housenumber":"2",
    "addr:postcode":"7500",
    "addr:street":"Rue Saint-Georges",
    "iso:country":"BE",
    "sg:address":"Rue Saint-georges 2",
    "sg:city":"Tournai",
    "sg:classifiers":[
        {
            "category":"Travel",
            "subcategory":"Hotels & Motels",
            "type":"Entertainment"
        }
    ],
    "sg:phone":"+32 69 22 50 35",
    "sg:postcode":"7500",
    "sg:province":"Hainaut",
    "wof:name":"Tour St-georges",
    "wof:placetype":"venue"
},
  "geometry": {"coordinates":[3.3856461048,50.6052055359],"type":"Point"}
}