{
  "type": "Feature",
  "properties": {
    "iso:country":"BE",
    "sg:address":"Molenstraat 52",
    "sg:city":"Essen",
    "sg:classifiers":[
        {
            "category":"Professional",
            "subcategory":"Accounting & Tax Preparation",
            "type":"Services"
        }
    ],
    "sg:phone":"+32 3 667 36 85",
    "sg:postcode":"2910",
    "sg:province":"Antwerpen",
    "sg:tags":[
        "accountant"
    ],
    "wof:name":"Bevers Achiel Bvba",
    "wof:placetype":"venue"
},
  "geometry": {"coordinates":[4.4616069794,51.4636421204],"type":"Point"}
}