{
  "type": "Feature",
  "properties": {
    "addr:full":"Avenue Des Hirondelles 2 Wemmel Vlaams-Brabant 1780",
    "addr:housenumber":"2",
    "addr:postcode":"1780",
    "addr:street":"Avenue Des Hirondelles;Vlaams-Brabant",
    "iso:country":"BE",
    "sg:address":"Avenue Des Hirondelles 2",
    "sg:city":"Wemmel",
    "sg:classifiers":[
        {
            "category":"Professional",
            "subcategory":"Management & Consulting",
            "type":"Services"
        }
    ],
    "sg:phone":"+32 2 460 27 52",
    "sg:postcode":"1780",
    "sg:province":"Vlaams-Brabant",
    "sg:tags":[
        "consultant"
    ],
    "wof:name":"Co-fintax",
    "wof:placetype":"venue"
},
  "geometry": {"coordinates":[4.3125720024,50.9218826294],"type":"Point"}
}