{
  "type": "Feature",
  "properties": {
    "iso:country":"BE",
    "sg:address":"Sint-augustinuslaan 4",
    "sg:city":"Vorst/forest",
    "sg:classifiers":[
        {
            "category":"Taxi",
            "type":"Transportation"
        }
    ],
    "sg:phone":"+32 2 345 10 48",
    "sg:postcode":"1190",
    "sg:province":"Bruxelles-Capitale",
    "sg:tags":[
        "taxi's"
    ],
    "wof:name":"Mohamed Adanouj",
    "wof:placetype":"venue"
},
  "geometry": {"coordinates":[4.3378748894,50.8167533875],"type":"Point"}
}