{
  "type": "Feature",
  "properties": {
    "addr:full":"Gauwelstraat 7 Zwevegem (heestert) West-Vlaanderen 8551",
    "addr:housenumber":"7",
    "addr:postcode":"8551",
    "addr:street":"Gauwelstraat",
    "iso:country":"BE",
    "sg:address":"Gauwelstraat 7",
    "sg:city":"Zwevegem (heestert)",
    "sg:classifiers":[
        {
            "category":"Shopping",
            "subcategory":"Bicycles & Sporting Goods",
            "type":"Retail Goods"
        }
    ],
    "sg:phone":"+32 56 64 80 31",
    "sg:postcode":"8551",
    "sg:province":"West-Vlaanderen",
    "sg:tags":[
        "-"
    ],
    "wof:name":"Defeyter",
    "wof:placetype":"venue"
},
  "geometry": {"coordinates":[3.4099149704,50.7821388245],"type":"Point"}
}