{
  "type": "Feature",
  "properties": {
    "iso:country":"BE",
    "sg:address":"De Heide 9",
    "sg:city":"Nijlen (kessel)",
    "sg:orig_category":"Imitation jewelry - Mfg.& Whol.",
    "sg:phone":"+32 3 480 19 06",
    "sg:postcode":"2560",
    "sg:province":"Antwerpen",
    "wof:name":"A.m.l. Bijoux",
    "wof:placetype":"venue"
},
  "geometry": {"coordinates":[4.6368141174,51.1566467285],"type":"Point"}
}