{
  "type": "Feature",
  "properties": {
    "iso:country":"BE",
    "sg:address":"Grand Rue 43",
    "sg:city":"Leuze-en-hainaut",
    "sg:classifiers":[
        {
            "category":"Shopping",
            "subcategory":"Clothing, Apparel, & Fashions",
            "type":"Retail Goods"
        }
    ],
    "sg:phone":"+32 69 66 40 73",
    "sg:postcode":"7900",
    "sg:province":"Hainaut",
    "sg:tags":[
        "underwear",
        "lingerie",
        "-"
    ],
    "wof:name":"New Look",
    "wof:placetype":"venue"
},
  "geometry": {"coordinates":[3.6189219952,50.599899292],"type":"Point"}
}