{
  "type": "Feature",
  "properties": {
    "addr:full":"Wervikstraat 75 Menen West-Vlaanderen 8930",
    "addr:housenumber":"75",
    "addr:postcode":"8930",
    "addr:street":"Wervikstraat",
    "iso:country":"BE",
    "sg:address":"Wervikstraat 75",
    "sg:city":"Menen",
    "sg:orig_category":"Slagers",
    "sg:phone":"+32 56 51 12 52",
    "sg:postcode":"8930",
    "sg:province":"West-Vlaanderen",
    "wof:name":"Ludwig Beeuwsaert",
    "wof:placetype":"venue"
},
  "geometry": {"coordinates":[3.1114299297,50.7965011597],"type":"Point"}
}