{
  "type": "Feature",
  "properties": {
    "iso:country":"BE",
    "sg:address":"Maldersesteenweg 20",
    "sg:city":"Londerzeel",
    "sg:orig_category":"Drogueries",
    "sg:phone":"+32 52 30 28 16",
    "sg:postcode":"1840",
    "sg:province":"Vlaams-Brabant",
    "wof:name":"Marcel Lamberts",
    "wof:placetype":"venue"
},
  "geometry": {"coordinates":[4.2809929848,51.0303993225],"type":"Point"}
}