{
  "type": "Feature",
  "properties": {
    "addr:full":"Lumenstraat 4b Vloesberg/flobecq Hainaut 7880",
    "addr:housenumber":"4b",
    "addr:postcode":"7880",
    "addr:street":"Lumenstraat",
    "iso:country":"BE",
    "sg:address":"Lumenstraat 4b",
    "sg:city":"Vloesberg/flobecq",
    "sg:orig_category":"Woningbouw",
    "sg:phone":"+32 68 44 84 98",
    "sg:postcode":"7880",
    "sg:province":"Hainaut",
    "wof:name":"Caro Construct",
    "wof:placetype":"venue"
},
  "geometry": {"coordinates":[3.7282629013,50.7654457092],"type":"Point"}
}