{
  "type": "Feature",
  "properties": {
    "addr:full":"Steenokkerzeelstraat 91 Zaventem Vlaams-Brabant 1930",
    "addr:housenumber":"91",
    "addr:postcode":"1930",
    "addr:street":"Steenokkerzeelstraat",
    "iso:country":"BE",
    "sg:address":"Steenokkerzeelstraat 91",
    "sg:city":"Zaventem",
    "sg:classifiers":[
        {
            "category":"Building & Trades",
            "subcategory":"Cleaning & Sanitation",
            "type":"Services"
        }
    ],
    "sg:phone":"+32 2 720 53 87",
    "sg:postcode":"1930",
    "sg:province":"Vlaams-Brabant",
    "sg:tags":[
        "cleaner",
        "window"
    ],
    "wof:name":"Haes",
    "wof:placetype":"venue"
},
  "geometry": {"coordinates":[4.4764261246,50.8865585327],"type":"Point"}
}