{
  "type": "Feature",
  "properties": {
    "iso:country":"BE",
    "sg:address":"Paardenmarkt 102",
    "sg:city":"Antwerpen",
    "sg:classifiers":[
        {
            "category":"Bars & Pubs",
            "type":"Food & Drink"
        }
    ],
    "sg:phone":"+32 3 225 09 73",
    "sg:postcode":"2000",
    "sg:province":"Antwerpen",
    "wof:name":"Grote Pint (de)",
    "wof:placetype":"venue"
},
  "geometry": {"coordinates":[4.4136781693,51.2245864868],"type":"Point"}
}