{
  "type": "Feature",
  "properties": {
    "addr:full":"Zamanstraat 51 Sint-niklaas Oost-Vlaanderen 9100",
    "addr:housenumber":"51",
    "addr:postcode":"9100",
    "addr:street":"Zamanstraat",
    "iso:country":"BE",
    "sg:address":"Zamanstraat 51",
    "sg:city":"Sint-niklaas",
    "sg:classifiers":[
        {
            "category":"Manufacturing",
            "subcategory":"Textiles",
            "type":"Manufacturing & Wholesale Goods"
        }
    ],
    "sg:phone":"+32 3 776 05 11",
    "sg:postcode":"9100",
    "sg:province":"Oost-Vlaanderen",
    "wof:name":"Albert Cauberghe",
    "wof:placetype":"venue"
},
  "geometry": {"coordinates":[4.1448631287,51.1675491333],"type":"Point"}
}