{
  "type": "Feature",
  "properties": {
    "iso:country":"BE",
    "sg:address":"Kruisweg 35",
    "sg:city":"Wuustwezel",
    "sg:orig_category":"Eleveurs and marchands de porcs",
    "sg:phone":"+32 3 669 69 83",
    "sg:postcode":"2990",
    "sg:province":"Antwerpen",
    "wof:name":"Koen Bernaerts",
    "wof:placetype":"venue"
},
  "geometry": {"coordinates":[4.5987839699,51.4033660889],"type":"Point"}
}