{
  "type": "Feature",
  "properties": {
    "addr:full":"Avenue Des Klauwaerts 38 Elsene/ixelles Bruxelles-Capitale 1050",
    "addr:housenumber":"38",
    "addr:postcode":"1050",
    "addr:street":"Avenue Des Klauwaerts",
    "iso:country":"BE",
    "sg:address":"Avenue Des Klauwaerts 38",
    "sg:city":"Elsene/ixelles",
    "sg:orig_category":"Jardinage",
    "sg:phone":"+32 2 647 43 33",
    "sg:postcode":"1050",
    "sg:province":"Bruxelles-Capitale",
    "wof:name":"Fe. Loncin",
    "wof:placetype":"venue"
},
  "geometry": {"coordinates":[4.3750219345,50.8202400208],"type":"Point"}
}