{
  "type": "Feature",
  "properties": {
    "iso:country":"BE",
    "sg:address":"Kerkstraat 22",
    "sg:city":"Vorselaar",
    "sg:classifiers":[
        {
            "category":"Building & Trades",
            "subcategory":"Pest Control",
            "type":"Services"
        }
    ],
    "sg:phone":"+32 14 51 12 77",
    "sg:postcode":"2290",
    "sg:province":"Antwerpen",
    "sg:tags":[
        "painting",
        "contractor"
    ],
    "wof:name":"Van Den Broeck F Schilder- & Behangwerken",
    "wof:placetype":"venue"
},
  "geometry": {"coordinates":[4.7700548172,51.202495575],"type":"Point"}
}