{
  "type": "Feature",
  "properties": {
    "iso:country":"BE",
    "sg:address":"Pannestraat 2",
    "sg:city":"Veurne",
    "sg:classifiers":[
        {
            "category":"Cafe",
            "type":"Food & Drink"
        }
    ],
    "sg:phone":"+32 58 31 33 80",
    "sg:postcode":"8630",
    "sg:province":"West-Vlaanderen",
    "sg:tags":[
        "caf\u00e9s"
    ],
    "wof:name":"Caf\u00c9 Montreal",
    "wof:placetype":"venue"
},
  "geometry": {"coordinates":[2.6619620323,51.0739402771],"type":"Point"}
}