{
  "type": "Feature",
  "properties": {
    "iso:country":"BE",
    "sg:address":"Rue Faweux 9",
    "sg:city":"Olne",
    "sg:classifiers":[
        {
            "category":"Parking",
            "subcategory":"Garage",
            "type":"Transportation"
        }
    ],
    "sg:phone":"+32 4 358 73 87",
    "sg:postcode":"4877",
    "sg:province":"Li\u00e8ge",
    "sg:tags":[
        "truck",
        "-",
        "dump",
        "transport"
    ],
    "wof:name":"Buchet P",
    "wof:placetype":"venue"
},
  "geometry": {"coordinates":[5.7183270454,50.5984344482],"type":"Point"}
}