{
  "type": "Feature",
  "properties": {
    "iso:country":"BE",
    "sg:address":"Rue De Neumoulin 22",
    "sg:city":"Bouillon (ucimont)",
    "sg:classifiers":[
        {
            "category":"Building & Trades",
            "subcategory":"Landscaping Services",
            "type":"Services"
        }
    ],
    "sg:phone":"+32 61 41 34 96",
    "sg:postcode":"6833",
    "sg:province":"Luxembourg",
    "sg:tags":[
        "forestry"
    ],
    "wof:name":"De Moffarts Baron Em",
    "wof:placetype":"venue"
},
  "geometry": {"coordinates":[5.0485811234,49.8210945129],"type":"Point"}
}