{
  "type": "Feature",
  "properties": {
    "iso:country":"BE",
    "sg:address":"Vlasmarkt 23",
    "sg:city":"Dendermonde",
    "sg:orig_category":"Enseignement secondaire g\u00e9n\u00e9ral",
    "sg:phone":"+32 52 22 29 59",
    "sg:postcode":"9200",
    "sg:province":"Oost-Vlaanderen",
    "wof:name":"Abdijschool",
    "wof:placetype":"venue"
},
  "geometry": {"coordinates":[4.0992450714,51.0295562744],"type":"Point"}
}