{
  "type": "Feature",
  "properties": {
    "addr:full":"Leeuwerikstraat 4 Mol Antwerpen 2400",
    "addr:housenumber":"4",
    "addr:postcode":"2400",
    "addr:street":"Leeuwerikstraat",
    "iso:country":"BE",
    "sg:address":"Leeuwerikstraat 4",
    "sg:city":"Mol",
    "sg:classifiers":[
        {
            "category":"Real Estate",
            "subcategory":"Architect",
            "type":"Services"
        }
    ],
    "sg:phone":"+32 14 31 89 02",
    "sg:postcode":"2400",
    "sg:province":"Antwerpen",
    "wof:name":"Lievens I Mevr",
    "wof:placetype":"venue"
},
  "geometry": {"coordinates":[5.0815258026,51.1862411499],"type":"Point"}
}