{
  "type": "Feature",
  "properties": {
    "addr:full":"Rue Du March\u00c9 Au Charbon 30 Brussel/bruxelles Bruxelles-Capitale 1000",
    "addr:housenumber":"30",
    "addr:postcode":"1000",
    "addr:street":"Rue Du Marche\u0301 Au Charbon;/",
    "iso:country":"BE",
    "sg:address":"Rue Du March\u00c9 Au Charbon 30",
    "sg:city":"Brussel/bruxelles",
    "sg:classifiers":[
        {
            "category":"Government",
            "subcategory":"Police Station",
            "type":"Public Place"
        }
    ],
    "sg:phone":"+32 2 517 96 11",
    "sg:postcode":"1000",
    "sg:province":"Bruxelles-Capitale",
    "sg:tags":[
        "gendarmerie"
    ],
    "wof:name":"Federale Politie/police F\u00c9d\u00c9rale",
    "wof:placetype":"venue"
},
  "geometry": {"coordinates":[4.3501739502,50.8463172913],"type":"Point"}
}