{
  "type": "Feature",
  "properties": {
    "iso:country":"BE",
    "sg:address":"Abdijstraat 249",
    "sg:city":"Antwerpen",
    "sg:orig_category":"Antiek",
    "sg:phone":"+32 3 257 09 29",
    "sg:postcode":"2020",
    "sg:province":"Antwerpen",
    "wof:name":"Art Deco Dream",
    "wof:placetype":"venue"
},
  "geometry": {"coordinates":[4.3873047829,51.1864547729],"type":"Point"}
}