{
  "type": "Feature",
  "properties": {
    "addr:full":"Place Froissart 18 Chimay Hainaut 6460",
    "addr:housenumber":"18",
    "addr:postcode":"6460",
    "addr:street":"Place Froissart",
    "iso:country":"BE",
    "sg:address":"Place Froissart 18",
    "sg:city":"Chimay",
    "sg:orig_category":"Articles m\u00e9dicaux and orthop\u00e9diques",
    "sg:phone":"+32 60 21 29 68",
    "sg:postcode":"6460",
    "sg:province":"Hainaut",
    "wof:name":"Centre Auditif Philips",
    "wof:placetype":"venue"
},
  "geometry": {"coordinates":[4.3131980896,50.0471572876],"type":"Point"}
}