{
  "type": "Feature",
  "properties": {
    "iso:country":"BE",
    "sg:address":"Rue De La Gagire 4",
    "sg:city":"Waimes",
    "sg:orig_category":"Installation de menuiserie en bois and plastique",
    "sg:phone":"+32 80 67 81 06",
    "sg:postcode":"4950",
    "sg:province":"Li\u00e8ge",
    "wof:name":"Alain Masson",
    "wof:placetype":"venue"
},
  "geometry": {"coordinates":[6.0873799324,50.3894767761],"type":"Point"}
}