{
  "type": "Feature",
  "properties": {
    "iso:country":"BE",
    "sg:address":"Avenue Brugmann 347",
    "sg:city":"Ukkel/uccle",
    "sg:orig_category":"Salles de spectacles",
    "sg:phone":"+32 2 424 14 77",
    "sg:postcode":"1180",
    "sg:province":"Bruxelles-Capitale",
    "wof:name":"Patchth\u00c9\u00c2tre",
    "wof:placetype":"venue"
},
  "geometry": {"coordinates":[4.3452301025,50.8097419739],"type":"Point"}
}