{
  "type": "Feature",
  "properties": {
    "iso:country":"BE",
    "sg:address":"Donksesteenweg 212",
    "sg:city":"Brasschaat",
    "sg:orig_category":"Boekhouders",
    "sg:phone":"+32 3 646 51 34",
    "sg:postcode":"2930",
    "sg:province":"Antwerpen",
    "wof:name":"Marc De Groof",
    "wof:placetype":"venue"
},
  "geometry": {"coordinates":[4.4540362358,51.2810211182],"type":"Point"}
}