{
  "type": "Feature",
  "properties": {
    "iso:country":"BE",
    "sg:address":"Rijksweg 119",
    "sg:city":"Dilsen-stokkem (dilsen)",
    "sg:classifiers":[
        {
            "category":"Retail",
            "subcategory":"Car Wash",
            "type":"Services"
        }
    ],
    "sg:phone":"+32 89 75 59 10",
    "sg:postcode":"3650",
    "sg:province":"Limburg",
    "sg:tags":[
        "automobile",
        "washing",
        "-",
        "truck"
    ],
    "wof:name":"Budna Tony",
    "wof:placetype":"venue"
},
  "geometry": {"coordinates":[5.7266697884,51.0228614807],"type":"Point"}
}