{
  "type": "Feature",
  "properties": {
    "iso:country":"BE",
    "sg:address":"Gilseinde 109",
    "sg:city":"Ravels",
    "sg:classifiers":[
        {
            "category":"Personal",
            "subcategory":"Beauty Salon",
            "type":"Services"
        }
    ],
    "sg:phone":"+32 14 65 85 64",
    "sg:postcode":"2380",
    "sg:province":"Antwerpen",
    "sg:tags":[
        "lady",
        "-",
        "hairdressing"
    ],
    "wof:name":"Marja",
    "wof:placetype":"venue"
},
  "geometry": {"coordinates":[5.0094151497,51.3722686768],"type":"Point"}
}