{
  "type": "Feature",
  "properties": {
    "addr:full":"Kerkstraat 8 Heist-op-den-berg (itegem) Antwerpen 2222",
    "addr:housenumber":"8",
    "addr:postcode":"2222",
    "addr:street":"Kerkstraat",
    "iso:country":"BE",
    "sg:address":"Kerkstraat 8",
    "sg:city":"Heist-op-den-berg (itegem)",
    "sg:classifiers":[
        {
            "category":"Bars & Pubs",
            "type":"Food & Drink"
        }
    ],
    "sg:phone":"+32 15 24 67 91",
    "sg:postcode":"2222",
    "sg:province":"Antwerpen",
    "wof:name":"Lux",
    "wof:placetype":"venue"
},
  "geometry": {"coordinates":[4.7295541763,51.0763931274],"type":"Point"}
}