{
  "type": "Feature",
  "properties": {
    "iso:country":"BE",
    "sg:address":"Rue Notre-dame 49",
    "sg:city":"Namur",
    "sg:classifiers":[
        {
            "category":"Personal",
            "subcategory":"Shoe Repair & Shine",
            "type":"Services"
        }
    ],
    "sg:phone":"+32 81 22 19 44",
    "sg:postcode":"5000",
    "sg:province":"Namur",
    "sg:tags":[
        "shoemaker"
    ],
    "wof:name":"Parmentier",
    "wof:placetype":"venue"
},
  "geometry": {"coordinates":[4.8667488098,50.4600715637],"type":"Point"}
}