{
  "type": "Feature",
  "properties": {
    "addr:full":"Sint-fledericusstraat 59c Sint-lievens-houtem (vlierzele) Oost-Vlaanderen 9520",
    "addr:housenumber":"59c",
    "addr:postcode":"9520",
    "addr:street":"Sint-Fledericusstraat",
    "iso:country":"BE",
    "sg:address":"Sint-fledericusstraat 59c",
    "sg:city":"Sint-lievens-houtem (vlierzele)",
    "sg:classifiers":[
        {
            "category":"Home & Garden",
            "subcategory":"Carpets & Floor Coverings",
            "type":"Retail Goods"
        }
    ],
    "sg:phone":"+32 53 62 98 59",
    "sg:postcode":"9520",
    "sg:province":"Oost-Vlaanderen",
    "sg:tags":[
        "layer",
        "mosaicists"
    ],
    "wof:name":"Bockstaele P",
    "wof:placetype":"venue"
},
  "geometry": {"coordinates":[3.9013700485,50.944278717],"type":"Point"}
}