{
  "type": "Feature",
  "properties": {
    "iso:country":"BE",
    "sg:address":"Tongersesteenweg 70a",
    "sg:city":"Borgloon",
    "sg:classifiers":[
        {
            "category":"Home & Garden",
            "subcategory":"Building Materials",
            "type":"Retail Goods"
        }
    ],
    "sg:phone":"+32 12 74 51 51",
    "sg:postcode":"3840",
    "sg:province":"Limburg",
    "sg:tags":[
        "wall",
        "cupboard"
    ],
    "wof:name":"Haling M",
    "wof:placetype":"venue"
},
  "geometry": {"coordinates":[5.3543901443,50.8003616333],"type":"Point"}
}