{
  "type": "Feature",
  "properties": {
    "addr:full":"Avenue Fructidor 34 Waterloo Brabant Wallon 1410",
    "addr:housenumber":"34",
    "addr:postcode":"1410",
    "addr:street":"Avenue Fructidor",
    "iso:country":"BE",
    "sg:address":"Avenue Fructidor 34",
    "sg:city":"Waterloo",
    "sg:classifiers":[
        {
            "category":"Professional",
            "subcategory":"Accounting & Tax Preparation",
            "type":"Services"
        }
    ],
    "sg:phone":"+32 2 351 38 06",
    "sg:postcode":"1410",
    "sg:province":"Brabant Wallon",
    "sg:tags":[
        "bookkeeper"
    ],
    "wof:name":"Van Gameren M-c",
    "wof:placetype":"venue"
},
  "geometry": {"coordinates":[4.3877511024,50.7092666626],"type":"Point"}
}