{
  "type": "Feature",
  "properties": {
    "iso:country":"BE",
    "sg:address":"Kortrijkstraat 126",
    "sg:city":"Tielt",
    "sg:classifiers":[
        {
            "category":"Shopping",
            "subcategory":"Crafts & Fabrics",
            "type":"Retail Goods"
        }
    ],
    "sg:phone":"+32 51 40 44 31",
    "sg:postcode":"8700",
    "sg:province":"West-Vlaanderen",
    "sg:tags":[
        "silk",
        "-"
    ],
    "wof:name":"Sabine Bvba",
    "wof:placetype":"venue"
},
  "geometry": {"coordinates":[3.3260838985,50.9953117371],"type":"Point"}
}