{
  "type": "Feature",
  "properties": {
    "iso:country":"BE",
    "sg:address":"Kerkstraat 105",
    "sg:city":"Buggenhout",
    "sg:orig_category":"Pharmaciens",
    "sg:phone":"+32 52 33 12 16",
    "sg:postcode":"9255",
    "sg:province":"Oost-Vlaanderen",
    "wof:name":"Apoth. De Vos En Van Peer",
    "wof:placetype":"venue"
},
  "geometry": {"coordinates":[4.2020959854,51.0144920349],"type":"Point"}
}