{
  "type": "Feature",
  "properties": {
    "iso:country":"BE",
    "sg:address":"Hazepootstraat 1",
    "sg:city":"Meise",
    "sg:classifiers":[
        {
            "category":"Building & Trades",
            "subcategory":"Construction",
            "type":"Services"
        }
    ],
    "sg:phone":"+32 2 466 46 76",
    "sg:postcode":"1860",
    "sg:province":"Vlaams-Brabant",
    "sg:tags":[
        "paper",
        "hanger"
    ],
    "wof:name":"De Loose Nv",
    "wof:placetype":"venue"
},
  "geometry": {"coordinates":[4.3407812119,50.9464645386],"type":"Point"}
}