{
  "type": "Feature",
  "properties": {
    "iso:country":"BE",
    "sg:address":"Knaptandstraat 60",
    "sg:city":"Sint-niklaas",
    "sg:orig_category":"Speciaalzaken",
    "sg:phone":"+32 3 776 12 88",
    "sg:postcode":"9100",
    "sg:province":"Oost-Vlaanderen",
    "wof:name":"Roland Van Hecke",
    "wof:placetype":"venue"
},
  "geometry": {"coordinates":[4.144051075,51.159324646],"type":"Point"}
}