{
  "type": "Feature",
  "properties": {
    "addr:full":"Kerkstraat 55bf Puurs Antwerpen 2870",
    "addr:housenumber":"55bf",
    "addr:postcode":"2870",
    "addr:street":"Kerkstraat",
    "iso:country":"BE",
    "sg:address":"Kerkstraat 55bf",
    "sg:city":"Puurs",
    "sg:orig_category":"Artsen and specialisten",
    "sg:phone":"+32 3 886 20 86",
    "sg:postcode":"2870",
    "sg:province":"Antwerpen",
    "wof:name":"Nancy Macharis",
    "wof:placetype":"venue"
},
  "geometry": {"coordinates":[4.3246188164,51.0836448669],"type":"Point"}
}