{
  "type": "Feature",
  "properties": {
    "addr:full":"J. E. Claeslaan 10 Nijlen Antwerpen 2560",
    "addr:housenumber":"10",
    "addr:postcode":"2560",
    "addr:street":"J. E. Claeslaan",
    "iso:country":"BE",
    "sg:address":"J. E. Claeslaan 10",
    "sg:city":"Nijlen",
    "sg:orig_category":"Banken and kredietinstellingen",
    "sg:phone":"+32 3 481 93 41",
    "sg:postcode":"2560",
    "sg:province":"Antwerpen",
    "wof:name":"Centea",
    "wof:placetype":"venue"
},
  "geometry": {"coordinates":[4.6667561531,51.1592559814],"type":"Point"}
}