{
  "type": "Feature",
  "properties": {
    "addr:full":"Rue Davignon 16 Herve Li\u00e8ge 4650",
    "addr:housenumber":"16",
    "addr:postcode":"4650",
    "addr:street":"Rue Davignon",
    "iso:country":"BE",
    "sg:address":"Rue Davignon 16",
    "sg:city":"Herve",
    "sg:classifiers":[
        {
            "category":"Health Services",
            "subcategory":"Health Practitioner",
            "type":"Services"
        }
    ],
    "sg:phone":"+32 87 67 54 19",
    "sg:postcode":"4650",
    "sg:province":"Li\u00e8ge",
    "sg:tags":[
        "physiotherapist"
    ],
    "wof:name":"Ruwet Yves",
    "wof:placetype":"venue"
},
  "geometry": {"coordinates":[5.7925891876,50.6390953064],"type":"Point"}
}