{
  "type": "Feature",
  "properties": {
    "addr:full":"Alkenlaan 10 Blankenberge West-Vlaanderen 8370",
    "addr:housenumber":"10",
    "addr:postcode":"8370",
    "addr:street":"Alkenlaan",
    "iso:country":"BE",
    "sg:address":"Alkenlaan 10",
    "sg:city":"Blankenberge",
    "sg:orig_category":"Artiesten and kunstenaars",
    "sg:phone":"+32 50 41 44 94",
    "sg:postcode":"8370",
    "sg:province":"West-Vlaanderen",
    "wof:name":"D. De Smedt",
    "wof:placetype":"venue"
},
  "geometry": {"coordinates":[3.1487131119,51.3086204529],"type":"Point"}
}