{
  "type": "Feature",
  "properties": {
    "iso:country":"BE",
    "sg:address":"Koning Albertstraat 25",
    "sg:city":"Lint",
    "sg:orig_category":"Pain, p\u00e2tisseries and confiseries",
    "sg:phone":"+32 3 455 29 89",
    "sg:postcode":"2547",
    "sg:province":"Antwerpen",
    "wof:name":"Bakkerij Elly",
    "wof:placetype":"venue"
},
  "geometry": {"coordinates":[4.4952311516,51.12758255],"type":"Point"}
}