{
  "type": "Feature",
  "properties": {
    "addr:full":"Avenue Des Mimosas 18 Sint-pieters-woluwe/woluwe-saint-pierre Bruxelles-Capitale 1150",
    "addr:housenumber":"18",
    "addr:postcode":"1150",
    "addr:street":"Avenue Des Mimosas;/",
    "iso:country":"BE",
    "sg:address":"Avenue Des Mimosas 18",
    "sg:city":"Sint-pieters-woluwe/woluwe-saint-pierre",
    "sg:orig_category":"Architectes",
    "sg:phone":"+32 2 734 47 76",
    "sg:postcode":"1150",
    "sg:province":"Bruxelles-Capitale",
    "wof:name":"Michel Benoit",
    "wof:placetype":"venue"
},
  "geometry": {"coordinates":[4.4077539444,50.8276824951],"type":"Point"}
}