{
  "type": "Feature",
  "properties": {
    "iso:country":"BE",
    "sg:address":"Rue Pierre Fontaine 56",
    "sg:city":"Lessines (papignies)",
    "sg:classifiers":[
        {
            "category":"Building & Trades",
            "subcategory":"Landscaping Services",
            "type":"Services"
        }
    ],
    "sg:phone":"+32 68 33 51 81",
    "sg:postcode":"7861",
    "sg:province":"Hainaut",
    "sg:tags":[
        "gardening",
        "garden",
        "maintenance"
    ],
    "wof:name":"Gravis P",
    "wof:placetype":"venue"
},
  "geometry": {"coordinates":[3.8209049702,50.6903686523],"type":"Point"}
}