{
  "type": "Feature",
  "properties": {
    "iso:country":"BE",
    "sg:address":"Tiendenschuurstraat 19",
    "sg:city":"Mechelen",
    "sg:orig_category":"Eleveurs de bovins",
    "sg:phone":"+32 15 41 39 32",
    "sg:postcode":"2811",
    "sg:province":"Antwerpen",
    "wof:name":"Leo Verbruggen",
    "wof:placetype":"venue"
},
  "geometry": {"coordinates":[4.4025831223,51.0221824646],"type":"Point"}
}