{
  "type": "Feature",
  "properties": {
    "iso:country":"BE",
    "sg:address":"Wijngaardstraat 20",
    "sg:city":"Opwijk",
    "sg:orig_category":"Produits surgel\u00e9s Gr",
    "sg:phone":"+32 52 35 56 05",
    "sg:postcode":"1745",
    "sg:province":"Vlaams-Brabant",
    "wof:name":"Geert Vermeir",
    "wof:placetype":"venue"
},
  "geometry": {"coordinates":[4.166615963,50.9702110291],"type":"Point"}
}