{
  "type": "Feature",
  "properties": {
    "addr:full":"Sint-maartensveldstraat 24 Ardooie West-Vlaanderen 8850",
    "addr:housenumber":"24",
    "addr:postcode":"8850",
    "addr:street":"Sint-Maartensveldstraat",
    "iso:country":"BE",
    "sg:address":"Sint-maartensveldstraat 24",
    "sg:city":"Ardooie",
    "sg:orig_category":"Bagage and lederwaren Bloemen and planten",
    "sg:phone":"+32 51 74 70 39",
    "sg:postcode":"8850",
    "sg:province":"West-Vlaanderen",
    "wof:name":"Carine Corneillie",
    "wof:placetype":"venue"
},
  "geometry": {"coordinates":[3.2121601105,50.9919586182],"type":"Point"}
}