{
  "type": "Feature",
  "properties": {
    "iso:country":"BE",
    "sg:address":"Rue Antoine Dansaert 10",
    "sg:city":"Bruxelles",
    "sg:classifiers":[
        {
            "category":"Shopping",
            "subcategory":"Shoes",
            "type":"Retail Goods"
        }
    ],
    "sg:phone":"+32 2 511 46 03",
    "sg:postcode":"1000",
    "sg:province":"Bruxelles-Capitale",
    "sg:tags":[
        "slipper",
        "-"
    ],
    "wof:name":"Virgin",
    "wof:placetype":"venue"
},
  "geometry": {"coordinates":[4.3475031853,50.8490638733],"type":"Point"}
}