{
  "type": "Feature",
  "properties": {
    "addr:full":"Papbosstraat 4 Brecht Antwerpen 2960",
    "addr:housenumber":"4",
    "addr:postcode":"2960",
    "addr:street":"Papbosstraat",
    "iso:country":"BE",
    "sg:address":"Papbosstraat 4",
    "sg:city":"Brecht",
    "sg:orig_category":"Eleveurs de bovins",
    "sg:phone":"+32 3 313 94 09",
    "sg:postcode":"2960",
    "sg:province":"Antwerpen",
    "wof:name":"Hendrik Van Aerde",
    "wof:placetype":"venue"
},
  "geometry": {"coordinates":[4.6346268654,51.3635826111],"type":"Point"}
}