{
  "type": "Feature",
  "properties": {
    "addr:full":"Geraardsbergsestraat 248 Aalst Oost-Vlaanderen 9300",
    "addr:housenumber":"248",
    "addr:postcode":"9300",
    "addr:street":"Geraardsbergsestraat",
    "iso:country":"BE",
    "sg:address":"Geraardsbergsestraat 248",
    "sg:city":"Aalst",
    "sg:classifiers":[
        {
            "category":"Shopping",
            "subcategory":"Clothing, Apparel, & Fashions",
            "type":"Retail Goods"
        }
    ],
    "sg:phone":"+32 53 21 59 68",
    "sg:postcode":"9300",
    "sg:province":"Oost-Vlaanderen",
    "sg:tags":[
        "v\u00eatements",
        "pour",
        "dame"
    ],
    "wof:name":"Top Shop",
    "wof:placetype":"venue"
},
  "geometry": {"coordinates":[4.0348701477,50.9283485413],"type":"Point"}
}