{
  "type": "Feature",
  "properties": {
    "iso:country":"BE",
    "sg:address":"Clos Des Princes 59",
    "sg:city":"Le Roeulx",
    "sg:classifiers":[
        {
            "category":"Building & Trades",
            "subcategory":"Plumbing",
            "type":"Services"
        }
    ],
    "sg:phone":"+32 64 66 57 74",
    "sg:postcode":"7070",
    "sg:province":"Hainaut",
    "sg:tags":[
        "pipe",
        "pushing"
    ],
    "wof:name":"Francois L",
    "wof:placetype":"venue"
},
  "geometry": {"coordinates":[4.1048731804,50.5146903992],"type":"Point"}
}