{
  "type": "Feature",
  "properties": {
    "iso:country":"BE",
    "sg:address":"Rue Albert I 14",
    "sg:city":"Amay",
    "sg:classifiers":[
        {
            "category":"Health Services",
            "subcategory":"Health Practitioner",
            "type":"Services"
        }
    ],
    "sg:phone":"+32 85 31 27 80",
    "sg:postcode":"4540",
    "sg:province":"Li\u00e8ge",
    "sg:tags":[
        "physiotherapist"
    ],
    "wof:name":"Lacroix Jean-luc",
    "wof:placetype":"venue"
},
  "geometry": {"coordinates":[5.3180990219,50.5478668213],"type":"Point"}
}