{
  "type": "Feature",
  "properties": {
    "addr:full":"Rue Bodson 15 Courcelles Hainaut 6180",
    "addr:housenumber":"15",
    "addr:postcode":"6180",
    "addr:street":"Rue Bodson",
    "iso:country":"BE",
    "sg:address":"Rue Bodson 15",
    "sg:city":"Courcelles",
    "sg:orig_category":"Woningbouw",
    "sg:phone":"+32 71 45 21 67",
    "sg:postcode":"6180",
    "sg:province":"Hainaut",
    "wof:name":"Vaclaw Walentynowicz",
    "wof:placetype":"venue"
},
  "geometry": {"coordinates":[4.3866591454,50.467754364],"type":"Point"}
}