{
  "type": "Feature",
  "properties": {
    "addr:full":"Blekerijstraat 128 Izegem West-Vlaanderen 8870",
    "addr:housenumber":"128",
    "addr:postcode":"8870",
    "addr:street":"Blekerijstraat",
    "iso:country":"BE",
    "sg:address":"Blekerijstraat 128",
    "sg:city":"Izegem",
    "sg:orig_category":"Eleveurs and marchands de porcs",
    "sg:phone":"+32 51 30 56 24",
    "sg:postcode":"8870",
    "sg:province":"West-Vlaanderen",
    "wof:name":"Gerard Descheemaeker",
    "wof:placetype":"venue"
},
  "geometry": {"coordinates":[3.2002639771,50.9015159607],"type":"Point"}
}