{
  "type": "Feature",
  "properties": {
    "addr:full":"Sint-pieterskerklaan 53 Brugge West-Vlaanderen 8000",
    "addr:housenumber":"53",
    "addr:postcode":"8000",
    "addr:street":"Sint-Pieterskerklaan",
    "iso:country":"BE",
    "sg:address":"Sint-pieterskerklaan 53",
    "sg:city":"Brugge",
    "sg:orig_category":"Huishoudapparaten, televisies and radio's",
    "sg:phone":"+32 50 31 44 16",
    "sg:postcode":"8000",
    "sg:province":"West-Vlaanderen",
    "wof:name":"Dirk Viaene",
    "wof:placetype":"venue"
},
  "geometry": {"coordinates":[3.2182660103,51.2213096619],"type":"Point"}
}