{
  "type": "Feature",
  "properties": {
    "iso:country":"BE",
    "sg:address":"Chauss\u00e9e De Charleroi 4",
    "sg:city":"Nivelles",
    "sg:classifiers":[
        {
            "category":"Professional",
            "subcategory":"Printing & Photocopies",
            "type":"Services"
        }
    ],
    "sg:phone":"+32 67 21 85 49",
    "sg:postcode":"1400",
    "sg:province":"Brabant Wallon",
    "sg:tags":[
        "silkscreen",
        "-"
    ],
    "wof:name":"Seridel",
    "wof:placetype":"venue"
},
  "geometry": {"coordinates":[4.3316469193,50.5884246826],"type":"Point"}
}