{
  "type": "Feature",
  "properties": {
    "iso:country":"BE",
    "sg:address":"Venelle De Terlongval 9",
    "sg:city":"Wavre",
    "sg:classifiers":[
        {
            "category":"Real Estate",
            "subcategory":"Architect",
            "type":"Services"
        }
    ],
    "sg:phone":"+32 10 22 83 18",
    "sg:postcode":"1300",
    "sg:province":"Brabant Wallon",
    "wof:name":"Vanderhofstadt",
    "wof:placetype":"venue"
},
  "geometry": {"coordinates":[4.6251177788,50.702255249],"type":"Point"}
}