{
  "type": "Feature",
  "properties": {
    "iso:country":"BE",
    "sg:address":"Rue Haisse 7",
    "sg:city":"Blegny",
    "sg:classifiers":[
        {
            "category":"Cafe",
            "type":"Food & Drink"
        }
    ],
    "sg:phone":"+32 4 387 42 13",
    "sg:postcode":"4670",
    "sg:province":"Li\u00e8ge",
    "sg:tags":[
        "caf\u00e9s"
    ],
    "wof:name":"Didier Demonceau",
    "wof:placetype":"venue"
},
  "geometry": {"coordinates":[5.724919796,50.6725769043],"type":"Point"}
}