{
  "type": "Feature",
  "properties": {
    "addr:full":"Industrialaan 35 Dilbeek Vlaams-Brabant 1702",
    "addr:housenumber":"35",
    "addr:postcode":"1702",
    "addr:street":"Industrialaan",
    "iso:country":"BE",
    "sg:address":"Industrialaan 35",
    "sg:city":"Dilbeek",
    "sg:orig_category":"Appareils de pulv\u00e9risation Fab",
    "sg:phone":"+32 2 467 72 11",
    "sg:postcode":"1702",
    "sg:province":"Vlaams-Brabant",
    "wof:name":"Ansul",
    "wof:placetype":"venue"
},
  "geometry": {"coordinates":[4.2683038712,50.8796272278],"type":"Point"}
}