{
  "type": "Feature",
  "properties": {
    "iso:country":"BE",
    "sg:address":"Kroonstraat 22",
    "sg:city":"Westerlo",
    "sg:orig_category":"G\u00e9om\u00e8tres",
    "sg:phone":"+32 14 21 59 13",
    "sg:postcode":"2260",
    "sg:province":"Antwerpen",
    "wof:name":"Alfons Vervoort",
    "wof:placetype":"venue"
},
  "geometry": {"coordinates":[4.8974070549,51.1406936646],"type":"Point"}
}