{
  "type": "Feature",
  "properties": {
    "addr:full":"Rue De Payot 5 Lasne Brabant Wallon 1380",
    "addr:housenumber":"5",
    "addr:postcode":"1380",
    "addr:street":"Rue De Payot",
    "iso:country":"BE",
    "sg:address":"Rue De Payot 5",
    "sg:city":"Lasne",
    "sg:orig_category":"Rundveehouders",
    "sg:phone":"+32 2 633 15 56",
    "sg:postcode":"1380",
    "sg:province":"Brabant Wallon",
    "wof:name":"Rene Delay",
    "wof:placetype":"venue"
},
  "geometry": {"coordinates":[4.4616827965,50.669593811],"type":"Point"}
}