{
  "type": "Feature",
  "properties": {
    "iso:country":"BE",
    "sg:address":"Unter Den Linden 5",
    "sg:city":"B\u00dctgenbach/b\u00dctgenbach",
    "sg:orig_category":"Assurances. Bureaux de poste",
    "sg:phone":"+32 80 44 48 03",
    "sg:postcode":"4750",
    "sg:province":"Li\u00e8ge",
    "wof:name":"La Poste",
    "wof:placetype":"venue"
},
  "geometry": {"coordinates":[6.2206501961,50.457408905],"type":"Point"}
}