{
  "type": "Feature",
  "properties": {
    "addr:full":"Kampendaal 75 Beersel Vlaams-Brabant 1653",
    "addr:housenumber":"75",
    "addr:postcode":"1653",
    "addr:street":"Kampendaal",
    "iso:country":"BE",
    "sg:address":"Kampendaal 75",
    "sg:city":"Beersel",
    "sg:orig_category":"M\u00e9decins and sp\u00e9cialistes",
    "sg:phone":"+32 2 380 17 79",
    "sg:postcode":"1653",
    "sg:province":"Vlaams-Brabant",
    "wof:name":"Linda De Raeve",
    "wof:placetype":"venue"
},
  "geometry": {"coordinates":[4.2991251945,50.7301254272],"type":"Point"}
}