{
  "type": "Feature",
  "properties": {
    "iso:country":"BE",
    "sg:address":"Pleispark 21",
    "sg:city":"Gent (sint-denijs-westrem - Afsnee)",
    "sg:classifiers":[
        {
            "category":"Health Services",
            "subcategory":"Doctor",
            "type":"Services"
        }
    ],
    "sg:phone":"+32 9 222 32 08",
    "sg:postcode":"9051",
    "sg:province":"Oost-Vlaanderen",
    "sg:tags":[
        "medicinephysicians",
        "surgeon"
    ],
    "wof:name":"Anaf C",
    "wof:placetype":"venue"
},
  "geometry": {"coordinates":[3.6933400631,51.0198669434],"type":"Point"}
}