{
  "type": "Feature",
  "properties": {
    "iso:country":"BE",
    "sg:address":"Chauss\u00e9e De Belle Vue 54",
    "sg:city":"Bernissart (pommeroeul)",
    "sg:classifiers":[
        {
            "category":"Retail",
            "subcategory":"Funeral Services",
            "type":"Services"
        }
    ],
    "sg:phone":"+32 65 62 03 91",
    "sg:postcode":"7322",
    "sg:province":"Hainaut",
    "sg:tags":[
        "director"
    ],
    "wof:name":"Miroir",
    "wof:placetype":"venue"
},
  "geometry": {"coordinates":[3.7286689281,50.4715576172],"type":"Point"}
}