{
  "type": "Feature",
  "properties": {
    "addr:full":"Diksmuidsestraat 38 Ieper West-Vlaanderen 8900",
    "addr:housenumber":"38",
    "addr:postcode":"8900",
    "addr:street":"Diksmuidsestraat",
    "iso:country":"BE",
    "sg:address":"Diksmuidsestraat 38",
    "sg:city":"Ieper",
    "sg:orig_category":"V\u00eatements",
    "sg:phone":"+32 57 21 95 15",
    "sg:postcode":"8900",
    "sg:province":"West-Vlaanderen",
    "wof:name":"Pantariba",
    "wof:placetype":"venue"
},
  "geometry": {"coordinates":[2.8866610527,50.8530654907],"type":"Point"}
}