{
  "type": "Feature",
  "properties": {
    "addr:full":"Machelendorp 4 Zulte (machelen) Oost-Vlaanderen 9870",
    "addr:housenumber":"4",
    "addr:postcode":"9870",
    "addr:street":"Machelendorp",
    "iso:country":"BE",
    "sg:address":"Machelendorp 4",
    "sg:city":"Zulte (machelen)",
    "sg:classifiers":[
        {
            "category":"Bars & Pubs",
            "type":"Food & Drink"
        }
    ],
    "sg:phone":"+32 9 386 27 33",
    "sg:postcode":"9870",
    "sg:province":"Oost-Vlaanderen",
    "wof:name":"Oud Gemeentehuis",
    "wof:placetype":"venue"
},
  "geometry": {"coordinates":[3.4859640598,50.9598846436],"type":"Point"}
}