{
  "type": "Feature",
  "properties": {
    "addr:full":"El Cw\u00e8ne 30 Durbuy (heyd) Luxembourg 6941",
    "addr:housenumber":"30",
    "addr:postcode":"6941",
    "iso:country":"BE",
    "sg:address":"El Cw\u00e8ne 30",
    "sg:city":"Durbuy (heyd)",
    "sg:classifiers":[
        {
            "category":"Building & Trades",
            "subcategory":"Equipment Rental",
            "type":"Services"
        }
    ],
    "sg:phone":"+32 475 69 73 58",
    "sg:postcode":"6941",
    "sg:province":"Luxembourg",
    "sg:tags":[
        "crane",
        "-"
    ],
    "wof:name":"Simon D",
    "wof:placetype":"venue"
},
  "geometry": {"coordinates":[5.5527539253,50.3456268311],"type":"Point"}
}