{
  "type": "Feature",
  "properties": {
    "iso:country":"BE",
    "sg:address":"Rue Des Martyrs 17",
    "sg:city":"Arlon",
    "sg:classifiers":[
        {
            "category":"Manufacturing",
            "subcategory":"Textiles",
            "type":"Manufacturing & Wholesale Goods"
        }
    ],
    "sg:phone":"+32 63 22 82 58",
    "sg:postcode":"6700",
    "sg:province":"Luxembourg",
    "sg:tags":[
        "fab",
        "diverse",
        "textielproducten"
    ],
    "wof:name":"Marquet Sport",
    "wof:placetype":"venue"
},
  "geometry": {"coordinates":[5.8106269836,49.6839332581],"type":"Point"}
}