{
  "type": "Feature",
  "properties": {
    "addr:full":"Rue D'amiens 7 Doornik Hainaut 7500",
    "addr:housenumber":"7",
    "addr:postcode":"7500",
    "addr:street":"Rue D'Amiens",
    "iso:country":"BE",
    "sg:address":"Rue D'amiens 7",
    "sg:city":"Doornik",
    "sg:orig_category":"Radioproductie and uitzendingen",
    "sg:phone":"+32 69 64 13 97",
    "sg:postcode":"7500",
    "sg:province":"Hainaut",
    "wof:name":"Nrj",
    "wof:placetype":"venue"
},
  "geometry": {"coordinates":[3.3785669804,50.6160583496],"type":"Point"}
}