{
  "type": "Feature",
  "properties": {
    "addr:full":"Place Peter Benoit 1 Bruxelles Bruxelles-Capitale 1120",
    "addr:housenumber":"1",
    "addr:postcode":"1120",
    "addr:street":"Place Peter Benoit",
    "iso:country":"BE",
    "sg:address":"Place Peter Benoit 1",
    "sg:city":"Bruxelles",
    "sg:classifiers":[
        {
            "category":"Bars & Pubs",
            "type":"Food & Drink"
        }
    ],
    "sg:phone":"+32 2 262 27 49",
    "sg:postcode":"1120",
    "sg:province":"Bruxelles-Capitale",
    "sg:tags":[
        "tavern"
    ],
    "wof:name":"Achtsten Hemel (in Den)",
    "wof:placetype":"venue"
},
  "geometry": {"coordinates":[4.3879709244,50.8952941895],"type":"Point"}
}