{
  "type": "Feature",
  "properties": {
    "iso:country":"BE",
    "sg:address":"Rue Aux Fleurs 1a",
    "sg:city":"Lasne (ohain)",
    "sg:orig_category":"Autombile concessionaires",
    "sg:phone":"+32 2 653 21 55",
    "sg:postcode":"1380",
    "sg:province":"Brabant Wallon",
    "wof:name":"De L'abbaye Sprl",
    "wof:placetype":"venue"
},
  "geometry": {"coordinates":[4.483235836,50.6850166321],"type":"Point"}
}