{
  "type": "Feature",
  "properties": {
    "iso:country":"BE",
    "sg:address":"Oostveld Kouter 74",
    "sg:city":"Lovendegem",
    "sg:classifiers":[
        {
            "category":"Real Estate",
            "subcategory":"Surveying",
            "type":"Services"
        }
    ],
    "sg:phone":"+32 9 372 76 19",
    "sg:postcode":"9920",
    "sg:province":"Oost-Vlaanderen",
    "sg:tags":[
        "surveyor",
        "land"
    ],
    "wof:name":"Wille R",
    "wof:placetype":"venue"
},
  "geometry": {"coordinates":[3.6203188896,51.1029853821],"type":"Point"}
}