{
  "type": "Feature",
  "properties": {
    "addr:full":"Vichtsesteenweg 150 Anzegem West-Vlaanderen 8570",
    "addr:housenumber":"150",
    "addr:postcode":"8570",
    "addr:street":"Vichtsesteenweg",
    "iso:country":"BE",
    "sg:address":"Vichtsesteenweg 150",
    "sg:city":"Anzegem",
    "sg:classifiers":[
        {
            "category":"Insurance",
            "subcategory":"Insurance Agent",
            "type":"Services"
        }
    ],
    "sg:phone":"+32 56 68 85 98",
    "sg:postcode":"8570",
    "sg:province":"West-Vlaanderen",
    "sg:tags":[
        "broker"
    ],
    "wof:name":"Verleyen D",
    "wof:placetype":"venue"
},
  "geometry": {"coordinates":[3.4395298958,50.8479881287],"type":"Point"}
}