{
  "type": "Feature",
  "properties": {
    "iso:country":"BE",
    "sg:address":"Kanadezenlaan 64",
    "sg:city":"Kalmthout",
    "sg:classifiers":[
        {
            "category":"Shopping",
            "subcategory":"Computers & Home Electronics",
            "type":"Retail Goods"
        }
    ],
    "sg:phone":"+32 3 666 44 27",
    "sg:postcode":"2920",
    "sg:province":"Antwerpen",
    "sg:tags":[
        "electronic",
        "module"
    ],
    "wof:name":"Schimmel J. Tijdelijke Handelsv.",
    "wof:placetype":"venue"
},
  "geometry": {"coordinates":[4.4504451752,51.361907959],"type":"Point"}
}