{
  "type": "Feature",
  "properties": {
    "addr:full":"Rue Du Long Sart 44 Namur Namur 5021",
    "addr:housenumber":"44",
    "addr:postcode":"5021",
    "addr:street":"Rue Du Long Sart",
    "iso:country":"BE",
    "sg:address":"Rue Du Long Sart 44",
    "sg:city":"Namur",
    "sg:orig_category":"Artsen and specialisten",
    "sg:phone":"+32 81 21 31 76",
    "sg:postcode":"5021",
    "sg:province":"Namur",
    "wof:name":"Marie-france Doyen",
    "wof:placetype":"venue"
},
  "geometry": {"coordinates":[4.914285183,50.4789276123],"type":"Point"}
}