{
  "type": "Feature",
  "properties": {
    "addr:full":"Rue Des Munos 1 Bertrix Luxembourg 6880",
    "addr:housenumber":"1",
    "addr:postcode":"6880",
    "addr:street":"Rue Des Munos",
    "iso:country":"BE",
    "sg:address":"Rue Des Munos 1",
    "sg:city":"Bertrix",
    "sg:orig_category":"Epiceries. Terrains de camping",
    "sg:phone":"+32 61 41 22 81",
    "sg:postcode":"6880",
    "sg:province":"Luxembourg",
    "wof:name":"Ic Camping",
    "wof:placetype":"venue"
},
  "geometry": {"coordinates":[5.2513980865,49.8467292786],"type":"Point"}
}