{
  "type": "Feature",
  "properties": {
    "addr:full":"Brouwershof 7 Zemst Vlaams-Brabant 1980",
    "addr:housenumber":"7",
    "addr:postcode":"1980",
    "addr:street":"Brouwershof;Vlaams-Brabant",
    "iso:country":"BE",
    "sg:address":"Brouwershof 7",
    "sg:city":"Zemst",
    "sg:orig_category":"D\u00e9corateurs d'int\u00e9rieur",
    "sg:phone":"+32 15 61 43 09",
    "sg:postcode":"1980",
    "sg:province":"Vlaams-Brabant",
    "wof:name":"Guy Vanden Branden",
    "wof:placetype":"venue"
},
  "geometry": {"coordinates":[4.4570479393,50.9665145874],"type":"Point"}
}