{
  "type": "Feature",
  "properties": {
    "addr:full":"P.f. De Naeyerstraat 6b Lebbeke Oost-Vlaanderen 9280",
    "addr:housenumber":"6b",
    "addr:postcode":"9280",
    "addr:street":"P.F. De Naeyerstraat",
    "iso:country":"BE",
    "sg:address":"P.f. De Naeyerstraat 6b",
    "sg:city":"Lebbeke",
    "sg:classifiers":[
        {
            "category":"Health Services",
            "subcategory":"Nursing And Care Facility",
            "type":"Services"
        }
    ],
    "sg:phone":"+32 52 40 80 41",
    "sg:postcode":"9280",
    "sg:province":"Oost-Vlaanderen",
    "sg:tags":[
        "home"
    ],
    "wof:name":"De Backer M",
    "wof:placetype":"venue"
},
  "geometry": {"coordinates":[4.1484451294,50.9958610535],"type":"Point"}
}