{
  "type": "Feature",
  "properties": {
    "iso:country":"BE",
    "sg:address":"Rue Du Prahy 51",
    "sg:city":"Sambreville",
    "sg:orig_category":"Installatie van houten of kunststof schrijnwerk MEUBELONTWERP AND -INSTALLATIE",
    "sg:phone":"+32 71 74 18 39",
    "sg:postcode":"5060",
    "sg:province":"Namur",
    "wof:name":"Michael Bertoni",
    "wof:placetype":"venue"
},
  "geometry": {"coordinates":[4.6339058876,50.4724006653],"type":"Point"}
}