{
  "type": "Feature",
  "properties": {
    "addr:full":"Kazernestraat 80 Brussel/bruxelles Bruxelles-Capitale 1000",
    "addr:housenumber":"80",
    "addr:postcode":"1000",
    "addr:street":"Kazernestraat;/",
    "iso:country":"BE",
    "sg:address":"Kazernestraat 80",
    "sg:city":"Brussel/bruxelles",
    "sg:orig_category":"Opinieonderzoekbureaus Werk and personeelsselectie",
    "sg:phone":"+32 2 501 27 11",
    "sg:postcode":"1000",
    "sg:province":"Bruxelles-Capitale",
    "wof:name":"Brann Ki Teleresources",
    "wof:placetype":"venue"
},
  "geometry": {"coordinates":[4.3417711258,50.8417015076],"type":"Point"}
}