{
  "type": "Feature",
  "properties": {
    "addr:full":"Don Bosco Straat 18 Hechtel Limburg 3940",
    "addr:housenumber":"18",
    "addr:postcode":"3940",
    "addr:street":"Don Bosco Straat",
    "iso:country":"BE",
    "sg:address":"Don Bosco Straat 18",
    "sg:city":"Hechtel",
    "sg:orig_category":"Juwelen and horloges Swatch",
    "sg:phone":"+32 11 73 49 60",
    "sg:postcode":"3940",
    "sg:province":"Limburg",
    "wof:name":"Juwelier Dries",
    "wof:placetype":"venue"
},
  "geometry": {"coordinates":[5.3655362129,51.1241569519],"type":"Point"}
}