{
  "type": "Feature",
  "properties": {
    "addr:full":"Grote Markt 56 Turnhout Antwerpen 2300",
    "addr:housenumber":"56",
    "addr:postcode":"2300",
    "addr:street":"Grote Markt",
    "iso:country":"BE",
    "sg:address":"Grote Markt 56",
    "sg:city":"Turnhout",
    "sg:classifiers":[
        {
            "category":"Fast Food",
            "type":"Food & Drink"
        }
    ],
    "sg:phone":"+32 14 41 27 01",
    "sg:postcode":"2300",
    "sg:province":"Antwerpen",
    "sg:tags":[
        "meeneem",
        "restaurant"
    ],
    "wof:name":"Tai Tong",
    "wof:placetype":"venue"
},
  "geometry": {"coordinates":[4.9478721619,51.3227462769],"type":"Point"}
}