{
  "type": "Feature",
  "properties": {
    "iso:country":"BE",
    "sg:address":"Rue Nazareth 11",
    "sg:city":"Herve (battice)",
    "sg:classifiers":[
        {
            "category":"Manufacturing",
            "subcategory":"Metals",
            "type":"Manufacturing & Wholesale Goods"
        }
    ],
    "sg:phone":"+32 87 69 27 40",
    "sg:postcode":"4651",
    "sg:province":"Li\u00e8ge",
    "sg:tags":[
        "ironwork"
    ],
    "wof:name":"Vitiello Sa",
    "wof:placetype":"venue"
},
  "geometry": {"coordinates":[5.8010401726,50.6468582153],"type":"Point"}
}