{
  "type": "Feature",
  "properties": {
    "iso:country":"BE",
    "sg:address":"Groeningelaan 4",
    "sg:city":"Kortrijk",
    "sg:classifiers":[
        {
            "category":"Professional",
            "subcategory":"Computer Services",
            "type":"Services"
        }
    ],
    "sg:phone":"+32 56 20 23 82",
    "sg:postcode":"8500",
    "sg:province":"West-Vlaanderen",
    "sg:tags":[
        "-",
        "processing",
        "data"
    ],
    "wof:name":"Essentials",
    "wof:placetype":"venue"
},
  "geometry": {"coordinates":[3.2757430077,50.8269386292],"type":"Point"}
}