{
  "type": "Feature",
  "properties": {
    "addr:full":"Rue Hov\u00c9mont 76 Theux Li\u00e8ge 4910",
    "addr:housenumber":"76",
    "addr:postcode":"4910",
    "addr:street":"Rue Hove\u0301Mont",
    "iso:country":"BE",
    "sg:address":"Rue Hov\u00c9mont 76",
    "sg:city":"Theux",
    "sg:orig_category":"Instituts de beaut\u00e9. M\u00e9decins and sp\u00e9cialistes",
    "sg:phone":"+32 87 54 16 09",
    "sg:postcode":"4910",
    "sg:province":"Li\u00e8ge",
    "wof:name":"Albert Freson-herman",
    "wof:placetype":"venue"
},
  "geometry": {"coordinates":[5.814748764,50.5326919556],"type":"Point"}
}