{
  "type": "Feature",
  "properties": {
    "addr:full":"Rue Hubert Stiernet 9 Waremme Li\u00e8ge 4300",
    "addr:housenumber":"9",
    "addr:postcode":"4300",
    "addr:street":"Rue Hubert Stiernet",
    "iso:country":"BE",
    "sg:address":"Rue Hubert Stiernet 9",
    "sg:city":"Waremme",
    "sg:classifiers":[
        {
            "category":"Retail",
            "subcategory":"Laundry & Dry Cleaning",
            "type":"Services"
        }
    ],
    "sg:phone":"+32 19 33 28 65",
    "sg:postcode":"4300",
    "sg:province":"Li\u00e8ge",
    "sg:tags":[
        "dyer",
        "cleaner"
    ],
    "wof:name":"Inter Pressing",
    "wof:placetype":"venue"
},
  "geometry": {"coordinates":[5.2561130524,50.6985359192],"type":"Point"}
}