{
  "type": "Feature",
  "properties": {
    "iso:country":"BE",
    "sg:address":"Koningsvijverstraat 5",
    "sg:city":"Herk-de-stad",
    "sg:orig_category":"M\u00e9decins and sp\u00e9cialistes",
    "sg:phone":"+32 13 55 15 84",
    "sg:postcode":"3540",
    "sg:province":"Limburg",
    "wof:name":"Kristien Paesmans",
    "wof:placetype":"venue"
},
  "geometry": {"coordinates":[5.184773922,50.9544334412],"type":"Point"}
}