{
  "type": "Feature",
  "properties": {
    "iso:country":"BE",
    "sg:address":"Lichtstoetstraat 2",
    "sg:city":"Mol",
    "sg:orig_category":"Paramedische behandelingen",
    "sg:phone":"+32 14 31 79 44",
    "sg:postcode":"2400",
    "sg:province":"Antwerpen",
    "wof:name":"Thuisverpleging Mol",
    "wof:placetype":"venue"
},
  "geometry": {"coordinates":[5.1237950325,51.1912956238],"type":"Point"}
}