{
  "type": "Feature",
  "properties": {
    "iso:country":"BE",
    "sg:address":"Rue Emile Vandervelde 267",
    "sg:city":"Mons",
    "sg:classifiers":[
        {
            "category":"Retail",
            "subcategory":"Auto Repair",
            "type":"Services"
        }
    ],
    "sg:phone":"+32 65 84 43 35",
    "sg:postcode":"7000",
    "sg:province":"Hainaut",
    "sg:tags":[
        "breakdown",
        "automobile",
        "-",
        "recovery"
    ],
    "wof:name":"Grouselle C",
    "wof:placetype":"venue"
},
  "geometry": {"coordinates":[3.9406020641,50.4402999878],"type":"Point"}
}