{
  "type": "Feature",
  "properties": {
    "addr:full":"Boekhoutstraat 2 Affligem (hekelgem) Vlaams-Brabant 1790",
    "addr:housenumber":"2",
    "addr:postcode":"1790",
    "addr:street":"Boekhoutstraat",
    "iso:country":"BE",
    "sg:address":"Boekhoutstraat 2",
    "sg:city":"Affligem (hekelgem)",
    "sg:classifiers":[
        {
            "category":"Bakery",
            "type":"Food & Drink"
        }
    ],
    "sg:phone":"+32 53 66 70 76",
    "sg:postcode":"1790",
    "sg:province":"Vlaams-Brabant",
    "sg:tags":[
        "confectioner",
        "baker"
    ],
    "wof:name":"Vermoesen L & Zonen Bakk. Bvba",
    "wof:placetype":"venue"
},
  "geometry": {"coordinates":[4.1043109894,50.9136962891],"type":"Point"}
}