{
  "type": "Feature",
  "properties": {
    "iso:country":"BE",
    "sg:address":"Rue Du Grand Chant",
    "sg:city":"Noville-les-bois",
    "sg:classifiers":[
        {
            "category":"Shopping",
            "subcategory":"Stationery & Office Supplies",
            "type":"Retail Goods"
        }
    ],
    "sg:phone":"+32 81 83 00 00",
    "sg:postcode":"5380",
    "sg:province":"Namur",
    "sg:tags":[
        "information",
        "technology",
        "telecommunication",
        "equipment"
    ],
    "wof:name":"Priminfo Sa",
    "wof:placetype":"venue"
},
  "geometry": {"coordinates":[4.9768600464,50.5379943848],"type":"Point"}
}