{
  "type": "Feature",
  "properties": {
    "iso:country":"BE",
    "sg:address":"Avenue De Wisterz\u00e9e 39",
    "sg:city":"Court-saint-etienne",
    "sg:classifiers":[
        {
            "category":"Professional",
            "subcategory":"Accounting & Tax Preparation",
            "type":"Services"
        }
    ],
    "sg:phone":"+32 10 61 74 41",
    "sg:postcode":"1490",
    "sg:province":"Brabant Wallon",
    "sg:tags":[
        "bookkeeper"
    ],
    "wof:name":"Guillaume H",
    "wof:placetype":"venue"
},
  "geometry": {"coordinates":[4.5641717911,50.6475830078],"type":"Point"}
}