{
  "type": "Feature",
  "properties": {
    "iso:country":"BE",
    "sg:address":"Tervuursesteenweg 286b2",
    "sg:city":"Steenokkerzeel",
    "sg:orig_category":"Avocats and conseillers juridiques",
    "sg:phone":"+32 2 751 82 54",
    "sg:postcode":"1820",
    "sg:province":"Vlaams-Brabant",
    "wof:name":"M. Smout",
    "wof:placetype":"venue"
},
  "geometry": {"coordinates":[4.5048298836,50.9167709351],"type":"Point"}
}