{
  "type": "Feature",
  "properties": {
    "iso:country":"BE",
    "sg:address":"Dr E. De Croesstraat 8",
    "sg:city":"Ternat",
    "sg:orig_category":"Equipements divers pour l\u00b4industrie Gr",
    "sg:phone":"+32 2 582 68 78",
    "sg:postcode":"1740",
    "sg:province":"Vlaams-Brabant",
    "wof:name":"Soxy Services",
    "wof:placetype":"venue"
},
  "geometry": {"coordinates":[4.1640758514,50.8751335144],"type":"Point"}
}