{
  "type": "Feature",
  "properties": {
    "addr:full":"Boulevard Emile Bockstael 93a Bruxelles Bruxelles-Capitale 1020",
    "addr:housenumber":"93a",
    "addr:postcode":"1020",
    "addr:street":"Boulevard Emile Bockstael",
    "iso:country":"BE",
    "sg:address":"Boulevard Emile Bockstael 93a",
    "sg:city":"Bruxelles",
    "sg:classifiers":[
        {
            "category":"Shopping",
            "subcategory":"Pawn Shop",
            "type":"Retail Goods"
        }
    ],
    "sg:phone":"+32 2 479 94 61",
    "sg:postcode":"1020",
    "sg:province":"Bruxelles-Capitale",
    "sg:tags":[
        "tax",
        "free"
    ],
    "wof:name":"Global Refund Belgium",
    "wof:placetype":"venue"
},
  "geometry": {"coordinates":[4.3458991051,50.8727722168],"type":"Point"}
}