{
  "type": "Feature",
  "properties": {
    "iso:country":"BE",
    "sg:address":"Avenue Bel Air 80",
    "sg:city":"Bruxelles (uccle)",
    "sg:classifiers":[
        {
            "category":"Real Estate",
            "subcategory":"Architect",
            "type":"Services"
        }
    ],
    "sg:phone":"+32 2 343 87 83",
    "sg:postcode":"1180",
    "sg:province":"Bruxelles-Capitale",
    "wof:name":"Gonzalez P",
    "wof:placetype":"venue"
},
  "geometry": {"coordinates":[4.3629770279,50.8125801086],"type":"Point"}
}