{
  "type": "Feature",
  "properties": {
    "addr:full":"Bitterzoetlaan 2 Koksijde (oostduinkerke) West-Vlaanderen 8670",
    "addr:housenumber":"2",
    "addr:postcode":"8670",
    "addr:street":"Bitterzoetlaan",
    "iso:country":"BE",
    "sg:address":"Bitterzoetlaan 2",
    "sg:city":"Koksijde (oostduinkerke)",
    "sg:classifiers":[
        {
            "category":"Health Services",
            "subcategory":"Health Practitioner",
            "type":"Services"
        }
    ],
    "sg:phone":"+32 58 51 40 32",
    "sg:postcode":"8670",
    "sg:province":"West-Vlaanderen",
    "sg:tags":[
        "physiotherapist"
    ],
    "wof:name":"Stockelynck P",
    "wof:placetype":"venue"
},
  "geometry": {"coordinates":[2.6773290634,51.1247787476],"type":"Point"}
}