{
  "type": "Feature",
  "properties": {
    "addr:full":"Place 11 Tournai (esplechin) Hainaut 7502",
    "addr:housenumber":"11",
    "addr:postcode":"7502",
    "addr:street":"Tournai Esplechin Hainaut",
    "iso:country":"BE",
    "sg:address":"Place 11",
    "sg:city":"Tournai (esplechin)",
    "sg:classifiers":[
        {
            "category":"Bars & Pubs",
            "type":"Food & Drink"
        }
    ],
    "sg:phone":"+32 69 64 76 71",
    "sg:postcode":"7502",
    "sg:province":"Hainaut",
    "wof:name":"Aux Gais Gamins",
    "wof:placetype":"venue"
},
  "geometry": {"coordinates":[3.3065268993,50.5743675232],"type":"Point"}
}