{
  "type": "Feature",
  "properties": {
    "iso:country":"BE",
    "sg:address":"Steenweg 181a Box 1",
    "sg:city":"Heers",
    "sg:classifiers":[
        {
            "category":"Professional",
            "subcategory":"Art Services",
            "type":"Services"
        }
    ],
    "sg:phone":"+32 11 48 18 59",
    "sg:postcode":"3870",
    "sg:province":"Limburg",
    "sg:tags":[
        "photography",
        "reporting",
        "-"
    ],
    "wof:name":"Studio Pierre Calu",
    "wof:placetype":"venue"
},
  "geometry": {"coordinates":[5.3005571365,50.7491226196],"type":"Point"}
}