{
  "type": "Feature",
  "properties": {
    "addr:full":"Rozenberg 85 Mol Antwerpen 2400",
    "addr:housenumber":"85",
    "addr:postcode":"2400",
    "addr:street":"Rozenberg",
    "iso:country":"BE",
    "sg:address":"Rozenberg 85",
    "sg:city":"Mol",
    "sg:classifiers":[
        {
            "category":"Building & Trades",
            "subcategory":"Landscaping Services",
            "type":"Services"
        }
    ],
    "sg:phone":"+32 14 32 46 70",
    "sg:postcode":"2400",
    "sg:province":"Antwerpen",
    "sg:tags":[
        "architect",
        "landscape"
    ],
    "wof:name":"'t Groen Design",
    "wof:placetype":"venue"
},
  "geometry": {"coordinates":[5.1209959984,51.1885528564],"type":"Point"}
}