{
  "type": "Feature",
  "properties": {
    "addr:full":"Liebaardstraat 150 Waregem West-Vlaanderen 8792",
    "addr:housenumber":"150",
    "addr:postcode":"8792",
    "addr:street":"Liebaardstraat",
    "iso:country":"BE",
    "sg:address":"Liebaardstraat 150",
    "sg:city":"Waregem",
    "sg:classifiers":[
        {
            "category":"Cafe",
            "type":"Food & Drink"
        }
    ],
    "sg:phone":"+32 56 71 97 96",
    "sg:postcode":"8792",
    "sg:province":"West-Vlaanderen",
    "sg:tags":[
        "caf\u00e9s"
    ],
    "wof:name":"Caf\u00c9 't Zweerd",
    "wof:placetype":"venue"
},
  "geometry": {"coordinates":[3.354268074,50.8828811646],"type":"Point"}
}