{
  "type": "Feature",
  "properties": {
    "addr:full":"Lievevrouwdreef 39 Maldegem Oost-Vlaanderen 9990",
    "addr:housenumber":"39",
    "addr:postcode":"9990",
    "addr:street":"Lievevrouwdreef",
    "iso:country":"BE",
    "sg:address":"Lievevrouwdreef 39",
    "sg:city":"Maldegem",
    "sg:orig_category":"Eleveurs and marchands de porcs. Eleveurs de bovins",
    "sg:phone":"+32 50 71 26 48",
    "sg:postcode":"9990",
    "sg:province":"Oost-Vlaanderen",
    "wof:name":"Gabriel Landuyt",
    "wof:placetype":"venue"
},
  "geometry": {"coordinates":[3.4380099773,51.1790885925],"type":"Point"}
}