{
  "type": "Feature",
  "properties": {
    "iso:country":"BE",
    "sg:address":"Marktstraat 25",
    "sg:city":"Hoeselt (sint-huibrechts-hern)",
    "sg:classifiers":[
        {
            "category":"Health Services",
            "subcategory":"Doctor",
            "type":"Services"
        }
    ],
    "sg:phone":"+32 12 39 41 92",
    "sg:postcode":"3730",
    "sg:province":"Limburg",
    "sg:tags":[
        "medicinephysicians",
        "surgeon"
    ],
    "wof:name":"Germeaux Y",
    "wof:placetype":"venue"
},
  "geometry": {"coordinates":[5.4478120804,50.8290596008],"type":"Point"}
}