{
  "type": "Feature",
  "properties": {
    "addr:full":"Kerkplein 26a Lommel Limburg 3920",
    "addr:housenumber":"26a",
    "addr:postcode":"3920",
    "addr:street":"Kerkplein",
    "iso:country":"BE",
    "sg:address":"Kerkplein 26a",
    "sg:city":"Lommel",
    "sg:classifiers":[
        {
            "category":"Professional",
            "subcategory":"Accounting & Tax Preparation",
            "type":"Services"
        }
    ],
    "sg:phone":"+32 11 54 01 51",
    "sg:postcode":"3920",
    "sg:province":"Limburg",
    "sg:tags":[
        "accountant"
    ],
    "wof:name":"Bastiaens K",
    "wof:placetype":"venue"
},
  "geometry": {"coordinates":[5.3144130707,51.2287025452],"type":"Point"}
}