{
  "type": "Feature",
  "properties": {
    "iso:country":"BE",
    "sg:address":"Industriepark Rostijne 4",
    "sg:city":"Zelzate",
    "sg:classifiers":[
        {
            "category":"Manufacturing",
            "subcategory":"Tools & Machinery",
            "type":"Manufacturing & Wholesale Goods"
        }
    ],
    "sg:phone":"+32 9 342 23 23",
    "sg:postcode":"9060",
    "sg:province":"Oost-Vlaanderen",
    "sg:tags":[
        "builder"
    ],
    "wof:name":"Pro-c-ept Nv",
    "wof:placetype":"venue"
},
  "geometry": {"coordinates":[3.8146300316,51.1975364685],"type":"Point"}
}