{
  "type": "Feature",
  "properties": {
    "addr:full":"Kanunnikstraat 9 Herzele Oost-Vlaanderen 9550",
    "addr:housenumber":"9",
    "addr:postcode":"9550",
    "addr:street":"Kanunnikstraat;Oost-Vlaanderen",
    "iso:country":"BE",
    "sg:address":"Kanunnikstraat 9",
    "sg:city":"Herzele",
    "sg:orig_category":"Non-Classified Establishments",
    "sg:phone":"+32 53 62 24 49",
    "sg:postcode":"9550",
    "sg:province":"Oost-Vlaanderen",
    "wof:name":"Luxus Korsetfabriek Bvba",
    "wof:placetype":"venue"
},
  "geometry": {"coordinates":[3.8944990635,50.8833236694],"type":"Point"}
}