{
  "type": "Feature",
  "properties": {
    "addr:full":"Ridder Van Ranstlei 28 Mortsel Antwerpen 2640",
    "addr:housenumber":"28",
    "addr:postcode":"2640",
    "addr:street":"Ridder Van Ranstlei",
    "iso:country":"BE",
    "sg:address":"Ridder Van Ranstlei 28",
    "sg:city":"Mortsel",
    "sg:orig_category":"Installatie van houten of kunststof schrijnwerk",
    "sg:phone":"+32 3 449 21 90",
    "sg:postcode":"2640",
    "sg:province":"Antwerpen",
    "wof:name":"Gerardus Kames",
    "wof:placetype":"venue"
},
  "geometry": {"coordinates":[4.4393920898,51.1742286682],"type":"Point"}
}