{
  "type": "Feature",
  "properties": {
    "addr:full":"Stationlei 32 Vilvoorde Vlaams-Brabant 1800",
    "addr:housenumber":"32",
    "addr:postcode":"1800",
    "addr:street":"Stationlei",
    "iso:country":"BE",
    "sg:address":"Stationlei 32",
    "sg:city":"Vilvoorde",
    "sg:classifiers":[
        {
            "category":"Health Services",
            "subcategory":"Dentist",
            "type":"Services"
        }
    ],
    "sg:phone":"+32 2 252 30 00",
    "sg:postcode":"1800",
    "sg:province":"Vlaams-Brabant",
    "wof:name":"De Groote P",
    "wof:placetype":"venue"
},
  "geometry": {"coordinates":[4.4294872284,50.9256095886],"type":"Point"}
}