{
  "type": "Feature",
  "properties": {
    "iso:country":"BE",
    "sg:address":"Rue Des Grands Terrains 13",
    "sg:city":"Namur",
    "sg:orig_category":"Fournitures de bureau. Ordinateurs and \u00e9quipement informatique. Imprimeries and copyshops",
    "sg:phone":"+32 81 46 29 39",
    "sg:postcode":"5100",
    "sg:province":"Namur",
    "wof:name":"Dessin Inform.div.madetec",
    "wof:placetype":"venue"
},
  "geometry": {"coordinates":[4.8593149185,50.4255104065],"type":"Point"}
}