{
  "type": "Feature",
  "properties": {
    "iso:country":"BE",
    "sg:address":"30",
    "sg:city":"Scheldedijk Haven 1025 2070 Zwijndrecht Burcht",
    "sg:classifiers":[
        {
            "category":"Manufacturing",
            "subcategory":"Tools & Machinery",
            "type":"Manufacturing & Wholesale Goods"
        }
    ],
    "sg:phone":"+32 3 250 55 11",
    "sg:postcode":"30",
    "sg:tags":[
        "environment",
        "equipment",
        "-"
    ],
    "wof:name":"Application Of Cleaning Techniques On Soils Nv",
    "wof:placetype":"venue"
},
  "geometry": {"coordinates":[4.30189991,51.2501144409],"type":"Point"}
}