{
  "type": "Feature",
  "properties": {
    "iso:country":"BE",
    "sg:address":"Place Roi Baudouin 1",
    "sg:city":"Floreffe",
    "sg:orig_category":"Banques and organismes de cr\u00e9dit",
    "sg:phone":"+32 81 44 73 40",
    "sg:postcode":"5150",
    "sg:province":"Namur",
    "wof:name":"Dexia",
    "wof:placetype":"venue"
},
  "geometry": {"coordinates":[4.7598891258,50.4357185364],"type":"Point"}
}