{
  "type": "Feature",
  "properties": {
    "iso:country":"BE",
    "sg:address":"Gaversepontweg 20",
    "sg:city":"Nazareth",
    "sg:orig_category":"Balie van Gent. Avocats and conseillers juridiques. Avocats and conseillers juridiques",
    "sg:phone":"+32 9 384 54 40",
    "sg:postcode":"9810",
    "sg:province":"Oost-Vlaanderen",
    "wof:name":"De Smijter Pierre",
    "wof:placetype":"venue"
},
  "geometry": {"coordinates":[3.6282351017,50.9347648621],"type":"Point"}
}