{
  "type": "Feature",
  "properties": {
    "addr:full":"Markt 20 Wielsbeke West-Vlaanderen 8710",
    "addr:housenumber":"20",
    "addr:postcode":"8710",
    "addr:street":"Markt;West-Vlaanderen",
    "iso:country":"BE",
    "sg:address":"Markt 20",
    "sg:city":"Wielsbeke",
    "sg:classifiers":[
        {
            "category":"Communications",
            "subcategory":"Radio Station",
            "type":"Services"
        }
    ],
    "sg:phone":"+32 56 66 90 00",
    "sg:postcode":"8710",
    "sg:province":"West-Vlaanderen",
    "sg:tags":[
        "diffusion",
        "production",
        "de",
        "programme"
    ],
    "wof:name":"Radio Mango",
    "wof:placetype":"venue"
},
  "geometry": {"coordinates":[3.3698010445,50.9087257385],"type":"Point"}
}