{
  "type": "Feature",
  "properties": {
    "addr:full":"Pastoriestraat 60 Tremelo (baal) Vlaams-Brabant 3128",
    "addr:housenumber":"60",
    "addr:postcode":"3128",
    "addr:street":"Pastoriestraat",
    "iso:country":"BE",
    "sg:address":"Pastoriestraat 60",
    "sg:city":"Tremelo (baal)",
    "sg:classifiers":[
        {
            "category":"Professional",
            "subcategory":"Testing Lab",
            "type":"Services"
        }
    ],
    "sg:phone":"+32 16 53 00 42",
    "sg:postcode":"3128",
    "sg:province":"Vlaams-Brabant",
    "sg:tags":[
        "chemist"
    ],
    "wof:name":"Dehing C",
    "wof:placetype":"venue"
},
  "geometry": {"coordinates":[4.7517261505,50.9981040955],"type":"Point"}
}