{
  "type": "Feature",
  "properties": {
    "iso:country":"BE",
    "sg:address":"Oude Vladslostraat 4",
    "sg:city":"Kortemark",
    "sg:classifiers":[
        {
            "category":"Bars & Pubs",
            "subcategory":"Lounge",
            "type":"Food & Drink"
        }
    ],
    "sg:phone":"+32 51 56 99 85",
    "sg:postcode":"8610",
    "sg:province":"West-Vlaanderen",
    "sg:tags":[
        "d",
        "restaurant",
        "organisation",
        "\u00c0",
        "domicile",
        "fast",
        "catering",
        "emporter",
        "livraison",
        "restaurants"
    ],
    "wof:name":"De Hobbit",
    "wof:placetype":"venue"
},
  "geometry": {"coordinates":[2.9430859089,51.0368156433],"type":"Point"}
}