{
  "type": "Feature",
  "properties": {
    "addr:full":"Markegemsesteenweg 20 Dentergem West-Vlaanderen 8720",
    "addr:housenumber":"20",
    "addr:postcode":"8720",
    "addr:street":"Markegemsesteenweg",
    "iso:country":"BE",
    "sg:address":"Markegemsesteenweg 20",
    "sg:city":"Dentergem",
    "sg:orig_category":"Motos. V\u00e9los",
    "sg:phone":"+32 51 63 34 27",
    "sg:postcode":"8720",
    "sg:province":"West-Vlaanderen",
    "wof:name":"Noel Vermeeren",
    "wof:placetype":"venue"
},
  "geometry": {"coordinates":[3.4172708988,50.9625282288],"type":"Point"}
}