{
  "type": "Feature",
  "properties": {
    "addr:full":"Rue Louis Mar\u00c9chal 114 Oreye Li\u00e8ge 4360",
    "addr:housenumber":"114",
    "addr:postcode":"4360",
    "addr:street":"Rue Louis Mare\u0301Chal",
    "iso:country":"BE",
    "sg:address":"Rue Louis Mar\u00c9chal 114",
    "sg:city":"Oreye",
    "sg:orig_category":"Dakwerken",
    "sg:phone":"+32 19 58 74 93",
    "sg:postcode":"4360",
    "sg:province":"Li\u00e8ge",
    "wof:name":"Entreprise Daniel",
    "wof:placetype":"venue"
},
  "geometry": {"coordinates":[5.336974144,50.7211990356],"type":"Point"}
}