{
  "type": "Feature",
  "properties": {
    "iso:country":"BE",
    "sg:address":"Avenue Am\u00c9d\u00c9e Hesse 9",
    "sg:city":"Spa",
    "sg:orig_category":"Sportterreinen and installaties behalve sportcentra",
    "sg:phone":"+32 87 77 21 10",
    "sg:postcode":"4900",
    "sg:province":"Li\u00e8ge",
    "wof:name":"Piscine Communale",
    "wof:placetype":"venue"
},
  "geometry": {"coordinates":[5.8742089272,50.4951591492],"type":"Point"}
}