{
  "type": "Feature",
  "properties": {
    "addr:full":"Rue Portaels 40 Bruxelles (schaerbeek) Bruxelles-Capitale 1030",
    "addr:housenumber":"40",
    "addr:postcode":"1030",
    "addr:street":"Rue Portaels",
    "iso:country":"BE",
    "sg:address":"Rue Portaels 40",
    "sg:city":"Bruxelles (schaerbeek)",
    "sg:classifiers":[
        {
            "category":"Wholesale",
            "subcategory":"Construction Materials",
            "type":"Manufacturing & Wholesale Goods"
        }
    ],
    "sg:phone":"+32 2 241 73 50",
    "sg:postcode":"1030",
    "sg:province":"Bruxelles-Capitale",
    "sg:tags":[
        "tubing",
        "industrial"
    ],
    "wof:name":"Synertra Sa",
    "wof:placetype":"venue"
},
  "geometry": {"coordinates":[4.3751502037,50.872959137],"type":"Point"}
}