{
  "type": "Feature",
  "properties": {
    "addr:full":"Sint-christianastraat 34 Box 2 Dendermonde Oost-Vlaanderen 9200",
    "addr:housenumber":"34;2",
    "addr:postcode":"9200",
    "addr:street":"Sint-Christianastraat;Box;Oost-Vlaanderen",
    "iso:country":"BE",
    "sg:address":"Sint-christianastraat 34 Box 2",
    "sg:city":"Dendermonde",
    "sg:classifiers":[
        {
            "category":"Professional",
            "subcategory":"Computer Services",
            "type":"Services"
        }
    ],
    "sg:phone":"+32 52 22 36 64",
    "sg:postcode":"9200",
    "sg:province":"Oost-Vlaanderen",
    "sg:tags":[
        "-",
        "processing",
        "data",
        "software"
    ],
    "wof:name":"Experts Technologies Nv",
    "wof:placetype":"venue"
},
  "geometry": {"coordinates":[4.0900101662,51.0324783325],"type":"Point"}
}