{
  "type": "Feature",
  "properties": {
    "iso:country":"BE",
    "sg:address":"Rue Au Dela De L'eau",
    "sg:city":"Nassogne (bande)",
    "sg:classifiers":[
        {
            "category":"Arena",
            "subcategory":"Sports Club",
            "type":"Entertainment"
        }
    ],
    "sg:phone":"+32 84 34 45 56",
    "sg:postcode":"6951",
    "sg:province":"Luxembourg",
    "wof:name":"Tennis Club De Bande Sprl",
    "wof:placetype":"venue"
},
  "geometry": {"coordinates":[5.4074110985,50.1609306335],"type":"Point"}
}