{
  "type": "Feature",
  "properties": {
    "iso:country":"BE",
    "sg:address":"Markt 26",
    "sg:city":"Ichtegem",
    "sg:classifiers":[
        {
            "category":"Farming",
            "subcategory":"Fish & Marine Products",
            "type":"Manufacturing & Wholesale Goods"
        }
    ],
    "sg:phone":"+32 51 58 03 95",
    "sg:postcode":"8480",
    "sg:province":"West-Vlaanderen",
    "sg:tags":[
        "retail",
        "-",
        "shellfish"
    ],
    "wof:name":"Claudine",
    "wof:placetype":"venue"
},
  "geometry": {"coordinates":[3.010160923,51.0922813416],"type":"Point"}
}