{
  "type": "Feature",
  "properties": {
    "iso:country":"BE",
    "sg:address":"Groteheide 74",
    "sg:city":"Neerpelt",
    "sg:orig_category":"Pluimveekwekers Rundveehouders",
    "sg:phone":"+32 11 64 76 80",
    "sg:postcode":"3910",
    "sg:province":"Limburg",
    "wof:name":"Johannes Jansen",
    "wof:placetype":"venue"
},
  "geometry": {"coordinates":[5.437210083,51.2591285706],"type":"Point"}
}