{
  "type": "Feature",
  "properties": {
    "addr:full":"Molenstraat 1ba Blankenberge West-Vlaanderen 8370",
    "addr:housenumber":"1ba",
    "addr:postcode":"8370",
    "addr:street":"Molenstraat",
    "iso:country":"BE",
    "sg:address":"Molenstraat 1ba",
    "sg:city":"Blankenberge",
    "sg:orig_category":"Banques and organismes de cr\u00e9dit",
    "sg:phone":"+32 50 41 17 45",
    "sg:postcode":"8370",
    "sg:province":"West-Vlaanderen",
    "wof:name":"Bbl",
    "wof:placetype":"venue"
},
  "geometry": {"coordinates":[3.1280319691,51.3138237],"type":"Point"}
}