{
  "type": "Feature",
  "properties": {
    "iso:country":"BE",
    "sg:address":"Felix Timmermanslaan 2",
    "sg:city":"Stekene",
    "sg:orig_category":"Ordinateurs and \u00e9quipement informatique",
    "sg:phone":"+32 3 779 61 67",
    "sg:postcode":"9190",
    "sg:province":"Oost-Vlaanderen",
    "wof:name":"'t Computerken",
    "wof:placetype":"venue"
},
  "geometry": {"coordinates":[4.0721640587,51.20835495],"type":"Point"}
}