{
  "type": "Feature",
  "properties": {
    "iso:country":"BE",
    "sg:address":"Nijverheidslaan 7ba1",
    "sg:city":"Wevelgem",
    "sg:orig_category":"Installatie van houten of kunststof schrijnwerk Verlichting and huishoudartikelen",
    "sg:phone":"+32 56 41 16 86",
    "sg:postcode":"8560",
    "sg:province":"West-Vlaanderen",
    "wof:name":"Geert Lust",
    "wof:placetype":"venue"
},
  "geometry": {"coordinates":[3.1858050823,50.8452720642],"type":"Point"}
}