{
  "type": "Feature",
  "properties": {
    "iso:country":"BE",
    "sg:address":"Gebroeders Romboutsstraat 2",
    "sg:city":"Mechelen",
    "sg:classifiers":[
        {
            "category":"Building & Trades",
            "subcategory":"Pest Control",
            "type":"Services"
        }
    ],
    "sg:phone":"+32 15 55 75 92",
    "sg:postcode":"2800",
    "sg:province":"Antwerpen",
    "sg:tags":[
        "painting",
        "contractor"
    ],
    "wof:name":"De Coninck",
    "wof:placetype":"venue"
},
  "geometry": {"coordinates":[4.4947719574,51.0365104675],"type":"Point"}
}