{
  "type": "Feature",
  "properties": {
    "addr:full":"Avenue J.f. Debecker 54 Bruxelles (woluwe-saint-lambert) Bruxelles-Capitale 1200",
    "addr:housenumber":"54",
    "addr:postcode":"1200",
    "addr:street":"Avenue J.F. Debecker",
    "iso:country":"BE",
    "sg:address":"Avenue J.f. Debecker 54",
    "sg:city":"Bruxelles (woluwe-saint-lambert)",
    "sg:classifiers":[
        {
            "category":"Retail",
            "subcategory":"Event Space",
            "type":"Services"
        }
    ],
    "sg:phone":"+32 2 770 03 44",
    "sg:postcode":"1200",
    "sg:province":"Bruxelles-Capitale",
    "sg:tags":[
        "rental",
        "-",
        "hall"
    ],
    "wof:name":"Fonds Sportif la Rotonde",
    "wof:placetype":"venue"
},
  "geometry": {"coordinates":[4.4441928864,50.8436927795],"type":"Point"}
}