{
  "type": "Feature",
  "properties": {
    "addr:full":"Lauwestraat 48 Menen West-Vlaanderen 8930",
    "addr:housenumber":"48",
    "addr:postcode":"8930",
    "addr:street":"Lauwestraat",
    "iso:country":"BE",
    "sg:address":"Lauwestraat 48",
    "sg:city":"Menen",
    "sg:orig_category":"Schoonmaakbedrijven and ongediertebestrijding",
    "sg:phone":"+32 56 42 13 46",
    "sg:postcode":"8930",
    "sg:province":"West-Vlaanderen",
    "wof:name":"Perfection",
    "wof:placetype":"venue"
},
  "geometry": {"coordinates":[3.164839983,50.7857437134],"type":"Point"}
}