{
  "type": "Feature",
  "properties": {
    "addr:full":"Galerie Ste-begge 7 Andenne Namur 5300",
    "addr:housenumber":"7",
    "addr:postcode":"5300",
    "iso:country":"BE",
    "sg:address":"Galerie Ste-begge 7",
    "sg:city":"Andenne",
    "sg:classifiers":[
        {
            "category":"Health Services",
            "subcategory":"Health Practitioner",
            "type":"Services"
        }
    ],
    "sg:phone":"+32 85 84 55 93",
    "sg:postcode":"5300",
    "sg:province":"Namur",
    "sg:tags":[
        "physiotherapist"
    ],
    "wof:name":"Magnus Jean-marc",
    "wof:placetype":"venue"
},
  "geometry": {"coordinates":[5.1009101868,50.4865226746],"type":"Point"}
}