{
  "type": "Feature",
  "properties": {
    "iso:country":"BE",
    "sg:address":"Koningin Astridlaan 130",
    "sg:city":"Gent",
    "sg:orig_category":"Blanchisseries and teintureries",
    "sg:phone":"+32 9 222 13 80",
    "sg:postcode":"9000",
    "sg:province":"Oost-Vlaanderen",
    "wof:name":"Wasserij Zonneschijn",
    "wof:placetype":"venue"
},
  "geometry": {"coordinates":[3.7140650749,51.0364685059],"type":"Point"}
}