{
  "type": "Feature",
  "properties": {
    "addr:full":"Dam 13 Kortrijk West-Vlaanderen 8500",
    "addr:housenumber":"13",
    "addr:postcode":"8500",
    "addr:street":"Dam",
    "iso:country":"BE",
    "sg:address":"Dam 13",
    "sg:city":"Kortrijk",
    "sg:classifiers":[
        {
            "category":"Real Estate",
            "subcategory":"Architect",
            "type":"Services"
        }
    ],
    "sg:phone":"+32 56 21 81 36",
    "sg:postcode":"8500",
    "sg:province":"West-Vlaanderen",
    "wof:name":"Demeyere A",
    "wof:placetype":"venue"
},
  "geometry": {"coordinates":[3.2642700672,50.8319740295],"type":"Point"}
}