{
  "type": "Feature",
  "properties": {
    "addr:full":"Warandestraat 2 Waasmunster Oost-Vlaanderen 9250",
    "addr:housenumber":"2",
    "addr:postcode":"9250",
    "addr:street":"Warandestraat",
    "iso:country":"BE",
    "sg:address":"Warandestraat 2",
    "sg:city":"Waasmunster",
    "sg:orig_category":"Artsen and specialisten",
    "sg:phone":"+32 52 46 18 67",
    "sg:postcode":"9250",
    "sg:province":"Oost-Vlaanderen",
    "wof:name":"L. Sillis",
    "wof:placetype":"venue"
},
  "geometry": {"coordinates":[4.1258711815,51.1141204834],"type":"Point"}
}