{
  "type": "Feature",
  "properties": {
    "addr:full":"Avenue Wanderpepen 25 Binche Hainaut 7130",
    "addr:housenumber":"25",
    "addr:postcode":"7130",
    "addr:street":"Avenue Wanderpepen",
    "iso:country":"BE",
    "sg:address":"Avenue Wanderpepen 25",
    "sg:city":"Binche",
    "sg:orig_category":"Boekhouders",
    "sg:phone":"+32 64 33 95 54",
    "sg:postcode":"7130",
    "sg:province":"Hainaut",
    "wof:name":"Karl Delobbe",
    "wof:placetype":"venue"
},
  "geometry": {"coordinates":[4.1690101624,50.4122047424],"type":"Point"}
}