{
  "type": "Feature",
  "properties": {
    "addr:full":"Dynastiestraat 30 Zemst Vlaams-Brabant 1982",
    "addr:housenumber":"30",
    "addr:postcode":"1982",
    "addr:street":"Dynastiestraat;Vlaams-Brabant",
    "iso:country":"BE",
    "sg:address":"Dynastiestraat 30",
    "sg:city":"Zemst",
    "sg:orig_category":"Plaatsen van vloer- and muurbekleding Schilders",
    "sg:phone":"+32 15 61 55 62",
    "sg:postcode":"1982",
    "sg:province":"Vlaams-Brabant",
    "wof:name":"Luc Brondel",
    "wof:placetype":"venue"
},
  "geometry": {"coordinates":[4.5003609657,50.9612236023],"type":"Point"}
}