{
  "type": "Feature",
  "properties": {
    "addr:full":"Waterloolaan 53b5 Brussel/bruxelles Bruxelles-Capitale 1000",
    "addr:housenumber":"53b5",
    "addr:postcode":"1000",
    "addr:street":"Waterloolaan;/",
    "iso:country":"BE",
    "sg:address":"Waterloolaan 53b5",
    "sg:city":"Brussel/bruxelles",
    "sg:orig_category":"Diverse opleidingen and onderwijs",
    "sg:phone":"+32 2 511 01 49",
    "sg:postcode":"1000",
    "sg:province":"Bruxelles-Capitale",
    "wof:name":"C.b.c.",
    "wof:placetype":"venue"
},
  "geometry": {"coordinates":[4.3563327789,50.8367729187],"type":"Point"}
}