{
  "type": "Feature",
  "properties": {
    "addr:full":"Rue De La Station 1 Rixensart Brabant Wallon 1330",
    "addr:housenumber":"1",
    "addr:postcode":"1330",
    "addr:street":"Rue De La Station;Wallon",
    "iso:country":"BE",
    "sg:address":"Rue De La Station 1",
    "sg:city":"Rixensart",
    "sg:orig_category":"Treinen and spoorwegen",
    "sg:phone":"+32 10 43 22 59",
    "sg:postcode":"1330",
    "sg:province":"Brabant Wallon",
    "wof:name":"Gare De Rixensart",
    "wof:placetype":"venue"
},
  "geometry": {"coordinates":[4.5132899284,50.7240600586],"type":"Point"}
}