{
  "type": "Feature",
  "properties": {
    "addr:full":"Boswachterlaan 10 Tremelo Vlaams-Brabant 3120",
    "addr:housenumber":"10",
    "addr:postcode":"3120",
    "addr:street":"Boswachterlaan",
    "iso:country":"BE",
    "sg:address":"Boswachterlaan 10",
    "sg:city":"Tremelo",
    "sg:orig_category":"V\u00eatements",
    "sg:phone":"+32 16 53 03 65",
    "sg:postcode":"3120",
    "sg:province":"Vlaams-Brabant",
    "wof:name":"Maria Van De Velde",
    "wof:placetype":"venue"
},
  "geometry": {"coordinates":[4.731098175,50.9960174561],"type":"Point"}
}