{
  "type": "Feature",
  "properties": {
    "addr:full":"Havenlaan 1 Beringen (koersel) Limburg 3582",
    "addr:housenumber":"1",
    "addr:postcode":"3582",
    "addr:street":"Havenlaan",
    "iso:country":"BE",
    "sg:address":"Havenlaan 1",
    "sg:city":"Beringen (koersel)",
    "sg:classifiers":[
        {
            "category":"Health Services",
            "subcategory":"Doctor",
            "type":"Services"
        }
    ],
    "sg:phone":"+32 11 42 52 07",
    "sg:postcode":"3582",
    "sg:province":"Limburg",
    "sg:tags":[
        "medicinephysicians",
        "surgeon"
    ],
    "wof:name":"De Spiegeleer P",
    "wof:placetype":"venue"
},
  "geometry": {"coordinates":[5.2119598389,51.0713653564],"type":"Point"}
}