{
  "type": "Feature",
  "properties": {
    "iso:country":"BE",
    "sg:address":"Reigersstraat 13",
    "sg:city":"Harelbeke",
    "sg:classifiers":[
        {
            "category":"Home & Garden",
            "subcategory":"Home Furnishings",
            "type":"Retail Goods"
        }
    ],
    "sg:phone":"+32 56 71 62 75",
    "sg:postcode":"8530",
    "sg:province":"West-Vlaanderen",
    "sg:tags":[
        "interior",
        "decoration"
    ],
    "wof:name":"Colle Walter",
    "wof:placetype":"venue"
},
  "geometry": {"coordinates":[3.3222010136,50.8524398804],"type":"Point"}
}