{
  "type": "Feature",
  "properties": {
    "iso:country":"BE",
    "sg:address":"Rue Haute 20",
    "sg:city":"Renaix",
    "sg:classifiers":[
        {
            "category":"Professional",
            "subcategory":"Accounting & Tax Preparation",
            "type":"Services"
        }
    ],
    "sg:phone":"+32 55 23 77 55",
    "sg:postcode":"9600",
    "sg:province":"Oost-Vlaanderen",
    "sg:tags":[
        "accountant"
    ],
    "wof:name":"Accountancy Decotignies & Van Dille Burg. Nv",
    "wof:placetype":"venue"
},
  "geometry": {"coordinates":[3.5983569622,50.7457466125],"type":"Point"}
}