{
  "type": "Feature",
  "properties": {
    "addr:full":"Hoogstraat 7 Harelbeke West-Vlaanderen 8531",
    "addr:housenumber":"7",
    "addr:postcode":"8531",
    "addr:street":"Hoogstraat",
    "iso:country":"BE",
    "sg:address":"Hoogstraat 7",
    "sg:city":"Harelbeke",
    "sg:classifiers":[
        {
            "category":"Cafe",
            "type":"Food & Drink"
        }
    ],
    "sg:phone":"+32 56 71 11 10",
    "sg:postcode":"8531",
    "sg:province":"West-Vlaanderen",
    "sg:tags":[
        "caf\u00e9s"
    ],
    "wof:name":"Frans Verschatse",
    "wof:placetype":"venue"
},
  "geometry": {"coordinates":[3.310172081,50.8790931702],"type":"Point"}
}