{
  "type": "Feature",
  "properties": {
    "addr:full":"Schootstraat 32-1 Heusden-zolder (heusden) Limburg 3550",
    "addr:housenumber":"32-1",
    "addr:postcode":"3550",
    "addr:street":"Schootstraat",
    "iso:country":"BE",
    "sg:address":"Schootstraat 32-1",
    "sg:city":"Heusden-zolder (heusden)",
    "sg:classifiers":[
        {
            "category":"Building & Trades",
            "subcategory":"Landscaping Services",
            "type":"Services"
        }
    ],
    "sg:phone":"+32 11 43 47 25",
    "sg:postcode":"3550",
    "sg:province":"Limburg",
    "sg:tags":[
        "architect",
        "landscape"
    ],
    "wof:name":"Roskans Groendesign",
    "wof:placetype":"venue"
},
  "geometry": {"coordinates":[5.2758579254,51.0250549316],"type":"Point"}
}