{
  "type": "Feature",
  "properties": {
    "addr:full":"Abeelestraat 41 Wielsbeke West-Vlaanderen 8710",
    "addr:housenumber":"41",
    "addr:postcode":"8710",
    "addr:street":"Abeelestraat",
    "iso:country":"BE",
    "sg:address":"Abeelestraat 41",
    "sg:city":"Wielsbeke",
    "sg:orig_category":"Peinture",
    "sg:phone":"+32 56 66 82 11",
    "sg:postcode":"8710",
    "sg:province":"West-Vlaanderen",
    "wof:name":"De Keukelare",
    "wof:placetype":"venue"
},
  "geometry": {"coordinates":[3.3828558922,50.9135971069],"type":"Point"}
}