{
  "type": "Feature",
  "properties": {
    "addr:full":"Chauss\u00e9e De Tirlemont 203 Gembloux-sur-orneau (gembloux) Namur 5030",
    "addr:housenumber":"203",
    "addr:postcode":"5030",
    "addr:street":"Chausse\u0301E De Tirlemont;Namur",
    "iso:country":"BE",
    "sg:address":"Chauss\u00e9e De Tirlemont 203",
    "sg:city":"Gembloux-sur-orneau (gembloux)",
    "sg:classifiers":[
        {
            "category":"Home & Garden",
            "subcategory":"Household Appliances",
            "type":"Retail Goods"
        }
    ],
    "sg:phone":"+32 81 61 54 36",
    "sg:postcode":"5030",
    "sg:province":"Namur",
    "sg:tags":[
        "repair",
        "mainten",
        "-",
        "electric"
    ],
    "wof:name":"Maduelectro Sa",
    "wof:placetype":"venue"
},
  "geometry": {"coordinates":[4.7198061943,50.5899353027],"type":"Point"}
}