{
  "type": "Feature",
  "properties": {
    "iso:country":"BE",
    "sg:address":"Route D'ottignies 56",
    "sg:city":"Lasne (lasne-chapelle-saint-lambert)",
    "sg:classifiers":[
        {
            "category":"Health Services",
            "subcategory":"Health Practitioner",
            "type":"Services"
        }
    ],
    "sg:phone":"+32 2 633 44 16",
    "sg:postcode":"1380",
    "sg:province":"Brabant Wallon",
    "sg:tags":[
        "physiotherapist"
    ],
    "wof:name":"Wiertz J",
    "wof:placetype":"venue"
},
  "geometry": {"coordinates":[4.5025749207,50.6911201477],"type":"Point"}
}