{
  "type": "Feature",
  "properties": {
    "iso:country":"BE",
    "sg:address":"Haag 78",
    "sg:city":"Mol",
    "sg:classifiers":[
        {
            "category":"Utilities",
            "subcategory":"Fuel Oil & Lpg",
            "type":"Services"
        }
    ],
    "sg:phone":"+32 14 31 16 51",
    "sg:postcode":"2400",
    "sg:province":"Antwerpen",
    "wof:name":"Caeyers J",
    "wof:placetype":"venue"
},
  "geometry": {"coordinates":[5.0712752342,51.1823883057],"type":"Point"}
}