{
  "type": "Feature",
  "properties": {
    "iso:country":"BE",
    "sg:address":"Rue Ways 28",
    "sg:city":"Soumagne (cerexhe-heuseux)",
    "sg:classifiers":[
        {
            "category":"Wholesale",
            "subcategory":"Scrap",
            "type":"Manufacturing & Wholesale Goods"
        }
    ],
    "sg:phone":"+32 4 387 45 86",
    "sg:postcode":"4632",
    "sg:province":"Li\u00e8ge",
    "sg:tags":[
        "metal"
    ],
    "wof:name":"Masuir Jacques Ets",
    "wof:placetype":"venue"
},
  "geometry": {"coordinates":[5.7101020813,50.6572036743],"type":"Point"}
}