{
  "type": "Feature",
  "properties": {
    "iso:country":"BE",
    "sg:address":"Rue Belvaux 93",
    "sg:city":"Li\u00e8ge 1 (grivegn\u00e9e)",
    "sg:classifiers":[
        {
            "category":"Community Center",
            "subcategory":"Youth",
            "type":"Public Place"
        }
    ],
    "sg:phone":"+32 4 342 61 42",
    "sg:postcode":"4030",
    "sg:province":"Li\u00e8ge",
    "sg:tags":[
        "club"
    ],
    "wof:name":"Soci\u00e9t\u00e9 Sp\u00e9l\u00e9ologique De Wallonie",
    "wof:placetype":"venue"
},
  "geometry": {"coordinates":[5.6000151634,50.6216468811],"type":"Point"}
}