{
  "type": "Feature",
  "properties": {
    "iso:country":"BE",
    "sg:address":"Liersebaan 90",
    "sg:city":"Zandhoven",
    "sg:orig_category":"Installation de menuiserie en bois and plastique",
    "sg:phone":"+32 3 385 90 36",
    "sg:postcode":"2240",
    "sg:province":"Antwerpen",
    "wof:name":"Polydoor",
    "wof:placetype":"venue"
},
  "geometry": {"coordinates":[4.6555709839,51.2106513977],"type":"Point"}
}