{
  "type": "Feature",
  "properties": {
    "addr:full":"Rue Jules Destr\u00c9e 7 Charleroi Hainaut 6001",
    "addr:housenumber":"7",
    "addr:postcode":"6001",
    "addr:street":"Rue Jules Destre\u0301E;Hainaut",
    "iso:country":"BE",
    "sg:address":"Rue Jules Destr\u00c9e 7",
    "sg:city":"Charleroi",
    "sg:classifiers":[
        {
            "category":"Insurance",
            "subcategory":"Life Insurance",
            "type":"Services"
        }
    ],
    "sg:phone":"+32 71 43 30 14",
    "sg:postcode":"6001",
    "sg:province":"Hainaut",
    "sg:tags":[
        "assurance"
    ],
    "wof:name":"Gobbe Albert",
    "wof:placetype":"venue"
},
  "geometry": {"coordinates":[4.4516181946,50.3986740112],"type":"Point"}
}