{
  "type": "Feature",
  "properties": {
    "iso:country":"BE",
    "sg:address":"Heideken 23",
    "sg:city":"Halle",
    "sg:orig_category":"Rev\u00eatements pour sols and murs. Peinture",
    "sg:phone":"+32 2 361 14 09",
    "sg:postcode":"1500",
    "sg:province":"Vlaams-Brabant",
    "wof:name":"Kreo-design",
    "wof:placetype":"venue"
},
  "geometry": {"coordinates":[4.2643079758,50.7235679626],"type":"Point"}
}