{
  "type": "Feature",
  "properties": {
    "addr:full":"Rue Du Sablon 167 Bastogne Luxembourg 6600",
    "addr:housenumber":"167",
    "addr:postcode":"6600",
    "addr:street":"Rue Du Sablon",
    "iso:country":"BE",
    "sg:address":"Rue Du Sablon 167",
    "sg:city":"Bastogne",
    "sg:orig_category":"Electrom\u00e9nager, t\u00e9l\u00e9visions and radios. Eclairage et \u00e9quipements du foyer. Articles de camping and d",
    "sg:phone":"+32 61 21 56 48",
    "sg:postcode":"6600",
    "sg:province":"Luxembourg",
    "wof:name":"Blokker",
    "wof:placetype":"venue"
},
  "geometry": {"coordinates":[5.7193589211,50.003993988],"type":"Point"}
}