{
  "type": "Feature",
  "properties": {
    "iso:country":"BE",
    "sg:address":"Place Des D\u00c9port\u00c9s 1",
    "sg:city":"Rochefort",
    "sg:orig_category":"Installation \u00e9lectrique r\u00e9sidentielle. Agences immobili\u00e8res. Installation de menuiserie en bois and ",
    "sg:phone":"+32 84 22 16 25",
    "sg:postcode":"5580",
    "sg:province":"Namur",
    "wof:name":"Immo-famenne",
    "wof:placetype":"venue"
},
  "geometry": {"coordinates":[5.2659201622,50.1613388062],"type":"Point"}
}