{
  "type": "Feature",
  "properties": {
    "iso:country":"BE",
    "sg:address":"Lapscheurestraat 1",
    "sg:city":"Damme",
    "sg:orig_category":"Entretien and r\u00e9parations de voitures. V\u00e9hicules automobiles",
    "sg:phone":"+32 50 50 04 22",
    "sg:postcode":"8340",
    "sg:province":"West-Vlaanderen",
    "wof:name":"Garage Delannoye",
    "wof:placetype":"venue"
},
  "geometry": {"coordinates":[3.3565011024,51.2776603699],"type":"Point"}
}