{
  "type": "Feature",
  "properties": {
    "addr:full":"Gruitroderkiezel 24 Bree Limburg 3960",
    "addr:housenumber":"24",
    "addr:postcode":"3960",
    "addr:street":"Gruitroderkiezel",
    "iso:country":"BE",
    "sg:address":"Gruitroderkiezel 24",
    "sg:city":"Bree",
    "sg:orig_category":"Entretien and r\u00e9parations de voitures",
    "sg:phone":"+32 89 46 11 92",
    "sg:postcode":"3960",
    "sg:province":"Limburg",
    "wof:name":"Garage Baens",
    "wof:placetype":"venue"
},
  "geometry": {"coordinates":[5.5931529999,51.1359176636],"type":"Point"}
}