{
  "type": "Feature",
  "properties": {
    "addr:full":"Chauss\u00c9e De Tirlemont 208 Wanze Li\u00e8ge 4520",
    "addr:housenumber":"208",
    "addr:postcode":"4520",
    "addr:street":"Chausse\u0301E De Tirlemont",
    "iso:country":"BE",
    "sg:address":"Chauss\u00c9e De Tirlemont 208",
    "sg:city":"Wanze",
    "sg:orig_category":"Woningbouw",
    "sg:phone":"+32 85 25 11 18",
    "sg:postcode":"4520",
    "sg:province":"Li\u00e8ge",
    "wof:name":"M.a.r.c.",
    "wof:placetype":"venue"
},
  "geometry": {"coordinates":[5.2215199471,50.5430488586],"type":"Point"}
}