{
  "type": "Feature",
  "properties": {
    "addr:full":"Berkenlaan 5 Diegem Vlaams-Brabant 1831",
    "addr:housenumber":"5",
    "addr:postcode":"1831",
    "addr:street":"Berkenlaan",
    "iso:country":"BE",
    "sg:address":"Berkenlaan 5",
    "sg:city":"Diegem",
    "sg:classifiers":[
        {
            "category":"Travel",
            "subcategory":"Hotels & Motels",
            "type":"Entertainment"
        }
    ],
    "sg:phone":"+32 2 725 33 80",
    "sg:postcode":"1831",
    "sg:province":"Vlaams-Brabant",
    "sg:tags":[
        "hotels",
        "business",
        "restaurant"
    ],
    "wof:name":"Express By Holiday Inn Brussels Airport Nv",
    "wof:placetype":"venue"
},
  "geometry": {"coordinates":[4.4446129799,50.8842849731],"type":"Point"}
}