{
  "type": "Feature",
  "properties": {
    "iso:country":"BE",
    "sg:address":"Rue Du Cur\u00e9 Du Ch\u00e2teau 1",
    "sg:city":"Tournai",
    "sg:classifiers":[
        {
            "category":"Health Services",
            "subcategory":"Health Practitioner",
            "type":"Services"
        }
    ],
    "sg:phone":"+32 69 21 15 12",
    "sg:postcode":"7500",
    "sg:province":"Hainaut",
    "sg:tags":[
        "physiotherapist"
    ],
    "wof:name":"Lebrun Patrick",
    "wof:placetype":"venue"
},
  "geometry": {"coordinates":[3.3900609016,50.6110801697],"type":"Point"}
}