{
  "type": "Feature",
  "properties": {
    "addr:full":"Place Bara 19 Antoing Hainaut 7640",
    "addr:housenumber":"19",
    "addr:postcode":"7640",
    "addr:street":"Place Bara",
    "iso:country":"BE",
    "sg:address":"Place Bara 19",
    "sg:city":"Antoing",
    "sg:orig_category":"Overheidsdiensten",
    "sg:phone":"+32 69 44 29 21",
    "sg:postcode":"7640",
    "sg:province":"Hainaut",
    "wof:name":"Administration Communale",
    "wof:placetype":"venue"
},
  "geometry": {"coordinates":[3.4488420486,50.5655593872],"type":"Point"}
}