{
  "type": "Feature",
  "properties": {
    "addr:full":"Boulevard Paul-henri Spaak 14 Leuze-en-hainaut Hainaut 7900",
    "addr:housenumber":"14",
    "addr:postcode":"7900",
    "addr:street":"Boulevard Paul-Henri Spaak",
    "iso:country":"BE",
    "sg:address":"Boulevard Paul-henri Spaak 14",
    "sg:city":"Leuze-en-hainaut",
    "sg:classifiers":[
        {
            "category":"Manufacturing",
            "subcategory":"Tools & Machinery",
            "type":"Manufacturing & Wholesale Goods"
        }
    ],
    "sg:phone":"+32 69 66 95 55",
    "sg:postcode":"7900",
    "sg:province":"Hainaut",
    "sg:tags":[
        "-"
    ],
    "wof:name":"Parduyns Sa",
    "wof:placetype":"venue"
},
  "geometry": {"coordinates":[3.6080179214,50.6007499695],"type":"Point"}
}