{
  "type": "Feature",
  "properties": {
    "iso:country":"BE",
    "sg:address":"Aaltersesteenweg 42",
    "sg:city":"Deinze",
    "sg:orig_category":"Animaux domestiques and accessoires",
    "sg:phone":"+32 9 386 42 90",
    "sg:postcode":"9800",
    "sg:province":"Oost-Vlaanderen",
    "wof:name":"Geert Cozijns",
    "wof:placetype":"venue"
},
  "geometry": {"coordinates":[3.5065219402,50.9908905029],"type":"Point"}
}