{
  "type": "Feature",
  "properties": {
    "addr:full":"Schanslaan 71 Borsbeek Antwerpen 2150",
    "addr:housenumber":"71",
    "addr:postcode":"2150",
    "addr:street":"Schanslaan",
    "iso:country":"BE",
    "sg:address":"Schanslaan 71",
    "sg:city":"Borsbeek",
    "sg:orig_category":"Belastingconsulenten Diverse juridische dienstverlening",
    "sg:phone":"+32 3 321 97 05",
    "sg:postcode":"2150",
    "sg:province":"Antwerpen",
    "wof:name":"Juriservice",
    "wof:placetype":"venue"
},
  "geometry": {"coordinates":[4.4932899475,51.1953659058],"type":"Point"}
}