{
  "type": "Feature",
  "properties": {
    "addr:full":"Chauss\u00c9e De Namur 24 Pietrebais Brabant Wallon 1315",
    "addr:housenumber":"24;1315",
    "addr:street":"Chausse\u0301E De Namur;Brabant Wallon",
    "iso:country":"BE",
    "sg:address":"Chauss\u00c9e De Namur 24",
    "sg:city":"Pietrebais",
    "sg:orig_category":"Verhuur cateringmateriaal and evenementuitrusting Verhuur diversen",
    "sg:phone":"+32 10 84 11 56",
    "sg:postcode":"1315",
    "sg:province":"Brabant Wallon",
    "wof:name":"Godefroid Location",
    "wof:placetype":"venue"
},
  "geometry": {"coordinates":[4.7772340775,50.7295608521],"type":"Point"}
}