{
  "type": "Feature",
  "properties": {
    "addr:full":"Rue De L'h\u00f4tel De Ville 39 La Louvi\u00e8re (haine-saint-pierre) Hainaut 7100",
    "addr:housenumber":"39",
    "addr:postcode":"7100",
    "addr:street":"Rue De L'Ho \u0302Tel De Ville",
    "iso:country":"BE",
    "sg:address":"Rue De L'h\u00f4tel De Ville 39",
    "sg:city":"La Louvi\u00e8re (haine-saint-pierre)",
    "sg:classifiers":[
        {
            "category":"Shopping",
            "subcategory":"Antiques",
            "type":"Retail Goods"
        }
    ],
    "sg:phone":"+32 64 26 23 17",
    "sg:postcode":"7100",
    "sg:province":"Hainaut",
    "wof:name":"Gallina",
    "wof:placetype":"venue"
},
  "geometry": {"coordinates":[4.1997060776,50.4601669312],"type":"Point"}
}