{
  "type": "Feature",
  "properties": {
    "iso:country":"BE",
    "sg:address":"Assesteenweg 18",
    "sg:city":"Asse (mollem)",
    "sg:classifiers":[
        {
            "category":"Home & Garden",
            "subcategory":"Garden Supply",
            "type":"Retail Goods"
        }
    ],
    "sg:phone":"+32 2 452 64 80",
    "sg:postcode":"1730",
    "sg:province":"Vlaams-Brabant",
    "wof:name":"De Ryck Frans",
    "wof:placetype":"venue"
},
  "geometry": {"coordinates":[4.1601018906,50.9172515869],"type":"Point"}
}