{
  "type": "Feature",
  "properties": {
    "addr:full":"Rue Des D\u00e9port\u00e9s 120 Verviers Li\u00e8ge 4800",
    "addr:housenumber":"120",
    "addr:postcode":"4800",
    "addr:street":"Rue Des De\u0301Porte\u0301S",
    "iso:country":"BE",
    "sg:address":"Rue Des D\u00e9port\u00e9s 120",
    "sg:city":"Verviers",
    "sg:classifiers":[
        {
            "category":"Professional",
            "subcategory":"Management & Consulting",
            "type":"Services"
        }
    ],
    "sg:phone":"+32 87 23 06 90",
    "sg:postcode":"4800",
    "sg:province":"Li\u00e8ge",
    "sg:tags":[
        "consultant"
    ],
    "wof:name":"Formac Consult Sa",
    "wof:placetype":"venue"
},
  "geometry": {"coordinates":[5.8503642082,50.5826034546],"type":"Point"}
}