{
  "type": "Feature",
  "properties": {
    "iso:country":"BE",
    "sg:address":"Oosterzonneplein 4 Box 2",
    "sg:city":"Zutendaal",
    "sg:classifiers":[
        {
            "category":"Professional",
            "subcategory":"Lawyer & Legal Services",
            "type":"Services"
        }
    ],
    "sg:phone":"+32 89 61 57 16",
    "sg:postcode":"3690",
    "sg:province":"Limburg",
    "wof:name":"Hoessels Gert",
    "wof:placetype":"venue"
},
  "geometry": {"coordinates":[5.5733819008,50.9329109192],"type":"Point"}
}