{
  "type": "Feature",
  "properties": {
    "iso:country":"BE",
    "sg:address":"Av. Commandants Borl\u00c9e 33",
    "sg:city":"Jodoigne",
    "sg:orig_category":"Verplichte sociale verzekeringen",
    "sg:phone":"+32 10 81 10 80",
    "sg:postcode":"1370",
    "sg:province":"Brabant Wallon",
    "wof:name":"Mutualit\u00c9 Socialiste",
    "wof:placetype":"venue"
},
  "geometry": {"coordinates":[4.8742752075,50.7219619751],"type":"Point"}
}