{
  "type": "Feature",
  "properties": {
    "addr:full":"Rue De L'eau Vive 39 Namur (vedrin - Daussoulx) Namur 5020",
    "addr:housenumber":"39",
    "addr:postcode":"5020",
    "addr:street":"Rue De L'Eau Vive",
    "iso:country":"BE",
    "sg:address":"Rue De L'eau Vive 39",
    "sg:city":"Namur (vedrin - Daussoulx)",
    "sg:classifiers":[
        {
            "category":"Health Services",
            "subcategory":"Doctor",
            "type":"Services"
        }
    ],
    "sg:phone":"+32 81 21 23 18",
    "sg:postcode":"5020",
    "sg:province":"Namur",
    "sg:tags":[
        "medicinephysicians",
        "surgeon"
    ],
    "wof:name":"Libon E",
    "wof:placetype":"venue"
},
  "geometry": {"coordinates":[4.8826131821,50.4898147583],"type":"Point"}
}