{
  "type": "Feature",
  "properties": {
    "iso:country":"BE",
    "sg:address":"Hubert D'ydewallestraat 50",
    "sg:city":"Beernem",
    "sg:classifiers":[
        {
            "category":"Social Services",
            "subcategory":"Child Care",
            "type":"Services"
        }
    ],
    "sg:phone":"+32 50 78 86 41",
    "sg:postcode":"8730",
    "sg:province":"West-Vlaanderen",
    "sg:tags":[
        "baby",
        "nursery",
        "day",
        "sitting"
    ],
    "wof:name":"Girafke('t)",
    "wof:placetype":"venue"
},
  "geometry": {"coordinates":[3.3222780228,51.1293563843],"type":"Point"}
}