{
  "type": "Feature",
  "properties": {
    "addr:full":"Zagerijstraat 26 Lille Antwerpen 2275",
    "addr:housenumber":"26",
    "addr:postcode":"2275",
    "addr:street":"Zagerijstraat",
    "iso:country":"BE",
    "sg:address":"Zagerijstraat 26",
    "sg:city":"Lille",
    "sg:classifiers":[
        {
            "category":"Manufacturing",
            "subcategory":"Textiles",
            "type":"Manufacturing & Wholesale Goods"
        }
    ],
    "sg:phone":"+32 14 88 03 35",
    "sg:postcode":"2275",
    "sg:province":"Antwerpen",
    "sg:tags":[
        "retail",
        "-"
    ],
    "wof:name":"Stoopen",
    "wof:placetype":"venue"
},
  "geometry": {"coordinates":[4.8248901367,51.2330513],"type":"Point"}
}