{
  "type": "Feature",
  "properties": {
    "iso:country":"BE",
    "sg:address":"Rue De Veeweyde 3",
    "sg:city":"Bruxelles (anderlecht)",
    "sg:classifiers":[
        {
            "category":"Shopping",
            "subcategory":"Gifts & Souvenirs",
            "type":"Retail Goods"
        }
    ],
    "sg:phone":"+32 2 523 63 89",
    "sg:postcode":"1070",
    "sg:province":"Bruxelles-Capitale",
    "sg:tags":[
        "postcard",
        "picture",
        "greeting",
        "card"
    ],
    "wof:name":"Id\u00e9es Cadeaux",
    "wof:placetype":"venue"
},
  "geometry": {"coordinates":[4.3068261147,50.8347511292],"type":"Point"}
}