{
  "type": "Feature",
  "properties": {
    "addr:full":"De Breyne Peelaertstraat 48 Diksmuide West-Vlaanderen 8600",
    "addr:housenumber":"48",
    "addr:postcode":"8600",
    "addr:street":"Peelaertstraat",
    "iso:country":"BE",
    "sg:address":"De Breyne Peelaertstraat 48",
    "sg:city":"Diksmuide",
    "sg:orig_category":"Non-Classified Establishments",
    "sg:phone":"+32 51 50 08 63",
    "sg:postcode":"8600",
    "sg:province":"West-Vlaanderen",
    "wof:name":"D'haene L",
    "wof:placetype":"venue"
},
  "geometry": {"coordinates":[2.8658061028,51.035572052],"type":"Point"}
}