{
  "type": "Feature",
  "properties": {
    "iso:country":"BE",
    "sg:address":"Sterrestraat 78",
    "sg:city":"Tielt",
    "sg:orig_category":"Installatie van houten of kunststof schrijnwerk",
    "sg:phone":"+32 51 63 56 81",
    "sg:postcode":"8700",
    "sg:province":"West-Vlaanderen",
    "wof:name":"Patrick De Soete",
    "wof:placetype":"venue"
},
  "geometry": {"coordinates":[3.4148190022,50.9934234619],"type":"Point"}
}