{
  "type": "Feature",
  "properties": {
    "addr:full":"Torhoutsesteenweg 383 Zedelgem West-Vlaanderen 8210",
    "addr:housenumber":"383",
    "addr:postcode":"8210",
    "addr:street":"Torhoutsesteenweg",
    "iso:country":"BE",
    "sg:address":"Torhoutsesteenweg 383",
    "sg:city":"Zedelgem",
    "sg:orig_category":"Benzinestations and brandstoffen Herstellingen and onderhoud van auto's Voertuigen",
    "sg:phone":"+32 50 27 74 94",
    "sg:postcode":"8210",
    "sg:province":"West-Vlaanderen",
    "wof:name":"Carrosserie Deketelaere",
    "wof:placetype":"venue"
},
  "geometry": {"coordinates":[3.1576468945,51.1365127563],"type":"Point"}
}