{
  "type": "Feature",
  "properties": {
    "iso:country":"BE",
    "sg:address":"Gouden-handstraat 17",
    "sg:city":"Brugge",
    "sg:classifiers":[
        {
            "category":"Shopping",
            "subcategory":"Bridal",
            "type":"Retail Goods"
        }
    ],
    "sg:phone":"+32 50 33 13 39",
    "sg:postcode":"8000",
    "sg:province":"West-Vlaanderen",
    "sg:tags":[
        "list",
        "-",
        "present",
        "wedding"
    ],
    "wof:name":"Corona Bruidswagens",
    "wof:placetype":"venue"
},
  "geometry": {"coordinates":[3.2271521091,51.2137908936],"type":"Point"}
}