{
  "type": "Feature",
  "properties": {
    "iso:country":"BE",
    "sg:address":"Rue Du March\u00c9 10",
    "sg:city":"Dour",
    "sg:orig_category":"Zalen voor culturele evenementen",
    "sg:phone":"+32 65 69 09 38",
    "sg:postcode":"7370",
    "sg:province":"Hainaut",
    "wof:name":"Th\u00c9\u00c2tre Le Rocamadour",
    "wof:placetype":"venue"
},
  "geometry": {"coordinates":[3.7800889015,50.3962554932],"type":"Point"}
}