{
  "type": "Feature",
  "properties": {
    "iso:country":"BE",
    "sg:address":"Rue Souveraine 18",
    "sg:city":"Elsene/ixelles",
    "sg:orig_category":"G\u00e9om\u00e8tres",
    "sg:phone":"+32 2 502 64 42",
    "sg:postcode":"1050",
    "sg:province":"Bruxelles-Capitale",
    "wof:name":"Vincent De Brochowski",
    "wof:placetype":"venue"
},
  "geometry": {"coordinates":[4.3653888702,50.8331489563],"type":"Point"}
}