{
  "type": "Feature",
  "properties": {
    "addr:full":"Volpestraat 1 Halle Vlaams-Brabant 1500",
    "addr:housenumber":"1",
    "addr:postcode":"1500",
    "addr:street":"Volpestraat",
    "iso:country":"BE",
    "sg:address":"Volpestraat 1",
    "sg:city":"Halle",
    "sg:orig_category":"Apotheken",
    "sg:phone":"+32 2 356 53 19",
    "sg:postcode":"1500",
    "sg:province":"Vlaams-Brabant",
    "wof:name":"Multipharma",
    "wof:placetype":"venue"
},
  "geometry": {"coordinates":[4.2362670898,50.7359542847],"type":"Point"}
}