{
  "type": "Feature",
  "properties": {
    "iso:country":"BE",
    "sg:address":"6",
    "sg:city":"Plasstraat 8980 Zonnebeke",
    "sg:orig_category":"Miscellaneous Products",
    "sg:phone":"+32 57 46 62 77",
    "sg:postcode":"6",
    "wof:name":"Tabakbedrijf Stubbe",
    "wof:placetype":"venue"
},
  "geometry": {"coordinates":[2.9971048832,50.8610877991],"type":"Point"}
}