{
  "type": "Feature",
  "properties": {
    "iso:country":"BE",
    "sg:address":"Bieshof 4",
    "sg:city":"Hoogstraten",
    "sg:orig_category":"Rundveehouders Varkenskwekers",
    "sg:phone":"+32 3 315 78 23",
    "sg:postcode":"2321",
    "sg:province":"Antwerpen",
    "wof:name":"Petrus Goetschalckx",
    "wof:placetype":"venue"
},
  "geometry": {"coordinates":[4.7292890549,51.467880249],"type":"Point"}
}