{
  "type": "Feature",
  "properties": {
    "addr:full":"Lindanusstraat 112 Dendermonde Oost-Vlaanderen 9200",
    "addr:housenumber":"112",
    "addr:postcode":"9200",
    "addr:street":"Lindanusstraat;Oost-Vlaanderen",
    "iso:country":"BE",
    "sg:address":"Lindanusstraat 112",
    "sg:city":"Dendermonde",
    "sg:classifiers":[
        {
            "category":"Education",
            "subcategory":"School",
            "type":"Public Place"
        }
    ],
    "sg:phone":"+32 53 25 82 78",
    "sg:postcode":"9200",
    "sg:province":"Oost-Vlaanderen",
    "sg:tags":[
        "-",
        "private"
    ],
    "wof:name":"Centrum Voor Basiseducatie",
    "wof:placetype":"venue"
},
  "geometry": {"coordinates":[4.1044797897,51.0275917053],"type":"Point"}
}