{
  "type": "Feature",
  "properties": {
    "addr:full":"Rue Nazarin 35 Charleroi Hainaut 6060",
    "addr:housenumber":"35",
    "addr:postcode":"6060",
    "addr:street":"Rue Nazarin;Hainaut",
    "iso:country":"BE",
    "sg:address":"Rue Nazarin 35",
    "sg:city":"Charleroi",
    "sg:orig_category":"Enseignement maternel and primaire",
    "sg:phone":"+32 71 41 67 70",
    "sg:postcode":"6060",
    "sg:province":"Hainaut",
    "wof:name":"Ecole Fond. Communale",
    "wof:placetype":"venue"
},
  "geometry": {"coordinates":[4.4880981445,50.4251937866],"type":"Point"}
}