{
  "type": "Feature",
  "properties": {
    "iso:country":"BE",
    "sg:address":"Rue De Lonette 39",
    "sg:city":"Fl\u00e9ron (retinne)",
    "sg:classifiers":[
        {
            "category":"Professional",
            "subcategory":"Management & Consulting",
            "type":"Services"
        }
    ],
    "sg:phone":"+32 4 377 65 35",
    "sg:postcode":"4621",
    "sg:province":"Li\u00e8ge",
    "sg:tags":[
        "marketing",
        "-",
        "consultant"
    ],
    "wof:name":"Fbcl",
    "wof:placetype":"venue"
},
  "geometry": {"coordinates":[5.683259964,50.6344184875],"type":"Point"}
}