{
  "type": "Feature",
  "properties": {
    "iso:country":"BE",
    "sg:address":"Sint-jorisstraat 85d",
    "sg:city":"Beernem",
    "sg:classifiers":[
        {
            "category":"Banks & Credit Unions",
            "subcategory":"Investment Brokerage",
            "type":"Services"
        }
    ],
    "sg:phone":"+32 50 79 18 79",
    "sg:postcode":"8730",
    "sg:province":"West-Vlaanderen",
    "sg:tags":[
        "printing",
        "-"
    ],
    "wof:name":"Drukkerij Harlekijn",
    "wof:placetype":"venue"
},
  "geometry": {"coordinates":[3.3459630013,51.1265983582],"type":"Point"}
}