{
  "type": "Feature",
  "properties": {
    "addr:full":"Rijvisschestraat 110 Gent Oost-Vlaanderen 9052",
    "addr:housenumber":"110",
    "addr:postcode":"9052",
    "addr:street":"Rijvisschestraat;Oost-Vlaanderen",
    "iso:country":"BE",
    "sg:address":"Rijvisschestraat 110",
    "sg:city":"Gent",
    "sg:orig_category":"Artsen and specialisten",
    "sg:phone":"+32 9 221 26 37",
    "sg:postcode":"9052",
    "sg:province":"Oost-Vlaanderen",
    "wof:name":"Ga\u00cbtan Verheecke",
    "wof:placetype":"venue"
},
  "geometry": {"coordinates":[3.7167270184,51.0002937317],"type":"Point"}
}