{
  "type": "Feature",
  "properties": {
    "addr:full":"Ossegemstraat 113 Meise Vlaams-Brabant 1861",
    "addr:housenumber":"113",
    "addr:postcode":"1861",
    "addr:street":"Ossegemstraat",
    "iso:country":"BE",
    "sg:address":"Ossegemstraat 113",
    "sg:city":"Meise",
    "sg:orig_category":"Artiesten and kunstenaars",
    "sg:phone":"+32 2 269 57 57",
    "sg:postcode":"1861",
    "sg:province":"Vlaams-Brabant",
    "wof:name":"Walter Philips",
    "wof:placetype":"venue"
},
  "geometry": {"coordinates":[4.321436882,50.9636726379],"type":"Point"}
}