{
  "type": "Feature",
  "properties": {
    "addr:full":"Beheerstraat 51 Kortrijk West-Vlaanderen 8500",
    "addr:housenumber":"51",
    "addr:postcode":"8500",
    "addr:street":"Beheerstraat",
    "iso:country":"BE",
    "sg:address":"Beheerstraat 51",
    "sg:city":"Kortrijk",
    "sg:orig_category":"V\u00e9hicules automobiles",
    "sg:phone":"+32 56 22 47 50",
    "sg:postcode":"8500",
    "sg:province":"West-Vlaanderen",
    "wof:name":"Garage Vereecke",
    "wof:placetype":"venue"
},
  "geometry": {"coordinates":[3.256896019,50.8279762268],"type":"Point"}
}