{
  "type": "Feature",
  "properties": {
    "addr:full":"Diestersteenweg 195b Nieuwerkerken Limburg 3850",
    "addr:housenumber":"195b",
    "addr:postcode":"3850",
    "addr:street":"Diestersteenweg",
    "iso:country":"BE",
    "sg:address":"Diestersteenweg 195b",
    "sg:city":"Nieuwerkerken",
    "sg:classifiers":[
        {
            "category":"Home & Garden",
            "subcategory":"Building Materials",
            "type":"Retail Goods"
        }
    ],
    "sg:phone":"+32 11 68 52 64",
    "sg:postcode":"3850",
    "sg:province":"Limburg",
    "sg:tags":[
        "article",
        "-",
        "do-it-yourself"
    ],
    "wof:name":"Hermans M",
    "wof:placetype":"venue"
},
  "geometry": {"coordinates":[5.1868100166,50.8748397827],"type":"Point"}
}