{
  "type": "Feature",
  "properties": {
    "iso:country":"BE",
    "sg:address":"Grand'route 67",
    "sg:city":"Mont-saint-guibert (corbais)",
    "sg:classifiers":[
        {
            "category":"Shopping",
            "subcategory":"Florist",
            "type":"Retail Goods"
        }
    ],
    "sg:phone":"+32 10 65 75 97",
    "sg:postcode":"1435",
    "sg:province":"Brabant Wallon",
    "wof:name":"Guibertine Fleurs (la)",
    "wof:placetype":"venue"
},
  "geometry": {"coordinates":[4.6107521057,50.6339874268],"type":"Point"}
}