{
  "type": "Feature",
  "properties": {
    "addr:full":"Rue Vaudr\u00e9e 161 Li\u00e8ge 1 (angleur) Li\u00e8ge 4031",
    "addr:housenumber":"161;1",
    "addr:postcode":"4031",
    "addr:street":"Rue Vaudre\u0301E",
    "iso:country":"BE",
    "sg:address":"Rue Vaudr\u00e9e 161",
    "sg:city":"Li\u00e8ge 1 (angleur)",
    "sg:classifiers":[
        {
            "category":"Personal",
            "subcategory":"Barber",
            "type":"Services"
        }
    ],
    "sg:phone":"+32 4 367 41 98",
    "sg:postcode":"4031",
    "sg:province":"Li\u00e8ge",
    "sg:tags":[
        "gentleman",
        "salon",
        "-",
        "hairdressing"
    ],
    "wof:name":"Becker G",
    "wof:placetype":"venue"
},
  "geometry": {"coordinates":[5.5911431313,50.6131782532],"type":"Point"}
}