{
  "type": "Feature",
  "properties": {
    "iso:country":"BE",
    "sg:address":"Uilenstraat 62",
    "sg:city":"Sint-niklaas",
    "sg:orig_category":"Jardinage",
    "sg:phone":"+32 3 777 26 09",
    "sg:postcode":"9100",
    "sg:province":"Oost-Vlaanderen",
    "wof:name":"De Vleeschauwer M.",
    "wof:placetype":"venue"
},
  "geometry": {"coordinates":[4.1681609154,51.181930542],"type":"Point"}
}