{
  "type": "Feature",
  "properties": {
    "iso:country":"BE",
    "sg:address":"Kemmelberglaan 7b13",
    "sg:city":"Vorst/forest",
    "sg:classifiers":[
        {
            "category":"Professional",
            "subcategory":"Accounting & Tax Preparation",
            "type":"Services"
        }
    ],
    "sg:phone":"+32 2 539 28 34",
    "sg:postcode":"1190",
    "sg:province":"Bruxelles-Capitale",
    "sg:tags":[
        "accountant"
    ],
    "wof:name":"Andr\u00c9 De Backer",
    "wof:placetype":"venue"
},
  "geometry": {"coordinates":[4.3411989212,50.8220405579],"type":"Point"}
}