{
  "type": "Feature",
  "properties": {
    "iso:country":"BE",
    "sg:address":"Nieuwstraat 72",
    "sg:city":"Asse",
    "sg:orig_category":"Enseignement maternel and primaire",
    "sg:phone":"+32 2 452 70 32",
    "sg:postcode":"1730",
    "sg:province":"Vlaams-Brabant",
    "wof:name":"Vrije Lagere School",
    "wof:placetype":"venue"
},
  "geometry": {"coordinates":[4.1939368248,50.910282135],"type":"Point"}
}