{
  "type": "Feature",
  "properties": {
    "iso:country":"BE",
    "sg:address":"Tuinstraat 81",
    "sg:city":"Melle",
    "sg:classifiers":[
        {
            "category":"Home & Garden",
            "subcategory":"Building Materials",
            "type":"Retail Goods"
        }
    ],
    "sg:phone":"+32 9 228 27 02",
    "sg:postcode":"9090",
    "sg:province":"Oost-Vlaanderen",
    "sg:tags":[
        "window"
    ],
    "wof:name":"Thierry Wiels",
    "wof:placetype":"venue"
},
  "geometry": {"coordinates":[3.7726180553,51.0181427002],"type":"Point"}
}