{
  "type": "Feature",
  "properties": {
    "iso:country":"BE",
    "sg:address":"Abdijstraat 127",
    "sg:city":"Antwerpen",
    "sg:classifiers":[
        {
            "category":"Wholesale",
            "subcategory":"Sporting Goods",
            "type":"Manufacturing & Wholesale Goods"
        }
    ],
    "sg:phone":"+32 3 237 60 89",
    "sg:postcode":"2020",
    "sg:province":"Antwerpen",
    "sg:tags":[
        "sport-",
        "kampeermateriaal"
    ],
    "wof:name":"General Sport",
    "wof:placetype":"venue"
},
  "geometry": {"coordinates":[4.3830227852,51.1884231567],"type":"Point"}
}