{
  "type": "Feature",
  "properties": {
    "iso:country":"BE",
    "sg:address":"Adegemse Kerkstraat 22",
    "sg:city":"Maldegem",
    "sg:orig_category":"Kapsalons",
    "sg:phone":"+32 50 71 50 76",
    "sg:postcode":"9991",
    "sg:province":"Oost-Vlaanderen",
    "wof:name":"Coiffure Greta",
    "wof:placetype":"venue"
},
  "geometry": {"coordinates":[3.4889318943,51.2042655945],"type":"Point"}
}