{
  "type": "Feature",
  "properties": {
    "iso:country":"BE",
    "sg:address":"Sarpestraat 14",
    "sg:city":"Moeskroen/mouscron",
    "sg:classifiers":[
        {
            "category":"Insurance",
            "subcategory":"Insurance Agent",
            "type":"Services"
        }
    ],
    "sg:phone":"+32 56 48 60 70",
    "sg:postcode":"7711",
    "sg:province":"Hainaut",
    "sg:tags":[
        "verzekeringsmakelaars",
        "expert"
    ],
    "wof:name":"Marquende",
    "wof:placetype":"venue"
},
  "geometry": {"coordinates":[3.2929000854,50.7344207764],"type":"Point"}
}