{
  "type": "Feature",
  "properties": {
    "addr:full":"Felix Beernaertsplein 65 Wetteren Oost-Vlaanderen 9230",
    "addr:housenumber":"65",
    "addr:postcode":"9230",
    "iso:country":"BE",
    "sg:address":"Felix Beernaertsplein 65",
    "sg:city":"Wetteren",
    "sg:orig_category":"S\u00e9curit\u00e9 sociale",
    "sg:phone":"+32 9 369 02 32",
    "sg:postcode":"9230",
    "sg:province":"Oost-Vlaanderen",
    "wof:name":"Bond Moyson",
    "wof:placetype":"venue"
},
  "geometry": {"coordinates":[3.8801670074,51.0033988953],"type":"Point"}
}