{
  "type": "Feature",
  "properties": {
    "iso:country":"BE",
    "sg:address":"Keiberg 12a",
    "sg:city":"Lede",
    "sg:classifiers":[
        {
            "category":"Personal",
            "subcategory":"Beauty Salon",
            "type":"Services"
        }
    ],
    "sg:phone":"+32 53 80 36 88",
    "sg:postcode":"9340",
    "sg:province":"Oost-Vlaanderen",
    "sg:tags":[
        "lady",
        "-",
        "hairdressing"
    ],
    "wof:name":"Marnix",
    "wof:placetype":"venue"
},
  "geometry": {"coordinates":[3.9840509892,50.9571228027],"type":"Point"}
}