{
  "type": "Feature",
  "properties": {
    "addr:full":"Chauss\u00c9e De Wavre 154 Elsene/ixelles Bruxelles-Capitale 1050",
    "addr:housenumber":"154",
    "addr:postcode":"1050",
    "addr:street":"Chausse\u0301E De Wavre",
    "iso:country":"BE",
    "sg:address":"Chauss\u00c9e De Wavre 154",
    "sg:city":"Elsene/ixelles",
    "sg:orig_category":"Entretien and r\u00e9parations de voitures. R\u00e9cup\u00e9ration de mati\u00e8res m\u00e9talliques recyclables and d\u00e9moliss",
    "sg:phone":"+32 2 511 22 73",
    "sg:postcode":"1050",
    "sg:province":"Bruxelles-Capitale",
    "wof:name":"Ramon Cars",
    "wof:placetype":"venue"
},
  "geometry": {"coordinates":[4.3701839447,50.8357391357],"type":"Point"}
}