{
  "type": "Feature",
  "properties": {
    "iso:country":"BE",
    "sg:address":"Rodesteenstraat 2",
    "sg:city":"Houthulst",
    "sg:orig_category":"Epiceries",
    "sg:phone":"+32 51 54 45 71",
    "sg:postcode":"8650",
    "sg:province":"West-Vlaanderen",
    "wof:name":"Christiane Gheeraert",
    "wof:placetype":"venue"
},
  "geometry": {"coordinates":[2.9509439468,50.9778862],"type":"Point"}
}