{
  "type": "Feature",
  "properties": {
    "addr:full":"Oude Reetsebaan 89 Boom Antwerpen 2850",
    "addr:housenumber":"89",
    "addr:postcode":"2850",
    "addr:street":"Oude Reetsebaan",
    "iso:country":"BE",
    "sg:address":"Oude Reetsebaan 89",
    "sg:city":"Boom",
    "sg:orig_category":"GROENTEN AND FRUIT Rundveehouders",
    "sg:phone":"+32 3 888 41 35",
    "sg:postcode":"2850",
    "sg:province":"Antwerpen",
    "wof:name":"Alfons Verbruggen",
    "wof:placetype":"venue"
},
  "geometry": {"coordinates":[4.3856921196,51.1010093689],"type":"Point"}
}