{
  "type": "Feature",
  "properties": {
    "addr:full":"De Merodestraat 45 Herenthout Antwerpen 2270",
    "addr:housenumber":"45",
    "addr:postcode":"2270",
    "addr:street":"De Merodestraat",
    "iso:country":"BE",
    "sg:address":"De Merodestraat 45",
    "sg:city":"Herenthout",
    "sg:orig_category":"Sportclubs Sportterreinen and installaties behalve sportcentra",
    "sg:phone":"+32 14 51 32 01",
    "sg:postcode":"2270",
    "sg:province":"Antwerpen",
    "wof:name":"K.f.c. Herenthout",
    "wof:placetype":"venue"
},
  "geometry": {"coordinates":[4.7418379784,51.1378898621],"type":"Point"}
}