{
  "type": "Feature",
  "properties": {
    "addr:full":"Rue Chantraine 38 Fleron Li\u00e8ge 4620",
    "addr:housenumber":"38",
    "addr:postcode":"4620",
    "addr:street":"Rue Chantraine",
    "iso:country":"BE",
    "sg:address":"Rue Chantraine 38",
    "sg:city":"Fleron",
    "sg:orig_category":"Brood, gebak and snoepgoed",
    "sg:phone":"+32 4 358 25 99",
    "sg:postcode":"4620",
    "sg:province":"Li\u00e8ge",
    "wof:name":"P\u00c2tisserie Schonmacker",
    "wof:placetype":"venue"
},
  "geometry": {"coordinates":[5.6751599312,50.6116485596],"type":"Point"}
}