{
  "type": "Feature",
  "properties": {
    "addr:full":"Dellestraat 25 Holsbeek Vlaams-Brabant 3220",
    "addr:housenumber":"25",
    "addr:postcode":"3220",
    "addr:street":"Dellestraat",
    "iso:country":"BE",
    "sg:address":"Dellestraat 25",
    "sg:city":"Holsbeek",
    "sg:orig_category":"Persagentschappen",
    "sg:phone":"+32 16 44 80 42",
    "sg:postcode":"3220",
    "sg:province":"Vlaams-Brabant",
    "wof:name":"Anna Mulders",
    "wof:placetype":"venue"
},
  "geometry": {"coordinates":[4.7301430702,50.9095916748],"type":"Point"}
}