{
  "type": "Feature",
  "properties": {
    "iso:country":"BE",
    "sg:address":"Place Alphonse Bosch 47",
    "sg:city":"Wavre",
    "sg:classifiers":[
        {
            "category":"Travel",
            "subcategory":"Travel Agent",
            "type":"Entertainment"
        }
    ],
    "sg:phone":"+32 10 24 33 85",
    "sg:postcode":"1300",
    "sg:province":"Brabant Wallon",
    "sg:tags":[
        "agency"
    ],
    "wof:name":"Scolaire-evasion",
    "wof:placetype":"venue"
},
  "geometry": {"coordinates":[4.6105971336,50.7144012451],"type":"Point"}
}