{
  "type": "Feature",
  "properties": {
    "iso:country":"BE",
    "sg:address":"Rue De Qui\u00c9vrain 16",
    "sg:city":"Boussu",
    "sg:classifiers":[
        {
            "category":"Fast Food",
            "type":"Food & Drink"
        }
    ],
    "sg:phone":"+32 65 78 24 99",
    "sg:postcode":"7300",
    "sg:province":"Hainaut",
    "sg:tags":[
        "meeneem",
        "restaurant"
    ],
    "wof:name":"Friterie Athena",
    "wof:placetype":"venue"
},
  "geometry": {"coordinates":[3.7920510769,50.4293365479],"type":"Point"}
}