{
  "type": "Feature",
  "properties": {
    "iso:country":"BE",
    "sg:address":"Steenweg Op Blaasveld 67a",
    "sg:city":"Mechelen (heffen)",
    "sg:classifiers":[
        {
            "category":"Farming",
            "subcategory":"Crops",
            "type":"Manufacturing & Wholesale Goods"
        }
    ],
    "sg:phone":"+32 3 886 39 85",
    "sg:postcode":"2801",
    "sg:province":"Antwerpen",
    "sg:tags":[
        "vegetable",
        "fruit",
        "-",
        "grower"
    ],
    "wof:name":"Candries F",
    "wof:placetype":"venue"
},
  "geometry": {"coordinates":[4.4068169594,51.0470504761],"type":"Point"}
}