{
  "type": "Feature",
  "properties": {
    "addr:full":"Elzestraat 30 Beveren (beveren-waas) Oost-Vlaanderen 9120",
    "addr:housenumber":"30",
    "addr:postcode":"9120",
    "addr:street":"Elzestraat;Oost-Vlaanderen",
    "iso:country":"BE",
    "sg:address":"Elzestraat 30",
    "sg:city":"Beveren (beveren-waas)",
    "sg:classifiers":[
        {
            "category":"Banks & Credit Unions",
            "subcategory":"Investment Brokerage",
            "type":"Services"
        }
    ],
    "sg:phone":"+32 3 775 70 31",
    "sg:postcode":"9120",
    "sg:province":"Oost-Vlaanderen",
    "sg:tags":[
        "wreath",
        "mourning"
    ],
    "wof:name":"Boudein E",
    "wof:placetype":"venue"
},
  "geometry": {"coordinates":[4.2289729118,51.2208938599],"type":"Point"}
}