{
  "type": "Feature",
  "properties": {
    "iso:country":"BE",
    "sg:address":"Veldstraat 27b",
    "sg:city":"Brecht",
    "sg:classifiers":[
        {
            "category":"Professional",
            "subcategory":"Engineering",
            "type":"Services"
        }
    ],
    "sg:phone":"+32 3 313 77 80",
    "sg:postcode":"2960",
    "sg:province":"Antwerpen",
    "sg:tags":[
        "-"
    ],
    "wof:name":"Phs Consulting & Proto Bvba",
    "wof:placetype":"venue"
},
  "geometry": {"coordinates":[4.6413211823,51.3546295166],"type":"Point"}
}