{
  "type": "Feature",
  "properties": {
    "addr:full":"Eksterstraat 59 Putte Antwerpen 2580",
    "addr:housenumber":"59",
    "addr:postcode":"2580",
    "addr:street":"Eksterstraat",
    "iso:country":"BE",
    "sg:address":"Eksterstraat 59",
    "sg:city":"Putte",
    "sg:orig_category":"Bouwmaterialen Gh Elektrische installaties voor woningen Procesbesturingssystemen Fab",
    "sg:phone":"+32 15 76 07 03",
    "sg:postcode":"2580",
    "sg:province":"Antwerpen",
    "wof:name":"A-maintenance",
    "wof:placetype":"venue"
},
  "geometry": {"coordinates":[4.6401982307,51.047794342],"type":"Point"}
}