{
  "type": "Feature",
  "properties": {
    "addr:full":"Zomerweg 16 Jabbeke West-Vlaanderen 8490",
    "addr:housenumber":"16",
    "addr:postcode":"8490",
    "addr:street":"Zomerweg",
    "iso:country":"BE",
    "sg:address":"Zomerweg 16",
    "sg:city":"Jabbeke",
    "sg:classifiers":[
        {
            "category":"Travel",
            "subcategory":"Resort",
            "type":"Entertainment"
        }
    ],
    "sg:phone":"+32 50 81 26 85",
    "sg:postcode":"8490",
    "sg:province":"West-Vlaanderen",
    "sg:tags":[
        "rental",
        "accomodation",
        "holiday",
        "-"
    ],
    "wof:name":"De Twee Eiken Hoeve",
    "wof:placetype":"venue"
},
  "geometry": {"coordinates":[3.0973479748,51.1702308655],"type":"Point"}
}