{
  "type": "Feature",
  "properties": {
    "addr:full":"Rue De Vis\u00c9 178 Vise Li\u00e8ge 4602",
    "addr:housenumber":"178",
    "addr:postcode":"vise;4602",
    "addr:street":"Rue De Vise\u0301",
    "iso:country":"BE",
    "sg:address":"Rue De Vis\u00c9 178",
    "sg:city":"Vise",
    "sg:orig_category":"Boucheries",
    "sg:phone":"+32 4 362 67 47",
    "sg:postcode":"4602",
    "sg:province":"Li\u00e8ge",
    "wof:name":"Didier Dobbelstein",
    "wof:placetype":"venue"
},
  "geometry": {"coordinates":[5.6714878082,50.6851921082],"type":"Point"}
}