{
  "type": "Feature",
  "properties": {
    "addr:full":"Avenue De L'europe 68 Ans Li\u00e8ge 4430",
    "addr:housenumber":"68",
    "addr:postcode":"4430",
    "addr:street":"Avenue De L'Europe",
    "iso:country":"BE",
    "sg:address":"Avenue De L'europe 68",
    "sg:city":"Ans",
    "sg:orig_category":"M\u00e9decins and sp\u00e9cialistes",
    "sg:phone":"+32 4 246 59 28",
    "sg:postcode":"4430",
    "sg:province":"Li\u00e8ge",
    "wof:name":"Ren\u00c9 Peuteman",
    "wof:placetype":"venue"
},
  "geometry": {"coordinates":[5.5236420631,50.6649513245],"type":"Point"}
}