{
  "type": "Feature",
  "properties": {
    "addr:full":"Chauss\u00c9e De Gilly 308 Charleroi Hainaut 6043",
    "addr:housenumber":"308",
    "addr:postcode":"6043",
    "addr:street":"Chausse\u0301E De Gilly;Hainaut",
    "iso:country":"BE",
    "sg:address":"Chauss\u00c9e De Gilly 308",
    "sg:city":"Charleroi",
    "sg:orig_category":"Chemicali\u00ebn Gh",
    "sg:phone":"+32 71 34 61 39",
    "sg:postcode":"6043",
    "sg:province":"Hainaut",
    "wof:name":"Copradis",
    "wof:placetype":"venue"
},
  "geometry": {"coordinates":[4.4839549065,50.4479637146],"type":"Point"}
}