{
  "type": "Feature",
  "properties": {
    "addr:full":"Oudstrijderslaan 38 Merelbeke Oost-Vlaanderen 9820",
    "addr:housenumber":"38",
    "addr:postcode":"9820",
    "addr:street":"Oudstrijderslaan",
    "iso:country":"BE",
    "sg:address":"Oudstrijderslaan 38",
    "sg:city":"Merelbeke",
    "sg:classifiers":[
        {
            "category":"Social Services",
            "subcategory":"Child Care",
            "type":"Services"
        }
    ],
    "sg:phone":"+32 9 211 02 81",
    "sg:postcode":"9820",
    "sg:province":"Oost-Vlaanderen",
    "sg:tags":[
        "baby",
        "nursery",
        "day",
        "sitting"
    ],
    "wof:name":"Vlerkopvang (de)",
    "wof:placetype":"venue"
},
  "geometry": {"coordinates":[3.7525789738,50.9999961853],"type":"Point"}
}