{
  "type": "Feature",
  "properties": {
    "iso:country":"BE",
    "sg:address":"Rue De La Sambre 5",
    "sg:city":"Arlon",
    "sg:classifiers":[
        {
            "category":"Arena",
            "subcategory":"Sports Club",
            "type":"Entertainment"
        }
    ],
    "sg:phone":"+32 63 23 24 70",
    "sg:postcode":"6700",
    "sg:province":"Luxembourg",
    "sg:tags":[
        "de"
    ],
    "wof:name":"J.c. Stockem",
    "wof:placetype":"venue"
},
  "geometry": {"coordinates":[5.8158888817,49.6737213135],"type":"Point"}
}