{
  "type": "Feature",
  "properties": {
    "iso:country":"BE",
    "sg:address":"Rue Du Fond Des Mays 18",
    "sg:city":"Wavre",
    "sg:orig_category":"Plomberie, chauffage and installations sanitaires. Air conditionn\u00e9 and ventilation",
    "sg:phone":"+32 10 22 72 08",
    "sg:postcode":"1300",
    "sg:province":"Brabant Wallon",
    "wof:name":"Marc Toubeau",
    "wof:placetype":"venue"
},
  "geometry": {"coordinates":[4.6132969856,50.7093315125],"type":"Point"}
}