{
  "type": "Feature",
  "properties": {
    "iso:country":"BE",
    "sg:address":"Daillylaan 25",
    "sg:city":"Schaarbeek/schaerbeek",
    "sg:orig_category":"Boekhandels Kantoormateriaal Krantenwinkels Rookartikelen",
    "sg:phone":"+32 2 215 30 90",
    "sg:postcode":"1030",
    "sg:province":"Bruxelles-Capitale",
    "wof:name":"Librairie Dailly",
    "wof:placetype":"venue"
},
  "geometry": {"coordinates":[4.3810181618,50.8580703735],"type":"Point"}
}