{
  "type": "Feature",
  "properties": {
    "iso:country":"BE",
    "sg:address":"Schoonbroek 31",
    "sg:city":"Antwerpen",
    "sg:classifiers":[
        {
            "category":"Professional",
            "subcategory":"Computer Services",
            "type":"Services"
        }
    ],
    "sg:phone":"+32 3 542 65 18",
    "sg:postcode":"2030",
    "sg:province":"Antwerpen",
    "sg:tags":[
        "repair",
        "processing",
        "-",
        "maintenance",
        "data"
    ],
    "wof:name":"P C Consult",
    "wof:placetype":"venue"
},
  "geometry": {"coordinates":[4.4117641449,51.2827606201],"type":"Point"}
}