{
  "type": "Feature",
  "properties": {
    "iso:country":"BE",
    "sg:address":"Koningin Astridlaan 19",
    "sg:city":"Maldegem",
    "sg:classifiers":[
        {
            "category":"Travel",
            "subcategory":"Hotels & Motels",
            "type":"Entertainment"
        }
    ],
    "sg:phone":"+32 50 71 45 45",
    "sg:postcode":"9990",
    "sg:province":"Oost-Vlaanderen",
    "wof:name":"De Warande",
    "wof:placetype":"venue"
},
  "geometry": {"coordinates":[3.444464922,51.2039451599],"type":"Point"}
}