{
  "type": "Feature",
  "properties": {
    "iso:country":"BE",
    "sg:address":"Rue De Waroux 38",
    "sg:city":"Li\u00e8ge 1",
    "sg:classifiers":[
        {
            "category":"Arts & Performance",
            "subcategory":"Music",
            "type":"Entertainment"
        }
    ],
    "sg:phone":"+32 4 226 12 04",
    "sg:postcode":"4000",
    "sg:province":"Li\u00e8ge",
    "sg:tags":[
        "freelance",
        "musician"
    ],
    "wof:name":"Savio S",
    "wof:placetype":"venue"
},
  "geometry": {"coordinates":[5.5561628342,50.6440238953],"type":"Point"}
}