{
  "type": "Feature",
  "properties": {
    "iso:country":"BE",
    "sg:address":"Onder-den-toren 8",
    "sg:city":"Mechelen",
    "sg:orig_category":"Herstelling and restauratie van meubelen Verlichting and huishoudartikelen",
    "sg:phone":"+32 15 20 45 92",
    "sg:postcode":"2800",
    "sg:province":"Antwerpen",
    "wof:name":"Winnepenninckx",
    "wof:placetype":"venue"
},
  "geometry": {"coordinates":[4.4779820442,51.0285720825],"type":"Point"}
}