{
  "type": "Feature",
  "properties": {
    "addr:full":"Gijverinkhovestraat 2 Alveringem West-Vlaanderen 8691",
    "addr:housenumber":"2",
    "addr:postcode":"8691",
    "addr:street":"Gijverinkhovestraat",
    "iso:country":"BE",
    "sg:address":"Gijverinkhovestraat 2",
    "sg:city":"Alveringem",
    "sg:orig_category":"Eleveurs and marchands de porcs",
    "sg:phone":"+32 58 29 91 52",
    "sg:postcode":"8691",
    "sg:province":"West-Vlaanderen",
    "wof:name":"Pierre Brutsaert",
    "wof:placetype":"venue"
},
  "geometry": {"coordinates":[2.6672968864,50.9672050476],"type":"Point"}
}