{
  "type": "Feature",
  "properties": {
    "addr:full":"Rue De Mons 46 Tubize Brabant Wallon 1480",
    "addr:housenumber":"46",
    "addr:postcode":"1480",
    "addr:street":"Rue De Mons;Wallon",
    "iso:country":"BE",
    "sg:address":"Rue De Mons 46",
    "sg:city":"Tubize",
    "sg:orig_category":"Textiles. V\u00eatements",
    "sg:phone":"+32 2 355 94 08",
    "sg:postcode":"1480",
    "sg:province":"Brabant Wallon",
    "wof:name":"Pingouin",
    "wof:placetype":"venue"
},
  "geometry": {"coordinates":[4.2040557861,50.6917419434],"type":"Point"}
}