{
  "type": "Feature",
  "properties": {
    "iso:country":"BE",
    "sg:address":"Rue Bois-du-mont 2",
    "sg:city":"Somme-leuze",
    "sg:orig_category":"Woningbouw",
    "sg:phone":"+32 86 34 53 10",
    "sg:postcode":"5377",
    "sg:province":"Namur",
    "wof:name":"E. Gianaroli",
    "wof:placetype":"venue"
},
  "geometry": {"coordinates":[5.2575287819,50.2893867493],"type":"Point"}
}