{
  "type": "Feature",
  "properties": {
    "iso:country":"BE",
    "sg:address":"Rue Estafflers 15",
    "sg:city":"Tournai",
    "sg:orig_category":"Rev\u00eatements pour sols and murs. Peinture",
    "sg:phone":"+32 69 35 10 02",
    "sg:postcode":"7520",
    "sg:province":"Hainaut",
    "wof:name":"Mario Djerdi",
    "wof:placetype":"venue"
},
  "geometry": {"coordinates":[3.2669320107,50.64320755],"type":"Point"}
}