{
  "type": "Feature",
  "properties": {
    "addr:full":"Rue Lebeau 3 Li\u00e8ge Li\u00e8ge 4000",
    "addr:housenumber":"3",
    "addr:postcode":"4000",
    "addr:street":"Rue Lebeau",
    "iso:country":"BE",
    "sg:address":"Rue Lebeau 3",
    "sg:city":"Li\u00e8ge",
    "sg:classifiers":[
        {
            "category":"Banks & Credit Unions",
            "subcategory":"Bank",
            "type":"Services"
        }
    ],
    "sg:postcode":"4000",
    "sg:province":"Li\u00e8ge",
    "wof:name":"Gewerbepark Augsburg Gmbh",
    "wof:placetype":"venue"
},
  "geometry": {"coordinates":[4.4686098099,51.4676513672],"type":"Point"}
}