{
  "type": "Feature",
  "properties": {
    "iso:country":"BE",
    "sg:address":"Rue Pierre-joseph Dum\u00c9nil 1",
    "sg:city":"Mons",
    "sg:orig_category":"Agences de voyages",
    "sg:phone":"+32 65 34 78 83",
    "sg:postcode":"7000",
    "sg:province":"Hainaut",
    "wof:name":"Cap Evasion",
    "wof:placetype":"venue"
},
  "geometry": {"coordinates":[3.9558980465,50.4596252441],"type":"Point"}
}