{
  "type": "Feature",
  "properties": {
    "addr:full":"Avenue Jules Destr\u00e9e 3 Charleroi (monceau-sur-sambre) Hainaut 6031",
    "addr:housenumber":"3",
    "addr:postcode":"6031",
    "addr:street":"Avenue Jules Destre\u0301E",
    "iso:country":"BE",
    "sg:address":"Avenue Jules Destr\u00e9e 3",
    "sg:city":"Charleroi (monceau-sur-sambre)",
    "sg:classifiers":[
        {
            "category":"Education",
            "subcategory":"School",
            "type":"Public Place"
        }
    ],
    "sg:phone":"+32 71 31 47 69",
    "sg:postcode":"6031",
    "sg:province":"Hainaut",
    "sg:tags":[
        "secondary"
    ],
    "wof:name":"Inst Sainte-marie",
    "wof:placetype":"venue"
},
  "geometry": {"coordinates":[4.4509840012,50.418510437],"type":"Point"}
}