{
  "type": "Feature",
  "properties": {
    "addr:full":"Leopoldlaan 17 Ninove Oost-Vlaanderen 9400",
    "addr:housenumber":"17",
    "addr:postcode":"9400",
    "addr:street":"Leopoldlaan",
    "iso:country":"BE",
    "sg:address":"Leopoldlaan 17",
    "sg:city":"Ninove",
    "sg:orig_category":"Avocats and conseillers juridiques",
    "sg:phone":"+32 54 33 53 50",
    "sg:postcode":"9400",
    "sg:province":"Oost-Vlaanderen",
    "wof:name":"Nele Meersman",
    "wof:placetype":"venue"
},
  "geometry": {"coordinates":[4.0223078728,50.8268814087],"type":"Point"}
}