{
  "type": "Feature",
  "properties": {
    "iso:country":"BE",
    "sg:address":"Berkenlaan 85",
    "sg:city":"Ranst",
    "sg:orig_category":"Artsen and specialisten",
    "sg:phone":"+32 3 485 60 33",
    "sg:postcode":"2520",
    "sg:province":"Antwerpen",
    "wof:name":"Christine Van Winghem",
    "wof:placetype":"venue"
},
  "geometry": {"coordinates":[4.5537381172,51.1928367615],"type":"Point"}
}