{
  "type": "Feature",
  "properties": {
    "iso:country":"BE",
    "sg:address":"Beversesteenweg 417",
    "sg:city":"Roeselare",
    "sg:orig_category":"Non-Classified Establishments",
    "sg:phone":"+32 51 24 49 59",
    "sg:postcode":"8800",
    "sg:province":"West-Vlaanderen",
    "wof:name":"Prestige",
    "wof:placetype":"venue"
},
  "geometry": {"coordinates":[3.1597049236,50.9739112854],"type":"Point"}
}