{
  "type": "Feature",
  "properties": {
    "iso:country":"BE",
    "sg:address":"Rue Jean-charles De Hugo 109",
    "sg:city":"Tintigny (bellefontaine)",
    "sg:classifiers":[
        {
            "category":"Manufacturing",
            "subcategory":"Furniture",
            "type":"Manufacturing & Wholesale Goods"
        }
    ],
    "sg:phone":"+32 63 44 48 75",
    "sg:postcode":"6730",
    "sg:province":"Luxembourg",
    "sg:tags":[
        "made",
        "-",
        "custom"
    ],
    "wof:name":"Gardien M",
    "wof:placetype":"venue"
},
  "geometry": {"coordinates":[5.496462822,49.663356781],"type":"Point"}
}