{
  "type": "Feature",
  "properties": {
    "iso:country":"BE",
    "sg:address":"Avenue De La Gare 12",
    "sg:city":"Habay (habay-la-neuve)",
    "sg:classifiers":[
        {
            "category":"Real Estate",
            "subcategory":"Architect",
            "type":"Services"
        }
    ],
    "sg:phone":"+32 63 42 35 32",
    "sg:postcode":"6720",
    "sg:province":"Luxembourg",
    "wof:name":"Thiry Jean",
    "wof:placetype":"venue"
},
  "geometry": {"coordinates":[5.6468100548,49.7278633118],"type":"Point"}
}