{
  "type": "Feature",
  "properties": {
    "iso:country":"BE",
    "sg:address":"Hoogstraat 37",
    "sg:city":"Lede",
    "sg:classifiers":[
        {
            "category":"Parking",
            "subcategory":"Bicycle",
            "type":"Transportation"
        }
    ],
    "sg:phone":"+32 53 80 14 52",
    "sg:postcode":"9340",
    "sg:province":"Oost-Vlaanderen",
    "sg:tags":[
        "chiropodist"
    ],
    "wof:name":"De Lathauwer M",
    "wof:placetype":"venue"
},
  "geometry": {"coordinates":[3.9769740105,50.9628410339],"type":"Point"}
}