{
  "type": "Feature",
  "properties": {
    "addr:full":"Moerstraat 24 Deinze Oost-Vlaanderen 9800",
    "addr:housenumber":"24",
    "addr:postcode":"9800",
    "addr:street":"Moerstraat",
    "iso:country":"BE",
    "sg:address":"Moerstraat 24",
    "sg:city":"Deinze",
    "sg:orig_category":"Eleveurs and marchands de porcs",
    "sg:phone":"+32 9 371 64 31",
    "sg:postcode":"9800",
    "sg:province":"Oost-Vlaanderen",
    "wof:name":"Roger De Baere",
    "wof:placetype":"venue"
},
  "geometry": {"coordinates":[3.5764079094,51.0252304077],"type":"Point"}
}