{
  "type": "Feature",
  "properties": {
    "iso:country":"BE",
    "sg:address":"Ninoofsesteenweg 71",
    "sg:city":"Halle",
    "sg:classifiers":[
        {
            "category":"Cafe",
            "type":"Food & Drink"
        }
    ],
    "sg:phone":"+32 2 360 14 20",
    "sg:postcode":"1500",
    "sg:province":"Vlaams-Brabant",
    "sg:tags":[
        "snack-bars"
    ],
    "wof:name":"Kannibal",
    "wof:placetype":"venue"
},
  "geometry": {"coordinates":[4.2334828377,50.7381858826],"type":"Point"}
}