{
  "type": "Feature",
  "properties": {
    "iso:country":"BE",
    "sg:address":"Neerstraat 38",
    "sg:city":"Mechelen (muizen)",
    "sg:orig_category":"Non-Classified Establishments",
    "sg:phone":"+32 15 43 08 43",
    "sg:postcode":"2812",
    "sg:province":"Antwerpen",
    "wof:name":"Eureka Bvba",
    "wof:placetype":"venue"
},
  "geometry": {"coordinates":[4.5212569237,51.011302948],"type":"Point"}
}