{
  "type": "Feature",
  "properties": {
    "addr:full":"Turnhoutsebaan 318 Wijnegem Antwerpen 2110",
    "addr:housenumber":"318",
    "addr:postcode":"2110",
    "addr:street":"Turnhoutsebaan",
    "iso:country":"BE",
    "sg:address":"Turnhoutsebaan 318",
    "sg:city":"Wijnegem",
    "sg:orig_category":"Brood, gebak and snoepgoed Verlichting and huishoudartikelen",
    "sg:phone":"+32 3 353 00 17",
    "sg:postcode":"2110",
    "sg:province":"Antwerpen",
    "wof:name":"Huis Rubens",
    "wof:placetype":"venue"
},
  "geometry": {"coordinates":[4.5175509453,51.2269172668],"type":"Point"}
}