{
  "type": "Feature",
  "properties": {
    "addr:full":"Rue Fran\u00c7ois Reconnu 15 Charleroi Hainaut 6061",
    "addr:housenumber":"15",
    "addr:postcode":"6061",
    "addr:street":"Rue Franc\u0327Ois Reconnu;Hainaut",
    "iso:country":"BE",
    "sg:address":"Rue Fran\u00c7ois Reconnu 15",
    "sg:city":"Charleroi",
    "sg:orig_category":"Sportclubs",
    "sg:phone":"+32 71 30 99 44",
    "sg:postcode":"6061",
    "sg:province":"Hainaut",
    "wof:name":"Fous Du Volant Thudinien",
    "wof:placetype":"venue"
},
  "geometry": {"coordinates":[4.477930069,50.4078102112],"type":"Point"}
}