{
  "type": "Feature",
  "properties": {
    "addr:full":"Rue Malgarny 2 Saint-nicolas Li\u00e8ge 4420",
    "addr:housenumber":"2",
    "addr:postcode":"4420",
    "addr:street":"Rue Malgarny",
    "iso:country":"BE",
    "sg:address":"Rue Malgarny 2",
    "sg:city":"Saint-nicolas",
    "sg:orig_category":"M\u00e9decins and sp\u00e9cialistes",
    "sg:phone":"+32 4 233 14 79",
    "sg:postcode":"4420",
    "sg:province":"Li\u00e8ge",
    "wof:name":"Christine Winand",
    "wof:placetype":"venue"
},
  "geometry": {"coordinates":[5.5277018547,50.6218643188],"type":"Point"}
}