{
  "type": "Feature",
  "properties": {
    "iso:country":"BE",
    "sg:address":"Place D'hanzinne 213a",
    "sg:city":"Florennes (hanzinne)",
    "sg:classifiers":[
        {
            "category":"Building & Trades",
            "subcategory":"Construction",
            "type":"Services"
        }
    ],
    "sg:phone":"+32 71 68 94 33",
    "sg:postcode":"5621",
    "sg:province":"Namur",
    "sg:tags":[
        "installation",
        "-",
        "central",
        "heating"
    ],
    "wof:name":"Delhaye M",
    "wof:placetype":"venue"
},
  "geometry": {"coordinates":[4.5413198471,50.3093185425],"type":"Point"}
}