{
  "type": "Feature",
  "properties": {
    "addr:full":"Melkerijstraat 27 Wachtebeke Oost-Vlaanderen 9185",
    "addr:housenumber":"27",
    "addr:postcode":"9185",
    "addr:street":"Melkerijstraat",
    "iso:country":"BE",
    "sg:address":"Melkerijstraat 27",
    "sg:city":"Wachtebeke",
    "sg:orig_category":"Artsen and specialisten",
    "sg:phone":"+32 9 345 73 72",
    "sg:postcode":"9185",
    "sg:province":"Oost-Vlaanderen",
    "wof:name":"Karin Meneve",
    "wof:placetype":"venue"
},
  "geometry": {"coordinates":[3.856637001,51.1743164062],"type":"Point"}
}