{
  "type": "Feature",
  "properties": {
    "iso:country":"BE",
    "sg:address":"Boniverlei 30",
    "sg:city":"Edegem",
    "sg:classifiers":[
        {
            "category":"Professional",
            "subcategory":"Accounting & Tax Preparation",
            "type":"Services"
        }
    ],
    "sg:phone":"+32 3 455 94 51",
    "sg:postcode":"2650",
    "sg:province":"Antwerpen",
    "sg:tags":[
        "accountant"
    ],
    "wof:name":"De Ridder J-p",
    "wof:placetype":"venue"
},
  "geometry": {"coordinates":[4.4550437927,51.1555709839],"type":"Point"}
}