{
  "type": "Feature",
  "properties": {
    "addr:full":"Kortrijkstraat 38 Lubbeek Vlaams-Brabant 3210",
    "addr:housenumber":"38",
    "addr:postcode":"3210",
    "addr:street":"Kortrijkstraat",
    "iso:country":"BE",
    "sg:address":"Kortrijkstraat 38",
    "sg:city":"Lubbeek",
    "sg:orig_category":"Artsen and specialisten",
    "sg:phone":"+32 16 26 04 00",
    "sg:postcode":"3210",
    "sg:province":"Vlaams-Brabant",
    "wof:name":"Karine Uyttebroeck",
    "wof:placetype":"venue"
},
  "geometry": {"coordinates":[4.7604298592,50.9004211426],"type":"Point"}
}