{
  "type": "Feature",
  "properties": {
    "iso:country":"BE",
    "sg:address":"Rue Du Calvaire 44",
    "sg:city":"Lobbes",
    "sg:orig_category":"Activit\u00e9s r\u00e9cr\u00e9atives diverses",
    "sg:phone":"+32 71 59 28 38",
    "sg:postcode":"6540",
    "sg:province":"Hainaut",
    "wof:name":"Le Trou De Sable De 5 \u00c0 13 Ans",
    "wof:placetype":"venue"
},
  "geometry": {"coordinates":[4.2731671333,50.3552055359],"type":"Point"}
}