{
  "type": "Feature",
  "properties": {
    "iso:country":"BE",
    "sg:address":"Rue De Rochefort 211-213",
    "sg:city":"Beauraing (focant)",
    "sg:classifiers":[
        {
            "category":"Professional",
            "subcategory":"Printing & Photocopies",
            "type":"Services"
        }
    ],
    "sg:phone":"+32 82 71 15 77",
    "sg:postcode":"5572",
    "sg:province":"Namur",
    "sg:tags":[
        "-",
        "offset"
    ],
    "wof:name":"Remy-roto Sa",
    "wof:placetype":"venue"
},
  "geometry": {"coordinates":[4.9775800705,50.1201705933],"type":"Point"}
}