{
  "type": "Feature",
  "properties": {
    "iso:country":"BE",
    "sg:address":"Chauss\u00e9e De Vilvorde 146",
    "sg:city":"Bruxelles",
    "sg:orig_category":"Non-Classified Establishments",
    "sg:phone":"+32 2 736 78 31",
    "sg:postcode":"1120",
    "sg:province":"Bruxelles-Capitale",
    "wof:name":"Troubadour",
    "wof:placetype":"venue"
},
  "geometry": {"coordinates":[4.3983879089,50.8945007324],"type":"Point"}
}