{
  "type": "Feature",
  "properties": {
    "addr:full":"Leie 25 Temse Oost-Vlaanderen 9140",
    "addr:housenumber":"25",
    "addr:postcode":"9140",
    "addr:street":"Leie",
    "iso:country":"BE",
    "sg:address":"Leie 25",
    "sg:city":"Temse",
    "sg:orig_category":"Jardinage",
    "sg:phone":"+32 3 771 10 42",
    "sg:postcode":"9140",
    "sg:province":"Oost-Vlaanderen",
    "wof:name":"Tuinarchitectuur Swinnen - Van De Voorde",
    "wof:placetype":"venue"
},
  "geometry": {"coordinates":[4.2061347961,51.1261024475],"type":"Point"}
}