{
  "type": "Feature",
  "properties": {
    "iso:country":"BE",
    "sg:address":"Grand Place 11",
    "sg:city":"Braine-le-chateau",
    "sg:classifiers":[
        {
            "category":"Restaurant",
            "type":"Food & Drink"
        }
    ],
    "sg:phone":"+32 2 366 30 42",
    "sg:postcode":"1440",
    "sg:province":"Brabant Wallon",
    "wof:name":"L'auberge Du Bailli",
    "wof:placetype":"venue"
},
  "geometry": {"coordinates":[4.2663431168,50.6818847656],"type":"Point"}
}