{
  "type": "Feature",
  "properties": {
    "addr:full":"Bernstraat 12 Gavere Oost-Vlaanderen 9890",
    "addr:housenumber":"12",
    "addr:postcode":"9890",
    "addr:street":"Bernstraat",
    "iso:country":"BE",
    "sg:address":"Bernstraat 12",
    "sg:city":"Gavere",
    "sg:orig_category":"Eleveurs de bovins",
    "sg:phone":"+32 9 384 82 79",
    "sg:postcode":"9890",
    "sg:province":"Oost-Vlaanderen",
    "wof:name":"Joseph Vandorpe",
    "wof:placetype":"venue"
},
  "geometry": {"coordinates":[3.6441500187,50.936050415],"type":"Point"}
}