{
  "type": "Feature",
  "properties": {
    "addr:full":"Arsenaalstraat 35 Mechelen Antwerpen 2800",
    "addr:housenumber":"35",
    "addr:postcode":"2800",
    "addr:street":"Arsenaalstraat",
    "iso:country":"BE",
    "sg:address":"Arsenaalstraat 35",
    "sg:city":"Mechelen",
    "sg:classifiers":[
        {
            "category":"Real Estate",
            "subcategory":"Architect",
            "type":"Services"
        }
    ],
    "sg:phone":"+32 15 43 15 40",
    "sg:postcode":"2800",
    "sg:province":"Antwerpen",
    "wof:name":"De Cock J",
    "wof:placetype":"venue"
},
  "geometry": {"coordinates":[4.4847421646,51.0203475952],"type":"Point"}
}