{
  "type": "Feature",
  "properties": {
    "addr:full":"Ambachtstraat 5 Torhout West-Vlaanderen 8820",
    "addr:housenumber":"5",
    "addr:postcode":"8820",
    "addr:street":"Ambachtstraat",
    "iso:country":"BE",
    "sg:address":"Ambachtstraat 5",
    "sg:city":"Torhout",
    "sg:classifiers":[
        {
            "category":"Food & Beverages",
            "subcategory":"Meat & Fish",
            "type":"Retail Goods"
        }
    ],
    "sg:phone":"+32 50 22 22 61",
    "sg:postcode":"8820",
    "sg:province":"West-Vlaanderen",
    "sg:tags":[
        "poultry",
        "whol",
        "game",
        "-"
    ],
    "wof:name":"Heindryckx",
    "wof:placetype":"venue"
},
  "geometry": {"coordinates":[3.1061499119,51.0767288208],"type":"Point"}
}