{
  "type": "Feature",
  "properties": {
    "iso:country":"BE",
    "sg:address":"Ardooisesteenweg 22",
    "sg:city":"Roeselare",
    "sg:orig_category":"Artsen and specialisten",
    "sg:phone":"+32 51 20 12 80",
    "sg:postcode":"8800",
    "sg:province":"West-Vlaanderen",
    "wof:name":"Willy Hostens",
    "wof:placetype":"venue"
},
  "geometry": {"coordinates":[3.1318910122,50.9490623474],"type":"Point"}
}