{
  "type": "Feature",
  "properties": {
    "iso:country":"BE",
    "sg:address":"Hoevelei 108",
    "sg:city":"Aartselaar",
    "sg:classifiers":[
        {
            "category":"Taxi",
            "type":"Transportation"
        }
    ],
    "sg:phone":"+32 3 239 60 60",
    "sg:postcode":"2630",
    "sg:province":"Antwerpen",
    "sg:tags":[
        "taxi's"
    ],
    "wof:name":"Berchem Taxi",
    "wof:placetype":"venue"
},
  "geometry": {"coordinates":[4.3820428848,51.138381958],"type":"Point"}
}