{
  "type": "Feature",
  "properties": {
    "addr:full":"Steenhouwersdijk 1 Brugge West-Vlaanderen 8000",
    "addr:housenumber":"1",
    "addr:postcode":"8000",
    "addr:street":"Steenhouwersdijk",
    "iso:country":"BE",
    "sg:address":"Steenhouwersdijk 1",
    "sg:city":"Brugge",
    "sg:classifiers":[
        {
            "category":"Travel",
            "subcategory":"Hotels & Motels",
            "type":"Entertainment"
        }
    ],
    "sg:phone":"+32 50 34 27 98",
    "sg:postcode":"8000",
    "sg:province":"West-Vlaanderen",
    "wof:name":"Die Swaene",
    "wof:placetype":"venue"
},
  "geometry": {"coordinates":[3.2295880318,51.2087135315],"type":"Point"}
}