{
  "type": "Feature",
  "properties": {
    "iso:country":"BE",
    "sg:address":"Oude Zandstraat 4b1",
    "sg:city":"Beveren",
    "sg:orig_category":"R\u00e9parations d'horloges, montres and bijoux. Bijouteries and horlogeries",
    "sg:phone":"+32 3 775 76 39",
    "sg:postcode":"9120",
    "sg:province":"Oost-Vlaanderen",
    "wof:name":"Huis Houttequiet",
    "wof:placetype":"venue"
},
  "geometry": {"coordinates":[4.2549858093,51.212688446],"type":"Point"}
}