{
  "type": "Feature",
  "properties": {
    "iso:country":"BE",
    "sg:address":"Rue Motte 8",
    "sg:city":"Beaumont",
    "sg:orig_category":"Woningbouw",
    "sg:phone":"+32 71 53 45 33",
    "sg:postcode":"6511",
    "sg:province":"Hainaut",
    "wof:name":"Albert Bomblet",
    "wof:placetype":"venue"
},
  "geometry": {"coordinates":[4.3002309799,50.2759933472],"type":"Point"}
}