{
  "type": "Feature",
  "properties": {
    "iso:country":"BE",
    "sg:address":"Amersveldestraat 64",
    "sg:city":"Hooglede",
    "sg:orig_category":"Groententeelt Varkenskwekers",
    "sg:phone":"+32 51 70 16 53",
    "sg:postcode":"8830",
    "sg:province":"West-Vlaanderen",
    "wof:name":"Gilbert Cornette",
    "wof:placetype":"venue"
},
  "geometry": {"coordinates":[3.0544600487,51.0003204346],"type":"Point"}
}