{
  "type": "Feature",
  "properties": {
    "iso:country":"BE",
    "sg:address":"Paul Gilsonstraat 11",
    "sg:city":"Brugge",
    "sg:orig_category":"Editeurs de journaux. Editeurs de revues and p\u00e9riodiques",
    "sg:phone":"+32 50 31 55 31",
    "sg:postcode":"8200",
    "sg:province":"West-Vlaanderen",
    "wof:name":"Vlaamse Koi-vijvervriend",
    "wof:placetype":"venue"
},
  "geometry": {"coordinates":[3.198982954,51.2081108093],"type":"Point"}
}