{
  "type": "Feature",
  "properties": {
    "iso:country":"BE",
    "sg:address":"Spreeuwstraat 6",
    "sg:city":"Evergem (ertvelde)",
    "sg:classifiers":[
        {
            "category":"Building & Trades",
            "subcategory":"Pest Control",
            "type":"Services"
        }
    ],
    "sg:phone":"+32 9 343 07 22",
    "sg:postcode":"9940",
    "sg:province":"Oost-Vlaanderen",
    "sg:tags":[
        "painting",
        "contractor"
    ],
    "wof:name":"Alero Bvba",
    "wof:placetype":"venue"
},
  "geometry": {"coordinates":[3.7590289116,51.1759643555],"type":"Point"}
}