{
  "type": "Feature",
  "properties": {
    "addr:full":"Ruiten 16 Turnhout Antwerpen 2300",
    "addr:housenumber":"16",
    "addr:postcode":"2300",
    "addr:street":"Ruiten",
    "iso:country":"BE",
    "sg:address":"Ruiten 16",
    "sg:city":"Turnhout",
    "sg:classifiers":[
        {
            "category":"Utilities",
            "subcategory":"Mobile Phone",
            "type":"Services"
        }
    ],
    "sg:phone":"+32 14 44 88 10",
    "sg:postcode":"2300",
    "sg:province":"Antwerpen",
    "sg:tags":[
        "answering",
        "telephone"
    ],
    "wof:name":"Domino",
    "wof:placetype":"venue"
},
  "geometry": {"coordinates":[4.9199080467,51.310634613],"type":"Point"}
}