{
  "type": "Feature",
  "properties": {
    "iso:country":"BE",
    "sg:address":"Dotterbloemstraat 10",
    "sg:city":"Evergem",
    "sg:orig_category":"Afvalwaterverwerking and ontstoppingsdiensten Dakwerken Huisvuilophaling and -verwerking",
    "sg:phone":"+32 9 253 57 93",
    "sg:postcode":"9940",
    "sg:province":"Oost-Vlaanderen",
    "wof:name":"Frank Franki",
    "wof:placetype":"venue"
},
  "geometry": {"coordinates":[3.7130279541,51.1085853577],"type":"Point"}
}