{
  "type": "Feature",
  "properties": {
    "addr:full":"Gistelse Steenweg 128 Brugge West-Vlaanderen 8200",
    "addr:housenumber":"128",
    "addr:postcode":"8200",
    "addr:street":"Gistelse Steenweg",
    "iso:country":"BE",
    "sg:address":"Gistelse Steenweg 128",
    "sg:city":"Brugge",
    "sg:orig_category":"Banques and organismes de cr\u00e9dit",
    "sg:phone":"+32 50 38 85 14",
    "sg:postcode":"8200",
    "sg:province":"West-Vlaanderen",
    "wof:name":"Bbl",
    "wof:placetype":"venue"
},
  "geometry": {"coordinates":[3.2031888962,51.2021026611],"type":"Point"}
}