{
  "type": "Feature",
  "properties": {
    "addr:full":"Prins-bisschoppenstraat 1 Box 1 Sint-truiden Limburg 3800",
    "addr:housenumber":"1;1",
    "addr:postcode":"3800",
    "addr:street":"Prins-Bisschoppenstraat;Box",
    "iso:country":"BE",
    "sg:address":"Prins-bisschoppenstraat 1 Box 1",
    "sg:city":"Sint-truiden",
    "sg:classifiers":[
        {
            "category":"Professional",
            "subcategory":"Accounting & Tax Preparation",
            "type":"Services"
        }
    ],
    "sg:phone":"+32 11 68 30 76",
    "sg:postcode":"3800",
    "sg:province":"Limburg",
    "sg:tags":[
        "bookkeeper"
    ],
    "wof:name":"Renard En Moors Nv",
    "wof:placetype":"venue"
},
  "geometry": {"coordinates":[5.1913638115,50.8149299622],"type":"Point"}
}