{
  "type": "Feature",
  "properties": {
    "iso:country":"BE",
    "sg:address":"Brusselsepoortstraat 18",
    "sg:city":"Mechelen",
    "sg:orig_category":"V\u00e9los",
    "sg:phone":"+32 15 43 27 49",
    "sg:postcode":"2800",
    "sg:province":"Antwerpen",
    "wof:name":"Huis Dockx",
    "wof:placetype":"venue"
},
  "geometry": {"coordinates":[4.4729862213,51.0215606689],"type":"Point"}
}