{
  "type": "Feature",
  "properties": {
    "addr:full":"Nieuwstraat 5 Box 1 Peer Limburg 3990",
    "addr:housenumber":"5;1",
    "addr:postcode":"3990",
    "addr:street":"Nieuwstraat;Box",
    "iso:country":"BE",
    "sg:address":"Nieuwstraat 5 Box 1",
    "sg:city":"Peer",
    "sg:classifiers":[
        {
            "category":"Professional",
            "subcategory":"Management & Consulting",
            "type":"Services"
        }
    ],
    "sg:phone":"+32 11 66 40 92",
    "sg:postcode":"3990",
    "sg:province":"Limburg",
    "sg:tags":[
        "consultant",
        "agency",
        "advertising"
    ],
    "wof:name":"Claes & Partners",
    "wof:placetype":"venue"
},
  "geometry": {"coordinates":[5.4534010887,51.1331367493],"type":"Point"}
}