{
  "type": "Feature",
  "properties": {
    "addr:full":"Stationsstraat 7 Ronse/renaix Oost-Vlaanderen 9600",
    "addr:housenumber":"7",
    "addr:postcode":"9600",
    "addr:street":"Stationsstraat",
    "iso:country":"BE",
    "sg:address":"Stationsstraat 7",
    "sg:city":"Ronse/renaix",
    "sg:orig_category":"Fotografen and fotostudio's",
    "sg:phone":"+32 55 20 75 26",
    "sg:postcode":"9600",
    "sg:province":"Oost-Vlaanderen",
    "wof:name":"Gees En Partners",
    "wof:placetype":"venue"
},
  "geometry": {"coordinates":[3.6005830765,50.7439727783],"type":"Point"}
}