{
  "type": "Feature",
  "properties": {
    "iso:country":"BE",
    "sg:address":"Avenue Huart Hamoir 152",
    "sg:city":"Schaarbeek/schaerbeek",
    "sg:orig_category":"Boucheries",
    "sg:phone":"+32 2 215 67 46",
    "sg:postcode":"1030",
    "sg:province":"Bruxelles-Capitale",
    "wof:name":"Boucherie Devos",
    "wof:placetype":"venue"
},
  "geometry": {"coordinates":[4.3867959976,50.8742141724],"type":"Point"}
}