{
  "type": "Feature",
  "properties": {
    "iso:country":"BE",
    "sg:address":"Rue De Mont-serrat 2a",
    "sg:city":"Jemeppe-sur-sambre (onoz)",
    "sg:orig_category":"Non-Classified Establishments",
    "sg:phone":"+32 81 63 33 11",
    "sg:postcode":"5190",
    "sg:province":"Namur",
    "wof:name":"Idv Lighting Sa",
    "wof:placetype":"venue"
},
  "geometry": {"coordinates":[4.6734080315,50.4868774414],"type":"Point"}
}