{
  "type": "Feature",
  "properties": {
    "addr:full":"Chauss\u00c9e De La Croix 3 Ottignies-louvain-la-neuve Brabant Wallon 1340",
    "addr:housenumber":"3",
    "addr:postcode":"1340",
    "addr:street":"Chausse\u0301E De La Croix",
    "iso:country":"BE",
    "sg:address":"Chauss\u00c9e De La Croix 3",
    "sg:city":"Ottignies-louvain-la-neuve",
    "sg:orig_category":"Opticiens. Articles m\u00e9dicaux and orthop\u00e9diques",
    "sg:phone":"+32 10 41 83 07",
    "sg:postcode":"1340",
    "sg:province":"Brabant Wallon",
    "wof:name":"Thierry Verstraete",
    "wof:placetype":"venue"
},
  "geometry": {"coordinates":[4.5737218857,50.6694755554],"type":"Point"}
}