{
  "type": "Feature",
  "properties": {
    "iso:country":"BE",
    "sg:address":"Stationsstraat 9",
    "sg:city":"Herselt (ramsel)",
    "sg:classifiers":[
        {
            "category":"Food & Beverages",
            "subcategory":"Supermarket",
            "type":"Retail Goods"
        }
    ],
    "sg:phone":"+32 16 68 03 88",
    "sg:postcode":"2230",
    "sg:province":"Antwerpen",
    "sg:tags":[
        "department",
        "store"
    ],
    "wof:name":"Pelgrims",
    "wof:placetype":"venue"
},
  "geometry": {"coordinates":[4.8819890022,51.0529556274],"type":"Point"}
}