{
  "type": "Feature",
  "properties": {
    "addr:full":"Dendermondesteenweg 32 Wetteren Oost-Vlaanderen 9230",
    "addr:housenumber":"32",
    "addr:postcode":"9230",
    "addr:street":"Dendermondesteenweg",
    "iso:country":"BE",
    "sg:address":"Dendermondesteenweg 32",
    "sg:city":"Wetteren",
    "sg:classifiers":[
        {
            "category":"Autos & Motor Vehicles",
            "subcategory":"Fuel & Gas Station",
            "type":"Retail Goods"
        }
    ],
    "sg:phone":"+32 9 369 24 11",
    "sg:postcode":"9230",
    "sg:province":"Oost-Vlaanderen",
    "sg:tags":[
        "stations-service",
        "carburants"
    ],
    "wof:name":"Guido Van Herreweghe",
    "wof:placetype":"venue"
},
  "geometry": {"coordinates":[3.9099678993,51.0110282898],"type":"Point"}
}