{
  "type": "Feature",
  "properties": {
    "iso:country":"BE",
    "sg:address":"Stichelberg 35",
    "sg:city":"Dilbeek (groot - Bijgaarden)",
    "sg:classifiers":[
        {
            "category":"Real Estate",
            "subcategory":"Real Estate Services",
            "type":"Services"
        }
    ],
    "sg:phone":"+32 2 466 19 61",
    "sg:postcode":"1702",
    "sg:province":"Vlaams-Brabant",
    "wof:name":"B.e.c. Willems-engineering",
    "wof:placetype":"venue"
},
  "geometry": {"coordinates":[4.2640109062,50.8643302917],"type":"Point"}
}