{
  "type": "Feature",
  "properties": {
    "addr:full":"Boerenkrijglaan 47 Herentals Antwerpen 2200",
    "addr:housenumber":"47",
    "addr:postcode":"2200",
    "addr:street":"Boerenkrijglaan",
    "iso:country":"BE",
    "sg:address":"Boerenkrijglaan 47",
    "sg:city":"Herentals",
    "sg:classifiers":[
        {
            "category":"Sports & Exercise",
            "subcategory":"Sports Center",
            "type":"Entertainment"
        }
    ],
    "sg:phone":"+32 14 21 25 49",
    "sg:postcode":"2200",
    "sg:province":"Antwerpen",
    "sg:tags":[
        "terrain",
        "hors",
        "de",
        "installation",
        "sportifs"
    ],
    "wof:name":"Herentalse Ruiterij",
    "wof:placetype":"venue"
},
  "geometry": {"coordinates":[4.8422732353,51.1741676331],"type":"Point"}
}