{
  "type": "Feature",
  "properties": {
    "addr:full":"Waterkuilstraat 36 Sint-truiden (zepperen) Limburg 3800",
    "addr:housenumber":"36",
    "addr:postcode":"3800",
    "addr:street":"Waterkuilstraat",
    "iso:country":"BE",
    "sg:address":"Waterkuilstraat 36",
    "sg:city":"Sint-truiden (zepperen)",
    "sg:classifiers":[
        {
            "category":"Health Services",
            "subcategory":"Health Practitioner",
            "type":"Services"
        }
    ],
    "sg:phone":"+32 11 70 75 05",
    "sg:postcode":"3800",
    "sg:province":"Limburg",
    "sg:tags":[
        "physiotherapist"
    ],
    "wof:name":"Heyman Mia",
    "wof:placetype":"venue"
},
  "geometry": {"coordinates":[5.2548451424,50.8351287842],"type":"Point"}
}