{
  "type": "Feature",
  "properties": {
    "iso:country":"BE",
    "sg:address":"Rue Pont De Bonne 22",
    "sg:city":"Modave",
    "sg:classifiers":[
        {
            "category":"Bars & Pubs",
            "type":"Food & Drink"
        }
    ],
    "sg:phone":"+32 85 41 11 33",
    "sg:postcode":"4577",
    "sg:province":"Li\u00e8ge",
    "wof:name":"Gillet-richard J-l",
    "wof:placetype":"venue"
},
  "geometry": {"coordinates":[5.285943985,50.4507865906],"type":"Point"}
}