{
  "type": "Feature",
  "properties": {
    "addr:full":"Avenue De La R\u00c9forme 63 Ganshoren/ganshoren Bruxelles-Capitale 1083",
    "addr:housenumber":"63",
    "addr:postcode":"1083",
    "addr:street":"Avenue De La Re\u0301Forme",
    "iso:country":"BE",
    "sg:address":"Avenue De La R\u00c9forme 63",
    "sg:city":"Ganshoren/ganshoren",
    "sg:classifiers":[
        {
            "category":"Health Services",
            "subcategory":"Nursing And Care Facility",
            "type":"Services"
        }
    ],
    "sg:phone":"+32 2 422 57 57",
    "sg:postcode":"1083",
    "sg:province":"Bruxelles-Capitale",
    "sg:tags":[
        "public"
    ],
    "wof:name":"C.p.a.s./o.c.m.w.",
    "wof:placetype":"venue"
},
  "geometry": {"coordinates":[4.3130259514,50.874835968],"type":"Point"}
}