{
  "type": "Feature",
  "properties": {
    "addr:full":"Fonteinplein 18 Oudenaarde Oost-Vlaanderen 9700",
    "addr:housenumber":"18",
    "addr:postcode":"9700",
    "addr:street":"Fonteinplein",
    "iso:country":"BE",
    "sg:address":"Fonteinplein 18",
    "sg:city":"Oudenaarde",
    "sg:classifiers":[
        {
            "category":"Wholesale",
            "subcategory":"Beer",
            "type":"Manufacturing & Wholesale Goods"
        }
    ],
    "sg:phone":"+32 55 31 96 74",
    "sg:postcode":"9700",
    "sg:province":"Oost-Vlaanderen",
    "sg:tags":[
        "ale",
        "-"
    ],
    "wof:name":"Brouwerij Clarysse",
    "wof:placetype":"venue"
},
  "geometry": {"coordinates":[3.6096899509,50.8358383179],"type":"Point"}
}