{
  "type": "Feature",
  "properties": {
    "addr:full":"Langveldstraat 93 Alken Limburg 3570",
    "addr:housenumber":"93",
    "addr:postcode":"3570",
    "addr:street":"Langveldstraat",
    "iso:country":"BE",
    "sg:address":"Langveldstraat 93",
    "sg:city":"Alken",
    "sg:orig_category":"Pleisterwerk",
    "sg:phone":"+32 11 31 53 88",
    "sg:postcode":"3570",
    "sg:province":"Limburg",
    "wof:name":"Philtjens Marc",
    "wof:placetype":"venue"
},
  "geometry": {"coordinates":[5.3016471863,50.8773078918],"type":"Point"}
}