{
  "type": "Feature",
  "properties": {
    "addr:full":"Oude Vismijn 32 Lokeren Oost-Vlaanderen 9160",
    "addr:housenumber":"32",
    "addr:postcode":"9160",
    "addr:street":"Oude Vismijn",
    "iso:country":"BE",
    "sg:address":"Oude Vismijn 32",
    "sg:city":"Lokeren",
    "sg:orig_category":"Installations and terrains de sport hors centres sportifs. Articles de camping and de sport. Centres",
    "sg:phone":"+32 9 348 76 56",
    "sg:postcode":"9160",
    "sg:province":"Oost-Vlaanderen",
    "wof:name":"Sportcentrum De Dam",
    "wof:placetype":"venue"
},
  "geometry": {"coordinates":[3.9864850044,51.1047401428],"type":"Point"}
}