{
  "type": "Feature",
  "properties": {
    "addr:full":"Holleweggaarde 6ba Schaarbeek/schaerbeek Bruxelles-Capitale 1030",
    "addr:housenumber":"6ba",
    "addr:postcode":"1030",
    "addr:street":"Holleweggaarde",
    "iso:country":"BE",
    "sg:address":"Holleweggaarde 6ba",
    "sg:city":"Schaarbeek/schaerbeek",
    "sg:orig_category":"Rusthuizen and serviceflats",
    "sg:phone":"+32 2 241 96 75",
    "sg:postcode":"1030",
    "sg:province":"Bruxelles-Capitale",
    "wof:name":"Home Ambroisie 3i\u00c8me Age",
    "wof:placetype":"venue"
},
  "geometry": {"coordinates":[4.3932051659,50.8647575378],"type":"Point"}
}