{
  "type": "Feature",
  "properties": {
    "iso:country":"BE",
    "sg:address":"Jantenstraat 7ba",
    "sg:city":"Lummen",
    "sg:orig_category":"Eleveurs d'animaux domestiques",
    "sg:phone":"+32 11 43 28 64",
    "sg:postcode":"3560",
    "sg:province":"Limburg",
    "wof:name":"Kennel Van Het Lumboshof",
    "wof:placetype":"venue"
},
  "geometry": {"coordinates":[5.2279372215,51.0065078735],"type":"Point"}
}