{
  "type": "Feature",
  "properties": {
    "addr:full":"Rue Des Viaducs 108 Mons Hainaut 7020",
    "addr:housenumber":"108",
    "addr:postcode":"7020",
    "addr:street":"Rue Des Viaducs;Hainaut",
    "iso:country":"BE",
    "sg:address":"Rue Des Viaducs 108",
    "sg:city":"Mons",
    "sg:orig_category":"Huisdieren and benodigdheden",
    "sg:phone":"+32 65 34 98 16",
    "sg:postcode":"7020",
    "sg:province":"Hainaut",
    "wof:name":"Aqua-nimy",
    "wof:placetype":"venue"
},
  "geometry": {"coordinates":[3.9553449154,50.4761772156],"type":"Point"}
}