{
  "type": "Feature",
  "properties": {
    "iso:country":"BE",
    "sg:address":"Boomgaardstraat 89",
    "sg:city":"Antwerpen",
    "sg:orig_category":"Travaux de pl\u00e2trage",
    "sg:phone":"+32 3 239 68 08",
    "sg:postcode":"2018",
    "sg:province":"Antwerpen",
    "wof:name":"Daniel Claes",
    "wof:placetype":"venue"
},
  "geometry": {"coordinates":[4.4230251312,51.2008781433],"type":"Point"}
}