{
  "type": "Feature",
  "properties": {
    "addr:full":"Cit\u00c9 L\u00c9vie 31 Morlanwelz Hainaut 7141",
    "addr:housenumber":"31",
    "addr:postcode":"7141",
    "addr:street":"Cite\u0301 Le\u0301Vie",
    "iso:country":"BE",
    "sg:address":"Cit\u00c9 L\u00c9vie 31",
    "sg:city":"Morlanwelz",
    "sg:orig_category":"Entretien and r\u00e9parations de voitures. V\u00e9hicules automobiles. R\u00e9cup\u00e9ration de mati\u00e8res m\u00e9talliques r",
    "sg:phone":"+32 64 44 69 12",
    "sg:postcode":"7141",
    "sg:province":"Hainaut",
    "wof:name":"Jean-marie Marcil",
    "wof:placetype":"venue"
},
  "geometry": {"coordinates":[4.2543048859,50.4436531067],"type":"Point"}
}