{
  "type": "Feature",
  "properties": {
    "addr:full":"Chauss\u00c9e De Mons 77 Charleroi Hainaut 6000",
    "addr:housenumber":"77",
    "addr:postcode":"6000",
    "addr:street":"Chausse\u0301E De Mons;Hainaut",
    "iso:country":"BE",
    "sg:address":"Chauss\u00c9e De Mons 77",
    "sg:city":"Charleroi",
    "sg:orig_category":"Mat\u00e9riaux de construction Rev\u00eatements de sols and murs",
    "sg:phone":"+32 71 32 93 60",
    "sg:postcode":"6000",
    "sg:province":"Hainaut",
    "wof:name":"Bruno",
    "wof:placetype":"venue"
},
  "geometry": {"coordinates":[4.4328989983,50.412109375],"type":"Point"}
}