{
  "type": "Feature",
  "properties": {
    "iso:country":"BE",
    "sg:address":"Leebrugstraat 32b",
    "sg:city":"Sint-niklaas (sinaai)",
    "sg:classifiers":[
        {
            "category":"Building & Trades",
            "subcategory":"Construction",
            "type":"Services"
        }
    ],
    "sg:phone":"+32 3 722 02 24",
    "sg:postcode":"9112",
    "sg:province":"Oost-Vlaanderen",
    "sg:tags":[
        "carpenter"
    ],
    "wof:name":"Ingels D",
    "wof:placetype":"venue"
},
  "geometry": {"coordinates":[4.0061187744,51.1529426575],"type":"Point"}
}