{
  "type": "Feature",
  "properties": {
    "addr:full":"Rue Belle Vue 8 Fernelmont (cortil-wodon) Namur 5380",
    "addr:housenumber":"8",
    "addr:postcode":"5380",
    "addr:street":"Rue Belle Vue",
    "iso:country":"BE",
    "sg:address":"Rue Belle Vue 8",
    "sg:city":"Fernelmont (cortil-wodon)",
    "sg:classifiers":[
        {
            "category":"Home & Garden",
            "subcategory":"Building Materials",
            "type":"Retail Goods"
        }
    ],
    "sg:phone":"+32 81 83 53 73",
    "sg:postcode":"5380",
    "sg:province":"Namur",
    "sg:tags":[
        "veranda"
    ],
    "wof:name":"Rossi (ets)",
    "wof:placetype":"venue"
},
  "geometry": {"coordinates":[4.9604802132,50.5670051575],"type":"Point"}
}