{
  "type": "Feature",
  "properties": {
    "iso:country":"BE",
    "sg:address":"Schillebeekstraat 111",
    "sg:city":"Geraardsbergen",
    "sg:orig_category":"Cr\u00e9meries",
    "sg:phone":"+32 54 41 39 58",
    "sg:postcode":"9500",
    "sg:province":"Oost-Vlaanderen",
    "wof:name":"Rosier",
    "wof:placetype":"venue"
},
  "geometry": {"coordinates":[3.8874299526,50.7627182007],"type":"Point"}
}