{
  "type": "Feature",
  "properties": {
    "addr:full":"Plaats 11 Galmaarden (tollembeek) Vlaams-Brabant 1570",
    "addr:housenumber":"11",
    "addr:postcode":"1570",
    "addr:street":"Plaats",
    "iso:country":"BE",
    "sg:address":"Plaats 11",
    "sg:city":"Galmaarden (tollembeek)",
    "sg:classifiers":[
        {
            "category":"Bars & Pubs",
            "type":"Food & Drink"
        }
    ],
    "sg:phone":"+32 54 58 08 54",
    "sg:postcode":"1570",
    "sg:province":"Vlaams-Brabant",
    "wof:name":"Pallieterken",
    "wof:placetype":"venue"
},
  "geometry": {"coordinates":[4.0082111359,50.7437667847],"type":"Point"}
}