{
  "type": "Feature",
  "properties": {
    "iso:country":"BE",
    "sg:address":"Watermolenstraat 16",
    "sg:city":"Galmaarden",
    "sg:classifiers":[
        {
            "category":"Personal",
            "subcategory":"Beauty Salon",
            "type":"Services"
        }
    ],
    "sg:phone":"+32 54 51 88 91",
    "sg:postcode":"1570",
    "sg:province":"Vlaams-Brabant",
    "sg:tags":[
        "lady",
        "-",
        "hairdressing"
    ],
    "wof:name":"De Smet C",
    "wof:placetype":"venue"
},
  "geometry": {"coordinates":[3.965720892,50.7529411316],"type":"Point"}
}