{
  "type": "Feature",
  "properties": {
    "addr:full":"Louizalaan 154 Elsene/ixelles Bruxelles-Capitale 1050",
    "addr:housenumber":"154",
    "addr:postcode":"1050",
    "addr:street":"Louizalaan",
    "iso:country":"BE",
    "sg:address":"Louizalaan 154",
    "sg:city":"Elsene/ixelles",
    "sg:orig_category":"Meubelzaken, woning- and keukeninrichting",
    "sg:phone":"+32 2 649 95 94",
    "sg:postcode":"1050",
    "sg:province":"Bruxelles-Capitale",
    "wof:name":"Dominique Rigo",
    "wof:placetype":"venue"
},
  "geometry": {"coordinates":[4.3573069572,50.8343505859],"type":"Point"}
}