{
  "type": "Feature",
  "properties": {
    "addr:full":"De Merodelei 37 Turnhout Antwerpen 2300",
    "addr:housenumber":"37",
    "addr:postcode":"2300",
    "addr:street":"De Merodelei",
    "iso:country":"BE",
    "sg:address":"De Merodelei 37",
    "sg:city":"Turnhout",
    "sg:orig_category":"Avocats and conseillers juridiques",
    "sg:phone":"+32 14 47 05 80",
    "sg:postcode":"2300",
    "sg:province":"Antwerpen",
    "wof:name":"J. De Chaffoy",
    "wof:placetype":"venue"
},
  "geometry": {"coordinates":[4.941409111,51.3220329285],"type":"Point"}
}