{
  "type": "Feature",
  "properties": {
    "addr:full":"Rue Des Hauchies 53b1 Charleroi Hainaut 6042",
    "addr:housenumber":"53b1",
    "addr:postcode":"6042",
    "addr:street":"Rue Des Hauchies;Hainaut",
    "iso:country":"BE",
    "sg:address":"Rue Des Hauchies 53b1",
    "sg:city":"Charleroi",
    "sg:orig_category":"Binnenhuisarchitecten",
    "sg:phone":"+32 71 41 04 81",
    "sg:postcode":"6042",
    "sg:province":"Hainaut",
    "wof:name":"Romain & Cie",
    "wof:placetype":"venue"
},
  "geometry": {"coordinates":[4.4579381943,50.3896408081],"type":"Point"}
}