{
  "type": "Feature",
  "properties": {
    "addr:full":"Avenue De La Victoire 64a Neufch\u00e2teau Luxembourg 6840",
    "addr:housenumber":"64a",
    "addr:postcode":"6840",
    "addr:street":"Avenue De La Victoire",
    "iso:country":"BE",
    "sg:address":"Avenue De La Victoire 64a",
    "sg:city":"Neufch\u00e2teau",
    "sg:classifiers":[
        {
            "category":"Social Services",
            "type":"Services"
        }
    ],
    "sg:phone":"+32 61 41 03 80",
    "sg:postcode":"6840",
    "sg:province":"Luxembourg",
    "wof:name":"Service D'aide \u00e0 La Jeunesse",
    "wof:placetype":"venue"
},
  "geometry": {"coordinates":[5.4345149994,49.8440895081],"type":"Point"}
}