{
  "type": "Feature",
  "properties": {
    "addr:full":"Avenue Royale 33 Rixensart Brabant Wallon 1330",
    "addr:housenumber":"33",
    "addr:postcode":"1330",
    "addr:street":"Avenue Royale;Wallon",
    "iso:country":"BE",
    "sg:address":"Avenue Royale 33",
    "sg:city":"Rixensart",
    "sg:classifiers":[
        {
            "category":"Professional",
            "subcategory":"Testing Lab",
            "type":"Services"
        }
    ],
    "sg:phone":"+32 2 653 43 53",
    "sg:postcode":"1330",
    "sg:province":"Brabant Wallon",
    "sg:tags":[
        "chemist"
    ],
    "wof:name":"Pharmacie De Froidmont",
    "wof:placetype":"venue"
},
  "geometry": {"coordinates":[4.5439648628,50.7119140625],"type":"Point"}
}