{
  "type": "Feature",
  "properties": {
    "iso:country":"BE",
    "sg:address":"Zaveldriesstraat 47",
    "sg:city":"Genk",
    "sg:orig_category":"Epiceries",
    "sg:phone":"+32 89 38 25 75",
    "sg:postcode":"3600",
    "sg:province":"Limburg",
    "wof:name":"Supermarkt",
    "wof:placetype":"venue"
},
  "geometry": {"coordinates":[5.4987359047,51.0061531067],"type":"Point"}
}