{
  "type": "Feature",
  "properties": {
    "addr:full":"De Ronde 1 Avelgem West-Vlaanderen 8580",
    "addr:housenumber":"1",
    "addr:postcode":"8580",
    "addr:street":"De Ronde",
    "iso:country":"BE",
    "sg:address":"De Ronde 1",
    "sg:city":"Avelgem",
    "sg:orig_category":"Maisons de repos and r\u00e9sidences",
    "sg:phone":"+32 56 64 53 06",
    "sg:postcode":"8580",
    "sg:province":"West-Vlaanderen",
    "wof:name":"S.f.g. Steenhuuse",
    "wof:placetype":"venue"
},
  "geometry": {"coordinates":[3.446532011,50.7727470398],"type":"Point"}
}