{
  "type": "Feature",
  "properties": {
    "addr:full":"Brelaarstraat 17 Beringen Limburg 3583",
    "addr:housenumber":"17",
    "addr:postcode":"3583",
    "addr:street":"Brelaarstraat",
    "iso:country":"BE",
    "sg:address":"Brelaarstraat 17",
    "sg:city":"Beringen",
    "sg:orig_category":"Banques and organismes de cr\u00e9dit",
    "sg:phone":"+32 11 42 89 35",
    "sg:postcode":"3583",
    "sg:province":"Limburg",
    "wof:name":"Citibank",
    "wof:placetype":"venue"
},
  "geometry": {"coordinates":[5.1706700325,51.0389442444],"type":"Point"}
}