{
  "type": "Feature",
  "properties": {
    "iso:country":"BE",
    "sg:address":"Westkaai 14",
    "sg:city":"Ieper",
    "sg:orig_category":"Elektrische installaties voor woningen",
    "sg:phone":"+32 57 20 18 89",
    "sg:postcode":"8900",
    "sg:province":"West-Vlaanderen",
    "wof:name":"Traen Electro",
    "wof:placetype":"venue"
},
  "geometry": {"coordinates":[2.8818740845,50.860912323],"type":"Point"}
}