{
  "type": "Feature",
  "properties": {
    "addr:full":"Zonhoevestraat 9 Bilzen Limburg 3740",
    "addr:housenumber":"9",
    "addr:postcode":"3740",
    "addr:street":"Zonhoevestraat",
    "iso:country":"BE",
    "sg:address":"Zonhoevestraat 9",
    "sg:city":"Bilzen",
    "sg:orig_category":"Artsen and specialisten",
    "sg:phone":"+32 89 41 10 65",
    "sg:postcode":"3740",
    "sg:province":"Limburg",
    "wof:name":"Luc Hendrix",
    "wof:placetype":"venue"
},
  "geometry": {"coordinates":[5.4712018967,50.8923530579],"type":"Point"}
}