{
  "type": "Feature",
  "properties": {
    "addr:full":"Rue Fernand M\u00c9lard 9 Brussel/bruxelles Bruxelles-Capitale 1200",
    "addr:housenumber":"9",
    "addr:postcode":"1200",
    "addr:street":"Rue Fernand Me\u0301Lard;/",
    "iso:country":"BE",
    "sg:address":"Rue Fernand M\u00c9lard 9",
    "sg:city":"Brussel/bruxelles",
    "sg:orig_category":"Produits chimiques Gr",
    "sg:phone":"+32 2 762 97 21",
    "sg:postcode":"1200",
    "sg:province":"Bruxelles-Capitale",
    "wof:name":"Indusun",
    "wof:placetype":"venue"
},
  "geometry": {"coordinates":[4.4280838966,50.8416366577],"type":"Point"}
}