{
  "type": "Feature",
  "properties": {
    "addr:full":"Route De Bullange 227 Amel/ambl\u00c8ve Li\u00e8ge 4770",
    "addr:housenumber":"227",
    "addr:postcode":"4770",
    "addr:street":"Route De Bullange",
    "iso:country":"BE",
    "sg:address":"Route De Bullange 227",
    "sg:city":"Amel/ambl\u00c8ve",
    "sg:classifiers":[
        {
            "category":"Government",
            "subcategory":"Police Station",
            "type":"Public Place"
        }
    ],
    "sg:phone":"+32 80 34 81 30",
    "sg:postcode":"4770",
    "sg:province":"Li\u00e8ge",
    "sg:tags":[
        "gendarmerie"
    ],
    "wof:name":"Polizei",
    "wof:placetype":"venue"
},
  "geometry": {"coordinates":[6.1876211166,50.3251914978],"type":"Point"}
}