{
  "type": "Feature",
  "properties": {
    "iso:country":"BE",
    "sg:address":"Septemberlaan 21",
    "sg:city":"Sint-lambrechts-woluwe/woluwe-saint-lambert",
    "sg:orig_category":"Artsen and specialisten",
    "sg:phone":"+32 2 771 20 33",
    "sg:postcode":"1200",
    "sg:province":"Bruxelles-Capitale",
    "wof:name":"Luc Arco",
    "wof:placetype":"venue"
},
  "geometry": {"coordinates":[4.4157090187,50.8470611572],"type":"Point"}
}