{
  "type": "Feature",
  "properties": {
    "iso:country":"BE",
    "sg:address":"Gentse Steenweg 136",
    "sg:city":"Lokeren",
    "sg:classifiers":[
        {
            "category":"Home & Garden",
            "subcategory":"Building Materials",
            "type":"Retail Goods"
        }
    ],
    "sg:phone":"+32 9 348 49 51",
    "sg:postcode":"9160",
    "sg:province":"Oost-Vlaanderen",
    "sg:tags":[
        "window"
    ],
    "wof:name":"Verkoopsconsortium Engels Nv-sa",
    "wof:placetype":"venue"
},
  "geometry": {"coordinates":[3.9550049305,51.1142616272],"type":"Point"}
}