{
  "type": "Feature",
  "properties": {
    "addr:full":"Chauss\u00c9e De Frasnes 136 Tournai Hainaut 7540",
    "addr:housenumber":"136",
    "addr:postcode":"7540",
    "addr:street":"Chausse\u0301E De Frasnes",
    "iso:country":"BE",
    "sg:address":"Chauss\u00c9e De Frasnes 136",
    "sg:city":"Tournai",
    "sg:classifiers":[
        {
            "category":"Food & Beverages",
            "subcategory":"Fruits & Vegetables",
            "type":"Retail Goods"
        }
    ],
    "sg:phone":"+32 69 22 61 47",
    "sg:postcode":"7540",
    "sg:province":"Hainaut",
    "sg:tags":[
        "l\u00e9gumes",
        "gr"
    ],
    "wof:name":"Jonckheere Marcel Et Fils",
    "wof:placetype":"venue"
},
  "geometry": {"coordinates":[3.5049169064,50.6484832764],"type":"Point"}
}