{
  "type": "Feature",
  "properties": {
    "addr:full":"Zoutleeuwstraat 46 Landen Vlaams-Brabant 3404",
    "addr:housenumber":"46",
    "addr:postcode":"3404",
    "addr:street":"Zoutleeuwstraat",
    "iso:country":"BE",
    "sg:address":"Zoutleeuwstraat 46",
    "sg:city":"Landen",
    "sg:orig_category":"Varkenskwekers",
    "sg:phone":"+32 11 88 16 16",
    "sg:postcode":"3404",
    "sg:province":"Vlaams-Brabant",
    "wof:name":"Frieda Wanten",
    "wof:placetype":"venue"
},
  "geometry": {"coordinates":[5.0791168213,50.7809181213],"type":"Point"}
}