{
  "type": "Feature",
  "properties": {
    "addr:full":"Rue Chatqueue 148 Seraing Li\u00e8ge 4100",
    "addr:housenumber":"148",
    "addr:postcode":"4100",
    "addr:street":"Rue Chatqueue",
    "iso:country":"BE",
    "sg:address":"Rue Chatqueue 148",
    "sg:city":"Seraing",
    "sg:classifiers":[
        {
            "category":"Building & Trades",
            "subcategory":"Construction",
            "type":"Services"
        }
    ],
    "sg:phone":"+32 4 336 30 32",
    "sg:postcode":"4100",
    "sg:province":"Li\u00e8ge",
    "sg:tags":[
        "paper",
        "hanger"
    ],
    "wof:name":"Martin J-f",
    "wof:placetype":"venue"
},
  "geometry": {"coordinates":[5.5200328827,50.5990600586],"type":"Point"}
}