{
  "type": "Feature",
  "properties": {
    "addr:full":"Place De La Gare 0 Ottignies-louvain-la-neuve Brabant Wallon 1340",
    "addr:housenumber":"0",
    "addr:postcode":"1340",
    "addr:street":"Place De La Gare",
    "iso:country":"BE",
    "sg:address":"Place De La Gare 0",
    "sg:city":"Ottignies-louvain-la-neuve",
    "sg:classifiers":[
        {
            "category":"Cafe",
            "type":"Food & Drink"
        }
    ],
    "sg:phone":"+32 10 41 09 60",
    "sg:postcode":"1340",
    "sg:province":"Brabant Wallon",
    "sg:tags":[
        "caf\u00e9s"
    ],
    "wof:name":"Buffet De La Gare",
    "wof:placetype":"venue"
},
  "geometry": {"coordinates":[4.570089817,50.6728553772],"type":"Point"}
}