{
  "type": "Feature",
  "properties": {
    "iso:country":"BE",
    "sg:address":"Beverenstraat 46",
    "sg:city":"Deerlijk",
    "sg:orig_category":"Travaux d\u00b4installation divers. D\u00e9molition d\u00b4immeubles and terrassements. El\u00e9ments en b\u00e9ton pour la c",
    "sg:phone":"+32 56 71 33 01",
    "sg:postcode":"8540",
    "sg:province":"West-Vlaanderen",
    "wof:name":"N.v. Frans Vanden Broecke",
    "wof:placetype":"venue"
},
  "geometry": {"coordinates":[3.3501141071,50.8561859131],"type":"Point"}
}