{
  "type": "Feature",
  "properties": {
    "iso:country":"BE",
    "sg:address":"Rue Fran\u00c7ois Libert 10",
    "sg:city":"Waterloo",
    "sg:orig_category":"Verlichting and huishoudartikelen Woningbouw",
    "sg:phone":"+32 2 353 25 26",
    "sg:postcode":"1410",
    "sg:province":"Brabant Wallon",
    "wof:name":"Maison Eric Mardaga",
    "wof:placetype":"venue"
},
  "geometry": {"coordinates":[4.3961100578,50.7174530029],"type":"Point"}
}