{
  "type": "Feature",
  "properties": {
    "addr:full":"Rue Wazon 35 Li\u00e8ge 1 Li\u00e8ge 4000",
    "addr:housenumber":"35;1",
    "addr:postcode":"4000",
    "addr:street":"Rue Wazon",
    "iso:country":"BE",
    "sg:address":"Rue Wazon 35",
    "sg:city":"Li\u00e8ge 1",
    "sg:classifiers":[
        {
            "category":"Manufacturing",
            "subcategory":"Glass & Minerals",
            "type":"Manufacturing & Wholesale Goods"
        }
    ],
    "sg:phone":"+32 4 221 38 86",
    "sg:postcode":"4000",
    "sg:province":"Li\u00e8ge",
    "sg:tags":[
        "stained",
        "glazier",
        "-"
    ],
    "wof:name":"Pirotte Tai Yung",
    "wof:placetype":"venue"
},
  "geometry": {"coordinates":[5.5581598282,50.6381912231],"type":"Point"}
}