{
  "type": "Feature",
  "properties": {
    "iso:country":"BE",
    "sg:address":"Werf",
    "sg:city":"Geel",
    "sg:orig_category":"Cin\u00e9mas",
    "sg:phone":"+32 14 58 74 07",
    "sg:postcode":"2440",
    "sg:province":"Antwerpen",
    "wof:name":"Studio",
    "wof:placetype":"venue"
},
  "geometry": {"coordinates":[4.9888839722,51.1618804932],"type":"Point"}
}