{
  "type": "Feature",
  "properties": {
    "iso:country":"BE",
    "sg:address":"Stalenstraat 134",
    "sg:city":"Genk",
    "sg:orig_category":"Services de t\u00e9l\u00e9communications. Production and distribution d'\u00e9lectricit\u00e9",
    "sg:phone":"+32 89 84 86 86",
    "sg:postcode":"3600",
    "sg:province":"Limburg",
    "wof:name":"Interelectra",
    "wof:placetype":"venue"
},
  "geometry": {"coordinates":[5.5129051208,50.9910850525],"type":"Point"}
}