{
  "type": "Feature",
  "properties": {
    "addr:full":"Stationstraat 74 Komen-waasten/comines-warneton Hainaut 7780",
    "addr:housenumber":"74;7780",
    "addr:street":"Stationstraat",
    "iso:country":"BE",
    "sg:address":"Stationstraat 74",
    "sg:city":"Komen-waasten/comines-warneton",
    "sg:orig_category":"Kruideniers Voedingsspeciaalzaken",
    "sg:phone":"+32 56 55 79 05",
    "sg:postcode":"7780",
    "sg:province":"Hainaut",
    "wof:name":"La Grappe De Raisin",
    "wof:placetype":"venue"
},
  "geometry": {"coordinates":[2.9984300137,50.7863311768],"type":"Point"}
}