{
  "type": "Feature",
  "properties": {
    "addr:full":"Blankenbergsesteenweg 161 Brugge West-Vlaanderen 8000",
    "addr:housenumber":"161",
    "addr:postcode":"8000",
    "addr:street":"Blankenbergsesteenweg",
    "iso:country":"BE",
    "sg:address":"Blankenbergsesteenweg 161",
    "sg:city":"Brugge",
    "sg:classifiers":[
        {
            "category":"Professional",
            "subcategory":"Detective & Security Services",
            "type":"Services"
        }
    ],
    "sg:phone":"+32 50 31 80 81",
    "sg:postcode":"8000",
    "sg:province":"West-Vlaanderen",
    "sg:tags":[
        "fab",
        "de",
        "travail",
        "v\u00eatements",
        "protection"
    ],
    "wof:name":"V.d.p.-optishop",
    "wof:placetype":"venue"
},
  "geometry": {"coordinates":[3.2012999058,51.2372512817],"type":"Point"}
}