{
  "type": "Feature",
  "properties": {
    "iso:country":"BE",
    "sg:address":"Voie Des Hougnes 42",
    "sg:city":"Herve (battice)",
    "sg:classifiers":[
        {
            "category":"Professional",
            "subcategory":"Art Services",
            "type":"Services"
        }
    ],
    "sg:phone":"+32 479 21 89 40",
    "sg:postcode":"4651",
    "sg:province":"Li\u00e8ge",
    "sg:tags":[
        "designer",
        "display"
    ],
    "wof:name":"Pauquay I",
    "wof:placetype":"venue"
},
  "geometry": {"coordinates":[5.7901902199,50.6536102295],"type":"Point"}
}