{
  "type": "Feature",
  "properties": {
    "iso:country":"BE",
    "sg:address":"Molenweg 6",
    "sg:city":"Huldenberg",
    "sg:orig_category":"Plomberie, chauffage and installations sanitaires",
    "sg:phone":"+32 16 47 28 85",
    "sg:postcode":"3040",
    "sg:province":"Vlaams-Brabant",
    "wof:name":"A.p.a.",
    "wof:placetype":"venue"
},
  "geometry": {"coordinates":[4.598156929,50.7922592163],"type":"Point"}
}