{
  "type": "Feature",
  "properties": {
    "addr:full":"Siemenslaan 21 Industrieterrein Lanklaar Dilsenstokkem Limburg 3650",
    "addr:housenumber":"21",
    "addr:postcode":"3650",
    "addr:street":"Siemenslaan;Industrieterrein Lanklaar",
    "iso:country":"BE",
    "sg:address":"Siemenslaan 21 Industrieterrein Lanklaar",
    "sg:city":"Dilsenstokkem",
    "sg:classifiers":[
        {
            "category":"Food & Beverages",
            "subcategory":"Groceries & Convenience Stores",
            "type":"Retail Goods"
        }
    ],
    "sg:phone":"+32 89 79 09 70",
    "sg:postcode":"3650",
    "sg:province":"Limburg",
    "sg:tags":[
        "product",
        "related"
    ],
    "wof:name":"Incopack Nv",
    "wof:placetype":"venue"
},
  "geometry": {"coordinates":[5.727396965,51.0364189148],"type":"Point"}
}