{
  "type": "Feature",
  "properties": {
    "addr:full":"Daalstraat 1b Wellen Limburg 3830",
    "addr:housenumber":"1b",
    "addr:postcode":"3830",
    "addr:street":"Daalstraat",
    "iso:country":"BE",
    "sg:address":"Daalstraat 1b",
    "sg:city":"Wellen",
    "sg:classifiers":[
        {
            "category":"Health Services",
            "subcategory":"Health Practitioner",
            "type":"Services"
        }
    ],
    "sg:phone":"+32 12 74 63 52",
    "sg:postcode":"3830",
    "sg:province":"Limburg",
    "sg:tags":[
        "physiotherapist"
    ],
    "wof:name":"Devogelaere J",
    "wof:placetype":"venue"
},
  "geometry": {"coordinates":[5.3184900284,50.8461723328],"type":"Point"}
}