{
  "type": "Feature",
  "properties": {
    "addr:full":"Heirbaan 45b1 Dendermonde Oost-Vlaanderen 9200",
    "addr:housenumber":"45b1",
    "addr:postcode":"9200",
    "addr:street":"Heirbaan;Oost-Vlaanderen",
    "iso:country":"BE",
    "sg:address":"Heirbaan 45b1",
    "sg:city":"Dendermonde",
    "sg:orig_category":"Boissons",
    "sg:phone":"+32 52 21 58 26",
    "sg:postcode":"9200",
    "sg:province":"Oost-Vlaanderen",
    "wof:name":"Willy Maes",
    "wof:placetype":"venue"
},
  "geometry": {"coordinates":[4.1136832237,51.0162887573],"type":"Point"}
}