{
  "type": "Feature",
  "properties": {
    "addr:full":"Rue Des Campeaux 28 Tournai Hainaut 7500",
    "addr:housenumber":"28",
    "addr:postcode":"7500",
    "addr:street":"Rue Des Campeaux",
    "iso:country":"BE",
    "sg:address":"Rue Des Campeaux 28",
    "sg:city":"Tournai",
    "sg:classifiers":[
        {
            "category":"Building & Trades",
            "subcategory":"Electrical",
            "type":"Services"
        }
    ],
    "sg:phone":"+32 69 21 63 74",
    "sg:postcode":"7500",
    "sg:province":"Hainaut",
    "sg:tags":[
        "industrial",
        "-",
        "electric",
        "contractor"
    ],
    "wof:name":"Tremar",
    "wof:placetype":"venue"
},
  "geometry": {"coordinates":[3.3925209045,50.6080322266],"type":"Point"}
}