{
  "type": "Feature",
  "properties": {
    "iso:country":"BE",
    "sg:address":"P. Benoitstraat 37",
    "sg:city":"Vilvoorde",
    "sg:classifiers":[
        {
            "category":"Professional",
            "subcategory":"Art Services",
            "type":"Services"
        }
    ],
    "sg:phone":"+32 2 251 32 93",
    "sg:postcode":"1800",
    "sg:province":"Vlaams-Brabant",
    "sg:tags":[
        "realization",
        "audio-visual"
    ],
    "wof:name":"Geraar Bvba",
    "wof:placetype":"venue"
},
  "geometry": {"coordinates":[4.4308748245,50.9310340881],"type":"Point"}
}