{
  "type": "Feature",
  "properties": {
    "addr:full":"Rue Royale 132 Box 2 Bruxelles Bruxelles-Capitale 1000",
    "addr:housenumber":"132;2",
    "addr:postcode":"1000",
    "addr:street":"Rue Royale;Box",
    "iso:country":"BE",
    "sg:address":"Rue Royale 132 Box 2",
    "sg:city":"Bruxelles",
    "sg:classifiers":[
        {
            "category":"Wholesale",
            "subcategory":"Books, Periodicals, & Newspapers",
            "type":"Manufacturing & Wholesale Goods"
        }
    ],
    "sg:phone":"+32 2 209 83 00",
    "sg:postcode":"1000",
    "sg:province":"Bruxelles-Capitale",
    "sg:tags":[
        "publisher"
    ],
    "wof:name":"Editions Casterman Sa",
    "wof:placetype":"venue"
},
  "geometry": {"coordinates":[4.3632931709,50.8489379883],"type":"Point"}
}