{
  "type": "Feature",
  "properties": {
    "addr:full":"Avenue Charles Deli\u00c8ge 43 Binche Hainaut 7130",
    "addr:housenumber":"43",
    "addr:postcode":"7130",
    "addr:street":"Avenue Charles Delie\u0300Ge",
    "iso:country":"BE",
    "sg:address":"Avenue Charles Deli\u00c8ge 43",
    "sg:city":"Binche",
    "sg:classifiers":[
        {
            "category":"Cafe",
            "type":"Food & Drink"
        }
    ],
    "sg:phone":"+32 64 36 91 23",
    "sg:postcode":"7130",
    "sg:province":"Hainaut",
    "sg:tags":[
        "caf\u00e9s"
    ],
    "wof:name":"Willy Challe",
    "wof:placetype":"venue"
},
  "geometry": {"coordinates":[4.1665139198,50.4127006531],"type":"Point"}
}