{
  "type": "Feature",
  "properties": {
    "addr:full":"Schaffelkantstraat 35 Herent Vlaams-Brabant 3020",
    "addr:housenumber":"35",
    "addr:postcode":"3020",
    "addr:street":"Schaffelkantstraat",
    "iso:country":"BE",
    "sg:address":"Schaffelkantstraat 35",
    "sg:city":"Herent",
    "sg:classifiers":[
        {
            "category":"Home & Garden",
            "subcategory":"Building Materials",
            "type":"Retail Goods"
        }
    ],
    "sg:phone":"+32 477 30 12 55",
    "sg:postcode":"3020",
    "sg:province":"Vlaams-Brabant",
    "sg:tags":[
        "wall",
        "cupboard"
    ],
    "wof:name":"Van Erom E",
    "wof:placetype":"venue"
},
  "geometry": {"coordinates":[4.678030014,50.8992767334],"type":"Point"}
}