{
  "type": "Feature",
  "properties": {
    "iso:country":"BE",
    "sg:address":"Terneuzenlaan 16",
    "sg:city":"Gent",
    "sg:classifiers":[
        {
            "category":"Shopping",
            "subcategory":"Discount & Variety Stores",
            "type":"Retail Goods"
        }
    ],
    "sg:phone":"+32 477 84 70 05",
    "sg:postcode":"9000",
    "sg:province":"Oost-Vlaanderen",
    "sg:tags":[
        "shop",
        "clearers",
        "curiosity",
        "furniture"
    ],
    "wof:name":"Aankoop Team",
    "wof:placetype":"venue"
},
  "geometry": {"coordinates":[3.7292668819,51.071144104],"type":"Point"}
}