{
  "type": "Feature",
  "properties": {
    "iso:country":"BE",
    "sg:address":"Venakker 26ba",
    "sg:city":"Aalter",
    "sg:orig_category":"Diverse bouwafwerking and reiniging",
    "sg:phone":"+32 9 374 75 55",
    "sg:postcode":"9880",
    "sg:province":"Oost-Vlaanderen",
    "wof:name":"Bart Botterman",
    "wof:placetype":"venue"
},
  "geometry": {"coordinates":[3.4463028908,51.0960235596],"type":"Point"}
}