{
  "type": "Feature",
  "properties": {
    "addr:full":"Zavelstraat 89 Leuven Vlaams-Brabant 3010",
    "addr:housenumber":"89",
    "addr:postcode":"3010",
    "addr:street":"Zavelstraat",
    "iso:country":"BE",
    "sg:address":"Zavelstraat 89",
    "sg:city":"Leuven",
    "sg:orig_category":"D\u00e9corateurs d'int\u00e9rieur",
    "sg:phone":"+32 16 25 68 97",
    "sg:postcode":"3010",
    "sg:province":"Vlaams-Brabant",
    "wof:name":"Lemmens",
    "wof:placetype":"venue"
},
  "geometry": {"coordinates":[4.7304501534,50.889755249],"type":"Point"}
}