{
  "type": "Feature",
  "properties": {
    "addr:full":"Sint-bavoplein 17 Boechout Antwerpen 2530",
    "addr:housenumber":"17",
    "addr:postcode":"2530",
    "addr:street":"Sint-Bavoplein",
    "iso:country":"BE",
    "sg:address":"Sint-bavoplein 17",
    "sg:city":"Boechout",
    "sg:classifiers":[
        {
            "category":"Arts & Performance",
            "subcategory":"Theater",
            "type":"Entertainment"
        }
    ],
    "sg:phone":"+32 3 289 09 78",
    "sg:postcode":"2530",
    "sg:province":"Antwerpen",
    "sg:tags":[
        "concert-halls",
        "theatre"
    ],
    "wof:name":"Theater Boechout Vooruit Vzw",
    "wof:placetype":"venue"
},
  "geometry": {"coordinates":[4.4917402267,51.158908844],"type":"Point"}
}