{
  "type": "Feature",
  "properties": {
    "addr:full":"Bareelstraat 3 Dendermonde (sint-gillis-bij-dendermonde) Oost-Vlaanderen 9200",
    "addr:housenumber":"3",
    "addr:postcode":"9200",
    "addr:street":"Bareelstraat",
    "iso:country":"BE",
    "sg:address":"Bareelstraat 3",
    "sg:city":"Dendermonde (sint-gillis-bij-dendermonde)",
    "sg:classifiers":[
        {
            "category":"Building & Trades",
            "subcategory":"Construction",
            "type":"Services"
        }
    ],
    "sg:phone":"+32 52 22 00 89",
    "sg:postcode":"9200",
    "sg:province":"Oost-Vlaanderen",
    "sg:tags":[
        "carpenter"
    ],
    "wof:name":"Verhaegen",
    "wof:placetype":"venue"
},
  "geometry": {"coordinates":[4.1139907837,51.0219764709],"type":"Point"}
}