{
  "type": "Feature",
  "properties": {
    "iso:country":"BE",
    "sg:address":"Rue Du Cur\u00e9 Notre-dame 5",
    "sg:city":"Tournai",
    "sg:classifiers":[
        {
            "category":"Retail",
            "subcategory":"Laundry & Dry Cleaning",
            "type":"Services"
        }
    ],
    "sg:phone":"+32 69 23 41 32",
    "sg:postcode":"7500",
    "sg:province":"Hainaut",
    "sg:tags":[
        "dyer",
        "cleaner"
    ],
    "wof:name":"Press'eco",
    "wof:placetype":"venue"
},
  "geometry": {"coordinates":[3.3885331154,50.6073875427],"type":"Point"}
}