{
  "type": "Feature",
  "properties": {
    "addr:full":"Avenue Cl\u00c9mentine 6 Vorst/forest Bruxelles-Capitale 1190",
    "addr:housenumber":"6",
    "addr:postcode":"1190",
    "addr:street":"Avenue Cle\u0301Mentine;/ Forest",
    "iso:country":"BE",
    "sg:address":"Avenue Cl\u00c9mentine 6",
    "sg:city":"Vorst/forest",
    "sg:orig_category":"M\u00e9decines alternatives. Maisons de repos and r\u00e9sidences",
    "sg:phone":"+32 2 537 59 31",
    "sg:postcode":"1190",
    "sg:province":"Bruxelles-Capitale",
    "wof:name":"Fanny Noskowicz",
    "wof:placetype":"venue"
},
  "geometry": {"coordinates":[4.3381738663,50.8243713379],"type":"Point"}
}