{
  "type": "Feature",
  "properties": {
    "addr:full":"Lorkendreef 14 Sint-martens-latem (deurle) Oost-Vlaanderen 9831",
    "addr:housenumber":"14",
    "addr:postcode":"9831",
    "addr:street":"Lorkendreef;Deurle",
    "iso:country":"BE",
    "sg:address":"Lorkendreef 14",
    "sg:city":"Sint-martens-latem (deurle)",
    "sg:classifiers":[
        {
            "category":"Real Estate",
            "subcategory":"Real Estate Services",
            "type":"Services"
        }
    ],
    "sg:phone":"+32 9 385 38 26",
    "sg:postcode":"9831",
    "sg:province":"Oost-Vlaanderen",
    "wof:name":"Best Invest Nv",
    "wof:placetype":"venue"
},
  "geometry": {"coordinates":[3.6130349636,51.0106201172],"type":"Point"}
}