{
  "type": "Feature",
  "properties": {
    "addr:full":"Kouteren 44 Zwalm Oost-Vlaanderen 9630",
    "addr:housenumber":"44",
    "addr:postcode":"9630",
    "addr:street":"Kouteren;Oost-Vlaanderen",
    "iso:country":"BE",
    "sg:address":"Kouteren 44",
    "sg:city":"Zwalm",
    "sg:orig_category":"Woningbouw",
    "sg:phone":"+32 55 49 88 46",
    "sg:postcode":"9630",
    "sg:province":"Oost-Vlaanderen",
    "wof:name":"Rudy De Clercq",
    "wof:placetype":"venue"
},
  "geometry": {"coordinates":[3.73001194,50.8539466858],"type":"Point"}
}