{
  "type": "Feature",
  "properties": {
    "iso:country":"BE",
    "sg:address":"Rijksweg 426",
    "sg:city":"Dilsen-stokkem",
    "sg:orig_category":"Meubles D\u00e9taillants, Am\u00e9nagement de B\u00e2timents et de Cuisines",
    "sg:phone":"+32 89 75 38 00",
    "sg:postcode":"3650",
    "sg:province":"Limburg",
    "wof:name":"Dotex",
    "wof:placetype":"venue"
},
  "geometry": {"coordinates":[5.7278618813,51.0333824158],"type":"Point"}
}