{
  "type": "Feature",
  "properties": {
    "iso:country":"BE",
    "sg:address":"Bredabaan 134",
    "sg:city":"Antwerpen",
    "sg:orig_category":"Artiesten and kunstenaars",
    "sg:phone":"+32 3 644 21 36",
    "sg:postcode":"2170",
    "sg:province":"Antwerpen",
    "wof:name":"Tintoretto Paint Thing Cy",
    "wof:placetype":"venue"
},
  "geometry": {"coordinates":[4.4246368408,51.2363395691],"type":"Point"}
}