{
  "type": "Feature",
  "properties": {
    "addr:full":"Sint-servatiusstraat 10 Diepenbeek Limburg 3590",
    "addr:housenumber":"10",
    "addr:postcode":"3590",
    "addr:street":"Sint-Servatiusstraat",
    "iso:country":"BE",
    "sg:address":"Sint-servatiusstraat 10",
    "sg:city":"Diepenbeek",
    "sg:orig_category":"V\u00e9t\u00e9rinaires",
    "sg:phone":"+32 11 32 44 90",
    "sg:postcode":"3590",
    "sg:province":"Limburg",
    "wof:name":"Guy Schouteden",
    "wof:placetype":"venue"
},
  "geometry": {"coordinates":[5.4435567856,50.9221763611],"type":"Point"}
}