{
  "type": "Feature",
  "properties": {
    "iso:country":"BE",
    "sg:address":"Hoogte 68",
    "sg:city":"Sint-laureins",
    "sg:classifiers":[
        {
            "category":"Parking",
            "subcategory":"Garage",
            "type":"Transportation"
        }
    ],
    "sg:phone":"+32 9 379 91 78",
    "sg:postcode":"9980",
    "sg:province":"Oost-Vlaanderen",
    "sg:tags":[
        "prefabricated",
        "-"
    ],
    "wof:name":"Dierkens R",
    "wof:placetype":"venue"
},
  "geometry": {"coordinates":[3.5936489105,51.2381896973],"type":"Point"}
}