{
  "type": "Feature",
  "properties": {
    "addr:full":"Rue Emile Claus 56-1 Bruxelles (uccle) Bruxelles-Capitale 1180",
    "addr:housenumber":"56-1",
    "addr:postcode":"1180",
    "addr:street":"Rue Emile Claus",
    "iso:country":"BE",
    "sg:address":"Rue Emile Claus 56-1",
    "sg:city":"Bruxelles (uccle)",
    "sg:classifiers":[
        {
            "category":"Personal",
            "subcategory":"Beauty Salon",
            "type":"Services"
        }
    ],
    "sg:phone":"+32 2 646 14 00",
    "sg:postcode":"1180",
    "sg:province":"Bruxelles-Capitale",
    "wof:name":"Mains De Gin (les)",
    "wof:placetype":"venue"
},
  "geometry": {"coordinates":[4.3674798012,50.8155975342],"type":"Point"}
}