{
  "type": "Feature",
  "properties": {
    "iso:country":"BE",
    "sg:address":"Mandekensstraat 200",
    "sg:city":"Termonde",
    "sg:orig_category":"Herstellingen and onderhoud van auto's",
    "sg:phone":"+32 52 34 51 13",
    "sg:postcode":"9200",
    "sg:province":"Oost-Vlaanderen",
    "wof:name":"Van Pollaert N",
    "wof:placetype":"venue"
},
  "geometry": {"coordinates":[4.0983099937,51.0315208435],"type":"Point"}
}