{
  "type": "Feature",
  "properties": {
    "iso:country":"BE",
    "sg:address":"Lange Munteplein 4",
    "sg:city":"Kortrijk",
    "sg:classifiers":[
        {
            "category":"Bars & Pubs",
            "type":"Food & Drink"
        }
    ],
    "sg:phone":"+32 56 20 13 30",
    "sg:postcode":"8500",
    "sg:province":"West-Vlaanderen",
    "sg:tags":[
        "tavern"
    ],
    "wof:name":"Den Haese",
    "wof:placetype":"venue"
},
  "geometry": {"coordinates":[3.2674291134,50.8260726929],"type":"Point"}
}