{
  "type": "Feature",
  "properties": {
    "addr:full":"Chauss\u00c9e De Louvain 270 Brussel/bruxelles Bruxelles-Capitale 1000",
    "addr:housenumber":"270",
    "addr:postcode":"1000",
    "addr:street":"Chausse\u0301E De Louvain;/",
    "iso:country":"BE",
    "sg:address":"Chauss\u00c9e De Louvain 270",
    "sg:city":"Brussel/bruxelles",
    "sg:orig_category":"Epiceries",
    "sg:phone":"+32 2 721 08 35",
    "sg:postcode":"1000",
    "sg:province":"Bruxelles-Capitale",
    "wof:name":"Maison India Port",
    "wof:placetype":"venue"
},
  "geometry": {"coordinates":[4.3815808296,50.8505973816],"type":"Point"}
}