{
  "type": "Feature",
  "properties": {
    "addr:full":"Station 59ba Gedinne Namur 5575",
    "addr:postcode":"5575",
    "addr:street":"Namur",
    "iso:country":"BE",
    "sg:address":"Station 59ba",
    "sg:city":"Gedinne",
    "sg:orig_category":"Benzinestations and brandstoffen",
    "sg:phone":"+32 61 58 80 01",
    "sg:postcode":"5575",
    "sg:province":"Namur",
    "wof:name":"Gedinne Station",
    "wof:placetype":"venue"
},
  "geometry": {"coordinates":[4.9788370132,49.9825592041],"type":"Point"}
}