{
  "type": "Feature",
  "properties": {
    "addr:full":"Rue Saint-roch 14 Momignies Hainaut 6596",
    "addr:housenumber":"14",
    "addr:postcode":"6596",
    "addr:street":"Rue Saint-Roch;Hainaut",
    "iso:country":"BE",
    "sg:address":"Rue Saint-roch 14",
    "sg:city":"Momignies",
    "sg:orig_category":"S\u00e9curit\u00e9 sociale",
    "sg:phone":"+32 60 51 14 65",
    "sg:postcode":"6596",
    "sg:province":"Hainaut",
    "wof:name":"Mutualit\u00c9 Lib\u00c9rale",
    "wof:placetype":"venue"
},
  "geometry": {"coordinates":[4.2543501854,50.0136756897],"type":"Point"}
}