{
  "type": "Feature",
  "properties": {
    "addr:full":"Watermolenstraat 79 Kortrijk West-Vlaanderen 8500",
    "addr:housenumber":"79",
    "addr:postcode":"8500",
    "addr:street":"Watermolenstraat",
    "iso:country":"BE",
    "sg:address":"Watermolenstraat 79",
    "sg:city":"Kortrijk",
    "sg:classifiers":[
        {
            "category":"Home & Garden",
            "subcategory":"Home Furnishings",
            "type":"Retail Goods"
        }
    ],
    "sg:phone":"+32 56 37 39 15",
    "sg:postcode":"8500",
    "sg:province":"West-Vlaanderen",
    "sg:tags":[
        "interior",
        "decoration"
    ],
    "wof:name":"Neo Cocoon",
    "wof:placetype":"venue"
},
  "geometry": {"coordinates":[3.2621059418,50.8379440308],"type":"Point"}
}