{
  "type": "Feature",
  "properties": {
    "addr:full":"Rue De Burhaimont 1a Bertrix Luxembourg 6880",
    "addr:housenumber":"1a",
    "addr:postcode":"6880",
    "addr:street":"Rue De Burhaimont",
    "iso:country":"BE",
    "sg:address":"Rue De Burhaimont 1a",
    "sg:city":"Bertrix",
    "sg:classifiers":[
        {
            "category":"Retail",
            "subcategory":"Veterinary Services",
            "type":"Services"
        }
    ],
    "sg:phone":"+32 61 41 13 00",
    "sg:postcode":"6880",
    "sg:province":"Luxembourg",
    "sg:tags":[
        "veterinarian"
    ],
    "wof:name":"Cornet E",
    "wof:placetype":"venue"
},
  "geometry": {"coordinates":[5.2523832321,49.8558502197],"type":"Point"}
}