{
  "type": "Feature",
  "properties": {
    "iso:country":"BE",
    "sg:address":"Wapenrustinglaan 48",
    "sg:city":"Vorst/forest",
    "sg:orig_category":"Artsen and specialisten",
    "sg:phone":"+32 2 345 59 10",
    "sg:postcode":"1190",
    "sg:province":"Bruxelles-Capitale",
    "wof:name":"Michel Masson",
    "wof:placetype":"venue"
},
  "geometry": {"coordinates":[4.3362751007,50.8147506714],"type":"Point"}
}