{
  "type": "Feature",
  "properties": {
    "addr:full":"Rue Au Vin 45 Renaix Oost-Vlaanderen 9600",
    "addr:housenumber":"45",
    "addr:postcode":"9600",
    "addr:street":"Rue Au Vin",
    "iso:country":"BE",
    "sg:address":"Rue Au Vin 45",
    "sg:city":"Renaix",
    "sg:classifiers":[
        {
            "category":"Shopping",
            "subcategory":"Clothing, Apparel, & Fashions",
            "type":"Retail Goods"
        }
    ],
    "sg:phone":"+32 55 21 04 73",
    "sg:postcode":"9600",
    "sg:province":"Oost-Vlaanderen",
    "sg:tags":[
        "-",
        "clothing",
        "child"
    ],
    "wof:name":"Scoubi'line",
    "wof:placetype":"venue"
},
  "geometry": {"coordinates":[3.5989809036,50.7477264404],"type":"Point"}
}