{
  "type": "Feature",
  "properties": {
    "addr:full":"Rue Des Alli\u00e9s 37 Frameries Hainaut 7080",
    "addr:housenumber":"37",
    "addr:postcode":"7080",
    "addr:street":"Rue Des Allie\u0301S",
    "iso:country":"BE",
    "sg:address":"Rue Des Alli\u00e9s 37",
    "sg:city":"Frameries",
    "sg:classifiers":[
        {
            "category":"Shopping",
            "subcategory":"Optician",
            "type":"Retail Goods"
        }
    ],
    "sg:phone":"+32 65 61 14 14",
    "sg:postcode":"7080",
    "sg:province":"Hainaut",
    "sg:tags":[
        "-"
    ],
    "wof:name":"Simonet Optique Sprl",
    "wof:placetype":"venue"
},
  "geometry": {"coordinates":[3.8946650028,50.4094314575],"type":"Point"}
}