{
  "type": "Feature",
  "properties": {
    "iso:country":"BE",
    "sg:address":"Rue Saint-jean 9",
    "sg:city":"Jodoigne",
    "sg:orig_category":"Banques and organismes de cr\u00e9dit",
    "sg:phone":"+32 10 81 24 34",
    "sg:postcode":"1370",
    "sg:province":"Brabant Wallon",
    "wof:name":"Dexia",
    "wof:placetype":"venue"
},
  "geometry": {"coordinates":[4.8701448441,50.724571228],"type":"Point"}
}