{
  "type": "Feature",
  "properties": {
    "addr:full":"Rue Des Sapins 1 Bernissart Hainaut 7321",
    "addr:housenumber":"1",
    "addr:postcode":"7321",
    "addr:street":"Rue Des Sapins",
    "iso:country":"BE",
    "sg:address":"Rue Des Sapins 1",
    "sg:city":"Bernissart",
    "sg:classifiers":[
        {
            "category":"Social Services",
            "subcategory":"Job Training",
            "type":"Services"
        }
    ],
    "sg:phone":"+32 69 57 72 33",
    "sg:postcode":"7321",
    "sg:province":"Hainaut",
    "sg:tags":[
        "de",
        "terrain",
        "camping"
    ],
    "wof:name":"Camping Les Gen\u00cats",
    "wof:placetype":"venue"
},
  "geometry": {"coordinates":[3.6611618996,50.5015869141],"type":"Point"}
}