{
  "type": "Feature",
  "properties": {
    "iso:country":"BE",
    "sg:address":"Hoefijzerlaan 20",
    "sg:city":"Brugge",
    "sg:orig_category":"Zalen voor culturele evenementen",
    "sg:phone":"+32 50 33 50 89",
    "sg:postcode":"8000",
    "sg:province":"West-Vlaanderen",
    "wof:name":"Galerij Dieperinck",
    "wof:placetype":"venue"
},
  "geometry": {"coordinates":[3.2159490585,51.2070999146],"type":"Point"}
}