{
  "type": "Feature",
  "properties": {
    "iso:country":"BE",
    "sg:address":"Route Jean Xiii 53",
    "sg:city":"Baelen",
    "sg:classifiers":[
        {
            "category":"Freight",
            "type":"Transportation"
        }
    ],
    "sg:phone":"+32 87 76 28 78",
    "sg:postcode":"4837",
    "sg:province":"Li\u00e8ge",
    "sg:tags":[
        "-",
        "transport"
    ],
    "wof:name":"Cremer J-p",
    "wof:placetype":"venue"
},
  "geometry": {"coordinates":[5.9713449478,50.6319007874],"type":"Point"}
}