{
  "type": "Feature",
  "properties": {
    "addr:full":"Violierstraat 4a Antwerpen Antwerpen 2060",
    "addr:housenumber":"4a",
    "addr:postcode":"2060",
    "addr:street":"Violierstraat",
    "iso:country":"BE",
    "sg:address":"Violierstraat 4a",
    "sg:city":"Antwerpen",
    "sg:classifiers":[
        {
            "category":"Health Services",
            "subcategory":"Doctor",
            "type":"Services"
        }
    ],
    "sg:phone":"+32 3 232 30 05",
    "sg:postcode":"2060",
    "sg:province":"Antwerpen",
    "sg:tags":[
        "medicinephysicians",
        "surgeon"
    ],
    "wof:name":"Adam A",
    "wof:placetype":"venue"
},
  "geometry": {"coordinates":[4.4170742035,51.2217903137],"type":"Point"}
}