{
  "type": "Feature",
  "properties": {
    "addr:full":"Brusselsesteenweg 414 Wetteren Oost-Vlaanderen 9230",
    "addr:housenumber":"414",
    "addr:postcode":"9230",
    "addr:street":"Brusselsesteenweg",
    "iso:country":"BE",
    "sg:address":"Brusselsesteenweg 414",
    "sg:city":"Wetteren",
    "sg:classifiers":[
        {
            "category":"Autos & Motor Vehicles",
            "subcategory":"Recreational Vehicle Sales",
            "type":"Retail Goods"
        }
    ],
    "sg:phone":"+32 9 369 12 83",
    "sg:postcode":"9230",
    "sg:province":"Oost-Vlaanderen",
    "sg:tags":[
        "caravan",
        "accessory"
    ],
    "wof:name":"Gassman Caravans Bvba",
    "wof:placetype":"venue"
},
  "geometry": {"coordinates":[3.8654038906,50.9741783142],"type":"Point"}
}