{
  "type": "Feature",
  "properties": {
    "addr:full":"Rue De L'amercoeur 71 Li\u00c8ge Li\u00e8ge 4020",
    "addr:housenumber":"71",
    "addr:postcode":"4020",
    "addr:street":"Rue De L'Amercoeur",
    "iso:country":"BE",
    "sg:address":"Rue De L'amercoeur 71",
    "sg:city":"Li\u00c8ge",
    "sg:orig_category":"M\u00e9decins and sp\u00e9cialistes",
    "sg:phone":"+32 4 343 38 09",
    "sg:postcode":"4020",
    "sg:province":"Li\u00e8ge",
    "wof:name":"Hue Hoac Khon",
    "wof:placetype":"venue"
},
  "geometry": {"coordinates":[5.5906319618,50.6360206604],"type":"Point"}
}