{
  "type": "Feature",
  "properties": {
    "addr:full":"Rue Du Village 160 Quaregnon Hainaut 7390",
    "addr:housenumber":"160",
    "addr:postcode":"7390",
    "addr:street":"Rue Du Village",
    "iso:country":"BE",
    "sg:address":"Rue Du Village 160",
    "sg:city":"Quaregnon",
    "sg:orig_category":"Opticiens",
    "sg:phone":"+32 65 77 01 78",
    "sg:postcode":"7390",
    "sg:province":"Hainaut",
    "wof:name":"Christian Cauchies",
    "wof:placetype":"venue"
},
  "geometry": {"coordinates":[3.865819931,50.4411811829],"type":"Point"}
}