{
  "type": "Feature",
  "properties": {
    "addr:full":"Ter Kassei 18 Wevelgem (moorsele) West-Vlaanderen 8560",
    "addr:housenumber":"18",
    "addr:postcode":"8560",
    "addr:street":"Ter Kassei",
    "iso:country":"BE",
    "sg:address":"Ter Kassei 18",
    "sg:city":"Wevelgem (moorsele)",
    "sg:classifiers":[
        {
            "category":"Food & Beverages",
            "subcategory":"Groceries & Convenience Stores",
            "type":"Retail Goods"
        }
    ],
    "sg:phone":"+32 56 41 83 23",
    "sg:postcode":"8560",
    "sg:province":"West-Vlaanderen",
    "sg:tags":[
        "grocer"
    ],
    "wof:name":"Deceuninck R",
    "wof:placetype":"venue"
},
  "geometry": {"coordinates":[3.1545040607,50.8383483887],"type":"Point"}
}