{
  "type": "Feature",
  "properties": {
    "iso:country":"BE",
    "sg:address":"Oscar Verschuerestraat 28",
    "sg:city":"Waregem",
    "sg:orig_category":"Cr\u00e9meries. Epiceries",
    "sg:phone":"+32 56 60 15 91",
    "sg:postcode":"8790",
    "sg:province":"West-Vlaanderen",
    "wof:name":"'t Hollands Kaashuis",
    "wof:placetype":"venue"
},
  "geometry": {"coordinates":[3.4296360016,50.8870582581],"type":"Point"}
}