{
  "type": "Feature",
  "properties": {
    "iso:country":"BE",
    "sg:address":"Vrijheid 100",
    "sg:city":"Arendonk",
    "sg:classifiers":[
        {
            "category":"Health Services",
            "subcategory":"Nursing And Care Facility",
            "type":"Services"
        }
    ],
    "sg:phone":"+32 14 67 25 30",
    "sg:postcode":"2370",
    "sg:province":"Antwerpen",
    "sg:tags":[
        "home",
        "rest"
    ],
    "wof:name":"St Isabella",
    "wof:placetype":"venue"
},
  "geometry": {"coordinates":[5.0916500092,51.3218917847],"type":"Point"}
}