{
  "type": "Feature",
  "properties": {
    "addr:full":"Rue Camille Giroul 2 Floreffe Namur 5150",
    "addr:housenumber":"2",
    "addr:postcode":"5150",
    "addr:street":"Rue Camille Giroul",
    "iso:country":"BE",
    "sg:address":"Rue Camille Giroul 2",
    "sg:city":"Floreffe",
    "sg:classifiers":[
        {
            "category":"Health Services",
            "subcategory":"Doctor",
            "type":"Services"
        }
    ],
    "sg:phone":"+32 81 44 10 42",
    "sg:postcode":"5150",
    "sg:province":"Namur",
    "sg:tags":[
        "medicinephysicians",
        "surgeon"
    ],
    "wof:name":"Hoslet Caty",
    "wof:placetype":"venue"
},
  "geometry": {"coordinates":[4.7594637871,50.4343833923],"type":"Point"}
}