{
  "type": "Feature",
  "properties": {
    "addr:full":"Avenue Montefiore 32 Esneux Li\u00e8ge 4130",
    "addr:housenumber":"32",
    "addr:postcode":"4130",
    "addr:street":"Avenue Montefiore",
    "iso:country":"BE",
    "sg:address":"Avenue Montefiore 32",
    "sg:city":"Esneux",
    "sg:orig_category":"M\u00e9decins and sp\u00e9cialistes",
    "sg:phone":"+32 4 380 15 82",
    "sg:postcode":"4130",
    "sg:province":"Li\u00e8ge",
    "wof:name":"Francis Piron",
    "wof:placetype":"venue"
},
  "geometry": {"coordinates":[5.5635380745,50.5317840576],"type":"Point"}
}