{
  "type": "Feature",
  "properties": {
    "iso:country":"BE",
    "sg:address":"Rue De Li\u00c8ge 189",
    "sg:city":"Kelmis/la Calamine",
    "sg:orig_category":"Meubles D\u00e9taillants, Am\u00e9nagement de B\u00e2timents et de Cuisines. Textiles",
    "sg:phone":"+32 87 65 33 91",
    "sg:postcode":"4721",
    "sg:province":"Li\u00e8ge",
    "wof:name":"Bazar Du Matelas",
    "wof:placetype":"venue"
},
  "geometry": {"coordinates":[6.0145730972,50.714805603],"type":"Point"}
}