{
  "type": "Feature",
  "properties": {
    "addr:full":"Staatsbaan 121 Bekkevoort Vlaams-Brabant 3460",
    "addr:housenumber":"121",
    "addr:postcode":"3460",
    "addr:street":"Staatsbaan",
    "iso:country":"BE",
    "sg:address":"Staatsbaan 121",
    "sg:city":"Bekkevoort",
    "sg:orig_category":"Brood, gebak and snoepgoed",
    "sg:phone":"+32 13 33 41 73",
    "sg:postcode":"3460",
    "sg:province":"Vlaams-Brabant",
    "wof:name":"Christiaan Ons",
    "wof:placetype":"venue"
},
  "geometry": {"coordinates":[4.9852399826,50.9479370117],"type":"Point"}
}