{
  "type": "Feature",
  "properties": {
    "iso:country":"BE",
    "sg:address":"Rue De Binte 7ba",
    "sg:city":"Marche-en-famenne",
    "sg:classifiers":[
        {
            "category":"Sports & Exercise",
            "subcategory":"Sports Center",
            "type":"Entertainment"
        }
    ],
    "sg:phone":"+32 84 21 34 32",
    "sg:postcode":"6900",
    "sg:province":"Luxembourg",
    "sg:tags":[
        "terrain",
        "hors",
        "de",
        "installation",
        "sportifs"
    ],
    "wof:name":"Man\u00c8ge Du Fr\u00cane",
    "wof:placetype":"venue"
},
  "geometry": {"coordinates":[5.3430151939,50.2273483276],"type":"Point"}
}