{
  "type": "Feature",
  "properties": {
    "iso:country":"BE",
    "sg:address":"Chauss\u00c9e D'audenarde 33",
    "sg:city":"Tournai",
    "sg:orig_category":"Epiceries",
    "sg:phone":"+32 69 22 13 64",
    "sg:postcode":"7500",
    "sg:province":"Hainaut",
    "wof:name":"Aimee Lecrocq",
    "wof:placetype":"venue"
},
  "geometry": {"coordinates":[3.388092041,50.6168518066],"type":"Point"}
}