{
  "type": "Feature",
  "properties": {
    "addr:full":"Zonnebloemstraat 7 Olen Antwerpen 2250",
    "addr:housenumber":"7",
    "addr:postcode":"2250",
    "addr:street":"Zonnebloemstraat",
    "iso:country":"BE",
    "sg:address":"Zonnebloemstraat 7",
    "sg:city":"Olen",
    "sg:classifiers":[
        {
            "category":"Health Services",
            "subcategory":"Nursing And Care Facility",
            "type":"Services"
        }
    ],
    "sg:phone":"+32 14 23 74 49",
    "sg:postcode":"2250",
    "sg:province":"Antwerpen",
    "sg:tags":[
        "home"
    ],
    "wof:name":"Peeters K",
    "wof:placetype":"venue"
},
  "geometry": {"coordinates":[4.8965988159,51.1676750183],"type":"Point"}
}