{
  "type": "Feature",
  "properties": {
    "addr:full":"Rue Du Bois 281 Tournai (havinnes) Hainaut 7531",
    "addr:housenumber":"281",
    "addr:postcode":"7531",
    "addr:street":"Rue Du Bois",
    "iso:country":"BE",
    "sg:address":"Rue Du Bois 281",
    "sg:city":"Tournai (havinnes)",
    "sg:classifiers":[
        {
            "category":"Insurance",
            "subcategory":"Insurance Agent",
            "type":"Services"
        }
    ],
    "sg:phone":"+32 69 54 80 82",
    "sg:postcode":"7531",
    "sg:province":"Hainaut",
    "sg:tags":[
        "broker"
    ],
    "wof:name":"Faignart A",
    "wof:placetype":"venue"
},
  "geometry": {"coordinates":[3.4616699219,50.6152877808],"type":"Point"}
}