{
  "type": "Feature",
  "properties": {
    "addr:full":"Sint-jansbergsesteenweg 81 Leuven (heverlee) Vlaams-Brabant 3001",
    "addr:housenumber":"81",
    "addr:postcode":"3001",
    "addr:street":"Sint-Jansbergsesteenweg",
    "iso:country":"BE",
    "sg:address":"Sint-jansbergsesteenweg 81",
    "sg:city":"Leuven (heverlee)",
    "sg:classifiers":[
        {
            "category":"Personal",
            "subcategory":"Beauty Salon",
            "type":"Services"
        }
    ],
    "sg:phone":"+32 16 23 08 20",
    "sg:postcode":"3001",
    "sg:province":"Vlaams-Brabant",
    "sg:tags":[
        "lady",
        "-",
        "hairdressing"
    ],
    "wof:name":"Jacobs D",
    "wof:placetype":"venue"
},
  "geometry": {"coordinates":[4.6659030914,50.8695831299],"type":"Point"}
}