{
  "type": "Feature",
  "properties": {
    "iso:country":"BE",
    "sg:address":"Assenedesteenweg 241",
    "sg:city":"Zelzate",
    "sg:orig_category":"Fietsen",
    "sg:phone":"+32 9 344 57 88",
    "sg:postcode":"9060",
    "sg:province":"Oost-Vlaanderen",
    "wof:name":"K. Van De Veire",
    "wof:placetype":"venue"
},
  "geometry": {"coordinates":[3.782075882,51.2028656006],"type":"Point"}
}