{
  "type": "Feature",
  "properties": {
    "iso:country":"BE",
    "sg:address":"Ketegemstraat 11",
    "sg:city":"Herzele (borsbeke)",
    "sg:classifiers":[
        {
            "category":"Manufacturing",
            "subcategory":"Tools & Machinery",
            "type":"Manufacturing & Wholesale Goods"
        }
    ],
    "sg:phone":"+32 53 60 30 54",
    "sg:postcode":"9552",
    "sg:province":"Oost-Vlaanderen",
    "sg:tags":[
        "-"
    ],
    "wof:name":"Dafco-nupla Nv",
    "wof:placetype":"venue"
},
  "geometry": {"coordinates":[3.9016311169,50.9062690735],"type":"Point"}
}