{
  "type": "Feature",
  "properties": {
    "addr:full":"Voie G\u00e9n\u00e9ral Bl\u00fccher 21 Wavre Brabant Wallon 1300",
    "addr:housenumber":"21;1300",
    "addr:street":"Voie Ge\u0301Ne\u0301Ral Bluecher",
    "iso:country":"BE",
    "sg:address":"Voie G\u00e9n\u00e9ral Bl\u00fccher 21",
    "sg:city":"Wavre",
    "sg:classifiers":[
        {
            "category":"Professional",
            "subcategory":"Accounting & Tax Preparation",
            "type":"Services"
        }
    ],
    "sg:phone":"+32 10 45 42 44",
    "sg:postcode":"1300",
    "sg:province":"Brabant Wallon",
    "sg:tags":[
        "bookkeeper"
    ],
    "wof:name":"Santin J",
    "wof:placetype":"venue"
},
  "geometry": {"coordinates":[4.6187930107,50.6890220642],"type":"Point"}
}