{
  "type": "Feature",
  "properties": {
    "iso:country":"BE",
    "sg:address":"Avenue Des Saisons 88",
    "sg:city":"Bruxelles (ixelles)",
    "sg:classifiers":[
        {
            "category":"Home & Garden",
            "subcategory":"Carpets & Floor Coverings",
            "type":"Retail Goods"
        }
    ],
    "sg:phone":"+32 2 648 43 05",
    "sg:postcode":"1050",
    "sg:province":"Bruxelles-Capitale",
    "sg:tags":[
        "-",
        "rug"
    ],
    "wof:name":"Spietz L Sa",
    "wof:placetype":"venue"
},
  "geometry": {"coordinates":[4.3879480362,50.8183822632],"type":"Point"}
}