{
  "type": "Feature",
  "properties": {
    "iso:country":"BE",
    "sg:address":"Gyselstraat 21",
    "sg:city":"Sint-niklaas",
    "sg:orig_category":"M\u00e9decins and sp\u00e9cialistes",
    "sg:phone":"+32 3 776 77 76",
    "sg:postcode":"9100",
    "sg:province":"Oost-Vlaanderen",
    "wof:name":"Carine De Rop",
    "wof:placetype":"venue"
},
  "geometry": {"coordinates":[4.1773810387,51.1944084167],"type":"Point"}
}