{
  "type": "Feature",
  "properties": {
    "iso:country":"BE",
    "sg:address":"Abtsulstraat 5ba",
    "sg:city":"Harelbeke",
    "sg:orig_category":"Rundveehouders Voedingsspeciaalzaken",
    "sg:phone":"+32 56 71 48 05",
    "sg:postcode":"8531",
    "sg:province":"West-Vlaanderen",
    "wof:name":"Johan Vancoillie",
    "wof:placetype":"venue"
},
  "geometry": {"coordinates":[3.2829709053,50.8856811523],"type":"Point"}
}