{
  "type": "Feature",
  "properties": {
    "addr:full":"Zilverstraat 43 Schoten Antwerpen 2900",
    "addr:housenumber":"43",
    "addr:postcode":"2900",
    "addr:street":"Zilverstraat",
    "iso:country":"BE",
    "sg:address":"Zilverstraat 43",
    "sg:city":"Schoten",
    "sg:classifiers":[
        {
            "category":"Arena",
            "subcategory":"Sports Club",
            "type":"Entertainment"
        }
    ],
    "sg:phone":"+32 3 658 66 61",
    "sg:postcode":"2900",
    "sg:province":"Antwerpen",
    "wof:name":"F C Koningshof Vzw",
    "wof:placetype":"venue"
},
  "geometry": {"coordinates":[4.5264849663,51.2648468018],"type":"Point"}
}