{
  "type": "Feature",
  "properties": {
    "iso:country":"BE",
    "sg:address":"Begoniastraat 11",
    "sg:city":"Nazareth (eke)",
    "sg:classifiers":[
        {
            "category":"Shopping",
            "subcategory":"Clothing, Apparel, & Fashions",
            "type":"Retail Goods"
        }
    ],
    "sg:phone":"+32 9 385 57 51",
    "sg:postcode":"9810",
    "sg:province":"Oost-Vlaanderen",
    "sg:tags":[
        "zipper"
    ],
    "wof:name":"Ykk Belgium Nv",
    "wof:placetype":"venue"
},
  "geometry": {"coordinates":[3.6602780819,50.9754562378],"type":"Point"}
}