{
  "type": "Feature",
  "properties": {
    "addr:full":"Dorp West 52 Zwijndrecht Antwerpen 2070",
    "addr:housenumber":"52",
    "addr:postcode":"2070",
    "addr:street":"Dorp West",
    "iso:country":"BE",
    "sg:address":"Dorp West 52",
    "sg:city":"Zwijndrecht",
    "sg:orig_category":"Electrom\u00e9nager, t\u00e9l\u00e9visions and radios",
    "sg:phone":"+32 3 252 71 87",
    "sg:postcode":"2070",
    "sg:province":"Antwerpen",
    "wof:name":"Georges Van Den Broeck",
    "wof:placetype":"venue"
},
  "geometry": {"coordinates":[4.322991848,51.2189331055],"type":"Point"}
}