{
  "type": "Feature",
  "properties": {
    "addr:full":"Wezestraat 23 Ardooie West-Vlaanderen 8850",
    "addr:housenumber":"23",
    "addr:postcode":"8850",
    "addr:street":"Wezestraat",
    "iso:country":"BE",
    "sg:address":"Wezestraat 23",
    "sg:city":"Ardooie",
    "sg:classifiers":[
        {
            "category":"Farming",
            "subcategory":"Poultry Farm",
            "type":"Manufacturing & Wholesale Goods"
        }
    ],
    "sg:phone":"+32 51 74 41 04",
    "sg:postcode":"8850",
    "sg:province":"West-Vlaanderen",
    "sg:tags":[
        "rabbit",
        "slaughterhouse"
    ],
    "wof:name":"Defraeye Pluimvee Slachterij",
    "wof:placetype":"venue"
},
  "geometry": {"coordinates":[3.2056379318,50.9728851318],"type":"Point"}
}