{
  "type": "Feature",
  "properties": {
    "iso:country":"BE",
    "sg:address":"Konijntje 2",
    "sg:city":"Knesselare",
    "sg:classifiers":[
        {
            "category":"Shopping",
            "subcategory":"Clothing, Apparel, & Fashions",
            "type":"Retail Goods"
        }
    ],
    "sg:phone":"+32 9 375 10 55",
    "sg:postcode":"9910",
    "sg:province":"Oost-Vlaanderen",
    "sg:tags":[
        "v\u00eatements",
        "pour",
        "dame"
    ],
    "wof:name":"Huis Carine B.",
    "wof:placetype":"venue"
},
  "geometry": {"coordinates":[3.503964901,51.1317062378],"type":"Point"}
}