{
  "type": "Feature",
  "properties": {
    "addr:full":"Avenue Des Pagodes 443 Bruxelles Bruxelles-Capitale 1020",
    "addr:housenumber":"443",
    "addr:postcode":"1020",
    "addr:street":"Avenue Des Pagodes",
    "iso:country":"BE",
    "sg:address":"Avenue Des Pagodes 443",
    "sg:city":"Bruxelles",
    "sg:orig_category":"Imitation jewelry - Mfg.& Whol.",
    "sg:phone":"+32 2 268 64 86",
    "sg:postcode":"1020",
    "sg:province":"Bruxelles-Capitale",
    "wof:name":"Sulevia Creation",
    "wof:placetype":"venue"
},
  "geometry": {"coordinates":[4.3566908836,50.8957595825],"type":"Point"}
}