{
  "type": "Feature",
  "properties": {
    "iso:country":"BE",
    "sg:address":"Rue Fran\u00e7ois Dorz\u00e9e 54",
    "sg:city":"Boussu",
    "sg:classifiers":[
        {
            "category":"Personal",
            "subcategory":"Beauty Salon",
            "type":"Services"
        }
    ],
    "sg:phone":"+32 65 77 03 91",
    "sg:postcode":"7300",
    "sg:province":"Hainaut",
    "wof:name":"Jouvence",
    "wof:placetype":"venue"
},
  "geometry": {"coordinates":[3.8000309467,50.4333839417],"type":"Point"}
}