{
  "type": "Feature",
  "properties": {
    "addr:full":"Rue Des Ardennes 476 Beauraing (winenne) Namur 5570",
    "addr:housenumber":"476",
    "addr:postcode":"5570",
    "addr:street":"Rue Des Ardennes",
    "iso:country":"BE",
    "sg:address":"Rue Des Ardennes 476",
    "sg:city":"Beauraing (winenne)",
    "sg:classifiers":[
        {
            "category":"Farming",
            "subcategory":"Farm & Veterinary Services",
            "type":"Manufacturing & Wholesale Goods"
        }
    ],
    "sg:phone":"+32 82 71 26 35",
    "sg:postcode":"5570",
    "sg:province":"Namur",
    "sg:tags":[
        "agricultural",
        "contractor"
    ],
    "wof:name":"Rolot & Fils Sa",
    "wof:placetype":"venue"
},
  "geometry": {"coordinates":[4.9469399452,50.1016616821],"type":"Point"}
}