{
  "type": "Feature",
  "properties": {
    "addr:full":"Opperveldlaan 11 Vilvoorde Vlaams-Brabant 1800",
    "addr:housenumber":"11",
    "addr:postcode":"1800",
    "addr:street":"Opperveldlaan",
    "iso:country":"BE",
    "sg:address":"Opperveldlaan 11",
    "sg:city":"Vilvoorde",
    "sg:classifiers":[
        {
            "category":"Health Services",
            "subcategory":"Health Practitioner",
            "type":"Services"
        }
    ],
    "sg:phone":"+32 2 267 54 75",
    "sg:postcode":"1800",
    "sg:province":"Vlaams-Brabant",
    "sg:tags":[
        "physiotherapist"
    ],
    "wof:name":"De Pauw Jeannine",
    "wof:placetype":"venue"
},
  "geometry": {"coordinates":[4.372961998,50.9132652283],"type":"Point"}
}