{
  "type": "Feature",
  "properties": {
    "iso:country":"BE",
    "sg:address":"Rue De Marchienne 157",
    "sg:city":"Thuin (goz\u00e9e)",
    "sg:classifiers":[
        {
            "category":"Autos & Motor Vehicles",
            "subcategory":"Automobile Sales",
            "type":"Retail Goods"
        }
    ],
    "sg:phone":"+32 71 51 15 05",
    "sg:postcode":"6534",
    "sg:province":"Hainaut",
    "sg:tags":[
        "car",
        "used",
        "-"
    ],
    "wof:name":"Jmp Cars",
    "wof:placetype":"venue"
},
  "geometry": {"coordinates":[4.3637452126,50.3505439758],"type":"Point"}
}