{
  "type": "Feature",
  "properties": {
    "iso:country":"BE",
    "sg:address":"Chauss\u00c9e D'ixelles 63",
    "sg:city":"Bruxelles",
    "sg:classifiers":[
        {
            "category":"Wholesale",
            "subcategory":"Sporting Goods",
            "type":"Manufacturing & Wholesale Goods"
        }
    ],
    "sg:phone":"+32 2 511 50 22",
    "sg:postcode":"1050",
    "sg:province":"Bruxelles-Capitale",
    "sg:tags":[
        "sport-",
        "kampeermateriaal"
    ],
    "wof:name":"Di-sport",
    "wof:placetype":"venue"
},
  "geometry": {"coordinates":[4.3627791405,50.8362121582],"type":"Point"}
}