{
  "type": "Feature",
  "properties": {
    "iso:country":"BE",
    "sg:address":"Boulevard D\u00b4avroy 3b22",
    "sg:city":"Li\u00c8ge",
    "sg:orig_category":"Organisatie van beurzen, congressen and tentoonstellingen",
    "sg:phone":"+32 4 221 21 26",
    "sg:postcode":"4000",
    "sg:province":"Li\u00e8ge",
    "wof:name":"Etude & Expansion",
    "wof:placetype":"venue"
},
  "geometry": {"coordinates":[5.5690932274,50.6400566101],"type":"Point"}
}