{
  "type": "Feature",
  "properties": {
    "addr:full":"Kooistraat 20 Evergem Oost-Vlaanderen 9940",
    "addr:housenumber":"20",
    "addr:postcode":"9940",
    "addr:street":"Kooistraat;Oost-Vlaanderen",
    "iso:country":"BE",
    "sg:address":"Kooistraat 20",
    "sg:city":"Evergem",
    "sg:orig_category":"Travaux de finition and nettoyage de b\u00e2timents",
    "sg:phone":"+32 9 253 54 64",
    "sg:postcode":"9940",
    "sg:province":"Oost-Vlaanderen",
    "wof:name":"Filip Claeys",
    "wof:placetype":"venue"
},
  "geometry": {"coordinates":[3.7666530609,51.1350746155],"type":"Point"}
}