{
  "type": "Feature",
  "properties": {
    "iso:country":"BE",
    "sg:address":"Rode-kruisstraat 9",
    "sg:city":"Lebbeke",
    "sg:orig_category":"Epiceries",
    "sg:phone":"+32 52 41 20 06",
    "sg:postcode":"9280",
    "sg:province":"Oost-Vlaanderen",
    "wof:name":"Shopwell",
    "wof:placetype":"venue"
},
  "geometry": {"coordinates":[4.0930700302,51.0034370422],"type":"Point"}
}