{
  "type": "Feature",
  "properties": {
    "iso:country":"BE",
    "sg:address":"Hoge Heideweg 106",
    "sg:city":"Rijkevorsel",
    "sg:orig_category":"MEUBELONTWERP AND -INSTALLATIE",
    "sg:phone":"+32 3 314 40 22",
    "sg:postcode":"2310",
    "sg:province":"Antwerpen",
    "wof:name":"Keukens Van De Mierop",
    "wof:placetype":"venue"
},
  "geometry": {"coordinates":[4.7854909897,51.3365364075],"type":"Point"}
}