{
  "type": "Feature",
  "properties": {
    "iso:country":"BE",
    "sg:address":"Rue Du Menil 89",
    "sg:city":"Braine-l`alleud",
    "sg:orig_category":"Kapsalons",
    "sg:phone":"+32 2 384 19 11",
    "sg:postcode":"1420",
    "sg:province":"Brabant Wallon",
    "wof:name":"Espace Coiffure",
    "wof:placetype":"venue"
},
  "geometry": {"coordinates":[4.3832921982,50.6882743835],"type":"Point"}
}