{
  "type": "Feature",
  "properties": {
    "iso:country":"BE",
    "sg:address":"Mouthorenstweg 58",
    "sg:city":"Aarschot",
    "sg:orig_category":"Entretien and r\u00e9parations de voitures",
    "sg:phone":"+32 13 77 22 91",
    "sg:postcode":"3201",
    "sg:province":"Vlaams-Brabant",
    "wof:name":"Mazda",
    "wof:placetype":"venue"
},
  "geometry": {"coordinates":[4.8698401451,50.9937286377],"type":"Point"}
}