{
  "type": "Feature",
  "properties": {
    "iso:country":"BE",
    "sg:address":"Clos Du Lac 91",
    "sg:city":"Wasseiges",
    "sg:classifiers":[
        {
            "category":"Education",
            "subcategory":"Special Training",
            "type":"Public Place"
        }
    ],
    "sg:phone":"+32 81 43 57 40",
    "sg:postcode":"4219",
    "sg:province":"Li\u00e8ge",
    "sg:tags":[
        "school",
        "flying"
    ],
    "wof:name":"Waucquez N",
    "wof:placetype":"venue"
},
  "geometry": {"coordinates":[4.9935002327,50.6220397949],"type":"Point"}
}