{
  "type": "Feature",
  "properties": {
    "addr:full":"Blankenbergse Steenweg 195 Brugge West-Vlaanderen 8000",
    "addr:housenumber":"195",
    "addr:postcode":"8000",
    "addr:street":"Blankenbergse Steenweg",
    "iso:country":"BE",
    "sg:address":"Blankenbergse Steenweg 195",
    "sg:city":"Brugge",
    "sg:orig_category":"Avocats and conseillers juridiques",
    "sg:phone":"+32 50 31 74 50",
    "sg:postcode":"8000",
    "sg:province":"West-Vlaanderen",
    "wof:name":"I. Costers",
    "wof:placetype":"venue"
},
  "geometry": {"coordinates":[3.2012999058,51.2372512817],"type":"Point"}
}