{
  "type": "Feature",
  "properties": {
    "addr:full":"Hoogstraat 397 Brussel/bruxelles Bruxelles-Capitale 1000",
    "addr:housenumber":"397",
    "addr:postcode":"1000",
    "addr:street":"Hoogstraat;/",
    "iso:country":"BE",
    "sg:address":"Hoogstraat 397",
    "sg:city":"Brussel/bruxelles",
    "sg:classifiers":[
        {
            "category":"Restaurant",
            "type":"Food & Drink"
        }
    ],
    "sg:phone":"+32 2 538 04 14",
    "sg:postcode":"1000",
    "sg:province":"Bruxelles-Capitale",
    "wof:name":"Restaurant Mar Bravo",
    "wof:placetype":"venue"
},
  "geometry": {"coordinates":[4.344933033,50.8337211609],"type":"Point"}
}