{
  "type": "Feature",
  "properties": {
    "iso:country":"BE",
    "sg:address":"Gasthuisstraat 42",
    "sg:city":"Geel",
    "sg:orig_category":"Cr\u00e9meries",
    "sg:phone":"+32 14 58 90 62",
    "sg:postcode":"2440",
    "sg:province":"Antwerpen",
    "wof:name":"L. Geukens",
    "wof:placetype":"venue"
},
  "geometry": {"coordinates":[4.9976191521,51.1600646973],"type":"Point"}
}