{
  "type": "Feature",
  "properties": {
    "iso:country":"BE",
    "sg:address":"Rue De La Roue 14-16",
    "sg:city":"Bruxelles",
    "sg:orig_category":"Non-Classified Establishments",
    "sg:phone":"+32 2 512 78 53",
    "sg:postcode":"1000",
    "sg:province":"Bruxelles-Capitale",
    "wof:name":"Nissim Sa",
    "wof:placetype":"venue"
},
  "geometry": {"coordinates":[4.3460049629,50.8419494629],"type":"Point"}
}