{
  "type": "Feature",
  "properties": {
    "iso:country":"BE",
    "sg:address":"Gorsemweg 5",
    "sg:city":"Sint-truiden",
    "sg:classifiers":[
        {
            "category":"Fast Food",
            "type":"Food & Drink"
        }
    ],
    "sg:phone":"+32 11 67 22 79",
    "sg:postcode":"3800",
    "sg:province":"Limburg",
    "sg:tags":[
        "\u00c0",
        "emporter",
        "restaurants"
    ],
    "wof:name":"Pizza La Fontanella",
    "wof:placetype":"venue"
},
  "geometry": {"coordinates":[5.1815981865,50.8192024231],"type":"Point"}
}