{
  "type": "Feature",
  "properties": {
    "addr:full":"Avenue De B\u00e2le 7 Bruxelles (evere) Bruxelles-Capitale 1140",
    "addr:housenumber":"7",
    "addr:postcode":"1140",
    "addr:street":"Avenue De Ba\u0302Le",
    "iso:country":"BE",
    "sg:address":"Avenue De B\u00e2le 7",
    "sg:city":"Bruxelles (evere)",
    "sg:classifiers":[
        {
            "category":"Professional",
            "subcategory":"Detective & Security Services",
            "type":"Services"
        }
    ],
    "sg:phone":"+32 2 726 99 10",
    "sg:postcode":"1140",
    "sg:province":"Bruxelles-Capitale",
    "sg:tags":[
        "-",
        "system",
        "apparatus",
        "surveillance"
    ],
    "wof:name":"Euromatec Sa",
    "wof:placetype":"venue"
},
  "geometry": {"coordinates":[4.4177041054,50.8745307922],"type":"Point"}
}