{
  "type": "Feature",
  "properties": {
    "addr:full":"Rue Du Manoir 38 Perwez (mal\u00e8ves-sainte-marie-wastines) Brabant Wallon 1360",
    "addr:housenumber":"38",
    "addr:postcode":"1360",
    "addr:street":"Rue Du Manoir;Wallon",
    "iso:country":"BE",
    "sg:address":"Rue Du Manoir 38",
    "sg:city":"Perwez (mal\u00e8ves-sainte-marie-wastines)",
    "sg:classifiers":[
        {
            "category":"Building & Trades",
            "subcategory":"Construction",
            "type":"Services"
        }
    ],
    "sg:phone":"+32 10 24 46 44",
    "sg:postcode":"1360",
    "sg:province":"Brabant Wallon",
    "sg:tags":[
        "surveyor",
        "-"
    ],
    "wof:name":"Bureau D'expertise Coppe",
    "wof:placetype":"venue"
},
  "geometry": {"coordinates":[4.7991099358,50.6666946411],"type":"Point"}
}