{
  "type": "Feature",
  "properties": {
    "iso:country":"BE",
    "sg:address":"Route De Cierreux 7",
    "sg:city":"Vielsalm (bihain)",
    "sg:classifiers":[
        {
            "category":"Building & Trades",
            "subcategory":"Landscaping Services",
            "type":"Services"
        }
    ],
    "sg:phone":"+32 80 21 59 66",
    "sg:postcode":"6690",
    "sg:province":"Luxembourg",
    "sg:tags":[
        "forestry"
    ],
    "wof:name":"Henquinet Denis Sprl",
    "wof:placetype":"venue"
},
  "geometry": {"coordinates":[5.904900074,50.2578010559],"type":"Point"}
}