{
  "type": "Feature",
  "properties": {
    "addr:full":"Rue Sainte-walburge 244 Li\u00e8ge 1 Li\u00e8ge 4000",
    "addr:housenumber":"244;1",
    "addr:postcode":"4000",
    "addr:street":"Rue Sainte-Walburge",
    "iso:country":"BE",
    "sg:address":"Rue Sainte-walburge 244",
    "sg:city":"Li\u00e8ge 1",
    "sg:classifiers":[
        {
            "category":"Community Center",
            "type":"Public Place"
        }
    ],
    "sg:phone":"+32 4 226 74 06",
    "sg:postcode":"4000",
    "sg:province":"Li\u00e8ge",
    "sg:tags":[
        "medical"
    ],
    "wof:name":"Centre M\u00e9dical Des Hauteurs",
    "wof:placetype":"venue"
},
  "geometry": {"coordinates":[5.5667009354,50.659614563],"type":"Point"}
}