{
  "type": "Feature",
  "properties": {
    "addr:full":"Houba De Strooperlaan 618 Brussel/bruxelles Bruxelles-Capitale 1020",
    "addr:housenumber":"618",
    "addr:postcode":"1020",
    "addr:street":"Houba De Strooperlaan;/",
    "iso:country":"BE",
    "sg:address":"Houba De Strooperlaan 618",
    "sg:city":"Brussel/bruxelles",
    "sg:orig_category":"Foto-uitrusting Fotografen and fotostudio's",
    "sg:phone":"+32 2 479 34 23",
    "sg:postcode":"1020",
    "sg:province":"Bruxelles-Capitale",
    "wof:name":"Color'in",
    "wof:placetype":"venue"
},
  "geometry": {"coordinates":[4.3303341866,50.8948707581],"type":"Point"}
}