{
  "type": "Feature",
  "properties": {
    "addr:full":"Chauss\u00e9e De Louvain 15 Box 4 Beauvechain (hamme-mille) Brabant Wallon 1320",
    "addr:housenumber":"15;4",
    "addr:postcode":"1320",
    "addr:street":"Chausse\u0301E De Louvain;Box",
    "iso:country":"BE",
    "sg:address":"Chauss\u00e9e De Louvain 15 Box 4",
    "sg:city":"Beauvechain (hamme-mille)",
    "sg:classifiers":[
        {
            "category":"Health Services",
            "subcategory":"Health Practitioner",
            "type":"Services"
        }
    ],
    "sg:phone":"+32 10 86 09 38",
    "sg:postcode":"1320",
    "sg:province":"Brabant Wallon",
    "sg:tags":[
        "therapist",
        "speech"
    ],
    "wof:name":"Vanden Durpel",
    "wof:placetype":"venue"
},
  "geometry": {"coordinates":[4.7921929359,50.7808570862],"type":"Point"}
}