{
  "type": "Feature",
  "properties": {
    "addr:full":"Bankstraat 5 Kruishoutem Oost-Vlaanderen 9770",
    "addr:housenumber":"5",
    "addr:postcode":"9770",
    "addr:street":"Bankstraat",
    "iso:country":"BE",
    "sg:address":"Bankstraat 5",
    "sg:city":"Kruishoutem",
    "sg:orig_category":"Loodgieterij, verwarming and sanitaire installaties",
    "sg:phone":"+32 9 383 58 82",
    "sg:postcode":"9770",
    "sg:province":"Oost-Vlaanderen",
    "wof:name":"H. Putman",
    "wof:placetype":"venue"
},
  "geometry": {"coordinates":[3.5273098946,50.9130363464],"type":"Point"}
}