{
  "type": "Feature",
  "properties": {
    "addr:full":"Dix Bonniers 40 Marchin Li\u00e8ge 4570",
    "addr:housenumber":"40",
    "addr:postcode":"4570",
    "addr:street":"Dix Bonniers",
    "iso:country":"BE",
    "sg:address":"Dix Bonniers 40",
    "sg:city":"Marchin",
    "sg:classifiers":[
        {
            "category":"Personal",
            "subcategory":"Nail Salon",
            "type":"Services"
        }
    ],
    "sg:phone":"+32 85 23 26 35",
    "sg:postcode":"4570",
    "sg:province":"Li\u00e8ge",
    "sg:tags":[
        "pedicure"
    ],
    "wof:name":"Drianne A",
    "wof:placetype":"venue"
},
  "geometry": {"coordinates":[5.2309598923,50.4823417664],"type":"Point"}
}