{
  "type": "Feature",
  "properties": {
    "iso:country":"BE",
    "sg:address":"Ketelstraat 20",
    "sg:city":"Zoutleeuw",
    "sg:orig_category":"Producteurs de fruits",
    "sg:phone":"+32 11 58 83 07",
    "sg:postcode":"3440",
    "sg:province":"Vlaams-Brabant",
    "wof:name":"Rudy Sempels",
    "wof:placetype":"venue"
},
  "geometry": {"coordinates":[5.0679540634,50.8739852905],"type":"Point"}
}