{
  "type": "Feature",
  "properties": {
    "addr:full":"Lambroekstr 50 Wetteren Oost-Vlaanderen 9230",
    "addr:housenumber":"50",
    "addr:postcode":"9230",
    "addr:street":"Lambroekstr",
    "iso:country":"BE",
    "sg:address":"Lambroekstr 50",
    "sg:city":"Wetteren",
    "sg:classifiers":[
        {
            "category":"Travel",
            "subcategory":"Hotels & Motels",
            "type":"Entertainment"
        }
    ],
    "sg:phone":"+32 9 369 13 72",
    "sg:postcode":"9230",
    "sg:province":"Oost-Vlaanderen",
    "sg:tags":[
        "hotels",
        "business",
        "restaurant"
    ],
    "wof:name":"Bossaert Lucien Georges M.",
    "wof:placetype":"venue"
},
  "geometry": {"coordinates":[3.8855400085,51.0070304871],"type":"Point"}
}