{
  "type": "Feature",
  "properties": {
    "iso:country":"BE",
    "sg:address":"Rue Des Gris 7",
    "sg:city":"Charleroi",
    "sg:orig_category":"Services de Nettoyage and de D\u00e9sinfection. Construction de maisons",
    "sg:phone":"+32 71 33 35 52",
    "sg:postcode":"6061",
    "sg:province":"Hainaut",
    "wof:name":"La Delfa A.",
    "wof:placetype":"venue"
},
  "geometry": {"coordinates":[4.460477829,50.4087104797],"type":"Point"}
}