{
  "type": "Feature",
  "properties": {
    "iso:country":"BE",
    "sg:address":"Sportveldenstraat 10",
    "sg:city":"Lommel",
    "sg:orig_category":"Cafetarias and selfservice restaurants",
    "sg:phone":"+32 11 55 13 17",
    "sg:postcode":"3920",
    "sg:province":"Limburg",
    "wof:name":"Speeltuin",
    "wof:placetype":"venue"
},
  "geometry": {"coordinates":[5.3058738708,51.2443733215],"type":"Point"}
}