{
  "type": "Feature",
  "properties": {
    "addr:full":"Kluizensesteenweg 1 Gent Oost-Vlaanderen 9000",
    "addr:housenumber":"1",
    "addr:postcode":"9000",
    "addr:street":"Kluizensesteenweg;Oost-Vlaanderen",
    "iso:country":"BE",
    "sg:address":"Kluizensesteenweg 1",
    "sg:city":"Gent",
    "sg:orig_category":"Hout and afgeleiden Gh IJzerwaren, bouw- and verfmaterialen",
    "sg:phone":"+32 9 253 16 71",
    "sg:postcode":"9000",
    "sg:province":"Oost-Vlaanderen",
    "wof:name":"Van Hoorebeke Panels",
    "wof:placetype":"venue"
},
  "geometry": {"coordinates":[3.7398269176,51.1128234863],"type":"Point"}
}