{
  "type": "Feature",
  "properties": {
    "addr:full":"Edouard De Thibaultlaan 51 Etterbeek Bruxelles-Capitale 1040",
    "addr:housenumber":"51",
    "addr:postcode":"1040",
    "addr:street":"Edouard De Thibaultlaan",
    "iso:country":"BE",
    "sg:address":"Edouard De Thibaultlaan 51",
    "sg:city":"Etterbeek",
    "sg:orig_category":"Kapsalons",
    "sg:phone":"+32 2 736 84 17",
    "sg:postcode":"1040",
    "sg:province":"Bruxelles-Capitale",
    "wof:name":"Robert Theys",
    "wof:placetype":"venue"
},
  "geometry": {"coordinates":[4.3977689743,50.8334465027],"type":"Point"}
}