{
  "type": "Feature",
  "properties": {
    "iso:country":"BE",
    "sg:address":"Rue Saint-martin 16",
    "sg:city":"Tournai",
    "sg:orig_category":"Boucheries",
    "sg:phone":"+32 69 22 43 84",
    "sg:postcode":"7500",
    "sg:province":"Hainaut",
    "wof:name":"Guy De Clercq",
    "wof:placetype":"venue"
},
  "geometry": {"coordinates":[3.3952829838,50.591293335],"type":"Point"}
}