{
  "type": "Feature",
  "properties": {
    "addr:full":"Hasseltsebaan 3 Hechtel-eksel Limburg 3940",
    "addr:housenumber":"3",
    "addr:postcode":"3940",
    "addr:street":"Hasseltsebaan",
    "iso:country":"BE",
    "sg:address":"Hasseltsebaan 3",
    "sg:city":"Hechtel-eksel",
    "sg:classifiers":[
        {
            "category":"Fast Food",
            "type":"Food & Drink"
        }
    ],
    "sg:phone":"+32 11 73 37 04",
    "sg:postcode":"3940",
    "sg:province":"Limburg",
    "sg:tags":[
        "\u00c0",
        "restaurants",
        "emporter",
        "restaurant"
    ],
    "wof:name":"Jumbo",
    "wof:placetype":"venue"
},
  "geometry": {"coordinates":[5.3750371933,51.0968093872],"type":"Point"}
}