{
  "type": "Feature",
  "properties": {
    "iso:country":"BE",
    "sg:address":"Van Wesemaelstraat 10",
    "sg:city":"Westerlo",
    "sg:classifiers":[
        {
            "category":"Professional",
            "subcategory":"Management & Consulting",
            "type":"Services"
        }
    ],
    "sg:phone":"+32 14 54 93 83",
    "sg:postcode":"2260",
    "sg:province":"Antwerpen",
    "sg:tags":[
        "-",
        "processing",
        "data",
        "consultant"
    ],
    "wof:name":"Mdb-it Bvba",
    "wof:placetype":"venue"
},
  "geometry": {"coordinates":[4.9140100479,51.0840187073],"type":"Point"}
}