{
  "type": "Feature",
  "properties": {
    "iso:country":"BE",
    "sg:address":"Raamstraat 49",
    "sg:city":"Eeklo",
    "sg:orig_category":"Meubelzaken, woning- and keukeninrichting",
    "sg:phone":"+32 9 377 29 78",
    "sg:postcode":"9900",
    "sg:province":"Oost-Vlaanderen",
    "wof:name":"Roger Hellebuyck",
    "wof:placetype":"venue"
},
  "geometry": {"coordinates":[3.568584919,51.1855049133],"type":"Point"}
}