{
  "type": "Feature",
  "properties": {
    "iso:country":"BE",
    "sg:address":"Dorpstraat 9",
    "sg:city":"Londerzeel",
    "sg:orig_category":"Mat\u00e9riel de T\u00e9l\u00e9communication. Installation \u00e9lectrique r\u00e9sidentielle. Electrom\u00e9nager, t\u00e9l\u00e9visions an",
    "sg:phone":"+32 52 30 93 23",
    "sg:postcode":"1840",
    "sg:province":"Vlaams-Brabant",
    "wof:name":"De Decker",
    "wof:placetype":"venue"
},
  "geometry": {"coordinates":[4.3025608063,51.0035934448],"type":"Point"}
}