{
  "type": "Feature",
  "properties": {
    "iso:country":"BE",
    "sg:address":"Rue De L'etang 13",
    "sg:city":"Beauvechain",
    "sg:orig_category":"Eleveurs de bovins",
    "sg:phone":"+32 10 86 63 01",
    "sg:postcode":"1320",
    "sg:province":"Brabant Wallon",
    "wof:name":"Albert Uytterhoeven",
    "wof:placetype":"venue"
},
  "geometry": {"coordinates":[4.7732701302,50.7803611755],"type":"Point"}
}