{
  "type": "Feature",
  "properties": {
    "addr:full":"J. Van Biesbroeckstraat 119 Gent Oost-Vlaanderen 9050",
    "addr:housenumber":"119",
    "addr:postcode":"9050",
    "addr:street":"J. Van Biesbroeckstraat;Oost-Vlaanderen",
    "iso:country":"BE",
    "sg:address":"J. Van Biesbroeckstraat 119",
    "sg:city":"Gent",
    "sg:orig_category":"Enseignement maternel and primaire",
    "sg:phone":"+32 9 230 95 68",
    "sg:postcode":"9050",
    "sg:province":"Oost-Vlaanderen",
    "wof:name":"Vrije Basisschool",
    "wof:placetype":"venue"
},
  "geometry": {"coordinates":[3.7589480877,51.0448532104],"type":"Point"}
}