{
  "type": "Feature",
  "properties": {
    "addr:full":"Rozenlaan 6 Sint-niklaas Oost-Vlaanderen 9111",
    "addr:housenumber":"6",
    "addr:postcode":"9111",
    "addr:street":"Rozenlaan",
    "iso:country":"BE",
    "sg:address":"Rozenlaan 6",
    "sg:city":"Sint-niklaas",
    "sg:orig_category":"Brood, gebak and snoepgoed",
    "sg:phone":"+32 3 772 12 99",
    "sg:postcode":"9111",
    "sg:province":"Oost-Vlaanderen",
    "wof:name":"Patisserie De Roos",
    "wof:placetype":"venue"
},
  "geometry": {"coordinates":[4.0967278481,51.1468963623],"type":"Point"}
}