{
  "type": "Feature",
  "properties": {
    "addr:full":"Brusselsesteenweg 151 Melle Oost-Vlaanderen 9090",
    "addr:housenumber":"151",
    "addr:postcode":"9090",
    "addr:street":"Brusselsesteenweg",
    "iso:country":"BE",
    "sg:address":"Brusselsesteenweg 151",
    "sg:city":"Melle",
    "sg:orig_category":"Bloemen and planten Gh",
    "sg:phone":"+32 9 230 66 89",
    "sg:postcode":"9090",
    "sg:province":"Oost-Vlaanderen",
    "wof:name":"Botelberge",
    "wof:placetype":"venue"
},
  "geometry": {"coordinates":[3.7841119766,51.0159683228],"type":"Point"}
}