{
  "type": "Feature",
  "properties": {
    "addr:full":"Rue De La Province 101 Seraing Li\u00e8ge 4100",
    "addr:housenumber":"101",
    "addr:postcode":"4100",
    "addr:street":"Rue De La Province",
    "iso:country":"BE",
    "sg:address":"Rue De La Province 101",
    "sg:city":"Seraing",
    "sg:classifiers":[
        {
            "category":"Education",
            "subcategory":"School",
            "type":"Public Place"
        }
    ],
    "sg:phone":"+32 4 337 04 96",
    "sg:postcode":"4100",
    "sg:province":"Li\u00e8ge",
    "sg:tags":[
        "secondary"
    ],
    "wof:name":"Coll\u00e8ge St-martin",
    "wof:placetype":"venue"
},
  "geometry": {"coordinates":[5.5045518875,50.6110191345],"type":"Point"}
}