{
  "type": "Feature",
  "properties": {
    "addr:full":"Kortrijkstraat 296 Wevelgem West-Vlaanderen 8560",
    "addr:housenumber":"296",
    "addr:postcode":"8560",
    "addr:street":"Kortrijkstraat",
    "iso:country":"BE",
    "sg:address":"Kortrijkstraat 296",
    "sg:city":"Wevelgem",
    "sg:orig_category":"Bouwmaterialen Gh",
    "sg:phone":"+32 56 41 17 39",
    "sg:postcode":"8560",
    "sg:province":"West-Vlaanderen",
    "wof:name":"West-vlaamse Steencentrale",
    "wof:placetype":"venue"
},
  "geometry": {"coordinates":[3.2002310753,50.8137321472],"type":"Point"}
}