{
  "type": "Feature",
  "properties": {
    "iso:country":"BE",
    "sg:address":"Bosstraat 327",
    "sg:city":"Sint-pieters-woluwe/woluwe-saint-pierre",
    "sg:orig_category":"Paramedische behandelingen",
    "sg:phone":"+32 2 772 19 14",
    "sg:postcode":"1150",
    "sg:province":"Bruxelles-Capitale",
    "wof:name":"M. Geuze",
    "wof:placetype":"venue"
},
  "geometry": {"coordinates":[4.4528570175,50.8304214478],"type":"Point"}
}