{
  "type": "Feature",
  "properties": {
    "iso:country":"BE",
    "sg:address":"Rue Village 90",
    "sg:city":"Olne",
    "sg:classifiers":[
        {
            "category":"Retail",
            "subcategory":"Event Space",
            "type":"Services"
        }
    ],
    "sg:phone":"+32 4 351 75 87",
    "sg:postcode":"4877",
    "sg:province":"Li\u00e8ge",
    "sg:tags":[
        "rental",
        "-",
        "hall"
    ],
    "wof:name":"Montagnards (les)",
    "wof:placetype":"venue"
},
  "geometry": {"coordinates":[5.7511410713,50.5915527344],"type":"Point"}
}