{
  "type": "Feature",
  "properties": {
    "addr:full":"Chauss\u00c9e D'asse 112 Edingen/enghien Hainaut 7850",
    "addr:housenumber":"112",
    "addr:postcode":"7850",
    "addr:street":"Chausse\u0301E D'Asse",
    "iso:country":"BE",
    "sg:address":"Chauss\u00c9e D'asse 112",
    "sg:city":"Edingen/enghien",
    "sg:orig_category":"Epiceries",
    "sg:phone":"+32 2 395 84 25",
    "sg:postcode":"7850",
    "sg:province":"Hainaut",
    "wof:name":"Spar",
    "wof:placetype":"venue"
},
  "geometry": {"coordinates":[4.0513978004,50.6981544495],"type":"Point"}
}