{
  "type": "Feature",
  "properties": {
    "iso:country":"BE",
    "sg:address":"Lange Akkerstraat 33",
    "sg:city":"Deinze",
    "sg:orig_category":"Installatie van houten of kunststof schrijnwerk",
    "sg:phone":"+32 9 380 05 70",
    "sg:postcode":"9800",
    "sg:province":"Oost-Vlaanderen",
    "wof:name":"Gilbert Standaert",
    "wof:placetype":"venue"
},
  "geometry": {"coordinates":[3.5394210815,51.0137481689],"type":"Point"}
}