{
  "type": "Feature",
  "properties": {
    "addr:full":"Weg Naar Zwartberg 47b1 Opglabbeek Limburg 3660",
    "addr:housenumber":"47b1",
    "addr:postcode":"3660",
    "addr:street":"Weg Naar Zwartberg",
    "iso:country":"BE",
    "sg:address":"Weg Naar Zwartberg 47b1",
    "sg:city":"Opglabbeek",
    "sg:orig_category":"Banken and kredietinstellingen",
    "sg:phone":"+32 89 85 52 85",
    "sg:postcode":"3660",
    "sg:province":"Limburg",
    "wof:name":"Kbc",
    "wof:placetype":"venue"
},
  "geometry": {"coordinates":[5.5793218613,51.0416488647],"type":"Point"}
}