{
  "type": "Feature",
  "properties": {
    "iso:country":"BE",
    "sg:address":"Vleminkstraat 44",
    "sg:city":"Aarschot (langdorp)",
    "sg:classifiers":[
        {
            "category":"Bars & Pubs",
            "type":"Food & Drink"
        }
    ],
    "sg:phone":"+32 16 56 55 96",
    "sg:postcode":"3201",
    "sg:province":"Vlaams-Brabant",
    "wof:name":"Araucanahof",
    "wof:placetype":"venue"
},
  "geometry": {"coordinates":[4.8773298264,51.0157318115],"type":"Point"}
}