{
  "type": "Feature",
  "properties": {
    "iso:country":"BE",
    "sg:address":"Langevenstraat 31a",
    "sg:city":"Tremelo",
    "sg:orig_category":"Installation \u00e9lectrique r\u00e9sidentielle. Boissons",
    "sg:phone":"+32 16 56 45 70",
    "sg:postcode":"3128",
    "sg:province":"Vlaams-Brabant",
    "wof:name":"Gh- Technics",
    "wof:placetype":"venue"
},
  "geometry": {"coordinates":[4.7501330376,51.017036438],"type":"Point"}
}