{
  "type": "Feature",
  "properties": {
    "addr:full":"Koning Albertstraat 2a Kortrijk West-Vlaanderen 8500",
    "addr:housenumber":"2a",
    "addr:postcode":"8500",
    "addr:street":"Koning Albertstraat",
    "iso:country":"BE",
    "sg:address":"Koning Albertstraat 2a",
    "sg:city":"Kortrijk",
    "sg:orig_category":"Agences d\u00b4interim and personnel temporaire",
    "sg:phone":"+32 56 25 96 35",
    "sg:postcode":"8500",
    "sg:province":"West-Vlaanderen",
    "wof:name":"Sicom Interim",
    "wof:placetype":"venue"
},
  "geometry": {"coordinates":[3.2638859749,50.8252372742],"type":"Point"}
}