{
  "type": "Feature",
  "properties": {
    "addr:full":"Rue Des R\u00e9fractaires 1a Tournai (froyennes) Hainaut 7503",
    "addr:housenumber":"1a",
    "addr:postcode":"7503",
    "addr:street":"Rue Des Re\u0301Fractaires",
    "iso:country":"BE",
    "sg:address":"Rue Des R\u00e9fractaires 1a",
    "sg:city":"Tournai (froyennes)",
    "sg:orig_category":"Non-Classified Establishments",
    "sg:phone":"+32 69 22 42 62",
    "sg:postcode":"7503",
    "sg:province":"Hainaut",
    "wof:name":"Moderie (la)",
    "wof:placetype":"venue"
},
  "geometry": {"coordinates":[3.2973499298,50.6201820374],"type":"Point"}
}