{
  "type": "Feature",
  "properties": {
    "iso:country":"BE",
    "sg:address":"Place De La Digue 28",
    "sg:city":"Charleroi",
    "sg:classifiers":[
        {
            "category":"Retail",
            "subcategory":"Driving School",
            "type":"Services"
        }
    ],
    "sg:phone":"+32 71 31 21 14",
    "sg:postcode":"6000",
    "sg:province":"Hainaut",
    "sg:tags":[
        "automobile",
        "officially",
        "-",
        "recognized"
    ],
    "wof:name":"Auto-ecoles Henry",
    "wof:placetype":"venue"
},
  "geometry": {"coordinates":[4.4378800392,50.4099273682],"type":"Point"}
}