{
  "type": "Feature",
  "properties": {
    "addr:full":"Menenstraat 17 Moorslede West-Vlaanderen 8890",
    "addr:housenumber":"17",
    "addr:postcode":"8890",
    "addr:street":"Menenstraat",
    "iso:country":"BE",
    "sg:address":"Menenstraat 17",
    "sg:city":"Moorslede",
    "sg:orig_category":"Herstellingen and onderhoud van auto's",
    "sg:phone":"+32 51 50 40 87",
    "sg:postcode":"8890",
    "sg:province":"West-Vlaanderen",
    "wof:name":"Garage Deleersnyder",
    "wof:placetype":"venue"
},
  "geometry": {"coordinates":[3.0998420715,50.8471565247],"type":"Point"}
}