{
  "type": "Feature",
  "properties": {
    "iso:country":"BE",
    "sg:address":"Rue Vanderveken 58",
    "sg:city":"Bruxelles (ganshoren)",
    "sg:classifiers":[
        {
            "category":"Shopping",
            "subcategory":"Florist",
            "type":"Retail Goods"
        }
    ],
    "sg:phone":"+32 2 465 52 50",
    "sg:postcode":"1083",
    "sg:province":"Bruxelles-Capitale",
    "wof:name":"Calypso",
    "wof:placetype":"venue"
},
  "geometry": {"coordinates":[4.3044028282,50.8747596741],"type":"Point"}
}