{
  "type": "Feature",
  "properties": {
    "iso:country":"BE",
    "sg:address":"Bullingen 256ba",
    "sg:city":"B\u00dcllingen/bullange",
    "sg:orig_category":"Herstellingen and onderhoud van auto's",
    "sg:phone":"+32 80 64 24 76",
    "sg:postcode":"4760",
    "sg:province":"Li\u00e8ge",
    "wof:name":"Ernst Jost",
    "wof:placetype":"venue"
},
  "geometry": {"coordinates":[6.3118200302,50.3753318787],"type":"Point"}
}