{
  "type": "Feature",
  "properties": {
    "addr:full":"Rue De La R\u00c9sidence 14 Li\u00c8ge Li\u00e8ge 4031",
    "addr:housenumber":"14",
    "addr:postcode":"4031",
    "addr:street":"Rue De La Re\u0301Sidence",
    "iso:country":"BE",
    "sg:address":"Rue De La R\u00c9sidence 14",
    "sg:city":"Li\u00c8ge",
    "sg:orig_category":"M\u00e9decins and sp\u00e9cialistes",
    "sg:phone":"+32 4 341 27 21",
    "sg:postcode":"4031",
    "sg:province":"Li\u00e8ge",
    "wof:name":"Marc Raepsaet",
    "wof:placetype":"venue"
},
  "geometry": {"coordinates":[5.5912561417,50.6126441956],"type":"Point"}
}