{
  "type": "Feature",
  "properties": {
    "iso:country":"BE",
    "sg:address":"Eernegemweg 17",
    "sg:city":"Jabbeke (snellegem)",
    "sg:classifiers":[
        {
            "category":"Social Services",
            "type":"Services"
        }
    ],
    "sg:phone":"+32 50 27 07 17",
    "sg:postcode":"8490",
    "sg:province":"West-Vlaanderen",
    "wof:name":"Anker Vzw (het)",
    "wof:placetype":"venue"
},
  "geometry": {"coordinates":[3.1211559772,51.1682014465],"type":"Point"}
}