{
  "type": "Feature",
  "properties": {
    "addr:full":"Kerkstraat 93 Arendonk Antwerpen 2370",
    "addr:housenumber":"93",
    "addr:postcode":"2370",
    "addr:street":"Kerkstraat",
    "iso:country":"BE",
    "sg:address":"Kerkstraat 93",
    "sg:city":"Arendonk",
    "sg:classifiers":[
        {
            "category":"Professional",
            "subcategory":"Management & Consulting",
            "type":"Services"
        }
    ],
    "sg:phone":"+32 14 67 75 40",
    "sg:postcode":"2370",
    "sg:province":"Antwerpen",
    "sg:tags":[
        "consultant"
    ],
    "wof:name":"De Coninck Management & Organisatie Bvba",
    "wof:placetype":"venue"
},
  "geometry": {"coordinates":[5.0767998695,51.3131637573],"type":"Point"}
}