{
  "type": "Feature",
  "properties": {
    "iso:country":"BE",
    "sg:address":"Antwerpsestraat 88",
    "sg:city":"Lier",
    "sg:orig_category":"V\u00eatements pour Hommes",
    "sg:phone":"+32 3 488 51 65",
    "sg:postcode":"2500",
    "sg:province":"Antwerpen",
    "wof:name":"Huis Portofino",
    "wof:placetype":"venue"
},
  "geometry": {"coordinates":[4.5672101974,51.1338729858],"type":"Point"}
}