{
  "type": "Feature",
  "properties": {
    "iso:country":"BE",
    "sg:address":"Donklaan 289",
    "sg:city":"Berlare (overmere)",
    "sg:classifiers":[
        {
            "category":"Banks & Credit Unions",
            "subcategory":"Investment Brokerage",
            "type":"Services"
        }
    ],
    "sg:phone":"+32 9 367 94 59",
    "sg:postcode":"9290",
    "sg:province":"Oost-Vlaanderen",
    "sg:tags":[
        "rental",
        "-",
        "yacht",
        "boat",
        "pleasure"
    ],
    "wof:name":"De Meyer E",
    "wof:placetype":"venue"
},
  "geometry": {"coordinates":[3.9795000553,51.0246582031],"type":"Point"}
}