{
  "type": "Feature",
  "properties": {
    "iso:country":"BE",
    "sg:address":"Avenue Louise 391 Box 1",
    "sg:city":"Bruxelles (ixelles)",
    "sg:classifiers":[
        {
            "category":"Professional",
            "subcategory":"Management & Consulting",
            "type":"Services"
        }
    ],
    "sg:phone":"+32 2 646 02 60",
    "sg:postcode":"1050",
    "sg:province":"Bruxelles-Capitale",
    "sg:tags":[
        "consultant",
        "law"
    ],
    "wof:name":"Masons",
    "wof:placetype":"venue"
},
  "geometry": {"coordinates":[4.3702440262,50.820148468],"type":"Point"}
}