{
  "type": "Feature",
  "properties": {
    "iso:country":"BE",
    "sg:address":"Chauss\u00e9e De Dinant 51",
    "sg:city":"Profondeville",
    "sg:classifiers":[
        {
            "category":"Retail",
            "subcategory":"Veterinary Services",
            "type":"Services"
        }
    ],
    "sg:phone":"+32 81 41 33 36",
    "sg:postcode":"5170",
    "sg:province":"Namur",
    "sg:tags":[
        "veterinarian"
    ],
    "wof:name":"Remy I",
    "wof:placetype":"venue"
},
  "geometry": {"coordinates":[4.874063015,50.3766822815],"type":"Point"}
}