{
  "type": "Feature",
  "properties": {
    "addr:full":"Josse Biesmansstraat 65 Hoeilaart Vlaams-Brabant 1560",
    "addr:housenumber":"65",
    "addr:postcode":"1560",
    "addr:street":"Josse Biesmansstraat",
    "iso:country":"BE",
    "sg:address":"Josse Biesmansstraat 65",
    "sg:city":"Hoeilaart",
    "sg:orig_category":"Boekhouders",
    "sg:phone":"+32 2 513 75 64",
    "sg:postcode":"1560",
    "sg:province":"Vlaams-Brabant",
    "wof:name":"Jean Charlier",
    "wof:placetype":"venue"
},
  "geometry": {"coordinates":[4.4658689499,50.770740509],"type":"Point"}
}