{
  "type": "Feature",
  "properties": {
    "iso:country":"BE",
    "sg:address":"Stationstraat 1",
    "sg:city":"Zottegem",
    "sg:orig_category":"V\u00eatements. V\u00eatements pour b\u00e9b\u00e9s and enfants",
    "sg:phone":"+32 9 361 35 16",
    "sg:postcode":"9620",
    "sg:province":"Oost-Vlaanderen",
    "wof:name":"Huis Absolu",
    "wof:placetype":"venue"
},
  "geometry": {"coordinates":[3.8113520145,50.8692626953],"type":"Point"}
}