{
  "type": "Feature",
  "properties": {
    "iso:country":"BE",
    "sg:address":"Scheldestraat 26",
    "sg:city":"Bornem (weert)",
    "sg:classifiers":[
        {
            "category":"Professional",
            "type":"Services"
        }
    ],
    "sg:phone":"+32 3 889 16 76",
    "sg:postcode":"2880",
    "sg:province":"Antwerpen",
    "sg:tags":[
        "industrial",
        "automation"
    ],
    "wof:name":"Verhofstede G",
    "wof:placetype":"venue"
},
  "geometry": {"coordinates":[4.1911969185,51.1027679443],"type":"Point"}
}