{
  "type": "Feature",
  "properties": {
    "addr:full":"Tuinbouwstraat 13 Aarschot Vlaams-Brabant 3201",
    "addr:housenumber":"13",
    "addr:postcode":"3201",
    "addr:street":"Tuinbouwstraat",
    "iso:country":"BE",
    "sg:address":"Tuinbouwstraat 13",
    "sg:city":"Aarschot",
    "sg:orig_category":"Producteurs de l\u00e9gumes",
    "sg:phone":"+32 13 77 11 44",
    "sg:postcode":"3201",
    "sg:province":"Vlaams-Brabant",
    "wof:name":"Adriaan Vissers",
    "wof:placetype":"venue"
},
  "geometry": {"coordinates":[4.9302048683,51.0268592834],"type":"Point"}
}