{
  "type": "Feature",
  "properties": {
    "iso:country":"BE",
    "sg:address":"Pachtgoeddreef 57",
    "sg:city":"Gent",
    "sg:orig_category":"Secretariaatsdiensten",
    "sg:phone":"+32 9 237 22 11",
    "sg:postcode":"9031",
    "sg:province":"Oost-Vlaanderen",
    "wof:name":"Aducom",
    "wof:placetype":"venue"
},
  "geometry": {"coordinates":[3.6626179218,51.0585098267],"type":"Point"}
}