{
  "type": "Feature",
  "properties": {
    "addr:full":"Kogelstraat 15 Sint-truiden Limburg 3800",
    "addr:housenumber":"15",
    "addr:postcode":"3800",
    "addr:street":"Kogelstraat",
    "iso:country":"BE",
    "sg:address":"Kogelstraat 15",
    "sg:city":"Sint-truiden",
    "sg:orig_category":"Fruitteelt",
    "sg:phone":"+32 11 69 47 20",
    "sg:postcode":"3800",
    "sg:province":"Limburg",
    "wof:name":"Peter Fabry",
    "wof:placetype":"venue"
},
  "geometry": {"coordinates":[5.2526931763,50.8218231201],"type":"Point"}
}