{
  "type": "Feature",
  "properties": {
    "iso:country":"BE",
    "sg:address":"Grand Bru 33b2",
    "sg:city":"Durbuy",
    "sg:orig_category":"Maisons de vacances",
    "sg:phone":"+32 86 49 92 83",
    "sg:postcode":"6941",
    "sg:province":"Luxembourg",
    "wof:name":"Les R\u00c9sidences De Virginie",
    "wof:placetype":"venue"
},
  "geometry": {"coordinates":[5.524184227,50.3770332336],"type":"Point"}
}