{
  "type": "Feature",
  "properties": {
    "addr:full":"Stationsstraat 85 Nazareth (eke) Oost-Vlaanderen 9810",
    "addr:housenumber":"85",
    "addr:postcode":"9810",
    "addr:street":"Stationsstraat",
    "iso:country":"BE",
    "sg:address":"Stationsstraat 85",
    "sg:city":"Nazareth (eke)",
    "sg:classifiers":[
        {
            "category":"Home & Garden",
            "subcategory":"Carpets & Floor Coverings",
            "type":"Retail Goods"
        }
    ],
    "sg:phone":"+32 9 385 44 14",
    "sg:postcode":"9810",
    "sg:province":"Oost-Vlaanderen",
    "sg:tags":[
        "layer",
        "mosaicists"
    ],
    "wof:name":"De Clercq L",
    "wof:placetype":"venue"
},
  "geometry": {"coordinates":[3.6333930492,50.9593734741],"type":"Point"}
}