{
  "type": "Feature",
  "properties": {
    "addr:full":"Hospitaalstraat 9 Box 2 Genk Limburg 3600",
    "addr:housenumber":"9;2",
    "addr:postcode":"3600",
    "addr:street":"Hospitaalstraat;Box",
    "iso:country":"BE",
    "sg:address":"Hospitaalstraat 9 Box 2",
    "sg:city":"Genk",
    "sg:classifiers":[
        {
            "category":"Government",
            "subcategory":"Post Office",
            "type":"Public Place"
        }
    ],
    "sg:phone":"+32 89 36 39 62",
    "sg:postcode":"3600",
    "sg:province":"Limburg",
    "sg:tags":[
        "yoga"
    ],
    "wof:name":"Moors E",
    "wof:placetype":"venue"
},
  "geometry": {"coordinates":[5.5076570511,50.9688529968],"type":"Point"}
}