{
  "type": "Feature",
  "properties": {
    "addr:full":"Nijverheidslaan 20 Diest Vlaams-Brabant 3290",
    "addr:housenumber":"20",
    "addr:postcode":"3290",
    "addr:street":"Nijverheidslaan",
    "iso:country":"BE",
    "sg:address":"Nijverheidslaan 20",
    "sg:city":"Diest",
    "sg:orig_category":"Natuursteenbewerking Vloer- and muurbekleding",
    "sg:phone":"+32 13 31 15 11",
    "sg:postcode":"3290",
    "sg:province":"Vlaams-Brabant",
    "wof:name":"De Maeght P",
    "wof:placetype":"venue"
},
  "geometry": {"coordinates":[5.0394568443,50.9885025024],"type":"Point"}
}