{
  "type": "Feature",
  "properties": {
    "iso:country":"BE",
    "sg:address":"Rue De Mons 7",
    "sg:city":"Li\u00c8ge",
    "sg:orig_category":"Diverse bouwinstallaties Diverse metaalwaren Fab Reclamebureaus Verlichtingsapparaten and elektrisch",
    "sg:phone":"+32 4 224 74 74",
    "sg:postcode":"4000",
    "sg:province":"Li\u00e8ge",
    "wof:name":"D.k.d.",
    "wof:placetype":"venue"
},
  "geometry": {"coordinates":[5.5751719475,50.6386566162],"type":"Point"}
}