{
  "type": "Feature",
  "properties": {
    "addr:full":"Baksveld 26 Westerlo Antwerpen 2260",
    "addr:housenumber":"26",
    "addr:postcode":"2260",
    "addr:street":"Baksveld",
    "iso:country":"BE",
    "sg:address":"Baksveld 26",
    "sg:city":"Westerlo",
    "sg:classifiers":[
        {
            "category":"Manufacturing",
            "subcategory":"Textiles",
            "type":"Manufacturing & Wholesale Goods"
        }
    ],
    "sg:phone":"+32 14 54 64 82",
    "sg:postcode":"2260",
    "sg:province":"Antwerpen",
    "wof:name":"Maria Peeters",
    "wof:placetype":"venue"
},
  "geometry": {"coordinates":[4.9170489311,51.0924873352],"type":"Point"}
}