{
  "type": "Feature",
  "properties": {
    "addr:full":"Stijn Streuvelsstraat 73 Waregem West-Vlaanderen 8790",
    "addr:housenumber":"73",
    "addr:postcode":"8790",
    "addr:street":"Stijn Streuvelsstraat",
    "iso:country":"BE",
    "sg:address":"Stijn Streuvelsstraat 73",
    "sg:city":"Waregem",
    "sg:orig_category":"Artiesten and kunstenaars",
    "sg:phone":"+32 56 60 29 41",
    "sg:postcode":"8790",
    "sg:province":"West-Vlaanderen",
    "wof:name":"Rosa Depoortere",
    "wof:placetype":"venue"
},
  "geometry": {"coordinates":[3.4190580845,50.8772468567],"type":"Point"}
}