{
  "type": "Feature",
  "properties": {
    "iso:country":"BE",
    "sg:address":"Herseauxlaan 144",
    "sg:city":"Moeskroen/mouscron",
    "sg:orig_category":"Herstellingen and onderhoud van auto's",
    "sg:phone":"+32 56 48 86 77",
    "sg:postcode":"7711",
    "sg:province":"Hainaut",
    "wof:name":"Carrosserie Deguffroy",
    "wof:placetype":"venue"
},
  "geometry": {"coordinates":[3.2929000854,50.7344207764],"type":"Point"}
}