{
  "type": "Feature",
  "properties": {
    "iso:country":"BE",
    "sg:address":"Eernegemsestraat 1b2",
    "sg:city":"Oudenburg",
    "sg:orig_category":"Avocats and conseillers juridiques",
    "sg:phone":"+32 59 25 09 94",
    "sg:postcode":"8460",
    "sg:province":"West-Vlaanderen",
    "wof:name":"Nicole D\u00b4hont",
    "wof:placetype":"venue"
},
  "geometry": {"coordinates":[3.0023450851,51.1840553284],"type":"Point"}
}