{
  "type": "Feature",
  "properties": {
    "iso:country":"BE",
    "sg:address":"Segherslaan 100",
    "sg:city":"Koekelberg/koekelberg",
    "sg:orig_category":"Artiesten and kunstenaars",
    "sg:phone":"+32 2 414 57 51",
    "sg:postcode":"1081",
    "sg:province":"Bruxelles-Capitale",
    "wof:name":"Bossaerts",
    "wof:placetype":"venue"
},
  "geometry": {"coordinates":[4.319770813,50.8642921448],"type":"Point"}
}