{
  "type": "Feature",
  "properties": {
    "addr:full":"Ambachtstraat 30 Beerse Antwerpen 2340",
    "addr:housenumber":"30",
    "addr:postcode":"2340",
    "addr:street":"Ambachtstraat",
    "iso:country":"BE",
    "sg:address":"Ambachtstraat 30",
    "sg:city":"Beerse",
    "sg:classifiers":[
        {
            "category":"Utilities",
            "subcategory":"Natural Gas",
            "type":"Services"
        }
    ],
    "sg:phone":"+32 14 60 00 10",
    "sg:postcode":"2340",
    "sg:province":"Antwerpen",
    "sg:tags":[
        "firework"
    ],
    "wof:name":"Dewico Bvba",
    "wof:placetype":"venue"
},
  "geometry": {"coordinates":[4.8341407776,51.3030776978],"type":"Point"}
}