{
  "type": "Feature",
  "properties": {
    "iso:country":"BE",
    "sg:address":"Rue Du Mont\u00e9n\u00e9gro 135",
    "sg:city":"Bruxelles (forest)",
    "sg:classifiers":[
        {
            "category":"Manufacturing",
            "subcategory":"Metals",
            "type":"Manufacturing & Wholesale Goods"
        }
    ],
    "sg:phone":"+32 2 537 81 79",
    "sg:postcode":"1190",
    "sg:province":"Bruxelles-Capitale",
    "sg:tags":[
        "ornamental",
        "work",
        "-"
    ],
    "wof:name":"Rodriguez Sprl",
    "wof:placetype":"venue"
},
  "geometry": {"coordinates":[4.3320531845,50.8266944885],"type":"Point"}
}