{
  "type": "Feature",
  "properties": {
    "addr:full":"Rue Saint-martin 18 Manhay (malempr\u00e9) Luxembourg 6960",
    "addr:housenumber":"18",
    "addr:postcode":"6960",
    "addr:street":"Rue Saint-Martin",
    "iso:country":"BE",
    "sg:address":"Rue Saint-martin 18",
    "sg:city":"Manhay (malempr\u00e9)",
    "sg:classifiers":[
        {
            "category":"Travel",
            "subcategory":"Resort",
            "type":"Entertainment"
        }
    ],
    "sg:phone":"+32 86 45 51 22",
    "sg:postcode":"6960",
    "sg:province":"Luxembourg",
    "sg:tags":[
        "farm",
        "house",
        "holiday",
        "guest"
    ],
    "wof:name":"Ferme St-martin",
    "wof:placetype":"venue"
},
  "geometry": {"coordinates":[5.7149782181,50.2812805176],"type":"Point"}
}