{
  "type": "Feature",
  "properties": {
    "iso:country":"BE",
    "sg:address":"Grand-rue 52",
    "sg:city":"Libramont-chevigny",
    "sg:orig_category":"Apotheken",
    "sg:phone":"+32 61 22 21 84",
    "sg:postcode":"6800",
    "sg:province":"Luxembourg",
    "wof:name":"Brigitte Mace",
    "wof:placetype":"venue"
},
  "geometry": {"coordinates":[5.4576530457,49.9803771973],"type":"Point"}
}