{
  "type": "Feature",
  "properties": {
    "iso:country":"BE",
    "sg:address":"Rue De Veeweyde 82",
    "sg:city":"Bruxelles (anderlecht)",
    "sg:classifiers":[
        {
            "category":"Education",
            "subcategory":"School",
            "type":"Public Place"
        }
    ],
    "sg:phone":"+32 2 521 80 18",
    "sg:postcode":"1070",
    "sg:province":"Bruxelles-Capitale",
    "sg:tags":[
        "primary"
    ],
    "wof:name":"Gesubsidi\u00eberde Gemeentelijke Lagere School",
    "wof:placetype":"venue"
},
  "geometry": {"coordinates":[4.3054637909,50.8309555054],"type":"Point"}
}