{
  "type": "Feature",
  "properties": {
    "iso:country":"BE",
    "sg:address":"Avenue Du Fusain 43",
    "sg:city":"Brussel/bruxelles",
    "sg:orig_category":"Fotogravure and zetwerk",
    "sg:phone":"+32 2 262 16 50",
    "sg:postcode":"1020",
    "sg:province":"Bruxelles-Capitale",
    "wof:name":"M.m. Teams",
    "wof:placetype":"venue"
},
  "geometry": {"coordinates":[4.3651762009,50.8946113586],"type":"Point"}
}