{
  "type": "Feature",
  "properties": {
    "iso:country":"BE",
    "sg:address":"Mulderstraat 13ba",
    "sg:city":"Herzele",
    "sg:orig_category":"Charpentes and couvertures",
    "sg:phone":"+32 54 50 04 28",
    "sg:postcode":"9550",
    "sg:province":"Oost-Vlaanderen",
    "wof:name":"De Zutter-kleynen",
    "wof:placetype":"venue"
},
  "geometry": {"coordinates":[3.9260671139,50.8503761292],"type":"Point"}
}