{
  "type": "Feature",
  "properties": {
    "iso:country":"BE",
    "sg:address":"Achterlee 53",
    "sg:city":"Kasterlee",
    "sg:classifiers":[
        {
            "category":"Cafe",
            "type":"Food & Drink"
        }
    ],
    "sg:phone":"+32 14 55 69 09",
    "sg:postcode":"2460",
    "sg:province":"Antwerpen",
    "sg:tags":[
        "caf\u00e9s"
    ],
    "wof:name":"Caf\u00c9 In De Perenboom",
    "wof:placetype":"venue"
},
  "geometry": {"coordinates":[4.9671049118,51.2406616211],"type":"Point"}
}