{
  "type": "Feature",
  "properties": {
    "addr:full":"Congostraat 32 Hasselt Limburg 3500",
    "addr:housenumber":"32",
    "addr:postcode":"3500",
    "addr:street":"Congostraat",
    "iso:country":"BE",
    "sg:address":"Congostraat 32",
    "sg:city":"Hasselt",
    "sg:orig_category":"Plomberie, chauffage and installations sanitaires",
    "sg:phone":"+32 11 23 10 89",
    "sg:postcode":"3500",
    "sg:province":"Limburg",
    "wof:name":"C A S",
    "wof:placetype":"venue"
},
  "geometry": {"coordinates":[5.3478140831,50.9325942993],"type":"Point"}
}