{
  "type": "Feature",
  "properties": {
    "addr:full":"Lillo Steenweg 10ba Houthalen-helchteren Limburg 3530",
    "addr:housenumber":"10ba",
    "addr:postcode":"3530",
    "addr:street":"Lillo Steenweg",
    "iso:country":"BE",
    "sg:address":"Lillo Steenweg 10ba",
    "sg:city":"Houthalen-helchteren",
    "sg:orig_category":"Diverse bouwafwerking and reiniging Gespecialiseerde residenti\u00eble bouw Woningbouw",
    "sg:phone":"+32 11 57 20 22",
    "sg:postcode":"3530",
    "sg:province":"Limburg",
    "wof:name":"Franco Schincariol",
    "wof:placetype":"venue"
},
  "geometry": {"coordinates":[5.3500819206,51.0428352356],"type":"Point"}
}