{
  "type": "Feature",
  "properties": {
    "addr:full":"B\u00e9verc\u00e9 11b Malmedy (beverc\u00e9) Li\u00e8ge 4960",
    "addr:housenumber":"11b",
    "addr:postcode":"4960",
    "addr:street":"Be\u0301Verce\u0301",
    "iso:country":"BE",
    "sg:address":"B\u00e9verc\u00e9 11b",
    "sg:city":"Malmedy (beverc\u00e9)",
    "sg:classifiers":[
        {
            "category":"Travel",
            "subcategory":"Hotels & Motels",
            "type":"Entertainment"
        }
    ],
    "sg:phone":"+32 80 77 18 27",
    "sg:postcode":"4960",
    "sg:province":"Li\u00e8ge",
    "wof:name":"Hotel De La Warche",
    "wof:placetype":"venue"
},
  "geometry": {"coordinates":[6.0306248665,50.4252433777],"type":"Point"}
}