{
  "type": "Feature",
  "properties": {
    "iso:country":"BE",
    "sg:address":"Hof Te Walle 44",
    "sg:city":"Kortrijk",
    "sg:classifiers":[
        {
            "category":"Professional",
            "subcategory":"Management & Consulting",
            "type":"Services"
        }
    ],
    "sg:phone":"+32 56 20 19 96",
    "sg:postcode":"8500",
    "sg:province":"West-Vlaanderen",
    "sg:tags":[
        "consultant"
    ],
    "wof:name":"Orgon",
    "wof:placetype":"venue"
},
  "geometry": {"coordinates":[3.2719600201,50.811706543],"type":"Point"}
}