{
  "type": "Feature",
  "properties": {
    "addr:full":"Rue Grange Des Champs 152 Braine L'alleud (braine-l'alleud) Brabant Wallon 1420",
    "addr:housenumber":"152",
    "addr:postcode":"1420",
    "addr:street":"Rue Grange Des Champs",
    "iso:country":"BE",
    "sg:address":"Rue Grange Des Champs 152",
    "sg:city":"Braine L'alleud (braine-l'alleud)",
    "sg:classifiers":[
        {
            "category":"Health Services",
            "subcategory":"Dentist",
            "type":"Services"
        }
    ],
    "sg:phone":"+32 2 384 37 46",
    "sg:postcode":"1420",
    "sg:province":"Brabant Wallon",
    "wof:name":"Depotter A",
    "wof:placetype":"venue"
},
  "geometry": {"coordinates":[-0.8630650043,47.4144668579],"type":"Point"}
}