{
  "type": "Feature",
  "properties": {
    "iso:country":"BE",
    "sg:address":"Kattestraat 29",
    "sg:city":"Sint-amands",
    "sg:classifiers":[
        {
            "category":"Personal",
            "subcategory":"Beauty Salon",
            "type":"Services"
        }
    ],
    "sg:phone":"+32 3 889 22 18",
    "sg:postcode":"2890",
    "sg:province":"Antwerpen",
    "sg:tags":[
        "de",
        "coiffure"
    ],
    "wof:name":"Marie-jose Windey",
    "wof:placetype":"venue"
},
  "geometry": {"coordinates":[4.2452230453,51.0696105957],"type":"Point"}
}