{
  "type": "Feature",
  "properties": {
    "addr:full":"Eeksken 13 Lovendegem Oost-Vlaanderen 9920",
    "addr:housenumber":"13",
    "addr:postcode":"9920",
    "addr:street":"Eeksken",
    "iso:country":"BE",
    "sg:address":"Eeksken 13",
    "sg:city":"Lovendegem",
    "sg:orig_category":"Elektrische installaties voor woningen",
    "sg:phone":"+32 9 357 31 76",
    "sg:postcode":"9920",
    "sg:province":"Oost-Vlaanderen",
    "wof:name":"Walter Haeck",
    "wof:placetype":"venue"
},
  "geometry": {"coordinates":[3.6426930428,51.1254615784],"type":"Point"}
}