{
  "type": "Feature",
  "properties": {
    "addr:full":"Rue Des Alexiens 18 Bruxelles Bruxelles-Capitale 1000",
    "addr:housenumber":"18",
    "addr:postcode":"1000",
    "addr:street":"Rue Des Alexiens",
    "iso:country":"BE",
    "sg:address":"Rue Des Alexiens 18",
    "sg:city":"Bruxelles",
    "sg:classifiers":[
        {
            "category":"Organizations",
            "subcategory":"Professional Association",
            "type":"Services"
        }
    ],
    "sg:phone":"+32 2 512 97 00",
    "sg:postcode":"1000",
    "sg:province":"Bruxelles-Capitale",
    "sg:tags":[
        "trade-union",
        "federation"
    ],
    "wof:name":"Centrale Alimentation-hor\u00e9ca-service Fgtb",
    "wof:placetype":"venue"
},
  "geometry": {"coordinates":[4.3509349823,50.8430252075],"type":"Point"}
}