{
  "type": "Feature",
  "properties": {
    "addr:full":"Roodborstjesstraat 5 Jabbeke West-Vlaanderen 8490",
    "addr:housenumber":"5",
    "addr:postcode":"8490",
    "addr:street":"Roodborstjesstraat",
    "iso:country":"BE",
    "sg:address":"Roodborstjesstraat 5",
    "sg:city":"Jabbeke",
    "sg:orig_category":"Non-Classified Establishments",
    "sg:phone":"+32 50 81 16 47",
    "sg:postcode":"8490",
    "sg:province":"West-Vlaanderen",
    "wof:name":"Bika Bvba",
    "wof:placetype":"venue"
},
  "geometry": {"coordinates":[3.0857601166,51.1838531494],"type":"Point"}
}