{
  "type": "Feature",
  "properties": {
    "iso:country":"BE",
    "sg:address":"Rue Nacfer 44",
    "sg:city":"Dour (wih\u00e9ries)",
    "sg:classifiers":[
        {
            "category":"Health Services",
            "subcategory":"Health Practitioner",
            "type":"Services"
        }
    ],
    "sg:phone":"+32 65 65 59 68",
    "sg:postcode":"7370",
    "sg:province":"Hainaut",
    "sg:tags":[
        "physiotherapist"
    ],
    "wof:name":"Jospin M-l",
    "wof:placetype":"venue"
},
  "geometry": {"coordinates":[3.7517259121,50.385974884],"type":"Point"}
}