{
  "type": "Feature",
  "properties": {
    "iso:country":"BE",
    "sg:address":"Avenue Boischamps 25",
    "sg:city":"Walcourt",
    "sg:orig_category":"Procesbesturingssystemen Fab",
    "sg:phone":"+32 10 65 85 06",
    "sg:postcode":"1450",
    "sg:province":"Brabant Wallon",
    "wof:name":"J.d.t.",
    "wof:placetype":"venue"
},
  "geometry": {"coordinates":[4.636452198,50.6085243225],"type":"Point"}
}