{
  "type": "Feature",
  "properties": {
    "addr:full":"Quai Des Carmes 73 Seraing Li\u00e8ge 4101",
    "addr:housenumber":"73",
    "addr:postcode":"4101",
    "addr:street":"Quai Des Carmes",
    "iso:country":"BE",
    "sg:address":"Quai Des Carmes 73",
    "sg:city":"Seraing",
    "sg:orig_category":"M\u00e9decins and sp\u00e9cialistes",
    "sg:phone":"+32 4 233 58 21",
    "sg:postcode":"4101",
    "sg:province":"Li\u00e8ge",
    "wof:name":"Luc Maghe",
    "wof:placetype":"venue"
},
  "geometry": {"coordinates":[5.5176792145,50.6188583374],"type":"Point"}
}