{
  "type": "Feature",
  "properties": {
    "iso:country":"BE",
    "sg:address":"L\u00e9once Roelsstraat 5",
    "sg:city":"Zottegem",
    "sg:classifiers":[
        {
            "category":"Health Services",
            "subcategory":"Doctor",
            "type":"Services"
        }
    ],
    "sg:phone":"+32 9 360 09 99",
    "sg:postcode":"9620",
    "sg:province":"Oost-Vlaanderen",
    "sg:tags":[
        "medicinephysicians",
        "surgeon"
    ],
    "wof:name":"Magherman Bart",
    "wof:placetype":"venue"
},
  "geometry": {"coordinates":[3.8131899834,50.8651313782],"type":"Point"}
}