{
  "type": "Feature",
  "properties": {
    "addr:full":"Houtemstraat 21 Veurne West-Vlaanderen 8630",
    "addr:housenumber":"21",
    "addr:postcode":"8630",
    "addr:street":"Houtemstraat",
    "iso:country":"BE",
    "sg:address":"Houtemstraat 21",
    "sg:city":"Veurne",
    "sg:orig_category":"Installation de menuiserie en bois and plastique",
    "sg:phone":"+32 58 29 97 00",
    "sg:postcode":"8630",
    "sg:province":"West-Vlaanderen",
    "wof:name":"Ivan De Hollander",
    "wof:placetype":"venue"
},
  "geometry": {"coordinates":[2.6129620075,51.0083808899],"type":"Point"}
}