{
  "type": "Feature",
  "properties": {
    "addr:full":"Chauss\u00c9e Romaine 60b3 Waremme Li\u00e8ge 4300",
    "addr:housenumber":"60b3",
    "addr:postcode":"4300",
    "addr:street":"Chausse\u0301E Romaine",
    "iso:country":"BE",
    "sg:address":"Chauss\u00c9e Romaine 60b3",
    "sg:city":"Waremme",
    "sg:orig_category":"Epiceries",
    "sg:phone":"+32 19 33 11 60",
    "sg:postcode":"4300",
    "sg:province":"Li\u00e8ge",
    "wof:name":"Eda",
    "wof:placetype":"venue"
},
  "geometry": {"coordinates":[5.2572999001,50.6874313354],"type":"Point"}
}