{
  "type": "Feature",
  "properties": {
    "addr:full":"Hoevelei 56 Aartselaar Antwerpen 2630",
    "addr:housenumber":"56",
    "addr:postcode":"2630",
    "addr:street":"Hoevelei",
    "iso:country":"BE",
    "sg:address":"Hoevelei 56",
    "sg:city":"Aartselaar",
    "sg:orig_category":"Boissons",
    "sg:phone":"+32 3 887 39 95",
    "sg:postcode":"2630",
    "sg:province":"Antwerpen",
    "wof:name":"Peter Verbeeck",
    "wof:placetype":"venue"
},
  "geometry": {"coordinates":[4.3861260414,51.1364250183],"type":"Point"}
}