{
  "type": "Feature",
  "properties": {
    "addr:full":"R Du Village 61 Olne Li\u00e8ge 4877",
    "addr:housenumber":"61",
    "addr:postcode":"4877",
    "addr:street":"R Du Village",
    "iso:country":"BE",
    "sg:address":"R Du Village 61",
    "sg:city":"Olne",
    "sg:classifiers":[
        {
            "category":"Personal",
            "subcategory":"Beauty Salon",
            "type":"Services"
        }
    ],
    "sg:phone":"+32 87 26 81 80",
    "sg:postcode":"4877",
    "sg:province":"Li\u00e8ge",
    "sg:tags":[
        "de",
        "coiffure"
    ],
    "wof:name":"Coiffure Anne",
    "wof:placetype":"venue"
},
  "geometry": {"coordinates":[5.7491631508,50.5907897949],"type":"Point"}
}