{
  "type": "Feature",
  "properties": {
    "addr:full":"Buitenbankstraat 1 Bilzen Limburg 3742",
    "addr:housenumber":"1",
    "addr:postcode":"3742",
    "addr:street":"Buitenbankstraat",
    "iso:country":"BE",
    "sg:address":"Buitenbankstraat 1",
    "sg:city":"Bilzen",
    "sg:orig_category":"Hout and afgeleiden Gh IJzerwaren, bouw- and verfmaterialen",
    "sg:phone":"+32 89 41 14 56",
    "sg:postcode":"3742",
    "sg:province":"Limburg",
    "wof:name":"Johnny Vanherle",
    "wof:placetype":"venue"
},
  "geometry": {"coordinates":[5.5354890823,50.8532218933],"type":"Point"}
}