{
  "type": "Feature",
  "properties": {
    "iso:country":"BE",
    "sg:address":"Schurhovenveld 3112",
    "sg:city":"Sint-truiden",
    "sg:classifiers":[
        {
            "category":"Wholesale",
            "subcategory":"Fruits & Vegetables",
            "type":"Manufacturing & Wholesale Goods"
        }
    ],
    "sg:phone":"+32 11 69 40 58",
    "sg:postcode":"3800",
    "sg:province":"Limburg",
    "sg:tags":[
        "whol",
        "-"
    ],
    "wof:name":"G.b.v. Nv",
    "wof:placetype":"venue"
},
  "geometry": {"coordinates":[5.1863641739,50.8153343201],"type":"Point"}
}