{
  "type": "Feature",
  "properties": {
    "addr:full":"Chauss\u00c9e Romaine 393 Brussel/bruxelles Bruxelles-Capitale 1020",
    "addr:housenumber":"393",
    "addr:postcode":"1020",
    "addr:street":"Chausse\u0301E Romaine;/",
    "iso:country":"BE",
    "sg:address":"Chauss\u00c9e Romaine 393",
    "sg:city":"Brussel/bruxelles",
    "sg:orig_category":"Artistes ind\u00e9pendants",
    "sg:phone":"+32 2 268 40 23",
    "sg:postcode":"1020",
    "sg:province":"Bruxelles-Capitale",
    "wof:name":"Sien Eggers",
    "wof:placetype":"venue"
},
  "geometry": {"coordinates":[4.3615040779,50.9004440308],"type":"Point"}
}