{
  "type": "Feature",
  "properties": {
    "iso:country":"BE",
    "sg:address":"Bohemen 28",
    "sg:city":"Wichelen",
    "sg:orig_category":"Imprimeries and copyshops",
    "sg:phone":"+32 52 42 25 06",
    "sg:postcode":"9260",
    "sg:province":"Oost-Vlaanderen",
    "wof:name":"Brabo",
    "wof:placetype":"venue"
},
  "geometry": {"coordinates":[3.97991395,51.0037879944],"type":"Point"}
}