{
  "type": "Feature",
  "properties": {
    "addr:full":"Brusselsesteenweg 145 Melle Oost-Vlaanderen 9090",
    "addr:housenumber":"145",
    "addr:postcode":"9090",
    "addr:street":"Brusselsesteenweg",
    "iso:country":"BE",
    "sg:address":"Brusselsesteenweg 145",
    "sg:city":"Melle",
    "sg:orig_category":"Plantes and fleurs Gr",
    "sg:phone":"+32 9 230 66 41",
    "sg:postcode":"9090",
    "sg:province":"Oost-Vlaanderen",
    "wof:name":"Mattelin W",
    "wof:placetype":"venue"
},
  "geometry": {"coordinates":[3.782998085,51.0168495178],"type":"Point"}
}