{
  "type": "Feature",
  "properties": {
    "iso:country":"BE",
    "sg:address":"Rue De Bruxelles 82",
    "sg:city":"Enghien",
    "sg:classifiers":[
        {
            "category":"Shopping",
            "subcategory":"Shoes",
            "type":"Retail Goods"
        }
    ],
    "sg:phone":"+32 2 395 72 13",
    "sg:postcode":"7850",
    "sg:province":"Hainaut",
    "sg:tags":[
        "slipper",
        "-"
    ],
    "wof:name":"Cachou",
    "wof:placetype":"venue"
},
  "geometry": {"coordinates":[4.0425429344,50.6949615479],"type":"Point"}
}