{
  "type": "Feature",
  "properties": {
    "iso:country":"BE",
    "sg:address":"Chauss\u00c9e De Louvain 41",
    "sg:city":"Eghezee",
    "sg:orig_category":"Herenkledingzaken",
    "sg:phone":"+32 81 81 27 27",
    "sg:postcode":"5310",
    "sg:province":"Namur",
    "wof:name":"Maison Pile Ou Face",
    "wof:placetype":"venue"
},
  "geometry": {"coordinates":[4.9092059135,50.5945091248],"type":"Point"}
}