{
  "type": "Feature",
  "properties": {
    "addr:full":"Corduwaniersstraat 65 Gent Oost-Vlaanderen 9000",
    "addr:housenumber":"65",
    "addr:postcode":"9000",
    "addr:street":"Corduwaniersstraat;Oost-Vlaanderen",
    "iso:country":"BE",
    "sg:address":"Corduwaniersstraat 65",
    "sg:city":"Gent",
    "sg:classifiers":[
        {
            "category":"Retail",
            "subcategory":"Event Space",
            "type":"Services"
        }
    ],
    "sg:phone":"+32 9 223 42 41",
    "sg:postcode":"9000",
    "sg:province":"Oost-Vlaanderen",
    "sg:tags":[
        "rental",
        "-",
        "hall"
    ],
    "wof:name":"Klokhuys ('t)",
    "wof:placetype":"venue"
},
  "geometry": {"coordinates":[3.7234098911,51.0579986572],"type":"Point"}
}