{
  "type": "Feature",
  "properties": {
    "addr:full":"Laarderweg 104 Peer Limburg 3990",
    "addr:housenumber":"104",
    "addr:postcode":"3990",
    "addr:street":"Laarderweg",
    "iso:country":"BE",
    "sg:address":"Laarderweg 104",
    "sg:city":"Peer",
    "sg:orig_category":"Eleveurs de bovins",
    "sg:phone":"+32 11 63 38 67",
    "sg:postcode":"3990",
    "sg:province":"Limburg",
    "wof:name":"Henri Hesius",
    "wof:placetype":"venue"
},
  "geometry": {"coordinates":[5.5117349625,51.1407928467],"type":"Point"}
}