{
  "type": "Feature",
  "properties": {
    "iso:country":"BE",
    "sg:address":"Rue Des Communes 12",
    "sg:city":"Genappe (baisy-thy)",
    "sg:classifiers":[
        {
            "category":"Parking",
            "subcategory":"Lot",
            "type":"Transportation"
        }
    ],
    "sg:phone":"+32 10 61 26 21",
    "sg:postcode":"1470",
    "sg:province":"Brabant Wallon",
    "sg:tags":[
        "-",
        "livestock",
        "transport"
    ],
    "wof:name":"Van Walleghem R",
    "wof:placetype":"venue"
},
  "geometry": {"coordinates":[4.5083580017,50.6034164429],"type":"Point"}
}