{
  "type": "Feature",
  "properties": {
    "addr:full":"Rue Brouck Au Tilleul 1 Bassenge Li\u00e8ge 4690",
    "addr:housenumber":"1",
    "addr:postcode":"4690",
    "addr:street":"Rue Brouck Au Tilleul",
    "iso:country":"BE",
    "sg:address":"Rue Brouck Au Tilleul 1",
    "sg:city":"Bassenge",
    "sg:classifiers":[
        {
            "category":"Arena",
            "subcategory":"Sports Club",
            "type":"Entertainment"
        }
    ],
    "sg:phone":"+32 4 286 16 90",
    "sg:postcode":"4690",
    "sg:province":"Li\u00e8ge",
    "sg:tags":[
        "de"
    ],
    "wof:name":"M.c. Casino",
    "wof:placetype":"venue"
},
  "geometry": {"coordinates":[5.5438499451,50.7564201355],"type":"Point"}
}