{
  "type": "Feature",
  "properties": {
    "addr:full":"Diepestraat 6 Wemmel Vlaams-Brabant 1780",
    "addr:housenumber":"6",
    "addr:postcode":"1780",
    "addr:street":"Diepestraat;Vlaams-Brabant",
    "iso:country":"BE",
    "sg:address":"Diepestraat 6",
    "sg:city":"Wemmel",
    "sg:classifiers":[
        {
            "category":"Insurance",
            "subcategory":"Life Insurance",
            "type":"Services"
        }
    ],
    "sg:phone":"+32 2 461 09 09",
    "sg:postcode":"1780",
    "sg:province":"Vlaams-Brabant",
    "sg:tags":[
        "assurance"
    ],
    "wof:name":"Verheyen",
    "wof:placetype":"venue"
},
  "geometry": {"coordinates":[4.3121099472,50.8995399475],"type":"Point"}
}