{
  "type": "Feature",
  "properties": {
    "iso:country":"BE",
    "sg:address":"Rue Patenier 57",
    "sg:city":"Namur",
    "sg:orig_category":"Avocats and conseillers juridiques",
    "sg:phone":"+32 81 73 66 58",
    "sg:postcode":"5000",
    "sg:province":"Namur",
    "wof:name":"D. Wattiez",
    "wof:placetype":"venue"
},
  "geometry": {"coordinates":[4.8463191986,50.4634475708],"type":"Point"}
}