{
  "type": "Feature",
  "properties": {
    "addr:full":"Geallieerdenlaan 195 Moeskroen/mouscron Hainaut 7711",
    "addr:housenumber":"195",
    "addr:postcode":"7711",
    "addr:street":"Geallieerdenlaan",
    "iso:country":"BE",
    "sg:address":"Geallieerdenlaan 195",
    "sg:city":"Moeskroen/mouscron",
    "sg:orig_category":"Voertuigen",
    "sg:phone":"+32 56 48 58 48",
    "sg:postcode":"7711",
    "sg:province":"Hainaut",
    "wof:name":"Auto Jacques",
    "wof:placetype":"venue"
},
  "geometry": {"coordinates":[3.2929000854,50.7344207764],"type":"Point"}
}