{
  "type": "Feature",
  "properties": {
    "iso:country":"BE",
    "sg:address":"Chauss\u00e9e De Waterloo 1104",
    "sg:city":"Bruxelles (uccle)",
    "sg:orig_category":"Non-Classified Establishments",
    "sg:phone":"+32 2 374 53 72",
    "sg:postcode":"1180",
    "sg:province":"Bruxelles-Capitale",
    "wof:name":"Cycles Derycke",
    "wof:placetype":"venue"
},
  "geometry": {"coordinates":[4.3755412102,50.7975196838],"type":"Point"}
}