{
  "type": "Feature",
  "properties": {
    "iso:country":"BE",
    "sg:address":"Koning Albertlaan 14",
    "sg:city":"Lanaken",
    "sg:orig_category":"Openbare veiligheid",
    "sg:phone":"+32 89 71 20 94",
    "sg:postcode":"3620",
    "sg:province":"Limburg",
    "wof:name":"Federale Politie",
    "wof:placetype":"venue"
},
  "geometry": {"coordinates":[5.6564440727,50.8918228149],"type":"Point"}
}