{
  "type": "Feature",
  "properties": {
    "addr:full":"Boulevard D'anvers 14 Bruxelles Bruxelles-Capitale 1000",
    "addr:housenumber":"14",
    "addr:postcode":"1000",
    "addr:street":"Boulevard D'Anvers",
    "iso:country":"BE",
    "sg:address":"Boulevard D'anvers 14",
    "sg:city":"Bruxelles",
    "sg:classifiers":[
        {
            "category":"Cafe",
            "type":"Food & Drink"
        }
    ],
    "sg:phone":"+32 2 218 41 74",
    "sg:postcode":"1000",
    "sg:province":"Bruxelles-Capitale",
    "sg:tags":[
        "snack-bars"
    ],
    "wof:name":"Jardin Des Champs Elys\u00e9es",
    "wof:placetype":"venue"
},
  "geometry": {"coordinates":[4.3537139893,50.856300354],"type":"Point"}
}