{
  "type": "Feature",
  "properties": {
    "addr:full":"Rue Edouard Henrard 2 Oudergem/auderghem Bruxelles-Capitale 1160",
    "addr:housenumber":"2",
    "addr:postcode":"1160",
    "addr:street":"Rue Edouard Henrard;/",
    "iso:country":"BE",
    "sg:address":"Rue Edouard Henrard 2",
    "sg:city":"Oudergem/auderghem",
    "sg:orig_category":"Maroquinerie and articles de voyage",
    "sg:phone":"+32 2 660 98 45",
    "sg:postcode":"1160",
    "sg:province":"Bruxelles-Capitale",
    "wof:name":"Maison New R\u00c9sidence",
    "wof:placetype":"venue"
},
  "geometry": {"coordinates":[4.4085421562,50.8232269287],"type":"Point"}
}