{
  "type": "Feature",
  "properties": {
    "iso:country":"BE",
    "sg:address":"Deken Adamstraat 5",
    "sg:city":"Turnhout",
    "sg:orig_category":"Beautyfarms, relaxatie and lichamelijk welzijn",
    "sg:phone":"+32 14 72 32 88",
    "sg:postcode":"2300",
    "sg:province":"Antwerpen",
    "wof:name":"Sun City",
    "wof:placetype":"venue"
},
  "geometry": {"coordinates":[4.9457302094,51.3203163147],"type":"Point"}
}