{
  "type": "Feature",
  "properties": {
    "iso:country":"BE",
    "sg:address":"Koolmijnlaan 78a",
    "sg:city":"Houthalen-helchteren (houthalen)",
    "sg:classifiers":[
        {
            "category":"Professional",
            "subcategory":"Testing Lab",
            "type":"Services"
        }
    ],
    "sg:phone":"+32 11 52 02 02",
    "sg:postcode":"3530",
    "sg:province":"Limburg",
    "sg:tags":[
        "chemist"
    ],
    "wof:name":"Langenaeken C",
    "wof:placetype":"venue"
},
  "geometry": {"coordinates":[5.3874168396,51.0190963745],"type":"Point"}
}