{
  "type": "Feature",
  "properties": {
    "addr:full":"Goorstraat 18 Meerhout Antwerpen 2450",
    "addr:housenumber":"18",
    "addr:postcode":"2450",
    "addr:street":"Goorstraat",
    "iso:country":"BE",
    "sg:address":"Goorstraat 18",
    "sg:city":"Meerhout",
    "sg:orig_category":"Ordinateurs and \u00e9quipement informatique",
    "sg:phone":"+32 14 71 00 90",
    "sg:postcode":"2450",
    "sg:province":"Antwerpen",
    "wof:name":"Comr@d",
    "wof:placetype":"venue"
},
  "geometry": {"coordinates":[5.0794677734,51.1324539185],"type":"Point"}
}