{
  "type": "Feature",
  "properties": {
    "iso:country":"BE",
    "sg:address":"Daalstraat 4",
    "sg:city":"Zutendaal",
    "sg:classifiers":[
        {
            "category":"Health Services",
            "subcategory":"Health Practitioner",
            "type":"Services"
        }
    ],
    "sg:phone":"+32 89 61 17 85",
    "sg:postcode":"3690",
    "sg:province":"Limburg",
    "sg:tags":[
        "physiotherapist"
    ],
    "wof:name":"Bijnens Hendrik",
    "wof:placetype":"venue"
},
  "geometry": {"coordinates":[5.571231842,50.9316596985],"type":"Point"}
}