{
  "type": "Feature",
  "properties": {
    "addr:full":"Polenplein 11b1 Roeselare West-Vlaanderen 8800",
    "addr:housenumber":"11b1",
    "addr:postcode":"8800",
    "addr:street":"Polenplein",
    "iso:country":"BE",
    "sg:address":"Polenplein 11b1",
    "sg:city":"Roeselare",
    "sg:orig_category":"M\u00e9decines alternatives",
    "sg:phone":"+32 51 20 65 58",
    "sg:postcode":"8800",
    "sg:province":"West-Vlaanderen",
    "wof:name":"B. Lambrecht",
    "wof:placetype":"venue"
},
  "geometry": {"coordinates":[3.1267740726,50.9444274902],"type":"Point"}
}