{
  "type": "Feature",
  "properties": {
    "addr:full":"Boulevard De L'imp\u00e9ratrice 70-72 Bruxelles Bruxelles-Capitale 1000",
    "addr:housenumber":"70-72",
    "addr:postcode":"1000",
    "addr:street":"Boulevard De L'Impe \u0301Ratrice",
    "iso:country":"BE",
    "sg:address":"Boulevard De L'imp\u00e9ratrice 70-72",
    "sg:city":"Bruxelles",
    "sg:classifiers":[
        {
            "category":"Travel",
            "subcategory":"Travel Agent",
            "type":"Entertainment"
        }
    ],
    "sg:phone":"+32 2 509 45 11",
    "sg:postcode":"1000",
    "sg:province":"Bruxelles-Capitale",
    "sg:tags":[
        "agency"
    ],
    "wof:name":"Cit Travel Belgium",
    "wof:placetype":"venue"
},
  "geometry": {"coordinates":[4.3570809364,50.8473930359],"type":"Point"}
}