{
  "type": "Feature",
  "properties": {
    "addr:full":"Bld De La Sauveni\u00c8re 72b11 Li\u00c8ge Li\u00e8ge 4000",
    "addr:housenumber":"72b11",
    "addr:postcode":"4000",
    "addr:street":"Bld De La Sauvenie\u0300Re",
    "iso:country":"BE",
    "sg:address":"Bld De La Sauveni\u00c8re 72b11",
    "sg:city":"Li\u00c8ge",
    "sg:orig_category":"S\u00e9curit\u00e9 sociale",
    "sg:phone":"+32 4 222 27 44",
    "sg:postcode":"4000",
    "sg:province":"Li\u00e8ge",
    "wof:name":"Euromut Mutualit\u00c9",
    "wof:placetype":"venue"
},
  "geometry": {"coordinates":[5.5663890839,50.643863678],"type":"Point"}
}