{
  "type": "Feature",
  "properties": {
    "iso:country":"BE",
    "sg:address":"Centrumlaan 12",
    "sg:city":"Ninove",
    "sg:orig_category":"Epiceries",
    "sg:phone":"+32 54 34 16 85",
    "sg:postcode":"9400",
    "sg:province":"Oost-Vlaanderen",
    "wof:name":"Absolu Kids",
    "wof:placetype":"venue"
},
  "geometry": {"coordinates":[4.0218100548,50.8344955444],"type":"Point"}
}