{
  "type": "Feature",
  "properties": {
    "addr:full":"Goebilkstraat 3 Maldegem Oost-Vlaanderen 9990",
    "addr:housenumber":"3",
    "addr:postcode":"9990",
    "addr:street":"Goebilkstraat",
    "iso:country":"BE",
    "sg:address":"Goebilkstraat 3",
    "sg:city":"Maldegem",
    "sg:orig_category":"Rundveehouders Varkenskwekers",
    "sg:phone":"+32 50 71 18 82",
    "sg:postcode":"9990",
    "sg:province":"Oost-Vlaanderen",
    "wof:name":"Aime Dobbelaere",
    "wof:placetype":"venue"
},
  "geometry": {"coordinates":[3.4105780125,51.1841087341],"type":"Point"}
}