{
  "type": "Feature",
  "properties": {
    "addr:full":"Drie Eikenstraat 112 Edegem Antwerpen 2650",
    "addr:housenumber":"112",
    "addr:postcode":"2650",
    "addr:street":"Drie Eikenstraat",
    "iso:country":"BE",
    "sg:address":"Drie Eikenstraat 112",
    "sg:city":"Edegem",
    "sg:classifiers":[
        {
            "category":"Manufacturing",
            "subcategory":"Electronics",
            "type":"Manufacturing & Wholesale Goods"
        }
    ],
    "sg:phone":"+32 3 457 24 82",
    "sg:postcode":"2650",
    "sg:province":"Antwerpen",
    "sg:tags":[
        "industrial",
        "cable"
    ],
    "wof:name":"Wisman Electro Techniek B.v.",
    "wof:placetype":"venue"
},
  "geometry": {"coordinates":[4.4379839897,51.1558151245],"type":"Point"}
}