{
  "type": "Feature",
  "properties": {
    "iso:country":"BE",
    "sg:address":"Rode Kruislaan 5",
    "sg:city":"Aarschot",
    "sg:classifiers":[
        {
            "category":"Professional",
            "subcategory":"Accounting & Tax Preparation",
            "type":"Services"
        }
    ],
    "sg:phone":"+32 16 56 96 96",
    "sg:postcode":"3200",
    "sg:province":"Vlaams-Brabant",
    "sg:tags":[
        "bookkeeper"
    ],
    "wof:name":"De Wachter A",
    "wof:placetype":"venue"
},
  "geometry": {"coordinates":[4.8416399956,50.993270874],"type":"Point"}
}