{
  "type": "Feature",
  "properties": {
    "addr:full":"Helkijnstraat 38 Zwevegem (sint-denijs) West-Vlaanderen 8554",
    "addr:housenumber":"38",
    "addr:postcode":"8554",
    "addr:street":"Helkijnstraat",
    "iso:country":"BE",
    "sg:address":"Helkijnstraat 38",
    "sg:city":"Zwevegem (sint-denijs)",
    "sg:classifiers":[
        {
            "category":"Food & Beverages",
            "subcategory":"Supermarket",
            "type":"Retail Goods"
        }
    ],
    "sg:phone":"+32 56 45 68 82",
    "sg:postcode":"8554",
    "sg:province":"West-Vlaanderen",
    "sg:tags":[
        "department",
        "store"
    ],
    "wof:name":"Prpma Vanhee-shopping",
    "wof:placetype":"venue"
},
  "geometry": {"coordinates":[3.3706920147,50.7496185303],"type":"Point"}
}