{
  "type": "Feature",
  "properties": {
    "addr:full":"Gullegemsestraat 90 Ledegem (sint-eloois-winkel) West-Vlaanderen 8880",
    "addr:housenumber":"90",
    "addr:postcode":"8880",
    "addr:street":"Gullegemsestraat",
    "iso:country":"BE",
    "sg:address":"Gullegemsestraat 90",
    "sg:city":"Ledegem (sint-eloois-winkel)",
    "sg:classifiers":[
        {
            "category":"Personal",
            "subcategory":"Beauty Salon",
            "type":"Services"
        }
    ],
    "sg:phone":"+32 56 50 24 01",
    "sg:postcode":"8880",
    "sg:province":"West-Vlaanderen",
    "sg:tags":[
        "lady",
        "-",
        "hairdressing"
    ],
    "wof:name":"Els",
    "wof:placetype":"venue"
},
  "geometry": {"coordinates":[3.1837949753,50.8702888489],"type":"Point"}
}