{
  "type": "Feature",
  "properties": {
    "iso:country":"BE",
    "sg:address":"Rue Des C\u00e9lestines 13",
    "sg:city":"Li\u00e8ge 1",
    "sg:classifiers":[
        {
            "category":"Bars & Pubs",
            "type":"Food & Drink"
        }
    ],
    "sg:phone":"+32 4 250 55 50",
    "sg:postcode":"4000",
    "sg:province":"Li\u00e8ge",
    "wof:name":"Diff\u00e9rence (la)",
    "wof:placetype":"venue"
},
  "geometry": {"coordinates":[5.5685992241,50.6417274475],"type":"Point"}
}