{
  "type": "Feature",
  "properties": {
    "addr:full":"Rue Du Thier 40 Soumagne (evegn\u00e9e-tign\u00e9e) Li\u00e8ge 4631",
    "addr:housenumber":"40",
    "addr:postcode":"4631",
    "addr:street":"Rue Du Thier;Evegne\u0301E-Tigne\u0301E",
    "iso:country":"BE",
    "sg:address":"Rue Du Thier 40",
    "sg:city":"Soumagne (evegn\u00e9e-tign\u00e9e)",
    "sg:classifiers":[
        {
            "category":"Banks & Credit Unions",
            "subcategory":"Bureau De Change",
            "type":"Services"
        }
    ],
    "sg:phone":"+32 4 377 29 31",
    "sg:postcode":"4631",
    "sg:province":"Li\u00e8ge",
    "sg:tags":[
        "measuring",
        "control",
        "apparatus"
    ],
    "wof:name":"E.g.e.p.",
    "wof:placetype":"venue"
},
  "geometry": {"coordinates":[5.7080960274,50.6459503174],"type":"Point"}
}