{
  "type": "Feature",
  "properties": {
    "iso:country":"BE",
    "sg:address":"Beauduinstraat 24",
    "sg:city":"Tienen",
    "sg:orig_category":"Opticiens",
    "sg:phone":"+32 16 81 97 76",
    "sg:postcode":"3300",
    "sg:province":"Vlaams-Brabant",
    "wof:name":"Frederic Van Lindt",
    "wof:placetype":"venue"
},
  "geometry": {"coordinates":[4.9416680336,50.8052825928],"type":"Point"}
}