{
  "type": "Feature",
  "properties": {
    "addr:full":"Bloemenhofplein 12 Brussel/bruxelles Bruxelles-Capitale 1000",
    "addr:housenumber":"12",
    "addr:postcode":"1000",
    "addr:street":"Bloemenhofplein;/",
    "iso:country":"BE",
    "sg:address":"Bloemenhofplein 12",
    "sg:city":"Brussel/bruxelles",
    "sg:orig_category":"Binnenhuisarchitecten",
    "sg:phone":"+32 2 511 54 43",
    "sg:postcode":"1000",
    "sg:province":"Bruxelles-Capitale",
    "wof:name":"Verhoustraeten Axel & Cie",
    "wof:placetype":"venue"
},
  "geometry": {"coordinates":[4.343211174,50.8480262756],"type":"Point"}
}