{
  "type": "Feature",
  "properties": {
    "iso:country":"BE",
    "sg:address":"Rue Joseph Wauters 48",
    "sg:city":"Saint-georges-sur-meuse",
    "sg:orig_category":"Boucheries",
    "sg:phone":"+32 4 275 30 16",
    "sg:postcode":"4470",
    "sg:province":"Li\u00e8ge",
    "wof:name":"Verte Campagne",
    "wof:placetype":"venue"
},
  "geometry": {"coordinates":[5.3610901833,50.578289032],"type":"Point"}
}