{
  "type": "Feature",
  "properties": {
    "addr:full":"Rodenemweg 35 Halle Vlaams-Brabant 1500",
    "addr:housenumber":"35",
    "addr:postcode":"1500",
    "addr:street":"Rodenemweg",
    "iso:country":"BE",
    "sg:address":"Rodenemweg 35",
    "sg:city":"Halle",
    "sg:orig_category":"Agences de publicit\u00e9",
    "sg:phone":"+32 2 361 38 92",
    "sg:postcode":"1500",
    "sg:province":"Vlaams-Brabant",
    "wof:name":"Philippe Thiery",
    "wof:placetype":"venue"
},
  "geometry": {"coordinates":[4.2364859581,50.726234436],"type":"Point"}
}