{
  "type": "Feature",
  "properties": {
    "addr:full":"Rue Joseph Wauters 35 La Louviere Hainaut 7110",
    "addr:housenumber":"35",
    "addr:postcode":"7110",
    "addr:street":"Rue Joseph Wauters",
    "iso:country":"BE",
    "sg:address":"Rue Joseph Wauters 35",
    "sg:city":"La Louviere",
    "sg:orig_category":"Banques and organismes de cr\u00e9dit",
    "sg:phone":"+32 64 67 68 63",
    "sg:postcode":"7110",
    "sg:province":"Hainaut",
    "wof:name":"Dexia",
    "wof:placetype":"venue"
},
  "geometry": {"coordinates":[4.1505050659,50.4826698303],"type":"Point"}
}