{
  "type": "Feature",
  "properties": {
    "iso:country":"BE",
    "sg:address":"Onze-lieve-vrouwestraat 42",
    "sg:city":"Kortrijk",
    "sg:classifiers":[
        {
            "category":"Shopping",
            "subcategory":"Antiques",
            "type":"Retail Goods"
        }
    ],
    "sg:phone":"+32 56 22 37 21",
    "sg:postcode":"8500",
    "sg:province":"West-Vlaanderen",
    "wof:name":"Antiquair Dejans P",
    "wof:placetype":"venue"
},
  "geometry": {"coordinates":[3.266518116,50.8290634155],"type":"Point"}
}