{
  "type": "Feature",
  "properties": {
    "iso:country":"BE",
    "sg:address":"Reperstraat 108",
    "sg:city":"Izegem",
    "sg:orig_category":"Diverse producten Gh",
    "sg:phone":"+32 51 31 64 48",
    "sg:postcode":"8870",
    "sg:province":"West-Vlaanderen",
    "wof:name":"Kariz",
    "wof:placetype":"venue"
},
  "geometry": {"coordinates":[3.2200250626,50.9322013855],"type":"Point"}
}