{
  "type": "Feature",
  "properties": {
    "addr:full":"Rue Croix Sainte-anne 42 Wellin (lomprez) Luxembourg 6924",
    "addr:housenumber":"42",
    "addr:postcode":"6924",
    "addr:street":"Rue Croix Sainte-Anne",
    "iso:country":"BE",
    "sg:address":"Rue Croix Sainte-anne 42",
    "sg:city":"Wellin (lomprez)",
    "sg:classifiers":[
        {
            "category":"Retail",
            "subcategory":"Veterinary Services",
            "type":"Services"
        }
    ],
    "sg:phone":"+32 84 38 88 29",
    "sg:postcode":"6924",
    "sg:province":"Luxembourg",
    "sg:tags":[
        "veterinarian"
    ],
    "wof:name":"Bughin J",
    "wof:placetype":"venue"
},
  "geometry": {"coordinates":[5.0913619995,50.0778808594],"type":"Point"}
}