{
  "type": "Feature",
  "properties": {
    "addr:full":"Rue Cit\u00c9 Du Chestia 3 Profondeville Namur 5170",
    "addr:housenumber":"3",
    "addr:postcode":"5170",
    "addr:street":"Rue Cite\u0301 Du Chestia",
    "iso:country":"BE",
    "sg:address":"Rue Cit\u00c9 Du Chestia 3",
    "sg:city":"Profondeville",
    "sg:orig_category":"Rev\u00eatements pour sols and murs",
    "sg:phone":"+32 81 43 39 49",
    "sg:postcode":"5170",
    "sg:province":"Namur",
    "wof:name":"Fe. Blanchy",
    "wof:placetype":"venue"
},
  "geometry": {"coordinates":[4.8674049377,50.3786392212],"type":"Point"}
}