{
  "type": "Feature",
  "properties": {
    "addr:full":"Rue Du Grand Brou 12a Beauvechain (tourinnes-la-grosse) Brabant Wallon 1320",
    "addr:housenumber":"12a",
    "addr:postcode":"1320",
    "addr:street":"Rue Du Grand Brou;Wallon",
    "iso:country":"BE",
    "sg:address":"Rue Du Grand Brou 12a",
    "sg:city":"Beauvechain (tourinnes-la-grosse)",
    "sg:classifiers":[
        {
            "category":"Personal",
            "subcategory":"Beauty Salon",
            "type":"Services"
        }
    ],
    "sg:phone":"+32 10 86 11 50",
    "sg:postcode":"1320",
    "sg:province":"Brabant Wallon",
    "sg:tags":[
        "lady",
        "-",
        "hairdressing"
    ],
    "wof:name":"Crea-tifs",
    "wof:placetype":"venue"
},
  "geometry": {"coordinates":[4.7386932373,50.7803459167],"type":"Point"}
}