{
  "type": "Feature",
  "properties": {
    "iso:country":"BE",
    "sg:address":"Rue Du Fays 19",
    "sg:city":"Fosses-la-ville",
    "sg:orig_category":"Rundveehouders",
    "sg:phone":"+32 71 71 15 50",
    "sg:postcode":"5070",
    "sg:province":"Namur",
    "wof:name":"Emile Godart",
    "wof:placetype":"venue"
},
  "geometry": {"coordinates":[4.6595721245,50.4054794312],"type":"Point"}
}