{
  "type": "Feature",
  "properties": {
    "iso:country":"BE",
    "sg:address":"Oostendse Baan 20a",
    "sg:city":"Gistel",
    "sg:classifiers":[
        {
            "category":"Personal",
            "subcategory":"Beauty Salon",
            "type":"Services"
        }
    ],
    "sg:phone":"+32 59 27 52 08",
    "sg:postcode":"8470",
    "sg:province":"West-Vlaanderen",
    "wof:name":"Nollet S",
    "wof:placetype":"venue"
},
  "geometry": {"coordinates":[2.9529900551,51.1502876282],"type":"Point"}
}