{
  "type": "Feature",
  "properties": {
    "addr:full":"Stationstraat 49ba Olen Antwerpen 2250",
    "addr:housenumber":"49ba",
    "addr:postcode":"2250",
    "addr:street":"Stationstraat",
    "iso:country":"BE",
    "sg:address":"Stationstraat 49ba",
    "sg:city":"Olen",
    "sg:orig_category":"Banken and kredietinstellingen Verzekeringsmakelaars and experts",
    "sg:phone":"+32 14 23 45 75",
    "sg:postcode":"2250",
    "sg:province":"Antwerpen",
    "wof:name":"Groep Argenta",
    "wof:placetype":"venue"
},
  "geometry": {"coordinates":[4.8600449562,51.1438446045],"type":"Point"}
}