{
  "type": "Feature",
  "properties": {
    "iso:country":"BE",
    "sg:address":"Zwaluwstraat 57",
    "sg:city":"Lokeren",
    "sg:orig_category":"Binnenhuisarchitecten",
    "sg:phone":"+32 9 348 36 23",
    "sg:postcode":"9160",
    "sg:province":"Oost-Vlaanderen",
    "wof:name":"Zadra Consulting",
    "wof:placetype":"venue"
},
  "geometry": {"coordinates":[4.0116081238,51.1124687195],"type":"Point"}
}