{
  "type": "Feature",
  "properties": {
    "iso:country":"BE",
    "sg:address":"Schooldreef 41",
    "sg:city":"Kalmthout",
    "sg:orig_category":"Enseignement maternel and primaire",
    "sg:phone":"+32 3 666 95 21",
    "sg:postcode":"2920",
    "sg:province":"Antwerpen",
    "wof:name":"Vrije Lagere School",
    "wof:placetype":"venue"
},
  "geometry": {"coordinates":[4.4697961807,51.3953475952],"type":"Point"}
}