{
  "type": "Feature",
  "properties": {
    "iso:country":"BE",
    "sg:address":"Emiel Banningstraat 56",
    "sg:city":"Antwerpen",
    "sg:classifiers":[
        {
            "category":"Retail",
            "subcategory":"Car Wash",
            "type":"Services"
        }
    ],
    "sg:phone":"+32 3 237 45 95",
    "sg:postcode":"2000",
    "sg:province":"Antwerpen",
    "sg:tags":[
        "automobile",
        "washing",
        "-",
        "truck"
    ],
    "wof:name":"City Car Wash (new)",
    "wof:placetype":"venue"
},
  "geometry": {"coordinates":[4.3886728287,51.205329895],"type":"Point"}
}