{
  "type": "Feature",
  "properties": {
    "iso:country":"BE",
    "sg:address":"Avil Geerincklaan 58",
    "sg:city":"Zele",
    "sg:orig_category":"Assistances juridiques. Conseillers fiscaux",
    "sg:phone":"+32 52 45 02 25",
    "sg:postcode":"9240",
    "sg:province":"Oost-Vlaanderen",
    "wof:name":"Demdes",
    "wof:placetype":"venue"
},
  "geometry": {"coordinates":[4.0359778404,51.0708236694],"type":"Point"}
}