{
  "type": "Feature",
  "properties": {
    "addr:full":"Quai Donat Casterman 57 Tournai Hainaut 7500",
    "addr:housenumber":"57",
    "addr:postcode":"7500",
    "addr:street":"Quai Donat Casterman",
    "iso:country":"BE",
    "sg:address":"Quai Donat Casterman 57",
    "sg:city":"Tournai",
    "sg:classifiers":[
        {
            "category":"Building & Trades",
            "subcategory":"Equipment Rental",
            "type":"Services"
        }
    ],
    "sg:postcode":"7500",
    "sg:province":"Hainaut",
    "sg:tags":[
        "crane",
        "-"
    ],
    "wof:name":"Translomat Sa-thiebaut",
    "wof:placetype":"venue"
},
  "geometry": {"coordinates":[3.378770113,50.6171607971],"type":"Point"}
}