{
  "type": "Feature",
  "properties": {
    "iso:country":"BE",
    "sg:address":"Zavelvennestraat 82",
    "sg:city":"Hasselt",
    "sg:classifiers":[
        {
            "category":"Real Estate",
            "subcategory":"Architect",
            "type":"Services"
        }
    ],
    "sg:phone":"+32 11 72 88 75",
    "sg:postcode":"3500",
    "sg:province":"Limburg",
    "wof:name":"Castro S",
    "wof:placetype":"venue"
},
  "geometry": {"coordinates":[5.3724598885,50.968460083],"type":"Point"}
}