{
  "type": "Feature",
  "properties": {
    "addr:full":"Wathermal 17 Gouvy Luxembourg 6672",
    "addr:housenumber":"17",
    "addr:postcode":"6672",
    "addr:street":"Wathermal",
    "iso:country":"BE",
    "sg:address":"Wathermal 17",
    "sg:city":"Gouvy",
    "sg:orig_category":"P\u00e9pini\u00e9ristes",
    "sg:phone":"+32 80 51 08 20",
    "sg:postcode":"6672",
    "sg:province":"Luxembourg",
    "wof:name":"Roland Halin",
    "wof:placetype":"venue"
},
  "geometry": {"coordinates":[5.981675148,50.1798629761],"type":"Point"}
}