{
  "type": "Feature",
  "properties": {
    "addr:full":"Rue De La Halle 20 Lessines Hainaut 7860",
    "addr:housenumber":"20",
    "addr:postcode":"7860",
    "addr:street":"Rue De La Halle;Hainaut",
    "iso:country":"BE",
    "sg:address":"Rue De La Halle 20",
    "sg:city":"Lessines",
    "sg:orig_category":"Avocats and conseillers juridiques",
    "sg:phone":"+32 68 33 40 58",
    "sg:postcode":"7860",
    "sg:province":"Hainaut",
    "wof:name":"N. Joly",
    "wof:placetype":"venue"
},
  "geometry": {"coordinates":[3.8298239708,50.7111206055],"type":"Point"}
}