{
  "type": "Feature",
  "properties": {
    "addr:full":"Rue Haute 139 Bruxelles Bruxelles-Capitale 1000",
    "addr:housenumber":"139",
    "addr:postcode":"1000",
    "addr:street":"Rue Haute",
    "iso:country":"BE",
    "sg:address":"Rue Haute 139",
    "sg:city":"Bruxelles",
    "sg:classifiers":[
        {
            "category":"Retail",
            "subcategory":"Event Space",
            "type":"Services"
        }
    ],
    "sg:phone":"+32 2 502 58 50",
    "sg:postcode":"1000",
    "sg:province":"Bruxelles-Capitale",
    "sg:tags":[
        "rental",
        "-",
        "hall"
    ],
    "wof:name":"Orangerie D'egmont (l')",
    "wof:placetype":"venue"
},
  "geometry": {"coordinates":[4.3501391411,50.8386421204],"type":"Point"}
}