{
  "type": "Feature",
  "properties": {
    "iso:country":"BE",
    "sg:address":"Dorpsstraat 57",
    "sg:city":"Staden",
    "sg:orig_category":"Bloemen and planten",
    "sg:phone":"+32 51 77 24 02",
    "sg:postcode":"8840",
    "sg:province":"West-Vlaanderen",
    "wof:name":"Puur Apart",
    "wof:placetype":"venue"
},
  "geometry": {"coordinates":[3.0124590397,50.9319648743],"type":"Point"}
}