{
  "type": "Feature",
  "properties": {
    "iso:country":"BE",
    "sg:address":"Lod. Vankeerberghenstr. 44",
    "sg:city":"Machelen",
    "sg:classifiers":[
        {
            "category":"Arena",
            "subcategory":"Sports Club",
            "type":"Entertainment"
        }
    ],
    "sg:phone":"+32 2 725 22 97",
    "sg:postcode":"1831",
    "sg:province":"Vlaams-Brabant",
    "sg:tags":[
        "terrain",
        "hors",
        "de",
        "installation",
        "sportifs"
    ],
    "wof:name":"K. Steenokkerzeel Vlug Op",
    "wof:placetype":"venue"
},
  "geometry": {"coordinates":[4.4403457642,50.8904876709],"type":"Point"}
}