{
  "type": "Feature",
  "properties": {
    "addr:full":"Sint-katelijnestraat 46 Brussel/bruxelles Bruxelles-Capitale 1000",
    "addr:housenumber":"46",
    "addr:postcode":"1000",
    "addr:street":"Sint-Katelijnestraat;/",
    "iso:country":"BE",
    "sg:address":"Sint-katelijnestraat 46",
    "sg:city":"Brussel/bruxelles",
    "sg:classifiers":[
        {
            "category":"Food & Beverages",
            "subcategory":"Meat & Fish",
            "type":"Retail Goods"
        }
    ],
    "sg:phone":"+32 2 512 75 47",
    "sg:postcode":"1000",
    "sg:province":"Bruxelles-Capitale",
    "sg:tags":[
        "vi",
        "zeevruchten"
    ],
    "wof:name":"Poissonnerie A.b.c.",
    "wof:placetype":"venue"
},
  "geometry": {"coordinates":[4.3478851318,50.8503112793],"type":"Point"}
}