{
  "type": "Feature",
  "properties": {
    "addr:full":"Rue Joseph-renquin 11 Bastogne Luxembourg 6600",
    "addr:housenumber":"11",
    "addr:postcode":"6600",
    "addr:street":"Rue Joseph-Renquin",
    "iso:country":"BE",
    "sg:address":"Rue Joseph-renquin 11",
    "sg:city":"Bastogne",
    "sg:classifiers":[
        {
            "category":"Fast Food",
            "type":"Food & Drink"
        }
    ],
    "sg:phone":"+32 61 21 93 38",
    "sg:postcode":"6600",
    "sg:province":"Luxembourg",
    "sg:tags":[
        "huis",
        "aan",
        "levering",
        "meeneem",
        "restaurant"
    ],
    "wof:name":"New Shangai",
    "wof:placetype":"venue"
},
  "geometry": {"coordinates":[5.7154240608,50.0001335144],"type":"Point"}
}