{
  "type": "Feature",
  "properties": {
    "addr:full":"Rue Chaumont 33 Jemeppe-sur-sambre Namur 5190",
    "addr:housenumber":"33",
    "addr:postcode":"5190",
    "addr:street":"Rue Chaumont",
    "iso:country":"BE",
    "sg:address":"Rue Chaumont 33",
    "sg:city":"Jemeppe-sur-sambre",
    "sg:orig_category":"Enseignement maternel and primaire",
    "sg:phone":"+32 71 78 59 17",
    "sg:postcode":"5190",
    "sg:province":"Namur",
    "wof:name":"Ecole Fondamentale",
    "wof:placetype":"venue"
},
  "geometry": {"coordinates":[4.6703448296,50.4645042419],"type":"Point"}
}