{
  "type": "Feature",
  "properties": {
    "addr:full":"Rue Des Bruy\u00e8res 65 Mons (obourg) Hainaut 7034",
    "addr:housenumber":"65",
    "addr:postcode":"7034",
    "addr:street":"Rue Des Bruye\u0300Res",
    "iso:country":"BE",
    "sg:address":"Rue Des Bruy\u00e8res 65",
    "sg:city":"Mons (obourg)",
    "sg:orig_category":"Newspapers, magazines, periodicals - Distribution",
    "sg:phone":"+32 478 23 64 92",
    "sg:postcode":"7034",
    "sg:province":"Hainaut",
    "wof:name":"Lesire E",
    "wof:placetype":"venue"
},
  "geometry": {"coordinates":[4.0086159706,50.4765396118],"type":"Point"}
}