{
  "type": "Feature",
  "properties": {
    "addr:full":"Place D'horrues 6 Soignies (horrues) Hainaut 7060",
    "addr:housenumber":"6",
    "addr:postcode":"7060",
    "addr:street":"Place D'Horrues",
    "iso:country":"BE",
    "sg:address":"Place D'horrues 6",
    "sg:city":"Soignies (horrues)",
    "sg:classifiers":[
        {
            "category":"Health Services",
            "subcategory":"Doctor",
            "type":"Services"
        }
    ],
    "sg:phone":"+32 67 33 48 39",
    "sg:postcode":"7060",
    "sg:province":"Hainaut",
    "sg:tags":[
        "medicinephysicians",
        "surgeon"
    ],
    "wof:name":"Hanssens Chantal",
    "wof:placetype":"venue"
},
  "geometry": {"coordinates":[4.0421419144,50.6087760925],"type":"Point"}
}