{
  "type": "Feature",
  "properties": {
    "addr:full":"Dorpsstraat 60 Begijnendijk Vlaams-Brabant 3130",
    "addr:housenumber":"60",
    "addr:postcode":"3130",
    "addr:street":"Dorpsstraat",
    "iso:country":"BE",
    "sg:address":"Dorpsstraat 60",
    "sg:city":"Begijnendijk",
    "sg:orig_category":"Groententeelt",
    "sg:phone":"+32 16 53 01 35",
    "sg:postcode":"3130",
    "sg:province":"Vlaams-Brabant",
    "wof:name":"Gustaaf Verhaegen",
    "wof:placetype":"venue"
},
  "geometry": {"coordinates":[4.7762589455,51.0225067139],"type":"Point"}
}