{
  "type": "Feature",
  "properties": {
    "iso:country":"BE",
    "sg:address":"Nieuwe-heidestraat 53",
    "sg:city":"Hasselt",
    "sg:orig_category":"Experts-comptables",
    "sg:phone":"+32 11 87 83 27",
    "sg:postcode":"3500",
    "sg:province":"Limburg",
    "wof:name":"Robert Ceuppens",
    "wof:placetype":"venue"
},
  "geometry": {"coordinates":[5.3686289787,50.9467926025],"type":"Point"}
}