{
  "type": "Feature",
  "properties": {
    "addr:full":"Torenstraat 45 Wommelgem Antwerpen 2160",
    "addr:housenumber":"45",
    "addr:postcode":"2160",
    "addr:street":"Torenstraat",
    "iso:country":"BE",
    "sg:address":"Torenstraat 45",
    "sg:city":"Wommelgem",
    "sg:classifiers":[
        {
            "category":"Real Estate",
            "subcategory":"Architect",
            "type":"Services"
        }
    ],
    "sg:phone":"+32 3 353 64 23",
    "sg:postcode":"2160",
    "sg:province":"Antwerpen",
    "wof:name":"Van Oosterwijck D",
    "wof:placetype":"venue"
},
  "geometry": {"coordinates":[4.5247368813,51.2060546875],"type":"Point"}
}