{
  "type": "Feature",
  "properties": {
    "addr:full":"Avenue Com. Borlez 42 Geldenaken Brabant Wallon 1370",
    "addr:housenumber":"42;1370",
    "addr:street":"Avenue Com. Borlez;Brabant Wallon",
    "iso:country":"BE",
    "sg:address":"Avenue Com. Borlez 42",
    "sg:city":"Geldenaken",
    "sg:orig_category":"Diverse kredietdiensten",
    "sg:postcode":"1370",
    "sg:province":"Brabant Wallon",
    "wof:name":"Postomat Jodoigne",
    "wof:placetype":"venue"
},
  "geometry": {"coordinates":[4.8679351807,50.7248001099],"type":"Point"}
}