{
  "type": "Feature",
  "properties": {
    "addr:full":"Krijtestraat 45 Gent (oostakker) Oost-Vlaanderen 9041",
    "addr:housenumber":"45",
    "addr:postcode":"9041",
    "addr:street":"Krijtestraat",
    "iso:country":"BE",
    "sg:address":"Krijtestraat 45",
    "sg:city":"Gent (oostakker)",
    "sg:classifiers":[
        {
            "category":"Professional",
            "subcategory":"Accounting & Tax Preparation",
            "type":"Services"
        }
    ],
    "sg:phone":"+32 9 259 13 10",
    "sg:postcode":"9041",
    "sg:province":"Oost-Vlaanderen",
    "sg:tags":[
        "bookkeeper"
    ],
    "wof:name":"Adviesbureau De Meester",
    "wof:placetype":"venue"
},
  "geometry": {"coordinates":[3.7680799961,51.0786552429],"type":"Point"}
}