{
  "type": "Feature",
  "properties": {
    "addr:full":"Gentpoortstraat 20 Box 2 Deinze Oost-Vlaanderen 9800",
    "addr:housenumber":"20;2",
    "addr:postcode":"9800",
    "addr:street":"Gentpoortstraat;Box",
    "iso:country":"BE",
    "sg:address":"Gentpoortstraat 20 Box 2",
    "sg:city":"Deinze",
    "sg:classifiers":[
        {
            "category":"Banks & Credit Unions",
            "subcategory":"Financial Services",
            "type":"Services"
        }
    ],
    "sg:phone":"+32 9 386 92 76",
    "sg:postcode":"9800",
    "sg:province":"Oost-Vlaanderen",
    "sg:tags":[
        "loan",
        "mortgage"
    ],
    "wof:name":"Eigen Woon Door Ons Loon Nv",
    "wof:placetype":"venue"
},
  "geometry": {"coordinates":[3.5279901028,50.9846496582],"type":"Point"}
}