{
  "type": "Feature",
  "properties": {
    "iso:country":"BE",
    "sg:address":"Rue De Rochefort 163",
    "sg:city":"Ciney (leignon)",
    "sg:classifiers":[
        {
            "category":"Real Estate",
            "subcategory":"Surveying",
            "type":"Services"
        }
    ],
    "sg:phone":"+32 83 21 34 49",
    "sg:postcode":"5590",
    "sg:province":"Namur",
    "sg:tags":[
        "surveyor",
        "land"
    ],
    "wof:name":"Deculot V",
    "wof:placetype":"venue"
},
  "geometry": {"coordinates":[5.1574749947,50.255279541],"type":"Point"}
}