{
  "type": "Feature",
  "properties": {
    "addr:full":"Hasseltsesteenweg 466 Tongeren Limburg 3700",
    "addr:housenumber":"466",
    "addr:postcode":"3700",
    "addr:street":"Hasseltsesteenweg",
    "iso:country":"BE",
    "sg:address":"Hasseltsesteenweg 466",
    "sg:city":"Tongeren",
    "sg:classifiers":[
        {
            "category":"Real Estate",
            "subcategory":"Architect",
            "type":"Services"
        }
    ],
    "sg:phone":"+32 12 23 61 93",
    "sg:postcode":"3700",
    "sg:province":"Limburg",
    "wof:name":"Leemen M",
    "wof:placetype":"venue"
},
  "geometry": {"coordinates":[5.4480662346,50.7972602844],"type":"Point"}
}