{
  "type": "Feature",
  "properties": {
    "iso:country":"BE",
    "sg:address":"Onze-lieve-vrouwestraat 20",
    "sg:city":"Izegem",
    "sg:classifiers":[
        {
            "category":"Banks & Credit Unions",
            "subcategory":"Investment Brokerage",
            "type":"Services"
        }
    ],
    "sg:phone":"+32 51 30 26 59",
    "sg:postcode":"8870",
    "sg:province":"West-Vlaanderen",
    "sg:tags":[
        "printing",
        "-"
    ],
    "wof:name":"Bogaert J",
    "wof:placetype":"venue"
},
  "geometry": {"coordinates":[3.2082750797,50.9185905457],"type":"Point"}
}