{
  "type": "Feature",
  "properties": {
    "iso:country":"BE",
    "sg:address":"Rue Barre Saint-brice 28",
    "sg:city":"Tournai",
    "sg:orig_category":"M\u00e9decins and sp\u00e9cialistes",
    "sg:phone":"+32 69 22 68 74",
    "sg:postcode":"7500",
    "sg:province":"Hainaut",
    "wof:name":"Cl\u00c9ment Neerdaels",
    "wof:placetype":"venue"
},
  "geometry": {"coordinates":[3.3938250542,50.6086845398],"type":"Point"}
}