{
  "type": "Feature",
  "properties": {
    "addr:full":"Impulsstraat 22 Heist-op-den-berg Antwerpen 2220",
    "addr:housenumber":"22",
    "addr:postcode":"2220",
    "addr:street":"Impulsstraat",
    "iso:country":"BE",
    "sg:address":"Impulsstraat 22",
    "sg:city":"Heist-op-den-berg",
    "sg:classifiers":[
        {
            "category":"Building & Trades",
            "subcategory":"Construction",
            "type":"Services"
        }
    ],
    "sg:phone":"+32 15 24 97 37",
    "sg:postcode":"2220",
    "sg:province":"Antwerpen",
    "sg:tags":[
        "stone",
        "cutter"
    ],
    "wof:name":"Eggers Bvba",
    "wof:placetype":"venue"
},
  "geometry": {"coordinates":[4.7000198364,51.0611686707],"type":"Point"}
}