{
  "type": "Feature",
  "properties": {
    "addr:full":"Rue Achille Bauduin 4 Limal Brabant Wallon 1300",
    "addr:housenumber":"4",
    "addr:postcode":"1300",
    "addr:street":"Rue Achille Bauduin;Wallon",
    "iso:country":"BE",
    "sg:address":"Rue Achille Bauduin 4",
    "sg:city":"Limal",
    "sg:classifiers":[
        {
            "category":"Banks & Credit Unions",
            "subcategory":"Atm",
            "type":"Services"
        }
    ],
    "sg:phone":"+32 10 41 90 20",
    "sg:postcode":"1300",
    "sg:province":"Brabant Wallon",
    "sg:tags":[
        "closure",
        "pack"
    ],
    "wof:name":"Plastics Tmp S.a.",
    "wof:placetype":"venue"
},
  "geometry": {"coordinates":[4.6116552353,50.7134132385],"type":"Point"}
}