{
  "type": "Feature",
  "properties": {
    "iso:country":"BE",
    "sg:address":"Pastoor Paquaylaan 37",
    "sg:city":"Heusden-zolder (heusden)",
    "sg:classifiers":[
        {
            "category":"Health Services",
            "subcategory":"Health Practitioner",
            "type":"Services"
        }
    ],
    "sg:phone":"+32 11 57 23 12",
    "sg:postcode":"3550",
    "sg:province":"Limburg",
    "sg:tags":[
        "physiotherapist"
    ],
    "wof:name":"De Pauw Ph",
    "wof:placetype":"venue"
},
  "geometry": {"coordinates":[5.3033738136,51.0424880981],"type":"Point"}
}