{
  "type": "Feature",
  "properties": {
    "addr:full":"Rue Du Coll\u00c8ge 82 Elsene/ixelles Bruxelles-Capitale 1050",
    "addr:housenumber":"82",
    "addr:postcode":"1050",
    "addr:street":"Rue Du Colle\u0300Ge",
    "iso:country":"BE",
    "sg:address":"Rue Du Coll\u00c8ge 82",
    "sg:city":"Elsene/ixelles",
    "sg:orig_category":"Artistes ind\u00e9pendants",
    "sg:phone":"+32 2 649 86 74",
    "sg:postcode":"1050",
    "sg:province":"Bruxelles-Capitale",
    "wof:name":"Hubert Mestrez",
    "wof:placetype":"venue"
},
  "geometry": {"coordinates":[4.3702979088,50.8320503235],"type":"Point"}
}