{
  "type": "Feature",
  "properties": {
    "addr:full":"Massenetlaan 23 Vorst/forest Bruxelles-Capitale 1190",
    "addr:housenumber":"23",
    "addr:postcode":"1190",
    "addr:street":"Massenetlaan;/ Forest",
    "iso:country":"BE",
    "sg:address":"Massenetlaan 23",
    "sg:city":"Vorst/forest",
    "sg:orig_category":"Alternatieve geneeskunde Artsen and specialisten",
    "sg:phone":"+32 2 347 35 53",
    "sg:postcode":"1190",
    "sg:province":"Bruxelles-Capitale",
    "wof:name":"Marcelle Gyre",
    "wof:placetype":"venue"
},
  "geometry": {"coordinates":[4.3332529068,50.8209037781],"type":"Point"}
}