{
  "type": "Feature",
  "properties": {
    "iso:country":"BE",
    "sg:address":"Rue Tienne Des Forges 25",
    "sg:city":"Charleroi (mont-sur-marchienne)",
    "sg:classifiers":[
        {
            "category":"Wholesale",
            "subcategory":"Wine & Distilled Alcoholic Beverages",
            "type":"Manufacturing & Wholesale Goods"
        }
    ],
    "sg:phone":"+32 71 43 64 87",
    "sg:postcode":"6032",
    "sg:province":"Hainaut",
    "sg:tags":[
        "whol",
        "-",
        "spirit",
        "mfg"
    ],
    "wof:name":"Cave De Justine (la)-andre Colasse",
    "wof:placetype":"venue"
},
  "geometry": {"coordinates":[4.4036288261,50.3926734924],"type":"Point"}
}