{
  "type": "Feature",
  "properties": {
    "addr:full":"Vostert 1111 Bree Limburg 3960",
    "addr:housenumber":"1111",
    "addr:postcode":"3960",
    "addr:street":"Bree Limburg",
    "iso:country":"BE",
    "sg:address":"Vostert 1111",
    "sg:city":"Bree",
    "sg:classifiers":[
        {
            "category":"Home & Garden",
            "subcategory":"Building Materials",
            "type":"Retail Goods"
        }
    ],
    "sg:phone":"+32 89 46 29 25",
    "sg:postcode":"3960",
    "sg:province":"Limburg",
    "sg:tags":[
        "steel",
        "metal",
        "made",
        "door",
        "gate"
    ],
    "wof:name":"Weldimo Nv",
    "wof:placetype":"venue"
},
  "geometry": {"coordinates":[5.5890097618,51.1217918396],"type":"Point"}
}