{
  "type": "Feature",
  "properties": {
    "addr:full":"Staatsbaan 79 Lanaken Limburg 3620",
    "addr:housenumber":"79",
    "addr:postcode":"3620",
    "addr:street":"Staatsbaan",
    "iso:country":"BE",
    "sg:address":"Staatsbaan 79",
    "sg:city":"Lanaken",
    "sg:orig_category":"Installatie van houten of kunststof schrijnwerk",
    "sg:phone":"+32 89 73 21 29",
    "sg:postcode":"3620",
    "sg:province":"Limburg",
    "wof:name":"Ramakers Garagepoorten",
    "wof:placetype":"venue"
},
  "geometry": {"coordinates":[5.6811141968,50.9106712341],"type":"Point"}
}