{
  "type": "Feature",
  "properties": {
    "addr:full":"Kasteelstraat 22 Temse Oost-Vlaanderen 9140",
    "addr:housenumber":"22",
    "addr:postcode":"9140",
    "addr:street":"Kasteelstraat",
    "iso:country":"BE",
    "sg:address":"Kasteelstraat 22",
    "sg:city":"Temse",
    "sg:orig_category":"Assurances vie compagnies. Assurances habitation compagnies. Banques and organismes de cr\u00e9dit",
    "sg:phone":"+32 3 710 95 20",
    "sg:postcode":"9140",
    "sg:province":"Oost-Vlaanderen",
    "wof:name":"Kbc",
    "wof:placetype":"venue"
},
  "geometry": {"coordinates":[4.2155909538,51.1246910095],"type":"Point"}
}