{
  "type": "Feature",
  "properties": {
    "addr:full":"Ninoofsesteenweg 94 Pepingen Vlaams-Brabant 1670",
    "addr:housenumber":"94",
    "addr:postcode":"1670",
    "addr:street":"Ninoofsesteenweg",
    "iso:country":"BE",
    "sg:address":"Ninoofsesteenweg 94",
    "sg:city":"Pepingen",
    "sg:orig_category":"Overheidsdiensten",
    "sg:phone":"+32 2 356 58 84",
    "sg:postcode":"1670",
    "sg:province":"Vlaams-Brabant",
    "wof:name":"Gemeentebestuur",
    "wof:placetype":"venue"
},
  "geometry": {"coordinates":[4.161798954,50.7593803406],"type":"Point"}
}