{
  "type": "Feature",
  "properties": {
    "addr:full":"Boulevard Joseph Tirou 70 Charleroi Hainaut 6000",
    "addr:housenumber":"70",
    "addr:postcode":"6000",
    "addr:street":"Boulevard Joseph Tirou;Hainaut",
    "iso:country":"BE",
    "sg:address":"Boulevard Joseph Tirou 70",
    "sg:city":"Charleroi",
    "sg:classifiers":[
        {
            "category":"Recreation",
            "subcategory":"Arcade",
            "type":"Entertainment"
        }
    ],
    "sg:phone":"+32 71 30 78 79",
    "sg:postcode":"6000",
    "sg:province":"Hainaut",
    "sg:tags":[
        "machine",
        "amusement"
    ],
    "wof:name":"Circus Charleroi",
    "wof:placetype":"venue"
},
  "geometry": {"coordinates":[4.4432001114,50.4076385498],"type":"Point"}
}