{
  "type": "Feature",
  "properties": {
    "iso:country":"BE",
    "sg:address":"Place Du Douzi\u00e8me De Ligne 13",
    "sg:city":"Herstal",
    "sg:classifiers":[
        {
            "category":"Bars & Pubs",
            "type":"Food & Drink"
        }
    ],
    "sg:phone":"+32 4 248 04 94",
    "sg:postcode":"4040",
    "sg:province":"Li\u00e8ge",
    "sg:tags":[
        "tavern"
    ],
    "wof:name":"Petite Taverne (la)",
    "wof:placetype":"venue"
},
  "geometry": {"coordinates":[5.6407608986,50.6736335754],"type":"Point"}
}