{
  "type": "Feature",
  "properties": {
    "addr:full":"Eikelstraat 5b2 Vorst/forest Bruxelles-Capitale 1190",
    "addr:housenumber":"5b2",
    "addr:postcode":"1190",
    "addr:street":"Eikelstraat;/ Forest",
    "iso:country":"BE",
    "sg:address":"Eikelstraat 5b2",
    "sg:city":"Vorst/forest",
    "sg:classifiers":[
        {
            "category":"Cafe",
            "type":"Food & Drink"
        }
    ],
    "sg:phone":"+32 2 345 89 73",
    "sg:postcode":"1190",
    "sg:province":"Bruxelles-Capitale",
    "sg:tags":[
        "caf\u00e9s"
    ],
    "wof:name":"Carmela Golisano",
    "wof:placetype":"venue"
},
  "geometry": {"coordinates":[4.3260288239,50.8199615479],"type":"Point"}
}