{
  "type": "Feature",
  "properties": {
    "addr:full":"Parklaan 55 Sint-niklaas Oost-Vlaanderen 9100",
    "addr:housenumber":"55",
    "addr:postcode":"9100",
    "addr:street":"Parklaan",
    "iso:country":"BE",
    "sg:address":"Parklaan 55",
    "sg:city":"Sint-niklaas",
    "sg:classifiers":[
        {
            "category":"Professional",
            "subcategory":"Advertising",
            "type":"Services"
        }
    ],
    "sg:phone":"+32 3 760 03 50",
    "sg:postcode":"9100",
    "sg:province":"Oost-Vlaanderen",
    "sg:tags":[
        "matter",
        "printed",
        "matters"
    ],
    "wof:name":"Groep Plus Vlaanderen Nv",
    "wof:placetype":"venue"
},
  "geometry": {"coordinates":[4.1469020844,51.1606025696],"type":"Point"}
}