{
  "type": "Feature",
  "properties": {
    "addr:full":"Rue Saint Barbe 44 Nivelles Brabant Wallon 1400",
    "addr:housenumber":"44",
    "addr:postcode":"1400",
    "addr:street":"Rue Saint Barbe",
    "iso:country":"BE",
    "sg:address":"Rue Saint Barbe 44",
    "sg:city":"Nivelles",
    "sg:classifiers":[
        {
            "category":"Arena",
            "subcategory":"Sports Club",
            "type":"Entertainment"
        }
    ],
    "sg:phone":"+32 2 384 93 29",
    "sg:postcode":"1400",
    "sg:province":"Brabant Wallon",
    "sg:tags":[
        "de"
    ],
    "wof:name":"Korean Training Center",
    "wof:placetype":"venue"
},
  "geometry": {"coordinates":[4.313439846,50.5909919739],"type":"Point"}
}