{
  "type": "Feature",
  "properties": {
    "addr:full":"Boulevard Bischoffsheim 41 Bruxelles Bruxelles-Capitale 1000",
    "addr:housenumber":"41",
    "addr:postcode":"1000",
    "addr:street":"Boulevard Bischoffsheim",
    "iso:country":"BE",
    "sg:address":"Boulevard Bischoffsheim 41",
    "sg:city":"Bruxelles",
    "sg:classifiers":[
        {
            "category":"Professional",
            "subcategory":"Computer Services",
            "type":"Services"
        }
    ],
    "sg:phone":"+32 2 217 73 61",
    "sg:postcode":"1000",
    "sg:province":"Bruxelles-Capitale",
    "sg:tags":[
        "-",
        "processing",
        "data",
        "software"
    ],
    "wof:name":"Mdcc",
    "wof:placetype":"venue"
},
  "geometry": {"coordinates":[4.3665018082,50.8526191711],"type":"Point"}
}