{
  "type": "Feature",
  "properties": {
    "addr:full":"Blekerijstraat 85b87 Roeselare West-Vlaanderen 8800",
    "addr:housenumber":"85b87",
    "addr:postcode":"8800",
    "addr:street":"Blekerijstraat",
    "iso:country":"BE",
    "sg:address":"Blekerijstraat 85b87",
    "sg:city":"Roeselare",
    "sg:orig_category":"Brood, gebak and snoepgoed Rookartikelen",
    "sg:phone":"+32 51 20 29 58",
    "sg:postcode":"8800",
    "sg:province":"West-Vlaanderen",
    "wof:name":"W Deceuninck",
    "wof:placetype":"venue"
},
  "geometry": {"coordinates":[3.1196489334,50.9425964355],"type":"Point"}
}