{
  "type": "Feature",
  "properties": {
    "addr:full":"Lindenpark 2bb Sint-martens-latem Oost-Vlaanderen 9831",
    "addr:housenumber":"2bb",
    "addr:postcode":"9831",
    "addr:street":"Lindenpark",
    "iso:country":"BE",
    "sg:address":"Lindenpark 2bb",
    "sg:city":"Sint-martens-latem",
    "sg:orig_category":"Jardinage",
    "sg:phone":"+32 9 282 84 00",
    "sg:postcode":"9831",
    "sg:province":"Oost-Vlaanderen",
    "wof:name":"Bureau No Van Wonterghem",
    "wof:placetype":"venue"
},
  "geometry": {"coordinates":[3.60582304,51.0115470886],"type":"Point"}
}