{
  "type": "Feature",
  "properties": {
    "addr:full":"Rue Comte D'ursel 30 Durbuy Luxembourg 6940",
    "addr:housenumber":"30",
    "addr:postcode":"6940",
    "addr:street":"Rue Comte D'Ursel",
    "iso:country":"BE",
    "sg:address":"Rue Comte D'ursel 30",
    "sg:city":"Durbuy",
    "sg:orig_category":"Artiesten and kunstenaars Zalen voor culturele evenementen",
    "sg:phone":"+32 86 21 21 77",
    "sg:postcode":"6940",
    "sg:province":"Luxembourg",
    "wof:name":"Roger Hanotiau",
    "wof:placetype":"venue"
},
  "geometry": {"coordinates":[5.4540429115,50.3515472412],"type":"Point"}
}