{
  "type": "Feature",
  "properties": {
    "iso:country":"BE",
    "sg:address":"Route De Mons-maubeuge 33",
    "sg:city":"Quevy",
    "sg:orig_category":"Bouwmaterialen Gh Dakwerken Loodgieterij, verwarming and sanitaire installaties",
    "sg:phone":"+32 65 56 88 85",
    "sg:postcode":"7041",
    "sg:province":"Hainaut",
    "wof:name":"Familtoit",
    "wof:placetype":"venue"
},
  "geometry": {"coordinates":[3.9674589634,50.3539390564],"type":"Point"}
}