{
  "type": "Feature",
  "properties": {
    "addr:full":"A. Casier De Ter Bekenln 36 Gent Oost-Vlaanderen 9030",
    "addr:housenumber":"36",
    "addr:postcode":"9030",
    "addr:street":"A.;De;Oost-Vlaanderen",
    "iso:country":"BE",
    "sg:address":"A. Casier De Ter Bekenln 36",
    "sg:city":"Gent",
    "sg:orig_category":"Avocats and conseillers juridiques",
    "sg:phone":"+32 9 226 22 57",
    "sg:postcode":"9030",
    "sg:province":"Oost-Vlaanderen",
    "wof:name":"B. Verkinderen",
    "wof:placetype":"venue"
},
  "geometry": {"coordinates":[3.6745951176,51.072933197],"type":"Point"}
}