{
  "type": "Feature",
  "properties": {
    "addr:full":"Visserij 207 Gent Oost-Vlaanderen 9000",
    "addr:housenumber":"207",
    "addr:postcode":"9000",
    "addr:street":"Visserij;Oost-Vlaanderen",
    "iso:country":"BE",
    "sg:address":"Visserij 207",
    "sg:city":"Gent",
    "sg:orig_category":"Entretien and r\u00e9parations de voitures",
    "sg:phone":"+32 9 223 82 17",
    "sg:postcode":"9000",
    "sg:province":"Oost-Vlaanderen",
    "wof:name":"Garage Pieters",
    "wof:placetype":"venue"
},
  "geometry": {"coordinates":[3.7396640778,51.0424041748],"type":"Point"}
}