{
  "type": "Feature",
  "properties": {
    "iso:country":"BE",
    "sg:address":"Melkerijstraat 24",
    "sg:city":"Essen",
    "sg:classifiers":[
        {
            "category":"Freight",
            "type":"Transportation"
        }
    ],
    "sg:phone":"+32 3 667 56 98",
    "sg:postcode":"2910",
    "sg:province":"Antwerpen",
    "sg:tags":[
        "-",
        "transport"
    ],
    "wof:name":"Esma Nv",
    "wof:placetype":"venue"
},
  "geometry": {"coordinates":[4.4773588181,51.4650268555],"type":"Point"}
}