{
  "type": "Feature",
  "properties": {
    "addr:full":"Avenue Des Capucines 17 Box 24 Kraainem Vlaams-Brabant 1950",
    "addr:housenumber":"17 box 24",
    "addr:postcode":"1950",
    "addr:street":"Avenue Des Capucines",
    "iso:country":"BE",
    "sg:address":"Avenue Des Capucines 17 Box 24",
    "sg:city":"Kraainem",
    "sg:classifiers":[
        {
            "category":"Shopping",
            "subcategory":"Antiques",
            "type":"Retail Goods"
        }
    ],
    "sg:phone":"+32 2 720 61 50",
    "sg:postcode":"1950",
    "sg:province":"Vlaams-Brabant",
    "wof:name":"Duc D'amaury",
    "wof:placetype":"venue"
},
  "geometry": {"coordinates":[4.4622488022,50.8532752991],"type":"Point"}
}