{
  "type": "Feature",
  "properties": {
    "iso:country":"BE",
    "sg:address":"Rue Du Berceau D'or 9",
    "sg:city":"Aubange",
    "sg:orig_category":"Huishoudapparaten, televisies and radio's",
    "sg:phone":"+32 63 38 85 57",
    "sg:postcode":"6792",
    "sg:province":"Luxembourg",
    "wof:name":"Megalux",
    "wof:placetype":"venue"
},
  "geometry": {"coordinates":[5.751229763,49.5752716064],"type":"Point"}
}