{
  "type": "Feature",
  "properties": {
    "addr:full":"Rue Du Loup 2 H\u00e9ron (couthuin) Li\u00e8ge 4218",
    "addr:housenumber":"2",
    "addr:postcode":"4218",
    "addr:street":"Rue Du Loup",
    "iso:country":"BE",
    "sg:address":"Rue Du Loup 2",
    "sg:city":"H\u00e9ron (couthuin)",
    "sg:classifiers":[
        {
            "category":"Personal",
            "subcategory":"Beauty Salon",
            "type":"Services"
        }
    ],
    "sg:phone":"+32 85 71 13 05",
    "sg:postcode":"4218",
    "sg:province":"Li\u00e8ge",
    "sg:tags":[
        "lady",
        "-",
        "hairdressing"
    ],
    "wof:name":"V\u00e9ronique Coiffure",
    "wof:placetype":"venue"
},
  "geometry": {"coordinates":[5.1405291557,50.5293655396],"type":"Point"}
}