{
  "type": "Feature",
  "properties": {
    "addr:full":"Rue Des Drapiers 43 Bruxelles (ixelles) Bruxelles-Capitale 1050",
    "addr:housenumber":"43",
    "addr:postcode":"1050",
    "addr:street":"Rue Des Drapiers",
    "iso:country":"BE",
    "sg:address":"Rue Des Drapiers 43",
    "sg:city":"Bruxelles (ixelles)",
    "sg:classifiers":[
        {
            "category":"Education",
            "subcategory":"University",
            "type":"Public Place"
        }
    ],
    "sg:phone":"+32 2 513 87 78",
    "sg:postcode":"1050",
    "sg:province":"Bruxelles-Capitale",
    "sg:tags":[
        "higher"
    ],
    "wof:name":"Ecole Superieure De Communication Et De Gestion (escg)",
    "wof:placetype":"venue"
},
  "geometry": {"coordinates":[4.3596749306,50.8346214294],"type":"Point"}
}