{
  "type": "Feature",
  "properties": {
    "addr:full":"Kerkstraat 107b1 Sint-gillis-waas Oost-Vlaanderen 9170",
    "addr:housenumber":"107b1",
    "addr:postcode":"9170",
    "addr:street":"Kerkstraat",
    "iso:country":"BE",
    "sg:address":"Kerkstraat 107b1",
    "sg:city":"Sint-gillis-waas",
    "sg:orig_category":"Herstelling leer and schoeisel Herstellingswinkels voor diverse persoonlijke and huishoudartikelen",
    "sg:phone":"+32 3 770 79 85",
    "sg:postcode":"9170",
    "sg:province":"Oost-Vlaanderen",
    "wof:name":"Schoenmakerij 't Leestje",
    "wof:placetype":"venue"
},
  "geometry": {"coordinates":[4.125398159,51.2192993164],"type":"Point"}
}