{
  "type": "Feature",
  "properties": {
    "addr:full":"Rue Ghislenghien 56 Ath Hainaut 7822",
    "addr:housenumber":"56",
    "addr:postcode":"7822",
    "addr:street":"Rue Ghislenghien",
    "iso:country":"BE",
    "sg:address":"Rue Ghislenghien 56",
    "sg:city":"Ath",
    "sg:classifiers":[
        {
            "category":"Personal",
            "subcategory":"Beauty Salon",
            "type":"Services"
        }
    ],
    "sg:phone":"+32 68 55 18 66",
    "sg:postcode":"7822",
    "sg:province":"Hainaut",
    "sg:tags":[
        "de",
        "coiffure"
    ],
    "wof:name":"Coiffure Fabienne",
    "wof:placetype":"venue"
},
  "geometry": {"coordinates":[3.8736848831,50.6571159363],"type":"Point"}
}