{
  "type": "Feature",
  "properties": {
    "addr:full":"Chemin De La Gh\u00c9sardr\u00c9e 23 Soignies Hainaut 7060",
    "addr:housenumber":"23",
    "addr:postcode":"7060",
    "addr:street":"Chemin De La Ghe\u0301Sardre\u0301E",
    "iso:country":"BE",
    "sg:address":"Chemin De La Gh\u00c9sardr\u00c9e 23",
    "sg:city":"Soignies",
    "sg:orig_category":"Afval and schroot Gh",
    "sg:phone":"+32 67 33 63 89",
    "sg:postcode":"7060",
    "sg:province":"Hainaut",
    "wof:name":"Fe. Cochez",
    "wof:placetype":"venue"
},
  "geometry": {"coordinates":[4.0749220848,50.5644111633],"type":"Point"}
}