{
  "type": "Feature",
  "properties": {
    "addr:full":"Brugmannlaan 404 Ukkel/uccle Bruxelles-Capitale 1180",
    "addr:housenumber":"404",
    "addr:postcode":"1180",
    "addr:street":"Brugmannlaan;/",
    "iso:country":"BE",
    "sg:address":"Brugmannlaan 404",
    "sg:city":"Ukkel/uccle",
    "sg:orig_category":"Advocaten and juridische adviseurs",
    "sg:phone":"+32 2 346 64 40",
    "sg:postcode":"1180",
    "sg:province":"Bruxelles-Capitale",
    "wof:name":"C. Coppin",
    "wof:placetype":"venue"
},
  "geometry": {"coordinates":[4.3427391052,50.8050727844],"type":"Point"}
}