{
  "type": "Feature",
  "properties": {
    "iso:country":"BE",
    "sg:address":"Varkensmarkt 2",
    "sg:city":"Merchtem",
    "sg:classifiers":[
        {
            "category":"Cafe",
            "type":"Food & Drink"
        }
    ],
    "sg:phone":"+32 52 37 16 02",
    "sg:postcode":"1785",
    "sg:province":"Vlaams-Brabant",
    "sg:tags":[
        "caf\u00e9s"
    ],
    "wof:name":"Jos De Mesmaeker",
    "wof:placetype":"venue"
},
  "geometry": {"coordinates":[4.2325201035,50.958442688],"type":"Point"}
}