{
  "type": "Feature",
  "properties": {
    "addr:full":"Januarilaan 5 Sint-lambrechts-woluwe/woluwe-saint-lambert Bruxelles-Capitale 1200",
    "addr:housenumber":"5",
    "addr:postcode":"1200",
    "addr:street":"Januarilaan",
    "iso:country":"BE",
    "sg:address":"Januarilaan 5",
    "sg:city":"Sint-lambrechts-woluwe/woluwe-saint-lambert",
    "sg:orig_category":"Artsen and specialisten",
    "sg:phone":"+32 2 772 22 90",
    "sg:postcode":"1200",
    "sg:province":"Bruxelles-Capitale",
    "wof:name":"J.p. Elens",
    "wof:placetype":"venue"
},
  "geometry": {"coordinates":[4.4144310951,50.8492546082],"type":"Point"}
}