{
  "type": "Feature",
  "properties": {
    "iso:country":"BE",
    "sg:address":"Bld Fr\u00c8re Orban 35ba",
    "sg:city":"Li\u00c8ge",
    "sg:orig_category":"M\u00e9decins and sp\u00e9cialistes",
    "sg:phone":"+32 4 252 33 88",
    "sg:postcode":"4000",
    "sg:province":"Li\u00e8ge",
    "wof:name":"Yvette Poutchinian",
    "wof:placetype":"venue"
},
  "geometry": {"coordinates":[5.5705461502,50.6304473877],"type":"Point"}
}