{
  "type": "Feature",
  "properties": {
    "iso:country":"BE",
    "sg:address":"Haut Nivez\u00c9 49",
    "sg:city":"Jalhay",
    "sg:orig_category":"Rundveehouders",
    "sg:phone":"+32 87 77 28 82",
    "sg:postcode":"4845",
    "sg:province":"Li\u00e8ge",
    "wof:name":"Emile Neuville",
    "wof:placetype":"venue"
},
  "geometry": {"coordinates":[5.9575738907,50.5569000244],"type":"Point"}
}