{
  "type": "Feature",
  "properties": {
    "iso:country":"BE",
    "sg:address":"Kruisstraat 20",
    "sg:city":"Damme",
    "sg:classifiers":[
        {
            "category":"Cafe",
            "type":"Food & Drink"
        }
    ],
    "sg:phone":"+32 50 35 53 75",
    "sg:postcode":"8340",
    "sg:province":"West-Vlaanderen",
    "sg:tags":[
        "caf\u00e9s"
    ],
    "wof:name":"Tennisclub Damme",
    "wof:placetype":"venue"
},
  "geometry": {"coordinates":[3.3181040287,51.2010765076],"type":"Point"}
}