{
  "type": "Feature",
  "properties": {
    "addr:full":"Grote Markt 1ba Roeselare West-Vlaanderen 8800",
    "addr:housenumber":"1ba",
    "addr:postcode":"8800",
    "addr:street":"Grote Markt",
    "iso:country":"BE",
    "sg:address":"Grote Markt 1ba",
    "sg:city":"Roeselare",
    "sg:classifiers":[
        {
            "category":"Restaurant",
            "type":"Food & Drink"
        }
    ],
    "sg:phone":"+32 51 24 23 23",
    "sg:postcode":"8800",
    "sg:province":"West-Vlaanderen",
    "sg:tags":[
        "caf\u00e9s"
    ],
    "wof:name":"Taverne De Klokke",
    "wof:placetype":"venue"
},
  "geometry": {"coordinates":[3.1247229576,50.9446525574],"type":"Point"}
}