{
  "type": "Feature",
  "properties": {
    "addr:full":"Place De Tourpes 5 Leuze-en-hainaut Hainaut 7904",
    "addr:housenumber":"5",
    "addr:postcode":"7904",
    "addr:street":"Place De Tourpes",
    "iso:country":"BE",
    "sg:address":"Place De Tourpes 5",
    "sg:city":"Leuze-en-hainaut",
    "sg:classifiers":[
        {
            "category":"Cafe",
            "type":"Food & Drink"
        }
    ],
    "sg:phone":"+32 69 67 11 40",
    "sg:postcode":"7904",
    "sg:province":"Hainaut",
    "sg:tags":[
        "caf\u00e9s"
    ],
    "wof:name":"Jacques Rasseneur",
    "wof:placetype":"venue"
},
  "geometry": {"coordinates":[3.6533789635,50.5703544617],"type":"Point"}
}