{
  "type": "Feature",
  "properties": {
    "iso:country":"BE",
    "sg:address":"Rue C\u00e9sar Despretz 60",
    "sg:city":"Lessines",
    "sg:classifiers":[
        {
            "category":"Professional",
            "subcategory":"Accounting & Tax Preparation",
            "type":"Services"
        }
    ],
    "sg:phone":"+32 68 33 34 07",
    "sg:postcode":"7860",
    "sg:province":"Hainaut",
    "sg:tags":[
        "accountant"
    ],
    "wof:name":"Boidequin R",
    "wof:placetype":"venue"
},
  "geometry": {"coordinates":[3.8282330036,50.7105140686],"type":"Point"}
}