{
  "type": "Feature",
  "properties": {
    "addr:full":"Joseph Ravoetstraat 3 Leuven Vlaams-Brabant 3012",
    "addr:housenumber":"3",
    "addr:postcode":"3012",
    "addr:street":"Joseph Ravoetstraat",
    "iso:country":"BE",
    "sg:address":"Joseph Ravoetstraat 3",
    "sg:city":"Leuven",
    "sg:classifiers":[
        {
            "category":"Insurance",
            "subcategory":"Insurance Agent",
            "type":"Services"
        }
    ],
    "sg:phone":"+32 16 44 63 14",
    "sg:postcode":"3012",
    "sg:province":"Vlaams-Brabant",
    "sg:tags":[
        "verzekeringsmakelaars",
        "expert"
    ],
    "wof:name":"Van De Zande",
    "wof:placetype":"venue"
},
  "geometry": {"coordinates":[4.7169427872,50.9160499573],"type":"Point"}
}