{
  "type": "Feature",
  "properties": {
    "addr:full":"Rue De La Grosse Cotte 252 Quaregnon Hainaut 7390",
    "addr:housenumber":"252",
    "addr:postcode":"7390",
    "addr:street":"Rue De La Grosse Cotte",
    "iso:country":"BE",
    "sg:address":"Rue De La Grosse Cotte 252",
    "sg:city":"Quaregnon",
    "sg:classifiers":[
        {
            "category":"Cafe",
            "type":"Food & Drink"
        }
    ],
    "sg:phone":"+32 65 82 33 48",
    "sg:postcode":"7390",
    "sg:province":"Hainaut",
    "sg:tags":[
        "caf\u00e9s"
    ],
    "wof:name":"Eric Ghys",
    "wof:placetype":"venue"
},
  "geometry": {"coordinates":[3.8794250488,50.4319496155],"type":"Point"}
}