{
  "type": "Feature",
  "properties": {
    "addr:full":"Rue De Tournai 24 Leuze-en-hainaut Hainaut 7900",
    "addr:housenumber":"24",
    "addr:postcode":"7900",
    "addr:street":"Rue De Tournai",
    "iso:country":"BE",
    "sg:address":"Rue De Tournai 24",
    "sg:city":"Leuze-en-hainaut",
    "sg:orig_category":"Notarissen",
    "sg:phone":"+32 69 66 20 33",
    "sg:postcode":"7900",
    "sg:province":"Hainaut",
    "wof:name":"Jean-louis Mertens",
    "wof:placetype":"venue"
},
  "geometry": {"coordinates":[3.6168749332,50.5983543396],"type":"Point"}
}