{
  "type": "Feature",
  "properties": {
    "iso:country":"BE",
    "sg:address":"Kastanjedreef 9",
    "sg:city":"Kortrijk (rollegem)",
    "sg:classifiers":[
        {
            "category":"Health Services",
            "subcategory":"Doctor",
            "type":"Services"
        }
    ],
    "sg:phone":"+32 56 25 66 09",
    "sg:postcode":"8510",
    "sg:province":"West-Vlaanderen",
    "sg:tags":[
        "medicinephysicians",
        "surgeon"
    ],
    "wof:name":"Bruneel Bart",
    "wof:placetype":"venue"
},
  "geometry": {"coordinates":[3.265182972,50.7918586731],"type":"Point"}
}