{
  "type": "Feature",
  "properties": {
    "iso:country":"BE",
    "sg:address":"Vaartstraat 128be3",
    "sg:city":"Ranst",
    "sg:orig_category":"Rev\u00eatements de sols and murs",
    "sg:phone":"+32 3 475 19 57",
    "sg:postcode":"2520",
    "sg:province":"Antwerpen",
    "wof:name":"Ftb Restoration",
    "wof:placetype":"venue"
},
  "geometry": {"coordinates":[4.5796599388,51.2046012878],"type":"Point"}
}