{
  "type": "Feature",
  "properties": {
    "iso:country":"BE",
    "sg:address":"Rue De Stassart 86",
    "sg:city":"Elsene/ixelles",
    "sg:orig_category":"Activit\u00e9s diverses d'imprimerie",
    "sg:phone":"+32 2 502 14 02",
    "sg:postcode":"1050",
    "sg:province":"Bruxelles-Capitale",
    "wof:name":"Johanna Fischer",
    "wof:placetype":"venue"
},
  "geometry": {"coordinates":[4.3596711159,50.8353691101],"type":"Point"}
}