{
  "type": "Feature",
  "properties": {
    "iso:country":"BE",
    "sg:address":"Avenue Albert Ier 71",
    "sg:city":"Huy",
    "sg:orig_category":"M\u00e9decins and sp\u00e9cialistes",
    "sg:phone":"+32 85 23 50 14",
    "sg:postcode":"4500",
    "sg:province":"Li\u00e8ge",
    "wof:name":"Suzanne Berg",
    "wof:placetype":"venue"
},
  "geometry": {"coordinates":[5.2333250046,50.5258102417],"type":"Point"}
}