{
  "type": "Feature",
  "properties": {
    "addr:full":"Velkuilenstraat 9 Bree Limburg 3960",
    "addr:housenumber":"9",
    "addr:postcode":"3960",
    "addr:street":"Velkuilenstraat",
    "iso:country":"BE",
    "sg:address":"Velkuilenstraat 9",
    "sg:city":"Bree",
    "sg:classifiers":[
        {
            "category":"Building & Trades",
            "subcategory":"Construction",
            "type":"Services"
        }
    ],
    "sg:phone":"+32 89 46 11 44",
    "sg:postcode":"3960",
    "sg:province":"Limburg",
    "sg:tags":[
        "stair"
    ],
    "wof:name":"Lemkens",
    "wof:placetype":"venue"
},
  "geometry": {"coordinates":[5.5942049026,51.1391677856],"type":"Point"}
}