{
  "type": "Feature",
  "properties": {
    "iso:country":"BE",
    "sg:address":"Avenue Franklin Roosevelt 38",
    "sg:city":"Vis\u00e9",
    "sg:classifiers":[
        {
            "category":"Social Services",
            "type":"Services"
        }
    ],
    "sg:phone":"+32 4 374 27 04",
    "sg:postcode":"4600",
    "sg:province":"Li\u00e8ge",
    "wof:name":"Saint-vincent De Paul",
    "wof:placetype":"venue"
},
  "geometry": {"coordinates":[5.6854000092,50.7377090454],"type":"Point"}
}