{
  "type": "Feature",
  "properties": {
    "addr:full":"Lange Kroonstraat 16 Boechout Antwerpen 2530",
    "addr:housenumber":"16",
    "addr:postcode":"2530",
    "addr:street":"Lange Kroonstraat",
    "iso:country":"BE",
    "sg:address":"Lange Kroonstraat 16",
    "sg:city":"Boechout",
    "sg:classifiers":[
        {
            "category":"Communications",
            "subcategory":"Film & Video Production",
            "type":"Services"
        }
    ],
    "sg:phone":"+32 3 454 55 44",
    "sg:postcode":"2530",
    "sg:province":"Antwerpen",
    "sg:tags":[
        "realisation",
        "-"
    ],
    "wof:name":"Video Equipe",
    "wof:placetype":"venue"
},
  "geometry": {"coordinates":[4.4901089668,51.161365509],"type":"Point"}
}