{
  "type": "Feature",
  "properties": {
    "iso:country":"BE",
    "sg:address":"Rue De Merbes 97",
    "sg:city":"Binche",
    "sg:classifiers":[
        {
            "category":"Health Services",
            "subcategory":"Doctor",
            "type":"Services"
        }
    ],
    "sg:phone":"+32 64 34 00 62",
    "sg:postcode":"7130",
    "sg:province":"Hainaut",
    "sg:tags":[
        "medicinephysicians",
        "surgeon"
    ],
    "wof:name":"Buisseret Jean-luc",
    "wof:placetype":"venue"
},
  "geometry": {"coordinates":[4.1703958511,50.4064483643],"type":"Point"}
}