{
  "type": "Feature",
  "properties": {
    "addr:full":"Vijversweg 33 Sint-genesius-rode/rhode-saint-genese Vlaams-Brabant 1640",
    "addr:housenumber":"33",
    "addr:postcode":"1640",
    "addr:street":"Vijversweg",
    "iso:country":"BE",
    "sg:address":"Vijversweg 33",
    "sg:city":"Sint-genesius-rode/rhode-saint-genese",
    "sg:orig_category":"Instellingen voor mindervalide volwassenen",
    "sg:phone":"+32 2 358 20 62",
    "sg:postcode":"1640",
    "sg:province":"Vlaams-Brabant",
    "wof:name":"Home La Bergerie",
    "wof:placetype":"venue"
},
  "geometry": {"coordinates":[4.3647871017,50.746925354],"type":"Point"}
}