{
  "type": "Feature",
  "properties": {
    "iso:country":"BE",
    "sg:address":"Rue De La Prelle 14",
    "sg:city":"Charleroi",
    "sg:orig_category":"Baby- and kinderkleding",
    "sg:phone":"+32 71 35 36 49",
    "sg:postcode":"6041",
    "sg:province":"Hainaut",
    "wof:name":"Maison Quintart Designer",
    "wof:placetype":"venue"
},
  "geometry": {"coordinates":[4.4314317703,50.4685935974],"type":"Point"}
}