{
  "type": "Feature",
  "properties": {
    "addr:full":"Rue Edouard Olivier 15 Bruxelles (watermael-boitsfort) Bruxelles-Capitale 1170",
    "addr:housenumber":"15",
    "addr:postcode":"1170",
    "addr:street":"Rue Edouard Olivier",
    "iso:country":"BE",
    "sg:address":"Rue Edouard Olivier 15",
    "sg:city":"Bruxelles (watermael-boitsfort)",
    "sg:classifiers":[
        {
            "category":"Building & Trades",
            "subcategory":"Pest Control",
            "type":"Services"
        }
    ],
    "sg:phone":"+32 2 672 57 72",
    "sg:postcode":"1170",
    "sg:province":"Bruxelles-Capitale",
    "sg:tags":[
        "painting",
        "contractor"
    ],
    "wof:name":"De Conde T",
    "wof:placetype":"venue"
},
  "geometry": {"coordinates":[4.3966341019,50.8119049072],"type":"Point"}
}