{
  "type": "Feature",
  "properties": {
    "addr:full":"Prins Boudewijnlaan 327 Box 9 Edegem Antwerpen 2650",
    "addr:housenumber":"327;9",
    "addr:postcode":"2650",
    "addr:street":"Prins Boudewijnlaan;Box",
    "iso:country":"BE",
    "sg:address":"Prins Boudewijnlaan 327 Box 9",
    "sg:city":"Edegem",
    "sg:classifiers":[
        {
            "category":"Professional",
            "subcategory":"Accounting & Tax Preparation",
            "type":"Services"
        }
    ],
    "sg:phone":"+32 3 457 78 11",
    "sg:postcode":"2650",
    "sg:province":"Antwerpen",
    "sg:tags":[
        "bookkeeper"
    ],
    "wof:name":"Vandenameele R Fisk & Boekh Cv",
    "wof:placetype":"venue"
},
  "geometry": {"coordinates":[4.4275817871,51.1647071838],"type":"Point"}
}