{
  "type": "Feature",
  "properties": {
    "addr:full":"Zonnedauw 25 Schilde ('s Gravenwezel) Antwerpen 2970",
    "addr:housenumber":"25",
    "addr:postcode":"2970",
    "addr:street":"Zonnedauw;S",
    "iso:country":"BE",
    "sg:address":"Zonnedauw 25",
    "sg:city":"Schilde ('s Gravenwezel)",
    "sg:classifiers":[
        {
            "category":"Health Services",
            "subcategory":"Nursing And Care Facility",
            "type":"Services"
        }
    ],
    "sg:phone":"+32 3 227 58 56",
    "sg:postcode":"2970",
    "sg:province":"Antwerpen",
    "sg:tags":[
        "home"
    ],
    "wof:name":"Filali S",
    "wof:placetype":"venue"
},
  "geometry": {"coordinates":[4.5680098534,51.2686462402],"type":"Point"}
}