{
  "type": "Feature",
  "properties": {
    "iso:country":"BE",
    "sg:address":"Voskapelstraat 32",
    "sg:city":"Zaventem",
    "sg:orig_category":"Messageries",
    "sg:phone":"+32 2 731 15 10",
    "sg:postcode":"1933",
    "sg:province":"Vlaams-Brabant",
    "wof:name":"Transport Precopuca",
    "wof:placetype":"venue"
},
  "geometry": {"coordinates":[4.517592907,50.8666534424],"type":"Point"}
}