{
  "type": "Feature",
  "properties": {
    "iso:country":"BE",
    "sg:address":"Kesseldorp 67",
    "sg:city":"Kessel-lo",
    "sg:orig_category":"Microsoft. Ordinateurs and \u00e9quipement informatique",
    "sg:phone":"+32 3 488 47 55",
    "sg:postcode":"2560",
    "sg:province":"Antwerpen",
    "wof:name":"Ice Intern Computer Engineering",
    "wof:placetype":"venue"
},
  "geometry": {"coordinates":[4.6300010681,51.1395874023],"type":"Point"}
}