{
  "type": "Feature",
  "properties": {
    "addr:full":"Gentsestraat 28 Izegem West-Vlaanderen 8870",
    "addr:housenumber":"28",
    "addr:postcode":"8870",
    "addr:street":"Gentsestraat",
    "iso:country":"BE",
    "sg:address":"Gentsestraat 28",
    "sg:city":"Izegem",
    "sg:classifiers":[
        {
            "category":"Insurance",
            "subcategory":"Life Insurance",
            "type":"Services"
        }
    ],
    "sg:phone":"+32 51 30 25 32",
    "sg:postcode":"8870",
    "sg:province":"West-Vlaanderen",
    "sg:tags":[
        "assurance"
    ],
    "wof:name":"Gasquet Andr\u00c9",
    "wof:placetype":"venue"
},
  "geometry": {"coordinates":[3.2257781029,50.9164619446],"type":"Point"}
}