{
  "type": "Feature",
  "properties": {
    "addr:full":"Chauss\u00c9e Des Cerises 14 Wavre Brabant Wallon 1300",
    "addr:housenumber":"14;1300",
    "addr:street":"Chausse\u0301E Des Cerises",
    "iso:country":"BE",
    "sg:address":"Chauss\u00c9e Des Cerises 14",
    "sg:city":"Wavre",
    "sg:orig_category":"M\u00e9decins and sp\u00e9cialistes",
    "sg:phone":"+32 10 22 71 79",
    "sg:postcode":"1300",
    "sg:province":"Brabant Wallon",
    "wof:name":"Jean-claude Debaisieux",
    "wof:placetype":"venue"
},
  "geometry": {"coordinates":[4.6076078415,50.7297058105],"type":"Point"}
}