{
  "type": "Feature",
  "properties": {
    "iso:country":"BE",
    "sg:address":"Rue Ansiaux 2",
    "sg:city":"Li\u00e8ge 1 (li\u00e8ge 2)",
    "sg:classifiers":[
        {
            "category":"Professional",
            "subcategory":"Art Services",
            "type":"Services"
        }
    ],
    "sg:phone":"+32 4 341 10 17",
    "sg:postcode":"4020",
    "sg:province":"Li\u00e8ge",
    "sg:tags":[
        "graphic",
        "designer"
    ],
    "wof:name":"Labour S",
    "wof:placetype":"venue"
},
  "geometry": {"coordinates":[5.5876731873,50.6324195862],"type":"Point"}
}