{
  "type": "Feature",
  "properties": {
    "addr:full":"Chauss\u00e9e De Dinant 305 Namur Namur 5000",
    "addr:housenumber":"305",
    "addr:postcode":"5000",
    "addr:street":"Chausse\u0301E De Dinant",
    "iso:country":"BE",
    "sg:address":"Chauss\u00e9e De Dinant 305",
    "sg:city":"Namur",
    "sg:classifiers":[
        {
            "category":"Health Services",
            "subcategory":"Health Practitioner",
            "type":"Services"
        }
    ],
    "sg:phone":"+32 81 22 77 04",
    "sg:postcode":"5000",
    "sg:province":"Namur",
    "sg:tags":[
        "physiotherapist"
    ],
    "wof:name":"Dupont M",
    "wof:placetype":"venue"
},
  "geometry": {"coordinates":[4.8574428558,50.4422187805],"type":"Point"}
}