{
  "type": "Feature",
  "properties": {
    "iso:country":"BE",
    "sg:address":"Bertheide 15",
    "sg:city":"Herentals",
    "sg:orig_category":"Epiceries",
    "sg:phone":"+32 14 26 78 51",
    "sg:postcode":"2200",
    "sg:province":"Antwerpen",
    "wof:name":"Tecno-fran",
    "wof:placetype":"venue"
},
  "geometry": {"coordinates":[4.7952189445,51.1227455139],"type":"Point"}
}