{
  "type": "Feature",
  "properties": {
    "iso:country":"BE",
    "sg:address":"Rotstraat 13",
    "sg:city":"Lubbeek",
    "sg:classifiers":[
        {
            "category":"Farming",
            "subcategory":"Farm & Veterinary Services",
            "type":"Manufacturing & Wholesale Goods"
        }
    ],
    "sg:phone":"+32 16 62 19 32",
    "sg:postcode":"3210",
    "sg:province":"Vlaams-Brabant",
    "sg:tags":[
        "agricultural",
        "contractor"
    ],
    "wof:name":"Vandael J",
    "wof:placetype":"venue"
},
  "geometry": {"coordinates":[4.8085098267,50.8969154358],"type":"Point"}
}