{
  "type": "Feature",
  "properties": {
    "addr:full":"Teniersdreef 18 Overijse Vlaams-Brabant 3090",
    "addr:housenumber":"18",
    "addr:postcode":"3090",
    "addr:street":"Teniersdreef",
    "iso:country":"BE",
    "sg:address":"Teniersdreef 18",
    "sg:city":"Overijse",
    "sg:classifiers":[
        {
            "category":"Professional",
            "subcategory":"Management & Consulting",
            "type":"Services"
        }
    ],
    "sg:phone":"+32 2 688 32 08",
    "sg:postcode":"3090",
    "sg:province":"Vlaams-Brabant",
    "sg:tags":[
        "-",
        "processing",
        "data",
        "consultant"
    ],
    "wof:name":"Softsolutions I D C",
    "wof:placetype":"venue"
},
  "geometry": {"coordinates":[4.5070171356,50.7918891907],"type":"Point"}
}