{
  "type": "Feature",
  "properties": {
    "addr:full":"Heirweg 93 Stekene Oost-Vlaanderen 9190",
    "addr:housenumber":"93",
    "addr:postcode":"9190",
    "addr:street":"Heirweg",
    "iso:country":"BE",
    "sg:address":"Heirweg 93",
    "sg:city":"Stekene",
    "sg:classifiers":[
        {
            "category":"Banks & Credit Unions",
            "subcategory":"Investment Brokerage",
            "type":"Services"
        }
    ],
    "sg:phone":"+32 3 779 92 76",
    "sg:postcode":"9190",
    "sg:province":"Oost-Vlaanderen",
    "sg:tags":[
        "repair",
        "-",
        "installation",
        "sanitary",
        "article"
    ],
    "wof:name":"Van Brussel J",
    "wof:placetype":"venue"
},
  "geometry": {"coordinates":[4.0119271278,51.1876296997],"type":"Point"}
}