{
  "type": "Feature",
  "properties": {
    "iso:country":"BE",
    "sg:address":"Oudenaardsesteenweg 45",
    "sg:city":"Kortrijk",
    "sg:classifiers":[
        {
            "category":"Shopping",
            "subcategory":"Antiques",
            "type":"Retail Goods"
        }
    ],
    "sg:phone":"+32 56 22 61 72",
    "sg:postcode":"8500",
    "sg:province":"West-Vlaanderen",
    "wof:name":"Scheers P",
    "wof:placetype":"venue"
},
  "geometry": {"coordinates":[3.2797420025,50.821762085],"type":"Point"}
}