{
  "type": "Feature",
  "properties": {
    "addr:full":"Lechtenstraat 15 Bocholt Limburg 3950",
    "addr:housenumber":"15",
    "addr:postcode":"3950",
    "addr:street":"Lechtenstraat",
    "iso:country":"BE",
    "sg:address":"Lechtenstraat 15",
    "sg:city":"Bocholt",
    "sg:classifiers":[
        {
            "category":"Airport",
            "subcategory":"International",
            "type":"Transportation"
        }
    ],
    "sg:phone":"+32 89 46 05 40",
    "sg:postcode":"3950",
    "sg:province":"Limburg",
    "sg:tags":[
        "-",
        "transport"
    ],
    "wof:name":"Bezuijen Transport",
    "wof:placetype":"venue"
},
  "geometry": {"coordinates":[5.5711078644,51.1778450012],"type":"Point"}
}