{
  "type": "Feature",
  "properties": {
    "addr:full":"Rue Du Ch\u00cane 5 Ciney Namur 5590",
    "addr:housenumber":"5",
    "addr:postcode":"5590",
    "addr:street":"Rue Du Che\u0302Ne",
    "iso:country":"BE",
    "sg:address":"Rue Du Ch\u00cane 5",
    "sg:city":"Ciney",
    "sg:orig_category":"Installation \u00e9lectrique r\u00e9sidentielle",
    "sg:phone":"+32 83 21 59 19",
    "sg:postcode":"5590",
    "sg:province":"Namur",
    "wof:name":"Marion Etienne Electricit\u00c9",
    "wof:placetype":"venue"
},
  "geometry": {"coordinates":[5.1022520065,50.297088623],"type":"Point"}
}