{
  "type": "Feature",
  "properties": {
    "addr:full":"Rue Des Bas Pr\u00e9s 72 Namur Namur 5000",
    "addr:housenumber":"72",
    "addr:postcode":"5000",
    "addr:street":"Rue Des Bas Pre\u0301S",
    "iso:country":"BE",
    "sg:address":"Rue Des Bas Pr\u00e9s 72",
    "sg:city":"Namur",
    "sg:classifiers":[
        {
            "category":"Insurance",
            "subcategory":"Insurance Agent",
            "type":"Services"
        }
    ],
    "sg:phone":"+32 81 73 67 40",
    "sg:postcode":"5000",
    "sg:province":"Namur",
    "sg:tags":[
        "broker"
    ],
    "wof:name":"Salpietro F",
    "wof:placetype":"venue"
},
  "geometry": {"coordinates":[4.8498458862,50.4665031433],"type":"Point"}
}