{
  "type": "Feature",
  "properties": {
    "iso:country":"BE",
    "sg:address":"Rue De Neufchateau 36",
    "sg:city":"Libramont-chevigny",
    "sg:orig_category":"Rundveehouders",
    "sg:phone":"+32 61 22 28 49",
    "sg:postcode":"6800",
    "sg:province":"Luxembourg",
    "wof:name":"Elvire Brolet",
    "wof:placetype":"venue"
},
  "geometry": {"coordinates":[5.3761348724,49.9199943542],"type":"Point"}
}