{
  "type": "Feature",
  "properties": {
    "iso:country":"BE",
    "sg:address":"Lumbeekstraat 31ba",
    "sg:city":"Dilbeek",
    "sg:orig_category":"Artiesten and kunstenaars",
    "sg:phone":"+32 2 453 92 10",
    "sg:postcode":"1700",
    "sg:province":"Vlaams-Brabant",
    "wof:name":"B. De Keyser",
    "wof:placetype":"venue"
},
  "geometry": {"coordinates":[4.2152409554,50.8804626465],"type":"Point"}
}