{
  "type": "Feature",
  "properties": {
    "iso:country":"BE",
    "sg:address":"Rue De Mariembourg 9",
    "sg:city":"Couvin (frasnes)",
    "sg:classifiers":[
        {
            "category":"Professional",
            "subcategory":"Computer Services",
            "type":"Services"
        }
    ],
    "sg:phone":"+32 60 31 34 20",
    "sg:postcode":"5660",
    "sg:province":"Namur",
    "sg:tags":[
        "-",
        "processing",
        "data",
        "software"
    ],
    "wof:name":"Informatique Et Services Sprl",
    "wof:placetype":"venue"
},
  "geometry": {"coordinates":[4.4037971497,50.1220054626],"type":"Point"}
}