{
  "type": "Feature",
  "properties": {
    "iso:country":"BE",
    "sg:address":"Battelsesteenweg 247",
    "sg:city":"Mechelen",
    "sg:orig_category":"Chaises and si\u00e8ges Fab. R\u00e9paration and restauration de meubles",
    "sg:phone":"+32 15 27 18 91",
    "sg:postcode":"2800",
    "sg:province":"Antwerpen",
    "wof:name":"Vandenbroeck H. & Co",
    "wof:placetype":"venue"
},
  "geometry": {"coordinates":[4.4619722366,51.0303993225],"type":"Point"}
}