{
  "type": "Feature",
  "properties": {
    "addr:full":"Adolf Buylstraat 22 Oostende West-Vlaanderen 8400",
    "addr:housenumber":"22",
    "addr:postcode":"8400",
    "addr:street":"Buylstraat",
    "iso:country":"BE",
    "sg:address":"Adolf Buylstraat 22",
    "sg:city":"Oostende",
    "sg:classifiers":[
        {
            "category":"Restaurant",
            "type":"Food & Drink"
        }
    ],
    "sg:phone":"+32 59 70 58 85",
    "sg:postcode":"8400",
    "sg:province":"West-Vlaanderen",
    "wof:name":"Glacier Au Parfait",
    "wof:placetype":"venue"
},
  "geometry": {"coordinates":[2.9160320759,51.2314682007],"type":"Point"}
}