{
  "type": "Feature",
  "properties": {
    "iso:country":"BE",
    "sg:address":"Kortrijksebaan 5",
    "sg:city":"Holsbeek",
    "sg:classifiers":[
        {
            "category":"Health Services",
            "subcategory":"Health Practitioner",
            "type":"Services"
        }
    ],
    "sg:phone":"+32 16 48 77 18",
    "sg:postcode":"3220",
    "sg:province":"Vlaams-Brabant",
    "sg:tags":[
        "therapist",
        "speech"
    ],
    "wof:name":"De Smedt M",
    "wof:placetype":"venue"
},
  "geometry": {"coordinates":[4.7599401474,50.9201164246],"type":"Point"}
}