{
  "type": "Feature",
  "properties": {
    "iso:country":"BE",
    "sg:address":"Keizerstraat 6",
    "sg:city":"Beveren (haasdonk)",
    "sg:classifiers":[
        {
            "category":"Personal",
            "subcategory":"Beauty Salon",
            "type":"Services"
        }
    ],
    "sg:phone":"+32 3 775 85 90",
    "sg:postcode":"9120",
    "sg:province":"Oost-Vlaanderen",
    "sg:tags":[
        "lady",
        "-",
        "hairdressing"
    ],
    "wof:name":"Andre",
    "wof:placetype":"venue"
},
  "geometry": {"coordinates":[4.240500927,51.1817054749],"type":"Point"}
}