{
  "type": "Feature",
  "properties": {
    "iso:country":"BE",
    "sg:address":"Place Capitaine Mostenne 49",
    "sg:city":"Marche-en-famenne (on)",
    "sg:classifiers":[
        {
            "category":"Arena",
            "subcategory":"Sports Club",
            "type":"Entertainment"
        }
    ],
    "sg:phone":"+32 84 37 95 79",
    "sg:postcode":"6900",
    "sg:province":"Luxembourg",
    "wof:name":"Petite Provence (la)",
    "wof:placetype":"venue"
},
  "geometry": {"coordinates":[5.285369873,50.1713562012],"type":"Point"}
}