{
  "type": "Feature",
  "properties": {
    "iso:country":"BE",
    "sg:address":"Grenadiersstraat 2",
    "sg:city":"Zonnebeke",
    "sg:orig_category":"Rundveehouders Varkenskwekers",
    "sg:phone":"+32 51 77 82 28",
    "sg:postcode":"8980",
    "sg:province":"West-Vlaanderen",
    "wof:name":"Jozef Vulsteke",
    "wof:placetype":"venue"
},
  "geometry": {"coordinates":[3.0175991058,50.901550293],"type":"Point"}
}