{
  "type": "Feature",
  "properties": {
    "iso:country":"BE",
    "sg:address":"Jules Lejeunestraat 30",
    "sg:city":"Elsene/ixelles",
    "sg:orig_category":"Immobili\u00ebnkantoren",
    "sg:phone":"+32 2 343 04 21",
    "sg:postcode":"1050",
    "sg:province":"Bruxelles-Capitale",
    "wof:name":"Gimmo",
    "wof:placetype":"venue"
},
  "geometry": {"coordinates":[4.3621768951,50.8171577454],"type":"Point"}
}