{
  "type": "Feature",
  "properties": {
    "iso:country":"BE",
    "sg:address":"Pontweg 12",
    "sg:city":"Aalst",
    "sg:orig_category":"Installatie van houten of kunststof schrijnwerk",
    "sg:phone":"+32 53 77 59 26",
    "sg:postcode":"9310",
    "sg:province":"Oost-Vlaanderen",
    "wof:name":"Fa. De Wolf E.",
    "wof:placetype":"venue"
},
  "geometry": {"coordinates":[4.0804080963,50.9644966125],"type":"Point"}
}