{
  "type": "Feature",
  "properties": {
    "addr:full":"Aarschotsesteenweg 181 Leuven (wilsele) Vlaams-Brabant 3012",
    "addr:housenumber":"181",
    "addr:postcode":"3012",
    "addr:street":"Aarschotsesteenweg",
    "iso:country":"BE",
    "sg:address":"Aarschotsesteenweg 181",
    "sg:city":"Leuven (wilsele)",
    "sg:classifiers":[
        {
            "category":"Bakery",
            "type":"Food & Drink"
        }
    ],
    "sg:phone":"+32 16 44 55 94",
    "sg:postcode":"3012",
    "sg:province":"Vlaams-Brabant",
    "sg:tags":[
        "confectioner",
        "baker"
    ],
    "wof:name":"Apers A",
    "wof:placetype":"venue"
},
  "geometry": {"coordinates":[4.713947773,50.9115753174],"type":"Point"}
}