{
  "type": "Feature",
  "properties": {
    "addr:full":"Guldensporenplein 4 Hasselt Limburg 3500",
    "addr:housenumber":"4",
    "addr:postcode":"3500",
    "addr:street":"Guldensporenplein",
    "iso:country":"BE",
    "sg:address":"Guldensporenplein 4",
    "sg:city":"Hasselt",
    "sg:classifiers":[
        {
            "category":"Bars & Pubs",
            "type":"Food & Drink"
        }
    ],
    "sg:phone":"+32 11 22 34 31",
    "sg:postcode":"3500",
    "sg:province":"Limburg",
    "wof:name":"Ramaekers P",
    "wof:placetype":"venue"
},
  "geometry": {"coordinates":[5.3445591927,50.9303779602],"type":"Point"}
}