{
  "type": "Feature",
  "properties": {
    "addr:full":"Faliestraat 41 Zedelgem West-Vlaanderen 8210",
    "addr:housenumber":"41",
    "addr:postcode":"8210",
    "addr:street":"Faliestraat",
    "iso:country":"BE",
    "sg:address":"Faliestraat 41",
    "sg:city":"Zedelgem",
    "sg:orig_category":"Eleveurs and marchands de porcs",
    "sg:phone":"+32 50 20 95 83",
    "sg:postcode":"8210",
    "sg:province":"West-Vlaanderen",
    "wof:name":"Zecovar",
    "wof:placetype":"venue"
},
  "geometry": {"coordinates":[3.1231861115,51.1354141235],"type":"Point"}
}