{
  "type": "Feature",
  "properties": {
    "addr:full":"Rue Des Deportes 25 Sivry-rance Hainaut 6470",
    "addr:housenumber":"25",
    "addr:postcode":"6470",
    "addr:street":"Rue Des Deportes",
    "iso:country":"BE",
    "sg:address":"Rue Des Deportes 25",
    "sg:city":"Sivry-rance",
    "sg:orig_category":"Architecten Landmeters and schatters",
    "sg:phone":"+32 60 41 11 83",
    "sg:postcode":"6470",
    "sg:province":"Hainaut",
    "wof:name":"Beno\u00cet Debacker",
    "wof:placetype":"venue"
},
  "geometry": {"coordinates":[4.2657670975,50.1432189941],"type":"Point"}
}