{
  "type": "Feature",
  "properties": {
    "addr:full":"Kruibekesteenweg 28 Beveren Oost-Vlaanderen 9120",
    "addr:housenumber":"28",
    "addr:postcode":"9120",
    "addr:street":"Kruibekesteenweg",
    "iso:country":"BE",
    "sg:address":"Kruibekesteenweg 28",
    "sg:city":"Beveren",
    "sg:classifiers":[
        {
            "category":"Food & Beverages",
            "subcategory":"Fruits & Vegetables",
            "type":"Retail Goods"
        }
    ],
    "sg:phone":"+32 3 775 79 22",
    "sg:postcode":"9120",
    "sg:province":"Oost-Vlaanderen",
    "sg:tags":[
        "groenten"
    ],
    "wof:name":"K. Van Leugenaeghe",
    "wof:placetype":"venue"
},
  "geometry": {"coordinates":[4.2594661713,51.2072601318],"type":"Point"}
}