{
  "type": "Feature",
  "properties": {
    "addr:full":"Golflaan 65 Sint-martens-latem Oost-Vlaanderen 9830",
    "addr:housenumber":"65",
    "addr:postcode":"9830",
    "addr:street":"Golflaan",
    "iso:country":"BE",
    "sg:address":"Golflaan 65",
    "sg:city":"Sint-martens-latem",
    "sg:orig_category":"Newspapers, magazines, periodicals - Distribution",
    "sg:phone":"+32 9 282 22 67",
    "sg:postcode":"9830",
    "sg:province":"Oost-Vlaanderen",
    "wof:name":"Krantenshop Verthez Bvba",
    "wof:placetype":"venue"
},
  "geometry": {"coordinates":[3.6315510273,51.0108108521],"type":"Point"}
}