{
  "type": "Feature",
  "properties": {
    "iso:country":"BE",
    "sg:address":"Rue Petite 41",
    "sg:city":"Qu\u00c9vy",
    "sg:orig_category":"Verplichte sociale verzekeringen",
    "sg:phone":"+32 65 56 82 89",
    "sg:postcode":"7040",
    "sg:province":"Hainaut",
    "wof:name":"Mutualit\u00c9 Socialiste",
    "wof:placetype":"venue"
},
  "geometry": {"coordinates":[3.9159519672,50.3907012939],"type":"Point"}
}