{
  "type": "Feature",
  "properties": {
    "iso:country":"BE",
    "sg:address":"Rekkemsestraat 78",
    "sg:city":"Kortrijk (marke)",
    "sg:classifiers":[
        {
            "category":"Food & Beverages",
            "subcategory":"Chocolate",
            "type":"Retail Goods"
        }
    ],
    "sg:phone":"+32 56 22 93 94",
    "sg:postcode":"8510",
    "sg:province":"West-Vlaanderen",
    "sg:tags":[
        "confectionery",
        "-"
    ],
    "wof:name":"Leonidas Genia",
    "wof:placetype":"venue"
},
  "geometry": {"coordinates":[3.2278389931,50.8081436157],"type":"Point"}
}