{
  "type": "Feature",
  "properties": {
    "addr:full":"Koffiestraat 75 Tienen Vlaams-Brabant 3300",
    "addr:housenumber":"75",
    "addr:postcode":"3300",
    "addr:street":"Koffiestraat",
    "iso:country":"BE",
    "sg:address":"Koffiestraat 75",
    "sg:city":"Tienen",
    "sg:orig_category":"M\u00e9decins and sp\u00e9cialistes",
    "sg:phone":"+32 16 81 72 03",
    "sg:postcode":"3300",
    "sg:province":"Vlaams-Brabant",
    "wof:name":"Willy Van Verrewegen",
    "wof:placetype":"venue"
},
  "geometry": {"coordinates":[4.930077076,50.8096694946],"type":"Point"}
}