{
  "type": "Feature",
  "properties": {
    "addr:full":"Bovenrij 50a Herentals Antwerpen 2200",
    "addr:housenumber":"50a",
    "addr:postcode":"2200",
    "addr:street":"Bovenrij",
    "iso:country":"BE",
    "sg:address":"Bovenrij 50a",
    "sg:city":"Herentals",
    "sg:classifiers":[
        {
            "category":"Communications",
            "subcategory":"Radio Station",
            "type":"Services"
        }
    ],
    "sg:phone":"+32 14 23 37 27",
    "sg:postcode":"2200",
    "sg:province":"Antwerpen",
    "sg:tags":[
        "local"
    ],
    "wof:name":"Radio Family Kempen (h.r.o.)",
    "wof:placetype":"venue"
},
  "geometry": {"coordinates":[4.8378868103,51.1749038696],"type":"Point"}
}