{
  "type": "Feature",
  "properties": {
    "iso:country":"BE",
    "sg:address":"Rue G. Van Laethem 36",
    "sg:city":"Evere",
    "sg:classifiers":[
        {
            "category":"Arena",
            "subcategory":"Sports Club",
            "type":"Entertainment"
        }
    ],
    "sg:phone":"+32 2 726 69 51",
    "sg:postcode":"1140",
    "sg:province":"Bruxelles-Capitale",
    "sg:tags":[
        "de"
    ],
    "wof:name":"Amicale Panhard",
    "wof:placetype":"venue"
},
  "geometry": {"coordinates":[4.4167537689,50.8580169678],"type":"Point"}
}