{
  "type": "Feature",
  "properties": {
    "addr:full":"Rue D'alost 8-10 Bruxelles Bruxelles-Capitale 1000",
    "addr:housenumber":"8-10",
    "addr:postcode":"1000",
    "addr:street":"Rue D'Alost",
    "iso:country":"BE",
    "sg:address":"Rue D'alost 8-10",
    "sg:city":"Bruxelles",
    "sg:classifiers":[
        {
            "category":"Manufacturing",
            "subcategory":"Paper Products",
            "type":"Manufacturing & Wholesale Goods"
        }
    ],
    "sg:phone":"+32 2 511 03 52",
    "sg:postcode":"1000",
    "sg:province":"Bruxelles-Capitale",
    "sg:tags":[
        "adhesive",
        "self-adhesive",
        "labels",
        "label"
    ],
    "wof:name":"Ets D'imprimerie Et Reliure Automatique S.p.r.l. - Eira",
    "wof:placetype":"venue"
},
  "geometry": {"coordinates":[4.3513898849,50.8584594727],"type":"Point"}
}