{
  "type": "Feature",
  "properties": {
    "iso:country":"BE",
    "sg:address":"Groenstraat 17",
    "sg:city":"Lanaken (rekem)",
    "sg:classifiers":[
        {
            "category":"Building & Trades",
            "subcategory":"Construction",
            "type":"Services"
        }
    ],
    "sg:phone":"+32 89 73 38 67",
    "sg:postcode":"3621",
    "sg:province":"Limburg",
    "sg:tags":[
        "industrial",
        "design"
    ],
    "wof:name":"R.l.j. Lahaye",
    "wof:placetype":"venue"
},
  "geometry": {"coordinates":[5.6968259811,50.9248809814],"type":"Point"}
}