{
  "type": "Feature",
  "properties": {
    "iso:country":"BE",
    "sg:address":"Drongensesteenweg 177",
    "sg:city":"Gent",
    "sg:orig_category":"V\u00e9t\u00e9rinaires",
    "sg:phone":"+32 9 227 94 73",
    "sg:postcode":"9000",
    "sg:province":"Oost-Vlaanderen",
    "wof:name":"Mieke Vandenborre",
    "wof:placetype":"venue"
},
  "geometry": {"coordinates":[3.6949169636,51.0560722351],"type":"Point"}
}