{
  "type": "Feature",
  "properties": {
    "iso:country":"BE",
    "sg:address":"Rue Chauss\u00e9e 24",
    "sg:city":"Awans",
    "sg:classifiers":[
        {
            "category":"Real Estate",
            "subcategory":"Architect",
            "type":"Services"
        }
    ],
    "sg:phone":"+32 4 360 83 37",
    "sg:postcode":"4340",
    "sg:province":"Li\u00e8ge",
    "wof:name":"Formes & Espaces Sprl Zweber M - Driesmans C",
    "wof:placetype":"venue"
},
  "geometry": {"coordinates":[5.4620018005,50.663772583],"type":"Point"}
}