{
  "type": "Feature",
  "properties": {
    "addr:full":"Sentier Du Bois Moue 2 Rixensart Brabant Wallon 1330",
    "addr:housenumber":"2",
    "addr:postcode":"1330",
    "addr:street":"Sentier Du Bois Moue;Wallon",
    "iso:country":"BE",
    "sg:address":"Sentier Du Bois Moue 2",
    "sg:city":"Rixensart",
    "sg:classifiers":[
        {
            "category":"Home & Garden",
            "subcategory":"Home Furnishings",
            "type":"Retail Goods"
        }
    ],
    "sg:phone":"+32 2 653 23 82",
    "sg:postcode":"1330",
    "sg:province":"Brabant Wallon",
    "sg:tags":[
        "interior",
        "decoration"
    ],
    "wof:name":"Ciselet B",
    "wof:placetype":"venue"
},
  "geometry": {"coordinates":[4.513944149,50.7016410828],"type":"Point"}
}