{
  "type": "Feature",
  "properties": {
    "addr:full":"Zuiderring 21 Genk Limburg 3600",
    "addr:housenumber":"21",
    "addr:postcode":"3600",
    "addr:street":"Zuiderring",
    "iso:country":"BE",
    "sg:address":"Zuiderring 21",
    "sg:city":"Genk",
    "sg:classifiers":[
        {
            "category":"Home & Garden",
            "subcategory":"Building Materials",
            "type":"Retail Goods"
        }
    ],
    "sg:phone":"+32 89 30 65 93",
    "sg:postcode":"3600",
    "sg:province":"Limburg",
    "sg:tags":[
        "veranda"
    ],
    "wof:name":"Oravera",
    "wof:placetype":"venue"
},
  "geometry": {"coordinates":[5.4893388748,50.9486122131],"type":"Point"}
}