{
  "type": "Feature",
  "properties": {
    "addr:full":"Gasthuisstraat 19 Merchtem Vlaams-Brabant 1785",
    "addr:housenumber":"19",
    "addr:postcode":"1785",
    "addr:street":"Gasthuisstraat",
    "iso:country":"BE",
    "sg:address":"Gasthuisstraat 19",
    "sg:city":"Merchtem",
    "sg:classifiers":[
        {
            "category":"Health Services",
            "subcategory":"Nursing And Care Facility",
            "type":"Services"
        }
    ],
    "sg:phone":"+32 52 37 26 40",
    "sg:postcode":"1785",
    "sg:province":"Vlaams-Brabant",
    "sg:tags":[
        "home",
        "rest"
    ],
    "wof:name":"Ocmw-rusthuis",
    "wof:placetype":"venue"
},
  "geometry": {"coordinates":[4.2308568954,50.9615135193],"type":"Point"}
}