{
  "type": "Feature",
  "properties": {
    "iso:country":"BE",
    "sg:address":"Avenue Du Roi Albert 675",
    "sg:city":"Mons",
    "sg:orig_category":"Industri\u00eble wasserijen and droogkuis",
    "sg:phone":"+32 65 88 44 47",
    "sg:postcode":"7012",
    "sg:province":"Hainaut",
    "wof:name":"La Bo\u00cete \u00c0 Bulles",
    "wof:placetype":"venue"
},
  "geometry": {"coordinates":[3.8894600868,50.4481964111],"type":"Point"}
}