{
  "type": "Feature",
  "properties": {
    "iso:country":"BE",
    "sg:address":"Chauss\u00e9e De Li\u00e8ge 997",
    "sg:city":"Namur (erpent)",
    "sg:classifiers":[
        {
            "category":"Retail",
            "subcategory":"Auto Repair",
            "type":"Services"
        }
    ],
    "sg:phone":"+32 81 58 21 58",
    "sg:postcode":"5101",
    "sg:province":"Namur",
    "sg:tags":[
        "garage"
    ],
    "wof:name":"Damsin J",
    "wof:placetype":"venue"
},
  "geometry": {"coordinates":[4.904815197,50.4481887817],"type":"Point"}
}