{
  "type": "Feature",
  "properties": {
    "addr:full":"Ninovesteenweg 57 Aalst Oost-Vlaanderen 9320",
    "addr:housenumber":"57",
    "addr:postcode":"9320",
    "addr:street":"Ninovesteenweg",
    "iso:country":"BE",
    "sg:address":"Ninovesteenweg 57",
    "sg:city":"Aalst",
    "sg:orig_category":"Bouwmaterialen Gh",
    "sg:phone":"+32 53 77 34 10",
    "sg:postcode":"9320",
    "sg:province":"Oost-Vlaanderen",
    "wof:name":"Alvodak",
    "wof:placetype":"venue"
},
  "geometry": {"coordinates":[4.0553851128,50.9209976196],"type":"Point"}
}