{
  "type": "Feature",
  "properties": {
    "addr:full":"Leuvensesteenweg 429 Zaventem Vlaams-Brabant 1930",
    "addr:housenumber":"429",
    "addr:postcode":"1930",
    "addr:street":"Leuvensesteenweg",
    "iso:country":"BE",
    "sg:address":"Leuvensesteenweg 429",
    "sg:city":"Zaventem",
    "sg:orig_category":"Installatie van houten of kunststof schrijnwerk",
    "sg:phone":"+32 2 720 73 15",
    "sg:postcode":"1930",
    "sg:province":"Vlaams-Brabant",
    "wof:name":"D'hondt",
    "wof:placetype":"venue"
},
  "geometry": {"coordinates":[4.4717431068,50.8722343445],"type":"Point"}
}