{
  "type": "Feature",
  "properties": {
    "iso:country":"BE",
    "sg:address":"Grootheide 153",
    "sg:city":"Bornem",
    "sg:classifiers":[
        {
            "category":"Food & Beverages",
            "subcategory":"Fruits & Vegetables",
            "type":"Retail Goods"
        }
    ],
    "sg:phone":"+32 3 899 35 24",
    "sg:postcode":"2880",
    "sg:province":"Antwerpen",
    "sg:tags":[
        "l\u00e9gumes"
    ],
    "wof:name":"De Moestuin",
    "wof:placetype":"venue"
},
  "geometry": {"coordinates":[4.2212181091,51.0858573914],"type":"Point"}
}