{
  "type": "Feature",
  "properties": {
    "iso:country":"BE",
    "sg:address":"Vierschaar 1",
    "sg:city":"Waasmunster",
    "sg:orig_category":"Werk and personeelsselectie",
    "sg:phone":"+32 52 46 95 10",
    "sg:postcode":"9250",
    "sg:province":"Oost-Vlaanderen",
    "wof:name":"Pwa Waasmunster",
    "wof:placetype":"venue"
},
  "geometry": {"coordinates":[4.0838441849,51.1094932556],"type":"Point"}
}