{
  "type": "Feature",
  "properties": {
    "addr:full":"Avenue De La R\u00c9sistance 168 Soumagne Li\u00e8ge 4630",
    "addr:housenumber":"168",
    "addr:postcode":"4630",
    "addr:street":"Avenue De La Re\u0301Sistance",
    "iso:country":"BE",
    "sg:address":"Avenue De La R\u00c9sistance 168",
    "sg:city":"Soumagne",
    "sg:orig_category":"Biens d'occasion. Meubles D\u00e9taillants, Am\u00e9nagement de B\u00e2timents et de Cuisines",
    "sg:phone":"+32 4 377 65 21",
    "sg:postcode":"4630",
    "sg:province":"Li\u00e8ge",
    "wof:name":"La Mansarde",
    "wof:placetype":"venue"
},
  "geometry": {"coordinates":[5.7472958565,50.6121063232],"type":"Point"}
}