{
  "type": "Feature",
  "properties": {
    "iso:country":"BE",
    "sg:address":"Rue Mauvais Tr\u00ce 9",
    "sg:city":"Namur",
    "sg:orig_category":"Instellingen voor probleemkinderen Kindertehuizen",
    "sg:phone":"+32 81 44 63 93",
    "sg:postcode":"5020",
    "sg:province":"Namur",
    "wof:name":"Home Les Cabris",
    "wof:placetype":"venue"
},
  "geometry": {"coordinates":[4.7952418327,50.4352035522],"type":"Point"}
}