{
  "type": "Feature",
  "properties": {
    "iso:country":"BE",
    "sg:address":"Posthoornstraat 64",
    "sg:city":"Zulte",
    "sg:orig_category":"Boucheries",
    "sg:phone":"+32 9 386 08 87",
    "sg:postcode":"9870",
    "sg:province":"Oost-Vlaanderen",
    "wof:name":"Chris Michels",
    "wof:placetype":"venue"
},
  "geometry": {"coordinates":[3.4968910217,50.9521331787],"type":"Point"}
}