{
  "type": "Feature",
  "properties": {
    "iso:country":"BE",
    "sg:address":"Eikestraat 50",
    "sg:city":"Mechelen",
    "sg:classifiers":[
        {
            "category":"Personal",
            "subcategory":"Beauty Salon",
            "type":"Services"
        }
    ],
    "sg:phone":"+32 15 20 21 21",
    "sg:postcode":"2800",
    "sg:province":"Antwerpen",
    "sg:tags":[
        "de",
        "coiffure"
    ],
    "wof:name":"Kapsalon Sjampoo",
    "wof:placetype":"venue"
},
  "geometry": {"coordinates":[4.4744811058,51.0439987183],"type":"Point"}
}