{
  "type": "Feature",
  "properties": {
    "iso:country":"BE",
    "sg:address":"Noormannenstraat 59",
    "sg:city":"Leuven",
    "sg:classifiers":[
        {
            "category":"Professional",
            "subcategory":"Management & Consulting",
            "type":"Services"
        }
    ],
    "sg:phone":"+32 16 22 68 08",
    "sg:postcode":"3000",
    "sg:province":"Vlaams-Brabant",
    "sg:tags":[
        "-",
        "processing",
        "data",
        "consultant"
    ],
    "wof:name":"Borgermans P",
    "wof:placetype":"venue"
},
  "geometry": {"coordinates":[4.688639164,50.8840675354],"type":"Point"}
}