{
  "type": "Feature",
  "properties": {
    "addr:full":"Raymond Delbekestraat 109 Zoersel Antwerpen 2980",
    "addr:housenumber":"109",
    "addr:postcode":"2980",
    "addr:street":"Delbekestraat",
    "iso:country":"BE",
    "sg:address":"Raymond Delbekestraat 109",
    "sg:city":"Zoersel",
    "sg:orig_category":"Transports routiers de marchandises",
    "sg:phone":"+32 3 384 31 39",
    "sg:postcode":"2980",
    "sg:province":"Antwerpen",
    "wof:name":"Transport Oorts Marc",
    "wof:placetype":"venue"
},
  "geometry": {"coordinates":[4.623005867,51.2762298584],"type":"Point"}
}