{
  "type": "Feature",
  "properties": {
    "addr:full":"Rue Seutin 11 Nivelles Brabant Wallon 1400",
    "addr:housenumber":"11",
    "addr:postcode":"1400",
    "addr:street":"Rue Seutin",
    "iso:country":"BE",
    "sg:address":"Rue Seutin 11",
    "sg:city":"Nivelles",
    "sg:classifiers":[
        {
            "category":"Professional",
            "subcategory":"Testing Lab",
            "type":"Services"
        }
    ],
    "sg:phone":"+32 2 345 44 81",
    "sg:postcode":"1400",
    "sg:province":"Brabant Wallon",
    "sg:tags":[
        "laboratory",
        "medical"
    ],
    "wof:name":"L.a.m. Roman Pais",
    "wof:placetype":"venue"
},
  "geometry": {"coordinates":[4.3215827942,50.5967025757],"type":"Point"}
}