{
  "type": "Feature",
  "properties": {
    "addr:full":"Loofblommestraat 11 Gent (sint-denijs-westrem - Afsnee) Oost-Vlaanderen 9051",
    "addr:housenumber":"11",
    "addr:postcode":"9051",
    "addr:street":"Loofblommestraat;Oost-Vlaanderen",
    "iso:country":"BE",
    "sg:address":"Loofblommestraat 11",
    "sg:city":"Gent (sint-denijs-westrem - Afsnee)",
    "sg:classifiers":[
        {
            "category":"Health Services",
            "subcategory":"Dentist",
            "type":"Services"
        }
    ],
    "sg:phone":"+32 9 222 34 36",
    "sg:postcode":"9051",
    "sg:province":"Oost-Vlaanderen",
    "wof:name":"Driege D",
    "wof:placetype":"venue"
},
  "geometry": {"coordinates":[3.6682839394,51.0208511353],"type":"Point"}
}