{
  "type": "Feature",
  "properties": {
    "addr:full":"Rue Charles Lamquet 45 Namur Namur 5100",
    "addr:housenumber":"45",
    "addr:postcode":"5100",
    "addr:street":"Rue Charles Lamquet",
    "iso:country":"BE",
    "sg:address":"Rue Charles Lamquet 45",
    "sg:city":"Namur",
    "sg:orig_category":"Instituts de beaut\u00e9",
    "sg:phone":"+32 81 30 02 16",
    "sg:postcode":"5100",
    "sg:province":"Namur",
    "wof:name":"P\u00c9dicure Simon",
    "wof:placetype":"venue"
},
  "geometry": {"coordinates":[4.8713750839,50.4566345215],"type":"Point"}
}