{
  "type": "Feature",
  "properties": {
    "iso:country":"BE",
    "sg:address":"Carnegielaan 1",
    "sg:city":"Hasselt",
    "sg:classifiers":[
        {
            "category":"Arena",
            "subcategory":"Sports Club",
            "type":"Entertainment"
        }
    ],
    "sg:phone":"+32 11 21 05 70",
    "sg:postcode":"3500",
    "sg:province":"Limburg",
    "sg:tags":[
        "de"
    ],
    "wof:name":"Excelsior Hasselt T.c.",
    "wof:placetype":"venue"
},
  "geometry": {"coordinates":[5.3503098488,50.957572937],"type":"Point"}
}