{
  "type": "Feature",
  "properties": {
    "addr:full":"Chauss\u00e9e D'herseaux 45 Estaimpuis Hainaut 7730",
    "addr:housenumber":"45",
    "addr:postcode":"7730",
    "addr:street":"Chausse\u0301E D'Herseaux;Hainaut",
    "iso:country":"BE",
    "sg:address":"Chauss\u00e9e D'herseaux 45",
    "sg:city":"Estaimpuis",
    "sg:classifiers":[
        {
            "category":"Retail",
            "subcategory":"Animal Services",
            "type":"Services"
        }
    ],
    "sg:phone":"+32 56 48 45 09",
    "sg:postcode":"7730",
    "sg:province":"Hainaut",
    "sg:tags":[
        "grooming",
        "-",
        "dog"
    ],
    "wof:name":"Beaut\u00e9 Canine",
    "wof:placetype":"venue"
},
  "geometry": {"coordinates":[3.2638480663,50.7160148621],"type":"Point"}
}