{
  "type": "Feature",
  "properties": {
    "addr:full":"R\u00c9sidence Du Ch\u00c2teau 19 La Louvi\u00c8re Hainaut 7110",
    "addr:housenumber":"19",
    "addr:postcode":"7110",
    "addr:street":"Re\u0301Sidence Du Cha\u0302Teau",
    "iso:country":"BE",
    "sg:address":"R\u00c9sidence Du Ch\u00c2teau 19",
    "sg:city":"La Louvi\u00c8re",
    "sg:classifiers":[
        {
            "category":"Food & Beverages",
            "subcategory":"Fruits & Vegetables",
            "type":"Retail Goods"
        }
    ],
    "sg:phone":"+32 64 66 46 43",
    "sg:postcode":"7110",
    "sg:province":"Hainaut",
    "sg:tags":[
        "groenten"
    ],
    "wof:name":"Marotta Et Fils",
    "wof:placetype":"venue"
},
  "geometry": {"coordinates":[4.1505050659,50.4826698303],"type":"Point"}
}