{
  "type": "Feature",
  "properties": {
    "iso:country":"BE",
    "sg:address":"Hijftestraat 112b",
    "sg:city":"Lochristi",
    "sg:orig_category":"Plantes and fleurs Gr",
    "sg:phone":"+32 9 356 96 50",
    "sg:postcode":"9080",
    "sg:province":"Oost-Vlaanderen",
    "wof:name":"De Wispelaere",
    "wof:placetype":"venue"
},
  "geometry": {"coordinates":[3.8139541149,51.1066894531],"type":"Point"}
}