{
  "type": "Feature",
  "properties": {
    "iso:country":"BE",
    "sg:address":"Jean En Pierre Carsoelln 156",
    "sg:city":"Ukkel/uccle",
    "sg:orig_category":"Artsen and specialisten",
    "sg:phone":"+32 2 374 94 31",
    "sg:postcode":"1180",
    "sg:province":"Bruxelles-Capitale",
    "wof:name":"Suzanne Timmerman",
    "wof:placetype":"venue"
},
  "geometry": {"coordinates":[4.3498878479,50.7951660156],"type":"Point"}
}