{
  "type": "Feature",
  "properties": {
    "addr:full":"Chauss\u00e9e De Braine 83 Ecaussinnes (ecaussinnes-d'enghien) Hainaut 7190",
    "addr:housenumber":"83",
    "addr:postcode":"7190",
    "addr:street":"Chausse\u0301E De Braine;Ecaussinnes-D'Enghien Hainaut",
    "iso:country":"BE",
    "sg:address":"Chauss\u00e9e De Braine 83",
    "sg:city":"Ecaussinnes (ecaussinnes-d'enghien)",
    "sg:classifiers":[
        {
            "category":"Banks & Credit Unions",
            "subcategory":"Financial Services",
            "type":"Services"
        }
    ],
    "sg:phone":"+32 67 49 11 79",
    "sg:postcode":"7190",
    "sg:province":"Hainaut",
    "sg:tags":[
        "loan",
        "mortgage"
    ],
    "wof:name":"Cr\u00e9dit Rapide",
    "wof:placetype":"venue"
},
  "geometry": {"coordinates":[4.1513490677,50.5698661804],"type":"Point"}
}