{
  "type": "Feature",
  "properties": {
    "addr:full":"Chauss\u00e9e De Bruxelles 221 Waterloo Brabant Wallon 1410",
    "addr:housenumber":"221",
    "addr:postcode":"1410",
    "addr:street":"Chausse\u0301E De Bruxelles",
    "iso:country":"BE",
    "sg:address":"Chauss\u00e9e De Bruxelles 221",
    "sg:city":"Waterloo",
    "sg:classifiers":[
        {
            "category":"Shopping",
            "subcategory":"Computers & Home Electronics",
            "type":"Retail Goods"
        }
    ],
    "sg:phone":"+32 2 357 06 20",
    "sg:postcode":"1410",
    "sg:province":"Brabant Wallon",
    "sg:tags":[
        "-",
        "television",
        "radio"
    ],
    "wof:name":"Vid\u00e9o Square",
    "wof:placetype":"venue"
},
  "geometry": {"coordinates":[4.3990559578,50.7152557373],"type":"Point"}
}