{
  "type": "Feature",
  "properties": {
    "iso:country":"BE",
    "sg:address":"H. Torleylaan 9",
    "sg:city":"Beersel (huizingen)",
    "sg:classifiers":[
        {
            "category":"Personal",
            "subcategory":"Beauty Salon",
            "type":"Services"
        }
    ],
    "sg:phone":"+32 2 356 72 35",
    "sg:postcode":"1654",
    "sg:province":"Vlaams-Brabant",
    "sg:tags":[
        "lady",
        "-",
        "hairdressing"
    ],
    "wof:name":"Herremans J",
    "wof:placetype":"venue"
},
  "geometry": {"coordinates":[4.2748007774,50.7468757629],"type":"Point"}
}