{
  "type": "Feature",
  "properties": {
    "addr:full":"Nijverheidsstraat 8 Wommelgem Antwerpen 2160",
    "addr:housenumber":"8",
    "addr:postcode":"2160",
    "addr:street":"Nijverheidsstraat",
    "iso:country":"BE",
    "sg:address":"Nijverheidsstraat 8",
    "sg:city":"Wommelgem",
    "sg:classifiers":[
        {
            "category":"Professional",
            "subcategory":"Printing & Photocopies",
            "type":"Services"
        }
    ],
    "sg:phone":"+32 3 355 13 00",
    "sg:postcode":"2160",
    "sg:province":"Antwerpen",
    "sg:tags":[
        "publishing"
    ],
    "wof:name":"Emico Offset Nv",
    "wof:placetype":"venue"
},
  "geometry": {"coordinates":[4.5054478645,51.2112197876],"type":"Point"}
}