{
  "type": "Feature",
  "properties": {
    "iso:country":"BE",
    "sg:address":"Kortrijksebaan 54",
    "sg:city":"Holsbeek",
    "sg:classifiers":[
        {
            "category":"Building & Trades",
            "subcategory":"Landscaping Services",
            "type":"Services"
        }
    ],
    "sg:phone":"+32 16 44 57 67",
    "sg:postcode":"3220",
    "sg:province":"Vlaams-Brabant",
    "sg:tags":[
        "gardening",
        "garden",
        "maintenance"
    ],
    "wof:name":"Van Goidsenhoven",
    "wof:placetype":"venue"
},
  "geometry": {"coordinates":[4.7659540176,50.9206924438],"type":"Point"}
}