{
  "type": "Feature",
  "properties": {
    "iso:country":"BE",
    "sg:address":"Hasseltsestraat 79",
    "sg:city":"Diest",
    "sg:classifiers":[
        {
            "category":"Banks & Credit Unions",
            "subcategory":"Financial Services",
            "type":"Services"
        }
    ],
    "sg:phone":"+32 13 31 10 14",
    "sg:postcode":"3290",
    "sg:province":"Vlaams-Brabant",
    "sg:tags":[
        "loan",
        "mortgage"
    ],
    "wof:name":"Dekeyser J",
    "wof:placetype":"venue"
},
  "geometry": {"coordinates":[5.0549230576,50.9798851013],"type":"Point"}
}