{
  "type": "Feature",
  "properties": {
    "iso:country":"BE",
    "sg:address":"Zonhoverweg 10",
    "sg:city":"Genk",
    "sg:orig_category":"Quincailleries",
    "sg:phone":"+32 89 30 38 18",
    "sg:postcode":"3600",
    "sg:province":"Limburg",
    "wof:name":"Wilfried Hotters",
    "wof:placetype":"venue"
},
  "geometry": {"coordinates":[5.4589481354,50.9746055603],"type":"Point"}
}