{
  "type": "Feature",
  "properties": {
    "addr:full":"Rue Joseph Renquin 52 Bastogne Luxembourg 6600",
    "addr:housenumber":"52",
    "addr:postcode":"6600",
    "addr:street":"Rue Joseph Renquin",
    "iso:country":"BE",
    "sg:address":"Rue Joseph Renquin 52",
    "sg:city":"Bastogne",
    "sg:classifiers":[
        {
            "category":"Personal",
            "subcategory":"Beauty Salon",
            "type":"Services"
        }
    ],
    "sg:phone":"+32 61 21 35 98",
    "sg:postcode":"6600",
    "sg:province":"Luxembourg",
    "sg:tags":[
        "equipment",
        "hairdressing",
        "-",
        "supply"
    ],
    "wof:name":"Pierrette Diffusion Sprl",
    "wof:placetype":"venue"
},
  "geometry": {"coordinates":[5.7164101601,49.9989013672],"type":"Point"}
}