{
  "type": "Feature",
  "properties": {
    "iso:country":"BE",
    "sg:address":"Chemin Coparty 2b5",
    "sg:city":"Nivelles",
    "sg:orig_category":"Cabinets d\u00b4huissiers",
    "sg:phone":"+32 67 21 24 28",
    "sg:postcode":"1400",
    "sg:province":"Brabant Wallon",
    "wof:name":"T\u00c9r\u00c9sa Vanderbeck",
    "wof:placetype":"venue"
},
  "geometry": {"coordinates":[4.3360648155,50.5956687927],"type":"Point"}
}