{
  "type": "Feature",
  "properties": {
    "iso:country":"BE",
    "sg:address":"Laambroekstraat 43",
    "sg:city":"Heusden-zolder",
    "sg:orig_category":"R\u00e9parations and entretien de motos",
    "sg:phone":"+32 11 53 82 01",
    "sg:postcode":"3550",
    "sg:province":"Limburg",
    "wof:name":"Ramaekers Motoren",
    "wof:placetype":"venue"
},
  "geometry": {"coordinates":[5.3337979317,51.0186195374],"type":"Point"}
}