{
  "type": "Feature",
  "properties": {
    "addr:full":"Smalvoortstraat 27b3 Turnhout Antwerpen 2300",
    "addr:housenumber":"27b3",
    "addr:postcode":"2300",
    "addr:street":"Smalvoortstraat",
    "iso:country":"BE",
    "sg:address":"Smalvoortstraat 27b3",
    "sg:city":"Turnhout",
    "sg:orig_category":"Paramedische behandelingen",
    "sg:phone":"+32 14 42 75 22",
    "sg:postcode":"2300",
    "sg:province":"Antwerpen",
    "wof:name":"L. Van Gool",
    "wof:placetype":"venue"
},
  "geometry": {"coordinates":[4.9523730278,51.3161239624],"type":"Point"}
}