{
  "type": "Feature",
  "properties": {
    "addr:full":"Hertogstraat 48 Sint-pieters-woluwe/woluwe-saint-pierre Bruxelles-Capitale 1150",
    "addr:housenumber":"48",
    "addr:postcode":"1150",
    "addr:street":"Hertogstraat;/",
    "iso:country":"BE",
    "sg:address":"Hertogstraat 48",
    "sg:city":"Sint-pieters-woluwe/woluwe-saint-pierre",
    "sg:orig_category":"Belastingconsulenten Boekhouders Diverse juridische dienstverlening",
    "sg:phone":"+32 2 770 81 73",
    "sg:postcode":"1150",
    "sg:province":"Bruxelles-Capitale",
    "wof:name":"Roger Temmerman",
    "wof:placetype":"venue"
},
  "geometry": {"coordinates":[4.4136080742,50.8375549316],"type":"Point"}
}