{
  "type": "Feature",
  "properties": {
    "addr:full":"Rue Henri Van Zuylen 78b15 Ukkel/uccle Bruxelles-Capitale 1180",
    "addr:housenumber":"78b15",
    "addr:postcode":"1180",
    "addr:street":"Rue Henri Van Zuylen;/",
    "iso:country":"BE",
    "sg:address":"Rue Henri Van Zuylen 78b15",
    "sg:city":"Ukkel/uccle",
    "sg:orig_category":"Vertalers and tolken",
    "sg:phone":"+32 2 374 91 46",
    "sg:postcode":"1180",
    "sg:province":"Bruxelles-Capitale",
    "wof:name":"Barlovatz A. Cbtip/bkvtf",
    "wof:placetype":"venue"
},
  "geometry": {"coordinates":[4.3415541649,50.7975654602],"type":"Point"}
}