{
  "type": "Feature",
  "properties": {
    "addr:full":"Rue Des Brebis 13 Onhaye Namur 5524",
    "addr:housenumber":"13",
    "addr:postcode":"5524",
    "addr:street":"Rue Des Brebis",
    "iso:country":"BE",
    "sg:address":"Rue Des Brebis 13",
    "sg:city":"Onhaye",
    "sg:orig_category":"Rev\u00eatements de sols and murs",
    "sg:phone":"+32 82 22 80 45",
    "sg:postcode":"5524",
    "sg:province":"Namur",
    "wof:name":"Menuiserie Bayard",
    "wof:placetype":"venue"
},
  "geometry": {"coordinates":[4.8244600296,50.2428131104],"type":"Point"}
}