{
  "type": "Feature",
  "properties": {
    "iso:country":"BE",
    "sg:address":"Rue De La Lib\u00c9ration 34",
    "sg:city":"Awans",
    "sg:classifiers":[
        {
            "category":"Professional",
            "subcategory":"Accounting & Tax Preparation",
            "type":"Services"
        }
    ],
    "sg:phone":"+32 4 257 66 90",
    "sg:postcode":"4342",
    "sg:province":"Li\u00e8ge",
    "sg:tags":[
        "accountant"
    ],
    "wof:name":"Joseph Lepage",
    "wof:placetype":"venue"
},
  "geometry": {"coordinates":[5.4550800323,50.6820487976],"type":"Point"}
}