{
  "type": "Feature",
  "properties": {
    "addr:full":"Steenweg Op Nieuwrode 99 Rotselaar (wezemaal) Vlaams-Brabant 3111",
    "addr:housenumber":"99",
    "addr:postcode":"3111",
    "addr:street":"Steenweg Op Nieuwrode",
    "iso:country":"BE",
    "sg:address":"Steenweg Op Nieuwrode 99",
    "sg:city":"Rotselaar (wezemaal)",
    "sg:classifiers":[
        {
            "category":"Food & Beverages",
            "subcategory":"Specialty",
            "type":"Retail Goods"
        }
    ],
    "sg:phone":"+32 16 58 07 84",
    "sg:postcode":"3111",
    "sg:province":"Vlaams-Brabant",
    "sg:tags":[
        "health",
        "dietary",
        "-",
        "biological"
    ],
    "wof:name":"Puur Natuureke ('t)",
    "wof:placetype":"venue"
},
  "geometry": {"coordinates":[4.7728481293,50.9466018677],"type":"Point"}
}