{
  "type": "Feature",
  "properties": {
    "addr:full":"Noordstraat 16 Moorsele West-Vlaanderen 8560",
    "addr:housenumber":"16",
    "addr:postcode":"8560",
    "addr:street":"Noordstraat",
    "iso:country":"BE",
    "sg:address":"Noordstraat 16",
    "sg:city":"Moorsele",
    "sg:orig_category":"Non-Classified Establishments",
    "sg:phone":"+32 56 41 04 83",
    "sg:postcode":"8560",
    "sg:province":"West-Vlaanderen",
    "wof:name":"Devalin Nv",
    "wof:placetype":"venue"
},
  "geometry": {"coordinates":[3.1803300381,50.847618103],"type":"Point"}
}