{
  "type": "Feature",
  "properties": {
    "addr:full":"Kerkstraat 28 Landen Vlaams-Brabant 3400",
    "addr:housenumber":"28",
    "addr:postcode":"3400",
    "addr:street":"Kerkstraat",
    "iso:country":"BE",
    "sg:address":"Kerkstraat 28",
    "sg:city":"Landen",
    "sg:classifiers":[
        {
            "category":"Personal",
            "subcategory":"Barber",
            "type":"Services"
        }
    ],
    "sg:phone":"+32 11 88 28 90",
    "sg:postcode":"3400",
    "sg:province":"Vlaams-Brabant",
    "sg:tags":[
        "gentleman",
        "salon",
        "-",
        "hairdressing"
    ],
    "wof:name":"Andre",
    "wof:placetype":"venue"
},
  "geometry": {"coordinates":[5.0801258087,50.7560424805],"type":"Point"}
}