{
  "type": "Feature",
  "properties": {
    "addr:full":"Avenue Du Bourgmestre Jean Materne 123 Namur (jambes) Namur 5100",
    "addr:housenumber":"123",
    "addr:postcode":"5100",
    "addr:street":"Avenue Du Bourgmestre Jean Materne",
    "iso:country":"BE",
    "sg:address":"Avenue Du Bourgmestre Jean Materne 123",
    "sg:city":"Namur (jambes)",
    "sg:classifiers":[
        {
            "category":"Shopping",
            "subcategory":"Jewelry",
            "type":"Retail Goods"
        }
    ],
    "sg:phone":"+32 81 31 28 27",
    "sg:postcode":"5100",
    "sg:province":"Namur",
    "sg:tags":[
        "-",
        "imitation"
    ],
    "wof:name":"Lavandine",
    "wof:placetype":"venue"
},
  "geometry": {"coordinates":[4.8713750839,50.4566345215],"type":"Point"}
}