{
  "type": "Feature",
  "properties": {
    "iso:country":"BE",
    "sg:address":"Hertbloklaan 27",
    "sg:city":"Steenokkerzeel",
    "sg:orig_category":"Entretien and r\u00e9parations de voitures",
    "sg:phone":"+32 2 751 85 29",
    "sg:postcode":"1820",
    "sg:province":"Vlaams-Brabant",
    "wof:name":"Ren\u00c9 Caliber",
    "wof:placetype":"venue"
},
  "geometry": {"coordinates":[4.5089201927,50.9243583679],"type":"Point"}
}