{
  "type": "Feature",
  "properties": {
    "addr:full":"Veurnestraat 134 Poperinge West-Vlaanderen 8970",
    "addr:housenumber":"134",
    "addr:postcode":"8970",
    "addr:street":"Veurnestraat",
    "iso:country":"BE",
    "sg:address":"Veurnestraat 134",
    "sg:city":"Poperinge",
    "sg:classifiers":[
        {
            "category":"Arena",
            "subcategory":"Sports Club",
            "type":"Entertainment"
        }
    ],
    "sg:phone":"+32 57 33 81 57",
    "sg:postcode":"8970",
    "sg:province":"West-Vlaanderen",
    "sg:tags":[
        "de"
    ],
    "wof:name":"V.c. Roepovo",
    "wof:placetype":"venue"
},
  "geometry": {"coordinates":[2.730946064,50.8606491089],"type":"Point"}
}