{
  "type": "Feature",
  "properties": {
    "iso:country":"BE",
    "sg:address":"Aerdenlei 16",
    "sg:city":"Brasschaat",
    "sg:orig_category":"Ordinateurs and \u00e9quipement informatique",
    "sg:phone":"+32 3 651 32 14",
    "sg:postcode":"2930",
    "sg:province":"Antwerpen",
    "wof:name":"Interchain Belgium",
    "wof:placetype":"venue"
},
  "geometry": {"coordinates":[4.4930667877,51.2928009033],"type":"Point"}
}