{
  "type": "Feature",
  "properties": {
    "addr:full":"Rue De La Concorde 10 La Louvi\u00c8re Hainaut 7100",
    "addr:housenumber":"10",
    "addr:postcode":"7100",
    "addr:street":"Rue De La Concorde",
    "iso:country":"BE",
    "sg:address":"Rue De La Concorde 10",
    "sg:city":"La Louvi\u00c8re",
    "sg:orig_category":"Woningbouw",
    "sg:phone":"+32 64 21 73 83",
    "sg:postcode":"7100",
    "sg:province":"Hainaut",
    "wof:name":"Ilias",
    "wof:placetype":"venue"
},
  "geometry": {"coordinates":[4.1887350082,50.4788284302],"type":"Point"}
}