{
  "type": "Feature",
  "properties": {
    "iso:country":"BE",
    "sg:address":"Holstraat 28",
    "sg:city":"Waregem",
    "sg:orig_category":"Banques and organismes de cr\u00e9dit",
    "sg:phone":"+32 56 60 89 12",
    "sg:postcode":"8790",
    "sg:province":"West-Vlaanderen",
    "wof:name":"Mercator Bank",
    "wof:placetype":"venue"
},
  "geometry": {"coordinates":[3.4341239929,50.8855934143],"type":"Point"}
}