{
  "type": "Feature",
  "properties": {
    "iso:country":"BE",
    "sg:address":"Kuipenstraat 25",
    "sg:city":"Oostkamp",
    "sg:orig_category":"Rundveehouders Varkenskwekers",
    "sg:phone":"+32 50 82 29 02",
    "sg:postcode":"8020",
    "sg:province":"West-Vlaanderen",
    "wof:name":"Roger Devriendt",
    "wof:placetype":"venue"
},
  "geometry": {"coordinates":[3.1958069801,51.1344718933],"type":"Point"}
}