{
  "type": "Feature",
  "properties": {
    "iso:country":"BE",
    "sg:address":"Gentsesteenweg 399",
    "sg:city":"Erpe-mere",
    "sg:orig_category":"Entretien and r\u00e9parations de voitures",
    "sg:phone":"+32 53 80 42 55",
    "sg:postcode":"9420",
    "sg:province":"Oost-Vlaanderen",
    "wof:name":"Car Wash C.w.e.",
    "wof:placetype":"venue"
},
  "geometry": {"coordinates":[3.9558980465,50.9465522766],"type":"Point"}
}