{
  "type": "Feature",
  "properties": {
    "addr:full":"Rameistraat 62 Overijse Vlaams-Brabant 3090",
    "addr:housenumber":"62",
    "addr:postcode":"3090",
    "addr:street":"Rameistraat",
    "iso:country":"BE",
    "sg:address":"Rameistraat 62",
    "sg:city":"Overijse",
    "sg:classifiers":[
        {
            "category":"Juice Bar",
            "subcategory":"None",
            "type":"Food & Drink"
        }
    ],
    "sg:postcode":"3090",
    "sg:province":"Vlaams-Brabant",
    "sg:tags":[
        "water",
        "soft"
    ],
    "wof:name":"Brasserie Vanderlinden/poidlin",
    "wof:placetype":"venue"
},
  "geometry": {"coordinates":[4.5385890007,50.7509765625],"type":"Point"}
}