{
  "type": "Feature",
  "properties": {
    "addr:full":"Brikhof 16 Borgloon (hoepertingen) Limburg 3840",
    "addr:housenumber":"16",
    "addr:postcode":"3840",
    "addr:street":"Brikhof",
    "iso:country":"BE",
    "sg:address":"Brikhof 16",
    "sg:city":"Borgloon (hoepertingen)",
    "sg:classifiers":[
        {
            "category":"Professional",
            "subcategory":"Accounting & Tax Preparation",
            "type":"Services"
        }
    ],
    "sg:phone":"+32 12 74 47 21",
    "sg:postcode":"3840",
    "sg:province":"Limburg",
    "sg:tags":[
        "bookkeeper"
    ],
    "wof:name":"Ben-account - Derwae B Bvba",
    "wof:placetype":"venue"
},
  "geometry": {"coordinates":[5.3441700935,50.8012466431],"type":"Point"}
}