{
  "type": "Feature",
  "properties": {
    "addr:full":"Eyndovensteenweg 101 Brecht Antwerpen 2960",
    "addr:housenumber":"101",
    "addr:postcode":"2960",
    "addr:street":"Eyndovensteenweg",
    "iso:country":"BE",
    "sg:address":"Eyndovensteenweg 101",
    "sg:city":"Brecht",
    "sg:orig_category":"Imprimeries and copyshops",
    "sg:phone":"+32 3 313 98 55",
    "sg:postcode":"2960",
    "sg:province":"Antwerpen",
    "wof:name":"Albert Couvreur",
    "wof:placetype":"venue"
},
  "geometry": {"coordinates":[4.6389012337,51.3416137695],"type":"Point"}
}