{
  "type": "Feature",
  "properties": {
    "addr:full":"Westerlosesteenweg 173a Herselt Antwerpen 2230",
    "addr:housenumber":"173a",
    "addr:postcode":"2230",
    "addr:street":"Westerlosesteenweg",
    "iso:country":"BE",
    "sg:address":"Westerlosesteenweg 173a",
    "sg:city":"Herselt",
    "sg:classifiers":[
        {
            "category":"Personal",
            "subcategory":"Beauty Salon",
            "type":"Services"
        }
    ],
    "sg:phone":"+32 14 54 60 81",
    "sg:postcode":"2230",
    "sg:province":"Antwerpen",
    "sg:tags":[
        "de",
        "coiffure"
    ],
    "wof:name":"De Kapster",
    "wof:placetype":"venue"
},
  "geometry": {"coordinates":[4.8923602104,51.0659103394],"type":"Point"}
}