{
  "type": "Feature",
  "properties": {
    "iso:country":"BE",
    "sg:address":"Slachthuisstraat 145",
    "sg:city":"Tienen",
    "sg:classifiers":[
        {
            "category":"Government",
            "subcategory":"Customs House",
            "type":"Public Place"
        }
    ],
    "sg:phone":"+32 16 82 26 72",
    "sg:postcode":"3300",
    "sg:province":"Vlaams-Brabant",
    "sg:tags":[
        "packing"
    ],
    "wof:name":"Pic Plastics Bvba",
    "wof:placetype":"venue"
},
  "geometry": {"coordinates":[4.9530000687,50.8062400818],"type":"Point"}
}