{
  "type": "Feature",
  "properties": {
    "iso:country":"BE",
    "sg:address":"Tresoriersstraat 1a",
    "sg:city":"Zonnebeke",
    "sg:classifiers":[
        {
            "category":"Health Services",
            "subcategory":"Doctor",
            "type":"Services"
        }
    ],
    "sg:phone":"+32 51 77 88 88",
    "sg:postcode":"8980",
    "sg:province":"West-Vlaanderen",
    "sg:tags":[
        "medicinephysicians",
        "surgeon"
    ],
    "wof:name":"Cornardt P",
    "wof:placetype":"venue"
},
  "geometry": {"coordinates":[2.9771358967,50.8692779541],"type":"Point"}
}