{
  "type": "Feature",
  "properties": {
    "iso:country":"BE",
    "sg:address":"Rue Clerbeau 46",
    "sg:city":"Herstal",
    "sg:orig_category":"Rundveehouders",
    "sg:phone":"+32 4 278 53 39",
    "sg:postcode":"4041",
    "sg:province":"Li\u00e8ge",
    "wof:name":"Norbert Froidmont",
    "wof:placetype":"venue"
},
  "geometry": {"coordinates":[5.5956058502,50.6915016174],"type":"Point"}
}