{
  "type": "Feature",
  "properties": {
    "addr:full":"Rue Adolphe Prayez 2bb Tournai Hainaut 7500",
    "addr:housenumber":"2bb",
    "addr:postcode":"7500",
    "addr:street":"Rue Adolphe Prayez",
    "iso:country":"BE",
    "sg:address":"Rue Adolphe Prayez 2bb",
    "sg:city":"Tournai",
    "sg:orig_category":"Jeux de hasard",
    "sg:phone":"+32 69 22 06 79",
    "sg:postcode":"7500",
    "sg:province":"Hainaut",
    "wof:name":"Agence Hippique Dumoulin",
    "wof:placetype":"venue"
},
  "geometry": {"coordinates":[3.3894200325,50.5936203003],"type":"Point"}
}