{
  "type": "Feature",
  "properties": {
    "addr:full":"Grensstraat 1 Sint-gillis-waas (meerdonk) Oost-Vlaanderen 9170",
    "addr:housenumber":"1",
    "addr:postcode":"9170",
    "addr:street":"Grensstraat",
    "iso:country":"BE",
    "sg:address":"Grensstraat 1",
    "sg:city":"Sint-gillis-waas (meerdonk)",
    "sg:classifiers":[
        {
            "category":"Retail",
            "subcategory":"Laundry & Dry Cleaning",
            "type":"Services"
        }
    ],
    "sg:phone":"+32 3 773 49 88",
    "sg:postcode":"9170",
    "sg:province":"Oost-Vlaanderen",
    "sg:tags":[
        "dyer",
        "cleaner"
    ],
    "wof:name":"Droogkuis Boke Bvba",
    "wof:placetype":"venue"
},
  "geometry": {"coordinates":[4.1650791168,51.2912101746],"type":"Point"}
}