{
  "type": "Feature",
  "properties": {
    "addr:full":"Mgr. Waffelaertlaan 45 Blankenberge West-Vlaanderen 8370",
    "addr:housenumber":"45",
    "addr:postcode":"8370",
    "addr:street":"Mgr. Waffelaertlaan",
    "iso:country":"BE",
    "sg:address":"Mgr. Waffelaertlaan 45",
    "sg:city":"Blankenberge",
    "sg:classifiers":[
        {
            "category":"Insurance",
            "subcategory":"Life Insurance",
            "type":"Services"
        }
    ],
    "sg:phone":"+32 50 41 50 55",
    "sg:postcode":"8370",
    "sg:province":"West-Vlaanderen",
    "sg:tags":[
        "assurance"
    ],
    "wof:name":"G. Bouche",
    "wof:placetype":"venue"
},
  "geometry": {"coordinates":[3.1388990879,51.3114089966],"type":"Point"}
}