{
  "type": "Feature",
  "properties": {
    "addr:full":"Paleisstraat 7b10 Antwerpen Antwerpen 2018",
    "addr:housenumber":"7b10",
    "addr:postcode":"2018",
    "addr:street":"Paleisstraat",
    "iso:country":"BE",
    "sg:address":"Paleisstraat 7b10",
    "sg:city":"Antwerpen",
    "sg:orig_category":"Diverse bedrijfsbeheeradviesbureaus",
    "sg:phone":"+32 3 237 94 99",
    "sg:postcode":"2018",
    "sg:province":"Antwerpen",
    "wof:name":"B & T Consulting",
    "wof:placetype":"venue"
},
  "geometry": {"coordinates":[4.4026789665,51.2077713013],"type":"Point"}
}