{
  "type": "Feature",
  "properties": {
    "iso:country":"BE",
    "sg:address":"Avenue Du Bourgmestre Jean Materne 115-117",
    "sg:city":"Namur (jambes)",
    "sg:classifiers":[
        {
            "category":"Banks & Credit Unions",
            "subcategory":"Investment Brokerage",
            "type":"Services"
        }
    ],
    "sg:phone":"+32 81 33 28 50",
    "sg:postcode":"5100",
    "sg:province":"Namur",
    "sg:tags":[
        "development",
        "economic",
        "institution"
    ],
    "wof:name":"Ofi Sa",
    "wof:placetype":"venue"
},
  "geometry": {"coordinates":[4.8713750839,50.4566345215],"type":"Point"}
}