{
  "type": "Feature",
  "properties": {
    "addr:full":"Genkersteenweg 201 Hasselt Limburg 3500",
    "addr:housenumber":"201",
    "addr:postcode":"3500",
    "addr:street":"Genkersteenweg",
    "iso:country":"BE",
    "sg:address":"Genkersteenweg 201",
    "sg:city":"Hasselt",
    "sg:classifiers":[
        {
            "category":"Manufacturing",
            "subcategory":"Metals",
            "type":"Manufacturing & Wholesale Goods"
        }
    ],
    "sg:phone":"+32 11 21 13 65",
    "sg:postcode":"3500",
    "sg:province":"Limburg",
    "sg:tags":[
        "blanking",
        "dy"
    ],
    "wof:name":"T.p.a.i. Nv",
    "wof:placetype":"venue"
},
  "geometry": {"coordinates":[5.3801698685,50.9444885254],"type":"Point"}
}