{
  "type": "Feature",
  "properties": {
    "addr:full":"Rue Foresteau 3 Frasnes-lez-anvaing Hainaut 7911",
    "addr:housenumber":"3",
    "addr:postcode":"7911",
    "addr:street":"Rue Foresteau",
    "iso:country":"BE",
    "sg:address":"Rue Foresteau 3",
    "sg:city":"Frasnes-lez-anvaing",
    "sg:orig_category":"Animations diverses",
    "sg:phone":"+32 479 79 14 30",
    "sg:postcode":"7911",
    "sg:province":"Hainaut",
    "wof:name":"Height Energy",
    "wof:placetype":"venue"
},
  "geometry": {"coordinates":[3.6347351074,50.650302887],"type":"Point"}
}