{
  "type": "Feature",
  "properties": {
    "iso:country":"BE",
    "sg:address":"Ahornlaan 14",
    "sg:city":"Gent",
    "sg:orig_category":"Artiestenbureaus",
    "sg:phone":"+32 9 226 33 33",
    "sg:postcode":"9030",
    "sg:province":"Oost-Vlaanderen",
    "wof:name":"Managementbureau Koen Crucke-willy Claes",
    "wof:placetype":"venue"
},
  "geometry": {"coordinates":[3.6892259121,51.075252533],"type":"Point"}
}