{
  "type": "Feature",
  "properties": {
    "iso:country":"BE",
    "sg:address":"Boterstraat 2",
    "sg:city":"Ieper",
    "sg:orig_category":"Banken and kredietinstellingen",
    "sg:phone":"+32 57 20 00 98",
    "sg:postcode":"8900",
    "sg:province":"West-Vlaanderen",
    "wof:name":"Bbl",
    "wof:placetype":"venue"
},
  "geometry": {"coordinates":[2.8845009804,50.8506813049],"type":"Point"}
}