{
  "type": "Feature",
  "properties": {
    "addr:full":"Rue Arnold Lecrenier 3 Saint-georges-sur-meuse Li\u00e8ge 4470",
    "addr:housenumber":"3",
    "addr:postcode":"4470",
    "addr:street":"Rue Arnold Lecrenier",
    "iso:country":"BE",
    "sg:address":"Rue Arnold Lecrenier 3",
    "sg:city":"Saint-georges-sur-meuse",
    "sg:orig_category":"Cr\u00e8ches and garderies d'enfants",
    "sg:phone":"+32 4 275 39 48",
    "sg:postcode":"4470",
    "sg:province":"Li\u00e8ge",
    "wof:name":"Les Galipettes",
    "wof:placetype":"venue"
},
  "geometry": {"coordinates":[5.3548359871,50.5805587769],"type":"Point"}
}