{
  "type": "Feature",
  "properties": {
    "iso:country":"BE",
    "sg:address":"Grote Baan 61",
    "sg:city":"Houthalen-helchteren",
    "sg:orig_category":"Sport- and kampeermateriaal Watersport-, Sport- and Kampeerbenodigdheden Verhuur",
    "sg:phone":"+32 11 52 66 18",
    "sg:postcode":"3530",
    "sg:province":"Limburg",
    "wof:name":"Fitosport",
    "wof:placetype":"venue"
},
  "geometry": {"coordinates":[5.3763837814,51.0317649841],"type":"Point"}
}