{
  "type": "Feature",
  "properties": {
    "iso:country":"BE",
    "sg:address":"Engerstraat 17",
    "sg:city":"Kortenberg (erps-kwerps)",
    "sg:classifiers":[
        {
            "category":"Health Services",
            "subcategory":"Health Practitioner",
            "type":"Services"
        }
    ],
    "sg:phone":"+32 2 759 95 74",
    "sg:postcode":"3071",
    "sg:province":"Vlaams-Brabant",
    "sg:tags":[
        "physiotherapist"
    ],
    "wof:name":"Bellemans D",
    "wof:placetype":"venue"
},
  "geometry": {"coordinates":[4.5589089394,50.9013824463],"type":"Point"}
}