{
  "type": "Feature",
  "properties": {
    "addr:full":"Nati\u00cbnlaan 260 Knokke-heist West-Vlaanderen 8300",
    "addr:housenumber":"260",
    "addr:postcode":"8300",
    "addr:street":"Natie\u0308Nlaan",
    "iso:country":"BE",
    "sg:address":"Nati\u00cbnlaan 260",
    "sg:city":"Knokke-heist",
    "sg:classifiers":[
        {
            "category":"Fast Food",
            "type":"Food & Drink"
        }
    ],
    "sg:phone":"+32 50 62 49 58",
    "sg:postcode":"8300",
    "sg:province":"West-Vlaanderen",
    "sg:tags":[
        "meeneem",
        "restaurant"
    ],
    "wof:name":"Mcdonald's",
    "wof:placetype":"venue"
},
  "geometry": {"coordinates":[3.2888998985,51.3360900879],"type":"Point"}
}