{
  "type": "Feature",
  "properties": {
    "iso:country":"BE",
    "sg:address":"Bloemendaalstraat 19",
    "sg:city":"Bilzen",
    "sg:orig_category":"Bloemen and planten",
    "sg:phone":"+32 89 41 24 57",
    "sg:postcode":"3740",
    "sg:province":"Limburg",
    "wof:name":"Meers",
    "wof:placetype":"venue"
},
  "geometry": {"coordinates":[5.5319800377,50.8812980652],"type":"Point"}
}