{
  "type": "Feature",
  "properties": {
    "addr:full":"Jan Boonlaan 7 Halle Vlaams-Brabant 1500",
    "addr:housenumber":"7",
    "addr:postcode":"1500",
    "addr:street":"Jan Boonlaan",
    "iso:country":"BE",
    "sg:address":"Jan Boonlaan 7",
    "sg:city":"Halle",
    "sg:orig_category":"M\u00e9decins and sp\u00e9cialistes",
    "sg:phone":"+32 2 360 01 35",
    "sg:postcode":"1500",
    "sg:province":"Vlaams-Brabant",
    "wof:name":"Veerle Vergauwen",
    "wof:placetype":"venue"
},
  "geometry": {"coordinates":[4.2347660065,50.7422103882],"type":"Point"}
}