{
  "type": "Feature",
  "properties": {
    "addr:full":"Hekkestr 20 Aalst Oost-Vlaanderen 9308",
    "addr:housenumber":"20",
    "addr:postcode":"9308",
    "addr:street":"Hekkestr",
    "iso:country":"BE",
    "sg:address":"Hekkestr 20",
    "sg:city":"Aalst",
    "sg:classifiers":[
        {
            "category":"Home & Garden",
            "subcategory":"Furniture",
            "type":"Retail Goods"
        }
    ],
    "sg:phone":"+32 53 82 57 00",
    "sg:postcode":"9308",
    "sg:province":"Oost-Vlaanderen",
    "sg:tags":[
        "wood"
    ],
    "wof:name":"Distri-hout Nv",
    "wof:placetype":"venue"
},
  "geometry": {"coordinates":[4.0347590446,50.9603500366],"type":"Point"}
}