{
  "type": "Feature",
  "properties": {
    "addr:full":"Rue Auguste Lambiotte 40 Schaarbeek/schaerbeek Bruxelles-Capitale 1030",
    "addr:housenumber":"40",
    "addr:postcode":"1030",
    "addr:street":"Rue Auguste Lambiotte",
    "iso:country":"BE",
    "sg:address":"Rue Auguste Lambiotte 40",
    "sg:city":"Schaarbeek/schaerbeek",
    "sg:orig_category":"Boucheries",
    "sg:phone":"+32 2 241 03 50",
    "sg:postcode":"1030",
    "sg:province":"Bruxelles-Capitale",
    "wof:name":"Groep Wauters/boucherie Wauters",
    "wof:placetype":"venue"
},
  "geometry": {"coordinates":[4.3876171112,50.8568115234],"type":"Point"}
}