{
  "type": "Feature",
  "properties": {
    "addr:full":"Ter Bist 12 Haacht Vlaams-Brabant 3150",
    "addr:housenumber":"12",
    "addr:postcode":"3150",
    "addr:street":"Ter Bist",
    "iso:country":"BE",
    "sg:address":"Ter Bist 12",
    "sg:city":"Haacht",
    "sg:orig_category":"Reclamebureaus",
    "sg:phone":"+32 16 60 96 62",
    "sg:postcode":"3150",
    "sg:province":"Vlaams-Brabant",
    "wof:name":"Blue C Communications",
    "wof:placetype":"venue"
},
  "geometry": {"coordinates":[4.6334309578,50.9798851013],"type":"Point"}
}