{
  "type": "Feature",
  "properties": {
    "addr:full":"Rue Des Vingt-deux 18 Li\u00c8ge Li\u00e8ge 4000",
    "addr:housenumber":"18",
    "addr:postcode":"4000",
    "addr:street":"Rue Des Vingt-Deux",
    "iso:country":"BE",
    "sg:address":"Rue Des Vingt-deux 18",
    "sg:city":"Li\u00c8ge",
    "sg:orig_category":"Architectes",
    "sg:phone":"+32 4 254 20 60",
    "sg:postcode":"4000",
    "sg:province":"Li\u00e8ge",
    "wof:name":"Claude Cousin",
    "wof:placetype":"venue"
},
  "geometry": {"coordinates":[5.569674015,50.6285057068],"type":"Point"}
}