{
  "type": "Feature",
  "properties": {
    "iso:country":"BE",
    "sg:address":"Rue De Dori\u00e9mont 18",
    "sg:city":"Doische (gochen\u00e9e)",
    "sg:classifiers":[
        {
            "category":"Farming",
            "subcategory":"Livestock Farm",
            "type":"Manufacturing & Wholesale Goods"
        }
    ],
    "sg:phone":"+32 82 67 73 58",
    "sg:postcode":"5680",
    "sg:province":"Namur",
    "sg:tags":[
        "breeding"
    ],
    "wof:name":"Dejardin Ph",
    "wof:placetype":"venue"
},
  "geometry": {"coordinates":[4.7556428909,50.1844406128],"type":"Point"}
}