{
  "type": "Feature",
  "properties": {
    "addr:full":"Lochtstraat 18 Hechtel-eksel Limburg 3941",
    "addr:housenumber":"18",
    "addr:postcode":"3941",
    "addr:street":"Lochtstraat",
    "iso:country":"BE",
    "sg:address":"Lochtstraat 18",
    "sg:city":"Hechtel-eksel",
    "sg:orig_category":"Enseignement maternel and primaire",
    "sg:phone":"+32 11 73 19 86",
    "sg:postcode":"3941",
    "sg:province":"Limburg",
    "wof:name":"Vrije Kleuterschool",
    "wof:placetype":"venue"
},
  "geometry": {"coordinates":[5.3624329567,51.1469345093],"type":"Point"}
}