{
  "type": "Feature",
  "properties": {
    "iso:country":"BE",
    "sg:address":"Klemskerkestraat 3",
    "sg:city":"Bredene",
    "sg:orig_category":"H\u00f4tels",
    "sg:phone":"+32 59 33 00 66",
    "sg:postcode":"8450",
    "sg:province":"West-Vlaanderen",
    "wof:name":"'t Hoeveke",
    "wof:placetype":"venue"
},
  "geometry": {"coordinates":[2.9817969799,51.2529258728],"type":"Point"}
}