{
  "type": "Feature",
  "properties": {
    "addr:full":"Giervalkenlaan 6 Watermaal-bosvoorde/watermael-boitsfort Bruxelles-Capitale 1170",
    "addr:housenumber":"6",
    "addr:postcode":"1170",
    "addr:street":"Giervalkenlaan",
    "iso:country":"BE",
    "sg:address":"Giervalkenlaan 6",
    "sg:city":"Watermaal-bosvoorde/watermael-boitsfort",
    "sg:orig_category":"Artsen and specialisten",
    "sg:phone":"+32 2 662 14 12",
    "sg:postcode":"1170",
    "sg:province":"Bruxelles-Capitale",
    "wof:name":"P. Feron",
    "wof:placetype":"venue"
},
  "geometry": {"coordinates":[4.4169812202,50.8117637634],"type":"Point"}
}