{
  "type": "Feature",
  "properties": {
    "addr:full":"Rue Victor Baudour 43-45 Mons (havr\u00e9) Hainaut 7021",
    "addr:housenumber":"43-45",
    "addr:postcode":"7021",
    "addr:street":"Rue Victor Baudour",
    "iso:country":"BE",
    "sg:address":"Rue Victor Baudour 43-45",
    "sg:city":"Mons (havr\u00e9)",
    "sg:classifiers":[
        {
            "category":"Health Services",
            "subcategory":"Health Practitioner",
            "type":"Services"
        }
    ],
    "sg:phone":"+32 65 87 34 08",
    "sg:postcode":"7021",
    "sg:province":"Hainaut",
    "sg:tags":[
        "physiotherapist"
    ],
    "wof:name":"Gantois Pierre",
    "wof:placetype":"venue"
},
  "geometry": {"coordinates":[4.0456829071,50.4640655518],"type":"Point"}
}