{
  "type": "Feature",
  "properties": {
    "addr:full":"Rue C\u00e9lestin Demblon 20 Soumagne Li\u00e8ge 4630",
    "addr:housenumber":"20",
    "addr:postcode":"4630",
    "addr:street":"Rue Ce\u0301Lestin Demblon",
    "iso:country":"BE",
    "sg:address":"Rue C\u00e9lestin Demblon 20",
    "sg:city":"Soumagne",
    "sg:classifiers":[
        {
            "category":"Real Estate",
            "subcategory":"Architect",
            "type":"Services"
        }
    ],
    "sg:phone":"+32 4 377 33 32",
    "sg:postcode":"4630",
    "sg:province":"Li\u00e8ge",
    "wof:name":"Biemar A",
    "wof:placetype":"venue"
},
  "geometry": {"coordinates":[5.7453150749,50.6137390137],"type":"Point"}
}