{
  "type": "Feature",
  "properties": {
    "iso:country":"BE",
    "sg:address":"Rue Fernand S\u00c9verin 75",
    "sg:city":"Schaarbeek/schaerbeek",
    "sg:orig_category":"Maisons de repos and r\u00e9sidences",
    "sg:phone":"+32 2 215 06 77",
    "sg:postcode":"1030",
    "sg:province":"Bruxelles-Capitale",
    "wof:name":"R\u00c9sidence Chantal",
    "wof:placetype":"venue"
},
  "geometry": {"coordinates":[4.390458107,50.876499176],"type":"Point"}
}