{
  "type": "Feature",
  "properties": {
    "addr:full":"Oedelemsestraat 53 Oostkamp West-Vlaanderen 8020",
    "addr:housenumber":"53",
    "addr:postcode":"8020",
    "addr:street":"Oedelemsestraat",
    "iso:country":"BE",
    "sg:address":"Oedelemsestraat 53",
    "sg:city":"Oostkamp",
    "sg:classifiers":[
        {
            "category":"Health Services",
            "subcategory":"Health Practitioner",
            "type":"Services"
        }
    ],
    "sg:phone":"+32 50 82 32 82",
    "sg:postcode":"8020",
    "sg:province":"West-Vlaanderen",
    "sg:tags":[
        "therapist",
        "speech"
    ],
    "wof:name":"Van De Sande Bea",
    "wof:placetype":"venue"
},
  "geometry": {"coordinates":[3.2709770203,51.1585426331],"type":"Point"}
}