{
  "type": "Feature",
  "properties": {
    "iso:country":"BE",
    "sg:address":"Rue De Tournai 255",
    "sg:city":"Beloeil (stambruges)",
    "sg:classifiers":[
        {
            "category":"Retail",
            "subcategory":"Animal Services",
            "type":"Services"
        }
    ],
    "sg:phone":"+32 69 64 18 76",
    "sg:postcode":"7973",
    "sg:province":"Hainaut",
    "sg:tags":[
        "grooming",
        "-",
        "dog"
    ],
    "wof:name":"Poil De Carotte",
    "wof:placetype":"venue"
},
  "geometry": {"coordinates":[3.7080059052,50.499130249],"type":"Point"}
}