{
  "type": "Feature",
  "properties": {
    "iso:country":"BE",
    "sg:address":"Gentsestraat 4",
    "sg:city":"Moorslede",
    "sg:orig_category":"Solariums",
    "sg:phone":"+32 51 77 28 51",
    "sg:postcode":"8890",
    "sg:province":"West-Vlaanderen",
    "wof:name":"Debacker V",
    "wof:placetype":"venue"
},
  "geometry": {"coordinates":[3.0683550835,50.8930549622],"type":"Point"}
}