{
  "type": "Feature",
  "properties": {
    "addr:full":"Rue Trieu Du Charnoy 70 Gerpinnes Hainaut 6280",
    "addr:housenumber":"70",
    "addr:postcode":"6280",
    "addr:street":"Rue Trieu Du Charnoy;Hainaut",
    "iso:country":"BE",
    "sg:address":"Rue Trieu Du Charnoy 70",
    "sg:city":"Gerpinnes",
    "sg:classifiers":[
        {
            "category":"Insurance",
            "subcategory":"Life Insurance",
            "type":"Services"
        }
    ],
    "sg:phone":"+32 71 50 53 93",
    "sg:postcode":"6280",
    "sg:province":"Hainaut",
    "sg:tags":[
        "assurance"
    ],
    "wof:name":"Claudine Lesoil",
    "wof:placetype":"venue"
},
  "geometry": {"coordinates":[4.5075831413,50.3585205078],"type":"Point"}
}