{
  "type": "Feature",
  "properties": {
    "iso:country":"BE",
    "sg:address":"Tienne Marion 15",
    "sg:city":"Mettet",
    "sg:orig_category":"Kapsalons",
    "sg:phone":"+32 71 72 96 98",
    "sg:postcode":"5644",
    "sg:province":"Namur",
    "wof:name":"Coiffure Anne",
    "wof:placetype":"venue"
},
  "geometry": {"coordinates":[4.7207927704,50.296875],"type":"Point"}
}