{
  "type": "Feature",
  "properties": {
    "addr:full":"Heinakker 7 Gent (wondelgem) Oost-Vlaanderen 9032",
    "addr:housenumber":"7",
    "addr:postcode":"9032",
    "addr:street":"Heinakker",
    "iso:country":"BE",
    "sg:address":"Heinakker 7",
    "sg:city":"Gent (wondelgem)",
    "sg:classifiers":[
        {
            "category":"Shopping",
            "type":"Retail Goods"
        }
    ],
    "sg:phone":"+32 9 253 11 70",
    "sg:postcode":"9032",
    "sg:province":"Oost-Vlaanderen",
    "sg:tags":[
        "bag",
        "burlap"
    ],
    "wof:name":"Van Doorselaere",
    "wof:placetype":"venue"
},
  "geometry": {"coordinates":[3.7162549496,51.0900535583],"type":"Point"}
}