{
  "type": "Feature",
  "properties": {
    "iso:country":"BE",
    "sg:address":"Havenstraat 30b2",
    "sg:city":"Genk",
    "sg:orig_category":"Benzinestations and brandstoffen Herstellingen and onderhoud van auto's",
    "sg:phone":"+32 89 36 31 86",
    "sg:postcode":"3600",
    "sg:province":"Limburg",
    "wof:name":"Garage Deben",
    "wof:placetype":"venue"
},
  "geometry": {"coordinates":[5.4948401451,50.9462966919],"type":"Point"}
}