{
  "type": "Feature",
  "properties": {
    "addr:full":"Dijkstraat 9b Lokeren Oost-Vlaanderen 9160",
    "addr:housenumber":"9b",
    "addr:postcode":"9160",
    "addr:street":"Dijkstraat",
    "iso:country":"BE",
    "sg:address":"Dijkstraat 9b",
    "sg:city":"Lokeren",
    "sg:classifiers":[
        {
            "category":"Wholesale",
            "subcategory":"Vending Machines",
            "type":"Manufacturing & Wholesale Goods"
        }
    ],
    "sg:phone":"+32 9 349 14 00",
    "sg:postcode":"9160",
    "sg:province":"Oost-Vlaanderen",
    "sg:tags":[
        "shop",
        "plants",
        "technical",
        "factory",
        "cleaning",
        "maintenance"
    ],
    "wof:name":"Desma Cleaning Nv",
    "wof:placetype":"venue"
},
  "geometry": {"coordinates":[4.0231661797,51.0923118591],"type":"Point"}
}