{
  "type": "Feature",
  "properties": {
    "addr:full":"Rue De La Poteresse 2ba Namur Namur 5004",
    "addr:housenumber":"2ba",
    "addr:postcode":"5004",
    "addr:street":"Rue De La Poteresse",
    "iso:country":"BE",
    "sg:address":"Rue De La Poteresse 2ba",
    "sg:city":"Namur",
    "sg:orig_category":"Sportclubs",
    "sg:phone":"+32 81 21 20 82",
    "sg:postcode":"5004",
    "sg:province":"Namur",
    "wof:name":"V.c. Eghezee",
    "wof:placetype":"venue"
},
  "geometry": {"coordinates":[4.8862218857,50.4743499756],"type":"Point"}
}