{
  "type": "Feature",
  "properties": {
    "addr:full":"Dr Van De Perrestraat 97 Geel Antwerpen 2440",
    "addr:housenumber":"97",
    "addr:postcode":"2440",
    "addr:street":"Dr Van De Perrestraat",
    "iso:country":"BE",
    "sg:address":"Dr Van De Perrestraat 97",
    "sg:city":"Geel",
    "sg:orig_category":"Plaatsen van vloer- and muurbekleding Schilders",
    "sg:phone":"+32 14 58 40 59",
    "sg:postcode":"2440",
    "sg:province":"Antwerpen",
    "wof:name":"Jozef Nuyts",
    "wof:placetype":"venue"
},
  "geometry": {"coordinates":[4.9873170853,51.1734733582],"type":"Point"}
}