{
  "type": "Feature",
  "properties": {
    "addr:full":"Bellekouter 42 Affligem (essene) Vlaams-Brabant 1790",
    "addr:housenumber":"42",
    "addr:postcode":"1790",
    "addr:street":"Bellekouter",
    "iso:country":"BE",
    "sg:address":"Bellekouter 42",
    "sg:city":"Affligem (essene)",
    "sg:classifiers":[
        {
            "category":"Personal",
            "subcategory":"Beauty Salon",
            "type":"Services"
        }
    ],
    "sg:phone":"+32 53 68 21 15",
    "sg:postcode":"1790",
    "sg:province":"Vlaams-Brabant",
    "sg:tags":[
        "lady",
        "-",
        "hairdressing"
    ],
    "wof:name":"Frou-frou",
    "wof:placetype":"venue"
},
  "geometry": {"coordinates":[4.1116170883,50.8941345215],"type":"Point"}
}