{
  "type": "Feature",
  "properties": {
    "iso:country":"BE",
    "sg:address":"Rue Du Mar\u00c9chal Joffre 3",
    "sg:city":"Colfontaine",
    "sg:orig_category":"Sociale secretariaten Verplichte sociale verzekeringen",
    "sg:phone":"+32 65 67 16 01",
    "sg:postcode":"7340",
    "sg:province":"Hainaut",
    "wof:name":"Partena",
    "wof:placetype":"venue"
},
  "geometry": {"coordinates":[3.8395850658,50.390422821],"type":"Point"}
}