{
  "type": "Feature",
  "properties": {
    "addr:full":"Rue L\u00e9on Burny 3 Les Bons Villers (mellet) Hainaut 6211",
    "addr:housenumber":"3",
    "addr:postcode":"6211",
    "addr:street":"Rue Le\u0301On Burny",
    "iso:country":"BE",
    "sg:address":"Rue L\u00e9on Burny 3",
    "sg:city":"Les Bons Villers (mellet)",
    "sg:classifiers":[
        {
            "category":"Building & Trades",
            "subcategory":"Construction",
            "type":"Services"
        }
    ],
    "sg:phone":"+32 71 85 18 85",
    "sg:postcode":"6211",
    "sg:province":"Hainaut",
    "sg:tags":[
        "installation",
        "-",
        "central",
        "heating"
    ],
    "wof:name":"Vaes E",
    "wof:placetype":"venue"
},
  "geometry": {"coordinates":[4.4791898727,50.5055961609],"type":"Point"}
}