{
  "type": "Feature",
  "properties": {
    "iso:country":"BE",
    "sg:address":"Rue De La Papyr\u00c9e 41",
    "sg:city":"Braine-l\u00b4alleud",
    "sg:classifiers":[
        {
            "category":"Sports & Exercise",
            "subcategory":"Sports Center",
            "type":"Entertainment"
        }
    ],
    "sg:phone":"+32 2 387 43 54",
    "sg:postcode":"1420",
    "sg:province":"Brabant Wallon",
    "sg:tags":[
        "terrain",
        "hors",
        "de",
        "installation",
        "sportifs"
    ],
    "wof:name":"A. Wotaland",
    "wof:placetype":"venue"
},
  "geometry": {"coordinates":[4.3623209,50.6887168884],"type":"Point"}
}