{
  "type": "Feature",
  "properties": {
    "addr:full":"Rue Mathieu De Lexhy 273-277 Gr\u00e2ce-hollogne (gr\u00e2ce-berleur) Li\u00e8ge 4460",
    "addr:postcode":"273-277;4460",
    "addr:street":"Rue Mathieu De Lexhy",
    "iso:country":"BE",
    "sg:address":"Rue Mathieu De Lexhy 273-277",
    "sg:city":"Gr\u00e2ce-hollogne (gr\u00e2ce-berleur)",
    "sg:classifiers":[
        {
            "category":"Manufacturing",
            "subcategory":"Lumber",
            "type":"Manufacturing & Wholesale Goods"
        }
    ],
    "sg:phone":"+32 4 246 02 13",
    "sg:postcode":"4460",
    "sg:province":"Li\u00e8ge",
    "sg:tags":[
        "timber"
    ],
    "wof:name":"Jonckers-clabots Sprl",
    "wof:placetype":"venue"
},
  "geometry": {"coordinates":[5.4983139038,50.6481513977],"type":"Point"}
}