{
  "type": "Feature",
  "properties": {
    "addr:full":"Lauweplaats 9 Menen (lauwe) West-Vlaanderen 8930",
    "addr:housenumber":"9",
    "addr:postcode":"8930",
    "addr:street":"Lauweplaats",
    "iso:country":"BE",
    "sg:address":"Lauweplaats 9",
    "sg:city":"Menen (lauwe)",
    "sg:classifiers":[
        {
            "category":"Professional",
            "subcategory":"Computer Services",
            "type":"Services"
        }
    ],
    "sg:phone":"+32 56 32 01 35",
    "sg:postcode":"8930",
    "sg:province":"West-Vlaanderen",
    "sg:tags":[
        "-",
        "processing",
        "data",
        "software"
    ],
    "wof:name":"Pavecom Bvba",
    "wof:placetype":"venue"
},
  "geometry": {"coordinates":[3.1649439335,50.7863426208],"type":"Point"}
}