{
  "type": "Feature",
  "properties": {
    "addr:full":"Rue Douffet 82 Li\u00e8ge 1 (li\u00e8ge 2) Li\u00e8ge 4020",
    "addr:housenumber":"82;1;2",
    "addr:postcode":"4020",
    "addr:street":"Rue Douffet",
    "iso:country":"BE",
    "sg:address":"Rue Douffet 82",
    "sg:city":"Li\u00e8ge 1 (li\u00e8ge 2)",
    "sg:classifiers":[
        {
            "category":"Arena",
            "subcategory":"Sports Club",
            "type":"Entertainment"
        }
    ],
    "sg:phone":"+32 4 342 98 46",
    "sg:postcode":"4020",
    "sg:province":"Li\u00e8ge",
    "wof:name":"Temps Libre Sprl",
    "wof:placetype":"venue"
},
  "geometry": {"coordinates":[5.5842251778,50.6349983215],"type":"Point"}
}