{
  "type": "Feature",
  "properties": {
    "iso:country":"BE",
    "sg:address":"Rue Warfus\u00c9 64",
    "sg:city":"Stockay Saint-george",
    "sg:orig_category":"Glaszetten and glaswerk",
    "sg:phone":"+32 4 275 29 12",
    "sg:postcode":"4470",
    "sg:province":"Li\u00e8ge",
    "wof:name":"Fe Dely-timsonet",
    "wof:placetype":"venue"
},
  "geometry": {"coordinates":[5.3648958206,50.5897865295],"type":"Point"}
}