{
  "type": "Feature",
  "properties": {
    "iso:country":"BE",
    "sg:address":"Vijverstraat 41",
    "sg:city":"Lede",
    "sg:classifiers":[
        {
            "category":"Arts & Performance",
            "subcategory":"Symphony",
            "type":"Entertainment"
        }
    ],
    "sg:phone":"+32 53 80 67 99",
    "sg:postcode":"9340",
    "sg:province":"Oost-Vlaanderen",
    "sg:tags":[
        "orchestra"
    ],
    "wof:name":"The Antonio's",
    "wof:placetype":"venue"
},
  "geometry": {"coordinates":[3.9795069695,50.970615387],"type":"Point"}
}