{
  "type": "Feature",
  "properties": {
    "iso:country":"BE",
    "sg:address":"Wolstraat 1",
    "sg:city":"Antwerpen",
    "sg:orig_category":"Meubelzaken, woning- and keukeninrichting Verlichting and huishoudartikelen",
    "sg:phone":"+32 3 226 35 52",
    "sg:postcode":"2000",
    "sg:province":"Antwerpen",
    "wof:name":"Mantis Interieur",
    "wof:placetype":"venue"
},
  "geometry": {"coordinates":[4.4024400711,51.2215499878],"type":"Point"}
}