{
  "type": "Feature",
  "properties": {
    "iso:country":"BE",
    "sg:address":"Veste 8",
    "sg:city":"Zaventem (sint-stevens-woluwe)",
    "sg:classifiers":[
        {
            "category":"Home & Garden",
            "subcategory":"Carpets & Floor Coverings",
            "type":"Retail Goods"
        }
    ],
    "sg:phone":"+32 475 46 26 79",
    "sg:postcode":"1932",
    "sg:province":"Vlaams-Brabant",
    "sg:tags":[
        "layer",
        "mosaicists"
    ],
    "wof:name":"Butera D",
    "wof:placetype":"venue"
},
  "geometry": {"coordinates":[4.4524841309,50.8691673279],"type":"Point"}
}