{
  "type": "Feature",
  "properties": {
    "iso:country":"BE",
    "sg:address":"Groignestraat 10",
    "sg:city":"Diksmuide",
    "sg:orig_category":"Rundveehouders Varkenskwekers",
    "sg:phone":"+32 58 28 85 83",
    "sg:postcode":"8600",
    "sg:province":"West-Vlaanderen",
    "wof:name":"Luc Seys",
    "wof:placetype":"venue"
},
  "geometry": {"coordinates":[2.8657801151,51.0334663391],"type":"Point"}
}