{
  "type": "Feature",
  "properties": {
    "iso:country":"BE",
    "sg:address":"Avenue Du Roi Albert 712",
    "sg:city":"Mons",
    "sg:orig_category":"Boucheries",
    "sg:phone":"+32 65 88 48 50",
    "sg:postcode":"7012",
    "sg:province":"Hainaut",
    "wof:name":"Boucherie Hauts Pays",
    "wof:placetype":"venue"
},
  "geometry": {"coordinates":[3.8894600868,50.4481964111],"type":"Point"}
}