{
  "type": "Feature",
  "properties": {
    "iso:country":"BE",
    "sg:address":"Rue De Fl\u00c9malle-gr. 24-26",
    "sg:city":"Flemalle",
    "sg:orig_category":"Royal Canin. Machines and mat\u00e9riel agricoles Articles de jardin",
    "sg:phone":"+32 4 233 92 20",
    "sg:postcode":"4400",
    "sg:province":"Li\u00e8ge",
    "wof:name":"Leroy-godenne & Fils",
    "wof:placetype":"venue"
},
  "geometry": {"coordinates":[5.4803719521,50.6054153442],"type":"Point"}
}