{
  "type": "Feature",
  "properties": {
    "addr:full":"Avenue Chantecler 18 Braine-l\u00b4alleud Brabant Wallon 1420",
    "addr:housenumber":"18",
    "addr:postcode":"1420",
    "addr:street":"Avenue Chantecler;Brabant Wallon",
    "iso:country":"BE",
    "sg:address":"Avenue Chantecler 18",
    "sg:city":"Braine-l\u00b4alleud",
    "sg:classifiers":[
        {
            "category":"Insurance",
            "subcategory":"Life Insurance",
            "type":"Services"
        }
    ],
    "sg:phone":"+32 2 384 78 72",
    "sg:postcode":"1420",
    "sg:province":"Brabant Wallon",
    "sg:tags":[
        "assurance"
    ],
    "wof:name":"I.p.s. Et Cie",
    "wof:placetype":"venue"
},
  "geometry": {"coordinates":[4.3741278648,50.6893959045],"type":"Point"}
}