{
  "type": "Feature",
  "properties": {
    "addr:full":"Grand-rue 30 Tintigny Luxembourg 6730",
    "addr:housenumber":"30",
    "addr:postcode":"6730",
    "addr:street":"Grand-Rue",
    "iso:country":"BE",
    "sg:address":"Grand-rue 30",
    "sg:city":"Tintigny",
    "sg:orig_category":"H\u00f4tels. Caf\u00e9s",
    "sg:phone":"+32 63 44 41 56",
    "sg:postcode":"6730",
    "sg:province":"Luxembourg",
    "wof:name":"H\u00d4tel La Vieille Gaume",
    "wof:placetype":"venue"
},
  "geometry": {"coordinates":[5.5203008652,49.6826210022],"type":"Point"}
}