{
  "type": "Feature",
  "properties": {
    "iso:country":"BE",
    "sg:address":"Boonmarkt 31",
    "sg:city":"Heist-op-den-berg",
    "sg:orig_category":"Instellingen voor mindervalide volwassenen",
    "sg:phone":"+32 15 25 85 81",
    "sg:postcode":"2220",
    "sg:province":"Antwerpen",
    "wof:name":"Home Marjorie",
    "wof:placetype":"venue"
},
  "geometry": {"coordinates":[4.7164001465,51.0866889954],"type":"Point"}
}