{
  "type": "Feature",
  "properties": {
    "iso:country":"BE",
    "sg:address":"Bredestraat 4",
    "sg:city":"Antwerpen",
    "sg:classifiers":[
        {
            "category":"Professional",
            "subcategory":"Management & Consulting",
            "type":"Services"
        }
    ],
    "sg:phone":"+32 3 233 35 75",
    "sg:postcode":"2000",
    "sg:province":"Antwerpen",
    "sg:tags":[
        "consultant",
        "agency",
        "advertising"
    ],
    "wof:name":"Antwerp Business House- Lectra",
    "wof:placetype":"venue"
},
  "geometry": {"coordinates":[4.4020428658,51.2151298523],"type":"Point"}
}