{
  "type": "Feature",
  "properties": {
    "iso:country":"BE",
    "sg:address":"Kapelsesteenweg 72",
    "sg:city":"Brasschaat",
    "sg:orig_category":"Kunstonderwijs",
    "sg:phone":"+32 3 646 47 30",
    "sg:postcode":"2930",
    "sg:province":"Antwerpen",
    "wof:name":"Tekenacademie St.michiel",
    "wof:placetype":"venue"
},
  "geometry": {"coordinates":[4.4582538605,51.2724761963],"type":"Point"}
}