{
  "type": "Feature",
  "properties": {
    "addr:full":"Chauss\u00e9e De Louvain 510 Bruxelles (schaerbeek) Bruxelles-Capitale 1030",
    "addr:housenumber":"510",
    "addr:postcode":"1030",
    "addr:street":"Chausse\u0301E De Louvain",
    "iso:country":"BE",
    "sg:address":"Chauss\u00e9e De Louvain 510",
    "sg:city":"Bruxelles (schaerbeek)",
    "sg:orig_category":"Autombile concessionaires",
    "sg:phone":"+32 2 739 12 00",
    "sg:postcode":"1030",
    "sg:province":"Bruxelles-Capitale",
    "wof:name":"D'ieteren Meiser",
    "wof:placetype":"venue"
},
  "geometry": {"coordinates":[4.3941221237,50.8538322449],"type":"Point"}
}