{
  "type": "Feature",
  "properties": {
    "iso:country":"BE",
    "sg:address":"Rue Foss\u00e9 Des Vaux 1",
    "sg:city":"Court-saint-etienne",
    "sg:classifiers":[
        {
            "category":"Real Estate",
            "subcategory":"Architect",
            "type":"Services"
        }
    ],
    "sg:phone":"+32 10 61 45 34",
    "sg:postcode":"1490",
    "sg:province":"Brabant Wallon",
    "wof:name":"Vandemeulebroucke M-p",
    "wof:placetype":"venue"
},
  "geometry": {"coordinates":[4.6017298698,50.646648407],"type":"Point"}
}