{
  "type": "Feature",
  "properties": {
    "iso:country":"BE",
    "sg:address":"Chauss\u00c9e De Tournai 352",
    "sg:city":"Ath",
    "sg:orig_category":"Serres and speciale beglazing",
    "sg:phone":"+32 68 28 53 57",
    "sg:postcode":"7812",
    "sg:province":"Hainaut",
    "wof:name":"Jose Legrand",
    "wof:placetype":"venue"
},
  "geometry": {"coordinates":[3.7079770565,50.6189002991],"type":"Point"}
}