{
  "type": "Feature",
  "properties": {
    "addr:full":"Grote Baan 209 Aalst Oost-Vlaanderen 9310",
    "addr:housenumber":"209",
    "addr:postcode":"9310",
    "addr:street":"Grote Baan",
    "iso:country":"BE",
    "sg:address":"Grote Baan 209",
    "sg:city":"Aalst",
    "sg:orig_category":"Enseignement maternel and primaire",
    "sg:phone":"+32 53 78 67 14",
    "sg:postcode":"9310",
    "sg:province":"Oost-Vlaanderen",
    "wof:name":"Gemeentelijke Basisschool",
    "wof:placetype":"venue"
},
  "geometry": {"coordinates":[4.098400116,50.9477767944],"type":"Point"}
}