{
  "type": "Feature",
  "properties": {
    "iso:country":"BE",
    "sg:address":"Steenstraat 46",
    "sg:city":"Evergem",
    "sg:orig_category":"Vloer- and muurbekleding Woningbouw",
    "sg:phone":"+32 9 344 41 09",
    "sg:postcode":"9940",
    "sg:province":"Oost-Vlaanderen",
    "wof:name":"Lippens En De Pauw",
    "wof:placetype":"venue"
},
  "geometry": {"coordinates":[3.7521879673,51.1765441895],"type":"Point"}
}