{
  "type": "Feature",
  "properties": {
    "addr:full":"Rue Des Grottes 15 Comblain-au-pont Li\u00e8ge 4170",
    "addr:housenumber":"15",
    "addr:postcode":"4170",
    "addr:street":"Rue Des Grottes",
    "iso:country":"BE",
    "sg:address":"Rue Des Grottes 15",
    "sg:city":"Comblain-au-pont",
    "sg:orig_category":"Werk and personeelsselectie",
    "sg:phone":"+32 4 369 99 21",
    "sg:postcode":"4170",
    "sg:province":"Li\u00e8ge",
    "wof:name":"S.l.a.i.e. Comblain-au-pont",
    "wof:placetype":"venue"
},
  "geometry": {"coordinates":[5.5734257698,50.4761352539],"type":"Point"}
}