{
  "type": "Feature",
  "properties": {
    "iso:country":"BE",
    "sg:address":"Rue Albert Ier 58",
    "sg:city":"Fl\u00c9ron",
    "sg:orig_category":"Woningbouw",
    "sg:phone":"+32 4 358 69 37",
    "sg:postcode":"4620",
    "sg:province":"Li\u00e8ge",
    "wof:name":"Luigi Panzica",
    "wof:placetype":"venue"
},
  "geometry": {"coordinates":[5.6739301682,50.6151504517],"type":"Point"}
}