{
  "type": "Feature",
  "properties": {
    "iso:country":"BE",
    "sg:address":"Avenue Des Combattants 38-40",
    "sg:city":"Gembloux-sur-orneau (gembloux)",
    "sg:classifiers":[
        {
            "category":"Professional",
            "subcategory":"Lawyer & Legal Services",
            "type":"Services"
        }
    ],
    "sg:phone":"+32 81 60 11 07",
    "sg:postcode":"5030",
    "sg:province":"Namur",
    "wof:name":"Linotte Caroline",
    "wof:placetype":"venue"
},
  "geometry": {"coordinates":[4.6998801231,50.5598297119],"type":"Point"}
}