{
  "type": "Feature",
  "properties": {
    "addr:full":"Dennenlaan 13 Zele Oost-Vlaanderen 9240",
    "addr:housenumber":"13",
    "addr:postcode":"9240",
    "addr:street":"Dennenlaan",
    "iso:country":"BE",
    "sg:address":"Dennenlaan 13",
    "sg:city":"Zele",
    "sg:orig_category":"Installatie van metalen schrijnwerk",
    "sg:phone":"+32 52 45 32 54",
    "sg:postcode":"9240",
    "sg:province":"Oost-Vlaanderen",
    "wof:name":"Johnny Boone",
    "wof:placetype":"venue"
},
  "geometry": {"coordinates":[4.0349760056,51.0730400085],"type":"Point"}
}