{
  "type": "Feature",
  "properties": {
    "iso:country":"BE",
    "sg:address":"Berchemstraat 71",
    "sg:city":"Dilbeek",
    "sg:orig_category":"Dakwerken",
    "sg:phone":"+32 2 463 46 33",
    "sg:postcode":"1700",
    "sg:province":"Vlaams-Brabant",
    "wof:name":"Eurofing",
    "wof:placetype":"venue"
},
  "geometry": {"coordinates":[4.2733187675,50.8478393555],"type":"Point"}
}