{
  "type": "Feature",
  "properties": {
    "iso:country":"BE",
    "sg:address":"Rue De Huy 149",
    "sg:city":"Villers-le-bouillet",
    "sg:orig_category":"Belastingconsulenten Diverse juridische dienstverlening",
    "sg:phone":"+32 85 21 70 40",
    "sg:postcode":"4530",
    "sg:province":"Li\u00e8ge",
    "wof:name":"Danielle Deprez",
    "wof:placetype":"venue"
},
  "geometry": {"coordinates":[5.2653999329,50.5547523499],"type":"Point"}
}