{
  "type": "Feature",
  "properties": {
    "iso:country":"BE",
    "sg:address":"Rue Du Vicinal 18",
    "sg:city":"Fl\u00e9malle (mons-lez-li\u00e8ge)",
    "sg:classifiers":[
        {
            "category":"Shopping",
            "subcategory":"Computers & Home Electronics",
            "type":"Retail Goods"
        }
    ],
    "sg:phone":"+32 4 234 19 85",
    "sg:postcode":"4400",
    "sg:province":"Li\u00e8ge",
    "sg:tags":[
        "equipment",
        "-"
    ],
    "wof:name":"E R S D",
    "wof:placetype":"venue"
},
  "geometry": {"coordinates":[5.4539551735,50.6244812012],"type":"Point"}
}