{
  "type": "Feature",
  "properties": {
    "addr:full":"Leopoldlaan 147 Middelkerke West-Vlaanderen 8430",
    "addr:housenumber":"147",
    "addr:postcode":"8430",
    "addr:street":"Leopoldlaan",
    "iso:country":"BE",
    "sg:address":"Leopoldlaan 147",
    "sg:city":"Middelkerke",
    "sg:classifiers":[
        {
            "category":"Sports & Exercise",
            "subcategory":"Sports Center",
            "type":"Entertainment"
        }
    ],
    "sg:phone":"+32 59 30 02 03",
    "sg:postcode":"8430",
    "sg:province":"West-Vlaanderen",
    "sg:tags":[
        "installation",
        "sportifs",
        "de",
        "terrain",
        "hors",
        "caf\u00e9s"
    ],
    "wof:name":"Tennis-mini Golf",
    "wof:placetype":"venue"
},
  "geometry": {"coordinates":[2.8090560436,51.1849098206],"type":"Point"}
}