{
  "type": "Feature",
  "properties": {
    "addr:full":"Seringenstraat 10 Beerse Antwerpen 2340",
    "addr:housenumber":"10",
    "addr:postcode":"2340",
    "addr:street":"Seringenstraat",
    "iso:country":"BE",
    "sg:address":"Seringenstraat 10",
    "sg:city":"Beerse",
    "sg:classifiers":[
        {
            "category":"Banks & Credit Unions",
            "subcategory":"Investment Brokerage",
            "type":"Services"
        }
    ],
    "sg:phone":"+32 14 61 25 82",
    "sg:postcode":"2340",
    "sg:province":"Antwerpen",
    "sg:tags":[
        "repair",
        "-",
        "installation",
        "sanitary",
        "article"
    ],
    "wof:name":"S.i.s. Bvba",
    "wof:placetype":"venue"
},
  "geometry": {"coordinates":[4.8646059036,51.3238487244],"type":"Point"}
}