{
  "type": "Feature",
  "properties": {
    "addr:full":"Koetsstraat 11 Houthalen-helchteren Limburg 3530",
    "addr:housenumber":"11",
    "addr:postcode":"3530",
    "addr:street":"Koetsstraat",
    "iso:country":"BE",
    "sg:address":"Koetsstraat 11",
    "sg:city":"Houthalen-helchteren",
    "sg:orig_category":"Producteurs de fruits",
    "sg:phone":"+32 11 52 49 13",
    "sg:postcode":"3530",
    "sg:province":"Limburg",
    "wof:name":"Brigitte Corthouts",
    "wof:placetype":"venue"
},
  "geometry": {"coordinates":[5.3551898003,51.0232162476],"type":"Point"}
}