{
  "type": "Feature",
  "properties": {
    "iso:country":"BE",
    "sg:address":"Rue De Bonne Fortune 40",
    "sg:city":"Ath (irchonwelz)",
    "sg:classifiers":[
        {
            "category":"Landmark",
            "subcategory":"Tourist Attraction",
            "type":"Public Place"
        }
    ],
    "sg:phone":"+32 68 28 44 44",
    "sg:postcode":"7801",
    "sg:province":"Hainaut",
    "sg:tags":[
        "-",
        "tourism",
        "interest",
        "sight"
    ],
    "wof:name":"Sgr Hainaut",
    "wof:placetype":"venue"
},
  "geometry": {"coordinates":[3.7581949234,50.6183280945],"type":"Point"}
}