{
  "type": "Feature",
  "properties": {
    "iso:country":"BE",
    "sg:address":"Rue Alfred Defuisseaux 37",
    "sg:city":"Charleroi (marcinelle)",
    "sg:classifiers":[
        {
            "category":"Health Services",
            "subcategory":"Dentist",
            "type":"Services"
        }
    ],
    "sg:phone":"+32 71 36 92 11",
    "sg:postcode":"6001",
    "sg:province":"Hainaut",
    "wof:name":"Houillet J",
    "wof:placetype":"venue"
},
  "geometry": {"coordinates":[4.4310131073,50.4009094238],"type":"Point"}
}