{
  "type": "Feature",
  "properties": {
    "iso:country":"BE",
    "sg:address":"Valkenbergstraat 19",
    "sg:city":"Zutendaal",
    "sg:classifiers":[
        {
            "category":"Manufacturing",
            "subcategory":"Lumber",
            "type":"Manufacturing & Wholesale Goods"
        }
    ],
    "sg:phone":"+32 89 71 63 85",
    "sg:postcode":"3690",
    "sg:province":"Limburg",
    "sg:tags":[
        "timber"
    ],
    "wof:name":"Kimpen Houthandel",
    "wof:placetype":"venue"
},
  "geometry": {"coordinates":[5.602809906,50.9183883667],"type":"Point"}
}