{
  "type": "Feature",
  "properties": {
    "iso:country":"BE",
    "sg:address":"Ijzerenleen 27",
    "sg:city":"Mechelen",
    "sg:classifiers":[
        {
            "category":"Shopping",
            "subcategory":"Bridal",
            "type":"Retail Goods"
        }
    ],
    "sg:phone":"+32 15 20 44 52",
    "sg:postcode":"2800",
    "sg:province":"Antwerpen",
    "sg:tags":[
        "list",
        "-",
        "present",
        "wedding"
    ],
    "wof:name":"Denies",
    "wof:placetype":"venue"
},
  "geometry": {"coordinates":[4.511341095,51.0355033875],"type":"Point"}
}