{
  "type": "Feature",
  "properties": {
    "addr:full":"Grotedijk 7 Diksmuide West-Vlaanderen 8600",
    "addr:housenumber":"7",
    "addr:postcode":"8600",
    "addr:street":"Grotedijk",
    "iso:country":"BE",
    "sg:address":"Grotedijk 7",
    "sg:city":"Diksmuide",
    "sg:orig_category":"Dierenartsen",
    "sg:phone":"+32 51 50 01 15",
    "sg:postcode":"8600",
    "sg:province":"West-Vlaanderen",
    "wof:name":"Wim Vandenbussche",
    "wof:placetype":"venue"
},
  "geometry": {"coordinates":[2.8644850254,51.0358390808],"type":"Point"}
}