{
  "type": "Feature",
  "properties": {
    "iso:country":"BE",
    "sg:address":"Nieuwstraat 202",
    "sg:city":"Diepenbeek",
    "sg:classifiers":[
        {
            "category":"Professional",
            "subcategory":"Computer Services",
            "type":"Services"
        }
    ],
    "sg:phone":"+32 11 35 11 01",
    "sg:postcode":"3590",
    "sg:province":"Limburg",
    "sg:tags":[
        "network"
    ],
    "wof:name":"It & S",
    "wof:placetype":"venue"
},
  "geometry": {"coordinates":[5.4595060349,50.9278450012],"type":"Point"}
}