{
  "type": "Feature",
  "properties": {
    "addr:full":"Chauss\u00c9e De Jolimont 132 La Louviere Hainaut 7100",
    "addr:housenumber":"132",
    "addr:postcode":"7100",
    "addr:street":"Chausse\u0301E De Jolimont",
    "iso:country":"BE",
    "sg:address":"Chauss\u00c9e De Jolimont 132",
    "sg:city":"La Louviere",
    "sg:classifiers":[
        {
            "category":"Insurance",
            "subcategory":"Insurance Agent",
            "type":"Services"
        }
    ],
    "sg:phone":"+32 64 22 44 45",
    "sg:postcode":"7100",
    "sg:province":"Hainaut",
    "sg:tags":[
        "verzekeringsmakelaars",
        "expert"
    ],
    "wof:name":"Fiduc. Comm. & Juridique",
    "wof:placetype":"venue"
},
  "geometry": {"coordinates":[4.2180700302,50.4738082886],"type":"Point"}
}