{
  "type": "Feature",
  "properties": {
    "addr:full":"Thier Des Vignes 2ba Anthisnes Li\u00e8ge 4160",
    "addr:housenumber":"2ba",
    "addr:postcode":"4160",
    "addr:street":"Thier Des Vignes",
    "iso:country":"BE",
    "sg:address":"Thier Des Vignes 2ba",
    "sg:city":"Anthisnes",
    "sg:orig_category":"Traitements param\u00e9dicaux",
    "sg:phone":"+32 4 383 69 05",
    "sg:postcode":"4160",
    "sg:province":"Li\u00e8ge",
    "wof:name":"M. Bergers",
    "wof:placetype":"venue"
},
  "geometry": {"coordinates":[5.5239467621,50.4815292358],"type":"Point"}
}