{
  "type": "Feature",
  "properties": {
    "addr:full":"Hoogboomsteenweg 94 Box 1 Kapellen (mariaburg) Antwerpen 2950",
    "addr:housenumber":"94;1",
    "addr:postcode":"2950",
    "addr:street":"Hoogboomsteenweg;Box",
    "iso:country":"BE",
    "sg:address":"Hoogboomsteenweg 94 Box 1",
    "sg:city":"Kapellen (mariaburg)",
    "sg:classifiers":[
        {
            "category":"Real Estate",
            "subcategory":"Developer",
            "type":"Services"
        }
    ],
    "sg:phone":"+32 3 664 31 07",
    "sg:postcode":"2950",
    "sg:province":"Antwerpen",
    "sg:tags":[
        "project"
    ],
    "wof:name":"Ruys & Wildiers Nv",
    "wof:placetype":"venue"
},
  "geometry": {"coordinates":[4.4469342232,51.309879303],"type":"Point"}
}