{
  "type": "Feature",
  "properties": {
    "addr:full":"Haringgat 14 Damme West-Vlaanderen 8340",
    "addr:housenumber":"14",
    "addr:postcode":"8340",
    "addr:street":"Haringgat",
    "iso:country":"BE",
    "sg:address":"Haringgat 14",
    "sg:city":"Damme",
    "sg:orig_category":"Elektrische installaties voor woningen",
    "sg:phone":"+32 50 50 17 75",
    "sg:postcode":"8340",
    "sg:province":"West-Vlaanderen",
    "wof:name":"Peter Vercruysse",
    "wof:placetype":"venue"
},
  "geometry": {"coordinates":[3.3732950687,51.2663879395],"type":"Point"}
}