{
  "type": "Feature",
  "properties": {
    "iso:country":"BE",
    "sg:address":"Vianderstraat 35",
    "sg:city":"Tienen",
    "sg:classifiers":[
        {
            "category":"Real Estate",
            "subcategory":"Architect",
            "type":"Services"
        }
    ],
    "sg:phone":"+32 16 81 98 97",
    "sg:postcode":"3300",
    "sg:province":"Vlaams-Brabant",
    "wof:name":"Henderix V",
    "wof:placetype":"venue"
},
  "geometry": {"coordinates":[4.9451618195,50.8132019043],"type":"Point"}
}