{
  "type": "Feature",
  "properties": {
    "iso:country":"BE",
    "sg:address":"Rue Des Am\u00e9ricains 128",
    "sg:city":"Mons (hyon)",
    "sg:classifiers":[
        {
            "category":"Health Services",
            "subcategory":"Health Practitioner",
            "type":"Services"
        }
    ],
    "sg:phone":"+32 65 33 91 29",
    "sg:postcode":"7022",
    "sg:province":"Hainaut",
    "sg:tags":[
        "physiotherapist"
    ],
    "wof:name":"Staquet Anne",
    "wof:placetype":"venue"
},
  "geometry": {"coordinates":[3.9613599777,50.4351081848],"type":"Point"}
}