{
  "type": "Feature",
  "properties": {
    "addr:full":"Baron Van Eetveldeplein 3 Mol Antwerpen 2400",
    "addr:housenumber":"3",
    "addr:postcode":"2400",
    "addr:street":"Baron Van Eetveldeplein",
    "iso:country":"BE",
    "sg:address":"Baron Van Eetveldeplein 3",
    "sg:city":"Mol",
    "sg:classifiers":[
        {
            "category":"Bars & Pubs",
            "type":"Food & Drink"
        }
    ],
    "sg:phone":"+32 14 32 26 78",
    "sg:postcode":"2400",
    "sg:province":"Antwerpen",
    "sg:tags":[
        "tavern"
    ],
    "wof:name":"Gildenhuis",
    "wof:placetype":"venue"
},
  "geometry": {"coordinates":[5.118074894,51.1856155396],"type":"Point"}
}