{
  "type": "Feature",
  "properties": {
    "iso:country":"BE",
    "sg:address":"Kloosterstraat 108",
    "sg:city":"Antwerpen",
    "sg:classifiers":[
        {
            "category":"Cafe",
            "type":"Food & Drink"
        }
    ],
    "sg:phone":"+32 3 248 70 83",
    "sg:postcode":"2000",
    "sg:province":"Antwerpen",
    "sg:tags":[
        "caf\u00e9s"
    ],
    "wof:name":"Caf\u00c9 De Nieuwe Kroon",
    "wof:placetype":"venue"
},
  "geometry": {"coordinates":[4.3935689926,51.2141418457],"type":"Point"}
}