{
  "type": "Feature",
  "properties": {
    "addr:full":"Torhoutbaan 91 Ichtegem West-Vlaanderen 8480",
    "addr:housenumber":"91",
    "addr:postcode":"8480",
    "addr:street":"Torhoutbaan",
    "iso:country":"BE",
    "sg:address":"Torhoutbaan 91",
    "sg:city":"Ichtegem",
    "sg:orig_category":"Rundveehouders Varkenskwekers",
    "sg:phone":"+32 51 58 80 46",
    "sg:postcode":"8480",
    "sg:province":"West-Vlaanderen",
    "wof:name":"Daniel Inghelbrecht",
    "wof:placetype":"venue"
},
  "geometry": {"coordinates":[3.0425128937,51.0950660706],"type":"Point"}
}