{
  "type": "Feature",
  "properties": {
    "iso:country":"BE",
    "sg:address":"Vinkenstraat 130",
    "sg:city":"Boechout",
    "sg:orig_category":"Eleveurs de bovins",
    "sg:phone":"+32 3 454 04 38",
    "sg:postcode":"2530",
    "sg:province":"Antwerpen",
    "wof:name":"Henri Adams",
    "wof:placetype":"venue"
},
  "geometry": {"coordinates":[4.5212550163,51.1466293335],"type":"Point"}
}