{
  "type": "Feature",
  "properties": {
    "addr:full":"Chauss\u00c9e De Mons 1044 Anderlecht/anderlecht Bruxelles-Capitale 1070",
    "addr:postcode":"1044;1070",
    "addr:street":"Chausse\u0301E De Mons",
    "iso:country":"BE",
    "sg:address":"Chauss\u00c9e De Mons 1044",
    "sg:city":"Anderlecht/anderlecht",
    "sg:orig_category":"Electrom\u00e9nager, t\u00e9l\u00e9visions and radios",
    "sg:phone":"+32 2 527 11 22",
    "sg:postcode":"1070",
    "sg:province":"Bruxelles-Capitale",
    "wof:name":"T\u00c9lectro Vision",
    "wof:placetype":"venue"
},
  "geometry": {"coordinates":[4.2952508926,50.8228225708],"type":"Point"}
}