{
  "type": "Feature",
  "properties": {
    "iso:country":"BE",
    "sg:address":"Henegauwlaan 61",
    "sg:city":"Hasselt",
    "sg:classifiers":[
        {
            "category":"Health Services",
            "subcategory":"Doctor",
            "type":"Services"
        }
    ],
    "sg:phone":"+32 11 27 45 91",
    "sg:postcode":"3500",
    "sg:province":"Limburg",
    "sg:tags":[
        "medicinephysicians",
        "surgeon"
    ],
    "wof:name":"Coenegrachts J",
    "wof:placetype":"venue"
},
  "geometry": {"coordinates":[5.3359251022,50.9270362854],"type":"Point"}
}