{
  "type": "Feature",
  "properties": {
    "addr:full":"Rue Sans-souci 122 Ixelles Bruxelles-Capitale 1050",
    "addr:housenumber":"122",
    "addr:postcode":"1050",
    "addr:street":"Rue Sans-Souci",
    "iso:country":"BE",
    "sg:address":"Rue Sans-souci 122",
    "sg:city":"Ixelles",
    "sg:classifiers":[
        {
            "category":"Taxi",
            "type":"Transportation"
        }
    ],
    "sg:phone":"+32 2 461 02 99",
    "sg:postcode":"1050",
    "sg:province":"Bruxelles-Capitale",
    "sg:tags":[
        "sp\u00e9ciaux"
    ],
    "wof:name":"T.m.s. Limousine",
    "wof:placetype":"venue"
},
  "geometry": {"coordinates":[4.3727078438,50.8325576782],"type":"Point"}
}