{
  "type": "Feature",
  "properties": {
    "addr:full":"Lotstraat 2 Sint-pieters-leeuw Vlaams-Brabant 1600",
    "addr:housenumber":"2",
    "addr:postcode":"1600",
    "addr:street":"Lotstraat",
    "iso:country":"BE",
    "sg:address":"Lotstraat 2",
    "sg:city":"Sint-pieters-leeuw",
    "sg:classifiers":[
        {
            "category":"Arena",
            "subcategory":"Sports Club",
            "type":"Entertainment"
        }
    ],
    "sg:phone":"+32 2 377 46 45",
    "sg:postcode":"1600",
    "sg:province":"Vlaams-Brabant",
    "sg:tags":[
        "terrain",
        "hors",
        "de",
        "installation",
        "sportifs"
    ],
    "wof:name":"Sportkring Leeuw",
    "wof:placetype":"venue"
},
  "geometry": {"coordinates":[4.2547898293,50.7790489197],"type":"Point"}
}