{
  "type": "Feature",
  "properties": {
    "addr:full":"Basiliekstraat 107 Halle Vlaams-Brabant 1500",
    "addr:housenumber":"107",
    "addr:postcode":"1500",
    "addr:street":"Basiliekstraat",
    "iso:country":"BE",
    "sg:address":"Basiliekstraat 107",
    "sg:city":"Halle",
    "sg:orig_category":"Dameskledingzaken",
    "sg:phone":"+32 2 356 35 75",
    "sg:postcode":"1500",
    "sg:province":"Vlaams-Brabant",
    "wof:name":"Huis Silks",
    "wof:placetype":"venue"
},
  "geometry": {"coordinates":[4.236451149,50.733669281],"type":"Point"}
}