{
  "type": "Feature",
  "properties": {
    "addr:full":"Rue Paul Emile Janson 17 Elsene/ixelles Bruxelles-Capitale 1050",
    "addr:housenumber":"17",
    "addr:postcode":"1050",
    "addr:street":"Rue Paul Emile Janson",
    "iso:country":"BE",
    "sg:address":"Rue Paul Emile Janson 17",
    "sg:city":"Elsene/ixelles",
    "sg:orig_category":"M\u00e9decins and sp\u00e9cialistes",
    "sg:phone":"+32 2 537 77 09",
    "sg:postcode":"1050",
    "sg:province":"Bruxelles-Capitale",
    "wof:name":"Christiane Mommaerts",
    "wof:placetype":"venue"
},
  "geometry": {"coordinates":[4.3605399132,50.8275413513],"type":"Point"}
}