{
  "type": "Feature",
  "properties": {
    "iso:country":"BE",
    "sg:address":"Tervuursesteenweg 535",
    "sg:city":"Zemst (elewijt)",
    "sg:classifiers":[
        {
            "category":"Bars & Pubs",
            "type":"Food & Drink"
        }
    ],
    "sg:phone":"+32 15 62 02 37",
    "sg:postcode":"1982",
    "sg:province":"Vlaams-Brabant",
    "wof:name":"Belved\u00e8re",
    "wof:placetype":"venue"
},
  "geometry": {"coordinates":[4.4965147972,50.9675865173],"type":"Point"}
}