{
  "type": "Feature",
  "properties": {
    "iso:country":"BE",
    "sg:address":"Roeselaarsestraat 414",
    "sg:city":"Izegem",
    "sg:orig_category":"Kansspelen",
    "sg:phone":"+32 51 30 16 11",
    "sg:postcode":"8870",
    "sg:province":"West-Vlaanderen",
    "wof:name":"Belgische P M U S V",
    "wof:placetype":"venue"
},
  "geometry": {"coordinates":[3.1947410107,50.923160553],"type":"Point"}
}