{
  "type": "Feature",
  "properties": {
    "iso:country":"BE",
    "sg:address":"Wallenstraat 33",
    "sg:city":"Roeselare",
    "sg:orig_category":"Opticiens",
    "sg:phone":"+32 51 24 10 43",
    "sg:postcode":"8800",
    "sg:province":"West-Vlaanderen",
    "wof:name":"Huis Patsy",
    "wof:placetype":"venue"
},
  "geometry": {"coordinates":[3.1209828854,50.9446868896],"type":"Point"}
}