{
  "type": "Feature",
  "properties": {
    "iso:country":"BE",
    "sg:address":"Rue De La Franco-belge 28",
    "sg:city":"La Louviere",
    "sg:classifiers":[
        {
            "category":"Cafe",
            "type":"Food & Drink"
        }
    ],
    "sg:phone":"+32 64 22 94 80",
    "sg:postcode":"7100",
    "sg:province":"Hainaut",
    "sg:tags":[
        "caf\u00e9s"
    ],
    "wof:name":"La Porte Du Prince",
    "wof:placetype":"venue"
},
  "geometry": {"coordinates":[4.206633091,50.4872627258],"type":"Point"}
}