{
  "type": "Feature",
  "properties": {
    "iso:country":"BE",
    "sg:address":"Ruitjesbosstraat 12",
    "sg:city":"Torhout",
    "sg:orig_category":"Eleveurs and marchands de porcs. Eleveurs de bovins",
    "sg:phone":"+32 50 21 17 70",
    "sg:postcode":"8820",
    "sg:province":"West-Vlaanderen",
    "wof:name":"Camiel Demeulenaere",
    "wof:placetype":"venue"
},
  "geometry": {"coordinates":[3.1345829964,51.0754394531],"type":"Point"}
}