{
  "type": "Feature",
  "properties": {
    "addr:full":"Chemin De La Procession 5 Lens Hainaut 7870",
    "addr:housenumber":"5",
    "addr:postcode":"7870",
    "addr:street":"Chemin De La Procession",
    "iso:country":"BE",
    "sg:address":"Chemin De La Procession 5",
    "sg:city":"Lens",
    "sg:orig_category":"HERSTELLING ELEKTRISCHE HUISHOUDAPPARATEN Kantoormateriaal Gh Telecommunicatieapparaten",
    "sg:phone":"+32 68 45 46 10",
    "sg:postcode":"7870",
    "sg:province":"Hainaut",
    "wof:name":"Potenza",
    "wof:placetype":"venue"
},
  "geometry": {"coordinates":[3.9001870155,50.5572738647],"type":"Point"}
}