{
  "type": "Feature",
  "properties": {
    "addr:full":"Rue Haute 2 Vise Li\u00e8ge 4600",
    "addr:housenumber":"2",
    "addr:postcode":"4600",
    "addr:street":"Rue Haute",
    "iso:country":"BE",
    "sg:address":"Rue Haute 2",
    "sg:city":"Vise",
    "sg:orig_category":"Chaussures",
    "sg:phone":"+32 4 379 75 99",
    "sg:postcode":"4600",
    "sg:province":"Li\u00e8ge",
    "wof:name":"Avance",
    "wof:placetype":"venue"
},
  "geometry": {"coordinates":[5.6950011253,50.7350463867],"type":"Point"}
}