{
  "type": "Feature",
  "properties": {
    "iso:country":"BE",
    "sg:address":"Rue Des Sabli\u00c8res 64",
    "sg:city":"Chatelet",
    "sg:orig_category":"Kapsalons",
    "sg:phone":"+32 71 38 61 91",
    "sg:postcode":"6200",
    "sg:province":"Hainaut",
    "wof:name":"Carole Urdaneta",
    "wof:placetype":"venue"
},
  "geometry": {"coordinates":[4.5313949585,50.39868927],"type":"Point"}
}