{
  "type": "Feature",
  "properties": {
    "addr:full":"Rue Du Progr\u00e8s 30 Bertrix Luxembourg 6880",
    "addr:housenumber":"30",
    "addr:postcode":"6880",
    "addr:street":"Rue Du Progre\u0300S",
    "iso:country":"BE",
    "sg:address":"Rue Du Progr\u00e8s 30",
    "sg:city":"Bertrix",
    "sg:classifiers":[
        {
            "category":"Arts & Performance",
            "subcategory":"Music",
            "type":"Entertainment"
        }
    ],
    "sg:phone":"+32 61 41 32 84",
    "sg:postcode":"6880",
    "sg:province":"Luxembourg",
    "sg:tags":[
        "disc-jockeys"
    ],
    "wof:name":"Sono Cibernight",
    "wof:placetype":"venue"
},
  "geometry": {"coordinates":[5.2703471184,49.8574142456],"type":"Point"}
}