{
  "type": "Feature",
  "properties": {
    "iso:country":"BE",
    "sg:address":"Wielewaalstraat 58",
    "sg:city":"Ieper",
    "sg:orig_category":"Installation de menuiserie en bois and plastique",
    "sg:phone":"+32 57 20 81 73",
    "sg:postcode":"8902",
    "sg:province":"West-Vlaanderen",
    "wof:name":"Pecceu",
    "wof:placetype":"venue"
},
  "geometry": {"coordinates":[2.9296998978,50.809967041],"type":"Point"}
}