{
  "type": "Feature",
  "properties": {
    "addr:full":"Groenstraat 43 Lint Antwerpen 2547",
    "addr:housenumber":"43",
    "addr:postcode":"2547",
    "addr:street":"Groenstraat",
    "iso:country":"BE",
    "sg:address":"Groenstraat 43",
    "sg:city":"Lint",
    "sg:orig_category":"Radioproductie and uitzendingen",
    "sg:phone":"+32 3 455 46 67",
    "sg:postcode":"2547",
    "sg:province":"Antwerpen",
    "wof:name":"Lobbes",
    "wof:placetype":"venue"
},
  "geometry": {"coordinates":[4.4819469452,51.1337738037],"type":"Point"}
}