{
  "type": "Feature",
  "properties": {
    "iso:country":"BE",
    "sg:address":"Revinzestraat 94",
    "sg:city":"Torhout",
    "sg:orig_category":"Travaux de pl\u00e2trage. Installation de menuiserie m\u00e9tallique",
    "sg:phone":"+32 50 21 40 31",
    "sg:postcode":"8820",
    "sg:province":"West-Vlaanderen",
    "wof:name":"Plakwerken E Tas",
    "wof:placetype":"venue"
},
  "geometry": {"coordinates":[3.079408884,51.0659141541],"type":"Point"}
}