{
  "type": "Feature",
  "properties": {
    "iso:country":"BE",
    "sg:address":"Tiensesteenweg 59",
    "sg:city":"Leuven (groot)",
    "sg:orig_category":"Verbruikerskredietinstellingen",
    "sg:phone":"+32 16 29 81 91",
    "sg:postcode":"3000",
    "sg:province":"Vlaams-Brabant",
    "wof:name":"Krefibel",
    "wof:placetype":"venue"
},
  "geometry": {"coordinates":[4.7050571442,50.8772163391],"type":"Point"}
}