{
  "type": "Feature",
  "properties": {
    "addr:full":"Breeweg 42 Oostkamp West-Vlaanderen 8020",
    "addr:housenumber":"42",
    "addr:postcode":"8020",
    "addr:street":"Breeweg",
    "iso:country":"BE",
    "sg:address":"Breeweg 42",
    "sg:city":"Oostkamp",
    "sg:orig_category":"Varkenskwekers",
    "sg:phone":"+32 50 27 74 53",
    "sg:postcode":"8020",
    "sg:province":"West-Vlaanderen",
    "wof:name":"Andreas Maertens",
    "wof:placetype":"venue"
},
  "geometry": {"coordinates":[3.2614300251,51.1152992249],"type":"Point"}
}