{
  "type": "Feature",
  "properties": {
    "iso:country":"BE",
    "sg:address":"Halfstraat 80",
    "sg:city":"Schelle",
    "sg:classifiers":[
        {
            "category":"Education",
            "subcategory":"Dance Studio",
            "type":"Public Place"
        }
    ],
    "sg:phone":"+32 3 877 60 35",
    "sg:postcode":"2627",
    "sg:province":"Antwerpen",
    "sg:tags":[
        "school",
        "dancing"
    ],
    "wof:name":"Dansstudio Ijvi Hagelstein",
    "wof:placetype":"venue"
},
  "geometry": {"coordinates":[4.3765802383,51.1169815063],"type":"Point"}
}