{
  "type": "Feature",
  "properties": {
    "addr:full":"Mayerlei 2 Mortsel Antwerpen 2640",
    "addr:housenumber":"2",
    "addr:postcode":"2640",
    "addr:street":"Mayerlei",
    "iso:country":"BE",
    "sg:address":"Mayerlei 2",
    "sg:city":"Mortsel",
    "sg:classifiers":[
        {
            "category":"Professional",
            "subcategory":"Management & Consulting",
            "type":"Services"
        }
    ],
    "sg:phone":"+32 3 454 56 98",
    "sg:postcode":"2640",
    "sg:province":"Antwerpen",
    "sg:tags":[
        "-",
        "processing",
        "data",
        "consultant"
    ],
    "wof:name":"Urveda Bvba",
    "wof:placetype":"venue"
},
  "geometry": {"coordinates":[4.4732470512,51.1625137329],"type":"Point"}
}