{
  "type": "Feature",
  "properties": {
    "addr:full":". Montigny-le-tilleul (groot) Hainaut 6110",
    "addr:postcode":"6110",
    "addr:street":"Groot Hainaut",
    "iso:country":"BE",
    "sg:address":".",
    "sg:city":"Montigny-le-tilleul (groot)",
    "sg:orig_category":"Apotheken",
    "sg:phone":"+32 900 10 500",
    "sg:postcode":"6110",
    "sg:province":"Hainaut",
    "wof:name":"Apothekers Van Wacht",
    "wof:placetype":"venue"
},
  "geometry": {"coordinates":[4.3799991608,50.3796157837],"type":"Point"}
}