{
  "type": "Feature",
  "properties": {
    "addr:full":"Winderickxplein 22 Beersel Vlaams-Brabant 1652",
    "addr:housenumber":"22",
    "addr:postcode":"1652",
    "addr:street":"Winderickxplein",
    "iso:country":"BE",
    "sg:address":"Winderickxplein 22",
    "sg:city":"Beersel",
    "sg:orig_category":"Advocaten and juridische adviseurs",
    "sg:phone":"+32 2 380 21 03",
    "sg:postcode":"1652",
    "sg:province":"Vlaams-Brabant",
    "wof:name":"M. Van Hemelryck",
    "wof:placetype":"venue"
},
  "geometry": {"coordinates":[4.3379058838,50.7413406372],"type":"Point"}
}