{
  "type": "Feature",
  "properties": {
    "addr:full":"Rue De Philippeville 115 Ham-sur-heure-nalinnes (nalinnes) Hainaut 6120",
    "addr:housenumber":"115",
    "addr:postcode":"6120",
    "addr:street":"Rue De Philippeville;Hainaut",
    "iso:country":"BE",
    "sg:address":"Rue De Philippeville 115",
    "sg:city":"Ham-sur-heure-nalinnes (nalinnes)",
    "sg:classifiers":[
        {
            "category":"Retail",
            "subcategory":"Auto Repair",
            "type":"Services"
        }
    ],
    "sg:phone":"+32 71 21 34 20",
    "sg:postcode":"6120",
    "sg:province":"Hainaut",
    "sg:tags":[
        "garage"
    ],
    "wof:name":"Rg Sprl",
    "wof:placetype":"venue"
},
  "geometry": {"coordinates":[4.4752340317,50.3341369629],"type":"Point"}
}