{
  "type": "Feature",
  "properties": {
    "addr:full":"Rodeheide 7 Tessenderlo Limburg 3980",
    "addr:housenumber":"7",
    "addr:postcode":"3980",
    "addr:street":"Rodeheide",
    "iso:country":"BE",
    "sg:address":"Rodeheide 7",
    "sg:city":"Tessenderlo",
    "sg:classifiers":[
        {
            "category":"Fast Food",
            "type":"Food & Drink"
        }
    ],
    "sg:phone":"+32 13 67 34 84",
    "sg:postcode":"3980",
    "sg:province":"Limburg",
    "sg:tags":[
        "\u00c0",
        "emporter",
        "restaurants"
    ],
    "wof:name":"De Looise Snackcar",
    "wof:placetype":"venue"
},
  "geometry": {"coordinates":[5.0906300545,51.0696601868],"type":"Point"}
}