{
  "type": "Feature",
  "properties": {
    "addr:full":"Ameiveld 102 Ninove Oost-Vlaanderen 9400",
    "addr:housenumber":"102",
    "addr:postcode":"9400",
    "iso:country":"BE",
    "sg:address":"Ameiveld 102",
    "sg:city":"Ninove",
    "sg:classifiers":[
        {
            "category":"Health Services",
            "subcategory":"Health Practitioner",
            "type":"Services"
        }
    ],
    "sg:phone":"+32 54 32 06 17",
    "sg:postcode":"9400",
    "sg:province":"Oost-Vlaanderen",
    "sg:tags":[
        "physiotherapist"
    ],
    "wof:name":"Van Den Steen Patricia",
    "wof:placetype":"venue"
},
  "geometry": {"coordinates":[4.0122041702,50.834274292],"type":"Point"}
}