{
  "type": "Feature",
  "properties": {
    "iso:country":"BE",
    "sg:address":"Rue Defnet 19",
    "sg:city":"Andenne",
    "sg:orig_category":"Editeurs de revues and p\u00e9riodiques. Imprimeries and copyshops. Editeurs de journaux. Agences de publ",
    "sg:phone":"+32 85 84 12 94",
    "sg:postcode":"5300",
    "sg:province":"Namur",
    "wof:name":"Imprimerie Lallemend",
    "wof:placetype":"venue"
},
  "geometry": {"coordinates":[5.0966739655,50.4873657227],"type":"Point"}
}