{
  "type": "Feature",
  "properties": {
    "addr:full":"Kuurnsesteenweg 46 Kortrijk West-Vlaanderen 8500",
    "addr:housenumber":"46",
    "addr:postcode":"8500",
    "addr:street":"Kuurnsesteenweg",
    "iso:country":"BE",
    "sg:address":"Kuurnsesteenweg 46",
    "sg:city":"Kortrijk",
    "sg:orig_category":"Elektrische installaties voor woningen Industri\u00eble elektrische installaties",
    "sg:phone":"+32 56 32 06 30",
    "sg:postcode":"8500",
    "sg:province":"West-Vlaanderen",
    "wof:name":"Elektro Vandoorne Ockier",
    "wof:placetype":"venue"
},
  "geometry": {"coordinates":[3.2663431168,50.8401870728],"type":"Point"}
}