{
  "type": "Feature",
  "properties": {
    "iso:country":"BE",
    "sg:address":"Nieuwenhovenstraat 8ba",
    "sg:city":"Beernem",
    "sg:orig_category":"Eleveurs and marchands de porcs. Eleveurs de bovins",
    "sg:phone":"+32 50 78 90 21",
    "sg:postcode":"8730",
    "sg:province":"West-Vlaanderen",
    "wof:name":"Sylveer Deschepper",
    "wof:placetype":"venue"
},
  "geometry": {"coordinates":[3.3965559006,51.1506195068],"type":"Point"}
}