{
  "type": "Feature",
  "properties": {
    "addr:full":"Jan Baptist Denayerstr. 24 Hoeilaart Vlaams-Brabant 1560",
    "addr:housenumber":"24",
    "addr:postcode":"1560",
    "addr:street":"Jan Baptist Denayerstr.",
    "iso:country":"BE",
    "sg:address":"Jan Baptist Denayerstr. 24",
    "sg:city":"Hoeilaart",
    "sg:orig_category":"Marktonderzoekbureaus",
    "sg:phone":"+32 2 657 61 26",
    "sg:postcode":"1560",
    "sg:province":"Vlaams-Brabant",
    "wof:name":"Irfab Chemical Consult.",
    "wof:placetype":"venue"
},
  "geometry": {"coordinates":[4.4797201157,50.7615127563],"type":"Point"}
}