{
  "type": "Feature",
  "properties": {
    "addr:full":"Dorpstraat 508 Bertem Vlaams-Brabant 3061",
    "addr:housenumber":"508",
    "addr:postcode":"3061",
    "addr:street":"Dorpstraat",
    "iso:country":"BE",
    "sg:address":"Dorpstraat 508",
    "sg:city":"Bertem",
    "sg:orig_category":"Imprimeries and copyshops",
    "sg:phone":"+32 2 767 01 94",
    "sg:postcode":"3061",
    "sg:province":"Vlaams-Brabant",
    "wof:name":"Roekens",
    "wof:placetype":"venue"
},
  "geometry": {"coordinates":[4.5920171738,50.848110199],"type":"Point"}
}