{
  "type": "Feature",
  "properties": {
    "iso:country":"BE",
    "sg:address":"Weg Naar Opoeteren 192",
    "sg:city":"Opglabbeek",
    "sg:classifiers":[
        {
            "category":"Bars & Pubs",
            "type":"Food & Drink"
        }
    ],
    "sg:phone":"+32 89 38 12 91",
    "sg:postcode":"3660",
    "sg:province":"Limburg",
    "wof:name":"De Sting",
    "wof:placetype":"venue"
},
  "geometry": {"coordinates":[5.6277961731,51.0567817688],"type":"Point"}
}