{
  "type": "Feature",
  "properties": {
    "addr:full":"19 Tienne-aux-balouches 5002 St Servais 19",
    "addr:housenumber":"19;19",
    "addr:postcode":"5002 st",
    "addr:street":"Tienne-Aux-Balouches",
    "iso:country":"BE",
    "sg:address":"19",
    "sg:city":"Tienne-aux-balouches 5002 St Servais",
    "sg:classifiers":[
        {
            "category":"Utilities",
            "subcategory":"Natural Gas",
            "type":"Services"
        }
    ],
    "sg:phone":"+32 81 73 15 39",
    "sg:postcode":"19",
    "sg:tags":[
        "good",
        "electricity",
        "energy",
        "material",
        "-",
        "metalworking",
        "metallic",
        "metallurgy",
        "raw",
        "finished"
    ],
    "wof:name":"Fabrication Tolerie Electrique Sa",
    "wof:placetype":"venue"
},
  "geometry": {"coordinates":[4.8609719276,50.4755172729],"type":"Point"}
}