{
  "type": "Feature",
  "properties": {
    "addr:full":"Mulk 158 Hamont-achel Limburg 3930",
    "addr:housenumber":"158",
    "addr:postcode":"3930",
    "addr:street":"Mulk",
    "iso:country":"BE",
    "sg:address":"Mulk 158",
    "sg:city":"Hamont-achel",
    "sg:orig_category":"Fabrication and montage de mobilier. Installation de menuiserie en bois and plastique",
    "sg:phone":"+32 11 44 60 85",
    "sg:postcode":"3930",
    "sg:province":"Limburg",
    "wof:name":"Marc Huibers",
    "wof:placetype":"venue"
},
  "geometry": {"coordinates":[5.5450549126,51.2511863708],"type":"Point"}
}