{
  "type": "Feature",
  "properties": {
    "iso:country":"BE",
    "sg:address":"Chauss\u00e9e D'ecaussinnes 110",
    "sg:city":"Braine-le-comte",
    "sg:classifiers":[
        {
            "category":"Autos & Motor Vehicles",
            "subcategory":"Motorcycle Sales",
            "type":"Retail Goods"
        }
    ],
    "sg:phone":"+32 67 56 08 48",
    "sg:postcode":"7090",
    "sg:province":"Hainaut",
    "sg:tags":[
        "motorbike"
    ],
    "wof:name":"Vlassenbroeck Motorcycles",
    "wof:placetype":"venue"
},
  "geometry": {"coordinates":[4.1319389343,50.6006240845],"type":"Point"}
}