{
  "type": "Feature",
  "properties": {
    "addr:full":"Derbystraat 345 Gent (sint-denijs-westrem - Afsnee) Oost-Vlaanderen 9051",
    "addr:housenumber":"345",
    "addr:postcode":"9051",
    "addr:street":"Derbystraat;Oost-Vlaanderen",
    "iso:country":"BE",
    "sg:address":"Derbystraat 345",
    "sg:city":"Gent (sint-denijs-westrem - Afsnee)",
    "sg:classifiers":[
        {
            "category":"Social Services",
            "subcategory":"Job Training",
            "type":"Services"
        }
    ],
    "sg:phone":"+32 9 242 99 88",
    "sg:postcode":"9051",
    "sg:province":"Oost-Vlaanderen",
    "sg:tags":[
        "coordinator",
        "safety"
    ],
    "wof:name":"B T I",
    "wof:placetype":"venue"
},
  "geometry": {"coordinates":[3.6967110634,51.0234603882],"type":"Point"}
}