{
  "type": "Feature",
  "properties": {
    "addr:full":"Duisburgsesteenweg 198 Overijse Vlaams-Brabant 3090",
    "addr:housenumber":"198",
    "addr:postcode":"3090",
    "addr:street":"Duisburgsesteenweg",
    "iso:country":"BE",
    "sg:address":"Duisburgsesteenweg 198",
    "sg:city":"Overijse",
    "sg:orig_category":"Avocats and conseillers juridiques",
    "sg:phone":"+32 2 688 24 20",
    "sg:postcode":"3090",
    "sg:province":"Vlaams-Brabant",
    "wof:name":"B. Verlooy",
    "wof:placetype":"venue"
},
  "geometry": {"coordinates":[4.5510168076,50.8007125854],"type":"Point"}
}