{
  "type": "Feature",
  "properties": {
    "iso:country":"BE",
    "sg:address":"Avenue De Bouillon 103",
    "sg:city":"Libramont-chevigny",
    "sg:orig_category":"Experts-comptables. Conseillers fiscaux. Assistances juridiques",
    "sg:phone":"+32 61 22 37 54",
    "sg:postcode":"6800",
    "sg:province":"Luxembourg",
    "wof:name":"J.p. Frognet",
    "wof:placetype":"venue"
},
  "geometry": {"coordinates":[5.3601098061,49.914478302],"type":"Point"}
}