{
  "type": "Feature",
  "properties": {
    "iso:country":"BE",
    "sg:address":"Lindelei 219",
    "sg:city":"Hemiksem",
    "sg:classifiers":[
        {
            "category":"Health Services",
            "subcategory":"Health Practitioner",
            "type":"Services"
        }
    ],
    "sg:phone":"+32 3 887 52 42",
    "sg:postcode":"2620",
    "sg:province":"Antwerpen",
    "sg:tags":[
        "physiotherapist"
    ],
    "wof:name":"Vermijlen J",
    "wof:placetype":"venue"
},
  "geometry": {"coordinates":[4.3449068069,51.1451644897],"type":"Point"}
}