{
  "type": "Feature",
  "properties": {
    "iso:country":"BE",
    "sg:address":"Schipperstraat 8",
    "sg:city":"Beernem (oedelem)",
    "sg:classifiers":[
        {
            "category":"Farming",
            "subcategory":"Livestock Farm",
            "type":"Manufacturing & Wholesale Goods"
        }
    ],
    "sg:phone":"+32 50 78 03 17",
    "sg:postcode":"8730",
    "sg:province":"West-Vlaanderen",
    "sg:tags":[
        "buyer"
    ],
    "wof:name":"Wittevrongel G",
    "wof:placetype":"venue"
},
  "geometry": {"coordinates":[3.3688080311,51.1519622803],"type":"Point"}
}