{
  "type": "Feature",
  "properties": {
    "iso:country":"BE",
    "sg:address":"Oeverstraat 81",
    "sg:city":"Temse",
    "sg:orig_category":"Non-Classified Establishments",
    "sg:phone":"+32 3 771 56 80",
    "sg:postcode":"9140",
    "sg:province":"Oost-Vlaanderen",
    "wof:name":"Belpaire-atlas",
    "wof:placetype":"venue"
},
  "geometry": {"coordinates":[4.2084908485,51.1258392334],"type":"Point"}
}