{
  "type": "Feature",
  "properties": {
    "addr:full":"Rue Grande 86 Quevy Hainaut 7040",
    "addr:housenumber":"86",
    "addr:postcode":"7040",
    "addr:street":"Rue Grande;Hainaut",
    "iso:country":"BE",
    "sg:address":"Rue Grande 86",
    "sg:city":"Quevy",
    "sg:orig_category":"Woningbouw",
    "sg:phone":"+32 65 56 70 81",
    "sg:postcode":"7040",
    "sg:province":"Hainaut",
    "wof:name":"Fe. Derudder",
    "wof:placetype":"venue"
},
  "geometry": {"coordinates":[3.9095098972,50.3884086609],"type":"Point"}
}