{
  "type": "Feature",
  "properties": {
    "addr:full":"Zuidmoerstraat 160 Eeklo Oost-Vlaanderen 9900",
    "addr:housenumber":"160",
    "addr:postcode":"9900",
    "addr:street":"Zuidmoerstraat",
    "iso:country":"BE",
    "sg:address":"Zuidmoerstraat 160",
    "sg:city":"Eeklo",
    "sg:orig_category":"Herstelling leer and schoeisel Schoenen",
    "sg:phone":"+32 9 377 17 40",
    "sg:postcode":"9900",
    "sg:province":"Oost-Vlaanderen",
    "wof:name":"Joannes Piepers",
    "wof:placetype":"venue"
},
  "geometry": {"coordinates":[3.5645298958,51.1821289062],"type":"Point"}
}