{
  "type": "Feature",
  "properties": {
    "addr:full":"Rue Du Fond Agny 13 Lasne (couture-saint-germain) Brabant Wallon 1380",
    "addr:housenumber":"13",
    "addr:postcode":"1380",
    "addr:street":"Rue Du Fond Agny;Wallon",
    "iso:country":"BE",
    "sg:address":"Rue Du Fond Agny 13",
    "sg:city":"Lasne (couture-saint-germain)",
    "sg:classifiers":[
        {
            "category":"Professional",
            "subcategory":"Accounting & Tax Preparation",
            "type":"Services"
        }
    ],
    "sg:phone":"+32 2 633 52 71",
    "sg:postcode":"1380",
    "sg:province":"Brabant Wallon",
    "sg:tags":[
        "bookkeeper"
    ],
    "wof:name":"Exfinco Sprl",
    "wof:placetype":"venue"
},
  "geometry": {"coordinates":[4.4854068756,50.65599823],"type":"Point"}
}