{
  "type": "Feature",
  "properties": {
    "addr:full":"Chemin Wellington 12 Nivelles Brabant Wallon 1400",
    "addr:housenumber":"12",
    "addr:postcode":"1400",
    "addr:street":"Chemin Wellington",
    "iso:country":"BE",
    "sg:address":"Chemin Wellington 12",
    "sg:city":"Nivelles",
    "sg:orig_category":"Rundveehouders",
    "sg:phone":"+32 67 87 90 86",
    "sg:postcode":"1400",
    "sg:province":"Brabant Wallon",
    "wof:name":"Depaepe G. & Courtain F.",
    "wof:placetype":"venue"
},
  "geometry": {"coordinates":[4.354142189,50.5651435852],"type":"Point"}
}