{
  "type": "Feature",
  "properties": {
    "iso:country":"BE",
    "sg:address":"Rue De Glaireuse 117",
    "sg:city":"Libin",
    "sg:orig_category":"Installation de menuiserie en bois and plastique",
    "sg:phone":"+32 61 65 53 01",
    "sg:postcode":"6890",
    "sg:province":"Luxembourg",
    "wof:name":"Jean-pierre Lambin",
    "wof:placetype":"venue"
},
  "geometry": {"coordinates":[5.2572650909,49.9713973999],"type":"Point"}
}