{
  "type": "Feature",
  "properties": {
    "addr:full":"Breedpadstraat 39 Heers Limburg 3870",
    "addr:housenumber":"39",
    "addr:postcode":"3870",
    "addr:street":"Breedpadstraat",
    "iso:country":"BE",
    "sg:address":"Breedpadstraat 39",
    "sg:city":"Heers",
    "sg:orig_category":"Producteurs de fruits",
    "sg:phone":"+32 11 48 43 84",
    "sg:postcode":"3870",
    "sg:province":"Limburg",
    "wof:name":"Alphonse Gielen",
    "wof:placetype":"venue"
},
  "geometry": {"coordinates":[5.2508721352,50.7269363403],"type":"Point"}
}