{
  "type": "Feature",
  "properties": {
    "iso:country":"BE",
    "sg:address":"Rue Saint-michel 21",
    "sg:city":"Brussel/bruxelles",
    "sg:orig_category":"RESTAURANTS: CAF\u00c9S",
    "sg:phone":"+32 2 217 38 14",
    "sg:postcode":"1000",
    "sg:province":"Bruxelles-Capitale",
    "wof:name":"Taverne St.michel",
    "wof:placetype":"venue"
},
  "geometry": {"coordinates":[4.354888916,50.8522148132],"type":"Point"}
}