{
  "type": "Feature",
  "properties": {
    "addr:full":"Kouter 341 Oudergem/auderghem Bruxelles-Capitale 1160",
    "addr:housenumber":"341",
    "addr:postcode":"1160",
    "addr:street":"Kouter;/",
    "iso:country":"BE",
    "sg:address":"Kouter 341",
    "sg:city":"Oudergem/auderghem",
    "sg:orig_category":"Fotografen and fotostudio's",
    "sg:phone":"+32 2 660 79 89",
    "sg:postcode":"1160",
    "sg:province":"Bruxelles-Capitale",
    "wof:name":"Guy Delepee",
    "wof:placetype":"venue"
},
  "geometry": {"coordinates":[4.4159851074,50.8202781677],"type":"Point"}
}