{
  "type": "Feature",
  "properties": {
    "addr:full":"Rue Du Bourdon 4 Profondeville Namur 5170",
    "addr:housenumber":"4",
    "addr:postcode":"5170",
    "addr:street":"Rue Du Bourdon",
    "iso:country":"BE",
    "sg:address":"Rue Du Bourdon 4",
    "sg:city":"Profondeville",
    "sg:orig_category":"Bloemen and planten Bloemen and planten Gh",
    "sg:phone":"+32 81 43 44 83",
    "sg:postcode":"5170",
    "sg:province":"Namur",
    "wof:name":"Au Jardin Fleuri",
    "wof:placetype":"venue"
},
  "geometry": {"coordinates":[4.8674049377,50.3786392212],"type":"Point"}
}