{
  "type": "Feature",
  "properties": {
    "iso:country":"BE",
    "sg:address":"Stanleystraat 64",
    "sg:city":"Ukkel/uccle",
    "sg:orig_category":"Landmeters",
    "sg:phone":"+32 2 345 31 64",
    "sg:postcode":"1180",
    "sg:province":"Bruxelles-Capitale",
    "wof:name":"Paul Berge",
    "wof:placetype":"venue"
},
  "geometry": {"coordinates":[4.3652410507,50.8153381348],"type":"Point"}
}