{
  "type": "Feature",
  "properties": {
    "iso:country":"BE",
    "sg:address":"L\u00c9on Theodorstraat 250",
    "sg:city":"Jette/jette",
    "sg:orig_category":"Verplichte sociale verzekeringen",
    "sg:phone":"+32 2 427 96 06",
    "sg:postcode":"1090",
    "sg:province":"Bruxelles-Capitale",
    "wof:name":"Mutualit\u00c9 Socialiste",
    "wof:placetype":"venue"
},
  "geometry": {"coordinates":[4.3293361664,50.8798370361],"type":"Point"}
}