{
  "type": "Feature",
  "properties": {
    "iso:country":"BE",
    "sg:address":"Statiestraat 8",
    "sg:city":"Aalst (moorsel)",
    "sg:classifiers":[
        {
            "category":"Health Services",
            "subcategory":"Dentist",
            "type":"Services"
        }
    ],
    "sg:phone":"+32 53 21 12 60",
    "sg:postcode":"9310",
    "sg:province":"Oost-Vlaanderen",
    "wof:name":"De Mey Betty",
    "wof:placetype":"venue"
},
  "geometry": {"coordinates":[4.0384712219,50.9428024292],"type":"Point"}
}