{
  "type": "Feature",
  "properties": {
    "iso:country":"BE",
    "sg:address":"Bruul 115",
    "sg:city":"Mechelen",
    "sg:orig_category":"Pain, p\u00e2tisseries and confiseries",
    "sg:phone":"+32 15 29 05 75",
    "sg:postcode":"2800",
    "sg:province":"Antwerpen",
    "wof:name":"Huis Devina",
    "wof:placetype":"venue"
},
  "geometry": {"coordinates":[4.4821610451,51.0237998962],"type":"Point"}
}