{
  "type": "Feature",
  "properties": {
    "addr:full":"Leemstraat 63 Lochristi Oost-Vlaanderen 9080",
    "addr:housenumber":"63",
    "addr:postcode":"9080",
    "addr:street":"Leemstraat",
    "iso:country":"BE",
    "sg:address":"Leemstraat 63",
    "sg:city":"Lochristi",
    "sg:orig_category":"Bloemen and planten Gh",
    "sg:phone":"+32 9 355 79 49",
    "sg:postcode":"9080",
    "sg:province":"Oost-Vlaanderen",
    "wof:name":"Van Hove L",
    "wof:placetype":"venue"
},
  "geometry": {"coordinates":[3.8805611134,51.1291313171],"type":"Point"}
}