{
  "type": "Feature",
  "properties": {
    "iso:country":"BE",
    "sg:address":"Vieille Rue Du Moulin 332",
    "sg:city":"Bruxelles (uccle)",
    "sg:classifiers":[
        {
            "category":"Home & Garden",
            "subcategory":"Home Furnishings",
            "type":"Retail Goods"
        }
    ],
    "sg:phone":"+32 2 375 40 36",
    "sg:postcode":"1180",
    "sg:province":"Bruxelles-Capitale",
    "sg:tags":[
        "interior",
        "decoration"
    ],
    "wof:name":"Wellens Jean-claude Sprl",
    "wof:placetype":"venue"
},
  "geometry": {"coordinates":[4.3742780685,50.7896728516],"type":"Point"}
}