{
  "type": "Feature",
  "properties": {
    "iso:country":"BE",
    "sg:address":"Rietenstraat 11",
    "sg:city":"Meeuwen-gruitrode",
    "sg:orig_category":"Afbraak- and draineerwerken",
    "sg:phone":"+32 89 47 31 42",
    "sg:postcode":"3670",
    "sg:province":"Limburg",
    "wof:name":"G. Nijs",
    "wof:placetype":"venue"
},
  "geometry": {"coordinates":[5.5503292084,51.0969314575],"type":"Point"}
}