{
  "type": "Feature",
  "properties": {
    "iso:country":"BE",
    "sg:address":"Palingbeekstraat 18",
    "sg:city":"Ieper",
    "sg:classifiers":[
        {
            "category":"Restaurant",
            "type":"Food & Drink"
        }
    ],
    "sg:phone":"+32 57 20 56 72",
    "sg:postcode":"8902",
    "sg:province":"West-Vlaanderen",
    "wof:name":"Restaurant De Palingbeek",
    "wof:placetype":"venue"
},
  "geometry": {"coordinates":[2.9205439091,50.8149261475],"type":"Point"}
}