{
  "type": "Feature",
  "properties": {
    "addr:full":"Leuvensebaan 81 Huldenberg Vlaams-Brabant 3040",
    "addr:housenumber":"81",
    "addr:postcode":"3040",
    "addr:street":"Leuvensebaan",
    "iso:country":"BE",
    "sg:address":"Leuvensebaan 81",
    "sg:city":"Huldenberg",
    "sg:orig_category":"Rundveehouders",
    "sg:phone":"+32 16 47 36 42",
    "sg:postcode":"3040",
    "sg:province":"Vlaams-Brabant",
    "wof:name":"Luc Mingneau",
    "wof:placetype":"venue"
},
  "geometry": {"coordinates":[4.6163511276,50.7541618347],"type":"Point"}
}