{
  "type": "Feature",
  "properties": {
    "addr:full":"Rue Des Haies 18 Ham-sur-heure-nalinnes (nalinnes) Hainaut 6120",
    "addr:housenumber":"18",
    "addr:postcode":"6120",
    "addr:street":"Rue Des Haies;Hainaut",
    "iso:country":"BE",
    "sg:address":"Rue Des Haies 18",
    "sg:city":"Ham-sur-heure-nalinnes (nalinnes)",
    "sg:classifiers":[
        {
            "category":"Personal",
            "subcategory":"Beauty Salon",
            "type":"Services"
        }
    ],
    "sg:phone":"+32 71 21 90 85",
    "sg:postcode":"6120",
    "sg:province":"Hainaut",
    "sg:tags":[
        "lady",
        "-",
        "hairdressing"
    ],
    "wof:name":"Personnalitif",
    "wof:placetype":"venue"
},
  "geometry": {"coordinates":[4.4451379776,50.3439865112],"type":"Point"}
}