{
  "type": "Feature",
  "properties": {
    "addr:full":"Rue De La Presse 4 Bruxelles Bruxelles-Capitale 1000",
    "addr:housenumber":"4",
    "addr:postcode":"1000",
    "addr:street":"Rue De La",
    "iso:country":"BE",
    "sg:address":"Rue De La Presse 4",
    "sg:city":"Bruxelles",
    "sg:classifiers":[
        {
            "category":"Building & Trades",
            "subcategory":"Construction",
            "type":"Services"
        }
    ],
    "sg:phone":"+32 2 675 84 12",
    "sg:postcode":"1000",
    "sg:province":"Bruxelles-Capitale",
    "sg:tags":[
        "work",
        "waterproofing"
    ],
    "wof:name":"Humi-stop",
    "wof:placetype":"venue"
},
  "geometry": {"coordinates":[4.3668470383,50.8492546082],"type":"Point"}
}