{
  "type": "Feature",
  "properties": {
    "iso:country":"BE",
    "sg:address":"Hoogbergstraat 11",
    "sg:city":"Kluisbergen",
    "sg:orig_category":"Eleveurs and marchands de porcs. Eleveurs de volaille",
    "sg:phone":"+32 55 21 24 74",
    "sg:postcode":"9690",
    "sg:province":"Oost-Vlaanderen",
    "wof:name":"Marciane Browaeys",
    "wof:placetype":"venue"
},
  "geometry": {"coordinates":[3.5768220425,50.7677726746],"type":"Point"}
}