{
  "type": "Feature",
  "properties": {
    "iso:country":"BE",
    "sg:address":"Kempenplein 19 Box 1",
    "sg:city":"Neerpelt",
    "sg:classifiers":[
        {
            "category":"Real Estate",
            "subcategory":"Surveying",
            "type":"Services"
        }
    ],
    "sg:phone":"+32 11 64 75 10",
    "sg:postcode":"3910",
    "sg:province":"Limburg",
    "sg:tags":[
        "surveyor",
        "land"
    ],
    "wof:name":"Achten J",
    "wof:placetype":"venue"
},
  "geometry": {"coordinates":[5.4326701164,51.2286643982],"type":"Point"}
}