{
  "type": "Feature",
  "properties": {
    "addr:full":"Motstraat 72 Hal 4 Mechelen Antwerpen 2800",
    "addr:housenumber":"72;4",
    "addr:postcode":"2800",
    "addr:street":"Motstraat;Hal",
    "iso:country":"BE",
    "sg:address":"Motstraat 72 Hal 4",
    "sg:city":"Mechelen",
    "sg:orig_category":"Rev\u00eatements pour sols and murs. Eclairage et \u00e9quipements du foyer. Peinture. Installation de menuise",
    "sg:phone":"+32 15 41 30 49",
    "sg:postcode":"2800",
    "sg:province":"Antwerpen",
    "wof:name":"Kiebooms",
    "wof:placetype":"venue"
},
  "geometry": {"coordinates":[4.475631237,51.0089950562],"type":"Point"}
}