{
  "type": "Feature",
  "properties": {
    "iso:country":"BE",
    "sg:address":"Eurolaan 5",
    "sg:city":"Temse",
    "sg:classifiers":[
        {
            "category":"Juice Bar",
            "subcategory":"None",
            "type":"Food & Drink"
        }
    ],
    "sg:phone":"+32 3 711 16 36",
    "sg:postcode":"9140",
    "sg:province":"Oost-Vlaanderen",
    "sg:tags":[
        "cellulose"
    ],
    "wof:name":"International Fiber Europe Nv",
    "wof:placetype":"venue"
},
  "geometry": {"coordinates":[4.1901450157,51.1372718811],"type":"Point"}
}