{
  "type": "Feature",
  "properties": {
    "iso:country":"BE",
    "sg:address":"Rue De Brest 1",
    "sg:city":"Paliseul (maissin)",
    "sg:classifiers":[
        {
            "category":"Manufacturing",
            "subcategory":"Wood Products",
            "type":"Manufacturing & Wholesale Goods"
        }
    ],
    "sg:phone":"+32 61 65 59 26",
    "sg:postcode":"6852",
    "sg:province":"Luxembourg",
    "sg:tags":[
        "firewood"
    ],
    "wof:name":"Gerard D",
    "wof:placetype":"venue"
},
  "geometry": {"coordinates":[5.1785240173,49.9646186829],"type":"Point"}
}