{
  "type": "Feature",
  "properties": {
    "addr:full":"Anselmostraat 93 Antwerpen Antwerpen 2018",
    "addr:housenumber":"93",
    "addr:postcode":"2018",
    "addr:street":"Anselmostraat",
    "iso:country":"BE",
    "sg:address":"Anselmostraat 93",
    "sg:city":"Antwerpen",
    "sg:orig_category":"Meubles D\u00e9taillants, Am\u00e9nagement de B\u00e2timents et de Cuisines",
    "sg:phone":"+32 3 237 51 26",
    "sg:postcode":"2018",
    "sg:province":"Antwerpen",
    "wof:name":"Gustaaf Bulkens",
    "wof:placetype":"venue"
},
  "geometry": {"coordinates":[4.4046988487,51.2052307129],"type":"Point"}
}