{
  "type": "Feature",
  "properties": {
    "iso:country":"BE",
    "sg:address":"Sint-anna 114",
    "sg:city":"Hamme",
    "sg:orig_category":"Herstellingen and onderhoud van auto's",
    "sg:phone":"+32 52 47 05 48",
    "sg:postcode":"9220",
    "sg:province":"Oost-Vlaanderen",
    "wof:name":"Carrosserie Lemeire",
    "wof:placetype":"venue"
},
  "geometry": {"coordinates":[4.0661950111,51.0936088562],"type":"Point"}
}