{
  "type": "Feature",
  "properties": {
    "addr:full":"Rue Chatqueue 112 Seraing Li\u00e8ge 4100",
    "addr:housenumber":"112",
    "addr:postcode":"4100",
    "addr:street":"Rue Chatqueue",
    "iso:country":"BE",
    "sg:address":"Rue Chatqueue 112",
    "sg:city":"Seraing",
    "sg:classifiers":[
        {
            "category":"Professional",
            "subcategory":"Testing Lab",
            "type":"Services"
        }
    ],
    "sg:phone":"+32 4 336 26 07",
    "sg:postcode":"4100",
    "sg:province":"Li\u00e8ge",
    "sg:tags":[
        "chemist"
    ],
    "wof:name":"Schrouff M",
    "wof:placetype":"venue"
},
  "geometry": {"coordinates":[5.5196518898,50.5998001099],"type":"Point"}
}