{
  "type": "Feature",
  "properties": {
    "addr:full":"Kleine Nieuwstraat 4 Zottegem Oost-Vlaanderen 9620",
    "addr:housenumber":"4",
    "addr:postcode":"9620",
    "addr:street":"Kleine Nieuwstraat",
    "iso:country":"BE",
    "sg:address":"Kleine Nieuwstraat 4",
    "sg:city":"Zottegem",
    "sg:classifiers":[
        {
            "category":"Professional",
            "subcategory":"Lawyer & Legal Services",
            "type":"Services"
        }
    ],
    "sg:phone":"+32 9 360 06 73",
    "sg:postcode":"9620",
    "sg:province":"Oost-Vlaanderen",
    "wof:name":"De Vleeschouwer H",
    "wof:placetype":"venue"
},
  "geometry": {"coordinates":[3.8135778904,50.8678588867],"type":"Point"}
}