{
  "type": "Feature",
  "properties": {
    "addr:full":"Dr\u00e8ve Richelle 274 Waterloo Brabant Wallon 1410",
    "addr:housenumber":"274",
    "addr:postcode":"1410",
    "addr:street":"Dre\u0300Ve Richelle",
    "iso:country":"BE",
    "sg:address":"Dr\u00e8ve Richelle 274",
    "sg:city":"Waterloo",
    "sg:classifiers":[
        {
            "category":"Real Estate",
            "subcategory":"Real Estate Services",
            "type":"Services"
        }
    ],
    "sg:phone":"+32 2 354 09 48",
    "sg:postcode":"1410",
    "sg:province":"Brabant Wallon",
    "wof:name":"Immo v",
    "wof:placetype":"venue"
},
  "geometry": {"coordinates":[4.4249401093,50.7003593445],"type":"Point"}
}