{
  "type": "Feature",
  "properties": {
    "addr:full":"Zarrenstraat 14 Kortemark West-Vlaanderen 8610",
    "addr:housenumber":"14",
    "addr:postcode":"8610",
    "addr:street":"Zarrenstraat",
    "iso:country":"BE",
    "sg:address":"Zarrenstraat 14",
    "sg:city":"Kortemark",
    "sg:orig_category":"Aardappelproducten Gh GROENTEN AND FRUIT Groenten and fruit Gh",
    "sg:phone":"+32 51 56 65 60",
    "sg:postcode":"8610",
    "sg:province":"West-Vlaanderen",
    "wof:name":"Jacques Hoorne",
    "wof:placetype":"venue"
},
  "geometry": {"coordinates":[2.9596550465,51.0192565918],"type":"Point"}
}