{
  "type": "Feature",
  "properties": {
    "iso:country":"BE",
    "sg:address":"Genkersteenweg 402",
    "sg:city":"Hasselt",
    "sg:orig_category":"Voertuigen",
    "sg:phone":"+32 11 22 85 31",
    "sg:postcode":"3500",
    "sg:province":"Limburg",
    "wof:name":"Garage Steinkamp",
    "wof:placetype":"venue"
},
  "geometry": {"coordinates":[5.381734848,50.9450645447],"type":"Point"}
}