{
  "type": "Feature",
  "properties": {
    "addr:full":"Voormezelestraat 5 Heuvelland West-Vlaanderen 8953",
    "addr:housenumber":"5",
    "addr:postcode":"8953",
    "addr:street":"Voormezelestraat",
    "iso:country":"BE",
    "sg:address":"Voormezelestraat 5",
    "sg:city":"Heuvelland",
    "sg:orig_category":"Varkenskwekers",
    "sg:phone":"+32 57 44 55 57",
    "sg:postcode":"8953",
    "sg:province":"West-Vlaanderen",
    "wof:name":"Marc Lobeau",
    "wof:placetype":"venue"
},
  "geometry": {"coordinates":[2.8750700951,50.8006629944],"type":"Point"}
}