{
  "type": "Feature",
  "properties": {
    "addr:full":"Rue Des Combattants 55 Jemeppe-sur-sambre Namur 5190",
    "addr:housenumber":"55",
    "addr:postcode":"5190",
    "addr:street":"Rue Des Combattants",
    "iso:country":"BE",
    "sg:address":"Rue Des Combattants 55",
    "sg:city":"Jemeppe-sur-sambre",
    "sg:orig_category":"Woningbouw",
    "sg:phone":"+32 71 78 74 39",
    "sg:postcode":"5190",
    "sg:province":"Namur",
    "wof:name":"L. Romain",
    "wof:placetype":"venue"
},
  "geometry": {"coordinates":[4.6703448296,50.4645042419],"type":"Point"}
}