{
  "type": "Feature",
  "properties": {
    "iso:country":"BE",
    "sg:address":"Rue Josaphat 135",
    "sg:city":"Bruxelles (schaerbeek)",
    "sg:classifiers":[
        {
            "category":"Health Services",
            "subcategory":"Nursing And Care Facility",
            "type":"Services"
        }
    ],
    "sg:phone":"+32 2 245 86 82",
    "sg:postcode":"1030",
    "sg:province":"Bruxelles-Capitale",
    "sg:tags":[
        "home"
    ],
    "wof:name":"Sante Chez Soi",
    "wof:placetype":"venue"
},
  "geometry": {"coordinates":[4.3752970695,50.8598022461],"type":"Point"}
}