{
  "type": "Feature",
  "properties": {
    "iso:country":"BE",
    "sg:address":"Technologieln 9",
    "sg:city":"Heverlee",
    "sg:classifiers":[
        {
            "category":"Wholesale",
            "subcategory":"Medical Equipment & Supplies",
            "type":"Manufacturing & Wholesale Goods"
        }
    ],
    "sg:phone":"+32 16 40 60 50",
    "sg:postcode":"3001",
    "sg:province":"Vlaams-Brabant",
    "sg:tags":[
        "instrument",
        "health",
        "-",
        "precision"
    ],
    "wof:name":"Ortec Nv",
    "wof:placetype":"venue"
},
  "geometry": {"coordinates":[4.7300601006,50.8533172607],"type":"Point"}
}