{
  "type": "Feature",
  "properties": {
    "iso:country":"BE",
    "sg:address":"Paardemarkt 15",
    "sg:city":"Sint-lievens-houtem",
    "sg:orig_category":"Bagage and lederwaren Schoenen",
    "sg:phone":"+32 53 62 86 11",
    "sg:postcode":"9520",
    "sg:province":"Oost-Vlaanderen",
    "wof:name":"Schoenen Maggy",
    "wof:placetype":"venue"
},
  "geometry": {"coordinates":[3.853302002,50.9207801819],"type":"Point"}
}