{
  "type": "Feature",
  "properties": {
    "iso:country":"BE",
    "sg:address":"Spoorwegbaan 20",
    "sg:city":"Ternat (sint-katherina-lombeek)",
    "sg:orig_category":"Non-Classified Establishments",
    "sg:phone":"+32 53 64 54 50",
    "sg:postcode":"1742",
    "sg:province":"Vlaams-Brabant",
    "wof:name":"Servibox Nv",
    "wof:placetype":"venue"
},
  "geometry": {"coordinates":[4.1222372055,50.8826751709],"type":"Point"}
}