{
  "type": "Feature",
  "properties": {
    "addr:full":"Singellaan 52 Mol Antwerpen 2400",
    "addr:housenumber":"52",
    "addr:postcode":"2400",
    "addr:street":"Singellaan",
    "iso:country":"BE",
    "sg:address":"Singellaan 52",
    "sg:city":"Mol",
    "sg:classifiers":[
        {
            "category":"Home & Garden",
            "subcategory":"Kitchen Supply",
            "type":"Retail Goods"
        }
    ],
    "sg:phone":"+32 14 31 80 56",
    "sg:postcode":"2400",
    "sg:province":"Antwerpen",
    "sg:tags":[
        "installation"
    ],
    "wof:name":"Heuvelmans Robert Bvba",
    "wof:placetype":"venue"
},
  "geometry": {"coordinates":[5.1270780563,51.1961402893],"type":"Point"}
}