{
  "type": "Feature",
  "properties": {
    "iso:country":"BE",
    "sg:address":"Quai Mativa 74",
    "sg:city":"Li\u00c8ge",
    "sg:orig_category":"Zalen voor culturele evenementen",
    "sg:phone":"+32 4 342 58 36",
    "sg:postcode":"4020",
    "sg:province":"Li\u00e8ge",
    "wof:name":"Th\u00c9\u00c2tre Gai Savoir",
    "wof:placetype":"venue"
},
  "geometry": {"coordinates":[5.5802898407,50.6239585876],"type":"Point"}
}