{
  "type": "Feature",
  "properties": {
    "iso:country":"BE",
    "sg:address":"Exterkenstraat 40",
    "sg:city":"Aalst",
    "sg:orig_category":"Agences de presse",
    "sg:phone":"+32 53 78 63 04",
    "sg:postcode":"9310",
    "sg:province":"Oost-Vlaanderen",
    "wof:name":"Johan Droessaert",
    "wof:placetype":"venue"
},
  "geometry": {"coordinates":[4.1072030067,50.9505157471],"type":"Point"}
}