{
  "type": "Feature",
  "properties": {
    "addr:full":"Herbesthaler Strasse 160 Eupen Li\u00e8ge 4700",
    "addr:housenumber":"160",
    "addr:postcode":"4700",
    "addr:street":"Herbesthaler Strasse",
    "iso:country":"BE",
    "sg:address":"Herbesthaler Strasse 160",
    "sg:city":"Eupen",
    "sg:classifiers":[
        {
            "category":"Autos & Motor Vehicles",
            "subcategory":"Auto Supplies",
            "type":"Retail Goods"
        }
    ],
    "sg:phone":"+32 87 56 02 74",
    "sg:postcode":"4700",
    "sg:province":"Li\u00e8ge",
    "sg:tags":[
        "automobile",
        "alarm",
        "-",
        "system"
    ],
    "wof:name":"Phelect Sprl",
    "wof:placetype":"venue"
},
  "geometry": {"coordinates":[6.0089101791,50.6441993713],"type":"Point"}
}