{
  "type": "Feature",
  "properties": {
    "iso:country":"BE",
    "sg:address":"Nieuwe Kouterstraat 48",
    "sg:city":"Bornem",
    "sg:classifiers":[
        {
            "category":"Insurance",
            "subcategory":"Insurance Agent",
            "type":"Services"
        }
    ],
    "sg:phone":"+32 3 889 93 92",
    "sg:postcode":"2880",
    "sg:province":"Antwerpen",
    "sg:tags":[
        "broker"
    ],
    "wof:name":"Gevaers B",
    "wof:placetype":"venue"
},
  "geometry": {"coordinates":[4.2376818657,51.0978927612],"type":"Point"}
}