{
  "type": "Feature",
  "properties": {
    "addr:full":"Ottr\u00e9 75 Vielsalm (bihain) Luxembourg 6690",
    "addr:housenumber":"75",
    "addr:postcode":"6690",
    "addr:street":"Ottre\u0301",
    "iso:country":"BE",
    "sg:address":"Ottr\u00e9 75",
    "sg:city":"Vielsalm (bihain)",
    "sg:classifiers":[
        {
            "category":"Military Area",
            "subcategory":"Air Force Base",
            "type":"Public Place"
        }
    ],
    "sg:phone":"+32 80 41 80 50",
    "sg:postcode":"6690",
    "sg:province":"Luxembourg",
    "sg:tags":[
        "herb",
        "-",
        "medicinal"
    ],
    "wof:name":"Agrimed",
    "wof:placetype":"venue"
},
  "geometry": {"coordinates":[5.839220047,50.2496452332],"type":"Point"}
}