{
  "type": "Feature",
  "properties": {
    "iso:country":"BE",
    "sg:address":"Herbert Hooverplein 1",
    "sg:city":"Leuven",
    "sg:orig_category":"GROENTEN AND FRUIT Groenten and fruit Gh",
    "sg:phone":"+32 16 22 54 91",
    "sg:postcode":"3000",
    "sg:province":"Vlaams-Brabant",
    "wof:name":"'t Pompoentje",
    "wof:placetype":"venue"
},
  "geometry": {"coordinates":[4.70540905,50.877117157],"type":"Point"}
}