{
  "type": "Feature",
  "properties": {
    "addr:full":"Parklaan 46 Sint-niklaas Oost-Vlaanderen 9100",
    "addr:housenumber":"46",
    "addr:postcode":"9100",
    "addr:street":"Parklaan",
    "iso:country":"BE",
    "sg:address":"Parklaan 46",
    "sg:city":"Sint-niklaas",
    "sg:classifiers":[
        {
            "category":"Health Services",
            "subcategory":"Doctor",
            "type":"Services"
        }
    ],
    "sg:phone":"+32 3 776 58 29",
    "sg:postcode":"9100",
    "sg:province":"Oost-Vlaanderen",
    "sg:tags":[
        "medicinephysicians",
        "surgeon"
    ],
    "wof:name":"Haentjens Paul",
    "wof:placetype":"venue"
},
  "geometry": {"coordinates":[4.1501832008,51.1593475342],"type":"Point"}
}