{
  "type": "Feature",
  "properties": {
    "iso:country":"BE",
    "sg:address":"Sint-jorislaan 145",
    "sg:city":"Herk-de-stad (schulen)",
    "sg:classifiers":[
        {
            "category":"Freight",
            "type":"Transportation"
        }
    ],
    "sg:phone":"+32 13 55 55 19",
    "sg:postcode":"3540",
    "sg:province":"Limburg",
    "sg:tags":[
        "-",
        "transport"
    ],
    "wof:name":"Slingers M",
    "wof:placetype":"venue"
},
  "geometry": {"coordinates":[5.1951241493,50.9524917603],"type":"Point"}
}