{
  "type": "Feature",
  "properties": {
    "iso:country":"BE",
    "sg:address":"Chauss\u00c9e De Haecht 89-91",
    "sg:city":"Schaarbeek/schaerbeek",
    "sg:classifiers":[
        {
            "category":"Fast Food",
            "type":"Food & Drink"
        }
    ],
    "sg:phone":"+32 2 218 51 27",
    "sg:postcode":"1030",
    "sg:province":"Bruxelles-Capitale",
    "sg:tags":[
        "\u00c0",
        "restaurants",
        "emporter",
        "restaurant"
    ],
    "wof:name":"Restaurant Izmir",
    "wof:placetype":"venue"
},
  "geometry": {"coordinates":[4.3694238663,50.8574409485],"type":"Point"}
}