{
  "type": "Feature",
  "properties": {
    "addr:full":"Koolkerkse Steenweg 12 Brugge West-Vlaanderen 8000",
    "addr:housenumber":"12",
    "addr:postcode":"8000",
    "addr:street":"Koolkerkse Steenweg",
    "iso:country":"BE",
    "sg:address":"Koolkerkse Steenweg 12",
    "sg:city":"Brugge",
    "sg:orig_category":"Advocaten and juridische adviseurs",
    "sg:phone":"+32 50 33 76 47",
    "sg:postcode":"8000",
    "sg:province":"West-Vlaanderen",
    "wof:name":"Michel Demolder",
    "wof:placetype":"venue"
},
  "geometry": {"coordinates":[3.2337949276,51.2226638794],"type":"Point"}
}