{
  "type": "Feature",
  "properties": {
    "iso:country":"BE",
    "sg:address":"Zeelsebaan 83bz",
    "sg:city":"Dendermonde",
    "sg:orig_category":"Meubles D\u00e9taillants, Am\u00e9nagement de B\u00e2timents et de Cuisines",
    "sg:phone":"+32 52 22 30 80",
    "sg:postcode":"9200",
    "sg:province":"Oost-Vlaanderen",
    "wof:name":"Domus",
    "wof:placetype":"venue"
},
  "geometry": {"coordinates":[4.0910840034,51.046421051],"type":"Point"}
}