{
  "type": "Feature",
  "properties": {
    "iso:country":"BE",
    "sg:address":"Chemin Du Sous-bois 36",
    "sg:city":"Spa",
    "sg:orig_category":"Articles de jardin. Fleurs and plantes",
    "sg:phone":"+32 87 77 10 25",
    "sg:postcode":"4900",
    "sg:province":"Li\u00e8ge",
    "wof:name":"Les Serres Du Sous-bois",
    "wof:placetype":"venue"
},
  "geometry": {"coordinates":[5.8835639954,50.4875869751],"type":"Point"}
}