{
  "type": "Feature",
  "properties": {
    "iso:country":"BE",
    "sg:address":"Tige D'oneux 6",
    "sg:city":"Ouffet",
    "sg:classifiers":[
        {
            "category":"Arena",
            "subcategory":"Sports Club",
            "type":"Entertainment"
        }
    ],
    "sg:phone":"+32 86 36 65 80",
    "sg:postcode":"4590",
    "sg:province":"Li\u00e8ge",
    "sg:tags":[
        "de"
    ],
    "wof:name":"V.c. Ouffet",
    "wof:placetype":"venue"
},
  "geometry": {"coordinates":[5.4250979424,50.4472808838],"type":"Point"}
}