{
  "type": "Feature",
  "properties": {
    "addr:full":"Linkhoutstraat 233 Lummen (linkhout) Limburg 3560",
    "addr:housenumber":"233",
    "addr:postcode":"3560",
    "addr:street":"Linkhoutstraat",
    "iso:country":"BE",
    "sg:address":"Linkhoutstraat 233",
    "sg:city":"Lummen (linkhout)",
    "sg:classifiers":[
        {
            "category":"Health Services",
            "subcategory":"Health Practitioner",
            "type":"Services"
        }
    ],
    "sg:phone":"+32 13 44 40 38",
    "sg:postcode":"3560",
    "sg:province":"Limburg",
    "sg:tags":[
        "physiotherapist"
    ],
    "wof:name":"Geybels Ilse",
    "wof:placetype":"venue"
},
  "geometry": {"coordinates":[5.1346077919,50.964717865],"type":"Point"}
}