{
  "type": "Feature",
  "properties": {
    "addr:full":"Overleiestraat 58 Harelbeke West-Vlaanderen 8530",
    "addr:housenumber":"58",
    "addr:postcode":"8530",
    "addr:street":"Overleiestraat",
    "iso:country":"BE",
    "sg:address":"Overleiestraat 58",
    "sg:city":"Harelbeke",
    "sg:orig_category":"Traitements param\u00e9dicaux",
    "sg:phone":"+32 56 72 79 88",
    "sg:postcode":"8530",
    "sg:province":"West-Vlaanderen",
    "wof:name":"A. Matton",
    "wof:placetype":"venue"
},
  "geometry": {"coordinates":[3.3062698841,50.8598518372],"type":"Point"}
}