{
  "type": "Feature",
  "properties": {
    "addr:full":"Europalaan 13 Izegem West-Vlaanderen 8870",
    "addr:housenumber":"13",
    "addr:postcode":"8870",
    "addr:street":"Europalaan",
    "iso:country":"BE",
    "sg:address":"Europalaan 13",
    "sg:city":"Izegem",
    "sg:classifiers":[
        {
            "category":"Professional",
            "subcategory":"Management & Consulting",
            "type":"Services"
        }
    ],
    "sg:phone":"+32 51 32 02 46",
    "sg:postcode":"8870",
    "sg:province":"West-Vlaanderen",
    "sg:tags":[
        "-",
        "processing",
        "data",
        "consultant"
    ],
    "wof:name":"Genius Ict Services",
    "wof:placetype":"venue"
},
  "geometry": {"coordinates":[3.200783968,50.9136505127],"type":"Point"}
}