{
  "type": "Feature",
  "properties": {
    "addr:full":"Sint-benedictusdreef 11 Schoten Antwerpen 2900",
    "addr:housenumber":"11",
    "addr:postcode":"2900",
    "addr:street":"Sint-Benedictusdreef",
    "iso:country":"BE",
    "sg:address":"Sint-benedictusdreef 11",
    "sg:city":"Schoten",
    "sg:classifiers":[
        {
            "category":"Personal",
            "subcategory":"Beauty Salon",
            "type":"Services"
        }
    ],
    "sg:phone":"+32 3 281 54 37",
    "sg:postcode":"2900",
    "sg:province":"Antwerpen",
    "wof:name":"Kerstens K",
    "wof:placetype":"venue"
},
  "geometry": {"coordinates":[4.5292339325,51.2478790283],"type":"Point"}
}