{
  "type": "Feature",
  "properties": {
    "addr:full":"Place Jean-charles De Hugo 94 Tintigny (bellefontaine) Luxembourg 6730",
    "addr:housenumber":"94",
    "addr:postcode":"6730",
    "addr:street":"Place Jean-Charles De Hugo",
    "iso:country":"BE",
    "sg:address":"Place Jean-charles De Hugo 94",
    "sg:city":"Tintigny (bellefontaine)",
    "sg:classifiers":[
        {
            "category":"Home & Garden",
            "subcategory":"Home Furnishings",
            "type":"Retail Goods"
        }
    ],
    "sg:phone":"+32 63 44 44 66",
    "sg:postcode":"6730",
    "sg:province":"Luxembourg",
    "sg:tags":[
        "wallpaper",
        "-"
    ],
    "wof:name":"Muttesch D\u00e9cor Sprl",
    "wof:placetype":"venue"
},
  "geometry": {"coordinates":[5.4962902069,49.6648483276],"type":"Point"}
}