{
  "type": "Feature",
  "properties": {
    "addr:full":"Eikevlietbaan 1 Puurs Antwerpen 2870",
    "addr:housenumber":"1",
    "addr:postcode":"2870",
    "addr:street":"Eikevlietbaan",
    "iso:country":"BE",
    "sg:address":"Eikevlietbaan 1",
    "sg:city":"Puurs",
    "sg:orig_category":"Tweedehandsgoederen",
    "sg:phone":"+32 3 889 63 30",
    "sg:postcode":"2870",
    "sg:province":"Antwerpen",
    "wof:name":"Klim Op",
    "wof:placetype":"venue"
},
  "geometry": {"coordinates":[4.2800068855,51.0780639648],"type":"Point"}
}