{
  "type": "Feature",
  "properties": {
    "addr:full":"Les Pl\u00c9nesses 69b Thimister-clermont Li\u00e8ge 4890",
    "addr:housenumber":"69b",
    "addr:postcode":"4890",
    "iso:country":"BE",
    "sg:address":"Les Pl\u00c9nesses 69b",
    "sg:city":"Thimister-clermont",
    "sg:orig_category":"Dakwerken",
    "sg:phone":"+32 87 44 67 41",
    "sg:postcode":"4890",
    "sg:province":"Li\u00e8ge",
    "wof:name":"Piront Vincent",
    "wof:placetype":"venue"
},
  "geometry": {"coordinates":[5.8719630241,50.6335678101],"type":"Point"}
}