{
  "type": "Feature",
  "properties": {
    "iso:country":"BE",
    "sg:address":"Rue Fran\u00c7ois Cornet 49",
    "sg:city":"Awans",
    "sg:orig_category":"Alternatieve geneeskunde Artsen and specialisten",
    "sg:phone":"+32 4 263 77 51",
    "sg:postcode":"4340",
    "sg:province":"Li\u00e8ge",
    "wof:name":"Pierre Um\u00c9",
    "wof:placetype":"venue"
},
  "geometry": {"coordinates":[5.4673428535,50.6698799133],"type":"Point"}
}