{
  "type": "Feature",
  "properties": {
    "iso:country":"BE",
    "sg:address":"Rue De La Liberte 35",
    "sg:city":"Chievres",
    "sg:orig_category":"V\u00e9hicules automobiles. Entretien and r\u00e9parations de voitures",
    "sg:phone":"+32 68 65 73 94",
    "sg:postcode":"7950",
    "sg:province":"Hainaut",
    "wof:name":"Garage Bralion",
    "wof:placetype":"venue"
},
  "geometry": {"coordinates":[3.8069698811,50.5864601135],"type":"Point"}
}