{
  "type": "Feature",
  "properties": {
    "iso:country":"BE",
    "sg:address":"Meir 34b36",
    "sg:city":"Antwerpen",
    "sg:orig_category":"V\u00eatements pour Hommes. V\u00eatements pour Dames",
    "sg:phone":"+32 3 225 24 37",
    "sg:postcode":"2000",
    "sg:province":"Antwerpen",
    "wof:name":"Faks",
    "wof:placetype":"venue"
},
  "geometry": {"coordinates":[4.4072318077,51.2180404663],"type":"Point"}
}