{
  "type": "Feature",
  "properties": {
    "addr:full":"Bergstraat 41 Waregem West-Vlaanderen 8790",
    "addr:housenumber":"41",
    "addr:postcode":"8790",
    "addr:street":"Bergstraat",
    "iso:country":"BE",
    "sg:address":"Bergstraat 41",
    "sg:city":"Waregem",
    "sg:orig_category":"RESTAURANTS: H\u00d4TELS",
    "sg:phone":"+32 56 60 97 47",
    "sg:postcode":"8790",
    "sg:province":"West-Vlaanderen",
    "wof:name":"Happy Golf Hotel",
    "wof:placetype":"venue"
},
  "geometry": {"coordinates":[3.4661910534,50.8821182251],"type":"Point"}
}