{
  "type": "Feature",
  "properties": {
    "iso:country":"BE",
    "sg:address":"Avenue Tedesco 1",
    "sg:city":"Oudergem/auderghem",
    "sg:classifiers":[
        {
            "category":"Personal",
            "subcategory":"Beauty Salon",
            "type":"Services"
        }
    ],
    "sg:phone":"+32 2 673 45 52",
    "sg:postcode":"1160",
    "sg:province":"Bruxelles-Capitale",
    "sg:tags":[
        "de",
        "coiffure"
    ],
    "wof:name":"Val Duchesse",
    "wof:placetype":"venue"
},
  "geometry": {"coordinates":[4.4279608727,50.8196372986],"type":"Point"}
}