{
  "type": "Feature",
  "properties": {
    "addr:full":"Rue Du Perron 45b2 Oupeye Li\u00e8ge 4681",
    "addr:housenumber":"45b2",
    "addr:postcode":"4681",
    "addr:street":"Rue Du Perron",
    "iso:country":"BE",
    "sg:address":"Rue Du Perron 45b2",
    "sg:city":"Oupeye",
    "sg:orig_category":"Paramedische behandelingen",
    "sg:phone":"+32 4 374 14 81",
    "sg:postcode":"4681",
    "sg:province":"Li\u00e8ge",
    "wof:name":"M. Humblet",
    "wof:placetype":"venue"
},
  "geometry": {"coordinates":[5.6804528236,50.7121772766],"type":"Point"}
}