{
  "type": "Feature",
  "properties": {
    "addr:full":"Rue De Genly 30 Qu\u00c9vy Hainaut 7040",
    "addr:housenumber":"30",
    "addr:postcode":"7040",
    "addr:street":"Rue De Genly;Hainaut",
    "iso:country":"BE",
    "sg:address":"Rue De Genly 30",
    "sg:city":"Qu\u00c9vy",
    "sg:orig_category":"Instituts de beaut\u00e9",
    "sg:phone":"+32 65 56 74 34",
    "sg:postcode":"7040",
    "sg:province":"Hainaut",
    "wof:name":"Jacqueline Masy",
    "wof:placetype":"venue"
},
  "geometry": {"coordinates":[3.8970139027,50.3627243042],"type":"Point"}
}