{
  "type": "Feature",
  "properties": {
    "iso:country":"BE",
    "sg:address":"Rue Delwaide 32",
    "sg:city":"Oupeye (hermalle-sous-argenteau)",
    "sg:classifiers":[
        {
            "category":"Professional",
            "subcategory":"Computer Services",
            "type":"Services"
        }
    ],
    "sg:phone":"+32 4 379 12 65",
    "sg:postcode":"4681",
    "sg:province":"Li\u00e8ge",
    "sg:tags":[
        "-",
        "processing",
        "data",
        "software"
    ],
    "wof:name":"Inforga",
    "wof:placetype":"venue"
},
  "geometry": {"coordinates":[5.6854839325,50.7179985046],"type":"Point"}
}