{
  "type": "Feature",
  "properties": {
    "iso:country":"BE",
    "sg:address":"Rue Des Hauts Arbres 29",
    "sg:city":"Chi\u00e8vres (ladeuze)",
    "sg:classifiers":[
        {
            "category":"Bars & Pubs",
            "type":"Food & Drink"
        }
    ],
    "sg:phone":"+32 69 68 70 50",
    "sg:postcode":"7950",
    "sg:province":"Hainaut",
    "wof:name":"Marmiton (taverne)",
    "wof:placetype":"venue"
},
  "geometry": {"coordinates":[3.7570800781,50.5641365051],"type":"Point"}
}