{
  "type": "Feature",
  "properties": {
    "iso:country":"BE",
    "sg:address":"Schuurweg 8",
    "sg:city":"Scherpenheuvel-zichem (testelt)",
    "sg:classifiers":[
        {
            "category":"Health Services",
            "subcategory":"Health Practitioner",
            "type":"Services"
        }
    ],
    "sg:phone":"+32 13 77 63 25",
    "sg:postcode":"3272",
    "sg:province":"Vlaams-Brabant",
    "sg:tags":[
        "physiotherapist"
    ],
    "wof:name":"Counotte Nicole",
    "wof:placetype":"venue"
},
  "geometry": {"coordinates":[4.9497518539,51.0077323914],"type":"Point"}
}