{
  "type": "Feature",
  "properties": {
    "iso:country":"BE",
    "sg:address":"Grote Markt 7",
    "sg:city":"Lier",
    "sg:orig_category":"Fleurs and plantes",
    "sg:phone":"+32 3 480 46 03",
    "sg:postcode":"2500",
    "sg:province":"Antwerpen",
    "wof:name":"De Groene Opera",
    "wof:placetype":"venue"
},
  "geometry": {"coordinates":[4.5707278252,51.1301689148],"type":"Point"}
}