{
  "type": "Feature",
  "properties": {
    "addr:full":"Nazarethese Steenweg 109 Kruishoutem (grand) Oost-Vlaanderen 9770",
    "addr:housenumber":"109",
    "addr:postcode":"9770",
    "addr:street":"Steenweg",
    "iso:country":"BE",
    "sg:address":"Nazarethese Steenweg 109",
    "sg:city":"Kruishoutem (grand)",
    "sg:orig_category":"Tuinbenodigdheden",
    "sg:phone":"+32 9 384 11 72",
    "sg:postcode":"9770",
    "sg:province":"Oost-Vlaanderen",
    "wof:name":"Van Den Brande",
    "wof:placetype":"venue"
},
  "geometry": {"coordinates":[3.5846030712,50.928401947],"type":"Point"}
}