{
  "type": "Feature",
  "properties": {
    "addr:full":"Rue De Mazy 9 Gembloux Namur 5030",
    "addr:housenumber":"9",
    "addr:postcode":"5030",
    "addr:street":"Rue De Mazy;Namur",
    "iso:country":"BE",
    "sg:address":"Rue De Mazy 9",
    "sg:city":"Gembloux",
    "sg:orig_category":"Boekhouders",
    "sg:phone":"+32 81 61 27 80",
    "sg:postcode":"5030",
    "sg:province":"Namur",
    "wof:name":"Daniel Lauriers",
    "wof:placetype":"venue"
},
  "geometry": {"coordinates":[4.6987280846,50.5571060181],"type":"Point"}
}