{
  "type": "Feature",
  "properties": {
    "addr:full":"Latemstraat 22 De Pinte Oost-Vlaanderen 9840",
    "addr:housenumber":"22",
    "addr:postcode":"9840",
    "addr:street":"Latemstraat",
    "iso:country":"BE",
    "sg:address":"Latemstraat 22",
    "sg:city":"De Pinte",
    "sg:orig_category":"M\u00e9decins and sp\u00e9cialistes",
    "sg:phone":"+32 9 282 53 12",
    "sg:postcode":"9840",
    "sg:province":"Oost-Vlaanderen",
    "wof:name":"A. Smis",
    "wof:placetype":"venue"
},
  "geometry": {"coordinates":[3.6505599022,51.0041007996],"type":"Point"}
}