{
  "type": "Feature",
  "properties": {
    "iso:country":"BE",
    "sg:address":"Rue De L'industrie 31",
    "sg:city":"Binche",
    "sg:classifiers":[
        {
            "category":"Cafe",
            "type":"Food & Drink"
        }
    ],
    "sg:phone":"+32 64 33 91 80",
    "sg:postcode":"7134",
    "sg:province":"Hainaut",
    "sg:tags":[
        "caf\u00e9s"
    ],
    "wof:name":"Francesco Cimino",
    "wof:placetype":"venue"
},
  "geometry": {"coordinates":[4.18957901,50.4286994934],"type":"Point"}
}