{
  "type": "Feature",
  "properties": {
    "addr:full":"Kasteellaan 37 Malle (westmalle) Antwerpen 2390",
    "addr:housenumber":"37",
    "addr:postcode":"2390",
    "addr:street":"Kasteellaan",
    "iso:country":"BE",
    "sg:address":"Kasteellaan 37",
    "sg:city":"Malle (westmalle)",
    "sg:classifiers":[
        {
            "category":"Personal",
            "subcategory":"Beauty Salon",
            "type":"Services"
        }
    ],
    "sg:phone":"+32 3 312 07 66",
    "sg:postcode":"2390",
    "sg:province":"Antwerpen",
    "sg:tags":[
        "lady",
        "-",
        "hairdressing"
    ],
    "wof:name":"Jamb\u00e9 V",
    "wof:placetype":"venue"
},
  "geometry": {"coordinates":[4.6895260811,51.3001441956],"type":"Point"}
}