{
  "type": "Feature",
  "properties": {
    "addr:full":"Prins Albertlaan 53 Sint-truiden Limburg 3800",
    "addr:housenumber":"53",
    "addr:postcode":"3800",
    "addr:street":"Prins Albertlaan",
    "iso:country":"BE",
    "sg:address":"Prins Albertlaan 53",
    "sg:city":"Sint-truiden",
    "sg:orig_category":"Herstellingen and onderhoud van auto's Onderdelen and accessoires voor auto's",
    "sg:phone":"+32 11 68 37 59",
    "sg:postcode":"3800",
    "sg:province":"Limburg",
    "wof:name":"Midas",
    "wof:placetype":"venue"
},
  "geometry": {"coordinates":[5.1779828072,50.81772995],"type":"Point"}
}