{
  "type": "Feature",
  "properties": {
    "addr:full":"Oude Haachtsesteenweg 121 Machelen Vlaams-Brabant 1831",
    "addr:housenumber":"121",
    "addr:postcode":"1831",
    "addr:street":"Oude Haachtsesteenweg",
    "iso:country":"BE",
    "sg:address":"Oude Haachtsesteenweg 121",
    "sg:city":"Machelen",
    "sg:orig_category":"Entretien and r\u00e9parations de voitures. V\u00e9hicules automobiles",
    "sg:phone":"+32 2 720 08 39",
    "sg:postcode":"1831",
    "sg:province":"Vlaams-Brabant",
    "wof:name":"Garage Peeters",
    "wof:placetype":"venue"
},
  "geometry": {"coordinates":[4.434264183,50.8955383301],"type":"Point"}
}