{
  "type": "Feature",
  "properties": {
    "iso:country":"BE",
    "sg:address":"Rue Du Ch\u00c8ne 121",
    "sg:city":"Seraing",
    "sg:orig_category":"M\u00e9decins and sp\u00e9cialistes",
    "sg:phone":"+32 4 337 15 89",
    "sg:postcode":"4100",
    "sg:province":"Li\u00e8ge",
    "wof:name":"Armand Lackmann",
    "wof:placetype":"venue"
},
  "geometry": {"coordinates":[5.5183730125,50.6031341553],"type":"Point"}
}