{
  "type": "Feature",
  "properties": {
    "iso:country":"BE",
    "sg:address":"Ruelle Siot 1",
    "sg:city":"Seneffe",
    "sg:classifiers":[
        {
            "category":"Communications",
            "subcategory":"Television Station",
            "type":"Services"
        }
    ],
    "sg:phone":"+32 475 42 19 46",
    "sg:postcode":"7180",
    "sg:province":"Hainaut",
    "sg:tags":[
        "report",
        "video"
    ],
    "wof:name":"Pixels Video",
    "wof:placetype":"venue"
},
  "geometry": {"coordinates":[4.2590909004,50.5355873108],"type":"Point"}
}