{
  "type": "Feature",
  "properties": {
    "iso:country":"BE",
    "sg:address":"Rue Des Champs 39",
    "sg:city":"Etterbeek",
    "sg:orig_category":"Supermarch\u00e9s",
    "sg:phone":"+32 2 647 44 73",
    "sg:postcode":"1040",
    "sg:province":"Bruxelles-Capitale",
    "wof:name":"Gb Contact",
    "wof:placetype":"venue"
},
  "geometry": {"coordinates":[4.3917198181,50.8302726746],"type":"Point"}
}