{
  "type": "Feature",
  "properties": {
    "iso:country":"BE",
    "sg:address":"Rue Du Pont 21",
    "sg:city":"Waremme",
    "sg:orig_category":"Dierenartsen",
    "sg:phone":"+32 19 33 15 33",
    "sg:postcode":"4300",
    "sg:province":"Li\u00e8ge",
    "wof:name":"Ph. Ocula",
    "wof:placetype":"venue"
},
  "geometry": {"coordinates":[5.25440979,50.7003211975],"type":"Point"}
}