{
  "type": "Feature",
  "properties": {
    "addr:full":"Eernegemsestraat 36 Zedelgem (aartrijke) West-Vlaanderen 8211",
    "addr:housenumber":"36",
    "addr:postcode":"8211",
    "addr:street":"Eernegemsestraat",
    "iso:country":"BE",
    "sg:address":"Eernegemsestraat 36",
    "sg:city":"Zedelgem (aartrijke)",
    "sg:classifiers":[
        {
            "category":"Home & Garden",
            "subcategory":"Kitchen Supply",
            "type":"Retail Goods"
        }
    ],
    "sg:phone":"+32 50 24 01 03",
    "sg:postcode":"8211",
    "sg:province":"West-Vlaanderen",
    "sg:tags":[
        "installation"
    ],
    "wof:name":"Desender-desmedt Nv",
    "wof:placetype":"venue"
},
  "geometry": {"coordinates":[3.0889649391,51.1200408936],"type":"Point"}
}