{
  "type": "Feature",
  "properties": {
    "addr:full":"Plein 157 Kaprijke Oost-Vlaanderen 9970",
    "addr:housenumber":"157",
    "addr:postcode":"9970",
    "addr:street":"Plein",
    "iso:country":"BE",
    "sg:address":"Plein 157",
    "sg:city":"Kaprijke",
    "sg:orig_category":"Banques and organismes de cr\u00e9dit",
    "sg:phone":"+32 9 373 84 54",
    "sg:postcode":"9970",
    "sg:province":"Oost-Vlaanderen",
    "wof:name":"Ippa",
    "wof:placetype":"venue"
},
  "geometry": {"coordinates":[3.6176359653,51.2171173096],"type":"Point"}
}