{
  "type": "Feature",
  "properties": {
    "addr:full":"Kamstraat 34 Herne Vlaams-Brabant 1540",
    "addr:housenumber":"34",
    "addr:postcode":"1540",
    "addr:street":"Kamstraat",
    "iso:country":"BE",
    "sg:address":"Kamstraat 34",
    "sg:city":"Herne",
    "sg:orig_category":"Banques and organismes de cr\u00e9dit",
    "sg:phone":"+32 54 56 62 98",
    "sg:postcode":"1540",
    "sg:province":"Vlaams-Brabant",
    "wof:name":"Centea",
    "wof:placetype":"venue"
},
  "geometry": {"coordinates":[4.0974798203,50.7540359497],"type":"Point"}
}