{
  "type": "Feature",
  "properties": {
    "addr:full":"Rue Des Trois Hur\u00c9es 206 Mons Hainaut 7012",
    "addr:housenumber":"206",
    "addr:postcode":"7012",
    "addr:street":"Rue Des Trois Hure\u0301Es;Hainaut",
    "iso:country":"BE",
    "sg:address":"Rue Des Trois Hur\u00c9es 206",
    "sg:city":"Mons",
    "sg:orig_category":"Traitements param\u00e9dicaux",
    "sg:phone":"+32 65 82 21 64",
    "sg:postcode":"7012",
    "sg:province":"Hainaut",
    "wof:name":"M. Baudoux",
    "wof:placetype":"venue"
},
  "geometry": {"coordinates":[3.8894600868,50.4481964111],"type":"Point"}
}