{
  "type": "Feature",
  "properties": {
    "addr:full":"Rue Roi Albert 2 Sambreville Namur 5060",
    "addr:housenumber":"2",
    "addr:postcode":"5060",
    "addr:street":"Rue Roi Albert",
    "iso:country":"BE",
    "sg:address":"Rue Roi Albert 2",
    "sg:city":"Sambreville",
    "sg:classifiers":[
        {
            "category":"Personal",
            "subcategory":"Beauty Salon",
            "type":"Services"
        }
    ],
    "sg:phone":"+32 71 77 62 48",
    "sg:postcode":"5060",
    "sg:province":"Namur",
    "sg:tags":[
        "de",
        "coiffure"
    ],
    "wof:name":"Coiffure D'hesley",
    "wof:placetype":"venue"
},
  "geometry": {"coordinates":[4.6213169098,50.4186019897],"type":"Point"}
}