{
  "type": "Feature",
  "properties": {
    "iso:country":"BE",
    "sg:address":"Avenue De La Lib\u00e9ration 15a",
    "sg:city":"Mons (ghlin)",
    "sg:classifiers":[
        {
            "category":"Manufacturing",
            "subcategory":"Furniture",
            "type":"Manufacturing & Wholesale Goods"
        }
    ],
    "sg:phone":"+32 65 35 21 15",
    "sg:postcode":"7011",
    "sg:province":"Hainaut",
    "sg:tags":[
        "armchair",
        "-"
    ],
    "wof:name":"Fontaine Relax Ets",
    "wof:placetype":"venue"
},
  "geometry": {"coordinates":[3.912539959,50.4712982178],"type":"Point"}
}