{
  "type": "Feature",
  "properties": {
    "iso:country":"BE",
    "sg:address":"Rue Des Haies 126",
    "sg:city":"Charleroi",
    "sg:orig_category":"Huishoudapparaten, televisies and radio's Meubelzaken, woning- and keukeninrichting",
    "sg:phone":"+32 71 36 37 69",
    "sg:postcode":"6001",
    "sg:province":"Hainaut",
    "wof:name":"Marcel Evlard",
    "wof:placetype":"venue"
},
  "geometry": {"coordinates":[4.4487028122,50.3949775696],"type":"Point"}
}