{
  "type": "Feature",
  "properties": {
    "addr:full":"Rue Du Trabloux 1 Saint-leger Luxembourg 6747",
    "addr:housenumber":"1",
    "addr:postcode":"6747",
    "addr:street":"Rue Du Trabloux",
    "iso:country":"BE",
    "sg:address":"Rue Du Trabloux 1",
    "sg:city":"Saint-leger",
    "sg:orig_category":"Rundveehouders",
    "sg:phone":"+32 63 22 60 15",
    "sg:postcode":"6747",
    "sg:province":"Luxembourg",
    "wof:name":"Joseph Thomas",
    "wof:placetype":"venue"
},
  "geometry": {"coordinates":[5.7120552063,49.6173057556],"type":"Point"}
}