{
  "type": "Feature",
  "properties": {
    "addr:full":"Rue Churchill 281-283 Courcelles Hainaut 6180",
    "addr:postcode":"281-283;6180",
    "addr:street":"Rue Churchill",
    "iso:country":"BE",
    "sg:address":"Rue Churchill 281-283",
    "sg:city":"Courcelles",
    "sg:classifiers":[
        {
            "category":"Industrial Area",
            "type":"Public Place"
        }
    ],
    "sg:phone":"+32 71 46 16 00",
    "sg:postcode":"6180",
    "sg:province":"Hainaut",
    "sg:tags":[
        "pump"
    ],
    "wof:name":"Evrard C.m. S.a.",
    "wof:placetype":"venue"
},
  "geometry": {"coordinates":[4.393778801,50.4632415771],"type":"Point"}
}