{
  "type": "Feature",
  "properties": {
    "addr:full":"Leitemolenstraat 4 Oostkamp (ruddervoorde) West-Vlaanderen 8020",
    "addr:housenumber":"4",
    "addr:postcode":"8020",
    "addr:street":"Leitemolenstraat",
    "iso:country":"BE",
    "sg:address":"Leitemolenstraat 4",
    "sg:city":"Oostkamp (ruddervoorde)",
    "sg:classifiers":[
        {
            "category":"Airport",
            "subcategory":"International",
            "type":"Transportation"
        }
    ],
    "sg:phone":"+32 50 28 80 80",
    "sg:postcode":"8020",
    "sg:province":"West-Vlaanderen",
    "sg:tags":[
        "-",
        "transport"
    ],
    "wof:name":"Verscheure Michel Transport",
    "wof:placetype":"venue"
},
  "geometry": {"coordinates":[3.2152149677,51.1002388],"type":"Point"}
}