{
  "type": "Feature",
  "properties": {
    "addr:full":"Av. Dr. Edmond Cordier 27 Oudergem/auderghem Bruxelles-Capitale 1160",
    "addr:housenumber":"27",
    "addr:postcode":"1160",
    "addr:street":"Av. Dr. Edmond Cordier;/",
    "iso:country":"BE",
    "sg:address":"Av. Dr. Edmond Cordier 27",
    "sg:city":"Oudergem/auderghem",
    "sg:orig_category":"M\u00e9decins and sp\u00e9cialistes",
    "sg:phone":"+32 2 672 40 57",
    "sg:postcode":"1160",
    "sg:province":"Bruxelles-Capitale",
    "wof:name":"Charles Chapelle",
    "wof:placetype":"venue"
},
  "geometry": {"coordinates":[4.4120578766,50.8220024109],"type":"Point"}
}