{
  "type": "Feature",
  "properties": {
    "addr:full":"Faubourg De Bruxelles 17 - 19 Charleroi Hainaut 6041",
    "addr:housenumber":"17 19",
    "addr:postcode":"6041",
    "addr:street":"Faubourg De Bruxelles;Hainaut",
    "iso:country":"BE",
    "sg:address":"Faubourg De Bruxelles 17 - 19",
    "sg:city":"Charleroi",
    "sg:orig_category":"R\u00e9parations d'appareils \u00e9lectrom\u00e9nagers. Electrom\u00e9nager, t\u00e9l\u00e9visions and radios",
    "sg:phone":"+32 71 35 56 40",
    "sg:postcode":"6041",
    "sg:province":"Hainaut",
    "wof:name":"Maison Rousseau",
    "wof:placetype":"venue"
},
  "geometry": {"coordinates":[4.4314317703,50.4685935974],"type":"Point"}
}