{
  "type": "Feature",
  "properties": {
    "iso:country":"BE",
    "sg:address":"Alkerweg 1",
    "sg:city":"Sint-truiden",
    "sg:classifiers":[
        {
            "category":"Personal",
            "subcategory":"Beauty Salon",
            "type":"Services"
        }
    ],
    "sg:phone":"+32 11 67 36 55",
    "sg:postcode":"3800",
    "sg:province":"Limburg",
    "sg:tags":[
        "de",
        "coiffure"
    ],
    "wof:name":"Coiffure Paulette",
    "wof:placetype":"venue"
},
  "geometry": {"coordinates":[5.227853775,50.8427772522],"type":"Point"}
}