{
  "type": "Feature",
  "properties": {
    "iso:country":"BE",
    "sg:address":"Beekhoek 41",
    "sg:city":"Geel",
    "sg:classifiers":[
        {
            "category":"Professional",
            "subcategory":"Engineering",
            "type":"Services"
        }
    ],
    "sg:phone":"+32 14 58 82 19",
    "sg:postcode":"2440",
    "sg:province":"Antwerpen",
    "sg:tags":[
        "civil",
        "offices-"
    ],
    "wof:name":"Forte Bvba",
    "wof:placetype":"venue"
},
  "geometry": {"coordinates":[4.987071991,51.2081451416],"type":"Point"}
}