{
  "type": "Feature",
  "properties": {
    "addr:full":"Maastrichterstraat 32 Hasselt Limburg 3500",
    "addr:housenumber":"32",
    "addr:postcode":"3500",
    "addr:street":"Maastrichterstraat",
    "iso:country":"BE",
    "sg:address":"Maastrichterstraat 32",
    "sg:city":"Hasselt",
    "sg:classifiers":[
        {
            "category":"Shopping",
            "subcategory":"Clothing, Apparel, & Fashions",
            "type":"Retail Goods"
        }
    ],
    "sg:phone":"+32 11 22 15 30",
    "sg:postcode":"3500",
    "sg:province":"Limburg",
    "sg:tags":[
        "-",
        "clothing",
        "child"
    ],
    "wof:name":"Papillon",
    "wof:placetype":"venue"
},
  "geometry": {"coordinates":[5.3391690254,50.9295883179],"type":"Point"}
}