{
  "type": "Feature",
  "properties": {
    "iso:country":"BE",
    "sg:address":"Harmoniestraat 134",
    "sg:city":"Antwerpen",
    "sg:orig_category":"M\u00e9decins and sp\u00e9cialistes",
    "sg:phone":"+32 3 238 68 28",
    "sg:postcode":"2018",
    "sg:province":"Antwerpen",
    "wof:name":"P. De Bom",
    "wof:placetype":"venue"
},
  "geometry": {"coordinates":[4.4080491066,51.1998672485],"type":"Point"}
}