{
  "type": "Feature",
  "properties": {
    "addr:full":"Vrasenestraat 47e Beveren (beveren-waas) Oost-Vlaanderen 9120",
    "addr:housenumber":"47e",
    "addr:postcode":"9120",
    "addr:street":"Vrasenestraat;Oost-Vlaanderen",
    "iso:country":"BE",
    "sg:address":"Vrasenestraat 47e",
    "sg:city":"Beveren (beveren-waas)",
    "sg:classifiers":[
        {
            "category":"Shopping",
            "subcategory":"Clothing, Apparel, & Fashions",
            "type":"Retail Goods"
        }
    ],
    "sg:phone":"+32 3 775 49 80",
    "sg:postcode":"9120",
    "sg:province":"Oost-Vlaanderen",
    "sg:tags":[
        "lady",
        "clothing",
        "-"
    ],
    "wof:name":"Kid'z",
    "wof:placetype":"venue"
},
  "geometry": {"coordinates":[4.2543039322,51.2135429382],"type":"Point"}
}