{
  "type": "Feature",
  "properties": {
    "iso:country":"BE",
    "sg:address":"Rue Houpi\u00e8re 249bis",
    "sg:city":"Cerfontaine (senzeille)",
    "sg:classifiers":[
        {
            "category":"Building & Trades",
            "subcategory":"Construction",
            "type":"Services"
        }
    ],
    "sg:phone":"+32 71 64 42 30",
    "sg:postcode":"5630",
    "sg:province":"Namur",
    "sg:tags":[
        "carpenter"
    ],
    "wof:name":"Menuiserie Eb\u00e9nisterie La Lorraine Sprl",
    "wof:placetype":"venue"
},
  "geometry": {"coordinates":[4.4662051201,50.1784515381],"type":"Point"}
}