{
  "type": "Feature",
  "properties": {
    "addr:full":"Rue Pont-saint-nicolas 1 Li\u00c8ge Li\u00e8ge 4020",
    "addr:housenumber":"1",
    "addr:postcode":"4020",
    "addr:street":"Rue Pont-Saint-Nicolas",
    "iso:country":"BE",
    "sg:address":"Rue Pont-saint-nicolas 1",
    "sg:city":"Li\u00c8ge",
    "sg:orig_category":"Brood, gebak and snoepgoed",
    "sg:phone":"+32 4 343 59 76",
    "sg:postcode":"4020",
    "sg:province":"Li\u00e8ge",
    "wof:name":"Point Chaud",
    "wof:placetype":"venue"
},
  "geometry": {"coordinates":[5.581802845,50.6412315369],"type":"Point"}
}