{
  "type": "Feature",
  "properties": {
    "addr:full":"Stationsstraat 90 Houthalen-helchteren (houthalen) Limburg 3530",
    "addr:housenumber":"90",
    "addr:postcode":"3530",
    "addr:street":"Stationsstraat",
    "iso:country":"BE",
    "sg:address":"Stationsstraat 90",
    "sg:city":"Houthalen-helchteren (houthalen)",
    "sg:classifiers":[
        {
            "category":"Retail",
            "subcategory":"Veterinary Services",
            "type":"Services"
        }
    ],
    "sg:phone":"+32 11 52 45 64",
    "sg:postcode":"3530",
    "sg:province":"Limburg",
    "sg:tags":[
        "veterinarian"
    ],
    "wof:name":"Timmers H",
    "wof:placetype":"venue"
},
  "geometry": {"coordinates":[5.3566551208,51.0266532898],"type":"Point"}
}