{
  "type": "Feature",
  "properties": {
    "iso:country":"BE",
    "sg:address":"Stendrich 154",
    "sg:city":"Eupen/eupen",
    "sg:orig_category":"Glaszetten and glaswerk Serres and speciale beglazing",
    "sg:phone":"+32 87 55 52 83",
    "sg:postcode":"4700",
    "sg:province":"Li\u00e8ge",
    "wof:name":"Demir",
    "wof:placetype":"venue"
},
  "geometry": {"coordinates":[6.0150570869,50.6242828369],"type":"Point"}
}