{
  "type": "Feature",
  "properties": {
    "iso:country":"BE",
    "sg:address":"Langestraat 20",
    "sg:city":"Zele",
    "sg:orig_category":"Boucheries",
    "sg:phone":"+32 52 45 27 26",
    "sg:postcode":"9240",
    "sg:province":"Oost-Vlaanderen",
    "wof:name":"Steven Beirens",
    "wof:placetype":"venue"
},
  "geometry": {"coordinates":[4.0349311829,51.065448761],"type":"Point"}
}