{
  "type": "Feature",
  "properties": {
    "addr:full":"Rue Du Brul\u00e9 1 Jemeppe-sur-sambre Namur 5190",
    "addr:housenumber":"1",
    "addr:postcode":"5190",
    "addr:street":"Rue Du Brule\u0301",
    "iso:country":"BE",
    "sg:address":"Rue Du Brul\u00e9 1",
    "sg:city":"Jemeppe-sur-sambre",
    "sg:classifiers":[
        {
            "category":"Real Estate",
            "subcategory":"Surveying",
            "type":"Services"
        }
    ],
    "sg:phone":"+32 71 78 80 49",
    "sg:postcode":"5190",
    "sg:province":"Namur",
    "sg:tags":[
        "surveyor",
        "land"
    ],
    "wof:name":"Quairiat Ch",
    "wof:placetype":"venue"
},
  "geometry": {"coordinates":[4.6586909294,50.4531478882],"type":"Point"}
}