{
  "type": "Feature",
  "properties": {
    "iso:country":"BE",
    "sg:address":"Avenue De La Couture 12",
    "sg:city":"Thuin",
    "sg:classifiers":[
        {
            "category":"Shopping",
            "subcategory":"Clothing, Apparel, & Fashions",
            "type":"Retail Goods"
        }
    ],
    "sg:phone":"+32 71 59 33 24",
    "sg:postcode":"6530",
    "sg:province":"Hainaut",
    "sg:tags":[
        "uniform"
    ],
    "wof:name":"Boite \u00e0 Couture",
    "wof:placetype":"venue"
},
  "geometry": {"coordinates":[4.2793269157,50.3437805176],"type":"Point"}
}