{
  "type": "Feature",
  "properties": {
    "iso:country":"BE",
    "sg:address":"Hoeksken 136",
    "sg:city":"Sint-lievens-houtem",
    "sg:classifiers":[
        {
            "category":"Personal",
            "subcategory":"Nail Salon",
            "type":"Services"
        }
    ],
    "sg:phone":"+32 495 77 67 27",
    "sg:postcode":"9520",
    "sg:province":"Oost-Vlaanderen",
    "sg:tags":[
        "pedicure"
    ],
    "wof:name":"Becaus T",
    "wof:placetype":"venue"
},
  "geometry": {"coordinates":[3.8427228928,50.9175834656],"type":"Point"}
}