{
  "type": "Feature",
  "properties": {
    "addr:full":"Rue De La Tour 7 Namur Namur 5000",
    "addr:housenumber":"7",
    "addr:postcode":"5000",
    "addr:street":"Rue De La Tour",
    "iso:country":"BE",
    "sg:address":"Rue De La Tour 7",
    "sg:city":"Namur",
    "sg:classifiers":[
        {
            "category":"Professional",
            "subcategory":"Secretarial Services",
            "type":"Services"
        }
    ],
    "sg:phone":"+32 81 22 93 91",
    "sg:postcode":"5000",
    "sg:province":"Namur",
    "sg:tags":[
        "firm"
    ],
    "wof:name":"Magnette",
    "wof:placetype":"venue"
},
  "geometry": {"coordinates":[4.8682489395,50.4634361267],"type":"Point"}
}