{
  "type": "Feature",
  "properties": {
    "iso:country":"BE",
    "sg:address":"Lichterveldestraat 33",
    "sg:city":"Kortemark",
    "sg:classifiers":[
        {
            "category":"Personal",
            "subcategory":"Nail Salon",
            "type":"Services"
        }
    ],
    "sg:phone":"+32 51 57 08 46",
    "sg:postcode":"8610",
    "sg:province":"West-Vlaanderen",
    "sg:tags":[
        "screw",
        "cutting"
    ],
    "wof:name":"Vanclooster Bvba",
    "wof:placetype":"venue"
},
  "geometry": {"coordinates":[3.0473029613,51.0285644531],"type":"Point"}
}