{
  "type": "Feature",
  "properties": {
    "addr:full":"Rue Ten-eycken 25 Plombi\u00e8res (montzen) Li\u00e8ge 4850",
    "addr:housenumber":"25",
    "addr:postcode":"4850",
    "addr:street":"Rue Ten-Eycken",
    "iso:country":"BE",
    "sg:address":"Rue Ten-eycken 25",
    "sg:city":"Plombi\u00e8res (montzen)",
    "sg:classifiers":[
        {
            "category":"Airport",
            "subcategory":"International",
            "type":"Transportation"
        }
    ],
    "sg:phone":"+32 87 33 72 96",
    "sg:postcode":"4850",
    "sg:province":"Li\u00e8ge",
    "sg:tags":[
        "-",
        "transport"
    ],
    "wof:name":"Transjohn",
    "wof:placetype":"venue"
},
  "geometry": {"coordinates":[5.9589571953,50.7254753113],"type":"Point"}
}