{
  "type": "Feature",
  "properties": {
    "addr:full":"Rue Fran\u00c7ois Gay 356 Sint-pieters-woluwe/woluwe-saint-pierre Bruxelles-Capitale 1150",
    "addr:housenumber":"356",
    "addr:postcode":"1150",
    "addr:street":"Rue Franc\u0327Ois Gay;/",
    "iso:country":"BE",
    "sg:address":"Rue Fran\u00c7ois Gay 356",
    "sg:city":"Sint-pieters-woluwe/woluwe-saint-pierre",
    "sg:classifiers":[
        {
            "category":"Cafe",
            "type":"Food & Drink"
        }
    ],
    "sg:phone":"+32 2 772 22 57",
    "sg:postcode":"1150",
    "sg:province":"Bruxelles-Capitale",
    "sg:tags":[
        "caf\u00e9s"
    ],
    "wof:name":"Bergent",
    "wof:placetype":"venue"
},
  "geometry": {"coordinates":[4.4157800674,50.8373718262],"type":"Point"}
}