{
  "type": "Feature",
  "properties": {
    "addr:full":"Kleine Molenstraat 6 Brugge (dudzele) West-Vlaanderen 8380",
    "addr:housenumber":"6",
    "addr:postcode":"8380",
    "addr:street":"Kleine Molenstraat",
    "iso:country":"BE",
    "sg:address":"Kleine Molenstraat 6",
    "sg:city":"Brugge (dudzele)",
    "sg:classifiers":[
        {
            "category":"Retail",
            "subcategory":"Funeral Services",
            "type":"Services"
        }
    ],
    "sg:phone":"+32 50 59 98 74",
    "sg:postcode":"8380",
    "sg:province":"West-Vlaanderen",
    "sg:tags":[
        "director"
    ],
    "wof:name":"De Brabander A",
    "wof:placetype":"venue"
},
  "geometry": {"coordinates":[3.2288448811,51.2742958069],"type":"Point"}
}