{
  "type": "Feature",
  "properties": {
    "iso:country":"BE",
    "sg:address":"Avenue Des Sorbiers 42",
    "sg:city":"Waremme",
    "sg:orig_category":"HUISBRANDOLIE",
    "sg:phone":"+32 19 32 27 96",
    "sg:postcode":"4300",
    "sg:province":"Li\u00e8ge",
    "wof:name":"Polkoszek",
    "wof:placetype":"venue"
},
  "geometry": {"coordinates":[5.2526988983,50.6890068054],"type":"Point"}
}