{
  "type": "Feature",
  "properties": {
    "iso:country":"BE",
    "sg:address":"Boelare 109",
    "sg:city":"Eeklo",
    "sg:classifiers":[
        {
            "category":"Bakery",
            "type":"Food & Drink"
        }
    ],
    "sg:phone":"+32 9 377 73 00",
    "sg:postcode":"9900",
    "sg:province":"Oost-Vlaanderen",
    "sg:tags":[
        "confectioner",
        "baker"
    ],
    "wof:name":"De Korenmaat",
    "wof:placetype":"venue"
},
  "geometry": {"coordinates":[3.564510107,51.1856040955],"type":"Point"}
}