{
  "type": "Feature",
  "properties": {
    "addr:full":"Neremsbroek 40 Tongeren (nerem) Limburg 3700",
    "addr:housenumber":"40",
    "addr:postcode":"3700",
    "addr:street":"Neremsbroek",
    "iso:country":"BE",
    "sg:address":"Neremsbroek 40",
    "sg:city":"Tongeren (nerem)",
    "sg:classifiers":[
        {
            "category":"Professional",
            "subcategory":"Art Services",
            "type":"Services"
        }
    ],
    "sg:phone":"+32 12 39 20 41",
    "sg:postcode":"3700",
    "sg:province":"Limburg",
    "sg:tags":[
        "graphic",
        "designer"
    ],
    "wof:name":"Meyers A",
    "wof:placetype":"venue"
},
  "geometry": {"coordinates":[5.4636240005,50.7807197571],"type":"Point"}
}