{
  "type": "Feature",
  "properties": {
    "iso:country":"BE",
    "sg:address":"Potaardestraat 14",
    "sg:city":"Lebbeke",
    "sg:classifiers":[
        {
            "category":"Health Services",
            "subcategory":"Health Practitioner",
            "type":"Services"
        }
    ],
    "sg:phone":"+32 478 20 36 24",
    "sg:postcode":"9280",
    "sg:province":"Oost-Vlaanderen",
    "sg:tags":[
        "physiotherapist"
    ],
    "wof:name":"Pissens Lies",
    "wof:placetype":"venue"
},
  "geometry": {"coordinates":[4.1547641754,50.9994850159],"type":"Point"}
}