{
  "type": "Feature",
  "properties": {
    "addr:full":"Schildesteenweg 75a Ranst (oelegem) Antwerpen 2520",
    "addr:housenumber":"75a",
    "addr:postcode":"2520",
    "addr:street":"Schildesteenweg",
    "iso:country":"BE",
    "sg:address":"Schildesteenweg 75a",
    "sg:city":"Ranst (oelegem)",
    "sg:classifiers":[
        {
            "category":"Sports & Exercise",
            "subcategory":"Stables",
            "type":"Entertainment"
        }
    ],
    "sg:phone":"+32 3 383 36 60",
    "sg:postcode":"2520",
    "sg:province":"Antwerpen",
    "sg:tags":[
        "riding",
        "school"
    ],
    "wof:name":"The Star Dust Ranch",
    "wof:placetype":"venue"
},
  "geometry": {"coordinates":[4.599656105,51.2172813416],"type":"Point"}
}