{
  "type": "Feature",
  "properties": {
    "addr:full":"Populierenlaan 36 Dilbeek Vlaams-Brabant 1700",
    "addr:housenumber":"36",
    "addr:postcode":"1700",
    "addr:street":"Populierenlaan",
    "iso:country":"BE",
    "sg:address":"Populierenlaan 36",
    "sg:city":"Dilbeek",
    "sg:classifiers":[
        {
            "category":"Organizations",
            "subcategory":"Professional Association",
            "type":"Services"
        }
    ],
    "sg:phone":"+32 2 567 23 60",
    "sg:postcode":"1700",
    "sg:province":"Vlaams-Brabant",
    "sg:tags":[
        "trade-union",
        "federation"
    ],
    "wof:name":"Saod-csiv",
    "wof:placetype":"venue"
},
  "geometry": {"coordinates":[4.246243,50.8526992798],"type":"Point"}
}