{
  "type": "Feature",
  "properties": {
    "addr:full":"Luikersteenweg 278 Sint-truiden Limburg 3800",
    "addr:housenumber":"278",
    "addr:postcode":"sint-truiden;3800",
    "addr:street":"Luikersteenweg",
    "iso:country":"BE",
    "sg:address":"Luikersteenweg 278",
    "sg:city":"Sint-truiden",
    "sg:orig_category":"V\u00e9hicules automobiles. Stations-service and carburants",
    "sg:phone":"+32 11 67 42 90",
    "sg:postcode":"3800",
    "sg:province":"Limburg",
    "wof:name":"Garage Merinsky",
    "wof:placetype":"venue"
},
  "geometry": {"coordinates":[5.2029700279,50.8036193848],"type":"Point"}
}