{
  "type": "Feature",
  "properties": {
    "addr:full":"Gentstraat Meulebeke West-Vlaanderen 8760",
    "addr:postcode":"8760",
    "addr:street":"Gentstraat",
    "iso:country":"BE",
    "sg:address":"Gentstraat",
    "sg:city":"Meulebeke",
    "sg:orig_category":"Non-Classified Establishments",
    "sg:phone":"+32 51 33 50 68",
    "sg:postcode":"8760",
    "sg:province":"West-Vlaanderen",
    "wof:name":"Chemo Syntha",
    "wof:placetype":"venue"
},
  "geometry": {"coordinates":[3.3356020451,50.9521141052],"type":"Point"}
}