{
  "type": "Feature",
  "properties": {
    "addr:full":"Rue Des Boissonnets 11 Chaumont-gistoux Brabant Wallon 1325",
    "addr:housenumber":"11",
    "addr:postcode":"1325",
    "addr:street":"Rue Des Boissonnets",
    "iso:country":"BE",
    "sg:address":"Rue Des Boissonnets 11",
    "sg:city":"Chaumont-gistoux",
    "sg:classifiers":[
        {
            "category":"Building & Trades",
            "subcategory":"Landscaping Services",
            "type":"Services"
        }
    ],
    "sg:phone":"+32 10 68 81 46",
    "sg:postcode":"1325",
    "sg:province":"Brabant Wallon",
    "sg:tags":[
        "forestry"
    ],
    "wof:name":"Denis J",
    "wof:placetype":"venue"
},
  "geometry": {"coordinates":[4.6855249405,50.6901435852],"type":"Point"}
}