{
  "type": "Feature",
  "properties": {
    "addr:full":"Stationsstraat 13 Wachtebeke Oost-Vlaanderen 9185",
    "addr:housenumber":"13",
    "addr:postcode":"9185",
    "addr:street":"Stationsstraat",
    "iso:country":"BE",
    "sg:address":"Stationsstraat 13",
    "sg:city":"Wachtebeke",
    "sg:orig_category":"Zuivelproducten",
    "sg:phone":"+32 9 345 08 03",
    "sg:postcode":"9185",
    "sg:province":"Oost-Vlaanderen",
    "wof:name":"Oscar Mareen",
    "wof:placetype":"venue"
},
  "geometry": {"coordinates":[3.8615050316,51.1717300415],"type":"Point"}
}