{
  "type": "Feature",
  "properties": {
    "iso:country":"BE",
    "sg:address":"Dorpstraat 163",
    "sg:city":"Bertem",
    "sg:classifiers":[
        {
            "category":"Insurance",
            "subcategory":"Insurance Agent",
            "type":"Services"
        }
    ],
    "sg:phone":"+32 16 23 40 40",
    "sg:postcode":"3060",
    "sg:province":"Vlaams-Brabant",
    "sg:tags":[
        "broker"
    ],
    "wof:name":"Verdeyen & De Brabandere",
    "wof:placetype":"venue"
},
  "geometry": {"coordinates":[4.6314358711,50.8628311157],"type":"Point"}
}