{
  "type": "Feature",
  "properties": {
    "iso:country":"BE",
    "sg:address":"Route De Limet 24",
    "sg:city":"Modave",
    "sg:orig_category":"Ordinateurs and \u00e9quipement informatique",
    "sg:phone":"+32 85 41 17 21",
    "sg:postcode":"4577",
    "sg:province":"Li\u00e8ge",
    "wof:name":"Bureau Asci",
    "wof:placetype":"venue"
},
  "geometry": {"coordinates":[5.3001742363,50.4592132568],"type":"Point"}
}