{
  "type": "Feature",
  "properties": {
    "addr:full":"Antwerpsestraat 95 Niel Antwerpen 2845",
    "addr:housenumber":"95",
    "addr:postcode":"2845",
    "addr:street":"Antwerpsestraat",
    "iso:country":"BE",
    "sg:address":"Antwerpsestraat 95",
    "sg:city":"Niel",
    "sg:classifiers":[
        {
            "category":"Banks & Credit Unions",
            "subcategory":"Investment Brokerage",
            "type":"Services"
        }
    ],
    "sg:phone":"+32 3 843 24 44",
    "sg:postcode":"2845",
    "sg:province":"Antwerpen",
    "sg:tags":[
        "jean",
        "casual",
        "wear"
    ],
    "wof:name":"Cathys Boetiek",
    "wof:placetype":"venue"
},
  "geometry": {"coordinates":[4.3309998512,51.1096763611],"type":"Point"}
}