{
  "type": "Feature",
  "properties": {
    "addr:full":"Zuidervest 9 Peer Limburg 3990",
    "addr:housenumber":"9",
    "addr:postcode":"3990",
    "addr:street":"Zuidervest",
    "iso:country":"BE",
    "sg:address":"Zuidervest 9",
    "sg:city":"Peer",
    "sg:classifiers":[
        {
            "category":"Fast Food",
            "type":"Food & Drink"
        }
    ],
    "sg:phone":"+32 11 63 27 99",
    "sg:postcode":"3990",
    "sg:province":"Limburg",
    "sg:tags":[
        "meeneem",
        "restaurant"
    ],
    "wof:name":"Pizzeria Franco",
    "wof:placetype":"venue"
},
  "geometry": {"coordinates":[5.4760341644,51.0809135437],"type":"Point"}
}