{
  "type": "Feature",
  "properties": {
    "iso:country":"BE",
    "sg:address":"Ahornbomenlaan 51",
    "sg:city":"Kampenhout",
    "sg:classifiers":[
        {
            "category":"Wholesale",
            "subcategory":"Vending Machines",
            "type":"Manufacturing & Wholesale Goods"
        }
    ],
    "sg:phone":"+32 16 65 71 68",
    "sg:postcode":"1910",
    "sg:province":"Vlaams-Brabant",
    "sg:tags":[
        "strip",
        "metal",
        "system",
        "treatment"
    ],
    "wof:name":"A. Janssens B.v.b.a.",
    "wof:placetype":"venue"
},
  "geometry": {"coordinates":[4.5556468964,50.9319953918],"type":"Point"}
}