{
  "type": "Feature",
  "properties": {
    "addr:full":"Rue Des Villas 67 Hastiere Namur 5540",
    "addr:housenumber":"67",
    "addr:postcode":"5540",
    "addr:street":"Rue Des Villas;Namur",
    "iso:country":"BE",
    "sg:address":"Rue Des Villas 67",
    "sg:city":"Hastiere",
    "sg:orig_category":"Installation \u00e9lectrique r\u00e9sidentielle",
    "sg:phone":"+32 82 64 40 14",
    "sg:postcode":"5540",
    "sg:province":"Namur",
    "wof:name":"Philippe Willeme",
    "wof:placetype":"venue"
},
  "geometry": {"coordinates":[4.8639068604,50.2035522461],"type":"Point"}
}