{
  "type": "Feature",
  "properties": {
    "addr:full":"Sint-truidersteenweg 465 Hasselt Limburg 3500",
    "addr:housenumber":"465",
    "addr:postcode":"3500",
    "addr:street":"Sint-Truidersteenweg",
    "iso:country":"BE",
    "sg:address":"Sint-truidersteenweg 465",
    "sg:city":"Hasselt",
    "sg:orig_category":"Dameskledingzaken",
    "sg:phone":"+32 11 28 32 17",
    "sg:postcode":"3500",
    "sg:province":"Limburg",
    "wof:name":"Huis Look",
    "wof:placetype":"venue"
},
  "geometry": {"coordinates":[5.327709198,50.9188766479],"type":"Point"}
}