{
  "type": "Feature",
  "properties": {
    "addr:full":"Hendrik Consciencelaan 15 Mortsel Antwerpen 2640",
    "addr:housenumber":"15",
    "addr:postcode":"2640",
    "addr:street":"Hendrik Consciencelaan",
    "iso:country":"BE",
    "sg:address":"Hendrik Consciencelaan 15",
    "sg:city":"Mortsel",
    "sg:classifiers":[
        {
            "category":"Building & Trades",
            "subcategory":"Electrical",
            "type":"Services"
        }
    ],
    "sg:phone":"+32 3 449 55 35",
    "sg:postcode":"2640",
    "sg:province":"Antwerpen",
    "sg:tags":[
        "electric",
        "-",
        "housewiring",
        "contractor"
    ],
    "wof:name":"Pattijn R Bvba",
    "wof:placetype":"venue"
},
  "geometry": {"coordinates":[4.4461240768,51.1734962463],"type":"Point"}
}