{
  "type": "Feature",
  "properties": {
    "iso:country":"BE",
    "sg:address":"Evarist Carpentierlaan 28",
    "sg:city":"Kortrijk",
    "sg:orig_category":"Instituts de beaut\u00e9",
    "sg:phone":"+32 56 35 99 23",
    "sg:postcode":"8500",
    "sg:province":"West-Vlaanderen",
    "wof:name":"Georgette Staelraeve",
    "wof:placetype":"venue"
},
  "geometry": {"coordinates":[3.2706339359,50.8405952454],"type":"Point"}
}