{
  "type": "Feature",
  "properties": {
    "addr:full":"Kerkstraat 19 Lummen Limburg 3560",
    "addr:housenumber":"19",
    "addr:postcode":"3560",
    "addr:street":"Kerkstraat",
    "iso:country":"BE",
    "sg:address":"Kerkstraat 19",
    "sg:city":"Lummen",
    "sg:orig_category":"Banken and kredietinstellingen",
    "sg:phone":"+32 13 52 19 15",
    "sg:postcode":"3560",
    "sg:province":"Limburg",
    "wof:name":"Kbc",
    "wof:placetype":"venue"
},
  "geometry": {"coordinates":[5.1895618439,50.9858283997],"type":"Point"}
}