{
  "type": "Feature",
  "properties": {
    "addr:full":"Avenue De Tervueren 149 Bruxelles (woluwe-saint-pierre) Bruxelles-Capitale 1150",
    "addr:housenumber":"149",
    "addr:postcode":"1150",
    "addr:street":"Avenue De Tervueren",
    "iso:country":"BE",
    "sg:address":"Avenue De Tervueren 149",
    "sg:city":"Bruxelles (woluwe-saint-pierre)",
    "sg:classifiers":[
        {
            "category":"Organizations",
            "subcategory":"Professional Association",
            "type":"Services"
        }
    ],
    "sg:phone":"+32 2 741 86 60",
    "sg:postcode":"1150",
    "sg:province":"Bruxelles-Capitale",
    "sg:tags":[
        "trade-union",
        "federation"
    ],
    "wof:name":"Epca",
    "wof:placetype":"venue"
},
  "geometry": {"coordinates":[4.4061560631,50.8374443054],"type":"Point"}
}