{
  "type": "Feature",
  "properties": {
    "iso:country":"BE",
    "sg:address":"Kartuizersvest 52",
    "sg:city":"Lier",
    "sg:classifiers":[
        {
            "category":"Shopping",
            "subcategory":"Gifts & Souvenirs",
            "type":"Retail Goods"
        }
    ],
    "sg:phone":"+32 3 489 30 09",
    "sg:postcode":"2500",
    "sg:province":"Antwerpen",
    "sg:tags":[
        "-"
    ],
    "wof:name":"Atelier Gigi",
    "wof:placetype":"venue"
},
  "geometry": {"coordinates":[4.5694379807,51.1340255737],"type":"Point"}
}