{
  "type": "Feature",
  "properties": {
    "iso:country":"BE",
    "sg:address":"Vennestraat 260",
    "sg:city":"Genk",
    "sg:classifiers":[
        {
            "category":"Professional",
            "subcategory":"Computer Services",
            "type":"Services"
        }
    ],
    "sg:phone":"+32 89 35 31 24",
    "sg:postcode":"3600",
    "sg:province":"Limburg",
    "sg:tags":[
        "-",
        "processing",
        "data",
        "software"
    ],
    "wof:name":"Fiscalc-kluwer Software",
    "wof:placetype":"venue"
},
  "geometry": {"coordinates":[5.4805488586,50.9665565491],"type":"Point"}
}