{
  "type": "Feature",
  "properties": {
    "addr:full":"Watergrasstraat Genk Limburg 3600",
    "addr:postcode":"3600",
    "addr:street":"Watergrasstraat;Limburg",
    "iso:country":"BE",
    "sg:address":"Watergrasstraat",
    "sg:city":"Genk",
    "sg:orig_category":"Bloemen and planten",
    "sg:phone":"+32 479 59 03 98",
    "sg:postcode":"3600",
    "sg:province":"Limburg",
    "wof:name":"Letizia",
    "wof:placetype":"venue"
},
  "geometry": {"coordinates":[5.5175700188,50.9944000244],"type":"Point"}
}