{
  "type": "Feature",
  "properties": {
    "addr:full":"Geraardsbergsestraat 120 Dilbeek Vlaams-Brabant 1703",
    "addr:housenumber":"120",
    "addr:postcode":"1703",
    "addr:street":"Geraardsbergsestraat",
    "iso:country":"BE",
    "sg:address":"Geraardsbergsestraat 120",
    "sg:city":"Dilbeek",
    "sg:orig_category":"Installatie van houten of kunststof schrijnwerk Installatie van metalen schrijnwerk MEUBELONTWERP AN",
    "sg:phone":"+32 2 569 20 46",
    "sg:postcode":"1703",
    "sg:province":"Vlaams-Brabant",
    "wof:name":"Etienne Walravens",
    "wof:placetype":"venue"
},
  "geometry": {"coordinates":[4.1915969849,50.8337059021],"type":"Point"}
}