{
  "type": "Feature",
  "properties": {
    "addr:full":"Steenweg Op Asse 84bb Merchtem Vlaams-Brabant 1785",
    "addr:housenumber":"84bb",
    "addr:postcode":"1785",
    "addr:street":"Steenweg Op Asse",
    "iso:country":"BE",
    "sg:address":"Steenweg Op Asse 84bb",
    "sg:city":"Merchtem",
    "sg:orig_category":"Artsen and specialisten",
    "sg:phone":"+32 2 452 37 00",
    "sg:postcode":"1785",
    "sg:province":"Vlaams-Brabant",
    "wof:name":"Lieven Stassijns",
    "wof:placetype":"venue"
},
  "geometry": {"coordinates":[4.2475571632,50.9240875244],"type":"Point"}
}