{
  "type": "Feature",
  "properties": {
    "addr:full":"Kraaistraat 2 Heuvelland West-Vlaanderen 8953",
    "addr:housenumber":"2",
    "addr:postcode":"8953",
    "addr:street":"Kraaistraat",
    "iso:country":"BE",
    "sg:address":"Kraaistraat 2",
    "sg:city":"Heuvelland",
    "sg:orig_category":"Rundveehouders Varkenskwekers",
    "sg:phone":"+32 57 44 48 97",
    "sg:postcode":"8953",
    "sg:province":"West-Vlaanderen",
    "wof:name":"Fernand Dauchy",
    "wof:placetype":"venue"
},
  "geometry": {"coordinates":[2.9113121033,50.7836227417],"type":"Point"}
}