{
  "type": "Feature",
  "properties": {
    "iso:country":"BE",
    "sg:address":"Bommelbekestraat 38",
    "sg:city":"Brugge",
    "sg:orig_category":"Epiceries",
    "sg:phone":"+32 50 33 55 99",
    "sg:postcode":"8000",
    "sg:province":"West-Vlaanderen",
    "wof:name":"Fernand Callant",
    "wof:placetype":"venue"
},
  "geometry": {"coordinates":[3.2347660065,51.2310562134],"type":"Point"}
}