{
  "type": "Feature",
  "properties": {
    "addr:full":"Fortuinstraat 17 Brugge (sint-kruis) West-Vlaanderen 8310",
    "addr:housenumber":"17",
    "addr:postcode":"8310",
    "addr:street":"Fortuinstraat",
    "iso:country":"BE",
    "sg:address":"Fortuinstraat 17",
    "sg:city":"Brugge (sint-kruis)",
    "sg:classifiers":[
        {
            "category":"Banks & Credit Unions",
            "subcategory":"Investment Brokerage",
            "type":"Services"
        }
    ],
    "sg:phone":"+32 50 37 53 28",
    "sg:postcode":"8310",
    "sg:province":"West-Vlaanderen",
    "sg:tags":[
        "printing",
        "-"
    ],
    "wof:name":"Van Loo Drukwerken",
    "wof:placetype":"venue"
},
  "geometry": {"coordinates":[3.2535009384,51.2082939148],"type":"Point"}
}