{
  "type": "Feature",
  "properties": {
    "iso:country":"BE",
    "sg:address":"Mechelsesteenweg 43",
    "sg:city":"Sint-katelijne-waver",
    "sg:classifiers":[
        {
            "category":"Autos & Motor Vehicles",
            "subcategory":"Fuel & Gas Station",
            "type":"Retail Goods"
        }
    ],
    "sg:phone":"+32 15 31 10 36",
    "sg:postcode":"2860",
    "sg:province":"Antwerpen",
    "sg:tags":[
        "stations-service",
        "carburants"
    ],
    "wof:name":"Texaco",
    "wof:placetype":"venue"
},
  "geometry": {"coordinates":[4.5292959213,51.0625419617],"type":"Point"}
}