{
  "type": "Feature",
  "properties": {
    "iso:country":"BE",
    "sg:address":"Chauss\u00c9e Brunehaut 37",
    "sg:city":"Qu\u00c9vy",
    "sg:classifiers":[
        {
            "category":"Insurance",
            "subcategory":"Insurance Agent",
            "type":"Services"
        }
    ],
    "sg:phone":"+32 65 58 68 06",
    "sg:postcode":"7041",
    "sg:province":"Hainaut",
    "sg:tags":[
        "verzekeringsmakelaars",
        "expert"
    ],
    "wof:name":"Fosinvest",
    "wof:placetype":"venue"
},
  "geometry": {"coordinates":[4.0337409973,50.3735389709],"type":"Point"}
}