{
  "type": "Feature",
  "properties": {
    "addr:full":"Rue Des Deux Eglises 73 Bruxelles (saint-josse-ten-noode) Bruxelles-Capitale 1210",
    "addr:housenumber":"73",
    "addr:postcode":"1210",
    "addr:street":"Rue Des Deux Eglises",
    "iso:country":"BE",
    "sg:address":"Rue Des Deux Eglises 73",
    "sg:city":"Bruxelles (saint-josse-ten-noode)",
    "sg:classifiers":[
        {
            "category":"Cafe",
            "type":"Food & Drink"
        }
    ],
    "sg:phone":"+32 2 230 71 07",
    "sg:postcode":"1210",
    "sg:province":"Bruxelles-Capitale",
    "sg:tags":[
        "snack-bars"
    ],
    "wof:name":"Sidonie Cie Sc",
    "wof:placetype":"venue"
},
  "geometry": {"coordinates":[4.3736300468,50.8478622437],"type":"Point"}
}