{
  "type": "Feature",
  "properties": {
    "addr:full":"Roeselarestraat 195 Wevelgem West-Vlaanderen 8560",
    "addr:housenumber":"195",
    "addr:postcode":"8560",
    "addr:street":"Roeselarestraat",
    "iso:country":"BE",
    "sg:address":"Roeselarestraat 195",
    "sg:city":"Wevelgem",
    "sg:classifiers":[
        {
            "category":"Shopping",
            "subcategory":"Stationery & Office Supplies",
            "type":"Retail Goods"
        }
    ],
    "sg:phone":"+32 56 42 72 24",
    "sg:postcode":"8560",
    "sg:province":"West-Vlaanderen",
    "sg:tags":[
        "-"
    ],
    "wof:name":"Buropa",
    "wof:placetype":"venue"
},
  "geometry": {"coordinates":[3.1788859367,50.8164787292],"type":"Point"}
}