{
  "type": "Feature",
  "properties": {
    "addr:full":"Kerkhofstraat 67 Avelgem West-Vlaanderen 8580",
    "addr:housenumber":"67",
    "addr:postcode":"8580",
    "addr:street":"Kerkhofstraat",
    "iso:country":"BE",
    "sg:address":"Kerkhofstraat 67",
    "sg:city":"Avelgem",
    "sg:orig_category":"Artsen and specialisten",
    "sg:phone":"+32 56 64 47 00",
    "sg:postcode":"8580",
    "sg:province":"West-Vlaanderen",
    "wof:name":"Isabel Lietaert",
    "wof:placetype":"venue"
},
  "geometry": {"coordinates":[3.4479939938,50.779094696],"type":"Point"}
}