{
  "type": "Feature",
  "properties": {
    "iso:country":"BE",
    "sg:address":"Gasthuisstraat 31b1",
    "sg:city":"Brussel/bruxelles",
    "sg:orig_category":"Sociale secretariaten",
    "sg:phone":"+32 2 289 68 02",
    "sg:postcode":"1000",
    "sg:province":"Bruxelles-Capitale",
    "wof:name":"Sociaal Verzekeringsfonds",
    "wof:placetype":"venue"
},
  "geometry": {"coordinates":[4.3536272049,50.8438682556],"type":"Point"}
}