{
  "type": "Feature",
  "properties": {
    "addr:full":"Groenstraat 40 Hoeselt Limburg 3730",
    "addr:housenumber":"40",
    "addr:postcode":"3730",
    "addr:street":"Groenstraat",
    "iso:country":"BE",
    "sg:address":"Groenstraat 40",
    "sg:city":"Hoeselt",
    "sg:classifiers":[
        {
            "category":"Personal",
            "subcategory":"Beauty Salon",
            "type":"Services"
        }
    ],
    "sg:phone":"+32 89 24 54 52",
    "sg:postcode":"3730",
    "sg:province":"Limburg",
    "sg:tags":[
        "lady",
        "-",
        "hairdressing"
    ],
    "wof:name":"Anita Hairstudio",
    "wof:placetype":"venue"
},
  "geometry": {"coordinates":[5.4789628983,50.8625869751],"type":"Point"}
}