{
  "type": "Feature",
  "properties": {
    "addr:full":"Beernegemstraat 10 Tielt West-Vlaanderen 8700",
    "addr:housenumber":"10",
    "addr:postcode":"8700",
    "addr:street":"Beernegemstraat",
    "iso:country":"BE",
    "sg:address":"Beernegemstraat 10",
    "sg:city":"Tielt",
    "sg:orig_category":"Hoger onderwijs",
    "sg:phone":"+32 51 40 02 40",
    "sg:postcode":"8700",
    "sg:province":"West-Vlaanderen",
    "wof:name":"Katholieke Hogeschool",
    "wof:placetype":"venue"
},
  "geometry": {"coordinates":[3.3315579891,50.9958305359],"type":"Point"}
}