{
  "type": "Feature",
  "properties": {
    "addr:full":"Bondgenotenlaan 22 Leuven Vlaams-Brabant 3000",
    "addr:housenumber":"22",
    "addr:postcode":"3000",
    "addr:street":"Bondgenotenlaan",
    "iso:country":"BE",
    "sg:address":"Bondgenotenlaan 22",
    "sg:city":"Leuven",
    "sg:classifiers":[
        {
            "category":"Insurance",
            "subcategory":"Life Insurance",
            "type":"Services"
        }
    ],
    "sg:phone":"+32 16 22 46 60",
    "sg:postcode":"3000",
    "sg:province":"Vlaams-Brabant",
    "sg:tags":[
        "assurance"
    ],
    "wof:name":"Fa. Rondou & Zoon",
    "wof:placetype":"venue"
},
  "geometry": {"coordinates":[4.7047052383,50.8794136047],"type":"Point"}
}