{
  "type": "Feature",
  "properties": {
    "addr:full":"Rue Du March\u00e9 Aux Herbes 52 Bruxelles Bruxelles-Capitale 1000",
    "addr:housenumber":"52",
    "addr:postcode":"1000",
    "addr:street":"Rue Du Marche\u0301 Aux Herbes",
    "iso:country":"BE",
    "sg:address":"Rue Du March\u00e9 Aux Herbes 52",
    "sg:city":"Bruxelles",
    "sg:classifiers":[
        {
            "category":"Shopping",
            "subcategory":"Gifts & Souvenirs",
            "type":"Retail Goods"
        }
    ],
    "sg:phone":"+32 2 511 36 30",
    "sg:postcode":"1000",
    "sg:province":"Bruxelles-Capitale",
    "sg:tags":[
        "-"
    ],
    "wof:name":"Euroline",
    "wof:placetype":"venue"
},
  "geometry": {"coordinates":[4.3529348373,50.8474159241],"type":"Point"}
}