{
  "type": "Feature",
  "properties": {
    "iso:country":"BE",
    "sg:address":"Clarissenstraat 31c",
    "sg:city":"Gent",
    "sg:classifiers":[
        {
            "category":"Building & Trades",
            "subcategory":"Landscaping Services",
            "type":"Services"
        }
    ],
    "sg:phone":"+32 9 223 31 25",
    "sg:postcode":"9000",
    "sg:province":"Oost-Vlaanderen",
    "sg:tags":[
        "gardening",
        "garden",
        "maintenance"
    ],
    "wof:name":"Goubau A",
    "wof:placetype":"venue"
},
  "geometry": {"coordinates":[3.7346119881,51.0437965393],"type":"Point"}
}