{
  "type": "Feature",
  "properties": {
    "iso:country":"BE",
    "sg:address":"Vuileseulestraat 20",
    "sg:city":"Poperinge",
    "sg:orig_category":"Eleveurs and marchands de porcs. Eleveurs de volaille",
    "sg:phone":"+32 57 38 81 89",
    "sg:postcode":"8978",
    "sg:province":"West-Vlaanderen",
    "wof:name":"Ivan De Baene",
    "wof:placetype":"venue"
},
  "geometry": {"coordinates":[2.6663401127,50.8371963501],"type":"Point"}
}