{
  "type": "Feature",
  "properties": {
    "addr:full":"Rue G\u00c9n\u00c9ral Jourdan 7 Arlon Luxembourg 6706",
    "addr:housenumber":"7",
    "addr:postcode":"6706",
    "addr:street":"Rue Ge\u0301Ne\u0301Ral Jourdan",
    "iso:country":"BE",
    "sg:address":"Rue G\u00c9n\u00c9ral Jourdan 7",
    "sg:city":"Arlon",
    "sg:orig_category":"Installation de menuiserie m\u00e9tallique. Installation de menuiserie en bois and plastique",
    "sg:phone":"+32 63 22 84 55",
    "sg:postcode":"6706",
    "sg:province":"Luxembourg",
    "wof:name":"Ch\u00c2ssis Confort Lux",
    "wof:placetype":"venue"
},
  "geometry": {"coordinates":[5.8697757721,49.6491928101],"type":"Point"}
}