{
  "type": "Feature",
  "properties": {
    "addr:full":"Assesteenweg 11 Asse Vlaams-Brabant 1730",
    "addr:housenumber":"11",
    "addr:postcode":"1730",
    "addr:street":"Assesteenweg",
    "iso:country":"BE",
    "sg:address":"Assesteenweg 11",
    "sg:city":"Asse",
    "sg:orig_category":"Apparatus, Containers, Tanks, Boilers Of Plastic",
    "sg:phone":"+32 2 452 95 61",
    "sg:postcode":"1730",
    "sg:province":"Vlaams-Brabant",
    "wof:name":"Plasti-bac B.v.b.a.",
    "wof:placetype":"venue"
},
  "geometry": {"coordinates":[4.1599731445,50.9175033569],"type":"Point"}
}