{
  "type": "Feature",
  "properties": {
    "iso:country":"BE",
    "sg:address":"Rue Du March\u00e9 Aux Herbes 87",
    "sg:city":"Bruxelles",
    "sg:orig_category":"Ice-cream parlours",
    "sg:phone":"+32 2 513 36 08",
    "sg:postcode":"1000",
    "sg:province":"Bruxelles-Capitale",
    "wof:name":"Papillon",
    "wof:placetype":"venue"
},
  "geometry": {"coordinates":[4.3540511131,50.846736908],"type":"Point"}
}