{
  "type": "Feature",
  "properties": {
    "iso:country":"BE",
    "sg:address":"Korspelsesteenweg 134",
    "sg:city":"Beringen (beverlo)",
    "sg:classifiers":[
        {
            "category":"Health Services",
            "subcategory":"Nursing And Care Facility",
            "type":"Services"
        }
    ],
    "sg:phone":"+32 11 34 57 19",
    "sg:postcode":"3581",
    "sg:province":"Limburg",
    "sg:tags":[
        "home"
    ],
    "wof:name":"Kaerts-vervloet I",
    "wof:placetype":"venue"
},
  "geometry": {"coordinates":[5.2345099449,51.0883598328],"type":"Point"}
}