{
  "type": "Feature",
  "properties": {
    "addr:full":"Plein 2 Zwevegem (heestert) West-Vlaanderen 8551",
    "addr:housenumber":"2",
    "addr:postcode":"8551",
    "addr:street":"Plein",
    "iso:country":"BE",
    "sg:address":"Plein 2",
    "sg:city":"Zwevegem (heestert)",
    "sg:classifiers":[
        {
            "category":"Insurance",
            "subcategory":"Insurance Agent",
            "type":"Services"
        }
    ],
    "sg:phone":"+32 56 64 65 66",
    "sg:postcode":"8551",
    "sg:province":"West-Vlaanderen",
    "sg:tags":[
        "broker"
    ],
    "wof:name":"Sengier Rik Bvba",
    "wof:placetype":"venue"
},
  "geometry": {"coordinates":[3.4109840393,50.782283783],"type":"Point"}
}