{
  "type": "Feature",
  "properties": {
    "iso:country":"BE",
    "sg:address":"Rue Du Bac 3bb",
    "sg:city":"Thimister-clermont",
    "sg:orig_category":"Installation \u00e9lectrique r\u00e9sidentielle",
    "sg:phone":"+32 87 44 57 48",
    "sg:postcode":"4890",
    "sg:province":"Li\u00e8ge",
    "wof:name":"Giuseppe Campione",
    "wof:placetype":"venue"
},
  "geometry": {"coordinates":[5.8846211433,50.6589241028],"type":"Point"}
}