{
  "type": "Feature",
  "properties": {
    "addr:full":"Quai De L'industrie 73 Sint-jans-molenbeek/molenbeek- Bruxelles-Capitale 1080",
    "addr:housenumber":"73",
    "addr:postcode":"1080",
    "addr:street":"Quai De L'Industrie;Molenbeek",
    "iso:country":"BE",
    "sg:address":"Quai De L'industrie 73",
    "sg:city":"Sint-jans-molenbeek/molenbeek-",
    "sg:orig_category":"Entretien and r\u00e9parations de voitures",
    "sg:phone":"+32 2 520 10 10",
    "sg:postcode":"1080",
    "sg:province":"Bruxelles-Capitale",
    "wof:name":"Cheatani Export",
    "wof:placetype":"venue"
},
  "geometry": {"coordinates":[4.3311080933,50.8476600647],"type":"Point"}
}