{
  "type": "Feature",
  "properties": {
    "iso:country":"BE",
    "sg:address":"Rue Du By 6",
    "sg:city":"Les Bons Villers (mellet)",
    "sg:classifiers":[
        {
            "category":"Retail",
            "subcategory":"Auto Repair",
            "type":"Services"
        }
    ],
    "sg:phone":"+32 71 85 34 97",
    "sg:postcode":"6211",
    "sg:province":"Hainaut",
    "sg:tags":[
        "automobile",
        "-",
        "wrecking"
    ],
    "wof:name":"Klimmek Christophe",
    "wof:placetype":"venue"
},
  "geometry": {"coordinates":[4.4791898727,50.5055961609],"type":"Point"}
}