{
  "type": "Feature",
  "properties": {
    "iso:country":"BE",
    "sg:address":"Britselei 10 Bus 15",
    "sg:city":"Antwerpen",
    "sg:orig_category":"Advocaten and juridische adviseurs",
    "sg:phone":"+32 3 232 30 22",
    "sg:postcode":"2000",
    "sg:province":"Antwerpen",
    "wof:name":"Antychin",
    "wof:placetype":"venue"
},
  "geometry": {"coordinates":[4.406788826,51.2107963562],"type":"Point"}
}