{
  "type": "Feature",
  "properties": {
    "iso:country":"BE",
    "sg:address":"Rijmenamsesteenweg 22",
    "sg:city":"Mechelen (muizen)",
    "sg:classifiers":[
        {
            "category":"Professional",
            "subcategory":"Art Services",
            "type":"Services"
        }
    ],
    "sg:phone":"+32 15 51 26 75",
    "sg:postcode":"2812",
    "sg:province":"Antwerpen",
    "sg:tags":[
        "-",
        "painter",
        "artist"
    ],
    "wof:name":"Peerlings F Atelier",
    "wof:placetype":"venue"
},
  "geometry": {"coordinates":[4.5323591232,51.0088920593],"type":"Point"}
}