{
  "type": "Feature",
  "properties": {
    "addr:full":"Stationsstraat 81 Liedekerke Vlaams-Brabant 1770",
    "addr:housenumber":"81",
    "addr:postcode":"1770",
    "addr:street":"Stationsstraat;Vlaams-Brabant",
    "iso:country":"BE",
    "sg:address":"Stationsstraat 81",
    "sg:city":"Liedekerke",
    "sg:orig_category":"Artsen and specialisten",
    "sg:phone":"+32 53 67 25 57",
    "sg:postcode":"1770",
    "sg:province":"Vlaams-Brabant",
    "wof:name":"E. Strypens",
    "wof:placetype":"venue"
},
  "geometry": {"coordinates":[4.0847101212,50.8728713989],"type":"Point"}
}