{
  "type": "Feature",
  "properties": {
    "addr:full":"Kromfortstraat 21 De Panne West-Vlaanderen 8660",
    "addr:housenumber":"21",
    "addr:postcode":"8660",
    "addr:street":"Kromfortstraat",
    "iso:country":"BE",
    "sg:address":"Kromfortstraat 21",
    "sg:city":"De Panne",
    "sg:classifiers":[
        {
            "category":"Cafe",
            "type":"Food & Drink"
        }
    ],
    "sg:phone":"+32 58 41 03 68",
    "sg:postcode":"8660",
    "sg:province":"West-Vlaanderen",
    "sg:tags":[
        "caf\u00e9s"
    ],
    "wof:name":"Gabrielle Debergh",
    "wof:placetype":"venue"
},
  "geometry": {"coordinates":[2.6033430099,51.0695343018],"type":"Point"}
}