{
  "type": "Feature",
  "properties": {
    "iso:country":"BE",
    "sg:address":"Rue Andr\u00c9 Halloin 22",
    "sg:city":"Fleurus",
    "sg:orig_category":"Groententeelt",
    "sg:phone":"+32 71 85 39 56",
    "sg:postcode":"6220",
    "sg:province":"Hainaut",
    "wof:name":"Philippe Ervinck",
    "wof:placetype":"venue"
},
  "geometry": {"coordinates":[4.4935741425,50.4801635742],"type":"Point"}
}