{
  "type": "Feature",
  "properties": {
    "addr:full":"Parvis De La Trinit\u00c9 7 Elsene/ixelles Bruxelles-Capitale 1050",
    "addr:housenumber":"7",
    "addr:postcode":"1050",
    "addr:street":"Parvis De La Trinite\u0301",
    "iso:country":"BE",
    "sg:address":"Parvis De La Trinit\u00c9 7",
    "sg:city":"Elsene/ixelles",
    "sg:orig_category":"Tabac. Librairies. Journaux",
    "sg:phone":"+32 2 537 00 08",
    "sg:postcode":"1050",
    "sg:province":"Bruxelles-Capitale",
    "wof:name":"Librairie La Trinit\u00c9",
    "wof:placetype":"venue"
},
  "geometry": {"coordinates":[4.3587341309,50.8253822327],"type":"Point"}
}