{
  "type": "Feature",
  "properties": {
    "addr:full":"Wolvertemsesteenweg 308 Grimbergen Vlaams-Brabant 1850",
    "addr:housenumber":"308",
    "addr:postcode":"1850",
    "addr:street":"Wolvertemsesteenweg",
    "iso:country":"BE",
    "sg:address":"Wolvertemsesteenweg 308",
    "sg:city":"Grimbergen",
    "sg:orig_category":"V\u00e9hicules automobiles. Entretien and r\u00e9parations de voitures",
    "sg:phone":"+32 2 269 83 63",
    "sg:postcode":"1850",
    "sg:province":"Vlaams-Brabant",
    "wof:name":"Garage Bogemans",
    "wof:placetype":"venue"
},
  "geometry": {"coordinates":[4.3516421318,50.9390106201],"type":"Point"}
}