{
  "type": "Feature",
  "properties": {
    "addr:full":"Oelegemsesteenweg 10 Broechem Antwerpen 2520",
    "addr:housenumber":"10",
    "addr:postcode":"2520",
    "addr:street":"Oelegemsesteenweg",
    "iso:country":"BE",
    "sg:address":"Oelegemsesteenweg 10",
    "sg:city":"Broechem",
    "sg:orig_category":"Huisdieren and benodigdheden Royal Canin",
    "sg:phone":"+32 3 485 53 02",
    "sg:postcode":"2520",
    "sg:province":"Antwerpen",
    "wof:name":"Nauwelaers Ralf",
    "wof:placetype":"venue"
},
  "geometry": {"coordinates":[4.6049389839,51.1885604858],"type":"Point"}
}