{
  "type": "Feature",
  "properties": {
    "iso:country":"BE",
    "sg:address":"Bruggesteenweg 119",
    "sg:city":"Middelkerke",
    "sg:classifiers":[
        {
            "category":"Wholesale",
            "subcategory":"Farm Supplies",
            "type":"Manufacturing & Wholesale Goods"
        }
    ],
    "sg:phone":"+32 58 23 93 99",
    "sg:postcode":"8433",
    "sg:province":"West-Vlaanderen",
    "sg:tags":[
        "machine",
        "agricoles",
        "mat\u00e9riel",
        "gr"
    ],
    "wof:name":"Marc Dekien",
    "wof:placetype":"venue"
},
  "geometry": {"coordinates":[2.8315300941,51.1189155579],"type":"Point"}
}