{
  "type": "Feature",
  "properties": {
    "addr:full":"Sint-truidersteenweg 60 Hasselt Limburg 3500",
    "addr:housenumber":"60",
    "addr:postcode":"3500",
    "addr:street":"Sint-Truidersteenweg",
    "iso:country":"BE",
    "sg:address":"Sint-truidersteenweg 60",
    "sg:city":"Hasselt",
    "sg:classifiers":[
        {
            "category":"Education",
            "subcategory":"School",
            "type":"Public Place"
        }
    ],
    "sg:phone":"+32 11 27 58 36",
    "sg:postcode":"3500",
    "sg:province":"Limburg",
    "sg:tags":[
        "-",
        "private"
    ],
    "wof:name":"Superlearning",
    "wof:placetype":"venue"
},
  "geometry": {"coordinates":[5.3341240883,50.9248466492],"type":"Point"}
}