{
  "type": "Feature",
  "properties": {
    "iso:country":"BE",
    "sg:address":"Gildestraat 10",
    "sg:city":"Blankenberge (uitkerke)",
    "sg:classifiers":[
        {
            "category":"Freight",
            "type":"Transportation"
        }
    ],
    "sg:phone":"+32 50 41 86 36",
    "sg:postcode":"8370",
    "sg:province":"West-Vlaanderen",
    "sg:tags":[
        "-",
        "transport"
    ],
    "wof:name":"De Cuyper Bvba",
    "wof:placetype":"venue"
},
  "geometry": {"coordinates":[3.1530818939,51.2981834412],"type":"Point"}
}