{
  "type": "Feature",
  "properties": {
    "addr:full":"Rue Basse-wez 24 Li\u00c8ge Li\u00e8ge 4020",
    "addr:housenumber":"24",
    "addr:postcode":"4020",
    "addr:street":"Rue Basse-Wez",
    "iso:country":"BE",
    "sg:address":"Rue Basse-wez 24",
    "sg:city":"Li\u00c8ge",
    "sg:classifiers":[
        {
            "category":"Restaurant",
            "type":"Food & Drink"
        }
    ],
    "sg:phone":"+32 4 342 00 83",
    "sg:postcode":"4020",
    "sg:province":"Li\u00e8ge",
    "wof:name":"Restaurant Rose De Casa",
    "wof:placetype":"venue"
},
  "geometry": {"coordinates":[5.5876150131,50.637638092],"type":"Point"}
}