{
  "type": "Feature",
  "properties": {
    "addr:full":"Stationsstraat 63 Waarschoot Oost-Vlaanderen 9950",
    "addr:housenumber":"63",
    "addr:postcode":"9950",
    "addr:street":"Stationsstraat",
    "iso:country":"BE",
    "sg:address":"Stationsstraat 63",
    "sg:city":"Waarschoot",
    "sg:classifiers":[
        {
            "category":"Food & Beverages",
            "subcategory":"Specialty",
            "type":"Retail Goods"
        }
    ],
    "sg:phone":"+32 9 377 41 63",
    "sg:postcode":"9950",
    "sg:province":"Oost-Vlaanderen",
    "sg:tags":[
        "health",
        "dietary",
        "-",
        "biological"
    ],
    "wof:name":"Capriccio",
    "wof:placetype":"venue"
},
  "geometry": {"coordinates":[3.6107459068,51.152256012],"type":"Point"}
}