{
  "type": "Feature",
  "properties": {
    "iso:country":"BE",
    "sg:address":"Wipstraat 5",
    "sg:city":"Brasschaat",
    "sg:orig_category":"Industri\u00eble and commerci\u00eble bouw Installatie van houten of kunststof schrijnwerk Woningbouw",
    "sg:phone":"+32 3 646 08 00",
    "sg:postcode":"2930",
    "sg:province":"Antwerpen",
    "wof:name":"Bouwbedrijf Flor\u00c9",
    "wof:placetype":"venue"
},
  "geometry": {"coordinates":[4.5195169449,51.3204956055],"type":"Point"}
}