{
  "type": "Feature",
  "properties": {
    "iso:country":"BE",
    "sg:address":"Rue Nestor Vandercamme 52",
    "sg:city":"Le Roeulx",
    "sg:orig_category":"Eleveurs de bovins",
    "sg:phone":"+32 67 44 26 21",
    "sg:postcode":"7070",
    "sg:province":"Hainaut",
    "wof:name":"Marc-rene Vercruysse",
    "wof:placetype":"venue"
},
  "geometry": {"coordinates":[4.1496801376,50.5205383301],"type":"Point"}
}