{
  "type": "Feature",
  "properties": {
    "addr:full":"Heuvelhoekstraat 5 Dentergem West-Vlaanderen 8720",
    "addr:housenumber":"5",
    "addr:postcode":"8720",
    "addr:street":"Heuvelhoekstraat",
    "iso:country":"BE",
    "sg:address":"Heuvelhoekstraat 5",
    "sg:city":"Dentergem",
    "sg:orig_category":"Radioproductie and uitzendingen",
    "sg:phone":"+32 9 388 68 89",
    "sg:postcode":"8720",
    "sg:province":"West-Vlaanderen",
    "wof:name":"Radio Caraat",
    "wof:placetype":"venue"
},
  "geometry": {"coordinates":[3.4320809841,50.9394226074],"type":"Point"}
}