{
  "type": "Feature",
  "properties": {
    "addr:full":"Oude Torhoutstraat 2 Hooglede West-Vlaanderen 8830",
    "addr:housenumber":"2",
    "addr:postcode":"8830",
    "addr:street":"Oude Torhoutstraat",
    "iso:country":"BE",
    "sg:address":"Oude Torhoutstraat 2",
    "sg:city":"Hooglede",
    "sg:classifiers":[
        {
            "category":"Professional",
            "subcategory":"Accounting & Tax Preparation",
            "type":"Services"
        }
    ],
    "sg:phone":"+32 51 70 19 77",
    "sg:postcode":"8830",
    "sg:province":"West-Vlaanderen",
    "sg:tags":[
        "bookkeeper"
    ],
    "wof:name":"Castelein Bvba",
    "wof:placetype":"venue"
},
  "geometry": {"coordinates":[3.0319209099,50.9971847534],"type":"Point"}
}