{
  "type": "Feature",
  "properties": {
    "addr:full":"Essenlaan 5 Genk (waterschei) Limburg 3600",
    "addr:housenumber":"5",
    "addr:postcode":"3600",
    "addr:street":"Essenlaan",
    "iso:country":"BE",
    "sg:address":"Essenlaan 5",
    "sg:city":"Genk (waterschei)",
    "sg:classifiers":[
        {
            "category":"Retail",
            "subcategory":"Auto Repair",
            "type":"Services"
        }
    ],
    "sg:phone":"+32 89 38 45 72",
    "sg:postcode":"3600",
    "sg:province":"Limburg",
    "sg:tags":[
        "automobile-body"
    ],
    "wof:name":"Vecarro Bvba",
    "wof:placetype":"venue"
},
  "geometry": {"coordinates":[5.4878101349,51.0077934265],"type":"Point"}
}