{
  "type": "Feature",
  "properties": {
    "iso:country":"BE",
    "sg:address":"Kruisvenlaan 31",
    "sg:city":"Dilsen-stokkem (lanklaar)",
    "sg:classifiers":[
        {
            "category":"Food & Beverages",
            "subcategory":"Meat & Fish",
            "type":"Retail Goods"
        }
    ],
    "sg:phone":"+32 89 65 01 12",
    "sg:postcode":"3650",
    "sg:province":"Limburg",
    "sg:tags":[
        "poultry",
        "whol",
        "game",
        "-"
    ],
    "wof:name":"kiekenbakker",
    "wof:placetype":"venue"
},
  "geometry": {"coordinates":[5.727396965,51.0364189148],"type":"Point"}
}