{
  "type": "Feature",
  "properties": {
    "iso:country":"BE",
    "sg:address":"Slachthuisstraat 20",
    "sg:city":"Eeklo",
    "sg:orig_category":"Production and transformation de viande",
    "sg:phone":"+32 9 377 35 47",
    "sg:postcode":"9900",
    "sg:province":"Oost-Vlaanderen",
    "wof:name":"M Ryckaert",
    "wof:placetype":"venue"
},
  "geometry": {"coordinates":[3.5479309559,51.1799812317],"type":"Point"}
}