{
  "type": "Feature",
  "properties": {
    "addr:full":"Rue Des Eglantiers 24 Chapelle-lez-herlaimont Hainaut 7160",
    "addr:housenumber":"24",
    "addr:postcode":"7160",
    "addr:street":"Rue Des Eglantiers",
    "iso:country":"BE",
    "sg:address":"Rue Des Eglantiers 24",
    "sg:city":"Chapelle-lez-herlaimont",
    "sg:orig_category":"Plomberie, chauffage and installations sanitaires",
    "sg:phone":"+32 475 60 10 21",
    "sg:postcode":"7160",
    "sg:province":"Hainaut",
    "wof:name":"Sani Services",
    "wof:placetype":"venue"
},
  "geometry": {"coordinates":[4.2745947838,50.4722480774],"type":"Point"}
}