{
  "type": "Feature",
  "properties": {
    "iso:country":"BE",
    "sg:address":"Rue Louis Buisseret 14",
    "sg:city":"Binche",
    "sg:classifiers":[
        {
            "category":"Health Services",
            "subcategory":"Doctor",
            "type":"Services"
        }
    ],
    "sg:phone":"+32 64 33 40 17",
    "sg:postcode":"7130",
    "sg:province":"Hainaut",
    "sg:tags":[
        "medicinephysicians",
        "surgeon"
    ],
    "wof:name":"Constant F",
    "wof:placetype":"venue"
},
  "geometry": {"coordinates":[4.1668958664,50.4116363525],"type":"Point"}
}