{
  "type": "Feature",
  "properties": {
    "addr:full":"Grote Steenweg 23 Zomergem Oost-Vlaanderen 9930",
    "addr:housenumber":"23",
    "addr:postcode":"9930",
    "addr:street":"Grote Steenweg",
    "iso:country":"BE",
    "sg:address":"Grote Steenweg 23",
    "sg:city":"Zomergem",
    "sg:classifiers":[
        {
            "category":"Retail",
            "subcategory":"Veterinary Services",
            "type":"Services"
        }
    ],
    "sg:phone":"+32 9 372 95 40",
    "sg:postcode":"9930",
    "sg:province":"Oost-Vlaanderen",
    "sg:tags":[
        "veterinarian"
    ],
    "wof:name":"Itterbeke G",
    "wof:placetype":"venue"
},
  "geometry": {"coordinates":[3.5772869587,51.1152534485],"type":"Point"}
}