{
  "type": "Feature",
  "properties": {
    "iso:country":"BE",
    "sg:address":"Boulevard Poincar\u00c9 46",
    "sg:city":"Anderlecht",
    "sg:orig_category":"Librairies",
    "sg:phone":"+32 2 524 43 51",
    "sg:postcode":"1070",
    "sg:province":"Bruxelles-Capitale",
    "wof:name":"Maison Excalibur",
    "wof:placetype":"venue"
},
  "geometry": {"coordinates":[4.3388872147,50.8432006836],"type":"Point"}
}