{
  "type": "Feature",
  "properties": {
    "addr:full":"Rue Du Vieux March\u00e9 27 Vielsalm Luxembourg 6690",
    "addr:housenumber":"27",
    "addr:postcode":"6690",
    "addr:street":"Rue Du Vieux Marche\u0301",
    "iso:country":"BE",
    "sg:address":"Rue Du Vieux March\u00e9 27",
    "sg:city":"Vielsalm",
    "sg:classifiers":[
        {
            "category":"Banks & Credit Unions",
            "subcategory":"Investment Brokerage",
            "type":"Services"
        }
    ],
    "sg:phone":"+32 80 21 70 35",
    "sg:postcode":"6690",
    "sg:province":"Luxembourg",
    "sg:tags":[
        "jean",
        "casual",
        "wear"
    ],
    "wof:name":"Big Bazar Boutique",
    "wof:placetype":"venue"
},
  "geometry": {"coordinates":[5.9150848389,50.2847862244],"type":"Point"}
}