{
  "type": "Feature",
  "properties": {
    "iso:country":"BE",
    "sg:address":"Patrijzenlaan 4",
    "sg:city":"Hove",
    "sg:classifiers":[
        {
            "category":"Professional",
            "subcategory":"Secretarial Services",
            "type":"Services"
        }
    ],
    "sg:phone":"+32 3 455 69 76",
    "sg:postcode":"2540",
    "sg:province":"Antwerpen",
    "sg:tags":[
        "firm"
    ],
    "wof:name":"Scriptor C Bvba",
    "wof:placetype":"venue"
},
  "geometry": {"coordinates":[4.4815478325,51.145740509],"type":"Point"}
}