{
  "type": "Feature",
  "properties": {
    "iso:country":"BE",
    "sg:address":"Rue De Lizin 3",
    "sg:city":"Ouffet (warz\u00e9e)",
    "sg:classifiers":[
        {
            "category":"Banks & Credit Unions",
            "subcategory":"Investment Brokerage",
            "type":"Services"
        }
    ],
    "sg:phone":"+32 86 36 67 71",
    "sg:postcode":"4590",
    "sg:province":"Li\u00e8ge",
    "sg:tags":[
        "auditor"
    ],
    "wof:name":"Mathieu N",
    "wof:placetype":"venue"
},
  "geometry": {"coordinates":[5.4621558189,50.4574775696],"type":"Point"}
}