{
  "type": "Feature",
  "properties": {
    "addr:full":"Molenstraat 95 Wetteren (groot) Oost-Vlaanderen 9230",
    "addr:housenumber":"95",
    "addr:postcode":"9230",
    "addr:street":"Molenstraat;Groot Oost-Vlaanderen",
    "iso:country":"BE",
    "sg:address":"Molenstraat 95",
    "sg:city":"Wetteren (groot)",
    "sg:classifiers":[
        {
            "category":"Personal",
            "subcategory":"Beauty Salon",
            "type":"Services"
        }
    ],
    "sg:phone":"+32 9 324 06 07",
    "sg:postcode":"9230",
    "sg:province":"Oost-Vlaanderen",
    "sg:tags":[
        "de",
        "coiffure"
    ],
    "wof:name":"Coiffure Nummer Vijftien",
    "wof:placetype":"venue"
},
  "geometry": {"coordinates":[3.8889110088,51.0041923523],"type":"Point"}
}