{
  "type": "Feature",
  "properties": {
    "iso:country":"BE",
    "sg:address":"Kaulillerweg 176",
    "sg:city":"Bocholt (kaulille)",
    "sg:orig_category":"Leisure articles",
    "sg:phone":"+32 89 46 22 28",
    "sg:postcode":"3950",
    "sg:province":"Limburg",
    "wof:name":"Hobbywinkelke ('t)",
    "wof:placetype":"venue"
},
  "geometry": {"coordinates":[5.5533399582,51.17760849],"type":"Point"}
}