{
  "type": "Feature",
  "properties": {
    "iso:country":"BE",
    "sg:address":"Avenue P\u00e8re Damien 15",
    "sg:city":"Bruxelles (woluwe-saint-pierre)",
    "sg:classifiers":[
        {
            "category":"Health Services",
            "subcategory":"Doctor",
            "type":"Services"
        }
    ],
    "sg:phone":"+32 2 762 25 73",
    "sg:postcode":"1150",
    "sg:province":"Bruxelles-Capitale",
    "sg:tags":[
        "medicinephysicians",
        "surgeon"
    ],
    "wof:name":"De Wil Paul",
    "wof:placetype":"venue"
},
  "geometry": {"coordinates":[4.4185957909,50.835811615],"type":"Point"}
}