{
  "type": "Feature",
  "properties": {
    "iso:country":"BE",
    "sg:address":"Rue De Xhygnez 30",
    "sg:city":"Sprimont",
    "sg:classifiers":[
        {
            "category":"Building & Trades",
            "subcategory":"Pest Control",
            "type":"Services"
        }
    ],
    "sg:phone":"+32 4 382 24 52",
    "sg:postcode":"4140",
    "sg:province":"Li\u00e8ge",
    "sg:tags":[
        "painting",
        "contractor"
    ],
    "wof:name":"Demarez D\u00e9co",
    "wof:placetype":"venue"
},
  "geometry": {"coordinates":[5.6388201714,50.509185791],"type":"Point"}
}