{
  "type": "Feature",
  "properties": {
    "iso:country":"BE",
    "sg:address":"Lakeman 70",
    "sg:city":"Londerzeel",
    "sg:orig_category":"Kapsalons",
    "sg:phone":"+32 52 30 10 83",
    "sg:postcode":"1840",
    "sg:province":"Vlaams-Brabant",
    "wof:name":"Benedikt Vergaelen",
    "wof:placetype":"venue"
},
  "geometry": {"coordinates":[4.2851920128,50.9994468689],"type":"Point"}
}