{
  "type": "Feature",
  "properties": {
    "iso:country":"BE",
    "sg:address":"Putkapelstraat 93",
    "sg:city":"Gent (sint-denijs-westrem - Afsnee)",
    "sg:classifiers":[
        {
            "category":"Professional",
            "subcategory":"Accounting & Tax Preparation",
            "type":"Services"
        }
    ],
    "sg:phone":"+32 9 222 22 80",
    "sg:postcode":"9051",
    "sg:province":"Oost-Vlaanderen",
    "sg:tags":[
        "bookkeeper"
    ],
    "wof:name":"Verlent H",
    "wof:placetype":"venue"
},
  "geometry": {"coordinates":[3.6928548813,51.0228271484],"type":"Point"}
}