{
  "type": "Feature",
  "properties": {
    "iso:country":"BE",
    "sg:address":"Tervuursesteenweg 456",
    "sg:city":"Bertem",
    "sg:orig_category":"Groententeelt",
    "sg:phone":"+32 16 48 88 00",
    "sg:postcode":"3060",
    "sg:province":"Vlaams-Brabant",
    "wof:name":"Emile Dekeyzer",
    "wof:placetype":"venue"
},
  "geometry": {"coordinates":[4.6064600945,50.8594017029],"type":"Point"}
}