{
  "type": "Feature",
  "properties": {
    "iso:country":"BE",
    "sg:address":"Kerkveld 29",
    "sg:city":"Ninove",
    "sg:orig_category":"Organisations and associations. Services pour animaux domestiques",
    "sg:phone":"+32 54 32 16 79",
    "sg:postcode":"9400",
    "sg:province":"Oost-Vlaanderen",
    "wof:name":"Dierenbescherming Ninove",
    "wof:placetype":"venue"
},
  "geometry": {"coordinates":[4.0415811539,50.80052948],"type":"Point"}
}