{
  "type": "Feature",
  "properties": {
    "addr:full":"Gemeenteplein 20 Bus 2 Knokke-heist West-Vlaanderen 8300",
    "addr:housenumber":"20 bus 2",
    "addr:postcode":"8300",
    "addr:street":"Gemeenteplein",
    "iso:country":"BE",
    "sg:address":"Gemeenteplein 20 Bus 2",
    "sg:city":"Knokke-heist",
    "sg:orig_category":"Articles de sport, camping and jouets Chaussures. Articles m\u00e9dicaux and orthop\u00e9diques",
    "sg:phone":"+32 50 61 45 55",
    "sg:postcode":"8300",
    "sg:province":"West-Vlaanderen",
    "wof:name":"Health Products Bandagisterie",
    "wof:placetype":"venue"
},
  "geometry": {"coordinates":[3.2903280258,51.3406562805],"type":"Point"}
}