{
  "type": "Feature",
  "properties": {
    "iso:country":"BE",
    "sg:address":"Strijpenplein 1",
    "sg:city":"Zottegem (strijpen)",
    "sg:classifiers":[
        {
            "category":"Building & Trades",
            "subcategory":"Electrical",
            "type":"Services"
        }
    ],
    "sg:phone":"+32 9 360 54 69",
    "sg:postcode":"9620",
    "sg:province":"Oost-Vlaanderen",
    "sg:tags":[
        "-",
        "electric",
        "contractor"
    ],
    "wof:name":"Roelec Bvba",
    "wof:placetype":"venue"
},
  "geometry": {"coordinates":[3.8112111092,50.871181488],"type":"Point"}
}