{
  "type": "Feature",
  "properties": {
    "addr:full":"Geraardsbergsestraat 56-58 Ninove Oost-Vlaanderen 9400",
    "addr:housenumber":"56-58",
    "addr:postcode":"9400",
    "addr:street":"Geraardsbergsestraat",
    "iso:country":"BE",
    "sg:address":"Geraardsbergsestraat 56-58",
    "sg:city":"Ninove",
    "sg:classifiers":[
        {
            "category":"Home & Garden",
            "subcategory":"Home Furnishings",
            "type":"Retail Goods"
        }
    ],
    "sg:phone":"+32 54 33 40 58",
    "sg:postcode":"9400",
    "sg:province":"Oost-Vlaanderen",
    "sg:tags":[
        "lighting",
        "fixture",
        "-"
    ],
    "wof:name":"Ela Bvba",
    "wof:placetype":"venue"
},
  "geometry": {"coordinates":[4.0171098709,50.8363990784],"type":"Point"}
}