{
  "type": "Feature",
  "properties": {
    "iso:country":"BE",
    "sg:address":"Kapelstraat 37",
    "sg:city":"Kortessem",
    "sg:classifiers":[
        {
            "category":"Cafe",
            "type":"Food & Drink"
        }
    ],
    "sg:phone":"+32 11 37 75 94",
    "sg:postcode":"3720",
    "sg:province":"Limburg",
    "sg:tags":[
        "caf\u00e9s"
    ],
    "wof:name":"Vechmaal",
    "wof:placetype":"venue"
},
  "geometry": {"coordinates":[5.3833708763,50.8667984009],"type":"Point"}
}