{
  "type": "Feature",
  "properties": {
    "addr:full":"Stakendijke 13bb Damme West-Vlaanderen 8340",
    "addr:housenumber":"13bb",
    "addr:postcode":"8340",
    "addr:street":"Stakendijke",
    "iso:country":"BE",
    "sg:address":"Stakendijke 13bb",
    "sg:city":"Damme",
    "sg:orig_category":"Instituts de beaut\u00e9",
    "sg:phone":"+32 50 37 11 88",
    "sg:postcode":"8340",
    "sg:province":"West-Vlaanderen",
    "wof:name":"Pedicure Spegelaere",
    "wof:placetype":"venue"
},
  "geometry": {"coordinates":[3.3172030449,51.2060661316],"type":"Point"}
}