{
  "type": "Feature",
  "properties": {
    "iso:country":"BE",
    "sg:address":"Avenue Sabin 4 Box 2",
    "sg:city":"Wavre",
    "sg:classifiers":[
        {
            "category":"Manufacturing",
            "subcategory":"Chemicals & Compounds",
            "type":"Manufacturing & Wholesale Goods"
        }
    ],
    "sg:phone":"+32 10 24 68 05",
    "sg:postcode":"1300",
    "sg:province":"Brabant Wallon",
    "sg:tags":[
        "pharmaceutical",
        "product"
    ],
    "wof:name":"Codimex Pharma",
    "wof:placetype":"venue"
},
  "geometry": {"coordinates":[4.613535881,50.7402992249],"type":"Point"}
}