{
  "type": "Feature",
  "properties": {
    "addr:full":"Tessenderloseweg 149 Diest Vlaams-Brabant 3290",
    "addr:housenumber":"149",
    "addr:postcode":"3290",
    "addr:street":"Tessenderloseweg",
    "iso:country":"BE",
    "sg:address":"Tessenderloseweg 149",
    "sg:city":"Diest",
    "sg:orig_category":"Afbraak- and draineerwerken",
    "sg:phone":"+32 13 66 22 30",
    "sg:postcode":"3290",
    "sg:province":"Vlaams-Brabant",
    "wof:name":"Aannemingsbedrijf Pieck",
    "wof:placetype":"venue"
},
  "geometry": {"coordinates":[5.0869998932,51.0491485596],"type":"Point"}
}