{
  "type": "Feature",
  "properties": {
    "addr:full":"Chauss\u00e9e De Zellik 1 Bruxelles (berchem-sainte-agathe) Bruxelles-Capitale 1082",
    "addr:housenumber":"1",
    "addr:postcode":"1082",
    "addr:street":"Chausse\u0301E De Zellik",
    "iso:country":"BE",
    "sg:address":"Chauss\u00e9e De Zellik 1",
    "sg:city":"Bruxelles (berchem-sainte-agathe)",
    "sg:classifiers":[
        {
            "category":"Autos & Motor Vehicles",
            "subcategory":"Fuel & Gas Station",
            "type":"Retail Goods"
        }
    ],
    "sg:phone":"+32 2 482 04 70",
    "sg:postcode":"1082",
    "sg:province":"Bruxelles-Capitale",
    "wof:name":"Vandenperre",
    "wof:placetype":"venue"
},
  "geometry": {"coordinates":[4.2918400764,50.8696022034],"type":"Point"}
}