{
  "type": "Feature",
  "properties": {
    "iso:country":"BE",
    "sg:address":"Reigerstraat 23",
    "sg:city":"Oudenburg",
    "sg:classifiers":[
        {
            "category":"Shopping",
            "subcategory":"Optician",
            "type":"Retail Goods"
        }
    ],
    "sg:phone":"+32 59 43 06 99",
    "sg:postcode":"8460",
    "sg:province":"West-Vlaanderen",
    "sg:tags":[
        "-"
    ],
    "wof:name":"Imolu",
    "wof:placetype":"venue"
},
  "geometry": {"coordinates":[2.9956591129,51.1891517639],"type":"Point"}
}