{
  "type": "Feature",
  "properties": {
    "addr:full":"March\u00e9 Au B\u00e9tail 4 Mons Hainaut 7000",
    "addr:housenumber":"4",
    "addr:postcode":"7000",
    "addr:street":"Hainaut",
    "iso:country":"BE",
    "sg:address":"March\u00e9 Au B\u00e9tail 4",
    "sg:city":"Mons",
    "sg:classifiers":[
        {
            "category":"Health Services",
            "subcategory":"Health Practitioner",
            "type":"Services"
        }
    ],
    "sg:phone":"+32 65 35 56 65",
    "sg:postcode":"7000",
    "sg:province":"Hainaut",
    "sg:tags":[
        "physiotherapist"
    ],
    "wof:name":"Deli\u00e8re F",
    "wof:placetype":"venue"
},
  "geometry": {"coordinates":[3.9522509575,50.4547271729],"type":"Point"}
}