{
  "type": "Feature",
  "properties": {
    "addr:full":"Keizer Karelstraat 131 Gent Oost-Vlaanderen 9000",
    "addr:housenumber":"131",
    "addr:postcode":"9000",
    "addr:street":"Keizer Karelstraat;Oost-Vlaanderen",
    "iso:country":"BE",
    "sg:address":"Keizer Karelstraat 131",
    "sg:city":"Gent",
    "sg:orig_category":"Instruments de musique",
    "sg:phone":"+32 9 224 00 36",
    "sg:postcode":"9000",
    "sg:province":"Oost-Vlaanderen",
    "wof:name":"Aphrodite",
    "wof:placetype":"venue"
},
  "geometry": {"coordinates":[3.733397007,51.0511283875],"type":"Point"}
}