{
  "type": "Feature",
  "properties": {
    "addr:full":"Oostvaartdijk 340 Grimbergen (humbeek) Vlaams-Brabant 1851",
    "addr:housenumber":"340",
    "addr:postcode":"1851",
    "addr:street":"Oostvaartdijk",
    "iso:country":"BE",
    "sg:address":"Oostvaartdijk 340",
    "sg:city":"Grimbergen (humbeek)",
    "sg:classifiers":[
        {
            "category":"Home & Garden",
            "subcategory":"Garden Supply",
            "type":"Retail Goods"
        }
    ],
    "sg:phone":"+32 2 251 74 80",
    "sg:postcode":"1851",
    "sg:province":"Vlaams-Brabant",
    "sg:tags":[
        "lawn",
        "mower"
    ],
    "wof:name":"Robberechts Tuinmachines",
    "wof:placetype":"venue"
},
  "geometry": {"coordinates":[4.3935818672,50.9752578735],"type":"Point"}
}