{
  "type": "Feature",
  "properties": {
    "addr:full":"Zeedijk-knokke 640bd Knokke-heist West-Vlaanderen 8300",
    "addr:postcode":"8300",
    "addr:street":"West-Vlaanderen",
    "iso:country":"BE",
    "sg:address":"Zeedijk-knokke 640bd",
    "sg:city":"Knokke-heist",
    "sg:orig_category":"Woningbouw",
    "sg:phone":"+32 50 60 03 44",
    "sg:postcode":"8300",
    "sg:province":"West-Vlaanderen",
    "wof:name":"Andr\u00c9 Saelens",
    "wof:placetype":"venue"
},
  "geometry": {"coordinates":[3.2814400196,51.3407287598],"type":"Point"}
}