{
  "type": "Feature",
  "properties": {
    "iso:country":"BE",
    "sg:address":"Rue D'hoves 19",
    "sg:city":"Silly (graty)",
    "sg:classifiers":[
        {
            "category":"Professional",
            "subcategory":"Management & Consulting",
            "type":"Services"
        }
    ],
    "sg:phone":"+32 67 45 81 88",
    "sg:postcode":"7830",
    "sg:province":"Hainaut",
    "sg:tags":[
        "-",
        "processing",
        "data",
        "consultant"
    ],
    "wof:name":"Rogge L",
    "wof:placetype":"venue"
},
  "geometry": {"coordinates":[4.0365409851,50.6708183289],"type":"Point"}
}