{
  "type": "Feature",
  "properties": {
    "addr:full":"Roeselaarsestraat 159 Izegem West-Vlaanderen 8870",
    "addr:housenumber":"159",
    "addr:postcode":"8870",
    "addr:street":"Roeselaarsestraat",
    "iso:country":"BE",
    "sg:address":"Roeselaarsestraat 159",
    "sg:city":"Izegem",
    "sg:classifiers":[
        {
            "category":"Bars & Pubs",
            "type":"Food & Drink"
        }
    ],
    "sg:phone":"+32 51 30 62 10",
    "sg:postcode":"8870",
    "sg:province":"West-Vlaanderen",
    "wof:name":"Ruste (de)",
    "wof:placetype":"venue"
},
  "geometry": {"coordinates":[3.2043740749,50.920337677],"type":"Point"}
}