{
  "type": "Feature",
  "properties": {
    "iso:country":"BE",
    "sg:address":"Rue Des J\u00c9suites 46",
    "sg:city":"Tournai",
    "sg:classifiers":[
        {
            "category":"Arena",
            "subcategory":"Sports Club",
            "type":"Entertainment"
        }
    ],
    "sg:phone":"+32 69 22 96 24",
    "sg:postcode":"7500",
    "sg:province":"Hainaut",
    "sg:tags":[
        "de"
    ],
    "wof:name":"R.t.c. Tournaisien",
    "wof:placetype":"venue"
},
  "geometry": {"coordinates":[3.3896009922,50.602104187],"type":"Point"}
}