{
  "type": "Feature",
  "properties": {
    "addr:full":"Dorpsstraat 26 Erembodegem 9440",
    "addr:housenumber":"26",
    "addr:postcode":"9440",
    "addr:street":"Dorpsstraat",
    "iso:country":"BE",
    "sg:address":"Dorpsstraat 26",
    "sg:city":"Erembodegem",
    "sg:classifiers":[
        {
            "category":"Banks & Credit Unions",
            "subcategory":"Bank",
            "type":"Services"
        }
    ],
    "sg:phone":"+32 53 21 26 28",
    "sg:postcode":"9440",
    "wof:name":"Gemeentekrediet",
    "wof:placetype":"venue"
},
  "geometry": {"coordinates":[6.2157897949,49.9458084106],"type":"Point"}
}