{
  "type": "Feature",
  "properties": {
    "addr:full":"Markt 25 Bilzen Limburg 3740",
    "addr:housenumber":"25",
    "addr:postcode":"3740",
    "addr:street":"Markt",
    "iso:country":"BE",
    "sg:address":"Markt 25",
    "sg:city":"Bilzen",
    "sg:orig_category":"Banken and kredietinstellingen",
    "sg:phone":"+32 89 41 52 15",
    "sg:postcode":"3740",
    "sg:province":"Limburg",
    "wof:name":"Bank Van Limburg",
    "wof:placetype":"venue"
},
  "geometry": {"coordinates":[5.5133070946,50.8699760437],"type":"Point"}
}