{
  "type": "Feature",
  "properties": {
    "addr:full":"Rue Des V\u00e9rennes 8 Beauraing (dion) Namur 5570",
    "addr:housenumber":"8",
    "addr:postcode":"5570",
    "addr:street":"Rue Des Ve\u0301Rennes;Dion",
    "iso:country":"BE",
    "sg:address":"Rue Des V\u00e9rennes 8",
    "sg:city":"Beauraing (dion)",
    "sg:classifiers":[
        {
            "category":"Building & Trades",
            "subcategory":"Landscaping Services",
            "type":"Services"
        }
    ],
    "sg:phone":"+32 82 71 25 25",
    "sg:postcode":"5570",
    "sg:province":"Namur",
    "sg:tags":[
        "gardening",
        "garden",
        "maintenance"
    ],
    "wof:name":"Wirard Willy Et Gomez Sacha",
    "wof:placetype":"venue"
},
  "geometry": {"coordinates":[4.8886470795,50.1175575256],"type":"Point"}
}