{
  "type": "Feature",
  "properties": {
    "iso:country":"BE",
    "sg:address":"Malta 30",
    "sg:city":"Bree",
    "sg:classifiers":[
        {
            "category":"Bakery",
            "type":"Food & Drink"
        }
    ],
    "sg:phone":"+32 89 46 13 82",
    "sg:postcode":"3960",
    "sg:province":"Limburg",
    "sg:tags":[
        "confectioner",
        "baker"
    ],
    "wof:name":"Deussen",
    "wof:placetype":"venue"
},
  "geometry": {"coordinates":[5.6027431488,51.1427612305],"type":"Point"}
}