{
  "type": "Feature",
  "properties": {
    "addr:full":"Rue De L'eglise 33 Welkenraedt Li\u00e8ge 4840",
    "addr:housenumber":"33",
    "addr:postcode":"4840",
    "addr:street":"Rue De L'Eglise",
    "iso:country":"BE",
    "sg:address":"Rue De L'eglise 33",
    "sg:city":"Welkenraedt",
    "sg:classifiers":[
        {
            "category":"Education",
            "subcategory":"School",
            "type":"Public Place"
        }
    ],
    "sg:phone":"+32 87 88 04 40",
    "sg:postcode":"4840",
    "sg:province":"Li\u00e8ge",
    "sg:tags":[
        "primary"
    ],
    "wof:name":"Ecole Primaire Libre St-joseph",
    "wof:placetype":"venue"
},
  "geometry": {"coordinates":[5.9701690674,50.6600036621],"type":"Point"}
}