{
  "type": "Feature",
  "properties": {
    "iso:country":"BE",
    "sg:address":"Wambeekstraat 54",
    "sg:city":"Steenokkerzeel",
    "sg:orig_category":"Woningbouw",
    "sg:phone":"+32 2 751 92 41",
    "sg:postcode":"1820",
    "sg:province":"Vlaams-Brabant",
    "wof:name":"Ramast",
    "wof:placetype":"venue"
},
  "geometry": {"coordinates":[4.5081958771,50.9183578491],"type":"Point"}
}