{
  "type": "Feature",
  "properties": {
    "addr:full":"Rue Saint-roch 5 Viroinval (nismes) Namur 5670",
    "addr:housenumber":"5",
    "addr:postcode":"5670",
    "addr:street":"Rue Saint-Roch",
    "iso:country":"BE",
    "sg:address":"Rue Saint-roch 5",
    "sg:city":"Viroinval (nismes)",
    "sg:classifiers":[
        {
            "category":"Banks & Credit Unions",
            "subcategory":"Financial Services",
            "type":"Services"
        }
    ],
    "sg:phone":"+32 60 31 22 86",
    "sg:postcode":"5670",
    "sg:province":"Namur",
    "sg:tags":[
        "loan",
        "mortgage"
    ],
    "wof:name":"Nimassur Sprl",
    "wof:placetype":"venue"
},
  "geometry": {"coordinates":[4.5466141701,50.07554245],"type":"Point"}
}