{
  "type": "Feature",
  "properties": {
    "iso:country":"BE",
    "sg:address":"Fabrieksstraat 13",
    "sg:city":"Willebroek",
    "sg:classifiers":[
        {
            "category":"Manufacturing",
            "subcategory":"Chemicals & Compounds",
            "type":"Manufacturing & Wholesale Goods"
        }
    ],
    "sg:phone":"+32 3 860 08 11",
    "sg:postcode":"2830",
    "sg:province":"Antwerpen",
    "sg:tags":[
        "industry",
        "containers",
        "tanks",
        "boiler",
        "apparatus"
    ],
    "wof:name":"Cmi Energy Services",
    "wof:placetype":"venue"
},
  "geometry": {"coordinates":[4.3643779755,51.061088562],"type":"Point"}
}