{
  "type": "Feature",
  "properties": {
    "addr:full":"Route Des Marni\u00c8res 32 Lasne Brabant Wallon 1380",
    "addr:housenumber":"32",
    "addr:postcode":"1380",
    "addr:street":"Route Des Marnie\u0300Res",
    "iso:country":"BE",
    "sg:address":"Route Des Marni\u00c8res 32",
    "sg:city":"Lasne",
    "sg:orig_category":"Immobili\u00ebnkantoren",
    "sg:phone":"+32 2 633 30 30",
    "sg:postcode":"1380",
    "sg:province":"Brabant Wallon",
    "wof:name":"Bureau Ibo Estate",
    "wof:placetype":"venue"
},
  "geometry": {"coordinates":[4.483235836,50.6850166321],"type":"Point"}
}