{
  "type": "Feature",
  "properties": {
    "addr:full":"Koerselsesteenweg 88 Beringen Limburg 3580",
    "addr:housenumber":"88",
    "addr:postcode":"3580",
    "addr:street":"Koerselsesteenweg",
    "iso:country":"BE",
    "sg:address":"Koerselsesteenweg 88",
    "sg:city":"Beringen",
    "sg:classifiers":[
        {
            "category":"Health Services",
            "subcategory":"Health Practitioner",
            "type":"Services"
        }
    ],
    "sg:phone":"+32 11 45 17 00",
    "sg:postcode":"3580",
    "sg:province":"Limburg",
    "sg:tags":[
        "physiotherapist"
    ],
    "wof:name":"Verwinnen Erik",
    "wof:placetype":"venue"
},
  "geometry": {"coordinates":[5.2330651283,51.0504951477],"type":"Point"}
}