{
  "type": "Feature",
  "properties": {
    "addr:full":"Chauss\u00c9e De Vleurgat 208 Brussel/bruxelles Bruxelles-Capitale 1000",
    "addr:housenumber":"208",
    "addr:postcode":"1000",
    "addr:street":"Chausse\u0301E De Vleurgat;/",
    "iso:country":"BE",
    "sg:address":"Chauss\u00c9e De Vleurgat 208",
    "sg:city":"Brussel/bruxelles",
    "sg:orig_category":"M\u00e9decins and sp\u00e9cialistes",
    "sg:phone":"+32 2 640 64 72",
    "sg:postcode":"1000",
    "sg:province":"Bruxelles-Capitale",
    "wof:name":"Cl\u00c9o Vanslambrouck",
    "wof:placetype":"venue"
},
  "geometry": {"coordinates":[4.3667798042,50.8212890625],"type":"Point"}
}