{
  "type": "Feature",
  "properties": {
    "addr:full":"Schallenberghlaan 3 Bonheiden Antwerpen 2820",
    "addr:housenumber":"3",
    "addr:postcode":"2820",
    "addr:street":"Schallenberghlaan",
    "iso:country":"BE",
    "sg:address":"Schallenberghlaan 3",
    "sg:city":"Bonheiden",
    "sg:classifiers":[
        {
            "category":"Insurance",
            "subcategory":"Insurance Agent",
            "type":"Services"
        }
    ],
    "sg:phone":"+32 15 55 65 60",
    "sg:postcode":"2820",
    "sg:province":"Antwerpen",
    "sg:tags":[
        "verzekeringsmakelaars",
        "expert"
    ],
    "wof:name":"Dorimmo",
    "wof:placetype":"venue"
},
  "geometry": {"coordinates":[4.5361971855,51.024356842],"type":"Point"}
}