{
  "type": "Feature",
  "properties": {
    "addr:full":"Hilarius Bertolfstraat 28 Gent (ledeberg) Oost-Vlaanderen 9050",
    "addr:housenumber":"28",
    "addr:postcode":"9050",
    "addr:street":"Bertolfstraat",
    "iso:country":"BE",
    "sg:address":"Hilarius Bertolfstraat 28",
    "sg:city":"Gent (ledeberg)",
    "sg:classifiers":[
        {
            "category":"Real Estate",
            "subcategory":"Architect",
            "type":"Services"
        }
    ],
    "sg:phone":"+32 9 231 03 25",
    "sg:postcode":"9050",
    "sg:province":"Oost-Vlaanderen",
    "wof:name":"Persoons P",
    "wof:placetype":"venue"
},
  "geometry": {"coordinates":[3.7459321022,51.0369720459],"type":"Point"}
}