{
  "type": "Feature",
  "properties": {
    "iso:country":"BE",
    "sg:address":"Rue Vaux 12",
    "sg:city":"Vis\u00c9",
    "sg:orig_category":"Woningbouw",
    "sg:phone":"+32 4 374 07 62",
    "sg:postcode":"4600",
    "sg:province":"Li\u00e8ge",
    "wof:name":"Didier Greday",
    "wof:placetype":"venue"
},
  "geometry": {"coordinates":[5.6952648163,50.7378158569],"type":"Point"}
}