{
  "type": "Feature",
  "properties": {
    "addr:full":"Chauss\u00c9e 1 Yvoir Namur 5530",
    "addr:housenumber":"1",
    "addr:postcode":"5530",
    "addr:street":"Chausse\u0301E",
    "iso:country":"BE",
    "sg:address":"Chauss\u00c9e 1",
    "sg:city":"Yvoir",
    "sg:orig_category":"Voertuigen",
    "sg:phone":"+32 82 61 25 82",
    "sg:postcode":"5530",
    "sg:province":"Namur",
    "wof:name":"Garage Brennet",
    "wof:placetype":"venue"
},
  "geometry": {"coordinates":[4.9164681435,50.3185424805],"type":"Point"}
}