{
  "type": "Feature",
  "properties": {
    "iso:country":"BE",
    "sg:address":"Industrieweg 12",
    "sg:city":"Lanaken",
    "sg:classifiers":[
        {
            "category":"Home & Garden",
            "subcategory":"Building Materials",
            "type":"Retail Goods"
        }
    ],
    "sg:phone":"+32 3 830 74 00",
    "sg:postcode":"3620",
    "sg:province":"Limburg",
    "sg:tags":[
        "aluminium",
        "ceiling",
        "panel"
    ],
    "wof:name":"Interalu Nv",
    "wof:placetype":"venue"
},
  "geometry": {"coordinates":[4.3608808517,51.1586456299],"type":"Point"}
}