{
  "type": "Feature",
  "properties": {
    "iso:country":"BE",
    "sg:address":"Bergstraat 90",
    "sg:city":"Heist-op-den-berg",
    "sg:classifiers":[
        {
            "category":"Restaurant",
            "type":"Food & Drink"
        }
    ],
    "sg:phone":"+32 15 25 11 15",
    "sg:postcode":"2220",
    "sg:province":"Antwerpen",
    "wof:name":"Tearoom \u00b4t Kaffepotteke",
    "wof:placetype":"venue"
},
  "geometry": {"coordinates":[4.7210421562,51.0764884949],"type":"Point"}
}