{
  "type": "Feature",
  "properties": {
    "iso:country":"BE",
    "sg:address":"Schepenenlaan 9",
    "sg:city":"Hoeselt",
    "sg:classifiers":[
        {
            "category":"Health Services",
            "subcategory":"Health Practitioner",
            "type":"Services"
        }
    ],
    "sg:phone":"+32 89 41 17 45",
    "sg:postcode":"3730",
    "sg:province":"Limburg",
    "sg:tags":[
        "physiotherapist"
    ],
    "wof:name":"Vangronsveld N",
    "wof:placetype":"venue"
},
  "geometry": {"coordinates":[5.4863839149,50.8493041992],"type":"Point"}
}