{
  "type": "Feature",
  "properties": {
    "addr:full":"Vollezelestraat 150 Gooik (oetingen) Vlaams-Brabant 1755",
    "addr:housenumber":"150",
    "addr:postcode":"1755",
    "addr:street":"Vollezelestraat",
    "iso:country":"BE",
    "sg:address":"Vollezelestraat 150",
    "sg:city":"Gooik (oetingen)",
    "sg:classifiers":[
        {
            "category":"Home & Garden",
            "subcategory":"Carpets & Floor Coverings",
            "type":"Retail Goods"
        }
    ],
    "sg:phone":"+32 54 56 86 94",
    "sg:postcode":"1755",
    "sg:province":"Vlaams-Brabant",
    "sg:tags":[
        "industrial",
        "-"
    ],
    "wof:name":"Lemaire L",
    "wof:placetype":"venue"
},
  "geometry": {"coordinates":[4.0422558784,50.7678375244],"type":"Point"}
}