{
  "type": "Feature",
  "properties": {
    "addr:full":"Baron De Gieylaan 1 De Pinte Oost-Vlaanderen 9840",
    "addr:housenumber":"1",
    "addr:postcode":"9840",
    "addr:street":"Baron De Gieylaan",
    "iso:country":"BE",
    "sg:address":"Baron De Gieylaan 1",
    "sg:city":"De Pinte",
    "sg:classifiers":[
        {
            "category":"Banks & Credit Unions",
            "subcategory":"Investment Brokerage",
            "type":"Services"
        }
    ],
    "sg:phone":"+32 9 282 80 44",
    "sg:postcode":"9840",
    "sg:province":"Oost-Vlaanderen",
    "sg:tags":[
        "jean",
        "casual",
        "wear"
    ],
    "wof:name":"Snoeck Sport/heyse",
    "wof:placetype":"venue"
},
  "geometry": {"coordinates":[3.6498179436,50.9917793274],"type":"Point"}
}