{
  "type": "Feature",
  "properties": {
    "iso:country":"BE",
    "sg:address":"Langerbruggekaai 43",
    "sg:city":"Gent",
    "sg:orig_category":"Woningbouw",
    "sg:phone":"+32 9 253 96 47",
    "sg:postcode":"9042",
    "sg:province":"Oost-Vlaanderen",
    "wof:name":"Bouwonderneming Delanghe",
    "wof:placetype":"venue"
},
  "geometry": {"coordinates":[3.778003931,51.1463508606],"type":"Point"}
}