{
  "type": "Feature",
  "properties": {
    "iso:country":"BE",
    "sg:address":"Moorsbergstraat 11",
    "sg:city":"As",
    "sg:classifiers":[
        {
            "category":"Real Estate",
            "subcategory":"Architect",
            "type":"Services"
        }
    ],
    "sg:phone":"+32 89 65 90 21",
    "sg:postcode":"3665",
    "sg:province":"Limburg",
    "wof:name":"Kessels S",
    "wof:placetype":"venue"
},
  "geometry": {"coordinates":[5.6054439545,51.0261192322],"type":"Point"}
}