{
  "type": "Feature",
  "properties": {
    "addr:full":"Hospitaalstraat 46bf Hamme Oost-Vlaanderen 9220",
    "addr:housenumber":"46bf",
    "addr:postcode":"9220",
    "addr:street":"Hospitaalstraat",
    "iso:country":"BE",
    "sg:address":"Hospitaalstraat 46bf",
    "sg:city":"Hamme",
    "sg:orig_category":"Pain, p\u00e2tisseries and confiseries",
    "sg:phone":"+32 52 47 12 32",
    "sg:postcode":"9220",
    "sg:province":"Oost-Vlaanderen",
    "wof:name":"Martine Colman",
    "wof:placetype":"venue"
},
  "geometry": {"coordinates":[4.1401600838,51.0937080383],"type":"Point"}
}