{
  "type": "Feature",
  "properties": {
    "iso:country":"BE",
    "sg:address":"Westvleterendorp 17",
    "sg:city":"Vleteren (westvleteren)",
    "sg:classifiers":[
        {
            "category":"Retail",
            "subcategory":"Veterinary Services",
            "type":"Services"
        }
    ],
    "sg:phone":"+32 57 40 12 11",
    "sg:postcode":"8640",
    "sg:province":"West-Vlaanderen",
    "sg:tags":[
        "veterinarian"
    ],
    "wof:name":"Vandenberghe M",
    "wof:placetype":"venue"
},
  "geometry": {"coordinates":[2.7183859348,50.926525116],"type":"Point"}
}