{
  "type": "Feature",
  "properties": {
    "addr:full":"Nieuwstraat 8 De Haan West-Vlaanderen 8420",
    "addr:housenumber":"8",
    "addr:postcode":"8420",
    "addr:street":"Nieuwstraat",
    "iso:country":"BE",
    "sg:address":"Nieuwstraat 8",
    "sg:city":"De Haan",
    "sg:orig_category":"Installatie van houten of kunststof schrijnwerk",
    "sg:phone":"+32 59 23 50 10",
    "sg:postcode":"8420",
    "sg:province":"West-Vlaanderen",
    "wof:name":"Delaere Roger",
    "wof:placetype":"venue"
},
  "geometry": {"coordinates":[3.034224987,51.2721214294],"type":"Point"}
}