{
  "type": "Feature",
  "properties": {
    "iso:country":"BE",
    "sg:address":"Houw 49",
    "sg:city":"Herzele (hillegem)",
    "sg:classifiers":[
        {
            "category":"Personal",
            "subcategory":"Beauty Salon",
            "type":"Services"
        }
    ],
    "sg:phone":"+32 53 62 25 48",
    "sg:postcode":"9550",
    "sg:province":"Oost-Vlaanderen",
    "sg:tags":[
        "lady",
        "-",
        "hairdressing"
    ],
    "wof:name":"Trendy",
    "wof:placetype":"venue"
},
  "geometry": {"coordinates":[3.8707718849,50.9020996094],"type":"Point"}
}