{
  "type": "Feature",
  "properties": {
    "iso:country":"BE",
    "sg:address":"Rue De La Limite 131c",
    "sg:city":"Herstal",
    "sg:classifiers":[
        {
            "category":"Building & Trades",
            "subcategory":"Cleaning & Sanitation",
            "type":"Services"
        }
    ],
    "sg:phone":"+32 4 240 10 34",
    "sg:postcode":"4040",
    "sg:province":"Li\u00e8ge",
    "sg:tags":[
        "janitor"
    ],
    "wof:name":"Piron",
    "wof:placetype":"venue"
},
  "geometry": {"coordinates":[5.6067762375,50.6829948425],"type":"Point"}
}