{
  "type": "Feature",
  "properties": {
    "iso:country":"BE",
    "sg:address":"Legeweg 21",
    "sg:city":"Jabbeke",
    "sg:orig_category":"Eleveurs de bovins",
    "sg:phone":"+32 50 81 13 75",
    "sg:postcode":"8490",
    "sg:province":"West-Vlaanderen",
    "wof:name":"Jules Acke",
    "wof:placetype":"venue"
},
  "geometry": {"coordinates":[3.1152288914,51.1929397583],"type":"Point"}
}