{
  "type": "Feature",
  "properties": {
    "iso:country":"BE",
    "sg:address":"Nederokkerzeelsesteenweg 20",
    "sg:city":"Kortenberg",
    "sg:orig_category":"Woningbouw",
    "sg:phone":"+32 2 759 40 37",
    "sg:postcode":"3071",
    "sg:province":"Vlaams-Brabant",
    "wof:name":"Michiels En Zoon",
    "wof:placetype":"venue"
},
  "geometry": {"coordinates":[4.5645179749,50.9073104858],"type":"Point"}
}