{
  "type": "Feature",
  "properties": {
    "iso:country":"BE",
    "sg:address":"Rue Des Ch\u00canes 184",
    "sg:city":"Dour",
    "sg:orig_category":"Rundveehouders",
    "sg:phone":"+32 65 65 24 05",
    "sg:postcode":"7370",
    "sg:province":"Hainaut",
    "wof:name":"Jose Dufour",
    "wof:placetype":"venue"
},
  "geometry": {"coordinates":[3.7513730526,50.381942749],"type":"Point"}
}