{
  "type": "Feature",
  "properties": {
    "addr:full":"Heidestraat 3 Mechelen (heffen) Antwerpen 2801",
    "addr:housenumber":"3",
    "addr:postcode":"2801",
    "addr:street":"Heidestraat",
    "iso:country":"BE",
    "sg:address":"Heidestraat 3",
    "sg:city":"Mechelen (heffen)",
    "sg:classifiers":[
        {
            "category":"Personal",
            "subcategory":"Beauty Salon",
            "type":"Services"
        }
    ],
    "sg:phone":"+32 3 866 36 95",
    "sg:postcode":"2801",
    "sg:province":"Antwerpen",
    "wof:name":"Bellezza",
    "wof:placetype":"venue"
},
  "geometry": {"coordinates":[4.3918008804,51.0385169983],"type":"Point"}
}