{
  "type": "Feature",
  "properties": {
    "iso:country":"BE",
    "sg:address":"Rue De Long Sart 38",
    "sg:city":"Namur",
    "sg:orig_category":"M\u00e9decins and sp\u00e9cialistes",
    "sg:phone":"+32 81 21 09 12",
    "sg:postcode":"5021",
    "sg:province":"Namur",
    "wof:name":"P. Vandepapeliere",
    "wof:placetype":"venue"
},
  "geometry": {"coordinates":[4.9140701294,50.4787559509],"type":"Point"}
}