{
  "type": "Feature",
  "properties": {
    "iso:country":"BE",
    "sg:address":"Rue De La Station 34",
    "sg:city":"Morlanwelz",
    "sg:orig_category":"Huishoudapparaten, televisies and radio's",
    "sg:phone":"+32 64 45 16 38",
    "sg:postcode":"7141",
    "sg:province":"Hainaut",
    "wof:name":"Leon Caty",
    "wof:placetype":"venue"
},
  "geometry": {"coordinates":[4.261452198,50.44789505],"type":"Point"}
}