{
  "type": "Feature",
  "properties": {
    "iso:country":"BE",
    "sg:address":"Rue D'argenteau 15",
    "sg:city":"Oupeye",
    "sg:orig_category":"Industri\u00eble and commerci\u00eble bouw Woningbouw",
    "sg:phone":"+32 4 379 96 40",
    "sg:postcode":"4681",
    "sg:province":"Li\u00e8ge",
    "wof:name":"Batitec",
    "wof:placetype":"venue"
},
  "geometry": {"coordinates":[5.6767849922,50.7128639221],"type":"Point"}
}