{
  "type": "Feature",
  "properties": {
    "iso:country":"BE",
    "sg:address":"Bogaardenstraat 19",
    "sg:city":"Aarschot",
    "sg:classifiers":[
        {
            "category":"Shopping",
            "subcategory":"Hobbies, Toys, & Games",
            "type":"Retail Goods"
        }
    ],
    "sg:phone":"+32 16 56 62 23",
    "sg:postcode":"3200",
    "sg:province":"Vlaams-Brabant",
    "sg:tags":[
        "toy",
        "-"
    ],
    "wof:name":"Ingelberts",
    "wof:placetype":"venue"
},
  "geometry": {"coordinates":[4.8393850327,50.9873733521],"type":"Point"}
}