{
  "type": "Feature",
  "properties": {
    "addr:full":"Van Den Heckestraat 41b43 Gent Oost-Vlaanderen 9050",
    "addr:housenumber":"41b43",
    "addr:postcode":"9050",
    "addr:street":"Van Den Heckestraat;Oost-Vlaanderen",
    "iso:country":"BE",
    "sg:address":"Van Den Heckestraat 41b43",
    "sg:city":"Gent",
    "sg:orig_category":"Instituts pour adultes moins valides",
    "sg:phone":"+32 9 231 96 08",
    "sg:postcode":"9050",
    "sg:province":"Oost-Vlaanderen",
    "wof:name":"Home Emma\u00dcs",
    "wof:placetype":"venue"
},
  "geometry": {"coordinates":[3.7452449799,51.0363616943],"type":"Point"}
}