{
  "type": "Feature",
  "properties": {
    "addr:full":"Centrum Zuid 1117 Houthalen-helchteren Limburg 3530",
    "addr:housenumber":"1117",
    "addr:postcode":"3530",
    "addr:street":"Centrum Zuid",
    "iso:country":"BE",
    "sg:address":"Centrum Zuid 1117",
    "sg:city":"Houthalen-helchteren",
    "sg:orig_category":"Industri\u00eble and commerci\u00eble bouw Installatie van metalen schrijnwerk",
    "sg:phone":"+32 11 52 40 06",
    "sg:postcode":"3530",
    "sg:province":"Limburg",
    "wof:name":"Dilien",
    "wof:placetype":"venue"
},
  "geometry": {"coordinates":[5.3518128395,51.0194778442],"type":"Point"}
}