{
  "type": "Feature",
  "properties": {
    "iso:country":"BE",
    "sg:address":"Binnensteenweg 182",
    "sg:city":"Boechout",
    "sg:orig_category":"Produits pharmaceutiques Gr",
    "sg:phone":"+32 3 454 00 96",
    "sg:postcode":"2530",
    "sg:province":"Antwerpen",
    "wof:name":"Hav",
    "wof:placetype":"venue"
},
  "geometry": {"coordinates":[4.4914097786,51.1665763855],"type":"Point"}
}