{
  "type": "Feature",
  "properties": {
    "iso:country":"BE",
    "sg:address":"Legen Heirweg 117",
    "sg:city":"Temse",
    "sg:classifiers":[
        {
            "category":"Cafe",
            "type":"Food & Drink"
        }
    ],
    "sg:phone":"+32 52 46 39 98",
    "sg:postcode":"9140",
    "sg:province":"Oost-Vlaanderen",
    "sg:tags":[
        "caf\u00e9s"
    ],
    "wof:name":"Vk Tielrode",
    "wof:placetype":"venue"
},
  "geometry": {"coordinates":[4.153637886,51.1139183044],"type":"Point"}
}