{
  "type": "Feature",
  "properties": {
    "addr:full":"Raerener Strasse 42 Raeren (eynatten) Li\u00e8ge 4731",
    "addr:housenumber":"42",
    "addr:postcode":"4731",
    "addr:street":"Raerener Strasse",
    "iso:country":"BE",
    "sg:address":"Raerener Strasse 42",
    "sg:city":"Raeren (eynatten)",
    "sg:classifiers":[
        {
            "category":"Arena",
            "subcategory":"Sports Club",
            "type":"Entertainment"
        }
    ],
    "sg:phone":"+32 87 85 10 82",
    "sg:postcode":"4731",
    "sg:province":"Li\u00e8ge",
    "wof:name":"Tennis-squash-center Lichtenbusch Ag",
    "wof:placetype":"venue"
},
  "geometry": {"coordinates":[6.0811729431,50.6908683777],"type":"Point"}
}