{
  "type": "Feature",
  "properties": {
    "addr:full":"Fabrieksstraat 40 Willebroek Antwerpen 2830",
    "addr:housenumber":"40",
    "addr:postcode":"2830",
    "addr:street":"Fabrieksstraat",
    "iso:country":"BE",
    "sg:address":"Fabrieksstraat 40",
    "sg:city":"Willebroek",
    "sg:orig_category":"Diverse kredietdiensten",
    "sg:postcode":"2830",
    "sg:province":"Antwerpen",
    "wof:name":"Bancontact-mister Cash",
    "wof:placetype":"venue"
},
  "geometry": {"coordinates":[4.3643779755,51.061088562],"type":"Point"}
}