{
  "type": "Feature",
  "properties": {
    "iso:country":"BE",
    "sg:address":"Madeliefjesstraat 32",
    "sg:city":"Grimbergen",
    "sg:orig_category":"Boekhouders",
    "sg:postcode":"1850",
    "sg:province":"Vlaams-Brabant",
    "wof:name":"Philippe Thienpont",
    "wof:placetype":"venue"
},
  "geometry": {"coordinates":[4.3877820969,50.9334716797],"type":"Point"}
}