{
  "type": "Feature",
  "properties": {
    "iso:country":"BE",
    "sg:address":"Chauss\u00e9e De Bruxelles 115",
    "sg:city":"Braine-le-comte",
    "sg:classifiers":[
        {
            "category":"Retail",
            "subcategory":"Auto Repair",
            "type":"Services"
        }
    ],
    "sg:phone":"+32 67 55 40 39",
    "sg:postcode":"7090",
    "sg:province":"Hainaut",
    "sg:tags":[
        "breakdown",
        "automobile",
        "-",
        "recovery"
    ],
    "wof:name":"Pilote (carrosserie)",
    "wof:placetype":"venue"
},
  "geometry": {"coordinates":[4.1439790726,50.6247749329],"type":"Point"}
}