{
  "type": "Feature",
  "properties": {
    "iso:country":"BE",
    "sg:address":"Kesselsesteenweg 46",
    "sg:city":"Lier",
    "sg:classifiers":[
        {
            "category":"Parking",
            "subcategory":"Bicycle",
            "type":"Transportation"
        }
    ],
    "sg:phone":"+32 3 489 26 14",
    "sg:postcode":"2500",
    "sg:province":"Antwerpen",
    "sg:tags":[
        "chiropodist"
    ],
    "wof:name":"Raets G",
    "wof:placetype":"venue"
},
  "geometry": {"coordinates":[4.5885090828,51.1304321289],"type":"Point"}
}