{
  "type": "Feature",
  "properties": {
    "iso:country":"BE",
    "sg:address":"Rue Vin\u00e2ve 131",
    "sg:city":"Li\u00e8ge 1 (grivegn\u00e9e)",
    "sg:classifiers":[
        {
            "category":"Community Center",
            "type":"Public Place"
        }
    ],
    "sg:phone":"+32 4 365 16 66",
    "sg:postcode":"4030",
    "sg:province":"Li\u00e8ge",
    "sg:tags":[
        "medical"
    ],
    "wof:name":"Centre M\u00e9dical Sp\u00e9cialis\u00e9 De Grivegn\u00e9e",
    "wof:placetype":"venue"
},
  "geometry": {"coordinates":[5.6076359749,50.6165504456],"type":"Point"}
}