{
  "type": "Feature",
  "properties": {
    "iso:country":"BE",
    "sg:address":"Genendries 28",
    "sg:city":"Millen",
    "sg:orig_category":"Royal Canin. Combustibles. Fleurs and plantes. Animaux domestiques and accessoires. Souvenirs and ob",
    "sg:phone":"+32 12 23 26 94",
    "sg:postcode":"3770",
    "sg:province":"Limburg",
    "wof:name":"Stassen Jos Aveve",
    "wof:placetype":"venue"
},
  "geometry": {"coordinates":[5.5552229881,50.7878379822],"type":"Point"}
}