{
  "type": "Feature",
  "properties": {
    "addr:full":"Ambachtstraat 25 Torhout West-Vlaanderen 8820",
    "addr:housenumber":"25",
    "addr:postcode":"8820",
    "addr:street":"Ambachtstraat",
    "iso:country":"BE",
    "sg:address":"Ambachtstraat 25",
    "sg:city":"Torhout",
    "sg:classifiers":[
        {
            "category":"Banks & Credit Unions",
            "subcategory":"Investment Brokerage",
            "type":"Services"
        }
    ],
    "sg:phone":"+32 50 21 64 91",
    "sg:postcode":"8820",
    "sg:province":"West-Vlaanderen",
    "sg:tags":[
        "printing",
        "-"
    ],
    "wof:name":"Drukkerij-uit.cornille L. Bvba",
    "wof:placetype":"venue"
},
  "geometry": {"coordinates":[3.1110489368,51.0791664124],"type":"Point"}
}