{
  "type": "Feature",
  "properties": {
    "iso:country":"BE",
    "sg:address":"Hasseltsesteenweg 461",
    "sg:city":"Tongeren",
    "sg:orig_category":"P\u00e9pini\u00e9ristes",
    "sg:phone":"+32 12 39 54 40",
    "sg:postcode":"3700",
    "sg:province":"Limburg",
    "wof:name":"Fa. Vanhove",
    "wof:placetype":"venue"
},
  "geometry": {"coordinates":[5.459335804,50.7829055786],"type":"Point"}
}