{
  "type": "Feature",
  "properties": {
    "iso:country":"BE",
    "sg:address":"Asberg 10",
    "sg:city":"Mol",
    "sg:classifiers":[
        {
            "category":"Professional",
            "subcategory":"Management & Consulting",
            "type":"Services"
        }
    ],
    "sg:phone":"+32 14 31 82 39",
    "sg:postcode":"2400",
    "sg:province":"Antwerpen",
    "sg:tags":[
        "consultant"
    ],
    "wof:name":"Cpc Bvba",
    "wof:placetype":"venue"
},
  "geometry": {"coordinates":[5.0813322067,51.1656684875],"type":"Point"}
}