{
  "type": "Feature",
  "properties": {
    "iso:country":"BE",
    "sg:address":"Route Militaire 404",
    "sg:city":"Ans",
    "sg:orig_category":"Ordinateurs and \u00e9quipement informatique",
    "sg:phone":"+32 4 263 31 13",
    "sg:postcode":"4432",
    "sg:province":"Li\u00e8ge",
    "wof:name":"S.i.a.b.t.",
    "wof:placetype":"venue"
},
  "geometry": {"coordinates":[5.5148057938,50.6829986572],"type":"Point"}
}