{
  "type": "Feature",
  "properties": {
    "addr:full":"Wijngaardlaan 1 Leuven (heverlee) Vlaams-Brabant 3001",
    "addr:housenumber":"1",
    "addr:postcode":"3001",
    "addr:street":"Wijngaardlaan",
    "iso:country":"BE",
    "sg:address":"Wijngaardlaan 1",
    "sg:city":"Leuven (heverlee)",
    "sg:classifiers":[
        {
            "category":"Health Services",
            "subcategory":"Dentist",
            "type":"Services"
        }
    ],
    "sg:phone":"+32 16 23 58 58",
    "sg:postcode":"3001",
    "sg:province":"Vlaams-Brabant",
    "wof:name":"Brosens B",
    "wof:placetype":"venue"
},
  "geometry": {"coordinates":[4.6905999184,50.8603363037],"type":"Point"}
}