{
  "type": "Feature",
  "properties": {
    "addr:full":"Ovenstraat 17 Roeselare West-Vlaanderen 8800",
    "addr:housenumber":"17",
    "addr:postcode":"8800",
    "addr:street":"Ovenstraat",
    "iso:country":"BE",
    "sg:address":"Ovenstraat 17",
    "sg:city":"Roeselare",
    "sg:classifiers":[
        {
            "category":"Professional",
            "subcategory":"Art Services",
            "type":"Services"
        }
    ],
    "sg:phone":"+32 51 24 53 30",
    "sg:postcode":"8800",
    "sg:province":"West-Vlaanderen",
    "sg:tags":[
        "stand",
        "construction",
        "exhibition",
        "fair",
        "trade"
    ],
    "wof:name":"Gm Productions",
    "wof:placetype":"venue"
},
  "geometry": {"coordinates":[3.0985860825,50.9481239319],"type":"Point"}
}