{
  "type": "Feature",
  "properties": {
    "iso:country":"BE",
    "sg:address":"Transvaal 19",
    "sg:city":"Hamme",
    "sg:orig_category":"Sportclubs",
    "sg:phone":"+32 52 47 02 04",
    "sg:postcode":"9220",
    "sg:province":"Oost-Vlaanderen",
    "wof:name":"T.c. 78",
    "wof:placetype":"venue"
},
  "geometry": {"coordinates":[4.1301660538,51.0907058716],"type":"Point"}
}