{
  "type": "Feature",
  "properties": {
    "iso:country":"BE",
    "sg:address":"Vleugtweg 21",
    "sg:city":"Wezemaal",
    "sg:orig_category":"Bloemen and planten",
    "sg:phone":"+32 16 58 06 83",
    "sg:postcode":"3111",
    "sg:province":"Vlaams-Brabant",
    "wof:name":"Bloemen Rozalinde",
    "wof:placetype":"venue"
},
  "geometry": {"coordinates":[4.7512187958,50.9486465454],"type":"Point"}
}