{
  "type": "Feature",
  "properties": {
    "iso:country":"BE",
    "sg:address":"Pastoor Schelkensplein",
    "sg:city":"Nijlen (kessel)",
    "sg:classifiers":[
        {
            "category":"Fast Food",
            "type":"Food & Drink"
        }
    ],
    "sg:phone":"+32 3 480 78 90",
    "sg:postcode":"2560",
    "sg:province":"Antwerpen",
    "sg:tags":[
        "fried",
        "stand",
        "potato"
    ],
    "wof:name":"Maria",
    "wof:placetype":"venue"
},
  "geometry": {"coordinates":[4.6279911995,51.1393089294],"type":"Point"}
}