{
  "type": "Feature",
  "properties": {
    "iso:country":"BE",
    "sg:address":"Chemin Malplaquet 8",
    "sg:city":"Ath (ghislenghien)",
    "sg:classifiers":[
        {
            "category":"Wholesale",
            "subcategory":"Machinery & Supplies",
            "type":"Manufacturing & Wholesale Goods"
        }
    ],
    "sg:phone":"+32 68 55 13 28",
    "sg:postcode":"7822",
    "sg:province":"Hainaut",
    "sg:tags":[
        "water",
        "pump",
        "-"
    ],
    "wof:name":"Aubia Sa",
    "wof:placetype":"venue"
},
  "geometry": {"coordinates":[3.862003088,50.6521606445],"type":"Point"}
}