{
  "type": "Feature",
  "properties": {
    "addr:full":"Rue Marcel De Linc\u00c9 17 Oupeye Li\u00e8ge 4680",
    "addr:housenumber":"17",
    "addr:postcode":"4680",
    "addr:street":"Rue Marcel De Lince\u0301",
    "iso:country":"BE",
    "sg:address":"Rue Marcel De Linc\u00c9 17",
    "sg:city":"Oupeye",
    "sg:classifiers":[
        {
            "category":"Insurance",
            "subcategory":"Insurance Agent",
            "type":"Services"
        }
    ],
    "sg:phone":"+32 4 248 34 07",
    "sg:postcode":"4680",
    "sg:province":"Li\u00e8ge",
    "sg:tags":[
        "verzekeringsmakelaars",
        "expert"
    ],
    "wof:name":"Philippe Collard",
    "wof:placetype":"venue"
},
  "geometry": {"coordinates":[5.6363711357,50.710647583],"type":"Point"}
}