{
  "type": "Feature",
  "properties": {
    "iso:country":"BE",
    "sg:address":"Doornstraat 13",
    "sg:city":"Wingene",
    "sg:classifiers":[
        {
            "category":"Retail",
            "subcategory":"Animal Services",
            "type":"Services"
        }
    ],
    "sg:phone":"+32 51 65 86 81",
    "sg:postcode":"8750",
    "sg:province":"West-Vlaanderen",
    "sg:tags":[
        "farrier"
    ],
    "wof:name":"Herpoel C",
    "wof:placetype":"venue"
},
  "geometry": {"coordinates":[3.2558250427,51.0703163147],"type":"Point"}
}