{
  "type": "Feature",
  "properties": {
    "iso:country":"BE",
    "sg:address":"Hazelaarsdreef 9",
    "sg:city":"Harelbeke",
    "sg:orig_category":"Entretien and r\u00e9parations de voitures",
    "sg:phone":"+32 56 22 19 70",
    "sg:postcode":"8530",
    "sg:province":"West-Vlaanderen",
    "wof:name":"Philippe Ryssaert",
    "wof:placetype":"venue"
},
  "geometry": {"coordinates":[3.3093709946,50.8398284912],"type":"Point"}
}