{
  "type": "Feature",
  "properties": {
    "addr:full":"Place De Frasnes 1 Les Bons Villers (frasnes-lez-gosselies) Hainaut 6210",
    "addr:housenumber":"1",
    "addr:postcode":"6210",
    "addr:street":"Place De Frasnes",
    "iso:country":"BE",
    "sg:address":"Place De Frasnes 1",
    "sg:city":"Les Bons Villers (frasnes-lez-gosselies)",
    "sg:classifiers":[
        {
            "category":"Social Services",
            "type":"Services"
        }
    ],
    "sg:phone":"+32 71 85 26 92",
    "sg:postcode":"6210",
    "sg:province":"Hainaut",
    "wof:name":"C.p.a.s.",
    "wof:placetype":"venue"
},
  "geometry": {"coordinates":[4.4511561394,50.5378227234],"type":"Point"}
}