{
  "type": "Feature",
  "properties": {
    "addr:full":"4 Leuvensepln Brussel Bruxelles-Capitale 1000",
    "addr:housenumber":"4",
    "addr:postcode":"1000",
    "addr:street":"Leuvensepln Brussel",
    "iso:country":"BE",
    "sg:address":"4 Leuvensepln",
    "sg:city":"Brussel",
    "sg:classifiers":[
        {
            "category":"Professional",
            "subcategory":"Business Services",
            "type":"Services"
        }
    ],
    "sg:phone":"+32 2 227 53 11",
    "sg:postcode":"1000",
    "sg:province":"Bruxelles-Capitale",
    "sg:tags":[
        "body",
        "advice"
    ],
    "wof:name":"Flanders Foreign Investment Office",
    "wof:placetype":"venue"
},
  "geometry": {"coordinates":[4.36247015,50.8482704163],"type":"Point"}
}