{
  "type": "Feature",
  "properties": {
    "addr:full":"Boulevard De La Dodaine 50 Nivelles Brabant Wallon 1400",
    "addr:housenumber":"50",
    "addr:postcode":"1400",
    "addr:street":"Boulevard De La Dodaine",
    "iso:country":"BE",
    "sg:address":"Boulevard De La Dodaine 50",
    "sg:city":"Nivelles",
    "sg:classifiers":[
        {
            "category":"Utilities",
            "subcategory":"Natural Gas",
            "type":"Services"
        }
    ],
    "sg:phone":"+32 67 84 34 85",
    "sg:postcode":"1400",
    "sg:province":"Brabant Wallon",
    "sg:tags":[
        "firework"
    ],
    "wof:name":"Ricard",
    "wof:placetype":"venue"
},
  "geometry": {"coordinates":[4.3222699165,50.5941810608],"type":"Point"}
}