{
  "type": "Feature",
  "properties": {
    "addr:full":"Sterrewegel 7 Zaventem (sterrebeek) Vlaams-Brabant 1933",
    "addr:housenumber":"7",
    "addr:postcode":"1933",
    "addr:street":"Sterrewegel",
    "iso:country":"BE",
    "sg:address":"Sterrewegel 7",
    "sg:city":"Zaventem (sterrebeek)",
    "sg:classifiers":[
        {
            "category":"Home & Garden",
            "subcategory":"Building Materials",
            "type":"Retail Goods"
        }
    ],
    "sg:phone":"+32 2 731 46 56",
    "sg:postcode":"1933",
    "sg:province":"Vlaams-Brabant",
    "sg:tags":[
        "article",
        "-",
        "do-it-yourself"
    ],
    "wof:name":"Crea Home Centrale",
    "wof:placetype":"venue"
},
  "geometry": {"coordinates":[4.4965882301,50.8670692444],"type":"Point"}
}