{
  "type": "Feature",
  "properties": {
    "addr:full":"Boskant 16 Westerlo Antwerpen 2260",
    "addr:housenumber":"16",
    "addr:postcode":"2260",
    "addr:street":"Boskant",
    "iso:country":"BE",
    "sg:address":"Boskant 16",
    "sg:city":"Westerlo",
    "sg:orig_category":"Emballages en papier and carton Fab. Equipement divers pour commerces Emballages en plastique Fab. I",
    "sg:phone":"+32 14 54 97 25",
    "sg:postcode":"2260",
    "sg:province":"Antwerpen",
    "wof:name":"Verbeek En Zonen",
    "wof:placetype":"venue"
},
  "geometry": {"coordinates":[4.91065979,51.0952568054],"type":"Point"}
}