{
  "type": "Feature",
  "properties": {
    "addr:full":"Bogaardestraat 65 Maldegem Oost-Vlaanderen 9990",
    "addr:housenumber":"65",
    "addr:postcode":"9990",
    "addr:street":"Bogaardestraat",
    "iso:country":"BE",
    "sg:address":"Bogaardestraat 65",
    "sg:city":"Maldegem",
    "sg:orig_category":"Non-Classified Establishments",
    "sg:phone":"+32 50 71 12 76",
    "sg:postcode":"9990",
    "sg:province":"Oost-Vlaanderen",
    "wof:name":"Longueville R",
    "wof:placetype":"venue"
},
  "geometry": {"coordinates":[3.4377000332,51.2059326172],"type":"Point"}
}