{
  "type": "Feature",
  "properties": {
    "addr:full":"Schoolstraat 60 Waarschoot Oost-Vlaanderen 9950",
    "addr:housenumber":"60",
    "addr:postcode":"9950",
    "addr:street":"Schoolstraat",
    "iso:country":"BE",
    "sg:address":"Schoolstraat 60",
    "sg:city":"Waarschoot",
    "sg:orig_category":"Notarissen",
    "sg:phone":"+32 9 377 18 94",
    "sg:postcode":"9950",
    "sg:province":"Oost-Vlaanderen",
    "wof:name":"Frank De Raedt",
    "wof:placetype":"venue"
},
  "geometry": {"coordinates":[3.5999979973,51.1541824341],"type":"Point"}
}