{
  "type": "Feature",
  "properties": {
    "addr:full":"Kortestraat 2 Leuven Vlaams-Brabant 3000",
    "addr:housenumber":"2",
    "addr:postcode":"3000",
    "addr:street":"Kortestraat",
    "iso:country":"BE",
    "sg:address":"Kortestraat 2",
    "sg:city":"Leuven",
    "sg:classifiers":[
        {
            "category":"Travel",
            "subcategory":"Hotels & Motels",
            "type":"Entertainment"
        }
    ],
    "sg:phone":"+32 16 23 87 80",
    "sg:postcode":"3000",
    "sg:province":"Vlaams-Brabant",
    "wof:name":"Jeff's Guesthouse",
    "wof:placetype":"venue"
},
  "geometry": {"coordinates":[4.7001218796,50.8789138794],"type":"Point"}
}