{
  "type": "Feature",
  "properties": {
    "iso:country":"BE",
    "sg:address":"Sint-truiderstraat 14",
    "sg:city":"Tongeren",
    "sg:orig_category":"Newspapers, magazines, periodicals - Publishers",
    "sg:phone":"+32 12 23 24 50",
    "sg:postcode":"3700",
    "sg:province":"Limburg",
    "wof:name":"Het Poske",
    "wof:placetype":"venue"
},
  "geometry": {"coordinates":[5.4625329971,50.7803726196],"type":"Point"}
}