{
  "type": "Feature",
  "properties": {
    "addr:full":"Memlinglaan 12 De Pinte Oost-Vlaanderen 9840",
    "addr:housenumber":"12",
    "addr:postcode":"9840",
    "addr:street":"Memlinglaan",
    "iso:country":"BE",
    "sg:address":"Memlinglaan 12",
    "sg:city":"De Pinte",
    "sg:classifiers":[
        {
            "category":"Manufacturing",
            "subcategory":"Musical Instruments",
            "type":"Manufacturing & Wholesale Goods"
        }
    ],
    "sg:phone":"+32 9 282 46 00",
    "sg:postcode":"9840",
    "sg:province":"Oost-Vlaanderen",
    "sg:tags":[
        "repair",
        "mainten",
        "-"
    ],
    "wof:name":"Vermeulen R",
    "wof:placetype":"venue"
},
  "geometry": {"coordinates":[3.6384758949,50.9926986694],"type":"Point"}
}