{
  "type": "Feature",
  "properties": {
    "addr:full":"Sperwerlaan 1 Sint-pieters-woluwe/woluwe-sai Bruxelles-Capitale 1150",
    "addr:housenumber":"1",
    "addr:postcode":"1150",
    "addr:street":"Sperwerlaan",
    "iso:country":"BE",
    "sg:address":"Sperwerlaan 1",
    "sg:city":"Sint-pieters-woluwe/woluwe-sai",
    "sg:orig_category":"Banken and kredietinstellingen",
    "sg:phone":"+32 2 762 17 65",
    "sg:postcode":"1150",
    "sg:province":"Bruxelles-Capitale",
    "wof:name":"Ippa",
    "wof:placetype":"venue"
},
  "geometry": {"coordinates":[4.4180088043,50.8278007507],"type":"Point"}
}