{
  "type": "Feature",
  "properties": {
    "addr:full":"Bergense Steenweg 642 Anderlecht Bruxelles-Capitale 1070",
    "addr:housenumber":"642",
    "addr:postcode":"1070",
    "addr:street":"Bergense Steenweg",
    "iso:country":"BE",
    "sg:address":"Bergense Steenweg 642",
    "sg:city":"Anderlecht",
    "sg:orig_category":"Industri\u00eble wasserijen and droogkuis",
    "sg:phone":"+32 2 523 13 55",
    "sg:postcode":"1070",
    "sg:province":"Bruxelles-Capitale",
    "wof:name":"Speedy Wash",
    "wof:placetype":"venue"
},
  "geometry": {"coordinates":[4.308262825,50.8301086426],"type":"Point"}
}