{
  "type": "Feature",
  "properties": {
    "iso:country":"BE",
    "sg:address":"Avenue Du Doyard 3",
    "sg:city":"Stavelot",
    "sg:classifiers":[
        {
            "category":"Building & Trades",
            "subcategory":"Construction",
            "type":"Services"
        }
    ],
    "sg:phone":"+32 80 86 29 30",
    "sg:postcode":"4970",
    "sg:province":"Li\u00e8ge",
    "sg:tags":[
        "installation",
        "-",
        "central",
        "heating"
    ],
    "wof:name":"Havet & Fils Sprl",
    "wof:placetype":"venue"
},
  "geometry": {"coordinates":[5.9266829491,50.3937530518],"type":"Point"}
}