{
  "type": "Feature",
  "properties": {
    "addr:full":"Boomgaardstraat 7 Merelbeke Oost-Vlaanderen 9820",
    "addr:housenumber":"7",
    "addr:postcode":"9820",
    "addr:street":"Boomgaardstraat",
    "iso:country":"BE",
    "sg:address":"Boomgaardstraat 7",
    "sg:city":"Merelbeke",
    "sg:classifiers":[
        {
            "category":"Building & Trades",
            "subcategory":"Plumbing",
            "type":"Services"
        }
    ],
    "sg:phone":"+32 9 231 56 00",
    "sg:postcode":"9820",
    "sg:province":"Oost-Vlaanderen",
    "sg:tags":[
        "diver",
        "commerce",
        "gr",
        "pour",
        "equipement"
    ],
    "wof:name":"Clement",
    "wof:placetype":"venue"
},
  "geometry": {"coordinates":[3.7597370148,50.9903488159],"type":"Point"}
}