{
  "type": "Feature",
  "properties": {
    "iso:country":"BE",
    "sg:address":"Rue Ch\u00e2mont 4",
    "sg:city":"La Roche-en-ardenne",
    "sg:classifiers":[
        {
            "category":"Shopping",
            "subcategory":"Clothing, Apparel, & Fashions",
            "type":"Retail Goods"
        }
    ],
    "sg:phone":"+32 84 41 12 19",
    "sg:postcode":"6980",
    "sg:province":"Luxembourg",
    "sg:tags":[
        "lady",
        "clothing",
        "-"
    ],
    "wof:name":"B.c.b.g.",
    "wof:placetype":"venue"
},
  "geometry": {"coordinates":[5.5768899918,50.1838150024],"type":"Point"}
}