{
  "type": "Feature",
  "properties": {
    "addr:full":"\u00b4t Hoge 118 Kortrijk West-Vlaanderen 8500",
    "addr:housenumber":"118",
    "addr:postcode":"8500",
    "addr:street":"Hoge",
    "iso:country":"BE",
    "sg:address":"\u00b4t Hoge 118",
    "sg:city":"Kortrijk",
    "sg:orig_category":"Entretien and r\u00e9parations de voitures. V\u00e9hicules automobiles. Stations-service and carburants",
    "sg:phone":"+32 56 21 57 48",
    "sg:postcode":"8500",
    "sg:province":"West-Vlaanderen",
    "wof:name":"Garage Vanderheeren",
    "wof:placetype":"venue"
},
  "geometry": {"coordinates":[3.2887198925,50.7949562073],"type":"Point"}
}