{
  "type": "Feature",
  "properties": {
    "addr:full":"Hoeksken 95 Sint-lievens-houtem Oost-Vlaanderen 9520",
    "addr:housenumber":"95",
    "addr:postcode":"9520",
    "addr:street":"Hoeksken",
    "iso:country":"BE",
    "sg:address":"Hoeksken 95",
    "sg:city":"Sint-lievens-houtem",
    "sg:classifiers":[
        {
            "category":"Health Services",
            "subcategory":"Health Practitioner",
            "type":"Services"
        }
    ],
    "sg:phone":"+32 478 32 45 59",
    "sg:postcode":"9520",
    "sg:province":"Oost-Vlaanderen",
    "sg:tags":[
        "physiotherapist"
    ],
    "wof:name":"Fosselle Katia",
    "wof:placetype":"venue"
},
  "geometry": {"coordinates":[3.8414471149,50.9166641235],"type":"Point"}
}