{
  "type": "Feature",
  "properties": {
    "addr:full":"Rue Du Blanc Scourchet 1 Ellezelles Hainaut 7890",
    "addr:housenumber":"1",
    "addr:postcode":"7890",
    "addr:street":"Rue Du Blanc Scourchet",
    "iso:country":"BE",
    "sg:address":"Rue Du Blanc Scourchet 1",
    "sg:city":"Ellezelles",
    "sg:orig_category":"Woningbouw",
    "sg:phone":"+32 68 44 85 18",
    "sg:postcode":"7890",
    "sg:province":"Hainaut",
    "wof:name":"Ongena Fr\u00c8res",
    "wof:placetype":"venue"
},
  "geometry": {"coordinates":[3.7128939629,50.7172164917],"type":"Point"}
}