{
  "type": "Feature",
  "properties": {
    "iso:country":"BE",
    "sg:address":"Hameau De Rennes 6",
    "sg:city":"Hamoir",
    "sg:orig_category":"Boissons",
    "sg:phone":"+32 86 38 86 34",
    "sg:postcode":"4180",
    "sg:province":"Li\u00e8ge",
    "wof:name":"Jacques Legros",
    "wof:placetype":"venue"
},
  "geometry": {"coordinates":[5.531235218,50.4267807007],"type":"Point"}
}