{
  "type": "Feature",
  "properties": {
    "iso:country":"BE",
    "sg:address":"Hoogakkers 37 A",
    "sg:city":"Arendonk",
    "sg:orig_category":"Jardinage",
    "sg:phone":"+32 14 67 09 30",
    "sg:postcode":"2370",
    "sg:province":"Antwerpen",
    "wof:name":"Gazonexpress",
    "wof:placetype":"venue"
},
  "geometry": {"coordinates":[5.0770630836,51.3245201111],"type":"Point"}
}