{
  "type": "Feature",
  "properties": {
    "addr:full":"Rue Du Stordoir 5a La Bruyere Namur 5081",
    "addr:housenumber":"5a",
    "addr:postcode":"5081",
    "addr:street":"Rue Du Stordoir;Bruyere",
    "iso:country":"BE",
    "sg:address":"Rue Du Stordoir 5a",
    "sg:city":"La Bruyere",
    "sg:orig_category":"Herstellingen and onderhoud van auto's",
    "sg:phone":"+32 81 56 87 87",
    "sg:postcode":"5081",
    "sg:province":"Namur",
    "wof:name":"Francis Challes",
    "wof:placetype":"venue"
},
  "geometry": {"coordinates":[4.7829780579,50.5363922119],"type":"Point"}
}