{
  "type": "Feature",
  "properties": {
    "addr:full":"Geeraard De Cremerstraat 18b Kruibeke (rupelmonde) Oost-Vlaanderen 9150",
    "addr:housenumber":"18b",
    "addr:postcode":"9150",
    "addr:street":"Geeraard De Cremerstraat",
    "iso:country":"BE",
    "sg:address":"Geeraard De Cremerstraat 18b",
    "sg:city":"Kruibeke (rupelmonde)",
    "sg:classifiers":[
        {
            "category":"Bars & Pubs",
            "type":"Food & Drink"
        }
    ],
    "sg:phone":"+32 3 774 19 70",
    "sg:postcode":"9150",
    "sg:province":"Oost-Vlaanderen",
    "wof:name":"Dorp (het)",
    "wof:placetype":"venue"
},
  "geometry": {"coordinates":[4.4404821396,51.1659088135],"type":"Point"}
}