{
  "type": "Feature",
  "properties": {
    "iso:country":"BE",
    "sg:address":"Markekerkstraat 66",
    "sg:city":"Kortrijk",
    "sg:orig_category":"Banken and kredietinstellingen",
    "sg:phone":"+32 56 22 19 44",
    "sg:postcode":"8510",
    "sg:province":"West-Vlaanderen",
    "wof:name":"Bbl",
    "wof:placetype":"venue"
},
  "geometry": {"coordinates":[3.2302451134,50.809223175],"type":"Point"}
}