{
  "type": "Feature",
  "properties": {
    "addr:full":"Markekerkstraat 66 Kortrijk West-Vlaanderen 8510",
    "addr:housenumber":"66",
    "addr:postcode":"8510",
    "addr:street":"Markekerkstraat",
    "iso:country":"BE",
    "sg:address":"Markekerkstraat 66",
    "sg:city":"Kortrijk",
    "sg:orig_category":"Banken and kredietinstellingen",
    "sg:phone":"+32 56 22 19 44",
    "sg:postcode":"8510",
    "sg:province":"West-Vlaanderen",
    "wof:name":"Bbl",
    "wof:placetype":"venue"
},
  "geometry": {"coordinates":[3.2302451134,50.809223175],"type":"Point"}
}