{
  "type": "Feature",
  "properties": {
    "iso:country":"BE",
    "sg:address":"Rue Vierset-godin 9",
    "sg:city":"Huy",
    "sg:classifiers":[
        {
            "category":"Restaurant",
            "type":"Food & Drink"
        }
    ],
    "sg:phone":"+32 85 21 20 41",
    "sg:postcode":"4500",
    "sg:province":"Li\u00e8ge",
    "sg:tags":[
        "caf\u00e9s"
    ],
    "wof:name":"Contre Vents Et Mar\u00c9es",
    "wof:placetype":"venue"
},
  "geometry": {"coordinates":[5.2414321899,50.5191345215],"type":"Point"}
}