{
  "type": "Feature",
  "properties": {
    "iso:country":"BE",
    "sg:address":"Rue Du Man\u00c8ge 5",
    "sg:city":"Vaux-sur-sure",
    "sg:orig_category":"Sportclubs Sportterreinen and installaties behalve sportcentra",
    "sg:phone":"+32 61 25 54 31",
    "sg:postcode":"6640",
    "sg:province":"Luxembourg",
    "wof:name":"E.s. Vaux-sur-sure",
    "wof:placetype":"venue"
},
  "geometry": {"coordinates":[5.5640559196,49.907989502],"type":"Point"}
}