{
  "type": "Feature",
  "properties": {
    "addr:full":"Rijksweg 165b1 Maasmechelen Limburg 3630",
    "addr:housenumber":"165b1",
    "addr:postcode":"3630",
    "addr:street":"Rijksweg",
    "iso:country":"BE",
    "sg:address":"Rijksweg 165b1",
    "sg:city":"Maasmechelen",
    "sg:orig_category":"Advocaten and juridische adviseurs",
    "sg:phone":"+32 89 76 39 89",
    "sg:postcode":"3630",
    "sg:province":"Limburg",
    "wof:name":"A. Boufflette",
    "wof:placetype":"venue"
},
  "geometry": {"coordinates":[5.7010397911,50.9787216187],"type":"Point"}
}