{
  "type": "Feature",
  "properties": {
    "iso:country":"BE",
    "sg:address":"Vaartstraat 141",
    "sg:city":"Leuven",
    "sg:classifiers":[
        {
            "category":"Bakery",
            "type":"Food & Drink"
        }
    ],
    "sg:phone":"+32 16 22 33 70",
    "sg:postcode":"3000",
    "sg:province":"Vlaams-Brabant",
    "sg:tags":[
        "confectioner",
        "baker"
    ],
    "wof:name":"Uyttebroeck L",
    "wof:placetype":"venue"
},
  "geometry": {"coordinates":[4.7022008896,50.8870887756],"type":"Point"}
}