{
  "type": "Feature",
  "properties": {
    "addr:full":"Grote Steenweg 133 Kontich Antwerpen 2550",
    "addr:housenumber":"133",
    "addr:postcode":"2550",
    "addr:street":"Grote Steenweg",
    "iso:country":"BE",
    "sg:address":"Grote Steenweg 133",
    "sg:city":"Kontich",
    "sg:orig_category":"HERSTELLING ELEKTRISCHE HUISHOUDAPPARATEN Herstelling aan huis van elektrische huishoudapparaten",
    "sg:phone":"+32 15 32 10 21",
    "sg:postcode":"2550",
    "sg:province":"Antwerpen",
    "wof:name":"T.v. Depannage",
    "wof:placetype":"venue"
},
  "geometry": {"coordinates":[4.4513378143,51.1019935608],"type":"Point"}
}