{
  "type": "Feature",
  "properties": {
    "iso:country":"BE",
    "sg:address":"Heidestraat 20",
    "sg:city":"Sint-gillis-waas",
    "sg:classifiers":[
        {
            "category":"Cafe",
            "type":"Food & Drink"
        }
    ],
    "sg:phone":"+32 3 770 53 79",
    "sg:postcode":"9170",
    "sg:province":"Oost-Vlaanderen",
    "sg:tags":[
        "caf\u00e9s"
    ],
    "wof:name":"Caf\u00c9 De Grensreiziger",
    "wof:placetype":"venue"
},
  "geometry": {"coordinates":[4.0872092247,51.2535514832],"type":"Point"}
}