{
  "type": "Feature",
  "properties": {
    "addr:full":"Rue De Belle T\u00eate 18 Ecaussinnes (ecaussinnes-d'enghien) Hainaut 7190",
    "addr:housenumber":"18",
    "addr:postcode":"7190",
    "addr:street":"Rue De Belle Te\u0302Te;Ecaussinnes-D'Enghien Hainaut",
    "iso:country":"BE",
    "sg:address":"Rue De Belle T\u00eate 18",
    "sg:city":"Ecaussinnes (ecaussinnes-d'enghien)",
    "sg:classifiers":[
        {
            "category":"Bakery",
            "type":"Food & Drink"
        }
    ],
    "sg:phone":"+32 67 44 32 64",
    "sg:postcode":"7190",
    "sg:province":"Hainaut",
    "sg:tags":[
        "confectioner",
        "baker"
    ],
    "wof:name":"Burion B",
    "wof:placetype":"venue"
},
  "geometry": {"coordinates":[4.1514000893,50.5660171509],"type":"Point"}
}