{
  "type": "Feature",
  "properties": {
    "iso:country":"BE",
    "sg:address":"Chemin Des Li\u00c8vres 249",
    "sg:city":"Somme-leuze",
    "sg:classifiers":[
        {
            "category":"Arena",
            "subcategory":"Sports Club",
            "type":"Entertainment"
        }
    ],
    "sg:phone":"+32 84 32 23 36",
    "sg:postcode":"5377",
    "sg:province":"Namur",
    "sg:tags":[
        "de"
    ],
    "wof:name":"Arashi",
    "wof:placetype":"venue"
},
  "geometry": {"coordinates":[5.2669181824,50.252407074],"type":"Point"}
}