{
  "type": "Feature",
  "properties": {
    "addr:full":"Rue Du Page 87 Bruxelles (ixelles) Bruxelles-Capitale 1050",
    "addr:housenumber":"87",
    "addr:postcode":"1050",
    "addr:street":"Rue Du Page",
    "iso:country":"BE",
    "sg:address":"Rue Du Page 87",
    "sg:city":"Bruxelles (ixelles)",
    "sg:classifiers":[
        {
            "category":"Education",
            "subcategory":"University",
            "type":"Public Place"
        }
    ],
    "sg:phone":"+32 2 538 98 29",
    "sg:postcode":"1050",
    "sg:province":"Bruxelles-Capitale",
    "sg:tags":[
        "higher"
    ],
    "wof:name":"Ecole De Recherche Graphique",
    "wof:placetype":"venue"
},
  "geometry": {"coordinates":[4.3571629524,50.8221435547],"type":"Point"}
}