{
  "type": "Feature",
  "properties": {
    "iso:country":"BE",
    "sg:address":"Sentier De Presles 20",
    "sg:city":"Chatelet",
    "sg:classifiers":[
        {
            "category":"Professional",
            "subcategory":"Art Services",
            "type":"Services"
        }
    ],
    "sg:phone":"+32 71 38 22 81",
    "sg:postcode":"6200",
    "sg:province":"Hainaut",
    "sg:tags":[
        "designer",
        "ontwerpers"
    ],
    "wof:name":"Couture Olivia Scala",
    "wof:placetype":"venue"
},
  "geometry": {"coordinates":[4.5180630684,50.3909072876],"type":"Point"}
}