{
  "type": "Feature",
  "properties": {
    "iso:country":"BE",
    "sg:address":"47 Boulevard Du R\u00e9gent",
    "sg:city":"Bruxelles",
    "sg:classifiers":[
        {
            "category":"Banks & Credit Unions",
            "subcategory":"Financial Services",
            "type":"Services"
        }
    ],
    "sg:phone":"+32 2 518 08 11",
    "sg:postcode":"1000",
    "sg:province":"Bruxelles-Capitale",
    "sg:tags":[
        "banking",
        "finance",
        "insurance"
    ],
    "wof:name":"Banque Nationale De Paris Sa",
    "wof:placetype":"venue"
},
  "geometry": {"coordinates":[4.3688850403,50.8486099243],"type":"Point"}
}