{
  "type": "Feature",
  "properties": {
    "iso:country":"BE",
    "sg:address":"Stationsstraat 50",
    "sg:city":"Puurs",
    "sg:orig_category":"Verplichte sociale verzekeringen",
    "sg:phone":"+32 3 889 01 80",
    "sg:postcode":"2870",
    "sg:province":"Antwerpen",
    "wof:name":"Socialist. Mutualiteit",
    "wof:placetype":"venue"
},
  "geometry": {"coordinates":[4.2823300362,51.0769538879],"type":"Point"}
}