{
  "type": "Feature",
  "properties": {
    "iso:country":"BE",
    "sg:address":"Rue De L'abreuvoir 7",
    "sg:city":"Chapelle-lez-herlaimont",
    "sg:classifiers":[
        {
            "category":"Organizations",
            "subcategory":"Community Association",
            "type":"Services"
        }
    ],
    "sg:phone":"+32 64 45 89 61",
    "sg:postcode":"7160",
    "sg:province":"Hainaut",
    "sg:tags":[
        "cultural"
    ],
    "wof:name":"Maison Des Jeunes",
    "wof:placetype":"venue"
},
  "geometry": {"coordinates":[4.2872309685,50.4707145691],"type":"Point"}
}