{
  "type": "Feature",
  "properties": {
    "iso:country":"BE",
    "sg:address":"Rue De Rosi\u00e8res 32",
    "sg:city":"Rixensart (genval)",
    "sg:classifiers":[
        {
            "category":"Health Services",
            "subcategory":"Health Practitioner",
            "type":"Services"
        }
    ],
    "sg:phone":"+32 2 652 42 51",
    "sg:postcode":"1332",
    "sg:province":"Brabant Wallon",
    "sg:tags":[
        "therapist",
        "speech"
    ],
    "wof:name":"Anastasiades L",
    "wof:placetype":"venue"
},
  "geometry": {"coordinates":[4.5165171623,50.7244377136],"type":"Point"}
}