{
  "type": "Feature",
  "properties": {
    "addr:full":"Molsesteenweg 108 Balen Antwerpen 2490",
    "addr:housenumber":"108",
    "addr:postcode":"2490",
    "addr:street":"Molsesteenweg",
    "iso:country":"BE",
    "sg:address":"Molsesteenweg 108",
    "sg:city":"Balen",
    "sg:orig_category":"Woningbouw",
    "sg:phone":"+32 14 31 00 91",
    "sg:postcode":"2490",
    "sg:province":"Antwerpen",
    "wof:name":"Stephan Geerts",
    "wof:placetype":"venue"
},
  "geometry": {"coordinates":[5.136496067,51.1745681763],"type":"Point"}
}