{
  "type": "Feature",
  "properties": {
    "iso:country":"BE",
    "sg:address":"Weststraat 66",
    "sg:city":"Ingelmunster",
    "sg:orig_category":"Pain, p\u00e2tisseries and confiseries",
    "sg:phone":"+32 51 30 20 98",
    "sg:postcode":"8770",
    "sg:province":"West-Vlaanderen",
    "wof:name":"Filip Deboosere",
    "wof:placetype":"venue"
},
  "geometry": {"coordinates":[3.2471458912,50.9218177795],"type":"Point"}
}