{
  "type": "Feature",
  "properties": {
    "iso:country":"BE",
    "sg:address":"Clos De La Chapelle 14",
    "sg:city":"Welkenraedt",
    "sg:orig_category":"Agents artistiques",
    "sg:phone":"+32 87 88 25 68",
    "sg:postcode":"4840",
    "sg:province":"Li\u00e8ge",
    "wof:name":"J.p.h. Productions",
    "wof:placetype":"venue"
},
  "geometry": {"coordinates":[5.9900360107,50.6544647217],"type":"Point"}
}