{
  "type": "Feature",
  "properties": {
    "iso:country":"BE",
    "sg:address":"Rue D'assaut 8",
    "sg:city":"Courcelles (souvret)",
    "sg:classifiers":[
        {
            "category":"Building & Trades",
            "subcategory":"Electrical",
            "type":"Services"
        }
    ],
    "sg:phone":"+32 71 45 10 45",
    "sg:postcode":"6182",
    "sg:province":"Hainaut",
    "sg:tags":[
        "electric",
        "-",
        "housewiring",
        "contractor"
    ],
    "wof:name":"Antarelec",
    "wof:placetype":"venue"
},
  "geometry": {"coordinates":[4.3509187698,50.4466247559],"type":"Point"}
}