{
  "type": "Feature",
  "properties": {
    "addr:full":"Klapstraat 76 Sint-martens-latem (deurle) Oost-Vlaanderen 9831",
    "addr:housenumber":"76",
    "addr:postcode":"9831",
    "addr:street":"Klapstraat",
    "iso:country":"BE",
    "sg:address":"Klapstraat 76",
    "sg:city":"Sint-martens-latem (deurle)",
    "sg:classifiers":[
        {
            "category":"Food & Beverages",
            "subcategory":"Meat & Fish",
            "type":"Retail Goods"
        }
    ],
    "sg:phone":"+32 9 282 93 62",
    "sg:postcode":"9831",
    "sg:province":"Oost-Vlaanderen",
    "sg:tags":[
        "poultry",
        "whol",
        "game",
        "-"
    ],
    "wof:name":"Kriel (de)",
    "wof:placetype":"venue"
},
  "geometry": {"coordinates":[3.6071829796,50.9892997742],"type":"Point"}
}