{
  "type": "Feature",
  "properties": {
    "addr:full":"Pauwengraaf 6 Maasmechelen Limburg 3630",
    "addr:housenumber":"6",
    "addr:postcode":"3630",
    "addr:street":"Pauwengraaf",
    "iso:country":"BE",
    "sg:address":"Pauwengraaf 6",
    "sg:city":"Maasmechelen",
    "sg:orig_category":"Pharmaciens",
    "sg:phone":"+32 89 76 40 69",
    "sg:postcode":"3630",
    "sg:province":"Limburg",
    "wof:name":"Apoteek S.smith",
    "wof:placetype":"venue"
},
  "geometry": {"coordinates":[5.6961350441,50.963848114],"type":"Point"}
}