{
  "type": "Feature",
  "properties": {
    "iso:country":"BE",
    "sg:address":"Dorperberg 26",
    "sg:city":"Maaseik (opoeteren)",
    "sg:classifiers":[
        {
            "category":"Professional",
            "subcategory":"Art Services",
            "type":"Services"
        }
    ],
    "sg:phone":"+32 89 86 49 77",
    "sg:postcode":"3680",
    "sg:province":"Limburg",
    "sg:tags":[
        "photographer"
    ],
    "wof:name":"Binnemans J",
    "wof:placetype":"venue"
},
  "geometry": {"coordinates":[5.791285038,51.0954208374],"type":"Point"}
}