{
  "type": "Feature",
  "properties": {
    "addr:full":"Kleemstraat 5 Waasmunster Oost-Vlaanderen 9250",
    "addr:housenumber":"5",
    "addr:postcode":"9250",
    "addr:street":"Kleemstraat",
    "iso:country":"BE",
    "sg:address":"Kleemstraat 5",
    "sg:city":"Waasmunster",
    "sg:orig_category":"Diverse bedrijfsbeheeradviesbureaus",
    "sg:phone":"+32 52 46 30 38",
    "sg:postcode":"9250",
    "sg:province":"Oost-Vlaanderen",
    "wof:name":"Rovapo",
    "wof:placetype":"venue"
},
  "geometry": {"coordinates":[4.0984220505,51.1166038513],"type":"Point"}
}