{
  "type": "Feature",
  "properties": {
    "iso:country":"BE",
    "sg:address":"Noordzandstraat 49",
    "sg:city":"Brugge",
    "sg:orig_category":"Herstelling aan huis van huishoudartikelen Herstelling leer and schoeisel",
    "sg:phone":"+32 50 33 47 04",
    "sg:postcode":"8000",
    "sg:province":"West-Vlaanderen",
    "wof:name":"Slotenmakerij Ablo",
    "wof:placetype":"venue"
},
  "geometry": {"coordinates":[3.2201349735,51.2073097229],"type":"Point"}
}