{
  "type": "Feature",
  "properties": {
    "iso:country":"BE",
    "sg:address":"Nieuwbrugstraat 42",
    "sg:city":"Machelen",
    "sg:orig_category":"Articles m\u00e9talliques ouvr\u00e9s divers Fab",
    "sg:phone":"+32 2 252 37 54",
    "sg:postcode":"1830",
    "sg:province":"Vlaams-Brabant",
    "wof:name":"Compas",
    "wof:placetype":"venue"
},
  "geometry": {"coordinates":[4.4280390739,50.9092788696],"type":"Point"}
}