{
  "type": "Feature",
  "properties": {
    "iso:country":"BE",
    "sg:address":"Boomstraat 18",
    "sg:city":"Bornem",
    "sg:orig_category":"Chaussures. Souvenirs and objets artisanaux",
    "sg:phone":"+32 3 889 23 93",
    "sg:postcode":"2880",
    "sg:province":"Antwerpen",
    "wof:name":"Transparant",
    "wof:placetype":"venue"
},
  "geometry": {"coordinates":[4.2338500023,51.0992889404],"type":"Point"}
}