{
  "type": "Feature",
  "properties": {
    "addr:full":"Puttestr 21 Balen Antwerpen 2490",
    "addr:housenumber":"21",
    "addr:postcode":"2490",
    "addr:street":"Puttestr",
    "iso:country":"BE",
    "sg:address":"Puttestr 21",
    "sg:city":"Balen",
    "sg:classifiers":[
        {
            "category":"Bakery",
            "type":"Food & Drink"
        }
    ],
    "sg:phone":"+32 14 81 65 50",
    "sg:postcode":"2490",
    "sg:province":"Antwerpen",
    "sg:tags":[
        "cake",
        "product",
        "related",
        "bread"
    ],
    "wof:name":"Bakkerij Marien Nv",
    "wof:placetype":"venue"
},
  "geometry": {"coordinates":[5.1527290344,51.1616325378],"type":"Point"}
}