{
  "type": "Feature",
  "properties": {
    "iso:country":"BE",
    "sg:address":"Hoogveld 15",
    "sg:city":"Avelgem",
    "sg:orig_category":"Installatie van houten of kunststof schrijnwerk",
    "sg:phone":"+32 56 64 52 28",
    "sg:postcode":"8580",
    "sg:province":"West-Vlaanderen",
    "wof:name":"Geert Demets",
    "wof:placetype":"venue"
},
  "geometry": {"coordinates":[3.4338479042,50.7775001526],"type":"Point"}
}