{
  "type": "Feature",
  "properties": {
    "iso:country":"BE",
    "sg:address":"Vrijestraat 28",
    "sg:city":"Assenede",
    "sg:classifiers":[
        {
            "category":"Manufacturing",
            "subcategory":"Chemicals & Compounds",
            "type":"Manufacturing & Wholesale Goods"
        }
    ],
    "sg:phone":"+32 9 344 53 38",
    "sg:postcode":"9960",
    "sg:province":"Oost-Vlaanderen",
    "sg:tags":[
        "pharmaceutical",
        "product"
    ],
    "wof:name":"Mpca Consultancy",
    "wof:placetype":"venue"
},
  "geometry": {"coordinates":[3.7927560806,51.2517738342],"type":"Point"}
}