{
  "type": "Feature",
  "properties": {
    "addr:full":"Dorpsstraat 6 Haacht Vlaams-Brabant 3150",
    "addr:housenumber":"6",
    "addr:postcode":"3150",
    "addr:street":"Dorpsstraat",
    "iso:country":"BE",
    "sg:address":"Dorpsstraat 6",
    "sg:city":"Haacht",
    "sg:orig_category":"Kapsalons",
    "sg:phone":"+32 16 60 48 39",
    "sg:postcode":"3150",
    "sg:province":"Vlaams-Brabant",
    "wof:name":"Coiffure Fabienne",
    "wof:placetype":"venue"
},
  "geometry": {"coordinates":[4.643075943,50.9428482056],"type":"Point"}
}