{
  "type": "Feature",
  "properties": {
    "iso:country":"BE",
    "sg:address":"Route D\u00b4evrehailles 29",
    "sg:city":"Yvoir",
    "sg:orig_category":"Vakantiehuizen",
    "sg:phone":"+32 82 61 42 76",
    "sg:postcode":"5530",
    "sg:province":"Namur",
    "wof:name":"Meunier - Mourin",
    "wof:placetype":"venue"
},
  "geometry": {"coordinates":[4.8798141479,50.3238830566],"type":"Point"}
}