{
  "type": "Feature",
  "properties": {
    "addr:full":"Chaus\u00c9e De Bruxelles 418 Waterloo Brabant Wallon 1410",
    "addr:housenumber":"418",
    "addr:postcode":"1410",
    "addr:street":"Chause\u0301E De Bruxelles",
    "iso:country":"BE",
    "sg:address":"Chaus\u00c9e De Bruxelles 418",
    "sg:city":"Waterloo",
    "sg:orig_category":"D\u00e9taillants en pi\u00e8ces and accessoires de voitures. Entretien and r\u00e9parations de voitures",
    "sg:phone":"+32 2 354 53 84",
    "sg:postcode":"1410",
    "sg:province":"Brabant Wallon",
    "wof:name":"Midas",
    "wof:placetype":"venue"
},
  "geometry": {"coordinates":[4.4012160301,50.7081565857],"type":"Point"}
}