{
  "type": "Feature",
  "properties": {
    "addr:full":"Grand'rue 160 Charleroi Hainaut 6000",
    "addr:housenumber":"160",
    "addr:postcode":"6000",
    "addr:street":"Grand'Rue;Hainaut",
    "iso:country":"BE",
    "sg:address":"Grand'rue 160",
    "sg:city":"Charleroi",
    "sg:classifiers":[
        {
            "category":"Shopping",
            "subcategory":"Computers & Home Electronics",
            "type":"Retail Goods"
        }
    ],
    "sg:phone":"+32 71 42 09 75",
    "sg:postcode":"6000",
    "sg:province":"Hainaut",
    "sg:tags":[
        "calculator"
    ],
    "wof:name":"Technomat Charleroi",
    "wof:placetype":"venue"
},
  "geometry": {"coordinates":[4.4527988434,50.4181480408],"type":"Point"}
}