{
  "type": "Feature",
  "properties": {
    "iso:country":"BE",
    "sg:address":"Beekweg 1",
    "sg:city":"Aalst (gijzegem)",
    "sg:classifiers":[
        {
            "category":"Shopping",
            "subcategory":"Clothing, Apparel, & Fashions",
            "type":"Retail Goods"
        }
    ],
    "sg:phone":"+32 53 21 46 48",
    "sg:postcode":"9308",
    "sg:province":"Oost-Vlaanderen",
    "sg:tags":[
        "underwear",
        "lingerie",
        "-"
    ],
    "wof:name":"Ledegen A",
    "wof:placetype":"venue"
},
  "geometry": {"coordinates":[4.0428471565,50.9922904968],"type":"Point"}
}