{
  "type": "Feature",
  "properties": {
    "iso:country":"BE",
    "sg:address":"Sint-godfriedstraat 3b101",
    "sg:city":"Sint-truiden",
    "sg:orig_category":"Dakwerken",
    "sg:phone":"+32 11 68 13 93",
    "sg:postcode":"3800",
    "sg:province":"Limburg",
    "wof:name":"A.d.r.",
    "wof:placetype":"venue"
},
  "geometry": {"coordinates":[5.2000789642,50.8316764832],"type":"Point"}
}