{
  "type": "Feature",
  "properties": {
    "iso:country":"BE",
    "sg:address":"Mussenburgstraat 4",
    "sg:city":"Bree",
    "sg:classifiers":[
        {
            "category":"Health Services",
            "subcategory":"Doctor",
            "type":"Services"
        }
    ],
    "sg:phone":"+32 89 46 59 37",
    "sg:postcode":"3960",
    "sg:province":"Limburg",
    "sg:tags":[
        "medicinephysicians",
        "surgeon"
    ],
    "wof:name":"Cuypers Yves",
    "wof:placetype":"venue"
},
  "geometry": {"coordinates":[5.6035318375,51.1410560608],"type":"Point"}
}