{
  "type": "Feature",
  "properties": {
    "addr:full":"Chauss\u00c9e De Bruxelles 63 Waterloo Brabant Wallon 1410",
    "addr:housenumber":"63",
    "addr:postcode":"1410",
    "addr:street":"Chausse\u0301E De Bruxelles",
    "iso:country":"BE",
    "sg:address":"Chauss\u00c9e De Bruxelles 63",
    "sg:city":"Waterloo",
    "sg:orig_category":"Activit\u00e9s r\u00e9cr\u00e9atives diverses",
    "sg:phone":"+32 2 351 23 45",
    "sg:postcode":"1410",
    "sg:province":"Brabant Wallon",
    "wof:name":"Kid's Factory",
    "wof:placetype":"venue"
},
  "geometry": {"coordinates":[4.3985772133,50.7252082825],"type":"Point"}
}