{
  "type": "Feature",
  "properties": {
    "iso:country":"BE",
    "sg:address":"Rue Des Fuchsias 26-28",
    "sg:city":"Bruxelles (molenbeek-saint-jean)",
    "sg:classifiers":[
        {
            "category":"Social Services",
            "subcategory":"Retirement Home",
            "type":"Services"
        }
    ],
    "sg:phone":"+32 2 414 62 39",
    "sg:postcode":"1080",
    "sg:province":"Bruxelles-Capitale",
    "sg:tags":[
        "residence"
    ],
    "wof:name":"Fuchsias (de-les)",
    "wof:placetype":"venue"
},
  "geometry": {"coordinates":[4.3197369576,50.8605995178],"type":"Point"}
}