{
  "type": "Feature",
  "properties": {
    "iso:country":"BE",
    "sg:address":"Amberloup 32",
    "sg:city":"Sainte-ode",
    "sg:orig_category":"Installatie van houten of kunststof schrijnwerk",
    "sg:phone":"+32 61 68 82 69",
    "sg:postcode":"6680",
    "sg:province":"Luxembourg",
    "wof:name":"Philippe Collet",
    "wof:placetype":"venue"
},
  "geometry": {"coordinates":[5.530921936,50.0324783325],"type":"Point"}
}