{
  "type": "Feature",
  "properties": {
    "addr:full":"Kortrijksesteenweg 214 Sint-martens-latem Oost-Vlaanderen 9830",
    "addr:housenumber":"214",
    "addr:postcode":"9830",
    "addr:street":"Kortrijksesteenweg",
    "iso:country":"BE",
    "sg:address":"Kortrijksesteenweg 214",
    "sg:city":"Sint-martens-latem",
    "sg:orig_category":"Bars Levering aan huis restaurants Restaurants",
    "sg:phone":"+32 9 282 31 71",
    "sg:postcode":"9830",
    "sg:province":"Oost-Vlaanderen",
    "wof:name":"Pompierke",
    "wof:placetype":"venue"
},
  "geometry": {"coordinates":[3.6295111179,51.0071601868],"type":"Point"}
}