{
  "type": "Feature",
  "properties": {
    "iso:country":"BE",
    "sg:address":"Wijerstraat 142",
    "sg:city":"Hasselt",
    "sg:classifiers":[
        {
            "category":"Arena",
            "subcategory":"Sports Club",
            "type":"Entertainment"
        }
    ],
    "sg:phone":"+32 11 59 34 19",
    "sg:postcode":"3510",
    "sg:province":"Limburg",
    "sg:tags":[
        "de"
    ],
    "wof:name":"Poong Cha Herk De Stad Vzw",
    "wof:placetype":"venue"
},
  "geometry": {"coordinates":[5.2236227989,50.9329986572],"type":"Point"}
}