{
  "type": "Feature",
  "properties": {
    "addr:full":"Rue De La Fray\u00e8re 20 Durbuy (bomal-sur-ourthe) Luxembourg 6941",
    "addr:housenumber":"20",
    "addr:postcode":"6941",
    "addr:street":"Rue De La Fraye\u0300Re",
    "iso:country":"BE",
    "sg:address":"Rue De La Fray\u00e8re 20",
    "sg:city":"Durbuy (bomal-sur-ourthe)",
    "sg:classifiers":[
        {
            "category":"Building & Trades",
            "subcategory":"Plumbing",
            "type":"Services"
        }
    ],
    "sg:phone":"+32 86 21 05 32",
    "sg:postcode":"6941",
    "sg:province":"Luxembourg",
    "sg:tags":[
        "repair",
        "mainten",
        "-",
        "central",
        "heating"
    ],
    "wof:name":"Heyrman J",
    "wof:placetype":"venue"
},
  "geometry": {"coordinates":[5.5155739784,50.3733711243],"type":"Point"}
}