{
  "type": "Feature",
  "properties": {
    "iso:country":"BE",
    "sg:address":"Lekestraat 54",
    "sg:city":"Koekelare",
    "sg:classifiers":[
        {
            "category":"Food & Beverages",
            "subcategory":"Groceries & Convenience Stores",
            "type":"Retail Goods"
        }
    ],
    "sg:phone":"+32 51 58 99 51",
    "sg:postcode":"8680",
    "sg:province":"West-Vlaanderen",
    "sg:tags":[
        "grocer"
    ],
    "wof:name":"Anseeuw",
    "wof:placetype":"venue"
},
  "geometry": {"coordinates":[2.9409790039,51.0858650208],"type":"Point"}
}