{
  "type": "Feature",
  "properties": {
    "addr:full":"Oostmeersdreef 45 Deinze Oost-Vlaanderen 9800",
    "addr:housenumber":"45",
    "addr:postcode":"9800",
    "addr:street":"Oostmeersdreef",
    "iso:country":"BE",
    "sg:address":"Oostmeersdreef 45",
    "sg:city":"Deinze",
    "sg:classifiers":[
        {
            "category":"Arena",
            "subcategory":"Sports Club",
            "type":"Entertainment"
        }
    ],
    "sg:phone":"+32 9 386 34 58",
    "sg:postcode":"9800",
    "sg:province":"Oost-Vlaanderen",
    "sg:tags":[
        "de"
    ],
    "wof:name":"W.c. Sportkomiteit",
    "wof:placetype":"venue"
},
  "geometry": {"coordinates":[3.5357749462,50.9828796387],"type":"Point"}
}