{
  "type": "Feature",
  "properties": {
    "iso:country":"BE",
    "sg:address":"Voie-jocqu\u00c9e 1",
    "sg:city":"Bouillon",
    "sg:classifiers":[
        {
            "category":"Restaurant",
            "type":"Food & Drink"
        }
    ],
    "sg:phone":"+32 61 46 63 98",
    "sg:postcode":"6830",
    "sg:province":"Luxembourg",
    "sg:tags":[
        "caf\u00e9s"
    ],
    "wof:name":"Taverne Des Sports",
    "wof:placetype":"venue"
},
  "geometry": {"coordinates":[5.071149826,49.7949256897],"type":"Point"}
}