{
  "type": "Feature",
  "properties": {
    "addr:full":"Rue De Ch\u00e2telet 17a Gerpinnes (gougnies) Hainaut 6280",
    "addr:housenumber":"17a",
    "addr:postcode":"6280",
    "addr:street":"Rue De Cha\u0302Telet",
    "iso:country":"BE",
    "sg:address":"Rue De Ch\u00e2telet 17a",
    "sg:city":"Gerpinnes (gougnies)",
    "sg:classifiers":[
        {
            "category":"Professional",
            "subcategory":"Computer Services",
            "type":"Services"
        }
    ],
    "sg:phone":"+32 71 50 50 66",
    "sg:postcode":"6280",
    "sg:province":"Hainaut",
    "sg:tags":[
        "repair",
        "processing",
        "-",
        "maintenance",
        "data"
    ],
    "wof:name":"Akela Sprl",
    "wof:placetype":"venue"
},
  "geometry": {"coordinates":[4.5654101372,50.3567695618],"type":"Point"}
}