{
  "type": "Feature",
  "properties": {
    "iso:country":"BE",
    "sg:address":"Rue Des Combattants 80",
    "sg:city":"Brunehaut",
    "sg:orig_category":"Benzinestations and brandstoffen",
    "sg:phone":"+32 69 34 41 33",
    "sg:postcode":"7620",
    "sg:province":"Hainaut",
    "wof:name":"Station Winckelmans",
    "wof:placetype":"venue"
},
  "geometry": {"coordinates":[3.4202709198,50.519153595],"type":"Point"}
}