{
  "type": "Feature",
  "properties": {
    "addr:full":"Brug Zuid 2b Aalter Oost-Vlaanderen 9880",
    "addr:housenumber":"2b",
    "addr:postcode":"9880",
    "addr:street":"Brug Zuid",
    "iso:country":"BE",
    "sg:address":"Brug Zuid 2b",
    "sg:city":"Aalter",
    "sg:classifiers":[
        {
            "category":"Building & Trades",
            "subcategory":"Landscaping Services",
            "type":"Services"
        }
    ],
    "sg:phone":"+32 9 375 38 75",
    "sg:postcode":"9880",
    "sg:province":"Oost-Vlaanderen",
    "sg:tags":[
        "gardening",
        "garden",
        "maintenance"
    ],
    "wof:name":"Huib Van Den Hoven Bv",
    "wof:placetype":"venue"
},
  "geometry": {"coordinates":[3.4409050941,51.1083297729],"type":"Point"}
}