{
  "type": "Feature",
  "properties": {
    "iso:country":"BE",
    "sg:address":"Chauss\u00c9e De Charleroi 461",
    "sg:city":"Fleurus",
    "sg:orig_category":"Bouwmaterialen Gh",
    "sg:phone":"+32 71 81 53 03",
    "sg:postcode":"6220",
    "sg:province":"Hainaut",
    "wof:name":"Center Carrelages",
    "wof:placetype":"venue"
},
  "geometry": {"coordinates":[4.5445580482,50.4751358032],"type":"Point"}
}