{
  "type": "Feature",
  "properties": {
    "addr:full":"Vleminkstraat 110b Aarschot (langdorp) Vlaams-Brabant 3201",
    "addr:housenumber":"110b",
    "addr:postcode":"3201",
    "addr:street":"Vleminkstraat",
    "iso:country":"BE",
    "sg:address":"Vleminkstraat 110b",
    "sg:city":"Aarschot (langdorp)",
    "sg:classifiers":[
        {
            "category":"Retail",
            "subcategory":"Auto Rental",
            "type":"Services"
        }
    ],
    "sg:phone":"+32 16 56 80 16",
    "sg:postcode":"3201",
    "sg:province":"Vlaams-Brabant",
    "sg:tags":[
        "milking",
        "machine"
    ],
    "wof:name":"Sma",
    "wof:placetype":"venue"
},
  "geometry": {"coordinates":[4.8704400063,51.0133934021],"type":"Point"}
}