{
  "type": "Feature",
  "properties": {
    "iso:country":"BE",
    "sg:address":"Centrumlaan 13",
    "sg:city":"Ninove",
    "sg:classifiers":[
        {
            "category":"Communications",
            "type":"Services"
        }
    ],
    "sg:phone":"+32 54 25 02 20",
    "sg:postcode":"9400",
    "sg:province":"Oost-Vlaanderen",
    "sg:tags":[
        "telecommunication"
    ],
    "wof:name":"Panatech",
    "wof:placetype":"venue"
},
  "geometry": {"coordinates":[4.0213999748,50.8346481323],"type":"Point"}
}