{
  "type": "Feature",
  "properties": {
    "addr:full":"Baalsebaan 203 Tremelo Vlaams-Brabant 3128",
    "addr:housenumber":"203",
    "addr:postcode":"3128",
    "addr:street":"Baalsebaan",
    "iso:country":"BE",
    "sg:address":"Baalsebaan 203",
    "sg:city":"Tremelo",
    "sg:orig_category":"Installation \u00e9lectrique r\u00e9sidentielle",
    "sg:phone":"+32 16 53 42 98",
    "sg:postcode":"3128",
    "sg:province":"Vlaams-Brabant",
    "wof:name":"Robert Goossens",
    "wof:placetype":"venue"
},
  "geometry": {"coordinates":[4.7364702225,50.9950637817],"type":"Point"}
}