{
  "type": "Feature",
  "properties": {
    "iso:country":"BE",
    "sg:address":"Hoogweg 24",
    "sg:city":"Londerzeel (malderen)",
    "sg:classifiers":[
        {
            "category":"Banks & Credit Unions",
            "subcategory":"Investment Brokerage",
            "type":"Services"
        }
    ],
    "sg:phone":"+32 52 33 29 20",
    "sg:postcode":"1840",
    "sg:province":"Vlaams-Brabant",
    "sg:tags":[
        "repair",
        "-",
        "installation",
        "sanitary",
        "article"
    ],
    "wof:name":"Maetens A",
    "wof:placetype":"venue"
},
  "geometry": {"coordinates":[4.2286047935,51.016254425],"type":"Point"}
}