{
  "type": "Feature",
  "properties": {
    "addr:full":"Dokter Haubenlaan 68 Maasmechelen Limburg 3630",
    "addr:housenumber":"68",
    "addr:postcode":"3630",
    "addr:street":"Dokter Haubenlaan",
    "iso:country":"BE",
    "sg:address":"Dokter Haubenlaan 68",
    "sg:city":"Maasmechelen",
    "sg:classifiers":[
        {
            "category":"Insurance",
            "subcategory":"Life Insurance",
            "type":"Services"
        }
    ],
    "sg:phone":"+32 89 76 41 33",
    "sg:postcode":"3630",
    "sg:province":"Limburg",
    "sg:tags":[
        "assurance"
    ],
    "wof:name":"Nijsten",
    "wof:placetype":"venue"
},
  "geometry": {"coordinates":[5.7036108971,50.9604492188],"type":"Point"}
}