{
  "type": "Feature",
  "properties": {
    "addr:full":"Rue Bizette 87 Herstal (vottem) Li\u00e8ge 4041",
    "addr:housenumber":"87",
    "addr:postcode":"4041",
    "addr:street":"Rue Bizette;Vottem",
    "iso:country":"BE",
    "sg:address":"Rue Bizette 87",
    "sg:city":"Herstal (vottem)",
    "sg:orig_category":"Non-Classified Establishments",
    "sg:phone":"+32 4 227 44 71",
    "sg:postcode":"4041",
    "sg:province":"Li\u00e8ge",
    "wof:name":"Maison De L'est Belge M.e.b.",
    "wof:placetype":"venue"
},
  "geometry": {"coordinates":[5.5849199295,50.6724891663],"type":"Point"}
}