{
  "type": "Feature",
  "properties": {
    "iso:country":"BE",
    "sg:address":"Beverenstraat 8",
    "sg:city":"Hooglede",
    "sg:classifiers":[
        {
            "category":"Insurance",
            "subcategory":"Insurance Agent",
            "type":"Services"
        }
    ],
    "sg:phone":"+32 51 24 94 14",
    "sg:postcode":"8830",
    "sg:province":"West-Vlaanderen",
    "sg:tags":[
        "verzekeringsmakelaars",
        "expert"
    ],
    "wof:name":"F. Leenknegt",
    "wof:placetype":"venue"
},
  "geometry": {"coordinates":[3.084788084,50.9770927429],"type":"Point"}
}