{
  "type": "Feature",
  "properties": {
    "addr:full":"Kauwstraat 35 Pittem West-Vlaanderen 8740",
    "addr:housenumber":"35",
    "addr:postcode":"8740",
    "addr:street":"Kauwstraat",
    "iso:country":"BE",
    "sg:address":"Kauwstraat 35",
    "sg:city":"Pittem",
    "sg:orig_category":"Traitements param\u00e9dicaux",
    "sg:phone":"+32 51 46 75 26",
    "sg:postcode":"8740",
    "sg:province":"West-Vlaanderen",
    "wof:name":"C. Lanckriet",
    "wof:placetype":"venue"
},
  "geometry": {"coordinates":[3.2641830444,50.9940986633],"type":"Point"}
}