{
  "type": "Feature",
  "properties": {
    "iso:country":"BE",
    "sg:address":"Meensesteenweg 449",
    "sg:city":"Kortrijk (bissegem)",
    "sg:classifiers":[
        {
            "category":"Organizations",
            "subcategory":"Professional Association",
            "type":"Services"
        }
    ],
    "sg:phone":"+32 56 37 29 01",
    "sg:postcode":"8501",
    "sg:province":"West-Vlaanderen",
    "sg:tags":[
        "tie",
        "scarf"
    ],
    "wof:name":"Modeno Nv",
    "wof:placetype":"venue"
},
  "geometry": {"coordinates":[3.2234230042,50.8212127686],"type":"Point"}
}