{
  "type": "Feature",
  "properties": {
    "addr:full":"Rue Try Marsin 1 Chastre Brabant Wallon 1450",
    "addr:housenumber":"1",
    "addr:postcode":"1450",
    "addr:street":"Rue Try Marsin",
    "iso:country":"BE",
    "sg:address":"Rue Try Marsin 1",
    "sg:city":"Chastre",
    "sg:orig_category":"Advocaten and juridische adviseurs",
    "sg:phone":"+32 71 87 47 09",
    "sg:postcode":"1450",
    "sg:province":"Brabant Wallon",
    "wof:name":"Delphine Duquesnoy",
    "wof:placetype":"venue"
},
  "geometry": {"coordinates":[4.6089401245,50.5870780945],"type":"Point"}
}