{
  "type": "Feature",
  "properties": {
    "addr:full":"Edingensesteenweg 658 Halle Vlaams-Brabant 1502",
    "addr:housenumber":"658;1502",
    "addr:street":"Edingensesteenweg",
    "iso:country":"BE",
    "sg:address":"Edingensesteenweg 658",
    "sg:city":"Halle",
    "sg:orig_category":"Charpentes and couvertures",
    "sg:phone":"+32 2 361 70 75",
    "sg:postcode":"1502",
    "sg:province":"Vlaams-Brabant",
    "wof:name":"Toidak",
    "wof:placetype":"venue"
},
  "geometry": {"coordinates":[4.1980948448,50.7204933167],"type":"Point"}
}