{
  "type": "Feature",
  "properties": {
    "addr:full":"Sint-jansstraat 55 Rotselaar (werchter) Vlaams-Brabant 3118",
    "addr:housenumber":"55",
    "addr:postcode":"3118",
    "addr:street":"Sint-Jansstraat",
    "iso:country":"BE",
    "sg:address":"Sint-jansstraat 55",
    "sg:city":"Rotselaar (werchter)",
    "sg:classifiers":[
        {
            "category":"Professional",
            "subcategory":"Engineering",
            "type":"Services"
        }
    ],
    "sg:phone":"+32 16 60 51 96",
    "sg:postcode":"3118",
    "sg:province":"Vlaams-Brabant",
    "sg:tags":[
        "-"
    ],
    "wof:name":"Octo Nv",
    "wof:placetype":"venue"
},
  "geometry": {"coordinates":[4.6964511871,50.9719161987],"type":"Point"}
}