{
  "type": "Feature",
  "properties": {
    "addr:full":"Gootje 83 Oosterzele (balegem) Oost-Vlaanderen 9860",
    "addr:housenumber":"83",
    "addr:postcode":"9860",
    "addr:street":"Gootje",
    "iso:country":"BE",
    "sg:address":"Gootje 83",
    "sg:city":"Oosterzele (balegem)",
    "sg:classifiers":[
        {
            "category":"Home & Garden",
            "subcategory":"Household Appliances",
            "type":"Retail Goods"
        }
    ],
    "sg:phone":"+32 9 362 54 87",
    "sg:postcode":"9860",
    "sg:province":"Oost-Vlaanderen",
    "sg:tags":[
        "repair",
        "mainten",
        "-",
        "electric"
    ],
    "wof:name":"Van De Velde Electro",
    "wof:placetype":"venue"
},
  "geometry": {"coordinates":[3.7997400761,50.9149398804],"type":"Point"}
}