{
  "type": "Feature",
  "properties": {
    "iso:country":"BE",
    "sg:address":"Rue Des Pommiers 31",
    "sg:city":"Montigny-le-tilleul",
    "sg:classifiers":[
        {
            "category":"Home & Garden",
            "subcategory":"Home Furnishings",
            "type":"Retail Goods"
        }
    ],
    "sg:phone":"+32 71 51 13 16",
    "sg:postcode":"6110",
    "sg:province":"Hainaut",
    "sg:tags":[
        "curtain",
        "-",
        "fixture"
    ],
    "wof:name":"Bleu Indigo",
    "wof:placetype":"venue"
},
  "geometry": {"coordinates":[4.3731799126,50.3715744019],"type":"Point"}
}