{
  "type": "Feature",
  "properties": {
    "addr:full":"Houtmarktstraat 22 Liedekerke Vlaams-Brabant 1770",
    "addr:housenumber":"22",
    "addr:postcode":"1770",
    "addr:street":"Houtmarktstraat;Vlaams-Brabant",
    "iso:country":"BE",
    "sg:address":"Houtmarktstraat 22",
    "sg:city":"Liedekerke",
    "sg:classifiers":[
        {
            "category":"Bakery",
            "type":"Food & Drink"
        }
    ],
    "sg:phone":"+32 53 66 75 11",
    "sg:postcode":"1770",
    "sg:province":"Vlaams-Brabant",
    "sg:tags":[
        "confectioner",
        "baker"
    ],
    "wof:name":"Van Den Eeckhoudt",
    "wof:placetype":"venue"
},
  "geometry": {"coordinates":[4.0806298256,50.8696594238],"type":"Point"}
}