{
  "type": "Feature",
  "properties": {
    "addr:full":"Rue Du Chant Des Oiseaux 10a Mettet (furnaux) Namur 5641",
    "addr:housenumber":"10a",
    "addr:postcode":"5641",
    "addr:street":"Rue Du Chant Des Oiseaux;Furnaux",
    "iso:country":"BE",
    "sg:address":"Rue Du Chant Des Oiseaux 10a",
    "sg:city":"Mettet (furnaux)",
    "sg:classifiers":[
        {
            "category":"Education",
            "subcategory":"School",
            "type":"Public Place"
        }
    ],
    "sg:phone":"+32 71 72 54 37",
    "sg:postcode":"5641",
    "sg:province":"Namur",
    "sg:tags":[
        "primary"
    ],
    "wof:name":"Ecoles Communales De Mettet",
    "wof:placetype":"venue"
},
  "geometry": {"coordinates":[4.7099428177,50.3090820312],"type":"Point"}
}