{
  "type": "Feature",
  "properties": {
    "addr:full":"Opaaigem 26 Erpe-mere (aaigem) Oost-Vlaanderen 9420",
    "addr:housenumber":"26",
    "addr:postcode":"9420",
    "addr:street":"Opaaigem",
    "iso:country":"BE",
    "sg:address":"Opaaigem 26",
    "sg:city":"Erpe-mere (aaigem)",
    "sg:classifiers":[
        {
            "category":"Shopping",
            "subcategory":"Florist",
            "type":"Retail Goods"
        }
    ],
    "sg:phone":"+32 53 62 32 32",
    "sg:postcode":"9420",
    "sg:province":"Oost-Vlaanderen",
    "wof:name":"Goessens R",
    "wof:placetype":"venue"
},
  "geometry": {"coordinates":[3.9363958836,50.892791748],"type":"Point"}
}