{
  "type": "Feature",
  "properties": {
    "iso:country":"BE",
    "sg:address":"Rue De L' Interieur 35",
    "sg:city":"Thorembais-saint-trond",
    "sg:classifiers":[
        {
            "category":"Building & Trades",
            "subcategory":"Landscaping Services",
            "type":"Services"
        }
    ],
    "sg:phone":"+32 81 65 63 03",
    "sg:postcode":"1360",
    "sg:province":"Brabant Wallon",
    "sg:tags":[
        "earth",
        "moving"
    ],
    "wof:name":"Sotraplant S.a.",
    "wof:placetype":"venue"
},
  "geometry": {"coordinates":[4.7817978859,50.6335296631],"type":"Point"}
}