{
  "type": "Feature",
  "properties": {
    "iso:country":"BE",
    "sg:address":"Rue Du Marais 2ba1",
    "sg:city":"Mons",
    "sg:orig_category":"Sportclubs",
    "sg:phone":"+32 65 33 56 16",
    "sg:postcode":"7032",
    "sg:province":"Hainaut",
    "wof:name":"B.c. The Flint",
    "wof:placetype":"venue"
},
  "geometry": {"coordinates":[3.9869709015,50.4255142212],"type":"Point"}
}