{
  "type": "Feature",
  "properties": {
    "iso:country":"BE",
    "sg:address":"Chemin Des Fagnes 43",
    "sg:city":"Malmedy/malmedy",
    "sg:orig_category":"Catering and organisatie van feesten",
    "sg:phone":"+32 80 33 96 60",
    "sg:postcode":"4960",
    "sg:province":"Li\u00e8ge",
    "wof:name":"Patrick Kesseler",
    "wof:placetype":"venue"
},
  "geometry": {"coordinates":[6.0576348305,50.405330658],"type":"Point"}
}