{
  "type": "Feature",
  "properties": {
    "addr:full":"Obterrestraat 8 Poperinge (proven) West-Vlaanderen 8972",
    "addr:housenumber":"8",
    "addr:postcode":"8972",
    "addr:street":"Obterrestraat",
    "iso:country":"BE",
    "sg:address":"Obterrestraat 8",
    "sg:city":"Poperinge (proven)",
    "sg:classifiers":[
        {
            "category":"Bars & Pubs",
            "type":"Food & Drink"
        }
    ],
    "sg:phone":"+32 57 30 04 83",
    "sg:postcode":"8972",
    "sg:province":"West-Vlaanderen",
    "wof:name":"St-elooi",
    "wof:placetype":"venue"
},
  "geometry": {"coordinates":[2.6556229591,50.8908576965],"type":"Point"}
}