{
  "type": "Feature",
  "properties": {
    "addr:full":"Boekweitstraat 88b4 Schoten Antwerpen 2900",
    "addr:housenumber":"88b4",
    "addr:postcode":"2900",
    "addr:street":"Boekweitstraat",
    "iso:country":"BE",
    "sg:address":"Boekweitstraat 88b4",
    "sg:city":"Schoten",
    "sg:orig_category":"Boekhouders Non-foodwinkels",
    "sg:phone":"+32 3 658 78 66",
    "sg:postcode":"2900",
    "sg:province":"Antwerpen",
    "wof:name":"Danny Beyltiens",
    "wof:placetype":"venue"
},
  "geometry": {"coordinates":[4.5016098022,51.2596893311],"type":"Point"}
}