{
  "type": "Feature",
  "properties": {
    "addr:full":"Bornstraat 67 Roeselare West-Vlaanderen 8800",
    "addr:housenumber":"67",
    "addr:postcode":"8800",
    "addr:street":"Bornstraat",
    "iso:country":"BE",
    "sg:address":"Bornstraat 67",
    "sg:city":"Roeselare",
    "sg:classifiers":[
        {
            "category":"Professional",
            "subcategory":"Accounting & Tax Preparation",
            "type":"Services"
        }
    ],
    "sg:phone":"+32 51 22 10 59",
    "sg:postcode":"8800",
    "sg:province":"West-Vlaanderen",
    "sg:tags":[
        "accountant"
    ],
    "wof:name":"Maxime Hamers",
    "wof:placetype":"venue"
},
  "geometry": {"coordinates":[3.1248118877,50.9281730652],"type":"Point"}
}