{
  "type": "Feature",
  "properties": {
    "iso:country":"BE",
    "sg:address":"Pastorijstraat 67",
    "sg:city":"Tremelo",
    "sg:orig_category":"RESTAURANTS: CAF\u00c9S",
    "sg:phone":"+32 16 53 46 61",
    "sg:postcode":"3128",
    "sg:province":"Vlaams-Brabant",
    "wof:name":"Taverne \u00b4t Kapittel",
    "wof:placetype":"venue"
},
  "geometry": {"coordinates":[4.7508111,50.9991989136],"type":"Point"}
}