{
  "type": "Feature",
  "properties": {
    "addr:full":"Rue Des Bach\u00c8res 14 Sambreville Namur 5060",
    "addr:housenumber":"14",
    "addr:postcode":"5060",
    "addr:street":"Rue Des Bache\u0300Res",
    "iso:country":"BE",
    "sg:address":"Rue Des Bach\u00c8res 14",
    "sg:city":"Sambreville",
    "sg:classifiers":[
        {
            "category":"Insurance",
            "subcategory":"Insurance Agent",
            "type":"Services"
        }
    ],
    "sg:phone":"+32 71 74 00 22",
    "sg:postcode":"5060",
    "sg:province":"Namur",
    "sg:tags":[
        "verzekeringsmakelaars",
        "expert"
    ],
    "wof:name":"Assurances Loiseau",
    "wof:placetype":"venue"
},
  "geometry": {"coordinates":[4.58893013,50.4367599487],"type":"Point"}
}