{
  "type": "Feature",
  "properties": {
    "iso:country":"BE",
    "sg:address":"Heilige-geeststraat 74",
    "sg:city":"Leuven",
    "sg:orig_category":"Overheidsdiensten",
    "sg:phone":"+32 16 31 08 33",
    "sg:postcode":"3000",
    "sg:province":"Vlaams-Brabant",
    "wof:name":"Admin. Directe Belast.",
    "wof:placetype":"venue"
},
  "geometry": {"coordinates":[4.6886439323,50.8766746521],"type":"Point"}
}