{
  "type": "Feature",
  "properties": {
    "addr:full":"Sint-alenalaan 55 Dilbeek Vlaams-Brabant 1700",
    "addr:housenumber":"55",
    "addr:postcode":"1700",
    "addr:street":"Sint-Alenalaan",
    "iso:country":"BE",
    "sg:address":"Sint-alenalaan 55",
    "sg:city":"Dilbeek",
    "sg:classifiers":[
        {
            "category":"Personal",
            "subcategory":"Nail Salon",
            "type":"Services"
        }
    ],
    "sg:phone":"+32 477 52 82 55",
    "sg:postcode":"1700",
    "sg:province":"Vlaams-Brabant",
    "sg:tags":[
        "pedicure"
    ],
    "wof:name":"Femina",
    "wof:placetype":"venue"
},
  "geometry": {"coordinates":[4.2646570206,50.8470420837],"type":"Point"}
}