{
  "type": "Feature",
  "properties": {
    "addr:full":"Rue Des Fran\u00e7ais 133 Charleroi (dampremy) Hainaut 6020",
    "addr:housenumber":"133",
    "addr:postcode":"6020",
    "addr:street":"Rue Des Franc\u0327Ais",
    "iso:country":"BE",
    "sg:address":"Rue Des Fran\u00e7ais 133",
    "sg:city":"Charleroi (dampremy)",
    "sg:classifiers":[
        {
            "category":"Shopping",
            "subcategory":"Stationery & Office Supplies",
            "type":"Retail Goods"
        }
    ],
    "sg:phone":"+32 71 31 02 03",
    "sg:postcode":"6020",
    "sg:province":"Hainaut",
    "sg:tags":[
        "partition"
    ],
    "wof:name":"Biyik D",
    "wof:placetype":"venue"
},
  "geometry": {"coordinates":[4.4357500076,50.4227981567],"type":"Point"}
}