{
  "type": "Feature",
  "properties": {
    "addr:full":"Avenue De La R\u00e9forme 74 Bruxelles (ganshoren) Bruxelles-Capitale 1083",
    "addr:housenumber":"74",
    "addr:postcode":"1083",
    "addr:street":"Avenue De La Re\u0301Forme",
    "iso:country":"BE",
    "sg:address":"Avenue De La R\u00e9forme 74",
    "sg:city":"Bruxelles (ganshoren)",
    "sg:classifiers":[
        {
            "category":"Parking",
            "subcategory":"Bicycle",
            "type":"Transportation"
        }
    ],
    "sg:phone":"+32 2 420 43 08",
    "sg:postcode":"1083",
    "sg:province":"Bruxelles-Capitale",
    "sg:tags":[
        "chiropodist"
    ],
    "wof:name":"Gillot",
    "wof:placetype":"venue"
},
  "geometry": {"coordinates":[4.3109021187,50.8749465942],"type":"Point"}
}