{
  "type": "Feature",
  "properties": {
    "addr:full":"Sint-michielslaan 12b2 Sint-pieters-woluwe/woluwe-saint-pierre Bruxelles-Capitale 1150",
    "addr:housenumber":"12b2",
    "addr:postcode":"1150",
    "addr:street":"Sint-Michielslaan;/",
    "iso:country":"BE",
    "sg:address":"Sint-michielslaan 12b2",
    "sg:city":"Sint-pieters-woluwe/woluwe-saint-pierre",
    "sg:classifiers":[
        {
            "category":"Professional",
            "subcategory":"Accounting & Tax Preparation",
            "type":"Services"
        }
    ],
    "sg:phone":"+32 2 734 28 83",
    "sg:postcode":"1150",
    "sg:province":"Bruxelles-Capitale",
    "sg:tags":[
        "accountant"
    ],
    "wof:name":"Albert Vanmolecot",
    "wof:placetype":"venue"
},
  "geometry": {"coordinates":[4.4074931145,50.8361968994],"type":"Point"}
}