{
  "type": "Feature",
  "properties": {
    "addr:full":"Blaisantvest 4 Gent Oost-Vlaanderen 9000",
    "addr:housenumber":"4",
    "addr:postcode":"9000",
    "addr:street":"Blaisantvest;Oost-Vlaanderen",
    "iso:country":"BE",
    "sg:address":"Blaisantvest 4",
    "sg:city":"Gent",
    "sg:orig_category":"Quincailleries",
    "sg:phone":"+32 9 223 96 50",
    "sg:postcode":"9000",
    "sg:province":"Oost-Vlaanderen",
    "wof:name":"Olga De Backer",
    "wof:placetype":"venue"
},
  "geometry": {"coordinates":[3.7209300995,51.0658416748],"type":"Point"}
}