{
  "type": "Feature",
  "properties": {
    "iso:country":"BE",
    "sg:address":"Oostendsesteenweg 85",
    "sg:city":"Zuienkerke",
    "sg:classifiers":[
        {
            "category":"Wholesale",
            "subcategory":"Sporting Goods",
            "type":"Manufacturing & Wholesale Goods"
        }
    ],
    "sg:phone":"+32 50 32 02 30",
    "sg:postcode":"8377",
    "sg:province":"West-Vlaanderen",
    "sg:tags":[
        "sport-",
        "kampeermateriaal"
    ],
    "wof:name":"Biljarts Danneels",
    "wof:placetype":"venue"
},
  "geometry": {"coordinates":[3.1065890789,51.2403907776],"type":"Point"}
}