{
  "type": "Feature",
  "properties": {
    "addr:full":"Kruishoutemsesteenweg 261 Zingem Oost-Vlaanderen 9750",
    "addr:housenumber":"261",
    "addr:postcode":"9750",
    "addr:street":"Kruishoutemsesteenweg;Oost-Vlaanderen",
    "iso:country":"BE",
    "sg:address":"Kruishoutemsesteenweg 261",
    "sg:city":"Zingem",
    "sg:orig_category":"Entretien and r\u00e9parations de voitures",
    "sg:phone":"+32 9 384 14 37",
    "sg:postcode":"9750",
    "sg:province":"Oost-Vlaanderen",
    "wof:name":"Garage 't Peerdeke",
    "wof:placetype":"venue"
},
  "geometry": {"coordinates":[3.6351799965,50.9094581604],"type":"Point"}
}