{
  "type": "Feature",
  "properties": {
    "addr:full":"Rue De La Chauss\u00e9e 58 Theux Li\u00e8ge 4910",
    "addr:housenumber":"58",
    "addr:postcode":"4910",
    "addr:street":"Rue De La Chausse\u0301E",
    "iso:country":"BE",
    "sg:address":"Rue De La Chauss\u00e9e 58",
    "sg:city":"Theux",
    "sg:classifiers":[
        {
            "category":"Banks & Credit Unions",
            "subcategory":"Investment Brokerage",
            "type":"Services"
        }
    ],
    "sg:phone":"+32 87 54 12 78",
    "sg:postcode":"4910",
    "sg:province":"Li\u00e8ge",
    "sg:tags":[
        "printing",
        "-"
    ],
    "wof:name":"Pirard Paul Sprl",
    "wof:placetype":"venue"
},
  "geometry": {"coordinates":[5.8103561401,50.534160614],"type":"Point"}
}