{
  "type": "Feature",
  "properties": {
    "iso:country":"BE",
    "sg:address":"Seulestraat 134",
    "sg:city":"Heuvelland",
    "sg:orig_category":"Groententeelt",
    "sg:phone":"+32 57 44 81 54",
    "sg:postcode":"8950",
    "sg:province":"West-Vlaanderen",
    "wof:name":"Jurgen Ollevier",
    "wof:placetype":"venue"
},
  "geometry": {"coordinates":[2.8249499798,50.7459411621],"type":"Point"}
}