{
  "type": "Feature",
  "properties": {
    "iso:country":"BE",
    "sg:address":"Rue De Li\u00c8ge 15",
    "sg:city":"Hamoir",
    "sg:orig_category":"Herstellingen and onderhoud van auto's",
    "sg:phone":"+32 86 38 93 07",
    "sg:postcode":"4180",
    "sg:province":"Li\u00e8ge",
    "wof:name":"Carrosserie Serge Vincent",
    "wof:placetype":"venue"
},
  "geometry": {"coordinates":[5.5450811386,50.4463119507],"type":"Point"}
}