{
  "type": "Feature",
  "properties": {
    "iso:country":"BE",
    "sg:address":"Steenakker 5",
    "sg:city":"Kontich",
    "sg:orig_category":"Tuinen",
    "sg:phone":"+32 3 457 16 02",
    "sg:postcode":"2550",
    "sg:province":"Antwerpen",
    "wof:name":"Ceuppens W.",
    "wof:placetype":"venue"
},
  "geometry": {"coordinates":[4.4731960297,51.1352767944],"type":"Point"}
}