{
  "type": "Feature",
  "properties": {
    "iso:country":"BE",
    "sg:address":"Schaaruit 5",
    "sg:city":"Duffel",
    "sg:orig_category":"Groententeelt",
    "sg:phone":"+32 15 31 20 85",
    "sg:postcode":"2570",
    "sg:province":"Antwerpen",
    "wof:name":"Denis Ceulemans",
    "wof:placetype":"venue"
},
  "geometry": {"coordinates":[4.5053877831,51.0833358765],"type":"Point"}
}