{
  "type": "Feature",
  "properties": {
    "addr:full":"Ottergemsesteenweg 15 Gent Oost-Vlaanderen 9000",
    "addr:housenumber":"15",
    "addr:postcode":"9000",
    "addr:street":"Ottergemsesteenweg;Oost-Vlaanderen",
    "iso:country":"BE",
    "sg:address":"Ottergemsesteenweg 15",
    "sg:city":"Gent",
    "sg:orig_category":"Entretien and r\u00e9parations de voitures",
    "sg:phone":"+32 9 222 21 34",
    "sg:postcode":"9000",
    "sg:province":"Oost-Vlaanderen",
    "wof:name":"Carr. Van Der Mynsbrugge",
    "wof:placetype":"venue"
},
  "geometry": {"coordinates":[3.7272729874,51.0371742249],"type":"Point"}
}