{
  "type": "Feature",
  "properties": {
    "iso:country":"BE",
    "sg:address":"Molenstraat 22",
    "sg:city":"Baarle-hertog",
    "sg:orig_category":"Speelgoed",
    "sg:phone":"+32 14 69 95 44",
    "sg:postcode":"2387",
    "sg:province":"Antwerpen",
    "wof:name":"Teddy's",
    "wof:placetype":"venue"
},
  "geometry": {"coordinates":[4.932199955,51.4400367737],"type":"Point"}
}