{
  "type": "Feature",
  "properties": {
    "addr:full":"Rue De Dampr\u00c9my 153 Charleroi Hainaut 6040",
    "addr:housenumber":"153",
    "addr:postcode":"6040",
    "addr:street":"Rue De Dampre\u0301My;Hainaut",
    "iso:country":"BE",
    "sg:address":"Rue De Dampr\u00c9my 153",
    "sg:city":"Charleroi",
    "sg:orig_category":"Kapsalons",
    "sg:phone":"+32 71 30 39 96",
    "sg:postcode":"6040",
    "sg:province":"Hainaut",
    "wof:name":"Graziela",
    "wof:placetype":"venue"
},
  "geometry": {"coordinates":[4.4219207764,50.4299163818],"type":"Point"}
}