{
  "type": "Feature",
  "properties": {
    "iso:country":"BE",
    "sg:address":"Avenue De Vis\u00c9 39",
    "sg:city":"Watermaal-bosvoorde",
    "sg:orig_category":"Editeurs de journaux. Organisations and associations. Editeurs de revues and p\u00e9riodiques",
    "sg:phone":"+32 2 673 52 30",
    "sg:postcode":"1170",
    "sg:province":"Bruxelles-Capitale",
    "wof:name":"Cha\u00cene Bleue Mondiale/blauwe Wereldketen",
    "wof:placetype":"venue"
},
  "geometry": {"coordinates":[4.3967351913,50.8106460571],"type":"Point"}
}