{
  "type": "Feature",
  "properties": {
    "addr:full":"Bist 156 Antwerpen Antwerpen 2610",
    "addr:housenumber":"156",
    "addr:postcode":"2610",
    "addr:street":"Bist",
    "iso:country":"BE",
    "sg:address":"Bist 156",
    "sg:city":"Antwerpen",
    "sg:orig_category":"Cr\u00e9dits divers",
    "sg:postcode":"2610",
    "sg:province":"Antwerpen",
    "wof:name":"Bancontact-mister Cash",
    "wof:placetype":"venue"
},
  "geometry": {"coordinates":[4.3946051598,51.1691131592],"type":"Point"}
}