{
  "type": "Feature",
  "properties": {
    "iso:country":"BE",
    "sg:address":"Avenue Winston Churchill 251 Box 1",
    "sg:city":"Bruxelles (uccle)",
    "sg:classifiers":[
        {
            "category":"Professional",
            "subcategory":"Lawyer & Legal Services",
            "type":"Services"
        }
    ],
    "sg:phone":"+32 2 346 25 46",
    "sg:postcode":"1180",
    "sg:province":"Bruxelles-Capitale",
    "wof:name":"De Smet Vinciane",
    "wof:placetype":"venue"
},
  "geometry": {"coordinates":[4.3671941757,50.811706543],"type":"Point"}
}