{
  "type": "Feature",
  "properties": {
    "addr:full":"Hellingstraat 58 Lanaken Limburg 3620",
    "addr:housenumber":"58",
    "addr:postcode":"3620",
    "addr:street":"Hellingstraat",
    "iso:country":"BE",
    "sg:address":"Hellingstraat 58",
    "sg:city":"Lanaken",
    "sg:orig_category":"Enseignement maternel and primaire",
    "sg:phone":"+32 89 71 21 18",
    "sg:postcode":"3620",
    "sg:province":"Limburg",
    "wof:name":"Vrije Basisschool",
    "wof:placetype":"venue"
},
  "geometry": {"coordinates":[5.6413340569,50.8927078247],"type":"Point"}
}