{
  "type": "Feature",
  "properties": {
    "iso:country":"BE",
    "sg:address":"Tiensesteenweg 170",
    "sg:city":"Sint-truiden",
    "sg:orig_category":"Sportclubs Sportterreinen and installaties behalve sportcentra",
    "sg:phone":"+32 11 68 38 29",
    "sg:postcode":"3800",
    "sg:province":"Limburg",
    "wof:name":"Sint-truiden Stvv",
    "wof:placetype":"venue"
},
  "geometry": {"coordinates":[5.1659250259,50.8141288757],"type":"Point"}
}