{
  "type": "Feature",
  "properties": {
    "iso:country":"BE",
    "sg:address":"Leopold I-laan 77-79",
    "sg:city":"Brugge",
    "sg:classifiers":[
        {
            "category":"Personal",
            "subcategory":"Beauty Salon",
            "type":"Services"
        }
    ],
    "sg:phone":"+32 50 31 43 90",
    "sg:postcode":"8000",
    "sg:province":"West-Vlaanderen",
    "sg:tags":[
        "de",
        "coiffure"
    ],
    "wof:name":"Rudy's Nova Linea",
    "wof:placetype":"venue"
},
  "geometry": {"coordinates":[3.2092239857,51.2154655457],"type":"Point"}
}