{
  "type": "Feature",
  "properties": {
    "iso:country":"BE",
    "sg:address":"Broekstraat 11",
    "sg:city":"Asse",
    "sg:classifiers":[
        {
            "category":"Real Estate",
            "subcategory":"Architect",
            "type":"Services"
        }
    ],
    "sg:phone":"+32 2 452 95 48",
    "sg:postcode":"1730",
    "sg:province":"Vlaams-Brabant",
    "wof:name":"Willems L",
    "wof:placetype":"venue"
},
  "geometry": {"coordinates":[4.2457208633,50.9100112915],"type":"Point"}
}