{
  "type": "Feature",
  "properties": {
    "addr:full":"Rue Du Viaduc 1 Soignies Hainaut 7060",
    "addr:housenumber":"1",
    "addr:postcode":"7060",
    "addr:street":"Rue Du Viaduc",
    "iso:country":"BE",
    "sg:address":"Rue Du Viaduc 1",
    "sg:city":"Soignies",
    "sg:classifiers":[
        {
            "category":"Manufacturing",
            "subcategory":"Furniture",
            "type":"Manufacturing & Wholesale Goods"
        }
    ],
    "sg:phone":"+32 67 33 68 68",
    "sg:postcode":"7060",
    "sg:province":"Hainaut",
    "sg:tags":[
        "design",
        "-"
    ],
    "wof:name":"Desseins Sprl",
    "wof:placetype":"venue"
},
  "geometry": {"coordinates":[4.0655708313,50.5725326538],"type":"Point"}
}