{
  "type": "Feature",
  "properties": {
    "addr:full":"Rue Des Communes 9 Ramillies (geest-g\u00e9rompont-petit-rosi\u00e8re) Brabant Wallon 1367",
    "addr:housenumber":"9",
    "addr:postcode":"1367",
    "addr:street":"Rue Des Communes;Wallon",
    "iso:country":"BE",
    "sg:address":"Rue Des Communes 9",
    "sg:city":"Ramillies (geest-g\u00e9rompont-petit-rosi\u00e8re)",
    "sg:classifiers":[
        {
            "category":"Food & Beverages",
            "subcategory":"Meat & Fish",
            "type":"Retail Goods"
        }
    ],
    "sg:phone":"+32 81 87 72 16",
    "sg:postcode":"1367",
    "sg:province":"Brabant Wallon",
    "sg:tags":[
        "-",
        "livestock"
    ],
    "wof:name":"Ravet Charbons",
    "wof:placetype":"venue"
},
  "geometry": {"coordinates":[4.8556900024,50.6401824951],"type":"Point"}
}