{
  "type": "Feature",
  "properties": {
    "iso:country":"BE",
    "sg:address":"Rue De Silly 1",
    "sg:city":"Brugelette",
    "sg:classifiers":[
        {
            "category":"Retail",
            "subcategory":"Auto Repair",
            "type":"Services"
        }
    ],
    "sg:phone":"+32 68 45 49 69",
    "sg:postcode":"7940",
    "sg:province":"Hainaut",
    "sg:tags":[
        "breakdown",
        "automobile",
        "-",
        "recovery"
    ],
    "wof:name":"Bossart",
    "wof:placetype":"venue"
},
  "geometry": {"coordinates":[3.855989933,50.5989608765],"type":"Point"}
}