{
  "type": "Feature",
  "properties": {
    "addr:full":"Rue De Hannut 1 Fernelmont (bierwart) Namur 5380",
    "addr:housenumber":"1",
    "addr:postcode":"5380",
    "addr:street":"Rue De Hannut",
    "iso:country":"BE",
    "sg:address":"Rue De Hannut 1",
    "sg:city":"Fernelmont (bierwart)",
    "sg:classifiers":[
        {
            "category":"Autos & Motor Vehicles",
            "subcategory":"Fuel & Gas Station",
            "type":"Retail Goods"
        }
    ],
    "sg:phone":"+32 81 83 38 77",
    "sg:postcode":"5380",
    "sg:province":"Namur",
    "wof:name":"Renard Luger Sprl",
    "wof:placetype":"venue"
},
  "geometry": {"coordinates":[5.0363211632,50.5560874939],"type":"Point"}
}