{
  "type": "Feature",
  "properties": {
    "iso:country":"BE",
    "sg:address":"Schoubroekstraat 2",
    "sg:city":"Boortmeerbeek",
    "sg:orig_category":"Forge, Moulage and Profilage des M\u00e9taux",
    "sg:phone":"+32 15 51 54 38",
    "sg:postcode":"3190",
    "sg:province":"Vlaams-Brabant",
    "wof:name":"Dumoulin Rudi",
    "wof:placetype":"venue"
},
  "geometry": {"coordinates":[4.5685219765,50.9868011475],"type":"Point"}
}