{
  "type": "Feature",
  "properties": {
    "addr:full":"Rue De Courtrai 17 Pecq Hainaut 7740",
    "addr:housenumber":"17",
    "addr:postcode":"7740",
    "addr:street":"Rue De Courtrai",
    "iso:country":"BE",
    "sg:address":"Rue De Courtrai 17",
    "sg:city":"Pecq",
    "sg:orig_category":"Artiesten and kunstenaars",
    "sg:phone":"+32 69 55 91 65",
    "sg:postcode":"7740",
    "sg:province":"Hainaut",
    "wof:name":"Lucien Florent",
    "wof:placetype":"venue"
},
  "geometry": {"coordinates":[3.3389539719,50.6862220764],"type":"Point"}
}