{
  "type": "Feature",
  "properties": {
    "addr:full":"Chauss\u00e9e De Waterloo 500 Namur (saint-servais) Namur 5002",
    "addr:housenumber":"500",
    "addr:postcode":"5002",
    "addr:street":"Chausse\u0301E De Waterloo",
    "iso:country":"BE",
    "sg:address":"Chauss\u00e9e De Waterloo 500",
    "sg:city":"Namur (saint-servais)",
    "sg:classifiers":[
        {
            "category":"Wholesale",
            "subcategory":"Auto Parts",
            "type":"Manufacturing & Wholesale Goods"
        }
    ],
    "sg:phone":"+32 81 73 06 20",
    "sg:postcode":"5002",
    "sg:province":"Namur",
    "sg:tags":[
        "body",
        "automobile",
        "supply",
        "equipment"
    ],
    "wof:name":"Autoland Sa",
    "wof:placetype":"venue"
},
  "geometry": {"coordinates":[4.8462319374,50.4782791138],"type":"Point"}
}