{
  "type": "Feature",
  "properties": {
    "addr:full":"Rue De L'eglise 42 Vresse-sur-semois Namur 5550",
    "addr:housenumber":"42",
    "addr:postcode":"5550",
    "addr:street":"Rue De L'Eglise",
    "iso:country":"BE",
    "sg:address":"Rue De L'eglise 42",
    "sg:city":"Vresse-sur-semois",
    "sg:classifiers":[
        {
            "category":"Manufacturing",
            "subcategory":"Textiles",
            "type":"Manufacturing & Wholesale Goods"
        }
    ],
    "sg:phone":"+32 61 50 01 65",
    "sg:postcode":"5550",
    "sg:province":"Namur",
    "wof:name":"Emmanuel Merveille",
    "wof:placetype":"venue"
},
  "geometry": {"coordinates":[4.9336800575,49.8729782104],"type":"Point"}
}