{
  "type": "Feature",
  "properties": {
    "addr:full":"Ruiterslaan 13 Zoersel Antwerpen 2980",
    "addr:housenumber":"13",
    "addr:postcode":"2980",
    "addr:street":"Ruiterslaan",
    "iso:country":"BE",
    "sg:address":"Ruiterslaan 13",
    "sg:city":"Zoersel",
    "sg:orig_category":"Articles m\u00e9dicaux and orthop\u00e9diques",
    "sg:phone":"+32 3 383 20 99",
    "sg:postcode":"2980",
    "sg:province":"Antwerpen",
    "wof:name":"Bluekens J.",
    "wof:placetype":"venue"
},
  "geometry": {"coordinates":[4.713435173,51.269985199],"type":"Point"}
}