{
  "type": "Feature",
  "properties": {
    "iso:country":"BE",
    "sg:address":"Loveld 11",
    "sg:city":"Laarne",
    "sg:orig_category":"Maatkleding Fab Ontwerpers and designers Textiel",
    "sg:phone":"+32 9 230 45 69",
    "sg:postcode":"9270",
    "sg:province":"Oost-Vlaanderen",
    "wof:name":"Huis Khamm",
    "wof:placetype":"venue"
},
  "geometry": {"coordinates":[3.8285980225,51.0308876038],"type":"Point"}
}