{
  "type": "Feature",
  "properties": {
    "iso:country":"BE",
    "sg:address":"Rue Des Bluets 41",
    "sg:city":"Kraainem/kraainem",
    "sg:orig_category":"Epiceries",
    "sg:phone":"+32 2 782 16 36",
    "sg:postcode":"1950",
    "sg:province":"Vlaams-Brabant",
    "wof:name":"Dimitrios Gikas",
    "wof:placetype":"venue"
},
  "geometry": {"coordinates":[4.4701662064,50.8493843079],"type":"Point"}
}