{
  "type": "Feature",
  "properties": {
    "addr:full":"Streepstraat 16 Kapellen Antwerpen 2950",
    "addr:housenumber":"16",
    "addr:postcode":"2950",
    "addr:street":"Streepstraat",
    "iso:country":"BE",
    "sg:address":"Streepstraat 16",
    "sg:city":"Kapellen",
    "sg:orig_category":"Maatschappelijke dienstverlening",
    "sg:phone":"+32 3 664 34 00",
    "sg:postcode":"2950",
    "sg:province":"Antwerpen",
    "wof:name":"Vclb-centrum",
    "wof:placetype":"venue"
},
  "geometry": {"coordinates":[4.4236001968,51.3191261292],"type":"Point"}
}