{
  "type": "Feature",
  "properties": {
    "addr:full":"Panhovenstraat 40 Bree Limburg 3960",
    "addr:housenumber":"40",
    "addr:postcode":"3960",
    "addr:street":"Panhovenstraat",
    "iso:country":"BE",
    "sg:address":"Panhovenstraat 40",
    "sg:city":"Bree",
    "sg:orig_category":"Belastingconsulenten Diverse juridische dienstverlening",
    "sg:phone":"+32 89 47 16 90",
    "sg:postcode":"3960",
    "sg:province":"Limburg",
    "wof:name":"Josiane Voortmans",
    "wof:placetype":"venue"
},
  "geometry": {"coordinates":[5.6160402298,51.1330337524],"type":"Point"}
}