{
  "type": "Feature",
  "properties": {
    "addr:full":"Chauss\u00e9e De Fleurus 461 Charleroi (gilly) Hainaut 6060",
    "addr:housenumber":"461",
    "addr:postcode":"6060",
    "addr:street":"Chausse\u0301E De Fleurus",
    "iso:country":"BE",
    "sg:address":"Chauss\u00e9e De Fleurus 461",
    "sg:city":"Charleroi (gilly)",
    "sg:classifiers":[
        {
            "category":"Building & Trades",
            "subcategory":"Landscaping Services",
            "type":"Services"
        }
    ],
    "sg:phone":"+32 71 42 15 85",
    "sg:postcode":"6060",
    "sg:province":"Hainaut",
    "sg:tags":[
        "gardening",
        "garden",
        "maintenance"
    ],
    "wof:name":"Styles Jardin",
    "wof:placetype":"venue"
},
  "geometry": {"coordinates":[4.4880981445,50.4251937866],"type":"Point"}
}