{
  "type": "Feature",
  "properties": {
    "iso:country":"BE",
    "sg:address":"Rue De La Station 9",
    "sg:city":"Viroinval",
    "sg:classifiers":[
        {
            "category":"Personal",
            "subcategory":"Beauty Salon",
            "type":"Services"
        }
    ],
    "sg:phone":"+32 60 31 12 01",
    "sg:postcode":"5670",
    "sg:province":"Namur",
    "sg:tags":[
        "de",
        "coiffure"
    ],
    "wof:name":"Jeannine Degrelle",
    "wof:placetype":"venue"
},
  "geometry": {"coordinates":[4.5499768257,50.0792045593],"type":"Point"}
}