{
  "type": "Feature",
  "properties": {
    "addr:full":"Rue De Roux 27 Charleroi Hainaut 6030",
    "addr:housenumber":"27",
    "addr:postcode":"6030",
    "addr:street":"Rue De Roux;Hainaut",
    "iso:country":"BE",
    "sg:address":"Rue De Roux 27",
    "sg:city":"Charleroi",
    "sg:orig_category":"Elektrische installaties voor woningen",
    "sg:phone":"+32 71 31 19 03",
    "sg:postcode":"6030",
    "sg:province":"Hainaut",
    "wof:name":"Bilalis Zacharias",
    "wof:placetype":"venue"
},
  "geometry": {"coordinates":[4.4044098854,50.427028656],"type":"Point"}
}