{
  "type": "Feature",
  "properties": {
    "addr:full":"Avenue De Longvic 20 Florennes Namur 5620",
    "addr:housenumber":"20",
    "addr:postcode":"5620",
    "addr:street":"Avenue De Longvic",
    "iso:country":"BE",
    "sg:address":"Avenue De Longvic 20",
    "sg:city":"Florennes",
    "sg:orig_category":"Brood, gebak and snoepgoed",
    "sg:phone":"+32 71 68 82 63",
    "sg:postcode":"5620",
    "sg:province":"Namur",
    "wof:name":"J.p. Marechal",
    "wof:placetype":"venue"
},
  "geometry": {"coordinates":[4.610449791,50.2454910278],"type":"Point"}
}