{
  "type": "Feature",
  "properties": {
    "iso:country":"BE",
    "sg:address":"Hendrik I Lei 27",
    "sg:city":"Vilvoorde",
    "sg:orig_category":"V\u00e9t\u00e9rinaires",
    "sg:phone":"+32 2 251 27 65",
    "sg:postcode":"1800",
    "sg:province":"Vlaams-Brabant",
    "wof:name":"Follebout",
    "wof:placetype":"venue"
},
  "geometry": {"coordinates":[4.4287648201,50.9308433533],"type":"Point"}
}