{
  "type": "Feature",
  "properties": {
    "iso:country":"BE",
    "sg:address":"Reinpadstraat 106",
    "sg:city":"Genk",
    "sg:orig_category":"M\u00e9decins and sp\u00e9cialistes",
    "sg:phone":"+32 89 36 12 40",
    "sg:postcode":"3600",
    "sg:province":"Limburg",
    "wof:name":"Rita Vanmaele",
    "wof:placetype":"venue"
},
  "geometry": {"coordinates":[5.5118899345,50.9724388123],"type":"Point"}
}