{
  "type": "Feature",
  "properties": {
    "iso:country":"BE",
    "sg:address":"Rue Des Bollandistes 27",
    "sg:city":"Etterbeek/etterbeek",
    "sg:orig_category":"Agences de presse",
    "sg:phone":"+32 2 687 50 14",
    "sg:postcode":"1040",
    "sg:province":"Bruxelles-Capitale",
    "wof:name":"Isabelle Ghislain",
    "wof:placetype":"venue"
},
  "geometry": {"coordinates":[4.4032759666,50.8355140686],"type":"Point"}
}