{
  "type": "Feature",
  "properties": {
    "addr:full":"Kruisstraat 224ba Ronse/renaix Oost-Vlaanderen 9600",
    "addr:housenumber":"224ba",
    "addr:postcode":"9600",
    "addr:street":"Kruisstraat",
    "iso:country":"BE",
    "sg:address":"Kruisstraat 224ba",
    "sg:city":"Ronse/renaix",
    "sg:orig_category":"Gespecialiseerde residenti\u00eble bouw",
    "sg:phone":"+32 55 20 93 31",
    "sg:postcode":"9600",
    "sg:province":"Oost-Vlaanderen",
    "wof:name":"Patrick Lammens",
    "wof:placetype":"venue"
},
  "geometry": {"coordinates":[3.5906429291,50.7554359436],"type":"Point"}
}