{
  "type": "Feature",
  "properties": {
    "iso:country":"BE",
    "sg:address":"Rue Du Pr\u00e9 De La Haye 16",
    "sg:city":"Oupeye",
    "sg:classifiers":[
        {
            "category":"Health Services",
            "subcategory":"Doctor",
            "type":"Services"
        }
    ],
    "sg:phone":"+32 4 264 40 88",
    "sg:postcode":"4680",
    "sg:province":"Li\u00e8ge",
    "sg:tags":[
        "medicinephysicians",
        "surgeon"
    ],
    "wof:name":"Collette R",
    "wof:placetype":"venue"
},
  "geometry": {"coordinates":[5.6448397636,50.7044792175],"type":"Point"}
}