{
  "type": "Feature",
  "properties": {
    "iso:country":"BE",
    "sg:address":"Barelstraat 132",
    "sg:city":"Bornem",
    "sg:classifiers":[
        {
            "category":"Building & Trades",
            "subcategory":"Pest Control",
            "type":"Services"
        }
    ],
    "sg:phone":"+32 3 889 15 82",
    "sg:postcode":"2880",
    "sg:province":"Antwerpen",
    "sg:tags":[
        "painting",
        "contractor"
    ],
    "wof:name":"Schilders Kamiel Bvba",
    "wof:placetype":"venue"
},
  "geometry": {"coordinates":[4.2330451012,51.0914306641],"type":"Point"}
}