{
  "type": "Feature",
  "properties": {
    "addr:full":"Bosstraat 18 Hemiksem Antwerpen 2620",
    "addr:housenumber":"18",
    "addr:postcode":"2620",
    "addr:street":"Bosstraat",
    "iso:country":"BE",
    "sg:address":"Bosstraat 18",
    "sg:city":"Hemiksem",
    "sg:orig_category":"Plaatsen van vloer- and muurbekleding Vloer- and muurbekleding",
    "sg:phone":"+32 3 887 62 67",
    "sg:postcode":"2620",
    "sg:province":"Antwerpen",
    "wof:name":"Ibea",
    "wof:placetype":"venue"
},
  "geometry": {"coordinates":[4.3368201256,51.1326904297],"type":"Point"}
}