{
  "type": "Feature",
  "properties": {
    "addr:full":"Rue Emile Vandervelde 119 Saint-ghislain Hainaut 7332",
    "addr:housenumber":"119",
    "addr:postcode":"7332",
    "addr:street":"Rue Emile Vandervelde;Hainaut",
    "iso:country":"BE",
    "sg:address":"Rue Emile Vandervelde 119",
    "sg:city":"Saint-ghislain",
    "sg:orig_category":"Dierenartsen",
    "sg:phone":"+32 65 62 00 21",
    "sg:postcode":"7332",
    "sg:province":"Hainaut",
    "wof:name":"Michel Doyen",
    "wof:placetype":"venue"
},
  "geometry": {"coordinates":[3.786839962,50.5054969788],"type":"Point"}
}