{
  "type": "Feature",
  "properties": {
    "addr:full":"Rue Du Mouton 17-19 Ath Hainaut 7800",
    "addr:housenumber":"17-19",
    "addr:postcode":"7800",
    "addr:street":"Rue Du Mouton",
    "iso:country":"BE",
    "sg:address":"Rue Du Mouton 17-19",
    "sg:city":"Ath",
    "sg:classifiers":[
        {
            "category":"Banks & Credit Unions",
            "subcategory":"Investment Brokerage",
            "type":"Services"
        }
    ],
    "sg:phone":"+32 68 28 28 25",
    "sg:postcode":"7800",
    "sg:province":"Hainaut",
    "sg:tags":[
        "printing",
        "-"
    ],
    "wof:name":"Paternostre",
    "wof:placetype":"venue"
},
  "geometry": {"coordinates":[3.7768929005,50.6301498413],"type":"Point"}
}