{
  "type": "Feature",
  "properties": {
    "iso:country":"BE",
    "sg:address":"Rue Foulia 4a",
    "sg:city":"Wanze",
    "sg:orig_category":"Telecommunicatieapparaten",
    "sg:phone":"+32 85 71 13 67",
    "sg:postcode":"4520",
    "sg:province":"Li\u00e8ge",
    "wof:name":"Ancia Ets",
    "wof:placetype":"venue"
},
  "geometry": {"coordinates":[5.1511211395,50.5454978943],"type":"Point"}
}