{
  "type": "Feature",
  "properties": {
    "addr:full":"Rivierstraat 54 Lochristi Oost-Vlaanderen 9080",
    "addr:housenumber":"54",
    "addr:postcode":"9080",
    "addr:street":"Rivierstraat",
    "iso:country":"BE",
    "sg:address":"Rivierstraat 54",
    "sg:city":"Lochristi",
    "sg:orig_category":"Imprimeries and copyshops",
    "sg:phone":"+32 9 355 52 70",
    "sg:postcode":"9080",
    "sg:province":"Oost-Vlaanderen",
    "wof:name":"Bruyneel",
    "wof:placetype":"venue"
},
  "geometry": {"coordinates":[3.8812859058,51.0743675232],"type":"Point"}
}