{
  "type": "Feature",
  "properties": {
    "addr:full":"Biestmolenstraat 33 Zwalm (nederzwalm-hermelgem) Oost-Vlaanderen 9636",
    "addr:housenumber":"33",
    "addr:postcode":"9636",
    "addr:street":"Biestmolenstraat;Nederzwalm-Hermelgem Oost-Vlaanderen",
    "iso:country":"BE",
    "sg:address":"Biestmolenstraat 33",
    "sg:city":"Zwalm (nederzwalm-hermelgem)",
    "sg:classifiers":[
        {
            "category":"Building & Trades",
            "subcategory":"Cleaning & Sanitation",
            "type":"Services"
        }
    ],
    "sg:phone":"+32 55 49 70 03",
    "sg:postcode":"9636",
    "sg:province":"Oost-Vlaanderen",
    "sg:tags":[
        "fa\u00e7ade",
        "maintenance"
    ],
    "wof:name":"Michiels W",
    "wof:placetype":"venue"
},
  "geometry": {"coordinates":[3.6943750381,50.879699707],"type":"Point"}
}