{
  "type": "Feature",
  "properties": {
    "iso:country":"BE",
    "sg:address":"De Rivierendreef 210b12",
    "sg:city":"Jette",
    "sg:classifiers":[
        {
            "category":"Insurance",
            "subcategory":"Insurance Agent",
            "type":"Services"
        }
    ],
    "sg:phone":"+32 2 428 24 36",
    "sg:postcode":"1090",
    "sg:province":"Bruxelles-Capitale",
    "sg:tags":[
        "verzekeringsmakelaars",
        "expert"
    ],
    "wof:name":"Assuconseil",
    "wof:placetype":"venue"
},
  "geometry": {"coordinates":[4.3198552132,50.8796920776],"type":"Point"}
}