{
  "type": "Feature",
  "properties": {
    "iso:country":"BE",
    "sg:address":"Beverhoutstraat 35",
    "sg:city":"Oostkamp",
    "sg:orig_category":"Groententeelt",
    "sg:phone":"+32 50 35 78 93",
    "sg:postcode":"8020",
    "sg:province":"West-Vlaanderen",
    "wof:name":"Luc Lootens",
    "wof:placetype":"venue"
},
  "geometry": {"coordinates":[3.2770550251,51.1762809753],"type":"Point"}
}