{
  "type": "Feature",
  "properties": {
    "iso:country":"BE",
    "sg:address":"Rue Des Fran\u00e7ais 99",
    "sg:city":"Aiseau-presles (roselies)",
    "sg:classifiers":[
        {
            "category":"Building & Trades",
            "subcategory":"Electrical",
            "type":"Services"
        }
    ],
    "sg:phone":"+32 71 74 45 05",
    "sg:postcode":"6250",
    "sg:province":"Hainaut",
    "sg:tags":[
        "electric",
        "-",
        "housewiring",
        "contractor"
    ],
    "wof:name":"Lambert B",
    "wof:placetype":"venue"
},
  "geometry": {"coordinates":[4.5805702209,50.4233932495],"type":"Point"}
}