{
  "type": "Feature",
  "properties": {
    "addr:full":"Hoogte Honderdplein 31 Vorst/forest Bruxelles-Capitale 1190",
    "addr:housenumber":"31",
    "addr:postcode":"1190",
    "addr:street":"Hoogte Honderdplein;/ Forest",
    "iso:country":"BE",
    "sg:address":"Hoogte Honderdplein 31",
    "sg:city":"Vorst/forest",
    "sg:orig_category":"Banken and kredietinstellingen",
    "sg:phone":"+32 2 344 32 01",
    "sg:postcode":"1190",
    "sg:province":"Bruxelles-Capitale",
    "wof:name":"Fortis",
    "wof:placetype":"venue"
},
  "geometry": {"coordinates":[4.3361091614,50.8163871765],"type":"Point"}
}