{
  "type": "Feature",
  "properties": {
    "addr:full":"Rue Vanderkindere 167 Ukkel/uccle Bruxelles-Capitale 1180",
    "addr:housenumber":"167",
    "addr:postcode":"1180",
    "addr:street":"Rue Vanderkindere;/",
    "iso:country":"BE",
    "sg:address":"Rue Vanderkindere 167",
    "sg:city":"Ukkel/uccle",
    "sg:orig_category":"Rev\u00eatements pour sols and murs. Peinture. Eclairage et \u00e9quipements du foyer",
    "sg:phone":"+32 2 343 64 54",
    "sg:postcode":"1180",
    "sg:province":"Bruxelles-Capitale",
    "wof:name":"Jacques Kinsoen",
    "wof:placetype":"venue"
},
  "geometry": {"coordinates":[4.3491611481,50.813785553],"type":"Point"}
}