{
  "type": "Feature",
  "properties": {
    "iso:country":"BE",
    "sg:address":"Rue Des Charrons 46",
    "sg:city":"Alleur",
    "sg:orig_category":"Anti-Skid Floor Treatment",
    "sg:phone":"+32 4 247 98 47",
    "sg:postcode":"4432",
    "sg:province":"Li\u00e8ge",
    "wof:name":"Travieso S.p.r.l.",
    "wof:placetype":"venue"
},
  "geometry": {"coordinates":[5.5058398247,50.6691131592],"type":"Point"}
}