{
  "type": "Feature",
  "properties": {
    "addr:full":"Processiebaan 36 Merchtem Vlaams-Brabant 1785",
    "addr:housenumber":"36",
    "addr:postcode":"1785",
    "addr:street":"Processiebaan",
    "iso:country":"BE",
    "sg:address":"Processiebaan 36",
    "sg:city":"Merchtem",
    "sg:orig_category":"Boissons",
    "sg:phone":"+32 52 37 22 05",
    "sg:postcode":"1785",
    "sg:province":"Vlaams-Brabant",
    "wof:name":"Supermarkt",
    "wof:placetype":"venue"
},
  "geometry": {"coordinates":[4.2263598442,50.9862365723],"type":"Point"}
}