{
  "type": "Feature",
  "properties": {
    "iso:country":"BE",
    "sg:address":"Molenstraat 135",
    "sg:city":"Affligem (essene)",
    "sg:orig_category":"Autombile concessionaires",
    "sg:phone":"+32 53 67 23 58",
    "sg:postcode":"1790",
    "sg:province":"Vlaams-Brabant",
    "wof:name":"Gar Peelman Bvba",
    "wof:placetype":"venue"
},
  "geometry": {"coordinates":[4.1230659485,50.8925132751],"type":"Point"}
}