{
  "type": "Feature",
  "properties": {
    "iso:country":"BE",
    "sg:address":"Hippoliet Persoonsstraat 8",
    "sg:city":"Gent (gentbrugge)",
    "sg:classifiers":[
        {
            "category":"Social Services",
            "subcategory":"Child Care",
            "type":"Services"
        }
    ],
    "sg:phone":"+32 9 231 75 54",
    "sg:postcode":"9050",
    "sg:province":"Oost-Vlaanderen",
    "sg:tags":[
        "baby",
        "nursery",
        "day",
        "sitting"
    ],
    "wof:name":"Paradijsje ('t)",
    "wof:placetype":"venue"
},
  "geometry": {"coordinates":[3.7571549416,51.0385360718],"type":"Point"}
}