{
  "type": "Feature",
  "properties": {
    "addr:full":"Rue Pont \u00e0 Nole 181 Charleroi (mont-sur-marchienne) Hainaut 6032",
    "addr:housenumber":"181",
    "addr:postcode":"6032",
    "addr:street":"Rue Pont A\u0300 Nole",
    "iso:country":"BE",
    "sg:address":"Rue Pont \u00e0 Nole 181",
    "sg:city":"Charleroi (mont-sur-marchienne)",
    "sg:classifiers":[
        {
            "category":"Mining & Drilling",
            "type":"Manufacturing & Wholesale Goods"
        }
    ],
    "sg:phone":"+32 71 51 53 58",
    "sg:postcode":"6032",
    "sg:province":"Hainaut",
    "sg:tags":[
        "quarry"
    ],
    "wof:name":"Gralex Carri\u00e8re Sa Sa",
    "wof:placetype":"venue"
},
  "geometry": {"coordinates":[4.3888998032,50.3833312988],"type":"Point"}
}