{
  "type": "Feature",
  "properties": {
    "iso:country":"BE",
    "sg:address":"Ieperstraat 120c",
    "sg:city":"Wervik (geluwe)",
    "sg:classifiers":[
        {
            "category":"Retail",
            "subcategory":"Veterinary Services",
            "type":"Services"
        }
    ],
    "sg:phone":"+32 56 51 45 48",
    "sg:postcode":"8940",
    "sg:province":"West-Vlaanderen",
    "sg:tags":[
        "veterinarian"
    ],
    "wof:name":"Vangheluwe L",
    "wof:placetype":"venue"
},
  "geometry": {"coordinates":[3.0651390553,50.8127632141],"type":"Point"}
}