{
  "type": "Feature",
  "properties": {
    "addr:full":"Koekuitstraat 3 Diksmuide West-Vlaanderen 8600",
    "addr:housenumber":"3",
    "addr:postcode":"8600",
    "addr:street":"Koekuitstraat",
    "iso:country":"BE",
    "sg:address":"Koekuitstraat 3",
    "sg:city":"Diksmuide",
    "sg:orig_category":"Varkenskwekers",
    "sg:phone":"+32 51 50 33 42",
    "sg:postcode":"8600",
    "sg:province":"West-Vlaanderen",
    "wof:name":"Christian Vangheluwe",
    "wof:placetype":"venue"
},
  "geometry": {"coordinates":[2.8842151165,51.0043334961],"type":"Point"}
}