{
  "type": "Feature",
  "properties": {
    "addr:full":"Nijverheidsstr 13 Boechout Antwerpen 2530",
    "addr:housenumber":"13",
    "addr:postcode":"2530",
    "addr:street":"Nijverheidsstr",
    "iso:country":"BE",
    "sg:address":"Nijverheidsstr 13",
    "sg:city":"Boechout",
    "sg:classifiers":[
        {
            "category":"Food & Beverages",
            "subcategory":"Groceries & Convenience Stores",
            "type":"Retail Goods"
        }
    ],
    "sg:phone":"+32 3 366 21 21",
    "sg:postcode":"2530",
    "sg:province":"Antwerpen",
    "sg:tags":[
        "product",
        "grain",
        "cereal",
        "related"
    ],
    "wof:name":"Oce-bio Bvba",
    "wof:placetype":"venue"
},
  "geometry": {"coordinates":[4.4894990921,51.1681137085],"type":"Point"}
}