{
  "type": "Feature",
  "properties": {
    "addr:full":"Diepenbekerweg 8 Hasselt Limburg 3500",
    "addr:housenumber":"8",
    "addr:postcode":"3500",
    "addr:street":"Diepenbekerweg",
    "iso:country":"BE",
    "sg:address":"Diepenbekerweg 8",
    "sg:city":"Hasselt",
    "sg:classifiers":[
        {
            "category":"Autos & Motor Vehicles",
            "subcategory":"Motorcycle Sales",
            "type":"Retail Goods"
        }
    ],
    "sg:phone":"+32 11 22 33 73",
    "sg:postcode":"3500",
    "sg:province":"Limburg",
    "sg:tags":[
        "yamaha"
    ],
    "wof:name":"Bike Service",
    "wof:placetype":"venue"
},
  "geometry": {"coordinates":[5.3617367744,50.9261627197],"type":"Point"}
}