{
  "type": "Feature",
  "properties": {
    "addr:full":"Rue Des Hayettes 88 Namur Namur 5000",
    "addr:housenumber":"88",
    "addr:postcode":"5000",
    "addr:street":"Rue Des Hayettes",
    "iso:country":"BE",
    "sg:address":"Rue Des Hayettes 88",
    "sg:city":"Namur",
    "sg:classifiers":[
        {
            "category":"Building & Trades",
            "subcategory":"Landscaping Services",
            "type":"Services"
        }
    ],
    "sg:phone":"+32 81 73 33 60",
    "sg:postcode":"5000",
    "sg:province":"Namur",
    "sg:tags":[
        "gardening",
        "garden",
        "maintenance"
    ],
    "wof:name":"A-z Jardins",
    "wof:placetype":"venue"
},
  "geometry": {"coordinates":[4.8405327797,50.4556465149],"type":"Point"}
}