{
  "type": "Feature",
  "properties": {
    "addr:full":"Diesterstraat 22 Box 2 Sint-truiden Limburg 3800",
    "addr:housenumber":"22;2",
    "addr:postcode":"3800",
    "addr:street":"Diesterstraat;Box",
    "iso:country":"BE",
    "sg:address":"Diesterstraat 22 Box 2",
    "sg:city":"Sint-truiden",
    "sg:classifiers":[
        {
            "category":"Home & Garden",
            "subcategory":"Home Furnishings",
            "type":"Retail Goods"
        }
    ],
    "sg:phone":"+32 11 68 01 30",
    "sg:postcode":"3800",
    "sg:province":"Limburg",
    "sg:tags":[
        "wallpaper",
        "-"
    ],
    "wof:name":"Lamberts Firma Bvba",
    "wof:placetype":"venue"
},
  "geometry": {"coordinates":[5.1856069565,50.8170471191],"type":"Point"}
}