{
  "type": "Feature",
  "properties": {
    "iso:country":"BE",
    "sg:address":"De Hoef 5",
    "sg:city":"Houthalen-helchteren",
    "sg:orig_category":"Erotische Etablissementen",
    "sg:phone":"+32 11 52 17 02",
    "sg:postcode":"3530",
    "sg:province":"Limburg",
    "wof:name":"Ho-rec",
    "wof:placetype":"venue"
},
  "geometry": {"coordinates":[5.4676308632,51.0240402222],"type":"Point"}
}