{
  "type": "Feature",
  "properties": {
    "iso:country":"BE",
    "sg:address":"Stationsstraat 91",
    "sg:city":"Lanaken",
    "sg:classifiers":[
        {
            "category":"Shopping",
            "subcategory":"Pets & Pet Supplies",
            "type":"Retail Goods"
        }
    ],
    "sg:phone":"+32 89 71 20 68",
    "sg:postcode":"3620",
    "sg:province":"Limburg",
    "sg:tags":[
        "shop",
        "-"
    ],
    "wof:name":"Bobbaerts Nv",
    "wof:placetype":"venue"
},
  "geometry": {"coordinates":[5.6473069191,50.8871955872],"type":"Point"}
}