{
  "type": "Feature",
  "properties": {
    "addr:full":"Lodorp 24 Aalter Oost-Vlaanderen 9880",
    "addr:housenumber":"24",
    "addr:postcode":"9880",
    "addr:street":"Lodorp",
    "iso:country":"BE",
    "sg:address":"Lodorp 24",
    "sg:city":"Aalter",
    "sg:orig_category":"Pain, p\u00e2tisseries and confiseries",
    "sg:phone":"+32 51 68 84 07",
    "sg:postcode":"9880",
    "sg:province":"Oost-Vlaanderen",
    "wof:name":"Patriek De Jaeger",
    "wof:placetype":"venue"
},
  "geometry": {"coordinates":[3.4635848999,51.0488815308],"type":"Point"}
}