{
  "type": "Feature",
  "properties": {
    "addr:full":"Jan Van Rijswijcklaan 164 Box 16 Antwerpen Antwerpen 2020",
    "addr:housenumber":"164 box 16",
    "addr:postcode":"2020",
    "addr:street":"Jan Van Rijswijcklaan",
    "iso:country":"BE",
    "sg:address":"Jan Van Rijswijcklaan 164 Box 16",
    "sg:city":"Antwerpen",
    "sg:classifiers":[
        {
            "category":"Real Estate",
            "subcategory":"Real Estate Services",
            "type":"Services"
        }
    ],
    "sg:phone":"+32 3 238 41 00",
    "sg:postcode":"2020",
    "sg:province":"Antwerpen",
    "wof:name":"Bouw & Immo Service (bis) Nv",
    "wof:placetype":"venue"
},
  "geometry": {"coordinates":[4.3977508545,51.1913223267],"type":"Point"}
}