{
  "type": "Feature",
  "properties": {
    "addr:full":"Generaal De Gaullelaan 18 Elsene/ixelles Bruxelles-Capitale 1050",
    "addr:housenumber":"18",
    "addr:postcode":"1050",
    "addr:street":"Generaal De Gaullelaan",
    "iso:country":"BE",
    "sg:address":"Generaal De Gaullelaan 18",
    "sg:city":"Elsene/ixelles",
    "sg:orig_category":"Diverse grafische activiteiten",
    "sg:phone":"+32 2 648 86 70",
    "sg:postcode":"1050",
    "sg:province":"Bruxelles-Capitale",
    "wof:name":"Bureau Marsily J.p.",
    "wof:placetype":"venue"
},
  "geometry": {"coordinates":[4.3708200455,50.8261184692],"type":"Point"}
}