{
  "type": "Feature",
  "properties": {
    "iso:country":"BE",
    "sg:address":"Diepestraat 7",
    "sg:city":"Houthalen-helchteren",
    "sg:orig_category":"Jardinage",
    "sg:phone":"+32 11 52 54 31",
    "sg:postcode":"3530",
    "sg:province":"Limburg",
    "wof:name":"Hendrickx",
    "wof:placetype":"venue"
},
  "geometry": {"coordinates":[5.3772039413,51.027721405],"type":"Point"}
}