{
  "type": "Feature",
  "properties": {
    "addr:full":"Gentsesteenweg 1131 Sint-agatha-berchem/berchem-sa Bruxelles-Capitale 1082",
    "addr:housenumber":"1131",
    "addr:postcode":"1082",
    "addr:street":"Gentsesteenweg",
    "iso:country":"BE",
    "sg:address":"Gentsesteenweg 1131",
    "sg:city":"Sint-agatha-berchem/berchem-sa",
    "sg:orig_category":"Banken and kredietinstellingen",
    "sg:phone":"+32 2 465 33 01",
    "sg:postcode":"1082",
    "sg:province":"Bruxelles-Capitale",
    "wof:name":"Fortis",
    "wof:placetype":"venue"
},
  "geometry": {"coordinates":[4.2970848083,50.8647613525],"type":"Point"}
}