{
  "type": "Feature",
  "properties": {
    "iso:country":"BE",
    "sg:address":"Oudstrijdersstraat 10",
    "sg:city":"Asse",
    "sg:classifiers":[
        {
            "category":"Cafe",
            "type":"Food & Drink"
        }
    ],
    "sg:phone":"+32 2 452 36 63",
    "sg:postcode":"1730",
    "sg:province":"Vlaams-Brabant",
    "sg:tags":[
        "caf\u00e9s"
    ],
    "wof:name":"Pascal Vanderstraeten",
    "wof:placetype":"venue"
},
  "geometry": {"coordinates":[4.2176418304,50.932926178],"type":"Point"}
}