{
  "type": "Feature",
  "properties": {
    "iso:country":"BE",
    "sg:address":"Groenenhoekweg 5",
    "sg:city":"Hemiksem",
    "sg:orig_category":"Avocats and conseillers juridiques",
    "sg:phone":"+32 3 248 56 91",
    "sg:postcode":"2620",
    "sg:province":"Antwerpen",
    "wof:name":"Veronique Rogiest",
    "wof:placetype":"venue"
},
  "geometry": {"coordinates":[4.3514261246,51.1471176147],"type":"Point"}
}