{
  "type": "Feature",
  "properties": {
    "addr:full":"Kammenstraat 31 Aalst (hofstade) Oost-Vlaanderen 9308",
    "addr:housenumber":"31",
    "addr:postcode":"9308",
    "addr:street":"Kammenstraat",
    "iso:country":"BE",
    "sg:address":"Kammenstraat 31",
    "sg:city":"Aalst (hofstade)",
    "sg:classifiers":[
        {
            "category":"Home & Garden",
            "subcategory":"Building Materials",
            "type":"Retail Goods"
        }
    ],
    "sg:phone":"+32 53 78 80 70",
    "sg:postcode":"9308",
    "sg:province":"Oost-Vlaanderen",
    "sg:tags":[
        "article",
        "-",
        "do-it-yourself"
    ],
    "wof:name":"De Somer Nv",
    "wof:placetype":"venue"
},
  "geometry": {"coordinates":[4.0347590446,50.9603500366],"type":"Point"}
}