{
  "type": "Feature",
  "properties": {
    "iso:country":"BE",
    "sg:address":"Max Temmermanlaan 30",
    "sg:city":"Kalmthout",
    "sg:orig_category":"Traitements param\u00e9dicaux",
    "sg:phone":"+32 3 666 48 84",
    "sg:postcode":"2920",
    "sg:province":"Antwerpen",
    "wof:name":"Van Gils En Eerdekens",
    "wof:placetype":"venue"
},
  "geometry": {"coordinates":[4.4460721016,51.3678207397],"type":"Point"}
}