{
  "type": "Feature",
  "properties": {
    "addr:full":"Akkerstraat 82-84 Gent Oost-Vlaanderen 9000",
    "addr:housenumber":"82-84",
    "addr:postcode":"9000",
    "addr:street":"Akkerstraat;Oost-Vlaanderen",
    "iso:country":"BE",
    "sg:address":"Akkerstraat 82-84",
    "sg:city":"Gent",
    "sg:orig_category":"V\u00eatements, chaussures and accessoires Gr",
    "sg:phone":"+32 9 224 20 04",
    "sg:postcode":"9000",
    "sg:province":"Oost-Vlaanderen",
    "wof:name":"Astria",
    "wof:placetype":"venue"
},
  "geometry": {"coordinates":[3.7099149227,51.055431366],"type":"Point"}
}