{
  "type": "Feature",
  "properties": {
    "addr:full":"Grand Bru 2 Durbuy Luxembourg 6941",
    "addr:housenumber":"2",
    "addr:postcode":"6941",
    "addr:street":"Grand Bru",
    "iso:country":"BE",
    "sg:address":"Grand Bru 2",
    "sg:city":"Durbuy",
    "sg:orig_category":"Installations and terrains de sport hors centres sportifs. Terrains de camping. H\u00f4tels",
    "sg:phone":"+32 86 49 95 81",
    "sg:postcode":"6941",
    "sg:province":"Luxembourg",
    "wof:name":"Grand Bru",
    "wof:placetype":"venue"
},
  "geometry": {"coordinates":[5.524184227,50.3770332336],"type":"Point"}
}