{
  "type": "Feature",
  "properties": {
    "addr:full":"Route Charlemagne 147 Welkenraedt (henri-chapelle) Li\u00e8ge 4841",
    "addr:housenumber":"147",
    "addr:postcode":"4841",
    "addr:street":"Route Charlemagne;Henri-Chapelle",
    "iso:country":"BE",
    "sg:address":"Route Charlemagne 147",
    "sg:city":"Welkenraedt (henri-chapelle)",
    "sg:classifiers":[
        {
            "category":"Professional",
            "subcategory":"Art Services",
            "type":"Services"
        }
    ],
    "sg:phone":"+32 87 89 02 76",
    "sg:postcode":"4841",
    "sg:province":"Li\u00e8ge",
    "sg:tags":[
        "installation",
        "cafe",
        "-",
        "equipment"
    ],
    "wof:name":"Vaniflor Plus",
    "wof:placetype":"venue"
},
  "geometry": {"coordinates":[5.9546499252,50.684299469],"type":"Point"}
}