{
  "type": "Feature",
  "properties": {
    "addr:full":"Vaartstraat 8 Kampenhout Vlaams-Brabant 1910",
    "addr:housenumber":"8",
    "addr:postcode":"1910",
    "addr:street":"Vaartstraat",
    "iso:country":"BE",
    "sg:address":"Vaartstraat 8",
    "sg:city":"Kampenhout",
    "sg:orig_category":"Kampeerterreinen",
    "sg:phone":"+32 16 60 36 37",
    "sg:postcode":"1910",
    "sg:province":"Vlaams-Brabant",
    "wof:name":"Kampeerverblijf Veronique",
    "wof:placetype":"venue"
},
  "geometry": {"coordinates":[4.6063699722,50.9565582275],"type":"Point"}
}