{
  "type": "Feature",
  "properties": {
    "iso:country":"BE",
    "sg:address":"Tentoonstellingslaan 61",
    "sg:city":"Gent",
    "sg:classifiers":[
        {
            "category":"Insurance",
            "subcategory":"Life Insurance",
            "type":"Services"
        }
    ],
    "sg:phone":"+32 9 223 90 34",
    "sg:postcode":"9000",
    "sg:province":"Oost-Vlaanderen",
    "sg:tags":[
        "assurance"
    ],
    "wof:name":"Denassur",
    "wof:placetype":"venue"
},
  "geometry": {"coordinates":[3.7334620953,51.0414543152],"type":"Point"}
}