{
  "type": "Feature",
  "properties": {
    "iso:country":"BE",
    "sg:address":"Oude Rondelaan 94",
    "sg:city":"Leuven",
    "sg:orig_category":"Boekhouders",
    "sg:phone":"+32 16 23 02 02",
    "sg:postcode":"3000",
    "sg:province":"Vlaams-Brabant",
    "wof:name":"Jacqueline Vanlint",
    "wof:placetype":"venue"
},
  "geometry": {"coordinates":[4.68663311,50.8868904114],"type":"Point"}
}