{
  "type": "Feature",
  "properties": {
    "iso:country":"BE",
    "sg:address":"Beverhoutsveldstraat 28",
    "sg:city":"Beernem (oedelem)",
    "sg:classifiers":[
        {
            "category":"Building & Trades",
            "subcategory":"Landscaping Services",
            "type":"Services"
        }
    ],
    "sg:phone":"+32 479 80 50 81",
    "sg:postcode":"8730",
    "sg:province":"West-Vlaanderen",
    "sg:tags":[
        "gardening",
        "garden",
        "maintenance"
    ],
    "wof:name":"Roose T",
    "wof:placetype":"venue"
},
  "geometry": {"coordinates":[3.3005259037,51.1805534363],"type":"Point"}
}