{
  "type": "Feature",
  "properties": {
    "addr:full":"'t Angereelstraat 78 Ninove Oost-Vlaanderen 9400",
    "addr:housenumber":"78",
    "addr:postcode":"9400",
    "addr:street":"';Angereelstraat",
    "iso:country":"BE",
    "sg:address":"'t Angereelstraat 78",
    "sg:city":"Ninove",
    "sg:orig_category":"Elektrische installaties voor woningen",
    "sg:phone":"+32 54 33 40 68",
    "sg:postcode":"9400",
    "sg:province":"Oost-Vlaanderen",
    "wof:name":"Hendrik Foutre",
    "wof:placetype":"venue"
},
  "geometry": {"coordinates":[3.9718499184,50.8149299622],"type":"Point"}
}