{
  "type": "Feature",
  "properties": {
    "iso:country":"BE",
    "sg:address":"Lenneke Marelaan 12 Box 1",
    "sg:city":"Zaventem (sint-stevens-woluwe)",
    "sg:classifiers":[
        {
            "category":"Utilities",
            "subcategory":"Telephone",
            "type":"Services"
        }
    ],
    "sg:phone":"+32 2 713 65 40",
    "sg:postcode":"1932",
    "sg:province":"Vlaams-Brabant",
    "sg:tags":[
        "-",
        "internet"
    ],
    "wof:name":"Uniway",
    "wof:placetype":"venue"
},
  "geometry": {"coordinates":[4.45043993,50.8566017151],"type":"Point"}
}