{
  "type": "Feature",
  "properties": {
    "addr:full":"Stwg. Op Vilvoorde 112 Opwijk Vlaams-Brabant 1745",
    "addr:housenumber":"112",
    "addr:postcode":"1745",
    "addr:street":"Op Vilvoorde",
    "iso:country":"BE",
    "sg:address":"Stwg. Op Vilvoorde 112",
    "sg:city":"Opwijk",
    "sg:classifiers":[
        {
            "category":"Military Area",
            "subcategory":"Naval Base",
            "type":"Public Place"
        }
    ],
    "sg:phone":"+32 52 35 55 54",
    "sg:postcode":"1745",
    "sg:province":"Vlaams-Brabant",
    "sg:tags":[
        "profile",
        "sun",
        "aluminium",
        "blind"
    ],
    "wof:name":"Van Hoof B.v.b.a.",
    "wof:placetype":"venue"
},
  "geometry": {"coordinates":[4.1936712265,50.9579124451],"type":"Point"}
}