{
  "type": "Feature",
  "properties": {
    "iso:country":"BE",
    "sg:address":"Rue Des D\u00e9port\u00e9s 63",
    "sg:city":"Charleroi (roux)",
    "sg:classifiers":[
        {
            "category":"Banks & Credit Unions",
            "subcategory":"Investment Brokerage",
            "type":"Services"
        }
    ],
    "sg:phone":"+32 71 35 43 64",
    "sg:postcode":"6044",
    "sg:province":"Hainaut",
    "sg:tags":[
        "-",
        "demonstration",
        "sale"
    ],
    "wof:name":"Chardon And Co",
    "wof:placetype":"venue"
},
  "geometry": {"coordinates":[4.4031648636,50.4332466125],"type":"Point"}
}