{
  "type": "Feature",
  "properties": {
    "iso:country":"BE",
    "sg:address":"Rue Aripette 68",
    "sg:city":"Seraing (jemeppe-sur-meuse)",
    "sg:classifiers":[
        {
            "category":"Manufacturing",
            "subcategory":"Tools & Machinery",
            "type":"Manufacturing & Wholesale Goods"
        }
    ],
    "sg:phone":"+32 4 233 60 55",
    "sg:postcode":"4101",
    "sg:province":"Li\u00e8ge",
    "sg:tags":[
        "builder"
    ],
    "wof:name":"Hydromeca 2000 Sprl",
    "wof:placetype":"venue"
},
  "geometry": {"coordinates":[5.4976959229,50.6156196594],"type":"Point"}
}