{
  "type": "Feature",
  "properties": {
    "addr:full":"Jan De Cordesstraat 19 Putte Antwerpen 2580",
    "addr:housenumber":"19",
    "addr:postcode":"2580",
    "addr:street":"Jan De Cordesstraat",
    "iso:country":"BE",
    "sg:address":"Jan De Cordesstraat 19",
    "sg:city":"Putte",
    "sg:orig_category":"S\u00e9curit\u00e9 sociale",
    "sg:phone":"+32 15 75 25 45",
    "sg:postcode":"2580",
    "sg:province":"Antwerpen",
    "wof:name":"Socialist. Mutualiteit",
    "wof:placetype":"venue"
},
  "geometry": {"coordinates":[4.66441679,51.0599136353],"type":"Point"}
}