{
  "type": "Feature",
  "properties": {
    "iso:country":"BE",
    "sg:address":"Leenweg 13",
    "sg:city":"Brugge",
    "sg:orig_category":"Paramedische behandelingen",
    "sg:phone":"+32 50 33 78 72",
    "sg:postcode":"8000",
    "sg:province":"West-Vlaanderen",
    "wof:name":"K. De Mey",
    "wof:placetype":"venue"
},
  "geometry": {"coordinates":[3.2425560951,51.2299957275],"type":"Point"}
}