{
  "type": "Feature",
  "properties": {
    "iso:country":"BE",
    "sg:address":"Venelle De La R\u00c9serve 31",
    "sg:city":"Wavre",
    "sg:orig_category":"Artsen and specialisten",
    "sg:phone":"+32 10 22 62 19",
    "sg:postcode":"1301",
    "sg:province":"Brabant Wallon",
    "wof:name":"Paul Bouch\u00c9",
    "wof:placetype":"venue"
},
  "geometry": {"coordinates":[4.6187157631,50.7028541565],"type":"Point"}
}