{
  "type": "Feature",
  "properties": {
    "iso:country":"BE",
    "sg:address":"Klaterbaan 82",
    "sg:city":"Aalst",
    "sg:orig_category":"Sportclubs",
    "sg:phone":"+32 53 70 43 88",
    "sg:postcode":"9300",
    "sg:province":"Oost-Vlaanderen",
    "wof:name":"B.c. Aalst",
    "wof:placetype":"venue"
},
  "geometry": {"coordinates":[4.0637001991,50.9386138916],"type":"Point"}
}