{
  "type": "Feature",
  "properties": {
    "addr:full":"Rue Du Commerce 38 Libin Luxembourg 6890",
    "addr:housenumber":"38",
    "addr:postcode":"6890",
    "addr:street":"Rue Du Commerce",
    "iso:country":"BE",
    "sg:address":"Rue Du Commerce 38",
    "sg:city":"Libin",
    "sg:orig_category":"Supermarkten",
    "sg:phone":"+32 61 65 54 94",
    "sg:postcode":"6890",
    "sg:province":"Luxembourg",
    "wof:name":"Libalimar",
    "wof:placetype":"venue"
},
  "geometry": {"coordinates":[5.2563910484,49.983089447],"type":"Point"}
}