{
  "type": "Feature",
  "properties": {
    "addr:full":"Eedstraat 91 Anderlecht/anderlecht Bruxelles-Capitale 1070",
    "addr:housenumber":"91",
    "addr:postcode":"1070",
    "addr:street":"Eedstraat",
    "iso:country":"BE",
    "sg:address":"Eedstraat 91",
    "sg:city":"Anderlecht/anderlecht",
    "sg:classifiers":[
        {
            "category":"Fast Food",
            "type":"Food & Drink"
        }
    ],
    "sg:phone":"+32 2 520 83 02",
    "sg:postcode":"1070",
    "sg:province":"Bruxelles-Capitale",
    "sg:tags":[
        "meeneem",
        "restaurant"
    ],
    "wof:name":"Rest. Dieux De L'olympe",
    "wof:placetype":"venue"
},
  "geometry": {"coordinates":[4.3083119392,50.838596344],"type":"Point"}
}