{
  "type": "Feature",
  "properties": {
    "addr:full":"Rue Doyen Van Belle 2 Braine L'alleud (braine-l'alleud) Brabant Wallon 1420",
    "addr:housenumber":"2",
    "addr:postcode":"1420",
    "addr:street":"Rue Doyen Van Belle",
    "iso:country":"BE",
    "sg:address":"Rue Doyen Van Belle 2",
    "sg:city":"Braine L'alleud (braine-l'alleud)",
    "sg:classifiers":[
        {
            "category":"Professional",
            "subcategory":"Lawyer & Legal Services",
            "type":"Services"
        }
    ],
    "sg:phone":"+32 2 384 22 00",
    "sg:postcode":"1420",
    "sg:province":"Brabant Wallon",
    "sg:tags":[
        "notary"
    ],
    "wof:name":"Van Elder C",
    "wof:placetype":"venue"
},
  "geometry": {"coordinates":[-75.60595703120001,37.7877616882],"type":"Point"}
}