{
  "type": "Feature",
  "properties": {
    "addr:full":"Rue De Gaesbecq 6b Ittre Brabant Wallon 1460",
    "addr:housenumber":"6b;1460",
    "addr:street":"Rue De Gaesbecq",
    "iso:country":"BE",
    "sg:address":"Rue De Gaesbecq 6b",
    "sg:city":"Ittre",
    "sg:classifiers":[
        {
            "category":"Health Services",
            "subcategory":"Doctor",
            "type":"Services"
        }
    ],
    "sg:phone":"+32 67 64 93 92",
    "sg:postcode":"1460",
    "sg:province":"Brabant Wallon",
    "sg:tags":[
        "medicinephysicians",
        "surgeon"
    ],
    "wof:name":"Hody Jean-luc",
    "wof:placetype":"venue"
},
  "geometry": {"coordinates":[4.2722091675,50.6501235962],"type":"Point"}
}