{
  "type": "Feature",
  "properties": {
    "addr:full":"Sint-jansstraat 29 Izegem West-Vlaanderen 8870",
    "addr:housenumber":"29",
    "addr:postcode":"8870",
    "addr:street":"Sint-Jansstraat",
    "iso:country":"BE",
    "sg:address":"Sint-jansstraat 29",
    "sg:city":"Izegem",
    "sg:orig_category":"Supermarkten Warenhuizen",
    "sg:phone":"+32 51 30 37 80",
    "sg:postcode":"8870",
    "sg:province":"West-Vlaanderen",
    "wof:name":"Supra Koffie",
    "wof:placetype":"venue"
},
  "geometry": {"coordinates":[3.195374012,50.9329719543],"type":"Point"}
}