{
  "type": "Feature",
  "properties": {
    "addr:full":"Tragel 9 Aalst Oost-Vlaanderen 9300",
    "addr:housenumber":"9",
    "addr:postcode":"9300",
    "addr:street":"Tragel",
    "iso:country":"BE",
    "sg:address":"Tragel 9",
    "sg:city":"Aalst",
    "sg:orig_category":"Zand and grindontginning",
    "sg:phone":"+32 53 78 95 01",
    "sg:postcode":"9300",
    "sg:province":"Oost-Vlaanderen",
    "wof:name":"C.n.a. Breekcentrale",
    "wof:placetype":"venue"
},
  "geometry": {"coordinates":[4.0362668037,50.948764801],"type":"Point"}
}