{
  "type": "Feature",
  "properties": {
    "iso:country":"BE",
    "sg:address":"Rue Bois-de-sclessin 52",
    "sg:city":"Li\u00c8ge",
    "sg:orig_category":"Afval and schroot Gh",
    "sg:phone":"+32 4 367 21 84",
    "sg:postcode":"4031",
    "sg:province":"Li\u00e8ge",
    "wof:name":"Richard Meurs",
    "wof:placetype":"venue"
},
  "geometry": {"coordinates":[5.5671758652,50.5917167664],"type":"Point"}
}