{
  "type": "Feature",
  "properties": {
    "addr:full":"Chemin De La Core 34 Libramont-chevigny (bras) Luxembourg 6800",
    "addr:housenumber":"34",
    "addr:postcode":"6800",
    "addr:street":"Chemin De La Core",
    "iso:country":"BE",
    "sg:address":"Chemin De La Core 34",
    "sg:city":"Libramont-chevigny (bras)",
    "sg:classifiers":[
        {
            "category":"Personal",
            "subcategory":"Beauty Salon",
            "type":"Services"
        }
    ],
    "sg:phone":"+32 61 61 19 53",
    "sg:postcode":"6800",
    "sg:province":"Luxembourg",
    "sg:tags":[
        "lady",
        "-",
        "hairdressing"
    ],
    "wof:name":"Kathy (coiffure)",
    "wof:placetype":"venue"
},
  "geometry": {"coordinates":[5.3891320229,49.9823493958],"type":"Point"}
}