{
  "type": "Feature",
  "properties": {
    "addr:full":"Kiewitseweg 5 Zutendaal Limburg 3690",
    "addr:housenumber":"5",
    "addr:postcode":"3690",
    "addr:street":"Kiewitseweg",
    "iso:country":"BE",
    "sg:address":"Kiewitseweg 5",
    "sg:city":"Zutendaal",
    "sg:orig_category":"Auberges de jeunesse and refuges",
    "sg:phone":"+32 89 71 40 65",
    "sg:postcode":"3690",
    "sg:province":"Limburg",
    "wof:name":"Jeugdhuis Broeder Bertus",
    "wof:placetype":"venue"
},
  "geometry": {"coordinates":[5.6036968231,50.9070739746],"type":"Point"}
}