{
  "type": "Feature",
  "properties": {
    "iso:country":"BE",
    "sg:address":"Gasthuisstraat 16",
    "sg:city":"Poperinge",
    "sg:orig_category":"Banques and organismes de cr\u00e9dit",
    "sg:phone":"+32 57 33 41 06",
    "sg:postcode":"8970",
    "sg:province":"West-Vlaanderen",
    "wof:name":"Bank Van Roeselare",
    "wof:placetype":"venue"
},
  "geometry": {"coordinates":[2.7243270874,50.8558006287],"type":"Point"}
}