{
  "type": "Feature",
  "properties": {
    "iso:country":"BE",
    "sg:address":"Leest 29",
    "sg:city":"Waarschoot",
    "sg:orig_category":"Studios photographiques",
    "sg:phone":"+32 9 377 21 33",
    "sg:postcode":"9950",
    "sg:province":"Oost-Vlaanderen",
    "wof:name":"Dirk Braeckman",
    "wof:placetype":"venue"
},
  "geometry": {"coordinates":[3.6049249172,51.1465072632],"type":"Point"}
}