{
  "type": "Feature",
  "properties": {
    "addr:full":"Avenue Des Sept Bonniers 28 Ukkel/uccle Bruxelles-Capitale 1180",
    "addr:housenumber":"28",
    "addr:postcode":"1180",
    "addr:street":"Avenue Des Sept Bonniers;/",
    "iso:country":"BE",
    "sg:address":"Avenue Des Sept Bonniers 28",
    "sg:city":"Ukkel/uccle",
    "sg:orig_category":"Pain, p\u00e2tisseries and confiseries",
    "sg:phone":"+32 2 347 12 58",
    "sg:postcode":"1180",
    "sg:province":"Bruxelles-Capitale",
    "wof:name":"Ronny Van Petegem",
    "wof:placetype":"venue"
},
  "geometry": {"coordinates":[4.3379678726,50.8133354187],"type":"Point"}
}