{
  "type": "Feature",
  "properties": {
    "iso:country":"BE",
    "sg:address":"Bouwelsesteenweg 190ba",
    "sg:city":"Nijlen",
    "sg:classifiers":[
        {
            "category":"Cafe",
            "type":"Food & Drink"
        }
    ],
    "sg:phone":"+32 3 411 22 40",
    "sg:postcode":"2560",
    "sg:province":"Antwerpen",
    "sg:tags":[
        "caf\u00e9s"
    ],
    "wof:name":"Caf\u00c9 Den Tassili",
    "wof:placetype":"venue"
},
  "geometry": {"coordinates":[4.6938209534,51.1649627686],"type":"Point"}
}