{
  "type": "Feature",
  "properties": {
    "addr:full":"Reyerstr 3 Kluisbergen Oost-Vlaanderen 9690",
    "addr:housenumber":"3",
    "addr:postcode":"9690",
    "addr:street":"Reyerstr",
    "iso:country":"BE",
    "sg:address":"Reyerstr 3",
    "sg:city":"Kluisbergen",
    "sg:classifiers":[
        {
            "category":"Banks & Credit Unions",
            "subcategory":"Bank",
            "type":"Services"
        }
    ],
    "sg:phone":"+32 55 38 85 74",
    "sg:postcode":"9690",
    "sg:province":"Oost-Vlaanderen",
    "wof:name":"Krediet Nuverheid",
    "wof:placetype":"venue"
},
  "geometry": {"coordinates":[3.5093300343,50.7905158997],"type":"Point"}
}