{
  "type": "Feature",
  "properties": {
    "iso:country":"BE",
    "sg:address":"Berkenlaan 84",
    "sg:city":"Leopoldsburg",
    "sg:classifiers":[
        {
            "category":"Insurance",
            "subcategory":"Insurance Agent",
            "type":"Services"
        }
    ],
    "sg:phone":"+32 11 34 48 94",
    "sg:postcode":"3970",
    "sg:province":"Limburg",
    "sg:tags":[
        "verzekeringsmakelaars",
        "expert"
    ],
    "wof:name":"Zabeau",
    "wof:placetype":"venue"
},
  "geometry": {"coordinates":[5.2480797768,51.1185035706],"type":"Point"}
}