{
  "type": "Feature",
  "properties": {
    "addr:full":"Heistraat 3 Temse Oost-Vlaanderen 9140",
    "addr:housenumber":"3",
    "addr:postcode":"9140",
    "addr:street":"Heistraat",
    "iso:country":"BE",
    "sg:address":"Heistraat 3",
    "sg:city":"Temse",
    "sg:classifiers":[
        {
            "category":"Retail",
            "subcategory":"Veterinary Services",
            "type":"Services"
        }
    ],
    "sg:phone":"+32 3 711 20 41",
    "sg:postcode":"9140",
    "sg:province":"Oost-Vlaanderen",
    "sg:tags":[
        "veterinarian"
    ],
    "wof:name":"Bosman T",
    "wof:placetype":"venue"
},
  "geometry": {"coordinates":[4.2078428268,51.1617469788],"type":"Point"}
}