{
  "type": "Feature",
  "properties": {
    "addr:full":"Wauterbos 73 Sint-genesius-rode/rhode-saint-genese Vlaams-Brabant 1640",
    "addr:housenumber":"73",
    "addr:postcode":"1640",
    "addr:street":"Wauterbos",
    "iso:country":"BE",
    "sg:address":"Wauterbos 73",
    "sg:city":"Sint-genesius-rode/rhode-saint-genese",
    "sg:orig_category":"Boucheries",
    "sg:phone":"+32 2 380 54 65",
    "sg:postcode":"1640",
    "sg:province":"Vlaams-Brabant",
    "wof:name":"Jean Averhals",
    "wof:placetype":"venue"
},
  "geometry": {"coordinates":[4.3568849564,50.7428207397],"type":"Point"}
}