{
  "type": "Feature",
  "properties": {
    "addr:full":"Tulpenstr. 11 Eke Oost-Vlaanderen 9810",
    "addr:housenumber":"11",
    "addr:postcode":"9810",
    "addr:street":"Tulpenstr.",
    "iso:country":"BE",
    "sg:address":"Tulpenstr. 11",
    "sg:city":"Eke",
    "sg:classifiers":[
        {
            "category":"Home & Garden",
            "subcategory":"Furniture",
            "type":"Retail Goods"
        }
    ],
    "sg:phone":"+32 9 228 57 48",
    "sg:postcode":"9810",
    "sg:province":"Oost-Vlaanderen",
    "sg:tags":[
        "wood"
    ],
    "wof:name":"Modern Home Nv",
    "wof:placetype":"venue"
},
  "geometry": {"coordinates":[3.658274889,50.9763908386],"type":"Point"}
}