{
  "type": "Feature",
  "properties": {
    "iso:country":"BE",
    "sg:address":"Stadswaag 1",
    "sg:city":"Hamont-achel",
    "sg:orig_category":"Banken and kredietinstellingen",
    "sg:phone":"+32 11 44 50 42",
    "sg:postcode":"3930",
    "sg:province":"Limburg",
    "wof:name":"Kbc",
    "wof:placetype":"venue"
},
  "geometry": {"coordinates":[5.5450549126,51.2511863708],"type":"Point"}
}