{
  "type": "Feature",
  "properties": {
    "iso:country":"BE",
    "sg:address":"Melopeestraat 50",
    "sg:city":"Sint-jans-molenbeek/molenbeek-saint-jean",
    "sg:orig_category":"Rusthuizen and serviceflats",
    "sg:phone":"+32 2 410 51 01",
    "sg:postcode":"1080",
    "sg:province":"Bruxelles-Capitale",
    "wof:name":"R\u00c9sid. La Toque D\u00b4argent",
    "wof:placetype":"venue"
},
  "geometry": {"coordinates":[4.3146500587,50.8539390564],"type":"Point"}
}