{
  "type": "Feature",
  "properties": {
    "iso:country":"BE",
    "sg:address":"Rue Vital Rousseau 28",
    "sg:city":"Genappe (vieux-genappe)",
    "sg:classifiers":[
        {
            "category":"Farming",
            "subcategory":"Livestock Farm",
            "type":"Manufacturing & Wholesale Goods"
        }
    ],
    "sg:phone":"+32 67 77 26 73",
    "sg:postcode":"1472",
    "sg:province":"Brabant Wallon",
    "sg:tags":[
        "buyer"
    ],
    "wof:name":"Manandise R",
    "wof:placetype":"venue"
},
  "geometry": {"coordinates":[4.393529892,50.6300697327],"type":"Point"}
}