{
  "type": "Feature",
  "properties": {
    "iso:country":"BE",
    "sg:address":"Zeuningenstraat 5",
    "sg:city":"Galmaarden (tollembeek)",
    "sg:classifiers":[
        {
            "category":"Exhibition Hall",
            "type":"Public Place"
        }
    ],
    "sg:phone":"+32 54 58 77 71",
    "sg:postcode":"1570",
    "sg:province":"Vlaams-Brabant",
    "sg:tags":[
        "stand"
    ],
    "wof:name":"Micoform Bvba",
    "wof:placetype":"venue"
},
  "geometry": {"coordinates":[3.9940340519,50.7417221069],"type":"Point"}
}