{
  "type": "Feature",
  "properties": {
    "iso:country":"BE",
    "sg:address":"Meibloemstraat 32",
    "sg:city":"Oud-turnhout",
    "sg:classifiers":[
        {
            "category":"Organizations",
            "subcategory":"Community Association",
            "type":"Services"
        }
    ],
    "sg:phone":"+32 14 45 14 03",
    "sg:postcode":"2360",
    "sg:province":"Antwerpen",
    "sg:tags":[
        "cultural"
    ],
    "wof:name":"Vriendenkring Het Centrum Vzw",
    "wof:placetype":"venue"
},
  "geometry": {"coordinates":[4.9896302223,51.3168411255],"type":"Point"}
}