{
  "type": "Feature",
  "properties": {
    "addr:full":"Chauss\u00e9e De Bruxelles 61e Court-saint-etienne Brabant Wallon 1490",
    "addr:housenumber":"61e;1490",
    "addr:street":"Chausse\u0301E De Bruxelles",
    "iso:country":"BE",
    "sg:address":"Chauss\u00e9e De Bruxelles 61e",
    "sg:city":"Court-saint-etienne",
    "sg:classifiers":[
        {
            "category":"Professional",
            "subcategory":"Computer Services",
            "type":"Services"
        }
    ],
    "sg:phone":"+32 10 61 30 00",
    "sg:postcode":"1490",
    "sg:province":"Brabant Wallon",
    "sg:tags":[
        "-",
        "processing",
        "data"
    ],
    "wof:name":"Neotech Consulting Sprl",
    "wof:placetype":"venue"
},
  "geometry": {"coordinates":[4.5345702171,50.6540603638],"type":"Point"}
}