{
  "type": "Feature",
  "properties": {
    "addr:full":"Place De L'abbaye 14 Komen-waasten/comines-warneton Hainaut 7784",
    "addr:housenumber":"14;7784",
    "addr:street":"Place De L'Abbaye",
    "iso:country":"BE",
    "sg:address":"Place De L'abbaye 14",
    "sg:city":"Komen-waasten/comines-warneton",
    "sg:classifiers":[
        {
            "category":"Cafe",
            "type":"Food & Drink"
        }
    ],
    "sg:phone":"+32 56 55 82 63",
    "sg:postcode":"7784",
    "sg:province":"Hainaut",
    "sg:tags":[
        "caf\u00e9s"
    ],
    "wof:name":"Caf\u00c9 Au Centre Sportif",
    "wof:placetype":"venue"
},
  "geometry": {"coordinates":[2.94947505,50.7527656555],"type":"Point"}
}