{
  "type": "Feature",
  "properties": {
    "addr:full":"Bethani\u00cbnlei 75 Zoersel Antwerpen 2980",
    "addr:housenumber":"75",
    "addr:postcode":"2980",
    "addr:street":"Bethanie\u0308Nlei",
    "iso:country":"BE",
    "sg:address":"Bethani\u00cbnlei 75",
    "sg:city":"Zoersel",
    "sg:classifiers":[
        {
            "category":"Personal",
            "subcategory":"Beauty Salon",
            "type":"Services"
        }
    ],
    "sg:phone":"+32 3 383 26 76",
    "sg:postcode":"2980",
    "sg:province":"Antwerpen",
    "sg:tags":[
        "de",
        "coiffure"
    ],
    "wof:name":"Coiffure Eddy",
    "wof:placetype":"venue"
},
  "geometry": {"coordinates":[4.6374869347,51.2716560364],"type":"Point"}
}