{
  "type": "Feature",
  "properties": {
    "iso:country":"BE",
    "sg:address":"Stationsdreef 47",
    "sg:city":"Roeselare",
    "sg:orig_category":"Alternatieve geneeskunde",
    "sg:phone":"+32 51 22 08 92",
    "sg:postcode":"8800",
    "sg:province":"West-Vlaanderen",
    "wof:name":"Osteopathieassociatie",
    "wof:placetype":"venue"
},
  "geometry": {"coordinates":[3.1274030209,50.953994751],"type":"Point"}
}