{
  "type": "Feature",
  "properties": {
    "iso:country":"BE",
    "sg:address":"Rue Du Ch\u00e2teau-massart 65",
    "sg:city":"Li\u00e8ge 1",
    "sg:classifiers":[
        {
            "category":"Utilities",
            "subcategory":"Telephone",
            "type":"Services"
        }
    ],
    "sg:phone":"+32 4 229 52 81",
    "sg:postcode":"4000",
    "sg:province":"Li\u00e8ge",
    "sg:tags":[
        "-",
        "internet"
    ],
    "wof:name":"Lechanteur Th",
    "wof:placetype":"venue"
},
  "geometry": {"coordinates":[5.5555491447,50.6352462769],"type":"Point"}
}