{
  "type": "Feature",
  "properties": {
    "addr:full":"Avenue De La R\u00c9sistance 14 Boussu Hainaut 7301",
    "addr:housenumber":"14",
    "addr:postcode":"7301",
    "addr:street":"Avenue De La Re\u0301Sistance",
    "iso:country":"BE",
    "sg:address":"Avenue De La R\u00c9sistance 14",
    "sg:city":"Boussu",
    "sg:orig_category":"Onderdelen and accessoires voor auto's",
    "sg:phone":"+32 475 91 41 41",
    "sg:postcode":"7301",
    "sg:province":"Hainaut",
    "wof:name":"Thierry Del Cane",
    "wof:placetype":"venue"
},
  "geometry": {"coordinates":[3.8105220795,50.3997573853],"type":"Point"}
}