{
  "type": "Feature",
  "properties": {
    "iso:country":"BE",
    "sg:address":"Berkenstraat 69",
    "sg:city":"Houthalen-helchteren",
    "sg:orig_category":"Installation \u00e9lectrique r\u00e9sidentielle",
    "sg:phone":"+32 89 84 13 29",
    "sg:postcode":"3530",
    "sg:province":"Limburg",
    "wof:name":"C.a. Electronics",
    "wof:placetype":"venue"
},
  "geometry": {"coordinates":[5.4694881439,51.0300559998],"type":"Point"}
}