{
  "type": "Feature",
  "properties": {
    "addr:full":"Rue Walth\u00e8re-dew\u00e9 72 Li\u00e8ge 1 Li\u00e8ge 4000",
    "addr:housenumber":"72;1",
    "addr:postcode":"4000",
    "addr:street":"Rue Walthe\u0300Re-Dewe\u0301",
    "iso:country":"BE",
    "sg:address":"Rue Walth\u00e8re-dew\u00e9 72",
    "sg:city":"Li\u00e8ge 1",
    "sg:orig_category":"Solariums",
    "sg:phone":"+32 4 227 15 50",
    "sg:postcode":"4000",
    "sg:province":"Li\u00e8ge",
    "wof:name":"Brin De Beaut\u00e9",
    "wof:placetype":"venue"
},
  "geometry": {"coordinates":[5.5929059982,50.6648216248],"type":"Point"}
}