{
  "type": "Feature",
  "properties": {
    "addr:full":"Spoelewielenlaan 8 Lendelede West-Vlaanderen 8860",
    "addr:housenumber":"8",
    "addr:postcode":"8860",
    "addr:street":"Spoelewielenlaan",
    "iso:country":"BE",
    "sg:address":"Spoelewielenlaan 8",
    "sg:city":"Lendelede",
    "sg:classifiers":[
        {
            "category":"Banks & Credit Unions",
            "subcategory":"Investment Brokerage",
            "type":"Services"
        }
    ],
    "sg:phone":"+32 51 30 29 85",
    "sg:postcode":"8860",
    "sg:province":"West-Vlaanderen",
    "sg:tags":[
        "machine",
        "stapling",
        "supply"
    ],
    "wof:name":"Vancanneyt Metaalwaren Nv",
    "wof:placetype":"venue"
},
  "geometry": {"coordinates":[3.2392239571,50.8912658691],"type":"Point"}
}