{
  "type": "Feature",
  "properties": {
    "addr:full":"Koning Albertstraat 103 Mechelen Antwerpen 2800",
    "addr:housenumber":"103",
    "addr:postcode":"2800",
    "addr:street":"Koning Albertstraat",
    "iso:country":"BE",
    "sg:address":"Koning Albertstraat 103",
    "sg:city":"Mechelen",
    "sg:orig_category":"Kapsalons",
    "sg:phone":"+32 15 20 43 87",
    "sg:postcode":"2800",
    "sg:province":"Antwerpen",
    "wof:name":"Coiffure Diane",
    "wof:placetype":"venue"
},
  "geometry": {"coordinates":[4.4707670212,51.0251541138],"type":"Point"}
}