{
  "type": "Feature",
  "properties": {
    "addr:full":"Rue Emile Fran\u00e7ois 3 Genappe (ways) Brabant Wallon 1474",
    "addr:housenumber":"3",
    "addr:postcode":"1474",
    "addr:street":"Rue Emile Franc\u0327Ois;Ways",
    "iso:country":"BE",
    "sg:address":"Rue Emile Fran\u00e7ois 3",
    "sg:city":"Genappe (ways)",
    "sg:classifiers":[
        {
            "category":"Professional",
            "subcategory":"Management & Consulting",
            "type":"Services"
        }
    ],
    "sg:phone":"+32 67 77 12 99",
    "sg:postcode":"1474",
    "sg:province":"Brabant Wallon",
    "sg:tags":[
        "consultant",
        "-",
        "legislation",
        "social"
    ],
    "wof:name":"Secr\u00e9tariat Lois Sociales Sa",
    "wof:placetype":"venue"
},
  "geometry": {"coordinates":[4.4630827904,50.6126594543],"type":"Point"}
}