{
  "type": "Feature",
  "properties": {
    "addr:full":"Chauss\u00e9e Du Roi Baudouin 80 Mons (saint-symphorien) Hainaut 7030",
    "addr:housenumber":"80",
    "addr:postcode":"7030",
    "addr:street":"Chausse\u0301E Du Roi Baudouin",
    "iso:country":"BE",
    "sg:address":"Chauss\u00e9e Du Roi Baudouin 80",
    "sg:city":"Mons (saint-symphorien)",
    "sg:classifiers":[
        {
            "category":"Health Services",
            "subcategory":"Doctor",
            "type":"Services"
        }
    ],
    "sg:phone":"+32 65 34 83 71",
    "sg:postcode":"7030",
    "sg:province":"Hainaut",
    "sg:tags":[
        "medicinephysicians",
        "surgeon"
    ],
    "wof:name":"Forthomme J P",
    "wof:placetype":"venue"
},
  "geometry": {"coordinates":[4.0108299255,50.4393882751],"type":"Point"}
}