{
  "type": "Feature",
  "properties": {
    "iso:country":"BE",
    "sg:address":"Chauss\u00c9e De Gilly 227",
    "sg:city":"Fleurus",
    "sg:orig_category":"Meubles D\u00e9taillants, Am\u00e9nagement de B\u00e2timents et de Cuisines",
    "sg:phone":"+32 71 39 66 76",
    "sg:postcode":"6220",
    "sg:province":"Hainaut",
    "wof:name":"Inter - Salons",
    "wof:placetype":"venue"
},
  "geometry": {"coordinates":[4.5226612091,50.4506912231],"type":"Point"}
}