{
  "type": "Feature",
  "properties": {
    "iso:country":"BE",
    "sg:address":"Route Du Tonnelet 15",
    "sg:city":"Spa",
    "sg:classifiers":[
        {
            "category":"Food & Beverages",
            "subcategory":"Specialty",
            "type":"Retail Goods"
        }
    ],
    "sg:phone":"+32 87 77 35 00",
    "sg:postcode":"4900",
    "sg:province":"Li\u00e8ge",
    "sg:tags":[
        "health",
        "dietary",
        "-",
        "biological"
    ],
    "wof:name":"Proteiform Sprl",
    "wof:placetype":"venue"
},
  "geometry": {"coordinates":[5.8775920868,50.4891738892],"type":"Point"}
}