{
  "type": "Feature",
  "properties": {
    "iso:country":"BE",
    "sg:address":"Rue Roger Salengro 2",
    "sg:city":"Moeskroen/mouscron",
    "sg:classifiers":[
        {
            "category":"Shopping Center",
            "type":"Public Place"
        }
    ],
    "sg:phone":"+32 56 34 97 66",
    "sg:postcode":"7700",
    "sg:province":"Hainaut",
    "sg:tags":[
        "enseignement",
        "formation"
    ],
    "wof:name":"Acad\u00c9mie Des Langues",
    "wof:placetype":"venue"
},
  "geometry": {"coordinates":[3.2323200703,50.7400932312],"type":"Point"}
}