{
  "type": "Feature",
  "properties": {
    "addr:full":"Rue D'anseremme 106a Dinant Namur 5500",
    "addr:housenumber":"106a",
    "addr:postcode":"5500",
    "addr:street":"Rue D'Anseremme",
    "iso:country":"BE",
    "sg:address":"Rue D'anseremme 106a",
    "sg:city":"Dinant",
    "sg:classifiers":[
        {
            "category":"Health Services",
            "subcategory":"Health Practitioner",
            "type":"Services"
        }
    ],
    "sg:phone":"+32 496 13 62 10",
    "sg:postcode":"5500",
    "sg:province":"Namur",
    "sg:tags":[
        "dietitian"
    ],
    "wof:name":"Bourgies Ph",
    "wof:placetype":"venue"
},
  "geometry": {"coordinates":[4.9076199532,50.2383918762],"type":"Point"}
}