{
  "type": "Feature",
  "properties": {
    "addr:full":"Chauss\u00e9e De Charleroi 123a Bruxelles (saint-gilles) Bruxelles-Capitale 1060",
    "addr:housenumber":"123a",
    "addr:postcode":"1060",
    "addr:street":"Chausse\u0301E De Charleroi",
    "iso:country":"BE",
    "sg:address":"Chauss\u00e9e De Charleroi 123a",
    "sg:city":"Bruxelles (saint-gilles)",
    "sg:classifiers":[
        {
            "category":"Professional",
            "subcategory":"Management & Consulting",
            "type":"Services"
        }
    ],
    "sg:phone":"+32 2 534 62 10",
    "sg:postcode":"1060",
    "sg:province":"Bruxelles-Capitale",
    "sg:tags":[
        "-",
        "processing",
        "data",
        "consultant"
    ],
    "wof:name":"European Dynamics Brussels",
    "wof:placetype":"venue"
},
  "geometry": {"coordinates":[4.355506897,50.8293533325],"type":"Point"}
}