{
  "type": "Feature",
  "properties": {
    "addr:full":"Rue De L'h\u00f4tel Communal 33 Fl\u00e9malle (mons-lez-li\u00e8ge) Li\u00e8ge 4400",
    "addr:housenumber":"33",
    "addr:postcode":"4400",
    "addr:street":"Rue De L'Ho \u0302Tel Communal;Mons-Lez-Lie\u0300Ge",
    "iso:country":"BE",
    "sg:address":"Rue De L'h\u00f4tel Communal 33",
    "sg:city":"Fl\u00e9malle (mons-lez-li\u00e8ge)",
    "sg:classifiers":[
        {
            "category":"Health Services",
            "subcategory":"Health Practitioner",
            "type":"Services"
        }
    ],
    "sg:phone":"+32 4 234 46 06",
    "sg:postcode":"4400",
    "sg:province":"Li\u00e8ge",
    "sg:tags":[
        "physiotherapist"
    ],
    "wof:name":"Kiyine Wahed",
    "wof:placetype":"venue"
},
  "geometry": {"coordinates":[5.4571728706,50.6242904663],"type":"Point"}
}