{
  "type": "Feature",
  "properties": {
    "addr:full":"Pladijsstraat 79 Deerlijk West-Vlaanderen 8540",
    "addr:housenumber":"79",
    "addr:postcode":"8540",
    "addr:street":"Pladijsstraat",
    "iso:country":"BE",
    "sg:address":"Pladijsstraat 79",
    "sg:city":"Deerlijk",
    "sg:classifiers":[
        {
            "category":"Food & Beverages",
            "subcategory":"Meat & Fish",
            "type":"Retail Goods"
        }
    ],
    "sg:phone":"+32 56 77 99 40",
    "sg:postcode":"8540",
    "sg:province":"West-Vlaanderen",
    "sg:tags":[
        "-",
        "livestock"
    ],
    "wof:name":"Verhelst P",
    "wof:placetype":"venue"
},
  "geometry": {"coordinates":[3.3563110828,50.8320350647],"type":"Point"}
}