{
  "type": "Feature",
  "properties": {
    "addr:full":"Boulevard Louis Schmidt 1b4 Etterbeek/etterbeek Bruxelles-Capitale 1040",
    "addr:housenumber":"1b4",
    "addr:postcode":"1040",
    "addr:street":"Boulevard Louis Schmidt",
    "iso:country":"BE",
    "sg:address":"Boulevard Louis Schmidt 1b4",
    "sg:city":"Etterbeek/etterbeek",
    "sg:classifiers":[
        {
            "category":"Real Estate",
            "subcategory":"Developer",
            "type":"Services"
        }
    ],
    "sg:phone":"+32 2 732 27 77",
    "sg:postcode":"1040",
    "sg:province":"Bruxelles-Capitale",
    "sg:tags":[
        "plomberie",
        "chauffage",
        "mat\u00e9riel",
        "gr",
        "pour"
    ],
    "wof:name":"Pugh & Co",
    "wof:placetype":"venue"
},
  "geometry": {"coordinates":[4.3976411819,50.8262405396],"type":"Point"}
}