{
  "type": "Feature",
  "properties": {
    "iso:country":"BE",
    "sg:address":"Swaenebeecklaan 25",
    "sg:city":"Schilde ('s Gravenwezel)",
    "sg:classifiers":[
        {
            "category":"Professional",
            "subcategory":"Art Services",
            "type":"Services"
        }
    ],
    "sg:phone":"+32 478 32 13 37",
    "sg:postcode":"2970",
    "sg:province":"Antwerpen",
    "sg:tags":[
        "photography",
        "reporting",
        "-"
    ],
    "wof:name":"Van Mol B",
    "wof:placetype":"venue"
},
  "geometry": {"coordinates":[4.5800938606,51.2601966858],"type":"Point"}
}