{
  "type": "Feature",
  "properties": {
    "addr:full":"Mechelsesteenweg 36 Zaventem Vlaams-Brabant 1933",
    "addr:housenumber":"36",
    "addr:postcode":"1933",
    "addr:street":"Mechelsesteenweg",
    "iso:country":"BE",
    "sg:address":"Mechelsesteenweg 36",
    "sg:city":"Zaventem",
    "sg:orig_category":"Voertuigen",
    "sg:phone":"+32 2 731 91 11",
    "sg:postcode":"1933",
    "sg:province":"Vlaams-Brabant",
    "wof:name":"All Cars",
    "wof:placetype":"venue"
},
  "geometry": {"coordinates":[4.5145277977,50.8618507385],"type":"Point"}
}