{
  "type": "Feature",
  "properties": {
    "addr:full":"Rue De La Halle 15 Namur Namur 5000",
    "addr:housenumber":"15",
    "addr:postcode":"5000",
    "addr:street":"Rue De La Halle",
    "iso:country":"BE",
    "sg:address":"Rue De La Halle 15",
    "sg:city":"Namur",
    "sg:classifiers":[
        {
            "category":"Shopping",
            "subcategory":"Jewelry",
            "type":"Retail Goods"
        }
    ],
    "sg:phone":"+32 81 22 88 60",
    "sg:postcode":"5000",
    "sg:province":"Namur",
    "sg:tags":[
        "jeweller",
        "-"
    ],
    "wof:name":"Maya",
    "wof:placetype":"venue"
},
  "geometry": {"coordinates":[4.8655281067,50.4626350403],"type":"Point"}
}