{
  "type": "Feature",
  "properties": {
    "addr:full":"Quai De L'ourthe 18 Li\u00e8ge 1 (li\u00e8ge 2) Li\u00e8ge 4020",
    "addr:housenumber":"18;1;2",
    "addr:postcode":"4020",
    "addr:street":"Quai De L'Ourthe",
    "iso:country":"BE",
    "sg:address":"Quai De L'ourthe 18",
    "sg:city":"Li\u00e8ge 1 (li\u00e8ge 2)",
    "sg:classifiers":[
        {
            "category":"Building & Trades",
            "subcategory":"Pest Control",
            "type":"Services"
        }
    ],
    "sg:phone":"+32 4 343 15 93",
    "sg:postcode":"4020",
    "sg:province":"Li\u00e8ge",
    "sg:tags":[
        "painting",
        "contractor"
    ],
    "wof:name":"Brants Ch",
    "wof:placetype":"venue"
},
  "geometry": {"coordinates":[5.583946228,50.6376571655],"type":"Point"}
}