{
  "type": "Feature",
  "properties": {
    "addr:full":"Vis\u00c9steenweg 170 Riemst Limburg 3770",
    "addr:housenumber":"170",
    "addr:postcode":"3770",
    "addr:street":"Vise\u0301Steenweg",
    "iso:country":"BE",
    "sg:address":"Vis\u00c9steenweg 170",
    "sg:city":"Riemst",
    "sg:classifiers":[
        {
            "category":"Personal",
            "subcategory":"Beauty Salon",
            "type":"Services"
        }
    ],
    "sg:phone":"+32 12 45 24 90",
    "sg:postcode":"3770",
    "sg:province":"Limburg",
    "sg:tags":[
        "de",
        "coiffure"
    ],
    "wof:name":"Maria Reggers",
    "wof:placetype":"venue"
},
  "geometry": {"coordinates":[5.606347084,50.8036117554],"type":"Point"}
}