{
  "type": "Feature",
  "properties": {
    "addr:full":"Avenue D'itterbeek 394b7 Anderlecht/anderlecht Bruxelles-Capitale 1070",
    "addr:housenumber":"394b7",
    "addr:postcode":"1070",
    "addr:street":"Avenue D'Itterbeek",
    "iso:country":"BE",
    "sg:address":"Avenue D'itterbeek 394b7",
    "sg:city":"Anderlecht/anderlecht",
    "sg:orig_category":"S\u00e9curit\u00e9 sociale",
    "sg:phone":"+32 2 527 18 73",
    "sg:postcode":"1070",
    "sg:province":"Bruxelles-Capitale",
    "wof:name":"Mutualit\u00c9 Socialiste",
    "wof:placetype":"venue"
},
  "geometry": {"coordinates":[4.2972741127,50.8356819153],"type":"Point"}
}