{
  "type": "Feature",
  "properties": {
    "iso:country":"BE",
    "sg:address":"Sint-pietersstraat 27ba",
    "sg:city":"Diksmuide",
    "sg:orig_category":"Eleveurs and marchands de porcs",
    "sg:phone":"+32 51 50 37 59",
    "sg:postcode":"8600",
    "sg:province":"West-Vlaanderen",
    "wof:name":"Joseph Degroote",
    "wof:placetype":"venue"
},
  "geometry": {"coordinates":[2.8799939156,50.9960021973],"type":"Point"}
}