{
  "type": "Feature",
  "properties": {
    "addr:full":"Zandvoordeplaats 16 Zonnebeke West-Vlaanderen 8980",
    "addr:housenumber":"16",
    "addr:postcode":"8980",
    "addr:street":"Zandvoordeplaats",
    "iso:country":"BE",
    "sg:address":"Zandvoordeplaats 16",
    "sg:city":"Zonnebeke",
    "sg:orig_category":"Huisdieren and benodigdheden",
    "sg:phone":"+32 57 46 66 03",
    "sg:postcode":"8980",
    "sg:province":"West-Vlaanderen",
    "wof:name":"G Bourgois",
    "wof:placetype":"venue"
},
  "geometry": {"coordinates":[2.9872550964,50.8730812073],"type":"Point"}
}