{
  "type": "Feature",
  "properties": {
    "addr:full":"Jef Buyckxstraat 206 Turnhout Antwerpen 2300",
    "addr:housenumber":"206",
    "addr:postcode":"2300",
    "addr:street":"Jef Buyckxstraat",
    "iso:country":"BE",
    "sg:address":"Jef Buyckxstraat 206",
    "sg:city":"Turnhout",
    "sg:orig_category":"V\u00e9los. Motos",
    "sg:phone":"+32 14 42 39 64",
    "sg:postcode":"2300",
    "sg:province":"Antwerpen",
    "wof:name":"Wheel Cat",
    "wof:placetype":"venue"
},
  "geometry": {"coordinates":[4.9347791672,51.3040313721],"type":"Point"}
}