{
  "type": "Feature",
  "properties": {
    "iso:country":"BE",
    "sg:address":"Brugmannlaan 235",
    "sg:city":"Elsene/ixelles",
    "sg:orig_category":"Diverse grafische activiteiten Marktonderzoekbureaus",
    "sg:phone":"+32 2 345 28 10",
    "sg:postcode":"1050",
    "sg:province":"Bruxelles-Capitale",
    "wof:name":"Fe. Eres Communication",
    "wof:placetype":"venue"
},
  "geometry": {"coordinates":[4.348154068,50.8143882751],"type":"Point"}
}