{
  "type": "Feature",
  "properties": {
    "iso:country":"BE",
    "sg:address":"Rue Du Tchaurnia 23",
    "sg:city":"Houyet (mesnil-saint-blaise)",
    "sg:classifiers":[
        {
            "category":"Building & Trades",
            "subcategory":"Plumbing",
            "type":"Services"
        }
    ],
    "sg:phone":"+32 82 74 44 77",
    "sg:postcode":"5560",
    "sg:province":"Namur",
    "sg:tags":[
        "contractor"
    ],
    "wof:name":"Rosiere Piette Sprl",
    "wof:placetype":"venue"
},
  "geometry": {"coordinates":[4.8931698799,50.1678009033],"type":"Point"}
}