{
  "type": "Feature",
  "properties": {
    "iso:country":"BE",
    "sg:address":"Pl Gambetta 26",
    "sg:city":"Roux",
    "sg:classifiers":[
        {
            "category":"Banks & Credit Unions",
            "subcategory":"Bank",
            "type":"Services"
        }
    ],
    "sg:phone":"+32 84 45 11 22",
    "sg:postcode":"6160",
    "wof:name":"Banque Bruxelles Lambert Sa",
    "wof:placetype":"venue"
},
  "geometry": {"coordinates":[19.1364707947,51.9225082397],"type":"Point"}
}