{
  "type": "Feature",
  "properties": {
    "iso:country":"BE",
    "sg:address":"Rue De Mons 21",
    "sg:city":"Soignies",
    "sg:orig_category":"Advocaten and juridische adviseurs",
    "sg:phone":"+32 67 34 11 51",
    "sg:postcode":"7060",
    "sg:province":"Hainaut",
    "wof:name":"Pascale Crucq",
    "wof:placetype":"venue"
},
  "geometry": {"coordinates":[4.0711488724,50.5782356262],"type":"Point"}
}