{
  "type": "Feature",
  "properties": {
    "iso:country":"BE",
    "sg:address":"Chauss\u00e9e De Ch\u00e2telineau 117",
    "sg:city":"Charleroi (montignies-sur-sambre)",
    "sg:classifiers":[
        {
            "category":"Health Services",
            "subcategory":"Doctor",
            "type":"Services"
        }
    ],
    "sg:phone":"+32 71 31 94 48",
    "sg:postcode":"6061",
    "sg:province":"Hainaut",
    "sg:tags":[
        "medicinephysicians",
        "surgeon"
    ],
    "wof:name":"Jacquet Michel",
    "wof:placetype":"venue"
},
  "geometry": {"coordinates":[4.4859170914,50.4009933472],"type":"Point"}
}