{
  "type": "Feature",
  "properties": {
    "iso:country":"BE",
    "sg:address":"Leuvensestraat 39",
    "sg:city":"Tienen",
    "sg:classifiers":[
        {
            "category":"Cafe",
            "type":"Food & Drink"
        }
    ],
    "sg:phone":"+32 16 78 25 82",
    "sg:postcode":"3300",
    "sg:province":"Vlaams-Brabant",
    "sg:tags":[
        "snack-bars"
    ],
    "wof:name":"Pousse Caf\u00e9",
    "wof:placetype":"venue"
},
  "geometry": {"coordinates":[4.9346528053,50.8090858459],"type":"Point"}
}