{
  "type": "Feature",
  "properties": {
    "iso:country":"BE",
    "sg:address":"Rue Du Cure 15",
    "sg:city":"Libin",
    "sg:classifiers":[
        {
            "category":"Food & Beverages",
            "subcategory":"Supermarket",
            "type":"Retail Goods"
        }
    ],
    "sg:phone":"+32 61 65 58 75",
    "sg:postcode":"6890",
    "sg:province":"Luxembourg",
    "sg:tags":[
        "department",
        "store"
    ],
    "wof:name":"Spar Supermarch\u00e9",
    "wof:placetype":"venue"
},
  "geometry": {"coordinates":[5.2581310272,49.9786872864],"type":"Point"}
}