{
  "type": "Feature",
  "properties": {
    "iso:country":"BE",
    "sg:address":"Rue Joseph Wauters 67",
    "sg:city":"Huy",
    "sg:classifiers":[
        {
            "category":"Retail",
            "subcategory":"Veterinary Services",
            "type":"Services"
        }
    ],
    "sg:phone":"+32 85 25 35 01",
    "sg:postcode":"4500",
    "sg:province":"Li\u00e8ge",
    "sg:tags":[
        "veterinarian"
    ],
    "wof:name":"Petit S",
    "wof:placetype":"venue"
},
  "geometry": {"coordinates":[5.2221531868,50.5186233521],"type":"Point"}
}