{
  "type": "Feature",
  "properties": {
    "addr:full":"Avenue Hugo Van Der Goes 59 Oudergem/auderghem Bruxelles-Capitale 1160",
    "addr:housenumber":"59",
    "addr:postcode":"1160",
    "addr:street":"Avenue Hugo Van Der Goes;/",
    "iso:country":"BE",
    "sg:address":"Avenue Hugo Van Der Goes 59",
    "sg:city":"Oudergem/auderghem",
    "sg:orig_category":"Mat\u00e9riel m\u00e9dical and orthop\u00e9dique and proth\u00e8ses Fab",
    "sg:phone":"+32 2 673 28 32",
    "sg:postcode":"1160",
    "sg:province":"Bruxelles-Capitale",
    "wof:name":"Michael Epiphanoff",
    "wof:placetype":"venue"
},
  "geometry": {"coordinates":[4.440694809,50.8093299866],"type":"Point"}
}