{
  "type": "Feature",
  "properties": {
    "addr:full":"Avenue Henri Lepage 5 Wavre Brabant Wallon 1300",
    "addr:housenumber":"5;1300",
    "addr:street":"Avenue Henri Lepage",
    "iso:country":"BE",
    "sg:address":"Avenue Henri Lepage 5",
    "sg:city":"Wavre",
    "sg:classifiers":[
        {
            "category":"Health Services",
            "subcategory":"Hospital",
            "type":"Services"
        }
    ],
    "sg:phone":"+32 10 24 16 26",
    "sg:postcode":"1300",
    "sg:province":"Brabant Wallon",
    "wof:name":"Clinique Du Champ Ste-anne Ex Index v",
    "wof:placetype":"venue"
},
  "geometry": {"coordinates":[4.608276844,50.719909668],"type":"Point"}
}