{
  "type": "Feature",
  "properties": {
    "iso:country":"BE",
    "sg:address":"Rue Des Canonniers 14",
    "sg:city":"Nivelles",
    "sg:classifiers":[
        {
            "category":"Education",
            "subcategory":"University",
            "type":"Public Place"
        }
    ],
    "sg:phone":"+32 67 84 13 75",
    "sg:postcode":"1400",
    "sg:province":"Brabant Wallon",
    "sg:tags":[
        "adult"
    ],
    "wof:name":"Centre De Formation Culturelle Et Sociale Ottignies",
    "wof:placetype":"venue"
},
  "geometry": {"coordinates":[4.3246850967,50.6003227234],"type":"Point"}
}