{
  "type": "Feature",
  "properties": {
    "iso:country":"BE",
    "sg:address":"Oude Kerkstraat 5",
    "sg:city":"Kruibeke",
    "sg:orig_category":"Producteurs de fruits",
    "sg:phone":"+32 3 774 18 04",
    "sg:postcode":"9150",
    "sg:province":"Oost-Vlaanderen",
    "wof:name":"Frans Blommaert",
    "wof:placetype":"venue"
},
  "geometry": {"coordinates":[4.2977957726,51.1477279663],"type":"Point"}
}