{
  "type": "Feature",
  "properties": {
    "addr:full":"Rue De Longpr\u00e9 25 Perwez (thorembais-les-b\u00e9guines) Brabant Wallon 1360",
    "addr:housenumber":"25",
    "addr:postcode":"1360",
    "addr:street":"Rue De Longpre\u0301;Wallon",
    "iso:country":"BE",
    "sg:address":"Rue De Longpr\u00e9 25",
    "sg:city":"Perwez (thorembais-les-b\u00e9guines)",
    "sg:classifiers":[
        {
            "category":"Banks & Credit Unions",
            "subcategory":"Investment Brokerage",
            "type":"Services"
        }
    ],
    "sg:phone":"+32 10 88 85 30",
    "sg:postcode":"1360",
    "sg:province":"Brabant Wallon",
    "sg:tags":[
        "auditor"
    ],
    "wof:name":"Carmon D",
    "wof:placetype":"venue"
},
  "geometry": {"coordinates":[4.8170700073,50.6551856995],"type":"Point"}
}