{
  "type": "Feature",
  "properties": {
    "addr:full":"Leebrugstraat 33 Sint-niklaas (sinaai) Oost-Vlaanderen 9112",
    "addr:housenumber":"33",
    "addr:postcode":"9112",
    "addr:street":"Leebrugstraat",
    "iso:country":"BE",
    "sg:address":"Leebrugstraat 33",
    "sg:city":"Sint-niklaas (sinaai)",
    "sg:classifiers":[
        {
            "category":"Parking",
            "subcategory":"Lot",
            "type":"Transportation"
        }
    ],
    "sg:phone":"+32 3 772 54 04",
    "sg:postcode":"9112",
    "sg:province":"Oost-Vlaanderen",
    "sg:tags":[
        "parking-places",
        "laying-out"
    ],
    "wof:name":"De Coster",
    "wof:placetype":"venue"
},
  "geometry": {"coordinates":[4.0066890717,51.1529998779],"type":"Point"}
}