{
  "type": "Feature",
  "properties": {
    "iso:country":"BE",
    "sg:address":"Dorpsstraat 37",
    "sg:city":"Koekelare",
    "sg:classifiers":[
        {
            "category":"Cafe",
            "type":"Food & Drink"
        }
    ],
    "sg:phone":"+32 51 58 97 36",
    "sg:postcode":"8680",
    "sg:province":"West-Vlaanderen",
    "sg:tags":[
        "caf\u00e9s"
    ],
    "wof:name":"Cafe De Lantaarn",
    "wof:placetype":"venue"
},
  "geometry": {"coordinates":[2.9758789539,51.0895385742],"type":"Point"}
}