{
  "type": "Feature",
  "properties": {
    "iso:country":"BE",
    "sg:address":"Cour Robert 43",
    "sg:city":"Saint-nicolas (tilleur)",
    "sg:classifiers":[
        {
            "category":"Building & Trades",
            "subcategory":"Pest Control",
            "type":"Services"
        }
    ],
    "sg:phone":"+32 4 234 49 51",
    "sg:postcode":"4420",
    "sg:province":"Li\u00e8ge",
    "sg:tags":[
        "machine",
        "vending"
    ],
    "wof:name":"Henin J",
    "wof:placetype":"venue"
},
  "geometry": {"coordinates":[5.52983284,50.6216850281],"type":"Point"}
}