{
  "type": "Feature",
  "properties": {
    "iso:country":"BE",
    "sg:address":"Rue S\u00c9minaire 5",
    "sg:city":"Floreffe",
    "sg:orig_category":"Enseignement maternel and primaire",
    "sg:phone":"+32 81 44 08 81",
    "sg:postcode":"5150",
    "sg:province":"Namur",
    "wof:name":"Ecole Primaire Libre",
    "wof:placetype":"venue"
},
  "geometry": {"coordinates":[4.7595148087,50.4320030212],"type":"Point"}
}