{
  "type": "Feature",
  "properties": {
    "addr:full":"Avenue Georges Lema\u00cetre 21 Charleroi Hainaut 6041",
    "addr:housenumber":"21",
    "addr:postcode":"6041",
    "addr:street":"Avenue Georges Lemai\u0302Tre;Hainaut",
    "iso:country":"BE",
    "sg:address":"Avenue Georges Lema\u00cetre 21",
    "sg:city":"Charleroi",
    "sg:orig_category":"Agences de publicit\u00e9. E-activit\u00e9s. Ordinateurs and \u00e9quipement informatique. R\u00e9alisation de programme",
    "sg:phone":"+32 71 25 00 00",
    "sg:postcode":"6041",
    "sg:province":"Hainaut",
    "wof:name":"Charline Production",
    "wof:placetype":"venue"
},
  "geometry": {"coordinates":[4.4795351028,50.4749755859],"type":"Point"}
}