{
  "type": "Feature",
  "properties": {
    "addr:full":"Vroegeinde 5 Zandhoven Antwerpen 2243",
    "addr:housenumber":"5",
    "addr:postcode":"2243",
    "addr:street":"Vroegeinde",
    "iso:country":"BE",
    "sg:address":"Vroegeinde 5",
    "sg:city":"Zandhoven",
    "sg:orig_category":"Eleveurs and marchands de porcs",
    "sg:phone":"+32 3 484 34 18",
    "sg:postcode":"2243",
    "sg:province":"Antwerpen",
    "wof:name":"Dirk Struyfs",
    "wof:placetype":"venue"
},
  "geometry": {"coordinates":[4.692920208,51.1990509033],"type":"Point"}
}