{
  "type": "Feature",
  "properties": {
    "addr:full":"Tremelobaan 119 Keerbergen Vlaams-Brabant 3140",
    "addr:housenumber":"119",
    "addr:postcode":"3140",
    "addr:street":"Tremelobaan",
    "iso:country":"BE",
    "sg:address":"Tremelobaan 119",
    "sg:city":"Keerbergen",
    "sg:classifiers":[
        {
            "category":"Home & Garden",
            "subcategory":"Kitchen Supply",
            "type":"Retail Goods"
        }
    ],
    "sg:phone":"+32 15 73 06 13",
    "sg:postcode":"3140",
    "sg:province":"Vlaams-Brabant",
    "sg:tags":[
        "-",
        "industrial",
        "installation",
        "equipment"
    ],
    "wof:name":"Adviesburo Vreys Sprl",
    "wof:placetype":"venue"
},
  "geometry": {"coordinates":[4.6625051498,50.997467041],"type":"Point"}
}