{
  "type": "Feature",
  "properties": {
    "addr:full":"Rue De Baume 195 La Louvi\u00e8re Hainaut 7100",
    "addr:housenumber":"195",
    "addr:postcode":"7100",
    "addr:street":"Rue De Baume",
    "iso:country":"BE",
    "sg:address":"Rue De Baume 195",
    "sg:city":"La Louvi\u00e8re",
    "sg:classifiers":[
        {
            "category":"Retail",
            "subcategory":"Car Wash",
            "type":"Services"
        }
    ],
    "sg:phone":"+32 64 26 33 56",
    "sg:postcode":"7100",
    "sg:province":"Hainaut",
    "sg:tags":[
        "automobile",
        "washing",
        "-",
        "truck"
    ],
    "wof:name":"Car-wash De Baume",
    "wof:placetype":"venue"
},
  "geometry": {"coordinates":[4.2056012154,50.4731407166],"type":"Point"}
}