{
  "type": "Feature",
  "properties": {
    "addr:full":"Spanjestraat 15 Roeselare West-Vlaanderen 8800",
    "addr:housenumber":"15",
    "addr:postcode":"8800",
    "addr:street":"Spanjestraat",
    "iso:country":"BE",
    "sg:address":"Spanjestraat 15",
    "sg:city":"Roeselare",
    "sg:classifiers":[
        {
            "category":"Building & Trades",
            "subcategory":"Construction",
            "type":"Services"
        }
    ],
    "sg:phone":"+32 51 22 84 97",
    "sg:postcode":"8800",
    "sg:province":"West-Vlaanderen",
    "sg:tags":[
        "ventilating",
        "system"
    ],
    "wof:name":"Elventi Bvba",
    "wof:placetype":"venue"
},
  "geometry": {"coordinates":[3.1326129436,50.9468345642],"type":"Point"}
}