{
  "type": "Feature",
  "properties": {
    "addr:full":"Hoogmolenwegel 11 Waregem West-Vlaanderen 8790",
    "addr:housenumber":"11",
    "addr:postcode":"8790",
    "addr:street":"Hoogmolenwegel",
    "iso:country":"BE",
    "sg:address":"Hoogmolenwegel 11",
    "sg:city":"Waregem",
    "sg:orig_category":"R\u00e9paration and restauration de meubles",
    "sg:phone":"+32 56 60 22 85",
    "sg:postcode":"8790",
    "sg:province":"West-Vlaanderen",
    "wof:name":"Julien Destoop",
    "wof:placetype":"venue"
},
  "geometry": {"coordinates":[3.412651062,50.8808250427],"type":"Point"}
}