{
  "type": "Feature",
  "properties": {
    "addr:full":"Oude Mechelsebaan 363 Aarschot (langdorp) Vlaams-Brabant 3201",
    "addr:housenumber":"363",
    "addr:postcode":"3201",
    "addr:street":"Oude Mechelsebaan",
    "iso:country":"BE",
    "sg:address":"Oude Mechelsebaan 363",
    "sg:city":"Aarschot (langdorp)",
    "sg:classifiers":[
        {
            "category":"Freight",
            "type":"Transportation"
        }
    ],
    "sg:phone":"+32 16 56 65 72",
    "sg:postcode":"3201",
    "sg:province":"Vlaams-Brabant",
    "sg:tags":[
        "-",
        "transport"
    ],
    "wof:name":"Lunatrans Bvba",
    "wof:placetype":"venue"
},
  "geometry": {"coordinates":[4.8547921181,51.0079994202],"type":"Point"}
}