{
  "type": "Feature",
  "properties": {
    "iso:country":"BE",
    "sg:address":"Sint-janslaan 19",
    "sg:city":"Diepenbeek",
    "sg:classifiers":[
        {
            "category":"Personal",
            "subcategory":"Beauty Salon",
            "type":"Services"
        }
    ],
    "sg:phone":"+32 11 32 36 84",
    "sg:postcode":"3590",
    "sg:province":"Limburg",
    "sg:tags":[
        "de",
        "coiffure"
    ],
    "wof:name":"Coiffure Brigitte",
    "wof:placetype":"venue"
},
  "geometry": {"coordinates":[5.4201569557,50.905834198],"type":"Point"}
}