{
  "type": "Feature",
  "properties": {
    "iso:country":"BE",
    "sg:address":"Groenlaan 96",
    "sg:city":"Herzele",
    "sg:orig_category":"Kapsalons",
    "sg:phone":"+32 53 63 16 30",
    "sg:postcode":"9550",
    "sg:province":"Oost-Vlaanderen",
    "wof:name":"Kapsalon Devriendt",
    "wof:placetype":"venue"
},
  "geometry": {"coordinates":[3.8870370388,50.8835334778],"type":"Point"}
}