{
  "type": "Feature",
  "properties": {
    "iso:country":"BE",
    "sg:address":"Boulevard Leopold Ii 241",
    "sg:city":"Koekelberg/koekelberg",
    "sg:orig_category":"M\u00e9decins and sp\u00e9cialistes",
    "sg:phone":"+32 2 420 45 45",
    "sg:postcode":"1081",
    "sg:province":"Bruxelles-Capitale",
    "wof:name":"William Colin",
    "wof:placetype":"venue"
},
  "geometry": {"coordinates":[4.3327140808,50.8628959656],"type":"Point"}
}