{
  "type": "Feature",
  "properties": {
    "addr:full":"Lindelei 65 Hemiksem Antwerpen 2620",
    "addr:housenumber":"65",
    "addr:postcode":"2620",
    "addr:street":"Lindelei",
    "iso:country":"BE",
    "sg:address":"Lindelei 65",
    "sg:city":"Hemiksem",
    "sg:classifiers":[
        {
            "category":"Manufacturing",
            "subcategory":"Lumber",
            "type":"Manufacturing & Wholesale Goods"
        }
    ],
    "sg:phone":"+32 3 870 80 20",
    "sg:postcode":"2620",
    "sg:province":"Antwerpen",
    "sg:tags":[
        "timber"
    ],
    "wof:name":"Gys J & J Houthandel Nv",
    "wof:placetype":"venue"
},
  "geometry": {"coordinates":[4.3425130844,51.148727417],"type":"Point"}
}