{
  "type": "Feature",
  "properties": {
    "addr:full":"Leuvensesteenweg 610 Schaarbeek/schaerbeek Bruxelles-Capitale 1030",
    "addr:housenumber":"610",
    "addr:postcode":"1030",
    "addr:street":"Leuvensesteenweg",
    "iso:country":"BE",
    "sg:address":"Leuvensesteenweg 610",
    "sg:city":"Schaarbeek/schaerbeek",
    "sg:orig_category":"Bagage and lederwaren Schoenen",
    "sg:phone":"+32 2 705 72 71",
    "sg:postcode":"1030",
    "sg:province":"Bruxelles-Capitale",
    "wof:name":"Brantano",
    "wof:placetype":"venue"
},
  "geometry": {"coordinates":[4.3996710777,50.8552589417],"type":"Point"}
}