{
  "type": "Feature",
  "properties": {
    "iso:country":"BE",
    "sg:address":"Rue Centrale 51",
    "sg:city":"Weismes (robertville)",
    "sg:classifiers":[
        {
            "category":"Building & Trades",
            "subcategory":"Construction",
            "type":"Services"
        }
    ],
    "sg:phone":"+32 80 44 55 27",
    "sg:postcode":"4950",
    "sg:province":"Li\u00e8ge",
    "sg:tags":[
        "installation",
        "-",
        "central",
        "heating"
    ],
    "wof:name":"Mts",
    "wof:placetype":"venue"
},
  "geometry": {"coordinates":[6.1224899292,50.4548377991],"type":"Point"}
}