{
  "type": "Feature",
  "properties": {
    "addr:full":"Reigerlaan 7 Alken Limburg 3570",
    "addr:housenumber":"7",
    "addr:postcode":"3570",
    "addr:street":"Reigerlaan",
    "iso:country":"BE",
    "sg:address":"Reigerlaan 7",
    "sg:city":"Alken",
    "sg:classifiers":[
        {
            "category":"Professional",
            "subcategory":"Management & Consulting",
            "type":"Services"
        }
    ],
    "sg:phone":"+32 11 31 42 56",
    "sg:postcode":"3570",
    "sg:province":"Limburg",
    "sg:tags":[
        "consultant"
    ],
    "wof:name":"Sudor Bvba",
    "wof:placetype":"venue"
},
  "geometry": {"coordinates":[5.310614109,50.8721580505],"type":"Point"}
}