{
  "type": "Feature",
  "properties": {
    "addr:full":"Stationsstraat 65 Hooglede (gits) West-Vlaanderen 8830",
    "addr:housenumber":"65",
    "addr:postcode":"8830",
    "addr:street":"Stationsstraat",
    "iso:country":"BE",
    "sg:address":"Stationsstraat 65",
    "sg:city":"Hooglede (gits)",
    "sg:classifiers":[
        {
            "category":"Health Services",
            "subcategory":"Doctor",
            "type":"Services"
        }
    ],
    "sg:phone":"+32 51 22 29 25",
    "sg:postcode":"8830",
    "sg:province":"West-Vlaanderen",
    "sg:tags":[
        "psychotherapist",
        "psychoanalyst"
    ],
    "wof:name":"Psychologisch Ergologisch Expertise Centrum Goddyn",
    "wof:placetype":"venue"
},
  "geometry": {"coordinates":[3.1025259495,50.997341156],"type":"Point"}
}