{
  "type": "Feature",
  "properties": {
    "iso:country":"BE",
    "sg:address":"Inz\u00c8s V\u00c2s 4",
    "sg:city":"Durbuy",
    "sg:classifiers":[
        {
            "category":"Arena",
            "subcategory":"Sports Club",
            "type":"Entertainment"
        }
    ],
    "sg:phone":"+32 86 21 29 31",
    "sg:postcode":"6941",
    "sg:province":"Luxembourg",
    "sg:tags":[
        "terrain",
        "hors",
        "de",
        "installation",
        "sportifs"
    ],
    "wof:name":"Etoile Sp. Heydoise",
    "wof:placetype":"venue"
},
  "geometry": {"coordinates":[5.5358982086,50.3730659485],"type":"Point"}
}