{
  "type": "Feature",
  "properties": {
    "iso:country":"BE",
    "sg:address":"Doelaagstraat 21",
    "sg:city":"Glabbeek (attenrode)",
    "sg:classifiers":[
        {
            "category":"Manufacturing",
            "subcategory":"Electronics",
            "type":"Manufacturing & Wholesale Goods"
        }
    ],
    "sg:phone":"+32 16 77 03 50",
    "sg:postcode":"3384",
    "sg:province":"Vlaams-Brabant",
    "sg:tags":[
        "telecommunication",
        "system"
    ],
    "wof:name":"Decomm Bvba",
    "wof:placetype":"venue"
},
  "geometry": {"coordinates":[4.9152722359,50.8795700073],"type":"Point"}
}