{
  "type": "Feature",
  "properties": {
    "addr:full":"Lourdesstraat 57 Wervik West-Vlaanderen 8940",
    "addr:housenumber":"57",
    "addr:postcode":"8940",
    "addr:street":"Lourdesstraat",
    "iso:country":"BE",
    "sg:address":"Lourdesstraat 57",
    "sg:city":"Wervik",
    "sg:classifiers":[
        {
            "category":"Food & Beverages",
            "subcategory":"Fruits & Vegetables",
            "type":"Retail Goods"
        }
    ],
    "sg:phone":"+32 56 51 16 86",
    "sg:postcode":"8940",
    "sg:province":"West-Vlaanderen",
    "sg:tags":[
        "l\u00e9gumes"
    ],
    "wof:name":"Bernard Ingelbeen",
    "wof:placetype":"venue"
},
  "geometry": {"coordinates":[3.0851631165,50.8148040771],"type":"Point"}
}