{
  "type": "Feature",
  "properties": {
    "iso:country":"BE",
    "sg:address":"Hazelarenlaan 52",
    "sg:city":"Belgium",
    "sg:orig_category":"Mat\u00e9riel scientifique and technique Fab. R\u00e9alisation de programmes and logiciels",
    "sg:phone":"+32 11 24 11 40",
    "sg:postcode":"3500",
    "sg:province":"Limburg",
    "wof:name":"Sts",
    "wof:placetype":"venue"
},
  "geometry": {"coordinates":[5.3548707962,50.9456062317],"type":"Point"}
}