{
  "type": "Feature",
  "properties": {
    "addr:full":"Rue D'harlue 3 Eghez\u00e9e (bolinne) Namur 5310",
    "addr:housenumber":"3",
    "addr:postcode":"5310",
    "addr:street":"Rue D'Harlue;Bolinne",
    "iso:country":"BE",
    "sg:address":"Rue D'harlue 3",
    "sg:city":"Eghez\u00e9e (bolinne)",
    "sg:classifiers":[
        {
            "category":"Freight",
            "type":"Transportation"
        }
    ],
    "sg:phone":"+32 81 81 33 65",
    "sg:postcode":"5310",
    "sg:province":"Namur",
    "sg:tags":[
        "-",
        "transport"
    ],
    "wof:name":"Domaine De Harlue",
    "wof:placetype":"venue"
},
  "geometry": {"coordinates":[4.9137010574,50.6084518433],"type":"Point"}
}