{
  "type": "Feature",
  "properties": {
    "addr:full":"Klaverstraat 49 Brugge West-Vlaanderen 8000",
    "addr:housenumber":"49",
    "addr:postcode":"8000",
    "addr:street":"Klaverstraat",
    "iso:country":"BE",
    "sg:address":"Klaverstraat 49",
    "sg:city":"Brugge",
    "sg:orig_category":"Non-Classified Establishments",
    "sg:phone":"+32 50 44 50 10",
    "sg:postcode":"8000",
    "sg:province":"West-Vlaanderen",
    "wof:name":"Clb 'de Klaver'",
    "wof:placetype":"venue"
},
  "geometry": {"coordinates":[3.2193040848,51.2153587341],"type":"Point"}
}