{
  "type": "Feature",
  "properties": {
    "addr:full":"Pontweg 113 Aalst (herdersem) Oost-Vlaanderen 9310",
    "addr:housenumber":"113",
    "addr:postcode":"9310",
    "addr:street":"Pontweg",
    "iso:country":"BE",
    "sg:address":"Pontweg 113",
    "sg:city":"Aalst (herdersem)",
    "sg:classifiers":[
        {
            "category":"Building & Trades",
            "subcategory":"Construction",
            "type":"Services"
        }
    ],
    "sg:phone":"+32 53 70 38 05",
    "sg:postcode":"9310",
    "sg:province":"Oost-Vlaanderen",
    "sg:tags":[
        "carpenter"
    ],
    "wof:name":"Jansegers K",
    "wof:placetype":"venue"
},
  "geometry": {"coordinates":[4.0774598122,50.961391449],"type":"Point"}
}