{
  "type": "Feature",
  "properties": {
    "addr:full":"Oudenaardestraat 52 Anzegem West-Vlaanderen 8570",
    "addr:housenumber":"52",
    "addr:postcode":"8570",
    "addr:street":"Oudenaardestraat",
    "iso:country":"BE",
    "sg:address":"Oudenaardestraat 52",
    "sg:city":"Anzegem",
    "sg:orig_category":"Overheidsdiensten",
    "sg:phone":"+32 56 77 88 28",
    "sg:postcode":"8570",
    "sg:province":"West-Vlaanderen",
    "wof:name":"O.c.m.w.",
    "wof:placetype":"venue"
},
  "geometry": {"coordinates":[3.4077699184,50.8390846252],"type":"Point"}
}