{
  "type": "Feature",
  "properties": {
    "addr:full":"Leon Spilliaertstraat 41 Oostende West-Vlaanderen 8400",
    "addr:housenumber":"41",
    "addr:postcode":"8400",
    "addr:street":"Leon Spilliaertstraat",
    "iso:country":"BE",
    "sg:address":"Leon Spilliaertstraat 41",
    "sg:city":"Oostende",
    "sg:classifiers":[
        {
            "category":"Personal",
            "subcategory":"Beauty Salon",
            "type":"Services"
        }
    ],
    "sg:phone":"+32 59 50 71 99",
    "sg:postcode":"8400",
    "sg:province":"West-Vlaanderen",
    "sg:tags":[
        "lady",
        "-",
        "hairdressing"
    ],
    "wof:name":"Nicky's Haute Coiffure",
    "wof:placetype":"venue"
},
  "geometry": {"coordinates":[2.9124948978,51.2275772095],"type":"Point"}
}