{
  "type": "Feature",
  "properties": {
    "addr:full":"Dorpstraat 72a Voeren/fourons Limburg 3790",
    "addr:housenumber":"72a",
    "addr:postcode":"3790",
    "addr:street":"Dorpstraat",
    "iso:country":"BE",
    "sg:address":"Dorpstraat 72a",
    "sg:city":"Voeren/fourons",
    "sg:orig_category":"HUISBRANDOLIE",
    "sg:phone":"+32 4 381 32 58",
    "sg:postcode":"3790",
    "sg:province":"Limburg",
    "wof:name":"Julien Walpot",
    "wof:placetype":"venue"
},
  "geometry": {"coordinates":[5.8454608917,50.7517814636],"type":"Point"}
}