{
  "type": "Feature",
  "properties": {
    "iso:country":"BE",
    "sg:address":"Winkelstraat 87",
    "sg:city":"Deinze",
    "sg:orig_category":"Quincailleries",
    "sg:phone":"+32 9 386 55 92",
    "sg:postcode":"9800",
    "sg:province":"Oost-Vlaanderen",
    "wof:name":"Van Maele",
    "wof:placetype":"venue"
},
  "geometry": {"coordinates":[3.530174017,50.9863166809],"type":"Point"}
}