{
  "type": "Feature",
  "properties": {
    "iso:country":"BE",
    "sg:address":"Rue De La Brasserie 28",
    "sg:city":"Charleroi",
    "sg:orig_category":"HUISBRANDOLIE",
    "sg:phone":"+32 71 31 45 23",
    "sg:postcode":"6061",
    "sg:province":"Hainaut",
    "wof:name":"Ets. Foret Guy",
    "wof:placetype":"venue"
},
  "geometry": {"coordinates":[4.4580187798,50.4078025818],"type":"Point"}
}