{
  "type": "Feature",
  "properties": {
    "iso:country":"BE",
    "sg:address":"De Potterstr. 11-13",
    "sg:city":"Brussel",
    "sg:classifiers":[
        {
            "category":"Professional",
            "subcategory":"Engineering",
            "type":"Services"
        }
    ],
    "sg:phone":"+32 2 215 94 29",
    "sg:postcode":"1030",
    "sg:province":"Bruxelles-Capitale",
    "sg:tags":[
        "machine",
        "-",
        "mechanical"
    ],
    "wof:name":"H.s. Dry Cleaning Bvba",
    "wof:placetype":"venue"
},
  "geometry": {"coordinates":[4.364730835,50.8639297485],"type":"Point"}
}