{
  "type": "Feature",
  "properties": {
    "addr:full":"Dorpsstraat 51-53 Kapellen Antwerpen 2950",
    "addr:housenumber":"51-53",
    "addr:postcode":"2950",
    "addr:street":"Dorpsstraat",
    "iso:country":"BE",
    "sg:address":"Dorpsstraat 51-53",
    "sg:city":"Kapellen",
    "sg:classifiers":[
        {
            "category":"Retail",
            "subcategory":"Repair Shop",
            "type":"Services"
        }
    ],
    "sg:phone":"+32 3 664 20 26",
    "sg:postcode":"2950",
    "sg:province":"Antwerpen",
    "sg:tags":[
        "-",
        "mainten",
        "watch",
        "clock"
    ],
    "wof:name":"Blankers Juwelen",
    "wof:placetype":"venue"
},
  "geometry": {"coordinates":[4.958108902,50.8883171082],"type":"Point"}
}