{
  "type": "Feature",
  "properties": {
    "iso:country":"BE",
    "sg:address":"Kazandstraat 5",
    "sg:city":"Pittem",
    "sg:orig_category":"Eleveurs de bovins",
    "sg:phone":"+32 51 40 47 96",
    "sg:postcode":"8740",
    "sg:province":"West-Vlaanderen",
    "wof:name":"Paul De Witte",
    "wof:placetype":"venue"
},
  "geometry": {"coordinates":[3.2921528816,50.9764213562],"type":"Point"}
}