{
  "type": "Feature",
  "properties": {
    "iso:country":"BE",
    "sg:address":"Sint-niklaasstraat 17",
    "sg:city":"Sint-gillis-waas",
    "sg:orig_category":"Experts-comptables",
    "sg:phone":"+32 3 770 55 63",
    "sg:postcode":"9170",
    "sg:province":"Oost-Vlaanderen",
    "wof:name":"R. Hamelinck",
    "wof:placetype":"venue"
},
  "geometry": {"coordinates":[4.1325302124,51.2135162354],"type":"Point"}
}