{
  "type": "Feature",
  "properties": {
    "addr:full":"Rue Fran\u00c7ois Cloes 38 Saint-nicolas Li\u00e8ge 4420",
    "addr:housenumber":"38",
    "addr:postcode":"4420",
    "addr:street":"Rue Franc\u0327Ois Cloes",
    "iso:country":"BE",
    "sg:address":"Rue Fran\u00c7ois Cloes 38",
    "sg:city":"Saint-nicolas",
    "sg:orig_category":"Artsen and specialisten",
    "sg:phone":"+32 4 263 03 37",
    "sg:postcode":"4420",
    "sg:province":"Li\u00e8ge",
    "wof:name":"Claude Foret",
    "wof:placetype":"venue"
},
  "geometry": {"coordinates":[5.5183348656,50.6377944946],"type":"Point"}
}