{
  "type": "Feature",
  "properties": {
    "iso:country":"BE",
    "sg:address":"Gildenstraat 80",
    "sg:city":"Rotselaar",
    "sg:classifiers":[
        {
            "category":"Building & Trades",
            "subcategory":"Electrical",
            "type":"Services"
        }
    ],
    "sg:phone":"+32 16 58 07 75",
    "sg:postcode":"3110",
    "sg:province":"Vlaams-Brabant",
    "sg:tags":[
        "electric",
        "-",
        "housewiring",
        "contractor"
    ],
    "wof:name":"Jacobs Elektro",
    "wof:placetype":"venue"
},
  "geometry": {"coordinates":[4.7107920647,50.9508590698],"type":"Point"}
}