{
  "type": "Feature",
  "properties": {
    "addr:full":"Ninoofsesteenweg 180 Dilbeek Vlaams-Brabant 1700",
    "addr:housenumber":"180",
    "addr:postcode":"1700",
    "addr:street":"Ninoofsesteenweg",
    "iso:country":"BE",
    "sg:address":"Ninoofsesteenweg 180",
    "sg:city":"Dilbeek",
    "sg:orig_category":"Banken and kredietinstellingen",
    "sg:phone":"+32 2 569 26 77",
    "sg:postcode":"1700",
    "sg:province":"Vlaams-Brabant",
    "wof:name":"Bacob",
    "wof:placetype":"venue"
},
  "geometry": {"coordinates":[4.2723731995,50.8445396423],"type":"Point"}
}