{
  "type": "Feature",
  "properties": {
    "addr:full":"Maalderijstraat 58 Gent Oost-Vlaanderen 9040",
    "addr:housenumber":"58",
    "addr:postcode":"9040",
    "addr:street":"Maalderijstraat;Oost-Vlaanderen",
    "iso:country":"BE",
    "sg:address":"Maalderijstraat 58",
    "sg:city":"Gent",
    "sg:orig_category":"Journaux. Fournitures de bureau. Tabac",
    "sg:phone":"+32 9 228 53 07",
    "sg:postcode":"9040",
    "sg:province":"Oost-Vlaanderen",
    "wof:name":"'t Schrijverke",
    "wof:placetype":"venue"
},
  "geometry": {"coordinates":[3.7730710506,51.0730552673],"type":"Point"}
}