{
  "type": "Feature",
  "properties": {
    "addr:full":"Rechtstraat 10 Riemst Limburg 3770",
    "addr:housenumber":"10",
    "addr:postcode":"3770",
    "addr:street":"Rechtstraat",
    "iso:country":"BE",
    "sg:address":"Rechtstraat 10",
    "sg:city":"Riemst",
    "sg:orig_category":"Ruimtes voor conferenties, recepties and feesten",
    "sg:phone":"+32 12 45 15 68",
    "sg:postcode":"3770",
    "sg:province":"Limburg",
    "wof:name":"De Florentijner",
    "wof:placetype":"venue"
},
  "geometry": {"coordinates":[5.5916042328,50.7867622375],"type":"Point"}
}