{
  "type": "Feature",
  "properties": {
    "iso:country":"BE",
    "sg:address":"Rue Des Chardonnerets 17",
    "sg:city":"Thuin",
    "sg:orig_category":"Woningbouw",
    "sg:phone":"+32 71 51 54 27",
    "sg:postcode":"6534",
    "sg:province":"Hainaut",
    "wof:name":"Alain Cordier",
    "wof:placetype":"venue"
},
  "geometry": {"coordinates":[4.36876297,50.3572463989],"type":"Point"}
}