{
  "type": "Feature",
  "properties": {
    "iso:country":"BE",
    "sg:address":"Rue Des Ecoles 78",
    "sg:city":"Limbourg",
    "sg:orig_category":"M\u00e9decins and sp\u00e9cialistes",
    "sg:phone":"+32 87 76 22 32",
    "sg:postcode":"4830",
    "sg:province":"Li\u00e8ge",
    "wof:name":"Didier Verstringe",
    "wof:placetype":"venue"
},
  "geometry": {"coordinates":[5.9407401085,50.6112518311],"type":"Point"}
}