{
  "type": "Feature",
  "properties": {
    "addr:full":"Broekstraat 5 Meise Vlaams-Brabant 1860",
    "addr:housenumber":"5",
    "addr:postcode":"1860",
    "addr:street":"Broekstraat",
    "iso:country":"BE",
    "sg:address":"Broekstraat 5",
    "sg:city":"Meise",
    "sg:orig_category":"Sportclubs",
    "sg:phone":"+32 2 269 08 63",
    "sg:postcode":"1860",
    "sg:province":"Vlaams-Brabant",
    "wof:name":"Recht Voor Allen",
    "wof:placetype":"venue"
},
  "geometry": {"coordinates":[4.3375301361,50.9636497498],"type":"Point"}
}