{
  "type": "Feature",
  "properties": {
    "iso:country":"BE",
    "sg:address":"Hendrik I Lei 46",
    "sg:city":"Vilvoorde",
    "sg:orig_category":"Kapsalons",
    "sg:phone":"+32 2 251 47 97",
    "sg:postcode":"1800",
    "sg:province":"Vlaams-Brabant",
    "wof:name":"Lily's Hair Force",
    "wof:placetype":"venue"
},
  "geometry": {"coordinates":[4.4291229248,50.9313011169],"type":"Point"}
}