{
  "type": "Feature",
  "properties": {
    "iso:country":"BE",
    "sg:address":"Grand Rue 31",
    "sg:city":"Courcelles (trazegnies)",
    "sg:classifiers":[
        {
            "category":"Manufacturing",
            "subcategory":"Metals",
            "type":"Manufacturing & Wholesale Goods"
        }
    ],
    "sg:phone":"+32 477 20 11 39",
    "sg:postcode":"6183",
    "sg:province":"Hainaut",
    "sg:tags":[
        "ironwork"
    ],
    "wof:name":"Bma Ferca",
    "wof:placetype":"venue"
},
  "geometry": {"coordinates":[4.3350520134,50.4609794617],"type":"Point"}
}