{
  "type": "Feature",
  "properties": {
    "iso:country":"BE",
    "sg:address":"Pittemstraat 32",
    "sg:city":"Meulebeke",
    "sg:classifiers":[
        {
            "category":"Real Estate",
            "subcategory":"Architect",
            "type":"Services"
        }
    ],
    "sg:phone":"+32 51 48 87 55",
    "sg:postcode":"8760",
    "sg:province":"West-Vlaanderen",
    "wof:name":"Vergote F",
    "wof:placetype":"venue"
},
  "geometry": {"coordinates":[3.2873198986,50.9527320862],"type":"Point"}
}