{
  "type": "Feature",
  "properties": {
    "iso:country":"BE",
    "sg:address":"Nederwijk Oost 283",
    "sg:city":"Ninove",
    "sg:classifiers":[
        {
            "category":"Freight",
            "type":"Transportation"
        }
    ],
    "sg:phone":"+32 53 83 66 81",
    "sg:postcode":"9400",
    "sg:province":"Oost-Vlaanderen",
    "sg:tags":[
        "-",
        "transport"
    ],
    "wof:name":"Eurotrans",
    "wof:placetype":"venue"
},
  "geometry": {"coordinates":[4.0476369858,50.8436164856],"type":"Point"}
}