{
  "type": "Feature",
  "properties": {
    "addr:full":"Hoevenzavellaan 29 Genk Limburg 3600",
    "addr:housenumber":"29",
    "addr:postcode":"3600",
    "addr:street":"Hoevenzavellaan",
    "iso:country":"BE",
    "sg:address":"Hoevenzavellaan 29",
    "sg:city":"Genk",
    "sg:orig_category":"Textiles. Eclairage et \u00e9quipements du foyer",
    "sg:phone":"+32 89 38 20 08",
    "sg:postcode":"3600",
    "sg:province":"Limburg",
    "wof:name":"Gordijnenhuis In De Roos",
    "wof:placetype":"venue"
},
  "geometry": {"coordinates":[5.5064601898,50.9998817444],"type":"Point"}
}