{
  "type": "Feature",
  "properties": {
    "addr:full":"Recogne 130 Bastogne Luxembourg 6600",
    "addr:housenumber":"130",
    "addr:postcode":"6600",
    "addr:street":"Recogne",
    "iso:country":"BE",
    "sg:address":"Recogne 130",
    "sg:city":"Bastogne",
    "sg:classifiers":[
        {
            "category":"Home & Garden",
            "subcategory":"Furniture",
            "type":"Retail Goods"
        }
    ],
    "sg:phone":"+32 61 21 52 71",
    "sg:postcode":"6600",
    "sg:province":"Luxembourg",
    "sg:tags":[
        "wood"
    ],
    "wof:name":"Simon Bois Sprl",
    "wof:placetype":"venue"
},
  "geometry": {"coordinates":[5.7148199081,50.0007820129],"type":"Point"}
}