{
  "type": "Feature",
  "properties": {
    "addr:full":"Chauss\u00c9e De Lodelinsart 271 Gilly Hainaut 6060",
    "addr:housenumber":"271",
    "addr:postcode":"6060",
    "addr:street":"Chausse\u0301E De Lodelinsart",
    "iso:country":"BE",
    "sg:address":"Chauss\u00c9e De Lodelinsart 271",
    "sg:city":"Gilly",
    "sg:orig_category":"HERSTELLING ELEKTRISCHE HUISHOUDAPPARATEN Huishoudapparaten, televisies and radio's Microsoft",
    "sg:phone":"+32 71 41 01 88",
    "sg:postcode":"6060",
    "sg:province":"Hainaut",
    "wof:name":"Dinsart",
    "wof:placetype":"venue"
},
  "geometry": {"coordinates":[4.4683098793,50.428768158],"type":"Point"}
}