{
  "type": "Feature",
  "properties": {
    "addr:full":"Oude Stationstraat 108 Tielt West-Vlaanderen 8700",
    "addr:housenumber":"108",
    "addr:postcode":"8700",
    "addr:street":"Oude Stationstraat",
    "iso:country":"BE",
    "sg:address":"Oude Stationstraat 108",
    "sg:city":"Tielt",
    "sg:classifiers":[
        {
            "category":"Personal",
            "subcategory":"Beauty Salon",
            "type":"Services"
        }
    ],
    "sg:phone":"+32 51 40 31 63",
    "sg:postcode":"8700",
    "sg:province":"West-Vlaanderen",
    "sg:tags":[
        "de",
        "coiffure"
    ],
    "wof:name":"Coiffure Kathelijne",
    "wof:placetype":"venue"
},
  "geometry": {"coordinates":[3.3297710419,50.9929046631],"type":"Point"}
}