{
  "type": "Feature",
  "properties": {
    "iso:country":"BE",
    "sg:address":"Baron Ruzettelaan 119",
    "sg:city":"Brugge (assebroek)",
    "sg:classifiers":[
        {
            "category":"Food & Beverages",
            "subcategory":"Liquor & Beverages",
            "type":"Retail Goods"
        }
    ],
    "sg:phone":"+32 50 35 65 01",
    "sg:postcode":"8310",
    "sg:province":"West-Vlaanderen",
    "sg:tags":[
        "-",
        "spirit",
        "wine"
    ],
    "wof:name":"Boutelegier O",
    "wof:placetype":"venue"
},
  "geometry": {"coordinates":[3.2320320606,51.1949462891],"type":"Point"}
}