{
  "type": "Feature",
  "properties": {
    "iso:country":"BE",
    "sg:address":"Molenstraat 8ba",
    "sg:city":"Oosterzele",
    "sg:orig_category":"Instituts de beaut\u00e9",
    "sg:phone":"+32 9 362 05 27",
    "sg:postcode":"9860",
    "sg:province":"Oost-Vlaanderen",
    "wof:name":"Pascale Serreyn",
    "wof:placetype":"venue"
},
  "geometry": {"coordinates":[3.7945039272,50.9220962524],"type":"Point"}
}