{
  "type": "Feature",
  "properties": {
    "iso:country":"BE",
    "sg:address":"Brusselsepoortstraat 20",
    "sg:city":"Mechelen",
    "sg:classifiers":[
        {
            "category":"Shopping",
            "subcategory":"Bicycles & Sporting Goods",
            "type":"Retail Goods"
        }
    ],
    "sg:phone":"+32 15 43 27 49",
    "sg:postcode":"2800",
    "sg:province":"Antwerpen",
    "sg:tags":[
        "-"
    ],
    "wof:name":"Huis Dockx Nv-fietsen Luc Nv",
    "wof:placetype":"venue"
},
  "geometry": {"coordinates":[4.4727602005,51.0215301514],"type":"Point"}
}