{
  "type": "Feature",
  "properties": {
    "addr:full":"Neerlintersesteenweg 118 Kortenaken (hoeleden) Vlaams-Brabant 3471",
    "addr:housenumber":"118",
    "addr:postcode":"3471",
    "addr:street":"Neerlintersesteenweg",
    "iso:country":"BE",
    "sg:address":"Neerlintersesteenweg 118",
    "sg:city":"Kortenaken (hoeleden)",
    "sg:classifiers":[
        {
            "category":"Health Services",
            "subcategory":"Nursing And Care Facility",
            "type":"Services"
        }
    ],
    "sg:phone":"+32 16 77 98 62",
    "sg:postcode":"3471",
    "sg:province":"Vlaams-Brabant",
    "sg:tags":[
        "home"
    ],
    "wof:name":"Theunis-van Uytven Bvba",
    "wof:placetype":"venue"
},
  "geometry": {"coordinates":[4.9989719391,50.8588867188],"type":"Point"}
}