{
  "type": "Feature",
  "properties": {
    "iso:country":"BE",
    "sg:address":"Ch De Charleroi 177",
    "sg:city":"Charleroi",
    "sg:classifiers":[
        {
            "category":"Building & Trades",
            "subcategory":"Construction",
            "type":"Services"
        }
    ],
    "sg:phone":"+32 71 30 42 22",
    "sg:postcode":"6060",
    "sg:province":"Hainaut",
    "sg:tags":[
        "work",
        "public"
    ],
    "wof:name":"Travaux Industriels Wallons Sa",
    "wof:placetype":"venue"
},
  "geometry": {"coordinates":[4.4695901871,50.4024467468],"type":"Point"}
}