{
  "type": "Feature",
  "properties": {
    "addr:full":"Pastorijstraat 48 Sint-niklaas Oost-Vlaanderen 9100",
    "addr:housenumber":"48",
    "addr:postcode":"9100",
    "addr:street":"Pastorijstraat",
    "iso:country":"BE",
    "sg:address":"Pastorijstraat 48",
    "sg:city":"Sint-niklaas",
    "sg:classifiers":[
        {
            "category":"Government",
            "subcategory":"Police Station",
            "type":"Public Place"
        }
    ],
    "sg:phone":"+32 3 776 05 18",
    "sg:postcode":"9100",
    "sg:province":"Oost-Vlaanderen",
    "sg:tags":[
        "gendarmerie"
    ],
    "wof:name":"Federale Politie",
    "wof:placetype":"venue"
},
  "geometry": {"coordinates":[4.1760120392,51.1932373047],"type":"Point"}
}