{
  "type": "Feature",
  "properties": {
    "addr:full":"Rue Des Emailleries 30 Charleroi (gosselies) Hainaut 6041",
    "addr:housenumber":"30",
    "addr:postcode":"6041",
    "addr:street":"Rue Des Emailleries",
    "iso:country":"BE",
    "sg:address":"Rue Des Emailleries 30",
    "sg:city":"Charleroi (gosselies)",
    "sg:classifiers":[
        {
            "category":"Autos & Motor Vehicles",
            "subcategory":"Fuel & Gas Station",
            "type":"Retail Goods"
        }
    ],
    "sg:phone":"+32 71 34 48 58",
    "sg:postcode":"6041",
    "sg:province":"Hainaut",
    "wof:name":"Magic Center",
    "wof:placetype":"venue"
},
  "geometry": {"coordinates":[4.4314317703,50.4685935974],"type":"Point"}
}