{
  "type": "Feature",
  "properties": {
    "addr:full":"Haardstedestraat 51 Gent Oost-Vlaanderen 9000",
    "addr:housenumber":"51",
    "addr:postcode":"9000",
    "addr:street":"Haardstedestraat;Oost-Vlaanderen",
    "iso:country":"BE",
    "sg:address":"Haardstedestraat 51",
    "sg:city":"Gent",
    "sg:classifiers":[
        {
            "category":"Food & Beverages",
            "subcategory":"Meat & Fish",
            "type":"Retail Goods"
        }
    ],
    "sg:phone":"+32 9 222 43 68",
    "sg:postcode":"9000",
    "sg:province":"Oost-Vlaanderen",
    "sg:tags":[
        "poultry",
        "whol",
        "game",
        "-"
    ],
    "wof:name":"Bloem Freddy's Kip Aan 't Spit",
    "wof:placetype":"venue"
},
  "geometry": {"coordinates":[3.7223498821,51.0192489624],"type":"Point"}
}