{
  "type": "Feature",
  "properties": {
    "addr:full":"Zoni\u00cbnwoudlaan 5 Beersel Vlaams-Brabant 1652",
    "addr:housenumber":"5",
    "addr:postcode":"1652",
    "addr:street":"Zonie\u0308Nwoudlaan",
    "iso:country":"BE",
    "sg:address":"Zoni\u00cbnwoudlaan 5",
    "sg:city":"Beersel",
    "sg:orig_category":"M\u00e9decins and sp\u00e9cialistes",
    "sg:phone":"+32 2 380 26 22",
    "sg:postcode":"1652",
    "sg:province":"Vlaams-Brabant",
    "wof:name":"H. Lannoy",
    "wof:placetype":"venue"
},
  "geometry": {"coordinates":[4.3388609886,50.7407112122],"type":"Point"}
}