{
  "type": "Feature",
  "properties": {
    "addr:full":"Rue De Bruxelles 130 Namur Namur 5000",
    "addr:housenumber":"130",
    "addr:postcode":"5000",
    "addr:street":"Rue De Bruxelles",
    "iso:country":"BE",
    "sg:address":"Rue De Bruxelles 130",
    "sg:city":"Namur",
    "sg:classifiers":[
        {
            "category":"Bars & Pubs",
            "type":"Food & Drink"
        }
    ],
    "sg:phone":"+32 81 26 37 26",
    "sg:postcode":"5000",
    "sg:province":"Namur",
    "sg:tags":[
        "tavern"
    ],
    "wof:name":"Sorbonne (la)",
    "wof:placetype":"venue"
},
  "geometry": {"coordinates":[4.8585991859,50.4675750732],"type":"Point"}
}