{
  "type": "Feature",
  "properties": {
    "addr:full":"Avenue De L'horizon 42 Bruxelles (woluwe-saint-pierre) Bruxelles-Capitale 1150",
    "addr:housenumber":"42",
    "addr:postcode":"1150",
    "addr:street":"Avenue De L'Horizon",
    "iso:country":"BE",
    "sg:address":"Avenue De L'horizon 42",
    "sg:city":"Bruxelles (woluwe-saint-pierre)",
    "sg:classifiers":[
        {
            "category":"Transit Center",
            "subcategory":"Freight",
            "type":"Transportation"
        }
    ],
    "sg:phone":"+32 2 770 33 04",
    "sg:postcode":"1150",
    "sg:province":"Bruxelles-Capitale",
    "sg:tags":[
        "import",
        "export",
        "-"
    ],
    "wof:name":"Sineuro Sa",
    "wof:placetype":"venue"
},
  "geometry": {"coordinates":[4.4154109955,50.8324928284],"type":"Point"}
}