{
  "type": "Feature",
  "properties": {
    "addr:full":"Knodbaan 18g Ranst (oelegem) Antwerpen 2520",
    "addr:housenumber":"18g",
    "addr:postcode":"2520",
    "addr:street":"Knodbaan",
    "iso:country":"BE",
    "sg:address":"Knodbaan 18g",
    "sg:city":"Ranst (oelegem)",
    "sg:classifiers":[
        {
            "category":"Shopping",
            "subcategory":"Party Supplies",
            "type":"Retail Goods"
        }
    ],
    "sg:phone":"+32 3 384 25 42",
    "sg:postcode":"2520",
    "sg:province":"Antwerpen",
    "sg:tags":[
        "rental",
        "-"
    ],
    "wof:name":"Lafaille",
    "wof:placetype":"venue"
},
  "geometry": {"coordinates":[4.594189167,51.2176132202],"type":"Point"}
}