{
  "type": "Feature",
  "properties": {
    "addr:full":"Avenue Des Martyrs 253 Fleron Li\u00e8ge 4620",
    "addr:housenumber":"253",
    "addr:postcode":"4620",
    "addr:street":"Avenue Des Martyrs",
    "iso:country":"BE",
    "sg:address":"Avenue Des Martyrs 253",
    "sg:city":"Fleron",
    "sg:orig_category":"V\u00eatements pour b\u00e9b\u00e9s and enfants. Articles pour b\u00e9b\u00e9s. V\u00eatements pour Dames",
    "sg:phone":"+32 4 358 24 48",
    "sg:postcode":"4620",
    "sg:province":"Li\u00e8ge",
    "wof:name":"Pr\u00c9maman",
    "wof:placetype":"venue"
},
  "geometry": {"coordinates":[5.6839442253,50.6148414612],"type":"Point"}
}