{
  "type": "Feature",
  "properties": {
    "iso:country":"BE",
    "sg:address":"Overheet 42",
    "sg:city":"Berlare",
    "sg:classifiers":[
        {
            "category":"Building & Trades",
            "subcategory":"Cleaning & Sanitation",
            "type":"Services"
        }
    ],
    "sg:phone":"+32 52 42 56 56",
    "sg:postcode":"9290",
    "sg:province":"Oost-Vlaanderen",
    "sg:tags":[
        "fa\u00e7ade",
        "maintenance"
    ],
    "wof:name":"Melis P",
    "wof:placetype":"venue"
},
  "geometry": {"coordinates":[4.0187659264,51.0148124695],"type":"Point"}
}