{
  "type": "Feature",
  "properties": {
    "addr:full":"Speelstraat 57 Zingem Oost-Vlaanderen 9750",
    "addr:housenumber":"57",
    "addr:postcode":"9750",
    "addr:street":"Speelstraat",
    "iso:country":"BE",
    "sg:address":"Speelstraat 57",
    "sg:city":"Zingem",
    "sg:orig_category":"Eleveurs de bovins",
    "sg:phone":"+32 9 384 18 94",
    "sg:postcode":"9750",
    "sg:province":"Oost-Vlaanderen",
    "wof:name":"Andre Van Den Bulcke",
    "wof:placetype":"venue"
},
  "geometry": {"coordinates":[3.6594789028,50.8943405151],"type":"Point"}
}