{
  "type": "Feature",
  "properties": {
    "iso:country":"BE",
    "sg:address":"Sentier Des Oies 5",
    "sg:city":"Waremme",
    "sg:orig_category":"Installation \u00e9lectrique r\u00e9sidentielle",
    "sg:phone":"+32 19 32 49 54",
    "sg:postcode":"4300",
    "sg:province":"Li\u00e8ge",
    "wof:name":"Armand Jammes",
    "wof:placetype":"venue"
},
  "geometry": {"coordinates":[5.2637901306,50.704875946],"type":"Point"}
}