{
  "type": "Feature",
  "properties": {
    "addr:full":"Rue Saint-jean En Isle 3 Liege Li\u00e8ge 4000",
    "addr:housenumber":"3",
    "addr:postcode":"4000",
    "addr:street":"Rue Saint-Jean En Isle",
    "iso:country":"BE",
    "sg:address":"Rue Saint-jean En Isle 3",
    "sg:city":"Liege",
    "sg:classifiers":[
        {
            "category":"Restaurant",
            "type":"Food & Drink"
        }
    ],
    "sg:phone":"+32 4 222 18 54",
    "sg:postcode":"4000",
    "sg:province":"Li\u00e8ge",
    "wof:name":"Il Etait Une Fois",
    "wof:placetype":"venue"
},
  "geometry": {"coordinates":[5.5687208176,50.6422805786],"type":"Point"}
}