{
  "type": "Feature",
  "properties": {
    "iso:country":"BE",
    "sg:address":"Schutterijstraat 15",
    "sg:city":"Neerpelt",
    "sg:classifiers":[
        {
            "category":"Taxi",
            "type":"Transportation"
        }
    ],
    "sg:phone":"+32 11 64 06 55",
    "sg:postcode":"3910",
    "sg:province":"Limburg",
    "wof:name":"Taxi Neerpelt",
    "wof:placetype":"venue"
},
  "geometry": {"coordinates":[5.4771881104,51.2169342041],"type":"Point"}
}