{
  "type": "Feature",
  "properties": {
    "iso:country":"BE",
    "sg:address":"Rue Edouard Colson 312",
    "sg:city":"Ans",
    "sg:orig_category":"Installation \u00e9lectrique r\u00e9sidentielle. Installation \u00e9lectrique industrielle. Mat\u00e9riel de contr\u00f4le de",
    "sg:phone":"+32 4 263 76 21",
    "sg:postcode":"4431",
    "sg:province":"Li\u00e8ge",
    "wof:name":"Hollenfeltz & Fils",
    "wof:placetype":"venue"
},
  "geometry": {"coordinates":[5.4908981323,50.6720314026],"type":"Point"}
}