{
  "type": "Feature",
  "properties": {
    "addr:full":"Schoterweg 322 Tessenderlo Limburg 3980",
    "addr:housenumber":"322",
    "addr:postcode":"3980",
    "addr:street":"Schoterweg",
    "iso:country":"BE",
    "sg:address":"Schoterweg 322",
    "sg:city":"Tessenderlo",
    "sg:orig_category":"Boomkwekerijen",
    "sg:phone":"+32 13 66 46 93",
    "sg:postcode":"3980",
    "sg:province":"Limburg",
    "wof:name":"Michel Poot",
    "wof:placetype":"venue"
},
  "geometry": {"coordinates":[5.0332150459,51.0668296814],"type":"Point"}
}