{
  "type": "Feature",
  "properties": {
    "addr:full":"Blekerijstraat 7 Dilbeek Vlaams-Brabant 1700",
    "addr:housenumber":"7",
    "addr:postcode":"1700",
    "addr:street":"Blekerijstraat",
    "iso:country":"BE",
    "sg:address":"Blekerijstraat 7",
    "sg:city":"Dilbeek",
    "sg:orig_category":"Slagers",
    "sg:phone":"+32 2 520 18 93",
    "sg:postcode":"1700",
    "sg:province":"Vlaams-Brabant",
    "wof:name":"De Vidts A",
    "wof:placetype":"venue"
},
  "geometry": {"coordinates":[4.2243518829,50.8485870361],"type":"Point"}
}