{
  "type": "Feature",
  "properties": {
    "iso:country":"BE",
    "sg:address":"Romershovenstraat 70",
    "sg:city":"Hoeselt",
    "sg:orig_category":"Maisons de vacances",
    "sg:phone":"+32 89 51 42 42",
    "sg:postcode":"3730",
    "sg:province":"Limburg",
    "wof:name":"Blokkesberg",
    "wof:placetype":"venue"
},
  "geometry": {"coordinates":[5.4595217705,50.8593978882],"type":"Point"}
}