{
  "type": "Feature",
  "properties": {
    "addr:full":"Rue Des Navets 26 Brussel/bruxelles Bruxelles-Capitale 1000",
    "addr:housenumber":"26",
    "addr:postcode":"1000",
    "addr:street":"Rue Des Navets;/",
    "iso:country":"BE",
    "sg:address":"Rue Des Navets 26",
    "sg:city":"Brussel/bruxelles",
    "sg:orig_category":"M\u00e9decins and sp\u00e9cialistes",
    "sg:phone":"+32 2 502 07 68",
    "sg:postcode":"1000",
    "sg:province":"Bruxelles-Capitale",
    "wof:name":"P. Geller",
    "wof:placetype":"venue"
},
  "geometry": {"coordinates":[4.3443198204,50.8456382751],"type":"Point"}
}