{
  "type": "Feature",
  "properties": {
    "iso:country":"BE",
    "sg:address":"Brabantstraat 212",
    "sg:city":"Schaarbeek/schaerbeek",
    "sg:orig_category":"Textiel",
    "sg:phone":"+32 2 219 38 23",
    "sg:postcode":"1030",
    "sg:province":"Bruxelles-Capitale",
    "wof:name":"Douniatex",
    "wof:placetype":"venue"
},
  "geometry": {"coordinates":[4.3648781776,50.8618507385],"type":"Point"}
}