{
  "type": "Feature",
  "properties": {
    "iso:country":"BE",
    "sg:address":"Gentsesteenweg 1337b3",
    "sg:city":"Sint-agatha-berchem/berchem-sainte-agathe",
    "sg:orig_category":"Boekhouders",
    "sg:phone":"+32 2 465 76 74",
    "sg:postcode":"1082",
    "sg:province":"Bruxelles-Capitale",
    "wof:name":"Marc Van Thournout",
    "wof:placetype":"venue"
},
  "geometry": {"coordinates":[4.2916479111,50.8702812195],"type":"Point"}
}