{
  "type": "Feature",
  "properties": {
    "addr:full":"Overstraat 4 Diest Vlaams-Brabant 3290",
    "addr:housenumber":"4",
    "addr:postcode":"3290",
    "addr:street":"Overstraat",
    "iso:country":"BE",
    "sg:address":"Overstraat 4",
    "sg:city":"Diest",
    "sg:classifiers":[
        {
            "category":"Insurance",
            "subcategory":"Life Insurance",
            "type":"Services"
        }
    ],
    "sg:phone":"+32 13 33 61 52",
    "sg:postcode":"3290",
    "sg:province":"Vlaams-Brabant",
    "sg:tags":[
        "assurance"
    ],
    "wof:name":"Didden Berna-plackl\u00c9 Ren\u00c9",
    "wof:placetype":"venue"
},
  "geometry": {"coordinates":[5.0540800095,50.9857597351],"type":"Point"}
}