{
  "type": "Feature",
  "properties": {
    "iso:country":"BE",
    "sg:address":"Herbiester 23",
    "sg:city":"Jalhay",
    "sg:orig_category":"Herstellingen and onderhoud van auto's",
    "sg:phone":"+32 87 64 71 10",
    "sg:postcode":"4845",
    "sg:province":"Li\u00e8ge",
    "wof:name":"Car-wash Thys",
    "wof:placetype":"venue"
},
  "geometry": {"coordinates":[5.9853610992,50.5632362366],"type":"Point"}
}