{
  "type": "Feature",
  "properties": {
    "iso:country":"BE",
    "sg:address":"Tempelstraat 31",
    "sg:city":"Ieper",
    "sg:classifiers":[
        {
            "category":"Personal",
            "subcategory":"Beauty Salon",
            "type":"Services"
        }
    ],
    "sg:phone":"+32 57 20 35 14",
    "sg:postcode":"8900",
    "sg:province":"West-Vlaanderen",
    "wof:name":"Delfosse-dewaele",
    "wof:placetype":"venue"
},
  "geometry": {"coordinates":[2.881978035,50.8491592407],"type":"Point"}
}