{
  "type": "Feature",
  "properties": {
    "iso:country":"BE",
    "sg:address":"Rue En Bois 11",
    "sg:city":"Gr\u00e2ce-hollogne (bierset)",
    "sg:classifiers":[
        {
            "category":"Professional",
            "subcategory":"Art Services",
            "type":"Services"
        }
    ],
    "sg:phone":"+32 4 250 21 75",
    "sg:postcode":"4460",
    "sg:province":"Li\u00e8ge",
    "sg:tags":[
        "-",
        "painter",
        "artist"
    ],
    "wof:name":"Barzin J",
    "wof:placetype":"venue"
},
  "geometry": {"coordinates":[5.4548840523,50.655582428],"type":"Point"}
}