{
  "type": "Feature",
  "properties": {
    "addr:full":"Kriesberg 59-61 Holsbeek (nieuwrode) Vlaams-Brabant 3221",
    "addr:housenumber":"59-61",
    "addr:postcode":"3221",
    "addr:street":"Kriesberg",
    "iso:country":"BE",
    "sg:address":"Kriesberg 59-61",
    "sg:city":"Holsbeek (nieuwrode)",
    "sg:classifiers":[
        {
            "category":"Organizations",
            "subcategory":"Community Association",
            "type":"Services"
        }
    ],
    "sg:phone":"+32 16 63 10 82",
    "sg:postcode":"3221",
    "sg:province":"Vlaams-Brabant",
    "sg:tags":[
        "cultural"
    ],
    "wof:name":"Moeder Aarde Vzw",
    "wof:placetype":"venue"
},
  "geometry": {"coordinates":[4.8590698242,50.9490318298],"type":"Point"}
}