{
  "type": "Feature",
  "properties": {
    "addr:full":"Mechelsesteenweg 46 Kontich Antwerpen 2550",
    "addr:housenumber":"46",
    "addr:postcode":"2550",
    "addr:street":"Mechelsesteenweg",
    "iso:country":"BE",
    "sg:address":"Mechelsesteenweg 46",
    "sg:city":"Kontich",
    "sg:classifiers":[
        {
            "category":"Shopping",
            "subcategory":"Shoes",
            "type":"Retail Goods"
        }
    ],
    "sg:phone":"+32 3 458 12 17",
    "sg:postcode":"2550",
    "sg:province":"Antwerpen",
    "sg:tags":[
        "slipper",
        "-"
    ],
    "wof:name":"Ara-schoenen Moens",
    "wof:placetype":"venue"
},
  "geometry": {"coordinates":[4.4455771446,51.1332702637],"type":"Point"}
}