{
  "type": "Feature",
  "properties": {
    "addr:full":"Oostnieuwkerksesteenweg 136a Roeselare West-Vlaanderen 8800",
    "addr:housenumber":"136a",
    "addr:postcode":"8800",
    "addr:street":"Oostnieuwkerksesteenweg",
    "iso:country":"BE",
    "sg:address":"Oostnieuwkerksesteenweg 136a",
    "sg:city":"Roeselare",
    "sg:classifiers":[
        {
            "category":"Retail",
            "subcategory":"Auto Repair",
            "type":"Services"
        }
    ],
    "sg:phone":"+32 51 25 12 02",
    "sg:postcode":"8800",
    "sg:province":"West-Vlaanderen",
    "sg:tags":[
        "garage"
    ],
    "wof:name":"A.a.s. Nv",
    "wof:placetype":"venue"
},
  "geometry": {"coordinates":[3.0978310108,50.9463806152],"type":"Point"}
}