{
  "type": "Feature",
  "properties": {
    "addr:full":"Grote Markt 3 Aalst Oost-Vlaanderen 9300",
    "addr:housenumber":"3",
    "addr:postcode":"9300",
    "addr:street":"Grote Markt",
    "iso:country":"BE",
    "sg:address":"Grote Markt 3",
    "sg:city":"Aalst",
    "sg:classifiers":[
        {
            "category":"Health Services",
            "subcategory":"Nursing And Care Facility",
            "type":"Services"
        }
    ],
    "sg:phone":"+32 53 73 21 11",
    "sg:postcode":"9300",
    "sg:province":"Oost-Vlaanderen",
    "sg:tags":[
        "public"
    ],
    "wof:name":"Stadsbestuur",
    "wof:placetype":"venue"
},
  "geometry": {"coordinates":[4.0381097794,50.9384269714],"type":"Point"}
}