{
  "type": "Feature",
  "properties": {
    "addr:full":"Dr.a. Goffinstraat 38 Landen Vlaams-Brabant 3401",
    "addr:housenumber":"38",
    "addr:postcode":"3401",
    "addr:street":"Goffinstraat",
    "iso:country":"BE",
    "sg:address":"Dr.a. Goffinstraat 38",
    "sg:city":"Landen",
    "sg:orig_category":"Artsen and specialisten",
    "sg:phone":"+32 11 88 11 06",
    "sg:postcode":"3401",
    "sg:province":"Vlaams-Brabant",
    "wof:name":"Hubert Goffin",
    "wof:placetype":"venue"
},
  "geometry": {"coordinates":[5.061686039,50.7322540283],"type":"Point"}
}