{
  "type": "Feature",
  "properties": {
    "addr:full":"Avenue Des Courtils 6 Oupeye (haccourt) Li\u00e8ge 4684",
    "addr:housenumber":"6",
    "addr:postcode":"4684",
    "addr:street":"Avenue Des Courtils",
    "iso:country":"BE",
    "sg:address":"Avenue Des Courtils 6",
    "sg:city":"Oupeye (haccourt)",
    "sg:classifiers":[
        {
            "category":"Retail",
            "subcategory":"Event Space",
            "type":"Services"
        }
    ],
    "sg:phone":"+32 4 374 22 83",
    "sg:postcode":"4684",
    "sg:province":"Li\u00e8ge",
    "sg:tags":[
        "rental",
        "-",
        "hall"
    ],
    "wof:name":"Postillon Organisation (le)",
    "wof:placetype":"venue"
},
  "geometry": {"coordinates":[5.6686229706,50.7294845581],"type":"Point"}
}