{
  "type": "Feature",
  "properties": {
    "iso:country":"BE",
    "sg:address":"Korte Begijnenstraat 22",
    "sg:city":"Turnhout",
    "sg:orig_category":"Pharmaciens",
    "sg:phone":"+32 14 43 62 45",
    "sg:postcode":"2300",
    "sg:province":"Antwerpen",
    "wof:name":"De Volksmacht",
    "wof:placetype":"venue"
},
  "geometry": {"coordinates":[4.9475660324,51.326423645],"type":"Point"}
}