{
  "type": "Feature",
  "properties": {
    "iso:country":"BE",
    "sg:address":"Genkerbaan 115",
    "sg:city":"Zonhoven",
    "sg:classifiers":[
        {
            "category":"Health Services",
            "subcategory":"Health Practitioner",
            "type":"Services"
        }
    ],
    "sg:phone":"+32 11 81 78 12",
    "sg:postcode":"3520",
    "sg:province":"Limburg",
    "sg:tags":[
        "osteopath"
    ],
    "wof:name":"Beckers Sofie D.o.-m.r.o.b.",
    "wof:placetype":"venue"
},
  "geometry": {"coordinates":[5.3826098442,50.9915046692],"type":"Point"}
}