{
  "type": "Feature",
  "properties": {
    "addr:full":"Brusselmanstraat 107 Buggenhout Oost-Vlaanderen 9255",
    "addr:housenumber":"107",
    "addr:postcode":"9255",
    "addr:street":"Brusselmanstraat",
    "iso:country":"BE",
    "sg:address":"Brusselmanstraat 107",
    "sg:city":"Buggenhout",
    "sg:orig_category":"HUISBRANDOLIE",
    "sg:phone":"+32 52 33 66 59",
    "sg:postcode":"9255",
    "sg:province":"Oost-Vlaanderen",
    "wof:name":"Van Den Bossche",
    "wof:placetype":"venue"
},
  "geometry": {"coordinates":[4.2215299606,51.0150184631],"type":"Point"}
}