{
  "type": "Feature",
  "properties": {
    "addr:full":"Chemin Vert 111 Tournai Hainaut 7500",
    "addr:housenumber":"111",
    "addr:postcode":"7500",
    "addr:street":"Chemin Vert",
    "iso:country":"BE",
    "sg:address":"Chemin Vert 111",
    "sg:city":"Tournai",
    "sg:orig_category":"Dierenartsen",
    "sg:phone":"+32 69 21 42 14",
    "sg:postcode":"7500",
    "sg:province":"Hainaut",
    "wof:name":"Pierre Guevar",
    "wof:placetype":"venue"
},
  "geometry": {"coordinates":[3.3605380058,50.6023750305],"type":"Point"}
}