{
  "type": "Feature",
  "properties": {
    "iso:country":"BE",
    "sg:address":"Auguste Lambiottestraat 37",
    "sg:city":"Schaarbeek/schaerbeek",
    "sg:orig_category":"Diverse metaalwaren Fab Schilders",
    "sg:phone":"+32 2 215 68 61",
    "sg:postcode":"1030",
    "sg:province":"Bruxelles-Capitale",
    "wof:name":"Ahmed Begdouri Achkari",
    "wof:placetype":"venue"
},
  "geometry": {"coordinates":[4.3879947662,50.8569374084],"type":"Point"}
}