{
  "type": "Feature",
  "properties": {
    "addr:full":"Molenberg 2 Geel Antwerpen 2440",
    "addr:housenumber":"2",
    "addr:postcode":"2440",
    "addr:street":"Molenberg",
    "iso:country":"BE",
    "sg:address":"Molenberg 2",
    "sg:city":"Geel",
    "sg:orig_category":"Production and transformation de viande",
    "sg:phone":"+32 14 58 50 81",
    "sg:postcode":"2440",
    "sg:province":"Antwerpen",
    "wof:name":"Staf Lornoy & Zonen",
    "wof:placetype":"venue"
},
  "geometry": {"coordinates":[4.9976940155,51.163433075],"type":"Point"}
}