{
  "type": "Feature",
  "properties": {
    "iso:country":"BE",
    "sg:address":"Rue De Liberchies 112",
    "sg:city":"Pont-a-celles",
    "sg:orig_category":"Meubles D\u00e9taillants, Am\u00e9nagement de B\u00e2timents et de Cuisines. Traitement and fa\u00e7onnage de la pierre.",
    "sg:phone":"+32 71 84 43 40",
    "sg:postcode":"6238",
    "sg:province":"Hainaut",
    "wof:name":"Fun\u00c9railles Denuit J.l.",
    "wof:placetype":"venue"
},
  "geometry": {"coordinates":[4.4056339264,50.513710022],"type":"Point"}
}