{
  "type": "Feature",
  "properties": {
    "addr:full":"Rue Daussoigne-m\u00c9hul 2 Li\u00c8ge Li\u00e8ge 4000",
    "addr:housenumber":"2",
    "addr:postcode":"4000",
    "addr:street":"Rue Daussoigne-Me\u0301Hul",
    "iso:country":"BE",
    "sg:address":"Rue Daussoigne-m\u00c9hul 2",
    "sg:city":"Li\u00c8ge",
    "sg:orig_category":"Cabinets d\u00b4huissiers",
    "sg:phone":"+32 4 226 54 95",
    "sg:postcode":"4000",
    "sg:province":"Li\u00e8ge",
    "wof:name":"Jean Bovy",
    "wof:placetype":"venue"
},
  "geometry": {"coordinates":[5.565612793,50.6540184021],"type":"Point"}
}