{
  "type": "Feature",
  "properties": {
    "iso:country":"BE",
    "sg:address":"Rozenhoedkaai 3",
    "sg:city":"Brugge",
    "sg:classifiers":[
        {
            "category":"Shopping",
            "subcategory":"Antiques",
            "type":"Retail Goods"
        }
    ],
    "sg:phone":"+32 50 34 56 61",
    "sg:postcode":"8000",
    "sg:province":"West-Vlaanderen",
    "wof:name":"Antique Studio",
    "wof:placetype":"venue"
},
  "geometry": {"coordinates":[3.2275519371,51.2069816589],"type":"Point"}
}