{
  "type": "Feature",
  "properties": {
    "addr:full":"Noordhinderstraat 18 Brugge West-Vlaanderen 8380",
    "addr:housenumber":"18",
    "addr:postcode":"8380",
    "addr:street":"Noordhinderstraat",
    "iso:country":"BE",
    "sg:address":"Noordhinderstraat 18",
    "sg:city":"Brugge",
    "sg:orig_category":"Poissonniers and \u00e9caillers",
    "sg:phone":"+32 50 54 57 81",
    "sg:postcode":"8380",
    "sg:province":"West-Vlaanderen",
    "wof:name":"Huis Stemifish",
    "wof:placetype":"venue"
},
  "geometry": {"coordinates":[3.2288448811,51.2742958069],"type":"Point"}
}