{
  "type": "Feature",
  "properties": {
    "addr:full":"Reukenwegel 12 Destelbergen (heusden) Oost-Vlaanderen 9070",
    "addr:housenumber":"12",
    "addr:postcode":"9070",
    "addr:street":"Reukenwegel",
    "iso:country":"BE",
    "sg:address":"Reukenwegel 12",
    "sg:city":"Destelbergen (heusden)",
    "sg:classifiers":[
        {
            "category":"Building & Trades",
            "subcategory":"Construction",
            "type":"Services"
        }
    ],
    "sg:phone":"+32 9 232 51 59",
    "sg:postcode":"9070",
    "sg:province":"Oost-Vlaanderen",
    "sg:tags":[
        "stucco",
        "contractor"
    ],
    "wof:name":"Hebbelinck",
    "wof:placetype":"venue"
},
  "geometry": {"coordinates":[3.812967062,51.0387268066],"type":"Point"}
}