{
  "type": "Feature",
  "properties": {
    "addr:full":"Izegemstraat 96 Roeselare West-Vlaanderen 8800",
    "addr:housenumber":"96",
    "addr:postcode":"8800",
    "addr:street":"Izegemstraat",
    "iso:country":"BE",
    "sg:address":"Izegemstraat 96",
    "sg:city":"Roeselare",
    "sg:orig_category":"R\u00e9cup\u00e9ration de mati\u00e8res m\u00e9talliques recyclables and d\u00e9molisseurs de voitures. V\u00e9hicules automobiles",
    "sg:phone":"+32 51 20 34 09",
    "sg:postcode":"8800",
    "sg:province":"West-Vlaanderen",
    "wof:name":"Garage Van Steenkiste",
    "wof:placetype":"venue"
},
  "geometry": {"coordinates":[3.1662909985,50.9309616089],"type":"Point"}
}