{
  "type": "Feature",
  "properties": {
    "addr:full":"Kapelstraat 96 Temse (steendorp) Oost-Vlaanderen 9140",
    "addr:housenumber":"96",
    "addr:postcode":"9140",
    "addr:street":"Kapelstraat",
    "iso:country":"BE",
    "sg:address":"Kapelstraat 96",
    "sg:city":"Temse (steendorp)",
    "sg:classifiers":[
        {
            "category":"Personal",
            "subcategory":"Barber",
            "type":"Services"
        }
    ],
    "sg:phone":"+32 3 774 22 71",
    "sg:postcode":"9140",
    "sg:province":"Oost-Vlaanderen",
    "sg:tags":[
        "gentleman",
        "salon",
        "-",
        "hairdressing"
    ],
    "wof:name":"Rudy",
    "wof:placetype":"venue"
},
  "geometry": {"coordinates":[4.2477002144,51.1289482117],"type":"Point"}
}