{
  "type": "Feature",
  "properties": {
    "iso:country":"BE",
    "sg:address":"Rue De L'arr\u00eat 14a",
    "sg:city":"Fexhe-le-haut-clocher",
    "sg:classifiers":[
        {
            "category":"Wholesale",
            "subcategory":"Meat",
            "type":"Manufacturing & Wholesale Goods"
        }
    ],
    "sg:phone":"+32 4 250 56 52",
    "sg:postcode":"4347",
    "sg:province":"Li\u00e8ge",
    "sg:tags":[
        "whol",
        "-"
    ],
    "wof:name":"I.d. Lunch Sprl",
    "wof:placetype":"venue"
},
  "geometry": {"coordinates":[5.4298648834,50.6576957703],"type":"Point"}
}