{
  "type": "Feature",
  "properties": {
    "addr:full":"Kwadestraat 271 Roeselare West-Vlaanderen 8800",
    "addr:housenumber":"271",
    "addr:postcode":"8800",
    "addr:street":"Kwadestraat",
    "iso:country":"BE",
    "sg:address":"Kwadestraat 271",
    "sg:city":"Roeselare",
    "sg:orig_category":"Eleveurs and marchands de porcs",
    "sg:phone":"+32 51 24 41 52",
    "sg:postcode":"8800",
    "sg:province":"West-Vlaanderen",
    "wof:name":"Dirk Bottelier",
    "wof:placetype":"venue"
},
  "geometry": {"coordinates":[3.1741800308,50.9050712585],"type":"Point"}
}