{
  "type": "Feature",
  "properties": {
    "addr:full":"O.-l.-vrouwestraat 4 Kortrijk West-Vlaanderen 8500",
    "addr:housenumber":"4",
    "addr:postcode":"8500",
    "addr:street":"O.-L.-Vrouwestraat",
    "iso:country":"BE",
    "sg:address":"O.-l.-vrouwestraat 4",
    "sg:city":"Kortrijk",
    "sg:orig_category":"Centres de relaxation and bien-\u00eatre. Instituts de beaut\u00e9",
    "sg:phone":"+32 56 21 88 21",
    "sg:postcode":"8500",
    "sg:province":"West-Vlaanderen",
    "wof:name":"Sunset Boulevard",
    "wof:placetype":"venue"
},
  "geometry": {"coordinates":[3.2650549412,50.827999115],"type":"Point"}
}