{
  "type": "Feature",
  "properties": {
    "addr:full":"Rue De La Lib\u00c9ration 9 Chapelle-lez-herlaimont Hainaut 7160",
    "addr:housenumber":"9",
    "addr:postcode":"7160",
    "addr:street":"Rue De La Libe\u0301Ration",
    "iso:country":"BE",
    "sg:address":"Rue De La Lib\u00c9ration 9",
    "sg:city":"Chapelle-lez-herlaimont",
    "sg:orig_category":"Boekhouders",
    "sg:phone":"+32 64 44 76 24",
    "sg:postcode":"7160",
    "sg:province":"Hainaut",
    "wof:name":"Guy Clignet",
    "wof:placetype":"venue"
},
  "geometry": {"coordinates":[4.2855839729,50.4889068604],"type":"Point"}
}