{
  "type": "Feature",
  "properties": {
    "addr:full":"Hezerheiweg 36 Diest Vlaams-Brabant 3290",
    "addr:housenumber":"36",
    "addr:postcode":"3290",
    "addr:street":"Hezerheiweg",
    "iso:country":"BE",
    "sg:address":"Hezerheiweg 36",
    "sg:city":"Diest",
    "sg:classifiers":[
        {
            "category":"Arena",
            "subcategory":"Sports Club",
            "type":"Entertainment"
        }
    ],
    "sg:phone":"+32 13 33 48 50",
    "sg:postcode":"3290",
    "sg:province":"Vlaams-Brabant",
    "sg:tags":[
        "de"
    ],
    "wof:name":"Wc Hezertrappers Schaffen Diest",
    "wof:placetype":"venue"
},
  "geometry": {"coordinates":[5.0938491821,50.9898681641],"type":"Point"}
}