{
  "type": "Feature",
  "properties": {
    "addr:full":"Kruisstraat 39 Zomergem Oost-Vlaanderen 9930",
    "addr:housenumber":"39",
    "addr:postcode":"9930",
    "addr:street":"Kruisstraat",
    "iso:country":"BE",
    "sg:address":"Kruisstraat 39",
    "sg:city":"Zomergem",
    "sg:orig_category":"Tuinen",
    "sg:phone":"+32 9 372 71 15",
    "sg:postcode":"9930",
    "sg:province":"Oost-Vlaanderen",
    "wof:name":"Bart Pattyn",
    "wof:placetype":"venue"
},
  "geometry": {"coordinates":[3.5854930878,51.110118866],"type":"Point"}
}