{
  "type": "Feature",
  "properties": {
    "addr:full":"Hauwaart 30 Oudenaarde Oost-Vlaanderen 9700",
    "addr:housenumber":"30",
    "addr:postcode":"9700",
    "addr:street":"Hauwaart",
    "iso:country":"BE",
    "sg:address":"Hauwaart 30",
    "sg:city":"Oudenaarde",
    "sg:orig_category":"Rundveehouders",
    "sg:phone":"+32 55 45 52 70",
    "sg:postcode":"9700",
    "sg:province":"Oost-Vlaanderen",
    "wof:name":"Germain Deprez",
    "wof:placetype":"venue"
},
  "geometry": {"coordinates":[3.6600561142,50.831401825],"type":"Point"}
}