{
  "type": "Feature",
  "properties": {
    "iso:country":"BE",
    "sg:address":"Linkestraat 2",
    "sg:city":"Beringen (koersel)",
    "sg:classifiers":[
        {
            "category":"Personal",
            "subcategory":"Beauty Salon",
            "type":"Services"
        }
    ],
    "sg:phone":"+32 11 42 62 45",
    "sg:postcode":"3582",
    "sg:province":"Limburg",
    "sg:tags":[
        "lady",
        "-",
        "hairdressing"
    ],
    "wof:name":"Criya",
    "wof:placetype":"venue"
},
  "geometry": {"coordinates":[5.2708749771,51.0595359802],"type":"Point"}
}