{
  "type": "Feature",
  "properties": {
    "addr:full":"Avenue De La Couronne 520 Ixelles Bruxelles-Capitale 1050",
    "addr:housenumber":"520",
    "addr:postcode":"1050",
    "addr:street":"Avenue De La Couronne",
    "iso:country":"BE",
    "sg:address":"Avenue De La Couronne 520",
    "sg:city":"Ixelles",
    "sg:orig_category":"Installatie van houten of kunststof schrijnwerk",
    "sg:phone":"+32 2 649 72 55",
    "sg:postcode":"1050",
    "sg:province":"Bruxelles-Capitale",
    "wof:name":"Ledecq Et Fils",
    "wof:placetype":"venue"
},
  "geometry": {"coordinates":[4.3919267654,50.8191680908],"type":"Point"}
}