{
  "type": "Feature",
  "properties": {
    "addr:full":"Rue Du Bosquet 7 Ottignies-louvain-la-neuve Brabant Wallon 1348",
    "addr:housenumber":"7",
    "addr:postcode":"1348",
    "addr:street":"Rue Du Bosquet",
    "iso:country":"BE",
    "sg:address":"Rue Du Bosquet 7",
    "sg:city":"Ottignies-louvain-la-neuve",
    "sg:orig_category":"Ordinateurs and \u00e9quipement informatique",
    "sg:phone":"+32 10 45 61 30",
    "sg:postcode":"1348",
    "sg:province":"Brabant Wallon",
    "wof:name":"Aethis",
    "wof:placetype":"venue"
},
  "geometry": {"coordinates":[4.6325969696,50.6606445312],"type":"Point"}
}