{
  "type": "Feature",
  "properties": {
    "addr:full":"Winketkaai 18 Box 11-12 Mechelen Antwerpen 2800",
    "addr:housenumber":"18 box 11-12",
    "addr:postcode":"2800",
    "addr:street":"Winketkaai",
    "iso:country":"BE",
    "sg:address":"Winketkaai 18 Box 11-12",
    "sg:city":"Mechelen",
    "sg:classifiers":[
        {
            "category":"Professional",
            "subcategory":"Management & Consulting",
            "type":"Services"
        }
    ],
    "sg:phone":"+32 15 26 07 12",
    "sg:postcode":"2800",
    "sg:province":"Antwerpen",
    "sg:tags":[
        "tax-consultants"
    ],
    "wof:name":"Kwanten M",
    "wof:placetype":"venue"
},
  "geometry": {"coordinates":[4.4854397774,51.0289268494],"type":"Point"}
}