{
  "type": "Feature",
  "properties": {
    "addr:full":"Boulevard Industriel 100 Mouscron Hainaut 7700",
    "addr:housenumber":"100",
    "addr:postcode":"7700",
    "addr:street":"Boulevard Industriel",
    "iso:country":"BE",
    "sg:address":"Boulevard Industriel 100",
    "sg:city":"Mouscron",
    "sg:classifiers":[
        {
            "category":"Manufacturing",
            "subcategory":"Textiles",
            "type":"Manufacturing & Wholesale Goods"
        }
    ],
    "sg:phone":"+32 56 85 32 11",
    "sg:postcode":"7700",
    "sg:province":"Hainaut",
    "sg:tags":[
        "spinning",
        "weaving",
        "mill"
    ],
    "wof:name":"Motte Spinning Company Sa",
    "wof:placetype":"venue"
},
  "geometry": {"coordinates":[3.2532138824,50.750743866],"type":"Point"}
}