{
  "type": "Feature",
  "properties": {
    "iso:country":"BE",
    "sg:address":"Zwarte-arendlaan 14",
    "sg:city":"Antwerpen",
    "sg:orig_category":"Pharmaciens",
    "sg:phone":"+32 3 324 77 11",
    "sg:postcode":"2100",
    "sg:province":"Antwerpen",
    "wof:name":"Jan De Keuster",
    "wof:placetype":"venue"
},
  "geometry": {"coordinates":[4.4272937775,51.2063903809],"type":"Point"}
}