{
  "type": "Feature",
  "properties": {
    "addr:full":"Bien 40 Hamont-achel (achel) Limburg 3930",
    "addr:housenumber":"40",
    "addr:postcode":"3930",
    "addr:street":"Bien",
    "iso:country":"BE",
    "sg:address":"Bien 40",
    "sg:city":"Hamont-achel (achel)",
    "sg:classifiers":[
        {
            "category":"Personal",
            "subcategory":"Beauty Salon",
            "type":"Services"
        }
    ],
    "sg:phone":"+32 477 66 22 62",
    "sg:postcode":"3930",
    "sg:province":"Limburg",
    "sg:tags":[
        "lady",
        "-",
        "hairdressing"
    ],
    "wof:name":"Cindy",
    "wof:placetype":"venue"
},
  "geometry": {"coordinates":[5.4716939926,51.2503547668],"type":"Point"}
}