{
  "type": "Feature",
  "properties": {
    "addr:full":"Rue Du Commerce 1 Wavre Brabant Wallon 1300",
    "addr:housenumber":"1;1300",
    "addr:street":"Rue Du Commerce",
    "iso:country":"BE",
    "sg:address":"Rue Du Commerce 1",
    "sg:city":"Wavre",
    "sg:classifiers":[
        {
            "category":"Health Services",
            "subcategory":"Health Practitioner",
            "type":"Services"
        }
    ],
    "sg:phone":"+32 10 22 59 12",
    "sg:postcode":"1300",
    "sg:province":"Brabant Wallon",
    "sg:tags":[
        "physiotherapist"
    ],
    "wof:name":"Simon M",
    "wof:placetype":"venue"
},
  "geometry": {"coordinates":[4.6103410721,50.7166366577],"type":"Point"}
}