{
  "type": "Feature",
  "properties": {
    "addr:full":"Avenue Des Myrtilles 17 Kraainem Vlaams-Brabant 1950",
    "addr:housenumber":"17",
    "addr:postcode":"1950",
    "addr:street":"Avenue Des Myrtilles",
    "iso:country":"BE",
    "sg:address":"Avenue Des Myrtilles 17",
    "sg:city":"Kraainem",
    "sg:classifiers":[
        {
            "category":"Professional",
            "subcategory":"Lawyer & Legal Services",
            "type":"Services"
        }
    ],
    "sg:phone":"+32 2 767 96 37",
    "sg:postcode":"1950",
    "sg:province":"Vlaams-Brabant",
    "wof:name":"Radar B\u00e9atrice",
    "wof:placetype":"venue"
},
  "geometry": {"coordinates":[4.4868049622,50.8220825195],"type":"Point"}
}