{
  "type": "Feature",
  "properties": {
    "addr:full":"Interleuvenlaan 62-63 Leuven (heverlee) Vlaams-Brabant 3001",
    "addr:postcode":"62-63;3001",
    "addr:street":"Interleuvenlaan",
    "iso:country":"BE",
    "sg:address":"Interleuvenlaan 62-63",
    "sg:city":"Leuven (heverlee)",
    "sg:classifiers":[
        {
            "category":"Professional",
            "subcategory":"Detective & Security Services",
            "type":"Services"
        }
    ],
    "sg:phone":"+32 497 48 06 97",
    "sg:postcode":"3001",
    "sg:province":"Vlaams-Brabant",
    "sg:tags":[
        "agency"
    ],
    "wof:name":"Dtx",
    "wof:placetype":"venue"
},
  "geometry": {"coordinates":[4.7360210419,50.849067688],"type":"Point"}
}