{
  "type": "Feature",
  "properties": {
    "addr:full":"Route De Namur 12 Ciplet Li\u00e8ge 4260",
    "addr:housenumber":"12",
    "addr:postcode":"4260",
    "addr:street":"Route De Namur;Ciplet Lie\u0300Ge",
    "iso:country":"BE",
    "sg:address":"Route De Namur 12",
    "sg:city":"Ciplet",
    "sg:orig_category":"Gespecialiseerde niet-residenti\u00eble bouw SMEEDWERK, METAALBEWERKING AND POEDERMETALLURGIE",
    "sg:phone":"+32 19 69 77 54",
    "sg:postcode":"4260",
    "sg:province":"Li\u00e8ge",
    "wof:name":"Malpaix Construction",
    "wof:placetype":"venue"
},
  "geometry": {"coordinates":[5.0830101967,50.6243591309],"type":"Point"}
}