{
  "type": "Feature",
  "properties": {
    "addr:full":"Rue Foppens 17a Bruxelles Bruxelles-Capitale 1070",
    "addr:housenumber":"17a",
    "addr:postcode":"1070",
    "addr:street":"Rue Foppens",
    "iso:country":"BE",
    "sg:address":"Rue Foppens 17a",
    "sg:city":"Bruxelles",
    "sg:classifiers":[
        {
            "category":"Real Estate",
            "subcategory":"Real Estate Operator",
            "type":"Services"
        }
    ],
    "sg:phone":"+32 2 522 37 15",
    "sg:postcode":"1070",
    "sg:province":"Bruxelles-Capitale",
    "sg:tags":[
        "clich\u00e9s"
    ],
    "wof:name":"M\u00e9tiers Photom\u00e9caniques Select S.p.r.l.",
    "wof:placetype":"venue"
},
  "geometry": {"coordinates":[4.3370141983,50.8460006714],"type":"Point"}
}