{
  "type": "Feature",
  "properties": {
    "addr:full":"Lieven Bauwensstraat 15 Brugge (sint-andries) West-Vlaanderen 8200",
    "addr:housenumber":"15",
    "addr:postcode":"8200",
    "addr:street":"Lieven Bauwensstraat",
    "iso:country":"BE",
    "sg:address":"Lieven Bauwensstraat 15",
    "sg:city":"Brugge (sint-andries)",
    "sg:classifiers":[
        {
            "category":"Home & Garden",
            "subcategory":"Furniture",
            "type":"Retail Goods"
        }
    ],
    "sg:phone":"+32 50 32 04 08",
    "sg:postcode":"8200",
    "sg:province":"West-Vlaanderen",
    "sg:tags":[
        "-"
    ],
    "wof:name":"Buro Center",
    "wof:placetype":"venue"
},
  "geometry": {"coordinates":[3.1946899891,51.2132072449],"type":"Point"}
}