{
  "type": "Feature",
  "properties": {
    "addr:full":"Burgemeester Karel Van Doorslaerlaan 20 Bornem (mariekerke) Antwerpen 2880",
    "addr:housenumber":"20",
    "addr:postcode":"2880",
    "addr:street":"Burgemeester Karel Van Doorslaerlaan",
    "iso:country":"BE",
    "sg:address":"Burgemeester Karel Van Doorslaerlaan 20",
    "sg:city":"Bornem (mariekerke)",
    "sg:classifiers":[
        {
            "category":"Professional",
            "subcategory":"Testing Lab",
            "type":"Services"
        }
    ],
    "sg:phone":"+32 52 33 33 32",
    "sg:postcode":"2880",
    "sg:province":"Antwerpen",
    "sg:tags":[
        "chemist"
    ],
    "wof:name":"Thienpont A",
    "wof:placetype":"venue"
},
  "geometry": {"coordinates":[4.1943759918,51.0624389648],"type":"Point"}
}