{
  "type": "Feature",
  "properties": {
    "addr:full":"Corneel De Ceusterstraat 2 Diegem Vlaams-Brabant 1831",
    "addr:housenumber":"2",
    "addr:postcode":"1831",
    "addr:street":"Ceusterstraat",
    "iso:country":"BE",
    "sg:address":"Corneel De Ceusterstraat 2",
    "sg:city":"Diegem",
    "sg:classifiers":[
        {
            "category":"Restaurant",
            "type":"Food & Drink"
        }
    ],
    "sg:phone":"+32 2 721 24 36",
    "sg:postcode":"1831",
    "sg:province":"Vlaams-Brabant",
    "sg:tags":[
        "\u00c0",
        "domicile",
        "o",
        "catering",
        "fast",
        "emporter",
        "livraison",
        "restaurants"
    ],
    "wof:name":"Park Diegem",
    "wof:placetype":"venue"
},
  "geometry": {"coordinates":[4.4397330284,50.8927955627],"type":"Point"}
}