{
  "type": "Feature",
  "properties": {
    "iso:country":"BE",
    "sg:address":"Sint-elooisstraat 20",
    "sg:city":"Oostkamp",
    "sg:orig_category":"Alternatieve geneeskunde Artsen and specialisten",
    "sg:phone":"+32 50 27 96 37",
    "sg:postcode":"8020",
    "sg:province":"West-Vlaanderen",
    "wof:name":"Dokter Vandenheede Guido",
    "wof:placetype":"venue"
},
  "geometry": {"coordinates":[3.2082331181,51.0965156555],"type":"Point"}
}