{
  "type": "Feature",
  "properties": {
    "iso:country":"BE",
    "sg:address":"Rue De Maire 3",
    "sg:city":"Tournai (froyennes)",
    "sg:classifiers":[
        {
            "category":"Retail",
            "subcategory":"Auto Repair",
            "type":"Services"
        }
    ],
    "sg:phone":"+32 69 22 98 52",
    "sg:postcode":"7503",
    "sg:province":"Hainaut",
    "sg:tags":[
        "garage"
    ],
    "wof:name":"Ecrepont L",
    "wof:placetype":"venue"
},
  "geometry": {"coordinates":[3.3700020313,50.6228599548],"type":"Point"}
}