{
  "type": "Feature",
  "properties": {
    "addr:full":"Karabiniersstr 17 Passendale 8698",
    "addr:housenumber":"17",
    "addr:postcode":"8698",
    "addr:street":"Karabiniersstr",
    "iso:country":"BE",
    "sg:address":"Karabiniersstr 17",
    "sg:city":"Passendale",
    "sg:classifiers":[
        {
            "category":"Banks & Credit Unions",
            "subcategory":"Bank",
            "type":"Services"
        }
    ],
    "sg:phone":"+32 51 77 80 00",
    "sg:postcode":"8698",
    "wof:name":"Caisse Nationale De, Cr\u00e9dit Professionnel",
    "wof:placetype":"venue"
},
  "geometry": {"coordinates":[3.0207700729,50.9000282288],"type":"Point"}
}