{
  "type": "Feature",
  "properties": {
    "addr:full":"Breendonkdorp 95 Puurs Antwerpen 2870",
    "addr:housenumber":"95",
    "addr:postcode":"2870",
    "addr:street":"Breendonkdorp",
    "iso:country":"BE",
    "sg:address":"Breendonkdorp 95",
    "sg:city":"Puurs",
    "sg:classifiers":[
        {
            "category":"Cafe",
            "type":"Food & Drink"
        }
    ],
    "sg:phone":"+32 3 886 19 43",
    "sg:postcode":"2870",
    "sg:province":"Antwerpen",
    "sg:tags":[
        "caf\u00e9s"
    ],
    "wof:name":"Caf\u00c9 St.sebastiaan",
    "wof:placetype":"venue"
},
  "geometry": {"coordinates":[4.3255448341,51.043888092],"type":"Point"}
}