{
  "type": "Feature",
  "properties": {
    "iso:country":"BE",
    "sg:address":"Torenstraat 59",
    "sg:city":"Lommel",
    "sg:classifiers":[
        {
            "category":"Cafe",
            "type":"Food & Drink"
        }
    ],
    "sg:phone":"+32 11 54 41 41",
    "sg:postcode":"3920",
    "sg:province":"Limburg",
    "sg:tags":[
        "caf\u00e9s"
    ],
    "wof:name":"Tom Vanden Eynde",
    "wof:placetype":"venue"
},
  "geometry": {"coordinates":[5.3356699944,51.235748291],"type":"Point"}
}