{
  "type": "Feature",
  "properties": {
    "iso:country":"BE",
    "sg:address":"Laarstraat 46",
    "sg:city":"Bilzen (beverst)",
    "sg:classifiers":[
        {
            "category":"Health Services",
            "subcategory":"Nursing And Care Facility",
            "type":"Services"
        }
    ],
    "sg:phone":"+32 89 41 24 87",
    "sg:postcode":"3740",
    "sg:province":"Limburg",
    "sg:tags":[
        "home"
    ],
    "wof:name":"Zeeuws L",
    "wof:placetype":"venue"
},
  "geometry": {"coordinates":[5.4935898781,50.8895606995],"type":"Point"}
}