{
  "type": "Feature",
  "properties": {
    "iso:country":"BE",
    "sg:address":"Kursaalstraat 19",
    "sg:city":"Knokke-heist",
    "sg:orig_category":"Brood, gebak and snoepgoed",
    "sg:phone":"+32 50 51 10 25",
    "sg:postcode":"8301",
    "sg:province":"West-Vlaanderen",
    "wof:name":"Bakkerij Schroyens",
    "wof:placetype":"venue"
},
  "geometry": {"coordinates":[3.2639000416,51.3396911621],"type":"Point"}
}