{
  "type": "Feature",
  "properties": {
    "iso:country":"BE",
    "sg:address":"Autostradeweg 2",
    "sg:city":"Melle",
    "sg:orig_category":"Non-Classified Establishments",
    "sg:phone":"+32 9 272 78 78",
    "sg:postcode":"9090",
    "sg:province":"Oost-Vlaanderen",
    "wof:name":"Bonneterie De Groote Belgium Nv",
    "wof:placetype":"venue"
},
  "geometry": {"coordinates":[3.7952139378,50.9911308289],"type":"Point"}
}