{
  "type": "Feature",
  "properties": {
    "addr:full":"Rue Lairesse 29 Li\u00c8ge Li\u00e8ge 4020",
    "addr:housenumber":"29",
    "addr:postcode":"4020",
    "addr:street":"Rue Lairesse",
    "iso:country":"BE",
    "sg:address":"Rue Lairesse 29",
    "sg:city":"Li\u00c8ge",
    "sg:orig_category":"M\u00e9decins and sp\u00e9cialistes",
    "sg:phone":"+32 4 343 46 71",
    "sg:postcode":"4020",
    "sg:province":"Li\u00e8ge",
    "wof:name":"Hong Van Truong",
    "wof:placetype":"venue"
},
  "geometry": {"coordinates":[5.5866098404,50.6358337402],"type":"Point"}
}