{
  "type": "Feature",
  "properties": {
    "addr:full":"Markt 26 Sint-katelijne-waver Antwerpen 2860",
    "addr:housenumber":"26",
    "addr:postcode":"2860",
    "addr:street":"Markt",
    "iso:country":"BE",
    "sg:address":"Markt 26",
    "sg:city":"Sint-katelijne-waver",
    "sg:orig_category":"Notaires",
    "sg:phone":"+32 15 31 43 31",
    "sg:postcode":"2860",
    "sg:province":"Antwerpen",
    "wof:name":"Leo Vlaeymans",
    "wof:placetype":"venue"
},
  "geometry": {"coordinates":[4.531460762,51.0703010559],"type":"Point"}
}