{
  "type": "Feature",
  "properties": {
    "addr:full":"Voie De L'ardenne 160 Chaudfontaine (embourg) Li\u00e8ge 4053",
    "addr:housenumber":"160",
    "addr:postcode":"4053",
    "addr:street":"Voie De L'Ardenne",
    "iso:country":"BE",
    "sg:address":"Voie De L'ardenne 160",
    "sg:city":"Chaudfontaine (embourg)",
    "sg:classifiers":[
        {
            "category":"Bars & Pubs",
            "type":"Food & Drink"
        }
    ],
    "sg:phone":"+32 4 367 15 75",
    "sg:postcode":"4053",
    "sg:province":"Li\u00e8ge",
    "sg:tags":[
        "tavern"
    ],
    "wof:name":"Beaubourg (le)",
    "wof:placetype":"venue"
},
  "geometry": {"coordinates":[5.613296032,50.5857315063],"type":"Point"}
}