{
  "type": "Feature",
  "properties": {
    "iso:country":"BE",
    "sg:address":"Koningin Astridlaan 80",
    "sg:city":"Bornem",
    "sg:orig_category":"Producteurs de l\u00e9gumes",
    "sg:phone":"+32 3 889 51 10",
    "sg:postcode":"2880",
    "sg:province":"Antwerpen",
    "wof:name":"Urbaan Van Noten",
    "wof:placetype":"venue"
},
  "geometry": {"coordinates":[4.2892079353,51.105884552],"type":"Point"}
}