{
  "type": "Feature",
  "properties": {
    "iso:country":"BE",
    "sg:address":"Smalvoortstraat 51",
    "sg:city":"Turnhout",
    "sg:orig_category":"Diverse grafische activiteiten",
    "sg:phone":"+32 14 72 79 45",
    "sg:postcode":"2300",
    "sg:province":"Antwerpen",
    "wof:name":"Bert Braet",
    "wof:placetype":"venue"
},
  "geometry": {"coordinates":[4.9558491707,51.3168716431],"type":"Point"}
}