{
  "type": "Feature",
  "properties": {
    "addr:full":"Rue D'austerlitz 35 Rochefort Namur 5580",
    "addr:housenumber":"35",
    "addr:postcode":"5580",
    "addr:street":"Rue D'Austerlitz",
    "iso:country":"BE",
    "sg:address":"Rue D'austerlitz 35",
    "sg:city":"Rochefort",
    "sg:classifiers":[
        {
            "category":"Building & Trades",
            "subcategory":"Cleaning & Sanitation",
            "type":"Services"
        }
    ],
    "sg:phone":"+32 84 31 33 04",
    "sg:postcode":"5580",
    "sg:province":"Namur",
    "sg:tags":[
        "cleaner",
        "window"
    ],
    "wof:name":"Pirlot De Corbion G",
    "wof:placetype":"venue"
},
  "geometry": {"coordinates":[5.2156867981,50.1612167358],"type":"Point"}
}