{
  "type": "Feature",
  "properties": {
    "iso:country":"BE",
    "sg:address":"Zonnewegel 36",
    "sg:city":"Zaventem (sterrebeek)",
    "sg:classifiers":[
        {
            "category":"Health Services",
            "subcategory":"Health Practitioner",
            "type":"Services"
        }
    ],
    "sg:phone":"+32 2 731 46 23",
    "sg:postcode":"1933",
    "sg:province":"Vlaams-Brabant",
    "sg:tags":[
        "physiotherapist"
    ],
    "wof:name":"Moenaert Genevieve",
    "wof:placetype":"venue"
},
  "geometry": {"coordinates":[4.4949231148,50.8656158447],"type":"Point"}
}