{
  "type": "Feature",
  "properties": {
    "addr:full":"Chauss\u00e9e De Bruxelles 206 Ath Hainaut 7800",
    "addr:housenumber":"206",
    "addr:postcode":"7800",
    "addr:street":"Chausse\u0301E De Bruxelles",
    "iso:country":"BE",
    "sg:address":"Chauss\u00e9e De Bruxelles 206",
    "sg:city":"Ath",
    "sg:classifiers":[
        {
            "category":"Utilities",
            "subcategory":"Fuel Oil & Lpg",
            "type":"Services"
        }
    ],
    "sg:phone":"+32 68 28 13 64",
    "sg:postcode":"7800",
    "sg:province":"Hainaut",
    "wof:name":"Donkerwolke-bonnami Sprl",
    "wof:placetype":"venue"
},
  "geometry": {"coordinates":[3.7952771187,50.6355934143],"type":"Point"}
}