{
  "type": "Feature",
  "properties": {
    "addr:full":"Rue Des Poiriers 9 Gembloux-sur-orneau (gembloux) Namur 5030",
    "addr:housenumber":"9",
    "addr:postcode":"5030",
    "addr:street":"Rue Des Poiriers;Namur",
    "iso:country":"BE",
    "sg:address":"Rue Des Poiriers 9",
    "sg:city":"Gembloux-sur-orneau (gembloux)",
    "sg:classifiers":[
        {
            "category":"Home & Garden",
            "subcategory":"Building Materials",
            "type":"Retail Goods"
        }
    ],
    "sg:phone":"+32 81 62 70 70",
    "sg:postcode":"5030",
    "sg:province":"Namur",
    "sg:tags":[
        "window"
    ],
    "wof:name":"Stralco Industrie",
    "wof:placetype":"venue"
},
  "geometry": {"coordinates":[4.7035827637,50.583656311],"type":"Point"}
}