{
  "type": "Feature",
  "properties": {
    "iso:country":"BE",
    "sg:address":"Braamstraat 2",
    "sg:city":"Pittem",
    "sg:orig_category":"Rundveehouders",
    "sg:phone":"+32 51 46 62 21",
    "sg:postcode":"8740",
    "sg:province":"West-Vlaanderen",
    "wof:name":"Ludovar",
    "wof:placetype":"venue"
},
  "geometry": {"coordinates":[3.2737340927,51.0094566345],"type":"Point"}
}