{
  "type": "Feature",
  "properties": {
    "addr:full":"Markt 5 Maaseik Limburg 3680",
    "addr:housenumber":"5",
    "addr:postcode":"3680",
    "addr:street":"Markt",
    "iso:country":"BE",
    "sg:address":"Markt 5",
    "sg:city":"Maaseik",
    "sg:orig_category":"Musea and historische gebouwen",
    "sg:phone":"+32 89 56 68 90",
    "sg:postcode":"3680",
    "sg:province":"Limburg",
    "wof:name":"Museactron",
    "wof:placetype":"venue"
},
  "geometry": {"coordinates":[5.7920632362,51.0949478149],"type":"Point"}
}