{
  "type": "Feature",
  "properties": {
    "iso:country":"BE",
    "sg:address":"7",
    "sg:city":"Rue Emile Vandervelde 6040 Jumet-belgique",
    "sg:classifiers":[
        {
            "category":"Professional",
            "subcategory":"Computer Services",
            "type":"Services"
        }
    ],
    "sg:phone":"+32 71 34 91 00",
    "sg:postcode":"7",
    "sg:tags":[
        "information",
        "technology",
        "software"
    ],
    "wof:name":"Win Pro",
    "wof:placetype":"venue"
},
  "geometry": {"coordinates":[4.4342160225,50.4411697388],"type":"Point"}
}