{
  "type": "Feature",
  "properties": {
    "addr:full":"7 Rue Emile Vandervelde 6040 Jumet-belgique 7",
    "addr:housenumber":"7;7",
    "addr:postcode":"6040",
    "addr:street":"Rue Emile Vandervelde;Jumet-Belgique",
    "iso:country":"BE",
    "sg:address":"7",
    "sg:city":"Rue Emile Vandervelde 6040 Jumet-belgique",
    "sg:classifiers":[
        {
            "category":"Professional",
            "subcategory":"Computer Services",
            "type":"Services"
        }
    ],
    "sg:phone":"+32 71 34 91 00",
    "sg:postcode":"7",
    "sg:tags":[
        "information",
        "technology",
        "software"
    ],
    "wof:name":"Win Pro",
    "wof:placetype":"venue"
},
  "geometry": {"coordinates":[4.4342160225,50.4411697388],"type":"Point"}
}