{
  "type": "Feature",
  "properties": {
    "addr:full":"Rue D'orbey 30 Fosses-la-ville Namur 5070",
    "addr:housenumber":"30",
    "addr:postcode":"5070",
    "addr:street":"Rue D'Orbey",
    "iso:country":"BE",
    "sg:address":"Rue D'orbey 30",
    "sg:city":"Fosses-la-ville",
    "sg:classifiers":[
        {
            "category":"Health Services",
            "subcategory":"Dentist",
            "type":"Services"
        }
    ],
    "sg:phone":"+32 71 71 26 48",
    "sg:postcode":"5070",
    "sg:province":"Namur",
    "wof:name":"Jean Fran\u00e7oise",
    "wof:placetype":"venue"
},
  "geometry": {"coordinates":[4.6955251694,50.3971862793],"type":"Point"}
}