{
  "type": "Feature",
  "properties": {
    "addr:full":"Rue Du Condroz 6 Ciney Namur 5590",
    "addr:housenumber":"6",
    "addr:postcode":"5590",
    "addr:street":"Rue Du Condroz",
    "iso:country":"BE",
    "sg:address":"Rue Du Condroz 6",
    "sg:city":"Ciney",
    "sg:classifiers":[
        {
            "category":"Communications",
            "subcategory":"Film & Video Production",
            "type":"Services"
        }
    ],
    "sg:phone":"+32 83 21 73 66",
    "sg:postcode":"5590",
    "sg:province":"Namur",
    "sg:tags":[
        "hiring",
        "-"
    ],
    "wof:name":"Video Clap",
    "wof:placetype":"venue"
},
  "geometry": {"coordinates":[5.1027579308,50.2969970703],"type":"Point"}
}