{
  "type": "Feature",
  "properties": {
    "addr:full":"Naamsesteenweg 74 Leuven (groot) Vlaams-Brabant 3001",
    "addr:housenumber":"74",
    "addr:postcode":"3001",
    "addr:street":"Naamsesteenweg;Groot Vlaams-Brabant",
    "iso:country":"BE",
    "sg:address":"Naamsesteenweg 74",
    "sg:city":"Leuven (groot)",
    "sg:orig_category":"Banques and organismes de cr\u00e9dit",
    "sg:phone":"+32 16 27 03 70",
    "sg:postcode":"3001",
    "sg:province":"Vlaams-Brabant",
    "wof:name":"Dexia",
    "wof:placetype":"venue"
},
  "geometry": {"coordinates":[4.696762085,50.8668403625],"type":"Point"}
}