{
  "type": "Feature",
  "properties": {
    "iso:country":"BE",
    "sg:address":"Rue Ah\u00c9r\u00c9e 16",
    "sg:city":"Walcourt",
    "sg:orig_category":"Installation de menuiserie en bois and plastique",
    "sg:phone":"+32 71 21 62 35",
    "sg:postcode":"5651",
    "sg:province":"Namur",
    "wof:name":"Andre Charlier",
    "wof:placetype":"venue"
},
  "geometry": {"coordinates":[4.5028548241,50.3165016174],"type":"Point"}
}