{
  "type": "Feature",
  "properties": {
    "iso:country":"BE",
    "sg:address":"Nazarethpad 46",
    "sg:city":"Zandhoven",
    "sg:orig_category":"Eleveurs de bovins",
    "sg:phone":"+32 3 484 48 74",
    "sg:postcode":"2240",
    "sg:province":"Antwerpen",
    "wof:name":"Frans Van Genechten",
    "wof:placetype":"venue"
},
  "geometry": {"coordinates":[4.6640949249,51.2282791138],"type":"Point"}
}