{
  "type": "Feature",
  "properties": {
    "addr:full":"Jonkershovestraat 250 Houthulst West-Vlaanderen 8650",
    "addr:housenumber":"250",
    "addr:postcode":"8650",
    "addr:street":"Jonkershovestraat",
    "iso:country":"BE",
    "sg:address":"Jonkershovestraat 250",
    "sg:city":"Houthulst",
    "sg:orig_category":"Pain, p\u00e2tisseries and confiseries",
    "sg:phone":"+32 51 54 56 82",
    "sg:postcode":"8650",
    "sg:province":"West-Vlaanderen",
    "wof:name":"Gino Vanthuyne",
    "wof:placetype":"venue"
},
  "geometry": {"coordinates":[2.9257929325,50.9714813232],"type":"Point"}
}