{
  "type": "Feature",
  "properties": {
    "addr:full":"Rue De Bouvy 90 La Louviere Hainaut 7100",
    "addr:housenumber":"90",
    "addr:postcode":"7100",
    "addr:street":"Rue De Bouvy",
    "iso:country":"BE",
    "sg:address":"Rue De Bouvy 90",
    "sg:city":"La Louviere",
    "sg:orig_category":"Artsen and specialisten",
    "sg:phone":"+32 64 22 38 54",
    "sg:postcode":"7100",
    "sg:province":"Hainaut",
    "wof:name":"Daniel Valentini",
    "wof:placetype":"venue"
},
  "geometry": {"coordinates":[4.1831321716,50.4719161987],"type":"Point"}
}