{
  "type": "Feature",
  "properties": {
    "iso:country":"BE",
    "sg:address":"Lobbensestraat 226",
    "sg:city":"Scherpenheuvel-zichem",
    "sg:orig_category":"Elektrische installaties voor woningen Installatie van houten of kunststof schrijnwerk Woningbouw",
    "sg:phone":"+32 13 77 89 73",
    "sg:postcode":"3271",
    "sg:province":"Vlaams-Brabant",
    "wof:name":"Gresco",
    "wof:placetype":"venue"
},
  "geometry": {"coordinates":[4.9435400963,50.9836807251],"type":"Point"}
}