{
  "type": "Feature",
  "properties": {
    "addr:full":"Rue De La Bourse 43 La Louvi\u00e8re (str\u00e9py-bracquegnies) Hainaut 7110",
    "addr:housenumber":"43",
    "addr:postcode":"7110",
    "addr:street":"Rue De La Bourse",
    "iso:country":"BE",
    "sg:address":"Rue De La Bourse 43",
    "sg:city":"La Louvi\u00e8re (str\u00e9py-bracquegnies)",
    "sg:classifiers":[
        {
            "category":"Personal",
            "subcategory":"Beauty Salon",
            "type":"Services"
        }
    ],
    "sg:phone":"+32 64 67 54 51",
    "sg:postcode":"7110",
    "sg:province":"Hainaut",
    "sg:tags":[
        "lady",
        "-",
        "hairdressing"
    ],
    "wof:name":"Frankie-look",
    "wof:placetype":"venue"
},
  "geometry": {"coordinates":[4.1505050659,50.4826698303],"type":"Point"}
}