{
  "type": "Feature",
  "properties": {
    "addr:full":"Terhagenstraat 16b Zoutleeuw (budingen) Vlaams-Brabant 3440",
    "addr:housenumber":"16b",
    "addr:postcode":"3440",
    "addr:street":"Terhagenstraat",
    "iso:country":"BE",
    "sg:address":"Terhagenstraat 16b",
    "sg:city":"Zoutleeuw (budingen)",
    "sg:classifiers":[
        {
            "category":"Home & Garden",
            "subcategory":"Hardware",
            "type":"Retail Goods"
        }
    ],
    "sg:phone":"+32 11 78 47 92",
    "sg:postcode":"3440",
    "sg:province":"Vlaams-Brabant",
    "sg:tags":[
        "machine",
        "horticultural"
    ],
    "wof:name":"Haenen L",
    "wof:placetype":"venue"
},
  "geometry": {"coordinates":[5.0800318718,50.8570823669],"type":"Point"}
}