{
  "type": "Feature",
  "properties": {
    "addr:full":"Avenue L\u00c9opold Wiener 82 Watermaal-bosvoorde/watermael-boitsfort Bruxelles-Capitale 1170",
    "addr:housenumber":"82",
    "addr:postcode":"1170",
    "addr:street":"Avenue Le\u0301Opold Wiener",
    "iso:country":"BE",
    "sg:address":"Avenue L\u00c9opold Wiener 82",
    "sg:city":"Watermaal-bosvoorde/watermael-boitsfort",
    "sg:orig_category":"Installation de menuiserie en bois and plastique",
    "sg:phone":"+32 2 672 12 14",
    "sg:postcode":"1170",
    "sg:province":"Bruxelles-Capitale",
    "wof:name":"Workmasters Europe",
    "wof:placetype":"venue"
},
  "geometry": {"coordinates":[4.4089818001,50.804599762],"type":"Point"}
}