{
  "type": "Feature",
  "properties": {
    "addr:full":"Stanleystraat 1 Antwerpen Antwerpen 2018",
    "addr:housenumber":"1",
    "addr:postcode":"2018",
    "addr:street":"Stanleystraat",
    "iso:country":"BE",
    "sg:address":"Stanleystraat 1",
    "sg:city":"Antwerpen",
    "sg:classifiers":[
        {
            "category":"Cafe",
            "type":"Food & Drink"
        }
    ],
    "sg:phone":"+32 3 239 64 58",
    "sg:postcode":"2018",
    "sg:province":"Antwerpen",
    "sg:tags":[
        "caf\u00e9s"
    ],
    "wof:name":"Bell",
    "wof:placetype":"venue"
},
  "geometry": {"coordinates":[4.4284100533,51.2028503418],"type":"Point"}
}