{
  "type": "Feature",
  "properties": {
    "iso:country":"BE",
    "sg:address":"Rue De L'eglise 38",
    "sg:city":"Estaimpuis",
    "sg:orig_category":"Kapsalons",
    "sg:phone":"+32 56 48 88 00",
    "sg:postcode":"7730",
    "sg:province":"Hainaut",
    "wof:name":"Coiffure Francine",
    "wof:placetype":"venue"
},
  "geometry": {"coordinates":[3.261275053,50.7066955566],"type":"Point"}
}