{
  "type": "Feature",
  "properties": {
    "addr:full":"Kattenbroekstraat 20 Aalst (moorsel) Oost-Vlaanderen 9310",
    "addr:housenumber":"20",
    "addr:postcode":"9310",
    "addr:street":"Kattenbroekstraat;Moorsel Oost-Vlaanderen",
    "iso:country":"BE",
    "sg:address":"Kattenbroekstraat 20",
    "sg:city":"Aalst (moorsel)",
    "sg:classifiers":[
        {
            "category":"Wholesale",
            "subcategory":"Plants",
            "type":"Manufacturing & Wholesale Goods"
        }
    ],
    "sg:phone":"+32 53 70 39 20",
    "sg:postcode":"9310",
    "sg:province":"Oost-Vlaanderen",
    "sg:tags":[
        "whol",
        "flower",
        "-",
        "grower"
    ],
    "wof:name":"Vermoesen J",
    "wof:placetype":"venue"
},
  "geometry": {"coordinates":[4.0894827843,50.9551811218],"type":"Point"}
}