{
  "type": "Feature",
  "properties": {
    "addr:full":"Stationsstraat 8 Herzele Oost-Vlaanderen 9550",
    "addr:housenumber":"8",
    "addr:postcode":"9550",
    "addr:street":"Stationsstraat;Oost-Vlaanderen",
    "iso:country":"BE",
    "sg:address":"Stationsstraat 8",
    "sg:city":"Herzele",
    "sg:orig_category":"Technisch and beroeps secundair onderwijs",
    "sg:phone":"+32 53 62 23 71",
    "sg:postcode":"9550",
    "sg:province":"Oost-Vlaanderen",
    "wof:name":"Koninklijk Atheneum",
    "wof:placetype":"venue"
},
  "geometry": {"coordinates":[3.8888380527,50.8900260925],"type":"Point"}
}