{
  "type": "Feature",
  "properties": {
    "iso:country":"BE",
    "sg:address":"Sterrenstraat 56c",
    "sg:city":"Lier",
    "sg:classifiers":[
        {
            "category":"Food & Beverages",
            "subcategory":"Meat & Fish",
            "type":"Retail Goods"
        }
    ],
    "sg:phone":"+32 3 488 14 15",
    "sg:postcode":"2500",
    "sg:province":"Antwerpen",
    "sg:tags":[
        "bedspread",
        "blanket",
        "-"
    ],
    "wof:name":"Mertex Bvba",
    "wof:placetype":"venue"
},
  "geometry": {"coordinates":[4.565841198,51.1393127441],"type":"Point"}
}