{
  "type": "Feature",
  "properties": {
    "addr:full":"Kerkstraat 82 Nieuwerkerken Limburg 3850",
    "addr:housenumber":"82",
    "addr:postcode":"3850",
    "addr:street":"Kerkstraat",
    "iso:country":"BE",
    "sg:address":"Kerkstraat 82",
    "sg:city":"Nieuwerkerken",
    "sg:orig_category":"Postkantoren Verzekeringsmakelaars and experts",
    "sg:phone":"+32 11 68 27 24",
    "sg:postcode":"3850",
    "sg:province":"Limburg",
    "wof:name":"De Post",
    "wof:placetype":"venue"
},
  "geometry": {"coordinates":[5.1925339699,50.8629112244],"type":"Point"}
}