{
  "type": "Feature",
  "properties": {
    "iso:country":"BE",
    "sg:address":"Rue D'harscamp 14-2",
    "sg:city":"Li\u00e8ge 1 (li\u00e8ge 2)",
    "sg:classifiers":[
        {
            "category":"Professional",
            "subcategory":"Accounting & Tax Preparation",
            "type":"Services"
        }
    ],
    "sg:phone":"+32 4 344 21 24",
    "sg:postcode":"4020",
    "sg:province":"Li\u00e8ge",
    "sg:tags":[
        "bookkeeper"
    ],
    "wof:name":"Legrain P",
    "wof:placetype":"venue"
},
  "geometry": {"coordinates":[5.5786809921,50.6346626282],"type":"Point"}
}