{
  "type": "Feature",
  "properties": {
    "addr:full":"Langeveldstraat 51b16 Ukkel/uccle Bruxelles-Capitale 1180",
    "addr:housenumber":"51b16",
    "addr:postcode":"1180",
    "addr:street":"Langeveldstraat;/",
    "iso:country":"BE",
    "sg:address":"Langeveldstraat 51b16",
    "sg:city":"Ukkel/uccle",
    "sg:classifiers":[
        {
            "category":"Professional",
            "subcategory":"Accounting & Tax Preparation",
            "type":"Services"
        }
    ],
    "sg:phone":"+32 2 373 51 00",
    "sg:postcode":"1180",
    "sg:province":"Bruxelles-Capitale",
    "sg:tags":[
        "accountant"
    ],
    "wof:name":"Michel Linet",
    "wof:placetype":"venue"
},
  "geometry": {"coordinates":[4.3627800941,50.7902793884],"type":"Point"}
}