{
  "type": "Feature",
  "properties": {
    "iso:country":"BE",
    "sg:address":"Veldstr 180",
    "sg:city":"Hasselt",
    "sg:classifiers":[
        {
            "category":"Banks & Credit Unions",
            "subcategory":"Investment Brokerage",
            "type":"Services"
        }
    ],
    "sg:phone":"+32 11 25 47 62",
    "sg:postcode":"3511",
    "sg:province":"Limburg",
    "sg:tags":[
        "horticulture",
        "good",
        "livestock",
        "household",
        "wood",
        "agriculture",
        "furniture"
    ],
    "wof:name":"Bloemen Thomas Bvba",
    "wof:placetype":"venue"
},
  "geometry": {"coordinates":[5.2975921631,50.9379272461],"type":"Point"}
}