{
  "type": "Feature",
  "properties": {
    "addr:full":"Rue Du Village 16 Fourons (fouron-st.-pierre) Limburg 3792",
    "addr:housenumber":"16",
    "addr:postcode":"3792",
    "addr:street":"Rue Du Village",
    "iso:country":"BE",
    "sg:address":"Rue Du Village 16",
    "sg:city":"Fourons (fouron-st.-pierre)",
    "sg:classifiers":[
        {
            "category":"Bars & Pubs",
            "type":"Food & Drink"
        }
    ],
    "sg:phone":"+32 4 381 01 93",
    "sg:postcode":"3792",
    "sg:province":"Limburg",
    "wof:name":"Commanderie",
    "wof:placetype":"venue"
},
  "geometry": {"coordinates":[5.8230772018,50.7382659912],"type":"Point"}
}