{
  "type": "Feature",
  "properties": {
    "addr:full":"Rue Hasse 3 Waimes Li\u00e8ge 4950",
    "addr:housenumber":"3",
    "addr:postcode":"4950",
    "addr:street":"Rue Hasse",
    "iso:country":"BE",
    "sg:address":"Rue Hasse 3",
    "sg:city":"Waimes",
    "sg:orig_category":"Immobili\u00ebnkantoren",
    "sg:phone":"+32 80 44 77 83",
    "sg:postcode":"4950",
    "sg:province":"Li\u00e8ge",
    "wof:name":"Immo-hasse",
    "wof:placetype":"venue"
},
  "geometry": {"coordinates":[6.1110301018,50.4149055481],"type":"Point"}
}