{
  "type": "Feature",
  "properties": {
    "addr:full":"Rue De Fiennes 15 Bruxelles (anderlecht) Bruxelles-Capitale 1070",
    "addr:housenumber":"15",
    "addr:postcode":"1070",
    "addr:street":"Rue De Fiennes",
    "iso:country":"BE",
    "sg:address":"Rue De Fiennes 15",
    "sg:city":"Bruxelles (anderlecht)",
    "sg:classifiers":[
        {
            "category":"Food & Beverages",
            "subcategory":"Supermarket",
            "type":"Retail Goods"
        }
    ],
    "sg:phone":"+32 2 524 40 81",
    "sg:postcode":"1070",
    "sg:province":"Bruxelles-Capitale",
    "sg:tags":[
        "department",
        "store"
    ],
    "wof:name":"Fruits & Legumes",
    "wof:placetype":"venue"
},
  "geometry": {"coordinates":[4.3346967697,50.8391685486],"type":"Point"}
}