{
  "type": "Feature",
  "properties": {
    "addr:full":"Rue De Bruxelles 36 Enghien Hainaut 7850",
    "addr:housenumber":"36",
    "addr:postcode":"7850",
    "addr:street":"Rue De Bruxelles",
    "iso:country":"BE",
    "sg:address":"Rue De Bruxelles 36",
    "sg:city":"Enghien",
    "sg:classifiers":[
        {
            "category":"Shopping",
            "subcategory":"Pets & Pet Supplies",
            "type":"Retail Goods"
        }
    ],
    "sg:phone":"+32 2 395 31 50",
    "sg:postcode":"7850",
    "sg:province":"Hainaut",
    "sg:tags":[
        "aquarium",
        "accessory"
    ],
    "wof:name":"Aquatile",
    "wof:placetype":"venue"
},
  "geometry": {"coordinates":[4.0408768654,50.6944885254],"type":"Point"}
}