{
  "type": "Feature",
  "properties": {
    "iso:country":"BE",
    "sg:address":"Rue Walthere Delvigne 10",
    "sg:city":"Fl\u00c9ron",
    "sg:orig_category":"Boekhouders",
    "sg:phone":"+32 4 358 94 73",
    "sg:postcode":"4624",
    "sg:province":"Li\u00e8ge",
    "wof:name":"P. Depraetere",
    "wof:placetype":"venue"
},
  "geometry": {"coordinates":[5.6729078293,50.608581543],"type":"Point"}
}