{
  "type": "Feature",
  "properties": {
    "iso:country":"BE",
    "sg:address":"Reepstraat 101ba",
    "sg:city":"Sint-gillis-waas",
    "sg:orig_category":"Rundveehouders Varkenskwekers",
    "sg:phone":"+32 3 770 52 90",
    "sg:postcode":"9170",
    "sg:province":"Oost-Vlaanderen",
    "wof:name":"Jozef Van Guyse",
    "wof:placetype":"venue"
},
  "geometry": {"coordinates":[4.1022391319,51.2276573181],"type":"Point"}
}