{
  "type": "Feature",
  "properties": {
    "addr:full":"Chauss\u00c9e De Brunehault 44 Morlanwelz Hainaut 7140",
    "addr:housenumber":"44",
    "addr:postcode":"7140",
    "addr:street":"Chausse\u0301E De Brunehault",
    "iso:country":"BE",
    "sg:address":"Chauss\u00c9e De Brunehault 44",
    "sg:city":"Morlanwelz",
    "sg:orig_category":"Begrafeniswezen",
    "sg:phone":"+32 64 44 44 44",
    "sg:postcode":"7140",
    "sg:province":"Hainaut",
    "wof:name":"Pompes Fun\u00c8bres Duvivier-deven",
    "wof:placetype":"venue"
},
  "geometry": {"coordinates":[4.2375311852,50.4479560852],"type":"Point"}
}