{
  "type": "Feature",
  "properties": {
    "iso:country":"BE",
    "sg:address":"Ankerslaan 55",
    "sg:city":"Gent (ledeberg)",
    "sg:classifiers":[
        {
            "category":"Health Services",
            "subcategory":"Health Practitioner",
            "type":"Services"
        }
    ],
    "sg:phone":"+32 9 232 24 44",
    "sg:postcode":"9050",
    "sg:province":"Oost-Vlaanderen",
    "sg:tags":[
        "physiotherapist"
    ],
    "wof:name":"De Paepe Hilde",
    "wof:placetype":"venue"
},
  "geometry": {"coordinates":[3.7503800392,51.0392608643],"type":"Point"}
}