{
  "type": "Feature",
  "properties": {
    "addr:full":"Koninklijke St.mariastr. 142 Schaarbeek/schaerbeek Bruxelles-Capitale 1030",
    "addr:housenumber":"142",
    "addr:postcode":"1030",
    "iso:country":"BE",
    "sg:address":"Koninklijke St.mariastr. 142",
    "sg:city":"Schaarbeek/schaerbeek",
    "sg:classifiers":[
        {
            "category":"Insurance",
            "subcategory":"Insurance Agent",
            "type":"Services"
        }
    ],
    "sg:phone":"+32 2 245 46 58",
    "sg:postcode":"1030",
    "sg:province":"Bruxelles-Capitale",
    "sg:tags":[
        "verzekeringsmakelaars",
        "expert"
    ],
    "wof:name":"Cr\u00c9dit Royal",
    "wof:placetype":"venue"
},
  "geometry": {"coordinates":[4.3718500137,50.8640365601],"type":"Point"}
}