{
  "type": "Feature",
  "properties": {
    "iso:country":"BE",
    "sg:address":"Zwevezeelsestraat 117",
    "sg:city":"Ardooie",
    "sg:orig_category":"Eleveurs and marchands de porcs. Eleveurs de bovins",
    "sg:phone":"+32 51 74 40 23",
    "sg:postcode":"8851",
    "sg:province":"West-Vlaanderen",
    "wof:name":"Erik Baekelandt",
    "wof:placetype":"venue"
},
  "geometry": {"coordinates":[3.2070219517,51.0125694275],"type":"Point"}
}