{
  "type": "Feature",
  "properties": {
    "iso:country":"BE",
    "sg:address":"Jean-baptiste Depaireln 123",
    "sg:city":"Brussel/bruxelles",
    "sg:orig_category":"Rusthuizen and serviceflats",
    "sg:phone":"+32 2 478 38 00",
    "sg:postcode":"1020",
    "sg:province":"Bruxelles-Capitale",
    "wof:name":"Gerifarm",
    "wof:placetype":"venue"
},
  "geometry": {"coordinates":[4.3291778564,50.8914451599],"type":"Point"}
}