{
  "type": "Feature",
  "properties": {
    "iso:country":"BE",
    "sg:address":"Wortegemstraat 32",
    "sg:city":"Oudenaarde",
    "sg:orig_category":"Film-, tv- and videoproductie Software ontwikkeling and ontwerp",
    "sg:phone":"+32 55 33 46 38",
    "sg:postcode":"9700",
    "sg:province":"Oost-Vlaanderen",
    "wof:name":"Multimediart",
    "wof:placetype":"venue"
},
  "geometry": {"coordinates":[3.5923829079,50.8522720337],"type":"Point"}
}