{
  "type": "Feature",
  "properties": {
    "addr:full":"Huidevettersstraat 50 Antwerpen Antwerpen 2000",
    "addr:housenumber":"50",
    "addr:postcode":"2000",
    "addr:street":"Huidevettersstraat",
    "iso:country":"BE",
    "sg:address":"Huidevettersstraat 50",
    "sg:city":"Antwerpen",
    "sg:classifiers":[
        {
            "category":"Government",
            "subcategory":"Post Office",
            "type":"Public Place"
        }
    ],
    "sg:phone":"+32 2 344 44 35",
    "sg:postcode":"2000",
    "sg:province":"Antwerpen",
    "sg:tags":[
        "box",
        "mail"
    ],
    "wof:name":"Novia Bvba",
    "wof:placetype":"venue"
},
  "geometry": {"coordinates":[4.4051508904,51.2164955139],"type":"Point"}
}