{
  "type": "Feature",
  "properties": {
    "addr:full":"Avenue Georges Henri 501 Sint-lambrechts-woluwe/woluwe-saint-lambert Bruxelles-Capitale 1200",
    "addr:housenumber":"501;/",
    "addr:postcode":"1200",
    "addr:street":"Avenue Georges Henri;Sint-Lambrechts-Woluwe",
    "iso:country":"BE",
    "sg:address":"Avenue Georges Henri 501",
    "sg:city":"Sint-lambrechts-woluwe/woluwe-saint-lambert",
    "sg:orig_category":"Eclairage et \u00e9quipements du foyer",
    "sg:phone":"+32 2 734 51 14",
    "sg:postcode":"1200",
    "sg:province":"Bruxelles-Capitale",
    "wof:name":"Maison Indigo Paprika",
    "wof:placetype":"venue"
},
  "geometry": {"coordinates":[4.4028859138,50.8413391113],"type":"Point"}
}