{
  "type": "Feature",
  "properties": {
    "iso:country":"BE",
    "sg:address":"Bellevaux 55",
    "sg:city":"Malmedy (bellevaux-lignueville)",
    "sg:classifiers":[
        {
            "category":"Real Estate",
            "subcategory":"Real Estate Services",
            "type":"Services"
        }
    ],
    "sg:phone":"+32 80 77 04 09",
    "sg:postcode":"4960",
    "sg:province":"Li\u00e8ge",
    "wof:name":"Ardennes Refuges",
    "wof:placetype":"venue"
},
  "geometry": {"coordinates":[6.0038452148,50.3967475891],"type":"Point"}
}