{
  "type": "Feature",
  "properties": {
    "addr:full":"Rue Des Martyrs 17 Verviers Li\u00e8ge 4800",
    "addr:housenumber":"17",
    "addr:postcode":"4800",
    "addr:street":"Rue Des Martyrs",
    "iso:country":"BE",
    "sg:address":"Rue Des Martyrs 17",
    "sg:city":"Verviers",
    "sg:classifiers":[
        {
            "category":"Health Services",
            "subcategory":"Dentist",
            "type":"Services"
        }
    ],
    "sg:phone":"+32 87 33 50 20",
    "sg:postcode":"4800",
    "sg:province":"Li\u00e8ge",
    "wof:name":"Tiquet Pierre",
    "wof:placetype":"venue"
},
  "geometry": {"coordinates":[5.86292696,50.5919570923],"type":"Point"}
}