{
  "type": "Feature",
  "properties": {
    "iso:country":"BE",
    "sg:address":"Avenue D'al\u00c8s 10-12",
    "sg:city":"Herstal",
    "sg:orig_category":"Dakwerken Loodgieterij, verwarming and sanitaire installaties",
    "sg:phone":"+32 4 264 32 30",
    "sg:postcode":"4040",
    "sg:province":"Li\u00e8ge",
    "wof:name":"Noriega",
    "wof:placetype":"venue"
},
  "geometry": {"coordinates":[5.6261019707,50.6709251404],"type":"Point"}
}