{
  "type": "Feature",
  "properties": {
    "addr:full":"Avenue Marcel Thiry 12 Sint-lambrechts-woluwe/woluwe-saint-lambert Bruxelles-Capitale 1200",
    "addr:housenumber":"12",
    "addr:postcode":"1200",
    "addr:street":"Avenue Marcel Thiry",
    "iso:country":"BE",
    "sg:address":"Avenue Marcel Thiry 12",
    "sg:city":"Sint-lambrechts-woluwe/woluwe-saint-lambert",
    "sg:orig_category":"Rev\u00eatements pour sols and murs. Peinture",
    "sg:phone":"+32 2 762 60 66",
    "sg:postcode":"1200",
    "sg:province":"Bruxelles-Capitale",
    "wof:name":"Anne Odvart D\u00c9coration",
    "wof:placetype":"venue"
},
  "geometry": {"coordinates":[4.4424939156,50.8544845581],"type":"Point"}
}