{
  "type": "Feature",
  "properties": {
    "addr:full":"Bergensesteenweg 480 Halle (groot) Vlaams-Brabant 1500",
    "addr:housenumber":"480;1500",
    "addr:street":"Bergensesteenweg;Groot Vlaams-Brabant",
    "iso:country":"BE",
    "sg:address":"Bergensesteenweg 480",
    "sg:city":"Halle (groot)",
    "sg:orig_category":"Artiesten and kunstenaars",
    "sg:phone":"+32 2 356 52 75",
    "sg:postcode":"1500",
    "sg:province":"Vlaams-Brabant",
    "wof:name":"Colruyt C Wed",
    "wof:placetype":"venue"
},
  "geometry": {"coordinates":[4.2246208191,50.7206726074],"type":"Point"}
}