{
  "type": "Feature",
  "properties": {
    "addr:full":"Rue Du Chemin De Fer 1 Chimay (saint-remy) Hainaut 6460",
    "addr:housenumber":"1",
    "addr:postcode":"6460",
    "addr:street":"Rue Du Chemin De Fer",
    "iso:country":"BE",
    "sg:address":"Rue Du Chemin De Fer 1",
    "sg:city":"Chimay (saint-remy)",
    "sg:classifiers":[
        {
            "category":"Health Services",
            "subcategory":"Health Practitioner",
            "type":"Services"
        }
    ],
    "sg:phone":"+32 60 21 22 85",
    "sg:postcode":"6460",
    "sg:province":"Hainaut",
    "sg:tags":[
        "physiotherapist"
    ],
    "wof:name":"Lurkin Alex",
    "wof:placetype":"venue"
},
  "geometry": {"coordinates":[4.2975921631,50.0435943604],"type":"Point"}
}