{
  "type": "Feature",
  "properties": {
    "addr:full":"Hendrik Consciencelaan 261 Evere/evere Bruxelles-Capitale 1140",
    "addr:housenumber":"261",
    "addr:postcode":"1140",
    "addr:street":"Hendrik Consciencelaan",
    "iso:country":"BE",
    "sg:address":"Hendrik Consciencelaan 261",
    "sg:city":"Evere/evere",
    "sg:orig_category":"Artsen and specialisten",
    "sg:phone":"+32 2 242 10 71",
    "sg:postcode":"1140",
    "sg:province":"Bruxelles-Capitale",
    "wof:name":"Egide Jongenelen",
    "wof:placetype":"venue"
},
  "geometry": {"coordinates":[4.4026789665,50.8741073608],"type":"Point"}
}