{
  "type": "Feature",
  "properties": {
    "addr:full":"Rue Camille Joset 2 Tintigny (rossignol) Luxembourg 6730",
    "addr:housenumber":"2",
    "addr:postcode":"6730",
    "addr:street":"Rue Camille Joset",
    "iso:country":"BE",
    "sg:address":"Rue Camille Joset 2",
    "sg:city":"Tintigny (rossignol)",
    "sg:classifiers":[
        {
            "category":"Organizations",
            "subcategory":"Community Association",
            "type":"Services"
        }
    ],
    "sg:phone":"+32 63 41 31 20",
    "sg:postcode":"6730",
    "sg:province":"Luxembourg",
    "sg:tags":[
        "cultural"
    ],
    "wof:name":"Centre Culturel Rossignol",
    "wof:placetype":"venue"
},
  "geometry": {"coordinates":[5.4857988358,49.7170906067],"type":"Point"}
}