{
  "type": "Feature",
  "properties": {
    "iso:country":"BE",
    "sg:address":"Meersbloem 20",
    "sg:city":"Oudenaarde",
    "sg:orig_category":"Rev\u00eatements de sols and murs",
    "sg:phone":"+32 55 33 59 11",
    "sg:postcode":"9700",
    "sg:province":"Oost-Vlaanderen",
    "wof:name":"Gilleman Dirk",
    "wof:placetype":"venue"
},
  "geometry": {"coordinates":[3.5910100937,50.8339118958],"type":"Point"}
}