{
  "type": "Feature",
  "properties": {
    "iso:country":"BE",
    "sg:address":"Doolhoflaan 42",
    "sg:city":"Mortsel",
    "sg:orig_category":"Experts-comptables",
    "sg:phone":"+32 3 449 15 19",
    "sg:postcode":"2640",
    "sg:province":"Antwerpen",
    "wof:name":"Paul Cools",
    "wof:placetype":"venue"
},
  "geometry": {"coordinates":[4.445526123,51.1656227112],"type":"Point"}
}