{
  "type": "Feature",
  "properties": {
    "addr:full":"Ninovesteenweg 85/b Aalst (groot) Oost-Vlaanderen 9320",
    "addr:housenumber":"85 / b",
    "addr:postcode":"9320",
    "addr:street":"Ninovesteenweg;Groot Oost-Vlaanderen",
    "iso:country":"BE",
    "sg:address":"Ninovesteenweg 85/b",
    "sg:city":"Aalst (groot)",
    "sg:orig_category":"Binnenhuisarchitecten",
    "sg:phone":"+32 53 41 07 20",
    "sg:postcode":"9320",
    "sg:province":"Oost-Vlaanderen",
    "wof:name":"Splinter",
    "wof:placetype":"venue"
},
  "geometry": {"coordinates":[4.0553851128,50.9209976196],"type":"Point"}
}