{
  "type": "Feature",
  "properties": {
    "addr:full":"Private Dreef 16 Meise Vlaams-Brabant 1860",
    "addr:housenumber":"16",
    "addr:postcode":"1860",
    "addr:street":"Private Dreef",
    "iso:country":"BE",
    "sg:address":"Private Dreef 16",
    "sg:city":"Meise",
    "sg:orig_category":"M\u00e9decins and sp\u00e9cialistes",
    "sg:phone":"+32 2 269 09 76",
    "sg:postcode":"1860",
    "sg:province":"Vlaams-Brabant",
    "wof:name":"F. Van Oost",
    "wof:placetype":"venue"
},
  "geometry": {"coordinates":[4.3394870758,50.9287147522],"type":"Point"}
}