{
  "type": "Feature",
  "properties": {
    "iso:country":"BE",
    "sg:address":"Statiestraat 3-5",
    "sg:city":"Antwerpen",
    "sg:classifiers":[
        {
            "category":"Restaurant",
            "type":"Food & Drink"
        }
    ],
    "sg:phone":"+32 3 231 63 53",
    "sg:postcode":"2018",
    "sg:province":"Antwerpen",
    "wof:name":"Indonesia",
    "wof:placetype":"venue"
},
  "geometry": {"coordinates":[4.4183487892,51.2184791565],"type":"Point"}
}