{
  "type": "Feature",
  "properties": {
    "addr:full":"Stationsstraat 20 Leopoldsburg Limburg 3970",
    "addr:housenumber":"20",
    "addr:postcode":"3970",
    "addr:street":"Stationsstraat",
    "iso:country":"BE",
    "sg:address":"Stationsstraat 20",
    "sg:city":"Leopoldsburg",
    "sg:classifiers":[
        {
            "category":"Shopping",
            "subcategory":"Baby Store",
            "type":"Retail Goods"
        }
    ],
    "sg:phone":"+32 11 34 83 57",
    "sg:postcode":"3970",
    "sg:province":"Limburg",
    "sg:tags":[
        "-",
        "accessory"
    ],
    "wof:name":"Babytrends",
    "wof:placetype":"venue"
},
  "geometry": {"coordinates":[5.2618551254,51.1176681519],"type":"Point"}
}