{
  "type": "Feature",
  "properties": {
    "iso:country":"BE",
    "sg:address":"Chauss\u00c9e De Charleroi 33ba",
    "sg:city":"Genappe",
    "sg:orig_category":"Landmeters",
    "sg:phone":"+32 67 78 07 43",
    "sg:postcode":"1471",
    "sg:province":"Brabant Wallon",
    "wof:name":"Pierre Verdonck",
    "wof:placetype":"venue"
},
  "geometry": {"coordinates":[4.4520258904,50.6059341431],"type":"Point"}
}