{
  "type": "Feature",
  "properties": {
    "iso:country":"BE",
    "sg:address":"Bloemgatstraat 7a",
    "sg:city":"Meulebeke",
    "sg:orig_category":"Drukkerijen and copyshops",
    "sg:phone":"+32 51 48 61 08",
    "sg:postcode":"8760",
    "sg:province":"West-Vlaanderen",
    "wof:name":"Drukkerij Van Driessche",
    "wof:placetype":"venue"
},
  "geometry": {"coordinates":[3.2306880951,50.9503593445],"type":"Point"}
}