{
  "type": "Feature",
  "properties": {
    "addr:full":"Proostdijk 8 Diksmuide West-Vlaanderen 8600",
    "addr:housenumber":"8",
    "addr:postcode":"8600",
    "addr:street":"Proostdijk",
    "iso:country":"BE",
    "sg:address":"Proostdijk 8",
    "sg:city":"Diksmuide",
    "sg:orig_category":"Boekhouders",
    "sg:phone":"+32 51 55 58 32",
    "sg:postcode":"8600",
    "sg:province":"West-Vlaanderen",
    "wof:name":"Philippe Braet",
    "wof:placetype":"venue"
},
  "geometry": {"coordinates":[2.787391901,51.0921783447],"type":"Point"}
}