{
  "type": "Feature",
  "properties": {
    "iso:country":"BE",
    "sg:address":"Rue Du Surtia 1",
    "sg:city":"La Bruy\u00c8re",
    "sg:classifiers":[
        {
            "category":"Arena",
            "subcategory":"Sports Club",
            "type":"Entertainment"
        }
    ],
    "sg:phone":"+32 81 56 78 40",
    "sg:postcode":"5081",
    "sg:province":"Namur",
    "sg:tags":[
        "de"
    ],
    "wof:name":"J.c. Saint-denis",
    "wof:placetype":"venue"
},
  "geometry": {"coordinates":[4.7726898193,50.5403900146],"type":"Point"}
}