{
  "type": "Feature",
  "properties": {
    "iso:country":"BE",
    "sg:address":"Kribbestraat 13",
    "sg:city":"Antwerpen",
    "sg:orig_category":"Assembling, Disassembling",
    "sg:phone":"+32 3 646 30 30",
    "sg:postcode":"2000",
    "sg:province":"Antwerpen",
    "wof:name":"Van Den Broeck & Co Verhuizingen B.v.b.a.",
    "wof:placetype":"venue"
},
  "geometry": {"coordinates":[4.4102897644,51.2303771973],"type":"Point"}
}