{
  "type": "Feature",
  "properties": {
    "iso:country":"BE",
    "sg:address":"Engelstraat 130",
    "sg:city":"Ichtegem",
    "sg:classifiers":[
        {
            "category":"Professional",
            "type":"Services"
        }
    ],
    "sg:phone":"+32 51 58 29 37",
    "sg:postcode":"8480",
    "sg:province":"West-Vlaanderen",
    "sg:tags":[
        "ceremony",
        "master"
    ],
    "wof:name":"Beernaert Luc",
    "wof:placetype":"venue"
},
  "geometry": {"coordinates":[3.0235080719,51.0965042114],"type":"Point"}
}