{
  "type": "Feature",
  "properties": {
    "addr:full":"Kasteelstraat 80 Buggenhout Oost-Vlaanderen 9255",
    "addr:housenumber":"80",
    "addr:postcode":"9255",
    "addr:street":"Kasteelstraat",
    "iso:country":"BE",
    "sg:address":"Kasteelstraat 80",
    "sg:city":"Buggenhout",
    "sg:classifiers":[
        {
            "category":"Freight",
            "type":"Transportation"
        }
    ],
    "sg:phone":"+32 52 33 48 70",
    "sg:postcode":"9255",
    "sg:province":"Oost-Vlaanderen",
    "sg:tags":[
        "-",
        "transport"
    ],
    "wof:name":"Van Zeebroeck W",
    "wof:placetype":"venue"
},
  "geometry": {"coordinates":[4.2045359612,51.0099601746],"type":"Point"}
}