{
  "type": "Feature",
  "properties": {
    "iso:country":"BE",
    "sg:address":"Bremveldstraat 5",
    "sg:city":"Herent",
    "sg:orig_category":"Schoonmaakbedrijven and ongediertebestrijding",
    "sg:phone":"+32 16 20 28 23",
    "sg:postcode":"3020",
    "sg:province":"Vlaams-Brabant",
    "wof:name":"Sunver",
    "wof:placetype":"venue"
},
  "geometry": {"coordinates":[4.6643419266,50.9051322937],"type":"Point"}
}