{
  "type": "Feature",
  "properties": {
    "iso:country":"BE",
    "sg:address":"Rue Beckers 19",
    "sg:city":"Etterbeek/etterbeek",
    "sg:orig_category":"Secr\u00e9tariats",
    "sg:phone":"+32 2 640 32 11",
    "sg:postcode":"1040",
    "sg:province":"Bruxelles-Capitale",
    "wof:name":"Procompo",
    "wof:placetype":"venue"
},
  "geometry": {"coordinates":[4.3879737854,50.8286399841],"type":"Point"}
}