{
  "type": "Feature",
  "properties": {
    "iso:country":"BE",
    "sg:address":"Dr\u00c8ve De L'infante 77",
    "sg:city":"Waterloo",
    "sg:orig_category":"Instellingen voor mindervalide volwassenen",
    "sg:phone":"+32 2 354 37 23",
    "sg:postcode":"1410",
    "sg:province":"Brabant Wallon",
    "wof:name":"I.m.p. La Cl\u00c9 Des Champs",
    "wof:placetype":"venue"
},
  "geometry": {"coordinates":[4.3832950592,50.7108192444],"type":"Point"}
}