{
  "type": "Feature",
  "properties": {
    "iso:country":"BE",
    "sg:address":"Stationsdreef 76",
    "sg:city":"Roeselare",
    "sg:classifiers":[
        {
            "category":"Food & Beverages",
            "subcategory":"Fruits & Vegetables",
            "type":"Retail Goods"
        }
    ],
    "sg:phone":"+32 51 20 25 05",
    "sg:postcode":"8800",
    "sg:province":"West-Vlaanderen",
    "sg:tags":[
        "groenten"
    ],
    "wof:name":"De Fruitkorf",
    "wof:placetype":"venue"
},
  "geometry": {"coordinates":[3.1279189587,50.9537506104],"type":"Point"}
}