{
  "type": "Feature",
  "properties": {
    "iso:country":"BE",
    "sg:address":"Reties Heike 19",
    "sg:city":"Kasterlee",
    "sg:orig_category":"Rundveehouders",
    "sg:phone":"+32 14 37 75 81",
    "sg:postcode":"2460",
    "sg:province":"Antwerpen",
    "wof:name":"Velka",
    "wof:placetype":"venue"
},
  "geometry": {"coordinates":[5.0249857903,51.2535858154],"type":"Point"}
}