{
  "type": "Feature",
  "properties": {
    "addr:full":"Kasteelstraat 64i Heist-op-den-berg Antwerpen 2220",
    "addr:housenumber":"64i",
    "addr:postcode":"2220",
    "addr:street":"Kasteelstraat",
    "iso:country":"BE",
    "sg:address":"Kasteelstraat 64i",
    "sg:city":"Heist-op-den-berg",
    "sg:classifiers":[
        {
            "category":"Professional",
            "subcategory":"Lawyer & Legal Services",
            "type":"Services"
        }
    ],
    "sg:phone":"+32 15 33 15 55",
    "sg:postcode":"2220",
    "sg:province":"Antwerpen",
    "wof:name":"Janssens Ingrid",
    "wof:placetype":"venue"
},
  "geometry": {"coordinates":[4.7111978531,51.0672569275],"type":"Point"}
}