{
  "type": "Feature",
  "properties": {
    "addr:full":"Schoordijkweg 0 Brecht Antwerpen 2960",
    "addr:housenumber":"0",
    "addr:postcode":"2960",
    "addr:street":"Schoordijkweg",
    "iso:country":"BE",
    "sg:address":"Schoordijkweg 0",
    "sg:city":"Brecht",
    "sg:orig_category":"DIVERSE RECREATIEVE ACTIVITEITEN",
    "sg:phone":"+32 3 325 78 10",
    "sg:postcode":"2960",
    "sg:province":"Antwerpen",
    "wof:name":"Golden Wings",
    "wof:placetype":"venue"
},
  "geometry": {"coordinates":[4.6074848175,51.3501930237],"type":"Point"}
}