{
  "type": "Feature",
  "properties": {
    "addr:full":"Route De Mons 13 Binche Hainaut 7130",
    "addr:housenumber":"13",
    "addr:postcode":"7130",
    "addr:street":"Route De Mons",
    "iso:country":"BE",
    "sg:address":"Route De Mons 13",
    "sg:city":"Binche",
    "sg:orig_category":"Pain, p\u00e2tisseries and confiseries",
    "sg:phone":"+32 64 33 24 65",
    "sg:postcode":"7130",
    "sg:province":"Hainaut",
    "wof:name":"P\u00c2tisserie Dequenne",
    "wof:placetype":"venue"
},
  "geometry": {"coordinates":[4.1655550003,50.4125366211],"type":"Point"}
}