{
  "type": "Feature",
  "properties": {
    "addr:full":"Varkensmarkt 70 Diepenbeek Limburg 3590",
    "addr:housenumber":"70",
    "addr:postcode":"3590",
    "addr:street":"Varkensmarkt",
    "iso:country":"BE",
    "sg:address":"Varkensmarkt 70",
    "sg:city":"Diepenbeek",
    "sg:orig_category":"Pain, p\u00e2tisseries and confiseries",
    "sg:phone":"+32 11 32 30 35",
    "sg:postcode":"3590",
    "sg:province":"Limburg",
    "wof:name":"Koelen",
    "wof:placetype":"venue"
},
  "geometry": {"coordinates":[5.4173002243,50.9069404602],"type":"Point"}
}