{
  "type": "Feature",
  "properties": {
    "iso:country":"BE",
    "sg:address":"Lombardenvest 54",
    "sg:city":"Antwerpen",
    "sg:orig_category":"V\u00eatements pour b\u00e9b\u00e9s and enfants",
    "sg:phone":"+32 3 213 22 33",
    "sg:postcode":"2000",
    "sg:province":"Antwerpen",
    "wof:name":"Huis Puzzles",
    "wof:placetype":"venue"
},
  "geometry": {"coordinates":[4.4028940201,51.2173309326],"type":"Point"}
}