{
  "type": "Feature",
  "properties": {
    "iso:country":"BE",
    "sg:address":"Koning Albertstraat 102",
    "sg:city":"Lint",
    "sg:classifiers":[
        {
            "category":"Health Services",
            "subcategory":"Health Practitioner",
            "type":"Services"
        }
    ],
    "sg:phone":"+32 3 454 31 95",
    "sg:postcode":"2547",
    "sg:province":"Antwerpen",
    "sg:tags":[
        "physiotherapist"
    ],
    "wof:name":"Janssens Machteld",
    "wof:placetype":"venue"
},
  "geometry": {"coordinates":[4.4919381142,51.1280937195],"type":"Point"}
}