{
  "type": "Feature",
  "properties": {
    "iso:country":"BE",
    "sg:address":"Oudestraat 47",
    "sg:city":"Aartselaar",
    "sg:classifiers":[
        {
            "category":"Wholesale",
            "subcategory":"Plants",
            "type":"Manufacturing & Wholesale Goods"
        }
    ],
    "sg:phone":"+32 3 887 40 64",
    "sg:postcode":"2630",
    "sg:province":"Antwerpen",
    "sg:tags":[
        "machine",
        "industrial",
        "automation"
    ],
    "wof:name":"Edd B.v.b.a.",
    "wof:placetype":"venue"
},
  "geometry": {"coordinates":[4.3838891983,51.1444816589],"type":"Point"}
}