{
  "type": "Feature",
  "properties": {
    "addr:full":"Vrijbosstraat 25 Staden West-Vlaanderen 8840",
    "addr:housenumber":"25",
    "addr:postcode":"8840",
    "addr:street":"Vrijbosstraat",
    "iso:country":"BE",
    "sg:address":"Vrijbosstraat 25",
    "sg:city":"Staden",
    "sg:classifiers":[
        {
            "category":"Shopping",
            "subcategory":"Antiques",
            "type":"Retail Goods"
        }
    ],
    "sg:phone":"+32 51 70 07 62",
    "sg:postcode":"8840",
    "sg:province":"West-Vlaanderen",
    "sg:tags":[
        "restoration"
    ],
    "wof:name":"Mutsaert (de)",
    "wof:placetype":"venue"
},
  "geometry": {"coordinates":[2.9702839851,50.9793434143],"type":"Point"}
}