{
  "type": "Feature",
  "properties": {
    "iso:country":"BE",
    "sg:address":"Provinciale Baan 37",
    "sg:city":"Beveren (vrasene)",
    "sg:classifiers":[
        {
            "category":"Retail",
            "subcategory":"Auto Repair",
            "type":"Services"
        }
    ],
    "sg:phone":"+32 3 775 95 94",
    "sg:postcode":"9120",
    "sg:province":"Oost-Vlaanderen",
    "sg:tags":[
        "garage"
    ],
    "wof:name":"Nys",
    "wof:placetype":"venue"
},
  "geometry": {"coordinates":[4.2574100494,51.2131843567],"type":"Point"}
}