{
  "type": "Feature",
  "properties": {
    "addr:full":"Jezusstraat 48 Antwerpen Antwerpen 2000",
    "addr:housenumber":"48",
    "addr:postcode":"2000",
    "addr:street":"Jezusstraat",
    "iso:country":"BE",
    "sg:address":"Jezusstraat 48",
    "sg:city":"Antwerpen",
    "sg:orig_category":"Tijdelijke werkgelegenheid and uitzendkantoren",
    "sg:phone":"+32 3 212 16 00",
    "sg:postcode":"2000",
    "sg:province":"Antwerpen",
    "wof:name":"Plus Uitzendkrachten",
    "wof:placetype":"venue"
},
  "geometry": {"coordinates":[4.4148907661,51.2196388245],"type":"Point"}
}