{
  "type": "Feature",
  "properties": {
    "iso:country":"BE",
    "sg:address":"Van De Wervestraat 16",
    "sg:city":"Antwerpen",
    "sg:classifiers":[
        {
            "category":"Professional",
            "type":"Services"
        }
    ],
    "sg:phone":"+32 3 226 62 96",
    "sg:postcode":"2060",
    "sg:province":"Antwerpen",
    "sg:tags":[
        "aux",
        "diver",
        "personnes"
    ],
    "wof:name":"Esser F.",
    "wof:placetype":"venue"
},
  "geometry": {"coordinates":[4.4153370857,51.2288551331],"type":"Point"}
}