{
  "type": "Feature",
  "properties": {
    "addr:full":"Dokter Verdurmenstraat 26 Sint-niklaas Oost-Vlaanderen 9100",
    "addr:housenumber":"26",
    "addr:postcode":"9100",
    "addr:street":"Dokter Verdurmenstraat",
    "iso:country":"BE",
    "sg:address":"Dokter Verdurmenstraat 26",
    "sg:city":"Sint-niklaas",
    "sg:classifiers":[
        {
            "category":"Health Services",
            "subcategory":"Doctor",
            "type":"Services"
        }
    ],
    "sg:phone":"+32 3 776 49 85",
    "sg:postcode":"9100",
    "sg:province":"Oost-Vlaanderen",
    "sg:tags":[
        "medicinephysicians",
        "surgeon"
    ],
    "wof:name":"Huyghe Jacques",
    "wof:placetype":"venue"
},
  "geometry": {"coordinates":[4.1428608894,51.1675682068],"type":"Point"}
}