{
  "type": "Feature",
  "properties": {
    "iso:country":"BE",
    "sg:address":"Grand Place 0",
    "sg:city":"Braine-le-comte",
    "sg:orig_category":"Openbare bibliotheken and archieven",
    "sg:phone":"+32 65 31 13 49",
    "sg:postcode":"7090",
    "sg:province":"Hainaut",
    "wof:name":"Discobus",
    "wof:placetype":"venue"
},
  "geometry": {"coordinates":[4.1367778778,50.6107292175],"type":"Point"}
}