{
  "type": "Feature",
  "properties": {
    "iso:country":"BE",
    "sg:address":"Heidestraat 45",
    "sg:city":"Sint-gillis-waas (de Klinge)",
    "sg:classifiers":[
        {
            "category":"Bakery",
            "type":"Food & Drink"
        }
    ],
    "sg:phone":"+32 3 770 57 59",
    "sg:postcode":"9170",
    "sg:province":"Oost-Vlaanderen",
    "sg:tags":[
        "confectioner",
        "baker"
    ],
    "wof:name":"Rombaut",
    "wof:placetype":"venue"
},
  "geometry": {"coordinates":[4.0863909721,51.2535858154],"type":"Point"}
}