{
  "type": "Feature",
  "properties": {
    "addr:full":"Place Albert Ier 10 Anderlues Hainaut 6150",
    "addr:housenumber":"10",
    "addr:postcode":"6150",
    "addr:street":"Place Albert Ier",
    "iso:country":"BE",
    "sg:address":"Place Albert Ier 10",
    "sg:city":"Anderlues",
    "sg:orig_category":"Banken and kredietinstellingen",
    "sg:phone":"+32 71 52 43 61",
    "sg:postcode":"6150",
    "sg:province":"Hainaut",
    "wof:name":"Bbl",
    "wof:placetype":"venue"
},
  "geometry": {"coordinates":[4.2700490952,50.4071350098],"type":"Point"}
}