{
  "type": "Feature",
  "properties": {
    "addr:full":"Hoofdrioolstraat 37 Anderlecht/anderlecht Bruxelles-Capitale 1070",
    "addr:housenumber":"37",
    "addr:postcode":"1070",
    "addr:street":"Hoofdrioolstraat",
    "iso:country":"BE",
    "sg:address":"Hoofdrioolstraat 37",
    "sg:city":"Anderlecht/anderlecht",
    "sg:orig_category":"Schoonmaakbedrijven and ongediertebestrijding",
    "sg:phone":"+32 2 521 91 00",
    "sg:postcode":"1070",
    "sg:province":"Bruxelles-Capitale",
    "wof:name":"Rentokil",
    "wof:placetype":"venue"
},
  "geometry": {"coordinates":[4.319589138,50.8391265869],"type":"Point"}
}