{
  "type": "Feature",
  "properties": {
    "iso:country":"BE",
    "sg:address":"Rue Louis Bertrand 130",
    "sg:city":"La Louviere",
    "sg:orig_category":"Schoonheidssalons",
    "sg:phone":"+32 64 22 82 81",
    "sg:postcode":"7100",
    "sg:province":"Hainaut",
    "wof:name":"Laurence Dangriau",
    "wof:placetype":"venue"
},
  "geometry": {"coordinates":[4.1745438576,50.4698905945],"type":"Point"}
}