{
  "type": "Feature",
  "properties": {
    "iso:country":"BE",
    "sg:address":"Parochiestraat 102",
    "sg:city":"Denderleeuw (iddergem)",
    "sg:classifiers":[
        {
            "category":"Retail",
            "subcategory":"Repair Shop",
            "type":"Services"
        }
    ],
    "sg:phone":"+32 53 66 72 05",
    "sg:postcode":"9472",
    "sg:province":"Oost-Vlaanderen",
    "sg:tags":[
        "jobbing",
        "tailoring",
        "-"
    ],
    "wof:name":"Embroidery Nv",
    "wof:placetype":"venue"
},
  "geometry": {"coordinates":[4.0479860306,50.8736953735],"type":"Point"}
}