{
  "type": "Feature",
  "properties": {
    "addr:full":"Rue De Herbestal 130 Eupen Li\u00e8ge 4700",
    "addr:housenumber":"130",
    "addr:postcode":"4700",
    "addr:street":"Rue De Herbestal",
    "iso:country":"BE",
    "sg:address":"Rue De Herbestal 130",
    "sg:city":"Eupen",
    "sg:classifiers":[
        {
            "category":"Building & Trades",
            "subcategory":"Construction",
            "type":"Services"
        }
    ],
    "sg:phone":"+32 87 56 00 63",
    "sg:postcode":"4700",
    "sg:province":"Li\u00e8ge",
    "sg:tags":[
        "industrial",
        "timber"
    ],
    "wof:name":"Lance S.p.r.l.",
    "wof:placetype":"venue"
},
  "geometry": {"coordinates":[6.0166320801,50.6389007568],"type":"Point"}
}