{
  "type": "Feature",
  "properties": {
    "iso:country":"BE",
    "sg:address":"Boulevard Neuf 3",
    "sg:city":"Villers-la-ville",
    "sg:classifiers":[
        {
            "category":"Professional",
            "subcategory":"Engineering",
            "type":"Services"
        }
    ],
    "sg:phone":"+32 71 87 98 10",
    "sg:postcode":"1495",
    "sg:province":"Brabant Wallon",
    "sg:tags":[
        "environmental",
        "technique",
        "-"
    ],
    "wof:name":"B.i.p. Sc",
    "wof:placetype":"venue"
},
  "geometry": {"coordinates":[4.5370779037,50.5812149048],"type":"Point"}
}