{
  "type": "Feature",
  "properties": {
    "addr:full":"Kongostraat 40 Kuurne West-Vlaanderen 8520",
    "addr:housenumber":"40",
    "addr:postcode":"8520",
    "addr:street":"Kongostraat",
    "iso:country":"BE",
    "sg:address":"Kongostraat 40",
    "sg:city":"Kuurne",
    "sg:orig_category":"Woningbouw",
    "sg:phone":"+32 56 35 55 16",
    "sg:postcode":"8520",
    "sg:province":"West-Vlaanderen",
    "wof:name":"Walter Verno",
    "wof:placetype":"venue"
},
  "geometry": {"coordinates":[3.2673950195,50.850643158],"type":"Point"}
}