{
  "type": "Feature",
  "properties": {
    "iso:country":"BE",
    "sg:address":"Beekstraat 22",
    "sg:city":"Oostrozebeke",
    "sg:orig_category":"Transports fluviaux. Installations and terrains de sport hors centres sportifs",
    "sg:phone":"+32 56 66 79 72",
    "sg:postcode":"8780",
    "sg:province":"West-Vlaanderen",
    "wof:name":"Wsw De Wante Ingelmunster",
    "wof:placetype":"venue"
},
  "geometry": {"coordinates":[3.3464679718,50.9204673767],"type":"Point"}
}