{
  "type": "Feature",
  "properties": {
    "iso:country":"BE",
    "sg:address":"Rue Des Maies 29",
    "sg:city":"Bastogne",
    "sg:orig_category":"Algemeen secundair onderwijs",
    "sg:phone":"+32 61 21 23 61",
    "sg:postcode":"6600",
    "sg:province":"Luxembourg",
    "wof:name":"E.s.e.s. Le Mardasson",
    "wof:placetype":"venue"
},
  "geometry": {"coordinates":[5.7135100365,50.0051116943],"type":"Point"}
}