{
  "type": "Feature",
  "properties": {
    "addr:full":"Lochtstraat 20 Scherpenheuvel-zichem (testelt) Vlaams-Brabant 3272",
    "addr:housenumber":"20",
    "addr:postcode":"3272",
    "addr:street":"Lochtstraat",
    "iso:country":"BE",
    "sg:address":"Lochtstraat 20",
    "sg:city":"Scherpenheuvel-zichem (testelt)",
    "sg:classifiers":[
        {
            "category":"Health Services",
            "subcategory":"Dentist",
            "type":"Services"
        }
    ],
    "sg:phone":"+32 13 77 40 21",
    "sg:postcode":"3272",
    "sg:province":"Vlaams-Brabant",
    "wof:name":"Janssens J",
    "wof:placetype":"venue"
},
  "geometry": {"coordinates":[4.9578080177,51.0151405334],"type":"Point"}
}