{
  "type": "Feature",
  "properties": {
    "addr:full":"Hoornwerk 10 Menen West-Vlaanderen 8930",
    "addr:housenumber":"10",
    "addr:postcode":"8930",
    "addr:street":"Hoornwerk",
    "iso:country":"BE",
    "sg:address":"Hoornwerk 10",
    "sg:city":"Menen",
    "sg:classifiers":[
        {
            "category":"Shopping",
            "subcategory":"Clothing, Apparel, & Fashions",
            "type":"Retail Goods"
        }
    ],
    "sg:phone":"+32 56 51 28 32",
    "sg:postcode":"8930",
    "sg:province":"West-Vlaanderen",
    "sg:tags":[
        "boutique"
    ],
    "wof:name":"Lady Samy",
    "wof:placetype":"venue"
},
  "geometry": {"coordinates":[3.1279129982,50.7865943909],"type":"Point"}
}