{
  "type": "Feature",
  "properties": {
    "iso:country":"BE",
    "sg:address":"Nivez\u00e9 Bas 123",
    "sg:city":"Jalhay (sart)",
    "sg:classifiers":[
        {
            "category":"Professional",
            "subcategory":"Accounting & Tax Preparation",
            "type":"Services"
        }
    ],
    "sg:phone":"+32 87 77 47 97",
    "sg:postcode":"4845",
    "sg:province":"Li\u00e8ge",
    "sg:tags":[
        "bookkeeper"
    ],
    "wof:name":"G\u00e9rard J-m",
    "wof:placetype":"venue"
},
  "geometry": {"coordinates":[5.8996210098,50.5005378723],"type":"Point"}
}