{
  "type": "Feature",
  "properties": {
    "iso:country":"BE",
    "sg:address":"Charles Ampestraat 4b",
    "sg:city":"Staden",
    "sg:classifiers":[
        {
            "category":"Insurance",
            "subcategory":"Insurance Agent",
            "type":"Services"
        }
    ],
    "sg:phone":"+32 51 70 46 10",
    "sg:postcode":"8840",
    "sg:province":"West-Vlaanderen",
    "sg:tags":[
        "broker"
    ],
    "wof:name":"Buro Ryon Cv",
    "wof:placetype":"venue"
},
  "geometry": {"coordinates":[3.0106720924,50.9791984558],"type":"Point"}
}