{
  "type": "Feature",
  "properties": {
    "addr:full":"Sander De Vosstraat 32 Lier (koningshooikt) Antwerpen 2500",
    "addr:housenumber":"32",
    "addr:postcode":"2500",
    "addr:street":"Sander De Vosstraat",
    "iso:country":"BE",
    "sg:address":"Sander De Vosstraat 32",
    "sg:city":"Lier (koningshooikt)",
    "sg:classifiers":[
        {
            "category":"Health Services",
            "subcategory":"Health Practitioner",
            "type":"Services"
        }
    ],
    "sg:phone":"+32 3 482 32 13",
    "sg:postcode":"2500",
    "sg:province":"Antwerpen",
    "sg:tags":[
        "physiotherapist"
    ],
    "wof:name":"Van Rompay Jef",
    "wof:placetype":"venue"
},
  "geometry": {"coordinates":[4.6146798134,51.0921592712],"type":"Point"}
}