{
  "type": "Feature",
  "properties": {
    "iso:country":"BE",
    "sg:address":"Muntstraat 11",
    "sg:city":"Mechelen",
    "sg:classifiers":[
        {
            "category":"Home & Garden",
            "subcategory":"Furniture",
            "type":"Retail Goods"
        }
    ],
    "sg:phone":"+32 15 29 01 28",
    "sg:postcode":"2800",
    "sg:province":"Antwerpen",
    "sg:tags":[
        "-"
    ],
    "wof:name":"De Tuinen Van Eva",
    "wof:placetype":"venue"
},
  "geometry": {"coordinates":[4.4835700989,51.0269775391],"type":"Point"}
}