{
  "type": "Feature",
  "properties": {
    "iso:country":"BE",
    "sg:address":"Rue Des Palais 18",
    "sg:city":"Schaarbeek/schaerbeek",
    "sg:orig_category":"Biens d'occasion",
    "sg:phone":"+32 2 217 62 59",
    "sg:postcode":"1030",
    "sg:province":"Bruxelles-Capitale",
    "wof:name":"Carlo Lorenzet",
    "wof:placetype":"venue"
},
  "geometry": {"coordinates":[4.3680047989,50.8590812683],"type":"Point"}
}