{
  "type": "Feature",
  "properties": {
    "iso:country":"BE",
    "sg:address":"Basse Cour 4",
    "sg:city":"Bassenge (wonck)",
    "sg:classifiers":[
        {
            "category":"Parking",
            "subcategory":"Garage",
            "type":"Transportation"
        }
    ],
    "sg:phone":"+32 4 351 89 29",
    "sg:postcode":"4690",
    "sg:province":"Li\u00e8ge",
    "sg:tags":[
        "truck",
        "-",
        "dump",
        "transport"
    ],
    "wof:name":"Transports Leclercq",
    "wof:placetype":"venue"
},
  "geometry": {"coordinates":[5.6296448708,50.7686271667],"type":"Point"}
}