{
  "type": "Feature",
  "properties": {
    "addr:full":"Rue De La Station Braine-le-comte Hainaut 7090",
    "addr:postcode":"7090",
    "addr:street":"Rue De La Station;Hainaut",
    "iso:country":"BE",
    "sg:address":"Rue De La Station",
    "sg:city":"Braine-le-comte",
    "sg:orig_category":"Royal Canin. Animaux domestiques and accessoires",
    "sg:phone":"+32 67 55 36 19",
    "sg:postcode":"7090",
    "sg:province":"Hainaut",
    "wof:name":"Allard Michael",
    "wof:placetype":"venue"
},
  "geometry": {"coordinates":[4.1375880241,50.6083946228],"type":"Point"}
}