{
  "type": "Feature",
  "properties": {
    "addr:full":"Stationsstraat 1 Hechtel-eksel Limburg 3941",
    "addr:housenumber":"1",
    "addr:postcode":"3941",
    "addr:street":"Stationsstraat",
    "iso:country":"BE",
    "sg:address":"Stationsstraat 1",
    "sg:city":"Hechtel-eksel",
    "sg:orig_category":"Diverse bedrijfsbeheeradviesbureaus",
    "sg:phone":"+32 11 73 49 00",
    "sg:postcode":"3941",
    "sg:province":"Limburg",
    "wof:name":"C.m.c",
    "wof:placetype":"venue"
},
  "geometry": {"coordinates":[5.395884037,51.15467453],"type":"Point"}
}