{
  "type": "Feature",
  "properties": {
    "iso:country":"BE",
    "sg:address":"Tieltstraat 22",
    "sg:city":"Dentergem (markegem)",
    "sg:classifiers":[
        {
            "category":"Professional",
            "subcategory":"Management & Consulting",
            "type":"Services"
        }
    ],
    "sg:phone":"+32 51 63 43 31",
    "sg:postcode":"8720",
    "sg:province":"West-Vlaanderen",
    "sg:tags":[
        "consultant",
        "agency",
        "advertising"
    ],
    "wof:name":"Makin' Memories",
    "wof:placetype":"venue"
},
  "geometry": {"coordinates":[3.3802559376,50.9494018555],"type":"Point"}
}