{
  "type": "Feature",
  "properties": {
    "addr:full":"Chauss\u00c9e De Dinant 193 Namur Namur 5100",
    "addr:housenumber":"193",
    "addr:postcode":"5100",
    "addr:street":"Chausse\u0301E De Dinant",
    "iso:country":"BE",
    "sg:address":"Chauss\u00c9e De Dinant 193",
    "sg:city":"Namur",
    "sg:orig_category":"Benzinestations and brandstoffen",
    "sg:phone":"+32 81 46 08 61",
    "sg:postcode":"5100",
    "sg:province":"Namur",
    "wof:name":"Shell",
    "wof:placetype":"venue"
},
  "geometry": {"coordinates":[4.8639001846,50.4321212769],"type":"Point"}
}