{
  "type": "Feature",
  "properties": {
    "iso:country":"BE",
    "sg:address":"Rue Des Sabli\u00e8res 178",
    "sg:city":"Ch\u00e2telet",
    "sg:classifiers":[
        {
            "category":"Banks & Credit Unions",
            "subcategory":"Investment Brokerage",
            "type":"Services"
        }
    ],
    "sg:phone":"+32 71 39 68 14",
    "sg:postcode":"6200",
    "sg:province":"Hainaut",
    "sg:tags":[
        "repair",
        "-",
        "installation",
        "sanitary",
        "article"
    ],
    "wof:name":"Strimelle C Ets",
    "wof:placetype":"venue"
},
  "geometry": {"coordinates":[4.533176899,50.395072937],"type":"Point"}
}