{
  "type": "Feature",
  "properties": {
    "iso:country":"BE",
    "sg:address":"Sterrestraat 203",
    "sg:city":"Lokeren",
    "sg:orig_category":"Rabbit Hair, Mordant-Dyed",
    "sg:phone":"+32 9 348 20 67",
    "sg:postcode":"9160",
    "sg:province":"Oost-Vlaanderen",
    "wof:name":"Belskin Nv",
    "wof:placetype":"venue"
},
  "geometry": {"coordinates":[3.9856250286,51.0950469971],"type":"Point"}
}