{
  "type": "Feature",
  "properties": {
    "addr:full":"Odrimont 30 Lierneux Li\u00e8ge 4990",
    "addr:housenumber":"30",
    "addr:postcode":"4990",
    "addr:street":"Odrimont",
    "iso:country":"BE",
    "sg:address":"Odrimont 30",
    "sg:city":"Lierneux",
    "sg:orig_category":"P\u00e9pini\u00e9ristes",
    "sg:phone":"+32 80 31 82 02",
    "sg:postcode":"4990",
    "sg:province":"Li\u00e8ge",
    "wof:name":"Serge Demoulin",
    "wof:placetype":"venue"
},
  "geometry": {"coordinates":[5.8094182014,50.3095016479],"type":"Point"}
}