{
  "type": "Feature",
  "properties": {
    "addr:full":"Schransstraat 60 Grobbendonk Antwerpen 2280",
    "addr:housenumber":"60",
    "addr:postcode":"2280",
    "addr:street":"Schransstraat",
    "iso:country":"BE",
    "sg:address":"Schransstraat 60",
    "sg:city":"Grobbendonk",
    "sg:classifiers":[
        {
            "category":"Arena",
            "subcategory":"Sports Club",
            "type":"Entertainment"
        }
    ],
    "sg:phone":"+32 14 51 12 10",
    "sg:postcode":"2280",
    "sg:province":"Antwerpen",
    "sg:tags":[
        "terrain",
        "hors",
        "de",
        "installation",
        "sportifs"
    ],
    "wof:name":"K.f.c. Grobbendonk",
    "wof:placetype":"venue"
},
  "geometry": {"coordinates":[4.7439608574,51.1940498352],"type":"Point"}
}