{
  "type": "Feature",
  "properties": {
    "addr:full":"Chauss\u00c9e De Chokier 55 Fl\u00c9malle Li\u00e8ge 4400",
    "addr:housenumber":"55",
    "addr:postcode":"4400",
    "addr:street":"Chausse\u0301E De Chokier",
    "iso:country":"BE",
    "sg:address":"Chauss\u00c9e De Chokier 55",
    "sg:city":"Fl\u00c9malle",
    "sg:classifiers":[
        {
            "category":"Insurance",
            "subcategory":"Life Insurance",
            "type":"Services"
        }
    ],
    "sg:phone":"+32 4 275 75 49",
    "sg:postcode":"4400",
    "sg:province":"Li\u00e8ge",
    "sg:tags":[
        "assurance"
    ],
    "wof:name":"R\u00c9gine Firquet",
    "wof:placetype":"venue"
},
  "geometry": {"coordinates":[5.4576430321,50.5693130493],"type":"Point"}
}