{
  "type": "Feature",
  "properties": {
    "addr:full":"Rue Emmanuel Van Driessche 34 Bruxelles (ixelles) Bruxelles-Capitale 1050",
    "addr:housenumber":"34",
    "addr:postcode":"1050",
    "addr:street":"Rue Emmanuel Van Driessche",
    "iso:country":"BE",
    "sg:address":"Rue Emmanuel Van Driessche 34",
    "sg:city":"Bruxelles (ixelles)",
    "sg:classifiers":[
        {
            "category":"Shopping",
            "subcategory":"Mobile Phones",
            "type":"Retail Goods"
        }
    ],
    "sg:phone":"+32 2 538 63 10",
    "sg:postcode":"1050",
    "sg:province":"Bruxelles-Capitale",
    "sg:tags":[
        "sound",
        "damping"
    ],
    "wof:name":"Ac Ways & Sounds",
    "wof:placetype":"venue"
},
  "geometry": {"coordinates":[4.3556199074,50.8196487427],"type":"Point"}
}