{
  "type": "Feature",
  "properties": {
    "iso:country":"BE",
    "sg:address":"Haven 1213",
    "sg:city":"Beveren",
    "sg:orig_category":"Agences d'exp\u00e9dition",
    "sg:phone":"+32 3 570 92 00",
    "sg:postcode":"9130",
    "sg:province":"Oost-Vlaanderen",
    "wof:name":"Fa. Enso West",
    "wof:placetype":"venue"
},
  "geometry": {"coordinates":[4.175344944,51.2897109985],"type":"Point"}
}