{
  "type": "Feature",
  "properties": {
    "iso:country":"BE",
    "sg:address":"Lange Zoutstraat 45",
    "sg:city":"Aalst",
    "sg:classifiers":[
        {
            "category":"Shopping",
            "subcategory":"Shoes",
            "type":"Retail Goods"
        }
    ],
    "sg:phone":"+32 53 21 61 37",
    "sg:postcode":"9300",
    "sg:province":"Oost-Vlaanderen",
    "sg:tags":[
        "slipper",
        "-"
    ],
    "wof:name":"Inter-moda Guy Bvba",
    "wof:placetype":"venue"
},
  "geometry": {"coordinates":[4.0394301414,50.9367599487],"type":"Point"}
}