{
  "type": "Feature",
  "properties": {
    "iso:country":"BE",
    "sg:address":"Rue Charles Henin 4",
    "sg:city":"Marche-en-famenne (waha)",
    "sg:classifiers":[
        {
            "category":"Health Services",
            "subcategory":"Health Practitioner",
            "type":"Services"
        }
    ],
    "sg:phone":"+32 84 31 25 29",
    "sg:postcode":"6900",
    "sg:province":"Luxembourg",
    "sg:tags":[
        "physiotherapist"
    ],
    "wof:name":"L\u00e9onard Centre De Kin\u00e9sith\u00e9rapie",
    "wof:placetype":"venue"
},
  "geometry": {"coordinates":[5.3220090866,50.2019119263],"type":"Point"}
}