{
  "type": "Feature",
  "properties": {
    "iso:country":"BE",
    "sg:address":"Rue Des Religieuses 15ba",
    "sg:city":"Philippeville",
    "sg:orig_category":"Enseignement maternel and primaire",
    "sg:phone":"+32 71 66 71 89",
    "sg:postcode":"5600",
    "sg:province":"Namur",
    "wof:name":"E.f.l. Notre Dame",
    "wof:placetype":"venue"
},
  "geometry": {"coordinates":[4.5451288223,50.1965522766],"type":"Point"}
}