{
  "type": "Feature",
  "properties": {
    "addr:full":"Renier Sniederspad 5 Vosselaar Antwerpen 2350",
    "addr:housenumber":"5",
    "addr:postcode":"2350",
    "addr:street":"Sniederspad",
    "iso:country":"BE",
    "sg:address":"Renier Sniederspad 5",
    "sg:city":"Vosselaar",
    "sg:classifiers":[
        {
            "category":"Health Services",
            "subcategory":"Dentist",
            "type":"Services"
        }
    ],
    "sg:phone":"+32 14 61 46 28",
    "sg:postcode":"2350",
    "sg:province":"Antwerpen",
    "wof:name":"Massin K",
    "wof:placetype":"venue"
},
  "geometry": {"coordinates":[4.8817501068,51.3077087402],"type":"Point"}
}