{
  "type": "Feature",
  "properties": {
    "addr:full":"Rue Joseph Wauters 74 Huy Li\u00e8ge 4500",
    "addr:housenumber":"74",
    "addr:postcode":"4500",
    "addr:street":"Rue Joseph Wauters",
    "iso:country":"BE",
    "sg:address":"Rue Joseph Wauters 74",
    "sg:city":"Huy",
    "sg:orig_category":"Avocats and conseillers juridiques",
    "sg:phone":"+32 85 21 60 80",
    "sg:postcode":"4500",
    "sg:province":"Li\u00e8ge",
    "wof:name":"Bertrand Rasquain",
    "wof:placetype":"venue"
},
  "geometry": {"coordinates":[5.2224359512,50.5182647705],"type":"Point"}
}