{
  "type": "Feature",
  "properties": {
    "iso:country":"BE",
    "sg:address":"R Des Rouliers 16",
    "sg:city":"Lappion",
    "sg:classifiers":[
        {
            "category":"Manufacturing",
            "subcategory":"Musical Instruments",
            "type":"Manufacturing & Wholesale Goods"
        }
    ],
    "sg:phone":"+33 3 23 22 08 08",
    "sg:postcode":"02150",
    "sg:tags":[
        "piano"
    ],
    "wof:name":"Pianos Perlot Sarl",
    "wof:placetype":"venue"
},
  "geometry": {"coordinates":[3.9557900429,49.5703697205],"type":"Point"}
}