{
  "type": "Feature",
  "properties": {
    "addr:full":"Mayerlei 112 Mortsel Antwerpen 2640",
    "addr:housenumber":"112",
    "addr:postcode":"2640",
    "addr:street":"Mayerlei",
    "iso:country":"BE",
    "sg:address":"Mayerlei 112",
    "sg:city":"Mortsel",
    "sg:classifiers":[
        {
            "category":"Manufacturing",
            "subcategory":"Building Materials",
            "type":"Manufacturing & Wholesale Goods"
        }
    ],
    "sg:phone":"+32 3 454 05 28",
    "sg:postcode":"2640",
    "sg:province":"Antwerpen",
    "sg:tags":[
        "fixture",
        "store"
    ],
    "wof:name":"Winka Bvba",
    "wof:placetype":"venue"
},
  "geometry": {"coordinates":[4.4724640846,51.1650543213],"type":"Point"}
}