{
  "type": "Feature",
  "properties": {
    "addr:full":"Joe Englishstraat 7 Veurne West-Vlaanderen 8630",
    "addr:housenumber":"7",
    "addr:postcode":"8630",
    "addr:street":"Joe Englishstraat",
    "iso:country":"BE",
    "sg:address":"Joe Englishstraat 7",
    "sg:city":"Veurne",
    "sg:orig_category":"Eleveurs de bovins",
    "sg:phone":"+32 58 29 90 90",
    "sg:postcode":"8630",
    "sg:province":"West-Vlaanderen",
    "wof:name":"Philip Dekervel",
    "wof:placetype":"venue"
},
  "geometry": {"coordinates":[2.6379170418,51.0123939514],"type":"Point"}
}