{
  "type": "Feature",
  "properties": {
    "addr:full":"Rue De Barvaux 178 Ciney Namur 5590",
    "addr:housenumber":"178",
    "addr:postcode":"5590",
    "addr:street":"Rue De Barvaux",
    "iso:country":"BE",
    "sg:address":"Rue De Barvaux 178",
    "sg:city":"Ciney",
    "sg:orig_category":"Bloemen and planten Rundveehouders Tuinen",
    "sg:phone":"+32 83 68 82 75",
    "sg:postcode":"5590",
    "sg:province":"Namur",
    "wof:name":"Jouant Bernard Entreprise",
    "wof:placetype":"venue"
},
  "geometry": {"coordinates":[5.1022520065,50.297088623],"type":"Point"}
}