{
  "type": "Feature",
  "properties": {
    "iso:country":"BE",
    "sg:address":"Fays 711b",
    "sg:city":"Bertogne (longchamps)",
    "sg:classifiers":[
        {
            "category":"Building & Trades",
            "subcategory":"Construction",
            "type":"Services"
        }
    ],
    "sg:phone":"+32 61 21 73 21",
    "sg:postcode":"6688",
    "sg:province":"Luxembourg",
    "sg:tags":[
        "stucco",
        "contractor"
    ],
    "wof:name":"Pierret E",
    "wof:placetype":"venue"
},
  "geometry": {"coordinates":[5.6698560715,50.0639343262],"type":"Point"}
}