{
  "type": "Feature",
  "properties": {
    "iso:country":"BE",
    "sg:address":"Rue Adolphe-damseaux 44",
    "sg:city":"Gembloux",
    "sg:orig_category":"Parfumeries",
    "sg:phone":"+32 81 61 42 19",
    "sg:postcode":"5030",
    "sg:province":"Namur",
    "wof:name":"Mich\u00c8le Graye",
    "wof:placetype":"venue"
},
  "geometry": {"coordinates":[4.6888189316,50.5624008179],"type":"Point"}
}