{
  "type": "Feature",
  "properties": {
    "addr:full":"Nieuwstraat 207 Sint-niklaas Oost-Vlaanderen 9100",
    "addr:housenumber":"207",
    "addr:postcode":"9100",
    "addr:street":"Nieuwstraat",
    "iso:country":"BE",
    "sg:address":"Nieuwstraat 207",
    "sg:city":"Sint-niklaas",
    "sg:classifiers":[
        {
            "category":"Fast Food",
            "type":"Food & Drink"
        }
    ],
    "sg:phone":"+32 3 296 33 84",
    "sg:postcode":"9100",
    "sg:province":"Oost-Vlaanderen",
    "sg:tags":[
        "fried",
        "stand",
        "potato"
    ],
    "wof:name":"Nieuwe Frietnisse (de)",
    "wof:placetype":"venue"
},
  "geometry": {"coordinates":[4.1322999001,51.1610908508],"type":"Point"}
}