{
  "type": "Feature",
  "properties": {
    "iso:country":"BE",
    "sg:address":"Rue Hemricourt 44",
    "sg:city":"Li\u00c8ge",
    "sg:orig_category":"Bouwmaterialen Gh Installatie van metalen schrijnwerk",
    "sg:phone":"+32 4 254 98 15",
    "sg:postcode":"4000",
    "sg:province":"Li\u00e8ge",
    "wof:name":"Wagener-jowaco",
    "wof:placetype":"venue"
},
  "geometry": {"coordinates":[5.5629639626,50.630607605],"type":"Point"}
}