{
  "type": "Feature",
  "properties": {
    "iso:country":"BE",
    "sg:address":"Rijselseweg 64",
    "sg:city":"Ieper",
    "sg:classifiers":[
        {
            "category":"Bars & Pubs",
            "type":"Food & Drink"
        }
    ],
    "sg:phone":"+32 57 20 19 90",
    "sg:postcode":"8900",
    "sg:province":"West-Vlaanderen",
    "wof:name":"Fontein (de)",
    "wof:placetype":"venue"
},
  "geometry": {"coordinates":[2.8888170719,50.8411598206],"type":"Point"}
}