{
  "type": "Feature",
  "properties": {
    "addr:full":"Rue J. Bogemans 92 Wemmel Vlaams-Brabant 1780",
    "addr:housenumber":"92",
    "addr:postcode":"1780",
    "addr:street":"Rue J. Bogemans;Vlaams-Brabant",
    "iso:country":"BE",
    "sg:address":"Rue J. Bogemans 92",
    "sg:city":"Wemmel",
    "sg:classifiers":[
        {
            "category":"Health Services",
            "subcategory":"Hospital",
            "type":"Services"
        }
    ],
    "sg:phone":"+32 2 461 36 88",
    "sg:postcode":"1780",
    "sg:province":"Vlaams-Brabant",
    "sg:tags":[
        "ambulance"
    ],
    "wof:name":"Gisa Ambulances",
    "wof:placetype":"venue"
},
  "geometry": {"coordinates":[4.3128800392,50.9047164917],"type":"Point"}
}