{
  "type": "Feature",
  "properties": {
    "addr:full":"Rue Auguste Latour 72 Braine-le-ch\u00e2teau Brabant Wallon 1440",
    "addr:housenumber":"72",
    "addr:postcode":"1440",
    "addr:street":"Rue Auguste Latour",
    "iso:country":"BE",
    "sg:address":"Rue Auguste Latour 72",
    "sg:city":"Braine-le-ch\u00e2teau",
    "sg:classifiers":[
        {
            "category":"Transit Center",
            "subcategory":"Freight",
            "type":"Transportation"
        }
    ],
    "sg:phone":"+32 2 355 12 90",
    "sg:postcode":"1440",
    "sg:province":"Brabant Wallon",
    "sg:tags":[
        "import",
        "export",
        "-"
    ],
    "wof:name":"Quatre X Quatre Explorer",
    "wof:placetype":"venue"
},
  "geometry": {"coordinates":[4.2658638954,50.6765632629],"type":"Point"}
}