{
  "type": "Feature",
  "properties": {
    "iso:country":"BE",
    "sg:address":"Asbroekstraat 60",
    "sg:city":"Zoutleeuw",
    "sg:classifiers":[
        {
            "category":"Insurance",
            "subcategory":"Life Insurance",
            "type":"Services"
        }
    ],
    "sg:phone":"+32 11 78 13 01",
    "sg:postcode":"3440",
    "sg:province":"Vlaams-Brabant",
    "sg:tags":[
        "assurance"
    ],
    "wof:name":"T. Daerden",
    "wof:placetype":"venue"
},
  "geometry": {"coordinates":[5.1159610748,50.8071212769],"type":"Point"}
}