{
  "type": "Feature",
  "properties": {
    "addr:full":"Aachener Strasse 216 Eupen (kettenis) Li\u00e8ge 4701",
    "addr:housenumber":"216",
    "addr:postcode":"4701",
    "addr:street":"Aachener Strasse",
    "iso:country":"BE",
    "sg:address":"Aachener Strasse 216",
    "sg:city":"Eupen (kettenis)",
    "sg:classifiers":[
        {
            "category":"Wholesale",
            "subcategory":"Vending Machines",
            "type":"Manufacturing & Wholesale Goods"
        }
    ],
    "sg:phone":"+32 87 55 38 95",
    "sg:postcode":"4701",
    "sg:province":"Li\u00e8ge",
    "sg:tags":[
        "-",
        "electric",
        "motor"
    ],
    "wof:name":"Leroy Atelier Sprl",
    "wof:placetype":"venue"
},
  "geometry": {"coordinates":[6.0412201881,50.6376190186],"type":"Point"}
}