{
  "type": "Feature",
  "properties": {
    "addr:full":"Chauss\u00c9e De Waterloo 320 Namur Namur 5002",
    "addr:housenumber":"320",
    "addr:postcode":"5002",
    "addr:street":"Chausse\u0301E De Waterloo",
    "iso:country":"BE",
    "sg:address":"Chauss\u00c9e De Waterloo 320",
    "sg:city":"Namur",
    "sg:orig_category":"Assistances juridiques",
    "sg:phone":"+32 81 74 99 88",
    "sg:postcode":"5002",
    "sg:province":"Namur",
    "wof:name":"Salle De Vente - Rops",
    "wof:placetype":"venue"
},
  "geometry": {"coordinates":[4.8462319374,50.4782791138],"type":"Point"}
}