{
  "type": "Feature",
  "properties": {
    "iso:country":"BE",
    "sg:address":"Lieskensakker 22",
    "sg:city":"Lochristi",
    "sg:orig_category":"Cr\u00e8ches and garderies d'enfants",
    "sg:phone":"+32 9 356 91 87",
    "sg:postcode":"9080",
    "sg:province":"Oost-Vlaanderen",
    "wof:name":"Bengelhuisje",
    "wof:placetype":"venue"
},
  "geometry": {"coordinates":[3.8394129276,51.1019706726],"type":"Point"}
}