{
  "type": "Feature",
  "properties": {
    "addr:full":"Rue Grande 22 Qui\u00e9vrain Hainaut 7380",
    "addr:housenumber":"22",
    "addr:postcode":"7380",
    "addr:street":"Rue Grande",
    "iso:country":"BE",
    "sg:address":"Rue Grande 22",
    "sg:city":"Qui\u00e9vrain",
    "sg:classifiers":[
        {
            "category":"Utilities",
            "subcategory":"Mobile Phone",
            "type":"Services"
        }
    ],
    "sg:phone":"+32 65 66 20 60",
    "sg:postcode":"7380",
    "sg:province":"Hainaut",
    "sg:tags":[
        "access",
        "gsm",
        "-",
        "apparatus"
    ],
    "wof:name":"Gsm Avenue",
    "wof:placetype":"venue"
},
  "geometry": {"coordinates":[3.6824519634,50.4069786072],"type":"Point"}
}