{
  "type": "Feature",
  "properties": {
    "iso:country":"BE",
    "sg:address":"Elisabethlaan 1a",
    "sg:city":"Antwerpen",
    "sg:orig_category":"Belastingconsulenten Diverse juridische dienstverlening",
    "sg:phone":"+32 3 239 38 96",
    "sg:postcode":"2600",
    "sg:province":"Antwerpen",
    "wof:name":"Unie Voor Brood-, Chocolade- & Ijsbedrijf",
    "wof:placetype":"venue"
},
  "geometry": {"coordinates":[4.4232978821,51.1821250916],"type":"Point"}
}