{
  "type": "Feature",
  "properties": {
    "addr:full":"Rue Trieu Kaisin 121 Charleroi Hainaut 6061",
    "addr:housenumber":"121",
    "addr:postcode":"6061",
    "addr:street":"Rue Trieu Kaisin;Hainaut",
    "iso:country":"BE",
    "sg:address":"Rue Trieu Kaisin 121",
    "sg:city":"Charleroi",
    "sg:orig_category":"Agences de publicit\u00e9",
    "sg:phone":"+32 71 31 37 70",
    "sg:postcode":"6061",
    "sg:province":"Hainaut",
    "wof:name":"Christian Vanderbruggen",
    "wof:placetype":"venue"
},
  "geometry": {"coordinates":[4.4751639366,50.4092025757],"type":"Point"}
}