{
  "type": "Feature",
  "properties": {
    "iso:country":"BE",
    "sg:address":"Avenue De Jemappes 123bis",
    "sg:city":"Mons",
    "sg:classifiers":[
        {
            "category":"Professional",
            "subcategory":"Accounting & Tax Preparation",
            "type":"Services"
        }
    ],
    "sg:phone":"+32 65 33 56 13",
    "sg:postcode":"7000",
    "sg:province":"Hainaut",
    "sg:tags":[
        "accountant"
    ],
    "wof:name":"Stievenart R",
    "wof:placetype":"venue"
},
  "geometry": {"coordinates":[3.932710886,50.4516334534],"type":"Point"}
}