{
  "type": "Feature",
  "properties": {
    "iso:country":"BE",
    "sg:address":"Vlaanderenstraat 90",
    "sg:city":"Gent",
    "sg:orig_category":"Tijdelijke werkgelegenheid and uitzendkantoren",
    "sg:phone":"+32 9 269 04 89",
    "sg:postcode":"9000",
    "sg:province":"Oost-Vlaanderen",
    "wof:name":"Abs Interim",
    "wof:placetype":"venue"
},
  "geometry": {"coordinates":[3.7304620743,51.0495796204],"type":"Point"}
}