{
  "type": "Feature",
  "properties": {
    "addr:full":"Guido Gezellelaan 37 Roeselare West-Vlaanderen 8800",
    "addr:housenumber":"37",
    "addr:postcode":"8800",
    "addr:street":"Guido Gezellelaan",
    "iso:country":"BE",
    "sg:address":"Guido Gezellelaan 37",
    "sg:city":"Roeselare",
    "sg:orig_category":"Ordinateurs and \u00e9quipement informatique",
    "sg:phone":"+32 475 95 43 21",
    "sg:postcode":"8800",
    "sg:province":"West-Vlaanderen",
    "wof:name":"Serve-it",
    "wof:placetype":"venue"
},
  "geometry": {"coordinates":[3.1394970417,50.9405441284],"type":"Point"}
}