{
  "type": "Feature",
  "properties": {
    "addr:full":"Spichtestraat 2 Zwevegem (heestert) West-Vlaanderen 8551",
    "addr:housenumber":"2",
    "addr:postcode":"8551",
    "addr:street":"Spichtestraat",
    "iso:country":"BE",
    "sg:address":"Spichtestraat 2",
    "sg:city":"Zwevegem (heestert)",
    "sg:classifiers":[
        {
            "category":"Building & Trades",
            "subcategory":"Construction",
            "type":"Services"
        }
    ],
    "sg:phone":"+32 56 64 90 16",
    "sg:postcode":"8551",
    "sg:province":"West-Vlaanderen",
    "sg:tags":[
        "carpenter"
    ],
    "wof:name":"De Witte Schrijnwerkerij",
    "wof:placetype":"venue"
},
  "geometry": {"coordinates":[3.4109840393,50.782283783],"type":"Point"}
}