{
  "type": "Feature",
  "properties": {
    "addr:full":"Sint-lazaruslaan 12 Sint-joost-ten-node/saint-josse-ten-noode Bruxelles-Capitale 1210",
    "addr:housenumber":"12",
    "addr:postcode":"1210",
    "addr:street":"Sint-Lazaruslaan",
    "iso:country":"BE",
    "sg:address":"Sint-lazaruslaan 12",
    "sg:city":"Sint-joost-ten-node/saint-josse-ten-noode",
    "sg:orig_category":"Artsen and specialisten",
    "sg:phone":"+32 2 218 38 26",
    "sg:postcode":"1210",
    "sg:province":"Bruxelles-Capitale",
    "wof:name":"Ren\u00c9 De Clercq",
    "wof:placetype":"venue"
},
  "geometry": {"coordinates":[4.3616299629,50.8570861816],"type":"Point"}
}