{
  "type": "Feature",
  "properties": {
    "iso:country":"BE",
    "sg:address":"Tervurenlaan 211",
    "sg:city":"Brussel",
    "sg:classifiers":[
        {
            "category":"Professional",
            "subcategory":"Accounting & Tax Preparation",
            "type":"Services"
        }
    ],
    "sg:phone":"+32 2 739 71 11",
    "sg:postcode":"1150",
    "sg:province":"Bruxelles-Capitale",
    "sg:tags":[
        "data",
        "acquisition"
    ],
    "wof:name":"Institut National D'assurance Maladie-invalid",
    "wof:placetype":"venue"
},
  "geometry": {"coordinates":[4.4101810455,50.836517334],"type":"Point"}
}