{
  "type": "Feature",
  "properties": {
    "iso:country":"BE",
    "sg:address":"Rue Saint-joseph 6",
    "sg:city":"Mouscron",
    "sg:orig_category":"Non-Classified Establishments",
    "sg:phone":"+32 56 39 16 04",
    "sg:postcode":"7700",
    "sg:province":"Hainaut",
    "wof:name":"Centres P.m.s.libre",
    "wof:placetype":"venue"
},
  "geometry": {"coordinates":[3.1942350864,50.7269439697],"type":"Point"}
}