{
  "type": "Feature",
  "properties": {
    "iso:country":"BE",
    "sg:address":"Hoek Ten Eiken 21",
    "sg:city":"Puurs",
    "sg:classifiers":[
        {
            "category":"Freight",
            "type":"Transportation"
        }
    ],
    "sg:phone":"+32 3 889 02 91",
    "sg:postcode":"2870",
    "sg:province":"Antwerpen",
    "sg:tags":[
        "-",
        "transport"
    ],
    "wof:name":"Dehertogh Guido Bvba",
    "wof:placetype":"venue"
},
  "geometry": {"coordinates":[4.2772698402,51.0763244629],"type":"Point"}
}