{
  "type": "Feature",
  "properties": {
    "addr:full":"Rue Du Sablon 113 Bastogne Luxembourg 6600",
    "addr:housenumber":"113",
    "addr:postcode":"6600",
    "addr:street":"Rue Du Sablon",
    "iso:country":"BE",
    "sg:address":"Rue Du Sablon 113",
    "sg:city":"Bastogne",
    "sg:orig_category":"Opticiens Pearle",
    "sg:phone":"+32 61 21 54 15",
    "sg:postcode":"6600",
    "sg:province":"Luxembourg",
    "wof:name":"Pearle Opticiens",
    "wof:placetype":"venue"
},
  "geometry": {"coordinates":[5.7181921005,50.0030288696],"type":"Point"}
}