{
  "type": "Feature",
  "properties": {
    "iso:country":"BE",
    "sg:address":"Cesar Van Kerckhovenstr. 110b210",
    "sg:city":"Bornem",
    "sg:classifiers":[
        {
            "category":"Insurance",
            "subcategory":"Life Insurance",
            "type":"Services"
        }
    ],
    "sg:phone":"+32 3 890 47 50",
    "sg:postcode":"2880",
    "sg:province":"Antwerpen",
    "sg:tags":[
        "assurance"
    ],
    "wof:name":"Warranty Holdings Int.",
    "wof:placetype":"venue"
},
  "geometry": {"coordinates":[4.2675909996,51.0953025818],"type":"Point"}
}