{
  "type": "Feature",
  "properties": {
    "addr:full":"Testeltsesteenweg 98 Aarschot Vlaams-Brabant 3201",
    "addr:housenumber":"98",
    "addr:postcode":"3201",
    "addr:street":"Testeltsesteenweg",
    "iso:country":"BE",
    "sg:address":"Testeltsesteenweg 98",
    "sg:city":"Aarschot",
    "sg:orig_category":"Elektrische installaties voor woningen",
    "sg:phone":"+32 16 56 38 33",
    "sg:postcode":"3201",
    "sg:province":"Vlaams-Brabant",
    "wof:name":"Dominik Galicia",
    "wof:placetype":"venue"
},
  "geometry": {"coordinates":[4.8908691406,51.0012702942],"type":"Point"}
}