{
  "type": "Feature",
  "properties": {
    "addr:full":"Passage Wellington Waterloo Brabant Wallon 1410",
    "addr:postcode":"1410",
    "addr:street":"Passage Wellington",
    "iso:country":"BE",
    "sg:address":"Passage Wellington",
    "sg:city":"Waterloo",
    "sg:classifiers":[
        {
            "category":"Cafe",
            "type":"Food & Drink"
        }
    ],
    "sg:phone":"+32 2 353 00 38",
    "sg:postcode":"1410",
    "sg:province":"Brabant Wallon",
    "sg:tags":[
        "snack-bars"
    ],
    "wof:name":"Rotonde (la)",
    "wof:placetype":"venue"
},
  "geometry": {"coordinates":[4.3995580673,50.7164573669],"type":"Point"}
}