{
  "type": "Feature",
  "properties": {
    "addr:full":"Zeedijk 92a Oostende West-Vlaanderen 8400",
    "addr:housenumber":"92a",
    "addr:postcode":"8400",
    "addr:street":"Zeedijk",
    "iso:country":"BE",
    "sg:address":"Zeedijk 92a",
    "sg:city":"Oostende",
    "sg:classifiers":[
        {
            "category":"Shopping",
            "subcategory":"Bicycles & Sporting Goods",
            "type":"Retail Goods"
        }
    ],
    "sg:phone":"+32 59 80 78 00",
    "sg:postcode":"8400",
    "sg:province":"West-Vlaanderen",
    "sg:tags":[
        "-"
    ],
    "wof:name":"Kurioosa",
    "wof:placetype":"venue"
},
  "geometry": {"coordinates":[2.8583700657,51.2067070007],"type":"Point"}
}