{
  "type": "Feature",
  "properties": {
    "iso:country":"BE",
    "sg:address":"Egide Walschaertsstraat 2",
    "sg:city":"Mechelen",
    "sg:orig_category":"Non-Classified Establishments",
    "sg:phone":"+32 15 40 90 60",
    "sg:postcode":"2800",
    "sg:province":"Antwerpen",
    "wof:name":"Buvetex Nv",
    "wof:placetype":"venue"
},
  "geometry": {"coordinates":[4.4642071724,51.0096168518],"type":"Point"}
}