{
  "type": "Feature",
  "properties": {
    "iso:country":"BE",
    "sg:address":"Rue De Neufch\u00e2teau 615",
    "sg:city":"Arlon (heinsch)",
    "sg:classifiers":[
        {
            "category":"Shopping",
            "subcategory":"Discount & Variety Stores",
            "type":"Retail Goods"
        }
    ],
    "sg:phone":"+32 63 22 14 04",
    "sg:postcode":"6700",
    "sg:province":"Luxembourg",
    "sg:tags":[
        "shop",
        "clearers",
        "curiosity",
        "furniture"
    ],
    "wof:name":"Mortier J",
    "wof:placetype":"venue"
},
  "geometry": {"coordinates":[5.7981181145,49.6860542297],"type":"Point"}
}