{
  "type": "Feature",
  "properties": {
    "addr:full":"Rue Des Ormes 151 Verviers (lambermont) Li\u00e8ge 4800",
    "addr:housenumber":"151",
    "addr:postcode":"4800",
    "addr:street":"Rue Des Ormes;Lambermont",
    "iso:country":"BE",
    "sg:address":"Rue Des Ormes 151",
    "sg:city":"Verviers (lambermont)",
    "sg:classifiers":[
        {
            "category":"Retail",
            "subcategory":"Auto Repair",
            "type":"Services"
        }
    ],
    "sg:phone":"+32 87 30 01 20",
    "sg:postcode":"4800",
    "sg:province":"Li\u00e8ge",
    "sg:tags":[
        "automobile-body"
    ],
    "wof:name":"Koch Serge Sprl",
    "wof:placetype":"venue"
},
  "geometry": {"coordinates":[5.8594508171,50.5917663574],"type":"Point"}
}