{
  "type": "Feature",
  "properties": {
    "addr:full":"Leembergstraat 14 Zuienkerke West-Vlaanderen 8377",
    "addr:housenumber":"14",
    "addr:postcode":"8377",
    "addr:street":"Leembergstraat",
    "iso:country":"BE",
    "sg:address":"Leembergstraat 14",
    "sg:city":"Zuienkerke",
    "sg:orig_category":"Activit\u00e9s d\u00b4action sociale sans h\u00e9bergement. M\u00e9decins and sp\u00e9cialistes",
    "sg:phone":"+32 50 31 36 34",
    "sg:postcode":"8377",
    "sg:province":"West-Vlaanderen",
    "wof:name":"B. Vanden Broecke",
    "wof:placetype":"venue"
},
  "geometry": {"coordinates":[3.1857030392,51.2565193176],"type":"Point"}
}