{
  "type": "Feature",
  "properties": {
    "addr:full":"Fran\u00e7ois Laurentplein 9 Gent Oost-Vlaanderen 9000",
    "addr:housenumber":"9",
    "addr:postcode":"9000",
    "addr:street":"Oost-Vlaanderen",
    "iso:country":"BE",
    "sg:address":"Fran\u00e7ois Laurentplein 9",
    "sg:city":"Gent",
    "sg:classifiers":[
        {
            "category":"Health Services",
            "subcategory":"Hospital",
            "type":"Services"
        }
    ],
    "sg:phone":"+32 9 264 12 30",
    "sg:postcode":"9000",
    "sg:province":"Oost-Vlaanderen",
    "wof:name":"Idewe Gent",
    "wof:placetype":"venue"
},
  "geometry": {"coordinates":[3.7284829617,51.0511703491],"type":"Point"}
}