{
  "type": "Feature",
  "properties": {
    "iso:country":"BE",
    "sg:address":"Rue Des Oeillets 10",
    "sg:city":"Voroux-lez-liers",
    "sg:orig_category":"Pompes and compresseurs Fab. Travaux d\u00b4installation divers. Quincailleries. V\u00eatements. Equipements d",
    "sg:phone":"+32 4 278 00 75",
    "sg:postcode":"4451",
    "sg:province":"Li\u00e8ge",
    "wof:name":"Tool Protection",
    "wof:placetype":"venue"
},
  "geometry": {"coordinates":[5.5532851219,50.6876792908],"type":"Point"}
}