{
  "type": "Feature",
  "properties": {
    "addr:full":"Rue Du Tienne 20 Gerpinnes Hainaut 6280",
    "addr:housenumber":"20",
    "addr:postcode":"6280",
    "addr:street":"Rue Du Tienne;Hainaut",
    "iso:country":"BE",
    "sg:address":"Rue Du Tienne 20",
    "sg:city":"Gerpinnes",
    "sg:orig_category":"Brood, gebak and snoepgoed",
    "sg:phone":"+32 71 50 46 71",
    "sg:postcode":"6280",
    "sg:province":"Hainaut",
    "wof:name":"La Villerssoise",
    "wof:placetype":"venue"
},
  "geometry": {"coordinates":[4.5468392372,50.3527641296],"type":"Point"}
}