{
  "type": "Feature",
  "properties": {
    "iso:country":"BE",
    "sg:address":"Zwijnaardsesteenweg 571",
    "sg:city":"Gent",
    "sg:orig_category":"Metaalbehandeling and -bekleding",
    "sg:phone":"+32 9 220 44 83",
    "sg:postcode":"9000",
    "sg:province":"Oost-Vlaanderen",
    "wof:name":"Lambrecht H",
    "wof:placetype":"venue"
},
  "geometry": {"coordinates":[3.7206149101,51.0230560303],"type":"Point"}
}