{
  "type": "Feature",
  "properties": {
    "iso:country":"BE",
    "sg:address":"Place Du Sud 25",
    "sg:city":"Quaregnon",
    "sg:classifiers":[
        {
            "category":"Shopping",
            "subcategory":"Books",
            "type":"Retail Goods"
        }
    ],
    "sg:phone":"+32 65 66 92 86",
    "sg:postcode":"7390",
    "sg:province":"Hainaut",
    "sg:tags":[
        "bookseller"
    ],
    "wof:name":"Sud (librairie Du)",
    "wof:placetype":"venue"
},
  "geometry": {"coordinates":[3.8660109043,50.4233131409],"type":"Point"}
}