{
  "type": "Feature",
  "properties": {
    "iso:country":"BE",
    "sg:address":"Alfons Minoodtlaan 8",
    "sg:city":"Gent",
    "sg:orig_category":"Peinture. Eclairage et \u00e9quipements du foyer. Rev\u00eatements pour sols and murs",
    "sg:phone":"+32 9 227 03 79",
    "sg:postcode":"9030",
    "sg:province":"Oost-Vlaanderen",
    "wof:name":"C En C",
    "wof:placetype":"venue"
},
  "geometry": {"coordinates":[3.6697659492,51.0735282898],"type":"Point"}
}