{
  "type": "Feature",
  "properties": {
    "iso:country":"BE",
    "sg:address":"Rue D'anderlues 6",
    "sg:city":"Lobbes",
    "sg:classifiers":[
        {
            "category":"Bars & Pubs",
            "type":"Food & Drink"
        }
    ],
    "sg:phone":"+32 71 59 13 51",
    "sg:postcode":"6540",
    "sg:province":"Hainaut",
    "wof:name":"Vieux Copain (au)",
    "wof:placetype":"venue"
},
  "geometry": {"coordinates":[4.2752070427,50.3698577881],"type":"Point"}
}