{
  "type": "Feature",
  "properties": {
    "addr:full":"Rue Des Piges \u00c0 Fenasses 43 Charleroi Hainaut 6031",
    "addr:housenumber":"43",
    "addr:postcode":"6031",
    "addr:street":"Rue Des Piges A\u0300 Fenasses;Hainaut",
    "iso:country":"BE",
    "sg:address":"Rue Des Piges \u00c0 Fenasses 43",
    "sg:city":"Charleroi",
    "sg:orig_category":"Woningbouw",
    "sg:phone":"+32 71 32 02 22",
    "sg:postcode":"6031",
    "sg:province":"Hainaut",
    "wof:name":"D.d.p.",
    "wof:placetype":"venue"
},
  "geometry": {"coordinates":[4.38022995,50.4121742249],"type":"Point"}
}