{
  "type": "Feature",
  "properties": {
    "addr:full":"Rue Du Temple 193 Ghlin Hainaut 7011",
    "addr:housenumber":"193",
    "addr:postcode":"7011",
    "addr:street":"Rue Du Temple",
    "iso:country":"BE",
    "sg:address":"Rue Du Temple 193",
    "sg:city":"Ghlin",
    "sg:orig_category":"Yamaha. Motos. V\u00e9hicules automobiles",
    "sg:phone":"+32 65 34 84 56",
    "sg:postcode":"7011",
    "sg:province":"Hainaut",
    "wof:name":"Motocross Action",
    "wof:placetype":"venue"
},
  "geometry": {"coordinates":[3.9316599369,50.4752082825],"type":"Point"}
}