{
  "type": "Feature",
  "properties": {
    "addr:full":"Rue Du Tensoul 5 Chastre (cortil-noirmont) Brabant Wallon 1450",
    "addr:housenumber":"5",
    "addr:postcode":"1450",
    "addr:street":"Rue Du Tensoul;Wallon",
    "iso:country":"BE",
    "sg:address":"Rue Du Tensoul 5",
    "sg:city":"Chastre (cortil-noirmont)",
    "sg:classifiers":[
        {
            "category":"Museum",
            "type":"Entertainment"
        }
    ],
    "sg:phone":"+32 81 61 31 40",
    "sg:postcode":"1450",
    "sg:province":"Brabant Wallon",
    "wof:name":"Mus\u00e9e Fran\u00e7ais Asbl",
    "wof:placetype":"venue"
},
  "geometry": {"coordinates":[4.636452198,50.6085243225],"type":"Point"}
}