{
  "type": "Feature",
  "properties": {
    "addr:full":"Rue De La Victoire 46 Le Roeulx Hainaut 7070",
    "addr:housenumber":"46",
    "addr:postcode":"7070",
    "addr:street":"Rue De La",
    "iso:country":"BE",
    "sg:address":"Rue De La Victoire 46",
    "sg:city":"Le Roeulx",
    "sg:classifiers":[
        {
            "category":"Arena",
            "subcategory":"Sports Club",
            "type":"Entertainment"
        }
    ],
    "sg:phone":"+32 64 66 31 24",
    "sg:postcode":"7070",
    "sg:province":"Hainaut",
    "sg:tags":[
        "de"
    ],
    "wof:name":"J.c. Rhodien",
    "wof:placetype":"venue"
},
  "geometry": {"coordinates":[4.1110239029,50.4971733093],"type":"Point"}
}