{
  "type": "Feature",
  "properties": {
    "addr:full":"Bruinstraat 49 Zonhoven Limburg 3520",
    "addr:housenumber":"49",
    "addr:postcode":"3520",
    "addr:street":"Bruinstraat",
    "iso:country":"BE",
    "sg:address":"Bruinstraat 49",
    "sg:city":"Zonhoven",
    "sg:classifiers":[
        {
            "category":"Personal",
            "subcategory":"Beauty Salon",
            "type":"Services"
        }
    ],
    "sg:phone":"+32 11 81 67 03",
    "sg:postcode":"3520",
    "sg:province":"Limburg",
    "sg:tags":[
        "lady",
        "-",
        "hairdressing"
    ],
    "wof:name":"Anita",
    "wof:placetype":"venue"
},
  "geometry": {"coordinates":[5.3548669815,51.0043144226],"type":"Point"}
}