{
  "type": "Feature",
  "properties": {
    "addr:full":"Kruiskerkestraat 45a Ruiselede West-Vlaanderen 8755",
    "addr:housenumber":"45a",
    "addr:postcode":"8755",
    "addr:street":"Kruiskerkestraat",
    "iso:country":"BE",
    "sg:address":"Kruiskerkestraat 45a",
    "sg:city":"Ruiselede",
    "sg:classifiers":[
        {
            "category":"Banks & Credit Unions",
            "subcategory":"Investment Brokerage",
            "type":"Services"
        }
    ],
    "sg:phone":"+32 51 68 70 01",
    "sg:postcode":"8755",
    "sg:province":"West-Vlaanderen",
    "sg:tags":[
        "repair",
        "-",
        "installation",
        "sanitary",
        "article"
    ],
    "wof:name":"Kerckaert G",
    "wof:placetype":"venue"
},
  "geometry": {"coordinates":[3.3868029118,51.0654335022],"type":"Point"}
}