{
  "type": "Feature",
  "properties": {
    "addr:full":"Ave De La Facult\u00e9 D'agronomie 69 Gembloux 5800",
    "addr:housenumber":"69",
    "addr:postcode":"5800",
    "addr:street":"Ave De La Faculte\u0301 D'Agronomie",
    "iso:country":"BE",
    "sg:address":"Ave De La Facult\u00e9 D'agronomie 69",
    "sg:city":"Gembloux",
    "sg:classifiers":[
        {
            "category":"Banks & Credit Unions",
            "subcategory":"Bank",
            "type":"Services"
        }
    ],
    "sg:phone":"+32 81 61 17 05",
    "sg:postcode":"5800",
    "wof:name":"G\u00e9n\u00e9rale De Banque Sa",
    "wof:placetype":"venue"
},
  "geometry": {"coordinates":[4.6946878433,50.5670547485],"type":"Point"}
}