{
  "type": "Feature",
  "properties": {
    "iso:country":"BE",
    "sg:address":"Meesberg 52",
    "sg:city":"Holsbeek",
    "sg:classifiers":[
        {
            "category":"Manufacturing",
            "subcategory":"Chemicals & Compounds",
            "type":"Manufacturing & Wholesale Goods"
        }
    ],
    "sg:phone":"+32 16 44 14 00",
    "sg:postcode":"3220",
    "sg:province":"Vlaams-Brabant",
    "sg:tags":[
        "pharmaceutical",
        "product"
    ],
    "wof:name":"Bofar Nv",
    "wof:placetype":"venue"
},
  "geometry": {"coordinates":[4.7496361732,50.9150161743],"type":"Point"}
}