{
  "type": "Feature",
  "properties": {
    "addr:full":"Fond Du Ruisseau 49 Saint-georges-sur-meuse Li\u00e8ge 4470",
    "addr:housenumber":"49",
    "addr:postcode":"4470",
    "addr:street":"Du Ruisseau",
    "iso:country":"BE",
    "sg:address":"Fond Du Ruisseau 49",
    "sg:city":"Saint-georges-sur-meuse",
    "sg:orig_category":"Mat\u00e9riel de contr\u00f4le des processus industriels Fab",
    "sg:phone":"+32 4 275 73 82",
    "sg:postcode":"4470",
    "sg:province":"Li\u00e8ge",
    "wof:name":"Brouwers",
    "wof:placetype":"venue"
},
  "geometry": {"coordinates":[5.372382164,50.6006584167],"type":"Point"}
}