{
  "type": "Feature",
  "properties": {
    "addr:full":"Av Du Roi Chevalier 42 Schaerbeek (bruxelles) Bruxelles-Capitale 1200",
    "addr:housenumber":"42",
    "addr:postcode":"1200",
    "addr:street":"Av Du Roi Chevalier",
    "iso:country":"BE",
    "sg:address":"Av Du Roi Chevalier 42",
    "sg:city":"Schaerbeek (bruxelles)",
    "sg:orig_category":"Kapsalons",
    "sg:phone":"+32 2 771 33 46",
    "sg:postcode":"1200",
    "sg:province":"Bruxelles-Capitale",
    "wof:name":"M.j.coiffure",
    "wof:placetype":"venue"
},
  "geometry": {"coordinates":[4.4252500534,50.8438148499],"type":"Point"}
}