{
  "type": "Feature",
  "properties": {
    "iso:country":"BE",
    "sg:address":"Rue Bois Du Prince 76",
    "sg:city":"Mettet",
    "sg:orig_category":"Plomberie, chauffage and installations sanitaires",
    "sg:phone":"+32 71 72 90 23",
    "sg:postcode":"5640",
    "sg:province":"Namur",
    "wof:name":"Poncelet",
    "wof:placetype":"venue"
},
  "geometry": {"coordinates":[4.6489219666,50.3469467163],"type":"Point"}
}