{
  "type": "Feature",
  "properties": {
    "addr:full":"Zeelaan 75 De Panne West-Vlaanderen 8660",
    "addr:housenumber":"75",
    "addr:postcode":"8660",
    "addr:street":"Zeelaan",
    "iso:country":"BE",
    "sg:address":"Zeelaan 75",
    "sg:city":"De Panne",
    "sg:orig_category":"Pharmaciens",
    "sg:phone":"+32 58 41 10 63",
    "sg:postcode":"8660",
    "sg:province":"West-Vlaanderen",
    "wof:name":"Erik Van Geluwe",
    "wof:placetype":"venue"
},
  "geometry": {"coordinates":[2.5856759548,51.1016120911],"type":"Point"}
}