{
  "type": "Feature",
  "properties": {
    "addr:full":"Gal. De La Porte Louise 203 Elsene/ixelles Bruxelles-Capitale 1050",
    "addr:housenumber":"203",
    "addr:postcode":"1050",
    "addr:street":"Gal. De La Porte Louise",
    "iso:country":"BE",
    "sg:address":"Gal. De La Porte Louise 203",
    "sg:city":"Elsene/ixelles",
    "sg:classifiers":[
        {
            "category":"Food & Beverages",
            "subcategory":"Fruits & Vegetables",
            "type":"Retail Goods"
        }
    ],
    "sg:phone":"+32 2 502 47 88",
    "sg:postcode":"1050",
    "sg:province":"Bruxelles-Capitale",
    "sg:tags":[
        "l\u00e9gumes",
        "gr"
    ],
    "wof:name":"Megatown International",
    "wof:placetype":"venue"
},
  "geometry": {"coordinates":[4.3567042351,50.835231781],"type":"Point"}
}