{
  "type": "Feature",
  "properties": {
    "addr:full":"Breugelweg 80 Overpelt Limburg 3900",
    "addr:housenumber":"80",
    "addr:postcode":"3900",
    "addr:street":"Breugelweg",
    "iso:country":"BE",
    "sg:address":"Breugelweg 80",
    "sg:city":"Overpelt",
    "sg:orig_category":"Parfumeries",
    "sg:phone":"+32 11 66 29 76",
    "sg:postcode":"3900",
    "sg:province":"Limburg",
    "wof:name":"Barbara Beckers",
    "wof:placetype":"venue"
},
  "geometry": {"coordinates":[5.4292068481,51.2025794983],"type":"Point"}
}