{
  "type": "Feature",
  "properties": {
    "iso:country":"BE",
    "sg:address":"Schuttersboomstraat 5",
    "sg:city":"Overpelt",
    "sg:classifiers":[
        {
            "category":"Wholesale",
            "subcategory":"Books, Periodicals, & Newspapers",
            "type":"Manufacturing & Wholesale Goods"
        }
    ],
    "sg:phone":"+32 11 64 75 29",
    "sg:postcode":"3900",
    "sg:province":"Limburg",
    "sg:tags":[
        "publisher",
        "book",
        "guide"
    ],
    "wof:name":"A.e.b. Uitgeverij B.v.b.a.",
    "wof:placetype":"venue"
},
  "geometry": {"coordinates":[5.4203281403,51.209438324],"type":"Point"}
}