{
  "type": "Feature",
  "properties": {
    "addr:full":"Hultjen 16 Evergem Oost-Vlaanderen 9940",
    "addr:housenumber":"16",
    "addr:postcode":"9940",
    "addr:street":"Hultjen;Oost-Vlaanderen",
    "iso:country":"BE",
    "sg:address":"Hultjen 16",
    "sg:city":"Evergem",
    "sg:orig_category":"Eleveurs de bovins. Eleveurs and marchands de porcs",
    "sg:phone":"+32 9 253 01 56",
    "sg:postcode":"9940",
    "sg:province":"Oost-Vlaanderen",
    "wof:name":"Alex Roegiers",
    "wof:placetype":"venue"
},
  "geometry": {"coordinates":[3.7101800442,51.1111564636],"type":"Point"}
}