{
  "type": "Feature",
  "properties": {
    "iso:country":"BE",
    "sg:address":"Leuvensestraat 90",
    "sg:city":"Oud-heverlee (sint-joris-weert)",
    "sg:classifiers":[
        {
            "category":"Real Estate",
            "subcategory":"Architect",
            "type":"Services"
        }
    ],
    "sg:phone":"+32 16 47 09 04",
    "sg:postcode":"3051",
    "sg:province":"Vlaams-Brabant",
    "wof:name":"Pattyn N",
    "wof:placetype":"venue"
},
  "geometry": {"coordinates":[4.6506938934,50.8102836609],"type":"Point"}
}