{
  "type": "Feature",
  "properties": {
    "addr:full":"Vedastusstraat 31ba Jabbeke West-Vlaanderen 8490",
    "addr:housenumber":"31ba",
    "addr:postcode":"8490",
    "addr:street":"Vedastusstraat",
    "iso:country":"BE",
    "sg:address":"Vedastusstraat 31ba",
    "sg:city":"Jabbeke",
    "sg:orig_category":"Pharmaciens",
    "sg:phone":"+32 50 81 21 03",
    "sg:postcode":"8490",
    "sg:province":"West-Vlaanderen",
    "wof:name":"Apotheek Vedastus",
    "wof:placetype":"venue"
},
  "geometry": {"coordinates":[3.063585043,51.1680297852],"type":"Point"}
}