{
  "type": "Feature",
  "properties": {
    "iso:country":"BE",
    "sg:address":"Gladiatorenstraat 35",
    "sg:city":"Kortrijk (marke)",
    "sg:classifiers":[
        {
            "category":"Social Services",
            "subcategory":"Job Training",
            "type":"Services"
        }
    ],
    "sg:phone":"+32 56 21 90 98",
    "sg:postcode":"8510",
    "sg:province":"West-Vlaanderen",
    "sg:tags":[
        "coordinator",
        "safety"
    ],
    "wof:name":"Maes P Bvba",
    "wof:placetype":"venue"
},
  "geometry": {"coordinates":[3.2210268974,50.7981338501],"type":"Point"}
}