{
  "type": "Feature",
  "properties": {
    "iso:country":"BE",
    "sg:address":"Nieuwpoortsesteenweg 2",
    "sg:city":"Oostende",
    "sg:orig_category":"Pharmaciens",
    "sg:phone":"+32 59 70 14 50",
    "sg:postcode":"8400",
    "sg:province":"West-Vlaanderen",
    "wof:name":"Apotheek Beuselinck",
    "wof:placetype":"venue"
},
  "geometry": {"coordinates":[2.9089560509,51.2246322632],"type":"Point"}
}