{
  "type": "Feature",
  "properties": {
    "iso:country":"BE",
    "sg:address":"Smetslaan 9",
    "sg:city":"Overijse",
    "sg:classifiers":[
        {
            "category":"Education",
            "subcategory":"School",
            "type":"Public Place"
        }
    ],
    "sg:phone":"+32 2 688 33 44",
    "sg:postcode":"3090",
    "sg:province":"Vlaams-Brabant",
    "sg:tags":[
        "-",
        "private"
    ],
    "wof:name":"Ipsen B",
    "wof:placetype":"venue"
},
  "geometry": {"coordinates":[4.5081558228,50.7416419983],"type":"Point"}
}