{
  "type": "Feature",
  "properties": {
    "addr:full":"Langenakkerlaan 44 Lochristi Oost-Vlaanderen 9080",
    "addr:housenumber":"44",
    "addr:postcode":"9080",
    "addr:street":"Langenakkerlaan",
    "iso:country":"BE",
    "sg:address":"Langenakkerlaan 44",
    "sg:city":"Lochristi",
    "sg:orig_category":"Produits surgel\u00e9s Gr",
    "sg:phone":"+32 9 355 50 78",
    "sg:postcode":"9080",
    "sg:province":"Oost-Vlaanderen",
    "wof:name":"Staelens-vandeweyer",
    "wof:placetype":"venue"
},
  "geometry": {"coordinates":[3.8567340374,51.0983314514],"type":"Point"}
}