{
  "type": "Feature",
  "properties": {
    "addr:full":"Rue De L'acad\u00e9mie 45 Li\u00e8ge 1 Li\u00e8ge 4000",
    "addr:housenumber":"45;1",
    "addr:postcode":"4000",
    "addr:street":"Rue De L'Acade \u0301Mie",
    "iso:country":"BE",
    "sg:address":"Rue De L'acad\u00e9mie 45",
    "sg:city":"Li\u00e8ge 1",
    "sg:classifiers":[
        {
            "category":"Building & Trades",
            "subcategory":"Pest Control",
            "type":"Services"
        }
    ],
    "sg:phone":"+32 4 223 05 99",
    "sg:postcode":"4000",
    "sg:province":"Li\u00e8ge",
    "sg:tags":[
        "painting",
        "contractor"
    ],
    "wof:name":"Cuypers M",
    "wof:placetype":"venue"
},
  "geometry": {"coordinates":[5.5669908524,50.6467590332],"type":"Point"}
}