{
  "type": "Feature",
  "properties": {
    "addr:full":"Vlasmarkt 8 Dendermonde Oost-Vlaanderen 9200",
    "addr:housenumber":"8",
    "addr:postcode":"9200",
    "addr:street":"Vlasmarkt;Oost-Vlaanderen",
    "iso:country":"BE",
    "sg:address":"Vlasmarkt 8",
    "sg:city":"Dendermonde",
    "sg:classifiers":[
        {
            "category":"Shopping",
            "subcategory":"Clothing, Apparel, & Fashions",
            "type":"Retail Goods"
        }
    ],
    "sg:phone":"+32 52 22 28 35",
    "sg:postcode":"9200",
    "sg:province":"Oost-Vlaanderen",
    "sg:tags":[
        "v\u00eatements",
        "pour",
        "dame"
    ],
    "wof:name":"Huis Maggy",
    "wof:placetype":"venue"
},
  "geometry": {"coordinates":[4.0988540649,51.0297203064],"type":"Point"}
}