{
  "type": "Feature",
  "properties": {
    "addr:full":"Industrieweg 7 Boom Antwerpen 2850",
    "addr:housenumber":"7",
    "addr:postcode":"2850",
    "addr:street":"Industrieweg",
    "iso:country":"BE",
    "sg:address":"Industrieweg 7",
    "sg:city":"Boom",
    "sg:classifiers":[
        {
            "category":"Wholesale",
            "subcategory":"Machinery & Supplies",
            "type":"Manufacturing & Wholesale Goods"
        }
    ],
    "sg:phone":"+32 3 353 10 10",
    "sg:postcode":"2850",
    "sg:province":"Antwerpen",
    "sg:tags":[
        "packing"
    ],
    "wof:name":"Inco Industry Nv",
    "wof:placetype":"venue"
},
  "geometry": {"coordinates":[4.3536720276,51.0997276306],"type":"Point"}
}