{
  "type": "Feature",
  "properties": {
    "addr:full":"Slingerstraat 1 Menen West-Vlaanderen 8930",
    "addr:housenumber":"1",
    "addr:postcode":"8930",
    "addr:street":"Slingerstraat",
    "iso:country":"BE",
    "sg:address":"Slingerstraat 1",
    "sg:city":"Menen",
    "sg:orig_category":"Eleveurs de bovins",
    "sg:phone":"+32 56 51 18 61",
    "sg:postcode":"8930",
    "sg:province":"West-Vlaanderen",
    "wof:name":"Martin Vervenne",
    "wof:placetype":"venue"
},
  "geometry": {"coordinates":[3.1157410145,50.8181037903],"type":"Point"}
}