{
  "type": "Feature",
  "properties": {
    "iso:country":"BE",
    "sg:address":"Chauss\u00c9e De Rixensart 7",
    "sg:city":"Lasne",
    "sg:orig_category":"Elektrische installaties voor woningen Woningbouw",
    "sg:phone":"+32 2 654 04 66",
    "sg:postcode":"1380",
    "sg:province":"Brabant Wallon",
    "wof:name":"A.t.r. Seegers",
    "wof:placetype":"venue"
},
  "geometry": {"coordinates":[4.5021710396,50.7028617859],"type":"Point"}
}