{
  "type": "Feature",
  "properties": {
    "addr:full":"Rue Chapelle Beaussart 80 Charleroi Hainaut 6030",
    "addr:housenumber":"80",
    "addr:postcode":"6030",
    "addr:street":"Rue Chapelle Beaussart;Hainaut",
    "iso:country":"BE",
    "sg:address":"Rue Chapelle Beaussart 80",
    "sg:city":"Charleroi",
    "sg:classifiers":[
        {
            "category":"Shopping",
            "subcategory":"Computers & Home Electronics",
            "type":"Retail Goods"
        }
    ],
    "sg:phone":"+32 2 381 21 86",
    "sg:postcode":"6030",
    "sg:province":"Hainaut",
    "sg:tags":[
        "electronic",
        "electrical",
        "equipment"
    ],
    "wof:name":"Altaluce Nv",
    "wof:placetype":"venue"
},
  "geometry": {"coordinates":[4.3574128151,50.7496376038],"type":"Point"}
}