{
  "type": "Feature",
  "properties": {
    "iso:country":"BE",
    "sg:address":"Chauss\u00c9e De Chokier 78",
    "sg:city":"Fl\u00c9malle",
    "sg:orig_category":"Artsen and specialisten",
    "sg:phone":"+32 4 275 75 80",
    "sg:postcode":"4400",
    "sg:province":"Li\u00e8ge",
    "wof:name":"G\u00c9n\u00c9vi\u00c8ve Bernaerts",
    "wof:placetype":"venue"
},
  "geometry": {"coordinates":[5.4576430321,50.5693130493],"type":"Point"}
}