{
  "type": "Feature",
  "properties": {
    "iso:country":"BE",
    "sg:address":"Rue De Verviers 29",
    "sg:city":"Eupen",
    "sg:orig_category":"M\u00e9decins and sp\u00e9cialistes",
    "sg:phone":"+32 87 55 54 01",
    "sg:postcode":"4700",
    "sg:province":"Li\u00e8ge",
    "wof:name":"Christel Baguette",
    "wof:placetype":"venue"
},
  "geometry": {"coordinates":[6.0249500275,50.6318473816],"type":"Point"}
}