{
  "type": "Feature",
  "properties": {
    "iso:country":"BE",
    "sg:address":"Avenue Des H\u00c9ros Leuzois 78",
    "sg:city":"Leuze-en-hainaut",
    "sg:orig_category":"DIVERSE RECREATIEVE ACTIVITEITEN",
    "sg:phone":"+32 69 66 10 49",
    "sg:postcode":"7900",
    "sg:province":"Hainaut",
    "wof:name":"L'echiquier Leuzois",
    "wof:placetype":"venue"
},
  "geometry": {"coordinates":[3.6392409801,50.6018257141],"type":"Point"}
}