{
  "type": "Feature",
  "properties": {
    "iso:country":"BE",
    "sg:address":"Molenweidestraat 3",
    "sg:city":"Destelbergen (heusden)",
    "sg:classifiers":[
        {
            "category":"Food & Beverages",
            "subcategory":"Meat & Fish",
            "type":"Retail Goods"
        }
    ],
    "sg:phone":"+32 9 230 84 75",
    "sg:postcode":"9070",
    "sg:province":"Oost-Vlaanderen",
    "sg:tags":[
        "poultry",
        "whol",
        "game",
        "-"
    ],
    "wof:name":"Joma",
    "wof:placetype":"venue"
},
  "geometry": {"coordinates":[3.793612957,51.0224227905],"type":"Point"}
}