{
  "type": "Feature",
  "properties": {
    "iso:country":"BE",
    "sg:address":"Ieperseweg 80",
    "sg:city":"Poperinge",
    "sg:classifiers":[
        {
            "category":"Wholesale",
            "subcategory":"Farm Supplies",
            "type":"Manufacturing & Wholesale Goods"
        }
    ],
    "sg:phone":"+32 57 33 52 84",
    "sg:postcode":"8970",
    "sg:province":"West-Vlaanderen",
    "sg:tags":[
        "machine",
        "agricoles",
        "mat\u00e9riel",
        "gr"
    ],
    "wof:name":"Gouwy Guido",
    "wof:placetype":"venue"
},
  "geometry": {"coordinates":[2.7716178894,50.8553771973],"type":"Point"}
}