{
  "type": "Feature",
  "properties": {
    "addr:full":"Heerbosstraat 26 Beringen (paal) Limburg 3583",
    "addr:housenumber":"26",
    "addr:postcode":"3583",
    "addr:street":"Heerbosstraat",
    "iso:country":"BE",
    "sg:address":"Heerbosstraat 26",
    "sg:city":"Beringen (paal)",
    "sg:classifiers":[
        {
            "category":"Utilities",
            "subcategory":"Telephone",
            "type":"Services"
        }
    ],
    "sg:phone":"+32 11 45 36 81",
    "sg:postcode":"3583",
    "sg:province":"Limburg",
    "sg:tags":[
        "-",
        "internet"
    ],
    "wof:name":"Worldsites",
    "wof:placetype":"venue"
},
  "geometry": {"coordinates":[5.1706700325,51.0389442444],"type":"Point"}
}