{
  "type": "Feature",
  "properties": {
    "addr:full":"Rue De La Lib\u00c9ration 68 Braine-le-comte Hainaut 7090",
    "addr:housenumber":"68",
    "addr:postcode":"7090",
    "addr:street":"Rue De La Libe\u0301Ration",
    "iso:country":"BE",
    "sg:address":"Rue De La Lib\u00c9ration 68",
    "sg:city":"Braine-le-comte",
    "sg:orig_category":"Groententeelt",
    "sg:phone":"+32 67 55 33 86",
    "sg:postcode":"7090",
    "sg:province":"Hainaut",
    "wof:name":"Cyrille Demeulemeester",
    "wof:placetype":"venue"
},
  "geometry": {"coordinates":[4.1499018669,50.6327171326],"type":"Point"}
}