{
  "type": "Feature",
  "properties": {
    "iso:country":"BE",
    "sg:address":"Avenue Nestor Martin 73",
    "sg:city":"Saint-hubert",
    "sg:classifiers":[
        {
            "category":"Retail",
            "subcategory":"Veterinary Services",
            "type":"Services"
        }
    ],
    "sg:phone":"+32 61 61 25 25",
    "sg:postcode":"6870",
    "sg:province":"Luxembourg",
    "sg:tags":[
        "veterinarian"
    ],
    "wof:name":"Neuvens D",
    "wof:placetype":"venue"
},
  "geometry": {"coordinates":[5.3659510612,50.0264511108],"type":"Point"}
}