{
  "type": "Feature",
  "properties": {
    "addr:full":"Rue Du Vallon 25 Plombieres/plombieres Li\u00e8ge 4850",
    "addr:housenumber":"25",
    "addr:postcode":"4850",
    "addr:street":"Rue Du Vallon",
    "iso:country":"BE",
    "sg:address":"Rue Du Vallon 25",
    "sg:city":"Plombieres/plombieres",
    "sg:classifiers":[
        {
            "category":"Cafe",
            "type":"Food & Drink"
        }
    ],
    "sg:phone":"+32 87 78 77 50",
    "sg:postcode":"4850",
    "sg:province":"Li\u00e8ge",
    "sg:tags":[
        "caf\u00e9s"
    ],
    "wof:name":"Wilhelmus Vluggen",
    "wof:placetype":"venue"
},
  "geometry": {"coordinates":[5.9626002312,50.7068138123],"type":"Point"}
}