{
  "type": "Feature",
  "properties": {
    "iso:country":"BE",
    "sg:address":"Treuveld 12",
    "sg:city":"Tervuren",
    "sg:orig_category":"Fleurs and plantes",
    "sg:phone":"+32 2 767 08 92",
    "sg:postcode":"3080",
    "sg:province":"Vlaams-Brabant",
    "wof:name":"Eddy Mommens",
    "wof:placetype":"venue"
},
  "geometry": {"coordinates":[4.5532398224,50.830619812],"type":"Point"}
}