{
  "type": "Feature",
  "properties": {
    "addr:full":"Zoning Industriel De L'europe 12 Leuze-en-hainaut Hainaut 7900",
    "addr:housenumber":"12",
    "addr:postcode":"7900",
    "addr:street":"Zoning Industriel De L'Europe",
    "iso:country":"BE",
    "sg:address":"Zoning Industriel De L'europe 12",
    "sg:city":"Leuze-en-hainaut",
    "sg:orig_category":"R\u00e9cup\u00e9ration de mati\u00e8res m\u00e9talliques recyclables and d\u00e9molisseurs de voitures",
    "sg:phone":"+32 69 66 96 00",
    "sg:postcode":"7900",
    "sg:province":"Hainaut",
    "wof:name":"Auto-pi\u00c8ces Deknudt G",
    "wof:placetype":"venue"
},
  "geometry": {"coordinates":[4.3742771149,50.8617973328],"type":"Point"}
}