{
  "type": "Feature",
  "properties": {
    "addr:full":"Vanderaeylaan 25 Ukkel/uccle Bruxelles-Capitale 1180",
    "addr:housenumber":"25",
    "addr:postcode":"1180",
    "addr:street":"Vanderaeylaan;/",
    "iso:country":"BE",
    "sg:address":"Vanderaeylaan 25",
    "sg:city":"Ukkel/uccle",
    "sg:orig_category":"Artsen and specialisten",
    "sg:phone":"+32 2 374 98 09",
    "sg:postcode":"1180",
    "sg:province":"Bruxelles-Capitale",
    "wof:name":"Consultation Nourrissons",
    "wof:placetype":"venue"
},
  "geometry": {"coordinates":[4.3372402191,50.7969474792],"type":"Point"}
}