{
  "type": "Feature",
  "properties": {
    "iso:country":"BE",
    "sg:address":"Rue Du Passage D'eau 1a",
    "sg:city":"Hermalle-sous-argenteau",
    "sg:classifiers":[
        {
            "category":"Bus Stop",
            "subcategory":"None",
            "type":"Transportation"
        }
    ],
    "sg:phone":"+32 4 227 31 03",
    "sg:postcode":"4681",
    "sg:province":"Li\u00e8ge",
    "sg:tags":[
        "photograph",
        "aerial"
    ],
    "wof:name":"Flying Cam S.a.",
    "wof:placetype":"venue"
},
  "geometry": {"coordinates":[5.6695728302,50.7134399414],"type":"Point"}
}