{
  "type": "Feature",
  "properties": {
    "iso:country":"BE",
    "sg:address":"Leo Baekelandstraat 10",
    "sg:city":"Gent",
    "sg:classifiers":[
        {
            "category":"Health Services",
            "subcategory":"Doctor",
            "type":"Services"
        }
    ],
    "sg:phone":"+32 9 222 57 50",
    "sg:postcode":"9000",
    "sg:province":"Oost-Vlaanderen",
    "sg:tags":[
        "medicinephysicians",
        "surgeon"
    ],
    "wof:name":"Kindt R",
    "wof:placetype":"venue"
},
  "geometry": {"coordinates":[3.7050909996,51.0253334045],"type":"Point"}
}