{
  "type": "Feature",
  "properties": {
    "iso:country":"BE",
    "sg:address":"Achterstraat 90",
    "sg:city":"Peer (wijchmaal)",
    "sg:classifiers":[
        {
            "category":"Autos & Motor Vehicles",
            "subcategory":"Recreational Vehicle Sales",
            "type":"Retail Goods"
        }
    ],
    "sg:phone":"+32 11 63 43 68",
    "sg:postcode":"3990",
    "sg:province":"Limburg",
    "sg:tags":[
        "saw"
    ],
    "wof:name":"Janssens",
    "wof:placetype":"venue"
},
  "geometry": {"coordinates":[5.4203538895,51.1215515137],"type":"Point"}
}