{
  "type": "Feature",
  "properties": {
    "iso:country":"BE",
    "sg:address":"Avenue Capitaine Piret 32",
    "sg:city":"Sint-pieters-woluwe/woluwe-saint-pierre",
    "sg:orig_category":"Avocats and conseillers juridiques",
    "sg:phone":"+32 2 771 61 14",
    "sg:postcode":"1150",
    "sg:province":"Bruxelles-Capitale",
    "wof:name":"Jo\u00cblle Vossen",
    "wof:placetype":"venue"
},
  "geometry": {"coordinates":[4.421807766,50.8379440308],"type":"Point"}
}