{
  "type": "Feature",
  "properties": {
    "iso:country":"BE",
    "sg:address":"Dorpsstraat 13",
    "sg:city":"Beveren",
    "sg:orig_category":"Alimentation sp\u00e9cialis\u00e9e. Catering and organisation de f\u00eates",
    "sg:phone":"+32 3 773 52 41",
    "sg:postcode":"9130",
    "sg:province":"Oost-Vlaanderen",
    "wof:name":"De Zeester",
    "wof:placetype":"venue"
},
  "geometry": {"coordinates":[4.1750750542,51.2897491455],"type":"Point"}
}