{
  "type": "Feature",
  "properties": {
    "iso:country":"BE",
    "sg:address":"Place De Leiche 1",
    "sg:city":"Fosses-la-ville",
    "sg:classifiers":[
        {
            "category":"Health Services",
            "subcategory":"Doctor",
            "type":"Services"
        }
    ],
    "sg:phone":"+32 71 71 18 67",
    "sg:postcode":"5070",
    "sg:province":"Namur",
    "sg:tags":[
        "medicinephysicians",
        "surgeon"
    ],
    "wof:name":"Crespeigne J",
    "wof:placetype":"venue"
},
  "geometry": {"coordinates":[4.6988668442,50.3960876465],"type":"Point"}
}