{
  "type": "Feature",
  "properties": {
    "addr:full":"Nieuwstad 54 Turnhout Antwerpen 2300",
    "addr:housenumber":"54",
    "addr:postcode":"2300",
    "addr:street":"Nieuwstad",
    "iso:country":"BE",
    "sg:address":"Nieuwstad 54",
    "sg:city":"Turnhout",
    "sg:classifiers":[
        {
            "category":"Shopping",
            "subcategory":"Clothing, Apparel, & Fashions",
            "type":"Retail Goods"
        }
    ],
    "sg:phone":"+32 14 41 31 88",
    "sg:postcode":"2300",
    "sg:province":"Antwerpen",
    "sg:tags":[
        "v\u00eatements",
        "pour",
        "dame"
    ],
    "wof:name":"Huis Sips",
    "wof:placetype":"venue"
},
  "geometry": {"coordinates":[4.9557337761,51.325378418],"type":"Point"}
}