{
  "type": "Feature",
  "properties": {
    "iso:country":"BE",
    "sg:address":"Rue De Huleu 23",
    "sg:city":"Ittre",
    "sg:orig_category":"Eleveurs de bovins",
    "sg:phone":"+32 67 64 62 73",
    "sg:postcode":"1460",
    "sg:province":"Brabant Wallon",
    "wof:name":"Joseph Winckel",
    "wof:placetype":"venue"
},
  "geometry": {"coordinates":[4.257912159,50.6407241821],"type":"Point"}
}