{
  "type": "Feature",
  "properties": {
    "iso:country":"BE",
    "sg:address":"Diestersteenweg 126",
    "sg:city":"Nieuwerkerken",
    "sg:classifiers":[
        {
            "category":"Shopping",
            "subcategory":"Shoes",
            "type":"Retail Goods"
        }
    ],
    "sg:phone":"+32 11 68 40 67",
    "sg:postcode":"3850",
    "sg:province":"Limburg",
    "sg:tags":[
        "slipper",
        "-"
    ],
    "wof:name":"Skoebidoe",
    "wof:placetype":"venue"
},
  "geometry": {"coordinates":[5.1888418198,50.863609314],"type":"Point"}
}