{
  "type": "Feature",
  "properties": {
    "addr:full":"Bld Alfred De Fontaine 10 Charleroi Hainaut 6000",
    "addr:housenumber":"10",
    "addr:postcode":"6000",
    "addr:street":"Bld Alfred De Fontaine;Hainaut",
    "iso:country":"BE",
    "sg:address":"Bld Alfred De Fontaine 10",
    "sg:city":"Charleroi",
    "sg:orig_category":"S\u00e9lection de personnel and placement",
    "sg:phone":"+32 71 30 17 28",
    "sg:postcode":"6000",
    "sg:province":"Hainaut",
    "wof:name":"Centrapsy",
    "wof:placetype":"venue"
},
  "geometry": {"coordinates":[4.4482541084,50.4113883972],"type":"Point"}
}