{
  "type": "Feature",
  "properties": {
    "iso:country":"BE",
    "sg:address":"Leuvensesteenweg 192",
    "sg:city":"Diest",
    "sg:orig_category":"Equipement divers pour commerces Meubles D\u00e9taillants, Am\u00e9nagement de B\u00e2timents et de Cuisines",
    "sg:phone":"+32 13 31 49 62",
    "sg:postcode":"3290",
    "sg:province":"Vlaams-Brabant",
    "wof:name":"Eurofrigo",
    "wof:placetype":"venue"
},
  "geometry": {"coordinates":[5.0362567902,50.9709701538],"type":"Point"}
}