{
  "type": "Feature",
  "properties": {
    "iso:country":"BE",
    "sg:address":"Marialoopsesteenweg 2e",
    "sg:city":"Tielt",
    "sg:classifiers":[
        {
            "category":"Food & Beverages",
            "subcategory":"Dairy",
            "type":"Retail Goods"
        }
    ],
    "sg:phone":"+32 51 40 22 60",
    "sg:postcode":"8700",
    "sg:province":"West-Vlaanderen",
    "sg:tags":[
        "product",
        "-"
    ],
    "wof:name":"Dejonckheere R",
    "wof:placetype":"venue"
},
  "geometry": {"coordinates":[3.3323910236,50.9801139832],"type":"Point"}
}