{
  "type": "Feature",
  "properties": {
    "addr:full":"Bleekstraat 6 Mechelen Antwerpen 2800",
    "addr:housenumber":"6",
    "addr:postcode":"2800",
    "addr:street":"Bleekstraat",
    "iso:country":"BE",
    "sg:address":"Bleekstraat 6",
    "sg:city":"Mechelen",
    "sg:classifiers":[
        {
            "category":"Manufacturing",
            "subcategory":"Chemicals & Compounds",
            "type":"Manufacturing & Wholesale Goods"
        }
    ],
    "sg:phone":"+32 15 29 06 19",
    "sg:postcode":"2800",
    "sg:province":"Antwerpen",
    "sg:tags":[
        "pharmaceutical",
        "product"
    ],
    "wof:name":"Aptec Diagnostics Nv",
    "wof:placetype":"venue"
},
  "geometry": {"coordinates":[4.4865307808,51.0277099609],"type":"Point"}
}