{
  "type": "Feature",
  "properties": {
    "addr:full":"Stationsstraat 43 Aalter Oost-Vlaanderen 9880",
    "addr:housenumber":"43",
    "addr:postcode":"9880",
    "addr:street":"Stationsstraat",
    "iso:country":"BE",
    "sg:address":"Stationsstraat 43",
    "sg:city":"Aalter",
    "sg:orig_category":"Banques and organismes de cr\u00e9dit",
    "sg:phone":"+32 9 374 71 11",
    "sg:postcode":"9880",
    "sg:province":"Oost-Vlaanderen",
    "wof:name":"V.d.k. Spaarbank",
    "wof:placetype":"venue"
},
  "geometry": {"coordinates":[3.4479169846,51.0855331421],"type":"Point"}
}