{
  "type": "Feature",
  "properties": {
    "iso:country":"BE",
    "sg:address":"Victor Demesmaekerstraat 103",
    "sg:city":"Halle",
    "sg:classifiers":[
        {
            "category":"Health Services",
            "subcategory":"Doctor",
            "type":"Services"
        }
    ],
    "sg:phone":"+32 2 361 32 42",
    "sg:postcode":"1500",
    "sg:province":"Vlaams-Brabant",
    "sg:tags":[
        "medicinephysicians",
        "surgeon"
    ],
    "wof:name":"Derluyn M",
    "wof:placetype":"venue"
},
  "geometry": {"coordinates":[4.2196769714,50.7354278564],"type":"Point"}
}