{
  "type": "Feature",
  "properties": {
    "addr:full":"Rue De Praetere 14 Bruxelles (ixelles) Bruxelles-Capitale 1050",
    "addr:housenumber":"14",
    "addr:postcode":"1050",
    "addr:street":"Rue De Praetere",
    "iso:country":"BE",
    "sg:address":"Rue De Praetere 14",
    "sg:city":"Bruxelles (ixelles)",
    "sg:classifiers":[
        {
            "category":"Communications",
            "subcategory":"Film & Video Production",
            "type":"Services"
        }
    ],
    "sg:phone":"+32 2 644 00 08",
    "sg:postcode":"1050",
    "sg:province":"Bruxelles-Capitale",
    "sg:tags":[
        "hiring",
        "distribution"
    ],
    "wof:name":"Films De L'elys\u00e9e (les)",
    "wof:placetype":"venue"
},
  "geometry": {"coordinates":[4.3700900078,50.8169784546],"type":"Point"}
}