{
  "type": "Feature",
  "properties": {
    "iso:country":"BE",
    "sg:address":"Appelveldstraat 73",
    "sg:city":"Bilzen",
    "sg:orig_category":"Verhuur diversen Winkelinrichting and handelsuitrusting Gh",
    "sg:phone":"+32 89 50 36 86",
    "sg:postcode":"3740",
    "sg:province":"Limburg",
    "wof:name":"Buntinx Leentje",
    "wof:placetype":"venue"
},
  "geometry": {"coordinates":[5.4713277817,50.9085350037],"type":"Point"}
}