{
  "type": "Feature",
  "properties": {
    "addr:full":"Hooiweg 30 Heist-op-den-berg Antwerpen 2222",
    "addr:housenumber":"30",
    "addr:postcode":"2222",
    "addr:street":"Hooiweg",
    "iso:country":"BE",
    "sg:address":"Hooiweg 30",
    "sg:city":"Heist-op-den-berg",
    "sg:orig_category":"Plaatsen van vloer- and muurbekleding Schilders",
    "sg:phone":"+32 15 25 12 84",
    "sg:postcode":"2222",
    "sg:province":"Antwerpen",
    "wof:name":"Willem Tubex",
    "wof:placetype":"venue"
},
  "geometry": {"coordinates":[4.7292399406,51.1032218933],"type":"Point"}
}