{
  "type": "Feature",
  "properties": {
    "iso:country":"BE",
    "sg:address":"Rue Balthasar Florence 27",
    "sg:city":"Namur",
    "sg:classifiers":[
        {
            "category":"Retail",
            "subcategory":"Auto Repair",
            "type":"Services"
        }
    ],
    "sg:phone":"+32 81 73 65 10",
    "sg:postcode":"5000",
    "sg:province":"Namur",
    "sg:tags":[
        "automobile",
        "servic",
        "electrical",
        "-"
    ],
    "wof:name":"Demonte J",
    "wof:placetype":"venue"
},
  "geometry": {"coordinates":[4.8446288109,50.4660339355],"type":"Point"}
}