{
  "type": "Feature",
  "properties": {
    "addr:full":"Meulebeeksesteenweg 12 Tielt West-Vlaanderen 8700",
    "addr:housenumber":"12",
    "addr:postcode":"8700",
    "addr:street":"Meulebeeksesteenweg",
    "iso:country":"BE",
    "sg:address":"Meulebeeksesteenweg 12",
    "sg:city":"Tielt",
    "sg:classifiers":[
        {
            "category":"Retail",
            "subcategory":"Auto Repair",
            "type":"Services"
        }
    ],
    "sg:phone":"+32 51 40 17 80",
    "sg:postcode":"8700",
    "sg:province":"West-Vlaanderen",
    "sg:tags":[
        "garage"
    ],
    "wof:name":"Decaigny",
    "wof:placetype":"venue"
},
  "geometry": {"coordinates":[3.3135509491,50.9850578308],"type":"Point"}
}