{
  "type": "Feature",
  "properties": {
    "iso:country":"BE",
    "sg:address":"Pastoor Meeusenlaan 5",
    "sg:city":"Schoten",
    "sg:classifiers":[
        {
            "category":"Building & Trades",
            "subcategory":"Construction",
            "type":"Services"
        }
    ],
    "sg:phone":"+32 3 658 59 83",
    "sg:postcode":"2900",
    "sg:province":"Antwerpen",
    "sg:tags":[
        "paper",
        "hanger"
    ],
    "wof:name":"Sprangers Interieur Bvba",
    "wof:placetype":"venue"
},
  "geometry": {"coordinates":[4.4955787659,51.2480163574],"type":"Point"}
}