{
  "type": "Feature",
  "properties": {
    "addr:full":"Sneppelaar 111 Londerzeel Vlaams-Brabant 1840",
    "addr:housenumber":"111",
    "addr:postcode":"1840",
    "addr:street":"Sneppelaar",
    "iso:country":"BE",
    "sg:address":"Sneppelaar 111",
    "sg:city":"Londerzeel",
    "sg:classifiers":[
        {
            "category":"Professional",
            "subcategory":"Accounting & Tax Preparation",
            "type":"Services"
        }
    ],
    "sg:phone":"+32 52 30 17 17",
    "sg:postcode":"1840",
    "sg:province":"Vlaams-Brabant",
    "sg:tags":[
        "accountant"
    ],
    "wof:name":"Rycken J",
    "wof:placetype":"venue"
},
  "geometry": {"coordinates":[4.2774791718,51.023475647],"type":"Point"}
}