{
  "type": "Feature",
  "properties": {
    "iso:country":"BE",
    "sg:address":"Avenue Emile Vandervelde 41",
    "sg:city":"Waremme",
    "sg:classifiers":[
        {
            "category":"Education",
            "subcategory":"Dance Studio",
            "type":"Public Place"
        }
    ],
    "sg:phone":"+32 19 32 38 55",
    "sg:postcode":"4300",
    "sg:province":"Li\u00e8ge",
    "sg:tags":[
        "school",
        "dancing"
    ],
    "wof:name":"Rosel",
    "wof:placetype":"venue"
},
  "geometry": {"coordinates":[5.2607889175,50.694984436],"type":"Point"}
}