{
  "type": "Feature",
  "properties": {
    "addr:full":"Pauwelstraat 7 Geraardsbergen Oost-Vlaanderen 9500",
    "addr:housenumber":"7",
    "addr:postcode":"9500",
    "addr:street":"Pauwelstraat",
    "iso:country":"BE",
    "sg:address":"Pauwelstraat 7",
    "sg:city":"Geraardsbergen",
    "sg:orig_category":"Installation \u00e9lectrique r\u00e9sidentielle. Installation \u00e9lectrique industrielle",
    "sg:phone":"+32 54 41 49 26",
    "sg:postcode":"9500",
    "sg:province":"Oost-Vlaanderen",
    "wof:name":"Vanderputten",
    "wof:placetype":"venue"
},
  "geometry": {"coordinates":[3.9204339981,50.7540473938],"type":"Point"}
}