{
  "type": "Feature",
  "properties": {
    "addr:full":"Avenue Jos\u00e9phine-charlotte 56 Rixensart Brabant Wallon 1330",
    "addr:housenumber":"56",
    "addr:postcode":"1330",
    "addr:street":"Avenue Jose\u0301Phine-Charlotte;Wallon",
    "iso:country":"BE",
    "sg:address":"Avenue Jos\u00e9phine-charlotte 56",
    "sg:city":"Rixensart",
    "sg:classifiers":[
        {
            "category":"Retail",
            "subcategory":"Veterinary Services",
            "type":"Services"
        }
    ],
    "sg:phone":"+32 475 76 79 41",
    "sg:postcode":"1330",
    "sg:province":"Brabant Wallon",
    "sg:tags":[
        "veterinarian"
    ],
    "wof:name":"Stacquez S",
    "wof:placetype":"venue"
},
  "geometry": {"coordinates":[4.5431261063,50.7068977356],"type":"Point"}
}