{
  "type": "Feature",
  "properties": {
    "iso:country":"BE",
    "sg:address":"Ruisbroek Dorp",
    "sg:city":"Puurs (ruisbroek)",
    "sg:classifiers":[
        {
            "category":"Arts & Performance",
            "subcategory":"Art Gallery",
            "type":"Entertainment"
        }
    ],
    "sg:phone":"+32 3 886 48 95",
    "sg:postcode":"2870",
    "sg:province":"Antwerpen",
    "wof:name":"Galery De Bres",
    "wof:placetype":"venue"
},
  "geometry": {"coordinates":[4.3308620453,51.0879364014],"type":"Point"}
}