{
  "type": "Feature",
  "properties": {
    "addr:full":"Leemstraat 12b1 Putte Antwerpen 2580",
    "addr:housenumber":"12b1",
    "addr:postcode":"2580",
    "addr:street":"Leemstraat",
    "iso:country":"BE",
    "sg:address":"Leemstraat 12b1",
    "sg:city":"Putte",
    "sg:orig_category":"Elektrische installaties voor woningen Industri\u00eble elektrische installaties",
    "sg:phone":"+32 15 75 41 85",
    "sg:postcode":"2580",
    "sg:province":"Antwerpen",
    "wof:name":"Vedelec",
    "wof:placetype":"venue"
},
  "geometry": {"coordinates":[4.6124610901,51.0587158203],"type":"Point"}
}