{
  "type": "Feature",
  "properties": {
    "addr:full":"Zoerselhofdreef 40 Zoersel Antwerpen 2980",
    "addr:housenumber":"40",
    "addr:postcode":"2980",
    "addr:street":"Zoerselhofdreef",
    "iso:country":"BE",
    "sg:address":"Zoerselhofdreef 40",
    "sg:city":"Zoersel",
    "sg:classifiers":[
        {
            "category":"Arena",
            "subcategory":"Sports Club",
            "type":"Entertainment"
        }
    ],
    "sg:phone":"+32 3 311 75 14",
    "sg:postcode":"2980",
    "sg:province":"Antwerpen",
    "wof:name":"T C De Meerheide",
    "wof:placetype":"venue"
},
  "geometry": {"coordinates":[4.7031202316,51.2574501038],"type":"Point"}
}