{
  "type": "Feature",
  "properties": {
    "addr:full":"Rue P\u00e8re Damien 5 Mouscron Hainaut 7700",
    "addr:housenumber":"5",
    "addr:postcode":"7700",
    "addr:street":"Rue Pe\u0300Re Damien",
    "iso:country":"BE",
    "sg:address":"Rue P\u00e8re Damien 5",
    "sg:city":"Mouscron",
    "sg:orig_category":"Non-Classified Establishments",
    "sg:phone":"+32 56 84 18 80",
    "sg:postcode":"7700",
    "sg:province":"Hainaut",
    "wof:name":"Neue Mode Nv",
    "wof:placetype":"venue"
},
  "geometry": {"coordinates":[3.2358679771,50.7475318909],"type":"Point"}
}