{
  "type": "Feature",
  "properties": {
    "iso:country":"BE",
    "sg:address":"Brouwerijstraat 35",
    "sg:city":"Aalter",
    "sg:classifiers":[
        {
            "category":"Cafe",
            "type":"Food & Drink"
        }
    ],
    "sg:phone":"+32 9 374 18 73",
    "sg:postcode":"9880",
    "sg:province":"Oost-Vlaanderen",
    "sg:tags":[
        "caf\u00e9s"
    ],
    "wof:name":"Caf\u00c9 Rialto",
    "wof:placetype":"venue"
},
  "geometry": {"coordinates":[3.4429869652,51.0831298828],"type":"Point"}
}