{
  "type": "Feature",
  "properties": {
    "addr:full":"Wijkstraat 35 Diepenbeek Limburg 3590",
    "addr:housenumber":"35",
    "addr:postcode":"3590",
    "addr:street":"Wijkstraat",
    "iso:country":"BE",
    "sg:address":"Wijkstraat 35",
    "sg:city":"Diepenbeek",
    "sg:classifiers":[
        {
            "category":"Shopping",
            "subcategory":"Pets & Pet Supplies",
            "type":"Retail Goods"
        }
    ],
    "sg:phone":"+32 11 87 29 73",
    "sg:postcode":"3590",
    "sg:province":"Limburg",
    "sg:tags":[
        "shop",
        "-"
    ],
    "wof:name":"Scooby Doo's",
    "wof:placetype":"venue"
},
  "geometry": {"coordinates":[5.4271860123,50.9069137573],"type":"Point"}
}