{
  "type": "Feature",
  "properties": {
    "iso:country":"BE",
    "sg:address":"Mallekotstr 62a",
    "sg:city":"Lier",
    "sg:classifiers":[
        {
            "category":"Government",
            "subcategory":"Department Of Motor Vehicles",
            "type":"Public Place"
        }
    ],
    "sg:phone":"+32 3 489 06 55",
    "sg:postcode":"2500",
    "sg:province":"Antwerpen",
    "sg:tags":[
        "equipment",
        "industrial",
        "transport",
        "motor-cars"
    ],
    "wof:name":"Garage A. Swinnen Bvba",
    "wof:placetype":"venue"
},
  "geometry": {"coordinates":[4.5711817741,51.146282196],"type":"Point"}
}