{
  "type": "Feature",
  "properties": {
    "iso:country":"BE",
    "sg:address":"Rue En Glain 105",
    "sg:city":"Luik (groot)",
    "sg:orig_category":"Jardinage",
    "sg:phone":"+32 4 226 48 44",
    "sg:postcode":"4000",
    "sg:province":"Li\u00e8ge",
    "wof:name":"Georges Ets",
    "wof:placetype":"venue"
},
  "geometry": {"coordinates":[5.5460400581,50.6462364197],"type":"Point"}
}