{
  "type": "Feature",
  "properties": {
    "addr:full":"Rue D'onnezies 1 Honnelles Hainaut 7387",
    "addr:housenumber":"1",
    "addr:postcode":"7387",
    "addr:street":"Rue D'Onnezies;Hainaut",
    "iso:country":"BE",
    "sg:address":"Rue D'onnezies 1",
    "sg:city":"Honnelles",
    "sg:classifiers":[
        {
            "category":"Insurance",
            "subcategory":"Insurance Agent",
            "type":"Services"
        }
    ],
    "sg:phone":"+32 65 75 92 03",
    "sg:postcode":"7387",
    "sg:province":"Hainaut",
    "sg:tags":[
        "verzekeringsmakelaars",
        "expert"
    ],
    "wof:name":"Bureau Tirlocq-colot",
    "wof:placetype":"venue"
},
  "geometry": {"coordinates":[3.6956520081,50.3320007324],"type":"Point"}
}