{
  "type": "Feature",
  "properties": {
    "iso:country":"BE",
    "sg:address":"Avenue Du Commerce 0",
    "sg:city":"Edingen",
    "sg:orig_category":"Gestion des d\u00e9charges and sites d\u00e9finitifs de stockage",
    "sg:phone":"+32 2 395 87 65",
    "sg:postcode":"7850",
    "sg:province":"Hainaut",
    "wof:name":"Containerpark Edingen-enghien",
    "wof:placetype":"venue"
},
  "geometry": {"coordinates":[4.051325798,50.7002754211],"type":"Point"}
}