{
  "type": "Feature",
  "properties": {
    "iso:country":"BE",
    "sg:address":"Retieseweg 28",
    "sg:city":"Geel",
    "sg:classifiers":[
        {
            "category":"Building & Trades",
            "subcategory":"Pest Control",
            "type":"Services"
        }
    ],
    "sg:phone":"+32 14 58 42 15",
    "sg:postcode":"2440",
    "sg:province":"Antwerpen",
    "sg:tags":[
        "painting",
        "contractor"
    ],
    "wof:name":"Meynen Bvba",
    "wof:placetype":"venue"
},
  "geometry": {"coordinates":[5.0128231049,51.1766357422],"type":"Point"}
}