{
  "type": "Feature",
  "properties": {
    "addr:full":"Rue De Hodimont 270 Verviers Li\u00e8ge 4800",
    "addr:housenumber":"270",
    "addr:postcode":"4800",
    "addr:street":"Rue De Hodimont",
    "iso:country":"BE",
    "sg:address":"Rue De Hodimont 270",
    "sg:city":"Verviers",
    "sg:orig_category":"Pain, p\u00e2tisseries and confiseries. Restaurants",
    "sg:phone":"+32 87 33 96 39",
    "sg:postcode":"4800",
    "sg:province":"Li\u00e8ge",
    "wof:name":"Glacier Mario",
    "wof:placetype":"venue"
},
  "geometry": {"coordinates":[5.8594508171,50.5917663574],"type":"Point"}
}