{
  "type": "Feature",
  "properties": {
    "iso:country":"BE",
    "sg:address":"Nijverheidsstraat 13",
    "sg:city":"Waarschoot",
    "sg:orig_category":"Brood, gebak and snoepgoed",
    "sg:phone":"+32 9 377 25 55",
    "sg:postcode":"9950",
    "sg:province":"Oost-Vlaanderen",
    "wof:name":"Bakkerij Guy Dhoore",
    "wof:placetype":"venue"
},
  "geometry": {"coordinates":[3.6049768925,51.1537399292],"type":"Point"}
}