{
  "type": "Feature",
  "properties": {
    "addr:full":"Rue Longue 48 Jodoigne Brabant Wallon 1370",
    "addr:housenumber":"48",
    "addr:postcode":"1370",
    "addr:street":"Rue Longue",
    "iso:country":"BE",
    "sg:address":"Rue Longue 48",
    "sg:city":"Jodoigne",
    "sg:orig_category":"Herstellingen and onderhoud van auto's Metaalafval, schrootrecyclage and sloperijen Voertuigen",
    "sg:phone":"+32 10 81 21 67",
    "sg:postcode":"1370",
    "sg:province":"Brabant Wallon",
    "wof:name":"Jacquemyn",
    "wof:placetype":"venue"
},
  "geometry": {"coordinates":[4.9097509384,50.7246932983],"type":"Point"}
}