{
  "type": "Feature",
  "properties": {
    "iso:country":"BE",
    "sg:address":"Kapellestraat 171",
    "sg:city":"Meulebeke",
    "sg:classifiers":[
        {
            "category":"Restaurant",
            "type":"Food & Drink"
        }
    ],
    "sg:phone":"+32 51 48 92 99",
    "sg:postcode":"8760",
    "sg:province":"West-Vlaanderen",
    "wof:name":"Tearoom 't Kapelhuis",
    "wof:placetype":"venue"
},
  "geometry": {"coordinates":[3.2822170258,50.9417114258],"type":"Point"}
}