{
  "type": "Feature",
  "properties": {
    "iso:country":"BE",
    "sg:address":"Jan Boonlaan 33",
    "sg:city":"Halle",
    "sg:classifiers":[
        {
            "category":"Professional",
            "subcategory":"Accounting & Tax Preparation",
            "type":"Services"
        }
    ],
    "sg:phone":"+32 2 356 13 37",
    "sg:postcode":"1500",
    "sg:province":"Vlaams-Brabant",
    "sg:tags":[
        "bookkeeper"
    ],
    "wof:name":"Merckx E",
    "wof:placetype":"venue"
},
  "geometry": {"coordinates":[4.2333498001,50.7415466309],"type":"Point"}
}