{
  "type": "Feature",
  "properties": {
    "iso:country":"BE",
    "sg:address":"Wingeweg 20",
    "sg:city":"Holsbeek",
    "sg:orig_category":"Kapsalons",
    "sg:phone":"+32 16 44 45 54",
    "sg:postcode":"3220",
    "sg:province":"Vlaams-Brabant",
    "wof:name":"Coiffure Christiane",
    "wof:placetype":"venue"
},
  "geometry": {"coordinates":[4.7603721619,50.9232635498],"type":"Point"}
}