{
  "type": "Feature",
  "properties": {
    "addr:full":"Nati\u00cbnlaan 14 Knokke-heist West-Vlaanderen 8300",
    "addr:housenumber":"14",
    "addr:postcode":"8300",
    "addr:street":"Natie\u0308Nlaan",
    "iso:country":"BE",
    "sg:address":"Nati\u00cbnlaan 14",
    "sg:city":"Knokke-heist",
    "sg:orig_category":"Stations-service and carburants. Entretien and r\u00e9parations de voitures",
    "sg:phone":"+32 50 60 95 00",
    "sg:postcode":"8300",
    "sg:province":"West-Vlaanderen",
    "wof:name":"Dibo",
    "wof:placetype":"venue"
},
  "geometry": {"coordinates":[3.2861700058,51.3386726379],"type":"Point"}
}