{
  "type": "Feature",
  "properties": {
    "iso:country":"BE",
    "sg:address":"Mirfeld 6",
    "sg:city":"Amel (heppenbach)",
    "sg:classifiers":[
        {
            "category":"Building & Trades",
            "subcategory":"Plumbing",
            "type":"Services"
        }
    ],
    "sg:phone":"+32 86 34 93 67",
    "sg:postcode":"4771",
    "sg:province":"Li\u00e8ge",
    "sg:tags":[
        "repair",
        "mainten",
        "-",
        "central",
        "heating"
    ],
    "wof:name":"Brodel J",
    "wof:placetype":"venue"
},
  "geometry": {"coordinates":[6.1880497932,50.359954834],"type":"Point"}
}