{
  "type": "Feature",
  "properties": {
    "iso:country":"BE",
    "sg:address":"Helhoekweg 18",
    "sg:city":"Rijkevorsel",
    "sg:orig_category":"Rusthuizen and serviceflats",
    "sg:phone":"+32 3 340 39 00",
    "sg:postcode":"2310",
    "sg:province":"Antwerpen",
    "wof:name":"Rusthuis Prinsenhof",
    "wof:placetype":"venue"
},
  "geometry": {"coordinates":[4.7559337616,51.345790863],"type":"Point"}
}