{
  "type": "Feature",
  "properties": {
    "iso:country":"BE",
    "sg:address":"Gemeenteplein 7",
    "sg:city":"Asse",
    "sg:classifiers":[
        {
            "category":"Shopping",
            "subcategory":"Music",
            "type":"Retail Goods"
        }
    ],
    "sg:phone":"+32 2 306 68 55",
    "sg:postcode":"1730",
    "sg:province":"Vlaams-Brabant",
    "sg:tags":[
        "-",
        "cd's",
        "recorded",
        "cassette"
    ],
    "wof:name":"Smiske ('t)",
    "wof:placetype":"venue"
},
  "geometry": {"coordinates":[4.1998410225,50.9101371765],"type":"Point"}
}