{
  "type": "Feature",
  "properties": {
    "addr:full":"Weggevoerdenstraat 88 Leuven Vlaams-Brabant 3012",
    "addr:housenumber":"88",
    "addr:postcode":"3012",
    "addr:street":"Weggevoerdenstraat",
    "iso:country":"BE",
    "sg:address":"Weggevoerdenstraat 88",
    "sg:city":"Leuven",
    "sg:orig_category":"Peinture. Rev\u00eatements pour sols and murs",
    "sg:phone":"+32 16 44 70 51",
    "sg:postcode":"3012",
    "sg:province":"Vlaams-Brabant",
    "wof:name":"Thomas Carlo",
    "wof:placetype":"venue"
},
  "geometry": {"coordinates":[4.7157812119,50.9247741699],"type":"Point"}
}