{
  "type": "Feature",
  "properties": {
    "iso:country":"BE",
    "sg:address":"Route De Floriheid 103a",
    "sg:city":"Malmedy",
    "sg:classifiers":[
        {
            "category":"Professional",
            "subcategory":"Management & Consulting",
            "type":"Services"
        }
    ],
    "sg:phone":"+32 80 77 07 37",
    "sg:postcode":"4960",
    "sg:province":"Li\u00e8ge",
    "sg:tags":[
        "consultant",
        "agency",
        "advertising"
    ],
    "wof:name":"Pigment Graphic",
    "wof:placetype":"venue"
},
  "geometry": {"coordinates":[6.0346927643,50.4173355103],"type":"Point"}
}