{
  "type": "Feature",
  "properties": {
    "iso:country":"BE",
    "sg:address":"Brugmannlaan 575",
    "sg:city":"Ukkel/uccle",
    "sg:orig_category":"Antiek Decoratieve kunst and kunstbenodigdheden",
    "sg:phone":"+32 2 344 66 68",
    "sg:postcode":"1180",
    "sg:province":"Bruxelles-Capitale",
    "wof:name":"Maison Dufrasne Ph.",
    "wof:placetype":"venue"
},
  "geometry": {"coordinates":[4.338599205,50.8012962341],"type":"Point"}
}