{
  "type": "Feature",
  "properties": {
    "addr:full":"Rue Du Cimeti\u00c8re 30 Sprimont Li\u00e8ge 4140",
    "addr:housenumber":"30",
    "addr:postcode":"4140",
    "addr:street":"Rue Du Cimetie\u0300Re",
    "iso:country":"BE",
    "sg:address":"Rue Du Cimeti\u00c8re 30",
    "sg:city":"Sprimont",
    "sg:orig_category":"Offices du tourisme",
    "sg:phone":"+32 4 382 21 05",
    "sg:postcode":"4140",
    "sg:province":"Li\u00e8ge",
    "wof:name":"Syndicat D'initiative",
    "wof:placetype":"venue"
},
  "geometry": {"coordinates":[5.6693248749,50.500125885],"type":"Point"}
}