{
  "type": "Feature",
  "properties": {
    "iso:country":"BE",
    "sg:address":"Hoolstmolenstraat 3",
    "sg:city":"Balen",
    "sg:orig_category":"Mat\u00e9riaux de construction Combustibles",
    "sg:phone":"+32 14 81 19 65",
    "sg:postcode":"2490",
    "sg:province":"Antwerpen",
    "wof:name":"Karel Lodewijckx",
    "wof:placetype":"venue"
},
  "geometry": {"coordinates":[5.1538472176,51.1517791748],"type":"Point"}
}