{
  "type": "Feature",
  "properties": {
    "iso:country":"BE",
    "sg:address":"Rue Du Presbyt\u00c8re 29",
    "sg:city":"Sint-jans-molenbeek/molenbeek-saint-jean",
    "sg:orig_category":"Pain, p\u00e2tisseries and confiseries",
    "sg:phone":"+32 2 414 03 03",
    "sg:postcode":"1080",
    "sg:province":"Bruxelles-Capitale",
    "wof:name":"Giovanna Giannone",
    "wof:placetype":"venue"
},
  "geometry": {"coordinates":[4.337553978,50.8574028015],"type":"Point"}
}