{
  "type": "Feature",
  "properties": {
    "iso:country":"BE",
    "sg:address":"Boulevard De Douai 29-9",
    "sg:city":"Li\u00e8ge 1 (grivegn\u00e9e)",
    "sg:classifiers":[
        {
            "category":"Home & Garden",
            "subcategory":"Hardware",
            "type":"Retail Goods"
        }
    ],
    "sg:phone":"+32 475 64 30 57",
    "sg:postcode":"4030",
    "sg:province":"Li\u00e8ge",
    "sg:tags":[
        "battery",
        "dry"
    ],
    "wof:name":"Cartissimo",
    "wof:placetype":"venue"
},
  "geometry": {"coordinates":[5.5945549011,50.621547699],"type":"Point"}
}