{
  "type": "Feature",
  "properties": {
    "iso:country":"BE",
    "sg:address":"Luchterenkerkweg 89",
    "sg:city":"Gent (drongen)",
    "sg:classifiers":[
        {
            "category":"Professional",
            "subcategory":"Management & Consulting",
            "type":"Services"
        }
    ],
    "sg:phone":"+32 9 226 79 16",
    "sg:postcode":"9031",
    "sg:province":"Oost-Vlaanderen",
    "sg:tags":[
        "consultant",
        "law"
    ],
    "wof:name":"Martens Bureau Alex J.",
    "wof:placetype":"venue"
},
  "geometry": {"coordinates":[3.6478130817,51.0574302673],"type":"Point"}
}