{
  "type": "Feature",
  "properties": {
    "iso:country":"BE",
    "sg:address":"Chemin D'hubeaumel 2",
    "sg:city":"Soignies",
    "sg:orig_category":"Rev\u00eatements pour sols and murs. Peinture. Eclairage et \u00e9quipements du foyer",
    "sg:phone":"+32 67 33 57 48",
    "sg:postcode":"7060",
    "sg:province":"Hainaut",
    "wof:name":"Laumonier",
    "wof:placetype":"venue"
},
  "geometry": {"coordinates":[4.0577311516,50.6018409729],"type":"Point"}
}