{
  "type": "Feature",
  "properties": {
    "addr:full":"Rue De L'etuve 24 Bruxelles Bruxelles-Capitale 1000",
    "addr:housenumber":"24",
    "addr:postcode":"1000",
    "addr:street":"Rue De L'Etuve",
    "iso:country":"BE",
    "sg:address":"Rue De L'etuve 24",
    "sg:city":"Bruxelles",
    "sg:classifiers":[
        {
            "category":"Shopping",
            "subcategory":"Gifts & Souvenirs",
            "type":"Retail Goods"
        }
    ],
    "sg:phone":"+32 2 514 23 06",
    "sg:postcode":"1000",
    "sg:province":"Bruxelles-Capitale",
    "sg:tags":[
        "-"
    ],
    "wof:name":"Brussels' Boutique",
    "wof:placetype":"venue"
},
  "geometry": {"coordinates":[4.3519678116,50.8579750061],"type":"Point"}
}