{
  "type": "Feature",
  "properties": {
    "iso:country":"BE",
    "sg:address":"Koestraat 181",
    "sg:city":"Roeselare",
    "sg:orig_category":"Kleding Schoenen Sport- and kampeermateriaal Watersport-, Sport- and Kampeerbenodigdheden Verhuur",
    "sg:phone":"+32 51 26 17 00",
    "sg:postcode":"8800",
    "sg:province":"West-Vlaanderen",
    "wof:name":"Sportline Roeselare",
    "wof:placetype":"venue"
},
  "geometry": {"coordinates":[3.148761034,50.9221801758],"type":"Point"}
}