{
  "type": "Feature",
  "properties": {
    "addr:full":"Gebr. Van Raemdonckstr. 15 Nijlen Antwerpen 2560",
    "addr:housenumber":"15",
    "addr:postcode":"2560",
    "iso:country":"BE",
    "sg:address":"Gebr. Van Raemdonckstr. 15",
    "sg:city":"Nijlen",
    "sg:orig_category":"Kapsalons",
    "sg:phone":"+32 3 481 92 16",
    "sg:postcode":"2560",
    "sg:province":"Antwerpen",
    "wof:name":"Coiffure Chris",
    "wof:placetype":"venue"
},
  "geometry": {"coordinates":[4.6672549248,51.1642951965],"type":"Point"}
}