{
  "type": "Feature",
  "properties": {
    "addr:full":"Rupelstraat 45 Schelle Antwerpen 2627",
    "addr:housenumber":"45",
    "addr:postcode":"2627",
    "addr:street":"Rupelstraat",
    "iso:country":"BE",
    "sg:address":"Rupelstraat 45",
    "sg:city":"Schelle",
    "sg:classifiers":[
        {
            "category":"Autos & Motor Vehicles",
            "subcategory":"Automobile Sales",
            "type":"Retail Goods"
        }
    ],
    "sg:phone":"+32 3 877 35 71",
    "sg:postcode":"2627",
    "sg:province":"Antwerpen",
    "sg:tags":[
        "car",
        "used",
        "-"
    ],
    "wof:name":"Antwerp Euro Car",
    "wof:placetype":"venue"
},
  "geometry": {"coordinates":[4.3356537819,51.125579834],"type":"Point"}
}