{
  "type": "Feature",
  "properties": {
    "iso:country":"BE",
    "sg:address":"Chauss\u00c9e De Tirlemont 218",
    "sg:city":"Jodoigne",
    "sg:orig_category":"H\u00f4tels. Restaurants",
    "sg:phone":"+32 10 81 48 84",
    "sg:postcode":"1370",
    "sg:province":"Brabant Wallon",
    "wof:name":"Auberge St.jean",
    "wof:placetype":"venue"
},
  "geometry": {"coordinates":[4.8814401627,50.7349586487],"type":"Point"}
}