{
  "type": "Feature",
  "properties": {
    "addr:full":"Rue Du Prince De Li\u00c8ge 48 Gerpinnes Hainaut 6280",
    "addr:housenumber":"48",
    "addr:postcode":"6280",
    "addr:street":"Rue Du Prince De Lie\u0300Ge;Hainaut",
    "iso:country":"BE",
    "sg:address":"Rue Du Prince De Li\u00c8ge 48",
    "sg:city":"Gerpinnes",
    "sg:orig_category":"Kapsalons",
    "sg:phone":"+32 71 50 28 34",
    "sg:postcode":"6280",
    "sg:province":"Hainaut",
    "wof:name":"Coiffure Nadine Marc",
    "wof:placetype":"venue"
},
  "geometry": {"coordinates":[4.5525832176,50.364025116],"type":"Point"}
}