{
  "type": "Feature",
  "properties": {
    "iso:country":"BE",
    "sg:address":"Bist 40",
    "sg:city":"Wilrijk",
    "sg:orig_category":"Mobistar Centres Telecommunicatieapparaten",
    "sg:phone":"+32 3 830 52 02",
    "sg:postcode":"2610",
    "sg:province":"Antwerpen",
    "wof:name":"Mobistar Center Wilrijk",
    "wof:placetype":"venue"
},
  "geometry": {"coordinates":[4.3933291435,51.1703529358],"type":"Point"}
}