{
  "type": "Feature",
  "properties": {
    "addr:full":"Rue Des Pr\u00c9s 1 Engis Li\u00e8ge 4480",
    "addr:housenumber":"1",
    "addr:postcode":"4480",
    "addr:street":"Rue Des Pre\u0301S",
    "iso:country":"BE",
    "sg:address":"Rue Des Pr\u00c9s 1",
    "sg:city":"Engis",
    "sg:orig_category":"Enseignement maternel and primaire",
    "sg:phone":"+32 4 275 29 69",
    "sg:postcode":"4480",
    "sg:province":"Li\u00e8ge",
    "wof:name":"Ecole Fond. Communale",
    "wof:placetype":"venue"
},
  "geometry": {"coordinates":[5.3985447884,50.5907783508],"type":"Point"}
}