{
  "type": "Feature",
  "properties": {
    "iso:country":"BE",
    "sg:address":"Blauwhuisstr 51",
    "sg:city":"Hulste",
    "sg:classifiers":[
        {
            "category":"Shopping",
            "type":"Retail Goods"
        }
    ],
    "sg:phone":"+32 56 66 71 97",
    "sg:postcode":"8531",
    "sg:province":"West-Vlaanderen",
    "sg:tags":[
        "metallurgy",
        "finished",
        "-",
        "metalworking",
        "metallic"
    ],
    "wof:name":"Roelandt Nv",
    "wof:placetype":"venue"
},
  "geometry": {"coordinates":[3.2876970768,50.8917579651],"type":"Point"}
}