{
  "type": "Feature",
  "properties": {
    "iso:country":"BE",
    "sg:address":"Roesbruggestraat 12",
    "sg:city":"Alveringem (beveren-aan-de-ijzer)",
    "sg:classifiers":[
        {
            "category":"Food & Beverages",
            "subcategory":"Groceries & Convenience Stores",
            "type":"Retail Goods"
        }
    ],
    "sg:phone":"+32 57 30 07 64",
    "sg:postcode":"8691",
    "sg:province":"West-Vlaanderen",
    "sg:tags":[
        "grocer"
    ],
    "wof:name":"Cokelaere M",
    "wof:placetype":"venue"
},
  "geometry": {"coordinates":[2.6407101154,50.9391212463],"type":"Point"}
}