{
  "type": "Feature",
  "properties": {
    "addr:full":"Rue Du Panorama 95 Verviers Li\u00e8ge 4801",
    "addr:housenumber":"95",
    "addr:postcode":"4801",
    "addr:street":"Rue Du Panorama",
    "iso:country":"BE",
    "sg:address":"Rue Du Panorama 95",
    "sg:city":"Verviers",
    "sg:orig_category":"Installation \u00e9lectrique r\u00e9sidentielle",
    "sg:phone":"+32 87 34 09 72",
    "sg:postcode":"4801",
    "sg:province":"Li\u00e8ge",
    "wof:name":"Gregory Frankar",
    "wof:placetype":"venue"
},
  "geometry": {"coordinates":[5.8930549622,50.5922393799],"type":"Point"}
}