{
  "type": "Feature",
  "properties": {
    "addr:full":"Rue Du Paradis 4b105 Ottignies-louvain-la-neuve Brabant Wallon 1348",
    "addr:housenumber":"4b105",
    "addr:postcode":"1348",
    "addr:street":"Rue Du Paradis",
    "iso:country":"BE",
    "sg:address":"Rue Du Paradis 4b105",
    "sg:city":"Ottignies-louvain-la-neuve",
    "sg:orig_category":"Software ontwikkeling and ontwerp",
    "sg:phone":"+32 10 45 51 69",
    "sg:postcode":"1348",
    "sg:province":"Brabant Wallon",
    "wof:name":"Positive Software",
    "wof:placetype":"venue"
},
  "geometry": {"coordinates":[4.6100621223,50.6721687317],"type":"Point"}
}