{
  "type": "Feature",
  "properties": {
    "addr:full":"Grand'place 55 Nivelles Brabant Wallon 1400",
    "addr:housenumber":"55",
    "addr:postcode":"1400",
    "addr:street":"Grand'Place",
    "iso:country":"BE",
    "sg:address":"Grand'place 55",
    "sg:city":"Nivelles",
    "sg:orig_category":"Brood, gebak and snoepgoed",
    "sg:phone":"+32 67 21 42 85",
    "sg:postcode":"1400",
    "sg:province":"Brabant Wallon",
    "wof:name":"M. Lombois",
    "wof:placetype":"venue"
},
  "geometry": {"coordinates":[4.3232650757,50.596786499],"type":"Point"}
}