{
  "type": "Feature",
  "properties": {
    "iso:country":"BE",
    "sg:address":"Rue Du Moniteur 7",
    "sg:city":"Bruxelles",
    "sg:classifiers":[
        {
            "category":"Shopping",
            "subcategory":"Books",
            "type":"Retail Goods"
        }
    ],
    "sg:postcode":"1000",
    "sg:province":"Bruxelles-Capitale",
    "sg:tags":[
        "bookseller"
    ],
    "wof:name":"Le Bon Livre",
    "wof:placetype":"venue"
},
  "geometry": {"coordinates":[4.364221096,50.8489151001],"type":"Point"}
}