{
  "type": "Feature",
  "properties": {
    "iso:country":"BE",
    "sg:address":"Bauterstraat 15",
    "sg:city":"Zulte",
    "sg:orig_category":"Eleveurs and marchands de porcs",
    "sg:phone":"+32 9 388 88 48",
    "sg:postcode":"9870",
    "sg:province":"Oost-Vlaanderen",
    "wof:name":"Agnes Staelens",
    "wof:placetype":"venue"
},
  "geometry": {"coordinates":[3.4904799461,50.9351234436],"type":"Point"}
}