{
  "type": "Feature",
  "properties": {
    "iso:country":"BE",
    "sg:address":"Heerstraat 15",
    "sg:city":"Neerpelt",
    "sg:classifiers":[
        {
            "category":"Restaurant",
            "type":"Food & Drink"
        }
    ],
    "sg:phone":"+32 11 64 01 71",
    "sg:postcode":"3910",
    "sg:province":"Limburg",
    "wof:name":"Koffiepotje",
    "wof:placetype":"venue"
},
  "geometry": {"coordinates":[5.4354910851,51.228843689],"type":"Point"}
}