{
  "type": "Feature",
  "properties": {
    "iso:country":"BE",
    "sg:address":"Westlaan 268",
    "sg:city":"Heusden-zolder",
    "sg:classifiers":[
        {
            "category":"Military Area",
            "subcategory":"Army Base",
            "type":"Public Place"
        }
    ],
    "sg:phone":"+32 13 52 10 11",
    "sg:postcode":"3550",
    "sg:province":"Limburg",
    "sg:tags":[
        "electrostatic",
        "coating",
        "powder"
    ],
    "wof:name":"Lakkerij Vandereyt Nv",
    "wof:placetype":"venue"
},
  "geometry": {"coordinates":[5.2387008667,50.9963531494],"type":"Point"}
}