{
  "type": "Feature",
  "properties": {
    "addr:full":"Ravenstraat 170 Buggenhout Oost-Vlaanderen 9255",
    "addr:housenumber":"170",
    "addr:postcode":"9255",
    "addr:street":"Ravenstraat",
    "iso:country":"BE",
    "sg:address":"Ravenstraat 170",
    "sg:city":"Buggenhout",
    "sg:orig_category":"Elektrische installaties voor woningen",
    "sg:phone":"+32 52 35 56 93",
    "sg:postcode":"9255",
    "sg:province":"Oost-Vlaanderen",
    "wof:name":"Dirk Van Laere",
    "wof:placetype":"venue"
},
  "geometry": {"coordinates":[4.188685894,50.987247467],"type":"Point"}
}