{
  "type": "Feature",
  "properties": {
    "addr:full":"Rue Des Martyrs 29 Arlon Luxembourg 6700",
    "addr:housenumber":"29",
    "addr:postcode":"6700",
    "addr:street":"Rue Des Martyrs",
    "iso:country":"BE",
    "sg:address":"Rue Des Martyrs 29",
    "sg:city":"Arlon",
    "sg:orig_category":"R\u00e9paration and restauration de meubles",
    "sg:phone":"+32 63 23 60 54",
    "sg:postcode":"6700",
    "sg:province":"Luxembourg",
    "wof:name":"Pascale Wery",
    "wof:placetype":"venue"
},
  "geometry": {"coordinates":[5.8098249435,49.6837997437],"type":"Point"}
}