{
  "type": "Feature",
  "properties": {
    "addr:full":"Spalbeekstraat 21 Hasselt Limburg 3510",
    "addr:housenumber":"21",
    "addr:postcode":"3510",
    "addr:street":"Spalbeekstraat",
    "iso:country":"BE",
    "sg:address":"Spalbeekstraat 21",
    "sg:city":"Hasselt",
    "sg:orig_category":"Epiceries. Journaux",
    "sg:phone":"+32 11 25 58 18",
    "sg:postcode":"3510",
    "sg:province":"Limburg",
    "wof:name":"Annie Volders",
    "wof:placetype":"venue"
},
  "geometry": {"coordinates":[5.2298331261,50.9492073059],"type":"Point"}
}