{
  "type": "Feature",
  "properties": {
    "addr:full":"Rue Pont De Bois 3 Walcourt Namur 5651",
    "addr:housenumber":"3",
    "addr:postcode":"5651",
    "addr:street":"Rue Pont De Bois",
    "iso:country":"BE",
    "sg:address":"Rue Pont De Bois 3",
    "sg:city":"Walcourt",
    "sg:orig_category":"Enseignement maternel and primaire",
    "sg:phone":"+32 71 61 41 99",
    "sg:postcode":"5651",
    "sg:province":"Namur",
    "wof:name":"Ecole Fond. Communale",
    "wof:placetype":"venue"
},
  "geometry": {"coordinates":[4.4008708,50.2877082825],"type":"Point"}
}