{
  "type": "Feature",
  "properties": {
    "addr:full":"De Beaulieulaan 25 Oudergem/auderghem Bruxelles-Capitale 1160",
    "addr:housenumber":"25",
    "addr:postcode":"1160",
    "addr:street":"De Beaulieulaan;/",
    "iso:country":"BE",
    "sg:address":"De Beaulieulaan 25",
    "sg:city":"Oudergem/auderghem",
    "sg:orig_category":"Marktonderzoekbureaus Reclamebureaus",
    "sg:phone":"+32 2 661 33 33",
    "sg:postcode":"1160",
    "sg:province":"Bruxelles-Capitale",
    "wof:name":"Imagineering Workshop",
    "wof:placetype":"venue"
},
  "geometry": {"coordinates":[4.4152078629,50.8141403198],"type":"Point"}
}