{
  "type": "Feature",
  "properties": {
    "iso:country":"BE",
    "sg:address":"Route De Wallonie 133",
    "sg:city":"Mons (baudour)",
    "sg:classifiers":[
        {
            "category":"Professional",
            "subcategory":"Accounting & Tax Preparation",
            "type":"Services"
        }
    ],
    "sg:phone":"+32 65 60 01 40",
    "sg:postcode":"7331",
    "sg:province":"Hainaut",
    "sg:tags":[
        "bookkeeper"
    ],
    "wof:name":"Dedisse C",
    "wof:placetype":"venue"
},
  "geometry": {"coordinates":[3.832367897,50.4841804504],"type":"Point"}
}