{
  "type": "Feature",
  "properties": {
    "addr:full":"Clos De La Qui\u00c8vre 3 Moeskroen/mouscron Hainaut 7700",
    "addr:housenumber":"3",
    "addr:postcode":"7700",
    "addr:street":"Clos De La Quie\u0300Vre",
    "iso:country":"BE",
    "sg:address":"Clos De La Qui\u00c8vre 3",
    "sg:city":"Moeskroen/mouscron",
    "sg:orig_category":"M\u00e9decins and sp\u00e9cialistes",
    "sg:phone":"+32 56 33 30 87",
    "sg:postcode":"7700",
    "sg:province":"Hainaut",
    "wof:name":"P. Jonckheere",
    "wof:placetype":"venue"
},
  "geometry": {"coordinates":[3.2323200703,50.7400932312],"type":"Point"}
}