{
  "type": "Feature",
  "properties": {
    "addr:full":"Statiestraat 96 Antwerpen Antwerpen 2600",
    "addr:housenumber":"96",
    "addr:postcode":"2600",
    "addr:street":"Statiestraat",
    "iso:country":"BE",
    "sg:address":"Statiestraat 96",
    "sg:city":"Antwerpen",
    "sg:orig_category":"Banques and organismes de cr\u00e9dit",
    "sg:phone":"+32 3 230 40 90",
    "sg:postcode":"2600",
    "sg:province":"Antwerpen",
    "wof:name":"Fortis",
    "wof:placetype":"venue"
},
  "geometry": {"coordinates":[4.4204521179,51.2179336548],"type":"Point"}
}