{
  "type": "Feature",
  "properties": {
    "iso:country":"BE",
    "sg:address":"Chauss\u00c9e D'alsemberg 427",
    "sg:city":"Ukkel/uccle",
    "sg:orig_category":"Blanchisseries and teintureries",
    "sg:phone":"+32 2 345 37 98",
    "sg:postcode":"1180",
    "sg:province":"Bruxelles-Capitale",
    "wof:name":"Spencer Shop",
    "wof:placetype":"venue"
},
  "geometry": {"coordinates":[4.3384962082,50.8130493164],"type":"Point"}
}