{
  "type": "Feature",
  "properties": {
    "iso:country":"BE",
    "sg:address":"Rue J D'outremeuse 13",
    "sg:city":"Luik",
    "sg:orig_category":"Artsen and specialisten",
    "sg:phone":"+32 4 342 23 20",
    "sg:postcode":"4020",
    "sg:province":"Li\u00e8ge",
    "wof:name":"Ciulla",
    "wof:placetype":"venue"
},
  "geometry": {"coordinates":[5.5825691223,50.6391983032],"type":"Point"}
}