{
  "type": "Feature",
  "properties": {
    "iso:country":"BE",
    "sg:address":"Rue Du Moulin 69",
    "sg:city":"Waremme",
    "sg:classifiers":[
        {
            "category":"Professional",
            "subcategory":"Engineering",
            "type":"Services"
        }
    ],
    "sg:phone":"+32 19 67 68 51",
    "sg:postcode":"4300",
    "sg:province":"Li\u00e8ge",
    "sg:tags":[
        "technical",
        "industrial",
        "-",
        "subcontracting"
    ],
    "wof:name":"C.m.e. Sprl",
    "wof:placetype":"venue"
},
  "geometry": {"coordinates":[5.2466697693,50.7073974609],"type":"Point"}
}