{
  "type": "Feature",
  "properties": {
    "addr:full":"Rue De Brabant 111 Bruxelles (schaerbeek) Bruxelles-Capitale 1030",
    "addr:housenumber":"111",
    "addr:postcode":"1030",
    "addr:street":"Rue De Brabant",
    "iso:country":"BE",
    "sg:address":"Rue De Brabant 111",
    "sg:city":"Bruxelles (schaerbeek)",
    "sg:classifiers":[
        {
            "category":"Retail",
            "subcategory":"Event Space",
            "type":"Services"
        }
    ],
    "sg:phone":"+32 2 219 62 61",
    "sg:postcode":"1030",
    "sg:province":"Bruxelles-Capitale",
    "sg:tags":[
        "product",
        "snack",
        "speciality",
        "potato",
        "stand",
        "fried"
    ],
    "wof:name":"Media Trading",
    "wof:placetype":"venue"
},
  "geometry": {"coordinates":[4.3640680313,50.8614730835],"type":"Point"}
}