{
  "type": "Feature",
  "properties": {
    "addr:full":"Heerbaan 264 Harelbeke West-Vlaanderen 8530",
    "addr:housenumber":"264",
    "addr:postcode":"8530",
    "addr:street":"Heerbaan",
    "iso:country":"BE",
    "sg:address":"Heerbaan 264",
    "sg:city":"Harelbeke",
    "sg:orig_category":"Bloemen and planten",
    "sg:phone":"+32 56 72 72 02",
    "sg:postcode":"8530",
    "sg:province":"West-Vlaanderen",
    "wof:name":"'t Gaverbloempje",
    "wof:placetype":"venue"
},
  "geometry": {"coordinates":[3.326595068,50.8502540588],"type":"Point"}
}