{
  "type": "Feature",
  "properties": {
    "addr:full":"Rue Des Combattants 61 Erquelinnes Hainaut 6560",
    "addr:housenumber":"61",
    "addr:postcode":"6560",
    "addr:street":"Rue Des Combattants",
    "iso:country":"BE",
    "sg:address":"Rue Des Combattants 61",
    "sg:city":"Erquelinnes",
    "sg:classifiers":[
        {
            "category":"Personal",
            "subcategory":"Beauty Salon",
            "type":"Services"
        }
    ],
    "sg:phone":"+32 71 55 56 11",
    "sg:postcode":"6560",
    "sg:province":"Hainaut",
    "sg:tags":[
        "de",
        "coiffure"
    ],
    "wof:name":"Josiane",
    "wof:placetype":"venue"
},
  "geometry": {"coordinates":[4.1162772179,50.3082084656],"type":"Point"}
}