{
  "type": "Feature",
  "properties": {
    "iso:country":"BE",
    "sg:address":"Hoogstraat 70",
    "sg:city":"Oostrozebeke",
    "sg:orig_category":"Benzinestations and brandstoffen",
    "sg:phone":"+32 56 66 63 59",
    "sg:postcode":"8780",
    "sg:province":"West-Vlaanderen",
    "wof:name":"Euro Belgo Station",
    "wof:placetype":"venue"
},
  "geometry": {"coordinates":[3.330121994,50.9204864502],"type":"Point"}
}