{
  "type": "Feature",
  "properties": {
    "iso:country":"BE",
    "sg:address":"Zaveldriesstraat 27",
    "sg:city":"Waterschei-zwartberg",
    "sg:classifiers":[
        {
            "category":"Bakery",
            "type":"Food & Drink"
        }
    ],
    "sg:phone":"+32 89 38 20 84",
    "sg:postcode":"3600",
    "sg:province":"Limburg",
    "sg:tags":[
        "cake",
        "product",
        "related",
        "bread"
    ],
    "wof:name":"De Achte Bakker",
    "wof:placetype":"venue"
},
  "geometry": {"coordinates":[5.4975337982,51.0058631897],"type":"Point"}
}