{
  "type": "Feature",
  "properties": {
    "addr:full":"Chauss\u00e9e De Bruxelles 248a Waterloo Brabant Wallon 1410",
    "addr:housenumber":"248a",
    "addr:postcode":"1410",
    "addr:street":"Chausse\u0301E De Bruxelles",
    "iso:country":"BE",
    "sg:address":"Chauss\u00e9e De Bruxelles 248a",
    "sg:city":"Waterloo",
    "sg:classifiers":[
        {
            "category":"Retail",
            "subcategory":"Laundry & Dry Cleaning",
            "type":"Services"
        }
    ],
    "sg:phone":"+32 2 354 50 88",
    "sg:postcode":"1410",
    "sg:province":"Brabant Wallon",
    "sg:tags":[
        "dyer",
        "cleaner"
    ],
    "wof:name":"Magradiva Sa",
    "wof:placetype":"venue"
},
  "geometry": {"coordinates":[4.3983211517,50.7158317566],"type":"Point"}
}