{
  "type": "Feature",
  "properties": {
    "iso:country":"BE",
    "sg:address":"Spoorweglaan 9",
    "sg:city":"Aalter",
    "sg:classifiers":[
        {
            "category":"Food & Beverages",
            "subcategory":"Specialty",
            "type":"Retail Goods"
        }
    ],
    "sg:phone":"+32 9 374 46 56",
    "sg:postcode":"9880",
    "sg:province":"Oost-Vlaanderen",
    "sg:tags":[
        "health",
        "dietary",
        "-",
        "biological"
    ],
    "wof:name":"Knoopsschat",
    "wof:placetype":"venue"
},
  "geometry": {"coordinates":[3.4486279488,51.0917282104],"type":"Point"}
}