{
  "type": "Feature",
  "properties": {
    "addr:full":"Berg 11 Oosterzele (balegem) Oost-Vlaanderen 9860",
    "addr:housenumber":"11",
    "addr:postcode":"9860",
    "addr:street":"Berg",
    "iso:country":"BE",
    "sg:address":"Berg 11",
    "sg:city":"Oosterzele (balegem)",
    "sg:classifiers":[
        {
            "category":"Bars & Pubs",
            "type":"Food & Drink"
        }
    ],
    "sg:phone":"+32 9 362 63 65",
    "sg:postcode":"9860",
    "sg:province":"Oost-Vlaanderen",
    "wof:name":"Steenput",
    "wof:placetype":"venue"
},
  "geometry": {"coordinates":[3.8137500286,50.9217338562],"type":"Point"}
}