{
  "type": "Feature",
  "properties": {
    "addr:full":"Diesterstraat 10 Sint-truiden Limburg 3800",
    "addr:housenumber":"10",
    "addr:postcode":"3800",
    "addr:street":"Diesterstraat",
    "iso:country":"BE",
    "sg:address":"Diesterstraat 10",
    "sg:city":"Sint-truiden",
    "sg:classifiers":[
        {
            "category":"Retail",
            "subcategory":"Repair Shop",
            "type":"Services"
        }
    ],
    "sg:phone":"+32 11 68 25 49",
    "sg:postcode":"3800",
    "sg:province":"Limburg",
    "sg:tags":[
        "machine",
        "sewing",
        "-"
    ],
    "wof:name":"Vandersmissen M",
    "wof:placetype":"venue"
},
  "geometry": {"coordinates":[5.1861181259,50.8165359497],"type":"Point"}
}