{
  "type": "Feature",
  "properties": {
    "addr:full":"August Van Landeghemstr. 92 Willebroek Antwerpen 2830",
    "addr:housenumber":"92",
    "addr:postcode":"2830",
    "addr:street":"August;Landeghemstr.",
    "iso:country":"BE",
    "sg:address":"August Van Landeghemstr. 92",
    "sg:city":"Willebroek",
    "sg:orig_category":"Diverse organisaties and verenigingen",
    "sg:phone":"+32 3 860 97 93",
    "sg:postcode":"2830",
    "sg:province":"Antwerpen",
    "wof:name":"Jeugdhuis Perron 4",
    "wof:placetype":"venue"
},
  "geometry": {"coordinates":[4.3625922203,51.0646858215],"type":"Point"}
}