{
  "type": "Feature",
  "properties": {
    "iso:country":"BE",
    "sg:address":"Rue Des Sorbiers 11",
    "sg:city":"Chaudfontaine",
    "sg:classifiers":[
        {
            "category":"Real Estate",
            "subcategory":"Architect",
            "type":"Services"
        }
    ],
    "sg:phone":"+32 4 368 74 45",
    "sg:postcode":"4050",
    "sg:province":"Li\u00e8ge",
    "wof:name":"Marissiaux L",
    "wof:placetype":"venue"
},
  "geometry": {"coordinates":[5.6434249878,50.5857200623],"type":"Point"}
}