{
  "type": "Feature",
  "properties": {
    "iso:country":"BE",
    "sg:address":"Wittebos 8",
    "sg:city":"Kortenaken",
    "sg:classifiers":[
        {
            "category":"Arena",
            "subcategory":"Sports Club",
            "type":"Entertainment"
        }
    ],
    "sg:phone":"+32 16 77 04 92",
    "sg:postcode":"3472",
    "sg:province":"Vlaams-Brabant",
    "sg:tags":[
        "de"
    ],
    "wof:name":"Lubanja Twins Bc",
    "wof:placetype":"venue"
},
  "geometry": {"coordinates":[5.0043668747,50.9013786316],"type":"Point"}
}