{
  "type": "Feature",
  "properties": {
    "addr:full":"Herzieningslaan 99 Anderlecht/anderlecht Bruxelles-Capitale 1070",
    "addr:housenumber":"99",
    "addr:postcode":"1070",
    "addr:street":"Herzieningslaan",
    "iso:country":"BE",
    "sg:address":"Herzieningslaan 99",
    "sg:city":"Anderlecht/anderlecht",
    "sg:orig_category":"Voedingsspeciaalzaken",
    "sg:phone":"+32 2 331 61 89",
    "sg:postcode":"1070",
    "sg:province":"Bruxelles-Capitale",
    "wof:name":"Regisana",
    "wof:placetype":"venue"
},
  "geometry": {"coordinates":[4.3268408775,50.8351211548],"type":"Point"}
}