{
  "type": "Feature",
  "properties": {
    "addr:full":"Waterstraat 24 Zottegem Oost-Vlaanderen 9620",
    "addr:housenumber":"24",
    "addr:postcode":"9620",
    "addr:street":"Waterstraat",
    "iso:country":"BE",
    "sg:address":"Waterstraat 24",
    "sg:city":"Zottegem",
    "sg:orig_category":"Winkelinrichting and handelsuitrusting Gh",
    "sg:phone":"+32 9 360 37 57",
    "sg:postcode":"9620",
    "sg:province":"Oost-Vlaanderen",
    "wof:name":"Automaten Bevo",
    "wof:placetype":"venue"
},
  "geometry": {"coordinates":[3.826775074,50.8646965027],"type":"Point"}
}