{
  "type": "Feature",
  "properties": {
    "iso:country":"BE",
    "sg:address":"Beaumont 15ba",
    "sg:city":"Stavelot",
    "sg:orig_category":"Sportclubs",
    "sg:phone":"+32 80 86 41 62",
    "sg:postcode":"4970",
    "sg:province":"Li\u00e8ge",
    "wof:name":"V.c. Stavelot",
    "wof:placetype":"venue"
},
  "geometry": {"coordinates":[5.997964859,50.3815231323],"type":"Point"}
}