{
  "type": "Feature",
  "properties": {
    "addr:full":"Rue Paul Devaux 5 Li\u00c8ge Li\u00e8ge 4000",
    "addr:housenumber":"5",
    "addr:postcode":"4000",
    "addr:street":"Rue Paul Devaux",
    "iso:country":"BE",
    "sg:address":"Rue Paul Devaux 5",
    "sg:city":"Li\u00c8ge",
    "sg:orig_category":"Experts-comptables",
    "sg:phone":"+32 4 252 43 03",
    "sg:postcode":"4000",
    "sg:province":"Li\u00e8ge",
    "wof:name":"Claude Warin",
    "wof:placetype":"venue"
},
  "geometry": {"coordinates":[5.5697960854,50.6320648193],"type":"Point"}
}