{
  "type": "Feature",
  "properties": {
    "iso:country":"BE",
    "sg:address":"Place Gustave Falmagne 5",
    "sg:city":"Namur",
    "sg:orig_category":"Artsen and specialisten",
    "sg:phone":"+32 81 73 41 59",
    "sg:postcode":"5000",
    "sg:province":"Namur",
    "wof:name":"R. Van Derperre",
    "wof:placetype":"venue"
},
  "geometry": {"coordinates":[4.8533620834,50.4662017822],"type":"Point"}
}