{
  "type": "Feature",
  "properties": {
    "iso:country":"BE",
    "sg:address":"Bevrijdingslaan 190",
    "sg:city":"Dendermonde",
    "sg:orig_category":"Installation de menuiserie en bois and plastique",
    "sg:phone":"+32 52 21 34 07",
    "sg:postcode":"9200",
    "sg:province":"Oost-Vlaanderen",
    "wof:name":"Pierre Dhondt",
    "wof:placetype":"venue"
},
  "geometry": {"coordinates":[4.0518331528,51.0234947205],"type":"Point"}
}