{
  "type": "Feature",
  "properties": {
    "iso:country":"BE",
    "sg:address":"Kasteelstraat 57",
    "sg:city":"Antwerpen",
    "sg:orig_category":"Boucheries",
    "sg:phone":"+32 3 238 05 41",
    "sg:postcode":"2000",
    "sg:province":"Antwerpen",
    "wof:name":"Paul Ivens",
    "wof:placetype":"venue"
},
  "geometry": {"coordinates":[4.392991066,51.2063293457],"type":"Point"}
}