{
  "type": "Feature",
  "properties": {
    "addr:full":"Route De L'abbaye 60 Chaudfontaine Li\u00e8ge 4052",
    "addr:housenumber":"60",
    "addr:postcode":"4052",
    "addr:street":"Route De L'Abbaye",
    "iso:country":"BE",
    "sg:address":"Route De L'abbaye 60",
    "sg:city":"Chaudfontaine",
    "sg:orig_category":"Diverse grafische activiteiten",
    "sg:phone":"+32 4 368 59 39",
    "sg:postcode":"4052",
    "sg:province":"Li\u00e8ge",
    "wof:name":"Bureau Graficom",
    "wof:placetype":"venue"
},
  "geometry": {"coordinates":[5.6438498497,50.5642585754],"type":"Point"}
}