{
  "type": "Feature",
  "properties": {
    "addr:full":"Rue Saint-nicolas 11 La Hulpe Brabant Wallon 1310",
    "addr:housenumber":"11",
    "addr:postcode":"1310",
    "addr:street":"Rue Saint-Nicolas",
    "iso:country":"BE",
    "sg:address":"Rue Saint-nicolas 11",
    "sg:city":"La Hulpe",
    "sg:orig_category":"Advocaten and juridische adviseurs",
    "sg:phone":"+32 2 653 29 81",
    "sg:postcode":"1310",
    "sg:province":"Brabant Wallon",
    "wof:name":"Ph. Leblanc",
    "wof:placetype":"venue"
},
  "geometry": {"coordinates":[4.491751194,50.7311096191],"type":"Point"}
}