{
  "type": "Feature",
  "properties": {
    "iso:country":"BE",
    "sg:address":"Rue Des Bruy\u00c8res 44",
    "sg:city":"Saint-ghislain",
    "sg:orig_category":"Installation de menuiserie en bois and plastique",
    "sg:phone":"+32 65 64 44 54",
    "sg:postcode":"7331",
    "sg:province":"Hainaut",
    "wof:name":"Claudy Letard",
    "wof:placetype":"venue"
},
  "geometry": {"coordinates":[3.8306930065,50.4886207581],"type":"Point"}
}