{
  "type": "Feature",
  "properties": {
    "addr:full":"Rijkestraat 50a Assenede (oosteeklo) Oost-Vlaanderen 9968",
    "addr:housenumber":"50a",
    "addr:postcode":"9968",
    "addr:street":"Rijkestraat",
    "iso:country":"BE",
    "sg:address":"Rijkestraat 50a",
    "sg:city":"Assenede (oosteeklo)",
    "sg:classifiers":[
        {
            "category":"Retail",
            "subcategory":"Auto Repair",
            "type":"Services"
        }
    ],
    "sg:phone":"+32 9 373 81 71",
    "sg:postcode":"9968",
    "sg:province":"Oost-Vlaanderen",
    "sg:tags":[
        "garage"
    ],
    "wof:name":"Van De Voorde M",
    "wof:placetype":"venue"
},
  "geometry": {"coordinates":[3.6813490391,51.1898651123],"type":"Point"}
}