{
  "type": "Feature",
  "properties": {
    "addr:full":"Kleine Hoolstraat 9 Herk-de-stad Limburg 3540",
    "addr:housenumber":"9",
    "addr:postcode":"3540",
    "addr:street":"Kleine Hoolstraat",
    "iso:country":"BE",
    "sg:address":"Kleine Hoolstraat 9",
    "sg:city":"Herk-de-stad",
    "sg:orig_category":"Voedingsspeciaalzaken",
    "sg:phone":"+32 13 55 41 57",
    "sg:postcode":"3540",
    "sg:province":"Limburg",
    "wof:name":"De Bosrank",
    "wof:placetype":"venue"
},
  "geometry": {"coordinates":[5.1655750275,50.9371566772],"type":"Point"}
}