{
  "type": "Feature",
  "properties": {
    "iso:country":"BE",
    "sg:address":"Rue Du Commerce 25",
    "sg:city":"Wavre",
    "sg:classifiers":[
        {
            "category":"Food & Beverages",
            "subcategory":"Dairy",
            "type":"Retail Goods"
        }
    ],
    "sg:phone":"+32 10 22 22 28",
    "sg:postcode":"1300",
    "sg:province":"Brabant Wallon",
    "sg:tags":[
        "product",
        "-"
    ],
    "wof:name":"Casi\u00e8re (la)",
    "wof:placetype":"venue"
},
  "geometry": {"coordinates":[4.6094841957,50.7161865234],"type":"Point"}
}