{
  "type": "Feature",
  "properties": {
    "addr:full":"Kruisstraat 42 Lierde (deftinge) Oost-Vlaanderen 9570",
    "addr:housenumber":"42",
    "addr:postcode":"9570",
    "addr:street":"Kruisstraat",
    "iso:country":"BE",
    "sg:address":"Kruisstraat 42",
    "sg:city":"Lierde (deftinge)",
    "sg:classifiers":[
        {
            "category":"Health Services",
            "subcategory":"Doctor",
            "type":"Services"
        }
    ],
    "sg:phone":"+32 54 41 32 88",
    "sg:postcode":"9570",
    "sg:province":"Oost-Vlaanderen",
    "sg:tags":[
        "medicinephysicians",
        "surgeon"
    ],
    "wof:name":"Desmidt Paul",
    "wof:placetype":"venue"
},
  "geometry": {"coordinates":[3.8349359035,50.7859687805],"type":"Point"}
}