{
  "type": "Feature",
  "properties": {
    "addr:full":"Rue Malgrave 1 Malmedy Li\u00e8ge 4960",
    "addr:housenumber":"1",
    "addr:postcode":"4960",
    "addr:street":"Rue Malgrave",
    "iso:country":"BE",
    "sg:address":"Rue Malgrave 1",
    "sg:city":"Malmedy",
    "sg:classifiers":[
        {
            "category":"Community Center",
            "type":"Public Place"
        }
    ],
    "sg:phone":"+32 80 79 98 30",
    "sg:postcode":"4960",
    "sg:province":"Li\u00e8ge",
    "sg:tags":[
        "medical"
    ],
    "wof:name":"Centre De Cure Et De Postcure les Hautes Fagnes",
    "wof:placetype":"venue"
},
  "geometry": {"coordinates":[6.0253472328,50.4267158508],"type":"Point"}
}