{
  "type": "Feature",
  "properties": {
    "addr:full":"Speurtstraat 45 Lede (oordegem) Oost-Vlaanderen 9340",
    "addr:housenumber":"45",
    "addr:postcode":"9340",
    "addr:street":"Speurtstraat",
    "iso:country":"BE",
    "sg:address":"Speurtstraat 45",
    "sg:city":"Lede (oordegem)",
    "sg:classifiers":[
        {
            "category":"Health Services",
            "subcategory":"Dentist",
            "type":"Services"
        }
    ],
    "sg:phone":"+32 9 369 74 38",
    "sg:postcode":"9340",
    "sg:province":"Oost-Vlaanderen",
    "wof:name":"Van Der Linden J-m",
    "wof:placetype":"venue"
},
  "geometry": {"coordinates":[3.8988409042,50.9607658386],"type":"Point"}
}