{
  "type": "Feature",
  "properties": {
    "addr:full":"Kamerstraat 22 Buggenhout Oost-Vlaanderen 9255",
    "addr:housenumber":"22",
    "addr:postcode":"9255",
    "addr:street":"Kamerstraat",
    "iso:country":"BE",
    "sg:address":"Kamerstraat 22",
    "sg:city":"Buggenhout",
    "sg:classifiers":[
        {
            "category":"Shopping",
            "subcategory":"Florist",
            "type":"Retail Goods"
        }
    ],
    "sg:phone":"+32 52 34 55 29",
    "sg:postcode":"9255",
    "sg:province":"Oost-Vlaanderen",
    "wof:name":"Frie En Lief",
    "wof:placetype":"venue"
},
  "geometry": {"coordinates":[4.2018032074,51.0194816589],"type":"Point"}
}