{
  "type": "Feature",
  "properties": {
    "addr:full":"Av. Fran\u00c7ois Sebrechts 48be4 Sint-jans-molenbeek/molenbeek-saint-jean Bruxelles-Capitale 1080",
    "addr:postcode":"1080",
    "addr:street":"Av. Franc\u0327Ois Sebrechts",
    "iso:country":"BE",
    "sg:address":"Av. Fran\u00c7ois Sebrechts 48be4",
    "sg:city":"Sint-jans-molenbeek/molenbeek-saint-jean",
    "sg:orig_category":"M\u00e9decins and sp\u00e9cialistes",
    "sg:phone":"+32 2 411 68 99",
    "sg:postcode":"1080",
    "sg:province":"Bruxelles-Capitale",
    "wof:name":"Ellen Anckaert",
    "wof:placetype":"venue"
},
  "geometry": {"coordinates":[4.3117499352,50.8646812439],"type":"Point"}
}