{
  "type": "Feature",
  "properties": {
    "iso:country":"BE",
    "sg:address":"Nieuwstraat 12",
    "sg:city":"Brecht",
    "sg:orig_category":"Elektrische installaties voor woningen",
    "sg:phone":"+32 3 313 97 75",
    "sg:postcode":"2960",
    "sg:province":"Antwerpen",
    "wof:name":"Paul Driessens",
    "wof:placetype":"venue"
},
  "geometry": {"coordinates":[4.6780328751,51.3462867737],"type":"Point"}
}