{
  "type": "Feature",
  "properties": {
    "addr:full":"Dorpelingenstraat 97 Bruxelles (auderghem) Bruxelles-Capitale 1160",
    "addr:housenumber":"97",
    "addr:postcode":"1160",
    "addr:street":"Dorpelingenstraat",
    "iso:country":"BE",
    "sg:address":"Dorpelingenstraat 97",
    "sg:city":"Bruxelles (auderghem)",
    "sg:classifiers":[
        {
            "category":"Health Services",
            "subcategory":"Health Practitioner",
            "type":"Services"
        }
    ],
    "sg:phone":"+32 2 673 98 42",
    "sg:postcode":"1160",
    "sg:province":"Bruxelles-Capitale",
    "sg:tags":[
        "physiotherapist"
    ],
    "wof:name":"Wybaux Olivier",
    "wof:placetype":"venue"
},
  "geometry": {"coordinates":[4.4309120178,50.8164100647],"type":"Point"}
}