{
  "type": "Feature",
  "properties": {
    "addr:full":"Buitensingel 60 Lommel Limburg 3920",
    "addr:housenumber":"60",
    "addr:postcode":"3920",
    "addr:street":"Buitensingel",
    "iso:country":"BE",
    "sg:address":"Buitensingel 60",
    "sg:city":"Lommel",
    "sg:orig_category":"V\u00eatements pour b\u00e9b\u00e9s and enfants. V\u00eatements pour Dames. V\u00eatements pour Hommes",
    "sg:phone":"+32 11 55 44 55",
    "sg:postcode":"3920",
    "sg:province":"Limburg",
    "wof:name":"Jbc Mode",
    "wof:placetype":"venue"
},
  "geometry": {"coordinates":[5.3159809113,51.221736908],"type":"Point"}
}