{
  "type": "Feature",
  "properties": {
    "iso:country":"BE",
    "sg:address":"Iepersteenweg 51ba",
    "sg:city":"Houthulst",
    "sg:classifiers":[
        {
            "category":"Arena",
            "subcategory":"Sports Club",
            "type":"Entertainment"
        }
    ],
    "sg:phone":"+32 51 54 57 24",
    "sg:postcode":"8650",
    "sg:province":"West-Vlaanderen",
    "sg:tags":[
        "terrain",
        "hors",
        "de",
        "installation",
        "sportifs"
    ],
    "wof:name":"D.v. Famkes Merkem",
    "wof:placetype":"venue"
},
  "geometry": {"coordinates":[2.8693199158,50.9711914062],"type":"Point"}
}