{
  "type": "Feature",
  "properties": {
    "addr:full":"Rue Neuve 49 Boussu Hainaut 7300",
    "addr:housenumber":"49",
    "addr:postcode":"7300",
    "addr:street":"Rue Neuve",
    "iso:country":"BE",
    "sg:address":"Rue Neuve 49",
    "sg:city":"Boussu",
    "sg:orig_category":"Ramassage and traitement des d\u00e9chets m\u00e9nagers",
    "sg:phone":"+32 65 79 31 16",
    "sg:postcode":"7300",
    "sg:province":"Hainaut",
    "wof:name":"Eco Containers",
    "wof:placetype":"venue"
},
  "geometry": {"coordinates":[3.7937569618,50.4311485291],"type":"Point"}
}