{
  "type": "Feature",
  "properties": {
    "iso:country":"BE",
    "sg:address":"Avenue Du Haut Pays 107",
    "sg:city":"Honnelles (athis)",
    "sg:classifiers":[
        {
            "category":"Professional",
            "subcategory":"Testing Lab",
            "type":"Services"
        }
    ],
    "sg:phone":"+32 65 63 11 05",
    "sg:postcode":"7387",
    "sg:province":"Hainaut",
    "sg:tags":[
        "chemist"
    ],
    "wof:name":"Jospin Sprl",
    "wof:placetype":"venue"
},
  "geometry": {"coordinates":[3.77967906,50.3618240356],"type":"Point"}
}