{
  "type": "Feature",
  "properties": {
    "addr:full":"Marcus Laurinstraat 53 Brugge West-Vlaanderen 8310",
    "addr:housenumber":"53",
    "addr:postcode":"8310",
    "addr:street":"Laurinstraat",
    "iso:country":"BE",
    "sg:address":"Marcus Laurinstraat 53",
    "sg:city":"Brugge",
    "sg:orig_category":"Artsen and specialisten",
    "sg:phone":"+32 50 35 06 66",
    "sg:postcode":"8310",
    "sg:province":"West-Vlaanderen",
    "wof:name":"Antony Van Eeghem",
    "wof:placetype":"venue"
},
  "geometry": {"coordinates":[3.244396925,51.215133667],"type":"Point"}
}