{
  "type": "Feature",
  "properties": {
    "addr:full":"Rue Des Carmes 32 Namur Namur 5000",
    "addr:housenumber":"32",
    "addr:postcode":"5000",
    "addr:street":"Rue Des Carmes",
    "iso:country":"BE",
    "sg:address":"Rue Des Carmes 32",
    "sg:city":"Namur",
    "sg:orig_category":"Disquaires",
    "sg:phone":"+32 81 22 49 59",
    "sg:postcode":"5000",
    "sg:province":"Namur",
    "wof:name":"Musique-loisirs",
    "wof:placetype":"venue"
},
  "geometry": {"coordinates":[4.8639259338,50.4660339355],"type":"Point"}
}