{
  "type": "Feature",
  "properties": {
    "iso:country":"BE",
    "sg:address":"Rue De Cond\u00e9 4",
    "sg:city":"Chi\u00e8vres",
    "sg:classifiers":[
        {
            "category":"Retail",
            "subcategory":"Veterinary Services",
            "type":"Services"
        }
    ],
    "sg:phone":"+32 68 65 74 68",
    "sg:postcode":"7950",
    "sg:province":"Hainaut",
    "sg:tags":[
        "veterinarian"
    ],
    "wof:name":"Jonckers F",
    "wof:placetype":"venue"
},
  "geometry": {"coordinates":[3.8050169945,50.5932044983],"type":"Point"}
}