{
  "type": "Feature",
  "properties": {
    "addr:full":"Brielstraat 94 Beveren (melsele) Oost-Vlaanderen 9120",
    "addr:housenumber":"94",
    "addr:postcode":"9120",
    "addr:street":"Brielstraat",
    "iso:country":"BE",
    "sg:address":"Brielstraat 94",
    "sg:city":"Beveren (melsele)",
    "sg:classifiers":[
        {
            "category":"Home & Garden",
            "subcategory":"Home Furnishings",
            "type":"Retail Goods"
        }
    ],
    "sg:phone":"+32 3 775 73 66",
    "sg:postcode":"9120",
    "sg:province":"Oost-Vlaanderen",
    "sg:tags":[
        "-",
        "bed",
        "mattress"
    ],
    "wof:name":"Pultina Meubelen",
    "wof:placetype":"venue"
},
  "geometry": {"coordinates":[4.2713108063,51.2319984436],"type":"Point"}
}