{
  "type": "Feature",
  "properties": {
    "addr:full":"Brekelen 9 Wuustwezel Antwerpen 2990",
    "addr:housenumber":"9",
    "addr:postcode":"2990",
    "addr:street":"Brekelen",
    "iso:country":"BE",
    "sg:address":"Brekelen 9",
    "sg:city":"Wuustwezel",
    "sg:orig_category":"Installatie van houten of kunststof schrijnwerk Installatie van metalen schrijnwerk",
    "sg:phone":"+32 3 669 72 47",
    "sg:postcode":"2990",
    "sg:province":"Antwerpen",
    "wof:name":"Van Looveren Juul",
    "wof:placetype":"venue"
},
  "geometry": {"coordinates":[4.5873842239,51.3876533508],"type":"Point"}
}