{
  "type": "Feature",
  "properties": {
    "addr:full":"Herenveldstraat 2ba Hoeselt Limburg 3730",
    "addr:postcode":"3730",
    "addr:street":"Herenveldstraat",
    "iso:country":"BE",
    "sg:address":"Herenveldstraat 2ba",
    "sg:city":"Hoeselt",
    "sg:orig_category":"Eleveurs d'animaux domestiques",
    "sg:phone":"+32 89 41 31 56",
    "sg:postcode":"3730",
    "sg:province":"Limburg",
    "wof:name":"Raymond Bertrangs",
    "wof:placetype":"venue"
},
  "geometry": {"coordinates":[5.496650219,50.855430603],"type":"Point"}
}