{
  "type": "Feature",
  "properties": {
    "addr:full":"Rue Du Bru 14 Gouvy (limerl\u00e9) Luxembourg 6670",
    "addr:housenumber":"14",
    "addr:postcode":"6670",
    "addr:street":"Rue Du Bru",
    "iso:country":"BE",
    "sg:address":"Rue Du Bru 14",
    "sg:city":"Gouvy (limerl\u00e9)",
    "sg:classifiers":[
        {
            "category":"Real Estate",
            "subcategory":"Architect",
            "type":"Services"
        }
    ],
    "sg:phone":"+32 80 51 77 28",
    "sg:postcode":"6670",
    "sg:province":"Luxembourg",
    "wof:name":"Garitte Ch",
    "wof:placetype":"venue"
},
  "geometry": {"coordinates":[5.9230799675,50.1580696106],"type":"Point"}
}