{
  "type": "Feature",
  "properties": {
    "iso:country":"BE",
    "sg:address":"Pijlkruidstraat 24",
    "sg:city":"Wuustwezel",
    "sg:classifiers":[
        {
            "category":"Airport",
            "subcategory":"International",
            "type":"Transportation"
        }
    ],
    "sg:phone":"+32 3 568 15 11",
    "sg:postcode":"2990",
    "sg:province":"Antwerpen",
    "sg:tags":[
        "-",
        "transport"
    ],
    "wof:name":"Walsh Western",
    "wof:placetype":"venue"
},
  "geometry": {"coordinates":[4.5551347733,51.3618392944],"type":"Point"}
}