{
  "type": "Feature",
  "properties": {
    "addr:full":"Rue Du Petit-leez 111 Gembloux Namur 5031",
    "addr:housenumber":"111",
    "addr:postcode":"5031",
    "addr:street":"Rue Du Petit-Leez;Namur",
    "iso:country":"BE",
    "sg:address":"Rue Du Petit-leez 111",
    "sg:city":"Gembloux",
    "sg:orig_category":"Eleveurs de bovins",
    "sg:phone":"+32 81 64 02 90",
    "sg:postcode":"5031",
    "sg:province":"Namur",
    "wof:name":"Charles Andre & Baudouin",
    "wof:placetype":"venue"
},
  "geometry": {"coordinates":[4.7727880478,50.5721511841],"type":"Point"}
}