{
  "type": "Feature",
  "properties": {
    "addr:full":"Leopoldlaan 89 Geraardsbergen Oost-Vlaanderen 9500",
    "addr:housenumber":"89",
    "addr:postcode":"9500",
    "addr:street":"Leopoldlaan",
    "iso:country":"BE",
    "sg:address":"Leopoldlaan 89",
    "sg:city":"Geraardsbergen",
    "sg:orig_category":"Etablissements Erotiques",
    "sg:phone":"+32 54 50 29 08",
    "sg:postcode":"9500",
    "sg:province":"Oost-Vlaanderen",
    "wof:name":"L'instant Terdeuse",
    "wof:placetype":"venue"
},
  "geometry": {"coordinates":[3.8843801022,50.7716445923],"type":"Point"}
}