{
  "type": "Feature",
  "properties": {
    "addr:full":"Rue Du Cimeti\u00e8re 7 Mettet Namur 5640",
    "addr:housenumber":"7",
    "addr:postcode":"5640",
    "addr:street":"Rue Du Cimetie\u0300Re",
    "iso:country":"BE",
    "sg:address":"Rue Du Cimeti\u00e8re 7",
    "sg:city":"Mettet",
    "sg:classifiers":[
        {
            "category":"Health Services",
            "subcategory":"Health Practitioner",
            "type":"Services"
        }
    ],
    "sg:phone":"+32 71 72 93 35",
    "sg:postcode":"5640",
    "sg:province":"Namur",
    "sg:tags":[
        "therapist",
        "speech"
    ],
    "wof:name":"Estievenart C",
    "wof:placetype":"venue"
},
  "geometry": {"coordinates":[4.6565928459,50.3190727234],"type":"Point"}
}