{
  "type": "Feature",
  "properties": {
    "addr:full":"Pastorijstraat 40 Evergem Oost-Vlaanderen 9940",
    "addr:housenumber":"40",
    "addr:postcode":"9940",
    "addr:street":"Pastorijstraat;Oost-Vlaanderen",
    "iso:country":"BE",
    "sg:address":"Pastorijstraat 40",
    "sg:city":"Evergem",
    "sg:orig_category":"Tweedehandsgoederen Verlichting and huishoudartikelen",
    "sg:phone":"+32 9 357 21 34",
    "sg:postcode":"9940",
    "sg:province":"Oost-Vlaanderen",
    "wof:name":"Oxfam Wereldwinkel",
    "wof:placetype":"venue"
},
  "geometry": {"coordinates":[3.7505700588,51.1787948608],"type":"Point"}
}