{
  "type": "Feature",
  "properties": {
    "addr:full":"Spaarzaamheidstraat 58 Oostende West-Vlaanderen 8400",
    "addr:housenumber":"58",
    "addr:postcode":"8400",
    "addr:street":"Spaarzaamheidstraat",
    "iso:country":"BE",
    "sg:address":"Spaarzaamheidstraat 58",
    "sg:city":"Oostende",
    "sg:classifiers":[
        {
            "category":"Personal",
            "subcategory":"Beauty Salon",
            "type":"Services"
        }
    ],
    "sg:phone":"+32 59 70 17 93",
    "sg:postcode":"8400",
    "sg:province":"West-Vlaanderen",
    "sg:tags":[
        "de",
        "coiffure"
    ],
    "wof:name":"Roger Hollevoet",
    "wof:placetype":"venue"
},
  "geometry": {"coordinates":[2.9002249241,51.218082428],"type":"Point"}
}