{
  "type": "Feature",
  "properties": {
    "addr:full":"Mereldreef 117 Keerbergen Antwerpen 2850",
    "addr:housenumber":"117",
    "addr:postcode":"2850",
    "addr:street":"Mereldreef",
    "iso:country":"BE",
    "sg:address":"Mereldreef 117",
    "sg:city":"Keerbergen",
    "sg:orig_category":"Paardenfokkers",
    "sg:phone":"+32 16 23 38 39",
    "sg:postcode":"2850",
    "sg:province":"Antwerpen",
    "wof:name":"Desert Arabians",
    "wof:placetype":"venue"
},
  "geometry": {"coordinates":[4.6839108467,51.0082817078],"type":"Point"}
}