{
  "type": "Feature",
  "properties": {
    "iso:country":"BE",
    "sg:address":"Rue Des Loups 1b1",
    "sg:city":"Wanze",
    "sg:orig_category":"Installation de menuiserie en bois and plastique",
    "sg:phone":"+32 85 23 64 91",
    "sg:postcode":"4520",
    "sg:province":"Li\u00e8ge",
    "wof:name":"Bawin F",
    "wof:placetype":"venue"
},
  "geometry": {"coordinates":[5.1931037903,50.5248031616],"type":"Point"}
}