{
  "type": "Feature",
  "properties": {
    "iso:country":"BE",
    "sg:address":"Quai Du Halage 19",
    "sg:city":"Vis\u00e9",
    "sg:classifiers":[
        {
            "category":"Health Services",
            "subcategory":"Doctor",
            "type":"Services"
        }
    ],
    "sg:phone":"+32 4 379 52 42",
    "sg:postcode":"4600",
    "sg:province":"Li\u00e8ge",
    "sg:tags":[
        "medicinephysicians",
        "surgeon"
    ],
    "wof:name":"Collette C",
    "wof:placetype":"venue"
},
  "geometry": {"coordinates":[5.6883168221,50.7384605408],"type":"Point"}
}