{
  "type": "Feature",
  "properties": {
    "iso:country":"BE",
    "sg:address":"Victoriestraat 9",
    "sg:city":"Turnhout",
    "sg:classifiers":[
        {
            "category":"Shopping",
            "subcategory":"Books",
            "type":"Retail Goods"
        }
    ],
    "sg:phone":"+32 14 42 43 93",
    "sg:postcode":"2300",
    "sg:province":"Antwerpen",
    "sg:tags":[
        "bookseller"
    ],
    "wof:name":"Taxandria Boekhandel Bvba",
    "wof:placetype":"venue"
},
  "geometry": {"coordinates":[4.9433279037,51.3220214844],"type":"Point"}
}