{
  "type": "Feature",
  "properties": {
    "addr:full":"Route D'arlon 64 Saint-leger Luxembourg 6747",
    "addr:housenumber":"64",
    "addr:postcode":"6747",
    "addr:street":"Route D'Arlon",
    "iso:country":"BE",
    "sg:address":"Route D'arlon 64",
    "sg:city":"Saint-leger",
    "sg:orig_category":"Houtbewerking and -behandeling",
    "sg:phone":"+32 63 23 96 50",
    "sg:postcode":"6747",
    "sg:province":"Luxembourg",
    "wof:name":"Scierie Eric Bouvy",
    "wof:placetype":"venue"
},
  "geometry": {"coordinates":[5.6651439667,49.6163139343],"type":"Point"}
}