{
  "type": "Feature",
  "properties": {
    "addr:full":"Avenue De La Closeraie 30 Li\u00c8ge Li\u00e8ge 4000",
    "addr:housenumber":"30",
    "addr:postcode":"4000",
    "addr:street":"Avenue De La Closeraie",
    "iso:country":"BE",
    "sg:address":"Avenue De La Closeraie 30",
    "sg:city":"Li\u00c8ge",
    "sg:orig_category":"M\u00e9decins and sp\u00e9cialistes",
    "sg:phone":"+32 4 224 00 12",
    "sg:postcode":"4000",
    "sg:province":"Li\u00e8ge",
    "wof:name":"Bernard Duquenne",
    "wof:placetype":"venue"
},
  "geometry": {"coordinates":[5.5553970337,50.6672744751],"type":"Point"}
}