{
  "type": "Feature",
  "properties": {
    "addr:full":"Kazernestraat 7 Lokeren Oost-Vlaanderen 9160",
    "addr:housenumber":"7",
    "addr:postcode":"9160",
    "addr:street":"Kazernestraat",
    "iso:country":"BE",
    "sg:address":"Kazernestraat 7",
    "sg:city":"Lokeren",
    "sg:classifiers":[
        {
            "category":"Education",
            "subcategory":"School",
            "type":"Public Place"
        }
    ],
    "sg:phone":"+32 9 348 27 90",
    "sg:postcode":"9160",
    "sg:province":"Oost-Vlaanderen",
    "sg:tags":[
        "primary"
    ],
    "wof:name":"Windekind Buiteng. Basis",
    "wof:placetype":"venue"
},
  "geometry": {"coordinates":[3.9892320633,51.1015625],"type":"Point"}
}