{
  "type": "Feature",
  "properties": {
    "addr:full":"Rue De Marbais 13 Floreffe (floriffoux) Namur 5150",
    "addr:housenumber":"13",
    "addr:postcode":"5150",
    "addr:street":"Rue De Marbais",
    "iso:country":"BE",
    "sg:address":"Rue De Marbais 13",
    "sg:city":"Floreffe (floriffoux)",
    "sg:classifiers":[
        {
            "category":"Utilities",
            "subcategory":"Fuel Oil & Lpg",
            "type":"Services"
        }
    ],
    "sg:phone":"+32 81 44 10 20",
    "sg:postcode":"5150",
    "sg:province":"Namur",
    "wof:name":"Dereppe-remy Sprl",
    "wof:placetype":"venue"
},
  "geometry": {"coordinates":[4.7710299492,50.4566192627],"type":"Point"}
}