{
  "type": "Feature",
  "properties": {
    "addr:full":"Gapaardstraat 3 Ardooie West-Vlaanderen 8850",
    "addr:housenumber":"3",
    "addr:postcode":"8850",
    "addr:street":"Gapaardstraat",
    "iso:country":"BE",
    "sg:address":"Gapaardstraat 3",
    "sg:city":"Ardooie",
    "sg:orig_category":"Cr\u00e9meries",
    "sg:phone":"+32 51 74 66 88",
    "sg:postcode":"8850",
    "sg:province":"West-Vlaanderen",
    "wof:name":"Fa. Cool-dejonckheere",
    "wof:placetype":"venue"
},
  "geometry": {"coordinates":[3.1737539768,50.9759254456],"type":"Point"}
}