{
  "type": "Feature",
  "properties": {
    "iso:country":"BE",
    "sg:address":"Ti\u00c8r Laurent 46",
    "sg:city":"Clavier",
    "sg:orig_category":"Alimentation sp\u00e9cialis\u00e9e",
    "sg:phone":"+32 83 63 45 33",
    "sg:postcode":"4560",
    "sg:province":"Li\u00e8ge",
    "wof:name":"Marie-j Henrard",
    "wof:placetype":"venue"
},
  "geometry": {"coordinates":[5.3128027916,50.3884773254],"type":"Point"}
}