{
  "type": "Feature",
  "properties": {
    "iso:country":"BE",
    "sg:address":"Musschaverstraat 15",
    "sg:city":"Nevele (landegem)",
    "sg:classifiers":[
        {
            "category":"Home & Garden",
            "subcategory":"Building Materials",
            "type":"Retail Goods"
        }
    ],
    "sg:phone":"+32 9 371 65 66",
    "sg:postcode":"9850",
    "sg:province":"Oost-Vlaanderen",
    "sg:tags":[
        "granite",
        "stone",
        "natural",
        "marble"
    ],
    "wof:name":"Gryp Vloeren Bvba",
    "wof:placetype":"venue"
},
  "geometry": {"coordinates":[3.5964889526,51.0569038391],"type":"Point"}
}