{
  "type": "Feature",
  "properties": {
    "addr:full":"Grand Place 4b6 Brussel/bruxelles Bruxelles-Capitale 1000",
    "addr:postcode":"4b6;/ bruxelles;1000",
    "addr:street":"Grand Place",
    "iso:country":"BE",
    "sg:address":"Grand Place 4b6",
    "sg:city":"Brussel/bruxelles",
    "sg:orig_category":"Effectenmakelaars and vermogensbeheer",
    "sg:phone":"+32 2 514 55 90",
    "sg:postcode":"1000",
    "sg:province":"Bruxelles-Capitale",
    "wof:name":"Von Ernst Belgium Management",
    "wof:placetype":"venue"
},
  "geometry": {"coordinates":[4.3518481255,50.8471450806],"type":"Point"}
}