{
  "type": "Feature",
  "properties": {
    "addr:full":"Bedrijfsstraat 19 Box 3 Peer (grote Brogel) Limburg 3990",
    "addr:housenumber":"19;3",
    "addr:postcode":"3990",
    "addr:street":"Bedrijfsstraat;Box;Grote Brogel Limburg",
    "iso:country":"BE",
    "sg:address":"Bedrijfsstraat 19 Box 3",
    "sg:city":"Peer (grote Brogel)",
    "sg:classifiers":[
        {
            "category":"Wholesale",
            "subcategory":"Scrap",
            "type":"Manufacturing & Wholesale Goods"
        }
    ],
    "sg:phone":"+32 11 79 32 38",
    "sg:postcode":"3990",
    "sg:province":"Limburg",
    "sg:tags":[
        "metal"
    ],
    "wof:name":"M&l Recycling",
    "wof:placetype":"venue"
},
  "geometry": {"coordinates":[5.4987192154,51.1376457214],"type":"Point"}
}