{
  "type": "Feature",
  "properties": {
    "addr:full":"Rue Du Coll\u00c8ge 36 Vis\u00c9 Li\u00e8ge 4600",
    "addr:housenumber":"36",
    "addr:postcode":"4600",
    "addr:street":"Rue Du Colle\u0300Ge",
    "iso:country":"BE",
    "sg:address":"Rue Du Coll\u00c8ge 36",
    "sg:city":"Vis\u00c9",
    "sg:orig_category":"Dameskledingzaken Schoenen",
    "sg:phone":"+32 4 374 06 76",
    "sg:postcode":"4600",
    "sg:province":"Li\u00e8ge",
    "wof:name":"Boutique Isabelle",
    "wof:placetype":"venue"
},
  "geometry": {"coordinates":[5.6950101852,50.7366714478],"type":"Point"}
}