{
  "type": "Feature",
  "properties": {
    "iso:country":"BE",
    "sg:address":"Antwerpsestraat 143",
    "sg:city":"Niel",
    "sg:classifiers":[
        {
            "category":"Fast Food",
            "type":"Food & Drink"
        }
    ],
    "sg:phone":"+32 3 844 63 64",
    "sg:postcode":"2845",
    "sg:province":"Antwerpen",
    "sg:tags":[
        "caf\u00e9s",
        "meeneem",
        "restaurant"
    ],
    "wof:name":"Pitta Cairo",
    "wof:placetype":"venue"
},
  "geometry": {"coordinates":[4.3319191933,51.110786438],"type":"Point"}
}