{
  "type": "Feature",
  "properties": {
    "addr:full":"Beekstraat 9 Sint-truiden Limburg 3800",
    "addr:housenumber":"9",
    "addr:postcode":"3800",
    "addr:street":"Beekstraat",
    "iso:country":"BE",
    "sg:address":"Beekstraat 9",
    "sg:city":"Sint-truiden",
    "sg:orig_category":"Avocats and conseillers juridiques",
    "sg:phone":"+32 11 69 43 69",
    "sg:postcode":"3800",
    "sg:province":"Limburg",
    "wof:name":"Jan Kevers",
    "wof:placetype":"venue"
},
  "geometry": {"coordinates":[5.1841759682,50.8153038025],"type":"Point"}
}