{
  "type": "Feature",
  "properties": {
    "iso:country":"BE",
    "sg:address":"Parc De La Sablonni\u00e8re 2 Box 11",
    "sg:city":"Mons",
    "sg:classifiers":[
        {
            "category":"Real Estate",
            "subcategory":"Architect",
            "type":"Services"
        }
    ],
    "sg:phone":"+32 477 96 07 94",
    "sg:postcode":"7000",
    "sg:province":"Hainaut",
    "wof:name":"Dirix C",
    "wof:placetype":"venue"
},
  "geometry": {"coordinates":[3.9828701019,50.4580192566],"type":"Point"}
}