{
  "type": "Feature",
  "properties": {
    "iso:country":"BE",
    "sg:address":"Dorpstraat 20",
    "sg:city":"Stabroek",
    "sg:orig_category":"Motos. R\u00e9parations and entretien de motos",
    "sg:phone":"+32 3 568 61 44",
    "sg:postcode":"2940",
    "sg:province":"Antwerpen",
    "wof:name":"Zwarte Arend",
    "wof:placetype":"venue"
},
  "geometry": {"coordinates":[4.363530159,51.331199646],"type":"Point"}
}