{
  "type": "Feature",
  "properties": {
    "iso:country":"BE",
    "sg:address":"Ruelle De Huy 12",
    "sg:city":"Havelange",
    "sg:orig_category":"Quincailleries. Rev\u00eatements de sols and murs",
    "sg:phone":"+32 83 63 46 07",
    "sg:postcode":"5376",
    "sg:province":"Namur",
    "wof:name":"Bernard Scoyer",
    "wof:placetype":"venue"
},
  "geometry": {"coordinates":[5.2432222366,50.3707084656],"type":"Point"}
}