{
  "type": "Feature",
  "properties": {
    "addr:full":"Emile De Blutslaan 14 Dilbeek Vlaams-Brabant 1702",
    "addr:housenumber":"14",
    "addr:postcode":"1702",
    "addr:street":"Emile;Blutslaan",
    "iso:country":"BE",
    "sg:address":"Emile De Blutslaan 14",
    "sg:city":"Dilbeek",
    "sg:orig_category":"Plaatsen van vloer- and muurbekleding Schilders",
    "sg:phone":"+32 2 466 05 97",
    "sg:postcode":"1702",
    "sg:province":"Vlaams-Brabant",
    "wof:name":"Willy Bolle",
    "wof:placetype":"venue"
},
  "geometry": {"coordinates":[4.2649321556,50.8648757935],"type":"Point"}
}