{
  "type": "Feature",
  "properties": {
    "addr:full":"Lindestraat 132 Gent (desteldonk) Oost-Vlaanderen 9042",
    "addr:housenumber":"132",
    "addr:postcode":"9042",
    "addr:street":"Lindestraat",
    "iso:country":"BE",
    "sg:address":"Lindestraat 132",
    "sg:city":"Gent (desteldonk)",
    "sg:classifiers":[
        {
            "category":"Farming",
            "subcategory":"Crops",
            "type":"Manufacturing & Wholesale Goods"
        }
    ],
    "sg:phone":"+32 9 356 96 01",
    "sg:postcode":"9042",
    "sg:province":"Oost-Vlaanderen",
    "sg:tags":[
        "vegetable",
        "fruit",
        "-",
        "grower"
    ],
    "wof:name":"Verniers C",
    "wof:placetype":"venue"
},
  "geometry": {"coordinates":[3.7816700935,51.1223831177],"type":"Point"}
}