{
  "type": "Feature",
  "properties": {
    "addr:full":"Weversstraat 26-3 Asse Vlaams-Brabant 1730",
    "addr:housenumber":"26-3",
    "addr:postcode":"1730",
    "addr:street":"Weversstraat",
    "iso:country":"BE",
    "sg:address":"Weversstraat 26-3",
    "sg:city":"Asse",
    "sg:classifiers":[
        {
            "category":"Personal",
            "subcategory":"Beauty Salon",
            "type":"Services"
        }
    ],
    "sg:phone":"+32 2 452 46 68",
    "sg:postcode":"1730",
    "sg:province":"Vlaams-Brabant",
    "wof:name":"Alpha",
    "wof:placetype":"venue"
},
  "geometry": {"coordinates":[4.2025718689,50.9091415405],"type":"Point"}
}