{
  "type": "Feature",
  "properties": {
    "addr:full":"Breestraat 132 Hasselt (grand) Limburg 3500",
    "addr:housenumber":"132",
    "addr:postcode":"3500",
    "addr:street":"Breestraat",
    "iso:country":"BE",
    "sg:address":"Breestraat 132",
    "sg:city":"Hasselt (grand)",
    "sg:orig_category":"Instituts de beaut\u00e9",
    "sg:phone":"+32 11 25 33 37",
    "sg:postcode":"3500",
    "sg:province":"Limburg",
    "wof:name":"Unicorn",
    "wof:placetype":"venue"
},
  "geometry": {"coordinates":[5.3277602196,50.9371795654],"type":"Point"}
}