{
  "type": "Feature",
  "properties": {
    "addr:full":"Raystraat 10 Begijnendijk Vlaams-Brabant 3130",
    "addr:housenumber":"10",
    "addr:postcode":"3130",
    "addr:street":"Raystraat",
    "iso:country":"BE",
    "sg:address":"Raystraat 10",
    "sg:city":"Begijnendijk",
    "sg:orig_category":"Producteurs de l\u00e9gumes",
    "sg:phone":"+32 16 53 44 29",
    "sg:postcode":"3130",
    "sg:province":"Vlaams-Brabant",
    "wof:name":"Willy Heiremans",
    "wof:placetype":"venue"
},
  "geometry": {"coordinates":[4.7747678757,50.9878921509],"type":"Point"}
}