{
  "type": "Feature",
  "properties": {
    "iso:country":"BE",
    "sg:address":"Jozef Van Gorpstraat 5",
    "sg:city":"Ravels",
    "sg:classifiers":[
        {
            "category":"Banks & Credit Unions",
            "subcategory":"Financial Services",
            "type":"Services"
        }
    ],
    "sg:phone":"+32 14 65 77 06",
    "sg:postcode":"2380",
    "sg:province":"Antwerpen",
    "sg:tags":[
        "loan",
        "mortgage"
    ],
    "wof:name":"Havermans Zakenkantoor Nv",
    "wof:placetype":"venue"
},
  "geometry": {"coordinates":[4.9919300079,51.3723907471],"type":"Point"}
}