{
  "type": "Feature",
  "properties": {
    "addr:full":"Rue L\u00c9on Willocq 4 Charleroi Hainaut 6044",
    "addr:housenumber":"4",
    "addr:postcode":"6044",
    "addr:street":"Rue Le\u0301On Willocq;Hainaut",
    "iso:country":"BE",
    "sg:address":"Rue L\u00c9on Willocq 4",
    "sg:city":"Charleroi",
    "sg:orig_category":"Enseignement maternel and primaire",
    "sg:phone":"+32 71 35 12 75",
    "sg:postcode":"6044",
    "sg:province":"Hainaut",
    "wof:name":"Ecole Fond. Communale",
    "wof:placetype":"venue"
},
  "geometry": {"coordinates":[4.386537075,50.439491272],"type":"Point"}
}