{
  "type": "Feature",
  "properties": {
    "addr:full":"Dorpstraat 179 Damme West-Vlaanderen 8340",
    "addr:housenumber":"179",
    "addr:postcode":"8340",
    "addr:street":"Dorpstraat",
    "iso:country":"BE",
    "sg:address":"Dorpstraat 179",
    "sg:city":"Damme",
    "sg:orig_category":"Warenhuizen",
    "sg:phone":"+32 50 35 53 99",
    "sg:postcode":"8340",
    "sg:province":"West-Vlaanderen",
    "wof:name":"Lidl",
    "wof:placetype":"venue"
},
  "geometry": {"coordinates":[3.3133480549,51.2033538818],"type":"Point"}
}