{
  "type": "Feature",
  "properties": {
    "addr:full":"Leffingestraat 254 Oostende West-Vlaanderen 8400",
    "addr:housenumber":"254",
    "addr:postcode":"8400",
    "addr:street":"Leffingestraat",
    "iso:country":"BE",
    "sg:address":"Leffingestraat 254",
    "sg:city":"Oostende",
    "sg:orig_category":"Drukkerijen and copyshops",
    "sg:phone":"+32 59 80 80 78",
    "sg:postcode":"8400",
    "sg:province":"West-Vlaanderen",
    "wof:name":"Etienne Portier",
    "wof:placetype":"venue"
},
  "geometry": {"coordinates":[2.9007899761,51.2149200439],"type":"Point"}
}