{
  "type": "Feature",
  "properties": {
    "iso:country":"BE",
    "sg:address":"Langeheidestraat 98",
    "sg:city":"Huldenberg",
    "sg:orig_category":"Kapsalons",
    "sg:phone":"+32 16 47 29 20",
    "sg:postcode":"3040",
    "sg:province":"Vlaams-Brabant",
    "wof:name":"Hair Point",
    "wof:placetype":"venue"
},
  "geometry": {"coordinates":[4.6358847618,50.7578315735],"type":"Point"}
}