{
  "type": "Feature",
  "properties": {
    "iso:country":"BE",
    "sg:address":"Gaston Roelandtsplein 17",
    "sg:city":"Brugge",
    "sg:orig_category":"Cr\u00e9dits divers",
    "sg:postcode":"8310",
    "sg:province":"West-Vlaanderen",
    "wof:name":"Bancontact-mister Cash",
    "wof:placetype":"venue"
},
  "geometry": {"coordinates":[3.2470378876,51.2006263733],"type":"Point"}
}