{
  "type": "Feature",
  "properties": {
    "addr:full":"Sint-trudostraat 10 Peer (wijchmaal) Limburg 3990",
    "addr:housenumber":"10",
    "addr:postcode":"3990",
    "addr:street":"Sint-Trudostraat",
    "iso:country":"BE",
    "sg:address":"Sint-trudostraat 10",
    "sg:city":"Peer (wijchmaal)",
    "sg:classifiers":[
        {
            "category":"Bars & Pubs",
            "type":"Food & Drink"
        }
    ],
    "sg:phone":"+32 11 63 59 13",
    "sg:postcode":"3990",
    "sg:province":"Limburg",
    "wof:name":"Dorpscaf\u00e9 't Pand",
    "wof:placetype":"venue"
},
  "geometry": {"coordinates":[5.4159879684,51.131061554],"type":"Point"}
}