{
  "type": "Feature",
  "properties": {
    "addr:full":"Bois De Chin 1 Celles (molenbaix) Hainaut 7760",
    "addr:housenumber":"1",
    "addr:postcode":"7760",
    "addr:street":"Bois De Chin",
    "iso:country":"BE",
    "sg:address":"Bois De Chin 1",
    "sg:city":"Celles (molenbaix)",
    "sg:classifiers":[
        {
            "category":"Shopping",
            "subcategory":"Bicycles & Sporting Goods",
            "type":"Retail Goods"
        }
    ],
    "sg:phone":"+32 69 55 89 02",
    "sg:postcode":"7760",
    "sg:province":"Hainaut",
    "sg:tags":[
        "-"
    ],
    "wof:name":"Multy Meka",
    "wof:placetype":"venue"
},
  "geometry": {"coordinates":[3.3899669647,50.6870002747],"type":"Point"}
}