{
  "type": "Feature",
  "properties": {
    "iso:country":"BE",
    "sg:address":"Rue Francisco Ferrer 26",
    "sg:city":"Courcelles",
    "sg:orig_category":"Fleurs and plantes",
    "sg:phone":"+32 71 84 21 63",
    "sg:postcode":"6181",
    "sg:province":"Hainaut",
    "wof:name":"Chrissi Flowers",
    "wof:placetype":"venue"
},
  "geometry": {"coordinates":[4.3278341293,50.4892082214],"type":"Point"}
}