{
  "type": "Feature",
  "properties": {
    "iso:country":"BE",
    "sg:address":"Terrestdreef 128",
    "sg:city":"Houthulst",
    "sg:classifiers":[
        {
            "category":"Utilities",
            "subcategory":"Refuse",
            "type":"Services"
        }
    ],
    "sg:phone":"+32 51 70 10 81",
    "sg:postcode":"8650",
    "sg:province":"West-Vlaanderen",
    "sg:tags":[
        "miller"
    ],
    "wof:name":"Lemahieu M",
    "wof:placetype":"venue"
},
  "geometry": {"coordinates":[2.9580140114,50.9885444641],"type":"Point"}
}