{
  "type": "Feature",
  "properties": {
    "addr:full":"Abrahamstraat 7 Riemst Limburg 3770",
    "addr:housenumber":"7",
    "addr:postcode":"3770",
    "addr:street":"Abrahamstraat",
    "iso:country":"BE",
    "sg:address":"Abrahamstraat 7",
    "sg:city":"Riemst",
    "sg:orig_category":"M\u00e9decins and sp\u00e9cialistes. M\u00e9decines alternatives",
    "sg:phone":"+32 12 45 21 89",
    "sg:postcode":"3770",
    "sg:province":"Limburg",
    "wof:name":"Dokter Simons Guido",
    "wof:placetype":"venue"
},
  "geometry": {"coordinates":[5.5969901085,50.8109016418],"type":"Point"}
}