{
  "type": "Feature",
  "properties": {
    "iso:country":"BE",
    "sg:address":"Vlamertingseweg 33",
    "sg:city":"Poperinge (reningelst)",
    "sg:orig_category":"Non-Classified Establishments",
    "sg:phone":"+32 57 33 39 30",
    "sg:postcode":"8970",
    "sg:province":"West-Vlaanderen",
    "wof:name":"Pauwelyn Voeders Nv",
    "wof:placetype":"venue"
},
  "geometry": {"coordinates":[2.7844669819,50.8256530762],"type":"Point"}
}