{
  "type": "Feature",
  "properties": {
    "iso:country":"BE",
    "sg:address":"Rue De La Place 15",
    "sg:city":"Mons (hyon)",
    "sg:classifiers":[
        {
            "category":"Professional",
            "subcategory":"Lawyer & Legal Services",
            "type":"Services"
        }
    ],
    "sg:phone":"+32 65 35 56 60",
    "sg:postcode":"7022",
    "sg:province":"Hainaut",
    "wof:name":"Gauqui\u00e9 D",
    "wof:placetype":"venue"
},
  "geometry": {"coordinates":[4.0181078911,50.4045410156],"type":"Point"}
}