{
  "type": "Feature",
  "properties": {
    "iso:country":"BE",
    "sg:address":"Paridaanstraat 15",
    "sg:city":"Zwevegem",
    "sg:orig_category":"Kapsalons",
    "sg:phone":"+32 56 75 82 20",
    "sg:postcode":"8550",
    "sg:province":"West-Vlaanderen",
    "wof:name":"Hair Design",
    "wof:placetype":"venue"
},
  "geometry": {"coordinates":[3.3609969616,50.8021583557],"type":"Point"}
}