{
  "type": "Feature",
  "properties": {
    "iso:country":"BE",
    "sg:address":"Rue De Jemeppe 14",
    "sg:city":"Grace-hollogne",
    "sg:orig_category":"Apotheken",
    "sg:phone":"+32 4 233 75 09",
    "sg:postcode":"4460",
    "sg:province":"Li\u00e8ge",
    "wof:name":"N. Gadisseur",
    "wof:placetype":"venue"
},
  "geometry": {"coordinates":[5.4858989716,50.6280441284],"type":"Point"}
}