{
  "type": "Feature",
  "properties": {
    "iso:country":"BE",
    "sg:address":"Emiel Van Hemeldonckstr. 38",
    "sg:city":"Hove",
    "sg:orig_category":"Quincailleries",
    "sg:phone":"+32 3 455 17 11",
    "sg:postcode":"2540",
    "sg:province":"Antwerpen",
    "wof:name":"Marc Lemmens",
    "wof:placetype":"venue"
},
  "geometry": {"coordinates":[4.4714112282,51.1534767151],"type":"Point"}
}