{
  "type": "Feature",
  "properties": {
    "addr:full":"Rue Du Bailli 49 Bruxelles (ixelles) Bruxelles-Capitale 1050",
    "addr:housenumber":"49",
    "addr:postcode":"1050",
    "addr:street":"Rue Du Bailli",
    "iso:country":"BE",
    "sg:address":"Rue Du Bailli 49",
    "sg:city":"Bruxelles (ixelles)",
    "sg:classifiers":[
        {
            "category":"Professional",
            "subcategory":"Lawyer & Legal Services",
            "type":"Services"
        }
    ],
    "sg:phone":"+32 2 646 01 13",
    "sg:postcode":"1050",
    "sg:province":"Bruxelles-Capitale",
    "wof:name":"Risselin M",
    "wof:placetype":"venue"
},
  "geometry": {"coordinates":[4.3610877991,50.8263664246],"type":"Point"}
}