{
  "type": "Feature",
  "properties": {
    "addr:full":"Konijnstr. 3 Zwevegem West-Vlaanderen 8551",
    "addr:housenumber":"3",
    "addr:postcode":"8551",
    "addr:street":"Konijnstr.",
    "iso:country":"BE",
    "sg:address":"Konijnstr. 3",
    "sg:city":"Zwevegem",
    "sg:classifiers":[
        {
            "category":"Professional",
            "type":"Services"
        }
    ],
    "sg:phone":"+32 56 64 52 52",
    "sg:postcode":"8551",
    "sg:province":"West-Vlaanderen",
    "sg:tags":[
        "transport",
        "road"
    ],
    "wof:name":"Bvba Lateur",
    "wof:placetype":"venue"
},
  "geometry": {"coordinates":[3.4109840393,50.782283783],"type":"Point"}
}