{
  "type": "Feature",
  "properties": {
    "addr:full":"Faubourg De Charleroi 4 Nivelles Brabant Wallon 1400",
    "addr:housenumber":"4",
    "addr:postcode":"1400",
    "addr:street":"Faubourg De Charleroi",
    "iso:country":"BE",
    "sg:address":"Faubourg De Charleroi 4",
    "sg:city":"Nivelles",
    "sg:classifiers":[
        {
            "category":"Professional",
            "subcategory":"Lawyer & Legal Services",
            "type":"Services"
        }
    ],
    "sg:phone":"+32 67 21 20 92",
    "sg:postcode":"1400",
    "sg:province":"Brabant Wallon",
    "sg:tags":[
        "notary"
    ],
    "wof:name":"Vanpee T",
    "wof:placetype":"venue"
},
  "geometry": {"coordinates":[4.326777935,50.5944290161],"type":"Point"}
}