{
  "type": "Feature",
  "properties": {
    "addr:full":"Hotelstraat 14 Geel Antwerpen 2260",
    "addr:housenumber":"14",
    "addr:postcode":"2260",
    "addr:street":"Hotelstraat",
    "iso:country":"BE",
    "sg:address":"Hotelstraat 14",
    "sg:city":"Geel",
    "sg:orig_category":"Tuinbenodigdheden Verlichting and huishoudartikelen Vloer- and muurbekleding",
    "sg:phone":"+32 14 58 28 92",
    "sg:postcode":"2260",
    "sg:province":"Antwerpen",
    "wof:name":"Kwantum",
    "wof:placetype":"venue"
},
  "geometry": {"coordinates":[4.9112768173,51.0883636475],"type":"Point"}
}