{
  "type": "Feature",
  "properties": {
    "iso:country":"BE",
    "sg:address":"Place Albert I 3",
    "sg:city":"Florenville",
    "sg:classifiers":[
        {
            "category":"Fast Food",
            "type":"Food & Drink"
        }
    ],
    "sg:phone":"+32 61 31 11 68",
    "sg:postcode":"6820",
    "sg:province":"Luxembourg",
    "sg:tags":[
        "fried",
        "stand",
        "potato"
    ],
    "wof:name":"Damin C",
    "wof:placetype":"venue"
},
  "geometry": {"coordinates":[5.3117861748,49.6979866028],"type":"Point"}
}