{
  "type": "Feature",
  "properties": {
    "addr:full":"Klaverstraat 31 Westerlo Antwerpen 2260",
    "addr:housenumber":"31",
    "addr:postcode":"2260",
    "addr:street":"Klaverstraat",
    "iso:country":"BE",
    "sg:address":"Klaverstraat 31",
    "sg:city":"Westerlo",
    "sg:orig_category":"Tuinen Vis- and schaaldierenkwekers",
    "sg:phone":"+32 14 26 60 51",
    "sg:postcode":"2260",
    "sg:province":"Antwerpen",
    "wof:name":"De Vijverhoeve",
    "wof:placetype":"venue"
},
  "geometry": {"coordinates":[4.8765921593,51.1044158936],"type":"Point"}
}