{
  "type": "Feature",
  "properties": {
    "addr:full":"Chauss\u00c9e De Charleroi 280 Corroy-le-chateau Namur 5032",
    "addr:housenumber":"280",
    "addr:postcode":"5032",
    "addr:street":"Chausse\u0301E De Charleroi;Namur",
    "iso:country":"BE",
    "sg:address":"Chauss\u00c9e De Charleroi 280",
    "sg:city":"Corroy-le-chateau",
    "sg:orig_category":"Rev\u00eatements de sols and murs. Installation de menuiserie en bois and plastique",
    "sg:phone":"+32 81 61 59 10",
    "sg:postcode":"5032",
    "sg:province":"Namur",
    "wof:name":"Van Hulst Didier Menuiserie",
    "wof:placetype":"venue"
},
  "geometry": {"coordinates":[4.6563310623,50.5459938049],"type":"Point"}
}