{
  "type": "Feature",
  "properties": {
    "addr:full":"Albert I Laan 157b-9a Nieuwpoort West-Vlaanderen 8620",
    "addr:postcode":"8620",
    "addr:street":"Albert I Laan 157B-9A",
    "iso:country":"BE",
    "sg:address":"Albert I Laan 157b-9a",
    "sg:city":"Nieuwpoort",
    "sg:classifiers":[
        {
            "category":"Wholesale",
            "subcategory":"Chemicals & Plastics",
            "type":"Manufacturing & Wholesale Goods"
        }
    ],
    "sg:phone":"+32 58 23 59 27",
    "sg:postcode":"8620",
    "sg:province":"West-Vlaanderen",
    "sg:tags":[
        "packing"
    ],
    "wof:name":"D.b.m. Bvba",
    "wof:placetype":"venue"
},
  "geometry": {"coordinates":[2.7205851078,51.1501846313],"type":"Point"}
}