{
  "type": "Feature",
  "properties": {
    "iso:country":"BE",
    "sg:address":"Ruiseledesteenweg 51 B",
    "sg:city":"Wingene",
    "sg:orig_category":"Electrom\u00e9nager, t\u00e9l\u00e9visions and radios. R\u00e9parations d'appareils \u00e9lectrom\u00e9nagers. Eclairage et \u00e9quipe",
    "sg:phone":"+32 51 65 65 63",
    "sg:postcode":"8750",
    "sg:province":"West-Vlaanderen",
    "wof:name":"Vromman Marnix (huishoudart.)",
    "wof:placetype":"venue"
},
  "geometry": {"coordinates":[3.3018200397,51.055431366],"type":"Point"}
}