{
  "type": "Feature",
  "properties": {
    "iso:country":"BE",
    "sg:address":"Rue De La Station 24",
    "sg:city":"Morlanwelz",
    "sg:orig_category":"Instituts de beaut\u00e9",
    "sg:phone":"+32 64 44 89 53",
    "sg:postcode":"7141",
    "sg:province":"Hainaut",
    "wof:name":"Josette Firla",
    "wof:placetype":"venue"
},
  "geometry": {"coordinates":[4.2609882355,50.4479675293],"type":"Point"}
}