{
  "type": "Feature",
  "properties": {
    "iso:country":"BE",
    "sg:address":"Begoniastraat 18",
    "sg:city":"Nazareth",
    "sg:classifiers":[
        {
            "category":"Real Estate",
            "subcategory":"Developer",
            "type":"Services"
        }
    ],
    "sg:phone":"+32 9 385 62 71",
    "sg:postcode":"9810",
    "sg:province":"Oost-Vlaanderen",
    "sg:tags":[
        "plomberie",
        "chauffage",
        "mat\u00e9riel",
        "gr",
        "pour"
    ],
    "wof:name":"R.s.c.",
    "wof:placetype":"venue"
},
  "geometry": {"coordinates":[3.65873909,50.9737854004],"type":"Point"}
}