{
  "type": "Feature",
  "properties": {
    "addr:full":"G. Gezellestraat 11 Brakel Oost-Vlaanderen 9660",
    "addr:housenumber":"11",
    "addr:postcode":"9660",
    "addr:street":"G. Gezellestraat",
    "iso:country":"BE",
    "sg:address":"G. Gezellestraat 11",
    "sg:city":"Brakel",
    "sg:orig_category":"Sportclubs",
    "sg:phone":"+32 55 42 66 18",
    "sg:postcode":"9660",
    "sg:province":"Oost-Vlaanderen",
    "wof:name":"De Gordelvrienden",
    "wof:placetype":"venue"
},
  "geometry": {"coordinates":[3.7642250061,50.8031082153],"type":"Point"}
}