{
  "type": "Feature",
  "properties": {
    "iso:country":"BE",
    "sg:address":"Jef Peetersstraat 6",
    "sg:city":"Turnhout",
    "sg:orig_category":"Boekenuitgeverijen",
    "sg:phone":"+32 14 42 52 60",
    "sg:postcode":"2300",
    "sg:province":"Antwerpen",
    "wof:name":"De Graal",
    "wof:placetype":"venue"
},
  "geometry": {"coordinates":[4.9231958389,51.323677063],"type":"Point"}
}