{
  "type": "Feature",
  "properties": {
    "addr:full":"Reigerstraat 61 Oosterzele Oost-Vlaanderen 9860",
    "addr:housenumber":"61",
    "addr:postcode":"9860",
    "addr:street":"Reigerstraat;Oost-Vlaanderen",
    "iso:country":"BE",
    "sg:address":"Reigerstraat 61",
    "sg:city":"Oosterzele",
    "sg:classifiers":[
        {
            "category":"Wholesale",
            "subcategory":"Fruits & Vegetables",
            "type":"Manufacturing & Wholesale Goods"
        }
    ],
    "sg:phone":"+32 9 362 45 83",
    "sg:postcode":"9860",
    "sg:province":"Oost-Vlaanderen",
    "sg:tags":[
        "whol",
        "-",
        "potato"
    ],
    "wof:name":"Aardappelhandel Gebr Aelbrecht Bvba",
    "wof:placetype":"venue"
},
  "geometry": {"coordinates":[3.8257229328,50.9568901062],"type":"Point"}
}