{
  "type": "Feature",
  "properties": {
    "iso:country":"BE",
    "sg:address":"Wijnstraat 2",
    "sg:city":"Riemst",
    "sg:orig_category":"Enseignement maternel and primaire",
    "sg:phone":"+32 12 23 58 16",
    "sg:postcode":"3770",
    "sg:province":"Limburg",
    "wof:name":"Vrije Basisschool",
    "wof:placetype":"venue"
},
  "geometry": {"coordinates":[5.5346941948,50.8141059875],"type":"Point"}
}