{
  "type": "Feature",
  "properties": {
    "addr:full":"Lijsterlaan 17 Liedekerke Vlaams-Brabant 1770",
    "addr:housenumber":"17",
    "addr:postcode":"1770",
    "addr:street":"Lijsterlaan;Vlaams-Brabant",
    "iso:country":"BE",
    "sg:address":"Lijsterlaan 17",
    "sg:city":"Liedekerke",
    "sg:orig_category":"Gespecialiseerde residenti\u00eble bouw",
    "sg:phone":"+32 53 67 27 23",
    "sg:postcode":"1770",
    "sg:province":"Vlaams-Brabant",
    "wof:name":"Clemminck",
    "wof:placetype":"venue"
},
  "geometry": {"coordinates":[4.1176638603,50.8585395813],"type":"Point"}
}