{
  "type": "Feature",
  "properties": {
    "addr:full":"Koningsdonkstraat 49 Gent (gentbrugge) Oost-Vlaanderen 9050",
    "addr:housenumber":"49",
    "addr:postcode":"9050",
    "addr:street":"Koningsdonkstraat",
    "iso:country":"BE",
    "sg:address":"Koningsdonkstraat 49",
    "sg:city":"Gent (gentbrugge)",
    "sg:classifiers":[
        {
            "category":"Health Services",
            "subcategory":"Nursing And Care Facility",
            "type":"Services"
        }
    ],
    "sg:phone":"+32 9 232 05 89",
    "sg:postcode":"9050",
    "sg:province":"Oost-Vlaanderen",
    "sg:tags":[
        "home"
    ],
    "wof:name":"Vereecken Mc",
    "wof:placetype":"venue"
},
  "geometry": {"coordinates":[3.7789540291,51.0396728516],"type":"Point"}
}