{
  "type": "Feature",
  "properties": {
    "addr:full":"Meistraat 199 Dessel Antwerpen 2480",
    "addr:housenumber":"199",
    "addr:postcode":"2480",
    "addr:street":"Meistraat",
    "iso:country":"BE",
    "sg:address":"Meistraat 199",
    "sg:city":"Dessel",
    "sg:classifiers":[
        {
            "category":"Retail",
            "subcategory":"Auto Rental",
            "type":"Services"
        }
    ],
    "sg:phone":"+32 14 37 31 37",
    "sg:postcode":"2480",
    "sg:province":"Antwerpen",
    "sg:tags":[
        "automobile",
        "-",
        "car",
        "self-drive"
    ],
    "wof:name":"A.a.v. Thijs J",
    "wof:placetype":"venue"
},
  "geometry": {"coordinates":[5.15290308,51.2402610779],"type":"Point"}
}