{
  "type": "Feature",
  "properties": {
    "addr:full":"Ch\u00c9e De La Seigneurie 13 Verviers Li\u00e8ge 4800",
    "addr:housenumber":"13",
    "addr:postcode":"4800",
    "addr:street":"La Seigneurie",
    "iso:country":"BE",
    "sg:address":"Ch\u00c9e De La Seigneurie 13",
    "sg:city":"Verviers",
    "sg:classifiers":[
        {
            "category":"Restaurant",
            "type":"Food & Drink"
        }
    ],
    "sg:phone":"+32 87 31 57 41",
    "sg:postcode":"4800",
    "sg:province":"Li\u00e8ge",
    "wof:name":"Restaurant La Chapellerie",
    "wof:placetype":"venue"
},
  "geometry": {"coordinates":[5.8594508171,50.5917663574],"type":"Point"}
}