{
  "type": "Feature",
  "properties": {
    "addr:full":"Winkel 75 Turnhout Antwerpen 2300",
    "addr:housenumber":"75",
    "addr:postcode":"2300",
    "addr:street":"Winkel",
    "iso:country":"BE",
    "sg:address":"Winkel 75",
    "sg:city":"Turnhout",
    "sg:orig_category":"Verhuur bouwmachines Verhuur doe-het-zelf materiaal",
    "sg:phone":"+32 14 85 03 09",
    "sg:postcode":"2300",
    "sg:province":"Antwerpen",
    "wof:name":"Bouwwerktuigen Eelen",
    "wof:placetype":"venue"
},
  "geometry": {"coordinates":[4.9486289024,51.2698669434],"type":"Point"}
}