{
  "type": "Feature",
  "properties": {
    "iso:country":"BE",
    "sg:address":"Hundelgemsesteenweg 34",
    "sg:city":"Gent",
    "sg:orig_category":"Epiceries",
    "sg:phone":"+32 9 231 30 34",
    "sg:postcode":"9050",
    "sg:province":"Oost-Vlaanderen",
    "wof:name":"Danny Hyde",
    "wof:placetype":"venue"
},
  "geometry": {"coordinates":[3.7426190376,51.0329971313],"type":"Point"}
}