{
  "type": "Feature",
  "properties": {
    "addr:full":"Winkelsestraat Lendelede West-Vlaanderen 8860",
    "addr:postcode":"8860",
    "addr:street":"Winkelsestraat",
    "iso:country":"BE",
    "sg:address":"Winkelsestraat",
    "sg:city":"Lendelede",
    "sg:orig_category":"Disneyland Parijs Reisbureaus",
    "sg:phone":"+32 51 31 37 60",
    "sg:postcode":"8860",
    "sg:province":"West-Vlaanderen",
    "wof:name":"Lendelede Travel",
    "wof:placetype":"venue"
},
  "geometry": {"coordinates":[3.2370769978,50.885925293],"type":"Point"}
}