{
  "type": "Feature",
  "properties": {
    "addr:full":"Magerstraat 18b Heule West-Vlaanderen 8501",
    "addr:housenumber":"18b",
    "addr:postcode":"8501",
    "addr:street":"Magerstraat",
    "iso:country":"BE",
    "sg:address":"Magerstraat 18b",
    "sg:city":"Heule",
    "sg:orig_category":"Dakwerken",
    "sg:phone":"+32 56 37 33 41",
    "sg:postcode":"8501",
    "sg:province":"West-Vlaanderen",
    "wof:name":"Depraetere Dakwerken",
    "wof:placetype":"venue"
},
  "geometry": {"coordinates":[3.2378630638,50.8586654663],"type":"Point"}
}