{
  "type": "Feature",
  "properties": {
    "iso:country":"BE",
    "sg:address":"Ambachtstr 8",
    "sg:city":"Oudenaarde",
    "sg:classifiers":[
        {
            "category":"Social Services",
            "subcategory":"Job Training",
            "type":"Services"
        }
    ],
    "sg:phone":"+32 55 30 03 20",
    "sg:postcode":"9700",
    "sg:province":"Oost-Vlaanderen",
    "sg:tags":[
        "information",
        "peripheral",
        "-",
        "technology",
        "software"
    ],
    "wof:name":"Computers And Communications Nv",
    "wof:placetype":"venue"
},
  "geometry": {"coordinates":[3.6142449379,50.8755950928],"type":"Point"}
}