{
  "type": "Feature",
  "properties": {
    "addr:full":"Rue Neuve 42 Herve Li\u00e8ge 4650",
    "addr:housenumber":"42",
    "addr:postcode":"4650",
    "addr:street":"Rue Neuve",
    "iso:country":"BE",
    "sg:address":"Rue Neuve 42",
    "sg:city":"Herve",
    "sg:classifiers":[
        {
            "category":"Shopping",
            "subcategory":"Clothing, Apparel, & Fashions",
            "type":"Retail Goods"
        }
    ],
    "sg:phone":"+32 87 67 85 52",
    "sg:postcode":"4650",
    "sg:province":"Li\u00e8ge",
    "sg:tags":[
        "-",
        "haberdashery"
    ],
    "wof:name":"Boutonni\u00e8re (la)",
    "wof:placetype":"venue"
},
  "geometry": {"coordinates":[5.7911810875,50.638759613],"type":"Point"}
}