{
  "type": "Feature",
  "properties": {
    "iso:country":"BE",
    "sg:address":"Rue De Bray 58",
    "sg:city":"Estinnes",
    "sg:orig_category":"Traitements param\u00e9dicaux",
    "sg:phone":"+32 64 33 17 57",
    "sg:postcode":"7120",
    "sg:province":"Hainaut",
    "wof:name":"I. Waroux",
    "wof:placetype":"venue"
},
  "geometry": {"coordinates":[4.106607914,50.4215545654],"type":"Point"}
}