{
  "type": "Feature",
  "properties": {
    "addr:full":"Dorperheideweg Maaseik (opoeteren) Limburg 3680",
    "addr:postcode":"3680",
    "addr:street":"Dorperheideweg",
    "iso:country":"BE",
    "sg:address":"Dorperheideweg",
    "sg:city":"Maaseik (opoeteren)",
    "sg:classifiers":[
        {
            "category":"Arena",
            "subcategory":"Sports Club",
            "type":"Entertainment"
        }
    ],
    "sg:phone":"+32 89 86 17 62",
    "sg:postcode":"3680",
    "sg:province":"Limburg",
    "wof:name":"S.s.d. Opoeteren Vzw",
    "wof:placetype":"venue"
},
  "geometry": {"coordinates":[5.791285038,51.0954208374],"type":"Point"}
}