{
  "type": "Feature",
  "properties": {
    "iso:country":"BE",
    "sg:address":"Nieuwe Baan 5",
    "sg:city":"Beveren (vrasene)",
    "sg:classifiers":[
        {
            "category":"Fast Food",
            "type":"Food & Drink"
        }
    ],
    "sg:phone":"+32 3 755 64 50",
    "sg:postcode":"9120",
    "sg:province":"Oost-Vlaanderen",
    "sg:tags":[
        "fried",
        "stand",
        "potato"
    ],
    "wof:name":"Transport (frituur)",
    "wof:placetype":"venue"
},
  "geometry": {"coordinates":[4.1941680908,51.2198562622],"type":"Point"}
}