{
  "type": "Feature",
  "properties": {
    "addr:full":"Wolsemstraat 138 Dilbeek Vlaams-Brabant 1700",
    "addr:housenumber":"138",
    "addr:postcode":"1700",
    "addr:street":"Wolsemstraat",
    "iso:country":"BE",
    "sg:address":"Wolsemstraat 138",
    "sg:city":"Dilbeek",
    "sg:classifiers":[
        {
            "category":"Freight",
            "type":"Transportation"
        }
    ],
    "sg:phone":"+32 2 582 62 81",
    "sg:postcode":"1700",
    "sg:province":"Vlaams-Brabant",
    "sg:tags":[
        "-",
        "transport"
    ],
    "wof:name":"Stivi-trans P\u00e8re & Fils Bvba",
    "wof:placetype":"venue"
},
  "geometry": {"coordinates":[4.2374300957,50.865940094],"type":"Point"}
}