{
  "type": "Feature",
  "properties": {
    "addr:full":"Lange Sterrestraat 44 Antwerpen Antwerpen 2180",
    "addr:housenumber":"44",
    "addr:postcode":"2180",
    "addr:street":"Lange Sterrestraat",
    "iso:country":"BE",
    "sg:address":"Lange Sterrestraat 44",
    "sg:city":"Antwerpen",
    "sg:classifiers":[
        {
            "category":"Arena",
            "subcategory":"Sports Club",
            "type":"Entertainment"
        }
    ],
    "sg:phone":"+32 3 568 15 25",
    "sg:postcode":"2180",
    "sg:province":"Antwerpen",
    "sg:tags":[
        "de"
    ],
    "wof:name":"B.s.c. Bears",
    "wof:placetype":"venue"
},
  "geometry": {"coordinates":[4.4182572365,51.2778625488],"type":"Point"}
}