{
  "type": "Feature",
  "properties": {
    "addr:full":"Avenue De Selliers De Moranville 50 Bruxelles (berchem-sainte-agathe) Bruxelles-Capitale 1082",
    "addr:housenumber":"50",
    "addr:postcode":"1082",
    "addr:street":"Avenue De Selliers De Moranville",
    "iso:country":"BE",
    "sg:address":"Avenue De Selliers De Moranville 50",
    "sg:city":"Bruxelles (berchem-sainte-agathe)",
    "sg:classifiers":[
        {
            "category":"Health Services",
            "subcategory":"Doctor",
            "type":"Services"
        }
    ],
    "sg:phone":"+32 2 465 38 27",
    "sg:postcode":"1082",
    "sg:province":"Bruxelles-Capitale",
    "sg:tags":[
        "medicinephysicians",
        "surgeon"
    ],
    "wof:name":"Lecuivre G",
    "wof:placetype":"venue"
},
  "geometry": {"coordinates":[4.2917141914,50.867729187],"type":"Point"}
}