{
  "type": "Feature",
  "properties": {
    "iso:country":"BE",
    "sg:address":"Belfortstraat 30",
    "sg:city":"Gent",
    "sg:orig_category":"Brood, gebak and snoepgoed",
    "sg:phone":"+32 9 223 66 00",
    "sg:postcode":"9000",
    "sg:province":"Oost-Vlaanderen",
    "wof:name":"Huis Belfort",
    "wof:placetype":"venue"
},
  "geometry": {"coordinates":[3.7276771069,51.0558013916],"type":"Point"}
}