{
  "type": "Feature",
  "properties": {
    "iso:country":"BE",
    "sg:address":"Korte Mermansstraat 18 Box 4",
    "sg:city":"Turnhout",
    "sg:classifiers":[
        {
            "category":"Utilities",
            "subcategory":"Fuel Oil & Lpg",
            "type":"Services"
        }
    ],
    "sg:phone":"+32 477 82 41 43",
    "sg:postcode":"2300",
    "sg:province":"Antwerpen",
    "wof:name":"Entech Cvoa",
    "wof:placetype":"venue"
},
  "geometry": {"coordinates":[4.9532442093,51.318977356],"type":"Point"}
}