{
  "type": "Feature",
  "properties": {
    "iso:country":"BE",
    "sg:address":"Guldensporenlaan 49",
    "sg:city":"Tremelo",
    "sg:classifiers":[
        {
            "category":"Professional",
            "type":"Services"
        }
    ],
    "sg:phone":"+32 16 53 20 02",
    "sg:postcode":"3120",
    "sg:province":"Vlaams-Brabant",
    "sg:tags":[
        "industrial",
        "automation"
    ],
    "wof:name":"Digatron Bvba",
    "wof:placetype":"venue"
},
  "geometry": {"coordinates":[4.6946392059,50.9962730408],"type":"Point"}
}