{
  "type": "Feature",
  "properties": {
    "iso:country":"BE",
    "sg:address":"Gemeentehuisstraat 11",
    "sg:city":"Ternat",
    "sg:classifiers":[
        {
            "category":"Insurance",
            "subcategory":"Insurance Agent",
            "type":"Services"
        }
    ],
    "sg:phone":"+32 2 583 00 11",
    "sg:postcode":"1740",
    "sg:province":"Vlaams-Brabant",
    "sg:tags":[
        "verzekeringsmakelaars",
        "expert"
    ],
    "wof:name":"P&v",
    "wof:placetype":"venue"
},
  "geometry": {"coordinates":[4.1793341637,50.8704872131],"type":"Point"}
}