{
  "type": "Feature",
  "properties": {
    "addr:full":"27 Zeemeeuwstraat 8480 Ichtegem 27",
    "addr:housenumber":"27;27",
    "addr:postcode":"8480",
    "addr:street":"Zeemeeuwstraat;Ichtegem",
    "iso:country":"BE",
    "sg:address":"27",
    "sg:city":"Zeemeeuwstraat 8480 Ichtegem",
    "sg:classifiers":[
        {
            "category":"Home & Garden",
            "subcategory":"Furniture",
            "type":"Retail Goods"
        }
    ],
    "sg:phone":"+32 51 56 80 42",
    "sg:postcode":"27",
    "sg:tags":[
        "household",
        "wood"
    ],
    "wof:name":"Houtland Meubelfabriek Nv",
    "wof:placetype":"venue"
},
  "geometry": {"coordinates":[3.037405014,51.0993614197],"type":"Point"}
}