{
  "type": "Feature",
  "properties": {
    "addr:full":"Brusselsesteenweg 110 Lebbeke (groot) Oost-Vlaanderen 9280",
    "addr:housenumber":"110",
    "addr:postcode":"9280",
    "addr:street":"Brusselsesteenweg;Groot Oost-Vlaanderen",
    "iso:country":"BE",
    "sg:address":"Brusselsesteenweg 110",
    "sg:city":"Lebbeke (groot)",
    "sg:orig_category":"Supermarch\u00e9s",
    "sg:phone":"+32 52 41 27 96",
    "sg:postcode":"9280",
    "sg:province":"Oost-Vlaanderen",
    "wof:name":"Colruyt",
    "wof:placetype":"venue"
},
  "geometry": {"coordinates":[4.1281199455,51.0000915527],"type":"Point"}
}