{
  "type": "Feature",
  "properties": {
    "iso:country":"BE",
    "sg:address":"Pont-zuid 20",
    "sg:city":"De Pinte",
    "sg:orig_category":"Boekbinderijen and afwerking",
    "sg:phone":"+32 9 385 47 55",
    "sg:postcode":"9840",
    "sg:province":"Oost-Vlaanderen",
    "wof:name":"Michele Christophe",
    "wof:placetype":"venue"
},
  "geometry": {"coordinates":[3.6838951111,50.9711532593],"type":"Point"}
}