{
  "type": "Feature",
  "properties": {
    "iso:country":"BE",
    "sg:address":"Vierde Regiment Karabiniersstraat 43",
    "sg:city":"Zonnebeke (passendale)",
    "sg:classifiers":[
        {
            "category":"Utilities",
            "subcategory":"Fuel Oil & Lpg",
            "type":"Services"
        }
    ],
    "sg:phone":"+32 51 78 02 10",
    "sg:postcode":"8980",
    "sg:province":"West-Vlaanderen",
    "wof:name":"Deforche Nv",
    "wof:placetype":"venue"
},
  "geometry": {"coordinates":[2.9872550964,50.8730812073],"type":"Point"}
}