{
  "type": "Feature",
  "properties": {
    "iso:country":"BE",
    "sg:address":"Dilserweg 15",
    "sg:city":"Maaseik (opoeteren)",
    "sg:classifiers":[
        {
            "category":"Fast Food",
            "type":"Food & Drink"
        }
    ],
    "sg:phone":"+32 89 86 70 40",
    "sg:postcode":"3680",
    "sg:province":"Limburg",
    "sg:tags":[
        "fried",
        "stand",
        "potato"
    ],
    "wof:name":"Frituurke ('t)",
    "wof:placetype":"venue"
},
  "geometry": {"coordinates":[5.791285038,51.0954208374],"type":"Point"}
}