{
  "type": "Feature",
  "properties": {
    "iso:country":"BE",
    "sg:address":"Belle Ile En Li\u00e8ge",
    "sg:city":"Li\u00e8ge 1 (li\u00e8ge 2)",
    "sg:classifiers":[
        {
            "category":"Shopping",
            "subcategory":"Clothing, Apparel, & Fashions",
            "type":"Retail Goods"
        }
    ],
    "sg:phone":"+32 4 344 52 55",
    "sg:postcode":"4020",
    "sg:province":"Li\u00e8ge",
    "sg:tags":[
        "boutique"
    ],
    "wof:name":"Mayerline",
    "wof:placetype":"venue"
},
  "geometry": {"coordinates":[5.5964818001,50.6152572632],"type":"Point"}
}