{
  "type": "Feature",
  "properties": {
    "iso:country":"BE",
    "sg:address":"Korendragersstraat 17",
    "sg:city":"Brugge",
    "sg:orig_category":"Artiesten and kunstenaars",
    "sg:phone":"+32 50 34 41 85",
    "sg:postcode":"8000",
    "sg:province":"West-Vlaanderen",
    "wof:name":"Main Street",
    "wof:placetype":"venue"
},
  "geometry": {"coordinates":[3.2328619957,51.22631073],"type":"Point"}
}