{
  "type": "Feature",
  "properties": {
    "addr:full":"Volkensvoortstraat 11ba Aarschot Vlaams-Brabant 3201",
    "addr:housenumber":"11ba",
    "addr:postcode":"3201",
    "addr:street":"Volkensvoortstraat",
    "iso:country":"BE",
    "sg:address":"Volkensvoortstraat 11ba",
    "sg:city":"Aarschot",
    "sg:orig_category":"Woningbouw",
    "sg:phone":"+32 13 77 72 05",
    "sg:postcode":"3201",
    "sg:province":"Vlaams-Brabant",
    "wof:name":"Parenco",
    "wof:placetype":"venue"
},
  "geometry": {"coordinates":[4.9159469604,51.0211372375],"type":"Point"}
}