{
  "type": "Feature",
  "properties": {
    "iso:country":"BE",
    "sg:address":"Donkstraat 1",
    "sg:city":"Oudenaarde",
    "sg:orig_category":"Goederenvervoer over de weg HUISBRANDOLIE",
    "sg:phone":"+32 55 30 14 30",
    "sg:postcode":"9700",
    "sg:province":"Oost-Vlaanderen",
    "wof:name":"Transport Van Coster & Co",
    "wof:placetype":"venue"
},
  "geometry": {"coordinates":[3.578963995,50.8436660767],"type":"Point"}
}