{
  "type": "Feature",
  "properties": {
    "iso:country":"BE",
    "sg:address":"Gelmelenstraat 91",
    "sg:city":"Schoten",
    "sg:classifiers":[
        {
            "category":"Health Services",
            "subcategory":"Health Practitioner",
            "type":"Services"
        }
    ],
    "sg:phone":"+32 3 658 41 27",
    "sg:postcode":"2900",
    "sg:province":"Antwerpen",
    "sg:tags":[
        "physiotherapist"
    ],
    "wof:name":"Peeters Joke",
    "wof:placetype":"venue"
},
  "geometry": {"coordinates":[4.4970970154,51.2525939941],"type":"Point"}
}