{
  "type": "Feature",
  "properties": {
    "iso:country":"BE",
    "sg:address":"Landriesstraat 7",
    "sg:city":"Wellen",
    "sg:orig_category":"Landbouwmachines Gh Loodgieterij, verwarming and sanitaire installaties",
    "sg:phone":"+32 12 74 17 04",
    "sg:postcode":"3832",
    "sg:province":"Limburg",
    "wof:name":"Landbouwmachines Ponet",
    "wof:placetype":"venue"
},
  "geometry": {"coordinates":[5.2866778374,50.8360557556],"type":"Point"}
}