{
  "type": "Feature",
  "properties": {
    "addr:full":"Rue Du Vieux Moulin 5 Huy Li\u00e8ge 4500",
    "addr:housenumber":"5",
    "addr:postcode":"4500",
    "addr:street":"Rue Du Vieux Moulin",
    "iso:country":"BE",
    "sg:address":"Rue Du Vieux Moulin 5",
    "sg:city":"Huy",
    "sg:classifiers":[
        {
            "category":"Bars & Pubs",
            "subcategory":"Nightclub",
            "type":"Food & Drink"
        }
    ],
    "sg:phone":"+32 85 61 29 50",
    "sg:postcode":"4500",
    "sg:province":"Li\u00e8ge",
    "sg:tags":[
        "nachtclubs",
        "dancing"
    ],
    "wof:name":"Soli\u00c8res Exploitation",
    "wof:placetype":"venue"
},
  "geometry": {"coordinates":[5.17689991,50.4784812927],"type":"Point"}
}