{
  "type": "Feature",
  "properties": {
    "addr:full":"Chauss\u00e9e De Wavre 253 Grez-doiceau Brabant Wallon 1390",
    "addr:housenumber":"253",
    "addr:postcode":"1390",
    "addr:street":"Chausse\u0301E De Wavre",
    "iso:country":"BE",
    "sg:address":"Chauss\u00e9e De Wavre 253",
    "sg:city":"Grez-doiceau",
    "sg:classifiers":[
        {
            "category":"Health Services",
            "subcategory":"Doctor",
            "type":"Services"
        }
    ],
    "sg:postcode":"1390",
    "sg:province":"Brabant Wallon",
    "sg:tags":[
        "psychotherapist",
        "psychoanalyst"
    ],
    "wof:name":"Joos Anne",
    "wof:placetype":"venue"
},
  "geometry": {"coordinates":[4.6712632179,50.7409133911],"type":"Point"}
}