{
  "type": "Feature",
  "properties": {
    "addr:full":"Route De Mons 22 Sivry-rance Hainaut 6470",
    "addr:housenumber":"22",
    "addr:postcode":"6470",
    "addr:street":"Route De Mons",
    "iso:country":"BE",
    "sg:address":"Route De Mons 22",
    "sg:city":"Sivry-rance",
    "sg:classifiers":[
        {
            "category":"Autos & Motor Vehicles",
            "subcategory":"Fuel & Gas Station",
            "type":"Retail Goods"
        }
    ],
    "sg:phone":"+32 60 45 63 55",
    "sg:postcode":"6470",
    "sg:province":"Hainaut",
    "sg:tags":[
        "stations-service",
        "carburants"
    ],
    "wof:name":"Graineterie Des Corv\u00c9es",
    "wof:placetype":"venue"
},
  "geometry": {"coordinates":[4.2243118286,50.1811637878],"type":"Point"}
}