{
  "type": "Feature",
  "properties": {
    "iso:country":"BE",
    "sg:address":"Rue De Chamb\u00c9ry 46",
    "sg:city":"Etterbeek/etterbeek",
    "sg:orig_category":"Travaux d'isolation",
    "sg:phone":"+32 2 648 98 98",
    "sg:postcode":"1040",
    "sg:province":"Bruxelles-Capitale",
    "wof:name":"Paul Verdeyen",
    "wof:placetype":"venue"
},
  "geometry": {"coordinates":[4.3879518509,50.8305587769],"type":"Point"}
}