{
  "type": "Feature",
  "properties": {
    "addr:full":"Rue Louis De Brouck\u00e8re 85 La Louvi\u00e8re Hainaut 7100",
    "addr:housenumber":"85",
    "addr:postcode":"7100",
    "addr:street":"Rue Louis De Broucke\u0300Re",
    "iso:country":"BE",
    "sg:address":"Rue Louis De Brouck\u00e8re 85",
    "sg:city":"La Louvi\u00e8re",
    "sg:classifiers":[
        {
            "category":"Shopping",
            "subcategory":"Bridal",
            "type":"Retail Goods"
        }
    ],
    "sg:phone":"+32 64 44 18 80",
    "sg:postcode":"7100",
    "sg:province":"Hainaut",
    "sg:tags":[
        "list",
        "-",
        "present",
        "wedding"
    ],
    "wof:name":"Casaviva",
    "wof:placetype":"venue"
},
  "geometry": {"coordinates":[4.190808773,50.4802856445],"type":"Point"}
}