{
  "type": "Feature",
  "properties": {
    "addr:full":"Mechelbaan 408 Putte Antwerpen 2580",
    "addr:housenumber":"408",
    "addr:postcode":"2580",
    "addr:street":"Mechelbaan",
    "iso:country":"BE",
    "sg:address":"Mechelbaan 408",
    "sg:city":"Putte",
    "sg:orig_category":"Verlichting and huishoudartikelen",
    "sg:phone":"+32 15 75 69 44",
    "sg:postcode":"2580",
    "sg:province":"Antwerpen",
    "wof:name":"Huis Kadoke",
    "wof:placetype":"venue"
},
  "geometry": {"coordinates":[4.6306672096,51.0558547974],"type":"Point"}
}