{
  "type": "Feature",
  "properties": {
    "addr:full":"Koning Albertstraat 10 Lier Antwerpen 2500",
    "addr:housenumber":"10",
    "addr:postcode":"2500",
    "addr:street":"Koning Albertstraat",
    "iso:country":"BE",
    "sg:address":"Koning Albertstraat 10",
    "sg:city":"Lier",
    "sg:classifiers":[
        {
            "category":"Professional",
            "subcategory":"Art Services",
            "type":"Services"
        }
    ],
    "sg:phone":"+32 3 489 07 91",
    "sg:postcode":"2500",
    "sg:province":"Antwerpen",
    "sg:tags":[
        "photographer"
    ],
    "wof:name":"Verstreken P",
    "wof:placetype":"venue"
},
  "geometry": {"coordinates":[4.5704369545,51.1314277649],"type":"Point"}
}