{
  "type": "Feature",
  "properties": {
    "iso:country":"BE",
    "sg:address":"Avenue De La Vecqu\u00c9e 533",
    "sg:city":"Namur",
    "sg:orig_category":"Afval and schroot Gh",
    "sg:phone":"+32 81 44 15 53",
    "sg:postcode":"5020",
    "sg:province":"Namur",
    "wof:name":"Kabbaltrading",
    "wof:placetype":"venue"
},
  "geometry": {"coordinates":[4.7952418327,50.4352035522],"type":"Point"}
}