{
  "type": "Feature",
  "properties": {
    "addr:full":"Drie Bunder 9 Aartselaar Antwerpen 2630",
    "addr:housenumber":"9",
    "addr:postcode":"2630",
    "addr:street":"Drie Bunder",
    "iso:country":"BE",
    "sg:address":"Drie Bunder 9",
    "sg:city":"Aartselaar",
    "sg:orig_category":"Artsen and specialisten",
    "sg:phone":"+32 3 887 89 68",
    "sg:postcode":"2630",
    "sg:province":"Antwerpen",
    "wof:name":"Jacques Van Damme",
    "wof:placetype":"venue"
},
  "geometry": {"coordinates":[4.3860650063,51.1420059204],"type":"Point"}
}