{
  "type": "Feature",
  "properties": {
    "addr:full":"Wijnendalestraat 171 Roeselare West-Vlaanderen 8800",
    "addr:housenumber":"171",
    "addr:postcode":"8800",
    "addr:street":"Wijnendalestraat",
    "iso:country":"BE",
    "sg:address":"Wijnendalestraat 171",
    "sg:city":"Roeselare",
    "sg:classifiers":[
        {
            "category":"Manufacturing",
            "subcategory":"Rubber & Plastics",
            "type":"Manufacturing & Wholesale Goods"
        }
    ],
    "sg:phone":"+32 51 23 02 11",
    "sg:postcode":"8800",
    "sg:province":"West-Vlaanderen",
    "sg:tags":[
        "industrial",
        "-"
    ],
    "wof:name":"Dumo Nv",
    "wof:placetype":"venue"
},
  "geometry": {"coordinates":[3.1290099621,50.9706611633],"type":"Point"}
}