{
  "type": "Feature",
  "properties": {
    "addr:full":"Avenue Des Ardennes 12 Huy Li\u00e8ge 4500",
    "addr:housenumber":"12",
    "addr:postcode":"4500",
    "addr:street":"Avenue Des Ardennes",
    "iso:country":"BE",
    "sg:address":"Avenue Des Ardennes 12",
    "sg:city":"Huy",
    "sg:classifiers":[
        {
            "category":"Retail",
            "subcategory":"Repair Shop",
            "type":"Services"
        }
    ],
    "sg:phone":"+32 85 21 24 66",
    "sg:postcode":"4500",
    "sg:province":"Li\u00e8ge",
    "sg:tags":[
        "photographic",
        "equipment",
        "-",
        "accessory"
    ],
    "wof:name":"Studio Pinon",
    "wof:placetype":"venue"
},
  "geometry": {"coordinates":[5.2392530441,50.5189743042],"type":"Point"}
}