{
  "type": "Feature",
  "properties": {
    "addr:full":"Camping La Foulerie Chiny Luxembourg 6810",
    "addr:postcode":"6810",
    "iso:country":"BE",
    "sg:address":"Camping La Foulerie",
    "sg:city":"Chiny",
    "sg:classifiers":[
        {
            "category":"Recreation",
            "subcategory":"Campground",
            "type":"Entertainment"
        }
    ],
    "sg:phone":"+32 61 31 17 72",
    "sg:postcode":"6810",
    "sg:province":"Luxembourg",
    "sg:tags":[
        "site",
        "camping"
    ],
    "wof:name":"Foulerie (la)",
    "wof:placetype":"venue"
},
  "geometry": {"coordinates":[5.3500900269,49.7392578125],"type":"Point"}
}