{
  "type": "Feature",
  "properties": {
    "iso:country":"BE",
    "sg:address":"Ontmijnersstraat 2b2",
    "sg:city":"Staden",
    "sg:orig_category":"Epiceries",
    "sg:phone":"+32 51 70 49 06",
    "sg:postcode":"8840",
    "sg:province":"West-Vlaanderen",
    "wof:name":"Voeding St.elooi",
    "wof:placetype":"venue"
},
  "geometry": {"coordinates":[2.9742920399,50.9497642517],"type":"Point"}
}