{
  "type": "Feature",
  "properties": {
    "iso:country":"BE",
    "sg:address":"Blaasveldstraat 187b",
    "sg:city":"Willebroek (tisselt)",
    "sg:classifiers":[
        {
            "category":"Professional",
            "subcategory":"Management & Consulting",
            "type":"Services"
        }
    ],
    "sg:phone":"+32 3 886 75 05",
    "sg:postcode":"2830",
    "sg:province":"Antwerpen",
    "sg:tags":[
        "consultant"
    ],
    "wof:name":"K-consult Bvba",
    "wof:placetype":"venue"
},
  "geometry": {"coordinates":[4.3757801056,51.0431365967],"type":"Point"}
}