{
  "type": "Feature",
  "properties": {
    "addr:full":"Rue Des Templiers 19 Chimay Hainaut 6464",
    "addr:housenumber":"19",
    "addr:postcode":"6464",
    "addr:street":"Rue Des Templiers",
    "iso:country":"BE",
    "sg:address":"Rue Des Templiers 19",
    "sg:city":"Chimay",
    "sg:classifiers":[
        {
            "category":"Recreation",
            "type":"Entertainment"
        }
    ],
    "sg:phone":"+32 60 21 35 54",
    "sg:postcode":"6464",
    "sg:province":"Hainaut",
    "sg:tags":[
        "diver",
        "amusement"
    ],
    "wof:name":"D.j. Awax",
    "wof:placetype":"venue"
},
  "geometry": {"coordinates":[4.3258328438,50.0274620056],"type":"Point"}
}