{
  "type": "Feature",
  "properties": {
    "addr:full":"Kuringer Steenweg 491 Hasselt Limburg 3511",
    "addr:housenumber":"491",
    "addr:postcode":"3511",
    "addr:street":"Steenweg",
    "iso:country":"BE",
    "sg:address":"Kuringer Steenweg 491",
    "sg:city":"Hasselt",
    "sg:orig_category":"Hypermarch\u00e9s. Articles de camping and de sport",
    "sg:phone":"+32 11 85 09 15",
    "sg:postcode":"3511",
    "sg:province":"Limburg",
    "wof:name":"Bigg's Continent Noord",
    "wof:placetype":"venue"
},
  "geometry": {"coordinates":[5.2920398712,50.9425086975],"type":"Point"}
}