{
  "type": "Feature",
  "properties": {
    "iso:country":"BE",
    "sg:address":"Chauss\u00c9e De Couvin 70",
    "sg:city":"Chimay",
    "sg:orig_category":"Benzinestations and brandstoffen",
    "sg:phone":"+32 60 21 22 96",
    "sg:postcode":"6460",
    "sg:province":"Hainaut",
    "wof:name":"Station Le Radar",
    "wof:placetype":"venue"
},
  "geometry": {"coordinates":[4.3299059868,50.0449104309],"type":"Point"}
}