{
  "type": "Feature",
  "properties": {
    "iso:country":"BE",
    "sg:address":"Rue De La Closi\u00e8re 11",
    "sg:city":"Fleurus (wanferc\u00e9e-baulet)",
    "sg:classifiers":[
        {
            "category":"Professional",
            "subcategory":"Accounting & Tax Preparation",
            "type":"Services"
        }
    ],
    "sg:phone":"+32 71 82 27 10",
    "sg:postcode":"6224",
    "sg:province":"Hainaut",
    "sg:tags":[
        "bookkeeper"
    ],
    "wof:name":"Bureau Comptable Et Fiscal Miaouli Scris",
    "wof:placetype":"venue"
},
  "geometry": {"coordinates":[4.5816531181,50.4614028931],"type":"Point"}
}