{
  "type": "Feature",
  "properties": {
    "addr:full":"Van Der Dilftlaan 21 Sint-pieters-leeuw Vlaams-Brabant 1600",
    "addr:housenumber":"21",
    "addr:postcode":"1600",
    "addr:street":"Van Der Dilftlaan",
    "iso:country":"BE",
    "sg:address":"Van Der Dilftlaan 21",
    "sg:city":"Sint-pieters-leeuw",
    "sg:classifiers":[
        {
            "category":"Health Services",
            "subcategory":"Health Practitioner",
            "type":"Services"
        }
    ],
    "sg:phone":"+32 2 378 27 99",
    "sg:postcode":"1600",
    "sg:province":"Vlaams-Brabant",
    "sg:tags":[
        "physiotherapist"
    ],
    "wof:name":"Roosens Eddy",
    "wof:placetype":"venue"
},
  "geometry": {"coordinates":[4.2516841888,50.7840003967],"type":"Point"}
}