{
  "type": "Feature",
  "properties": {
    "iso:country":"BE",
    "sg:address":"All\u00e9e Des Roitelets 5",
    "sg:city":"Namur (erpent)",
    "sg:classifiers":[
        {
            "category":"Professional",
            "subcategory":"Lawyer & Legal Services",
            "type":"Services"
        }
    ],
    "sg:phone":"+32 81 30 21 22",
    "sg:postcode":"5101",
    "sg:province":"Namur",
    "wof:name":"De Vos Danielle",
    "wof:placetype":"venue"
},
  "geometry": {"coordinates":[4.9027571678,50.4383087158],"type":"Point"}
}