{
  "type": "Feature",
  "properties": {
    "addr:full":"Belfortstraat 41 Gent Oost-Vlaanderen 9000",
    "addr:housenumber":"41",
    "addr:postcode":"9000",
    "addr:street":"Belfortstraat;Oost-Vlaanderen",
    "iso:country":"BE",
    "sg:address":"Belfortstraat 41",
    "sg:city":"Gent",
    "sg:orig_category":"Banques and organismes de cr\u00e9dit",
    "sg:phone":"+32 9 225 32 14",
    "sg:postcode":"9000",
    "sg:province":"Oost-Vlaanderen",
    "wof:name":"Fortis",
    "wof:placetype":"venue"
},
  "geometry": {"coordinates":[3.7273499966,51.055847168],"type":"Point"}
}