{
  "type": "Feature",
  "properties": {
    "iso:country":"BE",
    "sg:address":"Rue De L'etat 10",
    "sg:city":"Chastre",
    "sg:orig_category":"Woningbouw",
    "sg:phone":"+32 71 87 94 07",
    "sg:postcode":"1450",
    "sg:province":"Brabant Wallon",
    "wof:name":"Dresse",
    "wof:placetype":"venue"
},
  "geometry": {"coordinates":[4.6094641685,50.5790328979],"type":"Point"}
}