{
  "type": "Feature",
  "properties": {
    "iso:country":"BE",
    "sg:address":"Rue Pierre Dupont 167",
    "sg:city":"Bruxelles (evere)",
    "sg:classifiers":[
        {
            "category":"Transit Center",
            "subcategory":"Freight",
            "type":"Transportation"
        }
    ],
    "sg:phone":"+32 2 726 16 85",
    "sg:postcode":"1140",
    "sg:province":"Bruxelles-Capitale",
    "sg:tags":[
        "glue"
    ],
    "wof:name":"Sika Sa",
    "wof:placetype":"venue"
},
  "geometry": {"coordinates":[4.4124150276,50.8641777039],"type":"Point"}
}