{
  "type": "Feature",
  "properties": {
    "addr:full":"Rue Saint-leger 35 Profondeville Namur 5170",
    "addr:housenumber":"35",
    "addr:postcode":"5170",
    "addr:street":"Rue Saint-Leger",
    "iso:country":"BE",
    "sg:address":"Rue Saint-leger 35",
    "sg:city":"Profondeville",
    "sg:orig_category":"Enseignement maternel and primaire",
    "sg:phone":"+32 81 41 16 32",
    "sg:postcode":"5170",
    "sg:province":"Namur",
    "wof:name":"Ecole Fond. Communale",
    "wof:placetype":"venue"
},
  "geometry": {"coordinates":[4.8987698555,50.3788986206],"type":"Point"}
}