{
  "type": "Feature",
  "properties": {
    "iso:country":"BE",
    "sg:address":"Sleidingedorp 46",
    "sg:city":"Evergem",
    "sg:orig_category":"S\u00e9curit\u00e9 sociale",
    "sg:phone":"+32 9 357 70 22",
    "sg:postcode":"9940",
    "sg:province":"Oost-Vlaanderen",
    "wof:name":"Christelijke Mutualiteit",
    "wof:placetype":"venue"
},
  "geometry": {"coordinates":[3.6794888973,51.1325340271],"type":"Point"}
}