{
  "type": "Feature",
  "properties": {
    "iso:country":"BE",
    "sg:address":"Abeelestraat 55",
    "sg:city":"Wielsbeke",
    "sg:orig_category":"Reisbureaus",
    "sg:phone":"+32 56 66 81 29",
    "sg:postcode":"8710",
    "sg:province":"West-Vlaanderen",
    "wof:name":"De Smedt",
    "wof:placetype":"venue"
},
  "geometry": {"coordinates":[3.3825209141,50.9149436951],"type":"Point"}
}