{
  "type": "Feature",
  "properties": {
    "iso:country":"BE",
    "sg:address":"Gulden Sporenstraat 37",
    "sg:city":"Eeklo",
    "sg:orig_category":"Architectes. Artistes ind\u00e9pendants",
    "sg:phone":"+32 9 378 27 26",
    "sg:postcode":"9900",
    "sg:province":"Oost-Vlaanderen",
    "wof:name":"Michiel Verstraete",
    "wof:placetype":"venue"
},
  "geometry": {"coordinates":[3.573004961,51.1790657043],"type":"Point"}
}