{
  "type": "Feature",
  "properties": {
    "addr:full":"Tongersesteenweg 120 Hoeselt Limburg 3730",
    "addr:housenumber":"120",
    "addr:postcode":"3730",
    "addr:street":"Tongersesteenweg",
    "iso:country":"BE",
    "sg:address":"Tongersesteenweg 120",
    "sg:city":"Hoeselt",
    "sg:orig_category":"Fruitteelt",
    "sg:phone":"+32 12 23 22 47",
    "sg:postcode":"3730",
    "sg:province":"Limburg",
    "wof:name":"Martin Broeders",
    "wof:placetype":"venue"
},
  "geometry": {"coordinates":[5.4671049118,50.8223571777],"type":"Point"}
}