{
  "type": "Feature",
  "properties": {
    "addr:full":"Berreweide 29 Londerzeel Vlaams-Brabant 1840",
    "addr:housenumber":"29",
    "addr:postcode":"1840",
    "addr:street":"Berreweide",
    "iso:country":"BE",
    "sg:address":"Berreweide 29",
    "sg:city":"Londerzeel",
    "sg:orig_category":"Informaticaconsulenten",
    "sg:phone":"+32 475 89 73 49",
    "sg:postcode":"1840",
    "sg:province":"Vlaams-Brabant",
    "wof:name":"Biesemans",
    "wof:placetype":"venue"
},
  "geometry": {"coordinates":[4.3077011108,51.0122642517],"type":"Point"}
}