{
  "type": "Feature",
  "properties": {
    "iso:country":"BE",
    "sg:address":"Potterijstraat 64",
    "sg:city":"Tienen",
    "sg:orig_category":"HERSTELLING ELEKTRISCHE HUISHOUDAPPARATEN Huishoudapparaten, televisies and radio's Telecommunicatie",
    "sg:phone":"+32 16 82 58 40",
    "sg:postcode":"3300",
    "sg:province":"Vlaams-Brabant",
    "wof:name":"Elektron",
    "wof:placetype":"venue"
},
  "geometry": {"coordinates":[4.9387049675,50.8001098633],"type":"Point"}
}