{
  "type": "Feature",
  "properties": {
    "iso:country":"BE",
    "sg:address":"Oudenaardestraat 84",
    "sg:city":"Anzegem (vichte)",
    "sg:classifiers":[
        {
            "category":"Manufacturing",
            "subcategory":"Textiles",
            "type":"Manufacturing & Wholesale Goods"
        }
    ],
    "sg:phone":"+32 56 77 77 51",
    "sg:postcode":"8570",
    "sg:province":"West-Vlaanderen",
    "sg:tags":[
        "technical"
    ],
    "wof:name":"Steverlynck Gebr",
    "wof:placetype":"venue"
},
  "geometry": {"coordinates":[3.412856102,50.8398857117],"type":"Point"}
}