{
  "type": "Feature",
  "properties": {
    "addr:full":"Boulevard L\u00c9opold 69 Tournai Hainaut 7500",
    "addr:housenumber":"69",
    "addr:postcode":"7500",
    "addr:street":"Boulevard Le\u0301Opold",
    "iso:country":"BE",
    "sg:address":"Boulevard L\u00c9opold 69",
    "sg:city":"Tournai",
    "sg:classifiers":[
        {
            "category":"Cafe",
            "type":"Food & Drink"
        }
    ],
    "sg:phone":"+32 69 84 62 95",
    "sg:postcode":"7500",
    "sg:province":"Hainaut",
    "sg:tags":[
        "caf\u00e9s"
    ],
    "wof:name":"Caf\u00c9 L'horticole",
    "wof:placetype":"venue"
},
  "geometry": {"coordinates":[3.3782539368,50.6098747253],"type":"Point"}
}