{
  "type": "Feature",
  "properties": {
    "addr:full":"Rue Emile Vandervelde 143 Mons Hainaut 7000",
    "addr:housenumber":"143",
    "addr:postcode":"7000",
    "addr:street":"Rue Emile Vandervelde;Hainaut",
    "iso:country":"BE",
    "sg:address":"Rue Emile Vandervelde 143",
    "sg:city":"Mons",
    "sg:orig_category":"Elektrische installaties voor woningen",
    "sg:phone":"+32 65 31 10 57",
    "sg:postcode":"7000",
    "sg:province":"Hainaut",
    "wof:name":"Wauquier A.",
    "wof:placetype":"venue"
},
  "geometry": {"coordinates":[3.935628891,50.4393348694],"type":"Point"}
}