{
  "type": "Feature",
  "properties": {
    "addr:full":"Rue De Neussart 19 Chaumont-gistoux (corroy-le-grand) Brabant Wallon 1325",
    "addr:housenumber":"19",
    "addr:postcode":"1325",
    "addr:street":"Rue De Neussart",
    "iso:country":"BE",
    "sg:address":"Rue De Neussart 19",
    "sg:city":"Chaumont-gistoux (corroy-le-grand)",
    "sg:classifiers":[
        {
            "category":"Building & Trades",
            "subcategory":"Construction",
            "type":"Services"
        }
    ],
    "sg:phone":"+32 10 68 81 53",
    "sg:postcode":"1325",
    "sg:province":"Brabant Wallon",
    "sg:tags":[
        "carpenter"
    ],
    "wof:name":"Dandois Ets",
    "wof:placetype":"venue"
},
  "geometry": {"coordinates":[4.6495628357,50.6726226807],"type":"Point"}
}