{
  "type": "Feature",
  "properties": {
    "addr:full":"Etikhoveplein 10 Maarkedal (etikhove) Oost-Vlaanderen 9680",
    "addr:housenumber":"10",
    "addr:postcode":"9680",
    "addr:street":"Etikhoveplein",
    "iso:country":"BE",
    "sg:address":"Etikhoveplein 10",
    "sg:city":"Maarkedal (etikhove)",
    "sg:orig_category":"Non-Classified Establishments",
    "sg:phone":"+32 55 31 26 40",
    "sg:postcode":"9680",
    "sg:province":"Oost-Vlaanderen",
    "wof:name":"Etexgro",
    "wof:placetype":"venue"
},
  "geometry": {"coordinates":[3.6263039112,50.8120536804],"type":"Point"}
}