{
  "type": "Feature",
  "properties": {
    "addr:full":"Rue Des Pr\u00c9aux 64 Beloeil Hainaut 7971",
    "addr:housenumber":"64",
    "addr:postcode":"7971",
    "addr:street":"Rue Des Pre\u0301Aux",
    "iso:country":"BE",
    "sg:address":"Rue Des Pr\u00c9aux 64",
    "sg:city":"Beloeil",
    "sg:orig_category":"Artsen and specialisten",
    "sg:phone":"+32 69 57 73 21",
    "sg:postcode":"7971",
    "sg:province":"Hainaut",
    "wof:name":"Luc Brouillard",
    "wof:placetype":"venue"
},
  "geometry": {"coordinates":[3.6503250599,50.5278892517],"type":"Point"}
}