{
  "type": "Feature",
  "properties": {
    "iso:country":"BE",
    "sg:address":"Fazantendreef 10",
    "sg:city":"Zoersel (halle)",
    "sg:classifiers":[
        {
            "category":"Social Services",
            "subcategory":"Job Training",
            "type":"Services"
        }
    ],
    "sg:phone":"+32 3 385 04 90",
    "sg:postcode":"2980",
    "sg:province":"Antwerpen",
    "sg:tags":[
        "personnel"
    ],
    "wof:name":"K+ Training En Consulting Bvba",
    "wof:placetype":"venue"
},
  "geometry": {"coordinates":[4.713435173,51.269985199],"type":"Point"}
}