{
  "type": "Feature",
  "properties": {
    "iso:country":"BE",
    "sg:address":"Rue De La Moinerie 31",
    "sg:city":"Verviers (petit-rechain)",
    "sg:classifiers":[
        {
            "category":"Health Services",
            "subcategory":"Nursing And Care Facility",
            "type":"Services"
        }
    ],
    "sg:phone":"+32 87 39 40 40",
    "sg:postcode":"4800",
    "sg:province":"Li\u00e8ge",
    "sg:tags":[
        "home",
        "rest"
    ],
    "wof:name":"R\u00e9sidence Bon Air",
    "wof:placetype":"venue"
},
  "geometry": {"coordinates":[5.8585791588,50.5884475708],"type":"Point"}
}