{
  "type": "Feature",
  "properties": {
    "addr:full":"Geraardsbergsesteenweg 9 Herne Vlaams-Brabant 1541",
    "addr:housenumber":"9",
    "addr:postcode":"1541",
    "addr:street":"Geraardsbergsesteenweg",
    "iso:country":"BE",
    "sg:address":"Geraardsbergsesteenweg 9",
    "sg:city":"Herne",
    "sg:orig_category":"Kantoormateriaal",
    "sg:phone":"+32 2 396 06 84",
    "sg:postcode":"1541",
    "sg:province":"Vlaams-Brabant",
    "wof:name":"Doppio Linea",
    "wof:placetype":"venue"
},
  "geometry": {"coordinates":[4.0283551216,50.7044830322],"type":"Point"}
}