{
  "type": "Feature",
  "properties": {
    "addr:full":"Hoogstraat 23 Putte Antwerpen 2580",
    "addr:housenumber":"23",
    "addr:postcode":"2580",
    "addr:street":"Hoogstraat",
    "iso:country":"BE",
    "sg:address":"Hoogstraat 23",
    "sg:city":"Putte",
    "sg:classifiers":[
        {
            "category":"Restaurant",
            "type":"Food & Drink"
        }
    ],
    "sg:phone":"+32 15 75 38 29",
    "sg:postcode":"2580",
    "sg:province":"Antwerpen",
    "wof:name":"Linda Swiggers",
    "wof:placetype":"venue"
},
  "geometry": {"coordinates":[4.6690478325,51.0574951172],"type":"Point"}
}