{
  "type": "Feature",
  "properties": {
    "iso:country":"BE",
    "sg:address":"Gemeenteplein 8",
    "sg:city":"Knokke-heist",
    "sg:orig_category":"Pain, p\u00e2tisseries and confiseries",
    "sg:phone":"+32 50 60 14 93",
    "sg:postcode":"8300",
    "sg:province":"West-Vlaanderen",
    "wof:name":"Robert Demeyer",
    "wof:placetype":"venue"
},
  "geometry": {"coordinates":[3.2895650864,51.340713501],"type":"Point"}
}