{
  "type": "Feature",
  "properties": {
    "iso:country":"BE",
    "sg:address":"Steenokkerzeelstraat 96b",
    "sg:city":"Zaventem",
    "sg:classifiers":[
        {
            "category":"Taxi",
            "type":"Transportation"
        }
    ],
    "sg:phone":"+32 2 720 68 38",
    "sg:postcode":"1930",
    "sg:province":"Vlaams-Brabant",
    "sg:tags":[
        "taxicab"
    ],
    "wof:name":"Air Auto",
    "wof:placetype":"venue"
},
  "geometry": {"coordinates":[4.4750962257,50.8878173828],"type":"Point"}
}