{
  "type": "Feature",
  "properties": {
    "addr:full":"Hoogstraat 62 Zottegem Oost-Vlaanderen 9620",
    "addr:housenumber":"62",
    "addr:postcode":"9620",
    "addr:street":"Hoogstraat",
    "iso:country":"BE",
    "sg:address":"Hoogstraat 62",
    "sg:city":"Zottegem",
    "sg:classifiers":[
        {
            "category":"Food & Beverages",
            "subcategory":"Specialty",
            "type":"Retail Goods"
        }
    ],
    "sg:phone":"+32 9 360 35 38",
    "sg:postcode":"9620",
    "sg:province":"Oost-Vlaanderen",
    "sg:tags":[
        "health",
        "dietary",
        "-",
        "biological"
    ],
    "wof:name":"De Korenbloem",
    "wof:placetype":"venue"
},
  "geometry": {"coordinates":[3.8088450432,50.8680000305],"type":"Point"}
}