{
  "type": "Feature",
  "properties": {
    "iso:country":"BE",
    "sg:address":"Chauss\u00c9e De Boondael 210",
    "sg:city":"Elsene/ixelles",
    "sg:orig_category":"Poissonniers and \u00e9caillers",
    "sg:phone":"+32 2 647 31 86",
    "sg:postcode":"1050",
    "sg:province":"Bruxelles-Capitale",
    "wof:name":"Ahmed Bensouda",
    "wof:placetype":"venue"
},
  "geometry": {"coordinates":[4.3805131912,50.8213500977],"type":"Point"}
}