{
  "type": "Feature",
  "properties": {
    "addr:full":"Pieter Landsensstraat 2 Koekelare West-Vlaanderen 8680",
    "addr:housenumber":"2",
    "addr:postcode":"8680",
    "addr:street":"Pieter Landsensstraat",
    "iso:country":"BE",
    "sg:address":"Pieter Landsensstraat 2",
    "sg:city":"Koekelare",
    "sg:orig_category":"Banques and organismes de cr\u00e9dit. Assurances. Pr\u00eats hypoth\u00e9caires and cr\u00e9dits immobiliers",
    "sg:phone":"+32 51 58 11 21",
    "sg:postcode":"8680",
    "sg:province":"West-Vlaanderen",
    "wof:name":"Kantoor Volcke/centea",
    "wof:placetype":"venue"
},
  "geometry": {"coordinates":[2.980700016,51.0904579163],"type":"Point"}
}