{
  "type": "Feature",
  "properties": {
    "addr:full":"Haachtsebaan 142 Keerbergen Vlaams-Brabant 3140",
    "addr:housenumber":"142",
    "addr:postcode":"3140",
    "addr:street":"Haachtsebaan",
    "iso:country":"BE",
    "sg:address":"Haachtsebaan 142",
    "sg:city":"Keerbergen",
    "sg:classifiers":[
        {
            "category":"Restaurant",
            "type":"Food & Drink"
        }
    ],
    "sg:phone":"+32 15 51 82 05",
    "sg:postcode":"3140",
    "sg:province":"Vlaams-Brabant",
    "wof:name":"Piervenshof",
    "wof:placetype":"venue"
},
  "geometry": {"coordinates":[4.6446208954,50.9941864014],"type":"Point"}
}