{
  "type": "Feature",
  "properties": {
    "iso:country":"BE",
    "sg:address":"Rue Fran\u00c7ois Dorz\u00c9e 2",
    "sg:city":"Boussu",
    "sg:orig_category":"Maisons de repos and r\u00e9sidences",
    "sg:phone":"+32 65 78 52 70",
    "sg:postcode":"7300",
    "sg:province":"Hainaut",
    "wof:name":"Home Guerin",
    "wof:placetype":"venue"
},
  "geometry": {"coordinates":[3.7968809605,50.433631897],"type":"Point"}
}