{
  "type": "Feature",
  "properties": {
    "addr:full":"Sint-benedictusstraat 121 Box E Mortsel Antwerpen 2640",
    "addr:housenumber":"121",
    "addr:postcode":"2640",
    "addr:street":"Sint-Benedictusstraat;Box E",
    "iso:country":"BE",
    "sg:address":"Sint-benedictusstraat 121 Box E",
    "sg:city":"Mortsel",
    "sg:classifiers":[
        {
            "category":"Professional",
            "subcategory":"Advertising",
            "type":"Services"
        }
    ],
    "sg:postcode":"2640",
    "sg:province":"Antwerpen",
    "sg:tags":[
        "clothes"
    ],
    "wof:name":"Class Broderie Bvba",
    "wof:placetype":"venue"
},
  "geometry": {"coordinates":[4.4624400139,51.1656799316],"type":"Point"}
}