{
  "type": "Feature",
  "properties": {
    "addr:full":"Place Albert Leemans 2-4 Bruxelles (ixelles) Bruxelles-Capitale 1050",
    "addr:housenumber":"2-4",
    "addr:postcode":"1050",
    "addr:street":"Place Albert Leemans",
    "iso:country":"BE",
    "sg:address":"Place Albert Leemans 2-4",
    "sg:city":"Bruxelles (ixelles)",
    "sg:classifiers":[
        {
            "category":"Professional",
            "subcategory":"Management & Consulting",
            "type":"Services"
        }
    ],
    "sg:phone":"+32 2 537 28 12",
    "sg:postcode":"1050",
    "sg:province":"Bruxelles-Capitale",
    "sg:tags":[
        "-",
        "processing",
        "data",
        "consultant"
    ],
    "wof:name":"Computer Graphics & Scientifics Applications",
    "wof:placetype":"venue"
},
  "geometry": {"coordinates":[4.3626871109,50.8219871521],"type":"Point"}
}