{
  "type": "Feature",
  "properties": {
    "addr:full":"R. Bultynckstraat 9 Ingelmunster West-Vlaanderen 8770",
    "addr:housenumber":"9",
    "addr:postcode":"8770",
    "addr:street":"Bultynckstraat",
    "iso:country":"BE",
    "sg:address":"R. Bultynckstraat 9",
    "sg:city":"Ingelmunster",
    "sg:orig_category":"V\u00eatements",
    "sg:phone":"+32 51 48 93 96",
    "sg:postcode":"8770",
    "sg:province":"West-Vlaanderen",
    "wof:name":"Bontatelier Coucke-desmet",
    "wof:placetype":"venue"
},
  "geometry": {"coordinates":[3.2575960159,50.9260902405],"type":"Point"}
}