{
  "type": "Feature",
  "properties": {
    "iso:country":"BE",
    "sg:address":"Hekkerstraat 40",
    "sg:city":"Wetteren",
    "sg:classifiers":[
        {
            "category":"Personal",
            "subcategory":"Nail Salon",
            "type":"Services"
        }
    ],
    "sg:phone":"+32 9 369 14 47",
    "sg:postcode":"9230",
    "sg:province":"Oost-Vlaanderen",
    "sg:tags":[
        "pedicure"
    ],
    "wof:name":"Bockstaele F",
    "wof:placetype":"venue"
},
  "geometry": {"coordinates":[3.8854300976,51.005569458],"type":"Point"}
}