{
  "type": "Feature",
  "properties": {
    "addr:full":"Chauss\u00c9e De Mons 141 Soignies Hainaut 7060",
    "addr:housenumber":"141",
    "addr:postcode":"7060",
    "addr:street":"Chausse\u0301E De Mons",
    "iso:country":"BE",
    "sg:address":"Chauss\u00c9e De Mons 141",
    "sg:city":"Soignies",
    "sg:orig_category":"Dameskledingzaken",
    "sg:phone":"+32 67 33 06 00",
    "sg:postcode":"7060",
    "sg:province":"Hainaut",
    "wof:name":"Maison Gipsy",
    "wof:placetype":"venue"
},
  "geometry": {"coordinates":[4.0617809296,50.5652542114],"type":"Point"}
}