{
  "type": "Feature",
  "properties": {
    "addr:full":"Rue De Verdun 368 Brussel/bruxelles Bruxelles-Capitale 1130",
    "addr:housenumber":"368",
    "addr:postcode":"1130",
    "addr:street":"Rue De Verdun;/",
    "iso:country":"BE",
    "sg:address":"Rue De Verdun 368",
    "sg:city":"Brussel/bruxelles",
    "sg:classifiers":[
        {
            "category":"Insurance",
            "subcategory":"Life Insurance",
            "type":"Services"
        }
    ],
    "sg:phone":"+32 2 216 03 69",
    "sg:postcode":"1130",
    "sg:province":"Bruxelles-Capitale",
    "sg:tags":[
        "assurance"
    ],
    "wof:name":"L. Mommaerts",
    "wof:placetype":"venue"
},
  "geometry": {"coordinates":[4.4176301956,50.891292572],"type":"Point"}
}