{
  "type": "Feature",
  "properties": {
    "iso:country":"BE",
    "sg:address":"Wijgmaalbroek 98",
    "sg:city":"Leuven (wijgmaal)",
    "sg:classifiers":[
        {
            "category":"Education",
            "subcategory":"Music School",
            "type":"Public Place"
        }
    ],
    "sg:phone":"+32 16 44 62 31",
    "sg:postcode":"3018",
    "sg:province":"Vlaams-Brabant",
    "sg:tags":[
        "-",
        "teacher",
        "private"
    ],
    "wof:name":"Andriessen E",
    "wof:placetype":"venue"
},
  "geometry": {"coordinates":[4.7056679726,50.9366416931],"type":"Point"}
}