{
  "type": "Feature",
  "properties": {
    "iso:country":"BE",
    "sg:address":"Bochtenstraat 44",
    "sg:city":"Laarne",
    "sg:orig_category":"V\u00e9t\u00e9rinaires",
    "sg:phone":"+32 9 369 50 45",
    "sg:postcode":"9270",
    "sg:province":"Oost-Vlaanderen",
    "wof:name":"Frank Van Imschoot",
    "wof:placetype":"venue"
},
  "geometry": {"coordinates":[3.8598101139,51.0325317383],"type":"Point"}
}