{
  "type": "Feature",
  "properties": {
    "iso:country":"BE",
    "sg:address":"Moschaardstraat 6",
    "sg:city":"Waregem",
    "sg:orig_category":"Plantes and fleurs Gr",
    "sg:phone":"+32 56 77 75 83",
    "sg:postcode":"8790",
    "sg:province":"West-Vlaanderen",
    "wof:name":"De Groote - Coorevits",
    "wof:placetype":"venue"
},
  "geometry": {"coordinates":[3.4057788849,50.8472938538],"type":"Point"}
}