{
  "type": "Feature",
  "properties": {
    "iso:country":"BE",
    "sg:address":"Rue Grande 95",
    "sg:city":"Gedinne (vencimont)",
    "sg:classifiers":[
        {
            "category":"Sports & Exercise",
            "subcategory":"Stables",
            "type":"Entertainment"
        }
    ],
    "sg:phone":"+32 61 58 76 24",
    "sg:postcode":"5575",
    "sg:province":"Namur",
    "sg:tags":[
        "riding",
        "school"
    ],
    "wof:name":"Moulin (club Equestre Du)",
    "wof:placetype":"venue"
},
  "geometry": {"coordinates":[4.919069767,50.031829834],"type":"Point"}
}