{
  "type": "Feature",
  "properties": {
    "addr:full":"Rue De La Bruy\u00c8re 138 Rixensart Brabant Wallon 1332",
    "addr:housenumber":"138",
    "addr:postcode":"1332",
    "addr:street":"Rue De La Bruye\u0300Re;Wallon",
    "iso:country":"BE",
    "sg:address":"Rue De La Bruy\u00c8re 138",
    "sg:city":"Rixensart",
    "sg:orig_category":"Dakwerken",
    "sg:phone":"+32 2 653 10 40",
    "sg:postcode":"1332",
    "sg:province":"Brabant Wallon",
    "wof:name":"Freddy Voets",
    "wof:placetype":"venue"
},
  "geometry": {"coordinates":[4.4914159775,50.7234611511],"type":"Point"}
}