{
  "type": "Feature",
  "properties": {
    "iso:country":"BE",
    "sg:address":"Groendreef 53",
    "sg:city":"Lokeren",
    "sg:classifiers":[
        {
            "category":"Shopping",
            "subcategory":"Crafts & Fabrics",
            "type":"Retail Goods"
        }
    ],
    "sg:phone":"+32 9 348 58 75",
    "sg:postcode":"9160",
    "sg:province":"Oost-Vlaanderen",
    "sg:tags":[
        "paints",
        "varnish",
        "-",
        "lacquers",
        "enamel"
    ],
    "wof:name":"Zeep- & Verffabriek",
    "wof:placetype":"venue"
},
  "geometry": {"coordinates":[3.9853188992,51.1095504761],"type":"Point"}
}