{
  "type": "Feature",
  "properties": {
    "addr:full":"Grand\u00b4rue - Rowe 23 Clavier Li\u00e8ge 4560",
    "addr:housenumber":"23",
    "addr:postcode":"4560",
    "iso:country":"BE",
    "sg:address":"Grand\u00b4rue - Rowe 23",
    "sg:city":"Clavier",
    "sg:orig_category":"Enseignement maternel and primaire",
    "sg:phone":"+32 86 34 46 22",
    "sg:postcode":"4560",
    "sg:province":"Li\u00e8ge",
    "wof:name":"E.p.l. St.remacle",
    "wof:placetype":"venue"
},
  "geometry": {"coordinates":[5.3973622322,50.3965377808],"type":"Point"}
}