{
  "type": "Feature",
  "properties": {
    "iso:country":"BE",
    "sg:address":"Rue De L\u00b4ile 20",
    "sg:city":"Anh\u00c9e",
    "sg:classifiers":[
        {
            "category":"Arena",
            "subcategory":"Sports Club",
            "type":"Entertainment"
        }
    ],
    "sg:phone":"+32 82 61 28 52",
    "sg:postcode":"5537",
    "sg:province":"Namur",
    "sg:tags":[
        "de"
    ],
    "wof:name":"P\u00c9dalier Mosan",
    "wof:placetype":"venue"
},
  "geometry": {"coordinates":[4.8948078156,50.2994537354],"type":"Point"}
}