{
  "type": "Feature",
  "properties": {
    "addr:full":"Nijlense Steenweg 252 Herenthout Antwerpen 2270",
    "addr:housenumber":"252",
    "addr:postcode":"2270",
    "addr:street":"Nijlense Steenweg",
    "iso:country":"BE",
    "sg:address":"Nijlense Steenweg 252",
    "sg:city":"Herenthout",
    "sg:orig_category":"Eleveurs de bovins",
    "sg:phone":"+32 14 51 14 56",
    "sg:postcode":"2270",
    "sg:province":"Antwerpen",
    "wof:name":"Rene Meuris",
    "wof:placetype":"venue"
},
  "geometry": {"coordinates":[4.7260861397,51.1459007263],"type":"Point"}
}