{
  "type": "Feature",
  "properties": {
    "addr:full":"Ieperse Steenweg 8 Veurne West-Vlaanderen 8630",
    "addr:housenumber":"8",
    "addr:postcode":"8630",
    "addr:street":"Steenweg",
    "iso:country":"BE",
    "sg:address":"Ieperse Steenweg 8",
    "sg:city":"Veurne",
    "sg:classifiers":[
        {
            "category":"Banks & Credit Unions",
            "subcategory":"Bank",
            "type":"Services"
        }
    ],
    "sg:phone":"+32 58 31 49 40",
    "sg:postcode":"8630",
    "sg:province":"West-Vlaanderen",
    "sg:tags":[
        "savings-banks"
    ],
    "wof:name":"Haerynck P",
    "wof:placetype":"venue"
},
  "geometry": {"coordinates":[2.6649739742,51.0675621033],"type":"Point"}
}