{
  "type": "Feature",
  "properties": {
    "iso:country":"BE",
    "sg:address":"Rue Du Lac 27",
    "sg:city":"Waimes/waimes",
    "sg:orig_category":"Artsen and specialisten",
    "sg:phone":"+32 80 44 44 48",
    "sg:postcode":"4950",
    "sg:province":"Li\u00e8ge",
    "wof:name":"Carine Werts",
    "wof:placetype":"venue"
},
  "geometry": {"coordinates":[6.1406908035,50.4036178589],"type":"Point"}
}