{
  "type": "Feature",
  "properties": {
    "iso:country":"BE",
    "sg:address":"'s-herenwegveld 22",
    "sg:city":"Herent",
    "sg:orig_category":"Animations diverses",
    "sg:phone":"+32 16 20 34 12",
    "sg:postcode":"3020",
    "sg:province":"Vlaams-Brabant",
    "wof:name":"Erin Gobragh",
    "wof:placetype":"venue"
},
  "geometry": {"coordinates":[4.6810708046,50.9023742676],"type":"Point"}
}