{
  "type": "Feature",
  "properties": {
    "addr:full":"Kastanjestraat 14 Houthalen-helchteren Limburg 3530",
    "addr:housenumber":"14",
    "addr:postcode":"3530",
    "addr:street":"Kastanjestraat",
    "iso:country":"BE",
    "sg:address":"Kastanjestraat 14",
    "sg:city":"Houthalen-helchteren",
    "sg:orig_category":"Diverse kredietdiensten",
    "sg:postcode":"3530",
    "sg:province":"Limburg",
    "wof:name":"Bancontact-mister Cash",
    "wof:placetype":"venue"
},
  "geometry": {"coordinates":[5.480861187,51.0244293213],"type":"Point"}
}