{
  "type": "Feature",
  "properties": {
    "addr:full":"Beertsestraat 21 Halle Vlaams-Brabant 1500",
    "addr:housenumber":"21",
    "addr:postcode":"1500",
    "addr:street":"Beertsestraat",
    "iso:country":"BE",
    "sg:address":"Beertsestraat 21",
    "sg:city":"Halle",
    "sg:classifiers":[
        {
            "category":"Health Services",
            "subcategory":"Hospital",
            "type":"Services"
        }
    ],
    "sg:phone":"+32 2 361 21 28",
    "sg:postcode":"1500",
    "sg:province":"Vlaams-Brabant",
    "wof:name":"Passant C.g.g. Vzw",
    "wof:placetype":"venue"
},
  "geometry": {"coordinates":[4.2314977646,50.7322044373],"type":"Point"}
}