{
  "type": "Feature",
  "properties": {
    "addr:full":"Kerkstraat 129 Anzegem West-Vlaanderen 8570",
    "addr:housenumber":"129",
    "addr:postcode":"8570",
    "addr:street":"Kerkstraat",
    "iso:country":"BE",
    "sg:address":"Kerkstraat 129",
    "sg:city":"Anzegem",
    "sg:classifiers":[
        {
            "category":"Bakery",
            "type":"Food & Drink"
        }
    ],
    "sg:phone":"+32 56 68 85 36",
    "sg:postcode":"8570",
    "sg:province":"West-Vlaanderen",
    "sg:tags":[
        "confectioner",
        "baker"
    ],
    "wof:name":"Vanhouteghem J",
    "wof:placetype":"venue"
},
  "geometry": {"coordinates":[3.4744200706,50.8386116028],"type":"Point"}
}