{
  "type": "Feature",
  "properties": {
    "addr:full":"Goorken 68 Westerlo Antwerpen 2260",
    "addr:housenumber":"68",
    "addr:postcode":"2260",
    "addr:street":"Goorken",
    "iso:country":"BE",
    "sg:address":"Goorken 68",
    "sg:city":"Westerlo",
    "sg:classifiers":[
        {
            "category":"Health Services",
            "subcategory":"Health Practitioner",
            "type":"Services"
        }
    ],
    "sg:phone":"+32 14 54 57 24",
    "sg:postcode":"2260",
    "sg:province":"Antwerpen",
    "sg:tags":[
        "physiotherapist"
    ],
    "wof:name":"Caers Louis",
    "wof:placetype":"venue"
},
  "geometry": {"coordinates":[4.9149799347,51.1002616882],"type":"Point"}
}