{
  "type": "Feature",
  "properties": {
    "iso:country":"BE",
    "sg:address":"Peerderbaan 38",
    "sg:city":"Bree",
    "sg:orig_category":"Benzinestations and brandstoffen Herstellingen and onderhoud van auto's Onderdelen and accessoires v",
    "sg:phone":"+32 89 46 18 12",
    "sg:postcode":"3960",
    "sg:province":"Limburg",
    "wof:name":"Gerard Heynickx",
    "wof:placetype":"venue"
},
  "geometry": {"coordinates":[5.5944190025,51.1405677795],"type":"Point"}
}