{
  "type": "Feature",
  "properties": {
    "iso:country":"BE",
    "sg:address":"Dalenbergstraat 44",
    "sg:city":"Beringen (paal)",
    "sg:classifiers":[
        {
            "category":"Building & Trades",
            "subcategory":"Landscaping Services",
            "type":"Services"
        }
    ],
    "sg:phone":"+32 11 42 94 51",
    "sg:postcode":"3583",
    "sg:province":"Limburg",
    "sg:tags":[
        "irrigation",
        "system"
    ],
    "wof:name":"Beregeningstechniek Danny Wils",
    "wof:placetype":"venue"
},
  "geometry": {"coordinates":[5.1706700325,51.0389442444],"type":"Point"}
}