{
  "type": "Feature",
  "properties": {
    "iso:country":"BE",
    "sg:address":"De Cassinastraat 38",
    "sg:city":"Deerlijk",
    "sg:orig_category":"Dierenartsen",
    "sg:phone":"+32 56 70 22 28",
    "sg:postcode":"8540",
    "sg:province":"West-Vlaanderen",
    "wof:name":"Jean Corteville",
    "wof:placetype":"venue"
},
  "geometry": {"coordinates":[3.3423480988,50.8498420715],"type":"Point"}
}