{
  "type": "Feature",
  "properties": {
    "addr:full":"Sint-maria-ten-boslei 10 Schoten Antwerpen 2900",
    "addr:housenumber":"10",
    "addr:postcode":"2900",
    "addr:street":"Sint-Maria-Ten-Boslei",
    "iso:country":"BE",
    "sg:address":"Sint-maria-ten-boslei 10",
    "sg:city":"Schoten",
    "sg:orig_category":"Enseignement maternel and primaire",
    "sg:phone":"+32 3 658 48 42",
    "sg:postcode":"2900",
    "sg:province":"Antwerpen",
    "wof:name":"Vrije Basisschool",
    "wof:placetype":"venue"
},
  "geometry": {"coordinates":[4.5320367813,51.2677268982],"type":"Point"}
}