{
  "type": "Feature",
  "properties": {
    "iso:country":"BE",
    "sg:address":"Chemin De La Neuville 54",
    "sg:city":"Dison",
    "sg:orig_category":"Artsen and specialisten",
    "sg:phone":"+32 87 31 59 16",
    "sg:postcode":"4821",
    "sg:province":"Li\u00e8ge",
    "wof:name":"Genevi\u00c8ve Schreuer",
    "wof:placetype":"venue"
},
  "geometry": {"coordinates":[5.881280899,50.6143875122],"type":"Point"}
}