{
  "type": "Feature",
  "properties": {
    "iso:country":"BE",
    "sg:address":"Rue Du Centre 24",
    "sg:city":"Sprimont",
    "sg:classifiers":[
        {
            "category":"Health Services",
            "subcategory":"Doctor",
            "type":"Services"
        }
    ],
    "sg:phone":"+32 4 382 15 01",
    "sg:postcode":"4140",
    "sg:province":"Li\u00e8ge",
    "sg:tags":[
        "orthopedist"
    ],
    "wof:name":"Lecrenier M",
    "wof:placetype":"venue"
},
  "geometry": {"coordinates":[5.6624631882,50.5044708252],"type":"Point"}
}