{
  "type": "Feature",
  "properties": {
    "addr:full":"Lindenstraat 24 Westerlo (oevel) Antwerpen 2260",
    "addr:housenumber":"24",
    "addr:postcode":"2260",
    "addr:street":"Lindenstraat",
    "iso:country":"BE",
    "sg:address":"Lindenstraat 24",
    "sg:city":"Westerlo (oevel)",
    "sg:classifiers":[
        {
            "category":"Bakery",
            "type":"Food & Drink"
        }
    ],
    "sg:phone":"+32 14 21 20 91",
    "sg:postcode":"2260",
    "sg:province":"Antwerpen",
    "sg:tags":[
        "confectioner",
        "baker"
    ],
    "wof:name":"Appels J",
    "wof:placetype":"venue"
},
  "geometry": {"coordinates":[4.9037008286,51.1407546997],"type":"Point"}
}