{
  "type": "Feature",
  "properties": {
    "addr:full":"Polberglei 14 Kapellen Antwerpen 2950",
    "addr:housenumber":"14",
    "addr:postcode":"2950",
    "addr:street":"Polberglei",
    "iso:country":"BE",
    "sg:address":"Polberglei 14",
    "sg:city":"Kapellen",
    "sg:orig_category":"Boekhouders",
    "sg:phone":"+32 3 666 69 55",
    "sg:postcode":"2950",
    "sg:province":"Antwerpen",
    "wof:name":"Jorg Lenaerts",
    "wof:placetype":"venue"
},
  "geometry": {"coordinates":[4.4665880203,51.3511161804],"type":"Point"}
}