{
  "type": "Feature",
  "properties": {
    "addr:full":"Naamsesteenweg 44 Leuven (heverlee) Vlaams-Brabant 3001",
    "addr:housenumber":"44",
    "addr:postcode":"3001",
    "addr:street":"Naamsesteenweg",
    "iso:country":"BE",
    "sg:address":"Naamsesteenweg 44",
    "sg:city":"Leuven (heverlee)",
    "sg:classifiers":[
        {
            "category":"Home & Garden",
            "subcategory":"Carpets & Floor Coverings",
            "type":"Retail Goods"
        }
    ],
    "sg:phone":"+32 16 40 16 19",
    "sg:postcode":"3001",
    "sg:province":"Vlaams-Brabant",
    "sg:tags":[
        "parquet"
    ],
    "wof:name":"D & M Parket",
    "wof:placetype":"venue"
},
  "geometry": {"coordinates":[4.6971650124,50.8672714233],"type":"Point"}
}