{
  "type": "Feature",
  "properties": {
    "iso:country":"BE",
    "sg:address":"Industriepark 15",
    "sg:city":"Hulshout",
    "sg:orig_category":"Herstellingen and onderhoud van auto's",
    "sg:phone":"+32 15 22 26 10",
    "sg:postcode":"2235",
    "sg:province":"Antwerpen",
    "wof:name":"Gustaaf Cle",
    "wof:placetype":"venue"
},
  "geometry": {"coordinates":[4.8110599518,51.0848503113],"type":"Point"}
}