{
  "type": "Feature",
  "properties": {
    "addr:full":"Lazarijstraat 144 Hasselt Limburg 3500",
    "addr:housenumber":"144",
    "addr:postcode":"3500",
    "addr:street":"Lazarijstraat",
    "iso:country":"BE",
    "sg:address":"Lazarijstraat 144",
    "sg:city":"Hasselt",
    "sg:classifiers":[
        {
            "category":"Health Services",
            "subcategory":"Dentist",
            "type":"Services"
        }
    ],
    "sg:phone":"+32 11 25 39 08",
    "sg:postcode":"3500",
    "sg:province":"Limburg",
    "wof:name":"Degueldre Veronique",
    "wof:placetype":"venue"
},
  "geometry": {"coordinates":[5.3324260712,50.9369621277],"type":"Point"}
}