{
  "type": "Feature",
  "properties": {
    "iso:country":"BE",
    "sg:address":"Rue De La Montagen 136",
    "sg:city":"Moeskroen",
    "sg:orig_category":"Eclairage et \u00e9quipements du foyer",
    "sg:phone":"+32 56 34 84 96",
    "sg:postcode":"7712",
    "sg:province":"Hainaut",
    "wof:name":"A Profil",
    "wof:placetype":"venue"
},
  "geometry": {"coordinates":[3.2305419445,50.7357406616],"type":"Point"}
}