{
  "type": "Feature",
  "properties": {
    "iso:country":"BE",
    "sg:address":"Kalmthoutsesteenweg 62ba",
    "sg:city":"Wuustwezel",
    "sg:orig_category":"Woningbouw",
    "sg:phone":"+32 3 669 65 25",
    "sg:postcode":"2990",
    "sg:province":"Antwerpen",
    "wof:name":"Balthazar",
    "wof:placetype":"venue"
},
  "geometry": {"coordinates":[4.5858941078,51.3898735046],"type":"Point"}
}