{
  "type": "Feature",
  "properties": {
    "iso:country":"BE",
    "sg:address":"Dreef 99",
    "sg:city":"Tongeren",
    "sg:orig_category":"Location de voitures",
    "sg:phone":"+32 12 23 88 04",
    "sg:postcode":"3700",
    "sg:province":"Limburg",
    "wof:name":"Sarelco",
    "wof:placetype":"venue"
},
  "geometry": {"coordinates":[5.4636240005,50.7807197571],"type":"Point"}
}