{
  "type": "Feature",
  "properties": {
    "iso:country":"BE",
    "sg:address":"Avenue De L'eau Vive 5",
    "sg:city":"Mouscron (luingne)",
    "sg:classifiers":[
        {
            "category":"Farming",
            "subcategory":"Poultry Farm",
            "type":"Manufacturing & Wholesale Goods"
        }
    ],
    "sg:phone":"+32 56 85 59 00",
    "sg:postcode":"7700",
    "sg:province":"Hainaut",
    "sg:tags":[
        "rabbit",
        "slaughterhouse"
    ],
    "wof:name":"Flandrex Sa",
    "wof:placetype":"venue"
},
  "geometry": {"coordinates":[3.2528369427,50.7444458008],"type":"Point"}
}