{
  "type": "Feature",
  "properties": {
    "iso:country":"BE",
    "sg:address":"Franklin Rooseveltlaan 24",
    "sg:city":"Waregem",
    "sg:orig_category":"Kinderopvang",
    "sg:phone":"+32 56 61 55 48",
    "sg:postcode":"8790",
    "sg:province":"West-Vlaanderen",
    "wof:name":"De Zeven Dwergen",
    "wof:placetype":"venue"
},
  "geometry": {"coordinates":[3.4391720295,50.8820571899],"type":"Point"}
}