{
  "type": "Feature",
  "properties": {
    "iso:country":"BE",
    "sg:address":"Dendermondesesteenweg 52",
    "sg:city":"Wichelen",
    "sg:orig_category":"Gespecialiseerde residenti\u00eble bouw",
    "sg:phone":"+32 9 366 71 51",
    "sg:postcode":"9260",
    "sg:province":"Oost-Vlaanderen",
    "wof:name":"Van Houwermeieren",
    "wof:placetype":"venue"
},
  "geometry": {"coordinates":[3.9378559589,51.007232666],"type":"Point"}
}