{
  "type": "Feature",
  "properties": {
    "addr:full":"Haachtsesteenweg 479 Schaarbeek/schaerbeek Bruxelles-Capitale 1030",
    "addr:housenumber":"479",
    "addr:postcode":"1030",
    "addr:street":"Haachtsesteenweg",
    "iso:country":"BE",
    "sg:address":"Haachtsesteenweg 479",
    "sg:city":"Schaarbeek/schaerbeek",
    "sg:orig_category":"Kinderopvang Kleuter- en basisonderwijs",
    "sg:phone":"+32 2 215 09 50",
    "sg:postcode":"1030",
    "sg:province":"Bruxelles-Capitale",
    "wof:name":"Kribbe Zonnekind",
    "wof:placetype":"venue"
},
  "geometry": {"coordinates":[4.3813281059,50.8681869507],"type":"Point"}
}