{
  "type": "Feature",
  "properties": {
    "addr:full":"Pitantiestraat 111 Waregem (desselgem) West-Vlaanderen 8792",
    "addr:housenumber":"111",
    "addr:postcode":"8792",
    "addr:street":"Pitantiestraat",
    "iso:country":"BE",
    "sg:address":"Pitantiestraat 111",
    "sg:city":"Waregem (desselgem)",
    "sg:orig_category":"Non-Classified Establishments",
    "sg:phone":"+32 56 72 51 40",
    "sg:postcode":"8792",
    "sg:province":"West-Vlaanderen",
    "wof:name":"Ritbel",
    "wof:placetype":"venue"
},
  "geometry": {"coordinates":[3.3731629848,50.8965034485],"type":"Point"}
}