{
  "type": "Feature",
  "properties": {
    "iso:country":"BE",
    "sg:address":"Dr\u00c9ve De La Bussche 4",
    "sg:city":"Komen-waasten/comines-warneton",
    "sg:orig_category":"Producteurs de l\u00e9gumes",
    "sg:phone":"+32 56 55 62 08",
    "sg:postcode":"7784",
    "sg:province":"Hainaut",
    "wof:name":"A La Ferme De L'emmanuel",
    "wof:placetype":"venue"
},
  "geometry": {"coordinates":[2.9637548923,50.7604637146],"type":"Point"}
}