{
  "type": "Feature",
  "properties": {
    "iso:country":"BE",
    "sg:address":"Route De Mons 22",
    "sg:city":"Charleroi",
    "sg:orig_category":"HERSTELLING ELEKTRISCHE HUISHOUDAPPARATEN Huishoudapparaten, televisies and radio's Telecommunicatie",
    "sg:phone":"+32 71 30 22 99",
    "sg:postcode":"6031",
    "sg:province":"Hainaut",
    "wof:name":"Eldi",
    "wof:placetype":"venue"
},
  "geometry": {"coordinates":[4.3944740295,50.4108009338],"type":"Point"}
}