{
  "type": "Feature",
  "properties": {
    "addr:full":"Kruisstraat 18 Izegem West-Vlaanderen 8870",
    "addr:housenumber":"18",
    "addr:postcode":"8870",
    "addr:street":"Kruisstraat",
    "iso:country":"BE",
    "sg:address":"Kruisstraat 18",
    "sg:city":"Izegem",
    "sg:classifiers":[
        {
            "category":"Insurance",
            "subcategory":"Insurance Agent",
            "type":"Services"
        }
    ],
    "sg:phone":"+32 51 30 43 24",
    "sg:postcode":"8870",
    "sg:province":"West-Vlaanderen",
    "sg:tags":[
        "broker"
    ],
    "wof:name":"Trust-as-sure Bvba",
    "wof:placetype":"venue"
},
  "geometry": {"coordinates":[3.2107839584,50.9194755554],"type":"Point"}
}