{
  "type": "Feature",
  "properties": {
    "addr:full":"Fortuinstraat 3 Roeselare West-Vlaanderen 8800",
    "addr:housenumber":"3",
    "addr:postcode":"8800",
    "addr:street":"Fortuinstraat",
    "iso:country":"BE",
    "sg:address":"Fortuinstraat 3",
    "sg:city":"Roeselare",
    "sg:classifiers":[
        {
            "category":"Real Estate",
            "subcategory":"Architect",
            "type":"Services"
        }
    ],
    "sg:phone":"+32 51 20 68 42",
    "sg:postcode":"8800",
    "sg:province":"West-Vlaanderen",
    "wof:name":"Remmery R",
    "wof:placetype":"venue"
},
  "geometry": {"coordinates":[3.1338551044,50.9465866089],"type":"Point"}
}