{
  "type": "Feature",
  "properties": {
    "addr:full":"Route D'ortho 16 La Roche-en-ardenne Luxembourg 6980",
    "addr:housenumber":"16",
    "addr:postcode":"6980",
    "addr:street":"Route D'Ortho",
    "iso:country":"BE",
    "sg:address":"Route D'ortho 16",
    "sg:city":"La Roche-en-ardenne",
    "sg:classifiers":[
        {
            "category":"Bars & Pubs",
            "type":"Food & Drink"
        }
    ],
    "sg:phone":"+32 84 43 31 19",
    "sg:postcode":"6980",
    "sg:province":"Luxembourg",
    "wof:name":"Sports (caf\u00e9 Des)",
    "wof:placetype":"venue"
},
  "geometry": {"coordinates":[5.5781478882,50.1763458252],"type":"Point"}
}