{
  "type": "Feature",
  "properties": {
    "iso:country":"BE",
    "sg:address":"Rotselaerlaan 48",
    "sg:city":"Tervuren",
    "sg:classifiers":[
        {
            "category":"Professional",
            "subcategory":"Engineering",
            "type":"Services"
        }
    ],
    "sg:phone":"+32 2 305 59 18",
    "sg:postcode":"3080",
    "sg:province":"Vlaams-Brabant",
    "sg:tags":[
        "civil",
        "offices-"
    ],
    "wof:name":"Concept Consult Design",
    "wof:placetype":"venue"
},
  "geometry": {"coordinates":[4.527671814,50.8360786438],"type":"Point"}
}