{
  "type": "Feature",
  "properties": {
    "addr:full":"Leistraat 50 Kasterlee (lichtaart) Antwerpen 2460",
    "addr:housenumber":"50",
    "addr:postcode":"2460",
    "addr:street":"Leistraat",
    "iso:country":"BE",
    "sg:address":"Leistraat 50",
    "sg:city":"Kasterlee (lichtaart)",
    "sg:classifiers":[
        {
            "category":"Shopping",
            "subcategory":"Shoes",
            "type":"Retail Goods"
        }
    ],
    "sg:phone":"+32 14 55 74 78",
    "sg:postcode":"2460",
    "sg:province":"Antwerpen",
    "sg:tags":[
        "slipper",
        "-"
    ],
    "wof:name":"Wuyts A",
    "wof:placetype":"venue"
},
  "geometry": {"coordinates":[4.9193401337,51.2246627808],"type":"Point"}
}