{
  "type": "Feature",
  "properties": {
    "iso:country":"BE",
    "sg:address":"Kerkstraat 13",
    "sg:city":"Sint-niklaas",
    "sg:orig_category":"Enseignement maternel and primaire",
    "sg:phone":"+32 3 772 35 12",
    "sg:postcode":"9111",
    "sg:province":"Oost-Vlaanderen",
    "wof:name":"Vrije Basisschool",
    "wof:placetype":"venue"
},
  "geometry": {"coordinates":[4.0889000893,51.1495285034],"type":"Point"}
}