{
  "type": "Feature",
  "properties": {
    "addr:full":"Rue De L'emprunt 73 Namur Namur 5100",
    "addr:housenumber":"73",
    "addr:postcode":"5100",
    "addr:street":"Rue De L'Emprunt",
    "iso:country":"BE",
    "sg:address":"Rue De L'emprunt 73",
    "sg:city":"Namur",
    "sg:orig_category":"Experts-comptables",
    "sg:phone":"+32 81 30 45 28",
    "sg:postcode":"5100",
    "sg:province":"Namur",
    "wof:name":"Rene Houdmont",
    "wof:placetype":"venue"
},
  "geometry": {"coordinates":[4.8666610718,50.4359169006],"type":"Point"}
}