{
  "type": "Feature",
  "properties": {
    "iso:country":"BE",
    "sg:address":"Brugse Heirweg 41",
    "sg:city":"Zedelgem",
    "sg:orig_category":"Mobiele kappers",
    "sg:phone":"+32 50 20 08 27",
    "sg:postcode":"8211",
    "sg:province":"West-Vlaanderen",
    "wof:name":"Lindsay Delaere",
    "wof:placetype":"venue"
},
  "geometry": {"coordinates":[3.0875279903,51.1224365234],"type":"Point"}
}