{
  "type": "Feature",
  "properties": {
    "addr:full":"Breugelweg 64 Overpelt Limburg 3900",
    "addr:housenumber":"64",
    "addr:postcode":"3900",
    "addr:street":"Breugelweg",
    "iso:country":"BE",
    "sg:address":"Breugelweg 64",
    "sg:city":"Overpelt",
    "sg:orig_category":"Royal Canin. Articles de jardin. Animaux domestiques and accessoires",
    "sg:phone":"+32 11 64 42 59",
    "sg:postcode":"3900",
    "sg:province":"Limburg",
    "wof:name":"Sevens Etienne",
    "wof:placetype":"venue"
},
  "geometry": {"coordinates":[5.4294447899,51.2036819458],"type":"Point"}
}