{
  "type": "Feature",
  "properties": {
    "iso:country":"BE",
    "sg:address":"Beernemstraat 34",
    "sg:city":"Wingene",
    "sg:classifiers":[
        {
            "category":"Shopping",
            "subcategory":"Shoes",
            "type":"Retail Goods"
        }
    ],
    "sg:phone":"+32 51 65 53 91",
    "sg:postcode":"8750",
    "sg:province":"West-Vlaanderen",
    "sg:tags":[
        "slipper",
        "-"
    ],
    "wof:name":"Paspaartoe",
    "wof:placetype":"venue"
},
  "geometry": {"coordinates":[3.2773439884,51.0616569519],"type":"Point"}
}