{
  "type": "Feature",
  "properties": {
    "addr:full":"Waterstraat 56 Gent Oost-Vlaanderen 9040",
    "addr:housenumber":"56",
    "addr:postcode":"9040",
    "addr:street":"Waterstraat;Oost-Vlaanderen",
    "iso:country":"BE",
    "sg:address":"Waterstraat 56",
    "sg:city":"Gent",
    "sg:orig_category":"Paramedische behandelingen",
    "sg:phone":"+32 9 259 28 38",
    "sg:postcode":"9040",
    "sg:province":"Oost-Vlaanderen",
    "wof:name":"Anniek Heymann",
    "wof:placetype":"venue"
},
  "geometry": {"coordinates":[3.7549769878,51.072303772],"type":"Point"}
}