{
  "type": "Feature",
  "properties": {
    "addr:full":"Hazenstraat 15 Maasmechelen Limburg 3630",
    "addr:housenumber":"15",
    "addr:postcode":"3630",
    "addr:street":"Hazenstraat",
    "iso:country":"BE",
    "sg:address":"Hazenstraat 15",
    "sg:city":"Maasmechelen",
    "sg:orig_category":"Traitements param\u00e9dicaux",
    "sg:phone":"+32 89 76 02 69",
    "sg:postcode":"3630",
    "sg:province":"Limburg",
    "wof:name":"Vranken",
    "wof:placetype":"venue"
},
  "geometry": {"coordinates":[5.7005372047,50.9564208984],"type":"Point"}
}