{
  "type": "Feature",
  "properties": {
    "iso:country":"BE",
    "sg:address":"Rue De Hanret 2",
    "sg:city":"Fernelmont",
    "sg:orig_category":"Rundveehouders Varkenskwekers",
    "sg:phone":"+32 81 83 31 17",
    "sg:postcode":"5380",
    "sg:province":"Namur",
    "wof:name":"Jean Nandrain",
    "wof:placetype":"venue"
},
  "geometry": {"coordinates":[4.9563131332,50.5680122375],"type":"Point"}
}