{
  "type": "Feature",
  "properties": {
    "addr:full":"Diestsestraat 259 Leuven Vlaams-Brabant 3000",
    "addr:housenumber":"259",
    "addr:postcode":"3000",
    "addr:street":"Diestsestraat",
    "iso:country":"BE",
    "sg:address":"Diestsestraat 259",
    "sg:city":"Leuven",
    "sg:classifiers":[
        {
            "category":"Cafe",
            "type":"Food & Drink"
        }
    ],
    "sg:phone":"+32 16 29 98 05",
    "sg:postcode":"3000",
    "sg:province":"Vlaams-Brabant",
    "sg:tags":[
        "snack-bars"
    ],
    "wof:name":"In De Rapte",
    "wof:placetype":"venue"
},
  "geometry": {"coordinates":[4.7132649422,50.8822631836],"type":"Point"}
}