{
  "type": "Feature",
  "properties": {
    "addr:full":"Rue Du Z\u00e9nith 71 Bruxelles (berchem-sainte-agathe) Bruxelles-Capitale 1082",
    "addr:housenumber":"71",
    "addr:postcode":"1082",
    "addr:street":"Rue Du Ze\u0301Nith",
    "iso:country":"BE",
    "sg:address":"Rue Du Z\u00e9nith 71",
    "sg:city":"Bruxelles (berchem-sainte-agathe)",
    "sg:classifiers":[
        {
            "category":"Education",
            "subcategory":"Dance Studio",
            "type":"Public Place"
        }
    ],
    "sg:phone":"+32 2 465 27 02",
    "sg:postcode":"1082",
    "sg:province":"Bruxelles-Capitale",
    "sg:tags":[
        "ballet",
        "school"
    ],
    "wof:name":"Arras",
    "wof:placetype":"venue"
},
  "geometry": {"coordinates":[4.2814769745,50.8642311096],"type":"Point"}
}