{
  "type": "Feature",
  "properties": {
    "iso:country":"BE",
    "sg:address":"Hoogstraat 221",
    "sg:city":"Duffel",
    "sg:orig_category":"Installation \u00e9lectrique r\u00e9sidentielle",
    "sg:phone":"+32 15 31 31 66",
    "sg:postcode":"2570",
    "sg:province":"Antwerpen",
    "wof:name":"Rombouts K",
    "wof:placetype":"venue"
},
  "geometry": {"coordinates":[4.5284762383,51.0925254822],"type":"Point"}
}