{
  "type": "Feature",
  "properties": {
    "iso:country":"BE",
    "sg:address":"Passage Lemonnier 1",
    "sg:city":"Li\u00e8ge 1",
    "sg:classifiers":[
        {
            "category":"Food & Beverages",
            "subcategory":"Fruits & Vegetables",
            "type":"Retail Goods"
        }
    ],
    "sg:phone":"+32 4 223 31 44",
    "sg:postcode":"4000",
    "sg:province":"Li\u00e8ge",
    "sg:tags":[
        "-",
        "shirt"
    ],
    "wof:name":"Aux 100.000 Chemises Sa",
    "wof:placetype":"venue"
},
  "geometry": {"coordinates":[5.5726780891,50.6426353455],"type":"Point"}
}