{
  "type": "Feature",
  "properties": {
    "addr:full":"Doorn 23 Kruibeke Oost-Vlaanderen 9150",
    "addr:housenumber":"23",
    "addr:postcode":"9150",
    "addr:street":"Doorn",
    "iso:country":"BE",
    "sg:address":"Doorn 23",
    "sg:city":"Kruibeke",
    "sg:classifiers":[
        {
            "category":"Shopping",
            "subcategory":"Bicycles & Sporting Goods",
            "type":"Retail Goods"
        }
    ],
    "sg:phone":"+32 3 774 06 67",
    "sg:postcode":"9150",
    "sg:province":"Oost-Vlaanderen",
    "sg:tags":[
        "sport",
        "-"
    ],
    "wof:name":"Segers Sport Supplies",
    "wof:placetype":"venue"
},
  "geometry": {"coordinates":[5.3469700813,52.0333213806],"type":"Point"}
}