{
  "type": "Feature",
  "properties": {
    "addr:full":"Klavet 14bc Geel Antwerpen 2440",
    "addr:housenumber":"14bc",
    "addr:postcode":"2440",
    "addr:street":"Klavet",
    "iso:country":"BE",
    "sg:address":"Klavet 14bc",
    "sg:city":"Geel",
    "sg:orig_category":"Quincailleries",
    "sg:phone":"+32 14 86 76 69",
    "sg:postcode":"2440",
    "sg:province":"Antwerpen",
    "wof:name":"Huis De Busser A.",
    "wof:placetype":"venue"
},
  "geometry": {"coordinates":[4.9686160088,51.11876297],"type":"Point"}
}