{
  "type": "Feature",
  "properties": {
    "iso:country":"BE",
    "sg:address":"Quai De L'ourthe 13",
    "sg:city":"Comblain-au-pont",
    "sg:orig_category":"V\u00e9hicules automobiles",
    "sg:phone":"+32 4 369 11 27",
    "sg:postcode":"4170",
    "sg:province":"Li\u00e8ge",
    "wof:name":"Garage Walhain Fr\u00c8res",
    "wof:placetype":"venue"
},
  "geometry": {"coordinates":[5.5780382156,50.4764022827],"type":"Point"}
}