{
  "type": "Feature",
  "properties": {
    "iso:country":"BE",
    "sg:address":"Schrevelstraat 15",
    "sg:city":"Houthulst",
    "sg:orig_category":"Eleveurs de bovins",
    "sg:phone":"+32 51 54 59 17",
    "sg:postcode":"8650",
    "sg:province":"West-Vlaanderen",
    "wof:name":"Emile Vangheluwe",
    "wof:placetype":"venue"
},
  "geometry": {"coordinates":[2.8965039253,50.9858055115],"type":"Point"}
}