{
  "type": "Feature",
  "properties": {
    "addr:full":"Godshuizenlaan 2 Gent Oost-Vlaanderen 9000",
    "addr:housenumber":"2",
    "addr:postcode":"9000",
    "addr:street":"Godshuizenlaan;Oost-Vlaanderen",
    "iso:country":"BE",
    "sg:address":"Godshuizenlaan 2",
    "sg:city":"Gent",
    "sg:classifiers":[
        {
            "category":"Museum",
            "type":"Entertainment"
        }
    ],
    "sg:phone":"+32 9 225 11 06",
    "sg:postcode":"9000",
    "sg:province":"Oost-Vlaanderen",
    "wof:name":"Oudheidkundig Museum Bijloke",
    "wof:placetype":"venue"
},
  "geometry": {"coordinates":[3.7167789936,51.0434684753],"type":"Point"}
}