{
  "type": "Feature",
  "properties": {
    "iso:country":"BE",
    "sg:address":"Rue Fran\u00e7ois Roffiaen 29",
    "sg:city":"Bruxelles (ixelles)",
    "sg:classifiers":[
        {
            "category":"Shopping",
            "subcategory":"Books",
            "type":"Retail Goods"
        }
    ],
    "sg:phone":"+32 2 647 19 16",
    "sg:postcode":"1050",
    "sg:province":"Bruxelles-Capitale",
    "sg:tags":[
        "antiquarian",
        "trade"
    ],
    "wof:name":"Librairie Archaion",
    "wof:placetype":"venue"
},
  "geometry": {"coordinates":[4.3823451996,50.8209495544],"type":"Point"}
}