{
  "type": "Feature",
  "properties": {
    "addr:full":"Antwerpsesteenweg 10 Rumst Antwerpen 2840",
    "addr:housenumber":"10",
    "addr:postcode":"2840",
    "addr:street":"Antwerpsesteenweg",
    "iso:country":"BE",
    "sg:address":"Antwerpsesteenweg 10",
    "sg:city":"Rumst",
    "sg:orig_category":"Openbare veiligheid",
    "sg:phone":"+32 15 31 13 93",
    "sg:postcode":"2840",
    "sg:province":"Antwerpen",
    "wof:name":"Federale Politie",
    "wof:placetype":"venue"
},
  "geometry": {"coordinates":[4.4522428513,51.0863800049],"type":"Point"}
}