{
  "type": "Feature",
  "properties": {
    "iso:country":"BE",
    "sg:address":"Dorpstraat 72d",
    "sg:city":"Temse (elversele)",
    "sg:classifiers":[
        {
            "category":"Food & Beverages",
            "subcategory":"Groceries & Convenience Stores",
            "type":"Retail Goods"
        }
    ],
    "sg:phone":"+32 52 46 04 34",
    "sg:postcode":"9140",
    "sg:province":"Oost-Vlaanderen",
    "sg:tags":[
        "grocer"
    ],
    "wof:name":"Prima",
    "wof:placetype":"venue"
},
  "geometry": {"coordinates":[4.1400871277,51.1142578125],"type":"Point"}
}