{
  "type": "Feature",
  "properties": {
    "addr:full":"Rue De Ch\u00can\u00c9e 53 Liege-centre Li\u00e8ge 4031",
    "addr:housenumber":"53",
    "addr:postcode":"4031",
    "addr:street":"Rue De Che\u0302Ne\u0301E",
    "iso:country":"BE",
    "sg:address":"Rue De Ch\u00can\u00c9e 53",
    "sg:city":"Liege-centre",
    "sg:orig_category":"Microsoft. Conseils en syst\u00e8mes informatiques",
    "sg:phone":"+32 4 365 65 72",
    "sg:postcode":"4031",
    "sg:province":"Li\u00e8ge",
    "wof:name":"C2d System House",
    "wof:placetype":"venue"
},
  "geometry": {"coordinates":[2.4079089165,44.1636695862],"type":"Point"}
}