{
  "type": "Feature",
  "properties": {
    "addr:full":"Nachtegaalstraat 1 Aalst Oost-Vlaanderen 9320",
    "addr:housenumber":"1",
    "addr:postcode":"9320",
    "addr:street":"Nachtegaalstraat",
    "iso:country":"BE",
    "sg:address":"Nachtegaalstraat 1",
    "sg:city":"Aalst",
    "sg:orig_category":"Herstellingen and onderhoud van auto's Voertuigen",
    "sg:phone":"+32 53 66 21 10",
    "sg:postcode":"9320",
    "sg:province":"Oost-Vlaanderen",
    "wof:name":"Garage Residence Ii",
    "wof:placetype":"venue"
},
  "geometry": {"coordinates":[4.0553851128,50.9209976196],"type":"Point"}
}