{
  "type": "Feature",
  "properties": {
    "iso:country":"BE",
    "sg:address":"Rue Des Briqueteries 19",
    "sg:city":"Seraing",
    "sg:orig_category":"Installation de menuiserie en bois and plastique",
    "sg:phone":"+32 4 336 91 54",
    "sg:postcode":"4100",
    "sg:province":"Li\u00e8ge",
    "wof:name":"Jean-marc Bourlard",
    "wof:placetype":"venue"
},
  "geometry": {"coordinates":[5.5025019646,50.5818252563],"type":"Point"}
}