{
  "type": "Feature",
  "properties": {
    "addr:full":"Bd Henri Rolin 5b Waterloo Brabant Wallon 1410",
    "addr:housenumber":"5b",
    "addr:postcode":"1410",
    "addr:street":"Bd Henri Rolin",
    "iso:country":"BE",
    "sg:address":"Bd Henri Rolin 5b",
    "sg:city":"Waterloo",
    "sg:classifiers":[
        {
            "category":"Sports & Exercise",
            "subcategory":"Sports Center",
            "type":"Entertainment"
        }
    ],
    "sg:phone":"+32 2 354 58 18",
    "sg:postcode":"1410",
    "sg:province":"Brabant Wallon",
    "sg:tags":[
        "game"
    ],
    "wof:name":"Waterloo Tennis Sa",
    "wof:placetype":"venue"
},
  "geometry": {"coordinates":[4.3998417854,50.7115440369],"type":"Point"}
}