{
  "type": "Feature",
  "properties": {
    "iso:country":"BE",
    "sg:address":"Hof Ter Bekelaan 12",
    "sg:city":"Herent (winksele)",
    "sg:classifiers":[
        {
            "category":"Professional",
            "subcategory":"Secretarial Services",
            "type":"Services"
        }
    ],
    "sg:phone":"+32 16 20 70 77",
    "sg:postcode":"3020",
    "sg:province":"Vlaams-Brabant",
    "sg:tags":[
        "-",
        "wordprocessing"
    ],
    "wof:name":"Rosselle K",
    "wof:placetype":"venue"
},
  "geometry": {"coordinates":[4.6700630188,50.8846969604],"type":"Point"}
}