{
  "type": "Feature",
  "properties": {
    "addr:full":"Grote Baan 221 Hulshout Antwerpen 2235",
    "addr:housenumber":"221",
    "addr:postcode":"2235",
    "addr:street":"Grote Baan",
    "iso:country":"BE",
    "sg:address":"Grote Baan 221",
    "sg:city":"Hulshout",
    "sg:classifiers":[
        {
            "category":"Fast Food",
            "type":"Food & Drink"
        }
    ],
    "sg:phone":"+32 15 22 58 24",
    "sg:postcode":"2235",
    "sg:province":"Antwerpen",
    "sg:tags":[
        "\u00c0",
        "emporter",
        "restaurants"
    ],
    "wof:name":"Frituur De Vaart",
    "wof:placetype":"venue"
},
  "geometry": {"coordinates":[4.8027467728,51.0732040405],"type":"Point"}
}