{
  "type": "Feature",
  "properties": {
    "addr:full":"Francisco Ferrerlaan 111 Gent Oost-Vlaanderen 9000",
    "addr:housenumber":"111",
    "addr:postcode":"9000",
    "addr:street":"Francisco Ferrerlaan;Oost-Vlaanderen",
    "iso:country":"BE",
    "sg:address":"Francisco Ferrerlaan 111",
    "sg:city":"Gent",
    "sg:classifiers":[
        {
            "category":"Health Services",
            "subcategory":"Health Practitioner",
            "type":"Services"
        }
    ],
    "sg:phone":"+32 9 226 11 19",
    "sg:postcode":"9000",
    "sg:province":"Oost-Vlaanderen",
    "sg:tags":[
        "physiotherapist"
    ],
    "wof:name":"Lievens Patrick",
    "wof:placetype":"venue"
},
  "geometry": {"coordinates":[3.7025830746,51.0697517395],"type":"Point"}
}