{
  "type": "Feature",
  "properties": {
    "iso:country":"BE",
    "sg:address":"Gentse Steenweg 79ba",
    "sg:city":"Damme",
    "sg:orig_category":"Elektrische installaties voor woningen Onderdelen and accessoires voor auto's Taxi's Taxi's speciale",
    "sg:phone":"+32 50 37 49 16",
    "sg:postcode":"8340",
    "sg:province":"West-Vlaanderen",
    "wof:name":"Autotronic",
    "wof:placetype":"venue"
},
  "geometry": {"coordinates":[3.3625779152,51.2037887573],"type":"Point"}
}