{
  "type": "Feature",
  "properties": {
    "iso:country":"BE",
    "sg:address":"Kastermanstraat 13",
    "sg:city":"Geel",
    "sg:orig_category":"Rundveehouders",
    "sg:phone":"+32 14 59 32 48",
    "sg:postcode":"2440",
    "sg:province":"Antwerpen",
    "wof:name":"Paul Biermans",
    "wof:placetype":"venue"
},
  "geometry": {"coordinates":[5.0012497902,51.1846199036],"type":"Point"}
}