{
  "type": "Feature",
  "properties": {
    "addr:full":"Rue Arthur Durant 55bbis Mons Hainaut 7012",
    "addr:housenumber":"55bbis",
    "addr:postcode":"7012",
    "addr:street":"Rue Arthur Durant;Hainaut",
    "iso:country":"BE",
    "sg:address":"Rue Arthur Durant 55bbis",
    "sg:city":"Mons",
    "sg:classifiers":[
        {
            "category":"Cafe",
            "type":"Food & Drink"
        }
    ],
    "sg:phone":"+32 65 88 58 59",
    "sg:postcode":"7012",
    "sg:province":"Hainaut",
    "sg:tags":[
        "caf\u00e9s"
    ],
    "wof:name":"Amis De L'appart",
    "wof:placetype":"venue"
},
  "geometry": {"coordinates":[3.8894600868,50.4481964111],"type":"Point"}
}