{
  "type": "Feature",
  "properties": {
    "addr:full":"Rue De Vis\u00e9 328b Li\u00e8ge 1 (jupille-sur-meuse) Li\u00e8ge 4020",
    "addr:housenumber":"328b;1",
    "addr:postcode":"4020",
    "addr:street":"Rue De Vise\u0301;Jupille-Sur-Meuse Lie\u0300Ge",
    "iso:country":"BE",
    "sg:address":"Rue De Vis\u00e9 328b",
    "sg:city":"Li\u00e8ge 1 (jupille-sur-meuse)",
    "sg:classifiers":[
        {
            "category":"Retail",
            "subcategory":"Auto Repair",
            "type":"Services"
        }
    ],
    "sg:phone":"+32 4 370 07 65",
    "sg:postcode":"4020",
    "sg:province":"Li\u00e8ge",
    "sg:tags":[
        "garage"
    ],
    "wof:name":"A.t.p.i. Sa",
    "wof:placetype":"venue"
},
  "geometry": {"coordinates":[5.6387968063,50.6502494812],"type":"Point"}
}