{
  "type": "Feature",
  "properties": {
    "addr:full":"Rue De Petin 24 Chimay (baileux) Hainaut 6464",
    "addr:housenumber":"24",
    "addr:postcode":"6464",
    "addr:street":"Rue De Petin",
    "iso:country":"BE",
    "sg:address":"Rue De Petin 24",
    "sg:city":"Chimay (baileux)",
    "sg:classifiers":[
        {
            "category":"Home & Garden",
            "subcategory":"Kitchen Supply",
            "type":"Retail Goods"
        }
    ],
    "sg:phone":"+32 60 21 20 95",
    "sg:postcode":"6464",
    "sg:province":"Hainaut",
    "sg:tags":[
        "installation"
    ],
    "wof:name":"Canivet M",
    "wof:placetype":"venue"
},
  "geometry": {"coordinates":[4.3763132095,50.03358078],"type":"Point"}
}