{
  "type": "Feature",
  "properties": {
    "iso:country":"BE",
    "sg:address":"Personaathoflaan 19",
    "sg:city":"Dilbeek",
    "sg:orig_category":"Woningbouw",
    "sg:phone":"+32 2 567 20 68",
    "sg:postcode":"1700",
    "sg:province":"Vlaams-Brabant",
    "wof:name":"Devuyst A",
    "wof:placetype":"venue"
},
  "geometry": {"coordinates":[4.2285041809,50.8538894653],"type":"Point"}
}