{
  "type": "Feature",
  "properties": {
    "addr:full":"Rue Des Trys 44 Yvoir (godinne) Namur 5530",
    "addr:housenumber":"44",
    "addr:postcode":"5530",
    "addr:street":"Rue Des Trys",
    "iso:country":"BE",
    "sg:address":"Rue Des Trys 44",
    "sg:city":"Yvoir (godinne)",
    "sg:classifiers":[
        {
            "category":"Health Services",
            "subcategory":"Doctor",
            "type":"Services"
        }
    ],
    "sg:phone":"+32 82 61 15 43",
    "sg:postcode":"5530",
    "sg:province":"Namur",
    "sg:tags":[
        "medicinephysicians",
        "surgeon"
    ],
    "wof:name":"Hembise P",
    "wof:placetype":"venue"
},
  "geometry": {"coordinates":[4.8792037964,50.3464698792],"type":"Point"}
}