{
  "type": "Feature",
  "properties": {
    "addr:full":"Rue Joseph Ferrant 15 Renaix Oost-Vlaanderen 9600",
    "addr:housenumber":"15",
    "addr:postcode":"9600",
    "addr:street":"Rue Joseph Ferrant",
    "iso:country":"BE",
    "sg:address":"Rue Joseph Ferrant 15",
    "sg:city":"Renaix",
    "sg:orig_category":"Non-Classified Establishments",
    "sg:phone":"+32 55 21 12 72",
    "sg:postcode":"9600",
    "sg:province":"Oost-Vlaanderen",
    "wof:name":"General Electric-rundfunk Vr",
    "wof:placetype":"venue"
},
  "geometry": {"coordinates":[3.6042830944,50.7436981201],"type":"Point"}
}