{
  "type": "Feature",
  "properties": {
    "addr:full":"Kezelbergstraat 1 Zedelgem West-Vlaanderen 8210",
    "addr:housenumber":"1",
    "addr:postcode":"8210",
    "addr:street":"Kezelbergstraat",
    "iso:country":"BE",
    "sg:address":"Kezelbergstraat 1",
    "sg:city":"Zedelgem",
    "sg:orig_category":"Artsen and specialisten",
    "sg:phone":"+32 50 20 85 89",
    "sg:postcode":"8210",
    "sg:province":"West-Vlaanderen",
    "wof:name":"Rony Rogiest",
    "wof:placetype":"venue"
},
  "geometry": {"coordinates":[3.1348540783,51.1470718384],"type":"Point"}
}