{
  "type": "Feature",
  "properties": {
    "addr:full":"Trieststraat 39 Assenede Oost-Vlaanderen 9960",
    "addr:housenumber":"39",
    "addr:postcode":"9960",
    "addr:street":"Trieststraat",
    "iso:country":"BE",
    "sg:address":"Trieststraat 39",
    "sg:city":"Assenede",
    "sg:classifiers":[
        {
            "category":"Personal",
            "subcategory":"Beauty Salon",
            "type":"Services"
        }
    ],
    "sg:phone":"+32 9 343 03 55",
    "sg:postcode":"9960",
    "sg:province":"Oost-Vlaanderen",
    "sg:tags":[
        "lady",
        "-",
        "hairdressing"
    ],
    "wof:name":"Hairflying",
    "wof:placetype":"venue"
},
  "geometry": {"coordinates":[3.7515931129,51.2221908569],"type":"Point"}
}