{
  "type": "Feature",
  "properties": {
    "iso:country":"BE",
    "sg:address":"Rue Des Combattants 40",
    "sg:city":"La Hulpe",
    "sg:classifiers":[
        {
            "category":"Bakery",
            "type":"Food & Drink"
        }
    ],
    "sg:phone":"+32 2 653 68 58",
    "sg:postcode":"1310",
    "sg:province":"Brabant Wallon",
    "sg:tags":[
        "confectioner",
        "baker"
    ],
    "wof:name":"Lonbois J-l",
    "wof:placetype":"venue"
},
  "geometry": {"coordinates":[4.4890217781,50.7315711975],"type":"Point"}
}