{
  "type": "Feature",
  "properties": {
    "iso:country":"BE",
    "sg:address":"Leuvensebaan 38",
    "sg:city":"Holsbeek",
    "sg:classifiers":[
        {
            "category":"Banks & Credit Unions",
            "subcategory":"Investment Brokerage",
            "type":"Services"
        }
    ],
    "sg:phone":"+32 16 44 52 40",
    "sg:postcode":"3220",
    "sg:province":"Vlaams-Brabant",
    "sg:tags":[
        "printing",
        "-"
    ],
    "wof:name":"Beullens Bvba",
    "wof:placetype":"venue"
},
  "geometry": {"coordinates":[4.7496061325,50.9177589417],"type":"Point"}
}