{
  "type": "Feature",
  "properties": {
    "addr:full":"Markt 4 Tessenderlo Limburg 3980",
    "addr:housenumber":"4",
    "addr:postcode":"3980",
    "addr:street":"Markt",
    "iso:country":"BE",
    "sg:address":"Markt 4",
    "sg:city":"Tessenderlo",
    "sg:orig_category":"Diverse kredietdiensten",
    "sg:postcode":"3980",
    "sg:province":"Limburg",
    "wof:name":"Bancontact-mister Cash",
    "wof:placetype":"venue"
},
  "geometry": {"coordinates":[5.0890049934,51.0672531128],"type":"Point"}
}