{
  "type": "Feature",
  "properties": {
    "addr:full":"Place Cur\u00c9 Borremans 3 Lessines Hainaut 7861",
    "addr:housenumber":"3",
    "addr:postcode":"7861",
    "addr:street":"Place Cure\u0301 Borremans;Hainaut",
    "iso:country":"BE",
    "sg:address":"Place Cur\u00c9 Borremans 3",
    "sg:city":"Lessines",
    "sg:orig_category":"Enseignement maternel and primaire",
    "sg:phone":"+32 68 33 74 02",
    "sg:postcode":"7861",
    "sg:province":"Hainaut",
    "wof:name":"Ecole Matern. Communale",
    "wof:placetype":"venue"
},
  "geometry": {"coordinates":[3.8180809021,50.6847496033],"type":"Point"}
}