{
  "type": "Feature",
  "properties": {
    "addr:full":"Hugo Verrieststraat 8 Meulebeke West-Vlaanderen 8760",
    "addr:housenumber":"8",
    "addr:postcode":"8760",
    "addr:street":"Hugo Verrieststraat",
    "iso:country":"BE",
    "sg:address":"Hugo Verrieststraat 8",
    "sg:city":"Meulebeke",
    "sg:classifiers":[
        {
            "category":"Professional",
            "subcategory":"Computer Services",
            "type":"Services"
        }
    ],
    "sg:phone":"+32 51 48 66 57",
    "sg:postcode":"8760",
    "sg:province":"West-Vlaanderen",
    "sg:tags":[
        "-",
        "processing",
        "data",
        "software"
    ],
    "wof:name":"Jsoft",
    "wof:placetype":"venue"
},
  "geometry": {"coordinates":[3.2823569775,50.945400238],"type":"Point"}
}