{
  "type": "Feature",
  "properties": {
    "addr:full":"Ninovestraat 110 Haaltert Oost-Vlaanderen 9450",
    "addr:housenumber":"110",
    "addr:postcode":"9450",
    "addr:street":"Ninovestraat",
    "iso:country":"BE",
    "sg:address":"Ninovestraat 110",
    "sg:city":"Haaltert",
    "sg:orig_category":"Plomberie, chauffage and installations sanitaires",
    "sg:phone":"+32 53 83 55 32",
    "sg:postcode":"9450",
    "sg:province":"Oost-Vlaanderen",
    "wof:name":"Fa. Alitech",
    "wof:placetype":"venue"
},
  "geometry": {"coordinates":[4.0250248909,50.900352478],"type":"Point"}
}