{
  "type": "Feature",
  "properties": {
    "addr:full":"Rue Thiot 100 Charleroi Hainaut 6060",
    "addr:housenumber":"100",
    "addr:postcode":"6060",
    "addr:street":"Rue Thiot;Hainaut",
    "iso:country":"BE",
    "sg:address":"Rue Thiot 100",
    "sg:city":"Charleroi",
    "sg:classifiers":[
        {
            "category":"Recreation",
            "type":"Entertainment"
        }
    ],
    "sg:phone":"+32 71 41 07 55",
    "sg:postcode":"6060",
    "sg:province":"Hainaut",
    "sg:tags":[
        "diver",
        "amusement"
    ],
    "wof:name":"Heigth Energy",
    "wof:placetype":"venue"
},
  "geometry": {"coordinates":[4.4880981445,50.4251937866],"type":"Point"}
}