{
  "type": "Feature",
  "properties": {
    "addr:full":"Sint-niklaasstraat 27 Westerlo (zoerle-parwijs) Antwerpen 2260",
    "addr:housenumber":"27",
    "addr:postcode":"2260",
    "addr:street":"Sint-Niklaasstraat",
    "iso:country":"BE",
    "sg:address":"Sint-niklaasstraat 27",
    "sg:city":"Westerlo (zoerle-parwijs)",
    "sg:classifiers":[
        {
            "category":"Personal",
            "subcategory":"Beauty Salon",
            "type":"Services"
        }
    ],
    "sg:phone":"+32 14 54 90 91",
    "sg:postcode":"2260",
    "sg:province":"Antwerpen",
    "sg:tags":[
        "lady",
        "-",
        "hairdressing"
    ],
    "wof:name":"Heidi",
    "wof:placetype":"venue"
},
  "geometry": {"coordinates":[4.9112768173,51.0883636475],"type":"Point"}
}