{
  "type": "Feature",
  "properties": {
    "iso:country":"BE",
    "sg:address":"Chauss\u00e9e De Bruxelles 326 Box 13",
    "sg:city":"Charleroi (lodelinsart)",
    "sg:classifiers":[
        {
            "category":"Professional",
            "subcategory":"Art Services",
            "type":"Services"
        }
    ],
    "sg:phone":"+32 71 30 44 24",
    "sg:postcode":"6042",
    "sg:province":"Hainaut",
    "sg:tags":[
        "installation",
        "cafe",
        "-",
        "equipment"
    ],
    "wof:name":"Equip Horeca A Zambon",
    "wof:placetype":"venue"
},
  "geometry": {"coordinates":[4.4350218773,50.4479560852],"type":"Point"}
}