{
  "type": "Feature",
  "properties": {
    "iso:country":"BE",
    "sg:address":"Hubensstraat 8",
    "sg:city":"Kinrooi",
    "sg:orig_category":"Eleveurs and marchands de porcs. Eleveurs de bovins",
    "sg:phone":"+32 89 70 23 37",
    "sg:postcode":"3640",
    "sg:province":"Limburg",
    "wof:name":"Grispen Lambert & Willy",
    "wof:placetype":"venue"
},
  "geometry": {"coordinates":[5.767677784,51.1527137756],"type":"Point"}
}