{
  "type": "Feature",
  "properties": {
    "iso:country":"BE",
    "sg:address":"Bosquetstraat 14",
    "sg:city":"Sint-gillis/saint-gilles",
    "sg:orig_category":"Advocaten and juridische adviseurs",
    "sg:phone":"+32 2 538 06 18",
    "sg:postcode":"1060",
    "sg:province":"Bruxelles-Capitale",
    "wof:name":"P. Landrien",
    "wof:placetype":"venue"
},
  "geometry": {"coordinates":[4.3556089401,50.8330955505],"type":"Point"}
}