{
  "type": "Feature",
  "properties": {
    "addr:full":"Groenlaan 44 Tervuren Vlaams-Brabant 3080",
    "addr:housenumber":"44",
    "addr:postcode":"3080",
    "addr:street":"Groenlaan",
    "iso:country":"BE",
    "sg:address":"Groenlaan 44",
    "sg:city":"Tervuren",
    "sg:classifiers":[
        {
            "category":"Arena",
            "subcategory":"Sports Club",
            "type":"Entertainment"
        }
    ],
    "sg:phone":"+32 2 767 36 07",
    "sg:postcode":"3080",
    "sg:province":"Vlaams-Brabant",
    "sg:tags":[
        "de"
    ],
    "wof:name":"Davis T.c.",
    "wof:placetype":"venue"
},
  "geometry": {"coordinates":[4.551680088,50.8557090759],"type":"Point"}
}