{
  "type": "Feature",
  "properties": {
    "addr:full":"Kliniekstraat 42 Tienen Vlaams-Brabant 3300",
    "addr:housenumber":"42",
    "addr:postcode":"3300",
    "addr:street":"Kliniekstraat",
    "iso:country":"BE",
    "sg:address":"Kliniekstraat 42",
    "sg:city":"Tienen",
    "sg:classifiers":[
        {
            "category":"Real Estate",
            "subcategory":"Surveying",
            "type":"Services"
        }
    ],
    "sg:phone":"+32 16 81 73 81",
    "sg:postcode":"3300",
    "sg:province":"Vlaams-Brabant",
    "sg:tags":[
        "surveyor",
        "land"
    ],
    "wof:name":"Thiunas Invest Nv",
    "wof:placetype":"venue"
},
  "geometry": {"coordinates":[4.930970192,50.811252594],"type":"Point"}
}