{
  "type": "Feature",
  "properties": {
    "iso:country":"BE",
    "sg:address":"Celestijnenlaan 37b41",
    "sg:city":"Leuven",
    "sg:orig_category":"M\u00e9decins and sp\u00e9cialistes",
    "sg:phone":"+32 16 23 18 23",
    "sg:postcode":"3001",
    "sg:province":"Vlaams-Brabant",
    "wof:name":"Sieglinde Blondeel",
    "wof:placetype":"venue"
},
  "geometry": {"coordinates":[4.6760458946,50.8706016541],"type":"Point"}
}