{
  "type": "Feature",
  "properties": {
    "iso:country":"BE",
    "sg:address":"Oude Mechelsebaan 284",
    "sg:city":"Aarschot",
    "sg:orig_category":"GROENTEN AND FRUIT Groenten and fruit Gh",
    "sg:phone":"+32 16 56 77 30",
    "sg:postcode":"3201",
    "sg:province":"Vlaams-Brabant",
    "wof:name":"Luc Van Den Brande",
    "wof:placetype":"venue"
},
  "geometry": {"coordinates":[4.8531780243,51.0081596375],"type":"Point"}
}