{
  "type": "Feature",
  "properties": {
    "addr:full":"Rue Des Ardennes 216 Beauraing Namur 5570",
    "addr:housenumber":"216",
    "addr:postcode":"5570",
    "addr:street":"Rue Des Ardennes",
    "iso:country":"BE",
    "sg:address":"Rue Des Ardennes 216",
    "sg:city":"Beauraing",
    "sg:orig_category":"Brood, gebak and snoepgoed",
    "sg:phone":"+32 82 71 11 87",
    "sg:postcode":"5570",
    "sg:province":"Namur",
    "wof:name":"Boulangerie Antoine",
    "wof:placetype":"venue"
},
  "geometry": {"coordinates":[4.9469399452,50.1016616821],"type":"Point"}
}