{
  "type": "Feature",
  "properties": {
    "iso:country":"BE",
    "sg:address":"Van Eycklaan 95c",
    "sg:city":"Maaseik",
    "sg:classifiers":[
        {
            "category":"Professional",
            "subcategory":"Lawyer & Legal Services",
            "type":"Services"
        }
    ],
    "sg:phone":"+32 89 56 72 61",
    "sg:postcode":"3680",
    "sg:province":"Limburg",
    "wof:name":"Van Kerckhoven L",
    "wof:placetype":"venue"
},
  "geometry": {"coordinates":[5.7844920158,51.0988044739],"type":"Point"}
}