{
  "type": "Feature",
  "properties": {
    "addr:full":"Rue De L'ath\u00c9n\u00c9e Royal 75 Sint-lambrechts-woluwe/woluwe-saint-lambert Bruxelles-Capitale 1200",
    "addr:housenumber":"75",
    "addr:postcode":"1200",
    "addr:street":"Rue De L'Athe;Royal",
    "iso:country":"BE",
    "sg:address":"Rue De L'ath\u00c9n\u00c9e Royal 75",
    "sg:city":"Sint-lambrechts-woluwe/woluwe-saint-lambert",
    "sg:orig_category":"Activit\u00e9s d\u00b4action sociale sans h\u00e9bergement",
    "sg:phone":"+32 2 762 87 27",
    "sg:postcode":"1200",
    "sg:province":"Bruxelles-Capitale",
    "wof:name":"Centre Commun. Fran\u00c7aise",
    "wof:placetype":"venue"
},
  "geometry": {"coordinates":[4.4388599396,50.8501777649],"type":"Point"}
}