{
  "type": "Feature",
  "properties": {
    "addr:full":"Rue Auguste Lambiotte 942 Bruxelles (schaerbeek) Bruxelles-Capitale 1030",
    "addr:housenumber":"942",
    "addr:postcode":"1030",
    "addr:street":"Rue Auguste Lambiotte",
    "iso:country":"BE",
    "sg:address":"Rue Auguste Lambiotte 942",
    "sg:city":"Bruxelles (schaerbeek)",
    "sg:classifiers":[
        {
            "category":"Building & Trades",
            "subcategory":"Plumbing",
            "type":"Services"
        }
    ],
    "sg:phone":"+32 2 779 82 26",
    "sg:postcode":"1030",
    "sg:province":"Bruxelles-Capitale",
    "sg:tags":[
        "contractor"
    ],
    "wof:name":"Jamsin G",
    "wof:placetype":"venue"
},
  "geometry": {"coordinates":[4.3913898468,50.8533210754],"type":"Point"}
}