{
  "type": "Feature",
  "properties": {
    "addr:full":"Rue De Renory 55 Li\u00e8ge 1 (angleur) Li\u00e8ge 4031",
    "addr:housenumber":"55;1",
    "addr:postcode":"4031",
    "addr:street":"Rue De Renory",
    "iso:country":"BE",
    "sg:address":"Rue De Renory 55",
    "sg:city":"Li\u00e8ge 1 (angleur)",
    "sg:classifiers":[
        {
            "category":"Shopping",
            "subcategory":"Books",
            "type":"Retail Goods"
        }
    ],
    "sg:phone":"+32 4 342 70 17",
    "sg:postcode":"4031",
    "sg:province":"Li\u00e8ge",
    "sg:tags":[
        "bookseller"
    ],
    "wof:name":"Laurent (chez)",
    "wof:placetype":"venue"
},
  "geometry": {"coordinates":[5.5798749924,50.614364624],"type":"Point"}
}