{
  "type": "Feature",
  "properties": {
    "addr:full":"Kapelstraat 3 Kortenaken Vlaams-Brabant 3470",
    "addr:housenumber":"3",
    "addr:postcode":"3470",
    "addr:street":"Kapelstraat",
    "iso:country":"BE",
    "sg:address":"Kapelstraat 3",
    "sg:city":"Kortenaken",
    "sg:orig_category":"Producteurs de fruits",
    "sg:phone":"+32 11 58 80 70",
    "sg:postcode":"3470",
    "sg:province":"Vlaams-Brabant",
    "wof:name":"Paul Vander Velpen",
    "wof:placetype":"venue"
},
  "geometry": {"coordinates":[5.0406560898,50.8605384827],"type":"Point"}
}