{
  "type": "Feature",
  "properties": {
    "iso:country":"BE",
    "sg:address":"E Vlieberghlaan 8",
    "sg:city":"Overpelt",
    "sg:orig_category":"Verhuisdiensten",
    "sg:phone":"+32 11 64 15 20",
    "sg:postcode":"3900",
    "sg:province":"Limburg",
    "wof:name":"Alders",
    "wof:placetype":"venue"
},
  "geometry": {"coordinates":[5.381248951,51.225933075],"type":"Point"}
}