{
  "type": "Feature",
  "properties": {
    "addr:full":"Rue De La Station 32c Florenville Luxembourg 6820",
    "addr:housenumber":"32c",
    "addr:postcode":"6820",
    "addr:street":"Rue De La Station",
    "iso:country":"BE",
    "sg:address":"Rue De La Station 32c",
    "sg:city":"Florenville",
    "sg:classifiers":[
        {
            "category":"Retail",
            "subcategory":"Auto Repair",
            "type":"Services"
        }
    ],
    "sg:phone":"+32 61 31 10 55",
    "sg:postcode":"6820",
    "sg:province":"Luxembourg",
    "sg:tags":[
        "garage"
    ],
    "wof:name":"Garage Mauxhin Et Fils",
    "wof:placetype":"venue"
},
  "geometry": {"coordinates":[5.3292560577,49.7043037415],"type":"Point"}
}