{
  "type": "Feature",
  "properties": {
    "addr:full":"Reepstraat 80 Sint-gillis-waas Oost-Vlaanderen 9170",
    "addr:housenumber":"80",
    "addr:postcode":"9170",
    "addr:street":"Reepstraat",
    "iso:country":"BE",
    "sg:address":"Reepstraat 80",
    "sg:city":"Sint-gillis-waas",
    "sg:classifiers":[
        {
            "category":"Health Services",
            "subcategory":"Health Practitioner",
            "type":"Services"
        }
    ],
    "sg:phone":"+32 3 770 52 79",
    "sg:postcode":"9170",
    "sg:province":"Oost-Vlaanderen",
    "sg:tags":[
        "physiotherapist"
    ],
    "wof:name":"De Vos M",
    "wof:placetype":"venue"
},
  "geometry": {"coordinates":[4.1096920967,51.2263641357],"type":"Point"}
}