{
  "type": "Feature",
  "properties": {
    "iso:country":"BE",
    "sg:address":"Muizelstraat 49",
    "sg:city":"Gent",
    "sg:orig_category":"Reclamebureaus",
    "sg:phone":"+32 9 251 46 89",
    "sg:postcode":"9041",
    "sg:province":"Oost-Vlaanderen",
    "wof:name":"Gh Projects",
    "wof:placetype":"venue"
},
  "geometry": {"coordinates":[3.7752680779,51.0936546326],"type":"Point"}
}