{
  "type": "Feature",
  "properties": {
    "iso:country":"BE",
    "sg:address":"Gustave De Stuersstraat 8",
    "sg:city":"Ieper",
    "sg:orig_category":"Advocaten and juridische adviseurs",
    "sg:phone":"+32 57 20 01 13",
    "sg:postcode":"8900",
    "sg:province":"West-Vlaanderen",
    "wof:name":"J. Van Der Mersch",
    "wof:placetype":"venue"
},
  "geometry": {"coordinates":[2.8807458878,50.8501434326],"type":"Point"}
}