{
  "type": "Feature",
  "properties": {
    "iso:country":"BE",
    "sg:address":"Kazernestraat 32",
    "sg:city":"Tielt",
    "sg:orig_category":"Eleveurs de bovins",
    "sg:phone":"+32 51 63 37 77",
    "sg:postcode":"8700",
    "sg:province":"West-Vlaanderen",
    "wof:name":"Roland Allaert",
    "wof:placetype":"venue"
},
  "geometry": {"coordinates":[3.4365119934,51.0125083923],"type":"Point"}
}