{
  "type": "Feature",
  "properties": {
    "iso:country":"BE",
    "sg:address":"Geelsebaan 19",
    "sg:city":"Kasterlee",
    "sg:classifiers":[
        {
            "category":"Fast Food",
            "type":"Food & Drink"
        }
    ],
    "sg:phone":"+32 14 85 01 97",
    "sg:postcode":"2460",
    "sg:province":"Antwerpen",
    "sg:tags":[
        "meeneem",
        "restaurant"
    ],
    "wof:name":"\u00b4t Beukenhof",
    "wof:placetype":"venue"
},
  "geometry": {"coordinates":[4.9685268402,51.2391700745],"type":"Point"}
}