{
  "type": "Feature",
  "properties": {
    "iso:country":"BE",
    "sg:address":"Rue De La Ville 8",
    "sg:city":"Crisn\u00e9e",
    "sg:classifiers":[
        {
            "category":"Professional",
            "subcategory":"Art Services",
            "type":"Services"
        }
    ],
    "sg:phone":"+32 19 67 74 56",
    "sg:postcode":"4367",
    "sg:province":"Li\u00e8ge",
    "sg:tags":[
        "work",
        "foundry"
    ],
    "wof:name":"Francart",
    "wof:placetype":"venue"
},
  "geometry": {"coordinates":[5.3963909149,50.7150535583],"type":"Point"}
}