{
  "type": "Feature",
  "properties": {
    "addr:full":"Zandvoort 1 Antwerpen Antwerpen 2030",
    "addr:housenumber":"1",
    "addr:postcode":"2030",
    "addr:street":"Zandvoort",
    "iso:country":"BE",
    "sg:address":"Zandvoort 1",
    "sg:city":"Antwerpen",
    "sg:orig_category":"Goederenvervoer over de weg",
    "sg:phone":"+32 3 541 31 86",
    "sg:postcode":"2030",
    "sg:province":"Antwerpen",
    "wof:name":"Vermeiren",
    "wof:placetype":"venue"
},
  "geometry": {"coordinates":[4.3590898514,51.2744407654],"type":"Point"}
}