{
  "type": "Feature",
  "properties": {
    "iso:country":"BE",
    "sg:address":"Geraardsbergsestraat 54",
    "sg:city":"Ninove",
    "sg:classifiers":[
        {
            "category":"Health Services",
            "subcategory":"Dentist",
            "type":"Services"
        }
    ],
    "sg:phone":"+32 54 32 40 53",
    "sg:postcode":"9400",
    "sg:province":"Oost-Vlaanderen",
    "wof:name":"Beele Piet",
    "wof:placetype":"venue"
},
  "geometry": {"coordinates":[4.0171098709,50.8363990784],"type":"Point"}
}