{
  "type": "Feature",
  "properties": {
    "iso:country":"BE",
    "sg:address":"Kruipuit 48ba",
    "sg:city":"Maldegem",
    "sg:orig_category":"Jardinage",
    "sg:phone":"+32 9 378 39 03",
    "sg:postcode":"9991",
    "sg:province":"Oost-Vlaanderen",
    "wof:name":"Fa. Peters P.",
    "wof:placetype":"venue"
},
  "geometry": {"coordinates":[3.5161399841,51.1567268372],"type":"Point"}
}