{
  "type": "Feature",
  "properties": {
    "iso:country":"BE",
    "sg:address":"Terbankstraat 63",
    "sg:city":"Haacht",
    "sg:orig_category":"Producteurs de l\u00e9gumes",
    "sg:phone":"+32 16 20 20 92",
    "sg:postcode":"3150",
    "sg:province":"Vlaams-Brabant",
    "wof:name":"August Gille",
    "wof:placetype":"venue"
},
  "geometry": {"coordinates":[4.6641969681,50.9297599792],"type":"Point"}
}