{
  "type": "Feature",
  "properties": {
    "addr:full":"Fazantenstraat 10 Beerse Antwerpen 2340",
    "addr:housenumber":"10",
    "addr:postcode":"2340",
    "addr:street":"Fazantenstraat",
    "iso:country":"BE",
    "sg:address":"Fazantenstraat 10",
    "sg:city":"Beerse",
    "sg:orig_category":"Agences d'exp\u00e9dition",
    "sg:phone":"+32 3 311 77 53",
    "sg:postcode":"2340",
    "sg:province":"Antwerpen",
    "wof:name":"C.f.f.i.",
    "wof:placetype":"venue"
},
  "geometry": {"coordinates":[4.7827539444,51.3160667419],"type":"Point"}
}