{
  "type": "Feature",
  "properties": {
    "addr:full":"Ruitersstraat 1 Oudenaarde (mater) Oost-Vlaanderen 9700",
    "addr:housenumber":"1",
    "addr:postcode":"9700",
    "addr:street":"Ruitersstraat;Mater Oost-Vlaanderen",
    "iso:country":"BE",
    "sg:address":"Ruitersstraat 1",
    "sg:city":"Oudenaarde (mater)",
    "sg:classifiers":[
        {
            "category":"Manufacturing",
            "subcategory":"Textiles",
            "type":"Manufacturing & Wholesale Goods"
        }
    ],
    "sg:phone":"+32 55 30 14 46",
    "sg:postcode":"9700",
    "sg:province":"Oost-Vlaanderen",
    "sg:tags":[
        "raw",
        "material",
        "-"
    ],
    "wof:name":"Internat. Textile Services Bvba",
    "wof:placetype":"venue"
},
  "geometry": {"coordinates":[3.6462779045,50.8435173035],"type":"Point"}
}