{
  "type": "Feature",
  "properties": {
    "iso:country":"BE",
    "sg:address":"Place De La F\u00e9ch\u00e8re 27",
    "sg:city":"Chastre (chastre-villeroux-blanmont)",
    "sg:classifiers":[
        {
            "category":"Health Services",
            "subcategory":"Doctor",
            "type":"Services"
        }
    ],
    "sg:phone":"+32 10 65 58 23",
    "sg:postcode":"1450",
    "sg:province":"Brabant Wallon",
    "sg:tags":[
        "medicinephysicians",
        "surgeon"
    ],
    "wof:name":"Fran\u00e7ois Marie",
    "wof:placetype":"venue"
},
  "geometry": {"coordinates":[4.6431450844,50.6232948303],"type":"Point"}
}