{
  "type": "Feature",
  "properties": {
    "addr:full":"Rue Des Champs 8 Ecaussinnes (marche-lez-ecaussines) Hainaut 7190",
    "addr:housenumber":"8",
    "addr:postcode":"7190",
    "addr:street":"Rue Des Champs;Marche-Lez-Ecaussines Hainaut",
    "iso:country":"BE",
    "sg:address":"Rue Des Champs 8",
    "sg:city":"Ecaussinnes (marche-lez-ecaussines)",
    "sg:classifiers":[
        {
            "category":"Professional",
            "subcategory":"Lawyer & Legal Services",
            "type":"Services"
        }
    ],
    "sg:phone":"+32 67 44 45 68",
    "sg:postcode":"7190",
    "sg:province":"Hainaut",
    "wof:name":"Soetaert Emmanuelle",
    "wof:placetype":"venue"
},
  "geometry": {"coordinates":[4.1913847923,50.5478515625],"type":"Point"}
}