{
  "type": "Feature",
  "properties": {
    "iso:country":"BE",
    "sg:address":"Diestsesteenweg 490",
    "sg:city":"Aarschot",
    "sg:classifiers":[
        {
            "category":"Food & Beverages",
            "subcategory":"Fruits & Vegetables",
            "type":"Retail Goods"
        }
    ],
    "sg:phone":"+32 16 50 24 16",
    "sg:postcode":"3202",
    "sg:province":"Vlaams-Brabant",
    "sg:tags":[
        "l\u00e9gumes",
        "gr"
    ],
    "wof:name":"Van De Laer - Swinkels",
    "wof:placetype":"venue"
},
  "geometry": {"coordinates":[4.9049601555,50.9751701355],"type":"Point"}
}