{
  "type": "Feature",
  "properties": {
    "addr:full":"Rue De Tongres 216 Oupeye (haccourt) Li\u00e8ge 4684",
    "addr:housenumber":"216",
    "addr:postcode":"4684",
    "addr:street":"Rue De Tongres",
    "iso:country":"BE",
    "sg:address":"Rue De Tongres 216",
    "sg:city":"Oupeye (haccourt)",
    "sg:classifiers":[
        {
            "category":"Banks & Credit Unions",
            "subcategory":"Investment Brokerage",
            "type":"Services"
        }
    ],
    "sg:phone":"+32 4 379 31 45",
    "sg:postcode":"4684",
    "sg:province":"Li\u00e8ge",
    "sg:tags":[
        "repair",
        "-",
        "installation",
        "sanitary",
        "article"
    ],
    "wof:name":"Lemaire J",
    "wof:placetype":"venue"
},
  "geometry": {"coordinates":[5.6607050896,50.7407035828],"type":"Point"}
}