{
  "type": "Feature",
  "properties": {
    "iso:country":"BE",
    "sg:address":"Hospitaalstraat 70",
    "sg:city":"Koersel",
    "sg:classifiers":[
        {
            "category":"Restaurant",
            "type":"Food & Drink"
        }
    ],
    "sg:phone":"+32 11 42 51 21",
    "sg:postcode":"3582",
    "sg:province":"Limburg",
    "wof:name":"\u00b4t Hoeveke",
    "wof:placetype":"venue"
},
  "geometry": {"coordinates":[5.2159042358,51.0663070679],"type":"Point"}
}