{
  "type": "Feature",
  "properties": {
    "iso:country":"BE",
    "sg:address":"Breughelstraat 31",
    "sg:city":"Antwerpen",
    "sg:classifiers":[
        {
            "category":"Social Services",
            "type":"Services"
        }
    ],
    "sg:phone":"+32 3 281 15 05",
    "sg:postcode":"2018",
    "sg:province":"Antwerpen",
    "wof:name":"Hand In Hand/vaka",
    "wof:placetype":"venue"
},
  "geometry": {"coordinates":[4.4148859978,51.2077903748],"type":"Point"}
}