{
  "type": "Feature",
  "properties": {
    "iso:country":"BE",
    "sg:address":"Sint-hubrechtsplein 1",
    "sg:city":"Ledegem",
    "sg:orig_category":"Pharmaciens",
    "sg:phone":"+32 56 50 00 57",
    "sg:postcode":"8880",
    "sg:province":"West-Vlaanderen",
    "wof:name":"W. Boonefaes",
    "wof:placetype":"venue"
},
  "geometry": {"coordinates":[3.1801290512,50.8760795593],"type":"Point"}
}