{
  "type": "Feature",
  "properties": {
    "addr:full":"Rue Des Ch\u00canes 2a Gembloux Namur 5031",
    "addr:housenumber":"2a",
    "addr:postcode":"5031",
    "addr:street":"Rue Des Che\u0302Nes;Namur",
    "iso:country":"BE",
    "sg:address":"Rue Des Ch\u00canes 2a",
    "sg:city":"Gembloux",
    "sg:orig_category":"Ecoles de pilotage de bateaux and d\u00b4avions",
    "sg:phone":"+32 81 64 03 49",
    "sg:postcode":"5031",
    "sg:province":"Namur",
    "wof:name":"Jonair Service",
    "wof:placetype":"venue"
},
  "geometry": {"coordinates":[4.7766261101,50.5881080627],"type":"Point"}
}