{
  "type": "Feature",
  "properties": {
    "iso:country":"BE",
    "sg:address":"Tertzweildreef 21",
    "sg:city":"Merelbeke",
    "sg:classifiers":[
        {
            "category":"Professional",
            "type":"Services"
        }
    ],
    "sg:phone":"+32 9 211 08 06",
    "sg:postcode":"9820",
    "sg:province":"Oost-Vlaanderen",
    "sg:tags":[
        "surveyor",
        "-",
        "valuer"
    ],
    "wof:name":"Wermenbol & Partners Gent",
    "wof:placetype":"venue"
},
  "geometry": {"coordinates":[3.7646570206,51.0129318237],"type":"Point"}
}