{
  "type": "Feature",
  "properties": {
    "addr:full":"Paanderstraat 3 Meulebeke West-Vlaanderen 8760",
    "addr:housenumber":"3",
    "addr:postcode":"8760",
    "addr:street":"Paanderstraat",
    "iso:country":"BE",
    "sg:address":"Paanderstraat 3",
    "sg:city":"Meulebeke",
    "sg:classifiers":[
        {
            "category":"Home & Garden",
            "subcategory":"Furniture",
            "type":"Retail Goods"
        }
    ],
    "sg:phone":"+32 51 48 90 02",
    "sg:postcode":"8760",
    "sg:province":"West-Vlaanderen",
    "sg:tags":[
        "small",
        "item",
        "-"
    ],
    "wof:name":"Deva Desimpelaere",
    "wof:placetype":"venue"
},
  "geometry": {"coordinates":[3.2982749939,50.9413337708],"type":"Point"}
}