{
  "type": "Feature",
  "properties": {
    "iso:country":"BE",
    "sg:address":"Achterlo 8",
    "sg:city":"Ranst",
    "sg:orig_category":"Groententeelt Pluimveekwekers Varkenskwekers",
    "sg:phone":"+32 3 485 57 86",
    "sg:postcode":"2520",
    "sg:province":"Antwerpen",
    "wof:name":"Leo Goris",
    "wof:placetype":"venue"
},
  "geometry": {"coordinates":[4.5827717781,51.1835289001],"type":"Point"}
}