{
  "type": "Feature",
  "properties": {
    "addr:full":"'s Hertogendijk 37 Stabroek Antwerpen 2940",
    "addr:housenumber":"37",
    "addr:postcode":"2940",
    "addr:street":"' S Hertogendijk",
    "iso:country":"BE",
    "sg:address":"'s Hertogendijk 37",
    "sg:city":"Stabroek",
    "sg:classifiers":[
        {
            "category":"Building & Trades",
            "subcategory":"Landscaping Services",
            "type":"Services"
        }
    ],
    "sg:phone":"+32 3 568 18 20",
    "sg:postcode":"2940",
    "sg:province":"Antwerpen",
    "sg:tags":[
        "gardening",
        "garden",
        "maintenance"
    ],
    "wof:name":"Galanthus",
    "wof:placetype":"venue"
},
  "geometry": {"coordinates":[4.377822876,51.3236732483],"type":"Point"}
}