{
  "type": "Feature",
  "properties": {
    "addr:full":"Nederstraat 50 Oudenaarde Oost-Vlaanderen 9700",
    "addr:housenumber":"50",
    "addr:postcode":"9700",
    "addr:street":"Nederstraat",
    "iso:country":"BE",
    "sg:address":"Nederstraat 50",
    "sg:city":"Oudenaarde",
    "sg:classifiers":[
        {
            "category":"Shopping",
            "subcategory":"Jewelry",
            "type":"Retail Goods"
        }
    ],
    "sg:phone":"+32 477 62 56 49",
    "sg:postcode":"9700",
    "sg:province":"Oost-Vlaanderen",
    "sg:tags":[
        "-",
        "imitation"
    ],
    "wof:name":"Fancy",
    "wof:placetype":"venue"
},
  "geometry": {"coordinates":[3.6027588844,50.8451576233],"type":"Point"}
}