{
  "type": "Feature",
  "properties": {
    "addr:full":"Grote Baan 80 Lovendegem Oost-Vlaanderen 9920",
    "addr:housenumber":"80",
    "addr:postcode":"9920",
    "addr:street":"Grote Baan",
    "iso:country":"BE",
    "sg:address":"Grote Baan 80",
    "sg:city":"Lovendegem",
    "sg:orig_category":"Newspapers, magazines, periodicals - Distribution",
    "sg:phone":"+32 9 372 77 21",
    "sg:postcode":"9920",
    "sg:province":"Oost-Vlaanderen",
    "wof:name":"Kubus 2000",
    "wof:placetype":"venue"
},
  "geometry": {"coordinates":[3.6365950108,51.0990943909],"type":"Point"}
}