{
  "type": "Feature",
  "properties": {
    "addr:full":"Boomstraat 16 Bornem Antwerpen 2880",
    "addr:housenumber":"16",
    "addr:postcode":"2880",
    "addr:street":"Boomstraat",
    "iso:country":"BE",
    "sg:address":"Boomstraat 16",
    "sg:city":"Bornem",
    "sg:orig_category":"Slagers",
    "sg:phone":"+32 3 889 73 93",
    "sg:postcode":"2880",
    "sg:province":"Antwerpen",
    "wof:name":"De Clippel",
    "wof:placetype":"venue"
},
  "geometry": {"coordinates":[4.2338762283,51.099357605],"type":"Point"}
}