{
  "type": "Feature",
  "properties": {
    "addr:full":"Jan-baptist Guinardstraat 34 Gent Oost-Vlaanderen 9000",
    "addr:housenumber":"34",
    "addr:postcode":"9000",
    "addr:street":"Jan-Baptist Guinardstraat;Oost-Vlaanderen",
    "iso:country":"BE",
    "sg:address":"Jan-baptist Guinardstraat 34",
    "sg:city":"Gent",
    "sg:classifiers":[
        {
            "category":"Social Services",
            "type":"Services"
        }
    ],
    "sg:phone":"+32 9 225 06 52",
    "sg:postcode":"9000",
    "sg:province":"Oost-Vlaanderen",
    "wof:name":"Centrum Voor Seksuele Voorlichting",
    "wof:placetype":"venue"
},
  "geometry": {"coordinates":[3.7246320248,51.0464286804],"type":"Point"}
}