{
  "type": "Feature",
  "properties": {
    "addr:full":"Square L\u00c9opold 15 Namur Namur 5000",
    "addr:housenumber":"15",
    "addr:postcode":"5000",
    "addr:street":"Square Le\u0301Opold",
    "iso:country":"BE",
    "sg:address":"Square L\u00c9opold 15",
    "sg:city":"Namur",
    "sg:orig_category":"Opticiens",
    "sg:phone":"+32 81 22 92 29",
    "sg:postcode":"5000",
    "sg:province":"Namur",
    "wof:name":"Cl. Frippiat",
    "wof:placetype":"venue"
},
  "geometry": {"coordinates":[4.8679070473,50.4683914185],"type":"Point"}
}