{
  "type": "Feature",
  "properties": {
    "addr:full":"Koningin Fabiolastraat 96 Wevelgem West-Vlaanderen 8560",
    "addr:housenumber":"96",
    "addr:postcode":"8560",
    "addr:street":"Koningin Fabiolastraat",
    "iso:country":"BE",
    "sg:address":"Koningin Fabiolastraat 96",
    "sg:city":"Wevelgem",
    "sg:orig_category":"Fleurs and plantes",
    "sg:phone":"+32 56 42 04 20",
    "sg:postcode":"8560",
    "sg:province":"West-Vlaanderen",
    "wof:name":"Huis Oase",
    "wof:placetype":"venue"
},
  "geometry": {"coordinates":[3.2001709938,50.8382644653],"type":"Point"}
}