{
  "type": "Feature",
  "properties": {
    "iso:country":"BE",
    "sg:address":"Varendries 6",
    "sg:city":"Herentals (noorderwijk)",
    "sg:classifiers":[
        {
            "category":"Banks & Credit Unions",
            "subcategory":"Investment Brokerage",
            "type":"Services"
        }
    ],
    "sg:phone":"+32 14 26 25 89",
    "sg:postcode":"2200",
    "sg:province":"Antwerpen",
    "sg:tags":[
        "fence"
    ],
    "wof:name":"Van Doninck J & M",
    "wof:placetype":"venue"
},
  "geometry": {"coordinates":[4.8446111679,51.1446647644],"type":"Point"}
}