{
  "type": "Feature",
  "properties": {
    "iso:country":"BE",
    "sg:address":"Hippolyte Meeuwsstraat 2-6",
    "sg:city":"Wijnegem",
    "sg:classifiers":[
        {
            "category":"Retail",
            "subcategory":"Auto Repair",
            "type":"Services"
        }
    ],
    "sg:phone":"+32 3 353 84 98",
    "sg:postcode":"2110",
    "sg:province":"Antwerpen",
    "sg:tags":[
        "garage"
    ],
    "wof:name":"Helssen Vic Carrosserie",
    "wof:placetype":"venue"
},
  "geometry": {"coordinates":[4.5412898064,51.2278633118],"type":"Point"}
}