{
  "type": "Feature",
  "properties": {
    "addr:full":"Briefdragerstraat 5 Sint-jans-molenbeek/molenbeek-saint-jean Bruxelles-Capitale 1080",
    "addr:housenumber":"5",
    "addr:postcode":"1080",
    "addr:street":"Briefdragerstraat",
    "iso:country":"BE",
    "sg:address":"Briefdragerstraat 5",
    "sg:city":"Sint-jans-molenbeek/molenbeek-saint-jean",
    "sg:orig_category":"Foto-uitrusting Fotografen and fotostudio's",
    "sg:phone":"+32 2 414 28 76",
    "sg:postcode":"1080",
    "sg:province":"Bruxelles-Capitale",
    "wof:name":"Lpm Diffusion",
    "wof:placetype":"venue"
},
  "geometry": {"coordinates":[4.3390870094,50.8557929993],"type":"Point"}
}