{
  "type": "Feature",
  "properties": {
    "iso:country":"BE",
    "sg:address":"Place Reine-astrid 4",
    "sg:city":"Florenville",
    "sg:orig_category":"Slagers",
    "sg:phone":"+32 61 31 41 50",
    "sg:postcode":"6820",
    "sg:province":"Luxembourg",
    "wof:name":"Boucherie Bechoux-dumont",
    "wof:placetype":"venue"
},
  "geometry": {"coordinates":[5.3077130318,49.6981391907],"type":"Point"}
}