{
  "type": "Feature",
  "properties": {
    "iso:country":"BE",
    "sg:address":"Blauwe Steenstraat 10",
    "sg:city":"Dendermonde",
    "sg:classifiers":[
        {
            "category":"Insurance",
            "subcategory":"Insurance Agent",
            "type":"Services"
        }
    ],
    "sg:phone":"+32 52 22 30 25",
    "sg:postcode":"9200",
    "sg:province":"Oost-Vlaanderen",
    "sg:tags":[
        "broker"
    ],
    "wof:name":"Qcs Bvba",
    "wof:placetype":"venue"
},
  "geometry": {"coordinates":[4.1178731918,51.0313148499],"type":"Point"}
}