{
  "type": "Feature",
  "properties": {
    "addr:full":"Kiezelweg 65 Mol Antwerpen 2400",
    "addr:housenumber":"65",
    "addr:postcode":"2400",
    "addr:street":"Kiezelweg",
    "iso:country":"BE",
    "sg:address":"Kiezelweg 65",
    "sg:city":"Mol",
    "sg:classifiers":[
        {
            "category":"Restaurant",
            "type":"Food & Drink"
        }
    ],
    "sg:phone":"+32 14 82 08 18",
    "sg:postcode":"2400",
    "sg:province":"Antwerpen",
    "wof:name":"Dynastie",
    "wof:placetype":"venue"
},
  "geometry": {"coordinates":[5.1824297905,51.2125701904],"type":"Point"}
}