{
  "type": "Feature",
  "properties": {
    "iso:country":"BE",
    "sg:address":"Zeveneken Dorp 56",
    "sg:city":"Lochristi (zeveneken)",
    "sg:orig_category":"Non-Classified Establishments",
    "sg:phone":"+32 9 355 55 18",
    "sg:postcode":"9080",
    "sg:province":"Oost-Vlaanderen",
    "wof:name":"Alderweireldt Bvba",
    "wof:placetype":"venue"
},
  "geometry": {"coordinates":[3.8337640762,51.1020126343],"type":"Point"}
}