{
  "type": "Feature",
  "properties": {
    "addr:full":"Statiestraat 18 Wichelen Oost-Vlaanderen 9260",
    "addr:housenumber":"18",
    "addr:postcode":"9260",
    "addr:street":"Statiestraat",
    "iso:country":"BE",
    "sg:address":"Statiestraat 18",
    "sg:city":"Wichelen",
    "sg:classifiers":[
        {
            "category":"Health Services",
            "subcategory":"Dentist",
            "type":"Services"
        }
    ],
    "sg:phone":"+32 52 42 30 63",
    "sg:postcode":"9260",
    "sg:province":"Oost-Vlaanderen",
    "wof:name":"Eeckhaut Alfons & Koen",
    "wof:placetype":"venue"
},
  "geometry": {"coordinates":[3.9719970226,51.0054397583],"type":"Point"}
}