{
  "type": "Feature",
  "properties": {
    "addr:full":"Avenue De L'atlantique 126b6 Sint-pieters-woluwe/woluwe-saint-pierre Bruxelles-Capitale 1150",
    "addr:housenumber":"126b6",
    "addr:postcode":"1150",
    "addr:street":"Avenue De L'Atlantique;/",
    "iso:country":"BE",
    "sg:address":"Avenue De L'atlantique 126b6",
    "sg:city":"Sint-pieters-woluwe/woluwe-saint-pierre",
    "sg:classifiers":[
        {
            "category":"Insurance",
            "subcategory":"Life Insurance",
            "type":"Services"
        }
    ],
    "sg:phone":"+32 2 763 04 03",
    "sg:postcode":"1150",
    "sg:province":"Bruxelles-Capitale",
    "sg:tags":[
        "assurance"
    ],
    "wof:name":"Burdass",
    "wof:placetype":"venue"
},
  "geometry": {"coordinates":[4.4187240601,50.8311767578],"type":"Point"}
}