{
  "type": "Feature",
  "properties": {
    "iso:country":"BE",
    "sg:address":"Kollegestraat 7b7",
    "sg:city":"Sint-niklaas",
    "sg:orig_category":"Artsen and specialisten",
    "sg:phone":"+32 3 777 14 00",
    "sg:postcode":"9100",
    "sg:province":"Oost-Vlaanderen",
    "wof:name":"Centrum Man,vrouw & Gezin",
    "wof:placetype":"venue"
},
  "geometry": {"coordinates":[4.1402978897,51.1656990051],"type":"Point"}
}