{
  "type": "Feature",
  "properties": {
    "iso:country":"BE",
    "sg:address":"Breendonklaan 3",
    "sg:city":"Bredene",
    "sg:classifiers":[
        {
            "category":"Arena",
            "subcategory":"Sports Club",
            "type":"Entertainment"
        }
    ],
    "sg:phone":"+32 59 32 58 29",
    "sg:postcode":"8450",
    "sg:province":"West-Vlaanderen",
    "sg:tags":[
        "de"
    ],
    "wof:name":"Chin Do Jang Torhout",
    "wof:placetype":"venue"
},
  "geometry": {"coordinates":[2.9634149075,51.2234573364],"type":"Point"}
}