{
  "type": "Feature",
  "properties": {
    "iso:country":"BE",
    "sg:address":"Moerkerkse Steenweg 605",
    "sg:city":"Brugge (sint-kruis)",
    "sg:classifiers":[
        {
            "category":"Shopping",
            "subcategory":"Pets & Pet Supplies",
            "type":"Retail Goods"
        }
    ],
    "sg:phone":"+32 50 36 16 95",
    "sg:postcode":"8310",
    "sg:province":"West-Vlaanderen",
    "sg:tags":[
        "shop",
        "-"
    ],
    "wof:name":"Hobby-center Lettenburg",
    "wof:placetype":"venue"
},
  "geometry": {"coordinates":[3.2643098831,51.2138404846],"type":"Point"}
}