{
  "type": "Feature",
  "properties": {
    "iso:country":"BE",
    "sg:address":"Steenpoort 22",
    "sg:city":"Kortrijk",
    "sg:orig_category":"Brood, gebak and snoepgoed",
    "sg:phone":"+32 56 22 13 14",
    "sg:postcode":"8500",
    "sg:province":"West-Vlaanderen",
    "wof:name":"Bakkerij Fran\u00c7aise",
    "wof:placetype":"venue"
},
  "geometry": {"coordinates":[3.2699079514,50.8271102905],"type":"Point"}
}