{
  "type": "Feature",
  "properties": {
    "iso:country":"BE",
    "sg:address":"Reistraat 21",
    "sg:city":"Lanaken",
    "sg:classifiers":[
        {
            "category":"Insurance",
            "subcategory":"Insurance Agent",
            "type":"Services"
        }
    ],
    "sg:phone":"+32 89 71 59 79",
    "sg:postcode":"3620",
    "sg:province":"Limburg",
    "sg:tags":[
        "broker"
    ],
    "wof:name":"Leenders Kantoor Vof",
    "wof:placetype":"venue"
},
  "geometry": {"coordinates":[5.6762018204,50.9032745361],"type":"Point"}
}