{
  "type": "Feature",
  "properties": {
    "iso:country":"BE",
    "sg:address":"Gistelse Steenweg 116",
    "sg:city":"Brugge (sint-andries)",
    "sg:classifiers":[
        {
            "category":"Bars & Pubs",
            "subcategory":"Nightclub",
            "type":"Food & Drink"
        }
    ],
    "sg:phone":"+32 50 39 42 59",
    "sg:postcode":"8200",
    "sg:province":"West-Vlaanderen",
    "wof:name":"Ibiza",
    "wof:placetype":"venue"
},
  "geometry": {"coordinates":[3.2035810947,51.2021484375],"type":"Point"}
}