{
  "type": "Feature",
  "properties": {
    "iso:country":"BE",
    "sg:address":"Sint-jobstraat 96",
    "sg:city":"Heusden-zolder",
    "sg:orig_category":"Kapsalons",
    "sg:phone":"+32 11 25 13 41",
    "sg:postcode":"3550",
    "sg:province":"Limburg",
    "wof:name":"Coiffure Castello",
    "wof:placetype":"venue"
},
  "geometry": {"coordinates":[5.2754201889,50.986782074],"type":"Point"}
}