{
  "type": "Feature",
  "properties": {
    "addr:full":"Scheiken 5 Herentals (noorderwijk) Antwerpen 2200",
    "addr:housenumber":"5",
    "addr:postcode":"2200",
    "addr:street":"Scheiken",
    "iso:country":"BE",
    "sg:address":"Scheiken 5",
    "sg:city":"Herentals (noorderwijk)",
    "sg:classifiers":[
        {
            "category":"Building & Trades",
            "subcategory":"Landscaping Services",
            "type":"Services"
        }
    ],
    "sg:phone":"+32 14 26 52 94",
    "sg:postcode":"2200",
    "sg:province":"Antwerpen",
    "sg:tags":[
        "gardening",
        "garden",
        "maintenance"
    ],
    "wof:name":"Strackx M",
    "wof:placetype":"venue"
},
  "geometry": {"coordinates":[4.8444600105,51.1223487854],"type":"Point"}
}