{
  "type": "Feature",
  "properties": {
    "addr:full":"Gelei 1 Lochristi Oost-Vlaanderen 9080",
    "addr:housenumber":"1",
    "addr:postcode":"9080",
    "addr:street":"Gelei",
    "iso:country":"BE",
    "sg:address":"Gelei 1",
    "sg:city":"Lochristi",
    "sg:orig_category":"Bloemen and planten Gh",
    "sg:phone":"+32 9 356 81 21",
    "sg:postcode":"9080",
    "sg:province":"Oost-Vlaanderen",
    "wof:name":"De Langhe",
    "wof:placetype":"venue"
},
  "geometry": {"coordinates":[3.829116106,51.1236686707],"type":"Point"}
}