{
  "type": "Feature",
  "properties": {
    "addr:full":"Troonstraat 77b6 Oostende West-Vlaanderen 8400",
    "addr:housenumber":"77b6",
    "addr:postcode":"8400",
    "addr:street":"Troonstraat",
    "iso:country":"BE",
    "sg:address":"Troonstraat 77b6",
    "sg:city":"Oostende",
    "sg:classifiers":[
        {
            "category":"Food & Beverages",
            "subcategory":"Meat & Fish",
            "type":"Retail Goods"
        }
    ],
    "sg:phone":"+32 59 80 15 66",
    "sg:postcode":"8400",
    "sg:province":"West-Vlaanderen",
    "sg:tags":[
        "vi",
        "zeevruchten"
    ],
    "wof:name":"Huis Ter Streep",
    "wof:placetype":"venue"
},
  "geometry": {"coordinates":[2.887955904,51.2198371887],"type":"Point"}
}