{
  "type": "Feature",
  "properties": {
    "addr:full":"Vinktsestraat 17 Aalter Oost-Vlaanderen 9880",
    "addr:housenumber":"17",
    "addr:postcode":"9880",
    "addr:street":"Vinktsestraat",
    "iso:country":"BE",
    "sg:address":"Vinktsestraat 17",
    "sg:city":"Aalter",
    "sg:orig_category":"Rundveehouders",
    "sg:phone":"+32 51 68 81 77",
    "sg:postcode":"9880",
    "sg:province":"Oost-Vlaanderen",
    "wof:name":"Julien Buysse",
    "wof:placetype":"venue"
},
  "geometry": {"coordinates":[3.4640920162,51.0233345032],"type":"Point"}
}