{
  "type": "Feature",
  "properties": {
    "addr:full":"Kerkhove 26 Bever/bievene Vlaams-Brabant 1547",
    "addr:housenumber":"26;1547",
    "addr:street":"Kerkhove;Vlaams-Brabant",
    "iso:country":"BE",
    "sg:address":"Kerkhove 26",
    "sg:city":"Bever/bievene",
    "sg:orig_category":"Banken and kredietinstellingen",
    "sg:phone":"+32 54 58 85 57",
    "sg:postcode":"1547",
    "sg:province":"Vlaams-Brabant",
    "wof:name":"Fortis",
    "wof:placetype":"venue"
},
  "geometry": {"coordinates":[3.9374918938,50.7154006958],"type":"Point"}
}