{
  "type": "Feature",
  "properties": {
    "iso:country":"BE",
    "sg:address":"Rue Du Roi Chevalier 4",
    "sg:city":"Andenne (nam\u00eache)",
    "sg:classifiers":[
        {
            "category":"Health Services",
            "subcategory":"Doctor",
            "type":"Services"
        }
    ],
    "sg:phone":"+32 81 58 86 60",
    "sg:postcode":"5300",
    "sg:province":"Namur",
    "sg:tags":[
        "medicinephysicians",
        "surgeon"
    ],
    "wof:name":"David A",
    "wof:placetype":"venue"
},
  "geometry": {"coordinates":[4.9907598495,50.4699211121],"type":"Point"}
}