{
  "type": "Feature",
  "properties": {
    "addr:full":"Warandestraat 6 Nevele (hansbeke) Oost-Vlaanderen 9850",
    "addr:housenumber":"6",
    "addr:postcode":"9850",
    "addr:street":"Warandestraat",
    "iso:country":"BE",
    "sg:address":"Warandestraat 6",
    "sg:city":"Nevele (hansbeke)",
    "sg:classifiers":[
        {
            "category":"Professional",
            "type":"Services"
        }
    ],
    "sg:phone":"+32 9 371 69 24",
    "sg:postcode":"9850",
    "sg:province":"Oost-Vlaanderen",
    "sg:tags":[
        "entertainer"
    ],
    "wof:name":"Raymond Van Het Groenewoud",
    "wof:placetype":"venue"
},
  "geometry": {"coordinates":[3.5281369686,51.0846939087],"type":"Point"}
}