{
  "type": "Feature",
  "properties": {
    "iso:country":"BE",
    "sg:address":"Rue De La Barri\u00e8re De Fer 125",
    "sg:city":"Mouscron (dottignies)",
    "sg:classifiers":[
        {
            "category":"Health Services",
            "subcategory":"Nursing And Care Facility",
            "type":"Services"
        }
    ],
    "sg:phone":"+32 56 48 60 93",
    "sg:postcode":"7711",
    "sg:province":"Hainaut",
    "sg:tags":[
        "home",
        "rest"
    ],
    "wof:name":"L'age Tranquille",
    "wof:placetype":"venue"
},
  "geometry": {"coordinates":[3.3080399036,50.7282752991],"type":"Point"}
}