{
  "type": "Feature",
  "properties": {
    "iso:country":"BE",
    "sg:address":"Rue Du Bois 129b",
    "sg:city":"Lessines (bois-de-lessines)",
    "sg:classifiers":[
        {
            "category":"Sports & Exercise",
            "subcategory":"Stables",
            "type":"Entertainment"
        }
    ],
    "sg:phone":"+32 2 395 81 30",
    "sg:postcode":"7866",
    "sg:province":"Hainaut",
    "sg:tags":[
        "riding",
        "school"
    ],
    "wof:name":"Simon Y",
    "wof:placetype":"venue"
},
  "geometry": {"coordinates":[3.9005548954,50.6891975403],"type":"Point"}
}