{
  "type": "Feature",
  "properties": {
    "addr:full":"Avenue Guillaume Gilbert 68 Bruxelles (ixelles) Bruxelles-Capitale 1050",
    "addr:housenumber":"68",
    "addr:postcode":"1050",
    "addr:street":"Avenue Guillaume Gilbert",
    "iso:country":"BE",
    "sg:address":"Avenue Guillaume Gilbert 68",
    "sg:city":"Bruxelles (ixelles)",
    "sg:classifiers":[
        {
            "category":"Health Services",
            "subcategory":"Doctor",
            "type":"Services"
        }
    ],
    "sg:phone":"+32 2 649 39 27",
    "sg:postcode":"1050",
    "sg:province":"Bruxelles-Capitale",
    "sg:tags":[
        "medicinephysicians",
        "surgeon"
    ],
    "wof:name":"De Francquen Ph",
    "wof:placetype":"venue"
},
  "geometry": {"coordinates":[4.3886327744,50.810798645],"type":"Point"}
}