{
  "type": "Feature",
  "properties": {
    "iso:country":"BE",
    "sg:address":"Generaal Lemanstraat 24",
    "sg:city":"Menen",
    "sg:classifiers":[
        {
            "category":"Health Services",
            "subcategory":"Doctor",
            "type":"Services"
        }
    ],
    "sg:phone":"+32 56 51 21 56",
    "sg:postcode":"8930",
    "sg:province":"West-Vlaanderen",
    "sg:tags":[
        "medicinephysicians",
        "surgeon"
    ],
    "wof:name":"Dewindt W",
    "wof:placetype":"venue"
},
  "geometry": {"coordinates":[3.1086070538,50.7985496521],"type":"Point"}
}