{
  "type": "Feature",
  "properties": {
    "iso:country":"BE",
    "sg:address":"Beverseaardeweg 43",
    "sg:city":"Roeselare",
    "sg:orig_category":"Fotografen and fotostudio's",
    "sg:phone":"+32 51 20 79 98",
    "sg:postcode":"8800",
    "sg:province":"West-Vlaanderen",
    "wof:name":"Etienne Gellynck",
    "wof:placetype":"venue"
},
  "geometry": {"coordinates":[3.1378879547,50.9554595947],"type":"Point"}
}