{
  "type": "Feature",
  "properties": {
    "iso:country":"BE",
    "sg:address":"Petterstraat 12",
    "sg:city":"Affligem (teralfene)",
    "sg:classifiers":[
        {
            "category":"Professional",
            "subcategory":"Lawyer & Legal Services",
            "type":"Services"
        }
    ],
    "sg:phone":"+32 53 66 72 37",
    "sg:postcode":"1790",
    "sg:province":"Vlaams-Brabant",
    "wof:name":"Walravens Ingrid",
    "wof:placetype":"venue"
},
  "geometry": {"coordinates":[4.109000206,50.8937492371],"type":"Point"}
}