{
  "type": "Feature",
  "properties": {
    "addr:full":"Grand'rue 62 Mont-saint-guibert Brabant Wallon 1435",
    "addr:housenumber":"62",
    "addr:postcode":"1435",
    "addr:street":"Grand'Rue",
    "iso:country":"BE",
    "sg:address":"Grand'rue 62",
    "sg:city":"Mont-saint-guibert",
    "sg:classifiers":[
        {
            "category":"Real Estate",
            "subcategory":"Surveying",
            "type":"Services"
        }
    ],
    "sg:phone":"+32 10 41 39 78",
    "sg:postcode":"1435",
    "sg:province":"Brabant Wallon",
    "sg:tags":[
        "surveyor",
        "land"
    ],
    "wof:name":"Vandendries Ch",
    "wof:placetype":"venue"
},
  "geometry": {"coordinates":[4.6107521057,50.6339874268],"type":"Point"}
}