{
  "type": "Feature",
  "properties": {
    "iso:country":"BE",
    "sg:address":"Avenue De Beaulieu 14",
    "sg:city":"Bruxelles (auderghem)",
    "sg:classifiers":[
        {
            "category":"Social Services",
            "subcategory":"Job Training",
            "type":"Services"
        }
    ],
    "sg:phone":"+32 2 660 62 09",
    "sg:postcode":"1160",
    "sg:province":"Bruxelles-Capitale",
    "sg:tags":[
        "interpreter"
    ],
    "wof:name":"Buck V",
    "wof:placetype":"venue"
},
  "geometry": {"coordinates":[4.4124541283,50.8139381409],"type":"Point"}
}