{
  "type": "Feature",
  "properties": {
    "iso:country":"BE",
    "sg:address":"Domentveldstraat 41bb",
    "sg:city":"Affligem",
    "sg:orig_category":"Paramedische behandelingen",
    "sg:phone":"+32 2 452 21 15",
    "sg:postcode":"1790",
    "sg:province":"Vlaams-Brabant",
    "wof:name":"Luc Loomans",
    "wof:placetype":"venue"
},
  "geometry": {"coordinates":[4.1323518753,50.9163208008],"type":"Point"}
}