{
  "type": "Feature",
  "properties": {
    "addr:full":"Avenue Des D\u00c9sirs 29 Evere Bruxelles-Capitale 1140",
    "addr:housenumber":"29",
    "addr:postcode":"1140",
    "addr:street":"Avenue Des De\u0301Sirs",
    "iso:country":"BE",
    "sg:address":"Avenue Des D\u00c9sirs 29",
    "sg:city":"Evere",
    "sg:orig_category":"Secr\u00e9tariats. Imprimeries and copyshops. Composition and photogravure",
    "sg:phone":"+32 2 705 18 35",
    "sg:postcode":"1140",
    "sg:province":"Bruxelles-Capitale",
    "wof:name":"Leyson",
    "wof:placetype":"venue"
},
  "geometry": {"coordinates":[4.4111561775,50.8592948914],"type":"Point"}
}