{
  "type": "Feature",
  "properties": {
    "iso:country":"BE",
    "sg:address":"Liersebaan 16",
    "sg:city":"Lier",
    "sg:orig_category":"M\u00e9decins and sp\u00e9cialistes",
    "sg:phone":"+32 3 482 10 58",
    "sg:postcode":"2500",
    "sg:province":"Antwerpen",
    "wof:name":"Katrien De Vadder",
    "wof:placetype":"venue"
},
  "geometry": {"coordinates":[4.6075868607,51.0988883972],"type":"Point"}
}