{
  "type": "Feature",
  "properties": {
    "iso:country":"BE",
    "sg:address":"De Breyne Peelaertstraat 52",
    "sg:city":"Diksmuide",
    "sg:classifiers":[
        {
            "category":"Health Services",
            "subcategory":"Doctor",
            "type":"Services"
        }
    ],
    "sg:phone":"+32 51 50 01 24",
    "sg:postcode":"8600",
    "sg:province":"West-Vlaanderen",
    "sg:tags":[
        "medicinephysicians",
        "surgeon"
    ],
    "wof:name":"Beuselinck P",
    "wof:placetype":"venue"
},
  "geometry": {"coordinates":[2.8656919003,51.0357322693],"type":"Point"}
}