{
  "type": "Feature",
  "properties": {
    "iso:country":"BE",
    "sg:address":"Gullegemsestraat 125",
    "sg:city":"Ledegem",
    "sg:classifiers":[
        {
            "category":"Insurance",
            "subcategory":"Insurance Agent",
            "type":"Services"
        }
    ],
    "sg:phone":"+32 56 50 46 75",
    "sg:postcode":"8880",
    "sg:province":"West-Vlaanderen",
    "sg:tags":[
        "verzekeringsmakelaars",
        "expert"
    ],
    "wof:name":"Bridelance",
    "wof:placetype":"venue"
},
  "geometry": {"coordinates":[3.1843919754,50.8693466187],"type":"Point"}
}