{
  "type": "Feature",
  "properties": {
    "iso:country":"BE",
    "sg:address":"Rue Des Violettes 18",
    "sg:city":"Binche",
    "sg:orig_category":"Artsen and specialisten",
    "sg:phone":"+32 64 36 66 93",
    "sg:postcode":"7134",
    "sg:province":"Hainaut",
    "wof:name":"Jo\u00cblle De Bock",
    "wof:placetype":"venue"
},
  "geometry": {"coordinates":[4.1927452087,50.4300041199],"type":"Point"}
}