{
  "type": "Feature",
  "properties": {
    "iso:country":"BE",
    "sg:address":"Chemin De Walcourt 15",
    "sg:city":"Thuin",
    "sg:classifiers":[
        {
            "category":"Health Services",
            "subcategory":"Nursing And Care Facility",
            "type":"Services"
        }
    ],
    "sg:phone":"+32 71 59 27 76",
    "sg:postcode":"6530",
    "sg:province":"Hainaut",
    "sg:tags":[
        "home"
    ],
    "wof:name":"Bougard M N",
    "wof:placetype":"venue"
},
  "geometry": {"coordinates":[4.2813110352,50.3302001953],"type":"Point"}
}