{
  "type": "Feature",
  "properties": {
    "addr:full":"Kerkstraat 83 Antwerpen Antwerpen 2060",
    "addr:housenumber":"83",
    "addr:postcode":"2060",
    "addr:street":"Kerkstraat",
    "iso:country":"BE",
    "sg:address":"Kerkstraat 83",
    "sg:city":"Antwerpen",
    "sg:orig_category":"Voedingsspeciaalzaken",
    "sg:phone":"+32 3 235 51 63",
    "sg:postcode":"2060",
    "sg:province":"Antwerpen",
    "wof:name":"Herman Vochten",
    "wof:placetype":"venue"
},
  "geometry": {"coordinates":[4.4317770004,51.218711853],"type":"Point"}
}