{
  "type": "Feature",
  "properties": {
    "iso:country":"BE",
    "sg:address":"Tinnenhoekstraat 50",
    "sg:city":"Aalst (moorsel)",
    "sg:classifiers":[
        {
            "category":"Shopping",
            "subcategory":"Luggage & Leather Goods",
            "type":"Retail Goods"
        }
    ],
    "sg:phone":"+32 53 78 33 57",
    "sg:postcode":"9310",
    "sg:province":"Oost-Vlaanderen",
    "sg:tags":[
        "-"
    ],
    "wof:name":"Callebaut L",
    "wof:placetype":"venue"
},
  "geometry": {"coordinates":[4.1025271416,50.9677505493],"type":"Point"}
}