{
  "type": "Feature",
  "properties": {
    "addr:full":"Noppenstraat 1 Bilzen Limburg 3740",
    "addr:housenumber":"1",
    "addr:postcode":"3740",
    "addr:street":"Noppenstraat",
    "iso:country":"BE",
    "sg:address":"Noppenstraat 1",
    "sg:city":"Bilzen",
    "sg:orig_category":"Enseignement maternel and primaire",
    "sg:phone":"+32 12 45 74 78",
    "sg:postcode":"3740",
    "sg:province":"Limburg",
    "wof:name":"Stedelijke Basisschool",
    "wof:placetype":"venue"
},
  "geometry": {"coordinates":[5.609290123,50.8451004028],"type":"Point"}
}