{
  "type": "Feature",
  "properties": {
    "addr:full":"Rue Nysten 22 Li\u00c8ge Li\u00e8ge 4000",
    "addr:housenumber":"22",
    "addr:postcode":"4000",
    "addr:street":"Rue Nysten",
    "iso:country":"BE",
    "sg:address":"Rue Nysten 22",
    "sg:city":"Li\u00c8ge",
    "sg:orig_category":"Kampeerterreinen",
    "sg:phone":"+32 4 252 89 42",
    "sg:postcode":"4000",
    "sg:province":"Li\u00e8ge",
    "wof:name":"Daniel Paquot",
    "wof:placetype":"venue"
},
  "geometry": {"coordinates":[5.5602397919,50.6340522766],"type":"Point"}
}