{
  "type": "Feature",
  "properties": {
    "addr:full":"Chauss\u00c9e D\u00b4ixelles 57 Elsene/ixelles Bruxelles-Capitale 1050",
    "addr:housenumber":"57",
    "addr:postcode":"1050",
    "addr:street":"Chausse\u0301E D\u00b4Ixelles",
    "iso:country":"BE",
    "sg:address":"Chauss\u00c9e D\u00b4ixelles 57",
    "sg:city":"Elsene/ixelles",
    "sg:orig_category":"V\u00eatements pour b\u00e9b\u00e9s and enfants",
    "sg:phone":"+32 2 511 72 18",
    "sg:postcode":"1050",
    "sg:province":"Bruxelles-Capitale",
    "wof:name":"z",
    "wof:placetype":"venue"
},
  "geometry": {"coordinates":[4.3626728058,50.8362884521],"type":"Point"}
}