{
  "type": "Feature",
  "properties": {
    "addr:full":"O L'z-ey\u00d4s 5 Malmedy/malmedy Li\u00e8ge 4960",
    "addr:housenumber":"5",
    "addr:postcode":"4960",
    "addr:street":"\u0302S",
    "iso:country":"BE",
    "sg:address":"O L'z-ey\u00d4s 5",
    "sg:city":"Malmedy/malmedy",
    "sg:orig_category":"Entretien and r\u00e9parations de voitures",
    "sg:phone":"+32 80 33 95 85",
    "sg:postcode":"4960",
    "sg:province":"Li\u00e8ge",
    "wof:name":"Carros. Charly Schmitz",
    "wof:placetype":"venue"
},
  "geometry": {"coordinates":[6.0054941177,50.4167709351],"type":"Point"}
}