{
  "type": "Feature",
  "properties": {
    "iso:country":"BE",
    "sg:address":"Franseweg 31",
    "sg:city":"Kalmthout",
    "sg:orig_category":"Agences de publicit\u00e9",
    "sg:phone":"+32 3 620 21 40",
    "sg:postcode":"2920",
    "sg:province":"Antwerpen",
    "wof:name":"A.m.s. Digital Printing",
    "wof:placetype":"venue"
},
  "geometry": {"coordinates":[4.5045800209,51.3629875183],"type":"Point"}
}