{
  "type": "Feature",
  "properties": {
    "iso:country":"BE",
    "sg:address":"Chauss\u00c9e De Bruxelles 393",
    "sg:city":"Waterloo",
    "sg:orig_category":"Assurances. Cr\u00e9dit \u00e0 la consommation. Pr\u00eats hypoth\u00e9caires and cr\u00e9dits immobiliers. Banques and organ",
    "sg:phone":"+32 2 354 70 04",
    "sg:postcode":"1410",
    "sg:province":"Brabant Wallon",
    "wof:name":"Bureau Daloze",
    "wof:placetype":"venue"
},
  "geometry": {"coordinates":[4.4022870064,50.700843811],"type":"Point"}
}