{
  "type": "Feature",
  "properties": {
    "iso:country":"BE",
    "sg:address":"Zeelaan 8",
    "sg:city":"De Panne",
    "sg:classifiers":[
        {
            "category":"Travel",
            "subcategory":"Resort",
            "type":"Entertainment"
        }
    ],
    "sg:phone":"+32 58 41 50 10",
    "sg:postcode":"8660",
    "sg:province":"West-Vlaanderen",
    "sg:tags":[
        "vacation"
    ],
    "wof:name":"Botaniek",
    "wof:placetype":"venue"
},
  "geometry": {"coordinates":[2.5889759064,51.0959587097],"type":"Point"}
}