{
  "type": "Feature",
  "properties": {
    "iso:country":"BE",
    "sg:address":"Reit 29",
    "sg:city":"Balen",
    "sg:classifiers":[
        {
            "category":"Wholesale",
            "subcategory":"Construction Materials",
            "type":"Manufacturing & Wholesale Goods"
        }
    ],
    "sg:phone":"+32 14 81 45 80",
    "sg:postcode":"2490",
    "sg:province":"Antwerpen",
    "sg:tags":[
        "steel",
        "plate"
    ],
    "wof:name":"S.i.s. - Swinnen Industrie Service B.v.b.a.",
    "wof:placetype":"venue"
},
  "geometry": {"coordinates":[5.1666498184,51.1645202637],"type":"Point"}
}