{
  "type": "Feature",
  "properties": {
    "addr:full":"Gaversesteenweg 108 Merelbeke Oost-Vlaanderen 9820",
    "addr:housenumber":"108",
    "addr:postcode":"9820",
    "addr:street":"Gaversesteenweg",
    "iso:country":"BE",
    "sg:address":"Gaversesteenweg 108",
    "sg:city":"Merelbeke",
    "sg:classifiers":[
        {
            "category":"Arena",
            "subcategory":"Sports Club",
            "type":"Entertainment"
        }
    ],
    "sg:phone":"+32 9 232 18 64",
    "sg:postcode":"9820",
    "sg:province":"Oost-Vlaanderen",
    "sg:tags":[
        "de"
    ],
    "wof:name":"Autostal Duindistel",
    "wof:placetype":"venue"
},
  "geometry": {"coordinates":[3.7448699474,50.9993896484],"type":"Point"}
}