{
  "type": "Feature",
  "properties": {
    "iso:country":"BE",
    "sg:address":"Tervurenlaan 298",
    "sg:city":"Sint-pieters-woluwe/woluwe-saint-pierre",
    "sg:orig_category":"Banken and kredietinstellingen",
    "sg:phone":"+32 2 770 96 93",
    "sg:postcode":"1150",
    "sg:province":"Bruxelles-Capitale",
    "wof:name":"Dexia",
    "wof:placetype":"venue"
},
  "geometry": {"coordinates":[4.4283428192,50.8351249695],"type":"Point"}
}