{
  "type": "Feature",
  "properties": {
    "iso:country":"BE",
    "sg:address":"Kuilstraat 80",
    "sg:city":"Erpe-mere (erondegem)",
    "sg:classifiers":[
        {
            "category":"Professional",
            "subcategory":"Accounting & Tax Preparation",
            "type":"Services"
        }
    ],
    "sg:phone":"+32 53 79 04 60",
    "sg:postcode":"9420",
    "sg:province":"Oost-Vlaanderen",
    "sg:tags":[
        "accountant"
    ],
    "wof:name":"De Wolf F",
    "wof:placetype":"venue"
},
  "geometry": {"coordinates":[3.9479410648,50.944026947],"type":"Point"}
}