{
  "type": "Feature",
  "properties": {
    "iso:country":"BE",
    "sg:address":"Hulstweg 4",
    "sg:city":"Anzegem",
    "sg:orig_category":"Varkenskwekers",
    "sg:phone":"+32 56 77 75 39",
    "sg:postcode":"8570",
    "sg:province":"West-Vlaanderen",
    "wof:name":"Geert Nijs",
    "wof:placetype":"venue"
},
  "geometry": {"coordinates":[3.4357769489,50.8302574158],"type":"Point"}
}