{
  "type": "Feature",
  "properties": {
    "addr:full":"Stationsstraat 98 Waregem West-Vlaanderen 8790",
    "addr:housenumber":"98",
    "addr:postcode":"8790",
    "addr:street":"Stationsstraat",
    "iso:country":"BE",
    "sg:address":"Stationsstraat 98",
    "sg:city":"Waregem",
    "sg:classifiers":[
        {
            "category":"Travel",
            "subcategory":"Travel Agent",
            "type":"Entertainment"
        }
    ],
    "sg:phone":"+32 56 60 41 31",
    "sg:postcode":"8790",
    "sg:province":"West-Vlaanderen",
    "sg:tags":[
        "agency"
    ],
    "wof:name":"Mars-travel Bvba",
    "wof:placetype":"venue"
},
  "geometry": {"coordinates":[3.429060936,50.8904380798],"type":"Point"}
}