{
  "type": "Feature",
  "properties": {
    "addr:full":"Sportlaan 1 Landen Vlaams-Brabant 3400",
    "addr:housenumber":"1",
    "addr:postcode":"3400",
    "addr:street":"Sportlaan",
    "iso:country":"BE",
    "sg:address":"Sportlaan 1",
    "sg:city":"Landen",
    "sg:classifiers":[
        {
            "category":"Arena",
            "subcategory":"Sports Club",
            "type":"Entertainment"
        }
    ],
    "sg:phone":"+32 11 88 31 11",
    "sg:postcode":"3400",
    "sg:province":"Vlaams-Brabant",
    "wof:name":"Olympic Vc Landen",
    "wof:placetype":"venue"
},
  "geometry": {"coordinates":[5.0833702087,50.7523117065],"type":"Point"}
}