{
  "type": "Feature",
  "properties": {
    "iso:country":"BE",
    "sg:address":"Winkelstraat 18",
    "sg:city":"Sint-amands",
    "sg:orig_category":"Loodgieterij, verwarming and sanitaire installaties",
    "sg:phone":"+32 52 33 46 99",
    "sg:postcode":"2890",
    "sg:province":"Antwerpen",
    "wof:name":"Wouters",
    "wof:placetype":"venue"
},
  "geometry": {"coordinates":[4.2069988251,51.0500793457],"type":"Point"}
}