{
  "type": "Feature",
  "properties": {
    "addr:full":"Grand Route 21 Neupr\u00e9 (plainevaux) Li\u00e8ge 4122",
    "addr:postcode":"4122",
    "addr:street":"Grand Route 21;Plainevaux",
    "iso:country":"BE",
    "sg:address":"Grand Route 21",
    "sg:city":"Neupr\u00e9 (plainevaux)",
    "sg:classifiers":[
        {
            "category":"Health Services",
            "subcategory":"Health Practitioner",
            "type":"Services"
        }
    ],
    "sg:phone":"+32 4 371 27 41",
    "sg:postcode":"4122",
    "sg:province":"Li\u00e8ge",
    "sg:tags":[
        "physiotherapist"
    ],
    "wof:name":"Badot Sophie",
    "wof:placetype":"venue"
},
  "geometry": {"coordinates":[5.5251932144,50.5452194214],"type":"Point"}
}