{
  "type": "Feature",
  "properties": {
    "iso:country":"BE",
    "sg:address":"Alsembergse Steenweg 1",
    "sg:city":"Sint-gillis/saint-gilles",
    "sg:orig_category":"Diverse kredietdiensten",
    "sg:postcode":"1060",
    "sg:province":"Bruxelles-Capitale",
    "wof:name":"Bancontact-mister Cash",
    "wof:placetype":"venue"
},
  "geometry": {"coordinates":[4.3441510201,50.8267402649],"type":"Point"}
}