{
  "type": "Feature",
  "properties": {
    "iso:country":"BE",
    "sg:address":"Gentstraat 75",
    "sg:city":"Oudenaarde",
    "sg:classifiers":[
        {
            "category":"Shopping Center",
            "type":"Public Place"
        }
    ],
    "sg:phone":"+32 55 30 24 32",
    "sg:postcode":"9700",
    "sg:province":"Oost-Vlaanderen",
    "sg:tags":[
        "enseignement",
        "formation"
    ],
    "wof:name":"Vdab Training En Opleiding",
    "wof:placetype":"venue"
},
  "geometry": {"coordinates":[3.5999319553,50.8525810242],"type":"Point"}
}