{
  "type": "Feature",
  "properties": {
    "addr:full":"Magnolialaan 3 Sint-niklaas Oost-Vlaanderen 9100",
    "addr:housenumber":"3",
    "addr:postcode":"9100",
    "addr:street":"Magnolialaan",
    "iso:country":"BE",
    "sg:address":"Magnolialaan 3",
    "sg:city":"Sint-niklaas",
    "sg:classifiers":[
        {
            "category":"Fast Food",
            "type":"Food & Drink"
        }
    ],
    "sg:phone":"+32 3 776 63 86",
    "sg:postcode":"9100",
    "sg:province":"Oost-Vlaanderen",
    "sg:tags":[
        "meeneem",
        "restaurant"
    ],
    "wof:name":"\u00b4t Brugsken",
    "wof:placetype":"venue"
},
  "geometry": {"coordinates":[4.1557021141,51.1605377197],"type":"Point"}
}