{
  "type": "Feature",
  "properties": {
    "addr:full":"Rue D'aix La Chapelle 96 Eupen/eupen Li\u00e8ge 4700",
    "addr:housenumber":"96",
    "addr:postcode":"4700",
    "addr:street":"Rue D'Aix La Chapelle",
    "iso:country":"BE",
    "sg:address":"Rue D'aix La Chapelle 96",
    "sg:city":"Eupen/eupen",
    "sg:orig_category":"Entretien and r\u00e9parations de voitures",
    "sg:phone":"+32 87 74 23 07",
    "sg:postcode":"4700",
    "sg:province":"Li\u00e8ge",
    "wof:name":"Garage Groteclaes",
    "wof:placetype":"venue"
},
  "geometry": {"coordinates":[6.1348800659,50.5989990234],"type":"Point"}
}