{
  "type": "Feature",
  "properties": {
    "addr:full":"Bankstraat 60 Gullegem West-Vlaanderen 8560",
    "addr:housenumber":"60",
    "addr:postcode":"8560",
    "addr:street":"Bankstraat",
    "iso:country":"BE",
    "sg:address":"Bankstraat 60",
    "sg:city":"Gullegem",
    "sg:orig_category":"Royal Canin. Animaux domestiques and accessoires",
    "sg:phone":"+32 56 41 16 48",
    "sg:postcode":"8560",
    "sg:province":"West-Vlaanderen",
    "wof:name":"Lambert Demeyere",
    "wof:placetype":"venue"
},
  "geometry": {"coordinates":[3.2006471157,50.8448066711],"type":"Point"}
}