{
  "type": "Feature",
  "properties": {
    "iso:country":"BE",
    "sg:address":"Harelbekestraat 29",
    "sg:city":"Anzegem",
    "sg:orig_category":"Eclairage et \u00e9quipements du foyer. Stations-service and carburants",
    "sg:phone":"+32 56 77 71 57",
    "sg:postcode":"8570",
    "sg:province":"West-Vlaanderen",
    "wof:name":"Callens Andre",
    "wof:placetype":"venue"
},
  "geometry": {"coordinates":[3.3997399807,50.8392181396],"type":"Point"}
}