{
  "type": "Feature",
  "properties": {
    "addr:full":"Rue De Libersart 66 Walhain (tourinnes-saint-lambert) Brabant Wallon 1457",
    "addr:housenumber":"66",
    "addr:postcode":"1457",
    "addr:street":"Rue De Libersart;Wallon",
    "iso:country":"BE",
    "sg:address":"Rue De Libersart 66",
    "sg:city":"Walhain (tourinnes-saint-lambert)",
    "sg:classifiers":[
        {
            "category":"Real Estate",
            "subcategory":"Architect",
            "type":"Services"
        }
    ],
    "sg:phone":"+32 10 68 92 90",
    "sg:postcode":"1457",
    "sg:province":"Brabant Wallon",
    "wof:name":"Stacquet A",
    "wof:placetype":"venue"
},
  "geometry": {"coordinates":[4.7177591324,50.6528282166],"type":"Point"}
}