{
  "type": "Feature",
  "properties": {
    "addr:full":"Chauss\u00c9e De Mons 52 Ath Hainaut 7800",
    "addr:housenumber":"52",
    "addr:postcode":"7800",
    "addr:street":"Chausse\u0301E De Mons",
    "iso:country":"BE",
    "sg:address":"Chauss\u00c9e De Mons 52",
    "sg:city":"Ath",
    "sg:classifiers":[
        {
            "category":"Fast Food",
            "type":"Food & Drink"
        }
    ],
    "sg:phone":"+32 68 28 46 08",
    "sg:postcode":"7800",
    "sg:province":"Hainaut",
    "sg:tags":[
        "meeneem",
        "restaurant"
    ],
    "wof:name":"Jimmy",
    "wof:placetype":"venue"
},
  "geometry": {"coordinates":[3.7730169296,50.6250190735],"type":"Point"}
}