{
  "type": "Feature",
  "properties": {
    "iso:country":"BE",
    "sg:address":"Oeverstraat 19",
    "sg:city":"Kruibeke (rupelmonde)",
    "sg:classifiers":[
        {
            "category":"Professional",
            "subcategory":"Art Services",
            "type":"Services"
        }
    ],
    "sg:phone":"+32 3 774 11 86",
    "sg:postcode":"9150",
    "sg:province":"Oost-Vlaanderen",
    "sg:tags":[
        "-",
        "painter",
        "artist"
    ],
    "wof:name":"Van De Graaf A",
    "wof:placetype":"venue"
},
  "geometry": {"coordinates":[4.2897639275,51.1263771057],"type":"Point"}
}