{
  "type": "Feature",
  "properties": {
    "iso:country":"BE",
    "sg:address":"Place De L'abbaye 5",
    "sg:city":"Erquelinnes (bersillies - L'abbaye)",
    "sg:classifiers":[
        {
            "category":"Insurance",
            "subcategory":"Insurance Agent",
            "type":"Services"
        }
    ],
    "sg:phone":"+32 71 55 70 46",
    "sg:postcode":"6560",
    "sg:province":"Hainaut",
    "sg:tags":[
        "broker"
    ],
    "wof:name":"Navaux Neukermans & Cie Snc",
    "wof:placetype":"venue"
},
  "geometry": {"coordinates":[4.1509971619,50.2623939514],"type":"Point"}
}