{
  "type": "Feature",
  "properties": {
    "addr:full":"Rijselstraat 87 Menen West-Vlaanderen 8930",
    "addr:housenumber":"87",
    "addr:postcode":"8930",
    "addr:street":"Rijselstraat",
    "iso:country":"BE",
    "sg:address":"Rijselstraat 87",
    "sg:city":"Menen",
    "sg:orig_category":"Muziekinstrumenten",
    "sg:phone":"+32 56 51 07 54",
    "sg:postcode":"8930",
    "sg:province":"West-Vlaanderen",
    "wof:name":"Huis Lemaire",
    "wof:placetype":"venue"
},
  "geometry": {"coordinates":[3.1236569881,50.7920227051],"type":"Point"}
}