{
  "type": "Feature",
  "properties": {
    "iso:country":"BE",
    "sg:address":"Rue Dubus 19bb",
    "sg:city":"Tournai",
    "sg:orig_category":"Woningbouw",
    "sg:phone":"+32 69 64 89 39",
    "sg:postcode":"7506",
    "sg:province":"Hainaut",
    "wof:name":"Michel Delmer",
    "wof:placetype":"venue"
},
  "geometry": {"coordinates":[3.3487200737,50.5716514587],"type":"Point"}
}