{
  "type": "Feature",
  "properties": {
    "addr:full":"Kloosterstraat 40 Bierbeek (korbeek-lo) Vlaams-Brabant 3360",
    "addr:housenumber":"40",
    "addr:postcode":"3360",
    "addr:street":"Kloosterstraat",
    "iso:country":"BE",
    "sg:address":"Kloosterstraat 40",
    "sg:city":"Bierbeek (korbeek-lo)",
    "sg:classifiers":[
        {
            "category":"Shopping",
            "subcategory":"Crafts & Fabrics",
            "type":"Retail Goods"
        }
    ],
    "sg:phone":"+32 16 46 36 16",
    "sg:postcode":"3360",
    "sg:province":"Vlaams-Brabant",
    "sg:tags":[
        "ceramic"
    ],
    "wof:name":"Atelier Vandoren",
    "wof:placetype":"venue"
},
  "geometry": {"coordinates":[4.7675871849,50.8634910583],"type":"Point"}
}