{
  "type": "Feature",
  "properties": {
    "addr:full":"Rue De La Bel 16 Aubel Li\u00e8ge 4880",
    "addr:housenumber":"16",
    "addr:postcode":"4880",
    "addr:street":"Rue De La Bel",
    "iso:country":"BE",
    "sg:address":"Rue De La Bel 16",
    "sg:city":"Aubel",
    "sg:orig_category":"Rechtbanken",
    "sg:phone":"+32 87 68 74 56",
    "sg:postcode":"4880",
    "sg:province":"Li\u00e8ge",
    "wof:name":"Justice De Paix",
    "wof:placetype":"venue"
},
  "geometry": {"coordinates":[5.8569989204,50.7107200623],"type":"Point"}
}