{
  "type": "Feature",
  "properties": {
    "addr:full":"Rochesterlaan 8 Gistel West-Vlaanderen 8470",
    "addr:housenumber":"8",
    "addr:postcode":"8470",
    "addr:street":"Rochesterlaan",
    "iso:country":"BE",
    "sg:address":"Rochesterlaan 8",
    "sg:city":"Gistel",
    "sg:classifiers":[
        {
            "category":"Retail",
            "subcategory":"Auto Rental",
            "type":"Services"
        }
    ],
    "sg:phone":"+32 59 27 85 29",
    "sg:postcode":"8470",
    "sg:province":"West-Vlaanderen",
    "sg:tags":[
        "milking",
        "machine"
    ],
    "wof:name":"Rommelaere Nv",
    "wof:placetype":"venue"
},
  "geometry": {"coordinates":[2.9458210468,51.1475448608],"type":"Point"}
}