{
  "type": "Feature",
  "properties": {
    "iso:country":"BE",
    "sg:address":"Stene 0",
    "sg:city":"Horebeke",
    "sg:classifiers":[
        {
            "category":"Cafe",
            "type":"Food & Drink"
        }
    ],
    "sg:phone":"+32 55 45 57 55",
    "sg:postcode":"9667",
    "sg:province":"Oost-Vlaanderen",
    "sg:tags":[
        "caf\u00e9s"
    ],
    "wof:name":"Voetballokaal Vv Horebeke",
    "wof:placetype":"venue"
},
  "geometry": {"coordinates":[3.6832740307,50.8191757202],"type":"Point"}
}