{
  "type": "Feature",
  "properties": {
    "iso:country":"BE",
    "sg:address":"Haenenstraat 21",
    "sg:city":"Bilzen (eigenbilzen)",
    "sg:classifiers":[
        {
            "category":"Food & Beverages",
            "subcategory":"Groceries & Convenience Stores",
            "type":"Retail Goods"
        }
    ],
    "sg:phone":"+32 89 41 23 03",
    "sg:postcode":"3740",
    "sg:province":"Limburg",
    "sg:tags":[
        "grocer"
    ],
    "wof:name":"Kuypers",
    "wof:placetype":"venue"
},
  "geometry": {"coordinates":[5.5724821091,50.8825721741],"type":"Point"}
}