{
  "type": "Feature",
  "properties": {
    "addr:full":"Brusselsesteenweg 64 Zemst Vlaams-Brabant 1980",
    "addr:housenumber":"64",
    "addr:postcode":"1980",
    "addr:street":"Brusselsesteenweg;Vlaams-Brabant",
    "iso:country":"BE",
    "sg:address":"Brusselsesteenweg 64",
    "sg:city":"Zemst",
    "sg:orig_category":"Pain, p\u00e2tisseries and confiseries",
    "sg:phone":"+32 15 61 24 43",
    "sg:postcode":"1980",
    "sg:province":"Vlaams-Brabant",
    "wof:name":"De Kock Herman & Kinderen",
    "wof:placetype":"venue"
},
  "geometry": {"coordinates":[4.4672279358,50.9857597351],"type":"Point"}
}