{
  "type": "Feature",
  "properties": {
    "iso:country":"BE",
    "sg:address":"Franz Courtensstraat 35",
    "sg:city":"Dendermonde",
    "sg:orig_category":"Industri\u00eble wasserijen and droogkuis",
    "sg:phone":"+32 52 21 11 82",
    "sg:postcode":"9200",
    "sg:province":"Oost-Vlaanderen",
    "wof:name":"Quick Shop",
    "wof:placetype":"venue"
},
  "geometry": {"coordinates":[4.1016559601,51.0323257446],"type":"Point"}
}