{
  "type": "Feature",
  "properties": {
    "addr:full":"Verhaegenlaan 8 Geraardsbergen Oost-Vlaanderen 9500",
    "addr:housenumber":"8",
    "addr:postcode":"9500",
    "addr:street":"Verhaegenlaan",
    "iso:country":"BE",
    "sg:address":"Verhaegenlaan 8",
    "sg:city":"Geraardsbergen",
    "sg:orig_category":"Advocaten and juridische adviseurs",
    "sg:phone":"+32 54 41 06 17",
    "sg:postcode":"9500",
    "sg:province":"Oost-Vlaanderen",
    "wof:name":"Geert Van Damme",
    "wof:placetype":"venue"
},
  "geometry": {"coordinates":[3.8772189617,50.7695350647],"type":"Point"}
}