{
  "type": "Feature",
  "properties": {
    "addr:full":"Rue D'oth\u00e9e 73 Ans Li\u00e8ge 4430",
    "addr:housenumber":"73",
    "addr:postcode":"4430",
    "addr:street":"Rue D'Othe \u0301E",
    "iso:country":"BE",
    "sg:address":"Rue D'oth\u00e9e 73",
    "sg:city":"Ans",
    "sg:classifiers":[
        {
            "category":"Home & Garden",
            "subcategory":"Building Materials",
            "type":"Retail Goods"
        }
    ],
    "sg:postcode":"4430",
    "sg:province":"Li\u00e8ge",
    "sg:tags":[
        "window"
    ],
    "wof:name":"Collignon Et Fils",
    "wof:placetype":"venue"
},
  "geometry": {"coordinates":[5.532201767,50.6647911072],"type":"Point"}
}