{
  "type": "Feature",
  "properties": {
    "addr:full":"Rue Du Pont Du Christ 30 Wavre Brabant Wallon 1300",
    "addr:housenumber":"30;1300",
    "addr:street":"Rue Du Pont Du Christ",
    "iso:country":"BE",
    "sg:address":"Rue Du Pont Du Christ 30",
    "sg:city":"Wavre",
    "sg:orig_category":"Dameskledingzaken",
    "sg:phone":"+32 10 22 21 51",
    "sg:postcode":"1300",
    "sg:province":"Brabant Wallon",
    "wof:name":"Best Sellers",
    "wof:placetype":"venue"
},
  "geometry": {"coordinates":[4.6098818779,50.715549469],"type":"Point"}
}