{
  "type": "Feature",
  "properties": {
    "iso:country":"BE",
    "sg:address":"Jachtlaan 201",
    "sg:city":"Etterbeek/etterbeek",
    "sg:orig_category":"Dierenartsen",
    "sg:phone":"+32 2 733 54 72",
    "sg:postcode":"1040",
    "sg:province":"Bruxelles-Capitale",
    "wof:name":"Albert Denisty",
    "wof:placetype":"venue"
},
  "geometry": {"coordinates":[4.3946428299,50.8357810974],"type":"Point"}
}