{
  "type": "Feature",
  "properties": {
    "addr:full":"Rue De Perwez 107 Gembloux Namur 5031",
    "addr:housenumber":"107",
    "addr:postcode":"5031",
    "addr:street":"Rue De Perwez;Namur",
    "iso:country":"BE",
    "sg:address":"Rue De Perwez 107",
    "sg:city":"Gembloux",
    "sg:orig_category":"Rev\u00eatements pour sols and murs",
    "sg:phone":"+32 81 64 00 70",
    "sg:postcode":"5031",
    "sg:province":"Namur",
    "wof:name":"Maurice Lebrun",
    "wof:placetype":"venue"
},
  "geometry": {"coordinates":[4.7781209946,50.5957489014],"type":"Point"}
}