{
  "type": "Feature",
  "properties": {
    "addr:full":". Denderleeuw (groot) Oost-Vlaanderen 9470",
    "addr:postcode":"9470",
    "addr:street":"Groot Oost-Vlaanderen",
    "iso:country":"BE",
    "sg:address":".",
    "sg:city":"Denderleeuw (groot)",
    "sg:orig_category":"Apotheken",
    "sg:phone":"+32 900 10 500",
    "sg:postcode":"9470",
    "sg:province":"Oost-Vlaanderen",
    "wof:name":"Apothekers Van Wacht",
    "wof:placetype":"venue"
},
  "geometry": {"coordinates":[4.0806999207,50.8829154968],"type":"Point"}
}