{
  "type": "Feature",
  "properties": {
    "addr:full":"Rue Du Drabe 12 Braine-le-chateau Brabant Wallon 1440",
    "addr:housenumber":"12",
    "addr:postcode":"1440",
    "addr:street":"Rue Du Drabe;Brabant Wallon",
    "iso:country":"BE",
    "sg:address":"Rue Du Drabe 12",
    "sg:city":"Braine-le-chateau",
    "sg:orig_category":"Activit\u00e9s diverses d'imprimerie",
    "sg:phone":"+32 2 366 12 48",
    "sg:postcode":"1440",
    "sg:province":"Brabant Wallon",
    "wof:name":"Jean-pierre Marsily",
    "wof:placetype":"venue"
},
  "geometry": {"coordinates":[4.2857689857,50.6836624146],"type":"Point"}
}