{
  "type": "Feature",
  "properties": {
    "addr:full":"Avenue Adolphe Lacombl\u00c9 88 Schaarbeek/schaerbeek Bruxelles-Capitale 1030",
    "addr:housenumber":"88",
    "addr:postcode":"1030",
    "addr:street":"Avenue Adolphe Lacomble\u0301",
    "iso:country":"BE",
    "sg:address":"Avenue Adolphe Lacombl\u00c9 88",
    "sg:city":"Schaarbeek/schaerbeek",
    "sg:classifiers":[
        {
            "category":"Personal",
            "subcategory":"Beauty Salon",
            "type":"Services"
        }
    ],
    "sg:phone":"+32 2 734 77 70",
    "sg:postcode":"1030",
    "sg:province":"Bruxelles-Capitale",
    "sg:tags":[
        "de",
        "coiffure"
    ],
    "wof:name":"Evelyne Nikoue",
    "wof:placetype":"venue"
},
  "geometry": {"coordinates":[4.3981409073,50.8481521606],"type":"Point"}
}