{
  "type": "Feature",
  "properties": {
    "iso:country":"BE",
    "sg:address":"Place De L'h\u00d4tel De Ville 7",
    "sg:city":"Herve",
    "sg:orig_category":"RESTAURANTS: LIVRAISON \u00c0 DOMICILE. RESTAURANTS",
    "sg:phone":"+32 87 67 96 42",
    "sg:postcode":"4650",
    "sg:province":"Li\u00e8ge",
    "wof:name":"E.m.a Cuisson",
    "wof:placetype":"venue"
},
  "geometry": {"coordinates":[-0.9248610139,48.1741142273],"type":"Point"}
}