{
  "type": "Feature",
  "properties": {
    "addr:full":"Rue De L'eglise 15 Aubange Luxembourg 6791",
    "addr:housenumber":"15",
    "addr:postcode":"6791",
    "addr:street":"Rue De L'Eglise",
    "iso:country":"BE",
    "sg:address":"Rue De L'eglise 15",
    "sg:city":"Aubange",
    "sg:classifiers":[
        {
            "category":"Personal",
            "subcategory":"Beauty Salon",
            "type":"Services"
        }
    ],
    "sg:phone":"+32 63 38 46 44",
    "sg:postcode":"6791",
    "sg:province":"Luxembourg",
    "sg:tags":[
        "de",
        "coiffure"
    ],
    "wof:name":"Men's Coiffure",
    "wof:placetype":"venue"
},
  "geometry": {"coordinates":[5.8353052139,49.5658950806],"type":"Point"}
}