{
  "type": "Feature",
  "properties": {
    "iso:country":"BE",
    "sg:address":"Hoegaardsesteenweg 30",
    "sg:city":"Bierbeek",
    "sg:classifiers":[
        {
            "category":"Cafe",
            "type":"Food & Drink"
        }
    ],
    "sg:phone":"+32 16 73 34 47",
    "sg:postcode":"3360",
    "sg:province":"Vlaams-Brabant",
    "sg:tags":[
        "caf\u00e9s"
    ],
    "wof:name":"Marcel Leclercq",
    "wof:placetype":"venue"
},
  "geometry": {"coordinates":[4.7914748192,50.8118209839],"type":"Point"}
}