{
  "type": "Feature",
  "properties": {
    "addr:full":"Luxemburgplein 14 Elsene/ixelles Bruxelles-Capitale 1050",
    "addr:housenumber":"14",
    "addr:postcode":"1050",
    "addr:street":"Luxemburgplein",
    "iso:country":"BE",
    "sg:address":"Luxemburgplein 14",
    "sg:city":"Elsene/ixelles",
    "sg:orig_category":"Banken and kredietinstellingen",
    "sg:phone":"+32 2 230 28 12",
    "sg:postcode":"1050",
    "sg:province":"Bruxelles-Capitale",
    "wof:name":"Fortis",
    "wof:placetype":"venue"
},
  "geometry": {"coordinates":[4.3724579811,50.839553833],"type":"Point"}
}