{
  "type": "Feature",
  "properties": {
    "iso:country":"BE",
    "sg:address":"Rue Fontaine Saint-pierre 1b",
    "sg:city":"Assesse",
    "sg:classifiers":[
        {
            "category":"Retail",
            "subcategory":"Car Wash",
            "type":"Services"
        }
    ],
    "sg:phone":"+32 83 65 58 05",
    "sg:postcode":"5330",
    "sg:province":"Namur",
    "sg:tags":[
        "automobile",
        "-",
        "washing",
        "truck",
        "equipment"
    ],
    "wof:name":"A.c. Sirio Belgium Sa",
    "wof:placetype":"venue"
},
  "geometry": {"coordinates":[5.0442857742,50.3694496155],"type":"Point"}
}