{
  "type": "Feature",
  "properties": {
    "iso:country":"BE",
    "sg:address":"Blarenberglaan 21 3",
    "sg:city":"Mechelen",
    "sg:orig_category":"Gespecialiseerde residenti\u00eble bouw Installatie van metalen schrijnwerk",
    "sg:phone":"+32 15 29 03 80",
    "sg:postcode":"2800",
    "sg:province":"Antwerpen",
    "wof:name":"Troax",
    "wof:placetype":"venue"
},
  "geometry": {"coordinates":[4.4509840012,51.0521621704],"type":"Point"}
}