{
  "type": "Feature",
  "properties": {
    "addr:full":"Predikherenhoevestraat 31 Rumst Antwerpen 2840",
    "addr:housenumber":"31",
    "addr:postcode":"2840",
    "addr:street":"Predikherenhoevestraat",
    "iso:country":"BE",
    "sg:address":"Predikherenhoevestraat 31",
    "sg:city":"Rumst",
    "sg:orig_category":"Enseignement maternel and primaire",
    "sg:phone":"+32 3 888 40 16",
    "sg:postcode":"2840",
    "sg:province":"Antwerpen",
    "wof:name":"B.s.b.o. Groenlaar",
    "wof:placetype":"venue"
},
  "geometry": {"coordinates":[4.3852472305,51.107208252],"type":"Point"}
}