{
  "type": "Feature",
  "properties": {
    "iso:country":"BE",
    "sg:address":"George Minnelaan 9",
    "sg:city":"Sint-martens-latem",
    "sg:classifiers":[
        {
            "category":"Communications",
            "subcategory":"Film & Video Production",
            "type":"Services"
        }
    ],
    "sg:phone":"+32 9 282 24 81",
    "sg:postcode":"9830",
    "sg:province":"Oost-Vlaanderen",
    "sg:tags":[
        "movie",
        "maker"
    ],
    "wof:name":"Dellaert C",
    "wof:placetype":"venue"
},
  "geometry": {"coordinates":[3.6299469471,51.0003356934],"type":"Point"}
}