{
  "type": "Feature",
  "properties": {
    "iso:country":"BE",
    "sg:address":"Kortrijkstraat 87",
    "sg:city":"Wevelgem",
    "sg:classifiers":[
        {
            "category":"Shopping",
            "subcategory":"Clothing, Apparel, & Fashions",
            "type":"Retail Goods"
        }
    ],
    "sg:phone":"+32 56 42 16 64",
    "sg:postcode":"8560",
    "sg:province":"West-Vlaanderen",
    "sg:tags":[
        "lady",
        "clothing",
        "-"
    ],
    "wof:name":"Isola",
    "wof:placetype":"venue"
},
  "geometry": {"coordinates":[3.1898040771,50.8108673096],"type":"Point"}
}