{
  "type": "Feature",
  "properties": {
    "iso:country":"BE",
    "sg:address":"Chauss\u00c9e Du Rh\u00d4ne 37",
    "sg:city":"Wavre",
    "sg:orig_category":"Slagers",
    "sg:phone":"+32 10 22 94 57",
    "sg:postcode":"1300",
    "sg:province":"Brabant Wallon",
    "wof:name":"Philippe Gourgue",
    "wof:placetype":"venue"
},
  "geometry": {"coordinates":[4.6115088463,50.7227210999],"type":"Point"}
}