{
  "type": "Feature",
  "properties": {
    "iso:country":"BE",
    "sg:address":"Koningslaan 146",
    "sg:city":"Knokke-heist (knokke)",
    "sg:classifiers":[
        {
            "category":"Insurance",
            "subcategory":"Insurance Agent",
            "type":"Services"
        }
    ],
    "sg:phone":"+32 50 62 45 46",
    "sg:postcode":"8300",
    "sg:province":"West-Vlaanderen",
    "sg:tags":[
        "broker"
    ],
    "wof:name":"Assuranties Gysel Nv",
    "wof:placetype":"venue"
},
  "geometry": {"coordinates":[3.2848498821,51.3465614319],"type":"Point"}
}