{
  "type": "Feature",
  "properties": {
    "addr:full":"Henri Verstappenplein 14 Box 10 Diest Vlaams-Brabant 3290",
    "addr:housenumber":"14 box 10",
    "addr:postcode":"3290",
    "addr:street":"Henri Verstappenplein",
    "iso:country":"BE",
    "sg:address":"Henri Verstappenplein 14 Box 10",
    "sg:city":"Diest",
    "sg:classifiers":[
        {
            "category":"Professional",
            "subcategory":"Management & Consulting",
            "type":"Services"
        }
    ],
    "sg:phone":"+32 13 33 33 95",
    "sg:postcode":"3290",
    "sg:province":"Vlaams-Brabant",
    "sg:tags":[
        "tax-consultants"
    ],
    "wof:name":"Timmermans W",
    "wof:placetype":"venue"
},
  "geometry": {"coordinates":[5.054268837,50.9845314026],"type":"Point"}
}