{
  "type": "Feature",
  "properties": {
    "iso:country":"BE",
    "sg:address":"Meirlare 19",
    "sg:city":"Zomergem",
    "sg:orig_category":"Eleveurs de bovins. Eleveurs and marchands de porcs",
    "sg:phone":"+32 9 372 42 82",
    "sg:postcode":"9930",
    "sg:province":"Oost-Vlaanderen",
    "wof:name":"Paul De Vliegher",
    "wof:placetype":"venue"
},
  "geometry": {"coordinates":[3.5788509846,51.131313324],"type":"Point"}
}