{
  "type": "Feature",
  "properties": {
    "iso:country":"BE",
    "sg:address":"La Basse Col\u00c8te 2",
    "sg:city":"Ferrieres",
    "sg:orig_category":"Pharmaciens",
    "sg:phone":"+32 86 40 00 72",
    "sg:postcode":"4190",
    "sg:province":"Li\u00e8ge",
    "wof:name":"J. Grailet",
    "wof:placetype":"venue"
},
  "geometry": {"coordinates":[5.6054267883,50.3997879028],"type":"Point"}
}