{
  "type": "Feature",
  "properties": {
    "addr:full":"Alpenroosbaan 5 Schoten Antwerpen 2900",
    "addr:housenumber":"5",
    "addr:postcode":"2900",
    "addr:street":"Alpenroosbaan",
    "iso:country":"BE",
    "sg:address":"Alpenroosbaan 5",
    "sg:city":"Schoten",
    "sg:classifiers":[
        {
            "category":"Professional",
            "subcategory":"Art Services",
            "type":"Services"
        }
    ],
    "sg:phone":"+32 478 78 95 98",
    "sg:postcode":"2900",
    "sg:province":"Antwerpen",
    "sg:tags":[
        "designer",
        "display"
    ],
    "wof:name":"Peeters M",
    "wof:placetype":"venue"
},
  "geometry": {"coordinates":[4.5180130005,51.2738685608],"type":"Point"}
}