{
  "type": "Feature",
  "properties": {
    "addr:full":"Roosbloemstraat 18 Oosterzele Oost-Vlaanderen 9860",
    "addr:housenumber":"18",
    "addr:postcode":"9860",
    "addr:street":"Roosbloemstraat;Oost-Vlaanderen",
    "iso:country":"BE",
    "sg:address":"Roosbloemstraat 18",
    "sg:city":"Oosterzele",
    "sg:classifiers":[
        {
            "category":"Arena",
            "subcategory":"Sports Club",
            "type":"Entertainment"
        }
    ],
    "sg:phone":"+32 9 362 00 13",
    "sg:postcode":"9860",
    "sg:province":"Oost-Vlaanderen",
    "sg:tags":[
        "de"
    ],
    "wof:name":"Tomodachi Karateclub",
    "wof:placetype":"venue"
},
  "geometry": {"coordinates":[3.8207149506,50.9462547302],"type":"Point"}
}