{
  "type": "Feature",
  "properties": {
    "addr:full":"Lombardsijdelaan 153 Westende West-Vlaanderen 8434",
    "addr:housenumber":"153",
    "addr:postcode":"8434",
    "addr:street":"Lombardsijdelaan",
    "iso:country":"BE",
    "sg:address":"Lombardsijdelaan 153",
    "sg:city":"Westende",
    "sg:classifiers":[
        {
            "category":"Social Services",
            "subcategory":"Job Training",
            "type":"Services"
        }
    ],
    "sg:phone":"+32 58 23 37 97",
    "sg:postcode":"8434",
    "sg:province":"West-Vlaanderen",
    "sg:tags":[
        "de",
        "terrain",
        "camping"
    ],
    "wof:name":"Tourcamp Bvba",
    "wof:placetype":"venue"
},
  "geometry": {"coordinates":[2.7608950138,51.1524772644],"type":"Point"}
}