{
  "type": "Feature",
  "properties": {
    "iso:country":"BE",
    "sg:address":"Deinzestraat 92",
    "sg:city":"Dentergem (oeselgem)",
    "sg:classifiers":[
        {
            "category":"Home & Garden",
            "subcategory":"Home Furnishings",
            "type":"Retail Goods"
        }
    ],
    "sg:phone":"+32 9 388 46 94",
    "sg:postcode":"8720",
    "sg:province":"West-Vlaanderen",
    "sg:tags":[
        "decoration"
    ],
    "wof:name":"Van Betsbrugge P",
    "wof:placetype":"venue"
},
  "geometry": {"coordinates":[3.4162099361,50.9655342102],"type":"Point"}
}