{
  "type": "Feature",
  "properties": {
    "addr:full":"Village 22 Welkenraedt (henri-chapelle) Li\u00e8ge 4841",
    "addr:housenumber":"22",
    "addr:postcode":"4841",
    "addr:street":"Henri-Chapelle",
    "iso:country":"BE",
    "sg:address":"Village 22",
    "sg:city":"Welkenraedt (henri-chapelle)",
    "sg:classifiers":[
        {
            "category":"Bakery",
            "type":"Food & Drink"
        }
    ],
    "sg:phone":"+32 87 88 05 12",
    "sg:postcode":"4841",
    "sg:province":"Li\u00e8ge",
    "sg:tags":[
        "confectioner",
        "baker"
    ],
    "wof:name":"Instant Gourmand (l')",
    "wof:placetype":"venue"
},
  "geometry": {"coordinates":[5.9307432175,50.6771125793],"type":"Point"}
}