{
  "type": "Feature",
  "properties": {
    "addr:full":"Leuvensesteenweg 196 Zaventem Vlaams-Brabant 1932",
    "addr:housenumber":"196",
    "addr:postcode":"1932",
    "addr:street":"Leuvensesteenweg",
    "iso:country":"BE",
    "sg:address":"Leuvensesteenweg 196",
    "sg:city":"Zaventem",
    "sg:classifiers":[
        {
            "category":"Government",
            "subcategory":"Police Station",
            "type":"Public Place"
        }
    ],
    "sg:phone":"+32 2 720 30 56",
    "sg:postcode":"1932",
    "sg:province":"Vlaams-Brabant",
    "sg:tags":[
        "gendarmerie"
    ],
    "wof:name":"Federale Politie",
    "wof:placetype":"venue"
},
  "geometry": {"coordinates":[4.4675021172,50.8715705872],"type":"Point"}
}