{
  "type": "Feature",
  "properties": {
    "iso:country":"BE",
    "sg:address":"Melkerijstraat 39c",
    "sg:city":"Wachtebeke",
    "sg:orig_category":"Houtbewerking and -behandeling",
    "sg:phone":"+32 9 345 89 30",
    "sg:postcode":"9185",
    "sg:province":"Oost-Vlaanderen",
    "wof:name":"De Wulf Bosontginning",
    "wof:placetype":"venue"
},
  "geometry": {"coordinates":[3.8575849533,51.1760406494],"type":"Point"}
}