{
  "type": "Feature",
  "properties": {
    "iso:country":"BE",
    "sg:address":"Hertog Van Brabantlaan 17",
    "sg:city":"Landen",
    "sg:orig_category":"Diverse grafische activiteiten",
    "sg:phone":"+32 11 83 12 35",
    "sg:postcode":"3400",
    "sg:province":"Vlaams-Brabant",
    "wof:name":"Imago",
    "wof:placetype":"venue"
},
  "geometry": {"coordinates":[5.0835728645,50.7561645508],"type":"Point"}
}