{
  "type": "Feature",
  "properties": {
    "iso:country":"BE",
    "sg:address":"Chemin Du Bois-moulin 4",
    "sg:city":"Braine-le-chateau",
    "sg:orig_category":"Sportterreinen and installaties behalve sportcentra Tuinen",
    "sg:phone":"+32 2 366 31 31",
    "sg:postcode":"1440",
    "sg:province":"Brabant Wallon",
    "wof:name":"Poney Club Willems H.",
    "wof:placetype":"venue"
},
  "geometry": {"coordinates":[4.3225917816,50.6675338745],"type":"Point"}
}