{
  "type": "Feature",
  "properties": {
    "iso:country":"BE",
    "sg:address":"Leuvensesteenweg 510gb7",
    "sg:city":"Zaventem",
    "sg:classifiers":[
        {
            "category":"Government",
            "subcategory":"Fire Station",
            "type":"Public Place"
        }
    ],
    "sg:phone":"+32 2 712 12 12",
    "sg:postcode":"1930",
    "sg:province":"Vlaams-Brabant",
    "sg:tags":[
        "copier",
        "digital"
    ],
    "wof:name":"Ricoh Belgium Nv",
    "wof:placetype":"venue"
},
  "geometry": {"coordinates":[4.4801468849,50.8718414307],"type":"Point"}
}