{
  "type": "Feature",
  "properties": {
    "addr:full":"Dam 25 Izegem West-Vlaanderen 8870",
    "addr:housenumber":"25",
    "addr:postcode":"8870",
    "addr:street":"Dam",
    "iso:country":"BE",
    "sg:address":"Dam 25",
    "sg:city":"Izegem",
    "sg:classifiers":[
        {
            "category":"Professional",
            "subcategory":"Lawyer & Legal Services",
            "type":"Services"
        }
    ],
    "sg:phone":"+32 51 30 17 22",
    "sg:postcode":"8870",
    "sg:province":"West-Vlaanderen",
    "wof:name":"Vandromme Philippe",
    "wof:placetype":"venue"
},
  "geometry": {"coordinates":[3.2167470455,50.9241523743],"type":"Point"}
}