{
  "type": "Feature",
  "properties": {
    "iso:country":"BE",
    "sg:address":"Pachthofstraat 6",
    "sg:city":"Zaventem",
    "sg:classifiers":[
        {
            "category":"Insurance",
            "subcategory":"Life Insurance",
            "type":"Services"
        }
    ],
    "sg:phone":"+32 2 759 22 18",
    "sg:postcode":"1930",
    "sg:province":"Vlaams-Brabant",
    "sg:tags":[
        "assurance"
    ],
    "wof:name":"Bureau Vandersypen",
    "wof:placetype":"venue"
},
  "geometry": {"coordinates":[4.5051589012,50.8794784546],"type":"Point"}
}