{
  "type": "Feature",
  "properties": {
    "addr:full":"Rue D'enghien 43-1 Mons Hainaut 7000",
    "addr:housenumber":"43-1",
    "addr:postcode":"7000",
    "addr:street":"Rue D'Enghien;Hainaut",
    "iso:country":"BE",
    "sg:address":"Rue D'enghien 43-1",
    "sg:city":"Mons",
    "sg:classifiers":[
        {
            "category":"Arts & Performance",
            "subcategory":"Art Gallery",
            "type":"Entertainment"
        }
    ],
    "sg:phone":"+32 65 84 62 99",
    "sg:postcode":"7000",
    "sg:province":"Hainaut",
    "wof:name":"Galerie Du Dragon",
    "wof:placetype":"venue"
},
  "geometry": {"coordinates":[3.9506409168,50.4550628662],"type":"Point"}
}