{
  "type": "Feature",
  "properties": {
    "addr:full":"Rue Du Rixhon 38 Aywaille Li\u00e8ge 4920",
    "addr:housenumber":"38",
    "addr:postcode":"4920",
    "addr:street":"Rue Du Rixhon",
    "iso:country":"BE",
    "sg:address":"Rue Du Rixhon 38",
    "sg:city":"Aywaille",
    "sg:classifiers":[
        {
            "category":"Home & Garden",
            "subcategory":"Hardware",
            "type":"Retail Goods"
        }
    ],
    "sg:phone":"+32 86 43 35 66",
    "sg:postcode":"4920",
    "sg:province":"Li\u00e8ge",
    "sg:tags":[
        "quincailleries",
        "bois",
        "gr"
    ],
    "wof:name":"Sapin",
    "wof:placetype":"venue"
},
  "geometry": {"coordinates":[5.6782069206,50.4738540649],"type":"Point"}
}