{
  "type": "Feature",
  "properties": {
    "addr:full":"Chauss\u00c9e De Gand 409 Sint-jans-molenbeek/molenbeek- Bruxelles-Capitale 1080",
    "addr:housenumber":"409;/",
    "addr:postcode":"1080",
    "addr:street":"Chausse\u0301E De Gand;Sint-Jans-Molenbeek",
    "iso:country":"BE",
    "sg:address":"Chauss\u00c9e De Gand 409",
    "sg:city":"Sint-jans-molenbeek/molenbeek-",
    "sg:orig_category":"Industri\u00eble wasserijen and droogkuis",
    "sg:phone":"+32 2 414 10 02",
    "sg:postcode":"1080",
    "sg:province":"Bruxelles-Capitale",
    "wof:name":"Ipsomat",
    "wof:placetype":"venue"
},
  "geometry": {"coordinates":[4.3201179504,50.8576583862],"type":"Point"}
}