{
  "type": "Feature",
  "properties": {
    "addr:full":"Meensesteenweg 23 Moorslede West-Vlaanderen 8890",
    "addr:housenumber":"23",
    "addr:postcode":"8890",
    "addr:street":"Meensesteenweg",
    "iso:country":"BE",
    "sg:address":"Meensesteenweg 23",
    "sg:city":"Moorslede",
    "sg:orig_category":"R\u00e9cup\u00e9ration de mati\u00e8res m\u00e9talliques recyclables and d\u00e9molisseurs de voitures. V\u00e9hicules automobiles",
    "sg:phone":"+32 56 50 01 10",
    "sg:postcode":"8890",
    "sg:province":"West-Vlaanderen",
    "wof:name":"Emiel Gryspeerdt",
    "wof:placetype":"venue"
},
  "geometry": {"coordinates":[3.1136438847,50.8871231079],"type":"Point"}
}