{
  "type": "Feature",
  "properties": {
    "addr:full":"Avenue Joseph Jongen 7 Ukkel/uccle Bruxelles-Capitale 1180",
    "addr:housenumber":"7",
    "addr:postcode":"1180",
    "addr:street":"Avenue Joseph Jongen;/",
    "iso:country":"BE",
    "sg:address":"Avenue Joseph Jongen 7",
    "sg:city":"Ukkel/uccle",
    "sg:orig_category":"M\u00e9decins and sp\u00e9cialistes",
    "sg:phone":"+32 2 332 06 66",
    "sg:postcode":"1180",
    "sg:province":"Bruxelles-Capitale",
    "wof:name":"Daniel Burdet",
    "wof:placetype":"venue"
},
  "geometry": {"coordinates":[4.3300609589,50.8003425598],"type":"Point"}
}