{
  "type": "Feature",
  "properties": {
    "addr:full":"Steenaardestraat 41 Gent Oost-Vlaanderen 9051",
    "addr:housenumber":"41",
    "addr:postcode":"9051",
    "addr:street":"Steenaardestraat;Oost-Vlaanderen",
    "iso:country":"BE",
    "sg:address":"Steenaardestraat 41",
    "sg:city":"Gent",
    "sg:orig_category":"Artsen and specialisten",
    "sg:phone":"+32 9 220 84 44",
    "sg:postcode":"9051",
    "sg:province":"Oost-Vlaanderen",
    "wof:name":"Mieke Moerman",
    "wof:placetype":"venue"
},
  "geometry": {"coordinates":[3.6762259007,51.027179718],"type":"Point"}
}