{
  "type": "Feature",
  "properties": {
    "iso:country":"BE",
    "sg:address":"Neervenweg 153",
    "sg:city":"Wuustwezel",
    "sg:orig_category":"Eleveurs and marchands de porcs",
    "sg:phone":"+32 3 669 87 51",
    "sg:postcode":"2990",
    "sg:province":"Antwerpen",
    "wof:name":"Marc Gagelmans",
    "wof:placetype":"venue"
},
  "geometry": {"coordinates":[4.6416769028,51.3851356506],"type":"Point"}
}