{
  "type": "Feature",
  "properties": {
    "addr:full":"Rue De La Fus\u00c9e 100b12 Brussel/bruxelles Bruxelles-Capitale 1130",
    "addr:housenumber":"100b12",
    "addr:postcode":"1130",
    "addr:street":"Rue De La Fuse\u0301E;/",
    "iso:country":"BE",
    "sg:address":"Rue De La Fus\u00c9e 100b12",
    "sg:city":"Brussel/bruxelles",
    "sg:orig_category":"S\u00e9lection de personnel and placement",
    "sg:phone":"+32 2 726 16 98",
    "sg:postcode":"1130",
    "sg:province":"Bruxelles-Capitale",
    "wof:name":"Young Executive Recruit.",
    "wof:placetype":"venue"
},
  "geometry": {"coordinates":[4.4334049225,50.879535675],"type":"Point"}
}