{
  "type": "Feature",
  "properties": {
    "iso:country":"BE",
    "sg:address":"Biestebroekstraat 2a",
    "sg:city":"Anderlecht",
    "sg:orig_category":"Bouwmaterialen Gh Diverse bouwafwerking and reiniging Gespecialiseerde residenti\u00eble bouw Schoonmaakb",
    "sg:phone":"+32 2 523 01 28",
    "sg:postcode":"1070",
    "sg:province":"Bruxelles-Capitale",
    "wof:name":"Protector Belgium",
    "wof:placetype":"venue"
},
  "geometry": {"coordinates":[4.3159980774,50.8345870972],"type":"Point"}
}