{
  "type": "Feature",
  "properties": {
    "addr:full":"Rue De L'eglise 12 Faimes Li\u00e8ge 4317",
    "addr:housenumber":"12",
    "addr:postcode":"4317",
    "addr:street":"Rue De L'Eglise",
    "iso:country":"BE",
    "sg:address":"Rue De L'eglise 12",
    "sg:city":"Faimes",
    "sg:orig_category":"Produits surgel\u00e9s Gr",
    "sg:phone":"+32 19 32 23 28",
    "sg:postcode":"4317",
    "sg:province":"Li\u00e8ge",
    "wof:name":"Gersigel",
    "wof:placetype":"venue"
},
  "geometry": {"coordinates":[5.2433199883,50.6545410156],"type":"Point"}
}