{
  "type": "Feature",
  "properties": {
    "iso:country":"BE",
    "sg:address":"Route D'eeghez\u00c9e 219",
    "sg:city":"Jemeppe-sur-sambre",
    "sg:orig_category":"Gespecialiseerde niet-residenti\u00eble bouw",
    "sg:phone":"+32 71 78 66 24",
    "sg:postcode":"5190",
    "sg:province":"Namur",
    "wof:name":"Bulon",
    "wof:placetype":"venue"
},
  "geometry": {"coordinates":[4.6703400612,50.4645004272],"type":"Point"}
}