{
  "type": "Feature",
  "properties": {
    "addr:full":"Rue Du Ch\u00cane 168 Chapelle-lez-herlaimont Hainaut 7160",
    "addr:housenumber":"168",
    "addr:postcode":"7160",
    "addr:street":"Rue Du Che\u0302Ne",
    "iso:country":"BE",
    "sg:address":"Rue Du Ch\u00cane 168",
    "sg:city":"Chapelle-lez-herlaimont",
    "sg:orig_category":"Dierenartsen Rundveehouders",
    "sg:phone":"+32 64 44 21 43",
    "sg:postcode":"7160",
    "sg:province":"Hainaut",
    "wof:name":"Pierre Felix",
    "wof:placetype":"venue"
},
  "geometry": {"coordinates":[4.2753372192,50.4769973755],"type":"Point"}
}