{
  "type": "Feature",
  "properties": {
    "addr:full":"Langemuntstraat 15 Ninove Oost-Vlaanderen 9400",
    "addr:housenumber":"15",
    "addr:postcode":"9400",
    "addr:street":"Langemuntstraat",
    "iso:country":"BE",
    "sg:address":"Langemuntstraat 15",
    "sg:city":"Ninove",
    "sg:classifiers":[
        {
            "category":"Professional",
            "subcategory":"Art Services",
            "type":"Services"
        }
    ],
    "sg:phone":"+32 473 48 47 36",
    "sg:postcode":"9400",
    "sg:province":"Oost-Vlaanderen",
    "sg:tags":[
        "photography",
        "reporting",
        "-"
    ],
    "wof:name":"Fotohuis-olivier Corthals",
    "wof:placetype":"venue"
},
  "geometry": {"coordinates":[4.022649765,50.8353004456],"type":"Point"}
}