{
  "type": "Feature",
  "properties": {
    "addr:full":"Bilzersteenweg 43 Riemst Limburg 3770",
    "addr:housenumber":"43",
    "addr:postcode":"3770",
    "addr:street":"Bilzersteenweg",
    "iso:country":"BE",
    "sg:address":"Bilzersteenweg 43",
    "sg:city":"Riemst",
    "sg:classifiers":[
        {
            "category":"Building & Trades",
            "subcategory":"Construction",
            "type":"Services"
        }
    ],
    "sg:phone":"+32 12 44 14 44",
    "sg:postcode":"3770",
    "sg:province":"Limburg",
    "sg:tags":[
        "roofing",
        "material",
        "-"
    ],
    "wof:name":"G.v. Products Nv",
    "wof:placetype":"venue"
},
  "geometry": {"coordinates":[5.5919260979,50.8159942627],"type":"Point"}
}