{
  "type": "Feature",
  "properties": {
    "addr:full":"Hannekestraat 1 Dessel Antwerpen 2480",
    "addr:housenumber":"1",
    "addr:postcode":"2480",
    "addr:street":"Hannekestraat",
    "iso:country":"BE",
    "sg:address":"Hannekestraat 1",
    "sg:city":"Dessel",
    "sg:orig_category":"Overheidsdiensten",
    "sg:phone":"+32 14 37 14 82",
    "sg:postcode":"2480",
    "sg:province":"Antwerpen",
    "wof:name":"O.c.m.w.",
    "wof:placetype":"venue"
},
  "geometry": {"coordinates":[5.1124129295,51.2392272949],"type":"Point"}
}