{
  "type": "Feature",
  "properties": {
    "iso:country":"BE",
    "sg:address":"All\u00e9e Des Moutons 102",
    "sg:city":"Bruxelles",
    "sg:classifiers":[
        {
            "category":"Health Services",
            "subcategory":"Health Practitioner",
            "type":"Services"
        }
    ],
    "sg:phone":"+32 2 268 38 63",
    "sg:postcode":"1020",
    "sg:province":"Bruxelles-Capitale",
    "sg:tags":[
        "psychologist"
    ],
    "wof:name":"Nadine Lefevre",
    "wof:placetype":"venue"
},
  "geometry": {"coordinates":[4.3676800728,50.899684906],"type":"Point"}
}