{
  "type": "Feature",
  "properties": {
    "iso:country":"BE",
    "sg:address":"Sint-jozefstraat 32",
    "sg:city":"Roeselare",
    "sg:orig_category":"Animations diverses",
    "sg:phone":"+32 51 22 83 61",
    "sg:postcode":"8800",
    "sg:province":"West-Vlaanderen",
    "wof:name":"Gcv Bjorn Thienpont & Co",
    "wof:placetype":"venue"
},
  "geometry": {"coordinates":[3.1195690632,50.937713623],"type":"Point"}
}