{
  "type": "Feature",
  "properties": {
    "addr:full":"Clos De La Ballade 1 Bruxelles (evere) Bruxelles-Capitale 1140",
    "addr:housenumber":"1",
    "addr:postcode":"1140",
    "addr:street":"Clos De La Ballade",
    "iso:country":"BE",
    "sg:address":"Clos De La Ballade 1",
    "sg:city":"Bruxelles (evere)",
    "sg:classifiers":[
        {
            "category":"Health Services",
            "subcategory":"Health Practitioner",
            "type":"Services"
        }
    ],
    "sg:phone":"+32 2 770 92 07",
    "sg:postcode":"1140",
    "sg:province":"Bruxelles-Capitale",
    "sg:tags":[
        "physiotherapist"
    ],
    "wof:name":"Cocq Ch",
    "wof:placetype":"venue"
},
  "geometry": {"coordinates":[4.407020092,50.8589630127],"type":"Point"}
}