{
  "type": "Feature",
  "properties": {
    "addr:full":"Stationsstraat 81 Hooglede West-Vlaanderen 8830",
    "addr:housenumber":"81",
    "addr:postcode":"8830",
    "addr:street":"Stationsstraat",
    "iso:country":"BE",
    "sg:address":"Stationsstraat 81",
    "sg:city":"Hooglede",
    "sg:orig_category":"Instituts de beaut\u00e9. Salons de coiffure",
    "sg:phone":"+32 51 22 93 56",
    "sg:postcode":"8830",
    "sg:province":"West-Vlaanderen",
    "wof:name":"Kapsalon Kris",
    "wof:placetype":"venue"
},
  "geometry": {"coordinates":[3.1036479473,50.9974365234],"type":"Point"}
}