{
  "type": "Feature",
  "properties": {
    "iso:country":"BE",
    "sg:address":"Boulevard Des Arts 80",
    "sg:city":"Seraing",
    "sg:orig_category":"Apotheken",
    "sg:phone":"+32 4 336 38 57",
    "sg:postcode":"4102",
    "sg:province":"Li\u00e8ge",
    "wof:name":"Pharmacie Du Peuple",
    "wof:placetype":"venue"
},
  "geometry": {"coordinates":[5.5383238792,50.5913658142],"type":"Point"}
}