{
  "type": "Feature",
  "properties": {
    "addr:full":"Hofstraat 84 Brasschaat Antwerpen 2930",
    "addr:housenumber":"84",
    "addr:postcode":"2930",
    "addr:street":"Hofstraat",
    "iso:country":"BE",
    "sg:address":"Hofstraat 84",
    "sg:city":"Brasschaat",
    "sg:classifiers":[
        {
            "category":"Social Services",
            "subcategory":"Job Training",
            "type":"Services"
        }
    ],
    "sg:phone":"+32 3 651 83 49",
    "sg:postcode":"2930",
    "sg:province":"Antwerpen",
    "sg:tags":[
        "paper",
        "machinery",
        "working",
        "cardboard"
    ],
    "wof:name":"Leyssens Alu-papier",
    "wof:placetype":"venue"
},
  "geometry": {"coordinates":[4.4884228706,51.2919006348],"type":"Point"}
}