{
  "type": "Feature",
  "properties": {
    "addr:full":"Avenue Des Croix De Guerre 350 Bruxelles Bruxelles-Capitale 1120",
    "addr:housenumber":"350",
    "addr:postcode":"1120",
    "addr:street":"Avenue Des Croix De Guerre",
    "iso:country":"BE",
    "sg:address":"Avenue Des Croix De Guerre 350",
    "sg:city":"Bruxelles",
    "sg:classifiers":[
        {
            "category":"Building & Trades",
            "subcategory":"Landscaping Services",
            "type":"Services"
        }
    ],
    "sg:phone":"+32 2 268 66 46",
    "sg:postcode":"1120",
    "sg:province":"Bruxelles-Capitale",
    "sg:tags":[
        "gardening",
        "garden",
        "maintenance"
    ],
    "wof:name":"Entreprise Van Nedervelde",
    "wof:placetype":"venue"
},
  "geometry": {"coordinates":[4.3925261497,50.8959503174],"type":"Point"}
}