{
  "type": "Feature",
  "properties": {
    "addr:full":"Rue Dupont 18 Marche-en-famenne Luxembourg 6900",
    "addr:housenumber":"18",
    "addr:postcode":"6900",
    "addr:street":"Rue Dupont",
    "iso:country":"BE",
    "sg:address":"Rue Dupont 18",
    "sg:city":"Marche-en-famenne",
    "sg:classifiers":[
        {
            "category":"Shopping",
            "subcategory":"Optician",
            "type":"Retail Goods"
        }
    ],
    "sg:phone":"+32 84 31 14 76",
    "sg:postcode":"6900",
    "sg:province":"Luxembourg",
    "sg:tags":[
        "-"
    ],
    "wof:name":"Optique Timerman Tony",
    "wof:placetype":"venue"
},
  "geometry": {"coordinates":[5.3433318138,50.2281150818],"type":"Point"}
}