{
  "type": "Feature",
  "properties": {
    "addr:full":"Adolf Baeyensstraat 49 Sint-amandsberg Oost-Vlaanderen 9040",
    "addr:housenumber":"49",
    "addr:postcode":"9040",
    "addr:street":"Baeyensstraat",
    "iso:country":"BE",
    "sg:address":"Adolf Baeyensstraat 49",
    "sg:city":"Sint-amandsberg",
    "sg:orig_category":"Advocaten and juridische adviseurs Balie van Gent",
    "sg:phone":"+32 9 219 02 90",
    "sg:postcode":"9040",
    "sg:province":"Oost-Vlaanderen",
    "wof:name":"Sirejacob Yves",
    "wof:placetype":"venue"
},
  "geometry": {"coordinates":[3.7522621155,51.0562057495],"type":"Point"}
}