{
  "type": "Feature",
  "properties": {
    "iso:country":"BE",
    "sg:address":"Avenue Notre-dame De Foy 4",
    "sg:city":"Florennes",
    "sg:classifiers":[
        {
            "category":"Health Services",
            "subcategory":"Health Practitioner",
            "type":"Services"
        }
    ],
    "sg:phone":"+32 71 68 70 96",
    "sg:postcode":"5620",
    "sg:province":"Namur",
    "sg:tags":[
        "physiotherapist"
    ],
    "wof:name":"Lechat A",
    "wof:placetype":"venue"
},
  "geometry": {"coordinates":[4.6067681313,50.2464981079],"type":"Point"}
}