{
  "type": "Feature",
  "properties": {
    "addr:full":"Nekkersput 15 Ninove (pollare) Oost-Vlaanderen 9401",
    "addr:housenumber":"15",
    "addr:postcode":"9401",
    "addr:street":"Nekkersput",
    "iso:country":"BE",
    "sg:address":"Nekkersput 15",
    "sg:city":"Ninove (pollare)",
    "sg:classifiers":[
        {
            "category":"Professional",
            "subcategory":"Accounting & Tax Preparation",
            "type":"Services"
        }
    ],
    "sg:phone":"+32 54 33 62 87",
    "sg:postcode":"9401",
    "sg:province":"Oost-Vlaanderen",
    "sg:tags":[
        "accountant"
    ],
    "wof:name":"Brysse J",
    "wof:placetype":"venue"
},
  "geometry": {"coordinates":[4.0013818741,50.819984436],"type":"Point"}
}