{
  "type": "Feature",
  "properties": {
    "iso:country":"BE",
    "sg:address":"Ieperstraat 210",
    "sg:city":"Wevelgem (moorsele)",
    "sg:classifiers":[
        {
            "category":"Wholesale",
            "subcategory":"Plants",
            "type":"Manufacturing & Wholesale Goods"
        }
    ],
    "sg:phone":"+32 56 50 10 98",
    "sg:postcode":"8560",
    "sg:province":"West-Vlaanderen",
    "sg:tags":[
        "decoration",
        "flower",
        "-"
    ],
    "wof:name":"Bloemencreaties Stefanie",
    "wof:placetype":"venue"
},
  "geometry": {"coordinates":[3.1087899208,50.8370018005],"type":"Point"}
}