{
  "type": "Feature",
  "properties": {
    "addr:full":"Avenue De La Gare 140 Grace-hollogne Li\u00e8ge 4460",
    "addr:housenumber":"140",
    "addr:postcode":"4460",
    "addr:street":"Avenue De La Gare",
    "iso:country":"BE",
    "sg:address":"Avenue De La Gare 140",
    "sg:city":"Grace-hollogne",
    "sg:orig_category":"Installatie van houten of kunststof schrijnwerk Woningbouw",
    "sg:phone":"+32 4 250 31 75",
    "sg:postcode":"4460",
    "sg:province":"Li\u00e8ge",
    "wof:name":"Philippe Cabay",
    "wof:placetype":"venue"
},
  "geometry": {"coordinates":[5.4507031441,50.6549720764],"type":"Point"}
}