{
  "type": "Feature",
  "properties": {
    "iso:country":"BE",
    "sg:address":"Nestor De Ti\u00c8restraat 35",
    "sg:city":"Aalst",
    "sg:orig_category":"Jardinage. D\u00e9corateurs d'int\u00e9rieur",
    "sg:phone":"+32 53 77 81 32",
    "sg:postcode":"9300",
    "sg:province":"Oost-Vlaanderen",
    "wof:name":"Landscape & Townscape",
    "wof:placetype":"venue"
},
  "geometry": {"coordinates":[4.0323758125,50.9403076172],"type":"Point"}
}