{
  "type": "Feature",
  "properties": {
    "iso:country":"BE",
    "sg:address":"Bovenlinde 17",
    "sg:city":"Peer",
    "sg:orig_category":"Meubelzaken, woning- and keukeninrichting",
    "sg:phone":"+32 11 79 15 34",
    "sg:postcode":"3990",
    "sg:province":"Limburg",
    "wof:name":"Levi Dubrulle",
    "wof:placetype":"venue"
},
  "geometry": {"coordinates":[5.444466114,51.0829772949],"type":"Point"}
}