{
  "type": "Feature",
  "properties": {
    "addr:full":"Otegemplaats 6 Zwevegem (otegem) West-Vlaanderen 8553",
    "addr:housenumber":"6",
    "addr:postcode":"8553",
    "addr:street":"Otegemplaats",
    "iso:country":"BE",
    "sg:address":"Otegemplaats 6",
    "sg:city":"Zwevegem (otegem)",
    "sg:classifiers":[
        {
            "category":"Shopping",
            "subcategory":"Computers & Home Electronics",
            "type":"Retail Goods"
        }
    ],
    "sg:phone":"+32 56 77 78 97",
    "sg:postcode":"8553",
    "sg:province":"West-Vlaanderen",
    "sg:tags":[
        "-",
        "television",
        "radio"
    ],
    "wof:name":"T'joens M",
    "wof:placetype":"venue"
},
  "geometry": {"coordinates":[3.4233999252,50.8082771301],"type":"Point"}
}