{
  "type": "Feature",
  "properties": {
    "addr:full":"Merksemsebaan 63 Wijnegem Antwerpen 2110",
    "addr:housenumber":"63",
    "addr:postcode":"2110",
    "addr:street":"Merksemsebaan",
    "iso:country":"BE",
    "sg:address":"Merksemsebaan 63",
    "sg:city":"Wijnegem",
    "sg:orig_category":"Brood, gebak and snoepgoed",
    "sg:phone":"+32 3 354 26 16",
    "sg:postcode":"2110",
    "sg:province":"Antwerpen",
    "wof:name":"Bakkerij Deera",
    "wof:placetype":"venue"
},
  "geometry": {"coordinates":[4.5148792267,51.2286453247],"type":"Point"}
}