{
  "type": "Feature",
  "properties": {
    "addr:full":"Molenstraat 36 Aalst Oost-Vlaanderen 9300",
    "addr:housenumber":"36",
    "addr:postcode":"9300",
    "addr:street":"Molenstraat",
    "iso:country":"BE",
    "sg:address":"Molenstraat 36",
    "sg:city":"Aalst",
    "sg:orig_category":"V\u00eatements pour Hommes",
    "sg:phone":"+32 53 77 59 84",
    "sg:postcode":"9300",
    "sg:province":"Oost-Vlaanderen",
    "wof:name":"Huis Suvretta",
    "wof:placetype":"venue"
},
  "geometry": {"coordinates":[4.0411567688,50.939201355],"type":"Point"}
}