{
  "type": "Feature",
  "properties": {
    "iso:country":"BE",
    "sg:address":"Diepestraat 130",
    "sg:city":"Antwerpen",
    "sg:orig_category":"V\u00eatements pour Hommes. V\u00eatements pour Dames",
    "sg:phone":"+32 3 272 34 41",
    "sg:postcode":"2060",
    "sg:province":"Antwerpen",
    "wof:name":"Clodagh Fashion",
    "wof:placetype":"venue"
},
  "geometry": {"coordinates":[4.4256491661,51.2224769592],"type":"Point"}
}