{
  "type": "Feature",
  "properties": {
    "addr:full":"Rue De L'ecuyer 37 Brussel/bruxelles Bruxelles-Capitale 1000",
    "addr:housenumber":"37",
    "addr:postcode":"1000",
    "addr:street":"Rue De L'Ecuyer;/",
    "iso:country":"BE",
    "sg:address":"Rue De L'ecuyer 37",
    "sg:city":"Brussel/bruxelles",
    "sg:orig_category":"Activit\u00e9s diverses d'imprimerie",
    "sg:phone":"+32 2 511 64 22",
    "sg:postcode":"1000",
    "sg:province":"Bruxelles-Capitale",
    "wof:name":"Geluck Suykens & Partners",
    "wof:placetype":"venue"
},
  "geometry": {"coordinates":[4.3544287682,50.8488311768],"type":"Point"}
}