{
  "type": "Feature",
  "properties": {
    "addr:full":"Torhoutsesteenweg 101 Zedelgem (loppem) West-Vlaanderen 8210",
    "addr:housenumber":"101",
    "addr:postcode":"8210",
    "addr:street":"Torhoutsesteenweg",
    "iso:country":"BE",
    "sg:address":"Torhoutsesteenweg 101",
    "sg:city":"Zedelgem (loppem)",
    "sg:classifiers":[
        {
            "category":"Home & Garden",
            "subcategory":"Home Furnishings",
            "type":"Retail Goods"
        }
    ],
    "sg:phone":"+32 50 82 77 74",
    "sg:postcode":"8210",
    "sg:province":"West-Vlaanderen",
    "sg:tags":[
        "interior",
        "decoration"
    ],
    "wof:name":"Naeyaert P",
    "wof:placetype":"venue"
},
  "geometry": {"coordinates":[3.1576468945,51.1365127563],"type":"Point"}
}