{
  "type": "Feature",
  "properties": {
    "iso:country":"BE",
    "sg:address":"Justitiestraat 43",
    "sg:city":"Antwerpen",
    "sg:classifiers":[
        {
            "category":"Travel",
            "subcategory":"Resort",
            "type":"Entertainment"
        }
    ],
    "sg:phone":"+32 3 248 15 39",
    "sg:postcode":"2018",
    "sg:province":"Antwerpen",
    "sg:tags":[
        "farm",
        "house",
        "holiday",
        "guest"
    ],
    "wof:name":"Ribbens-engelen",
    "wof:placetype":"venue"
},
  "geometry": {"coordinates":[4.4053421021,51.2086982727],"type":"Point"}
}