{
  "type": "Feature",
  "properties": {
    "iso:country":"BE",
    "sg:address":"Groteheide 17",
    "sg:city":"Neerpelt",
    "sg:orig_category":"M\u00e9decins and sp\u00e9cialistes",
    "sg:phone":"+32 11 64 57 19",
    "sg:postcode":"3910",
    "sg:province":"Limburg",
    "wof:name":"Alain Vanpeperstraete",
    "wof:placetype":"venue"
},
  "geometry": {"coordinates":[5.437210083,51.2591285706],"type":"Point"}
}