{
  "type": "Feature",
  "properties": {
    "addr:full":"Chauss\u00e9e De Nivelles 207 Genappe (loupoigne) Brabant Wallon 1471",
    "addr:housenumber":"207",
    "addr:postcode":"1471",
    "addr:street":"Chausse\u0301E De Nivelles",
    "iso:country":"BE",
    "sg:address":"Chauss\u00e9e De Nivelles 207",
    "sg:city":"Genappe (loupoigne)",
    "sg:classifiers":[
        {
            "category":"Building & Trades",
            "subcategory":"Landscaping Services",
            "type":"Services"
        }
    ],
    "sg:phone":"+32 67 79 01 98",
    "sg:postcode":"1471",
    "sg:province":"Brabant Wallon",
    "sg:tags":[
        "gardening",
        "garden",
        "maintenance"
    ],
    "wof:name":"Van Deuren Ch",
    "wof:placetype":"venue"
},
  "geometry": {"coordinates":[4.4184560776,50.6037750244],"type":"Point"}
}