{
  "type": "Feature",
  "properties": {
    "addr:full":"Rue Grande 21 Erezee Luxembourg 6997",
    "addr:housenumber":"21",
    "addr:postcode":"6997",
    "addr:street":"Rue Grande",
    "iso:country":"BE",
    "sg:address":"Rue Grande 21",
    "sg:city":"Erezee",
    "sg:orig_category":"Elektrische installaties voor woningen",
    "sg:phone":"+32 86 47 74 74",
    "sg:postcode":"6997",
    "sg:province":"Luxembourg",
    "wof:name":"Clavier A.",
    "wof:placetype":"venue"
},
  "geometry": {"coordinates":[5.5379600525,50.2919311523],"type":"Point"}
}