{
  "type": "Feature",
  "properties": {
    "iso:country":"BE",
    "sg:address":"Vuilewaasstraat 13",
    "sg:city":"Zonnebeke",
    "sg:classifiers":[
        {
            "category":"Personal",
            "subcategory":"Beauty Salon",
            "type":"Services"
        }
    ],
    "sg:phone":"+32 57 46 67 05",
    "sg:postcode":"8980",
    "sg:province":"West-Vlaanderen",
    "sg:tags":[
        "de",
        "coiffure"
    ],
    "wof:name":"Coiffure Annie",
    "wof:placetype":"venue"
},
  "geometry": {"coordinates":[3.022233963,50.8453941345],"type":"Point"}
}