{
  "type": "Feature",
  "properties": {
    "addr:full":"Avenue Alfred Solvay 4 Bruxelles (watermael-boitsfort) Bruxelles-Capitale 1170",
    "addr:housenumber":"4",
    "addr:postcode":"1170",
    "addr:street":"Avenue Alfred Solvay",
    "iso:country":"BE",
    "sg:address":"Avenue Alfred Solvay 4",
    "sg:city":"Bruxelles (watermael-boitsfort)",
    "sg:classifiers":[
        {
            "category":"Education",
            "subcategory":"School",
            "type":"Public Place"
        }
    ],
    "sg:phone":"+32 2 663 82 90",
    "sg:postcode":"1170",
    "sg:province":"Bruxelles-Capitale",
    "sg:tags":[
        "secondary"
    ],
    "wof:name":"Institut De L'assomption",
    "wof:placetype":"venue"
},
  "geometry": {"coordinates":[4.4181699753,50.8094024658],"type":"Point"}
}