{
  "type": "Feature",
  "properties": {
    "iso:country":"BE",
    "sg:address":"Rue De La Technologie 61",
    "sg:city":"Bruxelles (berchem-sainte-agathe)",
    "sg:classifiers":[
        {
            "category":"Utilities",
            "subcategory":"Telephone",
            "type":"Services"
        }
    ],
    "sg:phone":"+32 2 464 29 50",
    "sg:postcode":"1082",
    "sg:province":"Bruxelles-Capitale",
    "sg:tags":[
        "-",
        "internet"
    ],
    "wof:name":"Arbalet Sa",
    "wof:placetype":"venue"
},
  "geometry": {"coordinates":[4.2918248177,50.8742828369],"type":"Point"}
}