{
  "type": "Feature",
  "properties": {
    "addr:full":"Avenue De Luxembourg 7 Arlon Luxembourg 6700",
    "addr:housenumber":"7",
    "addr:postcode":"6700",
    "addr:street":"Avenue De Luxembourg",
    "iso:country":"BE",
    "sg:address":"Avenue De Luxembourg 7",
    "sg:city":"Arlon",
    "sg:classifiers":[
        {
            "category":"Real Estate",
            "subcategory":"Architect",
            "type":"Services"
        }
    ],
    "sg:phone":"+32 63 22 35 22",
    "sg:postcode":"6700",
    "sg:province":"Luxembourg",
    "wof:name":"Claisse J",
    "wof:placetype":"venue"
},
  "geometry": {"coordinates":[5.8220582008,49.6776504517],"type":"Point"}
}