{
  "type": "Feature",
  "properties": {
    "addr:full":"Grote Baan 42 Herk-de-stad Limburg 3540",
    "addr:housenumber":"42",
    "addr:postcode":"3540",
    "addr:street":"Grote Baan",
    "iso:country":"BE",
    "sg:address":"Grote Baan 42",
    "sg:city":"Herk-de-stad",
    "sg:orig_category":"Bloemen and planten Tuinbenodigdheden Verlichting and huishoudartikelen",
    "sg:phone":"+32 13 44 17 06",
    "sg:postcode":"3540",
    "sg:province":"Limburg",
    "wof:name":"Bloemenboetiek",
    "wof:placetype":"venue"
},
  "geometry": {"coordinates":[5.1506409645,50.9437484741],"type":"Point"}
}