{
  "type": "Feature",
  "properties": {
    "addr:full":"Boulevard Saint-michel 28 Bruxelles (etterbeek) Bruxelles-Capitale 1040",
    "addr:housenumber":"28",
    "addr:postcode":"1040",
    "addr:street":"Boulevard Saint-Michel",
    "iso:country":"BE",
    "sg:address":"Boulevard Saint-michel 28",
    "sg:city":"Bruxelles (etterbeek)",
    "sg:classifiers":[
        {
            "category":"Professional",
            "subcategory":"Management & Consulting",
            "type":"Services"
        }
    ],
    "sg:phone":"+32 2 733 83 87",
    "sg:postcode":"1040",
    "sg:province":"Bruxelles-Capitale",
    "sg:tags":[
        "-",
        "processing",
        "data",
        "consultant"
    ],
    "wof:name":"Mainsys Engineering",
    "wof:placetype":"venue"
},
  "geometry": {"coordinates":[4.406047821,50.8336639404],"type":"Point"}
}