{
  "type": "Feature",
  "properties": {
    "addr:full":"Kerkweg 2 Boortmeerbeek Vlaams-Brabant 3190",
    "addr:housenumber":"2",
    "addr:postcode":"3190",
    "addr:street":"Kerkweg",
    "iso:country":"BE",
    "sg:address":"Kerkweg 2",
    "sg:city":"Boortmeerbeek",
    "sg:classifiers":[
        {
            "category":"Professional",
            "subcategory":"Accounting & Tax Preparation",
            "type":"Services"
        }
    ],
    "sg:phone":"+32 15 51 88 28",
    "sg:postcode":"3190",
    "sg:province":"Vlaams-Brabant",
    "sg:tags":[
        "accountant"
    ],
    "wof:name":"Engels D",
    "wof:placetype":"venue"
},
  "geometry": {"coordinates":[4.5693907738,50.9818344116],"type":"Point"}
}