{
  "type": "Feature",
  "properties": {
    "addr:full":"Boskant 102 Lille Antwerpen 2275",
    "addr:housenumber":"102",
    "addr:postcode":"2275",
    "addr:street":"Boskant",
    "iso:country":"BE",
    "sg:address":"Boskant 102",
    "sg:city":"Lille",
    "sg:orig_category":"Sportclubs Sportterreinen and installaties behalve sportcentra",
    "sg:phone":"+32 14 88 19 88",
    "sg:postcode":"2275",
    "sg:province":"Antwerpen",
    "wof:name":"K. Tubantia Borgerhout Vk",
    "wof:placetype":"venue"
},
  "geometry": {"coordinates":[4.8160071373,51.2477455139],"type":"Point"}
}