{
  "type": "Feature",
  "properties": {
    "addr:full":"Wolvertemsesteenweg 184 Merchtem Vlaams-Brabant 1785",
    "addr:housenumber":"184",
    "addr:postcode":"1785",
    "addr:street":"Wolvertemsesteenweg",
    "iso:country":"BE",
    "sg:address":"Wolvertemsesteenweg 184",
    "sg:city":"Merchtem",
    "sg:orig_category":"Articles de jardin. Fleurs and plantes",
    "sg:phone":"+32 52 37 29 13",
    "sg:postcode":"1785",
    "sg:province":"Vlaams-Brabant",
    "wof:name":"Paul Vermeir",
    "wof:placetype":"venue"
},
  "geometry": {"coordinates":[4.2588877678,50.9541664124],"type":"Point"}
}