{
  "type": "Feature",
  "properties": {
    "iso:country":"BE",
    "sg:address":"Rue Du Chauny 3",
    "sg:city":"Frasnes-lez-anvaing",
    "sg:orig_category":"Rundveehouders",
    "sg:phone":"+32 69 85 91 91",
    "sg:postcode":"7910",
    "sg:province":"Hainaut",
    "wof:name":"Robert Loosfeldt",
    "wof:placetype":"venue"
},
  "geometry": {"coordinates":[3.5159170628,50.6950645447],"type":"Point"}
}