{
  "type": "Feature",
  "properties": {
    "addr:full":"Rue De L'ev\u00cach\u00c9 1 Nivelles Brabant Wallon 1400",
    "addr:housenumber":"1",
    "addr:postcode":"1400",
    "addr:street":"Rue De L'Eve \u0302Che\u0301",
    "iso:country":"BE",
    "sg:address":"Rue De L'ev\u00cach\u00c9 1",
    "sg:city":"Nivelles",
    "sg:orig_category":"Librairies",
    "sg:phone":"+32 67 84 21 36",
    "sg:postcode":"1400",
    "sg:province":"Brabant Wallon",
    "wof:name":"Mission B.d.",
    "wof:placetype":"venue"
},
  "geometry": {"coordinates":[4.3258690834,50.5980758667],"type":"Point"}
}