{
  "type": "Feature",
  "properties": {
    "iso:country":"BE",
    "sg:address":"Rue J. Bondas 24",
    "sg:city":"Seraing (jemeppe-sur-meuse)",
    "sg:classifiers":[
        {
            "category":"Health Services",
            "subcategory":"Health Practitioner",
            "type":"Services"
        }
    ],
    "sg:phone":"+32 4 233 84 99",
    "sg:postcode":"4101",
    "sg:province":"Li\u00e8ge",
    "sg:tags":[
        "physiotherapist"
    ],
    "wof:name":"Bruy\u00e8re J",
    "wof:placetype":"venue"
},
  "geometry": {"coordinates":[5.4907960892,50.6223945618],"type":"Point"}
}