{
  "type": "Feature",
  "properties": {
    "addr:full":"Oude Beukenstraat 1 Buggenhout Oost-Vlaanderen 9255",
    "addr:housenumber":"1",
    "addr:postcode":"9255",
    "addr:street":"Oude Beukenstraat",
    "iso:country":"BE",
    "sg:address":"Oude Beukenstraat 1",
    "sg:city":"Buggenhout",
    "sg:orig_category":"Rundveehouders",
    "sg:phone":"+32 52 33 12 73",
    "sg:postcode":"9255",
    "sg:province":"Oost-Vlaanderen",
    "wof:name":"Paul Tilley",
    "wof:placetype":"venue"
},
  "geometry": {"coordinates":[4.1815671921,51.0096473694],"type":"Point"}
}