{
  "type": "Feature",
  "properties": {
    "addr:full":"Joe Englishstraat 33 Roeselare (rumbeke) West-Vlaanderen 8800",
    "addr:housenumber":"33",
    "addr:postcode":"8800",
    "addr:street":"Joe Englishstraat",
    "iso:country":"BE",
    "sg:address":"Joe Englishstraat 33",
    "sg:city":"Roeselare (rumbeke)",
    "sg:classifiers":[
        {
            "category":"Professional",
            "subcategory":"Accounting & Tax Preparation",
            "type":"Services"
        }
    ],
    "sg:phone":"+32 51 20 09 93",
    "sg:postcode":"8800",
    "sg:province":"West-Vlaanderen",
    "sg:tags":[
        "bookkeeper"
    ],
    "wof:name":"Lintermans D",
    "wof:placetype":"venue"
},
  "geometry": {"coordinates":[3.1637570858,50.9294776917],"type":"Point"}
}