{
  "type": "Feature",
  "properties": {
    "iso:country":"BE",
    "sg:address":"Beelshoek 38",
    "sg:city":"Ingelmunster",
    "sg:orig_category":"Woningbouw",
    "sg:phone":"+32 56 66 57 31",
    "sg:postcode":"8770",
    "sg:province":"West-Vlaanderen",
    "wof:name":"Bart Vanhee",
    "wof:placetype":"venue"
},
  "geometry": {"coordinates":[3.2919299603,50.9200820923],"type":"Point"}
}