{
  "type": "Feature",
  "properties": {
    "iso:country":"BE",
    "sg:address":"Albert Scheuremanspark 24",
    "sg:city":"Zedelgem",
    "sg:orig_category":"Installation de menuiserie en bois and plastique. Construction industrielle and commerciale",
    "sg:phone":"+32 50 84 20 24",
    "sg:postcode":"8210",
    "sg:province":"West-Vlaanderen",
    "wof:name":"Procon",
    "wof:placetype":"venue"
},
  "geometry": {"coordinates":[3.1458399296,51.1376457214],"type":"Point"}
}