{
  "type": "Feature",
  "properties": {
    "addr:full":"Nieuwstraat 28 Haacht Vlaams-Brabant 3150",
    "addr:housenumber":"28",
    "addr:postcode":"3150",
    "addr:street":"Nieuwstraat",
    "iso:country":"BE",
    "sg:address":"Nieuwstraat 28",
    "sg:city":"Haacht",
    "sg:orig_category":"Tweedehandsgoederen",
    "sg:phone":"+32 16 61 81 20",
    "sg:postcode":"3150",
    "sg:province":"Vlaams-Brabant",
    "wof:name":"Spit",
    "wof:placetype":"venue"
},
  "geometry": {"coordinates":[4.6380047798,50.9768714905],"type":"Point"}
}