{
  "type": "Feature",
  "properties": {
    "addr:full":"Jonkerweg 5 Loenhout Antwerpen 2990",
    "addr:housenumber":"5",
    "addr:postcode":"2990",
    "addr:street":"Jonkerweg",
    "iso:country":"BE",
    "sg:address":"Jonkerweg 5",
    "sg:city":"Loenhout",
    "sg:orig_category":"Services pour animaux domestiques",
    "sg:phone":"+32 3 669 50 65",
    "sg:postcode":"2990",
    "sg:province":"Antwerpen",
    "wof:name":"Dierenhotel Popendonk",
    "wof:placetype":"venue"
},
  "geometry": {"coordinates":[4.6628842354,51.4098548889],"type":"Point"}
}