{
  "type": "Feature",
  "properties": {
    "addr:full":"Neutralstrasse 84 Lontzen Li\u00e8ge 4710",
    "addr:housenumber":"84",
    "addr:postcode":"4710",
    "addr:street":"Neutralstrasse",
    "iso:country":"BE",
    "sg:address":"Neutralstrasse 84",
    "sg:city":"Lontzen",
    "sg:classifiers":[
        {
            "category":"Shopping",
            "subcategory":"Florist",
            "type":"Retail Goods"
        }
    ],
    "sg:phone":"+32 87 88 33 22",
    "sg:postcode":"4710",
    "sg:province":"Li\u00e8ge",
    "wof:name":"Plaisir (pour Le)-collard Denise",
    "wof:placetype":"venue"
},
  "geometry": {"coordinates":[5.9620499611,50.6794281006],"type":"Point"}
}