{
  "type": "Feature",
  "properties": {
    "iso:country":"BE",
    "sg:address":"Avenue Houba-de-strooper 145",
    "sg:city":"Brussel",
    "sg:classifiers":[
        {
            "category":"Sports & Exercise",
            "subcategory":"Sports Center",
            "type":"Entertainment"
        }
    ],
    "sg:phone":"+32 2 477 12 11",
    "sg:postcode":"1020",
    "sg:province":"Bruxelles-Capitale",
    "sg:tags":[
        "game"
    ],
    "wof:name":"Koninklijke Belgische Voetbalbond Asbl",
    "wof:placetype":"venue"
},
  "geometry": {"coordinates":[4.3357467651,50.8913192749],"type":"Point"}
}