{
  "type": "Feature",
  "properties": {
    "addr:full":"Hofstraat 92 Tessenderlo Limburg 3980",
    "addr:housenumber":"92",
    "addr:postcode":"3980",
    "addr:street":"Hofstraat",
    "iso:country":"BE",
    "sg:address":"Hofstraat 92",
    "sg:city":"Tessenderlo",
    "sg:orig_category":"Enseignement maternel and primaire",
    "sg:phone":"+32 13 66 31 71",
    "sg:postcode":"3980",
    "sg:province":"Limburg",
    "wof:name":"Vrije Basisschool",
    "wof:placetype":"venue"
},
  "geometry": {"coordinates":[5.12541008,51.0673217773],"type":"Point"}
}