{
  "type": "Feature",
  "properties": {
    "iso:country":"BE",
    "sg:address":"Francis De Meeuslaan 10",
    "sg:city":"Maldegem",
    "sg:classifiers":[
        {
            "category":"Farming",
            "subcategory":"Livestock Farm",
            "type":"Manufacturing & Wholesale Goods"
        }
    ],
    "sg:phone":"+32 50 71 12 54",
    "sg:postcode":"9990",
    "sg:province":"Oost-Vlaanderen",
    "sg:tags":[
        "buyer"
    ],
    "wof:name":"Matthijs Bvba",
    "wof:placetype":"venue"
},
  "geometry": {"coordinates":[3.4152100086,51.1933555603],"type":"Point"}
}