{
  "type": "Feature",
  "properties": {
    "addr:full":"Rue De L'eglise 44 Pont-a-celles Hainaut 6230",
    "addr:housenumber":"44",
    "addr:postcode":"6230",
    "addr:street":"Rue De L'Eglise",
    "iso:country":"BE",
    "sg:address":"Rue De L'eglise 44",
    "sg:city":"Pont-a-celles",
    "sg:orig_category":"Banques and organismes de cr\u00e9dit",
    "sg:phone":"+32 71 84 40 42",
    "sg:postcode":"6230",
    "sg:province":"Hainaut",
    "wof:name":"Bbl",
    "wof:placetype":"venue"
},
  "geometry": {"coordinates":[4.3636260033,50.5104103088],"type":"Point"}
}