{
  "type": "Feature",
  "properties": {
    "addr:full":"Helmetsesteenweg 368 Schaarbeek/schaerbeek Bruxelles-Capitale 1030",
    "addr:housenumber":"368",
    "addr:postcode":"1030",
    "addr:street":"Helmetsesteenweg",
    "iso:country":"BE",
    "sg:address":"Helmetsesteenweg 368",
    "sg:city":"Schaarbeek/schaerbeek",
    "sg:orig_category":"Artsen and specialisten",
    "sg:phone":"+32 2 215 93 32",
    "sg:postcode":"1030",
    "sg:province":"Bruxelles-Capitale",
    "wof:name":"C. Tilborg",
    "wof:placetype":"venue"
},
  "geometry": {"coordinates":[4.3917927742,50.8755874634],"type":"Point"}
}