{
  "type": "Feature",
  "properties": {
    "iso:country":"BE",
    "sg:address":"Hisselsgasse 81",
    "sg:city":"Eupen",
    "sg:classifiers":[
        {
            "category":"Real Estate",
            "subcategory":"Architect",
            "type":"Services"
        }
    ],
    "sg:phone":"+32 87 56 01 60",
    "sg:postcode":"4700",
    "sg:province":"Li\u00e8ge",
    "wof:name":"Aussems R",
    "wof:placetype":"venue"
},
  "geometry": {"coordinates":[6.0407972336,50.6282501221],"type":"Point"}
}