{
  "type": "Feature",
  "properties": {
    "addr:full":"Avenue Des D\u00e9mineurs 11 Bruxelles (jette) Bruxelles-Capitale 1090",
    "addr:housenumber":"11",
    "addr:postcode":"1090",
    "addr:street":"Avenue Des De\u0301Mineurs",
    "iso:country":"BE",
    "sg:address":"Avenue Des D\u00e9mineurs 11",
    "sg:city":"Bruxelles (jette)",
    "sg:classifiers":[
        {
            "category":"Wholesale",
            "subcategory":"Music Publishers",
            "type":"Manufacturing & Wholesale Goods"
        }
    ],
    "sg:phone":"+32 2 305 64 41",
    "sg:postcode":"1090",
    "sg:province":"Bruxelles-Capitale",
    "wof:name":"Parasjoet Productions Bvba",
    "wof:placetype":"venue"
},
  "geometry": {"coordinates":[4.3322768211,50.8790855408],"type":"Point"}
}