{
  "type": "Feature",
  "properties": {
    "iso:country":"BE",
    "sg:address":"Dorpsstraat 81",
    "sg:city":"As",
    "sg:orig_category":"Epiceries",
    "sg:phone":"+32 89 65 96 50",
    "sg:postcode":"3665",
    "sg:province":"Limburg",
    "wof:name":"Spar",
    "wof:placetype":"venue"
},
  "geometry": {"coordinates":[5.5831370354,51.0069618225],"type":"Point"}
}