{
  "type": "Feature",
  "properties": {
    "addr:full":"Adjudant Masscheleinlaan 48 Ieper West-Vlaanderen 8900",
    "addr:housenumber":"48",
    "addr:postcode":"8900",
    "addr:street":"Masscheleinlaan",
    "iso:country":"BE",
    "sg:address":"Adjudant Masscheleinlaan 48",
    "sg:city":"Ieper",
    "sg:orig_category":"Ziekenvervoer",
    "sg:phone":"+32 57 20 75 75",
    "sg:postcode":"8900",
    "sg:province":"West-Vlaanderen",
    "wof:name":"Het Vlaamse Kruis",
    "wof:placetype":"venue"
},
  "geometry": {"coordinates":[2.8837029934,50.8553962708],"type":"Point"}
}