{
  "type": "Feature",
  "properties": {
    "iso:country":"BE",
    "sg:address":"Oudegemse Baan 7",
    "sg:city":"Dendermonde (oudegem)",
    "sg:classifiers":[
        {
            "category":"Health Services",
            "subcategory":"Dentist",
            "type":"Services"
        }
    ],
    "sg:phone":"+32 52 21 95 29",
    "sg:postcode":"9200",
    "sg:province":"Oost-Vlaanderen",
    "wof:name":"Dierickx L",
    "wof:placetype":"venue"
},
  "geometry": {"coordinates":[4.0290870667,50.9950866699],"type":"Point"}
}