{
  "type": "Feature",
  "properties": {
    "iso:country":"BE",
    "sg:address":"Marktplein 17a",
    "sg:city":"Sint-lievens-houtem",
    "sg:classifiers":[
        {
            "category":"Sports & Exercise",
            "subcategory":"Sports Center",
            "type":"Entertainment"
        }
    ],
    "sg:phone":"+32 53 63 02 48",
    "sg:postcode":"9520",
    "sg:province":"Oost-Vlaanderen",
    "sg:tags":[
        "holiday",
        "language"
    ],
    "wof:name":"Plus Taalvakanties Vzw",
    "wof:placetype":"venue"
},
  "geometry": {"coordinates":[3.8576009274,50.9200897217],"type":"Point"}
}