{
  "type": "Feature",
  "properties": {
    "iso:country":"BE",
    "sg:address":"17-19 Kruiningestraat",
    "sg:city":"Deurne",
    "sg:classifiers":[
        {
            "category":"Autos & Motor Vehicles",
            "subcategory":"Automobile Sales",
            "type":"Retail Goods"
        }
    ],
    "sg:phone":"+32 3 325 34 00",
    "sg:postcode":"2100",
    "sg:province":"Antwerpen",
    "sg:tags":[
        "equipment",
        "motor-cars",
        "transport"
    ],
    "wof:name":"Alr Nv",
    "wof:placetype":"venue"
},
  "geometry": {"coordinates":[4.4773550034,51.2363815308],"type":"Point"}
}