{
  "type": "Feature",
  "properties": {
    "addr:full":"Rue Grand-vin\u00c2ve 105 Seraing Li\u00e8ge 4101",
    "addr:housenumber":"105",
    "addr:postcode":"4101",
    "addr:street":"Rue Grand-Vina\u0302Ve",
    "iso:country":"BE",
    "sg:address":"Rue Grand-vin\u00c2ve 105",
    "sg:city":"Seraing",
    "sg:classifiers":[
        {
            "category":"Shopping",
            "subcategory":"Clothing, Apparel, & Fashions",
            "type":"Retail Goods"
        }
    ],
    "sg:phone":"+32 4 231 04 11",
    "sg:postcode":"4101",
    "sg:province":"Li\u00e8ge",
    "sg:tags":[
        "ondergoed",
        "lingerie"
    ],
    "wof:name":"Maison Voluptia",
    "wof:placetype":"venue"
},
  "geometry": {"coordinates":[5.5069441795,50.6172370911],"type":"Point"}
}