{
  "type": "Feature",
  "properties": {
    "iso:country":"BE",
    "sg:address":"Speelpleinstraat 10",
    "sg:city":"Bierbeek",
    "sg:orig_category":"Openbare bibliotheken and archieven",
    "sg:phone":"+32 16 26 97 46",
    "sg:postcode":"3360",
    "sg:province":"Vlaams-Brabant",
    "wof:name":"Openbare Bibliotheek",
    "wof:placetype":"venue"
},
  "geometry": {"coordinates":[4.7540369034,50.8271408081],"type":"Point"}
}