{
  "type": "Feature",
  "properties": {
    "iso:country":"BE",
    "sg:address":"Eikenstraat 29",
    "sg:city":"Rumst",
    "sg:orig_category":"Quincailleries",
    "sg:phone":"+32 3 888 40 90",
    "sg:postcode":"2840",
    "sg:province":"Antwerpen",
    "wof:name":"Huis Devrieze-aster A.",
    "wof:placetype":"venue"
},
  "geometry": {"coordinates":[4.4227218628,51.0800132751],"type":"Point"}
}