{
  "type": "Feature",
  "properties": {
    "iso:country":"BE",
    "sg:address":"Scheldestraat 52",
    "sg:city":"Gent",
    "sg:orig_category":"Jardins botaniques, zoologiques, observatoires and r\u00e9serves naturelles",
    "sg:phone":"+32 9 228 07 06",
    "sg:postcode":"9040",
    "sg:province":"Oost-Vlaanderen",
    "wof:name":"Damvallei (destelbergen)",
    "wof:placetype":"venue"
},
  "geometry": {"coordinates":[3.7496600151,51.0511131287],"type":"Point"}
}