{
  "type": "Feature",
  "properties": {
    "iso:country":"BE",
    "sg:address":"Onderrichtsstraat 112b16",
    "sg:city":"Brussel/bruxelles",
    "sg:orig_category":"Marktonderzoekbureaus",
    "sg:phone":"+32 2 217 60 09",
    "sg:postcode":"1000",
    "sg:province":"Bruxelles-Capitale",
    "wof:name":"Bureau Cefores",
    "wof:placetype":"venue"
},
  "geometry": {"coordinates":[4.3654928207,50.8493041992],"type":"Point"}
}