{
  "type": "Feature",
  "properties": {
    "iso:country":"BE",
    "sg:address":"Avenue Wielemans Ceuppens 128",
    "sg:city":"Vorst/forest",
    "sg:classifiers":[
        {
            "category":"Cafe",
            "type":"Food & Drink"
        }
    ],
    "sg:phone":"+32 2 534 88 41",
    "sg:postcode":"1190",
    "sg:province":"Bruxelles-Capitale",
    "sg:tags":[
        "caf\u00e9s"
    ],
    "wof:name":"Le Nelson",
    "wof:placetype":"venue"
},
  "geometry": {"coordinates":[4.3317098618,50.8244094849],"type":"Point"}
}