{
  "type": "Feature",
  "properties": {
    "iso:country":"BE",
    "sg:address":"Chauss\u00e9e De Bruxelles 81",
    "sg:city":"Court-saint-etienne",
    "sg:classifiers":[
        {
            "category":"Professional",
            "subcategory":"Accounting & Tax Preparation",
            "type":"Services"
        }
    ],
    "sg:phone":"+32 10 61 54 59",
    "sg:postcode":"1490",
    "sg:province":"Brabant Wallon",
    "sg:tags":[
        "bookkeeper"
    ],
    "wof:name":"Management R.d.r. Scrl",
    "wof:placetype":"venue"
},
  "geometry": {"coordinates":[4.5345702171,50.6540603638],"type":"Point"}
}