{
  "type": "Feature",
  "properties": {
    "iso:country":"BE",
    "sg:address":"Gemeentestraat 4",
    "sg:city":"Duffel",
    "sg:orig_category":"Advocaten and juridische adviseurs",
    "sg:phone":"+32 15 31 37 38",
    "sg:postcode":"2570",
    "sg:province":"Antwerpen",
    "wof:name":"Hugo Stuyck",
    "wof:placetype":"venue"
},
  "geometry": {"coordinates":[4.5056967735,51.0953025818],"type":"Point"}
}