{
  "type": "Feature",
  "properties": {
    "iso:country":"BE",
    "sg:address":"Josef Pontenweg 25",
    "sg:city":"Raeren",
    "sg:orig_category":"Schoonheidssalons",
    "sg:phone":"+32 87 86 60 68",
    "sg:postcode":"4730",
    "sg:province":"Li\u00e8ge",
    "wof:name":"Liliane Dresse",
    "wof:placetype":"venue"
},
  "geometry": {"coordinates":[6.1148810387,50.6774864197],"type":"Point"}
}