{
  "type": "Feature",
  "properties": {
    "iso:country":"BE",
    "sg:address":"Jozef Van Cleemputplein 1",
    "sg:city":"Boom",
    "sg:orig_category":"Bloemen and planten Brood, gebak and snoepgoed Krantenwinkels Speelgoed",
    "sg:phone":"+32 3 844 42 44",
    "sg:postcode":"2850",
    "sg:province":"Antwerpen",
    "wof:name":"Brandt",
    "wof:placetype":"venue"
},
  "geometry": {"coordinates":[4.3707499504,51.0885314941],"type":"Point"}
}