{
  "type": "Feature",
  "properties": {
    "iso:country":"BE",
    "sg:address":"Tulpenstraat 5",
    "sg:city":"Overpelt",
    "sg:orig_category":"Artsen and specialisten",
    "sg:phone":"+32 11 66 56 67",
    "sg:postcode":"3900",
    "sg:province":"Limburg",
    "wof:name":"Nancy Nuyt",
    "wof:placetype":"venue"
},
  "geometry": {"coordinates":[5.3700079918,51.2048416138],"type":"Point"}
}