{
  "type": "Feature",
  "properties": {
    "iso:country":"BE",
    "sg:address":"Rue De L'industrie 185",
    "sg:city":"Frameries",
    "sg:orig_category":"Supermarkten Warenhuizen",
    "sg:phone":"+32 65 67 46 76",
    "sg:postcode":"7080",
    "sg:province":"Hainaut",
    "wof:name":"Unic",
    "wof:placetype":"venue"
},
  "geometry": {"coordinates":[3.8841249943,50.4087600708],"type":"Point"}
}