{
  "type": "Feature",
  "properties": {
    "addr:full":"Diependale 2 Oudenaarde Oost-Vlaanderen 9700",
    "addr:housenumber":"2",
    "addr:postcode":"9700",
    "addr:street":"Diependale",
    "iso:country":"BE",
    "sg:address":"Diependale 2",
    "sg:city":"Oudenaarde",
    "sg:orig_category":"Textiel",
    "sg:phone":"+32 55 30 24 02",
    "sg:postcode":"9700",
    "sg:province":"Oost-Vlaanderen",
    "wof:name":"Pand Diependale",
    "wof:placetype":"venue"
},
  "geometry": {"coordinates":[3.6072199345,50.8375282288],"type":"Point"}
}