{
  "type": "Feature",
  "properties": {
    "iso:country":"BE",
    "sg:address":"Chauss\u00e9e De Charleroi 335",
    "sg:city":"Fleurus",
    "sg:orig_category":"Non-Classified Establishments",
    "sg:phone":"+32 71 81 27 00",
    "sg:postcode":"6220",
    "sg:province":"Hainaut",
    "wof:name":"A U B",
    "wof:placetype":"venue"
},
  "geometry": {"coordinates":[4.5481090546,50.4790534973],"type":"Point"}
}