{
  "type": "Feature",
  "properties": {
    "addr:full":"Kleinhoefstraat 6 Geel Antwerpen 2440",
    "addr:housenumber":"6",
    "addr:postcode":"2440",
    "addr:street":"Kleinhoefstraat",
    "iso:country":"BE",
    "sg:address":"Kleinhoefstraat 6",
    "sg:city":"Geel",
    "sg:orig_category":"Diverse opleidingen and onderwijs Informaticaconsulenten Software ontwikkeling and ontwerp",
    "sg:phone":"+32 14 57 96 50",
    "sg:postcode":"2440",
    "sg:province":"Antwerpen",
    "wof:name":"C.i.t. Engineering",
    "wof:placetype":"venue"
},
  "geometry": {"coordinates":[4.9633450508,51.1628417969],"type":"Point"}
}