{
  "type": "Feature",
  "properties": {
    "iso:country":"BE",
    "sg:address":"Malta 19",
    "sg:city":"Bree",
    "sg:orig_category":"Peinture. Textiles. Rev\u00eatements de sols and murs. Eclairage et \u00e9quipements du foyer. Rev\u00eatements pou",
    "sg:phone":"+32 89 46 13 28",
    "sg:postcode":"3960",
    "sg:province":"Limburg",
    "wof:name":"Huis Mertens",
    "wof:placetype":"venue"
},
  "geometry": {"coordinates":[5.6021199226,51.1424102783],"type":"Point"}
}