{
  "type": "Feature",
  "properties": {
    "iso:country":"BE",
    "sg:address":"Iepersestraat 469",
    "sg:city":"Roeselare",
    "sg:orig_category":"Brood, gebak and snoepgoed",
    "sg:phone":"+32 51 22 86 77",
    "sg:postcode":"8800",
    "sg:province":"West-Vlaanderen",
    "wof:name":"P.c.b.",
    "wof:placetype":"venue"
},
  "geometry": {"coordinates":[3.1009659767,50.9331893921],"type":"Point"}
}