{
  "type": "Feature",
  "properties": {
    "addr:full":"Poddegemstraat 59 Grimbergen Vlaams-Brabant 1850",
    "addr:housenumber":"59",
    "addr:postcode":"1850",
    "addr:street":"Poddegemstraat",
    "iso:country":"BE",
    "sg:address":"Poddegemstraat 59",
    "sg:city":"Grimbergen",
    "sg:classifiers":[
        {
            "category":"Bars & Pubs",
            "type":"Food & Drink"
        }
    ],
    "sg:phone":"+32 2 270 93 62",
    "sg:postcode":"1850",
    "sg:province":"Vlaams-Brabant",
    "wof:name":"Veldkant (in De)",
    "wof:placetype":"venue"
},
  "geometry": {"coordinates":[4.38586092,50.9396247864],"type":"Point"}
}