{
  "type": "Feature",
  "properties": {
    "addr:full":"Burgemeester Karel Van Doorslaerlaan 22 Bornem (mariekerke) Antwerpen 2880",
    "addr:housenumber":"22",
    "addr:postcode":"2880",
    "addr:street":"Burgemeester Karel Van Doorslaerlaan",
    "iso:country":"BE",
    "sg:address":"Burgemeester Karel Van Doorslaerlaan 22",
    "sg:city":"Bornem (mariekerke)",
    "sg:classifiers":[
        {
            "category":"Health Services",
            "subcategory":"Doctor",
            "type":"Services"
        }
    ],
    "sg:phone":"+32 52 33 24 00",
    "sg:postcode":"2880",
    "sg:province":"Antwerpen",
    "sg:tags":[
        "medicinephysicians",
        "surgeon"
    ],
    "wof:name":"De Bleser A",
    "wof:placetype":"venue"
},
  "geometry": {"coordinates":[4.1945137978,51.0623588562],"type":"Point"}
}