{
  "type": "Feature",
  "properties": {
    "addr:full":"Spinnerijstraat 25 Harelbeke West-Vlaanderen 8530",
    "addr:housenumber":"25",
    "addr:postcode":"8530",
    "addr:street":"Spinnerijstraat",
    "iso:country":"BE",
    "sg:address":"Spinnerijstraat 25",
    "sg:city":"Harelbeke",
    "sg:orig_category":"Rev\u00eatements pour sols and murs. Installation de menuiserie en bois and plastique",
    "sg:phone":"+32 56 20 14 10",
    "sg:postcode":"8530",
    "sg:province":"West-Vlaanderen",
    "wof:name":"Marbra-lys Trappen",
    "wof:placetype":"venue"
},
  "geometry": {"coordinates":[3.3057479858,50.8304023743],"type":"Point"}
}