{
  "type": "Feature",
  "properties": {
    "addr:full":"Potaardestraat 86 Lebbeke Oost-Vlaanderen 9280",
    "addr:housenumber":"86",
    "addr:postcode":"9280",
    "addr:street":"Potaardestraat",
    "iso:country":"BE",
    "sg:address":"Potaardestraat 86",
    "sg:city":"Lebbeke",
    "sg:orig_category":"Pleisterwerk",
    "sg:phone":"+32 52 41 38 98",
    "sg:postcode":"9280",
    "sg:province":"Oost-Vlaanderen",
    "wof:name":"Dirk Van Sinay",
    "wof:placetype":"venue"
},
  "geometry": {"coordinates":[4.1619610786,51.0052871704],"type":"Point"}
}