{
  "type": "Feature",
  "properties": {
    "iso:country":"BE",
    "sg:address":"Rue De Wangenies 103",
    "sg:city":"Fleurus",
    "sg:classifiers":[
        {
            "category":"Building & Trades",
            "subcategory":"Landscaping Services",
            "type":"Services"
        }
    ],
    "sg:phone":"+32 477 20 52 89",
    "sg:postcode":"6220",
    "sg:province":"Hainaut",
    "sg:tags":[
        "gardening",
        "garden",
        "maintenance"
    ],
    "wof:name":"Joly Jardins",
    "wof:placetype":"venue"
},
  "geometry": {"coordinates":[4.5265002251,50.4568710327],"type":"Point"}
}