{
  "type": "Feature",
  "properties": {
    "iso:country":"BE",
    "sg:address":"Chauss\u00e9e De Jolimont 69",
    "sg:city":"La Louvi\u00e8re (haine-saint-pierre)",
    "sg:classifiers":[
        {
            "category":"Health Services",
            "subcategory":"Dentist",
            "type":"Services"
        }
    ],
    "sg:phone":"+32 64 21 54 49",
    "sg:postcode":"7100",
    "sg:province":"Hainaut",
    "wof:name":"Hofbauer D",
    "wof:placetype":"venue"
},
  "geometry": {"coordinates":[4.2157001495,50.4721488953],"type":"Point"}
}