{
  "type": "Feature",
  "properties": {
    "addr:full":"Bosstraat 29 Erpe-mere (mere) Oost-Vlaanderen 9420",
    "addr:housenumber":"29",
    "addr:postcode":"9420",
    "addr:street":"Bosstraat;Mere Oost-Vlaanderen",
    "iso:country":"BE",
    "sg:address":"Bosstraat 29",
    "sg:city":"Erpe-mere (mere)",
    "sg:classifiers":[
        {
            "category":"Home & Garden",
            "subcategory":"Carpets & Floor Coverings",
            "type":"Retail Goods"
        }
    ],
    "sg:phone":"+32 53 83 92 17",
    "sg:postcode":"9420",
    "sg:province":"Oost-Vlaanderen",
    "sg:tags":[
        "parquet"
    ],
    "wof:name":"I & P",
    "wof:placetype":"venue"
},
  "geometry": {"coordinates":[3.9659268856,50.9238166809],"type":"Point"}
}