{
  "type": "Feature",
  "properties": {
    "addr:full":"Kerkstraat 29 Sint-gillis-waas Oost-Vlaanderen 9170",
    "addr:housenumber":"29",
    "addr:postcode":"9170",
    "addr:street":"Kerkstraat",
    "iso:country":"BE",
    "sg:address":"Kerkstraat 29",
    "sg:city":"Sint-gillis-waas",
    "sg:orig_category":"Overheidsdiensten",
    "sg:phone":"+32 3 727 17 00",
    "sg:postcode":"9170",
    "sg:province":"Oost-Vlaanderen",
    "wof:name":"Gemeentebestuur",
    "wof:placetype":"venue"
},
  "geometry": {"coordinates":[4.1285691261,51.2173194885],"type":"Point"}
}