{
  "type": "Feature",
  "properties": {
    "iso:country":"BE",
    "sg:address":"Stedemolenstraat 92",
    "sg:city":"Tielt",
    "sg:orig_category":"Boucheries",
    "sg:phone":"+32 51 40 05 11",
    "sg:postcode":"8700",
    "sg:province":"West-Vlaanderen",
    "wof:name":"Marnix Vanhee",
    "wof:placetype":"venue"
},
  "geometry": {"coordinates":[3.31676507,50.994682312],"type":"Point"}
}