{
  "type": "Feature",
  "properties": {
    "iso:country":"BE",
    "sg:address":"Beverstraat 23",
    "sg:city":"Ninove",
    "sg:orig_category":"Chaussures",
    "sg:phone":"+32 54 33 58 41",
    "sg:postcode":"9400",
    "sg:province":"Oost-Vlaanderen",
    "wof:name":"Shoes In The Box",
    "wof:placetype":"venue"
},
  "geometry": {"coordinates":[4.021791935,50.8364295959],"type":"Point"}
}