{
  "type": "Feature",
  "properties": {
    "addr:full":"Gemeenteplein 2 Waregem West-Vlaanderen 8790",
    "addr:housenumber":"2",
    "addr:postcode":"8790",
    "addr:street":"Gemeenteplein",
    "iso:country":"BE",
    "sg:address":"Gemeenteplein 2",
    "sg:city":"Waregem",
    "sg:orig_category":"Openbare veiligheid",
    "sg:phone":"+32 56 62 13 00",
    "sg:postcode":"8790",
    "sg:province":"West-Vlaanderen",
    "wof:name":"Federale Politie",
    "wof:placetype":"venue"
},
  "geometry": {"coordinates":[3.4314920902,50.8855247498],"type":"Point"}
}