{
  "type": "Feature",
  "properties": {
    "iso:country":"BE",
    "sg:address":"Wetstraat 30",
    "sg:city":"Waregem",
    "sg:classifiers":[
        {
            "category":"Food & Beverages",
            "subcategory":"Dairy",
            "type":"Retail Goods"
        }
    ],
    "sg:phone":"+32 56 60 33 65",
    "sg:postcode":"8790",
    "sg:province":"West-Vlaanderen",
    "sg:tags":[
        "product",
        "-"
    ],
    "wof:name":"Van Thuyne",
    "wof:placetype":"venue"
},
  "geometry": {"coordinates":[3.3799030781,50.8844337463],"type":"Point"}
}