{
  "type": "Feature",
  "properties": {
    "iso:country":"BE",
    "sg:address":"Rue Bayet 9",
    "sg:city":"Charleroi",
    "sg:orig_category":"M\u00e9decins and sp\u00e9cialistes",
    "sg:phone":"+32 71 41 75 61",
    "sg:postcode":"6000",
    "sg:province":"Hainaut",
    "wof:name":"Jean Paquet",
    "wof:placetype":"venue"
},
  "geometry": {"coordinates":[4.4602189064,50.4227790833],"type":"Point"}
}