{
  "type": "Feature",
  "properties": {
    "addr:full":"Molenstraat 28 Scherpenheuvel-zichem Vlaams-Brabant 3270",
    "addr:housenumber":"28",
    "addr:postcode":"3270",
    "addr:street":"Molenstraat",
    "iso:country":"BE",
    "sg:address":"Molenstraat 28",
    "sg:city":"Scherpenheuvel-zichem",
    "sg:orig_category":"Banques and organismes de cr\u00e9dit",
    "sg:phone":"+32 13 77 61 05",
    "sg:postcode":"3270",
    "sg:province":"Vlaams-Brabant",
    "wof:name":"Kbc",
    "wof:placetype":"venue"
},
  "geometry": {"coordinates":[4.9748811722,50.9808235168],"type":"Point"}
}