{
  "type": "Feature",
  "properties": {
    "iso:country":"BE",
    "sg:address":"Rue De Hamoir 18",
    "sg:city":"Ouffet",
    "sg:orig_category":"Entretien and r\u00e9parations de voitures",
    "sg:phone":"+32 86 36 62 80",
    "sg:postcode":"4590",
    "sg:province":"Li\u00e8ge",
    "wof:name":"Jean-marie Monfort",
    "wof:placetype":"venue"
},
  "geometry": {"coordinates":[5.4765658379,50.437953949],"type":"Point"}
}