{
  "type": "Feature",
  "properties": {
    "iso:country":"BE",
    "sg:address":"Tieltsesteenweg 238",
    "sg:city":"Deinze",
    "sg:classifiers":[
        {
            "category":"Shopping",
            "subcategory":"Bicycles & Sporting Goods",
            "type":"Retail Goods"
        }
    ],
    "sg:phone":"+32 9 386 13 59",
    "sg:postcode":"9800",
    "sg:province":"Oost-Vlaanderen",
    "sg:tags":[
        "tyre"
    ],
    "wof:name":"Debels Banden & Aluvelgencenter Bvba",
    "wof:placetype":"venue"
},
  "geometry": {"coordinates":[3.4533720016,50.9890403748],"type":"Point"}
}