{
  "type": "Feature",
  "properties": {
    "iso:country":"BE",
    "sg:address":"Avenue Eiffel 5 Z.i. Nord",
    "sg:city":"Wavre",
    "sg:orig_category":"Accessories For Starters",
    "sg:phone":"+32 10 23 13 11",
    "sg:postcode":"1300",
    "sg:province":"Brabant Wallon",
    "wof:name":"Caron Vector S.a.",
    "wof:placetype":"venue"
},
  "geometry": {"coordinates":[4.5970110893,50.7374801636],"type":"Point"}
}