{
  "type": "Feature",
  "properties": {
    "iso:country":"BE",
    "sg:address":"Molenbergstraat 80",
    "sg:city":"Rumst",
    "sg:classifiers":[
        {
            "category":"Health Services",
            "subcategory":"Health Practitioner",
            "type":"Services"
        }
    ],
    "sg:phone":"+32 3 888 55 36",
    "sg:postcode":"2840",
    "sg:province":"Antwerpen",
    "sg:tags":[
        "physiotherapist"
    ],
    "wof:name":"De Laet Vic",
    "wof:placetype":"venue"
},
  "geometry": {"coordinates":[4.4226131439,51.0798606873],"type":"Point"}
}