{
  "type": "Feature",
  "properties": {
    "addr:full":"Avenue Du Sabottier 40 Braine-l`alleud Brabant Wallon 1428",
    "addr:housenumber":"40",
    "addr:postcode":"1428",
    "addr:street":"Avenue Du Sabottier;Brabant Wallon",
    "iso:country":"BE",
    "sg:address":"Avenue Du Sabottier 40",
    "sg:city":"Braine-l`alleud",
    "sg:classifiers":[
        {
            "category":"Travel",
            "subcategory":"Hotels & Motels",
            "type":"Entertainment"
        }
    ],
    "sg:phone":"+32 2 384 69 56",
    "sg:postcode":"1428",
    "sg:province":"Brabant Wallon",
    "wof:name":"H\u00d4tel Witterzee",
    "wof:placetype":"venue"
},
  "geometry": {"coordinates":[1.2029399872,47.4052200317],"type":"Point"}
}