{
  "type": "Feature",
  "properties": {
    "iso:country":"BE",
    "sg:address":"Moeresteenweg 36",
    "sg:city":"De Panne (adinkerke)",
    "sg:classifiers":[
        {
            "category":"Bars & Pubs",
            "type":"Food & Drink"
        }
    ],
    "sg:phone":"+32 58 41 03 34",
    "sg:postcode":"8660",
    "sg:province":"West-Vlaanderen",
    "wof:name":"Veld ('t)",
    "wof:placetype":"venue"
},
  "geometry": {"coordinates":[2.5898230076,51.0596504211],"type":"Point"}
}