{
  "type": "Feature",
  "properties": {
    "addr:full":"Rue De Landen 53a Hannut Li\u00e8ge 4280",
    "addr:housenumber":"53a",
    "addr:postcode":"4280",
    "addr:street":"Rue De Landen",
    "iso:country":"BE",
    "sg:address":"Rue De Landen 53a",
    "sg:city":"Hannut",
    "sg:classifiers":[
        {
            "category":"Personal",
            "subcategory":"Beauty Salon",
            "type":"Services"
        }
    ],
    "sg:phone":"+32 19 51 14 70",
    "sg:postcode":"4280",
    "sg:province":"Li\u00e8ge",
    "sg:tags":[
        "lady",
        "-",
        "hairdressing"
    ],
    "wof:name":"Daniel Coiffure",
    "wof:placetype":"venue"
},
  "geometry": {"coordinates":[5.081952095,50.680305481],"type":"Point"}
}