{
  "type": "Feature",
  "properties": {
    "addr:full":"Rue De Marpent 11 Erquelinnes Hainaut 6560",
    "addr:housenumber":"11",
    "addr:postcode":"6560",
    "addr:street":"Rue De Marpent",
    "iso:country":"BE",
    "sg:address":"Rue De Marpent 11",
    "sg:city":"Erquelinnes",
    "sg:classifiers":[
        {
            "category":"Cafe",
            "type":"Food & Drink"
        }
    ],
    "sg:phone":"+32 64 77 26 89",
    "sg:postcode":"6560",
    "sg:province":"Hainaut",
    "sg:tags":[
        "caf\u00e9s"
    ],
    "wof:name":"Chez Gilot",
    "wof:placetype":"venue"
},
  "geometry": {"coordinates":[4.0791049004,50.319190979],"type":"Point"}
}