{
  "type": "Feature",
  "properties": {
    "addr:full":"Rue Des Bouvreuils 8 Neupre Li\u00e8ge 4121",
    "addr:housenumber":"8",
    "addr:postcode":"4121",
    "addr:street":"Rue Des Bouvreuils",
    "iso:country":"BE",
    "sg:address":"Rue Des Bouvreuils 8",
    "sg:city":"Neupre",
    "sg:orig_category":"Instituts de beaut\u00e9",
    "sg:phone":"+32 4 371 39 73",
    "sg:postcode":"4121",
    "sg:province":"Li\u00e8ge",
    "wof:name":"Le Renouveau",
    "wof:placetype":"venue"
},
  "geometry": {"coordinates":[5.4574589729,50.5468597412],"type":"Point"}
}