{
  "type": "Feature",
  "properties": {
    "addr:full":"Place Reine Astrid 4 Vis\u00e9 Li\u00e8ge 4600",
    "addr:housenumber":"4",
    "addr:postcode":"4600",
    "addr:street":"Place Reine Astrid",
    "iso:country":"BE",
    "sg:address":"Place Reine Astrid 4",
    "sg:city":"Vis\u00e9",
    "sg:classifiers":[
        {
            "category":"Bars & Pubs",
            "type":"Food & Drink"
        }
    ],
    "sg:phone":"+32 4 379 11 59",
    "sg:postcode":"4600",
    "sg:province":"Li\u00e8ge",
    "wof:name":"Lehaen (chez)",
    "wof:placetype":"venue"
},
  "geometry": {"coordinates":[5.6947231293,50.7376403809],"type":"Point"}
}