{
  "type": "Feature",
  "properties": {
    "iso:country":"BE",
    "sg:address":"Rue De L'ile 2",
    "sg:city":"Anhee",
    "sg:orig_category":"Brood, gebak and snoepgoed",
    "sg:phone":"+32 82 61 15 31",
    "sg:postcode":"5537",
    "sg:province":"Namur",
    "wof:name":"Pierre Fecherolle",
    "wof:placetype":"venue"
},
  "geometry": {"coordinates":[4.8947639465,50.30128479],"type":"Point"}
}