{
  "type": "Feature",
  "properties": {
    "addr:full":"Rerum Novarumlaan 48 Malle (westmalle) Antwerpen 2390",
    "addr:housenumber":"48",
    "addr:postcode":"2390",
    "addr:street":"Rerum Novarumlaan",
    "iso:country":"BE",
    "sg:address":"Rerum Novarumlaan 48",
    "sg:city":"Malle (westmalle)",
    "sg:classifiers":[
        {
            "category":"Health Services",
            "subcategory":"Dentist",
            "type":"Services"
        }
    ],
    "sg:phone":"+32 3 312 49 83",
    "sg:postcode":"2390",
    "sg:province":"Antwerpen",
    "wof:name":"De Boel Christine",
    "wof:placetype":"venue"
},
  "geometry": {"coordinates":[4.6851859093,51.300403595],"type":"Point"}
}