{
  "type": "Feature",
  "properties": {
    "iso:country":"BE",
    "sg:address":"Jules Moretuslei 2",
    "sg:city":"Wilrijk",
    "sg:classifiers":[
        {
            "category":"Professional",
            "subcategory":"Business Services",
            "type":"Services"
        }
    ],
    "sg:phone":"+32 3 828 95 60",
    "sg:postcode":"2610",
    "sg:province":"Antwerpen",
    "sg:tags":[
        "body",
        "advice"
    ],
    "wof:name":"Intercom Vercrematorium Cv",
    "wof:placetype":"venue"
},
  "geometry": {"coordinates":[4.3761267662,51.170879364],"type":"Point"}
}