{
  "type": "Feature",
  "properties": {
    "iso:country":"BE",
    "sg:address":"Rue De L'industrie 5",
    "sg:city":"Wavre",
    "sg:orig_category":"Baby- and kinderkleding",
    "sg:phone":"+32 10 41 41 70",
    "sg:postcode":"1301",
    "sg:province":"Brabant Wallon",
    "wof:name":"Maserco",
    "wof:placetype":"venue"
},
  "geometry": {"coordinates":[4.5952281952,50.706237793],"type":"Point"}
}