{
  "type": "Feature",
  "properties": {
    "iso:country":"BE",
    "sg:address":"Rue Du Bois D'hautmont 4",
    "sg:city":"Braine-le-ch\u00e2teau (wauthier-braine)",
    "sg:classifiers":[
        {
            "category":"Building & Trades",
            "subcategory":"Construction",
            "type":"Services"
        }
    ],
    "sg:phone":"+32 800 95 174",
    "sg:postcode":"1440",
    "sg:province":"Brabant Wallon",
    "sg:tags":[
        "glazier"
    ],
    "wof:name":"Petits Services (aux)",
    "wof:placetype":"venue"
},
  "geometry": {"coordinates":[4.3155288696,50.6843528748],"type":"Point"}
}