{
  "type": "Feature",
  "properties": {
    "iso:country":"BE",
    "sg:address":"Echel 47",
    "sg:city":"Ninove (pollare)",
    "sg:classifiers":[
        {
            "category":"Professional",
            "subcategory":"Engineering",
            "type":"Services"
        }
    ],
    "sg:phone":"+32 475 47 26 48",
    "sg:postcode":"9401",
    "sg:province":"Oost-Vlaanderen",
    "sg:tags":[
        "civil",
        "offices-"
    ],
    "wof:name":"Pythagoras",
    "wof:placetype":"venue"
},
  "geometry": {"coordinates":[4.0013818741,50.819984436],"type":"Point"}
}