{
  "type": "Feature",
  "properties": {
    "iso:country":"BE",
    "sg:address":"Albertwal 36",
    "sg:city":"Tongeren",
    "sg:classifiers":[
        {
            "category":"Health Services",
            "subcategory":"Health Practitioner",
            "type":"Services"
        }
    ],
    "sg:phone":"+32 12 23 30 86",
    "sg:postcode":"3700",
    "sg:province":"Limburg",
    "sg:tags":[
        "psychologist"
    ],
    "wof:name":"Janssens I",
    "wof:placetype":"venue"
},
  "geometry": {"coordinates":[5.4612898827,50.7769775391],"type":"Point"}
}