{
  "type": "Feature",
  "properties": {
    "iso:country":"BE",
    "sg:address":"Grand Route 137",
    "sg:city":"Fexhe-le-haut-clocher",
    "sg:orig_category":"D\u00e9taillants en pi\u00e8ces and accessoires de voitures. Entretien and r\u00e9parations de voitures",
    "sg:phone":"+32 4 250 15 82",
    "sg:postcode":"4347",
    "sg:province":"Li\u00e8ge",
    "wof:name":"Soregi Gedima Pneus",
    "wof:placetype":"venue"
},
  "geometry": {"coordinates":[5.4037008286,50.6561737061],"type":"Point"}
}