{
  "type": "Feature",
  "properties": {
    "addr:full":"Prekelindenlaan 24 Sint-lambrechts-woluwe/woluwe-saint-lambert Bruxelles-Capitale 1200",
    "addr:housenumber":"24",
    "addr:postcode":"1200",
    "addr:street":"Prekelindenlaan",
    "iso:country":"BE",
    "sg:address":"Prekelindenlaan 24",
    "sg:city":"Sint-lambrechts-woluwe/woluwe-saint-lambert",
    "sg:orig_category":"Boekenuitgeverijen",
    "sg:phone":"+32 2 736 74 84",
    "sg:postcode":"1200",
    "sg:province":"Bruxelles-Capitale",
    "wof:name":"High Life De Belgique",
    "wof:placetype":"venue"
},
  "geometry": {"coordinates":[4.4105401039,50.8401145935],"type":"Point"}
}