{
  "type": "Feature",
  "properties": {
    "iso:country":"BE",
    "sg:address":"Avenue De Bouillon 196",
    "sg:city":"Libramont-chevigny (recogne)",
    "sg:classifiers":[
        {
            "category":"Autos & Motor Vehicles",
            "subcategory":"Automobile Sales",
            "type":"Retail Goods"
        }
    ],
    "sg:phone":"+32 61 22 59 08",
    "sg:postcode":"6800",
    "sg:province":"Luxembourg",
    "sg:tags":[
        "car",
        "used",
        "-"
    ],
    "wof:name":"G.t.s. Gillet T",
    "wof:placetype":"venue"
},
  "geometry": {"coordinates":[5.3593502045,49.9141998291],"type":"Point"}
}