{
  "type": "Feature",
  "properties": {
    "iso:country":"BE",
    "sg:address":"Lindestraat 62",
    "sg:city":"Wortegem-petegem",
    "sg:orig_category":"Dranken",
    "sg:phone":"+32 55 31 20 93",
    "sg:postcode":"9790",
    "sg:province":"Oost-Vlaanderen",
    "wof:name":"Daniel Speleers",
    "wof:placetype":"venue"
},
  "geometry": {"coordinates":[3.5549299717,50.8403358459],"type":"Point"}
}