{
  "type": "Feature",
  "properties": {
    "addr:full":"Rue Lambert Vandervelde 3 Bruxelles (watermael-boitsfort) Bruxelles-Capitale 1170",
    "addr:housenumber":"3",
    "addr:postcode":"1170",
    "addr:street":"Rue Lambert Vandervelde",
    "iso:country":"BE",
    "sg:address":"Rue Lambert Vandervelde 3",
    "sg:city":"Bruxelles (watermael-boitsfort)",
    "sg:classifiers":[
        {
            "category":"Personal",
            "subcategory":"Barber",
            "type":"Services"
        }
    ],
    "sg:phone":"+32 2 660 73 73",
    "sg:postcode":"1170",
    "sg:province":"Bruxelles-Capitale",
    "sg:tags":[
        "gentleman",
        "salon",
        "-",
        "hairdressing"
    ],
    "wof:name":"Maurice (coiffure Masculine)",
    "wof:placetype":"venue"
},
  "geometry": {"coordinates":[4.3980660439,50.8103103638],"type":"Point"}
}