{
  "type": "Feature",
  "properties": {
    "iso:country":"BE",
    "sg:address":"Nieuwpoortstraat 6",
    "sg:city":"Lokeren",
    "sg:orig_category":"Installation \u00e9lectrique r\u00e9sidentielle",
    "sg:phone":"+32 9 348 57 70",
    "sg:postcode":"9160",
    "sg:province":"Oost-Vlaanderen",
    "wof:name":"Marcel Van De Velde",
    "wof:placetype":"venue"
},
  "geometry": {"coordinates":[3.9254889488,51.1057395935],"type":"Point"}
}