{
  "type": "Feature",
  "properties": {
    "addr:full":"Schoendalestraat 379 Waregem West-Vlaanderen 8792",
    "addr:housenumber":"379",
    "addr:postcode":"8792",
    "addr:street":"Schoendalestraat",
    "iso:country":"BE",
    "sg:address":"Schoendalestraat 379",
    "sg:city":"Waregem",
    "sg:orig_category":"Experts-comptables",
    "sg:phone":"+32 56 72 56 45",
    "sg:postcode":"8792",
    "sg:province":"West-Vlaanderen",
    "wof:name":"Jean-marie Hillewaere",
    "wof:placetype":"venue"
},
  "geometry": {"coordinates":[3.3659219742,50.8904380798],"type":"Point"}
}