{
  "type": "Feature",
  "properties": {
    "iso:country":"BE",
    "sg:address":"Rue Monplaisir 20",
    "sg:city":"Beloeil",
    "sg:orig_category":"Rundveehouders",
    "sg:phone":"+32 69 68 91 16",
    "sg:postcode":"7972",
    "sg:province":"Hainaut",
    "wof:name":"Ferme Tondreau-baudart",
    "wof:placetype":"venue"
},
  "geometry": {"coordinates":[3.6716198921,50.5595970154],"type":"Point"}
}