{
  "type": "Feature",
  "properties": {
    "iso:country":"BE",
    "sg:address":"Rue Saint-martin 8",
    "sg:city":"Eghezee",
    "sg:orig_category":"Winkelinrichting and handelsuitrusting Gh",
    "sg:phone":"+32 81 51 21 55",
    "sg:postcode":"5310",
    "sg:province":"Namur",
    "wof:name":"Marie Libertiaux",
    "wof:placetype":"venue"
},
  "geometry": {"coordinates":[4.9093418121,50.559337616],"type":"Point"}
}