{
  "type": "Feature",
  "properties": {
    "iso:country":"BE",
    "sg:address":"Rue Du Rempart Des Moines 135 Box 34",
    "sg:city":"Bruxelles",
    "sg:classifiers":[
        {
            "category":"Social Services",
            "type":"Services"
        }
    ],
    "sg:phone":"+32 2 513 75 54",
    "sg:postcode":"1000",
    "sg:province":"Bruxelles-Capitale",
    "wof:name":"Foyer Bruxellois (le)",
    "wof:placetype":"venue"
},
  "geometry": {"coordinates":[4.3427500725,50.8487701416],"type":"Point"}
}