{
  "type": "Feature",
  "properties": {
    "iso:country":"BE",
    "sg:address":"Zone Industrielle 0",
    "sg:city":"Aubange",
    "sg:orig_category":"Gespecialiseerde niet-residenti\u00eble bouw",
    "sg:phone":"+32 63 37 17 77",
    "sg:postcode":"6790",
    "sg:province":"Luxembourg",
    "wof:name":"Lovema",
    "wof:placetype":"venue"
},
  "geometry": {"coordinates":[5.8051338196,49.5689849854],"type":"Point"}
}