{
  "type": "Feature",
  "properties": {
    "iso:country":"BE",
    "sg:address":"Ieperstraat 130",
    "sg:city":"Staden",
    "sg:orig_category":"Benzinestations and brandstoffen Herstellingen and onderhoud van auto's",
    "sg:phone":"+32 51 70 13 35",
    "sg:postcode":"8840",
    "sg:province":"West-Vlaanderen",
    "wof:name":"Garage Vanslambrouck",
    "wof:placetype":"venue"
},
  "geometry": {"coordinates":[3.0081670284,50.9691963196],"type":"Point"}
}