{
  "type": "Feature",
  "properties": {
    "addr:full":"Rue Saint-fargeau Ponthierry 34 Namur (temploux) Namur 5020",
    "addr:housenumber":"34",
    "addr:postcode":"5020",
    "addr:street":"Rue Saint-Fargeau Ponthierry",
    "iso:country":"BE",
    "sg:address":"Rue Saint-fargeau Ponthierry 34",
    "sg:city":"Namur (temploux)",
    "sg:classifiers":[
        {
            "category":"Retail",
            "subcategory":"Event Space",
            "type":"Services"
        }
    ],
    "sg:phone":"+32 81 56 78 18",
    "sg:postcode":"5020",
    "sg:province":"Namur",
    "sg:tags":[
        "rental",
        "-",
        "hall"
    ],
    "wof:name":"Ferme De L'escaille",
    "wof:placetype":"venue"
},
  "geometry": {"coordinates":[4.7952418327,50.4352035522],"type":"Point"}
}