{
  "type": "Feature",
  "properties": {
    "iso:country":"BE",
    "sg:address":"Rue Du Cowa 26b1",
    "sg:city":"Flemalle",
    "sg:orig_category":"M\u00e9decins and sp\u00e9cialistes",
    "sg:phone":"+32 4 275 57 56",
    "sg:postcode":"4400",
    "sg:province":"Li\u00e8ge",
    "wof:name":"Patrick Coucke",
    "wof:placetype":"venue"
},
  "geometry": {"coordinates":[5.4134559631,50.6158294678],"type":"Point"}
}