{
  "type": "Feature",
  "properties": {
    "iso:country":"BE",
    "sg:address":"Edegemsestraat 95",
    "sg:city":"Mortsel",
    "sg:orig_category":"M\u00e9decins and sp\u00e9cialistes",
    "sg:phone":"+32 3 449 75 94",
    "sg:postcode":"2640",
    "sg:province":"Antwerpen",
    "wof:name":"Bart Van Den Eynden",
    "wof:placetype":"venue"
},
  "geometry": {"coordinates":[4.4465551376,51.1684112549],"type":"Point"}
}