{
  "type": "Feature",
  "properties": {
    "addr:full":"Rue De Huy 15 Burdinne Li\u00e8ge 4210",
    "addr:housenumber":"15",
    "addr:postcode":"4210",
    "addr:street":"Rue De Huy",
    "iso:country":"BE",
    "sg:address":"Rue De Huy 15",
    "sg:city":"Burdinne",
    "sg:classifiers":[
        {
            "category":"Cafe",
            "type":"Food & Drink"
        }
    ],
    "sg:phone":"+32 85 71 27 61",
    "sg:postcode":"4210",
    "sg:province":"Li\u00e8ge",
    "sg:tags":[
        "caf\u00e9s"
    ],
    "wof:name":"Caf\u00c9 Le Relax",
    "wof:placetype":"venue"
},
  "geometry": {"coordinates":[5.0731091499,50.5827178955],"type":"Point"}
}