{
  "type": "Feature",
  "properties": {
    "addr:full":"Stotert 56 Balen (olmen) Antwerpen 2491",
    "addr:housenumber":"56",
    "addr:postcode":"2491",
    "addr:street":"Stotert",
    "iso:country":"BE",
    "sg:address":"Stotert 56",
    "sg:city":"Balen (olmen)",
    "sg:classifiers":[
        {
            "category":"Freight",
            "type":"Transportation"
        }
    ],
    "sg:phone":"+32 11 40 33 01",
    "sg:postcode":"2491",
    "sg:province":"Antwerpen",
    "sg:tags":[
        "-",
        "transport"
    ],
    "wof:name":"Adriaensen K",
    "wof:placetype":"venue"
},
  "geometry": {"coordinates":[5.1771168709,51.1293144226],"type":"Point"}
}