{
  "type": "Feature",
  "properties": {
    "addr:full":"Lebekestraat 37 Ninove (outer) Oost-Vlaanderen 9406",
    "addr:housenumber":"37",
    "addr:postcode":"9406",
    "addr:street":"Lebekestraat;Outer Oost-Vlaanderen",
    "iso:country":"BE",
    "sg:address":"Lebekestraat 37",
    "sg:city":"Ninove (outer)",
    "sg:orig_category":"Non-Classified Establishments",
    "sg:phone":"+32 54 32 83 37",
    "sg:postcode":"9406",
    "sg:province":"Oost-Vlaanderen",
    "wof:name":"Firma Raes Herman",
    "wof:placetype":"venue"
},
  "geometry": {"coordinates":[3.9894530773,50.8486328125],"type":"Point"}
}