{
  "type": "Feature",
  "properties": {
    "addr:full":"Rue Du Beemdgracht 2 Brussel/bruxelles Bruxelles-Capitale 1130",
    "addr:housenumber":"2",
    "addr:postcode":"1130",
    "addr:street":"Rue Du Beemdgracht;/",
    "iso:country":"BE",
    "sg:address":"Rue Du Beemdgracht 2",
    "sg:city":"Brussel/bruxelles",
    "sg:orig_category":"Enseignement maternel and primaire",
    "sg:phone":"+32 2 215 90 20",
    "sg:postcode":"1130",
    "sg:province":"Bruxelles-Capitale",
    "wof:name":"Vrije Basisschool",
    "wof:placetype":"venue"
},
  "geometry": {"coordinates":[4.4187679291,50.895160675],"type":"Point"}
}