{
  "type": "Feature",
  "properties": {
    "iso:country":"BE",
    "sg:address":"Rue Axheli\u00c8re",
    "sg:city":"Huy",
    "sg:orig_category":"Activit\u00e9s r\u00e9cr\u00e9atives diverses. Enseignement secondaire technique and professionnel. Enseignement se",
    "sg:phone":"+32 85 21 14 49",
    "sg:postcode":"4500",
    "sg:province":"Li\u00e8ge",
    "wof:name":"Echiquier Hutois",
    "wof:placetype":"venue"
},
  "geometry": {"coordinates":[5.2305212021,50.5248222351],"type":"Point"}
}