{
  "type": "Feature",
  "properties": {
    "iso:country":"BE",
    "sg:address":"Priester Daensstraat 9",
    "sg:city":"Lommel",
    "sg:orig_category":"Cleaning Agents For Trucks",
    "sg:phone":"+32 11 54 80 00",
    "sg:postcode":"3920",
    "sg:province":"Limburg",
    "wof:name":"Chrisal Nv",
    "wof:placetype":"venue"
},
  "geometry": {"coordinates":[5.2705669403,51.2169113159],"type":"Point"}
}