{
  "type": "Feature",
  "properties": {
    "addr:full":"Grand Route 210 Beyne-heusay Li\u00e8ge 4610",
    "addr:postcode":"4610",
    "addr:street":"Grand Route 210",
    "iso:country":"BE",
    "sg:address":"Grand Route 210",
    "sg:city":"Beyne-heusay",
    "sg:classifiers":[
        {
            "category":"Insurance",
            "subcategory":"Life Insurance",
            "type":"Services"
        }
    ],
    "sg:phone":"+32 4 367 63 52",
    "sg:postcode":"4610",
    "sg:province":"Li\u00e8ge",
    "sg:tags":[
        "assurance"
    ],
    "wof:name":"Laurette Delsemme",
    "wof:placetype":"venue"
},
  "geometry": {"coordinates":[5.6520648003,50.6228370667],"type":"Point"}
}