{
  "type": "Feature",
  "properties": {
    "addr:full":"Koninklijke Baan 341 Koksijde West-Vlaanderen 8670",
    "addr:housenumber":"341",
    "addr:postcode":"8670",
    "addr:street":"Koninklijke Baan",
    "iso:country":"BE",
    "sg:address":"Koninklijke Baan 341",
    "sg:city":"Koksijde",
    "sg:classifiers":[
        {
            "category":"Autos & Motor Vehicles",
            "subcategory":"Fuel & Gas Station",
            "type":"Retail Goods"
        }
    ],
    "sg:phone":"+32 58 52 45 50",
    "sg:postcode":"8670",
    "sg:province":"West-Vlaanderen",
    "wof:name":"Station Willy",
    "wof:placetype":"venue"
},
  "geometry": {"coordinates":[2.6268680096,51.1137161255],"type":"Point"}
}