{
  "type": "Feature",
  "properties": {
    "iso:country":"BE",
    "sg:address":"Waterloolaan 36",
    "sg:city":"Brussel/bruxelles",
    "sg:orig_category":"Juwelen and horloges",
    "sg:phone":"+32 2 511 67 01",
    "sg:postcode":"1000",
    "sg:province":"Bruxelles-Capitale",
    "wof:name":"Maison Bulgari",
    "wof:placetype":"venue"
},
  "geometry": {"coordinates":[4.3577818871,50.8373641968],"type":"Point"}
}