{
  "type": "Feature",
  "properties": {
    "iso:country":"BE",
    "sg:address":"Victor Hugostraat 26",
    "sg:city":"Antwerpen",
    "sg:classifiers":[
        {
            "category":"Education",
            "subcategory":"Special Training",
            "type":"Public Place"
        }
    ],
    "sg:phone":"+32 3 219 24 01",
    "sg:postcode":"2050",
    "sg:province":"Antwerpen",
    "sg:tags":[
        "school",
        "language"
    ],
    "wof:name":"Senior D",
    "wof:placetype":"venue"
},
  "geometry": {"coordinates":[4.3893070221,51.2286949158],"type":"Point"}
}