{
  "type": "Feature",
  "properties": {
    "addr:full":"Houtestraat 5 Mechelen Antwerpen 2811",
    "addr:housenumber":"5",
    "addr:postcode":"2811",
    "addr:street":"Houtestraat",
    "iso:country":"BE",
    "sg:address":"Houtestraat 5",
    "sg:city":"Mechelen",
    "sg:orig_category":"Producteurs de l\u00e9gumes",
    "sg:phone":"+32 15 41 40 52",
    "sg:postcode":"2811",
    "sg:province":"Antwerpen",
    "wof:name":"Marcel De Hoef",
    "wof:placetype":"venue"
},
  "geometry": {"coordinates":[4.4352321625,51.0034828186],"type":"Point"}
}