{
  "type": "Feature",
  "properties": {
    "iso:country":"BE",
    "sg:address":"Waterloostraat 6",
    "sg:city":"Knokke-heist",
    "sg:orig_category":"Technische studies and ingenieursactiviteiten",
    "sg:phone":"+32 50 60 80 28",
    "sg:postcode":"8301",
    "sg:province":"West-Vlaanderen",
    "wof:name":"Evb Consulting",
    "wof:placetype":"venue"
},
  "geometry": {"coordinates":[3.2763528824,51.3440895081],"type":"Point"}
}