{
  "type": "Feature",
  "properties": {
    "addr:full":"Diksmuidseweg 374 Ieper West-Vlaanderen 8904",
    "addr:housenumber":"374",
    "addr:postcode":"8904",
    "iso:country":"BE",
    "sg:address":"Diksmuidseweg 374",
    "sg:city":"Ieper",
    "sg:orig_category":"Epiceries",
    "sg:phone":"+32 57 42 10 69",
    "sg:postcode":"8904",
    "sg:province":"West-Vlaanderen",
    "wof:name":"Lena Bourree",
    "wof:placetype":"venue"
},
  "geometry": {"coordinates":[2.8598051071,50.8936347961],"type":"Point"}
}