{
  "type": "Feature",
  "properties": {
    "iso:country":"BE",
    "sg:address":"Lansival 8",
    "sg:city":"Lierneux",
    "sg:orig_category":"Rundveehouders",
    "sg:phone":"+32 80 31 91 81",
    "sg:postcode":"4990",
    "sg:province":"Li\u00e8ge",
    "wof:name":"Lucienne Noel",
    "wof:placetype":"venue"
},
  "geometry": {"coordinates":[5.7744569778,50.2952728271],"type":"Point"}
}