{
  "type": "Feature",
  "properties": {
    "addr:full":"Rue Georges Bodard 14 Musson Luxembourg 6750",
    "addr:housenumber":"14",
    "addr:postcode":"6750",
    "addr:street":"Rue Georges Bodard",
    "iso:country":"BE",
    "sg:address":"Rue Georges Bodard 14",
    "sg:city":"Musson",
    "sg:orig_category":"Voedingsspeciaalzaken",
    "sg:phone":"+32 63 67 83 18",
    "sg:postcode":"6750",
    "sg:province":"Luxembourg",
    "wof:name":"Jean-paul Leva Giampaolo Dit",
    "wof:placetype":"venue"
},
  "geometry": {"coordinates":[5.7101759911,49.5580291748],"type":"Point"}
}