{
  "type": "Feature",
  "properties": {
    "addr:full":"Chauss\u00e9e De L'orangerie 104 Wavre Brabant Wallon 1300",
    "addr:housenumber":"104;1300",
    "addr:street":"Chausse\u0301E De L'Orangerie",
    "iso:country":"BE",
    "sg:address":"Chauss\u00e9e De L'orangerie 104",
    "sg:city":"Wavre",
    "sg:classifiers":[
        {
            "category":"Building & Trades",
            "subcategory":"Electrical",
            "type":"Services"
        }
    ],
    "sg:phone":"+32 10 22 39 72",
    "sg:postcode":"1300",
    "sg:province":"Brabant Wallon",
    "sg:tags":[
        "electric",
        "-",
        "housewiring",
        "contractor"
    ],
    "wof:name":"Electricit\u00e9 Du Parc Des Saules",
    "wof:placetype":"venue"
},
  "geometry": {"coordinates":[4.6074252129,50.7257118225],"type":"Point"}
}