{
  "type": "Feature",
  "properties": {
    "addr:full":"Rue Saint-nicolas 482 Li\u00c8ge Li\u00e8ge 4000",
    "addr:housenumber":"482",
    "addr:postcode":"4000",
    "addr:street":"Rue Saint-Nicolas",
    "iso:country":"BE",
    "sg:address":"Rue Saint-nicolas 482",
    "sg:city":"Li\u00c8ge",
    "sg:orig_category":"Opticiens",
    "sg:phone":"+32 4 226 57 86",
    "sg:postcode":"4000",
    "sg:province":"Li\u00e8ge",
    "wof:name":"Maison Bartholome",
    "wof:placetype":"venue"
},
  "geometry": {"coordinates":[5.536272049,50.6399612427],"type":"Point"}
}