{
  "type": "Feature",
  "properties": {
    "addr:full":"Veldeken 36 Nevele Oost-Vlaanderen 9850",
    "addr:housenumber":"36",
    "addr:postcode":"9850",
    "addr:street":"Veldeken",
    "iso:country":"BE",
    "sg:address":"Veldeken 36",
    "sg:city":"Nevele",
    "sg:classifiers":[
        {
            "category":"Farming",
            "subcategory":"Crops",
            "type":"Manufacturing & Wholesale Goods"
        }
    ],
    "sg:phone":"+32 9 371 68 08",
    "sg:postcode":"9850",
    "sg:province":"Oost-Vlaanderen",
    "sg:tags":[
        "vegetable",
        "fruit",
        "-",
        "grower"
    ],
    "wof:name":"Cornelis",
    "wof:placetype":"venue"
},
  "geometry": {"coordinates":[3.5109040737,51.0594291687],"type":"Point"}
}