{
  "type": "Feature",
  "properties": {
    "addr:full":"Guldensporenlaan 41 Torhout West-Vlaanderen 8820",
    "addr:housenumber":"41",
    "addr:postcode":"8820",
    "addr:street":"Guldensporenlaan",
    "iso:country":"BE",
    "sg:address":"Guldensporenlaan 41",
    "sg:city":"Torhout",
    "sg:orig_category":"Drukkerijen and copyshops",
    "sg:phone":"+32 50 21 44 07",
    "sg:postcode":"8820",
    "sg:province":"West-Vlaanderen",
    "wof:name":"Jan Hemeryck",
    "wof:placetype":"venue"
},
  "geometry": {"coordinates":[3.0671670437,51.0903434753],"type":"Point"}
}