{
  "type": "Feature",
  "properties": {
    "addr:full":"Ruytenburgstraat 11 Antwerpen (berchem) Antwerpen 2600",
    "addr:housenumber":"11",
    "addr:postcode":"2600",
    "addr:street":"Ruytenburgstraat;Antwerpen",
    "iso:country":"BE",
    "sg:address":"Ruytenburgstraat 11",
    "sg:city":"Antwerpen (berchem)",
    "sg:classifiers":[
        {
            "category":"Professional",
            "subcategory":"Computer Services",
            "type":"Services"
        }
    ],
    "sg:phone":"+32 3 239 84 89",
    "sg:postcode":"2600",
    "sg:province":"Antwerpen",
    "sg:tags":[
        "webdesign",
        "-",
        "internet"
    ],
    "wof:name":"Berger Information Systems Nv",
    "wof:placetype":"venue"
},
  "geometry": {"coordinates":[4.4174151421,51.1974411011],"type":"Point"}
}