{
  "type": "Feature",
  "properties": {
    "iso:country":"BE",
    "sg:address":"Jacques Eggermontstraat 63",
    "sg:city":"Gent",
    "sg:orig_category":"Bagage and lederwaren Schoenen",
    "sg:phone":"+32 9 231 24 77",
    "sg:postcode":"9050",
    "sg:province":"Oost-Vlaanderen",
    "wof:name":"Huis Enig",
    "wof:placetype":"venue"
},
  "geometry": {"coordinates":[3.740019083,51.0369720459],"type":"Point"}
}