{
  "type": "Feature",
  "properties": {
    "addr:full":"Drongensesteenweg 12 Lovendegem Oost-Vlaanderen 9921",
    "addr:housenumber":"12",
    "addr:postcode":"9921",
    "addr:street":"Drongensesteenweg",
    "iso:country":"BE",
    "sg:address":"Drongensesteenweg 12",
    "sg:city":"Lovendegem",
    "sg:orig_category":"SMEEDWERK, METAALBEWERKING AND POEDERMETALLURGIE",
    "sg:phone":"+32 9 226 63 42",
    "sg:postcode":"9921",
    "sg:province":"Oost-Vlaanderen",
    "wof:name":"Van Parys",
    "wof:placetype":"venue"
},
  "geometry": {"coordinates":[3.6376600266,51.0873756409],"type":"Point"}
}