{
  "type": "Feature",
  "properties": {
    "addr:full":"Parochiaansstraat 15 Brussel/bruxelles Bruxelles-Capitale 1000",
    "addr:housenumber":"15",
    "addr:postcode":"1000",
    "addr:street":"Parochiaansstraat;/",
    "iso:country":"BE",
    "sg:address":"Parochiaansstraat 15",
    "sg:city":"Brussel/bruxelles",
    "sg:orig_category":"Instellingen voor probleemkinderen Kindertehuizen",
    "sg:phone":"+32 2 553 68 12",
    "sg:postcode":"1000",
    "sg:province":"Bruxelles-Capitale",
    "wof:name":"Gemeenschapsinstelling",
    "wof:placetype":"venue"
},
  "geometry": {"coordinates":[4.3596801758,50.8471298218],"type":"Point"}
}