{
  "type": "Feature",
  "properties": {
    "addr:full":"Wingensesteenweg 1 A Tielt West-Vlaanderen 8700",
    "addr:housenumber":"1 a",
    "addr:postcode":"8700",
    "addr:street":"Wingensesteenweg",
    "iso:country":"BE",
    "sg:address":"Wingensesteenweg 1 A",
    "sg:city":"Tielt",
    "sg:orig_category":"Entretien and r\u00e9parations de voitures",
    "sg:phone":"+32 51 40 90 80",
    "sg:postcode":"8700",
    "sg:province":"West-Vlaanderen",
    "wof:name":"Metaglas",
    "wof:placetype":"venue"
},
  "geometry": {"coordinates":[3.3227460384,51.0041923523],"type":"Point"}
}