{
  "type": "Feature",
  "properties": {
    "iso:country":"BE",
    "sg:address":"Sint-truiderstraat 36",
    "sg:city":"Tongeren",
    "sg:orig_category":"Eclairage et \u00e9quipements du foyer",
    "sg:phone":"+32 12 23 47 17",
    "sg:postcode":"3700",
    "sg:province":"Limburg",
    "wof:name":"Huis Plejade",
    "wof:placetype":"venue"
},
  "geometry": {"coordinates":[5.461411953,50.7801170349],"type":"Point"}
}