{
  "type": "Feature",
  "properties": {
    "iso:country":"BE",
    "sg:address":"Turcksinstraat 37",
    "sg:city":"Machelen",
    "sg:classifiers":[
        {
            "category":"Shopping",
            "subcategory":"Clothing, Apparel, & Fashions",
            "type":"Retail Goods"
        }
    ],
    "sg:phone":"+32 2 305 45 88",
    "sg:postcode":"1830",
    "sg:province":"Vlaams-Brabant",
    "sg:tags":[
        "boutique"
    ],
    "wof:name":"Dominiek's Boetiek",
    "wof:placetype":"venue"
},
  "geometry": {"coordinates":[4.438888073,50.9146461487],"type":"Point"}
}