{
  "type": "Feature",
  "properties": {
    "iso:country":"BE",
    "sg:address":"Rue Du Commerce 61",
    "sg:city":"Charleroi (montignies-sur-sambre)",
    "sg:orig_category":"Non-Classified Establishments",
    "sg:phone":"+32 71 41 53 95",
    "sg:postcode":"6061",
    "sg:province":"Hainaut",
    "wof:name":"Derameaux J",
    "wof:placetype":"venue"
},
  "geometry": {"coordinates":[4.4615511894,50.4155540466],"type":"Point"}
}