{
  "type": "Feature",
  "properties": {
    "addr:full":"Rue Des Taxandres 8 Box 5 Bruxelles (etterbeek) Bruxelles-Capitale 1040",
    "addr:housenumber":"8;5",
    "addr:postcode":"1040",
    "addr:street":"Rue Des Taxandres;Box",
    "iso:country":"BE",
    "sg:address":"Rue Des Taxandres 8 Box 5",
    "sg:city":"Bruxelles (etterbeek)",
    "sg:classifiers":[
        {
            "category":"Arena",
            "subcategory":"Sports Club",
            "type":"Entertainment"
        }
    ],
    "sg:phone":"+32 2 734 49 71",
    "sg:postcode":"1040",
    "sg:province":"Bruxelles-Capitale",
    "sg:tags":[
        "martial art",
        "accessory"
    ],
    "wof:name":"Brussels Aikido & Budo Federation",
    "wof:placetype":"venue"
},
  "geometry": {"coordinates":[4.4028291702,50.8366012573],"type":"Point"}
}