{
  "type": "Feature",
  "properties": {
    "iso:country":"BE",
    "sg:address":"Heidestraat 104",
    "sg:city":"Heusden-zolder",
    "sg:orig_category":"Artsen and specialisten",
    "sg:phone":"+32 11 87 36 75",
    "sg:postcode":"3550",
    "sg:province":"Limburg",
    "wof:name":"Marleen De Fraeye",
    "wof:placetype":"venue"
},
  "geometry": {"coordinates":[5.2886772156,50.9806213379],"type":"Point"}
}