{
  "type": "Feature",
  "properties": {
    "iso:country":"BE",
    "sg:address":"Lausbedstraat 8",
    "sg:city":"Maasmechelen",
    "sg:classifiers":[
        {
            "category":"Retail",
            "subcategory":"Laundry & Dry Cleaning",
            "type":"Services"
        }
    ],
    "sg:phone":"+32 89 77 78 74",
    "sg:postcode":"3630",
    "sg:province":"Limburg",
    "wof:name":"Pro Lease Belgium Nv",
    "wof:placetype":"venue"
},
  "geometry": {"coordinates":[5.700152874,50.9500541687],"type":"Point"}
}