{
  "type": "Feature",
  "properties": {
    "iso:country":"BE",
    "sg:address":"Nieuwe Beggaardenstraat 37",
    "sg:city":"Mechelen",
    "sg:orig_category":"Pharmaciens",
    "sg:phone":"+32 15 20 19 28",
    "sg:postcode":"2800",
    "sg:province":"Antwerpen",
    "wof:name":"Apotheek De Voorzorg",
    "wof:placetype":"venue"
},
  "geometry": {"coordinates":[4.4736890793,51.0296325684],"type":"Point"}
}