{
  "type": "Feature",
  "properties": {
    "iso:country":"BE",
    "sg:address":"Rue Du Parc 7",
    "sg:city":"Marchin (vyle-et-tharoul)",
    "sg:classifiers":[
        {
            "category":"Building & Trades",
            "subcategory":"Plumbing",
            "type":"Services"
        }
    ],
    "sg:phone":"+32 85 41 36 46",
    "sg:postcode":"4570",
    "sg:province":"Li\u00e8ge",
    "sg:tags":[
        "repair",
        "mainten",
        "-",
        "central",
        "heating"
    ],
    "wof:name":"Michaux E",
    "wof:placetype":"venue"
},
  "geometry": {"coordinates":[5.2660279274,50.4468421936],"type":"Point"}
}