{
  "type": "Feature",
  "properties": {
    "iso:country":"BE",
    "sg:address":"Leireken 115",
    "sg:city":"Merchtem",
    "sg:orig_category":"Artsen and specialisten",
    "sg:phone":"+32 52 37 20 75",
    "sg:postcode":"1785",
    "sg:province":"Vlaams-Brabant",
    "wof:name":"R. Van Bael",
    "wof:placetype":"venue"
},
  "geometry": {"coordinates":[4.2269701958,50.9840431213],"type":"Point"}
}