{
  "type": "Feature",
  "properties": {
    "iso:country":"BE",
    "sg:address":"Square Gutenberg 25",
    "sg:city":"Bruxelles",
    "sg:classifiers":[
        {
            "category":"Bars & Pubs",
            "type":"Food & Drink"
        }
    ],
    "sg:phone":"+32 2 230 73 90",
    "sg:postcode":"1000",
    "sg:province":"Bruxelles-Capitale",
    "sg:tags":[
        "tavern"
    ],
    "wof:name":"Gutenberg",
    "wof:placetype":"venue"
},
  "geometry": {"coordinates":[4.3778800964,50.8488235474],"type":"Point"}
}