{
  "type": "Feature",
  "properties": {
    "addr:full":"Mendelssohnlaan 23 Brecht Antwerpen 2960",
    "addr:housenumber":"23",
    "addr:postcode":"2960",
    "addr:street":"Mendelssohnlaan",
    "iso:country":"BE",
    "sg:address":"Mendelssohnlaan 23",
    "sg:city":"Brecht",
    "sg:orig_category":"Installation de menuiserie en bois and plastique",
    "sg:phone":"+32 3 633 20 14",
    "sg:postcode":"2960",
    "sg:province":"Antwerpen",
    "wof:name":"Fa. Bubendorff",
    "wof:placetype":"venue"
},
  "geometry": {"coordinates":[4.6415200233,51.3512115479],"type":"Point"}
}