{
  "type": "Feature",
  "properties": {
    "iso:country":"BE",
    "sg:address":"Rue Du Rogissart 6",
    "sg:city":"Tubize",
    "sg:orig_category":"Loodgieterij, verwarming and sanitaire installaties",
    "sg:phone":"+32 2 355 03 43",
    "sg:postcode":"1480",
    "sg:province":"Brabant Wallon",
    "wof:name":"Yves Postelmans",
    "wof:placetype":"venue"
},
  "geometry": {"coordinates":[4.2313189507,50.6827201843],"type":"Point"}
}