{
  "type": "Feature",
  "properties": {
    "addr:full":"Rue Rogier 61 Namur Namur 5000",
    "addr:housenumber":"61",
    "addr:postcode":"5000",
    "addr:street":"Rue Rogier",
    "iso:country":"BE",
    "sg:address":"Rue Rogier 61",
    "sg:city":"Namur",
    "sg:classifiers":[
        {
            "category":"Shopping",
            "subcategory":"Baby Store",
            "type":"Retail Goods"
        }
    ],
    "sg:phone":"+32 81 22 04 45",
    "sg:postcode":"5000",
    "sg:province":"Namur",
    "sg:tags":[
        "-",
        "accessory"
    ],
    "wof:name":"Baby Hall Sprl",
    "wof:placetype":"venue"
},
  "geometry": {"coordinates":[4.8682928085,50.467590332],"type":"Point"}
}