{
  "type": "Feature",
  "properties": {
    "iso:country":"BE",
    "sg:address":"Putsebaan 2",
    "sg:city":"Antwerpen",
    "sg:orig_category":"Slagers Zuivelproducten",
    "sg:phone":"+32 3 568 61 00",
    "sg:postcode":"2040",
    "sg:province":"Antwerpen",
    "wof:name":"Marc Beyers",
    "wof:placetype":"venue"
},
  "geometry": {"coordinates":[4.3309559822,51.3577919006],"type":"Point"}
}