{
  "type": "Feature",
  "properties": {
    "iso:country":"BE",
    "sg:address":"Europark 1070",
    "sg:city":"Houthalen-helchteren",
    "sg:classifiers":[
        {
            "category":"Shopping",
            "subcategory":"Crafts & Fabrics",
            "type":"Retail Goods"
        }
    ],
    "sg:phone":"+32 11 52 42 57",
    "sg:postcode":"3530",
    "sg:province":"Limburg",
    "sg:tags":[
        "textile",
        "linen",
        "clothing"
    ],
    "wof:name":"Formafoam Belgie Nv",
    "wof:placetype":"venue"
},
  "geometry": {"coordinates":[5.4049201012,51.0440063477],"type":"Point"}
}