{
  "type": "Feature",
  "properties": {
    "iso:country":"BE",
    "sg:address":"Heuvel 19",
    "sg:city":"Lommel",
    "sg:orig_category":"Diverse bouwafwerking and reiniging",
    "sg:phone":"+32 11 54 67 26",
    "sg:postcode":"3920",
    "sg:province":"Limburg",
    "wof:name":"Carlo Hendrikx",
    "wof:placetype":"venue"
},
  "geometry": {"coordinates":[5.3383450508,51.2393341064],"type":"Point"}
}