{
  "type": "Feature",
  "properties": {
    "iso:country":"BE",
    "sg:address":"Rue Des Prof. Jeener Et Brachet 12",
    "sg:city":"Gosselies",
    "sg:classifiers":[
        {
            "category":"Professional",
            "subcategory":"Engineering",
            "type":"Services"
        }
    ],
    "sg:phone":"+32 71 37 89 02",
    "sg:postcode":"6041",
    "sg:province":"Hainaut",
    "sg:tags":[
        "bio",
        "genetic"
    ],
    "wof:name":"Henogen S.a.",
    "wof:placetype":"venue"
},
  "geometry": {"coordinates":[4.465195179,50.4714546204],"type":"Point"}
}