{
  "type": "Feature",
  "properties": {
    "addr:full":"Rue De Le Jardin 1a Sainte-ode (lavacherie) Luxembourg 6681",
    "addr:housenumber":"1a",
    "addr:postcode":"6681",
    "addr:street":"Rue De Le Jardin",
    "iso:country":"BE",
    "sg:address":"Rue De Le Jardin 1a",
    "sg:city":"Sainte-ode (lavacherie)",
    "sg:classifiers":[
        {
            "category":"Manufacturing",
            "subcategory":"Furniture",
            "type":"Manufacturing & Wholesale Goods"
        }
    ],
    "sg:phone":"+32 61 68 85 41",
    "sg:postcode":"6681",
    "sg:province":"Luxembourg",
    "sg:tags":[
        "made",
        "-",
        "custom"
    ],
    "wof:name":"Mercenier J-meunier I",
    "wof:placetype":"venue"
},
  "geometry": {"coordinates":[5.5106501579,50.05260849],"type":"Point"}
}