{
  "type": "Feature",
  "properties": {
    "addr:full":"Rue De L'etoile 66 Morlanwelz Hainaut 7140",
    "addr:housenumber":"66",
    "addr:postcode":"7140",
    "addr:street":"Rue De L'Etoile",
    "iso:country":"BE",
    "sg:address":"Rue De L'etoile 66",
    "sg:city":"Morlanwelz",
    "sg:orig_category":"Installation \u00e9lectrique r\u00e9sidentielle. Construction de maisons. Installation \u00e9lectrique industrielle",
    "sg:phone":"+32 64 45 13 11",
    "sg:postcode":"7140",
    "sg:province":"Hainaut",
    "wof:name":"Manini",
    "wof:placetype":"venue"
},
  "geometry": {"coordinates":[4.2562828064,50.4696502686],"type":"Point"}
}