{
  "type": "Feature",
  "properties": {
    "iso:country":"BE",
    "sg:address":"Rue Hector Chainaye 2",
    "sg:city":"Li\u00c8ge",
    "sg:orig_category":"Kinderopvang",
    "sg:phone":"+32 4 342 09 59",
    "sg:postcode":"4020",
    "sg:province":"Li\u00e8ge",
    "wof:name":"Cr\u00c8che De Droixhe",
    "wof:placetype":"venue"
},
  "geometry": {"coordinates":[5.6060118675,50.6466598511],"type":"Point"}
}