{
  "type": "Feature",
  "properties": {
    "iso:country":"BE",
    "sg:address":"Koekoekstraat 22",
    "sg:city":"Houthalen-helchteren",
    "sg:orig_category":"Artsen and specialisten",
    "sg:phone":"+32 89 38 45 39",
    "sg:postcode":"3530",
    "sg:province":"Limburg",
    "wof:name":"Rudi Hoogmartens",
    "wof:placetype":"venue"
},
  "geometry": {"coordinates":[5.4547557831,51.0161972046],"type":"Point"}
}