{
  "type": "Feature",
  "properties": {
    "addr:full":"Crombachstr 103 Saint-vith Li\u00e8ge 4780",
    "addr:housenumber":"103",
    "addr:postcode":"4780",
    "addr:street":"Saint-Vith Lie\u0300Ge",
    "iso:country":"BE",
    "sg:address":"Crombachstr 103",
    "sg:city":"Saint-vith",
    "sg:classifiers":[
        {
            "category":"Building & Trades",
            "subcategory":"Construction",
            "type":"Services"
        }
    ],
    "sg:phone":"+32 80 22 87 42",
    "sg:postcode":"4780",
    "sg:province":"Li\u00e8ge",
    "sg:tags":[
        "carpenter"
    ],
    "wof:name":"Servaty W",
    "wof:placetype":"venue"
},
  "geometry": {"coordinates":[6.1256680489,50.2810821533],"type":"Point"}
}