{
  "type": "Feature",
  "properties": {
    "iso:country":"BE",
    "sg:address":"Damse Vaart Zuid 6",
    "sg:city":"Brugge",
    "sg:orig_category":"Agences d'exp\u00e9dition",
    "sg:phone":"+32 50 36 36 72",
    "sg:postcode":"8310",
    "sg:province":"West-Vlaanderen",
    "wof:name":"Baisco",
    "wof:placetype":"venue"
},
  "geometry": {"coordinates":[3.2355630398,51.2217788696],"type":"Point"}
}