{
  "type": "Feature",
  "properties": {
    "addr:full":"Fourneau Marchand 17 Etalle (sainte-marie-sur-semois) Luxembourg 6740",
    "addr:housenumber":"17",
    "addr:postcode":"6740",
    "iso:country":"BE",
    "sg:address":"Fourneau Marchand 17",
    "sg:city":"Etalle (sainte-marie-sur-semois)",
    "sg:classifiers":[
        {
            "category":"Farming",
            "subcategory":"Fish & Marine Products",
            "type":"Manufacturing & Wholesale Goods"
        }
    ],
    "sg:phone":"+32 63 45 52 49",
    "sg:postcode":"6740",
    "sg:province":"Luxembourg",
    "sg:tags":[
        "breeding"
    ],
    "wof:name":"Fourneau Marchand (pisciculture Du)",
    "wof:placetype":"venue"
},
  "geometry": {"coordinates":[5.5693178177,49.641330719],"type":"Point"}
}