{
  "type": "Feature",
  "properties": {
    "addr:full":"Markstraat 15 Lichtervelde West-Vlaanderen 8810",
    "addr:housenumber":"15",
    "addr:postcode":"8810",
    "addr:street":"Markstraat",
    "iso:country":"BE",
    "sg:address":"Markstraat 15",
    "sg:city":"Lichtervelde",
    "sg:orig_category":"Electrom\u00e9nager, t\u00e9l\u00e9visions and radios. Mat\u00e9riel de T\u00e9l\u00e9communication",
    "sg:phone":"+32 51 72 29 90",
    "sg:postcode":"8810",
    "sg:province":"West-Vlaanderen",
    "wof:name":"Vandevelde",
    "wof:placetype":"venue"
},
  "geometry": {"coordinates":[3.1386458874,51.0266914368],"type":"Point"}
}