{
  "type": "Feature",
  "properties": {
    "addr:full":"Rue L\u00c9pold Iii 33 Pont-a-celles Hainaut 6230",
    "addr:housenumber":"33",
    "addr:postcode":"6230",
    "addr:street":"Rue Le\u0301Pold Iii",
    "iso:country":"BE",
    "sg:address":"Rue L\u00c9pold Iii 33",
    "sg:city":"Pont-a-celles",
    "sg:orig_category":"Studios photographiques. Agences de presse",
    "sg:phone":"+32 71 84 55 10",
    "sg:postcode":"6230",
    "sg:province":"Hainaut",
    "wof:name":"Studio Flemal",
    "wof:placetype":"venue"
},
  "geometry": {"coordinates":[4.3707361221,50.507106781],"type":"Point"}
}