{
  "type": "Feature",
  "properties": {
    "iso:country":"BE",
    "sg:address":"Leuvensesteenweg 456",
    "sg:city":"Kortenberg",
    "sg:orig_category":"Aeronautic Motor-cars Vehicles and Transport Equipment",
    "sg:phone":"+32 2 757 01 02",
    "sg:postcode":"3071",
    "sg:province":"Vlaams-Brabant",
    "wof:name":"Act Research Bvba",
    "wof:placetype":"venue"
},
  "geometry": {"coordinates":[4.5601558685,50.8903465271],"type":"Point"}
}