{
  "type": "Feature",
  "properties": {
    "addr:full":"Petit Pourrain 8a Gesves Namur 5340",
    "addr:housenumber":"8a",
    "addr:postcode":"5340",
    "iso:country":"BE",
    "sg:address":"Petit Pourrain 8a",
    "sg:city":"Gesves",
    "sg:classifiers":[
        {
            "category":"Building & Trades",
            "subcategory":"Construction",
            "type":"Services"
        }
    ],
    "sg:phone":"+32 83 67 73 04",
    "sg:postcode":"5340",
    "sg:province":"Namur",
    "sg:tags":[
        "installation",
        "-",
        "central",
        "heating"
    ],
    "wof:name":"Guissard P",
    "wof:placetype":"venue"
},
  "geometry": {"coordinates":[5.0602798462,50.3924331665],"type":"Point"}
}