{
  "type": "Feature",
  "properties": {
    "addr:full":"Plantin & Moretuslei 295 Borgerhout Antwerpen 2140",
    "addr:housenumber":"295;2140",
    "addr:street":"Borgerhout Antwerpen",
    "iso:country":"BE",
    "sg:address":"Plantin & Moretuslei 295",
    "sg:city":"Borgerhout",
    "sg:orig_category":"Banken and kredietinstellingen",
    "sg:phone":"+32 3 217 51 11",
    "sg:postcode":"2140",
    "sg:province":"Antwerpen",
    "wof:name":"Van Breda & Co",
    "wof:placetype":"venue"
},
  "geometry": {"coordinates":[4.4327588081,51.2093162537],"type":"Point"}
}