{
  "type": "Feature",
  "properties": {
    "addr:full":"Rue Dachet 35b Namur Namur 5100",
    "addr:housenumber":"35b",
    "addr:postcode":"5100",
    "addr:street":"Rue Dachet",
    "iso:country":"BE",
    "sg:address":"Rue Dachet 35b",
    "sg:city":"Namur",
    "sg:orig_category":"Foto-uitrusting Fotografen and fotostudio's",
    "sg:phone":"+32 81 46 18 00",
    "sg:postcode":"5100",
    "sg:province":"Namur",
    "wof:name":"Positif Bucolic\u00b4images",
    "wof:placetype":"venue"
},
  "geometry": {"coordinates":[4.8713731766,50.4213905334],"type":"Point"}
}