{
  "type": "Feature",
  "properties": {
    "addr:full":"Grotenbergestraat 29 Zottegem Oost-Vlaanderen 9620",
    "addr:housenumber":"29",
    "addr:postcode":"9620",
    "addr:street":"Grotenbergestraat",
    "iso:country":"BE",
    "sg:address":"Grotenbergestraat 29",
    "sg:city":"Zottegem",
    "sg:classifiers":[
        {
            "category":"Autos & Motor Vehicles",
            "subcategory":"Auto Supplies",
            "type":"Retail Goods"
        }
    ],
    "sg:phone":"+32 9 360 73 10",
    "sg:postcode":"9620",
    "sg:province":"Oost-Vlaanderen",
    "sg:tags":[
        "automobile",
        "-",
        "radio"
    ],
    "wof:name":"Exclusieve Car Design",
    "wof:placetype":"venue"
},
  "geometry": {"coordinates":[3.8171229362,50.872051239],"type":"Point"}
}