{
  "type": "Feature",
  "properties": {
    "iso:country":"BE",
    "sg:address":"Hippolyte Meeuwsstraat 40",
    "sg:city":"Wijnegem",
    "sg:classifiers":[
        {
            "category":"Arts & Performance",
            "subcategory":"Symphony",
            "type":"Entertainment"
        }
    ],
    "sg:phone":"+32 3 353 07 43",
    "sg:postcode":"2110",
    "sg:province":"Antwerpen",
    "sg:tags":[
        "orchestra"
    ],
    "wof:name":"The Dazzling Dixie Dream Streetband",
    "wof:placetype":"venue"
},
  "geometry": {"coordinates":[4.5418701172,51.2269515991],"type":"Point"}
}