{
  "type": "Feature",
  "properties": {
    "iso:country":"BE",
    "sg:address":"Rue De Diekirch 16",
    "sg:city":"Arlon",
    "sg:orig_category":"Dameskledingzaken Herenkledingzaken",
    "sg:phone":"+32 63 23 55 84",
    "sg:postcode":"6700",
    "sg:province":"Luxembourg",
    "wof:name":"Maison Dany's",
    "wof:placetype":"venue"
},
  "geometry": {"coordinates":[5.8125648499,49.6847610474],"type":"Point"}
}