{
  "type": "Feature",
  "properties": {
    "iso:country":"BE",
    "sg:address":"Kon. Astridplein 21",
    "sg:city":"Kruibeke",
    "sg:orig_category":"Openbare bibliotheken and archieven",
    "sg:phone":"+32 3 744 17 52",
    "sg:postcode":"9150",
    "sg:province":"Oost-Vlaanderen",
    "wof:name":"Gemeentelijke Openbare Bibliotheek",
    "wof:placetype":"venue"
},
  "geometry": {"coordinates":[4.3002800941,51.1466712952],"type":"Point"}
}