{
  "type": "Feature",
  "properties": {
    "iso:country":"BE",
    "sg:address":"Beneluxln 1",
    "sg:city":"Zelzate",
    "sg:classifiers":[
        {
            "category":"Banks & Credit Unions",
            "subcategory":"Investment Brokerage",
            "type":"Services"
        }
    ],
    "sg:phone":"+32 9 344 51 43",
    "sg:postcode":"9060",
    "sg:province":"Oost-Vlaanderen",
    "sg:tags":[
        "-",
        "transport",
        "related"
    ],
    "wof:name":"Vandevyver Douane Agentschap",
    "wof:placetype":"venue"
},
  "geometry": {"coordinates":[3.7997100353,51.2026863098],"type":"Point"}
}