{
  "type": "Feature",
  "properties": {
    "iso:country":"BE",
    "sg:address":"Les Plenesses 75",
    "sg:city":"Thimister-clermont",
    "sg:orig_category":"Eleveurs and marchands de porcs. Eleveurs de bovins",
    "sg:phone":"+32 87 44 65 52",
    "sg:postcode":"4890",
    "sg:province":"Li\u00e8ge",
    "wof:name":"Ren\u00c9 Schonbrodt",
    "wof:placetype":"venue"
},
  "geometry": {"coordinates":[5.8746581078,50.6339225769],"type":"Point"}
}