{
  "type": "Feature",
  "properties": {
    "iso:country":"BE",
    "sg:address":"Goor 23",
    "sg:city":"Kasterlee",
    "sg:orig_category":"RESTAURANTS: SALLES DE CONF\u00c9RENCES AND DE R\u00c9CEPTIONS",
    "sg:phone":"+32 14 85 25 06",
    "sg:postcode":"2460",
    "sg:province":"Antwerpen",
    "wof:name":"Koningsbos",
    "wof:placetype":"venue"
},
  "geometry": {"coordinates":[4.95125103,51.2213935852],"type":"Point"}
}