{
  "type": "Feature",
  "properties": {
    "iso:country":"BE",
    "sg:address":"Crapaurue 88",
    "sg:city":"Verviers",
    "sg:classifiers":[
        {
            "category":"Shopping",
            "subcategory":"Clothing, Apparel, & Fashions",
            "type":"Retail Goods"
        }
    ],
    "sg:phone":"+32 87 34 11 59",
    "sg:postcode":"4800",
    "sg:province":"Li\u00e8ge",
    "sg:tags":[
        "v\u00eatements",
        "pour",
        "dame"
    ],
    "wof:name":"Maison Bis\u00b4s",
    "wof:placetype":"venue"
},
  "geometry": {"coordinates":[5.8645272255,50.5930290222],"type":"Point"}
}