{
  "type": "Feature",
  "properties": {
    "iso:country":"BE",
    "sg:address":"Schave 84",
    "sg:city":"Deinze",
    "sg:classifiers":[
        {
            "category":"Arena",
            "subcategory":"Sports Club",
            "type":"Entertainment"
        }
    ],
    "sg:phone":"+32 9 386 56 85",
    "sg:postcode":"9800",
    "sg:province":"Oost-Vlaanderen",
    "sg:tags":[
        "de"
    ],
    "wof:name":"De Zwervende Pallieters",
    "wof:placetype":"venue"
},
  "geometry": {"coordinates":[3.5182380676,50.993637085],"type":"Point"}
}