{
  "type": "Feature",
  "properties": {
    "addr:full":"Rue Des B\u00c9gards 2 Li\u00c8ge Li\u00e8ge 4000",
    "addr:housenumber":"2",
    "addr:postcode":"4000",
    "addr:street":"Rue Des Be\u0301Gards",
    "iso:country":"BE",
    "sg:address":"Rue Des B\u00c9gards 2",
    "sg:city":"Li\u00c8ge",
    "sg:orig_category":"Fast food and meeneem restaurants Restaurants Ruimtes voor conferenties, recepties and feesten",
    "sg:phone":"+32 4 223 13 23",
    "sg:postcode":"4000",
    "sg:province":"Li\u00e8ge",
    "wof:name":"La Cit\u00c9 Du Dragon",
    "wof:placetype":"venue"
},
  "geometry": {"coordinates":[5.5645751953,50.643989563],"type":"Point"}
}