{
  "type": "Feature",
  "properties": {
    "addr:full":"Vismarkt 1 Lier Antwerpen 2500",
    "addr:housenumber":"1",
    "addr:postcode":"2500",
    "addr:street":"Vismarkt",
    "iso:country":"BE",
    "sg:address":"Vismarkt 1",
    "sg:city":"Lier",
    "sg:classifiers":[
        {
            "category":"Airport",
            "subcategory":"General Aviation",
            "type":"Transportation"
        }
    ],
    "sg:phone":"+32 495 50 99 20",
    "sg:postcode":"2500",
    "sg:province":"Antwerpen",
    "sg:tags":[
        "transport"
    ],
    "wof:name":"All Passenger Services",
    "wof:placetype":"venue"
},
  "geometry": {"coordinates":[4.5710749626,51.1303939819],"type":"Point"}
}