{
  "type": "Feature",
  "properties": {
    "iso:country":"BE",
    "sg:address":"Terdekdelleweg 43",
    "sg:city":"Overijse",
    "sg:classifiers":[
        {
            "category":"Health Services",
            "subcategory":"Doctor",
            "type":"Services"
        }
    ],
    "sg:phone":"+32 2 687 64 47",
    "sg:postcode":"3090",
    "sg:province":"Vlaams-Brabant",
    "sg:tags":[
        "medicinephysicians",
        "surgeon"
    ],
    "wof:name":"Knoops P",
    "wof:placetype":"venue"
},
  "geometry": {"coordinates":[4.5624990463,50.7543373108],"type":"Point"}
}