{
  "type": "Feature",
  "properties": {
    "addr:full":"Weverijstraat Geraardsbergen (groot) Oost-Vlaanderen 9500",
    "addr:postcode":"9500",
    "addr:street":"Weverijstraat;Groot Oost-Vlaanderen",
    "iso:country":"BE",
    "sg:address":"Weverijstraat",
    "sg:city":"Geraardsbergen (groot)",
    "sg:classifiers":[
        {
            "category":"Arena",
            "subcategory":"Sports Club",
            "type":"Entertainment"
        }
    ],
    "sg:phone":"+32 54 41 27 16",
    "sg:postcode":"9500",
    "sg:province":"Oost-Vlaanderen",
    "sg:tags":[
        "de"
    ],
    "wof:name":"De Koninklijke Vrijschutters",
    "wof:placetype":"venue"
},
  "geometry": {"coordinates":[3.8818700314,50.7762947083],"type":"Point"}
}