{
  "type": "Feature",
  "properties": {
    "addr:full":"Rue Edmond Laffineur 9 Wavre Brabant Wallon 1300",
    "addr:housenumber":"9;1300",
    "addr:street":"Rue Edmond Laffineur",
    "iso:country":"BE",
    "sg:address":"Rue Edmond Laffineur 9",
    "sg:city":"Wavre",
    "sg:orig_category":"Apotheken",
    "sg:phone":"+32 10 41 37 83",
    "sg:postcode":"1300",
    "sg:province":"Brabant Wallon",
    "wof:name":"Mattens - Mettewie",
    "wof:placetype":"venue"
},
  "geometry": {"coordinates":[4.6116552353,50.7134132385],"type":"Point"}
}