{
  "type": "Feature",
  "properties": {
    "addr:full":"Grand Route 149 Drogenbos/drogenbos Vlaams-Brabant 1620",
    "addr:postcode":"1620",
    "addr:street":"Grand Route 149",
    "iso:country":"BE",
    "sg:address":"Grand Route 149",
    "sg:city":"Drogenbos/drogenbos",
    "sg:orig_category":"Plomberie, chauffage and installations sanitaires",
    "sg:phone":"+32 2 377 43 10",
    "sg:postcode":"1620",
    "sg:province":"Vlaams-Brabant",
    "wof:name":"H J Seminckx",
    "wof:placetype":"venue"
},
  "geometry": {"coordinates":[4.3209500313,50.7822685242],"type":"Point"}
}