{
  "type": "Feature",
  "properties": {
    "iso:country":"BE",
    "sg:address":"Vlamingstraat 85",
    "sg:city":"Sint-laureins (sint-margriete)",
    "sg:classifiers":[
        {
            "category":"Building & Trades",
            "subcategory":"Landscaping Services",
            "type":"Services"
        }
    ],
    "sg:phone":"+32 9 379 79 59",
    "sg:postcode":"9981",
    "sg:province":"Oost-Vlaanderen",
    "sg:tags":[
        "gardening",
        "garden",
        "maintenance"
    ],
    "wof:name":"Evergreen-greenart",
    "wof:placetype":"venue"
},
  "geometry": {"coordinates":[3.5385110378,51.2464141846],"type":"Point"}
}