{
  "type": "Feature",
  "properties": {
    "iso:country":"BE",
    "sg:address":"Heislagsebaan 153",
    "sg:city":"Brasschaat",
    "sg:classifiers":[
        {
            "category":"Professional",
            "type":"Services"
        }
    ],
    "sg:phone":"+32 3 651 94 70",
    "sg:postcode":"2930",
    "sg:province":"Antwerpen",
    "sg:tags":[
        "surveyor",
        "-",
        "valuer"
    ],
    "wof:name":"Joris Jan Studieburo Bvba",
    "wof:placetype":"venue"
},
  "geometry": {"coordinates":[4.5033221245,51.3000717163],"type":"Point"}
}