{
  "type": "Feature",
  "properties": {
    "addr:full":"Rue Antoine Cuvelier 5 Chaudfontaine Li\u00e8ge 4053",
    "addr:housenumber":"5",
    "addr:postcode":"4053",
    "addr:street":"Rue Antoine Cuvelier",
    "iso:country":"BE",
    "sg:address":"Rue Antoine Cuvelier 5",
    "sg:city":"Chaudfontaine",
    "sg:orig_category":"Woningbouw",
    "sg:phone":"+32 4 367 39 20",
    "sg:postcode":"4053",
    "sg:province":"Li\u00e8ge",
    "wof:name":"Michel Bastin",
    "wof:placetype":"venue"
},
  "geometry": {"coordinates":[5.6081461906,50.5903167725],"type":"Point"}
}