{
  "type": "Feature",
  "properties": {
    "iso:country":"BE",
    "sg:address":"All\u00e9e Du Bois De Bercuit 99",
    "sg:city":"Grez-doiceau",
    "sg:classifiers":[
        {
            "category":"Real Estate",
            "subcategory":"Real Estate Services",
            "type":"Services"
        }
    ],
    "sg:phone":"+32 10 84 60 84",
    "sg:postcode":"1390",
    "sg:province":"Brabant Wallon",
    "wof:name":"Claude Bernard Sa",
    "wof:placetype":"venue"
},
  "geometry": {"coordinates":[4.6799211502,50.7330284119],"type":"Point"}
}