{
  "type": "Feature",
  "properties": {
    "addr:full":"Leiestraat 16 Roeselare West-Vlaanderen 8800",
    "addr:housenumber":"16",
    "addr:postcode":"8800",
    "addr:street":"Leiestraat",
    "iso:country":"BE",
    "sg:address":"Leiestraat 16",
    "sg:city":"Roeselare",
    "sg:classifiers":[
        {
            "category":"Building & Trades",
            "subcategory":"Pest Control",
            "type":"Services"
        }
    ],
    "sg:phone":"+32 51 24 71 71",
    "sg:postcode":"8800",
    "sg:province":"West-Vlaanderen",
    "sg:tags":[
        "painting",
        "contractor"
    ],
    "wof:name":"Plysier P",
    "wof:placetype":"venue"
},
  "geometry": {"coordinates":[3.1473779678,50.9663848877],"type":"Point"}
}