{
  "type": "Feature",
  "properties": {
    "addr:full":"Kardinaal Cardijnplein Bornem Antwerpen 2880",
    "addr:postcode":"2880",
    "addr:street":"Kardinaal Cardijnplein",
    "iso:country":"BE",
    "sg:address":"Kardinaal Cardijnplein",
    "sg:city":"Bornem",
    "sg:classifiers":[
        {
            "category":"Bars & Pubs",
            "type":"Food & Drink"
        }
    ],
    "sg:phone":"+32 3 899 41 31",
    "sg:postcode":"2880",
    "sg:province":"Antwerpen",
    "wof:name":"Differance (la)",
    "wof:placetype":"venue"
},
  "geometry": {"coordinates":[4.2348618507,51.0995178223],"type":"Point"}
}