{
  "type": "Feature",
  "properties": {
    "iso:country":"BE",
    "sg:address":"Pas 264",
    "sg:city":"Geel",
    "sg:orig_category":"Notaires",
    "sg:phone":"+32 14 58 44 41",
    "sg:postcode":"2440",
    "sg:province":"Antwerpen",
    "wof:name":"M. Bogaert",
    "wof:placetype":"venue"
},
  "geometry": {"coordinates":[4.9760131836,51.1530151367],"type":"Point"}
}