{
  "type": "Feature",
  "properties": {
    "addr:full":"Molenbergstraat 2 Antwerpen Antwerpen 2000",
    "addr:housenumber":"2",
    "addr:postcode":"2000",
    "addr:street":"Molenbergstraat",
    "iso:country":"BE",
    "sg:address":"Molenbergstraat 2",
    "sg:city":"Antwerpen",
    "sg:classifiers":[
        {
            "category":"Health Services",
            "subcategory":"Hospital",
            "type":"Services"
        }
    ],
    "sg:phone":"+32 3 221 92 21",
    "sg:postcode":"2000",
    "sg:province":"Antwerpen",
    "sg:tags":[
        "ambulance"
    ],
    "wof:name":"Cm-foon",
    "wof:placetype":"venue"
},
  "geometry": {"coordinates":[4.4152741432,51.2206001282],"type":"Point"}
}