{
  "type": "Feature",
  "properties": {
    "addr:full":"Ter Cleye 12 Merelbeke Oost-Vlaanderen 9820",
    "addr:housenumber":"12",
    "addr:postcode":"9820",
    "addr:street":"Cleye",
    "iso:country":"BE",
    "sg:address":"Ter Cleye 12",
    "sg:city":"Merelbeke",
    "sg:classifiers":[
        {
            "category":"Professional",
            "subcategory":"Printing & Photocopies",
            "type":"Services"
        }
    ],
    "sg:phone":"+32 475 82 45 54",
    "sg:postcode":"9820",
    "sg:province":"Oost-Vlaanderen",
    "sg:tags":[
        "silkscreen",
        "-"
    ],
    "wof:name":"M.h. Solutions",
    "wof:placetype":"venue"
},
  "geometry": {"coordinates":[3.7445249557,50.9919776917],"type":"Point"}
}