{
  "type": "Feature",
  "properties": {
    "iso:country":"BE",
    "sg:address":"Rue Des Archers 2",
    "sg:city":"Mons",
    "sg:classifiers":[
        {
            "category":"Shopping",
            "subcategory":"Gifts & Souvenirs",
            "type":"Retail Goods"
        }
    ],
    "sg:phone":"+32 65 35 29 16",
    "sg:postcode":"7000",
    "sg:province":"Hainaut",
    "sg:tags":[
        "-"
    ],
    "wof:name":"Matthys Sa",
    "wof:placetype":"venue"
},
  "geometry": {"coordinates":[3.9580290318,50.452709198],"type":"Point"}
}