{
  "type": "Feature",
  "properties": {
    "iso:country":"BE",
    "sg:address":"Rue Du Solitaire 32",
    "sg:city":"Leuze-en-hainaut",
    "sg:classifiers":[
        {
            "category":"Health Services",
            "subcategory":"Doctor",
            "type":"Services"
        }
    ],
    "sg:phone":"+32 69 66 58 48",
    "sg:postcode":"7900",
    "sg:province":"Hainaut",
    "sg:tags":[
        "medicinephysicians",
        "surgeon"
    ],
    "wof:name":"Hourez W",
    "wof:placetype":"venue"
},
  "geometry": {"coordinates":[3.6120169163,50.596660614],"type":"Point"}
}