{
  "type": "Feature",
  "properties": {
    "addr:full":"Sint-jacobstraat 26 Dendermonde Oost-Vlaanderen 9200",
    "addr:housenumber":"26",
    "addr:postcode":"9200",
    "addr:street":"Sint-Jacobstraat;Oost-Vlaanderen",
    "iso:country":"BE",
    "sg:address":"Sint-jacobstraat 26",
    "sg:city":"Dendermonde",
    "sg:orig_category":"Gevangenissen and strafinrichtingen",
    "sg:phone":"+32 52 21 90 51",
    "sg:postcode":"9200",
    "sg:province":"Oost-Vlaanderen",
    "wof:name":"Gevangenis",
    "wof:placetype":"venue"
},
  "geometry": {"coordinates":[4.1039600372,51.0303726196],"type":"Point"}
}