{
  "type": "Feature",
  "properties": {
    "addr:full":"Rue G\u00c9rard-de-cambrai 12 Florennes Namur 5620",
    "addr:housenumber":"12",
    "addr:postcode":"5620",
    "addr:street":"Rue Ge\u0301Rard-De-Cambrai",
    "iso:country":"BE",
    "sg:address":"Rue G\u00c9rard-de-cambrai 12",
    "sg:city":"Florennes",
    "sg:orig_category":"Rundveehouders",
    "sg:phone":"+32 71 68 85 14",
    "sg:postcode":"5620",
    "sg:province":"Namur",
    "wof:name":"Nicolas Paquet",
    "wof:placetype":"venue"
},
  "geometry": {"coordinates":[4.6103639603,50.2514190674],"type":"Point"}
}