{
  "type": "Feature",
  "properties": {
    "iso:country":"BE",
    "sg:address":"Brusselsesteenweg 23",
    "sg:city":"Gent (ledeberg)",
    "sg:classifiers":[
        {
            "category":"Professional",
            "subcategory":"Testing Lab",
            "type":"Services"
        }
    ],
    "sg:phone":"+32 9 231 09 16",
    "sg:postcode":"9050",
    "sg:province":"Oost-Vlaanderen",
    "sg:tags":[
        "chemist"
    ],
    "wof:name":"Martin Apotheek",
    "wof:placetype":"venue"
},
  "geometry": {"coordinates":[3.7418780327,51.041305542],"type":"Point"}
}