{
  "type": "Feature",
  "properties": {
    "addr:full":"Lage Rooy 14 Hoogstraten Antwerpen 2328",
    "addr:housenumber":"14",
    "addr:postcode":"2328",
    "addr:street":"Lage Rooy",
    "iso:country":"BE",
    "sg:address":"Lage Rooy 14",
    "sg:city":"Hoogstraten",
    "sg:orig_category":"Decoratieve kunst and kunstbenodigdheden",
    "sg:phone":"+32 3 315 00 11",
    "sg:postcode":"2328",
    "sg:province":"Antwerpen",
    "wof:name":"Kunstgalerij De Pastorale",
    "wof:placetype":"venue"
},
  "geometry": {"coordinates":[4.8139448166,51.4608840942],"type":"Point"}
}