{
  "type": "Feature",
  "properties": {
    "addr:full":"Chemin Du Grand Ry 1 Namur Namur 5100",
    "addr:housenumber":"1",
    "addr:postcode":"5100",
    "addr:street":"Chemin Du Grand Ry",
    "iso:country":"BE",
    "sg:address":"Chemin Du Grand Ry 1",
    "sg:city":"Namur",
    "sg:orig_category":"Voertuigen",
    "sg:phone":"+32 81 46 17 63",
    "sg:postcode":"5100",
    "sg:province":"Namur",
    "wof:name":"Imporautopneu S.g.i.c.",
    "wof:placetype":"venue"
},
  "geometry": {"coordinates":[4.881881237,50.4067764282],"type":"Point"}
}