{
  "type": "Feature",
  "properties": {
    "iso:country":"BE",
    "sg:address":"Dokter Persoonslaan 25",
    "sg:city":"Willebroek",
    "sg:orig_category":"Artsen and specialisten",
    "sg:phone":"+32 3 886 66 17",
    "sg:postcode":"2830",
    "sg:province":"Antwerpen",
    "wof:name":"J. De Boeck",
    "wof:placetype":"venue"
},
  "geometry": {"coordinates":[4.3617181778,51.0597610474],"type":"Point"}
}