{
  "type": "Feature",
  "properties": {
    "addr:full":"Rue De Diekirch 134 Arlon Luxembourg 6700",
    "addr:housenumber":"134",
    "addr:postcode":"6700",
    "addr:street":"Rue De Diekirch",
    "iso:country":"BE",
    "sg:address":"Rue De Diekirch 134",
    "sg:city":"Arlon",
    "sg:orig_category":"Artsen and specialisten",
    "sg:phone":"+32 63 22 57 62",
    "sg:postcode":"6700",
    "sg:province":"Luxembourg",
    "wof:name":"J. Deraedt",
    "wof:placetype":"venue"
},
  "geometry": {"coordinates":[5.8172559738,49.6885566711],"type":"Point"}
}