{
  "type": "Feature",
  "properties": {
    "addr:full":"Avenue De Burlet 22 Binche Hainaut 7130",
    "addr:housenumber":"22",
    "addr:postcode":"7130",
    "addr:street":"Avenue De Burlet",
    "iso:country":"BE",
    "sg:address":"Avenue De Burlet 22",
    "sg:city":"Binche",
    "sg:classifiers":[
        {
            "category":"Health Services",
            "subcategory":"Doctor",
            "type":"Services"
        }
    ],
    "sg:phone":"+32 64 36 76 25",
    "sg:postcode":"7130",
    "sg:province":"Hainaut",
    "sg:tags":[
        "medicinephysicians",
        "surgeon"
    ],
    "wof:name":"Colonval Stephane",
    "wof:placetype":"venue"
},
  "geometry": {"coordinates":[4.1742801666,50.4107666016],"type":"Point"}
}