{
  "type": "Feature",
  "properties": {
    "iso:country":"BE",
    "sg:address":"Leiweg 9",
    "sg:city":"Wuustwezel",
    "sg:orig_category":"Production and transformation de viande",
    "sg:phone":"+32 3 314 10 69",
    "sg:postcode":"2990",
    "sg:province":"Antwerpen",
    "wof:name":"Fa. Konijneboutje",
    "wof:placetype":"venue"
},
  "geometry": {"coordinates":[4.6934919357,51.3815727234],"type":"Point"}
}