{
  "type": "Feature",
  "properties": {
    "addr:full":"Welvaartstraat 191 Berlaar Antwerpen 2590",
    "addr:housenumber":"191",
    "addr:postcode":"2590",
    "addr:street":"Welvaartstraat",
    "iso:country":"BE",
    "sg:address":"Welvaartstraat 191",
    "sg:city":"Berlaar",
    "sg:classifiers":[
        {
            "category":"Farming",
            "subcategory":"Crops",
            "type":"Manufacturing & Wholesale Goods"
        }
    ],
    "sg:phone":"+32 3 482 14 87",
    "sg:postcode":"2590",
    "sg:province":"Antwerpen",
    "sg:tags":[
        "vegetable",
        "fruit",
        "-",
        "grower"
    ],
    "wof:name":"Hanquet R",
    "wof:placetype":"venue"
},
  "geometry": {"coordinates":[4.6427202225,51.1030311584],"type":"Point"}
}