{
  "type": "Feature",
  "properties": {
    "iso:country":"BE",
    "sg:address":"Dr. J. Geensstraat 32",
    "sg:city":"Tienen",
    "sg:orig_category":"Avocats and conseillers juridiques",
    "sg:phone":"+32 16 81 66 24",
    "sg:postcode":"3300",
    "sg:province":"Vlaams-Brabant",
    "wof:name":"E. Vandebempt",
    "wof:placetype":"venue"
},
  "geometry": {"coordinates":[4.9340500832,50.8074493408],"type":"Point"}
}