{
  "type": "Feature",
  "properties": {
    "iso:country":"BE",
    "sg:address":"Rue Mab\u00eeme 166",
    "sg:city":"Ans (alleur)",
    "sg:classifiers":[
        {
            "category":"Building & Trades",
            "subcategory":"Construction",
            "type":"Services"
        }
    ],
    "sg:phone":"+32 4 263 01 81",
    "sg:postcode":"4432",
    "sg:province":"Li\u00e8ge",
    "sg:tags":[
        "installation",
        "-",
        "central",
        "heating"
    ],
    "wof:name":"Bielen P",
    "wof:placetype":"venue"
},
  "geometry": {"coordinates":[5.5259399414,50.667591095],"type":"Point"}
}