{
  "type": "Feature",
  "properties": {
    "addr:full":"Hippolyte Boulengerlaan 48 Tervuren Vlaams-Brabant 3080",
    "addr:housenumber":"48",
    "addr:postcode":"3080",
    "addr:street":"Hippolyte Boulengerlaan",
    "iso:country":"BE",
    "sg:address":"Hippolyte Boulengerlaan 48",
    "sg:city":"Tervuren",
    "sg:classifiers":[
        {
            "category":"Health Services",
            "subcategory":"Doctor",
            "type":"Services"
        }
    ],
    "sg:phone":"+32 2 767 68 52",
    "sg:postcode":"3080",
    "sg:province":"Vlaams-Brabant",
    "sg:tags":[
        "medicinephysicians",
        "surgeon"
    ],
    "wof:name":"Kharkevitch T",
    "wof:placetype":"venue"
},
  "geometry": {"coordinates":[4.5033278465,50.8208503723],"type":"Point"}
}