{
  "type": "Feature",
  "properties": {
    "addr:full":"Place Des Hautchamps 29a Bernissart (pommeroeul) Hainaut 7322",
    "addr:housenumber":"29a",
    "addr:postcode":"7322",
    "addr:street":"Place Des Hautchamps",
    "iso:country":"BE",
    "sg:address":"Place Des Hautchamps 29a",
    "sg:city":"Bernissart (pommeroeul)",
    "sg:classifiers":[
        {
            "category":"Personal",
            "subcategory":"Beauty Salon",
            "type":"Services"
        }
    ],
    "sg:phone":"+32 65 62 23 88",
    "sg:postcode":"7322",
    "sg:province":"Hainaut",
    "sg:tags":[
        "lady",
        "-",
        "hairdressing"
    ],
    "wof:name":"Liliane",
    "wof:placetype":"venue"
},
  "geometry": {"coordinates":[3.7120049,50.4628295898],"type":"Point"}
}