{
  "type": "Feature",
  "properties": {
    "iso:country":"BE",
    "sg:address":"Potterstraat 125",
    "sg:city":"Sint-gillis-waas",
    "sg:orig_category":"Dameskledingzaken",
    "sg:phone":"+32 3 777 24 96",
    "sg:postcode":"9170",
    "sg:province":"Oost-Vlaanderen",
    "wof:name":"Huis Catwalk",
    "wof:placetype":"venue"
},
  "geometry": {"coordinates":[4.1078839302,51.1865234375],"type":"Point"}
}