{
  "type": "Feature",
  "properties": {
    "iso:country":"BE",
    "sg:address":"Chauss\u00c9e De Li\u00c8ge 83",
    "sg:city":"Herve",
    "sg:orig_category":"Rev\u00eatements pour sols and murs. Mat\u00e9riaux de construction Gr",
    "sg:phone":"+32 87 67 52 18",
    "sg:postcode":"4652",
    "sg:province":"Li\u00e8ge",
    "wof:name":"Jean Gaspard",
    "wof:placetype":"venue"
},
  "geometry": {"coordinates":[5.7697739601,50.6179084778],"type":"Point"}
}