{
  "type": "Feature",
  "properties": {
    "addr:full":"Tiensestraat 174 Leuven Vlaams-Brabant 3000",
    "addr:housenumber":"174",
    "addr:postcode":"3000",
    "addr:street":"Tiensestraat",
    "iso:country":"BE",
    "sg:address":"Tiensestraat 174",
    "sg:city":"Leuven",
    "sg:orig_category":"RESTAURANTS: RESTAURANTS LIVRAISON \u00c0 DOMICILE",
    "sg:phone":"+32 16 23 59 01",
    "sg:postcode":"3000",
    "sg:province":"Vlaams-Brabant",
    "wof:name":"'t Smullerke",
    "wof:placetype":"venue"
},
  "geometry": {"coordinates":[4.7102818489,50.874961853],"type":"Point"}
}