{
  "type": "Feature",
  "properties": {
    "addr:full":"Keienveldstraat 48 Elsene/ixelles Bruxelles-Capitale 1050",
    "addr:housenumber":"48",
    "addr:postcode":"1050",
    "addr:street":"Keienveldstraat",
    "iso:country":"BE",
    "sg:address":"Keienveldstraat 48",
    "sg:city":"Elsene/ixelles",
    "sg:orig_category":"Advocaten and juridische adviseurs",
    "sg:phone":"+32 2 513 43 26",
    "sg:postcode":"1050",
    "sg:province":"Bruxelles-Capitale",
    "wof:name":"G\u00c9raldine Balthazar",
    "wof:placetype":"venue"
},
  "geometry": {"coordinates":[4.3615589142,50.8348312378],"type":"Point"}
}