{
  "type": "Feature",
  "properties": {
    "addr:full":"Kapellestraat 69 Oostende West-Vlaanderen 8400",
    "addr:housenumber":"69",
    "addr:postcode":"8400",
    "addr:street":"Kapellestraat",
    "iso:country":"BE",
    "sg:address":"Kapellestraat 69",
    "sg:city":"Oostende",
    "sg:orig_category":"Slagers",
    "sg:phone":"+32 59 70 14 29",
    "sg:postcode":"8400",
    "sg:province":"West-Vlaanderen",
    "wof:name":"Huis Vanderghote W.",
    "wof:placetype":"venue"
},
  "geometry": {"coordinates":[2.9193899632,51.2295913696],"type":"Point"}
}