{
  "type": "Feature",
  "properties": {
    "iso:country":"BE",
    "sg:address":"Desguinlei 92",
    "sg:city":"Antwerpen",
    "sg:classifiers":[
        {
            "category":"Insurance",
            "subcategory":"Insurance Agent",
            "type":"Services"
        }
    ],
    "sg:phone":"+32 3 244 66 88",
    "sg:postcode":"2018",
    "sg:province":"Antwerpen",
    "sg:tags":[
        "-",
        "representative"
    ],
    "wof:name":"Ing Insurance",
    "wof:placetype":"venue"
},
  "geometry": {"coordinates":[4.4064640999,51.1939811707],"type":"Point"}
}