{
  "type": "Feature",
  "properties": {
    "iso:country":"BE",
    "sg:address":"Lindestraat 44",
    "sg:city":"Neerpelt (sint-huibrechts-lille)",
    "sg:classifiers":[
        {
            "category":"Professional",
            "subcategory":"Printing & Photocopies",
            "type":"Services"
        }
    ],
    "sg:phone":"+32 11 64 47 17",
    "sg:postcode":"3910",
    "sg:province":"Limburg",
    "sg:tags":[
        "-",
        "offset"
    ],
    "wof:name":"Drukkerij T Goyens",
    "wof:placetype":"venue"
},
  "geometry": {"coordinates":[5.4883050919,51.2244873047],"type":"Point"}
}