{
  "type": "Feature",
  "properties": {
    "addr:full":"Mispadstraat 15 Genk Limburg 3600",
    "addr:housenumber":"15",
    "addr:postcode":"3600",
    "addr:street":"Mispadstraat",
    "iso:country":"BE",
    "sg:address":"Mispadstraat 15",
    "sg:city":"Genk",
    "sg:orig_category":"Kapsalons",
    "sg:phone":"+32 89 38 22 50",
    "sg:postcode":"3600",
    "sg:province":"Limburg",
    "wof:name":"Coiffure Sandra",
    "wof:placetype":"venue"
},
  "geometry": {"coordinates":[5.5254797935,50.9843406677],"type":"Point"}
}