{
  "type": "Feature",
  "properties": {
    "addr:full":"Albert I Laan 168 Nieuwpoort West-Vlaanderen 8620",
    "addr:housenumber":"168",
    "addr:postcode":"8620",
    "addr:street":"Albert I Laan",
    "iso:country":"BE",
    "sg:address":"Albert I Laan 168",
    "sg:city":"Nieuwpoort",
    "sg:classifiers":[
        {
            "category":"Shopping",
            "subcategory":"Beauty & Cosmetics",
            "type":"Retail Goods"
        }
    ],
    "sg:phone":"+32 58 24 14 19",
    "sg:postcode":"8620",
    "sg:province":"West-Vlaanderen",
    "sg:tags":[
        "-",
        "perfumery"
    ],
    "wof:name":"Nausikaa",
    "wof:placetype":"venue"
},
  "geometry": {"coordinates":[2.7507851124,51.1285133362],"type":"Point"}
}