{
  "type": "Feature",
  "properties": {
    "addr:full":"Rue Des Bouleaux 13 Li\u00c8ge Li\u00e8ge 4031",
    "addr:housenumber":"13",
    "addr:postcode":"4031",
    "addr:street":"Rue Des Bouleaux",
    "iso:country":"BE",
    "sg:address":"Rue Des Bouleaux 13",
    "sg:city":"Li\u00c8ge",
    "sg:classifiers":[
        {
            "category":"Professional",
            "subcategory":"Accounting & Tax Preparation",
            "type":"Services"
        }
    ],
    "sg:phone":"+32 4 367 36 57",
    "sg:postcode":"4031",
    "sg:province":"Li\u00e8ge",
    "sg:tags":[
        "accountant"
    ],
    "wof:name":"Francis Swinnen",
    "wof:placetype":"venue"
},
  "geometry": {"coordinates":[5.5706357956,50.5945014954],"type":"Point"}
}