{
  "type": "Feature",
  "properties": {
    "iso:country":"BE",
    "sg:address":"Steenweg Op Deinze 180",
    "sg:city":"Aalter",
    "sg:orig_category":"M\u00e9decins and sp\u00e9cialistes",
    "sg:phone":"+32 51 68 64 64",
    "sg:postcode":"9880",
    "sg:province":"Oost-Vlaanderen",
    "wof:name":"Erwin Praet",
    "wof:placetype":"venue"
},
  "geometry": {"coordinates":[3.4559299946,51.0652313232],"type":"Point"}
}