{
  "type": "Feature",
  "properties": {
    "iso:country":"BE",
    "sg:address":"Gerom.-route De Waimes 48",
    "sg:city":"Malmedy/malmedy",
    "sg:orig_category":"Plaatsen van vloer- and muurbekleding Schilders",
    "sg:phone":"+32 80 33 75 04",
    "sg:postcode":"4960",
    "sg:province":"Li\u00e8ge",
    "wof:name":"D.s. D\u00c9cors",
    "wof:placetype":"venue"
},
  "geometry": {"coordinates":[6.0585079193,50.406829834],"type":"Point"}
}