{
  "type": "Feature",
  "properties": {
    "iso:country":"BE",
    "sg:address":"Parklaan 6",
    "sg:city":"Ninove",
    "sg:orig_category":"Artsen and specialisten",
    "sg:phone":"+32 54 32 39 29",
    "sg:postcode":"9400",
    "sg:province":"Oost-Vlaanderen",
    "wof:name":"L. Vander Biest",
    "wof:placetype":"venue"
},
  "geometry": {"coordinates":[4.0219092369,50.8297119141],"type":"Point"}
}