{
  "type": "Feature",
  "properties": {
    "addr:full":"Menenstraat 418 Wevelgem West-Vlaanderen 8560",
    "addr:housenumber":"418",
    "addr:postcode":"8560",
    "addr:street":"Menenstraat",
    "iso:country":"BE",
    "sg:address":"Menenstraat 418",
    "sg:city":"Wevelgem",
    "sg:classifiers":[
        {
            "category":"Structure",
            "subcategory":"Building",
            "type":"Public Place"
        }
    ],
    "sg:phone":"+32 56 42 74 21",
    "sg:postcode":"8560",
    "sg:province":"West-Vlaanderen",
    "sg:tags":[
        "door"
    ],
    "wof:name":"Demaco/couckuyt Patrick",
    "wof:placetype":"venue"
},
  "geometry": {"coordinates":[3.1554560661,50.8027420044],"type":"Point"}
}