{
  "type": "Feature",
  "properties": {
    "iso:country":"BE",
    "sg:address":"Wayezstraat 17",
    "sg:city":"Anderlecht/anderlecht",
    "sg:orig_category":"HERSTELLING ELEKTRISCHE HUISHOUDAPPARATEN Huishoudapparaten, televisies and radio's",
    "sg:phone":"+32 2 523 42 35",
    "sg:postcode":"1070",
    "sg:province":"Bruxelles-Capitale",
    "wof:name":"Maison Electrica",
    "wof:placetype":"venue"
},
  "geometry": {"coordinates":[4.3163590431,50.836566925],"type":"Point"}
}