{
  "type": "Feature",
  "properties": {
    "iso:country":"BE",
    "sg:address":"Eilandstraat 1-5",
    "sg:city":"Gent",
    "sg:classifiers":[
        {
            "category":"Military Area",
            "subcategory":"Air Force Base",
            "type":"Public Place"
        }
    ],
    "sg:phone":"+32 9 258 28 65",
    "sg:postcode":"9000",
    "sg:province":"Oost-Vlaanderen",
    "sg:tags":[
        "detector",
        "metal"
    ],
    "wof:name":"Mc & C Metaaldetectoren Vandamme",
    "wof:placetype":"venue"
},
  "geometry": {"coordinates":[3.7392311096,51.1109809875],"type":"Point"}
}