{
  "type": "Feature",
  "properties": {
    "iso:country":"BE",
    "sg:address":"Rue Des Monts 9",
    "sg:city":"Hotton",
    "sg:classifiers":[
        {
            "category":"Travel",
            "subcategory":"Hotels & Motels",
            "type":"Entertainment"
        }
    ],
    "sg:phone":"+32 84 46 62 35",
    "sg:postcode":"6990",
    "sg:province":"Luxembourg",
    "wof:name":"Besace (la)",
    "wof:placetype":"venue"
},
  "geometry": {"coordinates":[5.4803152084,50.2610626221],"type":"Point"}
}