{
  "type": "Feature",
  "properties": {
    "iso:country":"BE",
    "sg:address":"Rue Philippe Collette 11",
    "sg:city":"Grez-doiceau (bossut-gottechain)",
    "sg:classifiers":[
        {
            "category":"Professional",
            "subcategory":"Management & Consulting",
            "type":"Services"
        }
    ],
    "sg:phone":"+32 10 84 58 87",
    "sg:postcode":"1390",
    "sg:province":"Brabant Wallon",
    "sg:tags":[
        "consultant"
    ],
    "wof:name":"Eurasco Sprl",
    "wof:placetype":"venue"
},
  "geometry": {"coordinates":[4.6969838142,50.7599716187],"type":"Point"}
}