{
  "type": "Feature",
  "properties": {
    "addr:full":"Oude Vaartstraat 30 Ranst Antwerpen 2520",
    "addr:housenumber":"30",
    "addr:postcode":"2520",
    "addr:street":"Oude Vaartstraat",
    "iso:country":"BE",
    "sg:address":"Oude Vaartstraat 30",
    "sg:city":"Ranst",
    "sg:orig_category":"Woningbouw",
    "sg:phone":"+32 3 485 66 03",
    "sg:postcode":"2520",
    "sg:province":"Antwerpen",
    "wof:name":"Hans Vandermoeren",
    "wof:placetype":"venue"
},
  "geometry": {"coordinates":[4.579887867,51.2042198181],"type":"Point"}
}