{
  "type": "Feature",
  "properties": {
    "addr:full":"Rue Vieille-chav\u00c9e 5 Vielsalm Luxembourg 6690",
    "addr:housenumber":"5",
    "addr:postcode":"6690",
    "addr:street":"Rue Vieille-Chave\u0301E",
    "iso:country":"BE",
    "sg:address":"Rue Vieille-chav\u00c9e 5",
    "sg:city":"Vielsalm",
    "sg:orig_category":"Artiesten and kunstenaars",
    "sg:phone":"+32 80 21 60 30",
    "sg:postcode":"6690",
    "sg:province":"Luxembourg",
    "wof:name":"Emile Renard",
    "wof:placetype":"venue"
},
  "geometry": {"coordinates":[5.9186491966,50.2850646973],"type":"Point"}
}