{
  "type": "Feature",
  "properties": {
    "addr:full":"Avenue De La Croix Rouge 40 Box 1 Braine L'alleud (braine-l'alleud) Brabant Wallon 1420",
    "addr:housenumber":"40;1",
    "addr:postcode":"1420",
    "addr:street":"Avenue De La Croix Rouge;Box",
    "iso:country":"BE",
    "sg:address":"Avenue De La Croix Rouge 40 Box 1",
    "sg:city":"Braine L'alleud (braine-l'alleud)",
    "sg:classifiers":[
        {
            "category":"Professional",
            "subcategory":"Accounting & Tax Preparation",
            "type":"Services"
        }
    ],
    "sg:phone":"+32 2 387 30 90",
    "sg:postcode":"1420",
    "sg:province":"Brabant Wallon",
    "sg:tags":[
        "bookkeeper"
    ],
    "wof:name":"Gasia O",
    "wof:placetype":"venue"
},
  "geometry": {"coordinates":[-0.7004899979,47.369140625],"type":"Point"}
}