{
  "type": "Feature",
  "properties": {
    "addr:full":"Stationstraat 33 Deinze Oost-Vlaanderen 9800",
    "addr:housenumber":"33",
    "addr:postcode":"9800",
    "addr:street":"Stationstraat",
    "iso:country":"BE",
    "sg:address":"Stationstraat 33",
    "sg:city":"Deinze",
    "sg:classifiers":[
        {
            "category":"Restaurant",
            "type":"Food & Drink"
        }
    ],
    "sg:phone":"+32 9 380 02 29",
    "sg:postcode":"9800",
    "sg:province":"Oost-Vlaanderen",
    "wof:name":"New - World",
    "wof:placetype":"venue"
},
  "geometry": {"coordinates":[3.5319681168,50.9782829285],"type":"Point"}
}