{
  "type": "Feature",
  "properties": {
    "addr:full":"Heindonksestw. 2 Willebroek Antwerpen 2830",
    "addr:housenumber":"2",
    "addr:postcode":"2830",
    "addr:street":"Heindonksestw.",
    "iso:country":"BE",
    "sg:address":"Heindonksestw. 2",
    "sg:city":"Willebroek",
    "sg:classifiers":[
        {
            "category":"Professional",
            "subcategory":"Advertising",
            "type":"Services"
        }
    ],
    "sg:phone":"+32 3 886 39 00",
    "sg:postcode":"2830",
    "sg:province":"Antwerpen",
    "sg:tags":[
        "marketing",
        "medium",
        "communication"
    ],
    "wof:name":"Mail Partners Bvba",
    "wof:placetype":"venue"
},
  "geometry": {"coordinates":[4.367618084,51.0643501282],"type":"Point"}
}