{
  "type": "Feature",
  "properties": {
    "addr:full":"Rue Menuquerai 4 Enghien (petit-enghien) Hainaut 7850",
    "addr:housenumber":"4",
    "addr:postcode":"7850",
    "addr:street":"Rue Menuquerai",
    "iso:country":"BE",
    "sg:address":"Rue Menuquerai 4",
    "sg:city":"Enghien (petit-enghien)",
    "sg:classifiers":[
        {
            "category":"Health Services",
            "subcategory":"Health Practitioner",
            "type":"Services"
        }
    ],
    "sg:phone":"+32 2 395 39 27",
    "sg:postcode":"7850",
    "sg:province":"Hainaut",
    "sg:tags":[
        "physiotherapist"
    ],
    "wof:name":"Dispa J",
    "wof:placetype":"venue"
},
  "geometry": {"coordinates":[4.067032814,50.6706199646],"type":"Point"}
}