{
  "type": "Feature",
  "properties": {
    "addr:full":"Torhoutsesteenweg 235 Oostende West-Vlaanderen 8400",
    "addr:housenumber":"235",
    "addr:postcode":"8400",
    "addr:street":"Torhoutsesteenweg",
    "iso:country":"BE",
    "sg:address":"Torhoutsesteenweg 235",
    "sg:city":"Oostende",
    "sg:classifiers":[
        {
            "category":"Communications",
            "subcategory":"Radio Station",
            "type":"Services"
        }
    ],
    "sg:phone":"+32 59 70 14 04",
    "sg:postcode":"8400",
    "sg:province":"West-Vlaanderen",
    "sg:tags":[
        "telephony"
    ],
    "wof:name":"Bourgeois",
    "wof:placetype":"venue"
},
  "geometry": {"coordinates":[2.907294035,51.2183914185],"type":"Point"}
}