{
  "type": "Feature",
  "properties": {
    "addr:full":"Vrieskaai 59z Antwerpen Antwerpen 2030",
    "addr:housenumber":"59z",
    "addr:postcode":"2030",
    "addr:street":"Vrieskaai",
    "iso:country":"BE",
    "sg:address":"Vrieskaai 59z",
    "sg:city":"Antwerpen",
    "sg:orig_category":"Dock warehousemen",
    "sg:phone":"+32 3 542 52 66",
    "sg:postcode":"2030",
    "sg:province":"Antwerpen",
    "wof:name":"Antwerp Mineral Terminal Nv",
    "wof:placetype":"venue"
},
  "geometry": {"coordinates":[4.400042057,51.2515449524],"type":"Point"}
}