{
  "type": "Feature",
  "properties": {
    "iso:country":"BE",
    "sg:address":"Rue L\u00c9on Duray 4",
    "sg:city":"La Louviere",
    "sg:orig_category":"Fleurs and plantes. Services fun\u00e9raires",
    "sg:phone":"+32 64 22 36 75",
    "sg:postcode":"7110",
    "sg:province":"Hainaut",
    "wof:name":"Derville",
    "wof:placetype":"venue"
},
  "geometry": {"coordinates":[4.1559991837,50.4866676331],"type":"Point"}
}