{
  "type": "Feature",
  "properties": {
    "addr:full":"Professor Scharp\u00e9laan 8 Begijnendijk (betekom) Vlaams-Brabant 3130",
    "addr:housenumber":"8",
    "addr:postcode":"3130",
    "addr:street":"Professor Scharpe\u0301Laan",
    "iso:country":"BE",
    "sg:address":"Professor Scharp\u00e9laan 8",
    "sg:city":"Begijnendijk (betekom)",
    "sg:classifiers":[
        {
            "category":"Shopping",
            "subcategory":"Bicycles & Sporting Goods",
            "type":"Retail Goods"
        }
    ],
    "sg:phone":"+32 16 56 68 19",
    "sg:postcode":"3130",
    "sg:province":"Vlaams-Brabant",
    "sg:tags":[
        "sport",
        "-"
    ],
    "wof:name":"Sport 80",
    "wof:placetype":"venue"
},
  "geometry": {"coordinates":[4.7817101479,50.9866294861],"type":"Point"}
}