{
  "type": "Feature",
  "properties": {
    "addr:full":"Rue Des Cultivateurs 37 Bruxelles (etterbeek) Bruxelles-Capitale 1040",
    "addr:housenumber":"37",
    "addr:postcode":"1040",
    "addr:street":"Rue Des Cultivateurs",
    "iso:country":"BE",
    "sg:address":"Rue Des Cultivateurs 37",
    "sg:city":"Bruxelles (etterbeek)",
    "sg:classifiers":[
        {
            "category":"Insurance",
            "subcategory":"Insurance Agent",
            "type":"Services"
        }
    ],
    "sg:phone":"+32 2 732 68 01",
    "sg:postcode":"1040",
    "sg:province":"Bruxelles-Capitale",
    "sg:tags":[
        "broker"
    ],
    "wof:name":"Thirifays Sprl",
    "wof:placetype":"venue"
},
  "geometry": {"coordinates":[4.3931531906,50.8313407898],"type":"Point"}
}