{
  "type": "Feature",
  "properties": {
    "addr:full":"Grand Chemin 7 Mont-de-l'enclus Hainaut 7750",
    "addr:housenumber":"7",
    "addr:postcode":"7750",
    "addr:street":"Grand Chemin;Hainaut",
    "iso:country":"BE",
    "sg:address":"Grand Chemin 7",
    "sg:city":"Mont-de-l'enclus",
    "sg:orig_category":"Eleveurs de bovins",
    "sg:phone":"+32 69 45 43 20",
    "sg:postcode":"7750",
    "sg:province":"Hainaut",
    "wof:name":"Jean-marie Dhondt",
    "wof:placetype":"venue"
},
  "geometry": {"coordinates":[2.6025109291,46.3370933533],"type":"Point"}
}