{
  "type": "Feature",
  "properties": {
    "addr:full":"Sint-lambertuslaan 26 Mechelen Antwerpen 2812",
    "addr:housenumber":"26",
    "addr:postcode":"2812",
    "addr:street":"Sint-Lambertuslaan",
    "iso:country":"BE",
    "sg:address":"Sint-lambertuslaan 26",
    "sg:city":"Mechelen",
    "sg:orig_category":"Banques and organismes de cr\u00e9dit",
    "sg:phone":"+32 15 43 00 39",
    "sg:postcode":"2812",
    "sg:province":"Antwerpen",
    "wof:name":"Groep Argenta",
    "wof:placetype":"venue"
},
  "geometry": {"coordinates":[4.513092041,51.01121521],"type":"Point"}
}