{
  "type": "Feature",
  "properties": {
    "iso:country":"BE",
    "sg:address":"Maurits No\u00cbstraat 116",
    "sg:city":"Oud-heverlee",
    "sg:orig_category":"Sportclubs",
    "sg:phone":"+32 16 40 24 42",
    "sg:postcode":"3054",
    "sg:province":"Vlaams-Brabant",
    "wof:name":"De Pedaalridders Vaalbeek",
    "wof:placetype":"venue"
},
  "geometry": {"coordinates":[4.6836891174,50.8246498108],"type":"Point"}
}