{
  "type": "Feature",
  "properties": {
    "addr:full":"Avenue De La Houssi\u00e8re 140 Braine-le-comte Hainaut 7090",
    "addr:housenumber":"140",
    "addr:postcode":"7090",
    "addr:street":"Avenue De La Houssie\u0300Re",
    "iso:country":"BE",
    "sg:address":"Avenue De La Houssi\u00e8re 140",
    "sg:city":"Braine-le-comte",
    "sg:classifiers":[
        {
            "category":"Professional",
            "subcategory":"Art Services",
            "type":"Services"
        }
    ],
    "sg:phone":"+32 67 55 21 16",
    "sg:postcode":"7090",
    "sg:province":"Hainaut",
    "sg:tags":[
        "interior",
        "designer"
    ],
    "wof:name":"Bertrand M",
    "wof:placetype":"venue"
},
  "geometry": {"coordinates":[4.1582078934,50.6104431152],"type":"Point"}
}