{
  "type": "Feature",
  "properties": {
    "iso:country":"BE",
    "sg:address":"Rue Antoine Andr\u00c9 79",
    "sg:city":"Wavre",
    "sg:orig_category":"Persagentschappen",
    "sg:phone":"+32 10 41 35 46",
    "sg:postcode":"1300",
    "sg:province":"Brabant Wallon",
    "wof:name":"Chantal Gras",
    "wof:placetype":"venue"
},
  "geometry": {"coordinates":[4.5899720192,50.6885452271],"type":"Point"}
}