{
  "type": "Feature",
  "properties": {
    "iso:country":"BE",
    "sg:address":"Moeder Tiburcestraat 15b2",
    "sg:city":"Ninove",
    "sg:orig_category":"Pain, p\u00e2tisseries and confiseries",
    "sg:phone":"+32 54 32 92 36",
    "sg:postcode":"9400",
    "sg:province":"Oost-Vlaanderen",
    "wof:name":"Jean-pierre Maes",
    "wof:placetype":"venue"
},
  "geometry": {"coordinates":[4.0307188034,50.8387832642],"type":"Point"}
}