{
  "type": "Feature",
  "properties": {
    "iso:country":"BE",
    "sg:address":"Oude Vaartstraat 111",
    "sg:city":"Turnhout",
    "sg:classifiers":[
        {
            "category":"Personal",
            "subcategory":"Beauty Salon",
            "type":"Services"
        }
    ],
    "sg:phone":"+32 14 42 11 76",
    "sg:postcode":"2300",
    "sg:province":"Antwerpen",
    "sg:tags":[
        "de",
        "coiffure"
    ],
    "wof:name":"Kapsalon Kathleen",
    "wof:placetype":"venue"
},
  "geometry": {"coordinates":[4.9462118149,51.3292007446],"type":"Point"}
}