{
  "type": "Feature",
  "properties": {
    "iso:country":"BE",
    "sg:address":"Baasrodestraat 32",
    "sg:city":"Lebbeke",
    "sg:orig_category":"Rundveehouders",
    "sg:phone":"+32 52 41 12 20",
    "sg:postcode":"9280",
    "sg:province":"Oost-Vlaanderen",
    "wof:name":"Oscar Vermeir",
    "wof:placetype":"venue"
},
  "geometry": {"coordinates":[4.1357598305,51.0061035156],"type":"Point"}
}