{
  "type": "Feature",
  "properties": {
    "addr:full":"Boulevard Emile Bockstael 260 Bruxelles Bruxelles-Capitale 1020",
    "addr:housenumber":"260",
    "addr:postcode":"1020",
    "addr:street":"Boulevard Emile Bockstael",
    "iso:country":"BE",
    "sg:address":"Boulevard Emile Bockstael 260",
    "sg:city":"Bruxelles",
    "sg:classifiers":[
        {
            "category":"Retail",
            "subcategory":"Repair Shop",
            "type":"Services"
        }
    ],
    "sg:phone":"+32 2 428 33 21",
    "sg:postcode":"1020",
    "sg:province":"Bruxelles-Capitale",
    "sg:tags":[
        "-",
        "mainten",
        "watch",
        "clock"
    ],
    "wof:name":"Rombaux F",
    "wof:placetype":"venue"
},
  "geometry": {"coordinates":[4.3477897644,50.8782615662],"type":"Point"}
}