{
  "type": "Feature",
  "properties": {
    "addr:full":"Wittemolenstraat 70 Brugge (sint-michiels) West-Vlaanderen 8200",
    "addr:housenumber":"70",
    "addr:postcode":"8200",
    "addr:street":"Wittemolenstraat",
    "iso:country":"BE",
    "sg:address":"Wittemolenstraat 70",
    "sg:city":"Brugge (sint-michiels)",
    "sg:classifiers":[
        {
            "category":"Shopping",
            "subcategory":"Clothing, Apparel, & Fashions",
            "type":"Retail Goods"
        }
    ],
    "sg:phone":"+32 50 38 28 41",
    "sg:postcode":"8200",
    "sg:province":"West-Vlaanderen",
    "sg:tags":[
        "organizer",
        "show"
    ],
    "wof:name":"Andante",
    "wof:placetype":"venue"
},
  "geometry": {"coordinates":[3.1904699802,51.1992111206],"type":"Point"}
}