{
  "type": "Feature",
  "properties": {
    "addr:full":"Rue E. Cuvelier 35 Namen (groot) Namur 5000",
    "addr:housenumber":"35",
    "addr:postcode":"5000",
    "addr:street":"Rue E. Cuvelier;Groot Namur",
    "iso:country":"BE",
    "sg:address":"Rue E. Cuvelier 35",
    "sg:city":"Namen (groot)",
    "sg:orig_category":"Banken and kredietinstellingen",
    "sg:phone":"+32 81 25 35 11",
    "sg:postcode":"5000",
    "sg:province":"Namur",
    "wof:name":"Artesia",
    "wof:placetype":"venue"
},
  "geometry": {"coordinates":[4.8665099144,50.4644393921],"type":"Point"}
}