{
  "type": "Feature",
  "properties": {
    "addr:full":"Route Charlemagne 160 Welkenraedt Li\u00e8ge 4841",
    "addr:housenumber":"160",
    "addr:postcode":"4841",
    "addr:street":"Route Charlemagne",
    "iso:country":"BE",
    "sg:address":"Route Charlemagne 160",
    "sg:city":"Welkenraedt",
    "sg:orig_category":"Goederenvervoer over de weg",
    "sg:phone":"+32 87 88 13 21",
    "sg:postcode":"4841",
    "sg:province":"Li\u00e8ge",
    "wof:name":"Fafchamps",
    "wof:placetype":"venue"
},
  "geometry": {"coordinates":[5.9449892044,50.6816062927],"type":"Point"}
}