{
  "type": "Feature",
  "properties": {
    "iso:country":"BE",
    "sg:address":"Rue Des R\u00c9collets 6",
    "sg:city":"Bastogne",
    "sg:orig_category":"Tribunaux",
    "sg:phone":"+32 61 21 18 79",
    "sg:postcode":"6600",
    "sg:province":"Luxembourg",
    "wof:name":"Justice De Paix",
    "wof:placetype":"venue"
},
  "geometry": {"coordinates":[5.7178401947,50.0022315979],"type":"Point"}
}