{
  "type": "Feature",
  "properties": {
    "addr:full":"Chauss\u00e9e De Namur 87 Anh\u00e9e Namur 5537",
    "addr:housenumber":"87",
    "addr:postcode":"5537",
    "addr:street":"Chausse\u0301E De Namur",
    "iso:country":"BE",
    "sg:address":"Chauss\u00e9e De Namur 87",
    "sg:city":"Anh\u00e9e",
    "sg:classifiers":[
        {
            "category":"Bars & Pubs",
            "type":"Food & Drink"
        }
    ],
    "sg:phone":"+32 82 61 10 52",
    "sg:postcode":"5537",
    "sg:province":"Namur",
    "sg:tags":[
        "tavern"
    ],
    "wof:name":"Auberge St-christophe",
    "wof:placetype":"venue"
},
  "geometry": {"coordinates":[4.8736982346,50.3212509155],"type":"Point"}
}