{
  "type": "Feature",
  "properties": {
    "addr:full":"Moerbekeplein 4 Geraardsbergen Oost-Vlaanderen 9500",
    "addr:housenumber":"4",
    "addr:postcode":"9500",
    "addr:street":"Moerbekeplein",
    "iso:country":"BE",
    "sg:address":"Moerbekeplein 4",
    "sg:city":"Geraardsbergen",
    "sg:classifiers":[
        {
            "category":"Personal",
            "subcategory":"Beauty Salon",
            "type":"Services"
        }
    ],
    "sg:phone":"+32 54 41 53 87",
    "sg:postcode":"9500",
    "sg:province":"Oost-Vlaanderen",
    "sg:tags":[
        "de",
        "coiffure"
    ],
    "wof:name":"Coiffure Betty",
    "wof:placetype":"venue"
},
  "geometry": {"coordinates":[3.9174389839,50.7527008057],"type":"Point"}
}