{
  "type": "Feature",
  "properties": {
    "addr:full":"Rue Du Ch\u00eane 54 Frameries (noirchain) Hainaut 7080",
    "addr:housenumber":"54",
    "addr:postcode":"7080",
    "addr:street":"Rue Du Che\u0302Ne",
    "iso:country":"BE",
    "sg:address":"Rue Du Ch\u00eane 54",
    "sg:city":"Frameries (noirchain)",
    "sg:classifiers":[
        {
            "category":"Building & Trades",
            "subcategory":"Construction",
            "type":"Services"
        }
    ],
    "sg:phone":"+32 65 51 20 58",
    "sg:postcode":"7080",
    "sg:province":"Hainaut",
    "sg:tags":[
        "carpenter"
    ],
    "wof:name":"Henry (menuiserie) Sa",
    "wof:placetype":"venue"
},
  "geometry": {"coordinates":[3.9223759174,50.4037857056],"type":"Point"}
}