{
  "type": "Feature",
  "properties": {
    "addr:full":"Chauss\u00c9e De Namur 15 Gembloux Namur 5030",
    "addr:housenumber":"15",
    "addr:postcode":"5030",
    "addr:street":"Chausse\u0301E De Namur;Namur",
    "iso:country":"BE",
    "sg:address":"Chauss\u00c9e De Namur 15",
    "sg:city":"Gembloux",
    "sg:orig_category":"Benzinestations and brandstoffen",
    "sg:phone":"+32 81 61 14 54",
    "sg:postcode":"5030",
    "sg:province":"Namur",
    "wof:name":"Texaco",
    "wof:placetype":"venue"
},
  "geometry": {"coordinates":[4.698266983,50.5723381042],"type":"Point"}
}