{
  "type": "Feature",
  "properties": {
    "addr:full":"Torendreef 14 Westerlo Antwerpen 2260",
    "addr:housenumber":"14",
    "addr:postcode":"2260",
    "addr:street":"Torendreef",
    "iso:country":"BE",
    "sg:address":"Torendreef 14",
    "sg:city":"Westerlo",
    "sg:orig_category":"Eleveurs de bovins",
    "sg:phone":"+32 14 54 13 59",
    "sg:postcode":"2260",
    "sg:province":"Antwerpen",
    "wof:name":"Marc Helsen",
    "wof:placetype":"venue"
},
  "geometry": {"coordinates":[4.8886809349,51.1116523743],"type":"Point"}
}