{
  "type": "Feature",
  "properties": {
    "iso:country":"BE",
    "sg:address":"Vossenbergstraat 10",
    "sg:city":"Gent (oostakker)",
    "sg:classifiers":[
        {
            "category":"Building & Trades",
            "subcategory":"Plumbing",
            "type":"Services"
        }
    ],
    "sg:phone":"+32 9 251 16 18",
    "sg:postcode":"9041",
    "sg:province":"Oost-Vlaanderen",
    "sg:tags":[
        "contractor"
    ],
    "wof:name":"Vander Schaeven Bvba",
    "wof:placetype":"venue"
},
  "geometry": {"coordinates":[3.7807400227,51.0840377808],"type":"Point"}
}