{
  "type": "Feature",
  "properties": {
    "addr:full":"Generaal Biebuyckstraat 36 Brussel/bruxelles Bruxelles-Capitale 1120",
    "addr:housenumber":"36",
    "addr:postcode":"1120",
    "addr:street":"Generaal Biebuyckstraat;/",
    "iso:country":"BE",
    "sg:address":"Generaal Biebuyckstraat 36",
    "sg:city":"Brussel/bruxelles",
    "sg:orig_category":"Kapsalons",
    "sg:phone":"+32 2 215 07 61",
    "sg:postcode":"1120",
    "sg:province":"Bruxelles-Capitale",
    "wof:name":"Serge Mazzola",
    "wof:placetype":"venue"
},
  "geometry": {"coordinates":[4.3826570511,50.8889808655],"type":"Point"}
}