{
  "type": "Feature",
  "properties": {
    "addr:full":"Rue Emile Vandervelde 213 Beyne-heusay (queue-du-bois) Li\u00e8ge 4610",
    "addr:housenumber":"213",
    "addr:postcode":"4610",
    "addr:street":"Rue Emile Vandervelde",
    "iso:country":"BE",
    "sg:address":"Rue Emile Vandervelde 213",
    "sg:city":"Beyne-heusay (queue-du-bois)",
    "sg:classifiers":[
        {
            "category":"Shopping",
            "subcategory":"Books",
            "type":"Retail Goods"
        }
    ],
    "sg:phone":"+32 4 370 18 58",
    "sg:postcode":"4610",
    "sg:province":"Li\u00e8ge",
    "sg:tags":[
        "bookseller"
    ],
    "wof:name":"Masson F",
    "wof:placetype":"venue"
},
  "geometry": {"coordinates":[5.674279213,50.6392326355],"type":"Point"}
}