{
  "type": "Feature",
  "properties": {
    "addr:full":"Lanestraat 1 Jabbeke West-Vlaanderen 8490",
    "addr:housenumber":"1",
    "addr:postcode":"8490",
    "addr:street":"Lanestraat",
    "iso:country":"BE",
    "sg:address":"Lanestraat 1",
    "sg:city":"Jabbeke",
    "sg:orig_category":"Eleveurs de bovins",
    "sg:phone":"+32 50 81 16 49",
    "sg:postcode":"8490",
    "sg:province":"West-Vlaanderen",
    "wof:name":"Valere Dugardeyn",
    "wof:placetype":"venue"
},
  "geometry": {"coordinates":[3.0648150444,51.1685256958],"type":"Point"}
}