{
  "type": "Feature",
  "properties": {
    "iso:country":"BE",
    "sg:address":"Astridlaan 11b2r",
    "sg:city":"Blankenberge",
    "sg:orig_category":"Sportclubs",
    "sg:phone":"+32 477 22 92 49",
    "sg:postcode":"8370",
    "sg:province":"West-Vlaanderen",
    "wof:name":"T.c. Blankenberge",
    "wof:placetype":"venue"
},
  "geometry": {"coordinates":[3.139277935,51.3170661926],"type":"Point"}
}