{
  "type": "Feature",
  "properties": {
    "addr:full":"Parvis Notre-dame 19 Rhode-saint-genese Vlaams-Brabant 1640",
    "addr:housenumber":"19",
    "addr:postcode":"1640",
    "addr:street":"Parvis Notre-Dame;Vlaams-Brabant",
    "iso:country":"BE",
    "sg:address":"Parvis Notre-dame 19",
    "sg:city":"Rhode-saint-genese",
    "sg:orig_category":"DIVERSE RECREATIEVE ACTIVITEITEN",
    "sg:phone":"+32 2 358 29 65",
    "sg:postcode":"1640",
    "sg:province":"Vlaams-Brabant",
    "wof:name":"Les Ateliers De L'art Du Temps",
    "wof:placetype":"venue"
},
  "geometry": {"coordinates":[4.3815760612,50.756603241],"type":"Point"}
}