{
  "type": "Feature",
  "properties": {
    "addr:full":"Rue Des Quatres Six-aymon 62 Lessines Hainaut 7860",
    "addr:housenumber":"62",
    "addr:postcode":"7860",
    "addr:street":"Rue Des Quatres Six-Aymon;Hainaut",
    "iso:country":"BE",
    "sg:address":"Rue Des Quatres Six-aymon 62",
    "sg:city":"Lessines",
    "sg:orig_category":"Location de logements sociaux",
    "sg:phone":"+32 68 34 07 33",
    "sg:postcode":"7860",
    "sg:province":"Hainaut",
    "wof:name":"Le Plus Grand Lessines",
    "wof:placetype":"venue"
},
  "geometry": {"coordinates":[3.832679987,50.7117233276],"type":"Point"}
}