{
  "type": "Feature",
  "properties": {
    "addr:full":"Rue Jean Etienne 15 Li\u00c8ge Li\u00e8ge 4000",
    "addr:housenumber":"15",
    "addr:postcode":"4000",
    "addr:street":"Rue Jean Etienne",
    "iso:country":"BE",
    "sg:address":"Rue Jean Etienne 15",
    "sg:city":"Li\u00c8ge",
    "sg:orig_category":"Artsen and specialisten",
    "sg:phone":"+32 4 226 51 52",
    "sg:postcode":"4000",
    "sg:province":"Li\u00e8ge",
    "wof:name":"Willy Larbanois",
    "wof:placetype":"venue"
},
  "geometry": {"coordinates":[5.5540251732,50.6608276367],"type":"Point"}
}