{
  "type": "Feature",
  "properties": {
    "addr:full":"Meuleschettestraat 74 Aalst Oost-Vlaanderen 9300",
    "addr:housenumber":"74",
    "addr:postcode":"9300",
    "addr:street":"Meuleschettestraat",
    "iso:country":"BE",
    "sg:address":"Meuleschettestraat 74",
    "sg:city":"Aalst",
    "sg:classifiers":[
        {
            "category":"Arts & Performance",
            "subcategory":"Theater",
            "type":"Entertainment"
        }
    ],
    "sg:phone":"+32 53 78 76 24",
    "sg:postcode":"9300",
    "sg:province":"Oost-Vlaanderen",
    "sg:tags":[
        "group",
        "theatre"
    ],
    "wof:name":"Pact Vzw",
    "wof:placetype":"venue"
},
  "geometry": {"coordinates":[4.0290641785,50.9425621033],"type":"Point"}
}