{
  "type": "Feature",
  "properties": {
    "iso:country":"BE",
    "sg:address":"Kasteleinsplein 38",
    "sg:city":"Elsene/ixelles",
    "sg:orig_category":"Immobili\u00ebnkantoren",
    "sg:phone":"+32 2 539 38 67",
    "sg:postcode":"1050",
    "sg:province":"Bruxelles-Capitale",
    "wof:name":"A.d.b. Invest",
    "wof:placetype":"venue"
},
  "geometry": {"coordinates":[4.3607759476,50.8245773315],"type":"Point"}
}