{
  "type": "Feature",
  "properties": {
    "addr:full":"Kloosterstraat 5 Kortrijk West-Vlaanderen 8510",
    "addr:housenumber":"5",
    "addr:postcode":"8510",
    "addr:street":"Kloosterstraat",
    "iso:country":"BE",
    "sg:address":"Kloosterstraat 5",
    "sg:city":"Kortrijk",
    "sg:orig_category":"Bagage and lederwaren Schoenen",
    "sg:phone":"+32 56 21 12 68",
    "sg:postcode":"8510",
    "sg:province":"West-Vlaanderen",
    "wof:name":"Huis Caliga",
    "wof:placetype":"venue"
},
  "geometry": {"coordinates":[3.2342469692,50.8069725037],"type":"Point"}
}