{
  "type": "Feature",
  "properties": {
    "iso:country":"BE",
    "sg:address":"Steinstraat 9",
    "sg:city":"Nazareth",
    "sg:classifiers":[
        {
            "category":"Arena",
            "subcategory":"Sports Club",
            "type":"Entertainment"
        }
    ],
    "sg:phone":"+32 9 385 65 14",
    "sg:postcode":"9810",
    "sg:province":"Oost-Vlaanderen",
    "sg:tags":[
        "de"
    ],
    "wof:name":"V.c. Navok Dames",
    "wof:placetype":"venue"
},
  "geometry": {"coordinates":[3.6060249805,50.9633674622],"type":"Point"}
}