{
  "type": "Feature",
  "properties": {
    "addr:full":"Mechelsestraat 62 Gingelom Limburg 3890",
    "addr:housenumber":"62",
    "addr:postcode":"3890",
    "addr:street":"Mechelsestraat",
    "iso:country":"BE",
    "sg:address":"Mechelsestraat 62",
    "sg:city":"Gingelom",
    "sg:orig_category":"Fruitteelt",
    "sg:phone":"+32 11 48 59 47",
    "sg:postcode":"3890",
    "sg:province":"Limburg",
    "wof:name":"Raymond Bex",
    "wof:placetype":"venue"
},
  "geometry": {"coordinates":[5.2387981415,50.7442703247],"type":"Point"}
}