{
  "type": "Feature",
  "properties": {
    "iso:country":"BE",
    "sg:address":"Andrimontlaan 13",
    "sg:city":"Ukkel/uccle",
    "sg:orig_category":"Loodgieterij, verwarming and sanitaire installaties",
    "sg:phone":"+32 2 374 00 37",
    "sg:postcode":"1180",
    "sg:province":"Bruxelles-Capitale",
    "wof:name":"Theeten Et Fils",
    "wof:placetype":"venue"
},
  "geometry": {"coordinates":[4.3660540581,50.7895355225],"type":"Point"}
}