{
  "type": "Feature",
  "properties": {
    "iso:country":"BE",
    "sg:address":"Vrombautstraat 75",
    "sg:city":"Eeklo",
    "sg:classifiers":[
        {
            "category":"Wholesale",
            "subcategory":"Fruits & Vegetables",
            "type":"Manufacturing & Wholesale Goods"
        }
    ],
    "sg:phone":"+32 9 377 27 17",
    "sg:postcode":"9900",
    "sg:province":"Oost-Vlaanderen",
    "sg:tags":[
        "whol",
        "-"
    ],
    "wof:name":"De Busschere J",
    "wof:placetype":"venue"
},
  "geometry": {"coordinates":[3.5793800354,51.1925773621],"type":"Point"}
}