{
  "type": "Feature",
  "properties": {
    "addr:full":"Gielelaan 13 Jette/jette Bruxelles-Capitale 1090",
    "addr:housenumber":"13",
    "addr:postcode":"1090",
    "addr:street":"Gielelaan",
    "iso:country":"BE",
    "sg:address":"Gielelaan 13",
    "sg:city":"Jette/jette",
    "sg:orig_category":"Kinderopvang",
    "sg:phone":"+32 2 425 96 12",
    "sg:postcode":"1090",
    "sg:province":"Bruxelles-Capitale",
    "wof:name":"Cr\u00c8che B\u00c9b\u00c9s A.b.c.",
    "wof:placetype":"venue"
},
  "geometry": {"coordinates":[4.3270711899,50.8678474426],"type":"Point"}
}