{
  "type": "Feature",
  "properties": {
    "iso:country":"BE",
    "sg:address":"Burchtstraat 20",
    "sg:city":"Leuven",
    "sg:classifiers":[
        {
            "category":"Structure",
            "subcategory":"Building",
            "type":"Public Place"
        }
    ],
    "sg:phone":"+32 16 22 67 52",
    "sg:postcode":"3000",
    "sg:province":"Vlaams-Brabant",
    "sg:tags":[
        "door"
    ],
    "wof:name":"Decoster L",
    "wof:placetype":"venue"
},
  "geometry": {"coordinates":[4.6974830627,50.8871688843],"type":"Point"}
}