{
  "type": "Feature",
  "properties": {
    "addr:full":"Sint-stefaansstraat 82 Zaventem (sint-stevens-woluwe) Vlaams-Brabant 1932",
    "addr:housenumber":"82",
    "addr:postcode":"1932",
    "addr:street":"Sint-Stefaansstraat",
    "iso:country":"BE",
    "sg:address":"Sint-stefaansstraat 82",
    "sg:city":"Zaventem (sint-stevens-woluwe)",
    "sg:classifiers":[
        {
            "category":"Real Estate",
            "subcategory":"Surveying",
            "type":"Services"
        }
    ],
    "sg:phone":"+32 2 725 70 44",
    "sg:postcode":"1932",
    "sg:province":"Vlaams-Brabant",
    "sg:tags":[
        "surveyor",
        "land"
    ],
    "wof:name":"Vanhemelryck A",
    "wof:placetype":"venue"
},
  "geometry": {"coordinates":[4.4517350197,50.8706474304],"type":"Point"}
}