{
  "type": "Feature",
  "properties": {
    "addr:full":"Kromstraat 9a Riemst (millen) Limburg 3770",
    "addr:housenumber":"9a",
    "addr:postcode":"3770",
    "addr:street":"Kromstraat",
    "iso:country":"BE",
    "sg:address":"Kromstraat 9a",
    "sg:city":"Riemst (millen)",
    "sg:classifiers":[
        {
            "category":"Health Services",
            "subcategory":"Health Practitioner",
            "type":"Services"
        }
    ],
    "sg:phone":"+32 12 26 40 35",
    "sg:postcode":"3770",
    "sg:province":"Limburg",
    "sg:tags":[
        "physiotherapist"
    ],
    "wof:name":"Steegen Peggy",
    "wof:placetype":"venue"
},
  "geometry": {"coordinates":[5.5969901085,50.8109016418],"type":"Point"}
}