{
  "type": "Feature",
  "properties": {
    "iso:country":"BE",
    "sg:address":"Rue Du Noir Jambon 4",
    "sg:city":"Silly",
    "sg:orig_category":"Rundveehouders",
    "sg:phone":"+32 67 45 83 82",
    "sg:postcode":"7830",
    "sg:province":"Hainaut",
    "wof:name":"Commerce Bailly",
    "wof:placetype":"venue"
},
  "geometry": {"coordinates":[3.9541540146,50.6073417664],"type":"Point"}
}