{
  "type": "Feature",
  "properties": {
    "addr:full":"Sint-janstraat 41 Beringen (paal) Limburg 3583",
    "addr:housenumber":"41",
    "addr:postcode":"3583",
    "addr:street":"Sint-Janstraat",
    "iso:country":"BE",
    "sg:address":"Sint-janstraat 41",
    "sg:city":"Beringen (paal)",
    "sg:classifiers":[
        {
            "category":"Bars & Pubs",
            "type":"Food & Drink"
        }
    ],
    "sg:phone":"+32 11 42 98 17",
    "sg:postcode":"3583",
    "sg:province":"Limburg",
    "sg:tags":[
        "tavern"
    ],
    "wof:name":"De Stam",
    "wof:placetype":"venue"
},
  "geometry": {"coordinates":[5.1769127846,51.0380401611],"type":"Point"}
}