{
  "type": "Feature",
  "properties": {
    "addr:full":"Rue Des D\u00e9port\u00e9s 38 Arlon Luxembourg 6700",
    "addr:housenumber":"38",
    "addr:postcode":"6700",
    "addr:street":"Rue Des De\u0301Porte\u0301S",
    "iso:country":"BE",
    "sg:address":"Rue Des D\u00e9port\u00e9s 38",
    "sg:city":"Arlon",
    "sg:classifiers":[
        {
            "category":"Communications",
            "subcategory":"Radio Station",
            "type":"Services"
        }
    ],
    "sg:phone":"+32 63 21 61 75",
    "sg:postcode":"6700",
    "sg:province":"Luxembourg",
    "sg:tags":[
        "local"
    ],
    "wof:name":"Nostalgie Radio",
    "wof:placetype":"venue"
},
  "geometry": {"coordinates":[5.8208508492,49.6791954041],"type":"Point"}
}