{
  "type": "Feature",
  "properties": {
    "addr:full":"Hofbilkstraat 56 Evergem Oost-Vlaanderen 9940",
    "addr:housenumber":"56",
    "addr:postcode":"9940",
    "addr:street":"Hofbilkstraat;Oost-Vlaanderen",
    "iso:country":"BE",
    "sg:address":"Hofbilkstraat 56",
    "sg:city":"Evergem",
    "sg:orig_category":"Brood, gebak and snoepgoed",
    "sg:phone":"+32 9 253 81 25",
    "sg:postcode":"9940",
    "sg:province":"Oost-Vlaanderen",
    "wof:name":"Gilbert Dossche",
    "wof:placetype":"venue"
},
  "geometry": {"coordinates":[3.7075529099,51.113368988],"type":"Point"}
}