{
  "type": "Feature",
  "properties": {
    "iso:country":"BE",
    "sg:address":"Redingenstraat 31",
    "sg:city":"Leuven",
    "sg:classifiers":[
        {
            "category":"Shopping",
            "subcategory":"Crafts & Fabrics",
            "type":"Retail Goods"
        }
    ],
    "sg:phone":"+32 16 20 62 41",
    "sg:postcode":"3000",
    "sg:province":"Vlaams-Brabant",
    "sg:tags":[
        "ceramic"
    ],
    "wof:name":"De Potpourri Keramiek-atelier Jan Vander Elst",
    "wof:placetype":"venue"
},
  "geometry": {"coordinates":[4.6963610649,50.8736000061],"type":"Point"}
}