{
  "type": "Feature",
  "properties": {
    "addr:full":"Chauss\u00e9e De Haecht 178 Bruxelles (schaerbeek) Bruxelles-Capitale 1030",
    "addr:housenumber":"178",
    "addr:postcode":"1030",
    "addr:street":"Chausse\u0301E De Haecht",
    "iso:country":"BE",
    "sg:address":"Chauss\u00e9e De Haecht 178",
    "sg:city":"Bruxelles (schaerbeek)",
    "sg:classifiers":[
        {
            "category":"Communications",
            "type":"Services"
        }
    ],
    "sg:phone":"+32 2 216 21 57",
    "sg:postcode":"1030",
    "sg:province":"Bruxelles-Capitale",
    "sg:tags":[
        "translator"
    ],
    "wof:name":"Kubat H",
    "wof:placetype":"venue"
},
  "geometry": {"coordinates":[4.3715519905,50.8603668213],"type":"Point"}
}