{
  "type": "Feature",
  "properties": {
    "iso:country":"BE",
    "sg:address":"S/n Parc Industriel Sud",
    "sg:city":"Nivelles",
    "sg:classifiers":[
        {
            "category":"Banks & Credit Unions",
            "subcategory":"Investment Brokerage",
            "type":"Services"
        }
    ],
    "sg:phone":"+32 67 21 63 31",
    "sg:postcode":"1400",
    "sg:province":"Brabant Wallon",
    "sg:tags":[
        "-",
        "transport",
        "related"
    ],
    "wof:name":"Trans Jung",
    "wof:placetype":"venue"
},
  "geometry": {"coordinates":[4.3223419189,50.5976524353],"type":"Point"}
}