{
  "type": "Feature",
  "properties": {
    "iso:country":"BE",
    "sg:address":"Bellegemsestraat 74",
    "sg:city":"Kortrijk",
    "sg:orig_category":"Artsen and specialisten",
    "sg:phone":"+32 56 22 65 96",
    "sg:postcode":"8510",
    "sg:province":"West-Vlaanderen",
    "wof:name":"Patrick Amez",
    "wof:placetype":"venue"
},
  "geometry": {"coordinates":[3.2859950066,50.7773780823],"type":"Point"}
}