{
  "type": "Feature",
  "properties": {
    "iso:country":"BE",
    "sg:address":"Priester Daensstraat 10",
    "sg:city":"Kruishoutem",
    "sg:classifiers":[
        {
            "category":"Arena",
            "subcategory":"Sports Club",
            "type":"Entertainment"
        }
    ],
    "sg:phone":"+32 9 383 64 86",
    "sg:postcode":"9770",
    "sg:province":"Oost-Vlaanderen",
    "sg:tags":[
        "terrain",
        "hors",
        "de",
        "installation",
        "sportifs"
    ],
    "wof:name":"K.s.k. Kruishoutem",
    "wof:placetype":"venue"
},
  "geometry": {"coordinates":[3.5265090466,50.899269104],"type":"Point"}
}