{
  "type": "Feature",
  "properties": {
    "addr:full":"Spitaalstraat 9 Waregem West-Vlaanderen 8790",
    "addr:housenumber":"9",
    "addr:postcode":"8790",
    "addr:street":"Spitaalstraat",
    "iso:country":"BE",
    "sg:address":"Spitaalstraat 9",
    "sg:city":"Waregem",
    "sg:orig_category":"Woningbouw",
    "sg:phone":"+32 56 61 20 02",
    "sg:postcode":"8790",
    "sg:province":"West-Vlaanderen",
    "wof:name":"Martin Derycke",
    "wof:placetype":"venue"
},
  "geometry": {"coordinates":[3.3979101181,50.8687705994],"type":"Point"}
}