{
  "type": "Feature",
  "properties": {
    "iso:country":"BE",
    "sg:address":"Koningin Astridlaan 47",
    "sg:city":"Kapellen",
    "sg:orig_category":"Diverse organisaties and verenigingen",
    "sg:phone":"+32 3 664 83 92",
    "sg:postcode":"2950",
    "sg:province":"Antwerpen",
    "wof:name":"Vvksm Akabe de Zonnepinkers",
    "wof:placetype":"venue"
},
  "geometry": {"coordinates":[4.4420900345,51.3120040894],"type":"Point"}
}