{
  "type": "Feature",
  "properties": {
    "addr:full":"Mechelsesteenweg 247-249 Bonheiden Antwerpen 2820",
    "addr:housenumber":"247-249",
    "addr:postcode":"2820",
    "addr:street":"Mechelsesteenweg",
    "iso:country":"BE",
    "sg:address":"Mechelsesteenweg 247-249",
    "sg:city":"Bonheiden",
    "sg:orig_category":"Industri\u00eble and commerci\u00eble bouw Loodgieterij, verwarming and sanitaire installaties",
    "sg:phone":"+32 15 55 51 51",
    "sg:postcode":"2820",
    "sg:province":"Antwerpen",
    "wof:name":"A.t.k.",
    "wof:placetype":"venue"
},
  "geometry": {"coordinates":[4.5277309418,51.0288238525],"type":"Point"}
}