{
  "type": "Feature",
  "properties": {
    "iso:country":"BE",
    "sg:address":"Dynastiestraat 86a",
    "sg:city":"Zemst (elewijt)",
    "sg:classifiers":[
        {
            "category":"Communications",
            "subcategory":"Film & Video Production",
            "type":"Services"
        }
    ],
    "sg:phone":"+32 15 61 69 19",
    "sg:postcode":"1982",
    "sg:province":"Vlaams-Brabant",
    "sg:tags":[
        "material",
        "audio-visual"
    ],
    "wof:name":"Blackfox Bvba",
    "wof:placetype":"venue"
},
  "geometry": {"coordinates":[4.5058569908,50.9627571106],"type":"Point"}
}