{
  "type": "Feature",
  "properties": {
    "addr:full":"Rue Du Beau Site 51 Charleroi (marcinelle) Hainaut 6001",
    "addr:housenumber":"51",
    "addr:postcode":"6001",
    "addr:street":"Rue Du Beau Site",
    "iso:country":"BE",
    "sg:address":"Rue Du Beau Site 51",
    "sg:city":"Charleroi (marcinelle)",
    "sg:classifiers":[
        {
            "category":"Health Services",
            "subcategory":"Health Practitioner",
            "type":"Services"
        }
    ],
    "sg:phone":"+32 71 43 20 44",
    "sg:postcode":"6001",
    "sg:province":"Hainaut",
    "sg:tags":[
        "physiotherapist"
    ],
    "wof:name":"Berwart C",
    "wof:placetype":"venue"
},
  "geometry": {"coordinates":[4.4249100685,50.3957519531],"type":"Point"}
}