{
  "type": "Feature",
  "properties": {
    "addr:full":"Desselgemseweg 113 Waregem West-Vlaanderen 8790",
    "addr:housenumber":"113",
    "addr:postcode":"8790",
    "iso:country":"BE",
    "sg:address":"Desselgemseweg 113",
    "sg:city":"Waregem",
    "sg:orig_category":"Peinture. Rev\u00eatements pour sols and murs",
    "sg:phone":"+32 56 61 07 97",
    "sg:postcode":"8790",
    "sg:province":"West-Vlaanderen",
    "wof:name":"Vervaeke Gebrs",
    "wof:placetype":"venue"
},
  "geometry": {"coordinates":[3.4063000679,50.8810806274],"type":"Point"}
}