{
  "type": "Feature",
  "properties": {
    "iso:country":"BE",
    "sg:address":"Rue Herman Reuleaux 54",
    "sg:city":"Li\u00c8ge",
    "sg:orig_category":"Activit\u00e9s r\u00e9cr\u00e9atives diverses",
    "sg:phone":"+32 4 343 86 22",
    "sg:postcode":"4020",
    "sg:province":"Li\u00e8ge",
    "wof:name":"Club Philat\u00c9lique Le Tram",
    "wof:placetype":"venue"
},
  "geometry": {"coordinates":[5.5917720795,50.637714386],"type":"Point"}
}