{
  "type": "Feature",
  "properties": {
    "addr:full":"Mispelstraat 46 Sint-niklaas Oost-Vlaanderen 9100",
    "addr:housenumber":"46",
    "addr:postcode":"9100",
    "addr:street":"Mispelstraat",
    "iso:country":"BE",
    "sg:address":"Mispelstraat 46",
    "sg:city":"Sint-niklaas",
    "sg:classifiers":[
        {
            "category":"Cafe",
            "type":"Food & Drink"
        }
    ],
    "sg:phone":"+32 3 777 02 28",
    "sg:postcode":"9100",
    "sg:province":"Oost-Vlaanderen",
    "sg:tags":[
        "caf\u00e9s"
    ],
    "wof:name":"Jenny Van Duyse",
    "wof:placetype":"venue"
},
  "geometry": {"coordinates":[4.1192669868,51.1765327454],"type":"Point"}
}