{
  "type": "Feature",
  "properties": {
    "addr:full":"Rue De La Brasserie 18 La Bruy\u00c8re Namur 5080",
    "addr:housenumber":"18",
    "addr:postcode":"5080",
    "addr:street":"Rue De La Brasserie",
    "iso:country":"BE",
    "sg:address":"Rue De La Brasserie 18",
    "sg:city":"La Bruy\u00c8re",
    "sg:classifiers":[
        {
            "category":"Arena",
            "subcategory":"Sports Club",
            "type":"Entertainment"
        }
    ],
    "sg:phone":"+32 81 51 10 87",
    "sg:postcode":"5080",
    "sg:province":"Namur",
    "sg:tags":[
        "de"
    ],
    "wof:name":"M.c. Les Petits Gris",
    "wof:placetype":"venue"
},
  "geometry": {"coordinates":[4.8665299416,50.5320854187],"type":"Point"}
}