{
  "type": "Feature",
  "properties": {
    "addr:full":"Marktstraat 25 Izegem West-Vlaanderen 8870",
    "addr:housenumber":"25",
    "addr:postcode":"8870",
    "addr:street":"Marktstraat",
    "iso:country":"BE",
    "sg:address":"Marktstraat 25",
    "sg:city":"Izegem",
    "sg:orig_category":"Parfumeries",
    "sg:phone":"+32 51 30 70 97",
    "sg:postcode":"8870",
    "sg:province":"West-Vlaanderen",
    "wof:name":"Parfumerie Piu Belli",
    "wof:placetype":"venue"
},
  "geometry": {"coordinates":[3.2149178982,50.9184799194],"type":"Point"}
}