{
  "type": "Feature",
  "properties": {
    "addr:full":"Place Albert Ier 26 Chapelle-lez-herlaimont Hainaut 7160",
    "addr:housenumber":"26",
    "addr:postcode":"7160",
    "addr:street":"Place Albert Ier",
    "iso:country":"BE",
    "sg:address":"Place Albert Ier 26",
    "sg:city":"Chapelle-lez-herlaimont",
    "sg:classifiers":[
        {
            "category":"Personal",
            "subcategory":"Beauty Salon",
            "type":"Services"
        }
    ],
    "sg:phone":"+32 64 26 79 00",
    "sg:postcode":"7160",
    "sg:province":"Hainaut",
    "sg:tags":[
        "de",
        "coiffure"
    ],
    "wof:name":"Les Femmes Et Les Enfants D'abad",
    "wof:placetype":"venue"
},
  "geometry": {"coordinates":[4.2810049057,50.4714736938],"type":"Point"}
}