{
  "type": "Feature",
  "properties": {
    "addr:full":"Leuvensesteenweg 319 Aarschot Vlaams-Brabant 3200",
    "addr:housenumber":"319",
    "addr:postcode":"3200",
    "addr:street":"Leuvensesteenweg",
    "iso:country":"BE",
    "sg:address":"Leuvensesteenweg 319",
    "sg:city":"Aarschot",
    "sg:orig_category":"Installatie van houten of kunststof schrijnwerk Installatie van metalen schrijnwerk Serres and speci",
    "sg:phone":"+32 16 56 08 51",
    "sg:postcode":"3200",
    "sg:province":"Vlaams-Brabant",
    "wof:name":"Bouw- En Constructiebedrijf Ve-ra-bo",
    "wof:placetype":"venue"
},
  "geometry": {"coordinates":[4.8058838844,50.9741363525],"type":"Point"}
}