{
  "type": "Feature",
  "properties": {
    "addr:full":"Koningslaan 165 Vorst/forest Bruxelles-Capitale 1190",
    "addr:housenumber":"165",
    "addr:postcode":"1190",
    "addr:street":"Koningslaan;/ Forest",
    "iso:country":"BE",
    "sg:address":"Koningslaan 165",
    "sg:city":"Vorst/forest",
    "sg:orig_category":"Artsen and specialisten",
    "sg:phone":"+32 2 534 10 06",
    "sg:postcode":"1190",
    "sg:province":"Bruxelles-Capitale",
    "wof:name":"Philippe Sorlin",
    "wof:placetype":"venue"
},
  "geometry": {"coordinates":[4.3341798782,50.8259506226],"type":"Point"}
}