{
  "type": "Feature",
  "properties": {
    "addr:full":"Spanjaardshoek 43 Maldegem Oost-Vlaanderen 9991",
    "addr:housenumber":"43",
    "addr:postcode":"9991",
    "addr:street":"Spanjaardshoek",
    "iso:country":"BE",
    "sg:address":"Spanjaardshoek 43",
    "sg:city":"Maldegem",
    "sg:classifiers":[
        {
            "category":"Insurance",
            "subcategory":"Insurance Agent",
            "type":"Services"
        }
    ],
    "sg:phone":"+32 50 71 25 87",
    "sg:postcode":"9991",
    "sg:province":"Oost-Vlaanderen",
    "sg:tags":[
        "verzekeringsmakelaars",
        "expert"
    ],
    "wof:name":"Kantoor Haneca Dewilde",
    "wof:placetype":"venue"
},
  "geometry": {"coordinates":[3.4930710793,51.1951713562],"type":"Point"}
}