{
  "type": "Feature",
  "properties": {
    "iso:country":"BE",
    "sg:address":"Rue De Boussoit 35",
    "sg:city":"La Louvi\u00c8re",
    "sg:orig_category":"S\u00e9curit\u00e9 sociale",
    "sg:phone":"+32 64 67 57 54",
    "sg:postcode":"7110",
    "sg:province":"Hainaut",
    "wof:name":"Mutualit\u00c9 Socialiste",
    "wof:placetype":"venue"
},
  "geometry": {"coordinates":[4.1505050659,50.4826698303],"type":"Point"}
}