{
  "type": "Feature",
  "properties": {
    "addr:full":"Moerhuizestraat 50 Maldegem Oost-Vlaanderen 9990",
    "addr:housenumber":"50",
    "addr:postcode":"9990",
    "addr:street":"Moerhuizestraat",
    "iso:country":"BE",
    "sg:address":"Moerhuizestraat 50",
    "sg:city":"Maldegem",
    "sg:classifiers":[
        {
            "category":"Bars & Pubs",
            "type":"Food & Drink"
        }
    ],
    "sg:phone":"+32 50 71 27 41",
    "sg:postcode":"9990",
    "sg:province":"Oost-Vlaanderen",
    "wof:name":"Populierenhof",
    "wof:placetype":"venue"
},
  "geometry": {"coordinates":[3.459086895,51.2337684631],"type":"Point"}
}