{
  "type": "Feature",
  "properties": {
    "iso:country":"BE",
    "sg:address":"Valkenlaan 6",
    "sg:city":"Menen",
    "sg:classifiers":[
        {
            "category":"Food & Beverages",
            "subcategory":"Supermarket",
            "type":"Retail Goods"
        }
    ],
    "sg:phone":"+32 56 51 44 09",
    "sg:postcode":"8930",
    "sg:province":"West-Vlaanderen",
    "sg:tags":[
        "frozen",
        "-"
    ],
    "wof:name":"Vancoillie B",
    "wof:placetype":"venue"
},
  "geometry": {"coordinates":[3.0972371101,50.7938995361],"type":"Point"}
}