{
  "type": "Feature",
  "properties": {
    "iso:country":"BE",
    "sg:address":"Christinastraat 51ba",
    "sg:city":"Oostende",
    "sg:orig_category":"Catering and organisatie van feesten Voedingsspeciaalzaken",
    "sg:phone":"+32 59 50 92 16",
    "sg:postcode":"8400",
    "sg:province":"West-Vlaanderen",
    "wof:name":"The Captain\u00b4s Table",
    "wof:placetype":"venue"
},
  "geometry": {"coordinates":[2.9165139198,51.2310447693],"type":"Point"}
}