{
  "type": "Feature",
  "properties": {
    "addr:full":"Parklaan 34 Temse Oost-Vlaanderen 9140",
    "addr:housenumber":"34",
    "addr:postcode":"9140",
    "addr:street":"Parklaan",
    "iso:country":"BE",
    "sg:address":"Parklaan 34",
    "sg:city":"Temse",
    "sg:classifiers":[
        {
            "category":"Military Area",
            "subcategory":"Air Force Base",
            "type":"Public Place"
        }
    ],
    "sg:phone":"+32 3 711 00 05",
    "sg:postcode":"9140",
    "sg:province":"Oost-Vlaanderen",
    "sg:tags":[
        "fire",
        "protection"
    ],
    "wof:name":"Avotex Bvba",
    "wof:placetype":"venue"
},
  "geometry": {"coordinates":[4.2223858833,51.1259994507],"type":"Point"}
}