{
  "type": "Feature",
  "properties": {
    "addr:full":"Eikenlaan 1 Bilzen Limburg 3740",
    "addr:housenumber":"1",
    "addr:postcode":"3740",
    "addr:street":"Eikenlaan",
    "iso:country":"BE",
    "sg:address":"Eikenlaan 1",
    "sg:city":"Bilzen",
    "sg:orig_category":"Diverse zakelijke dienstverlening",
    "sg:phone":"+32 89 41 89 38",
    "sg:postcode":"3740",
    "sg:province":"Limburg",
    "wof:name":"Allround Stage Crew",
    "wof:placetype":"venue"
},
  "geometry": {"coordinates":[5.5103797913,50.8686485291],"type":"Point"}
}