{
  "type": "Feature",
  "properties": {
    "iso:country":"BE",
    "sg:address":"Kempische Steenweg 567",
    "sg:city":"Hasselt",
    "sg:classifiers":[
        {
            "category":"Professional",
            "subcategory":"Computer Services",
            "type":"Services"
        }
    ],
    "sg:phone":"+32 11 21 13 11",
    "sg:postcode":"3500",
    "sg:province":"Limburg",
    "sg:tags":[
        "-",
        "processing",
        "data",
        "software"
    ],
    "wof:name":"Alfa Computers Nv",
    "wof:placetype":"venue"
},
  "geometry": {"coordinates":[5.3410100937,50.9384231567],"type":"Point"}
}