{
  "type": "Feature",
  "properties": {
    "iso:country":"BE",
    "sg:address":"Waterlozestraat 72",
    "sg:city":"Hasselt (stokrooie)",
    "sg:classifiers":[
        {
            "category":"Health Services",
            "subcategory":"Nursing And Care Facility",
            "type":"Services"
        }
    ],
    "sg:phone":"+32 11 25 65 31",
    "sg:postcode":"3511",
    "sg:province":"Limburg",
    "sg:tags":[
        "home"
    ],
    "wof:name":"Ceunen P",
    "wof:placetype":"venue"
},
  "geometry": {"coordinates":[5.2637667656,50.9701042175],"type":"Point"}
}