{
  "type": "Feature",
  "properties": {
    "addr:full":"Rue Vall\u00c9e 598 Trooz Li\u00e8ge 4870",
    "addr:housenumber":"598",
    "addr:postcode":"4870",
    "addr:street":"Rue Valle\u0301E",
    "iso:country":"BE",
    "sg:address":"Rue Vall\u00c9e 598",
    "sg:city":"Trooz",
    "sg:classifiers":[
        {
            "category":"Insurance",
            "subcategory":"Insurance Agent",
            "type":"Services"
        }
    ],
    "sg:phone":"+32 87 26 91 92",
    "sg:postcode":"4870",
    "sg:province":"Li\u00e8ge",
    "sg:tags":[
        "verzekeringsmakelaars",
        "expert"
    ],
    "wof:name":"G\u00c9rard Duquenne",
    "wof:placetype":"venue"
},
  "geometry": {"coordinates":[5.6734352112,50.5785331726],"type":"Point"}
}