{
  "type": "Feature",
  "properties": {
    "addr:full":"Rue Bonneels 19 Bruxelles (saint-josse-ten-noode) Bruxelles-Capitale 1210",
    "addr:housenumber":"19",
    "addr:postcode":"1210",
    "addr:street":"Rue Bonneels",
    "iso:country":"BE",
    "sg:address":"Rue Bonneels 19",
    "sg:city":"Bruxelles (saint-josse-ten-noode)",
    "sg:classifiers":[
        {
            "category":"Community Center",
            "type":"Public Place"
        }
    ],
    "sg:phone":"+32 2 230 46 58",
    "sg:postcode":"1210",
    "sg:province":"Bruxelles-Capitale",
    "sg:tags":[
        "medical"
    ],
    "wof:name":"Oceanide Therapy Center",
    "wof:placetype":"venue"
},
  "geometry": {"coordinates":[4.378027916,50.8492507935],"type":"Point"}
}