{
  "type": "Feature",
  "properties": {
    "addr:full":"Zuidhoekweg 5ba Ledegem West-Vlaanderen 8880",
    "addr:postcode":"8880",
    "addr:street":"Zuidhoekweg",
    "iso:country":"BE",
    "sg:address":"Zuidhoekweg 5ba",
    "sg:city":"Ledegem",
    "sg:classifiers":[
        {
            "category":"Cafe",
            "type":"Food & Drink"
        }
    ],
    "sg:phone":"+32 56 50 67 33",
    "sg:postcode":"8880",
    "sg:province":"West-Vlaanderen",
    "sg:tags":[
        "caf\u00e9s"
    ],
    "wof:name":"Koenraad Dupont",
    "wof:placetype":"venue"
},
  "geometry": {"coordinates":[3.1893389225,50.8635902405],"type":"Point"}
}