{
  "type": "Feature",
  "properties": {
    "iso:country":"BE",
    "sg:address":"Koralenhoeve 8a",
    "sg:city":"Wommelgem",
    "sg:classifiers":[
        {
            "category":"Building & Trades",
            "subcategory":"Plumbing",
            "type":"Services"
        }
    ],
    "sg:phone":"+32 3 354 23 00",
    "sg:postcode":"2160",
    "sg:province":"Antwerpen",
    "sg:tags":[
        "diver",
        "commerce",
        "gr",
        "pour",
        "equipement"
    ],
    "wof:name":"Carrier Transicold",
    "wof:placetype":"venue"
},
  "geometry": {"coordinates":[4.5206990242,51.2103462219],"type":"Point"}
}