{
  "type": "Feature",
  "properties": {
    "addr:full":"Vestenstraat 14 Vilvoorde Vlaams-Brabant 1800",
    "addr:housenumber":"14",
    "addr:postcode":"1800",
    "addr:street":"Vestenstraat",
    "iso:country":"BE",
    "sg:address":"Vestenstraat 14",
    "sg:city":"Vilvoorde",
    "sg:orig_category":"Enseignement secondaire g\u00e9n\u00e9ral",
    "sg:phone":"+32 2 251 27 03",
    "sg:postcode":"1800",
    "sg:province":"Vlaams-Brabant",
    "wof:name":"Buso",
    "wof:placetype":"venue"
},
  "geometry": {"coordinates":[4.4211277962,50.9324455261],"type":"Point"}
}