{
  "type": "Feature",
  "properties": {
    "iso:country":"BE",
    "sg:address":"Kerkstraat 218",
    "sg:city":"Deerlijk",
    "sg:orig_category":"Epiceries",
    "sg:phone":"+32 56 77 92 07",
    "sg:postcode":"8540",
    "sg:province":"West-Vlaanderen",
    "wof:name":"Carlos Cottenier",
    "wof:placetype":"venue"
},
  "geometry": {"coordinates":[3.385322094,50.8290519714],"type":"Point"}
}