{
  "type": "Feature",
  "properties": {
    "addr:full":"Schierveldestraat 55 Roeselare West-Vlaanderen 8800",
    "addr:housenumber":"55",
    "addr:postcode":"8800",
    "addr:street":"Schierveldestraat",
    "iso:country":"BE",
    "sg:address":"Schierveldestraat 55",
    "sg:city":"Roeselare",
    "sg:orig_category":"Enseignement maternel and primaire",
    "sg:phone":"+32 51 24 35 36",
    "sg:postcode":"8800",
    "sg:province":"West-Vlaanderen",
    "wof:name":"Vrije Kleuterschool",
    "wof:placetype":"venue"
},
  "geometry": {"coordinates":[3.1081221104,50.9505386353],"type":"Point"}
}