{
  "type": "Feature",
  "properties": {
    "addr:full":"Rue Du Coll\u00c8ge 107 Elsene/ixelles Bruxelles-Capitale 1050",
    "addr:housenumber":"107",
    "addr:postcode":"1050",
    "addr:street":"Rue Du Colle\u0300Ge",
    "iso:country":"BE",
    "sg:address":"Rue Du Coll\u00c8ge 107",
    "sg:city":"Elsene/ixelles",
    "sg:orig_category":"Activit\u00e9s diverses d'imprimerie",
    "sg:phone":"+32 2 644 65 66",
    "sg:postcode":"1050",
    "sg:province":"Bruxelles-Capitale",
    "wof:name":"Bureau Nathan",
    "wof:placetype":"venue"
},
  "geometry": {"coordinates":[4.3719701767,50.8302154541],"type":"Point"}
}