{
  "type": "Feature",
  "properties": {
    "addr:full":"Rue Longchamps 7 Genappe Brabant Wallon 1470",
    "addr:housenumber":"7",
    "addr:postcode":"1470",
    "addr:street":"Rue Longchamps;Wallon",
    "iso:country":"BE",
    "sg:address":"Rue Longchamps 7",
    "sg:city":"Genappe",
    "sg:orig_category":"Entretien and r\u00e9parations de voitures",
    "sg:phone":"+32 67 77 20 65",
    "sg:postcode":"1470",
    "sg:province":"Brabant Wallon",
    "wof:name":"Ets Decra",
    "wof:placetype":"venue"
},
  "geometry": {"coordinates":[4.4669928551,50.5998649597],"type":"Point"}
}