{
  "type": "Feature",
  "properties": {
    "addr:full":"Quai De Rome 85b12 Li\u00c8ge Li\u00e8ge 4000",
    "addr:housenumber":"85b12",
    "addr:postcode":"4000",
    "addr:street":"Quai De Rome",
    "iso:country":"BE",
    "sg:address":"Quai De Rome 85b12",
    "sg:city":"Li\u00c8ge",
    "sg:orig_category":"Apotheken",
    "sg:phone":"+32 4 252 74 17",
    "sg:postcode":"4000",
    "sg:province":"Li\u00e8ge",
    "wof:name":"Laurette Evrard",
    "wof:placetype":"venue"
},
  "geometry": {"coordinates":[5.577914238,50.6197624207],"type":"Point"}
}