{
  "type": "Feature",
  "properties": {
    "iso:country":"BE",
    "sg:address":"Lindenstraat 16",
    "sg:city":"Keerbergen",
    "sg:classifiers":[
        {
            "category":"Home & Garden",
            "subcategory":"Home Furnishings",
            "type":"Retail Goods"
        }
    ],
    "sg:phone":"+32 15 51 62 75",
    "sg:postcode":"3140",
    "sg:province":"Vlaams-Brabant",
    "sg:tags":[
        "interior",
        "decoration"
    ],
    "wof:name":"Linea Keerbergen Bvba",
    "wof:placetype":"venue"
},
  "geometry": {"coordinates":[4.6342749596,51.0023002625],"type":"Point"}
}