{
  "type": "Feature",
  "properties": {
    "iso:country":"BE",
    "sg:address":"Rue G\u00c9n\u00c9ral Thys 37",
    "sg:city":"Dalhem",
    "sg:orig_category":"Loodgieterij, verwarming and sanitaire installaties",
    "sg:phone":"+32 4 374 17 75",
    "sg:postcode":"4607",
    "sg:province":"Li\u00e8ge",
    "wof:name":"Marc Goessens",
    "wof:placetype":"venue"
},
  "geometry": {"coordinates":[5.7248439789,50.7120819092],"type":"Point"}
}