{
  "type": "Feature",
  "properties": {
    "addr:full":"Elstrekenweg 80 Zonhoven Limburg 3520",
    "addr:housenumber":"80",
    "addr:postcode":"3520",
    "addr:street":"Elstrekenweg",
    "iso:country":"BE",
    "sg:address":"Elstrekenweg 80",
    "sg:city":"Zonhoven",
    "sg:classifiers":[
        {
            "category":"Personal",
            "subcategory":"Beauty Salon",
            "type":"Services"
        }
    ],
    "sg:phone":"+32 11 81 47 29",
    "sg:postcode":"3520",
    "sg:province":"Limburg",
    "sg:tags":[
        "lady",
        "-",
        "hairdressing"
    ],
    "wof:name":"Liliann",
    "wof:placetype":"venue"
},
  "geometry": {"coordinates":[5.4094219208,50.9792366028],"type":"Point"}
}