{
  "type": "Feature",
  "properties": {
    "iso:country":"BE",
    "sg:address":"Gen.dos. De St.georgesln 47",
    "sg:city":"Elsene/ixelles",
    "sg:orig_category":"Advocaten and juridische adviseurs",
    "sg:phone":"+32 2 648 34 47",
    "sg:postcode":"1050",
    "sg:province":"Bruxelles-Capitale",
    "wof:name":"N. Voskressensky",
    "wof:placetype":"venue"
},
  "geometry": {"coordinates":[4.3879160881,50.8097305298],"type":"Point"}
}