{
  "type": "Feature",
  "properties": {
    "iso:country":"BE",
    "sg:address":"Revinzestraat 68",
    "sg:city":"Torhout",
    "sg:classifiers":[
        {
            "category":"Shopping",
            "type":"Retail Goods"
        }
    ],
    "sg:phone":"+32 50 21 32 15",
    "sg:postcode":"8820",
    "sg:province":"West-Vlaanderen",
    "sg:tags":[
        "product",
        "cleaning",
        "maintenance"
    ],
    "wof:name":"Huyghe C",
    "wof:placetype":"venue"
},
  "geometry": {"coordinates":[3.0819330215,51.0666122437],"type":"Point"}
}