{
  "type": "Feature",
  "properties": {
    "addr:full":"Rue Du Temple 25 Fleurus Hainaut 6220",
    "addr:housenumber":"25",
    "addr:postcode":"6220",
    "addr:street":"Rue Du Temple",
    "iso:country":"BE",
    "sg:address":"Rue Du Temple 25",
    "sg:city":"Fleurus",
    "sg:orig_category":"Imprimeries and copyshops",
    "sg:phone":"+32 71 81 40 53",
    "sg:postcode":"6220",
    "sg:province":"Hainaut",
    "wof:name":"Yves Robert",
    "wof:placetype":"venue"
},
  "geometry": {"coordinates":[4.5496749878,50.4825363159],"type":"Point"}
}