{
  "type": "Feature",
  "properties": {
    "addr:full":"Victor Servranckxstraat 8 Zemst Vlaams-Brabant 1982",
    "addr:housenumber":"8",
    "addr:postcode":"1982",
    "addr:street":"Victor Servranckxstraat;Vlaams-Brabant",
    "iso:country":"BE",
    "sg:address":"Victor Servranckxstraat 8",
    "sg:city":"Zemst",
    "sg:orig_category":"M\u00e9decins and sp\u00e9cialistes",
    "sg:phone":"+32 15 61 13 20",
    "sg:postcode":"1982",
    "sg:province":"Vlaams-Brabant",
    "wof:name":"F. Verheyden",
    "wof:placetype":"venue"
},
  "geometry": {"coordinates":[4.4991340637,50.9602165222],"type":"Point"}
}