{
  "type": "Feature",
  "properties": {
    "iso:country":"BE",
    "sg:address":"Binnensteenweg 182",
    "sg:city":"Boechout",
    "sg:classifiers":[
        {
            "category":"Wholesale",
            "subcategory":"Medical Equipment & Supplies",
            "type":"Manufacturing & Wholesale Goods"
        }
    ],
    "sg:phone":"+32 3 236 25 35",
    "sg:postcode":"2530",
    "sg:province":"Antwerpen",
    "sg:tags":[
        "instrument",
        "apparatus"
    ],
    "wof:name":"Ace",
    "wof:placetype":"venue"
},
  "geometry": {"coordinates":[4.4914097786,51.1665763855],"type":"Point"}
}