{
  "type": "Feature",
  "properties": {
    "iso:country":"BE",
    "sg:address":"Treurnietstraat 59",
    "sg:city":"Harelbeke (bavikhove)",
    "sg:classifiers":[
        {
            "category":"Government",
            "subcategory":"Fire Station",
            "type":"Public Place"
        }
    ],
    "sg:phone":"+32 56 70 21 25",
    "sg:postcode":"8531",
    "sg:province":"West-Vlaanderen",
    "sg:tags":[
        "detection",
        "installation",
        "material",
        "-"
    ],
    "wof:name":"De Moor",
    "wof:placetype":"venue"
},
  "geometry": {"coordinates":[3.3101670742,50.8860282898],"type":"Point"}
}