{
  "type": "Feature",
  "properties": {
    "iso:country":"BE",
    "sg:address":"Kapeldreef 62",
    "sg:city":"Leuven (heverlee)",
    "sg:classifiers":[
        {
            "category":"Social Services",
            "subcategory":"Job Training",
            "type":"Services"
        }
    ],
    "sg:phone":"+32 16 32 75 73",
    "sg:postcode":"3001",
    "sg:province":"Vlaams-Brabant",
    "sg:tags":[
        "personnel"
    ],
    "wof:name":"Europace",
    "wof:placetype":"venue"
},
  "geometry": {"coordinates":[4.6589579582,50.860004425],"type":"Point"}
}