{
  "type": "Feature",
  "properties": {
    "addr:full":"Lijsterlaan 1 Wingene West-Vlaanderen 8750",
    "addr:housenumber":"1",
    "addr:postcode":"8750",
    "addr:street":"Lijsterlaan",
    "iso:country":"BE",
    "sg:address":"Lijsterlaan 1",
    "sg:city":"Wingene",
    "sg:orig_category":"Non-Classified Establishments",
    "sg:phone":"+32 51 65 81 15",
    "sg:postcode":"8750",
    "sg:province":"West-Vlaanderen",
    "wof:name":"Fegema",
    "wof:placetype":"venue"
},
  "geometry": {"coordinates":[3.2656550407,51.0524406433],"type":"Point"}
}