{
  "type": "Feature",
  "properties": {
    "addr:full":"Rue De Tohogne 10 Hamoir Li\u00e8ge 4180",
    "addr:housenumber":"10",
    "addr:postcode":"4180",
    "addr:street":"Rue De Tohogne",
    "iso:country":"BE",
    "sg:address":"Rue De Tohogne 10",
    "sg:city":"Hamoir",
    "sg:orig_category":"Protection civile",
    "sg:phone":"+32 86 38 82 67",
    "sg:postcode":"4180",
    "sg:province":"Li\u00e8ge",
    "wof:name":"Corps De Pompiers",
    "wof:placetype":"venue"
},
  "geometry": {"coordinates":[5.5293102264,50.4255943298],"type":"Point"}
}