{
  "type": "Feature",
  "properties": {
    "iso:country":"BE",
    "sg:address":"Doornveld 1b21",
    "sg:city":"Zellik",
    "sg:classifiers":[
        {
            "category":"Manufacturing",
            "subcategory":"Printing",
            "type":"Manufacturing & Wholesale Goods"
        }
    ],
    "sg:phone":"+32 2 463 09 70",
    "sg:postcode":"1731",
    "sg:province":"Vlaams-Brabant",
    "sg:tags":[
        "system",
        "digital"
    ],
    "wof:name":"Prontophot Belgium Nv",
    "wof:placetype":"venue"
},
  "geometry": {"coordinates":[4.2581400871,50.8911552429],"type":"Point"}
}