{
  "type": "Feature",
  "properties": {
    "addr:full":"Chemin Des Pr\u00e9elles 14 Mons Hainaut 7000",
    "addr:housenumber":"14",
    "addr:postcode":"7000",
    "addr:street":"Chemin Des Pre\u0301Elles;Hainaut",
    "iso:country":"BE",
    "sg:address":"Chemin Des Pr\u00e9elles 14",
    "sg:city":"Mons",
    "sg:classifiers":[
        {
            "category":"Real Estate",
            "subcategory":"Surveying",
            "type":"Services"
        }
    ],
    "sg:phone":"+32 65 84 18 92",
    "sg:postcode":"7000",
    "sg:province":"Hainaut",
    "sg:tags":[
        "surveyor",
        "land"
    ],
    "wof:name":"Bouquelle D",
    "wof:placetype":"venue"
},
  "geometry": {"coordinates":[3.9637179375,50.4502258301],"type":"Point"}
}