{
  "type": "Feature",
  "properties": {
    "addr:full":"Rue De La Bruyere 34 Braine-l`alleud Brabant Wallon 1420",
    "addr:housenumber":"34",
    "addr:postcode":"1420",
    "addr:street":"Rue De La Bruyere;Brabant Wallon",
    "iso:country":"BE",
    "sg:address":"Rue De La Bruyere 34",
    "sg:city":"Braine-l`alleud",
    "sg:orig_category":"Imprimeries and copyshops",
    "sg:phone":"+32 2 384 95 31",
    "sg:postcode":"1420",
    "sg:province":"Brabant Wallon",
    "wof:name":"Business And Development",
    "wof:placetype":"venue"
},
  "geometry": {"coordinates":[4.3276748657,50.728717804],"type":"Point"}
}