{
  "type": "Feature",
  "properties": {
    "iso:country":"BE",
    "sg:address":"Sint-niklaasstraat 136",
    "sg:city":"Sint-gillis-waas",
    "sg:orig_category":"Enseignement maternel and primaire",
    "sg:phone":"+32 3 770 51 08",
    "sg:postcode":"9170",
    "sg:province":"Oost-Vlaanderen",
    "wof:name":"Vrije Basisschool",
    "wof:placetype":"venue"
},
  "geometry": {"coordinates":[4.1446270943,51.2069587708],"type":"Point"}
}