{
  "type": "Feature",
  "properties": {
    "addr:full":"Rue Neuve 64 Eupen Li\u00e8ge 4700",
    "addr:housenumber":"64",
    "addr:postcode":"4700",
    "addr:street":"Rue Neuve",
    "iso:country":"BE",
    "sg:address":"Rue Neuve 64",
    "sg:city":"Eupen",
    "sg:orig_category":"Secr\u00e9tariats sociaux",
    "sg:phone":"+32 87 55 34 19",
    "sg:postcode":"4700",
    "sg:province":"Li\u00e8ge",
    "wof:name":"Ucm",
    "wof:placetype":"venue"
},
  "geometry": {"coordinates":[6.0312280655,50.6259384155],"type":"Point"}
}