{
  "type": "Feature",
  "properties": {
    "iso:country":"BE",
    "sg:address":"Houtvensesteenweg 48",
    "sg:city":"Herselt (ramsel)",
    "sg:classifiers":[
        {
            "category":"Professional",
            "subcategory":"Accounting & Tax Preparation",
            "type":"Services"
        }
    ],
    "sg:phone":"+32 16 69 74 96",
    "sg:postcode":"2230",
    "sg:province":"Antwerpen",
    "sg:tags":[
        "bookkeeper"
    ],
    "wof:name":"Fiscomad Bvba",
    "wof:placetype":"venue"
},
  "geometry": {"coordinates":[4.8169617653,51.0348701477],"type":"Point"}
}