{
  "type": "Feature",
  "properties": {
    "iso:country":"BE",
    "sg:address":"Vaux-lez-ch\u00cane 6",
    "sg:city":"Leglise",
    "sg:orig_category":"Eleveurs de bovins",
    "sg:phone":"+32 61 25 55 36",
    "sg:postcode":"6860",
    "sg:province":"Luxembourg",
    "wof:name":"Jacqmin Andre & Gilbert",
    "wof:placetype":"venue"
},
  "geometry": {"coordinates":[5.5349779129,49.7996826172],"type":"Point"}
}