{
  "type": "Feature",
  "properties": {
    "addr:full":"Lichterveldestraat 34 Kortemark West-Vlaanderen 8610",
    "addr:housenumber":"34",
    "addr:postcode":"8610",
    "addr:street":"Lichterveldestraat",
    "iso:country":"BE",
    "sg:address":"Lichterveldestraat 34",
    "sg:city":"Kortemark",
    "sg:orig_category":"Artsen and specialisten",
    "sg:phone":"+32 51 56 91 51",
    "sg:postcode":"8610",
    "sg:province":"West-Vlaanderen",
    "wof:name":"Johan Crevits",
    "wof:placetype":"venue"
},
  "geometry": {"coordinates":[3.0491011143,51.0282936096],"type":"Point"}
}