{
  "type": "Feature",
  "properties": {
    "addr:full":"Coupure 22 Brugge West-Vlaanderen 8000",
    "addr:housenumber":"22",
    "addr:postcode":"8000",
    "addr:street":"Coupure",
    "iso:country":"BE",
    "sg:address":"Coupure 22",
    "sg:city":"Brugge",
    "sg:orig_category":"Pensions de famille",
    "sg:phone":"+32 50 33 55 69",
    "sg:postcode":"8000",
    "sg:province":"West-Vlaanderen",
    "wof:name":"Van Ermengem",
    "wof:placetype":"venue"
},
  "geometry": {"coordinates":[3.2336239815,51.2075843811],"type":"Point"}
}