{
  "type": "Feature",
  "properties": {
    "iso:country":"BE",
    "sg:address":"Directoirelaan 52",
    "sg:city":"Ukkel/uccle",
    "sg:orig_category":"Medische apparatuur, orthopedische artikelen and prothesen Fab",
    "sg:phone":"+32 2 375 19 54",
    "sg:postcode":"1180",
    "sg:province":"Bruxelles-Capitale",
    "wof:name":"Christian Dosogne",
    "wof:placetype":"venue"
},
  "geometry": {"coordinates":[4.36186409,50.7869949341],"type":"Point"}
}