{
  "type": "Feature",
  "properties": {
    "addr:full":"Koningin Astridplein 6 Lebbeke Oost-Vlaanderen 9280",
    "addr:housenumber":"6",
    "addr:postcode":"9280",
    "addr:street":"Koningin Astridplein",
    "iso:country":"BE",
    "sg:address":"Koningin Astridplein 6",
    "sg:city":"Lebbeke",
    "sg:orig_category":"M\u00e9decins and sp\u00e9cialistes",
    "sg:phone":"+32 52 41 45 25",
    "sg:postcode":"9280",
    "sg:province":"Oost-Vlaanderen",
    "wof:name":"Consultatiebur.jonge Kind",
    "wof:placetype":"venue"
},
  "geometry": {"coordinates":[4.1331801414,51.0004615784],"type":"Point"}
}