{
  "type": "Feature",
  "properties": {
    "iso:country":"BE",
    "sg:address":"Torendreef 15",
    "sg:city":"Westerlo",
    "sg:orig_category":"Rundveehouders",
    "sg:phone":"+32 14 54 52 34",
    "sg:postcode":"2260",
    "sg:province":"Antwerpen",
    "wof:name":"Jozef Van Den Eynde",
    "wof:placetype":"venue"
},
  "geometry": {"coordinates":[4.8882899284,51.1114654541],"type":"Point"}
}