{
  "type": "Feature",
  "properties": {
    "addr:full":"Liersesteenweg 43 Begijnendijk Vlaams-Brabant 3130",
    "addr:housenumber":"43",
    "addr:postcode":"3130",
    "addr:street":"Liersesteenweg",
    "iso:country":"BE",
    "sg:address":"Liersesteenweg 43",
    "sg:city":"Begijnendijk",
    "sg:orig_category":"Dakwerken Gespecialiseerde residenti\u00eble bouw",
    "sg:phone":"+32 16 53 25 16",
    "sg:postcode":"3130",
    "sg:province":"Vlaams-Brabant",
    "wof:name":"Aquahalt",
    "wof:placetype":"venue"
},
  "geometry": {"coordinates":[4.773900032,51.0299873352],"type":"Point"}
}