{
  "type": "Feature",
  "properties": {
    "addr:full":"Ren\u00e9 Gombertstraat 26 Menen West-Vlaanderen 8930",
    "addr:housenumber":"26",
    "addr:postcode":"8930",
    "addr:street":"Rene\u0301 Gombertstraat",
    "iso:country":"BE",
    "sg:address":"Ren\u00e9 Gombertstraat 26",
    "sg:city":"Menen",
    "sg:orig_category":"Non-Classified Establishments",
    "sg:phone":"+32 56 51 35 08",
    "sg:postcode":"8930",
    "sg:province":"West-Vlaanderen",
    "wof:name":"Verschatse E",
    "wof:placetype":"venue"
},
  "geometry": {"coordinates":[3.1181139946,50.798664093],"type":"Point"}
}