{
  "type": "Feature",
  "properties": {
    "addr:full":"Kerkstraat 51 Lommel Limburg 3920",
    "addr:housenumber":"51",
    "addr:postcode":"3920",
    "addr:street":"Kerkstraat",
    "iso:country":"BE",
    "sg:address":"Kerkstraat 51",
    "sg:city":"Lommel",
    "sg:classifiers":[
        {
            "category":"Restaurant",
            "type":"Food & Drink"
        }
    ],
    "sg:phone":"+32 11 55 18 21",
    "sg:postcode":"3920",
    "sg:province":"Limburg",
    "wof:name":"Restaurant Op \u00b4t Hoekske",
    "wof:placetype":"venue"
},
  "geometry": {"coordinates":[5.3128328323,51.2294425964],"type":"Point"}
}