{
  "type": "Feature",
  "properties": {
    "addr:full":"Braemstraat 161 Gent Oost-Vlaanderen 9050",
    "addr:housenumber":"161",
    "addr:postcode":"9050",
    "addr:street":"Braemstraat;Oost-Vlaanderen",
    "iso:country":"BE",
    "sg:address":"Braemstraat 161",
    "sg:city":"Gent",
    "sg:orig_category":"M\u00e9decins and sp\u00e9cialistes",
    "sg:phone":"+32 9 230 13 33",
    "sg:postcode":"9050",
    "sg:province":"Oost-Vlaanderen",
    "wof:name":"L. Verlinden",
    "wof:placetype":"venue"
},
  "geometry": {"coordinates":[3.7638700008,51.0354347229],"type":"Point"}
}