{
  "type": "Feature",
  "properties": {
    "addr:full":"Lodewijk De Meesterstraat 110 Sint-niklaas Oost-Vlaanderen 9100",
    "addr:housenumber":"110",
    "addr:postcode":"9100",
    "addr:street":"Lodewijk De Meesterstraat",
    "iso:country":"BE",
    "sg:address":"Lodewijk De Meesterstraat 110",
    "sg:city":"Sint-niklaas",
    "sg:classifiers":[
        {
            "category":"Shopping",
            "subcategory":"Gifts & Souvenirs",
            "type":"Retail Goods"
        }
    ],
    "sg:phone":"+32 3 778 19 44",
    "sg:postcode":"9100",
    "sg:province":"Oost-Vlaanderen",
    "sg:tags":[
        "-"
    ],
    "wof:name":"Nina",
    "wof:placetype":"venue"
},
  "geometry": {"coordinates":[4.1531648636,51.1640090942],"type":"Point"}
}