{
  "type": "Feature",
  "properties": {
    "addr:full":"Rode Kruislaan 26 Malle (westmalle) Antwerpen 2390",
    "addr:housenumber":"26",
    "addr:postcode":"2390",
    "addr:street":"Rode Kruislaan",
    "iso:country":"BE",
    "sg:address":"Rode Kruislaan 26",
    "sg:city":"Malle (westmalle)",
    "sg:classifiers":[
        {
            "category":"Health Services",
            "subcategory":"Doctor",
            "type":"Services"
        }
    ],
    "sg:phone":"+32 3 311 50 40",
    "sg:postcode":"2390",
    "sg:province":"Antwerpen",
    "sg:tags":[
        "medicinephysicians",
        "surgeon"
    ],
    "wof:name":"Ceulemans B",
    "wof:placetype":"venue"
},
  "geometry": {"coordinates":[4.666408062,51.2777061462],"type":"Point"}
}