{
  "type": "Feature",
  "properties": {
    "iso:country":"BE",
    "sg:address":"Bosstraat 48",
    "sg:city":"Hamont-achel",
    "sg:orig_category":"Erotische Etablissementen",
    "sg:phone":"+32 11 62 17 39",
    "sg:postcode":"3930",
    "sg:province":"Limburg",
    "wof:name":"Jean De Boel",
    "wof:placetype":"venue"
},
  "geometry": {"coordinates":[5.5450549126,51.2511863708],"type":"Point"}
}