{
  "type": "Feature",
  "properties": {
    "iso:country":"BE",
    "sg:address":"Kapellestraat 125",
    "sg:city":"Wetteren",
    "sg:classifiers":[
        {
            "category":"Retail",
            "subcategory":"Auto Repair",
            "type":"Services"
        }
    ],
    "sg:phone":"+32 9 369 14 16",
    "sg:postcode":"9230",
    "sg:province":"Oost-Vlaanderen",
    "sg:tags":[
        "automobile-body"
    ],
    "wof:name":"De Wilde Luc Bvba",
    "wof:placetype":"venue"
},
  "geometry": {"coordinates":[3.8916521072,51.0035057068],"type":"Point"}
}