{
  "type": "Feature",
  "properties": {
    "iso:country":"BE",
    "sg:address":"Grote Markt 62",
    "sg:city":"Lier",
    "sg:orig_category":"Alimentation sp\u00e9cialis\u00e9e",
    "sg:phone":"+32 3 480 09 65",
    "sg:postcode":"2500",
    "sg:province":"Antwerpen",
    "wof:name":"Huis Vereycken",
    "wof:placetype":"venue"
},
  "geometry": {"coordinates":[4.5705928802,51.130355835],"type":"Point"}
}