{
  "type": "Feature",
  "properties": {
    "addr:full":"Bremenhulweg 27 Lede Oost-Vlaanderen 9340",
    "addr:housenumber":"27",
    "addr:postcode":"9340",
    "addr:street":"Bremenhulweg",
    "iso:country":"BE",
    "sg:address":"Bremenhulweg 27",
    "sg:city":"Lede",
    "sg:classifiers":[
        {
            "category":"Health Services",
            "subcategory":"Health Practitioner",
            "type":"Services"
        }
    ],
    "sg:phone":"+32 53 80 66 93",
    "sg:postcode":"9340",
    "sg:province":"Oost-Vlaanderen",
    "sg:tags":[
        "psychologist"
    ],
    "wof:name":"De Brauw L",
    "wof:placetype":"venue"
},
  "geometry": {"coordinates":[3.9906299114,50.9697761536],"type":"Point"}
}