{
  "type": "Feature",
  "properties": {
    "iso:country":"BE",
    "sg:address":"Leuvense Steenweg 114",
    "sg:city":"Sint-joost-ten-node/saint-josse-ten-noode",
    "sg:orig_category":"Slagers",
    "sg:phone":"+32 2 230 58 16",
    "sg:postcode":"1210",
    "sg:province":"Bruxelles-Capitale",
    "wof:name":"Jean-louis Troye",
    "wof:placetype":"venue"
},
  "geometry": {"coordinates":[4.3752779961,50.8498153687],"type":"Point"}
}