{
  "type": "Feature",
  "properties": {
    "addr:full":"Oostmalsesteenweg 191 Rijkevorsel Antwerpen 2310",
    "addr:housenumber":"191",
    "addr:postcode":"2310",
    "addr:street":"Oostmalsesteenweg",
    "iso:country":"BE",
    "sg:address":"Oostmalsesteenweg 191",
    "sg:city":"Rijkevorsel",
    "sg:orig_category":"Juwelen and edelstenen Fab",
    "sg:phone":"+32 3 312 21 95",
    "sg:postcode":"2310",
    "sg:province":"Antwerpen",
    "wof:name":"Herwig Van Dooren",
    "wof:placetype":"venue"
},
  "geometry": {"coordinates":[4.7514090538,51.336517334],"type":"Point"}
}