{
  "type": "Feature",
  "properties": {
    "addr:full":"Nationalestraat 72 Antwerpen Antwerpen 2000",
    "addr:housenumber":"72",
    "addr:postcode":"2000",
    "addr:street":"Nationalestraat",
    "iso:country":"BE",
    "sg:address":"Nationalestraat 72",
    "sg:city":"Antwerpen",
    "sg:classifiers":[
        {
            "category":"Shopping",
            "subcategory":"Clothing, Apparel, & Fashions",
            "type":"Retail Goods"
        }
    ],
    "sg:phone":"+32 3 485 86 87",
    "sg:postcode":"2000",
    "sg:province":"Antwerpen",
    "sg:tags":[
        "lady",
        "clothing",
        "-"
    ],
    "wof:name":"Garde-robe Nationale",
    "wof:placetype":"venue"
},
  "geometry": {"coordinates":[4.3986368179,51.2155075073],"type":"Point"}
}