{
  "type": "Feature",
  "properties": {
    "iso:country":"BE",
    "sg:address":"Assenedesteenweg 66",
    "sg:city":"Zelzate",
    "sg:orig_category":"M\u00e9decins and sp\u00e9cialistes",
    "sg:phone":"+32 9 344 69 80",
    "sg:postcode":"9060",
    "sg:province":"Oost-Vlaanderen",
    "wof:name":"M. Calle",
    "wof:placetype":"venue"
},
  "geometry": {"coordinates":[3.7939600945,51.1978607178],"type":"Point"}
}