{
  "type": "Feature",
  "properties": {
    "iso:country":"BE",
    "sg:address":"Rue Des Fuchsias 38",
    "sg:city":"Brussel/bruxelles",
    "sg:orig_category":"M\u00e9decins and sp\u00e9cialistes",
    "sg:phone":"+32 2 414 61 57",
    "sg:postcode":"1080",
    "sg:province":"Bruxelles-Capitale",
    "wof:name":"Viseur",
    "wof:placetype":"venue"
},
  "geometry": {"coordinates":[4.3209028244,50.8608589172],"type":"Point"}
}