{
  "type": "Feature",
  "properties": {
    "addr:full":"Henri Vandermaelenstraat 72 Sint-pieters-woluwe/woluwe-saint-pierre Bruxelles-Capitale 1150",
    "addr:housenumber":"72",
    "addr:postcode":"1150",
    "addr:street":"Henri Vandermaelenstraat;/",
    "iso:country":"BE",
    "sg:address":"Henri Vandermaelenstraat 72",
    "sg:city":"Sint-pieters-woluwe/woluwe-saint-pierre",
    "sg:orig_category":"Immobili\u00ebnkantoren Landmeters and schatters",
    "sg:phone":"+32 2 779 88 05",
    "sg:postcode":"1150",
    "sg:province":"Bruxelles-Capitale",
    "wof:name":"Bureau Bestate",
    "wof:placetype":"venue"
},
  "geometry": {"coordinates":[4.4611711502,50.8424873352],"type":"Point"}
}