{
  "type": "Feature",
  "properties": {
    "addr:full":"Kwikstraat 56 Kortenberg (everberg) Vlaams-Brabant 3078",
    "addr:housenumber":"56",
    "addr:postcode":"3078",
    "addr:street":"Kwikstraat",
    "iso:country":"BE",
    "sg:address":"Kwikstraat 56",
    "sg:city":"Kortenberg (everberg)",
    "sg:classifiers":[
        {
            "category":"Home & Garden",
            "subcategory":"Kitchen Supply",
            "type":"Retail Goods"
        }
    ],
    "sg:phone":"+32 2 759 44 72",
    "sg:postcode":"3078",
    "sg:province":"Vlaams-Brabant",
    "sg:tags":[
        "installation"
    ],
    "wof:name":"Sommereyns",
    "wof:placetype":"venue"
},
  "geometry": {"coordinates":[4.5800437927,50.8773269653],"type":"Point"}
}