{
  "type": "Feature",
  "properties": {
    "addr:full":"Pallo 48 Geel Antwerpen 2440",
    "addr:housenumber":"48",
    "addr:postcode":"2440",
    "addr:street":"Pallo",
    "iso:country":"BE",
    "sg:address":"Pallo 48",
    "sg:city":"Geel",
    "sg:orig_category":"Gespecialiseerde niet-residenti\u00eble bouw",
    "sg:phone":"+32 14 72 31 85",
    "sg:postcode":"2440",
    "sg:province":"Antwerpen",
    "wof:name":"S'jegers M",
    "wof:placetype":"venue"
},
  "geometry": {"coordinates":[4.9918580055,51.1652908325],"type":"Point"}
}