{
  "type": "Feature",
  "properties": {
    "addr:full":"Rue Clarisse 2 Nivelles Brabant Wallon 1400",
    "addr:housenumber":"2",
    "addr:postcode":"1400",
    "addr:street":"Rue Clarisse",
    "iso:country":"BE",
    "sg:address":"Rue Clarisse 2",
    "sg:city":"Nivelles",
    "sg:orig_category":"Enseignement maternel and primaire",
    "sg:phone":"+32 67 21 23 88",
    "sg:postcode":"1400",
    "sg:province":"Brabant Wallon",
    "wof:name":"E.f.l. St.th\u00c9r\u00c8se",
    "wof:placetype":"venue"
},
  "geometry": {"coordinates":[4.336359024,50.5981445312],"type":"Point"}
}