{
  "type": "Feature",
  "properties": {
    "iso:country":"BE",
    "sg:address":"Binnenheide 30a",
    "sg:city":"Grobbendonk (bouwel)",
    "sg:classifiers":[
        {
            "category":"Professional",
            "subcategory":"Computer Services",
            "type":"Services"
        }
    ],
    "sg:phone":"+32 14 50 13 05",
    "sg:postcode":"2288",
    "sg:province":"Antwerpen",
    "sg:tags":[
        "-",
        "processing",
        "data",
        "software"
    ],
    "wof:name":"Software Product Research",
    "wof:placetype":"venue"
},
  "geometry": {"coordinates":[4.7235989571,51.1576080322],"type":"Point"}
}