{
  "type": "Feature",
  "properties": {
    "iso:country":"BE",
    "sg:address":"Pulsebaan 41",
    "sg:city":"Zandhoven (pulderbos)",
    "sg:classifiers":[
        {
            "category":"Building & Trades",
            "subcategory":"Pest Control",
            "type":"Services"
        }
    ],
    "sg:phone":"+32 3 466 00 50",
    "sg:postcode":"2242",
    "sg:province":"Antwerpen",
    "sg:tags":[
        "machine",
        "vending"
    ],
    "wof:name":"Antenor Automation Nv",
    "wof:placetype":"venue"
},
  "geometry": {"coordinates":[4.6939988136,51.2137832642],"type":"Point"}
}