{
  "type": "Feature",
  "properties": {
    "addr:full":"Schrovestraat 3 Lebbeke Oost-Vlaanderen 9280",
    "addr:housenumber":"3",
    "addr:postcode":"9280",
    "addr:street":"Schrovestraat",
    "iso:country":"BE",
    "sg:address":"Schrovestraat 3",
    "sg:city":"Lebbeke",
    "sg:orig_category":"Ordinateurs and \u00e9quipement informatique",
    "sg:phone":"+32 53 77 90 95",
    "sg:postcode":"9280",
    "sg:province":"Oost-Vlaanderen",
    "wof:name":"Info Navigator",
    "wof:placetype":"venue"
},
  "geometry": {"coordinates":[4.0801258087,50.9784851074],"type":"Point"}
}