{
  "type": "Feature",
  "properties": {
    "addr:full":"Kapelstraat 23 Sint-niklaas Oost-Vlaanderen 9100",
    "addr:housenumber":"23",
    "addr:postcode":"9100",
    "addr:street":"Kapelstraat",
    "iso:country":"BE",
    "sg:address":"Kapelstraat 23",
    "sg:city":"Sint-niklaas",
    "sg:orig_category":"Diensten voor huisdieren",
    "sg:phone":"+32 3 766 41 68",
    "sg:postcode":"9100",
    "sg:province":"Oost-Vlaanderen",
    "wof:name":"Canis",
    "wof:placetype":"venue"
},
  "geometry": {"coordinates":[4.1506910324,51.1494903564],"type":"Point"}
}