{
  "type": "Feature",
  "properties": {
    "iso:country":"BE",
    "sg:address":"Rue Des Trois Fr\u00e8res Servais 3",
    "sg:city":"Jemeppe-sur-sambre",
    "sg:classifiers":[
        {
            "category":"Arena",
            "subcategory":"Sports Club",
            "type":"Entertainment"
        }
    ],
    "sg:phone":"+32 71 78 65 37",
    "sg:postcode":"5190",
    "sg:province":"Namur",
    "wof:name":"Envol ('l)",
    "wof:placetype":"venue"
},
  "geometry": {"coordinates":[4.6611299515,50.4523086548],"type":"Point"}
}