{
  "type": "Feature",
  "properties": {
    "iso:country":"BE",
    "sg:address":"Rue De Nazareth 5",
    "sg:city":"Herve",
    "sg:classifiers":[
        {
            "category":"Building & Trades",
            "subcategory":"Construction",
            "type":"Services"
        }
    ],
    "sg:phone":"+32 4 343 44 37",
    "sg:postcode":"4650",
    "sg:province":"Li\u00e8ge",
    "sg:tags":[
        "installation",
        "air-conditioning",
        "system"
    ],
    "wof:name":"Vrancken S.p.r.l.",
    "wof:placetype":"venue"
},
  "geometry": {"coordinates":[5.5968441963,50.6220054626],"type":"Point"}
}