{
  "type": "Feature",
  "properties": {
    "addr:full":"Stationsstraat 112a Lebbeke Oost-Vlaanderen 9280",
    "addr:housenumber":"112a",
    "addr:postcode":"9280",
    "addr:street":"Stationsstraat",
    "iso:country":"BE",
    "sg:address":"Stationsstraat 112a",
    "sg:city":"Lebbeke",
    "sg:orig_category":"Electrom\u00e9nager, t\u00e9l\u00e9visions and radios. Eclairage et \u00e9quipements du foyer",
    "sg:phone":"+32 52 41 57 73",
    "sg:postcode":"9280",
    "sg:province":"Oost-Vlaanderen",
    "wof:name":"Hot Items",
    "wof:placetype":"venue"
},
  "geometry": {"coordinates":[4.1339578629,51.0053367615],"type":"Point"}
}