{
  "type": "Feature",
  "properties": {
    "iso:country":"BE",
    "sg:address":"Place Jean Lariguette 3",
    "sg:city":"Ottignies-louvain-la-neuve",
    "sg:orig_category":"M\u00e9decins and sp\u00e9cialistes",
    "sg:phone":"+32 10 45 06 28",
    "sg:postcode":"1348",
    "sg:province":"Brabant Wallon",
    "wof:name":"A. Poltoracky",
    "wof:placetype":"venue"
},
  "geometry": {"coordinates":[4.6130228043,50.6738510132],"type":"Point"}
}