{
  "type": "Feature",
  "properties": {
    "addr:full":"Lindekensbaan 87a Nijlen (kessel) Antwerpen 2560",
    "addr:housenumber":"87a",
    "addr:postcode":"2560",
    "addr:street":"Lindekensbaan",
    "iso:country":"BE",
    "sg:address":"Lindekensbaan 87a",
    "sg:city":"Nijlen (kessel)",
    "sg:classifiers":[
        {
            "category":"Insurance",
            "subcategory":"Insurance Agent",
            "type":"Services"
        }
    ],
    "sg:phone":"+32 3 480 22 77",
    "sg:postcode":"2560",
    "sg:province":"Antwerpen",
    "sg:tags":[
        "broker"
    ],
    "wof:name":"Vercammen Bvba",
    "wof:placetype":"venue"
},
  "geometry": {"coordinates":[4.6256070137,51.1549491882],"type":"Point"}
}