{
  "type": "Feature",
  "properties": {
    "addr:full":"Boterhoekstraat 8 Merelbeke (melsen) Oost-Vlaanderen 9820",
    "addr:housenumber":"8",
    "addr:postcode":"9820",
    "addr:street":"Boterhoekstraat",
    "iso:country":"BE",
    "sg:address":"Boterhoekstraat 8",
    "sg:city":"Merelbeke (melsen)",
    "sg:classifiers":[
        {
            "category":"Real Estate",
            "subcategory":"Architect",
            "type":"Services"
        }
    ],
    "sg:phone":"+32 9 384 32 08",
    "sg:postcode":"9820",
    "sg:province":"Oost-Vlaanderen",
    "wof:name":"De Keukelaere F",
    "wof:placetype":"venue"
},
  "geometry": {"coordinates":[3.6987669468,50.9587860107],"type":"Point"}
}