{
  "type": "Feature",
  "properties": {
    "addr:full":"Stationsstraat 35 Waasmunster Oost-Vlaanderen 9250",
    "addr:housenumber":"35",
    "addr:postcode":"9250",
    "addr:street":"Stationsstraat",
    "iso:country":"BE",
    "sg:address":"Stationsstraat 35",
    "sg:city":"Waasmunster",
    "sg:orig_category":"Plaatsen van vloer- and muurbekleding Schilders",
    "sg:phone":"+32 52 46 23 39",
    "sg:postcode":"9250",
    "sg:province":"Oost-Vlaanderen",
    "wof:name":"Leon Wauters",
    "wof:placetype":"venue"
},
  "geometry": {"coordinates":[4.0958662033,51.1132049561],"type":"Point"}
}