{
  "type": "Feature",
  "properties": {
    "addr:full":"Kerkstraat 28b Lommel Limburg 3920",
    "addr:housenumber":"28b",
    "addr:postcode":"3920",
    "addr:street":"Kerkstraat",
    "iso:country":"BE",
    "sg:address":"Kerkstraat 28b",
    "sg:city":"Lommel",
    "sg:orig_category":"Imitation jewelry - Mfg.& Whol.",
    "sg:phone":"+32 11 55 25 04",
    "sg:postcode":"3920",
    "sg:province":"Limburg",
    "wof:name":"Follies Bvba",
    "wof:placetype":"venue"
},
  "geometry": {"coordinates":[5.3112688065,51.2298812866],"type":"Point"}
}