{
  "type": "Feature",
  "properties": {
    "addr:full":"Bankelindeweg 60 Poperinge West-Vlaanderen 8972",
    "addr:housenumber":"60",
    "addr:postcode":"8972",
    "addr:street":"Bankelindeweg",
    "iso:country":"BE",
    "sg:address":"Bankelindeweg 60",
    "sg:city":"Poperinge",
    "sg:orig_category":"Mat\u00e9riaux de construction Gr",
    "sg:phone":"+32 57 33 83 28",
    "sg:postcode":"8972",
    "sg:province":"West-Vlaanderen",
    "wof:name":"Trap-division Import",
    "wof:placetype":"venue"
},
  "geometry": {"coordinates":[2.6944639683,50.8983306885],"type":"Point"}
}