{
  "type": "Feature",
  "properties": {
    "iso:country":"BE",
    "sg:address":"Chauss\u00e9e De Saint-job 267",
    "sg:city":"Bruxelles (uccle)",
    "sg:classifiers":[
        {
            "category":"Building & Trades",
            "subcategory":"Cleaning & Sanitation",
            "type":"Services"
        }
    ],
    "sg:phone":"+32 2 375 46 06",
    "sg:postcode":"1180",
    "sg:province":"Bruxelles-Capitale",
    "sg:tags":[
        "sweep",
        "chimney"
    ],
    "wof:name":"Desmet J-c",
    "wof:placetype":"venue"
},
  "geometry": {"coordinates":[4.3429121971,50.7914581299],"type":"Point"}
}