{
  "type": "Feature",
  "properties": {
    "iso:country":"BE",
    "sg:address":"Baron R. De Vironlaan 17",
    "sg:city":"Dilbeek",
    "sg:orig_category":"Studios photographiques",
    "sg:phone":"+32 2 532 49 83",
    "sg:postcode":"1700",
    "sg:province":"Vlaams-Brabant",
    "wof:name":"V.c.t.",
    "wof:placetype":"venue"
},
  "geometry": {"coordinates":[4.2665901184,50.8475456238],"type":"Point"}
}