{
  "type": "Feature",
  "properties": {
    "addr:full":"Cornelstraat 34 Bilzen Limburg 3740",
    "addr:housenumber":"34",
    "addr:postcode":"3740",
    "addr:street":"Cornelstraat",
    "iso:country":"BE",
    "sg:address":"Cornelstraat 34",
    "sg:city":"Bilzen",
    "sg:orig_category":"Plantes and fleurs Producteurs de l\u00e9gumes",
    "sg:phone":"+32 89 41 16 60",
    "sg:postcode":"3740",
    "sg:province":"Limburg",
    "wof:name":"Hubert Hansen",
    "wof:placetype":"venue"
},
  "geometry": {"coordinates":[5.5327920914,50.8870887756],"type":"Point"}
}