{
  "type": "Feature",
  "properties": {
    "addr:full":"Brusselsesteenweg 87 Tervuren Vlaams-Brabant 3080",
    "addr:housenumber":"87",
    "addr:postcode":"3080",
    "addr:street":"Brusselsesteenweg",
    "iso:country":"BE",
    "sg:address":"Brusselsesteenweg 87",
    "sg:city":"Tervuren",
    "sg:orig_category":"Fotografen and fotostudio's",
    "sg:phone":"+32 2 767 51 55",
    "sg:postcode":"3080",
    "sg:province":"Vlaams-Brabant",
    "wof:name":"Elisa Derveaux",
    "wof:placetype":"venue"
},
  "geometry": {"coordinates":[4.5071310997,50.82396698],"type":"Point"}
}