{
  "type": "Feature",
  "properties": {
    "addr:full":"Avenue Du Pesage 122 Bruxelles (ixelles) Bruxelles-Capitale 1050",
    "addr:housenumber":"122",
    "addr:postcode":"1050",
    "addr:street":"Avenue Du Pesage",
    "iso:country":"BE",
    "sg:address":"Avenue Du Pesage 122",
    "sg:city":"Bruxelles (ixelles)",
    "sg:classifiers":[
        {
            "category":"Health Services",
            "subcategory":"Health Practitioner",
            "type":"Services"
        }
    ],
    "sg:phone":"+32 2 640 65 69",
    "sg:postcode":"1050",
    "sg:province":"Bruxelles-Capitale",
    "sg:tags":[
        "physiotherapist"
    ],
    "wof:name":"Dumont Isabelle",
    "wof:placetype":"venue"
},
  "geometry": {"coordinates":[4.3877477646,50.8072967529],"type":"Point"}
}