{
  "type": "Feature",
  "properties": {
    "addr:full":"Diksmuidestraat 37 Houthulst West-Vlaanderen 8650",
    "addr:housenumber":"37",
    "addr:postcode":"8650",
    "addr:street":"Diksmuidestraat",
    "iso:country":"BE",
    "sg:address":"Diksmuidestraat 37",
    "sg:city":"Houthulst",
    "sg:orig_category":"Peinture. Rev\u00eatements pour sols and murs. Rev\u00eatements de sols and murs",
    "sg:phone":"+32 51 54 55 85",
    "sg:postcode":"8650",
    "sg:province":"West-Vlaanderen",
    "wof:name":"Alain Loncke",
    "wof:placetype":"venue"
},
  "geometry": {"coordinates":[2.9509439468,50.9778862],"type":"Point"}
}