{
  "type": "Feature",
  "properties": {
    "iso:country":"BE",
    "sg:address":"Rue Allard 1",
    "sg:city":"Schaarbeek/schaerbeek",
    "sg:classifiers":[
        {
            "category":"Fast Food",
            "type":"Food & Drink"
        }
    ],
    "sg:phone":"+32 2 219 01 17",
    "sg:postcode":"1030",
    "sg:province":"Bruxelles-Capitale",
    "sg:tags":[
        "\u00c0",
        "emporter",
        "restaurants"
    ],
    "wof:name":"La Frite D'or",
    "wof:placetype":"venue"
},
  "geometry": {"coordinates":[4.3623290062,50.8597373962],"type":"Point"}
}