{
  "type": "Feature",
  "properties": {
    "addr:full":"Engelse Wandeling 2k Kortrijk West-Vlaanderen 8500",
    "addr:housenumber":"2k",
    "addr:postcode":"8500",
    "addr:street":"Engelse Wandeling",
    "iso:country":"BE",
    "sg:address":"Engelse Wandeling 2k",
    "sg:city":"Kortrijk",
    "sg:orig_category":"Editeurs de revues and p\u00e9riodiques. Editeurs de journaux",
    "sg:phone":"+32 56 25 28 68",
    "sg:postcode":"8500",
    "sg:province":"West-Vlaanderen",
    "wof:name":"Spots",
    "wof:placetype":"venue"
},
  "geometry": {"coordinates":[3.2476019859,50.8158874512],"type":"Point"}
}