{
  "type": "Feature",
  "properties": {
    "iso:country":"BE",
    "sg:address":"Merelstraat 9",
    "sg:city":"Mol",
    "sg:orig_category":"Mat\u00e9riel pour plomberie and chauffage Electrom\u00e9nager, t\u00e9l\u00e9visions and radios. Installation \u00e9lectriqu",
    "sg:phone":"+32 14 32 15 77",
    "sg:postcode":"2400",
    "sg:province":"Antwerpen",
    "wof:name":"Airplus Medibo",
    "wof:placetype":"venue"
},
  "geometry": {"coordinates":[5.0729799271,51.1834983826],"type":"Point"}
}