{
  "type": "Feature",
  "properties": {
    "addr:full":"Voorstraat 32 Kaprijke Oost-Vlaanderen 9970",
    "addr:housenumber":"32",
    "addr:postcode":"9970",
    "addr:street":"Voorstraat",
    "iso:country":"BE",
    "sg:address":"Voorstraat 32",
    "sg:city":"Kaprijke",
    "sg:orig_category":"Enseignement maternel and primaire",
    "sg:phone":"+32 9 373 73 81",
    "sg:postcode":"9970",
    "sg:province":"Oost-Vlaanderen",
    "wof:name":"Vrije Lagere School",
    "wof:placetype":"venue"
},
  "geometry": {"coordinates":[3.6131100655,51.2181282043],"type":"Point"}
}