{
  "type": "Feature",
  "properties": {
    "iso:country":"BE",
    "sg:address":"Rue De La Sauveni\u00e8re 4",
    "sg:city":"Fernelmont (franc-waret)",
    "sg:classifiers":[
        {
            "category":"Retail",
            "subcategory":"Repair Shop",
            "type":"Services"
        }
    ],
    "sg:phone":"+32 81 83 35 58",
    "sg:postcode":"5380",
    "sg:province":"Namur",
    "sg:tags":[
        "-",
        "mainten",
        "watch",
        "clock"
    ],
    "wof:name":"Thonus J",
    "wof:placetype":"venue"
},
  "geometry": {"coordinates":[4.974588871,50.5179519653],"type":"Point"}
}