{
  "type": "Feature",
  "properties": {
    "addr:full":"Chauss\u00e9e De Louvain 47 Box 1 Waterloo Brabant Wallon 1410",
    "addr:housenumber":"47;1",
    "addr:postcode":"1410",
    "addr:street":"Chausse\u0301E De Louvain;Box",
    "iso:country":"BE",
    "sg:address":"Chauss\u00e9e De Louvain 47 Box 1",
    "sg:city":"Waterloo",
    "sg:classifiers":[
        {
            "category":"Professional",
            "subcategory":"Employment Agencies",
            "type":"Services"
        }
    ],
    "sg:phone":"+32 2 389 00 89",
    "sg:postcode":"1410",
    "sg:province":"Brabant Wallon",
    "sg:tags":[
        "market",
        "research"
    ],
    "wof:name":"Icma International Nv",
    "wof:placetype":"venue"
},
  "geometry": {"coordinates":[4.4109802246,50.6911773682],"type":"Point"}
}