{
  "type": "Feature",
  "properties": {
    "addr:full":"Trumelet Faberstraat 2 Koksijde (oostduinkerke) West-Vlaanderen 8670",
    "addr:housenumber":"2",
    "addr:postcode":"8670",
    "addr:street":"Faberstraat",
    "iso:country":"BE",
    "sg:address":"Trumelet Faberstraat 2",
    "sg:city":"Koksijde (oostduinkerke)",
    "sg:classifiers":[
        {
            "category":"Personal",
            "subcategory":"Barber",
            "type":"Services"
        }
    ],
    "sg:phone":"+32 58 51 38 22",
    "sg:postcode":"8670",
    "sg:province":"West-Vlaanderen",
    "sg:tags":[
        "gentleman",
        "salon",
        "-",
        "hairdressing"
    ],
    "wof:name":"Roger",
    "wof:placetype":"venue"
},
  "geometry": {"coordinates":[2.6700179577,51.1317710876],"type":"Point"}
}