{
  "type": "Feature",
  "properties": {
    "iso:country":"BE",
    "sg:address":"Dooistraat 74a",
    "sg:city":"Diepenbeek",
    "sg:classifiers":[
        {
            "category":"Shopping",
            "subcategory":"Florist",
            "type":"Retail Goods"
        }
    ],
    "sg:phone":"+32 11 32 27 84",
    "sg:postcode":"3590",
    "sg:province":"Limburg",
    "wof:name":"Knuts Bloemenkwekerij",
    "wof:placetype":"venue"
},
  "geometry": {"coordinates":[5.4196062088,50.8989753723],"type":"Point"}
}