{
  "type": "Feature",
  "properties": {
    "addr:full":"Toekomststraat 58 Hasselt Limburg 3500",
    "addr:housenumber":"58",
    "addr:postcode":"3500",
    "addr:street":"Toekomststraat",
    "iso:country":"BE",
    "sg:address":"Toekomststraat 58",
    "sg:city":"Hasselt",
    "sg:classifiers":[
        {
            "category":"Arts & Performance",
            "subcategory":"Art Gallery",
            "type":"Entertainment"
        }
    ],
    "sg:phone":"+32 11 72 90 20",
    "sg:postcode":"3500",
    "sg:province":"Limburg",
    "wof:name":"Galerie Ammoniet",
    "wof:placetype":"venue"
},
  "geometry": {"coordinates":[5.3389029503,50.9245262146],"type":"Point"}
}