{
  "type": "Feature",
  "properties": {
    "iso:country":"BE",
    "sg:address":"Kleine Molenweg 211",
    "sg:city":"Stabroek",
    "sg:orig_category":"Begrafeniswezen",
    "sg:phone":"+32 3 568 77 97",
    "sg:postcode":"2940",
    "sg:province":"Antwerpen",
    "wof:name":"Begrafenissen Holemans",
    "wof:placetype":"venue"
},
  "geometry": {"coordinates":[4.3739299774,51.3257675171],"type":"Point"}
}