{
  "type": "Feature",
  "properties": {
    "addr:full":"Grand'rue 97 Charleroi Hainaut 6061",
    "addr:housenumber":"97",
    "addr:postcode":"6061",
    "addr:street":"Grand'Rue;Hainaut",
    "iso:country":"BE",
    "sg:address":"Grand'rue 97",
    "sg:city":"Charleroi",
    "sg:classifiers":[
        {
            "category":"Food & Beverages",
            "subcategory":"Fruits & Vegetables",
            "type":"Retail Goods"
        }
    ],
    "sg:phone":"+32 71 41 02 26",
    "sg:postcode":"6061",
    "sg:province":"Hainaut",
    "sg:tags":[
        "groenten"
    ],
    "wof:name":"F.t.l.",
    "wof:placetype":"venue"
},
  "geometry": {"coordinates":[4.459209919,50.4121246338],"type":"Point"}
}