{
  "type": "Feature",
  "properties": {
    "addr:full":"Dendeldonk 8 Wetteren Oost-Vlaanderen 9230",
    "addr:housenumber":"8",
    "addr:postcode":"9230",
    "addr:street":"Dendeldonk",
    "iso:country":"BE",
    "sg:address":"Dendeldonk 8",
    "sg:city":"Wetteren",
    "sg:classifiers":[
        {
            "category":"Professional",
            "subcategory":"Management & Consulting",
            "type":"Services"
        }
    ],
    "sg:phone":"+32 9 365 04 63",
    "sg:postcode":"9230",
    "sg:province":"Oost-Vlaanderen",
    "sg:tags":[
        "consultant"
    ],
    "wof:name":"Schotte J",
    "wof:placetype":"venue"
},
  "geometry": {"coordinates":[3.8773999214,51.018699646],"type":"Point"}
}