{
  "type": "Feature",
  "properties": {
    "addr:full":"Luiseekdam 7 Temse Oost-Vlaanderen 9140",
    "addr:housenumber":"7",
    "addr:postcode":"9140",
    "addr:street":"Luiseekdam",
    "iso:country":"BE",
    "sg:address":"Luiseekdam 7",
    "sg:city":"Temse",
    "sg:classifiers":[
        {
            "category":"Banks & Credit Unions",
            "subcategory":"Bank",
            "type":"Services"
        }
    ],
    "sg:phone":"+32 3 755 27 27",
    "sg:postcode":"9140",
    "sg:province":"Oost-Vlaanderen",
    "sg:tags":[
        "savings-banks"
    ],
    "wof:name":"Smet R",
    "wof:placetype":"venue"
},
  "geometry": {"coordinates":[4.2158489227,51.1684455872],"type":"Point"}
}