{
  "type": "Feature",
  "properties": {
    "iso:country":"BE",
    "sg:address":"Halmaaldorp 57",
    "sg:city":"Sint-truiden",
    "sg:orig_category":"Artsen and specialisten",
    "sg:phone":"+32 11 68 67 90",
    "sg:postcode":"3800",
    "sg:province":"Limburg",
    "wof:name":"Anita Simon",
    "wof:placetype":"venue"
},
  "geometry": {"coordinates":[5.151720047,50.8018608093],"type":"Point"}
}