{
  "type": "Feature",
  "properties": {
    "addr:full":"Blandenstraat 130 Oud-heverlee Vlaams-Brabant 3053",
    "addr:housenumber":"130",
    "addr:postcode":"3053",
    "addr:street":"Blandenstraat",
    "iso:country":"BE",
    "sg:address":"Blandenstraat 130",
    "sg:city":"Oud-heverlee",
    "sg:orig_category":"Artistes ind\u00e9pendants",
    "sg:phone":"+32 16 40 34 65",
    "sg:postcode":"3053",
    "sg:province":"Vlaams-Brabant",
    "wof:name":"Luc Mutsaerts",
    "wof:placetype":"venue"
},
  "geometry": {"coordinates":[4.7241168022,50.8339385986],"type":"Point"}
}