{
  "type": "Feature",
  "properties": {
    "addr:full":"Rue Des Huit Bonniers 1 Le Roeulx Hainaut 7070",
    "addr:housenumber":"1",
    "addr:postcode":"7070",
    "addr:street":"Rue Des Huit Bonniers",
    "iso:country":"BE",
    "sg:address":"Rue Des Huit Bonniers 1",
    "sg:city":"Le Roeulx",
    "sg:classifiers":[
        {
            "category":"Bakery",
            "type":"Food & Drink"
        }
    ],
    "sg:phone":"+32 64 66 29 03",
    "sg:postcode":"7070",
    "sg:province":"Hainaut",
    "sg:tags":[
        "confectioner",
        "baker"
    ],
    "wof:name":"Pesesse M",
    "wof:placetype":"venue"
},
  "geometry": {"coordinates":[4.1136760712,50.5015144348],"type":"Point"}
}