{
  "type": "Feature",
  "properties": {
    "addr:full":"Rue De La Consolation 70 Bruxelles (schaerbeek) Bruxelles-Capitale 1030",
    "addr:housenumber":"70",
    "addr:postcode":"1030",
    "addr:street":"Rue De La Consolation",
    "iso:country":"BE",
    "sg:address":"Rue De La Consolation 70",
    "sg:city":"Bruxelles (schaerbeek)",
    "sg:classifiers":[
        {
            "category":"Shopping",
            "subcategory":"Stationery & Office Supplies",
            "type":"Retail Goods"
        }
    ],
    "sg:phone":"+32 2 240 94 00",
    "sg:postcode":"1030",
    "sg:province":"Bruxelles-Capitale",
    "sg:tags":[
        "label"
    ],
    "wof:name":"Eurabel-turbel",
    "wof:placetype":"venue"
},
  "geometry": {"coordinates":[4.3790750504,50.8551826477],"type":"Point"}
}