{
  "type": "Feature",
  "properties": {
    "addr:full":"Rue De Bertaimont 51 Mons Hainaut 7000",
    "addr:housenumber":"51",
    "addr:postcode":"7000",
    "addr:street":"Rue De Bertaimont;Hainaut",
    "iso:country":"BE",
    "sg:address":"Rue De Bertaimont 51",
    "sg:city":"Mons",
    "sg:orig_category":"Naai- and breimachines",
    "sg:phone":"+32 65 36 19 01",
    "sg:postcode":"7000",
    "sg:province":"Hainaut",
    "wof:name":"Husqvarna",
    "wof:placetype":"venue"
},
  "geometry": {"coordinates":[3.9488461018,50.447681427],"type":"Point"}
}