{
  "type": "Feature",
  "properties": {
    "iso:country":"BE",
    "sg:address":"Rue Des Lutins 8",
    "sg:city":"Bruxelles",
    "sg:classifiers":[
        {
            "category":"Real Estate",
            "subcategory":"Surveying",
            "type":"Services"
        }
    ],
    "sg:phone":"+32 2 333 00 33",
    "sg:postcode":"1190",
    "sg:province":"Bruxelles-Capitale",
    "sg:tags":[
        "material",
        "photographic"
    ],
    "wof:name":"Filmobel S.a.",
    "wof:placetype":"venue"
},
  "geometry": {"coordinates":[4.3150601387,50.7998466492],"type":"Point"}
}