{
  "type": "Feature",
  "properties": {
    "iso:country":"BE",
    "sg:address":"Sommerstraat 19",
    "sg:city":"Antwerpen",
    "sg:orig_category":"Rev\u00eatements pour sols and murs. Constructions r\u00e9sidentielles sp\u00e9cifiques. Construction de maisons",
    "sg:phone":"+32 3 231 02 24",
    "sg:postcode":"2018",
    "sg:province":"Antwerpen",
    "wof:name":"Renzo Borioni",
    "wof:placetype":"venue"
},
  "geometry": {"coordinates":[4.4254879951,51.2117424011],"type":"Point"}
}