{
  "type": "Feature",
  "properties": {
    "iso:country":"BE",
    "sg:address":"D'oultremontstraat 30",
    "sg:city":"Sint-joost-ten-node/saint-josse-ten-noode",
    "sg:orig_category":"Fotografen and fotostudio's",
    "sg:phone":"+32 2 734 59 74",
    "sg:postcode":"1210",
    "sg:province":"Bruxelles-Capitale",
    "wof:name":"Studio D'hooge",
    "wof:placetype":"venue"
},
  "geometry": {"coordinates":[4.3710961342,50.852771759],"type":"Point"}
}