{
  "type": "Feature",
  "properties": {
    "iso:country":"BE",
    "sg:address":"Rue Kindermans 14",
    "sg:city":"Brussel/bruxelles",
    "sg:orig_category":"M\u00e9decines alternatives. M\u00e9decins and sp\u00e9cialistes",
    "sg:phone":"+32 2 538 89 58",
    "sg:postcode":"1000",
    "sg:province":"Bruxelles-Capitale",
    "wof:name":"Katia Akenbaum",
    "wof:placetype":"venue"
},
  "geometry": {"coordinates":[4.3662891388,50.8231887817],"type":"Point"}
}