{
  "type": "Feature",
  "properties": {
    "iso:country":"BE",
    "sg:address":"Diesterstraat 76",
    "sg:city":"Sint-truiden",
    "sg:classifiers":[
        {
            "category":"Professional",
            "subcategory":"Art Services",
            "type":"Services"
        }
    ],
    "sg:phone":"+32 11 68 37 14",
    "sg:postcode":"3800",
    "sg:province":"Limburg",
    "sg:tags":[
        "photography",
        "reporting",
        "-"
    ],
    "wof:name":"Custers Fotografie",
    "wof:placetype":"venue"
},
  "geometry": {"coordinates":[5.182407856,50.8184013367],"type":"Point"}
}