{
  "type": "Feature",
  "properties": {
    "iso:country":"BE",
    "sg:address":"Rue De Mortagne 122",
    "sg:city":"Leuze-en-hainaut (pipaix)",
    "sg:classifiers":[
        {
            "category":"Retail",
            "subcategory":"Veterinary Services",
            "type":"Services"
        }
    ],
    "sg:phone":"+32 69 66 69 66",
    "sg:postcode":"7904",
    "sg:province":"Hainaut",
    "sg:tags":[
        "veterinarian"
    ],
    "wof:name":"Havaux C",
    "wof:placetype":"venue"
},
  "geometry": {"coordinates":[3.5838429928,50.5783462524],"type":"Point"}
}