{
  "type": "Feature",
  "properties": {
    "addr:full":"Avenue Louise 94c Bruxelles (ixelles) Bruxelles-Capitale 1050",
    "addr:housenumber":"94c",
    "addr:postcode":"1050",
    "addr:street":"Avenue Louise",
    "iso:country":"BE",
    "sg:address":"Avenue Louise 94c",
    "sg:city":"Bruxelles (ixelles)",
    "sg:classifiers":[
        {
            "category":"Personal",
            "subcategory":"Nail Salon",
            "type":"Services"
        }
    ],
    "sg:phone":"+32 2 511 28 01",
    "sg:postcode":"1050",
    "sg:province":"Bruxelles-Capitale",
    "sg:tags":[
        "pedicure"
    ],
    "wof:name":"Beaute & Esthetique",
    "wof:placetype":"venue"
},
  "geometry": {"coordinates":[4.3572201729,50.8337287903],"type":"Point"}
}