{
  "type": "Feature",
  "properties": {
    "addr:full":"Rue Du Christ 65 Mouscron Hainaut 7700",
    "addr:housenumber":"65",
    "addr:postcode":"7700",
    "addr:street":"Rue Du Christ",
    "iso:country":"BE",
    "sg:address":"Rue Du Christ 65",
    "sg:city":"Mouscron",
    "sg:classifiers":[
        {
            "category":"Shopping",
            "subcategory":"Clothing, Apparel, & Fashions",
            "type":"Retail Goods"
        }
    ],
    "sg:phone":"+32 56 34 36 61",
    "sg:postcode":"7700",
    "sg:province":"Hainaut",
    "sg:tags":[
        "-",
        "clothing",
        "child"
    ],
    "wof:name":"Cotontige",
    "wof:placetype":"venue"
},
  "geometry": {"coordinates":[3.2071509361,50.7438278198],"type":"Point"}
}