{
  "type": "Feature",
  "properties": {
    "iso:country":"BE",
    "sg:address":"Geerstraat 84",
    "sg:city":"Baasrode",
    "sg:orig_category":"Catering and organisatie van feesten Ruimtes voor conferenties, recepties and feesten",
    "sg:phone":"+32 52 21 73 44",
    "sg:postcode":"9200",
    "sg:province":"Oost-Vlaanderen",
    "wof:name":"Feestzalen Hof Ter Velden",
    "wof:placetype":"venue"
},
  "geometry": {"coordinates":[4.1488280296,51.0276832581],"type":"Point"}
}