{
  "type": "Feature",
  "properties": {
    "addr:full":"Chauss\u00c9e De Louvain 22 Eghezee Namur 5310",
    "addr:housenumber":"22",
    "addr:postcode":"5310",
    "addr:street":"Chausse\u0301E De Louvain;Namur",
    "iso:country":"BE",
    "sg:address":"Chauss\u00c9e De Louvain 22",
    "sg:city":"Eghezee",
    "sg:orig_category":"Diverse kredietdiensten",
    "sg:postcode":"5310",
    "sg:province":"Namur",
    "wof:name":"Bancontact-mister Cash",
    "wof:placetype":"venue"
},
  "geometry": {"coordinates":[4.9108052254,50.5934257507],"type":"Point"}
}