{
  "type": "Feature",
  "properties": {
    "iso:country":"BE",
    "sg:address":"Avenue Napol\u00c9on 20",
    "sg:city":"Waterloo",
    "sg:orig_category":"Artsen and specialisten",
    "sg:phone":"+32 2 354 75 75",
    "sg:postcode":"1410",
    "sg:province":"Brabant Wallon",
    "wof:name":"Hubert Chardon",
    "wof:placetype":"venue"
},
  "geometry": {"coordinates":[4.4028968811,50.7168273926],"type":"Point"}
}