{
  "type": "Feature",
  "properties": {
    "addr:full":"Sentier De La Bourgerie 4 Moeskroen/mouscron Hainaut 7700",
    "addr:housenumber":"4",
    "addr:postcode":"7700",
    "addr:street":"Sentier De La Bourgerie",
    "iso:country":"BE",
    "sg:address":"Sentier De La Bourgerie 4",
    "sg:city":"Moeskroen/mouscron",
    "sg:orig_category":"Eleveurs de bovins",
    "sg:phone":"+32 56 34 36 59",
    "sg:postcode":"7700",
    "sg:province":"Hainaut",
    "wof:name":"Andre Renard",
    "wof:placetype":"venue"
},
  "geometry": {"coordinates":[3.2323200703,50.7400932312],"type":"Point"}
}