{
  "type": "Feature",
  "properties": {
    "iso:country":"BE",
    "sg:address":"Place Du Ballon 37",
    "sg:city":"Charleroi (jumet)",
    "sg:classifiers":[
        {
            "category":"Bars & Pubs",
            "type":"Food & Drink"
        }
    ],
    "sg:phone":"+32 71 35 37 65",
    "sg:postcode":"6040",
    "sg:province":"Hainaut",
    "sg:tags":[
        "tavern"
    ],
    "wof:name":"La Montgolfiere",
    "wof:placetype":"venue"
},
  "geometry": {"coordinates":[4.4142370224,50.4339561462],"type":"Point"}
}