{
  "type": "Feature",
  "properties": {
    "iso:country":"BE",
    "sg:address":"Stationstraat 82",
    "sg:city":"Turnhout",
    "sg:orig_category":"Diverse opleidingen and onderwijs",
    "sg:phone":"+32 14 41 53 98",
    "sg:postcode":"2300",
    "sg:province":"Antwerpen",
    "wof:name":"Trainingcentrum Of Course",
    "wof:placetype":"venue"
},
  "geometry": {"coordinates":[4.9403100014,51.3242111206],"type":"Point"}
}