{
  "type": "Feature",
  "properties": {
    "iso:country":"BE",
    "sg:address":"J. Van Elewijckstraat 35",
    "sg:city":"Grimbergen",
    "sg:orig_category":"Restaurants Ruimtes voor conferenties, recepties and feesten",
    "sg:phone":"+32 2 267 55 00",
    "sg:postcode":"1853",
    "sg:province":"Vlaams-Brabant",
    "wof:name":"Rijckendael",
    "wof:placetype":"venue"
},
  "geometry": {"coordinates":[4.3532061577,50.9044189453],"type":"Point"}
}