{
  "type": "Feature",
  "properties": {
    "iso:country":"BE",
    "sg:address":"N. Van Der Vekenstraat 20",
    "sg:city":"Mechelen",
    "sg:orig_category":"Activit\u00e9s diverses d'imprimerie",
    "sg:phone":"+32 15 41 78 61",
    "sg:postcode":"2800",
    "sg:province":"Antwerpen",
    "wof:name":"Hi.er",
    "wof:placetype":"venue"
},
  "geometry": {"coordinates":[4.4699997902,51.0099754333],"type":"Point"}
}