{
  "type": "Feature",
  "properties": {
    "iso:country":"BE",
    "sg:address":"Desselgemseweg 130",
    "sg:city":"Waregem",
    "sg:orig_category":"Elektrische installaties voor woningen",
    "sg:phone":"+32 56 60 51 64",
    "sg:postcode":"8790",
    "sg:province":"West-Vlaanderen",
    "wof:name":"Transfotec",
    "wof:placetype":"venue"
},
  "geometry": {"coordinates":[3.4062879086,50.8813476562],"type":"Point"}
}