{
  "type": "Feature",
  "properties": {
    "addr:full":"Veerstraat 81 Berlare Oost-Vlaanderen 9290",
    "addr:housenumber":"81",
    "addr:postcode":"9290",
    "addr:street":"Veerstraat",
    "iso:country":"BE",
    "sg:address":"Veerstraat 81",
    "sg:city":"Berlare",
    "sg:orig_category":"Transports routiers de marchandises. D\u00e9m\u00e9nagements",
    "sg:phone":"+32 9 367 50 19",
    "sg:postcode":"9290",
    "sg:province":"Oost-Vlaanderen",
    "wof:name":"Schatteman-trans",
    "wof:placetype":"venue"
},
  "geometry": {"coordinates":[3.9525210857,51.0235328674],"type":"Point"}
}