{
  "type": "Feature",
  "properties": {
    "iso:country":"BE",
    "sg:address":"Asserendries 4",
    "sg:city":"Aalst",
    "sg:classifiers":[
        {
            "category":"Bars & Pubs",
            "type":"Food & Drink"
        }
    ],
    "sg:phone":"+32 53 41 02 30",
    "sg:postcode":"9300",
    "sg:province":"Oost-Vlaanderen",
    "wof:name":"'t Goed Leven",
    "wof:placetype":"venue"
},
  "geometry": {"coordinates":[4.0267400742,50.9414710999],"type":"Point"}
}