{
  "type": "Feature",
  "properties": {
    "addr:full":"Transportstraat 1 Tessenderlo Limburg 3980",
    "addr:housenumber":"1",
    "addr:postcode":"3980",
    "addr:street":"Transportstraat",
    "iso:country":"BE",
    "sg:address":"Transportstraat 1",
    "sg:city":"Tessenderlo",
    "sg:classifiers":[
        {
            "category":"Communications",
            "type":"Services"
        }
    ],
    "sg:phone":"+32 13 61 16 33",
    "sg:postcode":"3980",
    "sg:province":"Limburg",
    "sg:tags":[
        "radio",
        "television",
        "broadcasting",
        "-"
    ],
    "wof:name":"Tvlokaal.com",
    "wof:placetype":"venue"
},
  "geometry": {"coordinates":[5.0875849724,51.0672340393],"type":"Point"}
}