{
  "type": "Feature",
  "properties": {
    "iso:country":"BE",
    "sg:address":"Quai Des Ardennes 135",
    "sg:city":"Angleur",
    "sg:orig_category":"Motos",
    "sg:phone":"+32 4 365 04 34",
    "sg:postcode":"4031",
    "sg:province":"Li\u00e8ge",
    "wof:name":"Maison Bikers-design",
    "wof:placetype":"venue"
},
  "geometry": {"coordinates":[5.6060600281,50.6152000427],"type":"Point"}
}