{
  "type": "Feature",
  "properties": {
    "iso:country":"BE",
    "sg:address":"Wynendalestraat 107",
    "sg:city":"Diksmuide",
    "sg:orig_category":"Elektrische installaties voor woningen",
    "sg:phone":"+32 51 50 00 08",
    "sg:postcode":"8600",
    "sg:province":"West-Vlaanderen",
    "wof:name":"Hubert Vandamme",
    "wof:placetype":"venue"
},
  "geometry": {"coordinates":[2.8657801151,51.0334663391],"type":"Point"}
}