{
  "type": "Feature",
  "properties": {
    "addr:full":"Vanderstichelenstraat 21 Sint-jans-molenbeek/molenbeek-saint-jean Bruxelles-Capitale 1080",
    "addr:housenumber":"21",
    "addr:postcode":"1080",
    "addr:street":"Vanderstichelenstraat",
    "iso:country":"BE",
    "sg:address":"Vanderstichelenstraat 21",
    "sg:city":"Sint-jans-molenbeek/molenbeek-saint-jean",
    "sg:orig_category":"Diverse organisaties and verenigingen",
    "sg:phone":"+32 2 425 81 08",
    "sg:postcode":"1080",
    "sg:province":"Bruxelles-Capitale",
    "wof:name":"Jeunesse Ouvri\u00c8re Chr\u00c9t.",
    "wof:placetype":"venue"
},
  "geometry": {"coordinates":[4.3419179916,50.8618507385],"type":"Point"}
}