{
  "type": "Feature",
  "properties": {
    "iso:country":"BE",
    "sg:address":"Lierbaan 123",
    "sg:city":"Putte",
    "sg:orig_category":"Protection civile",
    "sg:phone":"+32 15 76 05 29",
    "sg:postcode":"2580",
    "sg:province":"Antwerpen",
    "wof:name":"Brandweerkazerne",
    "wof:placetype":"venue"
},
  "geometry": {"coordinates":[4.6283431053,51.058921814],"type":"Point"}
}