{
  "type": "Feature",
  "properties": {
    "addr:full":"Sint-jozefswijk 1 Peer Limburg 3990",
    "addr:housenumber":"1",
    "addr:postcode":"3990",
    "addr:street":"Sint-Jozefswijk",
    "iso:country":"BE",
    "sg:address":"Sint-jozefswijk 1",
    "sg:city":"Peer",
    "sg:orig_category":"Plomberie, chauffage and installations sanitaires",
    "sg:phone":"+32 11 63 23 16",
    "sg:postcode":"3990",
    "sg:province":"Limburg",
    "wof:name":"Adriaan Janssen",
    "wof:placetype":"venue"
},
  "geometry": {"coordinates":[5.4571461678,51.1868591309],"type":"Point"}
}