{
  "type": "Feature",
  "properties": {
    "addr:full":"Champ Du Vert Chasseur 86 Bruxelles (uccle) Bruxelles-Capitale 1180",
    "addr:housenumber":"86",
    "addr:postcode":"1180",
    "addr:street":"Champ Du Vert Chasseur",
    "iso:country":"BE",
    "sg:address":"Champ Du Vert Chasseur 86",
    "sg:city":"Bruxelles (uccle)",
    "sg:classifiers":[
        {
            "category":"Professional",
            "subcategory":"Computer Services",
            "type":"Services"
        }
    ],
    "sg:phone":"+32 2 376 43 31",
    "sg:postcode":"1180",
    "sg:province":"Bruxelles-Capitale",
    "sg:tags":[
        "network"
    ],
    "wof:name":"Solutions Systems Inform",
    "wof:placetype":"venue"
},
  "geometry": {"coordinates":[4.3737912178,50.8020553589],"type":"Point"}
}