{
  "type": "Feature",
  "properties": {
    "iso:country":"BE",
    "sg:address":"Land Van Waaslaan Haven",
    "sg:city":"Beveren (verrebroek)",
    "sg:classifiers":[
        {
            "category":"Banks & Credit Unions",
            "subcategory":"Investment Brokerage",
            "type":"Services"
        }
    ],
    "sg:phone":"+32 3 570 93 20",
    "sg:postcode":"9130",
    "sg:province":"Oost-Vlaanderen",
    "sg:tags":[
        "distributor",
        "-",
        "distributors",
        "physical"
    ],
    "wof:name":"Upm-kymmene Distribution",
    "wof:placetype":"venue"
},
  "geometry": {"coordinates":[4.2524251938,51.3222732544],"type":"Point"}
}