{
  "type": "Feature",
  "properties": {
    "iso:country":"BE",
    "sg:address":"Rooierweg 35",
    "sg:city":"Bilzen",
    "sg:orig_category":"Afval and schroot Gh",
    "sg:phone":"+32 89 41 82 39",
    "sg:postcode":"3740",
    "sg:province":"Limburg",
    "wof:name":"Fa. Erlich",
    "wof:placetype":"venue"
},
  "geometry": {"coordinates":[5.5057621002,50.8783912659],"type":"Point"}
}