{
  "type": "Feature",
  "properties": {
    "iso:country":"BE",
    "sg:address":"Spanjaardstraat 5b",
    "sg:city":"Gent",
    "sg:classifiers":[
        {
            "category":"Professional",
            "subcategory":"Engineering",
            "type":"Services"
        }
    ],
    "sg:phone":"+32 9 329 72 58",
    "sg:postcode":"9000",
    "sg:province":"Oost-Vlaanderen",
    "sg:tags":[
        "technical",
        "equipment",
        "offices-"
    ],
    "wof:name":"Electrical Diagrams Design",
    "wof:placetype":"venue"
},
  "geometry": {"coordinates":[3.7355940342,51.0540504456],"type":"Point"}
}