{
  "type": "Feature",
  "properties": {
    "addr:full":"Dorp 1 Sint-martens-latem Oost-Vlaanderen 9830",
    "addr:housenumber":"1",
    "addr:postcode":"9830",
    "addr:street":"Dorp",
    "iso:country":"BE",
    "sg:address":"Dorp 1",
    "sg:city":"Sint-martens-latem",
    "sg:classifiers":[
        {
            "category":"Government",
            "subcategory":"Police Station",
            "type":"Public Place"
        }
    ],
    "sg:phone":"+32 9 282 54 40",
    "sg:postcode":"9830",
    "sg:province":"Oost-Vlaanderen",
    "sg:tags":[
        "gendarmerie"
    ],
    "wof:name":"Federale Politie",
    "wof:placetype":"venue"
},
  "geometry": {"coordinates":[3.640007019,51.0207557678],"type":"Point"}
}