{
  "type": "Feature",
  "properties": {
    "iso:country":"BE",
    "sg:address":"Nieuwstraat 127",
    "sg:city":"Knokke-heist (knokke)",
    "sg:classifiers":[
        {
            "category":"Tea Room",
            "subcategory":"None",
            "type":"Food & Drink"
        }
    ],
    "sg:phone":"+32 50 61 24 54",
    "sg:postcode":"8300",
    "sg:province":"West-Vlaanderen",
    "wof:name":"De 6 Bochten",
    "wof:placetype":"venue"
},
  "geometry": {"coordinates":[3.2804570198,51.3331718445],"type":"Point"}
}