{
  "type": "Feature",
  "properties": {
    "addr:full":"Rue De L'aite 3 Hannut Li\u00e8ge 4280",
    "addr:housenumber":"3",
    "addr:postcode":"4280",
    "addr:street":"Rue De L'Aite",
    "iso:country":"BE",
    "sg:address":"Rue De L'aite 3",
    "sg:city":"Hannut",
    "sg:orig_category":"Overheidsdiensten",
    "sg:phone":"+32 19 51 24 27",
    "sg:postcode":"4280",
    "sg:province":"Li\u00e8ge",
    "wof:name":"C.p.a.s.",
    "wof:placetype":"venue"
},
  "geometry": {"coordinates":[5.0772027969,50.6711273193],"type":"Point"}
}