{
  "type": "Feature",
  "properties": {
    "iso:country":"BE",
    "sg:address":"7320",
    "sg:city":"Bernissart (grand)",
    "sg:orig_category":"Pharmaciens",
    "sg:phone":"+32 900 10 500",
    "sg:postcode":"7320",
    "sg:province":"Hainaut",
    "wof:name":"Pharmacies De Garde",
    "wof:placetype":"venue"
},
  "geometry": {"coordinates":[3.6437900066,50.4788284302],"type":"Point"}
}