{
  "type": "Feature",
  "properties": {
    "iso:country":"BE",
    "sg:address":"Tongersesteenweg 4a",
    "sg:city":"Kortessem",
    "sg:classifiers":[
        {
            "category":"Shopping",
            "subcategory":"Florist",
            "type":"Retail Goods"
        }
    ],
    "sg:phone":"+32 11 37 73 16",
    "sg:postcode":"3720",
    "sg:province":"Limburg",
    "wof:name":"Bloemen Orchis",
    "wof:placetype":"venue"
},
  "geometry": {"coordinates":[5.3875341415,50.8571205139],"type":"Point"}
}