{
  "type": "Feature",
  "properties": {
    "iso:country":"BE",
    "sg:address":"Heiken 25",
    "sg:city":"Sint-katelijne-waver (onze-lieve-vrouw-waver)",
    "sg:classifiers":[
        {
            "category":"Home & Garden",
            "subcategory":"Building Materials",
            "type":"Retail Goods"
        }
    ],
    "sg:phone":"+32 15 55 19 35",
    "sg:postcode":"2861",
    "sg:province":"Antwerpen",
    "sg:tags":[
        "window"
    ],
    "wof:name":"De Haes M & Zoon Bvba",
    "wof:placetype":"venue"
},
  "geometry": {"coordinates":[4.5467171669,51.0482902527],"type":"Point"}
}