{
  "type": "Feature",
  "properties": {
    "iso:country":"BE",
    "sg:address":"Heiststeenweg 5",
    "sg:city":"Putte",
    "sg:orig_category":"M\u00e9decins and sp\u00e9cialistes",
    "sg:phone":"+32 15 75 77 57",
    "sg:postcode":"2580",
    "sg:province":"Antwerpen",
    "wof:name":"J. Spincemaille",
    "wof:placetype":"venue"
},
  "geometry": {"coordinates":[4.6723599434,51.0577507019],"type":"Point"}
}