{
  "type": "Feature",
  "properties": {
    "addr:full":"Mimosalaan 40 Boortmeerbeek Vlaams-Brabant 3190",
    "addr:housenumber":"40",
    "addr:postcode":"3190",
    "addr:street":"Mimosalaan",
    "iso:country":"BE",
    "sg:address":"Mimosalaan 40",
    "sg:city":"Boortmeerbeek",
    "sg:orig_category":"Diverse opleidingen and onderwijs Informaticaconsulenten",
    "sg:phone":"+32 15 61 41 05",
    "sg:postcode":"3190",
    "sg:province":"Vlaams-Brabant",
    "wof:name":"Eldeka",
    "wof:placetype":"venue"
},
  "geometry": {"coordinates":[4.5727658272,50.9819335938],"type":"Point"}
}