{
  "type": "Feature",
  "properties": {
    "iso:country":"BE",
    "sg:address":"Oostmeersdreef 92",
    "sg:city":"Deinze",
    "sg:orig_category":"Installation de menuiserie en bois and plastique",
    "sg:phone":"+32 9 386 15 96",
    "sg:postcode":"9800",
    "sg:province":"Oost-Vlaanderen",
    "wof:name":"De Smet",
    "wof:placetype":"venue"
},
  "geometry": {"coordinates":[3.5387599468,50.9830322266],"type":"Point"}
}