{
  "type": "Feature",
  "properties": {
    "addr:full":"Rogierlaan 53ba Oostende West-Vlaanderen 8400",
    "addr:housenumber":"53ba",
    "addr:postcode":"8400",
    "addr:street":"Rogierlaan",
    "iso:country":"BE",
    "sg:address":"Rogierlaan 53ba",
    "sg:city":"Oostende",
    "sg:orig_category":"Verplichte sociale verzekeringen",
    "sg:phone":"+32 59 50 00 28",
    "sg:postcode":"8400",
    "sg:province":"West-Vlaanderen",
    "wof:name":"Hulpkas Voor Z.i.v.",
    "wof:placetype":"venue"
},
  "geometry": {"coordinates":[2.9118909836,51.2262954712],"type":"Point"}
}