{
  "type": "Feature",
  "properties": {
    "iso:country":"BE",
    "sg:address":"Gr. De Smet De Naeyerln 81",
    "sg:city":"Kortrijk",
    "sg:classifiers":[
        {
            "category":"Fast Food",
            "type":"Food & Drink"
        }
    ],
    "sg:phone":"+32 56 35 85 49",
    "sg:postcode":"8500",
    "sg:province":"West-Vlaanderen",
    "sg:tags":[
        "\u00c0",
        "restaurants",
        "emporter",
        "restaurant"
    ],
    "wof:name":"Restaurant Thai",
    "wof:placetype":"venue"
},
  "geometry": {"coordinates":[3.2566459179,50.8346977234],"type":"Point"}
}