{
  "type": "Feature",
  "properties": {
    "iso:country":"BE",
    "sg:address":"Baudeloostraat 58",
    "sg:city":"Tielt (aarsele)",
    "sg:classifiers":[
        {
            "category":"Freight",
            "type":"Transportation"
        }
    ],
    "sg:phone":"+32 51 63 31 24",
    "sg:postcode":"8700",
    "sg:province":"West-Vlaanderen",
    "sg:tags":[
        "-",
        "transport"
    ],
    "wof:name":"Dewinter-callewaert & Zn",
    "wof:placetype":"venue"
},
  "geometry": {"coordinates":[3.435395956,50.9943962097],"type":"Point"}
}