{
  "type": "Feature",
  "properties": {
    "addr:full":"Avenue Hamoir 10b1 Ukkel/uccle Bruxelles-Capitale 1180",
    "addr:housenumber":"10b1",
    "addr:postcode":"1180",
    "addr:street":"Avenue Hamoir;/",
    "iso:country":"BE",
    "sg:address":"Avenue Hamoir 10b1",
    "sg:city":"Ukkel/uccle",
    "sg:classifiers":[
        {
            "category":"Arena",
            "subcategory":"Sports Club",
            "type":"Entertainment"
        }
    ],
    "sg:phone":"+32 2 375 18 92",
    "sg:postcode":"1180",
    "sg:province":"Bruxelles-Capitale",
    "sg:tags":[
        "de"
    ],
    "wof:name":"R. L\u00c9opold Club",
    "wof:placetype":"venue"
},
  "geometry": {"coordinates":[4.3724899292,50.7979507446],"type":"Point"}
}