{
  "type": "Feature",
  "properties": {
    "addr:full":"Rue Van Eyck 57 Elsene/ixelles Bruxelles-Capitale 1050",
    "addr:housenumber":"57",
    "addr:postcode":"1050",
    "addr:street":"Rue Van Eyck",
    "iso:country":"BE",
    "sg:address":"Rue Van Eyck 57",
    "sg:city":"Elsene/ixelles",
    "sg:orig_category":"Epiceries",
    "sg:phone":"+32 2 647 26 69",
    "sg:postcode":"1050",
    "sg:province":"Bruxelles-Capitale",
    "wof:name":"Turquoise",
    "wof:placetype":"venue"
},
  "geometry": {"coordinates":[4.369038105,50.8193702698],"type":"Point"}
}