{
  "type": "Feature",
  "properties": {
    "iso:country":"BE",
    "sg:address":"De Donckerstraat 6",
    "sg:city":"Gistel",
    "sg:classifiers":[
        {
            "category":"Insurance",
            "subcategory":"Insurance Agent",
            "type":"Services"
        }
    ],
    "sg:phone":"+32 59 27 86 63",
    "sg:postcode":"8470",
    "sg:province":"West-Vlaanderen",
    "sg:tags":[
        "broker"
    ],
    "wof:name":"Astaes J",
    "wof:placetype":"venue"
},
  "geometry": {"coordinates":[2.9634490013,51.1551704407],"type":"Point"}
}