{
  "type": "Feature",
  "properties": {
    "addr:full":"Route De Landen 166 Hannut Li\u00e8ge 4280",
    "addr:housenumber":"166",
    "addr:postcode":"4280",
    "addr:street":"Route De Landen",
    "iso:country":"BE",
    "sg:address":"Route De Landen 166",
    "sg:city":"Hannut",
    "sg:classifiers":[
        {
            "category":"Autos & Motor Vehicles",
            "subcategory":"Automobile Sales",
            "type":"Retail Goods"
        }
    ],
    "sg:phone":"+32 19 51 24 40",
    "sg:postcode":"4280",
    "sg:province":"Li\u00e8ge",
    "sg:tags":[
        "voertuigen",
        "bmw",
        "auto's"
    ],
    "wof:name":"Delbrassinne Motors",
    "wof:placetype":"venue"
},
  "geometry": {"coordinates":[5.0820288658,50.7016181946],"type":"Point"}
}