{
  "type": "Feature",
  "properties": {
    "iso:country":"BE",
    "sg:address":"Banneuxstraat 4",
    "sg:city":"Hasselt",
    "sg:classifiers":[
        {
            "category":"Shopping",
            "subcategory":"Optician",
            "type":"Retail Goods"
        }
    ],
    "sg:phone":"+32 11 21 55 22",
    "sg:postcode":"3500",
    "sg:province":"Limburg",
    "sg:tags":[
        "-"
    ],
    "wof:name":"Kristien Maris-optiek",
    "wof:placetype":"venue"
},
  "geometry": {"coordinates":[5.3460268974,50.9479522705],"type":"Point"}
}