{
  "type": "Feature",
  "properties": {
    "iso:country":"BE",
    "sg:address":"Gemeentehuisstraat 10",
    "sg:city":"Gavere",
    "sg:orig_category":"Artsen and specialisten",
    "sg:phone":"+32 9 384 78 05",
    "sg:postcode":"9890",
    "sg:province":"Oost-Vlaanderen",
    "wof:name":"Yves Benoit",
    "wof:placetype":"venue"
},
  "geometry": {"coordinates":[3.6894879341,50.9207954407],"type":"Point"}
}