{
  "type": "Feature",
  "properties": {
    "addr:full":"Hooiweg 8 Diksmuide West-Vlaanderen 8600",
    "addr:housenumber":"8",
    "addr:postcode":"8600",
    "addr:street":"Hooiweg",
    "iso:country":"BE",
    "sg:address":"Hooiweg 8",
    "sg:city":"Diksmuide",
    "sg:orig_category":"Eleveurs and marchands de porcs. Eleveurs de bovins",
    "sg:phone":"+32 51 50 06 05",
    "sg:postcode":"8600",
    "sg:province":"West-Vlaanderen",
    "wof:name":"Eric Sampers",
    "wof:placetype":"venue"
},
  "geometry": {"coordinates":[2.9253439903,51.0264816284],"type":"Point"}
}