{
  "type": "Feature",
  "properties": {
    "iso:country":"BE",
    "sg:address":"Avenue De La Plante 11",
    "sg:city":"Namur",
    "sg:classifiers":[
        {
            "category":"Building & Trades",
            "subcategory":"Construction",
            "type":"Services"
        }
    ],
    "sg:phone":"+32 81 22 39 95",
    "sg:postcode":"5000",
    "sg:province":"Namur",
    "sg:tags":[
        "work",
        "waterproofing"
    ],
    "wof:name":"Margot B",
    "wof:placetype":"venue"
},
  "geometry": {"coordinates":[4.8622841835,50.4568367004],"type":"Point"}
}