{
  "type": "Feature",
  "properties": {
    "addr:full":"Tieltstr. 87 Meulebeke West-Vlaanderen 8760",
    "addr:housenumber":"87",
    "addr:postcode":"8760",
    "addr:street":"Tieltstr.",
    "iso:country":"BE",
    "sg:address":"Tieltstr. 87",
    "sg:city":"Meulebeke",
    "sg:orig_category":"Miscellaneous Products",
    "sg:phone":"+32 51 48 80 39",
    "sg:postcode":"8760",
    "sg:province":"West-Vlaanderen",
    "wof:name":"Blaton En Everaert Bvba",
    "wof:placetype":"venue"
},
  "geometry": {"coordinates":[3.2957561016,50.9561195374],"type":"Point"}
}