{
  "type": "Feature",
  "properties": {
    "addr:full":"Rue Des Tanni\u00e8res 7 Rouvroy (lamorteau) Luxembourg 6767",
    "addr:housenumber":"7",
    "addr:postcode":"6767",
    "addr:street":"Rue Des Tannie\u0300Res",
    "iso:country":"BE",
    "sg:address":"Rue Des Tanni\u00e8res 7",
    "sg:city":"Rouvroy (lamorteau)",
    "sg:classifiers":[
        {
            "category":"Health Services",
            "subcategory":"Doctor",
            "type":"Services"
        }
    ],
    "sg:phone":"+32 63 57 74 27",
    "sg:postcode":"6767",
    "sg:province":"Luxembourg",
    "sg:tags":[
        "medicinephysicians",
        "surgeon"
    ],
    "wof:name":"G\u00e9rin Marc",
    "wof:placetype":"venue"
},
  "geometry": {"coordinates":[5.4772992134,49.5242881775],"type":"Point"}
}