{
  "type": "Feature",
  "properties": {
    "addr:full":"Hollestraat 30 Galmaarden Vlaams-Brabant 1570",
    "addr:housenumber":"30",
    "addr:postcode":"1570",
    "addr:street":"Hollestraat",
    "iso:country":"BE",
    "sg:address":"Hollestraat 30",
    "sg:city":"Galmaarden",
    "sg:orig_category":"V\u00e9t\u00e9rinaires",
    "sg:phone":"+32 54 58 76 55",
    "sg:postcode":"1570",
    "sg:province":"Vlaams-Brabant",
    "wof:name":"Johan Juwet",
    "wof:placetype":"venue"
},
  "geometry": {"coordinates":[4.0154709816,50.7439880371],"type":"Point"}
}