{
  "type": "Feature",
  "properties": {
    "addr:full":"Rue De Menuchamps 6 Paliseul (fays-les-veneurs) Luxembourg 6856",
    "addr:housenumber":"6",
    "addr:postcode":"6856",
    "addr:street":"Rue De Menuchamps",
    "iso:country":"BE",
    "sg:address":"Rue De Menuchamps 6",
    "sg:city":"Paliseul (fays-les-veneurs)",
    "sg:classifiers":[
        {
            "category":"Travel",
            "subcategory":"Resort",
            "type":"Entertainment"
        }
    ],
    "sg:phone":"+32 61 53 35 16",
    "sg:postcode":"6856",
    "sg:province":"Luxembourg",
    "sg:tags":[
        "farm",
        "house",
        "holiday",
        "guest"
    ],
    "wof:name":"Menuchamps (le)",
    "wof:placetype":"venue"
},
  "geometry": {"coordinates":[5.1614809036,49.8669815063],"type":"Point"}
}