{
  "type": "Feature",
  "properties": {
    "iso:country":"BE",
    "sg:address":"Eikenlei 8",
    "sg:city":"Brasschaat",
    "sg:classifiers":[
        {
            "category":"Manufacturing",
            "subcategory":"Textiles",
            "type":"Manufacturing & Wholesale Goods"
        }
    ],
    "sg:phone":"+32 3 645 61 11",
    "sg:postcode":"2930",
    "sg:province":"Antwerpen",
    "sg:tags":[
        "polyester"
    ],
    "wof:name":"M\u00fcnch Chemie",
    "wof:placetype":"venue"
},
  "geometry": {"coordinates":[4.4664268494,51.2729148865],"type":"Point"}
}