{
  "type": "Feature",
  "properties": {
    "addr:full":"Vicognedijk 31 Oostende West-Vlaanderen 8400",
    "addr:housenumber":"31",
    "addr:postcode":"8400",
    "addr:street":"Vicognedijk",
    "iso:country":"BE",
    "sg:address":"Vicognedijk 31",
    "sg:city":"Oostende",
    "sg:classifiers":[
        {
            "category":"Arena",
            "subcategory":"Sports Club",
            "type":"Entertainment"
        }
    ],
    "sg:phone":"+32 59 32 37 27",
    "sg:postcode":"8400",
    "sg:province":"West-Vlaanderen",
    "wof:name":"Bloso-centrum wittebrug",
    "wof:placetype":"venue"
},
  "geometry": {"coordinates":[2.945360899,51.2245788574],"type":"Point"}
}