{
  "type": "Feature",
  "properties": {
    "addr:full":"Les Martignons 11 Momignies Hainaut 6590",
    "addr:housenumber":"11",
    "addr:postcode":"6590",
    "addr:street":"Hainaut",
    "iso:country":"BE",
    "sg:address":"Les Martignons 11",
    "sg:city":"Momignies",
    "sg:orig_category":"Sportclubs",
    "sg:phone":"+32 60 51 20 04",
    "sg:postcode":"6590",
    "sg:province":"Hainaut",
    "wof:name":"Union Sud Volley 86",
    "wof:placetype":"venue"
},
  "geometry": {"coordinates":[4.1721391678,50.0255317688],"type":"Point"}
}