{
  "type": "Feature",
  "properties": {
    "iso:country":"BE",
    "sg:address":"Nieuwe Stationsstraat 63",
    "sg:city":"Lokeren",
    "sg:classifiers":[
        {
            "category":"Building & Trades",
            "subcategory":"Pest Control",
            "type":"Services"
        }
    ],
    "sg:phone":"+32 9 355 91 15",
    "sg:postcode":"9160",
    "sg:province":"Oost-Vlaanderen",
    "sg:tags":[
        "painting",
        "contractor"
    ],
    "wof:name":"Naudts",
    "wof:placetype":"venue"
},
  "geometry": {"coordinates":[3.9079740047,51.0918388367],"type":"Point"}
}