{
  "type": "Feature",
  "properties": {
    "iso:country":"BE",
    "sg:address":"Maaldestedestraat 53",
    "sg:city":"Ieper",
    "sg:orig_category":"Gespecialiseerde residenti\u00eble bouw",
    "sg:phone":"+32 57 20 37 94",
    "sg:postcode":"8902",
    "sg:province":"West-Vlaanderen",
    "wof:name":"Jackie Defever",
    "wof:placetype":"venue"
},
  "geometry": {"coordinates":[2.9164168835,50.8467178345],"type":"Point"}
}