{
  "type": "Feature",
  "properties": {
    "iso:country":"BE",
    "sg:address":"Chauss\u00c9e De Charleroi 44",
    "sg:city":"Nivelles",
    "sg:orig_category":"Eclairage et \u00e9quipements du foyer",
    "sg:phone":"+32 67 22 02 54",
    "sg:postcode":"1400",
    "sg:province":"Brabant Wallon",
    "wof:name":"Maison Italfer",
    "wof:placetype":"venue"
},
  "geometry": {"coordinates":[4.3364682198,50.5839691162],"type":"Point"}
}