{
  "type": "Feature",
  "properties": {
    "iso:country":"BE",
    "sg:address":"Klein Tegelrijstraat 98",
    "sg:city":"Nieuwerkerken",
    "sg:orig_category":"Rev\u00eatements pour sols and murs. Construction de maisons",
    "sg:phone":"+32 11 69 20 94",
    "sg:postcode":"3850",
    "sg:province":"Limburg",
    "wof:name":"Lode Winnen",
    "wof:placetype":"venue"
},
  "geometry": {"coordinates":[5.1886081696,50.8798484802],"type":"Point"}
}