{
  "type": "Feature",
  "properties": {
    "addr:full":"Martin Pr\u00c9 1 Beaumont Hainaut 6500",
    "addr:housenumber":"1",
    "addr:postcode":"6500",
    "addr:street":"Martin Pre\u0301;Hainaut",
    "iso:country":"BE",
    "sg:address":"Martin Pr\u00c9 1",
    "sg:city":"Beaumont",
    "sg:orig_category":"Dierenartsen",
    "sg:phone":"+32 71 58 89 05",
    "sg:postcode":"6500",
    "sg:province":"Hainaut",
    "wof:name":"Martine Laloyaux",
    "wof:placetype":"venue"
},
  "geometry": {"coordinates":[4.2611517906,50.265422821],"type":"Point"}
}