{
  "type": "Feature",
  "properties": {
    "addr:full":"Rue Franz Merjay 197 Bruxelles (ixelles) Bruxelles-Capitale 1050",
    "addr:housenumber":"197",
    "addr:postcode":"1050",
    "addr:street":"Rue Franz Merjay",
    "iso:country":"BE",
    "sg:address":"Rue Franz Merjay 197",
    "sg:city":"Bruxelles (ixelles)",
    "sg:classifiers":[
        {
            "category":"Health Services",
            "subcategory":"Doctor",
            "type":"Services"
        }
    ],
    "sg:phone":"+32 2 345 35 53",
    "sg:postcode":"1050",
    "sg:province":"Bruxelles-Capitale",
    "sg:tags":[
        "medicinephysicians",
        "surgeon"
    ],
    "wof:name":"Delattre Andr\u00e9",
    "wof:placetype":"venue"
},
  "geometry": {"coordinates":[4.3511791229,50.8153915405],"type":"Point"}
}