{
  "type": "Feature",
  "properties": {
    "iso:country":"BE",
    "sg:address":"Burgemeester Nolfstraat 16",
    "sg:city":"Kortrijk",
    "sg:orig_category":"M\u00e9decins and sp\u00e9cialistes",
    "sg:phone":"+32 56 22 65 03",
    "sg:postcode":"8500",
    "sg:province":"West-Vlaanderen",
    "wof:name":"Andr\u00c9 Verbeke",
    "wof:placetype":"venue"
},
  "geometry": {"coordinates":[3.2580330372,50.827419281],"type":"Point"}
}