{
  "type": "Feature",
  "properties": {
    "iso:country":"BE",
    "sg:address":"Hazelaarstraat 45",
    "sg:city":"Izegem",
    "sg:orig_category":"Woningbouw",
    "sg:phone":"+32 51 30 32 19",
    "sg:postcode":"8870",
    "sg:province":"West-Vlaanderen",
    "wof:name":"Rufin Loonis",
    "wof:placetype":"venue"
},
  "geometry": {"coordinates":[3.1914019585,50.9122390747],"type":"Point"}
}