{
  "type": "Feature",
  "properties": {
    "addr:full":"Rue De Tournai 9 Leuze-en-hainaut Hainaut 7900",
    "addr:housenumber":"9",
    "addr:postcode":"7900",
    "addr:street":"Rue De Tournai",
    "iso:country":"BE",
    "sg:address":"Rue De Tournai 9",
    "sg:city":"Leuze-en-hainaut",
    "sg:classifiers":[
        {
            "category":"Shopping",
            "subcategory":"Jewelry",
            "type":"Retail Goods"
        }
    ],
    "sg:phone":"+32 69 66 31 81",
    "sg:postcode":"7900",
    "sg:province":"Hainaut",
    "sg:tags":[
        "jeweller",
        "-"
    ],
    "wof:name":"Beaumont P",
    "wof:placetype":"venue"
},
  "geometry": {"coordinates":[3.61729002,50.5988731384],"type":"Point"}
}