{
  "type": "Feature",
  "properties": {
    "addr:full":"Chauss\u00c9e De Bruxelles 50 Charleroi Hainaut 6042",
    "addr:housenumber":"50",
    "addr:postcode":"6042",
    "addr:street":"Chausse\u0301E De Bruxelles;Hainaut",
    "iso:country":"BE",
    "sg:address":"Chauss\u00c9e De Bruxelles 50",
    "sg:city":"Charleroi",
    "sg:orig_category":"Entretien and r\u00e9parations de voitures",
    "sg:phone":"+32 71 70 19 04",
    "sg:postcode":"6042",
    "sg:province":"Hainaut",
    "wof:name":"Hoggar Automobiles",
    "wof:placetype":"venue"
},
  "geometry": {"coordinates":[4.4396820068,50.4368629456],"type":"Point"}
}