{
  "type": "Feature",
  "properties": {
    "iso:country":"BE",
    "sg:address":"Bovigny 96a",
    "sg:city":"Gouvy (bovigny)",
    "sg:classifiers":[
        {
            "category":"Personal",
            "subcategory":"Beauty Salon",
            "type":"Services"
        }
    ],
    "sg:phone":"+32 80 21 72 52",
    "sg:postcode":"6671",
    "sg:province":"Luxembourg",
    "sg:tags":[
        "lady",
        "-",
        "hairdressing"
    ],
    "wof:name":"Gregoire B",
    "wof:placetype":"venue"
},
  "geometry": {"coordinates":[5.9151639938,50.2191238403],"type":"Point"}
}