{
  "type": "Feature",
  "properties": {
    "addr:full":"Route De Flandre 81 Comines-warneton (comines) Hainaut 7780",
    "addr:housenumber":"81",
    "addr:postcode":"7780",
    "addr:street":"Route De Flandre",
    "iso:country":"BE",
    "sg:address":"Route De Flandre 81",
    "sg:city":"Comines-warneton (comines)",
    "sg:classifiers":[
        {
            "category":"Wholesale",
            "subcategory":"Meat",
            "type":"Manufacturing & Wholesale Goods"
        }
    ],
    "sg:phone":"+32 475 45 03 68",
    "sg:postcode":"7780",
    "sg:province":"Hainaut",
    "sg:tags":[
        "whol",
        "-"
    ],
    "wof:name":"Depypere D",
    "wof:placetype":"venue"
},
  "geometry": {"coordinates":[3.0023899078,50.7912712097],"type":"Point"}
}