{
  "type": "Feature",
  "properties": {
    "addr:full":"Rue D'amberloup 21 Libramont-chevigny Luxembourg 6800",
    "addr:housenumber":"21",
    "addr:postcode":"6800",
    "addr:street":"Rue D'Amberloup",
    "iso:country":"BE",
    "sg:address":"Rue D'amberloup 21",
    "sg:city":"Libramont-chevigny",
    "sg:orig_category":"Boucheries",
    "sg:phone":"+32 61 22 25 23",
    "sg:postcode":"6800",
    "sg:province":"Luxembourg",
    "wof:name":"Roland Penoy",
    "wof:placetype":"venue"
},
  "geometry": {"coordinates":[5.4136447906,49.9524307251],"type":"Point"}
}