{
  "type": "Feature",
  "properties": {
    "addr:full":"Berlaarbaan 246 Sint-katelijne-waver Antwerpen 2861",
    "addr:housenumber":"246",
    "addr:postcode":"2861",
    "addr:street":"Berlaarbaan",
    "iso:country":"BE",
    "sg:address":"Berlaarbaan 246",
    "sg:city":"Sint-katelijne-waver",
    "sg:orig_category":"Groententeelt",
    "sg:phone":"+32 15 55 17 19",
    "sg:postcode":"2861",
    "sg:province":"Antwerpen",
    "wof:name":"Uytterhoeven Fr. & D.",
    "wof:placetype":"venue"
},
  "geometry": {"coordinates":[4.5469589233,51.0551185608],"type":"Point"}
}