{
  "type": "Feature",
  "properties": {
    "iso:country":"BE",
    "sg:address":"Dr. Emmanuelle 32",
    "sg:city":"Genepien",
    "sg:orig_category":"Diverse bedrijfsbeheeradviesbureaus",
    "sg:phone":"+32 10 61 66 12",
    "sg:postcode":"1470",
    "sg:province":"Brabant Wallon",
    "wof:name":"Larbouillat Danny",
    "wof:placetype":"venue"
},
  "geometry": {"coordinates":[4.5347018242,50.6464195251],"type":"Point"}
}