{
  "type": "Feature",
  "properties": {
    "addr:full":"Rue Du P\u00c9rr\u00c9on 34 Sprimont Li\u00e8ge 4141",
    "addr:housenumber":"34",
    "addr:postcode":"4141",
    "addr:street":"Rue Du Pe\u0301Rre\u0301On",
    "iso:country":"BE",
    "sg:address":"Rue Du P\u00c9rr\u00c9on 34",
    "sg:city":"Sprimont",
    "sg:orig_category":"Tribunaux",
    "sg:phone":"+32 4 360 81 81",
    "sg:postcode":"4141",
    "sg:province":"Li\u00e8ge",
    "wof:name":"Justice De Paix",
    "wof:placetype":"venue"
},
  "geometry": {"coordinates":[5.7107048035,50.5303001404],"type":"Point"}
}