{
  "type": "Feature",
  "properties": {
    "addr:full":"Europalaan 104 Halle Vlaams-Brabant 1500",
    "addr:housenumber":"104",
    "addr:postcode":"1500",
    "addr:street":"Europalaan",
    "iso:country":"BE",
    "sg:address":"Europalaan 104",
    "sg:city":"Halle",
    "sg:classifiers":[
        {
            "category":"Professional",
            "subcategory":"Art Services",
            "type":"Services"
        }
    ],
    "sg:phone":"+32 2 356 28 30",
    "sg:postcode":"1500",
    "sg:province":"Vlaams-Brabant",
    "sg:tags":[
        "graphic",
        "designer"
    ],
    "wof:name":"Geleyns H",
    "wof:placetype":"venue"
},
  "geometry": {"coordinates":[4.2220687866,50.7211494446],"type":"Point"}
}