{
  "type": "Feature",
  "properties": {
    "addr:full":"Oostendestraat 260 Torhout West-Vlaanderen 8820",
    "addr:housenumber":"260",
    "addr:postcode":"8820",
    "addr:street":"Oostendestraat",
    "iso:country":"BE",
    "sg:address":"Oostendestraat 260",
    "sg:city":"Torhout",
    "sg:classifiers":[
        {
            "category":"Home & Garden",
            "subcategory":"Home Furnishings",
            "type":"Retail Goods"
        }
    ],
    "sg:phone":"+32 50 21 21 23",
    "sg:postcode":"8820",
    "sg:province":"West-Vlaanderen",
    "sg:tags":[
        "-",
        "furniture"
    ],
    "wof:name":"Meublux Bvba",
    "wof:placetype":"venue"
},
  "geometry": {"coordinates":[3.0835580826,51.0710372925],"type":"Point"}
}