{
  "type": "Feature",
  "properties": {
    "iso:country":"BE",
    "sg:address":"Biermanstraat 6",
    "sg:city":"Schuiferskapelle",
    "sg:classifiers":[
        {
            "category":"Bakery",
            "type":"Food & Drink"
        }
    ],
    "sg:phone":"+32 51 40 04 04",
    "sg:postcode":"8700",
    "sg:province":"West-Vlaanderen",
    "sg:tags":[
        "cake",
        "product",
        "related",
        "bread"
    ],
    "wof:name":"Dhr Willy Vergote",
    "wof:placetype":"venue"
},
  "geometry": {"coordinates":[3.3350830078,51.0329971313],"type":"Point"}
}