{
  "type": "Feature",
  "properties": {
    "addr:full":"Rue Du Travail 1 Grace-hollogne Li\u00e8ge 4460",
    "addr:housenumber":"1",
    "addr:postcode":"4460",
    "addr:street":"Rue Du Travail",
    "iso:country":"BE",
    "sg:address":"Rue Du Travail 1",
    "sg:city":"Grace-hollogne",
    "sg:orig_category":"Rev\u00eatements de sols and murs",
    "sg:phone":"+32 4 246 35 95",
    "sg:postcode":"4460",
    "sg:province":"Li\u00e8ge",
    "wof:name":"Dcsc",
    "wof:placetype":"venue"
},
  "geometry": {"coordinates":[5.4963970184,50.6553115845],"type":"Point"}
}