{
  "type": "Feature",
  "properties": {
    "addr:full":"Large Voie 81 Herstal Li\u00e8ge 4040",
    "addr:housenumber":"81",
    "addr:postcode":"4040",
    "addr:street":"Large Voie",
    "iso:country":"BE",
    "sg:address":"Large Voie 81",
    "sg:city":"Herstal",
    "sg:orig_category":"Foto-uitrusting Fotografen and fotostudio's",
    "sg:phone":"+32 4 264 20 08",
    "sg:postcode":"4040",
    "sg:province":"Li\u00e8ge",
    "wof:name":"Photos Salmon News",
    "wof:placetype":"venue"
},
  "geometry": {"coordinates":[5.634373188,50.6669464111],"type":"Point"}
}