{
  "type": "Feature",
  "properties": {
    "addr:full":"Vrijheidsstraat 18 Neerpelt Limburg 3910",
    "addr:housenumber":"18",
    "addr:postcode":"3910",
    "addr:street":"Vrijheidsstraat",
    "iso:country":"BE",
    "sg:address":"Vrijheidsstraat 18",
    "sg:city":"Neerpelt",
    "sg:orig_category":"Artsen and specialisten",
    "sg:phone":"+32 11 66 70 67",
    "sg:postcode":"3910",
    "sg:province":"Limburg",
    "wof:name":"Stijn Schapmans",
    "wof:placetype":"venue"
},
  "geometry": {"coordinates":[5.4368371964,51.2277107239],"type":"Point"}
}