{
  "type": "Feature",
  "properties": {
    "addr:full":"Warandestraat 65 Turnhout Antwerpen 2300",
    "addr:housenumber":"65",
    "addr:postcode":"2300",
    "addr:street":"Warandestraat",
    "iso:country":"BE",
    "sg:address":"Warandestraat 65",
    "sg:city":"Turnhout",
    "sg:classifiers":[
        {
            "category":"Restaurant",
            "type":"Food & Drink"
        }
    ],
    "sg:phone":"+32 14 43 89 44",
    "sg:postcode":"2300",
    "sg:province":"Antwerpen",
    "wof:name":"De Foyer",
    "wof:placetype":"venue"
},
  "geometry": {"coordinates":[4.9415168762,51.3242874146],"type":"Point"}
}