{
  "type": "Feature",
  "properties": {
    "addr:full":"Otegemstraat 92 Zwevegem West-Vlaanderen 8550",
    "addr:housenumber":"92",
    "addr:postcode":"8550",
    "addr:street":"Otegemstraat",
    "iso:country":"BE",
    "sg:address":"Otegemstraat 92",
    "sg:city":"Zwevegem",
    "sg:orig_category":"Boucheries",
    "sg:phone":"+32 56 75 86 55",
    "sg:postcode":"8550",
    "sg:province":"West-Vlaanderen",
    "wof:name":"Carl Vermeersch",
    "wof:placetype":"venue"
},
  "geometry": {"coordinates":[3.339329958,50.8132896423],"type":"Point"}
}