{
  "type": "Feature",
  "properties": {
    "addr:full":"Nekkersputstraat 59 Gent Oost-Vlaanderen 9000",
    "addr:housenumber":"59",
    "addr:postcode":"9000",
    "addr:street":"Nekkersputstraat;Oost-Vlaanderen",
    "iso:country":"BE",
    "sg:address":"Nekkersputstraat 59",
    "sg:city":"Gent",
    "sg:classifiers":[
        {
            "category":"Health Services",
            "subcategory":"Dentist",
            "type":"Services"
        }
    ],
    "sg:phone":"+32 9 227 62 31",
    "sg:postcode":"9000",
    "sg:province":"Oost-Vlaanderen",
    "wof:name":"Vervust C",
    "wof:placetype":"venue"
},
  "geometry": {"coordinates":[3.6908330917,51.0594406128],"type":"Point"}
}