{
  "type": "Feature",
  "properties": {
    "iso:country":"BE",
    "sg:address":"Palinghuizen 102",
    "sg:city":"Gent",
    "sg:orig_category":"Travail and traitement du bois",
    "sg:phone":"+32 9 236 27 27",
    "sg:postcode":"9000",
    "sg:province":"Oost-Vlaanderen",
    "wof:name":"Maurits De Graeve",
    "wof:placetype":"venue"
},
  "geometry": {"coordinates":[3.6979050636,51.0679092407],"type":"Point"}
}