{
  "type": "Feature",
  "properties": {
    "iso:country":"BE",
    "sg:address":"Industrieter 1144",
    "sg:city":"Herk-de-stad",
    "sg:orig_category":"Installation de menuiserie en bois and plastique",
    "sg:phone":"+32 13 55 47 73",
    "sg:postcode":"3540",
    "sg:province":"Limburg",
    "wof:name":"Heeren",
    "wof:placetype":"venue"
},
  "geometry": {"coordinates":[5.1653671265,50.9463691711],"type":"Point"}
}