{
  "type": "Feature",
  "properties": {
    "iso:country":"BE",
    "sg:address":"Romeins Plein 3b1",
    "sg:city":"Zottegem",
    "sg:orig_category":"Woningbouw",
    "sg:phone":"+32 9 360 40 06",
    "sg:postcode":"9620",
    "sg:province":"Oost-Vlaanderen",
    "wof:name":"Johan Vermassen",
    "wof:placetype":"venue"
},
  "geometry": {"coordinates":[3.7821679115,50.8830223083],"type":"Point"}
}