{
  "type": "Feature",
  "properties": {
    "iso:country":"BE",
    "sg:address":"Rue Du Bati 52",
    "sg:city":"Durbuy",
    "sg:orig_category":"V\u00e9t\u00e9rinaires",
    "sg:phone":"+32 86 46 78 27",
    "sg:postcode":"6941",
    "sg:province":"Luxembourg",
    "wof:name":"Olivier Deom",
    "wof:placetype":"venue"
},
  "geometry": {"coordinates":[5.5630531311,50.3443717957],"type":"Point"}
}