{
  "type": "Feature",
  "properties": {
    "addr:full":"Koning Albertlaan 31 De Pinte Oost-Vlaanderen 9840",
    "addr:housenumber":"31",
    "addr:postcode":"9840",
    "addr:street":"Koning Albertlaan",
    "iso:country":"BE",
    "sg:address":"Koning Albertlaan 31",
    "sg:city":"De Pinte",
    "sg:classifiers":[
        {
            "category":"Shopping",
            "subcategory":"Stationery & Office Supplies",
            "type":"Retail Goods"
        }
    ],
    "sg:phone":"+32 9 281 11 31",
    "sg:postcode":"9840",
    "sg:province":"Oost-Vlaanderen",
    "sg:tags":[
        "equipment",
        "dairy"
    ],
    "wof:name":"Polyketting Conveyor Technology",
    "wof:placetype":"venue"
},
  "geometry": {"coordinates":[3.6507489681,50.9949226379],"type":"Point"}
}