{
  "type": "Feature",
  "properties": {
    "addr:full":"Hubert Fr\u00e8re-orbanlaan 569 Gent Oost-Vlaanderen 9000",
    "addr:housenumber":"569",
    "addr:postcode":"9000",
    "addr:street":"Hubert Fre\u0300Re-Orbanlaan;Oost-Vlaanderen",
    "iso:country":"BE",
    "sg:address":"Hubert Fr\u00e8re-orbanlaan 569",
    "sg:city":"Gent",
    "sg:classifiers":[
        {
            "category":"Home & Garden",
            "subcategory":"Furniture",
            "type":"Retail Goods"
        }
    ],
    "sg:phone":"+32 9 225 04 19",
    "sg:postcode":"9000",
    "sg:province":"Oost-Vlaanderen",
    "sg:tags":[
        "-"
    ],
    "wof:name":"G.o.m.e.s.",
    "wof:placetype":"venue"
},
  "geometry": {"coordinates":[3.7363390923,51.0405921936],"type":"Point"}
}