{
  "type": "Feature",
  "properties": {
    "iso:country":"BE",
    "sg:address":"Houplinesstraat 6",
    "sg:city":"Komen-waasten/comines-warneton",
    "sg:orig_category":"Rundveehouders",
    "sg:phone":"+32 56 58 93 74",
    "sg:postcode":"7783",
    "sg:province":"Hainaut",
    "wof:name":"Michel Capelle",
    "wof:placetype":"venue"
},
  "geometry": {"coordinates":[2.8828949928,50.7069244385],"type":"Point"}
}