{
  "type": "Feature",
  "properties": {
    "addr:full":"Tarwestraat 29 Dilsen-stokkem Limburg 3650",
    "addr:housenumber":"29",
    "addr:postcode":"3650",
    "addr:street":"Tarwestraat",
    "iso:country":"BE",
    "sg:address":"Tarwestraat 29",
    "sg:city":"Dilsen-stokkem",
    "sg:classifiers":[
        {
            "category":"Arena",
            "subcategory":"Sports Club",
            "type":"Entertainment"
        }
    ],
    "sg:phone":"+32 89 79 30 51",
    "sg:postcode":"3650",
    "sg:province":"Limburg",
    "sg:tags":[
        "de"
    ],
    "wof:name":"Boksschool Stokkem",
    "wof:placetype":"venue"
},
  "geometry": {"coordinates":[5.7143940926,51.0369262695],"type":"Point"}
}