{
  "type": "Feature",
  "properties": {
    "iso:country":"BE",
    "sg:address":"Rue Leli\u00c8vre 9",
    "sg:city":"Namur",
    "sg:orig_category":"Advocaten and juridische adviseurs",
    "sg:phone":"+32 81 22 21 81",
    "sg:postcode":"5000",
    "sg:province":"Namur",
    "wof:name":"N. Gendrin",
    "wof:placetype":"venue"
},
  "geometry": {"coordinates":[4.8607997894,50.4650382996],"type":"Point"}
}