{
  "type": "Feature",
  "properties": {
    "addr:full":"Ter Beemden 11 Izegem West-Vlaanderen 8870",
    "addr:housenumber":"11",
    "addr:postcode":"8870",
    "addr:street":"Ter Beemden",
    "iso:country":"BE",
    "sg:address":"Ter Beemden 11",
    "sg:city":"Izegem",
    "sg:classifiers":[
        {
            "category":"Manufacturing",
            "subcategory":"Tools & Machinery",
            "type":"Manufacturing & Wholesale Goods"
        }
    ],
    "sg:phone":"+32 51 31 39 11",
    "sg:postcode":"8870",
    "sg:province":"West-Vlaanderen",
    "sg:tags":[
        "-"
    ],
    "wof:name":"Optimax Vlaanderen",
    "wof:placetype":"venue"
},
  "geometry": {"coordinates":[3.1950891018,50.9046287537],"type":"Point"}
}