{
  "type": "Feature",
  "properties": {
    "addr:full":"Rue De Li\u00c8ge 94 Li\u00c8ge Li\u00e8ge 4020",
    "addr:housenumber":"94",
    "addr:postcode":"4020",
    "addr:street":"Rue De Lie\u0300Ge",
    "iso:country":"BE",
    "sg:address":"Rue De Li\u00c8ge 94",
    "sg:city":"Li\u00c8ge",
    "sg:orig_category":"Bouwmaterialen Gh Drogisterijen",
    "sg:phone":"+32 4 362 94 23",
    "sg:postcode":"4020",
    "sg:province":"Li\u00e8ge",
    "wof:name":"Lebens-deitermann",
    "wof:placetype":"venue"
},
  "geometry": {"coordinates":[5.6160120964,50.6427993774],"type":"Point"}
}