{
  "type": "Feature",
  "properties": {
    "iso:country":"BE",
    "sg:address":"Avenue De La R\u00e9sistance 7",
    "sg:city":"Vielsalm (grand-halleux)",
    "sg:classifiers":[
        {
            "category":"Retail",
            "subcategory":"Auto Repair",
            "type":"Services"
        }
    ],
    "sg:phone":"+32 80 21 67 47",
    "sg:postcode":"6698",
    "sg:province":"Luxembourg",
    "sg:tags":[
        "garage"
    ],
    "wof:name":"Bietheres J Sprl",
    "wof:placetype":"venue"
},
  "geometry": {"coordinates":[5.908053875,50.3257751465],"type":"Point"}
}