{
  "type": "Feature",
  "properties": {
    "addr:full":"Avenue Henri Conscience 201 Bruxelles (evere) Bruxelles-Capitale 1140",
    "addr:housenumber":"201",
    "addr:postcode":"1140",
    "addr:street":"Avenue Henri Conscience",
    "iso:country":"BE",
    "sg:address":"Avenue Henri Conscience 201",
    "sg:city":"Bruxelles (evere)",
    "sg:classifiers":[
        {
            "category":"Government",
            "subcategory":"Fire Station",
            "type":"Public Place"
        }
    ],
    "sg:phone":"+32 2 241 35 77",
    "sg:postcode":"1140",
    "sg:province":"Bruxelles-Capitale",
    "sg:tags":[
        "installation",
        "-",
        "air conditioning"
    ],
    "wof:name":"Becrou Scrl",
    "wof:placetype":"venue"
},
  "geometry": {"coordinates":[4.4007167816,50.8731193542],"type":"Point"}
}