{
  "type": "Feature",
  "properties": {
    "iso:country":"BE",
    "sg:address":"Stapelplein 70b100",
    "sg:city":"Gent",
    "sg:classifiers":[
        {
            "category":"Banks & Credit Unions",
            "subcategory":"Atm",
            "type":"Services"
        }
    ],
    "sg:phone":"+32 9 265 87 99",
    "sg:postcode":"9000",
    "sg:province":"Oost-Vlaanderen",
    "sg:tags":[
        "d'entreprises",
        "de",
        "bureau"
    ],
    "wof:name":"Bultinck Zakenkantoor",
    "wof:placetype":"venue"
},
  "geometry": {"coordinates":[3.7341051102,51.0647697449],"type":"Point"}
}