{
  "type": "Feature",
  "properties": {
    "iso:country":"BE",
    "sg:address":"Rue Du Commerce 24",
    "sg:city":"Wavre",
    "sg:orig_category":"Pharmaciens",
    "sg:phone":"+32 10 22 23 31",
    "sg:postcode":"1300",
    "sg:province":"Brabant Wallon",
    "wof:name":"Pharmacie Familia",
    "wof:placetype":"venue"
},
  "geometry": {"coordinates":[4.6100897789,50.7163352966],"type":"Point"}
}