{
  "type": "Feature",
  "properties": {
    "iso:country":"BE",
    "sg:address":"Drabstraat 109",
    "sg:city":"Mortsel",
    "sg:orig_category":"M\u00e9decins and sp\u00e9cialistes. V\u00e9t\u00e9rinaires",
    "sg:phone":"+32 3 449 78 31",
    "sg:postcode":"2640",
    "sg:province":"Antwerpen",
    "wof:name":"Erwin De Winter",
    "wof:placetype":"venue"
},
  "geometry": {"coordinates":[4.4669308662,51.1730995178],"type":"Point"}
}