{
  "type": "Feature",
  "properties": {
    "iso:country":"BE",
    "sg:address":"Donk 69",
    "sg:city":"Oud-turnhout",
    "sg:classifiers":[
        {
            "category":"Personal",
            "subcategory":"Nail Salon",
            "type":"Services"
        }
    ],
    "sg:phone":"+32 14 45 00 16",
    "sg:postcode":"2360",
    "sg:province":"Antwerpen",
    "sg:tags":[
        "pedicure"
    ],
    "wof:name":"Horemans",
    "wof:placetype":"venue"
},
  "geometry": {"coordinates":[5.0291829109,51.2970237732],"type":"Point"}
}