{
  "type": "Feature",
  "properties": {
    "addr:full":"Graethemstraat 6 Borgloon Limburg 3840",
    "addr:housenumber":"6",
    "addr:postcode":"3840",
    "addr:street":"Graethemstraat",
    "iso:country":"BE",
    "sg:address":"Graethemstraat 6",
    "sg:city":"Borgloon",
    "sg:classifiers":[
        {
            "category":"Food & Beverages",
            "subcategory":"Fruits & Vegetables",
            "type":"Retail Goods"
        }
    ],
    "sg:phone":"+32 12 74 47 73",
    "sg:postcode":"3840",
    "sg:province":"Limburg",
    "sg:tags":[
        "l\u00e9gumes"
    ],
    "wof:name":"Huis 't Vitamientje",
    "wof:placetype":"venue"
},
  "geometry": {"coordinates":[5.3408808708,50.8031806946],"type":"Point"}
}