{
  "type": "Feature",
  "properties": {
    "addr:full":"Bovigny 88 Gouvy (bovigny) Luxembourg 6671",
    "addr:housenumber":"88",
    "addr:postcode":"6671",
    "addr:street":"Bovigny",
    "iso:country":"BE",
    "sg:address":"Bovigny 88",
    "sg:city":"Gouvy (bovigny)",
    "sg:classifiers":[
        {
            "category":"Building & Trades",
            "subcategory":"Landscaping Services",
            "type":"Services"
        }
    ],
    "sg:phone":"+32 80 21 75 00",
    "sg:postcode":"6671",
    "sg:province":"Luxembourg",
    "sg:tags":[
        "-",
        "lopping",
        "work",
        "tree",
        "felling"
    ],
    "wof:name":"Gregoire R",
    "wof:placetype":"venue"
},
  "geometry": {"coordinates":[5.9151639938,50.2191238403],"type":"Point"}
}