{
  "type": "Feature",
  "properties": {
    "addr:full":"Avenue Du Bourgmestre Jean Materne 52-83 Namur (jambes) Namur 5100",
    "addr:postcode":"52-83;5100",
    "addr:street":"Avenue Du Bourgmestre Jean Materne",
    "iso:country":"BE",
    "sg:address":"Avenue Du Bourgmestre Jean Materne 52-83",
    "sg:city":"Namur (jambes)",
    "sg:classifiers":[
        {
            "category":"Home & Garden",
            "subcategory":"Home Furnishings",
            "type":"Retail Goods"
        }
    ],
    "sg:phone":"+32 81 30 03 41",
    "sg:postcode":"5100",
    "sg:province":"Namur",
    "sg:tags":[
        "-",
        "bed",
        "mattress"
    ],
    "wof:name":"Meubles Massart",
    "wof:placetype":"venue"
},
  "geometry": {"coordinates":[4.8713750839,50.4566345215],"type":"Point"}
}