{
  "type": "Feature",
  "properties": {
    "iso:country":"BE",
    "sg:address":"Aachenerstrasse 220",
    "sg:city":"Eupen",
    "sg:orig_category":"V\u00e9hicules automobiles",
    "sg:phone":"+32 87 55 77 60",
    "sg:postcode":"4701",
    "sg:province":"Li\u00e8ge",
    "wof:name":"Vis\u00c9 Gert",
    "wof:placetype":"venue"
},
  "geometry": {"coordinates":[6.0412201881,50.6376190186],"type":"Point"}
}