{
  "type": "Feature",
  "properties": {
    "addr:full":"Rue En Bois 102 Liege Li\u00e8ge 4000",
    "addr:housenumber":"102",
    "addr:postcode":"4000",
    "addr:street":"Rue En Bois",
    "iso:country":"BE",
    "sg:address":"Rue En Bois 102",
    "sg:city":"Liege",
    "sg:orig_category":"Herstellingen and onderhoud van auto's",
    "sg:phone":"+32 4 226 27 37",
    "sg:postcode":"4000",
    "sg:province":"Li\u00e8ge",
    "wof:name":"Vandersmissen",
    "wof:placetype":"venue"
},
  "geometry": {"coordinates":[5.5483489037,50.6463813782],"type":"Point"}
}