{
  "type": "Feature",
  "properties": {
    "addr:full":"Grand-rue 6 Martelange Luxembourg 6630",
    "addr:housenumber":"6",
    "addr:postcode":"6630",
    "addr:street":"Grand-Rue",
    "iso:country":"BE",
    "sg:address":"Grand-rue 6",
    "sg:city":"Martelange",
    "sg:orig_category":"Overheidsdiensten",
    "sg:phone":"+32 63 60 01 73",
    "sg:postcode":"6630",
    "sg:province":"Luxembourg",
    "wof:name":"Administration Communale",
    "wof:placetype":"venue"
},
  "geometry": {"coordinates":[5.7406840324,49.832862854],"type":"Point"}
}