{
  "type": "Feature",
  "properties": {
    "iso:country":"BE",
    "sg:address":"Gabriellestraat 56",
    "sg:city":"Ukkel/uccle",
    "sg:orig_category":"Artsen and specialisten",
    "sg:phone":"+32 2 343 77 18",
    "sg:postcode":"1180",
    "sg:province":"Bruxelles-Capitale",
    "wof:name":"Alicja Frenkel/a. Frenkel",
    "wof:placetype":"venue"
},
  "geometry": {"coordinates":[4.3599209785,50.8136825562],"type":"Point"}
}