{
  "type": "Feature",
  "properties": {
    "addr:full":"Koning Ridderstraat 11 Moeskroen/mouscron Hainaut 7700",
    "addr:housenumber":"11",
    "addr:postcode":"7700",
    "addr:street":"Koning Ridderstraat",
    "iso:country":"BE",
    "sg:address":"Koning Ridderstraat 11",
    "sg:city":"Moeskroen/mouscron",
    "sg:orig_category":"Onderdelen and accessoires voor auto's",
    "sg:phone":"+32 56 33 30 35",
    "sg:postcode":"7700",
    "sg:province":"Hainaut",
    "wof:name":"Centrale Du Pneu",
    "wof:placetype":"venue"
},
  "geometry": {"coordinates":[3.2323200703,50.7400932312],"type":"Point"}
}