{
  "type": "Feature",
  "properties": {
    "iso:country":"BE",
    "sg:address":"Rue De France 79",
    "sg:city":"Florenville",
    "sg:orig_category":"V\u00e9t\u00e9rinaires",
    "sg:phone":"+32 61 31 15 45",
    "sg:postcode":"6820",
    "sg:province":"Luxembourg",
    "wof:name":"Albert Didier",
    "wof:placetype":"venue"
},
  "geometry": {"coordinates":[5.294754982,49.6981201172],"type":"Point"}
}