{
  "type": "Feature",
  "properties": {
    "addr:full":"Ieperweg 31 Zedelgem (loppem) West-Vlaanderen 8210",
    "addr:housenumber":"31",
    "addr:postcode":"8210",
    "addr:street":"Ieperweg",
    "iso:country":"BE",
    "sg:address":"Ieperweg 31",
    "sg:city":"Zedelgem (loppem)",
    "sg:classifiers":[
        {
            "category":"Freight",
            "type":"Transportation"
        }
    ],
    "sg:phone":"+32 50 84 03 71",
    "sg:postcode":"8210",
    "sg:province":"West-Vlaanderen",
    "sg:tags":[
        "-",
        "transport"
    ],
    "wof:name":"Bussche F",
    "wof:placetype":"venue"
},
  "geometry": {"coordinates":[3.1458399296,51.1376457214],"type":"Point"}
}