{
  "type": "Feature",
  "properties": {
    "addr:full":"Rue De La Cambre 22bc-d Sint-lambrechts-woluwe/woluwe-saint-lambert Bruxelles-Capitale 1200",
    "addr:housenumber":"22bc-d sint-lambrechts-woluwe",
    "addr:postcode":"1200",
    "addr:street":"Rue De La Cambre",
    "iso:country":"BE",
    "sg:address":"Rue De La Cambre 22bc-d",
    "sg:city":"Sint-lambrechts-woluwe/woluwe-saint-lambert",
    "sg:orig_category":"Avocats and conseillers juridiques",
    "sg:phone":"+32 2 762 95 95",
    "sg:postcode":"1200",
    "sg:province":"Bruxelles-Capitale",
    "wof:name":"G. De Walque",
    "wof:placetype":"venue"
},
  "geometry": {"coordinates":[4.4252500534,50.8438110352],"type":"Point"}
}