{
  "type": "Feature",
  "properties": {
    "addr:full":"Rue De La Borgnette 15bis Tournai Hainaut 7500",
    "addr:housenumber":"15bis",
    "addr:postcode":"7500",
    "addr:street":"Rue De La Borgnette",
    "iso:country":"BE",
    "sg:address":"Rue De La Borgnette 15bis",
    "sg:city":"Tournai",
    "sg:classifiers":[
        {
            "category":"Home & Garden",
            "subcategory":"Building Materials",
            "type":"Retail Goods"
        }
    ],
    "sg:phone":"+32 69 21 46 90",
    "sg:postcode":"7500",
    "sg:province":"Hainaut",
    "sg:tags":[
        "veranda"
    ],
    "wof:name":"Aliplast-db Aluminium",
    "wof:placetype":"venue"
},
  "geometry": {"coordinates":[3.371931076,50.6222229004],"type":"Point"}
}