{
  "type": "Feature",
  "properties": {
    "addr:full":"Rue De Coppin 206 Namur (jambes) Namur 5100",
    "addr:housenumber":"206",
    "addr:postcode":"5100",
    "addr:street":"Rue De Coppin",
    "iso:country":"BE",
    "sg:address":"Rue De Coppin 206",
    "sg:city":"Namur (jambes)",
    "sg:classifiers":[
        {
            "category":"Professional",
            "subcategory":"Accounting & Tax Preparation",
            "type":"Services"
        }
    ],
    "sg:phone":"+32 81 30 90 66",
    "sg:postcode":"5100",
    "sg:province":"Namur",
    "sg:tags":[
        "bookkeeper"
    ],
    "wof:name":"Dethinne-delplanche",
    "wof:placetype":"venue"
},
  "geometry": {"coordinates":[4.8713750839,50.4566345215],"type":"Point"}
}