{
  "type": "Feature",
  "properties": {
    "addr:full":"Schoolstraat 14 Zele Oost-Vlaanderen 9240",
    "addr:housenumber":"14",
    "addr:postcode":"9240",
    "addr:street":"Schoolstraat",
    "iso:country":"BE",
    "sg:address":"Schoolstraat 14",
    "sg:city":"Zele",
    "sg:classifiers":[
        {
            "category":"Home & Garden",
            "subcategory":"Carpets & Floor Coverings",
            "type":"Retail Goods"
        }
    ],
    "sg:phone":"+32 3 777 07 78",
    "sg:postcode":"9240",
    "sg:province":"Oost-Vlaanderen",
    "sg:tags":[
        "parquet"
    ],
    "wof:name":"Artekta",
    "wof:placetype":"venue"
},
  "geometry": {"coordinates":[4.0517301559,51.0881881714],"type":"Point"}
}