{
  "type": "Feature",
  "properties": {
    "addr:full":"Heimeulenweg 105 Zoersel Antwerpen 2980",
    "addr:housenumber":"105",
    "addr:postcode":"2980",
    "iso:country":"BE",
    "sg:address":"Heimeulenweg 105",
    "sg:city":"Zoersel",
    "sg:classifiers":[
        {
            "category":"Utilities",
            "subcategory":"Natural Gas",
            "type":"Services"
        }
    ],
    "sg:phone":"+32 3 385 59 10",
    "sg:postcode":"2980",
    "sg:province":"Antwerpen",
    "sg:tags":[
        "welding"
    ],
    "wof:name":"Inomaxe",
    "wof:placetype":"venue"
},
  "geometry": {"coordinates":[4.713435173,51.269985199],"type":"Point"}
}