{
  "type": "Feature",
  "properties": {
    "addr:full":"Koning Albertlaan 106 Lochristi Oost-Vlaanderen 9080",
    "addr:housenumber":"106",
    "addr:postcode":"9080",
    "addr:street":"Koning Albertlaan",
    "iso:country":"BE",
    "sg:address":"Koning Albertlaan 106",
    "sg:city":"Lochristi",
    "sg:orig_category":"Telecommunicatieapparaten",
    "sg:phone":"+32 9 355 91 18",
    "sg:postcode":"9080",
    "sg:province":"Oost-Vlaanderen",
    "wof:name":"King's Electronics Import",
    "wof:placetype":"venue"
},
  "geometry": {"coordinates":[3.8251240253,51.1054077148],"type":"Point"}
}