{
  "type": "Feature",
  "properties": {
    "addr:full":"Route Lierneux 9999 Manhay Luxembourg 6960",
    "addr:housenumber":"9999",
    "addr:postcode":"6960",
    "addr:street":"Route Lierneux",
    "iso:country":"BE",
    "sg:address":"Route Lierneux 9999",
    "sg:city":"Manhay",
    "sg:orig_category":"Beheer van afvalopslag- and stortplaatsen",
    "sg:phone":"+32 86 45 58 48",
    "sg:postcode":"6960",
    "sg:province":"Luxembourg",
    "wof:name":"Parcs A Conteneurs Manhay",
    "wof:placetype":"venue"
},
  "geometry": {"coordinates":[5.6754698753,50.291759491],"type":"Point"}
}