{
  "type": "Feature",
  "properties": {
    "iso:country":"BE",
    "sg:address":"Guido Gezellestraat 113-115",
    "sg:city":"Denderleeuw",
    "sg:classifiers":[
        {
            "category":"Professional",
            "subcategory":"Lawyer & Legal Services",
            "type":"Services"
        }
    ],
    "sg:phone":"+32 53 66 60 20",
    "sg:postcode":"9470",
    "sg:province":"Oost-Vlaanderen",
    "sg:tags":[
        "notary"
    ],
    "wof:name":"Rottier J",
    "wof:placetype":"venue"
},
  "geometry": {"coordinates":[4.0772118568,50.8879814148],"type":"Point"}
}