{
  "type": "Feature",
  "properties": {
    "iso:country":"BE",
    "sg:address":"Bruggesteenweg 34",
    "sg:city":"Middelkerke",
    "sg:orig_category":"Rundveehouders Varkenskwekers",
    "sg:phone":"+32 59 27 83 88",
    "sg:postcode":"8433",
    "sg:province":"West-Vlaanderen",
    "wof:name":"Stijn D'hulster",
    "wof:placetype":"venue"
},
  "geometry": {"coordinates":[2.8457300663,51.1217842102],"type":"Point"}
}