{
  "type": "Feature",
  "properties": {
    "iso:country":"BE",
    "sg:address":"Zonnestraat 6",
    "sg:city":"Gent",
    "sg:orig_category":"Notaires",
    "sg:phone":"+32 9 225 17 24",
    "sg:postcode":"9000",
    "sg:province":"Oost-Vlaanderen",
    "wof:name":"Y. Tytgat",
    "wof:placetype":"venue"
},
  "geometry": {"coordinates":[3.7221400738,51.0505256653],"type":"Point"}
}