{
  "type": "Feature",
  "properties": {
    "addr:full":"Lodderstraat 18 Bornem Antwerpen 2880",
    "addr:housenumber":"18",
    "addr:postcode":"2880",
    "addr:street":"Lodderstraat",
    "iso:country":"BE",
    "sg:address":"Lodderstraat 18",
    "sg:city":"Bornem",
    "sg:classifiers":[
        {
            "category":"Manufacturing",
            "subcategory":"Printing",
            "type":"Manufacturing & Wholesale Goods"
        }
    ],
    "sg:phone":"+32 3 890 19 11",
    "sg:postcode":"2880",
    "sg:province":"Antwerpen",
    "sg:tags":[
        "publishing"
    ],
    "wof:name":"Multirotamail Nv",
    "wof:placetype":"venue"
},
  "geometry": {"coordinates":[4.2761597633,51.087059021],"type":"Point"}
}