{
  "type": "Feature",
  "properties": {
    "addr:full":"Wegvoeringsstraat 126 Sint-niklaas Oost-Vlaanderen 9100",
    "addr:housenumber":"126",
    "addr:postcode":"9100",
    "addr:street":"Wegvoeringsstraat",
    "iso:country":"BE",
    "sg:address":"Wegvoeringsstraat 126",
    "sg:city":"Sint-niklaas",
    "sg:orig_category":"Onderhoud van kantoor- and computeruitrusting",
    "sg:phone":"+32 3 296 56 10",
    "sg:postcode":"9100",
    "sg:province":"Oost-Vlaanderen",
    "wof:name":"Fa. Covacomp",
    "wof:placetype":"venue"
},
  "geometry": {"coordinates":[4.1293091774,51.1729850769],"type":"Point"}
}