{
  "type": "Feature",
  "properties": {
    "iso:country":"BE",
    "sg:address":"Landbouwstraat 148",
    "sg:city":"Mechelen",
    "sg:classifiers":[
        {
            "category":"Arts & Performance",
            "subcategory":"Theater",
            "type":"Entertainment"
        }
    ],
    "sg:phone":"+32 15 27 00 22",
    "sg:postcode":"2800",
    "sg:province":"Antwerpen",
    "sg:tags":[
        "concert-halls",
        "theatre"
    ],
    "wof:name":"Ticketline Entertainment @ Events",
    "wof:placetype":"venue"
},
  "geometry": {"coordinates":[4.4593372345,51.0245704651],"type":"Point"}
}