{
  "type": "Feature",
  "properties": {
    "iso:country":"BE",
    "sg:address":"2288",
    "sg:city":"Grobbendonk",
    "sg:orig_category":"Erotische- and Escortediensten",
    "sg:phone":"+32 14 51 99 50",
    "sg:postcode":"2288",
    "sg:province":"Antwerpen",
    "wof:name":"Jill, Nina, Babs, Noeki",
    "wof:placetype":"venue"
},
  "geometry": {"coordinates":[4.736869812,51.1619186401],"type":"Point"}
}