{
  "type": "Feature",
  "properties": {
    "iso:country":"BE",
    "sg:address":"Molenstraat 73",
    "sg:city":"Dilbeek",
    "sg:orig_category":"M\u00e9decins and sp\u00e9cialistes",
    "sg:phone":"+32 2 582 63 84",
    "sg:postcode":"1700",
    "sg:province":"Vlaams-Brabant",
    "wof:name":"Rudolf Steenwegen",
    "wof:placetype":"venue"
},
  "geometry": {"coordinates":[4.2074460983,50.8659362793],"type":"Point"}
}