{
  "type": "Feature",
  "properties": {
    "iso:country":"BE",
    "sg:address":"Oostendesteenweg 8",
    "sg:city":"Ichtegem",
    "sg:classifiers":[
        {
            "category":"Cafe",
            "type":"Food & Drink"
        }
    ],
    "sg:phone":"+32 51 58 84 59",
    "sg:postcode":"8480",
    "sg:province":"West-Vlaanderen",
    "sg:tags":[
        "caf\u00e9s"
    ],
    "wof:name":"Annie Demeulenaere",
    "wof:placetype":"venue"
},
  "geometry": {"coordinates":[3.0312590599,51.1020278931],"type":"Point"}
}