{
  "type": "Feature",
  "properties": {
    "iso:country":"BE",
    "sg:address":"Rue De La Terre \u00e0 Briques 14",
    "sg:city":"Tournai (blandain - Hertain)",
    "sg:orig_category":"Non-Classified Establishments",
    "sg:phone":"+32 69 84 26 28",
    "sg:postcode":"7522",
    "sg:province":"Hainaut",
    "wof:name":"Uni-veg Agro Belgique Sa",
    "wof:placetype":"venue"
},
  "geometry": {"coordinates":[3.3004500866,50.6229057312],"type":"Point"}
}