{
  "type": "Feature",
  "properties": {
    "iso:country":"BE",
    "sg:address":"Place Du Brguinage 4",
    "sg:city":"Mons",
    "sg:orig_category":"Sportcentra",
    "sg:phone":"+32 65 84 08 25",
    "sg:postcode":"7000",
    "sg:province":"Hainaut",
    "wof:name":"Centre Shikantaza",
    "wof:placetype":"venue"
},
  "geometry": {"coordinates":[3.9522509575,50.4547271729],"type":"Point"}
}