{
  "type": "Feature",
  "properties": {
    "iso:country":"BE",
    "sg:address":"Tramstraat 17",
    "sg:city":"Riemst",
    "sg:orig_category":"Woningbouw",
    "sg:phone":"+32 12 45 26 15",
    "sg:postcode":"3770",
    "sg:province":"Limburg",
    "wof:name":"Young Budget Homes",
    "wof:placetype":"venue"
},
  "geometry": {"coordinates":[5.6055431366,50.8117218018],"type":"Point"}
}