{
  "type": "Feature",
  "properties": {
    "iso:country":"BE",
    "sg:address":"Avenue Prince De Li\u00c8ge 56",
    "sg:city":"Namur",
    "sg:orig_category":"Verbruikerskredietinstellingen",
    "sg:phone":"+32 81 31 23 29",
    "sg:postcode":"5100",
    "sg:province":"Namur",
    "wof:name":"Crefibel",
    "wof:placetype":"venue"
},
  "geometry": {"coordinates":[4.8713750839,50.4566345215],"type":"Point"}
}