{
  "type": "Feature",
  "properties": {
    "addr:full":"Broekhoven 28 Herentals (morkhoven) Antwerpen 2200",
    "addr:housenumber":"28",
    "addr:postcode":"2200",
    "addr:street":"Broekhoven",
    "iso:country":"BE",
    "sg:address":"Broekhoven 28",
    "sg:city":"Herentals (morkhoven)",
    "sg:orig_category":"Non-Classified Establishments",
    "sg:phone":"+32 14 26 05 50",
    "sg:postcode":"2200",
    "sg:province":"Antwerpen",
    "wof:name":"Lindehof (het)",
    "wof:placetype":"venue"
},
  "geometry": {"coordinates":[4.8242330551,51.1043777466],"type":"Point"}
}