{
  "type": "Feature",
  "properties": {
    "addr:full":"Heidelaan 70 Sint-genesius-rode/rhode-saint-gen\u00c8se Vlaams-Brabant 1640",
    "addr:housenumber":"70",
    "addr:postcode":"1640",
    "addr:street":"Heidelaan",
    "iso:country":"BE",
    "sg:address":"Heidelaan 70",
    "sg:city":"Sint-genesius-rode/rhode-saint-gen\u00c8se",
    "sg:orig_category":"Artsen and specialisten",
    "sg:phone":"+32 2 380 33 30",
    "sg:postcode":"1640",
    "sg:province":"Vlaams-Brabant",
    "wof:name":"Roland Bernard",
    "wof:placetype":"venue"
},
  "geometry": {"coordinates":[4.3239030838,50.7283058167],"type":"Point"}
}