{
  "type": "Feature",
  "properties": {
    "addr:full":"58 Rue Des Combattants 1450 Chastre 58",
    "addr:housenumber":"58;58",
    "addr:postcode":"1450",
    "addr:street":"Rue Des Combattants",
    "iso:country":"BE",
    "sg:address":"58",
    "sg:city":"Rue Des Combattants 1450 Chastre",
    "sg:classifiers":[
        {
            "category":"Professional",
            "subcategory":"Engineering",
            "type":"Services"
        }
    ],
    "sg:phone":"+32 10 65 79 27",
    "sg:postcode":"58",
    "sg:tags":[
        "machine",
        "-",
        "mechanical"
    ],
    "wof:name":"Ets Denis Legrand Sa",
    "wof:placetype":"venue"
},
  "geometry": {"coordinates":[4.6497349739,50.6182518005],"type":"Point"}
}