{
  "type": "Feature",
  "properties": {
    "addr:full":"Itali\u00cblei 213b13 Antwerpen Antwerpen 2000",
    "addr:housenumber":"213b13",
    "addr:postcode":"2000",
    "addr:street":"Italie\u0308Lei",
    "iso:country":"BE",
    "sg:address":"Itali\u00cblei 213b13",
    "sg:city":"Antwerpen",
    "sg:orig_category":"R\u00e9alisation de programmes and logiciels",
    "sg:phone":"+32 3 232 15 39",
    "sg:postcode":"2000",
    "sg:province":"Antwerpen",
    "wof:name":"Via Futura",
    "wof:placetype":"venue"
},
  "geometry": {"coordinates":[4.4169998169,51.2214660645],"type":"Point"}
}