{
  "type": "Feature",
  "properties": {
    "iso:country":"BE",
    "sg:address":"Kerzestraat 5",
    "sg:city":"Rotselaar",
    "sg:orig_category":"Ordinateurs and \u00e9quipement informatique",
    "sg:phone":"+32 16 58 22 02",
    "sg:postcode":"3111",
    "sg:province":"Vlaams-Brabant",
    "wof:name":"Cassa",
    "wof:placetype":"venue"
},
  "geometry": {"coordinates":[4.7577390671,50.9508056641],"type":"Point"}
}