{
  "type": "Feature",
  "properties": {
    "iso:country":"BE",
    "sg:address":"Zeedijk",
    "sg:city":"Blankenberge",
    "sg:orig_category":"Vakantiehuizen",
    "sg:phone":"+32 59 50 31 12",
    "sg:postcode":"8370",
    "sg:province":"West-Vlaanderen",
    "wof:name":"Hof Ter Duinen",
    "wof:placetype":"venue"
},
  "geometry": {"coordinates":[3.1381599903,51.3186340332],"type":"Point"}
}