{
  "type": "Feature",
  "properties": {
    "iso:country":"BE",
    "sg:address":"Rue Mean 269",
    "sg:city":"Grace-berleur",
    "sg:classifiers":[
        {
            "category":"Health Services",
            "subcategory":"Doctor",
            "type":"Services"
        }
    ],
    "sg:postcode":"4460",
    "sg:province":"Li\u00e8ge",
    "sg:tags":[
        "medicinephysicians",
        "surgeon"
    ],
    "wof:name":"Guillaume-neuville",
    "wof:placetype":"venue"
},
  "geometry": {"coordinates":[5.4707832336,50.6321029663],"type":"Point"}
}