{
  "type": "Feature",
  "properties": {
    "iso:country":"BE",
    "sg:address":"Rue L\u00c9opold 39",
    "sg:city":"Li\u00c8ge",
    "sg:classifiers":[
        {
            "category":"Personal",
            "subcategory":"Beauty Salon",
            "type":"Services"
        }
    ],
    "sg:phone":"+32 4 223 30 33",
    "sg:postcode":"4000",
    "sg:province":"Li\u00e8ge",
    "sg:tags":[
        "de",
        "coiffure"
    ],
    "wof:name":"Coiffure C.r.",
    "wof:placetype":"venue"
},
  "geometry": {"coordinates":[5.577475071,50.6440315247],"type":"Point"}
}