{
  "type": "Feature",
  "properties": {
    "addr:full":"Bevrstraat 19 Geraardsbergen Oost-Vlaanderen 9500",
    "addr:housenumber":"19",
    "addr:postcode":"9500",
    "addr:street":"Bevrstraat",
    "iso:country":"BE",
    "sg:address":"Bevrstraat 19",
    "sg:city":"Geraardsbergen",
    "sg:orig_category":"Informaticaconsulenten",
    "sg:phone":"+32 474 76 98 66",
    "sg:postcode":"9500",
    "sg:province":"Oost-Vlaanderen",
    "wof:name":"Datos It Solutions",
    "wof:placetype":"venue"
},
  "geometry": {"coordinates":[3.8843801022,50.7716445923],"type":"Point"}
}