{
  "type": "Feature",
  "properties": {
    "iso:country":"BE",
    "sg:address":"Kruisstraat 38",
    "sg:city":"Laakdal",
    "sg:orig_category":"Passagiersvervoer over de weg Reisbureaus",
    "sg:phone":"+32 14 84 01 82",
    "sg:postcode":"2431",
    "sg:province":"Antwerpen",
    "wof:name":"De Wijngaard",
    "wof:placetype":"venue"
},
  "geometry": {"coordinates":[4.9792909622,51.0646591187],"type":"Point"}
}