{
  "type": "Feature",
  "properties": {
    "iso:country":"BE",
    "sg:address":"Hundelingenstraat 42",
    "sg:city":"Gingelom (jeuk)",
    "sg:classifiers":[
        {
            "category":"Travel",
            "subcategory":"Hotels & Motels",
            "type":"Entertainment"
        }
    ],
    "sg:phone":"+32 11 48 56 94",
    "sg:postcode":"3890",
    "sg:province":"Limburg",
    "wof:name":"Clos Saint Georges",
    "wof:placetype":"venue"
},
  "geometry": {"coordinates":[5.2065591812,50.7408676147],"type":"Point"}
}