{
  "type": "Feature",
  "properties": {
    "addr:full":"Ommegangstraat 79 Izegem West-Vlaanderen 8870",
    "addr:housenumber":"79",
    "addr:postcode":"8870",
    "addr:street":"Ommegangstraat",
    "iso:country":"BE",
    "sg:address":"Ommegangstraat 79",
    "sg:city":"Izegem",
    "sg:orig_category":"S\u00e9curit\u00e9 sociale",
    "sg:phone":"+32 51 31 16 27",
    "sg:postcode":"8870",
    "sg:province":"West-Vlaanderen",
    "wof:name":"Onafhank. Ziekenfonds 503",
    "wof:placetype":"venue"
},
  "geometry": {"coordinates":[3.2088999748,50.9153060913],"type":"Point"}
}