{
  "type": "Feature",
  "properties": {
    "addr:full":"Rue Saint-martin 37 Merbes-le-ch\u00c2teau Hainaut 6567",
    "addr:housenumber":"37",
    "addr:postcode":"6567",
    "addr:street":"Rue Saint-Martin",
    "iso:country":"BE",
    "sg:address":"Rue Saint-martin 37",
    "sg:city":"Merbes-le-ch\u00c2teau",
    "sg:orig_category":"M\u00e9decins and sp\u00e9cialistes",
    "sg:phone":"+32 71 55 70 70",
    "sg:postcode":"6567",
    "sg:province":"Hainaut",
    "wof:name":"J.m. Vreux",
    "wof:placetype":"venue"
},
  "geometry": {"coordinates":[4.1587147713,50.3233451843],"type":"Point"}
}