{
  "type": "Feature",
  "properties": {
    "addr:full":"Groeningelaan 42ba Kortrijk West-Vlaanderen 8500",
    "addr:housenumber":"42ba",
    "addr:postcode":"8500",
    "addr:street":"Groeningelaan",
    "iso:country":"BE",
    "sg:address":"Groeningelaan 42ba",
    "sg:city":"Kortrijk",
    "sg:orig_category":"Enseignement maternel and primaire",
    "sg:phone":"+32 56 22 66 39",
    "sg:postcode":"8500",
    "sg:province":"West-Vlaanderen",
    "wof:name":"Vrije Lagere School",
    "wof:placetype":"venue"
},
  "geometry": {"coordinates":[3.2762811184,50.8278961182],"type":"Point"}
}