{
  "type": "Feature",
  "properties": {
    "addr:full":"Bochtenstraat 6 Rijkevorsel Antwerpen 2310",
    "addr:housenumber":"6",
    "addr:postcode":"2310",
    "addr:street":"Bochtenstraat",
    "iso:country":"BE",
    "sg:address":"Bochtenstraat 6",
    "sg:city":"Rijkevorsel",
    "sg:orig_category":"Auto-\u00e9coles",
    "sg:phone":"+32 3 341 96 39",
    "sg:postcode":"2310",
    "sg:province":"Antwerpen",
    "wof:name":"Autorijschool U.v.a.",
    "wof:placetype":"venue"
},
  "geometry": {"coordinates":[4.7618918419,51.3482246399],"type":"Point"}
}