{
  "type": "Feature",
  "properties": {
    "addr:full":"Wulfsdam 10 Ledegem West-Vlaanderen 8880",
    "addr:housenumber":"10",
    "addr:postcode":"8880",
    "addr:street":"Wulfsdam",
    "iso:country":"BE",
    "sg:address":"Wulfsdam 10",
    "sg:city":"Ledegem",
    "sg:orig_category":"Elektrische installaties voor woningen",
    "sg:phone":"+32 56 50 44 03",
    "sg:postcode":"8880",
    "sg:province":"West-Vlaanderen",
    "wof:name":"Jose Vandamme",
    "wof:placetype":"venue"
},
  "geometry": {"coordinates":[3.1333448887,50.8565864563],"type":"Point"}
}