{
  "type": "Feature",
  "properties": {
    "addr:full":"Ninovesteenweg 190 Box 1 Aalst (erembodegem) Oost-Vlaanderen 9320",
    "addr:housenumber":"190;1",
    "addr:postcode":"9320",
    "addr:street":"Ninovesteenweg;Box",
    "iso:country":"BE",
    "sg:address":"Ninovesteenweg 190 Box 1",
    "sg:city":"Aalst (erembodegem)",
    "sg:classifiers":[
        {
            "category":"Banks & Credit Unions",
            "subcategory":"Investment Brokerage",
            "type":"Services"
        }
    ],
    "sg:phone":"+32 53 75 06 51",
    "sg:postcode":"9320",
    "sg:province":"Oost-Vlaanderen",
    "sg:tags":[
        "auditor"
    ],
    "wof:name":"Moens, Van Pethegem & Co",
    "wof:placetype":"venue"
},
  "geometry": {"coordinates":[4.0553851128,50.9209976196],"type":"Point"}
}