{
  "type": "Feature",
  "properties": {
    "addr:full":"Place Verte 17 Dour Hainaut 7370",
    "addr:housenumber":"17",
    "addr:postcode":"7370",
    "addr:street":"Place Verte;Hainaut",
    "iso:country":"BE",
    "sg:address":"Place Verte 17",
    "sg:city":"Dour",
    "sg:classifiers":[
        {
            "category":"Shopping",
            "subcategory":"Clothing, Apparel, & Fashions",
            "type":"Retail Goods"
        }
    ],
    "sg:phone":"+32 65 63 39 54",
    "sg:postcode":"7370",
    "sg:province":"Hainaut",
    "sg:tags":[
        "boutique"
    ],
    "wof:name":"Pyramides",
    "wof:placetype":"venue"
},
  "geometry": {"coordinates":[3.7876400948,50.3985137939],"type":"Point"}
}