{
  "type": "Feature",
  "properties": {
    "iso:country":"BE",
    "sg:address":"Peperdam 10",
    "sg:city":"Beveren (vrasene)",
    "sg:classifiers":[
        {
            "category":"Parking",
            "subcategory":"Lot",
            "type":"Transportation"
        }
    ],
    "sg:phone":"+32 3 775 16 84",
    "sg:postcode":"9120",
    "sg:province":"Oost-Vlaanderen",
    "sg:tags":[
        "parking-places",
        "laying-out"
    ],
    "wof:name":"Hollanders G",
    "wof:placetype":"venue"
},
  "geometry": {"coordinates":[4.255628109,51.2121772766],"type":"Point"}
}