{
  "type": "Feature",
  "properties": {
    "addr:full":"Hoogstraat 44 Lebbeke Oost-Vlaanderen 9280",
    "addr:housenumber":"44",
    "addr:postcode":"9280",
    "addr:street":"Hoogstraat",
    "iso:country":"BE",
    "sg:address":"Hoogstraat 44",
    "sg:city":"Lebbeke",
    "sg:classifiers":[
        {
            "category":"Restaurant",
            "type":"Food & Drink"
        }
    ],
    "sg:phone":"+32 53 77 64 83",
    "sg:postcode":"9280",
    "sg:province":"Oost-Vlaanderen",
    "sg:tags":[
        "caf\u00e9s"
    ],
    "wof:name":"Taverne 't Moleken",
    "wof:placetype":"venue"
},
  "geometry": {"coordinates":[4.0912461281,50.98777771],"type":"Point"}
}