{
  "type": "Feature",
  "properties": {
    "iso:country":"BE",
    "sg:address":"Geuzestraat 46",
    "sg:city":"Knesselare",
    "sg:orig_category":"Non-Classified Establishments",
    "sg:phone":"+32 9 375 26 43",
    "sg:postcode":"9910",
    "sg:province":"Oost-Vlaanderen",
    "wof:name":"No Halm",
    "wof:placetype":"venue"
},
  "geometry": {"coordinates":[3.4148681164,51.1540908813],"type":"Point"}
}