{
  "type": "Feature",
  "properties": {
    "iso:country":"BE",
    "sg:address":"Rue Vallaville 37",
    "sg:city":"Lens",
    "sg:orig_category":"Poissonniers and \u00e9caillers",
    "sg:phone":"+32 65 22 62 05",
    "sg:postcode":"7870",
    "sg:province":"Hainaut",
    "wof:name":"Maison Le Turbotin",
    "wof:placetype":"venue"
},
  "geometry": {"coordinates":[3.9016969204,50.5578117371],"type":"Point"}
}