{
  "type": "Feature",
  "properties": {
    "iso:country":"BE",
    "sg:address":"Geraardsbergsesteenweg 30",
    "sg:city":"Oosterzele",
    "sg:orig_category":"Gespecialiseerde residenti\u00eble bouw",
    "sg:phone":"+32 9 362 47 96",
    "sg:postcode":"9860",
    "sg:province":"Oost-Vlaanderen",
    "wof:name":"Boudewijn Saegerman",
    "wof:placetype":"venue"
},
  "geometry": {"coordinates":[3.8061490059,50.9648780823],"type":"Point"}
}