{
  "type": "Feature",
  "properties": {
    "iso:country":"BE",
    "sg:address":"Rue De Villers 26",
    "sg:city":"Court-saint-etienne",
    "sg:orig_category":"Enseignement maternel and primaire",
    "sg:phone":"+32 10 61 31 35",
    "sg:postcode":"1490",
    "sg:province":"Brabant Wallon",
    "wof:name":"Ecole Matern. Communale",
    "wof:placetype":"venue"
},
  "geometry": {"coordinates":[4.5375947952,50.6109886169],"type":"Point"}
}