{
  "type": "Feature",
  "properties": {
    "iso:country":"BE",
    "sg:address":"Route De Lennik 398",
    "sg:city":"Anderlecht",
    "sg:orig_category":"Alimentation sp\u00e9cialis\u00e9e. M\u00e9decines alternatives",
    "sg:phone":"+32 2 527 36 69",
    "sg:postcode":"1070",
    "sg:province":"Bruxelles-Capitale",
    "wof:name":"Natura Form",
    "wof:placetype":"venue"
},
  "geometry": {"coordinates":[4.2807369232,50.817111969],"type":"Point"}
}