{
  "type": "Feature",
  "properties": {
    "iso:country":"BE",
    "sg:address":"Noordlaan 31",
    "sg:city":"Dendermonde",
    "sg:orig_category":"Rechtbanken",
    "sg:phone":"+32 52 25 96 30",
    "sg:postcode":"9200",
    "sg:province":"Oost-Vlaanderen",
    "wof:name":"Arbeidsrechtbank",
    "wof:placetype":"venue"
},
  "geometry": {"coordinates":[4.099219799,51.0331001282],"type":"Point"}
}