{
  "type": "Feature",
  "properties": {
    "iso:country":"BE",
    "sg:address":"Marcel Thirylaan 216",
    "sg:city":"Sint-lambrechts-woluwe/woluwe-saint-lambert",
    "sg:orig_category":"Belastingconsulenten Diverse juridische dienstverlening",
    "sg:phone":"+32 2 710 42 11",
    "sg:postcode":"1200",
    "sg:province":"Bruxelles-Capitale",
    "wof:name":"Pricewaterhousecoopers",
    "wof:placetype":"venue"
},
  "geometry": {"coordinates":[4.4321532249,50.8567886353],"type":"Point"}
}