{
  "type": "Feature",
  "properties": {
    "iso:country":"BE",
    "sg:address":"Gentsesteenweg 100-102",
    "sg:city":"Aalst",
    "sg:classifiers":[
        {
            "category":"Restaurant",
            "type":"Food & Drink"
        }
    ],
    "sg:phone":"+32 53 21 27 97",
    "sg:postcode":"9300",
    "sg:province":"Oost-Vlaanderen",
    "wof:name":"Koot D\u00b4alost",
    "wof:placetype":"venue"
},
  "geometry": {"coordinates":[4.0224781036,50.9383583069],"type":"Point"}
}