{
  "type": "Feature",
  "properties": {
    "addr:full":"Rue De Saint-donat 8 Mettet Namur 5640",
    "addr:housenumber":"8",
    "addr:postcode":"5640",
    "addr:street":"Rue De Saint-Donat",
    "iso:country":"BE",
    "sg:address":"Rue De Saint-donat 8",
    "sg:city":"Mettet",
    "sg:classifiers":[
        {
            "category":"Autos & Motor Vehicles",
            "subcategory":"Auto Supplies",
            "type":"Retail Goods"
        }
    ],
    "sg:phone":"+32 71 72 80 30",
    "sg:postcode":"5640",
    "sg:province":"Namur",
    "sg:tags":[
        "automobile",
        "absorber",
        "shock",
        "-"
    ],
    "wof:name":"Sabatino",
    "wof:placetype":"venue"
},
  "geometry": {"coordinates":[4.6524600983,50.3029212952],"type":"Point"}
}