{
  "type": "Feature",
  "properties": {
    "addr:full":"Vredeborgstraat 12 Boechout Antwerpen 2530",
    "addr:housenumber":"12",
    "addr:postcode":"2530",
    "addr:street":"Vredeborgstraat",
    "iso:country":"BE",
    "sg:address":"Vredeborgstraat 12",
    "sg:city":"Boechout",
    "sg:orig_category":"M\u00e9decins and sp\u00e9cialistes",
    "sg:phone":"+32 3 455 14 85",
    "sg:postcode":"2530",
    "sg:province":"Antwerpen",
    "wof:name":"M. De Naegel",
    "wof:placetype":"venue"
},
  "geometry": {"coordinates":[4.4931879044,51.1569519043],"type":"Point"}
}