{
  "type": "Feature",
  "properties": {
    "iso:country":"BE",
    "sg:address":"Place Toussaint Balthasart 1",
    "sg:city":"Chaudfontaine (vaux-sous-ch\u00e8vremont)",
    "sg:classifiers":[
        {
            "category":"Health Services",
            "subcategory":"Health Practitioner",
            "type":"Services"
        }
    ],
    "sg:phone":"+32 4 367 13 79",
    "sg:postcode":"4051",
    "sg:province":"Li\u00e8ge",
    "sg:tags":[
        "osteopath"
    ],
    "wof:name":"Dehan M D.o.",
    "wof:placetype":"venue"
},
  "geometry": {"coordinates":[5.6280097961,50.6061592102],"type":"Point"}
}