{
  "type": "Feature",
  "properties": {
    "iso:country":"BE",
    "sg:address":"Touwslagerstr 8",
    "sg:city":"Zele",
    "sg:classifiers":[
        {
            "category":"Manufacturing",
            "subcategory":"Wood Products",
            "type":"Manufacturing & Wholesale Goods"
        }
    ],
    "sg:phone":"+32 52 44 54 40",
    "sg:postcode":"9240",
    "sg:province":"Oost-Vlaanderen",
    "sg:tags":[
        "professional",
        "household",
        "furniture"
    ],
    "wof:name":"Gloria Construct Nv",
    "wof:placetype":"venue"
},
  "geometry": {"coordinates":[4.0534739494,51.0685348511],"type":"Point"}
}