{
  "type": "Feature",
  "properties": {
    "iso:country":"BE",
    "sg:address":"Chauss\u00e9e De Waremme 4-c",
    "sg:city":"Wanze (antheit)",
    "sg:classifiers":[
        {
            "category":"Professional",
            "subcategory":"Accounting & Tax Preparation",
            "type":"Services"
        }
    ],
    "sg:phone":"+32 85 32 84 90",
    "sg:postcode":"4520",
    "sg:province":"Li\u00e8ge",
    "sg:tags":[
        "bookkeeper"
    ],
    "wof:name":"Claus G",
    "wof:placetype":"venue"
},
  "geometry": {"coordinates":[5.2633690834,50.5505256653],"type":"Point"}
}