{
  "type": "Feature",
  "properties": {
    "iso:country":"BE",
    "sg:address":"Wielendaalstraat 58",
    "sg:city":"Brakel",
    "sg:orig_category":"Epiceries",
    "sg:phone":"+32 55 42 22 21",
    "sg:postcode":"9660",
    "sg:province":"Oost-Vlaanderen",
    "wof:name":"Van Wielendaele",
    "wof:placetype":"venue"
},
  "geometry": {"coordinates":[3.7620449066,50.8052978516],"type":"Point"}
}