{
  "type": "Feature",
  "properties": {
    "iso:country":"BE",
    "sg:address":"Wijnendalestraat 182",
    "sg:city":"Diksmuide (beerst)",
    "sg:classifiers":[
        {
            "category":"Farming",
            "subcategory":"Farm & Veterinary Services",
            "type":"Manufacturing & Wholesale Goods"
        }
    ],
    "sg:phone":"+32 51 50 10 79",
    "sg:postcode":"8600",
    "sg:province":"West-Vlaanderen",
    "sg:tags":[
        "agricultural",
        "contractor"
    ],
    "wof:name":"Vansteelandt O",
    "wof:placetype":"venue"
},
  "geometry": {"coordinates":[2.9137918949,51.0625953674],"type":"Point"}
}