{
  "type": "Feature",
  "properties": {
    "addr:full":"Olenseweg 328 Westerlo Antwerpen 2260",
    "addr:housenumber":"328",
    "addr:postcode":"2260",
    "addr:street":"Olenseweg",
    "iso:country":"BE",
    "sg:address":"Olenseweg 328",
    "sg:city":"Westerlo",
    "sg:classifiers":[
        {
            "category":"Restaurant",
            "type":"Food & Drink"
        }
    ],
    "sg:phone":"+32 14 26 54 06",
    "sg:postcode":"2260",
    "sg:province":"Antwerpen",
    "wof:name":"Bakkershof Taverne",
    "wof:placetype":"venue"
},
  "geometry": {"coordinates":[4.8694601059,51.10546875],"type":"Point"}
}