{
  "type": "Feature",
  "properties": {
    "iso:country":"BE",
    "sg:address":"Kerkhofstraat 8",
    "sg:city":"Roosdaal",
    "sg:classifiers":[
        {
            "category":"Wholesale",
            "subcategory":"Fruits & Vegetables",
            "type":"Manufacturing & Wholesale Goods"
        }
    ],
    "sg:phone":"+32 54 33 99 40",
    "sg:postcode":"1760",
    "sg:province":"Vlaams-Brabant",
    "sg:tags":[
        "whol",
        "-"
    ],
    "wof:name":"Valckenier Marcel Fruithandel",
    "wof:placetype":"venue"
},
  "geometry": {"coordinates":[4.0744271278,50.8435707092],"type":"Point"}
}