{
  "type": "Feature",
  "properties": {
    "addr:full":"Dorpsstraat 1 Wetteren Oost-Vlaanderen 9230",
    "addr:housenumber":"1",
    "addr:postcode":"9230",
    "addr:street":"Dorpsstraat",
    "iso:country":"BE",
    "sg:address":"Dorpsstraat 1",
    "sg:city":"Wetteren",
    "sg:classifiers":[
        {
            "category":"Cafe",
            "type":"Food & Drink"
        }
    ],
    "sg:phone":"+32 9 252 16 30",
    "sg:postcode":"9230",
    "sg:province":"Oost-Vlaanderen",
    "sg:tags":[
        "caf\u00e9s"
    ],
    "wof:name":"Parochiale Werken St.anna",
    "wof:placetype":"venue"
},
  "geometry": {"coordinates":[3.8692989349,50.9719467163],"type":"Point"}
}