{
  "type": "Feature",
  "properties": {
    "addr:full":"De Smet De Naeyerlaan 149 Blankenberge West-Vlaanderen 8370",
    "addr:housenumber":"149",
    "addr:postcode":"8370",
    "addr:street":"De Smet De Naeyerlaan",
    "iso:country":"BE",
    "sg:address":"De Smet De Naeyerlaan 149",
    "sg:city":"Blankenberge",
    "sg:orig_category":"Autombile concessionaires",
    "sg:phone":"+32 50 41 24 86",
    "sg:postcode":"8370",
    "sg:province":"West-Vlaanderen",
    "wof:name":"Gar Universel Bvba",
    "wof:placetype":"venue"
},
  "geometry": {"coordinates":[3.1297419071,51.3116607666],"type":"Point"}
}