{
  "type": "Feature",
  "properties": {
    "iso:country":"BE",
    "sg:address":"Liersesteenweg 177",
    "sg:city":"Begijnendijk",
    "sg:orig_category":"Journaux",
    "sg:phone":"+32 16 53 14 47",
    "sg:postcode":"3130",
    "sg:province":"Vlaams-Brabant",
    "wof:name":"Kranten Nicole",
    "wof:placetype":"venue"
},
  "geometry": {"coordinates":[4.7925601006,51.0207901001],"type":"Point"}
}