{
  "type": "Feature",
  "properties": {
    "iso:country":"BE",
    "sg:address":"Rue De La Bruy\u00e8re 46",
    "sg:city":"Sambreville (auvelais)",
    "sg:classifiers":[
        {
            "category":"Building & Trades",
            "subcategory":"Construction",
            "type":"Services"
        }
    ],
    "sg:phone":"+32 71 74 41 94",
    "sg:postcode":"5060",
    "sg:province":"Namur",
    "sg:tags":[
        "installation",
        "-",
        "central",
        "heating"
    ],
    "wof:name":"Van Den Bergh H",
    "wof:placetype":"venue"
},
  "geometry": {"coordinates":[4.6335711479,50.4375686646],"type":"Point"}
}