{
  "type": "Feature",
  "properties": {
    "addr:full":"Chemin Des Cressonni\u00c8res 16 Chaumont-gistoux Brabant Wallon 1325",
    "addr:housenumber":"16",
    "addr:postcode":"1325",
    "addr:street":"Chemin Des Cressonnie\u0300Res",
    "iso:country":"BE",
    "sg:address":"Chemin Des Cressonni\u00c8res 16",
    "sg:city":"Chaumont-gistoux",
    "sg:orig_category":"Astrologen, grafologen and mediums Immobili\u00ebnkantoren Werk and personeelsselectie",
    "sg:phone":"+32 10 68 13 63",
    "sg:postcode":"1325",
    "sg:province":"Brabant Wallon",
    "wof:name":"Promexpo",
    "wof:placetype":"venue"
},
  "geometry": {"coordinates":[4.6935591698,50.6752204895],"type":"Point"}
}