{
  "type": "Feature",
  "properties": {
    "addr:full":"Chauss\u00c9e De Malines 71 Wezembeek-oppem Vlaams-Brabant 1970",
    "addr:housenumber":"71",
    "addr:postcode":"1970",
    "addr:street":"Chausse\u0301E De Malines",
    "iso:country":"BE",
    "sg:address":"Chauss\u00c9e De Malines 71",
    "sg:city":"Wezembeek-oppem",
    "sg:orig_category":"Instituts de beaut\u00e9",
    "sg:phone":"+32 2 731 85 62",
    "sg:postcode":"1970",
    "sg:province":"Vlaams-Brabant",
    "wof:name":"Institut Sveltesse",
    "wof:placetype":"venue"
},
  "geometry": {"coordinates":[4.5000610352,50.8451156616],"type":"Point"}
}