{
  "type": "Feature",
  "properties": {
    "addr:full":"Rue De P\u00e2turages 71 Qu\u00e9vy (givry) Hainaut 7041",
    "addr:housenumber":"71",
    "addr:postcode":"7041",
    "addr:street":"Rue De Pa\u0302Turages",
    "iso:country":"BE",
    "sg:address":"Rue De P\u00e2turages 71",
    "sg:city":"Qu\u00e9vy (givry)",
    "sg:classifiers":[
        {
            "category":"Farming",
            "subcategory":"Farm & Veterinary Services",
            "type":"Manufacturing & Wholesale Goods"
        }
    ],
    "sg:phone":"+32 65 58 63 02",
    "sg:postcode":"7041",
    "sg:province":"Hainaut",
    "sg:tags":[
        "agricultural",
        "contractor"
    ],
    "wof:name":"Hulin R",
    "wof:placetype":"venue"
},
  "geometry": {"coordinates":[4.0278129578,50.3789405823],"type":"Point"}
}