{
  "type": "Feature",
  "properties": {
    "addr:full":"Ren\u00c9 Gobertlaan 31 Ukkel/uccle Bruxelles-Capitale 1180",
    "addr:housenumber":"31",
    "addr:postcode":"1180",
    "addr:street":"Rene\u0301 Gobertlaan;/",
    "iso:country":"BE",
    "sg:address":"Ren\u00c9 Gobertlaan 31",
    "sg:city":"Ukkel/uccle",
    "sg:orig_category":"Diverse opleidingen and onderwijs",
    "sg:phone":"+32 2 374 27 08",
    "sg:postcode":"1180",
    "sg:province":"Bruxelles-Capitale",
    "wof:name":"Kid\u00b4s Computer Club",
    "wof:placetype":"venue"
},
  "geometry": {"coordinates":[4.3683800697,50.8080024719],"type":"Point"}
}