{
  "type": "Feature",
  "properties": {
    "addr:full":"Rue Devant Les Grands Moulins 84 Malmedy Li\u00e8ge 4960",
    "addr:housenumber":"84",
    "addr:postcode":"4960",
    "addr:street":"Rue Devant Les Grands Moulins",
    "iso:country":"BE",
    "sg:address":"Rue Devant Les Grands Moulins 84",
    "sg:city":"Malmedy",
    "sg:classifiers":[
        {
            "category":"Professional",
            "subcategory":"Art Services",
            "type":"Services"
        }
    ],
    "sg:phone":"+32 80 33 96 01",
    "sg:postcode":"4960",
    "sg:province":"Li\u00e8ge",
    "sg:tags":[
        "graphic",
        "designer"
    ],
    "wof:name":"Warnon D",
    "wof:placetype":"venue"
},
  "geometry": {"coordinates":[6.0281867981,50.4307899475],"type":"Point"}
}