{
  "type": "Feature",
  "properties": {
    "iso:country":"BE",
    "sg:address":"Galgstraat 269",
    "sg:city":"Sint-pieters-leeuw",
    "sg:classifiers":[
        {
            "category":"Fast Food",
            "type":"Food & Drink"
        }
    ],
    "sg:phone":"+32 2 657 12 87",
    "sg:postcode":"1600",
    "sg:province":"Vlaams-Brabant",
    "sg:tags":[
        "\u00c0",
        "emporter",
        "restaurants"
    ],
    "wof:name":"Friet House",
    "wof:placetype":"venue"
},
  "geometry": {"coordinates":[4.2488040924,50.7750320435],"type":"Point"}
}