{
  "type": "Feature",
  "properties": {
    "addr:full":"Benediktinessenstraat 10-12 Menen West-Vlaanderen 8930",
    "addr:postcode":"10-12;8930",
    "addr:street":"Benediktinessenstraat",
    "iso:country":"BE",
    "sg:address":"Benediktinessenstraat 10-12",
    "sg:city":"Menen",
    "sg:classifiers":[
        {
            "category":"Shopping",
            "subcategory":"Musical Instruments",
            "type":"Retail Goods"
        }
    ],
    "sg:phone":"+32 56 51 13 82",
    "sg:postcode":"8930",
    "sg:province":"West-Vlaanderen",
    "sg:tags":[
        "-"
    ],
    "wof:name":"Andriessen Bvba",
    "wof:placetype":"venue"
},
  "geometry": {"coordinates":[3.1238090992,50.7993965149],"type":"Point"}
}