{
  "type": "Feature",
  "properties": {
    "addr:full":"Generaal Eisenhowerlei 47 Antwerpen (borgerhout) Antwerpen 2140",
    "addr:housenumber":"47",
    "addr:postcode":"2140",
    "addr:street":"Generaal Eisenhowerlei",
    "iso:country":"BE",
    "sg:address":"Generaal Eisenhowerlei 47",
    "sg:city":"Antwerpen (borgerhout)",
    "sg:classifiers":[
        {
            "category":"Community Center",
            "subcategory":"Youth",
            "type":"Public Place"
        }
    ],
    "sg:phone":"+32 3 271 07 82",
    "sg:postcode":"2140",
    "sg:province":"Antwerpen",
    "sg:tags":[
        "club"
    ],
    "wof:name":"Jeugdwelzijnswerk Oud-borgerhout Vzw",
    "wof:placetype":"venue"
},
  "geometry": {"coordinates":[4.4332199097,51.2137565613],"type":"Point"}
}