{
  "type": "Feature",
  "properties": {
    "iso:country":"BE",
    "sg:address":"Rue Gr\u00e9try",
    "sg:city":"Li\u00e8ge 1 (li\u00e8ge 2)",
    "sg:classifiers":[
        {
            "category":"Health Services",
            "subcategory":"Nursing And Care Facility",
            "type":"Services"
        }
    ],
    "sg:phone":"+32 4 221 10 10",
    "sg:postcode":"4020",
    "sg:province":"Li\u00e8ge",
    "sg:tags":[
        "safe"
    ],
    "wof:name":"A. Abus Security",
    "wof:placetype":"venue"
},
  "geometry": {"coordinates":[5.5861678123,50.6453857422],"type":"Point"}
}