{
  "type": "Feature",
  "properties": {
    "addr:full":"Chemin Du Puits 12 Bruxelles (uccle) Bruxelles-Capitale 1180",
    "addr:housenumber":"12",
    "addr:postcode":"1180",
    "addr:street":"Chemin Du Puits",
    "iso:country":"BE",
    "sg:address":"Chemin Du Puits 12",
    "sg:city":"Bruxelles (uccle)",
    "sg:classifiers":[
        {
            "category":"Professional",
            "subcategory":"Art Services",
            "type":"Services"
        }
    ],
    "sg:phone":"+32 2 374 15 25",
    "sg:postcode":"1180",
    "sg:province":"Bruxelles-Capitale",
    "sg:tags":[
        "interior",
        "designer"
    ],
    "wof:name":"Martial M",
    "wof:placetype":"venue"
},
  "geometry": {"coordinates":[4.3426737785,50.7855567932],"type":"Point"}
}