{
  "type": "Feature",
  "properties": {
    "addr:full":"Rue De La Pairelle 50 Walcourt Namur 5651",
    "addr:housenumber":"50",
    "addr:postcode":"5651",
    "addr:street":"Rue De La Pairelle",
    "iso:country":"BE",
    "sg:address":"Rue De La Pairelle 50",
    "sg:city":"Walcourt",
    "sg:orig_category":"Onderhoud van kantoor- and computeruitrusting",
    "sg:phone":"+32 71 61 29 98",
    "sg:postcode":"5651",
    "sg:province":"Namur",
    "wof:name":"S\u00c9bastien Ranieri",
    "wof:placetype":"venue"
},
  "geometry": {"coordinates":[4.4262080193,50.2824401855],"type":"Point"}
}