{
  "type": "Feature",
  "properties": {
    "iso:country":"BE",
    "sg:address":"Boterdijk 26",
    "sg:city":"Middelkerke",
    "sg:orig_category":"Rundveehouders Varkenskwekers",
    "sg:phone":"+32 58 23 36 61",
    "sg:postcode":"8434",
    "sg:province":"West-Vlaanderen",
    "wof:name":"Roger Hosten",
    "wof:placetype":"venue"
},
  "geometry": {"coordinates":[2.7569050789,51.1488685608],"type":"Point"}
}