{
  "type": "Feature",
  "properties": {
    "addr:full":"Rue De L'ancienne Potence 32 Doornik Hainaut 7501",
    "addr:housenumber":"32",
    "addr:postcode":"7501",
    "addr:street":"Rue De L'Ancienne Potence;Hainaut",
    "iso:country":"BE",
    "sg:address":"Rue De L'ancienne Potence 32",
    "sg:city":"Doornik",
    "sg:orig_category":"Agences d'exp\u00e9dition",
    "sg:phone":"+32 69 84 52 24",
    "sg:postcode":"7501",
    "sg:province":"Hainaut",
    "wof:name":"Ngd",
    "wof:placetype":"venue"
},
  "geometry": {"coordinates":[3.3389029503,50.6113967896],"type":"Point"}
}