{
  "type": "Feature",
  "properties": {
    "iso:country":"BE",
    "sg:address":"Meester Van Der Borghtstraat 32",
    "sg:city":"Putte",
    "sg:classifiers":[
        {
            "category":"Retail",
            "subcategory":"Veterinary Services",
            "type":"Services"
        }
    ],
    "sg:phone":"+32 15 75 38 00",
    "sg:postcode":"2580",
    "sg:province":"Antwerpen",
    "sg:tags":[
        "veterinarian"
    ],
    "wof:name":"Celis G",
    "wof:placetype":"venue"
},
  "geometry": {"coordinates":[4.6606149673,51.0398216248],"type":"Point"}
}