{
  "type": "Feature",
  "properties": {
    "iso:country":"BE",
    "sg:address":"Rue Isidor Hoton 23",
    "sg:city":"Ath",
    "sg:orig_category":"Notarissen",
    "sg:phone":"+32 68 28 21 76",
    "sg:postcode":"7800",
    "sg:province":"Hainaut",
    "wof:name":"Laurent Barnich",
    "wof:placetype":"venue"
},
  "geometry": {"coordinates":[3.7815039158,50.6328620911],"type":"Point"}
}