{
  "type": "Feature",
  "properties": {
    "addr:full":"Ledegemsestraat 119 Wevelgem (moorsele) West-Vlaanderen 8560",
    "addr:housenumber":"119",
    "addr:postcode":"8560",
    "addr:street":"Ledegemsestraat",
    "iso:country":"BE",
    "sg:address":"Ledegemsestraat 119",
    "sg:city":"Wevelgem (moorsele)",
    "sg:classifiers":[
        {
            "category":"Wholesale",
            "subcategory":"Fruits & Vegetables",
            "type":"Manufacturing & Wholesale Goods"
        }
    ],
    "sg:phone":"+32 56 50 47 92",
    "sg:postcode":"8560",
    "sg:province":"West-Vlaanderen",
    "sg:tags":[
        "whol",
        "-",
        "potato"
    ],
    "wof:name":"Belfraco Holding Nv",
    "wof:placetype":"venue"
},
  "geometry": {"coordinates":[3.1449229717,50.8478012085],"type":"Point"}
}