{
  "type": "Feature",
  "properties": {
    "iso:country":"BE",
    "sg:address":"Darse De Baudour",
    "sg:city":"Saint-ghislain",
    "sg:orig_category":"B\u00e9ton pr\u00eat \u00e0 l'emploi Fab",
    "sg:phone":"+32 65 64 29 01",
    "sg:postcode":"7331",
    "sg:province":"Hainaut",
    "wof:name":"Readymix",
    "wof:placetype":"venue"
},
  "geometry": {"coordinates":[3.8367009163,50.4836997986],"type":"Point"}
}