{
  "type": "Feature",
  "properties": {
    "iso:country":"BE",
    "sg:address":"Rue Du Roi Albert 226",
    "sg:city":"Colfontaine",
    "sg:orig_category":"Herstellingen and onderhoud van auto's",
    "sg:phone":"+32 65 67 17 72",
    "sg:postcode":"7080",
    "sg:province":"Hainaut",
    "wof:name":"Carrosserie Cordaro",
    "wof:placetype":"venue"
},
  "geometry": {"coordinates":[3.9013249874,50.4052352905],"type":"Point"}
}