{
  "type": "Feature",
  "properties": {
    "iso:country":"BE",
    "sg:address":"Noorderlaan 133b12",
    "sg:city":"Antwerpen",
    "sg:orig_category":"Services de t\u00e9l\u00e9communications",
    "sg:phone":"+32 800 57 772",
    "sg:postcode":"2000",
    "sg:province":"Antwerpen",
    "wof:name":"Versatel",
    "wof:placetype":"venue"
},
  "geometry": {"coordinates":[4.4140148163,51.2309379578],"type":"Point"}
}