{
  "type": "Feature",
  "properties": {
    "iso:country":"BE",
    "sg:address":"Steenpoort 26",
    "sg:city":"Kortrijk",
    "sg:orig_category":"Dameskledingzaken",
    "sg:phone":"+32 56 22 38 35",
    "sg:postcode":"8500",
    "sg:province":"West-Vlaanderen",
    "wof:name":"Huis Paris Vienne",
    "wof:placetype":"venue"
},
  "geometry": {"coordinates":[3.270031929,50.8271636963],"type":"Point"}
}