{
  "type": "Feature",
  "properties": {
    "iso:country":"BE",
    "sg:address":"Molenstraat 41",
    "sg:city":"Baarle-hertog",
    "sg:classifiers":[
        {
            "category":"Shopping",
            "subcategory":"Shoes",
            "type":"Retail Goods"
        }
    ],
    "sg:phone":"+32 14 69 02 53",
    "sg:postcode":"2387",
    "sg:province":"Antwerpen",
    "sg:tags":[
        "slipper",
        "-"
    ],
    "wof:name":"Kids Shoes",
    "wof:placetype":"venue"
},
  "geometry": {"coordinates":[4.9322662354,51.4411392212],"type":"Point"}
}