{
  "type": "Feature",
  "properties": {
    "addr:full":"Kortewagenstraat 71 Roeselare West-Vlaanderen 8800",
    "addr:housenumber":"71",
    "addr:postcode":"8800",
    "addr:street":"Kortewagenstraat",
    "iso:country":"BE",
    "sg:address":"Kortewagenstraat 71",
    "sg:city":"Roeselare",
    "sg:orig_category":"Varkenskwekers",
    "sg:phone":"+32 56 50 97 23",
    "sg:postcode":"8800",
    "sg:province":"West-Vlaanderen",
    "wof:name":"Joseph Decancq",
    "wof:placetype":"venue"
},
  "geometry": {"coordinates":[3.1226019859,50.8944473267],"type":"Point"}
}