{
  "type": "Feature",
  "properties": {
    "iso:country":"BE",
    "sg:address":"Brusselsesteenweg 214",
    "sg:city":"Mechelen",
    "sg:orig_category":"Verhuisdiensten",
    "sg:phone":"+32 477 20 11 93",
    "sg:postcode":"2800",
    "sg:province":"Antwerpen",
    "wof:name":"Transport Put",
    "wof:placetype":"venue"
},
  "geometry": {"coordinates":[4.4728169441,51.0146865845],"type":"Point"}
}