{
  "type": "Feature",
  "properties": {
    "addr:full":"Avenue Des Etats-unis 7 Gosselies Hainaut 6041",
    "addr:housenumber":"7",
    "addr:postcode":"6041",
    "addr:street":"Avenue Des Etats-Unis",
    "iso:country":"BE",
    "sg:address":"Avenue Des Etats-unis 7",
    "sg:city":"Gosselies",
    "sg:classifiers":[
        {
            "category":"Utilities",
            "subcategory":"Water",
            "type":"Services"
        }
    ],
    "sg:phone":"+32 71 37 81 70",
    "sg:postcode":"6041",
    "sg:province":"Hainaut",
    "sg:tags":[
        "remediation"
    ],
    "wof:name":"Ibtv S.a.",
    "wof:placetype":"venue"
},
  "geometry": {"coordinates":[4.4470472336,50.4740715027],"type":"Point"}
}