{
  "type": "Feature",
  "properties": {
    "addr:full":"Rue De La R\u00e9sistance 18bis Tournai (kain) Hainaut 7540",
    "addr:housenumber":"18bis",
    "addr:postcode":"7540",
    "addr:street":"Rue De La Re\u0301Sistance",
    "iso:country":"BE",
    "sg:address":"Rue De La R\u00e9sistance 18bis",
    "sg:city":"Tournai (kain)",
    "sg:classifiers":[
        {
            "category":"Landmark",
            "subcategory":"Memorial",
            "type":"Public Place"
        }
    ],
    "sg:phone":"+32 69 22 48 76",
    "sg:postcode":"7540",
    "sg:province":"Hainaut",
    "sg:tags":[
        "-",
        "monument"
    ],
    "wof:name":"Timmerman J Sprl",
    "wof:placetype":"venue"
},
  "geometry": {"coordinates":[3.3818109035,50.6398696899],"type":"Point"}
}