{
  "type": "Feature",
  "properties": {
    "iso:country":"BE",
    "sg:address":"Rue De La Coupe 45",
    "sg:city":"Mons",
    "sg:orig_category":"Bloemen and planten",
    "sg:phone":"+32 65 31 64 31",
    "sg:postcode":"7000",
    "sg:province":"Hainaut",
    "wof:name":"Fran\u00c7oise & Christophe",
    "wof:placetype":"venue"
},
  "geometry": {"coordinates":[3.9522030354,50.4524459839],"type":"Point"}
}