{
  "type": "Feature",
  "properties": {
    "iso:country":"BE",
    "sg:address":"Dorpsstraat 30",
    "sg:city":"Sint-laureins",
    "sg:orig_category":"Slagers",
    "sg:phone":"+32 9 379 04 18",
    "sg:postcode":"9980",
    "sg:province":"Oost-Vlaanderen",
    "wof:name":"Bart Janssens",
    "wof:placetype":"venue"
},
  "geometry": {"coordinates":[3.5201470852,51.2431602478],"type":"Point"}
}