{
  "type": "Feature",
  "properties": {
    "addr:full":"Zeedijk-heist 175b1 Knokke-heist West-Vlaanderen 8301",
    "addr:housenumber":"175b1",
    "addr:postcode":"8301",
    "addr:street":"Zeedijk-Heist",
    "iso:country":"BE",
    "sg:address":"Zeedijk-heist 175b1",
    "sg:city":"Knokke-heist",
    "sg:orig_category":"M\u00e9decins and sp\u00e9cialistes",
    "sg:phone":"+32 50 51 98 88",
    "sg:postcode":"8301",
    "sg:province":"West-Vlaanderen",
    "wof:name":"Fanny Mestdagh",
    "wof:placetype":"venue"
},
  "geometry": {"coordinates":[3.2381000519,51.3277587891],"type":"Point"}
}