{
  "type": "Feature",
  "properties": {
    "addr:full":"Rue De Petit Fays 94 Vresse-sur-semois (vresse) Namur 5550",
    "addr:housenumber":"94",
    "addr:postcode":"5550",
    "addr:street":"Rue De Petit Fays",
    "iso:country":"BE",
    "sg:address":"Rue De Petit Fays 94",
    "sg:city":"Vresse-sur-semois (vresse)",
    "sg:classifiers":[
        {
            "category":"Travel",
            "subcategory":"Hotels & Motels",
            "type":"Entertainment"
        }
    ],
    "sg:phone":"+32 61 50 01 22",
    "sg:postcode":"5550",
    "sg:province":"Namur",
    "wof:name":"Fletcher Hotel L'eau Vive",
    "wof:placetype":"venue"
},
  "geometry": {"coordinates":[4.9336900711,49.8729820251],"type":"Point"}
}