{
  "type": "Feature",
  "properties": {
    "iso:country":"BE",
    "sg:address":"Roeselberg 39",
    "sg:city":"Tielt-winge (houwaart)",
    "sg:classifiers":[
        {
            "category":"Building & Trades",
            "subcategory":"Plumbing",
            "type":"Services"
        }
    ],
    "sg:phone":"+32 16 64 08 32",
    "sg:postcode":"3390",
    "sg:province":"Vlaams-Brabant",
    "sg:tags":[
        "repair",
        "mainten",
        "-",
        "central",
        "heating"
    ],
    "wof:name":"Van Horebeek H",
    "wof:placetype":"venue"
},
  "geometry": {"coordinates":[4.8640980721,50.9207344055],"type":"Point"}
}