{
  "type": "Feature",
  "properties": {
    "addr:full":"Alsembergse Steenweg 944 Ukkel/uccle Bruxelles-Capitale 1180",
    "addr:housenumber":"944",
    "addr:postcode":"1180",
    "addr:street":"Alsembergse Steenweg;/",
    "iso:country":"BE",
    "sg:address":"Alsembergse Steenweg 944",
    "sg:city":"Ukkel/uccle",
    "sg:classifiers":[
        {
            "category":"Insurance",
            "subcategory":"Insurance Agent",
            "type":"Services"
        }
    ],
    "sg:phone":"+32 2 332 32 92",
    "sg:postcode":"1180",
    "sg:province":"Bruxelles-Capitale",
    "sg:tags":[
        "verzekeringsmakelaars",
        "expert"
    ],
    "wof:name":"Bureau Vassart & Cie",
    "wof:placetype":"venue"
},
  "geometry": {"coordinates":[4.3340730667,50.7934951782],"type":"Point"}
}