{
  "type": "Feature",
  "properties": {
    "iso:country":"BE",
    "sg:address":"Rue Achille Chav\u00e9e 24",
    "sg:city":"La Louvi\u00e8re",
    "sg:classifiers":[
        {
            "category":"Health Services",
            "subcategory":"Doctor",
            "type":"Services"
        }
    ],
    "sg:phone":"+32 64 22 10 05",
    "sg:postcode":"7100",
    "sg:province":"Hainaut",
    "sg:tags":[
        "medicinephysicians",
        "surgeon"
    ],
    "wof:name":"Authom J",
    "wof:placetype":"venue"
},
  "geometry": {"coordinates":[4.1658182144,50.4652023315],"type":"Point"}
}