{
  "type": "Feature",
  "properties": {
    "iso:country":"BE",
    "sg:address":"Route De L\u00b4etat 241",
    "sg:city":"Lasne",
    "sg:orig_category":"Jardinage",
    "sg:phone":"+32 2 633 49 94",
    "sg:postcode":"1380",
    "sg:province":"Brabant Wallon",
    "wof:name":"Progarden",
    "wof:placetype":"venue"
},
  "geometry": {"coordinates":[4.4813399315,50.6839485168],"type":"Point"}
}