{
  "type": "Feature",
  "properties": {
    "iso:country":"BE",
    "sg:address":"Lindenplaats 7",
    "sg:city":"Moerbeke",
    "sg:orig_category":"Overheidsdiensten",
    "sg:phone":"+32 9 346 80 05",
    "sg:postcode":"9180",
    "sg:province":"Oost-Vlaanderen",
    "wof:name":"Gemeentebestuur",
    "wof:placetype":"venue"
},
  "geometry": {"coordinates":[3.9379179478,51.172416687],"type":"Point"}
}