{
  "type": "Feature",
  "properties": {
    "addr:full":"All\u00e9e Du Traynoy 14 Genappe (bousval) Brabant Wallon 1470",
    "addr:housenumber":"14",
    "addr:postcode":"1470",
    "addr:street":"Alle\u0301E Du Traynoy;Wallon",
    "iso:country":"BE",
    "sg:address":"All\u00e9e Du Traynoy 14",
    "sg:city":"Genappe (bousval)",
    "sg:orig_category":"Non-Classified Establishments",
    "sg:phone":"+32 10 61 75 29",
    "sg:postcode":"1470",
    "sg:province":"Brabant Wallon",
    "wof:name":"Arche (l') - Refuge",
    "wof:placetype":"venue"
},
  "geometry": {"coordinates":[4.5156898499,50.6247634888],"type":"Point"}
}