{
  "type": "Feature",
  "properties": {
    "iso:country":"BE",
    "sg:address":"Langemunte 46",
    "sg:city":"Lierde",
    "sg:orig_category":"Sportclubs",
    "sg:phone":"+32 55 42 09 02",
    "sg:postcode":"9570",
    "sg:province":"Oost-Vlaanderen",
    "wof:name":"T.c. Lierde Tempelhof",
    "wof:placetype":"venue"
},
  "geometry": {"coordinates":[3.8465709686,50.8137893677],"type":"Point"}
}