{
  "type": "Feature",
  "properties": {
    "addr:full":"Burg J Chalmetlaan 63 Zelzate Oost-Vlaanderen 9060",
    "addr:housenumber":"63",
    "addr:postcode":"9060",
    "addr:street":"Burg;Chalmetlaan",
    "iso:country":"BE",
    "sg:address":"Burg J Chalmetlaan 63",
    "sg:city":"Zelzate",
    "sg:orig_category":"D\u00e9taillants en pi\u00e8ces and accessoires de voitures",
    "sg:phone":"+32 9 345 82 14",
    "sg:postcode":"9060",
    "sg:province":"Oost-Vlaanderen",
    "wof:name":"Speedy",
    "wof:placetype":"venue"
},
  "geometry": {"coordinates":[3.816188097,51.1971969604],"type":"Point"}
}