{
  "type": "Feature",
  "properties": {
    "iso:country":"BE",
    "sg:address":"Dalstraat 20",
    "sg:city":"Elsene/ixelles",
    "sg:orig_category":"Diverse grafische activiteiten Film-, tv- and videoproductie",
    "sg:phone":"+32 2 640 38 12",
    "sg:postcode":"1050",
    "sg:province":"Bruxelles-Capitale",
    "wof:name":"Bureau Rumeurs",
    "wof:placetype":"venue"
},
  "geometry": {"coordinates":[4.371368885,50.8241882324],"type":"Point"}
}