{
  "type": "Feature",
  "properties": {
    "iso:country":"BE",
    "sg:address":"Grand'place 21",
    "sg:city":"Farciennes",
    "sg:classifiers":[
        {
            "category":"Wholesale",
            "subcategory":"Medical Equipment & Supplies",
            "type":"Manufacturing & Wholesale Goods"
        }
    ],
    "sg:phone":"+32 71 39 43 24",
    "sg:postcode":"6240",
    "sg:province":"Hainaut",
    "sg:tags":[
        "aid",
        "hearing"
    ],
    "wof:name":"Leonardelli",
    "wof:placetype":"venue"
},
  "geometry": {"coordinates":[4.5526208878,50.4286384583],"type":"Point"}
}