{
  "type": "Feature",
  "properties": {
    "addr:full":"Rue Du March\u00e9 20 Li\u00e8ge 1 (li\u00e8ge 2) Li\u00e8ge 4020",
    "addr:housenumber":"20;1;2",
    "addr:postcode":"4020",
    "addr:street":"Rue Du Marche\u0301",
    "iso:country":"BE",
    "sg:address":"Rue Du March\u00e9 20",
    "sg:city":"Li\u00e8ge 1 (li\u00e8ge 2)",
    "sg:classifiers":[
        {
            "category":"Transit Center",
            "subcategory":"Freight",
            "type":"Transportation"
        }
    ],
    "sg:phone":"+32 4 342 58 95",
    "sg:postcode":"4020",
    "sg:province":"Li\u00e8ge",
    "sg:tags":[
        "import",
        "export",
        "-"
    ],
    "wof:name":"K.p.n. Services",
    "wof:placetype":"venue"
},
  "geometry": {"coordinates":[5.5924839973,50.6412887573],"type":"Point"}
}