{
  "type": "Feature",
  "properties": {
    "addr:full":"Kortrijkstraat 96 Wevelgem West-Vlaanderen 8560",
    "addr:housenumber":"96",
    "addr:postcode":"8560",
    "addr:street":"Kortrijkstraat",
    "iso:country":"BE",
    "sg:address":"Kortrijkstraat 96",
    "sg:city":"Wevelgem",
    "sg:classifiers":[
        {
            "category":"Shopping",
            "subcategory":"Clothing, Apparel, & Fashions",
            "type":"Retail Goods"
        }
    ],
    "sg:phone":"+32 56 41 10 57",
    "sg:postcode":"8560",
    "sg:province":"West-Vlaanderen",
    "sg:tags":[
        "boutique"
    ],
    "wof:name":"Koky",
    "wof:placetype":"venue"
},
  "geometry": {"coordinates":[3.1897530556,50.8105430603],"type":"Point"}
}