{
  "type": "Feature",
  "properties": {
    "iso:country":"BE",
    "sg:address":"Avenue Armand Huysmans 212",
    "sg:city":"Bruxelles (ixelles)",
    "sg:classifiers":[
        {
            "category":"Real Estate",
            "subcategory":"Architect",
            "type":"Services"
        }
    ],
    "sg:phone":"+32 2 673 94 40",
    "sg:postcode":"1050",
    "sg:province":"Bruxelles-Capitale",
    "wof:name":"T\u00fcreg\u00fcn I",
    "wof:placetype":"venue"
},
  "geometry": {"coordinates":[4.3909077644,50.8075828552],"type":"Point"}
}