{
  "type": "Feature",
  "properties": {
    "addr:full":"Chauss\u00e9e D'alsemberg 410 Bruxelles (uccle) Bruxelles-Capitale 1180",
    "addr:housenumber":"410",
    "addr:postcode":"1180",
    "addr:street":"Chausse\u0301E D'Alsemberg",
    "iso:country":"BE",
    "sg:address":"Chauss\u00e9e D'alsemberg 410",
    "sg:city":"Bruxelles (uccle)",
    "sg:classifiers":[
        {
            "category":"Professional",
            "subcategory":"Accounting & Tax Preparation",
            "type":"Services"
        }
    ],
    "sg:phone":"+32 2 343 82 04",
    "sg:postcode":"1180",
    "sg:province":"Bruxelles-Capitale",
    "sg:tags":[
        "accountant"
    ],
    "wof:name":"Piraux Ph",
    "wof:placetype":"venue"
},
  "geometry": {"coordinates":[4.3389558792,50.813167572],"type":"Point"}
}