{
  "type": "Feature",
  "properties": {
    "addr:full":"Rue Jean-d'outremeuse 64 Li\u00e8ge 1 (li\u00e8ge 2) Li\u00e8ge 4020",
    "addr:housenumber":"64;1;2",
    "addr:postcode":"4020",
    "addr:street":"Rue Jean-D'Outremeuse",
    "iso:country":"BE",
    "sg:address":"Rue Jean-d'outremeuse 64",
    "sg:city":"Li\u00e8ge 1 (li\u00e8ge 2)",
    "sg:classifiers":[
        {
            "category":"Education",
            "subcategory":"School",
            "type":"Public Place"
        }
    ],
    "sg:phone":"+32 4 343 48 32",
    "sg:postcode":"4020",
    "sg:province":"Li\u00e8ge",
    "sg:tags":[
        "secondary"
    ],
    "wof:name":"Etablissement Mixte Enseignement Secondaire Sp\u00e9cial",
    "wof:placetype":"venue"
},
  "geometry": {"coordinates":[5.5858559608,50.6407165527],"type":"Point"}
}