{
  "type": "Feature",
  "properties": {
    "addr:full":"Rue D'engihoul 11 Nandrin Li\u00e8ge 4550",
    "addr:housenumber":"11",
    "addr:postcode":"4550",
    "addr:street":"Rue D'Engihoul",
    "iso:country":"BE",
    "sg:address":"Rue D'engihoul 11",
    "sg:city":"Nandrin",
    "sg:orig_category":"Enseignement maternel and primaire",
    "sg:phone":"+32 4 371 41 35",
    "sg:postcode":"4550",
    "sg:province":"Li\u00e8ge",
    "wof:name":"Ecole Fond. Communale",
    "wof:placetype":"venue"
},
  "geometry": {"coordinates":[5.41188097,50.5292892456],"type":"Point"}
}