{
  "type": "Feature",
  "properties": {
    "iso:country":"BE",
    "sg:address":"Petrus Bayensstraat 10",
    "sg:city":"Dilbeek",
    "sg:classifiers":[
        {
            "category":"Arena",
            "subcategory":"Sports Club",
            "type":"Entertainment"
        }
    ],
    "sg:phone":"+32 2 466 75 02",
    "sg:postcode":"1702",
    "sg:province":"Vlaams-Brabant",
    "sg:tags":[
        "de"
    ],
    "wof:name":"V.c. Compubooks Dilbeek",
    "wof:placetype":"venue"
},
  "geometry": {"coordinates":[4.2768359184,50.8668212891],"type":"Point"}
}