{
  "type": "Feature",
  "properties": {
    "addr:full":"Staprijk 27 Oud-turnhout Antwerpen 2360",
    "addr:housenumber":"27",
    "addr:postcode":"2360",
    "addr:street":"Staprijk",
    "iso:country":"BE",
    "sg:address":"Staprijk 27",
    "sg:city":"Oud-turnhout",
    "sg:classifiers":[
        {
            "category":"Shopping",
            "subcategory":"Florist",
            "type":"Retail Goods"
        }
    ],
    "sg:phone":"+32 14 45 28 23",
    "sg:postcode":"2360",
    "sg:province":"Antwerpen",
    "wof:name":"Sels J",
    "wof:placetype":"venue"
},
  "geometry": {"coordinates":[5.0014820099,51.3076667786],"type":"Point"}
}