{
  "type": "Feature",
  "properties": {
    "addr:full":"Abdijlaan 38 Brecht Antwerpen 2960",
    "addr:housenumber":"38",
    "addr:postcode":"2960",
    "addr:street":"Abdijlaan",
    "iso:country":"BE",
    "sg:address":"Abdijlaan 38",
    "sg:city":"Brecht",
    "sg:orig_category":"Rundveehouders Varkenskwekers",
    "sg:phone":"+32 3 313 94 32",
    "sg:postcode":"2960",
    "sg:province":"Antwerpen",
    "wof:name":"Henri De Bruyn",
    "wof:placetype":"venue"
},
  "geometry": {"coordinates":[4.6312069893,51.3013725281],"type":"Point"}
}