{
  "type": "Feature",
  "properties": {
    "addr:full":"Rue Emile Vandervelde 106 Ans Li\u00e8ge 4431",
    "addr:housenumber":"106",
    "addr:postcode":"4431",
    "addr:street":"Rue Emile Vandervelde",
    "iso:country":"BE",
    "sg:address":"Rue Emile Vandervelde 106",
    "sg:city":"Ans",
    "sg:classifiers":[
        {
            "category":"Cafe",
            "type":"Food & Drink"
        }
    ],
    "sg:phone":"+32 4 263 50 32",
    "sg:postcode":"4431",
    "sg:province":"Li\u00e8ge",
    "sg:tags":[
        "caf\u00e9s"
    ],
    "wof:name":"Preference",
    "wof:placetype":"venue"
},
  "geometry": {"coordinates":[5.5053739548,50.6584281921],"type":"Point"}
}