{
  "type": "Feature",
  "properties": {
    "iso:country":"BE",
    "sg:address":"Rue Du Tienne 1",
    "sg:city":"Gerpinnes",
    "sg:orig_category":"Dakwerken HERSTELLING ELEKTRISCHE HUISHOUDAPPARATEN Huishoudapparaten, televisies and radio's Loodgi",
    "sg:phone":"+32 71 50 20 81",
    "sg:postcode":"6280",
    "sg:province":"Hainaut",
    "wof:name":"Galle M.",
    "wof:placetype":"venue"
},
  "geometry": {"coordinates":[4.5466680527,50.3520851135],"type":"Point"}
}