{
  "type": "Feature",
  "properties": {
    "addr:full":"Bredabaan 222 Brasschaat Antwerpen 2930",
    "addr:housenumber":"222",
    "addr:postcode":"2930",
    "addr:street":"Bredabaan",
    "iso:country":"BE",
    "sg:address":"Bredabaan 222",
    "sg:city":"Brasschaat",
    "sg:classifiers":[
        {
            "category":"Shopping",
            "subcategory":"Clothing, Apparel, & Fashions",
            "type":"Retail Goods"
        }
    ],
    "sg:phone":"+32 3 651 40 65",
    "sg:postcode":"2930",
    "sg:province":"Antwerpen",
    "sg:tags":[
        "lingerie",
        "sous-v\u00eatements"
    ],
    "wof:name":"Huis Catherine Dessous",
    "wof:placetype":"venue"
},
  "geometry": {"coordinates":[4.4893870354,51.2891616821],"type":"Point"}
}