{
  "type": "Feature",
  "properties": {
    "iso:country":"BE",
    "sg:address":"Planche 41a",
    "sg:city":"Flobecq",
    "sg:classifiers":[
        {
            "category":"Health Services",
            "subcategory":"Dentist",
            "type":"Services"
        }
    ],
    "sg:phone":"+32 68 44 95 87",
    "sg:postcode":"7880",
    "sg:province":"Hainaut",
    "wof:name":"Jouret Sandrine",
    "wof:placetype":"venue"
},
  "geometry": {"coordinates":[3.7223799229,50.7412109375],"type":"Point"}
}