{
  "type": "Feature",
  "properties": {
    "iso:country":"BE",
    "sg:address":"Kloosterstraat 40",
    "sg:city":"Antwerpen",
    "sg:classifiers":[
        {
            "category":"Home & Garden",
            "subcategory":"Home Furnishings",
            "type":"Retail Goods"
        }
    ],
    "sg:phone":"+32 3 226 25 96",
    "sg:postcode":"2000",
    "sg:province":"Antwerpen",
    "sg:tags":[
        "lighting",
        "fixture",
        "-"
    ],
    "wof:name":"Glashuys ('t)",
    "wof:placetype":"venue"
},
  "geometry": {"coordinates":[4.3949289322,51.2163848877],"type":"Point"}
}