{
  "type": "Feature",
  "properties": {
    "iso:country":"BE",
    "sg:address":"Chauss\u00e9e Romaine 5",
    "sg:city":"Hannut (moxhe)",
    "sg:classifiers":[
        {
            "category":"Building & Trades",
            "subcategory":"Construction",
            "type":"Services"
        }
    ],
    "sg:phone":"+32 19 69 82 53",
    "sg:postcode":"4280",
    "sg:province":"Li\u00e8ge",
    "sg:tags":[
        "carpenter"
    ],
    "wof:name":"In 't Groen W",
    "wof:placetype":"venue"
},
  "geometry": {"coordinates":[5.081843853,50.637878418],"type":"Point"}
}