{
  "type": "Feature",
  "properties": {
    "addr:full":"Groenstraat 41 Aalst Oost-Vlaanderen 9300",
    "addr:housenumber":"41",
    "addr:postcode":"9300",
    "addr:street":"Groenstraat",
    "iso:country":"BE",
    "sg:address":"Groenstraat 41",
    "sg:city":"Aalst",
    "sg:orig_category":"Animaux domestiques and accessoires",
    "sg:phone":"+32 53 70 64 47",
    "sg:postcode":"9300",
    "sg:province":"Oost-Vlaanderen",
    "wof:name":"Siervis Octopus",
    "wof:placetype":"venue"
},
  "geometry": {"coordinates":[4.0499968529,50.9431037903],"type":"Point"}
}