{
  "type": "Feature",
  "properties": {
    "addr:full":"Avenue De Merode 29 Rixensart Brabant Wallon 1330",
    "addr:housenumber":"29",
    "addr:postcode":"1330",
    "addr:street":"Avenue De Merode;Wallon",
    "iso:country":"BE",
    "sg:address":"Avenue De Merode 29",
    "sg:city":"Rixensart",
    "sg:orig_category":"Pharmaciens",
    "sg:phone":"+32 2 653 67 10",
    "sg:postcode":"1330",
    "sg:province":"Brabant Wallon",
    "wof:name":"Pharmacie Monseur-donis",
    "wof:placetype":"venue"
},
  "geometry": {"coordinates":[4.5281620026,50.7124252319],"type":"Point"}
}