{
  "type": "Feature",
  "properties": {
    "iso:country":"BE",
    "sg:address":"Chemin De Signeulx 7",
    "sg:city":"Virton (bleid)",
    "sg:classifiers":[
        {
            "category":"Travel",
            "subcategory":"Resort",
            "type":"Entertainment"
        }
    ],
    "sg:phone":"+32 63 57 89 37",
    "sg:postcode":"6760",
    "sg:province":"Luxembourg",
    "sg:tags":[
        "farm",
        "house",
        "holiday",
        "guest"
    ],
    "wof:name":"Cailteux A",
    "wof:placetype":"venue"
},
  "geometry": {"coordinates":[5.5347180367,49.5672607422],"type":"Point"}
}