{
  "type": "Feature",
  "properties": {
    "iso:country":"BE",
    "sg:address":"Chauss\u00c9e De Wavre 1422",
    "sg:city":"Oudergem/auderghem",
    "sg:classifiers":[
        {
            "category":"Insurance",
            "subcategory":"Life Insurance",
            "type":"Services"
        }
    ],
    "sg:phone":"+32 2 660 56 75",
    "sg:postcode":"1160",
    "sg:province":"Bruxelles-Capitale",
    "sg:tags":[
        "assurance"
    ],
    "wof:name":"F. Venturi",
    "wof:placetype":"venue"
},
  "geometry": {"coordinates":[4.4160981178,50.8188858032],"type":"Point"}
}