{
  "type": "Feature",
  "properties": {
    "addr:full":"Remience 7 Vaux-sur-sure Luxembourg 6640",
    "addr:housenumber":"7",
    "addr:postcode":"6640",
    "addr:street":"Remience",
    "iso:country":"BE",
    "sg:address":"Remience 7",
    "sg:city":"Vaux-sur-sure",
    "sg:orig_category":"Eleveurs de bovins",
    "sg:phone":"+32 61 26 62 02",
    "sg:postcode":"6640",
    "sg:province":"Luxembourg",
    "wof:name":"Achille Ska",
    "wof:placetype":"venue"
},
  "geometry": {"coordinates":[5.5671000481,49.91065979],"type":"Point"}
}