{
  "type": "Feature",
  "properties": {
    "iso:country":"BE",
    "sg:address":"Jagersborgweg",
    "sg:city":"Maaseik",
    "sg:classifiers":[
        {
            "category":"Community Center",
            "subcategory":"Social",
            "type":"Public Place"
        }
    ],
    "sg:phone":"+32 89 56 56 29",
    "sg:postcode":"3680",
    "sg:province":"Limburg",
    "sg:tags":[
        "automobile",
        "-",
        "diagnostic"
    ],
    "wof:name":"Bosch Service Janssen",
    "wof:placetype":"venue"
},
  "geometry": {"coordinates":[5.7457351685,51.1024703979],"type":"Point"}
}