{
  "type": "Feature",
  "properties": {
    "iso:country":"BE",
    "sg:address":"Rogierlaan 269",
    "sg:city":"Schaarbeek/schaerbeek",
    "sg:orig_category":"Binnenhuisarchitecten",
    "sg:phone":"+32 2 216 82 30",
    "sg:postcode":"1030",
    "sg:province":"Bruxelles-Capitale",
    "wof:name":"Andre Verroken",
    "wof:placetype":"venue"
},
  "geometry": {"coordinates":[4.3868699074,50.8573265076],"type":"Point"}
}