{
  "type": "Feature",
  "properties": {
    "addr:full":"Molenbaan 8 Vorselaar Antwerpen 2290",
    "addr:housenumber":"8",
    "addr:postcode":"2290",
    "addr:street":"Molenbaan",
    "iso:country":"BE",
    "sg:address":"Molenbaan 8",
    "sg:city":"Vorselaar",
    "sg:classifiers":[
        {
            "category":"Health Services",
            "subcategory":"Medical Lab",
            "type":"Services"
        }
    ],
    "sg:phone":"+32 14 51 91 78",
    "sg:postcode":"2290",
    "sg:province":"Antwerpen",
    "sg:tags":[
        "laboratory",
        "dental"
    ],
    "wof:name":"Tandex",
    "wof:placetype":"venue"
},
  "geometry": {"coordinates":[4.7675337791,51.2128753662],"type":"Point"}
}