{
  "type": "Feature",
  "properties": {
    "iso:country":"BE",
    "sg:address":"Naamsevest 60b1",
    "sg:city":"Sint-truiden",
    "sg:classifiers":[
        {
            "category":"Arena",
            "subcategory":"Sports Club",
            "type":"Entertainment"
        }
    ],
    "sg:phone":"+32 11 68 24 06",
    "sg:postcode":"3800",
    "sg:province":"Limburg",
    "sg:tags":[
        "de"
    ],
    "wof:name":"T.c. De Schans",
    "wof:placetype":"venue"
},
  "geometry": {"coordinates":[5.1858048439,50.8124465942],"type":"Point"}
}