{
  "type": "Feature",
  "properties": {
    "iso:country":"BE",
    "sg:address":"Claeysstraat 4",
    "sg:city":"Oostkamp",
    "sg:orig_category":"Installatie van houten of kunststof schrijnwerk",
    "sg:phone":"+32 50 27 75 32",
    "sg:postcode":"8020",
    "sg:province":"West-Vlaanderen",
    "wof:name":"Krekelberg",
    "wof:placetype":"venue"
},
  "geometry": {"coordinates":[3.1710848808,51.0777130127],"type":"Point"}
}