{
  "type": "Feature",
  "properties": {
    "addr:full":"Quai Edouard Van Beneden 8b2 Li\u00c8ge Li\u00e8ge 4020",
    "addr:housenumber":"8b2",
    "addr:postcode":"4020",
    "addr:street":"Quai Edouard Van Beneden",
    "iso:country":"BE",
    "sg:address":"Quai Edouard Van Beneden 8b2",
    "sg:city":"Li\u00c8ge",
    "sg:classifiers":[
        {
            "category":"Professional",
            "type":"Services"
        }
    ],
    "sg:phone":"+32 4 342 46 06",
    "sg:postcode":"4020",
    "sg:province":"Li\u00e8ge",
    "sg:tags":[
        "aux",
        "diver",
        "personnes"
    ],
    "wof:name":"Andre Services",
    "wof:placetype":"venue"
},
  "geometry": {"coordinates":[5.5776991844,50.6370391846],"type":"Point"}
}