{
  "type": "Feature",
  "properties": {
    "iso:country":"BE",
    "sg:address":"Kapelweg 14",
    "sg:city":"Kortrijk",
    "sg:classifiers":[
        {
            "category":"Personal",
            "subcategory":"Beauty Salon",
            "type":"Services"
        }
    ],
    "sg:phone":"+32 56 21 30 06",
    "sg:postcode":"8510",
    "sg:province":"West-Vlaanderen",
    "sg:tags":[
        "de",
        "coiffure"
    ],
    "wof:name":"Coiffure Marie-th\u00c9r\u00c8se",
    "wof:placetype":"venue"
},
  "geometry": {"coordinates":[3.2745718956,50.7794532776],"type":"Point"}
}