{
  "type": "Feature",
  "properties": {
    "iso:country":"BE",
    "sg:address":"Lange Zandstraat 30",
    "sg:city":"Sint-katelijne-waver",
    "sg:orig_category":"Entretien and r\u00e9parations de voitures",
    "sg:phone":"+32 15 31 18 32",
    "sg:postcode":"2860",
    "sg:province":"Antwerpen",
    "wof:name":"Garage Van Den Berg",
    "wof:placetype":"venue"
},
  "geometry": {"coordinates":[4.4797930717,51.0704307556],"type":"Point"}
}