{
  "type": "Feature",
  "properties": {
    "iso:country":"BE",
    "sg:address":"Oostveldstraat 177",
    "sg:city":"Eeklo",
    "sg:orig_category":"Eleveurs de bovins. Eleveurs and marchands de porcs",
    "sg:phone":"+32 9 377 28 79",
    "sg:postcode":"9900",
    "sg:province":"Oost-Vlaanderen",
    "wof:name":"Adelijn De Geeter",
    "wof:placetype":"venue"
},
  "geometry": {"coordinates":[3.5925350189,51.1821517944],"type":"Point"}
}