{
  "type": "Feature",
  "properties": {
    "iso:country":"BE",
    "sg:address":"Eikelenweg 78",
    "sg:city":"Lanaken",
    "sg:classifiers":[
        {
            "category":"Health Services",
            "subcategory":"Dentist",
            "type":"Services"
        }
    ],
    "sg:phone":"+32 89 71 63 77",
    "sg:postcode":"3620",
    "sg:province":"Limburg",
    "wof:name":"Geelen J",
    "wof:placetype":"venue"
},
  "geometry": {"coordinates":[5.6332302094,50.8952293396],"type":"Point"}
}