{
  "type": "Feature",
  "properties": {
    "iso:country":"BE",
    "sg:address":"Rue De Folx-les-caves 26",
    "sg:city":"Orp-jauche",
    "sg:orig_category":"Enseignement maternel and primaire",
    "sg:phone":"+32 19 63 54 50",
    "sg:postcode":"1350",
    "sg:province":"Brabant Wallon",
    "wof:name":"Ecole Fond. Communale",
    "wof:placetype":"venue"
},
  "geometry": {"coordinates":[4.97920084,50.6738891602],"type":"Point"}
}