{
  "type": "Feature",
  "properties": {
    "addr:full":"Rue Des Carri\u00e8res 39 Beauraing (winenne) Namur 5570",
    "addr:housenumber":"39",
    "addr:postcode":"5570",
    "addr:street":"Rue Des Carrie\u0300Res",
    "iso:country":"BE",
    "sg:address":"Rue Des Carri\u00e8res 39",
    "sg:city":"Beauraing (winenne)",
    "sg:classifiers":[
        {
            "category":"Food & Beverages",
            "subcategory":"Fruits & Vegetables",
            "type":"Retail Goods"
        }
    ],
    "sg:phone":"+32 82 71 26 15",
    "sg:postcode":"5570",
    "sg:province":"Namur",
    "sg:tags":[
        "-"
    ],
    "wof:name":"G\u00e9rardy D",
    "wof:placetype":"venue"
},
  "geometry": {"coordinates":[4.8886051178,50.0962028503],"type":"Point"}
}