{
  "type": "Feature",
  "properties": {
    "iso:country":"BE",
    "sg:address":"Voetbalstraat 33b2",
    "sg:city":"Zoersel",
    "sg:orig_category":"Dierentuinen, botanische tuinen, sterrenwachten and natuurreservaten",
    "sg:phone":"+32 3 309 06 70",
    "sg:postcode":"2980",
    "sg:province":"Antwerpen",
    "wof:name":"Hoekse Beemden (brecht)",
    "wof:placetype":"venue"
},
  "geometry": {"coordinates":[4.7132000923,51.2759971619],"type":"Point"}
}