{
  "type": "Feature",
  "properties": {
    "addr:full":"Rode Kruislaan 54 Tongeren Limburg 3700",
    "addr:housenumber":"54",
    "addr:postcode":"3700",
    "addr:street":"Rode Kruislaan",
    "iso:country":"BE",
    "sg:address":"Rode Kruislaan 54",
    "sg:city":"Tongeren",
    "sg:classifiers":[
        {
            "category":"Food & Beverages",
            "subcategory":"Supermarket",
            "type":"Retail Goods"
        }
    ],
    "sg:phone":"+32 12 23 31 49",
    "sg:postcode":"3700",
    "sg:province":"Limburg",
    "sg:tags":[
        "department",
        "store"
    ],
    "wof:name":"Sparmarkt Vos",
    "wof:placetype":"venue"
},
  "geometry": {"coordinates":[5.4496850967,50.7768630981],"type":"Point"}
}