{
  "type": "Feature",
  "properties": {
    "addr:full":"Rue De La Justice 2 Leuze-en-hainaut (pipaix) Hainaut 7904",
    "addr:housenumber":"2",
    "addr:postcode":"7904",
    "addr:street":"Rue De La Justice;Hainaut",
    "iso:country":"BE",
    "sg:address":"Rue De La Justice 2",
    "sg:city":"Leuze-en-hainaut (pipaix)",
    "sg:classifiers":[
        {
            "category":"Real Estate",
            "subcategory":"Architect",
            "type":"Services"
        }
    ],
    "sg:phone":"+32 69 66 51 10",
    "sg:postcode":"7904",
    "sg:province":"Hainaut",
    "wof:name":"Opsomer A",
    "wof:placetype":"venue"
},
  "geometry": {"coordinates":[3.5624799728,50.5703811646],"type":"Point"}
}