{
  "type": "Feature",
  "properties": {
    "iso:country":"BE",
    "sg:address":"Rue Du Mont Doyelle 18",
    "sg:city":"Frasnes-lez-anvaing",
    "sg:orig_category":"Schoonheidssalons",
    "sg:phone":"+32 69 76 95 66",
    "sg:postcode":"7912",
    "sg:province":"Hainaut",
    "wof:name":"Ingrid De Jonghe",
    "wof:placetype":"venue"
},
  "geometry": {"coordinates":[3.5887680054,50.7042198181],"type":"Point"}
}