{
  "type": "Feature",
  "properties": {
    "addr:full":"Rue Notre-dame 41 Walcourt Namur 5650",
    "addr:housenumber":"41",
    "addr:postcode":"5650",
    "addr:street":"Rue Notre-Dame",
    "iso:country":"BE",
    "sg:address":"Rue Notre-dame 41",
    "sg:city":"Walcourt",
    "sg:orig_category":"Schoonheidssalons",
    "sg:phone":"+32 71 61 41 09",
    "sg:postcode":"5650",
    "sg:province":"Namur",
    "wof:name":"Catherine Brohet",
    "wof:placetype":"venue"
},
  "geometry": {"coordinates":[4.4293842316,50.2504386902],"type":"Point"}
}