{
  "type": "Feature",
  "properties": {
    "addr:full":"Eendenstraat 8 Beerse Antwerpen 2340",
    "addr:housenumber":"8",
    "addr:postcode":"2340",
    "addr:street":"Eendenstraat",
    "iso:country":"BE",
    "sg:address":"Eendenstraat 8",
    "sg:city":"Beerse",
    "sg:classifiers":[
        {
            "category":"Insurance",
            "subcategory":"Insurance Agent",
            "type":"Services"
        }
    ],
    "sg:phone":"+32 3 309 15 45",
    "sg:postcode":"2340",
    "sg:province":"Antwerpen",
    "sg:tags":[
        "verzekeringsmakelaars",
        "expert"
    ],
    "wof:name":"Ecobuild Insurance",
    "wof:placetype":"venue"
},
  "geometry": {"coordinates":[4.7877721786,51.3160400391],"type":"Point"}
}