{
  "type": "Feature",
  "properties": {
    "addr:full":"Meest. De Beenhouwerstr. 34 Zoersel Antwerpen 2980",
    "addr:housenumber":"34",
    "addr:postcode":"2980",
    "iso:country":"BE",
    "sg:address":"Meest. De Beenhouwerstr. 34",
    "sg:city":"Zoersel",
    "sg:orig_category":"Peinture. Rev\u00eatements pour sols and murs. Eclairage et \u00e9quipements du foyer",
    "sg:phone":"+32 3 311 57 04",
    "sg:postcode":"2980",
    "sg:province":"Antwerpen",
    "wof:name":"Andre Ceulemans",
    "wof:placetype":"venue"
},
  "geometry": {"coordinates":[4.7064847946,51.2673225403],"type":"Point"}
}