{
  "type": "Feature",
  "properties": {
    "addr:full":"Rue M\u00e2lon Fontaine 6 Ecaussinnes (ecaussinnes-d'enghien) Hainaut 7190",
    "addr:housenumber":"6",
    "addr:postcode":"7190",
    "addr:street":"Rue Ma\u0302Lon Fontaine;Ecaussinnes-D'Enghien Hainaut",
    "iso:country":"BE",
    "sg:address":"Rue M\u00e2lon Fontaine 6",
    "sg:city":"Ecaussinnes (ecaussinnes-d'enghien)",
    "sg:classifiers":[
        {
            "category":"Shopping",
            "subcategory":"Antiques",
            "type":"Retail Goods"
        }
    ],
    "sg:phone":"+32 67 44 35 53",
    "sg:postcode":"7190",
    "sg:province":"Hainaut",
    "wof:name":"Gehain M",
    "wof:placetype":"venue"
},
  "geometry": {"coordinates":[4.1652331352,50.5546073914],"type":"Point"}
}