{
  "type": "Feature",
  "properties": {
    "addr:full":"Kleinven 43 Genk Limburg 3600",
    "addr:housenumber":"43",
    "addr:postcode":"3600",
    "addr:street":"Kleinven",
    "iso:country":"BE",
    "sg:address":"Kleinven 43",
    "sg:city":"Genk",
    "sg:classifiers":[
        {
            "category":"Autos & Motor Vehicles",
            "subcategory":"Automobile Sales",
            "type":"Retail Goods"
        }
    ],
    "sg:phone":"+32 89 35 17 39",
    "sg:postcode":"3600",
    "sg:province":"Limburg",
    "sg:tags":[
        "ceremony",
        "car"
    ],
    "wof:name":"Stal-boxberg",
    "wof:placetype":"venue"
},
  "geometry": {"coordinates":[5.4411301613,50.967300415],"type":"Point"}
}