{
  "type": "Feature",
  "properties": {
    "addr:full":"Rue Saint-agathe 3 Vresse-sur-semois (vresse) Namur 5550",
    "addr:housenumber":"3",
    "addr:postcode":"5550",
    "addr:street":"Rue Saint-Agathe;Vresse",
    "iso:country":"BE",
    "sg:address":"Rue Saint-agathe 3",
    "sg:city":"Vresse-sur-semois (vresse)",
    "sg:classifiers":[
        {
            "category":"Health Services",
            "subcategory":"Doctor",
            "type":"Services"
        }
    ],
    "sg:phone":"+32 61 50 14 10",
    "sg:postcode":"5550",
    "sg:province":"Namur",
    "sg:tags":[
        "medicinephysicians",
        "surgeon"
    ],
    "wof:name":"Coche M-h",
    "wof:placetype":"venue"
},
  "geometry": {"coordinates":[4.9312801361,49.8652877808],"type":"Point"}
}