{
  "type": "Feature",
  "properties": {
    "iso:country":"BE",
    "sg:address":"Naalstraat 43d",
    "sg:city":"Duffel",
    "sg:classifiers":[
        {
            "category":"Personal",
            "type":"Services"
        }
    ],
    "sg:phone":"+32 15 31 66 66",
    "sg:postcode":"2570",
    "sg:province":"Antwerpen",
    "sg:tags":[
        "party",
        "planning"
    ],
    "wof:name":"'t Lepeltje Bvba",
    "wof:placetype":"venue"
},
  "geometry": {"coordinates":[4.5105991364,51.0831108093],"type":"Point"}
}