{
  "type": "Feature",
  "properties": {
    "iso:country":"BE",
    "sg:address":"Looikesstraat 1",
    "sg:city":"Boortmeerbeek",
    "sg:classifiers":[
        {
            "category":"Professional",
            "subcategory":"Engineering",
            "type":"Services"
        }
    ],
    "sg:phone":"+32 477 33 50 17",
    "sg:postcode":"3190",
    "sg:province":"Vlaams-Brabant",
    "sg:tags":[
        "-"
    ],
    "wof:name":"E & M Consult Bvba",
    "wof:placetype":"venue"
},
  "geometry": {"coordinates":[4.572617054,50.9893531799],"type":"Point"}
}