{
  "type": "Feature",
  "properties": {
    "addr:full":"Voort 34 Hoogstraten (meerle) Antwerpen 2328",
    "addr:housenumber":"34",
    "addr:postcode":"2328",
    "addr:street":"Voort",
    "iso:country":"BE",
    "sg:address":"Voort 34",
    "sg:city":"Hoogstraten (meerle)",
    "sg:classifiers":[
        {
            "category":"Home & Garden",
            "subcategory":"Household Appliances",
            "type":"Retail Goods"
        }
    ],
    "sg:phone":"+32 3 315 97 36",
    "sg:postcode":"2328",
    "sg:province":"Antwerpen",
    "sg:tags":[
        "housewares",
        "-"
    ],
    "wof:name":"Buytenhuys (het)",
    "wof:placetype":"venue"
},
  "geometry": {"coordinates":[4.7950501442,51.4611663818],"type":"Point"}
}