{
  "type": "Feature",
  "properties": {
    "iso:country":"BE",
    "sg:address":"Kruisstraat 18",
    "sg:city":"Hoeselt",
    "sg:orig_category":"Eleveurs de bovins",
    "sg:phone":"+32 89 51 44 07",
    "sg:postcode":"3730",
    "sg:province":"Limburg",
    "wof:name":"Hendrik Daenen",
    "wof:placetype":"venue"
},
  "geometry": {"coordinates":[5.4767608643,50.8478813171],"type":"Point"}
}