{
  "type": "Feature",
  "properties": {
    "addr:full":"Trapkensstraat 5 Borgloon Limburg 3840",
    "addr:housenumber":"5",
    "addr:postcode":"3840",
    "addr:street":"Trapkensstraat",
    "iso:country":"BE",
    "sg:address":"Trapkensstraat 5",
    "sg:city":"Borgloon",
    "sg:classifiers":[
        {
            "category":"Wholesale",
            "subcategory":"Plants",
            "type":"Manufacturing & Wholesale Goods"
        }
    ],
    "sg:phone":"+32 12 74 65 95",
    "sg:postcode":"3840",
    "sg:province":"Limburg",
    "sg:tags":[
        "decoration",
        "flower",
        "-"
    ],
    "wof:name":"Volkstuinen Vzw",
    "wof:placetype":"venue"
},
  "geometry": {"coordinates":[5.3438501358,50.8013114929],"type":"Point"}
}