{
  "type": "Feature",
  "properties": {
    "addr:full":"Tuinlaan 1 Sint-niklaas Oost-Vlaanderen 9111",
    "addr:housenumber":"1",
    "addr:postcode":"9111",
    "addr:street":"Tuinlaan",
    "iso:country":"BE",
    "sg:address":"Tuinlaan 1",
    "sg:city":"Sint-niklaas",
    "sg:classifiers":[
        {
            "category":"Cafe",
            "type":"Food & Drink"
        }
    ],
    "sg:phone":"+32 3 722 08 57",
    "sg:postcode":"9111",
    "sg:province":"Oost-Vlaanderen",
    "sg:tags":[
        "caf\u00e9s"
    ],
    "wof:name":"Caf\u00c9 Dekpriem",
    "wof:placetype":"venue"
},
  "geometry": {"coordinates":[4.1031098366,51.148021698],"type":"Point"}
}