{
  "type": "Feature",
  "properties": {
    "iso:country":"BE",
    "sg:address":"Solheidelaan 22",
    "sg:city":"Huldenberg",
    "sg:classifiers":[
        {
            "category":"Cafe",
            "type":"Food & Drink"
        }
    ],
    "sg:phone":"+32 2 687 30 00",
    "sg:postcode":"3040",
    "sg:province":"Vlaams-Brabant",
    "sg:tags":[
        "caf\u00e9s"
    ],
    "wof:name":"Jules Vanmeerbeek",
    "wof:placetype":"venue"
},
  "geometry": {"coordinates":[4.5877141953,50.7916793823],"type":"Point"}
}