{
  "type": "Feature",
  "properties": {
    "addr:full":"Roua 222 Engis (clermont-sous-huy) Li\u00e8ge 4480",
    "addr:housenumber":"222",
    "addr:postcode":"4480",
    "addr:street":"Roua;Clermont-Sous-Huy",
    "iso:country":"BE",
    "sg:address":"Roua 222",
    "sg:city":"Engis (clermont-sous-huy)",
    "sg:classifiers":[
        {
            "category":"Retail",
            "subcategory":"Repair Shop",
            "type":"Services"
        }
    ],
    "sg:phone":"+32 85 31 18 70",
    "sg:postcode":"4480",
    "sg:province":"Li\u00e8ge",
    "sg:tags":[
        "machine",
        "sewing",
        "-"
    ],
    "wof:name":"Patrick Smitz",
    "wof:placetype":"venue"
},
  "geometry": {"coordinates":[5.3795571327,50.5611953735],"type":"Point"}
}