{
  "type": "Feature",
  "properties": {
    "addr:full":"Drogenboomstraat 68a Waregem West-Vlaanderen 8790",
    "addr:housenumber":"68a",
    "addr:postcode":"8790",
    "addr:street":"Drogenboomstraat",
    "iso:country":"BE",
    "sg:address":"Drogenboomstraat 68a",
    "sg:city":"Waregem",
    "sg:classifiers":[
        {
            "category":"Building & Trades",
            "subcategory":"Electrical",
            "type":"Services"
        }
    ],
    "sg:phone":"+32 56 61 52 05",
    "sg:postcode":"8790",
    "sg:province":"West-Vlaanderen",
    "sg:tags":[
        "electric",
        "-",
        "housewiring",
        "contractor"
    ],
    "wof:name":"Sanelek Van Wynsberge",
    "wof:placetype":"venue"
},
  "geometry": {"coordinates":[3.4506959915,50.8993721008],"type":"Point"}
}