{
  "type": "Feature",
  "properties": {
    "iso:country":"BE",
    "sg:address":"Appelstraat 28",
    "sg:city":"Tielt",
    "sg:orig_category":"Eleveurs de volaille",
    "sg:phone":"+32 51 63 34 38",
    "sg:postcode":"8700",
    "sg:province":"West-Vlaanderen",
    "wof:name":"Etienne Maes",
    "wof:placetype":"venue"
},
  "geometry": {"coordinates":[3.4011409283,50.9819221497],"type":"Point"}
}