{
  "type": "Feature",
  "properties": {
    "iso:country":"BE",
    "sg:address":"Boonstraat 29",
    "sg:city":"Hamme",
    "sg:orig_category":"R\u00e9alisation de programmes and logiciels",
    "sg:phone":"+32 52 48 40 38",
    "sg:postcode":"9220",
    "sg:province":"Oost-Vlaanderen",
    "wof:name":"De Maere Rudy",
    "wof:placetype":"venue"
},
  "geometry": {"coordinates":[4.1476559639,51.0706329346],"type":"Point"}
}