{
  "type": "Feature",
  "properties": {
    "addr:full":"Rue Joseph Ii 73 La Louviere Hainaut 7110",
    "addr:housenumber":"73",
    "addr:postcode":"7110",
    "addr:street":"Rue Joseph Ii",
    "iso:country":"BE",
    "sg:address":"Rue Joseph Ii 73",
    "sg:city":"La Louviere",
    "sg:classifiers":[
        {
            "category":"Insurance",
            "subcategory":"Insurance Agent",
            "type":"Services"
        }
    ],
    "sg:phone":"+32 495 52 06 51",
    "sg:postcode":"7110",
    "sg:province":"Hainaut",
    "sg:tags":[
        "verzekeringsmakelaars",
        "expert"
    ],
    "wof:name":"Van Nimmen",
    "wof:placetype":"venue"
},
  "geometry": {"coordinates":[4.1505050659,50.4826698303],"type":"Point"}
}