{
  "type": "Feature",
  "properties": {
    "addr:full":"Herpelsstraat 99 Harelbeke West-Vlaanderen 8530",
    "addr:housenumber":"99",
    "addr:postcode":"8530",
    "addr:street":"Herpelsstraat",
    "iso:country":"BE",
    "sg:address":"Herpelsstraat 99",
    "sg:city":"Harelbeke",
    "sg:orig_category":"Woningbouw",
    "sg:phone":"+32 56 70 51 21",
    "sg:postcode":"8530",
    "sg:province":"West-Vlaanderen",
    "wof:name":"Dan Verhelst",
    "wof:placetype":"venue"
},
  "geometry": {"coordinates":[3.3289940357,50.8551902771],"type":"Point"}
}