{
  "type": "Feature",
  "properties": {
    "iso:country":"BE",
    "sg:address":"Nieuwstraat 18",
    "sg:city":"Essen",
    "sg:orig_category":"Librairies",
    "sg:phone":"+32 3 667 64 64",
    "sg:postcode":"2910",
    "sg:province":"Antwerpen",
    "wof:name":"Huis De Bladwijzer",
    "wof:placetype":"venue"
},
  "geometry": {"coordinates":[4.4707508087,51.4661369324],"type":"Point"}
}