{
  "type": "Feature",
  "properties": {
    "addr:full":"Spoelewielenlaan 16 Lendelede West-Vlaanderen 8860",
    "addr:housenumber":"16",
    "addr:postcode":"8860",
    "addr:street":"Spoelewielenlaan",
    "iso:country":"BE",
    "sg:address":"Spoelewielenlaan 16",
    "sg:city":"Lendelede",
    "sg:orig_category":"Chemicali\u00ebn Gh",
    "sg:phone":"+32 51 30 23 84",
    "sg:postcode":"8860",
    "sg:province":"West-Vlaanderen",
    "wof:name":"Jern Cosmetics",
    "wof:placetype":"venue"
},
  "geometry": {"coordinates":[3.2385699749,50.8914413452],"type":"Point"}
}