{
  "type": "Feature",
  "properties": {
    "addr:full":"Rue Bon Dieu De Maka 1 La Roche-en-ardenne Luxembourg 6980",
    "addr:housenumber":"1",
    "addr:postcode":"6980",
    "addr:street":"Rue Bon Dieu De Maka",
    "iso:country":"BE",
    "sg:address":"Rue Bon Dieu De Maka 1",
    "sg:city":"La Roche-en-ardenne",
    "sg:classifiers":[
        {
            "category":"Health Services",
            "subcategory":"Health Practitioner",
            "type":"Services"
        }
    ],
    "sg:phone":"+32 84 41 21 81",
    "sg:postcode":"6980",
    "sg:province":"Luxembourg",
    "sg:tags":[
        "physiotherapist"
    ],
    "wof:name":"Legros Florence",
    "wof:placetype":"venue"
},
  "geometry": {"coordinates":[5.5774359703,50.1802787781],"type":"Point"}
}