{
  "type": "Feature",
  "properties": {
    "iso:country":"BE",
    "sg:address":"Merelstraat 103",
    "sg:city":"Zonhoven",
    "sg:classifiers":[
        {
            "category":"Recreation",
            "type":"Entertainment"
        }
    ],
    "sg:phone":"+32 11 82 50 70",
    "sg:postcode":"3520",
    "sg:province":"Limburg",
    "sg:tags":[
        "diver",
        "amusement"
    ],
    "wof:name":"Juliaan",
    "wof:placetype":"venue"
},
  "geometry": {"coordinates":[5.326086998,50.9931144714],"type":"Point"}
}