{
  "type": "Feature",
  "properties": {
    "addr:full":"Opeindestraat 40 Kortessem Limburg 3720",
    "addr:housenumber":"40",
    "addr:postcode":"3720",
    "addr:street":"Opeindestraat;Limburg",
    "iso:country":"BE",
    "sg:address":"Opeindestraat 40",
    "sg:city":"Kortessem",
    "sg:orig_category":"Installation de menuiserie en bois and plastique",
    "sg:phone":"+32 11 37 62 78",
    "sg:postcode":"3720",
    "sg:province":"Limburg",
    "wof:name":"Houbrix Jozef & Jules",
    "wof:placetype":"venue"
},
  "geometry": {"coordinates":[5.3834729195,50.8548240662],"type":"Point"}
}