{
  "type": "Feature",
  "properties": {
    "addr:full":"Geraardsbergsestw 304 Aspelare Oost-Vlaanderen 9404",
    "addr:housenumber":"304",
    "addr:postcode":"9404",
    "addr:street":"Aspelare Oost-Vlaanderen",
    "iso:country":"BE",
    "sg:address":"Geraardsbergsestw 304",
    "sg:city":"Aspelare",
    "sg:classifiers":[
        {
            "category":"Banks & Credit Unions",
            "subcategory":"Bank",
            "type":"Services"
        }
    ],
    "sg:phone":"+32 54 32 84 71",
    "sg:postcode":"9404",
    "sg:province":"Oost-Vlaanderen",
    "wof:name":"G\u00e9n\u00e9rale De Banque Sa",
    "wof:placetype":"venue"
},
  "geometry": {"coordinates":[3.9576060772,50.8424186707],"type":"Point"}
}