{
  "type": "Feature",
  "properties": {
    "addr:full":"Waalpoelstraat 26 Assenede Oost-Vlaanderen 9960",
    "addr:housenumber":"26",
    "addr:postcode":"9960",
    "addr:street":"Waalpoelstraat",
    "iso:country":"BE",
    "sg:address":"Waalpoelstraat 26",
    "sg:city":"Assenede",
    "sg:classifiers":[
        {
            "category":"Real Estate",
            "subcategory":"Architect",
            "type":"Services"
        }
    ],
    "sg:phone":"+32 9 344 61 77",
    "sg:postcode":"9960",
    "sg:province":"Oost-Vlaanderen",
    "wof:name":"Mechelinck G",
    "wof:placetype":"venue"
},
  "geometry": {"coordinates":[3.7388958931,51.2205047607],"type":"Point"}
}