{
  "type": "Feature",
  "properties": {
    "iso:country":"BE",
    "sg:address":"Rue Jean Jaur\u00c8s 2",
    "sg:city":"Courcelles",
    "sg:orig_category":"Opvangtehuizen and vluchthuizen",
    "sg:phone":"+32 71 45 15 54",
    "sg:postcode":"6180",
    "sg:province":"Hainaut",
    "wof:name":"Centre De Service Social",
    "wof:placetype":"venue"
},
  "geometry": {"coordinates":[4.3757858276,50.45753479],"type":"Point"}
}