{
  "type": "Feature",
  "properties": {
    "iso:country":"BE",
    "sg:address":"Groeneweg 159",
    "sg:city":"Zulte",
    "sg:orig_category":"Installatie van houten of kunststof schrijnwerk",
    "sg:phone":"+32 9 388 52 14",
    "sg:postcode":"9870",
    "sg:province":"Oost-Vlaanderen",
    "wof:name":"Jan Callens",
    "wof:placetype":"venue"
},
  "geometry": {"coordinates":[3.4849879742,50.9390945435],"type":"Point"}
}