{
  "type": "Feature",
  "properties": {
    "addr:full":"Arnold Sauwenlaan 20 Dilsen-stokkem (stokkem) Limburg 3650",
    "addr:housenumber":"20",
    "addr:postcode":"3650",
    "addr:street":"Sauwenlaan",
    "iso:country":"BE",
    "sg:address":"Arnold Sauwenlaan 20",
    "sg:city":"Dilsen-stokkem (stokkem)",
    "sg:classifiers":[
        {
            "category":"Professional",
            "subcategory":"Art Services",
            "type":"Services"
        }
    ],
    "sg:phone":"+32 89 75 52 01",
    "sg:postcode":"3650",
    "sg:province":"Limburg",
    "sg:tags":[
        "interior",
        "designer"
    ],
    "wof:name":"Archi. Merken",
    "wof:placetype":"venue"
},
  "geometry": {"coordinates":[5.727396965,51.0364189148],"type":"Point"}
}