{
  "type": "Feature",
  "properties": {
    "iso:country":"BE",
    "sg:address":"Beernemstraat 103",
    "sg:city":"Wingene",
    "sg:classifiers":[
        {
            "category":"Health Services",
            "subcategory":"Health Practitioner",
            "type":"Services"
        }
    ],
    "sg:phone":"+32 51 65 85 00",
    "sg:postcode":"8750",
    "sg:province":"West-Vlaanderen",
    "sg:tags":[
        "physiotherapist"
    ],
    "wof:name":"Vanneste Jan",
    "wof:placetype":"venue"
},
  "geometry": {"coordinates":[3.2800810337,51.0641746521],"type":"Point"}
}