{
  "type": "Feature",
  "properties": {
    "iso:country":"BE",
    "sg:address":"Industrielaan 40",
    "sg:city":"Eeklo",
    "sg:orig_category":"Entreprises de travail adapt\u00e9",
    "sg:phone":"+32 9 377 40 29",
    "sg:postcode":"9900",
    "sg:province":"Oost-Vlaanderen",
    "wof:name":"Revam",
    "wof:placetype":"venue"
},
  "geometry": {"coordinates":[3.5459520817,51.1822967529],"type":"Point"}
}