{
  "type": "Feature",
  "properties": {
    "addr:full":"Rijksweg 952 Dilsen-stokkem (dilsen) Limburg 3650",
    "addr:housenumber":"952",
    "addr:postcode":"3650",
    "addr:street":"Rijksweg",
    "iso:country":"BE",
    "sg:address":"Rijksweg 952",
    "sg:city":"Dilsen-stokkem (dilsen)",
    "sg:classifiers":[
        {
            "category":"Manufacturing",
            "subcategory":"Furniture",
            "type":"Manufacturing & Wholesale Goods"
        }
    ],
    "sg:phone":"+32 89 56 66 21",
    "sg:postcode":"3650",
    "sg:province":"Limburg",
    "sg:tags":[
        "made",
        "-",
        "custom"
    ],
    "wof:name":"Kalders M",
    "wof:placetype":"venue"
},
  "geometry": {"coordinates":[5.7348308563,51.0439147949],"type":"Point"}
}