{
  "type": "Feature",
  "properties": {
    "iso:country":"BE",
    "sg:address":"Roosbloemstraat 8bb",
    "sg:city":"Oosterzele",
    "sg:orig_category":"Boomkwekerijen",
    "sg:phone":"+32 9 362 01 35",
    "sg:postcode":"9860",
    "sg:province":"Oost-Vlaanderen",
    "wof:name":"Michael Rahoens",
    "wof:placetype":"venue"
},
  "geometry": {"coordinates":[3.8207149506,50.9462547302],"type":"Point"}
}