{
  "type": "Feature",
  "properties": {
    "iso:country":"BE",
    "sg:address":"Rue Du Village 2",
    "sg:city":"Aubange",
    "sg:classifiers":[
        {
            "category":"Shopping",
            "subcategory":"Bicycles & Sporting Goods",
            "type":"Retail Goods"
        }
    ],
    "sg:phone":"+32 63 38 93 61",
    "sg:postcode":"6790",
    "sg:province":"Luxembourg",
    "sg:tags":[
        "article",
        "de",
        "sport",
        "camping"
    ],
    "wof:name":"Maison Muller Rossignon",
    "wof:placetype":"venue"
},
  "geometry": {"coordinates":[5.8043990135,49.5689849854],"type":"Point"}
}