{
  "type": "Feature",
  "properties": {
    "addr:full":"Grand'rue 32 Lessines Hainaut 7860",
    "addr:housenumber":"32",
    "addr:postcode":"7860",
    "addr:street":"Grand'Rue;Hainaut",
    "iso:country":"BE",
    "sg:address":"Grand'rue 32",
    "sg:city":"Lessines",
    "sg:classifiers":[
        {
            "category":"Bakery",
            "type":"Food & Drink"
        }
    ],
    "sg:phone":"+32 68 33 64 91",
    "sg:postcode":"7860",
    "sg:province":"Hainaut",
    "sg:tags":[
        "confectioner",
        "baker"
    ],
    "wof:name":"Lucy",
    "wof:placetype":"venue"
},
  "geometry": {"coordinates":[3.8290889263,50.7124633789],"type":"Point"}
}