{
  "type": "Feature",
  "properties": {
    "iso:country":"BE",
    "sg:address":"Zomerweg 12",
    "sg:city":"Lendelede",
    "sg:orig_category":"Royal Canin. Animaux domestiques and accessoires",
    "sg:phone":"+32 51 30 83 07",
    "sg:postcode":"8860",
    "sg:province":"West-Vlaanderen",
    "wof:name":"Verstraete Gilbert",
    "wof:placetype":"venue"
},
  "geometry": {"coordinates":[3.2518370152,50.8874740601],"type":"Point"}
}