{
  "type": "Feature",
  "properties": {
    "iso:country":"BE",
    "sg:address":"P. De Smet De Naeyerpln 16",
    "sg:city":"Gent",
    "sg:orig_category":"M\u00e9decins and sp\u00e9cialistes",
    "sg:phone":"+32 9 222 46 49",
    "sg:postcode":"9000",
    "sg:province":"Oost-Vlaanderen",
    "wof:name":"Gaston Verdonck",
    "wof:placetype":"venue"
},
  "geometry": {"coordinates":[3.7195289135,51.0306739807],"type":"Point"}
}