{
  "type": "Feature",
  "properties": {
    "addr:full":"Lange Beeldekensstraat 282 Antwerpen Antwerpen 2060",
    "addr:housenumber":"282",
    "addr:postcode":"2060",
    "addr:street":"Lange Beeldekensstraat",
    "iso:country":"BE",
    "sg:address":"Lange Beeldekensstraat 282",
    "sg:city":"Antwerpen",
    "sg:classifiers":[
        {
            "category":"Bars & Pubs",
            "type":"Food & Drink"
        }
    ],
    "sg:phone":"+32 3 235 10 42",
    "sg:postcode":"2060",
    "sg:province":"Antwerpen",
    "wof:name":"Bridge",
    "wof:placetype":"venue"
},
  "geometry": {"coordinates":[4.435049057,51.2219963074],"type":"Point"}
}