{
  "type": "Feature",
  "properties": {
    "addr:full":"Boulevard Audent 14 Box 5 Charleroi Hainaut 6000",
    "addr:housenumber":"14;5",
    "addr:postcode":"6000",
    "addr:street":"Boulevard Audent;Box;Hainaut",
    "iso:country":"BE",
    "sg:address":"Boulevard Audent 14 Box 5",
    "sg:city":"Charleroi",
    "sg:classifiers":[
        {
            "category":"Utilities",
            "subcategory":"Telephone",
            "type":"Services"
        }
    ],
    "sg:phone":"+32 71 23 81 38",
    "sg:postcode":"6000",
    "sg:province":"Hainaut",
    "sg:tags":[
        "-",
        "internet"
    ],
    "wof:name":"Cybercentre Ifpme",
    "wof:placetype":"venue"
},
  "geometry": {"coordinates":[4.4441080093,50.4096641541],"type":"Point"}
}