{
  "type": "Feature",
  "properties": {
    "addr:full":"Heirweg 63 Maaseik Limburg 3680",
    "addr:housenumber":"63",
    "addr:postcode":"3680",
    "addr:street":"Heirweg",
    "iso:country":"BE",
    "sg:address":"Heirweg 63",
    "sg:city":"Maaseik",
    "sg:classifiers":[
        {
            "category":"Professional",
            "subcategory":"Advertising",
            "type":"Services"
        }
    ],
    "sg:phone":"+32 89 57 22 36",
    "sg:postcode":"3680",
    "sg:province":"Limburg",
    "sg:tags":[
        "item",
        "-",
        "business",
        "gift",
        "promotional"
    ],
    "wof:name":"Romon Promotion Nv",
    "wof:placetype":"venue"
},
  "geometry": {"coordinates":[5.782720089,51.1023292542],"type":"Point"}
}