{
  "type": "Feature",
  "properties": {
    "addr:full":"Bouwelse Steenweg 36 Herenthout Antwerpen 2270",
    "addr:housenumber":"36",
    "addr:postcode":"2270",
    "addr:street":"Bouwelse Steenweg",
    "iso:country":"BE",
    "sg:address":"Bouwelse Steenweg 36",
    "sg:city":"Herenthout",
    "sg:classifiers":[
        {
            "category":"Professional",
            "subcategory":"Accounting & Tax Preparation",
            "type":"Services"
        }
    ],
    "sg:phone":"+32 14 50 07 32",
    "sg:postcode":"2270",
    "sg:province":"Antwerpen",
    "sg:tags":[
        "accountant"
    ],
    "wof:name":"Ceusters J Bvba",
    "wof:placetype":"venue"
},
  "geometry": {"coordinates":[4.7545647621,51.1424674988],"type":"Point"}
}