{
  "type": "Feature",
  "properties": {
    "addr:full":"Rue De Genleau 9 Lasne (lasne-chapelle-saint-lambert) Brabant Wallon 1380",
    "addr:housenumber":"9",
    "addr:postcode":"1380",
    "addr:street":"Rue De Genleau;Wallon",
    "iso:country":"BE",
    "sg:address":"Rue De Genleau 9",
    "sg:city":"Lasne (lasne-chapelle-saint-lambert)",
    "sg:classifiers":[
        {
            "category":"Health Services",
            "subcategory":"Dentist",
            "type":"Services"
        }
    ],
    "sg:phone":"+32 2 633 16 60",
    "sg:postcode":"1380",
    "sg:province":"Brabant Wallon",
    "wof:name":"Ferdowsi Guilda",
    "wof:placetype":"venue"
},
  "geometry": {"coordinates":[4.4812550545,50.6849212646],"type":"Point"}
}