{
  "type": "Feature",
  "properties": {
    "iso:country":"BE",
    "sg:address":"Leuvensesteenweg 81",
    "sg:city":"Tervuren",
    "sg:classifiers":[
        {
            "category":"Autos & Motor Vehicles",
            "subcategory":"Fuel & Gas Station",
            "type":"Retail Goods"
        }
    ],
    "sg:phone":"+32 2 767 12 64",
    "sg:postcode":"3080",
    "sg:province":"Vlaams-Brabant",
    "sg:tags":[
        "stations-service",
        "carburants"
    ],
    "wof:name":"Jet",
    "wof:placetype":"venue"
},
  "geometry": {"coordinates":[4.5429229736,50.8382873535],"type":"Point"}
}