{
  "type": "Feature",
  "properties": {
    "iso:country":"BE",
    "sg:address":"Sparreweg 187",
    "sg:city":"Tessenderlo",
    "sg:orig_category":"Tuinen",
    "sg:phone":"+32 13 66 23 98",
    "sg:postcode":"3980",
    "sg:province":"Limburg",
    "wof:name":"'t Vijvertje",
    "wof:placetype":"venue"
},
  "geometry": {"coordinates":[5.0443401337,51.0595550537],"type":"Point"}
}