{
  "type": "Feature",
  "properties": {
    "addr:full":"Centrum Zuid 3041 Houthalen-helchteren (houthalen) Limburg 3530",
    "addr:postcode":"3041;3530",
    "addr:street":"Centrum Zuid",
    "iso:country":"BE",
    "sg:address":"Centrum Zuid 3041",
    "sg:city":"Houthalen-helchteren (houthalen)",
    "sg:classifiers":[
        {
            "category":"Transit Center",
            "subcategory":"Freight",
            "type":"Transportation"
        }
    ],
    "sg:phone":"+32 11 52 58 80",
    "sg:postcode":"3530",
    "sg:province":"Limburg",
    "sg:tags":[
        "-",
        "tape",
        "adhesive"
    ],
    "wof:name":"A.d. Products Nv",
    "wof:placetype":"venue"
},
  "geometry": {"coordinates":[5.3625979424,51.0190887451],"type":"Point"}
}