{
  "type": "Feature",
  "properties": {
    "addr:full":"Sint-gummarusstraat 24 Antwerpen Antwerpen 2060",
    "addr:housenumber":"24",
    "addr:postcode":"2060",
    "addr:street":"Sint-Gummarusstraat",
    "iso:country":"BE",
    "sg:address":"Sint-gummarusstraat 24",
    "sg:city":"Antwerpen",
    "sg:classifiers":[
        {
            "category":"Health Services",
            "subcategory":"Health Practitioner",
            "type":"Services"
        }
    ],
    "sg:phone":"+32 3 231 44 46",
    "sg:postcode":"2060",
    "sg:province":"Antwerpen",
    "sg:tags":[
        "physiotherapist"
    ],
    "wof:name":"Camerlynck Bj\u00f6rn",
    "wof:placetype":"venue"
},
  "geometry": {"coordinates":[4.4200549126,51.2246932983],"type":"Point"}
}