{
  "type": "Feature",
  "properties": {
    "addr:full":"Avenue De La Balance 12b Waterloo Brabant Wallon 1410",
    "addr:housenumber":"12b",
    "addr:postcode":"1410",
    "addr:street":"Avenue De La Balance",
    "iso:country":"BE",
    "sg:address":"Avenue De La Balance 12b",
    "sg:city":"Waterloo",
    "sg:classifiers":[
        {
            "category":"Building & Trades",
            "subcategory":"Pest Control",
            "type":"Services"
        }
    ],
    "sg:phone":"+32 2 354 33 86",
    "sg:postcode":"1410",
    "sg:province":"Brabant Wallon",
    "sg:tags":[
        "painting",
        "contractor"
    ],
    "wof:name":"Paradis P",
    "wof:placetype":"venue"
},
  "geometry": {"coordinates":[4.409924984,50.7011680603],"type":"Point"}
}