{
  "type": "Feature",
  "properties": {
    "addr:full":"Mechelsesteenweg 38 Antwerpen (groot) Antwerpen 2018",
    "addr:housenumber":"38",
    "addr:postcode":"2018",
    "addr:street":"Mechelsesteenweg;Groot Antwerpen",
    "iso:country":"BE",
    "sg:address":"Mechelsesteenweg 38",
    "sg:city":"Antwerpen (groot)",
    "sg:orig_category":"Banques and organismes de cr\u00e9dit",
    "sg:phone":"+32 3 238 11 25",
    "sg:postcode":"2018",
    "sg:province":"Antwerpen",
    "wof:name":"Recordbank",
    "wof:placetype":"venue"
},
  "geometry": {"coordinates":[4.4077987671,51.2098693848],"type":"Point"}
}