{
  "type": "Feature",
  "properties": {
    "addr:full":"Pikstraat 71 Londerzeel Vlaams-Brabant 1840",
    "addr:housenumber":"71",
    "addr:postcode":"1840",
    "addr:street":"Pikstraat",
    "iso:country":"BE",
    "sg:address":"Pikstraat 71",
    "sg:city":"Londerzeel",
    "sg:classifiers":[
        {
            "category":"Farming",
            "subcategory":"Berry Farm",
            "type":"Manufacturing & Wholesale Goods"
        }
    ],
    "sg:phone":"+32 52 30 25 01",
    "sg:postcode":"1840",
    "sg:province":"Vlaams-Brabant",
    "sg:tags":[
        "horticulture",
        "-",
        "broker",
        "whol",
        "seed",
        "grain",
        "agriculture"
    ],
    "wof:name":"Guido Robberechts Bvba",
    "wof:placetype":"venue"
},
  "geometry": {"coordinates":[4.3134188652,51.0214538574],"type":"Point"}
}