{
  "type": "Feature",
  "properties": {
    "addr:full":"Rue Des Enfers 40 Brugelette Hainaut 7941",
    "addr:housenumber":"40",
    "addr:postcode":"7941",
    "addr:street":"Rue Des Enfers;Hainaut",
    "iso:country":"BE",
    "sg:address":"Rue Des Enfers 40",
    "sg:city":"Brugelette",
    "sg:orig_category":"Herstellingen and onderhoud aan huis voor voertuigen Herstellingen and onderhoud van auto's Metaalaf",
    "sg:phone":"+32 68 45 56 54",
    "sg:postcode":"7941",
    "sg:province":"Hainaut",
    "wof:name":"Garage Willain",
    "wof:placetype":"venue"
},
  "geometry": {"coordinates":[3.8395678997,50.6083450317],"type":"Point"}
}