{
  "type": "Feature",
  "properties": {
    "addr:full":"Spoorwegstraat 16 Evergem Oost-Vlaanderen 9940",
    "addr:housenumber":"16",
    "addr:postcode":"9940",
    "addr:street":"Spoorwegstraat;Oost-Vlaanderen",
    "iso:country":"BE",
    "sg:address":"Spoorwegstraat 16",
    "sg:city":"Evergem",
    "sg:orig_category":"Salles de conf\u00e9rences and de r\u00e9ceptions",
    "sg:phone":"+32 9 253 80 56",
    "sg:postcode":"9940",
    "sg:province":"Oost-Vlaanderen",
    "wof:name":"Feestzaal Volksverheffing",
    "wof:placetype":"venue"
},
  "geometry": {"coordinates":[3.7031860352,51.1074676514],"type":"Point"}
}