{
  "type": "Feature",
  "properties": {
    "iso:country":"BE",
    "sg:address":"V. Coppensstraat 9",
    "sg:city":"Sint-gillis-waas",
    "sg:classifiers":[
        {
            "category":"Home & Garden",
            "subcategory":"Carpets & Floor Coverings",
            "type":"Retail Goods"
        }
    ],
    "sg:phone":"+32 3 770 79 80",
    "sg:postcode":"9170",
    "sg:province":"Oost-Vlaanderen",
    "sg:tags":[
        "layer",
        "mosaicists"
    ],
    "wof:name":"Kegels Vloerwerken Bvba",
    "wof:placetype":"venue"
},
  "geometry": {"coordinates":[4.1231479645,51.2165718079],"type":"Point"}
}