{
  "type": "Feature",
  "properties": {
    "addr:full":"Rue Des Combattants 53 Tubize (clabecq) Brabant Wallon 1480",
    "addr:housenumber":"53",
    "addr:postcode":"1480",
    "addr:street":"Rue Des Combattants;Wallon",
    "iso:country":"BE",
    "sg:address":"Rue Des Combattants 53",
    "sg:city":"Tubize (clabecq)",
    "sg:classifiers":[
        {
            "category":"Health Services",
            "subcategory":"Doctor",
            "type":"Services"
        }
    ],
    "sg:phone":"+32 2 355 20 73",
    "sg:postcode":"1480",
    "sg:province":"Brabant Wallon",
    "sg:tags":[
        "medicinephysicians",
        "surgeon"
    ],
    "wof:name":"Courtoy I",
    "wof:placetype":"venue"
},
  "geometry": {"coordinates":[4.2353582382,50.6803207397],"type":"Point"}
}