{
  "type": "Feature",
  "properties": {
    "iso:country":"BE",
    "sg:address":"Gerhagen 5",
    "sg:city":"Olen",
    "sg:classifiers":[
        {
            "category":"Restaurant",
            "type":"Food & Drink"
        }
    ],
    "sg:phone":"+32 14 21 61 85",
    "sg:postcode":"2250",
    "sg:province":"Antwerpen",
    "sg:tags":[
        "caf\u00e9s"
    ],
    "wof:name":"Taverne Bagatel",
    "wof:placetype":"venue"
},
  "geometry": {"coordinates":[4.9124798775,51.1634407043],"type":"Point"}
}