{
  "type": "Feature",
  "properties": {
    "iso:country":"BE",
    "sg:address":"Kleine Warmestraat 33",
    "sg:city":"Maldegem",
    "sg:orig_category":"Meubles D\u00e9taillants, Am\u00e9nagement de B\u00e2timents et de Cuisines",
    "sg:phone":"+32 50 71 52 67",
    "sg:postcode":"9990",
    "sg:province":"Oost-Vlaanderen",
    "wof:name":"Therese Matthys",
    "wof:placetype":"venue"
},
  "geometry": {"coordinates":[3.4511640072,51.2172431946],"type":"Point"}
}