{
  "type": "Feature",
  "properties": {
    "addr:full":"Albert Van Cotthemstraat 54 Sint-pieters-leeuw Vlaams-Brabant 1600",
    "addr:housenumber":"54",
    "addr:postcode":"1600",
    "addr:street":"Albert Van Cotthemstraat",
    "iso:country":"BE",
    "sg:address":"Albert Van Cotthemstraat 54",
    "sg:city":"Sint-pieters-leeuw",
    "sg:classifiers":[
        {
            "category":"Retail",
            "subcategory":"Event Space",
            "type":"Services"
        }
    ],
    "sg:phone":"+32 2 378 30 60",
    "sg:postcode":"1600",
    "sg:province":"Vlaams-Brabant",
    "sg:tags":[
        "box",
        "chemical-pharmaceutical",
        "industry",
        "cardboard"
    ],
    "wof:name":"Field Boxmore Healthcare Packaging Brussels Nv",
    "wof:placetype":"venue"
},
  "geometry": {"coordinates":[4.2845659256,50.8017311096],"type":"Point"}
}