{
  "type": "Feature",
  "properties": {
    "iso:country":"BE",
    "sg:address":"Rue Z\u00c9phirin Fontaine 0",
    "sg:city":"Binche",
    "sg:orig_category":"Supermarch\u00e9s",
    "sg:phone":"+32 64 33 45 45",
    "sg:postcode":"7130",
    "sg:province":"Hainaut",
    "wof:name":"Match",
    "wof:placetype":"venue"
},
  "geometry": {"coordinates":[4.1660728455,50.412311554],"type":"Point"}
}