{
  "type": "Feature",
  "properties": {
    "iso:country":"BE",
    "sg:address":"Noorderlaan 139",
    "sg:city":"Antwerpen",
    "sg:classifiers":[
        {
            "category":"Transit Center",
            "subcategory":"Freight",
            "type":"Transportation"
        }
    ],
    "sg:phone":"+32 3 545 06 11",
    "sg:postcode":"2030",
    "sg:province":"Antwerpen",
    "sg:tags":[
        "forwarding",
        "agency"
    ],
    "wof:name":"Hapag-lloyd Belgium Nv",
    "wof:placetype":"venue"
},
  "geometry": {"coordinates":[4.4007821083,51.2644691467],"type":"Point"}
}