{
  "type": "Feature",
  "properties": {
    "iso:country":"BE",
    "sg:address":"Eeuwfeestlaan 56",
    "sg:city":"Lier",
    "sg:classifiers":[
        {
            "category":"Professional",
            "subcategory":"Accounting & Tax Preparation",
            "type":"Services"
        }
    ],
    "sg:phone":"+32 3 489 05 43",
    "sg:postcode":"2500",
    "sg:province":"Antwerpen",
    "sg:tags":[
        "accountant"
    ],
    "wof:name":"Fiduciaire Eulaers Bvba",
    "wof:placetype":"venue"
},
  "geometry": {"coordinates":[4.5605068207,51.1386413574],"type":"Point"}
}