{
  "type": "Feature",
  "properties": {
    "addr:full":"Rue Des Taillettes 20 Court-saint-etienne Brabant Wallon 1490",
    "addr:housenumber":"20;1490",
    "addr:street":"Rue Des Taillettes",
    "iso:country":"BE",
    "sg:address":"Rue Des Taillettes 20",
    "sg:city":"Court-saint-etienne",
    "sg:classifiers":[
        {
            "category":"Taxi",
            "type":"Transportation"
        }
    ],
    "sg:phone":"+32 10 61 64 41",
    "sg:postcode":"1490",
    "sg:province":"Brabant Wallon",
    "sg:tags":[
        "taxi's"
    ],
    "wof:name":"Taxi Dantoing",
    "wof:placetype":"venue"
},
  "geometry": {"coordinates":[4.5511250496,50.6422843933],"type":"Point"}
}