{
  "type": "Feature",
  "properties": {
    "addr:full":"Sint-annastraat 29 Hoeilaart Vlaams-Brabant 1560",
    "addr:housenumber":"29",
    "addr:postcode":"1560",
    "addr:street":"Sint-Annastraat",
    "iso:country":"BE",
    "sg:address":"Sint-annastraat 29",
    "sg:city":"Hoeilaart",
    "sg:orig_category":"Peinture. Rev\u00eatements pour sols and murs",
    "sg:phone":"+32 2 657 64 10",
    "sg:postcode":"1560",
    "sg:province":"Vlaams-Brabant",
    "wof:name":"Vanstallen Decor",
    "wof:placetype":"venue"
},
  "geometry": {"coordinates":[4.4790148735,50.7622756958],"type":"Point"}
}