{
  "type": "Feature",
  "properties": {
    "iso:country":"BE",
    "sg:address":"Chauss\u00e9e De Waterloo 1336",
    "sg:city":"Bruxelles (uccle)",
    "sg:classifiers":[
        {
            "category":"Professional",
            "subcategory":"Engineering",
            "type":"Services"
        }
    ],
    "sg:phone":"+32 2 646 47 47",
    "sg:postcode":"1180",
    "sg:province":"Bruxelles-Capitale",
    "sg:tags":[
        "lighting",
        "-"
    ],
    "wof:name":"Metrac Fiber Optic Lighting",
    "wof:placetype":"venue"
},
  "geometry": {"coordinates":[4.3749141693,50.7901268005],"type":"Point"}
}