{
  "type": "Feature",
  "properties": {
    "addr:full":"Rue Des Ecomines 2 Spa Li\u00e8ge 4900",
    "addr:housenumber":"2",
    "addr:postcode":"4900",
    "addr:street":"Rue Des Ecomines",
    "iso:country":"BE",
    "sg:address":"Rue Des Ecomines 2",
    "sg:city":"Spa",
    "sg:classifiers":[
        {
            "category":"Bakery",
            "type":"Food & Drink"
        }
    ],
    "sg:phone":"+32 87 77 13 31",
    "sg:postcode":"4900",
    "sg:province":"Li\u00e8ge",
    "sg:tags":[
        "confectioner",
        "baker"
    ],
    "wof:name":"Caligola",
    "wof:placetype":"venue"
},
  "geometry": {"coordinates":[5.8662719727,50.4908828735],"type":"Point"}
}