{
  "type": "Feature",
  "properties": {
    "addr:full":"Rue Emile-baudrux 3 Habay Luxembourg 6720",
    "addr:housenumber":"3",
    "addr:postcode":"6720",
    "addr:street":"Rue Emile-Baudrux",
    "iso:country":"BE",
    "sg:address":"Rue Emile-baudrux 3",
    "sg:city":"Habay",
    "sg:orig_category":"Banques and organismes de cr\u00e9dit",
    "sg:phone":"+32 63 42 28 27",
    "sg:postcode":"6720",
    "sg:province":"Luxembourg",
    "wof:name":"Fortis",
    "wof:placetype":"venue"
},
  "geometry": {"coordinates":[5.6468100548,49.7278633118],"type":"Point"}
}