{
  "type": "Feature",
  "properties": {
    "iso:country":"BE",
    "sg:address":"Rue Aux Gades 21",
    "sg:city":"Ath",
    "sg:orig_category":"Eclairage et \u00e9quipements du foyer. Textiles. Meubles D\u00e9taillants, Am\u00e9nagement de B\u00e2timents et de Cui",
    "sg:phone":"+32 68 28 15 11",
    "sg:postcode":"7800",
    "sg:province":"Hainaut",
    "wof:name":"La Maison De Nathalie",
    "wof:placetype":"venue"
},
  "geometry": {"coordinates":[3.7759919167,50.6301269531],"type":"Point"}
}