{
  "type": "Feature",
  "properties": {
    "addr:full":"Kwadries 113 Wevelgem West-Vlaanderen 8560",
    "addr:housenumber":"113",
    "addr:postcode":"8560",
    "iso:country":"BE",
    "sg:address":"Kwadries 113",
    "sg:city":"Wevelgem",
    "sg:classifiers":[
        {
            "category":"Recreation",
            "type":"Entertainment"
        }
    ],
    "sg:phone":"+32 56 40 00 67",
    "sg:postcode":"8560",
    "sg:province":"West-Vlaanderen",
    "sg:tags":[
        "diver",
        "amusement"
    ],
    "wof:name":"D.j. Telstar",
    "wof:placetype":"venue"
},
  "geometry": {"coordinates":[3.2026600838,50.8475227356],"type":"Point"}
}