{
  "type": "Feature",
  "properties": {
    "iso:country":"BE",
    "sg:address":"Sint-antoniusstraat 5",
    "sg:city":"Geel",
    "sg:orig_category":"Woningbouw",
    "sg:phone":"+32 14 59 31 08",
    "sg:postcode":"2440",
    "sg:province":"Antwerpen",
    "wof:name":"J En A Laenen",
    "wof:placetype":"venue"
},
  "geometry": {"coordinates":[5.063642025,51.1680297852],"type":"Point"}
}