{
  "type": "Feature",
  "properties": {
    "addr:full":"Windhalmstraat 42 Antwerpen Antwerpen 2040",
    "addr:housenumber":"42",
    "addr:postcode":"2040",
    "addr:street":"Windhalmstraat",
    "iso:country":"BE",
    "sg:address":"Windhalmstraat 42",
    "sg:city":"Antwerpen",
    "sg:classifiers":[
        {
            "category":"Fast Food",
            "type":"Food & Drink"
        }
    ],
    "sg:phone":"+32 475 51 74 00",
    "sg:postcode":"2040",
    "sg:province":"Antwerpen",
    "sg:tags":[
        "fried",
        "stand",
        "potato"
    ],
    "wof:name":"Van Schoor & Co",
    "wof:placetype":"venue"
},
  "geometry": {"coordinates":[4.3141150475,51.3429756165],"type":"Point"}
}