{
  "type": "Feature",
  "properties": {
    "addr:full":"Pannestraat 24 Veurne West-Vlaanderen 8630",
    "addr:housenumber":"24",
    "addr:postcode":"8630",
    "addr:street":"Pannestraat",
    "iso:country":"BE",
    "sg:address":"Pannestraat 24",
    "sg:city":"Veurne",
    "sg:classifiers":[
        {
            "category":"Bars & Pubs",
            "type":"Food & Drink"
        }
    ],
    "sg:phone":"+32 58 31 74 00",
    "sg:postcode":"8630",
    "sg:province":"West-Vlaanderen",
    "wof:name":"Zeemanshuis",
    "wof:placetype":"venue"
},
  "geometry": {"coordinates":[2.660378933,51.074131012],"type":"Point"}
}