{
  "type": "Feature",
  "properties": {
    "addr:full":"Kortrijkstraat 341b2 Wevelgem West-Vlaanderen 8560",
    "addr:housenumber":"341b2",
    "addr:postcode":"8560",
    "addr:street":"Kortrijkstraat",
    "iso:country":"BE",
    "sg:address":"Kortrijkstraat 341b2",
    "sg:city":"Wevelgem",
    "sg:orig_category":"Chaussures",
    "sg:phone":"+32 56 42 42 12",
    "sg:postcode":"8560",
    "sg:province":"West-Vlaanderen",
    "wof:name":"Primo",
    "wof:placetype":"venue"
},
  "geometry": {"coordinates":[3.21113801,50.8170204163],"type":"Point"}
}