{
  "type": "Feature",
  "properties": {
    "addr:full":"Tienne Aux Pierres 101 Namur (w\u00e9pion) Namur 5100",
    "addr:housenumber":"101",
    "addr:postcode":"5100",
    "iso:country":"BE",
    "sg:address":"Tienne Aux Pierres 101",
    "sg:city":"Namur (w\u00e9pion)",
    "sg:classifiers":[
        {
            "category":"Professional",
            "subcategory":"Management & Consulting",
            "type":"Services"
        }
    ],
    "sg:phone":"+32 81 47 05 12",
    "sg:postcode":"5100",
    "sg:province":"Namur",
    "sg:tags":[
        "consultant"
    ],
    "wof:name":"Alba Concept Sa",
    "wof:placetype":"venue"
},
  "geometry": {"coordinates":[4.8601021767,50.4058990479],"type":"Point"}
}