{
  "type": "Feature",
  "properties": {
    "addr:full":"Steenakkerdreef 9 Destelbergen Oost-Vlaanderen 9070",
    "addr:housenumber":"9",
    "addr:postcode":"9070",
    "addr:street":"Steenakkerdreef",
    "iso:country":"BE",
    "sg:address":"Steenakkerdreef 9",
    "sg:city":"Destelbergen",
    "sg:orig_category":"Maisons de vacances",
    "sg:phone":"+32 9 229 11 10",
    "sg:postcode":"9070",
    "sg:province":"Oost-Vlaanderen",
    "wof:name":"Lagacie Alex",
    "wof:placetype":"venue"
},
  "geometry": {"coordinates":[3.7797729969,51.0536308289],"type":"Point"}
}