{
  "type": "Feature",
  "properties": {
    "addr:full":"Rue Du Faucon 2a Brussel/bruxelles Bruxelles-Capitale 1000",
    "addr:housenumber":"2a",
    "addr:postcode":"1000",
    "addr:street":"Rue Du Faucon;/",
    "iso:country":"BE",
    "sg:address":"Rue Du Faucon 2a",
    "sg:city":"Brussel/bruxelles",
    "sg:classifiers":[
        {
            "category":"Restaurant",
            "type":"Food & Drink"
        }
    ],
    "sg:phone":"+32 2 502 19 81",
    "sg:postcode":"1000",
    "sg:province":"Bruxelles-Capitale",
    "wof:name":"Le Pinnemoech",
    "wof:placetype":"venue"
},
  "geometry": {"coordinates":[4.3485732079,50.8367729187],"type":"Point"}
}