{
  "type": "Feature",
  "properties": {
    "addr:full":"Koekoekstraat 85 Waregem (sint-eloois-vijve) West-Vlaanderen 8793",
    "addr:housenumber":"85",
    "addr:postcode":"8793",
    "addr:street":"Koekoekstraat",
    "iso:country":"BE",
    "sg:address":"Koekoekstraat 85",
    "sg:city":"Waregem (sint-eloois-vijve)",
    "sg:classifiers":[
        {
            "category":"Building & Trades",
            "subcategory":"Construction",
            "type":"Services"
        }
    ],
    "sg:phone":"+32 56 60 70 84",
    "sg:postcode":"8793",
    "sg:province":"West-Vlaanderen",
    "sg:tags":[
        "installation",
        "-",
        "central",
        "heating"
    ],
    "wof:name":"Devos Jan Bvba",
    "wof:placetype":"venue"
},
  "geometry": {"coordinates":[3.4030990601,50.9017295837],"type":"Point"}
}