{
  "type": "Feature",
  "properties": {
    "iso:country":"BE",
    "sg:address":"Maarschalk Fochstraat 12-14",
    "sg:city":"Leopoldsburg",
    "sg:classifiers":[
        {
            "category":"Education",
            "subcategory":"School",
            "type":"Public Place"
        }
    ],
    "sg:phone":"+32 11 34 17 87",
    "sg:postcode":"3970",
    "sg:province":"Limburg",
    "sg:tags":[
        "supply"
    ],
    "wof:name":"Huis Moestermans",
    "wof:placetype":"venue"
},
  "geometry": {"coordinates":[5.26121521,51.1167755127],"type":"Point"}
}