{
  "type": "Feature",
  "properties": {
    "iso:country":"BE",
    "sg:address":"Hoefijzerlaan 24",
    "sg:city":"Brugge",
    "sg:classifiers":[
        {
            "category":"Manufacturing",
            "subcategory":"Furniture",
            "type":"Manufacturing & Wholesale Goods"
        }
    ],
    "sg:phone":"+32 50 34 60 05",
    "sg:postcode":"8000",
    "sg:province":"West-Vlaanderen",
    "sg:tags":[
        "armchair",
        "-"
    ],
    "wof:name":"Loft (de)",
    "wof:placetype":"venue"
},
  "geometry": {"coordinates":[3.2159779072,51.2073974609],"type":"Point"}
}