{
  "type": "Feature",
  "properties": {
    "iso:country":"BE",
    "sg:address":"Zaanstraat 5",
    "sg:city":"Antwerpen",
    "sg:classifiers":[
        {
            "category":"Professional",
            "subcategory":"Accounting & Tax Preparation",
            "type":"Services"
        }
    ],
    "sg:phone":"+32 3 216 10 68",
    "sg:postcode":"2020",
    "sg:province":"Antwerpen",
    "sg:tags":[
        "bookkeeper"
    ],
    "wof:name":"Vermeiren G",
    "wof:placetype":"venue"
},
  "geometry": {"coordinates":[4.3788909912,51.1912269592],"type":"Point"}
}