{
  "type": "Feature",
  "properties": {
    "iso:country":"BE",
    "sg:address":"Veldbloemenlaan 5",
    "sg:city":"Bertem (leefdaal)",
    "sg:classifiers":[
        {
            "category":"Professional",
            "subcategory":"Management & Consulting",
            "type":"Services"
        }
    ],
    "sg:phone":"+32 2 767 22 48",
    "sg:postcode":"3061",
    "sg:province":"Vlaams-Brabant",
    "sg:tags":[
        "consultant"
    ],
    "wof:name":"Devolder G",
    "wof:placetype":"venue"
},
  "geometry": {"coordinates":[4.5910139084,50.8443603516],"type":"Point"}
}