{
  "type": "Feature",
  "properties": {
    "iso:country":"BE",
    "sg:address":"Lauwsestraat 79",
    "sg:city":"Kortrijk",
    "sg:orig_category":"Rundveehouders",
    "sg:phone":"+32 56 42 61 42",
    "sg:postcode":"8511",
    "sg:province":"West-Vlaanderen",
    "wof:name":"Christophe Dejonckheere",
    "wof:placetype":"venue"
},
  "geometry": {"coordinates":[3.2219400406,50.7800674438],"type":"Point"}
}