{
  "type": "Feature",
  "properties": {
    "addr:full":"Place Albert Ier 7 Manage Hainaut 7170",
    "addr:housenumber":"7",
    "addr:postcode":"7170",
    "addr:street":"Place Albert Ier",
    "iso:country":"BE",
    "sg:address":"Place Albert Ier 7",
    "sg:city":"Manage",
    "sg:orig_category":"Openbare veiligheid",
    "sg:phone":"+32 64 51 83 04",
    "sg:postcode":"7170",
    "sg:province":"Hainaut",
    "wof:name":"Police F\u00c9d\u00c9rale",
    "wof:placetype":"venue"
},
  "geometry": {"coordinates":[4.22874403,50.4904518127],"type":"Point"}
}