{
  "type": "Feature",
  "properties": {
    "addr:full":"Hasseltsepoort 2 Bilzen Limburg 3740",
    "addr:housenumber":"2",
    "addr:postcode":"3740",
    "addr:street":"Hasseltsepoort",
    "iso:country":"BE",
    "sg:address":"Hasseltsepoort 2",
    "sg:city":"Bilzen",
    "sg:classifiers":[
        {
            "category":"Health Services",
            "subcategory":"Doctor",
            "type":"Services"
        }
    ],
    "sg:phone":"+32 89 41 12 26",
    "sg:postcode":"3740",
    "sg:province":"Limburg",
    "sg:tags":[
        "medicinephysicians",
        "surgeon"
    ],
    "wof:name":"Geusens Paul",
    "wof:placetype":"venue"
},
  "geometry": {"coordinates":[5.4900717735,50.8819389343],"type":"Point"}
}