{
  "type": "Feature",
  "properties": {
    "addr:full":"Sint-salvatorskerkhof 5 Brugge West-Vlaanderen 8000",
    "addr:housenumber":"5",
    "addr:postcode":"8000",
    "addr:street":"Sint-Salvatorskerkhof",
    "iso:country":"BE",
    "sg:address":"Sint-salvatorskerkhof 5",
    "sg:city":"Brugge",
    "sg:classifiers":[
        {
            "category":"Cafe",
            "type":"Food & Drink"
        }
    ],
    "sg:phone":"+32 50 33 03 51",
    "sg:postcode":"8000",
    "sg:province":"West-Vlaanderen",
    "sg:tags":[
        "caf\u00e9s"
    ],
    "wof:name":"Caf\u00c9 The Top",
    "wof:placetype":"venue"
},
  "geometry": {"coordinates":[3.2220470905,51.2059593201],"type":"Point"}
}