{
  "type": "Feature",
  "properties": {
    "addr:full":"Rijksweg 440 Maasmechelen Limburg 3630",
    "addr:housenumber":"440",
    "addr:postcode":"3630",
    "addr:street":"Rijksweg",
    "iso:country":"BE",
    "sg:address":"Rijksweg 440",
    "sg:city":"Maasmechelen",
    "sg:orig_category":"HUISBRANDOLIE MEUBELONTWERP AND -INSTALLATIE",
    "sg:phone":"+32 89 76 41 99",
    "sg:postcode":"3630",
    "sg:province":"Limburg",
    "wof:name":"Keukens Warson",
    "wof:placetype":"venue"
},
  "geometry": {"coordinates":[5.6952090263,50.9635696411],"type":"Point"}
}