{
  "type": "Feature",
  "properties": {
    "addr:full":"Potstraat 75 Tienen (bost) Vlaams-Brabant 3300",
    "addr:housenumber":"75",
    "addr:postcode":"3300",
    "addr:street":"Potstraat",
    "iso:country":"BE",
    "sg:address":"Potstraat 75",
    "sg:city":"Tienen (bost)",
    "sg:classifiers":[
        {
            "category":"Retail",
            "subcategory":"Animal Services",
            "type":"Services"
        }
    ],
    "sg:phone":"+32 16 81 73 94",
    "sg:postcode":"3300",
    "sg:province":"Vlaams-Brabant",
    "sg:tags":[
        "grooming",
        "-",
        "dog"
    ],
    "wof:name":"Kiky",
    "wof:placetype":"venue"
},
  "geometry": {"coordinates":[4.9382982254,50.800201416],"type":"Point"}
}