{
  "type": "Feature",
  "properties": {
    "iso:country":"BE",
    "sg:address":"Vennestraat 46",
    "sg:city":"Genk",
    "sg:classifiers":[
        {
            "category":"Retail",
            "subcategory":"Auto Repair",
            "type":"Services"
        }
    ],
    "sg:phone":"+32 89 61 59 09",
    "sg:postcode":"3600",
    "sg:province":"Limburg",
    "sg:tags":[
        "lpg",
        "automobile",
        "-",
        "system"
    ],
    "wof:name":"Dmd Auto Bvba",
    "wof:placetype":"venue"
},
  "geometry": {"coordinates":[5.4921398163,50.9804916382],"type":"Point"}
}