{
  "type": "Feature",
  "properties": {
    "iso:country":"BE",
    "sg:address":"Rue De L'universit\u00c9 39",
    "sg:city":"Li\u00c8ge",
    "sg:orig_category":"Kansspelen",
    "sg:phone":"+32 4 223 14 17",
    "sg:postcode":"4000",
    "sg:province":"Li\u00e8ge",
    "wof:name":"Ladbrokes",
    "wof:placetype":"venue"
},
  "geometry": {"coordinates":[5.5743851662,50.6415328979],"type":"Point"}
}