{
  "type": "Feature",
  "properties": {
    "addr:full":"Antwerpsesteenweg 78 Vosselaar Antwerpen 2350",
    "addr:housenumber":"78",
    "addr:postcode":"2350",
    "addr:street":"Antwerpsesteenweg",
    "iso:country":"BE",
    "sg:address":"Antwerpsesteenweg 78",
    "sg:city":"Vosselaar",
    "sg:classifiers":[
        {
            "category":"Sports & Exercise",
            "subcategory":"Gym",
            "type":"Entertainment"
        }
    ],
    "sg:phone":"+32 14 61 90 03",
    "sg:postcode":"2350",
    "sg:province":"Antwerpen",
    "sg:tags":[
        "fitness"
    ],
    "wof:name":"Hi-tech Gym",
    "wof:placetype":"venue"
},
  "geometry": {"coordinates":[4.8884720802,51.3149719238],"type":"Point"}
}