{
  "type": "Feature",
  "properties": {
    "iso:country":"BE",
    "sg:address":"Rue D'engihoul 106",
    "sg:city":"Nandrin",
    "sg:orig_category":"SMEEDWERK, METAALBEWERKING AND POEDERMETALLURGIE",
    "sg:phone":"+32 4 371 37 99",
    "sg:postcode":"4550",
    "sg:province":"Li\u00e8ge",
    "wof:name":"Cloix",
    "wof:placetype":"venue"
},
  "geometry": {"coordinates":[5.4190979004,50.5247573853],"type":"Point"}
}