{
  "type": "Feature",
  "properties": {
    "iso:country":"BE",
    "sg:address":"Rue Dejoncker 21",
    "sg:city":"Sint-gillis/saint-gilles",
    "sg:classifiers":[
        {
            "category":"Fast Food",
            "type":"Food & Drink"
        }
    ],
    "sg:phone":"+32 2 537 49 57",
    "sg:postcode":"1060",
    "sg:province":"Bruxelles-Capitale",
    "sg:tags":[
        "de",
        "restaurant",
        "organisation",
        "\u00c0",
        "catering",
        "emporter",
        "f\u00cates",
        "restaurants"
    ],
    "wof:name":"Restaurant Vitale",
    "wof:placetype":"venue"
},
  "geometry": {"coordinates":[4.354724884,50.8342056274],"type":"Point"}
}