{
  "type": "Feature",
  "properties": {
    "iso:country":"BE",
    "sg:address":"Battelsesteenweg 256",
    "sg:city":"Mechelen",
    "sg:classifiers":[
        {
            "category":"Shopping",
            "subcategory":"Florist",
            "type":"Retail Goods"
        }
    ],
    "sg:phone":"+32 15 27 17 07",
    "sg:postcode":"2800",
    "sg:province":"Antwerpen",
    "wof:name":"Bloemen Goossens",
    "wof:placetype":"venue"
},
  "geometry": {"coordinates":[4.4616150856,51.031047821],"type":"Point"}
}