{
  "type": "Feature",
  "properties": {
    "iso:country":"BE",
    "sg:address":"Beukenlaan 48",
    "sg:city":"Retie",
    "sg:orig_category":"Secr\u00e9tariats. R\u00e9alisation de programmes and logiciels. Production de films, t\u00e9l\u00e9films and vid\u00e9os",
    "sg:phone":"+32 14 37 20 14",
    "sg:postcode":"2470",
    "sg:province":"Antwerpen",
    "wof:name":"Varidex Graphics",
    "wof:placetype":"venue"
},
  "geometry": {"coordinates":[5.0835561752,51.2570571899],"type":"Point"}
}