{
  "type": "Feature",
  "properties": {
    "iso:country":"BE",
    "sg:address":"Lierselei 11",
    "sg:city":"Malle",
    "sg:classifiers":[
        {
            "category":"Fast Food",
            "type":"Food & Drink"
        }
    ],
    "sg:phone":"+32 3 312 56 71",
    "sg:postcode":"2390",
    "sg:province":"Antwerpen",
    "sg:tags":[
        "\u00c0",
        "emporter",
        "restaurants"
    ],
    "wof:name":"Sfinx",
    "wof:placetype":"venue"
},
  "geometry": {"coordinates":[4.7336168289,51.3002967834],"type":"Point"}
}