{
  "type": "Feature",
  "properties": {
    "iso:country":"BE",
    "sg:address":"Wilgenlaan 10",
    "sg:city":"Hever",
    "sg:orig_category":"Installation \u00e9lectrique r\u00e9sidentielle. Plomberie, chauffage and installations sanitaires",
    "sg:phone":"+32 475 31 71 25",
    "sg:postcode":"3191",
    "sg:province":"Vlaams-Brabant",
    "wof:name":"Allro",
    "wof:placetype":"venue"
},
  "geometry": {"coordinates":[4.536011219,50.9979133606],"type":"Point"}
}