{
  "type": "Feature",
  "properties": {
    "addr:full":"Rue L\u00e9on Theodor 13 Bruxelles (jette) Bruxelles-Capitale 1090",
    "addr:housenumber":"13",
    "addr:postcode":"1090",
    "addr:street":"Rue Le\u0301On Theodor",
    "iso:country":"BE",
    "sg:address":"Rue L\u00e9on Theodor 13",
    "sg:city":"Bruxelles (jette)",
    "sg:classifiers":[
        {
            "category":"Professional",
            "subcategory":"Testing Lab",
            "type":"Services"
        }
    ],
    "sg:phone":"+32 2 426 93 22",
    "sg:postcode":"1090",
    "sg:province":"Bruxelles-Capitale",
    "sg:tags":[
        "chemist"
    ],
    "wof:name":"Miroir (du)",
    "wof:placetype":"venue"
},
  "geometry": {"coordinates":[4.3261270523,50.8735351562],"type":"Point"}
}