{
  "type": "Feature",
  "properties": {
    "addr:full":"Place De Wasmes 4 Colfontaine (wasmes) Hainaut 7340",
    "addr:housenumber":"4",
    "addr:postcode":"7340",
    "addr:street":"Place De Wasmes",
    "iso:country":"BE",
    "sg:address":"Place De Wasmes 4",
    "sg:city":"Colfontaine (wasmes)",
    "sg:classifiers":[
        {
            "category":"Shopping",
            "subcategory":"Florist",
            "type":"Retail Goods"
        }
    ],
    "sg:phone":"+32 65 77 98 78",
    "sg:postcode":"7340",
    "sg:province":"Hainaut",
    "wof:name":"Capiflor",
    "wof:placetype":"venue"
},
  "geometry": {"coordinates":[3.8437159061,50.4225082397],"type":"Point"}
}