{
  "type": "Feature",
  "properties": {
    "iso:country":"BE",
    "sg:address":"Kruishoutemseweg 221",
    "sg:city":"Waregem",
    "sg:orig_category":"Gespecialiseerde residenti\u00eble bouw Woningbouw",
    "sg:phone":"+32 56 60 67 23",
    "sg:postcode":"8790",
    "sg:province":"West-Vlaanderen",
    "wof:name":"Roland Glorieux",
    "wof:placetype":"venue"
},
  "geometry": {"coordinates":[3.468460083,50.8942260742],"type":"Point"}
}