{
  "type": "Feature",
  "properties": {
    "addr:full":"Bleekhofstraat 15 Antwerpen Antwerpen 2018",
    "addr:housenumber":"15",
    "addr:postcode":"2018",
    "addr:street":"Bleekhofstraat",
    "iso:country":"BE",
    "sg:address":"Bleekhofstraat 15",
    "sg:city":"Antwerpen",
    "sg:classifiers":[
        {
            "category":"Food & Beverages",
            "subcategory":"Chocolate",
            "type":"Retail Goods"
        }
    ],
    "sg:phone":"+32 3 235 43 52",
    "sg:postcode":"2018",
    "sg:province":"Antwerpen",
    "sg:tags":[
        "candy"
    ],
    "wof:name":"Chocolaterie Willems Dirk",
    "wof:placetype":"venue"
},
  "geometry": {"coordinates":[4.4267311096,51.2119026184],"type":"Point"}
}