{
  "type": "Feature",
  "properties": {
    "addr:full":"Liersesteenweg 69 Begijnendijk Vlaams-Brabant 3130",
    "addr:housenumber":"69",
    "addr:postcode":"3130",
    "addr:street":"Liersesteenweg",
    "iso:country":"BE",
    "sg:address":"Liersesteenweg 69",
    "sg:city":"Begijnendijk",
    "sg:orig_category":"Etalage- and showroomontwerpers",
    "sg:phone":"+32 16 53 20 93",
    "sg:postcode":"3130",
    "sg:province":"Vlaams-Brabant",
    "wof:name":"Luyten",
    "wof:placetype":"venue"
},
  "geometry": {"coordinates":[4.7779159546,51.027973175],"type":"Point"}
}