{
  "type": "Feature",
  "properties": {
    "addr:full":"Grote Markt 20 Halle Vlaams-Brabant 1500",
    "addr:housenumber":"20",
    "addr:postcode":"1500",
    "addr:street":"Grote Markt",
    "iso:country":"BE",
    "sg:address":"Grote Markt 20",
    "sg:city":"Halle",
    "sg:classifiers":[
        {
            "category":"Cafe",
            "type":"Food & Drink"
        }
    ],
    "sg:phone":"+32 2 361 60 01",
    "sg:postcode":"1500",
    "sg:province":"Vlaams-Brabant",
    "sg:tags":[
        "caf\u00e9s"
    ],
    "wof:name":"Eddy\u00b4s Music Cafe",
    "wof:placetype":"venue"
},
  "geometry": {"coordinates":[4.2370219231,50.7367782593],"type":"Point"}
}