{
  "type": "Feature",
  "properties": {
    "addr:full":"Avenue Du Domaine 159 Box 11 Bruxelles (forest) Bruxelles-Capitale 1190",
    "addr:housenumber":"159 box 11",
    "addr:postcode":"1190",
    "addr:street":"Avenue Du Domaine",
    "iso:country":"BE",
    "sg:address":"Avenue Du Domaine 159 Box 11",
    "sg:city":"Bruxelles (forest)",
    "sg:classifiers":[
        {
            "category":"Home & Garden",
            "subcategory":"Home Furnishings",
            "type":"Retail Goods"
        }
    ],
    "sg:phone":"+32 2 344 91 38",
    "sg:postcode":"1190",
    "sg:province":"Bruxelles-Capitale",
    "sg:tags":[
        "interior",
        "decoration"
    ],
    "wof:name":"Cecere Peinture Sprl",
    "wof:placetype":"venue"
},
  "geometry": {"coordinates":[4.329723835,50.8119239807],"type":"Point"}
}