{
  "type": "Feature",
  "properties": {
    "addr:full":"Rue Du G\u00e9n\u00e9ral De Gaulle 4b Courcelles Hainaut 6180",
    "addr:housenumber":"4b",
    "addr:postcode":"6180",
    "addr:street":"Rue Du Ge\u0301Ne\u0301Ral De Gaulle",
    "iso:country":"BE",
    "sg:address":"Rue Du G\u00e9n\u00e9ral De Gaulle 4b",
    "sg:city":"Courcelles",
    "sg:classifiers":[
        {
            "category":"Food & Beverages",
            "subcategory":"Cheese",
            "type":"Retail Goods"
        }
    ],
    "sg:phone":"+32 71 45 61 37",
    "sg:postcode":"6180",
    "sg:province":"Hainaut",
    "sg:tags":[
        "-"
    ],
    "wof:name":"Fromager (le)",
    "wof:placetype":"venue"
},
  "geometry": {"coordinates":[4.3800258636,50.4591026306],"type":"Point"}
}