{
  "type": "Feature",
  "properties": {
    "iso:country":"BE",
    "sg:address":"Rue Neuvice 56",
    "sg:city":"Li\u00c8ge",
    "sg:orig_category":"M\u00e9decins and sp\u00e9cialistes",
    "sg:phone":"+32 4 221 13 69",
    "sg:postcode":"4000",
    "sg:province":"Li\u00e8ge",
    "wof:name":"Henri Beaudry",
    "wof:placetype":"venue"
},
  "geometry": {"coordinates":[5.5773172379,50.6443786621],"type":"Point"}
}