{
  "type": "Feature",
  "properties": {
    "addr:full":"Zeedijk 241 Middelkerke West-Vlaanderen 8430",
    "addr:housenumber":"241",
    "addr:postcode":"8430",
    "addr:street":"Zeedijk",
    "iso:country":"BE",
    "sg:address":"Zeedijk 241",
    "sg:city":"Middelkerke",
    "sg:orig_category":"Agences immobili\u00e8res. Maisons de vacances. Evaluation and estimation de biens immobiliers",
    "sg:phone":"+32 59 30 17 79",
    "sg:postcode":"8430",
    "sg:province":"West-Vlaanderen",
    "wof:name":"Agem",
    "wof:placetype":"venue"
},
  "geometry": {"coordinates":[2.8011879921,51.1821365356],"type":"Point"}
}