{
  "type": "Feature",
  "properties": {
    "iso:country":"BE",
    "sg:address":"Rue Mosseroux 9",
    "sg:city":"Andenne",
    "sg:orig_category":"Woningbouw",
    "sg:phone":"+32 81 58 98 11",
    "sg:postcode":"5300",
    "sg:province":"Namur",
    "wof:name":"Delisee F",
    "wof:placetype":"venue"
},
  "geometry": {"coordinates":[5.0047240257,50.4677200317],"type":"Point"}
}