{
  "type": "Feature",
  "properties": {
    "addr:full":"Place Communale 14 Floreffe Namur 5150",
    "addr:housenumber":"14",
    "addr:postcode":"5150",
    "addr:street":"Place Communale",
    "iso:country":"BE",
    "sg:address":"Place Communale 14",
    "sg:city":"Floreffe",
    "sg:orig_category":"Pain, p\u00e2tisseries and confiseries",
    "sg:phone":"+32 81 44 40 16",
    "sg:postcode":"5150",
    "sg:province":"Namur",
    "wof:name":"S. Robaux",
    "wof:placetype":"venue"
},
  "geometry": {"coordinates":[4.7597332001,50.4353713989],"type":"Point"}
}