{
  "type": "Feature",
  "properties": {
    "iso:country":"BE",
    "sg:address":"Houtemstraat 443",
    "sg:city":"Tienen",
    "sg:orig_category":"ACCOUNTANTS Belastingconsulenten Diverse juridische dienstverlening",
    "sg:phone":"+32 16 82 21 11",
    "sg:postcode":"3300",
    "sg:province":"Vlaams-Brabant",
    "wof:name":"Accountantskant. Goossens",
    "wof:placetype":"venue"
},
  "geometry": {"coordinates":[4.9456100464,50.8188896179],"type":"Point"}
}