{
  "type": "Feature",
  "properties": {
    "iso:country":"BE",
    "sg:address":"Postelarenweg 227",
    "sg:city":"Mol",
    "sg:orig_category":"R\u00e9parations and entretien de motos. Motos",
    "sg:phone":"+32 14 32 37 69",
    "sg:postcode":"2400",
    "sg:province":"Antwerpen",
    "wof:name":"Ludo Van Der Veken",
    "wof:placetype":"venue"
},
  "geometry": {"coordinates":[5.0970458984,51.1913871765],"type":"Point"}
}