{
  "type": "Feature",
  "properties": {
    "addr:full":"Gemeenteplein 1ba Riemst Limburg 3770",
    "addr:housenumber":"1ba",
    "addr:postcode":"3770",
    "addr:street":"Gemeenteplein",
    "iso:country":"BE",
    "sg:address":"Gemeenteplein 1ba",
    "sg:city":"Riemst",
    "sg:classifiers":[
        {
            "category":"Insurance",
            "subcategory":"Insurance Agent",
            "type":"Services"
        }
    ],
    "sg:phone":"+32 12 45 22 80",
    "sg:postcode":"3770",
    "sg:province":"Limburg",
    "sg:tags":[
        "verzekeringsmakelaars",
        "expert"
    ],
    "wof:name":"Meertens & Co",
    "wof:placetype":"venue"
},
  "geometry": {"coordinates":[5.5961771011,50.8115310669],"type":"Point"}
}