{
  "type": "Feature",
  "properties": {
    "addr:full":"Veldstraat 31 Kapelle-op-den-bos Vlaams-Brabant 1880",
    "addr:housenumber":"31",
    "addr:postcode":"1880",
    "addr:street":"Veldstraat",
    "iso:country":"BE",
    "sg:address":"Veldstraat 31",
    "sg:city":"Kapelle-op-den-bos",
    "sg:orig_category":"Artsen and specialisten",
    "sg:phone":"+32 15 71 33 90",
    "sg:postcode":"1880",
    "sg:province":"Vlaams-Brabant",
    "wof:name":"Etienne Van Der Auwera",
    "wof:placetype":"venue"
},
  "geometry": {"coordinates":[4.3558602333,51.0032997131],"type":"Point"}
}