{
  "type": "Feature",
  "properties": {
    "iso:country":"BE",
    "sg:address":"Bosstraat 29",
    "sg:city":"Westerlo",
    "sg:orig_category":"Rundveehouders",
    "sg:phone":"+32 14 54 52 48",
    "sg:postcode":"2260",
    "sg:province":"Antwerpen",
    "wof:name":"Fa. Backx",
    "wof:placetype":"venue"
},
  "geometry": {"coordinates":[4.9048848152,51.118144989],"type":"Point"}
}