{
  "type": "Feature",
  "properties": {
    "iso:country":"BE",
    "sg:address":"Betgn\u00c9 1",
    "sg:city":"Sprimont",
    "sg:orig_category":"M\u00e9decins and sp\u00e9cialistes",
    "sg:phone":"+32 4 380 18 04",
    "sg:postcode":"4140",
    "sg:province":"Li\u00e8ge",
    "wof:name":"Th\u00c9r\u00c8se Delvaux",
    "wof:placetype":"venue"
},
  "geometry": {"coordinates":[5.6597499847,50.5072059631],"type":"Point"}
}