{
  "type": "Feature",
  "properties": {
    "addr:full":"Albertlaan 149 Vorst/forest Bruxelles-Capitale 1190",
    "addr:housenumber":"149",
    "addr:postcode":"1190",
    "addr:street":"Albertlaan;/ Forest",
    "iso:country":"BE",
    "sg:address":"Albertlaan 149",
    "sg:city":"Vorst/forest",
    "sg:classifiers":[
        {
            "category":"Insurance",
            "subcategory":"Insurance Agent",
            "type":"Services"
        }
    ],
    "sg:phone":"+32 2 344 59 07",
    "sg:postcode":"1190",
    "sg:province":"Bruxelles-Capitale",
    "sg:tags":[
        "verzekeringsmakelaars",
        "expert"
    ],
    "wof:name":"M. Beling",
    "wof:placetype":"venue"
},
  "geometry": {"coordinates":[4.3453798294,50.8187026978],"type":"Point"}
}