{
  "type": "Feature",
  "properties": {
    "iso:country":"BE",
    "sg:address":"Moerstraat 4",
    "sg:city":"Deinze",
    "sg:orig_category":"Bouwmaterialen Gh Dakwerken Woningbouw",
    "sg:phone":"+32 9 371 65 18",
    "sg:postcode":"9800",
    "sg:province":"Oost-Vlaanderen",
    "wof:name":"Hautekeete Luc",
    "wof:placetype":"venue"
},
  "geometry": {"coordinates":[3.573472023,51.0215110779],"type":"Point"}
}