{
  "type": "Feature",
  "properties": {
    "iso:country":"BE",
    "sg:address":"Heistraat 129",
    "sg:city":"Antwerpen",
    "sg:orig_category":"Industri\u00eble and commerci\u00eble bouw Woningbouw",
    "sg:phone":"+32 3 820 64 64",
    "sg:postcode":"2610",
    "sg:province":"Antwerpen",
    "wof:name":"Interbuild",
    "wof:placetype":"venue"
},
  "geometry": {"coordinates":[4.3908619881,51.1809959412],"type":"Point"}
}