{
  "type": "Feature",
  "properties": {
    "addr:full":"Schoolstraat 52 Izegem West-Vlaanderen 8870",
    "addr:housenumber":"52",
    "addr:postcode":"8870",
    "addr:street":"Schoolstraat",
    "iso:country":"BE",
    "sg:address":"Schoolstraat 52",
    "sg:city":"Izegem",
    "sg:classifiers":[
        {
            "category":"Health Services",
            "subcategory":"Health Practitioner",
            "type":"Services"
        }
    ],
    "sg:phone":"+32 51 32 12 36",
    "sg:postcode":"8870",
    "sg:province":"West-Vlaanderen",
    "sg:tags":[
        "physiotherapist"
    ],
    "wof:name":"Vandenbroucke Sophie",
    "wof:placetype":"venue"
},
  "geometry": {"coordinates":[3.2141039371,50.9112205505],"type":"Point"}
}