{
  "type": "Feature",
  "properties": {
    "addr:full":"Leebrugstraat 32bb Sint-niklaas Oost-Vlaanderen 9112",
    "addr:housenumber":"32bb",
    "addr:postcode":"9112",
    "addr:street":"Leebrugstraat",
    "iso:country":"BE",
    "sg:address":"Leebrugstraat 32bb",
    "sg:city":"Sint-niklaas",
    "sg:orig_category":"Installation de menuiserie en bois and plastique",
    "sg:phone":"+32 3 722 02 24",
    "sg:postcode":"9112",
    "sg:province":"Oost-Vlaanderen",
    "wof:name":"Dirk Ingels",
    "wof:placetype":"venue"
},
  "geometry": {"coordinates":[4.0061187744,51.1529426575],"type":"Point"}
}