{
  "type": "Feature",
  "properties": {
    "iso:country":"BE",
    "sg:address":"Waterdamstraat 2",
    "sg:city":"Moorslede",
    "sg:orig_category":"Non-Classified Establishments",
    "sg:phone":"+32 51 78 00 85",
    "sg:postcode":"8890",
    "sg:province":"West-Vlaanderen",
    "wof:name":"Dumoulin Voeders Sanders Nv",
    "wof:placetype":"venue"
},
  "geometry": {"coordinates":[3.0656340122,50.8754310608],"type":"Point"}
}