{
  "type": "Feature",
  "properties": {
    "addr:full":"Sint-helenavest 8 Tienen Vlaams-Brabant 3300",
    "addr:housenumber":"8",
    "addr:postcode":"3300",
    "addr:street":"Sint-Helenavest",
    "iso:country":"BE",
    "sg:address":"Sint-helenavest 8",
    "sg:city":"Tienen",
    "sg:classifiers":[
        {
            "category":"Utilities",
            "subcategory":"Fuel Oil & Lpg",
            "type":"Services"
        }
    ],
    "sg:phone":"+32 16 81 25 28",
    "sg:postcode":"3300",
    "sg:province":"Vlaams-Brabant",
    "wof:name":"Lenaerts",
    "wof:placetype":"venue"
},
  "geometry": {"coordinates":[4.9355049133,50.8021621704],"type":"Point"}
}