{
  "type": "Feature",
  "properties": {
    "addr:full":"Rue Puissant 16 Charleroi (jumet) Hainaut 6040",
    "addr:housenumber":"16",
    "addr:postcode":"6040",
    "addr:street":"Rue Puissant",
    "iso:country":"BE",
    "sg:address":"Rue Puissant 16",
    "sg:city":"Charleroi (jumet)",
    "sg:classifiers":[
        {
            "category":"Professional",
            "subcategory":"Art Services",
            "type":"Services"
        }
    ],
    "sg:phone":"+32 71 34 59 33",
    "sg:postcode":"6040",
    "sg:province":"Hainaut",
    "sg:tags":[
        "photographer"
    ],
    "wof:name":"D'haeyaert D",
    "wof:placetype":"venue"
},
  "geometry": {"coordinates":[4.4374828339,50.4389572144],"type":"Point"}
}