{
  "type": "Feature",
  "properties": {
    "addr:full":"Route De Bouillon 0 Gedinne Namur 5575",
    "addr:housenumber":"0",
    "addr:postcode":"5575",
    "addr:street":"Route De Bouillon",
    "iso:country":"BE",
    "sg:address":"Route De Bouillon 0",
    "sg:city":"Gedinne",
    "sg:orig_category":"Beheer van afvalopslag- and stortplaatsen",
    "sg:phone":"+32 61 58 99 47",
    "sg:postcode":"5575",
    "sg:province":"Namur",
    "wof:name":"Parcs A Conteneurs Malvoisin",
    "wof:placetype":"venue"
},
  "geometry": {"coordinates":[4.9806652069,49.9767379761],"type":"Point"}
}