{
  "type": "Feature",
  "properties": {
    "iso:country":"BE",
    "sg:address":"Rue Bl\u00c9val 2",
    "sg:city":"Nivelles",
    "sg:orig_category":"Traitements param\u00e9dicaux",
    "sg:phone":"+32 67 21 48 05",
    "sg:postcode":"1400",
    "sg:province":"Brabant Wallon",
    "wof:name":"S. Kaye",
    "wof:placetype":"venue"
},
  "geometry": {"coordinates":[4.3220567703,50.5979042053],"type":"Point"}
}