{
  "type": "Feature",
  "properties": {
    "addr:full":"Vieux Chemin De Hal 22 Braine-le-chateau Brabant Wallon 1440",
    "addr:housenumber":"22",
    "addr:postcode":"1440",
    "addr:street":"Vieux Chemin De Hal;Brabant Wallon",
    "iso:country":"BE",
    "sg:address":"Vieux Chemin De Hal 22",
    "sg:city":"Braine-le-chateau",
    "sg:orig_category":"Eleveurs de bovins",
    "sg:phone":"+32 2 366 90 63",
    "sg:postcode":"1440",
    "sg:province":"Brabant Wallon",
    "wof:name":"Jean Desmet",
    "wof:placetype":"venue"
},
  "geometry": {"coordinates":[4.2634758949,50.691493988],"type":"Point"}
}