{
  "type": "Feature",
  "properties": {
    "addr:full":"Bosstraat 49 Mere Oost-Vlaanderen 9420",
    "addr:housenumber":"49",
    "addr:postcode":"9420",
    "addr:street":"Bosstraat",
    "iso:country":"BE",
    "sg:address":"Bosstraat 49",
    "sg:city":"Mere",
    "sg:orig_category":"Schilders",
    "sg:phone":"+32 53 83 38 53",
    "sg:postcode":"9420",
    "sg:province":"Oost-Vlaanderen",
    "wof:name":"Geert Wyns",
    "wof:placetype":"venue"
},
  "geometry": {"coordinates":[3.9654099941,50.9242172241],"type":"Point"}
}