{
  "type": "Feature",
  "properties": {
    "addr:full":"Rue Modeste Cornil 7 Charleroi Hainaut 6041",
    "addr:housenumber":"7",
    "addr:postcode":"6041",
    "addr:street":"Rue Modeste Cornil;Hainaut",
    "iso:country":"BE",
    "sg:address":"Rue Modeste Cornil 7",
    "sg:city":"Charleroi",
    "sg:orig_category":"Banques and organismes de cr\u00e9dit",
    "sg:phone":"+32 71 35 14 33",
    "sg:postcode":"6041",
    "sg:province":"Hainaut",
    "wof:name":"Citibank",
    "wof:placetype":"venue"
},
  "geometry": {"coordinates":[4.4314317703,50.4685935974],"type":"Point"}
}