{
  "type": "Feature",
  "properties": {
    "addr:full":"Driekoningenstraat 12 Sint-niklaas Oost-Vlaanderen 9100",
    "addr:housenumber":"12",
    "addr:postcode":"9100",
    "addr:street":"Driekoningenstraat",
    "iso:country":"BE",
    "sg:address":"Driekoningenstraat 12",
    "sg:city":"Sint-niklaas",
    "sg:orig_category":"Boekhouders",
    "sg:phone":"+32 3 777 15 07",
    "sg:postcode":"9100",
    "sg:province":"Oost-Vlaanderen",
    "wof:name":"Ludo Lardenoit",
    "wof:placetype":"venue"
},
  "geometry": {"coordinates":[4.1400442123,51.1715583801],"type":"Point"}
}