{
  "type": "Feature",
  "properties": {
    "addr:full":"Vrijheidslaan 35b Dilbeek Vlaams-Brabant 1700",
    "addr:housenumber":"35b",
    "addr:postcode":"1700",
    "addr:street":"Vrijheidslaan",
    "iso:country":"BE",
    "sg:address":"Vrijheidslaan 35b",
    "sg:city":"Dilbeek",
    "sg:classifiers":[
        {
            "category":"Building & Trades",
            "subcategory":"Plumbing",
            "type":"Services"
        }
    ],
    "sg:phone":"+32 477 37 09 83",
    "sg:postcode":"1700",
    "sg:province":"Vlaams-Brabant",
    "sg:tags":[
        "contractor"
    ],
    "wof:name":"Blommaert J",
    "wof:placetype":"venue"
},
  "geometry": {"coordinates":[4.2604718208,50.841545105],"type":"Point"}
}