{
  "type": "Feature",
  "properties": {
    "addr:full":"Boulevard Ernest M\u00c9lot 25 Namur Namur 5000",
    "addr:housenumber":"25",
    "addr:postcode":"5000",
    "addr:street":"Boulevard Ernest Me\u0301Lot",
    "iso:country":"BE",
    "sg:address":"Boulevard Ernest M\u00c9lot 25",
    "sg:city":"Namur",
    "sg:orig_category":"Postkantoren Verzekeringsmakelaars and experts",
    "sg:phone":"+32 81 22 02 20",
    "sg:postcode":"5000",
    "sg:province":"Namur",
    "wof:name":"La Poste",
    "wof:placetype":"venue"
},
  "geometry": {"coordinates":[4.8607478142,50.468372345],"type":"Point"}
}