{
  "type": "Feature",
  "properties": {
    "addr:full":"Leuvensesteenweg 277 Boortmeerbeek Vlaams-Brabant 3190",
    "addr:housenumber":"277",
    "addr:postcode":"3190",
    "addr:street":"Leuvensesteenweg",
    "iso:country":"BE",
    "sg:address":"Leuvensesteenweg 277",
    "sg:city":"Boortmeerbeek",
    "sg:orig_category":"Meubelzaken, woning- and keukeninrichting",
    "sg:phone":"+32 15 52 99 15",
    "sg:postcode":"3190",
    "sg:province":"Vlaams-Brabant",
    "wof:name":"Home-style",
    "wof:placetype":"venue"
},
  "geometry": {"coordinates":[4.564871788,50.9738426208],"type":"Point"}
}