{
  "type": "Feature",
  "properties": {
    "addr:full":"Grand-place 5 Moeskroen/mouscron Hainaut 7700",
    "addr:housenumber":"5",
    "addr:postcode":"7700",
    "addr:street":"Grand-Place",
    "iso:country":"BE",
    "sg:address":"Grand-place 5",
    "sg:city":"Moeskroen/mouscron",
    "sg:orig_category":"Banques and organismes de cr\u00e9dit",
    "sg:phone":"+32 56 34 68 67",
    "sg:postcode":"7700",
    "sg:province":"Hainaut",
    "wof:name":"Citibank",
    "wof:placetype":"venue"
},
  "geometry": {"coordinates":[3.2323200703,50.7400932312],"type":"Point"}
}