{
  "type": "Feature",
  "properties": {
    "addr:full":"Jacob Lacoopsstraat 2c Oudenaarde Oost-Vlaanderen 9700",
    "addr:housenumber":"2c",
    "addr:postcode":"9700",
    "addr:street":"Lacoopsstraat",
    "iso:country":"BE",
    "sg:address":"Jacob Lacoopsstraat 2c",
    "sg:city":"Oudenaarde",
    "sg:orig_category":"Quincailleries",
    "sg:phone":"+32 55 30 01 75",
    "sg:postcode":"9700",
    "sg:province":"Oost-Vlaanderen",
    "wof:name":"Brico",
    "wof:placetype":"venue"
},
  "geometry": {"coordinates":[3.6085999012,50.842590332],"type":"Point"}
}