{
  "type": "Feature",
  "properties": {
    "addr:full":"Rue Delpr\u00c9e 3 Frasnes-lez-anvaing Hainaut 7910",
    "addr:housenumber":"3",
    "addr:postcode":"7910",
    "addr:street":"Rue Delpre\u0301E",
    "iso:country":"BE",
    "sg:address":"Rue Delpr\u00c9e 3",
    "sg:city":"Frasnes-lez-anvaing",
    "sg:orig_category":"Rundveehouders",
    "sg:phone":"+32 69 85 98 43",
    "sg:postcode":"7910",
    "sg:province":"Hainaut",
    "wof:name":"Roger Demets",
    "wof:placetype":"venue"
},
  "geometry": {"coordinates":[3.5399229527,50.6881752014],"type":"Point"}
}