{
  "type": "Feature",
  "properties": {
    "iso:country":"BE",
    "sg:address":"Muisstraat 47",
    "sg:city":"Haaltert",
    "sg:orig_category":"Avocats and conseillers juridiques",
    "sg:phone":"+32 53 83 33 00",
    "sg:postcode":"9450",
    "sg:province":"Oost-Vlaanderen",
    "wof:name":"K. Bodard",
    "wof:placetype":"venue"
},
  "geometry": {"coordinates":[4.0078349113,50.9051132202],"type":"Point"}
}