{
  "type": "Feature",
  "properties": {
    "iso:country":"BE",
    "sg:address":"Paul Malustraat 4",
    "sg:city":"Hoeilaart",
    "sg:classifiers":[
        {
            "category":"Professional",
            "subcategory":"Lawyer & Legal Services",
            "type":"Services"
        }
    ],
    "sg:phone":"+32 2 657 03 66",
    "sg:postcode":"1560",
    "sg:province":"Vlaams-Brabant",
    "wof:name":"Vandenput Dirk",
    "wof:placetype":"venue"
},
  "geometry": {"coordinates":[4.4764099121,50.7667922974],"type":"Point"}
}