{
  "type": "Feature",
  "properties": {
    "iso:country":"BE",
    "sg:address":"Rue Robert Fesler 45",
    "sg:city":"Charleroi",
    "sg:orig_category":"Auto-\u00e9coles",
    "sg:phone":"+32 71 31 74 20",
    "sg:postcode":"6030",
    "sg:province":"Hainaut",
    "wof:name":"Auto-ecole Bara",
    "wof:placetype":"venue"
},
  "geometry": {"coordinates":[4.3949518204,50.4099884033],"type":"Point"}
}