{
  "type": "Feature",
  "properties": {
    "addr:full":"Rue Du Centre 29 Herve (grand) Li\u00e8ge 4651",
    "addr:housenumber":"29",
    "addr:postcode":"4651",
    "addr:street":"Rue Du Centre;Grand Lie\u0300Ge",
    "iso:country":"BE",
    "sg:address":"Rue Du Centre 29",
    "sg:city":"Herve (grand)",
    "sg:orig_category":"Secr\u00e9tariats sociaux",
    "sg:phone":"+32 87 46 36 02",
    "sg:postcode":"4651",
    "sg:province":"Li\u00e8ge",
    "wof:name":"Ellix Developpement",
    "wof:placetype":"venue"
},
  "geometry": {"coordinates":[5.8225131035,50.6474494934],"type":"Point"}
}