{
  "type": "Feature",
  "properties": {
    "iso:country":"BE",
    "sg:address":"Rue De La Digue 25",
    "sg:city":"Li\u00e8ge 1 (ch\u00ean\u00e9e)",
    "sg:classifiers":[
        {
            "category":"Professional",
            "subcategory":"Accounting & Tax Preparation",
            "type":"Services"
        }
    ],
    "sg:phone":"+32 4 366 13 92",
    "sg:postcode":"4032",
    "sg:province":"Li\u00e8ge",
    "sg:tags":[
        "bookkeeper"
    ],
    "wof:name":"Berryer",
    "wof:placetype":"venue"
},
  "geometry": {"coordinates":[5.611866951,50.6056137085],"type":"Point"}
}