{
  "type": "Feature",
  "properties": {
    "addr:full":"Renaissancelaan 42 Brussel/bruxelles Bruxelles-Capitale 1000",
    "addr:housenumber":"42",
    "addr:postcode":"1000",
    "addr:street":"Renaissancelaan;/",
    "iso:country":"BE",
    "sg:address":"Renaissancelaan 42",
    "sg:city":"Brussel/bruxelles",
    "sg:classifiers":[
        {
            "category":"Restaurant",
            "type":"Food & Drink"
        }
    ],
    "sg:phone":"+32 2 735 15 08",
    "sg:postcode":"1000",
    "sg:province":"Bruxelles-Capitale",
    "wof:name":"Le Pr\u00c9 Aux Clercs",
    "wof:placetype":"venue"
},
  "geometry": {"coordinates":[4.394135952,50.8428268433],"type":"Point"}
}