{
  "type": "Feature",
  "properties": {
    "iso:country":"BE",
    "sg:address":"Heuvelstraat 2",
    "sg:city":"Asse",
    "sg:orig_category":"Dakwerken",
    "sg:phone":"+32 2 452 78 66",
    "sg:postcode":"1730",
    "sg:province":"Vlaams-Brabant",
    "wof:name":"Verhertbruggen-roggeman",
    "wof:placetype":"venue"
},
  "geometry": {"coordinates":[4.1615262032,50.9206199646],"type":"Point"}
}