{
  "type": "Feature",
  "properties": {
    "addr:full":"Wijtschatestraat 38 Heuvelland (kemmel) West-Vlaanderen 8956",
    "addr:housenumber":"38",
    "addr:postcode":"8956",
    "addr:street":"Wijtschatestraat",
    "iso:country":"BE",
    "sg:address":"Wijtschatestraat 38",
    "sg:city":"Heuvelland (kemmel)",
    "sg:classifiers":[
        {
            "category":"Wholesale",
            "subcategory":"Machinery & Supplies",
            "type":"Manufacturing & Wholesale Goods"
        }
    ],
    "sg:phone":"+32 57 44 78 53",
    "sg:postcode":"8956",
    "sg:province":"West-Vlaanderen",
    "sg:tags":[
        "agricultural",
        "tractor"
    ],
    "wof:name":"Dauchy-frimout Bvba",
    "wof:placetype":"venue"
},
  "geometry": {"coordinates":[2.8343200684,50.7822990417],"type":"Point"}
}