{
  "type": "Feature",
  "properties": {
    "addr:full":"Vliegpleinstraat 56 Evere Bruxelles-Capitale 1140",
    "addr:housenumber":"56",
    "addr:postcode":"1140",
    "addr:street":"Vliegpleinstraat",
    "iso:country":"BE",
    "sg:address":"Vliegpleinstraat 56",
    "sg:city":"Evere",
    "sg:orig_category":"Kapsalons",
    "sg:phone":"+32 2 216 83 95",
    "sg:postcode":"1140",
    "sg:province":"Bruxelles-Capitale",
    "wof:name":"Tamoun",
    "wof:placetype":"venue"
},
  "geometry": {"coordinates":[4.40502882,50.8762741089],"type":"Point"}
}