{
  "type": "Feature",
  "properties": {
    "iso:country":"BE",
    "sg:address":"Galgeveldstraat 100",
    "sg:city":"Diest (kaggevinne)",
    "sg:classifiers":[
        {
            "category":"Professional",
            "type":"Services"
        }
    ],
    "sg:phone":"+32 13 31 47 19",
    "sg:postcode":"3293",
    "sg:province":"Vlaams-Brabant",
    "sg:tags":[
        "entertainer"
    ],
    "wof:name":"Tootsie Music Bvba",
    "wof:placetype":"venue"
},
  "geometry": {"coordinates":[5.0388498306,50.9746513367],"type":"Point"}
}