{
  "type": "Feature",
  "properties": {
    "addr:full":"Rue Branche Planchard 79 Ans Li\u00e8ge 4430",
    "addr:housenumber":"79",
    "addr:postcode":"4430",
    "addr:street":"Rue Branche Planchard",
    "iso:country":"BE",
    "sg:address":"Rue Branche Planchard 79",
    "sg:city":"Ans",
    "sg:orig_category":"Entretien et r\u00e9parations de v\u00e9hicules \u00e0 domicile. Entretien and r\u00e9parations de voitures. R\u00e9cup\u00e9ratio",
    "sg:phone":"+32 4 247 16 45",
    "sg:postcode":"4430",
    "sg:province":"Li\u00e8ge",
    "wof:name":"Garage Reul",
    "wof:placetype":"venue"
},
  "geometry": {"coordinates":[5.51963377,50.6577987671],"type":"Point"}
}