{
  "type": "Feature",
  "properties": {
    "addr:full":"Rue De Vis\u00c9 99 Vise Li\u00e8ge 4602",
    "addr:housenumber":"99",
    "addr:postcode":"4602",
    "addr:street":"Rue De Vise\u0301",
    "iso:country":"BE",
    "sg:address":"Rue De Vis\u00c9 99",
    "sg:city":"Vise",
    "sg:orig_category":"Herstellingen and onderhoud van auto's",
    "sg:phone":"+32 4 362 62 25",
    "sg:postcode":"4602",
    "sg:province":"Li\u00e8ge",
    "wof:name":"R. Huynen",
    "wof:placetype":"venue"
},
  "geometry": {"coordinates":[5.6696381569,50.681968689],"type":"Point"}
}