{
  "type": "Feature",
  "properties": {
    "addr:full":"Lindestraat 21 Zele Oost-Vlaanderen 9240",
    "addr:housenumber":"21",
    "addr:postcode":"9240",
    "addr:street":"Lindestraat",
    "iso:country":"BE",
    "sg:address":"Lindestraat 21",
    "sg:city":"Zele",
    "sg:classifiers":[
        {
            "category":"Wholesale",
            "subcategory":"Scrap",
            "type":"Manufacturing & Wholesale Goods"
        }
    ],
    "sg:phone":"+32 52 45 31 97",
    "sg:postcode":"9240",
    "sg:province":"Oost-Vlaanderen",
    "sg:tags":[
        "metal"
    ],
    "wof:name":"Kabel Recycling Company",
    "wof:placetype":"venue"
},
  "geometry": {"coordinates":[4.054090023,51.0728874207],"type":"Point"}
}