{
  "type": "Feature",
  "properties": {
    "addr:full":"Rue Du Coll\u00c8ge 29 Bouillon Luxembourg 6830",
    "addr:housenumber":"29",
    "addr:postcode":"6830",
    "addr:street":"Rue Du Colle\u0300Ge",
    "iso:country":"BE",
    "sg:address":"Rue Du Coll\u00c8ge 29",
    "sg:city":"Bouillon",
    "sg:orig_category":"Tribunaux",
    "sg:phone":"+32 61 46 61 39",
    "sg:postcode":"6830",
    "sg:province":"Luxembourg",
    "wof:name":"Justice De Paix",
    "wof:placetype":"venue"
},
  "geometry": {"coordinates":[5.0676717758,49.7920646667],"type":"Point"}
}