{
  "type": "Feature",
  "properties": {
    "iso:country":"BE",
    "sg:address":"Jozef Verhaegenstraat 42",
    "sg:city":"Schoten",
    "sg:orig_category":"Installatie van metalen schrijnwerk",
    "sg:phone":"+32 3 644 86 43",
    "sg:postcode":"2900",
    "sg:province":"Antwerpen",
    "wof:name":"Eric Colman",
    "wof:placetype":"venue"
},
  "geometry": {"coordinates":[4.4614877701,51.2433891296],"type":"Point"}
}