{
  "type": "Feature",
  "properties": {
    "addr:full":"Leopoldstraat 8 Blankenberge West-Vlaanderen 8370",
    "addr:housenumber":"8",
    "addr:postcode":"8370",
    "addr:street":"Leopoldstraat",
    "iso:country":"BE",
    "sg:address":"Leopoldstraat 8",
    "sg:city":"Blankenberge",
    "sg:classifiers":[
        {
            "category":"Tea Room",
            "subcategory":"None",
            "type":"Food & Drink"
        }
    ],
    "sg:phone":"+32 50 42 30 36",
    "sg:postcode":"8370",
    "sg:province":"West-Vlaanderen",
    "wof:name":"Belle Epoque",
    "wof:placetype":"venue"
},
  "geometry": {"coordinates":[3.1229009628,51.3144226074],"type":"Point"}
}