{
  "type": "Feature",
  "properties": {
    "addr:full":"Burg. De Lausnaystraat 41 Berlare Oost-Vlaanderen 9290",
    "addr:housenumber":"41",
    "addr:postcode":"9290",
    "addr:street":"Burg.;Lausnaystraat",
    "iso:country":"BE",
    "sg:address":"Burg. De Lausnaystraat 41",
    "sg:city":"Berlare",
    "sg:classifiers":[
        {
            "category":"Food & Beverages",
            "subcategory":"Fruits & Vegetables",
            "type":"Retail Goods"
        }
    ],
    "sg:phone":"+32 9 367 62 41",
    "sg:postcode":"9290",
    "sg:province":"Oost-Vlaanderen",
    "sg:tags":[
        "groenten"
    ],
    "wof:name":"Huis 't Boerken",
    "wof:placetype":"venue"
},
  "geometry": {"coordinates":[4.005710125,51.0165214539],"type":"Point"}
}