{
  "type": "Feature",
  "properties": {
    "addr:full":"Rue Chestr\u00c9e 1 Yvoir Namur 5530",
    "addr:housenumber":"1",
    "addr:postcode":"5530",
    "addr:street":"Rue Chestre\u0301E",
    "iso:country":"BE",
    "sg:address":"Rue Chestr\u00c9e 1",
    "sg:city":"Yvoir",
    "sg:orig_category":"Rundveehouders",
    "sg:phone":"+32 83 69 99 68",
    "sg:postcode":"5530",
    "sg:province":"Namur",
    "wof:name":"Paul Paquet",
    "wof:placetype":"venue"
},
  "geometry": {"coordinates":[4.9769301414,50.3181228638],"type":"Point"}
}