{
  "type": "Feature",
  "properties": {
    "iso:country":"BE",
    "sg:address":"Boudewijnlaan 11",
    "sg:city":"Herenthout",
    "sg:classifiers":[
        {
            "category":"Bakery",
            "type":"Food & Drink"
        }
    ],
    "sg:phone":"+32 14 51 70 01",
    "sg:postcode":"2270",
    "sg:province":"Antwerpen",
    "sg:tags":[
        "confectioner",
        "baker"
    ],
    "wof:name":"Horemans W",
    "wof:placetype":"venue"
},
  "geometry": {"coordinates":[4.7706689835,51.1403427124],"type":"Point"}
}