{
  "type": "Feature",
  "properties": {
    "iso:country":"BE",
    "sg:address":"F Allenstraat 32",
    "sg:city":"Diest",
    "sg:classifiers":[
        {
            "category":"Shopping",
            "subcategory":"Stationery & Office Supplies",
            "type":"Retail Goods"
        }
    ],
    "sg:phone":"+32 13 31 14 52",
    "sg:postcode":"3290",
    "sg:province":"Vlaams-Brabant",
    "sg:tags":[
        "fab",
        "carton",
        "en",
        "papier",
        "emballages"
    ],
    "wof:name":"Papier Wolfs",
    "wof:placetype":"venue"
},
  "geometry": {"coordinates":[5.0511350632,50.9845848083],"type":"Point"}
}