{
  "type": "Feature",
  "properties": {
    "addr:full":"Grand-rue 47 Courcelles Hainaut 6183",
    "addr:housenumber":"47",
    "addr:postcode":"6183",
    "addr:street":"Grand-Rue",
    "iso:country":"BE",
    "sg:address":"Grand-rue 47",
    "sg:city":"Courcelles",
    "sg:orig_category":"Artsen and specialisten",
    "sg:phone":"+32 71 45 06 47",
    "sg:postcode":"6183",
    "sg:province":"Hainaut",
    "wof:name":"Yves Gilon",
    "wof:placetype":"venue"
},
  "geometry": {"coordinates":[4.3350520134,50.4609794617],"type":"Point"}
}