{
  "type": "Feature",
  "properties": {
    "iso:country":"BE",
    "sg:address":"32",
    "sg:city":"Minderbroedersrui 2000 Antwerpen",
    "sg:classifiers":[
        {
            "category":"Professional",
            "type":"Services"
        }
    ],
    "sg:phone":"+32 3 227 41 97",
    "sg:postcode":"32",
    "sg:tags":[
        "transport",
        "road"
    ],
    "wof:name":"Art & Exhibition Services",
    "wof:placetype":"venue"
},
  "geometry": {"coordinates":[4.4037098885,51.2230987549],"type":"Point"}
}