{
  "type": "Feature",
  "properties": {
    "addr:full":"Rue Des Garennes 8 Moeskroen/mouscron Hainaut 7700",
    "addr:housenumber":"8",
    "addr:postcode":"7700",
    "addr:street":"Rue Des Garennes",
    "iso:country":"BE",
    "sg:address":"Rue Des Garennes 8",
    "sg:city":"Moeskroen/mouscron",
    "sg:orig_category":"Epiceries",
    "sg:phone":"+32 56 84 09 43",
    "sg:postcode":"7700",
    "sg:province":"Hainaut",
    "wof:name":"Maison Amental",
    "wof:placetype":"venue"
},
  "geometry": {"coordinates":[3.2323200703,50.7400932312],"type":"Point"}
}