{
  "type": "Feature",
  "properties": {
    "addr:full":"Rue Vanderkindere 380 Ukkel/uccle Bruxelles-Capitale 1180",
    "addr:housenumber":"380",
    "addr:postcode":"1180",
    "addr:street":"Rue Vanderkindere;/",
    "iso:country":"BE",
    "sg:address":"Rue Vanderkindere 380",
    "sg:city":"Ukkel/uccle",
    "sg:orig_category":"Meubles D\u00e9taillants, Am\u00e9nagement de B\u00e2timents et de Cuisines",
    "sg:phone":"+32 2 345 79 31",
    "sg:postcode":"1180",
    "sg:province":"Bruxelles-Capitale",
    "wof:name":"Lundia",
    "wof:placetype":"venue"
},
  "geometry": {"coordinates":[4.35750103,50.8143768311],"type":"Point"}
}