{
  "type": "Feature",
  "properties": {
    "iso:country":"BE",
    "sg:address":"Grand'rue 29",
    "sg:city":"Sankt Vith/saint-vith",
    "sg:orig_category":"Bijouteries and horlogeries",
    "sg:phone":"+32 80 22 80 24",
    "sg:postcode":"4780",
    "sg:province":"Li\u00e8ge",
    "wof:name":"Marlene Markefka",
    "wof:placetype":"venue"
},
  "geometry": {"coordinates":[6.1256599426,50.2810783386],"type":"Point"}
}