{
  "type": "Feature",
  "properties": {
    "addr:full":"Rue Ren\u00e9e Prinz 44 Namur (jambes) Namur 5100",
    "addr:housenumber":"44",
    "addr:postcode":"5100",
    "addr:street":"Rue Rene\u0301E Prinz",
    "iso:country":"BE",
    "sg:address":"Rue Ren\u00e9e Prinz 44",
    "sg:city":"Namur (jambes)",
    "sg:classifiers":[
        {
            "category":"Professional",
            "subcategory":"Credit Reporting & Collection",
            "type":"Services"
        }
    ],
    "sg:phone":"+32 81 33 18 18",
    "sg:postcode":"5100",
    "sg:province":"Namur",
    "sg:tags":[
        "bailiff"
    ],
    "wof:name":"Bloquiaux Annick",
    "wof:placetype":"venue"
},
  "geometry": {"coordinates":[4.8685779572,50.456401825],"type":"Point"}
}