{
  "type": "Feature",
  "properties": {
    "addr:full":"Rue Des Trixhes 20 Dalhem Li\u00e8ge 4607",
    "addr:housenumber":"20",
    "addr:postcode":"4607",
    "addr:street":"Rue Des Trixhes",
    "iso:country":"BE",
    "sg:address":"Rue Des Trixhes 20",
    "sg:city":"Dalhem",
    "sg:orig_category":"Electrom\u00e9nager, t\u00e9l\u00e9visions and radios. Installation \u00e9lectrique r\u00e9sidentielle",
    "sg:phone":"+32 4 379 46 52",
    "sg:postcode":"4607",
    "sg:province":"Li\u00e8ge",
    "wof:name":"Yvon Dewitte",
    "wof:placetype":"venue"
},
  "geometry": {"coordinates":[5.7287101746,50.7444190979],"type":"Point"}
}