{
  "type": "Feature",
  "properties": {
    "addr:full":"Rue Gustave Lhoir 73 Saint-ghislain Hainaut 7334",
    "addr:housenumber":"73",
    "addr:postcode":"7334",
    "addr:street":"Rue Gustave Lhoir;Hainaut",
    "iso:country":"BE",
    "sg:address":"Rue Gustave Lhoir 73",
    "sg:city":"Saint-ghislain",
    "sg:classifiers":[
        {
            "category":"Food & Beverages",
            "subcategory":"Fruits & Vegetables",
            "type":"Retail Goods"
        }
    ],
    "sg:phone":"+32 65 62 31 80",
    "sg:postcode":"7334",
    "sg:province":"Hainaut",
    "sg:tags":[
        "groenten"
    ],
    "wof:name":"Maison Cannuyer",
    "wof:placetype":"venue"
},
  "geometry": {"coordinates":[3.7644500732,50.479675293],"type":"Point"}
}