{
  "type": "Feature",
  "properties": {
    "addr:full":"Kaatstraat 21 Lommel Limburg 3920",
    "addr:housenumber":"21",
    "addr:postcode":"3920",
    "addr:street":"Kaatstraat",
    "iso:country":"BE",
    "sg:address":"Kaatstraat 21",
    "sg:city":"Lommel",
    "sg:orig_category":"Quincailleries",
    "sg:phone":"+32 11 55 11 50",
    "sg:postcode":"3920",
    "sg:province":"Limburg",
    "wof:name":"Profi-paint",
    "wof:placetype":"venue"
},
  "geometry": {"coordinates":[5.2943739891,51.1845207214],"type":"Point"}
}