{
  "type": "Feature",
  "properties": {
    "iso:country":"BE",
    "sg:address":"Brusselsesteenweg 101",
    "sg:city":"Mechelen",
    "sg:classifiers":[
        {
            "category":"Personal",
            "subcategory":"Beauty Salon",
            "type":"Services"
        }
    ],
    "sg:phone":"+32 15 42 35 34",
    "sg:postcode":"2800",
    "sg:province":"Antwerpen",
    "wof:name":"Olijfke Schoonheidshuisje ('t)",
    "wof:placetype":"venue"
},
  "geometry": {"coordinates":[4.4729270935,51.0172653198],"type":"Point"}
}