{
  "type": "Feature",
  "properties": {
    "addr:full":"Kasteelhoek 39a Beernem West-Vlaanderen 8730",
    "addr:housenumber":"39a",
    "addr:postcode":"8730",
    "addr:street":"Kasteelhoek",
    "iso:country":"BE",
    "sg:address":"Kasteelhoek 39a",
    "sg:city":"Beernem",
    "sg:classifiers":[
        {
            "category":"Professional",
            "subcategory":"Management & Consulting",
            "type":"Services"
        }
    ],
    "sg:phone":"+32 478 76 91 41",
    "sg:postcode":"8730",
    "sg:province":"West-Vlaanderen",
    "sg:tags":[
        "-",
        "processing",
        "data",
        "consultant"
    ],
    "wof:name":"Ict Advies",
    "wof:placetype":"venue"
},
  "geometry": {"coordinates":[3.2926449776,51.1526641846],"type":"Point"}
}