{
  "type": "Feature",
  "properties": {
    "addr:full":"Blijdschapsstraat 43 Anderlecht/anderlecht Bruxelles-Capitale 1070",
    "addr:housenumber":"43",
    "addr:postcode":"1070",
    "addr:street":"Blijdschapsstraat",
    "iso:country":"BE",
    "sg:address":"Blijdschapsstraat 43",
    "sg:city":"Anderlecht/anderlecht",
    "sg:orig_category":"Elektrische installaties voor woningen Installatie van metalen schrijnwerk",
    "sg:phone":"+32 2 521 47 37",
    "sg:postcode":"1070",
    "sg:province":"Bruxelles-Capitale",
    "wof:name":"Caci",
    "wof:placetype":"venue"
},
  "geometry": {"coordinates":[4.3106708527,50.8337059021],"type":"Point"}
}