{
  "type": "Feature",
  "properties": {
    "addr:full":"Leon Grosjeanlaan 79 Brussel/bruxelles Bruxelles-Capitale 1140",
    "addr:housenumber":"79",
    "addr:postcode":"1140",
    "addr:street":"Grosjeanlaan;/",
    "iso:country":"BE",
    "sg:address":"Leon Grosjeanlaan 79",
    "sg:city":"Brussel/bruxelles",
    "sg:orig_category":"Boekenuitgeverijen",
    "sg:phone":"+32 2 702 24 89",
    "sg:postcode":"1140",
    "sg:province":"Bruxelles-Capitale",
    "wof:name":"Be's Songs",
    "wof:placetype":"venue"
},
  "geometry": {"coordinates":[4.4153208733,50.855255127],"type":"Point"}
}