{
  "type": "Feature",
  "properties": {
    "addr:full":"Zeypestraat 7 Mechelen Antwerpen 2800",
    "addr:housenumber":"7",
    "addr:postcode":"2800",
    "addr:street":"Zeypestraat",
    "iso:country":"BE",
    "sg:address":"Zeypestraat 7",
    "sg:city":"Mechelen",
    "sg:classifiers":[
        {
            "category":"Professional",
            "type":"Services"
        }
    ],
    "sg:phone":"+32 15 34 79 89",
    "sg:postcode":"2800",
    "sg:province":"Antwerpen",
    "sg:tags":[
        "entertainer"
    ],
    "wof:name":"Body Fantasy Art",
    "wof:placetype":"venue"
},
  "geometry": {"coordinates":[4.4854397774,51.0289268494],"type":"Point"}
}