{
  "type": "Feature",
  "properties": {
    "iso:country":"BE",
    "sg:address":"Avenue Des Cerisiers 4",
    "sg:city":"Tubize (clabecq)",
    "sg:classifiers":[
        {
            "category":"Health Services",
            "subcategory":"Health Practitioner",
            "type":"Services"
        }
    ],
    "sg:phone":"+32 2 355 53 90",
    "sg:postcode":"1480",
    "sg:province":"Brabant Wallon",
    "sg:tags":[
        "physiotherapist"
    ],
    "wof:name":"Paradoms Christian",
    "wof:placetype":"venue"
},
  "geometry": {"coordinates":[4.2252731323,50.6862945557],"type":"Point"}
}