{
  "type": "Feature",
  "properties": {
    "addr:full":"Rue De La Limerie 23 Mons Hainaut 7000",
    "addr:housenumber":"23",
    "addr:postcode":"7000",
    "addr:street":"Rue De La Limerie;Hainaut",
    "iso:country":"BE",
    "sg:address":"Rue De La Limerie 23",
    "sg:city":"Mons",
    "sg:classifiers":[
        {
            "category":"Health Services",
            "subcategory":"Nursing And Care Facility",
            "type":"Services"
        }
    ],
    "sg:phone":"+32 65 36 12 91",
    "sg:postcode":"7000",
    "sg:province":"Hainaut",
    "sg:tags":[
        "home"
    ],
    "wof:name":"Marchand G",
    "wof:placetype":"venue"
},
  "geometry": {"coordinates":[3.953676939,50.4469184875],"type":"Point"}
}