{
  "type": "Feature",
  "properties": {
    "addr:full":"Chauss\u00e9e De Tirlemont 149 Gembloux-sur-orneau (gembloux) Namur 5030",
    "addr:housenumber":"149",
    "addr:postcode":"5030",
    "addr:street":"Chausse\u0301E De Tirlemont;Namur",
    "iso:country":"BE",
    "sg:address":"Chauss\u00e9e De Tirlemont 149",
    "sg:city":"Gembloux-sur-orneau (gembloux)",
    "sg:classifiers":[
        {
            "category":"Building & Trades",
            "subcategory":"Construction",
            "type":"Services"
        }
    ],
    "sg:phone":"+32 81 61 36 15",
    "sg:postcode":"5030",
    "sg:province":"Namur",
    "sg:tags":[
        "carpenter"
    ],
    "wof:name":"Bielande Jean-claude",
    "wof:placetype":"venue"
},
  "geometry": {"coordinates":[4.7139778137,50.5853538513],"type":"Point"}
}