{
  "type": "Feature",
  "properties": {
    "addr:full":"Bellegemsestraat 219 Kortrijk (bellegem) West-Vlaanderen 8510",
    "addr:housenumber":"219",
    "addr:postcode":"8510",
    "addr:street":"Bellegemsestraat",
    "iso:country":"BE",
    "sg:address":"Bellegemsestraat 219",
    "sg:city":"Kortrijk (bellegem)",
    "sg:classifiers":[
        {
            "category":"Shopping",
            "subcategory":"Florist",
            "type":"Retail Goods"
        }
    ],
    "sg:phone":"+32 56 20 55 01",
    "sg:postcode":"8510",
    "sg:province":"West-Vlaanderen",
    "wof:name":"Amaranthus",
    "wof:placetype":"venue"
},
  "geometry": {"coordinates":[3.2962601185,50.7776565552],"type":"Point"}
}