{
  "type": "Feature",
  "properties": {
    "iso:country":"BE",
    "sg:address":"Rue De Moorslede 40b",
    "sg:city":"Brussel/bruxelles",
    "sg:orig_category":"Imprimeries and copyshops",
    "sg:phone":"+32 2 425 82 40",
    "sg:postcode":"1020",
    "sg:province":"Bruxelles-Capitale",
    "wof:name":"Espace Copy",
    "wof:placetype":"venue"
},
  "geometry": {"coordinates":[4.3506960869,50.8762931824],"type":"Point"}
}