{
  "type": "Feature",
  "properties": {
    "addr:full":"Knesselarestraat 209 Beernem (oedelem) West-Vlaanderen 8730",
    "addr:housenumber":"209",
    "addr:postcode":"8730",
    "addr:street":"Knesselarestraat",
    "iso:country":"BE",
    "sg:address":"Knesselarestraat 209",
    "sg:city":"Beernem (oedelem)",
    "sg:classifiers":[
        {
            "category":"Airport",
            "subcategory":"International",
            "type":"Transportation"
        }
    ],
    "sg:phone":"+32 50 78 17 26",
    "sg:postcode":"8730",
    "sg:province":"West-Vlaanderen",
    "sg:tags":[
        "-",
        "transport"
    ],
    "wof:name":"Mouton Patrick Bvba",
    "wof:placetype":"venue"
},
  "geometry": {"coordinates":[3.3967370987,51.1464118958],"type":"Point"}
}