{
  "type": "Feature",
  "properties": {
    "addr:full":"Groenstraat 39 Zottegem Oost-Vlaanderen 9620",
    "addr:housenumber":"39",
    "addr:postcode":"9620",
    "addr:street":"Groenstraat",
    "iso:country":"BE",
    "sg:address":"Groenstraat 39",
    "sg:city":"Zottegem",
    "sg:orig_category":"Eleveurs de bovins",
    "sg:phone":"+32 9 360 01 43",
    "sg:postcode":"9620",
    "sg:province":"Oost-Vlaanderen",
    "wof:name":"Gilbert Renaer",
    "wof:placetype":"venue"
},
  "geometry": {"coordinates":[3.8159298897,50.8611183167],"type":"Point"}
}