{
  "type": "Feature",
  "properties": {
    "iso:country":"BE",
    "sg:address":"Zandstraat 10",
    "sg:city":"Brugge (sint-andries)",
    "sg:classifiers":[
        {
            "category":"Health Services",
            "subcategory":"Nursing And Care Facility",
            "type":"Services"
        }
    ],
    "sg:phone":"+32 50 31 55 33",
    "sg:postcode":"8200",
    "sg:province":"West-Vlaanderen",
    "sg:tags":[
        "home",
        "rest"
    ],
    "wof:name":"Residence Rozenhof Vzw",
    "wof:placetype":"venue"
},
  "geometry": {"coordinates":[3.2046730518,51.2032814026],"type":"Point"}
}