{
  "type": "Feature",
  "properties": {
    "addr:full":"Violetstraat 18 Belgium Bruxelles-Capitale 1000",
    "addr:housenumber":"18",
    "addr:postcode":"1000",
    "addr:street":"Violetstraat",
    "iso:country":"BE",
    "sg:address":"Violetstraat 18",
    "sg:city":"Belgium",
    "sg:classifiers":[
        {
            "category":"Travel",
            "subcategory":"Travel Agent",
            "type":"Entertainment"
        }
    ],
    "sg:phone":"+32 2 512 57 45",
    "sg:postcode":"1000",
    "sg:province":"Bruxelles-Capitale",
    "wof:name":"Brussels On Stage",
    "wof:placetype":"venue"
},
  "geometry": {"coordinates":[4.3540182114,50.8493347168],"type":"Point"}
}