{
  "type": "Feature",
  "properties": {
    "iso:country":"BE",
    "sg:address":"Kruisstraat 108",
    "sg:city":"Grimbergen (humbeek)",
    "sg:classifiers":[
        {
            "category":"Home & Garden",
            "subcategory":"Building Materials",
            "type":"Retail Goods"
        }
    ],
    "sg:phone":"+32 2 269 28 68",
    "sg:postcode":"1851",
    "sg:province":"Vlaams-Brabant",
    "sg:tags":[
        "aluminium",
        "construction",
        "-"
    ],
    "wof:name":"Thielemans & Co Nv",
    "wof:placetype":"venue"
},
  "geometry": {"coordinates":[4.3688259125,50.9626998901],"type":"Point"}
}