{
  "type": "Feature",
  "properties": {
    "addr:full":"Markt 11 Kortemark West-Vlaanderen 8610",
    "addr:housenumber":"11",
    "addr:postcode":"8610",
    "addr:street":"Markt",
    "iso:country":"BE",
    "sg:address":"Markt 11",
    "sg:city":"Kortemark",
    "sg:orig_category":"Boucheries",
    "sg:phone":"+32 51 56 76 92",
    "sg:postcode":"8610",
    "sg:province":"West-Vlaanderen",
    "wof:name":"Slagerij Lust-vantyghen",
    "wof:placetype":"venue"
},
  "geometry": {"coordinates":[3.0432488918,51.0286598206],"type":"Point"}
}