{
  "type": "Feature",
  "properties": {
    "addr:full":"Briekhoekstraat 7 Moorslede West-Vlaanderen 8890",
    "addr:housenumber":"7",
    "addr:postcode":"8890",
    "addr:street":"Briekhoekstraat",
    "iso:country":"BE",
    "sg:address":"Briekhoekstraat 7",
    "sg:city":"Moorslede",
    "sg:classifiers":[
        {
            "category":"Building & Trades",
            "subcategory":"Construction",
            "type":"Services"
        }
    ],
    "sg:phone":"+32 51 77 82 48",
    "sg:postcode":"8890",
    "sg:province":"West-Vlaanderen",
    "sg:tags":[
        "builder",
        "chimney"
    ],
    "wof:name":"Bemaco",
    "wof:placetype":"venue"
},
  "geometry": {"coordinates":[3.082365036,50.8874893188],"type":"Point"}
}