{
  "type": "Feature",
  "properties": {
    "iso:country":"BE",
    "sg:address":"Dreef 45",
    "sg:city":"Zomergem",
    "sg:classifiers":[
        {
            "category":"Health Services",
            "subcategory":"Dentist",
            "type":"Services"
        }
    ],
    "sg:phone":"+32 9 372 76 35",
    "sg:postcode":"9930",
    "sg:province":"Oost-Vlaanderen",
    "wof:name":"Haemers L",
    "wof:placetype":"venue"
},
  "geometry": {"coordinates":[3.5640249252,51.1193008423],"type":"Point"}
}