{
  "type": "Feature",
  "properties": {
    "addr:full":"Avenue Wanderpepen 51 Binche (groot) Hainaut 7130",
    "addr:housenumber":"51",
    "addr:postcode":"7130",
    "addr:street":"Avenue Wanderpepen;Groot Hainaut",
    "iso:country":"BE",
    "sg:address":"Avenue Wanderpepen 51",
    "sg:city":"Binche (groot)",
    "sg:orig_category":"Kapsalons",
    "sg:phone":"+32 64 36 69 44",
    "sg:postcode":"7130",
    "sg:province":"Hainaut",
    "wof:name":"Studio Look",
    "wof:placetype":"venue"
},
  "geometry": {"coordinates":[4.1696381569,50.411895752],"type":"Point"}
}