{
  "type": "Feature",
  "properties": {
    "iso:country":"BE",
    "sg:address":"Corneel Smitslei 20",
    "sg:city":"Borsbeek",
    "sg:classifiers":[
        {
            "category":"Health Services",
            "subcategory":"Health Practitioner",
            "type":"Services"
        }
    ],
    "sg:phone":"+32 3 321 07 11",
    "sg:postcode":"2150",
    "sg:province":"Antwerpen",
    "sg:tags":[
        "physiotherapist"
    ],
    "wof:name":"Van Dessel J",
    "wof:placetype":"venue"
},
  "geometry": {"coordinates":[4.4881119728,51.1964912415],"type":"Point"}
}