{
  "type": "Feature",
  "properties": {
    "iso:country":"BE",
    "sg:address":"Rue De La Papeterie 2",
    "sg:city":"Stembert",
    "sg:classifiers":[
        {
            "category":"Manufacturing",
            "subcategory":"Paper Products",
            "type":"Manufacturing & Wholesale Goods"
        }
    ],
    "sg:phone":"+32 87 30 66 11",
    "sg:postcode":"4801",
    "sg:province":"Li\u00e8ge",
    "sg:tags":[
        "household"
    ],
    "wof:name":"Sca Hygi\u00e8ne Products S.a.",
    "wof:placetype":"venue"
},
  "geometry": {"coordinates":[5.9070558548,50.6018104553],"type":"Point"}
}