{
  "type": "Feature",
  "properties": {
    "iso:country":"BE",
    "sg:address":"Chauss\u00e9e De Marche 482",
    "sg:city":"Namur (erpent)",
    "sg:classifiers":[
        {
            "category":"Professional",
            "subcategory":"Engineering",
            "type":"Services"
        }
    ],
    "sg:phone":"+32 81 20 11 60",
    "sg:postcode":"5101",
    "sg:province":"Namur",
    "sg:tags":[
        "technical",
        "equipment",
        "offices-"
    ],
    "wof:name":"Gdl Engineering",
    "wof:placetype":"venue"
},
  "geometry": {"coordinates":[4.8994088173,50.4454078674],"type":"Point"}
}