{
  "type": "Feature",
  "properties": {
    "iso:country":"BE",
    "sg:address":"Rue Buisson-st.-guibert 23",
    "sg:city":"Gembloux",
    "sg:orig_category":"Advocaten and juridische adviseurs",
    "sg:phone":"+32 81 60 12 92",
    "sg:postcode":"5030",
    "sg:province":"Namur",
    "wof:name":"Serge Leonard",
    "wof:placetype":"venue"
},
  "geometry": {"coordinates":[4.6897392273,50.5691795349],"type":"Point"}
}