{
  "type": "Feature",
  "properties": {
    "iso:country":"BE",
    "sg:address":"Blaesstr 40",
    "sg:city":"Brussel",
    "sg:classifiers":[
        {
            "category":"Home & Garden",
            "subcategory":"Furniture",
            "type":"Retail Goods"
        }
    ],
    "sg:phone":"+32 2 511 10 18",
    "sg:postcode":"1000",
    "sg:province":"Bruxelles-Capitale",
    "sg:tags":[
        "household",
        "wood"
    ],
    "wof:name":"New De Wolf Nv",
    "wof:placetype":"venue"
},
  "geometry": {"coordinates":[4.3498911858,50.8399658203],"type":"Point"}
}