{
  "type": "Feature",
  "properties": {
    "iso:country":"BE",
    "sg:address":"Maastrichtersteenweg 22bb",
    "sg:city":"Riemst",
    "sg:orig_category":"Slagers",
    "sg:phone":"+32 12 45 31 76",
    "sg:postcode":"3770",
    "sg:province":"Limburg",
    "wof:name":"Budgetslager",
    "wof:placetype":"venue"
},
  "geometry": {"coordinates":[5.6004528999,50.8137741089],"type":"Point"}
}