{
  "type": "Feature",
  "properties": {
    "iso:country":"BE",
    "sg:address":"Oplintersesteenweg 217ba/04",
    "sg:city":"Tienen",
    "sg:orig_category":"V\u00eatements",
    "sg:phone":"+32 16 82 13 64",
    "sg:postcode":"3300",
    "sg:province":"Vlaams-Brabant",
    "wof:name":"Huis Va Bene",
    "wof:placetype":"venue"
},
  "geometry": {"coordinates":[4.9461121559,50.8186264038],"type":"Point"}
}