{
  "type": "Feature",
  "properties": {
    "iso:country":"BE",
    "sg:address":"Industriepark De Bruwaan 28",
    "sg:city":"Oudenaarde",
    "sg:classifiers":[
        {
            "category":"Local Transit",
            "type":"Transportation"
        }
    ],
    "sg:phone":"+32 55 31 51 05",
    "sg:postcode":"9700",
    "sg:province":"Oost-Vlaanderen",
    "sg:tags":[
        "tanner"
    ],
    "wof:name":"Bekaert La Visonnette Nv",
    "wof:placetype":"venue"
},
  "geometry": {"coordinates":[3.601293087,50.8672447205],"type":"Point"}
}