{
  "type": "Feature",
  "properties": {
    "addr:full":"Leuvensesteenweg 613 Zaventem Vlaams-Brabant 1930",
    "addr:housenumber":"613",
    "addr:postcode":"1930",
    "addr:street":"Leuvensesteenweg",
    "iso:country":"BE",
    "sg:address":"Leuvensesteenweg 613",
    "sg:city":"Zaventem",
    "sg:orig_category":"Werk and personeelsselectie",
    "sg:phone":"+32 2 757 90 24",
    "sg:postcode":"1930",
    "sg:province":"Vlaams-Brabant",
    "wof:name":"V.v.o. Outplacement Int.",
    "wof:placetype":"venue"
},
  "geometry": {"coordinates":[4.4972071648,50.8761253357],"type":"Point"}
}