{
  "type": "Feature",
  "properties": {
    "addr:full":"Ekkersputstraat 7 Zonhoven Limburg 3520",
    "addr:housenumber":"7",
    "addr:postcode":"3520",
    "addr:street":"Ekkersputstraat",
    "iso:country":"BE",
    "sg:address":"Ekkersputstraat 7",
    "sg:city":"Zonhoven",
    "sg:orig_category":"Brood, gebak and snoepgoed",
    "sg:phone":"+32 11 81 70 10",
    "sg:postcode":"3520",
    "sg:province":"Limburg",
    "wof:name":"Elke Reuvis",
    "wof:placetype":"venue"
},
  "geometry": {"coordinates":[5.3592801094,50.9957389832],"type":"Point"}
}