{
  "type": "Feature",
  "properties": {
    "addr:full":"Hoeksken 54 Lille Antwerpen 2275",
    "addr:housenumber":"54",
    "addr:postcode":"2275",
    "addr:street":"Hoeksken",
    "iso:country":"BE",
    "sg:address":"Hoeksken 54",
    "sg:city":"Lille",
    "sg:orig_category":"Kapsalons",
    "sg:phone":"+32 14 88 10 81",
    "sg:postcode":"2275",
    "sg:province":"Antwerpen",
    "wof:name":"Cathy Neefs",
    "wof:placetype":"venue"
},
  "geometry": {"coordinates":[4.8273072243,51.2432556152],"type":"Point"}
}