{
  "type": "Feature",
  "properties": {
    "addr:full":"Leestraat 27 Sint-niklaas (sinaai) Oost-Vlaanderen 9112",
    "addr:housenumber":"27",
    "addr:postcode":"9112",
    "addr:street":"Leestraat;Oost-Vlaanderen",
    "iso:country":"BE",
    "sg:address":"Leestraat 27",
    "sg:city":"Sint-niklaas (sinaai)",
    "sg:classifiers":[
        {
            "category":"Home & Garden",
            "subcategory":"Building Materials",
            "type":"Retail Goods"
        }
    ],
    "sg:phone":"+32 3 722 15 19",
    "sg:postcode":"9112",
    "sg:province":"Oost-Vlaanderen",
    "sg:tags":[
        "window"
    ],
    "wof:name":"Vahodha Bvba",
    "wof:placetype":"venue"
},
  "geometry": {"coordinates":[4.0106391907,51.1439094543],"type":"Point"}
}