{
  "type": "Feature",
  "properties": {
    "iso:country":"BE",
    "sg:address":"Maldegemseweg 67",
    "sg:city":"Knesselare",
    "sg:orig_category":"V\u00e9los",
    "sg:phone":"+32 9 374 45 07",
    "sg:postcode":"9910",
    "sg:province":"Oost-Vlaanderen",
    "wof:name":"Fietshuis De Loof Geert",
    "wof:placetype":"venue"
},
  "geometry": {"coordinates":[3.423707962,51.1416358948],"type":"Point"}
}