{
  "type": "Feature",
  "properties": {
    "addr:full":"Hundelgemsebaan 127 Zwalm (hundelgem) Oost-Vlaanderen 9630",
    "addr:housenumber":"127",
    "addr:postcode":"9630",
    "addr:street":"Zwalm Hundelgem Oost-Vlaanderen",
    "iso:country":"BE",
    "sg:address":"Hundelgemsebaan 127",
    "sg:city":"Zwalm (hundelgem)",
    "sg:classifiers":[
        {
            "category":"Banks & Credit Unions",
            "subcategory":"Investment Brokerage",
            "type":"Services"
        }
    ],
    "sg:phone":"+32 55 49 97 88",
    "sg:postcode":"9630",
    "sg:province":"Oost-Vlaanderen",
    "sg:tags":[
        "repair",
        "-",
        "installation",
        "sanitary",
        "article"
    ],
    "wof:name":"Van Den Noortgate C",
    "wof:placetype":"venue"
},
  "geometry": {"coordinates":[3.7548511028,50.8886146545],"type":"Point"}
}