{
  "type": "Feature",
  "properties": {
    "iso:country":"BE",
    "sg:address":"Rue Stevens-delannoy 95",
    "sg:city":"Bruxelles",
    "sg:classifiers":[
        {
            "category":"Wholesale",
            "subcategory":"Painting Supplies",
            "type":"Manufacturing & Wholesale Goods"
        }
    ],
    "sg:phone":"+32 2 476 01 65",
    "sg:postcode":"1020",
    "sg:province":"Bruxelles-Capitale",
    "sg:tags":[
        "industrial",
        "-"
    ],
    "wof:name":"European Paint Contractors Sa-epc",
    "wof:placetype":"venue"
},
  "geometry": {"coordinates":[4.3416471481,50.8895721436],"type":"Point"}
}