{
  "type": "Feature",
  "properties": {
    "addr:full":"Roodkruisstraat 20 Hamme Oost-Vlaanderen 9220",
    "addr:housenumber":"20",
    "addr:postcode":"9220",
    "addr:street":"Roodkruisstraat",
    "iso:country":"BE",
    "sg:address":"Roodkruisstraat 20",
    "sg:city":"Hamme",
    "sg:orig_category":"Textiel Verlichting and huishoudartikelen",
    "sg:phone":"+32 52 47 89 31",
    "sg:postcode":"9220",
    "sg:province":"Oost-Vlaanderen",
    "wof:name":"Christel Fieer",
    "wof:placetype":"venue"
},
  "geometry": {"coordinates":[4.1424608231,51.1005172729],"type":"Point"}
}