{
  "type": "Feature",
  "properties": {
    "iso:country":"BE",
    "sg:address":"Betekomsestraat 100",
    "sg:city":"Tremelo (baal)",
    "sg:classifiers":[
        {
            "category":"Retail",
            "subcategory":"Funeral Services",
            "type":"Services"
        }
    ],
    "sg:phone":"+32 16 53 42 06",
    "sg:postcode":"3128",
    "sg:province":"Vlaams-Brabant",
    "sg:tags":[
        "director"
    ],
    "wof:name":"Van Edom Begrafenissen",
    "wof:placetype":"venue"
},
  "geometry": {"coordinates":[4.7639679909,50.9905815125],"type":"Point"}
}