{
  "type": "Feature",
  "properties": {
    "addr:full":"Sylvain Dupuislaan 137b8 Anderlecht/anderlecht Bruxelles-Capitale 1070",
    "addr:housenumber":"137b8",
    "addr:postcode":"1070",
    "addr:street":"Sylvain Dupuislaan",
    "iso:country":"BE",
    "sg:address":"Sylvain Dupuislaan 137b8",
    "sg:city":"Anderlecht/anderlecht",
    "sg:classifiers":[
        {
            "category":"Cafe",
            "type":"Food & Drink"
        }
    ],
    "sg:phone":"+32 2 522 15 99",
    "sg:postcode":"1070",
    "sg:province":"Bruxelles-Capitale",
    "sg:tags":[
        "caf\u00e9s"
    ],
    "wof:name":"Liliane Wagenaar",
    "wof:placetype":"venue"
},
  "geometry": {"coordinates":[4.2997951508,50.8372993469],"type":"Point"}
}