{
  "type": "Feature",
  "properties": {
    "addr:full":"Rue Gasniere 5 Villers-le-bouillet Li\u00e8ge 4530",
    "addr:housenumber":"5",
    "addr:postcode":"4530",
    "addr:street":"Rue Gasniere",
    "iso:country":"BE",
    "sg:address":"Rue Gasniere 5",
    "sg:city":"Villers-le-bouillet",
    "sg:orig_category":"Rundveehouders",
    "sg:phone":"+32 19 56 61 51",
    "sg:postcode":"4530",
    "sg:province":"Li\u00e8ge",
    "wof:name":"Philippe Peigneux",
    "wof:placetype":"venue"
},
  "geometry": {"coordinates":[5.2067708969,50.6142997742],"type":"Point"}
}