{
  "type": "Feature",
  "properties": {
    "iso:country":"BE",
    "sg:address":"Avenue Des H\u00catres 25",
    "sg:city":"Sint-genesius-rode/rhode-saint-gen\u00c8se",
    "sg:orig_category":"D\u00e9corateurs d'int\u00e9rieur",
    "sg:phone":"+32 2 358 15 40",
    "sg:postcode":"1640",
    "sg:province":"Vlaams-Brabant",
    "wof:name":"Beatrice Weber",
    "wof:placetype":"venue"
},
  "geometry": {"coordinates":[4.3824181557,50.7566833496],"type":"Point"}
}