{
  "type": "Feature",
  "properties": {
    "iso:country":"BE",
    "sg:address":"Beverlaai 49",
    "sg:city":"Kortrijk",
    "sg:classifiers":[
        {
            "category":"Real Estate",
            "subcategory":"Architect",
            "type":"Services"
        }
    ],
    "sg:phone":"+32 56 22 48 00",
    "sg:postcode":"8500",
    "sg:province":"West-Vlaanderen",
    "wof:name":"Pauwels P",
    "wof:placetype":"venue"
},
  "geometry": {"coordinates":[3.2641870975,50.8212814331],"type":"Point"}
}