{
  "type": "Feature",
  "properties": {
    "addr:full":"Avenue De Scheut 24 Anderlecht Bruxelles-Capitale 1070",
    "addr:housenumber":"24",
    "addr:postcode":"1070",
    "addr:street":"Avenue De Scheut",
    "iso:country":"BE",
    "sg:address":"Avenue De Scheut 24",
    "sg:city":"Anderlecht",
    "sg:orig_category":"Machines-outils Gr",
    "sg:phone":"+32 2 524 32 73",
    "sg:postcode":"1070",
    "sg:province":"Bruxelles-Capitale",
    "wof:name":"Buteco Sprl",
    "wof:placetype":"venue"
},
  "geometry": {"coordinates":[4.3153309822,50.841796875],"type":"Point"}
}