{
  "type": "Feature",
  "properties": {
    "iso:country":"BE",
    "sg:address":"Rue Henri Delhalle 42",
    "sg:city":"Fl\u00e9malle (awirs)",
    "sg:classifiers":[
        {
            "category":"Building & Trades",
            "subcategory":"Electrical",
            "type":"Services"
        }
    ],
    "sg:phone":"+32 4 275 46 83",
    "sg:postcode":"4400",
    "sg:province":"Li\u00e8ge",
    "sg:tags":[
        "electric",
        "-",
        "housewiring",
        "contractor"
    ],
    "wof:name":"Spelgatti J-p",
    "wof:placetype":"venue"
},
  "geometry": {"coordinates":[5.4161639214,50.6064414978],"type":"Point"}
}