{
  "type": "Feature",
  "properties": {
    "iso:country":"BE",
    "sg:address":"Chemin De Feluy 285",
    "sg:city":"Braine-le-comte",
    "sg:classifiers":[
        {
            "category":"Professional",
            "subcategory":"Management & Consulting",
            "type":"Services"
        }
    ],
    "sg:phone":"+32 67 63 71 02",
    "sg:postcode":"7090",
    "sg:province":"Hainaut",
    "sg:tags":[
        "-",
        "processing",
        "data",
        "consultant"
    ],
    "wof:name":"E.v. Consult Sprl",
    "wof:placetype":"venue"
},
  "geometry": {"coordinates":[4.1590209007,50.5944747925],"type":"Point"}
}