{
  "type": "Feature",
  "properties": {
    "addr:full":"Bessemstraat 20 Waregem West-Vlaanderen 8790",
    "addr:housenumber":"20",
    "addr:postcode":"8790",
    "addr:street":"Bessemstraat",
    "iso:country":"BE",
    "sg:address":"Bessemstraat 20",
    "sg:city":"Waregem",
    "sg:classifiers":[
        {
            "category":"Cafe",
            "type":"Food & Drink"
        }
    ],
    "sg:phone":"+32 56 60 28 53",
    "sg:postcode":"8790",
    "sg:province":"West-Vlaanderen",
    "sg:tags":[
        "caf\u00e9s"
    ],
    "wof:name":"Caf\u00c9 Karrekiet",
    "wof:placetype":"venue"
},
  "geometry": {"coordinates":[3.4509971142,50.8833007812],"type":"Point"}
}