{
  "type": "Feature",
  "properties": {
    "iso:country":"BE",
    "sg:address":"Vlassenhout 6",
    "sg:city":"Dendermonde",
    "sg:orig_category":"Projectontwikkelaars",
    "sg:phone":"+32 52 21 14 60",
    "sg:postcode":"9200",
    "sg:province":"Oost-Vlaanderen",
    "wof:name":"Ledanco",
    "wof:placetype":"venue"
},
  "geometry": {"coordinates":[4.1248989105,51.0311012268],"type":"Point"}
}