{
  "type": "Feature",
  "properties": {
    "iso:country":"BE",
    "sg:address":"Rue Du Chemin Vert 105",
    "sg:city":"Charleroi",
    "sg:orig_category":"Rev\u00eatements de sols and murs. Installation de menuiserie en bois and plastique. Bois Quincailleries.",
    "sg:phone":"+32 71 32 10 26",
    "sg:postcode":"6042",
    "sg:province":"Hainaut",
    "wof:name":"Pan O Bois",
    "wof:placetype":"venue"
},
  "geometry": {"coordinates":[4.4421172142,50.4274024963],"type":"Point"}
}