{
  "type": "Feature",
  "properties": {
    "iso:country":"BE",
    "sg:address":"Au-moulin 1",
    "sg:city":"Vresse-sur-semois",
    "sg:orig_category":"Rusthuizen and serviceflats",
    "sg:phone":"+32 61 50 00 20",
    "sg:postcode":"5550",
    "sg:province":"Namur",
    "wof:name":"Seign.du Moulin De Membre",
    "wof:placetype":"venue"
},
  "geometry": {"coordinates":[4.9009847641,49.8628997803],"type":"Point"}
}