{
  "type": "Feature",
  "properties": {
    "iso:country":"BE",
    "sg:address":"Iepersestraat 400",
    "sg:city":"Roeselare",
    "sg:orig_category":"Banques and organismes de cr\u00e9dit",
    "sg:phone":"+32 51 22 98 69",
    "sg:postcode":"8800",
    "sg:province":"West-Vlaanderen",
    "wof:name":"Landbouwkrediet",
    "wof:placetype":"venue"
},
  "geometry": {"coordinates":[3.1051259041,50.9354286194],"type":"Point"}
}