{
  "type": "Feature",
  "properties": {
    "iso:country":"BE",
    "sg:address":"Rue D'houthem 35",
    "sg:city":"Komen-waasten/comines-warneton",
    "sg:orig_category":"Jeux de hasard",
    "sg:phone":"+32 56 55 52 69",
    "sg:postcode":"7780",
    "sg:province":"Hainaut",
    "wof:name":"Pmu",
    "wof:placetype":"venue"
},
  "geometry": {"coordinates":[2.9926259518,50.7723007202],"type":"Point"}
}