{
  "type": "Feature",
  "properties": {
    "iso:country":"BE",
    "sg:address":"Veerstraat 79",
    "sg:city":"Berlare (uitbergen)",
    "sg:classifiers":[
        {
            "category":"Building & Trades",
            "subcategory":"Equipment Rental",
            "type":"Services"
        }
    ],
    "sg:phone":"+32 9 367 70 55",
    "sg:postcode":"9290",
    "sg:province":"Oost-Vlaanderen",
    "sg:tags":[
        "safety",
        "collective",
        "individual",
        "-"
    ],
    "wof:name":"P.c.c. Workwear Nv",
    "wof:placetype":"venue"
},
  "geometry": {"coordinates":[3.9532260895,51.0233383179],"type":"Point"}
}