{
  "type": "Feature",
  "properties": {
    "iso:country":"BE",
    "sg:address":"Vriesenhof 20 Box 5",
    "sg:city":"Leuven",
    "sg:classifiers":[
        {
            "category":"Health Services",
            "subcategory":"Health Practitioner",
            "type":"Services"
        }
    ],
    "sg:phone":"+32 497 93 08 47",
    "sg:postcode":"3000",
    "sg:province":"Vlaams-Brabant",
    "sg:tags":[
        "therapist",
        "speech"
    ],
    "wof:name":"Royackers L",
    "wof:placetype":"venue"
},
  "geometry": {"coordinates":[4.6930470467,50.8819084167],"type":"Point"}
}