{
  "type": "Feature",
  "properties": {
    "addr:full":"Van Eycklaan 89b1 Maaseik Limburg 3680",
    "addr:housenumber":"89b1",
    "addr:postcode":"3680",
    "addr:street":"Van Eycklaan",
    "iso:country":"BE",
    "sg:address":"Van Eycklaan 89b1",
    "sg:city":"Maaseik",
    "sg:orig_category":"Beautyfarms, relaxatie and lichamelijk welzijn Schoonheidssalons",
    "sg:phone":"+32 89 56 59 59",
    "sg:postcode":"3680",
    "sg:province":"Limburg",
    "wof:name":"Instituut Muscari",
    "wof:placetype":"venue"
},
  "geometry": {"coordinates":[5.786383152,51.0990638733],"type":"Point"}
}