{
  "type": "Feature",
  "properties": {
    "iso:country":"BE",
    "sg:address":"Monseigneur De Haerneln 43",
    "sg:city":"Kortrijk",
    "sg:orig_category":"M\u00e9decins and sp\u00e9cialistes",
    "sg:phone":"+32 56 22 39 66",
    "sg:postcode":"8500",
    "sg:province":"West-Vlaanderen",
    "wof:name":"Christiaan De Niel",
    "wof:placetype":"venue"
},
  "geometry": {"coordinates":[3.2602050304,50.8214302063],"type":"Point"}
}