{
  "type": "Feature",
  "properties": {
    "iso:country":"BE",
    "sg:address":"Ankerstraat 2-4",
    "sg:city":"Sint-niklaas",
    "sg:classifiers":[
        {
            "category":"Casinos & Gambling",
            "type":"Entertainment"
        }
    ],
    "sg:phone":"+32 3 765 06 84",
    "sg:postcode":"9100",
    "sg:province":"Oost-Vlaanderen",
    "wof:name":"Circus Leisure Nv",
    "wof:placetype":"venue"
},
  "geometry": {"coordinates":[4.1432499886,51.1653442383],"type":"Point"}
}