{
  "type": "Feature",
  "properties": {
    "addr:full":"Rue Du Bosquet 3 Ottignies-louvain-la-neuve (louvain-la-neuve) Brabant Wallon 1348",
    "addr:housenumber":"3",
    "addr:postcode":"1348",
    "addr:street":"Rue Du Bosquet",
    "iso:country":"BE",
    "sg:address":"Rue Du Bosquet 3",
    "sg:city":"Ottignies-louvain-la-neuve (louvain-la-neuve)",
    "sg:classifiers":[
        {
            "category":"Professional",
            "subcategory":"Computer Services",
            "type":"Services"
        }
    ],
    "sg:phone":"+32 10 45 04 36",
    "sg:postcode":"1348",
    "sg:province":"Brabant Wallon",
    "sg:tags":[
        "-",
        "processing",
        "data",
        "software"
    ],
    "wof:name":"Sage Center Louvain-la-neuve",
    "wof:placetype":"venue"
},
  "geometry": {"coordinates":[4.6317892075,50.6617698669],"type":"Point"}
}