{
  "type": "Feature",
  "properties": {
    "addr:full":"Halensebaan 154 Diest Vlaams-Brabant 3290",
    "addr:housenumber":"154",
    "addr:postcode":"3290",
    "addr:street":"Halensebaan",
    "iso:country":"BE",
    "sg:address":"Halensebaan 154",
    "sg:city":"Diest",
    "sg:classifiers":[
        {
            "category":"Restaurant",
            "type":"Food & Drink"
        }
    ],
    "sg:phone":"+32 13 32 27 90",
    "sg:postcode":"3290",
    "sg:province":"Vlaams-Brabant",
    "sg:tags":[
        "organisatie",
        "feesten",
        "van",
        "catering"
    ],
    "wof:name":"De Leigracht Restaurant",
    "wof:placetype":"venue"
},
  "geometry": {"coordinates":[5.0777821541,50.9664230347],"type":"Point"}
}