{
  "type": "Feature",
  "properties": {
    "iso:country":"BE",
    "sg:address":"Lange Dijkstraat 165",
    "sg:city":"Dendermonde (sint-gillis-bij-dendermonde)",
    "sg:classifiers":[
        {
            "category":"Social Services",
            "subcategory":"Job Training",
            "type":"Services"
        }
    ],
    "sg:phone":"+32 52 22 16 94",
    "sg:postcode":"9200",
    "sg:province":"Oost-Vlaanderen",
    "sg:tags":[
        "personnel"
    ],
    "wof:name":"Interpres",
    "wof:placetype":"venue"
},
  "geometry": {"coordinates":[4.1291389465,51.0262870789],"type":"Point"}
}