{
  "type": "Feature",
  "properties": {
    "addr:full":"Clos Des Erables 22 Mouscron (herseaux) Hainaut 7712",
    "addr:housenumber":"22",
    "addr:postcode":"7712",
    "addr:street":"Clos Des Erables",
    "iso:country":"BE",
    "sg:address":"Clos Des Erables 22",
    "sg:city":"Mouscron (herseaux)",
    "sg:classifiers":[
        {
            "category":"Health Services",
            "subcategory":"Nursing And Care Facility",
            "type":"Services"
        }
    ],
    "sg:phone":"+32 56 33 69 22",
    "sg:postcode":"7712",
    "sg:province":"Hainaut",
    "sg:tags":[
        "home"
    ],
    "wof:name":"Hespel L",
    "wof:placetype":"venue"
},
  "geometry": {"coordinates":[3.2333610058,50.7282066345],"type":"Point"}
}