{
  "type": "Feature",
  "properties": {
    "addr:full":"Waterloolaan 61 Brussel/bruxelles Bruxelles-Capitale 1000",
    "addr:housenumber":"61",
    "addr:postcode":"1000",
    "addr:street":"Waterloolaan;/",
    "iso:country":"BE",
    "sg:address":"Waterloolaan 61",
    "sg:city":"Brussel/bruxelles",
    "sg:classifiers":[
        {
            "category":"Restaurant",
            "type":"Food & Drink"
        }
    ],
    "sg:phone":"+32 2 511 11 27",
    "sg:postcode":"1000",
    "sg:province":"Bruxelles-Capitale",
    "wof:name":"Le Nemrod",
    "wof:placetype":"venue"
},
  "geometry": {"coordinates":[4.3554940224,50.8362960815],"type":"Point"}
}