{
  "type": "Feature",
  "properties": {
    "iso:country":"BE",
    "sg:address":"Nieuwbrugstraat 40",
    "sg:city":"Machelen",
    "sg:orig_category":"Rev\u00eatements de sols and murs",
    "sg:phone":"+32 2 251 60 18",
    "sg:postcode":"1830",
    "sg:province":"Vlaams-Brabant",
    "wof:name":"Schumacher (clypot)",
    "wof:placetype":"venue"
},
  "geometry": {"coordinates":[4.4280390739,50.9092788696],"type":"Point"}
}