{
  "type": "Feature",
  "properties": {
    "addr:full":"Dorpsstraat 36 De Panne West-Vlaanderen 8660",
    "addr:housenumber":"36",
    "addr:postcode":"8660",
    "addr:street":"Dorpsstraat",
    "iso:country":"BE",
    "sg:address":"Dorpsstraat 36",
    "sg:city":"De Panne",
    "sg:orig_category":"Eleveurs and marchands de porcs",
    "sg:phone":"+32 58 41 10 84",
    "sg:postcode":"8660",
    "sg:province":"West-Vlaanderen",
    "wof:name":"Jose Soubry",
    "wof:placetype":"venue"
},
  "geometry": {"coordinates":[2.600258112,51.0744628906],"type":"Point"}
}