{
  "type": "Feature",
  "properties": {
    "addr:full":"Rakestraat 23 Wingene West-Vlaanderen 8750",
    "addr:housenumber":"23",
    "addr:postcode":"8750",
    "addr:street":"Rakestraat",
    "iso:country":"BE",
    "sg:address":"Rakestraat 23",
    "sg:city":"Wingene",
    "sg:orig_category":"Afbraak- and draineerwerken Antiek",
    "sg:phone":"+32 51 65 74 13",
    "sg:postcode":"8750",
    "sg:province":"West-Vlaanderen",
    "wof:name":"Ludwig Deblaere",
    "wof:placetype":"venue"
},
  "geometry": {"coordinates":[3.2985620499,51.0717582703],"type":"Point"}
}