{
  "type": "Feature",
  "properties": {
    "addr:full":"Rue Du Jardinage 19 Sint-agatha-berchem Bruxelles-Capitale 1082",
    "addr:housenumber":"19",
    "addr:postcode":"1082",
    "addr:street":"Rue Du Jardinage",
    "iso:country":"BE",
    "sg:address":"Rue Du Jardinage 19",
    "sg:city":"Sint-agatha-berchem",
    "sg:orig_category":"Jardinage",
    "sg:phone":"+32 2 465 23 59",
    "sg:postcode":"1082",
    "sg:province":"Bruxelles-Capitale",
    "wof:name":"Andr\u00c9 Gil",
    "wof:placetype":"venue"
},
  "geometry": {"coordinates":[4.2962379456,50.8562545776],"type":"Point"}
}