{
  "type": "Feature",
  "properties": {
    "addr:full":"Lierbaan 16b2 Putte Antwerpen 2580",
    "addr:housenumber":"16b2",
    "addr:postcode":"2580",
    "addr:street":"Lierbaan",
    "iso:country":"BE",
    "sg:address":"Lierbaan 16b2",
    "sg:city":"Putte",
    "sg:orig_category":"D\u00e9corateurs d'int\u00e9rieur",
    "sg:phone":"+32 15 76 12 99",
    "sg:postcode":"2580",
    "sg:province":"Antwerpen",
    "wof:name":"Martens Design",
    "wof:placetype":"venue"
},
  "geometry": {"coordinates":[4.629087925,51.055683136],"type":"Point"}
}