{
  "type": "Feature",
  "properties": {
    "addr:full":"Gomar Vandewielelaan 11 Ronse/renaix Oost-Vlaanderen 9600",
    "addr:housenumber":"11",
    "addr:postcode":"9600",
    "addr:street":"Vandewielelaan",
    "iso:country":"BE",
    "sg:address":"Gomar Vandewielelaan 11",
    "sg:city":"Ronse/renaix",
    "sg:classifiers":[
        {
            "category":"Professional",
            "subcategory":"Accounting & Tax Preparation",
            "type":"Services"
        }
    ],
    "sg:phone":"+32 55 21 43 11",
    "sg:postcode":"9600",
    "sg:province":"Oost-Vlaanderen",
    "sg:tags":[
        "accountant"
    ],
    "wof:name":"Charles Vanderbecken",
    "wof:placetype":"venue"
},
  "geometry": {"coordinates":[3.5940380096,50.7421607971],"type":"Point"}
}