{
  "type": "Feature",
  "properties": {
    "iso:country":"BE",
    "sg:address":"Moerstraat 73",
    "sg:city":"Kaprijke",
    "sg:orig_category":"Epiceries",
    "sg:phone":"+32 9 379 87 03",
    "sg:postcode":"9970",
    "sg:province":"Oost-Vlaanderen",
    "wof:name":"Kati Claeys",
    "wof:placetype":"venue"
},
  "geometry": {"coordinates":[3.5904409885,51.2319831848],"type":"Point"}
}