{
  "type": "Feature",
  "properties": {
    "addr:full":"Tongersestr 56 Bilzen Limburg 3740",
    "addr:housenumber":"56",
    "addr:postcode":"3740",
    "addr:street":"Tongersestr",
    "iso:country":"BE",
    "sg:address":"Tongersestr 56",
    "sg:city":"Bilzen",
    "sg:classifiers":[
        {
            "category":"Autos & Motor Vehicles",
            "subcategory":"Automobile Sales",
            "type":"Retail Goods"
        }
    ],
    "sg:phone":"+32 89 49 21 27",
    "sg:postcode":"3740",
    "sg:province":"Limburg",
    "sg:tags":[
        "equipment",
        "motor-cars",
        "transport"
    ],
    "wof:name":"Smets Armand Garage Nv",
    "wof:placetype":"venue"
},
  "geometry": {"coordinates":[5.5073781013,50.8657722473],"type":"Point"}
}