{
  "type": "Feature",
  "properties": {
    "addr:full":"Ijzerwegstraat 7 Gistel (snaaskerke) West-Vlaanderen 8470",
    "addr:housenumber":"7",
    "addr:postcode":"8470",
    "addr:street":"Ijzerwegstraat",
    "iso:country":"BE",
    "sg:address":"Ijzerwegstraat 7",
    "sg:city":"Gistel (snaaskerke)",
    "sg:classifiers":[
        {
            "category":"Shopping",
            "subcategory":"Party Supplies",
            "type":"Retail Goods"
        }
    ],
    "sg:phone":"+32 59 27 43 44",
    "sg:postcode":"8470",
    "sg:province":"West-Vlaanderen",
    "sg:tags":[
        "-",
        "pedicure"
    ],
    "wof:name":"Axamed A.c.-medico",
    "wof:placetype":"venue"
},
  "geometry": {"coordinates":[2.940901041,51.1776123047],"type":"Point"}
}