{
  "type": "Feature",
  "properties": {
    "addr:full":"Wampenberg 83 Arendonk Antwerpen 2370",
    "addr:housenumber":"83",
    "addr:postcode":"2370",
    "addr:street":"Wampenberg",
    "iso:country":"BE",
    "sg:address":"Wampenberg 83",
    "sg:city":"Arendonk",
    "sg:orig_category":"Banques and organismes de cr\u00e9dit",
    "sg:phone":"+32 14 67 82 71",
    "sg:postcode":"2370",
    "sg:province":"Antwerpen",
    "wof:name":"Bankunie",
    "wof:placetype":"venue"
},
  "geometry": {"coordinates":[5.0936489105,51.3274345398],"type":"Point"}
}