{
  "type": "Feature",
  "properties": {
    "addr:full":"Stijn Streuvelsstraat 25 Anzegem West-Vlaanderen 8570",
    "addr:housenumber":"25",
    "addr:postcode":"8570",
    "addr:street":"Stijn Streuvelsstraat",
    "iso:country":"BE",
    "sg:address":"Stijn Streuvelsstraat 25",
    "sg:city":"Anzegem",
    "sg:orig_category":"Mus\u00e9es and patrimoine culturel",
    "sg:phone":"+32 56 77 72 14",
    "sg:postcode":"8570",
    "sg:province":"West-Vlaanderen",
    "wof:name":"Museum S. Streuvels",
    "wof:placetype":"venue"
},
  "geometry": {"coordinates":[3.4388918877,50.8147315979],"type":"Point"}
}