{
  "type": "Feature",
  "properties": {
    "addr:full":"Hoekstraat 10 Leopoldsburg (heppen) Limburg 3971",
    "addr:housenumber":"10",
    "addr:postcode":"3971",
    "addr:street":"Hoekstraat",
    "iso:country":"BE",
    "sg:address":"Hoekstraat 10",
    "sg:city":"Leopoldsburg (heppen)",
    "sg:classifiers":[
        {
            "category":"Health Services",
            "subcategory":"Health Practitioner",
            "type":"Services"
        }
    ],
    "sg:phone":"+32 11 34 78 80",
    "sg:postcode":"3971",
    "sg:province":"Limburg",
    "sg:tags":[
        "therapist",
        "speech"
    ],
    "wof:name":"Janssen C",
    "wof:placetype":"venue"
},
  "geometry": {"coordinates":[5.228705883,51.1063995361],"type":"Point"}
}