{
  "type": "Feature",
  "properties": {
    "addr:full":"Rue De Goz\u00c9e 569 Montigny-le-tilleul Hainaut 6110",
    "addr:housenumber":"569",
    "addr:postcode":"6110",
    "addr:street":"Rue De Goze\u0301E",
    "iso:country":"BE",
    "sg:address":"Rue De Goz\u00c9e 569",
    "sg:city":"Montigny-le-tilleul",
    "sg:orig_category":"V\u00e9t\u00e9rinaires",
    "sg:phone":"+32 71 51 64 62",
    "sg:postcode":"6110",
    "sg:province":"Hainaut",
    "wof:name":"Philippe Bury",
    "wof:placetype":"venue"
},
  "geometry": {"coordinates":[4.3638110161,50.3700332642],"type":"Point"}
}