{
  "type": "Feature",
  "properties": {
    "addr:full":"Henri Cartonstraat 3 Ieper West-Vlaanderen 8900",
    "addr:housenumber":"3",
    "addr:postcode":"8900",
    "addr:street":"Henri Cartonstraat",
    "iso:country":"BE",
    "sg:address":"Henri Cartonstraat 3",
    "sg:city":"Ieper",
    "sg:classifiers":[
        {
            "category":"Real Estate",
            "subcategory":"Architect",
            "type":"Services"
        }
    ],
    "sg:phone":"+32 57 20 77 60",
    "sg:postcode":"8900",
    "sg:province":"West-Vlaanderen",
    "wof:name":"Defever I",
    "wof:placetype":"venue"
},
  "geometry": {"coordinates":[2.886674881,50.8533706665],"type":"Point"}
}