{
  "type": "Feature",
  "properties": {
    "addr:full":"Geraardsbergsestraat 7 Dilbeek (schepdaal) Vlaams-Brabant 1703",
    "addr:housenumber":"7",
    "addr:postcode":"1703",
    "addr:street":"Geraardsbergsestraat",
    "iso:country":"BE",
    "sg:address":"Geraardsbergsestraat 7",
    "sg:city":"Dilbeek (schepdaal)",
    "sg:classifiers":[
        {
            "category":"Professional",
            "subcategory":"Management & Consulting",
            "type":"Services"
        }
    ],
    "sg:phone":"+32 2 567 21 75",
    "sg:postcode":"1703",
    "sg:province":"Vlaams-Brabant",
    "sg:tags":[
        "consultant",
        "relation",
        "public"
    ],
    "wof:name":"G & G Productions",
    "wof:placetype":"venue"
},
  "geometry": {"coordinates":[4.2113389969,50.8363990784],"type":"Point"}
}