{
  "type": "Feature",
  "properties": {
    "addr:full":"Azalealei 2 Hove Antwerpen 2540",
    "addr:housenumber":"2",
    "addr:postcode":"2540",
    "addr:street":"Azalealei",
    "iso:country":"BE",
    "sg:address":"Azalealei 2",
    "sg:city":"Hove",
    "sg:classifiers":[
        {
            "category":"Health Services",
            "subcategory":"Doctor",
            "type":"Services"
        }
    ],
    "sg:phone":"+32 3 455 90 30",
    "sg:postcode":"2540",
    "sg:province":"Antwerpen",
    "sg:tags":[
        "medicinephysicians",
        "surgeon"
    ],
    "wof:name":"Lenz Mark",
    "wof:placetype":"venue"
},
  "geometry": {"coordinates":[4.4694399834,51.1557579041],"type":"Point"}
}