{
  "type": "Feature",
  "properties": {
    "addr:full":"Stationsstraat 125 Sint-katelijne-waver Antwerpen 2860",
    "addr:housenumber":"125",
    "addr:postcode":"2860",
    "addr:street":"Stationsstraat",
    "iso:country":"BE",
    "sg:address":"Stationsstraat 125",
    "sg:city":"Sint-katelijne-waver",
    "sg:orig_category":"Avocats and conseillers juridiques",
    "sg:phone":"+32 15 31 13 21",
    "sg:postcode":"2860",
    "sg:province":"Antwerpen",
    "wof:name":"A. Wittevrongel",
    "wof:placetype":"venue"
},
  "geometry": {"coordinates":[4.5191102028,51.0704154968],"type":"Point"}
}