{
  "type": "Feature",
  "properties": {
    "addr:full":"Rue De La Tulipe 41 Elsene/ixelles Bruxelles-Capitale 1050",
    "addr:housenumber":"41",
    "addr:postcode":"1050",
    "addr:street":"Rue De La Tulipe",
    "iso:country":"BE",
    "sg:address":"Rue De La Tulipe 41",
    "sg:city":"Elsene/ixelles",
    "sg:orig_category":"Services annexes des transports terrestres",
    "sg:phone":"+32 2 511 37 52",
    "sg:postcode":"1050",
    "sg:province":"Bruxelles-Capitale",
    "wof:name":"Parking Tulipe",
    "wof:placetype":"venue"
},
  "geometry": {"coordinates":[4.3679847717,50.834941864],"type":"Point"}
}