{
  "type": "Feature",
  "properties": {
    "addr:full":"Rue Rodolphe Delval 39 Courcelles Hainaut 6183",
    "addr:housenumber":"39",
    "addr:postcode":"6183",
    "addr:street":"Rue Rodolphe Delval",
    "iso:country":"BE",
    "sg:address":"Rue Rodolphe Delval 39",
    "sg:city":"Courcelles",
    "sg:orig_category":"Pharmaciens",
    "sg:phone":"+32 71 45 01 96",
    "sg:postcode":"6183",
    "sg:province":"Hainaut",
    "wof:name":"Multipharma",
    "wof:placetype":"venue"
},
  "geometry": {"coordinates":[4.3293838501,50.4633407593],"type":"Point"}
}