{
  "type": "Feature",
  "properties": {
    "iso:country":"BE",
    "sg:address":"Rue De Lexhy 37",
    "sg:city":"Fexhe-le-haut-clocher",
    "sg:classifiers":[
        {
            "category":"Shopping",
            "subcategory":"Antiques",
            "type":"Retail Goods"
        }
    ],
    "sg:phone":"+32 4 250 57 04",
    "sg:postcode":"4347",
    "sg:province":"Li\u00e8ge",
    "sg:tags":[
        "restoration"
    ],
    "wof:name":"Monfort L",
    "wof:placetype":"venue"
},
  "geometry": {"coordinates":[5.4029459953,50.6492385864],"type":"Point"}
}