{
  "type": "Feature",
  "properties": {
    "addr:full":"Edestraat 14ba Haaltert Oost-Vlaanderen 9450",
    "addr:housenumber":"14ba",
    "addr:postcode":"9450",
    "addr:street":"Edestraat",
    "iso:country":"BE",
    "sg:address":"Edestraat 14ba",
    "sg:city":"Haaltert",
    "sg:orig_category":"Fabrication and montage de mobilier",
    "sg:phone":"+32 53 83 55 62",
    "sg:postcode":"9450",
    "sg:province":"Oost-Vlaanderen",
    "wof:name":"Karel Beernaert",
    "wof:placetype":"venue"
},
  "geometry": {"coordinates":[3.9953699112,50.9091796875],"type":"Point"}
}