{
  "type": "Feature",
  "properties": {
    "iso:country":"BE",
    "sg:address":"Generaal Lemanstraat 142",
    "sg:city":"Generaal Lemanstraat 142",
    "sg:orig_category":"Installatie van metalen schrijnwerk",
    "sg:phone":"+32 71 37 00 21",
    "sg:postcode":"6043",
    "sg:province":"Hainaut",
    "wof:name":"Europortes",
    "wof:placetype":"venue"
},
  "geometry": {"coordinates":[4.3895030022,50.4449501038],"type":"Point"}
}