{
  "type": "Feature",
  "properties": {
    "iso:country":"BE",
    "sg:address":"Eikenlaan 10",
    "sg:city":"Bilzen",
    "sg:orig_category":"Alternatieve geneeskunde",
    "sg:phone":"+32 89 50 30 45",
    "sg:postcode":"3740",
    "sg:province":"Limburg",
    "wof:name":"Bodystyling",
    "wof:placetype":"venue"
},
  "geometry": {"coordinates":[5.5112099648,50.8679008484],"type":"Point"}
}