{
  "type": "Feature",
  "properties": {
    "iso:country":"BE",
    "sg:address":"Vrijthout 31",
    "sg:city":"Asse",
    "sg:classifiers":[
        {
            "category":"Farming",
            "subcategory":"Livestock Farm",
            "type":"Manufacturing & Wholesale Goods"
        }
    ],
    "sg:phone":"+32 2 452 87 53",
    "sg:postcode":"1730",
    "sg:province":"Vlaams-Brabant",
    "sg:tags":[
        "buyer"
    ],
    "wof:name":"Buyl H",
    "wof:placetype":"venue"
},
  "geometry": {"coordinates":[4.2106947899,50.8879203796],"type":"Point"}
}