{
  "type": "Feature",
  "properties": {
    "iso:country":"BE",
    "sg:address":"Rue De Porcheresse 9",
    "sg:city":"Paliseul (opont)",
    "sg:classifiers":[
        {
            "category":"Farming",
            "subcategory":"Fish & Marine Products",
            "type":"Manufacturing & Wholesale Goods"
        }
    ],
    "sg:phone":"+32 61 53 49 77",
    "sg:postcode":"6852",
    "sg:province":"Luxembourg",
    "sg:tags":[
        "breeding"
    ],
    "wof:name":"Matton J",
    "wof:placetype":"venue"
},
  "geometry": {"coordinates":[5.1229200363,49.9619483948],"type":"Point"}
}