{
  "type": "Feature",
  "properties": {
    "addr:full":"Chauss\u00e9e De Wavre 733 Bruxelles (etterbeek) Bruxelles-Capitale 1040",
    "addr:housenumber":"733",
    "addr:postcode":"1040",
    "addr:street":"Chausse\u0301E De Wavre",
    "iso:country":"BE",
    "sg:address":"Chauss\u00e9e De Wavre 733",
    "sg:city":"Bruxelles (etterbeek)",
    "sg:classifiers":[
        {
            "category":"Retail",
            "subcategory":"Repair Shop",
            "type":"Services"
        }
    ],
    "sg:phone":"+32 2 647 38 69",
    "sg:postcode":"1040",
    "sg:province":"Bruxelles-Capitale",
    "sg:tags":[
        "machine",
        "sewing",
        "-"
    ],
    "wof:name":"E.m.c.",
    "wof:placetype":"venue"
},
  "geometry": {"coordinates":[4.3920121193,50.8290786743],"type":"Point"}
}