{
  "type": "Feature",
  "properties": {
    "addr:full":"Averegtenlaan 14 Heist-op-den-berg Antwerpen 2220",
    "addr:housenumber":"14",
    "addr:postcode":"2220",
    "addr:street":"Averegtenlaan",
    "iso:country":"BE",
    "sg:address":"Averegtenlaan 14",
    "sg:city":"Heist-op-den-berg",
    "sg:orig_category":"Artsen and specialisten",
    "sg:phone":"+32 15 24 82 37",
    "sg:postcode":"2220",
    "sg:province":"Antwerpen",
    "wof:name":"Carolus Mertens",
    "wof:placetype":"venue"
},
  "geometry": {"coordinates":[4.7241001129,51.0802383423],"type":"Point"}
}