{
  "type": "Feature",
  "properties": {
    "addr:full":"Roze 18 Eeklo Oost-Vlaanderen 9900",
    "addr:housenumber":"18",
    "addr:postcode":"9900",
    "addr:street":"Roze",
    "iso:country":"BE",
    "sg:address":"Roze 18",
    "sg:city":"Eeklo",
    "sg:orig_category":"D\u00e9taillants en pi\u00e8ces and accessoires de voitures",
    "sg:phone":"+32 9 377 61 88",
    "sg:postcode":"9900",
    "sg:province":"Oost-Vlaanderen",
    "wof:name":"W. Thys",
    "wof:placetype":"venue"
},
  "geometry": {"coordinates":[3.5719609261,51.1876106262],"type":"Point"}
}