{
  "type": "Feature",
  "properties": {
    "addr:full":"Lostraat 5 Nevele (merendree) Oost-Vlaanderen 9850",
    "addr:housenumber":"5",
    "addr:postcode":"9850",
    "addr:street":"Lostraat",
    "iso:country":"BE",
    "sg:address":"Lostraat 5",
    "sg:city":"Nevele (merendree)",
    "sg:classifiers":[
        {
            "category":"Freight",
            "type":"Transportation"
        }
    ],
    "sg:phone":"+32 9 371 51 44",
    "sg:postcode":"9850",
    "sg:province":"Oost-Vlaanderen",
    "sg:tags":[
        "-",
        "transport"
    ],
    "wof:name":"Verhelst W",
    "wof:placetype":"venue"
},
  "geometry": {"coordinates":[3.5826079845,51.0799446106],"type":"Point"}
}