{
  "type": "Feature",
  "properties": {
    "addr:full":"Asserweg 124 Zutendaal Limburg 3690",
    "addr:housenumber":"124",
    "addr:postcode":"3690",
    "addr:street":"Asserweg",
    "iso:country":"BE",
    "sg:address":"Asserweg 124",
    "sg:city":"Zutendaal",
    "sg:orig_category":"Sportclubs",
    "sg:phone":"+32 89 61 19 09",
    "sg:postcode":"3690",
    "sg:province":"Limburg",
    "wof:name":"Zutend. Hartenvrienden",
    "wof:placetype":"venue"
},
  "geometry": {"coordinates":[5.564209938,50.9630584717],"type":"Point"}
}