{
  "type": "Feature",
  "properties": {
    "iso:country":"BE",
    "sg:address":"Quai Godefroid Kurth 15",
    "sg:city":"Li\u00c8ge",
    "sg:orig_category":"Artistes ind\u00e9pendants",
    "sg:phone":"+32 4 343 83 61",
    "sg:postcode":"4020",
    "sg:province":"Li\u00e8ge",
    "wof:name":"Marie-rose Roland",
    "wof:placetype":"venue"
},
  "geometry": {"coordinates":[5.5882182121,50.6459655762],"type":"Point"}
}