{
  "type": "Feature",
  "properties": {
    "addr:full":"Oostkade 10 Zelzate Oost-Vlaanderen 9060",
    "addr:housenumber":"10",
    "addr:postcode":"9060",
    "addr:street":"Oostkade",
    "iso:country":"BE",
    "sg:address":"Oostkade 10",
    "sg:city":"Zelzate",
    "sg:orig_category":"Banken and kredietinstellingen",
    "sg:phone":"+32 9 345 50 21",
    "sg:postcode":"9060",
    "sg:province":"Oost-Vlaanderen",
    "wof:name":"Fortis",
    "wof:placetype":"venue"
},
  "geometry": {"coordinates":[3.8096299171,51.2006988525],"type":"Point"}
}