{
  "type": "Feature",
  "properties": {
    "iso:country":"BE",
    "sg:address":"Vilvoordsesteenweg 299",
    "sg:city":"Grimbergen",
    "sg:orig_category":"Cosmetica and toiletartikelen Drogisterijen",
    "sg:phone":"+32 2 253 41 66",
    "sg:postcode":"1850",
    "sg:province":"Vlaams-Brabant",
    "wof:name":"Di",
    "wof:placetype":"venue"
},
  "geometry": {"coordinates":[4.3897109032,50.9273643494],"type":"Point"}
}