{
  "type": "Feature",
  "properties": {
    "addr:full":"Place Reine Astrid 1 Vis\u00c9 Li\u00e8ge 4600",
    "addr:housenumber":"1",
    "addr:postcode":"4600",
    "addr:street":"Place Reine Astrid",
    "iso:country":"BE",
    "sg:address":"Place Reine Astrid 1",
    "sg:city":"Vis\u00c9",
    "sg:orig_category":"Verlichting and huishoudartikelen",
    "sg:phone":"+32 4 379 71 73",
    "sg:postcode":"4600",
    "sg:province":"Li\u00e8ge",
    "wof:name":"Maison Douin",
    "wof:placetype":"venue"
},
  "geometry": {"coordinates":[5.6940031052,50.7375869751],"type":"Point"}
}