{
  "type": "Feature",
  "properties": {
    "iso:country":"BE",
    "sg:address":"Meensesteenweg 384",
    "sg:city":"Kortrijk",
    "sg:orig_category":"Kapsalons",
    "sg:phone":"+32 56 37 22 95",
    "sg:postcode":"8501",
    "sg:province":"West-Vlaanderen",
    "wof:name":"Coiffure Unique",
    "wof:placetype":"venue"
},
  "geometry": {"coordinates":[3.2233710289,50.8215293884],"type":"Point"}
}