{
  "type": "Feature",
  "properties": {
    "iso:country":"BE",
    "sg:address":"Zwevegemsestraat 163",
    "sg:city":"Harelbeke",
    "sg:classifiers":[
        {
            "category":"Autos & Motor Vehicles",
            "subcategory":"Automobile Sales",
            "type":"Retail Goods"
        }
    ],
    "sg:phone":"+32 56 21 93 96",
    "sg:postcode":"8530",
    "sg:province":"West-Vlaanderen",
    "sg:tags":[
        "car",
        "used",
        "-"
    ],
    "wof:name":"Huysentruyt F",
    "wof:placetype":"venue"
},
  "geometry": {"coordinates":[3.3223659992,50.8249053955],"type":"Point"}
}