{
  "type": "Feature",
  "properties": {
    "addr:full":"Keuvelhoekstraat 58 Knokke-heist West-Vlaanderen 8300",
    "addr:housenumber":"58",
    "addr:postcode":"8300",
    "addr:street":"Keuvelhoekstraat",
    "iso:country":"BE",
    "sg:address":"Keuvelhoekstraat 58",
    "sg:city":"Knokke-heist",
    "sg:orig_category":"Sportclubs",
    "sg:phone":"+32 50 61 42 76",
    "sg:postcode":"8300",
    "sg:province":"West-Vlaanderen",
    "wof:name":"Wandelende Noordzee Boy's",
    "wof:placetype":"venue"
},
  "geometry": {"coordinates":[3.2985169888,51.339805603],"type":"Point"}
}