{
  "type": "Feature",
  "properties": {
    "iso:country":"BE",
    "sg:address":"Justus Lipsiusstraat 46",
    "sg:city":"Leuven",
    "sg:orig_category":"Editeurs de journaux. Editeurs de revues and p\u00e9riodiques",
    "sg:phone":"+32 11 64 03 31",
    "sg:postcode":"3000",
    "sg:province":"Vlaams-Brabant",
    "wof:name":"Gonzo Circus",
    "wof:placetype":"venue"
},
  "geometry": {"coordinates":[4.7154541016,50.8777885437],"type":"Point"}
}