{
  "type": "Feature",
  "properties": {
    "addr:full":"Mannenberg 4 Scherpenheuvel-zichem Vlaams-Brabant 3270",
    "addr:housenumber":"4",
    "addr:postcode":"3270",
    "addr:street":"Mannenberg",
    "iso:country":"BE",
    "sg:address":"Mannenberg 4",
    "sg:city":"Scherpenheuvel-zichem",
    "sg:orig_category":"Mat\u00e9riel de T\u00e9l\u00e9communication",
    "sg:phone":"+32 13 77 61 45",
    "sg:postcode":"3270",
    "sg:province":"Vlaams-Brabant",
    "wof:name":"Pollet",
    "wof:placetype":"venue"
},
  "geometry": {"coordinates":[4.9593811035,50.9788703918],"type":"Point"}
}