{
  "type": "Feature",
  "properties": {
    "addr:full":"Markt 90 Deinze Oost-Vlaanderen 9800",
    "addr:housenumber":"90",
    "addr:postcode":"9800",
    "addr:street":"Markt",
    "iso:country":"BE",
    "sg:address":"Markt 90",
    "sg:city":"Deinze",
    "sg:orig_category":"Tijdelijke werkgelegenheid and uitzendkantoren",
    "sg:phone":"+32 9 381 58 00",
    "sg:postcode":"9800",
    "sg:province":"Oost-Vlaanderen",
    "wof:name":"Manpower",
    "wof:placetype":"venue"
},
  "geometry": {"coordinates":[3.5249629021,50.9859886169],"type":"Point"}
}