{
  "type": "Feature",
  "properties": {
    "addr:full":"5540 Hasti\u00c8re Namur 5540",
    "addr:postcode":"5540;5540",
    "iso:country":"BE",
    "sg:address":"5540",
    "sg:city":"Hasti\u00c8re",
    "sg:orig_category":"Pharmaciens",
    "sg:phone":"+32 900 10 500",
    "sg:postcode":"5540",
    "sg:province":"Namur",
    "wof:name":"Pharmacies De Garde",
    "wof:placetype":"venue"
},
  "geometry": {"coordinates":[4.8582201004,50.211769104],"type":"Point"}
}