{
  "type": "Feature",
  "properties": {
    "addr:full":"Baliestraat 28 Gent Oost-Vlaanderen 9000",
    "addr:housenumber":"28",
    "addr:postcode":"9000",
    "addr:street":"Baliestraat;Oost-Vlaanderen",
    "iso:country":"BE",
    "sg:address":"Baliestraat 28",
    "sg:city":"Gent",
    "sg:classifiers":[
        {
            "category":"Professional",
            "subcategory":"Lawyer & Legal Services",
            "type":"Services"
        }
    ],
    "sg:phone":"+32 9 221 20 15",
    "sg:postcode":"9000",
    "sg:province":"Oost-Vlaanderen",
    "wof:name":"Huybrechts Lies",
    "wof:placetype":"venue"
},
  "geometry": {"coordinates":[3.7159869671,51.0403785706],"type":"Point"}
}