{
  "type": "Feature",
  "properties": {
    "iso:country":"BE",
    "sg:address":"Koralenhoeve 9",
    "sg:city":"Wommelgem",
    "sg:classifiers":[
        {
            "category":"Building & Trades",
            "subcategory":"Electrical",
            "type":"Services"
        }
    ],
    "sg:phone":"+32 3 350 61 61",
    "sg:postcode":"2160",
    "sg:province":"Antwerpen",
    "sg:tags":[
        "industrial",
        "-",
        "electric",
        "contractor"
    ],
    "wof:name":"Imtech Automation",
    "wof:placetype":"venue"
},
  "geometry": {"coordinates":[4.5193810463,51.2105789185],"type":"Point"}
}