{
  "type": "Feature",
  "properties": {
    "iso:country":"BE",
    "sg:address":"Rue De Bomer\u00c9e 21",
    "sg:city":"Montigny-le-tilleul",
    "sg:orig_category":"Charpentes and couvertures",
    "sg:phone":"+32 71 51 64 57",
    "sg:postcode":"6110",
    "sg:province":"Hainaut",
    "wof:name":"Christian Dewez",
    "wof:placetype":"venue"
},
  "geometry": {"coordinates":[4.3803157806,50.3779449463],"type":"Point"}
}