{
  "type": "Feature",
  "properties": {
    "addr:full":"Prins Albertlaan 39 Izegem West-Vlaanderen 8870",
    "addr:housenumber":"39",
    "addr:postcode":"8870",
    "addr:street":"Prins Albertlaan",
    "iso:country":"BE",
    "sg:address":"Prins Albertlaan 39",
    "sg:city":"Izegem",
    "sg:orig_category":"Non-Classified Establishments",
    "sg:phone":"+32 51 30 03 70",
    "sg:postcode":"8870",
    "sg:province":"West-Vlaanderen",
    "wof:name":"Colpaert",
    "wof:placetype":"venue"
},
  "geometry": {"coordinates":[3.2036190033,50.9231872559],"type":"Point"}
}