{
  "type": "Feature",
  "properties": {
    "addr:full":"Rue De La Fourche 46-48 Bruxelles Bruxelles-Capitale 1000",
    "addr:postcode":"46-48;1000",
    "addr:street":"Rue De La Fourche",
    "iso:country":"BE",
    "sg:address":"Rue De La Fourche 46-48",
    "sg:city":"Bruxelles",
    "sg:orig_category":"Kapsalons",
    "sg:phone":"+32 2 219 63 87",
    "sg:postcode":"1000",
    "sg:province":"Bruxelles-Capitale",
    "wof:name":"Les Ciseaux D'or",
    "wof:placetype":"venue"
},
  "geometry": {"coordinates":[4.3535752296,50.8488883972],"type":"Point"}
}