{
  "type": "Feature",
  "properties": {
    "iso:country":"BE",
    "sg:address":"Markt 18",
    "sg:city":"Tessenderlo",
    "sg:orig_category":"Activit\u00e9s d\u00b4action sociale sans h\u00e9bergement",
    "sg:phone":"+32 13 66 15 51",
    "sg:postcode":"3980",
    "sg:province":"Limburg",
    "wof:name":"Medi Prevent",
    "wof:placetype":"venue"
},
  "geometry": {"coordinates":[5.0896601677,51.0673789978],"type":"Point"}
}