{
  "type": "Feature",
  "properties": {
    "iso:country":"BE",
    "sg:address":"Madestraat 82",
    "sg:city":"Herselt",
    "sg:orig_category":"Animations diverses",
    "sg:phone":"+32 475 91 18 01",
    "sg:postcode":"2230",
    "sg:province":"Antwerpen",
    "wof:name":"Scoebidoe Discobar",
    "wof:placetype":"venue"
},
  "geometry": {"coordinates":[4.835146904,51.015460968],"type":"Point"}
}