{
  "type": "Feature",
  "properties": {
    "iso:country":"BE",
    "sg:address":"Rue De Temploux 2",
    "sg:city":"Jemeppe-sur-sambre",
    "sg:classifiers":[
        {
            "category":"Arena",
            "subcategory":"Sports Club",
            "type":"Entertainment"
        }
    ],
    "sg:phone":"+32 71 78 69 69",
    "sg:postcode":"5190",
    "sg:province":"Namur",
    "sg:tags":[
        "de"
    ],
    "wof:name":"Spy T.c.",
    "wof:placetype":"venue"
},
  "geometry": {"coordinates":[4.7094211578,50.4818611145],"type":"Point"}
}