{
  "type": "Feature",
  "properties": {
    "iso:country":"BE",
    "sg:address":"Meerlaanstraat 24",
    "sg:city":"Oosterzele",
    "sg:orig_category":"Installation de menuiserie en bois and plastique",
    "sg:phone":"+32 9 362 27 40",
    "sg:postcode":"9860",
    "sg:province":"Oost-Vlaanderen",
    "wof:name":"Creyan",
    "wof:placetype":"venue"
},
  "geometry": {"coordinates":[3.7833640575,50.9188270569],"type":"Point"}
}