{
  "type": "Feature",
  "properties": {
    "iso:country":"BE",
    "sg:address":"Rue Des B\u00c9guines 16",
    "sg:city":"Profondeville",
    "sg:orig_category":"Loodgieterij, verwarming and sanitaire installaties",
    "sg:phone":"+32 81 41 26 01",
    "sg:postcode":"5170",
    "sg:province":"Namur",
    "wof:name":"J.c. Crohin",
    "wof:placetype":"venue"
},
  "geometry": {"coordinates":[4.8674049377,50.3786392212],"type":"Point"}
}