{
  "type": "Feature",
  "properties": {
    "addr:full":"Volksverheffingsstraat 83 Aalst Oost-Vlaanderen 9300",
    "addr:housenumber":"83",
    "addr:postcode":"9300",
    "addr:street":"Volksverheffingsstraat",
    "iso:country":"BE",
    "sg:address":"Volksverheffingsstraat 83",
    "sg:city":"Aalst",
    "sg:classifiers":[
        {
            "category":"Real Estate",
            "subcategory":"Architect",
            "type":"Services"
        }
    ],
    "sg:phone":"+32 53 78 15 43",
    "sg:postcode":"9300",
    "sg:province":"Oost-Vlaanderen",
    "wof:name":"Van Schuylenbergh B",
    "wof:placetype":"venue"
},
  "geometry": {"coordinates":[4.0245060921,50.9420280457],"type":"Point"}
}