{
  "type": "Feature",
  "properties": {
    "addr:full":"Gentsesteenweg 366 Molenbeek Bruxelles-Capitale 1080",
    "addr:housenumber":"366",
    "addr:postcode":"1080",
    "addr:street":"Gentsesteenweg",
    "iso:country":"BE",
    "sg:address":"Gentsesteenweg 366",
    "sg:city":"Molenbeek",
    "sg:orig_category":"Erotische Etablissementen Erotische- and Escortediensten",
    "sg:phone":"+32 476 85 07 00",
    "sg:postcode":"1080",
    "sg:province":"Bruxelles-Capitale",
    "wof:name":"Fem Dom",
    "wof:placetype":"venue"
},
  "geometry": {"coordinates":[4.3390049934,50.8550453186],"type":"Point"}
}