{
  "type": "Feature",
  "properties": {
    "addr:full":"Hoogstraat 33 Wichelen (schellebelle) Oost-Vlaanderen 9260",
    "addr:housenumber":"33",
    "addr:postcode":"9260",
    "addr:street":"Hoogstraat",
    "iso:country":"BE",
    "sg:address":"Hoogstraat 33",
    "sg:city":"Wichelen (schellebelle)",
    "sg:classifiers":[
        {
            "category":"Professional",
            "subcategory":"Testing Lab",
            "type":"Services"
        }
    ],
    "sg:phone":"+32 9 369 34 46",
    "sg:postcode":"9260",
    "sg:province":"Oost-Vlaanderen",
    "sg:tags":[
        "chemist"
    ],
    "wof:name":"Bontinck H",
    "wof:placetype":"venue"
},
  "geometry": {"coordinates":[3.9311170578,51.0117607117],"type":"Point"}
}