{
  "type": "Feature",
  "properties": {
    "addr:full":"Jagersdreef 100 Kapellen (mariaburg) Antwerpen 2950",
    "addr:housenumber":"100",
    "addr:postcode":"2950",
    "addr:street":"Jagersdreef",
    "iso:country":"BE",
    "sg:address":"Jagersdreef 100",
    "sg:city":"Kapellen (mariaburg)",
    "sg:classifiers":[
        {
            "category":"Health Services",
            "subcategory":"Hospital",
            "type":"Services"
        }
    ],
    "sg:phone":"+32 3 664 34 23",
    "sg:postcode":"2950",
    "sg:province":"Antwerpen",
    "wof:name":"Psychiatrisch Ziekenhuis Bethani\u00ebnhuis Nieuw Medister/campus Kapellen",
    "wof:placetype":"venue"
},
  "geometry": {"coordinates":[4.4556250572,51.3024673462],"type":"Point"}
}