{
  "type": "Feature",
  "properties": {
    "iso:country":"BE",
    "sg:address":"Rue Saint-donat 18",
    "sg:city":"Leglise",
    "sg:orig_category":"Eleveurs de bovins",
    "sg:phone":"+32 63 43 34 92",
    "sg:postcode":"6860",
    "sg:province":"Luxembourg",
    "wof:name":"Francois Parisse",
    "wof:placetype":"venue"
},
  "geometry": {"coordinates":[5.5567798615,49.7959365845],"type":"Point"}
}