{
  "type": "Feature",
  "properties": {
    "iso:country":"BE",
    "sg:address":"Industrieweg 18",
    "sg:city":"Malle (oostmalle)",
    "sg:classifiers":[
        {
            "category":"Home & Garden",
            "subcategory":"Building Materials",
            "type":"Retail Goods"
        }
    ],
    "sg:phone":"+32 3 312 37 27",
    "sg:postcode":"2390",
    "sg:province":"Antwerpen",
    "sg:tags":[
        "window"
    ],
    "wof:name":"Ka Construct Nv",
    "wof:placetype":"venue"
},
  "geometry": {"coordinates":[4.7109189034,51.2957000732],"type":"Point"}
}