{
  "type": "Feature",
  "properties": {
    "iso:country":"BE",
    "sg:address":"Rue Montagne Aux Herbes Potag\u00e8res",
    "sg:city":"Bruxelles",
    "sg:classifiers":[
        {
            "category":"Bars & Pubs",
            "type":"Food & Drink"
        }
    ],
    "sg:phone":"+32 2 512 86 64",
    "sg:postcode":"1000",
    "sg:province":"Bruxelles-Capitale",
    "sg:tags":[
        "tavern"
    ],
    "wof:name":"Mort Subite (a La)",
    "wof:placetype":"venue"
},
  "geometry": {"coordinates":[4.3568539619,50.8492698669],"type":"Point"}
}