{
  "type": "Feature",
  "properties": {
    "addr:full":"Place R\u00c9g. Au Long Col 1 Mons Hainaut 7000",
    "addr:housenumber":"1",
    "addr:postcode":"7000",
    "addr:street":"Place Re\u0301G Au Long Col;Hainaut",
    "iso:country":"BE",
    "sg:address":"Place R\u00c9g. Au Long Col 1",
    "sg:city":"Mons",
    "sg:orig_category":"Pi\u00e8ces and accessoires de v\u00e9hicules automobiles D\u00e9taillants en pi\u00e8ces and accessoires de voitures",
    "sg:phone":"+32 65 31 25 70",
    "sg:postcode":"7000",
    "sg:province":"Hainaut",
    "wof:name":"Apea",
    "wof:placetype":"venue"
},
  "geometry": {"coordinates":[3.9563100338,50.4607009888],"type":"Point"}
}