{
  "type": "Feature",
  "properties": {
    "iso:country":"BE",
    "sg:address":"Rue Du Hautbois 2ba",
    "sg:city":"Le Roeulx",
    "sg:orig_category":"Rundveehouders Varkenskwekers",
    "sg:phone":"+32 64 66 33 53",
    "sg:postcode":"7070",
    "sg:province":"Hainaut",
    "wof:name":"Louis J.p.+louis Th.",
    "wof:placetype":"venue"
},
  "geometry": {"coordinates":[4.1086750031,50.5015830994],"type":"Point"}
}