{
  "type": "Feature",
  "properties": {
    "iso:country":"BE",
    "sg:address":"Rue De L'eglise 25",
    "sg:city":"Seraing (boncelles)",
    "sg:classifiers":[
        {
            "category":"Education",
            "subcategory":"School",
            "type":"Public Place"
        }
    ],
    "sg:phone":"+32 4 385 04 52",
    "sg:postcode":"4100",
    "sg:province":"Li\u00e8ge",
    "sg:tags":[
        "primary"
    ],
    "wof:name":"Ecole Communale Fondamentale De Boncelles",
    "wof:placetype":"venue"
},
  "geometry": {"coordinates":[5.5354828835,50.5741043091],"type":"Point"}
}