{
  "type": "Feature",
  "properties": {
    "iso:country":"BE",
    "sg:address":"Poststraat 8",
    "sg:city":"Ham",
    "sg:orig_category":"Postkantoren Verzekeringsmakelaars and experts",
    "sg:phone":"+32 13 66 12 68",
    "sg:postcode":"3945",
    "sg:province":"Limburg",
    "wof:name":"De Post",
    "wof:placetype":"venue"
},
  "geometry": {"coordinates":[5.1776199341,51.1046104431],"type":"Point"}
}