{
  "type": "Feature",
  "properties": {
    "iso:country":"BE",
    "sg:address":"Kloosterstraat 27",
    "sg:city":"Zele",
    "sg:classifiers":[
        {
            "category":"Education",
            "subcategory":"School",
            "type":"Public Place"
        }
    ],
    "sg:phone":"+32 52 44 48 41",
    "sg:postcode":"9240",
    "sg:province":"Oost-Vlaanderen",
    "sg:tags":[
        "secondary"
    ],
    "wof:name":"Pius X-instituut",
    "wof:placetype":"venue"
},
  "geometry": {"coordinates":[4.0413899422,51.0693740845],"type":"Point"}
}