{
  "type": "Feature",
  "properties": {
    "iso:country":"BE",
    "sg:address":"Bruul 35",
    "sg:city":"Mechelen",
    "sg:orig_category":"Microsoft. Production de films, t\u00e9l\u00e9films and vid\u00e9os. Disquaires. Ordinateurs and \u00e9quipement informa",
    "sg:phone":"+32 15 21 03 00",
    "sg:postcode":"2800",
    "sg:province":"Antwerpen",
    "wof:name":"Hvh Inno Mechelen",
    "wof:placetype":"venue"
},
  "geometry": {"coordinates":[4.4812040329,51.0264282227],"type":"Point"}
}