{
  "type": "Feature",
  "properties": {
    "iso:country":"BE",
    "sg:address":"Solvynsstraat 5",
    "sg:city":"Antwerpen",
    "sg:orig_category":"Advocaten and juridische adviseurs",
    "sg:phone":"+32 3 248 26 19",
    "sg:postcode":"2018",
    "sg:province":"Antwerpen",
    "wof:name":"Frank Tim\u00c9",
    "wof:placetype":"venue"
},
  "geometry": {"coordinates":[4.4024329185,51.2074317932],"type":"Point"}
}