{
  "type": "Feature",
  "properties": {
    "iso:country":"BE",
    "sg:address":"Keizer Karellaan 374",
    "sg:city":"Ganshoren",
    "sg:orig_category":"Douanekantoren Verzekeringsmakelaars and experts Vrachtvervoer",
    "sg:phone":"+32 2 469 13 13",
    "sg:postcode":"1083",
    "sg:province":"Bruxelles-Capitale",
    "wof:name":"E.p.y. Investments",
    "wof:placetype":"venue"
},
  "geometry": {"coordinates":[4.2998361588,50.8719177246],"type":"Point"}
}