{
  "type": "Feature",
  "properties": {
    "addr:full":"Kapelle Straat 70 Deinze Oost-Vlaanderen 9800",
    "addr:housenumber":"70",
    "addr:postcode":"9800",
    "addr:street":"Kapelle Straat",
    "iso:country":"BE",
    "sg:address":"Kapelle Straat 70",
    "sg:city":"Deinze",
    "sg:classifiers":[
        {
            "category":"Wholesale",
            "subcategory":"Machinery & Supplies",
            "type":"Manufacturing & Wholesale Goods"
        }
    ],
    "sg:phone":"+32 9 387 92 11",
    "sg:postcode":"9800",
    "sg:province":"Oost-Vlaanderen",
    "sg:tags":[
        "-",
        "machine",
        "equipment",
        "engineering",
        "animal",
        "mechanical",
        "breeding",
        "agriculture"
    ],
    "wof:name":"Versele Laga Nv",
    "wof:placetype":"venue"
},
  "geometry": {"coordinates":[3.5479300022,50.9813995361],"type":"Point"}
}