{
  "type": "Feature",
  "properties": {
    "addr:full":"Rue C. Jaumotte 16 Wavre Brabant Wallon 1300",
    "addr:housenumber":"16;1300",
    "addr:street":"Rue C. Jaumotte",
    "iso:country":"BE",
    "sg:address":"Rue C. Jaumotte 16",
    "sg:city":"Wavre",
    "sg:orig_category":"Produits chimiques Gr",
    "sg:phone":"+32 10 41 63 17",
    "sg:postcode":"1300",
    "sg:province":"Brabant Wallon",
    "wof:name":"Prodilo",
    "wof:placetype":"venue"
},
  "geometry": {"coordinates":[4.6116552353,50.7134132385],"type":"Point"}
}