{
  "type": "Feature",
  "properties": {
    "iso:country":"BE",
    "sg:address":"Rue De Tirlemont 16",
    "sg:city":"Lincent (racour)",
    "sg:classifiers":[
        {
            "category":"Health Services",
            "subcategory":"Health Practitioner",
            "type":"Services"
        }
    ],
    "sg:phone":"+32 19 65 64 62",
    "sg:postcode":"4287",
    "sg:province":"Li\u00e8ge",
    "sg:tags":[
        "physiotherapist"
    ],
    "wof:name":"Cobben Bernadette",
    "wof:placetype":"venue"
},
  "geometry": {"coordinates":[5.0258550644,50.7400856018],"type":"Point"}
}