{
  "type": "Feature",
  "properties": {
    "addr:full":"Beukenlei 52 Brecht (sint-job-in-'t Goor) Antwerpen 2960",
    "addr:housenumber":"52",
    "addr:postcode":"2960",
    "addr:street":"Beukenlei;' T Goor",
    "iso:country":"BE",
    "sg:address":"Beukenlei 52",
    "sg:city":"Brecht (sint-job-in-'t Goor)",
    "sg:classifiers":[
        {
            "category":"Health Services",
            "subcategory":"Dentist",
            "type":"Services"
        }
    ],
    "sg:phone":"+32 3 636 41 41",
    "sg:postcode":"2960",
    "sg:province":"Antwerpen",
    "wof:name":"Wuyts Patrick",
    "wof:placetype":"venue"
},
  "geometry": {"coordinates":[4.5639028549,51.3064193726],"type":"Point"}
}