{
  "type": "Feature",
  "properties": {
    "iso:country":"BE",
    "sg:address":"Sint-jorisstraat 128",
    "sg:city":"Beernem",
    "sg:orig_category":"Woningbouw",
    "sg:phone":"+32 50 78 80 43",
    "sg:postcode":"8730",
    "sg:province":"West-Vlaanderen",
    "wof:name":"Romain Croene",
    "wof:placetype":"venue"
},
  "geometry": {"coordinates":[3.3475100994,51.126121521],"type":"Point"}
}