{
  "type": "Feature",
  "properties": {
    "addr:full":"Boulevard Jules Graindor 7 Anderlecht Bruxelles-Capitale 1070",
    "addr:housenumber":"7",
    "addr:postcode":"1070",
    "addr:street":"Boulevard Jules Graindor",
    "iso:country":"BE",
    "sg:address":"Boulevard Jules Graindor 7",
    "sg:city":"Anderlecht",
    "sg:orig_category":"M\u00e9decins and sp\u00e9cialistes",
    "sg:phone":"+32 2 523 85 02",
    "sg:postcode":"1070",
    "sg:province":"Bruxelles-Capitale",
    "wof:name":"Jean-claude Pector",
    "wof:placetype":"venue"
},
  "geometry": {"coordinates":[4.3144011497,50.843837738],"type":"Point"}
}