{
  "type": "Feature",
  "properties": {
    "addr:full":"Kardinaal Cardijnlaan 23 Bonheiden Antwerpen 2820",
    "addr:housenumber":"23",
    "addr:postcode":"2820",
    "addr:street":"Kardinaal Cardijnlaan",
    "iso:country":"BE",
    "sg:address":"Kardinaal Cardijnlaan 23",
    "sg:city":"Bonheiden",
    "sg:orig_category":"Leisure articles",
    "sg:phone":"+32 15 51 78 14",
    "sg:postcode":"2820",
    "sg:province":"Antwerpen",
    "wof:name":"Argante",
    "wof:placetype":"venue"
},
  "geometry": {"coordinates":[4.5476169586,51.0272521973],"type":"Point"}
}