{
  "type": "Feature",
  "properties": {
    "iso:country":"BE",
    "sg:address":"Karreweg 139a",
    "sg:city":"Kruishoutem",
    "sg:classifiers":[
        {
            "category":"Utilities",
            "subcategory":"Electric",
            "type":"Services"
        }
    ],
    "sg:phone":"+32 9 388 80 85",
    "sg:postcode":"9770",
    "sg:province":"Oost-Vlaanderen",
    "sg:tags":[
        "generator"
    ],
    "wof:name":"Locquet",
    "wof:placetype":"venue"
},
  "geometry": {"coordinates":[3.4890658855,50.918170929],"type":"Point"}
}