{
  "type": "Feature",
  "properties": {
    "iso:country":"BE",
    "sg:address":"Rue Thier Du Ry 34",
    "sg:city":"Bl\u00c9gny",
    "sg:classifiers":[
        {
            "category":"Personal",
            "subcategory":"Beauty Salon",
            "type":"Services"
        }
    ],
    "sg:phone":"+32 4 387 84 33",
    "sg:postcode":"4671",
    "sg:province":"Li\u00e8ge",
    "sg:tags":[
        "de",
        "coiffure"
    ],
    "wof:name":"Coiffure Actuelle",
    "wof:placetype":"venue"
},
  "geometry": {"coordinates":[5.6975131035,50.6681518555],"type":"Point"}
}