{
  "type": "Feature",
  "properties": {
    "addr:full":"Rue Des Brebis 23 Watermaal-bosvoorde/watermael-boitsfort Bruxelles-Capitale 1170",
    "addr:housenumber":"23",
    "addr:postcode":"1170",
    "addr:street":"Rue Des Brebis",
    "iso:country":"BE",
    "sg:address":"Rue Des Brebis 23",
    "sg:city":"Watermaal-bosvoorde/watermael-boitsfort",
    "sg:orig_category":"Installation de menuiserie en bois and plastique",
    "sg:phone":"+32 2 672 65 90",
    "sg:postcode":"1170",
    "sg:province":"Bruxelles-Capitale",
    "wof:name":"Rene Stie",
    "wof:placetype":"venue"
},
  "geometry": {"coordinates":[4.3939609528,50.812335968],"type":"Point"}
}