{
  "type": "Feature",
  "properties": {
    "addr:full":"Avenue Francisco Ferrer 20b22 Herstal Li\u00e8ge 4040",
    "addr:housenumber":"20b22",
    "addr:postcode":"4040",
    "addr:street":"Avenue Francisco Ferrer",
    "iso:country":"BE",
    "sg:address":"Avenue Francisco Ferrer 20b22",
    "sg:city":"Herstal",
    "sg:orig_category":"Mat\u00e9riaux de construction Rev\u00eatements pour sols and murs. Peinture",
    "sg:phone":"+32 4 264 33 49",
    "sg:postcode":"4040",
    "sg:province":"Li\u00e8ge",
    "wof:name":"Marbrerie Mathys",
    "wof:placetype":"venue"
},
  "geometry": {"coordinates":[5.6283521652,50.6716194153],"type":"Point"}
}