{
  "type": "Feature",
  "properties": {
    "iso:country":"BE",
    "sg:address":"Chauss\u00c9e De Namur 95",
    "sg:city":"Nivelles",
    "sg:orig_category":"Meubelzaken, woning- and keukeninrichting",
    "sg:phone":"+32 67 84 33 41",
    "sg:postcode":"1400",
    "sg:province":"Brabant Wallon",
    "wof:name":"Meubles Decorex",
    "wof:placetype":"venue"
},
  "geometry": {"coordinates":[4.3656802177,50.5953826904],"type":"Point"}
}