{
  "type": "Feature",
  "properties": {
    "addr:full":"Magermerriestraat 1ba Roeselare West-Vlaanderen 8800",
    "addr:housenumber":"1ba",
    "addr:postcode":"8800",
    "addr:street":"Magermerriestraat",
    "iso:country":"BE",
    "sg:address":"Magermerriestraat 1ba",
    "sg:city":"Roeselare",
    "sg:orig_category":"Producteurs de l\u00e9gumes",
    "sg:phone":"+32 51 77 86 31",
    "sg:postcode":"8800",
    "sg:province":"West-Vlaanderen",
    "wof:name":"Donald Leerg",
    "wof:placetype":"venue"
},
  "geometry": {"coordinates":[3.0714859962,50.9236488342],"type":"Point"}
}