{
  "type": "Feature",
  "properties": {
    "addr:full":"Aarschotsesteenweg 433b1 Leuven Vlaams-Brabant 3012",
    "addr:housenumber":"433b1",
    "addr:postcode":"3012",
    "addr:street":"Aarschotsesteenweg",
    "iso:country":"BE",
    "sg:address":"Aarschotsesteenweg 433b1",
    "sg:city":"Leuven",
    "sg:orig_category":"Traitements param\u00e9dicaux",
    "sg:phone":"+32 89 38 04 18",
    "sg:postcode":"3012",
    "sg:province":"Vlaams-Brabant",
    "wof:name":"Hauwaerts Orthopedie",
    "wof:placetype":"venue"
},
  "geometry": {"coordinates":[4.7212100029,50.9242591858],"type":"Point"}
}