{
  "type": "Feature",
  "properties": {
    "addr:full":"Duisburgsesteenweg 85b Overijse Vlaams-Brabant 3090",
    "addr:housenumber":"85b",
    "addr:postcode":"3090",
    "addr:street":"Duisburgsesteenweg",
    "iso:country":"BE",
    "sg:address":"Duisburgsesteenweg 85b",
    "sg:city":"Overijse",
    "sg:classifiers":[
        {
            "category":"Health Services",
            "subcategory":"Doctor",
            "type":"Services"
        }
    ],
    "sg:phone":"+32 2 687 68 00",
    "sg:postcode":"3090",
    "sg:province":"Vlaams-Brabant",
    "sg:tags":[
        "medicinephysicians",
        "surgeon"
    ],
    "wof:name":"Charlier Edmond",
    "wof:placetype":"venue"
},
  "geometry": {"coordinates":[4.5402998924,50.789730072],"type":"Point"}
}