{
  "type": "Feature",
  "properties": {
    "addr:full":"Botsewegel 2 Oosterzele Oost-Vlaanderen 9860",
    "addr:housenumber":"2",
    "addr:postcode":"9860",
    "addr:street":"Botsewegel;Oost-Vlaanderen",
    "iso:country":"BE",
    "sg:address":"Botsewegel 2",
    "sg:city":"Oosterzele",
    "sg:classifiers":[
        {
            "category":"Personal",
            "subcategory":"Beauty Salon",
            "type":"Services"
        }
    ],
    "sg:phone":"+32 9 362 68 77",
    "sg:postcode":"9860",
    "sg:province":"Oost-Vlaanderen",
    "sg:tags":[
        "de",
        "coiffure"
    ],
    "wof:name":"Coiffure Christiane",
    "wof:placetype":"venue"
},
  "geometry": {"coordinates":[3.7518100739,50.9299163818],"type":"Point"}
}