{
  "type": "Feature",
  "properties": {
    "iso:country":"BE",
    "sg:address":"Sint-omaarsstraat 5",
    "sg:city":"Alveringem",
    "sg:orig_category":"Varkenskwekers",
    "sg:phone":"+32 57 30 05 75",
    "sg:postcode":"8691",
    "sg:province":"West-Vlaanderen",
    "wof:name":"Denis Vandromme",
    "wof:placetype":"venue"
},
  "geometry": {"coordinates":[2.6017398834,50.9172668457],"type":"Point"}
}