{
  "type": "Feature",
  "properties": {
    "iso:country":"BE",
    "sg:address":"Pacificatiestraat 9b1",
    "sg:city":"Antwerpen",
    "sg:orig_category":"Software ontwikkeling and ontwerp",
    "sg:phone":"+32 3 238 06 19",
    "sg:postcode":"2000",
    "sg:province":"Antwerpen",
    "wof:name":"Alveko",
    "wof:placetype":"venue"
},
  "geometry": {"coordinates":[4.3877577782,51.206363678],"type":"Point"}
}