{
  "type": "Feature",
  "properties": {
    "iso:country":"BE",
    "sg:address":"Rue Po\u00c8te Folie 53",
    "sg:city":"Fleurus",
    "sg:orig_category":"M\u00e9decins and sp\u00e9cialistes",
    "sg:phone":"+32 71 81 64 31",
    "sg:postcode":"6220",
    "sg:province":"Hainaut",
    "wof:name":"Bernard Bouffioux",
    "wof:placetype":"venue"
},
  "geometry": {"coordinates":[4.5462827682,50.4812088013],"type":"Point"}
}