{
  "type": "Feature",
  "properties": {
    "addr:full":"Groenplaats 33 Antwerpen Antwerpen 2000",
    "addr:housenumber":"33",
    "addr:postcode":"2000",
    "addr:street":"Groenplaats",
    "iso:country":"BE",
    "sg:address":"Groenplaats 33",
    "sg:city":"Antwerpen",
    "sg:classifiers":[
        {
            "category":"Cafe",
            "type":"Food & Drink"
        }
    ],
    "sg:phone":"+32 3 233 10 45",
    "sg:postcode":"2000",
    "sg:province":"Antwerpen",
    "sg:tags":[
        "caf\u00e9s"
    ],
    "wof:name":"Karbonkel",
    "wof:placetype":"venue"
},
  "geometry": {"coordinates":[4.4016041756,51.218334198],"type":"Point"}
}