{
  "type": "Feature",
  "properties": {
    "addr:full":"Rue Van Soust 109 Bruxelles Bruxelles-Capitale 1070",
    "addr:housenumber":"109",
    "addr:postcode":"1070",
    "addr:street":"Rue Van Soust",
    "iso:country":"BE",
    "sg:address":"Rue Van Soust 109",
    "sg:city":"Bruxelles",
    "sg:classifiers":[
        {
            "category":"Manufacturing",
            "subcategory":"Tools & Machinery",
            "type":"Manufacturing & Wholesale Goods"
        }
    ],
    "sg:phone":"+32 2 521 61 06",
    "sg:postcode":"1070",
    "sg:province":"Bruxelles-Capitale",
    "sg:tags":[
        "machine",
        "allround",
        "turning",
        "milling",
        "drilling"
    ],
    "wof:name":"Bamac Machining Systems S.a.",
    "wof:placetype":"venue"
},
  "geometry": {"coordinates":[4.309469223,50.8469696045],"type":"Point"}
}