{
  "type": "Feature",
  "properties": {
    "addr:full":"Rogierlaan 207 Schaarbeek/schaerbeek Bruxelles-Capitale 1030",
    "addr:housenumber":"207",
    "addr:postcode":"1030",
    "addr:street":"Rogierlaan",
    "iso:country":"BE",
    "sg:address":"Rogierlaan 207",
    "sg:city":"Schaarbeek/schaerbeek",
    "sg:orig_category":"Binnenhuisarchitecten",
    "sg:phone":"+32 2 242 81 42",
    "sg:postcode":"1030",
    "sg:province":"Bruxelles-Capitale",
    "wof:name":"Bureau Du Four Jan",
    "wof:placetype":"venue"
},
  "geometry": {"coordinates":[4.3826818466,50.8581809998],"type":"Point"}
}