{
  "type": "Feature",
  "properties": {
    "addr:full":"Quai Paul Van Hoegaerden 2 Li\u00e8ge 1 Li\u00e8ge 4000",
    "addr:housenumber":"2;1",
    "addr:postcode":"4000",
    "addr:street":"Quai Paul;Hoegaerden",
    "iso:country":"BE",
    "sg:address":"Quai Paul Van Hoegaerden 2",
    "sg:city":"Li\u00e8ge 1",
    "sg:classifiers":[
        {
            "category":"Health Services",
            "subcategory":"Doctor",
            "type":"Services"
        }
    ],
    "sg:phone":"+32 4 222 31 38",
    "sg:postcode":"4000",
    "sg:province":"Li\u00e8ge",
    "sg:tags":[
        "medicinephysicians",
        "surgeon"
    ],
    "wof:name":"Dezfoulian Bita",
    "wof:placetype":"venue"
},
  "geometry": {"coordinates":[5.5766267776,50.6393089294],"type":"Point"}
}