{
  "type": "Feature",
  "properties": {
    "addr:full":"Oud-strijderslaan 0 Herentals Antwerpen 2200",
    "addr:housenumber":"0",
    "addr:postcode":"2200",
    "addr:street":"Oud-Strijderslaan",
    "iso:country":"BE",
    "sg:address":"Oud-strijderslaan 0",
    "sg:city":"Herentals",
    "sg:orig_category":"Baby- and kinderkleding Dameskledingzaken Herenkledingzaken",
    "sg:phone":"+32 14 21 48 18",
    "sg:postcode":"2200",
    "sg:province":"Antwerpen",
    "wof:name":"E5 Mode",
    "wof:placetype":"venue"
},
  "geometry": {"coordinates":[4.841791153,51.1868858337],"type":"Point"}
}