{
  "type": "Feature",
  "properties": {
    "iso:country":"BE",
    "sg:address":"Kleistraat 5",
    "sg:city":"Oosterzele",
    "sg:orig_category":"Non-Classified Establishments",
    "sg:phone":"+32 9 362 52 70",
    "sg:postcode":"9860",
    "sg:province":"Oost-Vlaanderen",
    "wof:name":"Salami De Neve Bvba",
    "wof:placetype":"venue"
},
  "geometry": {"coordinates":[3.8335030079,50.9649238586],"type":"Point"}
}