{
  "type": "Feature",
  "properties": {
    "iso:country":"BE",
    "sg:address":"Sint-annastraat 22",
    "sg:city":"Kortrijk",
    "sg:orig_category":"Diverse opleidingen and onderwijs",
    "sg:phone":"+32 56 20 47 75",
    "sg:postcode":"8510",
    "sg:province":"West-Vlaanderen",
    "wof:name":"Koenraad Denolf",
    "wof:placetype":"venue"
},
  "geometry": {"coordinates":[3.249104023,50.8024711609],"type":"Point"}
}