{
  "type": "Feature",
  "properties": {
    "addr:full":"Houthulstseweg 83 Langemark-poelkapelle (langemark) West-Vlaanderen 8920",
    "addr:housenumber":"83",
    "addr:postcode":"8920",
    "addr:street":"Houthulstseweg",
    "iso:country":"BE",
    "sg:address":"Houthulstseweg 83",
    "sg:city":"Langemark-poelkapelle (langemark)",
    "sg:classifiers":[
        {
            "category":"Social Services",
            "subcategory":"Child Care",
            "type":"Services"
        }
    ],
    "sg:phone":"+32 57 48 65 01",
    "sg:postcode":"8920",
    "sg:province":"West-Vlaanderen",
    "sg:tags":[
        "baby",
        "nursery",
        "day",
        "sitting"
    ],
    "wof:name":"Petoetje",
    "wof:placetype":"venue"
},
  "geometry": {"coordinates":[2.9413208961,50.9361686707],"type":"Point"}
}