{
  "type": "Feature",
  "properties": {
    "addr:full":"Kampenstraat 61 Herzele Oost-Vlaanderen 9552",
    "addr:housenumber":"61",
    "addr:postcode":"9552",
    "addr:street":"Kampenstraat;Oost-Vlaanderen",
    "iso:country":"BE",
    "sg:address":"Kampenstraat 61",
    "sg:city":"Herzele",
    "sg:orig_category":"Herstelling and restauratie van meubelen",
    "sg:phone":"+32 53 62 48 39",
    "sg:postcode":"9552",
    "sg:province":"Oost-Vlaanderen",
    "wof:name":"Norbert Verstuyft",
    "wof:placetype":"venue"
},
  "geometry": {"coordinates":[3.8921980858,50.9126358032],"type":"Point"}
}