{
  "type": "Feature",
  "properties": {
    "iso:country":"BE",
    "sg:address":"Sint-magdalenastraat 44",
    "sg:city":"Herentals",
    "sg:classifiers":[
        {
            "category":"Professional",
            "subcategory":"Management & Consulting",
            "type":"Services"
        }
    ],
    "sg:phone":"+32 476 26 45 16",
    "sg:postcode":"2200",
    "sg:province":"Antwerpen",
    "sg:tags":[
        "consultant"
    ],
    "wof:name":"Hoshin Bvba",
    "wof:placetype":"venue"
},
  "geometry": {"coordinates":[4.8299350739,51.1784896851],"type":"Point"}
}