{
  "type": "Feature",
  "properties": {
    "iso:country":"BE",
    "sg:address":"Waterloosesteenweg 1250",
    "sg:city":"Ukkel/uccle",
    "sg:orig_category":"Herstellingen and onderhoud van auto's Voertuigen",
    "sg:phone":"+32 2 375 44 72",
    "sg:postcode":"1180",
    "sg:province":"Bruxelles-Capitale",
    "wof:name":"Group Motors",
    "wof:placetype":"venue"
},
  "geometry": {"coordinates":[4.374174118,50.7931785583],"type":"Point"}
}