{
  "type": "Feature",
  "properties": {
    "addr:full":"Putse Baan 157 Antwerpen Antwerpen 2040",
    "addr:housenumber":"157",
    "addr:postcode":"2040",
    "addr:street":"Putse Baan",
    "iso:country":"BE",
    "sg:address":"Putse Baan 157",
    "sg:city":"Antwerpen",
    "sg:classifiers":[
        {
            "category":"Personal",
            "subcategory":"Beauty Salon",
            "type":"Services"
        }
    ],
    "sg:phone":"+32 3 568 81 06",
    "sg:postcode":"2040",
    "sg:province":"Antwerpen",
    "sg:tags":[
        "lady",
        "-",
        "hairdressing"
    ],
    "wof:name":"Haartooi Lombardo",
    "wof:placetype":"venue"
},
  "geometry": {"coordinates":[4.3311300278,51.3580284119],"type":"Point"}
}