{
  "type": "Feature",
  "properties": {
    "addr:full":"Rue Du Canal 1 Peruwelz Hainaut 7600",
    "addr:housenumber":"1",
    "addr:postcode":"7600",
    "addr:street":"Rue Du Canal;Hainaut",
    "iso:country":"BE",
    "sg:address":"Rue Du Canal 1",
    "sg:city":"Peruwelz",
    "sg:orig_category":"Quincailleries. Mat\u00e9riaux de construction Bois Gr. B\u00e9ton pr\u00eat \u00e0 l'emploi Fab",
    "sg:phone":"+32 69 77 31 19",
    "sg:postcode":"7600",
    "sg:province":"Hainaut",
    "wof:name":"Roucourt Beton",
    "wof:placetype":"venue"
},
  "geometry": {"coordinates":[3.5908699036,50.5080947876],"type":"Point"}
}