{
  "type": "Feature",
  "properties": {
    "iso:country":"BE",
    "sg:address":"Avenue De Bouillon 62",
    "sg:city":"Libramont-chevigny",
    "sg:orig_category":"Entretien and r\u00e9parations de voitures. Stations-service and carburants. V\u00e9hicules automobiles",
    "sg:phone":"+32 61 22 32 55",
    "sg:postcode":"6800",
    "sg:province":"Luxembourg",
    "wof:name":"Carrosserie Pierson",
    "wof:placetype":"venue"
},
  "geometry": {"coordinates":[5.364440918,49.915802002],"type":"Point"}
}