{
  "type": "Feature",
  "properties": {
    "addr:full":"Rue G\u00c9n\u00c9ral-leman 3 Nivelles Brabant Wallon 1400",
    "addr:housenumber":"3",
    "addr:postcode":"1400",
    "addr:street":"Rue Ge\u0301Ne\u0301Ral-Leman",
    "iso:country":"BE",
    "sg:address":"Rue G\u00c9n\u00c9ral-leman 3",
    "sg:city":"Nivelles",
    "sg:orig_category":"Architecten",
    "sg:phone":"+32 67 84 18 82",
    "sg:postcode":"1400",
    "sg:province":"Brabant Wallon",
    "wof:name":"Muriel Le Clercq",
    "wof:placetype":"venue"
},
  "geometry": {"coordinates":[4.3310008049,50.5997428894],"type":"Point"}
}