{
  "type": "Feature",
  "properties": {
    "addr:full":"Eekhoutdriesstraat 67 Gent (oostakker) Oost-Vlaanderen 9041",
    "addr:housenumber":"67",
    "addr:postcode":"9041",
    "addr:street":"Eekhoutdriesstraat",
    "iso:country":"BE",
    "sg:address":"Eekhoutdriesstraat 67",
    "sg:city":"Gent (oostakker)",
    "sg:classifiers":[
        {
            "category":"Professional",
            "subcategory":"Printing & Photocopies",
            "type":"Services"
        }
    ],
    "sg:phone":"+32 9 251 05 75",
    "sg:postcode":"9041",
    "sg:province":"Oost-Vlaanderen",
    "sg:tags":[
        "digital"
    ],
    "wof:name":"Geers Offset Nv",
    "wof:placetype":"venue"
},
  "geometry": {"coordinates":[3.7622458935,51.1050186157],"type":"Point"}
}