{
  "type": "Feature",
  "properties": {
    "iso:country":"BE",
    "sg:address":"Dokter Haekstraat 64",
    "sg:city":"Dendermonde (grembergen)",
    "sg:classifiers":[
        {
            "category":"Professional",
            "subcategory":"Testing Lab",
            "type":"Services"
        }
    ],
    "sg:phone":"+32 52 21 14 19",
    "sg:postcode":"9200",
    "sg:province":"Oost-Vlaanderen",
    "sg:tags":[
        "chemist"
    ],
    "wof:name":"Goethals-debrabandere Bvba",
    "wof:placetype":"venue"
},
  "geometry": {"coordinates":[4.1073989868,51.0506782532],"type":"Point"}
}