{
  "type": "Feature",
  "properties": {
    "addr:full":"Rue De La Croix Rouge 104 Tinlot Li\u00e8ge 4557",
    "addr:housenumber":"104",
    "addr:postcode":"4557",
    "addr:street":"Rue De La Croix Rouge",
    "iso:country":"BE",
    "sg:address":"Rue De La Croix Rouge 104",
    "sg:city":"Tinlot",
    "sg:orig_category":"Elektrische installaties voor woningen Loodgieterij, verwarming and sanitaire installaties",
    "sg:phone":"+32 85 51 28 30",
    "sg:postcode":"4557",
    "sg:province":"Li\u00e8ge",
    "wof:name":"Devillers Jean-marc",
    "wof:placetype":"venue"
},
  "geometry": {"coordinates":[5.4152851105,50.4851608276],"type":"Point"}
}