{
  "type": "Feature",
  "properties": {
    "addr:full":"Oude Veldstraat 126 Lochristi (zaffelare) Oost-Vlaanderen 9080",
    "addr:housenumber":"126",
    "addr:postcode":"9080",
    "addr:street":"Oude Veldstraat",
    "iso:country":"BE",
    "sg:address":"Oude Veldstraat 126",
    "sg:city":"Lochristi (zaffelare)",
    "sg:classifiers":[
        {
            "category":"Building & Trades",
            "subcategory":"Landscaping Services",
            "type":"Services"
        }
    ],
    "sg:phone":"+32 9 355 39 94",
    "sg:postcode":"9080",
    "sg:province":"Oost-Vlaanderen",
    "sg:tags":[
        "gardening",
        "garden",
        "maintenance"
    ],
    "wof:name":"Gieselaere C",
    "wof:placetype":"venue"
},
  "geometry": {"coordinates":[3.8602399826,51.1202507019],"type":"Point"}
}