{
  "type": "Feature",
  "properties": {
    "addr:full":"Rue Des Augustins 3 Enghien Hainaut 7850",
    "addr:housenumber":"3",
    "addr:postcode":"7850",
    "addr:street":"Rue Des Augustins",
    "iso:country":"BE",
    "sg:address":"Rue Des Augustins 3",
    "sg:city":"Enghien",
    "sg:classifiers":[
        {
            "category":"Education",
            "subcategory":"Library",
            "type":"Public Place"
        }
    ],
    "sg:phone":"+32 2 395 34 53",
    "sg:postcode":"7850",
    "sg:province":"Hainaut",
    "wof:name":"Biblioth\u00e8que D'enghien",
    "wof:placetype":"venue"
},
  "geometry": {"coordinates":[4.0370960236,50.6924514771],"type":"Point"}
}