{
  "type": "Feature",
  "properties": {
    "iso:country":"BE",
    "sg:address":"Gasthuisbosdreef 29",
    "sg:city":"Tongeren",
    "sg:classifiers":[
        {
            "category":"Shopping",
            "subcategory":"Clothing, Apparel, & Fashions",
            "type":"Retail Goods"
        }
    ],
    "sg:phone":"+32 12 23 37 93",
    "sg:postcode":"3700",
    "sg:province":"Limburg",
    "sg:tags":[
        "textile",
        "clothing",
        "clothes"
    ],
    "wof:name":"Escobel Confectie Bvba",
    "wof:placetype":"venue"
},
  "geometry": {"coordinates":[5.4550318718,50.7917480469],"type":"Point"}
}