{
  "type": "Feature",
  "properties": {
    "iso:country":"BE",
    "sg:address":"Oude Molenstraat 31bb",
    "sg:city":"Dendermonde",
    "sg:orig_category":"Eleveurs de bovins",
    "sg:phone":"+32 52 21 78 90",
    "sg:postcode":"9200",
    "sg:province":"Oost-Vlaanderen",
    "wof:name":"Remi Smet",
    "wof:placetype":"venue"
},
  "geometry": {"coordinates":[4.0996909142,51.0266418457],"type":"Point"}
}