{
  "type": "Feature",
  "properties": {
    "iso:country":"BE",
    "sg:address":"Avenue Franklin Roosevelt 29",
    "sg:city":"Vis\u00e9",
    "sg:classifiers":[
        {
            "category":"Insurance",
            "subcategory":"Insurance Agent",
            "type":"Services"
        }
    ],
    "sg:phone":"+32 4 379 21 55",
    "sg:postcode":"4600",
    "sg:province":"Li\u00e8ge",
    "sg:tags":[
        "broker"
    ],
    "wof:name":"Spits P.",
    "wof:placetype":"venue"
},
  "geometry": {"coordinates":[5.6856789589,50.7373886108],"type":"Point"}
}