{
  "type": "Feature",
  "properties": {
    "iso:country":"BE",
    "sg:address":"Rue De La Terre \u00e0 Briques",
    "sg:city":"Tournai (froyennes)",
    "sg:classifiers":[
        {
            "category":"Shopping",
            "subcategory":"Discount & Variety Stores",
            "type":"Retail Goods"
        }
    ],
    "sg:phone":"+32 69 22 48 04",
    "sg:postcode":"7503",
    "sg:province":"Hainaut",
    "sg:tags":[
        "warehouse",
        "-",
        "merchandise"
    ],
    "wof:name":"C.s.l.",
    "wof:placetype":"venue"
},
  "geometry": {"coordinates":[3.3313469887,50.617225647],"type":"Point"}
}