{
  "type": "Feature",
  "properties": {
    "addr:full":". Les Bons Villers Hainaut 6210",
    "addr:postcode":"6210",
    "iso:country":"BE",
    "sg:address":".",
    "sg:city":"Les Bons Villers",
    "sg:orig_category":"Apotheken",
    "sg:phone":"+32 900 10 500",
    "sg:postcode":"6210",
    "sg:province":"Hainaut",
    "wof:name":"Apothekers Van Wacht",
    "wof:placetype":"venue"
},
  "geometry": {"coordinates":[4.4511561394,50.5378227234],"type":"Point"}
}