{
  "type": "Feature",
  "properties": {
    "iso:country":"BE",
    "sg:address":"Avenue Marie-jos\u00c9 115",
    "sg:city":"Brussel",
    "sg:orig_category":"Agences d'exp\u00e9dition",
    "sg:phone":"+32 2 732 60 99",
    "sg:postcode":"1200",
    "sg:province":"Bruxelles-Capitale",
    "wof:name":"Zabelex",
    "wof:placetype":"venue"
},
  "geometry": {"coordinates":[4.4094099998,50.844669342],"type":"Point"}
}