{
  "type": "Feature",
  "properties": {
    "addr:full":"Droeskouterstraat 27 Haaltert Oost-Vlaanderen 9450",
    "addr:housenumber":"27",
    "addr:postcode":"9450",
    "addr:street":"Droeskouterstraat",
    "iso:country":"BE",
    "sg:address":"Droeskouterstraat 27",
    "sg:city":"Haaltert",
    "sg:classifiers":[
        {
            "category":"Arena",
            "subcategory":"Sports Club",
            "type":"Entertainment"
        }
    ],
    "sg:phone":"+32 53 83 11 06",
    "sg:postcode":"9450",
    "sg:province":"Oost-Vlaanderen",
    "sg:tags":[
        "de"
    ],
    "wof:name":"B.c. Center",
    "wof:placetype":"venue"
},
  "geometry": {"coordinates":[4.0047712326,50.8976249695],"type":"Point"}
}