{
  "type": "Feature",
  "properties": {
    "addr:full":"Driesstraat 43 Beringen (paal) Limburg 3583",
    "addr:housenumber":"43",
    "addr:postcode":"3583",
    "addr:street":"Driesstraat",
    "iso:country":"BE",
    "sg:address":"Driesstraat 43",
    "sg:city":"Beringen (paal)",
    "sg:classifiers":[
        {
            "category":"Wholesale",
            "subcategory":"Plants",
            "type":"Manufacturing & Wholesale Goods"
        }
    ],
    "sg:phone":"+32 11 42 42 75",
    "sg:postcode":"3583",
    "sg:province":"Limburg",
    "sg:tags":[
        "whol",
        "flower",
        "-",
        "grower"
    ],
    "wof:name":"Meuws Boomkwekerij",
    "wof:placetype":"venue"
},
  "geometry": {"coordinates":[5.1706700325,51.0389442444],"type":"Point"}
}