{
  "type": "Feature",
  "properties": {
    "addr:full":"Monseigneur Cardijnlaan 1 Edegem Antwerpen 2650",
    "addr:housenumber":"1",
    "addr:postcode":"2650",
    "addr:street":"Monseigneur Cardijnlaan",
    "iso:country":"BE",
    "sg:address":"Monseigneur Cardijnlaan 1",
    "sg:city":"Edegem",
    "sg:orig_category":"Algemeen secundair onderwijs Technisch and beroeps secundair onderwijs",
    "sg:phone":"+32 3 457 11 15",
    "sg:postcode":"2650",
    "sg:province":"Antwerpen",
    "wof:name":"Koninklijk Atheneum",
    "wof:placetype":"venue"
},
  "geometry": {"coordinates":[4.4443302155,51.1518516541],"type":"Point"}
}