{
  "type": "Feature",
  "properties": {
    "addr:full":"Rue Calus 4 Waterloo Brabant Wallon 1400",
    "addr:housenumber":"4",
    "addr:postcode":"1400",
    "addr:street":"Rue Calus",
    "iso:country":"BE",
    "sg:address":"Rue Calus 4",
    "sg:city":"Waterloo",
    "sg:orig_category":"Speelgoed",
    "sg:phone":"+32 2 351 07 39",
    "sg:postcode":"1400",
    "sg:province":"Brabant Wallon",
    "wof:name":"Club De Mod\u00c9lisme",
    "wof:placetype":"venue"
},
  "geometry": {"coordinates":[-84.9924316406,41.5135879517],"type":"Point"}
}