{
  "type": "Feature",
  "properties": {
    "addr:full":"Chauss\u00e9e De Li\u00e8ge 90 Amay Li\u00e8ge 4540",
    "addr:housenumber":"90",
    "addr:postcode":"4540",
    "addr:street":"Chausse\u0301E De Lie\u0300Ge",
    "iso:country":"BE",
    "sg:address":"Chauss\u00e9e De Li\u00e8ge 90",
    "sg:city":"Amay",
    "sg:classifiers":[
        {
            "category":"Retail",
            "subcategory":"Auto Repair",
            "type":"Services"
        }
    ],
    "sg:phone":"+32 85 31 35 52",
    "sg:postcode":"4540",
    "sg:province":"Li\u00e8ge",
    "sg:tags":[
        "automobile-body"
    ],
    "wof:name":"Rigo P",
    "wof:placetype":"venue"
},
  "geometry": {"coordinates":[5.2987098694,50.5410614014],"type":"Point"}
}