{
  "type": "Feature",
  "properties": {
    "iso:country":"BE",
    "sg:address":"Steenweg Op Mol 38b1",
    "sg:city":"Oud-turnhout",
    "sg:classifiers":[
        {
            "category":"Organizations",
            "subcategory":"Community Association",
            "type":"Services"
        }
    ],
    "sg:phone":"+32 14 45 49 59",
    "sg:postcode":"2360",
    "sg:province":"Antwerpen",
    "sg:tags":[
        "organisation"
    ],
    "wof:name":"Jeugdhuis De Splinter",
    "wof:placetype":"venue"
},
  "geometry": {"coordinates":[4.9846968651,51.3170471191],"type":"Point"}
}