{
  "type": "Feature",
  "properties": {
    "addr:full":"Oudburg 90 Gent Oost-Vlaanderen 9000",
    "addr:housenumber":"90",
    "addr:postcode":"9000",
    "addr:street":"Oudburg;Oost-Vlaanderen",
    "iso:country":"BE",
    "sg:address":"Oudburg 90",
    "sg:city":"Gent",
    "sg:classifiers":[
        {
            "category":"Restaurant",
            "type":"Food & Drink"
        }
    ],
    "sg:phone":"+32 9 225 34 37",
    "sg:postcode":"9000",
    "sg:province":"Oost-Vlaanderen",
    "wof:name":"Kanta",
    "wof:placetype":"venue"
},
  "geometry": {"coordinates":[3.7250490189,51.0593452454],"type":"Point"}
}