{
  "type": "Feature",
  "properties": {
    "iso:country":"BE",
    "sg:address":"Pierstraat 229",
    "sg:city":"Kontich",
    "sg:orig_category":"Herstellingen and onderhoud van auto's Voertuigen",
    "sg:phone":"+32 3 450 02 11",
    "sg:postcode":"2550",
    "sg:province":"Antwerpen",
    "wof:name":"Mitsubishi",
    "wof:placetype":"venue"
},
  "geometry": {"coordinates":[4.4212899208,51.1286354065],"type":"Point"}
}