{
  "type": "Feature",
  "properties": {
    "addr:full":"Rue De Strichon 48 Villers-la-ville (tilly) Brabant Wallon 1495",
    "addr:housenumber":"48",
    "addr:postcode":"1495",
    "addr:street":"Rue De Strichon;Wallon",
    "iso:country":"BE",
    "sg:address":"Rue De Strichon 48",
    "sg:city":"Villers-la-ville (tilly)",
    "sg:classifiers":[
        {
            "category":"Building & Trades",
            "subcategory":"Cleaning & Sanitation",
            "type":"Services"
        }
    ],
    "sg:phone":"+32 71 87 70 76",
    "sg:postcode":"1495",
    "sg:province":"Brabant Wallon",
    "sg:tags":[
        "janitor"
    ],
    "wof:name":"Net O Flash",
    "wof:placetype":"venue"
},
  "geometry": {"coordinates":[4.5588498116,50.577960968],"type":"Point"}
}