{
  "type": "Feature",
  "properties": {
    "addr:full":"Sint-laurentiusstraat 47 Beveren Oost-Vlaanderen 9130",
    "addr:housenumber":"47",
    "addr:postcode":"9130",
    "addr:street":"Sint-Laurentiusstraat",
    "iso:country":"BE",
    "sg:address":"Sint-laurentiusstraat 47",
    "sg:city":"Beveren",
    "sg:classifiers":[
        {
            "category":"Insurance",
            "subcategory":"Insurance Agent",
            "type":"Services"
        }
    ],
    "sg:phone":"+32 3 773 54 18",
    "sg:postcode":"9130",
    "sg:province":"Oost-Vlaanderen",
    "sg:tags":[
        "verzekeringsmakelaars",
        "expert"
    ],
    "wof:name":"Gemimien Aerts",
    "wof:placetype":"venue"
},
  "geometry": {"coordinates":[4.1811990738,51.253616333],"type":"Point"}
}