{
  "type": "Feature",
  "properties": {
    "iso:country":"BE",
    "sg:address":"Sint-katelijnestraat 68",
    "sg:city":"Mechelen",
    "sg:classifiers":[
        {
            "category":"Insurance",
            "subcategory":"Insurance Agent",
            "type":"Services"
        }
    ],
    "sg:phone":"+32 15 21 99 44",
    "sg:postcode":"2800",
    "sg:province":"Antwerpen",
    "sg:tags":[
        "broker"
    ],
    "wof:name":"Luyten E",
    "wof:placetype":"venue"
},
  "geometry": {"coordinates":[4.4759597778,51.0312538147],"type":"Point"}
}