{
  "type": "Feature",
  "properties": {
    "addr:full":"Rue De Fl\u00c9malle-grande 326 Fl\u00c9malle Li\u00e8ge 4400",
    "addr:housenumber":"326",
    "addr:postcode":"4400",
    "addr:street":"Rue De Fle\u0301Malle-Grande",
    "iso:country":"BE",
    "sg:address":"Rue De Fl\u00c9malle-grande 326",
    "sg:city":"Fl\u00c9malle",
    "sg:orig_category":"Ordinateurs and \u00e9quipement informatique",
    "sg:phone":"+32 4 234 46 74",
    "sg:postcode":"4400",
    "sg:province":"Li\u00e8ge",
    "wof:name":"Thierry Adam",
    "wof:placetype":"venue"
},
  "geometry": {"coordinates":[5.4769711494,50.6150894165],"type":"Point"}
}