{
  "type": "Feature",
  "properties": {
    "iso:country":"BE",
    "sg:address":"Rue Raoul Follereau 6",
    "sg:city":"Mons (maisi\u00e8res)",
    "sg:classifiers":[
        {
            "category":"Bars & Pubs",
            "subcategory":"Wine Bar",
            "type":"Food & Drink"
        }
    ],
    "sg:phone":"+32 65 33 94 09",
    "sg:postcode":"7020",
    "sg:province":"Hainaut",
    "sg:tags":[
        "cellar",
        "fixture"
    ],
    "wof:name":"Agence Impor-g\u00e9",
    "wof:placetype":"venue"
},
  "geometry": {"coordinates":[3.9553449154,50.4761772156],"type":"Point"}
}