{
  "type": "Feature",
  "properties": {
    "addr:full":"Molenhoek 3 Koekelare (bovekerke) West-Vlaanderen 8680",
    "addr:housenumber":"3",
    "addr:postcode":"8680",
    "addr:street":"Molenhoek",
    "iso:country":"BE",
    "sg:address":"Molenhoek 3",
    "sg:city":"Koekelare (bovekerke)",
    "sg:classifiers":[
        {
            "category":"Food & Beverages",
            "subcategory":"Meat & Fish",
            "type":"Retail Goods"
        }
    ],
    "sg:phone":"+32 51 56 86 77",
    "sg:postcode":"8680",
    "sg:province":"West-Vlaanderen",
    "sg:tags":[
        "poultry",
        "whol",
        "game",
        "-"
    ],
    "wof:name":"Europe Hunting Nv",
    "wof:placetype":"venue"
},
  "geometry": {"coordinates":[2.9583029747,51.0479469299],"type":"Point"}
}