{
  "type": "Feature",
  "properties": {
    "addr:full":"Kerkstraat 30 Riemst Limburg 3770",
    "addr:housenumber":"30",
    "addr:postcode":"3770",
    "addr:street":"Kerkstraat",
    "iso:country":"BE",
    "sg:address":"Kerkstraat 30",
    "sg:city":"Riemst",
    "sg:orig_category":"Diensten voor huisdieren Huisdieren and benodigdheden Huisdierenkwekers",
    "sg:phone":"+32 12 45 55 24",
    "sg:postcode":"3770",
    "sg:province":"Limburg",
    "wof:name":"Het Heinenhof",
    "wof:placetype":"venue"
},
  "geometry": {"coordinates":[5.5762910843,50.8089027405],"type":"Point"}
}