{
  "type": "Feature",
  "properties": {
    "iso:country":"BE",
    "sg:address":"Rue De Bruxelles 60",
    "sg:city":"Enghien",
    "sg:orig_category":"Bijouteries and horlogeries",
    "sg:phone":"+32 2 395 89 49",
    "sg:postcode":"7850",
    "sg:province":"Hainaut",
    "wof:name":"Lazuli",
    "wof:placetype":"venue"
},
  "geometry": {"coordinates":[4.0417790413,50.6947860718],"type":"Point"}
}