{
  "type": "Feature",
  "properties": {
    "addr:full":"Levergem 30 Beveren (beveren-waas) Oost-Vlaanderen 9120",
    "addr:housenumber":"30",
    "addr:postcode":"9120",
    "addr:street":"Levergem;Oost-Vlaanderen",
    "iso:country":"BE",
    "sg:address":"Levergem 30",
    "sg:city":"Beveren (beveren-waas)",
    "sg:classifiers":[
        {
            "category":"Professional",
            "subcategory":"Art Services",
            "type":"Services"
        }
    ],
    "sg:phone":"+32 3 775 33 62",
    "sg:postcode":"9120",
    "sg:province":"Oost-Vlaanderen",
    "sg:tags":[
        "photographer"
    ],
    "wof:name":"Foto Design Ivens",
    "wof:placetype":"venue"
},
  "geometry": {"coordinates":[4.2455258369,51.2213134766],"type":"Point"}
}