{
  "type": "Feature",
  "properties": {
    "addr:full":"Berentrodedreef 51ba Bonheiden Antwerpen 2820",
    "addr:housenumber":"51ba",
    "addr:postcode":"2820",
    "addr:street":"Berentrodedreef",
    "iso:country":"BE",
    "sg:address":"Berentrodedreef 51ba",
    "sg:city":"Bonheiden",
    "sg:orig_category":"Etalage- and showroomontwerpers",
    "sg:phone":"+32 15 51 20 25",
    "sg:postcode":"2820",
    "sg:province":"Antwerpen",
    "wof:name":"Van Craen",
    "wof:placetype":"venue"
},
  "geometry": {"coordinates":[4.5570898056,51.0261154175],"type":"Point"}
}