{
  "type": "Feature",
  "properties": {
    "iso:country":"BE",
    "sg:address":"Industrieter. Daelemveld 1026",
    "sg:city":"Herk-de-stad",
    "sg:orig_category":"Loodgieterij and centrale verwarming Gh",
    "sg:phone":"+32 800 91 551",
    "sg:postcode":"3540",
    "sg:province":"Limburg",
    "wof:name":"Aquacare Belgium",
    "wof:placetype":"venue"
},
  "geometry": {"coordinates":[5.1723918915,50.9441490173],"type":"Point"}
}