{
  "type": "Feature",
  "properties": {
    "addr:full":"Weidenstraat 30 Drogenbos/drogenbos Vlaams-Brabant 1620",
    "addr:housenumber":"30",
    "addr:postcode":"1620",
    "addr:street":"Weidenstraat",
    "iso:country":"BE",
    "sg:address":"Weidenstraat 30",
    "sg:city":"Drogenbos/drogenbos",
    "sg:orig_category":"Artiesten and kunstenaars",
    "sg:phone":"+32 2 377 01 22",
    "sg:postcode":"1620",
    "sg:province":"Vlaams-Brabant",
    "wof:name":"Rene De Broyer",
    "wof:placetype":"venue"
},
  "geometry": {"coordinates":[4.3140749931,50.7954864502],"type":"Point"}
}