{
  "type": "Feature",
  "properties": {
    "addr:full":"Rue Maria Gilles 2 Hannut Li\u00e8ge 4280",
    "addr:housenumber":"2",
    "addr:postcode":"4280",
    "addr:street":"Rue Maria Gilles",
    "iso:country":"BE",
    "sg:address":"Rue Maria Gilles 2",
    "sg:city":"Hannut",
    "sg:orig_category":"Bouwmaterialen Gh",
    "sg:phone":"+32 19 63 20 50",
    "sg:postcode":"4280",
    "sg:province":"Li\u00e8ge",
    "wof:name":"Alfalu",
    "wof:placetype":"venue"
},
  "geometry": {"coordinates":[5.0203499794,50.6872940063],"type":"Point"}
}