{
  "type": "Feature",
  "properties": {
    "addr:full":"Zonnebekestr 52 Langemark-poelkape West-Vlaanderen 8920",
    "addr:housenumber":"52",
    "addr:postcode":"8920",
    "addr:street":"Zonnebekestr;West-Vlaanderen",
    "iso:country":"BE",
    "sg:address":"Zonnebekestr 52",
    "sg:city":"Langemark-poelkape",
    "sg:classifiers":[
        {
            "category":"Government",
            "subcategory":"Department Of Motor Vehicles",
            "type":"Public Place"
        }
    ],
    "sg:phone":"+32 57 48 87 11",
    "sg:postcode":"8920",
    "sg:province":"West-Vlaanderen",
    "sg:tags":[
        "equipment",
        "industrial",
        "transport",
        "motor-cars"
    ],
    "wof:name":"Garage Vanhaelewijn Nv",
    "wof:placetype":"venue"
},
  "geometry": {"coordinates":[2.919770956,50.9132423401],"type":"Point"}
}