{
  "type": "Feature",
  "properties": {
    "addr:full":"Hoogkamerstraat 302 Temse Oost-Vlaanderen 9140",
    "addr:housenumber":"302",
    "addr:postcode":"9140",
    "addr:street":"Hoogkamerstraat",
    "iso:country":"BE",
    "sg:address":"Hoogkamerstraat 302",
    "sg:city":"Temse",
    "sg:classifiers":[
        {
            "category":"Food & Beverages",
            "subcategory":"Meat & Fish",
            "type":"Retail Goods"
        }
    ],
    "sg:phone":"+32 53 70 54 51",
    "sg:postcode":"9140",
    "sg:province":"Oost-Vlaanderen",
    "sg:tags":[
        "fresh"
    ],
    "wof:name":"Van Lysebeth-windey Nv",
    "wof:placetype":"venue"
},
  "geometry": {"coordinates":[4.0417661667,50.9645843506],"type":"Point"}
}