{
  "type": "Feature",
  "properties": {
    "addr:full":"Land Van Waaslaan 104 Gent Oost-Vlaanderen 9040",
    "addr:housenumber":"104",
    "addr:postcode":"9040",
    "addr:street":"Land Van Waaslaan;Oost-Vlaanderen",
    "iso:country":"BE",
    "sg:address":"Land Van Waaslaan 104",
    "sg:city":"Gent",
    "sg:classifiers":[
        {
            "category":"Autos & Motor Vehicles",
            "subcategory":"Fuel & Gas Station",
            "type":"Retail Goods"
        }
    ],
    "sg:phone":"+32 9 238 36 57",
    "sg:postcode":"9040",
    "sg:province":"Oost-Vlaanderen",
    "sg:tags":[
        "stations-service",
        "carburants"
    ],
    "wof:name":"Sven Van Woensel",
    "wof:placetype":"venue"
},
  "geometry": {"coordinates":[3.7469420433,51.0582885742],"type":"Point"}
}