{
  "type": "Feature",
  "properties": {
    "iso:country":"BE",
    "sg:address":"Rue Du Poseur 54",
    "sg:city":"Braine-le-comte",
    "sg:orig_category":"Installation de menuiserie en bois and plastique",
    "sg:phone":"+32 67 55 36 33",
    "sg:postcode":"7090",
    "sg:province":"Hainaut",
    "wof:name":"Jean Lhoir",
    "wof:placetype":"venue"
},
  "geometry": {"coordinates":[4.1352682114,50.6187667847],"type":"Point"}
}