{
  "type": "Feature",
  "properties": {
    "addr:full":"Stationstraat 27 Overijse 1900",
    "addr:housenumber":"27",
    "addr:postcode":"1900",
    "addr:street":"Stationstraat",
    "iso:country":"BE",
    "sg:address":"Stationstraat 27",
    "sg:city":"Overijse",
    "sg:classifiers":[
        {
            "category":"Banks & Credit Unions",
            "subcategory":"Bank",
            "type":"Services"
        }
    ],
    "sg:phone":"+32 2 687 67 48",
    "sg:postcode":"1900",
    "wof:name":"Aslk-cger Bank",
    "wof:placetype":"venue"
},
  "geometry": {"coordinates":[4.5359997749,50.7716751099],"type":"Point"}
}