{
  "type": "Feature",
  "properties": {
    "addr:full":"Belseledorp 160 Sint-niklaas (belsele) Oost-Vlaanderen 9111",
    "addr:housenumber":"160",
    "addr:postcode":"9111",
    "iso:country":"BE",
    "sg:address":"Belseledorp 160",
    "sg:city":"Sint-niklaas (belsele)",
    "sg:classifiers":[
        {
            "category":"Social Services",
            "subcategory":"Child Care",
            "type":"Services"
        }
    ],
    "sg:phone":"+32 3 772 31 76",
    "sg:postcode":"9111",
    "sg:province":"Oost-Vlaanderen",
    "sg:tags":[
        "home"
    ],
    "wof:name":"Lenteweelde",
    "wof:placetype":"venue"
},
  "geometry": {"coordinates":[4.0797457695,51.1427536011],"type":"Point"}
}