{
  "type": "Feature",
  "properties": {
    "addr:full":"Emiel Clausstraat 21 Sint-eloois-vijve West-Vlaanderen 8793",
    "addr:housenumber":"21",
    "addr:postcode":"8793",
    "addr:street":"Emiel Clausstraat;West-Vlaanderen",
    "iso:country":"BE",
    "sg:address":"Emiel Clausstraat 21",
    "sg:city":"Sint-eloois-vijve",
    "sg:classifiers":[
        {
            "category":"Home & Garden",
            "subcategory":"Building Materials",
            "type":"Retail Goods"
        }
    ],
    "sg:phone":"+32 56 60 00 38",
    "sg:postcode":"8793",
    "sg:province":"West-Vlaanderen",
    "sg:tags":[
        "aluminium",
        "window"
    ],
    "wof:name":"Terras Decor Nv",
    "wof:placetype":"venue"
},
  "geometry": {"coordinates":[3.4070138931,50.9092483521],"type":"Point"}
}