{
  "type": "Feature",
  "properties": {
    "addr:full":"Rue Cur\u00c9 Ramoux 11 Bassenge Li\u00e8ge 4690",
    "addr:housenumber":"11",
    "addr:postcode":"4690",
    "addr:street":"Rue Cure\u0301 Ramoux",
    "iso:country":"BE",
    "sg:address":"Rue Cur\u00c9 Ramoux 11",
    "sg:city":"Bassenge",
    "sg:orig_category":"Notarissen",
    "sg:phone":"+32 4 286 34 14",
    "sg:postcode":"4690",
    "sg:province":"Li\u00e8ge",
    "wof:name":"Jean Van Der Wielen",
    "wof:placetype":"venue"
},
  "geometry": {"coordinates":[5.5460867882,50.7517471313],"type":"Point"}
}