{
  "type": "Feature",
  "properties": {
    "iso:country":"BE",
    "sg:address":"Alice Nahonlei 3",
    "sg:city":"Schoten",
    "sg:classifiers":[
        {
            "category":"Professional",
            "subcategory":"Management & Consulting",
            "type":"Services"
        }
    ],
    "sg:phone":"+32 3 658 43 15",
    "sg:postcode":"2900",
    "sg:province":"Antwerpen",
    "sg:tags":[
        "consultant"
    ],
    "wof:name":"Van Strydonck R",
    "wof:placetype":"venue"
},
  "geometry": {"coordinates":[4.5357642174,51.2557144165],"type":"Point"}
}