{
  "type": "Feature",
  "properties": {
    "addr:full":"Beukenlaan 2a Rotselaar Vlaams-Brabant 3110",
    "addr:housenumber":"2a",
    "addr:postcode":"3110",
    "addr:street":"Beukenlaan",
    "iso:country":"BE",
    "sg:address":"Beukenlaan 2a",
    "sg:city":"Rotselaar",
    "sg:classifiers":[
        {
            "category":"Professional",
            "subcategory":"Computer Services",
            "type":"Services"
        }
    ],
    "sg:phone":"+32 16 44 65 01",
    "sg:postcode":"3110",
    "sg:province":"Vlaams-Brabant",
    "sg:tags":[
        "webdesign",
        "-",
        "internet"
    ],
    "wof:name":"Moons E",
    "wof:placetype":"venue"
},
  "geometry": {"coordinates":[4.7107920647,50.9508590698],"type":"Point"}
}