{
  "type": "Feature",
  "properties": {
    "addr:full":"Avenue De L'h\u00f4pital Fran\u00e7ais 2 Bruxelles (ganshoren) Bruxelles-Capitale 1083",
    "addr:housenumber":"2",
    "addr:postcode":"1083",
    "addr:street":"Avenue De L'Ho \u0302Pital Franc\u0327Ais",
    "iso:country":"BE",
    "sg:address":"Avenue De L'h\u00f4pital Fran\u00e7ais 2",
    "sg:city":"Bruxelles (ganshoren)",
    "sg:classifiers":[
        {
            "category":"Professional",
            "subcategory":"Testing Lab",
            "type":"Services"
        }
    ],
    "sg:phone":"+32 2 426 55 12",
    "sg:postcode":"1083",
    "sg:province":"Bruxelles-Capitale",
    "sg:tags":[
        "chemist"
    ],
    "wof:name":"Tielen Sprl",
    "wof:placetype":"venue"
},
  "geometry": {"coordinates":[4.3145031929,50.8672409058],"type":"Point"}
}