{
  "type": "Feature",
  "properties": {
    "iso:country":"BE",
    "sg:address":"Rue De L'\u00c9glise 105",
    "sg:city":"Sint-pieters-woluwe",
    "sg:orig_category":"Medische and orthopedische apparaten",
    "sg:phone":"+32 2 779 17 06",
    "sg:postcode":"1150",
    "sg:province":"Bruxelles-Capitale",
    "wof:name":"Acoustic Lm",
    "wof:placetype":"venue"
},
  "geometry": {"coordinates":[4.4631619453,50.8405723572],"type":"Point"}
}