{
  "type": "Feature",
  "properties": {
    "iso:country":"BE",
    "sg:address":"Markt 28",
    "sg:city":"Wetteren",
    "sg:classifiers":[
        {
            "category":"Shopping",
            "subcategory":"Clothing, Apparel, & Fashions",
            "type":"Retail Goods"
        }
    ],
    "sg:phone":"+32 9 369 57 44",
    "sg:postcode":"9230",
    "sg:province":"Oost-Vlaanderen",
    "sg:tags":[
        "underwear",
        "lingerie",
        "-"
    ],
    "wof:name":"Sweet & Beauty",
    "wof:placetype":"venue"
},
  "geometry": {"coordinates":[3.8861351013,51.0067901611],"type":"Point"}
}