{
  "type": "Feature",
  "properties": {
    "addr:full":"105 Rue Du Foyer Schaerbeekois 1030 Bruxelles 105",
    "addr:housenumber":"105;105",
    "addr:postcode":"1030",
    "addr:street":"Rue Du Foyer Schaerbeekois",
    "iso:country":"BE",
    "sg:address":"105",
    "sg:city":"Rue Du Foyer Schaerbeekois 1030 Bruxelles",
    "sg:classifiers":[
        {
            "category":"Government",
            "subcategory":"Department Of Motor Vehicles",
            "type":"Public Place"
        }
    ],
    "sg:phone":"+32 2 216 10 42",
    "sg:postcode":"105",
    "sg:tags":[
        "equipment",
        "industrial",
        "transport",
        "motor-cars"
    ],
    "wof:name":"Denserco Sa",
    "wof:placetype":"venue"
},
  "geometry": {"coordinates":[4.3857002258,50.8717346191],"type":"Point"}
}