{
  "type": "Feature",
  "properties": {
    "iso:country":"BE",
    "sg:address":"Rue De La Ram\u00c9e 11b2",
    "sg:city":"Ottignies-louvain-la-neuve",
    "sg:orig_category":"Ordinateurs and \u00e9quipement informatique",
    "sg:phone":"+32 10 45 55 44",
    "sg:postcode":"1348",
    "sg:province":"Brabant Wallon",
    "wof:name":"We Work With You",
    "wof:placetype":"venue"
},
  "geometry": {"coordinates":[4.6171488762,50.6736526489],"type":"Point"}
}