{
  "type": "Feature",
  "properties": {
    "iso:country":"BE",
    "sg:address":"Europalaan 104a",
    "sg:city":"Dilsen-stokkem (dilsen)",
    "sg:classifiers":[
        {
            "category":"Food & Beverages",
            "subcategory":"Supermarket",
            "type":"Retail Goods"
        }
    ],
    "sg:phone":"+32 89 79 26 74",
    "sg:postcode":"3650",
    "sg:province":"Limburg",
    "sg:tags":[
        "department",
        "store"
    ],
    "wof:name":"Peevan Nv Gb Partner",
    "wof:placetype":"venue"
},
  "geometry": {"coordinates":[5.7183890343,51.0381240845],"type":"Point"}
}