{
  "type": "Feature",
  "properties": {
    "addr:full":"Seringenstraat 83 Roeselare West-Vlaanderen 8800",
    "addr:housenumber":"83",
    "addr:postcode":"8800",
    "addr:street":"Seringenstraat",
    "iso:country":"BE",
    "sg:address":"Seringenstraat 83",
    "sg:city":"Roeselare",
    "sg:classifiers":[
        {
            "category":"Personal",
            "subcategory":"Beauty Salon",
            "type":"Services"
        }
    ],
    "sg:phone":"+32 51 22 53 71",
    "sg:postcode":"8800",
    "sg:province":"West-Vlaanderen",
    "sg:tags":[
        "lady",
        "-",
        "hairdressing"
    ],
    "wof:name":"Fashion Coiffure",
    "wof:placetype":"venue"
},
  "geometry": {"coordinates":[3.1363990307,50.9402008057],"type":"Point"}
}