{
  "type": "Feature",
  "properties": {
    "addr:full":"Steenberghoekstraat 23 Rumst Antwerpen 2840",
    "addr:housenumber":"23",
    "addr:postcode":"2840",
    "addr:street":"Steenberghoekstraat",
    "iso:country":"BE",
    "sg:address":"Steenberghoekstraat 23",
    "sg:city":"Rumst",
    "sg:classifiers":[
        {
            "category":"Home & Garden",
            "subcategory":"Kitchen Supply",
            "type":"Retail Goods"
        }
    ],
    "sg:phone":"+32 3 888 55 22",
    "sg:postcode":"2840",
    "sg:province":"Antwerpen",
    "sg:tags":[
        "installation"
    ],
    "wof:name":"Pivaro Interieur Bvba",
    "wof:placetype":"venue"
},
  "geometry": {"coordinates":[4.4180941582,51.0803413391],"type":"Point"}
}