{
  "type": "Feature",
  "properties": {
    "addr:full":"Rue Du Centre 17 Ciney Namur 5590",
    "addr:housenumber":"17",
    "addr:postcode":"5590",
    "addr:street":"Rue Du Centre",
    "iso:country":"BE",
    "sg:address":"Rue Du Centre 17",
    "sg:city":"Ciney",
    "sg:classifiers":[
        {
            "category":"Insurance",
            "subcategory":"Insurance Agent",
            "type":"Services"
        }
    ],
    "sg:phone":"+32 83 21 18 70",
    "sg:postcode":"5590",
    "sg:province":"Namur",
    "sg:tags":[
        "broker"
    ],
    "wof:name":"Dewez R",
    "wof:placetype":"venue"
},
  "geometry": {"coordinates":[5.1003079414,50.2960891724],"type":"Point"}
}