{
  "type": "Feature",
  "properties": {
    "iso:country":"BE",
    "sg:address":"Rue De La Couronne 10",
    "sg:city":"Wavre",
    "sg:orig_category":"Activit\u00e9s d\u00b4action sociale sans h\u00e9bergement",
    "sg:phone":"+32 10 22 60 76",
    "sg:postcode":"1301",
    "sg:province":"Brabant Wallon",
    "wof:name":"Resto Du Coeur",
    "wof:placetype":"venue"
},
  "geometry": {"coordinates":[4.6110491753,50.7077522278],"type":"Point"}
}