{
  "type": "Feature",
  "properties": {
    "iso:country":"BE",
    "sg:address":"Avenue Charles Deli\u00e8ge 4",
    "sg:city":"Binche",
    "sg:classifiers":[
        {
            "category":"Home & Garden",
            "subcategory":"Hardware",
            "type":"Retail Goods"
        }
    ],
    "sg:phone":"+32 64 33 27 34",
    "sg:postcode":"7130",
    "sg:province":"Hainaut",
    "sg:tags":[
        "-"
    ],
    "wof:name":"Maison Traets",
    "wof:placetype":"venue"
},
  "geometry": {"coordinates":[4.1672549248,50.4147453308],"type":"Point"}
}