{
  "type": "Feature",
  "properties": {
    "iso:country":"BE",
    "sg:address":"Meyenbos 6",
    "sg:city":"Merksplas",
    "sg:orig_category":"Rundveehouders",
    "sg:phone":"+32 14 63 46 34",
    "sg:postcode":"2330",
    "sg:province":"Antwerpen",
    "wof:name":"Josephus Smets",
    "wof:placetype":"venue"
},
  "geometry": {"coordinates":[4.8891458511,51.344165802],"type":"Point"}
}