{
  "type": "Feature",
  "properties": {
    "iso:country":"BE",
    "sg:address":"Rue Major Housiau 39",
    "sg:city":"Montigny-le-tilleul",
    "sg:orig_category":"Installation de menuiserie m\u00e9tallique. Installation de menuiserie en bois and plastique",
    "sg:phone":"+32 71 56 08 12",
    "sg:postcode":"6110",
    "sg:province":"Hainaut",
    "wof:name":"D.f. Volets",
    "wof:placetype":"venue"
},
  "geometry": {"coordinates":[4.3794560432,50.3750114441],"type":"Point"}
}