{
  "type": "Feature",
  "properties": {
    "addr:full":"Leuvensesteenweg 63 Mechelen Antwerpen 2800",
    "addr:housenumber":"63",
    "addr:postcode":"2800",
    "addr:street":"Leuvensesteenweg",
    "iso:country":"BE",
    "sg:address":"Leuvensesteenweg 63",
    "sg:city":"Mechelen",
    "sg:classifiers":[
        {
            "category":"Shopping",
            "subcategory":"Clothing, Apparel, & Fashions",
            "type":"Retail Goods"
        }
    ],
    "sg:phone":"+32 15 41 22 98",
    "sg:postcode":"2800",
    "sg:province":"Antwerpen",
    "sg:tags":[
        "milliner"
    ],
    "wof:name":"Buelens J",
    "wof:placetype":"venue"
},
  "geometry": {"coordinates":[4.4920067787,51.0202445984],"type":"Point"}
}