{
  "type": "Feature",
  "properties": {
    "addr:full":"Rue Du Fays 2 Juprelle Li\u00e8ge 4450",
    "addr:housenumber":"2",
    "addr:postcode":"4450",
    "addr:street":"Rue Du Fays",
    "iso:country":"BE",
    "sg:address":"Rue Du Fays 2",
    "sg:city":"Juprelle",
    "sg:orig_category":"Architectes",
    "sg:phone":"+32 4 263 91 08",
    "sg:postcode":"4450",
    "sg:province":"Li\u00e8ge",
    "wof:name":"S\u00c9verine Rondal",
    "wof:placetype":"venue"
},
  "geometry": {"coordinates":[5.5194821358,50.6912956238],"type":"Point"}
}