{
  "type": "Feature",
  "properties": {
    "addr:full":"Groenplaats 7b2 Antwerpen Antwerpen 2000",
    "addr:housenumber":"7b2",
    "addr:postcode":"2000",
    "addr:street":"Groenplaats",
    "iso:country":"BE",
    "sg:address":"Groenplaats 7b2",
    "sg:city":"Antwerpen",
    "sg:orig_category":"Artiesten and kunstenaars",
    "sg:phone":"+32 3 232 22 64",
    "sg:postcode":"2000",
    "sg:province":"Antwerpen",
    "wof:name":"Herwig Ilegems",
    "wof:placetype":"venue"
},
  "geometry": {"coordinates":[4.401239872,51.2197189331],"type":"Point"}
}