{
  "type": "Feature",
  "properties": {
    "addr:full":"Korenlei 17 Gent Oost-Vlaanderen 9000",
    "addr:housenumber":"17",
    "addr:postcode":"9000",
    "addr:street":"Korenlei;Oost-Vlaanderen",
    "iso:country":"BE",
    "sg:address":"Korenlei 17",
    "sg:city":"Gent",
    "sg:orig_category":"Cr\u00e9dit \u00e0 la consommation. Pr\u00eats hypoth\u00e9caires and cr\u00e9dits immobiliers",
    "sg:phone":"+32 9 225 86 55",
    "sg:postcode":"9000",
    "sg:province":"Oost-Vlaanderen",
    "wof:name":"Cr\u00c9ditmar",
    "wof:placetype":"venue"
},
  "geometry": {"coordinates":[3.719960928,51.054397583],"type":"Point"}
}