{
  "type": "Feature",
  "properties": {
    "iso:country":"BE",
    "sg:address":"Bellemdorpweg 72",
    "sg:city":"Aalter",
    "sg:orig_category":"Technische studies and ingenieursactiviteiten",
    "sg:phone":"+32 9 374 80 84",
    "sg:postcode":"9881",
    "sg:province":"Oost-Vlaanderen",
    "wof:name":"Buro C & C",
    "wof:placetype":"venue"
},
  "geometry": {"coordinates":[3.4878079891,51.0917625427],"type":"Point"}
}