{
  "type": "Feature",
  "properties": {
    "addr:full":"Theet 31 Hamme Oost-Vlaanderen 9220",
    "addr:housenumber":"31",
    "addr:postcode":"9220",
    "addr:street":"Theet",
    "iso:country":"BE",
    "sg:address":"Theet 31",
    "sg:city":"Hamme",
    "sg:orig_category":"HUISBRANDOLIE",
    "sg:phone":"+32 52 47 77 75",
    "sg:postcode":"9220",
    "sg:province":"Oost-Vlaanderen",
    "wof:name":"De Mulder",
    "wof:placetype":"venue"
},
  "geometry": {"coordinates":[4.1311807632,51.0807533264],"type":"Point"}
}