{
  "type": "Feature",
  "properties": {
    "addr:full":"Duinenstraat 83 Bredene West-Vlaanderen 8450",
    "addr:housenumber":"83",
    "addr:postcode":"8450",
    "addr:street":"Duinenstraat",
    "iso:country":"BE",
    "sg:address":"Duinenstraat 83",
    "sg:city":"Bredene",
    "sg:classifiers":[
        {
            "category":"Home & Garden",
            "subcategory":"Household Appliances",
            "type":"Retail Goods"
        }
    ],
    "sg:phone":"+32 59 32 37 56",
    "sg:postcode":"8450",
    "sg:province":"West-Vlaanderen",
    "sg:tags":[
        "repair",
        "mainten",
        "-",
        "electric"
    ],
    "wof:name":"Marlein H",
    "wof:placetype":"venue"
},
  "geometry": {"coordinates":[2.9690909386,51.2386245728],"type":"Point"}
}