{
  "type": "Feature",
  "properties": {
    "addr:full":"Hoeksken 78a Evergem Oost-Vlaanderen 9940",
    "addr:housenumber":"78a",
    "addr:postcode":"9940",
    "addr:street":"Hoeksken;Oost-Vlaanderen",
    "iso:country":"BE",
    "sg:address":"Hoeksken 78a",
    "sg:city":"Evergem",
    "sg:classifiers":[
        {
            "category":"Bars & Pubs",
            "type":"Food & Drink"
        }
    ],
    "sg:phone":"+32 9 258 25 75",
    "sg:postcode":"9940",
    "sg:province":"Oost-Vlaanderen",
    "sg:tags":[
        "tavern"
    ],
    "wof:name":"Liquide",
    "wof:placetype":"venue"
},
  "geometry": {"coordinates":[3.7035009861,51.1112632751],"type":"Point"}
}