{
  "type": "Feature",
  "properties": {
    "addr:full":"Avenue Des Muguets 24 Braine L'alleud (braine-l'alleud) Brabant Wallon 1420",
    "addr:housenumber":"24",
    "addr:postcode":"1420",
    "addr:street":"Avenue Des Muguets",
    "iso:country":"BE",
    "sg:address":"Avenue Des Muguets 24",
    "sg:city":"Braine L'alleud (braine-l'alleud)",
    "sg:classifiers":[
        {
            "category":"Professional",
            "subcategory":"Management & Consulting",
            "type":"Services"
        }
    ],
    "sg:phone":"+32 2 351 04 13",
    "sg:postcode":"1420",
    "sg:province":"Brabant Wallon",
    "sg:tags":[
        "consultant"
    ],
    "wof:name":"Macoserv Sprl",
    "wof:placetype":"venue"
},
  "geometry": {"coordinates":[-0.7004899979,47.369140625],"type":"Point"}
}