{
  "type": "Feature",
  "properties": {
    "iso:country":"BE",
    "sg:address":"Broekstraat 22",
    "sg:city":"Tervuren",
    "sg:classifiers":[
        {
            "category":"Building & Trades",
            "subcategory":"Construction",
            "type":"Services"
        }
    ],
    "sg:phone":"+32 2 767 41 08",
    "sg:postcode":"3080",
    "sg:province":"Vlaams-Brabant",
    "sg:tags":[
        "paper",
        "hanger"
    ],
    "wof:name":"Derom R",
    "wof:placetype":"venue"
},
  "geometry": {"coordinates":[4.510158062,50.8258514404],"type":"Point"}
}