{
  "type": "Feature",
  "properties": {
    "addr:full":"Blekerijstraat 82 Izegem West-Vlaanderen 8870",
    "addr:housenumber":"82",
    "addr:postcode":"8870",
    "addr:street":"Blekerijstraat",
    "iso:country":"BE",
    "sg:address":"Blekerijstraat 82",
    "sg:city":"Izegem",
    "sg:orig_category":"Installatie van houten of kunststof schrijnwerk",
    "sg:phone":"+32 51 30 34 49",
    "sg:postcode":"8870",
    "sg:province":"West-Vlaanderen",
    "wof:name":"Deveeuw",
    "wof:placetype":"venue"
},
  "geometry": {"coordinates":[3.2010309696,50.9046554565],"type":"Point"}
}