{
  "type": "Feature",
  "properties": {
    "addr:full":"Lode Zielenslaan 12 Wommelgem Antwerpen 2160",
    "addr:housenumber":"12",
    "addr:postcode":"2160",
    "addr:street":"Lode Zielenslaan",
    "iso:country":"BE",
    "sg:address":"Lode Zielenslaan 12",
    "sg:city":"Wommelgem",
    "sg:orig_category":"Services de Nettoyage and de D\u00e9sinfection",
    "sg:phone":"+32 3 353 41 73",
    "sg:postcode":"2160",
    "sg:province":"Antwerpen",
    "wof:name":"Het Ponske",
    "wof:placetype":"venue"
},
  "geometry": {"coordinates":[4.4924650192,51.2140083313],"type":"Point"}
}