{
  "type": "Feature",
  "properties": {
    "addr:full":"Oranjestraat 56 Scherpenheuvel-zichem Vlaams-Brabant 3271",
    "addr:housenumber":"56",
    "addr:postcode":"3271",
    "addr:street":"Oranjestraat",
    "iso:country":"BE",
    "sg:address":"Oranjestraat 56",
    "sg:city":"Scherpenheuvel-zichem",
    "sg:classifiers":[
        {
            "category":"Personal",
            "subcategory":"Beauty Salon",
            "type":"Services"
        }
    ],
    "sg:phone":"+32 13 78 39 68",
    "sg:postcode":"3271",
    "sg:province":"Vlaams-Brabant",
    "sg:tags":[
        "de",
        "coiffure"
    ],
    "wof:name":"Koen Rayen",
    "wof:placetype":"venue"
},
  "geometry": {"coordinates":[4.984495163,51.0000228882],"type":"Point"}
}