{
  "type": "Feature",
  "properties": {
    "addr:full":"Vredestraat 15 Beerse Antwerpen 2340",
    "addr:housenumber":"15",
    "addr:postcode":"2340",
    "addr:street":"Vredestraat",
    "iso:country":"BE",
    "sg:address":"Vredestraat 15",
    "sg:city":"Beerse",
    "sg:orig_category":"V\u00eatements pour b\u00e9b\u00e9s and enfants. Articles pour b\u00e9b\u00e9s",
    "sg:phone":"+32 14 61 20 11",
    "sg:postcode":"2340",
    "sg:province":"Antwerpen",
    "wof:name":"Katrin",
    "wof:placetype":"venue"
},
  "geometry": {"coordinates":[4.8570680618,51.3199310303],"type":"Point"}
}