{
  "type": "Feature",
  "properties": {
    "iso:country":"BE",
    "sg:address":"Wolfhaagweg 21",
    "sg:city":"Geetbets",
    "sg:classifiers":[
        {
            "category":"Utilities",
            "subcategory":"Natural Gas",
            "type":"Services"
        }
    ],
    "sg:phone":"+32 11 58 46 68",
    "sg:postcode":"3450",
    "sg:province":"Vlaams-Brabant",
    "sg:tags":[
        "blacksmith"
    ],
    "wof:name":"Isenborg",
    "wof:placetype":"venue"
},
  "geometry": {"coordinates":[5.0840702057,50.8972930908],"type":"Point"}
}