{
  "type": "Feature",
  "properties": {
    "iso:country":"BE",
    "sg:address":"Kruisweg 36",
    "sg:city":"Wuustwezel",
    "sg:orig_category":"Rundveehouders",
    "sg:phone":"+32 3 669 77 36",
    "sg:postcode":"2990",
    "sg:province":"Antwerpen",
    "wof:name":"Emiel Jacobs",
    "wof:placetype":"venue"
},
  "geometry": {"coordinates":[4.5989961624,51.4031333923],"type":"Point"}
}