{
  "type": "Feature",
  "properties": {
    "iso:country":"BE",
    "sg:address":"Rue De La Closi\u00c8re 12",
    "sg:city":"Wavre",
    "sg:orig_category":"Beschutte werkplaatsen",
    "sg:phone":"+32 10 41 53 87",
    "sg:postcode":"1300",
    "sg:province":"Brabant Wallon",
    "wof:name":"Atelier Prot\u00c9g\u00c9 Kennedy",
    "wof:placetype":"venue"
},
  "geometry": {"coordinates":[4.6116552353,50.7134132385],"type":"Point"}
}