{
  "type": "Feature",
  "properties": {
    "addr:full":"Het Wijngaardeke 62 De Pinte (zevergem) Oost-Vlaanderen 9840",
    "addr:housenumber":"62",
    "addr:postcode":"9840",
    "iso:country":"BE",
    "sg:address":"Het Wijngaardeke 62",
    "sg:city":"De Pinte (zevergem)",
    "sg:classifiers":[
        {
            "category":"Health Services",
            "subcategory":"Health Practitioner",
            "type":"Services"
        }
    ],
    "sg:phone":"+32 9 385 69 59",
    "sg:postcode":"9840",
    "sg:province":"Oost-Vlaanderen",
    "sg:tags":[
        "physiotherapist"
    ],
    "wof:name":"Guns An",
    "wof:placetype":"venue"
},
  "geometry": {"coordinates":[3.6970419884,50.9823074341],"type":"Point"}
}