{
  "type": "Feature",
  "properties": {
    "addr:full":"Avenue Eug\u00c8ne Mascaux 19 Charleroi Hainaut 6001",
    "addr:housenumber":"19",
    "addr:postcode":"6001",
    "addr:street":"Avenue Euge\u0300Ne Mascaux;Hainaut",
    "iso:country":"BE",
    "sg:address":"Avenue Eug\u00c8ne Mascaux 19",
    "sg:city":"Charleroi",
    "sg:orig_category":"Artsen and specialisten Medische and orthopedische apparaten",
    "sg:phone":"+32 71 47 19 12",
    "sg:postcode":"6001",
    "sg:province":"Hainaut",
    "wof:name":"Carolo C.t.o.",
    "wof:placetype":"venue"
},
  "geometry": {"coordinates":[4.4471321106,50.3992881775],"type":"Point"}
}