{
  "type": "Feature",
  "properties": {
    "addr:full":"Vieux Chemin Du Poete 60 Wavre Brabant Wallon 1301",
    "addr:housenumber":"60;1301",
    "addr:street":"Vieux Chemin Du Poete",
    "iso:country":"BE",
    "sg:address":"Vieux Chemin Du Poete 60",
    "sg:city":"Wavre",
    "sg:orig_category":"Tuinen",
    "sg:phone":"+32 10 41 00 85",
    "sg:postcode":"1301",
    "sg:province":"Brabant Wallon",
    "wof:name":"Patrick Anciaux Henry De Faveaux",
    "wof:placetype":"venue"
},
  "geometry": {"coordinates":[4.5778841972,50.7053070068],"type":"Point"}
}