{
  "type": "Feature",
  "properties": {
    "addr:full":"Rosmolenstraat Roeselare (oekene) West-Vlaanderen 8800",
    "addr:postcode":"8800",
    "addr:street":"Rosmolenstraat",
    "iso:country":"BE",
    "sg:address":"Rosmolenstraat",
    "sg:city":"Roeselare (oekene)",
    "sg:classifiers":[
        {
            "category":"Parking",
            "subcategory":"Lot",
            "type":"Transportation"
        }
    ],
    "sg:phone":"+32 51 25 15 69",
    "sg:postcode":"8800",
    "sg:province":"West-Vlaanderen",
    "sg:tags":[
        "parking-places",
        "laying-out"
    ],
    "wof:name":"Vanmoerkerke Ph",
    "wof:placetype":"venue"
},
  "geometry": {"coordinates":[3.1230149269,50.9443435669],"type":"Point"}
}