{
  "type": "Feature",
  "properties": {
    "addr:full":"Rue Du Ch\u00c2teau-ferme 12 Onhaye Namur 5522",
    "addr:housenumber":"12",
    "addr:postcode":"5522",
    "addr:street":"Rue Du Cha\u0302Teau-Ferme",
    "iso:country":"BE",
    "sg:address":"Rue Du Ch\u00c2teau-ferme 12",
    "sg:city":"Onhaye",
    "sg:orig_category":"Antiek",
    "sg:phone":"+32 82 69 95 08",
    "sg:postcode":"5522",
    "sg:province":"Namur",
    "wof:name":"La Doy\u00c8re",
    "wof:placetype":"venue"
},
  "geometry": {"coordinates":[4.7961750031,50.2784347534],"type":"Point"}
}