{
  "type": "Feature",
  "properties": {
    "iso:country":"BE",
    "sg:address":"Route De March\u00c9 16",
    "sg:city":"Ferri\u00c8res",
    "sg:orig_category":"Entretien et r\u00e9parations de v\u00e9hicules \u00e0 domicile",
    "sg:phone":"+32 4 369 14 88",
    "sg:postcode":"4190",
    "sg:province":"Li\u00e8ge",
    "wof:name":"Fe. Du Bati",
    "wof:placetype":"venue"
},
  "geometry": {"coordinates":[5.6169781685,50.4399490356],"type":"Point"}
}