{
  "type": "Feature",
  "properties": {
    "addr:full":"Chauss\u00c9e De Charleroi 16 Namen (groot) Namur 5000",
    "addr:housenumber":"16",
    "addr:postcode":"5000",
    "addr:street":"Chausse\u0301E De Charleroi;Groot Namur",
    "iso:country":"BE",
    "sg:address":"Chauss\u00c9e De Charleroi 16",
    "sg:city":"Namen (groot)",
    "sg:orig_category":"Supermarch\u00e9s",
    "sg:phone":"+32 81 73 74 64",
    "sg:postcode":"5000",
    "sg:province":"Namur",
    "wof:name":"Colruyt",
    "wof:placetype":"venue"
},
  "geometry": {"coordinates":[4.8422298431,50.4626808167],"type":"Point"}
}