{
  "type": "Feature",
  "properties": {
    "iso:country":"BE",
    "sg:address":"Bedrijfsstraat 26",
    "sg:city":"Hasselt",
    "sg:orig_category":"Installatie van houten of kunststof schrijnwerk Installatie van metalen schrijnwerk",
    "sg:phone":"+32 11 21 06 99",
    "sg:postcode":"3500",
    "sg:province":"Limburg",
    "wof:name":"Steegmans Konstruktie",
    "wof:placetype":"venue"
},
  "geometry": {"coordinates":[5.3630819321,50.9544143677],"type":"Point"}
}