{
  "type": "Feature",
  "properties": {
    "addr:full":"Kwalestraat 43 Erpe-mere Oost-Vlaanderen 9420",
    "addr:housenumber":"43",
    "addr:postcode":"9420",
    "addr:street":"Kwalestraat",
    "iso:country":"BE",
    "sg:address":"Kwalestraat 43",
    "sg:city":"Erpe-mere",
    "sg:orig_category":"Banques and organismes de cr\u00e9dit",
    "sg:phone":"+32 53 62 63 85",
    "sg:postcode":"9420",
    "sg:province":"Oost-Vlaanderen",
    "wof:name":"Landbouwkrediet",
    "wof:placetype":"venue"
},
  "geometry": {"coordinates":[3.9347081184,50.914024353],"type":"Point"}
}