{
  "type": "Feature",
  "properties": {
    "addr:full":"Place De L'h\u00f4tel De Ville 2 Gembloux-sur-orneau (gembloux) Namur 5030",
    "addr:housenumber":"2",
    "addr:postcode":"5030",
    "addr:street":"Place De L'Ho \u0302Tel De Ville;Namur",
    "iso:country":"BE",
    "sg:address":"Place De L'h\u00f4tel De Ville 2",
    "sg:city":"Gembloux-sur-orneau (gembloux)",
    "sg:classifiers":[
        {
            "category":"Bars & Pubs",
            "type":"Food & Drink"
        }
    ],
    "sg:phone":"+32 81 61 57 78",
    "sg:postcode":"5030",
    "sg:province":"Namur",
    "wof:name":"Agora",
    "wof:placetype":"venue"
},
  "geometry": {"coordinates":[4.6945400238,50.5666313171],"type":"Point"}
}