{
  "type": "Feature",
  "properties": {
    "addr:full":"Almache 4 Paliseul (nollevaux) Luxembourg 6851",
    "addr:housenumber":"4",
    "addr:postcode":"6851",
    "addr:street":"Almache",
    "iso:country":"BE",
    "sg:address":"Almache 4",
    "sg:city":"Paliseul (nollevaux)",
    "sg:classifiers":[
        {
            "category":"Building & Trades",
            "subcategory":"Landscaping Services",
            "type":"Services"
        }
    ],
    "sg:phone":"+32 61 53 38 00",
    "sg:postcode":"6851",
    "sg:province":"Luxembourg",
    "sg:tags":[
        "forestry"
    ],
    "wof:name":"Pirot Sprl",
    "wof:placetype":"venue"
},
  "geometry": {"coordinates":[5.1208949089,49.8696746826],"type":"Point"}
}