{
  "type": "Feature",
  "properties": {
    "addr:full":"Chauss\u00e9e De Lille 4 Tournai Hainaut 7500",
    "addr:housenumber":"4",
    "addr:postcode":"7500",
    "addr:street":"Chausse\u0301E De Lille",
    "iso:country":"BE",
    "sg:address":"Chauss\u00e9e De Lille 4",
    "sg:city":"Tournai",
    "sg:classifiers":[
        {
            "category":"Communications",
            "subcategory":"Film & Video Production",
            "type":"Services"
        }
    ],
    "sg:phone":"+32 69 84 34 65",
    "sg:postcode":"7500",
    "sg:province":"Hainaut",
    "sg:tags":[
        "hiring",
        "-"
    ],
    "wof:name":"Brother's Video",
    "wof:placetype":"venue"
},
  "geometry": {"coordinates":[3.3762209415,50.6052207947],"type":"Point"}
}