{
  "type": "Feature",
  "properties": {
    "iso:country":"BE",
    "sg:address":"Sint-amandsstraat 123",
    "sg:city":"Grimbergen",
    "sg:orig_category":"Eclairage et \u00e9quipements du foyer. Rev\u00eatements pour sols and murs. Peinture",
    "sg:phone":"+32 2 261 05 35",
    "sg:postcode":"1853",
    "sg:province":"Vlaams-Brabant",
    "wof:name":"Eric Appelmans",
    "wof:placetype":"venue"
},
  "geometry": {"coordinates":[4.3604478836,50.9055862427],"type":"Point"}
}