{
  "type": "Feature",
  "properties": {
    "addr:full":"Koolskampstraat 33a Torhout West-Vlaanderen 8820",
    "addr:housenumber":"33a",
    "addr:postcode":"8820",
    "addr:street":"Koolskampstraat",
    "iso:country":"BE",
    "sg:address":"Koolskampstraat 33a",
    "sg:city":"Torhout",
    "sg:classifiers":[
        {
            "category":"Building & Trades",
            "subcategory":"Electrical",
            "type":"Services"
        }
    ],
    "sg:phone":"+32 50 21 44 74",
    "sg:postcode":"8820",
    "sg:province":"West-Vlaanderen",
    "sg:tags":[
        "tool",
        "electric"
    ],
    "wof:name":"Tormetal-heynderick Koenraad Bvba",
    "wof:placetype":"venue"
},
  "geometry": {"coordinates":[3.1163721085,51.0527763367],"type":"Point"}
}