{
  "type": "Feature",
  "properties": {
    "addr:full":"Hauptstrasse 37 Sankt Vith/saint-vith Li\u00e8ge 4780",
    "addr:housenumber":"37",
    "addr:postcode":"4780",
    "addr:street":"Hauptstrasse",
    "iso:country":"BE",
    "sg:address":"Hauptstrasse 37",
    "sg:city":"Sankt Vith/saint-vith",
    "sg:classifiers":[
        {
            "category":"Wholesale",
            "subcategory":"Sporting Goods",
            "type":"Manufacturing & Wholesale Goods"
        }
    ],
    "sg:phone":"+32 80 22 61 05",
    "sg:postcode":"4780",
    "sg:province":"Li\u00e8ge",
    "sg:tags":[
        "sport-",
        "kampeermateriaal"
    ],
    "wof:name":"Maison Sport 3000",
    "wof:placetype":"venue"
},
  "geometry": {"coordinates":[6.0429549217,50.3349761963],"type":"Point"}
}