{
  "type": "Feature",
  "properties": {
    "addr:full":"Poekestraat 23 Aalter Oost-Vlaanderen 9880",
    "addr:housenumber":"23",
    "addr:postcode":"9880",
    "addr:street":"Poekestraat",
    "iso:country":"BE",
    "sg:address":"Poekestraat 23",
    "sg:city":"Aalter",
    "sg:classifiers":[
        {
            "category":"Insurance",
            "subcategory":"Life Insurance",
            "type":"Services"
        }
    ],
    "sg:phone":"+32 51 68 76 87",
    "sg:postcode":"9880",
    "sg:province":"Oost-Vlaanderen",
    "sg:tags":[
        "assurance"
    ],
    "wof:name":"Wyckhuys Laurent",
    "wof:placetype":"venue"
},
  "geometry": {"coordinates":[3.4581460953,51.0467224121],"type":"Point"}
}