{
  "type": "Feature",
  "properties": {
    "iso:country":"BE",
    "sg:address":"Kerkhofdries 2",
    "sg:city":"Sint-amands",
    "sg:classifiers":[
        {
            "category":"Health Services",
            "subcategory":"Dentist",
            "type":"Services"
        }
    ],
    "sg:phone":"+32 52 33 08 17",
    "sg:postcode":"2890",
    "sg:province":"Antwerpen",
    "wof:name":"De Saeger Martine",
    "wof:placetype":"venue"
},
  "geometry": {"coordinates":[4.2051730156,51.0557022095],"type":"Point"}
}