{
  "type": "Feature",
  "properties": {
    "addr:full":"Rozendalestraat 0 Wingene West-Vlaanderen 8750",
    "addr:housenumber":"0",
    "addr:postcode":"8750",
    "addr:street":"Rozendalestraat",
    "iso:country":"BE",
    "sg:address":"Rozendalestraat 0",
    "sg:city":"Wingene",
    "sg:orig_category":"Beheer van afvalopslag- and stortplaatsen",
    "sg:phone":"+32 51 65 70 71",
    "sg:postcode":"8750",
    "sg:province":"West-Vlaanderen",
    "wof:name":"Containerpark Wingene",
    "wof:placetype":"venue"
},
  "geometry": {"coordinates":[3.2594769001,51.0695075989],"type":"Point"}
}