{
  "type": "Feature",
  "properties": {
    "iso:country":"BE",
    "sg:address":"Place Du March\u00e9 6",
    "sg:city":"Saint-hubert",
    "sg:classifiers":[
        {
            "category":"Bakery",
            "type":"Food & Drink"
        }
    ],
    "sg:phone":"+32 61 61 23 73",
    "sg:postcode":"6870",
    "sg:province":"Luxembourg",
    "sg:tags":[
        "confectioner",
        "baker"
    ],
    "wof:name":"Arnould P\u00e2tisserie",
    "wof:placetype":"venue"
},
  "geometry": {"coordinates":[5.3732638359,50.025478363],"type":"Point"}
}