{
  "type": "Feature",
  "properties": {
    "iso:country":"BE",
    "sg:address":"Scheldestraat 16",
    "sg:city":"Zwalm",
    "sg:classifiers":[
        {
            "category":"Personal",
            "subcategory":"Beauty Salon",
            "type":"Services"
        }
    ],
    "sg:phone":"+32 55 49 66 68",
    "sg:postcode":"9636",
    "sg:province":"Oost-Vlaanderen",
    "sg:tags":[
        "de",
        "coiffure"
    ],
    "wof:name":"Ann De Meyer",
    "wof:placetype":"venue"
},
  "geometry": {"coordinates":[3.6854660511,50.8924636841],"type":"Point"}
}