{
  "type": "Feature",
  "properties": {
    "iso:country":"BE",
    "sg:address":"Waterloose Steenweg 1334",
    "sg:city":"Ukkel/uccle",
    "sg:orig_category":"Bagage and lederwaren Dameskledingzaken Herenkledingzaken",
    "sg:phone":"+32 2 375 35 16",
    "sg:postcode":"1180",
    "sg:province":"Bruxelles-Capitale",
    "wof:name":"Maison Prince Of Wales",
    "wof:placetype":"venue"
},
  "geometry": {"coordinates":[4.3751211166,50.7902069092],"type":"Point"}
}