{
  "type": "Feature",
  "properties": {
    "addr:full":"Rodtstraat 0 Lede Oost-Vlaanderen 9340",
    "addr:housenumber":"0",
    "addr:postcode":"9340",
    "addr:street":"Rodtstraat",
    "iso:country":"BE",
    "sg:address":"Rodtstraat 0",
    "sg:city":"Lede",
    "sg:orig_category":"Travail and traitement du bois",
    "sg:phone":"+32 9 369 78 75",
    "sg:postcode":"9340",
    "sg:province":"Oost-Vlaanderen",
    "wof:name":"Meuleman M.",
    "wof:placetype":"venue"
},
  "geometry": {"coordinates":[3.9040169716,50.9607810974],"type":"Point"}
}