{
  "type": "Feature",
  "properties": {
    "iso:country":"BE",
    "sg:address":"Rue De L'eglise 20",
    "sg:city":"Juprelle",
    "sg:orig_category":"Werk and personeelsselectie",
    "sg:phone":"+32 4 278 75 60",
    "sg:postcode":"4450",
    "sg:province":"Li\u00e8ge",
    "wof:name":"Ale Juprelle",
    "wof:placetype":"venue"
},
  "geometry": {"coordinates":[5.5815691948,50.6424980164],"type":"Point"}
}