{
  "type": "Feature",
  "properties": {
    "addr:full":"Rue De La Ville 12 Couvin Namur 5660",
    "addr:housenumber":"12",
    "addr:postcode":"5660",
    "addr:street":"Rue De La Ville",
    "iso:country":"BE",
    "sg:address":"Rue De La Ville 12",
    "sg:city":"Couvin",
    "sg:classifiers":[
        {
            "category":"Insurance",
            "subcategory":"Insurance Agent",
            "type":"Services"
        }
    ],
    "sg:phone":"+32 60 34 44 89",
    "sg:postcode":"5660",
    "sg:province":"Namur",
    "sg:tags":[
        "verzekeringsmakelaars",
        "expert"
    ],
    "wof:name":"Comptoir G\u00c9n\u00c9ral D'assurances Garcia",
    "wof:placetype":"venue"
},
  "geometry": {"coordinates":[4.4961900711,50.0521278381],"type":"Point"}
}