{
  "type": "Feature",
  "properties": {
    "addr:full":"Albert Servaeslaan 48ba Waregem West-Vlaanderen 8790",
    "addr:housenumber":"48ba",
    "addr:postcode":"8790",
    "addr:street":"Albert Servaeslaan",
    "iso:country":"BE",
    "sg:address":"Albert Servaeslaan 48ba",
    "sg:city":"Waregem",
    "sg:orig_category":"Epiceries",
    "sg:phone":"+32 56 60 53 75",
    "sg:postcode":"8790",
    "sg:province":"West-Vlaanderen",
    "wof:name":"Spar",
    "wof:placetype":"venue"
},
  "geometry": {"coordinates":[3.4421670437,50.8933105469],"type":"Point"}
}