{
  "type": "Feature",
  "properties": {
    "addr:full":"Driesstraat 12 Bornem Antwerpen 2880",
    "addr:housenumber":"12",
    "addr:postcode":"2880",
    "addr:street":"Driesstraat",
    "iso:country":"BE",
    "sg:address":"Driesstraat 12",
    "sg:city":"Bornem",
    "sg:classifiers":[
        {
            "category":"Education",
            "subcategory":"School",
            "type":"Public Place"
        }
    ],
    "sg:phone":"+32 3 889 44 26",
    "sg:postcode":"2880",
    "sg:province":"Antwerpen",
    "sg:tags":[
        "primary"
    ],
    "wof:name":"Onze Lieve Vrouw Presentatie",
    "wof:placetype":"venue"
},
  "geometry": {"coordinates":[4.237019062,51.1000938416],"type":"Point"}
}