{
  "type": "Feature",
  "properties": {
    "iso:country":"BE",
    "sg:address":"Melkerijstraat 20",
    "sg:city":"Nevele",
    "sg:orig_category":"Kapsalons",
    "sg:phone":"+32 9 371 66 45",
    "sg:postcode":"9850",
    "sg:province":"Oost-Vlaanderen",
    "wof:name":"Coiffure Marian",
    "wof:placetype":"venue"
},
  "geometry": {"coordinates":[3.5341410637,51.0749435425],"type":"Point"}
}