{
  "type": "Feature",
  "properties": {
    "addr:full":"Berckhovenstraat 6 Malle (westmalle) Antwerpen 2390",
    "addr:housenumber":"6",
    "addr:postcode":"2390",
    "addr:street":"Berckhovenstraat",
    "iso:country":"BE",
    "sg:address":"Berckhovenstraat 6",
    "sg:city":"Malle (westmalle)",
    "sg:orig_category":"Solariums",
    "sg:phone":"+32 3 309 93 86",
    "sg:postcode":"2390",
    "sg:province":"Antwerpen",
    "wof:name":"Sunbody",
    "wof:placetype":"venue"
},
  "geometry": {"coordinates":[4.6965560913,51.2982025146],"type":"Point"}
}