{
  "type": "Feature",
  "properties": {
    "iso:country":"BE",
    "sg:address":"Diesterstraat 26",
    "sg:city":"Tessenderlo",
    "sg:orig_category":"Banken and kredietinstellingen",
    "sg:phone":"+32 13 67 29 00",
    "sg:postcode":"3980",
    "sg:province":"Limburg",
    "wof:name":"Centea",
    "wof:placetype":"venue"
},
  "geometry": {"coordinates":[5.087679863,51.0661010742],"type":"Point"}
}