{
  "type": "Feature",
  "properties": {
    "addr:full":"Gasthuisstraat 46 Poperinge West-Vlaanderen 8970",
    "addr:housenumber":"46",
    "addr:postcode":"8970",
    "addr:street":"Gasthuisstraat",
    "iso:country":"BE",
    "sg:address":"Gasthuisstraat 46",
    "sg:city":"Poperinge",
    "sg:orig_category":"V\u00eatements pour b\u00e9b\u00e9s and enfants. V\u00eatements pour Dames. Articles pour b\u00e9b\u00e9s",
    "sg:phone":"+32 57 33 75 12",
    "sg:postcode":"8970",
    "sg:province":"West-Vlaanderen",
    "wof:name":"Pr\u00c9maman",
    "wof:placetype":"venue"
},
  "geometry": {"coordinates":[2.7231099606,50.8556480408],"type":"Point"}
}