{
  "type": "Feature",
  "properties": {
    "iso:country":"BE",
    "sg:address":"Rue De La Fusee 60",
    "sg:city":"Bruxelles",
    "sg:classifiers":[
        {
            "category":"Utilities",
            "subcategory":"Water",
            "type":"Services"
        }
    ],
    "sg:phone":"+32 70 22 56 45",
    "sg:postcode":"1130",
    "sg:province":"Bruxelles-Capitale",
    "sg:tags":[
        "filter",
        "treatment"
    ],
    "wof:name":"Millipore S.a.",
    "wof:placetype":"venue"
},
  "geometry": {"coordinates":[4.4193868637,50.8776702881],"type":"Point"}
}