{
  "type": "Feature",
  "properties": {
    "addr:full":"Rue Des Fr\u00e8res Verkleeren 28 Tubize (saintes) Brabant Wallon 1480",
    "addr:housenumber":"28",
    "addr:postcode":"1480",
    "addr:street":"Rue Des Fre\u0300Res Verkleeren",
    "iso:country":"BE",
    "sg:address":"Rue Des Fr\u00e8res Verkleeren 28",
    "sg:city":"Tubize (saintes)",
    "sg:classifiers":[
        {
            "category":"Professional",
            "subcategory":"Management & Consulting",
            "type":"Services"
        }
    ],
    "sg:phone":"+32 2 355 11 89",
    "sg:postcode":"1480",
    "sg:province":"Brabant Wallon",
    "sg:tags":[
        "consultant"
    ],
    "wof:name":"Field Human Consult",
    "wof:placetype":"venue"
},
  "geometry": {"coordinates":[4.1652550697,50.6993789673],"type":"Point"}
}