{
  "type": "Feature",
  "properties": {
    "iso:country":"BE",
    "sg:address":"Nieuwpoortsesteenweg 66",
    "sg:city":"Oostende",
    "sg:orig_category":"Non-Classified Establishments",
    "sg:phone":"+32 59 70 30 36",
    "sg:postcode":"8400",
    "sg:province":"West-Vlaanderen",
    "wof:name":"Vanslembrouck (firma)",
    "wof:placetype":"venue"
},
  "geometry": {"coordinates":[2.9058980942,51.223236084],"type":"Point"}
}