{
  "type": "Feature",
  "properties": {
    "addr:full":"Noordzeestraat 25 Oostende West-Vlaanderen 8400",
    "addr:housenumber":"25",
    "addr:postcode":"8400",
    "addr:street":"Noordzeestraat",
    "iso:country":"BE",
    "sg:address":"Noordzeestraat 25",
    "sg:city":"Oostende",
    "sg:orig_category":"Paramedische behandelingen",
    "sg:phone":"+32 59 33 05 26",
    "sg:postcode":"8400",
    "sg:province":"West-Vlaanderen",
    "wof:name":"V. Janssens",
    "wof:placetype":"venue"
},
  "geometry": {"coordinates":[2.9126999378,51.2312583923],"type":"Point"}
}