{
  "type": "Feature",
  "properties": {
    "iso:country":"BE",
    "sg:address":"Rue Le Marais 7",
    "sg:city":"Villers-le-bouillet",
    "sg:classifiers":[
        {
            "category":"Professional",
            "subcategory":"Lawyer & Legal Services",
            "type":"Services"
        }
    ],
    "sg:phone":"+32 85 21 43 15",
    "sg:postcode":"4530",
    "sg:province":"Li\u00e8ge",
    "sg:tags":[
        "notary"
    ],
    "wof:name":"Garsou Chr",
    "wof:placetype":"venue"
},
  "geometry": {"coordinates":[5.2633728981,50.5775871277],"type":"Point"}
}