{
  "type": "Feature",
  "properties": {
    "iso:country":"BE",
    "sg:address":"Groenlarenstraat 1",
    "sg:city":"Lummen",
    "sg:orig_category":"Caf\u00e9s. Cr\u00e9meries",
    "sg:phone":"+32 11 42 53 21",
    "sg:postcode":"3560",
    "sg:province":"Limburg",
    "wof:name":"Gilberte Houben",
    "wof:placetype":"venue"
},
  "geometry": {"coordinates":[5.1989598274,51.0079498291],"type":"Point"}
}