{
  "type": "Feature",
  "properties": {
    "iso:country":"BE",
    "sg:address":"Hoogkamerstraat 13",
    "sg:city":"Sint-niklaas",
    "sg:orig_category":"Industri\u00eble and commerci\u00eble bouw Woningbouw",
    "sg:phone":"+32 3 776 70 04",
    "sg:postcode":"9100",
    "sg:province":"Oost-Vlaanderen",
    "wof:name":"Van Laere Gustaaf",
    "wof:placetype":"venue"
},
  "geometry": {"coordinates":[4.1815810204,51.1446113586],"type":"Point"}
}