{
  "type": "Feature",
  "properties": {
    "addr:full":"Place De Molenbaix 42 Celles Hainaut 7760",
    "addr:housenumber":"42",
    "addr:postcode":"7760",
    "addr:street":"Place De Molenbaix",
    "iso:country":"BE",
    "sg:address":"Place De Molenbaix 42",
    "sg:city":"Celles",
    "sg:orig_category":"Installatie van houten of kunststof schrijnwerk",
    "sg:phone":"+32 69 45 61 19",
    "sg:postcode":"7760",
    "sg:province":"Hainaut",
    "wof:name":"Delenin",
    "wof:placetype":"venue"
},
  "geometry": {"coordinates":[3.4301600456,50.6927490234],"type":"Point"}
}