{
  "type": "Feature",
  "properties": {
    "iso:country":"BE",
    "sg:address":"Kwaplasstraat 56",
    "sg:city":"Torhout",
    "sg:orig_category":"Woningbouw",
    "sg:phone":"+32 50 21 56 95",
    "sg:postcode":"8820",
    "sg:province":"West-Vlaanderen",
    "wof:name":"Danny Rogiers",
    "wof:placetype":"venue"
},
  "geometry": {"coordinates":[3.1215291023,51.0584144592],"type":"Point"}
}