{
  "type": "Feature",
  "properties": {
    "iso:country":"BE",
    "sg:address":"Hertevelden 17",
    "sg:city":"Arendonk",
    "sg:classifiers":[
        {
            "category":"Professional",
            "subcategory":"Art Services",
            "type":"Services"
        }
    ],
    "sg:phone":"+32 14 68 70 44",
    "sg:postcode":"2370",
    "sg:province":"Antwerpen",
    "sg:tags":[
        "photographer"
    ],
    "wof:name":"Nijsmans Sophie",
    "wof:placetype":"venue"
},
  "geometry": {"coordinates":[5.0915298462,51.3128700256],"type":"Point"}
}