{
  "type": "Feature",
  "properties": {
    "addr:full":"Chauss\u00c9e De Thuin 62 Anderlues Hainaut 6150",
    "addr:housenumber":"62",
    "addr:postcode":"6150",
    "addr:street":"Chausse\u0301E De Thuin",
    "iso:country":"BE",
    "sg:address":"Chauss\u00c9e De Thuin 62",
    "sg:city":"Anderlues",
    "sg:classifiers":[
        {
            "category":"Taxi",
            "type":"Transportation"
        }
    ],
    "sg:phone":"+32 71 52 87 26",
    "sg:postcode":"6150",
    "sg:province":"Hainaut",
    "sg:tags":[
        "sp\u00e9ciaux"
    ],
    "wof:name":"Jacques Cortembos",
    "wof:placetype":"venue"
},
  "geometry": {"coordinates":[4.2869257927,50.403137207],"type":"Point"}
}