{
  "type": "Feature",
  "properties": {
    "iso:country":"BE",
    "sg:address":"Rue De Fexhe Slins 108",
    "sg:city":"Oupeye",
    "sg:orig_category":"Gespecialiseerde residenti\u00eble bouw Installatie van metalen schrijnwerk SMEEDWERK, METAALBEWERKING AN",
    "sg:phone":"+32 4 278 27 42",
    "sg:postcode":"4680",
    "sg:province":"Li\u00e8ge",
    "wof:name":"Zannelli",
    "wof:placetype":"venue"
},
  "geometry": {"coordinates":[5.6444120407,50.7089729309],"type":"Point"}
}