{
  "type": "Feature",
  "properties": {
    "iso:country":"BE",
    "sg:address":"Hoogveld 1",
    "sg:city":"Avelgem",
    "sg:orig_category":"M\u00e9decins and sp\u00e9cialistes",
    "sg:phone":"+32 56 64 57 85",
    "sg:postcode":"8580",
    "sg:province":"West-Vlaanderen",
    "wof:name":"Erik Vandereecken",
    "wof:placetype":"venue"
},
  "geometry": {"coordinates":[3.4341440201,50.7766418457],"type":"Point"}
}