{
  "type": "Feature",
  "properties": {
    "iso:country":"BE",
    "sg:address":"Tiensesteenweg 34",
    "sg:city":"Tielt-winge",
    "sg:orig_category":"Epiceries",
    "sg:phone":"+32 16 63 41 94",
    "sg:postcode":"3390",
    "sg:province":"Vlaams-Brabant",
    "wof:name":"Spar",
    "wof:placetype":"venue"
},
  "geometry": {"coordinates":[4.8767971992,50.9052810669],"type":"Point"}
}