{
  "type": "Feature",
  "properties": {
    "iso:country":"BE",
    "sg:address":"Papenbruggestraat 82 Box 1",
    "sg:city":"Turnhout",
    "sg:classifiers":[
        {
            "category":"Professional",
            "subcategory":"Credit Reporting & Collection",
            "type":"Services"
        }
    ],
    "sg:phone":"+32 14 43 52 00",
    "sg:postcode":"2300",
    "sg:province":"Antwerpen",
    "sg:tags":[
        "bailiff"
    ],
    "wof:name":"Deckmyn W",
    "wof:placetype":"venue"
},
  "geometry": {"coordinates":[4.9446568489,51.313293457],"type":"Point"}
}