{
  "type": "Feature",
  "properties": {
    "addr:full":"Hogeweg 156 Geraardsbergen Oost-Vlaanderen 9500",
    "addr:housenumber":"156",
    "addr:postcode":"9500",
    "addr:street":"Hogeweg",
    "iso:country":"BE",
    "sg:address":"Hogeweg 156",
    "sg:city":"Geraardsbergen",
    "sg:orig_category":"Orphelinats. Instituts pour enfants en difficult\u00e9",
    "sg:phone":"+32 54 41 26 68",
    "sg:postcode":"9500",
    "sg:province":"Oost-Vlaanderen",
    "wof:name":"Home Magnolia I",
    "wof:placetype":"venue"
},
  "geometry": {"coordinates":[3.8589830399,50.7648773193],"type":"Point"}
}