{
  "type": "Feature",
  "properties": {
    "iso:country":"BE",
    "sg:address":"Regentieplein 1",
    "sg:city":"Sint-niklaas",
    "sg:orig_category":"Quincailleries. Drogueries. Art and fournitures artistiques",
    "sg:phone":"+32 3 776 14 28",
    "sg:postcode":"9100",
    "sg:province":"Oost-Vlaanderen",
    "wof:name":"Goderis Drogisterij",
    "wof:placetype":"venue"
},
  "geometry": {"coordinates":[4.1449098587,51.1680412292],"type":"Point"}
}