{
  "type": "Feature",
  "properties": {
    "addr:full":"Zelebaan 63 Lokeren Oost-Vlaanderen 9160",
    "addr:housenumber":"63",
    "addr:postcode":"9160",
    "addr:street":"Zelebaan",
    "iso:country":"BE",
    "sg:address":"Zelebaan 63",
    "sg:city":"Lokeren",
    "sg:orig_category":"Eclairage et \u00e9quipements du foyer. Electrom\u00e9nager, t\u00e9l\u00e9visions and radios. Jeux and jouets",
    "sg:phone":"+32 9 348 89 13",
    "sg:postcode":"9160",
    "sg:province":"Oost-Vlaanderen",
    "wof:name":"Blokker",
    "wof:placetype":"venue"
},
  "geometry": {"coordinates":[4.0147719383,51.0928573608],"type":"Point"}
}