{
  "type": "Feature",
  "properties": {
    "addr:full":"Muinklaan 12 Gent-centrum Oost-Vlaanderen 9000",
    "addr:housenumber":"12",
    "addr:postcode":"9000",
    "addr:street":"Muinklaan;Oost-Vlaanderen",
    "iso:country":"BE",
    "sg:address":"Muinklaan 12",
    "sg:city":"Gent-centrum",
    "sg:orig_category":"Balie van Gent. Avocats and conseillers juridiques. Avocats and conseillers juridiques",
    "sg:phone":"+32 9 224 11 34",
    "sg:postcode":"9000",
    "sg:province":"Oost-Vlaanderen",
    "wof:name":"Neels Dirk",
    "wof:placetype":"venue"
},
  "geometry": {"coordinates":[3.7290608883,51.046459198],"type":"Point"}
}