{
  "type": "Feature",
  "properties": {
    "addr:full":"Gentsesteenweg 119 Harelbeke West-Vlaanderen 8530",
    "addr:housenumber":"119",
    "addr:postcode":"8530",
    "addr:street":"Gentsesteenweg",
    "iso:country":"BE",
    "sg:address":"Gentsesteenweg 119",
    "sg:city":"Harelbeke",
    "sg:orig_category":"Traitements param\u00e9dicaux",
    "sg:phone":"+32 56 72 42 48",
    "sg:postcode":"8530",
    "sg:province":"West-Vlaanderen",
    "wof:name":"Maaike Depoortere",
    "wof:placetype":"venue"
},
  "geometry": {"coordinates":[3.3285059929,50.8654785156],"type":"Point"}
}