{
  "type": "Feature",
  "properties": {
    "addr:full":"Strijdersstraat 35 Tienen Vlaams-Brabant 3300",
    "addr:housenumber":"35",
    "addr:postcode":"3300",
    "addr:street":"Strijdersstraat",
    "iso:country":"BE",
    "sg:address":"Strijdersstraat 35",
    "sg:city":"Tienen",
    "sg:orig_category":"Producteurs de fruits",
    "sg:phone":"+32 16 81 66 05",
    "sg:postcode":"3300",
    "sg:province":"Vlaams-Brabant",
    "wof:name":"Gebroeders Vanherwegen",
    "wof:placetype":"venue"
},
  "geometry": {"coordinates":[4.9381642342,50.811252594],"type":"Point"}
}