{
  "type": "Feature",
  "properties": {
    "iso:country":"BE",
    "sg:address":"Erasmuslaan 14",
    "sg:city":"Hasselt",
    "sg:classifiers":[
        {
            "category":"Social Services",
            "subcategory":"Child Care",
            "type":"Services"
        }
    ],
    "sg:phone":"+32 11 21 21 15",
    "sg:postcode":"3500",
    "sg:province":"Limburg",
    "sg:tags":[
        "baby",
        "nursery",
        "day",
        "sitting"
    ],
    "wof:name":"Ukkies (de)",
    "wof:placetype":"venue"
},
  "geometry": {"coordinates":[5.3525547981,50.9493637085],"type":"Point"}
}