{
  "type": "Feature",
  "properties": {
    "addr:full":"Rue Des Glands 21 Vorst/forest Bruxelles-Capitale 1190",
    "addr:housenumber":"21",
    "addr:postcode":"1190",
    "addr:street":"Rue Des Glands;/ Forest",
    "iso:country":"BE",
    "sg:address":"Rue Des Glands 21",
    "sg:city":"Vorst/forest",
    "sg:orig_category":"Architectes",
    "sg:phone":"+32 2 345 88 18",
    "sg:postcode":"1190",
    "sg:province":"Bruxelles-Capitale",
    "wof:name":"Van Baren D",
    "wof:placetype":"venue"
},
  "geometry": {"coordinates":[4.3265810013,50.8198547363],"type":"Point"}
}