{
  "type": "Feature",
  "properties": {
    "iso:country":"BE",
    "sg:address":"460 Ch De Mons",
    "sg:city":"Bruxelles",
    "sg:classifiers":[
        {
            "category":"Autos & Motor Vehicles",
            "subcategory":"Automobile Sales",
            "type":"Retail Goods"
        }
    ],
    "sg:phone":"+32 2 522 97 07",
    "sg:postcode":"1070",
    "sg:province":"Bruxelles-Capitale",
    "sg:tags":[
        "equipment",
        "transport"
    ],
    "wof:name":"Recup Moto Fun Sprl",
    "wof:placetype":"venue"
},
  "geometry": {"coordinates":[4.2889780998,50.8081893921],"type":"Point"}
}