{
  "type": "Feature",
  "properties": {
    "iso:country":"BE",
    "sg:address":"Cooppallaan 128",
    "sg:city":"Wetteren",
    "sg:orig_category":"Sportcentra",
    "sg:phone":"+32 9 369 79 80",
    "sg:postcode":"9230",
    "sg:province":"Oost-Vlaanderen",
    "wof:name":"Sportzaal Inst. Scheppers",
    "wof:placetype":"venue"
},
  "geometry": {"coordinates":[3.8700549603,51.0088882446],"type":"Point"}
}