{
  "type": "Feature",
  "properties": {
    "iso:country":"BE",
    "sg:address":"Oestrasse 6",
    "sg:city":"Eupen",
    "sg:classifiers":[
        {
            "category":"Health Services",
            "subcategory":"Dentist",
            "type":"Services"
        }
    ],
    "sg:phone":"+32 87 74 32 49",
    "sg:postcode":"4700",
    "sg:province":"Li\u00e8ge",
    "wof:name":"Renson Bernard",
    "wof:placetype":"venue"
},
  "geometry": {"coordinates":[6.0362029076,50.6238861084],"type":"Point"}
}