{
  "type": "Feature",
  "properties": {
    "addr:full":"Leuvense Steenweg 52 Boortmeerbeek (hever) Vlaams-Brabant 3191",
    "addr:housenumber":"52",
    "addr:postcode":"3191",
    "addr:street":"Leuvense Steenweg",
    "iso:country":"BE",
    "sg:address":"Leuvense Steenweg 52",
    "sg:city":"Boortmeerbeek (hever)",
    "sg:classifiers":[
        {
            "category":"Retail",
            "subcategory":"Repair Shop",
            "type":"Services"
        }
    ],
    "sg:phone":"+32 15 52 83 93",
    "sg:postcode":"3191",
    "sg:province":"Vlaams-Brabant",
    "sg:tags":[
        "radio",
        "television",
        "-",
        "maintenance"
    ],
    "wof:name":"Sound And Vision Service Bvba",
    "wof:placetype":"venue"
},
  "geometry": {"coordinates":[4.5368618965,50.9913253784],"type":"Point"}
}