{
  "type": "Feature",
  "properties": {
    "iso:country":"BE",
    "sg:address":"Rue De La Gare 19/21",
    "sg:city":"Malmedy",
    "sg:orig_category":"Computers and computerapparatuur Kantoormateriaal Kantoormateriaal Gh Software ontwikkeling and ontw",
    "sg:phone":"+32 80 33 82 46",
    "sg:postcode":"4960",
    "sg:province":"Li\u00e8ge",
    "wof:name":"Binckom",
    "wof:placetype":"venue"
},
  "geometry": {"coordinates":[6.0326728821,50.4243354797],"type":"Point"}
}