{
  "type": "Feature",
  "properties": {
    "iso:country":"BE",
    "sg:address":"Rue Jean Schoenaerts 9",
    "sg:city":"Awans",
    "sg:classifiers":[
        {
            "category":"Home & Garden",
            "subcategory":"Kitchen Supply",
            "type":"Retail Goods"
        }
    ],
    "sg:phone":"+32 4 246 94 17",
    "sg:postcode":"4340",
    "sg:province":"Li\u00e8ge",
    "sg:tags":[
        "installation"
    ],
    "wof:name":"Leduc T",
    "wof:placetype":"venue"
},
  "geometry": {"coordinates":[5.4662680626,50.6659736633],"type":"Point"}
}