{
  "type": "Feature",
  "properties": {
    "addr:full":"Openveldstraat 28 Asse Vlaams-Brabant 1731",
    "addr:housenumber":"28",
    "addr:postcode":"1731",
    "addr:street":"Openveldstraat",
    "iso:country":"BE",
    "sg:address":"Openveldstraat 28",
    "sg:city":"Asse",
    "sg:orig_category":"Mat\u00e9riel de T\u00e9l\u00e9communication",
    "sg:phone":"+32 2 463 32 09",
    "sg:postcode":"1731",
    "sg:province":"Vlaams-Brabant",
    "wof:name":"Eserasat",
    "wof:placetype":"venue"
},
  "geometry": {"coordinates":[4.2739238739,50.88671875],"type":"Point"}
}