{
  "type": "Feature",
  "properties": {
    "addr:full":"Grand-rue 54 Morlanwelz Hainaut 7140",
    "addr:housenumber":"54",
    "addr:postcode":"7140",
    "addr:street":"Grand-Rue",
    "iso:country":"BE",
    "sg:address":"Grand-rue 54",
    "sg:city":"Morlanwelz",
    "sg:orig_category":"Boucheries",
    "sg:phone":"+32 64 44 22 13",
    "sg:postcode":"7140",
    "sg:province":"Hainaut",
    "wof:name":"Boucherie Au Marcassin",
    "wof:placetype":"venue"
},
  "geometry": {"coordinates":[4.2454371452,50.4557495117],"type":"Point"}
}