{
  "type": "Feature",
  "properties": {
    "iso:country":"BE",
    "sg:address":"Vergotesquare 39",
    "sg:city":"Schaarbeek/schaerbeek",
    "sg:orig_category":"Belastingconsulenten Diverse juridische dienstverlening",
    "sg:phone":"+32 2 736 25 25",
    "sg:postcode":"1030",
    "sg:province":"Bruxelles-Capitale",
    "wof:name":"P.n.m. & Co",
    "wof:placetype":"venue"
},
  "geometry": {"coordinates":[4.4033608437,50.845867157],"type":"Point"}
}