{
  "type": "Feature",
  "properties": {
    "addr:full":"Zoerselbaan 4 Malle Antwerpen 2390",
    "addr:housenumber":"4",
    "addr:postcode":"2390",
    "addr:street":"Zoerselbaan",
    "iso:country":"BE",
    "sg:address":"Zoerselbaan 4",
    "sg:city":"Malle",
    "sg:orig_category":"Supermarkten",
    "sg:postcode":"2390",
    "sg:province":"Antwerpen",
    "wof:name":"Aldi",
    "wof:placetype":"venue"
},
  "geometry": {"coordinates":[4.6939611435,51.2964706421],"type":"Point"}
}