{
  "type": "Feature",
  "properties": {
    "addr:full":"Schatting 15 Zedelgem West-Vlaanderen 8210",
    "addr:housenumber":"15",
    "addr:postcode":"8210",
    "addr:street":"Schatting",
    "iso:country":"BE",
    "sg:address":"Schatting 15",
    "sg:city":"Zedelgem",
    "sg:classifiers":[
        {
            "category":"Professional",
            "subcategory":"Art Services",
            "type":"Services"
        }
    ],
    "sg:phone":"+32 50 20 19 32",
    "sg:postcode":"8210",
    "sg:province":"West-Vlaanderen",
    "sg:tags":[
        "automobile",
        "transit",
        "-",
        "export",
        "import"
    ],
    "wof:name":"Belauto",
    "wof:placetype":"venue"
},
  "geometry": {"coordinates":[3.1428759098,51.1367378235],"type":"Point"}
}