{
  "type": "Feature",
  "properties": {
    "addr:full":"Joseph Possozplein 9b2 Halle Vlaams-Brabant 1500",
    "addr:housenumber":"9b2",
    "addr:postcode":"1500",
    "addr:street":"Possozplein",
    "iso:country":"BE",
    "sg:address":"Joseph Possozplein 9b2",
    "sg:city":"Halle",
    "sg:orig_category":"Advocaten and juridische adviseurs",
    "sg:phone":"+32 2 356 87 23",
    "sg:postcode":"1500",
    "sg:province":"Vlaams-Brabant",
    "wof:name":"Jan Van Springel",
    "wof:placetype":"venue"
},
  "geometry": {"coordinates":[4.2374820709,50.7356948853],"type":"Point"}
}