{
  "type": "Feature",
  "properties": {
    "addr:full":"Beverenstraat 17 /31 Deerlijk West-Vlaanderen 8540",
    "addr:housenumber":"17 / 31",
    "addr:postcode":"8540",
    "addr:street":"Beverenstraat",
    "iso:country":"BE",
    "sg:address":"Beverenstraat 17 /31",
    "sg:city":"Deerlijk",
    "sg:classifiers":[
        {
            "category":"Shopping",
            "subcategory":"Crafts & Fabrics",
            "type":"Retail Goods"
        }
    ],
    "sg:phone":"+32 56 71 75 31",
    "sg:postcode":"8540",
    "sg:province":"West-Vlaanderen",
    "sg:tags":[
        "textile",
        "linen",
        "clothing"
    ],
    "wof:name":"Acotex Nv",
    "wof:placetype":"venue"
},
  "geometry": {"coordinates":[3.3501529694,50.8547172546],"type":"Point"}
}