{
  "type": "Feature",
  "properties": {
    "addr:full":"Vleugdstraat 2 Diest Vlaams-Brabant 3290",
    "addr:housenumber":"2",
    "addr:postcode":"3290",
    "addr:street":"Vleugdstraat",
    "iso:country":"BE",
    "sg:address":"Vleugdstraat 2",
    "sg:city":"Diest",
    "sg:orig_category":"Fer and acier Fab",
    "sg:phone":"+32 13 33 30 10",
    "sg:postcode":"3290",
    "sg:province":"Vlaams-Brabant",
    "wof:name":"Bauwens",
    "wof:placetype":"venue"
},
  "geometry": {"coordinates":[5.1092658043,51.0171775818],"type":"Point"}
}