{
  "type": "Feature",
  "properties": {
    "iso:country":"BE",
    "sg:address":"Het Bergske 30",
    "sg:city":"Oud-turnhout",
    "sg:classifiers":[
        {
            "category":"Professional",
            "subcategory":"Management & Consulting",
            "type":"Services"
        }
    ],
    "sg:phone":"+32 14 70 04 87",
    "sg:postcode":"2360",
    "sg:province":"Antwerpen",
    "sg:tags":[
        "-",
        "processing",
        "data",
        "consultant"
    ],
    "wof:name":"Kapitol-e",
    "wof:placetype":"venue"
},
  "geometry": {"coordinates":[4.9790959358,51.3150634766],"type":"Point"}
}