{
  "type": "Feature",
  "properties": {
    "iso:country":"BE",
    "sg:address":"Route De Philippeville 463",
    "sg:city":"Charleroi (couillet)",
    "sg:classifiers":[
        {
            "category":"Professional",
            "subcategory":"Testing Lab",
            "type":"Services"
        }
    ],
    "sg:phone":"+32 71 36 25 43",
    "sg:postcode":"6010",
    "sg:province":"Hainaut",
    "sg:tags":[
        "chemist"
    ],
    "wof:name":"Pharmacie De La Cascade",
    "wof:placetype":"venue"
},
  "geometry": {"coordinates":[4.4662299156,50.378288269],"type":"Point"}
}