{
  "type": "Feature",
  "properties": {
    "iso:country":"BE",
    "sg:address":"Grand'rue Des Bouchers 20",
    "sg:city":"Ath",
    "sg:orig_category":"Pain, p\u00e2tisseries and confiseries",
    "sg:phone":"+32 68 28 28 33",
    "sg:postcode":"7800",
    "sg:province":"Hainaut",
    "wof:name":"Yves Picron",
    "wof:placetype":"venue"
},
  "geometry": {"coordinates":[3.7767679691,50.6313171387],"type":"Point"}
}