{
  "type": "Feature",
  "properties": {
    "addr:full":"Bredabaan 253 Brasschaat Antwerpen 2930",
    "addr:housenumber":"253",
    "addr:postcode":"2930",
    "addr:street":"Bredabaan",
    "iso:country":"BE",
    "sg:address":"Bredabaan 253",
    "sg:city":"Brasschaat",
    "sg:classifiers":[
        {
            "category":"Real Estate",
            "subcategory":"Real Estate Services",
            "type":"Services"
        }
    ],
    "sg:phone":"+32 3 653 52 90",
    "sg:postcode":"2930",
    "sg:province":"Antwerpen",
    "sg:tags":[
        "-",
        "abroad"
    ],
    "wof:name":"North Estates Bvba",
    "wof:placetype":"venue"
},
  "geometry": {"coordinates":[4.4868922234,51.2876014709],"type":"Point"}
}