{
  "type": "Feature",
  "properties": {
    "iso:country":"BE",
    "sg:address":"Rue Des Fran\u00e7ais 42",
    "sg:city":"Charleroi (dampremy)",
    "sg:classifiers":[
        {
            "category":"Professional",
            "subcategory":"Management & Consulting",
            "type":"Services"
        }
    ],
    "sg:phone":"+32 71 31 60 74",
    "sg:postcode":"6020",
    "sg:province":"Hainaut",
    "sg:tags":[
        "marketing",
        "-",
        "consultant"
    ],
    "wof:name":"Attardo S",
    "wof:placetype":"venue"
},
  "geometry": {"coordinates":[4.4387230873,50.422252655],"type":"Point"}
}