{
  "type": "Feature",
  "properties": {
    "addr:full":"Rijselstraat 93 Menen West-Vlaanderen 8930",
    "addr:housenumber":"93",
    "addr:postcode":"8930",
    "addr:street":"Rijselstraat",
    "iso:country":"BE",
    "sg:address":"Rijselstraat 93",
    "sg:city":"Menen",
    "sg:classifiers":[
        {
            "category":"Fast Food",
            "type":"Food & Drink"
        }
    ],
    "sg:phone":"+32 56 51 35 65",
    "sg:postcode":"8930",
    "sg:province":"West-Vlaanderen",
    "sg:tags":[
        "huis",
        "aan",
        "levering",
        "meeneem",
        "restaurant"
    ],
    "wof:name":"Pizza Mania",
    "wof:placetype":"venue"
},
  "geometry": {"coordinates":[3.1238000393,50.7918968201],"type":"Point"}
}