{
  "type": "Feature",
  "properties": {
    "iso:country":"BE",
    "sg:address":"Hielstraat 98",
    "sg:city":"Gent",
    "sg:orig_category":"Cr\u00e9meries",
    "sg:phone":"+32 9 230 36 66",
    "sg:postcode":"9050",
    "sg:province":"Oost-Vlaanderen",
    "wof:name":"Snauwaert",
    "wof:placetype":"venue"
},
  "geometry": {"coordinates":[3.7589480877,51.0448532104],"type":"Point"}
}