{
  "type": "Feature",
  "properties": {
    "iso:country":"BE",
    "sg:address":"Centrumstraat 80",
    "sg:city":"Zulte",
    "sg:orig_category":"Postkantoren Verzekeringsmakelaars and experts",
    "sg:phone":"+32 9 388 81 83",
    "sg:postcode":"9870",
    "sg:province":"Oost-Vlaanderen",
    "wof:name":"De Post",
    "wof:placetype":"venue"
},
  "geometry": {"coordinates":[3.469894886,50.9315986633],"type":"Point"}
}