{
  "type": "Feature",
  "properties": {
    "addr:full":"Centrumstraat 80 Zulte Oost-Vlaanderen 9870",
    "addr:housenumber":"80",
    "addr:postcode":"9870",
    "addr:street":"Centrumstraat",
    "iso:country":"BE",
    "sg:address":"Centrumstraat 80",
    "sg:city":"Zulte",
    "sg:orig_category":"Postkantoren Verzekeringsmakelaars and experts",
    "sg:phone":"+32 9 388 81 83",
    "sg:postcode":"9870",
    "sg:province":"Oost-Vlaanderen",
    "wof:name":"De Post",
    "wof:placetype":"venue"
},
  "geometry": {"coordinates":[3.469894886,50.9315986633],"type":"Point"}
}