{
  "type": "Feature",
  "properties": {
    "iso:country":"BE",
    "sg:address":"Herman Teirlinckstraat 8",
    "sg:city":"Zele",
    "sg:classifiers":[
        {
            "category":"Building & Trades",
            "subcategory":"Construction",
            "type":"Services"
        }
    ],
    "sg:phone":"+32 52 44 71 38",
    "sg:postcode":"9240",
    "sg:province":"Oost-Vlaanderen",
    "sg:tags":[
        "installation",
        "-",
        "central",
        "heating"
    ],
    "wof:name":"Sani/therm",
    "wof:placetype":"venue"
},
  "geometry": {"coordinates":[4.0379428864,51.0579681396],"type":"Point"}
}