{
  "type": "Feature",
  "properties": {
    "addr:full":"Chauss\u00c9e De Chimay 12-1bis Beaumont Hainaut 6500",
    "addr:housenumber":"12-1bis",
    "addr:postcode":"6500",
    "addr:street":"Chausse\u0301E De Chimay;Hainaut",
    "iso:country":"BE",
    "sg:address":"Chauss\u00c9e De Chimay 12-1bis",
    "sg:city":"Beaumont",
    "sg:orig_category":"Entretien and r\u00e9parations de voitures",
    "sg:phone":"+32 71 58 81 57",
    "sg:postcode":"6500",
    "sg:province":"Hainaut",
    "wof:name":"Ets. Antoine",
    "wof:placetype":"venue"
},
  "geometry": {"coordinates":[4.2381501198,50.2345314026],"type":"Point"}
}