{
  "type": "Feature",
  "properties": {
    "addr:full":"Kwadestraat 62 Wevelgem (gullegem) West-Vlaanderen 8560",
    "addr:housenumber":"62",
    "addr:postcode":"8560",
    "addr:street":"Kwadestraat",
    "iso:country":"BE",
    "sg:address":"Kwadestraat 62",
    "sg:city":"Wevelgem (gullegem)",
    "sg:classifiers":[
        {
            "category":"Bars & Pubs",
            "type":"Food & Drink"
        }
    ],
    "sg:phone":"+32 56 41 43 76",
    "sg:postcode":"8560",
    "sg:province":"West-Vlaanderen",
    "wof:name":"El Charro",
    "wof:placetype":"venue"
},
  "geometry": {"coordinates":[3.205370903,50.8497810364],"type":"Point"}
}