{
  "type": "Feature",
  "properties": {
    "iso:country":"BE",
    "sg:address":"Jan Van Rijswijcklaan 142 Box 1",
    "sg:city":"Antwerpen",
    "sg:classifiers":[
        {
            "category":"Professional",
            "subcategory":"Lawyer & Legal Services",
            "type":"Services"
        }
    ],
    "sg:phone":"+32 3 238 52 93",
    "sg:postcode":"2018",
    "sg:province":"Antwerpen",
    "sg:tags":[
        "notary"
    ],
    "wof:name":"De Groof P",
    "wof:placetype":"venue"
},
  "geometry": {"coordinates":[4.4024381638,51.1945877075],"type":"Point"}
}