{
  "type": "Feature",
  "properties": {
    "addr:full":"Etikhoveplein 16 Maarkedal Oost-Vlaanderen 9680",
    "addr:housenumber":"16",
    "addr:postcode":"9680",
    "addr:street":"Etikhoveplein",
    "iso:country":"BE",
    "sg:address":"Etikhoveplein 16",
    "sg:city":"Maarkedal",
    "sg:orig_category":"Orphelinats. Instituts pour enfants en difficult\u00e9",
    "sg:phone":"+32 55 31 17 85",
    "sg:postcode":"9680",
    "sg:province":"Oost-Vlaanderen",
    "wof:name":"Home Maria Goretti",
    "wof:placetype":"venue"
},
  "geometry": {"coordinates":[3.6264419556,50.8122673035],"type":"Point"}
}