{
  "type": "Feature",
  "properties": {
    "addr:full":"Elfnovemberlaan 14 Leuven Vlaams-Brabant 3010",
    "addr:housenumber":"14",
    "addr:postcode":"3010",
    "addr:street":"Elfnovemberlaan",
    "iso:country":"BE",
    "sg:address":"Elfnovemberlaan 14",
    "sg:city":"Leuven",
    "sg:orig_category":"Producteurs de l\u00e9gumes",
    "sg:phone":"+32 16 25 77 83",
    "sg:postcode":"3010",
    "sg:province":"Vlaams-Brabant",
    "wof:name":"Bruno Vuerinckx",
    "wof:placetype":"venue"
},
  "geometry": {"coordinates":[4.7304501534,50.889755249],"type":"Point"}
}