{
  "type": "Feature",
  "properties": {
    "addr:full":"Chauss\u00c9e De Nivelles 227 Pont-\u00c0-celles Hainaut 6238",
    "addr:housenumber":"227",
    "addr:postcode":"6238",
    "addr:street":"Chausse\u0301E De Nivelles",
    "iso:country":"BE",
    "sg:address":"Chauss\u00c9e De Nivelles 227",
    "sg:city":"Pont-\u00c0-celles",
    "sg:orig_category":"Electrom\u00e9nager, t\u00e9l\u00e9visions and radios. Animations diverses. Eclairage et \u00e9quipements du foyer",
    "sg:phone":"+32 71 84 59 96",
    "sg:postcode":"6238",
    "sg:province":"Hainaut",
    "wof:name":"D.j. New Tone",
    "wof:placetype":"venue"
},
  "geometry": {"coordinates":[4.4219369888,50.5065994263],"type":"Point"}
}