{
  "type": "Feature",
  "properties": {
    "iso:country":"BE",
    "sg:address":"Rue De La Forge 14",
    "sg:city":"Mont-saint-guibert",
    "sg:classifiers":[
        {
            "category":"Personal",
            "subcategory":"Beauty Salon",
            "type":"Services"
        }
    ],
    "sg:phone":"+32 10 65 83 20",
    "sg:postcode":"1435",
    "sg:province":"Brabant Wallon",
    "sg:tags":[
        "de",
        "coiffure"
    ],
    "wof:name":"Coiffure Brigitte",
    "wof:placetype":"venue"
},
  "geometry": {"coordinates":[4.6521282196,50.6452522278],"type":"Point"}
}