{
  "type": "Feature",
  "properties": {
    "addr:full":"Avenue Van Der Meerschen 166 Sint-pieters-woluwe/woluwe-saint-pierre Bruxelles-Capitale 1150",
    "addr:housenumber":"166",
    "addr:postcode":"1150",
    "addr:street":"Avenue Van Der Meerschen;/",
    "iso:country":"BE",
    "sg:address":"Avenue Van Der Meerschen 166",
    "sg:city":"Sint-pieters-woluwe/woluwe-saint-pierre",
    "sg:orig_category":"Pain, p\u00e2tisseries and confiseries",
    "sg:phone":"+32 2 770 93 86",
    "sg:postcode":"1150",
    "sg:province":"Bruxelles-Capitale",
    "wof:name":"Codistri",
    "wof:placetype":"venue"
},
  "geometry": {"coordinates":[4.4635519981,50.8288002014],"type":"Point"}
}