{
  "type": "Feature",
  "properties": {
    "iso:country":"BE",
    "sg:address":"Zandstraat 58",
    "sg:city":"Laakdal (veerle)",
    "sg:classifiers":[
        {
            "category":"Education",
            "subcategory":"School",
            "type":"Public Place"
        }
    ],
    "sg:phone":"+32 14 84 01 80",
    "sg:postcode":"2431",
    "sg:province":"Antwerpen",
    "sg:tags":[
        "primary"
    ],
    "wof:name":"T'schanske",
    "wof:placetype":"venue"
},
  "geometry": {"coordinates":[4.9575600624,51.055141449],"type":"Point"}
}