{
  "type": "Feature",
  "properties": {
    "iso:country":"BE",
    "sg:address":"Hogenakkerstraat 178",
    "sg:city":"Sint-niklaas",
    "sg:orig_category":"Kapsalons",
    "sg:phone":"+32 3 777 68 53",
    "sg:postcode":"9100",
    "sg:province":"Oost-Vlaanderen",
    "wof:name":"Coiffure Gunther",
    "wof:placetype":"venue"
},
  "geometry": {"coordinates":[4.1618199348,51.1661300659],"type":"Point"}
}