{
  "type": "Feature",
  "properties": {
    "iso:country":"BE",
    "sg:address":"Rue Des Mazys 2",
    "sg:city":"Gedinne",
    "sg:orig_category":"Kapsalons",
    "sg:phone":"+32 61 58 90 51",
    "sg:postcode":"5575",
    "sg:province":"Namur",
    "wof:name":"Sylvie Languillier",
    "wof:placetype":"venue"
},
  "geometry": {"coordinates":[4.9327301979,49.9574584961],"type":"Point"}
}