{
  "type": "Feature",
  "properties": {
    "addr:full":"Rue De La Fronti\u00c8re 31 Dour Hainaut 7370",
    "addr:housenumber":"31",
    "addr:postcode":"7370",
    "addr:street":"Rue De La Frontie\u0300Re;Hainaut",
    "iso:country":"BE",
    "sg:address":"Rue De La Fronti\u00c8re 31",
    "sg:city":"Dour",
    "sg:orig_category":"Verplichte sociale verzekeringen",
    "sg:phone":"+32 65 65 56 60",
    "sg:postcode":"7370",
    "sg:province":"Hainaut",
    "wof:name":"Mutualit\u00c9 Socialiste",
    "wof:placetype":"venue"
},
  "geometry": {"coordinates":[3.8039569855,50.3734054565],"type":"Point"}
}