{
  "type": "Feature",
  "properties": {
    "addr:full":"J.-b. Carnoyplein 20 Sint-lambrechts-woluwe/woluwe-saint-lambert Bruxelles-Capitale 1200",
    "addr:housenumber":"20",
    "addr:postcode":"1200",
    "addr:street":"J.-B. Carnoyplein",
    "iso:country":"BE",
    "sg:address":"J.-b. Carnoyplein 20",
    "sg:city":"Sint-lambrechts-woluwe/woluwe-saint-lambert",
    "sg:classifiers":[
        {
            "category":"Restaurant",
            "type":"Food & Drink"
        }
    ],
    "sg:phone":"+32 2 771 78 17",
    "sg:postcode":"1200",
    "sg:province":"Bruxelles-Capitale",
    "wof:name":"Le Panier De St.luc",
    "wof:placetype":"venue"
},
  "geometry": {"coordinates":[4.4153561592,50.8513336182],"type":"Point"}
}