{
  "type": "Feature",
  "properties": {
    "iso:country":"BE",
    "sg:address":"Kapelstraat 237b",
    "sg:city":"Bredene",
    "sg:classifiers":[
        {
            "category":"Home & Garden",
            "subcategory":"Home Furnishings",
            "type":"Retail Goods"
        }
    ],
    "sg:phone":"+32 59 33 05 15",
    "sg:postcode":"8450",
    "sg:province":"West-Vlaanderen",
    "sg:tags":[
        "interior",
        "decoration"
    ],
    "wof:name":"Paint & Deco",
    "wof:placetype":"venue"
},
  "geometry": {"coordinates":[2.9792261124,51.2529640198],"type":"Point"}
}