{
  "type": "Feature",
  "properties": {
    "iso:country":"BE",
    "sg:address":"Avenue Du Mussain 35",
    "sg:city":"Tubize",
    "sg:classifiers":[
        {
            "category":"Cafe",
            "type":"Food & Drink"
        }
    ],
    "sg:phone":"+32 2 355 99 74",
    "sg:postcode":"1480",
    "sg:province":"Brabant Wallon",
    "sg:tags":[
        "caf\u00e9s"
    ],
    "wof:name":"Marc Bernis",
    "wof:placetype":"venue"
},
  "geometry": {"coordinates":[4.1612048149,50.7169303894],"type":"Point"}
}