{
  "type": "Feature",
  "properties": {
    "iso:country":"BE",
    "sg:address":"Kerkstraat 359",
    "sg:city":"Blankenberge",
    "sg:orig_category":"Avocats and conseillers juridiques",
    "sg:phone":"+32 50 41 90 27",
    "sg:postcode":"8370",
    "sg:province":"West-Vlaanderen",
    "wof:name":"Mia Vert\u00c9",
    "wof:placetype":"venue"
},
  "geometry": {"coordinates":[3.14052701,51.3055267334],"type":"Point"}
}