{
  "type": "Feature",
  "properties": {
    "addr:full":"Overdemerstraat 43 Hasselt (kuringen) Limburg 3511",
    "addr:housenumber":"43",
    "addr:postcode":"3511",
    "addr:street":"Overdemerstraat",
    "iso:country":"BE",
    "sg:address":"Overdemerstraat 43",
    "sg:city":"Hasselt (kuringen)",
    "sg:classifiers":[
        {
            "category":"Home & Garden",
            "subcategory":"Carpets & Floor Coverings",
            "type":"Retail Goods"
        }
    ],
    "sg:phone":"+32 11 25 14 29",
    "sg:postcode":"3511",
    "sg:province":"Limburg",
    "sg:tags":[
        "-"
    ],
    "wof:name":"Lambrighs E (algem Schilderw) Nv",
    "wof:placetype":"venue"
},
  "geometry": {"coordinates":[5.3095808029,50.9481620789],"type":"Point"}
}