{
  "type": "Feature",
  "properties": {
    "addr:full":"Europarklaan 2064 Houthalen-helchteren (houthalen) Limburg 3530",
    "addr:postcode":"2064;3530",
    "addr:street":"Europarklaan",
    "iso:country":"BE",
    "sg:address":"Europarklaan 2064",
    "sg:city":"Houthalen-helchteren (houthalen)",
    "sg:orig_category":"Non-Classified Establishments",
    "sg:phone":"+32 11 52 29 96",
    "sg:postcode":"3530",
    "sg:province":"Limburg",
    "wof:name":"Ellimac Nv",
    "wof:placetype":"venue"
},
  "geometry": {"coordinates":[5.3915300369,51.03565979],"type":"Point"}
}