{
  "type": "Feature",
  "properties": {
    "iso:country":"BE",
    "sg:address":"Drongenstraat 33a",
    "sg:city":"Lokeren",
    "sg:classifiers":[
        {
            "category":"Home & Garden",
            "subcategory":"Building Materials",
            "type":"Retail Goods"
        }
    ],
    "sg:phone":"+32 9 356 89 54",
    "sg:postcode":"9160",
    "sg:province":"Oost-Vlaanderen",
    "sg:tags":[
        "insulation",
        "thermical"
    ],
    "wof:name":"V D I Bvba",
    "wof:placetype":"venue"
},
  "geometry": {"coordinates":[3.9066729546,51.1016159058],"type":"Point"}
}