{
  "type": "Feature",
  "properties": {
    "addr:full":"Meistraat 219 Dessel Antwerpen 2480",
    "addr:housenumber":"219",
    "addr:postcode":"2480",
    "addr:street":"Meistraat",
    "iso:country":"BE",
    "sg:address":"Meistraat 219",
    "sg:city":"Dessel",
    "sg:orig_category":"Entretien and r\u00e9parations de voitures",
    "sg:phone":"+32 14 37 88 53",
    "sg:postcode":"2480",
    "sg:province":"Antwerpen",
    "wof:name":"Leo Hannes",
    "wof:placetype":"venue"
},
  "geometry": {"coordinates":[5.1562209129,51.2404403687],"type":"Point"}
}