{
  "type": "Feature",
  "properties": {
    "iso:country":"BE",
    "sg:address":"Bessenlaan 32",
    "sg:city":"Rotselaar",
    "sg:orig_category":"Sportclubs",
    "sg:phone":"+32 16 58 06 34",
    "sg:postcode":"3110",
    "sg:province":"Vlaams-Brabant",
    "wof:name":"Duivenbond De Nachtkrabbers",
    "wof:placetype":"venue"
},
  "geometry": {"coordinates":[4.7488069534,50.9576072693],"type":"Point"}
}