{
  "type": "Feature",
  "properties": {
    "iso:country":"BE",
    "sg:address":"Linde 110",
    "sg:city":"Londerzeel",
    "sg:classifiers":[
        {
            "category":"Personal",
            "subcategory":"Beauty Salon",
            "type":"Services"
        }
    ],
    "sg:phone":"+32 52 30 11 07",
    "sg:postcode":"1840",
    "sg:province":"Vlaams-Brabant",
    "sg:tags":[
        "lady",
        "-",
        "hairdressing"
    ],
    "wof:name":"Tintina",
    "wof:placetype":"venue"
},
  "geometry": {"coordinates":[4.289662838,51.0030288696],"type":"Point"}
}