{
  "type": "Feature",
  "properties": {
    "iso:country":"BE",
    "sg:address":"Hennepstraat 8",
    "sg:city":"Lommel",
    "sg:orig_category":"Gespecialiseerde residenti\u00eble bouw",
    "sg:phone":"+32 11 54 05 45",
    "sg:postcode":"3920",
    "sg:province":"Limburg",
    "wof:name":"Ludo Berckmans",
    "wof:placetype":"venue"
},
  "geometry": {"coordinates":[5.30975914,51.218788147],"type":"Point"}
}