{
  "type": "Feature",
  "properties": {
    "addr:full":"Chauss\u00c9e De Helmet 157 Schaarbeek/schaerbeek Bruxelles-Capitale 1030",
    "addr:housenumber":"157",
    "addr:postcode":"1030",
    "addr:street":"Chausse\u0301E De Helmet",
    "iso:country":"BE",
    "sg:address":"Chauss\u00c9e De Helmet 157",
    "sg:city":"Schaarbeek/schaerbeek",
    "sg:orig_category":"R\u00e9paration and restauration de meubles",
    "sg:phone":"+32 2 242 56 38",
    "sg:postcode":"1030",
    "sg:province":"Bruxelles-Capitale",
    "wof:name":"Rene Colonval",
    "wof:placetype":"venue"
},
  "geometry": {"coordinates":[4.3845891953,50.8718757629],"type":"Point"}
}