{
  "type": "Feature",
  "properties": {
    "iso:country":"BE",
    "sg:address":"Zerkegemstraat 23a",
    "sg:city":"Ichtegem (bekegem)",
    "sg:classifiers":[
        {
            "category":"Retail",
            "subcategory":"Auto Repair",
            "type":"Services"
        }
    ],
    "sg:phone":"+32 50 81 14 70",
    "sg:postcode":"8480",
    "sg:province":"West-Vlaanderen",
    "sg:tags":[
        "garage"
    ],
    "wof:name":"Samaey F",
    "wof:placetype":"venue"
},
  "geometry": {"coordinates":[3.0566859245,51.1586799622],"type":"Point"}
}