{
  "type": "Feature",
  "properties": {
    "iso:country":"BE",
    "sg:address":"Torhoutse Steenweg 305",
    "sg:city":"Brugge",
    "sg:orig_category":"Transports routiers de marchandises",
    "sg:phone":"+32 50 39 14 13",
    "sg:postcode":"8200",
    "sg:province":"West-Vlaanderen",
    "wof:name":"Cools Marcel",
    "wof:placetype":"venue"
},
  "geometry": {"coordinates":[3.1986250877,51.1942024231],"type":"Point"}
}