{
  "type": "Feature",
  "properties": {
    "addr:full":"Vossenstraat 15 Brussel/bruxelles Bruxelles-Capitale 1000",
    "addr:housenumber":"15",
    "addr:postcode":"1000",
    "addr:street":"Vossenstraat;/",
    "iso:country":"BE",
    "sg:address":"Vossenstraat 15",
    "sg:city":"Brussel/bruxelles",
    "sg:orig_category":"Zalen voor culturele evenementen",
    "sg:phone":"+32 2 513 06 29",
    "sg:postcode":"1000",
    "sg:province":"Bruxelles-Capitale",
    "wof:name":"Galerie Catherine Mayeur",
    "wof:placetype":"venue"
},
  "geometry": {"coordinates":[4.346244812,50.837688446],"type":"Point"}
}