{
  "type": "Feature",
  "properties": {
    "iso:country":"BE",
    "sg:address":"Heffink 8",
    "sg:city":"Evergem",
    "sg:orig_category":"Rundveehouders",
    "sg:phone":"+32 9 357 30 44",
    "sg:postcode":"9940",
    "sg:province":"Oost-Vlaanderen",
    "wof:name":"Herman Goethals",
    "wof:placetype":"venue"
},
  "geometry": {"coordinates":[3.7182350159,51.1371994019],"type":"Point"}
}