{
  "type": "Feature",
  "properties": {
    "iso:country":"BE",
    "sg:address":"Chauss\u00e9e De Lodelinsart 64",
    "sg:city":"Charleroi (gilly)",
    "sg:classifiers":[
        {
            "category":"Community Center",
            "subcategory":"Youth",
            "type":"Public Place"
        }
    ],
    "sg:phone":"+32 71 41 62 17",
    "sg:postcode":"6060",
    "sg:province":"Hainaut",
    "sg:tags":[
        "club"
    ],
    "wof:name":"Ener'j",
    "wof:placetype":"venue"
},
  "geometry": {"coordinates":[4.4498310089,50.4204826355],"type":"Point"}
}