{
  "type": "Feature",
  "properties": {
    "iso:country":"BE",
    "sg:address":"Avenue Ernestine 20b9",
    "sg:city":"Elsene/ixelles",
    "sg:orig_category":"M\u00e9decins and sp\u00e9cialistes",
    "sg:phone":"+32 2 647 52 69",
    "sg:postcode":"1050",
    "sg:province":"Bruxelles-Capitale",
    "wof:name":"Jean Selleslags",
    "wof:placetype":"venue"
},
  "geometry": {"coordinates":[4.3798441887,50.8155784607],"type":"Point"}
}