{
  "type": "Feature",
  "properties": {
    "addr:full":"Bremstraat 1bc Ronse/renaix Oost-Vlaanderen 9600",
    "addr:housenumber":"1bc",
    "addr:postcode":"9600",
    "addr:street":"Bremstraat",
    "iso:country":"BE",
    "sg:address":"Bremstraat 1bc",
    "sg:city":"Ronse/renaix",
    "sg:orig_category":"Meubelzaken, woning- and keukeninrichting",
    "sg:phone":"+32 55 21 47 87",
    "sg:postcode":"9600",
    "sg:province":"Oost-Vlaanderen",
    "wof:name":"Jacques Verschelden",
    "wof:placetype":"venue"
},
  "geometry": {"coordinates":[3.5451290607,50.7568206787],"type":"Point"}
}