{
  "type": "Feature",
  "properties": {
    "iso:country":"BE",
    "sg:address":"Hannuitsesteenweg 544",
    "sg:city":"Tienen",
    "sg:orig_category":"M\u00e9decins and sp\u00e9cialistes",
    "sg:phone":"+32 16 81 65 52",
    "sg:postcode":"3300",
    "sg:province":"Vlaams-Brabant",
    "wof:name":"Guido Vermeulen",
    "wof:placetype":"venue"
},
  "geometry": {"coordinates":[4.930077076,50.8096694946],"type":"Point"}
}