{
  "type": "Feature",
  "properties": {
    "iso:country":"BE",
    "sg:address":"Rue Du Moulin 120",
    "sg:city":"Li\u00c8ge",
    "sg:orig_category":"V\u00eatements pour b\u00e9b\u00e9s and enfants. V\u00eatements pour Dames. R\u00e9parations de chaussures and articles en cu",
    "sg:phone":"+32 4 343 82 70",
    "sg:postcode":"4020",
    "sg:province":"Li\u00e8ge",
    "wof:name":"Cordonnerie Cuypers",
    "wof:placetype":"venue"
},
  "geometry": {"coordinates":[5.5935502052,50.637348175],"type":"Point"}
}