{
  "type": "Feature",
  "properties": {
    "addr:full":"Meerseniersstraat 4 Gent Oost-Vlaanderen 9000",
    "addr:housenumber":"4",
    "addr:postcode":"9000",
    "addr:street":"Meerseniersstraat;Oost-Vlaanderen",
    "iso:country":"BE",
    "sg:address":"Meerseniersstraat 4",
    "sg:city":"Gent",
    "sg:orig_category":"Zuivelproducten",
    "sg:phone":"+32 9 233 70 75",
    "sg:postcode":"9000",
    "sg:province":"Oost-Vlaanderen",
    "wof:name":"Kaasfermetje",
    "wof:placetype":"venue"
},
  "geometry": {"coordinates":[3.7243850231,51.057559967],"type":"Point"}
}