{
  "type": "Feature",
  "properties": {
    "addr:full":"Brielstraat 27 Deinze Oost-Vlaanderen 9800",
    "addr:housenumber":"27",
    "addr:postcode":"9800",
    "addr:street":"Brielstraat",
    "iso:country":"BE",
    "sg:address":"Brielstraat 27",
    "sg:city":"Deinze",
    "sg:orig_category":"Tribunaux",
    "sg:phone":"+32 9 386 26 34",
    "sg:postcode":"9800",
    "sg:province":"Oost-Vlaanderen",
    "wof:name":"Vredegerecht",
    "wof:placetype":"venue"
},
  "geometry": {"coordinates":[3.5237998962,50.9821815491],"type":"Point"}
}