{
  "type": "Feature",
  "properties": {
    "iso:country":"BE",
    "sg:address":"Chauss\u00c9e De Dinant 4",
    "sg:city":"Anh\u00c9e",
    "sg:orig_category":"Herstellingen and onderhoud van auto's",
    "sg:phone":"+32 82 61 21 22",
    "sg:postcode":"5537",
    "sg:province":"Namur",
    "wof:name":"Multi Services Coppens",
    "wof:placetype":"venue"
},
  "geometry": {"coordinates":[4.8810038567,50.3085594177],"type":"Point"}
}