{
  "type": "Feature",
  "properties": {
    "addr:full":"Rue Vankeerberghen 35 Huy Li\u00e8ge 4500",
    "addr:housenumber":"35",
    "addr:postcode":"4500",
    "addr:street":"Rue Vankeerberghen",
    "iso:country":"BE",
    "sg:address":"Rue Vankeerberghen 35",
    "sg:city":"Huy",
    "sg:classifiers":[
        {
            "category":"Professional",
            "subcategory":"Lawyer & Legal Services",
            "type":"Services"
        }
    ],
    "sg:phone":"+32 85 27 43 50",
    "sg:postcode":"4500",
    "sg:province":"Li\u00e8ge",
    "sg:tags":[
        "notary"
    ],
    "wof:name":"Battaille J",
    "wof:placetype":"venue"
},
  "geometry": {"coordinates":[5.2444119453,50.5191612244],"type":"Point"}
}