{
  "type": "Feature",
  "properties": {
    "iso:country":"BE",
    "sg:address":"Kortrijkstraat 122ba",
    "sg:city":"Menen",
    "sg:classifiers":[
        {
            "category":"Cafe",
            "type":"Food & Drink"
        }
    ],
    "sg:phone":"+32 56 51 20 45",
    "sg:postcode":"8930",
    "sg:province":"West-Vlaanderen",
    "sg:tags":[
        "caf\u00e9s"
    ],
    "wof:name":"Luc Vandenhoeke",
    "wof:placetype":"venue"
},
  "geometry": {"coordinates":[3.1257760525,50.7968673706],"type":"Point"}
}