{
  "type": "Feature",
  "properties": {
    "addr:full":"Kapelanielaan 4 Temse Oost-Vlaanderen 9140",
    "addr:housenumber":"4",
    "addr:postcode":"9140",
    "addr:street":"Kapelanielaan",
    "iso:country":"BE",
    "sg:address":"Kapelanielaan 4",
    "sg:city":"Temse",
    "sg:orig_category":"Voertuigen",
    "sg:phone":"+32 3 711 14 44",
    "sg:postcode":"9140",
    "sg:province":"Oost-Vlaanderen",
    "wof:name":"Iveco Waasland",
    "wof:placetype":"venue"
},
  "geometry": {"coordinates":[4.1772141457,51.1390991211],"type":"Point"}
}