{
  "type": "Feature",
  "properties": {
    "iso:country":"BE",
    "sg:address":"Rue De L'industrie 27",
    "sg:city":"Namur (saint-servais)",
    "sg:classifiers":[
        {
            "category":"Mining & Drilling",
            "type":"Manufacturing & Wholesale Goods"
        }
    ],
    "sg:phone":"+32 81 73 11 26",
    "sg:postcode":"5002",
    "sg:province":"Namur",
    "sg:tags":[
        "quarry"
    ],
    "wof:name":"Briot Sa (carri\u00e8re & Scierie)",
    "wof:placetype":"venue"
},
  "geometry": {"coordinates":[4.8540410995,50.4740524292],"type":"Point"}
}