{
  "type": "Feature",
  "properties": {
    "iso:country":"BE",
    "sg:address":"Rue Van Wambeek 45",
    "sg:city":"Sint-jans-molenbeek/molenbeek-",
    "sg:orig_category":"Etablissements Erotiques",
    "sg:phone":"+32 2 411 34 14",
    "sg:postcode":"1080",
    "sg:province":"Bruxelles-Capitale",
    "wof:name":"Le Sinclair Studio",
    "wof:placetype":"venue"
},
  "geometry": {"coordinates":[4.3023428917,50.8492355347],"type":"Point"}
}