{
  "type": "Feature",
  "properties": {
    "addr:full":"Av De La Bugrane N\u00b01 Bruxelles Bruxelles-Capitale 1020",
    "addr:housenumber":"n\u00b01",
    "addr:postcode":"1020",
    "addr:street":"Av De La Bugrane",
    "iso:country":"BE",
    "sg:address":"Av De La Bugrane N\u00b01",
    "sg:city":"Bruxelles",
    "sg:classifiers":[
        {
            "category":"Professional",
            "subcategory":"Business Services",
            "type":"Services"
        }
    ],
    "sg:phone":"+32 2 268 29 77",
    "sg:postcode":"1020",
    "sg:province":"Bruxelles-Capitale",
    "sg:tags":[
        "training",
        "advice"
    ],
    "wof:name":"Zusters Van Vorselaar",
    "wof:placetype":"venue"
},
  "geometry": {"coordinates":[4.3462300301,50.8855514526],"type":"Point"}
}