{
  "type": "Feature",
  "properties": {
    "addr:full":"Rue Turenne 46 Charleroi Hainaut 6000",
    "addr:housenumber":"46",
    "addr:postcode":"6000",
    "addr:street":"Rue Turenne;Hainaut",
    "iso:country":"BE",
    "sg:address":"Rue Turenne 46",
    "sg:city":"Charleroi",
    "sg:orig_category":"Beschutte werkplaatsen",
    "sg:phone":"+32 71 32 88 22",
    "sg:postcode":"6000",
    "sg:province":"Hainaut",
    "wof:name":"Atel. Prot. Ligue Braille",
    "wof:placetype":"venue"
},
  "geometry": {"coordinates":[4.4405012131,50.4116592407],"type":"Point"}
}