{
  "type": "Feature",
  "properties": {
    "addr:full":"Stationsstraat 26 Meise (wolvertem) Vlaams-Brabant 1861",
    "addr:housenumber":"26",
    "addr:postcode":"1861",
    "addr:street":"Stationsstraat",
    "iso:country":"BE",
    "sg:address":"Stationsstraat 26",
    "sg:city":"Meise (wolvertem)",
    "sg:classifiers":[
        {
            "category":"Travel",
            "subcategory":"Resort",
            "type":"Entertainment"
        }
    ],
    "sg:phone":"+32 2 270 02 38",
    "sg:postcode":"1861",
    "sg:province":"Vlaams-Brabant",
    "sg:tags":[
        "health"
    ],
    "wof:name":"De Levensgenieter",
    "wof:placetype":"venue"
},
  "geometry": {"coordinates":[4.3115181923,50.9493980408],"type":"Point"}
}