{
  "type": "Feature",
  "properties": {
    "addr:full":"Rue De Dour 412 Boussu Hainaut 7300",
    "addr:housenumber":"412",
    "addr:postcode":"7300",
    "addr:street":"Rue De Dour",
    "iso:country":"BE",
    "sg:address":"Rue De Dour 412",
    "sg:city":"Boussu",
    "sg:orig_category":"Kapsalons",
    "sg:phone":"+32 65 65 01 38",
    "sg:postcode":"7300",
    "sg:province":"Hainaut",
    "wof:name":"Coiffure Hair Style",
    "wof:placetype":"venue"
},
  "geometry": {"coordinates":[3.7864499092,50.4198112488],"type":"Point"}
}