{
  "type": "Feature",
  "properties": {
    "addr:full":"Kokelarestraat 66 Izegem West-Vlaanderen 8870",
    "addr:housenumber":"66",
    "addr:postcode":"8870",
    "addr:street":"Kokelarestraat",
    "iso:country":"BE",
    "sg:address":"Kokelarestraat 66",
    "sg:city":"Izegem",
    "sg:orig_category":"Installation \u00e9lectrique r\u00e9sidentielle",
    "sg:phone":"+32 51 33 50 10",
    "sg:postcode":"8870",
    "sg:province":"West-Vlaanderen",
    "wof:name":"Hanssens Telecommunicat.",
    "wof:placetype":"venue"
},
  "geometry": {"coordinates":[3.1906409264,50.9098892212],"type":"Point"}
}