{
  "type": "Feature",
  "properties": {
    "addr:full":"Rue Arthur Snaps 44 Grez-doiceau Brabant Wallon 1390",
    "addr:housenumber":"44",
    "addr:postcode":"1390",
    "addr:street":"Rue Arthur Snaps",
    "iso:country":"BE",
    "sg:address":"Rue Arthur Snaps 44",
    "sg:city":"Grez-doiceau",
    "sg:orig_category":"Catering and organisation de f\u00eates",
    "sg:phone":"+32 10 84 50 81",
    "sg:postcode":"1390",
    "sg:province":"Brabant Wallon",
    "wof:name":"Didier Van Bever",
    "wof:placetype":"venue"
},
  "geometry": {"coordinates":[4.6546721458,50.7737236023],"type":"Point"}
}