{
  "type": "Feature",
  "properties": {
    "iso:country":"BE",
    "sg:address":"Rue Saint-ursmer 43",
    "sg:city":"Ath (ormeignies)",
    "sg:classifiers":[
        {
            "category":"Bars & Pubs",
            "type":"Food & Drink"
        }
    ],
    "sg:phone":"+32 68 28 12 18",
    "sg:postcode":"7802",
    "sg:province":"Hainaut",
    "wof:name":"R\u00e9tro (le)",
    "wof:placetype":"venue"
},
  "geometry": {"coordinates":[3.7504498959,50.5941886902],"type":"Point"}
}