{
  "type": "Feature",
  "properties": {
    "iso:country":"BE",
    "sg:address":"Rue De Blindef 7ba",
    "sg:city":"Sprimont",
    "sg:orig_category":"Woningbouw",
    "sg:phone":"+32 4 360 90 77",
    "sg:postcode":"4141",
    "sg:province":"Li\u00e8ge",
    "wof:name":"G.danhieux",
    "wof:placetype":"venue"
},
  "geometry": {"coordinates":[5.7102560997,50.5312538147],"type":"Point"}
}