{
  "type": "Feature",
  "properties": {
    "iso:country":"BE",
    "sg:address":"Veurnestraat 113",
    "sg:city":"Poperinge",
    "sg:orig_category":"Boucheries",
    "sg:phone":"+32 57 33 35 93",
    "sg:postcode":"8970",
    "sg:province":"West-Vlaanderen",
    "wof:name":"Rik Goussey",
    "wof:placetype":"venue"
},
  "geometry": {"coordinates":[2.7298309803,50.8591575623],"type":"Point"}
}