{
  "type": "Feature",
  "properties": {
    "iso:country":"BE",
    "sg:address":"Gebroeders De Smetstraat 9",
    "sg:city":"Gent",
    "sg:orig_category":"Newspapers, magazines, periodicals - Distribution",
    "sg:phone":"+32 9 224 24 14",
    "sg:postcode":"9000",
    "sg:province":"Oost-Vlaanderen",
    "wof:name":"Krantje ('t)",
    "wof:placetype":"venue"
},
  "geometry": {"coordinates":[3.7049319744,51.0632476807],"type":"Point"}
}