{
  "type": "Feature",
  "properties": {
    "iso:country":"BE",
    "sg:address":"Meersstraat 10",
    "sg:city":"Gavere (baaigem)",
    "sg:classifiers":[
        {
            "category":"Building & Trades",
            "subcategory":"Electrical",
            "type":"Services"
        }
    ],
    "sg:phone":"+32 9 362 41 85",
    "sg:postcode":"9890",
    "sg:province":"Oost-Vlaanderen",
    "sg:tags":[
        "electric",
        "-",
        "housewiring",
        "contractor"
    ],
    "wof:name":"Cnockaert M",
    "wof:placetype":"venue"
},
  "geometry": {"coordinates":[3.7301518917,50.9317169189],"type":"Point"}
}