{
  "type": "Feature",
  "properties": {
    "addr:full":"Rue De Valenciennes 459 Boussu Hainaut 7300",
    "addr:housenumber":"459",
    "addr:postcode":"7300",
    "addr:street":"Rue De Valenciennes",
    "iso:country":"BE",
    "sg:address":"Rue De Valenciennes 459",
    "sg:city":"Boussu",
    "sg:classifiers":[
        {
            "category":"Retail",
            "subcategory":"Auto Repair",
            "type":"Services"
        }
    ],
    "sg:phone":"+32 65 78 45 25",
    "sg:postcode":"7300",
    "sg:province":"Hainaut",
    "sg:tags":[
        "lpg",
        "automobile",
        "-",
        "system"
    ],
    "wof:name":"Boussu Motor Sprl",
    "wof:placetype":"venue"
},
  "geometry": {"coordinates":[3.8059179783,50.4321975708],"type":"Point"}
}