{
  "type": "Feature",
  "properties": {
    "iso:country":"BE",
    "sg:address":"Belgradostraat 70",
    "sg:city":"Gent",
    "sg:classifiers":[
        {
            "category":"Cafe",
            "type":"Food & Drink"
        }
    ],
    "sg:phone":"+32 9 225 97 00",
    "sg:postcode":"9000",
    "sg:province":"Oost-Vlaanderen",
    "sg:tags":[
        "caf\u00e9s"
    ],
    "wof:name":"Clin Josette",
    "wof:placetype":"venue"
},
  "geometry": {"coordinates":[3.7326889038,51.0510864258],"type":"Point"}
}