{
  "type": "Feature",
  "properties": {
    "addr:full":"Pas 25 Geel Antwerpen 2440",
    "addr:housenumber":"25",
    "addr:postcode":"2440",
    "addr:street":"Pas",
    "iso:country":"BE",
    "sg:address":"Pas 25",
    "sg:city":"Geel",
    "sg:classifiers":[
        {
            "category":"Shopping",
            "subcategory":"Jewelry",
            "type":"Retail Goods"
        }
    ],
    "sg:phone":"+32 14 59 04 83",
    "sg:postcode":"2440",
    "sg:province":"Antwerpen",
    "sg:tags":[
        "-",
        "imitation"
    ],
    "wof:name":"Twice As Nice",
    "wof:placetype":"venue"
},
  "geometry": {"coordinates":[4.9898381233,51.1598052979],"type":"Point"}
}