{
  "type": "Feature",
  "properties": {
    "iso:country":"BE",
    "sg:address":"Rode Dreef 23",
    "sg:city":"Wijnegem",
    "sg:orig_category":"Mat\u00e9riel m\u00e9dical and orthop\u00e9dique and proth\u00e8ses Fab",
    "sg:phone":"+32 3 353 63 44",
    "sg:postcode":"2110",
    "sg:province":"Antwerpen",
    "wof:name":"Kefel D.t.b.",
    "wof:placetype":"venue"
},
  "geometry": {"coordinates":[4.5468502045,51.2253837585],"type":"Point"}
}