{
  "type": "Feature",
  "properties": {
    "iso:country":"BE",
    "sg:address":"Rue De Tr\u00e9mouroux 3",
    "sg:city":"Floreffe (frani\u00e8re)",
    "sg:classifiers":[
        {
            "category":"Building & Trades",
            "subcategory":"Landscaping Services",
            "type":"Services"
        }
    ],
    "sg:phone":"+32 81 44 15 83",
    "sg:postcode":"5150",
    "sg:province":"Namur",
    "sg:tags":[
        "moss",
        "removal"
    ],
    "wof:name":"Eurodemoussage",
    "wof:placetype":"venue"
},
  "geometry": {"coordinates":[4.7320790291,50.4344139099],"type":"Point"}
}