{
  "type": "Feature",
  "properties": {
    "iso:country":"BE",
    "sg:address":"Kalkoven 89",
    "sg:city":"Asse",
    "sg:classifiers":[
        {
            "category":"Farming",
            "subcategory":"Fish & Marine Products",
            "type":"Manufacturing & Wholesale Goods"
        }
    ],
    "sg:phone":"+32 2 452 67 52",
    "sg:postcode":"1730",
    "sg:province":"Vlaams-Brabant",
    "sg:tags":[
        "retail",
        "-",
        "shellfish"
    ],
    "wof:name":"Zeester (de)",
    "wof:placetype":"venue"
},
  "geometry": {"coordinates":[4.194671154,50.9130516052],"type":"Point"}
}