{
  "type": "Feature",
  "properties": {
    "iso:country":"BE",
    "sg:address":"Rue Bouteille 30",
    "sg:city":"Olne",
    "sg:orig_category":"Brood, gebak and snoepgoed",
    "sg:phone":"+32 87 26 70 87",
    "sg:postcode":"4877",
    "sg:province":"Li\u00e8ge",
    "wof:name":"Fr\u00c9d\u00c9ric",
    "wof:placetype":"venue"
},
  "geometry": {"coordinates":[5.7593598366,50.5990028381],"type":"Point"}
}