{
  "type": "Feature",
  "properties": {
    "iso:country":"BE",
    "sg:address":"Venlosesteenweg 108",
    "sg:city":"Maaseik",
    "sg:orig_category":"Medische apparatuur, orthopedische artikelen and prothesen Fab",
    "sg:phone":"+32 89 56 59 08",
    "sg:postcode":"3680",
    "sg:province":"Limburg",
    "wof:name":"Jozef Gorissen",
    "wof:placetype":"venue"
},
  "geometry": {"coordinates":[5.7975888252,51.1071624756],"type":"Point"}
}