{
  "type": "Feature",
  "properties": {
    "iso:country":"BE",
    "sg:address":"Kattestraat 24",
    "sg:city":"Aalst",
    "sg:classifiers":[
        {
            "category":"Banks & Credit Unions",
            "subcategory":"Investment Brokerage",
            "type":"Services"
        }
    ],
    "sg:phone":"+32 53 71 11 95",
    "sg:postcode":"9300",
    "sg:province":"Oost-Vlaanderen",
    "sg:tags":[
        "jean",
        "casual",
        "wear"
    ],
    "wof:name":"Kaviaar",
    "wof:placetype":"venue"
},
  "geometry": {"coordinates":[4.0377988815,50.9390602112],"type":"Point"}
}