{
  "type": "Feature",
  "properties": {
    "iso:country":"BE",
    "sg:address":"Rue Des Sablons 15",
    "sg:city":"Bruxelles",
    "sg:classifiers":[
        {
            "category":"Home & Garden",
            "subcategory":"Carpets & Floor Coverings",
            "type":"Retail Goods"
        }
    ],
    "sg:phone":"+32 2 513 78 55",
    "sg:postcode":"1000",
    "sg:province":"Bruxelles-Capitale",
    "sg:tags":[
        "oriental"
    ],
    "wof:name":"Achete Ancien Tapis",
    "wof:placetype":"venue"
},
  "geometry": {"coordinates":[4.3556060791,50.8398208618],"type":"Point"}
}