{
  "type": "Feature",
  "properties": {
    "iso:country":"BE",
    "sg:address":"Reinpadstraat 21b4",
    "sg:city":"Genk",
    "sg:orig_category":"Benzinestations and brandstoffen",
    "sg:phone":"+32 89 35 97 68",
    "sg:postcode":"3600",
    "sg:province":"Limburg",
    "wof:name":"Jean Dubois",
    "wof:placetype":"venue"
},
  "geometry": {"coordinates":[5.50496912,50.9690589905],"type":"Point"}
}