{
  "type": "Feature",
  "properties": {
    "iso:country":"BE",
    "sg:address":"Naamsesteenweg 205",
    "sg:city":"Leuven (heverlee)",
    "sg:classifiers":[
        {
            "category":"Bars & Pubs",
            "type":"Food & Drink"
        }
    ],
    "sg:phone":"+32 16 20 44 13",
    "sg:postcode":"3001",
    "sg:province":"Vlaams-Brabant",
    "wof:name":"Funck",
    "wof:placetype":"venue"
},
  "geometry": {"coordinates":[4.6959738731,50.8627090454],"type":"Point"}
}