{
  "type": "Feature",
  "properties": {
    "addr:full":"Lage Kaart 354 Brasschaat Antwerpen 2930",
    "addr:housenumber":"354",
    "addr:postcode":"2930",
    "addr:street":"Lage Kaart",
    "iso:country":"BE",
    "sg:address":"Lage Kaart 354",
    "sg:city":"Brasschaat",
    "sg:orig_category":"Dranken",
    "sg:phone":"+32 3 653 35 28",
    "sg:postcode":"2930",
    "sg:province":"Antwerpen",
    "wof:name":"Huis Lauwers",
    "wof:placetype":"venue"
},
  "geometry": {"coordinates":[4.4843530655,51.3034248352],"type":"Point"}
}