{
  "type": "Feature",
  "properties": {
    "addr:full":"Rue De Clairvaux 40-204 Ottignies-louvain-la-neuve (louvain-la-neuve) Brabant Wallon 1348",
    "addr:postcode":"40-204;1348",
    "addr:street":"Rue De Clairvaux",
    "iso:country":"BE",
    "sg:address":"Rue De Clairvaux 40-204",
    "sg:city":"Ottignies-louvain-la-neuve (louvain-la-neuve)",
    "sg:classifiers":[
        {
            "category":"Professional",
            "subcategory":"Accounting & Tax Preparation",
            "type":"Services"
        }
    ],
    "sg:phone":"+32 10 22 55 56",
    "sg:postcode":"1348",
    "sg:province":"Brabant Wallon",
    "sg:tags":[
        "accountant"
    ],
    "wof:name":"Ollieuz G",
    "wof:placetype":"venue"
},
  "geometry": {"coordinates":[4.6189308167,50.6766014099],"type":"Point"}
}