{
  "type": "Feature",
  "properties": {
    "addr:full":"Cour Robert 55 Saint-nicolas Li\u00e8ge 4420",
    "addr:housenumber":"55",
    "addr:postcode":"4420",
    "addr:street":"Cour Robert",
    "iso:country":"BE",
    "sg:address":"Cour Robert 55",
    "sg:city":"Saint-nicolas",
    "sg:orig_category":"Kapsalons",
    "sg:phone":"+32 4 231 30 84",
    "sg:postcode":"4420",
    "sg:province":"Li\u00e8ge",
    "wof:name":"Fabian Nuyts",
    "wof:placetype":"venue"
},
  "geometry": {"coordinates":[5.52983284,50.6216850281],"type":"Point"}
}