{
  "type": "Feature",
  "properties": {
    "iso:country":"BE",
    "sg:address":"Kemmelbergstraat 26",
    "sg:city":"Oostende",
    "sg:orig_category":"Pain, p\u00e2tisseries and confiseries",
    "sg:phone":"+32 59 70 40 43",
    "sg:postcode":"8400",
    "sg:province":"West-Vlaanderen",
    "wof:name":"Patrick Boudengen",
    "wof:placetype":"venue"
},
  "geometry": {"coordinates":[2.9091560841,51.2287750244],"type":"Point"}
}