{
  "type": "Feature",
  "properties": {
    "iso:country":"BE",
    "sg:address":"Lloyd Georgelaan 16",
    "sg:city":"Brussel/bruxelles",
    "sg:orig_category":"Antiek Diverse zakelijke dienstverlening",
    "sg:phone":"+32 2 640 69 48",
    "sg:postcode":"1000",
    "sg:province":"Bruxelles-Capitale",
    "wof:name":"Philippe Guimiot/ph. Guimiot",
    "wof:placetype":"venue"
},
  "geometry": {"coordinates":[4.3761658669,50.8155174255],"type":"Point"}
}