{
  "type": "Feature",
  "properties": {
    "addr:full":"K. Janssenslaan 45 Oostende West-Vlaanderen 8400",
    "addr:housenumber":"45",
    "addr:postcode":"8400",
    "addr:street":"K. Janssenslaan",
    "iso:country":"BE",
    "sg:address":"K. Janssenslaan 45",
    "sg:city":"Oostende",
    "sg:orig_category":"Industri\u00eble wasserijen and droogkuis",
    "sg:phone":"+32 59 70 75 98",
    "sg:postcode":"8400",
    "sg:province":"West-Vlaanderen",
    "wof:name":"Automatik Service",
    "wof:placetype":"venue"
},
  "geometry": {"coordinates":[2.9112598896,51.2285232544],"type":"Point"}
}