{
  "type": "Feature",
  "properties": {
    "addr:full":"Route De Surister 19 Jalhay Li\u00e8ge 4845",
    "addr:housenumber":"19",
    "addr:postcode":"4845",
    "addr:street":"Route De Surister",
    "iso:country":"BE",
    "sg:address":"Route De Surister 19",
    "sg:city":"Jalhay",
    "sg:classifiers":[
        {
            "category":"Building & Trades",
            "subcategory":"Pest Control",
            "type":"Services"
        }
    ],
    "sg:phone":"+32 495 23 38 99",
    "sg:postcode":"4845",
    "sg:province":"Li\u00e8ge",
    "sg:tags":[
        "painting",
        "contractor"
    ],
    "wof:name":"Fonsny V",
    "wof:placetype":"venue"
},
  "geometry": {"coordinates":[5.926030159,50.5511703491],"type":"Point"}
}