{
  "type": "Feature",
  "properties": {
    "addr:full":"Geeraard De Cremerstraat 3 Kruibeke (rupelmonde) Oost-Vlaanderen 9150",
    "addr:housenumber":"3",
    "addr:postcode":"9150",
    "addr:street":"Geeraard De Cremerstraat",
    "iso:country":"BE",
    "sg:address":"Geeraard De Cremerstraat 3",
    "sg:city":"Kruibeke (rupelmonde)",
    "sg:classifiers":[
        {
            "category":"Bars & Pubs",
            "type":"Food & Drink"
        }
    ],
    "sg:phone":"+32 3 744 17 79",
    "sg:postcode":"9150",
    "sg:province":"Oost-Vlaanderen",
    "sg:tags":[
        "tavern"
    ],
    "wof:name":"Gildenhuis ('t)",
    "wof:placetype":"venue"
},
  "geometry": {"coordinates":[4.2911429405,51.1279335022],"type":"Point"}
}