{
  "type": "Feature",
  "properties": {
    "addr:full":"Hoogstraat 24 Heist-op-den-berg (schriek) Antwerpen 2223",
    "addr:housenumber":"24",
    "addr:postcode":"2223",
    "addr:street":"Hoogstraat",
    "iso:country":"BE",
    "sg:address":"Hoogstraat 24",
    "sg:city":"Heist-op-den-berg (schriek)",
    "sg:classifiers":[
        {
            "category":"Bakery",
            "type":"Food & Drink"
        }
    ],
    "sg:phone":"+32 15 23 31 24",
    "sg:postcode":"2223",
    "sg:province":"Antwerpen",
    "sg:tags":[
        "confectioner",
        "baker"
    ],
    "wof:name":"Gregor",
    "wof:placetype":"venue"
},
  "geometry": {"coordinates":[4.6935648918,51.0282707214],"type":"Point"}
}