{
  "type": "Feature",
  "properties": {
    "addr:full":"Rue Nysten 44 Li\u00e8ge 1 Li\u00e8ge 4000",
    "addr:housenumber":"44;1",
    "addr:postcode":"4000",
    "addr:street":"Rue Nysten",
    "iso:country":"BE",
    "sg:address":"Rue Nysten 44",
    "sg:city":"Li\u00e8ge 1",
    "sg:classifiers":[
        {
            "category":"Real Estate",
            "subcategory":"Real Estate Services",
            "type":"Services"
        }
    ],
    "sg:phone":"+32 4 253 35 85",
    "sg:postcode":"4000",
    "sg:province":"Li\u00e8ge",
    "wof:name":"Immo Def & Jd Sa",
    "wof:placetype":"venue"
},
  "geometry": {"coordinates":[5.561563015,50.6333312988],"type":"Point"}
}