{
  "type": "Feature",
  "properties": {
    "addr:full":"Rue Jules Dekeyn 4 Braine-le-comte (ronqui\u00e8res) Hainaut 7090",
    "addr:housenumber":"4",
    "addr:postcode":"7090",
    "addr:street":"Rue Jules Dekeyn;Ronquie\u0300Res Hainaut",
    "iso:country":"BE",
    "sg:address":"Rue Jules Dekeyn 4",
    "sg:city":"Braine-le-comte (ronqui\u00e8res)",
    "sg:classifiers":[
        {
            "category":"Health Services",
            "subcategory":"Dentist",
            "type":"Services"
        }
    ],
    "sg:phone":"+32 67 64 63 84",
    "sg:postcode":"7090",
    "sg:province":"Hainaut",
    "wof:name":"Van Haute Ghislain",
    "wof:placetype":"venue"
},
  "geometry": {"coordinates":[4.2221632004,50.6093940735],"type":"Point"}
}