{
  "type": "Feature",
  "properties": {
    "iso:country":"BE",
    "sg:address":"Stationsdreef 36",
    "sg:city":"Roeselare",
    "sg:orig_category":"Fruits and l\u00e9gumes Produits surgel\u00e9s Gr",
    "sg:phone":"+32 51 22 63 35",
    "sg:postcode":"8800",
    "sg:province":"West-Vlaanderen",
    "wof:name":"Prodiro",
    "wof:placetype":"venue"
},
  "geometry": {"coordinates":[3.1282160282,50.9528503418],"type":"Point"}
}