{
  "type": "Feature",
  "properties": {
    "iso:country":"BE",
    "sg:address":"Kipdorpvest 40",
    "sg:city":"Antwerpen",
    "sg:classifiers":[
        {
            "category":"Cafe",
            "type":"Food & Drink"
        }
    ],
    "sg:phone":"+32 3 225 27 00",
    "sg:postcode":"2000",
    "sg:province":"Antwerpen",
    "sg:tags":[
        "snack-bars"
    ],
    "wof:name":"The Better Sandwich Company",
    "wof:placetype":"venue"
},
  "geometry": {"coordinates":[4.4139318466,51.2178421021],"type":"Point"}
}