{
  "type": "Feature",
  "properties": {
    "iso:country":"BE",
    "sg:address":"Iepersestraat 382",
    "sg:city":"Roeselare",
    "sg:orig_category":"Traitements param\u00e9dicaux",
    "sg:phone":"+32 51 20 64 14",
    "sg:postcode":"8800",
    "sg:province":"West-Vlaanderen",
    "wof:name":"C. Vandecasteele",
    "wof:placetype":"venue"
},
  "geometry": {"coordinates":[3.1061639786,50.9360237122],"type":"Point"}
}