{
  "type": "Feature",
  "properties": {
    "addr:full":"21 Bert Leysenlaan 2490 Balen 21",
    "addr:housenumber":"21;21",
    "addr:postcode":"2490",
    "addr:street":"Bert Leysenlaan",
    "iso:country":"BE",
    "sg:address":"21",
    "sg:city":"Bert Leysenlaan 2490 Balen",
    "sg:classifiers":[
        {
            "category":"Professional",
            "subcategory":"Business Services",
            "type":"Services"
        }
    ],
    "sg:phone":"+32 14 81 17 29",
    "sg:postcode":"21",
    "sg:tags":[
        "travel",
        "fair"
    ],
    "wof:name":"Traiteur Saelen Jos Bvba",
    "wof:placetype":"venue"
},
  "geometry": {"coordinates":[5.1621599197,51.1743202209],"type":"Point"}
}