{
  "type": "Feature",
  "properties": {
    "addr:full":"Rue Du Moulin D'havr\u00e9 39 Mons (havr\u00e9) Hainaut 7021",
    "addr:housenumber":"39",
    "addr:postcode":"7021",
    "addr:street":"Rue Du Moulin D'Havre \u0301",
    "iso:country":"BE",
    "sg:address":"Rue Du Moulin D'havr\u00e9 39",
    "sg:city":"Mons (havr\u00e9)",
    "sg:classifiers":[
        {
            "category":"Arena",
            "subcategory":"Sports Club",
            "type":"Entertainment"
        }
    ],
    "sg:phone":"+32 65 87 29 71",
    "sg:postcode":"7021",
    "sg:province":"Hainaut",
    "wof:name":"Tennis Club Havr\u00e9",
    "wof:placetype":"venue"
},
  "geometry": {"coordinates":[4.0448040962,50.4641685486],"type":"Point"}
}