{
  "type": "Feature",
  "properties": {
    "addr:full":"Oude Markt 36 Leuven Vlaams-Brabant 3000",
    "addr:housenumber":"36",
    "addr:postcode":"3000",
    "addr:street":"Oude Markt",
    "iso:country":"BE",
    "sg:address":"Oude Markt 36",
    "sg:city":"Leuven",
    "sg:classifiers":[
        {
            "category":"Cafe",
            "type":"Food & Drink"
        }
    ],
    "sg:phone":"+32 16 29 10 75",
    "sg:postcode":"3000",
    "sg:province":"Vlaams-Brabant",
    "sg:tags":[
        "caf\u00e9s"
    ],
    "wof:name":"De Kroeg",
    "wof:placetype":"venue"
},
  "geometry": {"coordinates":[4.6990699768,50.8780288696],"type":"Point"}
}