{
  "type": "Feature",
  "properties": {
    "addr:full":"Olenseweg 375 Westerlo Antwerpen 2260",
    "addr:housenumber":"375",
    "addr:postcode":"2260",
    "addr:street":"Olenseweg",
    "iso:country":"BE",
    "sg:address":"Olenseweg 375",
    "sg:city":"Westerlo",
    "sg:classifiers":[
        {
            "category":"Health Services",
            "subcategory":"Doctor",
            "type":"Services"
        }
    ],
    "sg:phone":"+32 14 26 69 91",
    "sg:postcode":"2260",
    "sg:province":"Antwerpen",
    "sg:tags":[
        "medicinephysicians",
        "surgeon"
    ],
    "wof:name":"Bens Joeri",
    "wof:placetype":"venue"
},
  "geometry": {"coordinates":[4.8694601059,51.10546875],"type":"Point"}
}