{
  "type": "Feature",
  "properties": {
    "iso:country":"BE",
    "sg:address":"Rue Du Vivier 44",
    "sg:city":"Bastogne",
    "sg:orig_category":"Baby- and kinderkleding",
    "sg:phone":"+32 61 21 13 17",
    "sg:postcode":"6600",
    "sg:province":"Luxembourg",
    "wof:name":"Z",
    "wof:placetype":"venue"
},
  "geometry": {"coordinates":[5.7173857689,50.0019989014],"type":"Point"}
}