{
  "type": "Feature",
  "properties": {
    "iso:country":"BE",
    "sg:address":"Murissonstraat 302",
    "sg:city":"Menen",
    "sg:orig_category":"Diverse bouwafwerking and reiniging Pleisterwerk",
    "sg:phone":"+32 56 40 27 11",
    "sg:postcode":"8930",
    "sg:province":"West-Vlaanderen",
    "wof:name":"Marnix Poublon",
    "wof:placetype":"venue"
},
  "geometry": {"coordinates":[3.1532800198,50.7858886719],"type":"Point"}
}