{
  "type": "Feature",
  "properties": {
    "addr:full":"Hertog Van Brabantlaan 61 Landen Vlaams-Brabant 3400",
    "addr:housenumber":"61",
    "addr:postcode":"3400",
    "addr:street":"Hertog Van Brabantlaan",
    "iso:country":"BE",
    "sg:address":"Hertog Van Brabantlaan 61",
    "sg:city":"Landen",
    "sg:orig_category":"Sociale huisvestingsmaatschappijen",
    "sg:phone":"+32 11 88 21 58",
    "sg:postcode":"3400",
    "sg:province":"Vlaams-Brabant",
    "wof:name":"Soc. Woningen Van Landen",
    "wof:placetype":"venue"
},
  "geometry": {"coordinates":[5.0843811035,50.7528190613],"type":"Point"}
}