{
  "type": "Feature",
  "properties": {
    "addr:full":"Kerkhoflei 61 Zoersel Antwerpen 2980",
    "addr:housenumber":"61",
    "addr:postcode":"2980",
    "addr:street":"Kerkhoflei",
    "iso:country":"BE",
    "sg:address":"Kerkhoflei 61",
    "sg:city":"Zoersel",
    "sg:classifiers":[
        {
            "category":"Retail",
            "subcategory":"Animal Services",
            "type":"Services"
        }
    ],
    "sg:phone":"+32 3 383 52 62",
    "sg:postcode":"2980",
    "sg:province":"Antwerpen",
    "sg:tags":[
        "grooming",
        "-",
        "dog"
    ],
    "wof:name":"Cartouche Hondenkapsalon",
    "wof:placetype":"venue"
},
  "geometry": {"coordinates":[4.713435173,51.269985199],"type":"Point"}
}