{
  "type": "Feature",
  "properties": {
    "addr:full":"Zandvliet 2 Dessel Antwerpen 2480",
    "addr:housenumber":"2",
    "addr:postcode":"2480",
    "addr:street":"Zandvliet",
    "iso:country":"BE",
    "sg:address":"Zandvliet 2",
    "sg:city":"Dessel",
    "sg:classifiers":[
        {
            "category":"Education",
            "subcategory":"School",
            "type":"Public Place"
        }
    ],
    "sg:phone":"+32 14 37 86 65",
    "sg:postcode":"2480",
    "sg:province":"Antwerpen",
    "sg:tags":[
        "primary"
    ],
    "wof:name":"Gemeenschapsonderwijs-buitengewone Basisscholen",
    "wof:placetype":"venue"
},
  "geometry": {"coordinates":[5.1186928749,51.2371025085],"type":"Point"}
}