{
  "type": "Feature",
  "properties": {
    "addr:full":"Route De Mons 12 Charleroi (dampremy) Hainaut 6020",
    "addr:housenumber":"12",
    "addr:postcode":"6020",
    "addr:street":"Route De Mons",
    "iso:country":"BE",
    "sg:address":"Route De Mons 12",
    "sg:city":"Charleroi (dampremy)",
    "sg:orig_category":"Accumulators",
    "sg:phone":"+32 87 22 21 01",
    "sg:postcode":"6020",
    "sg:province":"Hainaut",
    "wof:name":"Devillers Autodistribution",
    "wof:placetype":"venue"
},
  "geometry": {"coordinates":[4.4353470802,50.4120178223],"type":"Point"}
}