{
  "type": "Feature",
  "properties": {
    "addr:full":"Loddershoek 6 Lennik Vlaams-Brabant 1750",
    "addr:housenumber":"6;1750",
    "addr:street":"Loddershoek;Vlaams-Brabant",
    "iso:country":"BE",
    "sg:address":"Loddershoek 6",
    "sg:city":"Lennik",
    "sg:orig_category":"Rev\u00eatements pour sols and murs. Peinture",
    "sg:phone":"+32 2 582 11 61",
    "sg:postcode":"1750",
    "sg:province":"Vlaams-Brabant",
    "wof:name":"Jan-baptist Segers",
    "wof:placetype":"venue"
},
  "geometry": {"coordinates":[4.1580109596,50.8359947205],"type":"Point"}
}