{
  "type": "Feature",
  "properties": {
    "addr:full":"Rue Forges-les-eaux 2 Herve Li\u00e8ge 4651",
    "addr:housenumber":"2",
    "addr:postcode":"4651",
    "addr:street":"Rue Forges-Les-Eaux",
    "iso:country":"BE",
    "sg:address":"Rue Forges-les-eaux 2",
    "sg:city":"Herve",
    "sg:orig_category":"Enseignement maternel and primaire",
    "sg:phone":"+32 87 67 85 70",
    "sg:postcode":"4651",
    "sg:province":"Li\u00e8ge",
    "wof:name":"Ecole Fond. Communale",
    "wof:placetype":"venue"
},
  "geometry": {"coordinates":[5.8225131035,50.6474494934],"type":"Point"}
}