{
  "type": "Feature",
  "properties": {
    "addr:full":"Liebaardstraat 81 Waregem West-Vlaanderen 8792",
    "addr:housenumber":"81",
    "addr:postcode":"8792",
    "addr:street":"Liebaardstraat",
    "iso:country":"BE",
    "sg:address":"Liebaardstraat 81",
    "sg:city":"Waregem",
    "sg:orig_category":"Catering and organisation de f\u00eates. Alimentation sp\u00e9cialis\u00e9e. Salles de conf\u00e9rences and de r\u00e9ception",
    "sg:phone":"+32 56 72 36 70",
    "sg:postcode":"8792",
    "sg:province":"West-Vlaanderen",
    "wof:name":"'t Smoefelke",
    "wof:placetype":"venue"
},
  "geometry": {"coordinates":[3.3530108929,50.8841285706],"type":"Point"}
}