{
  "type": "Feature",
  "properties": {
    "addr:full":"Ledeganckkaai 25 Antwerpen Antwerpen 2000",
    "addr:housenumber":"25",
    "addr:postcode":"2000",
    "addr:street":"Ledeganckkaai",
    "iso:country":"BE",
    "sg:address":"Ledeganckkaai 25",
    "sg:city":"Antwerpen",
    "sg:classifiers":[
        {
            "category":"Building & Trades",
            "subcategory":"Landscaping Services",
            "type":"Services"
        }
    ],
    "sg:phone":"+32 3 238 78 68",
    "sg:postcode":"2000",
    "sg:province":"Antwerpen",
    "sg:tags":[
        "etude",
        "technique",
        "ing\u00e9nierie"
    ],
    "wof:name":"European Systems Supply",
    "wof:placetype":"venue"
},
  "geometry": {"coordinates":[4.3805980682,51.2058868408],"type":"Point"}
}