{
  "type": "Feature",
  "properties": {
    "addr:full":"Avenue Des Pagodes 411b3 Brussel/bruxelles Bruxelles-Capitale 1020",
    "addr:housenumber":"411b3",
    "addr:postcode":"1020",
    "addr:street":"Avenue Des Pagodes;/",
    "iso:country":"BE",
    "sg:address":"Avenue Des Pagodes 411b3",
    "sg:city":"Brussel/bruxelles",
    "sg:classifiers":[
        {
            "category":"Personal",
            "subcategory":"Beauty Salon",
            "type":"Services"
        }
    ],
    "sg:phone":"+32 2 268 40 91",
    "sg:postcode":"1020",
    "sg:province":"Bruxelles-Capitale",
    "sg:tags":[
        "de",
        "coiffure"
    ],
    "wof:name":"Christine Legrand",
    "wof:placetype":"venue"
},
  "geometry": {"coordinates":[4.3594632149,50.8959236145],"type":"Point"}
}