{
  "type": "Feature",
  "properties": {
    "addr:full":"Rue Des Trois Entit\u00e9s 8 Thimister Li\u00e8ge 4890",
    "addr:housenumber":"8",
    "addr:postcode":"4890",
    "addr:street":"Rue Des Trois Entite\u0301S",
    "iso:country":"BE",
    "sg:address":"Rue Des Trois Entit\u00e9s 8",
    "sg:city":"Thimister",
    "sg:classifiers":[
        {
            "category":"Organizations",
            "subcategory":"Religious Organization",
            "type":"Services"
        }
    ],
    "sg:phone":"+32 87 31 60 16",
    "sg:postcode":"4890",
    "sg:province":"Li\u00e8ge",
    "sg:tags":[
        "ventilation",
        "system",
        "maintenance",
        "servicing"
    ],
    "wof:name":"Optitherm S.a.",
    "wof:placetype":"venue"
},
  "geometry": {"coordinates":[5.8855748177,50.6361160278],"type":"Point"}
}