{
  "type": "Feature",
  "properties": {
    "addr:full":"Place Du Chapitre Mons Hainaut 7000",
    "addr:postcode":"7000",
    "addr:street":"Place Du Chapitre;Hainaut",
    "iso:country":"BE",
    "sg:address":"Place Du Chapitre",
    "sg:city":"Mons",
    "sg:orig_category":"Mus\u00e9es and patrimoine culturel",
    "sg:phone":"+32 65 33 55 80",
    "sg:postcode":"7000",
    "sg:province":"Hainaut",
    "wof:name":"Tr\u00c9sor De La Coll\u00c9giale Sainte-waudru",
    "wof:placetype":"venue"
},
  "geometry": {"coordinates":[3.94836092,50.4530525208],"type":"Point"}
}