{
  "type": "Feature",
  "properties": {
    "iso:country":"BE",
    "sg:address":"Wontergemstraat 25",
    "sg:city":"Tielt",
    "sg:orig_category":"Rundveehouders Varkenskwekers",
    "sg:phone":"+32 51 63 46 28",
    "sg:postcode":"8700",
    "sg:province":"West-Vlaanderen",
    "wof:name":"Patrick Malfait",
    "wof:placetype":"venue"
},
  "geometry": {"coordinates":[3.4286770821,50.9894638062],"type":"Point"}
}