{
  "type": "Feature",
  "properties": {
    "addr:full":"Rue Du Fourneau 86 Li\u00e8ge 1 (grivegn\u00e9e) Li\u00e8ge 4030",
    "addr:housenumber":"86;1",
    "addr:postcode":"4030",
    "addr:street":"Rue Du Fourneau",
    "iso:country":"BE",
    "sg:address":"Rue Du Fourneau 86",
    "sg:city":"Li\u00e8ge 1 (grivegn\u00e9e)",
    "sg:classifiers":[
        {
            "category":"Retail",
            "subcategory":"Repair Shop",
            "type":"Services"
        }
    ],
    "sg:phone":"+32 4 344 28 60",
    "sg:postcode":"4030",
    "sg:province":"Li\u00e8ge",
    "sg:tags":[
        "upholsterer"
    ],
    "wof:name":"Vill\u00e9 S",
    "wof:placetype":"venue"
},
  "geometry": {"coordinates":[5.6029028893,50.6186180115],"type":"Point"}
}