{
  "type": "Feature",
  "properties": {
    "addr:full":"Dorp-oost 103ba Lochristi Oost-Vlaanderen 9080",
    "addr:postcode":"9080",
    "addr:street":"Oost-Vlaanderen",
    "iso:country":"BE",
    "sg:address":"Dorp-oost 103ba",
    "sg:city":"Lochristi",
    "sg:orig_category":"Airconditioning and ventilatie Loodgieterij, verwarming and sanitaire installaties",
    "sg:phone":"+32 9 355 98 39",
    "sg:postcode":"9080",
    "sg:province":"Oost-Vlaanderen",
    "wof:name":"Matthijs Dirk",
    "wof:placetype":"venue"
},
  "geometry": {"coordinates":[3.8436789513,51.0990753174],"type":"Point"}
}