{
  "type": "Feature",
  "properties": {
    "iso:country":"BE",
    "sg:address":"Avenue G\u00e9n\u00e9ral Jacques 25",
    "sg:city":"Nivelles",
    "sg:classifiers":[
        {
            "category":"Professional",
            "subcategory":"Lawyer & Legal Services",
            "type":"Services"
        }
    ],
    "sg:phone":"+32 67 21 50 31",
    "sg:postcode":"1400",
    "sg:province":"Brabant Wallon",
    "wof:name":"Hunger Michel",
    "wof:placetype":"venue"
},
  "geometry": {"coordinates":[4.3305010796,50.594745636],"type":"Point"}
}