{
  "type": "Feature",
  "properties": {
    "iso:country":"BE",
    "sg:address":"Rue Des Rocailles 13",
    "sg:city":"Farciennes (grand)",
    "sg:classifiers":[
        {
            "category":"Personal",
            "subcategory":"Beauty Salon",
            "type":"Services"
        }
    ],
    "sg:phone":"+32 71 39 33 80",
    "sg:postcode":"6240",
    "sg:province":"Hainaut",
    "sg:tags":[
        "de",
        "coiffure"
    ],
    "wof:name":"Lambreghts M",
    "wof:placetype":"venue"
},
  "geometry": {"coordinates":[4.537209034,50.4288406372],"type":"Point"}
}