{
  "type": "Feature",
  "properties": {
    "addr:full":"Hermkesstraat 6 Zutendaal Limburg 3690",
    "addr:housenumber":"6",
    "addr:postcode":"3690",
    "addr:street":"Hermkesstraat",
    "iso:country":"BE",
    "sg:address":"Hermkesstraat 6",
    "sg:city":"Zutendaal",
    "sg:orig_category":"Dakwerken",
    "sg:phone":"+32 89 61 34 52",
    "sg:postcode":"3690",
    "sg:province":"Limburg",
    "wof:name":"Gielen",
    "wof:placetype":"venue"
},
  "geometry": {"coordinates":[5.5570111275,50.9478874207],"type":"Point"}
}