{
  "type": "Feature",
  "properties": {
    "addr:full":"Rue Marie Solheid 30ba Malmedy/malmedy Li\u00e8ge 4960",
    "addr:housenumber":"30ba",
    "addr:postcode":"4960",
    "addr:street":"Rue Marie Solheid",
    "iso:country":"BE",
    "sg:address":"Rue Marie Solheid 30ba",
    "sg:city":"Malmedy/malmedy",
    "sg:orig_category":"Artsen and specialisten",
    "sg:phone":"+32 80 33 06 85",
    "sg:postcode":"4960",
    "sg:province":"Li\u00e8ge",
    "wof:name":"Sylvie Heinrichs",
    "wof:placetype":"venue"
},
  "geometry": {"coordinates":[6.068406105,50.4587745667],"type":"Point"}
}