{
  "type": "Feature",
  "properties": {
    "addr:full":"R Du Ry Angon 3 Mont-st-guibert Brabant Wallon 1435",
    "addr:housenumber":"3;1435",
    "addr:street":"R Du Ry Angon;Brabant Wallon",
    "iso:country":"BE",
    "sg:address":"R Du Ry Angon 3",
    "sg:city":"Mont-st-guibert",
    "sg:classifiers":[
        {
            "category":"Health Services",
            "subcategory":"Doctor",
            "type":"Services"
        }
    ],
    "sg:phone":"+32 476 99 70 77",
    "sg:postcode":"1435",
    "sg:province":"Brabant Wallon",
    "sg:tags":[
        "psychotherapist",
        "psychoanalyst"
    ],
    "wof:name":"Groulard A-c",
    "wof:placetype":"venue"
},
  "geometry": {"coordinates":[4.5988402367,50.6556549072],"type":"Point"}
}