{
  "type": "Feature",
  "properties": {
    "addr:full":"Tuinlaan 49 Sint-niklaas (belsele) Oost-Vlaanderen 9111",
    "addr:housenumber":"49",
    "addr:postcode":"9111",
    "addr:street":"Tuinlaan",
    "iso:country":"BE",
    "sg:address":"Tuinlaan 49",
    "sg:city":"Sint-niklaas (belsele)",
    "sg:classifiers":[
        {
            "category":"Home & Garden",
            "subcategory":"Hardware",
            "type":"Retail Goods"
        }
    ],
    "sg:phone":"+32 3 777 21 20",
    "sg:postcode":"9111",
    "sg:province":"Oost-Vlaanderen",
    "sg:tags":[
        "machine",
        "horticultural"
    ],
    "wof:name":"Vercauteren M Bvba",
    "wof:placetype":"venue"
},
  "geometry": {"coordinates":[4.110118866,51.1526031494],"type":"Point"}
}