{
  "type": "Feature",
  "properties": {
    "addr:full":"Place Joseph Wauters 9 Bruxelles (watermael-boitsfort) Bruxelles-Capitale 1170",
    "addr:housenumber":"9",
    "addr:postcode":"1170",
    "addr:street":"Place Joseph Wauters",
    "iso:country":"BE",
    "sg:address":"Place Joseph Wauters 9",
    "sg:city":"Bruxelles (watermael-boitsfort)",
    "sg:classifiers":[
        {
            "category":"Social Services",
            "type":"Services"
        }
    ],
    "sg:phone":"+32 2 672 31 42",
    "sg:postcode":"1170",
    "sg:province":"Bruxelles-Capitale",
    "wof:name":"Floreal Sc",
    "wof:placetype":"venue"
},
  "geometry": {"coordinates":[4.4189839363,50.8085632324],"type":"Point"}
}