{
  "type": "Feature",
  "properties": {
    "addr:full":"Haverveldstraat 30 Heusden-zolder (zolder) Limburg 3550",
    "addr:housenumber":"30",
    "addr:postcode":"3550",
    "addr:street":"Haverveldstraat",
    "iso:country":"BE",
    "sg:address":"Haverveldstraat 30",
    "sg:city":"Heusden-zolder (zolder)",
    "sg:orig_category":"Non-Classified Establishments",
    "sg:phone":"+32 11 53 80 55",
    "sg:postcode":"3550",
    "sg:province":"Limburg",
    "wof:name":"Music-box",
    "wof:placetype":"venue"
},
  "geometry": {"coordinates":[5.3077511787,51.0205192566],"type":"Point"}
}