{
  "type": "Feature",
  "properties": {
    "addr:full":"Maastrichterstraat Riemst (herderen) Limburg 3770",
    "addr:postcode":"3770",
    "addr:street":"Maastrichterstraat",
    "iso:country":"BE",
    "sg:address":"Maastrichterstraat",
    "sg:city":"Riemst (herderen)",
    "sg:classifiers":[
        {
            "category":"Home & Garden",
            "subcategory":"Carpets & Floor Coverings",
            "type":"Retail Goods"
        }
    ],
    "sg:phone":"+32 12 45 21 62",
    "sg:postcode":"3770",
    "sg:province":"Limburg",
    "sg:tags":[
        "prefab",
        "element"
    ],
    "wof:name":"Hedra-beton Sa-merken Mathieu",
    "wof:placetype":"venue"
},
  "geometry": {"coordinates":[5.5968599319,50.8124885559],"type":"Point"}
}