{
  "type": "Feature",
  "properties": {
    "addr:full":"Rue Emile Vandervelde 28 Fl\u00e9ron (roms\u00e9e) Li\u00e8ge 4624",
    "addr:housenumber":"28",
    "addr:postcode":"4624",
    "addr:street":"Rue Emile Vandervelde",
    "iso:country":"BE",
    "sg:address":"Rue Emile Vandervelde 28",
    "sg:city":"Fl\u00e9ron (roms\u00e9e)",
    "sg:classifiers":[
        {
            "category":"Insurance",
            "subcategory":"Insurance Agent",
            "type":"Services"
        }
    ],
    "sg:phone":"+32 4 358 58 07",
    "sg:postcode":"4624",
    "sg:province":"Li\u00e8ge",
    "sg:tags":[
        "broker"
    ],
    "wof:name":"Prevot Robert Sprl",
    "wof:placetype":"venue"
},
  "geometry": {"coordinates":[5.6678800583,50.6108551025],"type":"Point"}
}