{
  "type": "Feature",
  "properties": {
    "iso:country":"BE",
    "sg:address":"Urselseweg 111a",
    "sg:city":"Knesselare",
    "sg:classifiers":[
        {
            "category":"Building & Trades",
            "subcategory":"Construction",
            "type":"Services"
        }
    ],
    "sg:phone":"+32 9 325 98 98",
    "sg:postcode":"9910",
    "sg:province":"Oost-Vlaanderen",
    "sg:tags":[
        "roofing"
    ],
    "wof:name":"Van Severen Nv",
    "wof:placetype":"venue"
},
  "geometry": {"coordinates":[3.4328451157,51.1336593628],"type":"Point"}
}