{
  "type": "Feature",
  "properties": {
    "iso:country":"BE",
    "sg:address":"Joos De Ter Beerstln 52",
    "sg:city":"Pittem",
    "sg:classifiers":[
        {
            "category":"Manufacturing",
            "subcategory":"Metals",
            "type":"Manufacturing & Wholesale Goods"
        }
    ],
    "sg:phone":"+32 51 46 65 65",
    "sg:postcode":"8740",
    "sg:province":"West-Vlaanderen",
    "sg:tags":[
        "metallurgy",
        "steel",
        "metalworking"
    ],
    "wof:name":"Aluminiumconstructie De Jaeghere Bvba",
    "wof:placetype":"venue"
},
  "geometry": {"coordinates":[3.2510859966,50.9938964844],"type":"Point"}
}