{
  "type": "Feature",
  "properties": {
    "addr:full":"Pater Beckersstraat 76 Heusden-zolder Limburg 3550",
    "addr:housenumber":"76",
    "addr:postcode":"3550",
    "addr:street":"Pater Beckersstraat",
    "iso:country":"BE",
    "sg:address":"Pater Beckersstraat 76",
    "sg:city":"Heusden-zolder",
    "sg:orig_category":"M\u00e9decins and sp\u00e9cialistes",
    "sg:phone":"+32 11 42 37 44",
    "sg:postcode":"3550",
    "sg:province":"Limburg",
    "wof:name":"Els Vandecruys",
    "wof:placetype":"venue"
},
  "geometry": {"coordinates":[5.2384262085,51.0303421021],"type":"Point"}
}