{
  "type": "Feature",
  "properties": {
    "addr:full":"Domentveldstraat 41b Affligem (essene) Vlaams-Brabant 1790",
    "addr:housenumber":"41b",
    "addr:postcode":"1790",
    "addr:street":"Domentveldstraat",
    "iso:country":"BE",
    "sg:address":"Domentveldstraat 41b",
    "sg:city":"Affligem (essene)",
    "sg:classifiers":[
        {
            "category":"Health Services",
            "subcategory":"Nursing And Care Facility",
            "type":"Services"
        }
    ],
    "sg:phone":"+32 2 452 21 15",
    "sg:postcode":"1790",
    "sg:province":"Vlaams-Brabant",
    "sg:tags":[
        "home"
    ],
    "wof:name":"Loomans L",
    "wof:placetype":"venue"
},
  "geometry": {"coordinates":[4.1323518753,50.9163208008],"type":"Point"}
}