{
  "type": "Feature",
  "properties": {
    "iso:country":"BE",
    "sg:address":"Hoogstraat 13-15",
    "sg:city":"Bree",
    "sg:classifiers":[
        {
            "category":"Shopping",
            "subcategory":"Clothing, Apparel, & Fashions",
            "type":"Retail Goods"
        }
    ],
    "sg:phone":"+32 89 46 22 23",
    "sg:postcode":"3960",
    "sg:province":"Limburg",
    "sg:tags":[
        "lady",
        "clothing",
        "-"
    ],
    "wof:name":"Martens Confectie",
    "wof:placetype":"venue"
},
  "geometry": {"coordinates":[5.5990028381,51.1415405273],"type":"Point"}
}