{
  "type": "Feature",
  "properties": {
    "iso:country":"BE",
    "sg:address":"Millekruisestraat 1a",
    "sg:city":"Heuvelland (kemmel)",
    "sg:classifiers":[
        {
            "category":"Farming",
            "subcategory":"Farm & Veterinary Services",
            "type":"Manufacturing & Wholesale Goods"
        }
    ],
    "sg:phone":"+32 57 44 42 65",
    "sg:postcode":"8956",
    "sg:province":"West-Vlaanderen",
    "sg:tags":[
        "agricultural",
        "contractor"
    ],
    "wof:name":"Dambre J",
    "wof:placetype":"venue"
},
  "geometry": {"coordinates":[2.821158886,50.7935905457],"type":"Point"}
}