{
  "type": "Feature",
  "properties": {
    "iso:country":"BE",
    "sg:address":"Rue De Lumechon 17",
    "sg:city":"Chapelle-lez-herlaimont (godarville)",
    "sg:classifiers":[
        {
            "category":"Personal",
            "subcategory":"Psychics & Astrologers",
            "type":"Services"
        }
    ],
    "sg:phone":"+32 64 46 07 94",
    "sg:postcode":"7160",
    "sg:province":"Hainaut",
    "sg:tags":[
        "astrology"
    ],
    "wof:name":"Vdlg",
    "wof:placetype":"venue"
},
  "geometry": {"coordinates":[4.2809071541,50.4939689636],"type":"Point"}
}