{
  "type": "Feature",
  "properties": {
    "addr:full":"Bannerlaan 79 Grobbendonk Antwerpen 2280",
    "addr:housenumber":"79",
    "addr:postcode":"2280",
    "addr:street":"Bannerlaan",
    "iso:country":"BE",
    "sg:address":"Bannerlaan 79",
    "sg:city":"Grobbendonk",
    "sg:orig_category":"Non-Classified Establishments",
    "sg:phone":"+32 14 25 73 57",
    "sg:postcode":"2280",
    "sg:province":"Antwerpen",
    "wof:name":"De Ceuster Meststoffen",
    "wof:placetype":"venue"
},
  "geometry": {"coordinates":[4.778069973,51.1640281677],"type":"Point"}
}