{
  "type": "Feature",
  "properties": {
    "addr:full":"Bld. De La Sauveni\u00c8re 1 Liege Li\u00e8ge 4000",
    "addr:housenumber":"1",
    "addr:postcode":"4000",
    "addr:street":"De La Sauvenie\u0300Re",
    "iso:country":"BE",
    "sg:address":"Bld. De La Sauveni\u00c8re 1",
    "sg:city":"Liege",
    "sg:orig_category":"Studios photographiques. Equipement photographique. Mat\u00e9riel de T\u00e9l\u00e9communication",
    "sg:phone":"+32 4 223 07 91",
    "sg:postcode":"4000",
    "sg:province":"Li\u00e8ge",
    "wof:name":"Positif Photo Galerie",
    "wof:placetype":"venue"
},
  "geometry": {"coordinates":[5.5699062347,50.6438789368],"type":"Point"}
}