{
  "type": "Feature",
  "properties": {
    "addr:full":"Kruisbaan 3-102 Mechelen Antwerpen 2800",
    "addr:postcode":"3-102;2800",
    "addr:street":"Kruisbaan",
    "iso:country":"BE",
    "sg:address":"Kruisbaan 3-102",
    "sg:city":"Mechelen",
    "sg:classifiers":[
        {
            "category":"Professional",
            "subcategory":"Computer Services",
            "type":"Services"
        }
    ],
    "sg:phone":"+32 15 28 56 50",
    "sg:postcode":"2800",
    "sg:province":"Antwerpen",
    "sg:tags":[
        "-",
        "processing",
        "data",
        "software"
    ],
    "wof:name":"Graitec Benelux Sprl",
    "wof:placetype":"venue"
},
  "geometry": {"coordinates":[4.4744338989,51.0091209412],"type":"Point"}
}