{
  "type": "Feature",
  "properties": {
    "addr:full":"Nieuwlandlaan 33a Aarschot Vlaams-Brabant 3200",
    "addr:housenumber":"33a",
    "addr:postcode":"3200",
    "addr:street":"Nieuwlandlaan",
    "iso:country":"BE",
    "sg:address":"Nieuwlandlaan 33a",
    "sg:city":"Aarschot",
    "sg:classifiers":[
        {
            "category":"Manufacturing",
            "subcategory":"Paper Products",
            "type":"Manufacturing & Wholesale Goods"
        }
    ],
    "sg:phone":"+32 16 56 74 63",
    "sg:postcode":"3200",
    "sg:province":"Vlaams-Brabant",
    "sg:tags":[
        "packing",
        "cardboard",
        "-"
    ],
    "wof:name":"Rembrandt Verpakkingen Nv",
    "wof:placetype":"venue"
},
  "geometry": {"coordinates":[4.8104801178,50.9781799316],"type":"Point"}
}