{
  "type": "Feature",
  "properties": {
    "addr:full":"Sint-truidensesteenweg 12 Tienen Vlaams-Brabant 3300",
    "addr:housenumber":"12",
    "addr:postcode":"3300",
    "addr:street":"Sint-Truidensesteenweg",
    "iso:country":"BE",
    "sg:address":"Sint-truidensesteenweg 12",
    "sg:city":"Tienen",
    "sg:classifiers":[
        {
            "category":"Professional",
            "subcategory":"Testing Lab",
            "type":"Services"
        }
    ],
    "sg:phone":"+32 16 81 12 64",
    "sg:postcode":"3300",
    "sg:province":"Vlaams-Brabant",
    "sg:tags":[
        "chemist"
    ],
    "wof:name":"Peeters",
    "wof:placetype":"venue"
},
  "geometry": {"coordinates":[4.954477787,50.8010597229],"type":"Point"}
}