{
  "type": "Feature",
  "properties": {
    "addr:full":"Rue L\u00e9opold Courouble 34 Bruxelles (schaerbeek) Bruxelles-Capitale 1030",
    "addr:housenumber":"34",
    "addr:postcode":"1030",
    "addr:street":"Rue Le\u0301Opold Courouble",
    "iso:country":"BE",
    "sg:address":"Rue L\u00e9opold Courouble 34",
    "sg:city":"Bruxelles (schaerbeek)",
    "sg:classifiers":[
        {
            "category":"Shopping",
            "subcategory":"Antiques",
            "type":"Retail Goods"
        }
    ],
    "sg:phone":"+32 2 245 85 86",
    "sg:postcode":"1030",
    "sg:province":"Bruxelles-Capitale",
    "sg:tags":[
        "restoration"
    ],
    "wof:name":"London Antiques Et Decoration",
    "wof:placetype":"venue"
},
  "geometry": {"coordinates":[4.3796868324,50.8716278076],"type":"Point"}
}