{
  "type": "Feature",
  "properties": {
    "addr:full":"Rue Docteur Colson 8ba Rebecq Brabant Wallon 1430",
    "addr:housenumber":"8ba",
    "addr:postcode":"1430",
    "addr:street":"Rue Docteur Colson",
    "iso:country":"BE",
    "sg:address":"Rue Docteur Colson 8ba",
    "sg:city":"Rebecq",
    "sg:classifiers":[
        {
            "category":"Restaurant",
            "type":"Food & Drink"
        }
    ],
    "sg:phone":"+32 67 63 89 79",
    "sg:postcode":"1430",
    "sg:province":"Brabant Wallon",
    "sg:tags":[
        "caf\u00e9s"
    ],
    "wof:name":"Taverne Le Momus",
    "wof:placetype":"venue"
},
  "geometry": {"coordinates":[4.1322331429,50.6636238098],"type":"Point"}
}