{
  "type": "Feature",
  "properties": {
    "iso:country":"BE",
    "sg:address":"Avenue Des Tilleuls 20",
    "sg:city":"Durbuy",
    "sg:orig_category":"Metaalbehandeling and -bekleding",
    "sg:phone":"+32 86 21 16 97",
    "sg:postcode":"6940",
    "sg:province":"Luxembourg",
    "wof:name":"Ready Tours",
    "wof:placetype":"venue"
},
  "geometry": {"coordinates":[5.4543361664,50.3515777588],"type":"Point"}
}