{
  "type": "Feature",
  "properties": {
    "addr:full":"Fruithoflaan 77 Antwerpen (berchem) Antwerpen 2600",
    "addr:housenumber":"77",
    "addr:postcode":"2600",
    "addr:street":"Fruithoflaan;Antwerpen",
    "iso:country":"BE",
    "sg:address":"Fruithoflaan 77",
    "sg:city":"Antwerpen (berchem)",
    "sg:classifiers":[
        {
            "category":"Personal",
            "subcategory":"Shoe Repair & Shine",
            "type":"Services"
        }
    ],
    "sg:phone":"+32 3 449 15 61",
    "sg:postcode":"2600",
    "sg:province":"Antwerpen",
    "sg:tags":[
        "shoemaker"
    ],
    "wof:name":"Tako Shoe Service",
    "wof:placetype":"venue"
},
  "geometry": {"coordinates":[4.4174151421,51.1974411011],"type":"Point"}
}