{
  "type": "Feature",
  "properties": {
    "addr:full":"De Heuf 513 Overpelt Limburg 3900",
    "addr:housenumber":"513",
    "addr:postcode":"3900",
    "addr:street":"De Heuf",
    "iso:country":"BE",
    "sg:address":"De Heuf 513",
    "sg:city":"Overpelt",
    "sg:orig_category":"M\u00e9decins and sp\u00e9cialistes",
    "sg:phone":"+32 11 80 12 69",
    "sg:postcode":"3900",
    "sg:province":"Limburg",
    "wof:name":"Noella Miguet",
    "wof:placetype":"venue"
},
  "geometry": {"coordinates":[5.4210939407,51.2126960754],"type":"Point"}
}