{
  "type": "Feature",
  "properties": {
    "iso:country":"BE",
    "sg:address":"Zeelaan 25",
    "sg:city":"Koksijde",
    "sg:classifiers":[
        {
            "category":"Wholesale",
            "subcategory":"Beer",
            "type":"Manufacturing & Wholesale Goods"
        }
    ],
    "sg:phone":"+32 58 51 10 27",
    "sg:postcode":"8670",
    "sg:province":"West-Vlaanderen",
    "sg:tags":[
        "ale",
        "-"
    ],
    "wof:name":"Houtsaeger Brouwerij Nv",
    "wof:placetype":"venue"
},
  "geometry": {"coordinates":[2.6496429443,51.1055793762],"type":"Point"}
}