{
  "type": "Feature",
  "properties": {
    "addr:full":"Louis Melsensstraat 14 Leuven Vlaams-Brabant 3000",
    "addr:housenumber":"14",
    "addr:postcode":"3000",
    "addr:street":"Louis Melsensstraat",
    "iso:country":"BE",
    "sg:address":"Louis Melsensstraat 14",
    "sg:city":"Leuven",
    "sg:classifiers":[
        {
            "category":"Food & Beverages",
            "subcategory":"Chocolate",
            "type":"Retail Goods"
        }
    ],
    "sg:phone":"+32 16 23 06 42",
    "sg:postcode":"3000",
    "sg:province":"Vlaams-Brabant",
    "sg:tags":[
        "confectionery",
        "-"
    ],
    "wof:name":"Tartufo",
    "wof:placetype":"venue"
},
  "geometry": {"coordinates":[4.7089838982,50.8806800842],"type":"Point"}
}