{
  "type": "Feature",
  "properties": {
    "iso:country":"BE",
    "sg:address":"Rue Du Moulin 3a",
    "sg:city":"La Roche-en-ardenne",
    "sg:classifiers":[
        {
            "category":"Banks & Credit Unions",
            "subcategory":"Bank",
            "type":"Services"
        }
    ],
    "sg:phone":"+32 84 41 27 87",
    "sg:postcode":"6980",
    "sg:province":"Luxembourg",
    "wof:name":"Assurances De L'ourthe Sprl",
    "wof:placetype":"venue"
},
  "geometry": {"coordinates":[5.5768408775,50.1827812195],"type":"Point"}
}