{
  "type": "Feature",
  "properties": {
    "addr:full":"Reeweg 29 Genk Limburg 3600",
    "addr:housenumber":"29",
    "addr:postcode":"3600",
    "addr:street":"Reeweg",
    "iso:country":"BE",
    "sg:address":"Reeweg 29",
    "sg:city":"Genk",
    "sg:classifiers":[
        {
            "category":"Insurance",
            "subcategory":"Insurance Agent",
            "type":"Services"
        }
    ],
    "sg:phone":"+32 89 36 30 81",
    "sg:postcode":"3600",
    "sg:province":"Limburg",
    "sg:tags":[
        "broker"
    ],
    "wof:name":"Varobo Bvba",
    "wof:placetype":"venue"
},
  "geometry": {"coordinates":[5.5130281448,50.9532966614],"type":"Point"}
}