{
  "type": "Feature",
  "properties": {
    "iso:country":"BE",
    "sg:address":"Grauwpoort 1",
    "sg:city":"Ghent",
    "sg:classifiers":[
        {
            "category":"Professional",
            "subcategory":"Computer Services",
            "type":"Services"
        }
    ],
    "sg:postcode":"9000",
    "sg:tags":[
        "events",
        "event-search",
        "event-database"
    ],
    "sg:website":"http://oxynade.com",
    "wof:name":"Oxynade",
    "wof:placetype":"venue"
},
  "geometry": {"coordinates":[3.71105,51.050314],"type":"Point"}
}