{
  "type": "Feature",
  "properties": {
    "iso:country":"BE",
    "sg:address":"Rue De Poix 104",
    "sg:city":"Libin",
    "sg:orig_category":"Fleurs and plantes",
    "sg:phone":"+32 61 65 58 90",
    "sg:postcode":"6890",
    "sg:province":"Luxembourg",
    "wof:name":"Joli-bois",
    "wof:placetype":"venue"
},
  "geometry": {"coordinates":[5.2570319176,49.9837684631],"type":"Point"}
}