{
  "type": "Feature",
  "properties": {
    "iso:country":"BE",
    "sg:address":"Kasterleesteenweg 34",
    "sg:city":"Kasterlee",
    "sg:classifiers":[
        {
            "category":"Freight",
            "type":"Transportation"
        }
    ],
    "sg:phone":"+32 14 55 62 69",
    "sg:postcode":"2460",
    "sg:province":"Antwerpen",
    "sg:tags":[
        "-",
        "transport"
    ],
    "wof:name":"Hetra",
    "wof:placetype":"venue"
},
  "geometry": {"coordinates":[4.9671049118,51.2406616211],"type":"Point"}
}