{
  "type": "Feature",
  "properties": {
    "iso:country":"BE",
    "sg:address":"Place Du March\u00e9 18",
    "sg:city":"Vis\u00e9",
    "sg:classifiers":[
        {
            "category":"Real Estate",
            "subcategory":"Real Estate Services",
            "type":"Services"
        }
    ],
    "sg:phone":"+32 4 374 26 06",
    "sg:postcode":"4600",
    "sg:province":"Li\u00e8ge",
    "wof:name":"D&d Projecten Sprl",
    "wof:placetype":"venue"
},
  "geometry": {"coordinates":[5.6968197823,50.7337989807],"type":"Point"}
}