{
  "type": "Feature",
  "properties": {
    "addr:full":"Galgenweellaan 70 Antwerpen Antwerpen 2050",
    "addr:housenumber":"70",
    "addr:postcode":"2050",
    "addr:street":"Galgenweellaan",
    "iso:country":"BE",
    "sg:address":"Galgenweellaan 70",
    "sg:city":"Antwerpen",
    "sg:classifiers":[
        {
            "category":"Food & Beverages",
            "subcategory":"Liquor & Beverages",
            "type":"Retail Goods"
        }
    ],
    "sg:phone":"+32 3 219 18 77",
    "sg:postcode":"2050",
    "sg:province":"Antwerpen",
    "sg:tags":[
        "-",
        "spirit",
        "wine"
    ],
    "wof:name":"Meul Bvba",
    "wof:placetype":"venue"
},
  "geometry": {"coordinates":[4.3780560493,51.2177886963],"type":"Point"}
}