{
  "type": "Feature",
  "properties": {
    "addr:full":"Avenue Van Volxem 74-76 Bruxelles (forest) Bruxelles-Capitale 1190",
    "addr:housenumber":"74-76",
    "addr:postcode":"1190",
    "addr:street":"Avenue Van Volxem",
    "iso:country":"BE",
    "sg:address":"Avenue Van Volxem 74-76",
    "sg:city":"Bruxelles (forest)",
    "sg:classifiers":[
        {
            "category":"Building & Trades",
            "subcategory":"Equipment Rental",
            "type":"Services"
        }
    ],
    "sg:phone":"+32 2 345 22 17",
    "sg:postcode":"1190",
    "sg:province":"Bruxelles-Capitale",
    "sg:tags":[
        "safety",
        "collective",
        "individual",
        "-"
    ],
    "wof:name":"N.m.s. Sa",
    "wof:placetype":"venue"
},
  "geometry": {"coordinates":[4.3247661591,50.8157463074],"type":"Point"}
}