{
  "type": "Feature",
  "properties": {
    "iso:country":"BE",
    "sg:address":"President Kennedylaan 13b1",
    "sg:city":"Izegem",
    "sg:orig_category":"Airconditioning and ventilatie Bouwmaterialen Gh Loodgieterij and centrale verwarming Gh",
    "sg:phone":"+32 51 31 19 37",
    "sg:postcode":"8870",
    "sg:province":"West-Vlaanderen",
    "wof:name":"Decotherm",
    "wof:placetype":"venue"
},
  "geometry": {"coordinates":[3.2121789455,50.9297409058],"type":"Point"}
}