{
  "type": "Feature",
  "properties": {
    "iso:country":"BE",
    "sg:address":"Av. Franklin Roosevelt 131",
    "sg:city":"Brussel/bruxelles",
    "sg:orig_category":"S\u00e9lection de personnel and placement",
    "sg:phone":"+32 2 675 66 12",
    "sg:postcode":"1050",
    "sg:province":"Bruxelles-Capitale",
    "wof:name":"Egosearch",
    "wof:placetype":"venue"
},
  "geometry": {"coordinates":[4.3930268288,50.7984809875],"type":"Point"}
}