{
  "type": "Feature",
  "properties": {
    "addr:full":"Stuivenbergstraat 4 Evergem Oost-Vlaanderen 9940",
    "addr:housenumber":"4",
    "addr:postcode":"9940",
    "addr:street":"Stuivenbergstraat;Oost-Vlaanderen",
    "iso:country":"BE",
    "sg:address":"Stuivenbergstraat 4",
    "sg:city":"Evergem",
    "sg:orig_category":"Hout and afgeleiden Gh IJzerwaren, bouw- and verfmaterialen Non-foodwinkels",
    "sg:phone":"+32 9 344 58 36",
    "sg:postcode":"9940",
    "sg:province":"Oost-Vlaanderen",
    "wof:name":"Stock Doe Het Zelf",
    "wof:placetype":"venue"
},
  "geometry": {"coordinates":[3.7349209785,51.1807060242],"type":"Point"}
}