{
  "type": "Feature",
  "properties": {
    "iso:country":"BE",
    "sg:address":"Kerkstraat 40",
    "sg:city":"Lovendegem",
    "sg:orig_category":"Peinture. Rev\u00eatements pour sols and murs",
    "sg:phone":"+32 9 372 78 86",
    "sg:postcode":"9920",
    "sg:province":"Oost-Vlaanderen",
    "wof:name":"Lisette Marquenie",
    "wof:placetype":"venue"
},
  "geometry": {"coordinates":[3.6090340614,51.0943183899],"type":"Point"}
}