{
  "type": "Feature",
  "properties": {
    "iso:country":"BE",
    "sg:address":"Marktplein 21",
    "sg:city":"Galmaarden",
    "sg:orig_category":"Elektrische installaties voor woningen Huishoudapparaten, televisies and radio's",
    "sg:phone":"+32 54 58 85 78",
    "sg:postcode":"1570",
    "sg:province":"Vlaams-Brabant",
    "wof:name":"Fa. Delbauf",
    "wof:placetype":"venue"
},
  "geometry": {"coordinates":[3.9703528881,50.7539863586],"type":"Point"}
}