{
  "type": "Feature",
  "properties": {
    "iso:country":"BE",
    "sg:address":"Rue Des Ducs De Brabant 17",
    "sg:city":"Chaumont-gistoux",
    "sg:classifiers":[
        {
            "category":"Home & Garden",
            "subcategory":"Home Furnishings",
            "type":"Retail Goods"
        }
    ],
    "sg:phone":"+32 10 68 10 45",
    "sg:postcode":"1325",
    "sg:province":"Brabant Wallon",
    "sg:tags":[
        "interior",
        "decoration"
    ],
    "wof:name":"Tauber E",
    "wof:placetype":"venue"
},
  "geometry": {"coordinates":[4.7088971138,50.6812019348],"type":"Point"}
}