{
  "type": "Feature",
  "properties": {
    "iso:country":"BE",
    "sg:address":"Grand Route 2",
    "sg:city":"Villers-le-bouillet",
    "sg:classifiers":[
        {
            "category":"Cafe",
            "type":"Food & Drink"
        }
    ],
    "sg:phone":"+32 19 56 76 14",
    "sg:postcode":"4530",
    "sg:province":"Li\u00e8ge",
    "sg:tags":[
        "caf\u00e9s"
    ],
    "wof:name":"Caf\u00c9 Les Routiers",
    "wof:placetype":"venue"
},
  "geometry": {"coordinates":[5.2604899406,50.5760765076],"type":"Point"}
}