{
  "type": "Feature",
  "properties": {
    "iso:country":"BE",
    "sg:address":"Berghei 4ba",
    "sg:city":"Neerpelt",
    "sg:orig_category":"Eleveurs and marchands de porcs",
    "sg:phone":"+32 11 66 31 32",
    "sg:postcode":"3910",
    "sg:province":"Limburg",
    "wof:name":"Jos Kauffmann",
    "wof:placetype":"venue"
},
  "geometry": {"coordinates":[5.5021348,51.2211227417],"type":"Point"}
}