{
  "type": "Feature",
  "properties": {
    "addr:full":"Clos Des Musiciens 2b2 Ganshoren/ganshoren Bruxelles-Capitale 1083",
    "addr:housenumber":"2b2",
    "addr:postcode":"1083",
    "addr:street":"Clos Des Musiciens",
    "iso:country":"BE",
    "sg:address":"Clos Des Musiciens 2b2",
    "sg:city":"Ganshoren/ganshoren",
    "sg:orig_category":"Agences immobili\u00e8res",
    "sg:phone":"+32 2 465 90 91",
    "sg:postcode":"1083",
    "sg:province":"Bruxelles-Capitale",
    "wof:name":"Immo-lajot",
    "wof:placetype":"venue"
},
  "geometry": {"coordinates":[4.301404953,50.8737754822],"type":"Point"}
}