{
  "type": "Feature",
  "properties": {
    "iso:country":"BE",
    "sg:address":"Nieuwstraat 222",
    "sg:city":"Waregem",
    "sg:orig_category":"Installation \u00e9lectrique r\u00e9sidentielle",
    "sg:phone":"+32 56 72 44 46",
    "sg:postcode":"8792",
    "sg:province":"West-Vlaanderen",
    "wof:name":"Doise D",
    "wof:placetype":"venue"
},
  "geometry": {"coordinates":[3.3635149002,50.8899078369],"type":"Point"}
}