{
  "type": "Feature",
  "properties": {
    "addr:full":"Wuytenweg 13 Overpelt Limburg 3900",
    "addr:housenumber":"13",
    "addr:postcode":"3900",
    "addr:street":"Wuytenweg",
    "iso:country":"BE",
    "sg:address":"Wuytenweg 13",
    "sg:city":"Overpelt",
    "sg:orig_category":"D\u00e9corateurs d'int\u00e9rieur",
    "sg:phone":"+32 11 66 50 59",
    "sg:postcode":"3900",
    "sg:province":"Limburg",
    "wof:name":"P. Jannis",
    "wof:placetype":"venue"
},
  "geometry": {"coordinates":[5.4185290337,51.2138442993],"type":"Point"}
}