{
  "type": "Feature",
  "properties": {
    "addr:full":"Denefstraat 61 Gierle Antwerpen 2275",
    "addr:housenumber":"61",
    "addr:postcode":"2275",
    "addr:street":"Denefstraat",
    "iso:country":"BE",
    "sg:address":"Denefstraat 61",
    "sg:city":"Gierle",
    "sg:orig_category":"Huisdieren and benodigdheden Royal Canin",
    "sg:phone":"+32 14 55 60 32",
    "sg:postcode":"2275",
    "sg:province":"Antwerpen",
    "wof:name":"Hermans-van Ballaer",
    "wof:placetype":"venue"
},
  "geometry": {"coordinates":[4.8714017868,51.2702407837],"type":"Point"}
}