{
  "type": "Feature",
  "properties": {
    "addr:full":"St-laureysplein 11 Hove Antwerpen 2540",
    "addr:housenumber":"11",
    "addr:postcode":"2540",
    "addr:street":"St-Laureysplein",
    "iso:country":"BE",
    "sg:address":"St-laureysplein 11",
    "sg:city":"Hove",
    "sg:orig_category":"Alimentation sp\u00e9cialis\u00e9e",
    "sg:phone":"+32 3 455 33 72",
    "sg:postcode":"2540",
    "sg:province":"Antwerpen",
    "wof:name":"Delicatessen Da Loca",
    "wof:placetype":"venue"
},
  "geometry": {"coordinates":[4.4710202217,51.1539344788],"type":"Point"}
}