{
  "type": "Feature",
  "properties": {
    "iso:country":"BE",
    "sg:address":"Mutsaertplaats 1",
    "sg:city":"Vilvoorde",
    "sg:classifiers":[
        {
            "category":"Restaurant",
            "type":"Food & Drink"
        }
    ],
    "sg:phone":"+32 2 267 43 57",
    "sg:postcode":"1800",
    "sg:province":"Vlaams-Brabant",
    "sg:tags":[
        "caf\u00e9s"
    ],
    "wof:name":"Mutsaert Pub",
    "wof:placetype":"venue"
},
  "geometry": {"coordinates":[4.3606767654,50.9012413025],"type":"Point"}
}