{
  "type": "Feature",
  "properties": {
    "addr:full":"Rue De La Gare-d'oret 29 Florennes (hanzinelle) Namur 5621",
    "addr:housenumber":"29",
    "addr:postcode":"5621",
    "addr:street":"Rue De La Gare-D'Oret",
    "iso:country":"BE",
    "sg:address":"Rue De La Gare-d'oret 29",
    "sg:city":"Florennes (hanzinelle)",
    "sg:classifiers":[
        {
            "category":"Retail",
            "subcategory":"Animal Services",
            "type":"Services"
        }
    ],
    "sg:phone":"+32 71 68 96 07",
    "sg:postcode":"5621",
    "sg:province":"Namur",
    "sg:tags":[
        "farrier"
    ],
    "wof:name":"Vanophalvens D",
    "wof:placetype":"venue"
},
  "geometry": {"coordinates":[4.5633440018,50.2944526672],"type":"Point"}
}