{
  "type": "Feature",
  "properties": {
    "iso:country":"BE",
    "sg:address":"Scharebrugstraat 76",
    "sg:city":"Blankenberge",
    "sg:orig_category":"Entretien and r\u00e9parations de voitures",
    "sg:phone":"+32 50 42 93 70",
    "sg:postcode":"8370",
    "sg:province":"West-Vlaanderen",
    "wof:name":"Garage Dennis",
    "wof:placetype":"venue"
},
  "geometry": {"coordinates":[3.1316940784,51.3075523376],"type":"Point"}
}