{
  "type": "Feature",
  "properties": {
    "iso:country":"BE",
    "sg:address":"Heilig Hartplein 1",
    "sg:city":"Sint-truiden",
    "sg:orig_category":"Syst\u00e8mes de t\u00e9l\u00e9communications. Mobistar Centres",
    "sg:phone":"+32 11 68 69 28",
    "sg:postcode":"3800",
    "sg:province":"Limburg",
    "wof:name":"Mobistar Center",
    "wof:placetype":"venue"
},
  "geometry": {"coordinates":[5.1870679855,50.8152313232],"type":"Point"}
}