{
  "type": "Feature",
  "properties": {
    "addr:full":"Lenniksesteenweg 45 Pepingen Vlaams-Brabant 1671",
    "addr:housenumber":"45",
    "addr:postcode":"1671",
    "addr:street":"Lenniksesteenweg",
    "iso:country":"BE",
    "sg:address":"Lenniksesteenweg 45",
    "sg:city":"Pepingen",
    "sg:orig_category":"Peinture. Rev\u00eatements pour sols and murs",
    "sg:phone":"+32 2 532 07 56",
    "sg:postcode":"1671",
    "sg:province":"Vlaams-Brabant",
    "wof:name":"Crabbe F.",
    "wof:placetype":"venue"
},
  "geometry": {"coordinates":[4.1669631004,50.7780723572],"type":"Point"}
}