{
  "type": "Feature",
  "properties": {
    "addr:full":"Heppensesteenweg 34 Ham (oostham) Limburg 3945",
    "addr:housenumber":"34",
    "addr:postcode":"oostham;3945",
    "addr:street":"Heppensesteenweg",
    "iso:country":"BE",
    "sg:address":"Heppensesteenweg 34",
    "sg:city":"Ham (oostham)",
    "sg:classifiers":[
        {
            "category":"Autos & Motor Vehicles",
            "subcategory":"Automobile Sales",
            "type":"Retail Goods"
        }
    ],
    "sg:phone":"+32 11 34 75 89",
    "sg:postcode":"3945",
    "sg:province":"Limburg",
    "sg:tags":[
        "car",
        "used",
        "-"
    ],
    "wof:name":"Noels P",
    "wof:placetype":"venue"
},
  "geometry": {"coordinates":[5.1776199341,51.1046104431],"type":"Point"}
}