{
  "type": "Feature",
  "properties": {
    "iso:country":"BE",
    "sg:address":"Kuipenstraat 1",
    "sg:city":"Oostkamp",
    "sg:orig_category":"Rev\u00eatements pour sols and murs. Peinture",
    "sg:phone":"+32 50 82 20 09",
    "sg:postcode":"8020",
    "sg:province":"West-Vlaanderen",
    "wof:name":"Pierrot De Clerck",
    "wof:placetype":"venue"
},
  "geometry": {"coordinates":[3.2055139542,51.1434020996],"type":"Point"}
}