{
  "type": "Feature",
  "properties": {
    "addr:full":"Rue Des Bruy\u00e8res 4 Jurbise Hainaut 7050",
    "addr:housenumber":"4",
    "addr:postcode":"7050",
    "addr:street":"Rue Des Bruye\u0300Res",
    "iso:country":"BE",
    "sg:address":"Rue Des Bruy\u00e8res 4",
    "sg:city":"Jurbise",
    "sg:classifiers":[
        {
            "category":"Professional",
            "subcategory":"Lawyer & Legal Services",
            "type":"Services"
        }
    ],
    "sg:phone":"+32 65 22 80 82",
    "sg:postcode":"7050",
    "sg:province":"Hainaut",
    "wof:name":"Senecaut Manuella",
    "wof:placetype":"venue"
},
  "geometry": {"coordinates":[3.9291510582,50.5074882507],"type":"Point"}
}