{
  "type": "Feature",
  "properties": {
    "iso:country":"BE",
    "sg:address":"Rue Des Trixhes 63",
    "sg:city":"Dalhem",
    "sg:classifiers":[
        {
            "category":"Arena",
            "subcategory":"Sports Club",
            "type":"Entertainment"
        }
    ],
    "sg:phone":"+32 4 379 50 19",
    "sg:postcode":"4607",
    "sg:province":"Li\u00e8ge",
    "sg:tags":[
        "terrain",
        "hors",
        "de",
        "installation",
        "sportifs"
    ],
    "wof:name":"Rugby Coq Mosan",
    "wof:placetype":"venue"
},
  "geometry": {"coordinates":[5.7299342155,50.7458267212],"type":"Point"}
}