{
  "type": "Feature",
  "properties": {
    "iso:country":"BE",
    "sg:address":"Rue Des Neuf Courtils 11",
    "sg:city":"Saint-hubert",
    "sg:classifiers":[
        {
            "category":"Insurance",
            "subcategory":"Insurance Agent",
            "type":"Services"
        }
    ],
    "sg:phone":"+32 61 61 15 28",
    "sg:postcode":"6870",
    "sg:province":"Luxembourg",
    "sg:tags":[
        "broker"
    ],
    "wof:name":"Felix R",
    "wof:placetype":"venue"
},
  "geometry": {"coordinates":[5.3723988533,50.0238342285],"type":"Point"}
}