{
  "type": "Feature",
  "properties": {
    "addr:full":"Kasteelstraat 189 Buggenhout Oost-Vlaanderen 9255",
    "addr:housenumber":"189",
    "addr:postcode":"9255",
    "addr:street":"Kasteelstraat",
    "iso:country":"BE",
    "sg:address":"Kasteelstraat 189",
    "sg:city":"Buggenhout",
    "sg:classifiers":[
        {
            "category":"Restaurant",
            "type":"Food & Drink"
        }
    ],
    "sg:phone":"+32 52 34 04 56",
    "sg:postcode":"9255",
    "sg:province":"Oost-Vlaanderen",
    "sg:tags":[
        "caf\u00e9s"
    ],
    "wof:name":"De Groene Wandeling",
    "wof:placetype":"venue"
},
  "geometry": {"coordinates":[4.2138681412,50.9909286499],"type":"Point"}
}