{
  "type": "Feature",
  "properties": {
    "iso:country":"BE",
    "sg:address":"Rubenslaan 15",
    "sg:city":"Ichtegem",
    "sg:classifiers":[
        {
            "category":"Building & Trades",
            "subcategory":"Equipment Rental",
            "type":"Services"
        }
    ],
    "sg:phone":"+32 51 58 12 99",
    "sg:postcode":"8480",
    "sg:province":"West-Vlaanderen",
    "sg:tags":[
        "sound",
        "-",
        "system"
    ],
    "wof:name":"Gvr Productions",
    "wof:placetype":"venue"
},
  "geometry": {"coordinates":[3.0116569996,51.0968360901],"type":"Point"}
}