{
  "type": "Feature",
  "properties": {
    "iso:country":"BE",
    "sg:address":"Rue Louis Mestrez 5",
    "sg:city":"Fl\u00e9malle (awirs)",
    "sg:classifiers":[
        {
            "category":"Manufacturing",
            "subcategory":"Paper Products",
            "type":"Manufacturing & Wholesale Goods"
        }
    ],
    "sg:phone":"+32 4 250 26 58",
    "sg:postcode":"4400",
    "sg:province":"Li\u00e8ge",
    "sg:tags":[
        "bag"
    ],
    "wof:name":"Galand Sa",
    "wof:placetype":"venue"
},
  "geometry": {"coordinates":[5.3923430443,50.6123542786],"type":"Point"}
}