{
  "type": "Feature",
  "properties": {
    "iso:country":"BE",
    "sg:address":"Zandstraat 84",
    "sg:city":"Sint-katelijne-waver",
    "sg:orig_category":"Bagage and lederwaren",
    "sg:phone":"+32 15 55 41 25",
    "sg:postcode":"2860",
    "sg:province":"Antwerpen",
    "wof:name":"Marcel Verreth",
    "wof:placetype":"venue"
},
  "geometry": {"coordinates":[4.4963321686,51.0448036194],"type":"Point"}
}