{
  "type": "Feature",
  "properties": {
    "iso:country":"BE",
    "sg:address":"Rue Poncia Du Ban 13",
    "sg:city":"Ciney (chevetogne)",
    "sg:classifiers":[
        {
            "category":"Shopping",
            "subcategory":"Stationery & Office Supplies",
            "type":"Retail Goods"
        }
    ],
    "sg:phone":"+32 83 21 36 27",
    "sg:postcode":"5590",
    "sg:province":"Namur",
    "sg:tags":[
        "partition"
    ],
    "wof:name":"Plafond Deco Sprl",
    "wof:placetype":"venue"
},
  "geometry": {"coordinates":[5.1022520065,50.297088623],"type":"Point"}
}