{
  "type": "Feature",
  "properties": {
    "addr:full":"Ridder Van Parijsstraat 16 Antwerpen (merksem) Antwerpen 2170",
    "addr:housenumber":"16",
    "addr:postcode":"2170",
    "addr:street":"Ridder Van Parijsstraat",
    "iso:country":"BE",
    "sg:address":"Ridder Van Parijsstraat 16",
    "sg:city":"Antwerpen (merksem)",
    "sg:classifiers":[
        {
            "category":"Professional",
            "subcategory":"Accounting & Tax Preparation",
            "type":"Services"
        }
    ],
    "sg:phone":"+32 3 647 07 07",
    "sg:postcode":"2170",
    "sg:province":"Antwerpen",
    "sg:tags":[
        "bookkeeper"
    ],
    "wof:name":"F.i.m. Nv",
    "wof:placetype":"venue"
},
  "geometry": {"coordinates":[4.4505147934,51.246723175],"type":"Point"}
}