{
  "type": "Feature",
  "properties": {
    "iso:country":"BE",
    "sg:address":"G. Gezellelaan 49b1",
    "sg:city":"Puurs",
    "sg:orig_category":"Location de logements sociaux",
    "sg:phone":"+32 3 889 18 48",
    "sg:postcode":"2870",
    "sg:province":"Antwerpen",
    "wof:name":"Kleine Landeigendom",
    "wof:placetype":"venue"
},
  "geometry": {"coordinates":[4.2859048843,51.0758514404],"type":"Point"}
}