{
  "type": "Feature",
  "properties": {
    "iso:country":"BE",
    "sg:address":"Cours D\u00b4orval 5",
    "sg:city":"Ottignies-louvain-la-neuve",
    "sg:orig_category":"Artsen and specialisten",
    "sg:phone":"+32 10 45 27 37",
    "sg:postcode":"1348",
    "sg:province":"Brabant Wallon",
    "wof:name":"J. Alpedrinha",
    "wof:placetype":"venue"
},
  "geometry": {"coordinates":[4.6153578758,50.6745147705],"type":"Point"}
}