{
  "type": "Feature",
  "properties": {
    "addr:full":"Kazernstraat 42 Zottegem Oost-Vlaanderen 9620",
    "addr:housenumber":"42",
    "addr:postcode":"9620",
    "addr:street":"Kazernstraat",
    "iso:country":"BE",
    "sg:address":"Kazernstraat 42",
    "sg:city":"Zottegem",
    "sg:classifiers":[
        {
            "category":"Personal",
            "subcategory":"Beauty Salon",
            "type":"Services"
        }
    ],
    "sg:phone":"+32 9 360 76 54",
    "sg:postcode":"9620",
    "sg:province":"Oost-Vlaanderen",
    "sg:tags":[
        "slimming"
    ],
    "wof:name":"Body Solution",
    "wof:placetype":"venue"
},
  "geometry": {"coordinates":[3.8121030331,50.8675117493],"type":"Point"}
}