{
  "type": "Feature",
  "properties": {
    "iso:country":"BE",
    "sg:address":"Rue Lloyd Georges 17",
    "sg:city":"Ch\u00e2telet (ch\u00e2telineau)",
    "sg:classifiers":[
        {
            "category":"Professional",
            "subcategory":"Credit Reporting & Collection",
            "type":"Services"
        }
    ],
    "sg:phone":"+32 71 38 50 99",
    "sg:postcode":"6200",
    "sg:province":"Hainaut",
    "sg:tags":[
        "bailiff"
    ],
    "wof:name":"Geeurickx Ph",
    "wof:placetype":"venue"
},
  "geometry": {"coordinates":[4.5194301605,50.4122467041],"type":"Point"}
}