{
  "type": "Feature",
  "properties": {
    "addr:full":"Plaats 13 Ledegem West-Vlaanderen 8880",
    "addr:housenumber":"13",
    "addr:postcode":"8880",
    "addr:street":"Plaats",
    "iso:country":"BE",
    "sg:address":"Plaats 13",
    "sg:city":"Ledegem",
    "sg:classifiers":[
        {
            "category":"Manufacturing",
            "subcategory":"Textiles",
            "type":"Manufacturing & Wholesale Goods"
        }
    ],
    "sg:phone":"+32 56 50 96 88",
    "sg:postcode":"8880",
    "sg:province":"West-Vlaanderen",
    "sg:tags":[
        "retail",
        "-"
    ],
    "wof:name":"Huis Van Gheluwe",
    "wof:placetype":"venue"
},
  "geometry": {"coordinates":[3.1263968945,50.8531761169],"type":"Point"}
}