{
  "type": "Feature",
  "properties": {
    "addr:full":"Avenue Du Lyc\u00e9e Fran\u00e7ais 1 Box 14 Bruxelles (uccle) Bruxelles-Capitale 1180",
    "addr:housenumber":"1 box 14",
    "addr:postcode":"1180",
    "addr:street":"Avenue Du Lyce\u0301E Franc\u0327Ais",
    "iso:country":"BE",
    "sg:address":"Avenue Du Lyc\u00e9e Fran\u00e7ais 1 Box 14",
    "sg:city":"Bruxelles (uccle)",
    "sg:classifiers":[
        {
            "category":"Professional",
            "subcategory":"Management & Consulting",
            "type":"Services"
        }
    ],
    "sg:phone":"+32 475 56 63 33",
    "sg:postcode":"1180",
    "sg:province":"Bruxelles-Capitale",
    "sg:tags":[
        "consultant",
        "promotion",
        "-",
        "sale"
    ],
    "wof:name":"Sapa Consult",
    "wof:placetype":"venue"
},
  "geometry": {"coordinates":[4.343515873,50.7904319763],"type":"Point"}
}