{
  "type": "Feature",
  "properties": {
    "addr:full":"Nieuwstraat 4 Deerlijk West-Vlaanderen 8540",
    "addr:housenumber":"4",
    "addr:postcode":"8540",
    "addr:street":"Nieuwstraat",
    "iso:country":"BE",
    "sg:address":"Nieuwstraat 4",
    "sg:city":"Deerlijk",
    "sg:classifiers":[
        {
            "category":"Professional",
            "subcategory":"Art Services",
            "type":"Services"
        }
    ],
    "sg:phone":"+32 478 72 03 92",
    "sg:postcode":"8540",
    "sg:province":"West-Vlaanderen",
    "sg:tags":[
        "interior",
        "designer"
    ],
    "wof:name":"Benoit W",
    "wof:placetype":"venue"
},
  "geometry": {"coordinates":[3.3572900295,50.8539657593],"type":"Point"}
}