{
  "type": "Feature",
  "properties": {
    "addr:full":"Rue Du Collecteur 22 Anderlecht/anderlecht Bruxelles-Capitale 1070",
    "addr:housenumber":"22",
    "addr:postcode":"1070",
    "addr:street":"Rue Du Collecteur",
    "iso:country":"BE",
    "sg:address":"Rue Du Collecteur 22",
    "sg:city":"Anderlecht/anderlecht",
    "sg:orig_category":"Articles textiles and tissus de d\u00e9coration Fab",
    "sg:phone":"+32 2 521 58 20",
    "sg:postcode":"1070",
    "sg:province":"Bruxelles-Capitale",
    "wof:name":"Renoma Auvent",
    "wof:placetype":"venue"
},
  "geometry": {"coordinates":[4.3220877647,50.8394355774],"type":"Point"}
}