{
  "type": "Feature",
  "properties": {
    "iso:country":"BE",
    "sg:address":"Pastorijstraat 4",
    "sg:city":"Hasselt",
    "sg:orig_category":"Sportcentra Sportclubs Sportterreinen and installaties behalve sportcentra",
    "sg:phone":"+32 11 31 15 95",
    "sg:postcode":"3500",
    "sg:province":"Limburg",
    "wof:name":"Sporthal Elckerlyc",
    "wof:placetype":"venue"
},
  "geometry": {"coordinates":[5.3069148064,50.8987922668],"type":"Point"}
}