{
  "type": "Feature",
  "properties": {
    "iso:country":"BE",
    "sg:address":"Ekkergemstraat 66",
    "sg:city":"Gent",
    "sg:orig_category":"GROENTEN AND FRUIT Kruideniers",
    "sg:phone":"+32 9 253 91 13",
    "sg:postcode":"9000",
    "sg:province":"Oost-Vlaanderen",
    "wof:name":"Twinkelke De Baere",
    "wof:placetype":"venue"
},
  "geometry": {"coordinates":[3.7042019367,51.0508804321],"type":"Point"}
}