{
  "type": "Feature",
  "properties": {
    "iso:country":"BE",
    "sg:address":"Rue Vilatte 3",
    "sg:city":"Charleroi (jumet)",
    "sg:classifiers":[
        {
            "category":"Professional",
            "subcategory":"Accounting & Tax Preparation",
            "type":"Services"
        }
    ],
    "sg:phone":"+32 71 37 58 41",
    "sg:postcode":"6040",
    "sg:province":"Hainaut",
    "sg:tags":[
        "bookkeeper"
    ],
    "wof:name":"Chauvaux D",
    "wof:placetype":"venue"
},
  "geometry": {"coordinates":[4.4141521454,50.4469261169],"type":"Point"}
}