{
  "type": "Feature",
  "properties": {
    "iso:country":"BE",
    "sg:address":"Steenweg Op Merchtem 37",
    "sg:city":"Sint-jans-molenbeek/molenbeek-saint-jean",
    "sg:orig_category":"Herstellingen and onderhoud van auto's Metaalafval, schrootrecyclage and sloperijen",
    "sg:phone":"+32 2 414 00 79",
    "sg:postcode":"1080",
    "sg:province":"Bruxelles-Capitale",
    "wof:name":"Amel Car",
    "wof:placetype":"venue"
},
  "geometry": {"coordinates":[4.336868763,50.8567428589],"type":"Point"}
}