{
  "type": "Feature",
  "properties": {
    "addr:full":"Korte Keer 1 Deinze Oost-Vlaanderen 9800",
    "addr:housenumber":"1",
    "addr:postcode":"9800",
    "addr:street":"Korte Keer",
    "iso:country":"BE",
    "sg:address":"Korte Keer 1",
    "sg:city":"Deinze",
    "sg:orig_category":"Eleveurs and marchands de porcs. Eleveurs de bovins",
    "sg:phone":"+32 51 63 32 14",
    "sg:postcode":"9800",
    "sg:province":"Oost-Vlaanderen",
    "wof:name":"Leopold Scherpereel",
    "wof:placetype":"venue"
},
  "geometry": {"coordinates":[3.4418969154,50.9568252563],"type":"Point"}
}