{
  "type": "Feature",
  "properties": {
    "iso:country":"BE",
    "sg:address":"Schotensteenweg 1",
    "sg:city":"Brecht",
    "sg:classifiers":[
        {
            "category":"Manufacturing",
            "subcategory":"Metals",
            "type":"Manufacturing & Wholesale Goods"
        }
    ],
    "sg:phone":"+32 3 313 09 59",
    "sg:postcode":"2960",
    "sg:province":"Antwerpen",
    "sg:tags":[
        "turning"
    ],
    "wof:name":"Verdijck Luc Bvba",
    "wof:placetype":"venue"
},
  "geometry": {"coordinates":[4.6155500412,51.3359107971],"type":"Point"}
}