{
  "type": "Feature",
  "properties": {
    "addr:full":"Rue De Neufchateau 175 Tintigny Luxembourg 6730",
    "addr:housenumber":"175",
    "addr:postcode":"6730",
    "addr:street":"Rue De Neufchateau",
    "iso:country":"BE",
    "sg:address":"Rue De Neufchateau 175",
    "sg:city":"Tintigny",
    "sg:orig_category":"Cr\u00e9meries",
    "sg:phone":"+32 63 41 20 14",
    "sg:postcode":"6730",
    "sg:province":"Luxembourg",
    "wof:name":"Ariane Pecheur",
    "wof:placetype":"venue"
},
  "geometry": {"coordinates":[5.5135030746,49.6826934814],"type":"Point"}
}