{
  "type": "Feature",
  "properties": {
    "addr:full":"Rue Des Coqs 1 Grace-hollogne Li\u00e8ge 4460",
    "addr:housenumber":"1",
    "addr:postcode":"4460",
    "addr:street":"Rue Des Coqs",
    "iso:country":"BE",
    "sg:address":"Rue Des Coqs 1",
    "sg:city":"Grace-hollogne",
    "sg:orig_category":"HERSTELLING ELEKTRISCHE HUISHOUDAPPARATEN",
    "sg:phone":"+32 4 234 14 06",
    "sg:postcode":"4460",
    "sg:province":"Li\u00e8ge",
    "wof:name":"Renders",
    "wof:placetype":"venue"
},
  "geometry": {"coordinates":[5.476099968,50.6357498169],"type":"Point"}
}