{
  "type": "Feature",
  "properties": {
    "addr:full":"Bellegemsestraat 98 Kortrijk West-Vlaanderen 8510",
    "addr:housenumber":"98",
    "addr:postcode":"8510",
    "addr:street":"Bellegemsestraat",
    "iso:country":"BE",
    "sg:address":"Bellegemsestraat 98",
    "sg:city":"Kortrijk",
    "sg:orig_category":"Sportclubs",
    "sg:phone":"+32 56 22 83 28",
    "sg:postcode":"8510",
    "sg:province":"West-Vlaanderen",
    "wof:name":"V.c. Bellegem",
    "wof:placetype":"venue"
},
  "geometry": {"coordinates":[3.288916111,50.7774887085],"type":"Point"}
}