{
  "type": "Feature",
  "properties": {
    "addr:full":"Jef De Belderlaan 4 Sint-martens-latem (deurle) Oost-Vlaanderen 9831",
    "addr:housenumber":"4",
    "addr:postcode":"9831",
    "addr:street":"Jef De Belderlaan;Deurle",
    "iso:country":"BE",
    "sg:address":"Jef De Belderlaan 4",
    "sg:city":"Sint-martens-latem (deurle)",
    "sg:classifiers":[
        {
            "category":"Banks & Credit Unions",
            "subcategory":"Investment Brokerage",
            "type":"Services"
        }
    ],
    "sg:phone":"+32 9 282 02 39",
    "sg:postcode":"9831",
    "sg:province":"Oost-Vlaanderen",
    "sg:tags":[
        "auditor"
    ],
    "wof:name":"Hellebaut L",
    "wof:placetype":"venue"
},
  "geometry": {"coordinates":[3.6114830971,51.0028533936],"type":"Point"}
}