{
  "type": "Feature",
  "properties": {
    "iso:country":"BE",
    "sg:address":"Ankerrui 20",
    "sg:city":"Antwerpen",
    "sg:orig_category":"Autoverhuur",
    "sg:phone":"+32 3 232 35 00",
    "sg:postcode":"2000",
    "sg:province":"Antwerpen",
    "wof:name":"Budget Car & Truck Rental",
    "wof:placetype":"venue"
},
  "geometry": {"coordinates":[4.4111199379,51.2268257141],"type":"Point"}
}