{
  "type": "Feature",
  "properties": {
    "addr:full":"Rue De Huy 27 Waremme Li\u00e8ge 4300",
    "addr:housenumber":"27",
    "addr:postcode":"4300",
    "addr:street":"Rue De Huy",
    "iso:country":"BE",
    "sg:address":"Rue De Huy 27",
    "sg:city":"Waremme",
    "sg:orig_category":"HUISBRANDOLIE",
    "sg:phone":"+32 19 32 50 14",
    "sg:postcode":"4300",
    "sg:province":"Li\u00e8ge",
    "wof:name":"W\u00c9richar",
    "wof:placetype":"venue"
},
  "geometry": {"coordinates":[5.2520418167,50.6939086914],"type":"Point"}
}