{
  "type": "Feature",
  "properties": {
    "iso:country":"BE",
    "sg:address":"Rue Des Meuniers 9",
    "sg:city":"Beloeil (stambruges)",
    "sg:classifiers":[
        {
            "category":"Personal",
            "subcategory":"Barber",
            "type":"Services"
        }
    ],
    "sg:phone":"+32 69 57 69 16",
    "sg:postcode":"7973",
    "sg:province":"Hainaut",
    "sg:tags":[
        "gentleman",
        "salon",
        "-",
        "hairdressing"
    ],
    "wof:name":"Jean-louis",
    "wof:placetype":"venue"
},
  "geometry": {"coordinates":[3.7133750916,50.5111618042],"type":"Point"}
}