{
  "type": "Feature",
  "properties": {
    "addr:full":"Watervalstraat 48 Ardooie West-Vlaanderen 8850",
    "addr:housenumber":"48",
    "addr:postcode":"8850",
    "addr:street":"Watervalstraat",
    "iso:country":"BE",
    "sg:address":"Watervalstraat 48",
    "sg:city":"Ardooie",
    "sg:classifiers":[
        {
            "category":"Professional",
            "subcategory":"Printing & Photocopies",
            "type":"Services"
        }
    ],
    "sg:phone":"+32 51 74 69 18",
    "sg:postcode":"8850",
    "sg:province":"West-Vlaanderen",
    "sg:tags":[
        "-",
        "offset"
    ],
    "wof:name":"Rap Af",
    "wof:placetype":"venue"
},
  "geometry": {"coordinates":[3.2006840706,50.985496521],"type":"Point"}
}