{
  "type": "Feature",
  "properties": {
    "iso:country":"BE",
    "sg:address":"Rue Des D\u00c9port\u00c9s 20",
    "sg:city":"Verviers",
    "sg:classifiers":[
        {
            "category":"Shopping Center",
            "type":"Public Place"
        }
    ],
    "sg:phone":"+32 87 22 86 64",
    "sg:postcode":"4800",
    "sg:province":"Li\u00e8ge",
    "sg:tags":[
        "enseignement",
        "formation"
    ],
    "wof:name":"B.d.i. Informatique",
    "wof:placetype":"venue"
},
  "geometry": {"coordinates":[5.8516998291,50.5840492249],"type":"Point"}
}