{
  "type": "Feature",
  "properties": {
    "addr:full":"Hendrik I Lei 247 Vilvoorde Vlaams-Brabant 1800",
    "addr:housenumber":"247",
    "addr:postcode":"1800",
    "addr:street":"Hendrik I Lei",
    "iso:country":"BE",
    "sg:address":"Hendrik I Lei 247",
    "sg:city":"Vilvoorde",
    "sg:orig_category":"Onderdelen and accessoires voor auto's Voertuigen",
    "sg:phone":"+32 2 253 53 53",
    "sg:postcode":"1800",
    "sg:province":"Vlaams-Brabant",
    "wof:name":"Cardoen",
    "wof:placetype":"venue"
},
  "geometry": {"coordinates":[4.4326291084,50.9369087219],"type":"Point"}
}