{
  "type": "Feature",
  "properties": {
    "addr:full":"Grand Rejet 4 Tournai Hainaut 7542",
    "addr:housenumber":"4",
    "addr:postcode":"7542",
    "addr:street":"Rejet",
    "iso:country":"BE",
    "sg:address":"Grand Rejet 4",
    "sg:city":"Tournai",
    "sg:orig_category":"Eleveurs de bovins",
    "sg:phone":"+32 69 45 44 34",
    "sg:postcode":"7542",
    "sg:province":"Hainaut",
    "wof:name":"Gilbert Van Wynsberghe",
    "wof:placetype":"venue"
},
  "geometry": {"coordinates":[3.416105032,50.676158905],"type":"Point"}
}