{
  "type": "Feature",
  "properties": {
    "iso:country":"BE",
    "sg:address":"Europalaan 22",
    "sg:city":"Wevelgem",
    "sg:orig_category":"Binnenhuisarchitecten",
    "sg:phone":"+32 56 40 17 93",
    "sg:postcode":"8560",
    "sg:province":"West-Vlaanderen",
    "wof:name":"Johan Sabbe",
    "wof:placetype":"venue"
},
  "geometry": {"coordinates":[3.2091209888,50.8407211304],"type":"Point"}
}