{
  "type": "Feature",
  "properties": {
    "iso:country":"BE",
    "sg:address":"Pater R. Vande Wouwerstr 18",
    "sg:city":"Scherpenheuvel-zichem",
    "sg:orig_category":"Fleurs and plantes",
    "sg:phone":"+32 13 77 45 46",
    "sg:postcode":"3271",
    "sg:province":"Vlaams-Brabant",
    "wof:name":"Huis Amaranthus",
    "wof:placetype":"venue"
},
  "geometry": {"coordinates":[4.9835767746,51.0009346008],"type":"Point"}
}