{
  "type": "Feature",
  "properties": {
    "addr:full":"Laarstraat 174b1 Zwijndrecht Antwerpen 2070",
    "addr:housenumber":"174b1",
    "addr:postcode":"2070",
    "addr:street":"Laarstraat",
    "iso:country":"BE",
    "sg:address":"Laarstraat 174b1",
    "sg:city":"Zwijndrecht",
    "sg:orig_category":"Installation \u00e9lectrique r\u00e9sidentielle",
    "sg:phone":"+32 3 775 18 64",
    "sg:postcode":"2070",
    "sg:province":"Antwerpen",
    "wof:name":"Electro-design Ro En Ro",
    "wof:placetype":"venue"
},
  "geometry": {"coordinates":[4.3393058777,51.2164802551],"type":"Point"}
}