{
  "type": "Feature",
  "properties": {
    "addr:full":"Hogeschoollaan 34 Elsene/ixelles Bruxelles-Capitale 1050",
    "addr:housenumber":"34",
    "addr:postcode":"1050",
    "addr:street":"Hogeschoollaan",
    "iso:country":"BE",
    "sg:address":"Hogeschoollaan 34",
    "sg:city":"Elsene/ixelles",
    "sg:orig_category":"Dameskledingzaken",
    "sg:phone":"+32 2 648 17 24",
    "sg:postcode":"1050",
    "sg:province":"Bruxelles-Capitale",
    "wof:name":"Jalutex",
    "wof:placetype":"venue"
},
  "geometry": {"coordinates":[4.3883528709,50.8149719238],"type":"Point"}
}