{
  "type": "Feature",
  "properties": {
    "iso:country":"BE",
    "sg:address":"Cederstraat 29",
    "sg:city":"Mechelen",
    "sg:classifiers":[
        {
            "category":"Shopping",
            "subcategory":"Pets & Pet Supplies",
            "type":"Retail Goods"
        }
    ],
    "sg:phone":"+32 477 50 76 54",
    "sg:postcode":"2800",
    "sg:province":"Antwerpen",
    "sg:tags":[
        "horseriding"
    ],
    "wof:name":"Bruggeman Michael",
    "wof:placetype":"venue"
},
  "geometry": {"coordinates":[4.480494976,51.0072441101],"type":"Point"}
}