{
  "type": "Feature",
  "properties": {
    "iso:country":"BE",
    "sg:address":"Rue Neuve 71",
    "sg:city":"Charleroi",
    "sg:orig_category":"Telecommunicatieapparaten",
    "sg:phone":"+32 71 31 30 05",
    "sg:postcode":"6000",
    "sg:province":"Hainaut",
    "wof:name":"Techno-comm",
    "wof:placetype":"venue"
},
  "geometry": {"coordinates":[4.4462828636,50.4137420654],"type":"Point"}
}