{
  "type": "Feature",
  "properties": {
    "iso:country":"BE",
    "sg:address":"Rue Chemin De Fer 50",
    "sg:city":"Comines-warneton",
    "sg:orig_category":"Reisbureaus",
    "sg:phone":"+32 56 55 52 58",
    "sg:postcode":"7780",
    "sg:province":"Hainaut",
    "wof:name":"Lys Travel",
    "wof:placetype":"venue"
},
  "geometry": {"coordinates":[3.0018720627,50.7724227905],"type":"Point"}
}