{
  "type": "Feature",
  "properties": {
    "iso:country":"BE",
    "sg:address":"Rue De La Grosse Pomme 10",
    "sg:city":"Mons",
    "sg:classifiers":[
        {
            "category":"Health Services",
            "subcategory":"Doctor",
            "type":"Services"
        }
    ],
    "sg:phone":"+32 65 31 69 48",
    "sg:postcode":"7000",
    "sg:province":"Hainaut",
    "sg:tags":[
        "medicinephysicians",
        "surgeon"
    ],
    "wof:name":"Baize Michel",
    "wof:placetype":"venue"
},
  "geometry": {"coordinates":[3.9460279942,50.4530754089],"type":"Point"}
}