{
  "type": "Feature",
  "properties": {
    "iso:country":"BE",
    "sg:address":"Bld Du Jardin Botanique 29",
    "sg:city":"Brussel/bruxelles",
    "sg:orig_category":"Services annexes des transports terrestres",
    "sg:phone":"+32 2 217 18 31",
    "sg:postcode":"1000",
    "sg:province":"Bruxelles-Capitale",
    "wof:name":"Parking Botanique",
    "wof:placetype":"venue"
},
  "geometry": {"coordinates":[4.3600959778,50.854637146],"type":"Point"}
}