{
  "type": "Feature",
  "properties": {
    "addr:full":"Boterhoek 19 Lovendegem Oost-Vlaanderen 9920",
    "addr:housenumber":"19",
    "addr:postcode":"9920",
    "addr:street":"Boterhoek",
    "iso:country":"BE",
    "sg:address":"Boterhoek 19",
    "sg:city":"Lovendegem",
    "sg:orig_category":"Producteurs de l\u00e9gumes. Transports terrestres de voyageurs",
    "sg:phone":"+32 9 372 76 60",
    "sg:postcode":"9920",
    "sg:province":"Oost-Vlaanderen",
    "wof:name":"Antoine De Pourcq",
    "wof:placetype":"venue"
},
  "geometry": {"coordinates":[3.6355130672,51.1154441833],"type":"Point"}
}