{
  "type": "Feature",
  "properties": {
    "iso:country":"BE",
    "sg:address":"Pansgatelaan 2",
    "sg:city":"Mortsel",
    "sg:orig_category":"Plaatsen van vloer- and muurbekleding Schilders",
    "sg:phone":"+32 3 440 89 55",
    "sg:postcode":"2640",
    "sg:province":"Antwerpen",
    "wof:name":"Frank Roggemans",
    "wof:placetype":"venue"
},
  "geometry": {"coordinates":[4.4476370811,51.1869277954],"type":"Point"}
}