{
  "type": "Feature",
  "properties": {
    "addr:full":"Hernestraat 9 Edingen/enghien Hainaut 7850",
    "addr:housenumber":"9",
    "addr:postcode":"7850",
    "addr:street":"Hernestraat",
    "iso:country":"BE",
    "sg:address":"Hernestraat 9",
    "sg:city":"Edingen/enghien",
    "sg:orig_category":"Industri\u00eble wasserijen and droogkuis",
    "sg:phone":"+32 2 395 60 73",
    "sg:postcode":"7850",
    "sg:province":"Hainaut",
    "wof:name":"Nett A Neuf",
    "wof:placetype":"venue"
},
  "geometry": {"coordinates":[4.0394091606,50.6938705444],"type":"Point"}
}