{
  "type": "Feature",
  "properties": {
    "addr:full":"Rue Du Grand Etang 44a Fosses-la-ville Namur 5070",
    "addr:housenumber":"44a",
    "addr:postcode":"5070",
    "addr:street":"Rue Du Grand Etang",
    "iso:country":"BE",
    "sg:address":"Rue Du Grand Etang 44a",
    "sg:city":"Fosses-la-ville",
    "sg:classifiers":[
        {
            "category":"Food & Beverages",
            "subcategory":"Groceries & Convenience Stores",
            "type":"Retail Goods"
        }
    ],
    "sg:phone":"+32 71 72 69 59",
    "sg:postcode":"5070",
    "sg:province":"Namur",
    "sg:tags":[
        "grocer"
    ],
    "wof:name":"Epiciers Sympas (les)",
    "wof:placetype":"venue"
},
  "geometry": {"coordinates":[4.6942338943,50.3745193481],"type":"Point"}
}