{
  "type": "Feature",
  "properties": {
    "addr:full":"Rue De L'ypr\u00c9au 22 Ronse/renaix Oost-Vlaanderen 9600",
    "addr:housenumber":"22",
    "addr:postcode":"9600",
    "addr:street":"Rue De L'Ypre \u0301Au",
    "iso:country":"BE",
    "sg:address":"Rue De L'ypr\u00c9au 22",
    "sg:city":"Ronse/renaix",
    "sg:orig_category":"Pharmaciens",
    "sg:phone":"+32 55 21 39 17",
    "sg:postcode":"9600",
    "sg:province":"Oost-Vlaanderen",
    "wof:name":"Anne-marie Van Laethem",
    "wof:placetype":"venue"
},
  "geometry": {"coordinates":[3.5999140739,50.7458534241],"type":"Point"}
}