{
  "type": "Feature",
  "properties": {
    "addr:full":"Doorniksewijk 88 Kortrijk West-Vlaanderen 8500",
    "addr:housenumber":"88",
    "addr:postcode":"8500",
    "addr:street":"Doorniksewijk",
    "iso:country":"BE",
    "sg:address":"Doorniksewijk 88",
    "sg:city":"Kortrijk",
    "sg:classifiers":[
        {
            "category":"Shopping",
            "subcategory":"Clothing, Apparel, & Fashions",
            "type":"Retail Goods"
        }
    ],
    "sg:phone":"+32 56 20 69 29",
    "sg:postcode":"8500",
    "sg:province":"West-Vlaanderen",
    "sg:tags":[
        "underwear",
        "lingerie",
        "-"
    ],
    "wof:name":"Allegria",
    "wof:placetype":"venue"
},
  "geometry": {"coordinates":[3.268871069,50.8206558228],"type":"Point"}
}