{
  "type": "Feature",
  "properties": {
    "iso:country":"BE",
    "sg:address":"Rue Drootbeek 91",
    "sg:city":"Bruxelles",
    "sg:classifiers":[
        {
            "category":"Professional",
            "subcategory":"Testing Lab",
            "type":"Services"
        }
    ],
    "sg:phone":"+32 2 425 43 72",
    "sg:postcode":"1020",
    "sg:province":"Bruxelles-Capitale",
    "sg:tags":[
        "chemist"
    ],
    "wof:name":"De Munck M",
    "wof:placetype":"venue"
},
  "geometry": {"coordinates":[4.348760128,50.872428894],"type":"Point"}
}