{
  "type": "Feature",
  "properties": {
    "addr:full":"Hoogleedsesteenweg 262 Roeselare West-Vlaanderen 8800",
    "addr:housenumber":"262",
    "addr:postcode":"8800",
    "addr:street":"Hoogleedsesteenweg",
    "iso:country":"BE",
    "sg:address":"Hoogleedsesteenweg 262",
    "sg:city":"Roeselare",
    "sg:classifiers":[
        {
            "category":"Health Services",
            "subcategory":"Chiropractor",
            "type":"Services"
        }
    ],
    "sg:phone":"+32 51 31 03 07",
    "sg:postcode":"8800",
    "sg:province":"West-Vlaanderen",
    "wof:name":"Van Neste M",
    "wof:placetype":"venue"
},
  "geometry": {"coordinates":[3.1086339951,50.9568748474],"type":"Point"}
}