{
  "type": "Feature",
  "properties": {
    "addr:full":"Opheersstraat 81 Heers (opheers) Limburg 3870",
    "addr:housenumber":"81",
    "addr:postcode":"3870",
    "addr:street":"Opheersstraat",
    "iso:country":"BE",
    "sg:address":"Opheersstraat 81",
    "sg:city":"Heers (opheers)",
    "sg:classifiers":[
        {
            "category":"Professional",
            "subcategory":"Art Services",
            "type":"Services"
        }
    ],
    "sg:phone":"+32 11 48 11 00",
    "sg:postcode":"3870",
    "sg:province":"Limburg",
    "sg:tags":[
        "interior",
        "designer"
    ],
    "wof:name":"Vof Ontwerpbureau Nv-vandueren Interieur Collection",
    "wof:placetype":"venue"
},
  "geometry": {"coordinates":[5.2985401154,50.7415885925],"type":"Point"}
}