{
  "type": "Feature",
  "properties": {
    "iso:country":"BE",
    "sg:address":"Aarschotsesteenweg 435",
    "sg:city":"Leuven (wilsele)",
    "sg:classifiers":[
        {
            "category":"Shopping",
            "subcategory":"Gifts & Souvenirs",
            "type":"Retail Goods"
        }
    ],
    "sg:phone":"+32 16 44 09 55",
    "sg:postcode":"3012",
    "sg:province":"Vlaams-Brabant",
    "sg:tags":[
        "-"
    ],
    "wof:name":"Paladini",
    "wof:placetype":"venue"
},
  "geometry": {"coordinates":[4.7211399078,50.9245452881],"type":"Point"}
}