{
  "type": "Feature",
  "properties": {
    "iso:country":"BE",
    "sg:address":"Rue Du Vicinal 115",
    "sg:city":"Arlon",
    "sg:orig_category":"HUISBRANDOLIE Installatie van houten of kunststof schrijnwerk",
    "sg:phone":"+32 63 22 63 86",
    "sg:postcode":"6700",
    "sg:province":"Luxembourg",
    "wof:name":"Serforex",
    "wof:placetype":"venue"
},
  "geometry": {"coordinates":[5.8126749992,49.6823234558],"type":"Point"}
}