{
  "type": "Feature",
  "properties": {
    "iso:country":"BE",
    "sg:address":"Nijverheidslaan 3",
    "sg:city":"Geluwe",
    "sg:classifiers":[
        {
            "category":"Structure",
            "subcategory":"Warehouse",
            "type":"Public Place"
        }
    ],
    "sg:phone":"+32 56 51 80 00",
    "sg:postcode":"8940",
    "sg:province":"West-Vlaanderen",
    "sg:tags":[
        "chiller",
        "air-conditioning",
        "system"
    ],
    "wof:name":"Calis Koeltechniek Nv",
    "wof:placetype":"venue"
},
  "geometry": {"coordinates":[3.069879055,50.8130950928],"type":"Point"}
}