{
  "type": "Feature",
  "properties": {
    "addr:full":"Avenue Des Fleurs 1 - Brussels Bruxelles-Capitale 1150",
    "addr:housenumber":"1",
    "addr:postcode":"1150",
    "addr:street":"Avenue Des Fleurs",
    "iso:country":"BE",
    "sg:address":"Avenue Des Fleurs 1 -",
    "sg:city":"Brussels",
    "sg:classifiers":[
        {
            "category":"Professional",
            "subcategory":"Art Services",
            "type":"Services"
        }
    ],
    "sg:phone":"+32 2 763 07 21",
    "sg:postcode":"1150",
    "sg:province":"Bruxelles-Capitale",
    "sg:tags":[
        "export-import"
    ],
    "wof:name":"Rwanda Embassy",
    "wof:placetype":"venue"
},
  "geometry": {"coordinates":[4.4398131371,50.8271255493],"type":"Point"}
}