{
  "type": "Feature",
  "properties": {
    "iso:country":"BE",
    "sg:address":"Oude Processieweg 42",
    "sg:city":"Nieuwerkerken",
    "sg:orig_category":"Studios photographiques",
    "sg:phone":"+32 11 67 25 81",
    "sg:postcode":"3850",
    "sg:province":"Limburg",
    "wof:name":"Jos Hermans",
    "wof:placetype":"venue"
},
  "geometry": {"coordinates":[5.2024588585,50.8659934998],"type":"Point"}
}