{
  "type": "Feature",
  "properties": {
    "addr:full":"Rue Pige Croly 39 Bergen Hainaut 7011",
    "addr:housenumber":"39",
    "addr:postcode":"7011",
    "addr:street":"Rue Pige Croly",
    "iso:country":"BE",
    "sg:address":"Rue Pige Croly 39",
    "sg:city":"Bergen",
    "sg:orig_category":"Brandweer and civiele bescherming",
    "sg:phone":"+32 65 35 43 00",
    "sg:postcode":"7011",
    "sg:province":"Hainaut",
    "wof:name":"Protection Civile Intervention Ghlin",
    "wof:placetype":"venue"
},
  "geometry": {"coordinates":[3.912539959,50.4712982178],"type":"Point"}
}