{
  "type": "Feature",
  "properties": {
    "addr:full":"Industriestraat 13 Kampenhout Vlaams-Brabant 1910",
    "addr:housenumber":"13",
    "addr:postcode":"1910",
    "addr:street":"Industriestraat",
    "iso:country":"BE",
    "sg:address":"Industriestraat 13",
    "sg:city":"Kampenhout",
    "sg:orig_category":"D\u00e9molition d\u00b4immeubles and terrassements",
    "sg:phone":"+32 16 60 88 04",
    "sg:postcode":"1910",
    "sg:province":"Vlaams-Brabant",
    "wof:name":"Oldstone",
    "wof:placetype":"venue"
},
  "geometry": {"coordinates":[4.5981850624,50.9587135315],"type":"Point"}
}