{
  "type": "Feature",
  "properties": {
    "addr:full":"Waterloostraat 4 Herentals Antwerpen 2200",
    "addr:housenumber":"4",
    "addr:postcode":"2200",
    "addr:street":"Waterloostraat",
    "iso:country":"BE",
    "sg:address":"Waterloostraat 4",
    "sg:city":"Herentals",
    "sg:classifiers":[
        {
            "category":"Arena",
            "subcategory":"Sports Club",
            "type":"Entertainment"
        }
    ],
    "sg:phone":"+32 14 21 16 91",
    "sg:postcode":"2200",
    "sg:province":"Antwerpen",
    "sg:tags":[
        "de"
    ],
    "wof:name":"B.s.c. Red White Giants",
    "wof:placetype":"venue"
},
  "geometry": {"coordinates":[4.8258519173,51.1744842529],"type":"Point"}
}