{
  "type": "Feature",
  "properties": {
    "addr:full":"Vrijheidstraat 13 Aalst Oost-Vlaanderen 9300",
    "addr:housenumber":"13",
    "addr:postcode":"9300",
    "addr:street":"Vrijheidstraat",
    "iso:country":"BE",
    "sg:address":"Vrijheidstraat 13",
    "sg:city":"Aalst",
    "sg:classifiers":[
        {
            "category":"Retail",
            "subcategory":"Laundry & Dry Cleaning",
            "type":"Services"
        }
    ],
    "sg:phone":"+32 53 21 38 65",
    "sg:postcode":"9300",
    "sg:province":"Oost-Vlaanderen",
    "sg:tags":[
        "dyer",
        "cleaner"
    ],
    "wof:name":"Super Shop",
    "wof:placetype":"venue"
},
  "geometry": {"coordinates":[4.0351610184,50.9407196045],"type":"Point"}
}