{
  "type": "Feature",
  "properties": {
    "iso:country":"BE",
    "sg:address":"Bruinsbroekstraat 2",
    "sg:city":"Galmaarden",
    "sg:classifiers":[
        {
            "category":"Professional",
            "subcategory":"Management & Consulting",
            "type":"Services"
        }
    ],
    "sg:phone":"+32 54 58 66 07",
    "sg:postcode":"1570",
    "sg:province":"Vlaams-Brabant",
    "sg:tags":[
        "consultant"
    ],
    "wof:name":"Consalmarkt Bvba",
    "wof:placetype":"venue"
},
  "geometry": {"coordinates":[3.9615700245,50.7670936584],"type":"Point"}
}