{
  "type": "Feature",
  "properties": {
    "iso:country":"BE",
    "sg:address":"Rue Des Foss\u00c9s Fleuris 4",
    "sg:city":"Namur",
    "sg:orig_category":"V\u00eatements",
    "sg:phone":"+32 81 26 04 48",
    "sg:postcode":"5000",
    "sg:province":"Namur",
    "wof:name":"Au Bleu Sarrau",
    "wof:placetype":"venue"
},
  "geometry": {"coordinates":[4.8653640747,50.4625968933],"type":"Point"}
}