{
  "type": "Feature",
  "properties": {
    "addr:full":"'t Hoge 57 Kortrijk West-Vlaanderen 8500",
    "addr:housenumber":"57",
    "addr:postcode":"8500",
    "addr:street":"' T Hoge",
    "iso:country":"BE",
    "sg:address":"'t Hoge 57",
    "sg:city":"Kortrijk",
    "sg:orig_category":"Rusthuizen and serviceflats",
    "sg:phone":"+32 56 21 85 34",
    "sg:postcode":"8500",
    "sg:province":"West-Vlaanderen",
    "wof:name":"Home 't Hoge",
    "wof:placetype":"venue"
},
  "geometry": {"coordinates":[3.2870059013,50.7974624634],"type":"Point"}
}