{
  "type": "Feature",
  "properties": {
    "iso:country":"BE",
    "sg:address":"Zandvoordestraat 51",
    "sg:city":"Oostende",
    "sg:orig_category":"Pain, p\u00e2tisseries and confiseries",
    "sg:phone":"+32 59 70 42 70",
    "sg:postcode":"8400",
    "sg:province":"West-Vlaanderen",
    "wof:name":"Pascal Lievens",
    "wof:placetype":"venue"
},
  "geometry": {"coordinates":[2.9380319118,51.2163085938],"type":"Point"}
}