{
  "type": "Feature",
  "properties": {
    "iso:country":"BE",
    "sg:address":"Rue Wirie 9",
    "sg:city":"Tournai (gaurain-ramecroix)",
    "sg:classifiers":[
        {
            "category":"Shopping",
            "subcategory":"Pets & Pet Supplies",
            "type":"Retail Goods"
        }
    ],
    "sg:phone":"+32 69 54 74 38",
    "sg:postcode":"7530",
    "sg:province":"Hainaut",
    "sg:tags":[
        "shop",
        "-"
    ],
    "wof:name":"Chatterie Full Power",
    "wof:placetype":"venue"
},
  "geometry": {"coordinates":[3.493293047,50.5971221924],"type":"Point"}
}