{
  "type": "Feature",
  "properties": {
    "iso:country":"BE",
    "sg:address":"Avenue Brugmann 542",
    "sg:city":"Ukkel/uccle",
    "sg:classifiers":[
        {
            "category":"Restaurant",
            "type":"Food & Drink"
        }
    ],
    "sg:phone":"+32 2 332 51 27",
    "sg:postcode":"1180",
    "sg:province":"Bruxelles-Capitale",
    "sg:tags":[
        "caf\u00e9s"
    ],
    "wof:name":"Taverne Le Central",
    "wof:placetype":"venue"
},
  "geometry": {"coordinates":[4.3369932175,50.8003425598],"type":"Point"}
}