{
  "type": "Feature",
  "properties": {
    "addr:full":"Heieinde 42 Hoogstraten (meerle) Antwerpen 2328",
    "addr:housenumber":"42",
    "addr:postcode":"2328",
    "addr:street":"Heieinde",
    "iso:country":"BE",
    "sg:address":"Heieinde 42",
    "sg:city":"Hoogstraten (meerle)",
    "sg:classifiers":[
        {
            "category":"Utilities",
            "subcategory":"Natural Gas",
            "type":"Services"
        }
    ],
    "sg:phone":"+32 3 315 88 70",
    "sg:postcode":"2328",
    "sg:province":"Antwerpen",
    "sg:tags":[
        "welding"
    ],
    "wof:name":"Van Den Broeck J",
    "wof:placetype":"venue"
},
  "geometry": {"coordinates":[4.7727937698,51.5028762817],"type":"Point"}
}