{
  "type": "Feature",
  "properties": {
    "iso:country":"BE",
    "sg:address":"Em. Vandersteenenstraat 56",
    "sg:city":"Sint-pieters-leeuw",
    "sg:orig_category":"Electrom\u00e9nager, t\u00e9l\u00e9visions and radios",
    "sg:phone":"+32 2 377 01 28",
    "sg:postcode":"1600",
    "sg:province":"Vlaams-Brabant",
    "wof:name":"Urbain Mostinckx",
    "wof:placetype":"venue"
},
  "geometry": {"coordinates":[4.2693710327,50.7822647095],"type":"Point"}
}