{
  "type": "Feature",
  "properties": {
    "iso:country":"BE",
    "sg:address":"Rue Des Bois 160",
    "sg:city":"La Louviere",
    "sg:orig_category":"Installation \u00e9lectrique r\u00e9sidentielle. Lampes and appareils \u00e9lectriques Fab. Installation \u00e9lectrique",
    "sg:phone":"+32 64 55 45 59",
    "sg:postcode":"7100",
    "sg:province":"Hainaut",
    "wof:name":"Patrick Mahieu",
    "wof:placetype":"venue"
},
  "geometry": {"coordinates":[4.2067461014,50.5013504028],"type":"Point"}
}