{
  "type": "Feature",
  "properties": {
    "addr:full":"Tweekapellenstraat 27 Gent Oost-Vlaanderen 9050",
    "addr:housenumber":"27",
    "addr:postcode":"9050",
    "addr:street":"Tweekapellenstraat;Oost-Vlaanderen",
    "iso:country":"BE",
    "sg:address":"Tweekapellenstraat 27",
    "sg:city":"Gent",
    "sg:classifiers":[
        {
            "category":"Organizations",
            "subcategory":"Community Association",
            "type":"Services"
        }
    ],
    "sg:phone":"+32 9 230 37 87",
    "sg:postcode":"9050",
    "sg:province":"Oost-Vlaanderen",
    "sg:tags":[
        "organisation"
    ],
    "wof:name":"J.a. Krejo",
    "wof:placetype":"venue"
},
  "geometry": {"coordinates":[3.7589480877,51.0448532104],"type":"Point"}
}