{
  "type": "Feature",
  "properties": {
    "iso:country":"BE",
    "sg:address":"Rue Pont-\u00e0-la-pont-faulx 16",
    "sg:city":"P\u00e9ruwelz",
    "sg:classifiers":[
        {
            "category":"Personal",
            "subcategory":"Beauty Salon",
            "type":"Services"
        }
    ],
    "sg:phone":"+32 69 78 02 85",
    "sg:postcode":"7600",
    "sg:province":"Hainaut",
    "sg:tags":[
        "lady",
        "-",
        "hairdressing"
    ],
    "wof:name":"Dory Del",
    "wof:placetype":"venue"
},
  "geometry": {"coordinates":[3.5950939655,50.5106887817],"type":"Point"}
}