{
  "type": "Feature",
  "properties": {
    "addr:full":"Abelestraat 36 Izegem West-Vlaanderen 8870",
    "addr:housenumber":"36",
    "addr:postcode":"8870",
    "addr:street":"Abelestraat",
    "iso:country":"BE",
    "sg:address":"Abelestraat 36",
    "sg:city":"Izegem",
    "sg:classifiers":[
        {
            "category":"Retail",
            "subcategory":"Event Space",
            "type":"Services"
        }
    ],
    "sg:phone":"+32 51 31 38 37",
    "sg:postcode":"8870",
    "sg:province":"West-Vlaanderen",
    "sg:tags":[
        "rental",
        "-",
        "hall"
    ],
    "wof:name":"Ter Maerel",
    "wof:placetype":"venue"
},
  "geometry": {"coordinates":[3.1889939308,50.9219360352],"type":"Point"}
}