{
  "type": "Feature",
  "properties": {
    "iso:country":"BE",
    "sg:address":"Jules Besmestraat 96",
    "sg:city":"Koekelberg/koekelberg",
    "sg:orig_category":"Elektrische installaties voor woningen",
    "sg:phone":"+32 2 414 68 53",
    "sg:postcode":"1081",
    "sg:province":"Bruxelles-Capitale",
    "wof:name":"Pedro Zapatero",
    "wof:placetype":"venue"
},
  "geometry": {"coordinates":[4.3205218315,50.8626441956],"type":"Point"}
}