{
  "type": "Feature",
  "properties": {
    "iso:country":"BE",
    "sg:address":"Koppelstraat 3",
    "sg:city":"Dilsen-stokkem",
    "sg:orig_category":"M\u00e9decins and sp\u00e9cialistes",
    "sg:phone":"+32 89 75 65 61",
    "sg:postcode":"3650",
    "sg:province":"Limburg",
    "wof:name":"C. Van De Beek",
    "wof:placetype":"venue"
},
  "geometry": {"coordinates":[5.7219891548,51.0164604187],"type":"Point"}
}