{
  "type": "Feature",
  "properties": {
    "iso:country":"BE",
    "sg:address":"Van Eycklaan 27",
    "sg:city":"Arendonk",
    "sg:orig_category":"Banken and kredietinstellingen",
    "sg:phone":"+32 14 67 82 36",
    "sg:postcode":"2370",
    "sg:province":"Antwerpen",
    "wof:name":"Groep Argenta",
    "wof:placetype":"venue"
},
  "geometry": {"coordinates":[5.0835180283,51.3233757019],"type":"Point"}
}