{
  "type": "Feature",
  "properties": {
    "addr:full":"Rue E. Claus 38 Elsene/ixelles Bruxelles-Capitale 1050",
    "addr:housenumber":"38",
    "addr:postcode":"1050",
    "addr:street":"Rue E. Claus",
    "iso:country":"BE",
    "sg:address":"Rue E. Claus 38",
    "sg:city":"Elsene/ixelles",
    "sg:orig_category":"Jardinage",
    "sg:phone":"+32 2 647 82 03",
    "sg:postcode":"1050",
    "sg:province":"Bruxelles-Capitale",
    "wof:name":"Matot Ph.",
    "wof:placetype":"venue"
},
  "geometry": {"coordinates":[4.3690562248,50.8158798218],"type":"Point"}
}