{
  "type": "Feature",
  "properties": {
    "iso:country":"BE",
    "sg:address":"Rue Albert I",
    "sg:city":"La Louvi\u00c8re",
    "sg:orig_category":"Bagage and lederwaren",
    "sg:phone":"+32 64 28 51 76",
    "sg:postcode":"7100",
    "sg:province":"Hainaut",
    "wof:name":"Maroquinerie Gallea",
    "wof:placetype":"venue"
},
  "geometry": {"coordinates":[4.1856532097,50.4756622314],"type":"Point"}
}