{
  "type": "Feature",
  "properties": {
    "iso:country":"BE",
    "sg:address":"Rue De Stockel 41",
    "sg:city":"Kraainem/kraainem",
    "sg:orig_category":"M\u00e9decins and sp\u00e9cialistes",
    "sg:phone":"+32 2 721 42 69",
    "sg:postcode":"1950",
    "sg:province":"Vlaams-Brabant",
    "wof:name":"Martine De Kock",
    "wof:placetype":"venue"
},
  "geometry": {"coordinates":[4.4671778679,50.8595619202],"type":"Point"}
}