{
  "type": "Feature",
  "properties": {
    "iso:country":"BE",
    "sg:address":"Lembekedorp 13",
    "sg:city":"Kaprijke",
    "sg:orig_category":"Artsen and specialisten",
    "sg:phone":"+32 9 378 05 55",
    "sg:postcode":"9971",
    "sg:province":"Oost-Vlaanderen",
    "wof:name":"J. Matthys",
    "wof:placetype":"venue"
},
  "geometry": {"coordinates":[3.6329059601,51.1953201294],"type":"Point"}
}