{
  "type": "Feature",
  "properties": {
    "addr:full":"Brugse Steenweg 67 Blankenberge (uitkerke) West-Vlaanderen 8370",
    "addr:housenumber":"67",
    "addr:postcode":"8370",
    "addr:street":"Brugse Steenweg",
    "iso:country":"BE",
    "sg:address":"Brugse Steenweg 67",
    "sg:city":"Blankenberge (uitkerke)",
    "sg:classifiers":[
        {
            "category":"Retail",
            "subcategory":"Auto Rental",
            "type":"Services"
        }
    ],
    "sg:phone":"+32 50 41 17 42",
    "sg:postcode":"8370",
    "sg:province":"West-Vlaanderen",
    "sg:tags":[
        "van",
        "hire",
        "-",
        "truck"
    ],
    "wof:name":"Remi Huurwagens",
    "wof:placetype":"venue"
},
  "geometry": {"coordinates":[3.1474559307,51.2995872498],"type":"Point"}
}