{
  "type": "Feature",
  "properties": {
    "addr:full":"Koolskampstraat 85 Lichtervelde West-Vlaanderen 8810",
    "addr:housenumber":"85",
    "addr:postcode":"8810",
    "addr:street":"Koolskampstraat",
    "iso:country":"BE",
    "sg:address":"Koolskampstraat 85",
    "sg:city":"Lichtervelde",
    "sg:orig_category":"Metaalbehandeling and -bekleding Paramedische behandelingen",
    "sg:phone":"+32 51 72 56 19",
    "sg:postcode":"8810",
    "sg:province":"West-Vlaanderen",
    "wof:name":"Van Doorne Metaal",
    "wof:placetype":"venue"
},
  "geometry": {"coordinates":[3.1537919044,51.0210113525],"type":"Point"}
}