{
  "type": "Feature",
  "properties": {
    "iso:country":"BE",
    "sg:address":"Rue Des Wallons 10",
    "sg:city":"Ottignies-louvain-la-neuve",
    "sg:orig_category":"Opvangtehuizen and vluchthuizen",
    "sg:phone":"+32 10 47 20 02",
    "sg:postcode":"1348",
    "sg:province":"Brabant Wallon",
    "wof:name":"Serv. Aide Aux Etudiants",
    "wof:placetype":"venue"
},
  "geometry": {"coordinates":[4.6160011292,50.6691246033],"type":"Point"}
}