{
  "type": "Feature",
  "properties": {
    "addr:full":"Acht Bundersstraat 56 Zaventem (grand) Vlaams-Brabant 1933",
    "addr:housenumber":"56;1933",
    "addr:street":"Acht Bundersstraat",
    "iso:country":"BE",
    "sg:address":"Acht Bundersstraat 56",
    "sg:city":"Zaventem (grand)",
    "sg:orig_category":"Elektrische installaties voor woningen",
    "sg:phone":"+32 2 731 65 48",
    "sg:postcode":"1933",
    "sg:province":"Vlaams-Brabant",
    "wof:name":"Avincelec",
    "wof:placetype":"venue"
},
  "geometry": {"coordinates":[4.5228328705,50.8632240295],"type":"Point"}
}