{
  "type": "Feature",
  "properties": {
    "addr:full":"Rue Ferrer 20 Dour Hainaut 7370",
    "addr:housenumber":"20",
    "addr:postcode":"7370",
    "addr:street":"Rue Ferrer;Hainaut",
    "iso:country":"BE",
    "sg:address":"Rue Ferrer 20",
    "sg:city":"Dour",
    "sg:orig_category":"Slagers",
    "sg:phone":"+32 65 65 51 32",
    "sg:postcode":"7370",
    "sg:province":"Hainaut",
    "wof:name":"Desire Tellier",
    "wof:placetype":"venue"
},
  "geometry": {"coordinates":[3.7562110424,50.3877906799],"type":"Point"}
}