{
  "type": "Feature",
  "properties": {
    "iso:country":"BE",
    "sg:address":"Gemeenteplein 14 Box 12",
    "sg:city":"Asse",
    "sg:classifiers":[
        {
            "category":"Professional",
            "subcategory":"Engineering",
            "type":"Services"
        }
    ],
    "sg:phone":"+32 2 452 81 51",
    "sg:postcode":"1730",
    "sg:province":"Vlaams-Brabant",
    "sg:tags":[
        "-"
    ],
    "wof:name":"De Valck Engineering-dve Nv",
    "wof:placetype":"venue"
},
  "geometry": {"coordinates":[4.1994819641,50.9103164673],"type":"Point"}
}