{
  "type": "Feature",
  "properties": {
    "addr:full":"Rue Albert I 56 La Louvi\u00e8re Hainaut 7100",
    "addr:housenumber":"56",
    "addr:postcode":"7100",
    "addr:street":"Rue Albert I",
    "iso:country":"BE",
    "sg:address":"Rue Albert I 56",
    "sg:city":"La Louvi\u00e8re",
    "sg:classifiers":[
        {
            "category":"Shopping",
            "subcategory":"Clothing, Apparel, & Fashions",
            "type":"Retail Goods"
        }
    ],
    "sg:phone":"+32 64 84 20 44",
    "sg:postcode":"7100",
    "sg:province":"Hainaut",
    "sg:tags":[
        "lady",
        "clothing",
        "-"
    ],
    "wof:name":"Jus De Fruits",
    "wof:placetype":"venue"
},
  "geometry": {"coordinates":[4.2118902206,50.4707603455],"type":"Point"}
}