{
  "type": "Feature",
  "properties": {
    "iso:country":"BE",
    "sg:address":"Quai Des Usines 22bg1",
    "sg:city":"Brussel/bruxelles",
    "sg:orig_category":"Fruits and l\u00e9gumes Caf\u00e9, th\u00e9, cacao and \u00e9pices Gr",
    "sg:phone":"+32 2 241 52 66",
    "sg:postcode":"1000",
    "sg:province":"Bruxelles-Capitale",
    "wof:name":"Clem-inter",
    "wof:placetype":"venue"
},
  "geometry": {"coordinates":[4.3659901619,50.8771324158],"type":"Point"}
}