{
  "type": "Feature",
  "properties": {
    "addr:full":"Veldstraat 25 Meulebeke West-Vlaanderen 8760",
    "addr:housenumber":"25",
    "addr:postcode":"8760",
    "addr:street":"Veldstraat",
    "iso:country":"BE",
    "sg:address":"Veldstraat 25",
    "sg:city":"Meulebeke",
    "sg:classifiers":[
        {
            "category":"Bars & Pubs",
            "type":"Food & Drink"
        }
    ],
    "sg:phone":"+32 51 48 66 16",
    "sg:postcode":"8760",
    "sg:province":"West-Vlaanderen",
    "wof:name":"Jocabie",
    "wof:placetype":"venue"
},
  "geometry": {"coordinates":[3.2724540234,50.9491004944],"type":"Point"}
}