{
  "type": "Feature",
  "properties": {
    "iso:country":"BE",
    "sg:address":"Steenweg 75",
    "sg:city":"Denderleeuw",
    "sg:classifiers":[
        {
            "category":"Insurance",
            "subcategory":"Life Insurance",
            "type":"Services"
        }
    ],
    "sg:phone":"+32 53 66 63 70",
    "sg:postcode":"9473",
    "sg:province":"Oost-Vlaanderen",
    "sg:tags":[
        "assurance"
    ],
    "wof:name":"Verzekeringen Bert",
    "wof:placetype":"venue"
},
  "geometry": {"coordinates":[4.0557751656,50.9031906128],"type":"Point"}
}