{
  "type": "Feature",
  "properties": {
    "addr:full":"Industriezone Zolder Limburg 3550",
    "addr:postcode":"3550",
    "addr:street":"Industriezone",
    "iso:country":"BE",
    "sg:address":"Industriezone",
    "sg:city":"Zolder",
    "sg:classifiers":[
        {
            "category":"Manufacturing",
            "subcategory":"Metals",
            "type":"Manufacturing & Wholesale Goods"
        }
    ],
    "sg:phone":"+32 13 53 03 70",
    "sg:postcode":"3550",
    "sg:province":"Limburg",
    "sg:tags":[
        "non-ferrous",
        "-"
    ],
    "wof:name":"Umicore Oxyde Belgium Nv",
    "wof:placetype":"venue"
},
  "geometry": {"coordinates":[5.2407388687,50.9928436279],"type":"Point"}
}