{
  "type": "Feature",
  "properties": {
    "iso:country":"BE",
    "sg:address":"Guido Gezellestraat 22",
    "sg:city":"Turnhout",
    "sg:classifiers":[
        {
            "category":"Building & Trades",
            "subcategory":"Pest Control",
            "type":"Services"
        }
    ],
    "sg:phone":"+32 14 42 85 57",
    "sg:postcode":"2300",
    "sg:province":"Antwerpen",
    "sg:tags":[
        "painting",
        "contractor"
    ],
    "wof:name":"Sas R",
    "wof:placetype":"venue"
},
  "geometry": {"coordinates":[4.9278922081,51.3230209351],"type":"Point"}
}