{
  "type": "Feature",
  "properties": {
    "addr:full":"Rue De L'hospice Communal 112 Bruxelles (watermael-boitsfort) Bruxelles-Capitale 1170",
    "addr:housenumber":"112",
    "addr:postcode":"1170",
    "addr:street":"Rue De L'Hospice Communal",
    "iso:country":"BE",
    "sg:address":"Rue De L'hospice Communal 112",
    "sg:city":"Bruxelles (watermael-boitsfort)",
    "sg:classifiers":[
        {
            "category":"Retail",
            "subcategory":"Auto Repair",
            "type":"Services"
        }
    ],
    "sg:phone":"+32 2 672 37 43",
    "sg:postcode":"1170",
    "sg:province":"Bruxelles-Capitale",
    "sg:tags":[
        "garage"
    ],
    "wof:name":"Ameel Garage",
    "wof:placetype":"venue"
},
  "geometry": {"coordinates":[4.4206109047,50.8016586304],"type":"Point"}
}