{
  "type": "Feature",
  "properties": {
    "addr:full":"Kapelstraat 269 Bredene West-Vlaanderen 8450",
    "addr:housenumber":"269",
    "addr:postcode":"8450",
    "addr:street":"Kapelstraat",
    "iso:country":"BE",
    "sg:address":"Kapelstraat 269",
    "sg:city":"Bredene",
    "sg:classifiers":[
        {
            "category":"Bakery",
            "type":"Food & Drink"
        }
    ],
    "sg:phone":"+32 59 32 35 04",
    "sg:postcode":"8450",
    "sg:province":"West-Vlaanderen",
    "sg:tags":[
        "confectioner",
        "baker"
    ],
    "wof:name":"Hypodrome",
    "wof:placetype":"venue"
},
  "geometry": {"coordinates":[2.9846110344,51.2547836304],"type":"Point"}
}