{
  "type": "Feature",
  "properties": {
    "iso:country":"BE",
    "sg:address":"Rue M\u00c9layes 15",
    "sg:city":"Villers-le-bouillet",
    "sg:orig_category":"Services de Nettoyage and de D\u00e9sinfection. Charpentes and couvertures",
    "sg:phone":"+32 85 23 56 17",
    "sg:postcode":"4530",
    "sg:province":"Li\u00e8ge",
    "wof:name":"Pierre Deswert",
    "wof:placetype":"venue"
},
  "geometry": {"coordinates":[5.2793078423,50.5565185547],"type":"Point"}
}