{
  "type": "Feature",
  "properties": {
    "addr:full":"1030 Schaarbeek (brussel) Bruxelles-Capitale 1030",
    "addr:postcode":"1030;1030",
    "iso:country":"BE",
    "sg:address":"1030",
    "sg:city":"Schaarbeek (brussel)",
    "sg:orig_category":"RESTAURANTS: LIVRAISON \u00c0 DOMICILE",
    "sg:phone":"+32 2 732 95 00",
    "sg:postcode":"1030",
    "sg:province":"Bruxelles-Capitale",
    "wof:name":"Domino's Pizza",
    "wof:placetype":"venue"
},
  "geometry": {"coordinates":[4.3852100372,50.8624992371],"type":"Point"}
}