{
  "type": "Feature",
  "properties": {
    "iso:country":"BE",
    "sg:address":"Tieltsesteenweg 30",
    "sg:city":"Eeklo",
    "sg:orig_category":"Meubelzaken, woning- and keukeninrichting",
    "sg:phone":"+32 9 377 56 56",
    "sg:postcode":"9900",
    "sg:province":"Oost-Vlaanderen",
    "wof:name":"Stockman",
    "wof:placetype":"venue"
},
  "geometry": {"coordinates":[3.5560150146,51.1844902039],"type":"Point"}
}