{
  "type": "Feature",
  "properties": {
    "iso:country":"BE",
    "sg:address":"Marktstraat 44",
    "sg:city":"Izegem",
    "sg:classifiers":[
        {
            "category":"Arena",
            "subcategory":"Sports Club",
            "type":"Entertainment"
        }
    ],
    "sg:phone":"+32 51 31 35 78",
    "sg:postcode":"8870",
    "sg:province":"West-Vlaanderen",
    "wof:name":"Iwv",
    "wof:placetype":"venue"
},
  "geometry": {"coordinates":[3.2155930996,50.918964386],"type":"Point"}
}