{
  "type": "Feature",
  "properties": {
    "iso:country":"BE",
    "sg:address":"Marktstraat 20",
    "sg:city":"Genk",
    "sg:orig_category":"Banques and organismes de cr\u00e9dit",
    "sg:phone":"+32 89 36 13 42",
    "sg:postcode":"3600",
    "sg:province":"Limburg",
    "wof:name":"Banca Monte Paschi Belgio",
    "wof:placetype":"venue"
},
  "geometry": {"coordinates":[5.4992980957,50.965423584],"type":"Point"}
}