{
  "type": "Feature",
  "properties": {
    "iso:country":"BE",
    "sg:address":"Rue F. Pelletier 82",
    "sg:city":"Schaarbeek (brussel)",
    "sg:classifiers":[
        {
            "category":"Organizations",
            "subcategory":"Community Association",
            "type":"Services"
        }
    ],
    "sg:phone":"+32 2 732 69 00",
    "sg:postcode":"1030",
    "sg:province":"Bruxelles-Capitale",
    "sg:tags":[
        "organisation"
    ],
    "wof:name":"Face",
    "wof:placetype":"venue"
},
  "geometry": {"coordinates":[4.4019141197,50.8460502625],"type":"Point"}
}