{
  "type": "Feature",
  "properties": {
    "addr:full":"Place Laixheau 35 Herstal Li\u00e8ge 4040",
    "addr:housenumber":"35",
    "addr:postcode":"4040",
    "addr:street":"Place Laixheau",
    "iso:country":"BE",
    "sg:address":"Place Laixheau 35",
    "sg:city":"Herstal",
    "sg:classifiers":[
        {
            "category":"Health Services",
            "subcategory":"Health Practitioner",
            "type":"Services"
        }
    ],
    "sg:phone":"+32 4 248 31 68",
    "sg:postcode":"4040",
    "sg:province":"Li\u00e8ge",
    "sg:tags":[
        "physiotherapist"
    ],
    "wof:name":"Parisse Jo\u00eblle",
    "wof:placetype":"venue"
},
  "geometry": {"coordinates":[5.6259012222,50.6679611206],"type":"Point"}
}