{
  "type": "Feature",
  "properties": {
    "addr:full":"Place Saint-denis 17 Bruxelles (forest) Bruxelles-Capitale 1190",
    "addr:housenumber":"17",
    "addr:postcode":"1190",
    "addr:street":"Place Saint-Denis",
    "iso:country":"BE",
    "sg:address":"Place Saint-denis 17",
    "sg:city":"Bruxelles (forest)",
    "sg:classifiers":[
        {
            "category":"Bars & Pubs",
            "type":"Food & Drink"
        }
    ],
    "sg:phone":"+32 2 376 73 08",
    "sg:postcode":"1190",
    "sg:province":"Bruxelles-Capitale",
    "wof:name":"Embuscade",
    "wof:placetype":"venue"
},
  "geometry": {"coordinates":[4.3191318512,50.8124923706],"type":"Point"}
}