{
  "type": "Feature",
  "properties": {
    "iso:country":"BE",
    "sg:address":"Rue De La Fourchin\u00e9e 20",
    "sg:city":"Momignies (seloignes)",
    "sg:classifiers":[
        {
            "category":"Home & Garden",
            "subcategory":"Home Furnishings",
            "type":"Retail Goods"
        }
    ],
    "sg:phone":"+32 60 51 13 17",
    "sg:postcode":"6596",
    "sg:province":"Hainaut",
    "sg:tags":[
        "-",
        "furniture"
    ],
    "wof:name":"Honor\u00e9 Meubles",
    "wof:placetype":"venue"
},
  "geometry": {"coordinates":[4.2488131523,49.9992027283],"type":"Point"}
}