{
  "type": "Feature",
  "properties": {
    "addr:full":"Rooigemlaan 222 Gent Oost-Vlaanderen 9000",
    "addr:housenumber":"222",
    "addr:postcode":"9000",
    "addr:street":"Rooigemlaan;Oost-Vlaanderen",
    "iso:country":"BE",
    "sg:address":"Rooigemlaan 222",
    "sg:city":"Gent",
    "sg:orig_category":"Banken and kredietinstellingen",
    "sg:phone":"+32 9 226 89 07",
    "sg:postcode":"9000",
    "sg:province":"Oost-Vlaanderen",
    "wof:name":"Landbouwkrediet",
    "wof:placetype":"venue"
},
  "geometry": {"coordinates":[3.6928870678,51.0578079224],"type":"Point"}
}