{
  "type": "Feature",
  "properties": {
    "addr:full":"Slachthuisstraat 68 Turnhout Antwerpen 2300",
    "addr:housenumber":"68",
    "addr:postcode":"2300",
    "addr:street":"Slachthuisstraat",
    "iso:country":"BE",
    "sg:address":"Slachthuisstraat 68",
    "sg:city":"Turnhout",
    "sg:classifiers":[
        {
            "category":"Government",
            "subcategory":"Court House",
            "type":"Public Place"
        }
    ],
    "sg:phone":"+32 14 40 18 11",
    "sg:postcode":"2300",
    "sg:province":"Antwerpen",
    "sg:tags":[
        "administration",
        "central"
    ],
    "wof:name":"Kempens Bedrijvencentrum Turnhout Nv",
    "wof:placetype":"venue"
},
  "geometry": {"coordinates":[4.9238181114,51.3042144775],"type":"Point"}
}