{
  "type": "Feature",
  "properties": {
    "addr:full":"Vaartstraaat 36 Lovendegem Oost-Vlaanderen 9920",
    "addr:housenumber":"36",
    "addr:postcode":"9920",
    "addr:street":"Vaartstraaat",
    "iso:country":"BE",
    "sg:address":"Vaartstraaat 36",
    "sg:city":"Lovendegem",
    "sg:orig_category":"Catering and organisatie van feesten",
    "sg:phone":"+32 9 372 81 33",
    "sg:postcode":"9920",
    "sg:province":"Oost-Vlaanderen",
    "wof:name":"De Baets-van Den Haute",
    "wof:placetype":"venue"
},
  "geometry": {"coordinates":[3.6097290516,51.0944099426],"type":"Point"}
}