{
  "type": "Feature",
  "properties": {
    "iso:country":"BE",
    "sg:address":"Rodenbachstraat 6",
    "sg:city":"Maasmechelen",
    "sg:classifiers":[
        {
            "category":"Shopping",
            "subcategory":"Clothing, Apparel, & Fashions",
            "type":"Retail Goods"
        }
    ],
    "sg:phone":"+32 89 76 13 00",
    "sg:postcode":"3630",
    "sg:province":"Limburg",
    "sg:tags":[
        "underwear",
        "lingerie",
        "-"
    ],
    "wof:name":"Anne-marie Bvba",
    "wof:placetype":"venue"
},
  "geometry": {"coordinates":[5.6966629028,50.9573364258],"type":"Point"}
}