{
  "type": "Feature",
  "properties": {
    "iso:country":"BE",
    "sg:address":"Boskant 32",
    "sg:city":"Kasterlee",
    "sg:orig_category":"Woningbouw",
    "sg:phone":"+32 14 55 34 19",
    "sg:postcode":"2460",
    "sg:province":"Antwerpen",
    "wof:name":"Walter Bosch",
    "wof:placetype":"venue"
},
  "geometry": {"coordinates":[4.9671049118,51.2406616211],"type":"Point"}
}