{
  "type": "Feature",
  "properties": {
    "iso:country":"BE",
    "sg:address":"Waterloose Steenweg 371",
    "sg:city":"Elsene/ixelles",
    "sg:orig_category":"Herenkledingzaken Maatkleding Fab",
    "sg:phone":"+32 2 345 47 60",
    "sg:postcode":"1050",
    "sg:province":"Bruxelles-Capitale",
    "wof:name":"Barnabe",
    "wof:placetype":"venue"
},
  "geometry": {"coordinates":[4.3543658257,50.8223228455],"type":"Point"}
}