{
  "type": "Feature",
  "properties": {
    "iso:country":"BE",
    "sg:address":"Leon De Loofstraat 32",
    "sg:city":"Gent",
    "sg:orig_category":"Artsen and specialisten",
    "sg:phone":"+32 9 231 77 51",
    "sg:postcode":"9050",
    "sg:province":"Oost-Vlaanderen",
    "wof:name":"Rita De Groot",
    "wof:placetype":"venue"
},
  "geometry": {"coordinates":[3.7595329285,51.0398674011],"type":"Point"}
}