{
  "type": "Feature",
  "properties": {
    "iso:country":"BE",
    "sg:address":"Brusselsesteenweg 40",
    "sg:city":"Asse",
    "sg:orig_category":"Immobili\u00ebnkantoren Landmeters and schatters",
    "sg:phone":"+32 2 452 80 80",
    "sg:postcode":"1730",
    "sg:province":"Vlaams-Brabant",
    "wof:name":"Immo Asse",
    "wof:placetype":"venue"
},
  "geometry": {"coordinates":[4.2101421356,50.9046669006],"type":"Point"}
}