{
  "type": "Feature",
  "properties": {
    "iso:country":"BE",
    "sg:address":"Bakelaarstraat 53",
    "sg:city":"Mechelen",
    "sg:orig_category":"Mat\u00e9riel \u00e9lectrique and \u00e9lectronique Magasins sp\u00e9cialis\u00e9s",
    "sg:phone":"+32 15 27 02 58",
    "sg:postcode":"2800",
    "sg:province":"Antwerpen",
    "wof:name":"Holec Componenten",
    "wof:placetype":"venue"
},
  "geometry": {"coordinates":[4.4887318611,51.0317764282],"type":"Point"}
}