{
  "type": "Feature",
  "properties": {
    "addr:full":"Parklaan 55b24 Turnhout Antwerpen 2300",
    "addr:housenumber":"55b24",
    "addr:postcode":"2300",
    "addr:street":"Parklaan",
    "iso:country":"BE",
    "sg:address":"Parklaan 55b24",
    "sg:city":"Turnhout",
    "sg:orig_category":"Banken and kredietinstellingen",
    "sg:phone":"+32 14 44 36 70",
    "sg:postcode":"2300",
    "sg:province":"Antwerpen",
    "wof:name":"Rabobank",
    "wof:placetype":"venue"
},
  "geometry": {"coordinates":[4.949942112,51.3127441406],"type":"Point"}
}