{
  "type": "Feature",
  "properties": {
    "iso:country":"BE",
    "sg:address":"Avenue De La Gare 45",
    "sg:city":"Arlon",
    "sg:classifiers":[
        {
            "category":"Bars & Pubs",
            "type":"Food & Drink"
        }
    ],
    "sg:phone":"+32 63 23 66 87",
    "sg:postcode":"6700",
    "sg:province":"Luxembourg",
    "sg:tags":[
        "tavern"
    ],
    "wof:name":"Courtois (brasserie Le)",
    "wof:placetype":"venue"
},
  "geometry": {"coordinates":[5.8098387718,49.680606842],"type":"Point"}
}