{
  "type": "Feature",
  "properties": {
    "addr:full":"Chauss\u00e9e Bara 596 Waterloo Brabant Wallon 1410",
    "addr:housenumber":"596",
    "addr:postcode":"1410",
    "addr:street":"Chausse\u0301E Bara",
    "iso:country":"BE",
    "sg:address":"Chauss\u00e9e Bara 596",
    "sg:city":"Waterloo",
    "sg:classifiers":[
        {
            "category":"Autos & Motor Vehicles",
            "subcategory":"Automobile Sales",
            "type":"Retail Goods"
        }
    ],
    "sg:phone":"+32 2 351 17 97",
    "sg:postcode":"1410",
    "sg:province":"Brabant Wallon",
    "sg:tags":[
        "car",
        "used",
        "-"
    ],
    "wof:name":"O.d. Car Sprl",
    "wof:placetype":"venue"
},
  "geometry": {"coordinates":[4.4003520012,50.7006187439],"type":"Point"}
}