{
  "type": "Feature",
  "properties": {
    "iso:country":"BE",
    "sg:address":"Droogte 208",
    "sg:city":"Evergem",
    "sg:orig_category":"Enseignement maternel and primaire",
    "sg:phone":"+32 9 357 30 67",
    "sg:postcode":"9940",
    "sg:province":"Oost-Vlaanderen",
    "wof:name":"Gemeentelijke Basisschool",
    "wof:placetype":"venue"
},
  "geometry": {"coordinates":[3.7243490219,51.1303062439],"type":"Point"}
}