{
  "type": "Feature",
  "properties": {
    "addr:full":"Vandendriesschestraat 5a Zottegem (leeuwergem) Oost-Vlaanderen 9620",
    "addr:housenumber":"5a",
    "addr:postcode":"9620",
    "addr:street":"Vandendriesschestraat",
    "iso:country":"BE",
    "sg:address":"Vandendriesschestraat 5a",
    "sg:city":"Zottegem (leeuwergem)",
    "sg:classifiers":[
        {
            "category":"Building & Trades",
            "subcategory":"Equipment Rental",
            "type":"Services"
        }
    ],
    "sg:phone":"+32 475 75 15 76",
    "sg:postcode":"9620",
    "sg:province":"Oost-Vlaanderen",
    "sg:tags":[
        "use",
        "apparatus",
        "tool",
        "-",
        "professional",
        "machines"
    ],
    "wof:name":"Daco Rent",
    "wof:placetype":"venue"
},
  "geometry": {"coordinates":[3.8177850246,50.8790855408],"type":"Point"}
}