{
  "type": "Feature",
  "properties": {
    "addr:full":"Plattesteen 4 Brussel/bruxelles Bruxelles-Capitale 1000",
    "addr:housenumber":"4",
    "addr:postcode":"1000",
    "addr:street":"Plattesteen;/",
    "iso:country":"BE",
    "sg:address":"Plattesteen 4",
    "sg:city":"Brussel/bruxelles",
    "sg:orig_category":"Boucheries",
    "sg:phone":"+32 2 512 06 37",
    "sg:postcode":"1000",
    "sg:province":"Bruxelles-Capitale",
    "wof:name":"Boucherie Rona",
    "wof:placetype":"venue"
},
  "geometry": {"coordinates":[4.3486561775,50.8469390869],"type":"Point"}
}