{
  "type": "Feature",
  "properties": {
    "iso:country":"BE",
    "sg:address":"Rue Jeunesse 15",
    "sg:city":"Farciennes",
    "sg:orig_category":"Caf\u00e9s Sportterreinen and installaties behalve sportcentra",
    "sg:phone":"+32 71 39 73 90",
    "sg:postcode":"6240",
    "sg:province":"Hainaut",
    "wof:name":"Centres Sportifs Farcien.",
    "wof:placetype":"venue"
},
  "geometry": {"coordinates":[4.5426697731,50.431930542],"type":"Point"}
}