{
  "type": "Feature",
  "properties": {
    "iso:country":"BE",
    "sg:address":"Rue Du Chalet 61",
    "sg:city":"La Roche-en-ardenne",
    "sg:classifiers":[
        {
            "category":"Travel",
            "subcategory":"Hotels & Motels",
            "type":"Entertainment"
        }
    ],
    "sg:phone":"+32 84 41 24 13",
    "sg:postcode":"6980",
    "sg:province":"Luxembourg",
    "wof:name":"Chalet (h\u00f4tel Du)",
    "wof:placetype":"venue"
},
  "geometry": {"coordinates":[5.5736479759,50.1831207275],"type":"Point"}
}