{
  "type": "Feature",
  "properties": {
    "iso:country":"BE",
    "sg:address":"Zeedijk-het Zoute 719",
    "sg:city":"Knokke-heist",
    "sg:orig_category":"Baby- and kinderkleding",
    "sg:phone":"+32 50 60 93 74",
    "sg:postcode":"8300",
    "sg:province":"West-Vlaanderen",
    "wof:name":"Rodrigues",
    "wof:placetype":"venue"
},
  "geometry": {"coordinates":[3.287694931,51.3467254639],"type":"Point"}
}