{
  "type": "Feature",
  "properties": {
    "addr:full":"G Gezellestr 75 Denderleeuw Oost-Vlaanderen 9470",
    "addr:housenumber":"75",
    "addr:postcode":"9470",
    "iso:country":"BE",
    "sg:address":"G Gezellestr 75",
    "sg:city":"Denderleeuw",
    "sg:classifiers":[
        {
            "category":"Banks & Credit Unions",
            "subcategory":"Bank",
            "type":"Services"
        }
    ],
    "sg:phone":"+32 53 66 68 60",
    "sg:postcode":"9470",
    "sg:province":"Oost-Vlaanderen",
    "wof:name":"Kredietbank",
    "wof:placetype":"venue"
},
  "geometry": {"coordinates":[4.0786089897,50.886428833],"type":"Point"}
}