{
  "type": "Feature",
  "properties": {
    "iso:country":"BE",
    "sg:address":"Karel Lodewijk Dierickxstraat 33",
    "sg:city":"Gent",
    "sg:classifiers":[
        {
            "category":"Personal",
            "subcategory":"Nail Salon",
            "type":"Services"
        }
    ],
    "sg:phone":"+32 9 223 06 92",
    "sg:postcode":"9000",
    "sg:province":"Oost-Vlaanderen",
    "sg:tags":[
        "pedicure"
    ],
    "wof:name":"An",
    "wof:placetype":"venue"
},
  "geometry": {"coordinates":[3.7054181099,51.0520401001],"type":"Point"}
}