{
  "type": "Feature",
  "properties": {
    "iso:country":"BE",
    "sg:address":"Zwarteberg 58",
    "sg:city":"Heuvelland",
    "sg:orig_category":"RESTAURANTS: MAISONS DE VACANCES. EPICERIES. TERRAINS DE CAMPING",
    "sg:phone":"+32 57 44 45 46",
    "sg:postcode":"8954",
    "sg:province":"West-Vlaanderen",
    "wof:name":"Douve",
    "wof:placetype":"venue"
},
  "geometry": {"coordinates":[2.7461020947,50.7974967957],"type":"Point"}
}