{
  "type": "Feature",
  "properties": {
    "addr:full":"La Cl\u00e9 Des Champs 5 Wezembeek-oppem Vlaams-Brabant 1970",
    "addr:housenumber":"5",
    "addr:postcode":"1970",
    "iso:country":"BE",
    "sg:address":"La Cl\u00e9 Des Champs 5",
    "sg:city":"Wezembeek-oppem",
    "sg:classifiers":[
        {
            "category":"Government",
            "subcategory":"Post Office",
            "type":"Public Place"
        }
    ],
    "sg:phone":"+32 2 731 49 64",
    "sg:postcode":"1970",
    "sg:province":"Vlaams-Brabant",
    "sg:tags":[
        "picture",
        "restoring"
    ],
    "wof:name":"Broumels M",
    "wof:placetype":"venue"
},
  "geometry": {"coordinates":[4.4861087799,50.845085144],"type":"Point"}
}