{
  "type": "Feature",
  "properties": {
    "iso:country":"BE",
    "sg:address":"Belzeelsestraat 25",
    "sg:city":"Evergem",
    "sg:classifiers":[
        {
            "category":"Building & Trades",
            "subcategory":"Construction",
            "type":"Services"
        }
    ],
    "sg:phone":"+32 9 253 05 02",
    "sg:postcode":"9940",
    "sg:province":"Oost-Vlaanderen",
    "sg:tags":[
        "carpenter"
    ],
    "wof:name":"Decri-projekt Bvba",
    "wof:placetype":"venue"
},
  "geometry": {"coordinates":[3.6582920551,51.1003265381],"type":"Point"}
}