{
  "type": "Feature",
  "properties": {
    "addr:full":"Botermarkt 5 Hasselt Limburg 3500",
    "addr:housenumber":"5",
    "addr:postcode":"3500",
    "addr:street":"Botermarkt",
    "iso:country":"BE",
    "sg:address":"Botermarkt 5",
    "sg:city":"Hasselt",
    "sg:classifiers":[
        {
            "category":"Shopping",
            "subcategory":"Clothing, Apparel, & Fashions",
            "type":"Retail Goods"
        }
    ],
    "sg:phone":"+32 11 22 26 80",
    "sg:postcode":"3500",
    "sg:province":"Limburg",
    "sg:tags":[
        "v\u00eatements",
        "pour",
        "dame"
    ],
    "wof:name":"My First Lady",
    "wof:placetype":"venue"
},
  "geometry": {"coordinates":[5.3382978439,50.9304618835],"type":"Point"}
}