{
  "type": "Feature",
  "properties": {
    "iso:country":"BE",
    "sg:address":"Rue Des Brasseurs 30",
    "sg:city":"Chatelet",
    "sg:orig_category":"Dranken",
    "sg:phone":"+32 71 39 39 13",
    "sg:postcode":"6200",
    "sg:province":"Hainaut",
    "wof:name":"Entrepots Du Roy",
    "wof:placetype":"venue"
},
  "geometry": {"coordinates":[4.5193967819,50.4036598206],"type":"Point"}
}