{
  "type": "Feature",
  "properties": {
    "addr:full":"Boulevard Pierre Mayence 19 Charleroi Hainaut 6000",
    "addr:housenumber":"19",
    "addr:postcode":"6000",
    "addr:street":"Boulevard Pierre Mayence;Hainaut",
    "iso:country":"BE",
    "sg:address":"Boulevard Pierre Mayence 19",
    "sg:city":"Charleroi",
    "sg:orig_category":"Avocats and conseillers juridiques",
    "sg:phone":"+32 71 70 03 90",
    "sg:postcode":"6000",
    "sg:province":"Hainaut",
    "wof:name":"Thierry Zuinen",
    "wof:placetype":"venue"
},
  "geometry": {"coordinates":[4.4524869919,50.40858078],"type":"Point"}
}