{
  "type": "Feature",
  "properties": {
    "iso:country":"BE",
    "sg:address":"Vijverstraat 15",
    "sg:city":"Beersel",
    "sg:classifiers":[
        {
            "category":"Cafe",
            "type":"Food & Drink"
        }
    ],
    "sg:phone":"+32 2 377 44 81",
    "sg:postcode":"1650",
    "sg:province":"Vlaams-Brabant",
    "sg:tags":[
        "caf\u00e9s"
    ],
    "wof:name":"Au Gai Pecheur",
    "wof:placetype":"venue"
},
  "geometry": {"coordinates":[4.3077540398,50.762928009],"type":"Point"}
}