{
  "type": "Feature",
  "properties": {
    "iso:country":"BE",
    "sg:address":"Stationsstraat 39",
    "sg:city":"Liedekerke",
    "sg:classifiers":[
        {
            "category":"Personal",
            "subcategory":"Shoe Repair & Shine",
            "type":"Services"
        }
    ],
    "sg:phone":"+32 53 66 77 67",
    "sg:postcode":"1770",
    "sg:province":"Vlaams-Brabant",
    "sg:tags":[
        "shoemaker"
    ],
    "wof:name":"'t Belfort",
    "wof:placetype":"venue"
},
  "geometry": {"coordinates":[4.0845108032,50.8722419739],"type":"Point"}
}