{
  "type": "Feature",
  "properties": {
    "addr:full":"Kiezelweg 78 Herk-de-stad (schulen) Limburg 3540",
    "addr:housenumber":"78",
    "addr:postcode":"3540",
    "addr:street":"Kiezelweg",
    "iso:country":"BE",
    "sg:address":"Kiezelweg 78",
    "sg:city":"Herk-de-stad (schulen)",
    "sg:classifiers":[
        {
            "category":"Tea Room",
            "subcategory":"None",
            "type":"Food & Drink"
        }
    ],
    "sg:phone":"+32 13 55 41 40",
    "sg:postcode":"3540",
    "sg:province":"Limburg",
    "wof:name":"Wendelenhof",
    "wof:placetype":"venue"
},
  "geometry": {"coordinates":[5.1768870354,50.956325531],"type":"Point"}
}