{
  "type": "Feature",
  "properties": {
    "addr:full":"Wallemeers 30b1 Roeselare West-Vlaanderen 8800",
    "addr:housenumber":"30b1",
    "addr:postcode":"8800",
    "addr:street":"Wallemeers",
    "iso:country":"BE",
    "sg:address":"Wallemeers 30b1",
    "sg:city":"Roeselare",
    "sg:orig_category":"Paramedische behandelingen",
    "sg:phone":"+32 51 24 77 43",
    "sg:postcode":"8800",
    "sg:province":"West-Vlaanderen",
    "wof:name":"N. Verlinde",
    "wof:placetype":"venue"
},
  "geometry": {"coordinates":[3.1298840046,50.9364280701],"type":"Point"}
}