{
  "type": "Feature",
  "properties": {
    "iso:country":"BE",
    "sg:address":"Rue Du Midi 169",
    "sg:city":"Bruxelles",
    "sg:classifiers":[
        {
            "category":"Shopping",
            "subcategory":"Computers & Home Electronics",
            "type":"Retail Goods"
        }
    ],
    "sg:phone":"+32 2 502 02 72",
    "sg:postcode":"1000",
    "sg:province":"Bruxelles-Capitale",
    "sg:tags":[
        "sound",
        "equipment",
        "-",
        "system"
    ],
    "wof:name":"A.d.s. Concert",
    "wof:placetype":"venue"
},
  "geometry": {"coordinates":[4.3461809158,50.8432579041],"type":"Point"}
}