{
  "type": "Feature",
  "properties": {
    "iso:country":"BE",
    "sg:address":"Place Des Verriers 14b6",
    "sg:city":"Seraing",
    "sg:orig_category":"V\u00e9t\u00e9rinaires",
    "sg:phone":"+32 4 338 39 38",
    "sg:postcode":"4100",
    "sg:province":"Li\u00e8ge",
    "wof:name":"Dispens.fond.pr.laurent",
    "wof:placetype":"venue"
},
  "geometry": {"coordinates":[5.4936442375,50.5900840759],"type":"Point"}
}