{
  "type": "Feature",
  "properties": {
    "iso:country":"BE",
    "sg:address":"Avenue A.j. Slegers 33",
    "sg:city":"Sint-lambrechts-woluwe/woluwe-saint-lambert",
    "sg:orig_category":"Rev\u00eatements pour sols and murs. Peinture",
    "sg:phone":"+32 2 770 64 07",
    "sg:postcode":"1200",
    "sg:province":"Bruxelles-Capitale",
    "wof:name":"Nadine De Troostembergh",
    "wof:placetype":"venue"
},
  "geometry": {"coordinates":[4.4306488037,50.8410148621],"type":"Point"}
}