{
  "type": "Feature",
  "properties": {
    "iso:country":"BE",
    "sg:address":"Ringlaan 21",
    "sg:city":"De Haan",
    "sg:orig_category":"Administration d'immeubles. Promoteurs immobiliers",
    "sg:phone":"+32 50 41 97 82",
    "sg:postcode":"8420",
    "sg:province":"West-Vlaanderen",
    "wof:name":"Bureau Gumares",
    "wof:placetype":"venue"
},
  "geometry": {"coordinates":[3.0268149376,51.2673454285],"type":"Point"}
}