{
  "type": "Feature",
  "properties": {
    "iso:country":"BE",
    "sg:address":"Veldstraat 4",
    "sg:city":"Assenede",
    "sg:orig_category":"Diensten voor huisdieren",
    "sg:phone":"+32 9 343 07 12",
    "sg:postcode":"9968",
    "sg:province":"Oost-Vlaanderen",
    "wof:name":"Dierenplezier",
    "wof:placetype":"venue"
},
  "geometry": {"coordinates":[3.7233929634,51.2016296387],"type":"Point"}
}