{
  "type": "Feature",
  "properties": {
    "addr:full":"Rue Aux Laines 10 Brussel/bruxelles Bruxelles-Capitale 1000",
    "addr:housenumber":"10",
    "addr:postcode":"1000",
    "addr:street":"Rue Aux Laines;/",
    "iso:country":"BE",
    "sg:address":"Rue Aux Laines 10",
    "sg:city":"Brussel/bruxelles",
    "sg:orig_category":"Avocats and conseillers juridiques",
    "sg:phone":"+32 2 501 61 91",
    "sg:postcode":"1000",
    "sg:province":"Bruxelles-Capitale",
    "wof:name":"A.-m. Predborski",
    "wof:placetype":"venue"
},
  "geometry": {"coordinates":[4.3565897942,50.8386459351],"type":"Point"}
}