{
  "type": "Feature",
  "properties": {
    "addr:full":"Brugsesteenweg 209 Oudenburg (roksem) West-Vlaanderen 8460",
    "addr:housenumber":"209",
    "addr:postcode":"8460",
    "addr:street":"Brugsesteenweg",
    "iso:country":"BE",
    "sg:address":"Brugsesteenweg 209",
    "sg:city":"Oudenburg (roksem)",
    "sg:classifiers":[
        {
            "category":"Autos & Motor Vehicles",
            "subcategory":"Automobile Sales",
            "type":"Retail Goods"
        }
    ],
    "sg:phone":"+32 50 81 24 25",
    "sg:postcode":"8460",
    "sg:province":"West-Vlaanderen",
    "sg:tags":[
        "car",
        "used",
        "-"
    ],
    "wof:name":"Schoutteet G & V Autoviger Nv",
    "wof:placetype":"venue"
},
  "geometry": {"coordinates":[3.0023450851,51.1840553284],"type":"Point"}
}