{
  "type": "Feature",
  "properties": {
    "addr:full":"Assesteenweg 27-29 Ternat Vlaams-Brabant 1740",
    "addr:postcode":"27-29;1740",
    "addr:street":"Assesteenweg",
    "iso:country":"BE",
    "sg:address":"Assesteenweg 27-29",
    "sg:city":"Ternat",
    "sg:orig_category":"Non-Classified Establishments",
    "sg:phone":"+32 2 582 82 50",
    "sg:postcode":"1740",
    "sg:province":"Vlaams-Brabant",
    "wof:name":"Ultraflex Contracture Treatment",
    "wof:placetype":"venue"
},
  "geometry": {"coordinates":[4.1683149338,50.8852424622],"type":"Point"}
}