{
  "type": "Feature",
  "properties": {
    "iso:country":"BE",
    "sg:address":"Rue Des Bl\u00c9s-d'or 15",
    "sg:city":"Messancy",
    "sg:orig_category":"H\u00f4tels",
    "sg:phone":"+32 63 22 52 34",
    "sg:postcode":"6780",
    "sg:province":"Luxembourg",
    "wof:name":"H\u00d4stellerie Les Bl\u00c9s D'or",
    "wof:placetype":"venue"
},
  "geometry": {"coordinates":[5.8763837814,49.5971984863],"type":"Point"}
}