{
  "type": "Feature",
  "properties": {
    "iso:country":"BE",
    "sg:address":"Rue Spinois 43",
    "sg:city":"Charleroi",
    "sg:orig_category":"Kapsalons",
    "sg:phone":"+32 71 31 19 29",
    "sg:postcode":"6061",
    "sg:province":"Hainaut",
    "wof:name":"Coiffure Oger",
    "wof:placetype":"venue"
},
  "geometry": {"coordinates":[4.4572620392,50.4144821167],"type":"Point"}
}