{
  "type": "Feature",
  "properties": {
    "addr:full":"Berkenlaan 47 De Pinte Oost-Vlaanderen 9840",
    "addr:housenumber":"47",
    "addr:postcode":"9840",
    "addr:street":"Berkenlaan",
    "iso:country":"BE",
    "sg:address":"Berkenlaan 47",
    "sg:city":"De Pinte",
    "sg:classifiers":[
        {
            "category":"Health Services",
            "subcategory":"Health Practitioner",
            "type":"Services"
        }
    ],
    "sg:phone":"+32 9 281 26 09",
    "sg:postcode":"9840",
    "sg:province":"Oost-Vlaanderen",
    "sg:tags":[
        "dietitian"
    ],
    "wof:name":"Delbeke I",
    "wof:placetype":"venue"
},
  "geometry": {"coordinates":[3.6408200264,50.9988822937],"type":"Point"}
}