{
  "type": "Feature",
  "properties": {
    "addr:full":"Rue Du Ramponneau 29 Frasnes-lez-anvaing Hainaut 7911",
    "addr:housenumber":"29",
    "addr:postcode":"7911",
    "addr:street":"Rue Du Ramponneau",
    "iso:country":"BE",
    "sg:address":"Rue Du Ramponneau 29",
    "sg:city":"Frasnes-lez-anvaing",
    "sg:orig_category":"M\u00e9decins and sp\u00e9cialistes",
    "sg:phone":"+32 69 86 66 53",
    "sg:postcode":"7911",
    "sg:province":"Hainaut",
    "wof:name":"D. Vandemeulebroecke",
    "wof:placetype":"venue"
},
  "geometry": {"coordinates":[3.6196279526,50.6722640991],"type":"Point"}
}