{
  "type": "Feature",
  "properties": {
    "addr:full":"Hooigaardestraat 1 Vilvoorde Vlaams-Brabant 1800",
    "addr:housenumber":"1",
    "addr:postcode":"1800",
    "addr:street":"Hooigaardestraat",
    "iso:country":"BE",
    "sg:address":"Hooigaardestraat 1",
    "sg:city":"Vilvoorde",
    "sg:classifiers":[
        {
            "category":"Professional",
            "subcategory":"Art Services",
            "type":"Services"
        }
    ],
    "sg:phone":"+32 2 253 20 06",
    "sg:postcode":"1800",
    "sg:province":"Vlaams-Brabant",
    "sg:tags":[
        "interior",
        "designer"
    ],
    "wof:name":"W2 Interieur",
    "wof:placetype":"venue"
},
  "geometry": {"coordinates":[4.460190773,50.9488372803],"type":"Point"}
}