{
  "type": "Feature",
  "properties": {
    "iso:country":"BE",
    "sg:address":"Driesstraat 1",
    "sg:city":"Kortenaken",
    "sg:orig_category":"Epiceries",
    "sg:phone":"+32 16 77 74 53",
    "sg:postcode":"3471",
    "sg:province":"Vlaams-Brabant",
    "wof:name":"M Dewil",
    "wof:placetype":"venue"
},
  "geometry": {"coordinates":[5.0083928108,50.8670005798],"type":"Point"}
}