{
  "type": "Feature",
  "properties": {
    "iso:country":"BE",
    "sg:address":"Rue Monulphe 67",
    "sg:city":"Li\u00c8ge",
    "sg:orig_category":"Artiesten and kunstenaars",
    "sg:phone":"+32 4 222 90 29",
    "sg:postcode":"4000",
    "sg:province":"Li\u00e8ge",
    "wof:name":"Fe. Salazar",
    "wof:placetype":"venue"
},
  "geometry": {"coordinates":[5.5591788292,50.6401443481],"type":"Point"}
}