{
  "type": "Feature",
  "properties": {
    "iso:country":"BE",
    "sg:address":"Hovesesteenweg 94",
    "sg:city":"Boechout",
    "sg:classifiers":[
        {
            "category":"Health Services",
            "subcategory":"Health Practitioner",
            "type":"Services"
        }
    ],
    "sg:phone":"+32 3 454 00 68",
    "sg:postcode":"2530",
    "sg:province":"Antwerpen",
    "sg:tags":[
        "physiotherapist"
    ],
    "wof:name":"De Schrijver E",
    "wof:placetype":"venue"
},
  "geometry": {"coordinates":[4.486120224,51.1573371887],"type":"Point"}
}