{
  "type": "Feature",
  "properties": {
    "addr:full":"Rue De L'eglise 96a Box 5 Bruxelles (woluwe-saint-pierre) Bruxelles-Capitale 1150",
    "addr:housenumber":"96a box 5",
    "addr:postcode":"1150",
    "addr:street":"Rue De L'Eglise",
    "iso:country":"BE",
    "sg:address":"Rue De L'eglise 96a Box 5",
    "sg:city":"Bruxelles (woluwe-saint-pierre)",
    "sg:classifiers":[
        {
            "category":"Shopping",
            "subcategory":"Clothing, Apparel, & Fashions",
            "type":"Retail Goods"
        }
    ],
    "sg:phone":"+32 2 779 16 68",
    "sg:postcode":"1150",
    "sg:province":"Bruxelles-Capitale",
    "sg:tags":[
        "boutique"
    ],
    "wof:name":"Benetton",
    "wof:placetype":"venue"
},
  "geometry": {"coordinates":[4.4639430046,50.8407173157],"type":"Point"}
}