{
  "type": "Feature",
  "properties": {
    "addr:full":"Rue Des Carri\u00c8res 21 Perwez Brabant Wallon 1360",
    "addr:housenumber":"21",
    "addr:postcode":"1360",
    "addr:street":"Rue Des Carrie\u0300Res",
    "iso:country":"BE",
    "sg:address":"Rue Des Carri\u00c8res 21",
    "sg:city":"Perwez",
    "sg:orig_category":"Elektrische installaties voor woningen",
    "sg:phone":"+32 81 65 56 52",
    "sg:postcode":"1360",
    "sg:province":"Brabant Wallon",
    "wof:name":"D-tech",
    "wof:placetype":"venue"
},
  "geometry": {"coordinates":[4.811727047,50.6261520386],"type":"Point"}
}