{
  "type": "Feature",
  "properties": {
    "addr:full":"Rue J. Wauters 24 Anderlues Hainaut 6150",
    "addr:housenumber":"24",
    "addr:postcode":"6150",
    "addr:street":"Rue J. Wauters",
    "iso:country":"BE",
    "sg:address":"Rue J. Wauters 24",
    "sg:city":"Anderlues",
    "sg:orig_category":"HERSTELLING ELEKTRISCHE HUISHOUDAPPARATEN Huishoudapparaten, televisies and radio's Telecommunicatie",
    "sg:phone":"+32 71 52 99 10",
    "sg:postcode":"6150",
    "sg:province":"Hainaut",
    "wof:name":"Van Lierde",
    "wof:placetype":"venue"
},
  "geometry": {"coordinates":[4.2685518265,50.4090156555],"type":"Point"}
}