{
  "type": "Feature",
  "properties": {
    "addr:full":"Dageraadplaats 3 Antwerpen Antwerpen 2018",
    "addr:housenumber":"3",
    "addr:postcode":"2018",
    "addr:street":"Dageraadplaats",
    "iso:country":"BE",
    "sg:address":"Dageraadplaats 3",
    "sg:city":"Antwerpen",
    "sg:classifiers":[
        {
            "category":"Restaurant",
            "type":"Food & Drink"
        }
    ],
    "sg:phone":"+32 3 272 39 21",
    "sg:postcode":"2018",
    "sg:province":"Antwerpen",
    "wof:name":"El Diablo",
    "wof:placetype":"venue"
},
  "geometry": {"coordinates":[4.430683136,51.2068710327],"type":"Point"}
}