{
  "type": "Feature",
  "properties": {
    "addr:full":"Impasse Du Quai 8+ Esneux Li\u00e8ge 4130",
    "addr:housenumber":"8 +",
    "addr:postcode":"4130",
    "addr:street":"Impasse Du Quai",
    "iso:country":"BE",
    "sg:address":"Impasse Du Quai 8+",
    "sg:city":"Esneux",
    "sg:orig_category":"Agences d'exp\u00e9dition",
    "sg:phone":"+32 4 388 24 37",
    "sg:postcode":"4130",
    "sg:province":"Li\u00e8ge",
    "wof:name":"H-b Trade & Consulting",
    "wof:placetype":"venue"
},
  "geometry": {"coordinates":[5.5825710297,50.5692863464],"type":"Point"}
}