{
  "type": "Feature",
  "properties": {
    "addr:full":"Chauss\u00c9e De Charleroi 218 Fleurus Hainaut 6220",
    "addr:housenumber":"218",
    "addr:postcode":"6220",
    "addr:street":"Chausse\u0301E De Charleroi",
    "iso:country":"BE",
    "sg:address":"Chauss\u00c9e De Charleroi 218",
    "sg:city":"Fleurus",
    "sg:classifiers":[
        {
            "category":"Restaurant",
            "type":"Food & Drink"
        }
    ],
    "sg:phone":"+32 71 81 41 61",
    "sg:postcode":"6220",
    "sg:province":"Hainaut",
    "sg:tags":[
        "de",
        "organisation",
        "\u00e0",
        "fast",
        "catering",
        "emporter",
        "f\u00eates",
        "restaurants"
    ],
    "wof:name":"La Bonne Moule",
    "wof:placetype":"venue"
},
  "geometry": {"coordinates":[4.5510621071,50.4818878174],"type":"Point"}
}