{
  "type": "Feature",
  "properties": {
    "iso:country":"BE",
    "sg:address":"Rue Maurice L\u00e9otard 1",
    "sg:city":"Beaumont",
    "sg:classifiers":[
        {
            "category":"Building & Trades",
            "subcategory":"Pest Control",
            "type":"Services"
        }
    ],
    "sg:phone":"+32 71 58 83 55",
    "sg:postcode":"6500",
    "sg:province":"Hainaut",
    "sg:tags":[
        "painting",
        "contractor"
    ],
    "wof:name":"Nova D\u00e9cor",
    "wof:placetype":"venue"
},
  "geometry": {"coordinates":[4.2367777824,50.2367935181],"type":"Point"}
}