{
  "type": "Feature",
  "properties": {
    "addr:full":"Zegbroek 69 Vorselaar Antwerpen 2290",
    "addr:housenumber":"69",
    "addr:postcode":"2290",
    "addr:street":"Zegbroek",
    "iso:country":"BE",
    "sg:address":"Zegbroek 69",
    "sg:city":"Vorselaar",
    "sg:classifiers":[
        {
            "category":"Professional",
            "subcategory":"Management & Consulting",
            "type":"Services"
        }
    ],
    "sg:phone":"+32 495 52 10 71",
    "sg:postcode":"2290",
    "sg:province":"Antwerpen",
    "sg:tags":[
        "consultant",
        "hygiene",
        "industrial",
        "safety"
    ],
    "wof:name":"Badeco",
    "wof:placetype":"venue"
},
  "geometry": {"coordinates":[4.7517418861,51.2266311646],"type":"Point"}
}