{
  "type": "Feature",
  "properties": {
    "addr:full":"Rue De L'egalit\u00c9 424 Soumagne Li\u00e8ge 4630",
    "addr:housenumber":"424",
    "addr:postcode":"4630",
    "addr:street":"Rue De L'Egalite \u0301",
    "iso:country":"BE",
    "sg:address":"Rue De L'egalit\u00c9 424",
    "sg:city":"Soumagne",
    "sg:classifiers":[
        {
            "category":"Personal",
            "subcategory":"Beauty Salon",
            "type":"Services"
        }
    ],
    "sg:phone":"+32 4 377 34 49",
    "sg:postcode":"4630",
    "sg:province":"Li\u00e8ge",
    "sg:tags":[
        "de",
        "coiffure"
    ],
    "wof:name":"Coiffure Jacques",
    "wof:placetype":"venue"
},
  "geometry": {"coordinates":[5.7474951744,50.6149749756],"type":"Point"}
}