{
  "type": "Feature",
  "properties": {
    "addr:full":"Nederstraat 30 Hoeselt Limburg 3730",
    "addr:housenumber":"30",
    "addr:postcode":"3730",
    "addr:street":"Nederstraat",
    "iso:country":"BE",
    "sg:address":"Nederstraat 30",
    "sg:city":"Hoeselt",
    "sg:orig_category":"Enseignement maternel and primaire",
    "sg:phone":"+32 89 41 39 71",
    "sg:postcode":"3730",
    "sg:province":"Limburg",
    "wof:name":"Vrije Basisschool",
    "wof:placetype":"venue"
},
  "geometry": {"coordinates":[5.481967926,50.8704566956],"type":"Point"}
}