{
  "type": "Feature",
  "properties": {
    "addr:full":"Priorijstraat 4 Waarschoot Oost-Vlaanderen 9950",
    "addr:housenumber":"4",
    "addr:postcode":"9950",
    "addr:street":"Priorijstraat",
    "iso:country":"BE",
    "sg:address":"Priorijstraat 4",
    "sg:city":"Waarschoot",
    "sg:classifiers":[
        {
            "category":"Transit Center",
            "subcategory":"Passenger",
            "type":"Transportation"
        }
    ],
    "sg:phone":"+32 9 327 06 15",
    "sg:postcode":"9950",
    "sg:province":"Oost-Vlaanderen",
    "sg:tags":[
        "car",
        "trailer"
    ],
    "wof:name":"Adrie-construct Bvba",
    "wof:placetype":"venue"
},
  "geometry": {"coordinates":[3.6116418839,51.1593170166],"type":"Point"}
}