{
  "type": "Feature",
  "properties": {
    "addr:full":"Digue Des Peupliers 129 Mons Hainaut 7000",
    "addr:housenumber":"129",
    "addr:postcode":"7000",
    "addr:street":"Digue Des Peupliers;Hainaut",
    "iso:country":"BE",
    "sg:address":"Digue Des Peupliers 129",
    "sg:city":"Mons",
    "sg:classifiers":[
        {
            "category":"Social Services",
            "type":"Services"
        }
    ],
    "sg:phone":"+32 800 95 105",
    "sg:postcode":"7000",
    "sg:province":"Hainaut",
    "wof:name":"Age D'or Services (l') Belgique",
    "wof:placetype":"venue"
},
  "geometry": {"coordinates":[3.9476869106,50.4445266724],"type":"Point"}
}