{
  "type": "Feature",
  "properties": {
    "addr:full":"Steenbakkerijstraat 38 Brussel/bruxelles Bruxelles-Capitale 1020",
    "addr:housenumber":"38",
    "addr:postcode":"1020",
    "addr:street":"Steenbakkerijstraat;/",
    "iso:country":"BE",
    "sg:address":"Steenbakkerijstraat 38",
    "sg:city":"Brussel/bruxelles",
    "sg:orig_category":"Dakwerken Loodgieterij, verwarming and sanitaire installaties Plaatsen van vloer- and muurbekleding ",
    "sg:phone":"+32 2 428 11 62",
    "sg:postcode":"1020",
    "sg:province":"Bruxelles-Capitale",
    "wof:name":"Stradiot",
    "wof:placetype":"venue"
},
  "geometry": {"coordinates":[4.3511209488,50.8732528687],"type":"Point"}
}