{
  "type": "Feature",
  "properties": {
    "iso:country":"BE",
    "sg:address":"Vieruitersten 20",
    "sg:city":"Wachtebeke",
    "sg:classifiers":[
        {
            "category":"Arena",
            "subcategory":"Sports Club",
            "type":"Entertainment"
        }
    ],
    "sg:phone":"+32 9 228 10 31",
    "sg:postcode":"9185",
    "sg:province":"Oost-Vlaanderen",
    "wof:name":"Zhong Guo Gent Vzw",
    "wof:placetype":"venue"
},
  "geometry": {"coordinates":[3.8907899857,51.193901062],"type":"Point"}
}