{
  "type": "Feature",
  "properties": {
    "iso:country":"BE",
    "sg:address":"Ooststraat 6",
    "sg:city":"Schaerbeek",
    "sg:orig_category":"Informaticaconsulenten",
    "sg:phone":"+32 475 34 30 89",
    "sg:postcode":"1030",
    "sg:province":"Bruxelles-Capitale",
    "wof:name":"Constructie Renovatie & Netwerk",
    "wof:placetype":"venue"
},
  "geometry": {"coordinates":[4.3734660149,50.8621788025],"type":"Point"}
}