{
  "type": "Feature",
  "properties": {
    "addr:full":"Rue De La Roche 9 Genappe (bousval) Brabant Wallon 1470",
    "addr:housenumber":"9",
    "addr:postcode":"1470",
    "addr:street":"Rue De La Roche;Wallon",
    "iso:country":"BE",
    "sg:address":"Rue De La Roche 9",
    "sg:city":"Genappe (bousval)",
    "sg:classifiers":[
        {
            "category":"Home & Garden",
            "subcategory":"Carpets & Floor Coverings",
            "type":"Retail Goods"
        }
    ],
    "sg:postcode":"1470",
    "sg:province":"Brabant Wallon",
    "sg:tags":[
        "industrial",
        "-"
    ],
    "wof:name":"All-stone Belgium Sprl",
    "wof:placetype":"venue"
},
  "geometry": {"coordinates":[4.5266571045,50.6207542419],"type":"Point"}
}