{
  "type": "Feature",
  "properties": {
    "addr:full":"Rue Du Tilleul 130 Sint-genesius-rode/rhode-saint-genese Vlaams-Brabant 1640",
    "addr:housenumber":"130",
    "addr:postcode":"1640",
    "addr:street":"Rue Du Tilleul",
    "iso:country":"BE",
    "sg:address":"Rue Du Tilleul 130",
    "sg:city":"Sint-genesius-rode/rhode-saint-genese",
    "sg:orig_category":"Agences de publicit\u00e9",
    "sg:phone":"+32 2 381 15 76",
    "sg:postcode":"1640",
    "sg:province":"Vlaams-Brabant",
    "wof:name":"Koan Lettering",
    "wof:placetype":"venue"
},
  "geometry": {"coordinates":[4.3527507782,50.7397117615],"type":"Point"}
}