{
  "type": "Feature",
  "properties": {
    "addr:full":"Hugo Verriestlaan 86 Wevelgem West-Vlaanderen 8560",
    "addr:housenumber":"86",
    "addr:postcode":"8560",
    "addr:street":"Hugo Verriestlaan",
    "iso:country":"BE",
    "sg:address":"Hugo Verriestlaan 86",
    "sg:city":"Wevelgem",
    "sg:orig_category":"Sportclubs",
    "sg:phone":"+32 56 41 89 09",
    "sg:postcode":"8560",
    "sg:province":"West-Vlaanderen",
    "wof:name":"Gullegem Bc Fv",
    "wof:placetype":"venue"
},
  "geometry": {"coordinates":[3.2052309513,50.8372001648],"type":"Point"}
}