{
  "type": "Feature",
  "properties": {
    "addr:full":"Caverstraat 12 Jabbeke West-Vlaanderen 8490",
    "addr:housenumber":"12",
    "addr:postcode":"8490",
    "addr:street":"Caverstraat",
    "iso:country":"BE",
    "sg:address":"Caverstraat 12",
    "sg:city":"Jabbeke",
    "sg:orig_category":"M\u00e9decins and sp\u00e9cialistes",
    "sg:phone":"+32 50 81 11 82",
    "sg:postcode":"8490",
    "sg:province":"West-Vlaanderen",
    "wof:name":"Rogier Knockaert",
    "wof:placetype":"venue"
},
  "geometry": {"coordinates":[3.0921919346,51.1835136414],"type":"Point"}
}