{
  "type": "Feature",
  "properties": {
    "iso:country":"BE",
    "sg:address":"Oude Iepersestraat 115",
    "sg:city":"Izegem",
    "sg:orig_category":"Jardinage. Eleveurs de bovins",
    "sg:phone":"+32 51 30 29 02",
    "sg:postcode":"8870",
    "sg:province":"West-Vlaanderen",
    "wof:name":"Filip Vansteenkiste",
    "wof:placetype":"venue"
},
  "geometry": {"coordinates":[3.1849689484,50.9003601074],"type":"Point"}
}