{
  "type": "Feature",
  "properties": {
    "iso:country":"BE",
    "sg:address":"19",
    "sg:city":"Montenau 4770 Amel",
    "sg:classifiers":[
        {
            "category":"Wholesale",
            "subcategory":"Meat",
            "type":"Manufacturing & Wholesale Goods"
        }
    ],
    "sg:phone":"+32 80 34 95 86",
    "sg:postcode":"19",
    "sg:tags":[
        "food",
        "cooked",
        "product",
        "related"
    ],
    "wof:name":"Montenauer Schinkenraucherei Sprl",
    "wof:placetype":"venue"
},
  "geometry": {"coordinates":[6.1092658043,50.3790054321],"type":"Point"}
}