{
  "type": "Feature",
  "properties": {
    "addr:full":"Rue Des Bruy\u00e8res 576 Wanze (moha) Li\u00e8ge 4520",
    "addr:housenumber":"576",
    "addr:postcode":"4520",
    "addr:street":"Rue Des Bruye\u0300Res",
    "iso:country":"BE",
    "sg:address":"Rue Des Bruy\u00e8res 576",
    "sg:city":"Wanze (moha)",
    "sg:classifiers":[
        {
            "category":"Farming",
            "subcategory":"Fish & Marine Products",
            "type":"Manufacturing & Wholesale Goods"
        }
    ],
    "sg:phone":"+32 85 21 13 42",
    "sg:postcode":"4520",
    "sg:province":"Li\u00e8ge",
    "sg:tags":[
        "photographer",
        "fashion",
        "-"
    ],
    "wof:name":"Heymans J",
    "wof:placetype":"venue"
},
  "geometry": {"coordinates":[5.1936588287,50.5542182922],"type":"Point"}
}