{
  "type": "Feature",
  "properties": {
    "addr:full":"Schoolstraat 12 Jabbeke (varsenare) West-Vlaanderen 8490",
    "addr:housenumber":"12",
    "addr:postcode":"8490",
    "addr:street":"Schoolstraat",
    "iso:country":"BE",
    "sg:address":"Schoolstraat 12",
    "sg:city":"Jabbeke (varsenare)",
    "sg:classifiers":[
        {
            "category":"Banks & Credit Unions",
            "subcategory":"Investment Brokerage",
            "type":"Services"
        }
    ],
    "sg:phone":"+32 50 38 85 44",
    "sg:postcode":"8490",
    "sg:province":"West-Vlaanderen",
    "sg:tags":[
        "repair",
        "-",
        "installation",
        "sanitary",
        "article"
    ],
    "wof:name":"Van Maele Nv",
    "wof:placetype":"venue"
},
  "geometry": {"coordinates":[3.1390109062,51.189453125],"type":"Point"}
}