{
  "type": "Feature",
  "properties": {
    "addr:full":"Liersesteenweg 125 Grobbendonk (groot) Antwerpen 2288",
    "addr:housenumber":"125",
    "addr:postcode":"2288",
    "addr:street":"Liersesteenweg;Groot Antwerpen",
    "iso:country":"BE",
    "sg:address":"Liersesteenweg 125",
    "sg:city":"Grobbendonk (groot)",
    "sg:classifiers":[
        {
            "category":"Bars & Pubs",
            "subcategory":"Nightclub",
            "type":"Food & Drink"
        }
    ],
    "sg:phone":"+32 14 51 17 19",
    "sg:postcode":"2288",
    "sg:province":"Antwerpen",
    "sg:tags":[
        "nachtclubs",
        "dancing"
    ],
    "wof:name":"Carat",
    "wof:placetype":"venue"
},
  "geometry": {"coordinates":[4.7453560829,51.1678504944],"type":"Point"}
}