{
  "type": "Feature",
  "properties": {
    "iso:country":"BE",
    "sg:address":"Jubelfeestlaan 55b1",
    "sg:city":"Sint-jans-molenbeek/molenbeek-saint-jean",
    "sg:orig_category":"Medische apparatuur, orthopedische artikelen and prothesen Fab",
    "sg:phone":"+32 2 420 03 90",
    "sg:postcode":"1080",
    "sg:province":"Bruxelles-Capitale",
    "wof:name":"Labo Verhulst",
    "wof:placetype":"venue"
},
  "geometry": {"coordinates":[4.3380279541,50.8637619019],"type":"Point"}
}