{
  "type": "Feature",
  "properties": {
    "iso:country":"BE",
    "sg:address":"Antwerpsesteenweg 1",
    "sg:city":"Sint-katelijne-waver",
    "sg:classifiers":[
        {
            "category":"Bars & Pubs",
            "type":"Food & Drink"
        }
    ],
    "sg:phone":"+32 15 21 80 16",
    "sg:postcode":"2860",
    "sg:province":"Antwerpen",
    "sg:tags":[
        "tavern"
    ],
    "wof:name":"Pastel (de)",
    "wof:placetype":"venue"
},
  "geometry": {"coordinates":[4.4658098221,51.0509681702],"type":"Point"}
}