{
  "type": "Feature",
  "properties": {
    "iso:country":"BE",
    "sg:address":"Kunstlaan 18",
    "sg:city":"Hasselt",
    "sg:orig_category":"Editeurs de journaux. Editeurs de revues and p\u00e9riodiques",
    "sg:phone":"+32 11 30 01 00",
    "sg:postcode":"3500",
    "sg:province":"Limburg",
    "wof:name":"G.o.m. Limburg",
    "wof:placetype":"venue"
},
  "geometry": {"coordinates":[5.3480558395,50.9268989563],"type":"Point"}
}