{
  "type": "Feature",
  "properties": {
    "addr:full":"Gentstraat 100 Kaprijke (lembeke) Oost-Vlaanderen 9971",
    "addr:housenumber":"100",
    "addr:postcode":"9971",
    "addr:street":"Gentstraat",
    "iso:country":"BE",
    "sg:address":"Gentstraat 100",
    "sg:city":"Kaprijke (lembeke)",
    "sg:classifiers":[
        {
            "category":"Building & Trades",
            "subcategory":"Landscaping Services",
            "type":"Services"
        }
    ],
    "sg:phone":"+32 9 377 66 60",
    "sg:postcode":"9971",
    "sg:province":"Oost-Vlaanderen",
    "sg:tags":[
        "gardening",
        "garden",
        "maintenance"
    ],
    "wof:name":"Van Renterghem L",
    "wof:placetype":"venue"
},
  "geometry": {"coordinates":[3.6439630985,51.1878128052],"type":"Point"}
}