{
  "type": "Feature",
  "properties": {
    "addr:full":"August Wautersstraat 43 Temse Oost-Vlaanderen 9140",
    "addr:housenumber":"43",
    "addr:postcode":"9140",
    "addr:street":"August Wautersstraat",
    "iso:country":"BE",
    "sg:address":"August Wautersstraat 43",
    "sg:city":"Temse",
    "sg:orig_category":"Baby- and kinderkleding Babyspullen",
    "sg:phone":"+32 3 771 12 40",
    "sg:postcode":"9140",
    "sg:province":"Oost-Vlaanderen",
    "wof:name":"Huis Graaftex",
    "wof:placetype":"venue"
},
  "geometry": {"coordinates":[4.2177200317,51.1277694702],"type":"Point"}
}