{
  "type": "Feature",
  "properties": {
    "addr:full":"Golvenstraat 9 Oostende West-Vlaanderen 8400",
    "addr:housenumber":"9",
    "addr:postcode":"8400",
    "addr:street":"Golvenstraat",
    "iso:country":"BE",
    "sg:address":"Golvenstraat 9",
    "sg:city":"Oostende",
    "sg:orig_category":"Sportclubs Sportterreinen and installaties behalve sportcentra",
    "sg:phone":"+32 59 50 26 22",
    "sg:postcode":"8400",
    "sg:province":"West-Vlaanderen",
    "wof:name":"F.c. Stormvogels",
    "wof:placetype":"venue"
},
  "geometry": {"coordinates":[2.8992590904,51.2148208618],"type":"Point"}
}