{
  "type": "Feature",
  "properties": {
    "addr:full":"Leugstraat 60 Aartselaar Antwerpen 2630",
    "addr:housenumber":"60",
    "addr:postcode":"2630",
    "addr:street":"Leugstraat",
    "iso:country":"BE",
    "sg:address":"Leugstraat 60",
    "sg:city":"Aartselaar",
    "sg:classifiers":[
        {
            "category":"Taxi",
            "type":"Transportation"
        }
    ],
    "sg:phone":"+32 3 887 66 66",
    "sg:postcode":"2630",
    "sg:province":"Antwerpen",
    "sg:tags":[
        "taxicab"
    ],
    "wof:name":"Edelweis",
    "wof:placetype":"venue"
},
  "geometry": {"coordinates":[4.3799738884,51.1312026978],"type":"Point"}
}