{
  "type": "Feature",
  "properties": {
    "iso:country":"BE",
    "sg:address":"Bosschelweg 6",
    "sg:city":"Bocholt (kaulille)",
    "sg:classifiers":[
        {
            "category":"Airport",
            "subcategory":"International",
            "type":"Transportation"
        }
    ],
    "sg:phone":"+32 11 62 10 96",
    "sg:postcode":"3950",
    "sg:province":"Limburg",
    "sg:tags":[
        "-",
        "transport"
    ],
    "wof:name":"Travel - Trans Bvba",
    "wof:placetype":"venue"
},
  "geometry": {"coordinates":[5.5151429176,51.1898574829],"type":"Point"}
}