{
  "type": "Feature",
  "properties": {
    "iso:country":"BE",
    "sg:address":"Vossel 5",
    "sg:city":"Haaltert (denderhoutem)",
    "sg:classifiers":[
        {
            "category":"Building & Trades",
            "subcategory":"Landscaping Services",
            "type":"Services"
        }
    ],
    "sg:phone":"+32 54 32 07 44",
    "sg:postcode":"9450",
    "sg:province":"Oost-Vlaanderen",
    "sg:tags":[
        "gardening",
        "garden",
        "maintenance"
    ],
    "wof:name":"Hooge R",
    "wof:placetype":"venue"
},
  "geometry": {"coordinates":[4.0248999596,50.8660507202],"type":"Point"}
}