{
  "type": "Feature",
  "properties": {
    "addr:full":"Gemeenteplein 28 Hoeilaart Vlaams-Brabant 1560",
    "addr:housenumber":"28",
    "addr:postcode":"1560",
    "addr:street":"Gemeenteplein",
    "iso:country":"BE",
    "sg:address":"Gemeenteplein 28",
    "sg:city":"Hoeilaart",
    "sg:orig_category":"Apotheken",
    "sg:phone":"+32 2 657 07 78",
    "sg:postcode":"1560",
    "sg:province":"Vlaams-Brabant",
    "wof:name":"Multipharma",
    "wof:placetype":"venue"
},
  "geometry": {"coordinates":[4.4723181725,50.7686080933],"type":"Point"}
}