{
  "type": "Feature",
  "properties": {
    "iso:country":"BE",
    "sg:address":"Rue Marcel Tonglet 148",
    "sg:city":"Beaumont",
    "sg:orig_category":"Charpentes and couvertures",
    "sg:phone":"+32 71 58 95 30",
    "sg:postcode":"6500",
    "sg:province":"Hainaut",
    "wof:name":"Laurent Buzin",
    "wof:placetype":"venue"
},
  "geometry": {"coordinates":[4.2415251732,50.2330627441],"type":"Point"}
}