{
  "type": "Feature",
  "properties": {
    "addr:full":"Bergstraat 25 Sint-gillis-waas Oost-Vlaanderen 9170",
    "addr:housenumber":"25",
    "addr:postcode":"9170",
    "addr:street":"Bergstraat",
    "iso:country":"BE",
    "sg:address":"Bergstraat 25",
    "sg:city":"Sint-gillis-waas",
    "sg:orig_category":"Apotheken",
    "sg:phone":"+32 3 770 64 26",
    "sg:postcode":"9170",
    "sg:province":"Oost-Vlaanderen",
    "wof:name":"Joannes Dhollander",
    "wof:placetype":"venue"
},
  "geometry": {"coordinates":[4.0839190483,51.249961853],"type":"Point"}
}