{
  "type": "Feature",
  "properties": {
    "addr:full":"Rue De La Gare 33 Manhay (dochamps) Luxembourg 6960",
    "addr:housenumber":"33",
    "addr:postcode":"6960",
    "addr:street":"Rue De La Gare",
    "iso:country":"BE",
    "sg:address":"Rue De La Gare 33",
    "sg:city":"Manhay (dochamps)",
    "sg:classifiers":[
        {
            "category":"Building & Trades",
            "subcategory":"Landscaping Services",
            "type":"Services"
        }
    ],
    "sg:phone":"+32 84 44 42 30",
    "sg:postcode":"6960",
    "sg:province":"Luxembourg",
    "sg:tags":[
        "gardening",
        "garden",
        "maintenance"
    ],
    "wof:name":"Thirion Freres Sprl",
    "wof:placetype":"venue"
},
  "geometry": {"coordinates":[5.62728405,50.2402992249],"type":"Point"}
}