{
  "type": "Feature",
  "properties": {
    "addr:full":"Chauss\u00e9e De Li\u00e8ge 49 Welkenraedt (henri-chapelle) Li\u00e8ge 4841",
    "addr:housenumber":"49",
    "addr:postcode":"4841",
    "addr:street":"Chausse\u0301E De Lie\u0300Ge;Henri-Chapelle",
    "iso:country":"BE",
    "sg:address":"Chauss\u00e9e De Li\u00e8ge 49",
    "sg:city":"Welkenraedt (henri-chapelle)",
    "sg:classifiers":[
        {
            "category":"Real Estate",
            "subcategory":"Surveying",
            "type":"Services"
        }
    ],
    "sg:phone":"+32 87 44 55 00",
    "sg:postcode":"4841",
    "sg:province":"Li\u00e8ge",
    "sg:tags":[
        "lettering",
        "letter"
    ],
    "wof:name":"Fassotte Ch",
    "wof:placetype":"venue"
},
  "geometry": {"coordinates":[5.9176068306,50.674785614],"type":"Point"}
}