{
  "type": "Feature",
  "properties": {
    "iso:country":"BE",
    "sg:address":"Avenue Des Tilleuls 8",
    "sg:city":"Rhode-saint-genese",
    "sg:orig_category":"Diverse bedrijfsbeheeradviesbureaus",
    "sg:phone":"+32 2 358 53 21",
    "sg:postcode":"1640",
    "sg:province":"Vlaams-Brabant",
    "wof:name":"Harrog",
    "wof:placetype":"venue"
},
  "geometry": {"coordinates":[4.3532729149,50.7498817444],"type":"Point"}
}