{
  "type": "Feature",
  "properties": {
    "iso:country":"BE",
    "sg:address":"Rue Fossoul 54",
    "sg:city":"Seraing (boncelles)",
    "sg:classifiers":[
        {
            "category":"Professional",
            "subcategory":"Engineering",
            "type":"Services"
        }
    ],
    "sg:phone":"+32 4 338 13 30",
    "sg:postcode":"4100",
    "sg:province":"Li\u00e8ge",
    "sg:tags":[
        "-"
    ],
    "wof:name":"Adtech Sa",
    "wof:placetype":"venue"
},
  "geometry": {"coordinates":[5.5135030746,50.6105766296],"type":"Point"}
}