{
  "type": "Feature",
  "properties": {
    "iso:country":"BE",
    "sg:address":"Gasstraat 2",
    "sg:city":"Boom",
    "sg:orig_category":"Enseignement maternel and primaire",
    "sg:phone":"+32 3 844 23 86",
    "sg:postcode":"2850",
    "sg:province":"Antwerpen",
    "wof:name":"Vrije Lagere School",
    "wof:placetype":"venue"
},
  "geometry": {"coordinates":[4.3687539101,51.0884971619],"type":"Point"}
}