{
  "type": "Feature",
  "properties": {
    "addr:full":"Fluweelstraat 22 Gent Oost-Vlaanderen 9000",
    "addr:housenumber":"22",
    "addr:postcode":"9000",
    "addr:street":"Fluweelstraat;Oost-Vlaanderen",
    "iso:country":"BE",
    "sg:address":"Fluweelstraat 22",
    "sg:city":"Gent",
    "sg:orig_category":"Enseignement maternel and primaire",
    "sg:phone":"+32 9 226 71 44",
    "sg:postcode":"9000",
    "sg:province":"Oost-Vlaanderen",
    "wof:name":"Vrije Basisschool",
    "wof:placetype":"venue"
},
  "geometry": {"coordinates":[3.6896901131,51.068359375],"type":"Point"}
}