{
  "type": "Feature",
  "properties": {
    "iso:country":"BE",
    "sg:address":"Voie Am\u00e9ricaine 12",
    "sg:city":"Mons (mesvin)",
    "sg:classifiers":[
        {
            "category":"Home & Garden",
            "subcategory":"Building Materials",
            "type":"Retail Goods"
        }
    ],
    "sg:phone":"+32 65 84 18 16",
    "sg:postcode":"7022",
    "sg:province":"Hainaut",
    "sg:tags":[
        "window"
    ],
    "wof:name":"Bondroit F Sprl",
    "wof:placetype":"venue"
},
  "geometry": {"coordinates":[3.9601829052,50.4239997864],"type":"Point"}
}