{
  "type": "Feature",
  "properties": {
    "addr:full":"Szamotulystraat 13 Tielt West-Vlaanderen 8700",
    "addr:housenumber":"13",
    "addr:postcode":"8700",
    "addr:street":"Szamotulystraat",
    "iso:country":"BE",
    "sg:address":"Szamotulystraat 13",
    "sg:city":"Tielt",
    "sg:classifiers":[
        {
            "category":"Building & Trades",
            "subcategory":"Construction",
            "type":"Services"
        }
    ],
    "sg:phone":"+32 51 63 39 40",
    "sg:postcode":"8700",
    "sg:province":"West-Vlaanderen",
    "sg:tags":[
        "installation",
        "-",
        "central",
        "heating"
    ],
    "wof:name":"Van Meerhaeghe Nv",
    "wof:placetype":"venue"
},
  "geometry": {"coordinates":[3.3575909138,50.9969711304],"type":"Point"}
}