{
  "type": "Feature",
  "properties": {
    "addr:full":"Broekborre 174 Halle Vlaams-Brabant 1500",
    "addr:housenumber":"174",
    "addr:postcode":"1500",
    "iso:country":"BE",
    "sg:address":"Broekborre 174",
    "sg:city":"Halle",
    "sg:classifiers":[
        {
            "category":"Parking",
            "subcategory":"Bicycle",
            "type":"Transportation"
        }
    ],
    "sg:phone":"+32 2 356 49 65",
    "sg:postcode":"1500",
    "sg:province":"Vlaams-Brabant",
    "sg:tags":[
        "chiropodist"
    ],
    "wof:name":"Stocke G",
    "wof:placetype":"venue"
},
  "geometry": {"coordinates":[4.2449588776,50.7351531982],"type":"Point"}
}