{
  "type": "Feature",
  "properties": {
    "iso:country":"BE",
    "sg:address":"Rue Bidaut 60",
    "sg:city":"Li\u00c8ge",
    "sg:orig_category":"Paramedische behandelingen",
    "sg:phone":"+32 4 224 05 17",
    "sg:postcode":"4000",
    "sg:province":"Li\u00e8ge",
    "wof:name":"Peeters",
    "wof:placetype":"venue"
},
  "geometry": {"coordinates":[5.5562081337,50.6425018311],"type":"Point"}
}