{
  "type": "Feature",
  "properties": {
    "addr:full":"Hoogstraat 1 Kruishoutem Oost-Vlaanderen 9770",
    "addr:housenumber":"1",
    "addr:postcode":"9770",
    "addr:street":"Hoogstraat",
    "iso:country":"BE",
    "sg:address":"Hoogstraat 1",
    "sg:city":"Kruishoutem",
    "sg:classifiers":[
        {
            "category":"Restaurant",
            "type":"Food & Drink"
        }
    ],
    "sg:phone":"+32 9 383 69 32",
    "sg:postcode":"9770",
    "sg:province":"Oost-Vlaanderen",
    "sg:tags":[
        "caf\u00e9s"
    ],
    "wof:name":"Taverne Kloefke",
    "wof:placetype":"venue"
},
  "geometry": {"coordinates":[3.5284869671,50.9043769836],"type":"Point"}
}