{
  "type": "Feature",
  "properties": {
    "iso:country":"BE",
    "sg:address":"Rue Des Tailles 8",
    "sg:city":"Rochefort",
    "sg:orig_category":"Agences immobili\u00e8res",
    "sg:phone":"+32 83 68 86 65",
    "sg:postcode":"5580",
    "sg:province":"Namur",
    "wof:name":"Wladimir Wastchenko",
    "wof:placetype":"venue"
},
  "geometry": {"coordinates":[5.2231431007,50.1608505249],"type":"Point"}
}