{
  "type": "Feature",
  "properties": {
    "addr:full":"Stationsstraat 113 Liedekerke Vlaams-Brabant 1770",
    "addr:housenumber":"113",
    "addr:postcode":"1770",
    "addr:street":"Stationsstraat;Vlaams-Brabant",
    "iso:country":"BE",
    "sg:address":"Stationsstraat 113",
    "sg:city":"Liedekerke",
    "sg:orig_category":"Artsen and specialisten",
    "sg:phone":"+32 53 68 45 69",
    "sg:postcode":"1770",
    "sg:province":"Vlaams-Brabant",
    "wof:name":"Pascal Scheerlinck",
    "wof:placetype":"venue"
},
  "geometry": {"coordinates":[4.0875630379,50.8739624023],"type":"Point"}
}