{
  "type": "Feature",
  "properties": {
    "iso:country":"BE",
    "sg:address":"Zeemeeuwstraat 6",
    "sg:city":"Ichtegem",
    "sg:orig_category":"Enseignement maternel and primaire",
    "sg:phone":"+32 51 58 10 53",
    "sg:postcode":"8480",
    "sg:province":"West-Vlaanderen",
    "wof:name":"Vrije Basisschool",
    "wof:placetype":"venue"
},
  "geometry": {"coordinates":[3.0367701054,51.1013565063],"type":"Point"}
}