{
  "type": "Feature",
  "properties": {
    "iso:country":"BE",
    "sg:address":"Rue Nestor Falise 15",
    "sg:city":"Courcelles",
    "sg:classifiers":[
        {
            "category":"Insurance",
            "subcategory":"Life Insurance",
            "type":"Services"
        }
    ],
    "sg:phone":"+32 71 45 24 89",
    "sg:postcode":"6180",
    "sg:province":"Hainaut",
    "sg:tags":[
        "assurance"
    ],
    "wof:name":"Assurances Yernaux",
    "wof:placetype":"venue"
},
  "geometry": {"coordinates":[4.3830251694,50.4584655762],"type":"Point"}
}