{
  "type": "Feature",
  "properties": {
    "iso:country":"BE",
    "sg:address":"Rue Du Docteur Des\u00e9n\u00e9part 7",
    "sg:city":"Lessines (ogy)",
    "sg:classifiers":[
        {
            "category":"Personal",
            "subcategory":"Beauty Salon",
            "type":"Services"
        }
    ],
    "sg:phone":"+32 68 44 86 80",
    "sg:postcode":"7862",
    "sg:province":"Hainaut",
    "wof:name":"Caprice",
    "wof:placetype":"venue"
},
  "geometry": {"coordinates":[3.7793281078,50.7204093933],"type":"Point"}
}