{
  "type": "Feature",
  "properties": {
    "addr:full":"Rue Des Martyrs 15 Herve Li\u00e8ge 4650",
    "addr:housenumber":"15",
    "addr:postcode":"4650",
    "addr:street":"Rue Des Martyrs",
    "iso:country":"BE",
    "sg:address":"Rue Des Martyrs 15",
    "sg:city":"Herve",
    "sg:orig_category":"D\u00e9taillants en pi\u00e8ces and accessoires de voitures",
    "sg:phone":"+32 87 67 98 24",
    "sg:postcode":"4650",
    "sg:province":"Li\u00e8ge",
    "wof:name":"Hervi Pneus",
    "wof:placetype":"venue"
},
  "geometry": {"coordinates":[5.7897257805,50.6415100098],"type":"Point"}
}