{
  "type": "Feature",
  "properties": {
    "addr:full":"Lommelsesteenweg 31 Leopoldsburg Limburg 3970",
    "addr:housenumber":"31",
    "addr:postcode":"3970",
    "addr:street":"Lommelsesteenweg",
    "iso:country":"BE",
    "sg:address":"Lommelsesteenweg 31",
    "sg:city":"Leopoldsburg",
    "sg:orig_category":"Geschenken and souvenirs Speelgoed Verlichting and huishoudartikelen",
    "sg:phone":"+32 11 40 18 50",
    "sg:postcode":"3970",
    "sg:province":"Limburg",
    "wof:name":"Blokker",
    "wof:placetype":"venue"
},
  "geometry": {"coordinates":[5.2565197945,51.1264686584],"type":"Point"}
}