{
  "type": "Feature",
  "properties": {
    "addr:full":"Industrielaan 12d Olen Antwerpen 2250",
    "addr:housenumber":"12d",
    "addr:postcode":"2250",
    "addr:street":"Industrielaan",
    "iso:country":"BE",
    "sg:address":"Industrielaan 12d",
    "sg:city":"Olen",
    "sg:classifiers":[
        {
            "category":"Home & Garden",
            "subcategory":"Household Appliances",
            "type":"Retail Goods"
        }
    ],
    "sg:phone":"+32 14 23 08 08",
    "sg:postcode":"2250",
    "sg:province":"Antwerpen",
    "sg:tags":[
        "repair",
        "mainten",
        "-",
        "electric"
    ],
    "wof:name":"Holemans L Bvba",
    "wof:placetype":"venue"
},
  "geometry": {"coordinates":[4.8750019073,51.1504402161],"type":"Point"}
}