{
  "type": "Feature",
  "properties": {
    "iso:country":"BE",
    "sg:address":"Rue Mignot Delstanche 67",
    "sg:city":"Brussel/bruxelles",
    "sg:orig_category":"Artsen and specialisten",
    "sg:phone":"+32 2 344 84 53",
    "sg:postcode":"1050",
    "sg:province":"Bruxelles-Capitale",
    "wof:name":"Harold Du Roy De Blicquy",
    "wof:placetype":"venue"
},
  "geometry": {"coordinates":[4.3573851585,50.8157463074],"type":"Point"}
}