{
  "type": "Feature",
  "properties": {
    "addr:full":"Adolphe Roobaertstraat 4 Ganshoren Bruxelles-Capitale 1083",
    "addr:housenumber":"4",
    "addr:postcode":"1083",
    "addr:street":"Adolphe Roobaertstraat",
    "iso:country":"BE",
    "sg:address":"Adolphe Roobaertstraat 4",
    "sg:city":"Ganshoren",
    "sg:orig_category":"Architecten Woningbouw",
    "sg:phone":"+32 2 465 28 61",
    "sg:postcode":"1083",
    "sg:province":"Bruxelles-Capitale",
    "wof:name":"Francis Ladavid",
    "wof:placetype":"venue"
},
  "geometry": {"coordinates":[4.3026738167,50.8760757446],"type":"Point"}
}