{
  "type": "Feature",
  "properties": {
    "iso:country":"BE",
    "sg:address":"Pannenhuisstraat 30ba",
    "sg:city":"Stekene",
    "sg:orig_category":"Peinture. Rev\u00eatements pour sols and murs",
    "sg:phone":"+32 9 346 64 47",
    "sg:postcode":"9190",
    "sg:province":"Oost-Vlaanderen",
    "wof:name":"Patrick De Clerck",
    "wof:placetype":"venue"
},
  "geometry": {"coordinates":[3.9932169914,51.1873130798],"type":"Point"}
}