{
  "type": "Feature",
  "properties": {
    "iso:country":"BE",
    "sg:address":"Delaeystraat 72",
    "sg:city":"Hooglede",
    "sg:orig_category":"Plaatsen van vloer- and muurbekleding Pleisterwerk",
    "sg:phone":"+32 51 70 28 85",
    "sg:postcode":"8830",
    "sg:province":"West-Vlaanderen",
    "wof:name":"Willemyns Reginald",
    "wof:placetype":"venue"
},
  "geometry": {"coordinates":[3.0350549221,50.9960212708],"type":"Point"}
}