{
  "type": "Feature",
  "properties": {
    "addr:full":"Rue De Virton 34 Meix-devant-virton Luxembourg 6769",
    "addr:housenumber":"34",
    "addr:postcode":"6769",
    "addr:street":"Rue De Virton",
    "iso:country":"BE",
    "sg:address":"Rue De Virton 34",
    "sg:city":"Meix-devant-virton",
    "sg:classifiers":[
        {
            "category":"Personal",
            "subcategory":"Beauty Salon",
            "type":"Services"
        }
    ],
    "sg:phone":"+32 63 57 74 57",
    "sg:postcode":"6769",
    "sg:province":"Luxembourg",
    "sg:tags":[
        "lady",
        "-",
        "hairdressing"
    ],
    "wof:name":"Froidcourt J",
    "wof:placetype":"venue"
},
  "geometry": {"coordinates":[5.4803819656,49.6036109924],"type":"Point"}
}