{
  "type": "Feature",
  "properties": {
    "addr:full":"Avenue Carsoel 12b4 Ukkel/uccle Bruxelles-Capitale 1180",
    "addr:housenumber":"12b4",
    "addr:postcode":"1180",
    "addr:street":"Avenue Carsoel;/",
    "iso:country":"BE",
    "sg:address":"Avenue Carsoel 12b4",
    "sg:city":"Ukkel/uccle",
    "sg:orig_category":"Pi\u00e8ces and accessoires de v\u00e9hicules automobiles Gr",
    "sg:phone":"+32 2 372 03 93",
    "sg:postcode":"1180",
    "sg:province":"Bruxelles-Capitale",
    "wof:name":"European Sales Office",
    "wof:placetype":"venue"
},
  "geometry": {"coordinates":[4.3633651733,50.7941856384],"type":"Point"}
}