{
  "type": "Feature",
  "properties": {
    "addr:full":"Sint-dionisiusstraat 25 Damme (moerkerke) West-Vlaanderen 8340",
    "addr:housenumber":"25",
    "addr:postcode":"8340",
    "addr:street":"Sint-Dionisiusstraat",
    "iso:country":"BE",
    "sg:address":"Sint-dionisiusstraat 25",
    "sg:city":"Damme (moerkerke)",
    "sg:classifiers":[
        {
            "category":"Health Services",
            "subcategory":"Health Practitioner",
            "type":"Services"
        }
    ],
    "sg:phone":"+32 50 50 09 05",
    "sg:postcode":"8340",
    "sg:province":"West-Vlaanderen",
    "sg:tags":[
        "physiotherapist"
    ],
    "wof:name":"Cruysberghs R",
    "wof:placetype":"venue"
},
  "geometry": {"coordinates":[3.3433148861,51.2469100952],"type":"Point"}
}