{
  "type": "Feature",
  "properties": {
    "addr:full":"Rue Capouillet 21 Bruxelles (saint-gilles) Bruxelles-Capitale 1060",
    "addr:housenumber":"21",
    "addr:postcode":"1060",
    "addr:street":"Rue Capouillet",
    "iso:country":"BE",
    "sg:address":"Rue Capouillet 21",
    "sg:city":"Bruxelles (saint-gilles)",
    "sg:classifiers":[
        {
            "category":"Building & Trades",
            "subcategory":"Plumbing",
            "type":"Services"
        }
    ],
    "sg:phone":"+32 2 536 87 23",
    "sg:postcode":"1060",
    "sg:province":"Bruxelles-Capitale",
    "sg:tags":[
        "relocation"
    ],
    "wof:name":"Destination-expatriate Services Sprl",
    "wof:placetype":"venue"
},
  "geometry": {"coordinates":[4.3548111916,50.832572937],"type":"Point"}
}