{
  "type": "Feature",
  "properties": {
    "addr:full":"Gemeentelijk Godshuisstr 47 Watermaal-bosvoorde/watermael-boitsfort Bruxelles-Capitale 1170",
    "addr:housenumber":"47;/",
    "addr:postcode":"1170",
    "addr:street":"Watermaal-Bosvoorde",
    "iso:country":"BE",
    "sg:address":"Gemeentelijk Godshuisstr 47",
    "sg:city":"Watermaal-bosvoorde/watermael-boitsfort",
    "sg:orig_category":"Fietsen Watersport-, Sport- and Kampeerbenodigdheden Verhuur",
    "sg:phone":"+32 2 672 16 98",
    "sg:postcode":"1170",
    "sg:province":"Bruxelles-Capitale",
    "wof:name":"Maison Pipette",
    "wof:placetype":"venue"
},
  "geometry": {"coordinates":[4.419192791,50.8000297546],"type":"Point"}
}