{
  "type": "Feature",
  "properties": {
    "iso:country":"BE",
    "sg:address":"St Martinusstr 20",
    "sg:city":"Velm",
    "sg:classifiers":[
        {
            "category":"Banks & Credit Unions",
            "subcategory":"Bank",
            "type":"Services"
        }
    ],
    "sg:phone":"+32 11 68 73 27",
    "sg:postcode":"3806",
    "sg:province":"Limburg",
    "wof:name":"Gemeentekrediet",
    "wof:placetype":"venue"
},
  "geometry": {"coordinates":[5.1349081993,50.7784805298],"type":"Point"}
}