{
  "type": "Feature",
  "properties": {
    "addr:full":"Groenestraat 301 Menen West-Vlaanderen 8930",
    "addr:housenumber":"301",
    "addr:postcode":"8930",
    "addr:street":"Groenestraat",
    "iso:country":"BE",
    "sg:address":"Groenestraat 301",
    "sg:city":"Menen",
    "sg:orig_category":"Eleveurs de bovins. Eleveurs and marchands de porcs",
    "sg:phone":"+32 56 41 14 05",
    "sg:postcode":"8930",
    "sg:province":"West-Vlaanderen",
    "wof:name":"Jozef Butaye",
    "wof:placetype":"venue"
},
  "geometry": {"coordinates":[3.1489739418,50.8068885803],"type":"Point"}
}