{
  "type": "Feature",
  "properties": {
    "addr:full":"Dambruggestraat 78 Antwerpen Antwerpen 2060",
    "addr:housenumber":"78",
    "addr:postcode":"2060",
    "addr:street":"Dambruggestraat",
    "iso:country":"BE",
    "sg:address":"Dambruggestraat 78",
    "sg:city":"Antwerpen",
    "sg:classifiers":[
        {
            "category":"Health Services",
            "subcategory":"Hospital",
            "type":"Services"
        }
    ],
    "sg:phone":"+32 3 233 99 14",
    "sg:postcode":"2060",
    "sg:province":"Antwerpen",
    "wof:name":"Dagcentrum De Sleutel",
    "wof:placetype":"venue"
},
  "geometry": {"coordinates":[4.4231710434,51.2208747864],"type":"Point"}
}