{
  "type": "Feature",
  "properties": {
    "iso:country":"BE",
    "sg:address":"Rue Edouard Colson 285",
    "sg:city":"Ans",
    "sg:classifiers":[
        {
            "category":"Restaurant",
            "type":"Food & Drink"
        }
    ],
    "sg:phone":"+32 4 247 13 37",
    "sg:postcode":"4431",
    "sg:province":"Li\u00e8ge",
    "wof:name":"Rotisserie Du Gort",
    "wof:placetype":"venue"
},
  "geometry": {"coordinates":[5.494342804,50.6704216003],"type":"Point"}
}