{
  "type": "Feature",
  "properties": {
    "addr:full":"Boulevard Piercot 35 Li\u00c8ge Li\u00e8ge 4000",
    "addr:housenumber":"35",
    "addr:postcode":"4000",
    "addr:street":"Boulevard Piercot",
    "iso:country":"BE",
    "sg:address":"Boulevard Piercot 35",
    "sg:city":"Li\u00c8ge",
    "sg:orig_category":"Banques and organismes de cr\u00e9dit",
    "sg:phone":"+32 4 220 72 11",
    "sg:postcode":"4000",
    "sg:province":"Li\u00e8ge",
    "wof:name":"Cr\u00c9dit G\u00c9n\u00c9ral Sa De Banque",
    "wof:placetype":"venue"
},
  "geometry": {"coordinates":[5.5697488785,50.6352424622],"type":"Point"}
}