{
  "type": "Feature",
  "properties": {
    "addr:full":"Pladijsstraat 237 Deerlijk West-Vlaanderen 8540",
    "addr:housenumber":"237",
    "addr:postcode":"8540",
    "addr:street":"Pladijsstraat",
    "iso:country":"BE",
    "sg:address":"Pladijsstraat 237",
    "sg:city":"Deerlijk",
    "sg:orig_category":"Apotheken",
    "sg:phone":"+32 56 77 80 01",
    "sg:postcode":"8540",
    "sg:province":"West-Vlaanderen",
    "wof:name":"Gabriel Vlieghe",
    "wof:placetype":"venue"
},
  "geometry": {"coordinates":[3.374245882,50.8237037659],"type":"Point"}
}