{
  "type": "Feature",
  "properties": {
    "addr:full":"Rozenlaan 30 Turnhout Antwerpen 2300",
    "addr:housenumber":"30",
    "addr:postcode":"2300",
    "addr:street":"Rozenlaan",
    "iso:country":"BE",
    "sg:address":"Rozenlaan 30",
    "sg:city":"Turnhout",
    "sg:orig_category":"Ordinateurs and \u00e9quipement informatique",
    "sg:phone":"+32 14 43 84 68",
    "sg:postcode":"2300",
    "sg:province":"Antwerpen",
    "wof:name":"Evrard",
    "wof:placetype":"venue"
},
  "geometry": {"coordinates":[4.9453730583,51.3042793274],"type":"Point"}
}