{
  "type": "Feature",
  "properties": {
    "addr:full":"Prinsenkouter 23 Destelbergen (heusden) Oost-Vlaanderen 9070",
    "addr:housenumber":"23",
    "addr:postcode":"9070",
    "addr:street":"Prinsenkouter",
    "iso:country":"BE",
    "sg:address":"Prinsenkouter 23",
    "sg:city":"Destelbergen (heusden)",
    "sg:classifiers":[
        {
            "category":"Building & Trades",
            "subcategory":"Landscaping Services",
            "type":"Services"
        }
    ],
    "sg:phone":"+32 9 232 48 92",
    "sg:postcode":"9070",
    "sg:province":"Oost-Vlaanderen",
    "sg:tags":[
        "gardening",
        "garden",
        "maintenance"
    ],
    "wof:name":"Moeraert Bvba",
    "wof:placetype":"venue"
},
  "geometry": {"coordinates":[3.8145000935,51.0407791138],"type":"Point"}
}