{
  "type": "Feature",
  "properties": {
    "addr:full":"Paul-aler-strasse 2 Sankt Vith/saint-vith Li\u00e8ge 4780",
    "addr:housenumber":"2",
    "addr:postcode":"4780",
    "addr:street":"Paul-Aler-Strasse",
    "iso:country":"BE",
    "sg:address":"Paul-aler-strasse 2",
    "sg:city":"Sankt Vith/saint-vith",
    "sg:classifiers":[
        {
            "category":"Cafe",
            "type":"Food & Drink"
        }
    ],
    "sg:phone":"+32 80 22 64 75",
    "sg:postcode":"4780",
    "sg:province":"Li\u00e8ge",
    "sg:tags":[
        "caf\u00e9s"
    ],
    "wof:name":"B. Kohn",
    "wof:placetype":"venue"
},
  "geometry": {"coordinates":[6.0429549217,50.3349761963],"type":"Point"}
}