{
  "type": "Feature",
  "properties": {
    "addr:full":"Rue Du Gros Ch\u00eane 94 Eghez\u00e9e (liernu) Namur 5310",
    "addr:housenumber":"94",
    "addr:postcode":"5310",
    "addr:street":"Rue Du Gros Che\u0302Ne;Liernu",
    "iso:country":"BE",
    "sg:address":"Rue Du Gros Ch\u00eane 94",
    "sg:city":"Eghez\u00e9e (liernu)",
    "sg:classifiers":[
        {
            "category":"Farming",
            "subcategory":"Livestock Farm",
            "type":"Manufacturing & Wholesale Goods"
        }
    ],
    "sg:phone":"+32 81 65 54 75",
    "sg:postcode":"5310",
    "sg:province":"Namur",
    "sg:tags":[
        "breeding"
    ],
    "wof:name":"Gomand Laurent-laruelle C\u00e9cile",
    "wof:placetype":"venue"
},
  "geometry": {"coordinates":[4.8149528503,50.5798225403],"type":"Point"}
}