{
  "type": "Feature",
  "properties": {
    "iso:country":"BE",
    "sg:address":"Rue Des Combattants 81",
    "sg:city":"La Hulpe",
    "sg:orig_category":"S\u00e9curit\u00e9 sociale",
    "sg:phone":"+32 2 653 13 53",
    "sg:postcode":"1310",
    "sg:province":"Brabant Wallon",
    "wof:name":"Mutualit\u00c9 Socialiste",
    "wof:placetype":"venue"
},
  "geometry": {"coordinates":[4.4880561829,50.7309570312],"type":"Point"}
}