{
  "type": "Feature",
  "properties": {
    "iso:country":"BE",
    "sg:address":"Rue D'aische-en-refail 13",
    "sg:city":"Gembloux",
    "sg:orig_category":"Rundveehouders",
    "sg:phone":"+32 81 64 01 08",
    "sg:postcode":"5031",
    "sg:province":"Namur",
    "wof:name":"Marc Calis",
    "wof:placetype":"venue"
},
  "geometry": {"coordinates":[4.7760939598,50.5842971802],"type":"Point"}
}