{
  "type": "Feature",
  "properties": {
    "iso:country":"BE",
    "sg:address":"Rue des Tanneurs, 60a",
    "sg:city":"Brussels",
    "sg:classifiers":[
        {
            "category":"Professional",
            "subcategory":"Computer Services",
            "type":"Services"
        }
    ],
    "sg:postcode":"1000",
    "sg:tags":[
        "social-networks",
        "networking",
        "web",
        "real-life",
        "web-2-0",
        "online-identities",
        "business-cards",
        "facebook",
        "linkedin",
        "twitter",
        "flickr",
        "myspace",
        "connector",
        "device",
        "community",
        "web-community",
        "usb",
        "rfid",
        "nfc",
        "start-up"
    ],
    "sg:website":"http://www.getyoo.com/",
    "wof:name":"Getyoo",
    "wof:placetype":"venue"
},
  "geometry": {"coordinates":[4.3464721,50.83997],"type":"Point"}
}