{
  "type": "Feature",
  "properties": {
    "iso:country":"BE",
    "sg:address":"Diestsestraat 9",
    "sg:city":"Kortenaken",
    "sg:classifiers":[
        {
            "category":"Bakery",
            "type":"Food & Drink"
        }
    ],
    "sg:phone":"+32 11 58 73 08",
    "sg:postcode":"3470",
    "sg:province":"Vlaams-Brabant",
    "sg:tags":[
        "confectioner",
        "baker"
    ],
    "wof:name":"Lavrijs Nv",
    "wof:placetype":"venue"
},
  "geometry": {"coordinates":[5.0627398491,50.914806366],"type":"Point"}
}