{
  "type": "Feature",
  "properties": {
    "iso:country":"BE",
    "sg:address":"Nerenaard 1",
    "sg:city":"Kontich",
    "sg:classifiers":[
        {
            "category":"Shopping",
            "subcategory":"Crafts & Fabrics",
            "type":"Retail Goods"
        }
    ],
    "sg:phone":"+32 3 457 97 22",
    "sg:postcode":"2550",
    "sg:province":"Antwerpen",
    "sg:tags":[
        "plant",
        "flower",
        "artificial"
    ],
    "wof:name":"V.a. Trading Nv-sa",
    "wof:placetype":"venue"
},
  "geometry": {"coordinates":[4.4381351471,51.1111946106],"type":"Point"}
}