{
  "type": "Feature",
  "properties": {
    "addr:full":"Leopoldsburgsesteenweg 6 Leopoldsburg (heppen) Limburg 3971",
    "addr:housenumber":"6",
    "addr:postcode":"3971",
    "addr:street":"Leopoldsburgsesteenweg",
    "iso:country":"BE",
    "sg:address":"Leopoldsburgsesteenweg 6",
    "sg:city":"Leopoldsburg (heppen)",
    "sg:classifiers":[
        {
            "category":"Shopping",
            "subcategory":"Pets & Pet Supplies",
            "type":"Retail Goods"
        }
    ],
    "sg:phone":"+32 11 34 17 26",
    "sg:postcode":"3971",
    "sg:province":"Limburg",
    "sg:tags":[
        "shop",
        "-"
    ],
    "wof:name":"Pet Food Center",
    "wof:placetype":"venue"
},
  "geometry": {"coordinates":[5.2330880165,51.1095657349],"type":"Point"}
}