{
  "type": "Feature",
  "properties": {
    "iso:country":"BE",
    "sg:address":"Sasstraat 4",
    "sg:city":"Hasselt",
    "sg:classifiers":[
        {
            "category":"Communications",
            "subcategory":"Film & Video Production",
            "type":"Services"
        }
    ],
    "sg:phone":"+32 11 22 31 00",
    "sg:postcode":"3500",
    "sg:province":"Limburg",
    "sg:tags":[
        "workshop",
        "graphic"
    ],
    "wof:name":"Leen Offsetdruk Nv",
    "wof:placetype":"venue"
},
  "geometry": {"coordinates":[5.358440876,50.9379920959],"type":"Point"}
}