{
  "type": "Feature",
  "properties": {
    "iso:country":"BE",
    "sg:address":"Boulevard Lambermont 140",
    "sg:city":"Bruxelles (schaerbeek)",
    "sg:classifiers":[
        {
            "category":"Professional",
            "subcategory":"Computer Services",
            "type":"Services"
        }
    ],
    "sg:phone":"+32 2 241 88 66",
    "sg:postcode":"1030",
    "sg:province":"Bruxelles-Capitale",
    "sg:tags":[
        "rental",
        "processing",
        "-",
        "data"
    ],
    "wof:name":"Actix Belgium Sa",
    "wof:placetype":"venue"
},
  "geometry": {"coordinates":[4.3807039261,50.8721046448],"type":"Point"}
}