{
  "type": "Feature",
  "properties": {
    "addr:full":"Kloosterstraat 50 Antwerpen (ekeren) Antwerpen 2180",
    "addr:housenumber":"50",
    "addr:postcode":"2180",
    "addr:street":"Kloosterstraat",
    "iso:country":"BE",
    "sg:address":"Kloosterstraat 50",
    "sg:city":"Antwerpen (ekeren)",
    "sg:classifiers":[
        {
            "category":"Shopping",
            "subcategory":"Discount & Variety Stores",
            "type":"Retail Goods"
        }
    ],
    "sg:phone":"+32 3 544 73 31",
    "sg:postcode":"2180",
    "sg:province":"Antwerpen",
    "sg:tags":[
        "shop",
        "night"
    ],
    "wof:name":"Sawera",
    "wof:placetype":"venue"
},
  "geometry": {"coordinates":[4.3947491646,51.2159767151],"type":"Point"}
}