{
  "type": "Feature",
  "properties": {
    "addr:full":"Patrijzendreef 6 Keerbergen Vlaams-Brabant 3140",
    "addr:housenumber":"6",
    "addr:postcode":"3140",
    "addr:street":"Patrijzendreef",
    "iso:country":"BE",
    "sg:address":"Patrijzendreef 6",
    "sg:city":"Keerbergen",
    "sg:classifiers":[
        {
            "category":"Health Services",
            "subcategory":"Health Practitioner",
            "type":"Services"
        }
    ],
    "sg:phone":"+32 15 23 50 07",
    "sg:postcode":"3140",
    "sg:province":"Vlaams-Brabant",
    "sg:tags":[
        "physiotherapist"
    ],
    "wof:name":"Vanhamme Y",
    "wof:placetype":"venue"
},
  "geometry": {"coordinates":[4.6531271935,51.0087852478],"type":"Point"}
}