{
  "type": "Feature",
  "properties": {
    "iso:country":"BE",
    "sg:address":"Rue D'ormont 2a",
    "sg:city":"Tournai (kain)",
    "sg:classifiers":[
        {
            "category":"Banks & Credit Unions",
            "subcategory":"Investment Brokerage",
            "type":"Services"
        }
    ],
    "sg:phone":"+32 69 84 04 60",
    "sg:postcode":"7540",
    "sg:province":"Hainaut",
    "sg:tags":[
        "printing",
        "-"
    ],
    "wof:name":"Imprimerie Renders",
    "wof:placetype":"venue"
},
  "geometry": {"coordinates":[3.3720209599,50.6339683533],"type":"Point"}
}