{
  "type": "Feature",
  "properties": {
    "iso:country":"BE",
    "sg:address":"Prins Boudewijnlaan 443",
    "sg:city":"Edegem",
    "sg:classifiers":[
        {
            "category":"Insurance",
            "subcategory":"Insurance Agent",
            "type":"Services"
        }
    ],
    "sg:phone":"+32 3 440 03 41",
    "sg:postcode":"2650",
    "sg:province":"Antwerpen",
    "sg:tags":[
        "verzekeringsmakelaars",
        "expert"
    ],
    "wof:name":"E. Brarens",
    "wof:placetype":"venue"
},
  "geometry": {"coordinates":[4.4263448715,51.1696434021],"type":"Point"}
}