{
  "type": "Feature",
  "properties": {
    "iso:country":"BE",
    "sg:address":"Kerselarenlaan 101",
    "sg:city":"Sint-lambrechts-woluwe/woluwe-saint-lambert",
    "sg:orig_category":"Kapsalons Mobiele kappers Schoonheidssalons",
    "sg:phone":"+32 2 733 70 78",
    "sg:postcode":"1200",
    "sg:province":"Bruxelles-Capitale",
    "wof:name":"Coiffure Mod'r'style",
    "wof:placetype":"venue"
},
  "geometry": {"coordinates":[4.4094572067,50.8474655151],"type":"Point"}
}