{
  "type": "Feature",
  "properties": {
    "addr:full":"Zeeweg 161 Oudenburg West-Vlaanderen 8460",
    "addr:housenumber":"161",
    "addr:postcode":"8460",
    "addr:street":"Zeeweg",
    "iso:country":"BE",
    "sg:address":"Zeeweg 161",
    "sg:city":"Oudenburg",
    "sg:orig_category":"Woningbouw",
    "sg:phone":"+32 59 26 66 62",
    "sg:postcode":"8460",
    "sg:province":"West-Vlaanderen",
    "wof:name":"Renostiel",
    "wof:placetype":"venue"
},
  "geometry": {"coordinates":[3.0301439762,51.1653213501],"type":"Point"}
}