{
  "type": "Feature",
  "properties": {
    "iso:country":"BE",
    "sg:address":"Stationsstraat 56 Box 1",
    "sg:city":"Lanaken",
    "sg:classifiers":[
        {
            "category":"Shopping",
            "subcategory":"Shoes",
            "type":"Retail Goods"
        }
    ],
    "sg:phone":"+32 89 71 14 80",
    "sg:postcode":"3620",
    "sg:province":"Limburg",
    "sg:tags":[
        "slipper",
        "-"
    ],
    "wof:name":"Imagoo",
    "wof:placetype":"venue"
},
  "geometry": {"coordinates":[5.6490321159,50.8879318237],"type":"Point"}
}