{
  "type": "Feature",
  "properties": {
    "addr:full":"Begijnhofstraat 16 Brussel/bruxelles Bruxelles-Capitale 1000",
    "addr:housenumber":"16",
    "addr:postcode":"1000",
    "addr:street":"Begijnhofstraat;/",
    "iso:country":"BE",
    "sg:address":"Begijnhofstraat 16",
    "sg:city":"Brussel/bruxelles",
    "sg:orig_category":"Decoratieve kunst and kunstbenodigdheden",
    "sg:phone":"+32 2 218 27 47",
    "sg:postcode":"1000",
    "sg:province":"Bruxelles-Capitale",
    "wof:name":"Renee Demeester",
    "wof:placetype":"venue"
},
  "geometry": {"coordinates":[4.3492331505,50.8528633118],"type":"Point"}
}