{
  "type": "Feature",
  "properties": {
    "addr:full":"Victor Hugostraat 113 Schaarbeek/schaerbeek Bruxelles-Capitale 1030",
    "addr:housenumber":"113",
    "addr:postcode":"1030",
    "addr:street":"Victor Hugostraat",
    "iso:country":"BE",
    "sg:address":"Victor Hugostraat 113",
    "sg:city":"Schaarbeek/schaerbeek",
    "sg:orig_category":"Artiesten and kunstenaars",
    "sg:phone":"+32 2 735 34 60",
    "sg:postcode":"1030",
    "sg:province":"Bruxelles-Capitale",
    "wof:name":"U. Baccarini",
    "wof:placetype":"venue"
},
  "geometry": {"coordinates":[4.3937578201,50.8506355286],"type":"Point"}
}