{
  "type": "Feature",
  "properties": {
    "iso:country":"BE",
    "sg:address":"Sombekedries 12",
    "sg:city":"Waasmunster",
    "sg:orig_category":"Instituts pour enfants en difficult\u00e9. Orphelinats",
    "sg:phone":"+32 52 46 95 34",
    "sg:postcode":"9250",
    "sg:province":"Oost-Vlaanderen",
    "wof:name":"Home Indigo",
    "wof:placetype":"venue"
},
  "geometry": {"coordinates":[4.1249260902,51.1133155823],"type":"Point"}
}