{
  "type": "Feature",
  "properties": {
    "iso:country":"BE",
    "sg:address":"Rue Du Cimetiere 3",
    "sg:city":"Pont-a-celles",
    "sg:orig_category":"Herstellingen and onderhoud van auto's",
    "sg:phone":"+32 71 84 39 48",
    "sg:postcode":"6230",
    "sg:province":"Hainaut",
    "wof:name":"Yannick Decarnoncle",
    "wof:placetype":"venue"
},
  "geometry": {"coordinates":[4.3636398315,50.5139503479],"type":"Point"}
}