{
  "type": "Feature",
  "properties": {
    "addr:full":"Rue Du Bois 12 Ittre Brabant Wallon 1460",
    "addr:housenumber":"12;1460",
    "addr:street":"Rue Du Bois",
    "iso:country":"BE",
    "sg:address":"Rue Du Bois 12",
    "sg:city":"Ittre",
    "sg:classifiers":[
        {
            "category":"Real Estate",
            "subcategory":"Real Estate Services",
            "type":"Services"
        }
    ],
    "sg:phone":"+32 67 64 77 74",
    "sg:postcode":"1460",
    "sg:province":"Brabant Wallon",
    "wof:name":"Du Green (immobilier)",
    "wof:placetype":"venue"
},
  "geometry": {"coordinates":[4.2396998405,50.6571922302],"type":"Point"}
}