{
  "type": "Feature",
  "properties": {
    "iso:country":"BE",
    "sg:address":"Liroux 10",
    "sg:city":"Dinant",
    "sg:orig_category":"Ordinateurs and \u00e9quipement informatique. Conseils en syst\u00e8mes informatiques. R\u00e9alisation de programm",
    "sg:phone":"+32 83 21 54 59",
    "sg:postcode":"5503",
    "sg:province":"Namur",
    "wof:name":"Michel Arrigoni",
    "wof:placetype":"venue"
},
  "geometry": {"coordinates":[4.9799208641,50.2595214844],"type":"Point"}
}