{
  "type": "Feature",
  "properties": {
    "iso:country":"BE",
    "sg:address":"Chauss\u00c9e De Wavre 826",
    "sg:city":"Etterbeek/etterbeek",
    "sg:orig_category":"Installation \u00e9lectrique r\u00e9sidentielle",
    "sg:phone":"+32 2 646 35 51",
    "sg:postcode":"1040",
    "sg:province":"Bruxelles-Capitale",
    "wof:name":"Electricit\u00c9 Georges",
    "wof:placetype":"venue"
},
  "geometry": {"coordinates":[4.392952919,50.8288841248],"type":"Point"}
}