{
  "type": "Feature",
  "properties": {
    "addr:full":"Voskensstraat 13 Wortegem-petegem Oost-Vlaanderen 9790",
    "addr:housenumber":"13",
    "addr:postcode":"9790",
    "addr:street":"Voskensstraat",
    "iso:country":"BE",
    "sg:address":"Voskensstraat 13",
    "sg:city":"Wortegem-petegem",
    "sg:orig_category":"Rundveehouders",
    "sg:phone":"+32 56 68 97 45",
    "sg:postcode":"9790",
    "sg:province":"Oost-Vlaanderen",
    "wof:name":"Maurice Vercruysse",
    "wof:placetype":"venue"
},
  "geometry": {"coordinates":[3.5241990089,50.8364143372],"type":"Point"}
}