{
  "type": "Feature",
  "properties": {
    "iso:country":"BE",
    "sg:address":"Voskenslaan 38",
    "sg:city":"Gent",
    "sg:classifiers":[
        {
            "category":"Arena",
            "subcategory":"Sports Club",
            "type":"Entertainment"
        }
    ],
    "sg:phone":"+32 9 243 72 72",
    "sg:postcode":"9000",
    "sg:province":"Oost-Vlaanderen",
    "wof:name":"Bloso-inspectiedienst Oost-vlaanderen",
    "wof:placetype":"venue"
},
  "geometry": {"coordinates":[3.7078039646,51.0342788696],"type":"Point"}
}