{
  "type": "Feature",
  "properties": {
    "addr:full":"Rue De L'yser 66 Marche-en-famenne Luxembourg 6900",
    "addr:housenumber":"66",
    "addr:postcode":"6900",
    "addr:street":"Rue De L'Yser",
    "iso:country":"BE",
    "sg:address":"Rue De L'yser 66",
    "sg:city":"Marche-en-famenne",
    "sg:orig_category":"Kapsalons",
    "sg:phone":"+32 84 21 39 38",
    "sg:postcode":"6900",
    "sg:province":"Luxembourg",
    "wof:name":"Coiffure Dany",
    "wof:placetype":"venue"
},
  "geometry": {"coordinates":[5.2783818245,50.1664085388],"type":"Point"}
}