{
  "type": "Feature",
  "properties": {
    "addr:full":"Chauss\u00e9e De Lille 6 Tournai (blandain - Hertain) Hainaut 7522",
    "addr:housenumber":"6",
    "addr:postcode":"7522",
    "addr:street":"Chausse\u0301E De Lille;Hainaut",
    "iso:country":"BE",
    "sg:address":"Chauss\u00e9e De Lille 6",
    "sg:city":"Tournai (blandain - Hertain)",
    "sg:classifiers":[
        {
            "category":"Health Services",
            "subcategory":"Health Practitioner",
            "type":"Services"
        }
    ],
    "sg:phone":"+32 69 84 13 09",
    "sg:postcode":"7522",
    "sg:province":"Hainaut",
    "sg:tags":[
        "physiotherapist"
    ],
    "wof:name":"Warlop A M",
    "wof:placetype":"venue"
},
  "geometry": {"coordinates":[3.3758149147,50.6051445007],"type":"Point"}
}