{
  "type": "Feature",
  "properties": {
    "addr:full":"Rijksweg 457 Dilsen-stokkem Limburg 3650",
    "addr:housenumber":"457",
    "addr:postcode":"dilsen-stokkem;3650",
    "addr:street":"Rijksweg",
    "iso:country":"BE",
    "sg:address":"Rijksweg 457",
    "sg:city":"Dilsen-stokkem",
    "sg:orig_category":"Beautyfarms, relaxatie and lichamelijk welzijn Schoonheidssalons",
    "sg:phone":"+32 89 75 20 52",
    "sg:postcode":"3650",
    "sg:province":"Limburg",
    "wof:name":"Instituut Odore",
    "wof:placetype":"venue"
},
  "geometry": {"coordinates":[5.7296628952,51.0358161926],"type":"Point"}
}