{
  "type": "Feature",
  "properties": {
    "addr:full":"Nederhasseltstraat 169 Ninove Oost-Vlaanderen 9400",
    "addr:housenumber":"169",
    "addr:postcode":"9400",
    "addr:street":"Nederhasseltstraat",
    "iso:country":"BE",
    "sg:address":"Nederhasseltstraat 169",
    "sg:city":"Ninove",
    "sg:orig_category":"Rev\u00eatements de sols and murs. Installation de menuiserie en bois and plastique",
    "sg:phone":"+32 54 33 27 56",
    "sg:postcode":"9400",
    "sg:province":"Oost-Vlaanderen",
    "wof:name":"Eddy De Braeckeleer",
    "wof:placetype":"venue"
},
  "geometry": {"coordinates":[3.9764719009,50.8468704224],"type":"Point"}
}