{
  "type": "Feature",
  "properties": {
    "addr:full":"Rue De La Trairie 27 Vise Li\u00e8ge 4600",
    "addr:housenumber":"27",
    "addr:postcode":"4600",
    "addr:street":"Rue De La Trairie",
    "iso:country":"BE",
    "sg:address":"Rue De La Trairie 27",
    "sg:city":"Vise",
    "sg:orig_category":"Enseignement maternel and primaire",
    "sg:phone":"+32 4 379 06 74",
    "sg:postcode":"4600",
    "sg:province":"Li\u00e8ge",
    "wof:name":"Ecole Fondamentale Libre",
    "wof:placetype":"venue"
},
  "geometry": {"coordinates":[5.6973590851,50.7372398376],"type":"Point"}
}