{
  "type": "Feature",
  "properties": {
    "addr:full":"Rue Ortho 67 La Roche-en-ardenne Luxembourg 6983",
    "addr:housenumber":"67",
    "addr:postcode":"6983",
    "addr:street":"Rue Ortho",
    "iso:country":"BE",
    "sg:address":"Rue Ortho 67",
    "sg:city":"La Roche-en-ardenne",
    "sg:orig_category":"Quincailleries. Bois Gr. Travail and traitement du bois. Charpentes and couvertures",
    "sg:phone":"+32 84 43 31 90",
    "sg:postcode":"6983",
    "sg:province":"Luxembourg",
    "wof:name":"Lapagne Toiture",
    "wof:placetype":"venue"
},
  "geometry": {"coordinates":[5.6178498268,50.1465682983],"type":"Point"}
}