{
  "type": "Feature",
  "properties": {
    "addr:full":"Ten Boschstraat 12b1 Edegem Antwerpen 2650",
    "addr:housenumber":"12b1",
    "addr:postcode":"2650",
    "addr:street":"Ten Boschstraat",
    "iso:country":"BE",
    "sg:address":"Ten Boschstraat 12b1",
    "sg:city":"Edegem",
    "sg:orig_category":"Krantenwinkels Rookartikelen",
    "sg:phone":"+32 3 449 71 62",
    "sg:postcode":"2650",
    "sg:province":"Antwerpen",
    "wof:name":"Christel",
    "wof:placetype":"venue"
},
  "geometry": {"coordinates":[4.4282832146,51.1575050354],"type":"Point"}
}