{
  "type": "Feature",
  "properties": {
    "addr:full":"Melseledijkstraat 2 Beveren Oost-Vlaanderen 9120",
    "addr:housenumber":"2",
    "addr:postcode":"9120",
    "addr:street":"Melseledijkstraat",
    "iso:country":"BE",
    "sg:address":"Melseledijkstraat 2",
    "sg:city":"Beveren",
    "sg:orig_category":"RESTAURANTS: CAF\u00c9S",
    "sg:phone":"+32 3 575 18 63",
    "sg:postcode":"9120",
    "sg:province":"Oost-Vlaanderen",
    "wof:name":"Taverne Scooters",
    "wof:placetype":"venue"
},
  "geometry": {"coordinates":[4.2574100494,51.2131843567],"type":"Point"}
}