{
  "type": "Feature",
  "properties": {
    "addr:full":"Bld Des Gerardchamps 176 Verviers Li\u00e8ge 4800",
    "addr:housenumber":"176",
    "addr:postcode":"4800",
    "addr:street":"Bld Des Gerardchamps",
    "iso:country":"BE",
    "sg:address":"Bld Des Gerardchamps 176",
    "sg:city":"Verviers",
    "sg:classifiers":[
        {
            "category":"Cafe",
            "type":"Food & Drink"
        }
    ],
    "sg:phone":"+32 87 35 46 78",
    "sg:postcode":"4800",
    "sg:province":"Li\u00e8ge",
    "sg:tags":[
        "caf\u00e9s"
    ],
    "wof:name":"Christophe Melchior",
    "wof:placetype":"venue"
},
  "geometry": {"coordinates":[5.849738121,50.5859565735],"type":"Point"}
}