{
  "type": "Feature",
  "properties": {
    "addr:full":"Bekemolen 1 Oudenaarde Oost-Vlaanderen 9700",
    "addr:housenumber":"1",
    "addr:postcode":"9700",
    "addr:street":"Bekemolen",
    "iso:country":"BE",
    "sg:address":"Bekemolen 1",
    "sg:city":"Oudenaarde",
    "sg:orig_category":"Pain, p\u00e2tisseries and confiseries",
    "sg:phone":"+32 9 384 13 42",
    "sg:postcode":"9700",
    "sg:province":"Oost-Vlaanderen",
    "wof:name":"Bakkerij Rombaut",
    "wof:placetype":"venue"
},
  "geometry": {"coordinates":[3.6175429821,50.8989143372],"type":"Point"}
}