{
  "type": "Feature",
  "properties": {
    "addr:full":"J Fr Willemsstraat 2 Boechout Antwerpen 2530",
    "addr:housenumber":"2",
    "addr:postcode":"2530",
    "addr:street":"J Fr Willemsstraat",
    "iso:country":"BE",
    "sg:address":"J Fr Willemsstraat 2",
    "sg:city":"Boechout",
    "sg:classifiers":[
        {
            "category":"Banks & Credit Unions",
            "subcategory":"Bank",
            "type":"Services"
        }
    ],
    "sg:phone":"+32 3 455 73 62",
    "sg:postcode":"2530",
    "sg:province":"Antwerpen",
    "wof:name":"Aslk-cger Bank",
    "wof:placetype":"venue"
},
  "geometry": {"coordinates":[4.4934449196,51.1625976562],"type":"Point"}
}