{
  "type": "Feature",
  "properties": {
    "iso:country":"BE",
    "sg:address":"Avenue Des Gerfauts 8 Box 52",
    "sg:city":"Bruxelles (watermael-boitsfort)",
    "sg:classifiers":[
        {
            "category":"Education",
            "subcategory":"School",
            "type":"Public Place"
        }
    ],
    "sg:phone":"+32 2 673 62 11",
    "sg:postcode":"1170",
    "sg:province":"Bruxelles-Capitale",
    "sg:tags":[
        "-",
        "private"
    ],
    "wof:name":"Atelier Nelly Corman",
    "wof:placetype":"venue"
},
  "geometry": {"coordinates":[4.4172902107,50.8119049072],"type":"Point"}
}