{
  "type": "Feature",
  "properties": {
    "addr:full":"Zeelaan 209 Koksijde West-Vlaanderen 8670",
    "addr:housenumber":"209",
    "addr:postcode":"8670",
    "addr:street":"Zeelaan",
    "iso:country":"BE",
    "sg:address":"Zeelaan 209",
    "sg:city":"Koksijde",
    "sg:orig_category":"Fietsen",
    "sg:phone":"+32 58 51 25 12",
    "sg:postcode":"8670",
    "sg:province":"West-Vlaanderen",
    "wof:name":"Vincent Vanneste",
    "wof:placetype":"venue"
},
  "geometry": {"coordinates":[2.6386229992,51.1155052185],"type":"Point"}
}