{
  "type": "Feature",
  "properties": {
    "addr:full":"Spitaalpoortstraat 29 Gent Oost-Vlaanderen 9000",
    "addr:housenumber":"29",
    "addr:postcode":"9000",
    "addr:street":"Spitaalpoortstraat;Oost-Vlaanderen",
    "iso:country":"BE",
    "sg:address":"Spitaalpoortstraat 29",
    "sg:city":"Gent",
    "sg:orig_category":"Mat\u00e9riel \u00e9lectrique and \u00e9lectronique Electrom\u00e9nager, t\u00e9l\u00e9visions and radios. R\u00e9parations d'appareils",
    "sg:phone":"+32 9 228 32 04",
    "sg:postcode":"9000",
    "sg:province":"Oost-Vlaanderen",
    "wof:name":"Vanderdonck En Goens",
    "wof:placetype":"venue"
},
  "geometry": {"coordinates":[3.7438681126,51.0588569641],"type":"Point"}
}