{
  "type": "Feature",
  "properties": {
    "addr:full":"Eekhoornlaan 3 Wezembeek-oppem Vlaams-Brabant 1970",
    "addr:housenumber":"3",
    "addr:postcode":"1970",
    "addr:street":"Eekhoornlaan",
    "iso:country":"BE",
    "sg:address":"Eekhoornlaan 3",
    "sg:city":"Wezembeek-oppem",
    "sg:orig_category":"Voertuigen",
    "sg:phone":"+32 2 731 11 58",
    "sg:postcode":"1970",
    "sg:province":"Vlaams-Brabant",
    "wof:name":"Auto\u00b4s Olivier",
    "wof:placetype":"venue"
},
  "geometry": {"coordinates":[4.4954051971,50.8358764648],"type":"Point"}
}