{
  "type": "Feature",
  "properties": {
    "addr:full":"Malehoeklaan 13 Brugge West-Vlaanderen 8310",
    "addr:housenumber":"13",
    "addr:postcode":"8310",
    "addr:street":"Malehoeklaan",
    "iso:country":"BE",
    "sg:address":"Malehoeklaan 13",
    "sg:city":"Brugge",
    "sg:orig_category":"M\u00e9decins and sp\u00e9cialistes",
    "sg:phone":"+32 50 35 04 55",
    "sg:postcode":"8310",
    "sg:province":"West-Vlaanderen",
    "wof:name":"Liesbeth Bollen",
    "wof:placetype":"venue"
},
  "geometry": {"coordinates":[3.2796599865,51.2128486633],"type":"Point"}
}