{
  "type": "Feature",
  "properties": {
    "iso:country":"BE",
    "sg:address":"Vosseschijnstraat 19kaai 108-110",
    "sg:city":"Antwerpen",
    "sg:classifiers":[
        {
            "category":"Banks & Credit Unions",
            "subcategory":"Investment Brokerage",
            "type":"Services"
        }
    ],
    "sg:phone":"+32 3 541 94 22",
    "sg:postcode":"2030",
    "sg:province":"Antwerpen",
    "sg:tags":[
        "fork",
        "lift",
        "truck",
        "electric"
    ],
    "wof:name":"Mt-lift Nv",
    "wof:placetype":"venue"
},
  "geometry": {"coordinates":[4.3637099266,51.2742385864],"type":"Point"}
}