{
  "type": "Feature",
  "properties": {
    "addr:full":"Brusselsesteenweg 188a Zemst Vlaams-Brabant 1980",
    "addr:housenumber":"188a",
    "addr:postcode":"1980",
    "addr:street":"Brusselsesteenweg;Vlaams-Brabant",
    "iso:country":"BE",
    "sg:address":"Brusselsesteenweg 188a",
    "sg:city":"Zemst",
    "sg:classifiers":[
        {
            "category":"Utilities",
            "subcategory":"Sewage",
            "type":"Services"
        }
    ],
    "sg:phone":"+32 15 61 32 20",
    "sg:postcode":"1980",
    "sg:province":"Vlaams-Brabant",
    "sg:tags":[
        "sealing",
        "site",
        "contaminated"
    ],
    "wof:name":"De Geest B.v.b.a.",
    "wof:placetype":"venue"
},
  "geometry": {"coordinates":[4.4589152336,50.9791488647],"type":"Point"}
}