{
  "type": "Feature",
  "properties": {
    "iso:country":"BE",
    "sg:address":"Rue Gr\u00c9try 1",
    "sg:city":"Brussel/bruxelles",
    "sg:orig_category":"Action sociale avec h\u00e9bergement",
    "sg:phone":"+32 2 227 02 04",
    "sg:postcode":"1000",
    "sg:province":"Bruxelles-Capitale",
    "wof:name":"C.a.w. Moza\u00cfek",
    "wof:placetype":"venue"
},
  "geometry": {"coordinates":[4.3503389359,50.8498954773],"type":"Point"}
}