{
  "type": "Feature",
  "properties": {
    "iso:country":"BE",
    "sg:address":"Avenue Pierre Dijon 29",
    "sg:city":"Huy",
    "sg:classifiers":[
        {
            "category":"Organizations",
            "subcategory":"Community Association",
            "type":"Services"
        }
    ],
    "sg:phone":"+32 85 23 19 26",
    "sg:postcode":"4500",
    "sg:province":"Li\u00e8ge",
    "sg:tags":[
        "cultural"
    ],
    "wof:name":"Amiti\u00e9 Sams Fronti\u00e8re",
    "wof:placetype":"venue"
},
  "geometry": {"coordinates":[5.2295260429,50.5330696106],"type":"Point"}
}