{
  "type": "Feature",
  "properties": {
    "addr:full":"Chauss\u00e9e De Waterloo 907 Bruxelles (uccle) Bruxelles-Capitale 1180",
    "addr:housenumber":"907",
    "addr:postcode":"1180",
    "addr:street":"Chausse\u0301E De Waterloo",
    "iso:country":"BE",
    "sg:address":"Chauss\u00e9e De Waterloo 907",
    "sg:city":"Bruxelles (uccle)",
    "sg:classifiers":[
        {
            "category":"Wholesale",
            "subcategory":"Scrap",
            "type":"Manufacturing & Wholesale Goods"
        }
    ],
    "sg:phone":"+32 2 374 53 56",
    "sg:postcode":"1180",
    "sg:province":"Bruxelles-Capitale",
    "sg:tags":[
        "metal"
    ],
    "wof:name":"Fabry O",
    "wof:placetype":"venue"
},
  "geometry": {"coordinates":[4.3704409599,50.8080101013],"type":"Point"}
}