{
  "type": "Feature",
  "properties": {
    "addr:full":"Molenstraat 76 Maasmechelen Limburg 3630",
    "addr:housenumber":"76",
    "addr:postcode":"3630",
    "addr:street":"Molenstraat",
    "iso:country":"BE",
    "sg:address":"Molenstraat 76",
    "sg:city":"Maasmechelen",
    "sg:orig_category":"S\u00e9curit\u00e9 sociale. Traitements param\u00e9dicaux",
    "sg:phone":"+32 89 75 77 08",
    "sg:postcode":"3630",
    "sg:province":"Limburg",
    "wof:name":"De Voorzorg",
    "wof:placetype":"venue"
},
  "geometry": {"coordinates":[5.7366828918,51.0003356934],"type":"Point"}
}