{
  "type": "Feature",
  "properties": {
    "iso:country":"BE",
    "sg:address":"Grand Chemin 94",
    "sg:city":"Tournai",
    "sg:orig_category":"Rundveehouders",
    "sg:phone":"+32 69 54 65 41",
    "sg:postcode":"7531",
    "sg:province":"Hainaut",
    "wof:name":"Louis Dubuisson",
    "wof:placetype":"venue"
},
  "geometry": {"coordinates":[3.4088859558,50.5986404419],"type":"Point"}
}