{
  "type": "Feature",
  "properties": {
    "iso:country":"BE",
    "sg:address":"Sint-claradreef 77",
    "sg:city":"Brugge",
    "sg:classifiers":[
        {
            "category":"Community Center",
            "type":"Public Place"
        }
    ],
    "sg:phone":"+32 50 44 33 44",
    "sg:postcode":"8000",
    "sg:province":"West-Vlaanderen",
    "sg:tags":[
        "medical"
    ],
    "wof:name":"Cosmipolis",
    "wof:placetype":"venue"
},
  "geometry": {"coordinates":[3.2218770981,51.2187461853],"type":"Point"}
}