{
  "type": "Feature",
  "properties": {
    "iso:country":"BE",
    "sg:address":"Roodkruisstraat 3",
    "sg:city":"Hamme",
    "sg:orig_category":"Mat\u00e9riaux de construction Gr",
    "sg:phone":"+32 52 47 82 54",
    "sg:postcode":"9220",
    "sg:province":"Oost-Vlaanderen",
    "wof:name":"Willy Van Den Broeck",
    "wof:placetype":"venue"
},
  "geometry": {"coordinates":[4.1388678551,51.1000328064],"type":"Point"}
}