{
  "type": "Feature",
  "properties": {
    "addr:full":"Ourthe 22 Gouvy Luxembourg 6672",
    "addr:housenumber":"22",
    "addr:postcode":"6672",
    "addr:street":"Ourthe",
    "iso:country":"BE",
    "sg:address":"Ourthe 22",
    "sg:city":"Gouvy",
    "sg:orig_category":"Rundveehouders",
    "sg:phone":"+32 80 51 72 38",
    "sg:postcode":"6672",
    "sg:province":"Luxembourg",
    "wof:name":"Moutschen Lucien & Benoit",
    "wof:placetype":"venue"
},
  "geometry": {"coordinates":[5.9981989861,50.2213783264],"type":"Point"}
}