{
  "type": "Feature",
  "properties": {
    "iso:country":"BE",
    "sg:address":"Ezelstraat 16",
    "sg:city":"Brugge",
    "sg:orig_category":"Salles de billard and snooker. Caf\u00e9s",
    "sg:phone":"+32 50 34 04 16",
    "sg:postcode":"8000",
    "sg:province":"West-Vlaanderen",
    "wof:name":"Snookercenter Ceulemans",
    "wof:placetype":"venue"
},
  "geometry": {"coordinates":[3.2201030254,51.2119102478],"type":"Point"}
}