{
  "type": "Feature",
  "properties": {
    "addr:full":"Koning Leopoldlaan 1 Westerlo Antwerpen 2260",
    "addr:housenumber":"1",
    "addr:postcode":"2260",
    "addr:street":"Koning Leopoldlaan",
    "iso:country":"BE",
    "sg:address":"Koning Leopoldlaan 1",
    "sg:city":"Westerlo",
    "sg:classifiers":[
        {
            "category":"Insurance",
            "subcategory":"Insurance Agent",
            "type":"Services"
        }
    ],
    "sg:phone":"+32 14 54 48 07",
    "sg:postcode":"2260",
    "sg:province":"Antwerpen",
    "sg:tags":[
        "broker"
    ],
    "wof:name":"Thijs Group",
    "wof:placetype":"venue"
},
  "geometry": {"coordinates":[4.9108181,51.0856132507],"type":"Point"}
}