{
  "type": "Feature",
  "properties": {
    "iso:country":"BE",
    "sg:address":"Meulebeeksestraat 23",
    "sg:city":"Ardooie",
    "sg:orig_category":"Woningbouw",
    "sg:phone":"+32 51 74 57 68",
    "sg:postcode":"8850",
    "sg:province":"West-Vlaanderen",
    "wof:name":"Coudenys Woningbouw",
    "wof:placetype":"venue"
},
  "geometry": {"coordinates":[3.2403669357,50.9659156799],"type":"Point"}
}