{
  "type": "Feature",
  "properties": {
    "addr:full":"Nieuwstraat 8ba Stekene Oost-Vlaanderen 9190",
    "addr:housenumber":"8ba",
    "addr:postcode":"9190",
    "addr:street":"Nieuwstraat",
    "iso:country":"BE",
    "sg:address":"Nieuwstraat 8ba",
    "sg:city":"Stekene",
    "sg:orig_category":"Schoenen",
    "sg:phone":"+32 3 779 74 68",
    "sg:postcode":"9190",
    "sg:province":"Oost-Vlaanderen",
    "wof:name":"Rene Van Camp",
    "wof:placetype":"venue"
},
  "geometry": {"coordinates":[4.0076532364,51.1883430481],"type":"Point"}
}