{
  "type": "Feature",
  "properties": {
    "addr:full":"Jan Bollenstraat 35 Brussel/bruxelles Bruxelles-Capitale 1020",
    "addr:housenumber":"35",
    "addr:postcode":"1020",
    "addr:street":"Jan Bollenstraat;/",
    "iso:country":"BE",
    "sg:address":"Jan Bollenstraat 35",
    "sg:city":"Brussel/bruxelles",
    "sg:classifiers":[
        {
            "category":"Restaurant",
            "type":"Food & Drink"
        }
    ],
    "sg:phone":"+32 2 426 08 37",
    "sg:postcode":"1020",
    "sg:province":"Bruxelles-Capitale",
    "sg:tags":[
        "caf\u00e9s"
    ],
    "wof:name":"Classic's Taverne",
    "wof:placetype":"venue"
},
  "geometry": {"coordinates":[4.3604860306,50.8963508606],"type":"Point"}
}