{
  "type": "Feature",
  "properties": {
    "iso:country":"BE",
    "sg:address":"Maarschalk Haiglaan 13",
    "sg:city":"Ieper",
    "sg:classifiers":[
        {
            "category":"Restaurant",
            "type":"Food & Drink"
        }
    ],
    "sg:phone":"+32 57 20 63 50",
    "sg:postcode":"8900",
    "sg:province":"West-Vlaanderen",
    "wof:name":"De Koperen Haan",
    "wof:placetype":"venue"
},
  "geometry": {"coordinates":[2.8757948875,50.8517303467],"type":"Point"}
}