{
  "type": "Feature",
  "properties": {
    "iso:country":"BE",
    "sg:address":"Collegestraat 4",
    "sg:city":"Heist-op-den-berg",
    "sg:classifiers":[
        {
            "category":"Personal",
            "subcategory":"Beauty Salon",
            "type":"Services"
        }
    ],
    "sg:phone":"+32 15 24 29 94",
    "sg:postcode":"2220",
    "sg:province":"Antwerpen",
    "sg:tags":[
        "de",
        "coiffure"
    ],
    "wof:name":"Coiffure Linda",
    "wof:placetype":"venue"
},
  "geometry": {"coordinates":[4.7014231682,51.0717697144],"type":"Point"}
}