{
  "type": "Feature",
  "properties": {
    "iso:country":"BE",
    "sg:address":"Hille 129",
    "sg:city":"Wingene",
    "sg:orig_category":"Slagers",
    "sg:phone":"+32 51 61 13 14",
    "sg:postcode":"8750",
    "sg:province":"West-Vlaanderen",
    "wof:name":"Jacques Defour",
    "wof:placetype":"venue"
},
  "geometry": {"coordinates":[3.2255010605,51.0462112427],"type":"Point"}
}