{
  "type": "Feature",
  "properties": {
    "addr:full":"Chauss\u00c9e De Renaix 4 Tournai Hainaut 7500",
    "addr:housenumber":"4",
    "addr:postcode":"7500",
    "addr:street":"Chausse\u0301E De Renaix",
    "iso:country":"BE",
    "sg:address":"Chauss\u00c9e De Renaix 4",
    "sg:city":"Tournai",
    "sg:orig_category":"Bloemen and planten",
    "sg:phone":"+32 69 22 20 31",
    "sg:postcode":"7500",
    "sg:province":"Hainaut",
    "wof:name":"A La Fleur De Nice",
    "wof:placetype":"venue"
},
  "geometry": {"coordinates":[3.4030070305,50.6125602722],"type":"Point"}
}