{
  "type": "Feature",
  "properties": {
    "iso:country":"BE",
    "sg:address":"Rue De Heuseux 36",
    "sg:city":"Blegny",
    "sg:orig_category":"M\u00e9decins and sp\u00e9cialistes",
    "sg:phone":"+32 4 387 62 48",
    "sg:postcode":"4671",
    "sg:province":"Li\u00e8ge",
    "wof:name":"Nicole Mulot",
    "wof:placetype":"venue"
},
  "geometry": {"coordinates":[5.7003488541,50.6654853821],"type":"Point"}
}