{
  "type": "Feature",
  "properties": {
    "iso:country":"BE",
    "sg:address":"Brechtsebaan 2a",
    "sg:city":"Schoten",
    "sg:classifiers":[
        {
            "category":"Retail",
            "subcategory":"Auto Repair",
            "type":"Services"
        }
    ],
    "sg:phone":"+32 3 658 26 22",
    "sg:postcode":"2900",
    "sg:province":"Antwerpen",
    "sg:tags":[
        "garage"
    ],
    "wof:name":"De Valk Garage Bvba",
    "wof:placetype":"venue"
},
  "geometry": {"coordinates":[4.5100498199,51.2647094727],"type":"Point"}
}