{
  "type": "Feature",
  "properties": {
    "addr:full":"Antwerpseweg 51a Geel Antwerpen 2440",
    "addr:housenumber":"51a",
    "addr:postcode":"2440",
    "addr:street":"Antwerpseweg",
    "iso:country":"BE",
    "sg:address":"Antwerpseweg 51a",
    "sg:city":"Geel",
    "sg:classifiers":[
        {
            "category":"Cafe",
            "type":"Food & Drink"
        }
    ],
    "sg:phone":"+32 14 59 03 40",
    "sg:postcode":"2440",
    "sg:province":"Antwerpen",
    "sg:tags":[
        "snack-bars"
    ],
    "wof:name":"Vlinderke ('t)",
    "wof:placetype":"venue"
},
  "geometry": {"coordinates":[4.9658279419,51.1495666504],"type":"Point"}
}