{
  "type": "Feature",
  "properties": {
    "addr:full":"Patijntjestraat 56 Gent Oost-Vlaanderen 9000",
    "addr:housenumber":"56",
    "addr:postcode":"9000",
    "addr:street":"Patijntjestraat;Oost-Vlaanderen",
    "iso:country":"BE",
    "sg:address":"Patijntjestraat 56",
    "sg:city":"Gent",
    "sg:orig_category":"Artsen and specialisten",
    "sg:phone":"+32 9 222 82 13",
    "sg:postcode":"9000",
    "sg:province":"Oost-Vlaanderen",
    "wof:name":"Marguerite Jonckheere",
    "wof:placetype":"venue"
},
  "geometry": {"coordinates":[3.7084550858,51.040222168],"type":"Point"}
}