{
  "type": "Feature",
  "properties": {
    "iso:country":"BE",
    "sg:address":"Gentsesteenweg 535",
    "sg:city":"Sint-jans-molenbeek/molenbeek-saint-jean",
    "sg:orig_category":"Openbare veiligheid",
    "sg:phone":"+32 2 482 09 00",
    "sg:postcode":"1080",
    "sg:province":"Bruxelles-Capitale",
    "wof:name":"Police F\u00c9d\u00c9rale",
    "wof:placetype":"venue"
},
  "geometry": {"coordinates":[4.3055300713,50.860660553],"type":"Point"}
}