{
  "type": "Feature",
  "properties": {
    "addr:full":"Stationstraat 9 Olen Antwerpen 2250",
    "addr:housenumber":"9",
    "addr:postcode":"2250",
    "addr:street":"Stationstraat",
    "iso:country":"BE",
    "sg:address":"Stationstraat 9",
    "sg:city":"Olen",
    "sg:orig_category":"V\u00eatements",
    "sg:phone":"+32 14 22 55 22",
    "sg:postcode":"2250",
    "sg:province":"Antwerpen",
    "wof:name":"Step-in",
    "wof:placetype":"venue"
},
  "geometry": {"coordinates":[4.9020609856,51.1682128906],"type":"Point"}
}