{
  "type": "Feature",
  "properties": {
    "iso:country":"BE",
    "sg:address":"Hille 82",
    "sg:city":"Wingene (zwevezele)",
    "sg:classifiers":[
        {
            "category":"Building & Trades",
            "subcategory":"Construction",
            "type":"Services"
        }
    ],
    "sg:phone":"+32 51 61 17 47",
    "sg:postcode":"8750",
    "sg:province":"West-Vlaanderen",
    "sg:tags":[
        "carpenter"
    ],
    "wof:name":"Vantornout W",
    "wof:placetype":"venue"
},
  "geometry": {"coordinates":[3.2261719704,51.0490608215],"type":"Point"}
}