{
  "type": "Feature",
  "properties": {
    "iso:country":"BE",
    "sg:address":"Otterstraat 134",
    "sg:city":"Turnhout",
    "sg:classifiers":[
        {
            "category":"Ice Cream",
            "type":"Food & Drink"
        }
    ],
    "sg:phone":"+32 14 41 21 80",
    "sg:postcode":"2300",
    "sg:province":"Antwerpen",
    "wof:name":"De Fijnproever",
    "wof:placetype":"venue"
},
  "geometry": {"coordinates":[4.9560041428,51.3214302063],"type":"Point"}
}