{
  "type": "Feature",
  "properties": {
    "iso:country":"BE",
    "sg:address":"Varendonksebaan 22b1",
    "sg:city":"Laakdal",
    "sg:orig_category":"Rundveehouders",
    "sg:phone":"+32 14 54 90 11",
    "sg:postcode":"2431",
    "sg:province":"Antwerpen",
    "wof:name":"Guido Vos",
    "wof:placetype":"venue"
},
  "geometry": {"coordinates":[4.9367442131,51.0664367676],"type":"Point"}
}