{
  "type": "Feature",
  "properties": {
    "addr:full":"Rue Temploux 48 Jemeppe-sur-sambre Namur 5190",
    "addr:housenumber":"48",
    "addr:postcode":"5190",
    "addr:street":"Rue Temploux",
    "iso:country":"BE",
    "sg:address":"Rue Temploux 48",
    "sg:city":"Jemeppe-sur-sambre",
    "sg:orig_category":"Boekhouders",
    "sg:phone":"+32 71 78 41 83",
    "sg:postcode":"5190",
    "sg:province":"Namur",
    "wof:name":"Davister Roger",
    "wof:placetype":"venue"
},
  "geometry": {"coordinates":[4.7182831764,50.4817695618],"type":"Point"}
}