{
  "type": "Feature",
  "properties": {
    "addr:full":"Rue De La Station 3 Sambreville Namur 5060",
    "addr:housenumber":"3",
    "addr:postcode":"5060",
    "addr:street":"Rue De La Station",
    "iso:country":"BE",
    "sg:address":"Rue De La Station 3",
    "sg:city":"Sambreville",
    "sg:orig_category":"Dameskledingzaken",
    "sg:phone":"+32 71 77 42 04",
    "sg:postcode":"5060",
    "sg:province":"Namur",
    "wof:name":"Quonc West",
    "wof:placetype":"venue"
},
  "geometry": {"coordinates":[4.6110620499,50.4323310852],"type":"Point"}
}