{
  "type": "Feature",
  "properties": {
    "addr:full":"Burgemeester Gillonlaan 43 Kortrijk West-Vlaanderen 8500",
    "addr:housenumber":"43",
    "addr:postcode":"8500",
    "addr:street":"Burgemeester Gillonlaan",
    "iso:country":"BE",
    "sg:address":"Burgemeester Gillonlaan 43",
    "sg:city":"Kortrijk",
    "sg:orig_category":"M\u00e9decins and sp\u00e9cialistes",
    "sg:phone":"+32 56 21 75 14",
    "sg:postcode":"8500",
    "sg:province":"West-Vlaanderen",
    "wof:name":"Luc Deleye",
    "wof:placetype":"venue"
},
  "geometry": {"coordinates":[3.2788670063,50.8197364807],"type":"Point"}
}