{
  "type": "Feature",
  "properties": {
    "iso:country":"BE",
    "sg:address":"Rue Chant Des Oiseaux 3",
    "sg:city":"Welkenraedt/welkenraedt",
    "sg:orig_category":"Rev\u00eatements pour sols and murs",
    "sg:phone":"+32 87 88 10 74",
    "sg:postcode":"4840",
    "sg:province":"Li\u00e8ge",
    "wof:name":"Angelo Mirolo",
    "wof:placetype":"venue"
},
  "geometry": {"coordinates":[5.9796700478,50.6616210938],"type":"Point"}
}