{
  "type": "Feature",
  "properties": {
    "iso:country":"BE",
    "sg:address":"Avenue Des Combattants 188",
    "sg:city":"Genappe (bousval)",
    "sg:classifiers":[
        {
            "category":"Shopping",
            "subcategory":"Stationery & Office Supplies",
            "type":"Retail Goods"
        }
    ],
    "sg:phone":"+32 10 61 20 86",
    "sg:postcode":"1470",
    "sg:province":"Brabant Wallon",
    "sg:tags":[
        "partition"
    ],
    "wof:name":"Cmdh",
    "wof:placetype":"venue"
},
  "geometry": {"coordinates":[4.5384349823,50.6342277527],"type":"Point"}
}