{
  "type": "Feature",
  "properties": {
    "addr:full":"Brusselsesteenweg 521 Asse Vlaams-Brabant 1731",
    "addr:housenumber":"521",
    "addr:postcode":"1731",
    "addr:street":"Brusselsesteenweg",
    "iso:country":"BE",
    "sg:address":"Brusselsesteenweg 521",
    "sg:city":"Asse",
    "sg:orig_category":"Banken and kredietinstellingen",
    "sg:phone":"+32 2 466 28 28",
    "sg:postcode":"1731",
    "sg:province":"Vlaams-Brabant",
    "wof:name":"Fortis",
    "wof:placetype":"venue"
},
  "geometry": {"coordinates":[4.2750291824,50.884147644],"type":"Point"}
}