{
  "type": "Feature",
  "properties": {
    "iso:country":"BE",
    "sg:address":"Rue Tour De La Vierge 36",
    "sg:city":"Chievres",
    "sg:orig_category":"Eleveurs de bovins",
    "sg:phone":"+32 68 65 77 66",
    "sg:postcode":"7951",
    "sg:province":"Hainaut",
    "wof:name":"Elie Dubois",
    "wof:placetype":"venue"
},
  "geometry": {"coordinates":[3.7741200924,50.5834884644],"type":"Point"}
}