{
  "type": "Feature",
  "properties": {
    "addr:full":"Zonnestraat 25 Aalst Oost-Vlaanderen 9300",
    "addr:housenumber":"25",
    "addr:postcode":"9300",
    "addr:street":"Zonnestraat",
    "iso:country":"BE",
    "sg:address":"Zonnestraat 25",
    "sg:city":"Aalst",
    "sg:orig_category":"Maatschappelijke dienstverlening",
    "sg:phone":"+32 53 78 37 35",
    "sg:postcode":"9300",
    "sg:province":"Oost-Vlaanderen",
    "wof:name":"Vclb-centrum",
    "wof:placetype":"venue"
},
  "geometry": {"coordinates":[4.0397119522,50.9345321655],"type":"Point"}
}