{
  "type": "Feature",
  "properties": {
    "addr:full":"Ieperstraat 1b Wevelgem (moorsele) West-Vlaanderen 8560",
    "addr:housenumber":"1b",
    "addr:postcode":"8560",
    "addr:street":"Ieperstraat",
    "iso:country":"BE",
    "sg:address":"Ieperstraat 1b",
    "sg:city":"Wevelgem (moorsele)",
    "sg:classifiers":[
        {
            "category":"Personal",
            "subcategory":"Beauty Salon",
            "type":"Services"
        }
    ],
    "sg:phone":"+32 56 42 55 46",
    "sg:postcode":"8560",
    "sg:province":"West-Vlaanderen",
    "sg:tags":[
        "lady",
        "-",
        "hairdressing"
    ],
    "wof:name":"Casier G",
    "wof:placetype":"venue"
},
  "geometry": {"coordinates":[3.1063759327,50.8374290466],"type":"Point"}
}