{
  "type": "Feature",
  "properties": {
    "addr:full":"Hemelstraat 90 Dendermonde Oost-Vlaanderen 9200",
    "addr:housenumber":"90",
    "addr:postcode":"9200",
    "addr:street":"Hemelstraat;Oost-Vlaanderen",
    "iso:country":"BE",
    "sg:address":"Hemelstraat 90",
    "sg:city":"Dendermonde",
    "sg:classifiers":[
        {
            "category":"Professional",
            "subcategory":"Management & Consulting",
            "type":"Services"
        }
    ],
    "sg:phone":"+32 52 21 62 28",
    "sg:postcode":"9200",
    "sg:province":"Oost-Vlaanderen",
    "sg:tags":[
        "-",
        "processing",
        "data",
        "consultant"
    ],
    "wof:name":"Sia, Voor Een Verhelderende Kijk Op Operationeel Onderzoek, Statistiek En Informatica",
    "wof:placetype":"venue"
},
  "geometry": {"coordinates":[4.1036148071,51.0210418701],"type":"Point"}
}