{
  "type": "Feature",
  "properties": {
    "addr:full":"Bissegemplaats 4 Kortrijk West-Vlaanderen 8501",
    "addr:housenumber":"4",
    "addr:postcode":"8501",
    "addr:street":"Bissegemplaats",
    "iso:country":"BE",
    "sg:address":"Bissegemplaats 4",
    "sg:city":"Kortrijk",
    "sg:orig_category":"Blanchisseries and teintureries",
    "sg:phone":"+32 56 35 17 30",
    "sg:postcode":"8501",
    "sg:province":"West-Vlaanderen",
    "wof:name":"Lutgarde Desmet",
    "wof:placetype":"venue"
},
  "geometry": {"coordinates":[3.2268109322,50.8235015869],"type":"Point"}
}