{
  "type": "Feature",
  "properties": {
    "addr:full":"Avenue De La Couture 21 Thuin Hainaut 6530",
    "addr:housenumber":"21",
    "addr:postcode":"6530",
    "addr:street":"Avenue De La Couture",
    "iso:country":"BE",
    "sg:address":"Avenue De La Couture 21",
    "sg:city":"Thuin",
    "sg:orig_category":"Diverse zakelijke dienstverlening",
    "sg:phone":"+32 71 59 06 50",
    "sg:postcode":"6530",
    "sg:province":"Hainaut",
    "wof:name":"Bmc",
    "wof:placetype":"venue"
},
  "geometry": {"coordinates":[4.2796859741,50.3443870544],"type":"Point"}
}