{
  "type": "Feature",
  "properties": {
    "iso:country":"BE",
    "sg:address":"Anselmostraat 1",
    "sg:city":"Antwerpen",
    "sg:classifiers":[
        {
            "category":"Shopping",
            "subcategory":"Clothing, Apparel, & Fashions",
            "type":"Retail Goods"
        }
    ],
    "sg:phone":"+32 3 237 34 37",
    "sg:postcode":"2018",
    "sg:province":"Antwerpen",
    "sg:tags":[
        "underwear",
        "lingerie",
        "-"
    ],
    "wof:name":"Orfalis",
    "wof:placetype":"venue"
},
  "geometry": {"coordinates":[4.4034171104,51.2079086304],"type":"Point"}
}