{
  "type": "Feature",
  "properties": {
    "iso:country":"BE",
    "sg:address":"Fuggerstr 12",
    "sg:city":"Antwerpen",
    "sg:classifiers":[
        {
            "category":"Banks & Credit Unions",
            "subcategory":"Financial Services",
            "type":"Services"
        }
    ],
    "sg:phone":"+32 3 231 94 38",
    "sg:postcode":"2060",
    "sg:province":"Antwerpen",
    "sg:tags":[
        "banking",
        "insurance",
        "institution",
        "finance"
    ],
    "wof:name":"Granhold Nv",
    "wof:placetype":"venue"
},
  "geometry": {"coordinates":[4.4184908867,51.2293510437],"type":"Point"}
}