{
  "type": "Feature",
  "properties": {
    "iso:country":"BE",
    "sg:address":"Eugene Ysayestraat 65",
    "sg:city":"Halle",
    "sg:classifiers":[
        {
            "category":"Insurance",
            "subcategory":"Life Insurance",
            "type":"Services"
        }
    ],
    "sg:phone":"+32 2 356 19 39",
    "sg:postcode":"1500",
    "sg:province":"Vlaams-Brabant",
    "sg:tags":[
        "assurance"
    ],
    "wof:name":"J.a. Surkeyn",
    "wof:placetype":"venue"
},
  "geometry": {"coordinates":[4.2541928291,50.7270240784],"type":"Point"}
}