{
  "type": "Feature",
  "properties": {
    "addr:full":"Kattestraat 22 Aalst Oost-Vlaanderen 9300",
    "addr:housenumber":"22",
    "addr:postcode":"9300",
    "addr:street":"Kattestraat",
    "iso:country":"BE",
    "sg:address":"Kattestraat 22",
    "sg:city":"Aalst",
    "sg:classifiers":[
        {
            "category":"Shopping",
            "subcategory":"Clothing, Apparel, & Fashions",
            "type":"Retail Goods"
        }
    ],
    "sg:phone":"+32 53 78 31 15",
    "sg:postcode":"9300",
    "sg:province":"Oost-Vlaanderen",
    "sg:tags":[
        "boutique"
    ],
    "wof:name":"New Top Corn",
    "wof:placetype":"venue"
},
  "geometry": {"coordinates":[4.0378661156,50.9390182495],"type":"Point"}
}