{
  "type": "Feature",
  "properties": {
    "iso:country":"BE",
    "sg:address":"Kuringersteenweg 512",
    "sg:city":"Hasselt",
    "sg:orig_category":"Babyspullen",
    "sg:phone":"+32 11 85 19 60",
    "sg:postcode":"3511",
    "sg:province":"Limburg",
    "wof:name":"Huis Nolmans",
    "wof:placetype":"venue"
},
  "geometry": {"coordinates":[5.2892398834,50.9426689148],"type":"Point"}
}