{
  "type": "Feature",
  "properties": {
    "addr:full":"Rue Cambron 43 Tournai Hainaut 7500",
    "addr:housenumber":"43",
    "addr:postcode":"7500",
    "addr:street":"Rue Cambron",
    "iso:country":"BE",
    "sg:address":"Rue Cambron 43",
    "sg:city":"Tournai",
    "sg:orig_category":"Brood, gebak and snoepgoed",
    "sg:phone":"+32 69 22 29 33",
    "sg:postcode":"7500",
    "sg:province":"Hainaut",
    "wof:name":"Au Pr\u00c9 Fleuri",
    "wof:placetype":"venue"
},
  "geometry": {"coordinates":[3.3952300549,50.607711792],"type":"Point"}
}