{
  "type": "Feature",
  "properties": {
    "iso:country":"BE",
    "sg:address":"Rittenweg 36",
    "sg:city":"Opglabbeek",
    "sg:classifiers":[
        {
            "category":"Health Services",
            "subcategory":"Health Practitioner",
            "type":"Services"
        }
    ],
    "sg:phone":"+32 89 85 57 87",
    "sg:postcode":"3660",
    "sg:province":"Limburg",
    "sg:tags":[
        "physiotherapist"
    ],
    "wof:name":"Gerarts Jos\u00e9e",
    "wof:placetype":"venue"
},
  "geometry": {"coordinates":[5.6103949547,51.0481681824],"type":"Point"}
}