{
  "type": "Feature",
  "properties": {
    "addr:full":"Galerie Des Carmes 24 Wavre Brabant Wallon 1300",
    "addr:housenumber":"1300",
    "addr:street":"Galerie",
    "iso:country":"BE",
    "sg:address":"Galerie Des Carmes 24",
    "sg:city":"Wavre",
    "sg:classifiers":[
        {
            "category":"Manufacturing",
            "subcategory":"Glass & Minerals",
            "type":"Manufacturing & Wholesale Goods"
        }
    ],
    "sg:phone":"+32 10 22 33 02",
    "sg:postcode":"1300",
    "sg:province":"Brabant Wallon",
    "sg:tags":[
        "precious",
        "stone"
    ],
    "wof:name":"Jardin De Genevieve (le)",
    "wof:placetype":"venue"
},
  "geometry": {"coordinates":[4.6071801186,50.7156562805],"type":"Point"}
}