{
  "type": "Feature",
  "properties": {
    "addr:full":"Au Pairon 37 Limbourg Li\u00e8ge 4831",
    "addr:housenumber":"37",
    "addr:postcode":"4831",
    "iso:country":"BE",
    "sg:address":"Au Pairon 37",
    "sg:city":"Limbourg",
    "sg:orig_category":"Boekhouders",
    "sg:phone":"+32 87 76 41 11",
    "sg:postcode":"4831",
    "sg:province":"Li\u00e8ge",
    "wof:name":"Assurances Collard",
    "wof:placetype":"venue"
},
  "geometry": {"coordinates":[5.9196591377,50.6248016357],"type":"Point"}
}