{
  "type": "Feature",
  "properties": {
    "addr:full":"Boonmarkt 5 Heist-op-den-berg (hallaar) Antwerpen 2220",
    "addr:housenumber":"5",
    "addr:postcode":"2220",
    "addr:street":"Boonmarkt",
    "iso:country":"BE",
    "sg:address":"Boonmarkt 5",
    "sg:city":"Heist-op-den-berg (hallaar)",
    "sg:classifiers":[
        {
            "category":"Personal",
            "type":"Services"
        }
    ],
    "sg:phone":"+32 15 24 10 59",
    "sg:postcode":"2220",
    "sg:province":"Antwerpen",
    "sg:tags":[
        "clothing",
        "men's",
        "tailor",
        "-"
    ],
    "wof:name":"Troonbeeckx",
    "wof:placetype":"venue"
},
  "geometry": {"coordinates":[4.7196831703,51.0884590149],"type":"Point"}
}