{
  "type": "Feature",
  "properties": {
    "addr:full":"Rue Des Montagnes 21 Chastre Brabant Wallon 1450",
    "addr:housenumber":"21",
    "addr:postcode":"1450",
    "addr:street":"Rue Des Montagnes",
    "iso:country":"BE",
    "sg:address":"Rue Des Montagnes 21",
    "sg:city":"Chastre",
    "sg:orig_category":"Public-relationsbureaus",
    "sg:phone":"+32 477 28 20 13",
    "sg:postcode":"1450",
    "sg:province":"Brabant Wallon",
    "wof:name":"I.n.t.i.",
    "wof:placetype":"venue"
},
  "geometry": {"coordinates":[4.6329770088,50.6266365051],"type":"Point"}
}