{
  "type": "Feature",
  "properties": {
    "addr:full":"Vlamingstraat 23 Wevelgem West-Vlaanderen 8560",
    "addr:housenumber":"23",
    "addr:postcode":"8560",
    "addr:street":"Vlamingstraat",
    "iso:country":"BE",
    "sg:address":"Vlamingstraat 23",
    "sg:city":"Wevelgem",
    "sg:classifiers":[
        {
            "category":"Real Estate",
            "subcategory":"Developer",
            "type":"Services"
        }
    ],
    "sg:phone":"+32 56 42 20 50",
    "sg:postcode":"8560",
    "sg:province":"West-Vlaanderen",
    "sg:tags":[
        "plomberie",
        "chauffage",
        "mat\u00e9riel",
        "gr",
        "pour"
    ],
    "wof:name":"Van Isacker-constructie",
    "wof:placetype":"venue"
},
  "geometry": {"coordinates":[3.2130060196,50.8117027283],"type":"Point"}
}