{
  "type": "Feature",
  "properties": {
    "addr:full":"Kerkstraat 234 Grimbergen Vlaams-Brabant 1851",
    "addr:housenumber":"234",
    "addr:postcode":"1851",
    "addr:street":"Kerkstraat",
    "iso:country":"BE",
    "sg:address":"Kerkstraat 234",
    "sg:city":"Grimbergen",
    "sg:orig_category":"Juwelen and horloges",
    "sg:phone":"+32 2 269 61 06",
    "sg:postcode":"1851",
    "sg:province":"Vlaams-Brabant",
    "wof:name":"Andre Lombaerts",
    "wof:placetype":"venue"
},
  "geometry": {"coordinates":[4.3892230988,50.976940155],"type":"Point"}
}