{
  "type": "Feature",
  "properties": {
    "addr:full":"Chauss\u00c9e De Lille 25 Tournai Hainaut 7522",
    "addr:housenumber":"25",
    "addr:postcode":"7522",
    "addr:street":"Chausse\u0301E De Lille",
    "iso:country":"BE",
    "sg:address":"Chauss\u00c9e De Lille 25",
    "sg:city":"Tournai",
    "sg:orig_category":"Pain, p\u00e2tisseries and confiseries",
    "sg:phone":"+32 69 84 34 10",
    "sg:postcode":"7522",
    "sg:province":"Hainaut",
    "wof:name":"Pascal Boudin",
    "wof:placetype":"venue"
},
  "geometry": {"coordinates":[3.3742489815,50.6052017212],"type":"Point"}
}