{
  "type": "Feature",
  "properties": {
    "addr:full":"Booitshoekestraat 1 Diksmuide West-Vlaanderen 8600",
    "addr:housenumber":"1",
    "addr:postcode":"8600",
    "addr:street":"Booitshoekestraat",
    "iso:country":"BE",
    "sg:address":"Booitshoekestraat 1",
    "sg:city":"Diksmuide",
    "sg:orig_category":"Rundveehouders Varkenskwekers",
    "sg:phone":"+32 51 55 50 90",
    "sg:postcode":"8600",
    "sg:province":"West-Vlaanderen",
    "wof:name":"Ignace Dobbelaere",
    "wof:placetype":"venue"
},
  "geometry": {"coordinates":[2.8657801151,51.0334663391],"type":"Point"}
}