{
  "type": "Feature",
  "properties": {
    "iso:country":"BE",
    "sg:address":"Dorp 37",
    "sg:city":"Bonheiden",
    "sg:classifiers":[
        {
            "category":"Bars & Pubs",
            "type":"Food & Drink"
        }
    ],
    "sg:phone":"+32 15 52 02 02",
    "sg:postcode":"2820",
    "sg:province":"Antwerpen",
    "wof:name":"Onder Den Toren",
    "wof:placetype":"venue"
},
  "geometry": {"coordinates":[4.5476880074,51.0222129822],"type":"Point"}
}