{
  "type": "Feature",
  "properties": {
    "addr:full":"Rue Ren\u00e9 Descartes 16 Mons Hainaut 7000",
    "addr:housenumber":"16",
    "addr:postcode":"7000",
    "addr:street":"Rue Rene\u0301 Descartes;Hainaut",
    "iso:country":"BE",
    "sg:address":"Rue Ren\u00e9 Descartes 16",
    "sg:city":"Mons",
    "sg:orig_category":"Non-Classified Establishments",
    "sg:phone":"+32 65 77 91 08",
    "sg:postcode":"7000",
    "sg:province":"Hainaut",
    "wof:name":"Feeling Eclairagistes Sprl",
    "wof:placetype":"venue"
},
  "geometry": {"coordinates":[3.9293420315,50.4596672058],"type":"Point"}
}