{
  "type": "Feature",
  "properties": {
    "addr:full":"Rue Grande 79 Dour Hainaut 7370",
    "addr:housenumber":"79",
    "addr:postcode":"7370",
    "addr:street":"Rue Grande;Hainaut",
    "iso:country":"BE",
    "sg:address":"Rue Grande 79",
    "sg:city":"Dour",
    "sg:orig_category":"Pain, p\u00e2tisseries and confiseries",
    "sg:phone":"+32 65 65 25 67",
    "sg:postcode":"7370",
    "sg:province":"Hainaut",
    "wof:name":"P\u00c2tisserie Godefroid",
    "wof:placetype":"venue"
},
  "geometry": {"coordinates":[3.7814590931,50.3993225098],"type":"Point"}
}