{
  "type": "Feature",
  "properties": {
    "addr:full":"Elfde-julilaan 100 Kortrijk West-Vlaanderen 8500",
    "addr:housenumber":"100",
    "addr:postcode":"8500",
    "iso:country":"BE",
    "sg:address":"Elfde-julilaan 100",
    "sg:city":"Kortrijk",
    "sg:orig_category":"Kinderopvang",
    "sg:phone":"+32 56 21 97 96",
    "sg:postcode":"8500",
    "sg:province":"West-Vlaanderen",
    "wof:name":"Kribbe Goofy",
    "wof:placetype":"venue"
},
  "geometry": {"coordinates":[3.2814149857,50.8222389221],"type":"Point"}
}