{
  "type": "Feature",
  "properties": {
    "iso:country":"BE",
    "sg:address":"Industriepark 24",
    "sg:city":"Diest (webbekom)",
    "sg:orig_category":"Non-Classified Establishments",
    "sg:phone":"+32 13 32 18 02",
    "sg:postcode":"3290",
    "sg:province":"Vlaams-Brabant",
    "wof:name":"Aerts Dakmaterialen Bvba",
    "wof:placetype":"venue"
},
  "geometry": {"coordinates":[5.0731592178,50.9659233093],"type":"Point"}
}