{
  "type": "Feature",
  "properties": {
    "iso:country":"BE",
    "sg:address":"Leebeekstraat 2",
    "sg:city":"Zingem",
    "sg:orig_category":"Rundveehouders",
    "sg:phone":"+32 9 384 46 57",
    "sg:postcode":"9750",
    "sg:province":"Oost-Vlaanderen",
    "wof:name":"Marnix Dockers",
    "wof:placetype":"venue"
},
  "geometry": {"coordinates":[3.6604919434,50.8919258118],"type":"Point"}
}