{
  "type": "Feature",
  "properties": {
    "addr:full":"Kerkstraat 149 Buggenhout Oost-Vlaanderen 9255",
    "addr:housenumber":"149",
    "addr:postcode":"9255",
    "addr:street":"Kerkstraat",
    "iso:country":"BE",
    "sg:address":"Kerkstraat 149",
    "sg:city":"Buggenhout",
    "sg:orig_category":"Banques and organismes de cr\u00e9dit",
    "sg:phone":"+32 52 33 39 71",
    "sg:postcode":"9255",
    "sg:province":"Oost-Vlaanderen",
    "wof:name":"Kbc",
    "wof:placetype":"venue"
},
  "geometry": {"coordinates":[4.2018399239,51.0136108398],"type":"Point"}
}