{
  "type": "Feature",
  "properties": {
    "iso:country":"BE",
    "sg:address":"Spikdorenstraat 13",
    "sg:city":"Tienen",
    "sg:orig_category":"Film-, tv- and videoproductie",
    "sg:phone":"+32 16 82 56 85",
    "sg:postcode":"3300",
    "sg:province":"Vlaams-Brabant",
    "wof:name":"T.v. Factory",
    "wof:placetype":"venue"
},
  "geometry": {"coordinates":[4.9249820709,50.8101615906],"type":"Point"}
}