{
  "type": "Feature",
  "properties": {
    "addr:full":"Ooststraat 23 Heist-op-den-berg Antwerpen 2220",
    "addr:housenumber":"23",
    "addr:postcode":"2220",
    "addr:street":"Ooststraat",
    "iso:country":"BE",
    "sg:address":"Ooststraat 23",
    "sg:city":"Heist-op-den-berg",
    "sg:orig_category":"Informaticaconsulenten Marktonderzoekbureaus Software ontwikkeling and ontwerp",
    "sg:phone":"+32 15 25 31 08",
    "sg:postcode":"2220",
    "sg:province":"Antwerpen",
    "wof:name":"Netstore",
    "wof:placetype":"venue"
},
  "geometry": {"coordinates":[4.7470698357,51.0609207153],"type":"Point"}
}