{
  "type": "Feature",
  "properties": {
    "iso:country":"BE",
    "sg:address":"Vliegveldlaan 2",
    "sg:city":"Sint-truiden (brustem)",
    "sg:classifiers":[
        {
            "category":"Shopping",
            "subcategory":"Antiques",
            "type":"Retail Goods"
        }
    ],
    "sg:phone":"+32 11 68 98 62",
    "sg:postcode":"3800",
    "sg:province":"Limburg",
    "wof:name":"Goevaerts",
    "wof:placetype":"venue"
},
  "geometry": {"coordinates":[5.2109699249,50.799495697],"type":"Point"}
}