{
  "type": "Feature",
  "properties": {
    "addr:full":"Rue Des Fusill\u00e9s 63 Ottignies-louvain-la-neuve (ottignies) Brabant Wallon 1340",
    "addr:housenumber":"63",
    "addr:postcode":"1340",
    "addr:street":"Rue Des Fusille\u0301S",
    "iso:country":"BE",
    "sg:address":"Rue Des Fusill\u00e9s 63",
    "sg:city":"Ottignies-louvain-la-neuve (ottignies)",
    "sg:classifiers":[
        {
            "category":"Health Services",
            "subcategory":"Health Practitioner",
            "type":"Services"
        }
    ],
    "sg:phone":"+32 10 40 01 87",
    "sg:postcode":"1340",
    "sg:province":"Brabant Wallon",
    "sg:tags":[
        "psychologist"
    ],
    "wof:name":"Dr\u00e8ze M",
    "wof:placetype":"venue"
},
  "geometry": {"coordinates":[4.5751309395,50.6715126038],"type":"Point"}
}