{
  "type": "Feature",
  "properties": {
    "iso:country":"BE",
    "sg:address":"Kapellestraat 8",
    "sg:city":"Hooglede (gits)",
    "sg:classifiers":[
        {
            "category":"Retail",
            "subcategory":"Veterinary Services",
            "type":"Services"
        }
    ],
    "sg:phone":"+32 51 20 93 92",
    "sg:postcode":"8830",
    "sg:province":"West-Vlaanderen",
    "sg:tags":[
        "veterinarian"
    ],
    "wof:name":"Declercq C",
    "wof:placetype":"venue"
},
  "geometry": {"coordinates":[3.0965669155,50.9965400696],"type":"Point"}
}