{
  "type": "Feature",
  "properties": {
    "addr:full":"Koning Albertstraat 175b302 Mechelen Antwerpen 2800",
    "addr:housenumber":"175b302",
    "addr:postcode":"2800",
    "addr:street":"Koning Albertstraat",
    "iso:country":"BE",
    "sg:address":"Koning Albertstraat 175b302",
    "sg:city":"Mechelen",
    "sg:classifiers":[
        {
            "category":"Arena",
            "subcategory":"Sports Club",
            "type":"Entertainment"
        }
    ],
    "sg:phone":"+32 15 26 25 85",
    "sg:postcode":"2800",
    "sg:province":"Antwerpen",
    "sg:tags":[
        "terrain",
        "hors",
        "de",
        "installation",
        "sportifs"
    ],
    "wof:name":"K. Mechelse Scheid. Sv",
    "wof:placetype":"venue"
},
  "geometry": {"coordinates":[4.4724068642,51.0232505798],"type":"Point"}
}