{
  "type": "Feature",
  "properties": {
    "addr:full":"Avenue Neptune 31b7 Brussel Bruxelles-Capitale 1190",
    "addr:housenumber":"31b7",
    "addr:postcode":"1190",
    "addr:street":"Avenue Neptune",
    "iso:country":"BE",
    "sg:address":"Avenue Neptune 31b7",
    "sg:city":"Brussel",
    "sg:orig_category":"Secr\u00e9tariats",
    "sg:phone":"+32 2 344 17 63",
    "sg:postcode":"1190",
    "sg:province":"Bruxelles-Capitale",
    "wof:name":"Wedner",
    "wof:placetype":"venue"
},
  "geometry": {"coordinates":[4.3333339691,50.8132820129],"type":"Point"}
}