{
  "type": "Feature",
  "properties": {
    "addr:full":"Eikerheide 8 Bornem Antwerpen 2880",
    "addr:housenumber":"8",
    "addr:postcode":"2880",
    "addr:street":"Eikerheide",
    "iso:country":"BE",
    "sg:address":"Eikerheide 8",
    "sg:city":"Bornem",
    "sg:classifiers":[
        {
            "category":"Building & Trades",
            "subcategory":"Landscaping Services",
            "type":"Services"
        }
    ],
    "sg:phone":"+32 3 889 10 65",
    "sg:postcode":"2880",
    "sg:province":"Antwerpen",
    "sg:tags":[
        "gardening",
        "garden",
        "maintenance"
    ],
    "wof:name":"De Pauw Tuinplanten Nv",
    "wof:placetype":"venue"
},
  "geometry": {"coordinates":[4.2766499519,51.0917930603],"type":"Point"}
}