{
  "type": "Feature",
  "properties": {
    "addr:full":"Diestersteenweg 101 Halen Limburg 3545",
    "addr:housenumber":"101",
    "addr:postcode":"3545",
    "addr:street":"Diestersteenweg",
    "iso:country":"BE",
    "sg:address":"Diestersteenweg 101",
    "sg:city":"Halen",
    "sg:orig_category":"Entretien and r\u00e9parations de voitures",
    "sg:phone":"+32 13 44 31 39",
    "sg:postcode":"3545",
    "sg:province":"Limburg",
    "wof:name":"Auto 2000",
    "wof:placetype":"venue"
},
  "geometry": {"coordinates":[5.1029038429,50.9522132874],"type":"Point"}
}