{
  "type": "Feature",
  "properties": {
    "addr:full":"Dr. R. Lambrechtslaan 80 Dilbeek Vlaams-Brabant 1700",
    "addr:housenumber":"80",
    "addr:postcode":"1700",
    "addr:street":"Dr.;Lambrechtslaan",
    "iso:country":"BE",
    "sg:address":"Dr. R. Lambrechtslaan 80",
    "sg:city":"Dilbeek",
    "sg:orig_category":"Boekhouders",
    "sg:phone":"+32 2 569 06 61",
    "sg:postcode":"1700",
    "sg:province":"Vlaams-Brabant",
    "wof:name":"Bernard Godfroid",
    "wof:placetype":"venue"
},
  "geometry": {"coordinates":[4.2627811432,50.8399581909],"type":"Point"}
}