{
  "type": "Feature",
  "properties": {
    "addr:full":"Route De Ronvaux 1 Ciney Namur 5590",
    "addr:housenumber":"1",
    "addr:postcode":"5590",
    "addr:street":"Route De Ronvaux",
    "iso:country":"BE",
    "sg:address":"Route De Ronvaux 1",
    "sg:city":"Ciney",
    "sg:classifiers":[
        {
            "category":"Sports & Exercise",
            "subcategory":"Sports Center",
            "type":"Entertainment"
        }
    ],
    "sg:phone":"+32 83 22 00 50",
    "sg:postcode":"5590",
    "sg:province":"Namur",
    "sg:tags":[
        "terrain",
        "hors",
        "de",
        "installation",
        "sportifs"
    ],
    "wof:name":"L.e.w.b.",
    "wof:placetype":"venue"
},
  "geometry": {"coordinates":[5.1022520065,50.297088623],"type":"Point"}
}