{
  "type": "Feature",
  "properties": {
    "addr:full":"Molenstraat 3 Rotselaar Vlaams-Brabant 3110",
    "addr:housenumber":"3",
    "addr:postcode":"3110",
    "addr:street":"Molenstraat",
    "iso:country":"BE",
    "sg:address":"Molenstraat 3",
    "sg:city":"Rotselaar",
    "sg:classifiers":[
        {
            "category":"Building & Trades",
            "subcategory":"Plumbing",
            "type":"Services"
        }
    ],
    "sg:phone":"+32 16 44 78 67",
    "sg:postcode":"3110",
    "sg:province":"Vlaams-Brabant",
    "sg:tags":[
        "contractor"
    ],
    "wof:name":"Freddy Michiels Bvba",
    "wof:placetype":"venue"
},
  "geometry": {"coordinates":[4.7035150528,50.9467735291],"type":"Point"}
}