{
  "type": "Feature",
  "properties": {
    "addr:full":"Rue Emile Carpentie 2b5 Anderlecht Bruxelles-Capitale 1070",
    "addr:housenumber":"2b5",
    "addr:postcode":"1070",
    "addr:street":"Rue Emile Carpentie",
    "iso:country":"BE",
    "sg:address":"Rue Emile Carpentie 2b5",
    "sg:city":"Anderlecht",
    "sg:orig_category":"Traducteurs and interpr\u00e8tes",
    "sg:phone":"+32 2 522 81 41",
    "sg:postcode":"1070",
    "sg:province":"Bruxelles-Capitale",
    "wof:name":"Poliakov-moulin O. Cbtip/bkvtf",
    "wof:placetype":"venue"
},
  "geometry": {"coordinates":[4.3226599693,50.8363685608],"type":"Point"}
}