{
  "type": "Feature",
  "properties": {
    "iso:country":"BE",
    "sg:address":"Kleinbroekstraat 46",
    "sg:city":"Hamme (moerzeke)",
    "sg:classifiers":[
        {
            "category":"Farming",
            "subcategory":"Crops",
            "type":"Manufacturing & Wholesale Goods"
        }
    ],
    "sg:phone":"+32 52 47 98 08",
    "sg:postcode":"9220",
    "sg:province":"Oost-Vlaanderen",
    "sg:tags":[
        "vegetable",
        "fruit",
        "-",
        "grower"
    ],
    "wof:name":"Nobels E",
    "wof:placetype":"venue"
},
  "geometry": {"coordinates":[4.1605081558,51.0662994385],"type":"Point"}
}