{
  "type": "Feature",
  "properties": {
    "addr:full":"Kloosterstraat 7 Lille (gierle) Antwerpen 2275",
    "addr:housenumber":"7",
    "addr:postcode":"2275",
    "addr:street":"Kloosterstraat",
    "iso:country":"BE",
    "sg:address":"Kloosterstraat 7",
    "sg:city":"Lille (gierle)",
    "sg:classifiers":[
        {
            "category":"Home & Garden",
            "subcategory":"Kitchen Supply",
            "type":"Retail Goods"
        }
    ],
    "sg:phone":"+32 14 37 44 24",
    "sg:postcode":"2275",
    "sg:province":"Antwerpen",
    "sg:tags":[
        "equipment",
        "aircleaning"
    ],
    "wof:name":"Rainbow",
    "wof:placetype":"venue"
},
  "geometry": {"coordinates":[4.8669309616,51.2661628723],"type":"Point"}
}