{
  "type": "Feature",
  "properties": {
    "addr:full":"Spieveldstraat 123 Sint-niklaas Oost-Vlaanderen 9100",
    "addr:housenumber":"123",
    "addr:postcode":"9100",
    "addr:street":"Spieveldstraat",
    "iso:country":"BE",
    "sg:address":"Spieveldstraat 123",
    "sg:city":"Sint-niklaas",
    "sg:classifiers":[
        {
            "category":"Home & Garden",
            "subcategory":"Carpets & Floor Coverings",
            "type":"Retail Goods"
        }
    ],
    "sg:phone":"+32 3 777 16 05",
    "sg:postcode":"9100",
    "sg:province":"Oost-Vlaanderen",
    "sg:tags":[
        "-"
    ],
    "wof:name":"Rasschaert M",
    "wof:placetype":"venue"
},
  "geometry": {"coordinates":[4.1181769371,51.1898880005],"type":"Point"}
}