{
  "type": "Feature",
  "properties": {
    "addr:full":"Beekstraat 2 Putte Antwerpen 2580",
    "addr:housenumber":"2",
    "addr:postcode":"2580",
    "addr:street":"Beekstraat",
    "iso:country":"BE",
    "sg:address":"Beekstraat 2",
    "sg:city":"Putte",
    "sg:orig_category":"Groententeelt",
    "sg:phone":"+32 15 75 74 76",
    "sg:postcode":"2580",
    "sg:province":"Antwerpen",
    "wof:name":"Frans Frans",
    "wof:placetype":"venue"
},
  "geometry": {"coordinates":[4.5953731537,51.0473251343],"type":"Point"}
}