{
  "type": "Feature",
  "properties": {
    "iso:country":"BE",
    "sg:address":"Groenstraat 66",
    "sg:city":"Aalst",
    "sg:orig_category":"Kapsalons",
    "sg:phone":"+32 53 71 02 57",
    "sg:postcode":"9320",
    "sg:province":"Oost-Vlaanderen",
    "wof:name":"O. De Rijcke",
    "wof:placetype":"venue"
},
  "geometry": {"coordinates":[4.0509109497,50.9435272217],"type":"Point"}
}