{
  "type": "Feature",
  "properties": {
    "addr:full":"Lageweg 72 Menen West-Vlaanderen 8930",
    "addr:housenumber":"72",
    "addr:postcode":"8930",
    "addr:street":"Lageweg",
    "iso:country":"BE",
    "sg:address":"Lageweg 72",
    "sg:city":"Menen",
    "sg:classifiers":[
        {
            "category":"Retail",
            "subcategory":"Veterinary Services",
            "type":"Services"
        }
    ],
    "sg:phone":"+32 56 51 94 56",
    "sg:postcode":"8930",
    "sg:province":"West-Vlaanderen",
    "sg:tags":[
        "veterinarian"
    ],
    "wof:name":"Nuytten J",
    "wof:placetype":"venue"
},
  "geometry": {"coordinates":[3.1017780304,50.7927131653],"type":"Point"}
}