{
  "type": "Feature",
  "properties": {
    "addr:full":"Rue De Marche 24 Nassogne Luxembourg 6950",
    "addr:housenumber":"24",
    "addr:postcode":"6950",
    "addr:street":"Rue De Marche",
    "iso:country":"BE",
    "sg:address":"Rue De Marche 24",
    "sg:city":"Nassogne",
    "sg:classifiers":[
        {
            "category":"Farming",
            "subcategory":"Farm & Veterinary Services",
            "type":"Manufacturing & Wholesale Goods"
        }
    ],
    "sg:phone":"+32 84 21 07 85",
    "sg:postcode":"6950",
    "sg:province":"Luxembourg",
    "sg:tags":[
        "agricultural",
        "contractor"
    ],
    "wof:name":"Ovis Sc",
    "wof:placetype":"venue"
},
  "geometry": {"coordinates":[5.3484930992,50.1358642578],"type":"Point"}
}