{
  "type": "Feature",
  "properties": {
    "iso:country":"BE",
    "sg:address":"Halstraat 106",
    "sg:city":"Heusden-zolder (heusden)",
    "sg:orig_category":"Leisure articles",
    "sg:phone":"+32 11 57 28 76",
    "sg:postcode":"3550",
    "sg:province":"Limburg",
    "wof:name":"Brigitte Poppenatelier",
    "wof:placetype":"venue"
},
  "geometry": {"coordinates":[5.307806015,51.0488891602],"type":"Point"}
}