{
  "type": "Feature",
  "properties": {
    "addr:full":"Avenue Ptol\u00e9m\u00e9e 12-1 Bruxelles (uccle) Bruxelles-Capitale 1180",
    "addr:housenumber":"12-1",
    "addr:postcode":"1180",
    "addr:street":"Avenue Ptole\u0301Me\u0301E",
    "iso:country":"BE",
    "sg:address":"Avenue Ptol\u00e9m\u00e9e 12-1",
    "sg:city":"Bruxelles (uccle)",
    "sg:classifiers":[
        {
            "category":"Professional",
            "subcategory":"Lawyer & Legal Services",
            "type":"Services"
        }
    ],
    "sg:phone":"+32 2 375 16 14",
    "sg:postcode":"1180",
    "sg:province":"Bruxelles-Capitale",
    "wof:name":"Huber Barbara",
    "wof:placetype":"venue"
},
  "geometry": {"coordinates":[4.3686051369,50.8035621643],"type":"Point"}
}