{
  "type": "Feature",
  "properties": {
    "iso:country":"BE",
    "sg:address":"Gaversesteenweg 108",
    "sg:city":"Deinze",
    "sg:orig_category":"Pain, p\u00e2tisseries and confiseries",
    "sg:phone":"+32 9 386 27 28",
    "sg:postcode":"9800",
    "sg:province":"Oost-Vlaanderen",
    "wof:name":"Fritz Dumalin",
    "wof:placetype":"venue"
},
  "geometry": {"coordinates":[3.530174017,50.9863166809],"type":"Point"}
}