{
  "type": "Feature",
  "properties": {
    "iso:country":"BE",
    "sg:address":"Kwabrugstraat 38",
    "sg:city":"Kortrijk (bellegem)",
    "sg:classifiers":[
        {
            "category":"Shopping",
            "subcategory":"Pets & Pet Supplies",
            "type":"Retail Goods"
        }
    ],
    "sg:phone":"+32 56 22 37 34",
    "sg:postcode":"8510",
    "sg:province":"West-Vlaanderen",
    "sg:tags":[
        "shop",
        "-"
    ],
    "wof:name":"De Sneppe",
    "wof:placetype":"venue"
},
  "geometry": {"coordinates":[3.2784171104,50.7751426697],"type":"Point"}
}