{
  "type": "Feature",
  "properties": {
    "addr:full":"Bronstraat 11 Lommel Limburg 3920",
    "addr:housenumber":"11",
    "addr:postcode":"3920",
    "addr:street":"Bronstraat",
    "iso:country":"BE",
    "sg:address":"Bronstraat 11",
    "sg:city":"Lommel",
    "sg:orig_category":"Artsen and specialisten",
    "sg:phone":"+32 11 54 50 37",
    "sg:postcode":"3920",
    "sg:province":"Limburg",
    "wof:name":"Martine Schrage",
    "wof:placetype":"venue"
},
  "geometry": {"coordinates":[5.2954750061,51.2310066223],"type":"Point"}
}