{
  "type": "Feature",
  "properties": {
    "iso:country":"BE",
    "sg:address":"Rue Surroyseux 2",
    "sg:city":"Modave",
    "sg:orig_category":"M\u00e9decins and sp\u00e9cialistes",
    "sg:phone":"+32 85 41 14 52",
    "sg:postcode":"4577",
    "sg:province":"Li\u00e8ge",
    "wof:name":"Jacques Lhermitte",
    "wof:placetype":"venue"
},
  "geometry": {"coordinates":[5.2979922295,50.4443855286],"type":"Point"}
}