{
  "type": "Feature",
  "properties": {
    "addr:full":"Rue Des Alli\u00e9s 94 Bruxelles (forest) Bruxelles-Capitale 1190",
    "addr:housenumber":"94",
    "addr:postcode":"1190",
    "addr:street":"Rue Des Allie\u0301S",
    "iso:country":"BE",
    "sg:address":"Rue Des Alli\u00e9s 94",
    "sg:city":"Bruxelles (forest)",
    "sg:classifiers":[
        {
            "category":"Banks & Credit Unions",
            "subcategory":"Bureau De Change",
            "type":"Services"
        }
    ],
    "sg:phone":"+32 2 344 44 91",
    "sg:postcode":"1190",
    "sg:province":"Bruxelles-Capitale",
    "sg:tags":[
        "measuring",
        "control",
        "apparatus"
    ],
    "wof:name":"Pyrindus",
    "wof:placetype":"venue"
},
  "geometry": {"coordinates":[4.3265590668,50.8170967102],"type":"Point"}
}