{
  "type": "Feature",
  "properties": {
    "iso:country":"BE",
    "sg:address":"Rue De La Cr\u00cate 40",
    "sg:city":"Chapelle-lez-herlaimont",
    "sg:orig_category":"Pleisterwerk",
    "sg:phone":"+32 64 44 32 05",
    "sg:postcode":"7160",
    "sg:province":"Hainaut",
    "wof:name":"Entr.andre Person",
    "wof:placetype":"venue"
},
  "geometry": {"coordinates":[4.2741742134,50.4740638733],"type":"Point"}
}