{
  "type": "Feature",
  "properties": {
    "addr:full":"Esenweg 50a Diksmuide West-Vlaanderen 8600",
    "addr:housenumber":"50a",
    "addr:postcode":"8600",
    "addr:street":"Esenweg",
    "iso:country":"BE",
    "sg:address":"Esenweg 50a",
    "sg:city":"Diksmuide",
    "sg:classifiers":[
        {
            "category":"Farming",
            "subcategory":"Livestock Farm",
            "type":"Manufacturing & Wholesale Goods"
        }
    ],
    "sg:phone":"+32 51 50 12 23",
    "sg:postcode":"8600",
    "sg:province":"West-Vlaanderen",
    "sg:tags":[
        "buyer"
    ],
    "wof:name":"Eurobeef Bvba",
    "wof:placetype":"venue"
},
  "geometry": {"coordinates":[2.8740389347,51.0324249268],"type":"Point"}
}