{
  "type": "Feature",
  "properties": {
    "addr:full":"Staatsbaan 65 Maldegem Oost-Vlaanderen 9991",
    "addr:housenumber":"65",
    "addr:postcode":"9991",
    "addr:street":"Staatsbaan",
    "iso:country":"BE",
    "sg:address":"Staatsbaan 65",
    "sg:city":"Maldegem",
    "sg:classifiers":[
        {
            "category":"Cafe",
            "type":"Food & Drink"
        }
    ],
    "sg:phone":"+32 50 71 66 29",
    "sg:postcode":"9991",
    "sg:province":"Oost-Vlaanderen",
    "sg:tags":[
        "caf\u00e9s"
    ],
    "wof:name":"Caf\u00c9 De Reislust",
    "wof:placetype":"venue"
},
  "geometry": {"coordinates":[3.4835100174,51.2048606873],"type":"Point"}
}