{
  "type": "Feature",
  "properties": {
    "addr:full":"Avenue Du Parc 36 Herve (chaineux) Li\u00e8ge 4650",
    "addr:housenumber":"36",
    "addr:postcode":"4650",
    "addr:street":"Avenue Du Parc",
    "iso:country":"BE",
    "sg:address":"Avenue Du Parc 36",
    "sg:city":"Herve (chaineux)",
    "sg:classifiers":[
        {
            "category":"Building & Trades",
            "subcategory":"Cleaning & Sanitation",
            "type":"Services"
        }
    ],
    "sg:phone":"+32 2 735 30 72",
    "sg:postcode":"4650",
    "sg:province":"Li\u00e8ge",
    "sg:tags":[
        "equipment",
        "industrial",
        "maintenance"
    ],
    "wof:name":"Spray-tech Sprl",
    "wof:placetype":"venue"
},
  "geometry": {"coordinates":[5.8329591751,50.6246604919],"type":"Point"}
}