{
  "type": "Feature",
  "properties": {
    "iso:country":"BE",
    "sg:address":"Chauss\u00e9e Brunehault 62",
    "sg:city":"Frasnes-lez-anvaing (oeudeghien)",
    "sg:classifiers":[
        {
            "category":"Health Services",
            "subcategory":"Health Practitioner",
            "type":"Services"
        }
    ],
    "sg:phone":"+32 68 64 56 84",
    "sg:postcode":"7911",
    "sg:province":"Hainaut",
    "sg:tags":[
        "physiotherapist"
    ],
    "wof:name":"Carton M",
    "wof:placetype":"venue"
},
  "geometry": {"coordinates":[3.7132050991,50.6884040833],"type":"Point"}
}