{
  "type": "Feature",
  "properties": {
    "iso:country":"BE",
    "sg:address":"Overheulestraat 101",
    "sg:city":"Wevelgem (moorsele)",
    "sg:classifiers":[
        {
            "category":"Parking",
            "subcategory":"Garage",
            "type":"Transportation"
        }
    ],
    "sg:phone":"+32 56 41 12 43",
    "sg:postcode":"8560",
    "sg:province":"West-Vlaanderen",
    "sg:tags":[
        "truck",
        "-",
        "dump",
        "transport"
    ],
    "wof:name":"Lapeire Vervoeronderneming Bvba",
    "wof:placetype":"venue"
},
  "geometry": {"coordinates":[3.1639139652,50.8448410034],"type":"Point"}
}