{
  "type": "Feature",
  "properties": {
    "addr:full":"Scheurestraat 27 Kinrooi Limburg 3640",
    "addr:housenumber":"27",
    "addr:postcode":"3640",
    "addr:street":"Scheurestraat",
    "iso:country":"BE",
    "sg:address":"Scheurestraat 27",
    "sg:city":"Kinrooi",
    "sg:orig_category":"M\u00e9decins and sp\u00e9cialistes",
    "sg:phone":"+32 89 70 13 51",
    "sg:postcode":"3640",
    "sg:province":"Limburg",
    "wof:name":"J. Alders",
    "wof:placetype":"venue"
},
  "geometry": {"coordinates":[5.7349767685,51.1734466553],"type":"Point"}
}