{
  "type": "Feature",
  "properties": {
    "iso:country":"BE",
    "sg:address":"Perkveld 6",
    "sg:city":"Wezembeek-oppem",
    "sg:classifiers":[
        {
            "category":"Professional",
            "subcategory":"Accounting & Tax Preparation",
            "type":"Services"
        }
    ],
    "sg:phone":"+32 2 782 00 93",
    "sg:postcode":"1970",
    "sg:province":"Vlaams-Brabant",
    "sg:tags":[
        "bookkeeper"
    ],
    "wof:name":"Cloetens & Co Snc",
    "wof:placetype":"venue"
},
  "geometry": {"coordinates":[4.4996371269,50.8473739624],"type":"Point"}
}