{
  "type": "Feature",
  "properties": {
    "addr:full":"Rue De La Station 73bs Silly Hainaut 7830",
    "addr:housenumber":"73bs",
    "addr:postcode":"7830",
    "addr:street":"Rue De La Station",
    "iso:country":"BE",
    "sg:address":"Rue De La Station 73bs",
    "sg:city":"Silly",
    "sg:orig_category":"Salles de conf\u00e9rences and de r\u00e9ceptions",
    "sg:phone":"+32 68 56 81 60",
    "sg:postcode":"7830",
    "sg:province":"Hainaut",
    "wof:name":"Sucrerie De Silly",
    "wof:placetype":"venue"
},
  "geometry": {"coordinates":[3.9115619659,50.6691017151],"type":"Point"}
}