{
  "type": "Feature",
  "properties": {
    "addr:full":"Leopoldlei 28 Heist-op-den-berg Antwerpen 2220",
    "addr:housenumber":"28",
    "addr:postcode":"2220",
    "addr:street":"Leopoldlei",
    "iso:country":"BE",
    "sg:address":"Leopoldlei 28",
    "sg:city":"Heist-op-den-berg",
    "sg:orig_category":"Herstellingen and onderhoud aan huis voor voertuigen Herstellingen and onderhoud van auto's Metaalaf",
    "sg:phone":"+32 15 24 14 82",
    "sg:postcode":"2220",
    "sg:province":"Antwerpen",
    "wof:name":"Garage Ceulemans",
    "wof:placetype":"venue"
},
  "geometry": {"coordinates":[4.7272939682,51.0773162842],"type":"Point"}
}