{
  "type": "Feature",
  "properties": {
    "iso:country":"BE",
    "sg:address":"Floris Primsstraat 38",
    "sg:city":"Grobbendonk",
    "sg:orig_category":"Plaatsen van vloer- and muurbekleding Woningbouw",
    "sg:phone":"+32 14 51 54 00",
    "sg:postcode":"2280",
    "sg:province":"Antwerpen",
    "wof:name":"Gebroeders Mylemans",
    "wof:placetype":"venue"
},
  "geometry": {"coordinates":[4.7316288948,51.195930481],"type":"Point"}
}