{
  "type": "Feature",
  "properties": {
    "addr:full":"Rue De Petit Leez 163 Gembloux-sur-orneau (grand-leez) Namur 5031",
    "addr:housenumber":"163",
    "addr:postcode":"5031",
    "addr:street":"Rue De Petit Leez;Grand-Leez",
    "iso:country":"BE",
    "sg:address":"Rue De Petit Leez 163",
    "sg:city":"Gembloux-sur-orneau (grand-leez)",
    "sg:classifiers":[
        {
            "category":"Food & Beverages",
            "subcategory":"Meat & Fish",
            "type":"Retail Goods"
        }
    ],
    "sg:phone":"+32 81 64 00 25",
    "sg:postcode":"5031",
    "sg:province":"Namur",
    "sg:tags":[
        "poultry",
        "whol",
        "game",
        "-"
    ],
    "wof:name":"D'hoedt E",
    "wof:placetype":"venue"
},
  "geometry": {"coordinates":[4.7704558372,50.5706977844],"type":"Point"}
}