{
  "type": "Feature",
  "properties": {
    "iso:country":"BE",
    "sg:address":"Groentemarkt 28",
    "sg:city":"Lokeren",
    "sg:classifiers":[
        {
            "category":"Shopping",
            "subcategory":"Gifts & Souvenirs",
            "type":"Retail Goods"
        }
    ],
    "sg:phone":"+32 9 348 71 63",
    "sg:postcode":"9160",
    "sg:province":"Oost-Vlaanderen",
    "sg:tags":[
        "geschenken"
    ],
    "wof:name":"Van Steenberghe Geschenken",
    "wof:placetype":"venue"
},
  "geometry": {"coordinates":[3.9893050194,51.103717804],"type":"Point"}
}