{
  "type": "Feature",
  "properties": {
    "addr:full":"Oudenaardestraat 85 Zulte Oost-Vlaanderen 9870",
    "addr:housenumber":"85",
    "addr:postcode":"9870",
    "addr:street":"Oudenaardestraat",
    "iso:country":"BE",
    "sg:address":"Oudenaardestraat 85",
    "sg:city":"Zulte",
    "sg:classifiers":[
        {
            "category":"Cafe",
            "type":"Food & Drink"
        }
    ],
    "sg:phone":"+32 9 388 54 15",
    "sg:postcode":"9870",
    "sg:province":"Oost-Vlaanderen",
    "sg:tags":[
        "caf\u00e9s"
    ],
    "wof:name":"Jacques Deneir",
    "wof:placetype":"venue"
},
  "geometry": {"coordinates":[3.476236105,50.928565979],"type":"Point"}
}