{
  "type": "Feature",
  "properties": {
    "addr:full":"Heusdenseweg 63 Beringen Limburg 3580",
    "addr:housenumber":"63",
    "addr:postcode":"3580",
    "addr:street":"Heusdenseweg",
    "iso:country":"BE",
    "sg:address":"Heusdenseweg 63",
    "sg:city":"Beringen",
    "sg:orig_category":"Schoonheidssalons",
    "sg:phone":"+32 11 42 45 63",
    "sg:postcode":"3580",
    "sg:province":"Limburg",
    "wof:name":"Lizette Claes",
    "wof:placetype":"venue"
},
  "geometry": {"coordinates":[5.243253231,51.0396347046],"type":"Point"}
}