{
  "type": "Feature",
  "properties": {
    "addr:full":"Lambermontplaats 20 Antwerpen Antwerpen 2000",
    "addr:housenumber":"20",
    "addr:postcode":"2000",
    "addr:street":"Lambermontplaats",
    "iso:country":"BE",
    "sg:address":"Lambermontplaats 20",
    "sg:city":"Antwerpen",
    "sg:orig_category":"M\u00e9decins and sp\u00e9cialistes",
    "sg:phone":"+32 3 238 65 10",
    "sg:postcode":"2000",
    "sg:province":"Antwerpen",
    "wof:name":"Guido Aelvoet",
    "wof:placetype":"venue"
},
  "geometry": {"coordinates":[4.3911590576,51.2066650391],"type":"Point"}
}