{
  "type": "Feature",
  "properties": {
    "iso:country":"BE",
    "sg:address":"Nieuwstraat 5",
    "sg:city":"Aalst (groot)",
    "sg:orig_category":"Dameskledingzaken",
    "sg:phone":"+32 53 75 08 68",
    "sg:postcode":"9300",
    "sg:province":"Oost-Vlaanderen",
    "wof:name":"Massimo Dutti",
    "wof:placetype":"venue"
},
  "geometry": {"coordinates":[4.0366401672,50.9384689331],"type":"Point"}
}