{
  "type": "Feature",
  "properties": {
    "iso:country":"BE",
    "sg:address":"Langestraat 45",
    "sg:city":"Brugge",
    "sg:classifiers":[
        {
            "category":"Wholesale",
            "subcategory":"Beer",
            "type":"Manufacturing & Wholesale Goods"
        }
    ],
    "sg:phone":"+32 50 33 06 99",
    "sg:postcode":"8000",
    "sg:province":"West-Vlaanderen",
    "sg:tags":[
        "regional"
    ],
    "wof:name":"De Gouden Boom Nv",
    "wof:placetype":"venue"
},
  "geometry": {"coordinates":[3.2342340946,51.2099838257],"type":"Point"}
}