{
  "type": "Feature",
  "properties": {
    "addr:full":"Agora 31 Ottignies-louvain-la-neuve Brabant Wallon 1348",
    "addr:housenumber":"31",
    "addr:postcode":"1348",
    "addr:street":"Ottignies-Louvain-La-Neuve Brabant",
    "iso:country":"BE",
    "sg:address":"Agora 31",
    "sg:city":"Ottignies-louvain-la-neuve",
    "sg:orig_category":"Banken and kredietinstellingen",
    "sg:phone":"+32 10 45 26 30",
    "sg:postcode":"1348",
    "sg:province":"Brabant Wallon",
    "wof:name":"Cbc",
    "wof:placetype":"venue"
},
  "geometry": {"coordinates":[4.567553997,50.6661262512],"type":"Point"}
}