{
  "type": "Feature",
  "properties": {
    "iso:country":"BE",
    "sg:address":"Krommestraat 47",
    "sg:city":"Meise",
    "sg:orig_category":"M\u00e9decins and sp\u00e9cialistes",
    "sg:phone":"+32 2 269 87 94",
    "sg:postcode":"1860",
    "sg:province":"Vlaams-Brabant",
    "wof:name":"Rudi Vliegen",
    "wof:placetype":"venue"
},
  "geometry": {"coordinates":[4.3444099426,50.9483299255],"type":"Point"}
}