{
  "type": "Feature",
  "properties": {
    "addr:full":"Merksplassesteenweg 104 Rijkevorsel Antwerpen 2310",
    "addr:housenumber":"104",
    "addr:postcode":"2310",
    "addr:street":"Merksplassesteenweg",
    "iso:country":"BE",
    "sg:address":"Merksplassesteenweg 104",
    "sg:city":"Rijkevorsel",
    "sg:orig_category":"Hout and afgeleiden Gh IJzerwaren, bouw- and verfmaterialen",
    "sg:phone":"+32 3 314 24 71",
    "sg:postcode":"2310",
    "sg:province":"Antwerpen",
    "wof:name":"Hubo",
    "wof:placetype":"venue"
},
  "geometry": {"coordinates":[4.7773098946,51.3453598022],"type":"Point"}
}