{
  "type": "Feature",
  "properties": {
    "addr:full":"Joseph G\u00c9rardstraat 43 Gent Oost-Vlaanderen 9040",
    "addr:housenumber":"43",
    "addr:postcode":"9040",
    "addr:street":"Ge\u0301Rardstraat;Oost-Vlaanderen",
    "iso:country":"BE",
    "sg:address":"Joseph G\u00c9rardstraat 43",
    "sg:city":"Gent",
    "sg:orig_category":"Postkantoren Verzekeringsmakelaars and experts",
    "sg:phone":"+32 9 228 21 84",
    "sg:postcode":"9040",
    "sg:province":"Oost-Vlaanderen",
    "wof:name":"De Post",
    "wof:placetype":"venue"
},
  "geometry": {"coordinates":[3.7464430332,51.0615730286],"type":"Point"}
}