{
  "type": "Feature",
  "properties": {
    "iso:country":"BE",
    "sg:address":"Rue De La Sault 4",
    "sg:city":"Florennes",
    "sg:orig_category":"Kapsalons",
    "sg:phone":"+32 71 68 95 85",
    "sg:postcode":"5620",
    "sg:province":"Namur",
    "wof:name":"Daniel Delvaux",
    "wof:placetype":"venue"
},
  "geometry": {"coordinates":[4.6033411026,50.2553672791],"type":"Point"}
}