{
  "type": "Feature",
  "properties": {
    "addr:full":"Koolkerkesteenweg 50 Damme (oostkerke - Hoeke) West-Vlaanderen 8340",
    "addr:housenumber":"50",
    "addr:postcode":"8340",
    "addr:street":"Koolkerkesteenweg",
    "iso:country":"BE",
    "sg:address":"Koolkerkesteenweg 50",
    "sg:city":"Damme (oostkerke - Hoeke)",
    "sg:classifiers":[
        {
            "category":"Wholesale",
            "subcategory":"Wine & Distilled Alcoholic Beverages",
            "type":"Manufacturing & Wholesale Goods"
        }
    ],
    "sg:phone":"+32 50 35 32 49",
    "sg:postcode":"8340",
    "sg:province":"West-Vlaanderen",
    "sg:tags":[
        "whol",
        "-",
        "spirit",
        "mfg"
    ],
    "wof:name":"Sap Bvba",
    "wof:placetype":"venue"
},
  "geometry": {"coordinates":[3.2815999985,51.2513160706],"type":"Point"}
}