{
  "type": "Feature",
  "properties": {
    "iso:country":"BE",
    "sg:address":"Dommelstraat 66",
    "sg:city":"Waasmunster",
    "sg:orig_category":"Cr\u00e8ches and garderies d'enfants",
    "sg:phone":"+32 52 46 13 43",
    "sg:postcode":"9250",
    "sg:province":"Oost-Vlaanderen",
    "wof:name":"Ustrubulleken",
    "wof:placetype":"venue"
},
  "geometry": {"coordinates":[4.1118102074,51.1140518188],"type":"Point"}
}