{
  "type": "Feature",
  "properties": {
    "addr:full":"Avenue Galil\u00e9e 5b Wavre Brabant Wallon 1300",
    "addr:housenumber":"5b;1300",
    "addr:street":"Avenue Galile\u0301E",
    "iso:country":"BE",
    "sg:address":"Avenue Galil\u00e9e 5b",
    "sg:city":"Wavre",
    "sg:classifiers":[
        {
            "category":"Professional",
            "subcategory":"Engineering",
            "type":"Services"
        }
    ],
    "sg:phone":"+32 10 24 53 39",
    "sg:postcode":"1300",
    "sg:province":"Brabant Wallon",
    "sg:tags":[
        "-"
    ],
    "wof:name":"Delta Concept Group Sa",
    "wof:placetype":"venue"
},
  "geometry": {"coordinates":[4.5826201439,50.736076355],"type":"Point"}
}