{
  "type": "Feature",
  "properties": {
    "iso:country":"BE",
    "sg:address":"Place Communale 20",
    "sg:city":"La Louvi\u00c8re (groot)",
    "sg:classifiers":[
        {
            "category":"Insurance",
            "subcategory":"Life Insurance",
            "type":"Services"
        }
    ],
    "sg:phone":"+32 64 23 80 80",
    "sg:postcode":"7100",
    "sg:province":"Hainaut",
    "sg:tags":[
        "assurance"
    ],
    "wof:name":"Smap",
    "wof:placetype":"venue"
},
  "geometry": {"coordinates":[4.1864500046,50.4791488647],"type":"Point"}
}