{
  "type": "Feature",
  "properties": {
    "iso:country":"BE",
    "sg:address":"Haagstraat 29",
    "sg:city":"Bilzen",
    "sg:orig_category":"Dierenartsen",
    "sg:phone":"+32 89 49 16 29",
    "sg:postcode":"3740",
    "sg:province":"Limburg",
    "wof:name":"Cecile Vanherle",
    "wof:placetype":"venue"
},
  "geometry": {"coordinates":[5.5222969055,50.89453125],"type":"Point"}
}