{
  "type": "Feature",
  "properties": {
    "addr:full":"Rue De Tergn\u00c9e 4 Aiseau-presles Hainaut 6250",
    "addr:housenumber":"4",
    "addr:postcode":"6250",
    "addr:street":"Rue De Tergne\u0301E;Hainaut",
    "iso:country":"BE",
    "sg:address":"Rue De Tergn\u00c9e 4",
    "sg:city":"Aiseau-presles",
    "sg:orig_category":"Installatie van houten of kunststof schrijnwerk",
    "sg:phone":"+32 71 77 00 75",
    "sg:postcode":"6250",
    "sg:province":"Hainaut",
    "wof:name":"Serge Demazy",
    "wof:placetype":"venue"
},
  "geometry": {"coordinates":[4.5680170059,50.4312896729],"type":"Point"}
}