{
  "type": "Feature",
  "properties": {
    "addr:full":"Marktplein 7 Oosterzele Oost-Vlaanderen 9860",
    "addr:housenumber":"7",
    "addr:postcode":"9860",
    "addr:street":"Marktplein;Oost-Vlaanderen",
    "iso:country":"BE",
    "sg:address":"Marktplein 7",
    "sg:city":"Oosterzele",
    "sg:orig_category":"Jardinage",
    "sg:phone":"+32 9 362 03 51",
    "sg:postcode":"9860",
    "sg:province":"Oost-Vlaanderen",
    "wof:name":"Ludo Vanborm",
    "wof:placetype":"venue"
},
  "geometry": {"coordinates":[3.7843539715,50.9376144409],"type":"Point"}
}