{
  "type": "Feature",
  "properties": {
    "addr:full":"Rooienberg 52 Duffel Antwerpen 2570",
    "addr:housenumber":"52",
    "addr:postcode":"2570",
    "addr:street":"Rooienberg",
    "iso:country":"BE",
    "sg:address":"Rooienberg 52",
    "sg:city":"Duffel",
    "sg:classifiers":[
        {
            "category":"Education",
            "subcategory":"School",
            "type":"Public Place"
        }
    ],
    "sg:phone":"+32 15 31 17 52",
    "sg:postcode":"2570",
    "sg:province":"Antwerpen",
    "sg:tags":[
        "primary"
    ],
    "wof:name":"Basisschool Kiliaan",
    "wof:placetype":"venue"
},
  "geometry": {"coordinates":[4.4957871437,51.0960235596],"type":"Point"}
}