{
  "type": "Feature",
  "properties": {
    "iso:country":"BE",
    "sg:address":"Stuivenbergplein 38",
    "sg:city":"Antwerpen",
    "sg:classifiers":[
        {
            "category":"Organizations",
            "subcategory":"Community Association",
            "type":"Services"
        }
    ],
    "sg:phone":"+32 3 272 31 40",
    "sg:postcode":"2060",
    "sg:province":"Antwerpen",
    "sg:tags":[
        "cultural"
    ],
    "wof:name":"Oude Badhuis (het)",
    "wof:placetype":"venue"
},
  "geometry": {"coordinates":[4.4310660362,51.2272758484],"type":"Point"}
}