{
  "type": "Feature",
  "properties": {
    "iso:country":"BE",
    "sg:address":"Rue Pierre Flamand 205",
    "sg:city":"Braine-l\u00b4alleud",
    "sg:orig_category":"D\u00e9corateurs d'int\u00e9rieur. Eclairage et \u00e9quipements du foyer. Rev\u00eatements pour sols and murs",
    "sg:phone":"+32 2 384 26 11",
    "sg:postcode":"1420",
    "sg:province":"Brabant Wallon",
    "wof:name":"Verly D\u00c9cor",
    "wof:placetype":"venue"
},
  "geometry": {"coordinates":[4.3701190948,50.6913566589],"type":"Point"}
}