{
  "type": "Feature",
  "properties": {
    "addr:full":"Kan 74 Aubel Li\u00e8ge 4880",
    "addr:housenumber":"74",
    "addr:postcode":"4880",
    "addr:street":"Kan",
    "iso:country":"BE",
    "sg:address":"Kan 74",
    "sg:city":"Aubel",
    "sg:classifiers":[
        {
            "category":"Retail",
            "subcategory":"Veterinary Services",
            "type":"Services"
        }
    ],
    "sg:phone":"+32 87 68 68 47",
    "sg:postcode":"4880",
    "sg:province":"Li\u00e8ge",
    "sg:tags":[
        "veterinarian"
    ],
    "wof:name":"Xhonneux M",
    "wof:placetype":"venue"
},
  "geometry": {"coordinates":[5.8648920059,50.7059669495],"type":"Point"}
}