{
  "type": "Feature",
  "properties": {
    "addr:full":"Hanenstraat 80 Buggenhout Oost-Vlaanderen 9255",
    "addr:housenumber":"80",
    "addr:postcode":"9255",
    "addr:street":"Hanenstraat",
    "iso:country":"BE",
    "sg:address":"Hanenstraat 80",
    "sg:city":"Buggenhout",
    "sg:classifiers":[
        {
            "category":"Cafe",
            "type":"Food & Drink"
        }
    ],
    "sg:phone":"+32 52 34 27 33",
    "sg:postcode":"9255",
    "sg:province":"Oost-Vlaanderen",
    "sg:tags":[
        "caf\u00e9s"
    ],
    "wof:name":"No Fear",
    "wof:placetype":"venue"
},
  "geometry": {"coordinates":[4.200220108,51.0131950378],"type":"Point"}
}