{
  "type": "Feature",
  "properties": {
    "addr:full":"Maarschalk Fochplein 15 Leuven Vlaams-Brabant 3000",
    "addr:housenumber":"15",
    "addr:postcode":"3000",
    "addr:street":"Maarschalk",
    "iso:country":"BE",
    "sg:address":"Maarschalk Fochplein 15",
    "sg:city":"Leuven",
    "sg:classifiers":[
        {
            "category":"Insurance",
            "subcategory":"Insurance Agent",
            "type":"Services"
        }
    ],
    "sg:phone":"+32 16 29 89 11",
    "sg:postcode":"3000",
    "sg:province":"Vlaams-Brabant",
    "sg:tags":[
        "broker"
    ],
    "wof:name":"Dewit & Partners Cvba",
    "wof:placetype":"venue"
},
  "geometry": {"coordinates":[4.7030148506,50.8791275024],"type":"Point"}
}