{
  "type": "Feature",
  "properties": {
    "iso:country":"BE",
    "sg:address":"Brugse Baan 132",
    "sg:city":"Gistel",
    "sg:orig_category":"M\u00e9decines alternatives. Conception d'\u00e9talages and de showrooms",
    "sg:phone":"+32 59 27 82 10",
    "sg:postcode":"8470",
    "sg:province":"West-Vlaanderen",
    "wof:name":"Patrick Vanhoutte",
    "wof:placetype":"venue"
},
  "geometry": {"coordinates":[2.986246109,51.157699585],"type":"Point"}
}