{
  "type": "Feature",
  "properties": {
    "addr:full":"Centrum-zuid 2053 Houthalen-helchteren Limburg 3530",
    "addr:postcode":"2053 houthalen-helchteren;3530",
    "iso:country":"BE",
    "sg:address":"Centrum-zuid 2053",
    "sg:city":"Houthalen-helchteren",
    "sg:orig_category":"Chemicali\u00ebn Gh",
    "sg:phone":"+32 11 60 29 78",
    "sg:postcode":"3530",
    "sg:province":"Limburg",
    "wof:name":"Roam Chemie",
    "wof:placetype":"venue"
},
  "geometry": {"coordinates":[5.3647789955,51.0148925781],"type":"Point"}
}