{
  "type": "Feature",
  "properties": {
    "iso:country":"BE",
    "sg:address":"Grand'place 28",
    "sg:city":"Lessines",
    "sg:orig_category":"Artsen and specialisten",
    "sg:phone":"+32 68 33 26 10",
    "sg:postcode":"7860",
    "sg:province":"Hainaut",
    "wof:name":"Jean-marie Septon",
    "wof:placetype":"venue"
},
  "geometry": {"coordinates":[3.8290889263,50.7124633789],"type":"Point"}
}