{
  "type": "Feature",
  "properties": {
    "addr:full":"Rue Colonel Tachet Des Combes 10 Yvoir Namur 5530",
    "addr:housenumber":"10",
    "addr:postcode":"5530",
    "addr:street":"Rue Colonel Tachet Des Combes",
    "iso:country":"BE",
    "sg:address":"Rue Colonel Tachet Des Combes 10",
    "sg:city":"Yvoir",
    "sg:classifiers":[
        {
            "category":"Shopping",
            "subcategory":"Books",
            "type":"Retail Goods"
        }
    ],
    "sg:phone":"+32 82 61 10 59",
    "sg:postcode":"5530",
    "sg:province":"Namur",
    "sg:tags":[
        "bookseller"
    ],
    "wof:name":"Librairie Gillet Sprl",
    "wof:placetype":"venue"
},
  "geometry": {"coordinates":[4.8788709641,50.326133728],"type":"Point"}
}