{
  "type": "Feature",
  "properties": {
    "iso:country":"BE",
    "sg:address":"Assenedesteenweg 10-14",
    "sg:city":"Zelzate",
    "sg:classifiers":[
        {
            "category":"Wholesale",
            "subcategory":"Beer",
            "type":"Manufacturing & Wholesale Goods"
        }
    ],
    "sg:phone":"+32 9 344 97 54",
    "sg:postcode":"9060",
    "sg:province":"Oost-Vlaanderen",
    "sg:tags":[
        "ale",
        "-"
    ],
    "wof:name":"Drankstation Lievens",
    "wof:placetype":"venue"
},
  "geometry": {"coordinates":[3.7989580631,51.197429657],"type":"Point"}
}