{
  "type": "Feature",
  "properties": {
    "addr:full":"Beukenweg 9ba Zedelgem West-Vlaanderen 8210",
    "addr:housenumber":"9ba",
    "addr:postcode":"8210",
    "addr:street":"Beukenweg",
    "iso:country":"BE",
    "sg:address":"Beukenweg 9ba",
    "sg:city":"Zedelgem",
    "sg:orig_category":"M\u00e9decins and sp\u00e9cialistes",
    "sg:phone":"+32 50 82 58 70",
    "sg:postcode":"8210",
    "sg:province":"West-Vlaanderen",
    "wof:name":"Hugo Arnout",
    "wof:placetype":"venue"
},
  "geometry": {"coordinates":[3.1375629902,51.1404495239],"type":"Point"}
}