{
  "type": "Feature",
  "properties": {
    "addr:full":"Molenpad 30 Lille (gierle) Antwerpen 2275",
    "addr:housenumber":"30",
    "addr:postcode":"2275",
    "addr:street":"Molenpad",
    "iso:country":"BE",
    "sg:address":"Molenpad 30",
    "sg:city":"Lille (gierle)",
    "sg:classifiers":[
        {
            "category":"Personal",
            "subcategory":"Beauty Salon",
            "type":"Services"
        }
    ],
    "sg:phone":"+32 14 55 55 64",
    "sg:postcode":"2275",
    "sg:province":"Antwerpen",
    "sg:tags":[
        "lady",
        "-",
        "hairdressing"
    ],
    "wof:name":"Chris",
    "wof:placetype":"venue"
},
  "geometry": {"coordinates":[4.825758934,51.2322502136],"type":"Point"}
}