{
  "type": "Feature",
  "properties": {
    "addr:full":"Vleurgatsesteenweg 206 Brussel/bruxelles Bruxelles-Capitale 1000",
    "addr:housenumber":"206",
    "addr:postcode":"1000",
    "addr:street":"Vleurgatsesteenweg;/",
    "iso:country":"BE",
    "sg:address":"Vleurgatsesteenweg 206",
    "sg:city":"Brussel/bruxelles",
    "sg:classifiers":[
        {
            "category":"Insurance",
            "subcategory":"Insurance Agent",
            "type":"Services"
        }
    ],
    "sg:phone":"+32 2 646 75 00",
    "sg:postcode":"1000",
    "sg:province":"Bruxelles-Capitale",
    "sg:tags":[
        "verzekeringsmakelaars",
        "expert"
    ],
    "wof:name":"Consulting & Management",
    "wof:placetype":"venue"
},
  "geometry": {"coordinates":[4.3667931557,50.8213424683],"type":"Point"}
}