{
  "type": "Feature",
  "properties": {
    "addr:full":"Leuvensesteenweg 43 Kortenberg Vlaams-Brabant 3070",
    "addr:housenumber":"43",
    "addr:postcode":"3070",
    "addr:street":"Leuvensesteenweg;Vlaams-Brabant",
    "iso:country":"BE",
    "sg:address":"Leuvensesteenweg 43",
    "sg:city":"Kortenberg",
    "sg:orig_category":"MEUBELONTWERP AND -INSTALLATIE Siematic Keukens",
    "sg:phone":"+32 2 757 93 04",
    "sg:postcode":"3070",
    "sg:province":"Vlaams-Brabant",
    "wof:name":"Siematic Brussels",
    "wof:placetype":"venue"
},
  "geometry": {"coordinates":[4.5227208138,50.8825645447],"type":"Point"}
}