{
  "type": "Feature",
  "properties": {
    "addr:full":"Boulevard Du Triomphe 1 Elsene/ixelles Bruxelles-Capitale 1050",
    "addr:housenumber":"1",
    "addr:postcode":"1050",
    "addr:street":"Boulevard Du Triomphe",
    "iso:country":"BE",
    "sg:address":"Boulevard Du Triomphe 1",
    "sg:city":"Elsene/ixelles",
    "sg:orig_category":"Enseignement sup\u00e9rieur",
    "sg:phone":"+32 2 650 50 95",
    "sg:postcode":"1050",
    "sg:province":"Bruxelles-Capitale",
    "wof:name":"I.s.a.i. Victor Horta",
    "wof:placetype":"venue"
},
  "geometry": {"coordinates":[4.4028968811,50.8186302185],"type":"Point"}
}