{
  "type": "Feature",
  "properties": {
    "addr:full":"Lisseweegse Steenweg 124 Brugge (zeebrugge - Lissewege) West-Vlaanderen 8380",
    "addr:housenumber":"124",
    "addr:postcode":"8380",
    "addr:street":"Steenweg",
    "iso:country":"BE",
    "sg:address":"Lisseweegse Steenweg 124",
    "sg:city":"Brugge (zeebrugge - Lissewege)",
    "sg:classifiers":[
        {
            "category":"Home & Garden",
            "subcategory":"Home Furnishings",
            "type":"Retail Goods"
        }
    ],
    "sg:phone":"+32 50 54 44 20",
    "sg:postcode":"8380",
    "sg:province":"West-Vlaanderen",
    "sg:tags":[
        "curtain",
        "-",
        "fixture"
    ],
    "wof:name":"Pitteljon A",
    "wof:placetype":"venue"
},
  "geometry": {"coordinates":[3.2288448811,51.2742958069],"type":"Point"}
}