{
  "type": "Feature",
  "properties": {
    "addr:full":"Boulevard Sylvain Dupuis 217 Box 1 Bruxelles (anderlecht) Bruxelles-Capitale 1070",
    "addr:housenumber":"217;1",
    "addr:postcode":"1070",
    "addr:street":"Boulevard Sylvain Dupuis;Box",
    "iso:country":"BE",
    "sg:address":"Boulevard Sylvain Dupuis 217 Box 1",
    "sg:city":"Bruxelles (anderlecht)",
    "sg:classifiers":[
        {
            "category":"Professional",
            "subcategory":"Accounting & Tax Preparation",
            "type":"Services"
        }
    ],
    "sg:phone":"+32 2 520 31 55",
    "sg:postcode":"1070",
    "sg:province":"Bruxelles-Capitale",
    "sg:tags":[
        "bookkeeper"
    ],
    "wof:name":"Respelier D",
    "wof:placetype":"venue"
},
  "geometry": {"coordinates":[4.2946600914,50.8374633789],"type":"Point"}
}