{
  "type": "Feature",
  "properties": {
    "addr:full":"Sparreweg 35 Brecht Antwerpen 2960",
    "addr:housenumber":"35",
    "addr:postcode":"2960",
    "addr:street":"Sparreweg",
    "iso:country":"BE",
    "sg:address":"Sparreweg 35",
    "sg:city":"Brecht",
    "sg:orig_category":"Enregistrements sonores",
    "sg:phone":"+32 3 636 26 97",
    "sg:postcode":"2960",
    "sg:province":"Antwerpen",
    "wof:name":"Alpha 9",
    "wof:placetype":"venue"
},
  "geometry": {"coordinates":[4.5634388924,51.2907943726],"type":"Point"}
}