{
  "type": "Feature",
  "properties": {
    "iso:country":"BE",
    "sg:address":"Waterhoenlaan 4",
    "sg:city":"Sint-genesius-rode/rhode-saint-genese",
    "sg:orig_category":"Speciaalzaken",
    "sg:phone":"+32 2 358 40 15",
    "sg:postcode":"1640",
    "sg:province":"Vlaams-Brabant",
    "wof:name":"Feuardent",
    "wof:placetype":"venue"
},
  "geometry": {"coordinates":[4.3763852119,50.7357215881],"type":"Point"}
}