{
  "type": "Feature",
  "properties": {
    "addr:full":"Stationlaan 6 Bilzen Limburg 3740",
    "addr:housenumber":"6",
    "addr:postcode":"3740",
    "addr:street":"Stationlaan",
    "iso:country":"BE",
    "sg:address":"Stationlaan 6",
    "sg:city":"Bilzen",
    "sg:classifiers":[
        {
            "category":"Banks & Credit Unions",
            "subcategory":"Investment Brokerage",
            "type":"Services"
        }
    ],
    "sg:phone":"+32 478 62 49 94",
    "sg:postcode":"3740",
    "sg:province":"Limburg",
    "sg:tags":[
        "jean",
        "casual",
        "wear"
    ],
    "wof:name":"Look At Me",
    "wof:placetype":"venue"
},
  "geometry": {"coordinates":[5.5130600929,50.8699417114],"type":"Point"}
}