{
  "type": "Feature",
  "properties": {
    "iso:country":"BE",
    "sg:address":"Lejeunelaan 13a",
    "sg:city":"Koksijde",
    "sg:classifiers":[
        {
            "category":"Structure",
            "subcategory":"Office Building",
            "type":"Public Place"
        }
    ],
    "sg:phone":"+32 58 51 11 88",
    "sg:postcode":"8670",
    "sg:province":"West-Vlaanderen",
    "sg:tags":[
        "-",
        "type",
        "door",
        "sliding",
        "overhead"
    ],
    "wof:name":"Recour Bvba",
    "wof:placetype":"venue"
},
  "geometry": {"coordinates":[2.6390490532,51.1168708801],"type":"Point"}
}