{
  "type": "Feature",
  "properties": {
    "addr:full":"Rue De Bretagne 24 Bruxelles (woluwe-saint-lambert) Bruxelles-Capitale 1200",
    "addr:housenumber":"24",
    "addr:postcode":"1200",
    "addr:street":"Rue De Bretagne",
    "iso:country":"BE",
    "sg:address":"Rue De Bretagne 24",
    "sg:city":"Bruxelles (woluwe-saint-lambert)",
    "sg:classifiers":[
        {
            "category":"Insurance",
            "subcategory":"Insurance Agent",
            "type":"Services"
        }
    ],
    "sg:phone":"+32 2 529 76 29",
    "sg:postcode":"1200",
    "sg:province":"Bruxelles-Capitale",
    "sg:tags":[
        "-",
        "representative"
    ],
    "wof:name":"Ineas",
    "wof:placetype":"venue"
},
  "geometry": {"coordinates":[4.4257321358,50.8555793762],"type":"Point"}
}