{
  "type": "Feature",
  "properties": {
    "iso:country":"BE",
    "sg:address":"Haanhoutstraat 87ba",
    "sg:city":"Lochristi",
    "sg:orig_category":"Loodgieterij, verwarming and sanitaire installaties",
    "sg:phone":"+32 9 355 04 96",
    "sg:postcode":"9080",
    "sg:province":"Oost-Vlaanderen",
    "wof:name":"Herman De Somviele",
    "wof:placetype":"venue"
},
  "geometry": {"coordinates":[3.8515999317,51.0768661499],"type":"Point"}
}