{
  "type": "Feature",
  "properties": {
    "iso:country":"BE",
    "sg:address":"Iepersteenweg 20",
    "sg:city":"Houthulst",
    "sg:classifiers":[
        {
            "category":"Personal",
            "subcategory":"Beauty Salon",
            "type":"Services"
        }
    ],
    "sg:phone":"+32 51 54 56 04",
    "sg:postcode":"8650",
    "sg:province":"West-Vlaanderen",
    "sg:tags":[
        "de",
        "coiffure"
    ],
    "wof:name":"Tine's Haaratelier",
    "wof:placetype":"venue"
},
  "geometry": {"coordinates":[2.8697440624,50.971157074],"type":"Point"}
}