{
  "type": "Feature",
  "properties": {
    "iso:country":"BE",
    "sg:address":"Rue Richard Vandevelde 63",
    "sg:city":"Bruxelles (schaerbeek)",
    "sg:classifiers":[
        {
            "category":"Shopping",
            "subcategory":"Used Merchandise",
            "type":"Retail Goods"
        }
    ],
    "sg:phone":"+32 2 216 14 80",
    "sg:postcode":"1030",
    "sg:province":"Bruxelles-Capitale",
    "sg:tags":[
        "salvage",
        "surplus"
    ],
    "wof:name":"Hammouti M",
    "wof:placetype":"venue"
},
  "geometry": {"coordinates":[4.3904070854,50.8726959229],"type":"Point"}
}