{
  "type": "Feature",
  "properties": {
    "addr:full":"Ingelmunstersteenweg 5 Oostrozebeke West-Vlaanderen 8780",
    "addr:housenumber":"5",
    "addr:postcode":"8780",
    "addr:street":"Ingelmunstersteenweg",
    "iso:country":"BE",
    "sg:address":"Ingelmunstersteenweg 5",
    "sg:city":"Oostrozebeke",
    "sg:orig_category":"Plaatsen van vloer- and muurbekleding",
    "sg:phone":"+32 56 66 94 57",
    "sg:postcode":"8780",
    "sg:province":"West-Vlaanderen",
    "wof:name":"Marc Meyfroot",
    "wof:placetype":"venue"
},
  "geometry": {"coordinates":[3.3229548931,50.9199790955],"type":"Point"}
}