{
  "type": "Feature",
  "properties": {
    "iso:country":"BE",
    "sg:address":"Rattepoelstraat 4a",
    "sg:city":"Maarkedal (maarke-kerkem)",
    "sg:classifiers":[
        {
            "category":"Building & Trades",
            "subcategory":"Construction",
            "type":"Services"
        }
    ],
    "sg:phone":"+32 55 30 01 50",
    "sg:postcode":"9680",
    "sg:province":"Oost-Vlaanderen",
    "sg:tags":[
        "carpenter"
    ],
    "wof:name":"Verschelden N",
    "wof:placetype":"venue"
},
  "geometry": {"coordinates":[3.6561050415,50.8093833923],"type":"Point"}
}