{
  "type": "Feature",
  "properties": {
    "iso:country":"BE",
    "sg:address":"Koning Boudewijnlaan 3",
    "sg:city":"De Pinte",
    "sg:orig_category":"Opsporingsdiensten and detectivebureaus",
    "sg:phone":"+32 9 282 51 99",
    "sg:postcode":"9840",
    "sg:province":"Oost-Vlaanderen",
    "wof:name":"Guy Van Den Bossche",
    "wof:placetype":"venue"
},
  "geometry": {"coordinates":[3.6534650326,50.9893951416],"type":"Point"}
}