{
  "type": "Feature",
  "properties": {
    "addr:full":"Karrestraat 114 Lokeren Oost-Vlaanderen 9160",
    "addr:housenumber":"114",
    "addr:postcode":"9160",
    "addr:street":"Karrestraat",
    "iso:country":"BE",
    "sg:address":"Karrestraat 114",
    "sg:city":"Lokeren",
    "sg:orig_category":"Onderdelen and accessoires voor auto's",
    "sg:phone":"+32 9 348 10 93",
    "sg:postcode":"9160",
    "sg:province":"Oost-Vlaanderen",
    "wof:name":"Bandencentr. De Borger P.",
    "wof:placetype":"venue"
},
  "geometry": {"coordinates":[4.0044140816,51.1208839417],"type":"Point"}
}