{
  "type": "Feature",
  "properties": {
    "iso:country":"BE",
    "sg:address":"Quai Taille-pierres 23",
    "sg:city":"Tournai",
    "sg:orig_category":"Belastingconsulenten Diverse juridische dienstverlening",
    "sg:phone":"+32 69 22 50 75",
    "sg:postcode":"7500",
    "sg:province":"Hainaut",
    "wof:name":"Figestour",
    "wof:placetype":"venue"
},
  "geometry": {"coordinates":[3.3970079422,50.6035690308],"type":"Point"}
}