{
  "type": "Feature",
  "properties": {
    "iso:country":"BE",
    "sg:address":"Leuvenstraat 9",
    "sg:city":"Herent",
    "sg:orig_category":"Epiceries",
    "sg:phone":"+32 16 49 07 01",
    "sg:postcode":"3020",
    "sg:province":"Vlaams-Brabant",
    "wof:name":"Paula Delaure",
    "wof:placetype":"venue"
},
  "geometry": {"coordinates":[4.6781420708,50.9015655518],"type":"Point"}
}