{
  "type": "Feature",
  "properties": {
    "addr:full":"Verdegemstraatje 12 Evergem Oost-Vlaanderen 9940",
    "addr:housenumber":"12",
    "addr:postcode":"9940",
    "addr:street":"Verdegemstraatje;Oost-Vlaanderen",
    "iso:country":"BE",
    "sg:address":"Verdegemstraatje 12",
    "sg:city":"Evergem",
    "sg:orig_category":"Elektrische installaties voor woningen",
    "sg:phone":"+32 9 253 09 11",
    "sg:postcode":"9940",
    "sg:province":"Oost-Vlaanderen",
    "wof:name":"Vlerick",
    "wof:placetype":"venue"
},
  "geometry": {"coordinates":[3.6570510864,51.0990905762],"type":"Point"}
}