{
  "type": "Feature",
  "properties": {
    "iso:country":"BE",
    "sg:address":"Rue Groynne 8",
    "sg:city":"Andenne",
    "sg:orig_category":"Woningbouw",
    "sg:phone":"+32 85 84 23 71",
    "sg:postcode":"5300",
    "sg:province":"Namur",
    "wof:name":"Alex Delree",
    "wof:placetype":"venue"
},
  "geometry": {"coordinates":[5.0796160698,50.4706802368],"type":"Point"}
}