{
  "type": "Feature",
  "properties": {
    "addr:full":"Moortselestraat 30 Oosterzele (moortsele) Oost-Vlaanderen 9860",
    "addr:housenumber":"30",
    "addr:postcode":"9860",
    "addr:street":"Moortselestraat;Moortsele Oost-Vlaanderen",
    "iso:country":"BE",
    "sg:address":"Moortselestraat 30",
    "sg:city":"Oosterzele (moortsele)",
    "sg:classifiers":[
        {
            "category":"Social Services",
            "subcategory":"Child Care",
            "type":"Services"
        }
    ],
    "sg:phone":"+32 9 362 42 69",
    "sg:postcode":"9860",
    "sg:province":"Oost-Vlaanderen",
    "sg:tags":[
        "baby",
        "nursery",
        "day",
        "sitting"
    ],
    "wof:name":"Ukkepuk",
    "wof:placetype":"venue"
},
  "geometry": {"coordinates":[3.7800219059,50.9554443359],"type":"Point"}
}