{
  "type": "Feature",
  "properties": {
    "addr:full":"Klaverstraat 31 Mechelen Antwerpen 2800",
    "addr:housenumber":"31",
    "addr:postcode":"2800",
    "addr:street":"Klaverstraat",
    "iso:country":"BE",
    "sg:address":"Klaverstraat 31",
    "sg:city":"Mechelen",
    "sg:classifiers":[
        {
            "category":"Arena",
            "subcategory":"Sports Club",
            "type":"Entertainment"
        }
    ],
    "sg:phone":"+32 15 42 33 00",
    "sg:postcode":"2800",
    "sg:province":"Antwerpen",
    "sg:tags":[
        "de"
    ],
    "wof:name":"Kc Shotokan",
    "wof:placetype":"venue"
},
  "geometry": {"coordinates":[4.4783029556,50.9989509583],"type":"Point"}
}