{
  "type": "Feature",
  "properties": {
    "addr:full":"Gistelsteenweg 319 Jabbeke West-Vlaanderen 8490",
    "addr:housenumber":"319",
    "addr:postcode":"8490",
    "addr:street":"Gistelsteenweg",
    "iso:country":"BE",
    "sg:address":"Gistelsteenweg 319",
    "sg:city":"Jabbeke",
    "sg:classifiers":[
        {
            "category":"Travel",
            "subcategory":"Hotels & Motels",
            "type":"Entertainment"
        }
    ],
    "sg:phone":"+32 50 38 67 71",
    "sg:postcode":"8490",
    "sg:province":"West-Vlaanderen",
    "wof:name":"Paul Vansieleghem",
    "wof:placetype":"venue"
},
  "geometry": {"coordinates":[3.1040439606,51.1788482666],"type":"Point"}
}