{
  "type": "Feature",
  "properties": {
    "iso:country":"BE",
    "sg:address":"Dendermondsesteenweg 438",
    "sg:city":"Destelbergen",
    "sg:classifiers":[
        {
            "category":"Arena",
            "subcategory":"Sports Club",
            "type":"Entertainment"
        }
    ],
    "sg:phone":"+32 9 229 22 80",
    "sg:postcode":"9070",
    "sg:province":"Oost-Vlaanderen",
    "sg:tags":[
        "de"
    ],
    "wof:name":"Opschutters",
    "wof:placetype":"venue"
},
  "geometry": {"coordinates":[3.8002359867,51.0560302734],"type":"Point"}
}