{
  "type": "Feature",
  "properties": {
    "iso:country":"BE",
    "sg:address":"Rue Des Vingt-deux 3",
    "sg:city":"Li\u00e8ge 1",
    "sg:classifiers":[
        {
            "category":"Banks & Credit Unions",
            "subcategory":"Bureau De Change",
            "type":"Services"
        }
    ],
    "sg:phone":"+32 4 253 58 11",
    "sg:postcode":"4000",
    "sg:province":"Li\u00e8ge",
    "sg:tags":[
        "belgian",
        "-",
        "broker",
        "exchange"
    ],
    "wof:name":"Schurmans G",
    "wof:placetype":"venue"
},
  "geometry": {"coordinates":[5.5704889297,50.6285514832],"type":"Point"}
}