{
  "type": "Feature",
  "properties": {
    "iso:country":"BE",
    "sg:address":"Rue Joseph-donneaux 27",
    "sg:city":"Li\u00e8ge 1 (rocourt)",
    "sg:classifiers":[
        {
            "category":"Health Services",
            "subcategory":"Doctor",
            "type":"Services"
        }
    ],
    "sg:phone":"+32 4 263 17 43",
    "sg:postcode":"4000",
    "sg:province":"Li\u00e8ge",
    "sg:tags":[
        "orthopedist"
    ],
    "wof:name":"Bellefroid Jc Orthopedie Sprl",
    "wof:placetype":"venue"
},
  "geometry": {"coordinates":[5.5452589989,50.6790542603],"type":"Point"}
}