{
  "type": "Feature",
  "properties": {
    "addr:full":"Lippenslaan 245 Knokke-heist West-Vlaanderen 8300",
    "addr:housenumber":"245",
    "addr:postcode":"8300",
    "addr:street":"Lippenslaan",
    "iso:country":"BE",
    "sg:address":"Lippenslaan 245",
    "sg:city":"Knokke-heist",
    "sg:orig_category":"Eclairage et \u00e9quipements du foyer",
    "sg:phone":"+32 50 62 83 42",
    "sg:postcode":"8300",
    "sg:province":"West-Vlaanderen",
    "wof:name":"Hebbe-ding",
    "wof:placetype":"venue"
},
  "geometry": {"coordinates":[3.2881801128,51.3485107422],"type":"Point"}
}