{
  "type": "Feature",
  "properties": {
    "addr:full":"Kerkstraat 111 Diest Vlaams-Brabant 3290",
    "addr:housenumber":"111",
    "addr:postcode":"3290",
    "addr:street":"Kerkstraat",
    "iso:country":"BE",
    "sg:address":"Kerkstraat 111",
    "sg:city":"Diest",
    "sg:classifiers":[
        {
            "category":"Arena",
            "subcategory":"Sports Club",
            "type":"Entertainment"
        }
    ],
    "sg:phone":"+32 13 33 63 34",
    "sg:postcode":"3290",
    "sg:province":"Vlaams-Brabant",
    "sg:tags":[
        "de"
    ],
    "wof:name":"V.c. Vocbar Testelt",
    "wof:placetype":"venue"
},
  "geometry": {"coordinates":[5.080163002,51.0089454651],"type":"Point"}
}