{
  "type": "Feature",
  "properties": {
    "addr:full":"Langevelde 13 Merchtem Vlaams-Brabant 1785",
    "addr:housenumber":"13",
    "addr:postcode":"1785",
    "addr:street":"Langevelde",
    "iso:country":"BE",
    "sg:address":"Langevelde 13",
    "sg:city":"Merchtem",
    "sg:orig_category":"M\u00e9decins and sp\u00e9cialistes",
    "sg:phone":"+32 52 37 33 25",
    "sg:postcode":"1785",
    "sg:province":"Vlaams-Brabant",
    "wof:name":"Maurice Everaet",
    "wof:placetype":"venue"
},
  "geometry": {"coordinates":[4.2475748062,50.9652900696],"type":"Point"}
}