{
  "type": "Feature",
  "properties": {
    "addr:full":"Bostsestraat 49 Box 2 Tienen Vlaams-Brabant 3300",
    "addr:housenumber":"49;2",
    "addr:postcode":"3300",
    "addr:street":"Bostsestraat;Box",
    "iso:country":"BE",
    "sg:address":"Bostsestraat 49 Box 2",
    "sg:city":"Tienen",
    "sg:classifiers":[
        {
            "category":"Professional",
            "subcategory":"Lawyer & Legal Services",
            "type":"Services"
        }
    ],
    "sg:phone":"+32 16 81 77 06",
    "sg:postcode":"3300",
    "sg:province":"Vlaams-Brabant",
    "wof:name":"Beelen M",
    "wof:placetype":"venue"
},
  "geometry": {"coordinates":[4.9401659966,50.8018569946],"type":"Point"}
}