{
  "type": "Feature",
  "properties": {
    "iso:country":"BE",
    "sg:address":"Grote Baan 105",
    "sg:city":"Beveren",
    "sg:orig_category":"Transports fluviaux. Clubs de sport. Installations and terrains de sport hors centres sportifs",
    "sg:phone":"+32 3 775 60 08",
    "sg:postcode":"9120",
    "sg:province":"Oost-Vlaanderen",
    "wof:name":"Vvw-kruibeke",
    "wof:placetype":"venue"
},
  "geometry": {"coordinates":[4.2953948975,51.2209739685],"type":"Point"}
}