{
  "type": "Feature",
  "properties": {
    "addr:full":"Bredestraat 78 Aalst Oost-Vlaanderen 9300",
    "addr:housenumber":"78",
    "addr:postcode":"9300",
    "addr:street":"Bredestraat",
    "iso:country":"BE",
    "sg:address":"Bredestraat 78",
    "sg:city":"Aalst",
    "sg:classifiers":[
        {
            "category":"Bars & Pubs",
            "type":"Food & Drink"
        }
    ],
    "sg:phone":"+32 53 77 13 90",
    "sg:postcode":"9300",
    "sg:province":"Oost-Vlaanderen",
    "wof:name":"Wembley",
    "wof:placetype":"venue"
},
  "geometry": {"coordinates":[4.0431170464,50.9499588013],"type":"Point"}
}