{
  "type": "Feature",
  "properties": {
    "addr:full":"Churchilllaan 7 Tongeren Limburg 3700",
    "addr:housenumber":"7",
    "addr:postcode":"3700",
    "addr:street":"Churchilllaan",
    "iso:country":"BE",
    "sg:address":"Churchilllaan 7",
    "sg:city":"Tongeren",
    "sg:classifiers":[
        {
            "category":"Professional",
            "subcategory":"Accounting & Tax Preparation",
            "type":"Services"
        }
    ],
    "sg:phone":"+32 12 23 86 21",
    "sg:postcode":"3700",
    "sg:province":"Limburg",
    "sg:tags":[
        "bookkeeper"
    ],
    "wof:name":"Fransen J",
    "wof:placetype":"venue"
},
  "geometry": {"coordinates":[5.4649720192,50.7738037109],"type":"Point"}
}