{
  "type": "Feature",
  "properties": {
    "iso:country":"BE",
    "sg:address":"Rue Docteur Pircard 29",
    "sg:city":"Charleroi",
    "sg:orig_category":"Cr\u00e9dit \u00e0 la consommation",
    "sg:phone":"+32 71 34 21 62",
    "sg:postcode":"6040",
    "sg:province":"Hainaut",
    "wof:name":"Finingest",
    "wof:placetype":"venue"
},
  "geometry": {"coordinates":[4.4218401909,50.4519004822],"type":"Point"}
}