{
  "type": "Feature",
  "properties": {
    "iso:country":"BE",
    "sg:address":"Avenue Sainte-anne 12",
    "sg:city":"Oudergem/auderghem",
    "sg:orig_category":"D\u00e9corateurs d'int\u00e9rieur",
    "sg:phone":"+32 2 660 29 74",
    "sg:postcode":"1160",
    "sg:province":"Bruxelles-Capitale",
    "wof:name":"Medius",
    "wof:placetype":"venue"
},
  "geometry": {"coordinates":[4.4377551079,50.817565918],"type":"Point"}
}