{
  "type": "Feature",
  "properties": {
    "iso:country":"BE",
    "sg:address":"Nationalestr 122",
    "sg:city":"Antwerpen",
    "sg:classifiers":[
        {
            "category":"Banks & Credit Unions",
            "subcategory":"Bank",
            "type":"Services"
        }
    ],
    "sg:phone":"+32 3 237 82 05",
    "sg:postcode":"2000",
    "sg:province":"Antwerpen",
    "wof:name":"Aslk-cger Bank",
    "wof:placetype":"venue"
},
  "geometry": {"coordinates":[4.3977150917,51.2136268616],"type":"Point"}
}