{
  "type": "Feature",
  "properties": {
    "addr:full":"Rue De Jumet 20 Charleroi (roux) Hainaut 6044",
    "addr:housenumber":"20;6044",
    "addr:street":"Rue De Jumet",
    "iso:country":"BE",
    "sg:address":"Rue De Jumet 20",
    "sg:city":"Charleroi (roux)",
    "sg:classifiers":[
        {
            "category":"Home & Garden",
            "subcategory":"Building Materials",
            "type":"Retail Goods"
        }
    ],
    "sg:phone":"+32 71 34 14 29",
    "sg:postcode":"6044",
    "sg:province":"Hainaut",
    "sg:tags":[
        "window"
    ],
    "wof:name":"Ozpen Sprl",
    "wof:placetype":"venue"
},
  "geometry": {"coordinates":[4.3969187737,50.4384727478],"type":"Point"}
}