{
  "type": "Feature",
  "properties": {
    "iso:country":"BE",
    "sg:address":"Brandstraat 17",
    "sg:city":"Lokeren",
    "sg:classifiers":[
        {
            "category":"Manufacturing",
            "subcategory":"Rubber & Plastics",
            "type":"Manufacturing & Wholesale Goods"
        }
    ],
    "sg:phone":"+32 9 340 46 46",
    "sg:postcode":"9160",
    "sg:province":"Oost-Vlaanderen",
    "sg:tags":[
        "industrial",
        "-"
    ],
    "wof:name":"T.i. Group Automotive Systems Belgium Nv",
    "wof:placetype":"venue"
},
  "geometry": {"coordinates":[4.0064492226,51.0818328857],"type":"Point"}
}