{
  "type": "Feature",
  "properties": {
    "iso:country":"BE",
    "sg:address":"Avenue Elisabeth 113",
    "sg:city":"Verviers",
    "sg:orig_category":"M\u00e9decins and sp\u00e9cialistes",
    "sg:phone":"+32 87 23 11 32",
    "sg:postcode":"4800",
    "sg:province":"Li\u00e8ge",
    "wof:name":"Joseph De Vogelaer",
    "wof:placetype":"venue"
},
  "geometry": {"coordinates":[5.8677859306,50.5826530457],"type":"Point"}
}