{
  "type": "Feature",
  "properties": {
    "addr:full":"6670 Gouvy Luxembourg 6670",
    "addr:postcode":"6670;6670",
    "iso:country":"BE",
    "sg:address":"6670",
    "sg:city":"Gouvy",
    "sg:classifiers":[
        {
            "category":"Sports & Exercise",
            "subcategory":"Sports Center",
            "type":"Entertainment"
        }
    ],
    "sg:phone":"+32 80 51 01 80",
    "sg:postcode":"6670",
    "sg:province":"Luxembourg",
    "sg:tags":[
        "terrain",
        "hors",
        "de",
        "installation",
        "sportifs"
    ],
    "wof:name":"Piste Ski De Gouvy",
    "wof:placetype":"venue"
},
  "geometry": {"coordinates":[5.9149298668,50.1594314575],"type":"Point"}
}