{
  "type": "Feature",
  "properties": {
    "addr:full":"Rue Des Filles-dieu 1ba Tournai Hainaut 7500",
    "addr:housenumber":"1ba",
    "addr:postcode":"7500",
    "addr:street":"Rue Des Filles-Dieu",
    "iso:country":"BE",
    "sg:address":"Rue Des Filles-dieu 1ba",
    "sg:city":"Tournai",
    "sg:orig_category":"Tribunaux",
    "sg:phone":"+32 69 22 88 13",
    "sg:postcode":"7500",
    "sg:province":"Hainaut",
    "wof:name":"Tribunal De Commerce",
    "wof:placetype":"venue"
},
  "geometry": {"coordinates":[3.3904900551,50.6033401489],"type":"Point"}
}