{
  "type": "Feature",
  "properties": {
    "addr:full":"Guido Gezellestraat 3 Denderleeuw Oost-Vlaanderen 9470",
    "addr:housenumber":"3",
    "addr:postcode":"9470",
    "addr:street":"Guido Gezellestraat",
    "iso:country":"BE",
    "sg:address":"Guido Gezellestraat 3",
    "sg:city":"Denderleeuw",
    "sg:orig_category":"Sportclubs",
    "sg:phone":"+32 53 66 68 63",
    "sg:postcode":"9470",
    "sg:province":"Oost-Vlaanderen",
    "wof:name":"Ttc Smash Denderleeuw",
    "wof:placetype":"venue"
},
  "geometry": {"coordinates":[4.080520153,50.8842697144],"type":"Point"}
}