{
  "type": "Feature",
  "properties": {
    "iso:country":"BE",
    "sg:address":"Quartier Du Centre 111",
    "sg:city":"Doische (gochen\u00e9e)",
    "sg:classifiers":[
        {
            "category":"Professional",
            "subcategory":"Management & Consulting",
            "type":"Services"
        }
    ],
    "sg:phone":"+32 82 67 89 03",
    "sg:postcode":"5680",
    "sg:province":"Namur",
    "sg:tags":[
        "consultant",
        "agency",
        "advertising"
    ],
    "wof:name":"N.e.s.",
    "wof:placetype":"venue"
},
  "geometry": {"coordinates":[4.7456698418,50.1359405518],"type":"Point"}
}