{
  "type": "Feature",
  "properties": {
    "addr:full":"Bergstrasse 0 Lontzen/lontzen Li\u00e8ge 4710",
    "addr:housenumber":"0",
    "addr:postcode":"4710",
    "addr:street":"Bergstrasse",
    "iso:country":"BE",
    "sg:address":"Bergstrasse 0",
    "sg:city":"Lontzen/lontzen",
    "sg:orig_category":"Toeristische diensten",
    "sg:phone":"+32 87 65 84 69",
    "sg:postcode":"4710",
    "sg:province":"Li\u00e8ge",
    "wof:name":"Verkehrsverein",
    "wof:placetype":"venue"
},
  "geometry": {"coordinates":[5.99229002,50.6763191223],"type":"Point"}
}