{
  "type": "Feature",
  "properties": {
    "iso:country":"BE",
    "sg:address":"Rue Des Oblats 22",
    "sg:city":"Li\u00e8ge 1 (grivegn\u00e9e)",
    "sg:classifiers":[
        {
            "category":"Real Estate",
            "subcategory":"Surveying",
            "type":"Services"
        }
    ],
    "sg:phone":"+32 4 343 01 02",
    "sg:postcode":"4030",
    "sg:province":"Li\u00e8ge",
    "sg:tags":[
        "surveyor",
        "land"
    ],
    "wof:name":"Brisbois M",
    "wof:placetype":"venue"
},
  "geometry": {"coordinates":[5.5898590088,50.6300582886],"type":"Point"}
}