{
  "type": "Feature",
  "properties": {
    "addr:full":"Rue De L'eglise 194 Hasti\u00e8re (heer) Namur 5543",
    "addr:housenumber":"194",
    "addr:postcode":"5543",
    "addr:street":"Rue De L'Eglise",
    "iso:country":"BE",
    "sg:address":"Rue De L'eglise 194",
    "sg:city":"Hasti\u00e8re (heer)",
    "sg:classifiers":[
        {
            "category":"Fast Food",
            "type":"Food & Drink"
        }
    ],
    "sg:phone":"+32 82 64 64 62",
    "sg:postcode":"5543",
    "sg:province":"Namur",
    "sg:tags":[
        "fried",
        "stand",
        "potato"
    ],
    "wof:name":"Relais De La Petite Bouffe (au)",
    "wof:placetype":"venue"
},
  "geometry": {"coordinates":[4.8331341743,50.1640052795],"type":"Point"}
}