{
  "type": "Feature",
  "properties": {
    "iso:country":"BE",
    "sg:address":"Koensborre 6",
    "sg:city":"Asse",
    "sg:classifiers":[
        {
            "category":"Bars & Pubs",
            "type":"Food & Drink"
        }
    ],
    "sg:phone":"+32 2 452 61 13",
    "sg:postcode":"1730",
    "sg:province":"Vlaams-Brabant",
    "wof:name":"Jadot (in De)",
    "wof:placetype":"venue"
},
  "geometry": {"coordinates":[4.1942048073,50.9109344482],"type":"Point"}
}