{
  "type": "Feature",
  "properties": {
    "iso:country":"BE",
    "sg:address":"39",
    "sg:city":"Maurits Sabbestraat 2800 Mechelen",
    "sg:classifiers":[
        {
            "category":"Professional",
            "subcategory":"Computer Services",
            "type":"Services"
        }
    ],
    "sg:phone":"+32 15 20 66 45",
    "sg:postcode":"39",
    "sg:tags":[
        "information",
        "technology",
        "software"
    ],
    "wof:name":"Het Computerwinkeltje Bvba",
    "wof:placetype":"venue"
},
  "geometry": {"coordinates":[4.4756698608,51.0353088379],"type":"Point"}
}