{
  "type": "Feature",
  "properties": {
    "addr:full":"Industrielaan 2 Diepenbeek Limburg 3590",
    "addr:housenumber":"2",
    "addr:postcode":"3590",
    "addr:street":"Industrielaan",
    "iso:country":"BE",
    "sg:address":"Industrielaan 2",
    "sg:city":"Diepenbeek",
    "sg:orig_category":"Installatie van houten of kunststof schrijnwerk Installatie van metalen schrijnwerk",
    "sg:phone":"+32 11 32 36 79",
    "sg:postcode":"3590",
    "sg:province":"Limburg",
    "wof:name":"Bruggen Ramen",
    "wof:placetype":"venue"
},
  "geometry": {"coordinates":[5.4284820557,50.9083023071],"type":"Point"}
}