{
  "type": "Feature",
  "properties": {
    "iso:country":"BE",
    "sg:address":"Rue Vital Fran\u00e7oisse 220",
    "sg:city":"Charleroi (marcinelle)",
    "sg:classifiers":[
        {
            "category":"Utilities",
            "subcategory":"Fuel Oil & Lpg",
            "type":"Services"
        }
    ],
    "sg:phone":"+32 71 47 84 00",
    "sg:postcode":"6001",
    "sg:province":"Hainaut",
    "sg:tags":[
        "charcoal"
    ],
    "wof:name":"Lucca Et Ecosacs",
    "wof:placetype":"venue"
},
  "geometry": {"coordinates":[4.4245409966,50.4035491943],"type":"Point"}
}