{
  "type": "Feature",
  "properties": {
    "iso:country":"BE",
    "sg:address":"Rue Fran\u00c7ois Andr\u00c9 2bb",
    "sg:city":"Hensies",
    "sg:orig_category":"Equipement photographique. Production de films, t\u00e9l\u00e9films and vid\u00e9os",
    "sg:phone":"+32 65 65 31 18",
    "sg:postcode":"7350",
    "sg:province":"Hainaut",
    "wof:name":"Serge Bodson",
    "wof:placetype":"venue"
},
  "geometry": {"coordinates":[3.7470459938,50.4194946289],"type":"Point"}
}