{
  "type": "Feature",
  "properties": {
    "iso:country":"BE",
    "sg:address":"Hoolst 75",
    "sg:city":"Balen",
    "sg:classifiers":[
        {
            "category":"Retail",
            "subcategory":"Auto Repair",
            "type":"Services"
        }
    ],
    "sg:phone":"+32 14 81 51 16",
    "sg:postcode":"2490",
    "sg:province":"Antwerpen",
    "sg:tags":[
        "garage"
    ],
    "wof:name":"Govaerts",
    "wof:placetype":"venue"
},
  "geometry": {"coordinates":[5.1529970169,51.15284729],"type":"Point"}
}