{
  "type": "Feature",
  "properties": {
    "addr:full":"14 Rue De La Batte 1350 Orp-jauche 14",
    "addr:housenumber":"14;14",
    "addr:postcode":"1350",
    "addr:street":"Rue De La Batte",
    "iso:country":"BE",
    "sg:address":"14",
    "sg:city":"Rue De La Batte 1350 Orp-jauche",
    "sg:classifiers":[
        {
            "category":"Food & Beverages",
            "subcategory":"Meat & Fish",
            "type":"Retail Goods"
        }
    ],
    "sg:phone":"+32 19 63 54 77",
    "sg:postcode":"14",
    "sg:tags":[
        "preserve",
        "cooked",
        "product",
        "related"
    ],
    "wof:name":"Le Clos De La Batte Sa",
    "wof:placetype":"venue"
},
  "geometry": {"coordinates":[4.97920084,50.6738891602],"type":"Point"}
}