{
  "type": "Feature",
  "properties": {
    "addr:full":"Gotstraat 7 Wortegem-petegem Oost-Vlaanderen 9790",
    "addr:housenumber":"7",
    "addr:postcode":"9790",
    "addr:street":"Gotstraat",
    "iso:country":"BE",
    "sg:address":"Gotstraat 7",
    "sg:city":"Wortegem-petegem",
    "sg:orig_category":"Antiquit\u00e9s",
    "sg:phone":"+32 56 68 75 75",
    "sg:postcode":"9790",
    "sg:province":"Oost-Vlaanderen",
    "wof:name":"Marc Labis",
    "wof:placetype":"venue"
},
  "geometry": {"coordinates":[3.5081019402,50.851348877],"type":"Point"}
}