{
  "type": "Feature",
  "properties": {
    "addr:full":"Schemkensstraat 3 Beringen (paal) Limburg 3583",
    "addr:housenumber":"3",
    "addr:postcode":"3583",
    "addr:street":"Schemkensstraat",
    "iso:country":"BE",
    "sg:address":"Schemkensstraat 3",
    "sg:city":"Beringen (paal)",
    "sg:classifiers":[
        {
            "category":"Wholesale",
            "subcategory":"Painting Supplies",
            "type":"Manufacturing & Wholesale Goods"
        }
    ],
    "sg:phone":"+32 11 43 35 39",
    "sg:postcode":"3583",
    "sg:province":"Limburg",
    "sg:tags":[
        "industrial",
        "-"
    ],
    "wof:name":"Ari\u00ebn Dekoning Nv",
    "wof:placetype":"venue"
},
  "geometry": {"coordinates":[5.1706700325,51.0389442444],"type":"Point"}
}