{
  "type": "Feature",
  "properties": {
    "iso:country":"BE",
    "sg:address":"Sint-amandsesteenweg 85",
    "sg:city":"Bornem (groot)",
    "sg:orig_category":"Supermarch\u00e9s",
    "sg:phone":"+32 3 899 15 60",
    "sg:postcode":"2880",
    "sg:province":"Antwerpen",
    "wof:name":"Colruyt",
    "wof:placetype":"venue"
},
  "geometry": {"coordinates":[4.2295060158,51.0919647217],"type":"Point"}
}