{
  "type": "Feature",
  "properties": {
    "addr:full":"Wezelbaan 26 Diest (schaffen) Vlaams-Brabant 3290",
    "addr:housenumber":"26",
    "addr:postcode":"3290",
    "addr:street":"Wezelbaan",
    "iso:country":"BE",
    "sg:address":"Wezelbaan 26",
    "sg:city":"Diest (schaffen)",
    "sg:classifiers":[
        {
            "category":"Health Services",
            "subcategory":"Health Practitioner",
            "type":"Services"
        }
    ],
    "sg:phone":"+32 13 33 42 88",
    "sg:postcode":"3290",
    "sg:province":"Vlaams-Brabant",
    "sg:tags":[
        "physiotherapist"
    ],
    "wof:name":"Meersman Hilde",
    "wof:placetype":"venue"
},
  "geometry": {"coordinates":[5.0873031616,51.0006065369],"type":"Point"}
}