{
  "type": "Feature",
  "properties": {
    "addr:full":"Pierlapont 72 Zedelgem West-Vlaanderen 8210",
    "addr:housenumber":"72",
    "addr:postcode":"8210",
    "addr:street":"Pierlapont",
    "iso:country":"BE",
    "sg:address":"Pierlapont 72",
    "sg:city":"Zedelgem",
    "sg:classifiers":[
        {
            "category":"Professional",
            "subcategory":"Accounting & Tax Preparation",
            "type":"Services"
        }
    ],
    "sg:phone":"+32 50 20 99 67",
    "sg:postcode":"8210",
    "sg:province":"West-Vlaanderen",
    "sg:tags":[
        "bookkeeper"
    ],
    "wof:name":"Vannieuwenborgh Nv",
    "wof:placetype":"venue"
},
  "geometry": {"coordinates":[3.1458399296,51.1376457214],"type":"Point"}
}