{
  "type": "Feature",
  "properties": {
    "addr:full":"Rue Du Condroz 18 Andenne Namur 5300",
    "addr:housenumber":"18",
    "addr:postcode":"5300",
    "addr:street":"Rue Du Condroz",
    "iso:country":"BE",
    "sg:address":"Rue Du Condroz 18",
    "sg:city":"Andenne",
    "sg:orig_category":"Pain, p\u00e2tisseries and confiseries",
    "sg:phone":"+32 85 84 17 16",
    "sg:postcode":"5300",
    "sg:province":"Namur",
    "wof:name":"Le P\u00cach\u00c9 Mignon",
    "wof:placetype":"venue"
},
  "geometry": {"coordinates":[5.0968542099,50.4853248596],"type":"Point"}
}