{
  "type": "Feature",
  "properties": {
    "addr:full":"Veldstraat 98 Gent Oost-Vlaanderen 9000",
    "addr:housenumber":"98",
    "addr:postcode":"9000",
    "addr:street":"Veldstraat;Oost-Vlaanderen",
    "iso:country":"BE",
    "sg:address":"Veldstraat 98",
    "sg:city":"Gent",
    "sg:orig_category":"Dameskledingzaken",
    "sg:phone":"+32 9 225 88 36",
    "sg:postcode":"9000",
    "sg:province":"Oost-Vlaanderen",
    "wof:name":"Huis Rubica",
    "wof:placetype":"venue"
},
  "geometry": {"coordinates":[3.7210969925,51.0505752563],"type":"Point"}
}