{
  "type": "Feature",
  "properties": {
    "iso:country":"BE",
    "sg:address":"Keyserlei 30",
    "sg:city":"Antwerpen",
    "sg:classifiers":[
        {
            "category":"Restaurant",
            "type":"Food & Drink"
        }
    ],
    "sg:phone":"+32 3 227 36 78",
    "sg:postcode":"2018",
    "sg:province":"Antwerpen",
    "wof:name":"Linea Frutti",
    "wof:placetype":"venue"
},
  "geometry": {"coordinates":[4.4183340073,51.2176971436],"type":"Point"}
}