{
  "type": "Feature",
  "properties": {
    "iso:country":"BE",
    "sg:address":"Rue Du Paradis 40",
    "sg:city":"Brunehaut",
    "sg:orig_category":"Installatie van houten of kunststof schrijnwerk",
    "sg:phone":"+32 69 34 40 92",
    "sg:postcode":"7621",
    "sg:province":"Hainaut",
    "wof:name":"Aubert Bonnet",
    "wof:placetype":"venue"
},
  "geometry": {"coordinates":[3.3877820969,50.5231361389],"type":"Point"}
}