{
  "type": "Feature",
  "properties": {
    "iso:country":"BE",
    "sg:address":"Foyr 110",
    "sg:city":"Jalhay",
    "sg:orig_category":"Rundveehouders Varkenskwekers",
    "sg:phone":"+32 87 64 77 54",
    "sg:postcode":"4845",
    "sg:province":"Li\u00e8ge",
    "wof:name":"Andre Engelskirchen",
    "wof:placetype":"venue"
},
  "geometry": {"coordinates":[5.9239859581,50.5720481873],"type":"Point"}
}