{
  "type": "Feature",
  "properties": {
    "addr:full":"Chauss\u00c9e De Mons 42 Nivelles Brabant Wallon 1400",
    "addr:housenumber":"42",
    "addr:postcode":"1400",
    "addr:street":"Chausse\u0301E De Mons",
    "iso:country":"BE",
    "sg:address":"Chauss\u00c9e De Mons 42",
    "sg:city":"Nivelles",
    "sg:orig_category":"Geschenken and souvenirs Herstelling horloges and juwelen Juwelen and edelstenen Fab Juwelen and hor",
    "sg:phone":"+32 67 84 03 72",
    "sg:postcode":"1400",
    "sg:province":"Brabant Wallon",
    "wof:name":"Venizi",
    "wof:placetype":"venue"
},
  "geometry": {"coordinates":[4.3182659149,50.5940551758],"type":"Point"}
}