{
  "type": "Feature",
  "properties": {
    "iso:country":"BE",
    "sg:address":"Rue De Tournai 13",
    "sg:city":"P\u00e9ruwelz (callenelle)",
    "sg:classifiers":[
        {
            "category":"Health Services",
            "subcategory":"Health Practitioner",
            "type":"Services"
        }
    ],
    "sg:phone":"+32 69 77 17 31",
    "sg:postcode":"7604",
    "sg:province":"Hainaut",
    "sg:tags":[
        "physiotherapist"
    ],
    "wof:name":"Simon Virginie",
    "wof:placetype":"venue"
},
  "geometry": {"coordinates":[3.5259430408,50.5286331177],"type":"Point"}
}