{
  "type": "Feature",
  "properties": {
    "addr:full":"Aarschotsestraat 92 Vilvoorde Vlaams-Brabant 1800",
    "addr:housenumber":"92",
    "addr:postcode":"1800",
    "addr:street":"Aarschotsestraat",
    "iso:country":"BE",
    "sg:address":"Aarschotsestraat 92",
    "sg:city":"Vilvoorde",
    "sg:classifiers":[
        {
            "category":"Government",
            "subcategory":"Police Station",
            "type":"Public Place"
        }
    ],
    "sg:phone":"+32 2 251 09 00",
    "sg:postcode":"1800",
    "sg:province":"Vlaams-Brabant",
    "sg:tags":[
        "gendarmerie"
    ],
    "wof:name":"Federale Politie",
    "wof:placetype":"venue"
},
  "geometry": {"coordinates":[4.4258608818,50.9269294739],"type":"Point"}
}