{
  "type": "Feature",
  "properties": {
    "addr:full":"Clos De Valognes 11 Waterloo Brabant Wallon 1410",
    "addr:housenumber":"11",
    "addr:postcode":"1410",
    "addr:street":"Clos De Valognes",
    "iso:country":"BE",
    "sg:address":"Clos De Valognes 11",
    "sg:city":"Waterloo",
    "sg:classifiers":[
        {
            "category":"Health Services",
            "subcategory":"Doctor",
            "type":"Services"
        }
    ],
    "sg:phone":"+32 2 384 00 27",
    "sg:postcode":"1410",
    "sg:province":"Brabant Wallon",
    "sg:tags":[
        "medicinephysicians",
        "surgeon"
    ],
    "wof:name":"Gu\u00e9risse P",
    "wof:placetype":"venue"
},
  "geometry": {"coordinates":[4.367041111,50.7026939392],"type":"Point"}
}