{
  "type": "Feature",
  "properties": {
    "addr:full":"Vorstlaan 250 Oudergem/auderghem Bruxelles-Capitale 1160",
    "addr:housenumber":"250",
    "addr:postcode":"1160",
    "addr:street":"Vorstlaan;/",
    "iso:country":"BE",
    "sg:address":"Vorstlaan 250",
    "sg:city":"Oudergem/auderghem",
    "sg:orig_category":"Sportclubs Sportterreinen and installaties behalve sportcentra",
    "sg:phone":"+32 2 374 10 18",
    "sg:postcode":"1160",
    "sg:province":"Bruxelles-Capitale",
    "wof:name":"Royale Union Auderghem",
    "wof:placetype":"venue"
},
  "geometry": {"coordinates":[4.4256711006,50.8153762817],"type":"Point"}
}