{
  "type": "Feature",
  "properties": {
    "iso:country":"BE",
    "sg:address":"Frits Van Den Berghelaan 58",
    "sg:city":"Aartselaar",
    "sg:orig_category":"M\u00e9decins and sp\u00e9cialistes",
    "sg:phone":"+32 3 877 11 40",
    "sg:postcode":"2630",
    "sg:province":"Antwerpen",
    "wof:name":"M. Van De Mosselaer",
    "wof:placetype":"venue"
},
  "geometry": {"coordinates":[4.3870668411,51.1382827759],"type":"Point"}
}