{
  "type": "Feature",
  "properties": {
    "iso:country":"BE",
    "sg:address":"Eernegemsestraat 97",
    "sg:city":"Zedelgem",
    "sg:orig_category":"Boucheries",
    "sg:phone":"+32 50 24 04 40",
    "sg:postcode":"8211",
    "sg:province":"West-Vlaanderen",
    "wof:name":"Geert Pollet",
    "wof:placetype":"venue"
},
  "geometry": {"coordinates":[3.0889649391,51.1200408936],"type":"Point"}
}