{
  "type": "Feature",
  "properties": {
    "iso:country":"BE",
    "sg:address":"Abdijmolenstraat 5",
    "sg:city":"Gent (drongen)",
    "sg:classifiers":[
        {
            "category":"Personal",
            "subcategory":"Beauty Salon",
            "type":"Services"
        }
    ],
    "sg:phone":"+32 9 227 61 27",
    "sg:postcode":"9031",
    "sg:province":"Oost-Vlaanderen",
    "sg:tags":[
        "lady",
        "-",
        "hairdressing"
    ],
    "wof:name":"Ginette",
    "wof:placetype":"venue"
},
  "geometry": {"coordinates":[3.6623980999,51.0512428284],"type":"Point"}
}