{
  "type": "Feature",
  "properties": {
    "addr:full":"Rue De Charleroi 38 Courcelles Hainaut 6180",
    "addr:housenumber":"38",
    "addr:postcode":"6180",
    "addr:street":"Rue De Charleroi",
    "iso:country":"BE",
    "sg:address":"Rue De Charleroi 38",
    "sg:city":"Courcelles",
    "sg:classifiers":[
        {
            "category":"Social Services",
            "subcategory":"Retirement Home",
            "type":"Services"
        }
    ],
    "sg:phone":"+32 71 54 25 10",
    "sg:postcode":"6180",
    "sg:province":"Hainaut",
    "sg:tags":[
        "dangerous",
        "work",
        "height"
    ],
    "wof:name":"Trendy Sprl",
    "wof:placetype":"venue"
},
  "geometry": {"coordinates":[4.3560171127,50.477016449],"type":"Point"}
}