{
  "type": "Feature",
  "properties": {
    "iso:country":"BE",
    "sg:address":"Rue De La Sucrerie 23",
    "sg:city":"Hannut (trogn\u00e9e)",
    "sg:classifiers":[
        {
            "category":"Shopping",
            "subcategory":"Party Supplies",
            "type":"Retail Goods"
        }
    ],
    "sg:phone":"+32 19 51 49 30",
    "sg:postcode":"4280",
    "sg:province":"Li\u00e8ge",
    "sg:tags":[
        "decoration",
        "exhibition"
    ],
    "wof:name":"Frank Music",
    "wof:placetype":"venue"
},
  "geometry": {"coordinates":[5.1226558685,50.6844749451],"type":"Point"}
}