{
  "type": "Feature",
  "properties": {
    "addr:full":"Koning Albertplein Mechelen Antwerpen 2800",
    "addr:postcode":"2800",
    "addr:street":"Koning Albertplein",
    "iso:country":"BE",
    "sg:address":"Koning Albertplein",
    "sg:city":"Mechelen",
    "sg:classifiers":[
        {
            "category":"Restaurant",
            "type":"Food & Drink"
        }
    ],
    "sg:phone":"+32 15 42 15 42",
    "sg:postcode":"2800",
    "sg:province":"Antwerpen",
    "sg:tags":[
        "caf\u00e9s"
    ],
    "wof:name":"La Fl\u00cache",
    "wof:placetype":"venue"
},
  "geometry": {"coordinates":[4.4822201729,51.0175933838],"type":"Point"}
}