{
  "type": "Feature",
  "properties": {
    "iso:country":"BE",
    "sg:address":"Veerledorp 49",
    "sg:city":"Laakdal",
    "sg:orig_category":"Banques and organismes de cr\u00e9dit",
    "sg:phone":"+32 14 84 13 83",
    "sg:postcode":"2431",
    "sg:province":"Antwerpen",
    "wof:name":"Fortis",
    "wof:placetype":"venue"
},
  "geometry": {"coordinates":[4.9878921509,51.0703163147],"type":"Point"}
}