{
  "type": "Feature",
  "properties": {
    "iso:country":"BE",
    "sg:address":"Wallenhove 8",
    "sg:city":"Jabbeke",
    "sg:orig_category":"Sportclubs",
    "sg:phone":"+32 50 81 43 14",
    "sg:postcode":"8490",
    "sg:province":"West-Vlaanderen",
    "wof:name":"K.b. Jabbeke",
    "wof:placetype":"venue"
},
  "geometry": {"coordinates":[3.0698840618,51.1643333435],"type":"Point"}
}