{
  "type": "Feature",
  "properties": {
    "iso:country":"BE",
    "sg:address":"Afrikalaan 188",
    "sg:city":"Gent",
    "sg:classifiers":[
        {
            "category":"Home & Garden",
            "subcategory":"Carpets & Floor Coverings",
            "type":"Retail Goods"
        }
    ],
    "sg:phone":"+32 53 66 79 95",
    "sg:postcode":"9000",
    "sg:province":"Oost-Vlaanderen",
    "sg:tags":[
        "laminate",
        "flooring"
    ],
    "wof:name":"Dekaply Nv",
    "wof:placetype":"venue"
},
  "geometry": {"coordinates":[4.0523657799,50.9125137329],"type":"Point"}
}