{
  "type": "Feature",
  "properties": {
    "addr:full":"Quai D'ougn\u00c9e 14 Seraing Li\u00e8ge 4102",
    "addr:housenumber":"14",
    "addr:postcode":"4102",
    "addr:street":"Quai;\u0301E",
    "iso:country":"BE",
    "sg:address":"Quai D'ougn\u00c9e 14",
    "sg:city":"Seraing",
    "sg:orig_category":"Ramassage and traitement des d\u00e9chets m\u00e9nagers",
    "sg:phone":"+32 4 338 05 60",
    "sg:postcode":"4102",
    "sg:province":"Li\u00e8ge",
    "wof:name":"Page Industrie",
    "wof:placetype":"venue"
},
  "geometry": {"coordinates":[5.534799099,50.6082344055],"type":"Point"}
}