{
  "type": "Feature",
  "properties": {
    "addr:full":"Edegemsestraat 109 Mortsel Antwerpen 2640",
    "addr:housenumber":"109",
    "addr:postcode":"2640",
    "addr:street":"Edegemsestraat",
    "iso:country":"BE",
    "sg:address":"Edegemsestraat 109",
    "sg:city":"Mortsel",
    "sg:orig_category":"Fietsen",
    "sg:phone":"+32 3 449 58 66",
    "sg:postcode":"2640",
    "sg:province":"Antwerpen",
    "wof:name":"Huis Verva",
    "wof:placetype":"venue"
},
  "geometry": {"coordinates":[4.4460740089,51.1680183411],"type":"Point"}
}