{
  "type": "Feature",
  "properties": {
    "addr:full":"Sint-jozefstraat 14 Rumst (reet) Antwerpen 2840",
    "addr:housenumber":"14",
    "addr:postcode":"2840",
    "addr:street":"Sint-Jozefstraat",
    "iso:country":"BE",
    "sg:address":"Sint-jozefstraat 14",
    "sg:city":"Rumst (reet)",
    "sg:classifiers":[
        {
            "category":"Retail",
            "subcategory":"Auto Repair",
            "type":"Services"
        }
    ],
    "sg:phone":"+32 3 880 55 55",
    "sg:postcode":"2840",
    "sg:province":"Antwerpen",
    "sg:tags":[
        "garage"
    ],
    "wof:name":"Vermant Nv",
    "wof:placetype":"venue"
},
  "geometry": {"coordinates":[4.3832921982,51.1108016968],"type":"Point"}
}