{
  "type": "Feature",
  "properties": {
    "addr:full":"Vlasmarkt 47 Dendermonde Oost-Vlaanderen 9200",
    "addr:housenumber":"47",
    "addr:postcode":"9200",
    "addr:street":"Vlasmarkt;Oost-Vlaanderen",
    "iso:country":"BE",
    "sg:address":"Vlasmarkt 47",
    "sg:city":"Dendermonde",
    "sg:orig_category":"Groenten and fruit Gh",
    "sg:phone":"+32 52 20 20 42",
    "sg:postcode":"9200",
    "sg:province":"Oost-Vlaanderen",
    "wof:name":"\u00b4t Vitamientje",
    "wof:placetype":"venue"
},
  "geometry": {"coordinates":[4.0988998413,51.0290374756],"type":"Point"}
}