{
  "type": "Feature",
  "properties": {
    "addr:full":"Boterstraat 39 Brussel/bruxelles Bruxelles-Capitale 1000",
    "addr:housenumber":"39",
    "addr:postcode":"1000",
    "addr:street":"Boterstraat;/",
    "iso:country":"BE",
    "sg:address":"Boterstraat 39",
    "sg:city":"Brussel/bruxelles",
    "sg:orig_category":"Juwelen and horloges",
    "sg:phone":"+32 2 513 46 79",
    "sg:postcode":"1000",
    "sg:province":"Bruxelles-Capitale",
    "wof:name":"Louvois",
    "wof:placetype":"venue"
},
  "geometry": {"coordinates":[4.3517069817,50.8473014832],"type":"Point"}
}