{
  "type": "Feature",
  "properties": {
    "iso:country":"BE",
    "sg:address":"Rue Grande 225",
    "sg:city":"Bernissart",
    "sg:orig_category":"Sportclubs",
    "sg:phone":"+32 69 57 86 70",
    "sg:postcode":"7320",
    "sg:province":"Hainaut",
    "wof:name":"V\u00c9lo Club Des Iguanodons",
    "wof:placetype":"venue"
},
  "geometry": {"coordinates":[3.6446509361,50.4729690552],"type":"Point"}
}