{
  "type": "Feature",
  "properties": {
    "iso:country":"BE",
    "sg:address":"Rue Du Ch\u00c2teau 16",
    "sg:city":"Brunehaut",
    "sg:orig_category":"Fruitteelt GROENTEN AND FRUIT Groenten and fruit Gh",
    "sg:phone":"+32 69 34 64 43",
    "sg:postcode":"7621",
    "sg:province":"Hainaut",
    "wof:name":"Norbert Verbeure",
    "wof:placetype":"venue"
},
  "geometry": {"coordinates":[3.3871510029,50.5199890137],"type":"Point"}
}