{
  "type": "Feature",
  "properties": {
    "iso:country":"BE",
    "sg:address":"Sint-lambertusstraat 22",
    "sg:city":"Hoeselt",
    "sg:orig_category":"Installation de menuiserie en bois and plastique",
    "sg:phone":"+32 12 23 10 80",
    "sg:postcode":"3730",
    "sg:province":"Limburg",
    "wof:name":"Fagard Meubelen",
    "wof:placetype":"venue"
},
  "geometry": {"coordinates":[5.4928750992,50.8255119324],"type":"Point"}
}