{
  "type": "Feature",
  "properties": {
    "iso:country":"BE",
    "sg:address":"Rue Edouard Andr\u00e9 8",
    "sg:city":"Virton (saint-mard)",
    "sg:classifiers":[
        {
            "category":"Health Services",
            "subcategory":"Doctor",
            "type":"Services"
        }
    ],
    "sg:phone":"+32 63 58 22 33",
    "sg:postcode":"6762",
    "sg:province":"Luxembourg",
    "sg:tags":[
        "medicinephysicians",
        "surgeon"
    ],
    "wof:name":"Leruth Sylvianne",
    "wof:placetype":"venue"
},
  "geometry": {"coordinates":[5.5198140144,49.5619163513],"type":"Point"}
}