{
  "type": "Feature",
  "properties": {
    "addr:full":"Malecotstraat 7 Blankenberge West-Vlaanderen 8370",
    "addr:housenumber":"7",
    "addr:postcode":"8370",
    "addr:street":"Malecotstraat",
    "iso:country":"BE",
    "sg:address":"Malecotstraat 7",
    "sg:city":"Blankenberge",
    "sg:classifiers":[
        {
            "category":"Fast Food",
            "type":"Food & Drink"
        }
    ],
    "sg:phone":"+32 50 41 07 89",
    "sg:postcode":"8370",
    "sg:province":"West-Vlaanderen",
    "sg:tags":[
        "fried",
        "stand",
        "potato"
    ],
    "wof:name":"Terminus",
    "wof:placetype":"venue"
},
  "geometry": {"coordinates":[3.1316840649,51.3160438538],"type":"Point"}
}