{
  "type": "Feature",
  "properties": {
    "addr:full":"Dokter Haubenlaan 34 Maasmechelen Limburg 3630",
    "addr:housenumber":"34",
    "addr:postcode":"3630",
    "addr:street":"Dokter Haubenlaan",
    "iso:country":"BE",
    "sg:address":"Dokter Haubenlaan 34",
    "sg:city":"Maasmechelen",
    "sg:classifiers":[
        {
            "category":"Restaurant",
            "type":"Food & Drink"
        }
    ],
    "sg:phone":"+32 89 76 63 33",
    "sg:postcode":"3630",
    "sg:province":"Limburg",
    "sg:tags":[
        "caf\u00e9s"
    ],
    "wof:name":"Taverne De Trepkes",
    "wof:placetype":"venue"
},
  "geometry": {"coordinates":[5.7017049789,50.9611053467],"type":"Point"}
}