{
  "type": "Feature",
  "properties": {
    "addr:full":"Rue Du Commerce 47 Libin Luxembourg 6890",
    "addr:housenumber":"47",
    "addr:postcode":"6890",
    "addr:street":"Rue Du Commerce",
    "iso:country":"BE",
    "sg:address":"Rue Du Commerce 47",
    "sg:city":"Libin",
    "sg:classifiers":[
        {
            "category":"Restaurant",
            "type":"Food & Drink"
        }
    ],
    "sg:phone":"+32 61 65 84 77",
    "sg:postcode":"6890",
    "sg:province":"Luxembourg",
    "wof:name":"Chez Nicola",
    "wof:placetype":"venue"
},
  "geometry": {"coordinates":[5.2548742294,49.9837303162],"type":"Point"}
}