{
  "type": "Feature",
  "properties": {
    "iso:country":"BE",
    "sg:address":"Moulin Du Ruy 32",
    "sg:city":"Stoumont (la Gleize)",
    "sg:classifiers":[
        {
            "category":"Education",
            "subcategory":"School",
            "type":"Public Place"
        }
    ],
    "sg:phone":"+32 80 78 51 04",
    "sg:postcode":"4987",
    "sg:province":"Li\u00e8ge",
    "sg:tags":[
        "primary"
    ],
    "wof:name":"Moulin Du Ruy",
    "wof:placetype":"venue"
},
  "geometry": {"coordinates":[5.8876471519,50.4238700867],"type":"Point"}
}