{
  "type": "Feature",
  "properties": {
    "addr:full":"Bergense Steenweg 1062 Anderlecht/anderlecht Bruxelles-Capitale 1070",
    "addr:postcode":"1062;1070",
    "addr:street":"Bergense Steenweg",
    "iso:country":"BE",
    "sg:address":"Bergense Steenweg 1062",
    "sg:city":"Anderlecht/anderlecht",
    "sg:orig_category":"Speelgoed",
    "sg:phone":"+32 2 521 87 21",
    "sg:postcode":"1070",
    "sg:province":"Bruxelles-Capitale",
    "wof:name":"Bazar De La Roue",
    "wof:placetype":"venue"
},
  "geometry": {"coordinates":[4.2949700356,50.8223686218],"type":"Point"}
}