{
  "type": "Feature",
  "properties": {
    "addr:full":"Rue Du Mar\u00c9chal 5 Brugelette Hainaut 7943",
    "addr:housenumber":"5",
    "addr:postcode":"7943",
    "addr:street":"Rue Du Mare\u0301Chal;Hainaut",
    "iso:country":"BE",
    "sg:address":"Rue Du Mar\u00c9chal 5",
    "sg:city":"Brugelette",
    "sg:orig_category":"Boekhouders",
    "sg:phone":"+32 68 45 55 79",
    "sg:postcode":"7943",
    "sg:province":"Hainaut",
    "wof:name":"Fievez Nathalie",
    "wof:placetype":"venue"
},
  "geometry": {"coordinates":[3.8913989067,50.6062774658],"type":"Point"}
}