{
  "type": "Feature",
  "properties": {
    "iso:country":"BE",
    "sg:address":"Av. Bourg. Jean Materne 19",
    "sg:city":"Namur",
    "sg:classifiers":[
        {
            "category":"Restaurant",
            "type":"Food & Drink"
        }
    ],
    "sg:phone":"+32 81 30 79 59",
    "sg:postcode":"5100",
    "sg:province":"Namur",
    "wof:name":"Snack-bar Le Pregos",
    "wof:placetype":"venue"
},
  "geometry": {"coordinates":[4.8713750839,50.4566345215],"type":"Point"}
}