{
  "type": "Feature",
  "properties": {
    "addr:full":"Zandstraat 11 Oud-turnhout Antwerpen 2360",
    "addr:housenumber":"11",
    "addr:postcode":"2360",
    "addr:street":"Zandstraat",
    "iso:country":"BE",
    "sg:address":"Zandstraat 11",
    "sg:city":"Oud-turnhout",
    "sg:classifiers":[
        {
            "category":"Manufacturing",
            "subcategory":"Metals",
            "type":"Manufacturing & Wholesale Goods"
        }
    ],
    "sg:phone":"+32 14 45 27 77",
    "sg:postcode":"2360",
    "sg:province":"Antwerpen",
    "sg:tags":[
        "turning"
    ],
    "wof:name":"Van Deun A",
    "wof:placetype":"venue"
},
  "geometry": {"coordinates":[4.9774541855,51.3094406128],"type":"Point"}
}