{
  "type": "Feature",
  "properties": {
    "addr:full":"Kamerdellelaan 16 Ukkel/uccle Bruxelles-Capitale 1180",
    "addr:housenumber":"16",
    "addr:postcode":"1180",
    "addr:street":"Kamerdellelaan;/",
    "iso:country":"BE",
    "sg:address":"Kamerdellelaan 16",
    "sg:city":"Ukkel/uccle",
    "sg:classifiers":[
        {
            "category":"Insurance",
            "subcategory":"Insurance Agent",
            "type":"Services"
        }
    ],
    "sg:phone":"+32 2 375 18 01",
    "sg:postcode":"1180",
    "sg:province":"Bruxelles-Capitale",
    "sg:tags":[
        "verzekeringsmakelaars",
        "expert"
    ],
    "wof:name":"Larege",
    "wof:placetype":"venue"
},
  "geometry": {"coordinates":[4.3469867706,50.8028907776],"type":"Point"}
}