{
  "type": "Feature",
  "properties": {
    "addr:full":"Oostendestraat 7b4 Torhout West-Vlaanderen 8820",
    "addr:housenumber":"7b4",
    "addr:postcode":"8820",
    "addr:street":"Oostendestraat",
    "iso:country":"BE",
    "sg:address":"Oostendestraat 7b4",
    "sg:city":"Torhout",
    "sg:orig_category":"Avocats and conseillers juridiques",
    "sg:phone":"+32 50 22 32 80",
    "sg:postcode":"8820",
    "sg:province":"West-Vlaanderen",
    "wof:name":"G. Vanhoutte",
    "wof:placetype":"venue"
},
  "geometry": {"coordinates":[3.0905900002,51.0691146851],"type":"Point"}
}