{
  "type": "Feature",
  "properties": {
    "addr:full":"Quai Des Ardennes 160b43 Li\u00c8ge Li\u00e8ge 4032",
    "addr:housenumber":"160b43",
    "addr:postcode":"4032",
    "addr:street":"Quai Des Ardennes",
    "iso:country":"BE",
    "sg:address":"Quai Des Ardennes 160b43",
    "sg:city":"Li\u00c8ge",
    "sg:classifiers":[
        {
            "category":"Personal",
            "subcategory":"Beauty Salon",
            "type":"Services"
        }
    ],
    "sg:phone":"+32 4 365 01 75",
    "sg:postcode":"4032",
    "sg:province":"Li\u00e8ge",
    "sg:tags":[
        "de",
        "coiffure"
    ],
    "wof:name":"Yvette Lecluse",
    "wof:placetype":"venue"
},
  "geometry": {"coordinates":[5.619579792,50.6117401123],"type":"Point"}
}