{
  "type": "Feature",
  "properties": {
    "iso:country":"BE",
    "sg:address":"Rupsenstraat 13",
    "sg:city":"Wingene",
    "sg:orig_category":"Gespecialiseerde residenti\u00eble bouw",
    "sg:phone":"+32 51 61 16 99",
    "sg:postcode":"8750",
    "sg:province":"West-Vlaanderen",
    "wof:name":"Denolf Danny",
    "wof:placetype":"venue"
},
  "geometry": {"coordinates":[3.2227060795,51.0409927368],"type":"Point"}
}