{
  "type": "Feature",
  "properties": {
    "addr:full":"Houwaartseweg 61 Aarschot Vlaams-Brabant 3200",
    "addr:housenumber":"61",
    "addr:postcode":"3200",
    "addr:street":"Houwaartseweg",
    "iso:country":"BE",
    "sg:address":"Houwaartseweg 61",
    "sg:city":"Aarschot",
    "sg:classifiers":[
        {
            "category":"Building & Trades",
            "subcategory":"Construction",
            "type":"Services"
        }
    ],
    "sg:phone":"+32 16 50 14 39",
    "sg:postcode":"3200",
    "sg:province":"Vlaams-Brabant",
    "sg:tags":[
        "carpenter"
    ],
    "wof:name":"Aerts R",
    "wof:placetype":"venue"
},
  "geometry": {"coordinates":[4.8676891327,50.9614334106],"type":"Point"}
}