{
  "type": "Feature",
  "properties": {
    "iso:country":"BE",
    "sg:address":"Rue De Waucomont 42",
    "sg:city":"Chaineux",
    "sg:classifiers":[
        {
            "category":"Shopping",
            "subcategory":"Clothing, Apparel, & Fashions",
            "type":"Retail Goods"
        }
    ],
    "sg:phone":"+32 87 67 45 35",
    "sg:postcode":"4650",
    "sg:province":"Li\u00e8ge",
    "sg:tags":[
        "textile",
        "clothing",
        "clothes"
    ],
    "wof:name":"Schyns Goldstein Sa",
    "wof:placetype":"venue"
},
  "geometry": {"coordinates":[5.8275241852,50.6433105469],"type":"Point"}
}