{
  "type": "Feature",
  "properties": {
    "addr:full":"Heuvel 34 Aalst (erembodegem) Oost-Vlaanderen 9320",
    "addr:housenumber":"34",
    "addr:postcode":"9320",
    "addr:street":"Heuvel",
    "iso:country":"BE",
    "sg:address":"Heuvel 34",
    "sg:city":"Aalst (erembodegem)",
    "sg:classifiers":[
        {
            "category":"Parking",
            "subcategory":"Bicycle",
            "type":"Transportation"
        }
    ],
    "sg:phone":"+32 53 71 00 54",
    "sg:postcode":"9320",
    "sg:province":"Oost-Vlaanderen",
    "sg:tags":[
        "chiropodist"
    ],
    "wof:name":"De Smedt E",
    "wof:placetype":"venue"
},
  "geometry": {"coordinates":[4.0553851128,50.9209976196],"type":"Point"}
}