{
  "type": "Feature",
  "properties": {
    "iso:country":"BE",
    "sg:address":"Borgstraat 153",
    "sg:city":"Sint-amands",
    "sg:orig_category":"Speelgoed",
    "sg:phone":"+32 52 33 74 54",
    "sg:postcode":"2890",
    "sg:province":"Antwerpen",
    "wof:name":"Top 1 Toys Van Bosch",
    "wof:placetype":"venue"
},
  "geometry": {"coordinates":[4.2058959007,51.0516700745],"type":"Point"}
}