{
  "type": "Feature",
  "properties": {
    "iso:country":"BE",
    "sg:address":"Dendermondsesteenweg 212",
    "sg:city":"Willebroek",
    "sg:classifiers":[
        {
            "category":"Autos & Motor Vehicles",
            "subcategory":"Auto Supplies",
            "type":"Retail Goods"
        }
    ],
    "sg:phone":"+32 3 886 35 06",
    "sg:postcode":"2830",
    "sg:province":"Antwerpen",
    "sg:tags":[
        "access",
        "automobile",
        "part",
        "-"
    ],
    "wof:name":"Auto Parts Center Willebroek",
    "wof:placetype":"venue"
},
  "geometry": {"coordinates":[4.3454799652,51.0590286255],"type":"Point"}
}