{
  "type": "Feature",
  "properties": {
    "iso:country":"BE",
    "sg:address":"Coenstraat 43",
    "sg:city":"Opwijk",
    "sg:classifiers":[
        {
            "category":"Food & Beverages",
            "subcategory":"Fruits & Vegetables",
            "type":"Retail Goods"
        }
    ],
    "sg:phone":"+32 52 35 65 39",
    "sg:postcode":"1745",
    "sg:province":"Vlaams-Brabant",
    "sg:tags":[
        "l\u00e9gumes",
        "gr"
    ],
    "wof:name":"Marc Vermoesen",
    "wof:placetype":"venue"
},
  "geometry": {"coordinates":[4.1564621925,50.9736022949],"type":"Point"}
}