{
  "type": "Feature",
  "properties": {
    "iso:country":"BE",
    "sg:address":"Bloemendaelstraat 7",
    "sg:city":"Herne",
    "sg:classifiers":[
        {
            "category":"Food & Beverages",
            "subcategory":"Meat & Fish",
            "type":"Retail Goods"
        }
    ],
    "sg:phone":"+32 2 396 22 25",
    "sg:postcode":"1540",
    "sg:province":"Vlaams-Brabant",
    "sg:tags":[
        "-",
        "livestock"
    ],
    "wof:name":"Van Den Hove",
    "wof:placetype":"venue"
},
  "geometry": {"coordinates":[4.028263092,50.7356185913],"type":"Point"}
}