{
  "type": "Feature",
  "properties": {
    "iso:country":"BE",
    "sg:address":"Wijgmaalbroek 21",
    "sg:city":"Leuven (wijgmaal)",
    "sg:classifiers":[
        {
            "category":"Real Estate",
            "subcategory":"Architect",
            "type":"Services"
        }
    ],
    "sg:phone":"+32 16 44 10 41",
    "sg:postcode":"3018",
    "sg:province":"Vlaams-Brabant",
    "wof:name":"Kuypers L",
    "wof:placetype":"venue"
},
  "geometry": {"coordinates":[4.7055649757,50.9280662537],"type":"Point"}
}