{
  "type": "Feature",
  "properties": {
    "iso:country":"BE",
    "sg:address":"Dorpsstraat 52",
    "sg:city":"Berlaar",
    "sg:classifiers":[
        {
            "category":"Fast Food",
            "type":"Food & Drink"
        }
    ],
    "sg:phone":"+32 3 482 25 22",
    "sg:postcode":"2590",
    "sg:province":"Antwerpen",
    "sg:tags":[
        "\u00c0",
        "restaurants",
        "emporter",
        "restaurant"
    ],
    "wof:name":"Long Sing Lau",
    "wof:placetype":"venue"
},
  "geometry": {"coordinates":[4.6533350945,51.117477417],"type":"Point"}
}