{
  "type": "Feature",
  "properties": {
    "addr:full":"Postelweg 21 Balen Antwerpen 2490",
    "addr:housenumber":"21",
    "addr:postcode":"2490",
    "addr:street":"Postelweg",
    "iso:country":"BE",
    "sg:address":"Postelweg 21",
    "sg:city":"Balen",
    "sg:orig_category":"V\u00e9hicules automobiles",
    "sg:phone":"+32 14 81 02 21",
    "sg:postcode":"2490",
    "sg:province":"Antwerpen",
    "wof:name":"Andre",
    "wof:placetype":"venue"
},
  "geometry": {"coordinates":[5.1811909676,51.1961898804],"type":"Point"}
}