{
  "type": "Feature",
  "properties": {
    "iso:country":"BE",
    "sg:address":"Casterstraat 9",
    "sg:city":"Hasselt",
    "sg:orig_category":"Boucheries",
    "sg:phone":"+32 11 22 04 90",
    "sg:postcode":"3500",
    "sg:province":"Limburg",
    "wof:name":"Budgetslager",
    "wof:placetype":"venue"
},
  "geometry": {"coordinates":[5.3496470451,50.9292907715],"type":"Point"}
}