{
  "type": "Feature",
  "properties": {
    "addr:full":"Chemin Tribouriau 97 Ath Hainaut 7822",
    "addr:housenumber":"97",
    "addr:postcode":"7822",
    "addr:street":"Chemin Tribouriau",
    "iso:country":"BE",
    "sg:address":"Chemin Tribouriau 97",
    "sg:city":"Ath",
    "sg:orig_category":"Eleveurs de bovins",
    "sg:phone":"+32 68 28 39 52",
    "sg:postcode":"7822",
    "sg:province":"Hainaut",
    "wof:name":"Desire Vandeguste",
    "wof:placetype":"venue"
},
  "geometry": {"coordinates":[3.8452620506,50.6482391357],"type":"Point"}
}