{
  "type": "Feature",
  "properties": {
    "addr:full":"Walleken 15 Wetteren Oost-Vlaanderen 9230",
    "addr:housenumber":"15",
    "addr:postcode":"9230",
    "addr:street":"Walleken",
    "iso:country":"BE",
    "sg:address":"Walleken 15",
    "sg:city":"Wetteren",
    "sg:orig_category":"Boekhouders",
    "sg:phone":"+32 9 366 24 41",
    "sg:postcode":"9230",
    "sg:province":"Oost-Vlaanderen",
    "wof:name":"Christiane De Smet",
    "wof:placetype":"venue"
},
  "geometry": {"coordinates":[3.8814771175,51.0176239014],"type":"Point"}
}