{
  "type": "Feature",
  "properties": {
    "addr:full":"Wippelgemdorp 48 Evergem Oost-Vlaanderen 9940",
    "addr:housenumber":"48",
    "addr:postcode":"9940",
    "addr:street":"Wippelgemdorp;Oost-Vlaanderen",
    "iso:country":"BE",
    "sg:address":"Wippelgemdorp 48",
    "sg:city":"Evergem",
    "sg:orig_category":"V\u00e9los. Motos",
    "sg:phone":"+32 9 357 62 35",
    "sg:postcode":"9940",
    "sg:province":"Oost-Vlaanderen",
    "wof:name":"Marc Van Hecke",
    "wof:placetype":"venue"
},
  "geometry": {"coordinates":[3.7316761017,51.142868042],"type":"Point"}
}