{
  "type": "Feature",
  "properties": {
    "iso:country":"BE",
    "sg:address":"Hofakkerstraat 80",
    "sg:city":"Gent",
    "sg:orig_category":"Loodgieterij, verwarming and sanitaire installaties",
    "sg:phone":"+32 475 31 56 00",
    "sg:postcode":"9052",
    "sg:province":"Oost-Vlaanderen",
    "wof:name":"De Tollenaere Francis",
    "wof:placetype":"venue"
},
  "geometry": {"coordinates":[3.7167270184,51.0002937317],"type":"Point"}
}