{
  "type": "Feature",
  "properties": {
    "addr:full":"Hovenstraat 12 Hasselt Limburg 3500",
    "addr:housenumber":"12",
    "addr:postcode":"3500",
    "addr:street":"Hovenstraat",
    "iso:country":"BE",
    "sg:address":"Hovenstraat 12",
    "sg:city":"Hasselt",
    "sg:orig_category":"Woningbouw",
    "sg:phone":"+32 11 22 15 21",
    "sg:postcode":"3500",
    "sg:province":"Limburg",
    "wof:name":"M En R Partners",
    "wof:placetype":"venue"
},
  "geometry": {"coordinates":[5.3405938148,50.9347801208],"type":"Point"}
}