{
  "type": "Feature",
  "properties": {
    "addr:full":"Wouwersstraat 6 Schilde ('s Gravenwezel) Antwerpen 2970",
    "addr:housenumber":"6",
    "addr:postcode":"2970",
    "addr:street":"Wouwersstraat;S",
    "iso:country":"BE",
    "sg:address":"Wouwersstraat 6",
    "sg:city":"Schilde ('s Gravenwezel)",
    "sg:classifiers":[
        {
            "category":"Building & Trades",
            "subcategory":"Cleaning & Sanitation",
            "type":"Services"
        }
    ],
    "sg:phone":"+32 476 77 85 00",
    "sg:postcode":"2970",
    "sg:province":"Antwerpen",
    "sg:tags":[
        "equipment",
        "industrial",
        "maintenance"
    ],
    "wof:name":"Advanced Technologies Europe",
    "wof:placetype":"venue"
},
  "geometry": {"coordinates":[4.5461959839,51.26770401],"type":"Point"}
}