{
  "type": "Feature",
  "properties": {
    "addr:full":"Avenue Du 4 Mai 28 Lasne Brabant Wallon 1380",
    "addr:housenumber":"28",
    "addr:postcode":"1380",
    "addr:street":"Avenue Du 4 Mai",
    "iso:country":"BE",
    "sg:address":"Avenue Du 4 Mai 28",
    "sg:city":"Lasne",
    "sg:orig_category":"Woningbouw",
    "sg:phone":"+32 2 654 09 62",
    "sg:postcode":"1380",
    "sg:province":"Brabant Wallon",
    "wof:name":"A.g. Construct",
    "wof:placetype":"venue"
},
  "geometry": {"coordinates":[4.483235836,50.6850166321],"type":"Point"}
}