{
  "type": "Feature",
  "properties": {
    "addr:full":"Brusselsesteenweg 441 Melle Oost-Vlaanderen 9090",
    "addr:housenumber":"441",
    "addr:postcode":"9090",
    "addr:street":"Brusselsesteenweg",
    "iso:country":"BE",
    "sg:address":"Brusselsesteenweg 441",
    "sg:city":"Melle",
    "sg:orig_category":"Installation \u00e9lectrique r\u00e9sidentielle. Installation \u00e9lectrique industrielle",
    "sg:phone":"+32 9 252 10 80",
    "sg:postcode":"9090",
    "sg:province":"Oost-Vlaanderen",
    "wof:name":"Quintiens",
    "wof:placetype":"venue"
},
  "geometry": {"coordinates":[3.8086578846,50.9993629456],"type":"Point"}
}