{
  "type": "Feature",
  "properties": {
    "addr:full":"Hoogstr 81 Waasmunster Oost-Vlaanderen 9250",
    "addr:housenumber":"81",
    "addr:postcode":"9250",
    "addr:street":"Hoogstr",
    "iso:country":"BE",
    "sg:address":"Hoogstr 81",
    "sg:city":"Waasmunster",
    "sg:orig_category":"Kapsalons",
    "sg:phone":"+32 52 46 15 74",
    "sg:postcode":"9250",
    "sg:province":"Oost-Vlaanderen",
    "wof:name":"Figaro",
    "wof:placetype":"venue"
},
  "geometry": {"coordinates":[4.0881490707,51.111076355],"type":"Point"}
}