{
  "type": "Feature",
  "properties": {
    "addr:full":"Rue De L'h\u00f4tel Des Monnaies 74 Bruxelles (saint-gilles) Bruxelles-Capitale 1060",
    "addr:housenumber":"74",
    "addr:postcode":"1060",
    "addr:street":"Rue De L'Ho;Des Monnaies",
    "iso:country":"BE",
    "sg:address":"Rue De L'h\u00f4tel Des Monnaies 74",
    "sg:city":"Bruxelles (saint-gilles)",
    "sg:classifiers":[
        {
            "category":"Autos & Motor Vehicles",
            "subcategory":"Motorcycle Sales",
            "type":"Retail Goods"
        }
    ],
    "sg:phone":"+32 2 537 96 43",
    "sg:postcode":"1060",
    "sg:province":"Bruxelles-Capitale",
    "sg:tags":[
        "automobile",
        "brake",
        "-",
        "truck"
    ],
    "wof:name":"Remetafrein Sprl",
    "wof:placetype":"venue"
},
  "geometry": {"coordinates":[4.3484158516,50.8307762146],"type":"Point"}
}