{
  "type": "Feature",
  "properties": {
    "addr:full":"9185 Wachtebeke Oost-Vlaanderen 9185",
    "addr:postcode":"9185;9185",
    "iso:country":"BE",
    "sg:address":"9185",
    "sg:city":"Wachtebeke",
    "sg:orig_category":"Pharmaciens",
    "sg:phone":"+32 900 10 500",
    "sg:postcode":"9185",
    "sg:province":"Oost-Vlaanderen",
    "wof:name":"Pharmacies De Garde",
    "wof:placetype":"venue"
},
  "geometry": {"coordinates":[3.8552510738,51.1666183472],"type":"Point"}
}