{
  "type": "Feature",
  "properties": {
    "iso:country":"BE",
    "sg:address":"Brusselsesteenweg 463",
    "sg:city":"Zemst",
    "sg:orig_category":"V\u00eatements",
    "sg:phone":"+32 2 251 40 49",
    "sg:postcode":"1980",
    "sg:province":"Vlaams-Brabant",
    "wof:name":"Snickers Original",
    "wof:placetype":"venue"
},
  "geometry": {"coordinates":[4.4552798271,50.9738502502],"type":"Point"}
}