{
  "type": "Feature",
  "properties": {
    "iso:country":"BE",
    "sg:address":"Rue Del\u00b4vaux 34",
    "sg:city":"Gembloux",
    "sg:orig_category":"V\u00e9hicules automobiles. Entretien and r\u00e9parations de voitures",
    "sg:phone":"+32 81 64 02 57",
    "sg:postcode":"5031",
    "sg:province":"Namur",
    "wof:name":"Garage Simonet & Fils",
    "wof:placetype":"venue"
},
  "geometry": {"coordinates":[4.7734627724,50.5832595825],"type":"Point"}
}