{
  "type": "Feature",
  "properties": {
    "addr:full":"Maalbroekstraat 16 Sint-lievens-houtem Oost-Vlaanderen 9520",
    "addr:housenumber":"16",
    "addr:postcode":"9520",
    "addr:street":"Maalbroekstraat;Oost-Vlaanderen",
    "iso:country":"BE",
    "sg:address":"Maalbroekstraat 16",
    "sg:city":"Sint-lievens-houtem",
    "sg:classifiers":[
        {
            "category":"Food & Beverages",
            "subcategory":"Fruits & Vegetables",
            "type":"Retail Goods"
        }
    ],
    "sg:phone":"+32 9 362 77 15",
    "sg:postcode":"9520",
    "sg:province":"Oost-Vlaanderen",
    "sg:tags":[
        "l\u00e9gumes"
    ],
    "wof:name":"Hubert Van Gysegem",
    "wof:placetype":"venue"
},
  "geometry": {"coordinates":[3.8577699661,50.9411315918],"type":"Point"}
}