{
  "type": "Feature",
  "properties": {
    "iso:country":"BE",
    "sg:address":"Rue Du Bempt 26",
    "sg:city":"Drogenbos",
    "sg:classifiers":[
        {
            "category":"Sports & Exercise",
            "subcategory":"Stables",
            "type":"Entertainment"
        }
    ],
    "sg:phone":"+32 2 378 38 30",
    "sg:postcode":"1620",
    "sg:province":"Vlaams-Brabant",
    "sg:tags":[
        "riding",
        "school"
    ],
    "wof:name":"Manege Astragale",
    "wof:placetype":"venue"
},
  "geometry": {"coordinates":[4.312183857,50.7935714722],"type":"Point"}
}