{
  "type": "Feature",
  "properties": {
    "iso:country":"BE",
    "sg:address":"Rue D'angoussart 53",
    "sg:city":"Waver",
    "sg:orig_category":"Ordinateurs and \u00e9quipement informatique",
    "sg:phone":"+32 10 41 90 51",
    "sg:postcode":"1301",
    "sg:province":"Brabant Wallon",
    "wof:name":"Micro Solution",
    "wof:placetype":"venue"
},
  "geometry": {"coordinates":[4.5666770935,50.7204551697],"type":"Point"}
}