{
  "type": "Feature",
  "properties": {
    "iso:country":"BE",
    "sg:address":"Rue Du Bon Pasteur 5054",
    "sg:city":"Bruxelles",
    "sg:classifiers":[
        {
            "category":"Professional",
            "subcategory":"Advertising",
            "type":"Services"
        }
    ],
    "sg:phone":"+32 2 240 44 11",
    "sg:postcode":"1140",
    "sg:province":"Bruxelles-Capitale",
    "sg:tags":[
        "information",
        "medium",
        "communication"
    ],
    "wof:name":"Inter Offset Sprl",
    "wof:placetype":"venue"
},
  "geometry": {"coordinates":[4.4026999474,50.8808708191],"type":"Point"}
}