{
  "type": "Feature",
  "properties": {
    "addr:full":"Chauss\u00e9e De Mons 70 Le Roeulx (thieu) Hainaut 7070",
    "addr:housenumber":"70",
    "addr:postcode":"7070",
    "addr:street":"Chausse\u0301E De Mons",
    "iso:country":"BE",
    "sg:address":"Chauss\u00e9e De Mons 70",
    "sg:city":"Le Roeulx (thieu)",
    "sg:classifiers":[
        {
            "category":"Retail",
            "subcategory":"Veterinary Services",
            "type":"Services"
        }
    ],
    "sg:phone":"+32 67 44 44 67",
    "sg:postcode":"7070",
    "sg:province":"Hainaut",
    "sg:tags":[
        "veterinarian"
    ],
    "wof:name":"Jacobs V",
    "wof:placetype":"venue"
},
  "geometry": {"coordinates":[4.1061401367,50.501750946],"type":"Point"}
}