{
  "type": "Feature",
  "properties": {
    "iso:country":"BE",
    "sg:address":"Rue De S\u00e9bastopol 25",
    "sg:city":"Bruxelles (anderlecht)",
    "sg:classifiers":[
        {
            "category":"Banks & Credit Unions",
            "subcategory":"Investment Brokerage",
            "type":"Services"
        }
    ],
    "sg:phone":"+32 2 520 35 22",
    "sg:postcode":"1070",
    "sg:province":"Bruxelles-Capitale",
    "sg:tags":[
        "printing",
        "-"
    ],
    "wof:name":"Callebaut Sprl",
    "wof:placetype":"venue"
},
  "geometry": {"coordinates":[4.3134078979,50.8392066956],"type":"Point"}
}