{
  "type": "Feature",
  "properties": {
    "addr:full":"Pastorijstraat 15 Evergem (ertvelde) Oost-Vlaanderen 9940",
    "addr:housenumber":"15",
    "addr:postcode":"9940",
    "addr:street":"Pastorijstraat;Ertvelde Oost-Vlaanderen",
    "iso:country":"BE",
    "sg:address":"Pastorijstraat 15",
    "sg:city":"Evergem (ertvelde)",
    "sg:classifiers":[
        {
            "category":"Freight",
            "type":"Transportation"
        }
    ],
    "sg:phone":"+32 9 344 50 96",
    "sg:postcode":"9940",
    "sg:province":"Oost-Vlaanderen",
    "sg:tags":[
        "-",
        "transport"
    ],
    "wof:name":"Van Thuyne",
    "wof:placetype":"venue"
},
  "geometry": {"coordinates":[3.751003027,51.1790733337],"type":"Point"}
}