{
  "type": "Feature",
  "properties": {
    "iso:country":"BE",
    "sg:address":"Place Du March\u00e9 20",
    "sg:city":"Li\u00e8ge 1",
    "sg:classifiers":[
        {
            "category":"Bakery",
            "type":"Food & Drink"
        }
    ],
    "sg:phone":"+32 4 222 03 22",
    "sg:postcode":"4000",
    "sg:province":"Li\u00e8ge",
    "sg:tags":[
        "confectioner",
        "baker"
    ],
    "wof:name":"Matin Li\u00e9geois (le)",
    "wof:placetype":"venue"
},
  "geometry": {"coordinates":[5.5765371323,50.6456069946],"type":"Point"}
}