{
  "type": "Feature",
  "properties": {
    "addr:full":"Rue Destriveaux 9 Li\u00e8ge 1 Li\u00e8ge 4000",
    "addr:housenumber":"9;1",
    "addr:postcode":"4000",
    "addr:street":"Rue Destriveaux",
    "iso:country":"BE",
    "sg:address":"Rue Destriveaux 9",
    "sg:city":"Li\u00e8ge 1",
    "sg:classifiers":[
        {
            "category":"Health Services",
            "subcategory":"Doctor",
            "type":"Services"
        }
    ],
    "sg:phone":"+32 4 252 50 25",
    "sg:postcode":"4000",
    "sg:province":"Li\u00e8ge",
    "sg:tags":[
        "medicinephysicians",
        "surgeon"
    ],
    "wof:name":"Lechanteur M",
    "wof:placetype":"venue"
},
  "geometry": {"coordinates":[5.5576457977,50.6346855164],"type":"Point"}
}