{
  "type": "Feature",
  "properties": {
    "iso:country":"BE",
    "sg:address":"Rue De La Gare 24",
    "sg:city":"Couvin",
    "sg:classifiers":[
        {
            "category":"Shopping",
            "subcategory":"Pets & Pet Supplies",
            "type":"Retail Goods"
        }
    ],
    "sg:phone":"+32 60 21 11 71",
    "sg:postcode":"5660",
    "sg:province":"Namur",
    "sg:tags":[
        "aquarium",
        "accessory"
    ],
    "wof:name":"Afriquarium",
    "wof:placetype":"venue"
},
  "geometry": {"coordinates":[4.4922919273,50.0551834106],"type":"Point"}
}