{
  "type": "Feature",
  "properties": {
    "addr:full":"Stationsstraat 175 Waregem West-Vlaanderen 8790",
    "addr:housenumber":"175",
    "addr:postcode":"8790",
    "addr:street":"Stationsstraat",
    "iso:country":"BE",
    "sg:address":"Stationsstraat 175",
    "sg:city":"Waregem",
    "sg:orig_category":"M\u00e9decines alternatives",
    "sg:phone":"+32 56 60 28 04",
    "sg:postcode":"8790",
    "sg:province":"West-Vlaanderen",
    "wof:name":"R.c. Becue",
    "wof:placetype":"venue"
},
  "geometry": {"coordinates":[3.4270679951,50.8919906616],"type":"Point"}
}