{
  "type": "Feature",
  "properties": {
    "iso:country":"BE",
    "sg:address":"Rue Du Try D'andoy 18",
    "sg:city":"Yvoir (durnal)",
    "sg:classifiers":[
        {
            "category":"Banks & Credit Unions",
            "subcategory":"Investment Brokerage",
            "type":"Services"
        }
    ],
    "sg:phone":"+32 83 69 95 99",
    "sg:postcode":"5530",
    "sg:province":"Namur",
    "sg:tags":[
        "repair",
        "-",
        "installation",
        "sanitary",
        "article"
    ],
    "wof:name":"Albert M",
    "wof:placetype":"venue"
},
  "geometry": {"coordinates":[4.9860029221,50.3362007141],"type":"Point"}
}