{
  "type": "Feature",
  "properties": {
    "iso:country":"BE",
    "sg:address":"Biezenstraat 19",
    "sg:city":"Roeselare",
    "sg:classifiers":[
        {
            "category":"Professional",
            "subcategory":"Management & Consulting",
            "type":"Services"
        }
    ],
    "sg:phone":"+32 51 22 75 13",
    "sg:postcode":"8800",
    "sg:province":"West-Vlaanderen",
    "sg:tags":[
        "consultant"
    ],
    "wof:name":"F Goos Advies",
    "wof:placetype":"venue"
},
  "geometry": {"coordinates":[3.1055440903,50.9598579407],"type":"Point"}
}