{
  "type": "Feature",
  "properties": {
    "iso:country":"BE",
    "sg:address":"Rue De L'arbre-courte-joie 330",
    "sg:city":"Li\u00e8ge 1 (rocourt)",
    "sg:classifiers":[
        {
            "category":"Travel",
            "subcategory":"Hotels & Motels",
            "type":"Entertainment"
        }
    ],
    "sg:phone":"+32 4 247 47 51",
    "sg:postcode":"4000",
    "sg:province":"Li\u00e8ge",
    "wof:name":"Premi\u00e8re Classe H\u00f4tel",
    "wof:placetype":"venue"
},
  "geometry": {"coordinates":[5.5407671928,50.6696472168],"type":"Point"}
}