{
  "type": "Feature",
  "properties": {
    "iso:country":"BE",
    "sg:address":"Goorstraat 43",
    "sg:city":"Schilde",
    "sg:classifiers":[
        {
            "category":"Food & Beverages",
            "subcategory":"Specialty",
            "type":"Retail Goods"
        }
    ],
    "sg:phone":"+32 3 383 07 82",
    "sg:postcode":"2970",
    "sg:province":"Antwerpen",
    "sg:tags":[
        "health",
        "dietary",
        "-",
        "biological"
    ],
    "wof:name":"Dobbelhoeve",
    "wof:placetype":"venue"
},
  "geometry": {"coordinates":[4.6073851585,51.228969574],"type":"Point"}
}