{
  "type": "Feature",
  "properties": {
    "addr:full":"Groenveldstraat 13-102 Leuven (heverlee) Vlaams-Brabant 3001",
    "addr:postcode":"13-102;3001",
    "addr:street":"Groenveldstraat",
    "iso:country":"BE",
    "sg:address":"Groenveldstraat 13-102",
    "sg:city":"Leuven (heverlee)",
    "sg:classifiers":[
        {
            "category":"Education",
            "subcategory":"Special Training",
            "type":"Public Place"
        }
    ],
    "sg:phone":"+32 16 29 91 15",
    "sg:postcode":"3001",
    "sg:province":"Vlaams-Brabant",
    "sg:tags":[
        "-",
        "processing",
        "data"
    ],
    "wof:name":"Cio Training Center",
    "wof:placetype":"venue"
},
  "geometry": {"coordinates":[4.6836571693,50.8740997314],"type":"Point"}
}