{
  "type": "Feature",
  "properties": {
    "addr:full":"Kokstraat 4 Aalst (moorsel) Oost-Vlaanderen 9310",
    "addr:housenumber":"4",
    "addr:postcode":"9310",
    "addr:street":"Kokstraat;Moorsel Oost-Vlaanderen",
    "iso:country":"BE",
    "sg:address":"Kokstraat 4",
    "sg:city":"Aalst (moorsel)",
    "sg:classifiers":[
        {
            "category":"Health Services",
            "subcategory":"Nursing And Care Facility",
            "type":"Services"
        }
    ],
    "sg:phone":"+32 53 77 97 79",
    "sg:postcode":"9310",
    "sg:province":"Oost-Vlaanderen",
    "sg:tags":[
        "home"
    ],
    "wof:name":"De Block M",
    "wof:placetype":"venue"
},
  "geometry": {"coordinates":[4.1086740494,50.9601402283],"type":"Point"}
}