{
  "type": "Feature",
  "properties": {
    "addr:full":"Rue Kessels 77 Schaarbeek/schaerbeek Bruxelles-Capitale 1030",
    "addr:housenumber":"77",
    "addr:postcode":"1030",
    "addr:street":"Rue Kessels",
    "iso:country":"BE",
    "sg:address":"Rue Kessels 77",
    "sg:city":"Schaarbeek/schaerbeek",
    "sg:orig_category":"Epiceries",
    "sg:phone":"+32 2 215 33 63",
    "sg:postcode":"1030",
    "sg:province":"Bruxelles-Capitale",
    "wof:name":"Leonardus Braeken",
    "wof:placetype":"venue"
},
  "geometry": {"coordinates":[4.377093792,50.863243103],"type":"Point"}
}