{
  "type": "Feature",
  "properties": {
    "addr:full":"Chauss\u00c9e De Namur 24 Incourt Brabant Wallon 1315",
    "addr:housenumber":"24",
    "addr:postcode":"1315",
    "addr:street":"Chausse\u0301E De Namur",
    "iso:country":"BE",
    "sg:address":"Chauss\u00c9e De Namur 24",
    "sg:city":"Incourt",
    "sg:orig_category":"Verhuur cateringmateriaal and evenementuitrusting Winkelinrichting and handelsuitrusting Gh",
    "sg:phone":"+32 10 84 11 56",
    "sg:postcode":"1315",
    "sg:province":"Brabant Wallon",
    "wof:name":"Godefroid Loctaion",
    "wof:placetype":"venue"
},
  "geometry": {"coordinates":[4.8042221069,50.6948051453],"type":"Point"}
}