{
  "type": "Feature",
  "properties": {
    "addr:full":"Antwerpsestraat 91 Boom Antwerpen 2850",
    "addr:housenumber":"91",
    "addr:postcode":"2850",
    "addr:street":"Antwerpsestraat",
    "iso:country":"BE",
    "sg:address":"Antwerpsestraat 91",
    "sg:city":"Boom",
    "sg:classifiers":[
        {
            "category":"Bars & Pubs",
            "type":"Food & Drink"
        }
    ],
    "sg:phone":"+32 3 844 34 24",
    "sg:postcode":"2850",
    "sg:province":"Antwerpen",
    "sg:tags":[
        "tavern"
    ],
    "wof:name":"Obelisk",
    "wof:placetype":"venue"
},
  "geometry": {"coordinates":[4.3652057648,51.0882644653],"type":"Point"}
}