{
  "type": "Feature",
  "properties": {
    "iso:country":"BE",
    "sg:address":"Rue Massart 2ba",
    "sg:city":"Court-saint-etienne",
    "sg:orig_category":"Plaatsen van vloer- and muurbekleding Schilders",
    "sg:phone":"+32 10 61 48 40",
    "sg:postcode":"1490",
    "sg:province":"Brabant Wallon",
    "wof:name":"Alain Foret",
    "wof:placetype":"venue"
},
  "geometry": {"coordinates":[4.5579271317,50.6161956787],"type":"Point"}
}