{
  "type": "Feature",
  "properties": {
    "addr:full":"Rue D'arnelle 28 Chaumont-gistoux Brabant Wallon 1325",
    "addr:housenumber":"28",
    "addr:postcode":"1325",
    "addr:street":"Rue D'Arnelle",
    "iso:country":"BE",
    "sg:address":"Rue D'arnelle 28",
    "sg:city":"Chaumont-gistoux",
    "sg:orig_category":"Woningbouw",
    "sg:phone":"+32 10 88 91 55",
    "sg:postcode":"1325",
    "sg:province":"Brabant Wallon",
    "wof:name":"Charpanterre",
    "wof:placetype":"venue"
},
  "geometry": {"coordinates":[4.7483839989,50.6951293945],"type":"Point"}
}