{
  "type": "Feature",
  "properties": {
    "iso:country":"BE",
    "sg:address":"Gentse Steenweg 287",
    "sg:city":"Zottegem",
    "sg:orig_category":"Dranken",
    "sg:phone":"+32 9 360 24 06",
    "sg:postcode":"9620",
    "sg:province":"Oost-Vlaanderen",
    "wof:name":"Rouckhout",
    "wof:placetype":"venue"
},
  "geometry": {"coordinates":[3.8307070732,50.8871269226],"type":"Point"}
}