{
  "type": "Feature",
  "properties": {
    "addr:full":"Veldkant 37 Kontich Antwerpen 2550",
    "addr:housenumber":"37",
    "addr:postcode":"2550",
    "addr:street":"Veldkant",
    "iso:country":"BE",
    "sg:address":"Veldkant 37",
    "sg:city":"Kontich",
    "sg:classifiers":[
        {
            "category":"Professional",
            "subcategory":"Management & Consulting",
            "type":"Services"
        }
    ],
    "sg:postcode":"2550",
    "sg:province":"Antwerpen",
    "sg:tags":[
        "consultant",
        "agency",
        "advertising"
    ],
    "wof:name":"Industrial Marketing System Nv",
    "wof:placetype":"venue"
},
  "geometry": {"coordinates":[4.4427628517,51.1410903931],"type":"Point"}
}