{
  "type": "Feature",
  "properties": {
    "iso:country":"BE",
    "sg:address":"Fazantenlaan 39",
    "sg:city":"Overijse",
    "sg:classifiers":[
        {
            "category":"Social Services",
            "subcategory":"Job Training",
            "type":"Services"
        }
    ],
    "sg:phone":"+32 2 688 23 11",
    "sg:postcode":"3090",
    "sg:province":"Vlaams-Brabant",
    "sg:tags":[
        "personnel"
    ],
    "wof:name":"Feux D'opale",
    "wof:placetype":"venue"
},
  "geometry": {"coordinates":[4.4963130951,50.7413101196],"type":"Point"}
}