{
  "type": "Feature",
  "properties": {
    "addr:full":"Peutiesesteenweg 113b Machelen Vlaams-Brabant 1830",
    "addr:housenumber":"113b",
    "addr:postcode":"1830",
    "addr:street":"Peutiesesteenweg",
    "iso:country":"BE",
    "sg:address":"Peutiesesteenweg 113b",
    "sg:city":"Machelen",
    "sg:classifiers":[
        {
            "category":"Home & Garden",
            "subcategory":"Building Materials",
            "type":"Retail Goods"
        }
    ],
    "sg:phone":"+32 2 253 87 72",
    "sg:postcode":"1830",
    "sg:province":"Vlaams-Brabant",
    "sg:tags":[
        "insect",
        "screen"
    ],
    "wof:name":"Feneko",
    "wof:placetype":"venue"
},
  "geometry": {"coordinates":[4.4506621361,50.9206809998],"type":"Point"}
}