{
  "type": "Feature",
  "properties": {
    "addr:full":"Chaussee De Liege 41 Marche-en-famenne Luxembourg 6900",
    "addr:housenumber":"41",
    "addr:postcode":"6900",
    "addr:street":"Chaussee De Liege",
    "iso:country":"BE",
    "sg:address":"Chaussee De Liege 41",
    "sg:city":"Marche-en-famenne",
    "sg:orig_category":"Hypermarkten Supermarkten Telecommunicatieapparaten",
    "sg:phone":"+32 84 32 07 11",
    "sg:postcode":"6900",
    "sg:province":"Luxembourg",
    "wof:name":"Carrefour - Maxitec",
    "wof:placetype":"venue"
},
  "geometry": {"coordinates":[5.3446359634,50.2340354919],"type":"Point"}
}