{
  "type": "Feature",
  "properties": {
    "iso:country":"BE",
    "sg:address":"Grand Place 67b",
    "sg:city":"Mons (grand)",
    "sg:classifiers":[
        {
            "category":"Fast Food",
            "type":"Food & Drink"
        }
    ],
    "sg:phone":"+32 65 33 42 77",
    "sg:postcode":"7033",
    "sg:province":"Hainaut",
    "sg:tags":[
        "\u00c0",
        "emporter",
        "restaurants"
    ],
    "wof:name":"Le R\u00c9gal",
    "wof:placetype":"venue"
},
  "geometry": {"coordinates":[3.9253261089,50.4366378784],"type":"Point"}
}