{
  "type": "Feature",
  "properties": {
    "iso:country":"BE",
    "sg:address":"Rue De Merbes 49",
    "sg:city":"Merbes-le-ch\u00e2teau",
    "sg:classifiers":[
        {
            "category":"Building & Trades",
            "subcategory":"Electrical",
            "type":"Services"
        }
    ],
    "sg:phone":"+32 478 92 18 10",
    "sg:postcode":"6567",
    "sg:province":"Hainaut",
    "sg:tags":[
        "electric",
        "-",
        "housewiring",
        "contractor"
    ],
    "wof:name":"Paucot Ch",
    "wof:placetype":"venue"
},
  "geometry": {"coordinates":[4.1710500717,50.3217582703],"type":"Point"}
}