{
  "type": "Feature",
  "properties": {
    "addr:full":"Rue De Tubize 137 Braine-le-ch\u00e2teau Brabant Wallon 1440",
    "addr:housenumber":"137",
    "addr:postcode":"1440",
    "addr:street":"Rue De Tubize",
    "iso:country":"BE",
    "sg:address":"Rue De Tubize 137",
    "sg:city":"Braine-le-ch\u00e2teau",
    "sg:orig_category":"Numbered Tickets, Also On Rolls",
    "sg:phone":"+32 2 366 99 60",
    "sg:postcode":"1440",
    "sg:province":"Brabant Wallon",
    "wof:name":"Imprimerie Chalot S.a.",
    "wof:placetype":"venue"
},
  "geometry": {"coordinates":[4.2492070198,50.6804237366],"type":"Point"}
}