{
  "type": "Feature",
  "properties": {
    "iso:country":"BE",
    "sg:address":"Italielei 197",
    "sg:city":"Antwerpen",
    "sg:classifiers":[
        {
            "category":"Building & Trades",
            "subcategory":"Plumbing",
            "type":"Services"
        }
    ],
    "sg:phone":"+32 3 232 56 89",
    "sg:postcode":"2000",
    "sg:province":"Antwerpen",
    "sg:tags":[
        "diver",
        "commerce",
        "gr",
        "pour",
        "equipement"
    ],
    "wof:name":"Pro-duo",
    "wof:placetype":"venue"
},
  "geometry": {"coordinates":[4.4166941643,51.2222747803],"type":"Point"}
}