{
  "type": "Feature",
  "properties": {
    "addr:full":"Avenue Mutsaard 72 Box 51 Bruxelles Bruxelles-Capitale 1020",
    "addr:housenumber":"72 box 51",
    "addr:postcode":"1020",
    "addr:street":"Avenue Mutsaard",
    "iso:country":"BE",
    "sg:address":"Avenue Mutsaard 72 Box 51",
    "sg:city":"Bruxelles",
    "sg:classifiers":[
        {
            "category":"Home & Garden",
            "subcategory":"Carpets & Floor Coverings",
            "type":"Retail Goods"
        }
    ],
    "sg:phone":"+32 2 268 75 00",
    "sg:postcode":"1020",
    "sg:province":"Bruxelles-Capitale",
    "sg:tags":[
        "repair",
        "stone",
        "natural",
        "-",
        "mainten",
        "marble"
    ],
    "wof:name":"Barbier & Fils Sprl",
    "wof:placetype":"venue"
},
  "geometry": {"coordinates":[4.3568987846,50.8984031677],"type":"Point"}
}