{
  "type": "Feature",
  "properties": {
    "addr:full":"Spelemanstraat 48 Knokke-heist West-Vlaanderen 8301",
    "addr:housenumber":"48",
    "addr:postcode":"8301",
    "addr:street":"Spelemanstraat",
    "iso:country":"BE",
    "sg:address":"Spelemanstraat 48",
    "sg:city":"Knokke-heist",
    "sg:classifiers":[
        {
            "category":"Arena",
            "subcategory":"Sports Club",
            "type":"Entertainment"
        }
    ],
    "sg:phone":"+32 50 51 36 54",
    "sg:postcode":"8301",
    "sg:province":"West-Vlaanderen",
    "sg:tags":[
        "de"
    ],
    "wof:name":"Klein Maar Moedig",
    "wof:placetype":"venue"
},
  "geometry": {"coordinates":[3.2506959438,51.3175582886],"type":"Point"}
}