{
  "type": "Feature",
  "properties": {
    "iso:country":"BE",
    "sg:address":"Boerenstraat 81",
    "sg:city":"Etterbeek/etterbeek",
    "sg:orig_category":"Voertuigen",
    "sg:phone":"+32 2 733 08 03",
    "sg:postcode":"1040",
    "sg:province":"Bruxelles-Capitale",
    "wof:name":"S.l. Motor",
    "wof:placetype":"venue"
},
  "geometry": {"coordinates":[4.3944330215,50.8348197937],"type":"Point"}
}