{
  "type": "Feature",
  "properties": {
    "iso:country":"BE",
    "sg:address":"De Moranvillestraat 6",
    "sg:city":"Jette",
    "sg:orig_category":"Gespecialiseerde niet-residenti\u00eble bouw Goederenvervoer over de weg Metalen constructies Fab",
    "sg:phone":"+32 2 420 97 65",
    "sg:postcode":"1090",
    "sg:province":"Bruxelles-Capitale",
    "wof:name":"Tecsa",
    "wof:placetype":"venue"
},
  "geometry": {"coordinates":[4.3298721313,50.8681755066],"type":"Point"}
}