{
  "type": "Feature",
  "properties": {
    "addr:full":"Rue De La Dime 11 Paliseul Luxembourg 6853",
    "addr:housenumber":"11",
    "addr:postcode":"6853",
    "addr:street":"Rue De La Dime",
    "iso:country":"BE",
    "sg:address":"Rue De La Dime 11",
    "sg:city":"Paliseul",
    "sg:orig_category":"Eleveurs de bovins",
    "sg:phone":"+32 61 53 36 46",
    "sg:postcode":"6853",
    "sg:province":"Luxembourg",
    "wof:name":"Fernand Prignon",
    "wof:placetype":"venue"
},
  "geometry": {"coordinates":[5.1591701508,49.9163093567],"type":"Point"}
}