{
  "type": "Feature",
  "properties": {
    "addr:full":"Dokter Eduard Moreauxlaan 257 Oostende West-Vlaanderen 8400",
    "addr:housenumber":"257",
    "addr:postcode":"8400",
    "addr:street":"Dokter Eduard Moreauxlaan",
    "iso:country":"BE",
    "sg:address":"Dokter Eduard Moreauxlaan 257",
    "sg:city":"Oostende",
    "sg:classifiers":[
        {
            "category":"Travel",
            "subcategory":"Resort",
            "type":"Entertainment"
        }
    ],
    "sg:phone":"+32 59 32 34 79",
    "sg:postcode":"8400",
    "sg:province":"West-Vlaanderen",
    "sg:tags":[
        "rental",
        "accomodation",
        "holiday",
        "-"
    ],
    "wof:name":"The Candle",
    "wof:placetype":"venue"
},
  "geometry": {"coordinates":[2.941865921,51.224445343],"type":"Point"}
}