{
  "type": "Feature",
  "properties": {
    "iso:country":"BE",
    "sg:address":"Steenwinkelstraat 45",
    "sg:city":"Schelle",
    "sg:orig_category":"Kapsalons",
    "sg:phone":"+32 3 887 52 81",
    "sg:postcode":"2627",
    "sg:province":"Antwerpen",
    "wof:name":"Coiffure Hilda",
    "wof:placetype":"venue"
},
  "geometry": {"coordinates":[4.3417439461,51.1250228882],"type":"Point"}
}