{
  "type": "Feature",
  "properties": {
    "addr:full":"Duivenstraat 90 Wervik West-Vlaanderen 8940",
    "addr:housenumber":"90",
    "addr:postcode":"8940",
    "addr:street":"Duivenstraat",
    "iso:country":"BE",
    "sg:address":"Duivenstraat 90",
    "sg:city":"Wervik",
    "sg:classifiers":[
        {
            "category":"Insurance",
            "subcategory":"Life Insurance",
            "type":"Services"
        }
    ],
    "sg:phone":"+32 56 31 06 54",
    "sg:postcode":"8940",
    "sg:province":"West-Vlaanderen",
    "sg:tags":[
        "assurance"
    ],
    "wof:name":"P. Overbergh",
    "wof:placetype":"venue"
},
  "geometry": {"coordinates":[3.0395998955,50.7811279297],"type":"Point"}
}