{
  "type": "Feature",
  "properties": {
    "iso:country":"BE",
    "sg:address":"Onze-lieve-vrouwstraat 29",
    "sg:city":"Hoeselt",
    "sg:classifiers":[
        {
            "category":"Home & Garden",
            "subcategory":"Building Materials",
            "type":"Retail Goods"
        }
    ],
    "sg:phone":"+32 89 49 24 76",
    "sg:postcode":"3730",
    "sg:province":"Limburg",
    "sg:tags":[
        "article",
        "-",
        "do-it-yourself"
    ],
    "wof:name":"Ghinique",
    "wof:placetype":"venue"
},
  "geometry": {"coordinates":[5.4918999672,50.8458633423],"type":"Point"}
}