{
  "type": "Feature",
  "properties": {
    "addr:full":"Grote Markt 34 Lier Antwerpen 2500",
    "addr:housenumber":"34",
    "addr:postcode":"2500",
    "addr:street":"Grote Markt",
    "iso:country":"BE",
    "sg:address":"Grote Markt 34",
    "sg:city":"Lier",
    "sg:orig_category":"Diverse kredietdiensten",
    "sg:postcode":"2500",
    "sg:province":"Antwerpen",
    "wof:name":"Bancontact-mister Cash",
    "wof:placetype":"venue"
},
  "geometry": {"coordinates":[4.5687952042,51.1309928894],"type":"Point"}
}