{
  "type": "Feature",
  "properties": {
    "iso:country":"BE",
    "sg:address":"Rue Victor Rousseau 45 Box 2",
    "sg:city":"Seneffe (feluy)",
    "sg:classifiers":[
        {
            "category":"Professional",
            "subcategory":"Business Services",
            "type":"Services"
        }
    ],
    "sg:postcode":"7181",
    "sg:province":"Hainaut",
    "sg:tags":[
        "firm"
    ],
    "wof:name":"Allinckx B",
    "wof:placetype":"venue"
},
  "geometry": {"coordinates":[4.2582211494,50.5633087158],"type":"Point"}
}