{
  "type": "Feature",
  "properties": {
    "addr:full":"Rue Canada 0 Theux Li\u00e8ge 4910",
    "addr:housenumber":"0",
    "addr:postcode":"4910",
    "addr:street":"Rue Canada",
    "iso:country":"BE",
    "sg:address":"Rue Canada 0",
    "sg:city":"Theux",
    "sg:classifiers":[
        {
            "category":"Cafe",
            "type":"Food & Drink"
        }
    ],
    "sg:phone":"+32 87 37 64 55",
    "sg:postcode":"4910",
    "sg:province":"Li\u00e8ge",
    "sg:tags":[
        "caf\u00e9s"
    ],
    "wof:name":"F.c. La Reid",
    "wof:placetype":"venue"
},
  "geometry": {"coordinates":[5.8063731194,50.4873428345],"type":"Point"}
}