{
  "type": "Feature",
  "properties": {
    "iso:country":"BE",
    "sg:address":"Rue De L'ommegang 66c",
    "sg:city":"Renaix",
    "sg:classifiers":[
        {
            "category":"Building & Trades",
            "subcategory":"Electrical",
            "type":"Services"
        }
    ],
    "sg:phone":"+32 55 21 12 99",
    "sg:postcode":"9600",
    "sg:province":"Oost-Vlaanderen",
    "sg:tags":[
        "electric",
        "-",
        "housewiring",
        "contractor"
    ],
    "wof:name":"De Rodder F",
    "wof:placetype":"venue"
},
  "geometry": {"coordinates":[3.6274590492,50.7416381836],"type":"Point"}
}