{
  "type": "Feature",
  "properties": {
    "addr:full":"Guldensporenlaan 62 Houthalen-helchteren Limburg 3530",
    "addr:housenumber":"62",
    "addr:postcode":"3530",
    "addr:street":"Guldensporenlaan",
    "iso:country":"BE",
    "sg:address":"Guldensporenlaan 62",
    "sg:city":"Houthalen-helchteren",
    "sg:orig_category":"Gespecialiseerde residenti\u00eble bouw",
    "sg:phone":"+32 11 60 10 94",
    "sg:postcode":"3530",
    "sg:province":"Limburg",
    "wof:name":"Ludo Thijs",
    "wof:placetype":"venue"
},
  "geometry": {"coordinates":[5.3655519485,51.0385398865],"type":"Point"}
}