{
  "type": "Feature",
  "properties": {
    "addr:full":"Boulevard Emile Devreux 22 Charleroi Hainaut 6000",
    "addr:housenumber":"22",
    "addr:postcode":"6000",
    "addr:street":"Boulevard Emile Devreux;Hainaut",
    "iso:country":"BE",
    "sg:address":"Boulevard Emile Devreux 22",
    "sg:city":"Charleroi",
    "sg:orig_category":"Avocats and conseillers juridiques",
    "sg:phone":"+32 71 20 10 60",
    "sg:postcode":"6000",
    "sg:province":"Hainaut",
    "wof:name":"E. Bernis",
    "wof:placetype":"venue"
},
  "geometry": {"coordinates":[4.4493989944,50.4077568054],"type":"Point"}
}