{
  "type": "Feature",
  "properties": {
    "iso:country":"BE",
    "sg:address":"Mellestraat 29",
    "sg:city":"Laarne",
    "sg:classifiers":[
        {
            "category":"Wholesale",
            "subcategory":"Plants",
            "type":"Manufacturing & Wholesale Goods"
        }
    ],
    "sg:phone":"+32 9 230 96 29",
    "sg:postcode":"9270",
    "sg:province":"Oost-Vlaanderen",
    "sg:tags":[
        "whol",
        "flower",
        "-",
        "grower"
    ],
    "wof:name":"De Graeve J & R",
    "wof:placetype":"venue"
},
  "geometry": {"coordinates":[3.8378200531,51.0238113403],"type":"Point"}
}