{
  "type": "Feature",
  "properties": {
    "iso:country":"BE",
    "sg:address":"Lotsestraat 65",
    "sg:city":"Beersel",
    "sg:classifiers":[
        {
            "category":"Restaurant",
            "type":"Food & Drink"
        }
    ],
    "sg:phone":"+32 2 377 10 47",
    "sg:postcode":"1650",
    "sg:province":"Vlaams-Brabant",
    "wof:name":"Auberge Kasteel Beersel",
    "wof:placetype":"venue"
},
  "geometry": {"coordinates":[4.2975230217,50.7663803101],"type":"Point"}
}