{
  "type": "Feature",
  "properties": {
    "iso:country":"BE",
    "sg:address":"R De Rudderstraat 14",
    "sg:city":"Diksmuide",
    "sg:classifiers":[
        {
            "category":"Shopping",
            "subcategory":"Gifts & Souvenirs",
            "type":"Retail Goods"
        }
    ],
    "sg:phone":"+32 51 50 35 59",
    "sg:postcode":"8600",
    "sg:province":"West-Vlaanderen",
    "sg:tags":[
        "geschenken"
    ],
    "wof:name":"Barbery C",
    "wof:placetype":"venue"
},
  "geometry": {"coordinates":[2.869052887,51.0217132568],"type":"Point"}
}