{
  "type": "Feature",
  "properties": {
    "iso:country":"BE",
    "sg:address":"Avenue Buysdelle 36",
    "sg:city":"Bruxelles (uccle)",
    "sg:orig_category":"Ergotherapists",
    "sg:phone":"+32 2 374 09 21",
    "sg:postcode":"1180",
    "sg:province":"Bruxelles-Capitale",
    "wof:name":"Rens A F",
    "wof:placetype":"venue"
},
  "geometry": {"coordinates":[4.3515601158,50.7764930725],"type":"Point"}
}