{
  "type": "Feature",
  "properties": {
    "iso:country":"BE",
    "sg:address":"Hoekskensstraat 85",
    "sg:city":"Lochristi",
    "sg:orig_category":"Bloemen and planten Bloemen and planten Gh",
    "sg:phone":"+32 9 355 75 23",
    "sg:postcode":"9080",
    "sg:province":"Oost-Vlaanderen",
    "wof:name":"Daniel De Clercq",
    "wof:placetype":"venue"
},
  "geometry": {"coordinates":[3.8380320072,51.1091461182],"type":"Point"}
}