{
  "type": "Feature",
  "properties": {
    "iso:country":"BE",
    "sg:address":"Rue De Liroux 9",
    "sg:city":"Gembloux-sur-orneau (gembloux)",
    "sg:classifiers":[
        {
            "category":"Professional",
            "subcategory":"Testing Lab",
            "type":"Services"
        }
    ],
    "sg:phone":"+32 81 62 65 73",
    "sg:postcode":"5030",
    "sg:province":"Namur",
    "sg:tags":[
        "laboratory",
        "-"
    ],
    "wof:name":"Requasud",
    "wof:placetype":"venue"
},
  "geometry": {"coordinates":[4.7118940353,50.5617675781],"type":"Point"}
}