{
  "type": "Feature",
  "properties": {
    "addr:full":"Beekstraat 2 Menen West-Vlaanderen 8930",
    "addr:housenumber":"2",
    "addr:postcode":"8930",
    "addr:street":"Beekstraat",
    "iso:country":"BE",
    "sg:address":"Beekstraat 2",
    "sg:city":"Menen",
    "sg:classifiers":[
        {
            "category":"Building & Trades",
            "subcategory":"Construction",
            "type":"Services"
        }
    ],
    "sg:phone":"+32 56 52 00 64",
    "sg:postcode":"8930",
    "sg:province":"West-Vlaanderen",
    "sg:tags":[
        "carpenter"
    ],
    "wof:name":"Malfait R Bvba",
    "wof:placetype":"venue"
},
  "geometry": {"coordinates":[3.1141009331,50.8184661865],"type":"Point"}
}