{
  "type": "Feature",
  "properties": {
    "iso:country":"BE",
    "sg:address":"Vluchtenboerstraat 15",
    "sg:city":"Gavere",
    "sg:orig_category":"Epiceries",
    "sg:phone":"+32 9 384 48 58",
    "sg:postcode":"9890",
    "sg:province":"Oost-Vlaanderen",
    "wof:name":"Marino Niemegeers",
    "wof:placetype":"venue"
},
  "geometry": {"coordinates":[3.673593998,50.9258956909],"type":"Point"}
}