{
  "type": "Feature",
  "properties": {
    "iso:country":"BE",
    "sg:address":"Ronsesestraat 18",
    "sg:city":"Brakel",
    "sg:classifiers":[
        {
            "category":"Fast Food",
            "type":"Food & Drink"
        }
    ],
    "sg:phone":"+32 55 42 80 80",
    "sg:postcode":"9660",
    "sg:province":"Oost-Vlaanderen",
    "sg:tags":[
        "restaurant",
        "\u00c0",
        "domicile",
        "o",
        "catering",
        "emporter",
        "livraison",
        "restaurants"
    ],
    "wof:name":"Restaurant Eekeveld",
    "wof:placetype":"venue"
},
  "geometry": {"coordinates":[3.7569820881,50.7975273132],"type":"Point"}
}