{
  "type": "Feature",
  "properties": {
    "iso:country":"BE",
    "sg:address":"Torenstraat 8",
    "sg:city":"Zandhoven (pulle)",
    "sg:classifiers":[
        {
            "category":"Professional",
            "subcategory":"Accounting & Tax Preparation",
            "type":"Services"
        }
    ],
    "sg:phone":"+32 3 466 00 80",
    "sg:postcode":"2243",
    "sg:province":"Antwerpen",
    "sg:tags":[
        "accountant"
    ],
    "wof:name":"Convents A",
    "wof:placetype":"venue"
},
  "geometry": {"coordinates":[4.7150168419,51.2024841309],"type":"Point"}
}