{
  "type": "Feature",
  "properties": {
    "addr:full":"Rue De Cognebeau 52 Soignies Hainaut 7060",
    "addr:housenumber":"52",
    "addr:postcode":"7060",
    "addr:street":"Rue De Cognebeau",
    "iso:country":"BE",
    "sg:address":"Rue De Cognebeau 52",
    "sg:city":"Soignies",
    "sg:classifiers":[
        {
            "category":"Banks & Credit Unions",
            "subcategory":"Investment Brokerage",
            "type":"Services"
        }
    ],
    "sg:phone":"+32 67 33 10 84",
    "sg:postcode":"7060",
    "sg:province":"Hainaut",
    "sg:tags":[
        "auditor"
    ],
    "wof:name":"Biller J L",
    "wof:placetype":"venue"
},
  "geometry": {"coordinates":[4.0640749931,50.5769233704],"type":"Point"}
}