{
  "type": "Feature",
  "properties": {
    "addr:full":"Rijselvoorstad 40 Komen-waasten/comines-warneton Hainaut 7784",
    "addr:housenumber":"40;7784",
    "addr:street":"Rijselvoorstad",
    "iso:country":"BE",
    "sg:address":"Rijselvoorstad 40",
    "sg:city":"Komen-waasten/comines-warneton",
    "sg:orig_category":"Dranken",
    "sg:phone":"+32 56 55 83 10",
    "sg:postcode":"7784",
    "sg:province":"Hainaut",
    "wof:name":"Brasserie Vanuxeem",
    "wof:placetype":"venue"
},
  "geometry": {"coordinates":[2.9385099411,50.738319397],"type":"Point"}
}