{
  "type": "Feature",
  "properties": {
    "addr:full":"Leegstraat 12 Zelzate Oost-Vlaanderen 9060",
    "addr:housenumber":"12",
    "addr:postcode":"9060",
    "addr:street":"Leegstraat",
    "iso:country":"BE",
    "sg:address":"Leegstraat 12",
    "sg:city":"Zelzate",
    "sg:orig_category":"Brood, gebak and snoepgoed",
    "sg:phone":"+32 9 345 62 86",
    "sg:postcode":"9060",
    "sg:province":"Oost-Vlaanderen",
    "wof:name":"Werner Van De Walle",
    "wof:placetype":"venue"
},
  "geometry": {"coordinates":[3.8152489662,51.200050354],"type":"Point"}
}