{
  "type": "Feature",
  "properties": {
    "addr:full":"Nieuwstraat 130 Diepenbeek Limburg 3590",
    "addr:housenumber":"130",
    "addr:postcode":"3590",
    "addr:street":"Nieuwstraat",
    "iso:country":"BE",
    "sg:address":"Nieuwstraat 130",
    "sg:city":"Diepenbeek",
    "sg:orig_category":"Kapsalons",
    "sg:phone":"+32 11 33 30 56",
    "sg:postcode":"3590",
    "sg:province":"Limburg",
    "wof:name":"Coiffure Knuts",
    "wof:placetype":"venue"
},
  "geometry": {"coordinates":[5.4499969482,50.9230537415],"type":"Point"}
}