{
  "type": "Feature",
  "properties": {
    "addr:full":"Potijzestraat 61 Ieper West-Vlaanderen 8900",
    "addr:housenumber":"61",
    "addr:postcode":"8900",
    "addr:street":"Potijzestraat",
    "iso:country":"BE",
    "sg:address":"Potijzestraat 61",
    "sg:city":"Ieper",
    "sg:orig_category":"Entretien and r\u00e9parations de voitures. D\u00e9taillants en pi\u00e8ces and accessoires de voitures",
    "sg:phone":"+32 57 20 32 21",
    "sg:postcode":"8900",
    "sg:province":"West-Vlaanderen",
    "wof:name":"Fa. Parret",
    "wof:placetype":"venue"
},
  "geometry": {"coordinates":[2.8878269196,50.8513641357],"type":"Point"}
}