{
  "type": "Feature",
  "properties": {
    "iso:country":"BE",
    "sg:address":"Lantaarnstraatje 12",
    "sg:city":"Aalter",
    "sg:classifiers":[
        {
            "category":"Home & Garden",
            "subcategory":"Carpets & Floor Coverings",
            "type":"Retail Goods"
        }
    ],
    "sg:phone":"+32 9 374 56 29",
    "sg:postcode":"9880",
    "sg:province":"Oost-Vlaanderen",
    "sg:tags":[
        "layer",
        "mosaicists"
    ],
    "wof:name":"Van Damme E",
    "wof:placetype":"venue"
},
  "geometry": {"coordinates":[3.3709030151,51.0923118591],"type":"Point"}
}