{
  "type": "Feature",
  "properties": {
    "iso:country":"BE",
    "sg:address":"Rue Des Jardins 4",
    "sg:city":"Erez\u00e9e (mormont)",
    "sg:classifiers":[
        {
            "category":"Health Services",
            "subcategory":"Doctor",
            "type":"Services"
        }
    ],
    "sg:phone":"+32 86 36 79 99",
    "sg:postcode":"6997",
    "sg:province":"Luxembourg",
    "sg:tags":[
        "psychotherapist",
        "psychoanalyst"
    ],
    "wof:name":"Marechal L",
    "wof:placetype":"venue"
},
  "geometry": {"coordinates":[5.5559430122,50.3171882629],"type":"Point"}
}