{
  "type": "Feature",
  "properties": {
    "addr:full":"Bois De Devant-houx 28 Yvoir Namur 5530",
    "addr:housenumber":"28",
    "addr:postcode":"5530",
    "addr:street":"Bois",
    "iso:country":"BE",
    "sg:address":"Bois De Devant-houx 28",
    "sg:city":"Yvoir",
    "sg:classifiers":[
        {
            "category":"Health Services",
            "subcategory":"Doctor",
            "type":"Services"
        }
    ],
    "sg:phone":"+32 82 61 31 18",
    "sg:postcode":"5530",
    "sg:province":"Namur",
    "sg:tags":[
        "medicinephysicians",
        "surgeon"
    ],
    "wof:name":"Donckier J",
    "wof:placetype":"venue"
},
  "geometry": {"coordinates":[4.8971300125,50.293094635],"type":"Point"}
}