{
  "type": "Feature",
  "properties": {
    "addr:full":"6120 Ham-sur-heure-nalinnes Hainaut 6120",
    "addr:postcode":"6120;6120",
    "addr:street":"Hainaut",
    "iso:country":"BE",
    "sg:address":"6120",
    "sg:city":"Ham-sur-heure-nalinnes",
    "sg:orig_category":"Pharmaciens",
    "sg:phone":"+32 900 10 500",
    "sg:postcode":"6120",
    "sg:province":"Hainaut",
    "wof:name":"Pharmacies De Garde",
    "wof:placetype":"venue"
},
  "geometry": {"coordinates":[4.4116201401,50.3258590698],"type":"Point"}
}