{
  "type": "Feature",
  "properties": {
    "iso:country":"BE",
    "sg:address":"Fourneau-saint-michel 0",
    "sg:city":"Saint-hubert",
    "sg:orig_category":"Musea and historische gebouwen",
    "sg:phone":"+32 84 21 08 90",
    "sg:postcode":"6870",
    "sg:province":"Luxembourg",
    "wof:name":"Mus\u00c9e Prov.luxembourgeois",
    "wof:placetype":"venue"
},
  "geometry": {"coordinates":[5.340596199,50.0844497681],"type":"Point"}
}