{
  "type": "Feature",
  "properties": {
    "addr:full":"Generaal Lemanlaan 122 Brugge (groot) West-Vlaanderen 8310",
    "addr:housenumber":"122",
    "addr:postcode":"8310",
    "addr:street":"Generaal Lemanlaan;Groot West-Vlaanderen",
    "iso:country":"BE",
    "sg:address":"Generaal Lemanlaan 122",
    "sg:city":"Brugge (groot)",
    "sg:orig_category":"Verplichte sociale verzekeringen",
    "sg:phone":"+32 50 36 80 90",
    "sg:postcode":"8310",
    "sg:province":"West-Vlaanderen",
    "wof:name":"Euromut",
    "wof:placetype":"venue"
},
  "geometry": {"coordinates":[3.2403941154,51.2017097473],"type":"Point"}
}