{
  "type": "Feature",
  "properties": {
    "iso:country":"BE",
    "sg:address":"Overbosstraat 17",
    "sg:city":"Hoeselt",
    "sg:orig_category":"Non-Classified Establishments",
    "sg:phone":"+32 89 41 88 61",
    "sg:postcode":"3730",
    "sg:province":"Limburg",
    "wof:name":"Gehard Klapp Cosmetics",
    "wof:placetype":"venue"
},
  "geometry": {"coordinates":[5.4622502327,50.8668937683],"type":"Point"}
}