{
  "type": "Feature",
  "properties": {
    "iso:country":"BE",
    "sg:address":"Staatsbaan 88",
    "sg:city":"Bekkevoort",
    "sg:orig_category":"V\u00e9hicules automobiles",
    "sg:phone":"+32 13 31 10 97",
    "sg:postcode":"3460",
    "sg:province":"Vlaams-Brabant",
    "wof:name":"Schurmans",
    "wof:placetype":"venue"
},
  "geometry": {"coordinates":[4.9826979637,50.9467544556],"type":"Point"}
}