{
  "type": "Feature",
  "properties": {
    "addr:full":"Route De Champion 229 Eghezee Namur 5310",
    "addr:housenumber":"229",
    "addr:postcode":"5310",
    "addr:street":"Route De Champion;Namur",
    "iso:country":"BE",
    "sg:address":"Route De Champion 229",
    "sg:city":"Eghezee",
    "sg:orig_category":"Rundveehouders",
    "sg:phone":"+32 81 51 15 31",
    "sg:postcode":"5310",
    "sg:province":"Namur",
    "wof:name":"Eugene Chouckart",
    "wof:placetype":"venue"
},
  "geometry": {"coordinates":[4.9300889969,50.5377693176],"type":"Point"}
}