{
  "type": "Feature",
  "properties": {
    "addr:full":"Rue De Liedekerke 6 Bruxelles (saint-josse-ten-noode) Bruxelles-Capitale 1210",
    "addr:housenumber":"6",
    "addr:postcode":"1210",
    "addr:street":"Rue De Liedekerke",
    "iso:country":"BE",
    "sg:address":"Rue De Liedekerke 6",
    "sg:city":"Bruxelles (saint-josse-ten-noode)",
    "sg:classifiers":[
        {
            "category":"Community Center",
            "subcategory":"Youth",
            "type":"Public Place"
        }
    ],
    "sg:phone":"+32 2 217 96 17",
    "sg:postcode":"1210",
    "sg:province":"Bruxelles-Capitale",
    "sg:tags":[
        "club"
    ],
    "wof:name":"Guides Et Scouts De L'anaconda",
    "wof:placetype":"venue"
},
  "geometry": {"coordinates":[4.3768939972,50.8501472473],"type":"Point"}
}