{
  "type": "Feature",
  "properties": {
    "iso:country":"BE",
    "sg:address":"Trassersweg 105",
    "sg:city":"Vilvoorde",
    "sg:classifiers":[
        {
            "category":"Building & Trades",
            "subcategory":"Construction",
            "type":"Services"
        }
    ],
    "sg:phone":"+32 2 268 85 66",
    "sg:postcode":"1800",
    "sg:province":"Vlaams-Brabant",
    "sg:tags":[
        "carpenter"
    ],
    "wof:name":"Agw Sprl",
    "wof:placetype":"venue"
},
  "geometry": {"coordinates":[4.3834347725,50.9042129517],"type":"Point"}
}