{
  "type": "Feature",
  "properties": {
    "addr:full":"Hoogstraat 1 Puurs Antwerpen 2870",
    "addr:housenumber":"1",
    "addr:postcode":"2870",
    "addr:street":"Hoogstraat",
    "iso:country":"BE",
    "sg:address":"Hoogstraat 1",
    "sg:city":"Puurs",
    "sg:orig_category":"Artsen and specialisten",
    "sg:phone":"+32 3 889 08 61",
    "sg:postcode":"2870",
    "sg:province":"Antwerpen",
    "wof:name":"Karel Van Ranst",
    "wof:placetype":"venue"
},
  "geometry": {"coordinates":[4.2773070335,51.0764579773],"type":"Point"}
}