{
  "type": "Feature",
  "properties": {
    "addr:full":"Ganzenberg 20 Hamme Oost-Vlaanderen 9220",
    "addr:housenumber":"20",
    "addr:postcode":"9220",
    "addr:street":"Ganzenberg",
    "iso:country":"BE",
    "sg:address":"Ganzenberg 20",
    "sg:city":"Hamme",
    "sg:orig_category":"Installation \u00e9lectrique r\u00e9sidentielle",
    "sg:phone":"+32 52 48 31 34",
    "sg:postcode":"9220",
    "sg:province":"Oost-Vlaanderen",
    "wof:name":"Luc Moortgat",
    "wof:placetype":"venue"
},
  "geometry": {"coordinates":[4.1674318314,51.048084259],"type":"Point"}
}