{
  "type": "Feature",
  "properties": {
    "iso:country":"BE",
    "sg:address":"Rue Hautes Saules 3",
    "sg:city":"Remicourt (pousset)",
    "sg:classifiers":[
        {
            "category":"Transit Center",
            "subcategory":"Freight",
            "type":"Transportation"
        }
    ],
    "sg:phone":"+32 19 54 90 34",
    "sg:postcode":"4350",
    "sg:province":"Li\u00e8ge",
    "sg:tags":[
        "import",
        "export",
        "-"
    ],
    "wof:name":"Product & Negoce Sprl",
    "wof:placetype":"venue"
},
  "geometry": {"coordinates":[5.3127741814,50.6911582947],"type":"Point"}
}