{
  "type": "Feature",
  "properties": {
    "iso:country":"BE",
    "sg:address":"Rue Du Coll\u00c8ge 87",
    "sg:city":"Yvoir",
    "sg:orig_category":"M\u00e9decins and sp\u00e9cialistes",
    "sg:phone":"+32 82 61 26 62",
    "sg:postcode":"5530",
    "sg:province":"Namur",
    "wof:name":"Jacques-yves Buchkremer",
    "wof:placetype":"venue"
},
  "geometry": {"coordinates":[4.8647608757,50.3404388428],"type":"Point"}
}