{
  "type": "Feature",
  "properties": {
    "addr:full":"Gentse Baan 38 Sint-niklaas Oost-Vlaanderen 9100",
    "addr:housenumber":"38",
    "addr:postcode":"9100",
    "addr:street":"Gentse Baan",
    "iso:country":"BE",
    "sg:address":"Gentse Baan 38",
    "sg:city":"Sint-niklaas",
    "sg:classifiers":[
        {
            "category":"Wholesale",
            "subcategory":"Meat",
            "type":"Manufacturing & Wholesale Goods"
        }
    ],
    "sg:phone":"+32 3 777 38 06",
    "sg:postcode":"9100",
    "sg:province":"Oost-Vlaanderen",
    "sg:tags":[
        "chicken"
    ],
    "wof:name":"Weyn Kipversnijderij Nv",
    "wof:placetype":"venue"
},
  "geometry": {"coordinates":[4.1291799545,51.1497001648],"type":"Point"}
}