{
  "type": "Feature",
  "properties": {
    "iso:country":"BE",
    "sg:address":"Weststraat 64",
    "sg:city":"Lichtervelde",
    "sg:orig_category":"Non-Classified Establishments",
    "sg:phone":"+32 51 72 41 25",
    "sg:postcode":"8810",
    "sg:province":"West-Vlaanderen",
    "wof:name":"Arvabel",
    "wof:placetype":"venue"
},
  "geometry": {"coordinates":[3.1166009903,51.0356712341],"type":"Point"}
}