{
  "type": "Feature",
  "properties": {
    "addr:full":"Rue G\u00e9n\u00e9ral Henry 145 Bruxelles (etterbeek) Bruxelles-Capitale 1040",
    "addr:housenumber":"145",
    "addr:postcode":"1040",
    "addr:street":"Rue Ge\u0301Ne\u0301Ral Henry",
    "iso:country":"BE",
    "sg:address":"Rue G\u00e9n\u00e9ral Henry 145",
    "sg:city":"Bruxelles (etterbeek)",
    "sg:classifiers":[
        {
            "category":"Building & Trades",
            "subcategory":"Pest Control",
            "type":"Services"
        }
    ],
    "sg:phone":"+32 2 649 38 92",
    "sg:postcode":"1040",
    "sg:province":"Bruxelles-Capitale",
    "sg:tags":[
        "painting",
        "contractor"
    ],
    "wof:name":"Victor Entreprise",
    "wof:placetype":"venue"
},
  "geometry": {"coordinates":[4.3945541382,50.8286552429],"type":"Point"}
}