{
  "type": "Feature",
  "properties": {
    "addr:full":"Avenue Rogier 87 Schaarbeek/schaerbeek Bruxelles-Capitale 1030",
    "addr:housenumber":"87",
    "addr:postcode":"1030",
    "addr:street":"Avenue Rogier",
    "iso:country":"BE",
    "sg:address":"Avenue Rogier 87",
    "sg:city":"Schaarbeek/schaerbeek",
    "sg:orig_category":"S\u00e9curit\u00e9 sociale",
    "sg:phone":"+32 2 216 67 03",
    "sg:postcode":"1030",
    "sg:province":"Bruxelles-Capitale",
    "wof:name":"Mutualit\u00c9 Socialiste",
    "wof:placetype":"venue"
},
  "geometry": {"coordinates":[4.3759169579,50.8596420288],"type":"Point"}
}