{
  "type": "Feature",
  "properties": {
    "addr:full":"Oostkaai 76 Ieper West-Vlaanderen 8900",
    "addr:housenumber":"76",
    "addr:postcode":"8900",
    "addr:street":"Oostkaai",
    "iso:country":"BE",
    "sg:address":"Oostkaai 76",
    "sg:city":"Ieper",
    "sg:classifiers":[
        {
            "category":"Autos & Motor Vehicles",
            "subcategory":"Auto Supplies",
            "type":"Retail Goods"
        }
    ],
    "sg:phone":"+32 57 40 15 33",
    "sg:postcode":"8900",
    "sg:province":"West-Vlaanderen",
    "sg:tags":[
        "automobile",
        "-",
        "equipment",
        "air conditioning"
    ],
    "wof:name":"Airco Service Debusschere Bvba",
    "wof:placetype":"venue"
},
  "geometry": {"coordinates":[2.8846380711,50.8590621948],"type":"Point"}
}