{
  "type": "Feature",
  "properties": {
    "addr:full":"Kongostraat 2 Turnhout Antwerpen 2300",
    "addr:housenumber":"2",
    "addr:postcode":"2300",
    "addr:street":"Kongostraat",
    "iso:country":"BE",
    "sg:address":"Kongostraat 2",
    "sg:city":"Turnhout",
    "sg:orig_category":"Artsen and specialisten",
    "sg:phone":"+32 14 43 66 28",
    "sg:postcode":"2300",
    "sg:province":"Antwerpen",
    "wof:name":"Guido Emsens",
    "wof:placetype":"venue"
},
  "geometry": {"coordinates":[4.9330477715,51.3236618042],"type":"Point"}
}