{
  "type": "Feature",
  "properties": {
    "iso:country":"BE",
    "sg:address":"Toekomststraat 47ba",
    "sg:city":"Vilvoorde",
    "sg:orig_category":"Quincailleries",
    "sg:phone":"+32 2 253 08 19",
    "sg:postcode":"1800",
    "sg:province":"Vlaams-Brabant",
    "wof:name":"Moreels En Co",
    "wof:placetype":"venue"
},
  "geometry": {"coordinates":[4.4267029762,50.9295387268],"type":"Point"}
}