{
  "type": "Feature",
  "properties": {
    "addr:full":"Rue D'achet 30b Hamois Namur 5360",
    "addr:housenumber":"30b",
    "addr:postcode":"5360",
    "addr:street":"Rue D'Achet",
    "iso:country":"BE",
    "sg:address":"Rue D'achet 30b",
    "sg:city":"Hamois",
    "sg:classifiers":[
        {
            "category":"Building & Trades",
            "subcategory":"Pest Control",
            "type":"Services"
        }
    ],
    "sg:phone":"+32 83 61 14 55",
    "sg:postcode":"5360",
    "sg:province":"Namur",
    "sg:tags":[
        "painting",
        "contractor"
    ],
    "wof:name":"Halin P",
    "wof:placetype":"venue"
},
  "geometry": {"coordinates":[5.1578102112,50.340221405],"type":"Point"}
}