{
  "type": "Feature",
  "properties": {
    "iso:country":"BE",
    "sg:address":"Hoge Kaart 118",
    "sg:city":"Brasschaat",
    "sg:classifiers":[
        {
            "category":"Personal",
            "subcategory":"Beauty Salon",
            "type":"Services"
        }
    ],
    "sg:phone":"+32 3 651 79 55",
    "sg:postcode":"2930",
    "sg:province":"Antwerpen",
    "sg:tags":[
        "de",
        "coiffure"
    ],
    "wof:name":"De France",
    "wof:placetype":"venue"
},
  "geometry": {"coordinates":[4.4786248207,51.3031845093],"type":"Point"}
}