{
  "type": "Feature",
  "properties": {
    "iso:country":"BE",
    "sg:address":"Koolmijnlaan 158",
    "sg:city":"Beringen",
    "sg:orig_category":"Medische apparatuur, orthopedische artikelen and prothesen Fab",
    "sg:phone":"+32 11 42 36 24",
    "sg:postcode":"3582",
    "sg:province":"Limburg",
    "wof:name":"Dirk Maes",
    "wof:placetype":"venue"
},
  "geometry": {"coordinates":[5.2216000557,51.0644302368],"type":"Point"}
}