{
  "type": "Feature",
  "properties": {
    "addr:full":"Brusselsesteenweg 256 Zemst (eppegem) Vlaams-Brabant 1980",
    "addr:housenumber":"256",
    "addr:postcode":"1980",
    "addr:street":"Brusselsesteenweg",
    "iso:country":"BE",
    "sg:address":"Brusselsesteenweg 256",
    "sg:city":"Zemst (eppegem)",
    "sg:classifiers":[
        {
            "category":"Home & Garden",
            "subcategory":"Building Materials",
            "type":"Retail Goods"
        }
    ],
    "sg:phone":"+32 15 61 00 29",
    "sg:postcode":"1980",
    "sg:province":"Vlaams-Brabant",
    "sg:tags":[
        "bathroom",
        "installation",
        "accessory"
    ],
    "wof:name":"Sanidec Sprl",
    "wof:placetype":"venue"
},
  "geometry": {"coordinates":[4.4552798271,50.9738502502],"type":"Point"}
}