{
  "type": "Feature",
  "properties": {
    "addr:full":"Universiteitslaan 11 Hasselt Limburg 3500",
    "addr:housenumber":"11",
    "addr:postcode":"3500",
    "addr:street":"Universiteitslaan",
    "iso:country":"BE",
    "sg:address":"Universiteitslaan 11",
    "sg:city":"Hasselt",
    "sg:orig_category":"Catering and organisatie van feesten Fast food and meeneem restaurants Levering aan huis restaurants",
    "sg:phone":"+32 11 23 57 37",
    "sg:postcode":"3500",
    "sg:province":"Limburg",
    "wof:name":"Restaurant De Foyer",
    "wof:placetype":"venue"
},
  "geometry": {"coordinates":[5.3700032234,50.9305953979],"type":"Point"}
}