{
  "type": "Feature",
  "properties": {
    "addr:full":"Brusselsestraat 4 Dendermonde Oost-Vlaanderen 9200",
    "addr:housenumber":"4",
    "addr:postcode":"9200",
    "addr:street":"Brusselsestraat;Oost-Vlaanderen",
    "iso:country":"BE",
    "sg:address":"Brusselsestraat 4",
    "sg:city":"Dendermonde",
    "sg:orig_category":"Disquaires",
    "sg:phone":"+32 52 20 35 44",
    "sg:postcode":"9200",
    "sg:province":"Oost-Vlaanderen",
    "wof:name":"Free Record Shop",
    "wof:placetype":"venue"
},
  "geometry": {"coordinates":[4.0984921455,51.0287628174],"type":"Point"}
}