{
  "type": "Feature",
  "properties": {
    "addr:full":"Sint-rochusstraat 6 Dendermonde Oost-Vlaanderen 9200",
    "addr:housenumber":"6",
    "addr:postcode":"9200",
    "addr:street":"Sint-Rochusstraat;Oost-Vlaanderen",
    "iso:country":"BE",
    "sg:address":"Sint-rochusstraat 6",
    "sg:city":"Dendermonde",
    "sg:orig_category":"Pain, p\u00e2tisseries and confiseries",
    "sg:phone":"+32 52 21 62 38",
    "sg:postcode":"9200",
    "sg:province":"Oost-Vlaanderen",
    "wof:name":"Bakkerij St.rochus",
    "wof:placetype":"venue"
},
  "geometry": {"coordinates":[4.0984501839,51.0281562805],"type":"Point"}
}