{
  "type": "Feature",
  "properties": {
    "addr:full":"Rue De Limbourg 131 Verviers (grand) Li\u00e8ge 4800",
    "addr:housenumber":"131",
    "addr:postcode":"4800",
    "addr:street":"Rue De Limbourg",
    "iso:country":"BE",
    "sg:address":"Rue De Limbourg 131",
    "sg:city":"Verviers (grand)",
    "sg:orig_category":"Recreatie- and lunaparken",
    "sg:phone":"+32 87 30 03 00",
    "sg:postcode":"4800",
    "sg:province":"Li\u00e8ge",
    "wof:name":"Pirouette",
    "wof:placetype":"venue"
},
  "geometry": {"coordinates":[5.8884620667,50.6021575928],"type":"Point"}
}