{
  "type": "Feature",
  "properties": {
    "iso:country":"BE",
    "sg:address":"Chauss\u00c9e De Wavre 141",
    "sg:city":"Rixensart",
    "sg:classifiers":[
        {
            "category":"Taxi",
            "type":"Transportation"
        }
    ],
    "sg:phone":"+32 2 652 03 88",
    "sg:postcode":"1332",
    "sg:province":"Brabant Wallon",
    "sg:tags":[
        "sp\u00e9ciaux"
    ],
    "wof:name":"Taxi Marc",
    "wof:placetype":"venue"
},
  "geometry": {"coordinates":[4.4974551201,50.7170753479],"type":"Point"}
}