{
  "type": "Feature",
  "properties": {
    "iso:country":"BE",
    "sg:address":"Westdorp 3",
    "sg:city":"Anzegem",
    "sg:orig_category":"S\u00e9lection de personnel and placement",
    "sg:phone":"+32 56 68 82 50",
    "sg:postcode":"8573",
    "sg:province":"West-Vlaanderen",
    "wof:name":"Pwa Anzegem",
    "wof:placetype":"venue"
},
  "geometry": {"coordinates":[3.476006031,50.8081054688],"type":"Point"}
}