{
  "type": "Feature",
  "properties": {
    "iso:country":"BE",
    "sg:address":"Jachthoornlaan 40",
    "sg:city":"Zoersel",
    "sg:orig_category":"Fleurs and plantes",
    "sg:phone":"+32 3 309 05 65",
    "sg:postcode":"2980",
    "sg:province":"Antwerpen",
    "wof:name":"Linda Breesch",
    "wof:placetype":"venue"
},
  "geometry": {"coordinates":[4.6982879639,51.2684364319],"type":"Point"}
}