{
  "type": "Feature",
  "properties": {
    "addr:full":"Rue De L'yser 166 Welkenraedt Li\u00e8ge 4840",
    "addr:housenumber":"166",
    "addr:postcode":"4840",
    "addr:street":"Rue De L'Yser",
    "iso:country":"BE",
    "sg:address":"Rue De L'yser 166",
    "sg:city":"Welkenraedt",
    "sg:classifiers":[
        {
            "category":"Home & Garden",
            "subcategory":"Building Materials",
            "type":"Retail Goods"
        }
    ],
    "sg:phone":"+32 87 88 34 70",
    "sg:postcode":"4840",
    "sg:province":"Li\u00e8ge",
    "sg:tags":[
        "window"
    ],
    "wof:name":"Gehlen Karl Sprl",
    "wof:placetype":"venue"
},
  "geometry": {"coordinates":[5.9600048065,50.6741905212],"type":"Point"}
}