{
  "type": "Feature",
  "properties": {
    "iso:country":"BE",
    "sg:address":"Boulevard Leopold Ii 240",
    "sg:city":"Bruxelles (koekelberg)",
    "sg:classifiers":[
        {
            "category":"Banks & Credit Unions",
            "subcategory":"Bureau De Change",
            "type":"Services"
        }
    ],
    "sg:phone":"+32 2 414 00 02",
    "sg:postcode":"1081",
    "sg:province":"Bruxelles-Capitale",
    "sg:tags":[
        "belgian",
        "-",
        "broker",
        "exchange"
    ],
    "wof:name":"De Sagher & Cie Scs",
    "wof:placetype":"venue"
},
  "geometry": {"coordinates":[4.33233881,50.8623771667],"type":"Point"}
}