{
  "type": "Feature",
  "properties": {
    "iso:country":"BE",
    "sg:address":"Dokter Persoonslaan 13",
    "sg:city":"Willebroek",
    "sg:orig_category":"Pain, p\u00e2tisseries and confiseries",
    "sg:phone":"+32 3 886 58 72",
    "sg:postcode":"2830",
    "sg:province":"Antwerpen",
    "wof:name":"Bakkerij Glenn",
    "wof:placetype":"venue"
},
  "geometry": {"coordinates":[4.3622889519,51.0597381592],"type":"Point"}
}