{
  "type": "Feature",
  "properties": {
    "addr:full":"Dorp 14 Aalst (moorsel) Oost-Vlaanderen 9310",
    "addr:housenumber":"14",
    "addr:postcode":"9310",
    "addr:street":"Dorp;Moorsel Oost-Vlaanderen",
    "iso:country":"BE",
    "sg:address":"Dorp 14",
    "sg:city":"Aalst (moorsel)",
    "sg:classifiers":[
        {
            "category":"Food & Beverages",
            "subcategory":"Fruits & Vegetables",
            "type":"Retail Goods"
        }
    ],
    "sg:phone":"+32 53 70 63 75",
    "sg:postcode":"9310",
    "sg:province":"Oost-Vlaanderen",
    "sg:tags":[
        "-"
    ],
    "wof:name":"Vinck Bvba",
    "wof:placetype":"venue"
},
  "geometry": {"coordinates":[4.098400116,50.9477767944],"type":"Point"}
}