{
  "type": "Feature",
  "properties": {
    "addr:full":"Heuvelstraat 134 Tielt-winge Vlaams-Brabant 3390",
    "addr:housenumber":"134",
    "addr:postcode":"3390",
    "addr:street":"Heuvelstraat",
    "iso:country":"BE",
    "sg:address":"Heuvelstraat 134",
    "sg:city":"Tielt-winge",
    "sg:orig_category":"Boucheries",
    "sg:phone":"+32 16 63 42 03",
    "sg:postcode":"3390",
    "sg:province":"Vlaams-Brabant",
    "wof:name":"P. Wuyts",
    "wof:placetype":"venue"
},
  "geometry": {"coordinates":[4.9462680817,50.9419746399],"type":"Point"}
}