{
  "type": "Feature",
  "properties": {
    "addr:full":"Rue Grande-champlon 102 Tenneville Luxembourg 6971",
    "addr:housenumber":"102",
    "addr:postcode":"6971",
    "addr:street":"Rue Grande-Champlon",
    "iso:country":"BE",
    "sg:address":"Rue Grande-champlon 102",
    "sg:city":"Tenneville",
    "sg:orig_category":"Travail and traitement du bois",
    "sg:phone":"+32 84 45 53 71",
    "sg:postcode":"6971",
    "sg:province":"Luxembourg",
    "wof:name":"Laurent Et Fils",
    "wof:placetype":"venue"
},
  "geometry": {"coordinates":[5.4833312035,50.1076202393],"type":"Point"}
}