{
  "type": "Feature",
  "properties": {
    "iso:country":"BE",
    "sg:address":"Square De L'aviation 7a",
    "sg:city":"Bruxelles (anderlecht)",
    "sg:classifiers":[
        {
            "category":"Communications",
            "subcategory":"Film & Video Production",
            "type":"Services"
        }
    ],
    "sg:phone":"+32 2 527 31 85",
    "sg:postcode":"1070",
    "sg:province":"Bruxelles-Capitale",
    "sg:tags":[
        "multimedia",
        "-",
        "system"
    ],
    "wof:name":"Image System Sa",
    "wof:placetype":"venue"
},
  "geometry": {"coordinates":[4.3395619392,50.8410491943],"type":"Point"}
}