{
  "type": "Feature",
  "properties": {
    "addr:full":"Rue Des Hauchies 83 Charleroi Hainaut 6042",
    "addr:housenumber":"83",
    "addr:postcode":"6042",
    "addr:street":"Rue Des Hauchies;Hainaut",
    "iso:country":"BE",
    "sg:address":"Rue Des Hauchies 83",
    "sg:city":"Charleroi",
    "sg:orig_category":"Sportclubs",
    "sg:phone":"+32 71 27 55 73",
    "sg:postcode":"6042",
    "sg:province":"Hainaut",
    "wof:name":"Tc Group. Corp. Charleroi",
    "wof:placetype":"venue"
},
  "geometry": {"coordinates":[4.4490199089,50.4293518066],"type":"Point"}
}