{
  "type": "Feature",
  "properties": {
    "iso:country":"BE",
    "sg:address":"Rue De La Fontaine 15",
    "sg:city":"Beauraing",
    "sg:classifiers":[
        {
            "category":"Professional",
            "subcategory":"Accounting & Tax Preparation",
            "type":"Services"
        }
    ],
    "sg:phone":"+32 82 71 41 75",
    "sg:postcode":"5570",
    "sg:province":"Namur",
    "sg:tags":[
        "bookkeeper"
    ],
    "wof:name":"Gesco Scrl",
    "wof:placetype":"venue"
},
  "geometry": {"coordinates":[4.9565720558,50.1085739136],"type":"Point"}
}