{
  "type": "Feature",
  "properties": {
    "addr:full":"Izegemsestraat 116 Kortrijk (heule) West-Vlaanderen 8501",
    "addr:housenumber":"116",
    "addr:postcode":"8501",
    "addr:street":"Izegemsestraat",
    "iso:country":"BE",
    "sg:address":"Izegemsestraat 116",
    "sg:city":"Kortrijk (heule)",
    "sg:classifiers":[
        {
            "category":"Health Services",
            "subcategory":"Dentist",
            "type":"Services"
        }
    ],
    "sg:phone":"+32 56 35 20 07",
    "sg:postcode":"8501",
    "sg:province":"West-Vlaanderen",
    "wof:name":"Van Tieghem D",
    "wof:placetype":"venue"
},
  "geometry": {"coordinates":[3.2580089569,50.8381996155],"type":"Point"}
}