{
  "type": "Feature",
  "properties": {
    "iso:country":"BE",
    "sg:address":"Snellegemsestraat 15",
    "sg:city":"Zedelgem",
    "sg:orig_category":"Plomberie, chauffage and installations sanitaires",
    "sg:phone":"+32 50 20 10 47",
    "sg:postcode":"8210",
    "sg:province":"West-Vlaanderen",
    "wof:name":"Verschaeve",
    "wof:placetype":"venue"
},
  "geometry": {"coordinates":[3.1358859539,51.1443939209],"type":"Point"}
}