{
  "type": "Feature",
  "properties": {
    "iso:country":"BE",
    "sg:address":"Beukenlaan 38",
    "sg:city":"Retie",
    "sg:classifiers":[
        {
            "category":"Professional",
            "subcategory":"Art Services",
            "type":"Services"
        }
    ],
    "sg:phone":"+32 14 37 89 05",
    "sg:postcode":"2470",
    "sg:province":"Antwerpen",
    "sg:tags":[
        "photographer"
    ],
    "wof:name":"Fokato",
    "wof:placetype":"venue"
},
  "geometry": {"coordinates":[5.08334589,51.2577018738],"type":"Point"}
}