{
  "type": "Feature",
  "properties": {
    "addr:full":"Binnenstraat 33 Aalst Oost-Vlaanderen 9300",
    "addr:housenumber":"33",
    "addr:postcode":"9300",
    "addr:street":"Binnenstraat",
    "iso:country":"BE",
    "sg:address":"Binnenstraat 33",
    "sg:city":"Aalst",
    "sg:classifiers":[
        {
            "category":"Wholesale",
            "subcategory":"Wine & Distilled Alcoholic Beverages",
            "type":"Manufacturing & Wholesale Goods"
        }
    ],
    "sg:phone":"+32 53 21 14 86",
    "sg:postcode":"9300",
    "sg:province":"Oost-Vlaanderen",
    "sg:tags":[
        "whol",
        "-",
        "spirit",
        "mfg"
    ],
    "wof:name":"V.d.s. Van Der Schueren",
    "wof:placetype":"venue"
},
  "geometry": {"coordinates":[4.0476431847,50.9429779053],"type":"Point"}
}