{
  "type": "Feature",
  "properties": {
    "iso:country":"BE",
    "sg:address":"Rue G. Cuvelier 12",
    "sg:city":"Florenville (groot)",
    "sg:orig_category":"Banques and organismes de cr\u00e9dit",
    "sg:phone":"+32 61 32 54 40",
    "sg:postcode":"6820",
    "sg:province":"Luxembourg",
    "wof:name":"Fortis",
    "wof:placetype":"venue"
},
  "geometry": {"coordinates":[5.3093848228,49.6979980469],"type":"Point"}
}