{
  "type": "Feature",
  "properties": {
    "addr:full":"Dendermondse Steenweg 162 Aalst Oost-Vlaanderen 9300",
    "addr:housenumber":"162",
    "addr:postcode":"9300",
    "addr:street":"Steenweg",
    "iso:country":"BE",
    "sg:address":"Dendermondse Steenweg 162",
    "sg:city":"Aalst",
    "sg:classifiers":[
        {
            "category":"Retail",
            "subcategory":"Auto Repair",
            "type":"Services"
        }
    ],
    "sg:phone":"+32 53 77 29 27",
    "sg:postcode":"9300",
    "sg:province":"Oost-Vlaanderen",
    "sg:tags":[
        "garage"
    ],
    "wof:name":"Motors Bvba",
    "wof:placetype":"venue"
},
  "geometry": {"coordinates":[4.0503549576,50.9522438049],"type":"Point"}
}