{
  "type": "Feature",
  "properties": {
    "iso:country":"BE",
    "sg:address":"Rue Du Monument 1",
    "sg:city":"Hannut",
    "sg:orig_category":"Boucheries",
    "sg:phone":"+32 19 51 21 00",
    "sg:postcode":"4280",
    "sg:province":"Li\u00e8ge",
    "wof:name":"Boucherie Stapelle J.",
    "wof:placetype":"venue"
},
  "geometry": {"coordinates":[5.1330008507,50.654258728],"type":"Point"}
}