{
  "type": "Feature",
  "properties": {
    "iso:country":"BE",
    "sg:address":"Kunstlaan 6",
    "sg:city":"Hasselt",
    "sg:classifiers":[
        {
            "category":"Health Services",
            "subcategory":"Doctor",
            "type":"Services"
        }
    ],
    "sg:phone":"+32 11 24 11 81",
    "sg:postcode":"3500",
    "sg:province":"Limburg",
    "sg:tags":[
        "medicinephysicians",
        "surgeon"
    ],
    "wof:name":"Jadoul P",
    "wof:placetype":"venue"
},
  "geometry": {"coordinates":[5.3431887627,50.9282951355],"type":"Point"}
}