{
  "type": "Feature",
  "properties": {
    "addr:full":"Nijvelsesteenweg 538 Halle Vlaams-Brabant 1500",
    "addr:housenumber":"538",
    "addr:postcode":"1500",
    "addr:street":"Nijvelsesteenweg",
    "iso:country":"BE",
    "sg:address":"Nijvelsesteenweg 538",
    "sg:city":"Halle",
    "sg:orig_category":"Epiceries. Boucheries",
    "sg:phone":"+32 2 356 17 88",
    "sg:postcode":"1500",
    "sg:province":"Vlaams-Brabant",
    "wof:name":"Delhaize",
    "wof:placetype":"venue"
},
  "geometry": {"coordinates":[4.2498221397,50.7215957642],"type":"Point"}
}