{
  "type": "Feature",
  "properties": {
    "addr:full":"Menenstraat 441 Wevelgem West-Vlaanderen 8560",
    "addr:housenumber":"441",
    "addr:postcode":"8560",
    "addr:street":"Menenstraat",
    "iso:country":"BE",
    "sg:address":"Menenstraat 441",
    "sg:city":"Wevelgem",
    "sg:orig_category":"HERSTELLING ELEKTRISCHE HUISHOUDAPPARATEN Huishoudapparaten, televisies and radio's",
    "sg:phone":"+32 56 41 51 20",
    "sg:postcode":"8560",
    "sg:province":"West-Vlaanderen",
    "wof:name":"Elektro Service",
    "wof:placetype":"venue"
},
  "geometry": {"coordinates":[3.1545069218,50.8023033142],"type":"Point"}
}