{
  "type": "Feature",
  "properties": {
    "iso:country":"BE",
    "sg:address":"Rue Bois L' Ev\u00c8que 55",
    "sg:city":"Nameche",
    "sg:orig_category":"Belastingconsulenten",
    "sg:phone":"+32 477 60 80 82",
    "sg:postcode":"5300",
    "sg:province":"Namur",
    "wof:name":"Bureau Comptable Bouchat Martin",
    "wof:placetype":"venue"
},
  "geometry": {"coordinates":[5.1341791153,50.5267791748],"type":"Point"}
}