{
  "type": "Feature",
  "properties": {
    "iso:country":"BE",
    "sg:address":"Chauss\u00e9e De Jodoigne 71",
    "sg:city":"Grez-doiceau",
    "sg:classifiers":[
        {
            "category":"Professional",
            "subcategory":"Business Services",
            "type":"Services"
        }
    ],
    "sg:phone":"+32 10 84 24 95",
    "sg:postcode":"1390",
    "sg:province":"Brabant Wallon",
    "sg:tags":[
        "bookkeeping"
    ],
    "wof:name":"Accounting Consulting & Serv Sa",
    "wof:placetype":"venue"
},
  "geometry": {"coordinates":[4.7041220665,50.7361831665],"type":"Point"}
}