{
  "type": "Feature",
  "properties": {
    "addr:full":"Oostmeers 128 Brugge West-Vlaanderen 8000",
    "addr:housenumber":"128",
    "addr:postcode":"8000",
    "addr:street":"Oostmeers",
    "iso:country":"BE",
    "sg:address":"Oostmeers 128",
    "sg:city":"Brugge",
    "sg:classifiers":[
        {
            "category":"Travel",
            "subcategory":"Hotels & Motels",
            "type":"Entertainment"
        }
    ],
    "sg:phone":"+32 50 34 34 28",
    "sg:postcode":"8000",
    "sg:province":"West-Vlaanderen",
    "wof:name":"Breughelhof",
    "wof:placetype":"venue"
},
  "geometry": {"coordinates":[3.2201800346,51.2000083923],"type":"Point"}
}