{
  "type": "Feature",
  "properties": {
    "addr:full":"V. Beauduinstraat 40 Tienen Vlaams-Brabant 3300",
    "addr:housenumber":"40",
    "addr:postcode":"3300",
    "addr:street":"Beauduinstraat",
    "iso:country":"BE",
    "sg:address":"V. Beauduinstraat 40",
    "sg:city":"Tienen",
    "sg:orig_category":"Mat\u00e9riel de T\u00e9l\u00e9communication. R\u00e9parations d'appareils \u00e9lectrom\u00e9nagers. Electrom\u00e9nager, t\u00e9l\u00e9visions ",
    "sg:phone":"+32 16 82 26 00",
    "sg:postcode":"3300",
    "sg:province":"Vlaams-Brabant",
    "wof:name":"Raddoux",
    "wof:placetype":"venue"
},
  "geometry": {"coordinates":[4.9421730042,50.8048057556],"type":"Point"}
}