{
  "type": "Feature",
  "properties": {
    "addr:full":"Hondseinde 26 Westerlo Antwerpen 2260",
    "addr:housenumber":"26",
    "addr:postcode":"2260",
    "addr:street":"Hondseinde",
    "iso:country":"BE",
    "sg:address":"Hondseinde 26",
    "sg:city":"Westerlo",
    "sg:orig_category":"Eleveurs de bovins",
    "sg:phone":"+32 14 54 53 85",
    "sg:postcode":"2260",
    "sg:province":"Antwerpen",
    "wof:name":"Luc Gielis",
    "wof:placetype":"venue"
},
  "geometry": {"coordinates":[4.9396939278,51.1073150635],"type":"Point"}
}