{
  "type": "Feature",
  "properties": {
    "iso:country":"BE",
    "sg:address":"Gentsesteenweg 283",
    "sg:city":"Asse",
    "sg:classifiers":[
        {
            "category":"Bakery",
            "type":"Food & Drink"
        }
    ],
    "sg:phone":"+32 2 452 27 86",
    "sg:postcode":"1730",
    "sg:province":"Vlaams-Brabant",
    "sg:tags":[
        "confectioner",
        "baker"
    ],
    "wof:name":"Erik & Karine Brood-patisserie",
    "wof:placetype":"venue"
},
  "geometry": {"coordinates":[4.1590209007,50.9194221497],"type":"Point"}
}