{
  "type": "Feature",
  "properties": {
    "addr:full":"Lange Nieuwstraat 58b11 Antwerpen Antwerpen 2000",
    "addr:housenumber":"58b11",
    "addr:postcode":"2000",
    "addr:street":"Lange Nieuwstraat",
    "iso:country":"BE",
    "sg:address":"Lange Nieuwstraat 58b11",
    "sg:city":"Antwerpen",
    "sg:classifiers":[
        {
            "category":"Professional",
            "subcategory":"Accounting & Tax Preparation",
            "type":"Services"
        }
    ],
    "sg:phone":"+32 3 232 62 37",
    "sg:postcode":"2000",
    "sg:province":"Antwerpen",
    "sg:tags":[
        "accountant"
    ],
    "wof:name":"Edgard Hubert",
    "wof:placetype":"venue"
},
  "geometry": {"coordinates":[4.4095377922,51.2195930481],"type":"Point"}
}