{
  "type": "Feature",
  "properties": {
    "iso:country":"BE",
    "sg:address":"Abdijstraat 2",
    "sg:city":"Westerlo (tongerlo)",
    "sg:classifiers":[
        {
            "category":"Insurance",
            "subcategory":"Insurance Agent",
            "type":"Services"
        }
    ],
    "sg:phone":"+32 14 54 67 70",
    "sg:postcode":"2260",
    "sg:province":"Antwerpen",
    "sg:tags":[
        "broker"
    ],
    "wof:name":"Van Bael Zakenkantoor Nv",
    "wof:placetype":"venue"
},
  "geometry": {"coordinates":[4.915304184,51.1061668396],"type":"Point"}
}