{
  "type": "Feature",
  "properties": {
    "iso:country":"BE",
    "sg:address":"Rijschoolstraat 31",
    "sg:city":"Tienen",
    "sg:orig_category":"Dakwerken",
    "sg:phone":"+32 16 82 44 55",
    "sg:postcode":"3300",
    "sg:province":"Vlaams-Brabant",
    "wof:name":"Johny Gijsenbergh",
    "wof:placetype":"venue"
},
  "geometry": {"coordinates":[4.9338378906,50.8051757812],"type":"Point"}
}