{
  "type": "Feature",
  "properties": {
    "addr:full":"Place Du Ch\u00c2telain 40 Elsene/ixelles Bruxelles-Capitale 1050",
    "addr:housenumber":"40",
    "addr:postcode":"1050",
    "addr:street":"Place Du Cha\u0302Telain",
    "iso:country":"BE",
    "sg:address":"Place Du Ch\u00c2telain 40",
    "sg:city":"Elsene/ixelles",
    "sg:classifiers":[
        {
            "category":"Restaurant",
            "type":"Food & Drink"
        }
    ],
    "sg:phone":"+32 2 644 03 23",
    "sg:postcode":"1050",
    "sg:province":"Bruxelles-Capitale",
    "wof:name":"O'comme 3 Pommes",
    "wof:placetype":"venue"
},
  "geometry": {"coordinates":[4.360877037,50.8247642517],"type":"Point"}
}