{
  "type": "Feature",
  "properties": {
    "iso:country":"BE",
    "sg:address":"Rue De Tournai 49",
    "sg:city":"Pecq",
    "sg:orig_category":"V\u00e9los. Articles de jardin",
    "sg:phone":"+32 69 55 61 33",
    "sg:postcode":"7740",
    "sg:province":"Hainaut",
    "wof:name":"Ets. Verpeut",
    "wof:placetype":"venue"
},
  "geometry": {"coordinates":[3.338588953,50.6840400696],"type":"Point"}
}