{
  "type": "Feature",
  "properties": {
    "addr:full":"Wippelberg 51 Arendonk Antwerpen 2370",
    "addr:housenumber":"51",
    "addr:postcode":"2370",
    "addr:street":"Wippelberg",
    "iso:country":"BE",
    "sg:address":"Wippelberg 51",
    "sg:city":"Arendonk",
    "sg:orig_category":"Radioproductie and uitzendingen",
    "sg:phone":"+32 14 67 00 67",
    "sg:postcode":"2370",
    "sg:province":"Antwerpen",
    "wof:name":"Radio Eagle",
    "wof:placetype":"venue"
},
  "geometry": {"coordinates":[5.0960102081,51.3207130432],"type":"Point"}
}