{
  "type": "Feature",
  "properties": {
    "addr:full":"Chemin Des Carriers 88 Jodoigne Brabant Wallon 1370",
    "addr:housenumber":"88",
    "addr:postcode":"1370",
    "addr:street":"Chemin Des Carriers",
    "iso:country":"BE",
    "sg:address":"Chemin Des Carriers 88",
    "sg:city":"Jodoigne",
    "sg:orig_category":"Bloemen and planten",
    "sg:phone":"+32 10 81 03 99",
    "sg:postcode":"1370",
    "sg:province":"Brabant Wallon",
    "wof:name":"Arbor & Flore",
    "wof:placetype":"venue"
},
  "geometry": {"coordinates":[4.8559308052,50.7465057373],"type":"Point"}
}