{
  "type": "Feature",
  "properties": {
    "addr:full":"Londenstraat 28-30 Antwerpen Antwerpen 2000",
    "addr:postcode":"28-30;2000",
    "addr:street":"Londenstraat",
    "iso:country":"BE",
    "sg:address":"Londenstraat 28-30",
    "sg:city":"Antwerpen",
    "sg:classifiers":[
        {
            "category":"Government",
            "subcategory":"Post Office",
            "type":"Public Place"
        }
    ],
    "sg:phone":"+32 3 205 60 60",
    "sg:postcode":"2000",
    "sg:province":"Antwerpen",
    "sg:tags":[
        "poster"
    ],
    "wof:name":"A.a.a. The Color Revolution",
    "wof:placetype":"venue"
},
  "geometry": {"coordinates":[4.4096360207,51.2307815552],"type":"Point"}
}