{
  "type": "Feature",
  "properties": {
    "addr:full":"Gen Lemanstr 2a Sint-pieters-leeuw Vlaams-Brabant 1600",
    "addr:housenumber":"2a",
    "addr:postcode":"1600",
    "iso:country":"BE",
    "sg:address":"Gen Lemanstr 2a",
    "sg:city":"Sint-pieters-leeuw",
    "sg:classifiers":[
        {
            "category":"Professional",
            "subcategory":"Engineering",
            "type":"Services"
        }
    ],
    "sg:phone":"+32 2 334 74 74",
    "sg:postcode":"1600",
    "sg:province":"Vlaams-Brabant",
    "sg:tags":[
        "machine",
        "-",
        "mechanical"
    ],
    "wof:name":"Magec Nv",
    "wof:placetype":"venue"
},
  "geometry": {"coordinates":[4.2839241028,50.7929191589],"type":"Point"}
}