{
  "type": "Feature",
  "properties": {
    "iso:country":"BE",
    "sg:address":"Paalsesteenweg 41",
    "sg:city":"Beringen",
    "sg:orig_category":"Herstellingen and onderhoud van auto's",
    "sg:phone":"+32 11 42 22 55",
    "sg:postcode":"3580",
    "sg:province":"Limburg",
    "wof:name":"Jacques Meekers",
    "wof:placetype":"venue"
},
  "geometry": {"coordinates":[5.2227168083,51.0474014282],"type":"Point"}
}