{
  "type": "Feature",
  "properties": {
    "iso:country":"BE",
    "sg:address":"Chauss\u00c9e De Neufch\u00c2teau 53",
    "sg:city":"Vaux-sur-sure",
    "sg:orig_category":"Artsen and specialisten",
    "sg:phone":"+32 61 25 52 26",
    "sg:postcode":"6640",
    "sg:province":"Luxembourg",
    "wof:name":"Anne-marie Bertrand",
    "wof:placetype":"venue"
},
  "geometry": {"coordinates":[5.5643501282,49.9097137451],"type":"Point"}
}