{
  "type": "Feature",
  "properties": {
    "iso:country":"BE",
    "sg:address":"Frumont 26",
    "sg:city":"Onhaye",
    "sg:classifiers":[
        {
            "category":"Professional",
            "subcategory":"Accounting & Tax Preparation",
            "type":"Services"
        }
    ],
    "sg:phone":"+32 82 64 52 52",
    "sg:postcode":"5520",
    "sg:province":"Namur",
    "sg:tags":[
        "bookkeeper"
    ],
    "wof:name":"Delobbe R",
    "wof:placetype":"venue"
},
  "geometry": {"coordinates":[4.8450369835,50.2362480164],"type":"Point"}
}