{
  "type": "Feature",
  "properties": {
    "addr:full":"Rue Du Maieur 5 Profondeville Namur 5170",
    "addr:housenumber":"5",
    "addr:postcode":"5170",
    "addr:street":"Rue Du Maieur",
    "iso:country":"BE",
    "sg:address":"Rue Du Maieur 5",
    "sg:city":"Profondeville",
    "sg:orig_category":"Afbraak- and draineerwerken",
    "sg:phone":"+32 81 43 48 52",
    "sg:postcode":"5170",
    "sg:province":"Namur",
    "wof:name":"Pascal Petit",
    "wof:placetype":"venue"
},
  "geometry": {"coordinates":[4.7760920525,50.3767242432],"type":"Point"}
}