{
  "type": "Feature",
  "properties": {
    "iso:country":"BE",
    "sg:address":"Hundelgemsesteenweg 499",
    "sg:city":"Merelbeke",
    "sg:orig_category":"Installation \u00e9lectrique r\u00e9sidentielle. Moteurs, transformateurs and groupes \u00e9lectrog\u00e8nes Fab",
    "sg:phone":"+32 9 231 21 43",
    "sg:postcode":"9820",
    "sg:province":"Oost-Vlaanderen",
    "wof:name":"Dirk De Vuyst",
    "wof:placetype":"venue"
},
  "geometry": {"coordinates":[3.7463290691,50.9872627258],"type":"Point"}
}