{
  "type": "Feature",
  "properties": {
    "addr:full":"Tulpenlaan 249 Deerlijk West-Vlaanderen 8540",
    "addr:housenumber":"249",
    "addr:postcode":"8540",
    "addr:street":"Tulpenlaan",
    "iso:country":"BE",
    "sg:address":"Tulpenlaan 249",
    "sg:city":"Deerlijk",
    "sg:classifiers":[
        {
            "category":"Bus Stop",
            "subcategory":"None",
            "type":"Transportation"
        }
    ],
    "sg:phone":"+32 56 71 06 83",
    "sg:postcode":"8540",
    "sg:province":"West-Vlaanderen",
    "sg:tags":[
        "electricity",
        "-",
        "high",
        "low",
        "cabin",
        "voltage"
    ],
    "wof:name":"Vanogroep Nv",
    "wof:placetype":"venue"
},
  "geometry": {"coordinates":[3.3505880833,50.8578643799],"type":"Point"}
}