{
  "type": "Feature",
  "properties": {
    "iso:country":"BE",
    "sg:address":"Baron Tibbautstraat 38a",
    "sg:city":"Berlare",
    "sg:orig_category":"Bloemen and planten Gh Groententeelt",
    "sg:phone":"+32 9 367 76 21",
    "sg:postcode":"9290",
    "sg:province":"Oost-Vlaanderen",
    "wof:name":"Eric Van De Steene",
    "wof:placetype":"venue"
},
  "geometry": {"coordinates":[3.9433689117,51.0454292297],"type":"Point"}
}