{
  "type": "Feature",
  "properties": {
    "addr:full":"Chauss\u00e9e De Mariemont 105a Morlanwelz (morlanwelz-mariemont) Hainaut 7140",
    "addr:housenumber":"105a",
    "addr:postcode":"7140",
    "addr:street":"Chausse\u0301E De Mariemont",
    "iso:country":"BE",
    "sg:address":"Chauss\u00e9e De Mariemont 105a",
    "sg:city":"Morlanwelz (morlanwelz-mariemont)",
    "sg:classifiers":[
        {
            "category":"Real Estate",
            "subcategory":"Architect",
            "type":"Services"
        }
    ],
    "sg:phone":"+32 64 45 04 58",
    "sg:postcode":"7140",
    "sg:province":"Hainaut",
    "wof:name":"Bognanno Michel Atelier Architecture Sprl",
    "wof:placetype":"venue"
},
  "geometry": {"coordinates":[4.2330608368,50.4649085999],"type":"Point"}
}