{
  "type": "Feature",
  "properties": {
    "addr:full":"Rue De Pellaines 60 Lincent (racour) Li\u00e8ge 4287",
    "addr:housenumber":"60",
    "addr:postcode":"4287",
    "addr:street":"Rue De Pellaines;Racour",
    "iso:country":"BE",
    "sg:address":"Rue De Pellaines 60",
    "sg:city":"Lincent (racour)",
    "sg:classifiers":[
        {
            "category":"Professional",
            "subcategory":"Accounting & Tax Preparation",
            "type":"Services"
        }
    ],
    "sg:phone":"+32 19 65 57 59",
    "sg:postcode":"4287",
    "sg:province":"Li\u00e8ge",
    "sg:tags":[
        "bookkeeper"
    ],
    "wof:name":"Deville G",
    "wof:placetype":"venue"
},
  "geometry": {"coordinates":[5.0234627724,50.7337150574],"type":"Point"}
}