{
  "type": "Feature",
  "properties": {
    "iso:country":"BE",
    "sg:address":"Place Du March\u00e9 10",
    "sg:city":"Ch\u00e2telet",
    "sg:classifiers":[
        {
            "category":"Cafe",
            "type":"Food & Drink"
        }
    ],
    "sg:phone":"+32 71 40 00 24",
    "sg:postcode":"6200",
    "sg:province":"Hainaut",
    "sg:tags":[
        "snack-bars"
    ],
    "wof:name":"Buonissimo",
    "wof:placetype":"venue"
},
  "geometry": {"coordinates":[4.5213809013,50.4056472778],"type":"Point"}
}