{
  "type": "Feature",
  "properties": {
    "iso:country":"BE",
    "sg:address":"Monnikstraat 4",
    "sg:city":"Tremelo",
    "sg:classifiers":[
        {
            "category":"Shopping",
            "subcategory":"Clothing, Apparel, & Fashions",
            "type":"Retail Goods"
        }
    ],
    "sg:phone":"+32 16 53 20 72",
    "sg:postcode":"3128",
    "sg:province":"Vlaams-Brabant",
    "sg:tags":[
        "v\u00eatements",
        "pour",
        "dame"
    ],
    "wof:name":"Huis Coleta",
    "wof:placetype":"venue"
},
  "geometry": {"coordinates":[4.744644165,50.9954032898],"type":"Point"}
}