{
  "type": "Feature",
  "properties": {
    "addr:full":"Akkerstraat 21 Brugge West-Vlaanderen 8310",
    "addr:housenumber":"21",
    "addr:postcode":"8310",
    "addr:street":"Akkerstraat",
    "iso:country":"BE",
    "sg:address":"Akkerstraat 21",
    "sg:city":"Brugge",
    "sg:orig_category":"Advocaten and juridische adviseurs",
    "sg:phone":"+32 50 35 98 06",
    "sg:postcode":"8310",
    "sg:province":"West-Vlaanderen",
    "wof:name":"B. Gailliaert",
    "wof:placetype":"venue"
},
  "geometry": {"coordinates":[3.2567100525,51.2123146057],"type":"Point"}
}