{
  "type": "Feature",
  "properties": {
    "addr:full":"Avenue Du Haut Pont 24 Bruxelles (ixelles) Bruxelles-Capitale 1050",
    "addr:housenumber":"24",
    "addr:postcode":"1050",
    "addr:street":"Avenue Du Haut Pont",
    "iso:country":"BE",
    "sg:address":"Avenue Du Haut Pont 24",
    "sg:city":"Bruxelles (ixelles)",
    "sg:classifiers":[
        {
            "category":"Health Services",
            "subcategory":"Health Practitioner",
            "type":"Services"
        }
    ],
    "sg:phone":"+32 475 28 53 92",
    "sg:postcode":"1050",
    "sg:province":"Bruxelles-Capitale",
    "sg:tags":[
        "physiotherapist"
    ],
    "wof:name":"Dejeneffe Philippe",
    "wof:placetype":"venue"
},
  "geometry": {"coordinates":[4.354156971,50.8206634521],"type":"Point"}
}