{
  "type": "Feature",
  "properties": {
    "iso:country":"BE",
    "sg:address":"Oosterzeelsesteenweg 5",
    "sg:city":"Wetteren",
    "sg:orig_category":"Plantes and fleurs Gr",
    "sg:phone":"+32 9 366 31 33",
    "sg:postcode":"9230",
    "sg:province":"Oost-Vlaanderen",
    "wof:name":"Tuve",
    "wof:placetype":"venue"
},
  "geometry": {"coordinates":[3.8439118862,50.9831047058],"type":"Point"}
}