{
  "type": "Feature",
  "properties": {
    "addr:full":"Rue Du Bois Rosine 2bb Modave Li\u00e8ge 4577",
    "addr:housenumber":"2bb",
    "addr:postcode":"4577",
    "addr:street":"Rue Du Bois Rosine",
    "iso:country":"BE",
    "sg:address":"Rue Du Bois Rosine 2bb",
    "sg:city":"Modave",
    "sg:classifiers":[
        {
            "category":"Insurance",
            "subcategory":"Life Insurance",
            "type":"Services"
        }
    ],
    "sg:phone":"+32 85 51 95 50",
    "sg:postcode":"4577",
    "sg:province":"Li\u00e8ge",
    "sg:tags":[
        "assurance"
    ],
    "wof:name":"De Biolley Michel",
    "wof:placetype":"venue"
},
  "geometry": {"coordinates":[5.323223114,50.4908905029],"type":"Point"}
}