{
  "type": "Feature",
  "properties": {
    "addr:full":"Place Communale 17 Silly Hainaut 7830",
    "addr:housenumber":"17",
    "addr:postcode":"7830",
    "addr:street":"Place Communale",
    "iso:country":"BE",
    "sg:address":"Place Communale 17",
    "sg:city":"Silly",
    "sg:orig_category":"Biblioth\u00e8ques and archives publiques",
    "sg:phone":"+32 68 25 05 13",
    "sg:postcode":"7830",
    "sg:province":"Hainaut",
    "wof:name":"Biblioth\u00c8que Publique",
    "wof:placetype":"venue"
},
  "geometry": {"coordinates":[3.9237558842,50.6489105225],"type":"Point"}
}