{
  "type": "Feature",
  "properties": {
    "addr:full":"Tieltseweg 149 Aarschot (rillaar) Vlaams-Brabant 3202",
    "addr:housenumber":"149",
    "addr:postcode":"3202",
    "iso:country":"BE",
    "sg:address":"Tieltseweg 149",
    "sg:city":"Aarschot (rillaar)",
    "sg:classifiers":[
        {
            "category":"Health Services",
            "subcategory":"Health Practitioner",
            "type":"Services"
        }
    ],
    "sg:phone":"+32 16 50 19 75",
    "sg:postcode":"3202",
    "sg:province":"Vlaams-Brabant",
    "sg:tags":[
        "physiotherapist"
    ],
    "wof:name":"De Rore Els",
    "wof:placetype":"venue"
},
  "geometry": {"coordinates":[4.8945579529,50.9678993225],"type":"Point"}
}