{
  "type": "Feature",
  "properties": {
    "iso:country":"BE",
    "sg:address":"De Breyne Peellaertstr. 13b1",
    "sg:city":"Diksmuide",
    "sg:orig_category":"Studios photographiques",
    "sg:phone":"+32 51 50 04 65",
    "sg:postcode":"8600",
    "sg:province":"West-Vlaanderen",
    "wof:name":"Paulette Vanhille",
    "wof:placetype":"venue"
},
  "geometry": {"coordinates":[2.8654680252,51.0343055725],"type":"Point"}
}