{
  "type": "Feature",
  "properties": {
    "addr:full":"Place Du Levant 1 Ottignies-louvain-la-neuve Brabant Wallon 1348",
    "addr:housenumber":"1",
    "addr:postcode":"1348",
    "addr:street":"Place Du Levant",
    "iso:country":"BE",
    "sg:address":"Place Du Levant 1",
    "sg:city":"Ottignies-louvain-la-neuve",
    "sg:orig_category":"Hoger onderwijs",
    "sg:phone":"+32 10 47 21 12",
    "sg:postcode":"1348",
    "sg:province":"Brabant Wallon",
    "wof:name":"U.c.l.-d\u00c9partement Amco",
    "wof:placetype":"venue"
},
  "geometry": {"coordinates":[4.6227231026,50.6683692932],"type":"Point"}
}