{
  "type": "Feature",
  "properties": {
    "addr:full":"Adolphstrasse 62 Grossrohrsdorf 01900",
    "addr:housenumber":"62",
    "addr:postcode":"01900",
    "addr:street":"Adolphstrasse;Grossrohrsdorf",
    "iso:country":"BE",
    "sg:address":"Adolphstrasse 62",
    "sg:city":"Grossrohrsdorf",
    "sg:classifiers":[
        {
            "category":"Manufacturing",
            "subcategory":"Building Materials",
            "type":"Manufacturing & Wholesale Goods"
        }
    ],
    "sg:postcode":"01900",
    "sg:tags":[
        "boiler",
        "manufacturer"
    ],
    "wof:name":"Haase Gfk-technik",
    "wof:placetype":"venue"
},
  "geometry": {"coordinates":[14.0280771255,51.1360435486],"type":"Point"}
}