{
  "type": "Feature",
  "properties": {
    "iso:country":"BE",
    "sg:address":"Groenewoud 23",
    "sg:city":"Hoogstraten",
    "sg:orig_category":"Experts-comptables",
    "sg:phone":"+32 3 314 69 56",
    "sg:postcode":"2320",
    "sg:province":"Antwerpen",
    "wof:name":"Philippe Verhoeven",
    "wof:placetype":"venue"
},
  "geometry": {"coordinates":[4.7676849365,51.3993225098],"type":"Point"}
}