{
  "type": "Feature",
  "properties": {
    "addr:full":"Rue De Bayet 64 Namur (gelbress\u00e9e) Namur 5024",
    "addr:housenumber":"64",
    "addr:postcode":"5024",
    "addr:street":"Rue De Bayet",
    "iso:country":"BE",
    "sg:address":"Rue De Bayet 64",
    "sg:city":"Namur (gelbress\u00e9e)",
    "sg:classifiers":[
        {
            "category":"Retail",
            "subcategory":"Veterinary Services",
            "type":"Services"
        }
    ],
    "sg:phone":"+32 81 58 05 37",
    "sg:postcode":"5024",
    "sg:province":"Namur",
    "sg:tags":[
        "veterinarian"
    ],
    "wof:name":"Denis",
    "wof:placetype":"venue"
},
  "geometry": {"coordinates":[4.9682879448,50.4898643494],"type":"Point"}
}