{
  "type": "Feature",
  "properties": {
    "iso:country":"BE",
    "sg:address":"Rue De Roucourt 53",
    "sg:city":"Peruwelz",
    "sg:orig_category":"Apotheken",
    "sg:phone":"+32 69 77 38 73",
    "sg:postcode":"7600",
    "sg:province":"Hainaut",
    "wof:name":"Mourin-brotcorne",
    "wof:placetype":"venue"
},
  "geometry": {"coordinates":[3.5889749527,50.510684967],"type":"Point"}
}