{
  "type": "Feature",
  "properties": {
    "iso:country":"BE",
    "sg:address":"Pittemsesteenweg 23",
    "sg:city":"Tielt",
    "sg:classifiers":[
        {
            "category":"Restaurant",
            "type":"Food & Drink"
        }
    ],
    "sg:phone":"+32 51 40 88 81",
    "sg:postcode":"8700",
    "sg:province":"West-Vlaanderen",
    "wof:name":"Amethyst Kristal",
    "wof:placetype":"venue"
},
  "geometry": {"coordinates":[3.3102800846,50.9977226257],"type":"Point"}
}