{
  "type": "Feature",
  "properties": {
    "iso:country":"BE",
    "sg:address":"Looi 10",
    "sg:city":"Rijkevorsel",
    "sg:orig_category":"Eleveurs de bovins",
    "sg:phone":"+32 3 312 08 29",
    "sg:postcode":"2310",
    "sg:province":"Antwerpen",
    "wof:name":"Lucas Aertsen",
    "wof:placetype":"venue"
},
  "geometry": {"coordinates":[4.7503809929,51.3330612183],"type":"Point"}
}