{
  "type": "Feature",
  "properties": {
    "addr:full":"Sint-kruisstraat 21 Brugge (assebroek) West-Vlaanderen 8310",
    "addr:housenumber":"21",
    "addr:postcode":"8310",
    "addr:street":"Sint-Kruisstraat",
    "iso:country":"BE",
    "sg:address":"Sint-kruisstraat 21",
    "sg:city":"Brugge (assebroek)",
    "sg:classifiers":[
        {
            "category":"Health Services",
            "subcategory":"Doctor",
            "type":"Services"
        }
    ],
    "sg:phone":"+32 50 36 38 20",
    "sg:postcode":"8310",
    "sg:province":"West-Vlaanderen",
    "sg:tags":[
        "medicinephysicians",
        "surgeon"
    ],
    "wof:name":"Loncke Jan",
    "wof:placetype":"venue"
},
  "geometry": {"coordinates":[3.2542169094,51.2037239075],"type":"Point"}
}