{
  "type": "Feature",
  "properties": {
    "addr:full":"Rue Henri Aubry 54 La Louvi\u00e8re (haine-saint-paul) Hainaut 7100",
    "addr:housenumber":"54",
    "addr:postcode":"7100",
    "addr:street":"Rue Henri Aubry",
    "iso:country":"BE",
    "sg:address":"Rue Henri Aubry 54",
    "sg:city":"La Louvi\u00e8re (haine-saint-paul)",
    "sg:classifiers":[
        {
            "category":"Food & Beverages",
            "subcategory":"Groceries & Convenience Stores",
            "type":"Retail Goods"
        }
    ],
    "sg:phone":"+32 64 21 18 33",
    "sg:postcode":"7100",
    "sg:province":"Hainaut",
    "sg:tags":[
        "grocer"
    ],
    "wof:name":"D'arco G",
    "wof:placetype":"venue"
},
  "geometry": {"coordinates":[4.1850848198,50.4748649597],"type":"Point"}
}