{
  "type": "Feature",
  "properties": {
    "addr:full":"Rue Des Combattants 10 Donceel Li\u00e8ge 4357",
    "addr:housenumber":"10",
    "addr:postcode":"4357",
    "addr:street":"Rue Des Combattants",
    "iso:country":"BE",
    "sg:address":"Rue Des Combattants 10",
    "sg:city":"Donceel",
    "sg:orig_category":"Bloemen and planten",
    "sg:phone":"+32 19 54 42 26",
    "sg:postcode":"4357",
    "sg:province":"Li\u00e8ge",
    "wof:name":"Le Panier Fleuri",
    "wof:placetype":"venue"
},
  "geometry": {"coordinates":[5.3117599487,50.6598777771],"type":"Point"}
}