{
  "type": "Feature",
  "properties": {
    "iso:country":"BE",
    "sg:address":"Hof Ten Berglaan 1",
    "sg:city":"Puurs",
    "sg:orig_category":"Autombile concessionaires",
    "sg:phone":"+32 3 889 00 95",
    "sg:postcode":"2870",
    "sg:province":"Antwerpen",
    "wof:name":"Reyniers Bvba",
    "wof:placetype":"venue"
},
  "geometry": {"coordinates":[4.2734069824,51.0751457214],"type":"Point"}
}