{
  "type": "Feature",
  "properties": {
    "addr:full":"Degstraat 12 Herselt Antwerpen 2230",
    "addr:housenumber":"12",
    "addr:postcode":"2230",
    "addr:street":"Degstraat",
    "iso:country":"BE",
    "sg:address":"Degstraat 12",
    "sg:city":"Herselt",
    "sg:classifiers":[
        {
            "category":"Animal Shelter",
            "type":"Public Place"
        }
    ],
    "sg:phone":"+32 14 84 17 53",
    "sg:postcode":"2230",
    "sg:province":"Antwerpen",
    "wof:name":"De Witte Bremshoeve",
    "wof:placetype":"venue"
},
  "geometry": {"coordinates":[4.963889122,51.0520858765],"type":"Point"}
}