{
  "type": "Feature",
  "properties": {
    "iso:country":"BE",
    "sg:address":"Mechelsesteenweg 68bg",
    "sg:city":"Mortsel",
    "sg:orig_category":"Plaatsen van vloer- and muurbekleding Schilders",
    "sg:phone":"+32 3 448 03 50",
    "sg:postcode":"2640",
    "sg:province":"Antwerpen",
    "wof:name":"Lieven Van Den Abbeele",
    "wof:placetype":"venue"
},
  "geometry": {"coordinates":[4.4514551163,51.1681365967],"type":"Point"}
}