{
  "type": "Feature",
  "properties": {
    "addr:full":"Rue De L'autonomie 35 Bruxelles (anderlecht) Bruxelles-Capitale 1070",
    "addr:housenumber":"35",
    "addr:postcode":"1070",
    "addr:street":"Rue De L'Autonomie",
    "iso:country":"BE",
    "sg:address":"Rue De L'autonomie 35",
    "sg:city":"Bruxelles (anderlecht)",
    "sg:orig_category":"Non-Classified Establishments",
    "sg:phone":"+32 2 520 37 39",
    "sg:postcode":"1070",
    "sg:province":"Bruxelles-Capitale",
    "wof:name":"Yonder-remake Ltd Scrl",
    "wof:placetype":"venue"
},
  "geometry": {"coordinates":[4.3368759155,50.839931488],"type":"Point"}
}