{
  "type": "Feature",
  "properties": {
    "iso:country":"BE",
    "sg:address":"Ommeganckstraat 66 Box 1",
    "sg:city":"Antwerpen",
    "sg:classifiers":[
        {
            "category":"Professional",
            "subcategory":"Art Services",
            "type":"Services"
        }
    ],
    "sg:phone":"+32 3 232 26 48",
    "sg:postcode":"2018",
    "sg:province":"Antwerpen",
    "sg:tags":[
        "photographer"
    ],
    "wof:name":"De Waal K",
    "wof:placetype":"venue"
},
  "geometry": {"coordinates":[4.425110817,51.2164306641],"type":"Point"}
}