{
  "type": "Feature",
  "properties": {
    "addr:full":"Rue Des Brasseurs 12 Ch\u00e2telet Hainaut 6200",
    "addr:housenumber":"12",
    "addr:postcode":"6200",
    "addr:street":"Rue Des Brasseurs",
    "iso:country":"BE",
    "sg:address":"Rue Des Brasseurs 12",
    "sg:city":"Ch\u00e2telet",
    "sg:classifiers":[
        {
            "category":"Shopping",
            "subcategory":"Computers & Home Electronics",
            "type":"Retail Goods"
        }
    ],
    "sg:phone":"+32 71 38 10 62",
    "sg:postcode":"6200",
    "sg:province":"Hainaut",
    "sg:tags":[
        "-",
        "television",
        "radio"
    ],
    "wof:name":"J P Delatte",
    "wof:placetype":"venue"
},
  "geometry": {"coordinates":[4.5199189186,50.4039001465],"type":"Point"}
}