{
  "type": "Feature",
  "properties": {
    "addr:full":"C. Van Der Heydenlaan 2 Gent Oost-Vlaanderen 9041",
    "addr:housenumber":"2",
    "addr:postcode":"9041",
    "addr:street":"C. Van Der Heydenlaan;Oost-Vlaanderen",
    "iso:country":"BE",
    "sg:address":"C. Van Der Heydenlaan 2",
    "sg:city":"Gent",
    "sg:orig_category":"Notarissen",
    "sg:phone":"+32 9 255 94 10",
    "sg:postcode":"9041",
    "sg:province":"Oost-Vlaanderen",
    "wof:name":"Alex De Wulf",
    "wof:placetype":"venue"
},
  "geometry": {"coordinates":[3.761868,51.0965614319],"type":"Point"}
}