{
  "type": "Feature",
  "properties": {
    "addr:full":"Zand 10 Lokeren Oost-Vlaanderen 9160",
    "addr:housenumber":"10",
    "addr:postcode":"9160",
    "addr:street":"Zand",
    "iso:country":"BE",
    "sg:address":"Zand 10",
    "sg:city":"Lokeren",
    "sg:classifiers":[
        {
            "category":"Food & Beverages",
            "subcategory":"Fruits & Vegetables",
            "type":"Retail Goods"
        }
    ],
    "sg:phone":"+32 9 339 08 40",
    "sg:postcode":"9160",
    "sg:province":"Oost-Vlaanderen",
    "sg:tags":[
        "-"
    ],
    "wof:name":"Vitamieneken",
    "wof:placetype":"venue"
},
  "geometry": {"coordinates":[3.9952170849,51.1025047302],"type":"Point"}
}