{
  "type": "Feature",
  "properties": {
    "addr:full":"Elsstraat 6 Laarne Oost-Vlaanderen 9270",
    "addr:housenumber":"6",
    "addr:postcode":"9270",
    "addr:street":"Elsstraat",
    "iso:country":"BE",
    "sg:address":"Elsstraat 6",
    "sg:city":"Laarne",
    "sg:orig_category":"Eleveurs de bovins",
    "sg:phone":"+32 9 355 74 87",
    "sg:postcode":"9270",
    "sg:province":"Oost-Vlaanderen",
    "wof:name":"Willem Van De Velde",
    "wof:placetype":"venue"
},
  "geometry": {"coordinates":[3.845001936,51.0507545471],"type":"Point"}
}