{
  "type": "Feature",
  "properties": {
    "addr:full":"Molenstraatje 3 Herent Vlaams-Brabant 3020",
    "addr:housenumber":"3",
    "addr:postcode":"3020",
    "addr:street":"Molenstraatje",
    "iso:country":"BE",
    "sg:address":"Molenstraatje 3",
    "sg:city":"Herent",
    "sg:orig_category":"Quincailleries. Fabrication and montage de mobilier. Installation de menuiserie en bois and plastiqu",
    "sg:phone":"+32 16 48 16 07",
    "sg:postcode":"3020",
    "sg:province":"Vlaams-Brabant",
    "wof:name":"G. Vanderwegen",
    "wof:placetype":"venue"
},
  "geometry": {"coordinates":[4.6749200821,50.9079055786],"type":"Point"}
}