{
  "type": "Feature",
  "properties": {
    "addr:full":"Atealaan 7 Herenthout Antwerpen 2270",
    "addr:housenumber":"7",
    "addr:postcode":"2270",
    "addr:street":"Atealaan",
    "iso:country":"BE",
    "sg:address":"Atealaan 7",
    "sg:city":"Herenthout",
    "sg:orig_category":"Fournitures de bureau. Imprimeries and copyshops",
    "sg:phone":"+32 14 28 58 58",
    "sg:postcode":"2270",
    "sg:province":"Antwerpen",
    "wof:name":"Kempische Papierhandel",
    "wof:placetype":"venue"
},
  "geometry": {"coordinates":[4.8035979271,51.1551551819],"type":"Point"}
}