{
  "type": "Feature",
  "properties": {
    "iso:country":"BE",
    "sg:address":"Chauss\u00c9e Churchill 79",
    "sg:city":"Saint-nicolas",
    "sg:orig_category":"Enseignement maternel and primaire",
    "sg:phone":"+32 4 362 90 96",
    "sg:postcode":"4420",
    "sg:province":"Li\u00e8ge",
    "wof:name":"La Petite Ecole",
    "wof:placetype":"venue"
},
  "geometry": {"coordinates":[5.5244197845,50.6453590393],"type":"Point"}
}