{
  "type": "Feature",
  "properties": {
    "addr:full":"Terhulpensesteenweg 101 Overijse Vlaams-Brabant 3090",
    "addr:housenumber":"101",
    "addr:postcode":"3090",
    "addr:street":"Terhulpensesteenweg",
    "iso:country":"BE",
    "sg:address":"Terhulpensesteenweg 101",
    "sg:city":"Overijse",
    "sg:classifiers":[
        {
            "category":"Utilities",
            "subcategory":"Water",
            "type":"Services"
        }
    ],
    "sg:phone":"+32 2 687 35 25",
    "sg:postcode":"3090",
    "sg:province":"Vlaams-Brabant",
    "sg:tags":[
        "softener"
    ],
    "wof:name":"Eurorepar",
    "wof:placetype":"venue"
},
  "geometry": {"coordinates":[4.5423989296,50.7666015625],"type":"Point"}
}