{
  "type": "Feature",
  "properties": {
    "iso:country":"BE",
    "sg:address":"Rue De Taillis-pr\u00c9 180",
    "sg:city":"Chatelet",
    "sg:classifiers":[
        {
            "category":"Cafe",
            "type":"Food & Drink"
        }
    ],
    "sg:phone":"+32 71 39 12 00",
    "sg:postcode":"6200",
    "sg:province":"Hainaut",
    "sg:tags":[
        "caf\u00e9s"
    ],
    "wof:name":"Josiane Debrux",
    "wof:placetype":"venue"
},
  "geometry": {"coordinates":[4.5112547874,50.4378318787],"type":"Point"}
}