{
  "type": "Feature",
  "properties": {
    "iso:country":"BE",
    "sg:address":"Fays 51",
    "sg:city":"Ciney",
    "sg:orig_category":"HUISBRANDOLIE",
    "sg:phone":"+32 83 21 45 45",
    "sg:postcode":"5590",
    "sg:province":"Namur",
    "wof:name":"Fe. Wegria P.",
    "wof:placetype":"venue"
},
  "geometry": {"coordinates":[5.1022520065,50.297088623],"type":"Point"}
}