{
  "type": "Feature",
  "properties": {
    "addr:full":"Nerenhoek 71 Lochristi Oost-Vlaanderen 9080",
    "addr:housenumber":"71",
    "addr:postcode":"9080",
    "addr:street":"Nerenhoek",
    "iso:country":"BE",
    "sg:address":"Nerenhoek 71",
    "sg:city":"Lochristi",
    "sg:classifiers":[
        {
            "category":"Organizations",
            "subcategory":"Professional Association",
            "type":"Services"
        }
    ],
    "sg:phone":"+32 9 355 89 89",
    "sg:postcode":"9080",
    "sg:province":"Oost-Vlaanderen",
    "sg:tags":[
        "domestiques",
        "organisation",
        "animaux",
        "pour"
    ],
    "wof:name":"Dierenbescherming Vlaanderense Dierenketen",
    "wof:placetype":"venue"
},
  "geometry": {"coordinates":[3.8325359821,51.1336936951],"type":"Point"}
}