{
  "type": "Feature",
  "properties": {
    "iso:country":"BE",
    "sg:address":"Provincieweg 306",
    "sg:city":"Herzele (hillegem)",
    "sg:classifiers":[
        {
            "category":"Retail",
            "subcategory":"Veterinary Services",
            "type":"Services"
        }
    ],
    "sg:phone":"+32 53 63 21 10",
    "sg:postcode":"9550",
    "sg:province":"Oost-Vlaanderen",
    "sg:tags":[
        "veterinarian"
    ],
    "wof:name":"Gillijns E",
    "wof:placetype":"venue"
},
  "geometry": {"coordinates":[3.8787400723,50.8998908997],"type":"Point"}
}