{
  "type": "Feature",
  "properties": {
    "addr:full":"Park Tremeland 50 Tremelo Vlaams-Brabant 3120",
    "addr:housenumber":"50",
    "addr:postcode":"3120",
    "addr:street":"Park Tremeland",
    "iso:country":"BE",
    "sg:address":"Park Tremeland 50",
    "sg:city":"Tremelo",
    "sg:classifiers":[
        {
            "category":"Professional",
            "subcategory":"Accounting & Tax Preparation",
            "type":"Services"
        }
    ],
    "sg:phone":"+32 16 52 07 15",
    "sg:postcode":"3120",
    "sg:province":"Vlaams-Brabant",
    "sg:tags":[
        "bookkeeper"
    ],
    "wof:name":"Vervan Finvest Bvba",
    "wof:placetype":"venue"
},
  "geometry": {"coordinates":[4.7268538475,51.0031929016],"type":"Point"}
}