{
  "type": "Feature",
  "properties": {
    "addr:full":"Vesten 40 Geraardsbergen Oost-Vlaanderen 9500",
    "addr:housenumber":"40",
    "addr:postcode":"9500",
    "addr:street":"Vesten",
    "iso:country":"BE",
    "sg:address":"Vesten 40",
    "sg:city":"Geraardsbergen",
    "sg:classifiers":[
        {
            "category":"Personal",
            "subcategory":"Beauty Salon",
            "type":"Services"
        }
    ],
    "sg:phone":"+32 54 41 18 09",
    "sg:postcode":"9500",
    "sg:province":"Oost-Vlaanderen",
    "sg:tags":[
        "de",
        "coiffure"
    ],
    "wof:name":"Coiffure Monique",
    "wof:placetype":"venue"
},
  "geometry": {"coordinates":[3.8846189976,50.7723884583],"type":"Point"}
}