{
  "type": "Feature",
  "properties": {
    "addr:full":"Turnhoutsebaan 532 Schilde Antwerpen 2970",
    "addr:housenumber":"532",
    "addr:postcode":"2970",
    "addr:street":"Turnhoutsebaan",
    "iso:country":"BE",
    "sg:address":"Turnhoutsebaan 532",
    "sg:city":"Schilde",
    "sg:classifiers":[
        {
            "category":"Bars & Pubs",
            "type":"Food & Drink"
        }
    ],
    "sg:phone":"+32 3 384 08 06",
    "sg:postcode":"2970",
    "sg:province":"Antwerpen",
    "wof:name":"Black Panter",
    "wof:placetype":"venue"
},
  "geometry": {"coordinates":[4.6100111008,51.2513504028],"type":"Point"}
}