{
  "type": "Feature",
  "properties": {
    "iso:country":"BE",
    "sg:address":"Thomasboslaan 98",
    "sg:city":"Maasmechelen",
    "sg:orig_category":"Apotheken",
    "sg:phone":"+32 89 76 07 38",
    "sg:postcode":"3630",
    "sg:province":"Limburg",
    "wof:name":"Apotheek Desiron",
    "wof:placetype":"venue"
},
  "geometry": {"coordinates":[5.6823549271,50.9809417725],"type":"Point"}
}