{
  "type": "Feature",
  "properties": {
    "addr:full":"Wapenplaats 33 Dentergem (wakken) West-Vlaanderen 8720",
    "addr:housenumber":"33",
    "addr:postcode":"8720",
    "addr:street":"Wapenplaats",
    "iso:country":"BE",
    "sg:address":"Wapenplaats 33",
    "sg:city":"Dentergem (wakken)",
    "sg:classifiers":[
        {
            "category":"Home & Garden",
            "subcategory":"Household Appliances",
            "type":"Retail Goods"
        }
    ],
    "sg:phone":"+32 56 60 23 30",
    "sg:postcode":"8720",
    "sg:province":"West-Vlaanderen",
    "sg:tags":[
        "housewares",
        "-"
    ],
    "wof:name":"Van Acker-robberecht",
    "wof:placetype":"venue"
},
  "geometry": {"coordinates":[3.3979671001,50.9310035706],"type":"Point"}
}