{
  "type": "Feature",
  "properties": {
    "iso:country":"BE",
    "sg:address":"Chauss\u00e9e De Gand 280-282",
    "sg:city":"Bruxelles (molenbeek-saint-jean)",
    "sg:classifiers":[
        {
            "category":"Organizations",
            "subcategory":"Community Association",
            "type":"Services"
        }
    ],
    "sg:phone":"+32 2 410 59 80",
    "sg:postcode":"1080",
    "sg:province":"Bruxelles-Capitale",
    "sg:tags":[
        "box",
        "cardboard"
    ],
    "wof:name":"Imprepack Cartonnages & Imprimerie Winderickx",
    "wof:placetype":"venue"
},
  "geometry": {"coordinates":[4.3268928528,50.8566665649],"type":"Point"}
}