{
  "type": "Feature",
  "properties": {
    "addr:full":"Ruisbroekdorp 32bb Puurs Antwerpen 2870",
    "addr:housenumber":"32bb",
    "addr:postcode":"2870",
    "addr:street":"Ruisbroekdorp",
    "iso:country":"BE",
    "sg:address":"Ruisbroekdorp 32bb",
    "sg:city":"Puurs",
    "sg:orig_category":"Enseignement maternel and primaire",
    "sg:phone":"+32 3 886 89 70",
    "sg:postcode":"2870",
    "sg:province":"Antwerpen",
    "wof:name":"Vrije Basisschool",
    "wof:placetype":"venue"
},
  "geometry": {"coordinates":[4.3316159248,51.0890922546],"type":"Point"}
}