{
  "type": "Feature",
  "properties": {
    "addr:full":"Heuvelstraat 150 Boechout Antwerpen 2530",
    "addr:housenumber":"150",
    "addr:postcode":"2530",
    "addr:street":"Heuvelstraat",
    "iso:country":"BE",
    "sg:address":"Heuvelstraat 150",
    "sg:city":"Boechout",
    "sg:orig_category":"Artsen and specialisten",
    "sg:phone":"+32 3 454 13 15",
    "sg:postcode":"2530",
    "sg:province":"Antwerpen",
    "wof:name":"Leen De Schampheleire",
    "wof:placetype":"venue"
},
  "geometry": {"coordinates":[4.4974350929,51.1634216309],"type":"Point"}
}