{
  "type": "Feature",
  "properties": {
    "addr:full":"Poelsdijk 6 Houthalen-helchteren Limburg 3530",
    "addr:housenumber":"6",
    "addr:postcode":"3530",
    "addr:street":"Poelsdijk",
    "iso:country":"BE",
    "sg:address":"Poelsdijk 6",
    "sg:city":"Houthalen-helchteren",
    "sg:classifiers":[
        {
            "category":"Personal",
            "subcategory":"Beauty Salon",
            "type":"Services"
        }
    ],
    "sg:phone":"+32 11 52 17 83",
    "sg:postcode":"3530",
    "sg:province":"Limburg",
    "sg:tags":[
        "de",
        "coiffure"
    ],
    "wof:name":"Coiffure Sil",
    "wof:placetype":"venue"
},
  "geometry": {"coordinates":[5.3719201088,51.0310020447],"type":"Point"}
}