{
  "type": "Feature",
  "properties": {
    "addr:full":"Lazarijstraat 52 Hasselt Limburg 3500",
    "addr:housenumber":"52",
    "addr:postcode":"3500",
    "addr:street":"Lazarijstraat",
    "iso:country":"BE",
    "sg:address":"Lazarijstraat 52",
    "sg:city":"Hasselt",
    "sg:classifiers":[
        {
            "category":"Health Services",
            "subcategory":"Dentist",
            "type":"Services"
        }
    ],
    "sg:phone":"+32 11 25 43 84",
    "sg:postcode":"3500",
    "sg:province":"Limburg",
    "wof:name":"Smeets Inge",
    "wof:placetype":"venue"
},
  "geometry": {"coordinates":[5.3288908005,50.9348297119],"type":"Point"}
}