{
  "type": "Feature",
  "properties": {
    "iso:country":"BE",
    "sg:address":"Waversebaan 83",
    "sg:city":"Leuven",
    "sg:orig_category":"Diensten voor huisdieren",
    "sg:phone":"+32 16 23 13 71",
    "sg:postcode":"3001",
    "sg:province":"Vlaams-Brabant",
    "wof:name":"Lady Leen",
    "wof:placetype":"venue"
},
  "geometry": {"coordinates":[4.6934990883,50.8636741638],"type":"Point"}
}