{
  "type": "Feature",
  "properties": {
    "addr:full":"Graaf De Broquevillestraat 35 Mol Antwerpen 2400",
    "addr:housenumber":"35",
    "addr:postcode":"2400",
    "addr:street":"Graaf De Broquevillestraat",
    "iso:country":"BE",
    "sg:address":"Graaf De Broquevillestraat 35",
    "sg:city":"Mol",
    "sg:orig_category":"Banques and organismes de cr\u00e9dit",
    "sg:phone":"+32 14 31 24 81",
    "sg:postcode":"2400",
    "sg:province":"Antwerpen",
    "wof:name":"Fortis",
    "wof:placetype":"venue"
},
  "geometry": {"coordinates":[5.1167721748,51.1852722168],"type":"Point"}
}