{
  "type": "Feature",
  "properties": {
    "addr:full":"Meerspoort 49b1 Oudenaarde Oost-Vlaanderen 9700",
    "addr:housenumber":"49b1",
    "addr:postcode":"9700",
    "addr:street":"Meerspoort",
    "iso:country":"BE",
    "sg:address":"Meerspoort 49b1",
    "sg:city":"Oudenaarde",
    "sg:orig_category":"Sportclubs",
    "sg:phone":"+32 55 31 38 77",
    "sg:postcode":"9700",
    "sg:province":"Oost-Vlaanderen",
    "wof:name":"Rap En Glad - Oudenaarde",
    "wof:placetype":"venue"
},
  "geometry": {"coordinates":[3.6011600494,50.840511322],"type":"Point"}
}