{
  "type": "Feature",
  "properties": {
    "addr:full":"Turfstraat 126 Genk Limburg 3600",
    "addr:housenumber":"126",
    "addr:postcode":"3600",
    "addr:street":"Turfstraat",
    "iso:country":"BE",
    "sg:address":"Turfstraat 126",
    "sg:city":"Genk",
    "sg:orig_category":"Woningbouw",
    "sg:phone":"+32 89 36 14 22",
    "sg:postcode":"3600",
    "sg:province":"Limburg",
    "wof:name":"Vekemans & Co",
    "wof:placetype":"venue"
},
  "geometry": {"coordinates":[5.4370231628,50.9671478271],"type":"Point"}
}