{
  "type": "Feature",
  "properties": {
    "iso:country":"BE",
    "sg:address":"Marcqstraat 3",
    "sg:city":"Brussel/bruxelles",
    "sg:orig_category":"Artsen and specialisten",
    "sg:phone":"+32 2 217 57 99",
    "sg:postcode":"1000",
    "sg:province":"Bruxelles-Capitale",
    "wof:name":"Dominique Vossen",
    "wof:placetype":"venue"
},
  "geometry": {"coordinates":[4.3486351967,50.8537406921],"type":"Point"}
}