{
  "type": "Feature",
  "properties": {
    "iso:country":"BE",
    "sg:address":"Rue De Buvrinnes 4",
    "sg:city":"Binche",
    "sg:orig_category":"Catering and organisation de f\u00eates. Alimentation sp\u00e9cialis\u00e9e. Epiceries",
    "sg:phone":"+32 64 33 23 06",
    "sg:postcode":"7130",
    "sg:province":"Hainaut",
    "wof:name":"Au Petit Bonhomme De Binche",
    "wof:placetype":"venue"
},
  "geometry": {"coordinates":[4.1709008217,50.4077911377],"type":"Point"}
}