{
  "type": "Feature",
  "properties": {
    "addr:full":"Archimedesstraat 21 Brussel/bruxelles Bruxelles-Capitale 1000",
    "addr:housenumber":"21",
    "addr:postcode":"1000",
    "addr:street":"Archimedesstraat;/",
    "iso:country":"BE",
    "sg:address":"Archimedesstraat 21",
    "sg:city":"Brussel/bruxelles",
    "sg:orig_category":"Banken and kredietinstellingen",
    "sg:phone":"+32 2 230 76 95",
    "sg:postcode":"1000",
    "sg:province":"Bruxelles-Capitale",
    "wof:name":"Fortis",
    "wof:placetype":"venue"
},
  "geometry": {"coordinates":[4.3840608597,50.8436317444],"type":"Point"}
}