{
  "type": "Feature",
  "properties": {
    "addr:full":"Miksebaan 122 Brasschaat Antwerpen 2930",
    "addr:housenumber":"122",
    "addr:postcode":"2930",
    "addr:street":"Miksebaan",
    "iso:country":"BE",
    "sg:address":"Miksebaan 122",
    "sg:city":"Brasschaat",
    "sg:classifiers":[
        {
            "category":"Health Services",
            "subcategory":"Dentist",
            "type":"Services"
        }
    ],
    "sg:phone":"+32 3 652 05 87",
    "sg:postcode":"2930",
    "sg:province":"Antwerpen",
    "wof:name":"Callewaert P",
    "wof:placetype":"venue"
},
  "geometry": {"coordinates":[4.5097088814,51.2939872742],"type":"Point"}
}