{
  "type": "Feature",
  "properties": {
    "iso:country":"BE",
    "sg:address":"Hopveld 31",
    "sg:city":"Buggenhout",
    "sg:orig_category":"Activit\u00e9s d\u00b4action sociale sans h\u00e9bergement",
    "sg:phone":"+32 52 33 14 42",
    "sg:postcode":"9255",
    "sg:province":"Oost-Vlaanderen",
    "wof:name":"Rode Kruis Buggenhout",
    "wof:placetype":"venue"
},
  "geometry": {"coordinates":[4.1580901146,51.0200386047],"type":"Point"}
}