{
  "type": "Feature",
  "properties": {
    "iso:country":"BE",
    "sg:address":"Rijksweg 517-519",
    "sg:city":"Dilsen-stokkem",
    "sg:orig_category":"Foto-uitrusting Fotografen and fotostudio's Fotolaboratoria",
    "sg:phone":"+32 89 75 64 55",
    "sg:postcode":"3650",
    "sg:province":"Limburg",
    "wof:name":"Jean-marie Van Goethemd",
    "wof:placetype":"venue"
},
  "geometry": {"coordinates":[5.7322149277,51.0401229858],"type":"Point"}
}