{
  "type": "Feature",
  "properties": {
    "iso:country":"BE",
    "sg:address":"Kapellensteenweg 61 Box 5",
    "sg:city":"Kalmthout",
    "sg:classifiers":[
        {
            "category":"Building & Trades",
            "subcategory":"Pest Control",
            "type":"Services"
        }
    ],
    "sg:phone":"+32 3 295 55 04",
    "sg:postcode":"2920",
    "sg:province":"Antwerpen",
    "sg:tags":[
        "painting",
        "contractor"
    ],
    "wof:name":"Algemene Schilderwerken Danny De Groof Vof",
    "wof:placetype":"venue"
},
  "geometry": {"coordinates":[4.474902153,51.3911437988],"type":"Point"}
}