{
  "type": "Feature",
  "properties": {
    "iso:country":"BE",
    "sg:address":"Avenue Du Bois Soleil 44",
    "sg:city":"Kraainem",
    "sg:classifiers":[
        {
            "category":"Health Services",
            "subcategory":"Doctor",
            "type":"Services"
        }
    ],
    "sg:phone":"+32 2 782 11 00",
    "sg:postcode":"1950",
    "sg:province":"Vlaams-Brabant",
    "sg:tags":[
        "medicinephysicians",
        "surgeon"
    ],
    "wof:name":"Keyen Annie",
    "wof:placetype":"venue"
},
  "geometry": {"coordinates":[4.4798598289,50.8338088989],"type":"Point"}
}