{
  "type": "Feature",
  "properties": {
    "addr:full":"Assenedestraat 53 Assenede (bassevelde) Oost-Vlaanderen 9968",
    "addr:housenumber":"53",
    "addr:postcode":"9968",
    "addr:street":"Assenedestraat",
    "iso:country":"BE",
    "sg:address":"Assenedestraat 53",
    "sg:city":"Assenede (bassevelde)",
    "sg:classifiers":[
        {
            "category":"Freight",
            "type":"Transportation"
        }
    ],
    "sg:phone":"+32 9 373 70 66",
    "sg:postcode":"9968",
    "sg:province":"Oost-Vlaanderen",
    "sg:tags":[
        "-",
        "transport"
    ],
    "wof:name":"Hertleer Transport",
    "wof:placetype":"venue"
},
  "geometry": {"coordinates":[3.6887938976,51.1923027039],"type":"Point"}
}