{
  "type": "Feature",
  "properties": {
    "iso:country":"BE",
    "sg:address":"Rue Jean-baptiste Vanp\u00e9 29",
    "sg:city":"Bruxelles (forest)",
    "sg:classifiers":[
        {
            "category":"Shopping",
            "subcategory":"Clothing, Apparel, & Fashions",
            "type":"Retail Goods"
        }
    ],
    "sg:phone":"+32 2 376 73 03",
    "sg:postcode":"1190",
    "sg:province":"Bruxelles-Capitale",
    "sg:tags":[
        "lady",
        "clothing",
        "-"
    ],
    "wof:name":"Denise (chez)",
    "wof:placetype":"venue"
},
  "geometry": {"coordinates":[4.318572998,50.8095970154],"type":"Point"}
}