{
  "type": "Feature",
  "properties": {
    "iso:country":"BE",
    "sg:address":"Laagweide 11",
    "sg:city":"Wevelgem",
    "sg:orig_category":"Installation \u00e9lectrique r\u00e9sidentielle",
    "sg:phone":"+32 56 37 01 90",
    "sg:postcode":"8560",
    "sg:province":"West-Vlaanderen",
    "wof:name":"E.c.s.",
    "wof:placetype":"venue"
},
  "geometry": {"coordinates":[3.2211880684,50.8450927734],"type":"Point"}
}