{
  "type": "Feature",
  "properties": {
    "addr:full":"Grote Markt 17 Tongeren Limburg 3700",
    "addr:housenumber":"17",
    "addr:postcode":"3700",
    "addr:street":"Grote Markt",
    "iso:country":"BE",
    "sg:address":"Grote Markt 17",
    "sg:city":"Tongeren",
    "sg:orig_category":"Verplichte sociale verzekeringen",
    "sg:phone":"+32 12 23 38 32",
    "sg:postcode":"3700",
    "sg:province":"Limburg",
    "wof:name":"Christelijke Mutualiteit",
    "wof:placetype":"venue"
},
  "geometry": {"coordinates":[5.4634299278,50.7806510925],"type":"Point"}
}