{
  "type": "Feature",
  "properties": {
    "addr:full":"Rue Des Fripiers 24b Bruxelles Bruxelles-Capitale 1000",
    "addr:housenumber":"24b",
    "addr:postcode":"1000",
    "addr:street":"Rue Des Fripiers",
    "iso:country":"BE",
    "sg:address":"Rue Des Fripiers 24b",
    "sg:city":"Bruxelles",
    "sg:classifiers":[
        {
            "category":"Health Services",
            "subcategory":"Dentist",
            "type":"Services"
        }
    ],
    "sg:phone":"+32 2 217 74 06",
    "sg:postcode":"1000",
    "sg:province":"Bruxelles-Capitale",
    "wof:name":"Toledano Jacky",
    "wof:placetype":"venue"
},
  "geometry": {"coordinates":[4.3523879051,50.8489341736],"type":"Point"}
}