{
  "type": "Feature",
  "properties": {
    "addr:full":"Leeuwerikenlei 23 Edegem Antwerpen 2650",
    "addr:housenumber":"23",
    "addr:postcode":"2650",
    "addr:street":"Leeuwerikenlei",
    "iso:country":"BE",
    "sg:address":"Leeuwerikenlei 23",
    "sg:city":"Edegem",
    "sg:classifiers":[
        {
            "category":"Professional",
            "subcategory":"Management & Consulting",
            "type":"Services"
        }
    ],
    "sg:phone":"+32 3 288 51 06",
    "sg:postcode":"2650",
    "sg:province":"Antwerpen",
    "sg:tags":[
        "marketing",
        "-",
        "consultant"
    ],
    "wof:name":"Marketing Plan Bvba",
    "wof:placetype":"venue"
},
  "geometry": {"coordinates":[4.4486660957,51.1511268616],"type":"Point"}
}