{
  "type": "Feature",
  "properties": {
    "iso:country":"BE",
    "sg:address":"Oossekouter 21",
    "sg:city":"Nevele",
    "sg:orig_category":"Afval and schroot Gh",
    "sg:phone":"+32 9 371 83 04",
    "sg:postcode":"9850",
    "sg:province":"Oost-Vlaanderen",
    "wof:name":"Eumaco",
    "wof:placetype":"venue"
},
  "geometry": {"coordinates":[3.5549840927,51.0418815613],"type":"Point"}
}