{
  "type": "Feature",
  "properties": {
    "iso:country":"BE",
    "sg:address":"Mgr. Morisstraat 4",
    "sg:city":"Peer",
    "sg:orig_category":"Varkenskwekers",
    "sg:phone":"+32 11 79 13 08",
    "sg:postcode":"3990",
    "sg:province":"Limburg",
    "wof:name":"Joannes Moris",
    "wof:placetype":"venue"
},
  "geometry": {"coordinates":[5.4565458298,51.1034622192],"type":"Point"}
}