{
  "type": "Feature",
  "properties": {
    "addr:full":"Tichelrei 1 Gent Oost-Vlaanderen 9000",
    "addr:housenumber":"1",
    "addr:postcode":"9000",
    "addr:street":"Tichelrei;Oost-Vlaanderen",
    "iso:country":"BE",
    "sg:address":"Tichelrei 1",
    "sg:city":"Gent",
    "sg:classifiers":[
        {
            "category":"Health Services",
            "subcategory":"Hospital",
            "type":"Services"
        }
    ],
    "sg:phone":"+32 9 235 42 11",
    "sg:postcode":"9000",
    "sg:province":"Oost-Vlaanderen",
    "wof:name":"A.z. Volkskliniek",
    "wof:placetype":"venue"
},
  "geometry": {"coordinates":[3.722589016,51.0607261658],"type":"Point"}
}