{
  "type": "Feature",
  "properties": {
    "addr:full":"Chauss\u00e9e De Beaumont 10 Mons Hainaut 7000",
    "addr:housenumber":"10",
    "addr:postcode":"7000",
    "addr:street":"Chausse\u0301E De Beaumont;Hainaut",
    "iso:country":"BE",
    "sg:address":"Chauss\u00e9e De Beaumont 10",
    "sg:city":"Mons",
    "sg:classifiers":[
        {
            "category":"Home & Garden",
            "subcategory":"Household Appliances",
            "type":"Retail Goods"
        }
    ],
    "sg:phone":"+32 65 31 92 62",
    "sg:postcode":"7000",
    "sg:province":"Hainaut",
    "sg:tags":[
        "repair",
        "mainten",
        "-",
        "electric"
    ],
    "wof:name":"Buccheri N",
    "wof:placetype":"venue"
},
  "geometry": {"coordinates":[3.9810550213,50.4499702454],"type":"Point"}
}