{
  "type": "Feature",
  "properties": {
    "addr:full":"Afrikalaan 73 Gent Oost-Vlaanderen 9000",
    "addr:housenumber":"73",
    "addr:postcode":"9000",
    "addr:street":"Afrikalaan;Oost-Vlaanderen",
    "iso:country":"BE",
    "sg:address":"Afrikalaan 73",
    "sg:city":"Gent",
    "sg:classifiers":[
        {
            "category":"Autos & Motor Vehicles",
            "subcategory":"Automobile Sales",
            "type":"Retail Goods"
        }
    ],
    "sg:phone":"+32 9 252 55 62",
    "sg:postcode":"9000",
    "sg:province":"Oost-Vlaanderen",
    "sg:tags":[
        "car",
        "used",
        "-"
    ],
    "wof:name":"Outreve",
    "wof:placetype":"venue"
},
  "geometry": {"coordinates":[3.7387750149,51.0651512146],"type":"Point"}
}