{
  "type": "Feature",
  "properties": {
    "addr:full":"Postiljonstraat 1 Ukkel/uccle Bruxelles-Capitale 1180",
    "addr:housenumber":"1",
    "addr:postcode":"1180",
    "addr:street":"Postiljonstraat;/",
    "iso:country":"BE",
    "sg:address":"Postiljonstraat 1",
    "sg:city":"Ukkel/uccle",
    "sg:orig_category":"Telecommunicatieapparaten Telecommunicatiesystemen",
    "sg:phone":"+32 2 344 00 95",
    "sg:postcode":"1180",
    "sg:province":"Bruxelles-Capitale",
    "wof:name":"Telecom Corner",
    "wof:placetype":"venue"
},
  "geometry": {"coordinates":[4.3394498825,50.8032188416],"type":"Point"}
}