{
  "type": "Feature",
  "properties": {
    "addr:full":"Rue De Douvrain 13 Mons (ghlin) Hainaut 7011",
    "addr:housenumber":"13",
    "addr:postcode":"7011",
    "addr:street":"Rue De Douvrain",
    "iso:country":"BE",
    "sg:address":"Rue De Douvrain 13",
    "sg:city":"Mons (ghlin)",
    "sg:classifiers":[
        {
            "category":"Manufacturing",
            "subcategory":"Motor Vehicles & Parts",
            "type":"Manufacturing & Wholesale Goods"
        }
    ],
    "sg:phone":"+32 65 31 22 80",
    "sg:postcode":"7011",
    "sg:province":"Hainaut",
    "sg:tags":[
        "body",
        "automobile",
        "construction",
        "-"
    ],
    "wof:name":"Ballez (carrosserie)",
    "wof:placetype":"venue"
},
  "geometry": {"coordinates":[3.912539959,50.4712982178],"type":"Point"}
}