{
  "type": "Feature",
  "properties": {
    "iso:country":"BE",
    "sg:address":"Tiensesteenweg 100",
    "sg:city":"Lubbeek (binkom)",
    "sg:classifiers":[
        {
            "category":"Parking",
            "subcategory":"Bicycle",
            "type":"Transportation"
        }
    ],
    "sg:phone":"+32 16 63 56 85",
    "sg:postcode":"3211",
    "sg:province":"Vlaams-Brabant",
    "sg:tags":[
        "chiropodist"
    ],
    "wof:name":"Brik\u00e9 A",
    "wof:placetype":"venue"
},
  "geometry": {"coordinates":[4.8877859116,50.8675537109],"type":"Point"}
}