{
  "type": "Feature",
  "properties": {
    "addr:full":"Rode Leeuwlaan 20 Mortsel Antwerpen 2640",
    "addr:housenumber":"20",
    "addr:postcode":"2640",
    "addr:street":"Rode Leeuwlaan",
    "iso:country":"BE",
    "sg:address":"Rode Leeuwlaan 20",
    "sg:city":"Mortsel",
    "sg:orig_category":"Non-Classified Establishments",
    "sg:phone":"+32 3 440 19 92",
    "sg:postcode":"2640",
    "sg:province":"Antwerpen",
    "wof:name":"Vandael J",
    "wof:placetype":"venue"
},
  "geometry": {"coordinates":[4.4488048553,51.1866798401],"type":"Point"}
}