{
  "type": "Feature",
  "properties": {
    "addr:full":"Rue Vis\u00c9 Voie 2 Oupeye Li\u00e8ge 4680",
    "addr:housenumber":"2",
    "addr:postcode":"4680",
    "addr:street":"Rue Vise\u0301 Voie",
    "iso:country":"BE",
    "sg:address":"Rue Vis\u00c9 Voie 2",
    "sg:city":"Oupeye",
    "sg:orig_category":"Parfumeries. Salons de coiffure",
    "sg:phone":"+32 4 264 36 43",
    "sg:postcode":"4680",
    "sg:province":"Li\u00e8ge",
    "wof:name":"Ren\u00c9 Et Monique",
    "wof:placetype":"venue"
},
  "geometry": {"coordinates":[5.6435680389,50.7090377808],"type":"Point"}
}