{
  "type": "Feature",
  "properties": {
    "addr:full":"Streekbaan 185 Vilvoorde Vlaams-Brabant 1800",
    "addr:housenumber":"185",
    "addr:postcode":"1800",
    "addr:street":"Streekbaan",
    "iso:country":"BE",
    "sg:address":"Streekbaan 185",
    "sg:city":"Vilvoorde",
    "sg:orig_category":"Salles de spectacles",
    "sg:phone":"+32 2 267 58 96",
    "sg:postcode":"1800",
    "sg:province":"Vlaams-Brabant",
    "wof:name":"Cultureel Centrum Koningslo",
    "wof:placetype":"venue"
},
  "geometry": {"coordinates":[4.3769798279,50.9059410095],"type":"Point"}
}