{
  "type": "Feature",
  "properties": {
    "addr:full":"Rue Albert I 74 Hannut Li\u00e8ge 4280",
    "addr:housenumber":"74",
    "addr:postcode":"4280",
    "addr:street":"Rue Albert I",
    "iso:country":"BE",
    "sg:address":"Rue Albert I 74",
    "sg:city":"Hannut",
    "sg:classifiers":[
        {
            "category":"Bars & Pubs",
            "type":"Food & Drink"
        }
    ],
    "sg:phone":"+32 19 51 15 84",
    "sg:postcode":"4280",
    "sg:province":"Li\u00e8ge",
    "wof:name":"Palace Ii (le)",
    "wof:placetype":"venue"
},
  "geometry": {"coordinates":[5.0834841728,50.6692237854],"type":"Point"}
}