{
  "type": "Feature",
  "properties": {
    "iso:country":"BE",
    "sg:address":"Nerenweg 168",
    "sg:city":"Laarne",
    "sg:orig_category":"Airconditioning and ventilatie",
    "sg:phone":"+32 9 367 57 00",
    "sg:postcode":"9270",
    "sg:province":"Oost-Vlaanderen",
    "wof:name":"Fa. Frigomar",
    "wof:placetype":"venue"
},
  "geometry": {"coordinates":[3.8967959881,51.0382881165],"type":"Point"}
}