{
  "type": "Feature",
  "properties": {
    "addr:full":"Turkije 5 Maarkedal (nukerke) Oost-Vlaanderen 9681",
    "addr:housenumber":"5",
    "addr:postcode":"9681",
    "addr:street":"Turkije",
    "iso:country":"BE",
    "sg:address":"Turkije 5",
    "sg:city":"Maarkedal (nukerke)",
    "sg:classifiers":[
        {
            "category":"Parking",
            "subcategory":"Lot",
            "type":"Transportation"
        }
    ],
    "sg:phone":"+32 55 20 88 00",
    "sg:postcode":"9681",
    "sg:province":"Oost-Vlaanderen",
    "sg:tags":[
        "parking-places",
        "laying-out"
    ],
    "wof:name":"Spileers P",
    "wof:placetype":"venue"
},
  "geometry": {"coordinates":[3.5952050686,50.7969856262],"type":"Point"}
}