{
  "type": "Feature",
  "properties": {
    "addr:full":"Boulevard Du R\u00e9gent 31 Bruxelles Bruxelles-Capitale 1000",
    "addr:housenumber":"31",
    "addr:postcode":"1000",
    "addr:street":"Boulevard Du Re\u0301Gent",
    "iso:country":"BE",
    "sg:address":"Boulevard Du R\u00e9gent 31",
    "sg:city":"Bruxelles",
    "sg:classifiers":[
        {
            "category":"Government",
            "subcategory":"Embassy",
            "type":"Public Place"
        }
    ],
    "sg:phone":"+32 2 502 17 91",
    "sg:postcode":"1000",
    "sg:province":"Bruxelles-Capitale",
    "sg:tags":[
        "consulate"
    ],
    "wof:name":"Mission De La Russie",
    "wof:placetype":"venue"
},
  "geometry": {"coordinates":[4.3676929474,50.8449172974],"type":"Point"}
}