{
  "type": "Feature",
  "properties": {
    "addr:full":"Heidijk 59 Beerse Antwerpen 2340",
    "addr:housenumber":"59",
    "addr:postcode":"2340",
    "addr:street":"Heidijk",
    "iso:country":"BE",
    "sg:address":"Heidijk 59",
    "sg:city":"Beerse",
    "sg:classifiers":[
        {
            "category":"Building & Trades",
            "subcategory":"Construction",
            "type":"Services"
        }
    ],
    "sg:phone":"+32 3 312 30 63",
    "sg:postcode":"2340",
    "sg:province":"Antwerpen",
    "sg:tags":[
        "roadway"
    ],
    "wof:name":"R & S B.v.b.a.",
    "wof:placetype":"venue"
},
  "geometry": {"coordinates":[4.7789812088,51.3001174927],"type":"Point"}
}