{
  "type": "Feature",
  "properties": {
    "iso:country":"BE",
    "sg:address":"Rue Du Ma\u00efeur Jean Duhot 22",
    "sg:city":"Hensies (thulin)",
    "sg:classifiers":[
        {
            "category":"Health Services",
            "subcategory":"Health Practitioner",
            "type":"Services"
        }
    ],
    "sg:phone":"+32 65 65 63 51",
    "sg:postcode":"7350",
    "sg:province":"Hainaut",
    "sg:tags":[
        "psychologist"
    ],
    "wof:name":"Lermusiaux J",
    "wof:placetype":"venue"
},
  "geometry": {"coordinates":[3.7435429096,50.4241676331],"type":"Point"}
}