{
  "type": "Feature",
  "properties": {
    "addr:full":"Brugsesteenweg 152 Oostende (zandvoorde) West-Vlaanderen 8400",
    "addr:housenumber":"152",
    "addr:postcode":"8400",
    "addr:street":"Brugsesteenweg",
    "iso:country":"BE",
    "sg:address":"Brugsesteenweg 152",
    "sg:city":"Oostende (zandvoorde)",
    "sg:classifiers":[
        {
            "category":"Shopping",
            "subcategory":"Computers & Home Electronics",
            "type":"Retail Goods"
        }
    ],
    "sg:phone":"+32 59 33 20 30",
    "sg:postcode":"8400",
    "sg:province":"West-Vlaanderen",
    "sg:tags":[
        "telephone",
        "apparatus",
        "accessory"
    ],
    "wof:name":"Flanders Engineering & Technology",
    "wof:placetype":"venue"
},
  "geometry": {"coordinates":[2.9890599251,51.2228889465],"type":"Point"}
}