{
  "type": "Feature",
  "properties": {
    "addr:full":"Boulevard De L'abattoir 35 Bruxelles Bruxelles-Capitale 1000",
    "addr:housenumber":"35",
    "addr:postcode":"1000",
    "addr:street":"Boulevard De L'Abattoir",
    "iso:country":"BE",
    "sg:address":"Boulevard De L'abattoir 35",
    "sg:city":"Bruxelles",
    "sg:classifiers":[
        {
            "category":"Shopping",
            "subcategory":"Computers & Home Electronics",
            "type":"Retail Goods"
        }
    ],
    "sg:phone":"+32 2 511 70 80",
    "sg:postcode":"1000",
    "sg:province":"Bruxelles-Capitale",
    "sg:tags":[
        "plate",
        "name"
    ],
    "wof:name":"Signa Art & Script Sprl",
    "wof:placetype":"venue"
},
  "geometry": {"coordinates":[4.3388900757,50.8461914062],"type":"Point"}
}