{
  "type": "Feature",
  "properties": {
    "addr:full":"Reppelsebaan Z/n Diest Vlaams-Brabant 3294",
    "addr:housenumber":"z / n",
    "addr:postcode":"3294",
    "iso:country":"BE",
    "sg:address":"Reppelsebaan Z/n",
    "sg:city":"Diest",
    "sg:orig_category":"Meubles Fab",
    "sg:phone":"+32 13 31 20 28",
    "sg:postcode":"3294",
    "sg:province":"Vlaams-Brabant",
    "wof:name":"Lambrechts",
    "wof:placetype":"venue"
},
  "geometry": {"coordinates":[5.0133299828,51.0038795471],"type":"Point"}
}