{
  "type": "Feature",
  "properties": {
    "iso:country":"BE",
    "sg:address":"Rijn 149",
    "sg:city":"Geel",
    "sg:orig_category":"Domotics",
    "sg:phone":"+32 14 63 51 30",
    "sg:postcode":"2440",
    "sg:province":"Antwerpen",
    "wof:name":"Toro Elektro Bvba",
    "wof:placetype":"venue"
},
  "geometry": {"coordinates":[5.0170922279,51.1635437012],"type":"Point"}
}