{
  "type": "Feature",
  "properties": {
    "iso:country":"BE",
    "sg:address":"Rue De Villers 334",
    "sg:city":"Charleroi",
    "sg:orig_category":"Jeux de hasard",
    "sg:phone":"+32 71 43 32 17",
    "sg:postcode":"6010",
    "sg:province":"Hainaut",
    "wof:name":"Ladbrokes",
    "wof:placetype":"venue"
},
  "geometry": {"coordinates":[4.4799079895,50.3831481934],"type":"Point"}
}