{
  "type": "Feature",
  "properties": {
    "iso:country":"BE",
    "sg:address":"O. Van Kersbeeckstraat 43",
    "sg:city":"Mechelen",
    "sg:classifiers":[
        {
            "category":"Arena",
            "subcategory":"Sports Club",
            "type":"Entertainment"
        }
    ],
    "sg:phone":"+32 15 20 24 52",
    "sg:postcode":"2800",
    "sg:province":"Antwerpen",
    "sg:tags":[
        "terrain",
        "hors",
        "de",
        "installation",
        "sportifs"
    ],
    "wof:name":"Racing Mechelen",
    "wof:placetype":"venue"
},
  "geometry": {"coordinates":[4.4726471901,51.0386657715],"type":"Point"}
}