{
  "type": "Feature",
  "properties": {
    "iso:country":"BE",
    "sg:address":"Blancefloerlaan 2",
    "sg:city":"Antwerpen",
    "sg:orig_category":"Banken and kredietinstellingen",
    "sg:phone":"+32 3 210 92 30",
    "sg:postcode":"2050",
    "sg:province":"Antwerpen",
    "wof:name":"Kbc",
    "wof:placetype":"venue"
},
  "geometry": {"coordinates":[4.3854660988,51.2207603455],"type":"Point"}
}