{
  "type": "Feature",
  "properties": {
    "addr:full":"Meerskant 22 Zele Oost-Vlaanderen 9240",
    "addr:housenumber":"22",
    "addr:postcode":"9240",
    "addr:street":"Meerskant",
    "iso:country":"BE",
    "sg:address":"Meerskant 22",
    "sg:city":"Zele",
    "sg:orig_category":"Diverse bouwafwerking and reiniging Woningbouw",
    "sg:phone":"+32 52 44 89 05",
    "sg:postcode":"9240",
    "sg:province":"Oost-Vlaanderen",
    "wof:name":"De Schrijder",
    "wof:placetype":"venue"
},
  "geometry": {"coordinates":[4.0279669762,51.0445671082],"type":"Point"}
}