{
  "type": "Feature",
  "properties": {
    "addr:full":"Vonckstraat 22 Herenthout Antwerpen 2270",
    "addr:housenumber":"22",
    "addr:postcode":"2270",
    "addr:street":"Vonckstraat",
    "iso:country":"BE",
    "sg:address":"Vonckstraat 22",
    "sg:city":"Herenthout",
    "sg:orig_category":"Banques and organismes de cr\u00e9dit",
    "sg:phone":"+32 14 51 10 08",
    "sg:postcode":"2270",
    "sg:province":"Antwerpen",
    "wof:name":"Bacob",
    "wof:placetype":"venue"
},
  "geometry": {"coordinates":[4.7582468987,51.1386451721],"type":"Point"}
}