{
  "type": "Feature",
  "properties": {
    "iso:country":"BE",
    "sg:address":"Kamerijckstraat 8a",
    "sg:city":"Gingelom",
    "sg:classifiers":[
        {
            "category":"Farming",
            "subcategory":"Crops",
            "type":"Manufacturing & Wholesale Goods"
        }
    ],
    "sg:phone":"+32 11 88 23 49",
    "sg:postcode":"3890",
    "sg:province":"Limburg",
    "sg:tags":[
        "vegetable",
        "fruit",
        "-",
        "grower"
    ],
    "wof:name":"Jahae",
    "wof:placetype":"venue"
},
  "geometry": {"coordinates":[5.1344561577,50.7560462952],"type":"Point"}
}