{
  "type": "Feature",
  "properties": {
    "addr:full":"Diksmuidseweg 505a Ieper (boezinge) West-Vlaanderen 8904",
    "addr:housenumber":"505a",
    "addr:postcode":"8904",
    "iso:country":"BE",
    "sg:address":"Diksmuidseweg 505a",
    "sg:city":"Ieper (boezinge)",
    "sg:classifiers":[
        {
            "category":"Autos & Motor Vehicles",
            "subcategory":"Automobile Sales",
            "type":"Retail Goods"
        }
    ],
    "sg:phone":"+32 57 42 31 22",
    "sg:postcode":"8904",
    "sg:province":"West-Vlaanderen",
    "sg:tags":[
        "car",
        "used",
        "-"
    ],
    "wof:name":"Ford-vanderjeugt Garage",
    "wof:placetype":"venue"
},
  "geometry": {"coordinates":[2.8404839039,50.9120254517],"type":"Point"}
}