{
  "type": "Feature",
  "properties": {
    "iso:country":"BE",
    "sg:address":"Rue De Mons 2",
    "sg:city":"Soignies",
    "sg:orig_category":"Tijdelijke werkgelegenheid and uitzendkantoren",
    "sg:phone":"+32 67 34 70 80",
    "sg:postcode":"7060",
    "sg:province":"Hainaut",
    "wof:name":"Vedior Interim",
    "wof:placetype":"venue"
},
  "geometry": {"coordinates":[4.0708098412,50.57862854],"type":"Point"}
}