{
  "type": "Feature",
  "properties": {
    "addr:full":"Herentalsesteenweg 97 Kasterlee Antwerpen 2460",
    "addr:housenumber":"97",
    "addr:postcode":"2460",
    "addr:street":"Herentalsesteenweg",
    "iso:country":"BE",
    "sg:address":"Herentalsesteenweg 97",
    "sg:city":"Kasterlee",
    "sg:classifiers":[
        {
            "category":"Cafe",
            "type":"Food & Drink"
        }
    ],
    "sg:phone":"+32 14 55 75 67",
    "sg:postcode":"2460",
    "sg:province":"Antwerpen",
    "sg:tags":[
        "caf\u00e9s"
    ],
    "wof:name":"De Heide",
    "wof:placetype":"venue"
},
  "geometry": {"coordinates":[4.894589901,51.2070617676],"type":"Point"}
}