{
  "type": "Feature",
  "properties": {
    "addr:full":"Komkommerstraat 8 Bertem Vlaams-Brabant 3060",
    "addr:housenumber":"8",
    "addr:postcode":"3060",
    "addr:street":"Komkommerstraat",
    "iso:country":"BE",
    "sg:address":"Komkommerstraat 8",
    "sg:city":"Bertem",
    "sg:orig_category":"Boekhouders",
    "sg:phone":"+32 16 48 95 72",
    "sg:postcode":"3060",
    "sg:province":"Vlaams-Brabant",
    "wof:name":"Albert Mees",
    "wof:placetype":"venue"
},
  "geometry": {"coordinates":[4.6374869347,50.8654708862],"type":"Point"}
}