{
  "type": "Feature",
  "properties": {
    "iso:country":"BE",
    "sg:address":"Kleine Kerkhofstraat 105",
    "sg:city":"Brugge (assebroek)",
    "sg:classifiers":[
        {
            "category":"Arena",
            "subcategory":"Sports Club",
            "type":"Entertainment"
        }
    ],
    "sg:phone":"+32 50 67 89 04",
    "sg:postcode":"8310",
    "sg:province":"West-Vlaanderen",
    "wof:name":"Mepse",
    "wof:placetype":"venue"
},
  "geometry": {"coordinates":[3.2367498875,51.1936264038],"type":"Point"}
}