{
  "type": "Feature",
  "properties": {
    "addr:full":"Rue Du Tultay 1 Sprimont Li\u00e8ge 4140",
    "addr:housenumber":"1",
    "addr:postcode":"4140",
    "addr:street":"Rue Du Tultay",
    "iso:country":"BE",
    "sg:address":"Rue Du Tultay 1",
    "sg:city":"Sprimont",
    "sg:orig_category":"Varkenskwekers",
    "sg:phone":"+32 4 382 12 37",
    "sg:postcode":"4140",
    "sg:province":"Li\u00e8ge",
    "wof:name":"Georges Pirard",
    "wof:placetype":"venue"
},
  "geometry": {"coordinates":[5.6666369438,50.5077781677],"type":"Point"}
}