{
  "type": "Feature",
  "properties": {
    "addr:full":"Rue Vaux 2 Soumagne Li\u00e8ge 4633",
    "addr:housenumber":"2",
    "addr:postcode":"4633",
    "addr:street":"Rue Vaux",
    "iso:country":"BE",
    "sg:address":"Rue Vaux 2",
    "sg:city":"Soumagne",
    "sg:orig_category":"Peinture. Rev\u00eatements pour sols and murs",
    "sg:phone":"+32 4 377 32 32",
    "sg:postcode":"4633",
    "sg:province":"Li\u00e8ge",
    "wof:name":"Peintures A. & D.",
    "wof:placetype":"venue"
},
  "geometry": {"coordinates":[5.7388892174,50.6499137878],"type":"Point"}
}