{
  "type": "Feature",
  "properties": {
    "iso:country":"BE",
    "sg:address":"Chauss\u00c9e D'alsemberg 743",
    "sg:city":"Ukkel/uccle",
    "sg:orig_category":"Eclairage et \u00e9quipements du foyer. Souvenirs and objets artisanaux",
    "sg:phone":"+32 2 346 45 32",
    "sg:postcode":"1180",
    "sg:province":"Bruxelles-Capitale",
    "wof:name":"Maison Cap Cadeau",
    "wof:placetype":"venue"
},
  "geometry": {"coordinates":[4.3365387917,50.8039703369],"type":"Point"}
}