{
  "type": "Feature",
  "properties": {
    "iso:country":"BE",
    "sg:address":"Rue Des Faubourgs 49",
    "sg:city":"Arlon",
    "sg:orig_category":"Industri\u00eble wasserijen and droogkuis",
    "sg:phone":"+32 63 22 76 55",
    "sg:postcode":"6700",
    "sg:province":"Luxembourg",
    "wof:name":"Cleaner Shop",
    "wof:placetype":"venue"
},
  "geometry": {"coordinates":[5.8111000061,49.684589386],"type":"Point"}
}