{
  "type": "Feature",
  "properties": {
    "addr:full":"Maasstraat 46 Sint-jans-molenbeek/molenbeek-saint-jean Bruxelles-Capitale 1080",
    "addr:housenumber":"46",
    "addr:postcode":"1080",
    "addr:street":"Maasstraat",
    "iso:country":"BE",
    "sg:address":"Maasstraat 46",
    "sg:city":"Sint-jans-molenbeek/molenbeek-saint-jean",
    "sg:orig_category":"Artsen and specialisten",
    "sg:phone":"+32 2 428 41 62",
    "sg:postcode":"1080",
    "sg:province":"Bruxelles-Capitale",
    "wof:name":"Louis Loontjens",
    "wof:placetype":"venue"
},
  "geometry": {"coordinates":[4.3363471031,50.8657455444],"type":"Point"}
}