{
  "type": "Feature",
  "properties": {
    "iso:country":"BE",
    "sg:address":"Vremdesesteenweg 5-7",
    "sg:city":"Boechout",
    "sg:classifiers":[
        {
            "category":"Retail",
            "subcategory":"Auto Repair",
            "type":"Services"
        }
    ],
    "sg:phone":"+32 3 455 72 72",
    "sg:postcode":"2530",
    "sg:province":"Antwerpen",
    "sg:tags":[
        "garage"
    ],
    "wof:name":"Hellemans",
    "wof:placetype":"venue"
},
  "geometry": {"coordinates":[4.5006079674,51.1645927429],"type":"Point"}
}