{
  "type": "Feature",
  "properties": {
    "iso:country":"BE",
    "sg:address":"Rue Du March\u00e9 Au Charbon 61",
    "sg:city":"Bruxelles",
    "sg:classifiers":[
        {
            "category":"Home & Garden",
            "subcategory":"Home Furnishings",
            "type":"Retail Goods"
        }
    ],
    "sg:phone":"+32 2 502 44 47",
    "sg:postcode":"1000",
    "sg:province":"Bruxelles-Capitale",
    "sg:tags":[
        "-",
        "bed",
        "mattress"
    ],
    "wof:name":"Futon Design",
    "wof:placetype":"venue"
},
  "geometry": {"coordinates":[4.3483958244,50.8461761475],"type":"Point"}
}