{
  "type": "Feature",
  "properties": {
    "iso:country":"BE",
    "sg:address":"Adolf Baeyensstraat 69",
    "sg:city":"Gent",
    "sg:classifiers":[
        {
            "category":"Shopping",
            "subcategory":"Crafts & Fabrics",
            "type":"Retail Goods"
        }
    ],
    "sg:phone":"+32 9 228 14 04",
    "sg:postcode":"9040",
    "sg:province":"Oost-Vlaanderen",
    "sg:tags":[
        "textile",
        "clothing"
    ],
    "wof:name":"Adolf Windey & Zonen Bvba",
    "wof:placetype":"venue"
},
  "geometry": {"coordinates":[3.7526659966,51.055809021],"type":"Point"}
}