{
  "type": "Feature",
  "properties": {
    "iso:country":"BE",
    "sg:address":"Peperstraat 3a",
    "sg:city":"Eeklo",
    "sg:classifiers":[
        {
            "category":"Retail",
            "subcategory":"Auto Repair",
            "type":"Services"
        }
    ],
    "sg:phone":"+32 9 377 12 62",
    "sg:postcode":"9900",
    "sg:province":"Oost-Vlaanderen",
    "sg:tags":[
        "garage"
    ],
    "wof:name":"Quadrifoglio",
    "wof:placetype":"venue"
},
  "geometry": {"coordinates":[3.5720601082,51.1983909607],"type":"Point"}
}