{
  "type": "Feature",
  "properties": {
    "iso:country":"BE",
    "sg:address":"Beverestraat 56",
    "sg:city":"Oudenaarde",
    "sg:orig_category":"Banken and kredietinstellingen",
    "sg:phone":"+32 55 31 43 40",
    "sg:postcode":"9700",
    "sg:province":"Oost-Vlaanderen",
    "wof:name":"Fortis",
    "wof:placetype":"venue"
},
  "geometry": {"coordinates":[3.5989038944,50.8490142822],"type":"Point"}
}