{
  "type": "Feature",
  "properties": {
    "addr:full":"Rue Du M\u00c9ridien 82 Sint-joost-ten-node/saint-joss Bruxelles-Capitale 1210",
    "addr:housenumber":"82",
    "addr:postcode":"1210",
    "addr:street":"Rue Du Me\u0301Ridien",
    "iso:country":"BE",
    "sg:address":"Rue Du M\u00c9ridien 82",
    "sg:city":"Sint-joost-ten-node/saint-joss",
    "sg:orig_category":"Bloemen and planten Gh",
    "sg:phone":"+32 2 219 44 69",
    "sg:postcode":"1210",
    "sg:province":"Bruxelles-Capitale",
    "wof:name":"Tablani Scris",
    "wof:placetype":"venue"
},
  "geometry": {"coordinates":[4.3690290451,50.8557090759],"type":"Point"}
}