{
  "type": "Feature",
  "properties": {
    "addr:full":"Rue Du Pr\u00c9-des-boeufs 15 Fernelmont Namur 5380",
    "addr:housenumber":"15",
    "addr:postcode":"5380",
    "addr:street":"Rue Du Pre\u0301-Des-Boeufs",
    "iso:country":"BE",
    "sg:address":"Rue Du Pr\u00c9-des-boeufs 15",
    "sg:city":"Fernelmont",
    "sg:orig_category":"Installation de menuiserie en bois and plastique",
    "sg:phone":"+32 81 83 50 52",
    "sg:postcode":"5380",
    "sg:province":"Namur",
    "wof:name":"Menuiserie Madera",
    "wof:placetype":"venue"
},
  "geometry": {"coordinates":[4.9973101616,50.5857009888],"type":"Point"}
}