{
  "type": "Feature",
  "properties": {
    "iso:country":"BE",
    "sg:address":"Gemeenteplein 1",
    "sg:city":"Keerbergen",
    "sg:classifiers":[
        {
            "category":"Shopping",
            "subcategory":"Jewelry",
            "type":"Retail Goods"
        }
    ],
    "sg:phone":"+32 15 51 30 61",
    "sg:postcode":"3140",
    "sg:province":"Vlaams-Brabant",
    "sg:tags":[
        "jeweller",
        "-"
    ],
    "wof:name":"Faes (huis)",
    "wof:placetype":"venue"
},
  "geometry": {"coordinates":[4.6286702156,51.0032691956],"type":"Point"}
}