{
  "type": "Feature",
  "properties": {
    "iso:country":"BE",
    "sg:address":"Steenweg Op Lebbeke 95",
    "sg:city":"Opwijk",
    "sg:orig_category":"Fleurs and plantes. Plantes and fleurs Gr",
    "sg:phone":"+32 52 35 68 79",
    "sg:postcode":"1745",
    "sg:province":"Vlaams-Brabant",
    "wof:name":"Aelbrecht - Van Der Veken",
    "wof:placetype":"venue"
},
  "geometry": {"coordinates":[4.1588191986,50.9845428467],"type":"Point"}
}