{
  "type": "Feature",
  "properties": {
    "addr:full":"Koning Leopold Iii-laan 53 Leuven (heverlee) Vlaams-Brabant 3001",
    "addr:housenumber":"53",
    "addr:postcode":"3001",
    "addr:street":"Koning Leopold Iii-Laan",
    "iso:country":"BE",
    "sg:address":"Koning Leopold Iii-laan 53",
    "sg:city":"Leuven (heverlee)",
    "sg:classifiers":[
        {
            "category":"Health Services",
            "subcategory":"Doctor",
            "type":"Services"
        }
    ],
    "sg:phone":"+32 16 39 10 06",
    "sg:postcode":"3001",
    "sg:province":"Vlaams-Brabant",
    "sg:tags":[
        "medicinephysicians",
        "surgeon"
    ],
    "wof:name":"Janssens S",
    "wof:placetype":"venue"
},
  "geometry": {"coordinates":[4.6888070107,50.8585853577],"type":"Point"}
}