{
  "type": "Feature",
  "properties": {
    "addr:full":"Luikersteenweg 40b Tongeren Limburg 3700",
    "addr:housenumber":"40b",
    "addr:postcode":"3700",
    "addr:street":"Luikersteenweg",
    "iso:country":"BE",
    "sg:address":"Luikersteenweg 40b",
    "sg:city":"Tongeren",
    "sg:classifiers":[
        {
            "category":"Home & Garden",
            "subcategory":"Garden Supply",
            "type":"Retail Goods"
        }
    ],
    "sg:phone":"+32 12 24 13 05",
    "sg:postcode":"3700",
    "sg:province":"Limburg",
    "wof:name":"Atd",
    "wof:placetype":"venue"
},
  "geometry": {"coordinates":[5.4614071846,50.7747459412],"type":"Point"}
}