{
  "type": "Feature",
  "properties": {
    "iso:country":"BE",
    "sg:address":"Route De Dinant 28",
    "sg:city":"Libramont-chevigny (saint-pierre)",
    "sg:classifiers":[
        {
            "category":"Real Estate",
            "subcategory":"Architect",
            "type":"Services"
        }
    ],
    "sg:phone":"+32 61 22 34 63",
    "sg:postcode":"6800",
    "sg:province":"Luxembourg",
    "wof:name":"Lievens C",
    "wof:placetype":"venue"
},
  "geometry": {"coordinates":[5.3761348724,49.9199943542],"type":"Point"}
}