{
  "type": "Feature",
  "properties": {
    "addr:full":"Hoogstraat 17a Antwerpen Antwerpen 2000",
    "addr:housenumber":"17a",
    "addr:postcode":"2000",
    "addr:street":"Hoogstraat",
    "iso:country":"BE",
    "sg:address":"Hoogstraat 17a",
    "sg:city":"Antwerpen",
    "sg:orig_category":"Brood, gebak and snoepgoed",
    "sg:phone":"+32 3 231 49 44",
    "sg:postcode":"2000",
    "sg:province":"Antwerpen",
    "wof:name":"Antwerps Snoephuis",
    "wof:placetype":"venue"
},
  "geometry": {"coordinates":[4.3987221718,51.2200202942],"type":"Point"}
}