{
  "type": "Feature",
  "properties": {
    "addr:full":"Rue Des Praules Gembloux Namur 5030",
    "addr:postcode":"5030",
    "addr:street":"Rue Des Praules",
    "iso:country":"BE",
    "sg:address":"Rue Des Praules",
    "sg:city":"Gembloux",
    "sg:orig_category":"Traitement and rev\u00eatement des m\u00e9taux",
    "sg:phone":"+32 81 61 42 82",
    "sg:postcode":"5030",
    "sg:province":"Namur",
    "wof:name":"Water Cutting",
    "wof:placetype":"venue"
},
  "geometry": {"coordinates":[4.71185112,50.5778160095],"type":"Point"}
}