{
  "type": "Feature",
  "properties": {
    "iso:country":"BE",
    "sg:address":"Rue Pr\u00c9voyance 36",
    "sg:city":"Tournai",
    "sg:classifiers":[
        {
            "category":"Personal",
            "subcategory":"Beauty Salon",
            "type":"Services"
        }
    ],
    "sg:phone":"+32 69 22 89 19",
    "sg:postcode":"7500",
    "sg:province":"Hainaut",
    "sg:tags":[
        "de",
        "coiffure"
    ],
    "wof:name":"Martine Battair",
    "wof:placetype":"venue"
},
  "geometry": {"coordinates":[3.3774709702,50.6006698608],"type":"Point"}
}