{
  "type": "Feature",
  "properties": {
    "addr:full":"Rue Du Rat D'eau 30 Honnelles Hainaut 7387",
    "addr:housenumber":"30",
    "addr:postcode":"7387",
    "addr:street":"Rue Du Rat D'Eau;Hainaut",
    "iso:country":"BE",
    "sg:address":"Rue Du Rat D'eau 30",
    "sg:city":"Honnelles",
    "sg:classifiers":[
        {
            "category":"Cafe",
            "type":"Food & Drink"
        }
    ],
    "sg:phone":"+32 65 65 06 37",
    "sg:postcode":"7387",
    "sg:province":"Hainaut",
    "sg:tags":[
        "caf\u00e9s"
    ],
    "wof:name":"Danielle Delarue",
    "wof:placetype":"venue"
},
  "geometry": {"coordinates":[3.7799580097,50.3628463745],"type":"Point"}
}