{
  "type": "Feature",
  "properties": {
    "iso:country":"BE",
    "sg:address":"Rue Philippe Baucq 48",
    "sg:city":"Etterbeek",
    "sg:orig_category":"M\u00e9decins and sp\u00e9cialistes",
    "sg:phone":"+32 2 644 52 33",
    "sg:postcode":"1040",
    "sg:province":"Bruxelles-Capitale",
    "wof:name":"Isabelle Jurisse",
    "wof:placetype":"venue"
},
  "geometry": {"coordinates":[4.3852219582,50.8313217163],"type":"Point"}
}