{
  "type": "Feature",
  "properties": {
    "iso:country":"BE",
    "sg:address":"Thier Du Goreu 57",
    "sg:city":"Li\u00e8ge 1 (jupille-sur-meuse)",
    "sg:classifiers":[
        {
            "category":"Health Services",
            "subcategory":"Doctor",
            "type":"Services"
        }
    ],
    "sg:phone":"+32 4 367 47 26",
    "sg:postcode":"4020",
    "sg:province":"Li\u00e8ge",
    "sg:tags":[
        "medicinephysicians",
        "surgeon"
    ],
    "wof:name":"Lifrange Marc",
    "wof:placetype":"venue"
},
  "geometry": {"coordinates":[5.6379542351,50.6353721619],"type":"Point"}
}