{
  "type": "Feature",
  "properties": {
    "addr:full":"Dorpsplein 2b1 Opglabbeek Limburg 3660",
    "addr:housenumber":"2b1",
    "addr:postcode":"3660",
    "addr:street":"Dorpsplein",
    "iso:country":"BE",
    "sg:address":"Dorpsplein 2b1",
    "sg:city":"Opglabbeek",
    "sg:classifiers":[
        {
            "category":"Insurance",
            "subcategory":"Insurance Agent",
            "type":"Services"
        }
    ],
    "sg:phone":"+32 89 85 52 02",
    "sg:postcode":"3660",
    "sg:province":"Limburg",
    "sg:tags":[
        "verzekeringsmakelaars",
        "expert"
    ],
    "wof:name":"Bureau Aerden",
    "wof:placetype":"venue"
},
  "geometry": {"coordinates":[5.5844259262,51.0431976318],"type":"Point"}
}