{
  "type": "Feature",
  "properties": {
    "iso:country":"BE",
    "sg:address":"Fortune De Kokerlaan 3",
    "sg:city":"Evergem",
    "sg:classifiers":[
        {
            "category":"Personal",
            "subcategory":"Beauty Salon",
            "type":"Services"
        }
    ],
    "sg:phone":"+32 9 253 77 75",
    "sg:postcode":"9940",
    "sg:province":"Oost-Vlaanderen",
    "sg:tags":[
        "de",
        "coiffure"
    ],
    "wof:name":"Ingrid Wellekens",
    "wof:placetype":"venue"
},
  "geometry": {"coordinates":[3.7092599869,51.1101417542],"type":"Point"}
}