{
  "type": "Feature",
  "properties": {
    "iso:country":"BE",
    "sg:address":"Rue Jehaes 3",
    "sg:city":"Fl\u00c9ron",
    "sg:orig_category":"Assurances. Pr\u00eats hypoth\u00e9caires and cr\u00e9dits immobiliers",
    "sg:phone":"+32 4 358 35 94",
    "sg:postcode":"4620",
    "sg:province":"Li\u00e8ge",
    "wof:name":"Bureau Joris",
    "wof:placetype":"venue"
},
  "geometry": {"coordinates":[5.6854901314,50.6135902405],"type":"Point"}
}