{
  "type": "Feature",
  "properties": {
    "addr:full":"Grote Steenweg 100 Zoutleeuw Vlaams-Brabant 3440",
    "addr:housenumber":"100",
    "addr:postcode":"3440",
    "addr:street":"Grote Steenweg;Vlaams-Brabant",
    "iso:country":"BE",
    "sg:address":"Grote Steenweg 100",
    "sg:city":"Zoutleeuw",
    "sg:orig_category":"Banques and organismes de cr\u00e9dit",
    "sg:phone":"+32 11 78 51 16",
    "sg:postcode":"3440",
    "sg:province":"Vlaams-Brabant",
    "wof:name":"Groep Argenta",
    "wof:placetype":"venue"
},
  "geometry": {"coordinates":[5.1073079109,50.8079986572],"type":"Point"}
}