{
  "type": "Feature",
  "properties": {
    "addr:full":"9810 Nazareth (groot) Oost-Vlaanderen 9810",
    "addr:postcode":"9810;9810",
    "addr:street":"Groot Oost-Vlaanderen",
    "iso:country":"BE",
    "sg:address":"9810",
    "sg:city":"Nazareth (groot)",
    "sg:orig_category":"Pharmaciens",
    "sg:phone":"+32 900 10 500",
    "sg:postcode":"9810",
    "sg:province":"Oost-Vlaanderen",
    "wof:name":"Pharmacies De Garde",
    "wof:placetype":"venue"
},
  "geometry": {"coordinates":[3.5967800617,50.9596405029],"type":"Point"}
}