{
  "type": "Feature",
  "properties": {
    "addr:full":"Onderbergen 39 Gent Oost-Vlaanderen 9000",
    "addr:housenumber":"39",
    "addr:postcode":"9000",
    "addr:street":"Onderbergen;Oost-Vlaanderen",
    "iso:country":"BE",
    "sg:address":"Onderbergen 39",
    "sg:city":"Gent",
    "sg:orig_category":"Rev\u00eatements pour sols and murs. Peinture. Eclairage et \u00e9quipements du foyer",
    "sg:phone":"+32 9 233 09 10",
    "sg:postcode":"9000",
    "sg:province":"Oost-Vlaanderen",
    "wof:name":"Serweytens Decoration",
    "wof:placetype":"venue"
},
  "geometry": {"coordinates":[3.7195858955,51.0512428284],"type":"Point"}
}