{
  "type": "Feature",
  "properties": {
    "addr:full":"Boulevard Louis Mettewie 61 Box 9 Bruxelles (molenbeek-saint-jean) Bruxelles-Capitale 1080",
    "addr:housenumber":"61;9",
    "addr:postcode":"1080",
    "addr:street":"Boulevard Louis Mettewie;Box",
    "iso:country":"BE",
    "sg:address":"Boulevard Louis Mettewie 61 Box 9",
    "sg:city":"Bruxelles (molenbeek-saint-jean)",
    "sg:classifiers":[
        {
            "category":"Banks & Credit Unions",
            "subcategory":"Investment Brokerage",
            "type":"Services"
        }
    ],
    "sg:phone":"+32 2 465 74 34",
    "sg:postcode":"1080",
    "sg:province":"Bruxelles-Capitale",
    "sg:tags":[
        "auditor"
    ],
    "wof:name":"Wets B",
    "wof:placetype":"venue"
},
  "geometry": {"coordinates":[4.3070731163,50.8558654785],"type":"Point"}
}