{
  "type": "Feature",
  "properties": {
    "iso:country":"BE",
    "sg:address":"Welvaartstraat 17",
    "sg:city":"Sint-katelijne-waver",
    "sg:orig_category":"Dameskledingzaken",
    "sg:phone":"+32 15 75 61 58",
    "sg:postcode":"2861",
    "sg:province":"Antwerpen",
    "wof:name":"Marie-louise Laureys",
    "wof:placetype":"venue"
},
  "geometry": {"coordinates":[4.5726799965,51.0582542419],"type":"Point"}
}