{
  "type": "Feature",
  "properties": {
    "addr:full":"Meerpoelstraat 1 Merchtem Vlaams-Brabant 1785",
    "addr:housenumber":"1",
    "addr:postcode":"1785",
    "addr:street":"Meerpoelstraat",
    "iso:country":"BE",
    "sg:address":"Meerpoelstraat 1",
    "sg:city":"Merchtem",
    "sg:orig_category":"Producteurs de l\u00e9gumes",
    "sg:phone":"+32 2 452 68 24",
    "sg:postcode":"1785",
    "sg:province":"Vlaams-Brabant",
    "wof:name":"Rene De Maeyer",
    "wof:placetype":"venue"
},
  "geometry": {"coordinates":[4.2276139259,50.9434928894],"type":"Point"}
}