{
  "type": "Feature",
  "properties": {
    "iso:country":"BE",
    "sg:address":"Tieltsesteenweg 67",
    "sg:city":"Eeklo",
    "sg:classifiers":[
        {
            "category":"Personal",
            "subcategory":"Beauty Salon",
            "type":"Services"
        }
    ],
    "sg:phone":"+32 9 377 20 79",
    "sg:postcode":"9900",
    "sg:province":"Oost-Vlaanderen",
    "sg:tags":[
        "de",
        "coiffure"
    ],
    "wof:name":"Renaat Ryckoort",
    "wof:placetype":"venue"
},
  "geometry": {"coordinates":[3.555670023,51.1836509705],"type":"Point"}
}