{
  "type": "Feature",
  "properties": {
    "addr:full":"Avenue Lat\u00e9rale 1 Bruxelles (uccle) Bruxelles-Capitale 1180",
    "addr:housenumber":"1",
    "addr:postcode":"1180",
    "addr:street":"Avenue Late\u0301Rale",
    "iso:country":"BE",
    "sg:address":"Avenue Lat\u00e9rale 1",
    "sg:city":"Bruxelles (uccle)",
    "sg:classifiers":[
        {
            "category":"Personal",
            "subcategory":"Barber",
            "type":"Services"
        }
    ],
    "sg:phone":"+32 2 372 24 48",
    "sg:postcode":"1180",
    "sg:province":"Bruxelles-Capitale",
    "sg:tags":[
        "gentleman",
        "salon",
        "-",
        "hairdressing"
    ],
    "wof:name":"Latour V",
    "wof:placetype":"venue"
},
  "geometry": {"coordinates":[4.3732638359,50.7965202332],"type":"Point"}
}