{
  "type": "Feature",
  "properties": {
    "addr:full":"Sint-michielsplein 16 Gent Oost-Vlaanderen 9000",
    "addr:housenumber":"16",
    "addr:postcode":"9000",
    "addr:street":"Sint-Michielsplein;Oost-Vlaanderen",
    "iso:country":"BE",
    "sg:address":"Sint-michielsplein 16",
    "sg:city":"Gent",
    "sg:orig_category":"Diverse kredietdiensten",
    "sg:postcode":"9000",
    "sg:province":"Oost-Vlaanderen",
    "wof:name":"Bancontact-mister Cash",
    "wof:placetype":"venue"
},
  "geometry": {"coordinates":[3.7187070847,51.0537643433],"type":"Point"}
}