{
  "type": "Feature",
  "properties": {
    "iso:country":"BE",
    "sg:address":"Sint-michielsplein 16",
    "sg:city":"Gent",
    "sg:orig_category":"Diverse kredietdiensten",
    "sg:postcode":"9000",
    "sg:province":"Oost-Vlaanderen",
    "wof:name":"Bancontact-mister Cash",
    "wof:placetype":"venue"
},
  "geometry": {"coordinates":[3.7187070847,51.0537643433],"type":"Point"}
}