{
  "type": "Feature",
  "properties": {
    "iso:country":"BE",
    "sg:address":"Place Communale 10",
    "sg:city":"Linkebeek",
    "sg:classifiers":[
        {
            "category":"Shopping",
            "subcategory":"Clothing, Apparel, & Fashions",
            "type":"Retail Goods"
        }
    ],
    "sg:phone":"+32 2 380 77 73",
    "sg:postcode":"1630",
    "sg:province":"Vlaams-Brabant",
    "sg:tags":[
        "purchase",
        "clothing",
        "-",
        "sale",
        "second-hand"
    ],
    "wof:name":"Bebe Antoine",
    "wof:placetype":"venue"
},
  "geometry": {"coordinates":[4.3368940353,50.7728843689],"type":"Point"}
}