{
  "type": "Feature",
  "properties": {
    "addr:full":"Rue De Menin 4 Estaimpuis Hainaut 7730",
    "addr:housenumber":"4",
    "addr:postcode":"7730",
    "addr:street":"Rue De Menin;Hainaut",
    "iso:country":"BE",
    "sg:address":"Rue De Menin 4",
    "sg:city":"Estaimpuis",
    "sg:classifiers":[
        {
            "category":"Banks & Credit Unions",
            "subcategory":"Financial Services",
            "type":"Services"
        }
    ],
    "sg:phone":"+32 56 85 19 09",
    "sg:postcode":"7730",
    "sg:province":"Hainaut",
    "sg:tags":[
        "loan",
        "mortgage"
    ],
    "wof:name":"Finaref",
    "wof:placetype":"venue"
},
  "geometry": {"coordinates":[3.2495200634,50.709690094],"type":"Point"}
}