{
  "type": "Feature",
  "properties": {
    "addr:full":"Route De Dolhain 31 Baelen/baelen Li\u00e8ge 4837",
    "addr:housenumber":"31",
    "addr:postcode":"4837",
    "addr:street":"Route De Dolhain",
    "iso:country":"BE",
    "sg:address":"Route De Dolhain 31",
    "sg:city":"Baelen/baelen",
    "sg:orig_category":"Experts-comptables",
    "sg:phone":"+32 87 76 37 20",
    "sg:postcode":"4837",
    "sg:province":"Li\u00e8ge",
    "wof:name":"Richard Julemont",
    "wof:placetype":"venue"
},
  "geometry": {"coordinates":[5.9696068764,50.6281814575],"type":"Point"}
}