{
  "type": "Feature",
  "properties": {
    "addr:full":"Place Du March\u00c9 33 Saint-hubert Luxembourg 6870",
    "addr:housenumber":"33",
    "addr:postcode":"6870",
    "addr:street":"Place Du Marche\u0301",
    "iso:country":"BE",
    "sg:address":"Place Du March\u00c9 33",
    "sg:city":"Saint-hubert",
    "sg:orig_category":"Tweedehandsgoederen Verlichting and huishoudartikelen",
    "sg:phone":"+32 61 61 25 63",
    "sg:postcode":"6870",
    "sg:province":"Luxembourg",
    "wof:name":"Oxfam Magasin Du Monde",
    "wof:placetype":"venue"
},
  "geometry": {"coordinates":[5.3735690117,50.0254974365],"type":"Point"}
}