{
  "type": "Feature",
  "properties": {
    "addr:full":"Rue De L'hydrion 0 Arlon Luxembourg 6700",
    "addr:housenumber":"0",
    "addr:postcode":"6700",
    "addr:street":"Rue De L'Hydrion",
    "iso:country":"BE",
    "sg:address":"Rue De L'hydrion 0",
    "sg:city":"Arlon",
    "sg:orig_category":"Gestion des d\u00e9charges and sites d\u00e9finitifs de stockage",
    "sg:phone":"+32 63 23 59 25",
    "sg:postcode":"6700",
    "sg:province":"Luxembourg",
    "wof:name":"Parcs A Conteneurs Arlon",
    "wof:placetype":"venue"
},
  "geometry": {"coordinates":[5.7947201729,49.6745986938],"type":"Point"}
}