{
  "type": "Feature",
  "properties": {
    "addr:full":"Avenue Cardinal Mercier 13 Namur Namur 5000",
    "addr:housenumber":"13",
    "addr:postcode":"5000",
    "addr:street":"Avenue Cardinal Mercier",
    "iso:country":"BE",
    "sg:address":"Avenue Cardinal Mercier 13",
    "sg:city":"Namur",
    "sg:orig_category":"Avocats and conseillers juridiques",
    "sg:phone":"+32 81 74 22 09",
    "sg:postcode":"5000",
    "sg:province":"Namur",
    "wof:name":"Andr\u00c9 Hancotte",
    "wof:placetype":"venue"
},
  "geometry": {"coordinates":[4.8524489403,50.4657592773],"type":"Point"}
}