{
  "type": "Feature",
  "properties": {
    "addr:full":"Doorniksesteenweg 224 Avelgem West-Vlaanderen 8580",
    "addr:housenumber":"224",
    "addr:postcode":"8580",
    "addr:street":"Doorniksesteenweg",
    "iso:country":"BE",
    "sg:address":"Doorniksesteenweg 224",
    "sg:city":"Avelgem",
    "sg:orig_category":"Installations and terrains de sport hors centres sportifs. Restaurants. Caf\u00e9s. Clubs de sport",
    "sg:phone":"+32 56 64 59 00",
    "sg:postcode":"8580",
    "sg:province":"West-Vlaanderen",
    "wof:name":"Golfclub",
    "wof:placetype":"venue"
},
  "geometry": {"coordinates":[3.4452490807,50.7710380554],"type":"Point"}
}