{
  "type": "Feature",
  "properties": {
    "addr:full":"Dorp 6 Lille (poederlee) Antwerpen 2275",
    "addr:housenumber":"6",
    "addr:postcode":"2275",
    "addr:street":"Dorp",
    "iso:country":"BE",
    "sg:address":"Dorp 6",
    "sg:city":"Lille (poederlee)",
    "sg:orig_category":"Newspapers, magazines, periodicals - Distribution",
    "sg:phone":"+32 14 88 27 89",
    "sg:postcode":"2275",
    "sg:province":"Antwerpen",
    "wof:name":"Sarti",
    "wof:placetype":"venue"
},
  "geometry": {"coordinates":[4.8361239433,51.2266387939],"type":"Point"}
}