{
  "type": "Feature",
  "properties": {
    "addr:full":"Ginderbuiten 136 Mol Antwerpen 2400",
    "addr:housenumber":"136",
    "addr:postcode":"2400",
    "addr:street":"Ginderbuiten",
    "iso:country":"BE",
    "sg:address":"Ginderbuiten 136",
    "sg:city":"Mol",
    "sg:classifiers":[
        {
            "category":"Food & Beverages",
            "subcategory":"Groceries & Convenience Stores",
            "type":"Retail Goods"
        }
    ],
    "sg:phone":"+32 14 31 23 37",
    "sg:postcode":"2400",
    "sg:province":"Antwerpen",
    "sg:tags":[
        "product",
        "related"
    ],
    "wof:name":"Butterfly Bcs Bvba",
    "wof:placetype":"venue"
},
  "geometry": {"coordinates":[5.1309409142,51.1975288391],"type":"Point"}
}