{
  "type": "Feature",
  "properties": {
    "addr:full":"Tripelenweg 2 Riemst Limburg 3770",
    "addr:housenumber":"2",
    "addr:postcode":"3770",
    "addr:street":"Tripelenweg",
    "iso:country":"BE",
    "sg:address":"Tripelenweg 2",
    "sg:city":"Riemst",
    "sg:orig_category":"Eleveurs de bovins",
    "sg:phone":"+32 12 39 33 23",
    "sg:postcode":"3770",
    "sg:province":"Limburg",
    "wof:name":"Pierre Germis",
    "wof:placetype":"venue"
},
  "geometry": {"coordinates":[5.5556821823,50.7834396362],"type":"Point"}
}