{
  "type": "Feature",
  "properties": {
    "iso:country":"BE",
    "sg:address":"Place De Thines 4",
    "sg:city":"Nivelles",
    "sg:orig_category":"Rundveehouders",
    "sg:phone":"+32 67 84 40 13",
    "sg:postcode":"1402",
    "sg:province":"Brabant Wallon",
    "wof:name":"Nicolas Mullier",
    "wof:placetype":"venue"
},
  "geometry": {"coordinates":[4.3679280281,50.5971603394],"type":"Point"}
}