{
  "type": "Feature",
  "properties": {
    "iso:country":"BE",
    "sg:address":"Adelberg 9",
    "sg:city":"Lommel",
    "sg:classifiers":[
        {
            "category":"Professional",
            "subcategory":"Computer Services",
            "type":"Services"
        }
    ],
    "sg:phone":"+32 11 55 45 13",
    "sg:postcode":"3920",
    "sg:province":"Limburg",
    "sg:tags":[
        "-",
        "processing",
        "data"
    ],
    "wof:name":"Autosoft Bvba",
    "wof:placetype":"venue"
},
  "geometry": {"coordinates":[5.3073501587,51.233959198],"type":"Point"}
}