{
  "type": "Feature",
  "properties": {
    "addr:full":"J. Anthierenslaan 9 De Pinte Oost-Vlaanderen 9840",
    "addr:housenumber":"9",
    "addr:postcode":"9840",
    "addr:street":"J. Anthierenslaan",
    "iso:country":"BE",
    "sg:address":"J. Anthierenslaan 9",
    "sg:city":"De Pinte",
    "sg:classifiers":[
        {
            "category":"Wholesale",
            "subcategory":"Fruits & Vegetables",
            "type":"Manufacturing & Wholesale Goods"
        }
    ],
    "sg:phone":"+32 9 282 59 81",
    "sg:postcode":"9840",
    "sg:province":"Oost-Vlaanderen",
    "sg:tags":[
        "whol",
        "-"
    ],
    "wof:name":"Vanhuffel-goeminne",
    "wof:placetype":"venue"
},
  "geometry": {"coordinates":[3.6543819904,50.9945106506],"type":"Point"}
}