{
  "type": "Feature",
  "properties": {
    "addr:full":"Avenue Des Muguets 2a Kraainem Vlaams-Brabant 1950",
    "addr:housenumber":"2a",
    "addr:postcode":"1950",
    "addr:street":"Avenue Des Muguets",
    "iso:country":"BE",
    "sg:address":"Avenue Des Muguets 2a",
    "sg:city":"Kraainem",
    "sg:classifiers":[
        {
            "category":"Health Services",
            "subcategory":"Doctor",
            "type":"Services"
        }
    ],
    "sg:phone":"+32 2 731 65 38",
    "sg:postcode":"1950",
    "sg:province":"Vlaams-Brabant",
    "sg:tags":[
        "medicinephysicians",
        "surgeon"
    ],
    "wof:name":"Crucifix M",
    "wof:placetype":"venue"
},
  "geometry": {"coordinates":[4.464799881,50.845199585],"type":"Point"}
}