{
  "type": "Feature",
  "properties": {
    "iso:country":"BE",
    "sg:address":"Dadizeelsestraat 173",
    "sg:city":"Moorslede",
    "sg:orig_category":"Loodgieterij, verwarming and sanitaire installaties",
    "sg:phone":"+32 56 50 99 27",
    "sg:postcode":"8890",
    "sg:province":"West-Vlaanderen",
    "wof:name":"Cnockaert",
    "wof:placetype":"venue"
},
  "geometry": {"coordinates":[3.0767920017,50.8650398254],"type":"Point"}
}