{
  "type": "Feature",
  "properties": {
    "addr:full":"Egelare Nevele Oost-Vlaanderen 9850",
    "addr:postcode":"9850",
    "addr:street":"Oost-Vlaanderen",
    "iso:country":"BE",
    "sg:address":"Egelare",
    "sg:city":"Nevele",
    "sg:orig_category":"Autombile concessionaires",
    "sg:phone":"+32 9 371 50 55",
    "sg:postcode":"9850",
    "sg:province":"Oost-Vlaanderen",
    "wof:name":"Autobedrijf Diericx Nv",
    "wof:placetype":"venue"
},
  "geometry": {"coordinates":[3.556634903,51.0345001221],"type":"Point"}
}