{
  "type": "Feature",
  "properties": {
    "iso:country":"BE",
    "sg:address":"Biertas\u00e8tsche 1a",
    "sg:city":"Malmedy",
    "sg:classifiers":[
        {
            "category":"Health Services",
            "subcategory":"Doctor",
            "type":"Services"
        }
    ],
    "sg:phone":"+32 80 33 07 27",
    "sg:postcode":"4960",
    "sg:province":"Li\u00e8ge",
    "sg:tags":[
        "medicinephysicians",
        "surgeon"
    ],
    "wof:name":"Isra\u00ebl E",
    "wof:placetype":"venue"
},
  "geometry": {"coordinates":[6.0368337631,50.4254379272],"type":"Point"}
}