{
  "type": "Feature",
  "properties": {
    "addr:full":"Place Communale 17 Rixensart (genval) Brabant Wallon 1332",
    "addr:housenumber":"17",
    "addr:postcode":"1332",
    "addr:street":"Place Communale",
    "iso:country":"BE",
    "sg:address":"Place Communale 17",
    "sg:city":"Rixensart (genval)",
    "sg:classifiers":[
        {
            "category":"Building & Trades",
            "subcategory":"Construction",
            "type":"Services"
        }
    ],
    "sg:phone":"+32 2 653 38 26",
    "sg:postcode":"1332",
    "sg:province":"Brabant Wallon",
    "sg:tags":[
        "carpenter"
    ],
    "wof:name":"Bontemps D",
    "wof:placetype":"venue"
},
  "geometry": {"coordinates":[4.498442173,50.7162857056],"type":"Point"}
}