{
  "type": "Feature",
  "properties": {
    "addr:full":"Rue D'en Bas 40 Lessines (deux-acren) Hainaut 7864",
    "addr:housenumber":"40",
    "addr:postcode":"7864",
    "addr:street":"Rue D'En Bas",
    "iso:country":"BE",
    "sg:address":"Rue D'en Bas 40",
    "sg:city":"Lessines (deux-acren)",
    "sg:classifiers":[
        {
            "category":"Home & Garden",
            "subcategory":"Building Materials",
            "type":"Retail Goods"
        }
    ],
    "sg:phone":"+32 68 33 27 03",
    "sg:postcode":"7864",
    "sg:province":"Hainaut",
    "sg:tags":[
        "veranda"
    ],
    "wof:name":"Vandroogenbroek & Fran\u00c7ois Sa",
    "wof:placetype":"venue"
},
  "geometry": {"coordinates":[1.6273139715,50.2169342041],"type":"Point"}
}