{
  "type": "Feature",
  "properties": {
    "iso:country":"BE",
    "sg:address":"Schaluinstraat 3",
    "sg:city":"Tremelo",
    "sg:orig_category":"IJzerwaren, bouw- and verfmaterialen Loodgieterij, verwarming and sanitaire installaties Viessmann",
    "sg:phone":"+32 16 53 33 00",
    "sg:postcode":"3120",
    "sg:province":"Vlaams-Brabant",
    "wof:name":"Van Houtte Patrick",
    "wof:placetype":"venue"
},
  "geometry": {"coordinates":[4.7372198105,50.9957962036],"type":"Point"}
}