{
  "type": "Feature",
  "properties": {
    "addr:full":"Rue Du Chevalet 20 Ottignies-louvain-la-neuve Brabant Wallon 1348",
    "addr:housenumber":"20",
    "addr:postcode":"1348",
    "addr:street":"Rue Du Chevalet",
    "iso:country":"BE",
    "sg:address":"Rue Du Chevalet 20",
    "sg:city":"Ottignies-louvain-la-neuve",
    "sg:orig_category":"Avocats and conseillers juridiques",
    "sg:phone":"+32 10 45 23 73",
    "sg:postcode":"1348",
    "sg:province":"Brabant Wallon",
    "wof:name":"G. Beliard",
    "wof:placetype":"venue"
},
  "geometry": {"coordinates":[4.606400013,50.6658325195],"type":"Point"}
}