{
  "type": "Feature",
  "properties": {
    "iso:country":"BE",
    "sg:address":"Burgemeester Pyckestraat 53",
    "sg:city":"Kortrijk",
    "sg:orig_category":"Avocats and conseillers juridiques",
    "sg:phone":"+32 56 22 98 49",
    "sg:postcode":"8500",
    "sg:province":"West-Vlaanderen",
    "wof:name":"P. Cambien",
    "wof:placetype":"venue"
},
  "geometry": {"coordinates":[3.2643580437,50.819229126],"type":"Point"}
}