{
  "type": "Feature",
  "properties": {
    "iso:country":"BE",
    "sg:address":"Museumstraat 49",
    "sg:city":"Aalter",
    "sg:orig_category":"Plaatsen van vloer- and muurbekleding Schilders",
    "sg:phone":"+32 9 374 48 93",
    "sg:postcode":"9881",
    "sg:province":"Oost-Vlaanderen",
    "wof:name":"Decoratie Robert Maenhout",
    "wof:placetype":"venue"
},
  "geometry": {"coordinates":[3.4932310581,51.0934257507],"type":"Point"}
}