{
  "type": "Feature",
  "properties": {
    "iso:country":"BE",
    "sg:address":"Rue Des H\u00eatres 80",
    "sg:city":"Bastogne",
    "sg:classifiers":[
        {
            "category":"Health Services",
            "subcategory":"Doctor",
            "type":"Services"
        }
    ],
    "sg:phone":"+32 61 21 25 33",
    "sg:postcode":"6600",
    "sg:province":"Luxembourg",
    "sg:tags":[
        "medicinephysicians",
        "surgeon"
    ],
    "wof:name":"Hindryckx Jacques",
    "wof:placetype":"venue"
},
  "geometry": {"coordinates":[5.7309441566,50.0042457581],"type":"Point"}
}