{
  "type": "Feature",
  "properties": {
    "addr:full":"Sint-jobsstraat 36 Herentals Antwerpen 2200",
    "addr:housenumber":"36",
    "addr:postcode":"2200",
    "addr:street":"Sint-Jobsstraat",
    "iso:country":"BE",
    "sg:address":"Sint-jobsstraat 36",
    "sg:city":"Herentals",
    "sg:classifiers":[
        {
            "category":"Professional",
            "subcategory":"Art Services",
            "type":"Services"
        }
    ],
    "sg:postcode":"2200",
    "sg:province":"Antwerpen",
    "sg:tags":[
        "interior",
        "designer"
    ],
    "wof:name":"And",
    "wof:placetype":"venue"
},
  "geometry": {"coordinates":[4.8426470757,51.1786651611],"type":"Point"}
}