{
  "type": "Feature",
  "properties": {
    "addr:full":"Avenue Du Parc 157 Vorst/forest Bruxelles-Capitale 1190",
    "addr:housenumber":"157",
    "addr:postcode":"1190",
    "addr:street":"Avenue Du Parc;/ Forest",
    "iso:country":"BE",
    "sg:address":"Avenue Du Parc 157",
    "sg:city":"Vorst/forest",
    "sg:orig_category":"Catering and organisation de f\u00eates. Alimentation sp\u00e9cialis\u00e9e",
    "sg:phone":"+32 2 537 26 21",
    "sg:postcode":"1190",
    "sg:province":"Bruxelles-Capitale",
    "wof:name":"Traiteur Du Parc",
    "wof:placetype":"venue"
},
  "geometry": {"coordinates":[4.3361358643,50.8246383667],"type":"Point"}
}