{
  "type": "Feature",
  "properties": {
    "addr:full":"Chauss\u00e9e De Gand 1140 Box 21 Bruxelles (berchem-sainte-agathe) Bruxelles-Capitale 1082",
    "addr:housenumber":"1140 box 21",
    "addr:postcode":"1082",
    "addr:street":"Chausse\u0301E De Gand",
    "iso:country":"BE",
    "sg:address":"Chauss\u00e9e De Gand 1140 Box 21",
    "sg:city":"Bruxelles (berchem-sainte-agathe)",
    "sg:classifiers":[
        {
            "category":"Professional",
            "subcategory":"Computer Services",
            "type":"Services"
        }
    ],
    "sg:phone":"+32 2 465 75 75",
    "sg:postcode":"1082",
    "sg:province":"Bruxelles-Capitale",
    "sg:tags":[
        "-",
        "processing",
        "data",
        "software"
    ],
    "wof:name":"Software Architects Bvba",
    "wof:placetype":"venue"
},
  "geometry": {"coordinates":[4.2982621193,50.8636779785],"type":"Point"}
}