{
  "type": "Feature",
  "properties": {
    "addr:full":"Rue De Pintamont 19 Ath Hainaut 7800",
    "addr:housenumber":"19",
    "addr:postcode":"7800",
    "addr:street":"Rue De Pintamont",
    "iso:country":"BE",
    "sg:address":"Rue De Pintamont 19",
    "sg:city":"Ath",
    "sg:classifiers":[
        {
            "category":"Personal",
            "subcategory":"Beauty Salon",
            "type":"Services"
        }
    ],
    "sg:phone":"+32 68 44 52 03",
    "sg:postcode":"7800",
    "sg:province":"Hainaut",
    "sg:tags":[
        "de",
        "coiffure"
    ],
    "wof:name":"Vogue",
    "wof:placetype":"venue"
},
  "geometry": {"coordinates":[3.7748119831,50.6288337708],"type":"Point"}
}