{
  "type": "Feature",
  "properties": {
    "iso:country":"BE",
    "sg:address":"Donsegemstraat 4",
    "sg:city":"Tielt",
    "sg:orig_category":"Jardinage",
    "sg:phone":"+32 51 63 49 19",
    "sg:postcode":"8700",
    "sg:province":"West-Vlaanderen",
    "wof:name":"Algreen-van Ryckeghem L.",
    "wof:placetype":"venue"
},
  "geometry": {"coordinates":[3.4409201145,51.0106391907],"type":"Point"}
}