{
  "type": "Feature",
  "properties": {
    "addr:full":"Boulevard Alfred De Fontaine 17 Charleroi Hainaut 6000",
    "addr:housenumber":"17",
    "addr:postcode":"6000",
    "addr:street":"Boulevard Alfred De Fontaine;Hainaut",
    "iso:country":"BE",
    "sg:address":"Boulevard Alfred De Fontaine 17",
    "sg:city":"Charleroi",
    "sg:classifiers":[
        {
            "category":"Professional",
            "subcategory":"Lawyer & Legal Services",
            "type":"Services"
        }
    ],
    "sg:phone":"+32 71 20 17 17",
    "sg:postcode":"6000",
    "sg:province":"Hainaut",
    "wof:name":"Dandois Olivier",
    "wof:placetype":"venue"
},
  "geometry": {"coordinates":[4.4465241432,50.4104614258],"type":"Point"}
}