{
  "type": "Feature",
  "properties": {
    "addr:full":"Rue Valenciennes Quievrain Hainaut 7380",
    "addr:postcode":"7380",
    "addr:street":"Rue Valenciennes Quievrain Hainaut",
    "iso:country":"BE",
    "sg:address":"Rue Valenciennes",
    "sg:city":"Quievrain",
    "sg:orig_category":"Animaux domestiques and accessoires",
    "sg:phone":"+32 65 45 73 27",
    "sg:postcode":"7380",
    "sg:province":"Hainaut",
    "wof:name":"Borowiec Stamislwa",
    "wof:placetype":"venue"
},
  "geometry": {"coordinates":[3.6836400032,50.4076461792],"type":"Point"}
}