{
  "type": "Feature",
  "properties": {
    "iso:country":"BE",
    "sg:address":"Avenue De La R\u00e9sistance 228",
    "sg:city":"Soumagne",
    "sg:classifiers":[
        {
            "category":"Professional",
            "subcategory":"Accounting & Tax Preparation",
            "type":"Services"
        }
    ],
    "sg:phone":"+32 4 237 07 07",
    "sg:postcode":"4630",
    "sg:province":"Li\u00e8ge",
    "sg:tags":[
        "bookkeeper"
    ],
    "wof:name":"Bureau Comptable Joye Patrick",
    "wof:placetype":"venue"
},
  "geometry": {"coordinates":[5.7331490517,50.630771637],"type":"Point"}
}