{
  "type": "Feature",
  "properties": {
    "addr:full":"Place Henri Hallet 15 Hannut Li\u00e8ge 4280",
    "addr:housenumber":"15",
    "addr:postcode":"4280",
    "addr:street":"Place Henri Hallet",
    "iso:country":"BE",
    "sg:address":"Place Henri Hallet 15",
    "sg:city":"Hannut",
    "sg:orig_category":"Baby- and kinderkleding Dameskledingzaken Herenkledingzaken",
    "sg:phone":"+32 19 51 25 13",
    "sg:postcode":"4280",
    "sg:province":"Li\u00e8ge",
    "wof:name":"Maison La Renomm\u00c9e",
    "wof:placetype":"venue"
},
  "geometry": {"coordinates":[5.0789899826,50.6713523865],"type":"Point"}
}