{
  "type": "Feature",
  "properties": {
    "addr:full":"Haasstrasse 33 Eupen/eupen Li\u00e8ge 4700",
    "addr:housenumber":"33",
    "addr:postcode":"4700",
    "addr:street":"Haasstrasse",
    "iso:country":"BE",
    "sg:address":"Haasstrasse 33",
    "sg:city":"Eupen/eupen",
    "sg:orig_category":"Artsen and specialisten",
    "sg:phone":"+32 87 74 20 92",
    "sg:postcode":"4700",
    "sg:province":"Li\u00e8ge",
    "wof:name":"C. Mockel",
    "wof:placetype":"venue"
},
  "geometry": {"coordinates":[6.0379838943,50.6232032776],"type":"Point"}
}