{
  "type": "Feature",
  "properties": {
    "addr:full":"Albertlaan 218 Vorst Bruxelles-Capitale 1190",
    "addr:housenumber":"218",
    "addr:postcode":"1190",
    "addr:street":"Albertlaan",
    "iso:country":"BE",
    "sg:address":"Albertlaan 218",
    "sg:city":"Vorst",
    "sg:classifiers":[
        {
            "category":"Shopping",
            "subcategory":"Clothing, Apparel, & Fashions",
            "type":"Retail Goods"
        }
    ],
    "sg:phone":"+32 2 344 91 76",
    "sg:postcode":"1190",
    "sg:province":"Bruxelles-Capitale",
    "sg:tags":[
        "textile",
        "clothing",
        "clothes"
    ],
    "wof:name":"Vossen & Co Nv",
    "wof:placetype":"venue"
},
  "geometry": {"coordinates":[4.3472208977,50.8159065247],"type":"Point"}
}