{
  "type": "Feature",
  "properties": {
    "iso:country":"BE",
    "sg:address":"Venstraat 29",
    "sg:city":"Zandhoven (viersel)",
    "sg:classifiers":[
        {
            "category":"Building & Trades",
            "subcategory":"Landscaping Services",
            "type":"Services"
        }
    ],
    "sg:phone":"+32 3 475 23 09",
    "sg:postcode":"2240",
    "sg:province":"Antwerpen",
    "sg:tags":[
        "gardening",
        "garden",
        "maintenance"
    ],
    "wof:name":"Vanleke T",
    "wof:placetype":"venue"
},
  "geometry": {"coordinates":[4.6514492035,51.1932296753],"type":"Point"}
}