{
  "type": "Feature",
  "properties": {
    "addr:full":"Nieuwe Wijk 63 Lierde (sint-maria-lierde) Oost-Vlaanderen 9570",
    "addr:housenumber":"63",
    "addr:postcode":"9570",
    "addr:street":"Nieuwe Wijk",
    "iso:country":"BE",
    "sg:address":"Nieuwe Wijk 63",
    "sg:city":"Lierde (sint-maria-lierde)",
    "sg:classifiers":[
        {
            "category":"Building & Trades",
            "subcategory":"Electrical",
            "type":"Services"
        }
    ],
    "sg:phone":"+32 55 42 27 19",
    "sg:postcode":"9570",
    "sg:province":"Oost-Vlaanderen",
    "sg:tags":[
        "heating"
    ],
    "wof:name":"Quick Elektriek Nv",
    "wof:placetype":"venue"
},
  "geometry": {"coordinates":[3.8278169632,50.8130722046],"type":"Point"}
}