{
  "type": "Feature",
  "properties": {
    "addr:full":"Fortstraat 10 Sint-gillis/saint-gilles Bruxelles-Capitale 1060",
    "addr:housenumber":"10",
    "addr:postcode":"1060",
    "addr:street":"Fortstraat",
    "iso:country":"BE",
    "sg:address":"Fortstraat 10",
    "sg:city":"Sint-gillis/saint-gilles",
    "sg:orig_category":"Artiestenbureaus Boekenuitgeverijen Divers amusement Diverse zakelijke dienstverlening",
    "sg:phone":"+32 2 534 71 84",
    "sg:postcode":"1060",
    "sg:province":"Bruxelles-Capitale",
    "wof:name":"Nada",
    "wof:placetype":"venue"
},
  "geometry": {"coordinates":[4.3437051773,50.8297195435],"type":"Point"}
}