{
  "type": "Feature",
  "properties": {
    "addr:full":"Loystraat 92 Hamme Oost-Vlaanderen 9220",
    "addr:housenumber":"92",
    "addr:postcode":"9220",
    "addr:street":"Loystraat",
    "iso:country":"BE",
    "sg:address":"Loystraat 92",
    "sg:city":"Hamme",
    "sg:orig_category":"Epiceries",
    "sg:phone":"+32 52 48 03 47",
    "sg:postcode":"9220",
    "sg:province":"Oost-Vlaanderen",
    "wof:name":"Spar",
    "wof:placetype":"venue"
},
  "geometry": {"coordinates":[4.1424870491,51.0931854248],"type":"Point"}
}