{
  "type": "Feature",
  "properties": {
    "addr:full":"Heistraat 64 Mol Antwerpen 2400",
    "addr:housenumber":"64",
    "addr:postcode":"2400",
    "addr:street":"Heistraat",
    "iso:country":"BE",
    "sg:address":"Heistraat 64",
    "sg:city":"Mol",
    "sg:classifiers":[
        {
            "category":"Professional",
            "subcategory":"Computer Services",
            "type":"Services"
        }
    ],
    "sg:phone":"+32 14 81 47 18",
    "sg:postcode":"2400",
    "sg:province":"Antwerpen",
    "sg:tags":[
        "-",
        "processing",
        "data",
        "software"
    ],
    "wof:name":"Enof Automation Services Nv",
    "wof:placetype":"venue"
},
  "geometry": {"coordinates":[5.194270134,51.2051811218],"type":"Point"}
}