{
  "type": "Feature",
  "properties": {
    "addr:full":"Gentstraat 121 Gent Oost-Vlaanderen 9041",
    "addr:housenumber":"121",
    "addr:postcode":"9041",
    "addr:street":"Gentstraat;Oost-Vlaanderen",
    "iso:country":"BE",
    "sg:address":"Gentstraat 121",
    "sg:city":"Gent",
    "sg:orig_category":"Chaussures",
    "sg:phone":"+32 9 251 40 64",
    "sg:postcode":"9041",
    "sg:province":"Oost-Vlaanderen",
    "wof:name":"Cardon De Decker",
    "wof:placetype":"venue"
},
  "geometry": {"coordinates":[3.7582759857,51.0908584595],"type":"Point"}
}