{
  "type": "Feature",
  "properties": {
    "iso:country":"BE",
    "sg:address":"Rue A. Marbotin 25-27",
    "sg:city":"Brussel",
    "sg:orig_category":"Mobilier and \u00e9quipement m\u00e9nager Equipement divers pour commerces Gr",
    "sg:phone":"+32 2 240 77 80",
    "sg:postcode":"1030",
    "sg:province":"Bruxelles-Capitale",
    "wof:name":"Sit's International",
    "wof:placetype":"venue"
},
  "geometry": {"coordinates":[4.3904819489,50.8693313599],"type":"Point"}
}