{
  "type": "Feature",
  "properties": {
    "addr:full":"Avenue Des Sorbiers 91 Ottignies-louvain-la-neuve Brabant Wallon 1342",
    "addr:housenumber":"91",
    "addr:postcode":"1342",
    "addr:street":"Avenue Des Sorbiers",
    "iso:country":"BE",
    "sg:address":"Avenue Des Sorbiers 91",
    "sg:city":"Ottignies-louvain-la-neuve",
    "sg:orig_category":"Cr\u00e8ches and garderies d'enfants",
    "sg:phone":"+32 10 41 04 02",
    "sg:postcode":"1342",
    "sg:province":"Brabant Wallon",
    "wof:name":"Petits Loups Du Buston",
    "wof:placetype":"venue"
},
  "geometry": {"coordinates":[4.5620760918,50.6780929565],"type":"Point"}
}