{
  "type": "Feature",
  "properties": {
    "addr:full":"Rue De Bertinchamps 4 Gembloux-sur-orneau (gembloux) Namur 5030",
    "addr:housenumber":"4",
    "addr:postcode":"5030",
    "addr:street":"Rue De Bertinchamps;Namur",
    "iso:country":"BE",
    "sg:address":"Rue De Bertinchamps 4",
    "sg:city":"Gembloux-sur-orneau (gembloux)",
    "sg:classifiers":[
        {
            "category":"Sports & Exercise",
            "subcategory":"Stables",
            "type":"Entertainment"
        }
    ],
    "sg:phone":"+32 81 63 36 63",
    "sg:postcode":"5030",
    "sg:province":"Namur",
    "sg:tags":[
        "riding",
        "school"
    ],
    "wof:name":"Bertinchamps Kid's Club",
    "wof:placetype":"venue"
},
  "geometry": {"coordinates":[4.6358327866,50.5579986572],"type":"Point"}
}