{
  "type": "Feature",
  "properties": {
    "addr:full":"Chauss\u00e9e De Drogenbos 229 Bruxelles (uccle) Bruxelles-Capitale 1180",
    "addr:housenumber":"229",
    "addr:postcode":"1180",
    "addr:street":"Chausse\u0301E De Drogenbos",
    "iso:country":"BE",
    "sg:address":"Chauss\u00e9e De Drogenbos 229",
    "sg:city":"Bruxelles (uccle)",
    "sg:classifiers":[
        {
            "category":"Real Estate",
            "subcategory":"Architect",
            "type":"Services"
        }
    ],
    "sg:phone":"+32 2 332 38 14",
    "sg:postcode":"1180",
    "sg:province":"Bruxelles-Capitale",
    "wof:name":"Libert S",
    "wof:placetype":"venue"
},
  "geometry": {"coordinates":[4.3211507797,50.7860298157],"type":"Point"}
}