{
  "type": "Feature",
  "properties": {
    "addr:full":"Avenue Van Crombrugghe 23 Bruxelles Bruxelles-Capitale 1150",
    "addr:housenumber":"23",
    "addr:postcode":"1150",
    "addr:street":"Avenue Van Crombrugghe",
    "iso:country":"BE",
    "sg:address":"Avenue Van Crombrugghe 23",
    "sg:city":"Bruxelles",
    "sg:classifiers":[
        {
            "category":"Professional",
            "subcategory":"Computer Services",
            "type":"Services"
        }
    ],
    "sg:phone":"+32 2 779 20 61",
    "sg:postcode":"1150",
    "sg:province":"Bruxelles-Capitale",
    "sg:tags":[
        "administration",
        "software"
    ],
    "wof:name":"Cdn-caic S.p.r.l.",
    "wof:placetype":"venue"
},
  "geometry": {"coordinates":[4.4577040672,50.8270111084],"type":"Point"}
}