{
  "type": "Feature",
  "properties": {
    "iso:country":"BE",
    "sg:address":"Veldstraat 31",
    "sg:city":"Knesselare",
    "sg:orig_category":"Boucheries",
    "sg:phone":"+32 9 374 33 10",
    "sg:postcode":"9910",
    "sg:province":"Oost-Vlaanderen",
    "wof:name":"Gentiel Smessaert",
    "wof:placetype":"venue"
},
  "geometry": {"coordinates":[3.4161260128,51.138130188],"type":"Point"}
}