{
  "type": "Feature",
  "properties": {
    "iso:country":"BE",
    "sg:address":"Sint-maartenstraat 55bd",
    "sg:city":"Leuven",
    "sg:orig_category":"Hoger onderwijs",
    "sg:phone":"+32 16 29 85 11",
    "sg:postcode":"3000",
    "sg:province":"Vlaams-Brabant",
    "wof:name":"K.h.l.-dep. Rega",
    "wof:placetype":"venue"
},
  "geometry": {"coordinates":[4.7037467957,50.882774353],"type":"Point"}
}