{
  "type": "Feature",
  "properties": {
    "addr:full":"Bruggestraat 50-52 Hooglede West-Vlaanderen 8830",
    "addr:postcode":"50-52;8830",
    "addr:street":"Bruggestraat",
    "iso:country":"BE",
    "sg:address":"Bruggestraat 50-52",
    "sg:city":"Hooglede",
    "sg:classifiers":[
        {
            "category":"Banks & Credit Unions",
            "subcategory":"Investment Brokerage",
            "type":"Services"
        }
    ],
    "sg:phone":"+32 51 20 54 73",
    "sg:postcode":"8830",
    "sg:province":"West-Vlaanderen",
    "sg:tags":[
        "printing",
        "-"
    ],
    "wof:name":"Decoster",
    "wof:placetype":"venue"
},
  "geometry": {"coordinates":[3.0859019756,50.9792709351],"type":"Point"}
}