{
  "type": "Feature",
  "properties": {
    "iso:country":"BE",
    "sg:address":"Zavelstraat 65",
    "sg:city":"Herzele",
    "sg:classifiers":[
        {
            "category":"Communications",
            "subcategory":"Television Station",
            "type":"Services"
        }
    ],
    "sg:phone":"+32 54 50 03 11",
    "sg:postcode":"9550",
    "sg:province":"Oost-Vlaanderen",
    "sg:tags":[
        "de",
        "production",
        "spectacle"
    ],
    "wof:name":"Kon.fanf.kunst-broedermin",
    "wof:placetype":"venue"
},
  "geometry": {"coordinates":[3.8998689651,50.8516769409],"type":"Point"}
}