{
  "type": "Feature",
  "properties": {
    "iso:country":"BE",
    "sg:address":"Sterrenstraat 52",
    "sg:city":"Lier",
    "sg:classifiers":[
        {
            "category":"Professional",
            "subcategory":"Printing & Photocopies",
            "type":"Services"
        }
    ],
    "sg:phone":"+32 3 480 11 53",
    "sg:postcode":"2500",
    "sg:province":"Antwerpen",
    "sg:tags":[
        "-",
        "offset"
    ],
    "wof:name":"Beukeleirs Bvba",
    "wof:placetype":"venue"
},
  "geometry": {"coordinates":[4.5657100677,51.1394577026],"type":"Point"}
}