{
  "type": "Feature",
  "properties": {
    "addr:full":"Rubensstraat 13 Kontich Antwerpen 2550",
    "addr:housenumber":"13",
    "addr:postcode":"2550",
    "addr:street":"Rubensstraat",
    "iso:country":"BE",
    "sg:address":"Rubensstraat 13",
    "sg:city":"Kontich",
    "sg:orig_category":"V\u00e9los",
    "sg:phone":"+32 3 457 78 41",
    "sg:postcode":"2550",
    "sg:province":"Antwerpen",
    "wof:name":"Huis 't Ventiel",
    "wof:placetype":"venue"
},
  "geometry": {"coordinates":[4.4427142143,51.1336898804],"type":"Point"}
}