{
  "type": "Feature",
  "properties": {
    "iso:country":"BE",
    "sg:address":"Doorniksesteenweg 22",
    "sg:city":"Kortrijk",
    "sg:classifiers":[
        {
            "category":"Fast Food",
            "type":"Food & Drink"
        }
    ],
    "sg:phone":"+32 56 25 20 04",
    "sg:postcode":"8500",
    "sg:province":"West-Vlaanderen",
    "sg:tags":[
        "fried",
        "stand",
        "potato"
    ],
    "wof:name":"De Blauwe Frituur",
    "wof:placetype":"venue"
},
  "geometry": {"coordinates":[3.2707419395,50.8162651062],"type":"Point"}
}