{
  "type": "Feature",
  "properties": {
    "addr:full":"Schoolstraat 8 Brakel Oost-Vlaanderen 9660",
    "addr:housenumber":"8",
    "addr:postcode":"9660",
    "addr:street":"Schoolstraat",
    "iso:country":"BE",
    "sg:address":"Schoolstraat 8",
    "sg:city":"Brakel",
    "sg:orig_category":"Enseignement maternel and primaire",
    "sg:phone":"+32 55 42 71 82",
    "sg:postcode":"9660",
    "sg:province":"Oost-Vlaanderen",
    "wof:name":"Vrije Kleuterschool",
    "wof:placetype":"venue"
},
  "geometry": {"coordinates":[3.7585680485,50.813419342],"type":"Point"}
}