{
  "type": "Feature",
  "properties": {
    "addr:full":"De Meyerstraat 3f Brecht Antwerpen 2960",
    "addr:housenumber":"3f",
    "addr:postcode":"2960",
    "addr:street":"De Meyerstraat",
    "iso:country":"BE",
    "sg:address":"De Meyerstraat 3f",
    "sg:city":"Brecht",
    "sg:orig_category":"Installation de menuiserie en bois and plastique",
    "sg:phone":"+32 3 645 32 34",
    "sg:postcode":"2960",
    "sg:province":"Antwerpen",
    "wof:name":"De Schrijn",
    "wof:placetype":"venue"
},
  "geometry": {"coordinates":[4.6014051437,51.3153114319],"type":"Point"}
}