{
  "type": "Feature",
  "properties": {
    "addr:full":"Buffelstraat 33 Zele Oost-Vlaanderen 9240",
    "addr:housenumber":"33",
    "addr:postcode":"9240",
    "addr:street":"Buffelstraat",
    "iso:country":"BE",
    "sg:address":"Buffelstraat 33",
    "sg:city":"Zele",
    "sg:classifiers":[
        {
            "category":"Building & Trades",
            "subcategory":"Landscaping Services",
            "type":"Services"
        }
    ],
    "sg:phone":"+32 52 44 41 19",
    "sg:postcode":"9240",
    "sg:province":"Oost-Vlaanderen",
    "sg:tags":[
        "gardening",
        "garden",
        "maintenance"
    ],
    "wof:name":"Van Bunder G",
    "wof:placetype":"venue"
},
  "geometry": {"coordinates":[4.0785050392,51.0671272278],"type":"Point"}
}