{
  "type": "Feature",
  "properties": {
    "addr:full":"Breendonkstraat 13 Willebroek Antwerpen 2830",
    "addr:housenumber":"13",
    "addr:postcode":"2830",
    "addr:street":"Breendonkstraat",
    "iso:country":"BE",
    "sg:address":"Breendonkstraat 13",
    "sg:city":"Willebroek",
    "sg:orig_category":"Sociale huisvestingsmaatschappijen",
    "sg:phone":"+32 3 886 56 12",
    "sg:postcode":"2830",
    "sg:province":"Antwerpen",
    "wof:name":"Volkshuisvesting S.m.",
    "wof:placetype":"venue"
},
  "geometry": {"coordinates":[4.354031086,51.0553588867],"type":"Point"}
}