{
  "type": "Feature",
  "properties": {
    "addr:full":"Lod Lavkiplein 8 Hasselt Limburg 3500",
    "addr:housenumber":"8",
    "addr:postcode":"3500",
    "addr:street":"Lavkiplein",
    "iso:country":"BE",
    "sg:address":"Lod Lavkiplein 8",
    "sg:city":"Hasselt",
    "sg:classifiers":[
        {
            "category":"Arts & Performance",
            "subcategory":"Music",
            "type":"Entertainment"
        }
    ],
    "sg:phone":"+32 11 22 29 35",
    "sg:postcode":"3500",
    "sg:province":"Limburg",
    "sg:tags":[
        "disc-jockeys"
    ],
    "wof:name":"Discobar Move",
    "wof:placetype":"venue"
},
  "geometry": {"coordinates":[5.3526182175,50.9464797974],"type":"Point"}
}