{
  "type": "Feature",
  "properties": {
    "addr:full":"Oude Beurs 23 Antwerpen Antwerpen 2000",
    "addr:housenumber":"23",
    "addr:postcode":"2000",
    "addr:street":"Oude Beurs",
    "iso:country":"BE",
    "sg:address":"Oude Beurs 23",
    "sg:city":"Antwerpen",
    "sg:classifiers":[
        {
            "category":"Arts & Performance",
            "subcategory":"Theater",
            "type":"Entertainment"
        }
    ],
    "sg:phone":"+32 3 226 23 76",
    "sg:postcode":"2000",
    "sg:province":"Antwerpen",
    "sg:tags":[
        "theatrical",
        "agency"
    ],
    "wof:name":"Impresariaat Jacques Senf",
    "wof:placetype":"venue"
},
  "geometry": {"coordinates":[4.4003958702,51.2221908569],"type":"Point"}
}