{
  "type": "Feature",
  "properties": {
    "iso:country":"BE",
    "sg:address":"Tiensesteenweg 386",
    "sg:city":"Leuven",
    "sg:classifiers":[
        {
            "category":"Building & Trades",
            "subcategory":"Construction",
            "type":"Services"
        }
    ],
    "sg:phone":"+32 16 25 00 15",
    "sg:postcode":"3000",
    "sg:province":"Vlaams-Brabant",
    "sg:tags":[
        "fireplace"
    ],
    "wof:name":"Standard Ahz Nv",
    "wof:placetype":"venue"
},
  "geometry": {"coordinates":[4.7407131195,50.8674697876],"type":"Point"}
}