{
  "type": "Feature",
  "properties": {
    "iso:country":"BE",
    "sg:address":"Hoevestraat 69",
    "sg:city":"Huldenberg",
    "sg:orig_category":"Elektrische installaties voor woningen",
    "sg:phone":"+32 16 47 05 92",
    "sg:postcode":"3040",
    "sg:province":"Vlaams-Brabant",
    "wof:name":"De Messemaekers",
    "wof:placetype":"venue"
},
  "geometry": {"coordinates":[4.6099791527,50.7583465576],"type":"Point"}
}