{
  "type": "Feature",
  "properties": {
    "iso:country":"BE",
    "sg:address":"Anzegemsesteenweg 8",
    "sg:city":"Kruishoutem",
    "sg:classifiers":[
        {
            "category":"Professional",
            "subcategory":"Computer Services",
            "type":"Services"
        }
    ],
    "sg:phone":"+32 474 89 58 00",
    "sg:postcode":"9770",
    "sg:province":"Oost-Vlaanderen",
    "sg:tags":[
        "-",
        "processing",
        "data"
    ],
    "wof:name":"Budget Computers",
    "wof:placetype":"venue"
},
  "geometry": {"coordinates":[3.5282580853,50.8990249634],"type":"Point"}
}