{
  "type": "Feature",
  "properties": {
    "iso:country":"BE",
    "sg:address":"Middelburgstraat 20",
    "sg:city":"Watermaal-bosvoorde/watermael-boitsfort",
    "sg:orig_category":"Slagers",
    "sg:phone":"+32 2 672 27 07",
    "sg:postcode":"1170",
    "sg:province":"Bruxelles-Capitale",
    "wof:name":"Willem Steenhoudt/w. Steenhoudt",
    "wof:placetype":"venue"
},
  "geometry": {"coordinates":[4.4178881645,50.797077179],"type":"Point"}
}