{
  "type": "Feature",
  "properties": {
    "addr:full":"Genkerbaan 107 Zonhoven Limburg 3520",
    "addr:housenumber":"107",
    "addr:postcode":"3520",
    "addr:street":"Genkerbaan",
    "iso:country":"BE",
    "sg:address":"Genkerbaan 107",
    "sg:city":"Zonhoven",
    "sg:classifiers":[
        {
            "category":"Building & Trades",
            "subcategory":"Construction",
            "type":"Services"
        }
    ],
    "sg:phone":"+32 11 81 23 19",
    "sg:postcode":"3520",
    "sg:province":"Limburg",
    "sg:tags":[
        "stucco",
        "contractor"
    ],
    "wof:name":"Hasevoets Guy",
    "wof:placetype":"venue"
},
  "geometry": {"coordinates":[5.3820939064,50.9914894104],"type":"Point"}
}