{
  "type": "Feature",
  "properties": {
    "addr:full":"Rue Du Comte Th\u00e9odule D'ursel 18 Durbuy Luxembourg 6940",
    "addr:housenumber":"18",
    "addr:postcode":"6940",
    "addr:street":"Rue Du Comte The\u0301Odule D'Ursel",
    "iso:country":"BE",
    "sg:address":"Rue Du Comte Th\u00e9odule D'ursel 18",
    "sg:city":"Durbuy",
    "sg:classifiers":[
        {
            "category":"Shopping",
            "subcategory":"Musical Instruments",
            "type":"Retail Goods"
        }
    ],
    "sg:phone":"+32 86 21 27 12",
    "sg:postcode":"6940",
    "sg:province":"Luxembourg",
    "sg:tags":[
        "-"
    ],
    "wof:name":"Note D'or (la)",
    "wof:placetype":"venue"
},
  "geometry": {"coordinates":[5.4542717934,50.3517341614],"type":"Point"}
}