{
  "type": "Feature",
  "properties": {
    "addr:full":"Place De La Chapelle 6 Brussel/bruxelles Bruxelles-Capitale 1000",
    "addr:housenumber":"6",
    "addr:postcode":"1000",
    "addr:street":"Place De La Chapelle;/",
    "iso:country":"BE",
    "sg:address":"Place De La Chapelle 6",
    "sg:city":"Brussel/bruxelles",
    "sg:orig_category":"Salles de conf\u00e9rences and de r\u00e9ceptions. Dancings and bo\u00eetes de nuit",
    "sg:phone":"+32 2 502 68 17",
    "sg:postcode":"1000",
    "sg:province":"Bruxelles-Capitale",
    "wof:name":"Caves Drouot",
    "wof:placetype":"venue"
},
  "geometry": {"coordinates":[4.3503808975,50.8412055969],"type":"Point"}
}