{
  "type": "Feature",
  "properties": {
    "addr:full":"Rue Neuve 111 Brussel/bruxelles Bruxelles-Capitale 1000",
    "addr:housenumber":"111",
    "addr:postcode":"1000",
    "addr:street":"Rue Neuve;/",
    "iso:country":"BE",
    "sg:address":"Rue Neuve 111",
    "sg:city":"Brussel/bruxelles",
    "sg:orig_category":"Parfumeries",
    "sg:phone":"+32 2 219 55 08",
    "sg:postcode":"1000",
    "sg:province":"Bruxelles-Capitale",
    "wof:name":"Lanc\u00d4me Stand Innovation",
    "wof:placetype":"venue"
},
  "geometry": {"coordinates":[4.3571557999,50.8536758423],"type":"Point"}
}