{
  "type": "Feature",
  "properties": {
    "iso:country":"BE",
    "sg:address":"Tiensesteenweg 266",
    "sg:city":"Sint-truiden (groot)",
    "sg:orig_category":"Supermarkten",
    "sg:phone":"+32 11 68 49 74",
    "sg:postcode":"3800",
    "sg:province":"Limburg",
    "wof:name":"Colruyt",
    "wof:placetype":"venue"
},
  "geometry": {"coordinates":[5.150742054,50.8125495911],"type":"Point"}
}