{
  "type": "Feature",
  "properties": {
    "addr:full":"Postelsesteenweg 71 Mol Antwerpen 2400",
    "addr:housenumber":"71",
    "addr:postcode":"2400",
    "addr:street":"Postelsesteenweg",
    "iso:country":"BE",
    "sg:address":"Postelsesteenweg 71",
    "sg:city":"Mol",
    "sg:classifiers":[
        {
            "category":"Government",
            "subcategory":"Office",
            "type":"Public Place"
        }
    ],
    "sg:phone":"+32 14 81 60 22",
    "sg:postcode":"2400",
    "sg:province":"Antwerpen",
    "sg:tags":[
        "-",
        "tourism",
        "federation"
    ],
    "wof:name":"Oosterkempen Vzw",
    "wof:placetype":"venue"
},
  "geometry": {"coordinates":[5.1824297905,51.2125701904],"type":"Point"}
}