{
  "type": "Feature",
  "properties": {
    "addr:full":"140 Rue De Letat 4682 Oupeye 140",
    "addr:housenumber":"140",
    "addr:postcode":"4682;140",
    "addr:street":"Rue De Letat",
    "iso:country":"BE",
    "sg:address":"140",
    "sg:city":"Rue De Letat 4682 Oupeye",
    "sg:classifiers":[
        {
            "category":"Building & Trades",
            "subcategory":"Construction",
            "type":"Services"
        }
    ],
    "sg:phone":"+32 4 286 11 81",
    "sg:postcode":"140",
    "sg:tags":[
        "work",
        "public"
    ],
    "wof:name":"Thomassen & Fils Sprl",
    "wof:placetype":"venue"
},
  "geometry": {"coordinates":[5.6338701248,50.7312393188],"type":"Point"}
}