{
  "type": "Feature",
  "properties": {
    "addr:full":"Gontrode Heirweg 85 Melle Oost-Vlaanderen 9090",
    "addr:housenumber":"85",
    "addr:postcode":"9090",
    "addr:street":"Gontrode Heirweg",
    "iso:country":"BE",
    "sg:address":"Gontrode Heirweg 85",
    "sg:city":"Melle",
    "sg:orig_category":"Accumulators",
    "sg:phone":"+32 9 230 74 72",
    "sg:postcode":"9090",
    "sg:province":"Oost-Vlaanderen",
    "wof:name":"Deta",
    "wof:placetype":"venue"
},
  "geometry": {"coordinates":[3.7690250874,51.0127716064],"type":"Point"}
}