{
  "type": "Feature",
  "properties": {
    "addr:full":"Parkstraat 103 Leuven Vlaams-Brabant 3000",
    "addr:housenumber":"103",
    "addr:postcode":"3000",
    "addr:street":"Parkstraat",
    "iso:country":"BE",
    "sg:address":"Parkstraat 103",
    "sg:city":"Leuven",
    "sg:classifiers":[
        {
            "category":"Bakery",
            "type":"Food & Drink"
        }
    ],
    "sg:phone":"+32 16 22 56 60",
    "sg:postcode":"3000",
    "sg:province":"Vlaams-Brabant",
    "sg:tags":[
        "confectioner",
        "baker"
    ],
    "wof:name":"Van Huyck",
    "wof:placetype":"venue"
},
  "geometry": {"coordinates":[4.7036571503,50.8724136353],"type":"Point"}
}