{
  "type": "Feature",
  "properties": {
    "iso:country":"BE",
    "sg:address":"Brusselsesteenweg 327",
    "sg:city":"Ninove",
    "sg:orig_category":"Autoverhuur Verhuisdiensten",
    "sg:phone":"+32 54 33 13 31",
    "sg:postcode":"9402",
    "sg:province":"Oost-Vlaanderen",
    "wof:name":"Nino Transport",
    "wof:placetype":"venue"
},
  "geometry": {"coordinates":[4.0395750999,50.8249015808],"type":"Point"}
}