{
  "type": "Feature",
  "properties": {
    "addr:full":"Remparden 37 Oudenaarde Oost-Vlaanderen 9700",
    "addr:housenumber":"37",
    "addr:postcode":"9700",
    "addr:street":"Remparden",
    "iso:country":"BE",
    "sg:address":"Remparden 37",
    "sg:city":"Oudenaarde",
    "sg:orig_category":"Kapsalons",
    "sg:phone":"+32 55 31 68 57",
    "sg:postcode":"9700",
    "sg:province":"Oost-Vlaanderen",
    "wof:name":"Coiffure Nadine",
    "wof:placetype":"venue"
},
  "geometry": {"coordinates":[3.6099560261,50.8403892517],"type":"Point"}
}