{
  "type": "Feature",
  "properties": {
    "iso:country":"BE",
    "sg:address":"Place Du Pr\u00e9au 7",
    "sg:city":"Antoing",
    "sg:classifiers":[
        {
            "category":"Shopping",
            "subcategory":"Jewelry",
            "type":"Retail Goods"
        }
    ],
    "sg:phone":"+32 69 44 27 15",
    "sg:postcode":"7640",
    "sg:province":"Hainaut",
    "sg:tags":[
        "jeweller",
        "-"
    ],
    "wof:name":"Hernould F",
    "wof:placetype":"venue"
},
  "geometry": {"coordinates":[3.4454519749,50.5673828125],"type":"Point"}
}