{
  "type": "Feature",
  "properties": {
    "iso:country":"BE",
    "sg:address":"Avenue Emile Vandervelde 9",
    "sg:city":"Waremme",
    "sg:orig_category":"Avocats and conseillers juridiques",
    "sg:phone":"+32 19 33 01 41",
    "sg:postcode":"4300",
    "sg:province":"Li\u00e8ge",
    "wof:name":"J.m. Tihon",
    "wof:placetype":"venue"
},
  "geometry": {"coordinates":[5.2580871582,50.6962852478],"type":"Point"}
}