{
  "type": "Feature",
  "properties": {
    "iso:country":"BE",
    "sg:address":"Gemeenteplein 15",
    "sg:city":"Melle",
    "sg:orig_category":"Foto-uitrusting",
    "sg:phone":"+32 9 224 19 14",
    "sg:postcode":"9090",
    "sg:province":"Oost-Vlaanderen",
    "wof:name":"Foto De Buck",
    "wof:placetype":"venue"
},
  "geometry": {"coordinates":[3.7994771004,51.0030326843],"type":"Point"}
}