{
  "type": "Feature",
  "properties": {
    "iso:country":"BE",
    "sg:address":"Rue Des Ardennes 21",
    "sg:city":"Saint-hubert",
    "sg:orig_category":"Enseignement maternel and primaire",
    "sg:phone":"+32 61 61 22 88",
    "sg:postcode":"6870",
    "sg:province":"Luxembourg",
    "wof:name":"Ecole Fond. Communale",
    "wof:placetype":"venue"
},
  "geometry": {"coordinates":[5.2937488556,50.0153427124],"type":"Point"}
}