{
  "type": "Feature",
  "properties": {
    "iso:country":"BE",
    "sg:address":"Fazantstraat 36",
    "sg:city":"Meeuwen-gruitrode",
    "sg:orig_category":"Woningbouw",
    "sg:phone":"+32 89 85 39 69",
    "sg:postcode":"3670",
    "sg:province":"Limburg",
    "wof:name":"Ibrahim Dusen",
    "wof:placetype":"venue"
},
  "geometry": {"coordinates":[5.5205497742,51.0963516235],"type":"Point"}
}