{
  "type": "Feature",
  "properties": {
    "addr:full":"Vichtestraat 11 Deerlijk West-Vlaanderen 8540",
    "addr:housenumber":"11",
    "addr:postcode":"8540",
    "addr:street":"Vichtestraat",
    "iso:country":"BE",
    "sg:address":"Vichtestraat 11",
    "sg:city":"Deerlijk",
    "sg:orig_category":"Sportclubs",
    "sg:phone":"+32 56 70 07 69",
    "sg:postcode":"8540",
    "sg:province":"West-Vlaanderen",
    "wof:name":"De Gildevliegers",
    "wof:placetype":"venue"
},
  "geometry": {"coordinates":[3.3666260242,50.8548431396],"type":"Point"}
}