{
  "type": "Feature",
  "properties": {
    "addr:full":"Sint-bernardusstraat 190 Sint-gillis/saint-gilles Bruxelles-Capitale 1060",
    "addr:housenumber":"190",
    "addr:postcode":"1060",
    "addr:street":"Sint-Bernardusstraat",
    "iso:country":"BE",
    "sg:address":"Sint-bernardusstraat 190",
    "sg:city":"Sint-gillis/saint-gilles",
    "sg:orig_category":"Zalen voor culturele evenementen",
    "sg:phone":"+32 2 538 82 83",
    "sg:postcode":"1060",
    "sg:province":"Bruxelles-Capitale",
    "wof:name":"Compagnie Du Vertige",
    "wof:placetype":"venue"
},
  "geometry": {"coordinates":[4.349503994,50.8253288269],"type":"Point"}
}