{
  "type": "Feature",
  "properties": {
    "iso:country":"BE",
    "sg:address":"Avenue Hanssen Soulie 78",
    "sg:city":"Brussel/bruxelles",
    "sg:orig_category":"Catering and organisatie van feesten",
    "sg:phone":"+32 2 648 47 66",
    "sg:postcode":"1040",
    "sg:province":"Bruxelles-Capitale",
    "wof:name":"Rodel",
    "wof:placetype":"venue"
},
  "geometry": {"coordinates":[4.3997998238,50.8301773071],"type":"Point"}
}