{
  "type": "Feature",
  "properties": {
    "addr:full":"Jozef Braetstraat 1 Oudenaarde Oost-Vlaanderen 9700",
    "addr:housenumber":"1",
    "addr:postcode":"9700",
    "addr:street":"Jozef Braetstraat",
    "iso:country":"BE",
    "sg:address":"Jozef Braetstraat 1",
    "sg:city":"Oudenaarde",
    "sg:classifiers":[
        {
            "category":"Shopping",
            "subcategory":"Florist",
            "type":"Retail Goods"
        }
    ],
    "sg:phone":"+32 55 30 19 72",
    "sg:postcode":"9700",
    "sg:province":"Oost-Vlaanderen",
    "wof:name":"Papaver",
    "wof:placetype":"venue"
},
  "geometry": {"coordinates":[3.6078989506,50.8388366699],"type":"Point"}
}