{
  "type": "Feature",
  "properties": {
    "addr:full":"Rue Du Coll\u00c8ge 12 Charleroi Hainaut 6000",
    "addr:housenumber":"12",
    "addr:postcode":"6000",
    "addr:street":"Rue Du Colle\u0300Ge;Hainaut",
    "iso:country":"BE",
    "sg:address":"Rue Du Coll\u00c8ge 12",
    "sg:city":"Charleroi",
    "sg:orig_category":"Quincailleries",
    "sg:phone":"+32 71 33 47 77",
    "sg:postcode":"6000",
    "sg:province":"Hainaut",
    "wof:name":"La Passion De L\u00b4art",
    "wof:placetype":"venue"
},
  "geometry": {"coordinates":[4.4399461746,50.4070281982],"type":"Point"}
}