{
  "type": "Feature",
  "properties": {
    "addr:full":"Sint-pietersnieuwstraat 130b Gent Oost-Vlaanderen 9000",
    "addr:housenumber":"130b",
    "addr:postcode":"9000",
    "addr:street":"Sint-Pietersnieuwstraat;Oost-Vlaanderen",
    "iso:country":"BE",
    "sg:address":"Sint-pietersnieuwstraat 130b",
    "sg:city":"Gent",
    "sg:classifiers":[
        {
            "category":"Utilities",
            "subcategory":"Recycling",
            "type":"Services"
        }
    ],
    "sg:phone":"+32 9 234 34 57",
    "sg:postcode":"9000",
    "sg:province":"Oost-Vlaanderen",
    "wof:name":"Bat Services Bvba",
    "wof:placetype":"venue"
},
  "geometry": {"coordinates":[3.7269029617,51.0469856262],"type":"Point"}
}