{
  "type": "Feature",
  "properties": {
    "iso:country":"BE",
    "sg:address":"Driesln 23",
    "sg:city":"Morsele",
    "sg:classifiers":[
        {
            "category":"Manufacturing",
            "subcategory":"Metals",
            "type":"Manufacturing & Wholesale Goods"
        }
    ],
    "sg:phone":"+32 56 40 20 57",
    "sg:postcode":"8560",
    "sg:province":"West-Vlaanderen",
    "sg:tags":[
        "metallurgy",
        "metalworking",
        "processing"
    ],
    "wof:name":"Jose Vancoillie En Co Bvba",
    "wof:placetype":"venue"
},
  "geometry": {"coordinates":[3.1799249649,50.808013916],"type":"Point"}
}