{
  "type": "Feature",
  "properties": {
    "addr:full":"Chausee De Namur 32 Sombreffe Namur 5140",
    "addr:housenumber":"32",
    "addr:postcode":"5140",
    "addr:street":"Chausee;Namur",
    "iso:country":"BE",
    "sg:address":"Chausee De Namur 32",
    "sg:city":"Sombreffe",
    "sg:orig_category":"Entretien and r\u00e9parations de voitures",
    "sg:phone":"+32 71 88 50 88",
    "sg:postcode":"5140",
    "sg:province":"Namur",
    "wof:name":"Carrosserie Du Docq",
    "wof:placetype":"venue"
},
  "geometry": {"coordinates":[4.6367697716,50.5226097107],"type":"Point"}
}