{
  "type": "Feature",
  "properties": {
    "addr:full":"Rue Au Bois 350 Bruxelles (woluwe-saint-pierre) Bruxelles-Capitale 1150",
    "addr:housenumber":"350",
    "addr:postcode":"1150",
    "addr:street":"Rue Au Bois",
    "iso:country":"BE",
    "sg:address":"Rue Au Bois 350",
    "sg:city":"Bruxelles (woluwe-saint-pierre)",
    "sg:classifiers":[
        {
            "category":"Deli",
            "type":"Food & Drink"
        }
    ],
    "sg:phone":"+32 2 345 59 58",
    "sg:postcode":"1150",
    "sg:province":"Bruxelles-Capitale",
    "sg:tags":[
        "delicatessen"
    ],
    "wof:name":"Scandinavian Catering",
    "wof:placetype":"venue"
},
  "geometry": {"coordinates":[4.4539108276,50.8302116394],"type":"Point"}
}