{
  "type": "Feature",
  "properties": {
    "iso:country":"BE",
    "sg:address":"Rue Ernest Solvay 11",
    "sg:city":"Elsene/ixelles",
    "sg:orig_category":"Traitements param\u00e9dicaux. M\u00e9decins and sp\u00e9cialistes",
    "sg:phone":"+32 2 512 73 66",
    "sg:postcode":"1050",
    "sg:province":"Bruxelles-Capitale",
    "wof:name":"Encalado",
    "wof:placetype":"venue"
},
  "geometry": {"coordinates":[4.3643407822,50.8357467651],"type":"Point"}
}