{
  "type": "Feature",
  "properties": {
    "iso:country":"BE",
    "sg:address":"3290",
    "sg:city":"Diest (groot)",
    "sg:orig_category":"Pharmaciens",
    "sg:phone":"+32 900 10 500",
    "sg:postcode":"3290",
    "sg:province":"Vlaams-Brabant",
    "wof:name":"Pharmacies De Garde",
    "wof:placetype":"venue"
},
  "geometry": {"coordinates":[5.0930600166,50.9964485168],"type":"Point"}
}