{
  "type": "Feature",
  "properties": {
    "iso:country":"BE",
    "sg:address":"Laageind 4",
    "sg:city":"Stabroek",
    "sg:orig_category":"Medische apparatuur, orthopedische artikelen and prothesen Fab",
    "sg:phone":"+32 3 569 16 56",
    "sg:postcode":"2940",
    "sg:province":"Antwerpen",
    "wof:name":"Karel Van Boxtel",
    "wof:placetype":"venue"
},
  "geometry": {"coordinates":[4.3622870445,51.3310050964],"type":"Point"}
}