{
  "type": "Feature",
  "properties": {
    "iso:country":"BE",
    "sg:address":"Rue Des Trois Rois 254",
    "sg:city":"Ans",
    "sg:orig_category":"M\u00e9decins and sp\u00e9cialistes",
    "sg:phone":"+32 4 246 49 63",
    "sg:postcode":"4430",
    "sg:province":"Li\u00e8ge",
    "wof:name":"Michael Schuerch",
    "wof:placetype":"venue"
},
  "geometry": {"coordinates":[5.5364589691,50.6631774902],"type":"Point"}
}