{
  "type": "Feature",
  "properties": {
    "iso:country":"BE",
    "sg:address":"Avenue Du Scheutbosch 26",
    "sg:city":"Sint-jans-molenbeek/molenbeek-saint-jean",
    "sg:orig_category":"Epiceries",
    "sg:phone":"+32 2 411 00 92",
    "sg:postcode":"1080",
    "sg:province":"Bruxelles-Capitale",
    "wof:name":"Sotirios Natsios",
    "wof:placetype":"venue"
},
  "geometry": {"coordinates":[4.3044099808,50.8512268066],"type":"Point"}
}