{
  "type": "Feature",
  "properties": {
    "iso:country":"BE",
    "sg:address":"Varentstraat 32",
    "sg:city":"Buggenhout",
    "sg:classifiers":[
        {
            "category":"Retail",
            "subcategory":"Auto Repair",
            "type":"Services"
        }
    ],
    "sg:phone":"+32 52 35 65 44",
    "sg:postcode":"9255",
    "sg:province":"Oost-Vlaanderen",
    "sg:tags":[
        "garage"
    ],
    "wof:name":"Servaes Cv",
    "wof:placetype":"venue"
},
  "geometry": {"coordinates":[4.1724581718,50.998588562],"type":"Point"}
}