{
  "type": "Feature",
  "properties": {
    "addr:full":"Mechelsesteenweg 263 Willebroek (blaasveld) Antwerpen 2830",
    "addr:housenumber":"263",
    "addr:postcode":"2830",
    "addr:street":"Mechelsesteenweg",
    "iso:country":"BE",
    "sg:address":"Mechelsesteenweg 263",
    "sg:city":"Willebroek (blaasveld)",
    "sg:classifiers":[
        {
            "category":"Shopping",
            "subcategory":"Jewelry",
            "type":"Retail Goods"
        }
    ],
    "sg:phone":"+32 3 886 81 63",
    "sg:postcode":"2830",
    "sg:province":"Antwerpen",
    "sg:tags":[
        "jeweller",
        "-"
    ],
    "wof:name":"Smets C",
    "wof:placetype":"venue"
},
  "geometry": {"coordinates":[4.3734622002,51.0501060486],"type":"Point"}
}