{
  "type": "Feature",
  "properties": {
    "iso:country":"BE",
    "sg:address":"Antwerpsesteenweg 895",
    "sg:city":"Gent (oostakker)",
    "sg:classifiers":[
        {
            "category":"Home & Garden",
            "subcategory":"Carpets & Floor Coverings",
            "type":"Retail Goods"
        }
    ],
    "sg:phone":"+32 9 355 92 96",
    "sg:postcode":"9041",
    "sg:province":"Oost-Vlaanderen",
    "sg:tags":[
        "oriental"
    ],
    "wof:name":"Tipu-orient Belgium",
    "wof:placetype":"venue"
},
  "geometry": {"coordinates":[3.7854158878,51.0798988342],"type":"Point"}
}