{
  "type": "Feature",
  "properties": {
    "iso:country":"BE",
    "sg:address":"Eikhoekstraat 65",
    "sg:city":"Vleteren",
    "sg:orig_category":"Instituts pour enfants en difficult\u00e9. Orphelinats",
    "sg:phone":"+32 57 40 07 47",
    "sg:postcode":"8640",
    "sg:province":"West-Vlaanderen",
    "wof:name":"Home De Walhoeve",
    "wof:placetype":"venue"
},
  "geometry": {"coordinates":[2.7406210899,50.9036331177],"type":"Point"}
}