{
  "type": "Feature",
  "properties": {
    "addr:full":"Rue La N\u00f4 35 Pepinster Li\u00e8ge 4860",
    "addr:housenumber":"35",
    "addr:postcode":"4860",
    "addr:street":"Rue La No\u0302",
    "iso:country":"BE",
    "sg:address":"Rue La N\u00f4 35",
    "sg:city":"Pepinster",
    "sg:orig_category":"Non-Classified Establishments",
    "sg:phone":"+32 87 46 01 71",
    "sg:postcode":"4860",
    "sg:province":"Li\u00e8ge",
    "wof:name":"Vanderheyden & Fils Sprl",
    "wof:placetype":"venue"
},
  "geometry": {"coordinates":[5.8020758629,50.5628547668],"type":"Point"}
}