{
  "type": "Feature",
  "properties": {
    "addr:full":"Oostendesteenweg 167a Ichtegem (eernegem) West-Vlaanderen 8480",
    "addr:housenumber":"167a",
    "addr:postcode":"8480",
    "addr:street":"Oostendesteenweg",
    "iso:country":"BE",
    "sg:address":"Oostendesteenweg 167a",
    "sg:city":"Ichtegem (eernegem)",
    "sg:classifiers":[
        {
            "category":"Communications",
            "subcategory":"Radio Station",
            "type":"Services"
        }
    ],
    "sg:phone":"+32 59 29 85 75",
    "sg:postcode":"8480",
    "sg:province":"West-Vlaanderen",
    "sg:tags":[
        "telephony"
    ],
    "wof:name":"Bostyn A",
    "wof:placetype":"venue"
},
  "geometry": {"coordinates":[3.0132501125,51.1129493713],"type":"Point"}
}