{
  "type": "Feature",
  "properties": {
    "iso:country":"BE",
    "sg:address":"Beugelstraat 87",
    "sg:city":"Zottegem (strijpen)",
    "sg:classifiers":[
        {
            "category":"Retail",
            "subcategory":"Event Space",
            "type":"Services"
        }
    ],
    "sg:phone":"+32 477 85 09 18",
    "sg:postcode":"9620",
    "sg:province":"Oost-Vlaanderen",
    "sg:tags":[
        "organisation"
    ],
    "wof:name":"Km Service",
    "wof:placetype":"venue"
},
  "geometry": {"coordinates":[3.8112111092,50.871181488],"type":"Point"}
}