{
  "type": "Feature",
  "properties": {
    "addr:full":"Egemveldweg 2 Pittem West-Vlaanderen 8740",
    "addr:housenumber":"2",
    "addr:postcode":"8740",
    "addr:street":"Egemveldweg",
    "iso:country":"BE",
    "sg:address":"Egemveldweg 2",
    "sg:city":"Pittem",
    "sg:classifiers":[
        {
            "category":"Professional",
            "type":"Services"
        }
    ],
    "sg:phone":"+32 51 61 14 89",
    "sg:postcode":"8740",
    "sg:province":"West-Vlaanderen",
    "sg:tags":[
        "transport",
        "road"
    ],
    "wof:name":"Van Bruwaene Daniel M.",
    "wof:placetype":"venue"
},
  "geometry": {"coordinates":[3.2614929676,51.0323944092],"type":"Point"}
}