{
  "type": "Feature",
  "properties": {
    "addr:full":"Zevekotestraat 16 Evergem Oost-Vlaanderen 9940",
    "addr:housenumber":"16",
    "addr:postcode":"9940",
    "addr:street":"Zevekotestraat;Oost-Vlaanderen",
    "iso:country":"BE",
    "sg:address":"Zevekotestraat 16",
    "sg:city":"Evergem",
    "sg:orig_category":"Varkenskwekers",
    "sg:phone":"+32 9 357 34 11",
    "sg:postcode":"9940",
    "sg:province":"Oost-Vlaanderen",
    "wof:name":"Hendrik De Baerdemaeker",
    "wof:placetype":"venue"
},
  "geometry": {"coordinates":[3.671544075,51.1155776978],"type":"Point"}
}