{
  "type": "Feature",
  "properties": {
    "addr:full":"Waterloogalerij 5 Elsene/ixelles Bruxelles-Capitale 1050",
    "addr:housenumber":"5",
    "addr:postcode":"1050",
    "addr:street":"Waterloogalerij",
    "iso:country":"BE",
    "sg:address":"Waterloogalerij 5",
    "sg:city":"Elsene/ixelles",
    "sg:orig_category":"Architecten",
    "sg:phone":"+32 2 346 42 94",
    "sg:postcode":"1050",
    "sg:province":"Bruxelles-Capitale",
    "wof:name":"Muriel Desmedt",
    "wof:placetype":"venue"
},
  "geometry": {"coordinates":[4.3596367836,50.8197021484],"type":"Point"}
}