{
  "type": "Feature",
  "properties": {
    "iso:country":"BE",
    "sg:address":"Rue Saint-martin 6",
    "sg:city":"Welkenraedt",
    "sg:orig_category":"Airconditioning and ventilatie Elektrische installaties voor woningen Loodgieterij, verwarming and s",
    "sg:phone":"+32 87 88 07 61",
    "sg:postcode":"4841",
    "sg:province":"Li\u00e8ge",
    "wof:name":"Henkens Fr\u00c8res",
    "wof:placetype":"venue"
},
  "geometry": {"coordinates":[5.936191082,50.6904678345],"type":"Point"}
}