{
  "type": "Feature",
  "properties": {
    "addr:full":"Columbiastraat 110 Antwerpen Antwerpen 2030",
    "addr:housenumber":"110",
    "addr:postcode":"2030",
    "addr:street":"Columbiastraat",
    "iso:country":"BE",
    "sg:address":"Columbiastraat 110",
    "sg:city":"Antwerpen",
    "sg:orig_category":"Salles de spectacles",
    "sg:phone":"+32 3 542 49 40",
    "sg:postcode":"2030",
    "sg:province":"Antwerpen",
    "wof:name":"Cultureel Centrum",
    "wof:placetype":"venue"
},
  "geometry": {"coordinates":[4.4232559204,51.253112793],"type":"Point"}
}