{
  "type": "Feature",
  "properties": {
    "addr:full":"Chauss\u00c9e Du Roeulx 1322 Mons Hainaut 7021",
    "addr:housenumber":"1322",
    "addr:postcode":"7021",
    "addr:street":"Chausse\u0301E Du Roeulx;Hainaut",
    "iso:country":"BE",
    "sg:address":"Chauss\u00c9e Du Roeulx 1322",
    "sg:city":"Mons",
    "sg:orig_category":"Voedingsspeciaalzaken",
    "sg:phone":"+32 65 87 13 80",
    "sg:postcode":"7021",
    "sg:province":"Hainaut",
    "wof:name":"Jardins De Marie",
    "wof:placetype":"venue"
},
  "geometry": {"coordinates":[4.0571751595,50.4690208435],"type":"Point"}
}