{
  "type": "Feature",
  "properties": {
    "addr:full":"Meerseweg 57b Hoogstraten (meer) Antwerpen 2321",
    "addr:housenumber":"57b",
    "addr:postcode":"2321",
    "addr:street":"Meerseweg;Meer",
    "iso:country":"BE",
    "sg:address":"Meerseweg 57b",
    "sg:city":"Hoogstraten (meer)",
    "sg:classifiers":[
        {
            "category":"Banks & Credit Unions",
            "subcategory":"Financial Services",
            "type":"Services"
        }
    ],
    "sg:phone":"+32 3 315 01 78",
    "sg:postcode":"2321",
    "sg:province":"Antwerpen",
    "sg:tags":[
        "loan",
        "mortgage"
    ],
    "wof:name":"Verboven & Swaenen Bvba",
    "wof:placetype":"venue"
},
  "geometry": {"coordinates":[4.7366099358,51.442325592],"type":"Point"}
}