{
  "type": "Feature",
  "properties": {
    "iso:country":"BE",
    "sg:address":"Dampoortstraat 8-10",
    "sg:city":"Gent",
    "sg:classifiers":[
        {
            "category":"Shopping",
            "subcategory":"Computers & Home Electronics",
            "type":"Retail Goods"
        }
    ],
    "sg:phone":"+32 9 223 50 98",
    "sg:postcode":"9000",
    "sg:province":"Oost-Vlaanderen",
    "sg:tags":[
        "personal",
        "-",
        "processing",
        "data"
    ],
    "wof:name":"Vercruysse Nv",
    "wof:placetype":"venue"
},
  "geometry": {"coordinates":[3.7340888977,51.0565605164],"type":"Point"}
}