{
  "type": "Feature",
  "properties": {
    "addr:full":"Sint-hubertstraat 196 Deinze Oost-Vlaanderen 9800",
    "addr:housenumber":"196",
    "addr:postcode":"9800",
    "iso:country":"BE",
    "sg:address":"Sint-hubertstraat 196",
    "sg:city":"Deinze",
    "sg:orig_category":"Rundveehouders",
    "sg:phone":"+32 9 386 22 33",
    "sg:postcode":"9800",
    "sg:province":"Oost-Vlaanderen",
    "wof:name":"Roger Yde",
    "wof:placetype":"venue"
},
  "geometry": {"coordinates":[3.520334959,50.9663887024],"type":"Point"}
}