{
  "type": "Feature",
  "properties": {
    "addr:full":"Rue Courte De La Station 1 Braine-le-chateau Brabant Wallon 1440",
    "addr:housenumber":"1",
    "addr:postcode":"1440",
    "addr:street":"Rue Courte De La Station;Brabant Wallon",
    "iso:country":"BE",
    "sg:address":"Rue Courte De La Station 1",
    "sg:city":"Braine-le-chateau",
    "sg:orig_category":"Cr\u00e9dits divers",
    "sg:postcode":"1440",
    "sg:province":"Brabant Wallon",
    "wof:name":"Bancontact-mister Cash",
    "wof:placetype":"venue"
},
  "geometry": {"coordinates":[4.2730078697,50.6817893982],"type":"Point"}
}