{
  "type": "Feature",
  "properties": {
    "addr:full":"Rue Godefroid-kurth 59 Arlon Luxembourg 6700",
    "addr:housenumber":"59",
    "addr:postcode":"6700",
    "addr:street":"Rue Godefroid-Kurth",
    "iso:country":"BE",
    "sg:address":"Rue Godefroid-kurth 59",
    "sg:city":"Arlon",
    "sg:orig_category":"Vertalers and tolken",
    "sg:phone":"+32 63 21 81 03",
    "sg:postcode":"6700",
    "sg:province":"Luxembourg",
    "wof:name":"Wagner M. Cbtip/bkvtf",
    "wof:placetype":"venue"
},
  "geometry": {"coordinates":[5.8215670586,49.6848373413],"type":"Point"}
}