{
  "type": "Feature",
  "properties": {
    "iso:country":"BE",
    "sg:address":"Ch De Namur 24-26",
    "sg:city":"Charleroi",
    "sg:classifiers":[
        {
            "category":"Autos & Motor Vehicles",
            "subcategory":"Automobile Sales",
            "type":"Retail Goods"
        }
    ],
    "sg:phone":"+32 71 41 19 27",
    "sg:postcode":"6061",
    "sg:province":"Hainaut",
    "sg:tags":[
        "equipment",
        "motor-cars",
        "transport"
    ],
    "wof:name":"Etablissements Wanet Et Fils Sa",
    "wof:placetype":"venue"
},
  "geometry": {"coordinates":[4.4675598145,50.4221496582],"type":"Point"}
}