{
  "type": "Feature",
  "properties": {
    "iso:country":"BE",
    "sg:address":"Bogaardwegel 1",
    "sg:city":"Ledegem (rollegem Kapelle)",
    "sg:classifiers":[
        {
            "category":"Home & Garden",
            "subcategory":"Carpets & Floor Coverings",
            "type":"Retail Goods"
        }
    ],
    "sg:phone":"+32 56 50 18 03",
    "sg:postcode":"8880",
    "sg:province":"West-Vlaanderen",
    "sg:tags":[
        "-"
    ],
    "wof:name":"Termote P",
    "wof:placetype":"venue"
},
  "geometry": {"coordinates":[3.1460280418,50.8691444397],"type":"Point"}
}