{
  "type": "Feature",
  "properties": {
    "iso:country":"BE",
    "sg:address":"Place Albert Ier 40",
    "sg:city":"Malmedy/malmedy",
    "sg:classifiers":[
        {
            "category":"Professional",
            "type":"Services"
        }
    ],
    "sg:phone":"+32 80 33 04 52",
    "sg:postcode":"4960",
    "sg:province":"Li\u00e8ge",
    "sg:tags":[
        "organisation",
        "de",
        "restaurants",
        "f\u00cates",
        "catering"
    ],
    "wof:name":"H\u00d4tel Albert I",
    "wof:placetype":"venue"
},
  "geometry": {"coordinates":[6.0551772118,50.37657547],"type":"Point"}
}