{
  "type": "Feature",
  "properties": {
    "addr:full":"Boulevard De La Sauveni\u00c8re 77 Li\u00c8ge Li\u00e8ge 4000",
    "addr:housenumber":"77",
    "addr:postcode":"4000",
    "addr:street":"Boulevard De La Sauvenie\u0300Re",
    "iso:country":"BE",
    "sg:address":"Boulevard De La Sauveni\u00c8re 77",
    "sg:city":"Li\u00c8ge",
    "sg:orig_category":"Offices du tourisme",
    "sg:phone":"+32 4 232 65 10",
    "sg:postcode":"4000",
    "sg:province":"Li\u00e8ge",
    "wof:name":"Tourisme De La Province De Li\u00c8ge",
    "wof:placetype":"venue"
},
  "geometry": {"coordinates":[5.5664100647,50.6432952881],"type":"Point"}
}