{
  "type": "Feature",
  "properties": {
    "addr:full":"Sluisstraat 19 Ham Limburg 3945",
    "addr:housenumber":"19",
    "addr:postcode":"3945",
    "addr:street":"Sluisstraat",
    "iso:country":"BE",
    "sg:address":"Sluisstraat 19",
    "sg:city":"Ham",
    "sg:orig_category":"Rundveehouders",
    "sg:phone":"+32 13 66 15 48",
    "sg:postcode":"3945",
    "sg:province":"Limburg",
    "wof:name":"Ferdinand Blarings",
    "wof:placetype":"venue"
},
  "geometry": {"coordinates":[5.1776199341,51.1046104431],"type":"Point"}
}