{
  "type": "Feature",
  "properties": {
    "iso:country":"BE",
    "sg:address":"1 Rue Bergifosse",
    "sg:city":"Boussu",
    "sg:classifiers":[
        {
            "category":"Transit Center",
            "subcategory":"Freight",
            "type":"Transportation"
        }
    ],
    "sg:phone":"+32 65 78 51 73",
    "sg:postcode":"7300",
    "sg:province":"Hainaut",
    "sg:tags":[
        "metallurgy",
        "pipe",
        "metalworking",
        "sheet"
    ],
    "wof:name":"Montages Et Tuyauteries Legros Sa",
    "wof:placetype":"venue"
},
  "geometry": {"coordinates":[3.800645113,50.4324531555],"type":"Point"}
}