{
  "type": "Feature",
  "properties": {
    "addr:full":"Rue Lavaniste Voie 350 Herstal (vottem) Li\u00e8ge 4041",
    "addr:housenumber":"350",
    "addr:postcode":"4041",
    "addr:street":"Rue Lavaniste Voie;Vottem",
    "iso:country":"BE",
    "sg:address":"Rue Lavaniste Voie 350",
    "sg:city":"Herstal (vottem)",
    "sg:classifiers":[
        {
            "category":"Building & Trades",
            "subcategory":"Pest Control",
            "type":"Services"
        }
    ],
    "sg:phone":"+32 4 227 69 28",
    "sg:postcode":"4041",
    "sg:province":"Li\u00e8ge",
    "sg:tags":[
        "machine",
        "vending"
    ],
    "wof:name":"Distrymatic Vending",
    "wof:placetype":"venue"
},
  "geometry": {"coordinates":[5.5914697647,50.6664505005],"type":"Point"}
}