{
  "type": "Feature",
  "properties": {
    "iso:country":"BE",
    "sg:address":"Lange Steenstraat 12",
    "sg:city":"Kortrijk",
    "sg:orig_category":"Dameskledingzaken",
    "sg:phone":"+32 56 20 34 27",
    "sg:postcode":"8500",
    "sg:province":"West-Vlaanderen",
    "wof:name":"Huis Nova Zembla",
    "wof:placetype":"venue"
},
  "geometry": {"coordinates":[3.2678170204,50.8263130188],"type":"Point"}
}