{
  "type": "Feature",
  "properties": {
    "iso:country":"BE",
    "sg:address":"Wayai 36a",
    "sg:city":"Jalhay (sart)",
    "sg:classifiers":[
        {
            "category":"Building & Trades",
            "subcategory":"Construction",
            "type":"Services"
        }
    ],
    "sg:phone":"+32 87 47 53 13",
    "sg:postcode":"4845",
    "sg:province":"Li\u00e8ge",
    "sg:tags":[
        "carpenter"
    ],
    "wof:name":"Michel B",
    "wof:placetype":"venue"
},
  "geometry": {"coordinates":[5.9532232285,50.502456665],"type":"Point"}
}