{
  "type": "Feature",
  "properties": {
    "addr:full":"Grote Markt 49 Lier Antwerpen 2500",
    "addr:housenumber":"49",
    "addr:postcode":"2500",
    "addr:street":"Grote Markt",
    "iso:country":"BE",
    "sg:address":"Grote Markt 49",
    "sg:city":"Lier",
    "sg:classifiers":[
        {
            "category":"Shopping",
            "subcategory":"Clothing, Apparel, & Fashions",
            "type":"Retail Goods"
        }
    ],
    "sg:phone":"+32 3 480 70 99",
    "sg:postcode":"2500",
    "sg:province":"Antwerpen",
    "sg:tags":[
        "lady",
        "clothing",
        "-"
    ],
    "wof:name":"Tess",
    "wof:placetype":"venue"
},
  "geometry": {"coordinates":[4.569475174,51.1315307617],"type":"Point"}
}