{
  "type": "Feature",
  "properties": {
    "addr:full":"Rue Des Chevreuils 23 Dinant Namur 5500",
    "addr:housenumber":"23",
    "addr:postcode":"5500",
    "addr:street":"Rue Des Chevreuils",
    "iso:country":"BE",
    "sg:address":"Rue Des Chevreuils 23",
    "sg:city":"Dinant",
    "sg:classifiers":[
        {
            "category":"Health Services",
            "subcategory":"Doctor",
            "type":"Services"
        }
    ],
    "sg:phone":"+32 82 22 54 22",
    "sg:postcode":"5500",
    "sg:province":"Namur",
    "sg:tags":[
        "medicinephysicians",
        "surgeon"
    ],
    "wof:name":"Damoiseaux Ph",
    "wof:placetype":"venue"
},
  "geometry": {"coordinates":[4.9306578636,50.248550415],"type":"Point"}
}