{
  "type": "Feature",
  "properties": {
    "addr:full":"Gereedstraat 48 Wetteren Oost-Vlaanderen 9230",
    "addr:housenumber":"48",
    "addr:postcode":"9230",
    "addr:street":"Gereedstraat",
    "iso:country":"BE",
    "sg:address":"Gereedstraat 48",
    "sg:city":"Wetteren",
    "sg:classifiers":[
        {
            "category":"Shopping",
            "subcategory":"Pets & Pet Supplies",
            "type":"Retail Goods"
        }
    ],
    "sg:phone":"+32 9 368 16 74",
    "sg:postcode":"9230",
    "sg:province":"Oost-Vlaanderen",
    "sg:tags":[
        "horseriding"
    ],
    "wof:name":"Guillemaere",
    "wof:placetype":"venue"
},
  "geometry": {"coordinates":[3.8814520836,51.0141067505],"type":"Point"}
}