{
  "type": "Feature",
  "properties": {
    "addr:full":"Kreuzstrasse 9 Lontzen Li\u00e8ge 4711",
    "addr:housenumber":"9",
    "addr:postcode":"4711",
    "addr:street":"Kreuzstrasse",
    "iso:country":"BE",
    "sg:address":"Kreuzstrasse 9",
    "sg:city":"Lontzen",
    "sg:orig_category":"Toeristische diensten",
    "sg:phone":"+32 87 65 82 43",
    "sg:postcode":"4711",
    "sg:province":"Li\u00e8ge",
    "wof:name":"Verkehrsverein",
    "wof:placetype":"venue"
},
  "geometry": {"coordinates":[6.047369957,50.6752853394],"type":"Point"}
}