{
  "type": "Feature",
  "properties": {
    "iso:country":"BE",
    "sg:address":"Tiensebaan 16",
    "sg:city":"Bekkevoort",
    "sg:orig_category":"Eleveurs and marchands de porcs",
    "sg:phone":"+32 16 77 98 99",
    "sg:postcode":"3461",
    "sg:province":"Vlaams-Brabant",
    "wof:name":"Frans Torbeyns",
    "wof:placetype":"venue"
},
  "geometry": {"coordinates":[4.9502081871,50.9086532593],"type":"Point"}
}