{
  "type": "Feature",
  "properties": {
    "addr:full":"Steenweg Op Ukkel 99 Beersel Vlaams-Brabant 1650",
    "addr:housenumber":"99",
    "addr:postcode":"1650",
    "addr:street":"Steenweg Op Ukkel",
    "iso:country":"BE",
    "sg:address":"Steenweg Op Ukkel 99",
    "sg:city":"Beersel",
    "sg:orig_category":"Autombile concessionaires",
    "sg:phone":"+32 2 331 02 08",
    "sg:postcode":"1650",
    "sg:province":"Vlaams-Brabant",
    "wof:name":"Andre",
    "wof:placetype":"venue"
},
  "geometry": {"coordinates":[4.313352108,50.7705497742],"type":"Point"}
}