{
  "type": "Feature",
  "properties": {
    "addr:full":"Bouwelse Steenweg 8 Herenthout Antwerpen 2270",
    "addr:housenumber":"8",
    "addr:postcode":"2270",
    "addr:street":"Bouwelse Steenweg",
    "iso:country":"BE",
    "sg:address":"Bouwelse Steenweg 8",
    "sg:city":"Herenthout",
    "sg:orig_category":"Brandweer and civiele bescherming",
    "sg:phone":"+32 14 51 52 57",
    "sg:postcode":"2270",
    "sg:province":"Antwerpen",
    "wof:name":"Brandweerkazerne",
    "wof:placetype":"venue"
},
  "geometry": {"coordinates":[4.7554368973,51.1400871277],"type":"Point"}
}