{
  "type": "Feature",
  "properties": {
    "addr:full":"Hofveld 6 Asse Vlaams-Brabant 1730",
    "addr:housenumber":"6",
    "addr:postcode":"1730",
    "addr:street":"Hofveld",
    "iso:country":"BE",
    "sg:address":"Hofveld 6",
    "sg:city":"Asse",
    "sg:orig_category":"Epiceries",
    "sg:phone":"+32 2 452 54 25",
    "sg:postcode":"1730",
    "sg:province":"Vlaams-Brabant",
    "wof:name":"Gustaaf Denijs",
    "wof:placetype":"venue"
},
  "geometry": {"coordinates":[4.1950101852,50.9093742371],"type":"Point"}
}