{
  "type": "Feature",
  "properties": {
    "addr:full":"Rue De Dampremy 14 Charleroi Hainaut 6000",
    "addr:housenumber":"14",
    "addr:postcode":"6000",
    "addr:street":"Rue De Dampremy;Hainaut",
    "iso:country":"BE",
    "sg:address":"Rue De Dampremy 14",
    "sg:city":"Charleroi",
    "sg:classifiers":[
        {
            "category":"Shopping",
            "subcategory":"Clothing, Apparel, & Fashions",
            "type":"Retail Goods"
        }
    ],
    "sg:phone":"+32 2 240 66 00",
    "sg:postcode":"6000",
    "sg:province":"Hainaut",
    "sg:tags":[
        "-",
        "clothing",
        "child"
    ],
    "wof:name":"Au Furet",
    "wof:placetype":"venue"
},
  "geometry": {"coordinates":[4.4419388771,50.4086990356],"type":"Point"}
}