{
  "type": "Feature",
  "properties": {
    "addr:full":"Avenue Bel Horizon 52 Rixensart (genval) Brabant Wallon 1332",
    "addr:housenumber":"52",
    "addr:postcode":"1332",
    "addr:street":"Avenue Bel Horizon",
    "iso:country":"BE",
    "sg:address":"Avenue Bel Horizon 52",
    "sg:city":"Rixensart (genval)",
    "sg:classifiers":[
        {
            "category":"Real Estate",
            "subcategory":"Architect",
            "type":"Services"
        }
    ],
    "sg:phone":"+32 2 653 12 15",
    "sg:postcode":"1332",
    "sg:province":"Brabant Wallon",
    "wof:name":"Damit R",
    "wof:placetype":"venue"
},
  "geometry": {"coordinates":[4.507806778,50.7287368774],"type":"Point"}
}