{
  "type": "Feature",
  "properties": {
    "iso:country":"BE",
    "sg:address":"Wellenstraat 33",
    "sg:city":"Borgloon",
    "sg:classifiers":[
        {
            "category":"Retail",
            "subcategory":"Laundry & Dry Cleaning",
            "type":"Services"
        }
    ],
    "sg:phone":"+32 12 74 26 21",
    "sg:postcode":"3840",
    "sg:province":"Limburg",
    "sg:tags":[
        "dyer",
        "cleaner"
    ],
    "wof:name":"Super Shop Bud\u00e9",
    "wof:placetype":"venue"
},
  "geometry": {"coordinates":[5.3421330452,50.8038978577],"type":"Point"}
}