{
  "type": "Feature",
  "properties": {
    "iso:country":"BE",
    "sg:address":"Grote Baan 188bd",
    "sg:city":"Houthalen-helchteren",
    "sg:orig_category":"Voertuigen",
    "sg:phone":"+32 11 52 20 62",
    "sg:postcode":"3530",
    "sg:province":"Limburg",
    "wof:name":"Garage Bosmans-vandijck",
    "wof:placetype":"venue"
},
  "geometry": {"coordinates":[5.3785867691,51.0377464294],"type":"Point"}
}