{
  "type": "Feature",
  "properties": {
    "addr:full":"Rue Du Bois Rosine 16 Modave Li\u00e8ge 4577",
    "addr:housenumber":"16",
    "addr:postcode":"4577",
    "addr:street":"Rue Du Bois Rosine",
    "iso:country":"BE",
    "sg:address":"Rue Du Bois Rosine 16",
    "sg:city":"Modave",
    "sg:orig_category":"Aanleg van wegen, sportterreinen and vliegvelden Afbraak- and draineerwerken Gespecialiseerde niet-r",
    "sg:phone":"+32 85 51 01 11",
    "sg:postcode":"4577",
    "sg:province":"Li\u00e8ge",
    "wof:name":"Duch\u00cane",
    "wof:placetype":"venue"
},
  "geometry": {"coordinates":[5.3249659538,50.4911766052],"type":"Point"}
}