{
  "type": "Feature",
  "properties": {
    "iso:country":"BE",
    "sg:address":"Rue Des Charrons 21ba",
    "sg:city":"Helecine",
    "sg:orig_category":"Slagers",
    "sg:phone":"+32 19 65 50 77",
    "sg:postcode":"1357",
    "sg:province":"Brabant Wallon",
    "wof:name":"Gauthier Stordeur",
    "wof:placetype":"venue"
},
  "geometry": {"coordinates":[4.9880671501,50.7569389343],"type":"Point"}
}