{
  "type": "Feature",
  "properties": {
    "iso:country":"BE",
    "sg:address":"Nijverheidsstraat 16",
    "sg:city":"Meulebeke",
    "sg:classifiers":[
        {
            "category":"Professional",
            "subcategory":"Management & Consulting",
            "type":"Services"
        }
    ],
    "sg:phone":"+32 51 48 01 80",
    "sg:postcode":"8760",
    "sg:province":"West-Vlaanderen",
    "sg:tags":[
        "consultant",
        "-",
        "legislation",
        "social"
    ],
    "wof:name":"Sociaal Secretariaat Easypay S.s.e.",
    "wof:placetype":"venue"
},
  "geometry": {"coordinates":[3.2960450649,50.9597511292],"type":"Point"}
}