{
  "type": "Feature",
  "properties": {
    "addr:full":"Rue Basse 31 Frasnes-lez-anvaing Hainaut 7911",
    "addr:housenumber":"31",
    "addr:postcode":"7911",
    "addr:street":"Rue Basse",
    "iso:country":"BE",
    "sg:address":"Rue Basse 31",
    "sg:city":"Frasnes-lez-anvaing",
    "sg:orig_category":"Services pour animaux domestiques",
    "sg:phone":"+32 69 86 61 38",
    "sg:postcode":"7911",
    "sg:province":"Hainaut",
    "wof:name":"Lig.r.belg.protec.oiseaux",
    "wof:placetype":"venue"
},
  "geometry": {"coordinates":[3.6194040775,50.6681556702],"type":"Point"}
}