{
  "type": "Feature",
  "properties": {
    "addr:full":"Leuvensesteenweg 47 Boortmeerbeek Vlaams-Brabant 3191",
    "addr:housenumber":"47",
    "addr:postcode":"3191",
    "addr:street":"Leuvensesteenweg",
    "iso:country":"BE",
    "sg:address":"Leuvensesteenweg 47",
    "sg:city":"Boortmeerbeek",
    "sg:orig_category":"V\u00e9los. Articles de camping and de sport",
    "sg:phone":"+32 15 52 86 46",
    "sg:postcode":"3191",
    "sg:province":"Vlaams-Brabant",
    "wof:name":"Fratelli Sport",
    "wof:placetype":"venue"
},
  "geometry": {"coordinates":[4.5359840393,50.9922676086],"type":"Point"}
}