{
  "type": "Feature",
  "properties": {
    "iso:country":"BE",
    "sg:address":"Rue R. P. Cambier 1b",
    "sg:city":"Flobecq",
    "sg:classifiers":[
        {
            "category":"Food & Beverages",
            "subcategory":"Groceries & Convenience Stores",
            "type":"Retail Goods"
        }
    ],
    "sg:phone":"+32 68 44 78 50",
    "sg:postcode":"7880",
    "sg:province":"Hainaut",
    "sg:tags":[
        "grocer"
    ],
    "wof:name":"Superette De La Gare",
    "wof:placetype":"venue"
},
  "geometry": {"coordinates":[3.7384328842,50.7368049622],"type":"Point"}
}