{
  "type": "Feature",
  "properties": {
    "addr:full":"Bieststr 80 Wevelgem West-Vlaanderen 8560",
    "addr:housenumber":"80",
    "addr:postcode":"8560",
    "addr:street":"Bieststr",
    "iso:country":"BE",
    "sg:address":"Bieststr 80",
    "sg:city":"Wevelgem",
    "sg:classifiers":[
        {
            "category":"Farming",
            "subcategory":"Livestock Farm",
            "type":"Manufacturing & Wholesale Goods"
        }
    ],
    "sg:phone":"+32 56 41 42 05",
    "sg:postcode":"8560",
    "sg:province":"West-Vlaanderen",
    "sg:tags":[
        "agriculture"
    ],
    "wof:name":"Ghekiere Nv",
    "wof:placetype":"venue"
},
  "geometry": {"coordinates":[3.1959540844,50.8197250366],"type":"Point"}
}