{
  "type": "Feature",
  "properties": {
    "iso:country":"BE",
    "sg:address":"Boerenstraat 10",
    "sg:city":"Zelzate",
    "sg:classifiers":[
        {
            "category":"Taxi",
            "type":"Transportation"
        }
    ],
    "sg:phone":"+32 9 342 91 16",
    "sg:postcode":"9060",
    "sg:province":"Oost-Vlaanderen",
    "sg:tags":[
        "taxi's"
    ],
    "wof:name":"Guldemont P",
    "wof:placetype":"venue"
},
  "geometry": {"coordinates":[3.8120379448,51.1967849731],"type":"Point"}
}