{
  "type": "Feature",
  "properties": {
    "iso:country":"BE",
    "sg:address":"Rue De Bruxelles 9",
    "sg:city":"Namur",
    "sg:orig_category":"Kapsalons",
    "sg:phone":"+32 81 22 06 63",
    "sg:postcode":"5000",
    "sg:province":"Namur",
    "wof:name":"Coiffeur Lecocq",
    "wof:placetype":"venue"
},
  "geometry": {"coordinates":[4.8631811142,50.4651985168],"type":"Point"}
}