{
  "type": "Feature",
  "properties": {
    "addr:full":"Rue Paul Pastur 78 Beloeil Hainaut 7972",
    "addr:housenumber":"78",
    "addr:postcode":"7972",
    "addr:street":"Rue Paul Pastur",
    "iso:country":"BE",
    "sg:address":"Rue Paul Pastur 78",
    "sg:city":"Beloeil",
    "sg:orig_category":"Travaux de pl\u00e2trage. Construction de maisons",
    "sg:phone":"+32 69 56 14 74",
    "sg:postcode":"7972",
    "sg:province":"Hainaut",
    "wof:name":"Michele Ricotta",
    "wof:placetype":"venue"
},
  "geometry": {"coordinates":[3.6905369759,50.526058197],"type":"Point"}
}