{
  "type": "Feature",
  "properties": {
    "iso:country":"BE",
    "sg:address":"Oude Steenweg 4",
    "sg:city":"Grobbendonk",
    "sg:orig_category":"Woningbouw",
    "sg:phone":"+32 14 51 78 50",
    "sg:postcode":"2280",
    "sg:province":"Antwerpen",
    "wof:name":"Stuco",
    "wof:placetype":"venue"
},
  "geometry": {"coordinates":[4.7410211563,51.1856002808],"type":"Point"}
}