{
  "type": "Feature",
  "properties": {
    "addr:full":"Chauss\u00c9e De Charleroi 123a Sint-gillis/saint-gilles Bruxelles-Capitale 1060",
    "addr:housenumber":"123a",
    "addr:postcode":"1060",
    "addr:street":"Chausse\u0301E De Charleroi",
    "iso:country":"BE",
    "sg:address":"Chauss\u00c9e De Charleroi 123a",
    "sg:city":"Sint-gillis/saint-gilles",
    "sg:orig_category":"Diverse voedingsmiddelen Gh",
    "sg:phone":"+32 2 533 04 11",
    "sg:postcode":"1060",
    "sg:province":"Bruxelles-Capitale",
    "wof:name":"Skw Biosystems Benelux",
    "wof:placetype":"venue"
},
  "geometry": {"coordinates":[4.355506897,50.8293533325],"type":"Point"}
}