{
  "type": "Feature",
  "properties": {
    "iso:country":"BE",
    "sg:address":"Kruisstraat 8",
    "sg:city":"Hoeselt",
    "sg:orig_category":"Producteurs de fruits",
    "sg:phone":"+32 89 51 44 56",
    "sg:postcode":"3730",
    "sg:province":"Limburg",
    "wof:name":"Roger Buysmans",
    "wof:placetype":"venue"
},
  "geometry": {"coordinates":[5.4746198654,50.8509216309],"type":"Point"}
}