{
  "type": "Feature",
  "properties": {
    "addr:full":"Lage Altaarstraat 1 Antwerpen Antwerpen 2018",
    "addr:housenumber":"1",
    "addr:postcode":"2018",
    "addr:street":"Altaarstraat",
    "iso:country":"BE",
    "sg:address":"Lage Altaarstraat 1",
    "sg:city":"Antwerpen",
    "sg:orig_category":"E-activit\u00e9s. R\u00e9alisation de programmes and logiciels",
    "sg:phone":"+32 3 271 12 22",
    "sg:postcode":"2018",
    "sg:province":"Antwerpen",
    "wof:name":"Netview",
    "wof:placetype":"venue"
},
  "geometry": {"coordinates":[4.4326510429,51.2075462341],"type":"Point"}
}