{
  "type": "Feature",
  "properties": {
    "iso:country":"BE",
    "sg:address":"Anne Frankplein 2",
    "sg:city":"Hasselt",
    "sg:orig_category":"Artsen and specialisten",
    "sg:phone":"+32 11 28 88 88",
    "sg:postcode":"3500",
    "sg:province":"Limburg",
    "wof:name":"P. Cuyvers",
    "wof:placetype":"venue"
},
  "geometry": {"coordinates":[5.3444428444,50.9202156067],"type":"Point"}
}