{
  "type": "Feature",
  "properties": {
    "addr:full":"Rue Des Archers 21 Braine-le-comte Hainaut 7090",
    "addr:housenumber":"21",
    "addr:postcode":"7090",
    "addr:street":"Rue Des Archers",
    "iso:country":"BE",
    "sg:address":"Rue Des Archers 21",
    "sg:city":"Braine-le-comte",
    "sg:orig_category":"Artsen and specialisten",
    "sg:phone":"+32 67 55 68 59",
    "sg:postcode":"7090",
    "sg:province":"Hainaut",
    "wof:name":"Th\u00c9r\u00c8se Sonck",
    "wof:placetype":"venue"
},
  "geometry": {"coordinates":[4.1860980988,50.6003417969],"type":"Point"}
}