{
  "type": "Feature",
  "properties": {
    "iso:country":"BE",
    "sg:address":"Place Palais-de-justice 0",
    "sg:city":"Neufchateau",
    "sg:orig_category":"Boucheries",
    "sg:phone":"+32 61 27 92 13",
    "sg:postcode":"6840",
    "sg:province":"Luxembourg",
    "wof:name":"J.l. Conrard",
    "wof:placetype":"venue"
},
  "geometry": {"coordinates":[5.4352059364,49.8415489197],"type":"Point"}
}