{
  "type": "Feature",
  "properties": {
    "iso:country":"BE",
    "sg:address":"Vijfseweg 130",
    "sg:city":"Waregem",
    "sg:orig_category":"Banques and organismes de cr\u00e9dit. Assurances",
    "sg:phone":"+32 56 60 33 74",
    "sg:postcode":"8790",
    "sg:province":"West-Vlaanderen",
    "wof:name":"Mercator Bank",
    "wof:placetype":"venue"
},
  "geometry": {"coordinates":[3.4199750423,50.8979187012],"type":"Point"}
}