{
  "type": "Feature",
  "properties": {
    "addr:full":"Stationsstraat 10ba Sint-truiden Limburg 3800",
    "addr:housenumber":"10ba",
    "addr:postcode":"3800",
    "addr:street":"Stationsstraat",
    "iso:country":"BE",
    "sg:address":"Stationsstraat 10ba",
    "sg:city":"Sint-truiden",
    "sg:orig_category":"Avocats and conseillers juridiques",
    "sg:phone":"+32 11 70 75 70",
    "sg:postcode":"3800",
    "sg:province":"Limburg",
    "wof:name":"E. Delvaux",
    "wof:placetype":"venue"
},
  "geometry": {"coordinates":[5.1786298752,50.816204071],"type":"Point"}
}