{
  "type": "Feature",
  "properties": {
    "addr:full":"Driesstraat 6 Oosterzele Oost-Vlaanderen 9860",
    "addr:housenumber":"6",
    "addr:postcode":"9860",
    "addr:street":"Driesstraat;Oost-Vlaanderen",
    "iso:country":"BE",
    "sg:address":"Driesstraat 6",
    "sg:city":"Oosterzele",
    "sg:orig_category":"HUISBRANDOLIE Tuinbenodigdheden",
    "sg:phone":"+32 9 362 50 48",
    "sg:postcode":"9860",
    "sg:province":"Oost-Vlaanderen",
    "wof:name":"H. Baele's Grondstoffen",
    "wof:placetype":"venue"
},
  "geometry": {"coordinates":[3.7841689587,50.9227180481],"type":"Point"}
}