{
  "type": "Feature",
  "properties": {
    "iso:country":"BE",
    "sg:address":"Rue Docteur Parent 185",
    "sg:city":"Andenne",
    "sg:orig_category":"Fleurs and plantes",
    "sg:phone":"+32 81 58 88 37",
    "sg:postcode":"5300",
    "sg:province":"Namur",
    "wof:name":"Fleurs Timsonet Josette",
    "wof:placetype":"venue"
},
  "geometry": {"coordinates":[5.031126976,50.4912757874],"type":"Point"}
}