{
  "type": "Feature",
  "properties": {
    "addr:full":"Rue Roture 13 Liege Li\u00e8ge 4020",
    "addr:housenumber":"13",
    "addr:postcode":"4020",
    "addr:street":"Rue Roture",
    "iso:country":"BE",
    "sg:address":"Rue Roture 13",
    "sg:city":"Liege",
    "sg:classifiers":[
        {
            "category":"Restaurant",
            "type":"Food & Drink"
        }
    ],
    "sg:phone":"+32 4 344 04 71",
    "sg:postcode":"4020",
    "sg:province":"Li\u00e8ge",
    "wof:name":"L'envers Du Cirque",
    "wof:placetype":"venue"
},
  "geometry": {"coordinates":[5.5828299522,50.6401596069],"type":"Point"}
}