{
  "type": "Feature",
  "properties": {
    "iso:country":"BE",
    "sg:address":"Schaatsmeers 6",
    "sg:city":"Gent",
    "sg:orig_category":"M\u00e9decins and sp\u00e9cialistes",
    "sg:phone":"+32 9 237 00 95",
    "sg:postcode":"9030",
    "sg:province":"Oost-Vlaanderen",
    "wof:name":"Andr\u00c9 De Vos",
    "wof:placetype":"venue"
},
  "geometry": {"coordinates":[3.6784989834,51.0694084167],"type":"Point"}
}