{
  "type": "Feature",
  "properties": {
    "iso:country":"BE",
    "sg:address":"Langestraat 8",
    "sg:city":"Maarkedal (schorisse)",
    "sg:classifiers":[
        {
            "category":"Shopping",
            "subcategory":"Florist",
            "type":"Retail Goods"
        }
    ],
    "sg:phone":"+32 55 45 61 19",
    "sg:postcode":"9688",
    "sg:province":"Oost-Vlaanderen",
    "wof:name":"T'bloemenhuisje",
    "wof:placetype":"venue"
},
  "geometry": {"coordinates":[3.6743879318,50.7967147827],"type":"Point"}
}