{
  "type": "Feature",
  "properties": {
    "iso:country":"BE",
    "sg:address":"Universiteitslaan 9",
    "sg:city":"Hasselt",
    "sg:orig_category":"Boekhouders",
    "sg:phone":"+32 11 24 02 66",
    "sg:postcode":"3500",
    "sg:province":"Limburg",
    "wof:name":"Alice Steegmans",
    "wof:placetype":"venue"
},
  "geometry": {"coordinates":[5.3700032234,50.9305953979],"type":"Point"}
}