{
  "type": "Feature",
  "properties": {
    "addr:full":"Gontrode Heirweg 126 Melle Oost-Vlaanderen 9090",
    "addr:housenumber":"126",
    "addr:postcode":"9090",
    "addr:street":"Gontrode Heirweg",
    "iso:country":"BE",
    "sg:address":"Gontrode Heirweg 126",
    "sg:city":"Melle",
    "sg:orig_category":"Leisure articles",
    "sg:phone":"+32 9 231 43 65",
    "sg:postcode":"9090",
    "sg:province":"Oost-Vlaanderen",
    "wof:name":"Duimelotje",
    "wof:placetype":"venue"
},
  "geometry": {"coordinates":[3.7695689201,51.0120544434],"type":"Point"}
}