{
  "type": "Feature",
  "properties": {
    "addr:full":"Lekestraat 67 Koekelare West-Vlaanderen 8680",
    "addr:housenumber":"67",
    "addr:postcode":"8680",
    "addr:street":"Lekestraat",
    "iso:country":"BE",
    "sg:address":"Lekestraat 67",
    "sg:city":"Koekelare",
    "sg:classifiers":[
        {
            "category":"Building & Trades",
            "subcategory":"Electrical",
            "type":"Services"
        }
    ],
    "sg:phone":"+32 51 58 89 15",
    "sg:postcode":"8680",
    "sg:province":"West-Vlaanderen",
    "sg:tags":[
        "heating"
    ],
    "wof:name":"Vantyghem-delaeter Bvba",
    "wof:placetype":"venue"
},
  "geometry": {"coordinates":[2.9394159317,51.0873184204],"type":"Point"}
}