{
  "type": "Feature",
  "properties": {
    "addr:full":"Gentsesteenweg 149 Aalst Oost-Vlaanderen 9300",
    "addr:housenumber":"149",
    "addr:postcode":"9300",
    "addr:street":"Gentsesteenweg",
    "iso:country":"BE",
    "sg:address":"Gentsesteenweg 149",
    "sg:city":"Aalst",
    "sg:classifiers":[
        {
            "category":"Professional",
            "subcategory":"Detective & Security Services",
            "type":"Services"
        }
    ],
    "sg:phone":"+32 53 77 21 62",
    "sg:postcode":"9300",
    "sg:province":"Oost-Vlaanderen",
    "sg:tags":[
        "installation",
        "alarm",
        "-",
        "system"
    ],
    "wof:name":"Van Der Biest Gino Alarmsystemen",
    "wof:placetype":"venue"
},
  "geometry": {"coordinates":[4.0197029114,50.9392623901],"type":"Point"}
}