{
  "type": "Feature",
  "properties": {
    "addr:full":"Globelaan 20 Vorst/forest Bruxelles-Capitale 1190",
    "addr:housenumber":"20",
    "addr:postcode":"1190",
    "addr:street":"Globelaan;/ Forest",
    "iso:country":"BE",
    "sg:address":"Globelaan 20",
    "sg:city":"Vorst/forest",
    "sg:orig_category":"Beautyfarms, relaxatie and lichamelijk welzijn Schoonheidssalons",
    "sg:phone":"+32 2 346 40 08",
    "sg:postcode":"1190",
    "sg:province":"Bruxelles-Capitale",
    "wof:name":"Ana\u00cfs",
    "wof:placetype":"venue"
},
  "geometry": {"coordinates":[4.3252778053,50.8094825745],"type":"Point"}
}