{
  "type": "Feature",
  "properties": {
    "iso:country":"BE",
    "sg:address":"J. Van Arteveldelaan 20",
    "sg:city":"Kortrijk",
    "sg:orig_category":"Diverse bedrijfsbeheeradviesbureaus",
    "sg:phone":"+32 56 20 14 12",
    "sg:postcode":"8500",
    "sg:province":"West-Vlaanderen",
    "wof:name":"Glamacon",
    "wof:placetype":"venue"
},
  "geometry": {"coordinates":[3.2768769264,50.8295211792],"type":"Point"}
}