{
  "type": "Feature",
  "properties": {
    "addr:full":"Zeelaan 169 De Panne West-Vlaanderen 8660",
    "addr:housenumber":"169",
    "addr:postcode":"8660",
    "addr:street":"Zeelaan",
    "iso:country":"BE",
    "sg:address":"Zeelaan 169",
    "sg:city":"De Panne",
    "sg:classifiers":[
        {
            "category":"Bars & Pubs",
            "type":"Food & Drink"
        }
    ],
    "sg:phone":"+32 58 41 52 47",
    "sg:postcode":"8660",
    "sg:province":"West-Vlaanderen",
    "wof:name":"Robinson (brasserie) F.v.",
    "wof:placetype":"venue"
},
  "geometry": {"coordinates":[2.5805599689,51.0997200012],"type":"Point"}
}