{
  "type": "Feature",
  "properties": {
    "addr:full":"Place De La Patrie 48 Brussel/bruxelles Bruxelles-Capitale 1030",
    "addr:housenumber":"48",
    "addr:postcode":"1030",
    "addr:street":"Place De La Patrie;/",
    "iso:country":"BE",
    "sg:address":"Place De La Patrie 48",
    "sg:city":"Brussel/bruxelles",
    "sg:orig_category":"Centres de relaxation and bien-\u00eatre. Instituts de beaut\u00e9",
    "sg:phone":"+32 2 215 68 73",
    "sg:postcode":"1030",
    "sg:province":"Bruxelles-Capitale",
    "wof:name":"Ghislena Delaet",
    "wof:placetype":"venue"
},
  "geometry": {"coordinates":[4.3919849396,50.8564109802],"type":"Point"}
}