{
  "type": "Feature",
  "properties": {
    "iso:country":"BE",
    "sg:address":"Weg Naar Zwartberg 63 Box 2",
    "sg:city":"Opglabbeek",
    "sg:classifiers":[
        {
            "category":"Cafe",
            "type":"Food & Drink"
        }
    ],
    "sg:phone":"+32 89 81 24 12",
    "sg:postcode":"3660",
    "sg:province":"Limburg",
    "sg:tags":[
        "snack-bars"
    ],
    "wof:name":"Pariguette",
    "wof:placetype":"venue"
},
  "geometry": {"coordinates":[5.5771489143,51.041847229],"type":"Point"}
}