{
  "type": "Feature",
  "properties": {
    "addr:full":"Kerkstraat 74 Sint-lievens-houtem (letterhoutem) Oost-Vlaanderen 9521",
    "addr:housenumber":"74",
    "addr:postcode":"9521",
    "addr:street":"Kerkstraat",
    "iso:country":"BE",
    "sg:address":"Kerkstraat 74",
    "sg:city":"Sint-lievens-houtem (letterhoutem)",
    "sg:classifiers":[
        {
            "category":"Retail",
            "subcategory":"Animal Services",
            "type":"Services"
        }
    ],
    "sg:phone":"+32 53 62 45 71",
    "sg:postcode":"9521",
    "sg:province":"Oost-Vlaanderen",
    "sg:tags":[
        "training",
        "dog"
    ],
    "wof:name":"Galajdova 2",
    "wof:placetype":"venue"
},
  "geometry": {"coordinates":[3.8786039352,50.9314117432],"type":"Point"}
}