{
  "type": "Feature",
  "properties": {
    "iso:country":"BE",
    "sg:address":"Pontstraat 42",
    "sg:city":"Kluisbergen (berchem)",
    "sg:classifiers":[
        {
            "category":"Wholesale",
            "subcategory":"Poultry",
            "type":"Manufacturing & Wholesale Goods"
        }
    ],
    "sg:phone":"+32 55 38 80 43",
    "sg:postcode":"9690",
    "sg:province":"Oost-Vlaanderen",
    "sg:tags":[
        "whol",
        "-",
        "egg"
    ],
    "wof:name":"De Jaegher J",
    "wof:placetype":"venue"
},
  "geometry": {"coordinates":[3.5201768875,50.7941856384],"type":"Point"}
}