{
  "type": "Feature",
  "properties": {
    "addr:full":"Place Emile De Lalieux 47 Nivelles Brabant Wallon 1400",
    "addr:housenumber":"47",
    "addr:postcode":"1400",
    "addr:street":"Place Emile De Lalieux",
    "iso:country":"BE",
    "sg:address":"Place Emile De Lalieux 47",
    "sg:city":"Nivelles",
    "sg:classifiers":[
        {
            "category":"Retail",
            "subcategory":"Laundry & Dry Cleaning",
            "type":"Services"
        }
    ],
    "sg:phone":"+32 67 21 43 23",
    "sg:postcode":"1400",
    "sg:province":"Brabant Wallon",
    "wof:name":"Aclot Clean Sa",
    "wof:placetype":"venue"
},
  "geometry": {"coordinates":[4.3289189339,50.5978965759],"type":"Point"}
}