{
  "type": "Feature",
  "properties": {
    "iso:country":"BE",
    "sg:address":"Zoete Moederstraat 17",
    "sg:city":"Kruibeke (rupelmonde)",
    "sg:classifiers":[
        {
            "category":"Manufacturing",
            "subcategory":"Wood Products",
            "type":"Manufacturing & Wholesale Goods"
        }
    ],
    "sg:phone":"+32 3 774 45 27",
    "sg:postcode":"9150",
    "sg:province":"Oost-Vlaanderen",
    "sg:tags":[
        "preservation"
    ],
    "wof:name":"Batens Erik Bvba",
    "wof:placetype":"venue"
},
  "geometry": {"coordinates":[4.2928528786,51.1294822693],"type":"Point"}
}