{
  "type": "Feature",
  "properties": {
    "iso:country":"BE",
    "sg:address":"Koning Leopold I-straat 20",
    "sg:city":"Leuven (groot)",
    "sg:orig_category":"Advocaten and juridische adviseurs",
    "sg:phone":"+32 16 23 62 32",
    "sg:postcode":"3000",
    "sg:province":"Vlaams-Brabant",
    "wof:name":"Werner Piessens",
    "wof:placetype":"venue"
},
  "geometry": {"coordinates":[4.7086949348,50.879119873],"type":"Point"}
}