{
  "type": "Feature",
  "properties": {
    "iso:country":"BE",
    "sg:address":"Rue Mabiets 22",
    "sg:city":"Villers-le-bouillet",
    "sg:classifiers":[
        {
            "category":"Travel",
            "subcategory":"Travel Agent",
            "type":"Entertainment"
        }
    ],
    "sg:phone":"+32 85 21 73 26",
    "sg:postcode":"4530",
    "sg:province":"Li\u00e8ge",
    "sg:tags":[
        "agency"
    ],
    "wof:name":"Pierrot Voyages",
    "wof:placetype":"venue"
},
  "geometry": {"coordinates":[5.2597851753,50.5597686768],"type":"Point"}
}