{
  "type": "Feature",
  "properties": {
    "iso:country":"BE",
    "sg:address":"Ave.des Francais 7",
    "sg:city":"Tamines",
    "sg:orig_category":"Motorfietsen",
    "sg:phone":"+32 71 76 04 77",
    "sg:postcode":"5060",
    "sg:province":"Namur",
    "wof:name":"Setmarie",
    "wof:placetype":"venue"
},
  "geometry": {"coordinates":[4.6149258614,50.4296684265],"type":"Point"}
}