{
  "type": "Feature",
  "properties": {
    "iso:country":"BE",
    "sg:address":"Centrum Zuid 1054",
    "sg:city":"Houthalen-helchteren",
    "sg:orig_category":"Huishoudapparaten, televisies and radio's Verhuur televisie- and audiovisuele apparatuur Verlichting",
    "sg:phone":"+32 11 60 91 92",
    "sg:postcode":"3530",
    "sg:province":"Limburg",
    "wof:name":"Flashlight",
    "wof:placetype":"venue"
},
  "geometry": {"coordinates":[5.3617529869,51.0223579407],"type":"Point"}
}