{
  "type": "Feature",
  "properties": {
    "addr:full":"Rue Du Moulin 9 Estinnes Hainaut 7120",
    "addr:housenumber":"9",
    "addr:postcode":"7120",
    "addr:street":"Rue Du Moulin",
    "iso:country":"BE",
    "sg:address":"Rue Du Moulin 9",
    "sg:city":"Estinnes",
    "sg:orig_category":"Kapsalons",
    "sg:phone":"+32 64 33 38 82",
    "sg:postcode":"7120",
    "sg:province":"Hainaut",
    "wof:name":"Coiffure Christiane",
    "wof:placetype":"venue"
},
  "geometry": {"coordinates":[4.0983309746,50.3877944946],"type":"Point"}
}