{
  "type": "Feature",
  "properties": {
    "addr:full":"Elyzeese Veldenstraat 87 Elsene/ixelles Bruxelles-Capitale 1050",
    "addr:housenumber":"87",
    "addr:postcode":"1050",
    "addr:street":"Elyzeese Veldenstraat",
    "iso:country":"BE",
    "sg:address":"Elyzeese Veldenstraat 87",
    "sg:city":"Elsene/ixelles",
    "sg:orig_category":"Etalage- and showroomontwerpers",
    "sg:phone":"+32 2 647 97 49",
    "sg:postcode":"1050",
    "sg:province":"Bruxelles-Capitale",
    "wof:name":"Les Comptoirs De L'image",
    "wof:placetype":"venue"
},
  "geometry": {"coordinates":[4.369161129,50.8284873962],"type":"Point"}
}