{
  "type": "Feature",
  "properties": {
    "iso:country":"BE",
    "sg:address":"Duinkerkestraat 17",
    "sg:city":"Veurne",
    "sg:classifiers":[
        {
            "category":"Professional",
            "subcategory":"Management & Consulting",
            "type":"Services"
        }
    ],
    "sg:phone":"+32 58 31 10 70",
    "sg:postcode":"8630",
    "sg:province":"West-Vlaanderen",
    "sg:tags":[
        "consultant",
        "-",
        "legislation",
        "social"
    ],
    "wof:name":"Admb",
    "wof:placetype":"venue"
},
  "geometry": {"coordinates":[2.6606380939,51.0709648132],"type":"Point"}
}