{
  "type": "Feature",
  "properties": {
    "addr:full":"Patersstraat 80 Turnhout Antwerpen 2300",
    "addr:housenumber":"80",
    "addr:postcode":"2300",
    "addr:street":"Patersstraat",
    "iso:country":"BE",
    "sg:address":"Patersstraat 80",
    "sg:city":"Turnhout",
    "sg:classifiers":[
        {
            "category":"Home & Garden",
            "subcategory":"Home Furnishings",
            "type":"Retail Goods"
        }
    ],
    "sg:phone":"+32 14 42 24 57",
    "sg:postcode":"2300",
    "sg:province":"Antwerpen",
    "sg:tags":[
        "interior",
        "decoration"
    ],
    "wof:name":"Woondekor Bvba",
    "wof:placetype":"venue"
},
  "geometry": {"coordinates":[4.9496731758,51.3264122009],"type":"Point"}
}