{
  "type": "Feature",
  "properties": {
    "iso:country":"BE",
    "sg:address":"Kloosterstraat 6",
    "sg:city":"Antwerpen (ekeren)",
    "sg:classifiers":[
        {
            "category":"Shopping",
            "subcategory":"Shoes",
            "type":"Retail Goods"
        }
    ],
    "sg:phone":"+32 3 542 62 96",
    "sg:postcode":"2180",
    "sg:province":"Antwerpen",
    "sg:tags":[
        "slipper",
        "-"
    ],
    "wof:name":"Heirman N",
    "wof:placetype":"venue"
},
  "geometry": {"coordinates":[4.3956851959,51.217414856],"type":"Point"}
}