{
  "type": "Feature",
  "properties": {
    "iso:country":"BE",
    "sg:address":"Dr\u00e8ve Richelle 265",
    "sg:city":"Waterloo",
    "sg:classifiers":[
        {
            "category":"Personal",
            "subcategory":"Beauty Salon",
            "type":"Services"
        }
    ],
    "sg:phone":"+32 2 354 33 50",
    "sg:postcode":"1410",
    "sg:province":"Brabant Wallon",
    "wof:name":"Nail Stylist",
    "wof:placetype":"venue"
},
  "geometry": {"coordinates":[4.4244627953,50.7007827759],"type":"Point"}
}