{
  "type": "Feature",
  "properties": {
    "iso:country":"BE",
    "sg:address":"Dr\u00c8ve Des Weig\u00c9lias 56",
    "sg:city":"Watermaal-bosvoorde/watermael-boitsfort",
    "sg:orig_category":"Rev\u00eatements pour sols and murs. Peinture",
    "sg:phone":"+32 2 673 14 82",
    "sg:postcode":"1170",
    "sg:province":"Bruxelles-Capitale",
    "wof:name":"Fe. Hermand Olivier",
    "wof:placetype":"venue"
},
  "geometry": {"coordinates":[4.3989601135,50.8084907532],"type":"Point"}
}