{
  "type": "Feature",
  "properties": {
    "iso:country":"BE",
    "sg:address":"Bergezijpestraat 8",
    "sg:city":"Kampenhout",
    "sg:orig_category":"Groententeelt",
    "sg:phone":"+32 16 65 04 73",
    "sg:postcode":"1910",
    "sg:province":"Vlaams-Brabant",
    "wof:name":"Leon Holsters",
    "wof:placetype":"venue"
},
  "geometry": {"coordinates":[4.5235657692,50.9612808228],"type":"Point"}
}