{
  "type": "Feature",
  "properties": {
    "addr:full":"Paddestraat 86 Zottegem Oost-Vlaanderen 9620",
    "addr:housenumber":"86",
    "addr:postcode":"9620",
    "addr:street":"Paddestraat",
    "iso:country":"BE",
    "sg:address":"Paddestraat 86",
    "sg:city":"Zottegem",
    "sg:orig_category":"Kinderopvang",
    "sg:phone":"+32 9 360 24 45",
    "sg:postcode":"9620",
    "sg:province":"Oost-Vlaanderen",
    "wof:name":"Kribbe 't Kabouterke",
    "wof:placetype":"venue"
},
  "geometry": {"coordinates":[3.7705368996,50.8796081543],"type":"Point"}
}