{
  "type": "Feature",
  "properties": {
    "addr:full":"Rue Des Iles 45 Florenville Luxembourg 6821",
    "addr:housenumber":"45",
    "addr:postcode":"6821",
    "addr:street":"Rue Des Iles",
    "iso:country":"BE",
    "sg:address":"Rue Des Iles 45",
    "sg:city":"Florenville",
    "sg:orig_category":"Brood, gebak and snoepgoed",
    "sg:phone":"+32 61 31 55 27",
    "sg:postcode":"6821",
    "sg:province":"Luxembourg",
    "wof:name":"Pascal Maitrejean",
    "wof:placetype":"venue"
},
  "geometry": {"coordinates":[5.3211989403,49.7118110657],"type":"Point"}
}