{
  "type": "Feature",
  "properties": {
    "iso:country":"BE",
    "sg:address":"Rue Pont D'ile 48",
    "sg:city":"Liege",
    "sg:orig_category":"V\u00eatements",
    "sg:phone":"+32 4 222 12 19",
    "sg:postcode":"4000",
    "sg:province":"Li\u00e8ge",
    "wof:name":"Jeans House",
    "wof:placetype":"venue"
},
  "geometry": {"coordinates":[5.5708928108,50.6423988342],"type":"Point"}
}