{
  "type": "Feature",
  "properties": {
    "addr:full":"Rue Andr\u00e9 Ruwet 8 Bl\u00e9gny (trembleur) Li\u00e8ge 4670",
    "addr:housenumber":"8",
    "addr:postcode":"4670",
    "addr:street":"Rue Andre\u0301 Ruwet;Trembleur",
    "iso:country":"BE",
    "sg:address":"Rue Andr\u00e9 Ruwet 8",
    "sg:city":"Bl\u00e9gny (trembleur)",
    "sg:classifiers":[
        {
            "category":"Education",
            "subcategory":"Special Training",
            "type":"Public Place"
        }
    ],
    "sg:phone":"+32 4 387 70 91",
    "sg:postcode":"4670",
    "sg:province":"Li\u00e8ge",
    "sg:tags":[
        "-",
        "processing",
        "data"
    ],
    "wof:name":"Winpc-piret Sonia",
    "wof:placetype":"venue"
},
  "geometry": {"coordinates":[5.7205262184,50.6730041504],"type":"Point"}
}