{
  "type": "Feature",
  "properties": {
    "iso:country":"BE",
    "sg:address":"Chauss\u00c9e De Neerstalle 471",
    "sg:city":"Ukkel/uccle",
    "sg:orig_category":"Elektrische and elektronische apparatuur Gh",
    "sg:phone":"+32 2 332 17 62",
    "sg:postcode":"1180",
    "sg:province":"Bruxelles-Capitale",
    "wof:name":"M.d.i.",
    "wof:placetype":"venue"
},
  "geometry": {"coordinates":[4.3201208115,50.7973976135],"type":"Point"}
}