{
  "type": "Feature",
  "properties": {
    "addr:full":"Tervuursesteenweg 122 Mechelen Antwerpen 2800",
    "addr:housenumber":"122",
    "addr:postcode":"2800",
    "addr:street":"Tervuursesteenweg",
    "iso:country":"BE",
    "sg:address":"Tervuursesteenweg 122",
    "sg:city":"Mechelen",
    "sg:orig_category":"Apotheken",
    "sg:phone":"+32 15 41 23 44",
    "sg:postcode":"2800",
    "sg:province":"Antwerpen",
    "wof:name":"Apotheek De Volksmacht",
    "wof:placetype":"venue"
},
  "geometry": {"coordinates":[4.48412323,51.0103416443],"type":"Point"}
}