{
  "type": "Feature",
  "properties": {
    "addr:full":"Kapellestraat 101 Oostende West-Vlaanderen 8400",
    "addr:housenumber":"101",
    "addr:postcode":"8400",
    "addr:street":"Kapellestraat",
    "iso:country":"BE",
    "sg:address":"Kapellestraat 101",
    "sg:city":"Oostende",
    "sg:orig_category":"V\u00eatements, chaussures and accessoires Gr",
    "sg:phone":"+32 59 70 84 04",
    "sg:postcode":"8400",
    "sg:province":"West-Vlaanderen",
    "wof:name":"Eider",
    "wof:placetype":"venue"
},
  "geometry": {"coordinates":[2.9204139709,51.2282791138],"type":"Point"}
}