{
  "type": "Feature",
  "properties": {
    "iso:country":"BE",
    "sg:address":"Rue Docteur-jeanty 7",
    "sg:city":"Virton",
    "sg:classifiers":[
        {
            "category":"Fast Food",
            "type":"Food & Drink"
        }
    ],
    "sg:phone":"+32 63 57 71 52",
    "sg:postcode":"6760",
    "sg:province":"Luxembourg",
    "sg:tags":[
        "meeneem",
        "restaurant"
    ],
    "wof:name":"Le Chalet",
    "wof:placetype":"venue"
},
  "geometry": {"coordinates":[5.530974865,49.5674247742],"type":"Point"}
}