{
  "type": "Feature",
  "properties": {
    "addr:full":"Husseveldestraat 78 Laarne Oost-Vlaanderen 9270",
    "addr:housenumber":"78",
    "addr:postcode":"9270",
    "addr:street":"Husseveldestraat",
    "iso:country":"BE",
    "sg:address":"Husseveldestraat 78",
    "sg:city":"Laarne",
    "sg:orig_category":"Rundveehouders Varkenskwekers",
    "sg:phone":"+32 9 367 53 25",
    "sg:postcode":"9270",
    "sg:province":"Oost-Vlaanderen",
    "wof:name":"Gerard Fiers",
    "wof:placetype":"venue"
},
  "geometry": {"coordinates":[3.9120969772,51.0693283081],"type":"Point"}
}