{
  "type": "Feature",
  "properties": {
    "addr:full":"Edgard Tinelstraat 29 Sint-niklaas Oost-Vlaanderen 9112",
    "addr:housenumber":"29",
    "addr:postcode":"9112",
    "addr:street":"Edgard Tinelstraat",
    "iso:country":"BE",
    "sg:address":"Edgard Tinelstraat 29",
    "sg:city":"Sint-niklaas",
    "sg:orig_category":"Enseignement maternel and primaire",
    "sg:phone":"+32 3 772 50 00",
    "sg:postcode":"9112",
    "sg:province":"Oost-Vlaanderen",
    "wof:name":"Vrije Lagere School",
    "wof:placetype":"venue"
},
  "geometry": {"coordinates":[4.0414199829,51.1588058472],"type":"Point"}
}