{
  "type": "Feature",
  "properties": {
    "iso:country":"BE",
    "sg:address":"Koolstraat 60",
    "sg:city":"Zonhoven",
    "sg:classifiers":[
        {
            "category":"Building & Trades",
            "subcategory":"Construction",
            "type":"Services"
        }
    ],
    "sg:phone":"+32 477 85 01 25",
    "sg:postcode":"3520",
    "sg:province":"Limburg",
    "sg:tags":[
        "stucco",
        "contractor"
    ],
    "wof:name":"Daemen S",
    "wof:placetype":"venue"
},
  "geometry": {"coordinates":[5.3785657883,50.9800720215],"type":"Point"}
}