{
  "type": "Feature",
  "properties": {
    "iso:country":"BE",
    "sg:address":"Place Albert Ier 24",
    "sg:city":"Malmedy/malmedy",
    "sg:orig_category":"Epiceries",
    "sg:phone":"+32 80 77 03 08",
    "sg:postcode":"4960",
    "sg:province":"Li\u00e8ge",
    "wof:name":"Au Panier Des Fagnes",
    "wof:placetype":"venue"
},
  "geometry": {"coordinates":[6.0551772118,50.37657547],"type":"Point"}
}