{
  "type": "Feature",
  "properties": {
    "addr:full":"L. Carr\u00c9straat 5 Heist-op-den-berg Antwerpen 2220",
    "addr:housenumber":"5",
    "addr:postcode":"2220",
    "addr:street":"L. Carre\u0301Straat",
    "iso:country":"BE",
    "sg:address":"L. Carr\u00c9straat 5",
    "sg:city":"Heist-op-den-berg",
    "sg:orig_category":"Verhuur bouwmachines",
    "sg:phone":"+32 15 24 46 66",
    "sg:postcode":"2220",
    "sg:province":"Antwerpen",
    "wof:name":"Carre",
    "wof:placetype":"venue"
},
  "geometry": {"coordinates":[4.7288827896,51.0845489502],"type":"Point"}
}