{
  "type": "Feature",
  "properties": {
    "addr:full":"Clos Des Chapeliers 6 Bassenge (roclenge-sur-geer) Li\u00e8ge 4690",
    "addr:housenumber":"6",
    "addr:postcode":"4690",
    "addr:street":"Clos Des Chapeliers;Roclenge-Sur-Geer",
    "iso:country":"BE",
    "sg:address":"Clos Des Chapeliers 6",
    "sg:city":"Bassenge (roclenge-sur-geer)",
    "sg:classifiers":[
        {
            "category":"Building & Trades",
            "subcategory":"Pest Control",
            "type":"Services"
        }
    ],
    "sg:phone":"+32 4 286 24 75",
    "sg:postcode":"4690",
    "sg:province":"Li\u00e8ge",
    "sg:tags":[
        "machine",
        "vending"
    ],
    "wof:name":"Vandenbosch",
    "wof:placetype":"venue"
},
  "geometry": {"coordinates":[5.5909748077,50.7581939697],"type":"Point"}
}