{
  "type": "Feature",
  "properties": {
    "addr:full":"Stationsstraat 96 Aalter Oost-Vlaanderen 9880",
    "addr:housenumber":"96",
    "addr:postcode":"9880",
    "addr:street":"Stationsstraat",
    "iso:country":"BE",
    "sg:address":"Stationsstraat 96",
    "sg:city":"Aalter",
    "sg:classifiers":[
        {
            "category":"Shopping",
            "subcategory":"Jewelry",
            "type":"Retail Goods"
        }
    ],
    "sg:phone":"+32 9 325 07 95",
    "sg:postcode":"9880",
    "sg:province":"Oost-Vlaanderen",
    "sg:tags":[
        "-",
        "imitation"
    ],
    "wof:name":"Glamour",
    "wof:placetype":"venue"
},
  "geometry": {"coordinates":[3.4498150349,51.0920066833],"type":"Point"}
}