{
  "type": "Feature",
  "properties": {
    "addr:full":"Dopheidestraat 34 Maasmechelen (eisden) Limburg 3630",
    "addr:housenumber":"34",
    "addr:postcode":"3630",
    "addr:street":"Dopheidestraat",
    "iso:country":"BE",
    "sg:address":"Dopheidestraat 34",
    "sg:city":"Maasmechelen (eisden)",
    "sg:classifiers":[
        {
            "category":"Retail",
            "subcategory":"Repair Shop",
            "type":"Services"
        }
    ],
    "sg:phone":"+32 89 76 61 97",
    "sg:postcode":"3630",
    "sg:province":"Limburg",
    "sg:tags":[
        "radio",
        "television",
        "-",
        "maintenance"
    ],
    "wof:name":"Electro Defect",
    "wof:placetype":"venue"
},
  "geometry": {"coordinates":[5.6961350441,50.963848114],"type":"Point"}
}