{
  "type": "Feature",
  "properties": {
    "addr:full":"Rue Hemricourt 28 Li\u00c8ge Li\u00e8ge 4000",
    "addr:housenumber":"28",
    "addr:postcode":"4000",
    "addr:street":"Rue Hemricourt",
    "iso:country":"BE",
    "sg:address":"Rue Hemricourt 28",
    "sg:city":"Li\u00c8ge",
    "sg:orig_category":"Artsen and specialisten",
    "sg:phone":"+32 4 252 55 50",
    "sg:postcode":"4000",
    "sg:province":"Li\u00e8ge",
    "wof:name":"Michel Thone",
    "wof:placetype":"venue"
},
  "geometry": {"coordinates":[5.5632948875,50.6309204102],"type":"Point"}
}