{
  "type": "Feature",
  "properties": {
    "iso:country":"BE",
    "sg:address":"Kanonstraat 35",
    "sg:city":"Kortrijk",
    "sg:orig_category":"Rev\u00eatements pour sols and murs. R\u00e9paration and restauration de meubles. Peinture",
    "sg:phone":"+32 56 25 61 91",
    "sg:postcode":"8500",
    "sg:province":"West-Vlaanderen",
    "wof:name":"Curd Vercruysse",
    "wof:placetype":"venue"
},
  "geometry": {"coordinates":[3.2707839012,50.8225212097],"type":"Point"}
}