{
  "type": "Feature",
  "properties": {
    "addr:full":"Hegge 111 Ravels Antwerpen 2382",
    "addr:housenumber":"111",
    "addr:postcode":"2382",
    "addr:street":"Hegge",
    "iso:country":"BE",
    "sg:address":"Hegge 111",
    "sg:city":"Ravels",
    "sg:classifiers":[
        {
            "category":"Shopping",
            "subcategory":"Clothing, Apparel, & Fashions",
            "type":"Retail Goods"
        }
    ],
    "sg:phone":"+32 14 65 84 12",
    "sg:postcode":"2382",
    "sg:province":"Antwerpen",
    "sg:tags":[
        "lingerie",
        "sous-v\u00eatements"
    ],
    "wof:name":"Huis Nore",
    "wof:placetype":"venue"
},
  "geometry": {"coordinates":[5.041768074,51.4469108582],"type":"Point"}
}