{
  "type": "Feature",
  "properties": {
    "addr:full":"Wijngaardlaan 34 Leuven (heverlee) Vlaams-Brabant 3001",
    "addr:housenumber":"34",
    "addr:postcode":"3001",
    "addr:street":"Wijngaardlaan",
    "iso:country":"BE",
    "sg:address":"Wijngaardlaan 34",
    "sg:city":"Leuven (heverlee)",
    "sg:classifiers":[
        {
            "category":"Social Services",
            "subcategory":"Job Training",
            "type":"Services"
        }
    ],
    "sg:phone":"+32 16 40 83 67",
    "sg:postcode":"3001",
    "sg:province":"Vlaams-Brabant",
    "sg:tags":[
        "personnel",
        "-selection",
        "recruitment"
    ],
    "wof:name":"Rosies & Partners Nv",
    "wof:placetype":"venue"
},
  "geometry": {"coordinates":[4.6915550232,50.8592071533],"type":"Point"}
}