{
  "type": "Feature",
  "properties": {
    "addr:full":"Heirbaan 263 Dendermonde Oost-Vlaanderen 9200",
    "addr:housenumber":"263",
    "addr:postcode":"9200",
    "addr:street":"Heirbaan;Oost-Vlaanderen",
    "iso:country":"BE",
    "sg:address":"Heirbaan 263",
    "sg:city":"Dendermonde",
    "sg:classifiers":[
        {
            "category":"Sports & Exercise",
            "subcategory":"Sports Center",
            "type":"Entertainment"
        }
    ],
    "sg:phone":"+32 52 21 30 05",
    "sg:postcode":"9200",
    "sg:province":"Oost-Vlaanderen",
    "sg:tags":[
        "de",
        "fitness"
    ],
    "wof:name":"Body Line",
    "wof:placetype":"venue"
},
  "geometry": {"coordinates":[4.1169290543,51.0112571716],"type":"Point"}
}