{
  "type": "Feature",
  "properties": {
    "addr:full":"Stationsplein Halle Vlaams-Brabant 1500",
    "addr:postcode":"1500",
    "addr:street":"Stationsplein",
    "iso:country":"BE",
    "sg:address":"Stationsplein",
    "sg:city":"Halle",
    "sg:orig_category":"Transports ferroviaires",
    "sg:phone":"+32 2 555 25 55",
    "sg:postcode":"1500",
    "sg:province":"Vlaams-Brabant",
    "wof:name":"Station Halle",
    "wof:placetype":"venue"
},
  "geometry": {"coordinates":[4.2391638756,50.7330741882],"type":"Point"}
}