{
  "type": "Feature",
  "properties": {
    "addr:full":"Blauweregenlaan 42 Schaarbeek (brussel) Bruxelles-Capitale 1030",
    "addr:housenumber":"42",
    "addr:postcode":"1030",
    "addr:street":"Blauweregenlaan",
    "iso:country":"BE",
    "sg:address":"Blauweregenlaan 42",
    "sg:city":"Schaarbeek (brussel)",
    "sg:orig_category":"Autokeuringen",
    "sg:phone":"+32 2 240 03 50",
    "sg:postcode":"1030",
    "sg:province":"Bruxelles-Capitale",
    "wof:name":"Autokeuring",
    "wof:placetype":"venue"
},
  "geometry": {"coordinates":[4.3894100189,50.8662109375],"type":"Point"}
}