{
  "type": "Feature",
  "properties": {
    "addr:full":"Urselweg 6 Box 1 Maldegem Oost-Vlaanderen 9990",
    "addr:housenumber":"6;1",
    "addr:postcode":"9990",
    "addr:street":"Urselweg;Box",
    "iso:country":"BE",
    "sg:address":"Urselweg 6 Box 1",
    "sg:city":"Maldegem",
    "sg:classifiers":[
        {
            "category":"Shopping",
            "subcategory":"Computers & Home Electronics",
            "type":"Retail Goods"
        }
    ],
    "sg:phone":"+32 50 71 10 21",
    "sg:postcode":"9990",
    "sg:province":"Oost-Vlaanderen",
    "sg:tags":[
        "spare",
        "part",
        "processing",
        "-",
        "data"
    ],
    "wof:name":"C.p. Systems Bvba",
    "wof:placetype":"venue"
},
  "geometry": {"coordinates":[3.4661900997,51.1760902405],"type":"Point"}
}