{
  "type": "Feature",
  "properties": {
    "addr:full":"Clos Du Bois Du Cheval 3 Mouscron Hainaut 7700",
    "addr:housenumber":"3",
    "addr:postcode":"7700",
    "addr:street":"Clos Du Bois Du Cheval",
    "iso:country":"BE",
    "sg:address":"Clos Du Bois Du Cheval 3",
    "sg:city":"Mouscron",
    "sg:classifiers":[
        {
            "category":"Retail",
            "subcategory":"Veterinary Services",
            "type":"Services"
        }
    ],
    "sg:phone":"+32 56 33 14 06",
    "sg:postcode":"7700",
    "sg:province":"Hainaut",
    "sg:tags":[
        "veterinarian"
    ],
    "wof:name":"Foulon F",
    "wof:placetype":"venue"
},
  "geometry": {"coordinates":[3.2096040249,50.7606468201],"type":"Point"}
}