{
  "type": "Feature",
  "properties": {
    "addr:full":"Leopold Ii Laan 2 Koksijde West-Vlaanderen 8670",
    "addr:housenumber":"2",
    "addr:postcode":"8670",
    "addr:street":"Leopold Ii Laan",
    "iso:country":"BE",
    "sg:address":"Leopold Ii Laan 2",
    "sg:city":"Koksijde",
    "sg:classifiers":[
        {
            "category":"Health Services",
            "subcategory":"Nursing And Care Facility",
            "type":"Services"
        }
    ],
    "sg:phone":"+32 58 51 60 11",
    "sg:postcode":"8670",
    "sg:province":"West-Vlaanderen",
    "sg:tags":[
        "public"
    ],
    "wof:name":"O.c.m.w.",
    "wof:placetype":"venue"
},
  "geometry": {"coordinates":[2.6823000908,51.1160392761],"type":"Point"}
}