{
  "type": "Feature",
  "properties": {
    "iso:country":"BE",
    "sg:address":"La Minerie 13",
    "sg:city":"Thimister-clermont",
    "sg:orig_category":"Installation \u00e9lectrique r\u00e9sidentielle",
    "sg:phone":"+32 87 44 62 44",
    "sg:postcode":"4890",
    "sg:province":"Li\u00e8ge",
    "wof:name":"Jacqui Legros Juli",
    "wof:placetype":"venue"
},
  "geometry": {"coordinates":[5.8476510048,50.6643562317],"type":"Point"}
}