{
  "type": "Feature",
  "properties": {
    "addr:full":"Dorpstraat 40 Ichtegem West-Vlaanderen 8480",
    "addr:housenumber":"40",
    "addr:postcode":"8480",
    "addr:street":"Dorpstraat",
    "iso:country":"BE",
    "sg:address":"Dorpstraat 40",
    "sg:city":"Ichtegem",
    "sg:orig_category":"Slagers",
    "sg:phone":"+32 50 81 54 55",
    "sg:postcode":"8480",
    "sg:province":"West-Vlaanderen",
    "wof:name":"Slagerij Bart & Sylvia",
    "wof:placetype":"venue"
},
  "geometry": {"coordinates":[3.0492019653,51.1587028503],"type":"Point"}
}