{
  "type": "Feature",
  "properties": {
    "addr:full":"A. Gironstraat 45 Elsene/ixelles Bruxelles-Capitale 1050",
    "addr:housenumber":"45",
    "addr:postcode":"1050",
    "addr:street":"A. Gironstraat",
    "iso:country":"BE",
    "sg:address":"A. Gironstraat 45",
    "sg:city":"Elsene/ixelles",
    "sg:orig_category":"Diverse organisaties and verenigingen",
    "sg:phone":"+32 2 648 56 95",
    "sg:postcode":"1050",
    "sg:province":"Bruxelles-Capitale",
    "wof:name":"Zero",
    "wof:placetype":"venue"
},
  "geometry": {"coordinates":[4.3788070679,50.8269538879],"type":"Point"}
}