{
  "type": "Feature",
  "properties": {
    "addr:full":"Rue De La Sambre 10-20 Bruxelles (molenbeek-saint-jean) Bruxelles-Capitale 1080",
    "addr:postcode":"10-20;molenbeek-saint-jean;1080",
    "addr:street":"Rue De La Sambre",
    "iso:country":"BE",
    "sg:address":"Rue De La Sambre 10-20",
    "sg:city":"Bruxelles (molenbeek-saint-jean)",
    "sg:classifiers":[
        {
            "category":"Wholesale",
            "subcategory":"Wine & Distilled Alcoholic Beverages",
            "type":"Manufacturing & Wholesale Goods"
        }
    ],
    "sg:phone":"+32 2 425 35 54",
    "sg:postcode":"1080",
    "sg:province":"Bruxelles-Capitale",
    "sg:tags":[
        "whol",
        "-",
        "spirit",
        "mfg"
    ],
    "wof:name":"Entrep\u00f4ts Nationaux Sprl",
    "wof:placetype":"venue"
},
  "geometry": {"coordinates":[4.342487812,50.8685684204],"type":"Point"}
}