{
  "type": "Feature",
  "properties": {
    "addr:full":"Place Joseph Thiry 21 Aywaille Li\u00e8ge 4920",
    "addr:housenumber":"21",
    "addr:postcode":"4920",
    "addr:street":"Place Joseph Thiry",
    "iso:country":"BE",
    "sg:address":"Place Joseph Thiry 21",
    "sg:city":"Aywaille",
    "sg:orig_category":"Boissons. Tabac",
    "sg:phone":"+32 4 384 57 48",
    "sg:postcode":"4920",
    "sg:province":"Li\u00e8ge",
    "wof:name":"Maison Aux Bons Buveurs",
    "wof:placetype":"venue"
},
  "geometry": {"coordinates":[5.6750621796,50.4741859436],"type":"Point"}
}