{
  "type": "Feature",
  "properties": {
    "iso:country":"BE",
    "sg:address":"Rue De La Burdinale 77",
    "sg:city":"Burdinne",
    "sg:orig_category":"Stations-service and carburants. Epiceries",
    "sg:phone":"+32 85 71 15 28",
    "sg:postcode":"4210",
    "sg:province":"Li\u00e8ge",
    "wof:name":"Carat",
    "wof:placetype":"venue"
},
  "geometry": {"coordinates":[5.0751137733,50.5849952698],"type":"Point"}
}