{
  "type": "Feature",
  "properties": {
    "iso:country":"BE",
    "sg:address":"Heulentakstraat 0",
    "sg:city":"Dilsen-stokkem",
    "sg:orig_category":"Mat\u00e9riaux de construction Gr",
    "sg:phone":"+32 89 79 04 44",
    "sg:postcode":"3650",
    "sg:province":"Limburg",
    "wof:name":"Thermic",
    "wof:placetype":"venue"
},
  "geometry": {"coordinates":[5.6973948479,51.0471992493],"type":"Point"}
}