{
  "type": "Feature",
  "properties": {
    "addr:full":"Place Albert Ier 27rc Charleroi (grand) Hainaut 6061",
    "addr:postcode":"27rc;6061",
    "addr:street":"Place Albert Ier",
    "iso:country":"BE",
    "sg:address":"Place Albert Ier 27rc",
    "sg:city":"Charleroi (grand)",
    "sg:orig_category":"Ordinateurs and \u00e9quipement informatique",
    "sg:phone":"+32 71 65 00 45",
    "sg:postcode":"6061",
    "sg:province":"Hainaut",
    "wof:name":"C.g.n Informatique Charleroi",
    "wof:placetype":"venue"
},
  "geometry": {"coordinates":[4.4792227745,50.4008216858],"type":"Point"}
}