{
  "type": "Feature",
  "properties": {
    "iso:country":"BE",
    "sg:address":"Elf Dagwand 24",
    "sg:city":"Denderleeuw",
    "sg:orig_category":"Pharmaciens",
    "sg:phone":"+32 53 66 79 07",
    "sg:postcode":"9473",
    "sg:province":"Oost-Vlaanderen",
    "wof:name":"Stefaan Van De Velde",
    "wof:placetype":"venue"
},
  "geometry": {"coordinates":[4.0552377701,50.8967247009],"type":"Point"}
}