{
  "type": "Feature",
  "properties": {
    "addr:full":"Clos Du Meunier 5 Wezembeek-oppem/wezembeek-oppem Vlaams-Brabant 1970",
    "addr:housenumber":"5",
    "addr:postcode":"1970",
    "addr:street":"Clos Du Meunier",
    "iso:country":"BE",
    "sg:address":"Clos Du Meunier 5",
    "sg:city":"Wezembeek-oppem/wezembeek-oppem",
    "sg:orig_category":"Parfumeries. Instituts de beaut\u00e9",
    "sg:phone":"+32 2 731 33 62",
    "sg:postcode":"1970",
    "sg:province":"Vlaams-Brabant",
    "wof:name":"Studio Colorane",
    "wof:placetype":"venue"
},
  "geometry": {"coordinates":[4.4894399643,50.8446006775],"type":"Point"}
}