{
  "type": "Feature",
  "properties": {
    "addr:full":"Avenue A.j. Slegers 65 Box 3 Bruxelles (woluwe-saint-lambert) Bruxelles-Capitale 1200",
    "addr:housenumber":"65;3",
    "addr:postcode":"1200",
    "addr:street":"Avenue A.J. Slegers;Box",
    "iso:country":"BE",
    "sg:address":"Avenue A.j. Slegers 65 Box 3",
    "sg:city":"Bruxelles (woluwe-saint-lambert)",
    "sg:classifiers":[
        {
            "category":"Professional",
            "subcategory":"Lawyer & Legal Services",
            "type":"Services"
        }
    ],
    "sg:phone":"+32 2 776 02 60",
    "sg:postcode":"1200",
    "sg:province":"Bruxelles-Capitale",
    "wof:name":"Sch\u00f6ller C\u00e9line",
    "wof:placetype":"venue"
},
  "geometry": {"coordinates":[4.4281778336,50.8408927917],"type":"Point"}
}