{
  "type": "Feature",
  "properties": {
    "iso:country":"BE",
    "sg:address":"Markt 23",
    "sg:city":"Meulebeke",
    "sg:classifiers":[
        {
            "category":"Bars & Pubs",
            "type":"Food & Drink"
        }
    ],
    "sg:phone":"+32 51 48 52 33",
    "sg:postcode":"8760",
    "sg:province":"West-Vlaanderen",
    "sg:tags":[
        "tavern"
    ],
    "wof:name":"De Nieuwe Leeuw",
    "wof:placetype":"venue"
},
  "geometry": {"coordinates":[3.2876589298,50.9495010376],"type":"Point"}
}