{
  "type": "Feature",
  "properties": {
    "iso:country":"BE",
    "sg:address":"Merelbekestraat 21",
    "sg:city":"Melle",
    "sg:classifiers":[
        {
            "category":"Health Services",
            "subcategory":"Health Practitioner",
            "type":"Services"
        }
    ],
    "sg:phone":"+32 9 232 58 80",
    "sg:postcode":"9090",
    "sg:province":"Oost-Vlaanderen",
    "sg:tags":[
        "physiotherapist"
    ],
    "wof:name":"Janssens Martine",
    "wof:placetype":"venue"
},
  "geometry": {"coordinates":[3.7718598843,51.023765564],"type":"Point"}
}