{
  "type": "Feature",
  "properties": {
    "addr:full":"Chemin Des M\u00e9sanges 1 Profondeville Namur 5170",
    "addr:housenumber":"1",
    "addr:postcode":"5170",
    "addr:street":"Chemin Des Me\u0301Sanges",
    "iso:country":"BE",
    "sg:address":"Chemin Des M\u00e9sanges 1",
    "sg:city":"Profondeville",
    "sg:classifiers":[
        {
            "category":"Communications",
            "subcategory":"Newspaper",
            "type":"Services"
        }
    ],
    "sg:phone":"+32 81 41 24 05",
    "sg:postcode":"5170",
    "sg:province":"Namur",
    "sg:tags":[
        "paper",
        "local",
        "free"
    ],
    "wof:name":"Delmotte E",
    "wof:placetype":"venue"
},
  "geometry": {"coordinates":[4.8582458496,50.3846130371],"type":"Point"}
}