{
  "type": "Feature",
  "properties": {
    "addr:full":"Wingensesteenweg 1a Tielt West-Vlaanderen 8700",
    "addr:housenumber":"1a",
    "addr:postcode":"8700",
    "addr:street":"Wingensesteenweg",
    "iso:country":"BE",
    "sg:address":"Wingensesteenweg 1a",
    "sg:city":"Tielt",
    "sg:classifiers":[
        {
            "category":"Manufacturing",
            "subcategory":"Glass & Minerals",
            "type":"Manufacturing & Wholesale Goods"
        }
    ],
    "sg:phone":"+32 51 40 90 80",
    "sg:postcode":"8700",
    "sg:province":"West-Vlaanderen",
    "sg:tags":[
        "automobile",
        "-"
    ],
    "wof:name":"Metaglas Bvba",
    "wof:placetype":"venue"
},
  "geometry": {"coordinates":[3.3227460384,51.0041923523],"type":"Point"}
}