{
  "type": "Feature",
  "properties": {
    "iso:country":"BE",
    "sg:address":"Reiningepad 5",
    "sg:city":"Blankenberge",
    "sg:classifiers":[
        {
            "category":"Wholesale",
            "subcategory":"Sporting Goods",
            "type":"Manufacturing & Wholesale Goods"
        }
    ],
    "sg:phone":"+32 50 41 73 87",
    "sg:postcode":"8370",
    "sg:province":"West-Vlaanderen",
    "sg:tags":[
        "sport-",
        "kampeermateriaal"
    ],
    "wof:name":"Stafreubens",
    "wof:placetype":"venue"
},
  "geometry": {"coordinates":[3.1219639778,51.3048744202],"type":"Point"}
}