{
  "type": "Feature",
  "properties": {
    "iso:country":"BE",
    "sg:address":"Rupelstraat 37",
    "sg:city":"Niel",
    "sg:classifiers":[
        {
            "category":"Autos & Motor Vehicles",
            "subcategory":"Fuel & Gas Station",
            "type":"Retail Goods"
        }
    ],
    "sg:phone":"+32 3 888 41 76",
    "sg:postcode":"2845",
    "sg:province":"Antwerpen",
    "sg:tags":[
        "stations-service",
        "carburants"
    ],
    "wof:name":"Garage Verstrepen",
    "wof:placetype":"venue"
},
  "geometry": {"coordinates":[4.3239850998,51.1063423157],"type":"Point"}
}