{
  "type": "Feature",
  "properties": {
    "addr:full":"Smisstraat 23 Beveren Oost-Vlaanderen 9120",
    "addr:housenumber":"23",
    "addr:postcode":"9120",
    "addr:street":"Smisstraat",
    "iso:country":"BE",
    "sg:address":"Smisstraat 23",
    "sg:city":"Beveren",
    "sg:orig_category":"Animations diverses",
    "sg:phone":"+32 3 755 24 45",
    "sg:postcode":"9120",
    "sg:province":"Oost-Vlaanderen",
    "wof:name":"Figurentheater Vlinders & Co",
    "wof:placetype":"venue"
},
  "geometry": {"coordinates":[4.1877660751,51.220161438],"type":"Point"}
}