{
  "type": "Feature",
  "properties": {
    "iso:country":"BE",
    "sg:address":"Affligemstraat 85",
    "sg:city":"Ternat",
    "sg:orig_category":"Mat\u00e9riel de T\u00e9l\u00e9communication",
    "sg:phone":"+32 53 67 30 60",
    "sg:postcode":"1742",
    "sg:province":"Vlaams-Brabant",
    "wof:name":"Ducque Equip",
    "wof:placetype":"venue"
},
  "geometry": {"coordinates":[4.1190037727,50.8815994263],"type":"Point"}
}