{
  "type": "Feature",
  "properties": {
    "iso:country":"BE",
    "sg:address":"Rue Traversi\u00c8re 8",
    "sg:city":"Saint-josse-ten-noode",
    "sg:orig_category":"Jeugdherbergen and berghutten",
    "sg:phone":"+32 2 217 01 58",
    "sg:postcode":"1210",
    "sg:province":"Bruxelles-Capitale",
    "wof:name":"Centre Vincent Van Gogh",
    "wof:placetype":"venue"
},
  "geometry": {"coordinates":[4.3681001663,50.8543205261],"type":"Point"}
}