{
  "type": "Feature",
  "properties": {
    "addr:full":"Steenkouter 41 Wichelen (serskamp) Oost-Vlaanderen 9260",
    "addr:housenumber":"41",
    "addr:postcode":"9260",
    "addr:street":"Steenkouter",
    "iso:country":"BE",
    "sg:address":"Steenkouter 41",
    "sg:city":"Wichelen (serskamp)",
    "sg:classifiers":[
        {
            "category":"Building & Trades",
            "subcategory":"Construction",
            "type":"Services"
        }
    ],
    "sg:phone":"+32 9 369 86 46",
    "sg:postcode":"9260",
    "sg:province":"Oost-Vlaanderen",
    "sg:tags":[
        "carpenter"
    ],
    "wof:name":"Van Damme",
    "wof:placetype":"venue"
},
  "geometry": {"coordinates":[3.9323370457,50.9841461182],"type":"Point"}
}