{
  "type": "Feature",
  "properties": {
    "iso:country":"BE",
    "sg:address":"Avenue De Spa 71",
    "sg:city":"Verviers",
    "sg:orig_category":"Artsen and specialisten",
    "sg:phone":"+32 87 22 56 54",
    "sg:postcode":"4802",
    "sg:province":"Li\u00e8ge",
    "wof:name":"Didier Lamalle",
    "wof:placetype":"venue"
},
  "geometry": {"coordinates":[5.8671250343,50.5714111328],"type":"Point"}
}