{
  "type": "Feature",
  "properties": {
    "iso:country":"BE",
    "sg:address":"Zoning Artisanal 27",
    "sg:city":"Trois-ponts - Fosse",
    "sg:classifiers":[
        {
            "category":"Home & Garden",
            "subcategory":"Carpets & Floor Coverings",
            "type":"Retail Goods"
        }
    ],
    "sg:phone":"+32 80 68 44 86",
    "sg:postcode":"4980",
    "sg:province":"Li\u00e8ge",
    "sg:tags":[
        "house",
        "prefabricated"
    ],
    "wof:name":"Gabriel Jean-luc",
    "wof:placetype":"venue"
},
  "geometry": {"coordinates":[5.9202442169,50.3550033569],"type":"Point"}
}