{
  "type": "Feature",
  "properties": {
    "addr:full":"Medell 175 Amel (meyerode) Li\u00e8ge 4770",
    "addr:housenumber":"175",
    "addr:postcode":"4770",
    "addr:street":"Medell;Meyerode",
    "iso:country":"BE",
    "sg:address":"Medell 175",
    "sg:city":"Amel (meyerode)",
    "sg:classifiers":[
        {
            "category":"Organizations",
            "subcategory":"Community Association",
            "type":"Services"
        }
    ],
    "sg:phone":"+32 80 34 92 88",
    "sg:postcode":"4770",
    "sg:province":"Li\u00e8ge",
    "sg:tags":[
        "cultural"
    ],
    "wof:name":"Volksbildungswerk St-vith",
    "wof:placetype":"venue"
},
  "geometry": {"coordinates":[6.1689629555,50.3543167114],"type":"Point"}
}