{
  "type": "Feature",
  "properties": {
    "iso:country":"BE",
    "sg:address":"Passage De La Bourse 24",
    "sg:city":"Charleroi",
    "sg:classifiers":[
        {
            "category":"Shopping",
            "subcategory":"Bicycles & Sporting Goods",
            "type":"Retail Goods"
        }
    ],
    "sg:phone":"+32 71 32 36 31",
    "sg:postcode":"6000",
    "sg:province":"Hainaut",
    "sg:tags":[
        "article",
        "de",
        "sport",
        "camping"
    ],
    "wof:name":"Maison Delvoie",
    "wof:placetype":"venue"
},
  "geometry": {"coordinates":[4.4405760765,50.4069366455],"type":"Point"}
}