{
  "type": "Feature",
  "properties": {
    "addr:full":"Riemenstraat 58 Vorselaar Antwerpen 2290",
    "addr:housenumber":"58",
    "addr:postcode":"2290",
    "addr:street":"Riemenstraat",
    "iso:country":"BE",
    "sg:address":"Riemenstraat 58",
    "sg:city":"Vorselaar",
    "sg:orig_category":"M\u00e9decins and sp\u00e9cialistes",
    "sg:phone":"+32 14 51 37 97",
    "sg:postcode":"2290",
    "sg:province":"Antwerpen",
    "wof:name":"Walter Van Der Kerken",
    "wof:placetype":"venue"
},
  "geometry": {"coordinates":[4.7779998779,51.2052001953],"type":"Point"}
}