{
  "type": "Feature",
  "properties": {
    "iso:country":"BE",
    "sg:address":"Industrieweg 3",
    "sg:city":"Leuven (heverlee)",
    "sg:classifiers":[
        {
            "category":"Utilities",
            "subcategory":"Sewage",
            "type":"Services"
        }
    ],
    "sg:phone":"+32 16 40 55 05",
    "sg:postcode":"3001",
    "sg:province":"Vlaams-Brabant",
    "sg:tags":[
        "acoustic",
        "consultant"
    ],
    "wof:name":"Scala Consultants",
    "wof:placetype":"venue"
},
  "geometry": {"coordinates":[4.7238640785,50.8459281921],"type":"Point"}
}