{
  "type": "Feature",
  "properties": {
    "iso:country":"BE",
    "sg:address":"Rue Saint-servais 1",
    "sg:city":"Arlon (toernich)",
    "sg:classifiers":[
        {
            "category":"Health Services",
            "subcategory":"Health Practitioner",
            "type":"Services"
        }
    ],
    "sg:phone":"+32 63 22 58 80",
    "sg:postcode":"6700",
    "sg:province":"Luxembourg",
    "sg:tags":[
        "physiotherapist"
    ],
    "wof:name":"Guiot V",
    "wof:placetype":"venue"
},
  "geometry": {"coordinates":[5.7719779015,49.636390686],"type":"Point"}
}