{
  "type": "Feature",
  "properties": {
    "addr:full":"Chemin De Wooz 32 Dison Li\u00e8ge 4821",
    "addr:housenumber":"32",
    "addr:postcode":"4821",
    "addr:street":"Chemin De Wooz",
    "iso:country":"BE",
    "sg:address":"Chemin De Wooz 32",
    "sg:city":"Dison",
    "sg:orig_category":"Eleveurs de bovins",
    "sg:phone":"+32 87 35 42 16",
    "sg:postcode":"4821",
    "sg:province":"Li\u00e8ge",
    "wof:name":"Bernard Roehl",
    "wof:placetype":"venue"
},
  "geometry": {"coordinates":[5.881280899,50.6143875122],"type":"Point"}
}