{
  "type": "Feature",
  "properties": {
    "iso:country":"BE",
    "sg:address":"Avenue Prof. Henrijean 133",
    "sg:city":"Spa",
    "sg:orig_category":"Auto-\u00e9coles",
    "sg:phone":"+32 87 77 13 67",
    "sg:postcode":"4900",
    "sg:province":"Li\u00e8ge",
    "wof:name":"M. Chaslin",
    "wof:placetype":"venue"
},
  "geometry": {"coordinates":[5.8538222313,50.4807434082],"type":"Point"}
}