{
  "type": "Feature",
  "properties": {
    "addr:full":"Otegemsesteenweg 27 Deerlijk West-Vlaanderen 8540",
    "addr:housenumber":"27",
    "addr:postcode":"8540",
    "addr:street":"Otegemsesteenweg",
    "iso:country":"BE",
    "sg:address":"Otegemsesteenweg 27",
    "sg:city":"Deerlijk",
    "sg:orig_category":"Kapsalons",
    "sg:phone":"+32 56 77 72 51",
    "sg:postcode":"8540",
    "sg:province":"West-Vlaanderen",
    "wof:name":"Coiffure Carine",
    "wof:placetype":"venue"
},
  "geometry": {"coordinates":[3.3757250309,50.8156089783],"type":"Point"}
}