{
  "type": "Feature",
  "properties": {
    "iso:country":"BE",
    "sg:address":"Hegstraat 1",
    "sg:city":"Maasmechelen (boorsem)",
    "sg:classifiers":[
        {
            "category":"Building & Trades",
            "subcategory":"Construction",
            "type":"Services"
        }
    ],
    "sg:phone":"+32 89 77 22 27",
    "sg:postcode":"3631",
    "sg:province":"Limburg",
    "sg:tags":[
        "stucco",
        "contractor"
    ],
    "wof:name":"Molenbruch J P",
    "wof:placetype":"venue"
},
  "geometry": {"coordinates":[5.7239232063,50.9423713684],"type":"Point"}
}