{
  "type": "Feature",
  "properties": {
    "iso:country":"BE",
    "sg:address":"Secretaris Vanmarckelaan 0",
    "sg:city":"Wevelgem",
    "sg:orig_category":"Sportcentra Sportterreinen and installaties behalve sportcentra",
    "sg:phone":"+32 56 41 04 55",
    "sg:postcode":"8560",
    "sg:province":"West-Vlaanderen",
    "wof:name":"Sporthal",
    "wof:placetype":"venue"
},
  "geometry": {"coordinates":[3.1680030823,50.8396492004],"type":"Point"}
}