{
  "type": "Feature",
  "properties": {
    "iso:country":"BE",
    "sg:address":"Rue De La Bruy\u00c8re 1",
    "sg:city":"Incourt",
    "sg:orig_category":"Landbouwmachines Gh",
    "sg:phone":"+32 10 88 85 92",
    "sg:postcode":"1315",
    "sg:province":"Brabant Wallon",
    "wof:name":"Ets. Bajoit",
    "wof:placetype":"venue"
},
  "geometry": {"coordinates":[4.8027901649,50.6850090027],"type":"Point"}
}