{
  "type": "Feature",
  "properties": {
    "addr:full":"Rue De La D\u00c9portation 5 Beaumont Hainaut 6500",
    "addr:housenumber":"5",
    "addr:postcode":"6500",
    "addr:street":"Rue De La De\u0301Portation;Hainaut",
    "iso:country":"BE",
    "sg:address":"Rue De La D\u00c9portation 5",
    "sg:city":"Beaumont",
    "sg:classifiers":[
        {
            "category":"Government",
            "subcategory":"Police Station",
            "type":"Public Place"
        }
    ],
    "sg:phone":"+32 71 58 86 88",
    "sg:postcode":"6500",
    "sg:province":"Hainaut",
    "sg:tags":[
        "gendarmerie"
    ],
    "wof:name":"Police F\u00c9d\u00c9rale",
    "wof:placetype":"venue"
},
  "geometry": {"coordinates":[4.2360038757,50.2374649048],"type":"Point"}
}