{
  "type": "Feature",
  "properties": {
    "iso:country":"BE",
    "sg:address":"Weidestraat 234",
    "sg:city":"Brugge",
    "sg:orig_category":"M\u00e9decines alternatives",
    "sg:phone":"+32 50 35 12 36",
    "sg:postcode":"8310",
    "sg:province":"West-Vlaanderen",
    "wof:name":"Praktijk Jonckheere",
    "wof:placetype":"venue"
},
  "geometry": {"coordinates":[3.2532970905,51.1886405945],"type":"Point"}
}