{
  "type": "Feature",
  "properties": {
    "addr:full":"Grand'place 1 Tubize Brabant Wallon 1480",
    "addr:housenumber":"1",
    "addr:postcode":"1480",
    "addr:street":"Grand'Place;Wallon",
    "iso:country":"BE",
    "sg:address":"Grand'place 1",
    "sg:city":"Tubize",
    "sg:classifiers":[
        {
            "category":"Health Services",
            "subcategory":"Nursing And Care Facility",
            "type":"Services"
        }
    ],
    "sg:phone":"+32 2 391 39 11",
    "sg:postcode":"1480",
    "sg:province":"Brabant Wallon",
    "sg:tags":[
        "public"
    ],
    "wof:name":"Administration Communale",
    "wof:placetype":"venue"
},
  "geometry": {"coordinates":[4.2045860291,50.6933784485],"type":"Point"}
}