{
  "type": "Feature",
  "properties": {
    "iso:country":"BE",
    "sg:address":"Fran\u00e7ois Van Impelaan 67",
    "sg:city":"Gent (oostakker)",
    "sg:classifiers":[
        {
            "category":"Home & Garden",
            "subcategory":"Building Materials",
            "type":"Retail Goods"
        }
    ],
    "sg:phone":"+32 9 259 26 11",
    "sg:postcode":"9041",
    "sg:province":"Oost-Vlaanderen",
    "sg:tags":[
        "granite",
        "stone",
        "natural",
        "marble"
    ],
    "wof:name":"Natuursteen Dolomiti",
    "wof:placetype":"venue"
},
  "geometry": {"coordinates":[3.7679710388,51.0919303894],"type":"Point"}
}