{
  "type": "Feature",
  "properties": {
    "iso:country":"BE",
    "sg:address":"V\u00f6lkerich 27",
    "sg:city":"Plombi\u00e8res (gemmenich)",
    "sg:classifiers":[
        {
            "category":"Organizations",
            "subcategory":"Professional Association",
            "type":"Services"
        }
    ],
    "sg:phone":"+32 87 78 43 57",
    "sg:postcode":"4851",
    "sg:province":"Li\u00e8ge",
    "sg:tags":[
        "organisation",
        "seminar"
    ],
    "wof:name":"Home Franck Asbl",
    "wof:placetype":"venue"
},
  "geometry": {"coordinates":[5.9952659607,50.7457046509],"type":"Point"}
}