{
  "type": "Feature",
  "properties": {
    "iso:country":"BE",
    "sg:address":"Koninksemsteenweg 95",
    "sg:city":"Tongeren",
    "sg:classifiers":[
        {
            "category":"Personal",
            "subcategory":"Beauty Salon",
            "type":"Services"
        }
    ],
    "sg:phone":"+32 12 26 13 77",
    "sg:postcode":"3700",
    "sg:province":"Limburg",
    "sg:tags":[
        "de",
        "coiffure"
    ],
    "wof:name":"Coiffure Sonja",
    "wof:placetype":"venue"
},
  "geometry": {"coordinates":[5.4566020966,50.7765884399],"type":"Point"}
}