{
  "type": "Feature",
  "properties": {
    "iso:country":"BE",
    "sg:address":"Rue Du Tr\u00f4ne 185",
    "sg:city":"Bruxelles (ixelles)",
    "sg:classifiers":[
        {
            "category":"Military Area",
            "subcategory":"Army Base",
            "type":"Public Place"
        }
    ],
    "sg:phone":"+32 2 514 22 60",
    "sg:postcode":"1050",
    "sg:province":"Bruxelles-Capitale",
    "sg:tags":[
        "equipment",
        "machinery",
        "vacuum"
    ],
    "wof:name":"Metys Sa",
    "wof:placetype":"venue"
},
  "geometry": {"coordinates":[4.3723788261,50.8348426819],"type":"Point"}
}