{
  "type": "Feature",
  "properties": {
    "addr:full":"Veurnestraat 128 Poperinge West-Vlaanderen 8970",
    "addr:housenumber":"128",
    "addr:postcode":"8970",
    "addr:street":"Veurnestraat",
    "iso:country":"BE",
    "sg:address":"Veurnestraat 128",
    "sg:city":"Poperinge",
    "sg:orig_category":"V\u00e9t\u00e9rinaires",
    "sg:phone":"+32 57 33 25 15",
    "sg:postcode":"8970",
    "sg:province":"West-Vlaanderen",
    "wof:name":"Ann Lein",
    "wof:placetype":"venue"
},
  "geometry": {"coordinates":[2.7303409576,50.8600349426],"type":"Point"}
}