{
  "type": "Feature",
  "properties": {
    "iso:country":"BE",
    "sg:address":"Driftweg 67",
    "sg:city":"Bredene",
    "sg:orig_category":"Rev\u00eatements pour sols and murs. Rev\u00eatements de sols and murs. Construction de maisons",
    "sg:phone":"+32 59 32 56 47",
    "sg:postcode":"8450",
    "sg:province":"West-Vlaanderen",
    "wof:name":"Groep Sleuyter",
    "wof:placetype":"venue"
},
  "geometry": {"coordinates":[2.9503910542,51.2438545227],"type":"Point"}
}