{
  "type": "Feature",
  "properties": {
    "addr:full":"Rue L\u00c9opold 1er 511 Jette Bruxelles-Capitale 1090",
    "addr:housenumber":"511",
    "addr:postcode":"1090",
    "addr:street":"Rue Le\u0301Opold 1Er",
    "iso:country":"BE",
    "sg:address":"Rue L\u00c9opold 1er 511",
    "sg:city":"Jette",
    "sg:orig_category":"Poissonniers and \u00e9caillers. Alimentation sp\u00e9cialis\u00e9e",
    "sg:phone":"+32 2 420 79 11",
    "sg:postcode":"1090",
    "sg:province":"Bruxelles-Capitale",
    "wof:name":"Fish Market",
    "wof:placetype":"venue"
},
  "geometry": {"coordinates":[4.3274250031,50.8731842041],"type":"Point"}
}