{
  "type": "Feature",
  "properties": {
    "addr:full":"Westelsebaan 135 Scherpenheuvel-zichem Vlaams-Brabant 3271",
    "addr:housenumber":"135",
    "addr:postcode":"3271",
    "addr:street":"Scherpenheuvel-Zichem Vlaams-Brabant",
    "iso:country":"BE",
    "sg:address":"Westelsebaan 135",
    "sg:city":"Scherpenheuvel-zichem",
    "sg:orig_category":"M\u00e9decins and sp\u00e9cialistes",
    "sg:phone":"+32 13 78 48 18",
    "sg:postcode":"3271",
    "sg:province":"Vlaams-Brabant",
    "wof:name":"Walter Geys",
    "wof:placetype":"venue"
},
  "geometry": {"coordinates":[4.9812488556,51.0284996033],"type":"Point"}
}