{
  "type": "Feature",
  "properties": {
    "addr:full":"Avenue Des Cerisiers 110 Bruxelles (woluwe-saint-lambert) Bruxelles-Capitale 1200",
    "addr:housenumber":"110",
    "addr:postcode":"1200",
    "addr:street":"Avenue Des Cerisiers",
    "iso:country":"BE",
    "sg:address":"Avenue Des Cerisiers 110",
    "sg:city":"Bruxelles (woluwe-saint-lambert)",
    "sg:classifiers":[
        {
            "category":"Real Estate",
            "subcategory":"Architect",
            "type":"Services"
        }
    ],
    "sg:phone":"+32 2 770 47 98",
    "sg:postcode":"1200",
    "sg:province":"Bruxelles-Capitale",
    "wof:name":"Willems Th",
    "wof:placetype":"venue"
},
  "geometry": {"coordinates":[4.4095420837,50.8477363586],"type":"Point"}
}