{
  "type": "Feature",
  "properties": {
    "iso:country":"BE",
    "sg:address":"Brakelsesteenweg 559",
    "sg:city":"Ninove",
    "sg:classifiers":[
        {
            "category":"Cafe",
            "type":"Food & Drink"
        }
    ],
    "sg:phone":"+32 54 50 02 44",
    "sg:postcode":"9400",
    "sg:province":"Oost-Vlaanderen",
    "sg:tags":[
        "caf\u00e9s"
    ],
    "wof:name":"'t Wit Paard",
    "wof:placetype":"venue"
},
  "geometry": {"coordinates":[4.0039701462,50.8359107971],"type":"Point"}
}