{
  "type": "Feature",
  "properties": {
    "iso:country":"BE",
    "sg:address":"Korenbloemstraat 6",
    "sg:city":"Neerpelt",
    "sg:classifiers":[
        {
            "category":"Health Services",
            "subcategory":"Health Practitioner",
            "type":"Services"
        }
    ],
    "sg:phone":"+32 11 64 65 54",
    "sg:postcode":"3910",
    "sg:province":"Limburg",
    "sg:tags":[
        "physiotherapist"
    ],
    "wof:name":"Bergs L",
    "wof:placetype":"venue"
},
  "geometry": {"coordinates":[5.4457330704,51.2249145508],"type":"Point"}
}