{
  "type": "Feature",
  "properties": {
    "addr:full":"Rue Du Luxembourg 16 Moeskroen/mouscron Hainaut 7700",
    "addr:housenumber":"16",
    "addr:postcode":"7700",
    "addr:street":"Rue Du Luxembourg",
    "iso:country":"BE",
    "sg:address":"Rue Du Luxembourg 16",
    "sg:city":"Moeskroen/mouscron",
    "sg:orig_category":"M\u00e9decins and sp\u00e9cialistes",
    "sg:phone":"+32 56 33 42 82",
    "sg:postcode":"7700",
    "sg:province":"Hainaut",
    "wof:name":"J. Van Hende",
    "wof:placetype":"venue"
},
  "geometry": {"coordinates":[3.2323200703,50.7400932312],"type":"Point"}
}