{
  "type": "Feature",
  "properties": {
    "addr:full":"Van Souststraat 102 Anderlecht/anderlecht Bruxelles-Capitale 1070",
    "addr:housenumber":"102",
    "addr:postcode":"1070",
    "addr:street":"Van Souststraat",
    "iso:country":"BE",
    "sg:address":"Van Souststraat 102",
    "sg:city":"Anderlecht/anderlecht",
    "sg:orig_category":"Herstellingswinkels voor diverse persoonlijke and huishoudartikelen",
    "sg:phone":"+32 2 522 67 75",
    "sg:postcode":"1070",
    "sg:province":"Bruxelles-Capitale",
    "wof:name":"Maison Francine",
    "wof:placetype":"venue"
},
  "geometry": {"coordinates":[4.3090658188,50.8465843201],"type":"Point"}
}