{
  "type": "Feature",
  "properties": {
    "addr:full":"Lambertus Coolsstraat 21 Middelkerke (slijpe) West-Vlaanderen 8433",
    "addr:housenumber":"21",
    "addr:postcode":"8433",
    "addr:street":"Lambertus Coolsstraat",
    "iso:country":"BE",
    "sg:address":"Lambertus Coolsstraat 21",
    "sg:city":"Middelkerke (slijpe)",
    "sg:classifiers":[
        {
            "category":"Banks & Credit Unions",
            "subcategory":"Investment Brokerage",
            "type":"Services"
        }
    ],
    "sg:phone":"+32 59 31 46 73",
    "sg:postcode":"8433",
    "sg:province":"West-Vlaanderen",
    "sg:tags":[
        "repair",
        "-",
        "installation",
        "sanitary",
        "article"
    ],
    "wof:name":"De Preter",
    "wof:placetype":"venue"
},
  "geometry": {"coordinates":[2.8440690041,51.1539726257],"type":"Point"}
}