{
  "type": "Feature",
  "properties": {
    "addr:full":"Avenue De La Reine 131 Bruxelles (schaerbeek) Bruxelles-Capitale 1030",
    "addr:housenumber":"131",
    "addr:postcode":"1030",
    "addr:street":"Avenue De La Reine",
    "iso:country":"BE",
    "sg:address":"Avenue De La Reine 131",
    "sg:city":"Bruxelles (schaerbeek)",
    "sg:orig_category":"Non-Classified Establishments",
    "sg:phone":"+32 2 201 06 10",
    "sg:postcode":"1030",
    "sg:province":"Bruxelles-Capitale",
    "wof:name":"Plexy-reine",
    "wof:placetype":"venue"
},
  "geometry": {"coordinates":[4.3632121086,50.8685302734],"type":"Point"}
}