{
  "type": "Feature",
  "properties": {
    "addr:full":"Rue Des Sept Collines 80 Chaudfontaine Li\u00e8ge 4052",
    "addr:housenumber":"80",
    "addr:postcode":"4052",
    "addr:street":"Rue Des Sept Collines",
    "iso:country":"BE",
    "sg:address":"Rue Des Sept Collines 80",
    "sg:city":"Chaudfontaine",
    "sg:orig_category":"M\u00e9decins and sp\u00e9cialistes",
    "sg:phone":"+32 4 368 71 86",
    "sg:postcode":"4052",
    "sg:province":"Li\u00e8ge",
    "wof:name":"Chantal Spadin-olivier",
    "wof:placetype":"venue"
},
  "geometry": {"coordinates":[5.6129508018,50.5724945068],"type":"Point"}
}