{
  "type": "Feature",
  "properties": {
    "addr:full":"Neerstraat 55 Tessenderlo Limburg 3980",
    "addr:housenumber":"55",
    "addr:postcode":"3980",
    "addr:street":"Neerstraat",
    "iso:country":"BE",
    "sg:address":"Neerstraat 55",
    "sg:city":"Tessenderlo",
    "sg:orig_category":"Installatie van houten of kunststof schrijnwerk",
    "sg:phone":"+32 13 67 35 11",
    "sg:postcode":"3980",
    "sg:province":"Limburg",
    "wof:name":"Beva",
    "wof:placetype":"venue"
},
  "geometry": {"coordinates":[5.088280201,51.0694198608],"type":"Point"}
}