{
  "type": "Feature",
  "properties": {
    "addr:full":"Troonstraat 101b20 Oostende West-Vlaanderen 8400",
    "addr:housenumber":"101b20",
    "addr:postcode":"8400",
    "addr:street":"Troonstraat",
    "iso:country":"BE",
    "sg:address":"Troonstraat 101b20",
    "sg:city":"Oostende",
    "sg:orig_category":"Artsen and specialisten",
    "sg:phone":"+32 59 80 31 33",
    "sg:postcode":"8400",
    "sg:province":"West-Vlaanderen",
    "wof:name":"Johan Pintelon",
    "wof:placetype":"venue"
},
  "geometry": {"coordinates":[2.8875699043,51.2195014954],"type":"Point"}
}