{
  "type": "Feature",
  "properties": {
    "addr:full":"Gouverneur Roppesingel 83 Hasselt Limburg 3500",
    "addr:housenumber":"83",
    "addr:postcode":"3500",
    "addr:street":"Gouverneur Roppesingel",
    "iso:country":"BE",
    "sg:address":"Gouverneur Roppesingel 83",
    "sg:city":"Hasselt",
    "sg:classifiers":[
        {
            "category":"Professional",
            "subcategory":"Accounting & Tax Preparation",
            "type":"Services"
        }
    ],
    "sg:phone":"+32 11 28 31 00",
    "sg:postcode":"3500",
    "sg:province":"Limburg",
    "sg:tags":[
        "accountant"
    ],
    "wof:name":"Roger Janssens",
    "wof:placetype":"venue"
},
  "geometry": {"coordinates":[5.3537302017,50.9197692871],"type":"Point"}
}