{
  "type": "Feature",
  "properties": {
    "iso:country":"BE",
    "sg:address":"Steenberg 79",
    "sg:city":"Ninove",
    "sg:orig_category":"Sportclubs Sportterreinen and installaties behalve sportcentra",
    "sg:phone":"+32 54 33 58 56",
    "sg:postcode":"9401",
    "sg:province":"Oost-Vlaanderen",
    "wof:name":"V.c. Osta Meerbeke",
    "wof:placetype":"venue"
},
  "geometry": {"coordinates":[3.9980449677,50.8108901978],"type":"Point"}
}