{
  "type": "Feature",
  "properties": {
    "addr:full":"Kehrweg 9bc Eupen/eupen Li\u00e8ge 4700",
    "addr:housenumber":"9bc",
    "addr:postcode":"4700",
    "addr:street":"Kehrweg",
    "iso:country":"BE",
    "sg:address":"Kehrweg 9bc",
    "sg:city":"Eupen/eupen",
    "sg:orig_category":"Brandweer and civiele bescherming",
    "sg:phone":"+32 87 55 31 49",
    "sg:postcode":"4700",
    "sg:province":"Li\u00e8ge",
    "wof:name":"Feuerwehrkaserne",
    "wof:placetype":"venue"
},
  "geometry": {"coordinates":[6.0447678566,50.6251068115],"type":"Point"}
}