{
  "type": "Feature",
  "properties": {
    "iso:country":"BE",
    "sg:address":"Einde Were 53",
    "sg:city":"Gent",
    "sg:orig_category":"Brood, gebak and snoepgoed",
    "sg:phone":"+32 9 225 40 41",
    "sg:postcode":"9000",
    "sg:province":"Oost-Vlaanderen",
    "wof:name":"Camille Minnekeer",
    "wof:placetype":"venue"
},
  "geometry": {"coordinates":[3.7013659477,51.0509147644],"type":"Point"}
}