{
  "type": "Feature",
  "properties": {
    "iso:country":"BE",
    "sg:address":"Bieststraat 12",
    "sg:city":"Bierbeek (lovenjoel)",
    "sg:classifiers":[
        {
            "category":"Shopping",
            "subcategory":"Clothing, Apparel, & Fashions",
            "type":"Retail Goods"
        }
    ],
    "sg:phone":"+32 16 46 35 89",
    "sg:postcode":"3360",
    "sg:province":"Vlaams-Brabant",
    "sg:tags":[
        "lady",
        "clothing",
        "-"
    ],
    "wof:name":"Luan Styling",
    "wof:placetype":"venue"
},
  "geometry": {"coordinates":[4.7760457993,50.8602333069],"type":"Point"}
}