{
  "type": "Feature",
  "properties": {
    "addr:full":"Kapellestraat 87bb Oostende West-Vlaanderen 8400",
    "addr:housenumber":"87bb",
    "addr:postcode":"8400",
    "addr:street":"Kapellestraat",
    "iso:country":"BE",
    "sg:address":"Kapellestraat 87bb",
    "sg:city":"Oostende",
    "sg:orig_category":"V\u00eatements. Maroquinerie and articles de voyage",
    "sg:phone":"+32 59 50 43 00",
    "sg:postcode":"8400",
    "sg:province":"West-Vlaanderen",
    "wof:name":"Kipling",
    "wof:placetype":"venue"
},
  "geometry": {"coordinates":[2.9199440479,51.2290878296],"type":"Point"}
}