{
  "type": "Feature",
  "properties": {
    "addr:full":"Overdemerstraat 9 Hasselt Limburg 3511",
    "addr:housenumber":"9",
    "addr:postcode":"3511",
    "addr:street":"Overdemerstraat",
    "iso:country":"BE",
    "sg:address":"Overdemerstraat 9",
    "sg:city":"Hasselt",
    "sg:orig_category":"Services pour animaux domestiques",
    "sg:phone":"+32 11 25 50 06",
    "sg:postcode":"3511",
    "sg:province":"Limburg",
    "wof:name":"Hondenkapsalon Marouf",
    "wof:placetype":"venue"
},
  "geometry": {"coordinates":[5.3076229095,50.9467391968],"type":"Point"}
}