{
  "type": "Feature",
  "properties": {
    "addr:full":"Koningin Astridlaan 13 Box 2 Lier Antwerpen 2500",
    "addr:housenumber":"13;2",
    "addr:postcode":"2500",
    "addr:street":"Koningin Astridlaan;Box",
    "iso:country":"BE",
    "sg:address":"Koningin Astridlaan 13 Box 2",
    "sg:city":"Lier",
    "sg:classifiers":[
        {
            "category":"Insurance",
            "subcategory":"Insurance Agent",
            "type":"Services"
        }
    ],
    "sg:phone":"+32 3 480 15 00",
    "sg:postcode":"2500",
    "sg:province":"Antwerpen",
    "sg:tags":[
        "broker"
    ],
    "wof:name":"Van Orshaegen F",
    "wof:placetype":"venue"
},
  "geometry": {"coordinates":[4.577504158,51.1279373169],"type":"Point"}
}