{
  "type": "Feature",
  "properties": {
    "iso:country":"BE",
    "sg:address":"Rue De Marcinelle 15",
    "sg:city":"Charleroi",
    "sg:orig_category":"Agences de voyages",
    "sg:phone":"+32 71 31 50 91",
    "sg:postcode":"6000",
    "sg:province":"Hainaut",
    "wof:name":"B.b.l Tickets",
    "wof:placetype":"venue"
},
  "geometry": {"coordinates":[4.4430098534,50.4070396423],"type":"Point"}
}