{
  "type": "Feature",
  "properties": {
    "addr:full":"Moststraat 1 Staden (oostnieuwkerke) West-Vlaanderen 8840",
    "addr:housenumber":"1",
    "addr:postcode":"8840",
    "addr:street":"Moststraat",
    "iso:country":"BE",
    "sg:address":"Moststraat 1",
    "sg:city":"Staden (oostnieuwkerke)",
    "sg:classifiers":[
        {
            "category":"Personal",
            "subcategory":"Beauty Salon",
            "type":"Services"
        }
    ],
    "sg:phone":"+32 51 20 15 71",
    "sg:postcode":"8840",
    "sg:province":"West-Vlaanderen",
    "sg:tags":[
        "lady",
        "-",
        "hairdressing"
    ],
    "wof:name":"Sabine",
    "wof:placetype":"venue"
},
  "geometry": {"coordinates":[3.0767099857,50.9423484802],"type":"Point"}
}