{
  "type": "Feature",
  "properties": {
    "addr:full":"Zandstraat 60 Turnhout Antwerpen 2300",
    "addr:housenumber":"60",
    "addr:postcode":"2300",
    "addr:street":"Zandstraat",
    "iso:country":"BE",
    "sg:address":"Zandstraat 60",
    "sg:city":"Turnhout",
    "sg:classifiers":[
        {
            "category":"Building & Trades",
            "subcategory":"Landscaping Services",
            "type":"Services"
        }
    ],
    "sg:phone":"+32 14 42 19 83",
    "sg:postcode":"2300",
    "sg:province":"Antwerpen",
    "sg:tags":[
        "handicraft"
    ],
    "wof:name":"Sant (het)",
    "wof:placetype":"venue"
},
  "geometry": {"coordinates":[4.9334979057,51.320514679],"type":"Point"}
}