{
  "type": "Feature",
  "properties": {
    "iso:country":"BE",
    "sg:address":"Rue De Laeken 169",
    "sg:city":"Brussel/bruxelles",
    "sg:orig_category":"Boucheries",
    "sg:phone":"+32 2 217 24 55",
    "sg:postcode":"1000",
    "sg:province":"Bruxelles-Capitale",
    "wof:name":"Boucherie Olbrechts",
    "wof:placetype":"venue"
},
  "geometry": {"coordinates":[4.352602005,50.8558006287],"type":"Point"}
}