{
  "type": "Feature",
  "properties": {
    "iso:country":"BE",
    "sg:address":"Rue Du Bois 13",
    "sg:city":"Ittre",
    "sg:classifiers":[
        {
            "category":"Retail",
            "subcategory":"Animal Services",
            "type":"Services"
        }
    ],
    "sg:phone":"+32 67 64 72 84",
    "sg:postcode":"1460",
    "sg:province":"Brabant Wallon",
    "sg:tags":[
        "grooming",
        "-",
        "dog"
    ],
    "wof:name":"Corine",
    "wof:placetype":"venue"
},
  "geometry": {"coordinates":[4.2403540611,50.6577262878],"type":"Point"}
}