{
  "type": "Feature",
  "properties": {
    "iso:country":"BE",
    "sg:address":"Faubourg-saint-germain 27",
    "sg:city":"Couvin",
    "sg:orig_category":"Reisbureaus",
    "sg:phone":"+32 60 34 44 98",
    "sg:postcode":"5660",
    "sg:province":"Namur",
    "wof:name":"Couvy-tour Voyages",
    "wof:placetype":"venue"
},
  "geometry": {"coordinates":[4.493929863,50.0523834229],"type":"Point"}
}