{
  "type": "Feature",
  "properties": {
    "addr:full":"Beerzelstraat 17b Putte Antwerpen 2580",
    "addr:housenumber":"17b",
    "addr:postcode":"2580",
    "addr:street":"Beerzelstraat",
    "iso:country":"BE",
    "sg:address":"Beerzelstraat 17b",
    "sg:city":"Putte",
    "sg:orig_category":"Plomberie, chauffage and installations sanitaires",
    "sg:phone":"+32 15 75 76 96",
    "sg:postcode":"2580",
    "sg:province":"Antwerpen",
    "wof:name":"Op De Beeck",
    "wof:placetype":"venue"
},
  "geometry": {"coordinates":[4.6791300774,51.050163269],"type":"Point"}
}