{
  "type": "Feature",
  "properties": {
    "iso:country":"BE",
    "sg:address":"Chauss\u00e9e De Gilly 110",
    "sg:city":"Charleroi (jumet)",
    "sg:classifiers":[
        {
            "category":"Health Services",
            "subcategory":"Health Practitioner",
            "type":"Services"
        }
    ],
    "sg:phone":"+32 71 35 03 38",
    "sg:postcode":"6040",
    "sg:province":"Hainaut",
    "sg:tags":[
        "physiotherapist"
    ],
    "wof:name":"Lemaire B",
    "wof:placetype":"venue"
},
  "geometry": {"coordinates":[4.449160099,50.4414978027],"type":"Point"}
}