{
  "type": "Feature",
  "properties": {
    "iso:country":"BE",
    "sg:address":"Sint-denijsplein 67",
    "sg:city":"Vorst/forest",
    "sg:classifiers":[
        {
            "category":"Cafe",
            "type":"Food & Drink"
        }
    ],
    "sg:phone":"+32 2 376 05 62",
    "sg:postcode":"1190",
    "sg:province":"Bruxelles-Capitale",
    "sg:tags":[
        "caf\u00e9s"
    ],
    "wof:name":"Caf\u00c9 Au Ballon",
    "wof:placetype":"venue"
},
  "geometry": {"coordinates":[4.3175292015,50.8097229004],"type":"Point"}
}