{
  "type": "Feature",
  "properties": {
    "iso:country":"BE",
    "sg:address":"Grote Steenweg 65",
    "sg:city":"Zulte",
    "sg:orig_category":"Slagers",
    "sg:phone":"+32 9 388 45 15",
    "sg:postcode":"9870",
    "sg:province":"Oost-Vlaanderen",
    "wof:name":"Kris Vererfven",
    "wof:placetype":"venue"
},
  "geometry": {"coordinates":[3.467730999,50.9376411438],"type":"Point"}
}