{
  "type": "Feature",
  "properties": {
    "addr:full":"Gouverneur Verwilghensingel 32 Hasselt Limburg 3500",
    "addr:housenumber":"32",
    "addr:postcode":"3500",
    "addr:street":"Gouverneur Verwilghensingel",
    "iso:country":"BE",
    "sg:address":"Gouverneur Verwilghensingel 32",
    "sg:city":"Hasselt",
    "sg:classifiers":[
        {
            "category":"Autos & Motor Vehicles",
            "subcategory":"Fuel & Gas Station",
            "type":"Retail Goods"
        }
    ],
    "sg:phone":"+32 11 72 26 00",
    "sg:postcode":"3500",
    "sg:province":"Limburg",
    "sg:tags":[
        "electricity",
        "supply"
    ],
    "wof:name":"Luminus",
    "wof:placetype":"venue"
},
  "geometry": {"coordinates":[5.3585710526,50.9281997681],"type":"Point"}
}