{
  "type": "Feature",
  "properties": {
    "iso:country":"BE",
    "sg:address":"Excelsiorlaan 32-34",
    "sg:city":"Zaventem",
    "sg:classifiers":[
        {
            "category":"Professional",
            "subcategory":"Management & Consulting",
            "type":"Services"
        }
    ],
    "sg:phone":"+32 2 725 23 24",
    "sg:postcode":"1930",
    "sg:province":"Vlaams-Brabant",
    "sg:tags":[
        "consultant"
    ],
    "wof:name":"Xansa Nv",
    "wof:placetype":"venue"
},
  "geometry": {"coordinates":[4.456433773,50.8846168518],"type":"Point"}
}