{
  "type": "Feature",
  "properties": {
    "addr:full":"Trapstraat 77 Geraardsbergen Oost-Vlaanderen 9500",
    "addr:housenumber":"77",
    "addr:postcode":"9500",
    "addr:street":"Trapstraat",
    "iso:country":"BE",
    "sg:address":"Trapstraat 77",
    "sg:city":"Geraardsbergen",
    "sg:classifiers":[
        {
            "category":"Cafe",
            "type":"Food & Drink"
        }
    ],
    "sg:phone":"+32 54 58 88 46",
    "sg:postcode":"9500",
    "sg:province":"Oost-Vlaanderen",
    "sg:tags":[
        "caf\u00e9s"
    ],
    "wof:name":"Krikilion-lamont",
    "wof:placetype":"venue"
},
  "geometry": {"coordinates":[3.9128708839,50.7333221436],"type":"Point"}
}