{
  "type": "Feature",
  "properties": {
    "addr:full":"Avenue De Villegas 41 Bruxelles (ganshoren) Bruxelles-Capitale 1083",
    "addr:housenumber":"41",
    "addr:postcode":"1083",
    "addr:street":"Avenue De Villegas",
    "iso:country":"BE",
    "sg:address":"Avenue De Villegas 41",
    "sg:city":"Bruxelles (ganshoren)",
    "sg:classifiers":[
        {
            "category":"Professional",
            "subcategory":"Lawyer & Legal Services",
            "type":"Services"
        }
    ],
    "sg:phone":"+32 2 465 02 80",
    "sg:postcode":"1083",
    "sg:province":"Bruxelles-Capitale",
    "wof:name":"Vanneste Yvette",
    "wof:placetype":"venue"
},
  "geometry": {"coordinates":[4.308619976,50.8710098267],"type":"Point"}
}