{
  "type": "Feature",
  "properties": {
    "iso:country":"BE",
    "sg:address":"Putlaan 44",
    "sg:city":"Edegem",
    "sg:classifiers":[
        {
            "category":"Personal",
            "subcategory":"Beauty Salon",
            "type":"Services"
        }
    ],
    "sg:phone":"+32 3 457 42 53",
    "sg:postcode":"2650",
    "sg:province":"Antwerpen",
    "wof:name":"Lane Schoonheidsinstituut",
    "wof:placetype":"venue"
},
  "geometry": {"coordinates":[4.4563140869,51.1512832642],"type":"Point"}
}