{
  "type": "Feature",
  "properties": {
    "iso:country":"BE",
    "sg:address":"Av De L'esp\u00e9rance Zi",
    "sg:city":"Fleurus",
    "sg:classifiers":[
        {
            "category":"Food & Beverages",
            "subcategory":"Groceries & Convenience Stores",
            "type":"Retail Goods"
        }
    ],
    "sg:phone":"+32 71 85 85 95",
    "sg:postcode":"6220",
    "sg:province":"Hainaut",
    "sg:tags":[
        "product",
        "related"
    ],
    "wof:name":"Becco Confiserie Sa",
    "wof:placetype":"venue"
},
  "geometry": {"coordinates":[4.5313301086,50.4716911316],"type":"Point"}
}