{
  "type": "Feature",
  "properties": {
    "iso:country":"BE",
    "sg:address":"Ottergemsesteenweg 155",
    "sg:city":"Gent",
    "sg:orig_category":"Enseignement maternel and primaire",
    "sg:phone":"+32 9 221 45 45",
    "sg:postcode":"9000",
    "sg:province":"Oost-Vlaanderen",
    "wof:name":"Vrije Basisschool",
    "wof:placetype":"venue"
},
  "geometry": {"coordinates":[3.7284419537,51.0338859558],"type":"Point"}
}