{
  "type": "Feature",
  "properties": {
    "addr:full":"Ballewijerweg 23 Zonhoven Limburg 3520",
    "addr:housenumber":"23",
    "addr:postcode":"3520",
    "addr:street":"Ballewijerweg",
    "iso:country":"BE",
    "sg:address":"Ballewijerweg 23",
    "sg:city":"Zonhoven",
    "sg:classifiers":[
        {
            "category":"Retail",
            "subcategory":"Repair Shop",
            "type":"Services"
        }
    ],
    "sg:phone":"+32 11 81 39 55",
    "sg:postcode":"3520",
    "sg:province":"Limburg",
    "sg:tags":[
        "radio",
        "television",
        "-",
        "maintenance"
    ],
    "wof:name":"Achten H",
    "wof:placetype":"venue"
},
  "geometry": {"coordinates":[5.3943400383,50.9875488281],"type":"Point"}
}