{
  "type": "Feature",
  "properties": {
    "addr:full":"Avenue Du Prince H\u00c9ritier 66 Sint-lambrechts-woluwe/woluwe-saint-lambert Bruxelles-Capitale 1200",
    "addr:housenumber":"66",
    "addr:postcode":"1200",
    "addr:street":"Avenue Du Prince He\u0301Ritier",
    "iso:country":"BE",
    "sg:address":"Avenue Du Prince H\u00c9ritier 66",
    "sg:city":"Sint-lambrechts-woluwe/woluwe-saint-lambert",
    "sg:orig_category":"Laboratoires photographiques",
    "sg:phone":"+32 2 733 21 29",
    "sg:postcode":"1200",
    "sg:province":"Bruxelles-Capitale",
    "wof:name":"Laboratoire Rottier",
    "wof:placetype":"venue"
},
  "geometry": {"coordinates":[4.4110078812,50.8426361084],"type":"Point"}
}