{
  "type": "Feature",
  "properties": {
    "addr:full":"Rue Royale Sainte-marie 23-25 Bruxelles (schaerbeek) Bruxelles-Capitale 1030",
    "addr:postcode":"23-25;1030",
    "addr:street":"Rue Royale",
    "iso:country":"BE",
    "sg:address":"Rue Royale Sainte-marie 23-25",
    "sg:city":"Bruxelles (schaerbeek)",
    "sg:classifiers":[
        {
            "category":"Shopping",
            "subcategory":"Crafts & Fabrics",
            "type":"Retail Goods"
        }
    ],
    "sg:phone":"+32 2 219 69 03",
    "sg:postcode":"1030",
    "sg:province":"Bruxelles-Capitale",
    "sg:tags":[
        "paints",
        "varnish",
        "-",
        "lacquers",
        "enamel"
    ],
    "wof:name":"4k-d\u00e9cor",
    "wof:placetype":"venue"
},
  "geometry": {"coordinates":[4.3690748215,50.8600769043],"type":"Point"}
}