{
  "type": "Feature",
  "properties": {
    "iso:country":"BE",
    "sg:address":"Maastrichtsesteenweg 167",
    "sg:city":"Tongeren",
    "sg:orig_category":"Grands magasins",
    "sg:phone":"+32 14380",
    "sg:postcode":"3700",
    "sg:province":"Limburg",
    "wof:name":"Lidl",
    "wof:placetype":"venue"
},
  "geometry": {"coordinates":[5.4817838669,50.7840194702],"type":"Point"}
}