{
  "type": "Feature",
  "properties": {
    "addr:full":"Merelstraat 11 Jabbeke West-Vlaanderen 8490",
    "addr:housenumber":"11",
    "addr:postcode":"8490",
    "addr:street":"Merelstraat",
    "iso:country":"BE",
    "sg:address":"Merelstraat 11",
    "sg:city":"Jabbeke",
    "sg:orig_category":"Boomkwekerijen",
    "sg:phone":"+32 50 81 26 68",
    "sg:postcode":"8490",
    "sg:province":"West-Vlaanderen",
    "wof:name":"Michel Darras",
    "wof:placetype":"venue"
},
  "geometry": {"coordinates":[3.089799881,51.1855735779],"type":"Point"}
}