{
  "type": "Feature",
  "properties": {
    "addr:full":"Doornweg 63 Wichelen Oost-Vlaanderen 9260",
    "addr:housenumber":"63",
    "addr:postcode":"9260",
    "addr:street":"Doornweg",
    "iso:country":"BE",
    "sg:address":"Doornweg 63",
    "sg:city":"Wichelen",
    "sg:classifiers":[
        {
            "category":"Shopping",
            "subcategory":"Clothing, Apparel, & Fashions",
            "type":"Retail Goods"
        }
    ],
    "sg:phone":"+32 52 42 36 63",
    "sg:postcode":"9260",
    "sg:province":"Oost-Vlaanderen",
    "sg:tags":[
        "lady",
        "clothing",
        "-"
    ],
    "wof:name":"Porseleynhuys (het)",
    "wof:placetype":"venue"
},
  "geometry": {"coordinates":[3.9752089977,51.003868103],"type":"Point"}
}