{
  "type": "Feature",
  "properties": {
    "iso:country":"BE",
    "sg:address":"Chaussee De Ninove 591",
    "sg:city":"Bruxelles",
    "sg:classifiers":[
        {
            "category":"Manufacturing",
            "subcategory":"Tools & Machinery",
            "type":"Manufacturing & Wholesale Goods"
        }
    ],
    "sg:phone":"+32 2 411 70 40",
    "sg:postcode":"1070",
    "sg:province":"Bruxelles-Capitale",
    "sg:tags":[
        "machine",
        "allround",
        "turning",
        "milling",
        "drilling"
    ],
    "wof:name":"Tecmo S.a.",
    "wof:placetype":"venue"
},
  "geometry": {"coordinates":[4.3000202179,50.8471412659],"type":"Point"}
}