{
  "type": "Feature",
  "properties": {
    "iso:country":"BE",
    "sg:address":"Luikstraat 30",
    "sg:city":"Lokeren",
    "sg:classifiers":[
        {
            "category":"Real Estate",
            "subcategory":"Architect",
            "type":"Services"
        }
    ],
    "sg:phone":"+32 9 348 14 74",
    "sg:postcode":"9160",
    "sg:province":"Oost-Vlaanderen",
    "wof:name":"Daens M",
    "wof:placetype":"venue"
},
  "geometry": {"coordinates":[3.9926309586,51.1020050049],"type":"Point"}
}