{
  "type": "Feature",
  "properties": {
    "iso:country":"BE",
    "sg:address":"Donkerstraat 20",
    "sg:city":"Huldenberg",
    "sg:orig_category":"Rev\u00eatements pour sols and murs",
    "sg:phone":"+32 16 47 78 53",
    "sg:postcode":"3040",
    "sg:province":"Vlaams-Brabant",
    "wof:name":"K.l.e.v.",
    "wof:placetype":"venue"
},
  "geometry": {"coordinates":[4.6170377731,50.8222465515],"type":"Point"}
}