{
  "type": "Feature",
  "properties": {
    "iso:country":"BE",
    "sg:address":"Place Pinoy 8b2",
    "sg:city":"Oudergem/auderghem",
    "sg:orig_category":"Computers and computerapparatuur Onderhoud van kantoor- and computeruitrusting Tweedehandsgoederen",
    "sg:phone":"+32 2 675 94 90",
    "sg:postcode":"1160",
    "sg:province":"Bruxelles-Capitale",
    "wof:name":"Tout-o.k.",
    "wof:placetype":"venue"
},
  "geometry": {"coordinates":[4.4251499176,50.8167381287],"type":"Point"}
}