{
  "type": "Feature",
  "properties": {
    "addr:full":"Van Schoonbekestraat 26 Antwerpen Antwerpen 2018",
    "addr:housenumber":"26",
    "addr:postcode":"2018",
    "addr:street":"Van Schoonbekestraat",
    "iso:country":"BE",
    "sg:address":"Van Schoonbekestraat 26",
    "sg:city":"Antwerpen",
    "sg:classifiers":[
        {
            "category":"Arts & Performance",
            "subcategory":"Art Gallery",
            "type":"Entertainment"
        }
    ],
    "sg:phone":"+32 3 238 98 37",
    "sg:postcode":"2018",
    "sg:province":"Antwerpen",
    "wof:name":"Campo Carine Gallery",
    "wof:placetype":"venue"
},
  "geometry": {"coordinates":[4.4086618423,51.2038726807],"type":"Point"}
}