{
  "type": "Feature",
  "properties": {
    "addr:full":"Rue Du Centre 13 Aywaille Li\u00e8ge 4920",
    "addr:housenumber":"13",
    "addr:postcode":"4920",
    "addr:street":"Rue Du Centre",
    "iso:country":"BE",
    "sg:address":"Rue Du Centre 13",
    "sg:city":"Aywaille",
    "sg:classifiers":[
        {
            "category":"Food & Beverages",
            "subcategory":"Groceries & Convenience Stores",
            "type":"Retail Goods"
        }
    ],
    "sg:phone":"+32 4 384 53 41",
    "sg:postcode":"4920",
    "sg:province":"Li\u00e8ge",
    "sg:tags":[
        "grocer"
    ],
    "wof:name":"Louon",
    "wof:placetype":"venue"
},
  "geometry": {"coordinates":[5.6773052216,50.4735450745],"type":"Point"}
}