{
  "type": "Feature",
  "properties": {
    "iso:country":"BE",
    "sg:address":"Aarschotsebaan 298",
    "sg:city":"Berlaar",
    "sg:orig_category":"Antiek Tweedehandsgoederen",
    "sg:phone":"+32 3 482 03 30",
    "sg:postcode":"2590",
    "sg:province":"Antwerpen",
    "wof:name":"Jachtliteratuur Bongers",
    "wof:placetype":"venue"
},
  "geometry": {"coordinates":[4.6392049789,51.087802887],"type":"Point"}
}