{
  "type": "Feature",
  "properties": {
    "iso:country":"BE",
    "sg:address":"Steenweg Op Bergen 747",
    "sg:city":"Sint-pieters-leeuw",
    "sg:orig_category":"Rev\u00eatements de sols and murs. Quincailleries",
    "sg:phone":"+32 2 356 30 76",
    "sg:postcode":"1600",
    "sg:province":"Vlaams-Brabant",
    "wof:name":"Tapis Land",
    "wof:placetype":"venue"
},
  "geometry": {"coordinates":[4.2521281242,50.7611846924],"type":"Point"}
}