{
  "type": "Feature",
  "properties": {
    "addr:full":"Korenbloemstraat 137 Torhout West-Vlaanderen 8820",
    "addr:housenumber":"137",
    "addr:postcode":"8820",
    "addr:street":"Korenbloemstraat",
    "iso:country":"BE",
    "sg:address":"Korenbloemstraat 137",
    "sg:city":"Torhout",
    "sg:orig_category":"Rundveehouders Varkenskwekers",
    "sg:phone":"+32 50 27 82 91",
    "sg:postcode":"8820",
    "sg:province":"West-Vlaanderen",
    "wof:name":"Stefaan Dedeene",
    "wof:placetype":"venue"
},
  "geometry": {"coordinates":[3.1520009041,51.0835189819],"type":"Point"}
}