{
  "type": "Feature",
  "properties": {
    "iso:country":"BE",
    "sg:address":"Steenweg Op Mol 51",
    "sg:city":"Oud-turnhout",
    "sg:classifiers":[
        {
            "category":"Home & Garden",
            "subcategory":"Carpets & Floor Coverings",
            "type":"Retail Goods"
        }
    ],
    "sg:phone":"+32 495 20 67 58",
    "sg:postcode":"2360",
    "sg:province":"Antwerpen",
    "sg:tags":[
        "tile"
    ],
    "wof:name":"D & G Bvba",
    "wof:placetype":"venue"
},
  "geometry": {"coordinates":[4.9860348701,51.315990448],"type":"Point"}
}