{
  "type": "Feature",
  "properties": {
    "iso:country":"BE",
    "sg:address":"Elegemstraat 85",
    "sg:city":"Dilbeek",
    "sg:classifiers":[
        {
            "category":"Insurance",
            "subcategory":"Insurance Agent",
            "type":"Services"
        }
    ],
    "sg:phone":"+32 2 463 58 88",
    "sg:postcode":"1700",
    "sg:province":"Vlaams-Brabant",
    "sg:tags":[
        "verzekeringsmakelaars",
        "expert"
    ],
    "wof:name":"Y. Wathelet",
    "wof:placetype":"venue"
},
  "geometry": {"coordinates":[4.2626481056,50.8601074219],"type":"Point"}
}