{
  "type": "Feature",
  "properties": {
    "iso:country":"BE",
    "sg:address":"Chemin De La Craie 2",
    "sg:city":"Baelen",
    "sg:classifiers":[
        {
            "category":"Arena",
            "subcategory":"Sports Club",
            "type":"Entertainment"
        }
    ],
    "sg:phone":"+32 87 76 25 61",
    "sg:postcode":"4837",
    "sg:province":"Li\u00e8ge",
    "sg:tags":[
        "de"
    ],
    "wof:name":"Royal Dison Motor Club",
    "wof:placetype":"venue"
},
  "geometry": {"coordinates":[5.9535489082,50.6246910095],"type":"Point"}
}