{
  "type": "Feature",
  "properties": {
    "iso:country":"BE",
    "sg:address":"Wiedauwkaai 81",
    "sg:city":"Gent",
    "sg:orig_category":"Voertuigen",
    "sg:phone":"+32 9 253 86 71",
    "sg:postcode":"9000",
    "sg:province":"Oost-Vlaanderen",
    "wof:name":"Comadis",
    "wof:placetype":"venue"
},
  "geometry": {"coordinates":[3.7254099846,51.077129364],"type":"Point"}
}