{
  "type": "Feature",
  "properties": {
    "iso:country":"BE",
    "sg:address":"Rue Haute 22",
    "sg:city":"Anhee",
    "sg:classifiers":[
        {
            "category":"Personal",
            "subcategory":"Beauty Salon",
            "type":"Services"
        }
    ],
    "sg:phone":"+32 71 79 92 30",
    "sg:postcode":"5537",
    "sg:province":"Namur",
    "sg:tags":[
        "de",
        "coiffure"
    ],
    "wof:name":"Coiffure Nathalie",
    "wof:placetype":"venue"
},
  "geometry": {"coordinates":[4.7489690781,50.3185806274],"type":"Point"}
}