{
  "type": "Feature",
  "properties": {
    "addr:full":"Rue De Tamines 5 Bruxelles (saint-gilles) Bruxelles-Capitale 1060",
    "addr:housenumber":"5",
    "addr:postcode":"1060",
    "addr:street":"Rue De Tamines",
    "iso:country":"BE",
    "sg:address":"Rue De Tamines 5",
    "sg:city":"Bruxelles (saint-gilles)",
    "sg:classifiers":[
        {
            "category":"Social Services",
            "subcategory":"Child Care",
            "type":"Services"
        }
    ],
    "sg:phone":"+32 2 538 07 73",
    "sg:postcode":"1060",
    "sg:province":"Bruxelles-Capitale",
    "sg:tags":[
        "baby",
        "nursery",
        "day",
        "sitting"
    ],
    "wof:name":"Nounours",
    "wof:placetype":"venue"
},
  "geometry": {"coordinates":[4.3481521606,50.8264541626],"type":"Point"}
}