{
  "type": "Feature",
  "properties": {
    "iso:country":"BE",
    "sg:address":"Bouwerijstraat 2",
    "sg:city":"Hemiksem",
    "sg:orig_category":"Non-Classified Establishments",
    "sg:phone":"+32 3 870 81 93",
    "sg:postcode":"2620",
    "sg:province":"Antwerpen",
    "wof:name":"Catena Bvba",
    "wof:placetype":"venue"
},
  "geometry": {"coordinates":[4.3386368752,51.1359519958],"type":"Point"}
}