{
  "type": "Feature",
  "properties": {
    "addr:full":"Rue Biscaille 2 Estinnes Hainaut 7120",
    "addr:housenumber":"2",
    "addr:postcode":"7120",
    "addr:street":"Rue Biscaille",
    "iso:country":"BE",
    "sg:address":"Rue Biscaille 2",
    "sg:city":"Estinnes",
    "sg:orig_category":"Rundveehouders",
    "sg:phone":"+32 64 33 28 29",
    "sg:postcode":"7120",
    "sg:province":"Hainaut",
    "wof:name":"Marc Belot",
    "wof:placetype":"venue"
},
  "geometry": {"coordinates":[4.1004390717,50.3782844543],"type":"Point"}
}