{
  "type": "Feature",
  "properties": {
    "iso:country":"BE",
    "sg:address":"Les Heures-claires 30b3",
    "sg:city":"Nivelles",
    "sg:orig_category":"M\u00e9decins and sp\u00e9cialistes",
    "sg:phone":"+32 67 84 01 44",
    "sg:postcode":"1400",
    "sg:province":"Brabant Wallon",
    "wof:name":"Martine Liegeois",
    "wof:placetype":"venue"
},
  "geometry": {"coordinates":[4.3327150345,50.6047134399],"type":"Point"}
}