{
  "type": "Feature",
  "properties": {
    "addr:full":"Albert Van Dyckstraat 39 Turnhout Antwerpen 2300",
    "addr:housenumber":"39",
    "addr:postcode":"2300",
    "addr:street":"Albert Van Dyckstraat",
    "iso:country":"BE",
    "sg:address":"Albert Van Dyckstraat 39",
    "sg:city":"Turnhout",
    "sg:orig_category":"Rusthuizen and serviceflats",
    "sg:phone":"+32 14 43 72 00",
    "sg:postcode":"2300",
    "sg:province":"Antwerpen",
    "wof:name":"R.v.t. St.petrus",
    "wof:placetype":"venue"
},
  "geometry": {"coordinates":[4.9413900375,51.3156700134],"type":"Point"}
}