{
  "type": "Feature",
  "properties": {
    "iso:country":"BE",
    "sg:address":"Molenstraat 52",
    "sg:city":"Boom",
    "sg:classifiers":[
        {
            "category":"Fast Food",
            "type":"Food & Drink"
        }
    ],
    "sg:phone":"+32 3 843 31 13",
    "sg:postcode":"2850",
    "sg:province":"Antwerpen",
    "sg:tags":[
        "fried",
        "stand",
        "potato"
    ],
    "wof:name":"Frit Cuic",
    "wof:placetype":"venue"
},
  "geometry": {"coordinates":[4.3695402145,51.0910797119],"type":"Point"}
}