{
  "type": "Feature",
  "properties": {
    "iso:country":"BE",
    "sg:address":"Vlasgaardstraat 18",
    "sg:city":"Izegem",
    "sg:orig_category":"Elektrische installaties voor woningen Procesbesturingssystemen Fab",
    "sg:phone":"+32 51 31 82 47",
    "sg:postcode":"8870",
    "sg:province":"West-Vlaanderen",
    "wof:name":"Decavan",
    "wof:placetype":"venue"
},
  "geometry": {"coordinates":[3.2145500183,50.9104385376],"type":"Point"}
}