{
  "type": "Feature",
  "properties": {
    "addr:full":"Rue Du Vivier 152 Bastogne Luxembourg 6600",
    "addr:housenumber":"152",
    "addr:postcode":"6600",
    "addr:street":"Rue Du Vivier",
    "iso:country":"BE",
    "sg:address":"Rue Du Vivier 152",
    "sg:city":"Bastogne",
    "sg:classifiers":[
        {
            "category":"Shopping",
            "subcategory":"Florist",
            "type":"Retail Goods"
        }
    ],
    "sg:phone":"+32 61 21 79 04",
    "sg:postcode":"6600",
    "sg:province":"Luxembourg",
    "wof:name":"Jardins De Monaco (aux)",
    "wof:placetype":"venue"
},
  "geometry": {"coordinates":[5.7173857689,50.0019989014],"type":"Point"}
}