{
  "type": "Feature",
  "properties": {
    "iso:country":"BE",
    "sg:address":"Nieuwe Kouterstraat 88",
    "sg:city":"Bornem",
    "sg:classifiers":[
        {
            "category":"Health Services",
            "subcategory":"Health Practitioner",
            "type":"Services"
        }
    ],
    "sg:phone":"+32 3 899 19 49",
    "sg:postcode":"2880",
    "sg:province":"Antwerpen",
    "sg:tags":[
        "physiotherapist"
    ],
    "wof:name":"Robberecht Luc",
    "wof:placetype":"venue"
},
  "geometry": {"coordinates":[4.2374382019,51.0966453552],"type":"Point"}
}