{
  "type": "Feature",
  "properties": {
    "iso:country":"BE",
    "sg:address":"Heikempstraat 1116",
    "sg:city":"Kinrooi (molenbeersel)",
    "sg:orig_category":"Non-Classified Establishments",
    "sg:phone":"+32 89 70 30 14",
    "sg:postcode":"3640",
    "sg:province":"Limburg",
    "wof:name":"Benningen Nv",
    "wof:placetype":"venue"
},
  "geometry": {"coordinates":[5.7236762047,51.1802139282],"type":"Point"}
}