{
  "type": "Feature",
  "properties": {
    "iso:country":"BE",
    "sg:address":"Rue Arthur Pollet 9",
    "sg:city":"Manage",
    "sg:classifiers":[
        {
            "category":"Professional",
            "subcategory":"Computer Services",
            "type":"Services"
        }
    ],
    "sg:phone":"+32 64 54 90 47",
    "sg:postcode":"7170",
    "sg:province":"Hainaut",
    "sg:tags":[
        "repair",
        "processing",
        "-",
        "maintenance",
        "data"
    ],
    "wof:name":"Computer Genius",
    "wof:placetype":"venue"
},
  "geometry": {"coordinates":[4.2303900719,50.5045890808],"type":"Point"}
}