{
  "type": "Feature",
  "properties": {
    "addr:full":"Bilzersteenweg 19 Hoeselt Limburg 3730",
    "addr:housenumber":"19",
    "addr:postcode":"3730",
    "addr:street":"Bilzersteenweg",
    "iso:country":"BE",
    "sg:address":"Bilzersteenweg 19",
    "sg:city":"Hoeselt",
    "sg:classifiers":[
        {
            "category":"Professional",
            "subcategory":"Art Services",
            "type":"Services"
        }
    ],
    "sg:phone":"+32 89 41 30 30",
    "sg:postcode":"3730",
    "sg:province":"Limburg",
    "sg:tags":[
        "photographer"
    ],
    "wof:name":"Foto Robert Baerten",
    "wof:placetype":"venue"
},
  "geometry": {"coordinates":[5.4930138588,50.8517303467],"type":"Point"}
}