{
  "type": "Feature",
  "properties": {
    "addr:full":"Rue Homvent 90 Saint-nicolas Li\u00e8ge 4420",
    "addr:housenumber":"90",
    "addr:postcode":"4420",
    "addr:street":"Rue Homvent",
    "iso:country":"BE",
    "sg:address":"Rue Homvent 90",
    "sg:city":"Saint-nicolas",
    "sg:classifiers":[
        {
            "category":"Food & Beverages",
            "subcategory":"Fruits & Vegetables",
            "type":"Retail Goods"
        }
    ],
    "sg:phone":"+32 4 235 13 13",
    "sg:postcode":"4420",
    "sg:province":"Li\u00e8ge",
    "sg:tags":[
        "l\u00e9gumes",
        "gr"
    ],
    "wof:name":"Meli Parlascino",
    "wof:placetype":"venue"
},
  "geometry": {"coordinates":[5.5216498375,50.629360199],"type":"Point"}
}