{
  "type": "Feature",
  "properties": {
    "addr:full":"Rue Jacques Jansen 1 Bruxelles (schaerbeek) Bruxelles-Capitale 1030",
    "addr:housenumber":"1",
    "addr:postcode":"1030",
    "addr:street":"Rue Jacques Jansen",
    "iso:country":"BE",
    "sg:address":"Rue Jacques Jansen 1",
    "sg:city":"Bruxelles (schaerbeek)",
    "sg:classifiers":[
        {
            "category":"Restaurant",
            "type":"Food & Drink"
        }
    ],
    "sg:phone":"+32 2 736 54 25",
    "sg:postcode":"1030",
    "sg:province":"Bruxelles-Capitale",
    "sg:tags":[
        "pasta"
    ],
    "wof:name":"Dongigi",
    "wof:placetype":"venue"
},
  "geometry": {"coordinates":[4.3883461952,50.8533172607],"type":"Point"}
}