{
  "type": "Feature",
  "properties": {
    "addr:full":"Prof. Rubbrechtstraat 35 Poperinge West-Vlaanderen 8972",
    "addr:housenumber":"35",
    "addr:postcode":"8972",
    "addr:street":"Rubbrechtstraat",
    "iso:country":"BE",
    "sg:address":"Prof. Rubbrechtstraat 35",
    "sg:city":"Poperinge",
    "sg:orig_category":"Brood, gebak and snoepgoed Zuivelproducten",
    "sg:phone":"+32 57 30 16 45",
    "sg:postcode":"8972",
    "sg:province":"West-Vlaanderen",
    "wof:name":"Bakkerij Verhaeghe",
    "wof:placetype":"venue"
},
  "geometry": {"coordinates":[2.6249849796,50.9184913635],"type":"Point"}
}