{
  "type": "Feature",
  "properties": {
    "addr:full":"Magdalenastraat Kontich Antwerpen 2550",
    "addr:postcode":"2550",
    "addr:street":"Magdalenastraat",
    "iso:country":"BE",
    "sg:address":"Magdalenastraat",
    "sg:city":"Kontich",
    "sg:classifiers":[
        {
            "category":"Arena",
            "subcategory":"Sports Club",
            "type":"Entertainment"
        }
    ],
    "sg:phone":"+32 3 457 50 04",
    "sg:postcode":"2550",
    "sg:province":"Antwerpen",
    "sg:tags":[
        "de"
    ],
    "wof:name":"T.t.k. Martinus",
    "wof:placetype":"venue"
},
  "geometry": {"coordinates":[4.4459600449,51.1350784302],"type":"Point"}
}