{
  "type": "Feature",
  "properties": {
    "iso:country":"BE",
    "sg:address":"Industrieter. Daelemveld 1150",
    "sg:city":"Herk-de-stad",
    "sg:orig_category":"Airconditioning and ventilatie Elektrische installaties voor woningen Winkelinrichting and handelsui",
    "sg:phone":"+32 13 55 22 41",
    "sg:postcode":"3540",
    "sg:province":"Limburg",
    "wof:name":"Vos Technics",
    "wof:placetype":"venue"
},
  "geometry": {"coordinates":[5.1684780121,50.9474449158],"type":"Point"}
}