{
  "type": "Feature",
  "properties": {
    "iso:country":"BE",
    "sg:address":"Rue Des Vennes 38",
    "sg:city":"Liege",
    "sg:orig_category":"Diverse bedrijfsbeheeradviesbureaus",
    "sg:phone":"+32 4 341 01 80",
    "sg:postcode":"4020",
    "sg:province":"Li\u00e8ge",
    "wof:name":"B.s.b. Tandem",
    "wof:placetype":"venue"
},
  "geometry": {"coordinates":[5.5810770988,50.6280441284],"type":"Point"}
}