{
  "type": "Feature",
  "properties": {
    "addr:full":"Rue De Marchienne 114 Charleroi (mont-sur-marchienne) Hainaut 6032",
    "addr:housenumber":"114",
    "addr:postcode":"6032",
    "addr:street":"Rue De Marchienne",
    "iso:country":"BE",
    "sg:address":"Rue De Marchienne 114",
    "sg:city":"Charleroi (mont-sur-marchienne)",
    "sg:classifiers":[
        {
            "category":"Health Services",
            "subcategory":"Health Practitioner",
            "type":"Services"
        }
    ],
    "sg:phone":"+32 71 36 29 57",
    "sg:postcode":"6032",
    "sg:province":"Hainaut",
    "sg:tags":[
        "physiotherapist"
    ],
    "wof:name":"Mattot Luc",
    "wof:placetype":"venue"
},
  "geometry": {"coordinates":[4.4033741951,50.3946762085],"type":"Point"}
}