{
  "type": "Feature",
  "properties": {
    "iso:country":"BE",
    "sg:address":"Grav.mad D'alcantara Laan 5",
    "sg:city":"Lembeke",
    "sg:orig_category":"Royal Canin. Articles de jardin",
    "sg:phone":"+32 9 377 02 66",
    "sg:postcode":"9971",
    "sg:province":"Oost-Vlaanderen",
    "wof:name":"Betsens A",
    "wof:placetype":"venue"
},
  "geometry": {"coordinates":[3.6357600689,51.1942100525],"type":"Point"}
}