{
  "type": "Feature",
  "properties": {
    "iso:country":"BE",
    "sg:address":"Monsieur Callewaertlaan 3",
    "sg:city":"Zwevegem",
    "sg:orig_category":"R\u00e9alisation de programmes and logiciels",
    "sg:phone":"+32 56 75 90 13",
    "sg:postcode":"8550",
    "sg:province":"West-Vlaanderen",
    "wof:name":"Add - It - Solutions",
    "wof:placetype":"venue"
},
  "geometry": {"coordinates":[3.3291699886,50.8153800964],"type":"Point"}
}