{
  "type": "Feature",
  "properties": {
    "iso:country":"BE",
    "sg:address":"Molenstraat 138",
    "sg:city":"Kaprijke",
    "sg:classifiers":[
        {
            "category":"Manufacturing",
            "subcategory":"Tobacco Products",
            "type":"Manufacturing & Wholesale Goods"
        }
    ],
    "sg:phone":"+32 9 379 82 29",
    "sg:postcode":"9970",
    "sg:province":"Oost-Vlaanderen",
    "sg:tags":[
        "soil",
        "peat"
    ],
    "wof:name":"Snebbout Nv",
    "wof:placetype":"venue"
},
  "geometry": {"coordinates":[3.6141490936,51.2429618835],"type":"Point"}
}