{
  "type": "Feature",
  "properties": {
    "iso:country":"BE",
    "sg:address":"Monschauerstrasse 17",
    "sg:city":"Eupen/eupen",
    "sg:orig_category":"Sportclubs",
    "sg:phone":"+32 87 74 42 45",
    "sg:postcode":"4700",
    "sg:province":"Li\u00e8ge",
    "wof:name":"Eupener T.v. 1967",
    "wof:placetype":"venue"
},
  "geometry": {"coordinates":[6.0452342033,50.6192054749],"type":"Point"}
}