{
  "type": "Feature",
  "properties": {
    "addr:full":"Romont 38 Bi\u00e9v\u00e8ne Vlaams-Brabant 1547",
    "addr:housenumber":"38",
    "addr:postcode":"1547",
    "addr:street":"Romont",
    "iso:country":"BE",
    "sg:address":"Romont 38",
    "sg:city":"Bi\u00e9v\u00e8ne",
    "sg:classifiers":[
        {
            "category":"Manufacturing",
            "subcategory":"Metals",
            "type":"Manufacturing & Wholesale Goods"
        }
    ],
    "sg:phone":"+32 54 58 86 56",
    "sg:postcode":"1547",
    "sg:province":"Vlaams-Brabant",
    "sg:tags":[
        "ironwork"
    ],
    "wof:name":"Deker Cvba",
    "wof:placetype":"venue"
},
  "geometry": {"coordinates":[3.9354999065,50.693687439],"type":"Point"}
}