{
  "type": "Feature",
  "properties": {
    "addr:full":"Sint-annastraat 2 Zottegem Oost-Vlaanderen 9620",
    "addr:housenumber":"2",
    "addr:postcode":"9620",
    "addr:street":"Sint-Annastraat",
    "iso:country":"BE",
    "sg:address":"Sint-annastraat 2",
    "sg:city":"Zottegem",
    "sg:classifiers":[
        {
            "category":"Real Estate",
            "subcategory":"Architect",
            "type":"Services"
        }
    ],
    "sg:phone":"+32 9 360 20 58",
    "sg:postcode":"9620",
    "sg:province":"Oost-Vlaanderen",
    "wof:name":"Ostyn C",
    "wof:placetype":"venue"
},
  "geometry": {"coordinates":[3.8118340969,50.8673858643],"type":"Point"}
}