{
  "type": "Feature",
  "properties": {
    "iso:country":"BE",
    "sg:address":"Noordzandstraat 43",
    "sg:city":"Brugge",
    "sg:classifiers":[
        {
            "category":"Shopping",
            "subcategory":"Shoes",
            "type":"Retail Goods"
        }
    ],
    "sg:phone":"+32 50 34 08 80",
    "sg:postcode":"8000",
    "sg:province":"West-Vlaanderen",
    "sg:tags":[
        "slipper",
        "-"
    ],
    "wof:name":"Topolino",
    "wof:placetype":"venue"
},
  "geometry": {"coordinates":[3.2202310562,51.2073898315],"type":"Point"}
}