{
  "type": "Feature",
  "properties": {
    "addr:full":"Stationsstraat 19 Lede Oost-Vlaanderen 9340",
    "addr:housenumber":"19",
    "addr:postcode":"9340",
    "addr:street":"Stationsstraat",
    "iso:country":"BE",
    "sg:address":"Stationsstraat 19",
    "sg:city":"Lede",
    "sg:orig_category":"Domotics",
    "sg:phone":"+32 53 80 12 17",
    "sg:postcode":"9340",
    "sg:province":"Oost-Vlaanderen",
    "wof:name":"Dewolec",
    "wof:placetype":"venue"
},
  "geometry": {"coordinates":[3.9808859825,50.9683761597],"type":"Point"}
}