{
  "type": "Feature",
  "properties": {
    "iso:country":"BE",
    "sg:address":"Izegemstraat 6",
    "sg:city":"Roeselare",
    "sg:orig_category":"Quincailleries",
    "sg:phone":"+32 51 20 27 91",
    "sg:postcode":"8800",
    "sg:province":"West-Vlaanderen",
    "wof:name":"Huis Cardoen",
    "wof:placetype":"venue"
},
  "geometry": {"coordinates":[3.1567630768,50.9324760437],"type":"Point"}
}