{
  "type": "Feature",
  "properties": {
    "addr:full":"Rue De Namur 21 Li\u00e8ge 1 Li\u00e8ge 4000",
    "addr:housenumber":"21;1",
    "addr:postcode":"4000",
    "addr:street":"Rue De Namur",
    "iso:country":"BE",
    "sg:address":"Rue De Namur 21",
    "sg:city":"Li\u00e8ge 1",
    "sg:classifiers":[
        {
            "category":"Home & Garden",
            "subcategory":"Kitchen Supply",
            "type":"Retail Goods"
        }
    ],
    "sg:phone":"+32 4 252 75 25",
    "sg:postcode":"4000",
    "sg:province":"Li\u00e8ge",
    "sg:tags":[
        "-",
        "industrial",
        "installation",
        "equipment"
    ],
    "wof:name":"Dejasse Olivier",
    "wof:placetype":"venue"
},
  "geometry": {"coordinates":[5.5750670433,50.619556427],"type":"Point"}
}