{
  "type": "Feature",
  "properties": {
    "addr:full":"Dorpsplein 5c Rotselaar Vlaams-Brabant 3110",
    "addr:housenumber":"5c",
    "addr:postcode":"3110",
    "addr:street":"Dorpsplein",
    "iso:country":"BE",
    "sg:address":"Dorpsplein 5c",
    "sg:city":"Rotselaar",
    "sg:classifiers":[
        {
            "category":"Home & Garden",
            "subcategory":"Hardware",
            "type":"Retail Goods"
        }
    ],
    "sg:phone":"+32 16 44 70 83",
    "sg:postcode":"3110",
    "sg:province":"Vlaams-Brabant",
    "sg:tags":[
        "compagnies",
        "vie",
        "assurances",
        "assurance",
        "habitation"
    ],
    "wof:name":"Zakenkantoor Meulemans",
    "wof:placetype":"venue"
},
  "geometry": {"coordinates":[4.7092618942,50.9510612488],"type":"Point"}
}