{
  "type": "Feature",
  "properties": {
    "addr:full":"Lommerlaan 32b29 Brussel/bruxelles Bruxelles-Capitale 1200",
    "addr:housenumber":"32b29",
    "addr:postcode":"1200",
    "addr:street":"Lommerlaan;/",
    "iso:country":"BE",
    "sg:address":"Lommerlaan 32b29",
    "sg:city":"Brussel/bruxelles",
    "sg:orig_category":"Fotografen and fotostudio's Reisbureaus",
    "sg:phone":"+32 2 763 14 21",
    "sg:postcode":"1200",
    "sg:province":"Bruxelles-Capitale",
    "wof:name":"Travexpert Asia",
    "wof:placetype":"venue"
},
  "geometry": {"coordinates":[4.413394928,50.839427948],"type":"Point"}
}