{
  "type": "Feature",
  "properties": {
    "iso:country":"BE",
    "sg:address":"Sparrenweg 260",
    "sg:city":"Tessenderlo",
    "sg:classifiers":[
        {
            "category":"Building & Trades",
            "subcategory":"Equipment Rental",
            "type":"Services"
        }
    ],
    "sg:phone":"+32 13 67 88 84",
    "sg:postcode":"3980",
    "sg:province":"Limburg",
    "sg:tags":[
        "lighting",
        "-",
        "fixture"
    ],
    "wof:name":"Tns Intelligent Licht Service",
    "wof:placetype":"venue"
},
  "geometry": {"coordinates":[5.0379900932,51.069770813],"type":"Point"}
}