{
  "type": "Feature",
  "properties": {
    "addr:full":"Industrieweg 61 Paal Limburg 3583",
    "addr:housenumber":"61",
    "addr:postcode":"3583",
    "addr:street":"Industrieweg",
    "iso:country":"BE",
    "sg:address":"Industrieweg 61",
    "sg:city":"Paal",
    "sg:classifiers":[
        {
            "category":"Bakery",
            "type":"Food & Drink"
        }
    ],
    "sg:phone":"+32 11 42 06 38",
    "sg:postcode":"3583",
    "sg:province":"Limburg",
    "sg:tags":[
        "cake",
        "product",
        "related",
        "bread"
    ],
    "wof:name":"De Reze Biscuit Choclate Bvba",
    "wof:placetype":"venue"
},
  "geometry": {"coordinates":[5.1853470802,51.048664093],"type":"Point"}
}