{
  "type": "Feature",
  "properties": {
    "addr:full":"Zuidstraat 69 Roeselare West-Vlaanderen 8800",
    "addr:housenumber":"69",
    "addr:postcode":"8800",
    "addr:street":"Zuidstraat",
    "iso:country":"BE",
    "sg:address":"Zuidstraat 69",
    "sg:city":"Roeselare",
    "sg:orig_category":"Kapsalons",
    "sg:phone":"+32 51 25 18 47",
    "sg:postcode":"8800",
    "sg:province":"West-Vlaanderen",
    "wof:name":"Coiffure Jean Louis Davis",
    "wof:placetype":"venue"
},
  "geometry": {"coordinates":[3.1248109341,50.9416046143],"type":"Point"}
}