{
  "type": "Feature",
  "properties": {
    "addr:full":"Morgenlandstraat 52 Etterbeek/etterbeek Bruxelles-Capitale 1040",
    "addr:housenumber":"52",
    "addr:postcode":"1040",
    "addr:street":"Morgenlandstraat",
    "iso:country":"BE",
    "sg:address":"Morgenlandstraat 52",
    "sg:city":"Etterbeek/etterbeek",
    "sg:orig_category":"Drukkerijen and copyshops",
    "sg:phone":"+32 2 647 33 20",
    "sg:postcode":"1040",
    "sg:province":"Bruxelles-Capitale",
    "wof:name":"Imprimerie Van Ruys",
    "wof:placetype":"venue"
},
  "geometry": {"coordinates":[4.3817000389,50.8344078064],"type":"Point"}
}