{
  "type": "Feature",
  "properties": {
    "iso:country":"BE",
    "sg:address":"Cederdreef 9",
    "sg:city":"Wetteren",
    "sg:orig_category":"Promoteurs immobiliers",
    "sg:phone":"+32 9 369 19 74",
    "sg:postcode":"9230",
    "sg:province":"Oost-Vlaanderen",
    "wof:name":"Immoflandria",
    "wof:placetype":"venue"
},
  "geometry": {"coordinates":[3.8776528835,51.0147171021],"type":"Point"}
}