{
  "type": "Feature",
  "properties": {
    "addr:full":"Rue Des Ardennes 12 Durbuy Luxembourg 6941",
    "addr:housenumber":"12",
    "addr:postcode":"6941",
    "addr:street":"Rue Des Ardennes",
    "iso:country":"BE",
    "sg:address":"Rue Des Ardennes 12",
    "sg:city":"Durbuy",
    "sg:orig_category":"Brood, gebak and snoepgoed",
    "sg:phone":"+32 86 21 10 71",
    "sg:postcode":"6941",
    "sg:province":"Luxembourg",
    "wof:name":"Chevigne",
    "wof:placetype":"venue"
},
  "geometry": {"coordinates":[5.524184227,50.3770332336],"type":"Point"}
}