{
  "type": "Feature",
  "properties": {
    "addr:full":"Strikkelaar 2 Schilde Antwerpen 2970",
    "addr:housenumber":"2",
    "addr:postcode":"2970",
    "addr:street":"Strikkelaar",
    "iso:country":"BE",
    "sg:address":"Strikkelaar 2",
    "sg:city":"Schilde",
    "sg:classifiers":[
        {
            "category":"Banks & Credit Unions",
            "subcategory":"Financial Services",
            "type":"Services"
        }
    ],
    "sg:phone":"+32 3 385 40 15",
    "sg:postcode":"2970",
    "sg:province":"Antwerpen",
    "sg:tags":[
        "group"
    ],
    "wof:name":"Matracon",
    "wof:placetype":"venue"
},
  "geometry": {"coordinates":[4.6046380997,51.2615394592],"type":"Point"}
}