{
  "type": "Feature",
  "properties": {
    "addr:full":"Putsebaan 192 Antwerpen Antwerpen 2040",
    "addr:housenumber":"192",
    "addr:postcode":"2040",
    "addr:street":"Putsebaan",
    "iso:country":"BE",
    "sg:address":"Putsebaan 192",
    "sg:city":"Antwerpen",
    "sg:orig_category":"Herstellingen and onderhoud van auto's",
    "sg:phone":"+32 3 568 78 54",
    "sg:postcode":"2040",
    "sg:province":"Antwerpen",
    "wof:name":"Nuyts Revisiebedrijf",
    "wof:placetype":"venue"
},
  "geometry": {"coordinates":[4.333509922,51.3579902649],"type":"Point"}
}