{
  "type": "Feature",
  "properties": {
    "addr:full":"Rue Eugene Dubois 5 La Louviere Hainaut 7100",
    "addr:housenumber":"5",
    "addr:postcode":"7100",
    "addr:street":"Rue Eugene Dubois",
    "iso:country":"BE",
    "sg:address":"Rue Eugene Dubois 5",
    "sg:city":"La Louviere",
    "sg:orig_category":"Brood, gebak and snoepgoed",
    "sg:phone":"+32 64 22 32 55",
    "sg:postcode":"7100",
    "sg:province":"Hainaut",
    "wof:name":"Boulangerie Jude",
    "wof:placetype":"venue"
},
  "geometry": {"coordinates":[4.2022900581,50.4899520874],"type":"Point"}
}