{
  "type": "Feature",
  "properties": {
    "iso:country":"BE",
    "sg:address":"Rue Des Vennes 27",
    "sg:city":"Li\u00c8ge",
    "sg:orig_category":"Epiceries",
    "sg:phone":"+32 4 349 02 10",
    "sg:postcode":"4020",
    "sg:province":"Li\u00e8ge",
    "wof:name":"Kevin Night Shop",
    "wof:placetype":"venue"
},
  "geometry": {"coordinates":[5.5820188522,50.6281738281],"type":"Point"}
}