{
  "type": "Feature",
  "properties": {
    "iso:country":"BE",
    "sg:address":"Rooshaegenweg 86",
    "sg:city":"Maasmechelen",
    "sg:orig_category":"Dierenartsen",
    "sg:phone":"+32 89 77 51 81",
    "sg:postcode":"3630",
    "sg:province":"Limburg",
    "wof:name":"Hendrikx R.",
    "wof:placetype":"venue"
},
  "geometry": {"coordinates":[5.6946182251,50.9711456299],"type":"Point"}
}