{
  "type": "Feature",
  "properties": {
    "addr:full":"Pl. Vlle Halle Aux Bl\u00c9s 11 Brussel/bruxelles Bruxelles-Capitale 1000",
    "addr:housenumber":"11",
    "addr:postcode":"1000",
    "addr:street":"Pl.;Halle Aux Ble\u0301S;/",
    "iso:country":"BE",
    "sg:address":"Pl. Vlle Halle Aux Bl\u00c9s 11",
    "sg:city":"Brussel/bruxelles",
    "sg:orig_category":"Editeurs de livres",
    "sg:phone":"+32 2 511 10 20",
    "sg:postcode":"1000",
    "sg:province":"Bruxelles-Capitale",
    "wof:name":"Edit. Musicales Pouchenel/f\u00c9d\u00c9ration Jacques Brel",
    "wof:placetype":"venue"
},
  "geometry": {"coordinates":[4.3503799438,50.8408851624],"type":"Point"}
}