{
  "type": "Feature",
  "properties": {
    "iso:country":"BE",
    "sg:address":"Chauss\u00c9e De Binche 215",
    "sg:city":"Mons",
    "sg:orig_category":"Poissonniers and \u00e9caillers",
    "sg:phone":"+32 65 31 10 53",
    "sg:postcode":"7000",
    "sg:province":"Hainaut",
    "wof:name":"Maison L'etal",
    "wof:placetype":"venue"
},
  "geometry": {"coordinates":[3.9904100895,50.4488296509],"type":"Point"}
}