{
  "type": "Feature",
  "properties": {
    "addr:full":"Markt 39 Peer Limburg 3990",
    "addr:housenumber":"39",
    "addr:postcode":"3990",
    "addr:street":"Markt",
    "iso:country":"BE",
    "sg:address":"Markt 39",
    "sg:city":"Peer",
    "sg:classifiers":[
        {
            "category":"Bars & Pubs",
            "type":"Food & Drink"
        }
    ],
    "sg:phone":"+32 11 63 42 42",
    "sg:postcode":"3990",
    "sg:province":"Limburg",
    "wof:name":"Markt (de)",
    "wof:placetype":"venue"
},
  "geometry": {"coordinates":[5.4555549622,51.1315383911],"type":"Point"}
}