{
  "type": "Feature",
  "properties": {
    "iso:country":"BE",
    "sg:address":"Oostmalsebaan 12",
    "sg:city":"Brecht",
    "sg:orig_category":"Ramassage and traitement des d\u00e9chets m\u00e9nagers. Mat\u00e9riaux de construction Gr",
    "sg:phone":"+32 3 313 82 34",
    "sg:postcode":"2960",
    "sg:province":"Antwerpen",
    "wof:name":"Knaepkens Gebrs",
    "wof:placetype":"venue"
},
  "geometry": {"coordinates":[4.6415200233,51.3512115479],"type":"Point"}
}