{
  "type": "Feature",
  "properties": {
    "addr:full":"Vrijheid 58 Hoogstraten Antwerpen 2320",
    "addr:housenumber":"58",
    "addr:postcode":"2320",
    "addr:street":"Vrijheid",
    "iso:country":"BE",
    "sg:address":"Vrijheid 58",
    "sg:city":"Hoogstraten",
    "sg:classifiers":[
        {
            "category":"Health Services",
            "subcategory":"Dentist",
            "type":"Services"
        }
    ],
    "sg:phone":"+32 3 314 45 56",
    "sg:postcode":"2320",
    "sg:province":"Antwerpen",
    "wof:name":"Steylaerts H",
    "wof:placetype":"venue"
},
  "geometry": {"coordinates":[4.7628087997,51.405506134],"type":"Point"}
}