{
  "type": "Feature",
  "properties": {
    "iso:country":"BE",
    "sg:address":"Burgemeester Karel Van Doorslaerlaan 67",
    "sg:city":"Bornem (mariekerke)",
    "sg:orig_category":"Solariums",
    "sg:phone":"+32 52 33 27 26",
    "sg:postcode":"2880",
    "sg:province":"Antwerpen",
    "wof:name":"Asselberghs",
    "wof:placetype":"venue"
},
  "geometry": {"coordinates":[4.1989340782,51.0622558594],"type":"Point"}
}