{
  "type": "Feature",
  "properties": {
    "addr:full":"Rue Card Lavigerie 13 Etterbeek Bruxelles-Capitale 1040",
    "addr:housenumber":"13",
    "addr:postcode":"1040",
    "addr:street":"Rue Card Lavigerie",
    "iso:country":"BE",
    "sg:address":"Rue Card Lavigerie 13",
    "sg:city":"Etterbeek",
    "sg:orig_category":"Astrologen, grafologen and mediums",
    "sg:phone":"+32 2 736 71 07",
    "sg:postcode":"1040",
    "sg:province":"Bruxelles-Capitale",
    "wof:name":"De Penaranda De Franchimont Y",
    "wof:placetype":"venue"
},
  "geometry": {"coordinates":[4.401447773,50.8274993896],"type":"Point"}
}