{
  "type": "Feature",
  "properties": {
    "iso:country":"BE",
    "sg:address":"Leo Baekelandstraat 3",
    "sg:city":"Edegem",
    "sg:classifiers":[
        {
            "category":"Recreation",
            "subcategory":"Gun Range",
            "type":"Entertainment"
        }
    ],
    "sg:phone":"+32 3 449 49 78",
    "sg:postcode":"2650",
    "sg:province":"Antwerpen",
    "sg:tags":[
        "ammunition",
        "-",
        "retail"
    ],
    "wof:name":"Hervens G Wapenmakerij & Handel",
    "wof:placetype":"venue"
},
  "geometry": {"coordinates":[4.4226231575,51.1639022827],"type":"Point"}
}