{
  "type": "Feature",
  "properties": {
    "addr:full":"Gaston Baertstraat 38 Deinze Oost-Vlaanderen 9800",
    "addr:housenumber":"38",
    "addr:postcode":"9800",
    "addr:street":"Baertstraat",
    "iso:country":"BE",
    "sg:address":"Gaston Baertstraat 38",
    "sg:city":"Deinze",
    "sg:orig_category":"Boekhouders",
    "sg:phone":"+32 9 282 02 60",
    "sg:postcode":"9800",
    "sg:province":"Oost-Vlaanderen",
    "wof:name":"Luc De Baere",
    "wof:placetype":"venue"
},
  "geometry": {"coordinates":[3.5838999748,51.0160522461],"type":"Point"}
}