{
  "type": "Feature",
  "properties": {
    "addr:full":"Jaak De Boeckstraat 6 Antwerpen Antwerpen 2170",
    "addr:housenumber":"6",
    "addr:postcode":"2170",
    "addr:street":"Jaak De Boeckstraat",
    "iso:country":"BE",
    "sg:address":"Jaak De Boeckstraat 6",
    "sg:city":"Antwerpen",
    "sg:orig_category":"Rusthuizen and serviceflats",
    "sg:phone":"+32 3 641 77 11",
    "sg:postcode":"2170",
    "sg:province":"Antwerpen",
    "wof:name":"Rusthuis St.bartholomeus",
    "wof:placetype":"venue"
},
  "geometry": {"coordinates":[4.4505147934,51.246723175],"type":"Point"}
}