{
  "type": "Feature",
  "properties": {
    "iso:country":"BE",
    "sg:address":"Ruelle Dupuis 5",
    "sg:city":"Beaumont",
    "sg:orig_category":"Souvenirs and objets artisanaux",
    "sg:phone":"+32 71 58 95 76",
    "sg:postcode":"6500",
    "sg:province":"Hainaut",
    "wof:name":"La Ciergerie",
    "wof:placetype":"venue"
},
  "geometry": {"coordinates":[4.2381467819,50.2359046936],"type":"Point"}
}