{
  "type": "Feature",
  "properties": {
    "addr:full":"Hadewijchplein 1 Lommel Limburg 3920",
    "addr:housenumber":"1",
    "addr:postcode":"3920",
    "addr:street":"Hadewijchplein",
    "iso:country":"BE",
    "sg:address":"Hadewijchplein 1",
    "sg:city":"Lommel",
    "sg:orig_category":"Installation \u00e9lectrique r\u00e9sidentielle",
    "sg:phone":"+32 11 54 21 88",
    "sg:postcode":"3920",
    "sg:province":"Limburg",
    "wof:name":"Pascal Vanendert",
    "wof:placetype":"venue"
},
  "geometry": {"coordinates":[5.2859740257,51.2321548462],"type":"Point"}
}