{
  "type": "Feature",
  "properties": {
    "iso:country":"BE",
    "sg:address":"Aisne 35",
    "sg:city":"Durbuy",
    "sg:orig_category":"Distilleries. Composition and photogravure. Vins Fab",
    "sg:phone":"+32 86 49 94 36",
    "sg:postcode":"6941",
    "sg:province":"Luxembourg",
    "wof:name":"Cidrerie Du Maitre Blanc",
    "wof:placetype":"venue"
},
  "geometry": {"coordinates":[5.524184227,50.3770332336],"type":"Point"}
}