{
  "type": "Feature",
  "properties": {
    "iso:country":"BE",
    "sg:address":"Driesstraat 18",
    "sg:city":"Nieuwerkerken",
    "sg:orig_category":"Installation de menuiserie en bois and plastique",
    "sg:phone":"+32 11 69 24 06",
    "sg:postcode":"3850",
    "sg:province":"Limburg",
    "wof:name":"Stefan Geysenbergh",
    "wof:placetype":"venue"
},
  "geometry": {"coordinates":[5.1939110756,50.8604316711],"type":"Point"}
}