{
  "type": "Feature",
  "properties": {
    "addr:full":"Ezelstraat 25 Brugge West-Vlaanderen 8000",
    "addr:housenumber":"25",
    "addr:postcode":"8000",
    "addr:street":"Ezelstraat",
    "iso:country":"BE",
    "sg:address":"Ezelstraat 25",
    "sg:city":"Brugge",
    "sg:classifiers":[
        {
            "category":"Government",
            "subcategory":"Embassy",
            "type":"Public Place"
        }
    ],
    "sg:phone":"+32 50 65 00 90",
    "sg:postcode":"8000",
    "sg:province":"West-Vlaanderen",
    "sg:tags":[
        "consulate"
    ],
    "wof:name":"Zweden (consulaat)",
    "wof:placetype":"venue"
},
  "geometry": {"coordinates":[3.219233036,51.2123146057],"type":"Point"}
}