{
  "type": "Feature",
  "properties": {
    "iso:country":"BE",
    "sg:address":"Brandstraat 122",
    "sg:city":"Beveren (vrasene)",
    "sg:classifiers":[
        {
            "category":"Building & Trades",
            "subcategory":"Construction",
            "type":"Services"
        }
    ],
    "sg:phone":"+32 3 775 43 55",
    "sg:postcode":"9120",
    "sg:province":"Oost-Vlaanderen",
    "sg:tags":[
        "installation",
        "-",
        "central",
        "heating"
    ],
    "wof:name":"Feko Bvba",
    "wof:placetype":"venue"
},
  "geometry": {"coordinates":[4.203166008,51.2061195374],"type":"Point"}
}