{
  "type": "Feature",
  "properties": {
    "addr:full":"Don Boscostraat 21 Hechtel-eksel (hechtel) Limburg 3940",
    "addr:housenumber":"21",
    "addr:postcode":"3940",
    "addr:street":"Don Boscostraat",
    "iso:country":"BE",
    "sg:address":"Don Boscostraat 21",
    "sg:city":"Hechtel-eksel (hechtel)",
    "sg:classifiers":[
        {
            "category":"Bakery",
            "type":"Food & Drink"
        }
    ],
    "sg:phone":"+32 11 73 43 57",
    "sg:postcode":"3940",
    "sg:province":"Limburg",
    "sg:tags":[
        "confectioner",
        "baker"
    ],
    "wof:name":"Gestels D",
    "wof:placetype":"venue"
},
  "geometry": {"coordinates":[5.364795208,51.1255340576],"type":"Point"}
}