{
  "type": "Feature",
  "properties": {
    "addr:full":"Rue De Chevrimont 1 Sprimont Li\u00e8ge 4140",
    "addr:housenumber":"1",
    "addr:postcode":"4140",
    "addr:street":"Rue De Chevrimont",
    "iso:country":"BE",
    "sg:address":"Rue De Chevrimont 1",
    "sg:city":"Sprimont",
    "sg:orig_category":"Rundveehouders",
    "sg:phone":"+32 4 369 24 46",
    "sg:postcode":"4140",
    "sg:province":"Li\u00e8ge",
    "wof:name":"Jean Pol Depreay",
    "wof:placetype":"venue"
},
  "geometry": {"coordinates":[5.6018252373,50.4958229065],"type":"Point"}
}