{
  "type": "Feature",
  "properties": {
    "addr:full":"Musschaverstraat 5 Nevele (groot) Oost-Vlaanderen 9850",
    "addr:housenumber":"5",
    "addr:postcode":"9850",
    "addr:street":"Musschaverstraat;Groot Oost-Vlaanderen",
    "iso:country":"BE",
    "sg:address":"Musschaverstraat 5",
    "sg:city":"Nevele (groot)",
    "sg:orig_category":"Installatie van houten of kunststof schrijnwerk",
    "sg:phone":"+32 9 371 53 22",
    "sg:postcode":"9850",
    "sg:province":"Oost-Vlaanderen",
    "wof:name":"Decnu",
    "wof:placetype":"venue"
},
  "geometry": {"coordinates":[3.5958609581,51.0566291809],"type":"Point"}
}