{
  "type": "Feature",
  "properties": {
    "addr:full":"Rue Fontena 3 Havelange (maffe) Namur 5374",
    "addr:housenumber":"3",
    "addr:postcode":"5374",
    "addr:street":"Rue Fontena",
    "iso:country":"BE",
    "sg:address":"Rue Fontena 3",
    "sg:city":"Havelange (maffe)",
    "sg:classifiers":[
        {
            "category":"Farming",
            "subcategory":"Farm & Veterinary Services",
            "type":"Manufacturing & Wholesale Goods"
        }
    ],
    "sg:phone":"+32 86 32 27 16",
    "sg:postcode":"5374",
    "sg:province":"Namur",
    "sg:tags":[
        "agricultural",
        "contractor"
    ],
    "wof:name":"Marot M",
    "wof:placetype":"venue"
},
  "geometry": {"coordinates":[5.3138341904,50.3554534912],"type":"Point"}
}