{
  "type": "Feature",
  "properties": {
    "addr:full":"Rue D'ath 3 Soignies Hainaut 7063",
    "addr:housenumber":"3",
    "addr:postcode":"7063",
    "addr:street":"Rue D'Ath",
    "iso:country":"BE",
    "sg:address":"Rue D'ath 3",
    "sg:city":"Soignies",
    "sg:orig_category":"Slagers",
    "sg:phone":"+32 67 45 87 44",
    "sg:postcode":"7063",
    "sg:province":"Hainaut",
    "wof:name":"Mic-meat",
    "wof:placetype":"venue"
},
  "geometry": {"coordinates":[3.9727900028,50.5907478333],"type":"Point"}
}