{
  "type": "Feature",
  "properties": {
    "addr:full":"Lisperstraat 123 Lier Antwerpen 2500",
    "addr:housenumber":"123",
    "addr:postcode":"2500",
    "addr:street":"Lisperstraat",
    "iso:country":"BE",
    "sg:address":"Lisperstraat 123",
    "sg:city":"Lier",
    "sg:orig_category":"Schoenen Sport- and kampeermateriaal",
    "sg:phone":"+32 3 480 31 93",
    "sg:postcode":"2500",
    "sg:province":"Antwerpen",
    "wof:name":"Vedette Sport",
    "wof:placetype":"venue"
},
  "geometry": {"coordinates":[4.5711941719,51.1347351074],"type":"Point"}
}