{
  "type": "Feature",
  "properties": {
    "addr:full":"Boulevard Des Canadiens 69 Moeskroen/mouscron Hainaut 7711",
    "addr:housenumber":"69",
    "addr:postcode":"7711",
    "addr:street":"Boulevard Des Canadiens",
    "iso:country":"BE",
    "sg:address":"Boulevard Des Canadiens 69",
    "sg:city":"Moeskroen/mouscron",
    "sg:classifiers":[
        {
            "category":"Autos & Motor Vehicles",
            "subcategory":"Fuel & Gas Station",
            "type":"Retail Goods"
        }
    ],
    "sg:phone":"+32 56 48 57 46",
    "sg:postcode":"7711",
    "sg:province":"Hainaut",
    "sg:tags":[
        "stations-service",
        "carburants"
    ],
    "wof:name":"Q8",
    "wof:placetype":"venue"
},
  "geometry": {"coordinates":[3.3200099468,50.7301254272],"type":"Point"}
}