{
  "type": "Feature",
  "properties": {
    "addr:full":"Gerststraat 2 Jabbeke West-Vlaanderen 8490",
    "addr:housenumber":"2",
    "addr:postcode":"8490",
    "addr:street":"Gerststraat",
    "iso:country":"BE",
    "sg:address":"Gerststraat 2",
    "sg:city":"Jabbeke",
    "sg:classifiers":[
        {
            "category":"Health Services",
            "subcategory":"Doctor",
            "type":"Services"
        }
    ],
    "sg:phone":"+32 50 81 38 83",
    "sg:postcode":"8490",
    "sg:province":"West-Vlaanderen",
    "sg:tags":[
        "psychotherapist",
        "psychoanalyst"
    ],
    "wof:name":"Van Den Bilcke P",
    "wof:placetype":"venue"
},
  "geometry": {"coordinates":[3.0847289562,51.1743354797],"type":"Point"}
}