{
  "type": "Feature",
  "properties": {
    "addr:full":"Quai Du Halage 276 Fl\u00e9malle Li\u00e8ge 4400",
    "addr:housenumber":"276",
    "addr:postcode":"4400",
    "addr:street":"Quai Du Halage",
    "iso:country":"BE",
    "sg:address":"Quai Du Halage 276",
    "sg:city":"Fl\u00e9malle",
    "sg:classifiers":[
        {
            "category":"Shopping",
            "subcategory":"Bicycles & Sporting Goods",
            "type":"Retail Goods"
        }
    ],
    "sg:phone":"+32 4 275 14 83",
    "sg:postcode":"4400",
    "sg:province":"Li\u00e8ge",
    "sg:tags":[
        "-"
    ],
    "wof:name":"Adam-smol Cycles",
    "wof:placetype":"venue"
},
  "geometry": {"coordinates":[5.4785251617,50.5973167419],"type":"Point"}
}