{
  "type": "Feature",
  "properties": {
    "addr:full":"Victor Nelisstraat 33 Schoten Antwerpen 2900",
    "addr:housenumber":"33",
    "addr:postcode":"2900",
    "addr:street":"Victor Nelisstraat",
    "iso:country":"BE",
    "sg:address":"Victor Nelisstraat 33",
    "sg:city":"Schoten",
    "sg:orig_category":"Installation de menuiserie en bois and plastique",
    "sg:phone":"+32 3 658 05 85",
    "sg:postcode":"2900",
    "sg:province":"Antwerpen",
    "wof:name":"Patrick Langlet",
    "wof:placetype":"venue"
},
  "geometry": {"coordinates":[4.4812779427,51.2501754761],"type":"Point"}
}