{
  "type": "Feature",
  "properties": {
    "addr:full":"Boeschepestraat 2 Heuvelland West-Vlaanderen 8954",
    "addr:housenumber":"2",
    "addr:postcode":"8954",
    "addr:street":"Boeschepestraat",
    "iso:country":"BE",
    "sg:address":"Boeschepestraat 2",
    "sg:city":"Heuvelland",
    "sg:orig_category":"Producteurs de l\u00e9gumes. Machines and mat\u00e9riel agricoles Gr",
    "sg:phone":"+32 57 44 44 65",
    "sg:postcode":"8954",
    "sg:province":"West-Vlaanderen",
    "wof:name":"Marc Delanote",
    "wof:placetype":"venue"
},
  "geometry": {"coordinates":[2.7432279587,50.7977790833],"type":"Point"}
}