{
  "type": "Feature",
  "properties": {
    "addr:full":"Rue De La R\u00c9sistance 26 Theux Li\u00e8ge 4910",
    "addr:housenumber":"26",
    "addr:postcode":"4910",
    "addr:street":"Rue De La Re\u0301Sistance",
    "iso:country":"BE",
    "sg:address":"Rue De La R\u00c9sistance 26",
    "sg:city":"Theux",
    "sg:classifiers":[
        {
            "category":"Personal",
            "subcategory":"Beauty Salon",
            "type":"Services"
        }
    ],
    "sg:phone":"+32 87 54 16 43",
    "sg:postcode":"4910",
    "sg:province":"Li\u00e8ge",
    "sg:tags":[
        "de",
        "coiffure"
    ],
    "wof:name":"M. Konten",
    "wof:placetype":"venue"
},
  "geometry": {"coordinates":[5.8130488396,50.5356216431],"type":"Point"}
}