{
  "type": "Feature",
  "properties": {
    "iso:country":"BE",
    "sg:address":"Chauss\u00c9e De Wavre 2b10",
    "sg:city":"Perwez",
    "sg:orig_category":"Opticiens",
    "sg:phone":"+32 81 65 62 03",
    "sg:postcode":"1360",
    "sg:province":"Brabant Wallon",
    "wof:name":"Philippe Londot",
    "wof:placetype":"venue"
},
  "geometry": {"coordinates":[4.7701201439,50.6437492371],"type":"Point"}
}