{
  "type": "Feature",
  "properties": {
    "iso:country":"BE",
    "sg:address":"Kauter 64",
    "sg:city":"Beernem",
    "sg:classifiers":[
        {
            "category":"Restaurant",
            "type":"Food & Drink"
        }
    ],
    "sg:phone":"+32 50 78 91 43",
    "sg:postcode":"8730",
    "sg:province":"West-Vlaanderen",
    "wof:name":"De Waterlady",
    "wof:placetype":"venue"
},
  "geometry": {"coordinates":[3.3710179329,51.1297645569],"type":"Point"}
}