{
  "type": "Feature",
  "properties": {
    "iso:country":"BE",
    "sg:address":"Rue De La Cayenne 59",
    "sg:city":"Perwez",
    "sg:classifiers":[
        {
            "category":"Parking",
            "subcategory":"Bicycle",
            "type":"Transportation"
        }
    ],
    "sg:phone":"+32 81 65 60 28",
    "sg:postcode":"1360",
    "sg:province":"Brabant Wallon",
    "sg:tags":[
        "chiropodist"
    ],
    "wof:name":"Charles C",
    "wof:placetype":"venue"
},
  "geometry": {"coordinates":[4.8132209778,50.6161003113],"type":"Point"}
}