{
  "type": "Feature",
  "properties": {
    "addr:full":"Slangbeekstraat 72 Hasselt (kuringen) Limburg 3511",
    "addr:housenumber":"72",
    "addr:postcode":"3511",
    "addr:street":"Slangbeekstraat",
    "iso:country":"BE",
    "sg:address":"Slangbeekstraat 72",
    "sg:city":"Hasselt (kuringen)",
    "sg:classifiers":[
        {
            "category":"Manufacturing",
            "subcategory":"Metals",
            "type":"Manufacturing & Wholesale Goods"
        }
    ],
    "sg:phone":"+32 11 22 58 78",
    "sg:postcode":"3511",
    "sg:province":"Limburg",
    "sg:tags":[
        "working"
    ],
    "wof:name":"Bortels R",
    "wof:placetype":"venue"
},
  "geometry": {"coordinates":[5.3205661774,50.9637145996],"type":"Point"}
}