{
  "type": "Feature",
  "properties": {
    "addr:full":"Avenue De Waterloo 42 Charleroi Hainaut 6000",
    "addr:housenumber":"42",
    "addr:postcode":"6000",
    "addr:street":"Avenue De Waterloo;Hainaut",
    "iso:country":"BE",
    "sg:address":"Avenue De Waterloo 42",
    "sg:city":"Charleroi",
    "sg:classifiers":[
        {
            "category":"Fast Food",
            "type":"Food & Drink"
        }
    ],
    "sg:phone":"+32 71 30 64 00",
    "sg:postcode":"6000",
    "sg:province":"Hainaut",
    "sg:tags":[
        "\u00c0",
        "emporter",
        "restaurants"
    ],
    "wof:name":"Charly's Burger",
    "wof:placetype":"venue"
},
  "geometry": {"coordinates":[4.4481549263,50.4153938293],"type":"Point"}
}