{
  "type": "Feature",
  "properties": {
    "addr:full":"Kopberg 24 Balen Antwerpen 2490",
    "addr:housenumber":"24",
    "addr:postcode":"2490",
    "addr:street":"Kopberg",
    "iso:country":"BE",
    "sg:address":"Kopberg 24",
    "sg:city":"Balen",
    "sg:orig_category":"Art and fournitures artistiques",
    "sg:phone":"+32 14 30 97 66",
    "sg:postcode":"2490",
    "sg:province":"Antwerpen",
    "wof:name":"Fa. Decor-line",
    "wof:placetype":"venue"
},
  "geometry": {"coordinates":[5.1101999283,51.1496810913],"type":"Point"}
}