{
  "type": "Feature",
  "properties": {
    "iso:country":"BE",
    "sg:address":"Musschaeverstraat 49",
    "sg:city":"Nevele",
    "sg:classifiers":[
        {
            "category":"Wholesale",
            "subcategory":"Sporting Goods",
            "type":"Manufacturing & Wholesale Goods"
        }
    ],
    "sg:phone":"+32 2 371 90 66",
    "sg:postcode":"9850",
    "sg:province":"Oost-Vlaanderen",
    "sg:tags":[
        "sport-",
        "kampeermateriaal"
    ],
    "wof:name":"Carlier",
    "wof:placetype":"venue"
},
  "geometry": {"coordinates":[3.6052279472,51.0620536804],"type":"Point"}
}