{
  "type": "Feature",
  "properties": {
    "iso:country":"BE",
    "sg:address":"August Dierckxlaan 20",
    "sg:city":"Schilde",
    "sg:classifiers":[
        {
            "category":"Building & Trades",
            "subcategory":"Construction",
            "type":"Services"
        }
    ],
    "sg:phone":"+32 3 384 13 89",
    "sg:postcode":"2970",
    "sg:province":"Antwerpen",
    "sg:tags":[
        "carpenter"
    ],
    "wof:name":"Van Berendonck Bvba",
    "wof:placetype":"venue"
},
  "geometry": {"coordinates":[4.5870480537,51.2361488342],"type":"Point"}
}