{
  "type": "Feature",
  "properties": {
    "addr:full":"Joseph Jongenlaan 28 Ukkel/uccle Bruxelles-Capitale 1180",
    "addr:housenumber":"28",
    "addr:postcode":"1180",
    "addr:street":"Joseph Jongenlaan;/",
    "iso:country":"BE",
    "sg:address":"Joseph Jongenlaan 28",
    "sg:city":"Ukkel/uccle",
    "sg:orig_category":"Immobili\u00ebnkantoren",
    "sg:phone":"+32 2 376 36 81",
    "sg:postcode":"1180",
    "sg:province":"Bruxelles-Capitale",
    "wof:name":"Bureau Rosal",
    "wof:placetype":"venue"
},
  "geometry": {"coordinates":[4.3301529884,50.7990608215],"type":"Point"}
}