{
  "type": "Feature",
  "properties": {
    "iso:country":"BE",
    "sg:address":"Ring 13",
    "sg:city":"Ninove",
    "sg:orig_category":"V\u00eatements pour b\u00e9b\u00e9s and enfants. V\u00eatements pour Hommes. V\u00eatements pour Dames",
    "sg:phone":"+32 54 32 31 32",
    "sg:postcode":"9400",
    "sg:province":"Oost-Vlaanderen",
    "wof:name":"Superconfex",
    "wof:placetype":"venue"
},
  "geometry": {"coordinates":[4.0310001373,50.8447799683],"type":"Point"}
}