{
  "type": "Feature",
  "properties": {
    "iso:country":"BE",
    "sg:address":"Zoerselbosdreef 35",
    "sg:city":"Zoersel",
    "sg:classifiers":[
        {
            "category":"Professional",
            "subcategory":"Management & Consulting",
            "type":"Services"
        }
    ],
    "sg:phone":"+32 3 309 42 62",
    "sg:postcode":"2980",
    "sg:province":"Antwerpen",
    "sg:tags":[
        "consultant"
    ],
    "wof:name":"Nathco",
    "wof:placetype":"venue"
},
  "geometry": {"coordinates":[4.6970319748,51.2531509399],"type":"Point"}
}