{
  "type": "Feature",
  "properties": {
    "addr:full":"Rue Albert I 63 Hannut Li\u00e8ge 4280",
    "addr:housenumber":"63",
    "addr:postcode":"4280",
    "addr:street":"Rue Albert I",
    "iso:country":"BE",
    "sg:address":"Rue Albert I 63",
    "sg:city":"Hannut",
    "sg:classifiers":[
        {
            "category":"Real Estate",
            "subcategory":"Real Estate Services",
            "type":"Services"
        }
    ],
    "sg:phone":"+32 19 51 45 55",
    "sg:postcode":"4280",
    "sg:province":"Li\u00e8ge",
    "wof:name":"Espace Habitat",
    "wof:placetype":"venue"
},
  "geometry": {"coordinates":[5.0833888054,50.6692733765],"type":"Point"}
}