{
  "type": "Feature",
  "properties": {
    "iso:country":"BE",
    "sg:address":"Chemin Vert 7",
    "sg:city":"Namur",
    "sg:orig_category":"Dranken",
    "sg:phone":"+32 81 40 16 15",
    "sg:postcode":"5100",
    "sg:province":"Namur",
    "wof:name":"La Commanderie Bons Crus",
    "wof:placetype":"venue"
},
  "geometry": {"coordinates":[4.8713750839,50.4566345215],"type":"Point"}
}