{
  "type": "Feature",
  "properties": {
    "iso:country":"BE",
    "sg:address":"Bremlaan 1",
    "sg:city":"Kortrijk",
    "sg:classifiers":[
        {
            "category":"Communications",
            "subcategory":"Film & Video Production",
            "type":"Services"
        }
    ],
    "sg:phone":"+32 56 21 44 88",
    "sg:postcode":"8500",
    "sg:province":"West-Vlaanderen",
    "sg:tags":[
        "movie",
        "maker"
    ],
    "wof:name":"Lammens R",
    "wof:placetype":"venue"
},
  "geometry": {"coordinates":[3.2933130264,50.825138092],"type":"Point"}
}