{
  "type": "Feature",
  "properties": {
    "iso:country":"BE",
    "sg:address":"Koningin Fabiolalaan 88",
    "sg:city":"Zelzate",
    "sg:orig_category":"Landmeters",
    "sg:phone":"+32 9 344 61 23",
    "sg:postcode":"9060",
    "sg:province":"Oost-Vlaanderen",
    "wof:name":"Gilbert Van De Velde",
    "wof:placetype":"venue"
},
  "geometry": {"coordinates":[3.7983119488,51.2026596069],"type":"Point"}
}