{
  "type": "Feature",
  "properties": {
    "iso:country":"BE",
    "sg:address":"Leenbosstraat 6",
    "sg:city":"Ardooie",
    "sg:orig_category":"Installation de menuiserie en bois and plastique",
    "sg:phone":"+32 51 30 14 24",
    "sg:postcode":"8850",
    "sg:province":"West-Vlaanderen",
    "wof:name":"Erik Vercruysse",
    "wof:placetype":"venue"
},
  "geometry": {"coordinates":[3.2215371132,50.9515724182],"type":"Point"}
}