{
  "type": "Feature",
  "properties": {
    "iso:country":"BE",
    "sg:address":"Rijselstraat 218",
    "sg:city":"Menen",
    "sg:orig_category":"Brood, gebak and snoepgoed",
    "sg:phone":"+32 56 51 11 55",
    "sg:postcode":"8930",
    "sg:province":"West-Vlaanderen",
    "wof:name":"Bakkerij Libbrecht",
    "wof:placetype":"venue"
},
  "geometry": {"coordinates":[3.1266410351,50.7891654968],"type":"Point"}
}