{
  "type": "Feature",
  "properties": {
    "iso:country":"BE",
    "sg:address":"Rue De Waremme 21",
    "sg:city":"Berloz",
    "sg:orig_category":"Eleveurs de volaille",
    "sg:phone":"+32 19 32 37 85",
    "sg:postcode":"4257",
    "sg:province":"Li\u00e8ge",
    "wof:name":"Elevage Avicole De Berloz",
    "wof:placetype":"venue"
},
  "geometry": {"coordinates":[5.2214970589,50.6958847046],"type":"Point"}
}