{
  "type": "Feature",
  "properties": {
    "addr:full":"Rue Du Ch\u00e2telain 8a Bruxelles Bruxelles-Capitale 1000",
    "addr:housenumber":"8a",
    "addr:postcode":"1000",
    "addr:street":"Rue Du Cha\u0302Telain",
    "iso:country":"BE",
    "sg:address":"Rue Du Ch\u00e2telain 8a",
    "sg:city":"Bruxelles",
    "sg:classifiers":[
        {
            "category":"Building & Trades",
            "subcategory":"Locksmith",
            "type":"Services"
        }
    ],
    "sg:phone":"+32 2 640 90 08",
    "sg:postcode":"1000",
    "sg:province":"Bruxelles-Capitale",
    "sg:tags":[
        "lock",
        "key"
    ],
    "wof:name":"Tinant R (ets) Sa",
    "wof:placetype":"venue"
},
  "geometry": {"coordinates":[4.3635420799,50.8257522583],"type":"Point"}
}