{
  "type": "Feature",
  "properties": {
    "addr:full":"Spechtendreef 9 Oud-turnhout Antwerpen 2360",
    "addr:housenumber":"9",
    "addr:postcode":"2360",
    "addr:street":"Spechtendreef",
    "iso:country":"BE",
    "sg:address":"Spechtendreef 9",
    "sg:city":"Oud-turnhout",
    "sg:classifiers":[
        {
            "category":"Real Estate",
            "subcategory":"Real Estate Services",
            "type":"Services"
        }
    ],
    "sg:phone":"+32 14 45 16 88",
    "sg:postcode":"2360",
    "sg:province":"Antwerpen",
    "sg:tags":[
        "-",
        "abroad"
    ],
    "wof:name":"Papiko Com Va",
    "wof:placetype":"venue"
},
  "geometry": {"coordinates":[5.0318770409,51.3167991638],"type":"Point"}
}