{
  "type": "Feature",
  "properties": {
    "iso:country":"BE",
    "sg:address":"Rue Du Trou Perdu 6a",
    "sg:city":"Andenne (thon)",
    "sg:classifiers":[
        {
            "category":"Building & Trades",
            "subcategory":"Cleaning & Sanitation",
            "type":"Services"
        }
    ],
    "sg:phone":"+32 81 58 92 42",
    "sg:postcode":"5300",
    "sg:province":"Namur",
    "sg:tags":[
        "fa\u00e7ade",
        "maintenance"
    ],
    "wof:name":"Willem F",
    "wof:placetype":"venue"
},
  "geometry": {"coordinates":[5.0040378571,50.4609489441],"type":"Point"}
}