{
  "type": "Feature",
  "properties": {
    "iso:country":"BE",
    "sg:address":"Middenlaan 18",
    "sg:city":"Sint-truiden",
    "sg:orig_category":"Rev\u00eatements de sols and murs. Rev\u00eatements pour sols and murs",
    "sg:phone":"+32 11 68 14 77",
    "sg:postcode":"3800",
    "sg:province":"Limburg",
    "wof:name":"Gicomi",
    "wof:placetype":"venue"
},
  "geometry": {"coordinates":[5.1736288071,50.8239135742],"type":"Point"}
}