{
  "type": "Feature",
  "properties": {
    "iso:country":"BE",
    "sg:address":"Kapelstraat 1",
    "sg:city":"Zemst",
    "sg:classifiers":[
        {
            "category":"Home & Garden",
            "subcategory":"Building Materials",
            "type":"Retail Goods"
        }
    ],
    "sg:phone":"+32 15 62 39 35",
    "sg:postcode":"1980",
    "sg:province":"Vlaams-Brabant",
    "sg:tags":[
        "insulation",
        "thermical"
    ],
    "wof:name":"Isoproc",
    "wof:placetype":"venue"
},
  "geometry": {"coordinates":[4.4328951836,50.9853858948],"type":"Point"}
}