{
  "type": "Feature",
  "properties": {
    "iso:country":"BE",
    "sg:address":"L'epine 2",
    "sg:city":"Bouillon",
    "sg:classifiers":[
        {
            "category":"Cafe",
            "type":"Food & Drink"
        }
    ],
    "sg:phone":"+32 61 46 60 73",
    "sg:postcode":"6832",
    "sg:province":"Luxembourg",
    "sg:tags":[
        "caf\u00e9s"
    ],
    "wof:name":"Pierre Didier",
    "wof:placetype":"venue"
},
  "geometry": {"coordinates":[5.0458540916,49.8038368225],"type":"Point"}
}