{
  "type": "Feature",
  "properties": {
    "iso:country":"BE",
    "sg:address":"Mechelsesteenweg 115",
    "sg:city":"Sint-katelijne-waver",
    "sg:orig_category":"Telecommunicatieapparaten Telecommunicatiesystemen",
    "sg:phone":"+32 15 56 00 56",
    "sg:postcode":"2860",
    "sg:province":"Antwerpen",
    "wof:name":"Tele Service Center",
    "wof:placetype":"venue"
},
  "geometry": {"coordinates":[4.5255250931,51.0579223633],"type":"Point"}
}