{
  "type": "Feature",
  "properties": {
    "addr:full":"Rue Aux Racines 1ba Braine-le-ch\u00c2teau Brabant Wallon 1440",
    "addr:housenumber":"1ba",
    "addr:postcode":"1440",
    "addr:street":"Rue Aux Racines",
    "iso:country":"BE",
    "sg:address":"Rue Aux Racines 1ba",
    "sg:city":"Braine-le-ch\u00c2teau",
    "sg:orig_category":"Boekhouders",
    "sg:phone":"+32 2 366 02 99",
    "sg:postcode":"1440",
    "sg:province":"Brabant Wallon",
    "wof:name":"Philippe Olivier",
    "wof:placetype":"venue"
},
  "geometry": {"coordinates":[4.2566461563,50.6793289185],"type":"Point"}
}