{
  "type": "Feature",
  "properties": {
    "iso:country":"BE",
    "sg:address":"Tweekerkenstraat 37b2",
    "sg:city":"Brussel/bruxelles",
    "sg:orig_category":"Public-relationsbureaus",
    "sg:phone":"+32 2 285 01 08",
    "sg:postcode":"1000",
    "sg:province":"Bruxelles-Capitale",
    "wof:name":"Anthonissen Assoc.",
    "wof:placetype":"venue"
},
  "geometry": {"coordinates":[4.3730831146,50.846622467],"type":"Point"}
}