{
  "type": "Feature",
  "properties": {
    "iso:country":"BE",
    "sg:address":"Rue Montenpeine 74",
    "sg:city":"Boussu",
    "sg:orig_category":"Boekhouders",
    "sg:phone":"+32 65 77 97 25",
    "sg:postcode":"7300",
    "sg:province":"Hainaut",
    "wof:name":"Roland Roy",
    "wof:placetype":"venue"
},
  "geometry": {"coordinates":[3.7953929901,50.4227905273],"type":"Point"}
}