{
  "type": "Feature",
  "properties": {
    "addr:full":"Coupure Rechts 302 Gent Oost-Vlaanderen 9000",
    "addr:housenumber":"302",
    "addr:postcode":"9000",
    "addr:street":"Coupure Rechts;Oost-Vlaanderen",
    "iso:country":"BE",
    "sg:address":"Coupure Rechts 302",
    "sg:city":"Gent",
    "sg:orig_category":"Artsen and specialisten",
    "sg:phone":"+32 9 223 86 30",
    "sg:postcode":"9000",
    "sg:province":"Oost-Vlaanderen",
    "wof:name":"L. Staelens",
    "wof:placetype":"venue"
},
  "geometry": {"coordinates":[3.7109360695,51.0510978699],"type":"Point"}
}