{
  "type": "Feature",
  "properties": {
    "addr:full":"Brichautstraat 2 Schaarbeek/schaerbeek Bruxelles-Capitale 1030",
    "addr:housenumber":"2",
    "addr:postcode":"1030",
    "addr:street":"Brichautstraat",
    "iso:country":"BE",
    "sg:address":"Brichautstraat 2",
    "sg:city":"Schaarbeek/schaerbeek",
    "sg:orig_category":"Rechtbanken",
    "sg:phone":"+32 2 215 11 28",
    "sg:postcode":"1030",
    "sg:province":"Bruxelles-Capitale",
    "wof:name":"Vredegerecht/justice De Paix",
    "wof:placetype":"venue"
},
  "geometry": {"coordinates":[4.3672838211,50.8632888794],"type":"Point"}
}