{
  "type": "Feature",
  "properties": {
    "iso:country":"BE",
    "sg:address":"Strandlaan 33",
    "sg:city":"Koksijde",
    "sg:orig_category":"HUISBRANDOLIE",
    "sg:phone":"+32 58 51 11 52",
    "sg:postcode":"8670",
    "sg:province":"West-Vlaanderen",
    "wof:name":"Ticket Gebroeders",
    "wof:placetype":"venue"
},
  "geometry": {"coordinates":[2.6284770966,51.1018180847],"type":"Point"}
}