{
  "type": "Feature",
  "properties": {
    "addr:full":"Rillaarseweg 103 Tielt-winge (tielt) Vlaams-Brabant 3390",
    "addr:housenumber":"103",
    "addr:postcode":"3390",
    "iso:country":"BE",
    "sg:address":"Rillaarseweg 103",
    "sg:city":"Tielt-winge (tielt)",
    "sg:classifiers":[
        {
            "category":"Retail",
            "subcategory":"Funeral Services",
            "type":"Services"
        }
    ],
    "sg:phone":"+32 16 50 11 16",
    "sg:postcode":"3390",
    "sg:province":"Vlaams-Brabant",
    "sg:tags":[
        "director"
    ],
    "wof:name":"Reweghs-pipeleers",
    "wof:placetype":"venue"
},
  "geometry": {"coordinates":[4.9021720886,50.94739151],"type":"Point"}
}