{
  "type": "Feature",
  "properties": {
    "iso:country":"BE",
    "sg:address":"Leuvensesteenweg 176",
    "sg:city":"Boortmeerbeek",
    "sg:orig_category":"Afbraak- and draineerwerken Afval and schroot Gh",
    "sg:phone":"+32 15 51 34 84",
    "sg:postcode":"3191",
    "sg:province":"Vlaams-Brabant",
    "wof:name":"Joska",
    "wof:placetype":"venue"
},
  "geometry": {"coordinates":[4.5564289093,50.9788513184],"type":"Point"}
}