{
  "type": "Feature",
  "properties": {
    "addr:full":"Kerstraat 6 Hoeselt Limburg 3730",
    "addr:housenumber":"6",
    "addr:postcode":"3730",
    "addr:street":"Kerstraat",
    "iso:country":"BE",
    "sg:address":"Kerstraat 6",
    "sg:city":"Hoeselt",
    "sg:orig_category":"Cr\u00e9meries",
    "sg:phone":"+32 89 41 74 50",
    "sg:postcode":"3730",
    "sg:province":"Limburg",
    "wof:name":"Jozef Hardy",
    "wof:placetype":"venue"
},
  "geometry": {"coordinates":[5.4888978004,50.8502578735],"type":"Point"}
}