{
  "type": "Feature",
  "properties": {
    "iso:country":"BE",
    "sg:address":"Kloosterstraat 2",
    "sg:city":"Melle",
    "sg:classifiers":[
        {
            "category":"Cafe",
            "type":"Food & Drink"
        }
    ],
    "sg:phone":"+32 9 252 12 35",
    "sg:postcode":"9090",
    "sg:province":"Oost-Vlaanderen",
    "sg:tags":[
        "caf\u00e9s"
    ],
    "wof:name":"Parochiehuis Van Melle",
    "wof:placetype":"venue"
},
  "geometry": {"coordinates":[3.8032999039,51.0036697388],"type":"Point"}
}