{
  "type": "Feature",
  "properties": {
    "addr:full":"Ankerstraat 136 Sint-niklaas Oost-Vlaanderen 9100",
    "addr:housenumber":"136",
    "addr:postcode":"9100",
    "addr:street":"Ankerstraat",
    "iso:country":"BE",
    "sg:address":"Ankerstraat 136",
    "sg:city":"Sint-niklaas",
    "sg:classifiers":[
        {
            "category":"Shopping",
            "subcategory":"Florist",
            "type":"Retail Goods"
        }
    ],
    "sg:phone":"+32 3 765 07 90",
    "sg:postcode":"9100",
    "sg:province":"Oost-Vlaanderen",
    "sg:tags":[
        "-",
        "supply"
    ],
    "wof:name":"Manuscript Cards",
    "wof:placetype":"venue"
},
  "geometry": {"coordinates":[4.1477851868,51.1677780151],"type":"Point"}
}