{
  "type": "Feature",
  "properties": {
    "addr:full":"Dendermondesteenweg 820 Destelbergen Oost-Vlaanderen 9070",
    "addr:housenumber":"820",
    "addr:postcode":"9070",
    "addr:street":"Dendermondesteenweg",
    "iso:country":"BE",
    "sg:address":"Dendermondesteenweg 820",
    "sg:city":"Destelbergen",
    "sg:classifiers":[
        {
            "category":"Social Services",
            "subcategory":"Job Training",
            "type":"Services"
        }
    ],
    "sg:phone":"+32 9 355 75 54",
    "sg:postcode":"9070",
    "sg:province":"Oost-Vlaanderen",
    "sg:tags":[
        "personnel"
    ],
    "wof:name":"Bni Nv",
    "wof:placetype":"venue"
},
  "geometry": {"coordinates":[3.8379850388,51.0580253601],"type":"Point"}
}