{
  "type": "Feature",
  "properties": {
    "addr:full":"Rue Des Lani\u00e8res 8 Qu\u00e9vy (qu\u00e9vy-le-grand) Hainaut 7040",
    "addr:housenumber":"8",
    "addr:postcode":"7040",
    "addr:street":"Rue Des Lanie\u0300Res;Que\u0301Vy-Le-Grand Hainaut",
    "iso:country":"BE",
    "sg:address":"Rue Des Lani\u00e8res 8",
    "sg:city":"Qu\u00e9vy (qu\u00e9vy-le-grand)",
    "sg:classifiers":[
        {
            "category":"Professional",
            "subcategory":"Business Services",
            "type":"Services"
        }
    ],
    "sg:phone":"+32 65 56 94 11",
    "sg:postcode":"7040",
    "sg:province":"Hainaut",
    "sg:tags":[
        "bookmaker"
    ],
    "wof:name":"Vincennes (tierce)",
    "wof:placetype":"venue"
},
  "geometry": {"coordinates":[3.94688797,50.3603591919],"type":"Point"}
}