{
  "type": "Feature",
  "properties": {
    "addr:full":"Veerstraat 43 Berlare Oost-Vlaanderen 9290",
    "addr:housenumber":"43",
    "addr:postcode":"9290",
    "addr:street":"Veerstraat",
    "iso:country":"BE",
    "sg:address":"Veerstraat 43",
    "sg:city":"Berlare",
    "sg:orig_category":"Kapsalons",
    "sg:phone":"+32 9 367 76 63",
    "sg:postcode":"9290",
    "sg:province":"Oost-Vlaanderen",
    "wof:name":"Kapsalon Geert",
    "wof:placetype":"venue"
},
  "geometry": {"coordinates":[3.9499850273,51.029548645],"type":"Point"}
}