{
  "type": "Feature",
  "properties": {
    "addr:full":"Chemin D'ardembreucq 3 Ath Hainaut 7822",
    "addr:housenumber":"3",
    "addr:postcode":"7822",
    "addr:street":"Chemin D'Ardembreucq",
    "iso:country":"BE",
    "sg:address":"Chemin D'ardembreucq 3",
    "sg:city":"Ath",
    "sg:orig_category":"Eleveurs de bovins",
    "sg:phone":"+32 68 55 12 04",
    "sg:postcode":"7822",
    "sg:province":"Hainaut",
    "wof:name":"Christophe Boisdenghien",
    "wof:placetype":"venue"
},
  "geometry": {"coordinates":[3.8474669456,50.6349372864],"type":"Point"}
}