{
  "type": "Feature",
  "properties": {
    "addr:full":"Bloklaan 18 Asse Vlaams-Brabant 1730",
    "addr:housenumber":"18",
    "addr:postcode":"1730",
    "addr:street":"Bloklaan",
    "iso:country":"BE",
    "sg:address":"Bloklaan 18",
    "sg:city":"Asse",
    "sg:orig_category":"Fleurs and plantes",
    "sg:phone":"+32 2 452 83 76",
    "sg:postcode":"1730",
    "sg:province":"Vlaams-Brabant",
    "wof:name":"Berghman Bloemen",
    "wof:placetype":"venue"
},
  "geometry": {"coordinates":[4.195045948,50.9097938538],"type":"Point"}
}