{
  "type": "Feature",
  "properties": {
    "addr:full":"Rue Des Capucins 17 Ciney Namur 5590",
    "addr:housenumber":"17",
    "addr:postcode":"5590",
    "addr:street":"Rue Des Capucins",
    "iso:country":"BE",
    "sg:address":"Rue Des Capucins 17",
    "sg:city":"Ciney",
    "sg:orig_category":"Enseignement maternel and primaire",
    "sg:phone":"+32 83 21 56 07",
    "sg:postcode":"5590",
    "sg:province":"Namur",
    "wof:name":"Ecole Fondamentale Libre",
    "wof:placetype":"venue"
},
  "geometry": {"coordinates":[5.093957901,50.2901725769],"type":"Point"}
}