{
  "type": "Feature",
  "properties": {
    "iso:country":"BE",
    "sg:address":"Place Des Alli\u00e9s 4b",
    "sg:city":"Mons",
    "sg:classifiers":[
        {
            "category":"Health Services",
            "subcategory":"Dentist",
            "type":"Services"
        }
    ],
    "sg:phone":"+32 65 34 85 97",
    "sg:postcode":"7000",
    "sg:province":"Hainaut",
    "wof:name":"Piller B",
    "wof:placetype":"venue"
},
  "geometry": {"coordinates":[3.9389829636,50.4489173889],"type":"Point"}
}