{
  "type": "Feature",
  "properties": {
    "iso:country":"BE",
    "sg:address":"Rue Jules Destr\u00e9e 19",
    "sg:city":"Aiseau-presles (roselies)",
    "sg:classifiers":[
        {
            "category":"Health Services",
            "subcategory":"Doctor",
            "type":"Services"
        }
    ],
    "sg:phone":"+32 71 74 33 03",
    "sg:postcode":"6250",
    "sg:province":"Hainaut",
    "sg:tags":[
        "medicinephysicians",
        "surgeon"
    ],
    "wof:name":"Arfa Nadia",
    "wof:placetype":"venue"
},
  "geometry": {"coordinates":[4.5720071793,50.4249458313],"type":"Point"}
}