{
  "type": "Feature",
  "properties": {
    "iso:country":"BE",
    "sg:address":"Chauss\u00c9e De Wervicq 275",
    "sg:city":"Komen-waasten/comines-warneton",
    "sg:orig_category":"R\u00e9parations d'appareils \u00e9lectrom\u00e9nagers. Electrom\u00e9nager, t\u00e9l\u00e9visions and radios",
    "sg:phone":"+32 56 55 61 28",
    "sg:postcode":"7780",
    "sg:province":"Hainaut",
    "wof:name":"Serge Plantefeve",
    "wof:placetype":"venue"
},
  "geometry": {"coordinates":[3.0177650452,50.7766265869],"type":"Point"}
}