{
  "type": "Feature",
  "properties": {
    "iso:country":"BE",
    "sg:address":"Rue Du Geer 38",
    "sg:city":"Oreye (grand)",
    "sg:orig_category":"Banques and organismes de cr\u00e9dit",
    "sg:phone":"+32 19 67 78 85",
    "sg:postcode":"4360",
    "sg:province":"Li\u00e8ge",
    "wof:name":"Gordenne Jacob Bureau",
    "wof:placetype":"venue"
},
  "geometry": {"coordinates":[5.3567152023,50.7285881042],"type":"Point"}
}