{
  "type": "Feature",
  "properties": {
    "addr:full":"Lamstraat 19 Merelbeke Oost-Vlaanderen 9820",
    "addr:housenumber":"19",
    "addr:postcode":"9820",
    "addr:street":"Lamstraat",
    "iso:country":"BE",
    "sg:address":"Lamstraat 19",
    "sg:city":"Merelbeke",
    "sg:classifiers":[
        {
            "category":"Building & Trades",
            "subcategory":"Landscaping Services",
            "type":"Services"
        }
    ],
    "sg:phone":"+32 9 231 67 91",
    "sg:postcode":"9820",
    "sg:province":"Oost-Vlaanderen",
    "sg:tags":[
        "gardening",
        "garden",
        "maintenance"
    ],
    "wof:name":"Van Isacker T",
    "wof:placetype":"venue"
},
  "geometry": {"coordinates":[3.7571790218,50.986656189],"type":"Point"}
}