{
  "type": "Feature",
  "properties": {
    "addr:full":"Chauss\u00e9e De Lille 4 Box 7 Tournai Hainaut 7500",
    "addr:housenumber":"4;7",
    "addr:postcode":"7500",
    "addr:street":"Chausse\u0301E De Lille;Box",
    "iso:country":"BE",
    "sg:address":"Chauss\u00e9e De Lille 4 Box 7",
    "sg:city":"Tournai",
    "sg:classifiers":[
        {
            "category":"Professional",
            "subcategory":"Accounting & Tax Preparation",
            "type":"Services"
        }
    ],
    "sg:phone":"+32 69 21 64 83",
    "sg:postcode":"7500",
    "sg:province":"Hainaut",
    "sg:tags":[
        "accountant"
    ],
    "wof:name":"Moulart A",
    "wof:placetype":"venue"
},
  "geometry": {"coordinates":[3.3762209415,50.6052207947],"type":"Point"}
}