{
  "type": "Feature",
  "properties": {
    "iso:country":"BE",
    "sg:address":"Vaartstraat 35",
    "sg:city":"Harelbeke",
    "sg:orig_category":"Produits \u00e0 base de pommes de terre Fruits and l\u00e9gumes Gr",
    "sg:phone":"+32 56 21 05 90",
    "sg:postcode":"8530",
    "sg:province":"West-Vlaanderen",
    "wof:name":"Deconick Georges & Zn",
    "wof:placetype":"venue"
},
  "geometry": {"coordinates":[3.3081190586,50.8287734985],"type":"Point"}
}