{
  "type": "Feature",
  "properties": {
    "addr:full":"Brugsesteenweg 273 Kuurne West-Vlaanderen 8520",
    "addr:housenumber":"273",
    "addr:postcode":"8520",
    "addr:street":"Brugsesteenweg",
    "iso:country":"BE",
    "sg:address":"Brugsesteenweg 273",
    "sg:city":"Kuurne",
    "sg:classifiers":[
        {
            "category":"Bars & Pubs",
            "type":"Food & Drink"
        }
    ],
    "sg:phone":"+32 56 37 17 18",
    "sg:postcode":"8520",
    "sg:province":"West-Vlaanderen",
    "wof:name":"De Wegwijzer",
    "wof:placetype":"venue"
},
  "geometry": {"coordinates":[3.2703230381,50.8597297668],"type":"Point"}
}