{
  "type": "Feature",
  "properties": {
    "addr:full":"Kerkstraat 3 Nieuwpoort West-Vlaanderen 8620",
    "addr:housenumber":"3",
    "addr:postcode":"8620",
    "addr:street":"Kerkstraat",
    "iso:country":"BE",
    "sg:address":"Kerkstraat 3",
    "sg:city":"Nieuwpoort",
    "sg:orig_category":"Pharmaciens",
    "sg:phone":"+32 58 23 31 92",
    "sg:postcode":"8620",
    "sg:province":"West-Vlaanderen",
    "wof:name":"Apoteek Amery",
    "wof:placetype":"venue"
},
  "geometry": {"coordinates":[2.7504239082,51.129447937],"type":"Point"}
}