{
  "type": "Feature",
  "properties": {
    "iso:country":"BE",
    "sg:address":"Parc Industriel De Petit-rechain 20",
    "sg:city":"Herve",
    "sg:classifiers":[
        {
            "category":"Retail",
            "subcategory":"Auto Repair",
            "type":"Services"
        }
    ],
    "sg:phone":"+32 87 31 59 49",
    "sg:postcode":"4650",
    "sg:province":"Li\u00e8ge",
    "sg:tags":[
        "garage"
    ],
    "wof:name":"Willemsens",
    "wof:placetype":"venue"
},
  "geometry": {"coordinates":[5.835627079,50.6292533875],"type":"Point"}
}