{
  "type": "Feature",
  "properties": {
    "iso:country":"BE",
    "sg:address":"Poststraat 10",
    "sg:city":"Roeselare",
    "sg:orig_category":"Enseignement secondaire g\u00e9n\u00e9ral. Enseignement secondaire technique and professionnel",
    "sg:phone":"+32 51 20 14 57",
    "sg:postcode":"8800",
    "sg:province":"West-Vlaanderen",
    "wof:name":"Inst. H.elisabeth Grauwz.",
    "wof:placetype":"venue"
},
  "geometry": {"coordinates":[3.1262760162,50.945854187],"type":"Point"}
}