{
  "type": "Feature",
  "properties": {
    "iso:country":"BE",
    "sg:address":"Rue Ledocte 11",
    "sg:city":"Chastre",
    "sg:orig_category":"Slagers",
    "sg:phone":"+32 10 65 59 04",
    "sg:postcode":"1450",
    "sg:province":"Brabant Wallon",
    "wof:name":"Boucherie Verhoeven",
    "wof:placetype":"venue"
},
  "geometry": {"coordinates":[4.6506447792,50.6079025269],"type":"Point"}
}