{
  "type": "Feature",
  "properties": {
    "iso:country":"BE",
    "sg:address":"Clos Fleuri 10",
    "sg:city":"Li\u00e8ge 1 (grivegn\u00e9e)",
    "sg:classifiers":[
        {
            "category":"Health Services",
            "subcategory":"Medical Lab",
            "type":"Services"
        }
    ],
    "sg:phone":"+32 4 343 16 41",
    "sg:postcode":"4030",
    "sg:province":"Li\u00e8ge",
    "sg:tags":[
        "laboratory",
        "dental"
    ],
    "wof:name":"L.d.p. Paulus",
    "wof:placetype":"venue"
},
  "geometry": {"coordinates":[5.6030302048,50.6251716614],"type":"Point"}
}