{
  "type": "Feature",
  "properties": {
    "iso:country":"BE",
    "sg:address":"Herentalsstraat 1 Box 1",
    "sg:city":"Turnhout",
    "sg:classifiers":[
        {
            "category":"Professional",
            "subcategory":"Art Services",
            "type":"Services"
        }
    ],
    "sg:phone":"+32 14 65 28 00",
    "sg:postcode":"2300",
    "sg:province":"Antwerpen",
    "sg:tags":[
        "realization",
        "audio-visual"
    ],
    "wof:name":"Norvell Jefferson Belgium",
    "wof:placetype":"venue"
},
  "geometry": {"coordinates":[4.9493079185,51.3222999573],"type":"Point"}
}