{
  "type": "Feature",
  "properties": {
    "iso:country":"BE",
    "sg:address":"Rue De Rollebeek 5",
    "sg:city":"Bruxelles",
    "sg:classifiers":[
        {
            "category":"Coffee & Tea",
            "type":"Food & Drink"
        }
    ],
    "sg:phone":"+32 2 511 81 17",
    "sg:postcode":"1000",
    "sg:province":"Bruxelles-Capitale",
    "sg:tags":[
        "retail",
        "-"
    ],
    "wof:name":"The Tea House",
    "wof:placetype":"venue"
},
  "geometry": {"coordinates":[4.3523898125,50.842048645],"type":"Point"}
}