{
  "type": "Feature",
  "properties": {
    "iso:country":"BE",
    "sg:address":"Avenue Lavoisier 35",
    "sg:city":"Wavre",
    "sg:classifiers":[
        {
            "category":"Shopping",
            "subcategory":"Clothing, Apparel, & Fashions",
            "type":"Retail Goods"
        }
    ],
    "sg:phone":"+32 10 24 85 92",
    "sg:postcode":"1300",
    "sg:province":"Brabant Wallon",
    "sg:tags":[
        "sportswear"
    ],
    "wof:name":"Lafuma Willefert",
    "wof:placetype":"venue"
},
  "geometry": {"coordinates":[4.5867071152,50.7363777161],"type":"Point"}
}