{
  "type": "Feature",
  "properties": {
    "iso:country":"BE",
    "sg:address":"Claesplein 8",
    "sg:city":"Halle",
    "sg:orig_category":"Banken and kredietinstellingen",
    "sg:phone":"+32 2 356 37 79",
    "sg:postcode":"1502",
    "sg:province":"Vlaams-Brabant",
    "wof:name":"Bbl",
    "wof:placetype":"venue"
},
  "geometry": {"coordinates":[4.2230520248,50.7133674622],"type":"Point"}
}