{
  "type": "Feature",
  "properties": {
    "iso:country":"BE",
    "sg:address":"Stokthoekstraat 35",
    "sg:city":"Temse",
    "sg:orig_category":"Installation de menuiserie en bois and plastique",
    "sg:phone":"+32 52 46 00 93",
    "sg:postcode":"9140",
    "sg:province":"Oost-Vlaanderen",
    "wof:name":"Roger Govaerts",
    "wof:placetype":"venue"
},
  "geometry": {"coordinates":[4.1327137947,51.1263122559],"type":"Point"}
}