{
  "type": "Feature",
  "properties": {
    "addr:full":"Goffontaine 47 Pepinster Li\u00e8ge 4860",
    "addr:housenumber":"47",
    "addr:postcode":"4860",
    "addr:street":"Goffontaine",
    "iso:country":"BE",
    "sg:address":"Goffontaine 47",
    "sg:city":"Pepinster",
    "sg:orig_category":"Non-Classified Establishments",
    "sg:phone":"+32 87 46 04 73",
    "sg:postcode":"4860",
    "sg:province":"Li\u00e8ge",
    "wof:name":"Moulin Fisenne Sa",
    "wof:placetype":"venue"
},
  "geometry": {"coordinates":[5.8032469749,50.5693511963],"type":"Point"}
}