{
  "type": "Feature",
  "properties": {
    "iso:country":"BE",
    "sg:address":"Schloss Strasse 41",
    "sg:city":"Lontzen/lontzen",
    "sg:orig_category":"Rundveehouders",
    "sg:phone":"+32 87 63 06 38",
    "sg:postcode":"4710",
    "sg:province":"Li\u00e8ge",
    "wof:name":"Leonard Kessel",
    "wof:placetype":"venue"
},
  "geometry": {"coordinates":[6.0109090805,50.6801757812],"type":"Point"}
}