{
  "type": "Feature",
  "properties": {
    "iso:country":"BE",
    "sg:address":"Pikkeleerstraat 22",
    "sg:city":"Herk-de-stad",
    "sg:classifiers":[
        {
            "category":"Cafe",
            "type":"Food & Drink"
        }
    ],
    "sg:phone":"+32 13 55 15 47",
    "sg:postcode":"3540",
    "sg:province":"Limburg",
    "sg:tags":[
        "caf\u00e9s"
    ],
    "wof:name":"Hugo Laenen",
    "wof:placetype":"venue"
},
  "geometry": {"coordinates":[5.1662368774,50.9348983765],"type":"Point"}
}