{
  "type": "Feature",
  "properties": {
    "iso:country":"BE",
    "sg:address":"Weidelaan 16",
    "sg:city":"Dilbeek",
    "sg:orig_category":"Agences de presse",
    "sg:phone":"+32 2 567 21 13",
    "sg:postcode":"1700",
    "sg:province":"Vlaams-Brabant",
    "wof:name":"Freddy Kempeneer",
    "wof:placetype":"venue"
},
  "geometry": {"coordinates":[4.2624697685,50.8459358215],"type":"Point"}
}