{
  "type": "Feature",
  "properties": {
    "addr:full":"Hovestraat 35 Edegem Antwerpen 2650",
    "addr:housenumber":"35",
    "addr:postcode":"2650",
    "addr:street":"Hovestraat",
    "iso:country":"BE",
    "sg:address":"Hovestraat 35",
    "sg:city":"Edegem",
    "sg:orig_category":"Banken and kredietinstellingen",
    "sg:phone":"+32 3 457 11 39",
    "sg:postcode":"2650",
    "sg:province":"Antwerpen",
    "wof:name":"Dexia",
    "wof:placetype":"venue"
},
  "geometry": {"coordinates":[4.4483008385,51.1555862427],"type":"Point"}
}