{
  "type": "Feature",
  "properties": {
    "iso:country":"BE",
    "sg:address":"Avenue Blonden 44b41",
    "sg:city":"Li\u00c8ge",
    "sg:orig_category":"Boekhouders",
    "sg:phone":"+32 4 252 77 84",
    "sg:postcode":"4000",
    "sg:province":"Li\u00e8ge",
    "wof:name":"Beno\u00cet Clotuche",
    "wof:placetype":"venue"
},
  "geometry": {"coordinates":[5.5702238083,50.6288032532],"type":"Point"}
}