{
  "type": "Feature",
  "properties": {
    "iso:country":"BE",
    "sg:address":"Dr\u00e8ve De Lorraine 45",
    "sg:city":"Bruxelles (uccle)",
    "sg:classifiers":[
        {
            "category":"Organizations",
            "subcategory":"Professional Association",
            "type":"Services"
        }
    ],
    "sg:phone":"+32 2 375 40 20",
    "sg:postcode":"1180",
    "sg:province":"Bruxelles-Capitale",
    "sg:tags":[
        "trade-union",
        "federation"
    ],
    "wof:name":"Repr\u00e9sentation Commerciale De La F\u00e9d\u00e9ration De Russie En Belgique Et Au Luxembourg",
    "wof:placetype":"venue"
},
  "geometry": {"coordinates":[4.387556076,50.7823753357],"type":"Point"}
}