{
  "type": "Feature",
  "properties": {
    "addr:full":"Lepelhoekstraat 49 Sint-niklaas Oost-Vlaanderen 9100",
    "addr:housenumber":"49",
    "addr:postcode":"9100",
    "addr:street":"Lepelhoekstraat",
    "iso:country":"BE",
    "sg:address":"Lepelhoekstraat 49",
    "sg:city":"Sint-niklaas",
    "sg:classifiers":[
        {
            "category":"Autos & Motor Vehicles",
            "subcategory":"Automobile Sales",
            "type":"Retail Goods"
        }
    ],
    "sg:phone":"+32 3 766 24 94",
    "sg:postcode":"9100",
    "sg:province":"Oost-Vlaanderen",
    "sg:tags":[
        "car",
        "used",
        "-"
    ],
    "wof:name":"Goossens J",
    "wof:placetype":"venue"
},
  "geometry": {"coordinates":[4.1424207687,51.179271698],"type":"Point"}
}