{
  "type": "Feature",
  "properties": {
    "addr:full":"Rue Du Cimeti\u00e8re 9b Esneux Li\u00e8ge 4130",
    "addr:housenumber":"9b",
    "addr:postcode":"4130",
    "addr:street":"Rue Du Cimetie\u0300Re",
    "iso:country":"BE",
    "sg:address":"Rue Du Cimeti\u00e8re 9b",
    "sg:city":"Esneux",
    "sg:classifiers":[
        {
            "category":"Building & Trades",
            "subcategory":"Pest Control",
            "type":"Services"
        }
    ],
    "sg:phone":"+32 4 380 26 17",
    "sg:postcode":"4130",
    "sg:province":"Li\u00e8ge",
    "sg:tags":[
        "painting",
        "contractor"
    ],
    "wof:name":"Delavignette J",
    "wof:placetype":"venue"
},
  "geometry": {"coordinates":[5.5790510178,50.5354156494],"type":"Point"}
}