{
  "type": "Feature",
  "properties": {
    "addr:full":"Zuidkaai 4 Ingelmunster West-Vlaanderen 8770",
    "addr:housenumber":"4",
    "addr:postcode":"8770",
    "addr:street":"Zuidkaai",
    "iso:country":"BE",
    "sg:address":"Zuidkaai 4",
    "sg:city":"Ingelmunster",
    "sg:classifiers":[
        {
            "category":"Farming",
            "subcategory":"Farm",
            "type":"Manufacturing & Wholesale Goods"
        }
    ],
    "sg:phone":"+32 51 30 44 38",
    "sg:postcode":"8770",
    "sg:province":"West-Vlaanderen",
    "sg:tags":[
        "horticulture",
        "agriculture",
        "livestock"
    ],
    "wof:name":"Westhoekveen Nv",
    "wof:placetype":"venue"
},
  "geometry": {"coordinates":[3.2848858833,50.9110145569],"type":"Point"}
}