{
  "type": "Feature",
  "properties": {
    "addr:full":"'t Leeghoek 3 Kruishoutem (wannegem-lede) Oost-Vlaanderen 9772",
    "addr:housenumber":"3",
    "addr:postcode":"9772",
    "addr:street":"'",
    "iso:country":"BE",
    "sg:address":"'t Leeghoek 3",
    "sg:city":"Kruishoutem (wannegem-lede)",
    "sg:classifiers":[
        {
            "category":"Professional",
            "subcategory":"Art Services",
            "type":"Services"
        }
    ],
    "sg:phone":"+32 9 383 57 19",
    "sg:postcode":"9772",
    "sg:province":"Oost-Vlaanderen",
    "sg:tags":[
        "sculptor"
    ],
    "wof:name":"De Meester W",
    "wof:placetype":"venue"
},
  "geometry": {"coordinates":[3.5455610752,50.8954772949],"type":"Point"}
}