{
  "type": "Feature",
  "properties": {
    "addr:full":"Varenstraat 46 Hemiksem Antwerpen 2620",
    "addr:housenumber":"46",
    "addr:postcode":"2620",
    "addr:street":"Varenstraat",
    "iso:country":"BE",
    "sg:address":"Varenstraat 46",
    "sg:city":"Hemiksem",
    "sg:orig_category":"Studios photographiques",
    "sg:phone":"+32 3 887 71 87",
    "sg:postcode":"2620",
    "sg:province":"Antwerpen",
    "wof:name":"Linda De Wolf",
    "wof:placetype":"venue"
},
  "geometry": {"coordinates":[4.3450870514,51.1527519226],"type":"Point"}
}