{
  "type": "Feature",
  "properties": {
    "iso:country":"BE",
    "sg:address":"Zandhoefstraat 28",
    "sg:city":"Geel",
    "sg:classifiers":[
        {
            "category":"Communications",
            "subcategory":"Radio Station",
            "type":"Services"
        }
    ],
    "sg:phone":"+32 14 58 82 82",
    "sg:postcode":"2440",
    "sg:province":"Antwerpen",
    "sg:tags":[
        "diffusion",
        "production",
        "de",
        "programme"
    ],
    "wof:name":"Lokale Radio Geel",
    "wof:placetype":"venue"
},
  "geometry": {"coordinates":[4.980050087,51.1787948608],"type":"Point"}
}