{
  "type": "Feature",
  "properties": {
    "addr:full":"Quai March\u00c9 Au Poisson 23 Tournai Hainaut 7500",
    "addr:housenumber":"23",
    "addr:postcode":"7500",
    "addr:street":"Quai Marche\u0301 Au Poisson",
    "iso:country":"BE",
    "sg:address":"Quai March\u00c9 Au Poisson 23",
    "sg:city":"Tournai",
    "sg:orig_category":"Cr\u00e9meries",
    "sg:phone":"+32 69 23 24 16",
    "sg:postcode":"7500",
    "sg:province":"Hainaut",
    "wof:name":"Luce Ratte",
    "wof:placetype":"venue"
},
  "geometry": {"coordinates":[3.3920741081,50.6070632935],"type":"Point"}
}