{
  "type": "Feature",
  "properties": {
    "addr:full":"Rue Du Tombeux 17 Verviers Li\u00e8ge 4801",
    "addr:housenumber":"17",
    "addr:postcode":"4801",
    "addr:street":"Rue Du Tombeux",
    "iso:country":"BE",
    "sg:address":"Rue Du Tombeux 17",
    "sg:city":"Verviers",
    "sg:orig_category":"Centres de relaxation and bien-\u00eatre",
    "sg:phone":"+32 87 31 07 96",
    "sg:postcode":"4801",
    "sg:province":"Li\u00e8ge",
    "wof:name":"Primasolar",
    "wof:placetype":"venue"
},
  "geometry": {"coordinates":[5.8930549622,50.5922393799],"type":"Point"}
}