{
  "type": "Feature",
  "properties": {
    "addr:full":"Jozef Van Elewijckstraat 56 Grimbergen (strombeek-bever) Vlaams-Brabant 1853",
    "addr:housenumber":"56",
    "addr:postcode":"1853",
    "addr:street":"Jozef Van Elewijckstraat",
    "iso:country":"BE",
    "sg:address":"Jozef Van Elewijckstraat 56",
    "sg:city":"Grimbergen (strombeek-bever)",
    "sg:classifiers":[
        {
            "category":"Building & Trades",
            "subcategory":"Cleaning & Sanitation",
            "type":"Services"
        }
    ],
    "sg:phone":"+32 2 267 30 71",
    "sg:postcode":"1853",
    "sg:province":"Vlaams-Brabant",
    "sg:tags":[
        "fa\u00e7ade",
        "maintenance"
    ],
    "wof:name":"New Reno Facade Bvba",
    "wof:placetype":"venue"
},
  "geometry": {"coordinates":[4.352104187,50.90391922],"type":"Point"}
}