{
  "type": "Feature",
  "properties": {
    "iso:country":"BE",
    "sg:address":"Bld Albert-elisabeth 11",
    "sg:city":"Mons",
    "sg:orig_category":"Studios photographiques",
    "sg:phone":"+32 65 36 09 17",
    "sg:postcode":"7000",
    "sg:province":"Hainaut",
    "wof:name":"Michel De Neve",
    "wof:placetype":"venue"
},
  "geometry": {"coordinates":[3.9542210102,50.4478149414],"type":"Point"}
}