{
  "type": "Feature",
  "properties": {
    "iso:country":"BE",
    "sg:address":"Rue De Paturages 146bb",
    "sg:city":"Colfontaine",
    "sg:orig_category":"Artiesten and kunstenaars",
    "sg:phone":"+32 65 67 25 89",
    "sg:postcode":"7340",
    "sg:province":"Hainaut",
    "wof:name":"Carion",
    "wof:placetype":"venue"
},
  "geometry": {"coordinates":[3.8537809849,50.4110908508],"type":"Point"}
}