{
  "type": "Feature",
  "properties": {
    "iso:country":"BE",
    "sg:address":"Gistelsteenweg 329",
    "sg:city":"Jabbeke",
    "sg:classifiers":[
        {
            "category":"Professional",
            "type":"Services"
        }
    ],
    "sg:phone":"+32 50 81 38 48",
    "sg:postcode":"8490",
    "sg:province":"West-Vlaanderen",
    "sg:tags":[
        "ceremony",
        "master"
    ],
    "wof:name":"Tavernier D",
    "wof:placetype":"venue"
},
  "geometry": {"coordinates":[3.1029109955,51.1789932251],"type":"Point"}
}