{
  "type": "Feature",
  "properties": {
    "addr:full":"Rue De L'egalit\u00e9 211 Seraing (ougr\u00e9e) Li\u00e8ge 4102",
    "addr:housenumber":"211",
    "addr:postcode":"4102",
    "addr:street":"Rue De L'Egalite \u0301",
    "iso:country":"BE",
    "sg:address":"Rue De L'egalit\u00e9 211",
    "sg:city":"Seraing (ougr\u00e9e)",
    "sg:classifiers":[
        {
            "category":"Personal",
            "subcategory":"Beauty Salon",
            "type":"Services"
        }
    ],
    "sg:phone":"+32 4 337 24 11",
    "sg:postcode":"4102",
    "sg:province":"Li\u00e8ge",
    "sg:tags":[
        "lady",
        "-",
        "hairdressing"
    ],
    "wof:name":"Lea",
    "wof:placetype":"venue"
},
  "geometry": {"coordinates":[5.5377650261,50.5971374512],"type":"Point"}
}