{
  "type": "Feature",
  "properties": {
    "iso:country":"BE",
    "sg:address":"Rue Potaarde 109",
    "sg:city":"Bruxelles (berchem-sainte-agathe)",
    "sg:classifiers":[
        {
            "category":"Health Services",
            "subcategory":"Health Practitioner",
            "type":"Services"
        }
    ],
    "sg:phone":"+32 2 465 56 31",
    "sg:postcode":"1082",
    "sg:province":"Bruxelles-Capitale",
    "sg:tags":[
        "physiotherapist"
    ],
    "wof:name":"Berghmans R",
    "wof:placetype":"venue"
},
  "geometry": {"coordinates":[4.2819228172,50.8637733459],"type":"Point"}
}