{
  "type": "Feature",
  "properties": {
    "addr:full":"Waaslandlaan 12 Lokeren Oost-Vlaanderen 9160",
    "addr:housenumber":"12",
    "addr:postcode":"9160",
    "addr:street":"Waaslandlaan",
    "iso:country":"BE",
    "sg:address":"Waaslandlaan 12",
    "sg:city":"Lokeren",
    "sg:orig_category":"Huishoudtextiel and -linnen Fab",
    "sg:phone":"+32 9 349 41 32",
    "sg:postcode":"9160",
    "sg:province":"Oost-Vlaanderen",
    "wof:name":"Caro Bedding",
    "wof:placetype":"venue"
},
  "geometry": {"coordinates":[4.0115551949,51.1209487915],"type":"Point"}
}