{
  "type": "Feature",
  "properties": {
    "iso:country":"BE",
    "sg:address":"Kouterbaan 21",
    "sg:city":"Lebbeke",
    "sg:orig_category":"Installatie van houten of kunststof schrijnwerk",
    "sg:phone":"+32 52 41 54 24",
    "sg:postcode":"9280",
    "sg:province":"Oost-Vlaanderen",
    "wof:name":"Intercor",
    "wof:placetype":"venue"
},
  "geometry": {"coordinates":[4.1208910942,50.9980888367],"type":"Point"}
}