{
  "type": "Feature",
  "properties": {
    "iso:country":"BE",
    "sg:address":"Rue De La Bouteillerie 2",
    "sg:city":"Estaimpuis",
    "sg:classifiers":[
        {
            "category":"Sports & Exercise",
            "subcategory":"Stables",
            "type":"Entertainment"
        }
    ],
    "sg:phone":"+32 56 48 90 31",
    "sg:postcode":"7730",
    "sg:province":"Hainaut",
    "sg:tags":[
        "riding",
        "school"
    ],
    "wof:name":"Man\u00e8ge D'estaimpuis",
    "wof:placetype":"venue"
},
  "geometry": {"coordinates":[3.2571489811,50.7088394165],"type":"Point"}
}