{
  "type": "Feature",
  "properties": {
    "iso:country":"BE",
    "sg:address":"Kapelstraat 44",
    "sg:city":"Sint-eloois-winkel",
    "sg:classifiers":[
        {
            "category":"Home & Garden",
            "subcategory":"Carpets & Floor Coverings",
            "type":"Retail Goods"
        }
    ],
    "sg:phone":"+32 64 22 71 93",
    "sg:postcode":"8880",
    "sg:province":"West-Vlaanderen",
    "sg:tags":[
        "flat",
        "leaf",
        "spring"
    ],
    "wof:name":"Ressort Routier Sprl",
    "wof:placetype":"venue"
},
  "geometry": {"coordinates":[4.2331838608,50.4764099121],"type":"Point"}
}