{
  "type": "Feature",
  "properties": {
    "iso:country":"BE",
    "sg:address":"Joseph Kelchtermansstr. 26",
    "sg:city":"Anderlecht",
    "sg:orig_category":"Fotografen and fotostudio's",
    "sg:phone":"+32 2 527 23 81",
    "sg:postcode":"1070",
    "sg:province":"Bruxelles-Capitale",
    "wof:name":"Dany Leroy",
    "wof:placetype":"venue"
},
  "geometry": {"coordinates":[4.303027153,50.8450469971],"type":"Point"}
}