{
  "type": "Feature",
  "properties": {
    "addr:full":"Avenue Chanoine Roose 7 Bruxelles (anderlecht) Bruxelles-Capitale 1070",
    "addr:housenumber":"7",
    "addr:postcode":"1070",
    "addr:street":"Avenue Chanoine Roose",
    "iso:country":"BE",
    "sg:address":"Avenue Chanoine Roose 7",
    "sg:city":"Bruxelles (anderlecht)",
    "sg:classifiers":[
        {
            "category":"Professional",
            "subcategory":"Management & Consulting",
            "type":"Services"
        }
    ],
    "sg:phone":"+32 2 523 62 21",
    "sg:postcode":"1070",
    "sg:province":"Bruxelles-Capitale",
    "sg:tags":[
        "consultant"
    ],
    "wof:name":"Synopsis Consulting",
    "wof:placetype":"venue"
},
  "geometry": {"coordinates":[4.2865581512,50.8323364258],"type":"Point"}
}