{
  "type": "Feature",
  "properties": {
    "iso:country":"BE",
    "sg:address":"Place Aux Foires 17",
    "sg:city":"Marche-en-famenne",
    "sg:orig_category":"RESTAURANTS: LIVRAISON \u00c0 DOMICILE. RESTAURANTS FAST FOOD AND \u00c0 EMPORTER",
    "sg:phone":"+32 84 31 57 64",
    "sg:postcode":"6900",
    "sg:province":"Luxembourg",
    "wof:name":"Pizza Pronto",
    "wof:placetype":"venue"
},
  "geometry": {"coordinates":[5.3449068069,50.2252922058],"type":"Point"}
}