{
  "type": "Feature",
  "properties": {
    "addr:full":"Roeselaarsestraat 188 Moorslede West-Vlaanderen 8890",
    "addr:housenumber":"188",
    "addr:postcode":"8890",
    "addr:street":"Roeselaarsestraat",
    "iso:country":"BE",
    "sg:address":"Roeselaarsestraat 188",
    "sg:city":"Moorslede",
    "sg:classifiers":[
        {
            "category":"Food & Beverages",
            "subcategory":"Fruits & Vegetables",
            "type":"Retail Goods"
        }
    ],
    "sg:phone":"+32 51 77 83 30",
    "sg:postcode":"8890",
    "sg:province":"West-Vlaanderen",
    "sg:tags":[
        "-"
    ],
    "wof:name":"Cauwelier A",
    "wof:placetype":"venue"
},
  "geometry": {"coordinates":[3.0724830627,50.9042663574],"type":"Point"}
}