{
  "type": "Feature",
  "properties": {
    "addr:full":"Dweerse Kromstraat 66 Beveren (beveren-waas) Oost-Vlaanderen 9120",
    "addr:housenumber":"66",
    "addr:postcode":"9120",
    "addr:street":"Kromstraat;Oost-Vlaanderen",
    "iso:country":"BE",
    "sg:address":"Dweerse Kromstraat 66",
    "sg:city":"Beveren (beveren-waas)",
    "sg:classifiers":[
        {
            "category":"Home & Garden",
            "subcategory":"Garden Supply",
            "type":"Retail Goods"
        }
    ],
    "sg:phone":"+32 3 775 84 56",
    "sg:postcode":"9120",
    "sg:province":"Oost-Vlaanderen",
    "wof:name":"Bloemenhuis Van Hove Nv",
    "wof:placetype":"venue"
},
  "geometry": {"coordinates":[4.2776970863,51.1997070312],"type":"Point"}
}