{
  "type": "Feature",
  "properties": {
    "addr:full":"Rue Biche Les Pr\u00e9s 5 Trooz (for\u00eat) Li\u00e8ge 4870",
    "addr:housenumber":"5",
    "addr:postcode":"4870",
    "addr:street":"Rue Biche Les Pre\u0301S;Fore\u0302T",
    "iso:country":"BE",
    "sg:address":"Rue Biche Les Pr\u00e9s 5",
    "sg:city":"Trooz (for\u00eat)",
    "sg:classifiers":[
        {
            "category":"Professional",
            "subcategory":"Lawyer & Legal Services",
            "type":"Services"
        }
    ],
    "sg:phone":"+32 4 351 67 40",
    "sg:postcode":"4870",
    "sg:province":"Li\u00e8ge",
    "wof:name":"Knaepen A",
    "wof:placetype":"venue"
},
  "geometry": {"coordinates":[5.6765871048,50.5544052124],"type":"Point"}
}