{
  "type": "Feature",
  "properties": {
    "addr:full":"Rue Michel Botte 104 Braine-l\u00b4alleud Brabant Wallon 1421",
    "addr:housenumber":"104;1421",
    "addr:street":"Rue Michel Botte;Brabant Wallon",
    "iso:country":"BE",
    "sg:address":"Rue Michel Botte 104",
    "sg:city":"Braine-l\u00b4alleud",
    "sg:orig_category":"Entretien and r\u00e9parations de voitures",
    "sg:phone":"+32 2 387 54 51",
    "sg:postcode":"1421",
    "sg:province":"Brabant Wallon",
    "wof:name":"Devillers Autodistribution",
    "wof:placetype":"venue"
},
  "geometry": {"coordinates":[4.3498539925,50.6672782898],"type":"Point"}
}