{
  "type": "Feature",
  "properties": {
    "iso:country":"BE",
    "sg:address":"Elsegemplein 1",
    "sg:city":"Wortegem-petegem (elsegem)",
    "sg:classifiers":[
        {
            "category":"Food & Beverages",
            "subcategory":"Meat & Fish",
            "type":"Retail Goods"
        }
    ],
    "sg:phone":"+32 56 68 81 20",
    "sg:postcode":"9790",
    "sg:province":"Oost-Vlaanderen",
    "sg:tags":[
        "-",
        "livestock"
    ],
    "wof:name":"Maes Nv",
    "wof:placetype":"venue"
},
  "geometry": {"coordinates":[3.5397379398,50.8231086731],"type":"Point"}
}