{
  "type": "Feature",
  "properties": {
    "iso:country":"BE",
    "sg:address":"Puursesteenweg 397",
    "sg:city":"Bornem",
    "sg:classifiers":[
        {
            "category":"Military Area",
            "subcategory":"Naval Base",
            "type":"Public Place"
        }
    ],
    "sg:phone":"+32 3 889 38 15",
    "sg:postcode":"2880",
    "sg:province":"Antwerpen",
    "sg:tags":[
        "athletic",
        "flooring",
        "facility"
    ],
    "wof:name":"Topfloor Nv",
    "wof:placetype":"venue"
},
  "geometry": {"coordinates":[4.2631859779,51.0858688354],"type":"Point"}
}