{
  "type": "Feature",
  "properties": {
    "addr:full":"Marie-jos\u00c9laan 101 Sint-lambrechts-woluwe/woluwe-saint-lambert Bruxelles-Capitale 1200",
    "addr:housenumber":"101",
    "addr:postcode":"1200",
    "addr:street":"Marie-Jose\u0301Laan",
    "iso:country":"BE",
    "sg:address":"Marie-jos\u00c9laan 101",
    "sg:city":"Sint-lambrechts-woluwe/woluwe-saint-lambert",
    "sg:orig_category":"Artsen and specialisten",
    "sg:phone":"+32 2 735 16 92",
    "sg:postcode":"1200",
    "sg:province":"Bruxelles-Capitale",
    "wof:name":"Jules Defort",
    "wof:placetype":"venue"
},
  "geometry": {"coordinates":[4.4101958275,50.844909668],"type":"Point"}
}