{
  "type": "Feature",
  "properties": {
    "addr:full":"Bld De La Fleur-de-lys 7 Nivelles Brabant Wallon 1400",
    "addr:housenumber":"7",
    "addr:postcode":"1400",
    "addr:street":"Bld De La Fleur-De-Lys",
    "iso:country":"BE",
    "sg:address":"Bld De La Fleur-de-lys 7",
    "sg:city":"Nivelles",
    "sg:orig_category":"Artsen and specialisten",
    "sg:phone":"+32 67 21 82 11",
    "sg:postcode":"1400",
    "sg:province":"Brabant Wallon",
    "wof:name":"Hubert Bertrand",
    "wof:placetype":"venue"
},
  "geometry": {"coordinates":[4.3266358376,50.6000061035],"type":"Point"}
}