{
  "type": "Feature",
  "properties": {
    "addr:full":"Lijsterdreef 7 Keerbergen Vlaams-Brabant 3140",
    "addr:housenumber":"7",
    "addr:postcode":"3140",
    "addr:street":"Lijsterdreef",
    "iso:country":"BE",
    "sg:address":"Lijsterdreef 7",
    "sg:city":"Keerbergen",
    "sg:orig_category":"Agences d'exp\u00e9dition. Air conditionn\u00e9 and ventilation",
    "sg:phone":"+32 15 23 63 17",
    "sg:postcode":"3140",
    "sg:province":"Vlaams-Brabant",
    "wof:name":"Wilfried Verbruggen",
    "wof:placetype":"venue"
},
  "geometry": {"coordinates":[4.6555190086,51.0022621155],"type":"Point"}
}