{
  "type": "Feature",
  "properties": {
    "iso:country":"BE",
    "sg:address":"Rue De Herve 817",
    "sg:city":"Beyne-heusay",
    "sg:classifiers":[
        {
            "category":"Shopping",
            "subcategory":"Discount & Variety Stores",
            "type":"Retail Goods"
        }
    ],
    "sg:phone":"+32 4 367 71 39",
    "sg:postcode":"4610",
    "sg:province":"Li\u00e8ge",
    "sg:tags":[
        "shop",
        "clearers",
        "curiosity",
        "furniture"
    ],
    "wof:name":"Brocanterie (la)",
    "wof:placetype":"venue"
},
  "geometry": {"coordinates":[5.6397857666,50.6259880066],"type":"Point"}
}