{
  "type": "Feature",
  "properties": {
    "iso:country":"BE",
    "sg:address":"Rue La Rue 79",
    "sg:city":"Donceel",
    "sg:orig_category":"Rundveehouders Varkenskwekers",
    "sg:phone":"+32 4 259 55 32",
    "sg:postcode":"4357",
    "sg:province":"Li\u00e8ge",
    "wof:name":"Pierre Lemmens",
    "wof:placetype":"venue"
},
  "geometry": {"coordinates":[5.3169932365,50.6453857422],"type":"Point"}
}