{
  "type": "Feature",
  "properties": {
    "iso:country":"BE",
    "sg:address":"Sint-denijsplaats 2a",
    "sg:city":"Zwevegem (sint-denijs)",
    "sg:classifiers":[
        {
            "category":"Professional",
            "subcategory":"Testing Lab",
            "type":"Services"
        }
    ],
    "sg:phone":"+32 56 45 52 45",
    "sg:postcode":"8554",
    "sg:province":"West-Vlaanderen",
    "sg:tags":[
        "chemist"
    ],
    "wof:name":"Dionysius",
    "wof:placetype":"venue"
},
  "geometry": {"coordinates":[3.3684940338,50.7514648438],"type":"Point"}
}