{
  "type": "Feature",
  "properties": {
    "iso:country":"BE",
    "sg:address":"Westelsebaan 186",
    "sg:city":"Scherpenheuvel-zichem",
    "sg:orig_category":"Pain, p\u00e2tisseries and confiseries",
    "sg:phone":"+32 13 77 18 55",
    "sg:postcode":"3271",
    "sg:province":"Vlaams-Brabant",
    "wof:name":"Dirk Van Gompel",
    "wof:placetype":"venue"
},
  "geometry": {"coordinates":[4.9794201851,51.0292778015],"type":"Point"}
}