{
  "type": "Feature",
  "properties": {
    "iso:country":"BE",
    "sg:address":"Antwerpse Steenweg 27",
    "sg:city":"Hemiksem",
    "sg:classifiers":[
        {
            "category":"Bakery",
            "type":"Food & Drink"
        }
    ],
    "sg:phone":"+32 3 887 43 60",
    "sg:postcode":"2620",
    "sg:province":"Antwerpen",
    "sg:tags":[
        "confectioner",
        "baker"
    ],
    "wof:name":"Van Roosbroeck R",
    "wof:placetype":"venue"
},
  "geometry": {"coordinates":[4.3394460678,51.1488227844],"type":"Point"}
}