{
  "type": "Feature",
  "properties": {
    "addr:full":"Aakaai 6bb Anderlecht Bruxelles-Capitale 1070",
    "addr:housenumber":"6bb",
    "addr:postcode":"1070",
    "addr:street":"Aakaai",
    "iso:country":"BE",
    "sg:address":"Aakaai 6bb",
    "sg:city":"Anderlecht",
    "sg:orig_category":"Reclamebureaus",
    "sg:phone":"+32 2 524 59 99",
    "sg:postcode":"1070",
    "sg:province":"Bruxelles-Capitale",
    "wof:name":"Osmose Creative Workshop",
    "wof:placetype":"venue"
},
  "geometry": {"coordinates":[4.304599762,50.8217048645],"type":"Point"}
}