{
  "type": "Feature",
  "properties": {
    "iso:country":"BE",
    "sg:address":"Rasselstraat 2",
    "sg:city":"Asse",
    "sg:orig_category":"Boekhouders",
    "sg:phone":"+32 2 460 49 75",
    "sg:postcode":"1731",
    "sg:province":"Vlaams-Brabant",
    "wof:name":"Eddy Van De Meirssche",
    "wof:placetype":"venue"
},
  "geometry": {"coordinates":[4.2883858681,50.9075737],"type":"Point"}
}