{
  "type": "Feature",
  "properties": {
    "addr:full":"Rue D'ans 45 Li\u00e8ge 1 (rocourt) Li\u00e8ge 4000",
    "addr:housenumber":"45;1",
    "addr:postcode":"4000",
    "addr:street":"Rue D'Ans",
    "iso:country":"BE",
    "sg:address":"Rue D'ans 45",
    "sg:city":"Li\u00e8ge 1 (rocourt)",
    "sg:classifiers":[
        {
            "category":"Real Estate",
            "subcategory":"Architect",
            "type":"Services"
        }
    ],
    "sg:phone":"+32 4 263 03 73",
    "sg:postcode":"4000",
    "sg:province":"Li\u00e8ge",
    "wof:name":"Robeerst J-m",
    "wof:placetype":"venue"
},
  "geometry": {"coordinates":[5.5430088043,50.6718902588],"type":"Point"}
}