{
  "type": "Feature",
  "properties": {
    "addr:full":"Place Flagey 28 Elsene/ixelles Bruxelles-Capitale 1050",
    "addr:housenumber":"28",
    "addr:postcode":"1050",
    "addr:street":"Place Flagey",
    "iso:country":"BE",
    "sg:address":"Place Flagey 28",
    "sg:city":"Elsene/ixelles",
    "sg:orig_category":"Architectes",
    "sg:phone":"+32 2 646 46 20",
    "sg:postcode":"1050",
    "sg:province":"Bruxelles-Capitale",
    "wof:name":"Thiry P.",
    "wof:placetype":"venue"
},
  "geometry": {"coordinates":[4.3731470108,50.8279914856],"type":"Point"}
}