{
  "type": "Feature",
  "properties": {
    "iso:country":"BE",
    "sg:address":"Schoendalestraat 182",
    "sg:city":"Waregem",
    "sg:orig_category":"Immobili\u00ebnkantoren",
    "sg:phone":"+32 56 60 82 70",
    "sg:postcode":"8793",
    "sg:province":"West-Vlaanderen",
    "wof:name":"Immobilien Verimba",
    "wof:placetype":"venue"
},
  "geometry": {"coordinates":[3.3865120411,50.8974571228],"type":"Point"}
}