{
  "type": "Feature",
  "properties": {
    "iso:country":"BE",
    "sg:address":"Avenue Rogier 16",
    "sg:city":"Li\u00e8ge 1",
    "sg:classifiers":[
        {
            "category":"Professional",
            "subcategory":"Testing Lab",
            "type":"Services"
        }
    ],
    "sg:phone":"+32 4 222 02 22",
    "sg:postcode":"4000",
    "sg:province":"Li\u00e8ge",
    "sg:tags":[
        "laboratory",
        "medical"
    ],
    "wof:name":"Avroy-laboratoire Vieux Mayeur",
    "wof:placetype":"venue"
},
  "geometry": {"coordinates":[5.5699291229,50.6335792542],"type":"Point"}
}