{
  "type": "Feature",
  "properties": {
    "iso:country":"BE",
    "sg:address":"Rue De Rotterdam 20",
    "sg:city":"Liege",
    "sg:orig_category":"Rev\u00eatements pour sols and murs. Peinture",
    "sg:phone":"+32 4 342 35 46",
    "sg:postcode":"4000",
    "sg:province":"Li\u00e8ge",
    "wof:name":"Prestige & D\u00c9cor",
    "wof:placetype":"venue"
},
  "geometry": {"coordinates":[5.5669760704,50.6307754517],"type":"Point"}
}