{
  "type": "Feature",
  "properties": {
    "iso:country":"BE",
    "sg:address":"Rubensstraat 47",
    "sg:city":"Kontich",
    "sg:orig_category":"Installatie van houten of kunststof schrijnwerk",
    "sg:phone":"+32 3 458 04 61",
    "sg:postcode":"2550",
    "sg:province":"Antwerpen",
    "wof:name":"Ronny Johnson",
    "wof:placetype":"venue"
},
  "geometry": {"coordinates":[4.4416399002,51.1332931519],"type":"Point"}
}