{
  "type": "Feature",
  "properties": {
    "iso:country":"BE",
    "sg:address":"Rue De Bouillon 50",
    "sg:city":"Beauraing",
    "sg:classifiers":[
        {
            "category":"Shopping",
            "subcategory":"Clothing, Apparel, & Fashions",
            "type":"Retail Goods"
        }
    ],
    "sg:phone":"+32 82 71 40 36",
    "sg:postcode":"5570",
    "sg:province":"Namur",
    "sg:tags":[
        "v\u00eatements",
        "pour",
        "dame"
    ],
    "wof:name":"Maison L'aziza",
    "wof:placetype":"venue"
},
  "geometry": {"coordinates":[4.9570112228,50.1089363098],"type":"Point"}
}