{
  "type": "Feature",
  "properties": {
    "addr:full":"Avenue De La Seigneurie 28 Chaumont-gistoux (dion-valmont) Brabant Wallon 1325",
    "addr:housenumber":"28;1325",
    "addr:street":"Avenue De La Seigneurie;Dion-Valmont;Wallon",
    "iso:country":"BE",
    "sg:address":"Avenue De La Seigneurie 28",
    "sg:city":"Chaumont-gistoux (dion-valmont)",
    "sg:classifiers":[
        {
            "category":"Professional",
            "subcategory":"Computer Services",
            "type":"Services"
        }
    ],
    "sg:phone":"+32 10 22 34 55",
    "sg:postcode":"1325",
    "sg:province":"Brabant Wallon",
    "sg:tags":[
        "-",
        "processing",
        "data"
    ],
    "wof:name":"Bytecom Sprl",
    "wof:placetype":"venue"
},
  "geometry": {"coordinates":[4.6401090622,50.690776825],"type":"Point"}
}