{
  "type": "Feature",
  "properties": {
    "iso:country":"BE",
    "sg:address":"Gouverneur Roppesingel 53",
    "sg:city":"Hasselt",
    "sg:orig_category":"Location de logements sociaux",
    "sg:phone":"+32 11 28 83 10",
    "sg:postcode":"3500",
    "sg:province":"Limburg",
    "wof:name":"Hasseltse Huisvestingsmij",
    "wof:placetype":"venue"
},
  "geometry": {"coordinates":[5.3555488586,50.9218444824],"type":"Point"}
}