{
  "type": "Feature",
  "properties": {
    "addr:full":"Riemsterweg 157 Bilzen (martenslinde) Limburg 3742",
    "addr:housenumber":"157",
    "addr:postcode":"3742",
    "addr:street":"Bilzen Martenslinde Limburg",
    "iso:country":"BE",
    "sg:address":"Riemsterweg 157",
    "sg:city":"Bilzen (martenslinde)",
    "sg:classifiers":[
        {
            "category":"Home & Garden",
            "subcategory":"Carpets & Floor Coverings",
            "type":"Retail Goods"
        }
    ],
    "sg:phone":"+32 89 41 13 68",
    "sg:postcode":"3742",
    "sg:province":"Limburg",
    "sg:tags":[
        "prefab",
        "element"
    ],
    "wof:name":"Oosterbosch & Zonen Bvba",
    "wof:placetype":"venue"
},
  "geometry": {"coordinates":[5.5370612144,50.8523406982],"type":"Point"}
}