{
  "type": "Feature",
  "properties": {
    "iso:country":"BE",
    "sg:address":"John Lijsenstraat 59",
    "sg:city":"Hoogstraten",
    "sg:orig_category":"P\u00e9pini\u00e9ristes",
    "sg:phone":"+32 3 315 95 33",
    "sg:postcode":"2321",
    "sg:province":"Antwerpen",
    "wof:name":"P. Lodders",
    "wof:placetype":"venue"
},
  "geometry": {"coordinates":[4.7014040947,51.4586143494],"type":"Point"}
}