{
  "type": "Feature",
  "properties": {
    "addr:full":"Oostendestraat 68 Diksmuide West-Vlaanderen 8600",
    "addr:housenumber":"68",
    "addr:postcode":"8600",
    "addr:street":"Oostendestraat",
    "iso:country":"BE",
    "sg:address":"Oostendestraat 68",
    "sg:city":"Diksmuide",
    "sg:classifiers":[
        {
            "category":"Home & Garden",
            "subcategory":"Kitchen Supply",
            "type":"Retail Goods"
        }
    ],
    "sg:phone":"+32 51 50 05 67",
    "sg:postcode":"8600",
    "sg:province":"West-Vlaanderen",
    "sg:tags":[
        "installation"
    ],
    "wof:name":"Gamme Bvba",
    "wof:placetype":"venue"
},
  "geometry": {"coordinates":[2.865983963,51.0381965637],"type":"Point"}
}