{
  "type": "Feature",
  "properties": {
    "addr:full":"R Lambert Crickx 9 Bruxelles Bruxelles-Capitale 1070",
    "addr:housenumber":"9",
    "addr:postcode":"1070",
    "addr:street":"Crickx",
    "iso:country":"BE",
    "sg:address":"R Lambert Crickx 9",
    "sg:city":"Bruxelles",
    "sg:classifiers":[
        {
            "category":"Shopping",
            "subcategory":"Clothing, Apparel, & Fashions",
            "type":"Retail Goods"
        }
    ],
    "sg:phone":"+32 2 520 20 34",
    "sg:postcode":"1070",
    "sg:province":"Bruxelles-Capitale",
    "sg:tags":[
        "textile",
        "clothing",
        "clothes"
    ],
    "wof:name":"Union Jack Sprl",
    "wof:placetype":"venue"
},
  "geometry": {"coordinates":[4.3380041122,50.8409500122],"type":"Point"}
}