{
  "type": "Feature",
  "properties": {
    "addr:full":"Bosdreef 35 Oud-turnhout Antwerpen 2360",
    "addr:housenumber":"35",
    "addr:postcode":"2360",
    "addr:street":"Bosdreef",
    "iso:country":"BE",
    "sg:address":"Bosdreef 35",
    "sg:city":"Oud-turnhout",
    "sg:orig_category":"D\u00e9corateurs d'int\u00e9rieur",
    "sg:phone":"+32 14 45 24 68",
    "sg:postcode":"2360",
    "sg:province":"Antwerpen",
    "wof:name":"Paul Rijs",
    "wof:placetype":"venue"
},
  "geometry": {"coordinates":[5.0077848434,51.3028793335],"type":"Point"}
}