{
  "type": "Feature",
  "properties": {
    "iso:country":"BE",
    "sg:address":"Ferdinand Maesstraat 52",
    "sg:city":"Waarloos",
    "sg:classifiers":[
        {
            "category":"Professional",
            "type":"Services"
        }
    ],
    "sg:phone":"+32 15 31 19 49",
    "sg:postcode":"2550",
    "sg:province":"Antwerpen",
    "sg:tags":[
        "transport"
    ],
    "wof:name":"Frans De Vocht B.v.b.a.",
    "wof:placetype":"venue"
},
  "geometry": {"coordinates":[4.4537258148,51.1058349609],"type":"Point"}
}