{
  "type": "Feature",
  "properties": {
    "iso:country":"BE",
    "sg:address":"Leopold Iii-laan 17",
    "sg:city":"Oostende",
    "sg:classifiers":[
        {
            "category":"Real Estate",
            "subcategory":"Real Estate Services",
            "type":"Services"
        }
    ],
    "sg:phone":"+32 59 43 00 00",
    "sg:postcode":"8400",
    "sg:province":"West-Vlaanderen",
    "wof:name":"Immo 43",
    "wof:placetype":"venue"
},
  "geometry": {"coordinates":[2.8941149712,51.2228012085],"type":"Point"}
}