{
  "type": "Feature",
  "properties": {
    "addr:full":"Sint-elooistraat 20 Deerlijk West-Vlaanderen 8540",
    "addr:housenumber":"20",
    "addr:postcode":"8540",
    "addr:street":"Sint-Elooistraat",
    "iso:country":"BE",
    "sg:address":"Sint-elooistraat 20",
    "sg:city":"Deerlijk",
    "sg:orig_category":"Eleveurs de bovins. Eleveurs and marchands de porcs",
    "sg:phone":"+32 56 77 70 71",
    "sg:postcode":"8540",
    "sg:province":"West-Vlaanderen",
    "wof:name":"Renaat Vanwynsberghe",
    "wof:placetype":"venue"
},
  "geometry": {"coordinates":[3.355891943,50.8363838196],"type":"Point"}
}