{
  "type": "Feature",
  "properties": {
    "addr:full":"Avenue D'auderghem 70 Bruxelles (etterbeek) Bruxelles-Capitale 1040",
    "addr:housenumber":"70",
    "addr:postcode":"1040",
    "addr:street":"Avenue D'Auderghem",
    "iso:country":"BE",
    "sg:address":"Avenue D'auderghem 70",
    "sg:city":"Bruxelles (etterbeek)",
    "sg:classifiers":[
        {
            "category":"Retail",
            "subcategory":"Auto Repair",
            "type":"Services"
        }
    ],
    "sg:phone":"+32 2 735 01 90",
    "sg:postcode":"1040",
    "sg:province":"Bruxelles-Capitale",
    "sg:tags":[
        "garage"
    ],
    "wof:name":"Dema Sa",
    "wof:placetype":"venue"
},
  "geometry": {"coordinates":[4.3860177994,50.8387489319],"type":"Point"}
}