{
  "type": "Feature",
  "properties": {
    "iso:country":"BE",
    "sg:address":"Fabiolalaan 5",
    "sg:city":"Aarschot",
    "sg:classifiers":[
        {
            "category":"Shopping",
            "subcategory":"Clothing, Apparel, & Fashions",
            "type":"Retail Goods"
        }
    ],
    "sg:phone":"+32 16 56 73 65",
    "sg:postcode":"3200",
    "sg:province":"Vlaams-Brabant",
    "sg:tags":[
        "v\u00eatements",
        "pour",
        "dame"
    ],
    "wof:name":"Gabriele Gevers",
    "wof:placetype":"venue"
},
  "geometry": {"coordinates":[4.8403019905,50.9943771362],"type":"Point"}
}