{
  "type": "Feature",
  "properties": {
    "addr:full":"Rue Oppermann 41 Charleroi Hainaut 6001",
    "addr:housenumber":"41",
    "addr:postcode":"6001",
    "addr:street":"Rue Oppermann;Hainaut",
    "iso:country":"BE",
    "sg:address":"Rue Oppermann 41",
    "sg:city":"Charleroi",
    "sg:orig_category":"Apotheken",
    "sg:phone":"+32 71 36 55 73",
    "sg:postcode":"6001",
    "sg:province":"Hainaut",
    "wof:name":"Andre Legros",
    "wof:placetype":"venue"
},
  "geometry": {"coordinates":[4.4368958473,50.3988113403],"type":"Point"}
}