{
  "type": "Feature",
  "properties": {
    "addr:full":"Edegemsesteenweg 63 Kontich Antwerpen 2550",
    "addr:housenumber":"63",
    "addr:postcode":"2550",
    "addr:street":"Edegemsesteenweg",
    "iso:country":"BE",
    "sg:address":"Edegemsesteenweg 63",
    "sg:city":"Kontich",
    "sg:classifiers":[
        {
            "category":"Building & Trades",
            "subcategory":"Construction",
            "type":"Services"
        }
    ],
    "sg:phone":"+32 3 457 66 81",
    "sg:postcode":"2550",
    "sg:province":"Antwerpen",
    "sg:tags":[
        "carpenter"
    ],
    "wof:name":"Van Gaver",
    "wof:placetype":"venue"
},
  "geometry": {"coordinates":[4.4454112053,51.1384239197],"type":"Point"}
}