{
  "type": "Feature",
  "properties": {
    "iso:country":"BE",
    "sg:address":"Casselsestraat 5ba",
    "sg:city":"Ieper",
    "sg:orig_category":"Eleveurs de bovins",
    "sg:phone":"+32 57 33 66 51",
    "sg:postcode":"8908",
    "sg:province":"West-Vlaanderen",
    "wof:name":"Albert Claeys",
    "wof:placetype":"venue"
},
  "geometry": {"coordinates":[2.8062810898,50.8505134583],"type":"Point"}
}