{
  "type": "Feature",
  "properties": {
    "addr:full":"Grand Rue 125 Mouscron Hainaut 7700",
    "addr:housenumber":"125",
    "addr:postcode":"7700",
    "addr:street":"Grand Rue",
    "iso:country":"BE",
    "sg:address":"Grand Rue 125",
    "sg:city":"Mouscron",
    "sg:classifiers":[
        {
            "category":"Bars & Pubs",
            "type":"Food & Drink"
        }
    ],
    "sg:phone":"+32 56 33 43 90",
    "sg:postcode":"7700",
    "sg:province":"Hainaut",
    "wof:name":"Be-bop",
    "wof:placetype":"venue"
},
  "geometry": {"coordinates":[3.1933128834,50.725730896],"type":"Point"}
}