{
  "type": "Feature",
  "properties": {
    "addr:full":"Rue De La Croix Hustin 30 Genappe Brabant Wallon 1470",
    "addr:housenumber":"30",
    "addr:postcode":"1470",
    "addr:street":"Rue De La Croix Hustin;Wallon",
    "iso:country":"BE",
    "sg:address":"Rue De La Croix Hustin 30",
    "sg:city":"Genappe",
    "sg:orig_category":"Artiesten and kunstenaars",
    "sg:phone":"+32 67 77 21 89",
    "sg:postcode":"1470",
    "sg:province":"Brabant Wallon",
    "wof:name":"Marcel Pierre",
    "wof:placetype":"venue"
},
  "geometry": {"coordinates":[4.4558172226,50.6027030945],"type":"Point"}
}