{
  "type": "Feature",
  "properties": {
    "addr:full":"7700 Mouscron Hainaut 7700",
    "addr:postcode":"7700;7700",
    "addr:street":"Hainaut",
    "iso:country":"BE",
    "sg:address":"7700",
    "sg:city":"Mouscron",
    "sg:orig_category":"Plomberie, chauffage and installations sanitaires",
    "sg:phone":"+32 56 51 85 10",
    "sg:postcode":"7700",
    "sg:province":"Hainaut",
    "wof:name":"Vaillant",
    "wof:placetype":"venue"
},
  "geometry": {"coordinates":[3.2271699905,50.7411499023],"type":"Point"}
}