{
  "type": "Feature",
  "properties": {
    "iso:country":"BE",
    "sg:address":"Rue De Jemappes 32",
    "sg:city":"Frameries",
    "sg:classifiers":[
        {
            "category":"Home & Garden",
            "subcategory":"Building Materials",
            "type":"Retail Goods"
        }
    ],
    "sg:phone":"+32 65 67 58 37",
    "sg:postcode":"7080",
    "sg:province":"Hainaut",
    "sg:tags":[
        "window"
    ],
    "wof:name":"Festa Augusto",
    "wof:placetype":"venue"
},
  "geometry": {"coordinates":[3.895457983,50.415019989],"type":"Point"}
}