{
  "type": "Feature",
  "properties": {
    "addr:full":"Rue De Xhoris 4 A Aywaille Li\u00e8ge 4920",
    "addr:housenumber":"4 a",
    "addr:postcode":"4920",
    "addr:street":"Rue De Xhoris",
    "iso:country":"BE",
    "sg:address":"Rue De Xhoris 4 A",
    "sg:city":"Aywaille",
    "sg:orig_category":"C\u00e9r\u00e9ales and aliments pour animaux Animaux domestiques and accessoires",
    "sg:phone":"+32 4 384 60 78",
    "sg:postcode":"4920",
    "sg:province":"Li\u00e8ge",
    "wof:name":"La Ferme De Harz\u00c9",
    "wof:placetype":"venue"
},
  "geometry": {"coordinates":[5.6326341629,50.4457321167],"type":"Point"}
}