{
  "type": "Feature",
  "properties": {
    "iso:country":"BE",
    "sg:address":"Avenue Jean Lambert 142",
    "sg:city":"Verviers",
    "sg:orig_category":"M\u00e9decins and sp\u00e9cialistes",
    "sg:phone":"+32 87 22 04 60",
    "sg:postcode":"4801",
    "sg:province":"Li\u00e8ge",
    "wof:name":"Maurice Debarre",
    "wof:placetype":"venue"
},
  "geometry": {"coordinates":[5.8858528137,50.5851325989],"type":"Point"}
}