{
  "type": "Feature",
  "properties": {
    "addr:full":"Place Colignon 48 Bruxelles-schaerbeek Bruxelles-Capitale 1030",
    "addr:housenumber":"48",
    "addr:postcode":"1030",
    "addr:street":"Place Colignon",
    "iso:country":"BE",
    "sg:address":"Place Colignon 48",
    "sg:city":"Bruxelles-schaerbeek",
    "sg:orig_category":"Royal Canin. Animaux domestiques and accessoires. Drogueries",
    "sg:phone":"+32 2 215 83 77",
    "sg:postcode":"1030",
    "sg:province":"Bruxelles-Capitale",
    "wof:name":"Moreau",
    "wof:placetype":"venue"
},
  "geometry": {"coordinates":[4.3743748665,50.8677253723],"type":"Point"}
}