{
  "type": "Feature",
  "properties": {
    "addr:full":"Rue Des Raines 83 Verviers Li\u00e8ge 4800",
    "addr:housenumber":"83",
    "addr:postcode":"4800",
    "addr:street":"Rue Des Raines",
    "iso:country":"BE",
    "sg:address":"Rue Des Raines 83",
    "sg:city":"Verviers",
    "sg:classifiers":[
        {
            "category":"Personal",
            "subcategory":"Beauty Salon",
            "type":"Services"
        }
    ],
    "sg:phone":"+32 87 33 48 12",
    "sg:postcode":"4800",
    "sg:province":"Li\u00e8ge",
    "wof:name":"Venus",
    "wof:placetype":"venue"
},
  "geometry": {"coordinates":[5.8664479256,50.5943336487],"type":"Point"}
}