{
  "type": "Feature",
  "properties": {
    "iso:country":"BE",
    "sg:address":"Van Overbekelaan 10",
    "sg:city":"Ganshoren",
    "sg:orig_category":"Algemeen secundair onderwijs Technisch and beroeps secundair onderwijs",
    "sg:phone":"+32 2 428 11 27",
    "sg:postcode":"1083",
    "sg:province":"Bruxelles-Capitale",
    "wof:name":"C.s. N.d. De La Sagesse",
    "wof:placetype":"venue"
},
  "geometry": {"coordinates":[4.3161158562,50.8692893982],"type":"Point"}
}