{
  "type": "Feature",
  "properties": {
    "addr:full":"Chemin Du Bassin 4 Dinant Namur 5501",
    "addr:housenumber":"4",
    "addr:postcode":"5501",
    "addr:street":"Chemin Du Bassin",
    "iso:country":"BE",
    "sg:address":"Chemin Du Bassin 4",
    "sg:city":"Dinant",
    "sg:orig_category":"Installation \u00e9lectrique industrielle. Mat\u00e9riel de contr\u00f4le des processus industriels Fab. Installati",
    "sg:phone":"+32 82 22 66 19",
    "sg:postcode":"5501",
    "sg:province":"Namur",
    "wof:name":"Amgil Alarmes",
    "wof:placetype":"venue"
},
  "geometry": {"coordinates":[4.9709310532,50.2836227417],"type":"Point"}
}