{
  "type": "Feature",
  "properties": {
    "addr:full":"Rue Des Combattants 40 Pepinster (wegnez) Li\u00e8ge 4860",
    "addr:housenumber":"40",
    "addr:postcode":"4860",
    "addr:street":"Rue Des Combattants",
    "iso:country":"BE",
    "sg:address":"Rue Des Combattants 40",
    "sg:city":"Pepinster (wegnez)",
    "sg:classifiers":[
        {
            "category":"Building & Trades",
            "subcategory":"Landscaping Services",
            "type":"Services"
        }
    ],
    "sg:phone":"+32 87 46 98 58",
    "sg:postcode":"4860",
    "sg:province":"Li\u00e8ge",
    "sg:tags":[
        "gardening",
        "garden",
        "maintenance"
    ],
    "wof:name":"Bolly J M",
    "wof:placetype":"venue"
},
  "geometry": {"coordinates":[5.8198637962,50.5799293518],"type":"Point"}
}