{
  "type": "Feature",
  "properties": {
    "addr:full":"Rue Des Brasseurs 12 Braine-l'alleud Brabant Wallon 1420",
    "addr:housenumber":"12",
    "addr:postcode":"1420",
    "addr:street":"Rue Des Brasseurs",
    "iso:country":"BE",
    "sg:address":"Rue Des Brasseurs 12",
    "sg:city":"Braine-l'alleud",
    "sg:orig_category":"Pain, p\u00e2tisseries and confiseries",
    "sg:phone":"+32 2 385 16 85",
    "sg:postcode":"1420",
    "sg:province":"Brabant Wallon",
    "wof:name":"P\u00c2tiss. Le P\u00c9ch\u00c9 Mignon",
    "wof:placetype":"venue"
},
  "geometry": {"coordinates":[-75.60595703120001,37.7877616882],"type":"Point"}
}