{
  "type": "Feature",
  "properties": {
    "iso:country":"BE",
    "sg:address":"Sint-kristoffelstraat 14",
    "sg:city":"Oosterzele",
    "sg:orig_category":"Diverse bouwinstallaties",
    "sg:phone":"+32 9 362 99 82",
    "sg:postcode":"9860",
    "sg:province":"Oost-Vlaanderen",
    "wof:name":"Deco Beton",
    "wof:placetype":"venue"
},
  "geometry": {"coordinates":[3.785173893,50.9338874817],"type":"Point"}
}