{
  "type": "Feature",
  "properties": {
    "addr:full":"Rue Saint-l\u00c9onard 246 Li\u00c8ge Li\u00e8ge 4000",
    "addr:housenumber":"246",
    "addr:postcode":"4000",
    "addr:street":"Rue Saint-Le\u0301Onard",
    "iso:country":"BE",
    "sg:address":"Rue Saint-l\u00c9onard 246",
    "sg:city":"Li\u00c8ge",
    "sg:orig_category":"RESTAURANTS: CAF\u00c9S",
    "sg:phone":"+32 4 227 51 83",
    "sg:postcode":"4000",
    "sg:province":"Li\u00e8ge",
    "wof:name":"La Taverne St.l\u00c9onard",
    "wof:placetype":"venue"
},
  "geometry": {"coordinates":[5.5921339989,50.6494750977],"type":"Point"}
}