{
  "type": "Feature",
  "properties": {
    "iso:country":"BE",
    "sg:address":"Ruilare 24",
    "sg:city":"Lochristi",
    "sg:classifiers":[
        {
            "category":"Building & Trades",
            "subcategory":"Landscaping Services",
            "type":"Services"
        }
    ],
    "sg:phone":"+32 9 355 19 67",
    "sg:postcode":"9080",
    "sg:province":"Oost-Vlaanderen",
    "sg:tags":[
        "-",
        "lopping",
        "work",
        "tree",
        "felling"
    ],
    "wof:name":"Van Peteghem H",
    "wof:placetype":"venue"
},
  "geometry": {"coordinates":[3.8927149773,51.1182060242],"type":"Point"}
}