{
  "type": "Feature",
  "properties": {
    "iso:country":"BE",
    "sg:address":"Rue D'h\u00c9rinnes 32",
    "sg:city":"Edingen/enghien",
    "sg:orig_category":"Jeux de hasard",
    "sg:phone":"+32 2 395 68 31",
    "sg:postcode":"7850",
    "sg:province":"Hainaut",
    "wof:name":"Tierc\u00c9 Franco-belge",
    "wof:placetype":"venue"
},
  "geometry": {"coordinates":[4.0386800766,50.6943244934],"type":"Point"}
}