{
  "type": "Feature",
  "properties": {
    "addr:full":"Daaleindestraat 102 Kortessem Limburg 3720",
    "addr:housenumber":"102",
    "addr:postcode":"3720",
    "addr:street":"Daaleindestraat;Limburg",
    "iso:country":"BE",
    "sg:address":"Daaleindestraat 102",
    "sg:city":"Kortessem",
    "sg:classifiers":[
        {
            "category":"Home & Garden",
            "subcategory":"Hardware",
            "type":"Retail Goods"
        }
    ],
    "sg:phone":"+32 11 37 77 39",
    "sg:postcode":"3720",
    "sg:province":"Limburg",
    "sg:tags":[
        "gate",
        "opener",
        "door",
        "automatic"
    ],
    "wof:name":"Nelissen E",
    "wof:placetype":"venue"
},
  "geometry": {"coordinates":[5.4024310112,50.8658485413],"type":"Point"}
}