{
  "type": "Feature",
  "properties": {
    "addr:full":"Plezantstraat 159 Sint-niklaas Oost-Vlaanderen 9100",
    "addr:housenumber":"159",
    "addr:postcode":"9100",
    "addr:street":"Plezantstraat",
    "iso:country":"BE",
    "sg:address":"Plezantstraat 159",
    "sg:city":"Sint-niklaas",
    "sg:orig_category":"Overheidsdiensten",
    "sg:phone":"+32 3 778 22 66",
    "sg:postcode":"9100",
    "sg:province":"Oost-Vlaanderen",
    "wof:name":"R.v.a.",
    "wof:placetype":"venue"
},
  "geometry": {"coordinates":[4.1334338188,51.1673164368],"type":"Point"}
}