{
  "type": "Feature",
  "properties": {
    "iso:country":"BE",
    "sg:address":"August De Boeckstraat 54",
    "sg:city":"Evere",
    "sg:orig_category":"Advocaten and juridische adviseurs",
    "sg:phone":"+32 2 240 15 20",
    "sg:postcode":"1140",
    "sg:province":"Bruxelles-Capitale",
    "wof:name":"Sophie Watillon",
    "wof:placetype":"venue"
},
  "geometry": {"coordinates":[4.3984189034,50.8679428101],"type":"Point"}
}