{
  "type": "Feature",
  "properties": {
    "iso:country":"BE",
    "sg:address":"Rue Des Closi\u00e8res 344",
    "sg:city":"Charleroi (marcinelle)",
    "sg:classifiers":[
        {
            "category":"Building & Trades",
            "subcategory":"Landscaping Services",
            "type":"Services"
        }
    ],
    "sg:phone":"+32 71 36 38 18",
    "sg:postcode":"6001",
    "sg:province":"Hainaut",
    "sg:tags":[
        "access",
        "pond",
        "laying-out",
        "-"
    ],
    "wof:name":"Le Ko\u00ef",
    "wof:placetype":"venue"
},
  "geometry": {"coordinates":[4.4215369225,50.3906593323],"type":"Point"}
}