{
  "type": "Feature",
  "properties": {
    "addr:full":"Quai Godefroid Kurth 13b93 Li\u00c8ge Li\u00e8ge 4020",
    "addr:housenumber":"13b93",
    "addr:postcode":"4020",
    "addr:street":"Quai Godefroid Kurth",
    "iso:country":"BE",
    "sg:address":"Quai Godefroid Kurth 13b93",
    "sg:city":"Li\u00c8ge",
    "sg:orig_category":"Plomberie, chauffage and installations sanitaires",
    "sg:phone":"+32 4 342 08 78",
    "sg:postcode":"4020",
    "sg:province":"Li\u00e8ge",
    "wof:name":"Allo Plombier",
    "wof:placetype":"venue"
},
  "geometry": {"coordinates":[5.5877070427,50.6458740234],"type":"Point"}
}