{
  "type": "Feature",
  "properties": {
    "addr:full":"Heistseweg 5a Heist-op-den-berg (booischot) Antwerpen 2221",
    "addr:housenumber":"5a",
    "addr:postcode":"2221",
    "addr:street":"Heistseweg",
    "iso:country":"BE",
    "sg:address":"Heistseweg 5a",
    "sg:city":"Heist-op-den-berg (booischot)",
    "sg:classifiers":[
        {
            "category":"Sports & Exercise",
            "subcategory":"Skate Park",
            "type":"Entertainment"
        }
    ],
    "sg:phone":"+32 15 22 38 07",
    "sg:postcode":"2221",
    "sg:province":"Antwerpen",
    "sg:tags":[
        "mushroom"
    ],
    "wof:name":"Vleugels K",
    "wof:placetype":"venue"
},
  "geometry": {"coordinates":[4.7739758492,51.0512428284],"type":"Point"}
}