{
  "type": "Feature",
  "properties": {
    "iso:country":"BE",
    "sg:address":"Alfons Jeurissenstraat 104",
    "sg:city":"Diepenbeek",
    "sg:classifiers":[
        {
            "category":"Home & Garden",
            "subcategory":"Garden Supply",
            "type":"Retail Goods"
        }
    ],
    "sg:phone":"+32 475 68 29 82",
    "sg:postcode":"3590",
    "sg:province":"Limburg",
    "wof:name":"Vangelooven Sierplanten",
    "wof:placetype":"venue"
},
  "geometry": {"coordinates":[5.4284281731,50.9299736023],"type":"Point"}
}