{
  "type": "Feature",
  "properties": {
    "iso:country":"BE",
    "sg:address":"Sint-hubertusstraat 4",
    "sg:city":"Lummen",
    "sg:classifiers":[
        {
            "category":"Personal",
            "subcategory":"Barber",
            "type":"Services"
        }
    ],
    "sg:phone":"+32 13 46 11 22",
    "sg:postcode":"3560",
    "sg:province":"Limburg",
    "sg:tags":[
        "gentleman",
        "salon",
        "-",
        "hairdressing"
    ],
    "wof:name":"Marleen Kapsalon",
    "wof:placetype":"venue"
},
  "geometry": {"coordinates":[5.1530680656,50.9807891846],"type":"Point"}
}