{
  "type": "Feature",
  "properties": {
    "iso:country":"BE",
    "sg:address":"Oudenaardsesteenweg 97",
    "sg:city":"Erpe-mere (bambrugge)",
    "sg:classifiers":[
        {
            "category":"Bars & Pubs",
            "type":"Food & Drink"
        }
    ],
    "sg:phone":"+32 53 62 25 61",
    "sg:postcode":"9420",
    "sg:province":"Oost-Vlaanderen",
    "wof:name":"Vriendenkring",
    "wof:placetype":"venue"
},
  "geometry": {"coordinates":[3.9451398849,50.921459198],"type":"Point"}
}