{
  "type": "Feature",
  "properties": {
    "iso:country":"BE",
    "sg:address":"Diestsevest 97",
    "sg:city":"Leuven",
    "sg:orig_category":"M\u00e9decins and sp\u00e9cialistes",
    "sg:phone":"+32 16 22 52 20",
    "sg:postcode":"3000",
    "sg:province":"Vlaams-Brabant",
    "wof:name":"Vincent Smekens",
    "wof:placetype":"venue"
},
  "geometry": {"coordinates":[4.7106761932,50.8849639893],"type":"Point"}
}