{
  "type": "Feature",
  "properties": {
    "iso:country":"BE",
    "sg:address":"Avenue Du Cor De Chasse 2",
    "sg:city":"Waterloo",
    "sg:orig_category":"Beheer onroerend goed Immobili\u00ebnkantoren",
    "sg:phone":"+32 2 351 25 60",
    "sg:postcode":"1410",
    "sg:province":"Brabant Wallon",
    "wof:name":"D.g.i. Consult",
    "wof:placetype":"venue"
},
  "geometry": {"coordinates":[4.397108078,50.7315063477],"type":"Point"}
}