{
  "type": "Feature",
  "properties": {
    "addr:full":"Koldamstraat 22 Hoeilaart Vlaams-Brabant 1560",
    "addr:housenumber":"22",
    "addr:postcode":"1560",
    "addr:street":"Koldamstraat",
    "iso:country":"BE",
    "sg:address":"Koldamstraat 22",
    "sg:city":"Hoeilaart",
    "sg:orig_category":"Installatie van metalen schrijnwerk Verlichting and huishoudartikelen",
    "sg:phone":"+32 2 657 07 00",
    "sg:postcode":"1560",
    "sg:province":"Vlaams-Brabant",
    "wof:name":"Cialu",
    "wof:placetype":"venue"
},
  "geometry": {"coordinates":[4.4770002365,50.7677383423],"type":"Point"}
}