{
  "type": "Feature",
  "properties": {
    "iso:country":"BE",
    "sg:address":"Brouwerijstraat 11",
    "sg:city":"Wevelgem",
    "sg:classifiers":[
        {
            "category":"Utilities",
            "subcategory":"Natural Gas",
            "type":"Services"
        }
    ],
    "sg:phone":"+32 56 41 76 85",
    "sg:postcode":"8560",
    "sg:province":"West-Vlaanderen",
    "sg:tags":[
        "industrial",
        "-"
    ],
    "wof:name":"Demeulemeester Jp",
    "wof:placetype":"venue"
},
  "geometry": {"coordinates":[3.1661350727,50.8053207397],"type":"Point"}
}