{
  "type": "Feature",
  "properties": {
    "iso:country":"BE",
    "sg:address":"Langestr 2",
    "sg:city":"Gent(ledeberg)",
    "sg:classifiers":[
        {
            "category":"Farming",
            "subcategory":"Livestock Farm",
            "type":"Manufacturing & Wholesale Goods"
        }
    ],
    "sg:phone":"+32 9 232 33 22",
    "sg:postcode":"9050",
    "sg:province":"Oost-Vlaanderen",
    "sg:tags":[
        "breeding",
        "agriculture",
        "animal"
    ],
    "wof:name":"Meersschaut",
    "wof:placetype":"venue"
},
  "geometry": {"coordinates":[3.7450249195,51.0394172668],"type":"Point"}
}