{
  "type": "Feature",
  "properties": {
    "iso:country":"BE",
    "sg:address":"Rue De Namur 53",
    "sg:city":"Chatelet",
    "sg:orig_category":"Huishoudapparaten, televisies and radio's Loodgieterij and centrale verwarming Gh Loodgieterij, verw",
    "sg:phone":"+32 71 38 11 72",
    "sg:postcode":"6200",
    "sg:province":"Hainaut",
    "wof:name":"Inter Chauffage Chatelet",
    "wof:placetype":"venue"
},
  "geometry": {"coordinates":[4.5314788818,50.4001045227],"type":"Point"}
}