{
  "type": "Feature",
  "properties": {
    "iso:country":"BE",
    "sg:address":"427",
    "sg:city":"Boomsesteenweg 2610 Antwerpen",
    "sg:classifiers":[
        {
            "category":"Autos & Motor Vehicles",
            "subcategory":"Automobile Sales",
            "type":"Retail Goods"
        }
    ],
    "sg:phone":"+32 3 820 74 00",
    "sg:postcode":"427",
    "sg:tags":[
        "equipment",
        "motor-cars",
        "transport"
    ],
    "wof:name":"Jorssen Nv",
    "wof:placetype":"venue"
},
  "geometry": {"coordinates":[4.3897399902,51.1815452576],"type":"Point"}
}