{
  "type": "Feature",
  "properties": {
    "addr:full":"Rue Des Coteaux 40-42 Bruxelles-schaerbeek Bruxelles-Capitale 1030",
    "addr:housenumber":"40-42",
    "addr:postcode":"1030",
    "addr:street":"Rue Des Coteaux",
    "iso:country":"BE",
    "sg:address":"Rue Des Coteaux 40-42",
    "sg:city":"Bruxelles-schaerbeek",
    "sg:orig_category":"Microsoft. Ordinateurs and \u00e9quipement informatique",
    "sg:phone":"+32 2 215 24 38",
    "sg:postcode":"1030",
    "sg:province":"Bruxelles-Capitale",
    "wof:name":"Delta Software Applications",
    "wof:placetype":"venue"
},
  "geometry": {"coordinates":[4.3747849464,50.8556251526],"type":"Point"}
}