{
  "type": "Feature",
  "properties": {
    "iso:country":"BE",
    "sg:address":"Polderstraat 32",
    "sg:city":"Londerzeel",
    "sg:classifiers":[
        {
            "category":"Professional",
            "subcategory":"Computer Services",
            "type":"Services"
        }
    ],
    "sg:phone":"+32 52 30 35 98",
    "sg:postcode":"1840",
    "sg:province":"Vlaams-Brabant",
    "sg:tags":[
        "webdesign",
        "-",
        "internet"
    ],
    "wof:name":"Vision Line Bvba",
    "wof:placetype":"venue"
},
  "geometry": {"coordinates":[4.2987318039,50.9998321533],"type":"Point"}
}