{
  "type": "Feature",
  "properties": {
    "iso:country":"BE",
    "sg:address":"Gentweg 35",
    "sg:city":"Gavere (vurste)",
    "sg:classifiers":[
        {
            "category":"Farming",
            "subcategory":"Livestock Farm",
            "type":"Manufacturing & Wholesale Goods"
        }
    ],
    "sg:phone":"+32 9 384 21 08",
    "sg:postcode":"9890",
    "sg:province":"Oost-Vlaanderen",
    "sg:tags":[
        "buyer"
    ],
    "wof:name":"De Boever G",
    "wof:placetype":"venue"
},
  "geometry": {"coordinates":[3.6832768917,50.9424133301],"type":"Point"}
}