{
  "type": "Feature",
  "properties": {
    "addr:full":"Grand-place 8 Leuze-en-hainaut Hainaut 7900",
    "addr:housenumber":"8",
    "addr:postcode":"7900",
    "addr:street":"Grand-Place",
    "iso:country":"BE",
    "sg:address":"Grand-place 8",
    "sg:city":"Leuze-en-hainaut",
    "sg:orig_category":"Postkantoren Verzekeringsmakelaars and experts",
    "sg:phone":"+32 69 66 23 31",
    "sg:postcode":"7900",
    "sg:province":"Hainaut",
    "wof:name":"La Poste",
    "wof:placetype":"venue"
},
  "geometry": {"coordinates":[3.6179430485,50.5985908508],"type":"Point"}
}