{
  "type": "Feature",
  "properties": {
    "addr:full":"Turnhoutsebaan 94 Kasterlee Antwerpen 2460",
    "addr:housenumber":"94",
    "addr:postcode":"2460",
    "addr:street":"Turnhoutsebaan",
    "iso:country":"BE",
    "sg:address":"Turnhoutsebaan 94",
    "sg:city":"Kasterlee",
    "sg:classifiers":[
        {
            "category":"Personal",
            "subcategory":"Beauty Salon",
            "type":"Services"
        }
    ],
    "sg:phone":"+32 14 85 07 47",
    "sg:postcode":"2460",
    "sg:province":"Antwerpen",
    "sg:tags":[
        "de",
        "coiffure"
    ],
    "wof:name":"Hairstudio Pascale",
    "wof:placetype":"venue"
},
  "geometry": {"coordinates":[4.9648160934,51.2464065552],"type":"Point"}
}