{
  "type": "Feature",
  "properties": {
    "addr:full":"Hoogstraat 17 Oudenaarde Oost-Vlaanderen 9700",
    "addr:housenumber":"17",
    "addr:postcode":"9700",
    "addr:street":"Hoogstraat",
    "iso:country":"BE",
    "sg:address":"Hoogstraat 17",
    "sg:city":"Oudenaarde",
    "sg:classifiers":[
        {
            "category":"Tea Room",
            "subcategory":"None",
            "type":"Food & Drink"
        }
    ],
    "sg:phone":"+32 55 31 15 66",
    "sg:postcode":"9700",
    "sg:province":"Oost-Vlaanderen",
    "wof:name":"Matagalpa",
    "wof:placetype":"venue"
},
  "geometry": {"coordinates":[3.6032559872,50.8443489075],"type":"Point"}
}