{
  "type": "Feature",
  "properties": {
    "addr:full":"Avenue De La Gare 28 Hotton Luxembourg 6990",
    "addr:housenumber":"28",
    "addr:postcode":"6990",
    "addr:street":"Avenue De La Gare",
    "iso:country":"BE",
    "sg:address":"Avenue De La Gare 28",
    "sg:city":"Hotton",
    "sg:classifiers":[
        {
            "category":"Retail",
            "subcategory":"Laundry & Dry Cleaning",
            "type":"Services"
        }
    ],
    "sg:phone":"+32 84 46 63 25",
    "sg:postcode":"6990",
    "sg:province":"Luxembourg",
    "sg:tags":[
        "dyer",
        "cleaner"
    ],
    "wof:name":"Hotton Pressing",
    "wof:placetype":"venue"
},
  "geometry": {"coordinates":[5.4400939941,50.272857666],"type":"Point"}
}