{
  "type": "Feature",
  "properties": {
    "addr:full":"Avenue Everard 28 Vorst/forest Bruxelles-Capitale 1190",
    "addr:housenumber":"28",
    "addr:postcode":"1190",
    "addr:street":"Avenue Everard;/ Forest",
    "iso:country":"BE",
    "sg:address":"Avenue Everard 28",
    "sg:city":"Vorst/forest",
    "sg:orig_category":"G\u00e9om\u00e8tres",
    "sg:phone":"+32 2 347 06 63",
    "sg:postcode":"1190",
    "sg:province":"Bruxelles-Capitale",
    "wof:name":"Maurice Swaelens",
    "wof:placetype":"venue"
},
  "geometry": {"coordinates":[4.3386268616,50.8160705566],"type":"Point"}
}