{
  "type": "Feature",
  "properties": {
    "addr:full":"All\u00e9e Des Renards 15 Profondeville Namur 5170",
    "addr:housenumber":"15",
    "addr:postcode":"5170",
    "addr:street":"Alle\u0301E Des Renards",
    "iso:country":"BE",
    "sg:address":"All\u00e9e Des Renards 15",
    "sg:city":"Profondeville",
    "sg:classifiers":[
        {
            "category":"Health Services",
            "subcategory":"Doctor",
            "type":"Services"
        }
    ],
    "sg:phone":"+32 81 41 24 94",
    "sg:postcode":"5170",
    "sg:province":"Namur",
    "sg:tags":[
        "medicinephysicians",
        "surgeon"
    ],
    "wof:name":"Lefebvre Beno\u00eet",
    "wof:placetype":"venue"
},
  "geometry": {"coordinates":[4.8583831787,50.3893623352],"type":"Point"}
}