{
  "type": "Feature",
  "properties": {
    "addr:full":"Avenue Du Roi Soldat 64 Bruxelles (anderlecht) Bruxelles-Capitale 1070",
    "addr:housenumber":"64",
    "addr:postcode":"1070",
    "addr:street":"Avenue Du Roi Soldat",
    "iso:country":"BE",
    "sg:address":"Avenue Du Roi Soldat 64",
    "sg:city":"Bruxelles (anderlecht)",
    "sg:classifiers":[
        {
            "category":"Health Services",
            "subcategory":"Doctor",
            "type":"Services"
        }
    ],
    "sg:phone":"+32 2 522 52 41",
    "sg:postcode":"1070",
    "sg:province":"Bruxelles-Capitale",
    "sg:tags":[
        "medicinephysicians",
        "surgeon"
    ],
    "wof:name":"Ketele F",
    "wof:placetype":"venue"
},
  "geometry": {"coordinates":[4.299200058,50.831401825],"type":"Point"}
}