{
  "type": "Feature",
  "properties": {
    "addr:full":"Avenue De L'aviation 72 Bruxelles (woluwe-saint-pierre) Bruxelles-Capitale 1150",
    "addr:housenumber":"72",
    "addr:postcode":"1150",
    "addr:street":"Avenue De L'Aviation",
    "iso:country":"BE",
    "sg:address":"Avenue De L'aviation 72",
    "sg:city":"Bruxelles (woluwe-saint-pierre)",
    "sg:classifiers":[
        {
            "category":"Health Services",
            "subcategory":"Health Practitioner",
            "type":"Services"
        }
    ],
    "sg:phone":"+32 2 772 04 30",
    "sg:postcode":"1150",
    "sg:province":"Bruxelles-Capitale",
    "sg:tags":[
        "physiotherapist"
    ],
    "wof:name":"Declerfayt Bernard",
    "wof:placetype":"venue"
},
  "geometry": {"coordinates":[4.4604568481,50.8319549561],"type":"Point"}
}