{
  "type": "Feature",
  "properties": {
    "iso:country":"BE",
    "sg:address":"Basse Marcelle 28",
    "sg:city":"Namur",
    "sg:orig_category":"Editeurs de revues and p\u00e9riodiques. Editeurs de journaux",
    "sg:phone":"+32 81 22 71 22",
    "sg:postcode":"5000",
    "sg:province":"Namur",
    "wof:name":"Imagine Le Monde",
    "wof:placetype":"venue"
},
  "geometry": {"coordinates":[4.8614339828,50.4646224976],"type":"Point"}
}