{
  "type": "Feature",
  "properties": {
    "addr:full":"Boerenlegerstraat 16 Edegem Antwerpen 2650",
    "addr:housenumber":"16",
    "addr:postcode":"2650",
    "addr:street":"Boerenlegerstraat",
    "iso:country":"BE",
    "sg:address":"Boerenlegerstraat 16",
    "sg:city":"Edegem",
    "sg:orig_category":"Location d'appareils audio-visuels. Animations diverses",
    "sg:phone":"+32 3 458 48 19",
    "sg:postcode":"2650",
    "sg:province":"Antwerpen",
    "wof:name":"Stage Master",
    "wof:placetype":"venue"
},
  "geometry": {"coordinates":[4.4445562363,51.1551208496],"type":"Point"}
}