{
  "type": "Feature",
  "properties": {
    "addr:full":"Karel Oomsstraat 11 Box 9 Antwerpen Antwerpen 2018",
    "addr:housenumber":"11;9",
    "addr:postcode":"2018",
    "addr:street":"Karel Oomsstraat;Box",
    "iso:country":"BE",
    "sg:address":"Karel Oomsstraat 11 Box 9",
    "sg:city":"Antwerpen",
    "sg:classifiers":[
        {
            "category":"Social Services",
            "type":"Services"
        }
    ],
    "sg:phone":"+32 3 216 23 31",
    "sg:postcode":"2018",
    "sg:province":"Antwerpen",
    "wof:name":"Grijze Panters (de) Vzw",
    "wof:placetype":"venue"
},
  "geometry": {"coordinates":[4.4097180367,51.1960220337],"type":"Point"}
}