{
  "type": "Feature",
  "properties": {
    "addr:full":"Zijpstraat 23 Duffel Antwerpen 2570",
    "addr:housenumber":"23",
    "addr:postcode":"2570",
    "addr:street":"Zijpstraat",
    "iso:country":"BE",
    "sg:address":"Zijpstraat 23",
    "sg:city":"Duffel",
    "sg:orig_category":"Groententeelt",
    "sg:phone":"+32 15 31 34 25",
    "sg:postcode":"2570",
    "sg:province":"Antwerpen",
    "wof:name":"Jozef Van Bulck",
    "wof:placetype":"venue"
},
  "geometry": {"coordinates":[4.5318408012,51.0961456299],"type":"Point"}
}