{
  "type": "Feature",
  "properties": {
    "addr:full":"Nederstraat 2 Kruibeke Oost-Vlaanderen 9150",
    "addr:housenumber":"2",
    "addr:postcode":"9150",
    "addr:street":"Nederstraat",
    "iso:country":"BE",
    "sg:address":"Nederstraat 2",
    "sg:city":"Kruibeke",
    "sg:orig_category":"Offices du tourisme",
    "sg:phone":"+32 3 744 10 13",
    "sg:postcode":"9150",
    "sg:province":"Oost-Vlaanderen",
    "wof:name":"V.v.v.",
    "wof:placetype":"venue"
},
  "geometry": {"coordinates":[4.2920632362,51.1262435913],"type":"Point"}
}