{
  "type": "Feature",
  "properties": {
    "iso:country":"BE",
    "sg:address":"Rue De Hotton 39ba",
    "sg:city":"Rendeux",
    "sg:classifiers":[
        {
            "category":"Home & Garden",
            "subcategory":"Carpets & Floor Coverings",
            "type":"Retail Goods"
        }
    ],
    "sg:phone":"+32 84 47 78 80",
    "sg:postcode":"6987",
    "sg:province":"Luxembourg",
    "sg:tags":[
        "l\u00e9gumes",
        "fruit",
        "gr"
    ],
    "wof:name":"Gossiau Fr\u00c8res",
    "wof:placetype":"venue"
},
  "geometry": {"coordinates":[5.5046601295,50.2384185791],"type":"Point"}
}