{
  "type": "Feature",
  "properties": {
    "iso:country":"BE",
    "sg:address":"Rue Osseghem 121",
    "sg:city":"Sint-jans-molenbeek/molenbeek-saint-jean",
    "sg:orig_category":"M\u00e9decins and sp\u00e9cialistes",
    "sg:phone":"+32 2 410 73 24",
    "sg:postcode":"1080",
    "sg:province":"Bruxelles-Capitale",
    "wof:name":"Isabelle Fran\u00c7ois",
    "wof:placetype":"venue"
},
  "geometry": {"coordinates":[4.3157558441,50.8537101746],"type":"Point"}
}