{
  "type": "Feature",
  "properties": {
    "addr:full":"Avenue Louis Pi\u00c9rard 19b1 Evere Bruxelles-Capitale 1140",
    "addr:housenumber":"19b1",
    "addr:postcode":"1140",
    "addr:street":"Avenue Louis Pie\u0301Rard",
    "iso:country":"BE",
    "sg:address":"Avenue Louis Pi\u00c9rard 19b1",
    "sg:city":"Evere",
    "sg:orig_category":"D\u00e9corateurs d'int\u00e9rieur",
    "sg:phone":"+32 2 248 17 17",
    "sg:postcode":"1140",
    "sg:province":"Bruxelles-Capitale",
    "wof:name":"Manuel Schneider",
    "wof:placetype":"venue"
},
  "geometry": {"coordinates":[4.4054107666,50.8743400574],"type":"Point"}
}