{
  "type": "Feature",
  "properties": {
    "iso:country":"BE",
    "sg:address":"Volpenswege 76",
    "sg:city":"Evergem",
    "sg:orig_category":"Eleveurs de bovins",
    "sg:phone":"+32 9 357 39 43",
    "sg:postcode":"9940",
    "sg:province":"Oost-Vlaanderen",
    "wof:name":"Willy Van Vooren",
    "wof:placetype":"venue"
},
  "geometry": {"coordinates":[3.6916639805,51.1613273621],"type":"Point"}
}