{
  "type": "Feature",
  "properties": {
    "addr:full":"Driemasten 63 Wevelgem West-Vlaanderen 8560",
    "addr:housenumber":"63",
    "addr:postcode":"8560",
    "addr:street":"Driemasten",
    "iso:country":"BE",
    "sg:address":"Driemasten 63",
    "sg:city":"Wevelgem",
    "sg:orig_category":"Verhuur cateringmateriaal and evenementuitrusting Verhuur diversen Winkelinrichting and handelsuitru",
    "sg:phone":"+32 56 40 06 99",
    "sg:postcode":"8560",
    "sg:province":"West-Vlaanderen",
    "wof:name":"Optima Rent",
    "wof:placetype":"venue"
},
  "geometry": {"coordinates":[3.1911959648,50.8530578613],"type":"Point"}
}