{
  "type": "Feature",
  "properties": {
    "iso:country":"BE",
    "sg:address":"Rue Large 17",
    "sg:city":"Li\u00e8ge 1 (ch\u00ean\u00e9e)",
    "sg:classifiers":[
        {
            "category":"Retail",
            "subcategory":"Veterinary Services",
            "type":"Services"
        }
    ],
    "sg:phone":"+32 4 365 14 94",
    "sg:postcode":"4032",
    "sg:province":"Li\u00e8ge",
    "sg:tags":[
        "veterinarian"
    ],
    "wof:name":"Delfontaine B",
    "wof:placetype":"venue"
},
  "geometry": {"coordinates":[5.6142349243,50.6141166687],"type":"Point"}
}