{
  "type": "Feature",
  "properties": {
    "iso:country":"BE",
    "sg:address":"Rue Augustin Duvivier 30",
    "sg:city":"Fleurus (lambusart)",
    "sg:classifiers":[
        {
            "category":"Professional",
            "subcategory":"Management & Consulting",
            "type":"Services"
        }
    ],
    "sg:phone":"+32 71 81 90 40",
    "sg:postcode":"6220",
    "sg:province":"Hainaut",
    "sg:tags":[
        "consultant",
        "law"
    ],
    "wof:name":"Gaspard M",
    "wof:placetype":"venue"
},
  "geometry": {"coordinates":[4.5573401451,50.4568748474],"type":"Point"}
}