{
  "type": "Feature",
  "properties": {
    "addr:full":"33-35 Oostendestraat Diksmuide West-Vlaanderen 8600",
    "addr:housenumber":"33-35",
    "addr:postcode":"8600",
    "addr:street":"Oostendestraat",
    "iso:country":"BE",
    "sg:address":"33-35 Oostendestraat",
    "sg:city":"Diksmuide",
    "sg:classifiers":[
        {
            "category":"Manufacturing",
            "subcategory":"Textiles",
            "type":"Manufacturing & Wholesale Goods"
        }
    ],
    "sg:phone":"+32 51 50 00 67",
    "sg:postcode":"8600",
    "sg:province":"West-Vlaanderen",
    "sg:tags":[
        "linen",
        "clothing",
        "fabric"
    ],
    "wof:name":"Bouwmaterialen Germain Vinckier Nv",
    "wof:placetype":"venue"
},
  "geometry": {"coordinates":[2.8657848835,51.0382461548],"type":"Point"}
}