{
  "type": "Feature",
  "properties": {
    "iso:country":"BE",
    "sg:address":"Rue Du Bourdon 70a",
    "sg:city":"Bruxelles (uccle)",
    "sg:classifiers":[
        {
            "category":"Depot",
            "subcategory":"Train",
            "type":"Transportation"
        }
    ],
    "sg:phone":"+32 2 376 45 98",
    "sg:postcode":"1180",
    "sg:province":"Bruxelles-Capitale",
    "sg:tags":[
        "gear",
        "lifting"
    ],
    "wof:name":"Promebat",
    "wof:placetype":"venue"
},
  "geometry": {"coordinates":[4.3316369057,50.7860565186],"type":"Point"}
}