{
  "type": "Feature",
  "properties": {
    "addr:full":"Vroente 35 Geel Antwerpen 2440",
    "addr:housenumber":"35",
    "addr:postcode":"2440",
    "addr:street":"Vroente",
    "iso:country":"BE",
    "sg:address":"Vroente 35",
    "sg:city":"Geel",
    "sg:classifiers":[
        {
            "category":"Arena",
            "subcategory":"Sports Club",
            "type":"Entertainment"
        }
    ],
    "sg:phone":"+32 14 58 68 57",
    "sg:postcode":"2440",
    "sg:province":"Antwerpen",
    "sg:tags":[
        "de"
    ],
    "wof:name":"Duivenbond Eindhout",
    "wof:placetype":"venue"
},
  "geometry": {"coordinates":[5.0091757774,51.1297111511],"type":"Point"}
}