{
  "type": "Feature",
  "properties": {
    "addr:full":"Provinciale Steenweg 44 Schelle Antwerpen 2627",
    "addr:housenumber":"44",
    "addr:postcode":"2627",
    "addr:street":"Provinciale Steenweg",
    "iso:country":"BE",
    "sg:address":"Provinciale Steenweg 44",
    "sg:city":"Schelle",
    "sg:orig_category":"Huishoudapparaten, televisies and radio's Verlichting and huishoudartikelen",
    "sg:phone":"+32 3 887 51 83",
    "sg:postcode":"2627",
    "sg:province":"Antwerpen",
    "wof:name":"Phaedon Univ.sonorisation",
    "wof:placetype":"venue"
},
  "geometry": {"coordinates":[4.3374509811,51.1282577515],"type":"Point"}
}