{
  "type": "Feature",
  "properties": {
    "addr:full":"Kruibekesteenweg 103ba Beveren Oost-Vlaanderen 9120",
    "addr:postcode":"9120",
    "addr:street":"Kruibekesteenweg;Oost-Vlaanderen",
    "iso:country":"BE",
    "sg:address":"Kruibekesteenweg 103ba",
    "sg:city":"Beveren",
    "sg:orig_category":"Installation \u00e9lectrique r\u00e9sidentielle",
    "sg:phone":"+32 3 755 36 59",
    "sg:postcode":"9120",
    "sg:province":"Oost-Vlaanderen",
    "wof:name":"Gert Cleys",
    "wof:placetype":"venue"
},
  "geometry": {"coordinates":[4.2637791634,51.203502655],"type":"Point"}
}