{
  "type": "Feature",
  "properties": {
    "iso:country":"BE",
    "sg:address":"Dennenstraat 13",
    "sg:city":"Meeuwen-gruitrode (wijshagen)",
    "sg:classifiers":[
        {
            "category":"Autos & Motor Vehicles",
            "subcategory":"Automobile Sales",
            "type":"Retail Goods"
        }
    ],
    "sg:phone":"+32 89 46 34 59",
    "sg:postcode":"3670",
    "sg:province":"Limburg",
    "sg:tags":[
        "car",
        "used",
        "-"
    ],
    "wof:name":"T.e.h.c.",
    "wof:placetype":"venue"
},
  "geometry": {"coordinates":[5.5521512032,51.1073760986],"type":"Point"}
}