{
  "type": "Feature",
  "properties": {
    "iso:country":"BE",
    "sg:address":"Rue Th\u00e9ophile Piat 25",
    "sg:city":"Wavre",
    "sg:classifiers":[
        {
            "category":"Education",
            "subcategory":"Special Training",
            "type":"Public Place"
        }
    ],
    "sg:phone":"+32 10 24 71 00",
    "sg:postcode":"1300",
    "sg:province":"Brabant Wallon",
    "sg:tags":[
        "school",
        "language"
    ],
    "wof:name":"Kindercaf\u00e9",
    "wof:placetype":"venue"
},
  "geometry": {"coordinates":[4.6056718826,50.7143135071],"type":"Point"}
}