{
  "type": "Feature",
  "properties": {
    "iso:country":"BE",
    "sg:address":"Molenhoekstraat 11",
    "sg:city":"Sint-gillis-waas",
    "sg:orig_category":"Jardinage",
    "sg:phone":"+32 3 773 49 35",
    "sg:postcode":"9170",
    "sg:province":"Oost-Vlaanderen",
    "wof:name":"Dhooge",
    "wof:placetype":"venue"
},
  "geometry": {"coordinates":[4.13189888,51.2712516785],"type":"Point"}
}