{
  "type": "Feature",
  "properties": {
    "addr:full":"Drie Kerkenstraat 23 Kortrijk West-Vlaanderen 8501",
    "addr:housenumber":"23",
    "addr:postcode":"8501",
    "addr:street":"Drie Kerkenstraat",
    "iso:country":"BE",
    "sg:address":"Drie Kerkenstraat 23",
    "sg:city":"Kortrijk",
    "sg:orig_category":"Huishoudapparaten, televisies and radio's Telecommunicatieapparaten",
    "sg:phone":"+32 56 35 25 51",
    "sg:postcode":"8501",
    "sg:province":"West-Vlaanderen",
    "wof:name":"Bostoen",
    "wof:placetype":"venue"
},
  "geometry": {"coordinates":[3.2336709499,50.8435592651],"type":"Point"}
}