{
  "type": "Feature",
  "properties": {
    "iso:country":"BE",
    "sg:address":"Beukenhofstraat 23",
    "sg:city":"Anzegem (vichte)",
    "sg:classifiers":[
        {
            "category":"Health Services",
            "subcategory":"Health Practitioner",
            "type":"Services"
        }
    ],
    "sg:phone":"+32 56 77 84 31",
    "sg:postcode":"8570",
    "sg:province":"West-Vlaanderen",
    "sg:tags":[
        "physiotherapist"
    ],
    "wof:name":"Clarisse Patrick",
    "wof:placetype":"venue"
},
  "geometry": {"coordinates":[3.3985540867,50.8369026184],"type":"Point"}
}