{
  "type": "Feature",
  "properties": {
    "iso:country":"BE",
    "sg:address":"Napoleonkaai 19",
    "sg:city":"Antwerpen",
    "sg:classifiers":[
        {
            "category":"Marine",
            "type":"Transportation"
        }
    ],
    "sg:phone":"+32 3 226 28 00",
    "sg:postcode":"2000",
    "sg:province":"Antwerpen",
    "sg:tags":[
        "chartering",
        "ship"
    ],
    "wof:name":"European Chartering Systems Nv",
    "wof:placetype":"venue"
},
  "geometry": {"coordinates":[4.4085679054,51.2300605774],"type":"Point"}
}