{
  "type": "Feature",
  "properties": {
    "addr:full":"Avenue Milcamps 8 Schaarbeek/schaerbeek Bruxelles-Capitale 1030",
    "addr:housenumber":"8",
    "addr:postcode":"1030",
    "addr:street":"Avenue Milcamps",
    "iso:country":"BE",
    "sg:address":"Avenue Milcamps 8",
    "sg:city":"Schaarbeek/schaerbeek",
    "sg:orig_category":"Avocats and conseillers juridiques",
    "sg:phone":"+32 2 743 84 52",
    "sg:postcode":"1030",
    "sg:province":"Bruxelles-Capitale",
    "wof:name":"Carlo Locchi",
    "wof:placetype":"venue"
},
  "geometry": {"coordinates":[4.3927750587,50.8476066589],"type":"Point"}
}