{
  "type": "Feature",
  "properties": {
    "addr:full":"Verbertveld 1 Grimbergen Vlaams-Brabant 1853",
    "addr:housenumber":"1",
    "addr:postcode":"1853",
    "addr:street":"Verbertveld",
    "iso:country":"BE",
    "sg:address":"Verbertveld 1",
    "sg:city":"Grimbergen",
    "sg:orig_category":"Charpentes and couvertures",
    "sg:phone":"+32 2 245 45 15",
    "sg:postcode":"1853",
    "sg:province":"Vlaams-Brabant",
    "wof:name":"S.m.c.o.",
    "wof:placetype":"venue"
},
  "geometry": {"coordinates":[4.3507881165,50.9054527283],"type":"Point"}
}