{
  "type": "Feature",
  "properties": {
    "addr:full":"Leopold Iii Straat 3 Kortessem Limburg 3724",
    "addr:housenumber":"3",
    "addr:postcode":"3724",
    "addr:street":"Leopold Iii Straat",
    "iso:country":"BE",
    "sg:address":"Leopold Iii Straat 3",
    "sg:city":"Kortessem",
    "sg:orig_category":"Instituts de beaut\u00e9",
    "sg:phone":"+32 12 39 20 47",
    "sg:postcode":"3724",
    "sg:province":"Limburg",
    "wof:name":"Marie-christine Rubens",
    "wof:placetype":"venue"
},
  "geometry": {"coordinates":[5.4292812347,50.8395347595],"type":"Point"}
}