{
  "type": "Feature",
  "properties": {
    "addr:full":"Stationsplein 27 Lokeren Oost-Vlaanderen 9160",
    "addr:housenumber":"27",
    "addr:postcode":"9160",
    "addr:street":"Stationsplein",
    "iso:country":"BE",
    "sg:address":"Stationsplein 27",
    "sg:city":"Lokeren",
    "sg:orig_category":"Treinen and spoorwegen",
    "sg:phone":"+32 9 348 25 60",
    "sg:postcode":"9160",
    "sg:province":"Oost-Vlaanderen",
    "wof:name":"Station Lokeren",
    "wof:placetype":"venue"
},
  "geometry": {"coordinates":[3.9877181053,51.1064376831],"type":"Point"}
}