{
  "type": "Feature",
  "properties": {
    "addr:full":"Rue De Monsville 43 Quaregnon Hainaut 7390",
    "addr:housenumber":"43",
    "addr:postcode":"7390",
    "addr:street":"Rue De Monsville",
    "iso:country":"BE",
    "sg:address":"Rue De Monsville 43",
    "sg:city":"Quaregnon",
    "sg:orig_category":"Verplichte sociale verzekeringen",
    "sg:phone":"+32 65 78 33 02",
    "sg:postcode":"7390",
    "sg:province":"Hainaut",
    "wof:name":"Mutuelle St.joseph",
    "wof:placetype":"venue"
},
  "geometry": {"coordinates":[3.866024971,50.4396934509],"type":"Point"}
}