{
  "type": "Feature",
  "properties": {
    "addr:full":"Steenweg Op Oosthoven 168 Turnhout Antwerpen 2300",
    "addr:housenumber":"168",
    "addr:postcode":"2300",
    "addr:street":"Steenweg Op Oosthoven",
    "iso:country":"BE",
    "sg:address":"Steenweg Op Oosthoven 168",
    "sg:city":"Turnhout",
    "sg:orig_category":"Cuisines Ilwa",
    "sg:phone":"+32 14 42 90 11",
    "sg:postcode":"2300",
    "sg:province":"Antwerpen",
    "wof:name":"Ilwa - A&p Design",
    "wof:placetype":"venue"
},
  "geometry": {"coordinates":[4.9504871368,51.3290977478],"type":"Point"}
}