{
  "type": "Feature",
  "properties": {
    "addr:full":"Rijksweg 139ba Dilsen-stokkem Limburg 3650",
    "addr:postcode":"3650",
    "addr:street":"Rijksweg 139Ba",
    "iso:country":"BE",
    "sg:address":"Rijksweg 139ba",
    "sg:city":"Dilsen-stokkem",
    "sg:orig_category":"Articles pour b\u00e9b\u00e9s. V\u00eatements pour b\u00e9b\u00e9s and enfants",
    "sg:phone":"+32 89 75 73 79",
    "sg:postcode":"3650",
    "sg:province":"Limburg",
    "wof:name":"Babyhome",
    "wof:placetype":"venue"
},
  "geometry": {"coordinates":[5.7266697884,51.0228614807],"type":"Point"}
}