{
  "type": "Feature",
  "properties": {
    "iso:country":"BE",
    "sg:address":"Hoogstraat 16",
    "sg:city":"Harelbeke (bavikhove)",
    "sg:classifiers":[
        {
            "category":"Real Estate",
            "subcategory":"Architect",
            "type":"Services"
        }
    ],
    "sg:phone":"+32 56 72 78 38",
    "sg:postcode":"8531",
    "sg:province":"West-Vlaanderen",
    "wof:name":"Samoy N",
    "wof:placetype":"venue"
},
  "geometry": {"coordinates":[3.31062603,50.8790245056],"type":"Point"}
}