{
  "type": "Feature",
  "properties": {
    "iso:country":"BE",
    "sg:address":"Rue De Robermont 8b",
    "sg:city":"Li\u00e8ge 1 (li\u00e8ge 2)",
    "sg:classifiers":[
        {
            "category":"Organizations",
            "subcategory":"Professional Association",
            "type":"Services"
        }
    ],
    "sg:phone":"+32 4 344 34 59",
    "sg:postcode":"4020",
    "sg:province":"Li\u00e8ge",
    "sg:tags":[
        "organisation",
        "seminar"
    ],
    "wof:name":"Les Caves De Cornillon",
    "wof:placetype":"venue"
},
  "geometry": {"coordinates":[5.5923728943,50.6354103088],"type":"Point"}
}