{
  "type": "Feature",
  "properties": {
    "iso:country":"BE",
    "sg:address":"Veemarkt 47",
    "sg:city":"Kortrijk",
    "sg:classifiers":[
        {
            "category":"Food & Beverages",
            "subcategory":"Liquor & Beverages",
            "type":"Retail Goods"
        }
    ],
    "sg:phone":"+32 477 63 63 49",
    "sg:postcode":"8500",
    "sg:province":"West-Vlaanderen",
    "sg:tags":[
        "-",
        "spirit",
        "wine"
    ],
    "wof:name":"Vroman B",
    "wof:placetype":"venue"
},
  "geometry": {"coordinates":[3.2737050056,50.8261947632],"type":"Point"}
}