{
  "type": "Feature",
  "properties": {
    "iso:country":"BE",
    "sg:address":"Boskant 65",
    "sg:city":"Bornem",
    "sg:orig_category":"Rundveehouders",
    "sg:phone":"+32 3 889 69 68",
    "sg:postcode":"2880",
    "sg:province":"Antwerpen",
    "wof:name":"Luciaan De Kerf",
    "wof:placetype":"venue"
},
  "geometry": {"coordinates":[4.2292108536,51.0781402588],"type":"Point"}
}