{
  "type": "Feature",
  "properties": {
    "addr:full":"Bruyningstraat 60 Kortrijk (marke) West-Vlaanderen 8510",
    "addr:housenumber":"60",
    "addr:postcode":"8510",
    "addr:street":"Bruyningstraat",
    "iso:country":"BE",
    "sg:address":"Bruyningstraat 60",
    "sg:city":"Kortrijk (marke)",
    "sg:classifiers":[
        {
            "category":"Building & Trades",
            "subcategory":"Landscaping Services",
            "type":"Services"
        }
    ],
    "sg:phone":"+32 56 20 37 20",
    "sg:postcode":"8510",
    "sg:province":"West-Vlaanderen",
    "sg:tags":[
        "access",
        "pond",
        "laying-out",
        "-"
    ],
    "wof:name":"Descamps Tuinen-jardins",
    "wof:placetype":"venue"
},
  "geometry": {"coordinates":[3.25750494,50.8076972961],"type":"Point"}
}