{
  "type": "Feature",
  "properties": {
    "addr:full":"Postbus 10 Balen Antwerpen 2490",
    "addr:housenumber":"10",
    "addr:postcode":"2490",
    "addr:street":"Postbus",
    "iso:country":"BE",
    "sg:address":"Postbus 10",
    "sg:city":"Balen",
    "sg:orig_category":"Agents artistiques. Editeurs d'enregistrements sonores",
    "sg:phone":"+32 14 82 07 18",
    "sg:postcode":"2490",
    "sg:province":"Antwerpen",
    "wof:name":"Wizard-records Belgium",
    "wof:placetype":"venue"
},
  "geometry": {"coordinates":[5.1680059433,51.1709327698],"type":"Point"}
}