{
  "type": "Feature",
  "properties": {
    "addr:full":"Kolonel Bourgstraat 111 Evere Bruxelles-Capitale 1140",
    "addr:housenumber":"111",
    "addr:postcode":"1140",
    "addr:street":"Kolonel Bourgstraat",
    "iso:country":"BE",
    "sg:address":"Kolonel Bourgstraat 111",
    "sg:city":"Evere",
    "sg:orig_category":"Werk and personeelsselectie",
    "sg:phone":"+32 2 730 11 75",
    "sg:postcode":"1140",
    "sg:province":"Bruxelles-Capitale",
    "wof:name":"Adecco Select",
    "wof:placetype":"venue"
},
  "geometry": {"coordinates":[4.4140529633,50.8541069031],"type":"Point"}
}