{
  "type": "Feature",
  "properties": {
    "addr:full":"Gen. Baron Jacquesstraat 3 Diksmuide West-Vlaanderen 8600",
    "addr:housenumber":"3",
    "addr:postcode":"8600",
    "addr:street":"Gen. Baron Jacquesstraat",
    "iso:country":"BE",
    "sg:address":"Gen. Baron Jacquesstraat 3",
    "sg:city":"Diksmuide",
    "sg:orig_category":"Pharmaciens",
    "sg:phone":"+32 51 50 00 52",
    "sg:postcode":"8600",
    "sg:province":"West-Vlaanderen",
    "wof:name":"Marc De Witte",
    "wof:placetype":"venue"
},
  "geometry": {"coordinates":[2.8634500504,51.0335617065],"type":"Point"}
}