{
  "type": "Feature",
  "properties": {
    "iso:country":"BE",
    "sg:address":"Chauss\u00c9e De Boondael 439",
    "sg:city":"Elsene/ixelles",
    "sg:orig_category":"Disquaires",
    "sg:phone":"+32 2 640 01 46",
    "sg:postcode":"1050",
    "sg:province":"Bruxelles-Capitale",
    "wof:name":"Music Mart",
    "wof:placetype":"venue"
},
  "geometry": {"coordinates":[4.3887629509,50.8168144226],"type":"Point"}
}