{
  "type": "Feature",
  "properties": {
    "iso:country":"BE",
    "sg:address":"Karmstraat 46",
    "sg:city":"Tielt",
    "sg:orig_category":"Rundveehouders Varkenskwekers",
    "sg:phone":"+32 51 63 33 59",
    "sg:postcode":"8700",
    "sg:province":"West-Vlaanderen",
    "wof:name":"Danny Rogge",
    "wof:placetype":"venue"
},
  "geometry": {"coordinates":[3.4058248997,50.9901885986],"type":"Point"}
}