{
  "type": "Feature",
  "properties": {
    "addr:full":"Liebaardstraat 176 Waregem (desselgem) West-Vlaanderen 8792",
    "addr:housenumber":"176",
    "addr:postcode":"8792",
    "addr:street":"Liebaardstraat",
    "iso:country":"BE",
    "sg:address":"Liebaardstraat 176",
    "sg:city":"Waregem (desselgem)",
    "sg:classifiers":[
        {
            "category":"Building & Trades",
            "subcategory":"Cleaning & Sanitation",
            "type":"Services"
        }
    ],
    "sg:phone":"+32 56 72 74 74",
    "sg:postcode":"8792",
    "sg:province":"West-Vlaanderen",
    "sg:tags":[
        "sweep",
        "chimney"
    ],
    "wof:name":"Abc-cleaning",
    "wof:placetype":"venue"
},
  "geometry": {"coordinates":[3.3555459976,50.8820571899],"type":"Point"}
}