{
  "type": "Feature",
  "properties": {
    "addr:full":"Avenue G\u00e9n\u00e9ral Dossin De Saint-georges 11 Bruxelles (ixelles) Bruxelles-Capitale 1050",
    "addr:housenumber":"11",
    "addr:postcode":"1050",
    "addr:street":"Avenue Ge\u0301Ne\u0301Ral Dossin De Saint-Georges",
    "iso:country":"BE",
    "sg:address":"Avenue G\u00e9n\u00e9ral Dossin De Saint-georges 11",
    "sg:city":"Bruxelles (ixelles)",
    "sg:classifiers":[
        {
            "category":"Personal",
            "subcategory":"Beauty Salon",
            "type":"Services"
        }
    ],
    "sg:phone":"+32 2 648 33 71",
    "sg:postcode":"1050",
    "sg:province":"Bruxelles-Capitale",
    "sg:tags":[
        "lady",
        "-",
        "hairdressing"
    ],
    "wof:name":"C. M. Coiffure",
    "wof:placetype":"venue"
},
  "geometry": {"coordinates":[4.3896222115,50.8103904724],"type":"Point"}
}