{
  "type": "Feature",
  "properties": {
    "addr:full":"Rue De Gen\u00e8ve 4 Bruxelles (evere) Bruxelles-Capitale 1140",
    "addr:housenumber":"4",
    "addr:postcode":"1140",
    "addr:street":"Rue De Gene\u0300Ve",
    "iso:country":"BE",
    "sg:address":"Rue De Gen\u00e8ve 4",
    "sg:city":"Bruxelles (evere)",
    "sg:classifiers":[
        {
            "category":"Professional",
            "subcategory":"Management & Consulting",
            "type":"Services"
        }
    ],
    "sg:phone":"+32 2 729 92 11",
    "sg:postcode":"1140",
    "sg:province":"Bruxelles-Capitale",
    "sg:tags":[
        "consultant",
        "-",
        "legislation",
        "social"
    ],
    "wof:name":"Career Consult Securex",
    "wof:placetype":"venue"
},
  "geometry": {"coordinates":[4.4032859802,50.8655014038],"type":"Point"}
}