{
  "type": "Feature",
  "properties": {
    "addr:full":"Rue Anne De Molina 5 Dison Li\u00e8ge 4821",
    "addr:housenumber":"5",
    "addr:postcode":"4821",
    "addr:street":"Rue Anne De Molina",
    "iso:country":"BE",
    "sg:address":"Rue Anne De Molina 5",
    "sg:city":"Dison",
    "sg:orig_category":"Verplichte sociale verzekeringen",
    "sg:phone":"+32 87 33 07 49",
    "sg:postcode":"4821",
    "sg:province":"Li\u00e8ge",
    "wof:name":"The Royal Self Help",
    "wof:placetype":"venue"
},
  "geometry": {"coordinates":[5.8627290726,50.6003952026],"type":"Point"}
}