{
  "type": "Feature",
  "properties": {
    "iso:country":"BE",
    "sg:address":"Rue De Saint-leger 79",
    "sg:city":"Moeskroen/mouscron",
    "sg:orig_category":"V\u00e9t\u00e9rinaires",
    "sg:phone":"+32 56 48 80 63",
    "sg:postcode":"7711",
    "sg:province":"Hainaut",
    "wof:name":"Christian D'haeye",
    "wof:placetype":"venue"
},
  "geometry": {"coordinates":[3.306098938,50.7245788574],"type":"Point"}
}