{
  "type": "Feature",
  "properties": {
    "iso:country":"BE",
    "sg:address":"Schotelven 18",
    "sg:city":"Arendonk",
    "sg:orig_category":"Autombile concessionaires",
    "sg:phone":"+32 14 67 77 55",
    "sg:postcode":"2370",
    "sg:province":"Antwerpen",
    "wof:name":"T.t.a. Arendonk Bvba",
    "wof:placetype":"venue"
},
  "geometry": {"coordinates":[5.0652108192,51.3156471252],"type":"Point"}
}