{
  "type": "Feature",
  "properties": {
    "addr:full":"Grote Baan 2 Hasselt (kuringen) Limburg 3511",
    "addr:housenumber":"2",
    "addr:postcode":"3511",
    "addr:street":"Grote Baan",
    "iso:country":"BE",
    "sg:address":"Grote Baan 2",
    "sg:city":"Hasselt (kuringen)",
    "sg:classifiers":[
        {
            "category":"Banks & Credit Unions",
            "subcategory":"Financial Services",
            "type":"Services"
        }
    ],
    "sg:phone":"+32 11 87 26 87",
    "sg:postcode":"3511",
    "sg:province":"Limburg",
    "sg:tags":[
        "loan",
        "mortgage"
    ],
    "wof:name":"Van Den Hove M Eurostudie Vof Vof",
    "wof:placetype":"venue"
},
  "geometry": {"coordinates":[5.3063459396,50.9401512146],"type":"Point"}
}