{
  "type": "Feature",
  "properties": {
    "iso:country":"BE",
    "sg:address":"Rue De La Mutualit\u00e9 123",
    "sg:city":"Li\u00e8ge 1 (grivegn\u00e9e)",
    "sg:classifiers":[
        {
            "category":"Health Services",
            "subcategory":"Doctor",
            "type":"Services"
        }
    ],
    "sg:phone":"+32 4 367 79 74",
    "sg:postcode":"4030",
    "sg:province":"Li\u00e8ge",
    "sg:tags":[
        "medicinephysicians",
        "surgeon"
    ],
    "wof:name":"Bitotwa Mbayo",
    "wof:placetype":"venue"
},
  "geometry": {"coordinates":[5.6217851639,50.6276359558],"type":"Point"}
}