{
  "type": "Feature",
  "properties": {
    "addr:full":"Avenue V\u00e9sale 17 Wavre Brabant Wallon 1300",
    "addr:housenumber":"17;1300",
    "addr:street":"Avenue Ve\u0301Sale",
    "iso:country":"BE",
    "sg:address":"Avenue V\u00e9sale 17",
    "sg:city":"Wavre",
    "sg:orig_category":"Non-Classified Establishments",
    "sg:phone":"+32 10 22 24 12",
    "sg:postcode":"1300",
    "sg:province":"Brabant Wallon",
    "wof:name":"Offermann Salons & D\u00e9coration",
    "wof:placetype":"venue"
},
  "geometry": {"coordinates":[4.5834951401,50.7342147827],"type":"Point"}
}