{
  "type": "Feature",
  "properties": {
    "iso:country":"BE",
    "sg:address":"Schuttersstraat 15",
    "sg:city":"Mechelen",
    "sg:classifiers":[
        {
            "category":"Professional",
            "subcategory":"Lawyer & Legal Services",
            "type":"Services"
        }
    ],
    "sg:phone":"+32 15 41 05 17",
    "sg:postcode":"2800",
    "sg:province":"Antwerpen",
    "wof:name":"Loncke Karel",
    "wof:placetype":"venue"
},
  "geometry": {"coordinates":[4.4872641563,51.0085906982],"type":"Point"}
}