{
  "type": "Feature",
  "properties": {
    "iso:country":"BE",
    "sg:address":"Rue Saint-sauveur 294",
    "sg:city":"Wanze (moha)",
    "sg:classifiers":[
        {
            "category":"Building & Trades",
            "subcategory":"Construction",
            "type":"Services"
        }
    ],
    "sg:phone":"+32 85 25 53 27",
    "sg:postcode":"4520",
    "sg:province":"Li\u00e8ge",
    "sg:tags":[
        "installation",
        "-",
        "central",
        "heating"
    ],
    "wof:name":"Buiter O",
    "wof:placetype":"venue"
},
  "geometry": {"coordinates":[5.1779689789,50.5416946411],"type":"Point"}
}