{
  "type": "Feature",
  "properties": {
    "addr:full":"Rue Beeckman 19 Li\u00e8ge 1 Li\u00e8ge 4000",
    "addr:housenumber":"19;1",
    "addr:postcode":"4000",
    "addr:street":"Rue Beeckman",
    "iso:country":"BE",
    "sg:address":"Rue Beeckman 19",
    "sg:city":"Li\u00e8ge 1",
    "sg:classifiers":[
        {
            "category":"Education",
            "subcategory":"University",
            "type":"Public Place"
        }
    ],
    "sg:phone":"+32 4 223 38 04",
    "sg:postcode":"4000",
    "sg:province":"Li\u00e8ge",
    "sg:tags":[
        "higher"
    ],
    "wof:name":"Institut Provincial D'enseignement Superieur Paramedical",
    "wof:placetype":"venue"
},
  "geometry": {"coordinates":[5.565196991,50.6369590759],"type":"Point"}
}