{
  "type": "Feature",
  "properties": {
    "addr:full":"Iz Schurhovenveld 2608 St-truiden Limburg 3800",
    "addr:housenumber":"2608",
    "addr:postcode":"3800",
    "addr:street":"Schurhovenveld",
    "iso:country":"BE",
    "sg:address":"Iz Schurhovenveld 2608",
    "sg:city":"St-truiden",
    "sg:classifiers":[
        {
            "category":"Government",
            "subcategory":"Department Of Motor Vehicles",
            "type":"Public Place"
        }
    ],
    "sg:phone":"+32 11 69 78 07",
    "sg:postcode":"3800",
    "sg:province":"Limburg",
    "sg:tags":[
        "equipment",
        "industrial",
        "transport",
        "motor-cars"
    ],
    "wof:name":"Celis Cars Nv",
    "wof:placetype":"venue"
},
  "geometry": {"coordinates":[5.1863641739,50.8153343201],"type":"Point"}
}