{
  "type": "Feature",
  "properties": {
    "iso:country":"BE",
    "sg:address":"Brugstraat 35",
    "sg:city":"Beveren",
    "sg:orig_category":"Gestion de portefeuilles and fortunes, conseils en placements",
    "sg:phone":"+32 3 755 49 14",
    "sg:postcode":"9120",
    "sg:province":"Oost-Vlaanderen",
    "wof:name":"Dierickx J",
    "wof:placetype":"venue"
},
  "geometry": {"coordinates":[4.1974468231,51.2200622559],"type":"Point"}
}