{
  "type": "Feature",
  "properties": {
    "addr:full":"Monseigneur Heylenstraat 13 Kasterlee Antwerpen 2460",
    "addr:housenumber":"13",
    "addr:postcode":"2460",
    "addr:street":"Monseigneur Heylenstraat",
    "iso:country":"BE",
    "sg:address":"Monseigneur Heylenstraat 13",
    "sg:city":"Kasterlee",
    "sg:classifiers":[
        {
            "category":"Health Services",
            "subcategory":"Health Practitioner",
            "type":"Services"
        }
    ],
    "sg:phone":"+32 14 85 34 38",
    "sg:postcode":"2460",
    "sg:province":"Antwerpen",
    "sg:tags":[
        "physiotherapist"
    ],
    "wof:name":"Wens I",
    "wof:placetype":"venue"
},
  "geometry": {"coordinates":[4.9658632278,51.2389564514],"type":"Point"}
}