{
  "type": "Feature",
  "properties": {
    "addr:full":"Ieperstraat 9 Mesen West-Vlaanderen 8957",
    "addr:housenumber":"9",
    "addr:postcode":"8957",
    "addr:street":"Ieperstraat",
    "iso:country":"BE",
    "sg:address":"Ieperstraat 9",
    "sg:city":"Mesen",
    "sg:orig_category":"Herstelling horloges and juwelen Juwelen and horloges Opticiens",
    "sg:phone":"+32 57 44 49 91",
    "sg:postcode":"8957",
    "sg:province":"West-Vlaanderen",
    "wof:name":"Grison",
    "wof:placetype":"venue"
},
  "geometry": {"coordinates":[2.8965339661,50.7656822205],"type":"Point"}
}