{
  "type": "Feature",
  "properties": {
    "addr:full":"Boulevard Emile Bockstael 201 Brussel/bruxelles Bruxelles-Capitale 1020",
    "addr:housenumber":"201",
    "addr:postcode":"1020",
    "addr:street":"Boulevard Emile Bockstael;/",
    "iso:country":"BE",
    "sg:address":"Boulevard Emile Bockstael 201",
    "sg:city":"Brussel/bruxelles",
    "sg:classifiers":[
        {
            "category":"Restaurant",
            "type":"Food & Drink"
        }
    ],
    "sg:phone":"+32 2 426 52 73",
    "sg:postcode":"1020",
    "sg:province":"Bruxelles-Capitale",
    "wof:name":"Le Frascati",
    "wof:placetype":"venue"
},
  "geometry": {"coordinates":[4.348651886,50.8760223389],"type":"Point"}
}