{
  "type": "Feature",
  "properties": {
    "addr:full":"Rue De Cond\u00e9 54 Mons (baudour) Hainaut 7331",
    "addr:housenumber":"54",
    "addr:postcode":"7331",
    "addr:street":"Rue De Conde\u0301",
    "iso:country":"BE",
    "sg:address":"Rue De Cond\u00e9 54",
    "sg:city":"Mons (baudour)",
    "sg:classifiers":[
        {
            "category":"Bakery",
            "type":"Food & Drink"
        }
    ],
    "sg:phone":"+32 65 64 13 68",
    "sg:postcode":"7331",
    "sg:province":"Hainaut",
    "sg:tags":[
        "confectioner",
        "baker"
    ],
    "wof:name":"Leclercq Fr\u00e8res Sprl",
    "wof:placetype":"venue"
},
  "geometry": {"coordinates":[3.832367897,50.4841804504],"type":"Point"}
}