{
  "type": "Feature",
  "properties": {
    "addr:full":"Vlamingstraat 2 Sint-laureins Oost-Vlaanderen 9980",
    "addr:housenumber":"2",
    "addr:postcode":"9980",
    "addr:street":"Vlamingstraat",
    "iso:country":"BE",
    "sg:address":"Vlamingstraat 2",
    "sg:city":"Sint-laureins",
    "sg:orig_category":"Epiceries",
    "sg:phone":"+32 9 379 09 65",
    "sg:postcode":"9980",
    "sg:province":"Oost-Vlaanderen",
    "wof:name":"Spar",
    "wof:placetype":"venue"
},
  "geometry": {"coordinates":[3.527025938,51.2416267395],"type":"Point"}
}