{
  "type": "Feature",
  "properties": {
    "addr:full":"Rue De Biron 73 Ciney Namur 5590",
    "addr:housenumber":"73",
    "addr:postcode":"5590",
    "addr:street":"Rue De Biron",
    "iso:country":"BE",
    "sg:address":"Rue De Biron 73",
    "sg:city":"Ciney",
    "sg:orig_category":"Installation de serres, double vitrage and fen\u00eatres",
    "sg:phone":"+32 83 21 24 57",
    "sg:postcode":"5590",
    "sg:province":"Namur",
    "wof:name":"Stanley Harrington",
    "wof:placetype":"venue"
},
  "geometry": {"coordinates":[5.110159874,50.2966194153],"type":"Point"}
}