{
  "type": "Feature",
  "properties": {
    "addr:full":"Rue De Menin 150 Mouscron Hainaut 7700",
    "addr:housenumber":"150",
    "addr:postcode":"7700",
    "addr:street":"Rue De Menin",
    "iso:country":"BE",
    "sg:address":"Rue De Menin 150",
    "sg:city":"Mouscron",
    "sg:orig_category":"Herstellingen and onderhoud van auto's",
    "sg:phone":"+32 56 85 65 00",
    "sg:postcode":"7700",
    "sg:province":"Hainaut",
    "wof:name":"Garage Blondeel",
    "wof:placetype":"venue"
},
  "geometry": {"coordinates":[3.2117750645,50.7485389709],"type":"Point"}
}