{
  "type": "Feature",
  "properties": {
    "addr:full":"Stokkelaar 8 Ind.zone E 17/3 Lokeren Oost-Vlaanderen 9160",
    "addr:housenumber":"8;17 / 3",
    "addr:postcode":"9160",
    "addr:street":"Stokkelaar;E;Lokeren Oost-Vlaanderen",
    "iso:country":"BE",
    "sg:address":"Stokkelaar 8 Ind.zone E 17/3",
    "sg:city":"Lokeren",
    "sg:classifiers":[
        {
            "category":"Utilities",
            "subcategory":"Electric",
            "type":"Services"
        }
    ],
    "sg:phone":"+32 9 353 91 11",
    "sg:postcode":"9160",
    "sg:province":"Oost-Vlaanderen",
    "sg:tags":[
        "electricity",
        "electronic",
        "electrical",
        "equipment"
    ],
    "wof:name":"Rittal Nv",
    "wof:placetype":"venue"
},
  "geometry": {"coordinates":[3.9864850044,51.1047401428],"type":"Point"}
}