{
  "type": "Feature",
  "properties": {
    "iso:country":"BE",
    "sg:address":"Hillestraat 19bb",
    "sg:city":"Maldegem",
    "sg:orig_category":"Dakwerken Loodgieterij, verwarming and sanitaire installaties",
    "sg:phone":"+32 50 71 21 66",
    "sg:postcode":"9991",
    "sg:province":"Oost-Vlaanderen",
    "wof:name":"Marnix De Lille",
    "wof:placetype":"venue"
},
  "geometry": {"coordinates":[3.4907979965,51.2015838623],"type":"Point"}
}