{
  "type": "Feature",
  "properties": {
    "iso:country":"BE",
    "sg:address":"Volhardingstraat 60",
    "sg:city":"Antwerpen",
    "sg:orig_category":"Artistes ind\u00e9pendants",
    "sg:phone":"+32 3 237 65 79",
    "sg:postcode":"2020",
    "sg:province":"Antwerpen",
    "wof:name":"Appel",
    "wof:placetype":"venue"
},
  "geometry": {"coordinates":[4.3915309906,51.1898727417],"type":"Point"}
}