{
  "type": "Feature",
  "properties": {
    "iso:country":"BE",
    "sg:address":"Rue Sainte-aldegonde 28",
    "sg:city":"Tournai",
    "sg:orig_category":"Assurances. Bureaux de poste",
    "sg:phone":"+32 69 22 55 00",
    "sg:postcode":"7540",
    "sg:province":"Hainaut",
    "wof:name":"La Poste",
    "wof:placetype":"venue"
},
  "geometry": {"coordinates":[3.3826489449,50.6289215088],"type":"Point"}
}