{
  "type": "Feature",
  "properties": {
    "iso:country":"BE",
    "sg:address":"Sint-lenaartseweg 3-5",
    "sg:city":"Hoogstraten",
    "sg:classifiers":[
        {
            "category":"Recreation",
            "subcategory":"Dance Hall",
            "type":"Entertainment"
        }
    ],
    "sg:phone":"+32 3 314 76 61",
    "sg:postcode":"2320",
    "sg:province":"Antwerpen",
    "sg:tags":[
        "discotheque"
    ],
    "wof:name":"High Street Nv",
    "wof:placetype":"venue"
},
  "geometry": {"coordinates":[4.7242379189,51.3828392029],"type":"Point"}
}