{
  "type": "Feature",
  "properties": {
    "addr:full":"Vondelstraat 13 Harelbeke West-Vlaanderen 8531",
    "addr:housenumber":"13",
    "addr:postcode":"8531",
    "addr:street":"Vondelstraat",
    "iso:country":"BE",
    "sg:address":"Vondelstraat 13",
    "sg:city":"Harelbeke",
    "sg:orig_category":"Artistes ind\u00e9pendants",
    "sg:phone":"+32 56 70 19 39",
    "sg:postcode":"8531",
    "sg:province":"West-Vlaanderen",
    "wof:name":"Ronald Thuylie",
    "wof:placetype":"venue"
},
  "geometry": {"coordinates":[3.3006379604,50.8710861206],"type":"Point"}
}