{
  "type": "Feature",
  "properties": {
    "addr:full":"Rue Francois Lef\u00e8bvre 212 Li\u00e8ge 1 (rocourt) Li\u00e8ge 4000",
    "addr:housenumber":"212;1",
    "addr:postcode":"4000",
    "addr:street":"Rue Francois Lefe\u0300Bvre",
    "iso:country":"BE",
    "sg:address":"Rue Francois Lef\u00e8bvre 212",
    "sg:city":"Li\u00e8ge 1 (rocourt)",
    "sg:classifiers":[
        {
            "category":"Shopping",
            "subcategory":"Florist",
            "type":"Retail Goods"
        }
    ],
    "sg:phone":"+32 4 263 95 06",
    "sg:postcode":"4000",
    "sg:province":"Li\u00e8ge",
    "wof:name":"Rose Fran\u00e7aise (la)",
    "wof:placetype":"venue"
},
  "geometry": {"coordinates":[5.5474748611,50.6791534424],"type":"Point"}
}