{
  "type": "Feature",
  "properties": {
    "iso:country":"BE",
    "sg:address":"Vichteplaats 1",
    "sg:city":"Anzegem (vichte)",
    "sg:classifiers":[
        {
            "category":"Shopping",
            "subcategory":"Optician",
            "type":"Retail Goods"
        }
    ],
    "sg:phone":"+32 56 77 63 31",
    "sg:postcode":"8570",
    "sg:province":"West-Vlaanderen",
    "sg:tags":[
        "-"
    ],
    "wof:name":"Optiek Dauw",
    "wof:placetype":"venue"
},
  "geometry": {"coordinates":[3.4031250477,50.8374938965],"type":"Point"}
}