{
  "type": "Feature",
  "properties": {
    "iso:country":"BE",
    "sg:address":"J. Claesstraat 13bcla",
    "sg:city":"Sint-truiden",
    "sg:orig_category":"Woningbouw",
    "sg:phone":"+32 11 69 57 54",
    "sg:postcode":"3800",
    "sg:province":"Limburg",
    "wof:name":"J P Willems",
    "wof:placetype":"venue"
},
  "geometry": {"coordinates":[5.2533931732,50.8364562988],"type":"Point"}
}