{
  "type": "Feature",
  "properties": {
    "addr:full":"Rue Surlet 44 Charleroi (jumet) Hainaut 6040",
    "addr:housenumber":"44",
    "addr:postcode":"6040",
    "addr:street":"Rue Surlet",
    "iso:country":"BE",
    "sg:address":"Rue Surlet 44",
    "sg:city":"Charleroi (jumet)",
    "sg:classifiers":[
        {
            "category":"Personal",
            "subcategory":"Nail Salon",
            "type":"Services"
        }
    ],
    "sg:phone":"+32 71 34 31 11",
    "sg:postcode":"6040",
    "sg:province":"Hainaut",
    "sg:tags":[
        "pedicure"
    ],
    "wof:name":"Gillis P",
    "wof:placetype":"venue"
},
  "geometry": {"coordinates":[4.4245052338,50.4448814392],"type":"Point"}
}