{
  "type": "Feature",
  "properties": {
    "addr:full":"Rector De Ramstraat 39a Nijlen Antwerpen 2560",
    "addr:housenumber":"39a",
    "addr:postcode":"2560",
    "addr:street":"Rector De Ramstraat",
    "iso:country":"BE",
    "sg:address":"Rector De Ramstraat 39a",
    "sg:city":"Nijlen",
    "sg:classifiers":[
        {
            "category":"Professional",
            "subcategory":"Computer Services",
            "type":"Services"
        }
    ],
    "sg:phone":"+32 3 646 90 94",
    "sg:postcode":"2560",
    "sg:province":"Antwerpen",
    "sg:tags":[
        "network"
    ],
    "wof:name":"Netconfig Bvba",
    "wof:placetype":"venue"
},
  "geometry": {"coordinates":[4.6768698692,51.158531189],"type":"Point"}
}