{
  "type": "Feature",
  "properties": {
    "addr:full":"Chauss\u00e9e De Louvain 473-7 Wavre Brabant Wallon 1300",
    "addr:housenumber":"1300",
    "addr:postcode":"473-7",
    "addr:street":"Chausse\u0301E De Louvain",
    "iso:country":"BE",
    "sg:address":"Chauss\u00e9e De Louvain 473-7",
    "sg:city":"Wavre",
    "sg:classifiers":[
        {
            "category":"Building & Trades",
            "subcategory":"Landscaping Services",
            "type":"Services"
        }
    ],
    "sg:phone":"+32 10 22 41 03",
    "sg:postcode":"1300",
    "sg:province":"Brabant Wallon",
    "sg:tags":[
        "access",
        "pond",
        "laying-out",
        "-"
    ],
    "wof:name":"Histoires D'eaux Sprl",
    "wof:placetype":"venue"
},
  "geometry": {"coordinates":[4.6294231415,50.7230033875],"type":"Point"}
}