{
  "type": "Feature",
  "properties": {
    "iso:country":"BE",
    "sg:address":"Stationstraat 153/3",
    "sg:city":"Gavere",
    "sg:orig_category":"Sportclubs",
    "sg:phone":"+32 9 384 98 30",
    "sg:postcode":"9890",
    "sg:province":"Oost-Vlaanderen",
    "wof:name":"De Zingemse Cyclo-crossvrienden",
    "wof:placetype":"venue"
},
  "geometry": {"coordinates":[3.6481730938,50.9292221069],"type":"Point"}
}