{
  "type": "Feature",
  "properties": {
    "addr:full":"Dr\u00e8ve De Nivelles 2 Bruxelles (woluwe-saint-pierre) Bruxelles-Capitale 1150",
    "addr:housenumber":"2",
    "addr:postcode":"1150",
    "addr:street":"Dre\u0300Ve De Nivelles",
    "iso:country":"BE",
    "sg:address":"Dr\u00e8ve De Nivelles 2",
    "sg:city":"Bruxelles (woluwe-saint-pierre)",
    "sg:classifiers":[
        {
            "category":"Professional",
            "subcategory":"Testing Lab",
            "type":"Services"
        }
    ],
    "sg:phone":"+32 2 762 53 39",
    "sg:postcode":"1150",
    "sg:province":"Bruxelles-Capitale",
    "sg:tags":[
        "chemist"
    ],
    "wof:name":"Lef\u00e9bure M-a",
    "wof:placetype":"venue"
},
  "geometry": {"coordinates":[4.4157118797,50.8303108215],"type":"Point"}
}