{
  "type": "Feature",
  "properties": {
    "iso:country":"BE",
    "sg:address":"Oude Leuvensestraat 24",
    "sg:city":"Tienen",
    "sg:classifiers":[
        {
            "category":"Personal",
            "subcategory":"Beauty Salon",
            "type":"Services"
        }
    ],
    "sg:phone":"+32 16 81 11 89",
    "sg:postcode":"3300",
    "sg:province":"Vlaams-Brabant",
    "sg:tags":[
        "de",
        "coiffure"
    ],
    "wof:name":"Victor Kinnaert",
    "wof:placetype":"venue"
},
  "geometry": {"coordinates":[4.9309902191,50.8102607727],"type":"Point"}
}