{
  "type": "Feature",
  "properties": {
    "addr:full":"Rue Saint-jean 29 Chi\u00e8vres Hainaut 7950",
    "addr:housenumber":"29",
    "addr:postcode":"7950",
    "addr:street":"Rue Saint-Jean;Hainaut",
    "iso:country":"BE",
    "sg:address":"Rue Saint-jean 29",
    "sg:city":"Chi\u00e8vres",
    "sg:classifiers":[
        {
            "category":"Professional",
            "subcategory":"Testing Lab",
            "type":"Services"
        }
    ],
    "sg:phone":"+32 68 66 50 77",
    "sg:postcode":"7950",
    "sg:province":"Hainaut",
    "sg:tags":[
        "chemist"
    ],
    "wof:name":"Marchal S",
    "wof:placetype":"venue"
},
  "geometry": {"coordinates":[3.8066809177,50.5863952637],"type":"Point"}
}