{
  "type": "Feature",
  "properties": {
    "addr:full":"Avenue Eudore Pirmez 35 Etterbeek/etterbeek Bruxelles-Capitale 1040",
    "addr:housenumber":"35",
    "addr:postcode":"1040",
    "addr:street":"Avenue Eudore Pirmez",
    "iso:country":"BE",
    "sg:address":"Avenue Eudore Pirmez 35",
    "sg:city":"Etterbeek/etterbeek",
    "sg:orig_category":"Fleurs and plantes",
    "sg:phone":"+32 2 648 66 11",
    "sg:postcode":"1040",
    "sg:province":"Bruxelles-Capitale",
    "wof:name":"Fondvert",
    "wof:placetype":"venue"
},
  "geometry": {"coordinates":[4.3882908821,50.8303413391],"type":"Point"}
}