{
  "type": "Feature",
  "properties": {
    "iso:country":"BE",
    "sg:address":"Rue Du Tr\u00f4ne 111",
    "sg:city":"Bruxelles (ixelles)",
    "sg:orig_category":"Non-Classified Establishments",
    "sg:phone":"+32 2 513 20 55",
    "sg:postcode":"1050",
    "sg:province":"Bruxelles-Capitale",
    "wof:name":"Centre P M S De La Communaut\u00e9 Fran\u00e7aise",
    "wof:placetype":"venue"
},
  "geometry": {"coordinates":[4.3698339462,50.836971283],"type":"Point"}
}