{
  "type": "Feature",
  "properties": {
    "iso:country":"BE",
    "sg:address":"Avenue Marius Meur\u00c9e 50",
    "sg:city":"Charleroi",
    "sg:orig_category":"Slagers",
    "sg:phone":"+32 71 36 07 20",
    "sg:postcode":"6001",
    "sg:province":"Hainaut",
    "wof:name":"Boucherie De L\u00b4avenue",
    "wof:placetype":"venue"
},
  "geometry": {"coordinates":[4.4465851784,50.4013710022],"type":"Point"}
}