{
  "type": "Feature",
  "properties": {
    "addr:full":"Rue Adolphe Willemyns 268 Bruxelles (anderlecht) Bruxelles-Capitale 1070",
    "addr:housenumber":"268",
    "addr:postcode":"1070",
    "addr:street":"Rue Adolphe Willemyns",
    "iso:country":"BE",
    "sg:address":"Rue Adolphe Willemyns 268",
    "sg:city":"Bruxelles (anderlecht)",
    "sg:classifiers":[
        {
            "category":"Health Services",
            "subcategory":"Health Practitioner",
            "type":"Services"
        }
    ],
    "sg:phone":"+32 2 520 89 73",
    "sg:postcode":"1070",
    "sg:province":"Bruxelles-Capitale",
    "sg:tags":[
        "physiotherapist"
    ],
    "wof:name":"Vetsuypens A",
    "wof:placetype":"venue"
},
  "geometry": {"coordinates":[4.2910151482,50.8395652771],"type":"Point"}
}