{
  "type": "Feature",
  "properties": {
    "iso:country":"BE",
    "sg:address":"Meenseweg 254",
    "sg:city":"Ieper",
    "sg:classifiers":[
        {
            "category":"Conference Center",
            "type":"Public Place"
        }
    ],
    "sg:phone":"+32 57 20 23 81",
    "sg:postcode":"8900",
    "sg:province":"West-Vlaanderen",
    "sg:tags":[
        "terrain",
        "vehicle"
    ],
    "wof:name":"Vandenbroucke D",
    "wof:placetype":"venue"
},
  "geometry": {"coordinates":[2.9105980396,50.8494682312],"type":"Point"}
}