{
  "type": "Feature",
  "properties": {
    "addr:full":"Dronckaertstraat 82 Menen West-Vlaanderen 8930",
    "addr:housenumber":"82",
    "addr:postcode":"8930",
    "addr:street":"Dronckaertstraat",
    "iso:country":"BE",
    "sg:address":"Dronckaertstraat 82",
    "sg:city":"Menen",
    "sg:orig_category":"Epiceries",
    "sg:phone":"+32 56 40 34 81",
    "sg:postcode":"8930",
    "sg:province":"West-Vlaanderen",
    "wof:name":"Bij Marleen",
    "wof:placetype":"venue"
},
  "geometry": {"coordinates":[3.1696391106,50.7719764709],"type":"Point"}
}