{
  "type": "Feature",
  "properties": {
    "iso:country":"BE",
    "sg:address":"Anspachlaan 159",
    "sg:city":"Brussel/bruxelles",
    "sg:classifiers":[
        {
            "category":"Travel",
            "subcategory":"Hotels & Motels",
            "type":"Entertainment"
        }
    ],
    "sg:phone":"+32 2 512 81 00",
    "sg:postcode":"1000",
    "sg:province":"Bruxelles-Capitale",
    "wof:name":"Royal Embassy",
    "wof:placetype":"venue"
},
  "geometry": {"coordinates":[4.3470511436,50.8459854126],"type":"Point"}
}