{
  "type": "Feature",
  "properties": {
    "iso:country":"BE",
    "sg:address":"Sareptastraat 2",
    "sg:city":"Damme",
    "sg:orig_category":"Eleveurs and marchands de porcs. Eleveurs de bovins",
    "sg:phone":"+32 50 50 03 96",
    "sg:postcode":"8340",
    "sg:province":"West-Vlaanderen",
    "wof:name":"Walter Mouton",
    "wof:placetype":"venue"
},
  "geometry": {"coordinates":[3.3584160805,51.2214546204],"type":"Point"}
}