{
  "type": "Feature",
  "properties": {
    "iso:country":"BE",
    "sg:address":"Molenlei 74",
    "sg:city":"Berlaar",
    "sg:classifiers":[
        {
            "category":"Health Services",
            "subcategory":"Health Practitioner",
            "type":"Services"
        }
    ],
    "sg:phone":"+32 3 482 38 31",
    "sg:postcode":"2590",
    "sg:province":"Antwerpen",
    "sg:tags":[
        "physiotherapist"
    ],
    "wof:name":"Van Beirs C",
    "wof:placetype":"venue"
},
  "geometry": {"coordinates":[4.6393728256,51.1178855896],"type":"Point"}
}