{
  "type": "Feature",
  "properties": {
    "iso:country":"BE",
    "sg:address":"Rue De Bouvy 240",
    "sg:city":"La Louvi\u00e8re",
    "sg:classifiers":[
        {
            "category":"Food & Beverages",
            "subcategory":"Groceries & Convenience Stores",
            "type":"Retail Goods"
        }
    ],
    "sg:phone":"+32 64 28 21 97",
    "sg:postcode":"7100",
    "sg:province":"Hainaut",
    "sg:tags":[
        "grocer"
    ],
    "wof:name":"Chez Pino",
    "wof:placetype":"venue"
},
  "geometry": {"coordinates":[4.1803231239,50.4677467346],"type":"Point"}
}