{
  "type": "Feature",
  "properties": {
    "addr:full":"Oude Luikerbaan 83 Hasselt Limburg 3500",
    "addr:housenumber":"83",
    "addr:postcode":"3500",
    "addr:street":"Oude Luikerbaan",
    "iso:country":"BE",
    "sg:address":"Oude Luikerbaan 83",
    "sg:city":"Hasselt",
    "sg:orig_category":"Enseignement maternel and primaire",
    "sg:phone":"+32 11 28 19 11",
    "sg:postcode":"3500",
    "sg:province":"Limburg",
    "wof:name":"Vrije Kleuterschool",
    "wof:placetype":"venue"
},
  "geometry": {"coordinates":[5.3389368057,50.9240875244],"type":"Point"}
}