{
  "type": "Feature",
  "properties": {
    "addr:full":"Gauwerstraat 115 Kortessem Limburg 3721",
    "addr:housenumber":"115",
    "addr:postcode":"3721",
    "addr:street":"Gauwerstraat;Limburg",
    "iso:country":"BE",
    "sg:address":"Gauwerstraat 115",
    "sg:city":"Kortessem",
    "sg:orig_category":"Herstellingen and onderhoud van auto's",
    "sg:phone":"+32 11 37 52 21",
    "sg:postcode":"3721",
    "sg:province":"Limburg",
    "wof:name":"Garage Rudi Verjans",
    "wof:placetype":"venue"
},
  "geometry": {"coordinates":[5.4121408463,50.87266922],"type":"Point"}
}