{
  "type": "Feature",
  "properties": {
    "addr:full":"Middelstraat 20 Koekelare West-Vlaanderen 8680",
    "addr:housenumber":"20",
    "addr:postcode":"8680",
    "addr:street":"Middelstraat",
    "iso:country":"BE",
    "sg:address":"Middelstraat 20",
    "sg:city":"Koekelare",
    "sg:orig_category":"Eleveurs and marchands de porcs",
    "sg:phone":"+32 51 58 84 91",
    "sg:postcode":"8680",
    "sg:province":"West-Vlaanderen",
    "wof:name":"Koen Gadeyne",
    "wof:placetype":"venue"
},
  "geometry": {"coordinates":[2.9707479477,51.0520782471],"type":"Point"}
}