{
  "type": "Feature",
  "properties": {
    "addr:full":"Gagelweg 3 Overpelt Limburg 3900",
    "addr:housenumber":"3",
    "addr:postcode":"3900",
    "addr:street":"Gagelweg",
    "iso:country":"BE",
    "sg:address":"Gagelweg 3",
    "sg:city":"Overpelt",
    "sg:classifiers":[
        {
            "category":"Fast Food",
            "type":"Food & Drink"
        }
    ],
    "sg:phone":"+32 11 66 18 86",
    "sg:postcode":"3900",
    "sg:province":"Limburg",
    "sg:tags":[
        "huis",
        "aan",
        "levering",
        "meeneem",
        "restaurant"
    ],
    "wof:name":"Den Halt",
    "wof:placetype":"venue"
},
  "geometry": {"coordinates":[5.3873839378,51.212436676],"type":"Point"}
}