{
  "type": "Feature",
  "properties": {
    "iso:country":"BE",
    "sg:address":"Zeveneken Dorp 43",
    "sg:city":"Lochristi (zeveneken)",
    "sg:classifiers":[
        {
            "category":"Banks & Credit Unions",
            "subcategory":"Investment Brokerage",
            "type":"Services"
        }
    ],
    "sg:phone":"+32 9 355 57 42",
    "sg:postcode":"9080",
    "sg:province":"Oost-Vlaanderen",
    "sg:tags":[
        "printing",
        "-"
    ],
    "wof:name":"Buyle H",
    "wof:placetype":"venue"
},
  "geometry": {"coordinates":[3.8286919594,51.1006011963],"type":"Point"}
}