{
  "type": "Feature",
  "properties": {
    "iso:country":"BE",
    "sg:address":"Rue Beeckman 106d",
    "sg:city":"Ukkel/uccle",
    "sg:orig_category":"Schoonheidssalons",
    "sg:phone":"+32 2 376 12 59",
    "sg:postcode":"1180",
    "sg:province":"Bruxelles-Capitale",
    "wof:name":"Esprit De Beaut\u00c9",
    "wof:placetype":"venue"
},
  "geometry": {"coordinates":[4.3347740173,50.8033752441],"type":"Point"}
}