{
  "type": "Feature",
  "properties": {
    "addr:full":"Prosper De Troyerstraat 34 Mechelen Antwerpen 2800",
    "addr:housenumber":"34",
    "addr:postcode":"2800",
    "addr:street":"Prosper De Troyerstraat",
    "iso:country":"BE",
    "sg:address":"Prosper De Troyerstraat 34",
    "sg:city":"Mechelen",
    "sg:orig_category":"DIVERSE RECREATIEVE ACTIVITEITEN",
    "sg:phone":"+32 15 26 02 96",
    "sg:postcode":"2800",
    "sg:province":"Antwerpen",
    "wof:name":"Bridge Club Keerbergen",
    "wof:placetype":"venue"
},
  "geometry": {"coordinates":[4.4643101692,51.0331993103],"type":"Point"}
}