{
  "type": "Feature",
  "properties": {
    "iso:country":"BE",
    "sg:address":"Chauss\u00e9e D'enghien 308",
    "sg:city":"Soignies",
    "sg:orig_category":"Newspapers, magazines, periodicals - Distribution",
    "sg:phone":"+32 67 33 47 77",
    "sg:postcode":"7060",
    "sg:province":"Hainaut",
    "wof:name":"Son\u00e9giens",
    "wof:placetype":"venue"
},
  "geometry": {"coordinates":[4.0579500198,50.6058540344],"type":"Point"}
}