{
  "type": "Feature",
  "properties": {
    "addr:full":"Rue Petite Guirlande 25 Mons Hainaut 7000",
    "addr:housenumber":"25",
    "addr:postcode":"7000",
    "addr:street":"Rue Petite Guirlande;Hainaut",
    "iso:country":"BE",
    "sg:address":"Rue Petite Guirlande 25",
    "sg:city":"Mons",
    "sg:classifiers":[
        {
            "category":"Shopping",
            "subcategory":"Clothing, Apparel, & Fashions",
            "type":"Retail Goods"
        }
    ],
    "sg:phone":"+32 65 33 53 07",
    "sg:postcode":"7000",
    "sg:province":"Hainaut",
    "sg:tags":[
        "v\u00eatements",
        "pour",
        "dame"
    ],
    "wof:name":"Maison Garina",
    "wof:placetype":"venue"
},
  "geometry": {"coordinates":[3.9451029301,50.4514122009],"type":"Point"}
}