{
  "type": "Feature",
  "properties": {
    "iso:country":"BE",
    "sg:address":"Paddenbroekstraat 9",
    "sg:city":"Gooik",
    "sg:classifiers":[
        {
            "category":"Restaurant",
            "type":"Food & Drink"
        }
    ],
    "sg:phone":"+32 54 56 88 62",
    "sg:postcode":"1755",
    "sg:province":"Vlaams-Brabant",
    "wof:name":"\u00b4t Zwart Schaap",
    "wof:placetype":"venue"
},
  "geometry": {"coordinates":[4.1006441116,50.7860679626],"type":"Point"}
}