{
  "type": "Feature",
  "properties": {
    "iso:country":"BE",
    "sg:address":"Barones Ludwina De Borrekensla 90",
    "sg:city":"Aartselaar",
    "sg:classifiers":[
        {
            "category":"Museum",
            "subcategory":"Aquarium",
            "type":"Entertainment"
        }
    ],
    "sg:phone":"+32 3 870 71 81",
    "sg:postcode":"2630",
    "sg:province":"Antwerpen",
    "sg:tags":[
        "tropical",
        "ornamental",
        "fish"
    ],
    "wof:name":"Aquaria Antwerp B.v.b.a.",
    "wof:placetype":"venue"
},
  "geometry": {"coordinates":[4.38185215,51.141708374],"type":"Point"}
}