{
  "type": "Feature",
  "properties": {
    "iso:country":"BE",
    "sg:address":"Rue Des H\u00eatres 95",
    "sg:city":"Bastogne",
    "sg:classifiers":[
        {
            "category":"Health Services",
            "subcategory":"Nursing And Care Facility",
            "type":"Services"
        }
    ],
    "sg:phone":"+32 61 21 32 90",
    "sg:postcode":"6600",
    "sg:province":"Luxembourg",
    "sg:tags":[
        "home"
    ],
    "wof:name":"Goffin-jacques M-a",
    "wof:placetype":"venue"
},
  "geometry": {"coordinates":[5.7312102318,50.0042991638],"type":"Point"}
}