{
  "type": "Feature",
  "properties": {
    "addr:full":"Heesveld 17 Herentals Antwerpen 2200",
    "addr:housenumber":"17",
    "addr:postcode":"2200",
    "addr:street":"Heesveld",
    "iso:country":"BE",
    "sg:address":"Heesveld 17",
    "sg:city":"Herentals",
    "sg:classifiers":[
        {
            "category":"Cafe",
            "type":"Food & Drink"
        }
    ],
    "sg:phone":"+32 14 21 93 69",
    "sg:postcode":"2200",
    "sg:province":"Antwerpen",
    "sg:tags":[
        "caf\u00e9s"
    ],
    "wof:name":"Sportkring Sefa Herentals",
    "wof:placetype":"venue"
},
  "geometry": {"coordinates":[4.8353409767,51.1628570557],"type":"Point"}
}