{
  "type": "Feature",
  "properties": {
    "addr:full":"H. Consciencestraat 14 Zele Oost-Vlaanderen 9240",
    "addr:housenumber":"14",
    "addr:postcode":"9240",
    "addr:street":"Consciencestraat",
    "iso:country":"BE",
    "sg:address":"H. Consciencestraat 14",
    "sg:city":"Zele",
    "sg:orig_category":"Agences d'exp\u00e9dition",
    "sg:phone":"+32 52 45 10 68",
    "sg:postcode":"9240",
    "sg:province":"Oost-Vlaanderen",
    "wof:name":"M.t.c.",
    "wof:placetype":"venue"
},
  "geometry": {"coordinates":[4.0344510078,51.0609550476],"type":"Point"}
}