{
  "type": "Feature",
  "properties": {
    "addr:full":"Weggevoerdenstraat 80 Ninove Oost-Vlaanderen 9400",
    "addr:housenumber":"80",
    "addr:postcode":"9400",
    "addr:street":"Weggevoerdenstraat",
    "iso:country":"BE",
    "sg:address":"Weggevoerdenstraat 80",
    "sg:city":"Ninove",
    "sg:orig_category":"Paramedische behandelingen",
    "sg:phone":"+32 54 34 23 43",
    "sg:postcode":"9400",
    "sg:province":"Oost-Vlaanderen",
    "wof:name":"D. Van Bellinghen",
    "wof:placetype":"venue"
},
  "geometry": {"coordinates":[4.0219497681,50.8399734497],"type":"Point"}
}