{
  "type": "Feature",
  "properties": {
    "iso:country":"BE",
    "sg:address":"Rue D'hymi\u00e9e 28",
    "sg:city":"Gerpinnes",
    "sg:classifiers":[
        {
            "category":"Health Services",
            "subcategory":"Health Practitioner",
            "type":"Services"
        }
    ],
    "sg:phone":"+32 71 50 52 44",
    "sg:postcode":"6280",
    "sg:province":"Hainaut",
    "sg:tags":[
        "therapist",
        "speech"
    ],
    "wof:name":"Malfliet T",
    "wof:placetype":"venue"
},
  "geometry": {"coordinates":[4.5381331444,50.3272819519],"type":"Point"}
}