{
  "type": "Feature",
  "properties": {
    "iso:country":"BE",
    "sg:address":"Mergelputstraat 132",
    "sg:city":"Vilvoorde",
    "sg:orig_category":"Charpentes and couvertures",
    "sg:phone":"+32 2 253 17 66",
    "sg:postcode":"1800",
    "sg:province":"Vlaams-Brabant",
    "wof:name":"Cover Services",
    "wof:placetype":"venue"
},
  "geometry": {"coordinates":[4.4100427628,50.9262657166],"type":"Point"}
}