{
  "type": "Feature",
  "properties": {
    "addr:full":"Bo\u00eete Postale 213 Waterloo Brabant Wallon 1410",
    "addr:housenumber":"213",
    "addr:postcode":"1410",
    "addr:street":"Waterloo Brabant",
    "iso:country":"BE",
    "sg:address":"Bo\u00eete Postale 213",
    "sg:city":"Waterloo",
    "sg:classifiers":[
        {
            "category":"Health Services",
            "subcategory":"Health Practitioner",
            "type":"Services"
        }
    ],
    "sg:phone":"+32 2 353 10 46",
    "sg:postcode":"1410",
    "sg:province":"Brabant Wallon",
    "sg:tags":[
        "dietitian"
    ],
    "wof:name":"Association Belge Des Dieteticiens Et Des Licencies En Nutrition Humaine De Langue Francaise",
    "wof:placetype":"venue"
},
  "geometry": {"coordinates":[4.3980250359,50.7174263],"type":"Point"}
}