{
  "type": "Feature",
  "properties": {
    "addr:full":"Meistraat 102ba Dessel Antwerpen 2480",
    "addr:postcode":"2480",
    "addr:street":"Meistraat 102Ba",
    "iso:country":"BE",
    "sg:address":"Meistraat 102ba",
    "sg:city":"Dessel",
    "sg:orig_category":"Dameskledingzaken",
    "sg:phone":"+32 14 37 78 98",
    "sg:postcode":"2480",
    "sg:province":"Antwerpen",
    "wof:name":"Mode Nicole",
    "wof:placetype":"venue"
},
  "geometry": {"coordinates":[5.1602301598,51.2412605286],"type":"Point"}
}