{
  "type": "Feature",
  "properties": {
    "addr:full":"A. De Cockstraat 1 Denderleeuw Oost-Vlaanderen 9470",
    "addr:housenumber":"1",
    "addr:postcode":"9470",
    "addr:street":"A. De Cockstraat",
    "iso:country":"BE",
    "sg:address":"A. De Cockstraat 1",
    "sg:city":"Denderleeuw",
    "sg:classifiers":[
        {
            "category":"Health Services",
            "subcategory":"Nursing And Care Facility",
            "type":"Services"
        }
    ],
    "sg:phone":"+32 53 66 73 91",
    "sg:postcode":"9470",
    "sg:province":"Oost-Vlaanderen",
    "sg:tags":[
        "public"
    ],
    "wof:name":"Gemeentebestuur",
    "wof:placetype":"venue"
},
  "geometry": {"coordinates":[4.0811910629,50.8833312988],"type":"Point"}
}