{
  "type": "Feature",
  "properties": {
    "addr:full":"Steenstraat 20 Vilvoorde Vlaams-Brabant 1800",
    "addr:housenumber":"20",
    "addr:postcode":"1800",
    "addr:street":"Steenstraat",
    "iso:country":"BE",
    "sg:address":"Steenstraat 20",
    "sg:city":"Vilvoorde",
    "sg:orig_category":"Produits chimiques Gr",
    "sg:phone":"+32 800 16 851",
    "sg:postcode":"1800",
    "sg:province":"Vlaams-Brabant",
    "wof:name":"Eastman Chemical",
    "wof:placetype":"venue"
},
  "geometry": {"coordinates":[4.3804030418,50.9064025879],"type":"Point"}
}