{
  "type": "Feature",
  "properties": {
    "addr:full":"Rue Saint-jacques 22 Namur Namur 5000",
    "addr:housenumber":"22",
    "addr:postcode":"5000",
    "addr:street":"Rue Saint-Jacques",
    "iso:country":"BE",
    "sg:address":"Rue Saint-jacques 22",
    "sg:city":"Namur",
    "sg:classifiers":[
        {
            "category":"Shopping",
            "subcategory":"Clothing, Apparel, & Fashions",
            "type":"Retail Goods"
        }
    ],
    "sg:phone":"+32 81 22 94 28",
    "sg:postcode":"5000",
    "sg:province":"Namur",
    "sg:tags":[
        "v\u00eatements",
        "pour",
        "dame"
    ],
    "wof:name":"Maison Maxmara",
    "wof:placetype":"venue"
},
  "geometry": {"coordinates":[4.8643112183,50.4651679993],"type":"Point"}
}