{
  "type": "Feature",
  "properties": {
    "addr:full":"Guchtstraat 60 Lede Oost-Vlaanderen 9340",
    "addr:housenumber":"60",
    "addr:postcode":"9340",
    "addr:street":"Guchtstraat",
    "iso:country":"BE",
    "sg:address":"Guchtstraat 60",
    "sg:city":"Lede",
    "sg:orig_category":"Woningbouw",
    "sg:phone":"+32 53 80 11 44",
    "sg:postcode":"9340",
    "sg:province":"Oost-Vlaanderen",
    "wof:name":"Marc Van Boxstael",
    "wof:placetype":"venue"
},
  "geometry": {"coordinates":[3.96510005,50.9690895081],"type":"Point"}
}