{
  "type": "Feature",
  "properties": {
    "iso:country":"BE",
    "sg:address":"Opitterkiezel 116",
    "sg:city":"Bree",
    "sg:classifiers":[
        {
            "category":"Banks & Credit Unions",
            "subcategory":"Investment Brokerage",
            "type":"Services"
        }
    ],
    "sg:phone":"+32 89 46 11 12",
    "sg:postcode":"3960",
    "sg:province":"Limburg",
    "sg:tags":[
        "fence"
    ],
    "wof:name":"Bekaert-shop Houben",
    "wof:placetype":"venue"
},
  "geometry": {"coordinates":[5.6164898872,51.1324691772],"type":"Point"}
}