{
  "type": "Feature",
  "properties": {
    "addr:full":"Begoniastraat 32 Nazareth Oost-Vlaanderen 9810",
    "addr:housenumber":"32",
    "addr:postcode":"9810",
    "addr:street":"Begoniastraat",
    "iso:country":"BE",
    "sg:address":"Begoniastraat 32",
    "sg:city":"Nazareth",
    "sg:orig_category":"V\u00e9hicules automobiles",
    "sg:phone":"+32 9 385 59 17",
    "sg:postcode":"9810",
    "sg:province":"Oost-Vlaanderen",
    "wof:name":"Appelmans J.",
    "wof:placetype":"venue"
},
  "geometry": {"coordinates":[3.6580600739,50.9781837463],"type":"Point"}
}