{
  "type": "Feature",
  "properties": {
    "iso:country":"BE",
    "sg:address":"Mezenstraat 30",
    "sg:city":"Bertem",
    "sg:orig_category":"M\u00e9decins and sp\u00e9cialistes",
    "sg:phone":"+32 2 767 53 08",
    "sg:postcode":"3061",
    "sg:province":"Vlaams-Brabant",
    "wof:name":"Myriam Surdiacourt",
    "wof:placetype":"venue"
},
  "geometry": {"coordinates":[4.5843710899,50.8480186462],"type":"Point"}
}