{
  "type": "Feature",
  "properties": {
    "addr:full":"Vrouwebroersstraat 2 Gent Oost-Vlaanderen 9000",
    "addr:housenumber":"2",
    "addr:postcode":"9000",
    "addr:street":"Vrouwebroersstraat;Oost-Vlaanderen",
    "iso:country":"BE",
    "sg:address":"Vrouwebroersstraat 2",
    "sg:city":"Gent",
    "sg:classifiers":[
        {
            "category":"Restaurant",
            "type":"Food & Drink"
        }
    ],
    "sg:phone":"+32 9 224 08 52",
    "sg:postcode":"9000",
    "sg:province":"Oost-Vlaanderen",
    "wof:name":"De Blauwe Zalm",
    "wof:placetype":"venue"
},
  "geometry": {"coordinates":[3.7224149704,51.0583877563],"type":"Point"}
}