{
  "type": "Feature",
  "properties": {
    "addr:full":"Rue Des Cultivateurs 82 Bruxelles (etterbeek) Bruxelles-Capitale 1040",
    "addr:housenumber":"82",
    "addr:postcode":"1040",
    "addr:street":"Rue Des Cultivateurs",
    "iso:country":"BE",
    "sg:address":"Rue Des Cultivateurs 82",
    "sg:city":"Bruxelles (etterbeek)",
    "sg:classifiers":[
        {
            "category":"Transit Center",
            "subcategory":"Freight",
            "type":"Transportation"
        }
    ],
    "sg:phone":"+32 2 733 47 10",
    "sg:postcode":"1040",
    "sg:province":"Bruxelles-Capitale",
    "sg:tags":[
        "import",
        "export",
        "-"
    ],
    "wof:name":"Pimilco & Co Sprl",
    "wof:placetype":"venue"
},
  "geometry": {"coordinates":[4.3936901093,50.8307495117],"type":"Point"}
}