{
  "type": "Feature",
  "properties": {
    "addr:full":"Lodewijk Dosfellaan 15 Heusden-zolder (zolder) Limburg 3550",
    "addr:housenumber":"15",
    "addr:postcode":"3550",
    "addr:street":"Lodewijk Dosfellaan",
    "iso:country":"BE",
    "sg:address":"Lodewijk Dosfellaan 15",
    "sg:city":"Heusden-zolder (zolder)",
    "sg:classifiers":[
        {
            "category":"Banks & Credit Unions",
            "subcategory":"Investment Brokerage",
            "type":"Services"
        }
    ],
    "sg:phone":"+32 11 53 75 44",
    "sg:postcode":"3550",
    "sg:province":"Limburg",
    "sg:tags":[
        "fence"
    ],
    "wof:name":"H G W Betonafsluitingen",
    "wof:placetype":"venue"
},
  "geometry": {"coordinates":[5.29373312,51.0163993835],"type":"Point"}
}