{
  "type": "Feature",
  "properties": {
    "addr:full":"Avenue Bel-air 62b11 Ukkel/uccle Bruxelles-Capitale 1180",
    "addr:housenumber":"62b11",
    "addr:postcode":"1180",
    "addr:street":"Avenue Bel-Air;/",
    "iso:country":"BE",
    "sg:address":"Avenue Bel-air 62b11",
    "sg:city":"Ukkel/uccle",
    "sg:orig_category":"Administration d'immeubles",
    "sg:phone":"+32 2 343 36 45",
    "sg:postcode":"1180",
    "sg:province":"Bruxelles-Capitale",
    "wof:name":"La Nationale De Bruxelles",
    "wof:placetype":"venue"
},
  "geometry": {"coordinates":[4.364054203,50.8127593994],"type":"Point"}
}