{
  "type": "Feature",
  "properties": {
    "addr:full":"Roggelaan 81 Kortrijk West-Vlaanderen 8500",
    "addr:housenumber":"81",
    "addr:postcode":"8500",
    "addr:street":"Roggelaan",
    "iso:country":"BE",
    "sg:address":"Roggelaan 81",
    "sg:city":"Kortrijk",
    "sg:classifiers":[
        {
            "category":"Manufacturing",
            "subcategory":"Textiles",
            "type":"Manufacturing & Wholesale Goods"
        }
    ],
    "sg:phone":"+32 56 22 32 33",
    "sg:postcode":"8500",
    "sg:province":"West-Vlaanderen",
    "sg:tags":[
        "technical"
    ],
    "wof:name":"Havatex Bvba",
    "wof:placetype":"venue"
},
  "geometry": {"coordinates":[3.2918510437,50.8124351501],"type":"Point"}
}