{
  "type": "Feature",
  "properties": {
    "iso:country":"BE",
    "sg:address":"Rue De La Victoire 52",
    "sg:city":"Remicourt",
    "sg:orig_category":"Dakwerken Hout and afgeleiden Gh",
    "sg:phone":"+32 19 54 52 60",
    "sg:postcode":"4350",
    "sg:province":"Li\u00e8ge",
    "wof:name":"Hayen J",
    "wof:placetype":"venue"
},
  "geometry": {"coordinates":[5.3342552185,50.6864852905],"type":"Point"}
}