{
  "type": "Feature",
  "properties": {
    "iso:country":"BE",
    "sg:address":"Damastweversstraat 3",
    "sg:city":"Kortrijk",
    "sg:classifiers":[
        {
            "category":"Building & Trades",
            "subcategory":"Cleaning & Sanitation",
            "type":"Services"
        }
    ],
    "sg:phone":"+32 56 23 70 31",
    "sg:postcode":"8500",
    "sg:province":"West-Vlaanderen",
    "sg:tags":[
        "janitor"
    ],
    "wof:name":"Cleon",
    "wof:placetype":"venue"
},
  "geometry": {"coordinates":[3.2825689316,50.8321037292],"type":"Point"}
}