{
  "type": "Feature",
  "properties": {
    "addr:full":"Ninoofsesteenweg 89 Halle Vlaams-Brabant 1500",
    "addr:housenumber":"89",
    "addr:postcode":"1500",
    "addr:street":"Ninoofsesteenweg",
    "iso:country":"BE",
    "sg:address":"Ninoofsesteenweg 89",
    "sg:city":"Halle",
    "sg:orig_category":"M\u00e9decins and sp\u00e9cialistes",
    "sg:phone":"+32 2 361 09 77",
    "sg:postcode":"1500",
    "sg:province":"Vlaams-Brabant",
    "wof:name":"Armelle Peeters",
    "wof:placetype":"venue"
},
  "geometry": {"coordinates":[4.2326169014,50.7384376526],"type":"Point"}
}