{
  "type": "Feature",
  "properties": {
    "iso:country":"BE",
    "sg:address":"Halewijnlaan 20",
    "sg:city":"Bertem",
    "sg:orig_category":"Assistances juridiques. Conseillers fiscaux. Experts-comptables. Comptables",
    "sg:phone":"+32 16 49 04 50",
    "sg:postcode":"3060",
    "sg:province":"Vlaams-Brabant",
    "wof:name":"Bureau Acfin",
    "wof:placetype":"venue"
},
  "geometry": {"coordinates":[4.6245741844,50.8602523804],"type":"Point"}
}