{
  "type": "Feature",
  "properties": {
    "addr:full":"Rue Des Deux Puissances 69 Sambreville (velaine-sur-sambre) Namur 5060",
    "addr:housenumber":"69",
    "addr:postcode":"5060",
    "addr:street":"Rue Des Deux Puissances",
    "iso:country":"BE",
    "sg:address":"Rue Des Deux Puissances 69",
    "sg:city":"Sambreville (velaine-sur-sambre)",
    "sg:classifiers":[
        {
            "category":"Food & Beverages",
            "subcategory":"Chocolate",
            "type":"Retail Goods"
        }
    ],
    "sg:phone":"+32 71 77 35 69",
    "sg:postcode":"5060",
    "sg:province":"Namur",
    "sg:tags":[
        "confectionery",
        "-"
    ],
    "wof:name":"Piette-lemille Sa",
    "wof:placetype":"venue"
},
  "geometry": {"coordinates":[4.6367669106,50.4575386047],"type":"Point"}
}