{
  "type": "Feature",
  "properties": {
    "addr:full":"Rue Du Palais De Justice 2 Huy Li\u00e8ge 4500",
    "addr:housenumber":"2",
    "addr:postcode":"4500",
    "addr:street":"Rue Du Palais De Justice",
    "iso:country":"BE",
    "sg:address":"Rue Du Palais De Justice 2",
    "sg:city":"Huy",
    "sg:classifiers":[
        {
            "category":"Social Services",
            "type":"Services"
        }
    ],
    "sg:phone":"+32 85 23 66 03",
    "sg:postcode":"4500",
    "sg:province":"Li\u00e8ge",
    "wof:name":"Structure Accueil Des Toxicomanes",
    "wof:placetype":"venue"
},
  "geometry": {"coordinates":[5.2622542381,50.5351028442],"type":"Point"}
}