{
  "type": "Feature",
  "properties": {
    "iso:country":"BE",
    "sg:address":"Sluisbamd 6",
    "sg:city":"Heusden-zolder (zolder)",
    "sg:classifiers":[
        {
            "category":"Shopping",
            "subcategory":"Crafts & Fabrics",
            "type":"Retail Goods"
        }
    ],
    "sg:phone":"+32 11 53 87 88",
    "sg:postcode":"3550",
    "sg:province":"Limburg",
    "sg:tags":[
        "silk",
        "-"
    ],
    "wof:name":"Makri",
    "wof:placetype":"venue"
},
  "geometry": {"coordinates":[5.3116340637,51.024520874],"type":"Point"}
}