{
  "type": "Feature",
  "properties": {
    "iso:country":"BE",
    "sg:address":"Nieuwstraat 96",
    "sg:city":"Geel",
    "sg:orig_category":"Slagers Zuivelproducten",
    "sg:phone":"+32 14 58 80 85",
    "sg:postcode":"2440",
    "sg:province":"Antwerpen",
    "wof:name":"\u00b4t Kaasboetiekje",
    "wof:placetype":"venue"
},
  "geometry": {"coordinates":[4.994767189,51.1633529663],"type":"Point"}
}