{
  "type": "Feature",
  "properties": {
    "addr:full":"Liebroekstraat 82 Halen Limburg 3545",
    "addr:housenumber":"82",
    "addr:postcode":"3545",
    "addr:street":"Liebroekstraat",
    "iso:country":"BE",
    "sg:address":"Liebroekstraat 82",
    "sg:city":"Halen",
    "sg:orig_category":"Ordinateurs and \u00e9quipement informatique",
    "sg:phone":"+32 13 46 01 00",
    "sg:postcode":"3545",
    "sg:province":"Limburg",
    "wof:name":"Hvh Halen",
    "wof:placetype":"venue"
},
  "geometry": {"coordinates":[5.08934021,50.9543800354],"type":"Point"}
}