{
  "type": "Feature",
  "properties": {
    "addr:full":"Tolpoortstraat 41 Deinze Oost-Vlaanderen 9800",
    "addr:housenumber":"41",
    "addr:postcode":"9800",
    "addr:street":"Tolpoortstraat",
    "iso:country":"BE",
    "sg:address":"Tolpoortstraat 41",
    "sg:city":"Deinze",
    "sg:classifiers":[
        {
            "category":"Shopping",
            "subcategory":"Clothing, Apparel, & Fashions",
            "type":"Retail Goods"
        }
    ],
    "sg:phone":"+32 9 380 11 05",
    "sg:postcode":"9800",
    "sg:province":"Oost-Vlaanderen",
    "sg:tags":[
        "hosiery"
    ],
    "wof:name":"Magino",
    "wof:placetype":"venue"
},
  "geometry": {"coordinates":[3.5292220116,50.9812850952],"type":"Point"}
}