{
  "type": "Feature",
  "properties": {
    "addr:full":"Kesseldallaan 60b301 Leuven Vlaams-Brabant 3010",
    "addr:housenumber":"60b301",
    "addr:postcode":"3010",
    "addr:street":"Kesseldallaan",
    "iso:country":"BE",
    "sg:address":"Kesseldallaan 60b301",
    "sg:city":"Leuven",
    "sg:orig_category":"Activit\u00e9s diverses d'imprimerie",
    "sg:phone":"+32 16 48 80 65",
    "sg:postcode":"3010",
    "sg:province":"Vlaams-Brabant",
    "wof:name":"Publi",
    "wof:placetype":"venue"
},
  "geometry": {"coordinates":[4.7304501534,50.889755249],"type":"Point"}
}