{
  "type": "Feature",
  "properties": {
    "iso:country":"BE",
    "sg:address":"Grande Ruelle 13",
    "sg:city":"Eghez\u00e9e (waret-la-chauss\u00e9e)",
    "sg:classifiers":[
        {
            "category":"Arena",
            "subcategory":"Sports Club",
            "type":"Entertainment"
        }
    ],
    "sg:phone":"+32 81 51 18 23",
    "sg:postcode":"5310",
    "sg:province":"Namur",
    "wof:name":"P.c.n.a.",
    "wof:placetype":"venue"
},
  "geometry": {"coordinates":[4.9179911613,50.5380706787],"type":"Point"}
}