{
  "type": "Feature",
  "properties": {
    "addr:full":"Rue Du Couvent 7 Eupen Li\u00e8ge 4700",
    "addr:housenumber":"7",
    "addr:postcode":"4700",
    "addr:street":"Rue Du Couvent",
    "iso:country":"BE",
    "sg:address":"Rue Du Couvent 7",
    "sg:city":"Eupen",
    "sg:classifiers":[
        {
            "category":"Insurance",
            "subcategory":"Life Insurance",
            "type":"Services"
        }
    ],
    "sg:phone":"+32 87 74 34 40",
    "sg:postcode":"4700",
    "sg:province":"Li\u00e8ge",
    "sg:tags":[
        "assurance"
    ],
    "wof:name":"Axa",
    "wof:placetype":"venue"
},
  "geometry": {"coordinates":[6.0303931236,50.6316642761],"type":"Point"}
}