{
  "type": "Feature",
  "properties": {
    "iso:country":"BE",
    "sg:address":"Noordstraat 13",
    "sg:city":"Kortrijk",
    "sg:classifiers":[
        {
            "category":"Shopping",
            "subcategory":"Clothing, Apparel, & Fashions",
            "type":"Retail Goods"
        }
    ],
    "sg:phone":"+32 56 35 00 04",
    "sg:postcode":"8500",
    "sg:province":"West-Vlaanderen",
    "sg:tags":[
        "lady",
        "clothing",
        "-"
    ],
    "wof:name":"Ribel",
    "wof:placetype":"venue"
},
  "geometry": {"coordinates":[3.255644083,50.8300971985],"type":"Point"}
}