{
  "type": "Feature",
  "properties": {
    "iso:country":"BE",
    "sg:address":"Ch De Marche 875",
    "sg:city":"Wierve",
    "sg:classifiers":[
        {
            "category":"Wholesale",
            "subcategory":"Machinery & Supplies",
            "type":"Manufacturing & Wholesale Goods"
        }
    ],
    "sg:phone":"+32 81 22 96 09",
    "sg:postcode":"5100",
    "sg:province":"Namur",
    "sg:tags":[
        "equipment",
        "precision"
    ],
    "wof:name":"Medical Quick Supplies Sa",
    "wof:placetype":"venue"
},
  "geometry": {"coordinates":[13.0062303543,43.3291816711],"type":"Point"}
}