{
  "type": "Feature",
  "properties": {
    "iso:country":"BE",
    "sg:address":"Heiwyckstraat 78",
    "sg:city":"Lanaken",
    "sg:orig_category":"Kapsalons",
    "sg:phone":"+32 89 71 52 32",
    "sg:postcode":"3620",
    "sg:province":"Limburg",
    "wof:name":"Lowis Ronald & David",
    "wof:placetype":"venue"
},
  "geometry": {"coordinates":[5.6050591469,50.9292984009],"type":"Point"}
}