{
  "type": "Feature",
  "properties": {
    "iso:country":"BE",
    "sg:address":"Vital Decosterstraat 67a",
    "sg:city":"Leuven",
    "sg:classifiers":[
        {
            "category":"Social Services",
            "type":"Services"
        }
    ],
    "sg:phone":"+32 16 23 72 30",
    "sg:postcode":"3000",
    "sg:province":"Vlaams-Brabant",
    "wof:name":"Diensten-en Ontmoetingscentrum (cawleuven) Vzw",
    "wof:placetype":"venue"
},
  "geometry": {"coordinates":[4.7028851509,50.8821372986],"type":"Point"}
}