{
  "type": "Feature",
  "properties": {
    "iso:country":"BE",
    "sg:address":"Pelgrimhofstraat 1",
    "sg:city":"Heist-op-den-berg",
    "sg:orig_category":"Eleveurs de bovins",
    "sg:phone":"+32 15 24 22 83",
    "sg:postcode":"2220",
    "sg:province":"Antwerpen",
    "wof:name":"Alfons Schellens",
    "wof:placetype":"venue"
},
  "geometry": {"coordinates":[4.6956157684,51.058555603],"type":"Point"}
}