{
  "type": "Feature",
  "properties": {
    "addr:full":"Schapenweg 74 Sterrebeek Vlaams-Brabant 1933",
    "addr:housenumber":"74",
    "addr:postcode":"1933",
    "addr:street":"Schapenweg",
    "iso:country":"BE",
    "sg:address":"Schapenweg 74",
    "sg:city":"Sterrebeek",
    "sg:orig_category":"Location de v\u00e9hicules sauf voitures. V\u00e9hicules automobiles. D\u00e9taillants en pi\u00e8ces and accessoires de",
    "sg:phone":"+32 2 686 60 50",
    "sg:postcode":"1933",
    "sg:province":"Vlaams-Brabant",
    "wof:name":"Abego",
    "wof:placetype":"venue"
},
  "geometry": {"coordinates":[4.5172867775,50.8589172363],"type":"Point"}
}