{
  "type": "Feature",
  "properties": {
    "addr:full":"Diestsestraat 58 Leuven Vlaams-Brabant 3000",
    "addr:housenumber":"58",
    "addr:postcode":"3000",
    "addr:street":"Diestsestraat",
    "iso:country":"BE",
    "sg:address":"Diestsestraat 58",
    "sg:city":"Leuven",
    "sg:orig_category":"V\u00eatements",
    "sg:phone":"+32 16 23 10 77",
    "sg:postcode":"3000",
    "sg:province":"Vlaams-Brabant",
    "wof:name":"Original Levi's Store",
    "wof:placetype":"venue"
},
  "geometry": {"coordinates":[4.7054209709,50.8802947998],"type":"Point"}
}