{
  "type": "Feature",
  "properties": {
    "iso:country":"BE",
    "sg:address":"Ren\u00e9 De Renessestraat 45",
    "sg:city":"Sint-pieters-leeuw",
    "sg:classifiers":[
        {
            "category":"Health Services",
            "subcategory":"Doctor",
            "type":"Services"
        }
    ],
    "sg:phone":"+32 2 377 15 63",
    "sg:postcode":"1600",
    "sg:province":"Vlaams-Brabant",
    "sg:tags":[
        "medicinephysicians",
        "surgeon"
    ],
    "wof:name":"Legrand Christian",
    "wof:placetype":"venue"
},
  "geometry": {"coordinates":[4.286096096,50.8037796021],"type":"Point"}
}