{
  "type": "Feature",
  "properties": {
    "addr:full":"Avenue Victor Jacobs 9 Etterbeek Bruxelles-Capitale 1040",
    "addr:housenumber":"9",
    "addr:postcode":"1040",
    "addr:street":"Avenue Victor Jacobs",
    "iso:country":"BE",
    "sg:address":"Avenue Victor Jacobs 9",
    "sg:city":"Etterbeek",
    "sg:orig_category":"Activit\u00e9s diverses d'imprimerie",
    "sg:phone":"+32 2 646 59 81",
    "sg:postcode":"1040",
    "sg:province":"Bruxelles-Capitale",
    "wof:name":"Bureau Kerstin Stout",
    "wof:placetype":"venue"
},
  "geometry": {"coordinates":[4.3853797913,50.8298912048],"type":"Point"}
}