{
  "type": "Feature",
  "properties": {
    "addr:full":"Capucienenstraat 10 Hasselt Limburg 3500",
    "addr:housenumber":"10",
    "addr:postcode":"3500",
    "addr:street":"Capucienenstraat",
    "iso:country":"BE",
    "sg:address":"Capucienenstraat 10",
    "sg:city":"Hasselt",
    "sg:orig_category":"Villages de vacances",
    "sg:phone":"+32 11 24 99 11",
    "sg:postcode":"3500",
    "sg:province":"Limburg",
    "wof:name":"Vakanties De Voorzorg",
    "wof:placetype":"venue"
},
  "geometry": {"coordinates":[5.3392529488,50.9278411865],"type":"Point"}
}