{
  "type": "Feature",
  "properties": {
    "addr:full":"De Baan 3 Westerlo Antwerpen 2260",
    "addr:housenumber":"3",
    "addr:postcode":"2260",
    "addr:street":"De Baan",
    "iso:country":"BE",
    "sg:address":"De Baan 3",
    "sg:city":"Westerlo",
    "sg:classifiers":[
        {
            "category":"Retail",
            "subcategory":"Auto Repair",
            "type":"Services"
        }
    ],
    "sg:phone":"+32 16 69 82 28",
    "sg:postcode":"2260",
    "sg:province":"Antwerpen",
    "sg:tags":[
        "garage"
    ],
    "wof:name":"Bellens",
    "wof:placetype":"venue"
},
  "geometry": {"coordinates":[4.8561911583,51.0944290161],"type":"Point"}
}