{
  "type": "Feature",
  "properties": {
    "iso:country":"BE",
    "sg:address":"Asselkouter 18",
    "sg:city":"Merelbeke",
    "sg:orig_category":"Services divers aux entreprises. Assurances. G\u00e9om\u00e8tres. Services de recherches and bureaux de d\u00e9tect",
    "sg:phone":"+32 9 362 97 62",
    "sg:postcode":"9820",
    "sg:province":"Oost-Vlaanderen",
    "wof:name":"Guy Bottequin",
    "wof:placetype":"venue"
},
  "geometry": {"coordinates":[3.7573509216,50.9472541809],"type":"Point"}
}