{
  "type": "Feature",
  "properties": {
    "iso:country":"BE",
    "sg:address":"Onze-lieve-vrouwestraat 100",
    "sg:city":"Mechelen",
    "sg:orig_category":"Verbruikerskredietinstellingen",
    "sg:phone":"+32 15 41 50 13",
    "sg:postcode":"2800",
    "sg:province":"Antwerpen",
    "wof:name":"Personhyfina",
    "wof:placetype":"venue"
},
  "geometry": {"coordinates":[4.4810519218,51.022644043],"type":"Point"}
}