{
  "type": "Feature",
  "properties": {
    "addr:full":"Mariakerkelaan 69 Oostende West-Vlaanderen 8400",
    "addr:housenumber":"69",
    "addr:postcode":"8400",
    "addr:street":"Mariakerkelaan",
    "iso:country":"BE",
    "sg:address":"Mariakerkelaan 69",
    "sg:city":"Oostende",
    "sg:orig_category":"Travaux de finition and nettoyage de b\u00e2timents",
    "sg:phone":"+32 59 80 82 82",
    "sg:postcode":"8400",
    "sg:province":"West-Vlaanderen",
    "wof:name":"Venus",
    "wof:placetype":"venue"
},
  "geometry": {"coordinates":[2.9058699608,51.2120895386],"type":"Point"}
}