{
  "type": "Feature",
  "properties": {
    "iso:country":"BE",
    "sg:address":"Bld G\u00c9n\u00c9ral Jacques 20b3",
    "sg:city":"Elsene/ixelles",
    "sg:orig_category":"Avocats and conseillers juridiques",
    "sg:phone":"+32 2 648 56 71",
    "sg:postcode":"1050",
    "sg:province":"Bruxelles-Capitale",
    "wof:name":"G. Fran\u00c7ois",
    "wof:placetype":"venue"
},
  "geometry": {"coordinates":[4.3779740334,50.8170433044],"type":"Point"}
}