{
  "type": "Feature",
  "properties": {
    "iso:country":"BE",
    "sg:address":"Hoveniersstraat 46",
    "sg:city":"Antwerpen",
    "sg:orig_category":"Horloges, m\u00e9taux pr\u00e9cieux and bijoux Produits interm\u00e9diaires Gr",
    "sg:phone":"+32 3 226 14 00",
    "sg:postcode":"2018",
    "sg:province":"Antwerpen",
    "wof:name":"Agem",
    "wof:placetype":"venue"
},
  "geometry": {"coordinates":[4.418607235,51.2147293091],"type":"Point"}
}