{
  "type": "Feature",
  "properties": {
    "iso:country":"BE",
    "sg:address":"Bremtstraat 105",
    "sg:city":"Aalst",
    "sg:orig_category":"Cr\u00e9meries",
    "sg:phone":"+32 53 83 38 90",
    "sg:postcode":"9320",
    "sg:province":"Oost-Vlaanderen",
    "wof:name":"Rudy Doolaege",
    "wof:placetype":"venue"
},
  "geometry": {"coordinates":[4.0553851128,50.9209976196],"type":"Point"}
}