{
  "type": "Feature",
  "properties": {
    "iso:country":"BE",
    "sg:address":"Luikersteenweg 63",
    "sg:city":"Tongeren",
    "sg:orig_category":"Travaux de pl\u00e2trage",
    "sg:phone":"+32 12 23 16 13",
    "sg:postcode":"3700",
    "sg:province":"Limburg",
    "wof:name":"Levenstond A. & R. & N.",
    "wof:placetype":"venue"
},
  "geometry": {"coordinates":[5.4603610039,50.7727546692],"type":"Point"}
}