{
  "type": "Feature",
  "properties": {
    "addr:full":"Marktplein 19 Wingene West-Vlaanderen 8750",
    "addr:housenumber":"19",
    "addr:postcode":"8750",
    "addr:street":"Marktplein",
    "iso:country":"BE",
    "sg:address":"Marktplein 19",
    "sg:city":"Wingene",
    "sg:orig_category":"Banken and kredietinstellingen",
    "sg:phone":"+32 51 61 10 37",
    "sg:postcode":"8750",
    "sg:province":"West-Vlaanderen",
    "wof:name":"Bbl",
    "wof:placetype":"venue"
},
  "geometry": {"coordinates":[3.2113149166,51.035785675],"type":"Point"}
}