{
  "type": "Feature",
  "properties": {
    "addr:full":"Predikherenlei 37 Evergem (ertvelde) Oost-Vlaanderen 9940",
    "addr:housenumber":"37",
    "addr:postcode":"9940",
    "addr:street":"Predikherenlei;Ertvelde Oost-Vlaanderen",
    "iso:country":"BE",
    "sg:address":"Predikherenlei 37",
    "sg:city":"Evergem (ertvelde)",
    "sg:classifiers":[
        {
            "category":"Home & Garden",
            "subcategory":"Carpets & Floor Coverings",
            "type":"Retail Goods"
        }
    ],
    "sg:phone":"+32 9 344 37 00",
    "sg:postcode":"9940",
    "sg:province":"Oost-Vlaanderen",
    "sg:tags":[
        "parquet"
    ],
    "wof:name":"Woodworks Nv",
    "wof:placetype":"venue"
},
  "geometry": {"coordinates":[3.7493240833,51.1895866394],"type":"Point"}
}