{
  "type": "Feature",
  "properties": {
    "addr:full":"Paassoldatenstraat 10 Halle (lembeek) Vlaams-Brabant 1502",
    "addr:housenumber":"10;1502",
    "addr:street":"Paassoldatenstraat",
    "iso:country":"BE",
    "sg:address":"Paassoldatenstraat 10",
    "sg:city":"Halle (lembeek)",
    "sg:classifiers":[
        {
            "category":"Health Services",
            "subcategory":"Health Practitioner",
            "type":"Services"
        }
    ],
    "sg:phone":"+32 2 361 50 11",
    "sg:postcode":"1502",
    "sg:province":"Vlaams-Brabant",
    "sg:tags":[
        "osteopath"
    ],
    "wof:name":"Schellemans D",
    "wof:placetype":"venue"
},
  "geometry": {"coordinates":[4.2126808167,50.7193374634],"type":"Point"}
}