{
  "type": "Feature",
  "properties": {
    "addr:full":"Avenue Professeur Henrijean 14 Spa Li\u00e8ge 4900",
    "addr:housenumber":"14",
    "addr:postcode":"4900",
    "addr:street":"Avenue Professeur Henrijean",
    "iso:country":"BE",
    "sg:address":"Avenue Professeur Henrijean 14",
    "sg:city":"Spa",
    "sg:classifiers":[
        {
            "category":"Health Services",
            "subcategory":"Nursing And Care Facility",
            "type":"Services"
        }
    ],
    "sg:phone":"+32 87 77 46 91",
    "sg:postcode":"4900",
    "sg:province":"Li\u00e8ge",
    "sg:tags":[
        "home",
        "rest"
    ],
    "wof:name":"Bleuets (les)",
    "wof:placetype":"venue"
},
  "geometry": {"coordinates":[5.8591389656,50.4871711731],"type":"Point"}
}