{
  "type": "Feature",
  "properties": {
    "iso:country":"BE",
    "sg:address":"Terbeke 27",
    "sg:city":"Maarkedal",
    "sg:orig_category":"Terrains de camping. Activit\u00e9s r\u00e9cr\u00e9atives diverses. Caf\u00e9s",
    "sg:phone":"+32 55 21 46 17",
    "sg:postcode":"9680",
    "sg:province":"Oost-Vlaanderen",
    "wof:name":"Camping De Visvijvers",
    "wof:placetype":"venue"
},
  "geometry": {"coordinates":[3.6251978874,50.8114929199],"type":"Point"}
}