{
  "type": "Feature",
  "properties": {
    "addr:full":"Sart D'avette 110 Fl\u00e9malle (awirs) Li\u00e8ge 4400",
    "addr:housenumber":"110",
    "addr:postcode":"4400",
    "addr:street":"Sart D'Avette",
    "iso:country":"BE",
    "sg:address":"Sart D'avette 110",
    "sg:city":"Fl\u00e9malle (awirs)",
    "sg:classifiers":[
        {
            "category":"Shopping",
            "subcategory":"Discount & Variety Stores",
            "type":"Retail Goods"
        }
    ],
    "sg:phone":"+32 4 273 72 00",
    "sg:postcode":"4400",
    "sg:province":"Li\u00e8ge",
    "sg:tags":[
        "warehouse",
        "-",
        "merchandise"
    ],
    "wof:name":"Soci\u00e9t\u00e9 Industrielle Du Hainaut",
    "wof:placetype":"venue"
},
  "geometry": {"coordinates":[5.4169368744,50.6062316895],"type":"Point"}
}