{
  "type": "Feature",
  "properties": {
    "addr:full":"Veldekens 25bd Maldegem Oost-Vlaanderen 9991",
    "addr:housenumber":"25bd",
    "addr:postcode":"9991",
    "addr:street":"Veldekens",
    "iso:country":"BE",
    "sg:address":"Veldekens 25bd",
    "sg:city":"Maldegem",
    "sg:orig_category":"Rundveehouders Varkenskwekers",
    "sg:phone":"+32 9 377 01 67",
    "sg:postcode":"9991",
    "sg:province":"Oost-Vlaanderen",
    "wof:name":"Willy Rabaeys",
    "wof:placetype":"venue"
},
  "geometry": {"coordinates":[3.5261049271,51.163318634],"type":"Point"}
}