{
  "type": "Feature",
  "properties": {
    "addr:full":"Mottaart 11 Herselt Antwerpen 2230",
    "addr:housenumber":"11",
    "addr:postcode":"2230",
    "addr:street":"Mottaart",
    "iso:country":"BE",
    "sg:address":"Mottaart 11",
    "sg:city":"Herselt",
    "sg:orig_category":"Bijouteries and horlogeries",
    "sg:phone":"+32 14 54 59 26",
    "sg:postcode":"2230",
    "sg:province":"Antwerpen",
    "wof:name":"Atelier Janssens",
    "wof:placetype":"venue"
},
  "geometry": {"coordinates":[4.8946051598,51.0407676697],"type":"Point"}
}