{
  "type": "Feature",
  "properties": {
    "iso:country":"BE",
    "sg:address":"Rue Charles Hanssens 10",
    "sg:city":"Brussel/bruxelles",
    "sg:orig_category":"Antiquit\u00e9s. Biens d'occasion",
    "sg:phone":"+32 2 725 70 25",
    "sg:postcode":"1000",
    "sg:province":"Bruxelles-Capitale",
    "wof:name":"Art Et D\u00c9coration",
    "wof:placetype":"venue"
},
  "geometry": {"coordinates":[4.3528580666,50.8393211365],"type":"Point"}
}