{
  "type": "Feature",
  "properties": {
    "addr:full":"Markgravelei 100 Antwerpen Antwerpen 2018",
    "addr:housenumber":"100",
    "addr:postcode":"2018",
    "iso:country":"BE",
    "sg:address":"Markgravelei 100",
    "sg:city":"Antwerpen",
    "sg:classifiers":[
        {
            "category":"Building & Trades",
            "subcategory":"Pest Control",
            "type":"Services"
        }
    ],
    "sg:phone":"+32 3 238 96 10",
    "sg:postcode":"2018",
    "sg:province":"Antwerpen",
    "sg:tags":[
        "painting",
        "contractor"
    ],
    "wof:name":"Smet O",
    "wof:placetype":"venue"
},
  "geometry": {"coordinates":[4.4028468132,51.1982688904],"type":"Point"}
}