{
  "type": "Feature",
  "properties": {
    "addr:full":"Kattebroekstraat 290 Dilbeek Vlaams-Brabant 1700",
    "addr:housenumber":"290",
    "addr:postcode":"1700",
    "addr:street":"Kattebroekstraat",
    "iso:country":"BE",
    "sg:address":"Kattebroekstraat 290",
    "sg:city":"Dilbeek",
    "sg:orig_category":"Solariums",
    "sg:phone":"+32 2 466 00 88",
    "sg:postcode":"1700",
    "sg:province":"Vlaams-Brabant",
    "wof:name":"A. Sauna & Beauty Thermen Dilbeek",
    "wof:placetype":"venue"
},
  "geometry": {"coordinates":[4.2787380219,50.8599472046],"type":"Point"}
}