{
  "type": "Feature",
  "properties": {
    "iso:country":"BE",
    "sg:address":"Beernemstraat 34",
    "sg:city":"Wingene",
    "sg:orig_category":"Chaussures",
    "sg:phone":"+32 51 65 82 52",
    "sg:postcode":"8750",
    "sg:province":"West-Vlaanderen",
    "wof:name":"Sofie Vandeweghe",
    "wof:placetype":"venue"
},
  "geometry": {"coordinates":[3.2773439884,51.0616569519],"type":"Point"}
}