{
  "type": "Feature",
  "properties": {
    "addr:full":"Place Des Martyrs 3 Dour Hainaut 7370",
    "addr:housenumber":"3",
    "addr:postcode":"7370",
    "addr:street":"Place Des Martyrs;Hainaut",
    "iso:country":"BE",
    "sg:address":"Place Des Martyrs 3",
    "sg:city":"Dour",
    "sg:orig_category":"Apotheken",
    "sg:phone":"+32 65 65 20 35",
    "sg:postcode":"7370",
    "sg:province":"Hainaut",
    "wof:name":"Pharmacie Cayman",
    "wof:placetype":"venue"
},
  "geometry": {"coordinates":[3.7817790508,50.4009017944],"type":"Point"}
}