{
  "type": "Feature",
  "properties": {
    "iso:country":"BE",
    "sg:address":"Rollegemkerkstraat 51",
    "sg:city":"Kortrijk",
    "sg:orig_category":"Instellingen voor mindervalide volwassenen",
    "sg:phone":"+32 56 22 57 87",
    "sg:postcode":"8510",
    "sg:province":"West-Vlaanderen",
    "wof:name":"De Kindervriend",
    "wof:placetype":"venue"
},
  "geometry": {"coordinates":[3.258920908,50.7674255371],"type":"Point"}
}