{
  "type": "Feature",
  "properties": {
    "addr:full":"Avenue Du Scheutbosch 53 Box 12 Bruxelles (molenbeek-saint-jean) Bruxelles-Capitale 1080",
    "addr:housenumber":"53 box 12",
    "addr:postcode":"1080",
    "addr:street":"Avenue Du Scheutbosch",
    "iso:country":"BE",
    "sg:address":"Avenue Du Scheutbosch 53 Box 12",
    "sg:city":"Bruxelles (molenbeek-saint-jean)",
    "sg:classifiers":[
        {
            "category":"Banks & Credit Unions",
            "subcategory":"Financial Services",
            "type":"Services"
        }
    ],
    "sg:phone":"+32 2 414 93 82",
    "sg:postcode":"1080",
    "sg:province":"Bruxelles-Capitale",
    "sg:tags":[
        "debt",
        "recovery"
    ],
    "wof:name":"Fimatil Bvba",
    "wof:placetype":"venue"
},
  "geometry": {"coordinates":[4.3046798706,50.851940155],"type":"Point"}
}