{
  "type": "Feature",
  "properties": {
    "addr:full":"B. De Lausnaystraat 11 Berlare Oost-Vlaanderen 9290",
    "addr:housenumber":"11",
    "addr:postcode":"9290",
    "addr:street":"B.;Lausnaystraat",
    "iso:country":"BE",
    "sg:address":"B. De Lausnaystraat 11",
    "sg:city":"Berlare",
    "sg:orig_category":"Bloemen and planten",
    "sg:phone":"+32 9 367 65 12",
    "sg:postcode":"9290",
    "sg:province":"Oost-Vlaanderen",
    "wof:name":"Myosotis",
    "wof:placetype":"venue"
},
  "geometry": {"coordinates":[4.005710125,51.0165214539],"type":"Point"}
}