{
  "type": "Feature",
  "properties": {
    "iso:country":"BE",
    "sg:address":"Moleken 25",
    "sg:city":"Wichelen",
    "sg:classifiers":[
        {
            "category":"Retail",
            "subcategory":"Auto Rental",
            "type":"Services"
        }
    ],
    "sg:phone":"+32 52 42 43 48",
    "sg:postcode":"9260",
    "sg:province":"Oost-Vlaanderen",
    "sg:tags":[
        "mazda",
        "automobile",
        "v\u00e9hicules"
    ],
    "wof:name":"Garage De Wolf",
    "wof:placetype":"venue"
},
  "geometry": {"coordinates":[3.9659519196,51.007976532],"type":"Point"}
}