{
  "type": "Feature",
  "properties": {
    "addr:full":"Meeuwenlaan 19 Middelkerke West-Vlaanderen 8434",
    "addr:housenumber":"19",
    "addr:postcode":"8434",
    "addr:street":"Meeuwenlaan",
    "iso:country":"BE",
    "sg:address":"Meeuwenlaan 19",
    "sg:city":"Middelkerke",
    "sg:classifiers":[
        {
            "category":"Restaurant",
            "type":"Food & Drink"
        }
    ],
    "sg:phone":"+32 59 31 21 18",
    "sg:postcode":"8434",
    "sg:province":"West-Vlaanderen",
    "sg:tags":[
        "caf\u00e9s"
    ],
    "wof:name":"Spots",
    "wof:placetype":"venue"
},
  "geometry": {"coordinates":[2.7761509418,51.170539856],"type":"Point"}
}