{
  "type": "Feature",
  "properties": {
    "addr:full":"Wetstraat 6 Brussel/bruxelles Bruxelles-Capitale 1000",
    "addr:housenumber":"6",
    "addr:postcode":"1000",
    "addr:street":"Wetstraat;/",
    "iso:country":"BE",
    "sg:address":"Wetstraat 6",
    "sg:city":"Brussel/bruxelles",
    "sg:orig_category":"Overheidsdiensten",
    "sg:phone":"+32 2 506 39 26",
    "sg:postcode":"1000",
    "sg:province":"Bruxelles-Capitale",
    "wof:name":"Documentation Et Recherches",
    "wof:placetype":"venue"
},
  "geometry": {"coordinates":[4.3635549545,50.846736908],"type":"Point"}
}