{
  "type": "Feature",
  "properties": {
    "iso:country":"BE",
    "sg:address":"Garenmarkt 10b3",
    "sg:city":"Brugge",
    "sg:orig_category":"Artsen and specialisten",
    "sg:phone":"+32 50 34 30 33",
    "sg:postcode":"8000",
    "sg:province":"West-Vlaanderen",
    "wof:name":"Dirk Decq",
    "wof:placetype":"venue"
},
  "geometry": {"coordinates":[3.2292990685,51.2051239014],"type":"Point"}
}