{
  "type": "Feature",
  "properties": {
    "iso:country":"BE",
    "sg:address":"Chauss\u00c9e De Charleroi 425",
    "sg:city":"Fosses-la-ville",
    "sg:orig_category":"Installation \u00e9lectrique r\u00e9sidentielle",
    "sg:phone":"+32 71 71 32 41",
    "sg:postcode":"5070",
    "sg:province":"Namur",
    "wof:name":"Michel Saublens",
    "wof:placetype":"venue"
},
  "geometry": {"coordinates":[4.6720647812,50.3931503296],"type":"Point"}
}