{
  "type": "Feature",
  "properties": {
    "iso:country":"BE",
    "sg:address":"Dr\u00e8ve De Colipain 203",
    "sg:city":"Braine L'alleud (braine-l'alleud)",
    "sg:classifiers":[
        {
            "category":"Health Services",
            "subcategory":"Doctor",
            "type":"Services"
        }
    ],
    "sg:phone":"+32 2 376 77 40",
    "sg:postcode":"1420",
    "sg:province":"Brabant Wallon",
    "sg:tags":[
        "medicinephysicians",
        "surgeon"
    ],
    "wof:name":"Lardinois I",
    "wof:placetype":"venue"
},
  "geometry": {"coordinates":[-0.7004899979,47.369140625],"type":"Point"}
}