{
  "type": "Feature",
  "properties": {
    "iso:country":"BE",
    "sg:address":"Grand Rue 42",
    "sg:city":"Durbuy",
    "sg:classifiers":[
        {
            "category":"Restaurant",
            "type":"Food & Drink"
        }
    ],
    "sg:phone":"+32 86 21 20 38",
    "sg:postcode":"6940",
    "sg:province":"Luxembourg",
    "wof:name":"Le Karawa",
    "wof:placetype":"venue"
},
  "geometry": {"coordinates":[5.4936180115,50.3507614136],"type":"Point"}
}