{
  "type": "Feature",
  "properties": {
    "addr:full":"Papdijk 18 Moerbeke Oost-Vlaanderen 9180",
    "addr:housenumber":"18",
    "addr:postcode":"9180",
    "addr:street":"Papdijk",
    "iso:country":"BE",
    "sg:address":"Papdijk 18",
    "sg:city":"Moerbeke",
    "sg:orig_category":"D\u00e9molition d\u00b4immeubles and terrassements. Machines and mat\u00e9riel agricoles Gr",
    "sg:phone":"+32 9 346 87 17",
    "sg:postcode":"9180",
    "sg:province":"Oost-Vlaanderen",
    "wof:name":"Freddy De Keyser",
    "wof:placetype":"venue"
},
  "geometry": {"coordinates":[3.9233050346,51.2016525269],"type":"Point"}
}