{
  "type": "Feature",
  "properties": {
    "addr:full":"Rue Sainte-walburge 21 Li\u00e8ge 1 Li\u00e8ge 4000",
    "addr:housenumber":"21;1",
    "addr:postcode":"4000",
    "addr:street":"Rue Sainte-Walburge",
    "iso:country":"BE",
    "sg:address":"Rue Sainte-walburge 21",
    "sg:city":"Li\u00e8ge 1",
    "sg:classifiers":[
        {
            "category":"Professional",
            "subcategory":"Art Services",
            "type":"Services"
        }
    ],
    "sg:phone":"+32 4 225 00 22",
    "sg:postcode":"4000",
    "sg:province":"Li\u00e8ge",
    "sg:tags":[
        "photographer"
    ],
    "wof:name":"Mariages Videos",
    "wof:placetype":"venue"
},
  "geometry": {"coordinates":[5.5738902092,50.6541900635],"type":"Point"}
}