{
  "type": "Feature",
  "properties": {
    "addr:full":"Vossenbergstraat 70 Hasselt Limburg 3500",
    "addr:housenumber":"70",
    "addr:postcode":"3500",
    "addr:street":"Vossenbergstraat",
    "iso:country":"BE",
    "sg:address":"Vossenbergstraat 70",
    "sg:city":"Hasselt",
    "sg:orig_category":"Koerierbedrijven",
    "sg:phone":"+32 11 22 65 42",
    "sg:postcode":"3500",
    "sg:province":"Limburg",
    "wof:name":"Roger Jacques",
    "wof:placetype":"venue"
},
  "geometry": {"coordinates":[5.3359251022,50.9270362854],"type":"Point"}
}