{
  "type": "Feature",
  "properties": {
    "addr:full":"Paviljoenstraat 25 Geel Antwerpen 2440",
    "addr:housenumber":"25",
    "addr:postcode":"2440",
    "addr:street":"Paviljoenstraat",
    "iso:country":"BE",
    "sg:address":"Paviljoenstraat 25",
    "sg:city":"Geel",
    "sg:classifiers":[
        {
            "category":"Home & Garden",
            "subcategory":"Carpets & Floor Coverings",
            "type":"Retail Goods"
        }
    ],
    "sg:phone":"+32 14 59 07 59",
    "sg:postcode":"2440",
    "sg:province":"Antwerpen",
    "sg:tags":[
        "tile"
    ],
    "wof:name":"Devis Nv",
    "wof:placetype":"venue"
},
  "geometry": {"coordinates":[4.9804148674,51.2000808716],"type":"Point"}
}