{
  "type": "Feature",
  "properties": {
    "addr:full":"Rue De France 39 Philippeville Namur 5600",
    "addr:housenumber":"39",
    "addr:postcode":"5600",
    "addr:street":"Rue De France",
    "iso:country":"BE",
    "sg:address":"Rue De France 39",
    "sg:city":"Philippeville",
    "sg:orig_category":"Telecommunicatieapparaten",
    "sg:phone":"+32 71 66 94 71",
    "sg:postcode":"5600",
    "sg:province":"Namur",
    "wof:name":"Eldi",
    "wof:placetype":"venue"
},
  "geometry": {"coordinates":[4.5383257866,50.1964530945],"type":"Point"}
}