{
  "type": "Feature",
  "properties": {
    "addr:full":"Dorpstraat 72bd Temse Oost-Vlaanderen 9140",
    "addr:housenumber":"72bd",
    "addr:postcode":"9140",
    "addr:street":"Dorpstraat",
    "iso:country":"BE",
    "sg:address":"Dorpstraat 72bd",
    "sg:city":"Temse",
    "sg:orig_category":"Epiceries",
    "sg:phone":"+32 52 46 04 34",
    "sg:postcode":"9140",
    "sg:province":"Oost-Vlaanderen",
    "wof:name":"Supermarkt",
    "wof:placetype":"venue"
},
  "geometry": {"coordinates":[4.1400871277,51.1142578125],"type":"Point"}
}