{
  "type": "Feature",
  "properties": {
    "addr:full":"Rue Longue 5 Viroinval Namur 5670",
    "addr:housenumber":"5",
    "addr:postcode":"5670",
    "addr:street":"Rue Longue",
    "iso:country":"BE",
    "sg:address":"Rue Longue 5",
    "sg:city":"Viroinval",
    "sg:orig_category":"Traitements param\u00e9dicaux",
    "sg:phone":"+32 60 31 37 70",
    "sg:postcode":"5670",
    "sg:province":"Namur",
    "wof:name":"Alice",
    "wof:placetype":"venue"
},
  "geometry": {"coordinates":[4.547524929,50.0749931335],"type":"Point"}
}