{
  "type": "Feature",
  "properties": {
    "addr:full":"Rue D'ah\u00e9r\u00e9e 39 Saint-l\u00e9ger (ch\u00e2tillon) Luxembourg 6747",
    "addr:housenumber":"39",
    "addr:postcode":"6747",
    "addr:street":"Rue D'Ahe \u0301Re\u0301E",
    "iso:country":"BE",
    "sg:address":"Rue D'ah\u00e9r\u00e9e 39",
    "sg:city":"Saint-l\u00e9ger (ch\u00e2tillon)",
    "sg:classifiers":[
        {
            "category":"Real Estate",
            "subcategory":"Surveying",
            "type":"Services"
        }
    ],
    "sg:phone":"+32 63 21 63 32",
    "sg:postcode":"6747",
    "sg:province":"Luxembourg",
    "sg:tags":[
        "surveyor",
        "land"
    ],
    "wof:name":"Simon F",
    "wof:placetype":"venue"
},
  "geometry": {"coordinates":[5.6852679253,49.6235313416],"type":"Point"}
}