{
  "type": "Feature",
  "properties": {
    "iso:country":"BE",
    "sg:address":"Mithremstraat 27",
    "sg:city":"Evergem (sleidinge)",
    "sg:classifiers":[
        {
            "category":"Parking",
            "subcategory":"Lot",
            "type":"Transportation"
        }
    ],
    "sg:phone":"+32 9 357 36 54",
    "sg:postcode":"9940",
    "sg:province":"Oost-Vlaanderen",
    "sg:tags":[
        "parking-places",
        "laying-out"
    ],
    "wof:name":"Caboor & Zonen Nv",
    "wof:placetype":"venue"
},
  "geometry": {"coordinates":[3.6614379883,51.1416091919],"type":"Point"}
}