{
  "type": "Feature",
  "properties": {
    "addr:full":"De Romboutweg 106 Brasschaat Antwerpen 2930",
    "addr:housenumber":"106",
    "addr:postcode":"2930",
    "iso:country":"BE",
    "sg:address":"De Romboutweg 106",
    "sg:city":"Brasschaat",
    "sg:orig_category":"Non-Classified Establishments",
    "sg:phone":"+32 3 651 47 63",
    "sg:postcode":"2930",
    "sg:province":"Antwerpen",
    "wof:name":"De With B",
    "wof:placetype":"venue"
},
  "geometry": {"coordinates":[4.4742012024,51.3061027527],"type":"Point"}
}