{
  "type": "Feature",
  "properties": {
    "addr:full":"Chauss\u00c9e Romaine 17 Silly Hainaut 7830",
    "addr:housenumber":"17",
    "addr:postcode":"7830",
    "addr:street":"Chausse\u0301E Romaine",
    "iso:country":"BE",
    "sg:address":"Chauss\u00c9e Romaine 17",
    "sg:city":"Silly",
    "sg:orig_category":"Eleveurs de bovins",
    "sg:phone":"+32 2 395 72 55",
    "sg:postcode":"7830",
    "sg:province":"Hainaut",
    "wof:name":"Duret Jules Et Luc",
    "wof:placetype":"venue"
},
  "geometry": {"coordinates":[4.0237498283,50.6393318176],"type":"Point"}
}