{
  "type": "Feature",
  "properties": {
    "iso:country":"BE",
    "sg:address":"Chauss\u00e9e Brunehaut 308",
    "sg:city":"Beloeil (ellignies-sainte-anne)",
    "sg:classifiers":[
        {
            "category":"Professional",
            "subcategory":"Engineering",
            "type":"Services"
        }
    ],
    "sg:phone":"+32 69 68 61 33",
    "sg:postcode":"7972",
    "sg:province":"Hainaut",
    "sg:tags":[
        "-"
    ],
    "wof:name":"Bureau D'etudes-assistance Technique",
    "wof:placetype":"venue"
},
  "geometry": {"coordinates":[3.6907989979,50.5417861938],"type":"Point"}
}