{
  "type": "Feature",
  "properties": {
    "iso:country":"BE",
    "sg:address":"Heiligstraat 99",
    "sg:city":"Hemiksem",
    "sg:classifiers":[
        {
            "category":"Professional",
            "type":"Services"
        }
    ],
    "sg:phone":"+32 3 887 74 11",
    "sg:postcode":"2620",
    "sg:province":"Antwerpen",
    "sg:tags":[
        "entertainer"
    ],
    "wof:name":"Goochelclub Vgb",
    "wof:placetype":"venue"
},
  "geometry": {"coordinates":[4.3477659225,51.1475410461],"type":"Point"}
}