{
  "type": "Feature",
  "properties": {
    "addr:full":"Duinbergenlaan 115 Knokke-heist West-Vlaanderen 8301",
    "addr:housenumber":"115",
    "addr:postcode":"8301",
    "addr:street":"Duinbergenlaan",
    "iso:country":"BE",
    "sg:address":"Duinbergenlaan 115",
    "sg:city":"Knokke-heist",
    "sg:orig_category":"Slagers",
    "sg:phone":"+32 50 51 10 85",
    "sg:postcode":"8301",
    "sg:province":"West-Vlaanderen",
    "wof:name":"Patrick Hillewaere",
    "wof:placetype":"venue"
},
  "geometry": {"coordinates":[3.2583310604,51.3443565369],"type":"Point"}
}