{
  "type": "Feature",
  "properties": {
    "addr:full":"Ooststr 10 Boekhoute Oost-Vlaanderen 9961",
    "addr:housenumber":"10",
    "addr:postcode":"9961",
    "addr:street":"Ooststr;Oost-Vlaanderen",
    "iso:country":"BE",
    "sg:address":"Ooststr 10",
    "sg:city":"Boekhoute",
    "sg:classifiers":[
        {
            "category":"Banks & Credit Unions",
            "subcategory":"Bank",
            "type":"Services"
        }
    ],
    "sg:phone":"+32 52 73 66 25",
    "sg:postcode":"9961",
    "sg:province":"Oost-Vlaanderen",
    "wof:name":"Gemeentekrediet",
    "wof:placetype":"venue"
},
  "geometry": {"coordinates":[3.719835043,51.2584266663],"type":"Point"}
}