{
  "type": "Feature",
  "properties": {
    "addr:full":"Legen Heirweg 56 Gavere (asper) Oost-Vlaanderen 9890",
    "addr:housenumber":"56",
    "addr:postcode":"9890",
    "addr:street":"Legen Heirweg",
    "iso:country":"BE",
    "sg:address":"Legen Heirweg 56",
    "sg:city":"Gavere (asper)",
    "sg:classifiers":[
        {
            "category":"Autos & Motor Vehicles",
            "subcategory":"Automobile Sales",
            "type":"Retail Goods"
        }
    ],
    "sg:phone":"+32 9 384 23 73",
    "sg:postcode":"9890",
    "sg:province":"Oost-Vlaanderen",
    "sg:tags":[
        "car",
        "used",
        "-"
    ],
    "wof:name":"Classic Cars",
    "wof:placetype":"venue"
},
  "geometry": {"coordinates":[3.647331953,50.9348297119],"type":"Point"}
}