{
  "type": "Feature",
  "properties": {
    "addr:full":"Broechemsesteenweg 106 Boechout (vremde) Antwerpen 2531",
    "addr:housenumber":"106",
    "addr:postcode":"2531",
    "addr:street":"Broechemsesteenweg",
    "iso:country":"BE",
    "sg:address":"Broechemsesteenweg 106",
    "sg:city":"Boechout (vremde)",
    "sg:classifiers":[
        {
            "category":"Shopping",
            "subcategory":"Florist",
            "type":"Retail Goods"
        }
    ],
    "sg:phone":"+32 3 225 21 28",
    "sg:postcode":"2531",
    "sg:province":"Antwerpen",
    "wof:name":"Floralco",
    "wof:placetype":"venue"
},
  "geometry": {"coordinates":[4.5603079796,51.1728057861],"type":"Point"}
}