{
  "type": "Feature",
  "properties": {
    "iso:country":"BE",
    "sg:address":"Neerstraat 22",
    "sg:city":"Dilbeek (sint-martens-bodegem)",
    "sg:classifiers":[
        {
            "category":"Insurance",
            "subcategory":"Insurance Agent",
            "type":"Services"
        }
    ],
    "sg:phone":"+32 2 582 71 49",
    "sg:postcode":"1700",
    "sg:province":"Vlaams-Brabant",
    "sg:tags":[
        "broker"
    ],
    "wof:name":"I & V - Risk Com V",
    "wof:placetype":"venue"
},
  "geometry": {"coordinates":[4.2195091248,50.8643264771],"type":"Point"}
}