{
  "type": "Feature",
  "properties": {
    "addr:full":"Rue Van Opre 79 Jambes Namur 5100",
    "addr:housenumber":"79",
    "addr:postcode":"5100",
    "addr:street":"Rue Van Opre",
    "iso:country":"BE",
    "sg:address":"Rue Van Opre 79",
    "sg:city":"Jambes",
    "sg:classifiers":[
        {
            "category":"Banks & Credit Unions",
            "subcategory":"Bank",
            "type":"Services"
        }
    ],
    "sg:phone":"+32 81 30 27 31",
    "sg:postcode":"5100",
    "sg:province":"Namur",
    "wof:name":"Sc De Cr\u00e9dit Artisanal, De La Province De Namur",
    "wof:placetype":"venue"
},
  "geometry": {"coordinates":[4.8744688034,50.4597320557],"type":"Point"}
}