{
  "type": "Feature",
  "properties": {
    "iso:country":"BE",
    "sg:address":"Chauss\u00c9e De Namur 71",
    "sg:city":"Wavre",
    "sg:orig_category":"R\u00e9parations de chaussures and articles en cuir",
    "sg:phone":"+32 10 22 31 40",
    "sg:postcode":"1300",
    "sg:province":"Brabant Wallon",
    "wof:name":"Jean Geuvens",
    "wof:placetype":"venue"
},
  "geometry": {"coordinates":[4.6157598495,50.7050056458],"type":"Point"}
}