{
  "type": "Feature",
  "properties": {
    "addr:full":"Zavelstraat 9 Mol Antwerpen 2400",
    "addr:housenumber":"9",
    "addr:postcode":"2400",
    "addr:street":"Zavelstraat",
    "iso:country":"BE",
    "sg:address":"Zavelstraat 9",
    "sg:city":"Mol",
    "sg:classifiers":[
        {
            "category":"Organizations",
            "subcategory":"Community Association",
            "type":"Services"
        }
    ],
    "sg:phone":"+32 14 31 53 65",
    "sg:postcode":"2400",
    "sg:province":"Antwerpen",
    "sg:tags":[
        "organisation"
    ],
    "wof:name":"V Vks",
    "wof:placetype":"venue"
},
  "geometry": {"coordinates":[5.1289200783,51.1993255615],"type":"Point"}
}