{
  "type": "Feature",
  "properties": {
    "iso:country":"BE",
    "sg:address":"Rue G Schildknecht 33",
    "sg:city":"Brussel/bruxelles",
    "sg:orig_category":"Goederenvervoer over de weg",
    "sg:phone":"+32 2 426 75 95",
    "sg:postcode":"1020",
    "sg:province":"Bruxelles-Capitale",
    "wof:name":"Tructrans",
    "wof:placetype":"venue"
},
  "geometry": {"coordinates":[4.3480710983,50.8730239868],"type":"Point"}
}