{
  "type": "Feature",
  "properties": {
    "addr:full":"Rue J. Bassem 103 Oudergem/auderghem Bruxelles-Capitale 1160",
    "addr:housenumber":"103",
    "addr:postcode":"1160",
    "addr:street":"Rue J. Bassem;/",
    "iso:country":"BE",
    "sg:address":"Rue J. Bassem 103",
    "sg:city":"Oudergem/auderghem",
    "sg:orig_category":"Herstellingen and onderhoud van auto's",
    "sg:phone":"+32 2 660 90 44",
    "sg:postcode":"1160",
    "sg:province":"Bruxelles-Capitale",
    "wof:name":"Boucher Ets- Looping",
    "wof:placetype":"venue"
},
  "geometry": {"coordinates":[4.428771019,50.8130569458],"type":"Point"}
}