{
  "type": "Feature",
  "properties": {
    "addr:full":"Leli\u00cbnlei 28b2 Lier Antwerpen 2500",
    "addr:housenumber":"28b2",
    "addr:postcode":"2500",
    "addr:street":"Lelie\u0308Nlei",
    "iso:country":"BE",
    "sg:address":"Leli\u00cbnlei 28b2",
    "sg:city":"Lier",
    "sg:orig_category":"Woningbouw",
    "sg:phone":"+32 3 422 56 25",
    "sg:postcode":"2500",
    "sg:province":"Antwerpen",
    "wof:name":"Peter Fleurbay",
    "wof:placetype":"venue"
},
  "geometry": {"coordinates":[4.6102480888,51.1031227112],"type":"Point"}
}