{
  "type": "Feature",
  "properties": {
    "addr:full":"Rue Des Tanneurs 80 Bruxelles Bruxelles-Capitale 1000",
    "addr:housenumber":"80",
    "addr:postcode":"1000",
    "addr:street":"Rue Des Tanneurs",
    "iso:country":"BE",
    "sg:address":"Rue Des Tanneurs 80",
    "sg:city":"Bruxelles",
    "sg:classifiers":[
        {
            "category":"Retail",
            "subcategory":"Event Space",
            "type":"Services"
        }
    ],
    "sg:phone":"+32 2 502 70 40",
    "sg:postcode":"1000",
    "sg:province":"Bruxelles-Capitale",
    "sg:tags":[
        "organisation"
    ],
    "wof:name":"Bakelite.tv",
    "wof:placetype":"venue"
},
  "geometry": {"coordinates":[4.3463191986,50.8392295837],"type":"Point"}
}