{
  "type": "Feature",
  "properties": {
    "addr:full":"Hogenhovestraat 61a Tielt (aarsele) West-Vlaanderen 8700",
    "addr:housenumber":"61a",
    "addr:postcode":"8700",
    "addr:street":"Hogenhovestraat",
    "iso:country":"BE",
    "sg:address":"Hogenhovestraat 61a",
    "sg:city":"Tielt (aarsele)",
    "sg:classifiers":[
        {
            "category":"Ferry",
            "type":"Transportation"
        }
    ],
    "sg:phone":"+32 51 63 58 00",
    "sg:postcode":"8700",
    "sg:province":"West-Vlaanderen",
    "sg:tags":[
        "whirlpool"
    ],
    "wof:name":"Sauna Design Bvba",
    "wof:placetype":"venue"
},
  "geometry": {"coordinates":[3.418555975,50.9856987],"type":"Point"}
}