{
  "type": "Feature",
  "properties": {
    "iso:country":"BE",
    "sg:address":"Passendaleplaats 11",
    "sg:city":"Zonnebeke (passendale)",
    "sg:classifiers":[
        {
            "category":"Building & Trades",
            "subcategory":"Pest Control",
            "type":"Services"
        }
    ],
    "sg:phone":"+32 51 77 82 46",
    "sg:postcode":"8980",
    "sg:province":"West-Vlaanderen",
    "sg:tags":[
        "painting",
        "contractor"
    ],
    "wof:name":"Vangheluwe H",
    "wof:placetype":"venue"
},
  "geometry": {"coordinates":[3.0017089844,50.8766555786],"type":"Point"}
}