{
  "type": "Feature",
  "properties": {
    "addr:full":"Hoogstraat 72 Mechelen Antwerpen 2800",
    "addr:housenumber":"72",
    "addr:postcode":"2800",
    "addr:street":"Hoogstraat",
    "iso:country":"BE",
    "sg:address":"Hoogstraat 72",
    "sg:city":"Mechelen",
    "sg:classifiers":[
        {
            "category":"Personal",
            "subcategory":"Beauty Salon",
            "type":"Services"
        }
    ],
    "sg:phone":"+32 15 41 87 48",
    "sg:postcode":"2800",
    "sg:province":"Antwerpen",
    "sg:tags":[
        "lady",
        "-",
        "hairdressing"
    ],
    "wof:name":"Anja",
    "wof:placetype":"venue"
},
  "geometry": {"coordinates":[4.4741210938,51.0224113464],"type":"Point"}
}