{
  "type": "Feature",
  "properties": {
    "iso:country":"BE",
    "sg:address":"Wijnegemsteenweg 2",
    "sg:city":"Schilde ('s Gravenwezel)",
    "sg:orig_category":"Non-Classified Establishments",
    "sg:phone":"+32 3 685 17 80",
    "sg:postcode":"2970",
    "sg:province":"Antwerpen",
    "wof:name":"Trade Fashion Nv",
    "wof:placetype":"venue"
},
  "geometry": {"coordinates":[4.5511140823,51.2631034851],"type":"Point"}
}