{
  "type": "Feature",
  "properties": {
    "addr:full":"Rue Maghin 65 Li\u00e8ge 1 Li\u00e8ge 4000",
    "addr:housenumber":"65;1",
    "addr:postcode":"4000",
    "addr:street":"Rue Maghin",
    "iso:country":"BE",
    "sg:address":"Rue Maghin 65",
    "sg:city":"Li\u00e8ge 1",
    "sg:classifiers":[
        {
            "category":"Professional",
            "subcategory":"Lawyer & Legal Services",
            "type":"Services"
        }
    ],
    "sg:phone":"+32 4 227 77 27",
    "sg:postcode":"4000",
    "sg:province":"Li\u00e8ge",
    "sg:tags":[
        "notary"
    ],
    "wof:name":"Glineur M-j",
    "wof:placetype":"venue"
},
  "geometry": {"coordinates":[5.5874090195,50.6504173279],"type":"Point"}
}