{
  "type": "Feature",
  "properties": {
    "iso:country":"BE",
    "sg:address":"Paddepoelstraat 11",
    "sg:city":"Ieper",
    "sg:orig_category":"Gespecialiseerde residenti\u00eble bouw",
    "sg:phone":"+32 57 20 36 78",
    "sg:postcode":"8900",
    "sg:province":"West-Vlaanderen",
    "wof:name":"Tom Parmentier",
    "wof:placetype":"venue"
},
  "geometry": {"coordinates":[2.8899989128,50.8484649658],"type":"Point"}
}