{
  "type": "Feature",
  "properties": {
    "addr:full":"Bosduivenlaan 15 Kraainem Vlaams-Brabant 1950",
    "addr:housenumber":"15",
    "addr:postcode":"1950",
    "addr:street":"Bosduivenlaan",
    "iso:country":"BE",
    "sg:address":"Bosduivenlaan 15",
    "sg:city":"Kraainem",
    "sg:orig_category":"Artsen and specialisten",
    "sg:phone":"+32 2 731 28 40",
    "sg:postcode":"1950",
    "sg:province":"Vlaams-Brabant",
    "wof:name":"J. Gobeaux",
    "wof:placetype":"venue"
},
  "geometry": {"coordinates":[4.4764480591,50.8317565918],"type":"Point"}
}