{
  "type": "Feature",
  "properties": {
    "addr:full":"Avenue De For\u00cat De Soignes 328 Sint-genesius-rode/rhode-saint-genese Vlaams-Brabant 1640",
    "addr:housenumber":"328",
    "addr:postcode":"1640",
    "addr:street":"Avenue De Fore\u0302T De Soignes",
    "iso:country":"BE",
    "sg:address":"Avenue De For\u00cat De Soignes 328",
    "sg:city":"Sint-genesius-rode/rhode-saint-genese",
    "sg:orig_category":"Opticiens",
    "sg:phone":"+32 2 358 43 60",
    "sg:postcode":"1640",
    "sg:province":"Vlaams-Brabant",
    "wof:name":"Green Optic",
    "wof:placetype":"venue"
},
  "geometry": {"coordinates":[4.3806738853,50.7574462891],"type":"Point"}
}