{
  "type": "Feature",
  "properties": {
    "addr:full":"Martelarenstraat 52 Aarschot Vlaams-Brabant 3200",
    "addr:housenumber":"52",
    "addr:postcode":"3200",
    "addr:street":"Martelarenstraat",
    "iso:country":"BE",
    "sg:address":"Martelarenstraat 52",
    "sg:city":"Aarschot",
    "sg:orig_category":"Warenhuizen",
    "sg:phone":"+32 16 56 62 11",
    "sg:postcode":"3200",
    "sg:province":"Vlaams-Brabant",
    "wof:name":"Bazar Verlinden",
    "wof:placetype":"venue"
},
  "geometry": {"coordinates":[4.833987236,50.9842605591],"type":"Point"}
}