{
  "type": "Feature",
  "properties": {
    "addr:full":"Melkstraat 91a Machelen Vlaams-Brabant 1830",
    "addr:housenumber":"91a",
    "addr:postcode":"1830",
    "addr:street":"Melkstraat",
    "iso:country":"BE",
    "sg:address":"Melkstraat 91a",
    "sg:city":"Machelen",
    "sg:orig_category":"Agences immobili\u00e8res",
    "sg:phone":"+32 2 253 20 05",
    "sg:postcode":"1830",
    "sg:province":"Vlaams-Brabant",
    "wof:name":"Foreign Relocation Service",
    "wof:placetype":"venue"
},
  "geometry": {"coordinates":[4.4364762306,50.9055328369],"type":"Point"}
}