{
  "type": "Feature",
  "properties": {
    "iso:country":"BE",
    "sg:address":"Maria Ter-heidelaan 7a",
    "sg:city":"Tremelo",
    "sg:classifiers":[
        {
            "category":"Wholesale",
            "subcategory":"Chemicals & Plastics",
            "type":"Manufacturing & Wholesale Goods"
        }
    ],
    "sg:phone":"+32 16 53 16 92",
    "sg:postcode":"3120",
    "sg:province":"Vlaams-Brabant",
    "sg:tags":[
        "packing"
    ],
    "wof:name":"Flex Film",
    "wof:placetype":"venue"
},
  "geometry": {"coordinates":[4.7225041389,50.9958114624],"type":"Point"}
}