{
  "type": "Feature",
  "properties": {
    "iso:country":"BE",
    "sg:address":"Rue Herman 25",
    "sg:city":"Saint-hubert",
    "sg:classifiers":[
        {
            "category":"Personal",
            "subcategory":"Beauty Salon",
            "type":"Services"
        }
    ],
    "sg:phone":"+32 61 61 27 68",
    "sg:postcode":"6870",
    "sg:province":"Luxembourg",
    "sg:tags":[
        "de",
        "coiffure"
    ],
    "wof:name":"Brolet",
    "wof:placetype":"venue"
},
  "geometry": {"coordinates":[5.3753628731,50.0255584717],"type":"Point"}
}