{
  "type": "Feature",
  "properties": {
    "iso:country":"BE",
    "sg:address":"Gelderhorsten 167",
    "sg:city":"Lommel",
    "sg:orig_category":"Animaux domestiques and accessoires",
    "sg:phone":"+32 11 55 13 59",
    "sg:postcode":"3920",
    "sg:province":"Limburg",
    "wof:name":"'t Schuurke",
    "wof:placetype":"venue"
},
  "geometry": {"coordinates":[5.2732639313,51.1836585999],"type":"Point"}
}