{
  "type": "Feature",
  "properties": {
    "addr:full":"Grote Markt 2 Aalst Oost-Vlaanderen 9300",
    "addr:housenumber":"2",
    "addr:postcode":"9300",
    "addr:street":"Grote Markt",
    "iso:country":"BE",
    "sg:address":"Grote Markt 2",
    "sg:city":"Aalst",
    "sg:orig_category":"Diverse kredietdiensten",
    "sg:postcode":"9300",
    "sg:province":"Oost-Vlaanderen",
    "wof:name":"Bancontact-mister Cash",
    "wof:placetype":"venue"
},
  "geometry": {"coordinates":[4.0379910469,50.938167572],"type":"Point"}
}