{
  "type": "Feature",
  "properties": {
    "iso:country":"BE",
    "sg:address":"Bremlaan 68",
    "sg:city":"Knokke-heist",
    "sg:orig_category":"Beautyfarms, relaxatie and lichamelijk welzijn Schoonheidssalons",
    "sg:phone":"+32 50 60 88 37",
    "sg:postcode":"8300",
    "sg:province":"West-Vlaanderen",
    "wof:name":"Pedicure Marie-c\u00c9cile",
    "wof:placetype":"venue"
},
  "geometry": {"coordinates":[3.3042359352,51.3361473083],"type":"Point"}
}