{
  "type": "Feature",
  "properties": {
    "iso:country":"BE",
    "sg:address":"Vuurkruisenlaan 301",
    "sg:city":"Brussel/bruxelles",
    "sg:classifiers":[
        {
            "category":"Insurance",
            "subcategory":"Insurance Agent",
            "type":"Services"
        }
    ],
    "sg:phone":"+32 2 268 26 03",
    "sg:postcode":"1020",
    "sg:province":"Bruxelles-Capitale",
    "sg:tags":[
        "verzekeringsmakelaars",
        "expert"
    ],
    "wof:name":"S. Poncin",
    "wof:placetype":"venue"
},
  "geometry": {"coordinates":[4.3588218689,50.8951301575],"type":"Point"}
}