{
  "type": "Feature",
  "properties": {
    "iso:country":"BE",
    "sg:address":"Avenue Des Tilleuls 2",
    "sg:city":"Li\u00e8ge 1",
    "sg:classifiers":[
        {
            "category":"Professional",
            "subcategory":"Art Services",
            "type":"Services"
        }
    ],
    "sg:phone":"+32 4 252 63 70",
    "sg:postcode":"4000",
    "sg:province":"Li\u00e8ge",
    "sg:tags":[
        "designer",
        "display"
    ],
    "wof:name":"Gualda Rodriguez J",
    "wof:placetype":"venue"
},
  "geometry": {"coordinates":[5.5778870583,50.6169471741],"type":"Point"}
}