{
  "type": "Feature",
  "properties": {
    "addr:full":"Chauss\u00c9e De Nivelles 196 Charleroi Hainaut 6041",
    "addr:housenumber":"196",
    "addr:postcode":"6041",
    "addr:street":"Chausse\u0301E De Nivelles;Hainaut",
    "iso:country":"BE",
    "sg:address":"Chauss\u00c9e De Nivelles 196",
    "sg:city":"Charleroi",
    "sg:orig_category":"Agences d'exp\u00e9dition",
    "sg:phone":"+32 71 30 21 78",
    "sg:postcode":"6041",
    "sg:province":"Hainaut",
    "wof:name":"Van Calytex",
    "wof:placetype":"venue"
},
  "geometry": {"coordinates":[4.4314317703,50.4685935974],"type":"Point"}
}