{
  "type": "Feature",
  "properties": {
    "addr:full":"Oedelemse Steenweg 62 Damme West-Vlaanderen 8340",
    "addr:housenumber":"62",
    "addr:postcode":"8340",
    "addr:street":"Steenweg",
    "iso:country":"BE",
    "sg:address":"Oedelemse Steenweg 62",
    "sg:city":"Damme",
    "sg:classifiers":[
        {
            "category":"Food & Beverages",
            "subcategory":"Fruits & Vegetables",
            "type":"Retail Goods"
        }
    ],
    "sg:phone":"+32 50 36 36 22",
    "sg:postcode":"8340",
    "sg:province":"West-Vlaanderen",
    "sg:tags":[
        "l\u00e9gumes"
    ],
    "wof:name":"Anne Aneca",
    "wof:placetype":"venue"
},
  "geometry": {"coordinates":[3.3293540478,51.1964225769],"type":"Point"}
}