{
  "type": "Feature",
  "properties": {
    "addr:full":"Rue Du Centre 50 Chastre (chastre-villeroux-blanmont) Brabant Wallon 1450",
    "addr:housenumber":"50",
    "addr:postcode":"1450",
    "addr:street":"Rue Du Centre;Wallon",
    "iso:country":"BE",
    "sg:address":"Rue Du Centre 50",
    "sg:city":"Chastre (chastre-villeroux-blanmont)",
    "sg:classifiers":[
        {
            "category":"Retail",
            "subcategory":"Veterinary Services",
            "type":"Services"
        }
    ],
    "sg:phone":"+32 10 65 92 01",
    "sg:postcode":"1450",
    "sg:province":"Brabant Wallon",
    "sg:tags":[
        "veterinarian"
    ],
    "wof:name":"Denis B",
    "wof:placetype":"venue"
},
  "geometry": {"coordinates":[4.6363787651,50.6083564758],"type":"Point"}
}