{
  "type": "Feature",
  "properties": {
    "addr:full":"Westrozebekestraat 23 Zonnebeke (passendale) West-Vlaanderen 8980",
    "addr:housenumber":"23",
    "addr:postcode":"8980",
    "addr:street":"Westrozebekestraat",
    "iso:country":"BE",
    "sg:address":"Westrozebekestraat 23",
    "sg:city":"Zonnebeke (passendale)",
    "sg:classifiers":[
        {
            "category":"Retail",
            "subcategory":"Veterinary Services",
            "type":"Services"
        }
    ],
    "sg:phone":"+32 51 77 81 19",
    "sg:postcode":"8980",
    "sg:province":"West-Vlaanderen",
    "sg:tags":[
        "veterinarian"
    ],
    "wof:name":"Vandaele G",
    "wof:placetype":"venue"
},
  "geometry": {"coordinates":[2.9872550964,50.8730812073],"type":"Point"}
}