{
  "type": "Feature",
  "properties": {
    "addr:full":"Hansbrugweg 27 Haacht Vlaams-Brabant 3150",
    "addr:housenumber":"27",
    "addr:postcode":"3150",
    "addr:street":"Hansbrugweg",
    "iso:country":"BE",
    "sg:address":"Hansbrugweg 27",
    "sg:city":"Haacht",
    "sg:orig_category":"Agences d'exp\u00e9dition",
    "sg:phone":"+32 16 60 64 13",
    "sg:postcode":"3150",
    "sg:province":"Vlaams-Brabant",
    "wof:name":"Link Business Consultancy",
    "wof:placetype":"venue"
},
  "geometry": {"coordinates":[4.6420860291,50.9857788086],"type":"Point"}
}