{
  "type": "Feature",
  "properties": {
    "iso:country":"BE",
    "sg:address":"Dreef 28",
    "sg:city":"Oosterzele",
    "sg:orig_category":"Herstelling leer and schoeisel",
    "sg:phone":"+32 9 362 65 32",
    "sg:postcode":"9860",
    "sg:province":"Oost-Vlaanderen",
    "wof:name":"Johan Raes",
    "wof:placetype":"venue"
},
  "geometry": {"coordinates":[3.7866799831,50.9450149536],"type":"Point"}
}