{
  "type": "Feature",
  "properties": {
    "addr:full":"Rue De Battice 134 Aubel Li\u00e8ge 4880",
    "addr:housenumber":"134",
    "addr:postcode":"4880",
    "addr:street":"Rue De Battice",
    "iso:country":"BE",
    "sg:address":"Rue De Battice 134",
    "sg:city":"Aubel",
    "sg:classifiers":[
        {
            "category":"Food & Beverages",
            "subcategory":"Fruits & Vegetables",
            "type":"Retail Goods"
        }
    ],
    "sg:phone":"+32 87 68 10 29",
    "sg:postcode":"4880",
    "sg:province":"Li\u00e8ge",
    "sg:tags":[
        "early",
        "season",
        "-"
    ],
    "wof:name":"Les Primeurs Aubeloises",
    "wof:placetype":"venue"
},
  "geometry": {"coordinates":[5.8543901443,50.6949996948],"type":"Point"}
}