{
  "type": "Feature",
  "properties": {
    "addr:full":". Bree (groot) Limburg 3960",
    "addr:postcode":"3960",
    "addr:street":"Bree Groot Limburg",
    "iso:country":"BE",
    "sg:address":".",
    "sg:city":"Bree (groot)",
    "sg:orig_category":"Apotheken",
    "sg:phone":"+32 900 10 500",
    "sg:postcode":"3960",
    "sg:province":"Limburg",
    "wof:name":"Apothekers Van Wacht",
    "wof:placetype":"venue"
},
  "geometry": {"coordinates":[5.5944190025,51.1405677795],"type":"Point"}
}