{
  "type": "Feature",
  "properties": {
    "iso:country":"BE",
    "sg:address":"Rue De La Tasni\u00c8re 83 A",
    "sg:city":"Rixensart",
    "sg:orig_category":"Installation de menuiserie m\u00e9tallique. Vitrage. Installation de menuiserie en bois and plastique. In",
    "sg:phone":"+32 2 652 40 40",
    "sg:postcode":"1332",
    "sg:province":"Brabant Wallon",
    "wof:name":"Batiglass",
    "wof:placetype":"venue"
},
  "geometry": {"coordinates":[4.5072040558,50.7289810181],"type":"Point"}
}