{
  "type": "Feature",
  "properties": {
    "addr:full":"Avenue Des Thermes 66 Chaudfontaine Li\u00e8ge 4050",
    "addr:housenumber":"66",
    "addr:postcode":"4050",
    "addr:street":"Avenue Des Thermes",
    "iso:country":"BE",
    "sg:address":"Avenue Des Thermes 66",
    "sg:city":"Chaudfontaine",
    "sg:orig_category":"Fast food and meeneem restaurants Restaurants Ruimtes voor conferenties, recepties and feesten",
    "sg:phone":"+32 4 366 10 58",
    "sg:postcode":"4050",
    "sg:province":"Li\u00e8ge",
    "wof:name":"China Garden",
    "wof:placetype":"venue"
},
  "geometry": {"coordinates":[5.6409401894,50.5862083435],"type":"Point"}
}