{
  "type": "Feature",
  "properties": {
    "addr:full":"Paddegatstraat 97 Kapelle-op-den-bos (nieuwenrode) Vlaams-Brabant 1880",
    "addr:housenumber":"97",
    "addr:postcode":"1880",
    "addr:street":"Paddegatstraat",
    "iso:country":"BE",
    "sg:address":"Paddegatstraat 97",
    "sg:city":"Kapelle-op-den-bos (nieuwenrode)",
    "sg:classifiers":[
        {
            "category":"Health Services",
            "subcategory":"Health Practitioner",
            "type":"Services"
        }
    ],
    "sg:phone":"+32 15 71 34 32",
    "sg:postcode":"1880",
    "sg:province":"Vlaams-Brabant",
    "sg:tags":[
        "physiotherapist"
    ],
    "wof:name":"Van Den Brande Ann",
    "wof:placetype":"venue"
},
  "geometry": {"coordinates":[4.350566864,50.9805297852],"type":"Point"}
}