{
  "type": "Feature",
  "properties": {
    "addr:full":"Place Elie Delferri\u00e8re 6-7 Charleroi Hainaut 6000",
    "addr:housenumber":"6-7",
    "addr:postcode":"6000",
    "addr:street":"Place Elie Delferrie\u0300Re;Hainaut",
    "iso:country":"BE",
    "sg:address":"Place Elie Delferri\u00e8re 6-7",
    "sg:city":"Charleroi",
    "sg:classifiers":[
        {
            "category":"Professional",
            "subcategory":"Credit Reporting & Collection",
            "type":"Services"
        }
    ],
    "sg:phone":"+32 71 41 74 56",
    "sg:postcode":"6000",
    "sg:province":"Hainaut",
    "sg:tags":[
        "bailiff"
    ],
    "wof:name":"Deffernez A-m",
    "wof:placetype":"venue"
},
  "geometry": {"coordinates":[4.4523940086,50.4216995239],"type":"Point"}
}