{
  "type": "Feature",
  "properties": {
    "addr:full":"Koningin Astridlaan 5 Borgloon Limburg 3840",
    "addr:housenumber":"5",
    "addr:postcode":"3840",
    "addr:street":"Koningin Astridlaan",
    "iso:country":"BE",
    "sg:address":"Koningin Astridlaan 5",
    "sg:city":"Borgloon",
    "sg:orig_category":"Banques and organismes de cr\u00e9dit",
    "sg:phone":"+32 12 67 06 96",
    "sg:postcode":"3840",
    "sg:province":"Limburg",
    "wof:name":"Requil\u00c9 En Leten",
    "wof:placetype":"venue"
},
  "geometry": {"coordinates":[5.34065485,50.8065185547],"type":"Point"}
}