{
  "type": "Feature",
  "properties": {
    "iso:country":"BE",
    "sg:address":"Prinsenstraat 26",
    "sg:city":"Grimbergen",
    "sg:orig_category":"Toeristische diensten",
    "sg:phone":"+32 2 260 12 58",
    "sg:postcode":"1850",
    "sg:province":"Vlaams-Brabant",
    "wof:name":"Dienst Voor Toerisme Grimbergen",
    "wof:placetype":"venue"
},
  "geometry": {"coordinates":[4.3716249466,50.9321403503],"type":"Point"}
}