{
  "type": "Feature",
  "properties": {
    "addr:full":"Rue Du Commerce 30 Verviers Li\u00e8ge 4800",
    "addr:housenumber":"30",
    "addr:postcode":"4800",
    "addr:street":"Rue Du Commerce",
    "iso:country":"BE",
    "sg:address":"Rue Du Commerce 30",
    "sg:city":"Verviers",
    "sg:classifiers":[
        {
            "category":"Cafe",
            "type":"Food & Drink"
        }
    ],
    "sg:phone":"+32 87 35 04 53",
    "sg:postcode":"4800",
    "sg:province":"Li\u00e8ge",
    "sg:tags":[
        "caf\u00e9s"
    ],
    "wof:name":"Ay Yildiz",
    "wof:placetype":"venue"
},
  "geometry": {"coordinates":[5.8594508171,50.5917663574],"type":"Point"}
}