{
  "type": "Feature",
  "properties": {
    "addr:full":"Hauptstrasse 64 Sankt Vith Li\u00e8ge 4780",
    "addr:housenumber":"64",
    "addr:postcode":"4780",
    "addr:street":"Hauptstrasse",
    "iso:country":"BE",
    "sg:address":"Hauptstrasse 64",
    "sg:city":"Sankt Vith",
    "sg:classifiers":[
        {
            "category":"Shopping",
            "subcategory":"Optician",
            "type":"Retail Goods"
        }
    ],
    "sg:phone":"+32 80 39 98 86",
    "sg:postcode":"4780",
    "sg:province":"Li\u00e8ge",
    "sg:tags":[
        "-"
    ],
    "wof:name":"Belle Optik",
    "wof:placetype":"venue"
},
  "geometry": {"coordinates":[6.1258130074,50.2812080383],"type":"Point"}
}