{
  "type": "Feature",
  "properties": {
    "addr:full":"Doorstraat 18 Nieuwerkerken Limburg 3850",
    "addr:housenumber":"18",
    "addr:postcode":"3850",
    "addr:street":"Doorstraat",
    "iso:country":"BE",
    "sg:address":"Doorstraat 18",
    "sg:city":"Nieuwerkerken",
    "sg:orig_category":"Producteurs de fruits",
    "sg:phone":"+32 11 31 46 24",
    "sg:postcode":"3850",
    "sg:province":"Limburg",
    "wof:name":"Marina Droogmans",
    "wof:placetype":"venue"
},
  "geometry": {"coordinates":[5.2336349487,50.8816642761],"type":"Point"}
}