{
  "type": "Feature",
  "properties": {
    "iso:country":"BE",
    "sg:address":"Chauss\u00c9e D'hondzocht 56",
    "sg:city":"Tubize",
    "sg:orig_category":"Catering and organisatie van feesten Slagers Voedingsspeciaalzaken",
    "sg:phone":"+32 2 355 78 48",
    "sg:postcode":"1480",
    "sg:province":"Brabant Wallon",
    "wof:name":"Boucherie Freddy",
    "wof:placetype":"venue"
},
  "geometry": {"coordinates":[4.202521801,50.6974029541],"type":"Point"}
}