{
  "type": "Feature",
  "properties": {
    "iso:country":"BE",
    "sg:address":"Kroonlaan 340",
    "sg:city":"Elsene/ixelles",
    "sg:orig_category":"Advocaten and juridische adviseurs",
    "sg:phone":"+32 2 649 94 94",
    "sg:postcode":"1050",
    "sg:province":"Bruxelles-Capitale",
    "wof:name":"J. Vanden Eynde",
    "wof:placetype":"venue"
},
  "geometry": {"coordinates":[4.3865990639,50.8238792419],"type":"Point"}
}