{
  "type": "Feature",
  "properties": {
    "addr:full":"Rue Saint-medard 17 Erquelinnes Hainaut 6560",
    "addr:housenumber":"17",
    "addr:postcode":"6560",
    "addr:street":"Rue Saint-Medard",
    "iso:country":"BE",
    "sg:address":"Rue Saint-medard 17",
    "sg:city":"Erquelinnes",
    "sg:classifiers":[
        {
            "category":"Cafe",
            "type":"Food & Drink"
        }
    ],
    "sg:phone":"+32 71 55 78 40",
    "sg:postcode":"6560",
    "sg:province":"Hainaut",
    "sg:tags":[
        "caf\u00e9s"
    ],
    "wof:name":"Caf\u00c9 Le Commerce",
    "wof:placetype":"venue"
},
  "geometry": {"coordinates":[4.1517729759,50.3087425232],"type":"Point"}
}