{
  "type": "Feature",
  "properties": {
    "addr:full":"Biezenhoek 18 Lille (poederlee) Antwerpen 2275",
    "addr:housenumber":"18",
    "addr:postcode":"2275",
    "addr:street":"Biezenhoek",
    "iso:country":"BE",
    "sg:address":"Biezenhoek 18",
    "sg:city":"Lille (poederlee)",
    "sg:classifiers":[
        {
            "category":"Utilities",
            "subcategory":"Natural Gas",
            "type":"Services"
        }
    ],
    "sg:phone":"+32 477 86 21 08",
    "sg:postcode":"2275",
    "sg:province":"Antwerpen",
    "sg:tags":[
        "welding"
    ],
    "wof:name":"Raeymakers N",
    "wof:placetype":"venue"
},
  "geometry": {"coordinates":[4.8373122215,51.2302246094],"type":"Point"}
}