{
  "type": "Feature",
  "properties": {
    "addr:full":"Rue Comhaire 39 Li\u00c8ge Li\u00e8ge 4000",
    "addr:housenumber":"39",
    "addr:postcode":"4000",
    "addr:street":"Rue Comhaire",
    "iso:country":"BE",
    "sg:address":"Rue Comhaire 39",
    "sg:city":"Li\u00c8ge",
    "sg:orig_category":"M\u00e9decins and sp\u00e9cialistes",
    "sg:phone":"+32 4 253 23 23",
    "sg:postcode":"4000",
    "sg:province":"Li\u00e8ge",
    "wof:name":"Jean-paul Harroy",
    "wof:placetype":"venue"
},
  "geometry": {"coordinates":[5.5545902252,50.630897522],"type":"Point"}
}