{
  "type": "Feature",
  "properties": {
    "iso:country":"BE",
    "sg:address":"Leopold Iii-straat 10b",
    "sg:city":"Kortessem (vliermaal)",
    "sg:classifiers":[
        {
            "category":"Personal",
            "subcategory":"Beauty Salon",
            "type":"Services"
        }
    ],
    "sg:phone":"+32 12 26 38 23",
    "sg:postcode":"3724",
    "sg:province":"Limburg",
    "sg:tags":[
        "lady",
        "-",
        "hairdressing"
    ],
    "wof:name":"Heidi",
    "wof:placetype":"venue"
},
  "geometry": {"coordinates":[5.4292058945,50.8398742676],"type":"Point"}
}