{
  "type": "Feature",
  "properties": {
    "addr:full":"Steenstraat 27 Kortrijk West-Vlaanderen 8501",
    "addr:housenumber":"27",
    "addr:postcode":"8501",
    "addr:street":"Steenstraat",
    "iso:country":"BE",
    "sg:address":"Steenstraat 27",
    "sg:city":"Kortrijk",
    "sg:orig_category":"Sportclubs",
    "sg:phone":"+32 56 35 25 06",
    "sg:postcode":"8501",
    "sg:province":"West-Vlaanderen",
    "wof:name":"P.c. Kortrijk",
    "wof:placetype":"venue"
},
  "geometry": {"coordinates":[3.2279500961,50.8455085754],"type":"Point"}
}