{
  "type": "Feature",
  "properties": {
    "addr:full":"Pannenhuisstraat 57 Ieper West-Vlaanderen 8900",
    "addr:housenumber":"57",
    "addr:postcode":"8900",
    "addr:street":"Pannenhuisstraat",
    "iso:country":"BE",
    "sg:address":"Pannenhuisstraat 57",
    "sg:city":"Ieper",
    "sg:orig_category":"Rundveehouders",
    "sg:phone":"+32 57 20 24 05",
    "sg:postcode":"8900",
    "sg:province":"West-Vlaanderen",
    "wof:name":"Etienne Verdonck",
    "wof:placetype":"venue"
},
  "geometry": {"coordinates":[2.8698499203,50.8348922729],"type":"Point"}
}