{
  "type": "Feature",
  "properties": {
    "addr:full":"Rue De Ten-brielen 160 Komen-waasten/comines-warneton Hainaut 7780",
    "addr:housenumber":"160;7780",
    "addr:street":"Rue De Ten-Brielen",
    "iso:country":"BE",
    "sg:address":"Rue De Ten-brielen 160",
    "sg:city":"Komen-waasten/comines-warneton",
    "sg:orig_category":"Maisons de repos and r\u00e9sidences",
    "sg:phone":"+32 56 55 50 90",
    "sg:postcode":"7780",
    "sg:province":"Hainaut",
    "wof:name":"Home Paul Demade",
    "wof:placetype":"venue"
},
  "geometry": {"coordinates":[2.9967899323,50.7743797302],"type":"Point"}
}