{
  "type": "Feature",
  "properties": {
    "addr:full":"Cours Du Cramignon 22 Ottignies-louvain-la-neuve (louvain-la-neuve) Brabant Wallon 1348",
    "addr:housenumber":"22",
    "addr:postcode":"1348",
    "addr:street":"Cours Du Cramignon",
    "iso:country":"BE",
    "sg:address":"Cours Du Cramignon 22",
    "sg:city":"Ottignies-louvain-la-neuve (louvain-la-neuve)",
    "sg:classifiers":[
        {
            "category":"Wholesale",
            "subcategory":"Tobacco Products",
            "type":"Manufacturing & Wholesale Goods"
        }
    ],
    "sg:phone":"+32 10 45 06 22",
    "sg:postcode":"1348",
    "sg:province":"Brabant Wallon",
    "sg:tags":[
        "-",
        "biotechnology",
        "installation",
        "equipment"
    ],
    "wof:name":"Trigone",
    "wof:placetype":"venue"
},
  "geometry": {"coordinates":[4.6135020256,50.6728286743],"type":"Point"}
}