{
  "type": "Feature",
  "properties": {
    "addr:full":"Rue De Gesves 182 Ohey Namur 5350",
    "addr:housenumber":"182",
    "addr:postcode":"5350",
    "addr:street":"Rue De Gesves",
    "iso:country":"BE",
    "sg:address":"Rue De Gesves 182",
    "sg:city":"Ohey",
    "sg:orig_category":"HUISBRANDOLIE",
    "sg:phone":"+32 85 61 11 47",
    "sg:postcode":"5350",
    "sg:province":"Namur",
    "wof:name":"Guiot Ph. & Fils",
    "wof:placetype":"venue"
},
  "geometry": {"coordinates":[5.1248660088,50.4292259216],"type":"Point"}
}