{
  "type": "Feature",
  "properties": {
    "addr:full":"Chauss\u00e9e De Louvain 615 Bruxelles (schaerbeek) Bruxelles-Capitale 1030",
    "addr:housenumber":"615",
    "addr:postcode":"1030",
    "addr:street":"Chausse\u0301E De Louvain",
    "iso:country":"BE",
    "sg:address":"Chauss\u00e9e De Louvain 615",
    "sg:city":"Bruxelles (schaerbeek)",
    "sg:classifiers":[
        {
            "category":"Professional",
            "subcategory":"Computer Services",
            "type":"Services"
        }
    ],
    "sg:phone":"+32 2 733 36 12",
    "sg:postcode":"1030",
    "sg:province":"Bruxelles-Capitale",
    "sg:tags":[
        "-",
        "processing",
        "data",
        "software"
    ],
    "wof:name":"Buildtech Sprl",
    "wof:placetype":"venue"
},
  "geometry": {"coordinates":[4.4042677879,50.8566589355],"type":"Point"}
}