{
  "type": "Feature",
  "properties": {
    "addr:full":"Avenue Voltaire 88 Bruxelles (schaerbeek) Bruxelles-Capitale 1030",
    "addr:housenumber":"88",
    "addr:postcode":"1030",
    "addr:street":"Avenue Voltaire",
    "iso:country":"BE",
    "sg:address":"Avenue Voltaire 88",
    "sg:city":"Bruxelles (schaerbeek)",
    "sg:orig_category":"Solar protection - Inside",
    "sg:phone":"+32 2 215 00 49",
    "sg:postcode":"1030",
    "sg:province":"Bruxelles-Capitale",
    "wof:name":"Jiv\u00e9 D\u00e9cor Sprl",
    "wof:placetype":"venue"
},
  "geometry": {"coordinates":[4.3787941933,50.8695487976],"type":"Point"}
}