{
  "type": "Feature",
  "properties": {
    "iso:country":"BE",
    "sg:address":"Rooberg 44",
    "sg:city":"Oosterzele",
    "sg:orig_category":"Woningbouw",
    "sg:phone":"+32 9 362 12 19",
    "sg:postcode":"9860",
    "sg:province":"Oost-Vlaanderen",
    "wof:name":"Marc Lammens",
    "wof:placetype":"venue"
},
  "geometry": {"coordinates":[3.8038170338,50.963886261],"type":"Point"}
}