{
  "type": "Feature",
  "properties": {
    "iso:country":"BE",
    "sg:address":"Rue De La Madeleine 55",
    "sg:city":"Charleroi",
    "sg:classifiers":[
        {
            "category":"Professional",
            "subcategory":"Accounting & Tax Preparation",
            "type":"Services"
        }
    ],
    "sg:phone":"+32 71 35 17 04",
    "sg:postcode":"6040",
    "sg:province":"Hainaut",
    "sg:tags":[
        "accountant"
    ],
    "wof:name":"Franz Remson",
    "wof:placetype":"venue"
},
  "geometry": {"coordinates":[4.4116740227,50.4421005249],"type":"Point"}
}