{
  "type": "Feature",
  "properties": {
    "iso:country":"BE",
    "sg:address":"Arthur Quintusstraat 19",
    "sg:city":"Sint-pieters-leeuw",
    "sg:orig_category":"Elektrische installaties voor woningen",
    "sg:phone":"+32 2 377 09 30",
    "sg:postcode":"1600",
    "sg:province":"Vlaams-Brabant",
    "wof:name":"Luc De Taeye",
    "wof:placetype":"venue"
},
  "geometry": {"coordinates":[4.2771668434,50.790977478],"type":"Point"}
}