{
  "type": "Feature",
  "properties": {
    "iso:country":"BE",
    "sg:address":"Rue De Dour 65b",
    "sg:city":"Qui\u00e9vrain",
    "sg:classifiers":[
        {
            "category":"Social Services",
            "type":"Services"
        }
    ],
    "sg:phone":"+32 65 65 09 70",
    "sg:postcode":"7380",
    "sg:province":"Hainaut",
    "wof:name":"Foyer Quievrainois",
    "wof:placetype":"venue"
},
  "geometry": {"coordinates":[3.6914429665,50.4069099426],"type":"Point"}
}