{
  "type": "Feature",
  "properties": {
    "iso:country":"BE",
    "sg:address":"Ferdinand Maesstraat 30",
    "sg:city":"Kontich (waarloos)",
    "sg:classifiers":[
        {
            "category":"Food & Beverages",
            "subcategory":"Chocolate",
            "type":"Retail Goods"
        }
    ],
    "sg:phone":"+32 15 32 19 93",
    "sg:postcode":"2550",
    "sg:province":"Antwerpen",
    "sg:tags":[
        "confectionery",
        "-"
    ],
    "wof:name":"Elly",
    "wof:placetype":"venue"
},
  "geometry": {"coordinates":[4.4527659416,51.1065673828],"type":"Point"}
}