{
  "type": "Feature",
  "properties": {
    "iso:country":"BE",
    "sg:address":"Rue Du Pont 9",
    "sg:city":"Hamoir",
    "sg:classifiers":[
        {
            "category":"Personal",
            "subcategory":"Beauty Salon",
            "type":"Services"
        }
    ],
    "sg:phone":"+32 86 38 80 51",
    "sg:postcode":"4180",
    "sg:province":"Li\u00e8ge",
    "sg:tags":[
        "lady",
        "-",
        "hairdressing"
    ],
    "wof:name":"Andr\u00e9 E",
    "wof:placetype":"venue"
},
  "geometry": {"coordinates":[5.5354552269,50.4256706238],"type":"Point"}
}