{
  "type": "Feature",
  "properties": {
    "addr:full":"Ledebaan 245b4 Aalst Oost-Vlaanderen 9300",
    "addr:housenumber":"245b4",
    "addr:postcode":"9300",
    "addr:street":"Ledebaan",
    "iso:country":"BE",
    "sg:address":"Ledebaan 245b4",
    "sg:city":"Aalst",
    "sg:orig_category":"Woningbouw",
    "sg:phone":"+32 53 77 33 85",
    "sg:postcode":"9300",
    "sg:province":"Oost-Vlaanderen",
    "wof:name":"Sabro",
    "wof:placetype":"venue"
},
  "geometry": {"coordinates":[4.0221772194,50.9499778748],"type":"Point"}
}