{
  "type": "Feature",
  "properties": {
    "addr:full":"Rue Yvonne Vieslet 2 Charleroi (monceau-sur-sambre) Hainaut 6031",
    "addr:housenumber":"2",
    "addr:postcode":"6031",
    "addr:street":"Rue Yvonne Vieslet",
    "iso:country":"BE",
    "sg:address":"Rue Yvonne Vieslet 2",
    "sg:city":"Charleroi (monceau-sur-sambre)",
    "sg:classifiers":[
        {
            "category":"Health Services",
            "subcategory":"Health Practitioner",
            "type":"Services"
        }
    ],
    "sg:phone":"+32 71 30 33 90",
    "sg:postcode":"6031",
    "sg:province":"Hainaut",
    "sg:tags":[
        "physiotherapist"
    ],
    "wof:name":"Navez A",
    "wof:placetype":"venue"
},
  "geometry": {"coordinates":[4.3982310295,50.4074630737],"type":"Point"}
}