{
  "type": "Feature",
  "properties": {
    "iso:country":"BE",
    "sg:address":"Bornedries 66",
    "sg:city":"Sint-truiden",
    "sg:classifiers":[
        {
            "category":"Arena",
            "subcategory":"Sports Club",
            "type":"Entertainment"
        }
    ],
    "sg:phone":"+32 11 58 75 59",
    "sg:postcode":"3800",
    "sg:province":"Limburg",
    "sg:tags":[
        "terrain",
        "hors",
        "de",
        "installation",
        "sportifs"
    ],
    "wof:name":"Psv Melveren-bornedries",
    "wof:placetype":"venue"
},
  "geometry": {"coordinates":[5.1979861259,50.8452758789],"type":"Point"}
}