{
  "type": "Feature",
  "properties": {
    "addr:full":"Abdijstraat 40 Antwerpen Antwerpen 2020",
    "addr:housenumber":"40",
    "addr:postcode":"2020",
    "addr:street":"Abdijstraat",
    "iso:country":"BE",
    "sg:address":"Abdijstraat 40",
    "sg:city":"Antwerpen",
    "sg:classifiers":[
        {
            "category":"Restaurant",
            "type":"Food & Drink"
        }
    ],
    "sg:phone":"+32 3 216 97 48",
    "sg:postcode":"2020",
    "sg:province":"Antwerpen",
    "wof:name":"La France",
    "wof:placetype":"venue"
},
  "geometry": {"coordinates":[4.3796920776,51.1895942688],"type":"Point"}
}