{
  "type": "Feature",
  "properties": {
    "addr:full":"Markegemstraat 73 Dentergem West-Vlaanderen 8720",
    "addr:housenumber":"73",
    "addr:postcode":"8720",
    "addr:street":"Markegemstraat",
    "iso:country":"BE",
    "sg:address":"Markegemstraat 73",
    "sg:city":"Dentergem",
    "sg:orig_category":"M\u00e9decins and sp\u00e9cialistes",
    "sg:phone":"+32 56 60 13 91",
    "sg:postcode":"8720",
    "sg:province":"West-Vlaanderen",
    "wof:name":"J. Van Betsbrugge",
    "wof:placetype":"venue"
},
  "geometry": {"coordinates":[3.3963620663,50.9349555969],"type":"Point"}
}