{
  "type": "Feature",
  "properties": {
    "iso:country":"BE",
    "sg:address":"Mechelsestraat 43",
    "sg:city":"Leuven",
    "sg:orig_category":"Voedingsspeciaalzaken",
    "sg:phone":"+32 16 23 30 95",
    "sg:postcode":"3000",
    "sg:province":"Vlaams-Brabant",
    "wof:name":"Pergola",
    "wof:placetype":"venue"
},
  "geometry": {"coordinates":[4.6994609833,50.8810043335],"type":"Point"}
}