{
  "type": "Feature",
  "properties": {
    "addr:full":"Rue Ren\u00e9 Declercq 36 Bruxelles (woluwe-saint-pierre) Bruxelles-Capitale 1150",
    "addr:housenumber":"36",
    "addr:postcode":"1150",
    "addr:street":"Rue Rene\u0301 Declercq",
    "iso:country":"BE",
    "sg:address":"Rue Ren\u00e9 Declercq 36",
    "sg:city":"Bruxelles (woluwe-saint-pierre)",
    "sg:classifiers":[
        {
            "category":"Shopping",
            "subcategory":"Discount & Variety Stores",
            "type":"Retail Goods"
        }
    ],
    "sg:phone":"+32 2 771 80 40",
    "sg:postcode":"1150",
    "sg:province":"Bruxelles-Capitale",
    "sg:tags":[
        "shop",
        "clearers",
        "curiosity",
        "furniture"
    ],
    "wof:name":"Timmermans",
    "wof:placetype":"venue"
},
  "geometry": {"coordinates":[4.4317932129,50.8364982605],"type":"Point"}
}