{
  "type": "Feature",
  "properties": {
    "iso:country":"BE",
    "sg:address":"Quai Saint-l\u00c9onard 16c11",
    "sg:city":"Li\u00c8ge",
    "sg:orig_category":"Experts-comptables. Conseillers fiscaux. Comptables. Assistances juridiques",
    "sg:phone":"+32 4 227 82 34",
    "sg:postcode":"4000",
    "sg:province":"Li\u00e8ge",
    "wof:name":"Jacques Lejeune",
    "wof:placetype":"venue"
},
  "geometry": {"coordinates":[5.5886068344,50.6475372314],"type":"Point"}
}