{
  "type": "Feature",
  "properties": {
    "iso:country":"BE",
    "sg:address":"64",
    "sg:city":"Naamsesteenweg 3052 Blanden",
    "sg:classifiers":[
        {
            "category":"Travel",
            "subcategory":"Hotels & Motels",
            "type":"Entertainment"
        }
    ],
    "sg:phone":"+32 16 40 05 03",
    "sg:postcode":"64",
    "sg:tags":[
        "hotels",
        "business",
        "restaurant"
    ],
    "wof:name":"D.c.m. Nv",
    "wof:placetype":"venue"
},
  "geometry": {"coordinates":[4.7000899315,50.8312263489],"type":"Point"}
}