{
  "type": "Feature",
  "properties": {
    "addr:full":"Pont Saint-laurent 1 Verviers Li\u00e8ge 4800",
    "addr:housenumber":"1",
    "addr:postcode":"4800",
    "addr:street":"Pont Saint-Laurent",
    "iso:country":"BE",
    "sg:address":"Pont Saint-laurent 1",
    "sg:city":"Verviers",
    "sg:orig_category":"Bagage and lederwaren Schoenen",
    "sg:phone":"+32 87 33 35 37",
    "sg:postcode":"4800",
    "sg:province":"Li\u00e8ge",
    "wof:name":"Avance",
    "wof:placetype":"venue"
},
  "geometry": {"coordinates":[5.8600001335,50.5925712585],"type":"Point"}
}