{
  "type": "Feature",
  "properties": {
    "addr:full":"Zeger Van Kortrijkstraat 18 Gent (drongen) Oost-Vlaanderen 9031",
    "addr:housenumber":"18",
    "addr:postcode":"9031",
    "addr:street":"Zeger Van Kortrijkstraat",
    "iso:country":"BE",
    "sg:address":"Zeger Van Kortrijkstraat 18",
    "sg:city":"Gent (drongen)",
    "sg:classifiers":[
        {
            "category":"Health Services",
            "subcategory":"Dentist",
            "type":"Services"
        }
    ],
    "sg:phone":"+32 9 236 31 36",
    "sg:postcode":"9031",
    "sg:province":"Oost-Vlaanderen",
    "wof:name":"D'haenens Kathleen",
    "wof:placetype":"venue"
},
  "geometry": {"coordinates":[3.6621220112,51.0557327271],"type":"Point"}
}