{
  "type": "Feature",
  "properties": {
    "addr:full":"Rue De Lavaux 22 Musson Luxembourg 6750",
    "addr:housenumber":"22",
    "addr:postcode":"6750",
    "addr:street":"Rue De Lavaux",
    "iso:country":"BE",
    "sg:address":"Rue De Lavaux 22",
    "sg:city":"Musson",
    "sg:orig_category":"Installation de menuiserie m\u00e9tallique",
    "sg:phone":"+32 63 67 52 84",
    "sg:postcode":"6750",
    "sg:province":"Luxembourg",
    "wof:name":"Franck Lefevre",
    "wof:placetype":"venue"
},
  "geometry": {"coordinates":[5.6627578735,49.5752906799],"type":"Point"}
}