{
  "type": "Feature",
  "properties": {
    "iso:country":"BE",
    "sg:address":"Bruinstraat 33",
    "sg:city":"Zonhoven",
    "sg:orig_category":"Divers amusement Verhuur televisie- and audiovisuele apparatuur",
    "sg:phone":"+32 11 81 67 79",
    "sg:postcode":"3520",
    "sg:province":"Limburg",
    "wof:name":"Anoniem Sound & Light",
    "wof:placetype":"venue"
},
  "geometry": {"coordinates":[5.3580870628,51.0051345825],"type":"Point"}
}