{
  "type": "Feature",
  "properties": {
    "iso:country":"BE",
    "sg:address":"Bredabaan 24",
    "sg:city":"Wuustwezel",
    "sg:classifiers":[
        {
            "category":"Professional",
            "subcategory":"Business Services",
            "type":"Services"
        }
    ],
    "sg:phone":"+32 3 669 74 74",
    "sg:postcode":"2990",
    "sg:province":"Antwerpen",
    "sg:tags":[
        "automobile",
        "-",
        "assessor"
    ],
    "wof:name":"Pacqu\u00e9e L",
    "wof:placetype":"venue"
},
  "geometry": {"coordinates":[4.6224532127,51.4248695374],"type":"Point"}
}