{
  "type": "Feature",
  "properties": {
    "addr:full":"Avenue Reine Astrid 175 Spa Li\u00e8ge 4900",
    "addr:housenumber":"175",
    "addr:postcode":"4900",
    "addr:street":"Avenue Reine Astrid",
    "iso:country":"BE",
    "sg:address":"Avenue Reine Astrid 175",
    "sg:city":"Spa",
    "sg:orig_category":"Stations-service and carburants. Location de voitures",
    "sg:phone":"+32 87 23 05 20",
    "sg:postcode":"4900",
    "sg:province":"Li\u00e8ge",
    "wof:name":"Hertz",
    "wof:placetype":"venue"
},
  "geometry": {"coordinates":[5.84476614,50.4899482727],"type":"Point"}
}