{
  "type": "Feature",
  "properties": {
    "addr:full":"Sint-gillislaan 91 Dendermonde Oost-Vlaanderen 9200",
    "addr:housenumber":"91",
    "addr:postcode":"9200",
    "addr:street":"Sint-Gillislaan;Oost-Vlaanderen",
    "iso:country":"BE",
    "sg:address":"Sint-gillislaan 91",
    "sg:city":"Dendermonde",
    "sg:orig_category":"Brood, gebak and snoepgoed",
    "sg:phone":"+32 52 21 19 56",
    "sg:postcode":"9200",
    "sg:province":"Oost-Vlaanderen",
    "wof:name":"Rose De Hertog",
    "wof:placetype":"venue"
},
  "geometry": {"coordinates":[4.1099901199,51.020236969],"type":"Point"}
}