{
  "type": "Feature",
  "properties": {
    "addr:full":"Moershoofde 33 Sint-laureins Oost-Vlaanderen 9980",
    "addr:housenumber":"33",
    "addr:postcode":"9980",
    "addr:street":"Moershoofde",
    "iso:country":"BE",
    "sg:address":"Moershoofde 33",
    "sg:city":"Sint-laureins",
    "sg:orig_category":"Rundveehouders",
    "sg:phone":"+32 9 379 01 48",
    "sg:postcode":"9980",
    "sg:province":"Oost-Vlaanderen",
    "wof:name":"Christian De Meulemeester",
    "wof:placetype":"venue"
},
  "geometry": {"coordinates":[3.5151178837,51.2444953918],"type":"Point"}
}