{
  "type": "Feature",
  "properties": {
    "iso:country":"BE",
    "sg:address":"Just. Lipsiusplein 2",
    "sg:city":"Overijse",
    "sg:orig_category":"Verplichte sociale verzekeringen",
    "sg:phone":"+32 2 687 84 16",
    "sg:postcode":"3090",
    "sg:province":"Vlaams-Brabant",
    "wof:name":"St.michielsbond",
    "wof:placetype":"venue"
},
  "geometry": {"coordinates":[4.5374851227,50.7726783752],"type":"Point"}
}