{
  "type": "Feature",
  "properties": {
    "addr:full":"Brammertstraatje 48 Dilsen-stokkem Limburg 3650",
    "addr:housenumber":"48",
    "addr:postcode":"3650",
    "addr:street":"Brammertstraatje",
    "iso:country":"BE",
    "sg:address":"Brammertstraatje 48",
    "sg:city":"Dilsen-stokkem",
    "sg:orig_category":"Fruitteelt",
    "sg:phone":"+32 89 75 57 52",
    "sg:postcode":"3650",
    "sg:province":"Limburg",
    "wof:name":"Ronald Bisschops",
    "wof:placetype":"venue"
},
  "geometry": {"coordinates":[5.727396965,51.0364189148],"type":"Point"}
}