{
  "type": "Feature",
  "properties": {
    "addr:full":"Chee De Dinant 8 Profondeville Namur 5170",
    "addr:housenumber":"8",
    "addr:postcode":"5170",
    "addr:street":"Chee;Dinant",
    "iso:country":"BE",
    "sg:address":"Chee De Dinant 8",
    "sg:city":"Profondeville",
    "sg:classifiers":[
        {
            "category":"Banks & Credit Unions",
            "subcategory":"Bank",
            "type":"Services"
        }
    ],
    "sg:phone":"+32 81 41 31 38",
    "sg:postcode":"5170",
    "sg:province":"Namur",
    "wof:name":"Aslk-cger Bank",
    "wof:placetype":"venue"
},
  "geometry": {"coordinates":[4.8696961403,50.3775215149],"type":"Point"}
}