{
  "type": "Feature",
  "properties": {
    "addr:full":"Avenue De Messidor 132 Ukkel/uccle Bruxelles-Capitale 1180",
    "addr:housenumber":"132",
    "addr:postcode":"1180",
    "addr:street":"Avenue De Messidor;/",
    "iso:country":"BE",
    "sg:address":"Avenue De Messidor 132",
    "sg:city":"Ukkel/uccle",
    "sg:classifiers":[
        {
            "category":"Arena",
            "subcategory":"Sports Club",
            "type":"Entertainment"
        }
    ],
    "sg:phone":"+32 2 344 90 74",
    "sg:postcode":"1180",
    "sg:province":"Bruxelles-Capitale",
    "sg:tags":[
        "de"
    ],
    "wof:name":"P\u00c9tanque Messidor",
    "wof:placetype":"venue"
},
  "geometry": {"coordinates":[4.3432488441,50.8101425171],"type":"Point"}
}