{
  "type": "Feature",
  "properties": {
    "addr:full":"Veldstraat 27 Overpelt Limburg 3900",
    "addr:housenumber":"27",
    "addr:postcode":"3900",
    "addr:street":"Veldstraat",
    "iso:country":"BE",
    "sg:address":"Veldstraat 27",
    "sg:city":"Overpelt",
    "sg:classifiers":[
        {
            "category":"Arena",
            "subcategory":"Sports Club",
            "type":"Entertainment"
        }
    ],
    "sg:phone":"+32 11 64 86 93",
    "sg:postcode":"3900",
    "sg:province":"Limburg",
    "sg:tags":[
        "de"
    ],
    "wof:name":"Dameshandbalklub Overpelt",
    "wof:placetype":"venue"
},
  "geometry": {"coordinates":[5.4321889877,51.2064437866],"type":"Point"}
}