{
  "type": "Feature",
  "properties": {
    "iso:country":"BE",
    "sg:address":"Jesserenstr 32",
    "sg:city":"Borgloon",
    "sg:classifiers":[
        {
            "category":"Professional",
            "subcategory":"Management & Consulting",
            "type":"Services"
        }
    ],
    "sg:phone":"+32 12 45 85 65",
    "sg:postcode":"3840",
    "sg:province":"Limburg",
    "sg:tags":[
        "consultant"
    ],
    "wof:name":"P S C Vof",
    "wof:placetype":"venue"
},
  "geometry": {"coordinates":[5.3441700935,50.8012466431],"type":"Point"}
}