{
  "type": "Feature",
  "properties": {
    "addr:full":"Bruulstraat 18 Haaltert Oost-Vlaanderen 9450",
    "addr:housenumber":"18",
    "addr:postcode":"9450",
    "addr:street":"Bruulstraat",
    "iso:country":"BE",
    "sg:address":"Bruulstraat 18",
    "sg:city":"Haaltert",
    "sg:orig_category":"Banken and kredietinstellingen",
    "sg:phone":"+32 53 83 22 93",
    "sg:postcode":"9450",
    "sg:province":"Oost-Vlaanderen",
    "wof:name":"Dexia",
    "wof:placetype":"venue"
},
  "geometry": {"coordinates":[4.0058350563,50.9027481079],"type":"Point"}
}