{
  "type": "Feature",
  "properties": {
    "addr:full":"Rue Du Sartia 5 Mettet Namur 5640",
    "addr:housenumber":"5",
    "addr:postcode":"5640",
    "addr:street":"Rue Du Sartia",
    "iso:country":"BE",
    "sg:address":"Rue Du Sartia 5",
    "sg:city":"Mettet",
    "sg:classifiers":[
        {
            "category":"Real Estate",
            "subcategory":"Architect",
            "type":"Services"
        }
    ],
    "sg:phone":"+32 71 72 58 56",
    "sg:postcode":"5640",
    "sg:province":"Namur",
    "wof:name":"Lechat D",
    "wof:placetype":"venue"
},
  "geometry": {"coordinates":[4.6455488205,50.3398857117],"type":"Point"}
}