{
  "type": "Feature",
  "properties": {
    "addr:full":"De Billemontstraat 92 Geel Antwerpen 2440",
    "addr:housenumber":"92",
    "addr:postcode":"2440",
    "addr:street":"De Billemontstraat",
    "iso:country":"BE",
    "sg:address":"De Billemontstraat 92",
    "sg:city":"Geel",
    "sg:classifiers":[
        {
            "category":"Cafe",
            "type":"Food & Drink"
        }
    ],
    "sg:phone":"+32 14 58 26 42",
    "sg:postcode":"2440",
    "sg:province":"Antwerpen",
    "sg:tags":[
        "caf\u00e9s"
    ],
    "wof:name":"Maria Geuens",
    "wof:placetype":"venue"
},
  "geometry": {"coordinates":[4.9999828339,51.1626739502],"type":"Point"}
}