{
  "type": "Feature",
  "properties": {
    "addr:full":"Regentieplein 8 Sint-niklaas Oost-Vlaanderen 9100",
    "addr:housenumber":"8",
    "addr:postcode":"9100",
    "addr:street":"Regentieplein",
    "iso:country":"BE",
    "sg:address":"Regentieplein 8",
    "sg:city":"Sint-niklaas",
    "sg:orig_category":"Advocaten and juridische adviseurs",
    "sg:phone":"+32 3 777 49 50",
    "sg:postcode":"9100",
    "sg:province":"Oost-Vlaanderen",
    "wof:name":"Mia Deyaert",
    "wof:placetype":"venue"
},
  "geometry": {"coordinates":[4.1453747749,51.16822052],"type":"Point"}
}