{
  "type": "Feature",
  "properties": {
    "iso:country":"BE",
    "sg:address":"Rue De L\u00b4industrie 25",
    "sg:city":"Saint-ghislain",
    "sg:orig_category":"Advocaten and juridische adviseurs",
    "sg:phone":"+32 65 79 33 94",
    "sg:postcode":"7330",
    "sg:province":"Hainaut",
    "wof:name":"E. Soetaert",
    "wof:placetype":"venue"
},
  "geometry": {"coordinates":[3.8185970783,50.4509315491],"type":"Point"}
}