{
  "type": "Feature",
  "properties": {
    "addr:full":"Naamsestraat 85b1 Leuven Vlaams-Brabant 3000",
    "addr:housenumber":"85b1",
    "addr:postcode":"3000",
    "addr:street":"Naamsestraat",
    "iso:country":"BE",
    "sg:address":"Naamsestraat 85b1",
    "sg:city":"Leuven",
    "sg:orig_category":"Artsen and specialisten",
    "sg:phone":"+32 16 23 18 78",
    "sg:postcode":"3000",
    "sg:province":"Vlaams-Brabant",
    "wof:name":"Andr\u00c9 Beuselinck",
    "wof:placetype":"venue"
},
  "geometry": {"coordinates":[4.6998977661,50.8731307983],"type":"Point"}
}