{
  "type": "Feature",
  "properties": {
    "addr:full":"H. Fordlaan 47 Genk Limburg 3600",
    "addr:housenumber":"47",
    "addr:postcode":"3600",
    "addr:street":"H. Fordlaan",
    "iso:country":"BE",
    "sg:address":"H. Fordlaan 47",
    "sg:city":"Genk",
    "sg:orig_category":"Sociale secretariaten",
    "sg:phone":"+32 89 32 30 32",
    "sg:postcode":"3600",
    "sg:province":"Limburg",
    "wof:name":"Sap Personeelsdiensten",
    "wof:placetype":"venue"
},
  "geometry": {"coordinates":[5.486205101,50.9196586609],"type":"Point"}
}