{
  "type": "Feature",
  "properties": {
    "iso:country":"BE",
    "sg:address":"Arthur Diderichstraat 44",
    "sg:city":"Sint-gillis/saint-gilles",
    "sg:orig_category":"Woningbouw",
    "sg:phone":"+32 2 539 01 85",
    "sg:postcode":"1060",
    "sg:province":"Bruxelles-Capitale",
    "wof:name":"Agostinho Morais Teixeira",
    "wof:placetype":"venue"
},
  "geometry": {"coordinates":[4.3437771797,50.8221740723],"type":"Point"}
}