{
  "type": "Feature",
  "properties": {
    "iso:country":"BE",
    "sg:address":"Houba De Strooperlaan 69",
    "sg:city":"Brussel/bruxelles",
    "sg:orig_category":"Kapsalons",
    "sg:phone":"+32 2 479 39 20",
    "sg:postcode":"1020",
    "sg:province":"Bruxelles-Capitale",
    "wof:name":"Coiffure Anastasia",
    "wof:placetype":"venue"
},
  "geometry": {"coordinates":[4.3398017883,50.8880157471],"type":"Point"}
}