{
  "type": "Feature",
  "properties": {
    "addr:full":"Rue De Stambruges 114 Bernissart (blaton) Hainaut 7321",
    "addr:housenumber":"114",
    "addr:postcode":"7321",
    "addr:street":"Rue De Stambruges",
    "iso:country":"BE",
    "sg:address":"Rue De Stambruges 114",
    "sg:city":"Bernissart (blaton)",
    "sg:classifiers":[
        {
            "category":"Parking",
            "subcategory":"Lot",
            "type":"Transportation"
        }
    ],
    "sg:phone":"+32 69 56 07 77",
    "sg:postcode":"7321",
    "sg:province":"Hainaut",
    "sg:tags":[
        "parking-places",
        "laying-out"
    ],
    "wof:name":"Deruelle Albert Sprl",
    "wof:placetype":"venue"
},
  "geometry": {"coordinates":[3.702837944,50.4840316772],"type":"Point"}
}