{
  "type": "Feature",
  "properties": {
    "addr:full":"Rue De Nivelles 107 Chapelle-lez-herlaimont (godarville) Hainaut 7160",
    "addr:housenumber":"107",
    "addr:postcode":"7160",
    "addr:street":"Rue De Nivelles",
    "iso:country":"BE",
    "sg:address":"Rue De Nivelles 107",
    "sg:city":"Chapelle-lez-herlaimont (godarville)",
    "sg:classifiers":[
        {
            "category":"Professional",
            "subcategory":"Management & Consulting",
            "type":"Services"
        }
    ],
    "sg:phone":"+32 64 45 04 40",
    "sg:postcode":"7160",
    "sg:province":"Hainaut",
    "sg:tags":[
        "-",
        "processing",
        "data",
        "consultant"
    ],
    "wof:name":"Watelet J-c",
    "wof:placetype":"venue"
},
  "geometry": {"coordinates":[4.2832398415,50.4971618652],"type":"Point"}
}