{
  "type": "Feature",
  "properties": {
    "iso:country":"BE",
    "sg:address":"Rue D'abolens 8",
    "sg:city":"Hannut",
    "sg:classifiers":[
        {
            "category":"Professional",
            "type":"Services"
        }
    ],
    "sg:phone":"+32 19 51 44 05",
    "sg:postcode":"4280",
    "sg:province":"Li\u00e8ge",
    "sg:tags":[
        "aux",
        "diver",
        "personnes"
    ],
    "wof:name":"Christine Flabat",
    "wof:placetype":"venue"
},
  "geometry": {"coordinates":[5.1202750206,50.6756362915],"type":"Point"}
}