{
  "type": "Feature",
  "properties": {
    "addr:full":"Chauss\u00e9e Du Roeulx 1214 Mons (havr\u00e9) Hainaut 7021",
    "addr:housenumber":"1214",
    "addr:postcode":"7021",
    "addr:street":"Chausse\u0301E Du Roeulx",
    "iso:country":"BE",
    "sg:address":"Chauss\u00e9e Du Roeulx 1214",
    "sg:city":"Mons (havr\u00e9)",
    "sg:classifiers":[
        {
            "category":"Health Services",
            "subcategory":"Dentist",
            "type":"Services"
        }
    ],
    "sg:phone":"+32 65 87 29 68",
    "sg:postcode":"7021",
    "sg:province":"Hainaut",
    "wof:name":"Laurent S",
    "wof:placetype":"venue"
},
  "geometry": {"coordinates":[4.0562500954,50.4683494568],"type":"Point"}
}