{
  "type": "Feature",
  "properties": {
    "iso:country":"BE",
    "sg:address":"Albert I-promenade 25",
    "sg:city":"Oostende",
    "sg:orig_category":"Non-Classified Establishments",
    "sg:phone":"+32 59 70 56 88",
    "sg:postcode":"8400",
    "sg:province":"West-Vlaanderen",
    "wof:name":"Witberg Nv",
    "wof:placetype":"venue"
},
  "geometry": {"coordinates":[2.9173181057,51.2350845337],"type":"Point"}
}