{
  "type": "Feature",
  "properties": {
    "addr:full":"Route Du Val Dieu 914 Herve (charneux) Li\u00e8ge 4654",
    "addr:housenumber":"914",
    "addr:postcode":"4654",
    "addr:street":"Route Du Val Dieu",
    "iso:country":"BE",
    "sg:address":"Route Du Val Dieu 914",
    "sg:city":"Herve (charneux)",
    "sg:classifiers":[
        {
            "category":"Wholesale",
            "subcategory":"Wine & Distilled Alcoholic Beverages",
            "type":"Manufacturing & Wholesale Goods"
        }
    ],
    "sg:phone":"+32 87 68 65 08",
    "sg:postcode":"4654",
    "sg:province":"Li\u00e8ge",
    "sg:tags":[
        "whol",
        "-",
        "spirit",
        "mfg"
    ],
    "wof:name":"Saute Michel Sprl",
    "wof:placetype":"venue"
},
  "geometry": {"coordinates":[5.810341835,50.6933441162],"type":"Point"}
}