{
  "type": "Feature",
  "properties": {
    "addr:full":"Zuiderlaan 73b2 Waregem West-Vlaanderen 8790",
    "addr:housenumber":"73b2",
    "addr:postcode":"8790",
    "addr:street":"Zuiderlaan",
    "iso:country":"BE",
    "sg:address":"Zuiderlaan 73b2",
    "sg:city":"Waregem",
    "sg:orig_category":"Fruits and l\u00e9gumes Produits \u00e0 base de pommes de terre Gr",
    "sg:phone":"+32 56 61 33 33",
    "sg:postcode":"8790",
    "sg:province":"West-Vlaanderen",
    "wof:name":"Walter Bruwier Potatoes",
    "wof:placetype":"venue"
},
  "geometry": {"coordinates":[3.4379758835,50.8861999512],"type":"Point"}
}