{
  "type": "Feature",
  "properties": {
    "addr:full":"Rue Du Chemin De Fer 16 Wavre Brabant Wallon 1300",
    "addr:housenumber":"16;1300",
    "addr:street":"Rue Du Chemin De Fer",
    "iso:country":"BE",
    "sg:address":"Rue Du Chemin De Fer 16",
    "sg:city":"Wavre",
    "sg:orig_category":"Alimentation sp\u00e9cialis\u00e9e",
    "sg:phone":"+32 10 22 80 29",
    "sg:postcode":"1300",
    "sg:province":"Brabant Wallon",
    "wof:name":"Le Point Vert",
    "wof:placetype":"venue"
},
  "geometry": {"coordinates":[4.607665062,50.716632843],"type":"Point"}
}