{
  "type": "Feature",
  "properties": {
    "addr:full":"Kamiel Van Baelenstraat 3 Turnhout Antwerpen 2300",
    "addr:housenumber":"3",
    "addr:postcode":"2300",
    "addr:street":"Kamiel Van Baelenstraat",
    "iso:country":"BE",
    "sg:address":"Kamiel Van Baelenstraat 3",
    "sg:city":"Turnhout",
    "sg:orig_category":"Landmeters",
    "sg:phone":"+32 14 42 43 90",
    "sg:postcode":"2300",
    "sg:province":"Antwerpen",
    "wof:name":"Karel Snoeckx",
    "wof:placetype":"venue"
},
  "geometry": {"coordinates":[4.9428529739,51.3204421997],"type":"Point"}
}