{
  "type": "Feature",
  "properties": {
    "iso:country":"BE",
    "sg:address":"Tournibois 4",
    "sg:city":"Vloesberg/flobecq",
    "sg:orig_category":"Installation de menuiserie en bois and plastique. Travaux de pl\u00e2trage",
    "sg:phone":"+32 68 44 74 78",
    "sg:postcode":"7880",
    "sg:province":"Hainaut",
    "wof:name":"Blommaert Fr\u00c8res",
    "wof:placetype":"venue"
},
  "geometry": {"coordinates":[3.7514500618,50.7548103333],"type":"Point"}
}