{
  "type": "Feature",
  "properties": {
    "iso:country":"BE",
    "sg:address":"Berchemstraat 70",
    "sg:city":"Dilbeek",
    "sg:classifiers":[
        {
            "category":"Transit Center",
            "subcategory":"Freight",
            "type":"Transportation"
        }
    ],
    "sg:phone":"+32 2 463 34 04",
    "sg:postcode":"1700",
    "sg:province":"Vlaams-Brabant",
    "sg:tags":[
        "import",
        "export",
        "-"
    ],
    "wof:name":"Afritex-services Sa",
    "wof:placetype":"venue"
},
  "geometry": {"coordinates":[4.2722268105,50.8476600647],"type":"Point"}
}