{
  "type": "Feature",
  "properties": {
    "addr:full":"Dorpsstraat 84 Berlaar Antwerpen 2590",
    "addr:housenumber":"84",
    "addr:postcode":"2590",
    "addr:street":"Dorpsstraat",
    "iso:country":"BE",
    "sg:address":"Dorpsstraat 84",
    "sg:city":"Berlaar",
    "sg:orig_category":"Openbare bibliotheken and archieven",
    "sg:phone":"+32 3 482 45 58",
    "sg:postcode":"2590",
    "sg:province":"Antwerpen",
    "wof:name":"Openbare Bibliotheek",
    "wof:placetype":"venue"
},
  "geometry": {"coordinates":[4.6521339417,51.1171684265],"type":"Point"}
}