{
  "type": "Feature",
  "properties": {
    "addr:full":"Molenstraat 31 Kluisbergen (berchem) Oost-Vlaanderen 9690",
    "addr:housenumber":"31",
    "addr:postcode":"9690",
    "addr:street":"Molenstraat",
    "iso:country":"BE",
    "sg:address":"Molenstraat 31",
    "sg:city":"Kluisbergen (berchem)",
    "sg:classifiers":[
        {
            "category":"Shopping",
            "subcategory":"Optician",
            "type":"Retail Goods"
        }
    ],
    "sg:phone":"+32 55 38 71 00",
    "sg:postcode":"9690",
    "sg:province":"Oost-Vlaanderen",
    "sg:tags":[
        "-"
    ],
    "wof:name":"Cool Optiek",
    "wof:placetype":"venue"
},
  "geometry": {"coordinates":[3.5076069832,50.7892456055],"type":"Point"}
}