{
  "type": "Feature",
  "properties": {
    "iso:country":"BE",
    "sg:address":"Rue G\u00e9rard De Cambrai 28",
    "sg:city":"Florennes",
    "sg:classifiers":[
        {
            "category":"Professional",
            "subcategory":"Lawyer & Legal Services",
            "type":"Services"
        }
    ],
    "sg:phone":"+32 71 68 80 19",
    "sg:postcode":"5620",
    "sg:province":"Namur",
    "sg:tags":[
        "notary"
    ],
    "wof:name":"Bouillet Y",
    "wof:placetype":"venue"
},
  "geometry": {"coordinates":[4.6130948067,50.2510681152],"type":"Point"}
}