{
  "type": "Feature",
  "properties": {
    "addr:full":"Havermarkt 3 Hasselt Limburg 3500",
    "addr:housenumber":"3",
    "addr:postcode":"3500",
    "addr:street":"Havermarkt",
    "iso:country":"BE",
    "sg:address":"Havermarkt 3",
    "sg:city":"Hasselt",
    "sg:orig_category":"Agences de publicit\u00e9",
    "sg:phone":"+32 11 22 38 47",
    "sg:postcode":"3500",
    "sg:province":"Limburg",
    "wof:name":"Linders Advertising",
    "wof:placetype":"venue"
},
  "geometry": {"coordinates":[5.3368420601,50.9295845032],"type":"Point"}
}