{
  "type": "Feature",
  "properties": {
    "iso:country":"BE",
    "sg:address":"Meensestraat 13",
    "sg:city":"Kortrijk",
    "sg:classifiers":[
        {
            "category":"Professional",
            "subcategory":"Advertising",
            "type":"Services"
        }
    ],
    "sg:phone":"+32 56 37 00 02",
    "sg:postcode":"8500",
    "sg:province":"West-Vlaanderen",
    "sg:tags":[
        "clothes"
    ],
    "wof:name":"Dafra Sport",
    "wof:placetype":"venue"
},
  "geometry": {"coordinates":[3.2578530312,50.8333854675],"type":"Point"}
}