{
  "type": "Feature",
  "properties": {
    "iso:country":"BE",
    "sg:address":"Rue Des Wallons 225",
    "sg:city":"Li\u00c8ge",
    "sg:orig_category":"M\u00e9decins and sp\u00e9cialistes",
    "sg:phone":"+32 4 253 08 09",
    "sg:postcode":"4000",
    "sg:province":"Li\u00e8ge",
    "wof:name":"Thanh Huynh-thu",
    "wof:placetype":"venue"
},
  "geometry": {"coordinates":[5.5551271439,50.6268119812],"type":"Point"}
}