{
  "type": "Feature",
  "properties": {
    "addr:full":"Kerkstraat 47 Middelkerke West-Vlaanderen 8430",
    "addr:housenumber":"47",
    "addr:postcode":"8430",
    "addr:street":"Kerkstraat",
    "iso:country":"BE",
    "sg:address":"Kerkstraat 47",
    "sg:city":"Middelkerke",
    "sg:classifiers":[
        {
            "category":"Food & Beverages",
            "subcategory":"Supermarket",
            "type":"Retail Goods"
        }
    ],
    "sg:phone":"+32 59 30 42 99",
    "sg:postcode":"8430",
    "sg:province":"West-Vlaanderen",
    "sg:tags":[
        "department",
        "store"
    ],
    "wof:name":"Delhaize",
    "wof:placetype":"venue"
},
  "geometry": {"coordinates":[2.8203859329,51.18592453],"type":"Point"}
}