{
  "type": "Feature",
  "properties": {
    "iso:country":"BE",
    "sg:address":"Lepelstraat 74",
    "sg:city":"Lommel",
    "sg:orig_category":"M\u00e9decins and sp\u00e9cialistes",
    "sg:phone":"+32 11 55 37 25",
    "sg:postcode":"3920",
    "sg:province":"Limburg",
    "wof:name":"Mario Bastini",
    "wof:placetype":"venue"
},
  "geometry": {"coordinates":[5.3095178604,51.2336883545],"type":"Point"}
}