{
  "type": "Feature",
  "properties": {
    "iso:country":"BE",
    "sg:address":"Tiensesteenweg 156",
    "sg:city":"Sint-truiden",
    "sg:orig_category":"V\u00e9t\u00e9rinaires",
    "sg:phone":"+32 11 68 97 05",
    "sg:postcode":"3800",
    "sg:province":"Limburg",
    "wof:name":"Francois Ory",
    "wof:placetype":"venue"
},
  "geometry": {"coordinates":[5.1684570312,50.8143730164],"type":"Point"}
}