{
  "type": "Feature",
  "properties": {
    "addr:full":"Rue Saint-jean 8 Charleroi Hainaut 6041",
    "addr:housenumber":"8",
    "addr:postcode":"6041",
    "addr:street":"Rue Saint-Jean;Hainaut",
    "iso:country":"BE",
    "sg:address":"Rue Saint-jean 8",
    "sg:city":"Charleroi",
    "sg:orig_category":"Artsen and specialisten",
    "sg:phone":"+32 71 35 62 74",
    "sg:postcode":"6041",
    "sg:province":"Hainaut",
    "wof:name":"J. Schoonbrood",
    "wof:placetype":"venue"
},
  "geometry": {"coordinates":[4.427740097,50.470867157],"type":"Point"}
}