{
  "type": "Feature",
  "properties": {
    "addr:full":"Kareelbakkerijstraat 39 Grimbergen (strombeek-bever) Vlaams-Brabant 1853",
    "addr:housenumber":"39",
    "addr:postcode":"1853",
    "addr:street":"Kareelbakkerijstraat",
    "iso:country":"BE",
    "sg:address":"Kareelbakkerijstraat 39",
    "sg:city":"Grimbergen (strombeek-bever)",
    "sg:classifiers":[
        {
            "category":"Health Services",
            "subcategory":"Nursing And Care Facility",
            "type":"Services"
        }
    ],
    "sg:phone":"+32 2 267 79 47",
    "sg:postcode":"1853",
    "sg:province":"Vlaams-Brabant",
    "sg:tags":[
        "home",
        "rest"
    ],
    "wof:name":"Iris Residentie Bvba",
    "wof:placetype":"venue"
},
  "geometry": {"coordinates":[4.3622598648,50.9057273865],"type":"Point"}
}