{
  "type": "Feature",
  "properties": {
    "addr:full":"Lijsterdreef 39 Schilde Antwerpen 2970",
    "addr:housenumber":"39",
    "addr:postcode":"2970",
    "addr:street":"Lijsterdreef",
    "iso:country":"BE",
    "sg:address":"Lijsterdreef 39",
    "sg:city":"Schilde",
    "sg:orig_category":"Artiesten and kunstenaars",
    "sg:phone":"+32 3 658 86 89",
    "sg:postcode":"2970",
    "sg:province":"Antwerpen",
    "wof:name":"Jean Xhoffer",
    "wof:placetype":"venue"
},
  "geometry": {"coordinates":[4.553068161,51.2540969849],"type":"Point"}
}