{
  "type": "Feature",
  "properties": {
    "addr:full":"Rue Des P\u00e2querettes 45 Gembloux-sur-orneau (gembloux) Namur 5030",
    "addr:housenumber":"45",
    "addr:postcode":"5030",
    "addr:street":"Rue Des Pa\u0302Querettes;Namur",
    "iso:country":"BE",
    "sg:address":"Rue Des P\u00e2querettes 45",
    "sg:city":"Gembloux-sur-orneau (gembloux)",
    "sg:classifiers":[
        {
            "category":"Professional",
            "subcategory":"Art Services",
            "type":"Services"
        }
    ],
    "sg:phone":"+32 81 61 35 60",
    "sg:postcode":"5030",
    "sg:province":"Namur",
    "sg:tags":[
        "interior",
        "designer"
    ],
    "wof:name":"Art Severine",
    "wof:placetype":"venue"
},
  "geometry": {"coordinates":[4.7225160599,50.5472869873],"type":"Point"}
}