{
  "type": "Feature",
  "properties": {
    "iso:country":"BE",
    "sg:address":"Oostendestraat 343",
    "sg:city":"Torhout",
    "sg:classifiers":[
        {
            "category":"Travel",
            "subcategory":"Hotels & Motels",
            "type":"Entertainment"
        }
    ],
    "sg:phone":"+32 50 21 23 14",
    "sg:postcode":"8820",
    "sg:province":"West-Vlaanderen",
    "wof:name":"Hostellerie Gravenhof",
    "wof:placetype":"venue"
},
  "geometry": {"coordinates":[3.0620961189,51.0807189941],"type":"Point"}
}