{
  "type": "Feature",
  "properties": {
    "iso:country":"BE",
    "sg:address":"Diestsesteenweg 14",
    "sg:city":"Herk-de-stad",
    "sg:orig_category":"Journaux",
    "sg:phone":"+32 13 55 10 16",
    "sg:postcode":"3540",
    "sg:province":"Limburg",
    "wof:name":"\u00b4t Gazetje",
    "wof:placetype":"venue"
},
  "geometry": {"coordinates":[5.1618790627,50.9408454895],"type":"Point"}
}