{
  "type": "Feature",
  "properties": {
    "addr:full":"Rue Charles-bartholomez 11 Li\u00c8ge Li\u00e8ge 4020",
    "addr:housenumber":"11",
    "addr:postcode":"4020",
    "addr:street":"Rue Charles-Bartholomez",
    "iso:country":"BE",
    "sg:address":"Rue Charles-bartholomez 11",
    "sg:city":"Li\u00c8ge",
    "sg:orig_category":"Antiek",
    "sg:phone":"+32 4 344 10 65",
    "sg:postcode":"4020",
    "sg:province":"Li\u00e8ge",
    "wof:name":"Maison Freuville J.",
    "wof:placetype":"venue"
},
  "geometry": {"coordinates":[5.590282917,50.638004303],"type":"Point"}
}