{
  "type": "Feature",
  "properties": {
    "iso:country":"BE",
    "sg:address":"Place Du Vieux March\u00c9 22",
    "sg:city":"Edingen/enghien",
    "sg:orig_category":"Pharmaciens",
    "sg:phone":"+32 2 395 72 03",
    "sg:postcode":"7850",
    "sg:province":"Hainaut",
    "wof:name":"Pharmacie Declercq",
    "wof:placetype":"venue"
},
  "geometry": {"coordinates":[4.0433139801,50.695438385],"type":"Point"}
}