{
  "type": "Feature",
  "properties": {
    "addr:full":"Rue Joseph Deflandre 27 Chaudfontaine Li\u00e8ge 4053",
    "addr:housenumber":"27",
    "addr:postcode":"4053",
    "addr:street":"Rue Joseph Deflandre",
    "iso:country":"BE",
    "sg:address":"Rue Joseph Deflandre 27",
    "sg:city":"Chaudfontaine",
    "sg:classifiers":[
        {
            "category":"Military Area",
            "subcategory":"Armory",
            "type":"Public Place"
        }
    ],
    "sg:phone":"+32 4 367 11 01",
    "sg:postcode":"4053",
    "sg:province":"Li\u00e8ge",
    "sg:tags":[
        "armes",
        "munition"
    ],
    "wof:name":"Fe. Tenaerts Paul",
    "wof:placetype":"venue"
},
  "geometry": {"coordinates":[5.6063599586,50.5931015015],"type":"Point"}
}