{
  "type": "Feature",
  "properties": {
    "iso:country":"BE",
    "sg:address":"Rue Vanderkindere 536",
    "sg:city":"Ukkel/uccle",
    "sg:orig_category":"Entretien and r\u00e9parations de voitures",
    "sg:phone":"+32 2 346 14 73",
    "sg:postcode":"1180",
    "sg:province":"Bruxelles-Capitale",
    "wof:name":"C. Verhoeven",
    "wof:placetype":"venue"
},
  "geometry": {"coordinates":[4.3653187752,50.8146820068],"type":"Point"}
}