{
  "type": "Feature",
  "properties": {
    "iso:country":"BE",
    "sg:address":"De Breyne Peellaertstr. 21",
    "sg:city":"Diksmuide",
    "sg:orig_category":"Advocaten and juridische adviseurs",
    "sg:phone":"+32 51 50 35 64",
    "sg:postcode":"8600",
    "sg:province":"West-Vlaanderen",
    "wof:name":"Ph. Libeert",
    "wof:placetype":"venue"
},
  "geometry": {"coordinates":[2.865557909,51.0348091125],"type":"Point"}
}