{
  "type": "Feature",
  "properties": {
    "iso:country":"BE",
    "sg:address":"Faliestraat 2",
    "sg:city":"Zedelgem",
    "sg:orig_category":"Eleveurs de bovins",
    "sg:phone":"+32 50 20 93 91",
    "sg:postcode":"8210",
    "sg:province":"West-Vlaanderen",
    "wof:name":"Roger Lagast",
    "wof:placetype":"venue"
},
  "geometry": {"coordinates":[3.1286299229,51.141494751],"type":"Point"}
}