{
  "type": "Feature",
  "properties": {
    "iso:country":"BE",
    "sg:address":"Eikenstraat 62b1",
    "sg:city":"Rumst",
    "sg:classifiers":[
        {
            "category":"Cafe",
            "type":"Food & Drink"
        }
    ],
    "sg:phone":"+32 3 844 85 44",
    "sg:postcode":"2840",
    "sg:province":"Antwerpen",
    "sg:tags":[
        "caf\u00e9s"
    ],
    "wof:name":"Reet Sportkring",
    "wof:placetype":"venue"
},
  "geometry": {"coordinates":[4.4118471146,51.103603363],"type":"Point"}
}