{
  "type": "Feature",
  "properties": {
    "iso:country":"BE",
    "sg:address":"Mathias Joostenslaan 36",
    "sg:city":"Zoersel",
    "sg:classifiers":[
        {
            "category":"Building & Trades",
            "subcategory":"Landscaping Services",
            "type":"Services"
        }
    ],
    "sg:phone":"+32 3 385 14 43",
    "sg:postcode":"2980",
    "sg:province":"Antwerpen",
    "sg:tags":[
        "-",
        "lopping",
        "work",
        "tree",
        "felling"
    ],
    "wof:name":"Van Doorn D",
    "wof:placetype":"venue"
},
  "geometry": {"coordinates":[4.6260619164,51.262840271],"type":"Point"}
}