{
  "type": "Feature",
  "properties": {
    "iso:country":"BE",
    "sg:address":"Dronckaertstraat 65",
    "sg:city":"Menen",
    "sg:orig_category":"V\u00eatements sur mesure Fab",
    "sg:phone":"+32 56 41 42 74",
    "sg:postcode":"8930",
    "sg:province":"West-Vlaanderen",
    "wof:name":"Brigitte Loosvelt",
    "wof:placetype":"venue"
},
  "geometry": {"coordinates":[3.1667420864,50.7709159851],"type":"Point"}
}