{
  "type": "Feature",
  "properties": {
    "addr:full":"Rue Gr\u00c9goire Chapuis 109 Seraing Li\u00e8ge 4100",
    "addr:housenumber":"109",
    "addr:postcode":"4100",
    "addr:street":"Rue Gre\u0301Goire Chapuis",
    "iso:country":"BE",
    "sg:address":"Rue Gr\u00c9goire Chapuis 109",
    "sg:city":"Seraing",
    "sg:orig_category":"Brood, gebak and snoepgoed",
    "sg:phone":"+32 4 336 14 99",
    "sg:postcode":"4100",
    "sg:province":"Li\u00e8ge",
    "wof:name":"Alfonsina Cicirello",
    "wof:placetype":"venue"
},
  "geometry": {"coordinates":[5.506072998,50.5988311768],"type":"Point"}
}