{
  "type": "Feature",
  "properties": {
    "addr:full":"Elckerliclaan 41 Izegem West-Vlaanderen 8870",
    "addr:housenumber":"41",
    "addr:postcode":"8870",
    "addr:street":"Elckerliclaan",
    "iso:country":"BE",
    "sg:address":"Elckerliclaan 41",
    "sg:city":"Izegem",
    "sg:classifiers":[
        {
            "category":"Freight",
            "type":"Transportation"
        }
    ],
    "sg:phone":"+32 51 32 11 60",
    "sg:postcode":"8870",
    "sg:province":"West-Vlaanderen",
    "sg:tags":[
        "-",
        "transport"
    ],
    "wof:name":"Stradeltrans Bvba",
    "wof:placetype":"venue"
},
  "geometry": {"coordinates":[3.2251598835,50.9047355652],"type":"Point"}
}