{
  "type": "Feature",
  "properties": {
    "iso:country":"BE",
    "sg:address":"H\u00e9domont 14c",
    "sg:city":"Malmedy (beverc\u00e9)",
    "sg:classifiers":[
        {
            "category":"Real Estate",
            "subcategory":"Real Estate Services",
            "type":"Services"
        }
    ],
    "sg:phone":"+32 80 33 85 37",
    "sg:postcode":"4960",
    "sg:province":"Li\u00e8ge",
    "wof:name":"Buchholz F",
    "wof:placetype":"venue"
},
  "geometry": {"coordinates":[6.0422477722,50.4034538269],"type":"Point"}
}