{
  "type": "Feature",
  "properties": {
    "addr:full":"Koning Albertlaan 1 Machelen Vlaams-Brabant 1830",
    "addr:housenumber":"1",
    "addr:postcode":"1830",
    "addr:street":"Koning Albertlaan",
    "iso:country":"BE",
    "sg:address":"Koning Albertlaan 1",
    "sg:city":"Machelen",
    "sg:orig_category":"Enseignement maternel and primaire",
    "sg:phone":"+32 2 251 39 31",
    "sg:postcode":"1830",
    "sg:province":"Vlaams-Brabant",
    "wof:name":"Basisschool",
    "wof:placetype":"venue"
},
  "geometry": {"coordinates":[4.4369912148,50.9101982117],"type":"Point"}
}