{
  "type": "Feature",
  "properties": {
    "addr:full":"Brugsesteenweg 606-608 Gent Oost-Vlaanderen 9030",
    "addr:housenumber":"606-608",
    "addr:postcode":"9030",
    "addr:street":"Brugsesteenweg;Oost-Vlaanderen",
    "iso:country":"BE",
    "sg:address":"Brugsesteenweg 606-608",
    "sg:city":"Gent",
    "sg:orig_category":"Transports terrestres de voyageurs. Taxis services sp\u00e9ciaux",
    "sg:phone":"+32 9 216 80 20",
    "sg:postcode":"9030",
    "sg:province":"Oost-Vlaanderen",
    "wof:name":"Taxi Hendriks Gent",
    "wof:placetype":"venue"
},
  "geometry": {"coordinates":[3.6796700954,51.0748901367],"type":"Point"}
}