{
  "type": "Feature",
  "properties": {
    "addr:full":"Vrasenestraat 24 Beveren (beveren-waas) Oost-Vlaanderen 9120",
    "addr:housenumber":"24",
    "addr:postcode":"9120",
    "addr:street":"Vrasenestraat;Oost-Vlaanderen",
    "iso:country":"BE",
    "sg:address":"Vrasenestraat 24",
    "sg:city":"Beveren (beveren-waas)",
    "sg:orig_category":"Non-Classified Establishments",
    "sg:phone":"+32 3 775 83 39",
    "sg:postcode":"9120",
    "sg:province":"Oost-Vlaanderen",
    "wof:name":"Werkpak ('t)",
    "wof:placetype":"venue"
},
  "geometry": {"coordinates":[4.2541928291,51.2141571045],"type":"Point"}
}