{
  "type": "Feature",
  "properties": {
    "addr:full":"Rue L\u00e9opold Sturbaut 22 Renaix Oost-Vlaanderen 9600",
    "addr:housenumber":"22",
    "addr:postcode":"9600",
    "addr:street":"Rue Le\u0301Opold Sturbaut",
    "iso:country":"BE",
    "sg:address":"Rue L\u00e9opold Sturbaut 22",
    "sg:city":"Renaix",
    "sg:classifiers":[
        {
            "category":"Shopping",
            "subcategory":"Clothing, Apparel, & Fashions",
            "type":"Retail Goods"
        }
    ],
    "sg:phone":"+32 55 21 59 01",
    "sg:postcode":"9600",
    "sg:province":"Oost-Vlaanderen",
    "sg:tags":[
        "-",
        "clothing",
        "child"
    ],
    "wof:name":"Okapi",
    "wof:placetype":"venue"
},
  "geometry": {"coordinates":[3.5962378979,50.7425346375],"type":"Point"}
}