{
  "type": "Feature",
  "properties": {
    "addr:full":"Deinsesteenweg 190 Tielt West-Vlaanderen 8700",
    "addr:housenumber":"190",
    "addr:postcode":"8700",
    "addr:street":"Deinsesteenweg",
    "iso:country":"BE",
    "sg:address":"Deinsesteenweg 190",
    "sg:city":"Tielt",
    "sg:classifiers":[
        {
            "category":"Retail",
            "subcategory":"Auto Repair",
            "type":"Services"
        }
    ],
    "sg:phone":"+32 51 63 33 83",
    "sg:postcode":"8700",
    "sg:province":"West-Vlaanderen",
    "sg:tags":[
        "automobile-body"
    ],
    "wof:name":"Vanhaeverbeke",
    "wof:placetype":"venue"
},
  "geometry": {"coordinates":[3.3780350685,50.9952201843],"type":"Point"}
}