{
  "type": "Feature",
  "properties": {
    "addr:full":"Avenue Orban 73 Sint-pieters-woluwe/woluwe-saint-pierre Bruxelles-Capitale 1150",
    "addr:housenumber":"73",
    "addr:postcode":"1150",
    "addr:street":"Avenue Orban;/",
    "iso:country":"BE",
    "sg:address":"Avenue Orban 73",
    "sg:city":"Sint-pieters-woluwe/woluwe-saint-pierre",
    "sg:orig_category":"Enseignement secondaire g\u00e9n\u00e9ral. Enseignement maternel and primaire",
    "sg:phone":"+32 2 770 32 50",
    "sg:postcode":"1150",
    "sg:province":"Bruxelles-Capitale",
    "wof:name":"Ecole Fondamentale",
    "wof:placetype":"venue"
},
  "geometry": {"coordinates":[4.4559831619,50.8341293335],"type":"Point"}
}