{
  "type": "Feature",
  "properties": {
    "iso:country":"BE",
    "sg:address":"Congresstraat 37",
    "sg:city":"Brussel/bruxelles",
    "sg:orig_category":"Banken and kredietinstellingen",
    "sg:phone":"+32 2 217 21 24",
    "sg:postcode":"1000",
    "sg:province":"Bruxelles-Capitale",
    "wof:name":"Centea",
    "wof:placetype":"venue"
},
  "geometry": {"coordinates":[4.3667650223,50.8492546082],"type":"Point"}
}