{
  "type": "Feature",
  "properties": {
    "addr:full":"Rue Jules Vieujant 35 Bruxelles (molenbeek-saint-jean) Bruxelles-Capitale 1080",
    "addr:housenumber":"35",
    "addr:postcode":"1080",
    "addr:street":"Rue Jules Vieujant",
    "iso:country":"BE",
    "sg:address":"Rue Jules Vieujant 35",
    "sg:city":"Bruxelles (molenbeek-saint-jean)",
    "sg:classifiers":[
        {
            "category":"Health Services",
            "subcategory":"Health Practitioner",
            "type":"Services"
        }
    ],
    "sg:phone":"+32 2 410 67 25",
    "sg:postcode":"1080",
    "sg:province":"Bruxelles-Capitale",
    "sg:tags":[
        "physiotherapist"
    ],
    "wof:name":"Leclercq Christian",
    "wof:placetype":"venue"
},
  "geometry": {"coordinates":[4.321955204,50.8537712097],"type":"Point"}
}