{
  "type": "Feature",
  "properties": {
    "iso:country":"BE",
    "sg:address":"Zandstraat 39",
    "sg:city":"Linter",
    "sg:orig_category":"Herstellingen and onderhoud van auto's",
    "sg:phone":"+32 16 78 80 36",
    "sg:postcode":"3350",
    "sg:province":"Vlaams-Brabant",
    "wof:name":"Johan D'haese",
    "wof:placetype":"venue"
},
  "geometry": {"coordinates":[5.0137319565,50.8122138977],"type":"Point"}
}