{
  "type": "Feature",
  "properties": {
    "addr:full":"Gewad 13 Gent Oost-Vlaanderen 9000",
    "addr:housenumber":"13",
    "addr:postcode":"9000",
    "addr:street":"Gewad;Oost-Vlaanderen",
    "iso:country":"BE",
    "sg:address":"Gewad 13",
    "sg:city":"Gent",
    "sg:classifiers":[
        {
            "category":"Health Services",
            "subcategory":"Hospital",
            "type":"Services"
        }
    ],
    "sg:phone":"+32 9 223 46 44",
    "sg:postcode":"9000",
    "sg:province":"Oost-Vlaanderen",
    "wof:name":"Medisch Sociaal Opvangcentrum Voor Druggebruikers Gent",
    "wof:placetype":"venue"
},
  "geometry": {"coordinates":[3.7189071178,51.0576286316],"type":"Point"}
}