{
  "type": "Feature",
  "properties": {
    "iso:country":"BE",
    "sg:address":"Cl\u00e9ment Behnplein 5",
    "sg:city":"Ninove",
    "sg:classifiers":[
        {
            "category":"Shopping",
            "subcategory":"Gifts & Souvenirs",
            "type":"Retail Goods"
        }
    ],
    "sg:phone":"+32 54 33 01 39",
    "sg:postcode":"9400",
    "sg:province":"Oost-Vlaanderen",
    "sg:tags":[
        "-"
    ],
    "wof:name":"Recado",
    "wof:placetype":"venue"
},
  "geometry": {"coordinates":[4.0262699127,50.8365402222],"type":"Point"}
}