{
  "type": "Feature",
  "properties": {
    "addr:full":"Rue De Bruxelles 78 Parc De La Technologie Tubize Brabant Wallon 1480",
    "addr:housenumber":"78",
    "addr:postcode":"1480",
    "addr:street":"Rue De Bruxelles;Parc De La Technologie;Wallon",
    "iso:country":"BE",
    "sg:address":"Rue De Bruxelles 78 Parc De La Technologie",
    "sg:city":"Tubize",
    "sg:classifiers":[
        {
            "category":"Professional",
            "subcategory":"Engineering",
            "type":"Services"
        }
    ],
    "sg:phone":"+32 2 391 08 30",
    "sg:postcode":"1480",
    "sg:province":"Brabant Wallon",
    "sg:tags":[
        "machine",
        "-",
        "mechanical"
    ],
    "wof:name":"Air Conditioning Technology Sa",
    "wof:placetype":"venue"
},
  "geometry": {"coordinates":[4.2044348717,50.6961669922],"type":"Point"}
}