{
  "type": "Feature",
  "properties": {
    "addr:full":"Vierhuizen 15 Olen Antwerpen 2250",
    "addr:housenumber":"15",
    "addr:postcode":"2250",
    "addr:street":"Vierhuizen",
    "iso:country":"BE",
    "sg:address":"Vierhuizen 15",
    "sg:city":"Olen",
    "sg:orig_category":"M\u00e9decines alternatives",
    "sg:phone":"+32 14 23 69 27",
    "sg:postcode":"2250",
    "sg:province":"Antwerpen",
    "wof:name":"De Schanshoeve",
    "wof:placetype":"venue"
},
  "geometry": {"coordinates":[4.8870158195,51.1651306152],"type":"Point"}
}