{
  "type": "Feature",
  "properties": {
    "iso:country":"BE",
    "sg:address":"Gasthuisstraat 6",
    "sg:city":"Beerse",
    "sg:classifiers":[
        {
            "category":"Home & Garden",
            "subcategory":"Household Appliances",
            "type":"Retail Goods"
        }
    ],
    "sg:phone":"+32 14 61 40 27",
    "sg:postcode":"2340",
    "sg:province":"Antwerpen",
    "sg:tags":[
        "housewares",
        "-"
    ],
    "wof:name":"Van Hees",
    "wof:placetype":"venue"
},
  "geometry": {"coordinates":[4.8562989235,51.320400238],"type":"Point"}
}