{
  "type": "Feature",
  "properties": {
    "iso:country":"BE",
    "sg:address":"Rue De Fl\u00e9ron 147",
    "sg:city":"Li\u00e8ge 1 (jupille-sur-meuse)",
    "sg:classifiers":[
        {
            "category":"Personal",
            "subcategory":"Beauty Salon",
            "type":"Services"
        }
    ],
    "sg:phone":"+32 4 362 72 79",
    "sg:postcode":"4020",
    "sg:province":"Li\u00e8ge",
    "sg:tags":[
        "lady",
        "-",
        "hairdressing"
    ],
    "wof:name":"Willem G",
    "wof:placetype":"venue"
},
  "geometry": {"coordinates":[5.6560130119,50.637878418],"type":"Point"}
}