{
  "type": "Feature",
  "properties": {
    "addr:full":"Werkenplein 23 Kortemark (werken) West-Vlaanderen 8610",
    "addr:housenumber":"23",
    "addr:postcode":"8610",
    "addr:street":"Werkenplein",
    "iso:country":"BE",
    "sg:address":"Werkenplein 23",
    "sg:city":"Kortemark (werken)",
    "sg:classifiers":[
        {
            "category":"Insurance",
            "subcategory":"Insurance Agent",
            "type":"Services"
        }
    ],
    "sg:phone":"+32 51 56 72 60",
    "sg:postcode":"8610",
    "sg:province":"West-Vlaanderen",
    "sg:tags":[
        "broker"
    ],
    "wof:name":"Van Steenkiste & Van Ackere",
    "wof:placetype":"venue"
},
  "geometry": {"coordinates":[2.998914957,51.0267982483],"type":"Point"}
}