{
  "type": "Feature",
  "properties": {
    "addr:full":"Marktplein 22 Wijnegem Antwerpen 2110",
    "addr:housenumber":"22",
    "addr:postcode":"2110",
    "addr:street":"Marktplein",
    "iso:country":"BE",
    "sg:address":"Marktplein 22",
    "sg:city":"Wijnegem",
    "sg:orig_category":"Avocats and conseillers juridiques",
    "sg:phone":"+32 3 353 18 13",
    "sg:postcode":"2110",
    "sg:province":"Antwerpen",
    "wof:name":"E. Joris",
    "wof:placetype":"venue"
},
  "geometry": {"coordinates":[4.5234408379,51.2268295288],"type":"Point"}
}