{
  "type": "Feature",
  "properties": {
    "addr:full":"Markt 36 Eeklo Oost-Vlaanderen 9900",
    "addr:housenumber":"36",
    "addr:postcode":"9900",
    "addr:street":"Markt",
    "iso:country":"BE",
    "sg:address":"Markt 36",
    "sg:city":"Eeklo",
    "sg:classifiers":[
        {
            "category":"Bars & Pubs",
            "type":"Food & Drink"
        }
    ],
    "sg:phone":"+32 9 377 18 58",
    "sg:postcode":"9900",
    "sg:province":"Oost-Vlaanderen",
    "wof:name":"Gouden Pluim",
    "wof:placetype":"venue"
},
  "geometry": {"coordinates":[3.5657660961,51.1846199036],"type":"Point"}
}