{
  "type": "Feature",
  "properties": {
    "addr:full":"Lostraat 8 Wingene (zwevezele) West-Vlaanderen 8750",
    "addr:housenumber":"8",
    "addr:postcode":"8750",
    "addr:street":"Lostraat",
    "iso:country":"BE",
    "sg:address":"Lostraat 8",
    "sg:city":"Wingene (zwevezele)",
    "sg:classifiers":[
        {
            "category":"Professional",
            "subcategory":"Computer Services",
            "type":"Services"
        }
    ],
    "sg:phone":"+32 51 61 34 72",
    "sg:postcode":"8750",
    "sg:province":"West-Vlaanderen",
    "sg:tags":[
        "-",
        "processing",
        "data"
    ],
    "wof:name":"Deprouw Computers",
    "wof:placetype":"venue"
},
  "geometry": {"coordinates":[3.2290570736,51.053150177],"type":"Point"}
}