{
  "type": "Feature",
  "properties": {
    "iso:country":"BE",
    "sg:address":"Roelstraat 22",
    "sg:city":"Zoutleeuw",
    "sg:orig_category":"Eleveurs de volaille",
    "sg:phone":"+32 11 58 74 87",
    "sg:postcode":"3440",
    "sg:province":"Vlaams-Brabant",
    "wof:name":"Ivo Beeterens",
    "wof:placetype":"venue"
},
  "geometry": {"coordinates":[5.0764818192,50.8652076721],"type":"Point"}
}