{
  "type": "Feature",
  "properties": {
    "addr:full":"Handboogstraat 6 Kortrijk West-Vlaanderen 8500",
    "addr:housenumber":"6",
    "addr:postcode":"8500",
    "addr:street":"Handboogstraat",
    "iso:country":"BE",
    "sg:address":"Handboogstraat 6",
    "sg:city":"Kortrijk",
    "sg:classifiers":[
        {
            "category":"Professional",
            "subcategory":"Employment Agencies",
            "type":"Services"
        }
    ],
    "sg:phone":"+32 56 26 06 26",
    "sg:postcode":"8500",
    "sg:province":"West-Vlaanderen",
    "sg:tags":[
        "temping",
        "-",
        "manual"
    ],
    "wof:name":"Plus Uitzendkrachten",
    "wof:placetype":"venue"
},
  "geometry": {"coordinates":[3.2644979954,50.8294334412],"type":"Point"}
}