{
  "type": "Feature",
  "properties": {
    "addr:full":"Rue Des Croisiers 21 Namur Namur 5000",
    "addr:housenumber":"21",
    "addr:postcode":"5000",
    "addr:street":"Rue Des Croisiers",
    "iso:country":"BE",
    "sg:address":"Rue Des Croisiers 21",
    "sg:city":"Namur",
    "sg:orig_category":"Tijdelijke werkgelegenheid and uitzendkantoren",
    "sg:phone":"+32 81 22 61 69",
    "sg:postcode":"5000",
    "sg:province":"Namur",
    "wof:name":"Vedior Interim",
    "wof:placetype":"venue"
},
  "geometry": {"coordinates":[4.8641500473,50.4671974182],"type":"Point"}
}