{
  "type": "Feature",
  "properties": {
    "addr:full":"Rue Saint-jacques 32 Namur Namur 5000",
    "addr:housenumber":"32",
    "addr:postcode":"5000",
    "addr:street":"Rue Saint-Jacques",
    "iso:country":"BE",
    "sg:address":"Rue Saint-jacques 32",
    "sg:city":"Namur",
    "sg:orig_category":"Beautyfarms, relaxatie and lichamelijk welzijn Schoonheidssalons",
    "sg:phone":"+32 81 22 55 10",
    "sg:postcode":"5000",
    "sg:province":"Namur",
    "wof:name":"La Plage Esthetique",
    "wof:placetype":"venue"
},
  "geometry": {"coordinates":[4.8640828133,50.4652137756],"type":"Point"}
}