{
  "type": "Feature",
  "properties": {
    "iso:country":"BE",
    "sg:address":"Chem.bon Dieu De Gibloux 11",
    "sg:city":"Waterloo",
    "sg:orig_category":"Kinderopvang",
    "sg:phone":"+32 2 353 04 08",
    "sg:postcode":"1410",
    "sg:province":"Brabant Wallon",
    "wof:name":"Cr\u00c8che La Sonatine",
    "wof:placetype":"venue"
},
  "geometry": {"coordinates":[4.4004359245,50.7053794861],"type":"Point"}
}