{
  "type": "Feature",
  "properties": {
    "addr:full":"Corn. Vissenaekensplein 18 Begijnendijk (betekom) Vlaams-Brabant 3130",
    "addr:housenumber":"18",
    "addr:postcode":"3130",
    "iso:country":"BE",
    "sg:address":"Corn. Vissenaekensplein 18",
    "sg:city":"Begijnendijk (betekom)",
    "sg:classifiers":[
        {
            "category":"Juice Bar",
            "subcategory":"None",
            "type":"Food & Drink"
        }
    ],
    "sg:phone":"+32 16 56 60 97",
    "sg:postcode":"3130",
    "sg:province":"Vlaams-Brabant",
    "sg:tags":[
        "water",
        "soft"
    ],
    "wof:name":"Brouwerij De Schrans",
    "wof:placetype":"venue"
},
  "geometry": {"coordinates":[4.7848348618,50.9859199524],"type":"Point"}
}