{
  "type": "Feature",
  "properties": {
    "addr:full":"Bergensesteenweg 226 Sint-pieters-leeuw Vlaams-Brabant 1600",
    "addr:housenumber":"226",
    "addr:postcode":"1600",
    "addr:street":"Bergensesteenweg",
    "iso:country":"BE",
    "sg:address":"Bergensesteenweg 226",
    "sg:city":"Sint-pieters-leeuw",
    "sg:orig_category":"M\u00e9decins and sp\u00e9cialistes",
    "sg:phone":"+32 2 377 03 61",
    "sg:postcode":"1600",
    "sg:province":"Vlaams-Brabant",
    "wof:name":"Robert De Corte",
    "wof:placetype":"venue"
},
  "geometry": {"coordinates":[4.2827301025,50.7930984497],"type":"Point"}
}