{
  "type": "Feature",
  "properties": {
    "iso:country":"BE",
    "sg:address":"Tabakbergstraat 6",
    "sg:city":"Tervuren",
    "sg:classifiers":[
        {
            "category":"Personal",
            "subcategory":"Beauty Salon",
            "type":"Services"
        }
    ],
    "sg:phone":"+32 2 767 49 39",
    "sg:postcode":"3080",
    "sg:province":"Vlaams-Brabant",
    "sg:tags":[
        "de",
        "coiffure"
    ],
    "wof:name":"Marie Spapen",
    "wof:placetype":"venue"
},
  "geometry": {"coordinates":[4.5062870979,50.8195838928],"type":"Point"}
}