{
  "type": "Feature",
  "properties": {
    "addr:full":"Kouter 7 Bertem Vlaams-Brabant 3060",
    "addr:housenumber":"7",
    "addr:postcode":"3060",
    "addr:street":"Kouter",
    "iso:country":"BE",
    "sg:address":"Kouter 7",
    "sg:city":"Bertem",
    "sg:classifiers":[
        {
            "category":"Arena",
            "subcategory":"Sports Club",
            "type":"Entertainment"
        }
    ],
    "sg:phone":"+32 16 48 08 28",
    "sg:postcode":"3060",
    "sg:province":"Vlaams-Brabant",
    "sg:tags":[
        "de"
    ],
    "wof:name":"Paradijske Bertem",
    "wof:placetype":"venue"
},
  "geometry": {"coordinates":[4.6272158623,50.8707313538],"type":"Point"}
}