{
  "type": "Feature",
  "properties": {
    "iso:country":"BE",
    "sg:address":"Steenkensstraat 1",
    "sg:city":"Laakdal",
    "sg:orig_category":"Rundveehouders",
    "sg:phone":"+32 14 86 79 83",
    "sg:postcode":"2430",
    "sg:province":"Antwerpen",
    "wof:name":"Franciscus Peeters",
    "wof:placetype":"venue"
},
  "geometry": {"coordinates":[5.0687851906,51.0857543945],"type":"Point"}
}