{
  "type": "Feature",
  "properties": {
    "iso:country":"BE",
    "sg:address":"Langemuntstraat 4",
    "sg:city":"Ninove",
    "sg:orig_category":"Herenkledingzaken",
    "sg:phone":"+32 54 33 24 19",
    "sg:postcode":"9400",
    "sg:province":"Oost-Vlaanderen",
    "wof:name":"Huis Denys - De Backer",
    "wof:placetype":"venue"
},
  "geometry": {"coordinates":[4.0231080055,50.8354492188],"type":"Point"}
}