{
  "type": "Feature",
  "properties": {
    "addr:full":"Leopoldlaan 42 Eeklo Oost-Vlaanderen 9900",
    "addr:housenumber":"42",
    "addr:postcode":"9900",
    "addr:street":"Leopoldlaan",
    "iso:country":"BE",
    "sg:address":"Leopoldlaan 42",
    "sg:city":"Eeklo",
    "sg:orig_category":"Paramedische behandelingen",
    "sg:phone":"+32 9 378 27 78",
    "sg:postcode":"9900",
    "sg:province":"Oost-Vlaanderen",
    "wof:name":"L. Vandevelde",
    "wof:placetype":"venue"
},
  "geometry": {"coordinates":[3.5477108955,51.193271637],"type":"Point"}
}