{
  "type": "Feature",
  "properties": {
    "addr:full":"Jeruzalemstraat 43 Erpe-mere (mere) Oost-Vlaanderen 9420",
    "addr:housenumber":"43",
    "addr:postcode":"9420",
    "addr:street":"Jeruzalemstraat;Mere Oost-Vlaanderen",
    "iso:country":"BE",
    "sg:address":"Jeruzalemstraat 43",
    "sg:city":"Erpe-mere (mere)",
    "sg:classifiers":[
        {
            "category":"Manufacturing",
            "subcategory":"Glass & Minerals",
            "type":"Manufacturing & Wholesale Goods"
        }
    ],
    "sg:phone":"+32 53 84 83 70",
    "sg:postcode":"9420",
    "sg:province":"Oost-Vlaanderen",
    "sg:tags":[
        "stained",
        "glazier",
        "-"
    ],
    "wof:name":"Moreels Hilde",
    "wof:placetype":"venue"
},
  "geometry": {"coordinates":[3.9753410816,50.9143562317],"type":"Point"}
}