{
  "type": "Feature",
  "properties": {
    "iso:country":"BE",
    "sg:address":"Gentsestraat 35",
    "sg:city":"Aalst",
    "sg:orig_category":"Plomberie, chauffage and installations sanitaires. Quincailleries. R\u00e9parations d'appareils \u00e9lectrom\u00e9",
    "sg:phone":"+32 53 77 60 01",
    "sg:postcode":"9300",
    "sg:province":"Oost-Vlaanderen",
    "wof:name":"De Bisschop",
    "wof:placetype":"venue"
},
  "geometry": {"coordinates":[4.0316910744,50.9382171631],"type":"Point"}
}