{
  "type": "Feature",
  "properties": {
    "addr:full":"Kouterveldstraat 4 Machelen (diegem) Vlaams-Brabant 1831",
    "addr:housenumber":"4",
    "addr:postcode":"1831",
    "addr:street":"Kouterveldstraat",
    "iso:country":"BE",
    "sg:address":"Kouterveldstraat 4",
    "sg:city":"Machelen (diegem)",
    "sg:classifiers":[
        {
            "category":"Manufacturing",
            "subcategory":"Electronics",
            "type":"Manufacturing & Wholesale Goods"
        }
    ],
    "sg:phone":"+32 2 725 75 34",
    "sg:postcode":"1831",
    "sg:province":"Vlaams-Brabant",
    "sg:tags":[
        "telecommunication",
        "system"
    ],
    "wof:name":"Fax Star Europe",
    "wof:placetype":"venue"
},
  "geometry": {"coordinates":[4.4359431267,50.8944854736],"type":"Point"}
}