{
  "type": "Feature",
  "properties": {
    "addr:full":"Rue Maurice Van Rolleghem 58 Bruxelles (jette) Bruxelles-Capitale 1090",
    "addr:housenumber":"58",
    "addr:postcode":"1090",
    "addr:street":"Rue Maurice Van Rolleghem",
    "iso:country":"BE",
    "sg:address":"Rue Maurice Van Rolleghem 58",
    "sg:city":"Bruxelles (jette)",
    "sg:classifiers":[
        {
            "category":"Retail",
            "subcategory":"Laundry & Dry Cleaning",
            "type":"Services"
        }
    ],
    "sg:phone":"+32 2 479 33 20",
    "sg:postcode":"1090",
    "sg:province":"Bruxelles-Capitale",
    "wof:name":"Sun-shine",
    "wof:placetype":"venue"
},
  "geometry": {"coordinates":[4.3217358589,50.8919677734],"type":"Point"}
}