{
  "type": "Feature",
  "properties": {
    "iso:country":"BE",
    "sg:address":"Heernisplein 2-3",
    "sg:city":"Gent (sint-amandsberg)",
    "sg:classifiers":[
        {
            "category":"Retail",
            "subcategory":"Self-service Laundry",
            "type":"Services"
        }
    ],
    "sg:phone":"+32 9 228 29 75",
    "sg:postcode":"9040",
    "sg:province":"Oost-Vlaanderen",
    "sg:tags":[
        "-",
        "outfit",
        "communion",
        "wear",
        "bridal",
        "rental",
        "formal"
    ],
    "wof:name":"De Telder Tailor",
    "wof:placetype":"venue"
},
  "geometry": {"coordinates":[3.7487370968,51.0524978638],"type":"Point"}
}