{
  "type": "Feature",
  "properties": {
    "iso:country":"BE",
    "sg:address":"Lakeman 92",
    "sg:city":"Londerzeel",
    "sg:classifiers":[
        {
            "category":"Professional",
            "subcategory":"Computer Services",
            "type":"Services"
        }
    ],
    "sg:phone":"+32 52 30 13 74",
    "sg:postcode":"1840",
    "sg:province":"Vlaams-Brabant",
    "sg:tags":[
        "-",
        "processing",
        "data",
        "software"
    ],
    "wof:name":"Vectis",
    "wof:placetype":"venue"
},
  "geometry": {"coordinates":[4.2786579132,50.9957809448],"type":"Point"}
}