{
  "type": "Feature",
  "properties": {
    "addr:full":"Beukenpark 1 Aalter Oost-Vlaanderen 9880",
    "addr:housenumber":"1",
    "addr:postcode":"9880",
    "addr:street":"Beukenpark",
    "iso:country":"BE",
    "sg:address":"Beukenpark 1",
    "sg:city":"Aalter",
    "sg:orig_category":"Meubelzaken, woning- and keukeninrichting",
    "sg:phone":"+32 9 374 67 05",
    "sg:postcode":"9880",
    "sg:province":"Oost-Vlaanderen",
    "wof:name":"Stani Holbrouck",
    "wof:placetype":"venue"
},
  "geometry": {"coordinates":[3.4521780014,51.0727157593],"type":"Point"}
}