{
  "type": "Feature",
  "properties": {
    "iso:country":"BE",
    "sg:address":"Rue Du Bon-lieu 1",
    "sg:city":"Virton",
    "sg:orig_category":"Location d'articles de sport, de sport nautique and de camping. Maisons de vacances. Clubs de sport",
    "sg:phone":"+32 63 57 01 44",
    "sg:postcode":"6760",
    "sg:province":"Luxembourg",
    "wof:name":"Camping Vall\u00c9e De Rabais",
    "wof:placetype":"venue"
},
  "geometry": {"coordinates":[5.5565981865,49.5808372498],"type":"Point"}
}