{
  "type": "Feature",
  "properties": {
    "addr:full":"Sint-rochusstraat 15 Aalst (nieuwerkerken) Oost-Vlaanderen 9320",
    "addr:housenumber":"15",
    "addr:postcode":"9320",
    "addr:street":"Sint-Rochusstraat",
    "iso:country":"BE",
    "sg:address":"Sint-rochusstraat 15",
    "sg:city":"Aalst (nieuwerkerken)",
    "sg:classifiers":[
        {
            "category":"Shopping",
            "subcategory":"Stationery & Office Supplies",
            "type":"Retail Goods"
        }
    ],
    "sg:phone":"+32 53 83 39 86",
    "sg:postcode":"9320",
    "sg:province":"Oost-Vlaanderen",
    "sg:tags":[
        "label"
    ],
    "wof:name":"Gevalo Nv",
    "wof:placetype":"venue"
},
  "geometry": {"coordinates":[4.0027980804,50.9176864624],"type":"Point"}
}