{
  "type": "Feature",
  "properties": {
    "addr:full":"Hollebeek 53 Temse Oost-Vlaanderen 9140",
    "addr:housenumber":"53",
    "addr:postcode":"9140",
    "addr:street":"Hollebeek",
    "iso:country":"BE",
    "sg:address":"Hollebeek 53",
    "sg:city":"Temse",
    "sg:orig_category":"HUISBRANDOLIE",
    "sg:phone":"+32 3 771 20 00",
    "sg:postcode":"9140",
    "sg:province":"Oost-Vlaanderen",
    "wof:name":"Troubleyn-de Bondt",
    "wof:placetype":"venue"
},
  "geometry": {"coordinates":[4.2365298271,51.1329612732],"type":"Point"}
}