{
  "type": "Feature",
  "properties": {
    "addr:full":"Rue Louise Debaty 18 Beauraing Namur 5570",
    "addr:housenumber":"18",
    "addr:postcode":"5570",
    "addr:street":"Rue Louise Debaty",
    "iso:country":"BE",
    "sg:address":"Rue Louise Debaty 18",
    "sg:city":"Beauraing",
    "sg:classifiers":[
        {
            "category":"Personal",
            "subcategory":"Beauty Salon",
            "type":"Services"
        }
    ],
    "sg:phone":"+32 82 71 36 90",
    "sg:postcode":"5570",
    "sg:province":"Namur",
    "sg:tags":[
        "de",
        "coiffure"
    ],
    "wof:name":"V\u00c9ronique Mathieu",
    "wof:placetype":"venue"
},
  "geometry": {"coordinates":[4.8943238258,50.1001930237],"type":"Point"}
}