{
  "type": "Feature",
  "properties": {
    "iso:country":"BE",
    "sg:address":"Bd. Des Alli\u00c9s",
    "sg:city":"Dottignies",
    "sg:orig_category":"Bloemen and planten Huisdieren and benodigdheden Royal Canin Tuinbenodigdheden",
    "sg:phone":"+32 56 48 53 33",
    "sg:postcode":"7711",
    "sg:province":"Hainaut",
    "wof:name":"Fauna Flor Sprl",
    "wof:placetype":"venue"
},
  "geometry": {"coordinates":[3.2862830162,50.7320098877],"type":"Point"}
}