{
  "type": "Feature",
  "properties": {
    "iso:country":"BE",
    "sg:address":"Broekstraat 4",
    "sg:city":"Kortenberg",
    "sg:orig_category":"Elektrische and elektronische apparatuur Gh",
    "sg:phone":"+32 2 758 00 20",
    "sg:postcode":"3078",
    "sg:province":"Vlaams-Brabant",
    "wof:name":"Sarel",
    "wof:placetype":"venue"
},
  "geometry": {"coordinates":[4.5894107819,50.8888015747],"type":"Point"}
}