{
  "type": "Feature",
  "properties": {
    "addr:full":"Lang-levenstraat 30 Elsene/ixelles Bruxelles-Capitale 1050",
    "addr:housenumber":"30",
    "addr:postcode":"1050",
    "addr:street":"Lang-Levenstraat",
    "iso:country":"BE",
    "sg:address":"Lang-levenstraat 30",
    "sg:city":"Elsene/ixelles",
    "sg:classifiers":[
        {
            "category":"Fast Food",
            "type":"Food & Drink"
        }
    ],
    "sg:phone":"+32 2 511 78 74",
    "sg:postcode":"1050",
    "sg:province":"Bruxelles-Capitale",
    "sg:tags":[
        "meeneem",
        "restaurant"
    ],
    "wof:name":"Snack-bar Dam\u00b4tartines",
    "wof:placetype":"venue"
},
  "geometry": {"coordinates":[4.3661599159,50.836151123],"type":"Point"}
}