{
  "type": "Feature",
  "properties": {
    "iso:country":"BE",
    "sg:address":"Stuurstraat 86",
    "sg:city":"Beveren",
    "sg:orig_category":"Entretien and r\u00e9parations de voitures",
    "sg:phone":"+32 3 775 08 61",
    "sg:postcode":"9120",
    "sg:province":"Oost-Vlaanderen",
    "wof:name":"Carrosserie De Wilde",
    "wof:placetype":"venue"
},
  "geometry": {"coordinates":[4.2229981422,51.1856498718],"type":"Point"}
}