{
  "type": "Feature",
  "properties": {
    "iso:country":"BE",
    "sg:address":"Krielweg 3ba",
    "sg:city":"Sint-laureins",
    "sg:orig_category":"Varkenskwekers",
    "sg:phone":"+32 9 379 97 47",
    "sg:postcode":"9980",
    "sg:province":"Oost-Vlaanderen",
    "wof:name":"Marnix Ingels",
    "wof:placetype":"venue"
},
  "geometry": {"coordinates":[3.5643939972,51.2436523438],"type":"Point"}
}