{
  "type": "Feature",
  "properties": {
    "addr:full":"Molsebaan 74 Retie Antwerpen 2470",
    "addr:housenumber":"74",
    "addr:postcode":"2470",
    "addr:street":"Molsebaan",
    "iso:country":"BE",
    "sg:address":"Molsebaan 74",
    "sg:city":"Retie",
    "sg:orig_category":"Huisdieren and benodigdheden",
    "sg:phone":"+32 14 37 18 27",
    "sg:postcode":"2470",
    "sg:province":"Antwerpen",
    "wof:name":"Benny Huysmans",
    "wof:placetype":"venue"
},
  "geometry": {"coordinates":[5.0904598236,51.2618713379],"type":"Point"}
}