{
  "type": "Feature",
  "properties": {
    "addr:full":"Stationsplein 4 Brakel Oost-Vlaanderen 9660",
    "addr:housenumber":"4",
    "addr:postcode":"9660",
    "addr:street":"Stationsplein",
    "iso:country":"BE",
    "sg:address":"Stationsplein 4",
    "sg:city":"Brakel",
    "sg:orig_category":"Aanleg van wegen, sportterreinen and vliegvelden Afbraak- and draineerwerken Huisvuilophaling and -v",
    "sg:phone":"+32 55 42 30 30",
    "sg:postcode":"9660",
    "sg:province":"Oost-Vlaanderen",
    "wof:name":"Roscam",
    "wof:placetype":"venue"
},
  "geometry": {"coordinates":[3.7662799358,50.8003311157],"type":"Point"}
}