{
  "type": "Feature",
  "properties": {
    "iso:country":"BE",
    "sg:address":"Rue Du Moulin-\u00c0-vent 20",
    "sg:city":"Gembloux",
    "sg:orig_category":"Produits pharmaceutiques Fab",
    "sg:phone":"+32 81 64 01 22",
    "sg:postcode":"5031",
    "sg:province":"Namur",
    "wof:name":"Fe. Phytophil Benelux",
    "wof:placetype":"venue"
},
  "geometry": {"coordinates":[4.7659392357,50.5773353577],"type":"Point"}
}