{
  "type": "Feature",
  "properties": {
    "iso:country":"BE",
    "sg:address":"Muilemlaan 53",
    "sg:city":"Ternat (sint-katherina-lombeek)",
    "sg:orig_category":"Cad/Cam systems",
    "sg:phone":"+32 2 582 72 64",
    "sg:postcode":"1742",
    "sg:province":"Vlaams-Brabant",
    "wof:name":"4d Select Nv",
    "wof:placetype":"venue"
},
  "geometry": {"coordinates":[4.1454210281,50.8761749268],"type":"Point"}
}