{
  "type": "Feature",
  "properties": {
    "iso:country":"BE",
    "sg:address":"Geraardsbergsesteenweg 117",
    "sg:city":"Aalst",
    "sg:orig_category":"Herstellingen and onderhoud van auto's",
    "sg:phone":"+32 53 83 08 02",
    "sg:postcode":"9320",
    "sg:province":"Oost-Vlaanderen",
    "wof:name":"Carrosserie Decoen",
    "wof:placetype":"venue"
},
  "geometry": {"coordinates":[4.0358109474,50.9313697815],"type":"Point"}
}