{
  "type": "Feature",
  "properties": {
    "iso:country":"BE",
    "sg:address":"Kerkstraat 1",
    "sg:city":"De Haan",
    "sg:classifiers":[
        {
            "category":"Restaurant",
            "type":"Food & Drink"
        }
    ],
    "sg:phone":"+32 50 41 30 95",
    "sg:postcode":"8420",
    "sg:province":"West-Vlaanderen",
    "wof:name":"Lams elektro Power",
    "wof:placetype":"venue"
},
  "geometry": {"coordinates":[3.0792000294,51.3011283875],"type":"Point"}
}