{
  "type": "Feature",
  "properties": {
    "addr:full":"Torkonjestr 67 Kortrijk West-Vlaanderen 8510",
    "addr:housenumber":"67",
    "addr:postcode":"8510",
    "addr:street":"Torkonjestr",
    "iso:country":"BE",
    "sg:address":"Torkonjestr 67",
    "sg:city":"Kortrijk",
    "sg:classifiers":[
        {
            "category":"Travel",
            "subcategory":"Hotels & Motels",
            "type":"Entertainment"
        }
    ],
    "sg:phone":"+32 56 21 41 24",
    "sg:postcode":"8510",
    "sg:province":"West-Vlaanderen",
    "sg:tags":[
        "hotels",
        "business",
        "restaurant"
    ],
    "wof:name":"Restaurant Carlton Bvba",
    "wof:placetype":"venue"
},
  "geometry": {"coordinates":[3.2358360291,50.7880134583],"type":"Point"}
}