{
  "type": "Feature",
  "properties": {
    "addr:full":"Boulevard Aristide Briand 19 Bruxelles (anderlecht) Bruxelles-Capitale 1070",
    "addr:housenumber":"19",
    "addr:postcode":"1070",
    "addr:street":"Boulevard Aristide Briand",
    "iso:country":"BE",
    "sg:address":"Boulevard Aristide Briand 19",
    "sg:city":"Bruxelles (anderlecht)",
    "sg:classifiers":[
        {
            "category":"Retail",
            "subcategory":"Auto Repair",
            "type":"Services"
        }
    ],
    "sg:phone":"+32 2 520 25 78",
    "sg:postcode":"1070",
    "sg:province":"Bruxelles-Capitale",
    "sg:tags":[
        "garage"
    ],
    "wof:name":"Paepsem (garage)",
    "wof:placetype":"venue"
},
  "geometry": {"coordinates":[4.3027029037,50.8290557861],"type":"Point"}
}