{
  "type": "Feature",
  "properties": {
    "iso:country":"BE",
    "sg:address":"Koning Albertstraat 8",
    "sg:city":"Scherpenheuvel-zichem",
    "sg:orig_category":"Studios photographiques",
    "sg:phone":"+32 13 77 57 23",
    "sg:postcode":"3270",
    "sg:province":"Vlaams-Brabant",
    "wof:name":"Fa. Sacha",
    "wof:placetype":"venue"
},
  "geometry": {"coordinates":[4.9710597992,50.9793930054],"type":"Point"}
}