{
  "type": "Feature",
  "properties": {
    "iso:country":"BE",
    "sg:address":"Du Roy De Blicquylaan 6",
    "sg:city":"Zaventem",
    "sg:orig_category":"Film-, tv- and videoproductie",
    "sg:phone":"+32 2 767 07 31",
    "sg:postcode":"1933",
    "sg:province":"Vlaams-Brabant",
    "wof:name":"Luc De Wilder",
    "wof:placetype":"venue"
},
  "geometry": {"coordinates":[4.5090317726,50.843421936],"type":"Point"}
}