{
  "type": "Feature",
  "properties": {
    "iso:country":"BE",
    "sg:address":"Kapelstraat 21",
    "sg:city":"Gooik",
    "sg:orig_category":"Avocats and conseillers juridiques",
    "sg:phone":"+32 54 56 76 22",
    "sg:postcode":"1755",
    "sg:province":"Vlaams-Brabant",
    "wof:name":"Ven Eckenrode Luc",
    "wof:placetype":"venue"
},
  "geometry": {"coordinates":[4.0670499802,50.7764396667],"type":"Point"}
}