{
  "type": "Feature",
  "properties": {
    "addr:full":"Rue Du Brou 15 Verviers Li\u00e8ge 4800",
    "addr:housenumber":"15",
    "addr:postcode":"4800",
    "addr:street":"Rue Du Brou",
    "iso:country":"BE",
    "sg:address":"Rue Du Brou 15",
    "sg:city":"Verviers",
    "sg:orig_category":"Chaussures",
    "sg:phone":"+32 87 33 15 40",
    "sg:postcode":"4800",
    "sg:province":"Li\u00e8ge",
    "wof:name":"Maison Marbaise",
    "wof:placetype":"venue"
},
  "geometry": {"coordinates":[5.859459877,50.5923500061],"type":"Point"}
}