{
  "type": "Feature",
  "properties": {
    "addr:full":"Aldestraat 35 Hasselt Limburg 3500",
    "addr:housenumber":"35",
    "addr:postcode":"3500",
    "addr:street":"Aldestraat",
    "iso:country":"BE",
    "sg:address":"Aldestraat 35",
    "sg:city":"Hasselt",
    "sg:orig_category":"Pain, p\u00e2tisseries and confiseries",
    "sg:phone":"+32 11 22 44 80",
    "sg:postcode":"3500",
    "sg:province":"Limburg",
    "wof:name":"Chocolat. Sweertvaegher",
    "wof:placetype":"venue"
},
  "geometry": {"coordinates":[5.335477829,50.9306297302],"type":"Point"}
}