{
  "type": "Feature",
  "properties": {
    "iso:country":"BE",
    "sg:address":"Joos De Ter Beerstlaan 33",
    "sg:city":"Pittem",
    "sg:orig_category":"Non-Classified Establishments",
    "sg:phone":"+32 51 46 43 41",
    "sg:postcode":"8740",
    "sg:province":"West-Vlaanderen",
    "wof:name":"Tal Nv",
    "wof:placetype":"venue"
},
  "geometry": {"coordinates":[3.2555780411,50.9932861328],"type":"Point"}
}