{
  "type": "Feature",
  "properties": {
    "iso:country":"BE",
    "sg:address":"Rue De La R\u00e9gence 55",
    "sg:city":"Li\u00e8ge 1",
    "sg:orig_category":"Newspapers, magazines, periodicals - Publishers",
    "sg:phone":"+32 4 384 44 20",
    "sg:postcode":"4000",
    "sg:province":"Li\u00e8ge",
    "wof:name":"Group Plus Belgium",
    "wof:placetype":"venue"
},
  "geometry": {"coordinates":[5.5757088661,50.6421089172],"type":"Point"}
}