{
  "type": "Feature",
  "properties": {
    "iso:country":"BE",
    "sg:address":"Destelbergenstraat 28",
    "sg:city":"Gent",
    "sg:orig_category":"Herstelling and restauratie van meubelen Stoelen and zitmeubelen Fab",
    "sg:phone":"+32 9 228 80 20",
    "sg:postcode":"9040",
    "sg:province":"Oost-Vlaanderen",
    "wof:name":"Astranova",
    "wof:placetype":"venue"
},
  "geometry": {"coordinates":[3.7543671131,51.0501823425],"type":"Point"}
}