{
  "type": "Feature",
  "properties": {
    "addr:full":"Rue Jules Destr\u00c9e 355-357 Quaregnon Hainaut 7390",
    "addr:postcode":"355-357;7390",
    "addr:street":"Rue Jules Destre\u0301E;Hainaut",
    "iso:country":"BE",
    "sg:address":"Rue Jules Destr\u00c9e 355-357",
    "sg:city":"Quaregnon",
    "sg:orig_category":"Quincailleries. Mat\u00e9riaux de construction Fabrication and montage de mobilier",
    "sg:phone":"+32 65 76 73 10",
    "sg:postcode":"7390",
    "sg:province":"Hainaut",
    "wof:name":"Bricorama",
    "wof:placetype":"venue"
},
  "geometry": {"coordinates":[3.8586659431,50.4432945251],"type":"Point"}
}