{
  "type": "Feature",
  "properties": {
    "iso:country":"BE",
    "sg:address":"Rue Neuve 4",
    "sg:city":"Mons",
    "sg:classifiers":[
        {
            "category":"Communications",
            "subcategory":"Film & Video Production",
            "type":"Services"
        }
    ],
    "sg:phone":"+32 65 34 78 00",
    "sg:postcode":"7000",
    "sg:province":"Hainaut",
    "sg:tags":[
        "realisation",
        "-"
    ],
    "wof:name":"A.v. Press",
    "wof:placetype":"venue"
},
  "geometry": {"coordinates":[3.9527499676,50.4554824829],"type":"Point"}
}