{
  "type": "Feature",
  "properties": {
    "iso:country":"BE",
    "sg:address":"Rue Beaugrand 16",
    "sg:city":"Ecaussinnes",
    "sg:orig_category":"V\u00e9t\u00e9rinaires",
    "sg:phone":"+32 67 48 53 38",
    "sg:postcode":"7190",
    "sg:province":"Hainaut",
    "wof:name":"Carl Grosjean",
    "wof:placetype":"venue"
},
  "geometry": {"coordinates":[4.1683731079,50.5619812012],"type":"Point"}
}