{
  "type": "Feature",
  "properties": {
    "addr:full":"Kortrijkstraat 236 Wevelgem West-Vlaanderen 8560",
    "addr:housenumber":"236",
    "addr:postcode":"8560",
    "addr:street":"Kortrijkstraat",
    "iso:country":"BE",
    "sg:address":"Kortrijkstraat 236",
    "sg:city":"Wevelgem",
    "sg:orig_category":"Serres and speciale beglazing",
    "sg:phone":"+32 56 41 35 78",
    "sg:postcode":"8560",
    "sg:province":"West-Vlaanderen",
    "wof:name":"Glascentrale",
    "wof:placetype":"venue"
},
  "geometry": {"coordinates":[3.1964700222,50.8125114441],"type":"Point"}
}