{
  "type": "Feature",
  "properties": {
    "addr:full":"Nieuwstraat 62 Torhout West-Vlaanderen 8820",
    "addr:housenumber":"62",
    "addr:postcode":"8820",
    "addr:street":"Nieuwstraat",
    "iso:country":"BE",
    "sg:address":"Nieuwstraat 62",
    "sg:city":"Torhout",
    "sg:classifiers":[
        {
            "category":"Insurance",
            "subcategory":"Insurance Agent",
            "type":"Services"
        }
    ],
    "sg:phone":"+32 50 21 61 36",
    "sg:postcode":"8820",
    "sg:province":"West-Vlaanderen",
    "sg:tags":[
        "verzekeringsmakelaars",
        "expert"
    ],
    "wof:name":"B. Van Loock",
    "wof:placetype":"venue"
},
  "geometry": {"coordinates":[3.0991508961,51.0652694702],"type":"Point"}
}