{
  "type": "Feature",
  "properties": {
    "iso:country":"BE",
    "sg:address":"Rue De La Clef 15",
    "sg:city":"Soumagne (melen)",
    "sg:classifiers":[
        {
            "category":"Conference Center",
            "type":"Public Place"
        }
    ],
    "sg:phone":"+32 87 66 15 32",
    "sg:postcode":"4633",
    "sg:province":"Li\u00e8ge",
    "sg:tags":[
        "terrain",
        "vehicle"
    ],
    "wof:name":"Hummer-off Road Service Bvba",
    "wof:placetype":"venue"
},
  "geometry": {"coordinates":[5.7360901833,50.6460418701],"type":"Point"}
}