{
  "type": "Feature",
  "properties": {
    "iso:country":"BE",
    "sg:address":"Kaaskerstraat 69",
    "sg:city":"Dixmude",
    "sg:orig_category":"Sportclubs",
    "sg:phone":"+32 51 50 28 77",
    "sg:postcode":"8600",
    "sg:province":"West-Vlaanderen",
    "wof:name":"Ippon Diksmuide",
    "wof:placetype":"venue"
},
  "geometry": {"coordinates":[2.8440289497,51.0345230103],"type":"Point"}
}