{
  "type": "Feature",
  "properties": {
    "addr:full":"Handelstraat 40 Antwerpen Antwerpen 2060",
    "addr:housenumber":"40",
    "addr:postcode":"2060",
    "addr:street":"Handelstraat",
    "iso:country":"BE",
    "sg:address":"Handelstraat 40",
    "sg:city":"Antwerpen",
    "sg:orig_category":"R\u00e9parations d'appareils \u00e9lectrom\u00e9nagers",
    "sg:phone":"+32 3 271 02 08",
    "sg:postcode":"2060",
    "sg:province":"Antwerpen",
    "wof:name":"Antwerp Tv Shop",
    "wof:placetype":"venue"
},
  "geometry": {"coordinates":[4.429090023,51.2235412598],"type":"Point"}
}