{
  "type": "Feature",
  "properties": {
    "iso:country":"BE",
    "sg:address":"Het Wijngaardeke 7",
    "sg:city":"De Pinte",
    "sg:orig_category":"Artsen and specialisten",
    "sg:phone":"+32 9 358 47 48",
    "sg:postcode":"9840",
    "sg:province":"Oost-Vlaanderen",
    "wof:name":"De Smet M.",
    "wof:placetype":"venue"
},
  "geometry": {"coordinates":[3.6936559677,50.9800834656],"type":"Point"}
}