{
  "type": "Feature",
  "properties": {
    "addr:full":"Het Hazepad 3 Aarschot (langdorp) Vlaams-Brabant 3201",
    "addr:housenumber":"3",
    "addr:postcode":"3201",
    "addr:street":"Het Hazepad",
    "iso:country":"BE",
    "sg:address":"Het Hazepad 3",
    "sg:city":"Aarschot (langdorp)",
    "sg:orig_category":"Imitation jewelry - Mfg.& Whol.",
    "sg:phone":"+32 16 56 15 56",
    "sg:postcode":"3201",
    "sg:province":"Vlaams-Brabant",
    "wof:name":"Manu",
    "wof:placetype":"venue"
},
  "geometry": {"coordinates":[4.8658490181,51.0033035278],"type":"Point"}
}