{
  "type": "Feature",
  "properties": {
    "iso:country":"BE",
    "sg:address":"Ch. Cappellestraat 150",
    "sg:city":"Menen",
    "sg:orig_category":"Boekhouders",
    "sg:phone":"+32 56 51 71 00",
    "sg:postcode":"8930",
    "sg:province":"West-Vlaanderen",
    "wof:name":"Alain Dumont",
    "wof:placetype":"venue"
},
  "geometry": {"coordinates":[3.0942060947,50.7902183533],"type":"Point"}
}