{
  "type": "Feature",
  "properties": {
    "addr:full":"Cannaertstraat 25 Kortrijk West-Vlaanderen 8510",
    "addr:housenumber":"25",
    "addr:postcode":"8510",
    "addr:street":"Cannaertstraat",
    "iso:country":"BE",
    "sg:address":"Cannaertstraat 25",
    "sg:city":"Kortrijk",
    "sg:orig_category":"Eleveurs de bovins",
    "sg:phone":"+32 56 22 12 21",
    "sg:postcode":"8510",
    "sg:province":"West-Vlaanderen",
    "wof:name":"Gerard Lefebvre",
    "wof:placetype":"venue"
},
  "geometry": {"coordinates":[3.2601420879,50.7982711792],"type":"Point"}
}