{
  "type": "Feature",
  "properties": {
    "iso:country":"BE",
    "sg:address":"Kerkhofpad 2",
    "sg:city":"Hoogstraten",
    "sg:orig_category":"Kapsalons",
    "sg:phone":"+32 3 314 68 95",
    "sg:postcode":"2322",
    "sg:province":"Antwerpen",
    "wof:name":"Coiffure Rian",
    "wof:placetype":"venue"
},
  "geometry": {"coordinates":[4.763384819,51.4160041809],"type":"Point"}
}