{
  "type": "Feature",
  "properties": {
    "addr:full":"Vier Linden 7 Kortrijk (heule) West-Vlaanderen 8501",
    "addr:housenumber":"7",
    "addr:postcode":"8501",
    "addr:street":"Linden",
    "iso:country":"BE",
    "sg:address":"Vier Linden 7",
    "sg:city":"Kortrijk (heule)",
    "sg:classifiers":[
        {
            "category":"Home & Garden",
            "subcategory":"Hardware",
            "type":"Retail Goods"
        }
    ],
    "sg:phone":"+32 56 36 45 11",
    "sg:postcode":"8501",
    "sg:province":"West-Vlaanderen",
    "sg:tags":[
        "equipment",
        "woodworking",
        "machinery"
    ],
    "wof:name":"Lecot Metaalwaren",
    "wof:placetype":"venue"
},
  "geometry": {"coordinates":[3.2424449921,50.8494491577],"type":"Point"}
}