{
  "type": "Feature",
  "properties": {
    "addr:full":"Avenue Albert I 23 Charleroi (mont-sur-marchienne) Hainaut 6032",
    "addr:housenumber":"23",
    "addr:postcode":"6032",
    "addr:street":"Avenue Albert I",
    "iso:country":"BE",
    "sg:address":"Avenue Albert I 23",
    "sg:city":"Charleroi (mont-sur-marchienne)",
    "sg:classifiers":[
        {
            "category":"Professional",
            "subcategory":"Management & Consulting",
            "type":"Services"
        }
    ],
    "sg:phone":"+32 71 47 02 18",
    "sg:postcode":"6032",
    "sg:province":"Hainaut",
    "sg:tags":[
        "consultant"
    ],
    "wof:name":"Arina Sprl",
    "wof:placetype":"venue"
},
  "geometry": {"coordinates":[4.403854847,50.3877906799],"type":"Point"}
}