{
  "type": "Feature",
  "properties": {
    "addr:full":"Hospitaalstraat 51 Zottegem Oost-Vlaanderen 9620",
    "addr:housenumber":"51",
    "addr:postcode":"9620",
    "addr:street":"Hospitaalstraat",
    "iso:country":"BE",
    "sg:address":"Hospitaalstraat 51",
    "sg:city":"Zottegem",
    "sg:orig_category":"Toeristische diensten",
    "sg:phone":"+32 9 360 27 93",
    "sg:postcode":"9620",
    "sg:province":"Oost-Vlaanderen",
    "wof:name":"G.v.v.v Zwalmstreek",
    "wof:placetype":"venue"
},
  "geometry": {"coordinates":[3.8130059242,50.8700294495],"type":"Point"}
}