{
  "type": "Feature",
  "properties": {
    "addr:full":"Gr\u00fcfflingen 41 Burg-reuland (thommen) Li\u00e8ge 4791",
    "addr:housenumber":"41",
    "addr:postcode":"4791",
    "addr:street":"Gruefflingen;Thommen",
    "iso:country":"BE",
    "sg:address":"Gr\u00fcfflingen 41",
    "sg:city":"Burg-reuland (thommen)",
    "sg:classifiers":[
        {
            "category":"Transit Center",
            "subcategory":"Freight",
            "type":"Transportation"
        }
    ],
    "sg:phone":"+32 80 42 04 30",
    "sg:postcode":"4791",
    "sg:province":"Li\u00e8ge",
    "sg:tags":[
        "pallet",
        "truck",
        "hand"
    ],
    "wof:name":"Schaefer",
    "wof:placetype":"venue"
},
  "geometry": {"coordinates":[6.0877599716,50.2253112793],"type":"Point"}
}