{
  "type": "Feature",
  "properties": {
    "addr:full":"Nieuwelaan 29 Kapellen Antwerpen 2950",
    "addr:housenumber":"29",
    "addr:postcode":"2950",
    "addr:street":"Nieuwelaan",
    "iso:country":"BE",
    "sg:address":"Nieuwelaan 29",
    "sg:city":"Kapellen",
    "sg:orig_category":"Agences de voyages",
    "sg:phone":"+32 3 605 35 02",
    "sg:postcode":"2950",
    "sg:province":"Antwerpen",
    "wof:name":"Master Tours",
    "wof:placetype":"venue"
},
  "geometry": {"coordinates":[4.4446539879,51.3295478821],"type":"Point"}
}