{
  "type": "Feature",
  "properties": {
    "addr:full":"Rue De L'escaille 6 Les Bons Villers (villers-perwin) Hainaut 6210",
    "addr:housenumber":"6",
    "addr:postcode":"6210",
    "addr:street":"Rue De L'Escaille",
    "iso:country":"BE",
    "sg:address":"Rue De L'escaille 6",
    "sg:city":"Les Bons Villers (villers-perwin)",
    "sg:classifiers":[
        {
            "category":"Manufacturing",
            "subcategory":"Tools & Machinery",
            "type":"Manufacturing & Wholesale Goods"
        }
    ],
    "sg:phone":"+32 71 85 31 99",
    "sg:postcode":"6210",
    "sg:province":"Hainaut",
    "sg:tags":[
        "builder"
    ],
    "wof:name":"Dumont De Chassart V",
    "wof:placetype":"venue"
},
  "geometry": {"coordinates":[4.4767231941,50.5267028809],"type":"Point"}
}