{
  "type": "Feature",
  "properties": {
    "iso:country":"BE",
    "sg:address":"Boulevard Chapman 18",
    "sg:city":"Spa",
    "sg:classifiers":[
        {
            "category":"Health Services",
            "subcategory":"Dentist",
            "type":"Services"
        }
    ],
    "sg:phone":"+32 87 77 06 09",
    "sg:postcode":"4900",
    "sg:province":"Li\u00e8ge",
    "wof:name":"Dagrain R",
    "wof:placetype":"venue"
},
  "geometry": {"coordinates":[5.86714077,50.4886894226],"type":"Point"}
}