{
  "type": "Feature",
  "properties": {
    "addr:full":"Torhoutsesteenweg 624 Oostende West-Vlaanderen 8400",
    "addr:housenumber":"624",
    "addr:postcode":"8400",
    "addr:street":"Torhoutsesteenweg",
    "iso:country":"BE",
    "sg:address":"Torhoutsesteenweg 624",
    "sg:city":"Oostende",
    "sg:orig_category":"Groenten and fruit Gh Herstellingen and onderhoud van auto's Voertuigen",
    "sg:phone":"+32 59 80 59 55",
    "sg:postcode":"8400",
    "sg:province":"West-Vlaanderen",
    "wof:name":"American Prestige Cars",
    "wof:placetype":"venue"
},
  "geometry": {"coordinates":[2.9064500332,51.2142601013],"type":"Point"}
}