{
  "type": "Feature",
  "properties": {
    "iso:country":"BE",
    "sg:address":"Bondgenotenlaan 2",
    "sg:city":"Landen",
    "sg:classifiers":[
        {
            "category":"Shopping",
            "subcategory":"Gifts & Souvenirs",
            "type":"Retail Goods"
        }
    ],
    "sg:phone":"+32 11 88 16 09",
    "sg:postcode":"3400",
    "sg:province":"Vlaams-Brabant",
    "sg:tags":[
        "-"
    ],
    "wof:name":"Mombaerts L",
    "wof:placetype":"venue"
},
  "geometry": {"coordinates":[5.0813350677,50.7503166199],"type":"Point"}
}