{
  "type": "Feature",
  "properties": {
    "addr:full":"Brouwerijstraat 60 Landen Vlaams-Brabant 3400",
    "addr:housenumber":"60",
    "addr:postcode":"3400",
    "addr:street":"Brouwerijstraat",
    "iso:country":"BE",
    "sg:address":"Brouwerijstraat 60",
    "sg:city":"Landen",
    "sg:orig_category":"Catering and organisatie van feesten",
    "sg:phone":"+32 16 78 01 01",
    "sg:postcode":"3400",
    "sg:province":"Vlaams-Brabant",
    "wof:name":"Bart De Ceuster",
    "wof:placetype":"venue"
},
  "geometry": {"coordinates":[5.0131602287,50.7825431824],"type":"Point"}
}