{
  "type": "Feature",
  "properties": {
    "iso:country":"BE",
    "sg:address":"Rue G\u00e9n\u00e9ral Tombeur 18",
    "sg:city":"Bruxelles (etterbeek)",
    "sg:classifiers":[
        {
            "category":"Professional",
            "subcategory":"Testing Lab",
            "type":"Services"
        }
    ],
    "sg:phone":"+32 2 735 33 05",
    "sg:postcode":"1040",
    "sg:province":"Bruxelles-Capitale",
    "sg:tags":[
        "laboratory",
        "photographic",
        "film"
    ],
    "wof:name":"Sadocolor Sprl",
    "wof:placetype":"venue"
},
  "geometry": {"coordinates":[4.3962521553,50.8362846375],"type":"Point"}
}