{
  "type": "Feature",
  "properties": {
    "addr:full":"Lozermolenstraat 30 Kruishoutem Oost-Vlaanderen 9770",
    "addr:housenumber":"30",
    "addr:postcode":"9770",
    "addr:street":"Lozermolenstraat",
    "iso:country":"BE",
    "sg:address":"Lozermolenstraat 30",
    "sg:city":"Kruishoutem",
    "sg:orig_category":"Elektrische installaties voor woningen",
    "sg:phone":"+32 9 380 04 97",
    "sg:postcode":"9770",
    "sg:province":"Oost-Vlaanderen",
    "wof:name":"Kurt Dewispelaere",
    "wof:placetype":"venue"
},
  "geometry": {"coordinates":[3.544975996,50.9308052063],"type":"Point"}
}