{
  "type": "Feature",
  "properties": {
    "iso:country":"BE",
    "sg:address":"Place De La Wanze 3",
    "sg:city":"Le Roeulx",
    "sg:orig_category":"Krantenwinkels Rookartikelen",
    "sg:phone":"+32 65 87 20 05",
    "sg:postcode":"7070",
    "sg:province":"Hainaut",
    "wof:name":"Librairie De La Place",
    "wof:placetype":"venue"
},
  "geometry": {"coordinates":[4.1086750031,50.5015830994],"type":"Point"}
}