{
  "type": "Feature",
  "properties": {
    "addr:full":"Overimpestraat 143 Lede Oost-Vlaanderen 9340",
    "addr:housenumber":"143",
    "addr:postcode":"9340",
    "addr:street":"Overimpestraat",
    "iso:country":"BE",
    "sg:address":"Overimpestraat 143",
    "sg:city":"Lede",
    "sg:orig_category":"Woningbouw",
    "sg:phone":"+32 53 80 46 31",
    "sg:postcode":"9340",
    "sg:province":"Oost-Vlaanderen",
    "wof:name":"Blondeel Jan & Zoon",
    "wof:placetype":"venue"
},
  "geometry": {"coordinates":[3.9647300243,50.9580383301],"type":"Point"}
}