{
  "type": "Feature",
  "properties": {
    "addr:full":"Rue Osseghem 194-196 Bruxelles (molenbeek-saint-jean) Bruxelles-Capitale 1080",
    "addr:postcode":"194-196;molenbeek-saint-jean;1080",
    "addr:street":"Rue Osseghem",
    "iso:country":"BE",
    "sg:address":"Rue Osseghem 194-196",
    "sg:city":"Bruxelles (molenbeek-saint-jean)",
    "sg:classifiers":[
        {
            "category":"Shopping",
            "subcategory":"Pets & Pet Supplies",
            "type":"Retail Goods"
        }
    ],
    "sg:phone":"+32 2 410 39 28",
    "sg:postcode":"1080",
    "sg:province":"Bruxelles-Capitale",
    "sg:tags":[
        "shop",
        "-"
    ],
    "wof:name":"Depredomme Marc Bvba",
    "wof:placetype":"venue"
},
  "geometry": {"coordinates":[4.3118448257,50.8523139954],"type":"Point"}
}