{
  "type": "Feature",
  "properties": {
    "iso:country":"BE",
    "sg:address":"Pl Albert I 6",
    "sg:city":"Sambreville",
    "sg:classifiers":[
        {
            "category":"Communications",
            "subcategory":"Radio Station",
            "type":"Services"
        }
    ],
    "sg:phone":"+32 71 77 43 13",
    "sg:postcode":"5060",
    "sg:province":"Namur",
    "sg:tags":[
        "diffusion",
        "production",
        "de",
        "programme"
    ],
    "wof:name":"Radio Angelica",
    "wof:placetype":"venue"
},
  "geometry": {"coordinates":[4.6215620041,50.4188308716],"type":"Point"}
}