{
  "type": "Feature",
  "properties": {
    "iso:country":"BE",
    "sg:address":"A. Waucquezlaan 24",
    "sg:city":"Dilbeek",
    "sg:orig_category":"M\u00e9decins and sp\u00e9cialistes",
    "sg:phone":"+32 2 463 04 24",
    "sg:postcode":"1700",
    "sg:province":"Vlaams-Brabant",
    "wof:name":"Didier Clause",
    "wof:placetype":"venue"
},
  "geometry": {"coordinates":[4.2813482285,50.8476600647],"type":"Point"}
}