{
  "type": "Feature",
  "properties": {
    "iso:country":"BE",
    "sg:address":"Chauss\u00e9e De Bascoup 115",
    "sg:city":"Anderlues",
    "sg:classifiers":[
        {
            "category":"Retail",
            "subcategory":"Auto Repair",
            "type":"Services"
        }
    ],
    "sg:phone":"+32 71 54 19 09",
    "sg:postcode":"6150",
    "sg:province":"Hainaut",
    "sg:tags":[
        "garage"
    ],
    "wof:name":"Audi-vag-detournay",
    "wof:placetype":"venue"
},
  "geometry": {"coordinates":[4.2827010155,50.4136695862],"type":"Point"}
}