{
  "type": "Feature",
  "properties": {
    "addr:full":"Rue Du Cou\u00ebt 64 Mouscron Hainaut 7700",
    "addr:housenumber":"64",
    "addr:postcode":"7700",
    "addr:street":"Rue Du Coue\u0308T",
    "iso:country":"BE",
    "sg:address":"Rue Du Cou\u00ebt 64",
    "sg:city":"Mouscron",
    "sg:classifiers":[
        {
            "category":"Professional",
            "subcategory":"Art Services",
            "type":"Services"
        }
    ],
    "sg:phone":"+32 56 33 30 67",
    "sg:postcode":"7700",
    "sg:province":"Hainaut",
    "sg:tags":[
        "picture",
        "framer"
    ],
    "wof:name":"Derycker R",
    "wof:placetype":"venue"
},
  "geometry": {"coordinates":[3.1939771175,50.7397727966],"type":"Point"}
}