{
  "type": "Feature",
  "properties": {
    "addr:full":"Heldergemstraat 113 Haaltert (heldergem) Oost-Vlaanderen 9450",
    "addr:housenumber":"113",
    "addr:postcode":"9450",
    "addr:street":"Heldergemstraat",
    "iso:country":"BE",
    "sg:address":"Heldergemstraat 113",
    "sg:city":"Haaltert (heldergem)",
    "sg:classifiers":[
        {
            "category":"Building & Trades",
            "subcategory":"Pest Control",
            "type":"Services"
        }
    ],
    "sg:phone":"+32 475 76 13 71",
    "sg:postcode":"9450",
    "sg:province":"Oost-Vlaanderen",
    "sg:tags":[
        "painting",
        "contractor"
    ],
    "wof:name":"Bdem Bvba",
    "wof:placetype":"venue"
},
  "geometry": {"coordinates":[3.9567759037,50.8772659302],"type":"Point"}
}