{
  "type": "Feature",
  "properties": {
    "iso:country":"BE",
    "sg:address":"Industrieweg 16",
    "sg:city":"Kortessem",
    "sg:orig_category":"Entretien and r\u00e9parations de voitures",
    "sg:phone":"+32 11 37 78 08",
    "sg:postcode":"3720",
    "sg:province":"Limburg",
    "wof:name":"Garage Franssens",
    "wof:placetype":"venue"
},
  "geometry": {"coordinates":[5.3680949211,50.873966217],"type":"Point"}
}