{
  "type": "Feature",
  "properties": {
    "addr:full":"Langeboeken 1 Zomergem Oost-Vlaanderen 9930",
    "addr:housenumber":"1",
    "addr:postcode":"9930",
    "addr:street":"Langeboeken",
    "iso:country":"BE",
    "sg:address":"Langeboeken 1",
    "sg:city":"Zomergem",
    "sg:classifiers":[
        {
            "category":"Airport",
            "subcategory":"International",
            "type":"Transportation"
        }
    ],
    "sg:phone":"+32 9 372 60 77",
    "sg:postcode":"9930",
    "sg:province":"Oost-Vlaanderen",
    "sg:tags":[
        "-",
        "transport"
    ],
    "wof:name":"Lataire Vervoer Nv",
    "wof:placetype":"venue"
},
  "geometry": {"coordinates":[3.5890319347,51.1102142334],"type":"Point"}
}