{
  "type": "Feature",
  "properties": {
    "iso:country":"BE",
    "sg:address":"Sint-katharinastraat 40ba",
    "sg:city":"Puurs",
    "sg:orig_category":"Woningbouw",
    "sg:phone":"+32 3 886 98 84",
    "sg:postcode":"2870",
    "sg:province":"Antwerpen",
    "wof:name":"Bouwond.van Camp Fran\u00c7ois",
    "wof:placetype":"venue"
},
  "geometry": {"coordinates":[4.328045845,51.0793151855],"type":"Point"}
}