{
  "type": "Feature",
  "properties": {
    "iso:country":"BE",
    "sg:address":"Eindhoutseweg 822",
    "sg:city":"Geel",
    "sg:classifiers":[
        {
            "category":"Shopping",
            "subcategory":"Pets & Pet Supplies",
            "type":"Retail Goods"
        }
    ],
    "sg:phone":"+32 14 86 74 95",
    "sg:postcode":"2440",
    "sg:province":"Antwerpen",
    "sg:tags":[
        "shop",
        "-"
    ],
    "wof:name":"B.k.k.v. Vzw",
    "wof:placetype":"venue"
},
  "geometry": {"coordinates":[4.990170002,51.1043891907],"type":"Point"}
}