{
  "type": "Feature",
  "properties": {
    "iso:country":"BE",
    "sg:address":"Leuvensesteenweg 8",
    "sg:city":"Aarschot (gelrode)",
    "sg:classifiers":[
        {
            "category":"Shopping",
            "subcategory":"Party Supplies",
            "type":"Retail Goods"
        }
    ],
    "sg:phone":"+32 16 56 11 05",
    "sg:postcode":"3200",
    "sg:province":"Vlaams-Brabant",
    "sg:tags":[
        "-",
        "watch",
        "clock"
    ],
    "wof:name":"Rokastrap",
    "wof:placetype":"venue"
},
  "geometry": {"coordinates":[4.8230700493,50.9806289673],"type":"Point"}
}