{
  "type": "Feature",
  "properties": {
    "iso:country":"BE",
    "sg:address":"Schatting 64a",
    "sg:city":"Zedelgem",
    "sg:classifiers":[
        {
            "category":"Building & Trades",
            "subcategory":"Construction",
            "type":"Services"
        }
    ],
    "sg:phone":"+32 50 82 21 14",
    "sg:postcode":"8210",
    "sg:province":"West-Vlaanderen",
    "sg:tags":[
        "glazier"
    ],
    "wof:name":"Vervaecke F",
    "wof:placetype":"venue"
},
  "geometry": {"coordinates":[3.1428699493,51.1376419067],"type":"Point"}
}