{
  "type": "Feature",
  "properties": {
    "addr:full":"Chauss\u00c9e De Mons 135 Soignies Hainaut 7060",
    "addr:housenumber":"135",
    "addr:postcode":"7060",
    "addr:street":"Chausse\u0301E De Mons",
    "iso:country":"BE",
    "sg:address":"Chauss\u00c9e De Mons 135",
    "sg:city":"Soignies",
    "sg:classifiers":[
        {
            "category":"Autos & Motor Vehicles",
            "subcategory":"Fuel & Gas Station",
            "type":"Retail Goods"
        }
    ],
    "sg:phone":"+32 67 33 25 53",
    "sg:postcode":"7060",
    "sg:province":"Hainaut",
    "sg:tags":[
        "stations-service",
        "carburants"
    ],
    "wof:name":"Bernadette Tison",
    "wof:placetype":"venue"
},
  "geometry": {"coordinates":[4.0620088577,50.5656356812],"type":"Point"}
}