{
  "type": "Feature",
  "properties": {
    "addr:full":"Gompelbaan 154 Mol Antwerpen 2400",
    "addr:housenumber":"154",
    "addr:postcode":"2400",
    "addr:street":"Gompelbaan",
    "iso:country":"BE",
    "sg:address":"Gompelbaan 154",
    "sg:city":"Mol",
    "sg:classifiers":[
        {
            "category":"Food & Beverages",
            "subcategory":"Groceries & Convenience Stores",
            "type":"Retail Goods"
        }
    ],
    "sg:phone":"+32 14 32 29 33",
    "sg:postcode":"2400",
    "sg:province":"Antwerpen",
    "sg:tags":[
        "grocer"
    ],
    "wof:name":"De Kruidenier",
    "wof:placetype":"venue"
},
  "geometry": {"coordinates":[5.1506500244,51.1936569214],"type":"Point"}
}