{
  "type": "Feature",
  "properties": {
    "iso:country":"BE",
    "sg:address":"Boutensdreef 2",
    "sg:city":"Torhout",
    "sg:classifiers":[
        {
            "category":"Building & Trades",
            "subcategory":"Electrical",
            "type":"Services"
        }
    ],
    "sg:phone":"+32 50 21 61 99",
    "sg:postcode":"8820",
    "sg:province":"West-Vlaanderen",
    "sg:tags":[
        "electric",
        "-",
        "housewiring",
        "contractor"
    ],
    "wof:name":"Tryhou L",
    "wof:placetype":"venue"
},
  "geometry": {"coordinates":[3.1394400597,51.0929527283],"type":"Point"}
}