{
  "type": "Feature",
  "properties": {
    "addr:full":"Stationsplein 2bb Geel Antwerpen 2440",
    "addr:housenumber":"2bb",
    "addr:postcode":"2440",
    "addr:street":"Stationsplein",
    "iso:country":"BE",
    "sg:address":"Stationsplein 2bb",
    "sg:city":"Geel",
    "sg:orig_category":"S\u00e9curit\u00e9 sociale",
    "sg:phone":"+32 14 58 80 96",
    "sg:postcode":"2440",
    "sg:province":"Antwerpen",
    "wof:name":"Kristelijk Ziekenfonds",
    "wof:placetype":"venue"
},
  "geometry": {"coordinates":[4.9882907867,51.1683998108],"type":"Point"}
}