{
  "type": "Feature",
  "properties": {
    "iso:country":"BE",
    "sg:address":"Zilvermeerlaan 2",
    "sg:city":"Mol",
    "sg:orig_category":"Terrains de camping. Luna-parks and parcs de r\u00e9cr\u00e9ation",
    "sg:phone":"+32 14 82 95 00",
    "sg:postcode":"2400",
    "sg:province":"Antwerpen",
    "wof:name":"Zilvermeer",
    "wof:placetype":"venue"
},
  "geometry": {"coordinates":[5.1722598076,51.2273178101],"type":"Point"}
}