{
  "type": "Feature",
  "properties": {
    "addr:full":"Bergstraat 98 Haaltert Oost-Vlaanderen 9451",
    "addr:housenumber":"98",
    "addr:postcode":"9451",
    "addr:street":"Bergstraat",
    "iso:country":"BE",
    "sg:address":"Bergstraat 98",
    "sg:city":"Haaltert",
    "sg:orig_category":"Advocaten and juridische adviseurs",
    "sg:phone":"+32 53 83 13 82",
    "sg:postcode":"9451",
    "sg:province":"Oost-Vlaanderen",
    "wof:name":"Ann Jacob",
    "wof:placetype":"venue"
},
  "geometry": {"coordinates":[3.9867670536,50.8826141357],"type":"Point"}
}