{
  "type": "Feature",
  "properties": {
    "addr:full":"Schelpheuvelstraat 7 Essen Antwerpen 2910",
    "addr:housenumber":"7",
    "addr:postcode":"2910",
    "addr:street":"Schelpheuvelstraat",
    "iso:country":"BE",
    "sg:address":"Schelpheuvelstraat 7",
    "sg:city":"Essen",
    "sg:orig_category":"Installatie van houten of kunststof schrijnwerk",
    "sg:phone":"+32 3 677 31 85",
    "sg:postcode":"2910",
    "sg:province":"Antwerpen",
    "wof:name":"Brosens",
    "wof:placetype":"venue"
},
  "geometry": {"coordinates":[4.4540681839,51.4495277405],"type":"Point"}
}