{
  "type": "Feature",
  "properties": {
    "addr:full":"Antwerpse Steenweg 177ba Sint-niklaas Oost-Vlaanderen 9100",
    "addr:postcode":"9100",
    "addr:street":"Antwerpse Steenweg 177Ba",
    "iso:country":"BE",
    "sg:address":"Antwerpse Steenweg 177ba",
    "sg:city":"Sint-niklaas",
    "sg:orig_category":"Brood, gebak and snoepgoed",
    "sg:phone":"+32 3 765 05 68",
    "sg:postcode":"9100",
    "sg:province":"Oost-Vlaanderen",
    "wof:name":"Bakkerij Katrien",
    "wof:placetype":"venue"
},
  "geometry": {"coordinates":[4.1576619148,51.1700019836],"type":"Point"}
}