{
  "type": "Feature",
  "properties": {
    "addr:full":"Frederik Wouterslaan 23 Kampenhout Vlaams-Brabant 1910",
    "addr:housenumber":"23",
    "addr:postcode":"1910",
    "addr:street":"Frederik Wouterslaan",
    "iso:country":"BE",
    "sg:address":"Frederik Wouterslaan 23",
    "sg:city":"Kampenhout",
    "sg:orig_category":"Plomberie, chauffage and installations sanitaires",
    "sg:phone":"+32 16 65 75 89",
    "sg:postcode":"1910",
    "sg:province":"Vlaams-Brabant",
    "wof:name":"Jean Ruysseveldt",
    "wof:placetype":"venue"
},
  "geometry": {"coordinates":[4.5513892174,50.9398117065],"type":"Point"}
}