{
  "type": "Feature",
  "properties": {
    "iso:country":"BE",
    "sg:address":"Rue Notre-dame De La Paix 1",
    "sg:city":"Chimay",
    "sg:classifiers":[
        {
            "category":"Professional",
            "subcategory":"Management & Consulting",
            "type":"Services"
        }
    ],
    "sg:phone":"+32 60 21 25 79",
    "sg:postcode":"6460",
    "sg:province":"Hainaut",
    "sg:tags":[
        "consultant",
        "law"
    ],
    "wof:name":"Gilot J",
    "wof:placetype":"venue"
},
  "geometry": {"coordinates":[4.308909893,50.0493049622],"type":"Point"}
}