{
  "type": "Feature",
  "properties": {
    "iso:country":"BE",
    "sg:address":"Olmendreef 36",
    "sg:city":"Rotselaar",
    "sg:classifiers":[
        {
            "category":"Professional",
            "subcategory":"Management & Consulting",
            "type":"Services"
        }
    ],
    "sg:phone":"+32 16 29 41 94",
    "sg:postcode":"3110",
    "sg:province":"Vlaams-Brabant",
    "sg:tags":[
        "-",
        "processing",
        "data",
        "consultant"
    ],
    "wof:name":"Solv It",
    "wof:placetype":"venue"
},
  "geometry": {"coordinates":[4.7107920647,50.9508590698],"type":"Point"}
}