{
  "type": "Feature",
  "properties": {
    "iso:country":"BE",
    "sg:address":"Helmetsesteenweg 387",
    "sg:city":"Schaarbeek/schaerbeek",
    "sg:classifiers":[
        {
            "category":"Fast Food",
            "type":"Food & Drink"
        }
    ],
    "sg:phone":"+32 2 215 37 46",
    "sg:postcode":"1030",
    "sg:province":"Bruxelles-Capitale",
    "sg:tags":[
        "meeneem",
        "restaurant"
    ],
    "wof:name":"Restaurant Asia",
    "wof:placetype":"venue"
},
  "geometry": {"coordinates":[4.3923478127,50.8759269714],"type":"Point"}
}