{
  "type": "Feature",
  "properties": {
    "addr:full":"Chauss\u00c9e Solvay 36 Charleroi Hainaut 6061",
    "addr:housenumber":"36",
    "addr:postcode":"6061",
    "addr:street":"Chausse\u0301E Solvay;Hainaut",
    "iso:country":"BE",
    "sg:address":"Chauss\u00c9e Solvay 36",
    "sg:city":"Charleroi",
    "sg:orig_category":"Artsen and specialisten",
    "sg:phone":"+32 71 31 06 87",
    "sg:postcode":"6061",
    "sg:province":"Hainaut",
    "wof:name":"Gilbert Fievez",
    "wof:placetype":"venue"
},
  "geometry": {"coordinates":[4.4822640419,50.3984832764],"type":"Point"}
}