{
  "type": "Feature",
  "properties": {
    "iso:country":"BE",
    "sg:address":"Winderickxplein 3",
    "sg:city":"Alsemberg",
    "sg:classifiers":[
        {
            "category":"Banks & Credit Unions",
            "subcategory":"Bank",
            "type":"Services"
        }
    ],
    "sg:phone":"+32 2 380 14 70",
    "sg:postcode":"1641",
    "wof:name":"Aslk-cger Bank",
    "wof:placetype":"venue"
},
  "geometry": {"coordinates":[4.3380708694,50.7415008545],"type":"Point"}
}