{
  "type": "Feature",
  "properties": {
    "addr:full":"Kortrijkstraat 160 Lubbeek Vlaams-Brabant 3210",
    "addr:housenumber":"160",
    "addr:postcode":"3210",
    "addr:street":"Kortrijkstraat",
    "iso:country":"BE",
    "sg:address":"Kortrijkstraat 160",
    "sg:city":"Lubbeek",
    "sg:orig_category":"Producteurs de l\u00e9gumes",
    "sg:phone":"+32 16 62 03 87",
    "sg:postcode":"3210",
    "sg:province":"Vlaams-Brabant",
    "wof:name":"Mark Vanstockstraeten",
    "wof:placetype":"venue"
},
  "geometry": {"coordinates":[4.7866859436,50.9084815979],"type":"Point"}
}