{
  "type": "Feature",
  "properties": {
    "addr:full":"Spijker 33 Essen Antwerpen 2910",
    "addr:housenumber":"33",
    "addr:postcode":"2910",
    "addr:street":"Spijker",
    "iso:country":"BE",
    "sg:address":"Spijker 33",
    "sg:city":"Essen",
    "sg:classifiers":[
        {
            "category":"Home & Garden",
            "subcategory":"Garden Supply",
            "type":"Retail Goods"
        }
    ],
    "sg:phone":"+32 3 667 29 04",
    "sg:postcode":"2910",
    "sg:province":"Antwerpen",
    "wof:name":"Aveve Tuincentrum",
    "wof:placetype":"venue"
},
  "geometry": {"coordinates":[4.4749798775,51.4567222595],"type":"Point"}
}