{
  "type": "Feature",
  "properties": {
    "addr:full":"Zoning Industriel 9 Bastogne Luxembourg 6600",
    "addr:housenumber":"9",
    "addr:postcode":"6600",
    "addr:street":"Zoning Industriel",
    "iso:country":"BE",
    "sg:address":"Zoning Industriel 9",
    "sg:city":"Bastogne",
    "sg:classifiers":[
        {
            "category":"Parking",
            "subcategory":"Lot",
            "type":"Transportation"
        }
    ],
    "sg:phone":"+32 61 21 42 78",
    "sg:postcode":"6600",
    "sg:province":"Luxembourg",
    "sg:tags":[
        "parking-places",
        "laying-out"
    ],
    "wof:name":"Englebert Serge Sprlu",
    "wof:placetype":"venue"
},
  "geometry": {"coordinates":[5.7091178894,49.9863891602],"type":"Point"}
}