{
  "type": "Feature",
  "properties": {
    "iso:country":"BE",
    "sg:address":"Lostraat 118 C",
    "sg:city":"Heist-op-den-berg",
    "sg:orig_category":"Paramedische behandelingen",
    "sg:phone":"+32 15 24 29 88",
    "sg:postcode":"2220",
    "sg:province":"Antwerpen",
    "wof:name":"S. Frans",
    "wof:placetype":"venue"
},
  "geometry": {"coordinates":[4.7350621223,51.0605392456],"type":"Point"}
}