{
  "type": "Feature",
  "properties": {
    "addr:full":"Rue Vandy 34 Flawinne Namur 5020",
    "addr:housenumber":"34",
    "addr:postcode":"5020",
    "addr:street":"Rue Vandy",
    "iso:country":"BE",
    "sg:address":"Rue Vandy 34",
    "sg:city":"Flawinne",
    "sg:orig_category":"Opticiens",
    "sg:phone":"+32 81 73 96 48",
    "sg:postcode":"5020",
    "sg:province":"Namur",
    "wof:name":"Flawinne Optique",
    "wof:placetype":"venue"
},
  "geometry": {"coordinates":[4.808822155,50.4572525024],"type":"Point"}
}