{
  "type": "Feature",
  "properties": {
    "iso:country":"BE",
    "sg:address":"Klokkengieterijstraat 21",
    "sg:city":"Lokeren",
    "sg:orig_category":"Muziekinstrumenten",
    "sg:phone":"+32 9 349 28 83",
    "sg:postcode":"9160",
    "sg:province":"Oost-Vlaanderen",
    "wof:name":"Music Electronics",
    "wof:placetype":"venue"
},
  "geometry": {"coordinates":[3.9888648987,51.0953025818],"type":"Point"}
}