{
  "type": "Feature",
  "properties": {
    "iso:country":"BE",
    "sg:address":"Ter Moude 29",
    "sg:city":"Zwevegem (moen)",
    "sg:classifiers":[
        {
            "category":"Home & Garden",
            "subcategory":"Carpets & Floor Coverings",
            "type":"Retail Goods"
        }
    ],
    "sg:phone":"+32 56 64 83 45",
    "sg:postcode":"8552",
    "sg:tags":[
        "parquet"
    ],
    "wof:name":"Baele Y",
    "wof:placetype":"venue"
},
  "geometry": {"coordinates":[3.3963670731,50.7679672241],"type":"Point"}
}