{
  "type": "Feature",
  "properties": {
    "addr:full":"Ridderstraat 10b Nieuwerkerken (kozen) Limburg 3850",
    "addr:housenumber":"10b",
    "addr:postcode":"3850",
    "addr:street":"Ridderstraat",
    "iso:country":"BE",
    "sg:address":"Ridderstraat 10b",
    "sg:city":"Nieuwerkerken (kozen)",
    "sg:classifiers":[
        {
            "category":"Home & Garden",
            "subcategory":"Building Materials",
            "type":"Retail Goods"
        }
    ],
    "sg:phone":"+32 11 59 15 86",
    "sg:postcode":"3850",
    "sg:province":"Limburg",
    "sg:tags":[
        "veranda"
    ],
    "wof:name":"Wils Bvba",
    "wof:placetype":"venue"
},
  "geometry": {"coordinates":[5.2366800308,50.8803710938],"type":"Point"}
}