{
  "type": "Feature",
  "properties": {
    "addr:full":"Rue Basse Voie 38 Verviers (stembert) Li\u00e8ge 4801",
    "addr:housenumber":"38",
    "addr:postcode":"4801",
    "addr:street":"Rue Basse Voie",
    "iso:country":"BE",
    "sg:address":"Rue Basse Voie 38",
    "sg:city":"Verviers (stembert)",
    "sg:classifiers":[
        {
            "category":"Real Estate",
            "subcategory":"Architect",
            "type":"Services"
        }
    ],
    "sg:phone":"+32 87 22 88 39",
    "sg:postcode":"4801",
    "sg:province":"Li\u00e8ge",
    "wof:name":"Andris C",
    "wof:placetype":"venue"
},
  "geometry": {"coordinates":[5.9009218216,50.5803375244],"type":"Point"}
}