{
  "type": "Feature",
  "properties": {
    "addr:full":"Broekstraat 113 Brussel/bruxelles Bruxelles-Capitale 1000",
    "addr:housenumber":"113",
    "addr:postcode":"1000",
    "addr:street":"Broekstraat;/",
    "iso:country":"BE",
    "sg:address":"Broekstraat 113",
    "sg:city":"Brussel/bruxelles",
    "sg:orig_category":"Sportcentra",
    "sg:phone":"+32 2 219 27 03",
    "sg:postcode":"1000",
    "sg:province":"Bruxelles-Capitale",
    "wof:name":"Salle Sp. Inst.st.louis",
    "wof:placetype":"venue"
},
  "geometry": {"coordinates":[4.3609819412,50.8539619446],"type":"Point"}
}