{
  "type": "Feature",
  "properties": {
    "iso:country":"BE",
    "sg:address":"Putberg 55",
    "sg:city":"Asse",
    "sg:classifiers":[
        {
            "category":"Farming",
            "subcategory":"Livestock Farm",
            "type":"Manufacturing & Wholesale Goods"
        }
    ],
    "sg:phone":"+32 2 452 64 32",
    "sg:postcode":"1730",
    "sg:province":"Vlaams-Brabant",
    "sg:tags":[
        "horse"
    ],
    "wof:name":"Limbourg F",
    "wof:placetype":"venue"
},
  "geometry": {"coordinates":[4.1850209236,50.9118766785],"type":"Point"}
}