{
  "type": "Feature",
  "properties": {
    "addr:full":"Rue Charlemagne 7 Ottignies-louvain-la-neuve (louvain-la-neuve) Brabant Wallon 1348",
    "addr:housenumber":"7",
    "addr:postcode":"1348",
    "addr:street":"Rue Charlemagne",
    "iso:country":"BE",
    "sg:address":"Rue Charlemagne 7",
    "sg:city":"Ottignies-louvain-la-neuve (louvain-la-neuve)",
    "sg:classifiers":[
        {
            "category":"Sports & Exercise",
            "subcategory":"Gym",
            "type":"Entertainment"
        }
    ],
    "sg:phone":"+32 10 45 52 26",
    "sg:postcode":"1348",
    "sg:province":"Brabant Wallon",
    "sg:tags":[
        "fitness"
    ],
    "wof:name":"American Body Center",
    "wof:placetype":"venue"
},
  "geometry": {"coordinates":[4.6125860214,50.6697807312],"type":"Point"}
}