{
  "type": "Feature",
  "properties": {
    "iso:country":"BE",
    "sg:address":"Rue Nestor De Ti\u00c8re 31",
    "sg:city":"Schaarbeek/schaerbeek",
    "sg:orig_category":"Peinture. Rev\u00eatements pour sols and murs",
    "sg:phone":"+32 2 215 76 05",
    "sg:postcode":"1030",
    "sg:province":"Bruxelles-Capitale",
    "wof:name":"Willy Daro",
    "wof:placetype":"venue"
},
  "geometry": {"coordinates":[4.3843970299,50.872756958],"type":"Point"}
}