{
  "type": "Feature",
  "properties": {
    "addr:full":"Rue De L\u00b4institut 40 Messancy Luxembourg 6780",
    "addr:housenumber":"40",
    "addr:postcode":"6780",
    "addr:street":"Rue De L\u00b4Institut",
    "iso:country":"BE",
    "sg:address":"Rue De L\u00b4institut 40",
    "sg:city":"Messancy",
    "sg:orig_category":"V\u00eatements pour b\u00e9b\u00e9s and enfants. V\u00eatements pour Dames. V\u00eatements pour Hommes",
    "sg:phone":"+32 63 38 45 01",
    "sg:postcode":"6780",
    "sg:province":"Luxembourg",
    "wof:name":"Pecotex",
    "wof:placetype":"venue"
},
  "geometry": {"coordinates":[5.8076748848,49.6155014038],"type":"Point"}
}