{
  "type": "Feature",
  "properties": {
    "iso:country":"BE",
    "sg:address":"Hoogledestraat 92",
    "sg:city":"Kortemark",
    "sg:classifiers":[
        {
            "category":"Freight",
            "type":"Transportation"
        }
    ],
    "sg:phone":"+32 51 57 57 00",
    "sg:postcode":"8610",
    "sg:province":"West-Vlaanderen",
    "sg:tags":[
        "-",
        "transport"
    ],
    "wof:name":"Deva-kort",
    "wof:placetype":"venue"
},
  "geometry": {"coordinates":[3.0463769436,51.0180397034],"type":"Point"}
}