{
  "type": "Feature",
  "properties": {
    "iso:country":"BE",
    "sg:address":"Van \u00b4t Sestichlaan 20",
    "sg:city":"Herent",
    "sg:orig_category":"Animations diverses",
    "sg:phone":"+32 16 48 82 43",
    "sg:postcode":"3020",
    "sg:province":"Vlaams-Brabant",
    "wof:name":"Arriba Discobar",
    "wof:placetype":"venue"
},
  "geometry": {"coordinates":[4.6554741859,50.8870544434],"type":"Point"}
}