{
  "type": "Feature",
  "properties": {
    "iso:country":"BE",
    "sg:address":"Stationsstraat 87",
    "sg:city":"Lendelede",
    "sg:orig_category":"Pain, p\u00e2tisseries and confiseries",
    "sg:phone":"+32 51 31 64 41",
    "sg:postcode":"8860",
    "sg:province":"West-Vlaanderen",
    "wof:name":"Joeri Deceuninck",
    "wof:placetype":"venue"
},
  "geometry": {"coordinates":[3.2469689846,50.8855705261],"type":"Point"}
}