{
  "type": "Feature",
  "properties": {
    "addr:full":"Rue Du Noyer 91 Brussel/bruxelles Bruxelles-Capitale 1000",
    "addr:housenumber":"91",
    "addr:postcode":"1000",
    "addr:street":"Rue Du Noyer;/",
    "iso:country":"BE",
    "sg:address":"Rue Du Noyer 91",
    "sg:city":"Brussel/bruxelles",
    "sg:orig_category":"Epiceries",
    "sg:phone":"+32 2 734 90 28",
    "sg:postcode":"1000",
    "sg:province":"Bruxelles-Capitale",
    "wof:name":"La Triestina",
    "wof:placetype":"venue"
},
  "geometry": {"coordinates":[4.3892140388,50.8492469788],"type":"Point"}
}