{
  "type": "Feature",
  "properties": {
    "iso:country":"BE",
    "sg:address":"Avenue Marius Renard 49b41",
    "sg:city":"Anderlecht",
    "sg:orig_category":"Plomberie, chauffage and installations sanitaires. Rev\u00eatements pour sols and murs",
    "sg:phone":"+32 2 524 28 39",
    "sg:postcode":"1070",
    "sg:province":"Bruxelles-Capitale",
    "wof:name":"Mosaideal",
    "wof:placetype":"venue"
},
  "geometry": {"coordinates":[4.2826089859,50.8257789612],"type":"Point"}
}