{
  "type": "Feature",
  "properties": {
    "iso:country":"BE",
    "sg:address":"Rue Du Pavillon 12",
    "sg:city":"Chimay",
    "sg:orig_category":"Sport- and kampeermateriaal Watersport-, Sport- and Kampeerbenodigdheden Verhuur",
    "sg:phone":"+32 60 21 33 39",
    "sg:postcode":"6460",
    "sg:province":"Hainaut",
    "wof:name":"But Sports",
    "wof:placetype":"venue"
},
  "geometry": {"coordinates":[4.3191161156,50.0482940674],"type":"Point"}
}