{
  "type": "Feature",
  "properties": {
    "iso:country":"BE",
    "sg:address":"Molenijzer 15",
    "sg:city":"Brugge (sint-andries)",
    "sg:classifiers":[
        {
            "category":"Building & Trades",
            "subcategory":"Construction",
            "type":"Services"
        }
    ],
    "sg:phone":"+32 50 39 08 25",
    "sg:postcode":"8200",
    "sg:province":"West-Vlaanderen",
    "sg:tags":[
        "paper",
        "hanger"
    ],
    "wof:name":"Bravo Paint",
    "wof:placetype":"venue"
},
  "geometry": {"coordinates":[3.1810400486,51.1874084473],"type":"Point"}
}