{
  "type": "Feature",
  "properties": {
    "addr:full":"Beselarestraat 296 Zonnebeke (beselare) West-Vlaanderen 8980",
    "addr:housenumber":"296",
    "addr:postcode":"8980",
    "addr:street":"Beselarestraat",
    "iso:country":"BE",
    "sg:address":"Beselarestraat 296",
    "sg:city":"Zonnebeke (beselare)",
    "sg:classifiers":[
        {
            "category":"Shopping",
            "subcategory":"Jewelry",
            "type":"Retail Goods"
        }
    ],
    "sg:phone":"+32 57 46 64 92",
    "sg:postcode":"8980",
    "sg:province":"West-Vlaanderen",
    "sg:tags":[
        "jeweller",
        "-"
    ],
    "wof:name":"Adriaen Tijl",
    "wof:placetype":"venue"
},
  "geometry": {"coordinates":[3.0099699497,50.8603096008],"type":"Point"}
}