{
  "type": "Feature",
  "properties": {
    "addr:full":"Kruynighemstraat 8 Mechelen (hombeek) Antwerpen 2811",
    "addr:housenumber":"8",
    "addr:postcode":"2811",
    "addr:street":"Kruynighemstraat",
    "iso:country":"BE",
    "sg:address":"Kruynighemstraat 8",
    "sg:city":"Mechelen (hombeek)",
    "sg:classifiers":[
        {
            "category":"Farming",
            "subcategory":"Livestock Farm",
            "type":"Manufacturing & Wholesale Goods"
        }
    ],
    "sg:phone":"+32 15 43 06 22",
    "sg:postcode":"2811",
    "sg:province":"Antwerpen",
    "sg:tags":[
        "buyer"
    ],
    "wof:name":"Vergauwen A",
    "wof:placetype":"venue"
},
  "geometry": {"coordinates":[4.4124331474,51.0089988708],"type":"Point"}
}