{
  "type": "Feature",
  "properties": {
    "addr:full":"Rue Verte 213 Seraing Li\u00e8ge 4100",
    "addr:housenumber":"213",
    "addr:postcode":"4100",
    "addr:street":"Rue Verte",
    "iso:country":"BE",
    "sg:address":"Rue Verte 213",
    "sg:city":"Seraing",
    "sg:orig_category":"Artsen and specialisten",
    "sg:phone":"+32 4 337 05 02",
    "sg:postcode":"4100",
    "sg:province":"Li\u00e8ge",
    "wof:name":"Johanna Denis",
    "wof:placetype":"venue"
},
  "geometry": {"coordinates":[5.5055260658,50.5784263611],"type":"Point"}
}