{
  "type": "Feature",
  "properties": {
    "addr:full":"Quai De Rome 15b33 Li\u00c8ge Li\u00e8ge 4000",
    "addr:housenumber":"15b33",
    "addr:postcode":"4000",
    "addr:street":"Quai De Rome",
    "iso:country":"BE",
    "sg:address":"Quai De Rome 15b33",
    "sg:city":"Li\u00c8ge",
    "sg:orig_category":"M\u00e9decins and sp\u00e9cialistes",
    "sg:phone":"+32 4 252 36 06",
    "sg:postcode":"4000",
    "sg:province":"Li\u00e8ge",
    "wof:name":"Edmond Carpentier",
    "wof:placetype":"venue"
},
  "geometry": {"coordinates":[5.5745100975,50.6256523132],"type":"Point"}
}