{
  "type": "Feature",
  "properties": {
    "iso:country":"BE",
    "sg:address":"Rue Des Marronniers 21",
    "sg:city":"Chiny",
    "sg:classifiers":[
        {
            "category":"Recreation",
            "type":"Entertainment"
        }
    ],
    "sg:phone":"+32 61 32 82 24",
    "sg:postcode":"6810",
    "sg:province":"Luxembourg",
    "sg:tags":[
        "diver",
        "amusement"
    ],
    "wof:name":"Star Fever (syst\u00c8me 2)",
    "wof:placetype":"venue"
},
  "geometry": {"coordinates":[5.3787579536,49.6993293762],"type":"Point"}
}