{
  "type": "Feature",
  "properties": {
    "addr:full":"Lindestraat 219 Evere Bruxelles-Capitale 1140",
    "addr:housenumber":"219",
    "addr:postcode":"1140",
    "addr:street":"Lindestraat",
    "iso:country":"BE",
    "sg:address":"Lindestraat 219",
    "sg:city":"Evere",
    "sg:orig_category":"Tuinen",
    "sg:phone":"+32 2 215 52 24",
    "sg:postcode":"1140",
    "sg:province":"Bruxelles-Capitale",
    "wof:name":"Les 4 Saisons",
    "wof:placetype":"venue"
},
  "geometry": {"coordinates":[4.3948860168,50.8719787598],"type":"Point"}
}