{
  "type": "Feature",
  "properties": {
    "addr:full":"Hekkergemstraat 77 Wichelen (schellebelle) Oost-Vlaanderen 9260",
    "addr:housenumber":"77",
    "addr:postcode":"9260",
    "addr:street":"Hekkergemstraat",
    "iso:country":"BE",
    "sg:address":"Hekkergemstraat 77",
    "sg:city":"Wichelen (schellebelle)",
    "sg:classifiers":[
        {
            "category":"Real Estate",
            "subcategory":"Architect",
            "type":"Services"
        }
    ],
    "sg:phone":"+32 9 366 43 66",
    "sg:postcode":"9260",
    "sg:province":"Oost-Vlaanderen",
    "wof:name":"De Schutter E",
    "wof:placetype":"venue"
},
  "geometry": {"coordinates":[3.9306430817,51.0106964111],"type":"Point"}
}