{
  "type": "Feature",
  "properties": {
    "iso:country":"BE",
    "sg:address":"Rue De For\u00cat 24",
    "sg:city":"Namur",
    "sg:orig_category":"Paramedische behandelingen",
    "sg:phone":"+32 81 22 41 08",
    "sg:postcode":"5000",
    "sg:province":"Namur",
    "wof:name":"Moyson-flament",
    "wof:placetype":"venue"
},
  "geometry": {"coordinates":[4.8617630005,50.4657287598],"type":"Point"}
}