{
  "type": "Feature",
  "properties": {
    "addr:full":"Grensstraat 76 Lommel Limburg 3920",
    "addr:housenumber":"76",
    "addr:postcode":"3920",
    "addr:street":"Grensstraat",
    "iso:country":"BE",
    "sg:address":"Grensstraat 76",
    "sg:city":"Lommel",
    "sg:classifiers":[
        {
            "category":"Home & Garden",
            "subcategory":"Hardware",
            "type":"Retail Goods"
        }
    ],
    "sg:phone":"+32 11 80 23 25",
    "sg:postcode":"3920",
    "sg:province":"Limburg",
    "sg:tags":[
        "fixing",
        "material"
    ],
    "wof:name":"Multi-fix Bvba",
    "wof:placetype":"venue"
},
  "geometry": {"coordinates":[5.3851599693,51.2667503357],"type":"Point"}
}