{
  "type": "Feature",
  "properties": {
    "addr:full":"Duinkerkestraat 119 Poperinge West-Vlaanderen 8970",
    "addr:housenumber":"119",
    "addr:postcode":"8970",
    "addr:street":"Duinkerkestraat",
    "iso:country":"BE",
    "sg:address":"Duinkerkestraat 119",
    "sg:city":"Poperinge",
    "sg:classifiers":[
        {
            "category":"Arena",
            "subcategory":"Sports Club",
            "type":"Entertainment"
        }
    ],
    "sg:phone":"+32 57 33 74 50",
    "sg:postcode":"8970",
    "sg:province":"West-Vlaanderen",
    "sg:tags":[
        "de"
    ],
    "wof:name":"V.c. Roepovo",
    "wof:placetype":"venue"
},
  "geometry": {"coordinates":[2.7148199081,50.8559379578],"type":"Point"}
}