{
  "type": "Feature",
  "properties": {
    "iso:country":"BE",
    "sg:address":"Bikschootsestraat 1",
    "sg:city":"Ieper",
    "sg:orig_category":"Varkenskwekers",
    "sg:phone":"+32 57 48 86 42",
    "sg:postcode":"8904",
    "sg:province":"West-Vlaanderen",
    "wof:name":"Luc Haghedooren",
    "wof:placetype":"venue"
},
  "geometry": {"coordinates":[2.8831710815,50.9046592712],"type":"Point"}
}