{
  "type": "Feature",
  "properties": {
    "addr:full":"Sint-katriensteenweg 189 Kuurne West-Vlaanderen 8520",
    "addr:housenumber":"189",
    "addr:postcode":"8520",
    "iso:country":"BE",
    "sg:address":"Sint-katriensteenweg 189",
    "sg:city":"Kuurne",
    "sg:classifiers":[
        {
            "category":"Building & Trades",
            "subcategory":"Pest Control",
            "type":"Services"
        }
    ],
    "sg:phone":"+32 56 35 55 22",
    "sg:postcode":"8520",
    "sg:province":"West-Vlaanderen",
    "sg:tags":[
        "painting",
        "contractor"
    ],
    "wof:name":"De Tollenaere E",
    "wof:placetype":"venue"
},
  "geometry": {"coordinates":[3.2537119389,50.8671417236],"type":"Point"}
}