{
  "type": "Feature",
  "properties": {
    "iso:country":"BE",
    "sg:address":"Riddershofstedelaan 53",
    "sg:city":"Ukkel/uccle",
    "sg:orig_category":"Boekhouders",
    "sg:phone":"+32 2 538 37 02",
    "sg:postcode":"1180",
    "sg:province":"Bruxelles-Capitale",
    "wof:name":"Hughes De Montjoye",
    "wof:placetype":"venue"
},
  "geometry": {"coordinates":[4.348154068,50.8024177551],"type":"Point"}
}