{
  "type": "Feature",
  "properties": {
    "iso:country":"BE",
    "sg:address":"Bellegemstraat 24a",
    "sg:city":"Zwevegem",
    "sg:classifiers":[
        {
            "category":"Health Services",
            "subcategory":"Health Practitioner",
            "type":"Services"
        }
    ],
    "sg:phone":"+32 56 25 25 45",
    "sg:postcode":"8550",
    "sg:province":"West-Vlaanderen",
    "sg:tags":[
        "therapist",
        "speech"
    ],
    "wof:name":"Remmerie Joke",
    "wof:placetype":"venue"
},
  "geometry": {"coordinates":[3.3406751156,50.8006248474],"type":"Point"}
}