{
  "type": "Feature",
  "properties": {
    "addr:full":"Gistelse Steenweg 101 Brugge (sint-andries) West-Vlaanderen 8200",
    "addr:housenumber":"101",
    "addr:postcode":"8200",
    "addr:street":"Gistelse Steenweg",
    "iso:country":"BE",
    "sg:address":"Gistelse Steenweg 101",
    "sg:city":"Brugge (sint-andries)",
    "sg:classifiers":[
        {
            "category":"Retail",
            "subcategory":"Repair Shop",
            "type":"Services"
        }
    ],
    "sg:phone":"+32 50 38 48 01",
    "sg:postcode":"8200",
    "sg:province":"West-Vlaanderen",
    "sg:tags":[
        "-",
        "clothing",
        "alteration"
    ],
    "wof:name":"Naaikorf",
    "wof:placetype":"venue"
},
  "geometry": {"coordinates":[3.2051360607,51.2028083801],"type":"Point"}
}