{
  "type": "Feature",
  "properties": {
    "addr:full":"Ouren 17a Burg-reuland Li\u00e8ge 4790",
    "addr:housenumber":"17a",
    "addr:postcode":"4790",
    "addr:street":"Ouren",
    "iso:country":"BE",
    "sg:address":"Ouren 17a",
    "sg:city":"Burg-reuland",
    "sg:classifiers":[
        {
            "category":"Personal",
            "subcategory":"Beauty Salon",
            "type":"Services"
        }
    ],
    "sg:phone":"+32 80 32 94 25",
    "sg:postcode":"4790",
    "sg:province":"Li\u00e8ge",
    "sg:tags":[
        "lady",
        "-",
        "hairdressing"
    ],
    "wof:name":"Yvonne Salon",
    "wof:placetype":"venue"
},
  "geometry": {"coordinates":[6.1373310089,50.1408081055],"type":"Point"}
}