{
  "type": "Feature",
  "properties": {
    "addr:full":"Zuiderdijk 7 Wetteren Oost-Vlaanderen 9230",
    "addr:housenumber":"7",
    "addr:postcode":"9230",
    "addr:street":"Zuiderdijk",
    "iso:country":"BE",
    "sg:address":"Zuiderdijk 7",
    "sg:city":"Wetteren",
    "sg:orig_category":"Baby- and kinderkleding Dameskledingzaken Herenkledingzaken Lingerie and ondergoed Textiel",
    "sg:phone":"+32 9 369 52 79",
    "sg:postcode":"9230",
    "sg:province":"Oost-Vlaanderen",
    "wof:name":"Artex Family",
    "wof:placetype":"venue"
},
  "geometry": {"coordinates":[3.877710104,51.0071601868],"type":"Point"}
}