{
  "type": "Feature",
  "properties": {
    "iso:country":"BE",
    "sg:address":"Mariakerksesteenweg 235",
    "sg:city":"Gent (drongen)",
    "sg:orig_category":"Non-Classified Establishments",
    "sg:phone":"+32 9 236 29 09",
    "sg:postcode":"9031",
    "sg:province":"Oost-Vlaanderen",
    "wof:name":"Moda Italiana",
    "wof:placetype":"venue"
},
  "geometry": {"coordinates":[3.6554000378,51.063835144],"type":"Point"}
}