{
  "type": "Feature",
  "properties": {
    "iso:country":"BE",
    "sg:address":"Bois De Virelles 9",
    "sg:city":"Chimay",
    "sg:orig_category":"Eleveurs de bovins",
    "sg:phone":"+32 60 21 21 32",
    "sg:postcode":"6461",
    "sg:province":"Hainaut",
    "wof:name":"Jean Geerts",
    "wof:placetype":"venue"
},
  "geometry": {"coordinates":[4.3301529884,50.0923576355],"type":"Point"}
}