{
  "type": "Feature",
  "properties": {
    "addr:full":"Witte-molenstraat 25 Brugge West-Vlaanderen 8200",
    "addr:housenumber":"25",
    "addr:postcode":"8200",
    "addr:street":"Witte-Molenstraat",
    "iso:country":"BE",
    "sg:address":"Witte-molenstraat 25",
    "sg:city":"Brugge",
    "sg:orig_category":"Brood, gebak and snoepgoed",
    "sg:phone":"+32 50 38 55 55",
    "sg:postcode":"8200",
    "sg:province":"West-Vlaanderen",
    "wof:name":"'t Molentje",
    "wof:placetype":"venue"
},
  "geometry": {"coordinates":[3.2070829868,51.2042770386],"type":"Point"}
}