{
  "type": "Feature",
  "properties": {
    "iso:country":"BE",
    "sg:address":"Avenue Albert Jonnart 1",
    "sg:city":"Sint-lambrechts-woluwe/woluwe-saint-lambert",
    "sg:orig_category":"Agences de publicit\u00e9. Traducteurs and interpr\u00e8tes. Formation and enseignement",
    "sg:phone":"+32 2 733 91 28",
    "sg:postcode":"1200",
    "sg:province":"Bruxelles-Capitale",
    "wof:name":"Linguacentre-teller L. Cbtip/bkvtf",
    "wof:placetype":"venue"
},
  "geometry": {"coordinates":[4.4048490524,50.8435096741],"type":"Point"}
}