{
  "type": "Feature",
  "properties": {
    "addr:full":". Herbeumont (groot) Luxembourg 6887",
    "addr:postcode":"6887",
    "addr:street":"Groot Luxembourg",
    "iso:country":"BE",
    "sg:address":".",
    "sg:city":"Herbeumont (groot)",
    "sg:orig_category":"Apotheken",
    "sg:phone":"+32 900 10 500",
    "sg:postcode":"6887",
    "sg:province":"Luxembourg",
    "wof:name":"Apothekers Van Wacht",
    "wof:placetype":"venue"
},
  "geometry": {"coordinates":[5.23706007,49.7813262939],"type":"Point"}
}