{
  "type": "Feature",
  "properties": {
    "addr:full":"Grand Place 76 Enghien Hainaut 7850",
    "addr:housenumber":"76",
    "addr:postcode":"7850",
    "addr:street":"Grand Place",
    "iso:country":"BE",
    "sg:address":"Grand Place 76",
    "sg:city":"Enghien",
    "sg:classifiers":[
        {
            "category":"Bars & Pubs",
            "type":"Food & Drink"
        }
    ],
    "sg:phone":"+32 2 395 39 40",
    "sg:postcode":"7850",
    "sg:province":"Hainaut",
    "wof:name":"Carillon (au)",
    "wof:placetype":"venue"
},
  "geometry": {"coordinates":[4.0165047646,50.6920394897],"type":"Point"}
}