{
  "type": "Feature",
  "properties": {
    "iso:country":"BE",
    "sg:address":"Steenbakkerijstraat 15",
    "sg:city":"Bredene",
    "sg:classifiers":[
        {
            "category":"Professional",
            "subcategory":"Advertising",
            "type":"Services"
        }
    ],
    "sg:phone":"+32 59 80 33 31",
    "sg:postcode":"8450",
    "sg:province":"West-Vlaanderen",
    "sg:tags":[
        "painter"
    ],
    "wof:name":"Focke G",
    "wof:placetype":"venue"
},
  "geometry": {"coordinates":[2.974490881,51.2220458984],"type":"Point"}
}