{
  "type": "Feature",
  "properties": {
    "addr:full":"Rue Caremberg 8 Edingen/enghien Hainaut 7850",
    "addr:housenumber":"8",
    "addr:postcode":"7850",
    "addr:street":"Rue Caremberg",
    "iso:country":"BE",
    "sg:address":"Rue Caremberg 8",
    "sg:city":"Edingen/enghien",
    "sg:classifiers":[
        {
            "category":"Taxi",
            "type":"Transportation"
        }
    ],
    "sg:phone":"+32 2 395 84 88",
    "sg:postcode":"7850",
    "sg:province":"Hainaut",
    "wof:name":"Raymond Sacepe",
    "wof:placetype":"venue"
},
  "geometry": {"coordinates":[4.0687451363,50.6922073364],"type":"Point"}
}