{
  "type": "Feature",
  "properties": {
    "addr:full":"Meensestraat 5 Ieper West-Vlaanderen 8900",
    "addr:housenumber":"5",
    "addr:postcode":"8900",
    "addr:street":"Meensestraat",
    "iso:country":"BE",
    "sg:address":"Meensestraat 5",
    "sg:city":"Ieper",
    "sg:orig_category":"Kapsalons",
    "sg:phone":"+32 57 20 06 43",
    "sg:postcode":"8900",
    "sg:province":"West-Vlaanderen",
    "wof:name":"Jacques Pauwels",
    "wof:placetype":"venue"
},
  "geometry": {"coordinates":[2.8882610798,50.8515701294],"type":"Point"}
}