{
  "type": "Feature",
  "properties": {
    "iso:country":"BE",
    "sg:address":"Rue De Droixhe 30",
    "sg:city":"Li\u00e8ge 1 (li\u00e8ge 2)",
    "sg:classifiers":[
        {
            "category":"Banks & Credit Unions",
            "subcategory":"Bureau De Change",
            "type":"Services"
        }
    ],
    "sg:postcode":"4020",
    "sg:province":"Li\u00e8ge",
    "sg:tags":[
        "measuring",
        "control",
        "apparatus"
    ],
    "wof:name":"S P M-instrument",
    "wof:placetype":"venue"
},
  "geometry": {"coordinates":[5.1428499222,51.6863708496],"type":"Point"}
}