{
  "type": "Feature",
  "properties": {
    "iso:country":"BE",
    "sg:address":"Molenstraat 37",
    "sg:city":"Bilzen",
    "sg:orig_category":"Sportclubs",
    "sg:phone":"+32 11 32 28 74",
    "sg:postcode":"3740",
    "sg:province":"Limburg",
    "wof:name":"De Pettemboeren",
    "wof:placetype":"venue"
},
  "geometry": {"coordinates":[5.467250824,50.901802063],"type":"Point"}
}