{
  "type": "Feature",
  "properties": {
    "addr:full":"Rue Barbothez 31 Herve Li\u00e8ge 4653",
    "addr:housenumber":"31",
    "addr:postcode":"4653",
    "addr:street":"Rue Barbothez",
    "iso:country":"BE",
    "sg:address":"Rue Barbothez 31",
    "sg:city":"Herve",
    "sg:orig_category":"Installatie van houten of kunststof schrijnwerk",
    "sg:phone":"+32 4 387 53 61",
    "sg:postcode":"4653",
    "sg:province":"Li\u00e8ge",
    "wof:name":"Vincent De Leval",
    "wof:placetype":"venue"
},
  "geometry": {"coordinates":[5.7308549881,50.664478302],"type":"Point"}
}