{
  "type": "Feature",
  "properties": {
    "addr:full":"Dauwlaan 8 Sint-genesius-rode/rhode-saint-gen\u00c8se Vlaams-Brabant 1640",
    "addr:housenumber":"8",
    "addr:postcode":"1640",
    "addr:street":"Dauwlaan",
    "iso:country":"BE",
    "sg:address":"Dauwlaan 8",
    "sg:city":"Sint-genesius-rode/rhode-saint-gen\u00c8se",
    "sg:orig_category":"Artsen and specialisten",
    "sg:phone":"+32 2 358 40 24",
    "sg:postcode":"1640",
    "sg:province":"Vlaams-Brabant",
    "wof:name":"Marie-france Vaes",
    "wof:placetype":"venue"
},
  "geometry": {"coordinates":[4.3919668198,50.7400131226],"type":"Point"}
}