{
  "type": "Feature",
  "properties": {
    "iso:country":"BE",
    "sg:address":"Avenue De Laeken 50",
    "sg:city":"Jette",
    "sg:classifiers":[
        {
            "category":"Autos & Motor Vehicles",
            "subcategory":"Fuel & Gas Station",
            "type":"Retail Goods"
        }
    ],
    "sg:phone":"+32 2 426 93 03",
    "sg:postcode":"1090",
    "sg:province":"Bruxelles-Capitale",
    "sg:tags":[
        "stations-service",
        "carburants"
    ],
    "wof:name":"Hamid Monjazizadehahmadi",
    "wof:placetype":"venue"
},
  "geometry": {"coordinates":[4.3233780861,50.8707199097],"type":"Point"}
}