{
  "type": "Feature",
  "properties": {
    "addr:full":"Reigerlostraat 33 Beernem West-Vlaanderen 8730",
    "addr:housenumber":"33",
    "addr:postcode":"8730",
    "addr:street":"Reigerlostraat",
    "iso:country":"BE",
    "sg:address":"Reigerlostraat 33",
    "sg:city":"Beernem",
    "sg:orig_category":"Woningbouw",
    "sg:phone":"+32 50 78 83 50",
    "sg:postcode":"8730",
    "sg:province":"West-Vlaanderen",
    "wof:name":"Frans Redde & Zn",
    "wof:placetype":"venue"
},
  "geometry": {"coordinates":[3.320800066,51.1165351868],"type":"Point"}
}