{
  "type": "Feature",
  "properties": {
    "addr:full":"Vilvoordsesteenweg 31be Steenokkerzeel Vlaams-Brabant 1820",
    "addr:housenumber":"31be",
    "addr:postcode":"1820",
    "addr:street":"Vilvoordsesteenweg",
    "iso:country":"BE",
    "sg:address":"Vilvoordsesteenweg 31be",
    "sg:city":"Steenokkerzeel",
    "sg:orig_category":"Groententeelt",
    "sg:phone":"+32 2 751 51 20",
    "sg:postcode":"1820",
    "sg:province":"Vlaams-Brabant",
    "wof:name":"Patrick Dewinter",
    "wof:placetype":"venue"
},
  "geometry": {"coordinates":[4.4877800941,50.9348106384],"type":"Point"}
}