{
  "type": "Feature",
  "properties": {
    "addr:full":"All\u00e9e Du Clo\u00eetre 43 Bruxelles Bruxelles-Capitale 1000",
    "addr:housenumber":"43",
    "addr:postcode":"1000",
    "addr:street":"Alle\u0301E Du Cloi\u0302Tre",
    "iso:country":"BE",
    "sg:address":"All\u00e9e Du Clo\u00eetre 43",
    "sg:city":"Bruxelles",
    "sg:classifiers":[
        {
            "category":"Communications",
            "subcategory":"Film & Video Production",
            "type":"Services"
        }
    ],
    "sg:phone":"+32 2 647 55 71",
    "sg:postcode":"1000",
    "sg:province":"Bruxelles-Capitale",
    "sg:tags":[
        "sound",
        "recording",
        "studio"
    ],
    "wof:name":"Amor Et Psyche Productions",
    "wof:placetype":"venue"
},
  "geometry": {"coordinates":[4.3734087944,50.819355011],"type":"Point"}
}