{
  "type": "Feature",
  "properties": {
    "iso:country":"BE",
    "sg:address":"De Leiteweg 14",
    "sg:city":"Oostkamp",
    "sg:orig_category":"Pain, p\u00e2tisseries and confiseries",
    "sg:phone":"+32 50 28 83 83",
    "sg:postcode":"8020",
    "sg:province":"West-Vlaanderen",
    "wof:name":"Bakkerij De Baets",
    "wof:placetype":"venue"
},
  "geometry": {"coordinates":[3.2220079899,51.1043548584],"type":"Point"}
}