{
  "type": "Feature",
  "properties": {
    "iso:country":"BE",
    "sg:address":"Grand'place 32",
    "sg:city":"Ath",
    "sg:classifiers":[
        {
            "category":"Health Services",
            "subcategory":"Dentist",
            "type":"Services"
        }
    ],
    "sg:phone":"+32 68 28 10 55",
    "sg:postcode":"7800",
    "sg:province":"Hainaut",
    "wof:name":"Antoine Didier",
    "wof:placetype":"venue"
},
  "geometry": {"coordinates":[3.7767679691,50.6313171387],"type":"Point"}
}