{
  "type": "Feature",
  "properties": {
    "addr:full":"Avenue De La Braban\u00e7onne 82 Bruxelles (schaerbeek) Bruxelles-Capitale 1030",
    "addr:housenumber":"82",
    "addr:postcode":"1030",
    "addr:street":"Avenue De La Brabanc\u0327Onne",
    "iso:country":"BE",
    "sg:address":"Avenue De La Braban\u00e7onne 82",
    "sg:city":"Bruxelles (schaerbeek)",
    "sg:classifiers":[
        {
            "category":"Shopping",
            "subcategory":"Florist",
            "type":"Retail Goods"
        }
    ],
    "sg:phone":"+32 2 736 76 63",
    "sg:postcode":"1030",
    "sg:province":"Bruxelles-Capitale",
    "wof:name":"Natural Art Floral",
    "wof:placetype":"venue"
},
  "geometry": {"coordinates":[4.3866591454,50.8510742188],"type":"Point"}
}