{
  "type": "Feature",
  "properties": {
    "iso:country":"BE",
    "sg:address":"Avenue Des Fr\u00c8res Legrain 80",
    "sg:city":"Sint-pieters-woluwe/woluwe-saint-pierre",
    "sg:orig_category":"Librairies. Tabac. Journaux",
    "sg:phone":"+32 2 770 23 15",
    "sg:postcode":"1150",
    "sg:province":"Bruxelles-Capitale",
    "wof:name":"Maison paroles",
    "wof:placetype":"venue"
},
  "geometry": {"coordinates":[4.4127731323,50.8261222839],"type":"Point"}
}