{
  "type": "Feature",
  "properties": {
    "addr:full":"Baronstraat 30 Middelkerke (westende) West-Vlaanderen 8434",
    "addr:housenumber":"30",
    "addr:postcode":"8434",
    "addr:street":"Baronstraat",
    "iso:country":"BE",
    "sg:address":"Baronstraat 30",
    "sg:city":"Middelkerke (westende)",
    "sg:classifiers":[
        {
            "category":"Utilities",
            "subcategory":"Fuel Oil & Lpg",
            "type":"Services"
        }
    ],
    "sg:phone":"+32 58 23 36 32",
    "sg:postcode":"8434",
    "sg:province":"West-Vlaanderen",
    "wof:name":"Blomme Bvba",
    "wof:placetype":"venue"
},
  "geometry": {"coordinates":[2.7614700794,51.1501693726],"type":"Point"}
}