{
  "type": "Feature",
  "properties": {
    "iso:country":"BE",
    "sg:address":"H\u00c9domont 5",
    "sg:city":"Malmedy/malmedy",
    "sg:orig_category":"Eleveurs de bovins",
    "sg:phone":"+32 80 33 08 69",
    "sg:postcode":"4960",
    "sg:province":"Li\u00e8ge",
    "wof:name":"Charles Dumoulin",
    "wof:placetype":"venue"
},
  "geometry": {"coordinates":[6.038725853,50.4053230286],"type":"Point"}
}