{
  "type": "Feature",
  "properties": {
    "iso:country":"BE",
    "sg:address":"Kanaalstraat 9",
    "sg:city":"Zelzate",
    "sg:classifiers":[
        {
            "category":"Government",
            "subcategory":"Fire Station",
            "type":"Public Place"
        }
    ],
    "sg:phone":"+32 9115453740",
    "sg:postcode":"9060",
    "sg:province":"Oost-Vlaanderen",
    "sg:tags":[
        "supraregional",
        "plant",
        "installation",
        "heating"
    ],
    "wof:name":"Meire Gebroeders B.v.b.a.",
    "wof:placetype":"venue"
},
  "geometry": {"coordinates":[3.8062269688,51.2011375427],"type":"Point"}
}