{
  "type": "Feature",
  "properties": {
    "iso:country":"BE",
    "sg:address":"Herkenrodebosstraat 30",
    "sg:city":"Hasselt",
    "sg:orig_category":"Computers and computerapparatuur Informaticaconsulenten",
    "sg:phone":"+32 11 87 30 17",
    "sg:postcode":"3511",
    "sg:province":"Limburg",
    "wof:name":"Icasa Consulting Groep",
    "wof:placetype":"venue"
},
  "geometry": {"coordinates":[5.3034238815,50.9432487488],"type":"Point"}
}