{
  "type": "Feature",
  "properties": {
    "addr:full":"Steenweg 112 Nazareth Oost-Vlaanderen 9810",
    "addr:housenumber":"112",
    "addr:postcode":"9810",
    "addr:street":"Steenweg",
    "iso:country":"BE",
    "sg:address":"Steenweg 112",
    "sg:city":"Nazareth",
    "sg:orig_category":"Postkantoren Verzekeringsmakelaars and experts",
    "sg:phone":"+32 9 385 42 37",
    "sg:postcode":"9810",
    "sg:province":"Oost-Vlaanderen",
    "wof:name":"De Post",
    "wof:placetype":"venue"
},
  "geometry": {"coordinates":[3.6426079273,50.9591674805],"type":"Point"}
}