{
  "type": "Feature",
  "properties": {
    "iso:country":"BE",
    "sg:address":"Koutermansstraat",
    "sg:city":"Alken",
    "sg:classifiers":[
        {
            "category":"Arena",
            "subcategory":"Sports Club",
            "type":"Entertainment"
        }
    ],
    "sg:phone":"+32 11 31 40 40",
    "sg:postcode":"3570",
    "sg:province":"Limburg",
    "wof:name":"Alk (de)",
    "wof:placetype":"venue"
},
  "geometry": {"coordinates":[5.3126821518,50.875743866],"type":"Point"}
}