{
  "type": "Feature",
  "properties": {
    "iso:country":"BE",
    "sg:address":"Av. Edouard Speeckaert 51",
    "sg:city":"Sint-lambrechts-woluwe/woluwe-saint-lambert",
    "sg:orig_category":"Artistes ind\u00e9pendants",
    "sg:phone":"+32 2 771 45 78",
    "sg:postcode":"1200",
    "sg:province":"Bruxelles-Capitale",
    "wof:name":"De Lee",
    "wof:placetype":"venue"
},
  "geometry": {"coordinates":[4.4189138412,50.8481025696],"type":"Point"}
}