{
  "type": "Feature",
  "properties": {
    "iso:country":"BE",
    "sg:address":"Hameistraat 3",
    "sg:city":"Genk",
    "sg:orig_category":"Boekhouders",
    "sg:phone":"+32 11 35 16 10",
    "sg:postcode":"3600",
    "sg:province":"Limburg",
    "wof:name":"Vos Willy",
    "wof:placetype":"venue"
},
  "geometry": {"coordinates":[5.5078349113,50.9595527649],"type":"Point"}
}