{
  "type": "Feature",
  "properties": {
    "iso:country":"BE",
    "sg:address":"Torhoutbaan 6a",
    "sg:city":"Ichtegem",
    "sg:classifiers":[
        {
            "category":"Insurance",
            "subcategory":"Insurance Agent",
            "type":"Services"
        }
    ],
    "sg:phone":"+32 51 58 97 34",
    "sg:postcode":"8480",
    "sg:province":"West-Vlaanderen",
    "sg:tags":[
        "broker"
    ],
    "wof:name":"Taveirne Philip Bvba & Missinne",
    "wof:placetype":"venue"
},
  "geometry": {"coordinates":[3.0325899124,51.1008224487],"type":"Point"}
}