{
  "type": "Feature",
  "properties": {
    "addr:full":"Meusegemstraat 59 Meise Vlaams-Brabant 1861",
    "addr:housenumber":"59",
    "addr:postcode":"1861",
    "addr:street":"Meusegemstraat",
    "iso:country":"BE",
    "sg:address":"Meusegemstraat 59",
    "sg:city":"Meise",
    "sg:classifiers":[
        {
            "category":"Personal",
            "subcategory":"Beauty Salon",
            "type":"Services"
        }
    ],
    "sg:phone":"+32 2 269 33 39",
    "sg:postcode":"1861",
    "sg:province":"Vlaams-Brabant",
    "sg:tags":[
        "de",
        "coiffure"
    ],
    "wof:name":"Fabienne",
    "wof:placetype":"venue"
},
  "geometry": {"coordinates":[4.2878479958,50.9578514099],"type":"Point"}
}