{
  "type": "Feature",
  "properties": {
    "addr:full":"Mechelsesteenweg 393 Herent Vlaams-Brabant 3020",
    "addr:housenumber":"393",
    "addr:postcode":"3020",
    "addr:street":"Mechelsesteenweg",
    "iso:country":"BE",
    "sg:address":"Mechelsesteenweg 393",
    "sg:city":"Herent",
    "sg:orig_category":"Advocaten and juridische adviseurs",
    "sg:phone":"+32 16 22 70 83",
    "sg:postcode":"3020",
    "sg:province":"Vlaams-Brabant",
    "wof:name":"Luc Vanleeuw",
    "wof:placetype":"venue"
},
  "geometry": {"coordinates":[4.6722040176,50.9050559998],"type":"Point"}
}