{
  "type": "Feature",
  "properties": {
    "iso:country":"BE",
    "sg:address":"Drie Eikenstraat 20",
    "sg:city":"Herselt",
    "sg:classifiers":[
        {
            "category":"Recreation",
            "subcategory":"Campground",
            "type":"Entertainment"
        }
    ],
    "sg:phone":"+32 14 54 55 02",
    "sg:postcode":"2230",
    "sg:province":"Antwerpen",
    "sg:tags":[
        "site",
        "camping"
    ],
    "wof:name":"Dry Eycken",
    "wof:placetype":"venue"
},
  "geometry": {"coordinates":[4.9036531448,51.0636940002],"type":"Point"}
}