{
  "type": "Feature",
  "properties": {
    "addr:full":"Jachthoornlaan 107 Watermaal-bosvoorde/watermael-boitsfort Bruxelles-Capitale 1170",
    "addr:housenumber":"107",
    "addr:postcode":"1170",
    "addr:street":"Jachthoornlaan",
    "iso:country":"BE",
    "sg:address":"Jachthoornlaan 107",
    "sg:city":"Watermaal-bosvoorde/watermael-boitsfort",
    "sg:orig_category":"Artsen and specialisten",
    "sg:phone":"+32 2 673 87 66",
    "sg:postcode":"1170",
    "sg:province":"Bruxelles-Capitale",
    "wof:name":"Mehnaz Maleki",
    "wof:placetype":"venue"
},
  "geometry": {"coordinates":[4.4011301994,50.8021697998],"type":"Point"}
}