{
  "type": "Feature",
  "properties": {
    "addr:full":"Rue De Saint-symphorien 50 Mons Hainaut 7021",
    "addr:housenumber":"50",
    "addr:postcode":"7021",
    "addr:street":"Rue De Saint-Symphorien;Hainaut",
    "iso:country":"BE",
    "sg:address":"Rue De Saint-symphorien 50",
    "sg:city":"Mons",
    "sg:orig_category":"V\u00eatements pour b\u00e9b\u00e9s and enfants",
    "sg:phone":"+32 65 87 39 53",
    "sg:postcode":"7021",
    "sg:province":"Hainaut",
    "wof:name":"Petites Canailles Degriff",
    "wof:placetype":"venue"
},
  "geometry": {"coordinates":[4.0456829071,50.4640655518],"type":"Point"}
}