{
  "type": "Feature",
  "properties": {
    "iso:country":"BE",
    "sg:address":"Rue Jean Depas 123",
    "sg:city":"Seraing",
    "sg:orig_category":"Traitements param\u00e9dicaux",
    "sg:phone":"+32 4 233 55 27",
    "sg:postcode":"4101",
    "sg:province":"Li\u00e8ge",
    "wof:name":"Joelle Moyse",
    "wof:placetype":"venue"
},
  "geometry": {"coordinates":[5.4881548882,50.621547699],"type":"Point"}
}