{
  "type": "Feature",
  "properties": {
    "iso:country":"BE",
    "sg:address":"Avenue A.j. Slegers 156b1",
    "sg:city":"Bruxelles",
    "sg:classifiers":[
        {
            "category":"Military Area",
            "subcategory":"Air Force Base",
            "type":"Public Place"
        }
    ],
    "sg:phone":"+32 2 772 72 00",
    "sg:postcode":"1200",
    "sg:province":"Bruxelles-Capitale",
    "sg:tags":[
        "filter",
        "bag",
        "system"
    ],
    "wof:name":"Hk Industries S.p.r.l.",
    "wof:placetype":"venue"
},
  "geometry": {"coordinates":[4.4222040176,50.8408088684],"type":"Point"}
}