{
  "type": "Feature",
  "properties": {
    "iso:country":"BE",
    "sg:address":"Rue Des Brasseurs 5",
    "sg:city":"Huy",
    "sg:orig_category":"V\u00eatements",
    "sg:phone":"+32 85 23 28 61",
    "sg:postcode":"4500",
    "sg:province":"Li\u00e8ge",
    "wof:name":"Super Jeans",
    "wof:placetype":"venue"
},
  "geometry": {"coordinates":[5.2411260605,50.5176467896],"type":"Point"}
}