{
  "type": "Feature",
  "properties": {
    "addr:full":"Ch\u00c2teau Des Mottes 1 Frasnes-lez-anvaing Hainaut 7911",
    "addr:housenumber":"1;7911",
    "addr:street":"Frasnes-Lez-Anvaing Hainaut",
    "iso:country":"BE",
    "sg:address":"Ch\u00c2teau Des Mottes 1",
    "sg:city":"Frasnes-lez-anvaing",
    "sg:orig_category":"Eleveurs de bovins",
    "sg:phone":"+32 69 86 70 10",
    "sg:postcode":"7911",
    "sg:province":"Hainaut",
    "wof:name":"Gerard Melys",
    "wof:placetype":"venue"
},
  "geometry": {"coordinates":[3.6380391121,50.6772270203],"type":"Point"}
}