{
  "type": "Feature",
  "properties": {
    "addr:full":"Dageraadlaan 8 Beerse Antwerpen 2340",
    "addr:housenumber":"8",
    "addr:postcode":"2340",
    "addr:street":"Dageraadlaan",
    "iso:country":"BE",
    "sg:address":"Dageraadlaan 8",
    "sg:city":"Beerse",
    "sg:classifiers":[
        {
            "category":"Health Services",
            "subcategory":"Dentist",
            "type":"Services"
        }
    ],
    "sg:phone":"+32 14 61 54 34",
    "sg:postcode":"2340",
    "sg:province":"Antwerpen",
    "wof:name":"Carpentier Filip",
    "wof:placetype":"venue"
},
  "geometry": {"coordinates":[4.8509249687,51.3050346375],"type":"Point"}
}