{
  "type": "Feature",
  "properties": {
    "iso:country":"BE",
    "sg:address":"Begonialaan 1",
    "sg:city":"Diksmuide",
    "sg:orig_category":"Maatschappelijke dienstverlening",
    "sg:phone":"+32 51 50 44 88",
    "sg:postcode":"8600",
    "sg:province":"West-Vlaanderen",
    "wof:name":"Rode Kruis Diksmuide",
    "wof:placetype":"venue"
},
  "geometry": {"coordinates":[2.8583490849,51.0314254761],"type":"Point"}
}