{
  "type": "Feature",
  "properties": {
    "iso:country":"BE",
    "sg:address":"Holleweg 18",
    "sg:city":"Kalmthout",
    "sg:orig_category":"M\u00e9decins and sp\u00e9cialistes",
    "sg:phone":"+32 3 677 19 30",
    "sg:postcode":"2920",
    "sg:province":"Antwerpen",
    "wof:name":"Elif Ercoskun",
    "wof:placetype":"venue"
},
  "geometry": {"coordinates":[4.5078601837,51.4310493469],"type":"Point"}
}