{
  "type": "Feature",
  "properties": {
    "iso:country":"BE",
    "sg:address":"Elsense Steenweg 91",
    "sg:city":"Elsene/ixelles",
    "sg:orig_category":"Geschenken and souvenirs Speelgoed Verlichting and huishoudartikelen",
    "sg:phone":"+32 2 502 54 64",
    "sg:postcode":"1050",
    "sg:province":"Bruxelles-Capitale",
    "wof:name":"Maison Amicrack",
    "wof:placetype":"venue"
},
  "geometry": {"coordinates":[4.3636817932,50.835231781],"type":"Point"}
}