{
  "type": "Feature",
  "properties": {
    "iso:country":"BE",
    "sg:address":"Heirweg 35",
    "sg:city":"Maldegem",
    "sg:orig_category":"Installation de menuiserie en bois and plastique",
    "sg:phone":"+32 50 71 62 99",
    "sg:postcode":"9990",
    "sg:province":"Oost-Vlaanderen",
    "wof:name":"Johan Vandesteene",
    "wof:placetype":"venue"
},
  "geometry": {"coordinates":[3.4036400318,51.212020874],"type":"Point"}
}