{
  "type": "Feature",
  "properties": {
    "addr:full":"Nijvelsesteenweg 44 Halle Vlaams-Brabant 1500",
    "addr:housenumber":"44",
    "addr:postcode":"1500",
    "addr:street":"Nijvelsesteenweg",
    "iso:country":"BE",
    "sg:address":"Nijvelsesteenweg 44",
    "sg:city":"Halle",
    "sg:classifiers":[
        {
            "category":"Bakery",
            "type":"Food & Drink"
        }
    ],
    "sg:phone":"+32 2 356 94 91",
    "sg:postcode":"1500",
    "sg:province":"Vlaams-Brabant",
    "sg:tags":[
        "confectioner",
        "baker"
    ],
    "wof:name":"Fran\u00e7ois F",
    "wof:placetype":"venue"
},
  "geometry": {"coordinates":[4.2430977821,50.7280311584],"type":"Point"}
}