{
  "type": "Feature",
  "properties": {
    "addr:full":"Lange Leemstraat 110 Antwerpen Antwerpen 2018",
    "addr:housenumber":"110",
    "addr:postcode":"2018",
    "addr:street":"Lange Leemstraat",
    "iso:country":"BE",
    "sg:address":"Lange Leemstraat 110",
    "sg:city":"Antwerpen",
    "sg:classifiers":[
        {
            "category":"Personal",
            "subcategory":"Skin Care",
            "type":"Services"
        }
    ],
    "sg:phone":"+32 3 234 13 01",
    "sg:postcode":"2018",
    "sg:province":"Antwerpen",
    "sg:tags":[
        "hair",
        "treatment"
    ],
    "wof:name":"Hair Weaving House",
    "wof:placetype":"venue"
},
  "geometry": {"coordinates":[4.4132490158,51.2076301575],"type":"Point"}
}