{
  "type": "Feature",
  "properties": {
    "addr:full":"Chauss\u00e9e De Charleroi 773 Fleurus Hainaut 6220",
    "addr:housenumber":"773",
    "addr:postcode":"6220",
    "addr:street":"Chausse\u0301E De Charleroi",
    "iso:country":"BE",
    "sg:address":"Chauss\u00e9e De Charleroi 773",
    "sg:city":"Fleurus",
    "sg:classifiers":[
        {
            "category":"Manufacturing",
            "subcategory":"Motor Vehicles & Parts",
            "type":"Manufacturing & Wholesale Goods"
        }
    ],
    "sg:phone":"+32 71 81 11 70",
    "sg:postcode":"6220",
    "sg:province":"Hainaut",
    "sg:tags":[
        "exhaust",
        "system"
    ],
    "wof:name":"Delcorps Auto-equipment",
    "wof:placetype":"venue"
},
  "geometry": {"coordinates":[4.5383300781,50.4679107666],"type":"Point"}
}