{
  "type": "Feature",
  "properties": {
    "addr:full":"Rue Dethy 4 Sint-gillis/saint-gilles Bruxelles-Capitale 1060",
    "addr:housenumber":"4",
    "addr:postcode":"1060",
    "addr:street":"Rue Dethy",
    "iso:country":"BE",
    "sg:address":"Rue Dethy 4",
    "sg:city":"Sint-gillis/saint-gilles",
    "sg:orig_category":"Epiceries",
    "sg:phone":"+32 2 539 06 12",
    "sg:postcode":"1060",
    "sg:province":"Bruxelles-Capitale",
    "wof:name":"Maison Frech-fruit",
    "wof:placetype":"venue"
},
  "geometry": {"coordinates":[4.3439450264,50.828666687],"type":"Point"}
}