{
  "type": "Feature",
  "properties": {
    "iso:country":"BE",
    "sg:address":"Avenue De La Brise 13",
    "sg:city":"Brussel/bruxelles",
    "sg:orig_category":"Assurances. Bureaux de poste",
    "sg:phone":"+32 2 262 05 39",
    "sg:postcode":"1020",
    "sg:province":"Bruxelles-Capitale",
    "wof:name":"La Poste",
    "wof:placetype":"venue"
},
  "geometry": {"coordinates":[4.3577342033,50.8975563049],"type":"Point"}
}