{
  "type": "Feature",
  "properties": {
    "addr:full":"Boulevard Louis Mettewie 445b5 Sint-jans-molenbeek/molenbeek-saint-jean Bruxelles-Capitale 1080",
    "addr:housenumber":"445b5",
    "addr:postcode":"1080",
    "addr:street":"Boulevard Louis Mettewie",
    "iso:country":"BE",
    "sg:address":"Boulevard Louis Mettewie 445b5",
    "sg:city":"Sint-jans-molenbeek/molenbeek-saint-jean",
    "sg:orig_category":"D\u00e9corateurs d'int\u00e9rieur",
    "sg:phone":"+32 2 411 45 39",
    "sg:postcode":"1080",
    "sg:province":"Bruxelles-Capitale",
    "wof:name":"Gyn Ronsse Interieur",
    "wof:placetype":"venue"
},
  "geometry": {"coordinates":[4.2987761497,50.8495826721],"type":"Point"}
}