{
  "type": "Feature",
  "properties": {
    "addr:full":"Eekhoutdriesstraat 49 Gent (oostakker) Oost-Vlaanderen 9041",
    "addr:housenumber":"49",
    "addr:postcode":"9041",
    "addr:street":"Eekhoutdriesstraat",
    "iso:country":"BE",
    "sg:address":"Eekhoutdriesstraat 49",
    "sg:city":"Gent (oostakker)",
    "sg:classifiers":[
        {
            "category":"Professional",
            "subcategory":"Art Services",
            "type":"Services"
        }
    ],
    "sg:phone":"+32 9 259 89 99",
    "sg:postcode":"9041",
    "sg:province":"Oost-Vlaanderen",
    "sg:tags":[
        "interior",
        "designer"
    ],
    "wof:name":"De Kesel J",
    "wof:placetype":"venue"
},
  "geometry": {"coordinates":[3.7618119717,51.1041069031],"type":"Point"}
}