{
  "type": "Feature",
  "properties": {
    "iso:country":"BE",
    "sg:address":"Avenue De La Sabli\u00e8re 2",
    "sg:city":"Bruxelles (auderghem)",
    "sg:classifiers":[
        {
            "category":"Education",
            "subcategory":"School",
            "type":"Public Place"
        }
    ],
    "sg:phone":"+32 2 672 38 67",
    "sg:postcode":"1160",
    "sg:province":"Bruxelles-Capitale",
    "sg:tags":[
        "secondary"
    ],
    "wof:name":"Lutgardiscollege-oudergem",
    "wof:placetype":"venue"
},
  "geometry": {"coordinates":[4.4288249016,50.818145752],"type":"Point"}
}