{
  "type": "Feature",
  "properties": {
    "iso:country":"BE",
    "sg:address":"Groot Hagelkruis 196",
    "sg:city":"Antwerpen",
    "sg:classifiers":[
        {
            "category":"Wholesale",
            "subcategory":"Office Equipment",
            "type":"Manufacturing & Wholesale Goods"
        }
    ],
    "sg:phone":"+32 3 541 38 90",
    "sg:postcode":"2030",
    "sg:province":"Antwerpen",
    "sg:tags":[
        "machine",
        "rental",
        "retail",
        "-"
    ],
    "wof:name":"Joris Bvba",
    "wof:placetype":"venue"
},
  "geometry": {"coordinates":[4.4092359543,51.2737350464],"type":"Point"}
}