{
  "type": "Feature",
  "properties": {
    "addr:full":"Edg. Farasijnstraat 11 Koksijde (oostduinkerke) West-Vlaanderen 8670",
    "addr:housenumber":"11",
    "addr:postcode":"8670",
    "addr:street":"Farasijnstraat",
    "iso:country":"BE",
    "sg:address":"Edg. Farasijnstraat 11",
    "sg:city":"Koksijde (oostduinkerke)",
    "sg:classifiers":[
        {
            "category":"Personal",
            "subcategory":"Beauty Salon",
            "type":"Services"
        }
    ],
    "sg:phone":"+32 58 51 27 87",
    "sg:postcode":"8670",
    "sg:province":"West-Vlaanderen",
    "wof:name":"Bellefroid M-a",
    "wof:placetype":"venue"
},
  "geometry": {"coordinates":[2.6492800713,51.1061401367],"type":"Point"}
}