{
  "type": "Feature",
  "properties": {
    "addr:full":"Grote Haart 20 Hamont-achel Limburg 3930",
    "addr:housenumber":"20",
    "addr:postcode":"3930",
    "addr:street":"Grote Haart",
    "iso:country":"BE",
    "sg:address":"Grote Haart 20",
    "sg:city":"Hamont-achel",
    "sg:orig_category":"Eleveurs de bovins",
    "sg:phone":"+32 11 44 58 64",
    "sg:postcode":"3930",
    "sg:province":"Limburg",
    "wof:name":"Willy Schuurmans",
    "wof:placetype":"venue"
},
  "geometry": {"coordinates":[5.5027117729,51.2558059692],"type":"Point"}
}