{
  "type": "Feature",
  "properties": {
    "iso:country":"BE",
    "sg:address":"All\u00c9e Des Peupliers 20",
    "sg:city":"Bernissart",
    "sg:orig_category":"Dakwerken Plaatsen van vloer- and muurbekleding Woningbouw",
    "sg:phone":"+32 69 56 00 19",
    "sg:postcode":"7320",
    "sg:province":"Hainaut",
    "wof:name":"Bernard Destrebecq",
    "wof:placetype":"venue"
},
  "geometry": {"coordinates":[3.664798975,50.4764823914],"type":"Point"}
}