{
  "type": "Feature",
  "properties": {
    "iso:country":"BE",
    "sg:address":"Meuleschettestraat 86",
    "sg:city":"Aalst",
    "sg:classifiers":[
        {
            "category":"Bakery",
            "type":"Food & Drink"
        }
    ],
    "sg:phone":"+32 53 21 37 58",
    "sg:postcode":"9300",
    "sg:province":"Oost-Vlaanderen",
    "sg:tags":[
        "confectioner",
        "baker"
    ],
    "wof:name":"Dufour G",
    "wof:placetype":"venue"
},
  "geometry": {"coordinates":[4.0286569595,50.942943573],"type":"Point"}
}