{
  "type": "Feature",
  "properties": {
    "iso:country":"BE",
    "sg:address":"Groenhovestraat 34",
    "sg:city":"Oostkamp",
    "sg:orig_category":"Rundveehouders",
    "sg:phone":"+32 50 27 83 21",
    "sg:postcode":"8020",
    "sg:province":"West-Vlaanderen",
    "wof:name":"Marcel Vanhauwaert",
    "wof:placetype":"venue"
},
  "geometry": {"coordinates":[3.1670930386,51.0856513977],"type":"Point"}
}