{
  "type": "Feature",
  "properties": {
    "addr:full":"Rue De Boncelles 69 Seraing Li\u00e8ge 4102",
    "addr:housenumber":"69",
    "addr:postcode":"4102",
    "addr:street":"Rue De Boncelles",
    "iso:country":"BE",
    "sg:address":"Rue De Boncelles 69",
    "sg:city":"Seraing",
    "sg:classifiers":[
        {
            "category":"Cafe",
            "type":"Food & Drink"
        }
    ],
    "sg:phone":"+32 4 385 16 85",
    "sg:postcode":"4102",
    "sg:province":"Li\u00e8ge",
    "sg:tags":[
        "caf\u00e9s"
    ],
    "wof:name":"Caf\u00c9 Novy",
    "wof:placetype":"venue"
},
  "geometry": {"coordinates":[5.5347099304,50.6039085388],"type":"Point"}
}