{
  "type": "Feature",
  "properties": {
    "addr:full":"Belgicalaan 10 Sint-jans-molenbeek/molenbeek- Bruxelles-Capitale 1080",
    "addr:housenumber":"10",
    "addr:postcode":"1080",
    "addr:street":"Belgicalaan",
    "iso:country":"BE",
    "sg:address":"Belgicalaan 10",
    "sg:city":"Sint-jans-molenbeek/molenbeek-",
    "sg:classifiers":[
        {
            "category":"Manufacturing",
            "subcategory":"Textiles",
            "type":"Manufacturing & Wholesale Goods"
        }
    ],
    "sg:phone":"+32 2 414 61 76",
    "sg:postcode":"1080",
    "sg:province":"Bruxelles-Capitale",
    "sg:tags":[
        "fab",
        "diverse",
        "textielproducten"
    ],
    "wof:name":"Harmony",
    "wof:placetype":"venue"
},
  "geometry": {"coordinates":[4.3382949829,50.8659362793],"type":"Point"}
}