{
  "type": "Feature",
  "properties": {
    "iso:country":"BE",
    "sg:address":"Avenue Du Douaire 2",
    "sg:city":"Ottignies-louvain-la-neuve",
    "sg:orig_category":"Parfumeries. Instituts de beaut\u00e9. Centres de relaxation and bien-\u00eatre",
    "sg:phone":"+32 10 41 69 36",
    "sg:postcode":"1340",
    "sg:province":"Brabant Wallon",
    "wof:name":"Institut Alexis",
    "wof:placetype":"venue"
},
  "geometry": {"coordinates":[4.5672249794,50.6636390686],"type":"Point"}
}