{
  "type": "Feature",
  "properties": {
    "iso:country":"BE",
    "sg:address":"Rue Des Drapiers 21",
    "sg:city":"Wavre",
    "sg:classifiers":[
        {
            "category":"Professional",
            "subcategory":"Accounting & Tax Preparation",
            "type":"Services"
        }
    ],
    "sg:phone":"+32 10 22 62 04",
    "sg:postcode":"1300",
    "sg:province":"Brabant Wallon",
    "sg:tags":[
        "accountant"
    ],
    "wof:name":"Philippe Puissant",
    "wof:placetype":"venue"
},
  "geometry": {"coordinates":[4.6212191582,50.717956543],"type":"Point"}
}