{
  "type": "Feature",
  "properties": {
    "addr:full":"Kruisstraat 22 A Affligem Vlaams-Brabant 1790",
    "addr:housenumber":"22 a",
    "addr:postcode":"1790",
    "addr:street":"Kruisstraat",
    "iso:country":"BE",
    "sg:address":"Kruisstraat 22 A",
    "sg:city":"Affligem",
    "sg:orig_category":"Verhuisdiensten",
    "sg:phone":"+32 53 66 16 77",
    "sg:postcode":"1790",
    "sg:province":"Vlaams-Brabant",
    "wof:name":"Bornauw Walter",
    "wof:placetype":"venue"
},
  "geometry": {"coordinates":[4.1068601608,50.9156608582],"type":"Point"}
}