{
  "type": "Feature",
  "properties": {
    "addr:full":"Rue Brouck Au Tilleul 44 Bassenge Li\u00e8ge 4690",
    "addr:housenumber":"44",
    "addr:postcode":"4690",
    "addr:street":"Rue Brouck Au Tilleul",
    "iso:country":"BE",
    "sg:address":"Rue Brouck Au Tilleul 44",
    "sg:city":"Bassenge",
    "sg:orig_category":"Benzinestations and brandstoffen Voertuigen",
    "sg:phone":"+32 4 286 17 11",
    "sg:postcode":"4690",
    "sg:province":"Li\u00e8ge",
    "wof:name":"Garage Neufcourt",
    "wof:placetype":"venue"
},
  "geometry": {"coordinates":[5.5472841263,50.7537498474],"type":"Point"}
}