{
  "type": "Feature",
  "properties": {
    "iso:country":"BE",
    "sg:address":"Noordstraat 26",
    "sg:city":"Kontich",
    "sg:orig_category":"Auto-\u00e9coles",
    "sg:phone":"+32 3 458 13 24",
    "sg:postcode":"2550",
    "sg:province":"Antwerpen",
    "wof:name":"A.r.m.",
    "wof:placetype":"venue"
},
  "geometry": {"coordinates":[4.4455060959,51.1365470886],"type":"Point"}
}