{
  "type": "Feature",
  "properties": {
    "addr:full":"Stationsstraat 17 Hoeselt Limburg 3730",
    "addr:housenumber":"17",
    "addr:postcode":"3730",
    "addr:street":"Stationsstraat",
    "iso:country":"BE",
    "sg:address":"Stationsstraat 17",
    "sg:city":"Hoeselt",
    "sg:orig_category":"V\u00eatements, chaussures and accessoires Articles de camping and de sport",
    "sg:phone":"+32 89 41 49 12",
    "sg:postcode":"3730",
    "sg:province":"Limburg",
    "wof:name":"Rema Sport",
    "wof:placetype":"venue"
},
  "geometry": {"coordinates":[5.4928917885,50.8498001099],"type":"Point"}
}