{
  "type": "Feature",
  "properties": {
    "iso:country":"BE",
    "sg:address":"Chemin De La Celle 2",
    "sg:city":"Thuin",
    "sg:orig_category":"Dierenartsen",
    "sg:phone":"+32 71 59 18 92",
    "sg:postcode":"6530",
    "sg:province":"Hainaut",
    "wof:name":"Anne Marlier",
    "wof:placetype":"venue"
},
  "geometry": {"coordinates":[4.2980308533,50.3418579102],"type":"Point"}
}