{
  "type": "Feature",
  "properties": {
    "iso:country":"BE",
    "sg:address":"Rodelos 1",
    "sg:city":"Oudenaarde",
    "sg:classifiers":[
        {
            "category":"Arena",
            "subcategory":"Sports Club",
            "type":"Entertainment"
        }
    ],
    "sg:phone":"+32 55 31 52 60",
    "sg:postcode":"9700",
    "sg:province":"Oost-Vlaanderen",
    "wof:name":"Sporthal",
    "wof:placetype":"venue"
},
  "geometry": {"coordinates":[3.6140649319,50.8509407043],"type":"Point"}
}