{
  "type": "Feature",
  "properties": {
    "addr:full":"August Wautersstraat 35 Ba Temse Oost-Vlaanderen 9140",
    "addr:housenumber":"35",
    "addr:postcode":"9140",
    "addr:street":"August Wautersstraat;Oost-Vlaanderen",
    "iso:country":"BE",
    "sg:address":"August Wautersstraat 35 Ba",
    "sg:city":"Temse",
    "sg:classifiers":[
        {
            "category":"Shopping",
            "subcategory":"Clothing, Apparel, & Fashions",
            "type":"Retail Goods"
        }
    ],
    "sg:phone":"+32 3 771 26 44",
    "sg:postcode":"9140",
    "sg:province":"Oost-Vlaanderen",
    "sg:tags":[
        "ondergoed",
        "lingerie"
    ],
    "wof:name":"Huis Peirsman",
    "wof:placetype":"venue"
},
  "geometry": {"coordinates":[4.2221589088,51.1755447388],"type":"Point"}
}