{
  "type": "Feature",
  "properties": {
    "addr:full":"Avenue Sti\u00e9non 100 Bruxelles Bruxelles-Capitale 1020",
    "addr:housenumber":"100",
    "addr:postcode":"1020",
    "addr:street":"Avenue Stie\u0301Non",
    "iso:country":"BE",
    "sg:address":"Avenue Sti\u00e9non 100",
    "sg:city":"Bruxelles",
    "sg:classifiers":[
        {
            "category":"Shopping",
            "subcategory":"Books",
            "type":"Retail Goods"
        }
    ],
    "sg:phone":"+32 2 478 59 48",
    "sg:postcode":"1020",
    "sg:province":"Bruxelles-Capitale",
    "sg:tags":[
        "bookseller"
    ],
    "wof:name":"Stienon",
    "wof:placetype":"venue"
},
  "geometry": {"coordinates":[4.3301529884,50.8903236389],"type":"Point"}
}