{
  "type": "Feature",
  "properties": {
    "addr:full":"Marktstraat 11 De Haan West-Vlaanderen 8420",
    "addr:housenumber":"11",
    "addr:postcode":"8420",
    "addr:street":"Marktstraat",
    "iso:country":"BE",
    "sg:address":"Marktstraat 11",
    "sg:city":"De Haan",
    "sg:classifiers":[
        {
            "category":"Restaurant",
            "type":"Food & Drink"
        }
    ],
    "sg:phone":"+32 59 23 58 67",
    "sg:postcode":"8420",
    "sg:province":"West-Vlaanderen",
    "sg:tags":[
        "caf\u00e9s"
    ],
    "wof:name":"Taverne Akotee",
    "wof:placetype":"venue"
},
  "geometry": {"coordinates":[3.0350320339,51.2726783752],"type":"Point"}
}