{
  "type": "Feature",
  "properties": {
    "iso:country":"BE",
    "sg:address":"Rue Georges Dispa 17",
    "sg:city":"Wanze (bas-oha)",
    "sg:classifiers":[
        {
            "category":"Communications",
            "subcategory":"News Services",
            "type":"Services"
        }
    ],
    "sg:phone":"+32 85 23 55 43",
    "sg:postcode":"4520",
    "sg:province":"Li\u00e8ge",
    "sg:tags":[
        "illustrator"
    ],
    "wof:name":"Faymonville T",
    "wof:placetype":"venue"
},
  "geometry": {"coordinates":[5.1888341904,50.5287284851],"type":"Point"}
}