{
  "type": "Feature",
  "properties": {
    "addr:full":"Rue Brun 24 Andenne Namur 5300",
    "addr:housenumber":"24",
    "addr:postcode":"5300",
    "addr:street":"Rue Brun",
    "iso:country":"BE",
    "sg:address":"Rue Brun 24",
    "sg:city":"Andenne",
    "sg:classifiers":[
        {
            "category":"Bakery",
            "type":"Food & Drink"
        }
    ],
    "sg:phone":"+32 85 84 15 30",
    "sg:postcode":"5300",
    "sg:province":"Namur",
    "sg:tags":[
        "confectioner",
        "baker"
    ],
    "wof:name":"Dieudonn\u00e9 M",
    "wof:placetype":"venue"
},
  "geometry": {"coordinates":[5.0974597931,50.4882888794],"type":"Point"}
}