{
  "type": "Feature",
  "properties": {
    "addr:full":"Stijn Streuvelsstraat 5 Ichtegem West-Vlaanderen 8480",
    "addr:housenumber":"5",
    "addr:postcode":"8480",
    "addr:street":"Stijn Streuvelsstraat",
    "iso:country":"BE",
    "sg:address":"Stijn Streuvelsstraat 5",
    "sg:city":"Ichtegem",
    "sg:orig_category":"Banken and kredietinstellingen",
    "sg:phone":"+32 59 29 01 10",
    "sg:postcode":"8480",
    "sg:province":"West-Vlaanderen",
    "wof:name":"Citibank",
    "wof:placetype":"venue"
},
  "geometry": {"coordinates":[3.0246899128,51.1353492737],"type":"Point"}
}