{
  "type": "Feature",
  "properties": {
    "iso:country":"BE",
    "sg:address":"Rue Du Ramponneau 29a",
    "sg:city":"Frasnes-lez-anvaing (frasnes - Lez - Buissenal)",
    "sg:classifiers":[
        {
            "category":"Banks & Credit Unions",
            "subcategory":"Investment Brokerage",
            "type":"Services"
        }
    ],
    "sg:phone":"+32 69 87 18 50",
    "sg:postcode":"7911",
    "sg:province":"Hainaut",
    "wof:name":"Rosier Y",
    "wof:placetype":"venue"
},
  "geometry": {"coordinates":[3.6196279526,50.6722640991],"type":"Point"}
}