{
  "type": "Feature",
  "properties": {
    "addr:full":"Rue De Merbes 143 Binche Hainaut 7131",
    "addr:housenumber":"143",
    "addr:postcode":"7131",
    "addr:street":"Rue De Merbes",
    "iso:country":"BE",
    "sg:address":"Rue De Merbes 143",
    "sg:city":"Binche",
    "sg:classifiers":[
        {
            "category":"Arena",
            "subcategory":"Sports Club",
            "type":"Entertainment"
        }
    ],
    "sg:phone":"+32 64 33 61 89",
    "sg:postcode":"7131",
    "sg:province":"Hainaut",
    "sg:tags":[
        "terrain",
        "hors",
        "de",
        "installation",
        "sportifs"
    ],
    "wof:name":"Us. Buvrinnes-epinois",
    "wof:placetype":"venue"
},
  "geometry": {"coordinates":[4.1708221436,50.4047737122],"type":"Point"}
}