{
  "type": "Feature",
  "properties": {
    "iso:country":"BE",
    "sg:address":"Rue Bonne-femme 64",
    "sg:city":"Li\u00c8ge",
    "sg:orig_category":"Slagers",
    "sg:phone":"+32 4 343 28 68",
    "sg:postcode":"4030",
    "sg:province":"Li\u00e8ge",
    "wof:name":"Groupe Wauters",
    "wof:placetype":"venue"
},
  "geometry": {"coordinates":[5.5865941048,50.6296768188],"type":"Point"}
}