{
  "type": "Feature",
  "properties": {
    "iso:country":"BE",
    "sg:address":"Rue Daily Bul 33",
    "sg:city":"La Louviere",
    "sg:orig_category":"Artsen and specialisten",
    "sg:phone":"+32 64 26 23 90",
    "sg:postcode":"7100",
    "sg:province":"Hainaut",
    "wof:name":"Fran\u00c7oise Embrechts",
    "wof:placetype":"venue"
},
  "geometry": {"coordinates":[4.1958699226,50.4763793945],"type":"Point"}
}