{
  "type": "Feature",
  "properties": {
    "iso:country":"BE",
    "sg:address":"Omleiding 200",
    "sg:city":"Herent",
    "sg:classifiers":[
        {
            "category":"Retail",
            "subcategory":"Auto Repair",
            "type":"Services"
        }
    ],
    "sg:phone":"+32 16 22 64 19",
    "sg:postcode":"3020",
    "sg:province":"Vlaams-Brabant",
    "sg:tags":[
        "automobile-body"
    ],
    "wof:name":"Verfaillie J",
    "wof:placetype":"venue"
},
  "geometry": {"coordinates":[4.664978981,50.9121246338],"type":"Point"}
}