{
  "type": "Feature",
  "properties": {
    "iso:country":"BE",
    "sg:address":"Van Gorplaan 9",
    "sg:city":"Putte",
    "sg:orig_category":"Diensten voor huisdieren",
    "sg:phone":"+32 15 75 35 34",
    "sg:postcode":"2580",
    "sg:province":"Antwerpen",
    "wof:name":"Amorado",
    "wof:placetype":"venue"
},
  "geometry": {"coordinates":[4.6340479851,51.0508766174],"type":"Point"}
}