{
  "type": "Feature",
  "properties": {
    "addr:full":"Rue Saint-remy 5 Liege Li\u00e8ge 4000",
    "addr:housenumber":"5",
    "addr:postcode":"4000",
    "addr:street":"Rue Saint-Remy",
    "iso:country":"BE",
    "sg:address":"Rue Saint-remy 5",
    "sg:city":"Liege",
    "sg:orig_category":"Effectenmakelaars and vermogensbeheer",
    "sg:phone":"+32 4 252 29 73",
    "sg:postcode":"4000",
    "sg:province":"Li\u00e8ge",
    "wof:name":"Altis",
    "wof:placetype":"venue"
},
  "geometry": {"coordinates":[5.5704421997,50.6390228271],"type":"Point"}
}