{
  "type": "Feature",
  "properties": {
    "iso:country":"BE",
    "sg:address":"Sint-jan-ter-biezen 26",
    "sg:city":"Poperinge",
    "sg:orig_category":"Epiceries",
    "sg:phone":"+32 57 38 80 86",
    "sg:postcode":"8978",
    "sg:province":"West-Vlaanderen",
    "wof:name":"Andrea Fossaert",
    "wof:placetype":"venue"
},
  "geometry": {"coordinates":[2.6660690308,50.8599243164],"type":"Point"}
}