{
  "type": "Feature",
  "properties": {
    "addr:full":"Avenue De L'eternit\u00e9 4 Bruxelles (anderlecht) Bruxelles-Capitale 1070",
    "addr:housenumber":"4",
    "addr:postcode":"1070",
    "addr:street":"Avenue De L'Eternite \u0301",
    "iso:country":"BE",
    "sg:address":"Avenue De L'eternit\u00e9 4",
    "sg:city":"Bruxelles (anderlecht)",
    "sg:classifiers":[
        {
            "category":"Shopping",
            "subcategory":"Discount & Variety Stores",
            "type":"Retail Goods"
        }
    ],
    "sg:phone":"+32 2 523 48 36",
    "sg:postcode":"1070",
    "sg:province":"Bruxelles-Capitale",
    "sg:tags":[
        "shop",
        "clearers",
        "curiosity",
        "furniture"
    ],
    "wof:name":"Brocante Remy",
    "wof:placetype":"venue"
},
  "geometry": {"coordinates":[4.3120408058,50.8397216797],"type":"Point"}
}