{
  "type": "Feature",
  "properties": {
    "iso:country":"BE",
    "sg:address":"Laarstraat 34",
    "sg:city":"Kampenhout",
    "sg:orig_category":"Groententeelt",
    "sg:phone":"+32 16 65 69 15",
    "sg:postcode":"1910",
    "sg:province":"Vlaams-Brabant",
    "wof:name":"Albert Deroover",
    "wof:placetype":"venue"
},
  "geometry": {"coordinates":[4.5455970764,50.9224586487],"type":"Point"}
}