{
  "type": "Feature",
  "properties": {
    "iso:country":"BE",
    "sg:address":"Rue Saint-roch 2",
    "sg:city":"Saint-hubert",
    "sg:orig_category":"Kapsalons",
    "sg:phone":"+32 61 61 25 05",
    "sg:postcode":"6870",
    "sg:province":"Luxembourg",
    "wof:name":"Beatif",
    "wof:placetype":"venue"
},
  "geometry": {"coordinates":[5.373497963,50.0249862671],"type":"Point"}
}