{
  "type": "Feature",
  "properties": {
    "addr:full":"Avenue John-fitzgerald Kennedy 35 Rixensart Brabant Wallon 1330",
    "addr:housenumber":"35",
    "addr:postcode":"1330",
    "addr:street":"Avenue John-Fitzgerald Kennedy;Wallon",
    "iso:country":"BE",
    "sg:address":"Avenue John-fitzgerald Kennedy 35",
    "sg:city":"Rixensart",
    "sg:classifiers":[
        {
            "category":"Retail",
            "subcategory":"Auto Repair",
            "type":"Services"
        }
    ],
    "sg:phone":"+32 2 653 94 17",
    "sg:postcode":"1330",
    "sg:province":"Brabant Wallon",
    "sg:tags":[
        "garage"
    ],
    "wof:name":"Av Motorsport Sprl",
    "wof:placetype":"venue"
},
  "geometry": {"coordinates":[4.5216188431,50.7069015503],"type":"Point"}
}