{
  "type": "Feature",
  "properties": {
    "iso:country":"BE",
    "sg:address":"Plaslaar 1",
    "sg:city":"Lier",
    "sg:orig_category":"Agences de voyages",
    "sg:phone":"+32 3 491 04 60",
    "sg:postcode":"2500",
    "sg:province":"Antwerpen",
    "wof:name":"Silverwing",
    "wof:placetype":"venue"
},
  "geometry": {"coordinates":[4.5469498634,51.144329071],"type":"Point"}
}