{
  "type": "Feature",
  "properties": {
    "iso:country":"BE",
    "sg:address":"Kapelleveld 7",
    "sg:city":"Ternat (sint-katherina-lombeek)",
    "sg:classifiers":[
        {
            "category":"Bars & Pubs",
            "type":"Food & Drink"
        }
    ],
    "sg:phone":"+32 2 582 34 34",
    "sg:postcode":"1742",
    "sg:province":"Vlaams-Brabant",
    "wof:name":"Ton (de)",
    "wof:placetype":"venue"
},
  "geometry": {"coordinates":[4.1568808556,50.8737373352],"type":"Point"}
}