{
  "type": "Feature",
  "properties": {
    "addr:full":"Tapuitstraat 13 Deerlijk West-Vlaanderen 8540",
    "addr:housenumber":"13",
    "addr:postcode":"8540",
    "addr:street":"Tapuitstraat",
    "iso:country":"BE",
    "sg:address":"Tapuitstraat 13",
    "sg:city":"Deerlijk",
    "sg:orig_category":"Dameskledingzaken",
    "sg:phone":"+32 56 77 66 15",
    "sg:postcode":"8540",
    "sg:province":"West-Vlaanderen",
    "wof:name":"Rik Roobrouck",
    "wof:placetype":"venue"
},
  "geometry": {"coordinates":[3.36602211,50.8425254822],"type":"Point"}
}