{
  "type": "Feature",
  "properties": {
    "addr:full":"Kanunnik Arthur Boonstraat 39 Willebroek (blaasveld) Antwerpen 2830",
    "addr:housenumber":"39",
    "addr:postcode":"2830",
    "addr:street":"Kanunnik Arthur Boonstraat",
    "iso:country":"BE",
    "sg:address":"Kanunnik Arthur Boonstraat 39",
    "sg:city":"Willebroek (blaasveld)",
    "sg:classifiers":[
        {
            "category":"Health Services",
            "subcategory":"Nursing And Care Facility",
            "type":"Services"
        }
    ],
    "sg:phone":"+32 3 886 06 09",
    "sg:postcode":"2830",
    "sg:province":"Antwerpen",
    "sg:tags":[
        "home"
    ],
    "wof:name":"Lauwers G",
    "wof:placetype":"venue"
},
  "geometry": {"coordinates":[4.3721261024,51.0582962036],"type":"Point"}
}