{
  "type": "Feature",
  "properties": {
    "iso:country":"BE",
    "sg:address":"Winterdijkweg 20",
    "sg:city":"Bocholt",
    "sg:orig_category":"Boekhouders",
    "sg:phone":"+32 11 44 13 50",
    "sg:postcode":"3950",
    "sg:province":"Limburg",
    "wof:name":"Antoon Cox",
    "wof:placetype":"venue"
},
  "geometry": {"coordinates":[5.504901886,51.1890182495],"type":"Point"}
}