{
  "type": "Feature",
  "properties": {
    "iso:country":"BE",
    "sg:address":"Karel Uytroevenlaan 15b1",
    "sg:city":"Zoersel",
    "sg:orig_category":"Plomberie, chauffage and installations sanitaires",
    "sg:phone":"+32 3 383 44 65",
    "sg:postcode":"2980",
    "sg:province":"Antwerpen",
    "wof:name":"Guido De Nef",
    "wof:placetype":"venue"
},
  "geometry": {"coordinates":[4.6453680992,51.2689704895],"type":"Point"}
}