{
  "type": "Feature",
  "properties": {
    "iso:country":"BE",
    "sg:address":"Fazantendreef 11",
    "sg:city":"Sint-michiels",
    "sg:orig_category":"Paraments",
    "sg:phone":"+32 50 38 05 45",
    "sg:postcode":"8200",
    "sg:province":"West-Vlaanderen",
    "wof:name":"Arte Gross\u00e9 B.v.b.a.",
    "wof:placetype":"venue"
},
  "geometry": {"coordinates":[3.2112550735,51.1885986328],"type":"Point"}
}