{
  "type": "Feature",
  "properties": {
    "iso:country":"BE",
    "sg:address":"Herfststraat 6",
    "sg:city":"Gent",
    "sg:classifiers":[
        {
            "category":"Building & Trades",
            "subcategory":"Construction",
            "type":"Services"
        }
    ],
    "sg:phone":"+32 9 245 38 56",
    "sg:postcode":"9000",
    "sg:province":"Oost-Vlaanderen",
    "sg:tags":[
        "glazier"
    ],
    "wof:name":"Roetynck V Kunstatelier",
    "wof:placetype":"venue"
},
  "geometry": {"coordinates":[3.7278630733,51.0345802307],"type":"Point"}
}