{
  "type": "Feature",
  "properties": {
    "iso:country":"BE",
    "sg:address":"Rue Mitoyenne 33",
    "sg:city":"Baelen/baelen",
    "sg:orig_category":"Entretien and r\u00e9parations de voitures",
    "sg:phone":"+32 87 88 33 02",
    "sg:postcode":"4837",
    "sg:province":"Li\u00e8ge",
    "wof:name":"E.t.c.",
    "wof:placetype":"venue"
},
  "geometry": {"coordinates":[6.0029168129,50.6479301453],"type":"Point"}
}