{
  "type": "Feature",
  "properties": {
    "addr:full":"De Merodelei 43 Turnhout Antwerpen 2300",
    "addr:housenumber":"43",
    "addr:postcode":"2300",
    "addr:street":"De Merodelei",
    "iso:country":"BE",
    "sg:address":"De Merodelei 43",
    "sg:city":"Turnhout",
    "sg:classifiers":[
        {
            "category":"Fast Food",
            "type":"Food & Drink"
        }
    ],
    "sg:phone":"+32 14 41 95 11",
    "sg:postcode":"2300",
    "sg:province":"Antwerpen",
    "sg:tags":[
        "\u00c0",
        "emporter",
        "restaurants"
    ],
    "wof:name":"Aksa",
    "wof:placetype":"venue"
},
  "geometry": {"coordinates":[4.9411878586,51.3219985962],"type":"Point"}
}