{
  "type": "Feature",
  "properties": {
    "addr:full":"Koning Albertlaan 168b1 Sint-agatha-berchem/berchem-sainte-agathe Bruxelles-Capitale 1082",
    "addr:housenumber":"168b1",
    "addr:postcode":"1082",
    "addr:street":"Koning Albertlaan;/",
    "iso:country":"BE",
    "sg:address":"Koning Albertlaan 168b1",
    "sg:city":"Sint-agatha-berchem/berchem-sainte-agathe",
    "sg:orig_category":"Dierenartsen",
    "sg:phone":"+32 2 468 11 30",
    "sg:postcode":"1082",
    "sg:province":"Bruxelles-Capitale",
    "wof:name":"Benoit Van Crombrugge",
    "wof:placetype":"venue"
},
  "geometry": {"coordinates":[4.2872929573,50.8666038513],"type":"Point"}
}