{
  "type": "Feature",
  "properties": {
    "addr:full":"Place Pierre Le Grand 5-6 Spa Li\u00e8ge 4900",
    "addr:housenumber":"5-6",
    "addr:postcode":"4900",
    "addr:street":"Place Pierre Le Grand",
    "iso:country":"BE",
    "sg:address":"Place Pierre Le Grand 5-6",
    "sg:city":"Spa",
    "sg:classifiers":[
        {
            "category":"Food & Beverages",
            "subcategory":"Liquor & Beverages",
            "type":"Retail Goods"
        }
    ],
    "sg:phone":"+32 87 77 04 08",
    "sg:postcode":"4900",
    "sg:province":"Li\u00e8ge",
    "sg:tags":[
        "-",
        "spirit",
        "wine"
    ],
    "wof:name":"Daenen R",
    "wof:placetype":"venue"
},
  "geometry": {"coordinates":[5.8667068481,50.4923324585],"type":"Point"}
}