{
  "type": "Feature",
  "properties": {
    "iso:country":"BE",
    "sg:address":"Bld Industriel 72",
    "sg:city":"Mouscron",
    "sg:orig_category":"Technische studies and ingenieursactiviteiten",
    "sg:phone":"+32 56 84 16 28",
    "sg:postcode":"7700",
    "sg:province":"Hainaut",
    "wof:name":"Bureau D'etudes Flamini Vittorio",
    "wof:placetype":"venue"
},
  "geometry": {"coordinates":[3.2424299717,50.747428894],"type":"Point"}
}