{
  "type": "Feature",
  "properties": {
    "addr:full":"Rue Capitaine Crespel 55 Bruxelles (ixelles) Bruxelles-Capitale 1050",
    "addr:housenumber":"55",
    "addr:postcode":"1050",
    "addr:street":"Rue Capitaine Crespel",
    "iso:country":"BE",
    "sg:address":"Rue Capitaine Crespel 55",
    "sg:city":"Bruxelles (ixelles)",
    "sg:classifiers":[
        {
            "category":"Professional",
            "subcategory":"Engineering",
            "type":"Services"
        }
    ],
    "sg:phone":"+32 2 511 29 35",
    "sg:postcode":"1050",
    "sg:province":"Bruxelles-Capitale",
    "sg:tags":[
        "-"
    ],
    "wof:name":"Burke S",
    "wof:placetype":"venue"
},
  "geometry": {"coordinates":[4.3583159447,50.8344955444],"type":"Point"}
}