{
  "type": "Feature",
  "properties": {
    "addr:full":"Weerstandsplein 0 Diest Vlaams-Brabant 3290",
    "addr:housenumber":"0",
    "addr:postcode":"3290",
    "addr:street":"Weerstandsplein",
    "iso:country":"BE",
    "sg:address":"Weerstandsplein 0",
    "sg:city":"Diest",
    "sg:orig_category":"Algemeen secundair onderwijs",
    "sg:phone":"+32 13 31 13 16",
    "sg:postcode":"3290",
    "sg:province":"Vlaams-Brabant",
    "wof:name":"A.s.o. Kon. Atheneum",
    "wof:placetype":"venue"
},
  "geometry": {"coordinates":[5.0537581444,50.9907493591],"type":"Point"}
}