{
  "type": "Feature",
  "properties": {
    "addr:full":"Nijverheidsstraat 54f Wommelgem Antwerpen 2160",
    "addr:housenumber":"54f",
    "addr:postcode":"2160",
    "addr:street":"Nijverheidsstraat",
    "iso:country":"BE",
    "sg:address":"Nijverheidsstraat 54f",
    "sg:city":"Wommelgem",
    "sg:classifiers":[
        {
            "category":"Banks & Credit Unions",
            "subcategory":"Investment Brokerage",
            "type":"Services"
        }
    ],
    "sg:phone":"+32 3 350 13 66",
    "sg:postcode":"2160",
    "sg:province":"Antwerpen",
    "sg:tags":[
        "distributor",
        "-",
        "distributors",
        "physical"
    ],
    "wof:name":"Systemplus Logistic Service Nv",
    "wof:placetype":"venue"
},
  "geometry": {"coordinates":[4.5078129768,51.2111549377],"type":"Point"}
}