{
  "type": "Feature",
  "properties": {
    "addr:full":"Rue P\u00c8re Nicolas Hardy 1 Thimister-clermont Li\u00e8ge 4890",
    "addr:housenumber":"1",
    "addr:postcode":"4890",
    "addr:street":"Rue Pe\u0300Re Nicolas Hardy",
    "iso:country":"BE",
    "sg:address":"Rue P\u00c8re Nicolas Hardy 1",
    "sg:city":"Thimister-clermont",
    "sg:classifiers":[
        {
            "category":"Cafe",
            "type":"Food & Drink"
        }
    ],
    "sg:phone":"+32 87 44 60 68",
    "sg:postcode":"4890",
    "sg:province":"Li\u00e8ge",
    "sg:tags":[
        "caf\u00e9s"
    ],
    "wof:name":"Louise Sequaris",
    "wof:placetype":"venue"
},
  "geometry": {"coordinates":[5.8943800926,50.6442375183],"type":"Point"}
}