{
  "type": "Feature",
  "properties": {
    "addr:full":"Diksmuidsestraat 5 Ieper West-Vlaanderen 8900",
    "addr:housenumber":"5",
    "addr:postcode":"8900",
    "addr:street":"Diksmuidsestraat",
    "iso:country":"BE",
    "sg:address":"Diksmuidsestraat 5",
    "sg:city":"Ieper",
    "sg:classifiers":[
        {
            "category":"Manufacturing",
            "subcategory":"Textiles",
            "type":"Manufacturing & Wholesale Goods"
        }
    ],
    "sg:phone":"+32 57 20 14 98",
    "sg:postcode":"8900",
    "sg:province":"West-Vlaanderen",
    "sg:tags":[
        "retail",
        "-"
    ],
    "wof:name":"Hollebeke B",
    "wof:placetype":"venue"
},
  "geometry": {"coordinates":[2.8865609169,50.8518486023],"type":"Point"}
}