{
  "type": "Feature",
  "properties": {
    "iso:country":"BE",
    "sg:address":"Ruggeveldlaan 1",
    "sg:city":"Deurne",
    "sg:orig_category":"Entretien and r\u00e9parations de voitures",
    "sg:phone":"+32 3 366 20 53",
    "sg:postcode":"2100",
    "sg:province":"Antwerpen",
    "wof:name":"Marco Bvba",
    "wof:placetype":"venue"
},
  "geometry": {"coordinates":[4.4810757637,51.2142372131],"type":"Point"}
}