{
  "type": "Feature",
  "properties": {
    "iso:country":"BE",
    "sg:address":"Hameau De La Houz\u00e9e",
    "sg:city":"Thuin (thuillies)",
    "sg:classifiers":[
        {
            "category":"Sports & Exercise",
            "subcategory":"Stables",
            "type":"Entertainment"
        }
    ],
    "sg:phone":"+32 71 53 31 63",
    "sg:postcode":"6536",
    "sg:province":"Hainaut",
    "sg:tags":[
        "riding",
        "school"
    ],
    "wof:name":"Man\u00e8ge De La Houz\u00e9e",
    "wof:placetype":"venue"
},
  "geometry": {"coordinates":[4.3362932205,50.3115577698],"type":"Point"}
}