{
  "type": "Feature",
  "properties": {
    "iso:country":"BE",
    "sg:address":"Desherenborn 4",
    "sg:city":"Bntgenbach/bntgenbach",
    "sg:orig_category":"Eleveurs de bovins",
    "sg:phone":"+32 80 44 51 27",
    "sg:postcode":"4750",
    "sg:province":"Li\u00e8ge",
    "wof:name":"Bernd Heinen",
    "wof:placetype":"venue"
},
  "geometry": {"coordinates":[6.2186841965,50.4545898438],"type":"Point"}
}