{
  "type": "Feature",
  "properties": {
    "iso:country":"BE",
    "sg:address":"Wolfshaegen 122",
    "sg:city":"Huldenberg",
    "sg:orig_category":"Peinture",
    "sg:phone":"+32 16 47 79 16",
    "sg:postcode":"3040",
    "sg:province":"Vlaams-Brabant",
    "wof:name":"Coopmans",
    "wof:placetype":"venue"
},
  "geometry": {"coordinates":[4.6260480881,50.7922592163],"type":"Point"}
}