{
  "type": "Feature",
  "properties": {
    "iso:country":"BE",
    "sg:address":"Voshol 6",
    "sg:city":"Lokeren",
    "sg:classifiers":[
        {
            "category":"Retail",
            "subcategory":"Repair Shop",
            "type":"Services"
        }
    ],
    "sg:phone":"+32 9 349 46 23",
    "sg:postcode":"9160",
    "sg:province":"Oost-Vlaanderen",
    "sg:tags":[
        "mainten",
        "-",
        "parquet"
    ],
    "wof:name":"Stals & Zoon Nv",
    "wof:placetype":"venue"
},
  "geometry": {"coordinates":[4.0131421089,51.0871238708],"type":"Point"}
}