{
  "type": "Feature",
  "properties": {
    "addr:full":"Rue Des Zolos 9 Fosses-la-ville Namur 5070",
    "addr:housenumber":"9",
    "addr:postcode":"5070",
    "addr:street":"Rue Des Zolos",
    "iso:country":"BE",
    "sg:address":"Rue Des Zolos 9",
    "sg:city":"Fosses-la-ville",
    "sg:orig_category":"Herstellingen and onderhoud van auto's",
    "sg:phone":"+32 71 71 23 91",
    "sg:postcode":"5070",
    "sg:province":"Namur",
    "wof:name":"Alain Mingeot",
    "wof:placetype":"venue"
},
  "geometry": {"coordinates":[4.699133873,50.396900177],"type":"Point"}
}