{
  "type": "Feature",
  "properties": {
    "addr:full":"Avenue Des Arts 2 Bruxelles (saint-josse-ten-noode) Bruxelles-Capitale 1210",
    "addr:housenumber":"2",
    "addr:postcode":"1210",
    "addr:street":"Avenue Des Arts",
    "iso:country":"BE",
    "sg:address":"Avenue Des Arts 2",
    "sg:city":"Bruxelles (saint-josse-ten-noode)",
    "sg:classifiers":[
        {
            "category":"Cafe",
            "type":"Food & Drink"
        }
    ],
    "sg:phone":"+32 2 218 10 96",
    "sg:postcode":"1210",
    "sg:province":"Bruxelles-Capitale",
    "sg:tags":[
        "snack-bars"
    ],
    "wof:name":"Lunch Time",
    "wof:placetype":"venue"
},
  "geometry": {"coordinates":[4.3695549965,50.8488845825],"type":"Point"}
}