{
  "type": "Feature",
  "properties": {
    "addr:full":"Rue De La Sabli\u00e8re 42 Villers-le-bouillet (fize-fontaine) Li\u00e8ge 4530",
    "addr:housenumber":"42",
    "addr:postcode":"4530",
    "addr:street":"Rue De La Sablie\u0300Re",
    "iso:country":"BE",
    "sg:address":"Rue De La Sabli\u00e8re 42",
    "sg:city":"Villers-le-bouillet (fize-fontaine)",
    "sg:classifiers":[
        {
            "category":"Home & Garden",
            "subcategory":"Building Materials",
            "type":"Retail Goods"
        }
    ],
    "sg:phone":"+32 4 259 42 03",
    "sg:postcode":"4530",
    "sg:province":"Li\u00e8ge",
    "sg:tags":[
        "granite",
        "stone",
        "natural",
        "marble"
    ],
    "wof:name":"Chevremont Freres Sprl",
    "wof:placetype":"venue"
},
  "geometry": {"coordinates":[5.279009819,50.5768203735],"type":"Point"}
}