{
  "type": "Feature",
  "properties": {
    "addr:full":"Beukendreef 3 Sint-katelijne-waver Antwerpen 2860",
    "addr:housenumber":"3",
    "addr:postcode":"2860",
    "addr:street":"Beukendreef",
    "iso:country":"BE",
    "sg:address":"Beukendreef 3",
    "sg:city":"Sint-katelijne-waver",
    "sg:orig_category":"Meubles D\u00e9taillants, Am\u00e9nagement de B\u00e2timents et de Cuisines",
    "sg:phone":"+32 15 31 36 13",
    "sg:postcode":"2860",
    "sg:province":"Antwerpen",
    "wof:name":"Van Beersel",
    "wof:placetype":"venue"
},
  "geometry": {"coordinates":[4.4769949913,51.0719680786],"type":"Point"}
}