{
  "type": "Feature",
  "properties": {
    "iso:country":"BE",
    "sg:address":"Heinrich-bischoff-strasse 26",
    "sg:city":"Raeren (hauset)",
    "sg:classifiers":[
        {
            "category":"Real Estate",
            "subcategory":"Real Estate Services",
            "type":"Services"
        }
    ],
    "sg:phone":"+32 87 63 06 31",
    "sg:postcode":"4730",
    "sg:province":"Li\u00e8ge",
    "wof:name":"H.b.s. Ag",
    "wof:placetype":"venue"
},
  "geometry": {"coordinates":[6.1169581413,50.6716804504],"type":"Point"}
}