{
  "type": "Feature",
  "properties": {
    "iso:country":"BE",
    "sg:address":"Rue Sainte-marguerite 106",
    "sg:city":"Li\u00e8ge 1",
    "sg:classifiers":[
        {
            "category":"Shopping",
            "subcategory":"Jewelry",
            "type":"Retail Goods"
        }
    ],
    "sg:phone":"+32 4 226 32 73",
    "sg:postcode":"4000",
    "sg:province":"Li\u00e8ge",
    "sg:tags":[
        "jeweller",
        "-"
    ],
    "wof:name":"Tortolani A",
    "wof:placetype":"venue"
},
  "geometry": {"coordinates":[5.5600581169,50.6457824707],"type":"Point"}
}