{
  "type": "Feature",
  "properties": {
    "addr:full":"Rue Joseph Romainville 1 Wanze Li\u00e8ge 4520",
    "addr:housenumber":"1",
    "addr:postcode":"4520",
    "addr:street":"Rue Joseph Romainville",
    "iso:country":"BE",
    "sg:address":"Rue Joseph Romainville 1",
    "sg:city":"Wanze",
    "sg:orig_category":"Offices du tourisme",
    "sg:phone":"+32 85 23 25 53",
    "sg:postcode":"4520",
    "sg:province":"Li\u00e8ge",
    "wof:name":"Office Du Tourisme",
    "wof:placetype":"venue"
},
  "geometry": {"coordinates":[5.1921319962,50.521736145],"type":"Point"}
}