{
  "type": "Feature",
  "properties": {
    "iso:country":"BE",
    "sg:address":"Avenue Eudore Pirmez 38",
    "sg:city":"Bruxelles (etterbeek)",
    "sg:classifiers":[
        {
            "category":"Food & Beverages",
            "subcategory":"Liquor & Beverages",
            "type":"Retail Goods"
        }
    ],
    "sg:phone":"+32 2 647 96 37",
    "sg:postcode":"1040",
    "sg:province":"Bruxelles-Capitale",
    "sg:tags":[
        "-",
        "spirit",
        "wine"
    ],
    "wof:name":"Cavin (le)",
    "wof:placetype":"venue"
},
  "geometry": {"coordinates":[4.3880028725,50.830165863],"type":"Point"}
}