{
  "type": "Feature",
  "properties": {
    "iso:country":"BE",
    "sg:address":"De Burburestraat 29 Box 11",
    "sg:city":"Antwerpen",
    "sg:classifiers":[
        {
            "category":"Professional",
            "subcategory":"Accounting & Tax Preparation",
            "type":"Services"
        }
    ],
    "sg:phone":"+32 3 244 01 55",
    "sg:postcode":"2000",
    "sg:province":"Antwerpen",
    "sg:tags":[
        "bookkeeper"
    ],
    "wof:name":"De Clercq S",
    "wof:placetype":"venue"
},
  "geometry": {"coordinates":[4.3921999931,51.208732605],"type":"Point"}
}