{
  "type": "Feature",
  "properties": {
    "iso:country":"BE",
    "sg:address":"Gasthuisstraat 44",
    "sg:city":"Temse",
    "sg:classifiers":[
        {
            "category":"Shopping",
            "subcategory":"Baby Store",
            "type":"Retail Goods"
        }
    ],
    "sg:phone":"+32 3 771 97 76",
    "sg:postcode":"9140",
    "sg:province":"Oost-Vlaanderen",
    "sg:tags":[
        "-",
        "accessory"
    ],
    "wof:name":"Tiende Maand (de)",
    "wof:placetype":"venue"
},
  "geometry": {"coordinates":[4.2129759789,51.1292648315],"type":"Point"}
}