{
  "type": "Feature",
  "properties": {
    "addr:full":"Rue De La Gal\u00c8ne 8 Plombieres/plombieres Li\u00e8ge 4850",
    "addr:housenumber":"8",
    "addr:postcode":"4850",
    "addr:street":"Rue De La Gale\u0300Ne",
    "iso:country":"BE",
    "sg:address":"Rue De La Gal\u00c8ne 8",
    "sg:city":"Plombieres/plombieres",
    "sg:orig_category":"Pain, p\u00e2tisseries and confiseries",
    "sg:phone":"+32 87 78 47 03",
    "sg:postcode":"4850",
    "sg:province":"Li\u00e8ge",
    "wof:name":"Nikolaus Niessen",
    "wof:placetype":"venue"
},
  "geometry": {"coordinates":[5.9626002312,50.7068138123],"type":"Point"}
}