{
  "type": "Feature",
  "properties": {
    "iso:country":"BE",
    "sg:address":"Rue Des Ecoles 5",
    "sg:city":"Comblain-au-pont",
    "sg:classifiers":[
        {
            "category":"Cafe",
            "type":"Food & Drink"
        }
    ],
    "sg:phone":"+32 4 380 46 00",
    "sg:postcode":"4171",
    "sg:province":"Li\u00e8ge",
    "sg:tags":[
        "caf\u00e9s"
    ],
    "wof:name":"Cercle St.paul",
    "wof:placetype":"venue"
},
  "geometry": {"coordinates":[5.5794038773,50.508846283],"type":"Point"}
}