{
  "type": "Feature",
  "properties": {
    "iso:country":"BE",
    "sg:address":"Nieuwstraat 120 Box 11",
    "sg:city":"Asse",
    "sg:classifiers":[
        {
            "category":"Building & Trades",
            "subcategory":"Construction",
            "type":"Services"
        }
    ],
    "sg:phone":"+32 2 453 11 01",
    "sg:postcode":"1730",
    "sg:province":"Vlaams-Brabant",
    "sg:tags":[
        "insulation",
        "thermical",
        "work",
        "acoustical"
    ],
    "wof:name":"Isolca Nv",
    "wof:placetype":"venue"
},
  "geometry": {"coordinates":[4.1917600632,50.9076843262],"type":"Point"}
}