{
  "type": "Feature",
  "properties": {
    "addr:full":"Havermarkt 24 Hasselt Limburg 3500",
    "addr:housenumber":"24",
    "addr:postcode":"3500",
    "addr:street":"Havermarkt",
    "iso:country":"BE",
    "sg:address":"Havermarkt 24",
    "sg:city":"Hasselt",
    "sg:classifiers":[
        {
            "category":"Banks & Credit Unions",
            "subcategory":"Bank",
            "type":"Services"
        }
    ],
    "sg:phone":"+32 11 22 40 24",
    "sg:postcode":"3500",
    "sg:province":"Limburg",
    "wof:name":"Famibank",
    "wof:placetype":"venue"
},
  "geometry": {"coordinates":[5.334897995,50.9291267395],"type":"Point"}
}