{
  "type": "Feature",
  "properties": {
    "addr:full":"Graaf Jansdijk 4 De Haan (wenduine) West-Vlaanderen 8420",
    "addr:housenumber":"4",
    "addr:postcode":"8420",
    "addr:street":"Graaf Jansdijk",
    "iso:country":"BE",
    "sg:address":"Graaf Jansdijk 4",
    "sg:city":"De Haan (wenduine)",
    "sg:classifiers":[
        {
            "category":"Tea Room",
            "subcategory":"None",
            "type":"Food & Drink"
        }
    ],
    "sg:phone":"+32 50 41 94 59",
    "sg:postcode":"8420",
    "sg:province":"West-Vlaanderen",
    "wof:name":"Moustache",
    "wof:placetype":"venue"
},
  "geometry": {"coordinates":[3.0784590244,51.3008766174],"type":"Point"}
}