{
  "type": "Feature",
  "properties": {
    "iso:country":"BE",
    "sg:address":"Heuveneindeweg 123",
    "sg:city":"Zonhoven",
    "sg:orig_category":"Voertuigen",
    "sg:phone":"+32 11 81 32 77",
    "sg:postcode":"3520",
    "sg:province":"Limburg",
    "wof:name":"Theophile Poecks",
    "wof:placetype":"venue"
},
  "geometry": {"coordinates":[5.361987114,50.9723396301],"type":"Point"}
}