{
  "type": "Feature",
  "properties": {
    "iso:country":"BE",
    "sg:address":"Chauss\u00c9e De Namur 263",
    "sg:city":"Wavre",
    "sg:orig_category":"Entretien and r\u00e9parations de voitures. V\u00e9hicules automobiles",
    "sg:phone":"+32 10 48 33 80",
    "sg:postcode":"1300",
    "sg:province":"Brabant Wallon",
    "wof:name":"Garage Bustin",
    "wof:placetype":"venue"
},
  "geometry": {"coordinates":[4.615544796,50.6910743713],"type":"Point"}
}