{
  "type": "Feature",
  "properties": {
    "iso:country":"BE",
    "sg:address":"Vinkeniersweg 6",
    "sg:city":"Borsbeek",
    "sg:classifiers":[
        {
            "category":"Transit Center",
            "subcategory":"Freight",
            "type":"Transportation"
        }
    ],
    "sg:phone":"+32 3 827 40 46",
    "sg:postcode":"2150",
    "sg:province":"Antwerpen",
    "sg:tags":[
        "import",
        "export",
        "-"
    ],
    "wof:name":"Elfe Bvba",
    "wof:placetype":"venue"
},
  "geometry": {"coordinates":[4.4752750397,51.1966018677],"type":"Point"}
}