{
  "type": "Feature",
  "properties": {
    "addr:full":"Tolhuislaan 121 Gent Oost-Vlaanderen 9000",
    "addr:housenumber":"121",
    "addr:postcode":"9000",
    "addr:street":"Tolhuislaan;Oost-Vlaanderen",
    "iso:country":"BE",
    "sg:address":"Tolhuislaan 121",
    "sg:city":"Gent",
    "sg:classifiers":[
        {
            "category":"Home & Garden",
            "subcategory":"Home Furnishings",
            "type":"Retail Goods"
        }
    ],
    "sg:phone":"+32 9 224 48 13",
    "sg:postcode":"9000",
    "sg:province":"Oost-Vlaanderen",
    "sg:tags":[
        "-",
        "bed",
        "mattress"
    ],
    "wof:name":"Matrassengigant",
    "wof:placetype":"venue"
},
  "geometry": {"coordinates":[3.726416111,51.0648193359],"type":"Point"}
}