{
  "type": "Feature",
  "properties": {
    "iso:country":"BE",
    "sg:address":"Eindekens 15",
    "sg:city":"Geel",
    "sg:orig_category":"Rundveehouders",
    "sg:phone":"+32 14 58 25 63",
    "sg:postcode":"2440",
    "sg:province":"Antwerpen",
    "wof:name":"Victor Vanbosch",
    "wof:placetype":"venue"
},
  "geometry": {"coordinates":[4.9544858932,51.1758041382],"type":"Point"}
}