{
  "type": "Feature",
  "properties": {
    "iso:country":"BE",
    "sg:address":"Komenstraat 29",
    "sg:city":"Wervik",
    "sg:classifiers":[
        {
            "category":"Personal",
            "subcategory":"Shoe Repair & Shine",
            "type":"Services"
        }
    ],
    "sg:phone":"+32 56 45 75 69",
    "sg:postcode":"8940",
    "sg:province":"West-Vlaanderen",
    "sg:tags":[
        "shoemaker"
    ],
    "wof:name":"Mister Shoe Service Bvba",
    "wof:placetype":"venue"
},
  "geometry": {"coordinates":[3.036632061,50.7806358337],"type":"Point"}
}