{
  "type": "Feature",
  "properties": {
    "addr:full":"Zoutstraat 40 Sint-truiden Limburg 3800",
    "addr:housenumber":"40",
    "addr:postcode":"3800",
    "addr:street":"Zoutstraat",
    "iso:country":"BE",
    "sg:address":"Zoutstraat 40",
    "sg:city":"Sint-truiden",
    "sg:orig_category":"Kapsalons",
    "sg:phone":"+32 11 68 44 61",
    "sg:postcode":"3800",
    "sg:province":"Limburg",
    "wof:name":"Coiffure Henri",
    "wof:placetype":"venue"
},
  "geometry": {"coordinates":[5.1835618019,50.8165969849],"type":"Point"}
}