{
  "type": "Feature",
  "properties": {
    "iso:country":"BE",
    "sg:address":"Hoevenstraat 44",
    "sg:city":"Wommelgem",
    "sg:classifiers":[
        {
            "category":"Home & Garden",
            "subcategory":"Home Furnishings",
            "type":"Retail Goods"
        }
    ],
    "sg:phone":"+32 3 354 08 23",
    "sg:postcode":"2160",
    "sg:province":"Antwerpen",
    "sg:tags":[
        "decoration"
    ],
    "wof:name":"Elgego Bvba",
    "wof:placetype":"venue"
},
  "geometry": {"coordinates":[4.5169219971,51.2044944763],"type":"Point"}
}