{
  "type": "Feature",
  "properties": {
    "iso:country":"BE",
    "sg:address":"Marktstr 28",
    "sg:city":"Oudenburg",
    "sg:classifiers":[
        {
            "category":"Banks & Credit Unions",
            "subcategory":"Bank",
            "type":"Services"
        }
    ],
    "sg:phone":"+32 59 26 70 24",
    "sg:postcode":"8230",
    "wof:name":"Aslk-cger Bank",
    "wof:placetype":"venue"
},
  "geometry": {"coordinates":[6.0402002335,49.6286888123],"type":"Point"}
}