{
  "type": "Feature",
  "properties": {
    "iso:country":"BE",
    "sg:address":"Place Du March\u00c9 Aux Tolles 2",
    "sg:city":"Ath",
    "sg:orig_category":"Opticiens",
    "sg:phone":"+32 68 28 42 30",
    "sg:postcode":"7800",
    "sg:province":"Hainaut",
    "wof:name":"Harksen J-opticien Krys",
    "wof:placetype":"venue"
},
  "geometry": {"coordinates":[3.7762498856,50.6313400269],"type":"Point"}
}