{
  "type": "Feature",
  "properties": {
    "iso:country":"BE",
    "sg:address":"Katelijnestraat 121",
    "sg:city":"Brugge",
    "sg:classifiers":[
        {
            "category":"Professional",
            "subcategory":"Advertising",
            "type":"Services"
        }
    ],
    "sg:phone":"+32 50 33 59 61",
    "sg:postcode":"8000",
    "sg:province":"West-Vlaanderen",
    "sg:tags":[
        "item",
        "-",
        "business",
        "gift",
        "promotional"
    ],
    "wof:name":"Toya Trading",
    "wof:placetype":"venue"
},
  "geometry": {"coordinates":[3.2283260822,51.2007865906],"type":"Point"}
}