{
  "type": "Feature",
  "properties": {
    "addr:full":"Rue De Marais 56 B Brussels Bruxelles-Capitale 1000",
    "addr:housenumber":"56 b",
    "addr:postcode":"1000",
    "addr:street":"Rue De Marais",
    "iso:country":"BE",
    "sg:address":"Rue De Marais 56 B",
    "sg:city":"Brussels",
    "sg:classifiers":[
        {
            "category":"Banks & Credit Unions",
            "subcategory":"Bank",
            "type":"Services"
        }
    ],
    "sg:postcode":"1000",
    "sg:province":"Bruxelles-Capitale",
    "wof:name":"Acii",
    "wof:placetype":"venue"
},
  "geometry": {"coordinates":[4.359085083,50.8517951965],"type":"Point"}
}