{
  "type": "Feature",
  "properties": {
    "addr:full":"Meestraat 2 Brugge West-Vlaanderen 8000",
    "addr:housenumber":"2",
    "addr:postcode":"8000",
    "addr:street":"Meestraat",
    "iso:country":"BE",
    "sg:address":"Meestraat 2",
    "sg:city":"Brugge",
    "sg:orig_category":"Notarissen",
    "sg:phone":"+32 50 33 96 86",
    "sg:postcode":"8000",
    "sg:province":"West-Vlaanderen",
    "wof:name":"Fran\u00c7oise Proot",
    "wof:placetype":"venue"
},
  "geometry": {"coordinates":[3.2292881012,51.2086105347],"type":"Point"}
}