{
  "type": "Feature",
  "properties": {
    "addr:full":"Massemsesteenweg 4 Wetteren Oost-Vlaanderen 9230",
    "addr:housenumber":"4",
    "addr:postcode":"9230",
    "addr:street":"Massemsesteenweg",
    "iso:country":"BE",
    "sg:address":"Massemsesteenweg 4",
    "sg:city":"Wetteren",
    "sg:classifiers":[
        {
            "category":"Restaurant",
            "type":"Food & Drink"
        }
    ],
    "sg:phone":"+32 9 366 49 48",
    "sg:postcode":"9230",
    "sg:province":"Oost-Vlaanderen",
    "sg:tags":[
        "organisation",
        "de",
        "f\u00eates",
        "catering"
    ],
    "wof:name":"Restaurant 't Saffraantje",
    "wof:placetype":"venue"
},
  "geometry": {"coordinates":[3.8814370632,50.9985580444],"type":"Point"}
}