{
  "type": "Feature",
  "properties": {
    "iso:country":"BE",
    "sg:address":"Vieux Remparts 20",
    "sg:city":"Hannut",
    "sg:classifiers":[
        {
            "category":"Health Services",
            "subcategory":"Health Practitioner",
            "type":"Services"
        }
    ],
    "sg:phone":"+32 19 51 33 07",
    "sg:postcode":"4280",
    "sg:province":"Li\u00e8ge",
    "sg:tags":[
        "physiotherapist"
    ],
    "wof:name":"Delvaux G",
    "wof:placetype":"venue"
},
  "geometry": {"coordinates":[5.0762147903,50.6733131409],"type":"Point"}
}