{
  "type": "Feature",
  "properties": {
    "addr:full":"Sint-clarastraat 43 Brugge West-Vlaanderen 8000",
    "addr:housenumber":"43",
    "addr:postcode":"8000",
    "addr:street":"Sint-Clarastraat",
    "iso:country":"BE",
    "sg:address":"Sint-clarastraat 43",
    "sg:city":"Brugge",
    "sg:classifiers":[
        {
            "category":"Cafe",
            "type":"Food & Drink"
        }
    ],
    "sg:phone":"+32 50 34 50 34",
    "sg:postcode":"8000",
    "sg:province":"West-Vlaanderen",
    "sg:tags":[
        "caf\u00e9s"
    ],
    "wof:name":"Caf\u00c9 Barabass",
    "wof:placetype":"venue"
},
  "geometry": {"coordinates":[3.2225348949,51.2151451111],"type":"Point"}
}