{
  "type": "Feature",
  "properties": {
    "iso:country":"BE",
    "sg:address":"Route De L'etat 315",
    "sg:city":"Lasne (lasne-chapelle-saint-lambert)",
    "sg:classifiers":[
        {
            "category":"Health Services",
            "subcategory":"Health Practitioner",
            "type":"Services"
        }
    ],
    "sg:phone":"+32 2 633 30 87",
    "sg:postcode":"1380",
    "sg:province":"Brabant Wallon",
    "sg:tags":[
        "therapist",
        "speech"
    ],
    "wof:name":"Jacques P",
    "wof:placetype":"venue"
},
  "geometry": {"coordinates":[4.4620919228,50.6602020264],"type":"Point"}
}