{
  "type": "Feature",
  "properties": {
    "iso:country":"BE",
    "sg:address":"Nati\u00ebnlaan 263",
    "sg:city":"Knokke-heist (knokke)",
    "sg:classifiers":[
        {
            "category":"Parking",
            "subcategory":"Lot",
            "type":"Transportation"
        }
    ],
    "sg:phone":"+32 50 60 17 79",
    "sg:postcode":"8300",
    "sg:province":"West-Vlaanderen",
    "sg:tags":[
        "parking-places",
        "laying-out"
    ],
    "wof:name":"Dhondt A En Zoon",
    "wof:placetype":"venue"
},
  "geometry": {"coordinates":[3.2890501022,51.3361816406],"type":"Point"}
}