{
  "type": "Feature",
  "properties": {
    "addr:full":"Kortrijksesteenweg 94 Sint-martens-latem Oost-Vlaanderen 9830",
    "addr:housenumber":"94",
    "addr:postcode":"9830",
    "addr:street":"Kortrijksesteenweg",
    "iso:country":"BE",
    "sg:address":"Kortrijksesteenweg 94",
    "sg:city":"Sint-martens-latem",
    "sg:classifiers":[
        {
            "category":"Autos & Motor Vehicles",
            "subcategory":"Automobile Sales",
            "type":"Retail Goods"
        }
    ],
    "sg:postcode":"9830",
    "sg:province":"Oost-Vlaanderen",
    "sg:tags":[
        "motorhomes",
        "accessory"
    ],
    "wof:name":"Schmidmotorhomes hymer",
    "wof:placetype":"venue"
},
  "geometry": {"coordinates":[3.6432418823,51.0125350952],"type":"Point"}
}