{
  "type": "Feature",
  "properties": {
    "addr:full":"Achttien Augustuslaan 153 Wetteren Oost-Vlaanderen 9230",
    "addr:housenumber":"153",
    "addr:postcode":"9230",
    "addr:street":"Augustuslaan",
    "iso:country":"BE",
    "sg:address":"Achttien Augustuslaan 153",
    "sg:city":"Wetteren",
    "sg:orig_category":"Avocats and conseillers juridiques",
    "sg:phone":"+32 9 369 41 89",
    "sg:postcode":"9230",
    "sg:province":"Oost-Vlaanderen",
    "wof:name":"Boudewijn Bracke",
    "wof:placetype":"venue"
},
  "geometry": {"coordinates":[3.8984239101,51.0039405823],"type":"Point"}
}