{
  "type": "Feature",
  "properties": {
    "iso:country":"BE",
    "sg:address":"Rue Des Bruy\u00e8res 28",
    "sg:city":"Ham-sur-heure-nalinnes (jamioulx)",
    "sg:classifiers":[
        {
            "category":"Professional",
            "subcategory":"Accounting & Tax Preparation",
            "type":"Services"
        }
    ],
    "sg:phone":"+32 71 21 88 15",
    "sg:postcode":"6120",
    "sg:province":"Hainaut",
    "sg:tags":[
        "bookkeeper"
    ],
    "wof:name":"Chapelle A",
    "wof:placetype":"venue"
},
  "geometry": {"coordinates":[4.4176859856,50.3570289612],"type":"Point"}
}