{
  "type": "Feature",
  "properties": {
    "addr:full":"Rue Neuve 24 Charleroi Hainaut 6000",
    "addr:housenumber":"24",
    "addr:postcode":"6000",
    "addr:street":"Rue Neuve;Hainaut",
    "iso:country":"BE",
    "sg:address":"Rue Neuve 24",
    "sg:city":"Charleroi",
    "sg:orig_category":"Slagers",
    "sg:phone":"+32 71 32 47 93",
    "sg:postcode":"6000",
    "sg:province":"Hainaut",
    "wof:name":"Supers Grandes Boucheries",
    "wof:placetype":"venue"
},
  "geometry": {"coordinates":[4.4444618225,50.4128761292],"type":"Point"}
}