{
  "type": "Feature",
  "properties": {
    "iso:country":"BE",
    "sg:address":"Chauss\u00e9e De Marche 7",
    "sg:city":"Neupr\u00e9 (neuville-en-condroz)",
    "sg:classifiers":[
        {
            "category":"Farming",
            "subcategory":"Farm & Veterinary Services",
            "type":"Manufacturing & Wholesale Goods"
        }
    ],
    "sg:phone":"+32 4 371 49 76",
    "sg:postcode":"4121",
    "sg:province":"Li\u00e8ge",
    "sg:tags":[
        "agricultural",
        "contractor"
    ],
    "wof:name":"Etienne G & V",
    "wof:placetype":"venue"
},
  "geometry": {"coordinates":[5.4530000687,50.5570983887],"type":"Point"}
}