{
  "type": "Feature",
  "properties": {
    "addr:full":"Parklaan 29b1 Aalst Oost-Vlaanderen 9300",
    "addr:housenumber":"29b1",
    "addr:postcode":"9300",
    "addr:street":"Parklaan",
    "iso:country":"BE",
    "sg:address":"Parklaan 29b1",
    "sg:city":"Aalst",
    "sg:orig_category":"Mat\u00e9riaux de construction Gr",
    "sg:phone":"+32 53 72 96 72",
    "sg:postcode":"9300",
    "sg:province":"Oost-Vlaanderen",
    "wof:name":"Lafarge Braas Roof Prod.",
    "wof:placetype":"venue"
},
  "geometry": {"coordinates":[4.0444078445,50.9318084717],"type":"Point"}
}