{
  "type": "Feature",
  "properties": {
    "addr:full":"Rue Eug\u00e8ne Vandenhoff 62 Li\u00e8ge 1 (grivegn\u00e9e) Li\u00e8ge 4030",
    "addr:housenumber":"62;1",
    "addr:postcode":"4030",
    "addr:street":"Rue Euge\u0300Ne Vandenhoff",
    "iso:country":"BE",
    "sg:address":"Rue Eug\u00e8ne Vandenhoff 62",
    "sg:city":"Li\u00e8ge 1 (grivegn\u00e9e)",
    "sg:classifiers":[
        {
            "category":"Personal",
            "subcategory":"Nail Salon",
            "type":"Services"
        }
    ],
    "sg:phone":"+32 4 365 71 13",
    "sg:postcode":"4030",
    "sg:province":"Li\u00e8ge",
    "sg:tags":[
        "pedicure"
    ],
    "wof:name":"Honen B",
    "wof:placetype":"venue"
},
  "geometry": {"coordinates":[5.6021361351,50.6297607422],"type":"Point"}
}