{
  "type": "Feature",
  "properties": {
    "addr:full":"Molenweg 30 Sint-genesius-rode Vlaams-Brabant 1640",
    "addr:housenumber":"30",
    "addr:postcode":"1640",
    "addr:street":"Molenweg",
    "iso:country":"BE",
    "sg:address":"Molenweg 30",
    "sg:city":"Sint-genesius-rode",
    "sg:orig_category":"Herstelling aan huis van huishoudartikelen Installatie van houten of kunststof schrijnwerk Loodgiete",
    "sg:phone":"+32 2 381 05 61",
    "sg:postcode":"1640",
    "sg:province":"Vlaams-Brabant",
    "wof:name":"Axa-therm",
    "wof:placetype":"venue"
},
  "geometry": {"coordinates":[4.3654580116,50.7368583679],"type":"Point"}
}