{
  "type": "Feature",
  "properties": {
    "iso:country":"BE",
    "sg:address":"Brugsken 144",
    "sg:city":"Sint-niklaas",
    "sg:orig_category":"HERSTELLING ELEKTRISCHE HUISHOUDAPPARATEN Huishoudapparaten, televisies and radio's",
    "sg:phone":"+32 3 776 16 82",
    "sg:postcode":"9100",
    "sg:province":"Oost-Vlaanderen",
    "wof:name":"Brugsken Tv & Video Labo",
    "wof:placetype":"venue"
},
  "geometry": {"coordinates":[4.1592931747,51.1587295532],"type":"Point"}
}