{
  "type": "Feature",
  "properties": {
    "iso:country":"BE",
    "sg:address":"Mulderslaan 123",
    "sg:city":"Oudergem/auderghem",
    "sg:orig_category":"Boekhandels",
    "sg:phone":"+32 2 672 90 90",
    "sg:postcode":"1160",
    "sg:province":"Bruxelles-Capitale",
    "wof:name":"O.c.s. Bookshop",
    "wof:placetype":"venue"
},
  "geometry": {"coordinates":[4.4111509323,50.8156700134],"type":"Point"}
}