{
  "type": "Feature",
  "properties": {
    "addr:full":"Andreas Vesaliuslaan 22 Hasselt Limburg 3500",
    "addr:housenumber":"22",
    "addr:postcode":"3500",
    "addr:street":"Andreas Vesaliuslaan",
    "iso:country":"BE",
    "sg:address":"Andreas Vesaliuslaan 22",
    "sg:city":"Hasselt",
    "sg:orig_category":"Diverse grafische activiteiten",
    "sg:phone":"+32 11 22 51 38",
    "sg:postcode":"3500",
    "sg:province":"Limburg",
    "wof:name":"Bureau Themacom",
    "wof:placetype":"venue"
},
  "geometry": {"coordinates":[5.3537549973,50.9249305725],"type":"Point"}
}