{
  "type": "Feature",
  "properties": {
    "addr:full":"Rue De La Station 24 Sambreville (tamines) Namur 5060",
    "addr:housenumber":"24",
    "addr:postcode":"5060",
    "addr:street":"Rue De La Station",
    "iso:country":"BE",
    "sg:address":"Rue De La Station 24",
    "sg:city":"Sambreville (tamines)",
    "sg:classifiers":[
        {
            "category":"Shopping",
            "subcategory":"Shoes",
            "type":"Retail Goods"
        }
    ],
    "sg:phone":"+32 71 77 14 78",
    "sg:postcode":"5060",
    "sg:province":"Namur",
    "sg:tags":[
        "slipper",
        "-"
    ],
    "wof:name":"Enfants De Marine (les)",
    "wof:placetype":"venue"
},
  "geometry": {"coordinates":[4.6110181808,50.4319992065],"type":"Point"}
}