{
  "type": "Feature",
  "properties": {
    "addr:full":"Rue Taverne De Maire Tournai Hainaut 7503",
    "addr:postcode":"7503",
    "addr:street":"Rue Taverne De Maire;Hainaut",
    "iso:country":"BE",
    "sg:address":"Rue Taverne De Maire",
    "sg:city":"Tournai",
    "sg:orig_category":"Chaussures",
    "sg:phone":"+32 69 21 37 03",
    "sg:postcode":"7503",
    "sg:province":"Hainaut",
    "wof:name":"Shoe Discount",
    "wof:placetype":"venue"
},
  "geometry": {"coordinates":[3.3686420918,50.6275558472],"type":"Point"}
}