{
  "type": "Feature",
  "properties": {
    "iso:country":"BE",
    "sg:address":"Abdijhoek 1",
    "sg:city":"Zedelgem",
    "sg:classifiers":[
        {
            "category":"Manufacturing",
            "subcategory":"Motor Vehicles & Parts",
            "type":"Manufacturing & Wholesale Goods"
        }
    ],
    "sg:phone":"+32 50 38 37 79",
    "sg:postcode":"8210",
    "sg:province":"West-Vlaanderen",
    "sg:tags":[
        "body",
        "automobile",
        "construction",
        "-"
    ],
    "wof:name":"Van Oost D",
    "wof:placetype":"venue"
},
  "geometry": {"coordinates":[3.1533660889,51.1501655579],"type":"Point"}
}