{
  "type": "Feature",
  "properties": {
    "addr:full":"Rue De L'eau 31 Bruxelles (forest) Bruxelles-Capitale 1190",
    "addr:housenumber":"31",
    "addr:postcode":"1190",
    "addr:street":"Rue De L'Eau",
    "iso:country":"BE",
    "sg:address":"Rue De L'eau 31",
    "sg:city":"Bruxelles (forest)",
    "sg:classifiers":[
        {
            "category":"Landmark",
            "subcategory":"Scenic View",
            "type":"Public Place"
        }
    ],
    "sg:phone":"+32 2 332 12 92",
    "sg:postcode":"1190",
    "sg:province":"Bruxelles-Capitale",
    "sg:tags":[
        "setting",
        "photographic"
    ],
    "wof:name":"M.v.diffusion",
    "wof:placetype":"venue"
},
  "geometry": {"coordinates":[4.3136510849,50.8080368042],"type":"Point"}
}