{
  "type": "Feature",
  "properties": {
    "iso:country":"BE",
    "sg:address":"Tomt 9",
    "sg:city":"Sint-lievens-houtem (vlierzele)",
    "sg:classifiers":[
        {
            "category":"Retail",
            "subcategory":"Auto Repair",
            "type":"Services"
        }
    ],
    "sg:phone":"+32 53 62 26 21",
    "sg:postcode":"9520",
    "sg:province":"Oost-Vlaanderen",
    "sg:tags":[
        "automobile-body"
    ],
    "wof:name":"De Vriendt Garage Bvba",
    "wof:placetype":"venue"
},
  "geometry": {"coordinates":[3.9029829502,50.931438446],"type":"Point"}
}