{
  "type": "Feature",
  "properties": {
    "iso:country":"BE",
    "sg:address":"Rue Des M\u00c9sanges 42",
    "sg:city":"Eghezee",
    "sg:orig_category":"Woningbouw",
    "sg:phone":"+32 81 51 19 43",
    "sg:postcode":"5310",
    "sg:province":"Namur",
    "wof:name":"Politi P",
    "wof:placetype":"venue"
},
  "geometry": {"coordinates":[4.9048810005,50.5511627197],"type":"Point"}
}