{
  "type": "Feature",
  "properties": {
    "iso:country":"BE",
    "sg:address":"Rubensstraat 104",
    "sg:city":"Turnhout",
    "sg:classifiers":[
        {
            "category":"Real Estate",
            "subcategory":"Real Estate Services",
            "type":"Services"
        }
    ],
    "sg:phone":"+32 14 47 08 49",
    "sg:postcode":"2300",
    "sg:province":"Antwerpen",
    "wof:name":"Improfund",
    "wof:placetype":"venue"
},
  "geometry": {"coordinates":[4.9436078072,51.3167152405],"type":"Point"}
}