{
  "type": "Feature",
  "properties": {
    "iso:country":"BE",
    "sg:address":"Rue Des Postes 101",
    "sg:city":"Braine-le-comte",
    "sg:orig_category":"Boekhouders",
    "sg:postcode":"7090",
    "sg:province":"Hainaut",
    "wof:name":"L\u00c9on Snyders",
    "wof:placetype":"venue"
},
  "geometry": {"coordinates":[4.1275901794,50.6067733765],"type":"Point"}
}