{
  "type": "Feature",
  "properties": {
    "addr:full":"Rue Du Centre 57 Soumagne (melen) Li\u00e8ge 4633",
    "addr:housenumber":"57",
    "addr:postcode":"4633",
    "addr:street":"Rue Du Centre;Melen",
    "iso:country":"BE",
    "sg:address":"Rue Du Centre 57",
    "sg:city":"Soumagne (melen)",
    "sg:classifiers":[
        {
            "category":"Building & Trades",
            "subcategory":"Plumbing",
            "type":"Services"
        }
    ],
    "sg:phone":"+32 4 377 53 30",
    "sg:postcode":"4633",
    "sg:province":"Li\u00e8ge",
    "sg:tags":[
        "contractor"
    ],
    "wof:name":"Wapi-toitures Sprl",
    "wof:placetype":"venue"
},
  "geometry": {"coordinates":[5.7347040176,50.6425552368],"type":"Point"}
}