{
  "type": "Feature",
  "properties": {
    "iso:country":"BE",
    "sg:address":"Rue Du Tiege 193",
    "sg:city":"Oupeye",
    "sg:orig_category":"Ordinateurs and \u00e9quipement informatique",
    "sg:phone":"+32 4 278 25 73",
    "sg:postcode":"4680",
    "sg:province":"Li\u00e8ge",
    "wof:name":"Joseph Ancion",
    "wof:placetype":"venue"
},
  "geometry": {"coordinates":[5.6314330101,50.7140541077],"type":"Point"}
}