{
  "type": "Feature",
  "properties": {
    "addr:full":"5170 Profondeville (groot) Namur 5170",
    "addr:postcode":"5170;5170",
    "addr:street":"Groot Namur",
    "iso:country":"BE",
    "sg:address":"5170",
    "sg:city":"Profondeville (groot)",
    "sg:orig_category":"Pharmaciens",
    "sg:phone":"+32 900 10 500",
    "sg:postcode":"5170",
    "sg:province":"Namur",
    "wof:name":"Pharmacies De Garde",
    "wof:placetype":"venue"
},
  "geometry": {"coordinates":[4.8674049377,50.3786392212],"type":"Point"}
}