{
  "type": "Feature",
  "properties": {
    "addr:full":"Adtridlaan 52 Overpelt Limburg 3900",
    "addr:housenumber":"52",
    "addr:postcode":"3900",
    "addr:street":"Adtridlaan",
    "iso:country":"BE",
    "sg:address":"Adtridlaan 52",
    "sg:city":"Overpelt",
    "sg:orig_category":"Antiek Tweedehandsgoederen",
    "sg:phone":"+32 11 66 30 80",
    "sg:postcode":"3900",
    "sg:province":"Limburg",
    "wof:name":"Compen Antiek En Curiosa",
    "wof:placetype":"venue"
},
  "geometry": {"coordinates":[5.4111180305,51.2099571228],"type":"Point"}
}