{
  "type": "Feature",
  "properties": {
    "addr:full":"Veemarkt 17 Lier Antwerpen 2500",
    "addr:housenumber":"17",
    "addr:postcode":"2500",
    "addr:street":"Veemarkt",
    "iso:country":"BE",
    "sg:address":"Veemarkt 17",
    "sg:city":"Lier",
    "sg:classifiers":[
        {
            "category":"Health Services",
            "subcategory":"Health Practitioner",
            "type":"Services"
        }
    ],
    "sg:phone":"+32 3 489 39 49",
    "sg:postcode":"2500",
    "sg:province":"Antwerpen",
    "sg:tags":[
        "physiotherapist"
    ],
    "wof:name":"Spruyt Veerle",
    "wof:placetype":"venue"
},
  "geometry": {"coordinates":[4.5828938484,51.127822876],"type":"Point"}
}