{
  "type": "Feature",
  "properties": {
    "addr:full":"Wenigerstraat 22 Borsbeek Antwerpen 2150",
    "addr:housenumber":"22",
    "addr:postcode":"2150",
    "addr:street":"Wenigerstraat",
    "iso:country":"BE",
    "sg:address":"Wenigerstraat 22",
    "sg:city":"Borsbeek",
    "sg:classifiers":[
        {
            "category":"Ice Cream",
            "type":"Food & Drink"
        }
    ],
    "sg:phone":"+32 3 321 51 91",
    "sg:postcode":"2150",
    "sg:province":"Antwerpen",
    "wof:name":"Exotisch Ijs",
    "wof:placetype":"venue"
},
  "geometry": {"coordinates":[4.4797358513,51.1981086731],"type":"Point"}
}