{
  "type": "Feature",
  "properties": {
    "addr:full":"Dadizeelsestraat 182 Moorslede West-Vlaanderen 8890",
    "addr:housenumber":"182",
    "addr:postcode":"8890",
    "addr:street":"Dadizeelsestraat",
    "iso:country":"BE",
    "sg:address":"Dadizeelsestraat 182",
    "sg:city":"Moorslede",
    "sg:classifiers":[
        {
            "category":"Airport",
            "subcategory":"International",
            "type":"Transportation"
        }
    ],
    "sg:phone":"+32 51 77 79 19",
    "sg:postcode":"8890",
    "sg:province":"West-Vlaanderen",
    "sg:tags":[
        "-",
        "transport"
    ],
    "wof:name":"Deletra",
    "wof:placetype":"venue"
},
  "geometry": {"coordinates":[3.0662600994,50.8734397888],"type":"Point"}
}