{
  "type": "Feature",
  "properties": {
    "addr:full":"Boulevard Maurice Lemonnier 3 Bruxelles Bruxelles-Capitale 1000",
    "addr:housenumber":"3",
    "addr:postcode":"1000",
    "addr:street":"Boulevard Maurice Lemonnier",
    "iso:country":"BE",
    "sg:address":"Boulevard Maurice Lemonnier 3",
    "sg:city":"Bruxelles",
    "sg:classifiers":[
        {
            "category":"Shopping",
            "subcategory":"Music",
            "type":"Retail Goods"
        }
    ],
    "sg:phone":"+32 2 511 70 44",
    "sg:postcode":"1000",
    "sg:province":"Bruxelles-Capitale",
    "sg:tags":[
        "-",
        "cd's",
        "recorded",
        "cassette"
    ],
    "wof:name":"Discomania",
    "wof:placetype":"venue"
},
  "geometry": {"coordinates":[4.3459839821,50.8450088501],"type":"Point"}
}