{
  "type": "Feature",
  "properties": {
    "addr:full":"Driesstraat 69 Affligem (teralfene) Vlaams-Brabant 1790",
    "addr:housenumber":"69",
    "addr:postcode":"1790",
    "addr:street":"Driesstraat",
    "iso:country":"BE",
    "sg:address":"Driesstraat 69",
    "sg:city":"Affligem (teralfene)",
    "sg:classifiers":[
        {
            "category":"Freight",
            "type":"Transportation"
        }
    ],
    "sg:phone":"+32 53 67 36 14",
    "sg:postcode":"1790",
    "sg:province":"Vlaams-Brabant",
    "sg:tags":[
        "-",
        "transport"
    ],
    "wof:name":"D M V Trans Bvba",
    "wof:placetype":"venue"
},
  "geometry": {"coordinates":[4.100839138,50.8892478943],"type":"Point"}
}