{
  "type": "Feature",
  "properties": {
    "addr:full":"Rue Des Coccinelles 16 Vis\u00e9 Li\u00e8ge 4600",
    "addr:housenumber":"16",
    "addr:postcode":"4600",
    "addr:street":"Rue Des Coccinelles",
    "iso:country":"BE",
    "sg:address":"Rue Des Coccinelles 16",
    "sg:city":"Vis\u00e9",
    "sg:classifiers":[
        {
            "category":"Insurance",
            "subcategory":"Insurance Agent",
            "type":"Services"
        }
    ],
    "sg:phone":"+32 4 264 31 99",
    "sg:postcode":"4600",
    "sg:province":"Li\u00e8ge",
    "sg:tags":[
        "broker"
    ],
    "wof:name":"Eerens L",
    "wof:placetype":"venue"
},
  "geometry": {"coordinates":[5.687661171,50.7351837158],"type":"Point"}
}