{
  "type": "Feature",
  "properties": {
    "iso:country":"BE",
    "sg:address":"Delannoylaan",
    "sg:city":"Leopoldsburg",
    "sg:classifiers":[
        {
            "category":"Sports & Exercise",
            "subcategory":"Stables",
            "type":"Entertainment"
        }
    ],
    "sg:phone":"+32 11 40 29 35",
    "sg:postcode":"3970",
    "sg:province":"Limburg",
    "sg:tags":[
        "riding",
        "school"
    ],
    "wof:name":"Dagen Van Het Paard Vzw",
    "wof:placetype":"venue"
},
  "geometry": {"coordinates":[5.2650752068,51.1056060791],"type":"Point"}
}