{
  "type": "Feature",
  "properties": {
    "addr:full":"Gustaaf Le F\u00e8vere De Ten Hovelaan 4 Gent (gentbrugge) Oost-Vlaanderen 9050",
    "addr:housenumber":"4",
    "addr:postcode":"9050",
    "addr:street":"Gustaaf Le Fe\u0300Vere De Ten Hovelaan",
    "iso:country":"BE",
    "sg:address":"Gustaaf Le F\u00e8vere De Ten Hovelaan 4",
    "sg:city":"Gent (gentbrugge)",
    "sg:classifiers":[
        {
            "category":"Professional",
            "subcategory":"Advertising",
            "type":"Services"
        }
    ],
    "sg:phone":"+32 9 232 46 48",
    "sg:postcode":"9050",
    "sg:province":"Oost-Vlaanderen",
    "sg:tags":[
        "aerial",
        "-"
    ],
    "wof:name":"A Balloon Adventure & Advertising",
    "wof:placetype":"venue"
},
  "geometry": {"coordinates":[3.7624459267,51.0389785767],"type":"Point"}
}