{
  "type": "Feature",
  "properties": {
    "iso:country":"BE",
    "sg:address":"Kongoplein 2 Bus 3",
    "sg:city":"Deinze",
    "sg:orig_category":"Rev\u00eatements de sols and murs. Blanchisserie, Nettoyage \u00e0 Sec and Salons-Lavoirs",
    "sg:phone":"+32 9 380 17 44",
    "sg:postcode":"9800",
    "sg:province":"Oost-Vlaanderen",
    "wof:name":"Chem Dry",
    "wof:placetype":"venue"
},
  "geometry": {"coordinates":[3.5225799084,50.987159729],"type":"Point"}
}