{
  "type": "Feature",
  "properties": {
    "addr:full":"Schaarbeeklei 740 Vilvoorde Vlaams-Brabant 1800",
    "addr:housenumber":"740",
    "addr:postcode":"1800",
    "addr:street":"Schaarbeeklei",
    "iso:country":"BE",
    "sg:address":"Schaarbeeklei 740",
    "sg:city":"Vilvoorde",
    "sg:orig_category":"Herstellingen and onderhoud van auto's",
    "sg:phone":"+32 2 251 63 54",
    "sg:postcode":"1800",
    "sg:province":"Vlaams-Brabant",
    "wof:name":"Carrosserie Ital-torino",
    "wof:placetype":"venue"
},
  "geometry": {"coordinates":[4.4135189056,50.9068641663],"type":"Point"}
}