{
  "type": "Feature",
  "properties": {
    "addr:full":"Rue D'aumale 110 Anderlecht/anderlecht Bruxelles-Capitale 1070",
    "addr:housenumber":"110",
    "addr:postcode":"1070",
    "addr:street":"Rue D'Aumale",
    "iso:country":"BE",
    "sg:address":"Rue D'aumale 110",
    "sg:city":"Anderlecht/anderlecht",
    "sg:orig_category":"Pain, p\u00e2tisseries and confiseries",
    "sg:phone":"+32 2 521 66 30",
    "sg:postcode":"1070",
    "sg:province":"Bruxelles-Capitale",
    "wof:name":"Boulangerie Monsif",
    "wof:placetype":"venue"
},
  "geometry": {"coordinates":[4.3109149933,50.838924408],"type":"Point"}
}