{
  "type": "Feature",
  "properties": {
    "addr:full":"Bussestraat 17 Rumst Antwerpen 2840",
    "addr:housenumber":"17",
    "addr:postcode":"2840",
    "addr:street":"Bussestraat",
    "iso:country":"BE",
    "sg:address":"Bussestraat 17",
    "sg:city":"Rumst",
    "sg:orig_category":"Produits pharmaceutiques Gr",
    "sg:phone":"+32 15 32 13 73",
    "sg:postcode":"2840",
    "sg:province":"Antwerpen",
    "wof:name":"O.s.g. Medical Software",
    "wof:placetype":"venue"
},
  "geometry": {"coordinates":[4.4491801262,51.0852127075],"type":"Point"}
}