{
  "type": "Feature",
  "properties": {
    "iso:country":"BE",
    "sg:address":"Ooievaarslaan 1",
    "sg:city":"Oostende",
    "sg:orig_category":"Maisons de repos and r\u00e9sidences",
    "sg:phone":"+32 59 55 11 00",
    "sg:postcode":"8400",
    "sg:province":"West-Vlaanderen",
    "wof:name":"Rusthuis Stijn",
    "wof:placetype":"venue"
},
  "geometry": {"coordinates":[2.9155709743,51.2174911499],"type":"Point"}
}