{
  "type": "Feature",
  "properties": {
    "addr:full":"Nicolas Meng\u00c9laan 13 Knokke-heist West-Vlaanderen 8301",
    "addr:housenumber":"13",
    "addr:postcode":"8301",
    "addr:street":"Menge\u0301Laan",
    "iso:country":"BE",
    "sg:address":"Nicolas Meng\u00c9laan 13",
    "sg:city":"Knokke-heist",
    "sg:orig_category":"Instituts de beaut\u00e9. Centres de relaxation and bien-\u00eatre",
    "sg:phone":"+32 50 51 32 87",
    "sg:postcode":"8301",
    "sg:province":"West-Vlaanderen",
    "wof:name":"Oceano",
    "wof:placetype":"venue"
},
  "geometry": {"coordinates":[3.2639000416,51.3396911621],"type":"Point"}
}