{
  "type": "Feature",
  "properties": {
    "iso:country":"BE",
    "sg:address":"Platanendreef 69",
    "sg:city":"Waregem",
    "sg:orig_category":"Plaatsen van vloer- and muurbekleding Schilders",
    "sg:phone":"+32 56 61 20 12",
    "sg:postcode":"8790",
    "sg:province":"West-Vlaanderen",
    "wof:name":"Callens",
    "wof:placetype":"venue"
},
  "geometry": {"coordinates":[3.408894062,50.8639030457],"type":"Point"}
}