{
  "type": "Feature",
  "properties": {
    "iso:country":"BE",
    "sg:address":"Willem Van Doornyckstraat 29",
    "sg:city":"Beveren (haasdonk)",
    "sg:classifiers":[
        {
            "category":"Personal",
            "subcategory":"Beauty Salon",
            "type":"Services"
        }
    ],
    "sg:phone":"+32 3 755 46 09",
    "sg:postcode":"9120",
    "sg:province":"Oost-Vlaanderen",
    "sg:tags":[
        "lady",
        "-",
        "hairdressing"
    ],
    "wof:name":"Antoine",
    "wof:placetype":"venue"
},
  "geometry": {"coordinates":[4.2361388206,51.1807365417],"type":"Point"}
}