{
  "type": "Feature",
  "properties": {
    "addr:full":"Rue De Percke 42 Bruxelles (uccle) Bruxelles-Capitale 1180",
    "addr:housenumber":"42",
    "addr:postcode":"1180",
    "addr:street":"Rue De Percke",
    "iso:country":"BE",
    "sg:address":"Rue De Percke 42",
    "sg:city":"Bruxelles (uccle)",
    "sg:classifiers":[
        {
            "category":"Railroad",
            "type":"Transportation"
        }
    ],
    "sg:phone":"+32 2 375 63 28",
    "sg:postcode":"1180",
    "sg:province":"Bruxelles-Capitale",
    "sg:tags":[
        "sieve"
    ],
    "wof:name":"B D C",
    "wof:placetype":"venue"
},
  "geometry": {"coordinates":[4.3690028191,50.7740592957],"type":"Point"}
}