{
  "type": "Feature",
  "properties": {
    "addr:full":"Koning Leopold Iiistraat 1 Merchtem Vlaams-Brabant 1785",
    "addr:housenumber":"1",
    "addr:postcode":"1785",
    "addr:street":"Koning Leopold Iiistraat",
    "iso:country":"BE",
    "sg:address":"Koning Leopold Iiistraat 1",
    "sg:city":"Merchtem",
    "sg:orig_category":"Paramedische behandelingen",
    "sg:phone":"+32 52 37 41 27",
    "sg:postcode":"1785",
    "sg:province":"Vlaams-Brabant",
    "wof:name":"D. Van Bossuyt",
    "wof:placetype":"venue"
},
  "geometry": {"coordinates":[4.2267351151,50.9562454224],"type":"Point"}
}