{
  "type": "Feature",
  "properties": {
    "addr:full":"Forelstraat 22 Gent Oost-Vlaanderen 9000",
    "addr:housenumber":"22",
    "addr:postcode":"9000",
    "addr:street":"Forelstraat;Oost-Vlaanderen",
    "iso:country":"BE",
    "sg:address":"Forelstraat 22",
    "sg:city":"Gent",
    "sg:orig_category":"Catalogues de vente par correspondance",
    "sg:phone":"+32 9 265 64 40",
    "sg:postcode":"9000",
    "sg:province":"Oost-Vlaanderen",
    "wof:name":"Selectief",
    "wof:placetype":"venue"
},
  "geometry": {"coordinates":[3.7404940128,51.0474205017],"type":"Point"}
}