{
  "type": "Feature",
  "properties": {
    "iso:country":"BE",
    "sg:address":"Tivolistraat 16",
    "sg:city":"Leuven",
    "sg:orig_category":"Film-, tv- and videoproductie",
    "sg:phone":"+32 16 20 14 30",
    "sg:postcode":"3001",
    "sg:province":"Vlaams-Brabant",
    "wof:name":"De Skriptank",
    "wof:placetype":"venue"
},
  "geometry": {"coordinates":[4.7178521156,50.8719062805],"type":"Point"}
}