{
  "type": "Feature",
  "properties": {
    "addr:full":"Affligemdreef 17 Aalst Oost-Vlaanderen 9300",
    "addr:housenumber":"17",
    "addr:postcode":"9300",
    "addr:street":"Affligemdreef",
    "iso:country":"BE",
    "sg:address":"Affligemdreef 17",
    "sg:city":"Aalst",
    "sg:orig_category":"Groenten and fruit Gh Groententeelt",
    "sg:phone":"+32 53 21 37 16",
    "sg:postcode":"9300",
    "sg:province":"Oost-Vlaanderen",
    "wof:name":"Alfons Arts",
    "wof:placetype":"venue"
},
  "geometry": {"coordinates":[4.061413765,50.9319725037],"type":"Point"}
}