{
  "type": "Feature",
  "properties": {
    "addr:full":"Stockbergerweg 15 Eupen Li\u00e8ge 4700",
    "addr:housenumber":"15",
    "addr:postcode":"4700",
    "addr:street":"Stockbergerweg",
    "iso:country":"BE",
    "sg:address":"Stockbergerweg 15",
    "sg:city":"Eupen",
    "sg:classifiers":[
        {
            "category":"Retail",
            "subcategory":"Veterinary Services",
            "type":"Services"
        }
    ],
    "sg:phone":"+32 474 93 04 98",
    "sg:postcode":"4700",
    "sg:province":"Li\u00e8ge",
    "sg:tags":[
        "veterinarian"
    ],
    "wof:name":"Bachour L",
    "wof:placetype":"venue"
},
  "geometry": {"coordinates":[6.0391511917,50.6277542114],"type":"Point"}
}