{
  "type": "Feature",
  "properties": {
    "iso:country":"BE",
    "sg:address":"Kaaistraat 1",
    "sg:city":"Roeselare",
    "sg:classifiers":[
        {
            "category":"Cafe",
            "type":"Food & Drink"
        }
    ],
    "sg:phone":"+32 51 22 09 56",
    "sg:postcode":"8800",
    "sg:province":"West-Vlaanderen",
    "sg:tags":[
        "caf\u00e9s"
    ],
    "wof:name":"Caf\u00c9 't Schippershof",
    "wof:placetype":"venue"
},
  "geometry": {"coordinates":[3.1326329708,50.9456939697],"type":"Point"}
}