{
  "type": "Feature",
  "properties": {
    "iso:country":"BE",
    "sg:address":"Wellingstraat 37",
    "sg:city":"Beernem",
    "sg:orig_category":"V\u00eatements sur mesure Fab. V\u00eatements pour Dames. V\u00eatements de mariage and c\u00e9r\u00e9monies",
    "sg:phone":"+32 50 79 08 08",
    "sg:postcode":"8730",
    "sg:province":"West-Vlaanderen",
    "wof:name":"Huis Veronique",
    "wof:placetype":"venue"
},
  "geometry": {"coordinates":[3.3194499016,51.131401062],"type":"Point"}
}