{
  "type": "Feature",
  "properties": {
    "addr:full":"Houwstraat 69 Putte Antwerpen 2580",
    "addr:housenumber":"69",
    "addr:postcode":"2580",
    "addr:street":"Houwstraat",
    "iso:country":"BE",
    "sg:address":"Houwstraat 69",
    "sg:city":"Putte",
    "sg:orig_category":"V\u00e9los",
    "sg:phone":"+32 15 75 71 97",
    "sg:postcode":"2580",
    "sg:province":"Antwerpen",
    "wof:name":"Vd Consult",
    "wof:placetype":"venue"
},
  "geometry": {"coordinates":[4.6565961838,51.0688781738],"type":"Point"}
}