{
  "type": "Feature",
  "properties": {
    "iso:country":"BE",
    "sg:address":"Industriepark Balendijk",
    "sg:city":"Lommel",
    "sg:classifiers":[
        {
            "category":"Manufacturing",
            "subcategory":"Metals",
            "type":"Manufacturing & Wholesale Goods"
        }
    ],
    "sg:phone":"+32 11 54 10 62",
    "sg:postcode":"3920",
    "sg:province":"Limburg",
    "sg:tags":[
        "working"
    ],
    "wof:name":"Janssen F",
    "wof:placetype":"venue"
},
  "geometry": {"coordinates":[5.3089981079,51.2305793762],"type":"Point"}
}