{
  "type": "Feature",
  "properties": {
    "addr:full":"Vinkenstraat 43 Boechout Antwerpen 2530",
    "addr:housenumber":"43",
    "addr:postcode":"2530",
    "addr:street":"Vinkenstraat",
    "iso:country":"BE",
    "sg:address":"Vinkenstraat 43",
    "sg:city":"Boechout",
    "sg:orig_category":"Experts-comptables",
    "sg:phone":"+32 3 455 52 78",
    "sg:postcode":"2530",
    "sg:province":"Antwerpen",
    "wof:name":"K. Delmotte",
    "wof:placetype":"venue"
},
  "geometry": {"coordinates":[4.5211648941,51.1527671814],"type":"Point"}
}