{
  "type": "Feature",
  "properties": {
    "addr:full":"Acacialaan 7 Scherpenheuvel-zichem Vlaams-Brabant 3271",
    "addr:housenumber":"7",
    "addr:postcode":"3271",
    "addr:street":"Acacialaan",
    "iso:country":"BE",
    "sg:address":"Acacialaan 7",
    "sg:city":"Scherpenheuvel-zichem",
    "sg:orig_category":"D\u00e9corateurs d'int\u00e9rieur",
    "sg:phone":"+32 13 77 53 22",
    "sg:postcode":"3271",
    "sg:province":"Vlaams-Brabant",
    "wof:name":"C.n.d.",
    "wof:placetype":"venue"
},
  "geometry": {"coordinates":[4.9569292068,50.9801254272],"type":"Point"}
}