{
  "type": "Feature",
  "properties": {
    "addr:full":"Oudenaardsesteenweg 52 Gent-centrum Oost-Vlaanderen 9000",
    "addr:housenumber":"52",
    "addr:postcode":"9000",
    "addr:street":"Oudenaardsesteenweg;Oost-Vlaanderen",
    "iso:country":"BE",
    "sg:address":"Oudenaardsesteenweg 52",
    "sg:city":"Gent-centrum",
    "sg:orig_category":"Advocaten and juridische adviseurs Balie van Gent",
    "sg:phone":"+32 9 221 88 32",
    "sg:postcode":"9000",
    "sg:province":"Oost-Vlaanderen",
    "wof:name":"Carre Guy",
    "wof:placetype":"venue"
},
  "geometry": {"coordinates":[3.708990097,51.0223999023],"type":"Point"}
}