{
  "type": "Feature",
  "properties": {
    "addr:full":"Nieuwstraat 21 Geel Antwerpen 2440",
    "addr:housenumber":"21",
    "addr:postcode":"2440",
    "addr:street":"Nieuwstraat",
    "iso:country":"BE",
    "sg:address":"Nieuwstraat 21",
    "sg:city":"Geel",
    "sg:classifiers":[
        {
            "category":"Shopping",
            "subcategory":"Clothing, Apparel, & Fashions",
            "type":"Retail Goods"
        }
    ],
    "sg:phone":"+32 14 58 83 21",
    "sg:postcode":"2440",
    "sg:province":"Antwerpen",
    "sg:tags":[
        "clothing",
        "-",
        "gentleman"
    ],
    "wof:name":"Lievens Kleding Nv",
    "wof:placetype":"venue"
},
  "geometry": {"coordinates":[4.9922032356,51.1626815796],"type":"Point"}
}