{
  "type": "Feature",
  "properties": {
    "addr:full":"Rootstraat 18 Tervuren Vlaams-Brabant 3080",
    "addr:housenumber":"18",
    "addr:postcode":"3080",
    "addr:street":"Rootstraat",
    "iso:country":"BE",
    "sg:address":"Rootstraat 18",
    "sg:city":"Tervuren",
    "sg:orig_category":"Fleurs and plantes",
    "sg:phone":"+32 2 767 99 73",
    "sg:postcode":"3080",
    "sg:province":"Vlaams-Brabant",
    "wof:name":"Helleborus",
    "wof:placetype":"venue"
},
  "geometry": {"coordinates":[4.5531988144,50.8170890808],"type":"Point"}
}