{
  "type": "Feature",
  "properties": {
    "addr:full":"Minnezangerslaan 109 Sint-jans-molenbeek/molenbeek-saint-jean Bruxelles-Capitale 1080",
    "addr:housenumber":"109",
    "addr:postcode":"1080",
    "addr:street":"Minnezangerslaan",
    "iso:country":"BE",
    "sg:address":"Minnezangerslaan 109",
    "sg:city":"Sint-jans-molenbeek/molenbeek-saint-jean",
    "sg:orig_category":"Apotheken",
    "sg:phone":"+32 2 411 15 59",
    "sg:postcode":"1080",
    "sg:province":"Bruxelles-Capitale",
    "wof:name":"Pharmacie Scheut",
    "wof:placetype":"venue"
},
  "geometry": {"coordinates":[4.3090438843,50.8503189087],"type":"Point"}
}