{
  "type": "Feature",
  "properties": {
    "iso:country":"BE",
    "sg:address":"Fritz Vinckelaan 5",
    "sg:city":"Bredene",
    "sg:classifiers":[
        {
            "category":"Fast Food",
            "type":"Food & Drink"
        }
    ],
    "sg:phone":"+32 59 32 37 36",
    "sg:postcode":"8450",
    "sg:province":"West-Vlaanderen",
    "sg:tags":[
        "fried",
        "stand",
        "potato"
    ],
    "wof:name":"Marie-claire",
    "wof:placetype":"venue"
},
  "geometry": {"coordinates":[2.9615991116,51.2243309021],"type":"Point"}
}