{
  "type": "Feature",
  "properties": {
    "addr:full":"Wolstraat 45 Antwerpen Antwerpen 2000",
    "addr:housenumber":"45",
    "addr:postcode":"2000",
    "addr:street":"Wolstraat",
    "iso:country":"BE",
    "sg:address":"Wolstraat 45",
    "sg:city":"Antwerpen",
    "sg:classifiers":[
        {
            "category":"Restaurant",
            "type":"Food & Drink"
        }
    ],
    "sg:phone":"+32 3 231 89 94",
    "sg:postcode":"2000",
    "sg:province":"Antwerpen",
    "wof:name":"Restaurant Rucolla",
    "wof:placetype":"venue"
},
  "geometry": {"coordinates":[4.404378891,51.2215614319],"type":"Point"}
}