{
  "type": "Feature",
  "properties": {
    "iso:country":"BE",
    "sg:address":"Verlorenbroodstraat 20c",
    "sg:city":"Merelbeke",
    "sg:orig_category":"Plantes and fleurs Gr",
    "sg:phone":"+32 9 230 66 02",
    "sg:postcode":"9820",
    "sg:province":"Oost-Vlaanderen",
    "wof:name":"De Clercq A. & Zoon",
    "wof:placetype":"venue"
},
  "geometry": {"coordinates":[3.7484779358,51.0144577026],"type":"Point"}
}