{
  "type": "Feature",
  "properties": {
    "addr:full":"Wisbeley 63 Libramont-chevigny Luxembourg 6800",
    "addr:housenumber":"63",
    "addr:postcode":"6800",
    "addr:street":"Wisbeley",
    "iso:country":"BE",
    "sg:address":"Wisbeley 63",
    "sg:city":"Libramont-chevigny",
    "sg:orig_category":"Herstellingen and onderhoud van auto's",
    "sg:phone":"+32 61 22 29 67",
    "sg:postcode":"6800",
    "sg:province":"Luxembourg",
    "wof:name":"Ferdinand Lambert",
    "wof:placetype":"venue"
},
  "geometry": {"coordinates":[5.3761348724,49.9199943542],"type":"Point"}
}