{
  "type": "Feature",
  "properties": {
    "iso:country":"BE",
    "sg:address":"Montagne De Saint-job 50",
    "sg:city":"Ukkel/uccle",
    "sg:orig_category":"Meubles D\u00e9taillants, Am\u00e9nagement de B\u00e2timents et de Cuisines. Fabrication and montage de mobilier. I",
    "sg:phone":"+32 2 374 57 46",
    "sg:postcode":"1180",
    "sg:province":"Bruxelles-Capitale",
    "wof:name":"Bernard Hanappe",
    "wof:placetype":"venue"
},
  "geometry": {"coordinates":[4.3655948639,50.7923240662],"type":"Point"}
}