{
  "type": "Feature",
  "properties": {
    "iso:country":"BE",
    "sg:address":"Buchenweg 5",
    "sg:city":"Sankt Vith",
    "sg:classifiers":[
        {
            "category":"Building & Trades",
            "subcategory":"Construction",
            "type":"Services"
        }
    ],
    "sg:phone":"+32 80 22 17 30",
    "sg:postcode":"4780",
    "sg:province":"Li\u00e8ge",
    "sg:tags":[
        "installation",
        "-",
        "central",
        "heating"
    ],
    "wof:name":"Diritherm Ag",
    "wof:placetype":"venue"
},
  "geometry": {"coordinates":[6.1171898842,50.2750892639],"type":"Point"}
}