{
  "type": "Feature",
  "properties": {
    "addr:full":"Tiensestraat 43 Hoegaarden Vlaams-Brabant 3320",
    "addr:housenumber":"43",
    "addr:postcode":"3320",
    "addr:street":"Tiensestraat",
    "iso:country":"BE",
    "sg:address":"Tiensestraat 43",
    "sg:city":"Hoegaarden",
    "sg:orig_category":"Sportcentra",
    "sg:phone":"+32 16 76 70 80",
    "sg:postcode":"3320",
    "sg:province":"Vlaams-Brabant",
    "wof:name":"Gemeentelijke Sporthal",
    "wof:placetype":"venue"
},
  "geometry": {"coordinates":[4.8932328224,50.7756195068],"type":"Point"}
}