{
  "type": "Feature",
  "properties": {
    "addr:full":"Kerkhofstraat 72 Londerzeel Vlaams-Brabant 1840",
    "addr:housenumber":"72",
    "addr:postcode":"1840",
    "addr:street":"Kerkhofstraat",
    "iso:country":"BE",
    "sg:address":"Kerkhofstraat 72",
    "sg:city":"Londerzeel",
    "sg:classifiers":[
        {
            "category":"Arts & Performance",
            "subcategory":"Symphony",
            "type":"Entertainment"
        }
    ],
    "sg:phone":"+32 52 30 69 22",
    "sg:postcode":"1840",
    "sg:province":"Vlaams-Brabant",
    "sg:tags":[
        "orchestra"
    ],
    "wof:name":"Ensemble Currende Vzw",
    "wof:placetype":"venue"
},
  "geometry": {"coordinates":[4.3072500229,51.0023155212],"type":"Point"}
}