{
  "type": "Feature",
  "properties": {
    "addr:full":"Bredabaan 453 Brasschaat Antwerpen 2930",
    "addr:housenumber":"453",
    "addr:postcode":"2930",
    "addr:street":"Bredabaan",
    "iso:country":"BE",
    "sg:address":"Bredabaan 453",
    "sg:city":"Brasschaat",
    "sg:classifiers":[
        {
            "category":"Shopping",
            "subcategory":"Clothing, Apparel, & Fashions",
            "type":"Retail Goods"
        }
    ],
    "sg:phone":"+32 3 653 41 87",
    "sg:postcode":"2930",
    "sg:province":"Antwerpen",
    "sg:tags":[
        "-",
        "clothing",
        "child"
    ],
    "wof:name":"Boboli",
    "wof:placetype":"venue"
},
  "geometry": {"coordinates":[4.4946060181,51.2925224304],"type":"Point"}
}