{
  "type": "Feature",
  "properties": {
    "iso:country":"BE",
    "sg:address":"Dorpstraat 1",
    "sg:city":"Koekelare",
    "sg:classifiers":[
        {
            "category":"Bars & Pubs",
            "type":"Food & Drink"
        }
    ],
    "sg:phone":"+32 51 54 48 87",
    "sg:postcode":"8680",
    "sg:province":"West-Vlaanderen",
    "wof:name":"De Plafonneur",
    "wof:placetype":"venue"
},
  "geometry": {"coordinates":[2.9778819084,51.0903053284],"type":"Point"}
}