{
  "type": "Feature",
  "properties": {
    "iso:country":"BE",
    "sg:address":"Turnhoutsebaan 129",
    "sg:city":"Schilde",
    "sg:orig_category":"Avocats and conseillers juridiques",
    "sg:phone":"+32 3 384 06 85",
    "sg:postcode":"2970",
    "sg:province":"Antwerpen",
    "wof:name":"Dirk Van Gestel",
    "wof:placetype":"venue"
},
  "geometry": {"coordinates":[4.5796480179,51.2393035889],"type":"Point"}
}