{
  "type": "Feature",
  "properties": {
    "addr:full":"Rue De Messitert 222 Aubel Li\u00e8ge 4880",
    "addr:housenumber":"222",
    "addr:postcode":"4880",
    "addr:street":"Rue De Messitert",
    "iso:country":"BE",
    "sg:address":"Rue De Messitert 222",
    "sg:city":"Aubel",
    "sg:classifiers":[
        {
            "category":"Health Services",
            "subcategory":"Health Practitioner",
            "type":"Services"
        }
    ],
    "sg:phone":"+32 87 68 69 89",
    "sg:postcode":"4880",
    "sg:province":"Li\u00e8ge",
    "sg:tags":[
        "physiotherapist"
    ],
    "wof:name":"Maurer Christine",
    "wof:placetype":"venue"
},
  "geometry": {"coordinates":[5.8530101776,50.6984786987],"type":"Point"}
}