{
  "type": "Feature",
  "properties": {
    "addr:full":"Rue Sous-le-ch\u00e2teau 42 Huy Li\u00e8ge 4500",
    "addr:housenumber":"42",
    "addr:postcode":"4500",
    "addr:street":"Rue Sous-Le-Cha\u0302Teau",
    "iso:country":"BE",
    "sg:address":"Rue Sous-le-ch\u00e2teau 42",
    "sg:city":"Huy",
    "sg:classifiers":[
        {
            "category":"Health Services",
            "subcategory":"Doctor",
            "type":"Services"
        }
    ],
    "sg:phone":"+32 476 69 10 25",
    "sg:postcode":"4500",
    "sg:province":"Li\u00e8ge",
    "sg:tags":[
        "medicinephysicians",
        "surgeon"
    ],
    "wof:name":"Garzaniti Nicolas",
    "wof:placetype":"venue"
},
  "geometry": {"coordinates":[5.2387990952,50.5173797607],"type":"Point"}
}