{
  "type": "Feature",
  "properties": {
    "iso:country":"BE",
    "sg:address":"Ringlaan 7",
    "sg:city":"Overpelt",
    "sg:classifiers":[
        {
            "category":"Transit Center",
            "subcategory":"Freight",
            "type":"Transportation"
        }
    ],
    "sg:phone":"+32 11 64 26 06",
    "sg:postcode":"3900",
    "sg:province":"Limburg",
    "sg:tags":[
        "import",
        "export",
        "-"
    ],
    "wof:name":"Jeegee",
    "wof:placetype":"venue"
},
  "geometry": {"coordinates":[5.4208769798,51.2087516785],"type":"Point"}
}