{
  "type": "Feature",
  "properties": {
    "iso:country":"BE",
    "sg:address":"Torhoutse Steenweg 262",
    "sg:city":"Brugge",
    "sg:orig_category":"Brood, gebak and snoepgoed",
    "sg:phone":"+32 50 38 33 50",
    "sg:postcode":"8200",
    "sg:province":"West-Vlaanderen",
    "wof:name":"Ferdinand Rigole Chris",
    "wof:placetype":"venue"
},
  "geometry": {"coordinates":[3.195991993,51.2005157471],"type":"Point"}
}