{
  "type": "Feature",
  "properties": {
    "addr:full":"Rue Du Moulin 5 Tournai Hainaut 7503",
    "addr:housenumber":"5",
    "addr:postcode":"7503",
    "addr:street":"Rue Du Moulin",
    "iso:country":"BE",
    "sg:address":"Rue Du Moulin 5",
    "sg:city":"Tournai",
    "sg:classifiers":[
        {
            "category":"Cinema",
            "subcategory":"Movie Rental",
            "type":"Entertainment"
        }
    ],
    "sg:phone":"+32 69 21 12 13",
    "sg:postcode":"7503",
    "sg:province":"Hainaut",
    "sg:tags":[
        "de",
        "cassette",
        "location",
        "vid\u00e9o",
        "audio"
    ],
    "wof:name":"Pierre Pollet",
    "wof:placetype":"venue"
},
  "geometry": {"coordinates":[3.3540370464,50.6223945618],"type":"Point"}
}