{
  "type": "Feature",
  "properties": {
    "addr:full":"Noordstraat 213 Maldegem Oost-Vlaanderen 9990",
    "addr:housenumber":"213",
    "addr:postcode":"9990",
    "addr:street":"Noordstraat",
    "iso:country":"BE",
    "sg:address":"Noordstraat 213",
    "sg:city":"Maldegem",
    "sg:classifiers":[
        {
            "category":"Building & Trades",
            "subcategory":"Electrical",
            "type":"Services"
        }
    ],
    "sg:phone":"+32 50 71 39 81",
    "sg:postcode":"9990",
    "sg:province":"Oost-Vlaanderen",
    "sg:tags":[
        "electric",
        "-",
        "housewiring",
        "contractor"
    ],
    "wof:name":"Leliaert E",
    "wof:placetype":"venue"
},
  "geometry": {"coordinates":[3.4471840858,51.216796875],"type":"Point"}
}