{
  "type": "Feature",
  "properties": {
    "iso:country":"BE",
    "sg:address":"Schelfheidestraat 29",
    "sg:city":"Nieuwerkerken",
    "sg:classifiers":[
        {
            "category":"Professional",
            "subcategory":"Engineering",
            "type":"Services"
        }
    ],
    "sg:phone":"+32 11 68 67 19",
    "sg:postcode":"3850",
    "sg:province":"Limburg",
    "sg:tags":[
        "environmental",
        "technique",
        "-"
    ],
    "wof:name":"Mivera",
    "wof:placetype":"venue"
},
  "geometry": {"coordinates":[5.1842889786,50.8736801147],"type":"Point"}
}