{
  "type": "Feature",
  "properties": {
    "iso:country":"BE",
    "sg:address":"Keiberg 58",
    "sg:city":"Zwevegem (heestert)",
    "sg:classifiers":[
        {
            "category":"Farming",
            "subcategory":"Livestock Farm",
            "type":"Manufacturing & Wholesale Goods"
        }
    ],
    "sg:phone":"+32 56 64 43 78",
    "sg:postcode":"8551",
    "sg:province":"West-Vlaanderen",
    "sg:tags":[
        "buyer"
    ],
    "wof:name":"Raepsaet R",
    "wof:placetype":"venue"
},
  "geometry": {"coordinates":[3.3861739635,50.7853469849],"type":"Point"}
}