{
  "type": "Feature",
  "properties": {
    "iso:country":"BE",
    "sg:address":"Avenue De La Gare 131e",
    "sg:city":"Neufchateau",
    "sg:orig_category":"Plomberie, chauffage and installations sanitaires",
    "sg:phone":"+32 61 27 73 36",
    "sg:postcode":"6840",
    "sg:province":"Luxembourg",
    "wof:name":"Paul Piron",
    "wof:placetype":"venue"
},
  "geometry": {"coordinates":[5.4448637962,49.8501853943],"type":"Point"}
}