{
  "type": "Feature",
  "properties": {
    "addr:full":"Rue Du Marais 52 Anderlues Hainaut 6150",
    "addr:housenumber":"52",
    "addr:postcode":"6150",
    "addr:street":"Rue Du Marais",
    "iso:country":"BE",
    "sg:address":"Rue Du Marais 52",
    "sg:city":"Anderlues",
    "sg:orig_category":"Sportclubs",
    "sg:phone":"+32 71 52 54 54",
    "sg:postcode":"6150",
    "sg:province":"Hainaut",
    "wof:name":"Cox Team Anderlues",
    "wof:placetype":"venue"
},
  "geometry": {"coordinates":[4.2684798241,50.4057807922],"type":"Point"}
}