{
  "type": "Feature",
  "properties": {
    "addr:full":"Dorfstrasse 59 Plombieres/plombieres Li\u00e8ge 4850",
    "addr:housenumber":"59",
    "addr:postcode":"4850",
    "addr:street":"Dorfstrasse",
    "iso:country":"BE",
    "sg:address":"Dorfstrasse 59",
    "sg:city":"Plombieres/plombieres",
    "sg:orig_category":"Slagers",
    "sg:phone":"+32 87 78 54 07",
    "sg:postcode":"4850",
    "sg:province":"Li\u00e8ge",
    "wof:name":"Martin Otten",
    "wof:placetype":"venue"
},
  "geometry": {"coordinates":[5.9626002312,50.7068138123],"type":"Point"}
}