{
  "type": "Feature",
  "properties": {
    "addr:full":"Noordeneind 22 Essen Antwerpen 2910",
    "addr:housenumber":"22",
    "addr:postcode":"2910",
    "addr:street":"Noordeneind",
    "iso:country":"BE",
    "sg:address":"Noordeneind 22",
    "sg:city":"Essen",
    "sg:orig_category":"Eleveurs de bovins",
    "sg:phone":"+32 3 667 40 21",
    "sg:postcode":"2910",
    "sg:province":"Antwerpen",
    "wof:name":"Florimond Van Thillo",
    "wof:placetype":"venue"
},
  "geometry": {"coordinates":[4.4097471237,51.4563598633],"type":"Point"}
}