{
  "type": "Feature",
  "properties": {
    "addr:full":"Markt 16 Mol Antwerpen 2400",
    "addr:housenumber":"16",
    "addr:postcode":"2400",
    "addr:street":"Markt",
    "iso:country":"BE",
    "sg:address":"Markt 16",
    "sg:city":"Mol",
    "sg:orig_category":"M\u00e9decins and sp\u00e9cialistes",
    "sg:phone":"+32 14 71 01 81",
    "sg:postcode":"2400",
    "sg:province":"Antwerpen",
    "wof:name":"Pieter Raus",
    "wof:placetype":"venue"
},
  "geometry": {"coordinates":[5.116517067,51.1846046448],"type":"Point"}
}