{
  "type": "Feature",
  "properties": {
    "addr:full":"Kwikstaartlaan 7 Tervuren Vlaams-Brabant 3080",
    "addr:housenumber":"7",
    "addr:postcode":"3080",
    "addr:street":"Kwikstaartlaan",
    "iso:country":"BE",
    "sg:address":"Kwikstaartlaan 7",
    "sg:city":"Tervuren",
    "sg:classifiers":[
        {
            "category":"Social Services",
            "subcategory":"Job Training",
            "type":"Services"
        }
    ],
    "sg:phone":"+32 2 305 00 97",
    "sg:postcode":"3080",
    "sg:province":"Vlaams-Brabant",
    "sg:tags":[
        "interpreter"
    ],
    "wof:name":"Lefebvre J",
    "wof:placetype":"venue"
},
  "geometry": {"coordinates":[4.5399479866,50.8534469604],"type":"Point"}
}