{
  "type": "Feature",
  "properties": {
    "addr:full":"Kievitlaan 17 Ninove Oost-Vlaanderen 9400",
    "addr:housenumber":"17",
    "addr:postcode":"9400",
    "addr:street":"Kievitlaan",
    "iso:country":"BE",
    "sg:address":"Kievitlaan 17",
    "sg:city":"Ninove",
    "sg:classifiers":[
        {
            "category":"Health Services",
            "subcategory":"Health Practitioner",
            "type":"Services"
        }
    ],
    "sg:phone":"+32 54 33 97 03",
    "sg:postcode":"9400",
    "sg:province":"Oost-Vlaanderen",
    "sg:tags":[
        "physiotherapist"
    ],
    "wof:name":"Lievens Mia",
    "wof:placetype":"venue"
},
  "geometry": {"coordinates":[4.0316390991,50.8416175842],"type":"Point"}
}