{
  "type": "Feature",
  "properties": {
    "addr:full":"Quastraat 5 Laarne Oost-Vlaanderen 9270",
    "addr:housenumber":"5",
    "addr:postcode":"9270",
    "addr:street":"Quastraat",
    "iso:country":"BE",
    "sg:address":"Quastraat 5",
    "sg:city":"Laarne",
    "sg:orig_category":"Fabrication and montage de mobilier",
    "sg:phone":"+32 9 366 13 30",
    "sg:postcode":"9270",
    "sg:province":"Oost-Vlaanderen",
    "wof:name":"Keukens Askat",
    "wof:placetype":"venue"
},
  "geometry": {"coordinates":[3.8552041054,51.0411949158],"type":"Point"}
}