{
  "type": "Feature",
  "properties": {
    "addr:full":"Waversesteenweg 6 Bierbeek (honsem) Vlaams-Brabant 3360",
    "addr:housenumber":"6",
    "addr:postcode":"3360",
    "addr:street":"Waversesteenweg",
    "iso:country":"BE",
    "sg:address":"Waversesteenweg 6",
    "sg:city":"Bierbeek (honsem)",
    "sg:classifiers":[
        {
            "category":"Professional",
            "subcategory":"Management & Consulting",
            "type":"Services"
        }
    ],
    "sg:phone":"+32 16 73 32 36",
    "sg:postcode":"3360",
    "sg:province":"Vlaams-Brabant",
    "sg:tags":[
        "consultant"
    ],
    "wof:name":"Delvaulx Consult Com V",
    "wof:placetype":"venue"
},
  "geometry": {"coordinates":[4.7825860977,50.8059043884],"type":"Point"}
}