{
  "type": "Feature",
  "properties": {
    "iso:country":"BE",
    "sg:address":"Rechterstrasse 15",
    "sg:city":"Amel/ambleve",
    "sg:orig_category":"Rundveehouders",
    "sg:phone":"+32 80 34 92 27",
    "sg:postcode":"4770",
    "sg:province":"Li\u00e8ge",
    "wof:name":"Michel Henkes",
    "wof:placetype":"venue"
},
  "geometry": {"coordinates":[6.1086120605,50.3356819153],"type":"Point"}
}