{
  "type": "Feature",
  "properties": {
    "addr:full":"Rue De Bruxelles 22 Fleurus Li\u00e8ge 4620",
    "addr:housenumber":"22",
    "addr:postcode":"4620",
    "addr:street":"Rue De Bruxelles",
    "iso:country":"BE",
    "sg:address":"Rue De Bruxelles 22",
    "sg:city":"Fleurus",
    "sg:orig_category":"Cr\u00e9dits divers",
    "sg:postcode":"4620",
    "sg:province":"Li\u00e8ge",
    "wof:name":"Postomat Fleurus",
    "wof:placetype":"venue"
},
  "geometry": {"coordinates":[5.6854658127,50.6180953979],"type":"Point"}
}