{
  "type": "Feature",
  "properties": {
    "iso:country":"BE",
    "sg:address":"Markt 44",
    "sg:city":"Eeklo",
    "sg:classifiers":[
        {
            "category":"Banks & Credit Unions",
            "subcategory":"Investment Brokerage",
            "type":"Services"
        }
    ],
    "sg:phone":"+32 9 377 23 79",
    "sg:postcode":"9900",
    "sg:province":"Oost-Vlaanderen",
    "sg:tags":[
        "jean",
        "casual",
        "wear"
    ],
    "wof:name":"Black Store",
    "wof:placetype":"venue"
},
  "geometry": {"coordinates":[3.5654320717,51.1848716736],"type":"Point"}
}