{
  "type": "Feature",
  "properties": {
    "iso:country":"BE",
    "sg:address":"Oud-hoflaan 23",
    "sg:city":"Kruibeke",
    "sg:orig_category":"Installatie van houten of kunststof schrijnwerk",
    "sg:phone":"+32 3 774 50 32",
    "sg:postcode":"9150",
    "sg:province":"Oost-Vlaanderen",
    "wof:name":"Sovape",
    "wof:placetype":"venue"
},
  "geometry": {"coordinates":[4.3071880341,51.1758918762],"type":"Point"}
}