{
  "type": "Feature",
  "properties": {
    "addr:full":"Bleystraat 44 Hoegaarden Vlaams-Brabant 3320",
    "addr:housenumber":"44",
    "addr:postcode":"3320",
    "addr:street":"Bleystraat",
    "iso:country":"BE",
    "sg:address":"Bleystraat 44",
    "sg:city":"Hoegaarden",
    "sg:orig_category":"M\u00e9decins and sp\u00e9cialistes",
    "sg:phone":"+32 16 76 63 71",
    "sg:postcode":"3320",
    "sg:province":"Vlaams-Brabant",
    "wof:name":"C. Delmulle",
    "wof:placetype":"venue"
},
  "geometry": {"coordinates":[4.9081878662,50.7738456726],"type":"Point"}
}