{
  "type": "Feature",
  "properties": {
    "addr:full":"Rue Bodson 119 Li\u00e8ge 1 (grivegn\u00e9e) Li\u00e8ge 4030",
    "addr:housenumber":"119;1",
    "addr:postcode":"4030",
    "addr:street":"Rue Bodson",
    "iso:country":"BE",
    "sg:address":"Rue Bodson 119",
    "sg:city":"Li\u00e8ge 1 (grivegn\u00e9e)",
    "sg:classifiers":[
        {
            "category":"Building & Trades",
            "subcategory":"Plumbing",
            "type":"Services"
        }
    ],
    "sg:phone":"+32 4 365 03 31",
    "sg:postcode":"4030",
    "sg:province":"Li\u00e8ge",
    "sg:tags":[
        "pipe",
        "drain",
        "unblocking"
    ],
    "wof:name":"Allo Sieuw",
    "wof:placetype":"venue"
},
  "geometry": {"coordinates":[5.6223678589,50.6321601868],"type":"Point"}
}