{
  "type": "Feature",
  "properties": {
    "addr:full":"Rue Du Maustichy 16 Ittre Brabant Wallon 1460",
    "addr:housenumber":"16;1460",
    "addr:street":"Rue Du Maustichy",
    "iso:country":"BE",
    "sg:address":"Rue Du Maustichy 16",
    "sg:city":"Ittre",
    "sg:classifiers":[
        {
            "category":"Health Services",
            "subcategory":"Health Practitioner",
            "type":"Services"
        }
    ],
    "sg:phone":"+32 67 64 86 89",
    "sg:postcode":"1460",
    "sg:province":"Brabant Wallon",
    "sg:tags":[
        "physiotherapist"
    ],
    "wof:name":"Remy P",
    "wof:placetype":"venue"
},
  "geometry": {"coordinates":[4.2621569633,50.6429672241],"type":"Point"}
}