{
  "type": "Feature",
  "properties": {
    "addr:full":"Tiensesteenweg 144 Glabbeek (bunsbeek) Vlaams-Brabant 3380",
    "addr:housenumber":"144",
    "addr:postcode":"3380",
    "addr:street":"Tiensesteenweg",
    "iso:country":"BE",
    "sg:address":"Tiensesteenweg 144",
    "sg:city":"Glabbeek (bunsbeek)",
    "sg:classifiers":[
        {
            "category":"Autos & Motor Vehicles",
            "subcategory":"Automobile Sales",
            "type":"Retail Goods"
        }
    ],
    "sg:phone":"+32 475 45 06 61",
    "sg:postcode":"3380",
    "sg:province":"Vlaams-Brabant",
    "sg:tags":[
        "car",
        "used",
        "-"
    ],
    "wof:name":"Benny's Cars",
    "wof:placetype":"venue"
},
  "geometry": {"coordinates":[4.9553570747,50.8616294861],"type":"Point"}
}