{
  "type": "Feature",
  "properties": {
    "addr:full":"Rue Albert Ier 154 Farciennes Hainaut 6240",
    "addr:housenumber":"154",
    "addr:postcode":"6240",
    "addr:street":"Rue Albert Ier",
    "iso:country":"BE",
    "sg:address":"Rue Albert Ier 154",
    "sg:city":"Farciennes",
    "sg:classifiers":[
        {
            "category":"Restaurant",
            "type":"Food & Drink"
        }
    ],
    "sg:phone":"+32 71 39 09 54",
    "sg:postcode":"6240",
    "sg:province":"Hainaut",
    "wof:name":"Pizza Elmas",
    "wof:placetype":"venue"
},
  "geometry": {"coordinates":[4.5516600609,50.426700592],"type":"Point"}
}