{
  "type": "Feature",
  "properties": {
    "iso:country":"BE",
    "sg:address":"Markt 27",
    "sg:city":"Maaseik",
    "sg:orig_category":"Banques and organismes de cr\u00e9dit. Cr\u00e9dit \u00e0 la consommation. Assurances habitation compagnies. Assura",
    "sg:phone":"+32 89 56 26 09",
    "sg:postcode":"3680",
    "sg:province":"Limburg",
    "wof:name":"Krediet A/d Nijverheid",
    "wof:placetype":"venue"
},
  "geometry": {"coordinates":[5.7913808823,51.0943145752],"type":"Point"}
}