{
  "type": "Feature",
  "properties": {
    "iso:country":"BE",
    "sg:address":"Rue D'aische En-refail 12",
    "sg:city":"Gembloux-sur-orneau (grand-leez)",
    "sg:classifiers":[
        {
            "category":"Shopping",
            "type":"Retail Goods"
        }
    ],
    "sg:phone":"+32 81 64 06 38",
    "sg:postcode":"5031",
    "sg:province":"Namur",
    "sg:tags":[
        "product",
        "cleaning",
        "maintenance"
    ],
    "wof:name":"Ha-ra Milis",
    "wof:placetype":"venue"
},
  "geometry": {"coordinates":[4.7762579918,50.584072113],"type":"Point"}
}