{
  "type": "Feature",
  "properties": {
    "addr:full":"Boulevard De La R\u00c9vision 67ba Anderlecht/anderlecht Bruxelles-Capitale 1070",
    "addr:housenumber":"67ba",
    "addr:postcode":"1070",
    "addr:street":"Boulevard De La Re\u0301Vision",
    "iso:country":"BE",
    "sg:address":"Boulevard De La R\u00c9vision 67ba",
    "sg:city":"Anderlecht/anderlecht",
    "sg:orig_category":"Pain, p\u00e2tisseries and confiseries",
    "sg:phone":"+32 2 521 74 14",
    "sg:postcode":"1070",
    "sg:province":"Bruxelles-Capitale",
    "wof:name":"Tempo",
    "wof:placetype":"venue"
},
  "geometry": {"coordinates":[4.3276510239,50.8356781006],"type":"Point"}
}