{
  "type": "Feature",
  "properties": {
    "iso:country":"BE",
    "sg:address":"Oostendestraat 28",
    "sg:city":"Nieuwpoort",
    "sg:classifiers":[
        {
            "category":"Utilities",
            "subcategory":"Telephone",
            "type":"Services"
        }
    ],
    "sg:phone":"+32 58 24 11 95",
    "sg:postcode":"8620",
    "sg:province":"West-Vlaanderen",
    "sg:tags":[
        "-",
        "internet"
    ],
    "wof:name":"C.i.n.s.",
    "wof:placetype":"venue"
},
  "geometry": {"coordinates":[2.7523460388,51.1323814392],"type":"Point"}
}