{
  "type": "Feature",
  "properties": {
    "addr:full":"Avenue De La Chevalerie 2a Brussel/bruxelles Bruxelles-Capitale 1000",
    "addr:housenumber":"2a",
    "addr:postcode":"1000",
    "addr:street":"Avenue De La Chevalerie;/",
    "iso:country":"BE",
    "sg:address":"Avenue De La Chevalerie 2a",
    "sg:city":"Brussel/bruxelles",
    "sg:orig_category":"Instituts de beaut\u00e9",
    "sg:phone":"+32 2 736 30 96",
    "sg:postcode":"1000",
    "sg:province":"Bruxelles-Capitale",
    "wof:name":"Francoise Deneyer",
    "wof:placetype":"venue"
},
  "geometry": {"coordinates":[4.3954381943,50.8424797058],"type":"Point"}
}