{
  "type": "Feature",
  "properties": {
    "addr:full":"Rafhay 45 Olne Li\u00e8ge 4877",
    "addr:housenumber":"45",
    "addr:postcode":"4877",
    "addr:street":"Rafhay",
    "iso:country":"BE",
    "sg:address":"Rafhay 45",
    "sg:city":"Olne",
    "sg:orig_category":"Aanleg van wegen, sportterreinen and vliegvelden Woningbouw",
    "sg:phone":"+32 4 377 41 55",
    "sg:postcode":"4877",
    "sg:province":"Li\u00e8ge",
    "wof:name":"Sacr\u00c9",
    "wof:placetype":"venue"
},
  "geometry": {"coordinates":[5.7336750031,50.6003799438],"type":"Point"}
}