{
  "type": "Feature",
  "properties": {
    "iso:country":"BE",
    "sg:address":"Jan Breydelstraat 40",
    "sg:city":"Eeklo",
    "sg:classifiers":[
        {
            "category":"Building & Trades",
            "subcategory":"Construction",
            "type":"Services"
        }
    ],
    "sg:phone":"+32 9 377 64 94",
    "sg:postcode":"9900",
    "sg:province":"Oost-Vlaanderen",
    "sg:tags":[
        "carpenter"
    ],
    "wof:name":"De Neve Woodworks",
    "wof:placetype":"venue"
},
  "geometry": {"coordinates":[3.5702340603,51.1772575378],"type":"Point"}
}