{
  "type": "Feature",
  "properties": {
    "iso:country":"BE",
    "sg:address":"Bergensesteenweg 518",
    "sg:city":"Lembeek",
    "sg:classifiers":[
        {
            "category":"Retail",
            "subcategory":"Car Wash",
            "type":"Services"
        }
    ],
    "sg:phone":"+32 2 360 10 65",
    "sg:postcode":"1502",
    "sg:province":"Vlaams-Brabant",
    "sg:tags":[
        "anti-corrosive",
        "coating"
    ],
    "wof:name":"Ferrodur S.a./n.v.",
    "wof:placetype":"venue"
},
  "geometry": {"coordinates":[4.2202701569,50.7151412964],"type":"Point"}
}