{
  "type": "Feature",
  "properties": {
    "iso:country":"BE",
    "sg:address":"Piepelpoel 21",
    "sg:city":"Tongeren",
    "sg:classifiers":[
        {
            "category":"Health Services",
            "subcategory":"Health Practitioner",
            "type":"Services"
        }
    ],
    "sg:phone":"+32 12 23 37 40",
    "sg:postcode":"3700",
    "sg:province":"Limburg",
    "sg:tags":[
        "physiotherapist"
    ],
    "wof:name":"Verjans L",
    "wof:placetype":"venue"
},
  "geometry": {"coordinates":[5.4655799866,50.7802505493],"type":"Point"}
}