{
  "type": "Feature",
  "properties": {
    "addr:full":"Driesstraat 144 Zemst (elewijt) Vlaams-Brabant 1982",
    "addr:housenumber":"144",
    "addr:postcode":"1982",
    "addr:street":"Driesstraat",
    "iso:country":"BE",
    "sg:address":"Driesstraat 144",
    "sg:city":"Zemst (elewijt)",
    "sg:classifiers":[
        {
            "category":"Freight",
            "type":"Transportation"
        }
    ],
    "sg:phone":"+32 15 61 12 51",
    "sg:postcode":"1982",
    "sg:province":"Vlaams-Brabant",
    "sg:tags":[
        "-",
        "transport"
    ],
    "wof:name":"Van Calster & Zonen Bvba",
    "wof:placetype":"venue"
},
  "geometry": {"coordinates":[4.5088758469,50.9636077881],"type":"Point"}
}