{
  "type": "Feature",
  "properties": {
    "addr:full":"Kapittelstraat 143 Ninove (appelterre-eichem) Oost-Vlaanderen 9400",
    "addr:housenumber":"143",
    "addr:postcode":"9400",
    "addr:street":"Kapittelstraat",
    "iso:country":"BE",
    "sg:address":"Kapittelstraat 143",
    "sg:city":"Ninove (appelterre-eichem)",
    "sg:classifiers":[
        {
            "category":"Food & Beverages",
            "subcategory":"Groceries & Convenience Stores",
            "type":"Retail Goods"
        }
    ],
    "sg:phone":"+32 54 33 88 88",
    "sg:postcode":"9400",
    "sg:province":"Oost-Vlaanderen",
    "sg:tags":[
        "baker",
        "-",
        "ingredient"
    ],
    "wof:name":"Castelein",
    "wof:placetype":"venue"
},
  "geometry": {"coordinates":[4.0232000351,50.8349113464],"type":"Point"}
}