{
  "type": "Feature",
  "properties": {
    "iso:country":"BE",
    "sg:address":"Rue De Houtain 17",
    "sg:city":"Oupeye",
    "sg:orig_category":"Transports routiers de marchandises",
    "sg:phone":"+32 4 286 31 42",
    "sg:postcode":"4682",
    "sg:province":"Li\u00e8ge",
    "wof:name":"Collard",
    "wof:placetype":"venue"
},
  "geometry": {"coordinates":[5.6338701248,50.7312393188],"type":"Point"}
}