{
  "type": "Feature",
  "properties": {
    "iso:country":"BE",
    "sg:address":"Albrecht Rodenbachstraat 20",
    "sg:city":"Roeselare",
    "sg:classifiers":[
        {
            "category":"Restaurant",
            "type":"Food & Drink"
        }
    ],
    "sg:phone":"+32 51 24 54 10",
    "sg:postcode":"8800",
    "sg:province":"West-Vlaanderen",
    "sg:tags":[
        "caf\u00e9s"
    ],
    "wof:name":"Taverne Foucquet",
    "wof:placetype":"venue"
},
  "geometry": {"coordinates":[3.1204879284,50.9457893372],"type":"Point"}
}