{
  "type": "Feature",
  "properties": {
    "addr:full":"Rue Du Bois D'hymi\u00c9e 23 Gerpinnes Hainaut 6280",
    "addr:housenumber":"23",
    "addr:postcode":"6280",
    "addr:street":"Rue Du Bois D'Hymie \u0301E;Hainaut",
    "iso:country":"BE",
    "sg:address":"Rue Du Bois D'hymi\u00c9e 23",
    "sg:city":"Gerpinnes",
    "sg:orig_category":"Boekhouders",
    "sg:phone":"+32 71 50 12 71",
    "sg:postcode":"6280",
    "sg:province":"Hainaut",
    "wof:name":"Dominique Deville",
    "wof:placetype":"venue"
},
  "geometry": {"coordinates":[4.5743741989,50.3304214478],"type":"Point"}
}