{
  "type": "Feature",
  "properties": {
    "addr:full":"Rue De Mortagne 65 P\u00e9ruwelz (baugnies) Hainaut 7604",
    "addr:housenumber":"65",
    "addr:postcode":"7604",
    "addr:street":"Rue De Mortagne",
    "iso:country":"BE",
    "sg:address":"Rue De Mortagne 65",
    "sg:city":"P\u00e9ruwelz (baugnies)",
    "sg:classifiers":[
        {
            "category":"Manufacturing",
            "subcategory":"Lumber",
            "type":"Manufacturing & Wholesale Goods"
        }
    ],
    "sg:phone":"+32 69 77 29 85",
    "sg:postcode":"7604",
    "sg:province":"Hainaut",
    "sg:tags":[
        "timber"
    ],
    "wof:name":"Delangre P (ets)",
    "wof:placetype":"venue"
},
  "geometry": {"coordinates":[3.5519099236,50.5615882874],"type":"Point"}
}