{
  "type": "Feature",
  "properties": {
    "addr:full":"Chauss\u00c9e De Huy 236 Chaumont-gistoux Brabant Wallon 1325",
    "addr:housenumber":"236",
    "addr:postcode":"1325",
    "addr:street":"Chausse\u0301E De Huy",
    "iso:country":"BE",
    "sg:address":"Chauss\u00c9e De Huy 236",
    "sg:city":"Chaumont-gistoux",
    "sg:classifiers":[
        {
            "category":"Insurance",
            "subcategory":"Life Insurance",
            "type":"Services"
        }
    ],
    "sg:phone":"+32 10 68 85 59",
    "sg:postcode":"1325",
    "sg:province":"Brabant Wallon",
    "sg:tags":[
        "assurance"
    ],
    "wof:name":"Gerard",
    "wof:placetype":"venue"
},
  "geometry": {"coordinates":[4.6946878433,50.6837387085],"type":"Point"}
}