{
  "type": "Feature",
  "properties": {
    "addr:full":"Rooskenstraat 34 Gent (zwijnaarde) Oost-Vlaanderen 9052",
    "addr:housenumber":"34",
    "addr:postcode":"9052",
    "addr:street":"Rooskenstraat",
    "iso:country":"BE",
    "sg:address":"Rooskenstraat 34",
    "sg:city":"Gent (zwijnaarde)",
    "sg:classifiers":[
        {
            "category":"Freight",
            "type":"Transportation"
        }
    ],
    "sg:phone":"+32 9 220 70 85",
    "sg:postcode":"9052",
    "sg:province":"Oost-Vlaanderen",
    "sg:tags":[
        "express",
        "transport"
    ],
    "wof:name":"Speedy Pussy International",
    "wof:placetype":"venue"
},
  "geometry": {"coordinates":[3.7167270184,51.0002937317],"type":"Point"}
}