{
  "type": "Feature",
  "properties": {
    "addr:full":"Westouterstraat 76 Poperinge West-Vlaanderen 8970",
    "addr:housenumber":"76",
    "addr:postcode":"8970",
    "addr:street":"Westouterstraat",
    "iso:country":"BE",
    "sg:address":"Westouterstraat 76",
    "sg:city":"Poperinge",
    "sg:orig_category":"Woningbouw",
    "sg:phone":"+32 57 33 71 18",
    "sg:postcode":"8970",
    "sg:province":"West-Vlaanderen",
    "wof:name":"Emile Deloz",
    "wof:placetype":"venue"
},
  "geometry": {"coordinates":[2.7279150486,50.845916748],"type":"Point"}
}