{
  "type": "Feature",
  "properties": {
    "iso:country":"BE",
    "sg:address":"Rue Des Martyrs 33",
    "sg:city":"Rendeux (marcourt)",
    "sg:classifiers":[
        {
            "category":"Retail",
            "subcategory":"Veterinary Services",
            "type":"Services"
        }
    ],
    "sg:phone":"+32 84 34 55 35",
    "sg:postcode":"6987",
    "sg:province":"Luxembourg",
    "sg:tags":[
        "veterinarian"
    ],
    "wof:name":"Libert S",
    "wof:placetype":"venue"
},
  "geometry": {"coordinates":[5.503636837,50.2335166931],"type":"Point"}
}