{
  "type": "Feature",
  "properties": {
    "addr:full":"Rue Des Guillemins 105 Liege Li\u00e8ge 4000",
    "addr:housenumber":"105",
    "addr:postcode":"4000",
    "addr:street":"Rue Des Guillemins",
    "iso:country":"BE",
    "sg:address":"Rue Des Guillemins 105",
    "sg:city":"Liege",
    "sg:classifiers":[
        {
            "category":"Restaurant",
            "type":"Food & Drink"
        }
    ],
    "sg:phone":"+32 4 254 36 88",
    "sg:postcode":"4000",
    "sg:province":"Li\u00e8ge",
    "wof:name":"Le Lion D'or",
    "wof:placetype":"venue"
},
  "geometry": {"coordinates":[5.5665187836,50.6265640259],"type":"Point"}
}