{
  "type": "Feature",
  "properties": {
    "addr:full":"Bld De La Sauveni\u00c8re 110bc Li\u00c8ge Li\u00e8ge 4000",
    "addr:housenumber":"110bc",
    "addr:postcode":"4000",
    "addr:street":"Bld De La Sauvenie\u0300Re",
    "iso:country":"BE",
    "sg:address":"Bld De La Sauveni\u00c8re 110bc",
    "sg:city":"Li\u00c8ge",
    "sg:orig_category":"Alternatieve geneeskunde",
    "sg:phone":"+32 475 77 49 56",
    "sg:postcode":"4000",
    "sg:province":"Li\u00e8ge",
    "wof:name":"J.l. Simonis",
    "wof:placetype":"venue"
},
  "geometry": {"coordinates":[5.5655488968,50.6425704956],"type":"Point"}
}