{
  "type": "Feature",
  "properties": {
    "addr:full":"Oostendesteenweg 270 Ichtegem West-Vlaanderen 8480",
    "addr:housenumber":"270",
    "addr:postcode":"8480",
    "addr:street":"Oostendesteenweg",
    "iso:country":"BE",
    "sg:address":"Oostendesteenweg 270",
    "sg:city":"Ichtegem",
    "sg:classifiers":[
        {
            "category":"Restaurant",
            "type":"Food & Drink"
        }
    ],
    "sg:phone":"+32 59 27 88 80",
    "sg:postcode":"8480",
    "sg:province":"West-Vlaanderen",
    "wof:name":"Restaurant Schuttershof",
    "wof:placetype":"venue"
},
  "geometry": {"coordinates":[3.0132501125,51.1129493713],"type":"Point"}
}