{
  "type": "Feature",
  "properties": {
    "addr:full":"Avenue De L'araucaria 22 Brussel/bruxelles Bruxelles-Capitale 1020",
    "addr:housenumber":"22",
    "addr:postcode":"1020",
    "addr:street":"Avenue De L'Araucaria;/",
    "iso:country":"BE",
    "sg:address":"Avenue De L'araucaria 22",
    "sg:city":"Brussel/bruxelles",
    "sg:orig_category":"V\u00e9t\u00e9rinaires",
    "sg:phone":"+32 2 268 39 51",
    "sg:postcode":"1020",
    "sg:province":"Bruxelles-Capitale",
    "wof:name":"Philippe Malevez",
    "wof:placetype":"venue"
},
  "geometry": {"coordinates":[4.3634448051,50.8943443298],"type":"Point"}
}