{
  "type": "Feature",
  "properties": {
    "addr:full":"Ravenstraat 80 Buggenhout Oost-Vlaanderen 9255",
    "addr:housenumber":"80",
    "addr:postcode":"9255",
    "addr:street":"Ravenstraat",
    "iso:country":"BE",
    "sg:address":"Ravenstraat 80",
    "sg:city":"Buggenhout",
    "sg:orig_category":"Gespecialiseerde residenti\u00eble bouw Pleisterwerk",
    "sg:phone":"+32 52 35 68 94",
    "sg:postcode":"9255",
    "sg:province":"Oost-Vlaanderen",
    "wof:name":"Jean De Nil",
    "wof:placetype":"venue"
},
  "geometry": {"coordinates":[4.1801600456,50.9934082031],"type":"Point"}
}