{
  "type": "Feature",
  "properties": {
    "iso:country":"BE",
    "sg:address":"Rue Vanderkindere 421",
    "sg:city":"Bruxelles (uccle)",
    "sg:classifiers":[
        {
            "category":"Retail",
            "subcategory":"Laundry & Dry Cleaning",
            "type":"Services"
        }
    ],
    "sg:phone":"+32 2 347 01 63",
    "sg:postcode":"1180",
    "sg:province":"Bruxelles-Capitale",
    "sg:tags":[
        "self",
        "-"
    ],
    "wof:name":"Lave-o-net",
    "wof:placetype":"venue"
},
  "geometry": {"coordinates":[4.3621320724,50.8143081665],"type":"Point"}
}