{
  "type": "Feature",
  "properties": {
    "iso:country":"BE",
    "sg:address":"Edingsesteenweg 259",
    "sg:city":"Gooik",
    "sg:classifiers":[
        {
            "category":"Bars & Pubs",
            "type":"Food & Drink"
        }
    ],
    "sg:phone":"+32 2 532 44 79",
    "sg:postcode":"1755",
    "sg:province":"Vlaams-Brabant",
    "wof:name":"Joma",
    "wof:placetype":"venue"
},
  "geometry": {"coordinates":[4.1230998039,50.7871284485],"type":"Point"}
}