{
  "type": "Feature",
  "properties": {
    "addr:full":"Rue Mazy 4 Yvoir Namur 5530",
    "addr:housenumber":"4",
    "addr:postcode":"5530",
    "addr:street":"Rue Mazy",
    "iso:country":"BE",
    "sg:address":"Rue Mazy 4",
    "sg:city":"Yvoir",
    "sg:orig_category":"Sportclubs Sportterreinen and installaties behalve sportcentra",
    "sg:phone":"+32 83 69 91 00",
    "sg:postcode":"5530",
    "sg:province":"Namur",
    "wof:name":"Union P.s.y. 88",
    "wof:placetype":"venue"
},
  "geometry": {"coordinates":[4.9737668037,50.3169441223],"type":"Point"}
}