{
  "type": "Feature",
  "properties": {
    "iso:country":"BE",
    "sg:address":"Jean D'ardennestraat 50",
    "sg:city":"Elsene/ixelles",
    "sg:orig_category":"Zalen voor culturele evenementen",
    "sg:phone":"+32 2 512 15 46",
    "sg:postcode":"1050",
    "sg:province":"Bruxelles-Capitale",
    "wof:name":"The Mc Geary Gallery",
    "wof:placetype":"venue"
},
  "geometry": {"coordinates":[4.3620419502,50.831703186],"type":"Point"}
}