{
  "type": "Feature",
  "properties": {
    "iso:country":"BE",
    "sg:address":"Rue Dupont 76",
    "sg:city":"Bruxelles (schaerbeek)",
    "sg:classifiers":[
        {
            "category":"Education",
            "subcategory":"Music School",
            "type":"Public Place"
        }
    ],
    "sg:phone":"+32 2 218 24 13",
    "sg:postcode":"1030",
    "sg:province":"Bruxelles-Capitale",
    "sg:tags":[
        "-",
        "teacher",
        "private"
    ],
    "wof:name":"Stutterheim R",
    "wof:placetype":"venue"
},
  "geometry": {"coordinates":[4.3665041924,50.8590240479],"type":"Point"}
}