{
  "type": "Feature",
  "properties": {
    "iso:country":"BE",
    "sg:address":"Breedstraat 9a",
    "sg:city":"Stekene (kemzeke)",
    "sg:classifiers":[
        {
            "category":"Freight",
            "type":"Transportation"
        }
    ],
    "sg:phone":"+32 3 779 50 77",
    "sg:postcode":"9190",
    "sg:province":"Oost-Vlaanderen",
    "sg:tags":[
        "container",
        "-",
        "transport"
    ],
    "wof:name":"Stenitra Bvba",
    "wof:placetype":"venue"
},
  "geometry": {"coordinates":[4.0430788994,51.238571167],"type":"Point"}
}