{
  "type": "Feature",
  "properties": {
    "addr:full":"Achel Statie 28 Hamont-achel Limburg 3930",
    "addr:housenumber":"28",
    "addr:postcode":"3930",
    "addr:street":"Achel Statie",
    "iso:country":"BE",
    "sg:address":"Achel Statie 28",
    "sg:city":"Hamont-achel",
    "sg:orig_category":"Immobili\u00ebnkantoren Projectontwikkelaars",
    "sg:phone":"+32 11 80 35 80",
    "sg:postcode":"3930",
    "sg:province":"Limburg",
    "wof:name":"Verberkmoes Beheer",
    "wof:placetype":"venue"
},
  "geometry": {"coordinates":[5.4723730087,51.2707977295],"type":"Point"}
}