{
  "type": "Feature",
  "properties": {
    "addr:full":"Brusselsesteenweg 572 Anderlecht (bruxelles) Bruxelles-Capitale 1070",
    "addr:housenumber":"572",
    "addr:postcode":"1070",
    "addr:street":"Brusselsesteenweg",
    "iso:country":"BE",
    "sg:address":"Brusselsesteenweg 572",
    "sg:city":"Anderlecht (bruxelles)",
    "sg:orig_category":"Onderdelen and accessoires voor auto's",
    "sg:phone":"+32 2 523 02 02",
    "sg:postcode":"1070",
    "sg:province":"Bruxelles-Capitale",
    "wof:name":"Auto M&m",
    "wof:placetype":"venue"
},
  "geometry": {"coordinates":[4.3296580315,50.8392295837],"type":"Point"}
}