{
  "type": "Feature",
  "properties": {
    "iso:country":"BE",
    "sg:address":"Rue Emile Solvay 75",
    "sg:city":"La Louviere",
    "sg:orig_category":"Diverse organisaties and verenigingen",
    "sg:phone":"+32 64 21 50 26",
    "sg:postcode":"7100",
    "sg:province":"Hainaut",
    "wof:name":"221\u00c9me Unit\u00c9 Sgp",
    "wof:placetype":"venue"
},
  "geometry": {"coordinates":[4.2003798485,50.4719657898],"type":"Point"}
}