{
  "type": "Feature",
  "properties": {
    "addr:full":"Industriepark Kolmen 1319 Alken Limburg 3570",
    "addr:housenumber":"1319",
    "addr:postcode":"3570",
    "addr:street":"Industriepark Kolmen",
    "iso:country":"BE",
    "sg:address":"Industriepark Kolmen 1319",
    "sg:city":"Alken",
    "sg:classifiers":[
        {
            "category":"Shopping",
            "subcategory":"Clothing, Apparel, & Fashions",
            "type":"Retail Goods"
        }
    ],
    "sg:phone":"+32 11 31 13 21",
    "sg:postcode":"3570",
    "sg:province":"Limburg",
    "sg:tags":[
        "textile",
        "clothing",
        "clothes"
    ],
    "wof:name":"Mopan Alken Nv",
    "wof:placetype":"venue"
},
  "geometry": {"coordinates":[5.2972297668,50.8865318298],"type":"Point"}
}