{
  "type": "Feature",
  "properties": {
    "addr:full":"Rue Salvador Allende 56 Binche Hainaut 7134",
    "addr:housenumber":"56",
    "addr:postcode":"7134",
    "addr:street":"Rue Salvador Allende",
    "iso:country":"BE",
    "sg:address":"Rue Salvador Allende 56",
    "sg:city":"Binche",
    "sg:orig_category":"Banken and kredietinstellingen",
    "sg:phone":"+32 64 33 33 09",
    "sg:postcode":"7134",
    "sg:province":"Hainaut",
    "wof:name":"Fortis",
    "wof:placetype":"venue"
},
  "geometry": {"coordinates":[4.2188978195,50.4188995361],"type":"Point"}
}