{
  "type": "Feature",
  "properties": {
    "addr:full":"Gistelsteenweg 47 Jabbeke West-Vlaanderen 8490",
    "addr:housenumber":"47",
    "addr:postcode":"8490",
    "addr:street":"Gistelsteenweg",
    "iso:country":"BE",
    "sg:address":"Gistelsteenweg 47",
    "sg:city":"Jabbeke",
    "sg:classifiers":[
        {
            "category":"Cafe",
            "type":"Food & Drink"
        }
    ],
    "sg:phone":"+32 50 39 26 25",
    "sg:postcode":"8490",
    "sg:province":"West-Vlaanderen",
    "sg:tags":[
        "caf\u00e9s"
    ],
    "wof:name":"Luc Depauw",
    "wof:placetype":"venue"
},
  "geometry": {"coordinates":[3.1111450195,51.1791343689],"type":"Point"}
}