{
  "type": "Feature",
  "properties": {
    "iso:country":"BE",
    "sg:address":"Kleine Zuidstraat 1",
    "sg:city":"Kaprijke",
    "sg:classifiers":[
        {
            "category":"Home & Garden",
            "subcategory":"Carpets & Floor Coverings",
            "type":"Retail Goods"
        }
    ],
    "sg:phone":"+32 9 373 66 42",
    "sg:postcode":"9970",
    "sg:province":"Oost-Vlaanderen",
    "sg:tags":[
        "tile"
    ],
    "wof:name":"Bouwmaterialen De Muynck Nv",
    "wof:placetype":"venue"
},
  "geometry": {"coordinates":[3.61064291,51.2152557373],"type":"Point"}
}