{
  "type": "Feature",
  "properties": {
    "addr:full":"Rue Du Tilleul 5-6 Oupeye Li\u00e8ge 4681",
    "addr:housenumber":"5-6",
    "addr:postcode":"4681",
    "addr:street":"Rue Du Tilleul",
    "iso:country":"BE",
    "sg:address":"Rue Du Tilleul 5-6",
    "sg:city":"Oupeye",
    "sg:orig_category":"Restaurants Ruimtes voor conferenties, recepties and feesten",
    "sg:phone":"+32 4 379 35 35",
    "sg:postcode":"4681",
    "sg:province":"Li\u00e8ge",
    "wof:name":"Au Comte De Mercy",
    "wof:placetype":"venue"
},
  "geometry": {"coordinates":[5.6742238998,50.7032737732],"type":"Point"}
}