{
  "type": "Feature",
  "properties": {
    "addr:full":"Smoorstraat 7 Waasmunster Oost-Vlaanderen 9250",
    "addr:housenumber":"7",
    "addr:postcode":"9250",
    "addr:street":"Smoorstraat",
    "iso:country":"BE",
    "sg:address":"Smoorstraat 7",
    "sg:city":"Waasmunster",
    "sg:classifiers":[
        {
            "category":"Home & Garden",
            "subcategory":"Carpets & Floor Coverings",
            "type":"Retail Goods"
        }
    ],
    "sg:phone":"+32 52 46 21 75",
    "sg:postcode":"9250",
    "sg:province":"Oost-Vlaanderen",
    "sg:tags":[
        "tile"
    ],
    "wof:name":"Keramiekatelier Mark Ausloos",
    "wof:placetype":"venue"
},
  "geometry": {"coordinates":[4.1245141029,51.1126098633],"type":"Point"}
}