{
  "type": "Feature",
  "properties": {
    "addr:full":"Jagerspad 4 Ham Limburg 3945",
    "addr:housenumber":"4",
    "addr:postcode":"3945",
    "addr:street":"Jagerspad",
    "iso:country":"BE",
    "sg:address":"Jagerspad 4",
    "sg:city":"Ham",
    "sg:orig_category":"Activit\u00e9s d\u00b4action sociale sans h\u00e9bergement",
    "sg:phone":"+32 11 34 31 17",
    "sg:postcode":"3945",
    "sg:province":"Limburg",
    "wof:name":"Rode Kruis Ham",
    "wof:placetype":"venue"
},
  "geometry": {"coordinates":[5.1776199341,51.1046104431],"type":"Point"}
}