{
  "type": "Feature",
  "properties": {
    "iso:country":"BE",
    "sg:address":"Visitatiestraat 3",
    "sg:city":"Gent",
    "sg:orig_category":"Hoger onderwijs",
    "sg:phone":"+32 9 228 49 10",
    "sg:postcode":"9040",
    "sg:province":"Oost-Vlaanderen",
    "wof:name":"Katholieke Hogeschool",
    "wof:placetype":"venue"
},
  "geometry": {"coordinates":[3.7485089302,51.0620193481],"type":"Point"}
}