{
  "type": "Feature",
  "properties": {
    "iso:country":"BE",
    "sg:address":"J. Tilborgstraat 87",
    "sg:city":"Kalmthout",
    "sg:orig_category":"D\u00e9molition d\u00b4immeubles and terrassements",
    "sg:phone":"+32 3 677 37 87",
    "sg:postcode":"2920",
    "sg:province":"Antwerpen",
    "wof:name":"Nouws",
    "wof:placetype":"venue"
},
  "geometry": {"coordinates":[4.5309209824,51.4371681213],"type":"Point"}
}