{
  "type": "Feature",
  "properties": {
    "iso:country":"BE",
    "sg:address":"Mee\u00ebnheide 138",
    "sg:city":"Genk",
    "sg:classifiers":[
        {
            "category":"Real Estate",
            "subcategory":"Architect",
            "type":"Services"
        }
    ],
    "sg:phone":"+32 89 30 78 05",
    "sg:postcode":"3600",
    "sg:province":"Limburg",
    "wof:name":"Loenders P",
    "wof:placetype":"venue"
},
  "geometry": {"coordinates":[5.4593248367,50.942150116],"type":"Point"}
}