{
  "type": "Feature",
  "properties": {
    "addr:full":"Rue De La For\u00eat 2 P\u00e9ruwelz (bon-secours) Hainaut 7603",
    "addr:housenumber":"2",
    "addr:postcode":"7603",
    "addr:street":"Rue De La Fore\u0302T",
    "iso:country":"BE",
    "sg:address":"Rue De La For\u00eat 2",
    "sg:city":"P\u00e9ruwelz (bon-secours)",
    "sg:classifiers":[
        {
            "category":"Health Services",
            "subcategory":"Nursing And Care Facility",
            "type":"Services"
        }
    ],
    "sg:phone":"+32 69 77 99 11",
    "sg:postcode":"7603",
    "sg:province":"Hainaut",
    "sg:tags":[
        "home",
        "rest"
    ],
    "wof:name":"Institut Notre Dame De La Mercie",
    "wof:placetype":"venue"
},
  "geometry": {"coordinates":[3.6084830761,50.4970397949],"type":"Point"}
}