{
  "type": "Feature",
  "properties": {
    "addr:full":"Rue De Saint-denis 40 La Bruy\u00c8re Namur 5080",
    "addr:housenumber":"40",
    "addr:postcode":"5080",
    "addr:street":"Rue De Saint-Denis",
    "iso:country":"BE",
    "sg:address":"Rue De Saint-denis 40",
    "sg:city":"La Bruy\u00c8re",
    "sg:orig_category":"Woningbouw",
    "sg:phone":"+32 81 56 62 22",
    "sg:postcode":"5080",
    "sg:province":"Namur",
    "wof:name":"Leclercq Ludovic",
    "wof:placetype":"venue"
},
  "geometry": {"coordinates":[4.8064007759,50.5110664368],"type":"Point"}
}