{
  "type": "Feature",
  "properties": {
    "addr:full":"Rue Des Ardennes 51 Braine-le-comte Hainaut 7090",
    "addr:housenumber":"51",
    "addr:postcode":"7090",
    "addr:street":"Rue Des Ardennes",
    "iso:country":"BE",
    "sg:address":"Rue Des Ardennes 51",
    "sg:city":"Braine-le-comte",
    "sg:orig_category":"Installation de menuiserie en bois and plastique",
    "sg:phone":"+32 67 64 73 15",
    "sg:postcode":"7090",
    "sg:province":"Hainaut",
    "wof:name":"Guy Bert",
    "wof:placetype":"venue"
},
  "geometry": {"coordinates":[4.1894102097,50.6413803101],"type":"Point"}
}