{
  "type": "Feature",
  "properties": {
    "iso:country":"BE",
    "sg:address":"Drapstraat 33",
    "sg:city":"Nazareth",
    "sg:orig_category":"Diverse metaalwaren Fab Elektrische installaties voor woningen Industri\u00eble elektrische installaties",
    "sg:phone":"+32 9 385 40 63",
    "sg:postcode":"9810",
    "sg:province":"Oost-Vlaanderen",
    "wof:name":"Callier",
    "wof:placetype":"venue"
},
  "geometry": {"coordinates":[3.5999419689,50.9598274231],"type":"Point"}
}