{
  "type": "Feature",
  "properties": {
    "addr:full":"Rue Richard-heintz 33 Nassogne Luxembourg 6950",
    "addr:housenumber":"33",
    "addr:postcode":"6950",
    "addr:street":"Rue Richard-Heintz",
    "iso:country":"BE",
    "sg:address":"Rue Richard-heintz 33",
    "sg:city":"Nassogne",
    "sg:orig_category":"Artsen and specialisten",
    "sg:phone":"+32 84 22 14 16",
    "sg:postcode":"6950",
    "sg:province":"Luxembourg",
    "wof:name":"Louis Jr. Lange",
    "wof:placetype":"venue"
},
  "geometry": {"coordinates":[5.3358159065,50.1322975159],"type":"Point"}
}