{
  "type": "Feature",
  "properties": {
    "iso:country":"BE",
    "sg:address":"Rue De Rochefort 364",
    "sg:city":"Beauraing",
    "sg:orig_category":"Mazda. V\u00e9hicules automobiles. Entretien and r\u00e9parations de voitures",
    "sg:phone":"+32 82 71 17 63",
    "sg:postcode":"5570",
    "sg:province":"Namur",
    "wof:name":"Garage Warin",
    "wof:placetype":"venue"
},
  "geometry": {"coordinates":[4.9897208214,50.1236991882],"type":"Point"}
}