{
  "type": "Feature",
  "properties": {
    "addr:full":"Rubenslei 28ba Antwerpen Antwerpen 2018",
    "addr:housenumber":"28ba",
    "addr:postcode":"2018",
    "addr:street":"Rubenslei",
    "iso:country":"BE",
    "sg:address":"Rubenslei 28ba",
    "sg:city":"Antwerpen",
    "sg:orig_category":"Diverse intermediaire producten Gh",
    "sg:phone":"+32 3 231 51 85",
    "sg:postcode":"2018",
    "sg:province":"Antwerpen",
    "wof:name":"United Gemrusa",
    "wof:placetype":"venue"
},
  "geometry": {"coordinates":[4.4111437798,51.2119178772],"type":"Point"}
}