{
  "type": "Feature",
  "properties": {
    "iso:country":"BE",
    "sg:address":"Nijverheidstraat 45",
    "sg:city":"Mechelen",
    "sg:orig_category":"Installation \u00e9lectrique industrielle. Installation \u00e9lectrique r\u00e9sidentielle",
    "sg:phone":"+32 15 55 58 41",
    "sg:postcode":"2800",
    "sg:province":"Antwerpen",
    "wof:name":"Staut",
    "wof:placetype":"venue"
},
  "geometry": {"coordinates":[4.4962778091,51.0340957642],"type":"Point"}
}