{
  "type": "Feature",
  "properties": {
    "addr:full":"Swytswal 2bc Koekelare West-Vlaanderen 8680",
    "addr:postcode":"8680",
    "iso:country":"BE",
    "sg:address":"Swytswal 2bc",
    "sg:city":"Koekelare",
    "sg:orig_category":"M\u00e9decins and sp\u00e9cialistes",
    "sg:phone":"+32 51 58 98 55",
    "sg:postcode":"8680",
    "sg:province":"West-Vlaanderen",
    "wof:name":"Marc Hemeryck",
    "wof:placetype":"venue"
},
  "geometry": {"coordinates":[2.9882390499,51.0896873474],"type":"Point"}
}