{
  "type": "Feature",
  "properties": {
    "iso:country":"BE",
    "sg:address":"Kouter 101",
    "sg:city":"Merchtem",
    "sg:orig_category":"Plomberie, chauffage and installations sanitaires",
    "sg:phone":"+32 52 37 23 59",
    "sg:postcode":"1785",
    "sg:province":"Vlaams-Brabant",
    "wof:name":"Rampelberg",
    "wof:placetype":"venue"
},
  "geometry": {"coordinates":[4.230632782,50.9783592224],"type":"Point"}
}