{
  "type": "Feature",
  "properties": {
    "iso:country":"BE",
    "sg:address":"Jubelfeestlaan 163",
    "sg:city":"Sint-jans-molenbeek/molenbeek-saint-jean",
    "sg:orig_category":"Apotheken",
    "sg:phone":"+32 2 425 81 77",
    "sg:postcode":"1080",
    "sg:province":"Bruxelles-Capitale",
    "wof:name":"Delport",
    "wof:placetype":"venue"
},
  "geometry": {"coordinates":[4.3408250809,50.8673973083],"type":"Point"}
}