{
  "type": "Feature",
  "properties": {
    "iso:country":"BE",
    "sg:address":"Rue Du Faubourg De Lille 23",
    "sg:city":"Comines-warneton",
    "sg:orig_category":"Electrom\u00e9nager, t\u00e9l\u00e9visions and radios. Mat\u00e9riel de T\u00e9l\u00e9communication",
    "sg:phone":"+32 56 55 57 63",
    "sg:postcode":"7784",
    "sg:province":"Hainaut",
    "wof:name":"Lesaffre Electro",
    "wof:placetype":"venue"
},
  "geometry": {"coordinates":[2.9414350986,50.7495651245],"type":"Point"}
}