{
  "type": "Feature",
  "properties": {
    "addr:full":"Cit\u00c9 Des Rys 53 Engis Li\u00e8ge 4480",
    "addr:housenumber":"53",
    "addr:postcode":"4480",
    "addr:street":"Cite\u0301 Des Rys",
    "iso:country":"BE",
    "sg:address":"Cit\u00c9 Des Rys 53",
    "sg:city":"Engis",
    "sg:orig_category":"Installation \u00e9lectrique r\u00e9sidentielle",
    "sg:phone":"+32 85 31 32 35",
    "sg:postcode":"4480",
    "sg:province":"Li\u00e8ge",
    "wof:name":"Daniel Melin",
    "wof:placetype":"venue"
},
  "geometry": {"coordinates":[5.4045758247,50.582069397],"type":"Point"}
}