{
  "type": "Feature",
  "properties": {
    "iso:country":"BE",
    "sg:address":"Molenstraat 18",
    "sg:city":"Dentergem",
    "sg:orig_category":"Cr\u00e8ches and garderies d'enfants",
    "sg:phone":"+32 56 60 07 28",
    "sg:postcode":"8720",
    "sg:province":"West-Vlaanderen",
    "wof:name":"Kribbe Kindermolentje",
    "wof:placetype":"venue"
},
  "geometry": {"coordinates":[3.4006829262,50.9292907715],"type":"Point"}
}