{
  "type": "Feature",
  "properties": {
    "iso:country":"BE",
    "sg:address":"Rue Nouvelle 32",
    "sg:city":"Tournai",
    "sg:orig_category":"Artsen and specialisten",
    "sg:phone":"+32 69 21 48 04",
    "sg:postcode":"7540",
    "sg:province":"Hainaut",
    "wof:name":"Carine Hinkeltz",
    "wof:placetype":"venue"
},
  "geometry": {"coordinates":[3.4185919762,50.6173095703],"type":"Point"}
}