{
  "type": "Feature",
  "properties": {
    "iso:country":"BE",
    "sg:address":"Adolf Queteletlaan 40",
    "sg:city":"Edegem",
    "sg:classifiers":[
        {
            "category":"Professional",
            "subcategory":"Management & Consulting",
            "type":"Services"
        }
    ],
    "sg:phone":"+32 3 449 30 09",
    "sg:postcode":"2650",
    "sg:province":"Antwerpen",
    "sg:tags":[
        "consultant"
    ],
    "wof:name":"Van Den Brandt M",
    "wof:placetype":"venue"
},
  "geometry": {"coordinates":[4.4233150482,51.1587715149],"type":"Point"}
}