{
  "type": "Feature",
  "properties": {
    "addr:full":"Kraaiveldstraat 5 Oostkamp (hertsberge) West-Vlaanderen 8020",
    "addr:housenumber":"5",
    "addr:postcode":"8020",
    "addr:street":"Kraaiveldstraat",
    "iso:country":"BE",
    "sg:address":"Kraaiveldstraat 5",
    "sg:city":"Oostkamp (hertsberge)",
    "sg:classifiers":[
        {
            "category":"Building & Trades",
            "subcategory":"Construction",
            "type":"Services"
        }
    ],
    "sg:phone":"+32 50 27 09 01",
    "sg:postcode":"8020",
    "sg:province":"West-Vlaanderen",
    "sg:tags":[
        "stucco",
        "contractor"
    ],
    "wof:name":"Van Belleghem K",
    "wof:placetype":"venue"
},
  "geometry": {"coordinates":[3.2350599766,51.1533241272],"type":"Point"}
}