{
  "type": "Feature",
  "properties": {
    "addr:full":"Caputsteenstraat 53 Mechelen Antwerpen 2800",
    "addr:housenumber":"53",
    "addr:postcode":"2800",
    "addr:street":"Caputsteenstraat",
    "iso:country":"BE",
    "sg:address":"Caputsteenstraat 53",
    "sg:city":"Mechelen",
    "sg:classifiers":[
        {
            "category":"Bars & Pubs",
            "subcategory":"Sports Bar",
            "type":"Food & Drink"
        }
    ],
    "sg:phone":"+32 15 55 54 61",
    "sg:postcode":"2800",
    "sg:province":"Antwerpen",
    "sg:tags":[
        "equipment",
        "beer",
        "plant"
    ],
    "wof:name":"Werkhuizen J. Verbeemen B.v.b.a.",
    "wof:placetype":"venue"
},
  "geometry": {"coordinates":[4.4909129143,51.0336227417],"type":"Point"}
}