{
  "type": "Feature",
  "properties": {
    "addr:full":"Brugstraat 50 Bree Limburg 3960",
    "addr:housenumber":"50",
    "addr:postcode":"3960",
    "addr:street":"Brugstraat",
    "iso:country":"BE",
    "sg:address":"Brugstraat 50",
    "sg:city":"Bree",
    "sg:orig_category":"M\u00e9decins and sp\u00e9cialistes",
    "sg:phone":"+32 89 46 04 04",
    "sg:postcode":"3960",
    "sg:province":"Limburg",
    "wof:name":"Jeltje Tack",
    "wof:placetype":"venue"
},
  "geometry": {"coordinates":[5.6138682365,51.1412239075],"type":"Point"}
}