{
  "type": "Feature",
  "properties": {
    "iso:country":"BE",
    "sg:address":"Brugsestraat 1",
    "sg:city":"Oostkamp",
    "sg:classifiers":[
        {
            "category":"Insurance",
            "subcategory":"Insurance Agent",
            "type":"Services"
        }
    ],
    "sg:phone":"+32 50 82 37 71",
    "sg:postcode":"8020",
    "sg:province":"West-Vlaanderen",
    "sg:tags":[
        "broker"
    ],
    "wof:name":"Meuleman-loeters Bvba",
    "wof:placetype":"venue"
},
  "geometry": {"coordinates":[3.2358300686,51.1553001404],"type":"Point"}
}