{
  "type": "Feature",
  "properties": {
    "iso:country":"BE",
    "sg:address":"Bansions 8ba",
    "sg:city":"Jalhay",
    "sg:orig_category":"Woningbouw",
    "sg:phone":"+32 87 47 44 58",
    "sg:postcode":"4845",
    "sg:province":"Li\u00e8ge",
    "wof:name":"Armand Depresseux",
    "wof:placetype":"venue"
},
  "geometry": {"coordinates":[5.9049901962,50.5258483887],"type":"Point"}
}