{
  "type": "Feature",
  "properties": {
    "addr:full":"Rue Noires-terres 7 Ecaussinnes (ecaussinnes-d'enghien) Hainaut 7190",
    "addr:housenumber":"7",
    "addr:postcode":"7190",
    "addr:street":"Rue Noires-Terres;Ecaussinnes-D'Enghien Hainaut",
    "iso:country":"BE",
    "sg:address":"Rue Noires-terres 7",
    "sg:city":"Ecaussinnes (ecaussinnes-d'enghien)",
    "sg:classifiers":[
        {
            "category":"Banks & Credit Unions",
            "subcategory":"Investment Brokerage",
            "type":"Services"
        }
    ],
    "sg:phone":"+32 67 48 58 87",
    "sg:postcode":"7190",
    "sg:province":"Hainaut",
    "sg:tags":[
        "printing",
        "-"
    ],
    "wof:name":"Urbain Imprimerie",
    "wof:placetype":"venue"
},
  "geometry": {"coordinates":[4.1673560143,50.5601043701],"type":"Point"}
}