{
  "type": "Feature",
  "properties": {
    "iso:country":"BE",
    "sg:address":"Stationsplein 0",
    "sg:city":"Roeselare",
    "sg:classifiers":[
        {
            "category":"Restaurant",
            "type":"Food & Drink"
        }
    ],
    "sg:phone":"+32 51 21 19 77",
    "sg:postcode":"8800",
    "sg:province":"West-Vlaanderen",
    "wof:name":"Stationsbuffet",
    "wof:placetype":"venue"
},
  "geometry": {"coordinates":[3.1299118996,50.9487800598],"type":"Point"}
}