{
  "type": "Feature",
  "properties": {
    "addr:full":"Eksaardserijweg 188 Oostakker Oost-Vlaanderen 9041",
    "addr:housenumber":"188",
    "addr:postcode":"9041",
    "iso:country":"BE",
    "sg:address":"Eksaardserijweg 188",
    "sg:city":"Oostakker",
    "sg:classifiers":[
        {
            "category":"Autos & Motor Vehicles",
            "subcategory":"Automobile Sales",
            "type":"Retail Goods"
        }
    ],
    "sg:phone":"+32 9 255 61 11",
    "sg:postcode":"9041",
    "sg:province":"Oost-Vlaanderen",
    "sg:tags":[
        "equipment",
        "motor-cars",
        "transport"
    ],
    "wof:name":"Volvo Information Technology Nv",
    "wof:placetype":"venue"
},
  "geometry": {"coordinates":[3.7728900909,51.0892715454],"type":"Point"}
}