{
  "type": "Feature",
  "properties": {
    "addr:full":"Diksmuidsesteenweg 335 Roeselare West-Vlaanderen 8800",
    "addr:housenumber":"335",
    "addr:postcode":"8800",
    "addr:street":"Diksmuidsesteenweg",
    "iso:country":"BE",
    "sg:address":"Diksmuidsesteenweg 335",
    "sg:city":"Roeselare",
    "sg:classifiers":[
        {
            "category":"Food & Beverages",
            "subcategory":"Fruits & Vegetables",
            "type":"Retail Goods"
        }
    ],
    "sg:phone":"+32 51 24 00 05",
    "sg:postcode":"8800",
    "sg:province":"West-Vlaanderen",
    "sg:tags":[
        "l\u00e9gumes",
        "gr"
    ],
    "wof:name":"Fa. Pacbelimex",
    "wof:placetype":"venue"
},
  "geometry": {"coordinates":[3.1132800579,50.9737586975],"type":"Point"}
}