{
  "type": "Feature",
  "properties": {
    "addr:full":"Rue De Mochamps 68 Libramont-chevigny (bras) Luxembourg 6800",
    "addr:housenumber":"68",
    "addr:postcode":"6800",
    "addr:street":"Rue De Mochamps",
    "iso:country":"BE",
    "sg:address":"Rue De Mochamps 68",
    "sg:city":"Libramont-chevigny (bras)",
    "sg:classifiers":[
        {
            "category":"Utilities",
            "subcategory":"Fuel Oil & Lpg",
            "type":"Services"
        }
    ],
    "sg:phone":"+32 61 61 27 51",
    "sg:postcode":"6800",
    "sg:province":"Luxembourg",
    "wof:name":"Flammang L\u00e9onard Sprl",
    "wof:placetype":"venue"
},
  "geometry": {"coordinates":[5.3788108826,49.9725379944],"type":"Point"}
}