{
  "type": "Feature",
  "properties": {
    "iso:country":"BE",
    "sg:address":"Zondereigen 97",
    "sg:city":"Baarle-hertog",
    "sg:orig_category":"Fruitteelt Groententeelt",
    "sg:phone":"+32 14 63 32 85",
    "sg:postcode":"2387",
    "sg:province":"Antwerpen",
    "wof:name":"Frans Cox",
    "wof:placetype":"venue"
},
  "geometry": {"coordinates":[4.8763771057,51.4092254639],"type":"Point"}
}