{
  "type": "Feature",
  "properties": {
    "addr:full":"Rue De Hiettine 19 Havelange Namur 5370",
    "addr:housenumber":"19",
    "addr:postcode":"5370",
    "addr:street":"Rue De Hiettine",
    "iso:country":"BE",
    "sg:address":"Rue De Hiettine 19",
    "sg:city":"Havelange",
    "sg:orig_category":"Installatie van houten of kunststof schrijnwerk",
    "sg:phone":"+32 83 63 41 96",
    "sg:postcode":"5370",
    "sg:province":"Namur",
    "wof:name":"Detal Philippe",
    "wof:placetype":"venue"
},
  "geometry": {"coordinates":[5.2407860756,50.3860664368],"type":"Point"}
}