{
  "type": "Feature",
  "properties": {
    "addr:full":"Grote Singel 3 Schoten Antwerpen 2900",
    "addr:housenumber":"3",
    "addr:postcode":"2900",
    "addr:street":"Grote Singel",
    "iso:country":"BE",
    "sg:address":"Grote Singel 3",
    "sg:city":"Schoten",
    "sg:orig_category":"Maisons de repos and r\u00e9sidences",
    "sg:phone":"+32 3 685 18 37",
    "sg:postcode":"2900",
    "sg:province":"Antwerpen",
    "wof:name":"Home Vergeet-mij-niet",
    "wof:placetype":"venue"
},
  "geometry": {"coordinates":[4.5152077675,51.2543029785],"type":"Point"}
}