{
  "type": "Feature",
  "properties": {
    "addr:full":"Lievevrouwestraat 30 Ranst Antwerpen 2520",
    "addr:housenumber":"30",
    "addr:postcode":"2520",
    "addr:street":"Lievevrouwestraat",
    "iso:country":"BE",
    "sg:address":"Lievevrouwestraat 30",
    "sg:city":"Ranst",
    "sg:orig_category":"Brood, gebak and snoepgoed",
    "sg:phone":"+32 3 485 52 31",
    "sg:postcode":"2520",
    "sg:province":"Antwerpen",
    "wof:name":"Norbert Pollet",
    "wof:placetype":"venue"
},
  "geometry": {"coordinates":[4.5622940063,51.1893768311],"type":"Point"}
}