{
  "type": "Feature",
  "properties": {
    "addr:full":"Rue Docteur Desire Coffee 83 La Louvi\u00e8re (str\u00e9py-bracquegnies) Hainaut 7110",
    "addr:housenumber":"83",
    "addr:postcode":"7110",
    "addr:street":"Rue Docteur;La",
    "iso:country":"BE",
    "sg:address":"Rue Docteur Desire Coffee 83",
    "sg:city":"La Louvi\u00e8re (str\u00e9py-bracquegnies)",
    "sg:classifiers":[
        {
            "category":"Retail",
            "subcategory":"Auto Repair",
            "type":"Services"
        }
    ],
    "sg:phone":"+32 64 67 32 76",
    "sg:postcode":"7110",
    "sg:province":"Hainaut",
    "sg:tags":[
        "garage"
    ],
    "wof:name":"Biccai G",
    "wof:placetype":"venue"
},
  "geometry": {"coordinates":[4.1505050659,50.4826698303],"type":"Point"}
}