{
  "type": "Feature",
  "properties": {
    "iso:country":"BE",
    "sg:address":"Rue Henry Leroy 9",
    "sg:city":"Soignies",
    "sg:orig_category":"Avocats and conseillers juridiques",
    "sg:phone":"+32 67 33 01 89",
    "sg:postcode":"7060",
    "sg:province":"Hainaut",
    "wof:name":"C. Dutry",
    "wof:placetype":"venue"
},
  "geometry": {"coordinates":[4.0708150864,50.5802879333],"type":"Point"}
}