{
  "type": "Feature",
  "properties": {
    "iso:country":"BE",
    "sg:address":"Kuipweg 40",
    "sg:city":"Oostende (zandvoorde)",
    "sg:classifiers":[
        {
            "category":"Utilities",
            "subcategory":"Recycling",
            "type":"Services"
        }
    ],
    "sg:phone":"+32 59 80 22 91",
    "sg:postcode":"8400",
    "sg:province":"West-Vlaanderen",
    "wof:name":"Recyc West Cvba",
    "wof:placetype":"venue"
},
  "geometry": {"coordinates":[2.9818000793,51.2081985474],"type":"Point"}
}