{
  "type": "Feature",
  "properties": {
    "addr:full":"Koolkerkesteenweg 3 Damme West-Vlaanderen 8340",
    "addr:housenumber":"3",
    "addr:postcode":"8340",
    "addr:street":"Koolkerkesteenweg",
    "iso:country":"BE",
    "sg:address":"Koolkerkesteenweg 3",
    "sg:city":"Damme",
    "sg:orig_category":"Immobili\u00ebnkantoren",
    "sg:phone":"+32 50 33 72 71",
    "sg:postcode":"8340",
    "sg:province":"West-Vlaanderen",
    "wof:name":"Bureau Garbo",
    "wof:placetype":"venue"
},
  "geometry": {"coordinates":[3.2815999985,51.2513160706],"type":"Point"}
}