{
  "type": "Feature",
  "properties": {
    "addr:full":"Silvesterdennenlaan 11 Malle (oostmalle) Antwerpen 2390",
    "addr:housenumber":"11",
    "addr:postcode":"2390",
    "addr:street":"Silvesterdennenlaan",
    "iso:country":"BE",
    "sg:address":"Silvesterdennenlaan 11",
    "sg:city":"Malle (oostmalle)",
    "sg:classifiers":[
        {
            "category":"Real Estate",
            "subcategory":"Architect",
            "type":"Services"
        }
    ],
    "sg:phone":"+32 3 312 30 54",
    "sg:postcode":"2390",
    "sg:province":"Antwerpen",
    "wof:name":"Verhamme P",
    "wof:placetype":"venue"
},
  "geometry": {"coordinates":[4.7362070084,51.2921676636],"type":"Point"}
}