{
  "type": "Feature",
  "properties": {
    "addr:full":"Gare Autorouti\u00e8re La Louvi\u00e8re (houdeng-goegnies) Hainaut 7110",
    "addr:postcode":"7110",
    "iso:country":"BE",
    "sg:address":"Gare Autorouti\u00e8re",
    "sg:city":"La Louvi\u00e8re (houdeng-goegnies)",
    "sg:classifiers":[
        {
            "category":"Travel",
            "subcategory":"Hotels & Motels",
            "type":"Entertainment"
        }
    ],
    "sg:phone":"+32 64 66 44 44",
    "sg:postcode":"7110",
    "sg:province":"Hainaut",
    "wof:name":"Akena",
    "wof:placetype":"venue"
},
  "geometry": {"coordinates":[4.1505050659,50.4826698303],"type":"Point"}
}