{
  "type": "Feature",
  "properties": {
    "addr:full":"Steenweg Op Edingen 105 Tubeke Brabant Wallon 1480",
    "addr:housenumber":"105",
    "addr:postcode":"1480",
    "addr:street":"Steenweg Op Edingen;Wallon",
    "iso:country":"BE",
    "sg:address":"Steenweg Op Edingen 105",
    "sg:city":"Tubeke",
    "sg:orig_category":"Meubelzaken, woning- and keukeninrichting",
    "sg:postcode":"1480",
    "sg:province":"Brabant Wallon",
    "wof:name":"Belgica",
    "wof:placetype":"venue"
},
  "geometry": {"coordinates":[4.204308033,50.6932029724],"type":"Point"}
}