{
  "type": "Feature",
  "properties": {
    "addr:full":"Kl\u00d6tzerbahn 8 Eupen Li\u00e8ge 4700",
    "addr:housenumber":"8",
    "addr:postcode":"4700",
    "addr:street":"Kloetzerbahn",
    "iso:country":"BE",
    "sg:address":"Kl\u00d6tzerbahn 8",
    "sg:city":"Eupen",
    "sg:orig_category":"Dranken",
    "sg:phone":"+32 87 56 14 06",
    "sg:postcode":"4700",
    "sg:province":"Li\u00e8ge",
    "wof:name":"Haus Panta",
    "wof:placetype":"venue"
},
  "geometry": {"coordinates":[6.0338931084,50.6303901672],"type":"Point"}
}