{
  "type": "Feature",
  "properties": {
    "addr:full":"Schouwburgplein 8 Kortrijk West-Vlaanderen 8500",
    "addr:housenumber":"8",
    "addr:postcode":"8500",
    "addr:street":"Schouwburgplein",
    "iso:country":"BE",
    "sg:address":"Schouwburgplein 8",
    "sg:city":"Kortrijk",
    "sg:classifiers":[
        {
            "category":"Professional",
            "subcategory":"Employment Agencies",
            "type":"Services"
        }
    ],
    "sg:phone":"+32 56 23 41 23",
    "sg:postcode":"8500",
    "sg:province":"West-Vlaanderen",
    "sg:tags":[
        "temping",
        "clerical",
        "-"
    ],
    "wof:name":"Accent Jobs For People",
    "wof:placetype":"venue"
},
  "geometry": {"coordinates":[3.265599966,50.8255310059],"type":"Point"}
}