{
  "type": "Feature",
  "properties": {
    "addr:full":"Fabriekstraat 23 Neerpelt Limburg 3910",
    "addr:housenumber":"23",
    "addr:postcode":"3910",
    "addr:street":"Fabriekstraat",
    "iso:country":"BE",
    "sg:address":"Fabriekstraat 23",
    "sg:city":"Neerpelt",
    "sg:orig_category":"Artsen and specialisten",
    "sg:phone":"+32 11 64 15 00",
    "sg:postcode":"3910",
    "sg:province":"Limburg",
    "wof:name":"M. Oversteyns",
    "wof:placetype":"venue"
},
  "geometry": {"coordinates":[5.4263648987,51.2297401428],"type":"Point"}
}