{
  "type": "Feature",
  "properties": {
    "addr:full":"Marais Gauquier 13a Frasnes-lez-anvaing (frasnes - Lez - Buissenal) Hainaut 7911",
    "addr:housenumber":"13a",
    "addr:postcode":"7911",
    "addr:street":"Gauquier",
    "iso:country":"BE",
    "sg:address":"Marais Gauquier 13a",
    "sg:city":"Frasnes-lez-anvaing (frasnes - Lez - Buissenal)",
    "sg:classifiers":[
        {
            "category":"Retail",
            "subcategory":"Auto Repair",
            "type":"Services"
        }
    ],
    "sg:phone":"+32 69 86 64 61",
    "sg:postcode":"7911",
    "sg:province":"Hainaut",
    "sg:tags":[
        "automobile-body"
    ],
    "wof:name":"Masure Carrosserie",
    "wof:placetype":"venue"
},
  "geometry": {"coordinates":[3.6166539192,50.6697273254],"type":"Point"}
}