{
  "type": "Feature",
  "properties": {
    "iso:country":"BE",
    "sg:address":"Coquilhatstraat 37",
    "sg:city":"Antwerpen",
    "sg:orig_category":"HUISBRANDOLIE Kruideniers",
    "sg:phone":"+32 3 238 67 36",
    "sg:postcode":"2000",
    "sg:province":"Antwerpen",
    "wof:name":"Roger Bruyndoncx",
    "wof:placetype":"venue"
},
  "geometry": {"coordinates":[4.3978819847,51.2092971802],"type":"Point"}
}