{
  "type": "Feature",
  "properties": {
    "addr:full":"Langestraat 86 Brugge West-Vlaanderen 8000",
    "addr:housenumber":"86",
    "addr:postcode":"8000",
    "addr:street":"Langestraat",
    "iso:country":"BE",
    "sg:address":"Langestraat 86",
    "sg:city":"Brugge",
    "sg:orig_category":"Non-Classified Establishments",
    "sg:phone":"+32 50 34 33 97",
    "sg:postcode":"8000",
    "sg:province":"West-Vlaanderen",
    "wof:name":"Viane Kaarsen",
    "wof:placetype":"venue"
},
  "geometry": {"coordinates":[3.2358329296,51.2105865479],"type":"Point"}
}