{
  "type": "Feature",
  "properties": {
    "iso:country":"BE",
    "sg:address":"Rue De Matagne 53",
    "sg:city":"Philippeville",
    "sg:orig_category":"Rundveehouders",
    "sg:phone":"+32 71 66 64 09",
    "sg:postcode":"5600",
    "sg:province":"Namur",
    "wof:name":"Groux Rene & Francine",
    "wof:placetype":"venue"
},
  "geometry": {"coordinates":[4.5811371803,50.1441078186],"type":"Point"}
}