{
  "type": "Feature",
  "properties": {
    "addr:full":"Tieltstraat 57 Wingene West-Vlaanderen 8750",
    "addr:housenumber":"57",
    "addr:postcode":"8750",
    "addr:street":"Tieltstraat",
    "iso:country":"BE",
    "sg:address":"Tieltstraat 57",
    "sg:city":"Wingene",
    "sg:classifiers":[
        {
            "category":"Wholesale",
            "subcategory":"Hardware",
            "type":"Manufacturing & Wholesale Goods"
        }
    ],
    "sg:phone":"+32 50 38 26 93",
    "sg:postcode":"8750",
    "sg:province":"West-Vlaanderen",
    "sg:tags":[
        "lubricating",
        "compound"
    ],
    "wof:name":"Detavernier Nv",
    "wof:placetype":"venue"
},
  "geometry": {"coordinates":[3.2856040001,51.0550537109],"type":"Point"}
}