{
  "type": "Feature",
  "properties": {
    "iso:country":"BE",
    "sg:address":"Rue Gallait 149",
    "sg:city":"Schaarbeek/schaerbeek",
    "sg:orig_category":"Poissonniers and \u00e9caillers",
    "sg:phone":"+32 2 241 35 32",
    "sg:postcode":"1030",
    "sg:province":"Bruxelles-Capitale",
    "wof:name":"Mohamed Bouassab",
    "wof:placetype":"venue"
},
  "geometry": {"coordinates":[4.3714227676,50.8693885803],"type":"Point"}
}