{
  "type": "Feature",
  "properties": {
    "iso:country":"BE",
    "sg:address":"Houtmarkt 15",
    "sg:city":"Sint-truiden",
    "sg:classifiers":[
        {
            "category":"Health Services",
            "subcategory":"Optometrist",
            "type":"Services"
        }
    ],
    "sg:phone":"+32 11 68 98 72",
    "sg:postcode":"3800",
    "sg:province":"Limburg",
    "wof:name":"Vanderschot J",
    "wof:placetype":"venue"
},
  "geometry": {"coordinates":[5.190155983,50.8168754578],"type":"Point"}
}