{
  "type": "Feature",
  "properties": {
    "addr:full":"Willem Herreynsstraat 43 Mechelen Antwerpen 2800",
    "addr:housenumber":"43",
    "addr:postcode":"2800",
    "addr:street":"Willem Herreynsstraat",
    "iso:country":"BE",
    "sg:address":"Willem Herreynsstraat 43",
    "sg:city":"Mechelen",
    "sg:orig_category":"Boekhouders",
    "sg:phone":"+32 15 41 75 93",
    "sg:postcode":"2800",
    "sg:province":"Antwerpen",
    "wof:name":"Christian Boute",
    "wof:placetype":"venue"
},
  "geometry": {"coordinates":[4.477312088,51.0186729431],"type":"Point"}
}