{
  "type": "Feature",
  "properties": {
    "addr:full":"Rue Sylvain Guyaux 55 La Louvi\u00c8re Hainaut 7100",
    "addr:housenumber":"55",
    "addr:postcode":"7100",
    "addr:street":"Rue Sylvain Guyaux",
    "iso:country":"BE",
    "sg:address":"Rue Sylvain Guyaux 55",
    "sg:city":"La Louvi\u00c8re",
    "sg:classifiers":[
        {
            "category":"Shopping",
            "subcategory":"Clothing, Apparel, & Fashions",
            "type":"Retail Goods"
        }
    ],
    "sg:phone":"+32 64 21 53 79",
    "sg:postcode":"7100",
    "sg:province":"Hainaut",
    "sg:tags":[
        "ondergoed",
        "lingerie"
    ],
    "wof:name":"Damart",
    "wof:placetype":"venue"
},
  "geometry": {"coordinates":[4.1835808754,50.4757118225],"type":"Point"}
}