{
  "type": "Feature",
  "properties": {
    "addr:full":"Avenue Du Ch\u00e2teau 23 Box 8 Bruxelles (molenbeek-saint-jean) Bruxelles-Capitale 1080",
    "addr:housenumber":"23;8",
    "addr:postcode":"1080",
    "addr:street":"Avenue Du Cha\u0302Teau;Box",
    "iso:country":"BE",
    "sg:address":"Avenue Du Ch\u00e2teau 23 Box 8",
    "sg:city":"Bruxelles (molenbeek-saint-jean)",
    "sg:classifiers":[
        {
            "category":"Professional",
            "subcategory":"Accounting & Tax Preparation",
            "type":"Services"
        }
    ],
    "sg:phone":"+32 2 414 25 62",
    "sg:postcode":"1080",
    "sg:province":"Bruxelles-Capitale",
    "sg:tags":[
        "bookkeeper"
    ],
    "wof:name":"Od Belgium Scris",
    "wof:placetype":"venue"
},
  "geometry": {"coordinates":[4.3134832382,50.86302948],"type":"Point"}
}