{
  "type": "Feature",
  "properties": {
    "addr:full":"Rue Du Parc 46 Ans Li\u00e8ge 4432",
    "addr:housenumber":"46",
    "addr:postcode":"4432",
    "addr:street":"Rue Du Parc",
    "iso:country":"BE",
    "sg:address":"Rue Du Parc 46",
    "sg:city":"Ans",
    "sg:orig_category":"Herstellingen and onderhoud van auto's",
    "sg:phone":"+32 4 247 17 90",
    "sg:postcode":"4432",
    "sg:province":"Li\u00e8ge",
    "wof:name":"Car Lifting",
    "wof:placetype":"venue"
},
  "geometry": {"coordinates":[5.5270237923,50.6819534302],"type":"Point"}
}