{
  "type": "Feature",
  "properties": {
    "iso:country":"BE",
    "sg:address":"Statiestraat 46-48",
    "sg:city":"Lint",
    "sg:classifiers":[
        {
            "category":"Retail",
            "subcategory":"Veterinary Services",
            "type":"Services"
        }
    ],
    "sg:phone":"+32 3 455 48 00",
    "sg:postcode":"2547",
    "sg:province":"Antwerpen",
    "sg:tags":[
        "veterinarian"
    ],
    "wof:name":"Eulaers C",
    "wof:placetype":"venue"
},
  "geometry": {"coordinates":[4.4973111153,51.1291275024],"type":"Point"}
}