{
  "type": "Feature",
  "properties": {
    "addr:full":"Defacqzstr 1 Bus 11 Brussel Bruxelles-Capitale 1000",
    "addr:housenumber":"1 bus 11",
    "addr:postcode":"1000",
    "addr:street":"Defacqzstr",
    "iso:country":"BE",
    "sg:address":"Defacqzstr 1 Bus 11",
    "sg:city":"Brussel",
    "sg:classifiers":[
        {
            "category":"Professional",
            "subcategory":"Business Services",
            "type":"Services"
        }
    ],
    "sg:phone":"+32 2 536 08 80",
    "sg:postcode":"1000",
    "sg:province":"Bruxelles-Capitale",
    "sg:tags":[
        "training",
        "advice"
    ],
    "wof:name":"Institut Intern Des Sciences Administratives Iwob",
    "wof:placetype":"venue"
},
  "geometry": {"coordinates":[4.3611187935,50.8287887573],"type":"Point"}
}