{
  "type": "Feature",
  "properties": {
    "addr:full":"Vilvoordelaan 153a Zaventem Vlaams-Brabant 1930",
    "addr:housenumber":"153a",
    "addr:postcode":"1930",
    "addr:street":"Vilvoordelaan",
    "iso:country":"BE",
    "sg:address":"Vilvoordelaan 153a",
    "sg:city":"Zaventem",
    "sg:classifiers":[
        {
            "category":"Airline",
            "type":"Transportation"
        }
    ],
    "sg:phone":"+32 2 712 64 21",
    "sg:postcode":"1930",
    "sg:province":"Vlaams-Brabant",
    "wof:name":"B.w.i.a.",
    "wof:placetype":"venue"
},
  "geometry": {"coordinates":[4.4713082314,50.8933067322],"type":"Point"}
}