{
  "type": "Feature",
  "properties": {
    "addr:full":"Heidebloemstraat 261 Sint-niklaas Oost-Vlaanderen 9100",
    "addr:housenumber":"261",
    "addr:postcode":"9100",
    "addr:street":"Heidebloemstraat",
    "iso:country":"BE",
    "sg:address":"Heidebloemstraat 261",
    "sg:city":"Sint-niklaas",
    "sg:classifiers":[
        {
            "category":"Taxi",
            "type":"Transportation"
        }
    ],
    "sg:phone":"+32 3770707",
    "sg:postcode":"9100",
    "sg:province":"Oost-Vlaanderen",
    "sg:tags":[
        "taxi's"
    ],
    "wof:name":"'t Pleintje",
    "wof:placetype":"venue"
},
  "geometry": {"coordinates":[4.1405391693,51.17578125],"type":"Point"}
}