{
  "type": "Feature",
  "properties": {
    "addr:full":"Oostkaai 25/6 Merksem Antwerpen 2170",
    "addr:housenumber":"25 / 6",
    "addr:postcode":"2170",
    "addr:street":"Oostkaai",
    "iso:country":"BE",
    "sg:address":"Oostkaai 25/6",
    "sg:city":"Merksem",
    "sg:classifiers":[
        {
            "category":"Professional",
            "subcategory":"Engineering",
            "type":"Services"
        }
    ],
    "sg:phone":"+32 3 645 25 10",
    "sg:postcode":"2170",
    "sg:province":"Antwerpen",
    "sg:tags":[
        "machine",
        "-",
        "environment",
        "equipment",
        "machinery",
        "mechanical"
    ],
    "wof:name":"Saval Nv",
    "wof:placetype":"venue"
},
  "geometry": {"coordinates":[4.4507780075,51.2395515442],"type":"Point"}
}