{
  "type": "Feature",
  "properties": {
    "addr:full":"Oostmoerstraat 1 Jabbeke (snellegem) West-Vlaanderen 8490",
    "addr:housenumber":"1",
    "addr:postcode":"8490",
    "addr:street":"Oostmoerstraat",
    "iso:country":"BE",
    "sg:address":"Oostmoerstraat 1",
    "sg:city":"Jabbeke (snellegem)",
    "sg:classifiers":[
        {
            "category":"Retail",
            "subcategory":"Event Space",
            "type":"Services"
        }
    ],
    "sg:phone":"+32 50 81 16 53",
    "sg:postcode":"8490",
    "sg:province":"West-Vlaanderen",
    "sg:tags":[
        "rental",
        "-",
        "hall"
    ],
    "wof:name":"'t Oosthof",
    "wof:placetype":"venue"
},
  "geometry": {"coordinates":[3.1234929562,51.1688041687],"type":"Point"}
}