{
  "type": "Feature",
  "properties": {
    "iso:country":"BE",
    "sg:address":"Diestsesteenweg 209bb1",
    "sg:city":"Lubbeek",
    "sg:orig_category":"Evaluation and estimation de biens immobiliers",
    "sg:phone":"+32 16 62 02 21",
    "sg:postcode":"3210",
    "sg:province":"Vlaams-Brabant",
    "wof:name":"Studiebureau Art",
    "wof:placetype":"venue"
},
  "geometry": {"coordinates":[4.8095397949,50.8933792114],"type":"Point"}
}