{
  "type": "Feature",
  "properties": {
    "iso:country":"BE",
    "sg:address":"Kloosterstraat 44",
    "sg:city":"Wuustwezel",
    "sg:orig_category":"Electrom\u00e9nager, t\u00e9l\u00e9visions and radios. Installation \u00e9lectrique r\u00e9sidentielle",
    "sg:phone":"+32 3 669 76 76",
    "sg:postcode":"2990",
    "sg:province":"Antwerpen",
    "wof:name":"Bevers-van Den Keybus",
    "wof:placetype":"venue"
},
  "geometry": {"coordinates":[4.5972242355,51.3920936584],"type":"Point"}
}