{
  "type": "Feature",
  "properties": {
    "iso:country":"BE",
    "sg:address":"Kerkbaan 1",
    "sg:city":"Wichelen (groot)",
    "sg:orig_category":"Textiel Verlichting and huishoudartikelen",
    "sg:phone":"+32 52 42 39 11",
    "sg:postcode":"9260",
    "sg:province":"Oost-Vlaanderen",
    "wof:name":"De Schrijver",
    "wof:placetype":"venue"
},
  "geometry": {"coordinates":[3.9752130508,51.0060386658],"type":"Point"}
}