{
  "type": "Feature",
  "properties": {
    "iso:country":"BE",
    "sg:address":"Quai Des Salines 35",
    "sg:city":"Tournai",
    "sg:orig_category":"M\u00e9decins and sp\u00e9cialistes",
    "sg:phone":"+32 69 84 50 51",
    "sg:postcode":"7500",
    "sg:province":"Hainaut",
    "wof:name":"Anne Doyen",
    "wof:placetype":"venue"
},
  "geometry": {"coordinates":[3.3834331036,50.612323761],"type":"Point"}
}