{
  "type": "Feature",
  "properties": {
    "addr:full":"Bredabaan 1209 Schoten Antwerpen 2900",
    "addr:housenumber":"1209",
    "addr:postcode":"2900",
    "addr:street":"Bredabaan",
    "iso:country":"BE",
    "sg:address":"Bredabaan 1209",
    "sg:city":"Schoten",
    "sg:classifiers":[
        {
            "category":"Autos & Motor Vehicles",
            "subcategory":"Automobile Sales",
            "type":"Retail Goods"
        }
    ],
    "sg:phone":"+32 3 640 39 39",
    "sg:postcode":"2900",
    "sg:province":"Antwerpen",
    "sg:tags":[
        "car",
        "used",
        "-"
    ],
    "wof:name":"Antwerpen Motors Bvba",
    "wof:placetype":"venue"
},
  "geometry": {"coordinates":[4.4634890556,51.264995575],"type":"Point"}
}