{
  "type": "Feature",
  "properties": {
    "iso:country":"BE",
    "sg:address":"Rue Ren\u00e9 Nicolas 27",
    "sg:city":"Musson",
    "sg:classifiers":[
        {
            "category":"Personal",
            "subcategory":"Beauty Salon",
            "type":"Services"
        }
    ],
    "sg:phone":"+32 63 67 75 87",
    "sg:postcode":"6750",
    "sg:province":"Luxembourg",
    "sg:tags":[
        "lady",
        "-",
        "hairdressing"
    ],
    "wof:name":"Jeanine",
    "wof:placetype":"venue"
},
  "geometry": {"coordinates":[5.7088608742,49.5590629578],"type":"Point"}
}