{
  "type": "Feature",
  "properties": {
    "addr:full":"Vijverstraat 42 Geetbets Vlaams-Brabant 3450",
    "addr:housenumber":"42",
    "addr:postcode":"3450",
    "addr:street":"Vijverstraat",
    "iso:country":"BE",
    "sg:address":"Vijverstraat 42",
    "sg:city":"Geetbets",
    "sg:orig_category":"Banken and kredietinstellingen",
    "sg:phone":"+32 11 58 75 89",
    "sg:postcode":"3450",
    "sg:province":"Vlaams-Brabant",
    "wof:name":"Landbouwkrediet",
    "wof:placetype":"venue"
},
  "geometry": {"coordinates":[5.1254792213,50.8728866577],"type":"Point"}
}