{
  "type": "Feature",
  "properties": {
    "addr:full":"Bedrijfsstraat 7 Peer (grote Brogel) Limburg 3990",
    "addr:housenumber":"7",
    "addr:postcode":"3990",
    "addr:street":"Bedrijfsstraat;Grote Brogel Limburg",
    "iso:country":"BE",
    "sg:address":"Bedrijfsstraat 7",
    "sg:city":"Peer (grote Brogel)",
    "sg:classifiers":[
        {
            "category":"Autos & Motor Vehicles",
            "subcategory":"Automobile Sales",
            "type":"Retail Goods"
        }
    ],
    "sg:phone":"+32 11 61 16 70",
    "sg:postcode":"3990",
    "sg:province":"Limburg",
    "sg:tags":[
        "delivery",
        "-",
        "used",
        "van",
        "truck"
    ],
    "wof:name":"Brouns Patrick",
    "wof:placetype":"venue"
},
  "geometry": {"coordinates":[5.503631115,51.1378555298],"type":"Point"}
}