{
  "type": "Feature",
  "properties": {
    "iso:country":"BE",
    "sg:address":"Paalsteen 4",
    "sg:city":"Sint-martens-latem",
    "sg:classifiers":[
        {
            "category":"Health Services",
            "subcategory":"Doctor",
            "type":"Services"
        }
    ],
    "sg:phone":"+32 9 281 25 45",
    "sg:postcode":"9830",
    "sg:province":"Oost-Vlaanderen",
    "sg:tags":[
        "medicinephysicians",
        "surgeon"
    ],
    "wof:name":"De Smedt Roselyne",
    "wof:placetype":"venue"
},
  "geometry": {"coordinates":[3.6240849495,51.0075912476],"type":"Point"}
}