{
  "type": "Feature",
  "properties": {
    "iso:country":"BE",
    "sg:address":"Lange Lobroekstraat 69",
    "sg:city":"Antwerpen",
    "sg:classifiers":[
        {
            "category":"Food & Beverages",
            "subcategory":"Meat & Fish",
            "type":"Retail Goods"
        }
    ],
    "sg:phone":"+32 3 271 05 84",
    "sg:postcode":"2060",
    "sg:province":"Antwerpen",
    "sg:tags":[
        "poultry",
        "whol",
        "game",
        "-"
    ],
    "wof:name":"De Poelier",
    "wof:placetype":"venue"
},
  "geometry": {"coordinates":[4.4321370125,51.2293357849],"type":"Point"}
}