{
  "type": "Feature",
  "properties": {
    "addr:full":"Boulevard Dolez 22 Mons Hainaut 7000",
    "addr:housenumber":"22",
    "addr:postcode":"7000",
    "addr:street":"Boulevard Dolez;Hainaut",
    "iso:country":"BE",
    "sg:address":"Boulevard Dolez 22",
    "sg:city":"Mons",
    "sg:orig_category":"Groenten and fruit Gh",
    "sg:phone":"+32 65 31 67 30",
    "sg:postcode":"7000",
    "sg:province":"Hainaut",
    "wof:name":"Luc Op De Beeck",
    "wof:placetype":"venue"
},
  "geometry": {"coordinates":[3.9583508968,50.4518966675],"type":"Point"}
}