{
  "type": "Feature",
  "properties": {
    "iso:country":"BE",
    "sg:address":"Rue Du Centre 51",
    "sg:city":"Pepinster",
    "sg:classifiers":[
        {
            "category":"Fast Food",
            "type":"Food & Drink"
        }
    ],
    "sg:phone":"+32 87 46 03 55",
    "sg:postcode":"4861",
    "sg:province":"Li\u00e8ge",
    "sg:tags":[
        "\u00c0",
        "restaurants",
        "emporter",
        "restaurant"
    ],
    "wof:name":"Restaurant Vieux Soiron",
    "wof:placetype":"venue"
},
  "geometry": {"coordinates":[5.7906870842,50.5916099548],"type":"Point"}
}