{
  "type": "Feature",
  "properties": {
    "addr:full":"Augustijnenstraat 5 Mechelen Antwerpen 2800",
    "addr:housenumber":"5",
    "addr:postcode":"2800",
    "addr:street":"Augustijnenstraat",
    "iso:country":"BE",
    "sg:address":"Augustijnenstraat 5",
    "sg:city":"Mechelen",
    "sg:orig_category":"M\u00e9decins and sp\u00e9cialistes",
    "sg:phone":"+32 15 21 29 95",
    "sg:postcode":"2800",
    "sg:province":"Antwerpen",
    "wof:name":"W. Haenen",
    "wof:placetype":"venue"
},
  "geometry": {"coordinates":[4.4854068756,51.0278320312],"type":"Point"}
}