{
  "type": "Feature",
  "properties": {
    "addr:full":"Vaartstraat 54 Geel Antwerpen 2440",
    "addr:housenumber":"54",
    "addr:postcode":"2440",
    "addr:street":"Vaartstraat",
    "iso:country":"BE",
    "sg:address":"Vaartstraat 54",
    "sg:city":"Geel",
    "sg:orig_category":"Krantenwinkels Rookartikelen",
    "sg:phone":"+32 14 85 27 01",
    "sg:postcode":"2440",
    "sg:province":"Antwerpen",
    "wof:name":"Etiket",
    "wof:placetype":"venue"
},
  "geometry": {"coordinates":[4.979142189,51.2034835815],"type":"Point"}
}