{
  "type": "Feature",
  "properties": {
    "addr:full":"Berkenhoekstraat 20 Sint-katelijne-waver Antwerpen 2861",
    "addr:housenumber":"20",
    "addr:postcode":"2861",
    "addr:street":"Berkenhoekstraat",
    "iso:country":"BE",
    "sg:address":"Berkenhoekstraat 20",
    "sg:city":"Sint-katelijne-waver",
    "sg:orig_category":"G\u00e2teaux, p\u00e2tisserie and biscuits Fab",
    "sg:phone":"+32 15 76 09 61",
    "sg:postcode":"2861",
    "sg:province":"Antwerpen",
    "wof:name":"Vicki Biscuits",
    "wof:placetype":"venue"
},
  "geometry": {"coordinates":[4.567440033,51.0541114807],"type":"Point"}
}