{
  "type": "Feature",
  "properties": {
    "iso:country":"BE",
    "sg:address":"Limburgerstrasse 71ba",
    "sg:city":"Lontzen/lontzen",
    "sg:orig_category":"Schoonheidssalons",
    "sg:phone":"+32 87 88 20 72",
    "sg:postcode":"4710",
    "sg:province":"Li\u00e8ge",
    "wof:name":"Maria Marichal",
    "wof:placetype":"venue"
},
  "geometry": {"coordinates":[5.9936881065,50.6608695984],"type":"Point"}
}