{
  "type": "Feature",
  "properties": {
    "iso:country":"BE",
    "sg:address":"Rue Des Campeaux 16",
    "sg:city":"Tournai",
    "sg:classifiers":[
        {
            "category":"Professional",
            "subcategory":"Lawyer & Legal Services",
            "type":"Services"
        }
    ],
    "sg:phone":"+32 69 84 83 56",
    "sg:postcode":"7500",
    "sg:province":"Hainaut",
    "wof:name":"Delhaye E",
    "wof:placetype":"venue"
},
  "geometry": {"coordinates":[3.393050909,50.6076087952],"type":"Point"}
}