{
  "type": "Feature",
  "properties": {
    "iso:country":"BE",
    "sg:address":"Avenue Des Combattants 94",
    "sg:city":"Dinant",
    "sg:orig_category":"Maisons de vacances",
    "sg:phone":"+32 3 636 35 85",
    "sg:postcode":"5500",
    "sg:province":"Namur",
    "wof:name":"H.croisier",
    "wof:placetype":"venue"
},
  "geometry": {"coordinates":[4.9146971703,50.2520294189],"type":"Point"}
}