{
  "type": "Feature",
  "properties": {
    "addr:full":"Oreyebergstraat 9 Heers Limburg 3870",
    "addr:housenumber":"9",
    "addr:postcode":"3870",
    "addr:street":"Oreyebergstraat",
    "iso:country":"BE",
    "sg:address":"Oreyebergstraat 9",
    "sg:city":"Heers",
    "sg:classifiers":[
        {
            "category":"Personal",
            "subcategory":"Beauty Salon",
            "type":"Services"
        }
    ],
    "sg:phone":"+32 11 48 58 34",
    "sg:postcode":"3870",
    "sg:province":"Limburg",
    "sg:tags":[
        "de",
        "coiffure"
    ],
    "wof:name":"Martine Lemmens",
    "wof:placetype":"venue"
},
  "geometry": {"coordinates":[5.3359532356,50.7580490112],"type":"Point"}
}