{
  "type": "Feature",
  "properties": {
    "addr:full":"Place Nicola\u00cf 14 Aubel Li\u00e8ge 4880",
    "addr:housenumber":"14",
    "addr:postcode":"4880",
    "addr:street":"Place Nicolai\u0308",
    "iso:country":"BE",
    "sg:address":"Place Nicola\u00cf 14",
    "sg:city":"Aubel",
    "sg:classifiers":[
        {
            "category":"Shopping",
            "subcategory":"Clothing, Apparel, & Fashions",
            "type":"Retail Goods"
        }
    ],
    "sg:phone":"+32 87 68 65 65",
    "sg:postcode":"4880",
    "sg:province":"Li\u00e8ge",
    "sg:tags":[
        "ondergoed",
        "lingerie"
    ],
    "wof:name":"Maison Baguette",
    "wof:placetype":"venue"
},
  "geometry": {"coordinates":[5.8581399918,50.7048683167],"type":"Point"}
}