{
  "type": "Feature",
  "properties": {
    "iso:country":"BE",
    "sg:address":"Lindelsebaan 187",
    "sg:city":"Overpelt",
    "sg:classifiers":[
        {
            "category":"Food & Beverages",
            "subcategory":"Fruits & Vegetables",
            "type":"Retail Goods"
        }
    ],
    "sg:phone":"+32 11 66 13 54",
    "sg:postcode":"3900",
    "sg:province":"Limburg",
    "sg:tags":[
        "l\u00e9gumes"
    ],
    "wof:name":"De Groenteman",
    "wof:placetype":"venue"
},
  "geometry": {"coordinates":[5.4038248062,51.2006797791],"type":"Point"}
}