{
  "type": "Feature",
  "properties": {
    "iso:country":"BE",
    "sg:address":"Meiren 3",
    "sg:city":"Olen",
    "sg:classifiers":[
        {
            "category":"Home & Garden",
            "subcategory":"Kitchen Supply",
            "type":"Retail Goods"
        }
    ],
    "sg:phone":"+32 14 22 24 78",
    "sg:postcode":"2250",
    "sg:province":"Antwerpen",
    "sg:tags":[
        "installation"
    ],
    "wof:name":"Vanga-form",
    "wof:placetype":"venue"
},
  "geometry": {"coordinates":[4.9061799049,51.178981781],"type":"Point"}
}