{
  "type": "Feature",
  "properties": {
    "iso:country":"BE",
    "sg:address":"R Des Palais 192",
    "sg:city":"Bruxelles",
    "sg:classifiers":[
        {
            "category":"Building & Trades",
            "subcategory":"Electrical",
            "type":"Services"
        }
    ],
    "sg:phone":"+32 2 242 14 70",
    "sg:postcode":"1030",
    "sg:province":"Bruxelles-Capitale",
    "sg:tags":[
        "electronic",
        "lighting",
        "equipment"
    ],
    "wof:name":"Finexim Sa",
    "wof:placetype":"venue"
},
  "geometry": {"coordinates":[4.3659892082,50.8657875061],"type":"Point"}
}