{
  "type": "Feature",
  "properties": {
    "addr:full":"Dorpsstraat 2 Laarne Oost-Vlaanderen 9270",
    "addr:housenumber":"2",
    "addr:postcode":"9270",
    "addr:street":"Dorpsstraat",
    "iso:country":"BE",
    "sg:address":"Dorpsstraat 2",
    "sg:city":"Laarne",
    "sg:classifiers":[
        {
            "category":"Health Services",
            "subcategory":"Nursing And Care Facility",
            "type":"Services"
        }
    ],
    "sg:phone":"+32 9 369 00 26",
    "sg:postcode":"9270",
    "sg:province":"Oost-Vlaanderen",
    "sg:tags":[
        "public"
    ],
    "wof:name":"Gemeentebestuur",
    "wof:placetype":"venue"
},
  "geometry": {"coordinates":[3.8480300903,51.029384613],"type":"Point"}
}