{
  "type": "Feature",
  "properties": {
    "iso:country":"BE",
    "sg:address":"Rue Defacqz 52",
    "sg:city":"Bruxelles (ixelles)",
    "sg:classifiers":[
        {
            "category":"Social Services",
            "type":"Services"
        }
    ],
    "sg:phone":"+32 2 538 25 93",
    "sg:postcode":"1050",
    "sg:province":"Bruxelles-Capitale",
    "wof:name":"Oeuvre Royale Des Automobiles Pour Invalides De Guerre",
    "wof:placetype":"venue"
},
  "geometry": {"coordinates":[4.3594760895,50.8277626038],"type":"Point"}
}