{
  "type": "Feature",
  "properties": {
    "addr:full":"Rue Albert I 62 Charleroi (ransart) Hainaut 6043",
    "addr:housenumber":"62",
    "addr:postcode":"6043",
    "addr:street":"Rue Albert I",
    "iso:country":"BE",
    "sg:address":"Rue Albert I 62",
    "sg:city":"Charleroi (ransart)",
    "sg:classifiers":[
        {
            "category":"Professional",
            "subcategory":"Accounting & Tax Preparation",
            "type":"Services"
        }
    ],
    "sg:phone":"+32 71 34 34 28",
    "sg:postcode":"6043",
    "sg:province":"Hainaut",
    "sg:tags":[
        "accountant"
    ],
    "wof:name":"Bernardi & Co Sprl",
    "wof:placetype":"venue"
},
  "geometry": {"coordinates":[4.4839549065,50.4479637146],"type":"Point"}
}