{
  "type": "Feature",
  "properties": {
    "iso:country":"BE",
    "sg:address":"A. Vaucampslaan 32",
    "sg:city":"Beersel",
    "sg:orig_category":"Drukkerijen and copyshops",
    "sg:phone":"+32 2 363 89 77",
    "sg:postcode":"1654",
    "sg:province":"Vlaams-Brabant",
    "wof:name":"Daubresse",
    "wof:placetype":"venue"
},
  "geometry": {"coordinates":[4.2770171165,50.7453041077],"type":"Point"}
}