{
  "type": "Feature",
  "properties": {
    "addr:full":"Hoefstadstraat 94 Genk Limburg 3600",
    "addr:housenumber":"94",
    "addr:postcode":"3600",
    "addr:street":"Hoefstadstraat",
    "iso:country":"BE",
    "sg:address":"Hoefstadstraat 94",
    "sg:city":"Genk",
    "sg:classifiers":[
        {
            "category":"Retail",
            "subcategory":"Event Space",
            "type":"Services"
        }
    ],
    "sg:phone":"+32 89 30 85 55",
    "sg:postcode":"3600",
    "sg:province":"Limburg",
    "sg:tags":[
        "organisation"
    ],
    "wof:name":"New Lines Nv",
    "wof:placetype":"venue"
},
  "geometry": {"coordinates":[5.506538868,50.9796829224],"type":"Point"}
}