{
  "type": "Feature",
  "properties": {
    "iso:country":"BE",
    "sg:address":"Chemin Des Noisetiers 223",
    "sg:city":"Attert (thiaumont)",
    "sg:classifiers":[
        {
            "category":"Shopping",
            "subcategory":"Musical Instruments",
            "type":"Retail Goods"
        }
    ],
    "sg:phone":"+32 63 21 80 15",
    "sg:postcode":"6717",
    "sg:province":"Luxembourg",
    "sg:tags":[
        "-"
    ],
    "wof:name":"Pro Musica",
    "wof:placetype":"venue"
},
  "geometry": {"coordinates":[5.7537941933,49.7194442749],"type":"Point"}
}