{
  "type": "Feature",
  "properties": {
    "addr:full":"Vijver 25 Ichtegem West-Vlaanderen 8480",
    "addr:housenumber":"25",
    "addr:postcode":"8480",
    "addr:street":"Vijver",
    "iso:country":"BE",
    "sg:address":"Vijver 25",
    "sg:city":"Ichtegem",
    "sg:classifiers":[
        {
            "category":"Arts & Performance",
            "subcategory":"Music",
            "type":"Entertainment"
        }
    ],
    "sg:phone":"+32 51 58 91 78",
    "sg:postcode":"8480",
    "sg:province":"West-Vlaanderen",
    "sg:tags":[
        "disc-jockeys"
    ],
    "wof:name":"Disco Wizard",
    "wof:placetype":"venue"
},
  "geometry": {"coordinates":[3.0089640617,51.1030654907],"type":"Point"}
}