{
  "type": "Feature",
  "properties": {
    "iso:country":"BE",
    "sg:address":"Rue Des Falaises 11",
    "sg:city":"Walcourt",
    "sg:orig_category":"M\u00e9decins and sp\u00e9cialistes",
    "sg:phone":"+32 71 65 00 88",
    "sg:postcode":"5651",
    "sg:province":"Namur",
    "wof:name":"J.l. Fontaine",
    "wof:placetype":"venue"
},
  "geometry": {"coordinates":[4.4262080193,50.2824401855],"type":"Point"}
}