{
  "type": "Feature",
  "properties": {
    "addr:full":"Boskant 18a Kasterlee (lichtaart) Antwerpen 2460",
    "addr:housenumber":"18a",
    "addr:postcode":"2460",
    "addr:street":"Boskant",
    "iso:country":"BE",
    "sg:address":"Boskant 18a",
    "sg:city":"Kasterlee (lichtaart)",
    "sg:classifiers":[
        {
            "category":"Building & Trades",
            "subcategory":"Construction",
            "type":"Services"
        }
    ],
    "sg:phone":"+32 14 55 36 98",
    "sg:postcode":"2460",
    "sg:province":"Antwerpen",
    "sg:tags":[
        "stucco",
        "contractor"
    ],
    "wof:name":"Puts Guy Plafonneerwerken",
    "wof:placetype":"venue"
},
  "geometry": {"coordinates":[4.9671049118,51.2406616211],"type":"Point"}
}