{
  "type": "Feature",
  "properties": {
    "iso:country":"BE",
    "sg:address":"Leuvensesteenweg 57",
    "sg:city":"Mechelen",
    "sg:classifiers":[
        {
            "category":"Professional",
            "subcategory":"Art Services",
            "type":"Services"
        }
    ],
    "sg:phone":"+32 15 41 28 38",
    "sg:postcode":"2800",
    "sg:province":"Antwerpen",
    "sg:tags":[
        "designer",
        "display"
    ],
    "wof:name":"Huys R",
    "wof:placetype":"venue"
},
  "geometry": {"coordinates":[4.4918532372,51.0203399658],"type":"Point"}
}