{
  "type": "Feature",
  "properties": {
    "iso:country":"BE",
    "sg:address":"Avenue De La Berg\u00e8re 8",
    "sg:city":"Bruxelles (berchem-sainte-agathe)",
    "sg:orig_category":"Newspapers, magazines, periodicals - Publishers",
    "sg:phone":"+32 2 425 61 06",
    "sg:postcode":"1082",
    "sg:province":"Bruxelles-Capitale",
    "wof:name":"Osservatore Romano (l')",
    "wof:placetype":"venue"
},
  "geometry": {"coordinates":[4.3105239868,50.8672103882],"type":"Point"}
}