{
  "type": "Feature",
  "properties": {
    "addr:full":"Quai Orban 18-71 Li\u00e8ge 1 (li\u00e8ge 2) Li\u00e8ge 4020",
    "addr:housenumber":"2",
    "addr:postcode":"18-71;4020",
    "addr:street":"Quai Orban;Lie\u0300Ge",
    "iso:country":"BE",
    "sg:address":"Quai Orban 18-71",
    "sg:city":"Li\u00e8ge 1 (li\u00e8ge 2)",
    "sg:classifiers":[
        {
            "category":"Banks & Credit Unions",
            "subcategory":"Investment Brokerage",
            "type":"Services"
        }
    ],
    "sg:phone":"+32 4 343 88 84",
    "sg:postcode":"4020",
    "sg:province":"Li\u00e8ge",
    "sg:tags":[
        "auditor"
    ],
    "wof:name":"Lipszyc G",
    "wof:placetype":"venue"
},
  "geometry": {"coordinates":[5.5784330368,50.6353874207],"type":"Point"}
}