{
  "type": "Feature",
  "properties": {
    "addr:full":"Doornstraat 57 Dilbeek Vlaams-Brabant 1700",
    "addr:housenumber":"57",
    "addr:postcode":"1700",
    "addr:street":"Doornstraat",
    "iso:country":"BE",
    "sg:address":"Doornstraat 57",
    "sg:city":"Dilbeek",
    "sg:orig_category":"Magasins sp\u00e9cialis\u00e9s",
    "sg:phone":"+32 2 569 59 68",
    "sg:postcode":"1700",
    "sg:province":"Vlaams-Brabant",
    "wof:name":"Alfatronics",
    "wof:placetype":"venue"
},
  "geometry": {"coordinates":[4.2523021698,50.8363189697],"type":"Point"}
}