{
  "type": "Feature",
  "properties": {
    "addr:full":"Offerandestraat 29 Antwerpen Antwerpen 2060",
    "addr:housenumber":"29",
    "addr:postcode":"2060",
    "addr:street":"Offerandestraat",
    "iso:country":"BE",
    "sg:address":"Offerandestraat 29",
    "sg:city":"Antwerpen",
    "sg:orig_category":"Pain, p\u00e2tisseries and confiseries",
    "sg:phone":"+32 3 231 22 20",
    "sg:postcode":"2060",
    "sg:province":"Antwerpen",
    "wof:name":"\u00b4t Frangipanneke",
    "wof:placetype":"venue"
},
  "geometry": {"coordinates":[4.4249601364,51.2202987671],"type":"Point"}
}