{
  "type": "Feature",
  "properties": {
    "addr:full":"R\u00c9s. Charles Plisnier 1 Mons Hainaut 7011",
    "addr:housenumber":"1",
    "addr:postcode":"7011",
    "addr:street":"Charles Plisnier;Hainaut",
    "iso:country":"BE",
    "sg:address":"R\u00c9s. Charles Plisnier 1",
    "sg:city":"Mons",
    "sg:orig_category":"Enseignement maternel and primaire",
    "sg:phone":"+32 65 33 87 02",
    "sg:postcode":"7011",
    "sg:province":"Hainaut",
    "wof:name":"Ecole Matern. Communale",
    "wof:placetype":"venue"
},
  "geometry": {"coordinates":[3.912539959,50.4712982178],"type":"Point"}
}