{
  "type": "Feature",
  "properties": {
    "iso:country":"BE",
    "sg:address":"Rue Pestelin 21",
    "sg:city":"Pont-a-celles",
    "sg:orig_category":"Vakantiehuizen",
    "sg:phone":"+32 71 84 58 89",
    "sg:postcode":"6238",
    "sg:province":"Hainaut",
    "wof:name":"Racour Roger",
    "wof:placetype":"venue"
},
  "geometry": {"coordinates":[4.3996648788,50.5133247375],"type":"Point"}
}