{
  "type": "Feature",
  "properties": {
    "iso:country":"BE",
    "sg:address":"Hombergstraat 1",
    "sg:city":"Bilzen",
    "sg:orig_category":"Producteurs de fruits",
    "sg:phone":"+32 89 41 73 51",
    "sg:postcode":"3740",
    "sg:province":"Limburg",
    "wof:name":"Georges Vandionant",
    "wof:placetype":"venue"
},
  "geometry": {"coordinates":[5.500248909,50.9062538147],"type":"Point"}
}