{
  "type": "Feature",
  "properties": {
    "addr:full":"Lieve Gruyaertstraat 17 Mortsel Antwerpen 2640",
    "addr:housenumber":"17",
    "addr:postcode":"2640",
    "addr:street":"Gruyaertstraat",
    "iso:country":"BE",
    "sg:address":"Lieve Gruyaertstraat 17",
    "sg:city":"Mortsel",
    "sg:classifiers":[
        {
            "category":"Manufacturing",
            "subcategory":"Metals",
            "type":"Manufacturing & Wholesale Goods"
        }
    ],
    "sg:phone":"+32 3 455 86 83",
    "sg:postcode":"2640",
    "sg:province":"Antwerpen",
    "sg:tags":[
        "treatment",
        "surface"
    ],
    "wof:name":"Jb-services",
    "wof:placetype":"venue"
},
  "geometry": {"coordinates":[4.4715561867,51.1694374084],"type":"Point"}
}