{
  "type": "Feature",
  "properties": {
    "iso:country":"BE",
    "sg:address":"Rue De La D\u00c9portation 108",
    "sg:city":"Tubize",
    "sg:orig_category":"Boekhouders",
    "sg:phone":"+32 2 355 26 24",
    "sg:postcode":"1480",
    "sg:province":"Brabant Wallon",
    "wof:name":"Willy Debast",
    "wof:placetype":"venue"
},
  "geometry": {"coordinates":[4.2104840279,50.6914825439],"type":"Point"}
}