{
  "type": "Feature",
  "properties": {
    "addr:full":"Kunstdal 21 Eeklo Oost-Vlaanderen 9900",
    "addr:housenumber":"21",
    "addr:postcode":"9900",
    "addr:street":"Kunstdal",
    "iso:country":"BE",
    "sg:address":"Kunstdal 21",
    "sg:city":"Eeklo",
    "sg:classifiers":[
        {
            "category":"Professional",
            "subcategory":"Testing Lab",
            "type":"Services"
        }
    ],
    "sg:phone":"+32 9 377 36 38",
    "sg:postcode":"9900",
    "sg:province":"Oost-Vlaanderen",
    "sg:tags":[
        "laboratory",
        "-",
        "machines",
        "apparatus",
        "supply"
    ],
    "wof:name":"Algemeen Labo",
    "wof:placetype":"venue"
},
  "geometry": {"coordinates":[3.5302650928,51.1977233887],"type":"Point"}
}