{
  "type": "Feature",
  "properties": {
    "addr:full":"Rue De Fexhe Slins 65 Oupeye (herm\u00e9e) Li\u00e8ge 4680",
    "addr:housenumber":"65",
    "addr:postcode":"4680",
    "addr:street":"Rue De Fexhe Slins",
    "iso:country":"BE",
    "sg:address":"Rue De Fexhe Slins 65",
    "sg:city":"Oupeye (herm\u00e9e)",
    "sg:classifiers":[
        {
            "category":"Building & Trades",
            "subcategory":"Cleaning & Sanitation",
            "type":"Services"
        }
    ],
    "sg:phone":"+32 4 278 43 41",
    "sg:postcode":"4680",
    "sg:province":"Li\u00e8ge",
    "sg:tags":[
        "mainten",
        "-",
        "boiler"
    ],
    "wof:name":"Gosin & Fils Sprl",
    "wof:placetype":"venue"
},
  "geometry": {"coordinates":[5.6444120407,50.7089729309],"type":"Point"}
}