{
  "type": "Feature",
  "properties": {
    "addr:full":"Avenue De La Plante 22 Namur Namur 5000",
    "addr:housenumber":"22",
    "addr:postcode":"5000",
    "addr:street":"Avenue De La Plante",
    "iso:country":"BE",
    "sg:address":"Avenue De La Plante 22",
    "sg:city":"Namur",
    "sg:classifiers":[
        {
            "category":"Utilities",
            "subcategory":"Recycling",
            "type":"Services"
        }
    ],
    "sg:phone":"+32 81 22 00 17",
    "sg:postcode":"5000",
    "sg:province":"Namur",
    "wof:name":"Recynam Sa",
    "wof:placetype":"venue"
},
  "geometry": {"coordinates":[4.8618102074,50.4555015564],"type":"Point"}
}