{
  "type": "Feature",
  "properties": {
    "iso:country":"BE",
    "sg:address":"Kaaistraat 17",
    "sg:city":"Gistel",
    "sg:classifiers":[
        {
            "category":"Bars & Pubs",
            "type":"Food & Drink"
        }
    ],
    "sg:phone":"+32 59 27 76 96",
    "sg:postcode":"8470",
    "sg:province":"West-Vlaanderen",
    "sg:tags":[
        "tavern"
    ],
    "wof:name":"Koekoeksnest Bvba",
    "wof:placetype":"venue"
},
  "geometry": {"coordinates":[2.9683759212,51.1591567993],"type":"Point"}
}