{
  "type": "Feature",
  "properties": {
    "iso:country":"BE",
    "sg:address":"Rue Dautzenberg 80",
    "sg:city":"Brussel/bruxelles",
    "sg:orig_category":"Peinture. Rev\u00eatements pour sols and murs",
    "sg:phone":"+32 2 640 17 33",
    "sg:postcode":"1000",
    "sg:province":"Bruxelles-Capitale",
    "wof:name":"Nilson Pratto",
    "wof:placetype":"venue"
},
  "geometry": {"coordinates":[4.3663520813,50.8257408142],"type":"Point"}
}