{
  "type": "Feature",
  "properties": {
    "addr:full":"Ertbrugstraat 6 Wichelen Oost-Vlaanderen 9260",
    "addr:housenumber":"6",
    "addr:postcode":"9260",
    "addr:street":"Ertbrugstraat",
    "iso:country":"BE",
    "sg:address":"Ertbrugstraat 6",
    "sg:city":"Wichelen",
    "sg:orig_category":"Installatie van houten of kunststof schrijnwerk",
    "sg:phone":"+32 9 369 99 18",
    "sg:postcode":"9260",
    "sg:province":"Oost-Vlaanderen",
    "wof:name":"Rudy Vekeman",
    "wof:placetype":"venue"
},
  "geometry": {"coordinates":[3.9211258888,51.0109100342],"type":"Point"}
}