{
  "type": "Feature",
  "properties": {
    "addr:full":"Kattestraat 73 Kuurne West-Vlaanderen 8520",
    "addr:housenumber":"73",
    "addr:postcode":"8520",
    "addr:street":"Kattestraat",
    "iso:country":"BE",
    "sg:address":"Kattestraat 73",
    "sg:city":"Kuurne",
    "sg:classifiers":[
        {
            "category":"Personal",
            "subcategory":"Beauty Salon",
            "type":"Services"
        }
    ],
    "sg:phone":"+32 56 70 30 48",
    "sg:postcode":"8520",
    "sg:province":"West-Vlaanderen",
    "sg:tags":[
        "lady",
        "-",
        "hairdressing"
    ],
    "wof:name":"Christine",
    "wof:placetype":"venue"
},
  "geometry": {"coordinates":[3.2814519405,50.8559684753],"type":"Point"}
}