{
  "type": "Feature",
  "properties": {
    "addr:full":"Rue De Chapelle 10 Courcelles Hainaut 6183",
    "addr:housenumber":"10",
    "addr:postcode":"6183",
    "addr:street":"Rue De Chapelle",
    "iso:country":"BE",
    "sg:address":"Rue De Chapelle 10",
    "sg:city":"Courcelles",
    "sg:orig_category":"Textiel",
    "sg:phone":"+32 71 45 69 62",
    "sg:postcode":"6183",
    "sg:province":"Hainaut",
    "wof:name":"Chantal Van Impe",
    "wof:placetype":"venue"
},
  "geometry": {"coordinates":[4.3226060867,50.4647521973],"type":"Point"}
}