{
  "type": "Feature",
  "properties": {
    "addr:full":"Nijverheidstraat 92 Lokeren Oost-Vlaanderen 9160",
    "addr:housenumber":"92",
    "addr:postcode":"9160",
    "addr:street":"Nijverheidstraat",
    "iso:country":"BE",
    "sg:address":"Nijverheidstraat 92",
    "sg:city":"Lokeren",
    "sg:orig_category":"Beautyfarms, relaxatie and lichamelijk welzijn Fitnesscentra",
    "sg:phone":"+32 9 349 11 33",
    "sg:postcode":"9160",
    "sg:province":"Oost-Vlaanderen",
    "wof:name":"Sauna Corpus",
    "wof:placetype":"venue"
},
  "geometry": {"coordinates":[3.993117094,51.1101303101],"type":"Point"}
}