{
  "type": "Feature",
  "properties": {
    "addr:full":"Groteheide 120ba Neerpelt Limburg 3910",
    "addr:postcode":"3910",
    "iso:country":"BE",
    "sg:address":"Groteheide 120ba",
    "sg:city":"Neerpelt",
    "sg:orig_category":"Varkenskwekers",
    "sg:phone":"+32 11 66 26 74",
    "sg:postcode":"3910",
    "sg:province":"Limburg",
    "wof:name":"Jozef Vranken",
    "wof:placetype":"venue"
},
  "geometry": {"coordinates":[5.4362368584,51.2625236511],"type":"Point"}
}