{
  "type": "Feature",
  "properties": {
    "iso:country":"BE",
    "sg:address":"Ten Akkerdreef 55",
    "sg:city":"Kortrijk",
    "sg:orig_category":"Actuators, Electric",
    "sg:phone":"+32 56 23 59 35",
    "sg:postcode":"8500",
    "sg:province":"West-Vlaanderen",
    "wof:name":"Aben International B.v.b.a",
    "wof:placetype":"venue"
},
  "geometry": {"coordinates":[3.2760601044,50.8203964233],"type":"Point"}
}