{
  "type": "Feature",
  "properties": {
    "addr:full":"Avenue De Juprelle 2 Li\u00e8ge 1 (rocourt) Li\u00e8ge 4000",
    "addr:housenumber":"2;1",
    "addr:postcode":"4000",
    "addr:street":"Avenue De Juprelle",
    "iso:country":"BE",
    "sg:address":"Avenue De Juprelle 2",
    "sg:city":"Li\u00e8ge 1 (rocourt)",
    "sg:classifiers":[
        {
            "category":"Professional",
            "subcategory":"Testing Lab",
            "type":"Services"
        }
    ],
    "sg:phone":"+32 4 263 84 74",
    "sg:postcode":"4000",
    "sg:province":"Li\u00e8ge",
    "sg:tags":[
        "chemist"
    ],
    "wof:name":"Houben M",
    "wof:placetype":"venue"
},
  "geometry": {"coordinates":[5.5523290634,50.6809997559],"type":"Point"}
}