{
  "type": "Feature",
  "properties": {
    "addr:full":"Kapellendries 62 Melle (gontrode) Oost-Vlaanderen 9090",
    "addr:housenumber":"62",
    "addr:postcode":"9090",
    "addr:street":"Kapellendries",
    "iso:country":"BE",
    "sg:address":"Kapellendries 62",
    "sg:city":"Melle (gontrode)",
    "sg:classifiers":[
        {
            "category":"Recreation",
            "subcategory":"Amusement Park",
            "type":"Entertainment"
        }
    ],
    "sg:phone":"+32 9 252 67 63",
    "sg:postcode":"9090",
    "sg:province":"Oost-Vlaanderen",
    "sg:tags":[
        "attraction",
        "-",
        "sale",
        "fair",
        "hiring"
    ],
    "wof:name":"Amutoys",
    "wof:placetype":"venue"
},
  "geometry": {"coordinates":[3.7928469181,50.9804725647],"type":"Point"}
}