{
  "type": "Feature",
  "properties": {
    "addr:full":"Avenue Paul Pastur 155 Charleroi (mont-sur-marchienne) Hainaut 6032",
    "addr:housenumber":"155",
    "addr:postcode":"6032",
    "addr:street":"Avenue Paul Pastur",
    "iso:country":"BE",
    "sg:address":"Avenue Paul Pastur 155",
    "sg:city":"Charleroi (mont-sur-marchienne)",
    "sg:classifiers":[
        {
            "category":"Professional",
            "subcategory":"Lawyer & Legal Services",
            "type":"Services"
        }
    ],
    "sg:phone":"+32 71 36 16 70",
    "sg:postcode":"6032",
    "sg:province":"Hainaut",
    "sg:tags":[
        "notary"
    ],
    "wof:name":"Ganty P",
    "wof:placetype":"venue"
},
  "geometry": {"coordinates":[4.4110531807,50.3919906616],"type":"Point"}
}