{
  "type": "Feature",
  "properties": {
    "iso:country":"BE",
    "sg:address":"Meensesteenweg 137",
    "sg:city":"Kortrijk",
    "sg:classifiers":[
        {
            "category":"Home & Garden",
            "subcategory":"Furniture",
            "type":"Retail Goods"
        }
    ],
    "sg:phone":"+32 56 35 32 33",
    "sg:postcode":"8500",
    "sg:province":"West-Vlaanderen",
    "sg:tags":[
        "household",
        "wood"
    ],
    "wof:name":"Cimar Nv",
    "wof:placetype":"venue"
},
  "geometry": {"coordinates":[3.2444410324,50.8275337219],"type":"Point"}
}