{
  "type": "Feature",
  "properties": {
    "iso:country":"BE",
    "sg:address":"Zoellaan 37",
    "sg:city":"Haacht",
    "sg:classifiers":[
        {
            "category":"Food & Beverages",
            "subcategory":"Groceries & Convenience Stores",
            "type":"Retail Goods"
        }
    ],
    "sg:phone":"+32 16 61 76 17",
    "sg:postcode":"3150",
    "sg:province":"Vlaams-Brabant",
    "sg:tags":[
        "baker",
        "-",
        "ingredient"
    ],
    "wof:name":"Croissy-gastron De France Nv",
    "wof:placetype":"venue"
},
  "geometry": {"coordinates":[4.62545681,50.9759674072],"type":"Point"}
}