{
  "type": "Feature",
  "properties": {
    "iso:country":"BE",
    "sg:address":"Rue Lucien-petit 34ba",
    "sg:city":"Gembloux",
    "sg:orig_category":"Alternatieve geneeskunde",
    "sg:phone":"+32 81 61 21 01",
    "sg:postcode":"5030",
    "sg:province":"Namur",
    "wof:name":"Institut Piscart J.",
    "wof:placetype":"venue"
},
  "geometry": {"coordinates":[4.6869311333,50.5578346252],"type":"Point"}
}