{
  "type": "Feature",
  "properties": {
    "addr:full":"Oudenaardsestraat 25 Geraardsbergen Oost-Vlaanderen 9500",
    "addr:housenumber":"25",
    "addr:postcode":"9500",
    "addr:street":"Oudenaardsestraat",
    "iso:country":"BE",
    "sg:address":"Oudenaardsestraat 25",
    "sg:city":"Geraardsbergen",
    "sg:orig_category":"Herstelling horloges and juwelen Juwelen and horloges",
    "sg:phone":"+32 54 41 28 77",
    "sg:postcode":"9500",
    "sg:province":"Oost-Vlaanderen",
    "wof:name":"Huis Herman",
    "wof:placetype":"venue"
},
  "geometry": {"coordinates":[3.8751130104,50.7719497681],"type":"Point"}
}