{
  "type": "Feature",
  "properties": {
    "iso:country":"BE",
    "sg:address":"Langegang 27",
    "sg:city":"Antwerpen",
    "sg:classifiers":[
        {
            "category":"Bars & Pubs",
            "type":"Food & Drink"
        }
    ],
    "sg:phone":"+32 3 231 61 11",
    "sg:postcode":"2000",
    "sg:province":"Antwerpen",
    "sg:tags":[
        "tavern"
    ],
    "wof:name":"De Gang",
    "wof:placetype":"venue"
},
  "geometry": {"coordinates":[4.412115097,51.2163047791],"type":"Point"}
}