{
  "type": "Feature",
  "properties": {
    "iso:country":"BE",
    "sg:address":"Elzenstraat 25",
    "sg:city":"Meeuwen-gruitrode",
    "sg:orig_category":"Kruideniers Zuivelproducten",
    "sg:phone":"+32 11 79 22 49",
    "sg:postcode":"3670",
    "sg:province":"Limburg",
    "wof:name":"Joseph Houben",
    "wof:placetype":"venue"
},
  "geometry": {"coordinates":[5.5089950562,51.1006736755],"type":"Point"}
}