{
  "type": "Feature",
  "properties": {
    "iso:country":"BE",
    "sg:address":"Rue Ronchain 26",
    "sg:city":"Saint-ghislain (tertre)",
    "sg:classifiers":[
        {
            "category":"Government",
            "subcategory":"Fire Station",
            "type":"Public Place"
        }
    ],
    "sg:phone":"+32 65 64 43 74",
    "sg:postcode":"7333",
    "sg:province":"Hainaut",
    "sg:tags":[
        "decoration",
        "glass",
        "porcelain"
    ],
    "wof:name":"J.c. Ceramic",
    "wof:placetype":"venue"
},
  "geometry": {"coordinates":[3.8111400604,50.4655151367],"type":"Point"}
}