{
  "type": "Feature",
  "properties": {
    "addr:full":"Stationsstraat 24 Kampenhout Vlaams-Brabant 1910",
    "addr:housenumber":"24",
    "addr:postcode":"1910",
    "addr:street":"Stationsstraat",
    "iso:country":"BE",
    "sg:address":"Stationsstraat 24",
    "sg:city":"Kampenhout",
    "sg:classifiers":[
        {
            "category":"Professional",
            "subcategory":"Testing Lab",
            "type":"Services"
        }
    ],
    "sg:phone":"+32 16 65 50 25",
    "sg:postcode":"1910",
    "sg:province":"Vlaams-Brabant",
    "sg:tags":[
        "chemist"
    ],
    "wof:name":"Centrum Apoteek",
    "wof:placetype":"venue"
},
  "geometry": {"coordinates":[4.5554161072,50.9411277771],"type":"Point"}
}