{
  "type": "Feature",
  "properties": {
    "iso:country":"BE",
    "sg:address":"Heynsbergstraat 11",
    "sg:city":"Kasterlee (tielen)",
    "sg:classifiers":[
        {
            "category":"Home & Garden",
            "subcategory":"Home Furnishings",
            "type":"Retail Goods"
        }
    ],
    "sg:phone":"+32 14 55 42 82",
    "sg:postcode":"2460",
    "sg:province":"Antwerpen",
    "sg:tags":[
        "interior",
        "decoration"
    ],
    "wof:name":"Alucan",
    "wof:placetype":"venue"
},
  "geometry": {"coordinates":[4.9044628143,51.2507896423],"type":"Point"}
}