{
  "type": "Feature",
  "properties": {
    "addr:full":"Elisabethstraat 4 Blankenberge West-Vlaanderen 8370",
    "addr:housenumber":"4",
    "addr:postcode":"8370",
    "addr:street":"Elisabethstraat",
    "iso:country":"BE",
    "sg:address":"Elisabethstraat 4",
    "sg:city":"Blankenberge",
    "sg:orig_category":"H\u00f4tels",
    "sg:phone":"+32 50 41 16 96",
    "sg:postcode":"8370",
    "sg:province":"West-Vlaanderen",
    "wof:name":"Hotel Univers",
    "wof:placetype":"venue"
},
  "geometry": {"coordinates":[3.1311869621,51.3150787354],"type":"Point"}
}