{
  "type": "Feature",
  "properties": {
    "iso:country":"BE",
    "sg:address":"Elsterweg 16",
    "sg:city":"Riemst",
    "sg:orig_category":"Varkenskwekers",
    "sg:phone":"+32 12 39 37 39",
    "sg:postcode":"3770",
    "sg:province":"Limburg",
    "wof:name":"Axel Janssens",
    "wof:placetype":"venue"
},
  "geometry": {"coordinates":[5.5562348366,50.7701263428],"type":"Point"}
}