{
  "type": "Feature",
  "properties": {
    "iso:country":"BE",
    "sg:address":"Boulevard Pierre Mayence 17",
    "sg:city":"Charleroi",
    "sg:orig_category":"Advocaten and juridische adviseurs",
    "sg:phone":"+32 71 30 70 97",
    "sg:postcode":"6000",
    "sg:province":"Hainaut",
    "wof:name":"Odille Deladriere",
    "wof:placetype":"venue"
},
  "geometry": {"coordinates":[4.4524168968,50.4085121155],"type":"Point"}
}