{
  "type": "Feature",
  "properties": {
    "addr:full":"Gen. Baron Jacquesstraat 10 Diksmuide West-Vlaanderen 8600",
    "addr:housenumber":"10",
    "addr:postcode":"8600",
    "addr:street":"Gen. Baron Jacquesstraat",
    "iso:country":"BE",
    "sg:address":"Gen. Baron Jacquesstraat 10",
    "sg:city":"Diksmuide",
    "sg:orig_category":"Opticiens",
    "sg:phone":"+32 51 50 48 33",
    "sg:postcode":"8600",
    "sg:province":"West-Vlaanderen",
    "wof:name":"Brilcenter",
    "wof:placetype":"venue"
},
  "geometry": {"coordinates":[2.8631830215,51.0333023071],"type":"Point"}
}