{
  "type": "Feature",
  "properties": {
    "iso:country":"BE",
    "sg:address":"Jacob Smitslaan 59b2",
    "sg:city":"Aartselaar",
    "sg:orig_category":"Paramedische behandelingen",
    "sg:phone":"+32 3 877 18 20",
    "sg:postcode":"2630",
    "sg:province":"Antwerpen",
    "wof:name":"S. D\u00b4hooghe",
    "wof:placetype":"venue"
},
  "geometry": {"coordinates":[4.3810968399,51.1394691467],"type":"Point"}
}