{
  "type": "Feature",
  "properties": {
    "iso:country":"BE",
    "sg:address":"Bergstraat 11",
    "sg:city":"Sint-katelijne-waver",
    "sg:classifiers":[
        {
            "category":"Restaurant",
            "type":"Food & Drink"
        }
    ],
    "sg:phone":"+32 15 75 71 63",
    "sg:postcode":"2861",
    "sg:province":"Antwerpen",
    "sg:tags":[
        "caf\u00e9s"
    ],
    "wof:name":"Taverne 't Lepeltje",
    "wof:placetype":"venue"
},
  "geometry": {"coordinates":[4.5657339096,51.0539093018],"type":"Point"}
}