{
  "type": "Feature",
  "properties": {
    "addr:full":"Rue De Rekkem 20 Moeskroen Hainaut 7700",
    "addr:housenumber":"20",
    "addr:postcode":"7700",
    "addr:street":"Rue De Rekkem;Hainaut",
    "iso:country":"BE",
    "sg:address":"Rue De Rekkem 20",
    "sg:city":"Moeskroen",
    "sg:orig_category":"Installation de menuiserie en bois and plastique",
    "sg:phone":"+32 56 33 38 60",
    "sg:postcode":"7700",
    "sg:province":"Hainaut",
    "wof:name":"Penninck",
    "wof:placetype":"venue"
},
  "geometry": {"coordinates":[3.1968109608,50.7522735596],"type":"Point"}
}