{
  "type": "Feature",
  "properties": {
    "addr:full":"Oosthoek 104 Assenede Oost-Vlaanderen 9968",
    "addr:housenumber":"104",
    "addr:postcode":"9968",
    "addr:street":"Oosthoek",
    "iso:country":"BE",
    "sg:address":"Oosthoek 104",
    "sg:city":"Assenede",
    "sg:orig_category":"Slagers",
    "sg:phone":"+32 9 373 91 77",
    "sg:postcode":"9968",
    "sg:province":"Oost-Vlaanderen",
    "wof:name":"Christian Van Thuyne",
    "wof:placetype":"venue"
},
  "geometry": {"coordinates":[3.6887938976,51.1923027039],"type":"Point"}
}