{
  "type": "Feature",
  "properties": {
    "addr:full":"Kerkstraat 67 Antwerpen (groot) Antwerpen 2060",
    "addr:housenumber":"67",
    "addr:postcode":"2060",
    "addr:street":"Kerkstraat;Groot Antwerpen",
    "iso:country":"BE",
    "sg:address":"Kerkstraat 67",
    "sg:city":"Antwerpen (groot)",
    "sg:orig_category":"Kapsalons",
    "sg:phone":"+32 3 235 27 94",
    "sg:postcode":"2060",
    "sg:province":"Antwerpen",
    "wof:name":"Jozef",
    "wof:placetype":"venue"
},
  "geometry": {"coordinates":[4.4310030937,51.2185935974],"type":"Point"}
}