{
  "type": "Feature",
  "properties": {
    "addr:full":"Brusselsesteenweg 386 Melle Oost-Vlaanderen 9090",
    "addr:housenumber":"386",
    "addr:postcode":"9090",
    "addr:street":"Brusselsesteenweg",
    "iso:country":"BE",
    "sg:address":"Brusselsesteenweg 386",
    "sg:city":"Melle",
    "sg:orig_category":"Woningbouw",
    "sg:phone":"+32 9 252 16 85",
    "sg:postcode":"9090",
    "sg:province":"Oost-Vlaanderen",
    "wof:name":"Marcel Janssens",
    "wof:placetype":"venue"
},
  "geometry": {"coordinates":[3.8246619701,50.9933662415],"type":"Point"}
}