{
  "type": "Feature",
  "properties": {
    "addr:full":"Weg Naar As 17 Opglabbeek Limburg 3660",
    "addr:housenumber":"17",
    "addr:postcode":"3660",
    "addr:street":"Weg Naar As",
    "iso:country":"BE",
    "sg:address":"Weg Naar As 17",
    "sg:city":"Opglabbeek",
    "sg:orig_category":"Banques and organismes de cr\u00e9dit",
    "sg:phone":"+32 89 85 69 21",
    "sg:postcode":"3660",
    "sg:province":"Limburg",
    "wof:name":"Bacob",
    "wof:placetype":"venue"
},
  "geometry": {"coordinates":[5.5832018852,51.0401153564],"type":"Point"}
}