{
  "type": "Feature",
  "properties": {
    "addr:full":"Grand-place 27 Leuze-en-hainaut Hainaut 7900",
    "addr:housenumber":"27",
    "addr:postcode":"7900",
    "addr:street":"Grand-Place",
    "iso:country":"BE",
    "sg:address":"Grand-place 27",
    "sg:city":"Leuze-en-hainaut",
    "sg:orig_category":"Cr\u00e9dits divers",
    "sg:postcode":"7900",
    "sg:province":"Hainaut",
    "wof:name":"Bancontact-mister Cash",
    "wof:placetype":"venue"
},
  "geometry": {"coordinates":[3.6179430485,50.5985908508],"type":"Point"}
}