{
  "type": "Feature",
  "properties": {
    "addr:full":"Groot-bijgaardenstraat 431 Berchem-sainte-agathe Bruxelles-Capitale 1082",
    "addr:housenumber":"431",
    "addr:postcode":"1082",
    "addr:street":"Groot-Bijgaardenstraat",
    "iso:country":"BE",
    "sg:address":"Groot-bijgaardenstraat 431",
    "sg:city":"Berchem-sainte-agathe",
    "sg:orig_category":"Jardinage",
    "sg:phone":"+32 2 465 92 64",
    "sg:postcode":"1082",
    "sg:province":"Bruxelles-Capitale",
    "wof:name":"Van Steenbrugge L",
    "wof:placetype":"venue"
},
  "geometry": {"coordinates":[4.2884120941,50.8627243042],"type":"Point"}
}