{
  "type": "Feature",
  "properties": {
    "addr:full":"Kertsbornstraat 1 Tongeren Limburg 3700",
    "addr:housenumber":"1",
    "addr:postcode":"3700",
    "addr:street":"Kertsbornstraat",
    "iso:country":"BE",
    "sg:address":"Kertsbornstraat 1",
    "sg:city":"Tongeren",
    "sg:orig_category":"Eleveurs and marchands de porcs",
    "sg:phone":"+32 12 23 43 91",
    "sg:postcode":"3700",
    "sg:province":"Limburg",
    "wof:name":"Rene Clerinx",
    "wof:placetype":"venue"
},
  "geometry": {"coordinates":[5.4636240005,50.7807197571],"type":"Point"}
}