{
  "type": "Feature",
  "properties": {
    "addr:full":"Weidestraat 24b1 Genk Limburg 3600",
    "addr:housenumber":"24b1",
    "addr:postcode":"3600",
    "addr:street":"Weidestraat",
    "iso:country":"BE",
    "sg:address":"Weidestraat 24b1",
    "sg:city":"Genk",
    "sg:orig_category":"D\u00e9taillants en pi\u00e8ces and accessoires de voitures",
    "sg:phone":"+32 89 35 15 01",
    "sg:postcode":"3600",
    "sg:province":"Limburg",
    "wof:name":"Dirk Noben",
    "wof:placetype":"venue"
},
  "geometry": {"coordinates":[5.4740171432,50.9534873962],"type":"Point"}
}