{
  "type": "Feature",
  "properties": {
    "addr:full":"Gillegomstraat 31 Brasschaat Antwerpen 2530",
    "addr:housenumber":"31",
    "addr:postcode":"2530",
    "addr:street":"Gillegomstraat",
    "iso:country":"BE",
    "sg:address":"Gillegomstraat 31",
    "sg:city":"Brasschaat",
    "sg:orig_category":"Elektrische installaties voor woningen",
    "sg:phone":"+32 3 653 28 57",
    "sg:postcode":"2530",
    "sg:province":"Antwerpen",
    "wof:name":"Ligna Forma",
    "wof:placetype":"venue"
},
  "geometry": {"coordinates":[4.4913249016,51.1586532593],"type":"Point"}
}