{
  "type": "Feature",
  "properties": {
    "addr:full":"Rue Jourdan 31 Bruxelles (saint-gilles) Bruxelles-Capitale 1060",
    "addr:housenumber":"31",
    "addr:postcode":"1060",
    "addr:street":"Rue Jourdan",
    "iso:country":"BE",
    "sg:address":"Rue Jourdan 31",
    "sg:city":"Bruxelles (saint-gilles)",
    "sg:classifiers":[
        {
            "category":"Professional",
            "subcategory":"Lawyer & Legal Services",
            "type":"Services"
        }
    ],
    "sg:phone":"+32 2 537 65 50",
    "sg:postcode":"1060",
    "sg:province":"Bruxelles-Capitale",
    "wof:name":"Wahis Serge",
    "wof:placetype":"venue"
},
  "geometry": {"coordinates":[4.3542108536,50.8343467712],"type":"Point"}
}