{
  "type": "Feature",
  "properties": {
    "addr:full":"Gentstraat 20 Meulebeke West-Vlaanderen 8760",
    "addr:housenumber":"20",
    "addr:postcode":"8760",
    "addr:street":"Gentstraat",
    "iso:country":"BE",
    "sg:address":"Gentstraat 20",
    "sg:city":"Meulebeke",
    "sg:classifiers":[
        {
            "category":"Insurance",
            "subcategory":"Insurance Agent",
            "type":"Services"
        }
    ],
    "sg:phone":"+32 51 48 81 99",
    "sg:postcode":"8760",
    "sg:province":"West-Vlaanderen",
    "sg:tags":[
        "broker"
    ],
    "wof:name":"Vergote-ducatteeuw Bvba",
    "wof:placetype":"venue"
},
  "geometry": {"coordinates":[3.2918550968,50.9483337402],"type":"Point"}
}