{
  "type": "Feature",
  "properties": {
    "iso:country":"BE",
    "sg:address":"Rue Gustave Delperdange 12",
    "sg:city":"Bastogne",
    "sg:classifiers":[
        {
            "category":"Education",
            "subcategory":"School",
            "type":"Public Place"
        }
    ],
    "sg:phone":"+32 61 21 53 51",
    "sg:postcode":"6600",
    "sg:province":"Luxembourg",
    "sg:tags":[
        "secondary"
    ],
    "wof:name":"Cefa Indse",
    "wof:placetype":"venue"
},
  "geometry": {"coordinates":[5.745347023,50.0071411133],"type":"Point"}
}