{
  "type": "Feature",
  "properties": {
    "addr:full":"Graaf Van Hoornestraat 65 Nevele Oost-Vlaanderen 9850",
    "addr:housenumber":"65",
    "addr:postcode":"9850",
    "addr:street":"Graaf Van Hoornestraat",
    "iso:country":"BE",
    "sg:address":"Graaf Van Hoornestraat 65",
    "sg:city":"Nevele",
    "sg:classifiers":[
        {
            "category":"Wholesale",
            "subcategory":"Plants",
            "type":"Manufacturing & Wholesale Goods"
        }
    ],
    "sg:phone":"+32 9 371 51 67",
    "sg:postcode":"9850",
    "sg:province":"Oost-Vlaanderen",
    "sg:tags":[
        "whol",
        "flower",
        "-",
        "grower"
    ],
    "wof:name":"Goossens",
    "wof:placetype":"venue"
},
  "geometry": {"coordinates":[3.531058073,51.0357894897],"type":"Point"}
}