{
  "type": "Feature",
  "properties": {
    "iso:country":"BE",
    "sg:address":"Boshoek 140",
    "sg:city":"Boechout",
    "sg:classifiers":[
        {
            "category":"Building & Trades",
            "subcategory":"Landscaping Services",
            "type":"Services"
        }
    ],
    "sg:phone":"+32 3 454 65 01",
    "sg:postcode":"2530",
    "sg:province":"Antwerpen",
    "sg:tags":[
        "architect",
        "landscape"
    ],
    "wof:name":"Guy Vandooren Tuincreaties",
    "wof:placetype":"venue"
},
  "geometry": {"coordinates":[4.5040221214,51.1510467529],"type":"Point"}
}