{
  "type": "Feature",
  "properties": {
    "addr:full":"Wouter Volcaertstraat 42 Mortsel Antwerpen 2640",
    "addr:housenumber":"42",
    "addr:postcode":"2640",
    "addr:street":"Wouter Volcaertstraat",
    "iso:country":"BE",
    "sg:address":"Wouter Volcaertstraat 42",
    "sg:city":"Mortsel",
    "sg:orig_category":"Activit\u00e9s r\u00e9cr\u00e9atives diverses",
    "sg:phone":"+32 3 440 42 78",
    "sg:postcode":"2640",
    "sg:province":"Antwerpen",
    "wof:name":"Inner Wheel Club",
    "wof:placetype":"venue"
},
  "geometry": {"coordinates":[4.4574298859,51.1792907715],"type":"Point"}
}