{
  "type": "Feature",
  "properties": {
    "addr:full":"Rue Herman 1 St. Hubert Luxembourg 6900",
    "addr:housenumber":"1",
    "addr:postcode":"6900",
    "addr:street":"Rue Herman",
    "iso:country":"BE",
    "sg:address":"Rue Herman 1",
    "sg:city":"St. Hubert",
    "sg:classifiers":[
        {
            "category":"Banks & Credit Unions",
            "subcategory":"Bank",
            "type":"Services"
        }
    ],
    "sg:phone":"+32 61 61 26 90",
    "sg:postcode":"6900",
    "sg:province":"Luxembourg",
    "wof:name":"Caisse Nationale De, Cr\u00e9dit Professionnel",
    "wof:placetype":"venue"
},
  "geometry": {"coordinates":[5.2869830132,50.1687393188],"type":"Point"}
}