{
  "type": "Feature",
  "properties": {
    "iso:country":"BE",
    "sg:address":"Vierschaarstraat 8",
    "sg:city":"Kortrijk",
    "sg:orig_category":"Herstellingswinkels voor diverse persoonlijke and huishoudartikelen Plaatsen van vloer- and muurbekl",
    "sg:phone":"+32 56 20 52 55",
    "sg:postcode":"8500",
    "sg:province":"West-Vlaanderen",
    "wof:name":"Kordekor",
    "wof:placetype":"venue"
},
  "geometry": {"coordinates":[3.2770810127,50.8215637207],"type":"Point"}
}