{
  "type": "Feature",
  "properties": {
    "addr:full":"Rue Du Moulin 24 Dave Namur 5100",
    "addr:housenumber":"24",
    "addr:postcode":"5100",
    "addr:street":"Rue Du Moulin",
    "iso:country":"BE",
    "sg:address":"Rue Du Moulin 24",
    "sg:city":"Dave",
    "sg:orig_category":"Installation \u00e9lectrique industrielle. Installation \u00e9lectrique r\u00e9sidentielle",
    "sg:phone":"+32 495 26 46 41",
    "sg:postcode":"5100",
    "sg:province":"Namur",
    "wof:name":"Rodrique Michel",
    "wof:placetype":"venue"
},
  "geometry": {"coordinates":[4.8893499374,50.4164199829],"type":"Point"}
}