{
  "type": "Feature",
  "properties": {
    "iso:country":"BE",
    "sg:address":"Strodorp 50",
    "sg:city":"Lanaken",
    "sg:orig_category":"R\u00e9paration and restauration de meubles. Installation de menuiserie en bois and plastique. Meubles D\u00e9",
    "sg:phone":"+32 89 71 40 43",
    "sg:postcode":"3620",
    "sg:province":"Limburg",
    "wof:name":"Meubelatelier Loyens",
    "wof:placetype":"venue"
},
  "geometry": {"coordinates":[5.6551351547,50.8912277222],"type":"Point"}
}