{
  "type": "Feature",
  "properties": {
    "addr:full":"Rue De La Rose 12 Seraing Li\u00e8ge 4102",
    "addr:housenumber":"12",
    "addr:postcode":"4102",
    "addr:street":"Rue De La Rose",
    "iso:country":"BE",
    "sg:address":"Rue De La Rose 12",
    "sg:city":"Seraing",
    "sg:orig_category":"M\u00e9decins and sp\u00e9cialistes",
    "sg:phone":"+32 4 337 80 80",
    "sg:postcode":"4102",
    "sg:province":"Li\u00e8ge",
    "wof:name":"Jean-marie Delvoye",
    "wof:placetype":"venue"
},
  "geometry": {"coordinates":[5.5387859344,50.5871696472],"type":"Point"}
}