{
  "type": "Feature",
  "properties": {
    "addr:full":"Avenue Louise 250bte 101 Bruxelles 1051",
    "addr:housenumber":"250bte 101",
    "addr:postcode":"1051",
    "addr:street":"Avenue Louise",
    "iso:country":"BE",
    "sg:address":"Avenue Louise 250bte 101",
    "sg:city":"Bruxelles",
    "sg:classifiers":[
        {
            "category":"Education",
            "subcategory":"Kindergarten",
            "type":"Public Place"
        }
    ],
    "sg:phone":"+32 2 648 58 90",
    "sg:postcode":"1051",
    "sg:tags":[
        "movement",
        "clock"
    ],
    "wof:name":"Rolex Benelux S.a.",
    "wof:placetype":"venue"
},
  "geometry": {"coordinates":[4.3666410446,50.8251457214],"type":"Point"}
}