{
  "type": "Feature",
  "properties": {
    "addr:full":"E. Ruelensvest 159 Heverlee Vlaams-Brabant 3001",
    "addr:housenumber":"159",
    "addr:postcode":"3001",
    "addr:street":"E. Ruelensvest",
    "iso:country":"BE",
    "sg:address":"E. Ruelensvest 159",
    "sg:city":"Heverlee",
    "sg:orig_category":"Maatschappelijke dienstverlening",
    "sg:phone":"+32 477 41 18 28",
    "sg:postcode":"3001",
    "sg:province":"Vlaams-Brabant",
    "wof:name":"Centrum Voor Psychoanalyse & Gezinstherapie",
    "wof:placetype":"venue"
},
  "geometry": {"coordinates":[4.7066087723,50.8685150146],"type":"Point"}
}