{
  "type": "Feature",
  "properties": {
    "addr:full":"Belhuttebaan 40 Koekelare West-Vlaanderen 8680",
    "addr:housenumber":"40",
    "addr:postcode":"8680",
    "addr:street":"Belhuttebaan",
    "iso:country":"BE",
    "sg:address":"Belhuttebaan 40",
    "sg:city":"Koekelare",
    "sg:classifiers":[
        {
            "category":"Arena",
            "subcategory":"Sports Club",
            "type":"Entertainment"
        }
    ],
    "sg:phone":"+32 51 58 92 30",
    "sg:postcode":"8680",
    "sg:province":"West-Vlaanderen",
    "sg:tags":[
        "terrain",
        "hors",
        "de",
        "installation",
        "sportifs"
    ],
    "wof:name":"Tennisclub De Mote",
    "wof:placetype":"venue"
},
  "geometry": {"coordinates":[2.9843270779,51.0847129822],"type":"Point"}
}