{
  "type": "Feature",
  "properties": {
    "addr:full":"Rue Sevrin 1 La Bruyere Namur 5080",
    "addr:housenumber":"1",
    "addr:postcode":"5080",
    "addr:street":"Rue Sevrin;La Bruyere",
    "iso:country":"BE",
    "sg:address":"Rue Sevrin 1",
    "sg:city":"La Bruyere",
    "sg:classifiers":[
        {
            "category":"Arena",
            "subcategory":"Sports Club",
            "type":"Entertainment"
        }
    ],
    "sg:phone":"+32 81 56 72 61",
    "sg:postcode":"5080",
    "sg:province":"Namur",
    "sg:tags":[
        "de"
    ],
    "wof:name":"La Belle Vue",
    "wof:placetype":"venue"
},
  "geometry": {"coordinates":[4.820081234,50.5167617798],"type":"Point"}
}