{
  "type": "Feature",
  "properties": {
    "iso:country":"BE",
    "sg:address":"Sterstraat 57",
    "sg:city":"Lommel",
    "sg:orig_category":"Installatie van houten of kunststof schrijnwerk",
    "sg:phone":"+32 11 55 36 18",
    "sg:postcode":"3920",
    "sg:province":"Limburg",
    "wof:name":"V B D Poorten",
    "wof:placetype":"venue"
},
  "geometry": {"coordinates":[5.292098999,51.2313117981],"type":"Point"}
}