{
  "type": "Feature",
  "properties": {
    "iso:country":"BE",
    "sg:address":"Loskaai-station",
    "sg:city":"Denderleeuw",
    "sg:classifiers":[
        {
            "category":"Utilities",
            "subcategory":"Fuel Oil & Lpg",
            "type":"Services"
        }
    ],
    "sg:phone":"+32 53 68 53 68",
    "sg:postcode":"9470",
    "sg:province":"Oost-Vlaanderen",
    "wof:name":"Ruysseveldt Kinderen",
    "wof:placetype":"venue"
},
  "geometry": {"coordinates":[4.0719671249,50.8920440674],"type":"Point"}
}