{
  "type": "Feature",
  "properties": {
    "iso:country":"BE",
    "sg:address":"Rue Des Ecoles 5",
    "sg:city":"Hensies",
    "sg:orig_category":"Traitements param\u00e9dicaux",
    "sg:phone":"+32 475 89 21 28",
    "sg:postcode":"7350",
    "sg:province":"Hainaut",
    "wof:name":"J. Walrant",
    "wof:placetype":"venue"
},
  "geometry": {"coordinates":[3.6856200695,50.4343833923],"type":"Point"}
}