{
  "type": "Feature",
  "properties": {
    "addr:full":"Th. Achterbist 16 Nijlen Antwerpen 2560",
    "addr:housenumber":"16",
    "addr:postcode":"2560",
    "addr:street":"Th. Achterbist",
    "iso:country":"BE",
    "sg:address":"Th. Achterbist 16",
    "sg:city":"Nijlen",
    "sg:orig_category":"Salles de spectacles",
    "sg:phone":"+32 3 481 76 99",
    "sg:postcode":"2560",
    "sg:province":"Antwerpen",
    "wof:name":"Teater Nok",
    "wof:placetype":"venue"
},
  "geometry": {"coordinates":[4.6463208199,51.1677322388],"type":"Point"}
}