{
  "type": "Feature",
  "properties": {
    "addr:full":"Europark 25 Houthalen Limburg 3530",
    "addr:housenumber":"25",
    "addr:postcode":"3530",
    "addr:street":"Europark",
    "iso:country":"BE",
    "sg:address":"Europark 25",
    "sg:city":"Houthalen",
    "sg:orig_category":"Entretien et r\u00e9parations de v\u00e9hicules \u00e0 domicile. Conseils en syst\u00e8mes informatiques. Ordinateurs an",
    "sg:phone":"+32 11 52 20 30",
    "sg:postcode":"3530",
    "sg:province":"Limburg",
    "wof:name":"Depannage Claes",
    "wof:placetype":"venue"
},
  "geometry": {"coordinates":[5.3899240494,51.0351867676],"type":"Point"}
}