{
  "type": "Feature",
  "properties": {
    "iso:country":"BE",
    "sg:address":"Rue De L'embarcad\u00e8re 35",
    "sg:city":"Chiny",
    "sg:classifiers":[
        {
            "category":"Travel",
            "subcategory":"Hotels & Motels",
            "type":"Entertainment"
        }
    ],
    "sg:phone":"+32 61 32 05 44",
    "sg:postcode":"6810",
    "sg:province":"Luxembourg",
    "wof:name":"Hostellerie Aux Comtes De Chiny",
    "wof:placetype":"venue"
},
  "geometry": {"coordinates":[5.3291702271,49.7402534485],"type":"Point"}
}