{
  "type": "Feature",
  "properties": {
    "iso:country":"BE",
    "sg:address":"Zittaart 25",
    "sg:city":"Lille",
    "sg:orig_category":"Artiesten and kunstenaars",
    "sg:phone":"+32 14 21 73 25",
    "sg:postcode":"2275",
    "sg:province":"Antwerpen",
    "wof:name":"Veerle Wijffels",
    "wof:placetype":"venue"
},
  "geometry": {"coordinates":[4.808371067,51.2192153931],"type":"Point"}
}