{
  "type": "Feature",
  "properties": {
    "addr:full":"Shopping Zuid Gent Oost-Vlaanderen 9000",
    "addr:postcode":"9000",
    "addr:street":"Oost-Vlaanderen",
    "iso:country":"BE",
    "sg:address":"Shopping Zuid",
    "sg:city":"Gent",
    "sg:classifiers":[
        {
            "category":"Wholesale",
            "subcategory":"Sporting Goods",
            "type":"Manufacturing & Wholesale Goods"
        }
    ],
    "sg:phone":"+32 9 269 85 85",
    "sg:postcode":"9000",
    "sg:province":"Oost-Vlaanderen",
    "sg:tags":[
        "sport-",
        "kampeermateriaal"
    ],
    "wof:name":"Giacomelli Sport",
    "wof:placetype":"venue"
},
  "geometry": {"coordinates":[3.7055399418,51.0597991943],"type":"Point"}
}