{
  "type": "Feature",
  "properties": {
    "addr:full":"Langestraat 128 Brugge West-Vlaanderen 8000",
    "addr:housenumber":"128",
    "addr:postcode":"8000",
    "addr:street":"Langestraat",
    "iso:country":"BE",
    "sg:address":"Langestraat 128",
    "sg:city":"Brugge",
    "sg:classifiers":[
        {
            "category":"Personal",
            "subcategory":"Beauty Salon",
            "type":"Services"
        }
    ],
    "sg:phone":"+32 50 33 90 32",
    "sg:postcode":"8000",
    "sg:province":"West-Vlaanderen",
    "sg:tags":[
        "de",
        "coiffure"
    ],
    "wof:name":"Coiffure Jeannine",
    "wof:placetype":"venue"
},
  "geometry": {"coordinates":[3.2381100655,51.2120170593],"type":"Point"}
}