{
  "type": "Feature",
  "properties": {
    "iso:country":"BE",
    "sg:address":"Avenue Joseph Lejeune 153",
    "sg:city":"Trois-ponts - Fosse",
    "sg:classifiers":[
        {
            "category":"Travel",
            "subcategory":"Resort",
            "type":"Entertainment"
        }
    ],
    "sg:phone":"+32 80 68 52 78",
    "sg:postcode":"4980",
    "sg:province":"Li\u00e8ge",
    "sg:tags":[
        "rental",
        "accomodation",
        "holiday",
        "-"
    ],
    "wof:name":"Hibou (le) Asbl",
    "wof:placetype":"venue"
},
  "geometry": {"coordinates":[5.8498501778,50.3678855896],"type":"Point"}
}