{
  "type": "Feature",
  "properties": {
    "iso:country":"BE",
    "sg:address":"J. De Troozlaan 50",
    "sg:city":"Blankenberge",
    "sg:classifiers":[
        {
            "category":"Personal",
            "subcategory":"Beauty Salon",
            "type":"Services"
        }
    ],
    "sg:phone":"+32 50 41 23 47",
    "sg:postcode":"8370",
    "sg:province":"West-Vlaanderen",
    "sg:tags":[
        "de",
        "coiffure"
    ],
    "wof:name":"Da Vinci Hair Style",
    "wof:placetype":"venue"
},
  "geometry": {"coordinates":[3.1337120533,51.3159790039],"type":"Point"}
}