{
  "type": "Feature",
  "properties": {
    "addr:full":"Chemin De Feluy 27 Braine-le-comte Hainaut 7090",
    "addr:housenumber":"27",
    "addr:postcode":"7090",
    "addr:street":"Chemin De Feluy",
    "iso:country":"BE",
    "sg:address":"Chemin De Feluy 27",
    "sg:city":"Braine-le-comte",
    "sg:classifiers":[
        {
            "category":"Recreation",
            "subcategory":"Boat Charter",
            "type":"Entertainment"
        }
    ],
    "sg:phone":"+32 67 55 38 10",
    "sg:postcode":"7090",
    "sg:province":"Hainaut",
    "sg:tags":[
        "-",
        "builder",
        "yacht",
        "pleasure"
    ],
    "wof:name":"Delta Nord Nv Sa",
    "wof:placetype":"venue"
},
  "geometry": {"coordinates":[4.1430602074,50.6071205139],"type":"Point"}
}