{
  "type": "Feature",
  "properties": {
    "addr:full":"Teerlingstraat 1 Stekene Oost-Vlaanderen 9190",
    "addr:housenumber":"1",
    "addr:postcode":"9190",
    "addr:street":"Teerlingstraat",
    "iso:country":"BE",
    "sg:address":"Teerlingstraat 1",
    "sg:city":"Stekene",
    "sg:orig_category":"Kapsalons",
    "sg:phone":"+32 3 789 24 46",
    "sg:postcode":"9190",
    "sg:province":"Oost-Vlaanderen",
    "wof:name":"Karine Annecour",
    "wof:placetype":"venue"
},
  "geometry": {"coordinates":[4.028881073,51.2135658264],"type":"Point"}
}