{
  "type": "Feature",
  "properties": {
    "addr:full":"Rue De L\u00b4union 28 La Louvi\u00c8re Hainaut 7100",
    "addr:housenumber":"28",
    "addr:postcode":"7100",
    "addr:street":"Rue De L\u00b4Union",
    "iso:country":"BE",
    "sg:address":"Rue De L\u00b4union 28",
    "sg:city":"La Louvi\u00c8re",
    "sg:orig_category":"Brood, gebak and snoepgoed",
    "sg:phone":"+32 64 22 15 01",
    "sg:postcode":"7100",
    "sg:province":"Hainaut",
    "wof:name":"Boulangerie Scohier",
    "wof:placetype":"venue"
},
  "geometry": {"coordinates":[4.2169218063,50.4737739563],"type":"Point"}
}