{
  "type": "Feature",
  "properties": {
    "addr:full":"Recul\u00c9mont 3ba Malmedy/malmedy Li\u00e8ge 4960",
    "addr:housenumber":"3ba",
    "addr:postcode":"4960",
    "addr:street":"Recule\u0301Mont",
    "iso:country":"BE",
    "sg:address":"Recul\u00c9mont 3ba",
    "sg:city":"Malmedy/malmedy",
    "sg:orig_category":"Woningbouw",
    "sg:phone":"+32 80 57 03 20",
    "sg:postcode":"4960",
    "sg:province":"Li\u00e8ge",
    "wof:name":"Leon Lemaire",
    "wof:placetype":"venue"
},
  "geometry": {"coordinates":[6.02546978,50.3857498169],"type":"Point"}
}