{
  "type": "Feature",
  "properties": {
    "iso:country":"BE",
    "sg:address":"Rue De Loyers 85",
    "sg:city":"Namur",
    "sg:classifiers":[
        {
            "category":"Cafe",
            "type":"Food & Drink"
        }
    ],
    "sg:phone":"+32 81 30 85 59",
    "sg:postcode":"5101",
    "sg:province":"Namur",
    "sg:tags":[
        "caf\u00e9s"
    ],
    "wof:name":"Dominique Dewitte",
    "wof:placetype":"venue"
},
  "geometry": {"coordinates":[4.904815197,50.4481887817],"type":"Point"}
}