{
  "type": "Feature",
  "properties": {
    "addr:full":"Boudewijnlaan 88 Knokke-heist West-Vlaanderen 8300",
    "addr:housenumber":"88",
    "addr:postcode":"8300",
    "addr:street":"Boudewijnlaan",
    "iso:country":"BE",
    "sg:address":"Boudewijnlaan 88",
    "sg:city":"Knokke-heist",
    "sg:orig_category":"Banques and organismes de cr\u00e9dit",
    "sg:phone":"+32 50 60 63 07",
    "sg:postcode":"8300",
    "sg:province":"West-Vlaanderen",
    "wof:name":"Centea",
    "wof:placetype":"venue"
},
  "geometry": {"coordinates":[3.2847709656,51.3426856995],"type":"Point"}
}