{
  "type": "Feature",
  "properties": {
    "addr:full":"Kerkstraat 248 Blankenberge West-Vlaanderen 8370",
    "addr:housenumber":"248",
    "addr:postcode":"8370",
    "addr:street":"Kerkstraat",
    "iso:country":"BE",
    "sg:address":"Kerkstraat 248",
    "sg:city":"Blankenberge",
    "sg:classifiers":[
        {
            "category":"Health Services",
            "subcategory":"Dentist",
            "type":"Services"
        }
    ],
    "sg:phone":"+32 50 41 45 78",
    "sg:postcode":"8370",
    "sg:province":"West-Vlaanderen",
    "wof:name":"Bosmans N",
    "wof:placetype":"venue"
},
  "geometry": {"coordinates":[3.1381080151,51.3079872131],"type":"Point"}
}