{
  "type": "Feature",
  "properties": {
    "addr:full":"Rillaarsebaan 173 Aarschot Vlaams-Brabant 3200",
    "addr:housenumber":"173",
    "addr:postcode":"3200",
    "iso:country":"BE",
    "sg:address":"Rillaarsebaan 173",
    "sg:city":"Aarschot",
    "sg:orig_category":"Producteurs de l\u00e9gumes",
    "sg:phone":"+32 16 56 32 28",
    "sg:postcode":"3200",
    "sg:province":"Vlaams-Brabant",
    "wof:name":"Jozef Jacobs",
    "wof:placetype":"venue"
},
  "geometry": {"coordinates":[4.8295297623,50.9657592773],"type":"Point"}
}