{
  "type": "Feature",
  "properties": {
    "iso:country":"BE",
    "sg:address":"Avenue Des Noisetiers 55",
    "sg:city":"Watermaal-bosvoorde/watermael-boitsfort",
    "sg:orig_category":"M\u00e9decins and sp\u00e9cialistes",
    "sg:phone":"+32 2 673 24 97",
    "sg:postcode":"1170",
    "sg:province":"Bruxelles-Capitale",
    "wof:name":"Hans-peter Z\u00c4hner",
    "wof:placetype":"venue"
},
  "geometry": {"coordinates":[4.4045262337,50.8046722412],"type":"Point"}
}