{
  "type": "Feature",
  "properties": {
    "iso:country":"BE",
    "sg:address":"Av. Bois Imp\u00c9rial Rognac 31",
    "sg:city":"Neupre",
    "sg:orig_category":"M\u00e9decins and sp\u00e9cialistes",
    "sg:phone":"+32 4 372 05 30",
    "sg:postcode":"4121",
    "sg:province":"Li\u00e8ge",
    "wof:name":"P. Ziad\u00c9",
    "wof:placetype":"venue"
},
  "geometry": {"coordinates":[5.4714522362,50.5540504456],"type":"Point"}
}