{
  "type": "Feature",
  "properties": {
    "iso:country":"BE",
    "sg:address":"Geelsebaan 150",
    "sg:city":"Retie",
    "sg:classifiers":[
        {
            "category":"Restaurant",
            "type":"Food & Drink"
        }
    ],
    "sg:phone":"+32 14 37 94 06",
    "sg:postcode":"2470",
    "sg:province":"Antwerpen",
    "sg:tags":[
        "caf\u00e9s"
    ],
    "wof:name":"Taverne De Witte Neet",
    "wof:placetype":"venue"
},
  "geometry": {"coordinates":[5.0693378448,51.2397117615],"type":"Point"}
}