{
  "type": "Feature",
  "properties": {
    "iso:country":"BE",
    "sg:address":"Rue Du Gaz 6",
    "sg:city":"Mouscron",
    "sg:classifiers":[
        {
            "category":"Bakery",
            "type":"Food & Drink"
        }
    ],
    "sg:phone":"+32 56 33 05 21",
    "sg:postcode":"7700",
    "sg:province":"Hainaut",
    "sg:tags":[
        "confectioner",
        "baker"
    ],
    "wof:name":"Pierre-alain",
    "wof:placetype":"venue"
},
  "geometry": {"coordinates":[3.2272109985,50.7423477173],"type":"Point"}
}