{
  "type": "Feature",
  "properties": {
    "iso:country":"BE",
    "sg:address":"Rue De Lowaige 32",
    "sg:city":"Awans",
    "sg:orig_category":"Agences d'exp\u00e9dition",
    "sg:phone":"+32 4 257 45 72",
    "sg:postcode":"4340",
    "sg:province":"Li\u00e8ge",
    "wof:name":"Vt Export Consulting",
    "wof:placetype":"venue"
},
  "geometry": {"coordinates":[5.461438179,50.7147903442],"type":"Point"}
}