{
  "type": "Feature",
  "properties": {
    "iso:country":"BE",
    "sg:address":"Ernest Claeslaan 2",
    "sg:city":"Aartselaar",
    "sg:classifiers":[
        {
            "category":"Landmark",
            "subcategory":"Scenic View",
            "type":"Public Place"
        }
    ],
    "sg:phone":"+32 3 887 06 52",
    "sg:postcode":"2630",
    "sg:province":"Antwerpen",
    "sg:tags":[
        "setting",
        "photographic"
    ],
    "wof:name":"Fotosetting J Robijns",
    "wof:placetype":"venue"
},
  "geometry": {"coordinates":[4.3908891678,51.1313972473],"type":"Point"}
}