{
  "type": "Feature",
  "properties": {
    "iso:country":"BE",
    "sg:address":"Chauss\u00e9e De Charleroi 266",
    "sg:city":"Fleurus",
    "sg:classifiers":[
        {
            "category":"Education",
            "subcategory":"Music School",
            "type":"Public Place"
        }
    ],
    "sg:phone":"+32 71 82 04 20",
    "sg:postcode":"6220",
    "sg:province":"Hainaut",
    "sg:tags":[
        "-",
        "teacher",
        "private"
    ],
    "wof:name":"Acad\u00e9mie De Musique",
    "wof:placetype":"venue"
},
  "geometry": {"coordinates":[4.5500707626,50.4808578491],"type":"Point"}
}