{
  "type": "Feature",
  "properties": {
    "addr:full":"Sergeyselsstraat 42 Antwerpen Antwerpen 2140",
    "addr:housenumber":"42",
    "addr:postcode":"2140",
    "addr:street":"Sergeyselsstraat",
    "iso:country":"BE",
    "sg:address":"Sergeyselsstraat 42",
    "sg:city":"Antwerpen",
    "sg:classifiers":[
        {
            "category":"Professional",
            "subcategory":"Business Services",
            "type":"Services"
        }
    ],
    "sg:phone":"+32 3 235 05 52",
    "sg:postcode":"2140",
    "sg:province":"Antwerpen",
    "sg:tags":[
        "aux",
        "diver",
        "entreprises"
    ],
    "wof:name":"Bureau Vulva Rex",
    "wof:placetype":"venue"
},
  "geometry": {"coordinates":[4.4332199097,51.2137565613],"type":"Point"}
}