{
  "type": "Feature",
  "properties": {
    "addr:full":". Bernissart (groot) Hainaut 7320",
    "addr:postcode":"7320",
    "addr:street":"Groot Hainaut",
    "iso:country":"BE",
    "sg:address":".",
    "sg:city":"Bernissart (groot)",
    "sg:orig_category":"Apotheken",
    "sg:phone":"+32 900 10 500",
    "sg:postcode":"7320",
    "sg:province":"Hainaut",
    "wof:name":"Apothekers Van Wacht",
    "wof:placetype":"venue"
},
  "geometry": {"coordinates":[3.6542139053,50.4827079773],"type":"Point"}
}