{
  "type": "Feature",
  "properties": {
    "iso:country":"BE",
    "sg:address":"Vredestraat 45",
    "sg:city":"Turnhout",
    "sg:classifiers":[
        {
            "category":"Social Services",
            "type":"Services"
        }
    ],
    "sg:phone":"+32 14 43 93 96",
    "sg:postcode":"2300",
    "sg:province":"Antwerpen",
    "wof:name":"Dagcentrum De Schommel",
    "wof:placetype":"venue"
},
  "geometry": {"coordinates":[4.9517989159,51.3282356262],"type":"Point"}
}