{
  "type": "Feature",
  "properties": {
    "iso:country":"BE",
    "sg:address":"Lostraat 16",
    "sg:city":"Alveringem",
    "sg:orig_category":"Rundveehouders",
    "sg:phone":"+32 58 29 83 36",
    "sg:postcode":"8691",
    "sg:province":"West-Vlaanderen",
    "wof:name":"Raphael Thomaere",
    "wof:placetype":"venue"
},
  "geometry": {"coordinates":[2.6269500256,50.9754981995],"type":"Point"}
}