{
  "type": "Feature",
  "properties": {
    "iso:country":"BE",
    "sg:address":"Tolpoortstraat 12",
    "sg:city":"Deinze",
    "sg:orig_category":"V\u00eatements",
    "sg:phone":"+32 9 380 39 50",
    "sg:postcode":"9800",
    "sg:province":"Oost-Vlaanderen",
    "wof:name":"Lagoon",
    "wof:placetype":"venue"
},
  "geometry": {"coordinates":[3.528744936,50.9821281433],"type":"Point"}
}