{
  "type": "Feature",
  "properties": {
    "iso:country":"BE",
    "sg:address":"Molenstraat 36",
    "sg:city":"Genk",
    "sg:orig_category":"Baby- and kinderkleding",
    "sg:phone":"+32 89 30 33 05",
    "sg:postcode":"3600",
    "sg:province":"Limburg",
    "wof:name":"Huis Lanoo",
    "wof:placetype":"venue"
},
  "geometry": {"coordinates":[5.5022530556,50.9641838074],"type":"Point"}
}