{
  "type": "Feature",
  "properties": {
    "addr:full":"Avenue De L'observatoire 357 Liege 1 Li\u00e8ge 4000",
    "addr:housenumber":"357;1",
    "addr:postcode":"4000",
    "addr:street":"Avenue De L'Observatoire;Liege",
    "iso:country":"BE",
    "sg:address":"Avenue De L'observatoire 357",
    "sg:city":"Liege 1",
    "sg:classifiers":[
        {
            "category":"Bars & Pubs",
            "type":"Food & Drink"
        }
    ],
    "sg:phone":"+32 4 253 02 50",
    "sg:postcode":"4000",
    "sg:province":"Li\u00e8ge",
    "sg:tags":[
        "tavern"
    ],
    "wof:name":"Wimbledon (le)",
    "wof:placetype":"venue"
},
  "geometry": {"coordinates":[5.5619659424,50.6294975281],"type":"Point"}
}