{
  "type": "Feature",
  "properties": {
    "addr:full":"Morisstraat 33 Sint-gillis/saint-gilles Bruxelles-Capitale 1060",
    "addr:housenumber":"33",
    "addr:postcode":"1060",
    "addr:street":"Morisstraat",
    "iso:country":"BE",
    "sg:address":"Morisstraat 33",
    "sg:city":"Sint-gillis/saint-gilles",
    "sg:orig_category":"Woningbouw",
    "sg:phone":"+32 2 544 04 00",
    "sg:postcode":"1060",
    "sg:province":"Bruxelles-Capitale",
    "wof:name":"Maintenance Travaux",
    "wof:placetype":"venue"
},
  "geometry": {"coordinates":[4.3515129089,50.8246841431],"type":"Point"}
}