{
  "type": "Feature",
  "properties": {
    "addr:full":"Rue De La For\u00cat 189 Seraing Li\u00e8ge 4100",
    "addr:housenumber":"189",
    "addr:postcode":"4100",
    "addr:street":"Rue De La Fore\u0302T",
    "iso:country":"BE",
    "sg:address":"Rue De La For\u00cat 189",
    "sg:city":"Seraing",
    "sg:orig_category":"Plomberie, chauffage and installations sanitaires",
    "sg:phone":"+32 4 336 03 12",
    "sg:postcode":"4100",
    "sg:province":"Li\u00e8ge",
    "wof:name":"Jacques Devosse",
    "wof:placetype":"venue"
},
  "geometry": {"coordinates":[5.5130000114,50.5847167969],"type":"Point"}
}