{
  "type": "Feature",
  "properties": {
    "iso:country":"BE",
    "sg:address":"Groenstraat 100",
    "sg:city":"Maasmechelen",
    "sg:orig_category":"Quincailleries. Plomberie, chauffage and installations sanitaires",
    "sg:phone":"+32 89 76 01 19",
    "sg:postcode":"3630",
    "sg:province":"Limburg",
    "wof:name":"Schreurs Saniver",
    "wof:placetype":"venue"
},
  "geometry": {"coordinates":[5.6961350441,50.963848114],"type":"Point"}
}