{
  "type": "Feature",
  "properties": {
    "iso:country":"BE",
    "sg:address":"Rue Priessevoye 5",
    "sg:city":"Blegny",
    "sg:orig_category":"Onderdelen and accessoires voor auto's",
    "sg:phone":"+32 4 362 91 22",
    "sg:postcode":"4671",
    "sg:province":"Li\u00e8ge",
    "wof:name":"Pneus Simonis",
    "wof:placetype":"venue"
},
  "geometry": {"coordinates":[5.6636791229,50.6577796936],"type":"Point"}
}