{
  "type": "Feature",
  "properties": {
    "iso:country":"BE",
    "sg:address":"Avenue Jean Mermoz 33",
    "sg:city":"Gosselies",
    "sg:classifiers":[
        {
            "category":"Government",
            "subcategory":"Court House",
            "type":"Public Place"
        }
    ],
    "sg:phone":"+32 71 34 91 11",
    "sg:postcode":"6041",
    "sg:province":"Hainaut",
    "sg:tags":[
        "bench",
        "saw",
        "circular"
    ],
    "wof:name":"De Pauw International S.a.",
    "wof:placetype":"venue"
},
  "geometry": {"coordinates":[4.4754152298,50.4759292603],"type":"Point"}
}