{
  "type": "Feature",
  "properties": {
    "iso:country":"BE",
    "sg:address":"Kasteelstraat 82",
    "sg:city":"De Panne",
    "sg:classifiers":[
        {
            "category":"Shopping",
            "subcategory":"Florist",
            "type":"Retail Goods"
        }
    ],
    "sg:phone":"+32 58 41 32 60",
    "sg:postcode":"8660",
    "sg:province":"West-Vlaanderen",
    "wof:name":"Camelia",
    "wof:placetype":"venue"
},
  "geometry": {"coordinates":[2.5914230347,51.095905304],"type":"Point"}
}