{
  "type": "Feature",
  "properties": {
    "iso:country":"BE",
    "sg:address":"Tervuursesteenweg 9",
    "sg:city":"Leuven (heverlee)",
    "sg:classifiers":[
        {
            "category":"Personal",
            "subcategory":"Nail Salon",
            "type":"Services"
        }
    ],
    "sg:phone":"+32 16 20 31 57",
    "sg:postcode":"3001",
    "sg:province":"Vlaams-Brabant",
    "sg:tags":[
        "pedicure"
    ],
    "wof:name":"Relax Schoonheidssalon",
    "wof:placetype":"venue"
},
  "geometry": {"coordinates":[4.6828489304,50.8766288757],"type":"Point"}
}