{
  "type": "Feature",
  "properties": {
    "addr:full":"Boulevard Brand Whitlock 2 Bruxelles (woluwe-saint-pierre) Bruxelles-Capitale 1150",
    "addr:housenumber":"2",
    "addr:postcode":"1150",
    "addr:street":"Boulevard Brand Whitlock",
    "iso:country":"BE",
    "sg:address":"Boulevard Brand Whitlock 2",
    "sg:city":"Bruxelles (woluwe-saint-pierre)",
    "sg:classifiers":[
        {
            "category":"Education",
            "subcategory":"Special Training",
            "type":"Public Place"
        }
    ],
    "sg:phone":"+32 2 739 37 49",
    "sg:postcode":"1150",
    "sg:province":"Bruxelles-Capitale",
    "sg:tags":[
        "-",
        "processing",
        "data"
    ],
    "wof:name":"Ichec-entreprises",
    "wof:placetype":"venue"
},
  "geometry": {"coordinates":[4.4083528519,50.8382835388],"type":"Point"}
}