{
  "type": "Feature",
  "properties": {
    "iso:country":"BE",
    "sg:address":"Bavikhoofsestraat 8",
    "sg:city":"Wielsbeke (ooigem)",
    "sg:orig_category":"Leisure articles",
    "sg:phone":"+32 56 66 61 72",
    "sg:postcode":"8710",
    "sg:province":"West-Vlaanderen",
    "wof:name":"Lerouge J",
    "wof:placetype":"venue"
},
  "geometry": {"coordinates":[3.3354249001,50.8928871155],"type":"Point"}
}