{
  "type": "Feature",
  "properties": {
    "iso:country":"BE",
    "sg:address":"Mostreystraat 9",
    "sg:city":"De Haan",
    "sg:orig_category":"M\u00e9decins and sp\u00e9cialistes",
    "sg:phone":"+32 50 41 24 85",
    "sg:postcode":"8420",
    "sg:province":"West-Vlaanderen",
    "wof:name":"Johan Lecluyse",
    "wof:placetype":"venue"
},
  "geometry": {"coordinates":[3.0829091072,51.3020591736],"type":"Point"}
}