{
  "type": "Feature",
  "properties": {
    "iso:country":"BE",
    "sg:address":"Nieuwe Steenweg 7",
    "sg:city":"Zuienkerke",
    "sg:classifiers":[
        {
            "category":"Health Services",
            "subcategory":"Doctor",
            "type":"Services"
        }
    ],
    "sg:phone":"+32 50 41 47 82",
    "sg:postcode":"8377",
    "sg:province":"West-Vlaanderen",
    "sg:tags":[
        "medicinephysicians",
        "surgeon"
    ],
    "wof:name":"Bertrem L",
    "wof:placetype":"venue"
},
  "geometry": {"coordinates":[3.1619288921,51.2674331665],"type":"Point"}
}