{
  "type": "Feature",
  "properties": {
    "iso:country":"BE",
    "sg:address":"Haasstrasse 17",
    "sg:city":"Eupen",
    "sg:classifiers":[
        {
            "category":"Personal",
            "subcategory":"Beauty Salon",
            "type":"Services"
        }
    ],
    "sg:phone":"+32 87 55 54 35",
    "sg:postcode":"4700",
    "sg:province":"Li\u00e8ge",
    "sg:tags":[
        "de",
        "coiffure"
    ],
    "wof:name":"Frisierstudio-negerle",
    "wof:placetype":"venue"
},
  "geometry": {"coordinates":[6.0373721123,50.6235046387],"type":"Point"}
}