{
  "type": "Feature",
  "properties": {
    "addr:full":"Dijken 1 Damme West-Vlaanderen 8340",
    "addr:housenumber":"1",
    "addr:postcode":"8340",
    "addr:street":"Dijken",
    "iso:country":"BE",
    "sg:address":"Dijken 1",
    "sg:city":"Damme",
    "sg:orig_category":"Rundveehouders",
    "sg:phone":"+32 50 35 44 93",
    "sg:postcode":"8340",
    "sg:province":"West-Vlaanderen",
    "wof:name":"Ivan Dhooge",
    "wof:placetype":"venue"
},
  "geometry": {"coordinates":[3.3655569553,51.2008934021],"type":"Point"}
}