{
  "type": "Feature",
  "properties": {
    "addr:full":"Jeruzalemstraat 29 Geluwe West-Vlaanderen 8940",
    "addr:housenumber":"29",
    "addr:postcode":"8940",
    "addr:street":"Jeruzalemstraat",
    "iso:country":"BE",
    "sg:address":"Jeruzalemstraat 29",
    "sg:city":"Geluwe",
    "sg:orig_category":"Elektrische installaties voor woningen HERSTELLING ELEKTRISCHE HUISHOUDAPPARATEN Huishoudapparaten, ",
    "sg:phone":"+32 56 51 30 28",
    "sg:postcode":"8940",
    "sg:province":"West-Vlaanderen",
    "wof:name":"Electro Lernout",
    "wof:placetype":"venue"
},
  "geometry": {"coordinates":[3.0736339092,50.8120269775],"type":"Point"}
}