{
  "type": "Feature",
  "properties": {
    "iso:country":"BE",
    "sg:address":"Naamsesteenweg 60",
    "sg:city":"Leuven",
    "sg:orig_category":"Kapsalons",
    "sg:phone":"+32 16 23 05 74",
    "sg:postcode":"3001",
    "sg:province":"Vlaams-Brabant",
    "wof:name":"Coiffure Men's World",
    "wof:placetype":"venue"
},
  "geometry": {"coordinates":[4.6969571114,50.8670578003],"type":"Point"}
}