{
  "type": "Feature",
  "properties": {
    "addr:full":"Kapellevelden 39 Putte Antwerpen 2580",
    "addr:housenumber":"39",
    "addr:postcode":"2580",
    "addr:street":"Kapellevelden",
    "iso:country":"BE",
    "sg:address":"Kapellevelden 39",
    "sg:city":"Putte",
    "sg:classifiers":[
        {
            "category":"Building & Trades",
            "subcategory":"Construction",
            "type":"Services"
        }
    ],
    "sg:phone":"+32 15 75 72 26",
    "sg:postcode":"2580",
    "sg:province":"Antwerpen",
    "sg:tags":[
        "stucco",
        "contractor"
    ],
    "wof:name":"Van Den Broeck L",
    "wof:placetype":"venue"
},
  "geometry": {"coordinates":[4.6258430481,51.0638847351],"type":"Point"}
}