{
  "type": "Feature",
  "properties": {
    "addr:full":"Looiend 21 Retie Antwerpen 2470",
    "addr:housenumber":"21",
    "addr:postcode":"2470",
    "addr:street":"Looiend",
    "iso:country":"BE",
    "sg:address":"Looiend 21",
    "sg:city":"Retie",
    "sg:classifiers":[
        {
            "category":"Structure",
            "subcategory":"Office Building",
            "type":"Public Place"
        }
    ],
    "sg:phone":"+32 14 37 01 72",
    "sg:postcode":"2470",
    "sg:province":"Antwerpen",
    "sg:tags":[
        "drawing"
    ],
    "wof:name":"Swinnen J",
    "wof:placetype":"venue"
},
  "geometry": {"coordinates":[5.0627379417,51.2779502869],"type":"Point"}
}