{
  "type": "Feature",
  "properties": {
    "iso:country":"BE",
    "sg:address":"Baalhoek 25 Box 3",
    "sg:city":"Grimbergen (strombeek-bever)",
    "sg:classifiers":[
        {
            "category":"Real Estate",
            "subcategory":"Architect",
            "type":"Services"
        }
    ],
    "sg:phone":"+32 2 267 53 10",
    "sg:postcode":"1853",
    "sg:province":"Vlaams-Brabant",
    "wof:name":"Nys A",
    "wof:placetype":"venue"
},
  "geometry": {"coordinates":[4.352189064,50.9049453735],"type":"Point"}
}