{
  "type": "Feature",
  "properties": {
    "iso:country":"BE",
    "sg:address":"Berkenlaan 2",
    "sg:city":"Kruibeke",
    "sg:classifiers":[
        {
            "category":"Health Services",
            "subcategory":"Dentist",
            "type":"Services"
        }
    ],
    "sg:phone":"+32 3 774 45 92",
    "sg:postcode":"9150",
    "sg:province":"Oost-Vlaanderen",
    "wof:name":"Boons E",
    "wof:placetype":"venue"
},
  "geometry": {"coordinates":[4.3091301918,51.1702461243],"type":"Point"}
}