{
  "type": "Feature",
  "properties": {
    "iso:country":"BE",
    "sg:address":"Coo 1",
    "sg:city":"Stavelot",
    "sg:classifiers":[
        {
            "category":"Restaurant",
            "type":"Food & Drink"
        }
    ],
    "sg:phone":"+32 80 68 53 00",
    "sg:postcode":"4970",
    "sg:province":"Li\u00e8ge",
    "wof:name":"Au Coin Fleuri",
    "wof:placetype":"venue"
},
  "geometry": {"coordinates":[5.879281044,50.3964614868],"type":"Point"}
}