{
  "type": "Feature",
  "properties": {
    "iso:country":"BE",
    "sg:address":"Nijlense Steenweg 61",
    "sg:city":"Herenthout",
    "sg:classifiers":[
        {
            "category":"Farming",
            "subcategory":"Livestock Farm",
            "type":"Manufacturing & Wholesale Goods"
        }
    ],
    "sg:phone":"+32 14 51 30 79",
    "sg:postcode":"2270",
    "sg:province":"Antwerpen",
    "sg:tags":[
        "buyer"
    ],
    "wof:name":"Krieckemans J",
    "wof:placetype":"venue"
},
  "geometry": {"coordinates":[4.7516899109,51.1404418945],"type":"Point"}
}