{
  "type": "Feature",
  "properties": {
    "addr:full":"Rue Du Teris Seraing Li\u00e8ge 4100",
    "addr:postcode":"4100",
    "addr:street":"Rue Du Teris",
    "iso:country":"BE",
    "sg:address":"Rue Du Teris",
    "sg:city":"Seraing",
    "sg:orig_category":"Wall And Ceiling Paints",
    "sg:phone":"+32 4 385 07 07",
    "sg:postcode":"4100",
    "sg:province":"Li\u00e8ge",
    "wof:name":"Houben S.a.",
    "wof:placetype":"venue"
},
  "geometry": {"coordinates":[5.4970769882,50.6005325317],"type":"Point"}
}