{
  "type": "Feature",
  "properties": {
    "iso:country":"BE",
    "sg:address":"Vlamingenstraat 2",
    "sg:city":"Leuven",
    "sg:orig_category":"Drukkerijen and copyshops",
    "sg:phone":"+32 16 23 78 38",
    "sg:postcode":"3000",
    "sg:province":"Vlaams-Brabant",
    "wof:name":"Print & Printing Shop",
    "wof:placetype":"venue"
},
  "geometry": {"coordinates":[4.7056078911,50.8761253357],"type":"Point"}
}