{
  "type": "Feature",
  "properties": {
    "iso:country":"BE",
    "sg:address":"Maastrichtersteenweg 236",
    "sg:city":"Hasselt",
    "sg:orig_category":"Moteurs, transformateurs and groupes \u00e9lectrog\u00e8nes Fab. Motos. R\u00e9parations and entretien de motos",
    "sg:phone":"+32 11 22 24 71",
    "sg:postcode":"3500",
    "sg:province":"Limburg",
    "wof:name":"Honda",
    "wof:placetype":"venue"
},
  "geometry": {"coordinates":[5.3574271202,50.9280853271],"type":"Point"}
}