{
  "type": "Feature",
  "properties": {
    "iso:country":"BE",
    "sg:address":"Rue Du Progr\u00c8s 323",
    "sg:city":"Brussel/bruxelles",
    "sg:orig_category":"Salles de spectacles. Production de films, t\u00e9l\u00e9films and vid\u00e9os. Services divers aux entreprises",
    "sg:phone":"+32 2 201 03 69",
    "sg:postcode":"1030",
    "sg:province":"Bruxelles-Capitale",
    "wof:name":"De Smaakmakerij",
    "wof:placetype":"venue"
},
  "geometry": {"coordinates":[4.3629488945,50.8661575317],"type":"Point"}
}