{
  "type": "Feature",
  "properties": {
    "addr:full":"Rue Des Forgerons 102 Charleroi Hainaut 6001",
    "addr:housenumber":"102",
    "addr:postcode":"6001",
    "addr:street":"Rue Des Forgerons;Hainaut",
    "iso:country":"BE",
    "sg:address":"Rue Des Forgerons 102",
    "sg:city":"Charleroi",
    "sg:classifiers":[
        {
            "category":"Food & Beverages",
            "subcategory":"Fruits & Vegetables",
            "type":"Retail Goods"
        }
    ],
    "sg:phone":"+32 71 43 11 84",
    "sg:postcode":"6001",
    "sg:province":"Hainaut",
    "sg:tags":[
        "l\u00e9gumes",
        "gr"
    ],
    "wof:name":"Fruits Edgard",
    "wof:placetype":"venue"
},
  "geometry": {"coordinates":[4.4531960487,50.3923377991],"type":"Point"}
}