{
  "type": "Feature",
  "properties": {
    "addr:full":"Arnhoutstraat 61 Sint-niklaas Oost-Vlaanderen 9111",
    "addr:housenumber":"61",
    "addr:postcode":"9111",
    "addr:street":"Arnhoutstraat",
    "iso:country":"BE",
    "sg:address":"Arnhoutstraat 61",
    "sg:city":"Sint-niklaas",
    "sg:orig_category":"Dranken",
    "sg:phone":"+32 3 776 62 00",
    "sg:postcode":"9111",
    "sg:province":"Oost-Vlaanderen",
    "wof:name":"Wijnen G.-h.",
    "wof:placetype":"venue"
},
  "geometry": {"coordinates":[4.11378479,51.1510467529],"type":"Point"}
}