{
  "type": "Feature",
  "properties": {
    "iso:country":"BE",
    "sg:address":"Rue Faider 14",
    "sg:city":"Sint-gillis/saint-gilles",
    "sg:orig_category":"Artistes ind\u00e9pendants",
    "sg:phone":"+32 2 538 33 31",
    "sg:postcode":"1060",
    "sg:province":"Bruxelles-Capitale",
    "wof:name":"Colette Bitker",
    "wof:placetype":"venue"
},
  "geometry": {"coordinates":[4.3566141129,50.8290328979],"type":"Point"}
}