{
  "type": "Feature",
  "properties": {
    "addr:full":"Vaartstraat 18 Ranst Antwerpen 2520",
    "addr:housenumber":"18",
    "addr:postcode":"2520",
    "addr:street":"Vaartstraat",
    "iso:country":"BE",
    "sg:address":"Vaartstraat 18",
    "sg:city":"Ranst",
    "sg:orig_category":"Secretariaatsdiensten",
    "sg:phone":"+32 3 820 16 11",
    "sg:postcode":"2520",
    "sg:province":"Antwerpen",
    "wof:name":"I D P C",
    "wof:placetype":"venue"
},
  "geometry": {"coordinates":[4.5762147903,51.2034034729],"type":"Point"}
}