{
  "type": "Feature",
  "properties": {
    "addr:full":"Rue Delcour 11 Onhaye (anth\u00e9e) Namur 5520",
    "addr:housenumber":"11",
    "addr:postcode":"5520",
    "addr:street":"Rue Delcour;Anthe\u0301E",
    "iso:country":"BE",
    "sg:address":"Rue Delcour 11",
    "sg:city":"Onhaye (anth\u00e9e)",
    "sg:classifiers":[
        {
            "category":"Home & Garden",
            "subcategory":"Garden Supply",
            "type":"Retail Goods"
        }
    ],
    "sg:phone":"+32 82 68 85 23",
    "sg:postcode":"5520",
    "sg:province":"Namur",
    "sg:tags":[
        "lawn",
        "mower"
    ],
    "wof:name":"Krutt Et Fils",
    "wof:placetype":"venue"
},
  "geometry": {"coordinates":[4.762237072,50.2404556274],"type":"Point"}
}