{
  "type": "Feature",
  "properties": {
    "addr:full":"Tramstraat 36 Tielt West-Vlaanderen 8700",
    "addr:housenumber":"36",
    "addr:postcode":"8700",
    "addr:street":"Tramstraat",
    "iso:country":"BE",
    "sg:address":"Tramstraat 36",
    "sg:city":"Tielt",
    "sg:orig_category":"Plaatsen van vloer- and muurbekleding Royal Canin",
    "sg:phone":"+32 51 40 30 10",
    "sg:postcode":"8700",
    "sg:province":"West-Vlaanderen",
    "wof:name":"Braekevelt-van Severen",
    "wof:placetype":"venue"
},
  "geometry": {"coordinates":[3.3290009499,51.0019111633],"type":"Point"}
}