{
  "type": "Feature",
  "properties": {
    "iso:country":"BE",
    "sg:address":"Rue Charles-steenebruggen 40",
    "sg:city":"Li\u00e8ge 1 (li\u00e8ge 2)",
    "sg:classifiers":[
        {
            "category":"Bars & Pubs",
            "type":"Food & Drink"
        }
    ],
    "sg:phone":"+32 4 341 09 12",
    "sg:postcode":"4020",
    "sg:province":"Li\u00e8ge",
    "wof:name":"Boulevard (le)",
    "wof:placetype":"venue"
},
  "geometry": {"coordinates":[5.5882220268,50.6263008118],"type":"Point"}
}