{
  "type": "Feature",
  "properties": {
    "addr:full":"Rue Des Masnuy 14 Jurbise Hainaut 7050",
    "addr:housenumber":"14",
    "addr:postcode":"7050",
    "addr:street":"Rue Des Masnuy",
    "iso:country":"BE",
    "sg:address":"Rue Des Masnuy 14",
    "sg:city":"Jurbise",
    "sg:classifiers":[
        {
            "category":"Building & Trades",
            "subcategory":"Electrical",
            "type":"Services"
        }
    ],
    "sg:phone":"+32 65 22 98 69",
    "sg:postcode":"7050",
    "sg:province":"Hainaut",
    "sg:tags":[
        "electric",
        "-",
        "housewiring",
        "contractor"
    ],
    "wof:name":"Bastien Nicolas",
    "wof:placetype":"venue"
},
  "geometry": {"coordinates":[3.9145820141,50.5285072327],"type":"Point"}
}