{
  "type": "Feature",
  "properties": {
    "iso:country":"BE",
    "sg:address":"Nekkersvijverstraat 62-64",
    "sg:city":"Gent (sint-amandsberg)",
    "sg:classifiers":[
        {
            "category":"Banks & Credit Unions",
            "subcategory":"Investment Brokerage",
            "type":"Services"
        }
    ],
    "sg:phone":"+32 9 222 94 71",
    "sg:postcode":"9040",
    "sg:province":"Oost-Vlaanderen",
    "sg:tags":[
        "printing",
        "-"
    ],
    "wof:name":"De Sloovere",
    "wof:placetype":"venue"
},
  "geometry": {"coordinates":[3.7560739517,51.049118042],"type":"Point"}
}