{
  "type": "Feature",
  "properties": {
    "addr:full":"Rue L\u00c9on Colin 17 Mettet Namur 5640",
    "addr:housenumber":"17",
    "addr:postcode":"5640",
    "addr:street":"Rue Le\u0301On Colin",
    "iso:country":"BE",
    "sg:address":"Rue L\u00c9on Colin 17",
    "sg:city":"Mettet",
    "sg:orig_category":"Bouwmaterialen Gh",
    "sg:phone":"+32 71 72 96 65",
    "sg:postcode":"5640",
    "sg:province":"Namur",
    "wof:name":"Fe. Crepin",
    "wof:placetype":"venue"
},
  "geometry": {"coordinates":[4.6548118591,50.325466156],"type":"Point"}
}