{
  "type": "Feature",
  "properties": {
    "iso:country":"BE",
    "sg:address":"Zavelstraat 202",
    "sg:city":"Zaventem (sterrebeek)",
    "sg:classifiers":[
        {
            "category":"Personal",
            "subcategory":"Beauty Salon",
            "type":"Services"
        }
    ],
    "sg:phone":"+32 2 731 25 46",
    "sg:postcode":"1933",
    "sg:province":"Vlaams-Brabant",
    "wof:name":"Sonja",
    "wof:placetype":"venue"
},
  "geometry": {"coordinates":[4.4951758385,50.8681983948],"type":"Point"}
}