{
  "type": "Feature",
  "properties": {
    "iso:country":"BE",
    "sg:address":"Rue De Durbuy 16",
    "sg:city":"Hotton",
    "sg:classifiers":[
        {
            "category":"Arts & Performance",
            "subcategory":"Music",
            "type":"Entertainment"
        }
    ],
    "sg:phone":"+32 84 46 65 14",
    "sg:postcode":"6990",
    "sg:province":"Luxembourg",
    "sg:tags":[
        "disc-jockeys"
    ],
    "wof:name":"New Kiss Junior",
    "wof:placetype":"venue"
},
  "geometry": {"coordinates":[5.4395017624,50.2839431763],"type":"Point"}
}