{
  "type": "Feature",
  "properties": {
    "iso:country":"BE",
    "sg:address":"Rafhay 2",
    "sg:city":"Olne",
    "sg:orig_category":"Rundveehouders",
    "sg:phone":"+32 87 26 71 06",
    "sg:postcode":"4877",
    "sg:province":"Li\u00e8ge",
    "wof:name":"Baar & Fils",
    "wof:placetype":"venue"
},
  "geometry": {"coordinates":[5.7512450218,50.5951843262],"type":"Point"}
}