{
  "type": "Feature",
  "properties": {
    "iso:country":"BE",
    "sg:address":"Velsterheide 6",
    "sg:city":"Zoersel",
    "sg:orig_category":"Bois Gr. Quincailleries. Boissons. Cr\u00e9meries",
    "sg:phone":"+32 3 383 03 70",
    "sg:postcode":"2980",
    "sg:province":"Antwerpen",
    "wof:name":"Alfons Cautereels",
    "wof:placetype":"venue"
},
  "geometry": {"coordinates":[4.638630867,51.2364234924],"type":"Point"}
}