{
  "type": "Feature",
  "properties": {
    "addr:full":"Rue De L'abbaye 4 Lobbes Hainaut 6540",
    "addr:housenumber":"4",
    "addr:postcode":"6540",
    "addr:street":"Rue De L'Abbaye",
    "iso:country":"BE",
    "sg:address":"Rue De L'abbaye 4",
    "sg:city":"Lobbes",
    "sg:orig_category":"Entretien and r\u00e9parations de voitures",
    "sg:phone":"+32 71 59 41 68",
    "sg:postcode":"6540",
    "sg:province":"Hainaut",
    "wof:name":"Carrosserie Bockholtz",
    "wof:placetype":"venue"
},
  "geometry": {"coordinates":[4.2649669647,50.3457069397],"type":"Point"}
}