{
  "type": "Feature",
  "properties": {
    "iso:country":"BE",
    "sg:address":"Diepenbekerweg 10",
    "sg:city":"Hasselt",
    "sg:classifiers":[
        {
            "category":"Professional",
            "type":"Services"
        }
    ],
    "sg:phone":"+32 11 35 25 48",
    "sg:postcode":"3500",
    "sg:province":"Limburg",
    "sg:tags":[
        "industrial",
        "automation"
    ],
    "wof:name":"Es International Nv",
    "wof:placetype":"venue"
},
  "geometry": {"coordinates":[5.3620529175,50.925994873],"type":"Point"}
}