{
  "type": "Feature",
  "properties": {
    "addr:full":"Place Gutenberg 15 Seraing Li\u00e8ge 4102",
    "addr:housenumber":"15",
    "addr:postcode":"4102",
    "addr:street":"Place Gutenberg",
    "iso:country":"BE",
    "sg:address":"Place Gutenberg 15",
    "sg:city":"Seraing",
    "sg:orig_category":"Location de logements sociaux",
    "sg:phone":"+32 4 336 19 50",
    "sg:postcode":"4102",
    "sg:province":"Li\u00e8ge",
    "wof:name":"Le Home Ougr\u00c9en",
    "wof:placetype":"venue"
},
  "geometry": {"coordinates":[5.5369930267,50.5924606323],"type":"Point"}
}