{
  "type": "Feature",
  "properties": {
    "iso:country":"BE",
    "sg:address":"Oppuurseweg 49",
    "sg:city":"Sint-amands (lippelo)",
    "sg:classifiers":[
        {
            "category":"Shopping",
            "subcategory":"Party Supplies",
            "type":"Retail Goods"
        }
    ],
    "sg:phone":"+32 52 33 00 20",
    "sg:postcode":"2890",
    "sg:province":"Antwerpen",
    "sg:tags":[
        "decoration",
        "exhibition"
    ],
    "wof:name":"Vermeren G",
    "wof:placetype":"venue"
},
  "geometry": {"coordinates":[4.2470378876,51.0497207642],"type":"Point"}
}