{
  "type": "Feature",
  "properties": {
    "addr:full":"Zavelstraat 43 Herzele Oost-Vlaanderen 9550",
    "addr:housenumber":"43",
    "addr:postcode":"9550",
    "addr:street":"Zavelstraat;Oost-Vlaanderen",
    "iso:country":"BE",
    "sg:address":"Zavelstraat 43",
    "sg:city":"Herzele",
    "sg:orig_category":"Loodgieterij, verwarming and sanitaire installaties",
    "sg:phone":"+32 54 50 19 74",
    "sg:postcode":"9550",
    "sg:province":"Oost-Vlaanderen",
    "wof:name":"Van Den Bossche Marc",
    "wof:placetype":"venue"
},
  "geometry": {"coordinates":[3.8974289894,50.8557014465],"type":"Point"}
}