{
  "type": "Feature",
  "properties": {
    "iso:country":"BE",
    "sg:address":"Haachtsesteenweg 199",
    "sg:city":"Melsbroek",
    "sg:orig_category":"Aircraft Parts, Components, Modules, And Construction Supplies",
    "sg:phone":"+32 2 751 81 10",
    "sg:postcode":"1820",
    "sg:province":"Vlaams-Brabant",
    "wof:name":"The Cessna Aircraft Company Nv",
    "wof:placetype":"venue"
},
  "geometry": {"coordinates":[4.4915270805,50.9149093628],"type":"Point"}
}