{
  "type": "Feature",
  "properties": {
    "addr:full":"Industrieweg 1301 Herk-de-stad Limburg 3540",
    "addr:housenumber":"1301",
    "addr:postcode":"3540",
    "addr:street":"Industrieweg",
    "iso:country":"BE",
    "sg:address":"Industrieweg 1301",
    "sg:city":"Herk-de-stad",
    "sg:orig_category":"Produits \u00e0 base de pommes de terre Fruits and l\u00e9gumes Gr",
    "sg:phone":"+32 13 55 26 56",
    "sg:postcode":"3540",
    "sg:province":"Limburg",
    "wof:name":"Aagros",
    "wof:placetype":"venue"
},
  "geometry": {"coordinates":[5.1707901955,50.9454612732],"type":"Point"}
}