{
  "type": "Feature",
  "properties": {
    "addr:full":"Rooyerstraat 2b Bree Limburg 3960",
    "addr:housenumber":"2b",
    "addr:postcode":"3960",
    "addr:street":"Rooyerstraat",
    "iso:country":"BE",
    "sg:address":"Rooyerstraat 2b",
    "sg:city":"Bree",
    "sg:classifiers":[
        {
            "category":"Banks & Credit Unions",
            "subcategory":"Investment Brokerage",
            "type":"Services"
        }
    ],
    "sg:phone":"+32 89 47 34 60",
    "sg:postcode":"3960",
    "sg:province":"Limburg",
    "sg:tags":[
        "aid",
        "rehabiliation",
        "apparatus"
    ],
    "wof:name":"Revilax",
    "wof:placetype":"venue"
},
  "geometry": {"coordinates":[5.5958828926,51.1179885864],"type":"Point"}
}