{
  "type": "Feature",
  "properties": {
    "iso:country":"BE",
    "sg:address":"Oude Vaartstraat 12",
    "sg:city":"Turnhout",
    "sg:orig_category":"Non-Classified Establishments",
    "sg:phone":"+32 14 88 01 51",
    "sg:postcode":"2300",
    "sg:province":"Antwerpen",
    "wof:name":"Clb Kempen",
    "wof:placetype":"venue"
},
  "geometry": {"coordinates":[4.9471030235,51.3265914917],"type":"Point"}
}