{
  "type": "Feature",
  "properties": {
    "addr:full":"Steenvoordelaan 54 Gent Oost-Vlaanderen 9050",
    "addr:housenumber":"54",
    "addr:postcode":"9050",
    "addr:street":"Steenvoordelaan;Oost-Vlaanderen",
    "iso:country":"BE",
    "sg:address":"Steenvoordelaan 54",
    "sg:city":"Gent",
    "sg:orig_category":"Artiesten and kunstenaars",
    "sg:phone":"+32 9 231 34 26",
    "sg:postcode":"9050",
    "sg:province":"Oost-Vlaanderen",
    "wof:name":"Michel Verghote",
    "wof:placetype":"venue"
},
  "geometry": {"coordinates":[3.7554581165,51.0356025696],"type":"Point"}
}