{
  "type": "Feature",
  "properties": {
    "addr:full":"Koninksemsteenweg 66 Tongeren Limburg 3700",
    "addr:housenumber":"66",
    "addr:postcode":"3700",
    "addr:street":"Koninksemsteenweg",
    "iso:country":"BE",
    "sg:address":"Koninksemsteenweg 66",
    "sg:city":"Tongeren",
    "sg:orig_category":"Maisons de repos and r\u00e9sidences",
    "sg:phone":"+32 12 39 81 81",
    "sg:postcode":"3700",
    "sg:province":"Limburg",
    "wof:name":"Serviceflats Livinia",
    "wof:placetype":"venue"
},
  "geometry": {"coordinates":[5.4576239586,50.7768707275],"type":"Point"}
}