{
  "type": "Feature",
  "properties": {
    "iso:country":"BE",
    "sg:address":"Haandekotstraat 10",
    "sg:city":"Poperinge",
    "sg:orig_category":"Rundveehouders Stoelen and zitmeubelen Fab Varkenskwekers",
    "sg:phone":"+32 57 30 07 41",
    "sg:postcode":"8972",
    "sg:province":"West-Vlaanderen",
    "wof:name":"Linda Vantomme",
    "wof:placetype":"venue"
},
  "geometry": {"coordinates":[2.6240999699,50.8992538452],"type":"Point"}
}