{
  "type": "Feature",
  "properties": {
    "iso:country":"BE",
    "sg:address":"Rue Tout-y-faut 68",
    "sg:city":"La Louvi\u00c8re",
    "sg:orig_category":"Belastingconsulenten Diverse juridische dienstverlening",
    "sg:phone":"+32 64 21 72 88",
    "sg:postcode":"7110",
    "sg:province":"Hainaut",
    "wof:name":"Rolando Morelli",
    "wof:placetype":"venue"
},
  "geometry": {"coordinates":[4.1505050659,50.4826698303],"type":"Point"}
}