{
  "type": "Feature",
  "properties": {
    "iso:country":"BE",
    "sg:address":"Avenue Fran\u00e7ois Cornesse 111",
    "sg:city":"Aywaille",
    "sg:classifiers":[
        {
            "category":"Personal",
            "subcategory":"Psychics & Astrologers",
            "type":"Services"
        }
    ],
    "sg:phone":"+32 4 384 87 50",
    "sg:postcode":"4920",
    "sg:province":"Li\u00e8ge",
    "sg:tags":[
        "astrology"
    ],
    "wof:name":"Delta Blanc Belgique Asbl",
    "wof:placetype":"venue"
},
  "geometry": {"coordinates":[5.6625127792,50.4736557007],"type":"Point"}
}