{
  "type": "Feature",
  "properties": {
    "iso:country":"BE",
    "sg:address":"Pl Du Moulin 7",
    "sg:city":"Florenville",
    "sg:classifiers":[
        {
            "category":"Restaurant",
            "type":"Food & Drink"
        }
    ],
    "sg:phone":"+32 61 32 99 60",
    "sg:postcode":"6823",
    "sg:province":"Luxembourg",
    "wof:name":"Dumez J-l",
    "wof:placetype":"venue"
},
  "geometry": {"coordinates":[5.3308258057,49.6185073853],"type":"Point"}
}