{
  "type": "Feature",
  "properties": {
    "addr:full":"Pelikaanstraat 116 Antwerpen-statiekwartier Antwerpen 2018",
    "addr:housenumber":"116",
    "addr:postcode":"2018",
    "addr:street":"Pelikaanstraat",
    "iso:country":"BE",
    "sg:address":"Pelikaanstraat 116",
    "sg:city":"Antwerpen-statiekwartier",
    "sg:orig_category":"Accessoires vestimentaires",
    "sg:phone":"+32 3 233 50 30",
    "sg:postcode":"2018",
    "sg:province":"Antwerpen",
    "wof:name":"Utilus",
    "wof:placetype":"venue"
},
  "geometry": {"coordinates":[4.4206209183,51.2133369446],"type":"Point"}
}