{
  "type": "Feature",
  "properties": {
    "iso:country":"BE",
    "sg:address":"Schransdreef 117",
    "sg:city":"Overijse",
    "sg:classifiers":[
        {
            "category":"Health Services",
            "subcategory":"Health Practitioner",
            "type":"Services"
        }
    ],
    "sg:phone":"+32 2 687 69 42",
    "sg:postcode":"3090",
    "sg:province":"Vlaams-Brabant",
    "sg:tags":[
        "physiotherapist"
    ],
    "wof:name":"Moens Mj",
    "wof:placetype":"venue"
},
  "geometry": {"coordinates":[4.5065059662,50.7940483093],"type":"Point"}
}