{
  "type": "Feature",
  "properties": {
    "iso:country":"BE",
    "sg:address":"Kerkdreef 17",
    "sg:city":"Waregem",
    "sg:orig_category":"Imprimeries and copyshops",
    "sg:phone":"+32 56 72 71 00",
    "sg:postcode":"8791",
    "sg:province":"West-Vlaanderen",
    "wof:name":"Baert",
    "wof:placetype":"venue"
},
  "geometry": {"coordinates":[3.3452870846,50.8749351501],"type":"Point"}
}