{
  "type": "Feature",
  "properties": {
    "addr:full":"Carnotstraat 120 Antwerpen Antwerpen 2060",
    "addr:housenumber":"120",
    "addr:postcode":"2060",
    "addr:street":"Carnotstraat",
    "iso:country":"BE",
    "sg:address":"Carnotstraat 120",
    "sg:city":"Antwerpen",
    "sg:classifiers":[
        {
            "category":"Manufacturing",
            "subcategory":"Textiles",
            "type":"Manufacturing & Wholesale Goods"
        }
    ],
    "sg:phone":"+32 3 233 55 32",
    "sg:postcode":"2060",
    "sg:province":"Antwerpen",
    "sg:tags":[
        "clothing",
        "accessory"
    ],
    "wof:name":"Eider Nv",
    "wof:placetype":"venue"
},
  "geometry": {"coordinates":[4.4270100594,51.2176628113],"type":"Point"}
}