{
  "type": "Feature",
  "properties": {
    "addr:full":"Vuurstraat 2 Vorst/forest Bruxelles-Capitale 1190",
    "addr:housenumber":"2",
    "addr:postcode":"1190",
    "addr:street":"Vuurstraat;/ Forest",
    "iso:country":"BE",
    "sg:address":"Vuurstraat 2",
    "sg:city":"Vorst/forest",
    "sg:orig_category":"Diepvriesproducten Gh",
    "sg:phone":"+32 2 347 21 10",
    "sg:postcode":"1190",
    "sg:province":"Bruxelles-Capitale",
    "wof:name":"Luciano Tarantini",
    "wof:placetype":"venue"
},
  "geometry": {"coordinates":[4.3220219612,50.8212852478],"type":"Point"}
}