{
  "type": "Feature",
  "properties": {
    "iso:country":"BE",
    "sg:address":"Capucienenstraat 7",
    "sg:city":"Aarschot",
    "sg:orig_category":"Salles de conf\u00e9rences and de r\u00e9ceptions",
    "sg:phone":"+32 16 56 54 03",
    "sg:postcode":"3200",
    "sg:province":"Vlaams-Brabant",
    "wof:name":"'t Capucijntje",
    "wof:placetype":"venue"
},
  "geometry": {"coordinates":[4.8343057632,50.9847602844],"type":"Point"}
}