{
  "type": "Feature",
  "properties": {
    "iso:country":"BE",
    "sg:address":"Klinkaardstraat 200",
    "sg:city":"Kapellen",
    "sg:orig_category":"Transports routiers de marchandises",
    "sg:phone":"+32 3 660 13 70",
    "sg:postcode":"2950",
    "sg:province":"Antwerpen",
    "wof:name":"Van Wellen Stevedoring",
    "wof:placetype":"venue"
},
  "geometry": {"coordinates":[4.4143338203,51.3517951965],"type":"Point"}
}