{
  "type": "Feature",
  "properties": {
    "iso:country":"BE",
    "sg:address":"Rootstraat 92",
    "sg:city":"Tervuren",
    "sg:orig_category":"Producteurs de l\u00e9gumes. Producteurs de fruits",
    "sg:phone":"+32 2 767 02 15",
    "sg:postcode":"3080",
    "sg:province":"Vlaams-Brabant",
    "wof:name":"Robert Felix",
    "wof:placetype":"venue"
},
  "geometry": {"coordinates":[4.5619292259,50.8204460144],"type":"Point"}
}