{
  "type": "Feature",
  "properties": {
    "iso:country":"BE",
    "sg:address":"Stationsstraat 32-34",
    "sg:city":"Peer (wijchmaal)",
    "sg:classifiers":[
        {
            "category":"Shopping",
            "subcategory":"Bicycles & Sporting Goods",
            "type":"Retail Goods"
        }
    ],
    "sg:phone":"+32 11 63 27 84",
    "sg:postcode":"3990",
    "sg:province":"Limburg",
    "sg:tags":[
        "-"
    ],
    "wof:name":"Deckers N",
    "wof:placetype":"venue"
},
  "geometry": {"coordinates":[5.4037079811,51.1283988953],"type":"Point"}
}