{
  "type": "Feature",
  "properties": {
    "iso:country":"BE",
    "sg:address":"Briefdragerstraat 27",
    "sg:city":"Sint-jans-molenbeek/molenbeek-saint-jean",
    "sg:orig_category":"Artsen and specialisten",
    "sg:phone":"+32 2 414 07 34",
    "sg:postcode":"1080",
    "sg:province":"Bruxelles-Capitale",
    "wof:name":"Polyclinique",
    "wof:placetype":"venue"
},
  "geometry": {"coordinates":[4.3379001617,50.8558082581],"type":"Point"}
}