{
  "type": "Feature",
  "properties": {
    "iso:country":"BE",
    "sg:address":"Mechelbaan 215",
    "sg:city":"Putte",
    "sg:orig_category":"Pharmaciens",
    "sg:phone":"+32 15 75 64 31",
    "sg:postcode":"2580",
    "sg:province":"Antwerpen",
    "wof:name":"K. De Bauw",
    "wof:placetype":"venue"
},
  "geometry": {"coordinates":[4.6525201797,51.0606994629],"type":"Point"}
}