{
  "type": "Feature",
  "properties": {
    "addr:full":"Molstraat 22 Temse Oost-Vlaanderen 9140",
    "addr:housenumber":"22",
    "addr:postcode":"9140",
    "addr:street":"Molstraat",
    "iso:country":"BE",
    "sg:address":"Molstraat 22",
    "sg:city":"Temse",
    "sg:orig_category":"Woningbouw",
    "sg:phone":"+32 3 774 27 48",
    "sg:postcode":"9140",
    "sg:province":"Oost-Vlaanderen",
    "wof:name":"Bouwbedrijf Van De Perre",
    "wof:placetype":"venue"
},
  "geometry": {"coordinates":[4.2735519409,51.1358032227],"type":"Point"}
}