{
  "type": "Feature",
  "properties": {
    "iso:country":"BE",
    "sg:address":"Kasteelstraat 81",
    "sg:city":"Temse",
    "sg:classifiers":[
        {
            "category":"Utilities",
            "subcategory":"Fuel Oil & Lpg",
            "type":"Services"
        }
    ],
    "sg:phone":"+32 3 711 09 69",
    "sg:postcode":"9140",
    "sg:province":"Oost-Vlaanderen",
    "wof:name":"Godima-goossens Walter",
    "wof:placetype":"venue"
},
  "geometry": {"coordinates":[4.2222719193,51.1240959167],"type":"Point"}
}