{
  "type": "Feature",
  "properties": {
    "addr:full":"Madouplein 6 Sint-joost-ten-node/saint-josse-ten-noode Bruxelles-Capitale 1210",
    "addr:housenumber":"6",
    "addr:postcode":"1210",
    "addr:street":"Madouplein",
    "iso:country":"BE",
    "sg:address":"Madouplein 6",
    "sg:city":"Sint-joost-ten-node/saint-josse-ten-noode",
    "sg:classifiers":[
        {
            "category":"Restaurant",
            "type":"Food & Drink"
        }
    ],
    "sg:phone":"+32 2 218 18 56",
    "sg:postcode":"1210",
    "sg:province":"Bruxelles-Capitale",
    "sg:tags":[
        "caf\u00e9s"
    ],
    "wof:name":"Le Paddock",
    "wof:placetype":"venue"
},
  "geometry": {"coordinates":[4.3696570396,50.8490447998],"type":"Point"}
}