{
  "type": "Feature",
  "properties": {
    "addr:full":"Rue De La Hocaille 24 Grez-doiceau Brabant Wallon 1390",
    "addr:housenumber":"24",
    "addr:postcode":"1390",
    "addr:street":"Rue De La Hocaille",
    "iso:country":"BE",
    "sg:address":"Rue De La Hocaille 24",
    "sg:city":"Grez-doiceau",
    "sg:classifiers":[
        {
            "category":"Arena",
            "subcategory":"Sports Club",
            "type":"Entertainment"
        }
    ],
    "sg:phone":"+32 10 84 06 31",
    "sg:postcode":"1390",
    "sg:province":"Brabant Wallon",
    "sg:tags":[
        "de"
    ],
    "wof:name":"Tennis De La Plaine & Tennis De Grez",
    "wof:placetype":"venue"
},
  "geometry": {"coordinates":[4.6774530411,50.7510566711],"type":"Point"}
}