{
  "type": "Feature",
  "properties": {
    "addr:full":"Rue De La Perche 4 Colfontaine (p\u00e2turages) Hainaut 7340",
    "addr:housenumber":"4",
    "addr:postcode":"7340",
    "addr:street":"Rue De La Perche",
    "iso:country":"BE",
    "sg:address":"Rue De La Perche 4",
    "sg:city":"Colfontaine (p\u00e2turages)",
    "sg:classifiers":[
        {
            "category":"Shopping",
            "subcategory":"Optician",
            "type":"Retail Goods"
        }
    ],
    "sg:phone":"+32 65 65 19 90",
    "sg:postcode":"7340",
    "sg:province":"Hainaut",
    "sg:tags":[
        "-"
    ],
    "wof:name":"Pers'optique",
    "wof:placetype":"venue"
},
  "geometry": {"coordinates":[3.861907959,50.4080886841],"type":"Point"}
}