{
  "type": "Feature",
  "properties": {
    "iso:country":"BE",
    "sg:address":"Pastoor Van Neylenstraat 5",
    "sg:city":"Geel",
    "sg:orig_category":"Artsen and specialisten",
    "sg:phone":"+32 14 58 94 80",
    "sg:postcode":"2440",
    "sg:province":"Antwerpen",
    "wof:name":"Jozef R.s.m. Blonde",
    "wof:placetype":"venue"
},
  "geometry": {"coordinates":[4.9971599579,51.1616096497],"type":"Point"}
}