{
  "type": "Feature",
  "properties": {
    "addr:full":"Champs De Foyr 72 Jalhay Li\u00e8ge 4845",
    "addr:housenumber":"72",
    "addr:postcode":"4845",
    "addr:street":"Champs De Foyr",
    "iso:country":"BE",
    "sg:address":"Champs De Foyr 72",
    "sg:city":"Jalhay",
    "sg:classifiers":[
        {
            "category":"Health Services",
            "subcategory":"Health Practitioner",
            "type":"Services"
        }
    ],
    "sg:phone":"+32 87 64 72 02",
    "sg:postcode":"4845",
    "sg:province":"Li\u00e8ge",
    "sg:tags":[
        "physiotherapist"
    ],
    "wof:name":"Koninckx Suzanne",
    "wof:placetype":"venue"
},
  "geometry": {"coordinates":[5.9394540787,50.5656356812],"type":"Point"}
}