{
  "type": "Feature",
  "properties": {
    "addr:full":"Rue De Saupont 44 Bertrix Luxembourg 6880",
    "addr:housenumber":"44",
    "addr:postcode":"6880",
    "addr:street":"Rue De Saupont",
    "iso:country":"BE",
    "sg:address":"Rue De Saupont 44",
    "sg:city":"Bertrix",
    "sg:classifiers":[
        {
            "category":"Building & Trades",
            "subcategory":"Plumbing",
            "type":"Services"
        }
    ],
    "sg:phone":"+32 61 41 32 75",
    "sg:postcode":"6880",
    "sg:province":"Luxembourg",
    "sg:tags":[
        "repair",
        "mainten",
        "-",
        "central",
        "heating"
    ],
    "wof:name":"Arnould B",
    "wof:placetype":"venue"
},
  "geometry": {"coordinates":[5.2742681503,49.852394104],"type":"Point"}
}