{
  "type": "Feature",
  "properties": {
    "iso:country":"BE",
    "sg:address":"Buizegemlei 124bd4",
    "sg:city":"Edegem",
    "sg:orig_category":"Installatie van houten of kunststof schrijnwerk Installatie van metalen schrijnwerk",
    "sg:phone":"+32 475 24 23 44",
    "sg:postcode":"2650",
    "sg:province":"Antwerpen",
    "wof:name":"Alco",
    "wof:placetype":"venue"
},
  "geometry": {"coordinates":[4.4594888687,51.1513061523],"type":"Point"}
}