{
  "type": "Feature",
  "properties": {
    "addr:full":"Boulevard Pr\u00e9sident Kennedy 67 Mons Hainaut 7000",
    "addr:housenumber":"67",
    "addr:postcode":"7000",
    "addr:street":"Boulevard Pre\u0301Sident Kennedy;Hainaut",
    "iso:country":"BE",
    "sg:address":"Boulevard Pr\u00e9sident Kennedy 67",
    "sg:city":"Mons",
    "sg:classifiers":[
        {
            "category":"Utilities",
            "subcategory":"Telephone",
            "type":"Services"
        }
    ],
    "sg:phone":"+32 65 40 35 35",
    "sg:postcode":"7000",
    "sg:province":"Hainaut",
    "sg:tags":[
        "-",
        "internet"
    ],
    "wof:name":"Bmind Sa",
    "wof:placetype":"venue"
},
  "geometry": {"coordinates":[3.9599049091,50.4588470459],"type":"Point"}
}