{
  "type": "Feature",
  "properties": {
    "iso:country":"BE",
    "sg:address":"Lange Leemstraat 338",
    "sg:city":"Antwerpen",
    "sg:classifiers":[
        {
            "category":"Education",
            "subcategory":"University",
            "type":"Public Place"
        }
    ],
    "sg:phone":"+32 3 286 78 40",
    "sg:postcode":"2018",
    "sg:province":"Antwerpen",
    "sg:tags":[
        "higher"
    ],
    "wof:name":"Hoger Instituut Voor Schone Kunsten-vlaanderen Vzw",
    "wof:placetype":"venue"
},
  "geometry": {"coordinates":[4.4257941246,51.203704834],"type":"Point"}
}