{
  "type": "Feature",
  "properties": {
    "iso:country":"BE",
    "sg:address":"Rue De L'egalit\u00e9 24",
    "sg:city":"Quaregnon",
    "sg:classifiers":[
        {
            "category":"Health Services",
            "subcategory":"Doctor",
            "type":"Services"
        }
    ],
    "sg:phone":"+32 65 79 20 72",
    "sg:postcode":"7390",
    "sg:province":"Hainaut",
    "sg:tags":[
        "medicinephysicians",
        "surgeon"
    ],
    "wof:name":"Asmaoui Nazia",
    "wof:placetype":"venue"
},
  "geometry": {"coordinates":[3.863961935,50.4409637451],"type":"Point"}
}