{
  "type": "Feature",
  "properties": {
    "iso:country":"BE",
    "sg:address":"Moerbosstraat 25",
    "sg:city":"Waregem",
    "sg:orig_category":"Installatie van houten of kunststof schrijnwerk",
    "sg:phone":"+32 56 60 78 22",
    "sg:postcode":"8793",
    "sg:province":"West-Vlaanderen",
    "wof:name":"Desmet Jos\u00c9",
    "wof:placetype":"venue"
},
  "geometry": {"coordinates":[3.390953064,50.8972511292],"type":"Point"}
}