{
  "type": "Feature",
  "properties": {
    "addr:full":"Rue De Jausselette 29 Perwez Brabant Wallon 1360",
    "addr:housenumber":"29",
    "addr:postcode":"1360",
    "addr:street":"Rue De Jausselette",
    "iso:country":"BE",
    "sg:address":"Rue De Jausselette 29",
    "sg:city":"Perwez",
    "sg:orig_category":"Woningbouw",
    "sg:phone":"+32 81 65 69 06",
    "sg:postcode":"1360",
    "sg:province":"Brabant Wallon",
    "wof:name":"Toutravo",
    "wof:placetype":"venue"
},
  "geometry": {"coordinates":[4.8382101059,50.6203117371],"type":"Point"}
}