{
  "type": "Feature",
  "properties": {
    "iso:country":"BE",
    "sg:address":"Nicolaylaan 16",
    "sg:city":"Leopoldsburg",
    "sg:classifiers":[
        {
            "category":"Bars & Pubs",
            "type":"Food & Drink"
        }
    ],
    "sg:phone":"+32 11 40 15 03",
    "sg:postcode":"3970",
    "sg:province":"Limburg",
    "wof:name":"The Blues",
    "wof:placetype":"venue"
},
  "geometry": {"coordinates":[5.2586197853,51.1163291931],"type":"Point"}
}