{
  "type": "Feature",
  "properties": {
    "addr:full":"Rue Kinet 2 Bruxelles (anderlecht) Bruxelles-Capitale 1070",
    "addr:housenumber":"2",
    "addr:postcode":"1070",
    "addr:street":"Rue Kinet",
    "iso:country":"BE",
    "sg:address":"Rue Kinet 2",
    "sg:city":"Bruxelles (anderlecht)",
    "sg:classifiers":[
        {
            "category":"Bars & Pubs",
            "type":"Food & Drink"
        }
    ],
    "sg:phone":"+32 2 527 26 73",
    "sg:postcode":"1070",
    "sg:province":"Bruxelles-Capitale",
    "wof:name":"Caphorn",
    "wof:placetype":"venue"
},
  "geometry": {"coordinates":[4.3074498177,50.8376655579],"type":"Point"}
}