{
  "type": "Feature",
  "properties": {
    "iso:country":"BE",
    "sg:address":"Blasiusstraat 65",
    "sg:city":"Poperinge",
    "sg:orig_category":"Epiceries",
    "sg:phone":"+32 57 30 07 49",
    "sg:postcode":"8972",
    "sg:province":"West-Vlaanderen",
    "wof:name":"Inge Devooght",
    "wof:placetype":"venue"
},
  "geometry": {"coordinates":[2.6732769012,50.8973731995],"type":"Point"}
}