{
  "type": "Feature",
  "properties": {
    "iso:country":"BE",
    "sg:address":"Winkelsestraat 234",
    "sg:city":"Lendelede",
    "sg:classifiers":[
        {
            "category":"Wholesale",
            "subcategory":"Machinery & Supplies",
            "type":"Manufacturing & Wholesale Goods"
        }
    ],
    "sg:phone":"+32 51 31 14 47",
    "sg:postcode":"8860",
    "sg:province":"West-Vlaanderen",
    "sg:tags":[
        "refrigeration",
        "-",
        "industrial",
        "commercial",
        "equipment"
    ],
    "wof:name":"Debode M",
    "wof:placetype":"venue"
},
  "geometry": {"coordinates":[3.2017409801,50.8807601929],"type":"Point"}
}