{
  "type": "Feature",
  "properties": {
    "addr:full":"Constant Lievensstraat 33 Roeselare West-Vlaanderen 8800",
    "addr:housenumber":"33",
    "addr:postcode":"8800",
    "addr:street":"Constant Lievensstraat",
    "iso:country":"BE",
    "sg:address":"Constant Lievensstraat 33",
    "sg:city":"Roeselare",
    "sg:orig_category":"Diverse bedrijfsbeheeradviesbureaus",
    "sg:phone":"+32 51 20 65 44",
    "sg:postcode":"8800",
    "sg:province":"West-Vlaanderen",
    "wof:name":"M.declercq",
    "wof:placetype":"venue"
},
  "geometry": {"coordinates":[3.14021492,50.956363678],"type":"Point"}
}