{
  "type": "Feature",
  "properties": {
    "addr:full":"A. Demaeghtlaan 67/21 Halle Vlaams-Brabant 1500",
    "addr:housenumber":"67 / 21",
    "addr:postcode":"1500",
    "addr:street":"Demaeghtlaan",
    "iso:country":"BE",
    "sg:address":"A. Demaeghtlaan 67/21",
    "sg:city":"Halle",
    "sg:orig_category":"Dansscholen",
    "sg:phone":"+32 477 90 41 25",
    "sg:postcode":"1500",
    "sg:province":"Vlaams-Brabant",
    "wof:name":"Atelier 21bis",
    "wof:placetype":"venue"
},
  "geometry": {"coordinates":[4.2361059189,50.7391929626],"type":"Point"}
}