{
  "type": "Feature",
  "properties": {
    "addr:full":"Rue Reine Astrid 47 Saint-georges-sur-meuse Li\u00e8ge 4470",
    "addr:housenumber":"47",
    "addr:postcode":"4470",
    "addr:street":"Rue Reine Astrid",
    "iso:country":"BE",
    "sg:address":"Rue Reine Astrid 47",
    "sg:city":"Saint-georges-sur-meuse",
    "sg:classifiers":[
        {
            "category":"Shopping",
            "subcategory":"Hobbies, Toys, & Games",
            "type":"Retail Goods"
        }
    ],
    "sg:phone":"+32 4 275 14 78",
    "sg:postcode":"4470",
    "sg:province":"Li\u00e8ge",
    "sg:tags":[
        "toy",
        "-"
    ],
    "wof:name":"L'ile Des Enfants Sa",
    "wof:placetype":"venue"
},
  "geometry": {"coordinates":[5.3590202332,50.5849304199],"type":"Point"}
}