{
  "type": "Feature",
  "properties": {
    "addr:full":"Plantin En Moretuslei 45 Antwerpen Antwerpen 2610",
    "addr:housenumber":"45",
    "addr:postcode":"2610",
    "addr:street":"Plantin En Moretuslei",
    "iso:country":"BE",
    "sg:address":"Plantin En Moretuslei 45",
    "sg:city":"Antwerpen",
    "sg:orig_category":"Schoenen",
    "sg:phone":"+32 3 232 22 49",
    "sg:postcode":"2610",
    "sg:province":"Antwerpen",
    "wof:name":"Pino Farina",
    "wof:placetype":"venue"
},
  "geometry": {"coordinates":[4.4209938049,51.2106513977],"type":"Point"}
}