{
  "type": "Feature",
  "properties": {
    "addr:full":"Rue Des Tongres 15-17 Bruxelles (etterbeek) Bruxelles-Capitale 1040",
    "addr:housenumber":"15-17",
    "addr:postcode":"1040",
    "addr:street":"Rue Des Tongres",
    "iso:country":"BE",
    "sg:address":"Rue Des Tongres 15-17",
    "sg:city":"Bruxelles (etterbeek)",
    "sg:classifiers":[
        {
            "category":"Food & Beverages",
            "subcategory":"Chocolate",
            "type":"Retail Goods"
        }
    ],
    "sg:phone":"+32 2 735 36 18",
    "sg:postcode":"1040",
    "sg:province":"Bruxelles-Capitale",
    "sg:tags":[
        "confectionery",
        "-"
    ],
    "wof:name":"Neuhaus-kengani",
    "wof:placetype":"venue"
},
  "geometry": {"coordinates":[4.3996977806,50.8395347595],"type":"Point"}
}