{
  "type": "Feature",
  "properties": {
    "iso:country":"BE",
    "sg:address":"Amandinaweg 50",
    "sg:city":"Herk-de-stad",
    "sg:orig_category":"V\u00e9hicules automobiles",
    "sg:phone":"+32 13 55 15 56",
    "sg:postcode":"3540",
    "sg:province":"Limburg",
    "wof:name":"B.a.t.",
    "wof:placetype":"venue"
},
  "geometry": {"coordinates":[5.1942811012,50.9144897461],"type":"Point"}
}