{
  "type": "Feature",
  "properties": {
    "iso:country":"BE",
    "sg:address":"Hinderhausen 105",
    "sg:city":"Sankt Vith/saint-vith",
    "sg:orig_category":"M\u00e9decins and sp\u00e9cialistes",
    "sg:phone":"+32 80 22 70 69",
    "sg:postcode":"4784",
    "sg:province":"Li\u00e8ge",
    "wof:name":"K. Roll",
    "wof:placetype":"venue"
},
  "geometry": {"coordinates":[6.0675911903,50.2596511841],"type":"Point"}
}