{
  "type": "Feature",
  "properties": {
    "addr:full":"Lauwsestraat 67 Kortrijk (aalbeke) West-Vlaanderen 8511",
    "addr:housenumber":"67",
    "addr:postcode":"8511",
    "addr:street":"Lauwsestraat",
    "iso:country":"BE",
    "sg:address":"Lauwsestraat 67",
    "sg:city":"Kortrijk (aalbeke)",
    "sg:classifiers":[
        {
            "category":"Health Services",
            "subcategory":"Doctor",
            "type":"Services"
        }
    ],
    "sg:phone":"+32 56 41 86 95",
    "sg:postcode":"8511",
    "sg:province":"West-Vlaanderen",
    "sg:tags":[
        "medicinephysicians",
        "surgeon"
    ],
    "wof:name":"Fabry J",
    "wof:placetype":"venue"
},
  "geometry": {"coordinates":[3.2226920128,50.779838562],"type":"Point"}
}