{
  "type": "Feature",
  "properties": {
    "addr:full":"Bd De La Cambre 57b Bruxelles Bruxelles-Capitale 1000",
    "addr:housenumber":"57b",
    "addr:postcode":"1000",
    "addr:street":"Bd De La Cambre",
    "iso:country":"BE",
    "sg:address":"Bd De La Cambre 57b",
    "sg:city":"Bruxelles",
    "sg:orig_category":"Miscellaneous Products",
    "sg:phone":"+32 2 646 35 33",
    "sg:postcode":"1000",
    "sg:province":"Bruxelles-Capitale",
    "wof:name":"Ewa Technical & Optical Equipement",
    "wof:placetype":"venue"
},
  "geometry": {"coordinates":[4.3728380203,50.8159065247],"type":"Point"}
}