{
  "type": "Feature",
  "properties": {
    "iso:country":"BE",
    "sg:address":"Waversesteenweg 148",
    "sg:city":"Bierbeek (honsem)",
    "sg:classifiers":[
        {
            "category":"Building & Trades",
            "subcategory":"Construction",
            "type":"Services"
        }
    ],
    "sg:phone":"+32 16 73 45 31",
    "sg:postcode":"3360",
    "sg:province":"Vlaams-Brabant",
    "sg:tags":[
        "installation",
        "-",
        "central",
        "heating"
    ],
    "wof:name":"Wilma Bvba",
    "wof:placetype":"venue"
},
  "geometry": {"coordinates":[4.8027148247,50.8185043335],"type":"Point"}
}