{
  "type": "Feature",
  "properties": {
    "iso:country":"BE",
    "sg:address":"Hoogstraat 17",
    "sg:city":"Lichtervelde",
    "sg:classifiers":[
        {
            "category":"Food & Beverages",
            "subcategory":"Specialty",
            "type":"Retail Goods"
        }
    ],
    "sg:phone":"+32 51 72 51 47",
    "sg:postcode":"8810",
    "sg:province":"West-Vlaanderen",
    "sg:tags":[
        "health",
        "dietary",
        "-",
        "biological"
    ],
    "wof:name":"Cruydhuys ('t)",
    "wof:placetype":"venue"
},
  "geometry": {"coordinates":[3.1415679455,51.0278663635],"type":"Point"}
}