{
  "type": "Feature",
  "properties": {
    "addr:full":"Victoriestraat 51 Turnhout Antwerpen 2300",
    "addr:housenumber":"51",
    "addr:postcode":"2300",
    "addr:street":"Victoriestraat",
    "iso:country":"BE",
    "sg:address":"Victoriestraat 51",
    "sg:city":"Turnhout",
    "sg:classifiers":[
        {
            "category":"Shopping",
            "subcategory":"Clothing, Apparel, & Fashions",
            "type":"Retail Goods"
        }
    ],
    "sg:phone":"+32 14 65 09 27",
    "sg:postcode":"2300",
    "sg:province":"Antwerpen",
    "sg:tags":[
        "-",
        "clothing",
        "child"
    ],
    "wof:name":"Ka Dee",
    "wof:placetype":"venue"
},
  "geometry": {"coordinates":[4.9434728622,51.321056366],"type":"Point"}
}