{
  "type": "Feature",
  "properties": {
    "iso:country":"BE",
    "sg:address":"Groene Hofstraat 18",
    "sg:city":"Boom",
    "sg:classifiers":[
        {
            "category":"Restaurant",
            "type":"Food & Drink"
        }
    ],
    "sg:phone":"+32 3 888 64 71",
    "sg:postcode":"2850",
    "sg:province":"Antwerpen",
    "wof:name":"Groenhof",
    "wof:placetype":"venue"
},
  "geometry": {"coordinates":[4.3646860123,51.085357666],"type":"Point"}
}