{
  "type": "Feature",
  "properties": {
    "iso:country":"BE",
    "sg:address":"Mazenque 58",
    "sg:city":"Lessines (ollignies)",
    "sg:classifiers":[
        {
            "category":"Health Services",
            "subcategory":"Health Practitioner",
            "type":"Services"
        }
    ],
    "sg:phone":"+32 68 33 88 98",
    "sg:postcode":"7866",
    "sg:province":"Hainaut",
    "sg:tags":[
        "physiotherapist"
    ],
    "wof:name":"Vandenbosche Ir\u00e8ne",
    "wof:placetype":"venue"
},
  "geometry": {"coordinates":[3.8597989082,50.6736412048],"type":"Point"}
}