{
  "type": "Feature",
  "properties": {
    "addr:full":"Ave Charles Deliege 86-90 Binche Hainaut 7130",
    "addr:postcode":"86-90;7130",
    "addr:street":"Ave Charles Deliege;Hainaut",
    "iso:country":"BE",
    "sg:address":"Ave Charles Deliege 86-90",
    "sg:city":"Binche",
    "sg:classifiers":[
        {
            "category":"Banks & Credit Unions",
            "subcategory":"Bank",
            "type":"Services"
        }
    ],
    "sg:phone":"+32 64 33 45 11",
    "sg:postcode":"7130",
    "sg:province":"Hainaut",
    "wof:name":"Aslk-cger Bank",
    "wof:placetype":"venue"
},
  "geometry": {"coordinates":[4.1668391228,50.4138145447],"type":"Point"}
}