{
  "type": "Feature",
  "properties": {
    "iso:country":"BE",
    "sg:address":"Alice Nahonstraat 16",
    "sg:city":"Putte",
    "sg:classifiers":[
        {
            "category":"Shopping",
            "subcategory":"Clothing, Apparel, & Fashions",
            "type":"Retail Goods"
        }
    ],
    "sg:phone":"+32 15 75 37 71",
    "sg:postcode":"2580",
    "sg:province":"Antwerpen",
    "sg:tags":[
        "bathing-",
        "beachwear"
    ],
    "wof:name":"Ria Lingerie",
    "wof:placetype":"venue"
},
  "geometry": {"coordinates":[4.6293301582,51.0560188293],"type":"Point"}
}