{
  "type": "Feature",
  "properties": {
    "iso:country":"BE",
    "sg:address":"Kievitstraat 16",
    "sg:city":"Mol",
    "sg:orig_category":"Fruitteelt",
    "sg:phone":"+32 14 31 02 64",
    "sg:postcode":"2400",
    "sg:province":"Antwerpen",
    "wof:name":"Karel Vos",
    "wof:placetype":"venue"
},
  "geometry": {"coordinates":[5.0592298508,51.1939506531],"type":"Point"}
}