{
  "type": "Feature",
  "properties": {
    "iso:country":"BE",
    "sg:address":"Nieuwpoortsesteenweg 184a",
    "sg:city":"Oostende",
    "sg:classifiers":[
        {
            "category":"Bakery",
            "type":"Food & Drink"
        }
    ],
    "sg:phone":"+32 59 50 82 05",
    "sg:postcode":"8400",
    "sg:province":"West-Vlaanderen",
    "sg:tags":[
        "confectioner",
        "baker"
    ],
    "wof:name":"Ovenkoekje ('t)",
    "wof:placetype":"venue"
},
  "geometry": {"coordinates":[2.9013779163,51.2210006714],"type":"Point"}
}