{
  "type": "Feature",
  "properties": {
    "iso:country":"BE",
    "sg:address":"Rue Longue 41 Box 10",
    "sg:city":"Braine L'alleud (braine-l'alleud)",
    "sg:classifiers":[
        {
            "category":"Professional",
            "subcategory":"Management & Consulting",
            "type":"Services"
        }
    ],
    "sg:phone":"+32 2 387 32 34",
    "sg:postcode":"1420",
    "sg:province":"Brabant Wallon",
    "sg:tags":[
        "-",
        "processing",
        "data",
        "consultant"
    ],
    "wof:name":"Karim El Founas",
    "wof:placetype":"venue"
},
  "geometry": {"coordinates":[-0.6410030127,47.4463195801],"type":"Point"}
}