{
  "type": "Feature",
  "properties": {
    "addr:full":"Stasegemdorp 60 Harelbeke West-Vlaanderen 8530",
    "addr:housenumber":"60",
    "addr:postcode":"8530",
    "addr:street":"Stasegemdorp",
    "iso:country":"BE",
    "sg:address":"Stasegemdorp 60",
    "sg:city":"Harelbeke",
    "sg:orig_category":"Installation \u00e9lectrique r\u00e9sidentielle",
    "sg:phone":"+32 56 25 67 10",
    "sg:postcode":"8530",
    "sg:province":"West-Vlaanderen",
    "wof:name":"Danny Callens",
    "wof:placetype":"venue"
},
  "geometry": {"coordinates":[3.3102478981,50.8311462402],"type":"Point"}
}