{
  "type": "Feature",
  "properties": {
    "iso:country":"BE",
    "sg:address":"Rue Emile Tumelaire 99",
    "sg:city":"Charleroi",
    "sg:classifiers":[
        {
            "category":"Real Estate",
            "subcategory":"Real Estate Services",
            "type":"Services"
        }
    ],
    "sg:phone":"+32 71 30 68 48",
    "sg:postcode":"6000",
    "sg:province":"Hainaut",
    "wof:name":"Dobbels B",
    "wof:placetype":"venue"
},
  "geometry": {"coordinates":[4.4521098137,50.4090805054],"type":"Point"}
}