{
  "type": "Feature",
  "properties": {
    "iso:country":"BE",
    "sg:address":"Val Du Fierain 1",
    "sg:city":"Pepinster",
    "sg:orig_category":"Woningbouw",
    "sg:phone":"+32 87 46 90 16",
    "sg:postcode":"4860",
    "sg:province":"Li\u00e8ge",
    "wof:name":"Georges Pagnoulle",
    "wof:placetype":"venue"
},
  "geometry": {"coordinates":[5.813475132,50.5866584778],"type":"Point"}
}