{
  "type": "Feature",
  "properties": {
    "iso:country":"BE",
    "sg:address":"Verwelkomingsstraat 15",
    "sg:city":"Anderlecht",
    "sg:orig_category":"Huishoudapparaten, televisies and radio's",
    "sg:phone":"+32 70 22 21 44",
    "sg:postcode":"1070",
    "sg:province":"Bruxelles-Capitale",
    "wof:name":"Bsh Service - Balay",
    "wof:placetype":"venue"
},
  "geometry": {"coordinates":[4.3057599068,50.8140487671],"type":"Point"}
}