{
  "type": "Feature",
  "properties": {
    "iso:country":"BE",
    "sg:address":"Kerkhofdries 7",
    "sg:city":"Sint-amands",
    "sg:classifiers":[
        {
            "category":"Shopping",
            "subcategory":"Bicycles & Sporting Goods",
            "type":"Retail Goods"
        }
    ],
    "sg:phone":"+32 52 33 23 79",
    "sg:postcode":"2890",
    "sg:province":"Antwerpen",
    "sg:tags":[
        "-"
    ],
    "wof:name":"Van Achter C",
    "wof:placetype":"venue"
},
  "geometry": {"coordinates":[4.205575943,51.0557899475],"type":"Point"}
}