{
  "type": "Feature",
  "properties": {
    "iso:country":"BE",
    "sg:address":"Avenue De L'abbaye 16a",
    "sg:city":"Anthisnes",
    "sg:classifiers":[
        {
            "category":"Health Services",
            "subcategory":"Doctor",
            "type":"Services"
        }
    ],
    "sg:phone":"+32 4 383 65 65",
    "sg:postcode":"4160",
    "sg:province":"Li\u00e8ge",
    "sg:tags":[
        "medicinephysicians",
        "surgeon"
    ],
    "wof:name":"Dellicour Jean-paul",
    "wof:placetype":"venue"
},
  "geometry": {"coordinates":[5.522356987,50.4792785645],"type":"Point"}
}