{
  "type": "Feature",
  "properties": {
    "addr:full":"Avenue J. Van Gijsel 9 Wemmel Vlaams-Brabant 1780",
    "addr:housenumber":"9",
    "addr:postcode":"1780",
    "addr:street":"Avenue J. Van Gijsel;Vlaams-Brabant",
    "iso:country":"BE",
    "sg:address":"Avenue J. Van Gijsel 9",
    "sg:city":"Wemmel",
    "sg:classifiers":[
        {
            "category":"Professional",
            "type":"Services"
        }
    ],
    "sg:phone":"+32 2 269 19 19",
    "sg:postcode":"1780",
    "sg:province":"Vlaams-Brabant",
    "sg:tags":[
        "entertainer"
    ],
    "wof:name":"Lize Marke",
    "wof:placetype":"venue"
},
  "geometry": {"coordinates":[4.3355379105,50.9215507507],"type":"Point"}
}