{
  "type": "Feature",
  "properties": {
    "addr:full":"Westkade 18 Zelzate Oost-Vlaanderen 9060",
    "addr:housenumber":"18",
    "addr:postcode":"9060",
    "addr:street":"Westkade",
    "iso:country":"BE",
    "sg:address":"Westkade 18",
    "sg:city":"Zelzate",
    "sg:orig_category":"Advocaten and juridische adviseurs",
    "sg:phone":"+32 9 345 60 27",
    "sg:postcode":"9060",
    "sg:province":"Oost-Vlaanderen",
    "wof:name":"Arsene Ryckaert",
    "wof:placetype":"venue"
},
  "geometry": {"coordinates":[3.8086190224,51.1993484497],"type":"Point"}
}