{
  "type": "Feature",
  "properties": {
    "iso:country":"BE",
    "sg:address":"Rue Des Aunes 27",
    "sg:city":"Eghez\u00e9e (upigny)",
    "sg:classifiers":[
        {
            "category":"Home & Garden",
            "subcategory":"Home Furnishings",
            "type":"Retail Goods"
        }
    ],
    "sg:phone":"+32 81 51 32 47",
    "sg:postcode":"5310",
    "sg:province":"Namur",
    "sg:tags":[
        "interior",
        "decoration"
    ],
    "wof:name":"Pinchart A",
    "wof:placetype":"venue"
},
  "geometry": {"coordinates":[4.8627181053,50.5784187317],"type":"Point"}
}