{
  "type": "Feature",
  "properties": {
    "iso:country":"BE",
    "sg:address":"Victor Rousseaulaan 149b8",
    "sg:city":"Forest",
    "sg:orig_category":"Elektrische installaties voor woningen Industri\u00eble elektrische installaties",
    "sg:phone":"+32 2 343 69 56",
    "sg:postcode":"1190",
    "sg:province":"Bruxelles-Capitale",
    "wof:name":"M. Desmet",
    "wof:placetype":"venue"
},
  "geometry": {"coordinates":[4.3265461922,50.8106269836],"type":"Point"}
}