{
  "type": "Feature",
  "properties": {
    "addr:full":"Reningsestraat 14 Ieper (boezinge) West-Vlaanderen 8904",
    "addr:housenumber":"14",
    "addr:postcode":"8904",
    "addr:street":"Reningsestraat",
    "iso:country":"BE",
    "sg:address":"Reningsestraat 14",
    "sg:city":"Ieper (boezinge)",
    "sg:classifiers":[
        {
            "category":"Farming",
            "subcategory":"Farm & Veterinary Services",
            "type":"Manufacturing & Wholesale Goods"
        }
    ],
    "sg:phone":"+32 57 42 35 18",
    "sg:postcode":"8904",
    "sg:province":"West-Vlaanderen",
    "sg:tags":[
        "agricultural",
        "contractor"
    ],
    "wof:name":"Landuyt D",
    "wof:placetype":"venue"
},
  "geometry": {"coordinates":[2.8272969723,50.9056167603],"type":"Point"}
}