{
  "type": "Feature",
  "properties": {
    "iso:country":"BE",
    "sg:address":"Benedictijnenstraat 41",
    "sg:city":"Brugge (assebroek)",
    "sg:classifiers":[
        {
            "category":"Manufacturing",
            "subcategory":"Textiles",
            "type":"Manufacturing & Wholesale Goods"
        }
    ],
    "sg:phone":"+32 50 37 33 29",
    "sg:postcode":"8310",
    "sg:province":"West-Vlaanderen",
    "sg:tags":[
        "retail",
        "-"
    ],
    "wof:name":"Caritex Bvba",
    "wof:placetype":"venue"
},
  "geometry": {"coordinates":[3.2383270264,51.1852226257],"type":"Point"}
}