{
  "type": "Feature",
  "properties": {
    "iso:country":"BE",
    "sg:address":"Avenue Du Centre 11",
    "sg:city":"Dison (andrimont)",
    "sg:classifiers":[
        {
            "category":"Health Services",
            "subcategory":"Health Practitioner",
            "type":"Services"
        }
    ],
    "sg:phone":"+32 87 31 53 95",
    "sg:postcode":"4821",
    "sg:province":"Li\u00e8ge",
    "sg:tags":[
        "physiotherapist"
    ],
    "wof:name":"Nizet Philippe",
    "wof:placetype":"venue"
},
  "geometry": {"coordinates":[5.8709340096,50.6054191589],"type":"Point"}
}