{
  "type": "Feature",
  "properties": {
    "iso:country":"BE",
    "sg:address":"Zuidstraat 76b6",
    "sg:city":"Roeselare",
    "sg:orig_category":"Verplichte sociale verzekeringen",
    "sg:phone":"+32 51 20 77 27",
    "sg:postcode":"8800",
    "sg:province":"West-Vlaanderen",
    "wof:name":"Mutualiteit N.m.v.",
    "wof:placetype":"venue"
},
  "geometry": {"coordinates":[3.1246399879,50.9412918091],"type":"Point"}
}