{
  "type": "Feature",
  "properties": {
    "addr:full":"Chauss\u00e9e De Charleroi 82 Jemeppe-sur-sambre Namur 5190",
    "addr:housenumber":"82",
    "addr:postcode":"5190",
    "addr:street":"Chausse\u0301E De Charleroi",
    "iso:country":"BE",
    "sg:address":"Chauss\u00e9e De Charleroi 82",
    "sg:city":"Jemeppe-sur-sambre",
    "sg:classifiers":[
        {
            "category":"Autos & Motor Vehicles",
            "subcategory":"Auto Supplies",
            "type":"Retail Goods"
        }
    ],
    "sg:phone":"+32 71 78 66 90",
    "sg:postcode":"5190",
    "sg:province":"Namur",
    "sg:tags":[
        "access",
        "automobile",
        "part",
        "-"
    ],
    "wof:name":"C P F E Sa",
    "wof:placetype":"venue"
},
  "geometry": {"coordinates":[4.6566591263,50.4597587585],"type":"Point"}
}