{
  "type": "Feature",
  "properties": {
    "iso:country":"BE",
    "sg:address":"Rue De Bruxelles 55",
    "sg:city":"Awans",
    "sg:orig_category":"Ice-cream parlours",
    "sg:phone":"+32 4 263 57 21",
    "sg:postcode":"4340",
    "sg:province":"Li\u00e8ge",
    "wof:name":"Glacier Louis & Fils",
    "wof:placetype":"venue"
},
  "geometry": {"coordinates":[5.4749479294,50.6784858704],"type":"Point"}
}