{
  "type": "Feature",
  "properties": {
    "addr:full":"Lombardstraat 22ba Brussel/bruxelles Bruxelles-Capitale 1000",
    "addr:housenumber":"22ba",
    "addr:postcode":"1000",
    "addr:street":"Lombardstraat;/",
    "iso:country":"BE",
    "sg:address":"Lombardstraat 22ba",
    "sg:city":"Brussel/bruxelles",
    "sg:orig_category":"Kapsalons",
    "sg:phone":"+32 2 512 61 54",
    "sg:postcode":"1000",
    "sg:province":"Bruxelles-Capitale",
    "wof:name":"Coiffure Josy",
    "wof:placetype":"venue"
},
  "geometry": {"coordinates":[4.3503751755,50.8458976746],"type":"Point"}
}