{
  "type": "Feature",
  "properties": {
    "iso:country":"BE",
    "sg:address":"Renning 9",
    "sg:city":"Waarschoot",
    "sg:classifiers":[
        {
            "category":"Retail",
            "subcategory":"Animal Services",
            "type":"Services"
        }
    ],
    "sg:phone":"+32 9 378 07 84",
    "sg:postcode":"9950",
    "sg:province":"Oost-Vlaanderen",
    "sg:tags":[
        "training",
        "dog"
    ],
    "wof:name":"Hondencenter Steady",
    "wof:placetype":"venue"
},
  "geometry": {"coordinates":[3.6042089462,51.1422843933],"type":"Point"}
}