{
  "type": "Feature",
  "properties": {
    "addr:full":"Rue Abb\u00c9 Cuylits 30 Anderlecht Bruxelles-Capitale 1070",
    "addr:housenumber":"30",
    "addr:postcode":"1070",
    "addr:street":"Rue Abbe\u0301 Cuylits",
    "iso:country":"BE",
    "sg:address":"Rue Abb\u00c9 Cuylits 30",
    "sg:city":"Anderlecht",
    "sg:orig_category":"Enseignement maternel and primaire",
    "sg:phone":"+32 2 522 17 94",
    "sg:postcode":"1070",
    "sg:province":"Bruxelles-Capitale",
    "wof:name":"Ecole Fondamentale Libre",
    "wof:placetype":"venue"
},
  "geometry": {"coordinates":[4.3343582153,50.8446426392],"type":"Point"}
}