{
  "type": "Feature",
  "properties": {
    "addr:full":"Kaststraat 62 Tongeren Limburg 3700",
    "addr:housenumber":"62",
    "addr:postcode":"3700",
    "addr:street":"Kaststraat",
    "iso:country":"BE",
    "sg:address":"Kaststraat 62",
    "sg:city":"Tongeren",
    "sg:orig_category":"Installation de menuiserie en bois and plastique",
    "sg:phone":"+32 12 39 19 29",
    "sg:postcode":"3700",
    "sg:province":"Limburg",
    "wof:name":"Jean Weerelds",
    "wof:placetype":"venue"
},
  "geometry": {"coordinates":[5.5213317871,50.7624702454],"type":"Point"}
}