{
  "type": "Feature",
  "properties": {
    "iso:country":"BE",
    "sg:address":"Waregemseweg 31",
    "sg:city":"Wortegem-petegem",
    "sg:classifiers":[
        {
            "category":"Personal",
            "subcategory":"Beauty Salon",
            "type":"Services"
        }
    ],
    "sg:phone":"+32 56 68 92 91",
    "sg:postcode":"9790",
    "sg:province":"Oost-Vlaanderen",
    "sg:tags":[
        "de",
        "coiffure"
    ],
    "wof:name":"Dirk Moerman",
    "wof:placetype":"venue"
},
  "geometry": {"coordinates":[3.5043389797,50.8546676636],"type":"Point"}
}