{
  "type": "Feature",
  "properties": {
    "addr:full":"Koning Leopoldlaan 22 De Pinte Oost-Vlaanderen 9840",
    "addr:housenumber":"22",
    "addr:postcode":"9840",
    "addr:street":"Koning Leopoldlaan",
    "iso:country":"BE",
    "sg:address":"Koning Leopoldlaan 22",
    "sg:city":"De Pinte",
    "sg:orig_category":"Animations diverses",
    "sg:phone":"+32 9 282 68 86",
    "sg:postcode":"9840",
    "sg:province":"Oost-Vlaanderen",
    "wof:name":"Muzircus",
    "wof:placetype":"venue"
},
  "geometry": {"coordinates":[3.6516270638,50.9948539734],"type":"Point"}
}