{
  "type": "Feature",
  "properties": {
    "addr:full":"Groeneweg 100 Zulte (olsene) Oost-Vlaanderen 9870",
    "addr:housenumber":"100",
    "addr:postcode":"9870",
    "addr:street":"Groeneweg",
    "iso:country":"BE",
    "sg:address":"Groeneweg 100",
    "sg:city":"Zulte (olsene)",
    "sg:classifiers":[
        {
            "category":"Wholesale",
            "subcategory":"Wine & Distilled Alcoholic Beverages",
            "type":"Manufacturing & Wholesale Goods"
        }
    ],
    "sg:phone":"+32 9 388 75 11",
    "sg:postcode":"9870",
    "sg:province":"Oost-Vlaanderen",
    "sg:tags":[
        "whol",
        "-",
        "spirit",
        "mfg"
    ],
    "wof:name":"Lassuyt",
    "wof:placetype":"venue"
},
  "geometry": {"coordinates":[3.4705469608,50.9334602356],"type":"Point"}
}