{
  "type": "Feature",
  "properties": {
    "addr:full":"Bremheidelaan 8 Turnhout Antwerpen 2300",
    "addr:housenumber":"8",
    "addr:postcode":"2300",
    "addr:street":"Bremheidelaan",
    "iso:country":"BE",
    "sg:address":"Bremheidelaan 8",
    "sg:city":"Turnhout",
    "sg:classifiers":[
        {
            "category":"Professional",
            "subcategory":"Engineering",
            "type":"Services"
        }
    ],
    "sg:phone":"+32 14 42 44 01",
    "sg:postcode":"2300",
    "sg:province":"Antwerpen",
    "sg:tags":[
        "electric",
        "-",
        "component",
        "machine",
        "mechanical",
        "electronic"
    ],
    "wof:name":"Smans Nv",
    "wof:placetype":"venue"
},
  "geometry": {"coordinates":[4.919511795,51.2921180725],"type":"Point"}
}