{
  "type": "Feature",
  "properties": {
    "addr:full":"Brusselsesteenweg 68 Halle Vlaams-Brabant 1500",
    "addr:housenumber":"68",
    "addr:postcode":"1500",
    "addr:street":"Brusselsesteenweg",
    "iso:country":"BE",
    "sg:address":"Brusselsesteenweg 68",
    "sg:city":"Halle",
    "sg:classifiers":[
        {
            "category":"Professional",
            "subcategory":"Art Services",
            "type":"Services"
        }
    ],
    "sg:phone":"+32 2 356 84 69",
    "sg:postcode":"1500",
    "sg:province":"Vlaams-Brabant",
    "sg:tags":[
        "designer",
        "display"
    ],
    "wof:name":"Bombeke H",
    "wof:placetype":"venue"
},
  "geometry": {"coordinates":[4.2384500504,50.7390556335],"type":"Point"}
}