{
  "type": "Feature",
  "properties": {
    "addr:full":"Rijselstraat 165 Menen West-Vlaanderen 8930",
    "addr:housenumber":"165",
    "addr:postcode":"8930",
    "addr:street":"Rijselstraat",
    "iso:country":"BE",
    "sg:address":"Rijselstraat 165",
    "sg:city":"Menen",
    "sg:orig_category":"Epiceries",
    "sg:phone":"+32 56 51 17 87",
    "sg:postcode":"8930",
    "sg:province":"West-Vlaanderen",
    "wof:name":"Huis Bonte",
    "wof:placetype":"venue"
},
  "geometry": {"coordinates":[3.1260108948,50.7893943787],"type":"Point"}
}