{
  "type": "Feature",
  "properties": {
    "iso:country":"BE",
    "sg:address":"Lintsesteenweg 107",
    "sg:city":"Duffel",
    "sg:classifiers":[
        {
            "category":"Professional",
            "subcategory":"Computer Services",
            "type":"Services"
        }
    ],
    "sg:phone":"+32 15 31 35 95",
    "sg:postcode":"2570",
    "sg:province":"Antwerpen",
    "sg:tags":[
        "repair",
        "processing",
        "-",
        "maintenance",
        "data"
    ],
    "wof:name":"Van Santfoort Vof",
    "wof:placetype":"venue"
},
  "geometry": {"coordinates":[4.5036010742,51.101764679],"type":"Point"}
}