{
  "type": "Feature",
  "properties": {
    "addr:full":"Rue G\u00c9n\u00c9ral Leman 78 Ans Li\u00e8ge 4430",
    "addr:housenumber":"78",
    "addr:postcode":"4430",
    "addr:street":"Rue Ge\u0301Ne\u0301Ral Leman",
    "iso:country":"BE",
    "sg:address":"Rue G\u00c9n\u00c9ral Leman 78",
    "sg:city":"Ans",
    "sg:orig_category":"Woningbouw",
    "sg:phone":"+32 4 239 08 09",
    "sg:postcode":"4430",
    "sg:province":"Li\u00e8ge",
    "wof:name":"Herion P. & Associ\u00c9s",
    "wof:placetype":"venue"
},
  "geometry": {"coordinates":[5.5162701607,50.6642189026],"type":"Point"}
}