{
  "type": "Feature",
  "properties": {
    "addr:full":"Keizer Leopoldstraat 3 Gent Oost-Vlaanderen 9000",
    "addr:housenumber":"3",
    "addr:postcode":"9000",
    "addr:street":"Keizer Leopoldstraat;Oost-Vlaanderen",
    "iso:country":"BE",
    "sg:address":"Keizer Leopoldstraat 3",
    "sg:city":"Gent",
    "sg:classifiers":[
        {
            "category":"Shopping",
            "subcategory":"Music",
            "type":"Retail Goods"
        }
    ],
    "sg:phone":"+32 9 223 67 37",
    "sg:postcode":"9000",
    "sg:province":"Oost-Vlaanderen",
    "sg:tags":[
        "-",
        "cd's",
        "recorded",
        "cassette"
    ],
    "wof:name":"Strictly Dance",
    "wof:placetype":"venue"
},
  "geometry": {"coordinates":[3.7340219021,51.0572280884],"type":"Point"}
}