{
  "type": "Feature",
  "properties": {
    "iso:country":"BE",
    "sg:address":"Fabriekstraat 15",
    "sg:city":"Sint-truiden",
    "sg:classifiers":[
        {
            "category":"Home & Garden",
            "subcategory":"Building Materials",
            "type":"Retail Goods"
        }
    ],
    "sg:phone":"+32 3 667 31 39",
    "sg:postcode":"3800",
    "sg:province":"Limburg",
    "sg:tags":[
        "-",
        "fireplace",
        "open",
        "ornamental"
    ],
    "wof:name":"V.f.m.",
    "wof:placetype":"venue"
},
  "geometry": {"coordinates":[5.1722278595,50.8165817261],"type":"Point"}
}