{
  "type": "Feature",
  "properties": {
    "iso:country":"BE",
    "sg:address":"Oude Weyerstraat 29",
    "sg:city":"Peer",
    "sg:orig_category":"Rundveehouders",
    "sg:phone":"+32 11 63 34 53",
    "sg:postcode":"3990",
    "sg:province":"Limburg",
    "wof:name":"Schalley Pieter & Leo",
    "wof:placetype":"venue"
},
  "geometry": {"coordinates":[5.4921498299,51.1653213501],"type":"Point"}
}