{
  "type": "Feature",
  "properties": {
    "addr:full":"Burgemeester Lionel Pussemierstraat 84 Eeklo Oost-Vlaanderen 9900",
    "addr:housenumber":"84",
    "addr:postcode":"9900",
    "addr:street":"Burgemeester Lionel Pussemierstraat",
    "iso:country":"BE",
    "sg:address":"Burgemeester Lionel Pussemierstraat 84",
    "sg:city":"Eeklo",
    "sg:classifiers":[
        {
            "category":"Personal",
            "subcategory":"Beauty Salon",
            "type":"Services"
        }
    ],
    "sg:phone":"+32 9 377 61 64",
    "sg:postcode":"9900",
    "sg:province":"Oost-Vlaanderen",
    "sg:tags":[
        "lady",
        "-",
        "hairdressing"
    ],
    "wof:name":"Coiffure Veronique",
    "wof:placetype":"venue"
},
  "geometry": {"coordinates":[3.5763831139,51.1864547729],"type":"Point"}
}