{
  "type": "Feature",
  "properties": {
    "iso:country":"BE",
    "sg:address":"Naamsevest 62",
    "sg:city":"Sint-truiden",
    "sg:orig_category":"V\u00eatements pour b\u00e9b\u00e9s and enfants. Articles pour b\u00e9b\u00e9s",
    "sg:phone":"+32 11 68 57 31",
    "sg:postcode":"3800",
    "sg:province":"Limburg",
    "wof:name":"Gamino",
    "wof:placetype":"venue"
},
  "geometry": {"coordinates":[5.1857590675,50.8124771118],"type":"Point"}
}