{
  "type": "Feature",
  "properties": {
    "addr:full":"Rue De Bruxelles 6 Esneux Li\u00e8ge 4130",
    "addr:housenumber":"6",
    "addr:postcode":"4130",
    "addr:street":"Rue De Bruxelles",
    "iso:country":"BE",
    "sg:address":"Rue De Bruxelles 6",
    "sg:city":"Esneux",
    "sg:classifiers":[
        {
            "category":"Insurance",
            "subcategory":"Insurance Agent",
            "type":"Services"
        }
    ],
    "sg:phone":"+32 4 380 14 67",
    "sg:postcode":"4130",
    "sg:province":"Li\u00e8ge",
    "sg:tags":[
        "verzekeringsmakelaars",
        "expert"
    ],
    "wof:name":"Brennenraedts J.",
    "wof:placetype":"venue"
},
  "geometry": {"coordinates":[5.5667910576,50.5316619873],"type":"Point"}
}