{
  "type": "Feature",
  "properties": {
    "addr:full":"Rue Henri Bl\u00c8s 118 Namur Namur 5000",
    "addr:housenumber":"118",
    "addr:postcode":"5000",
    "addr:street":"Rue Henri Ble\u0300S",
    "iso:country":"BE",
    "sg:address":"Rue Henri Bl\u00c8s 118",
    "sg:city":"Namur",
    "sg:orig_category":"M\u00e9decins and sp\u00e9cialistes",
    "sg:phone":"+32 81 73 63 65",
    "sg:postcode":"5000",
    "sg:province":"Namur",
    "wof:name":"Guy Manil",
    "wof:placetype":"venue"
},
  "geometry": {"coordinates":[4.8422999382,50.4653358459],"type":"Point"}
}