{
  "type": "Feature",
  "properties": {
    "addr:full":"Kattestraat 22 Riemst (millen) Limburg 3770",
    "addr:housenumber":"22",
    "addr:postcode":"3770",
    "addr:street":"Kattestraat",
    "iso:country":"BE",
    "sg:address":"Kattestraat 22",
    "sg:city":"Riemst (millen)",
    "sg:classifiers":[
        {
            "category":"Bars & Pubs",
            "type":"Food & Drink"
        }
    ],
    "sg:phone":"+32 12 45 86 42",
    "sg:postcode":"3770",
    "sg:province":"Limburg",
    "wof:name":"Millen Waterburcht",
    "wof:placetype":"venue"
},
  "geometry": {"coordinates":[5.5579371452,50.7862854004],"type":"Point"}
}