{
  "type": "Feature",
  "properties": {
    "addr:full":"Boterstraat 5 Aalst Oost-Vlaanderen 9300",
    "addr:housenumber":"5",
    "addr:postcode":"9300",
    "addr:street":"Boterstraat",
    "iso:country":"BE",
    "sg:address":"Boterstraat 5",
    "sg:city":"Aalst",
    "sg:classifiers":[
        {
            "category":"Cafe",
            "type":"Food & Drink"
        }
    ],
    "sg:phone":"+32 53 21 24 33",
    "sg:postcode":"9300",
    "sg:province":"Oost-Vlaanderen",
    "sg:tags":[
        "caf\u00e9s"
    ],
    "wof:name":"Guy De Bundel",
    "wof:placetype":"venue"
},
  "geometry": {"coordinates":[4.0362329483,50.9368934631],"type":"Point"}
}