{
  "type": "Feature",
  "properties": {
    "iso:country":"BE",
    "sg:address":"Ophovenstraat 1b4",
    "sg:city":"Maaseik",
    "sg:orig_category":"Installation de menuiserie en bois and plastique",
    "sg:phone":"+32 89 86 78 63",
    "sg:postcode":"3680",
    "sg:province":"Limburg",
    "wof:name":"Mathieu Meuwis",
    "wof:placetype":"venue"
},
  "geometry": {"coordinates":[5.791285038,51.0954208374],"type":"Point"}
}