{
  "type": "Feature",
  "properties": {
    "addr:full":"Bloemenlaan 71 Maasmechelen Limburg 3630",
    "addr:housenumber":"71",
    "addr:postcode":"3630",
    "addr:street":"Bloemenlaan",
    "iso:country":"BE",
    "sg:address":"Bloemenlaan 71",
    "sg:city":"Maasmechelen",
    "sg:orig_category":"Enseignement maternel and primaire",
    "sg:phone":"+32 89 76 03 10",
    "sg:postcode":"3630",
    "sg:province":"Limburg",
    "wof:name":"Vrije Basisschool",
    "wof:placetype":"venue"
},
  "geometry": {"coordinates":[5.7006950378,50.9813652039],"type":"Point"}
}