{
  "type": "Feature",
  "properties": {
    "addr:full":"Rue Saint-gustave 21 Charleroi Hainaut 6030",
    "addr:housenumber":"21",
    "addr:postcode":"6030",
    "addr:street":"Rue Saint-Gustave;Hainaut",
    "iso:country":"BE",
    "sg:address":"Rue Saint-gustave 21",
    "sg:city":"Charleroi",
    "sg:classifiers":[
        {
            "category":"Government",
            "subcategory":"Police Station",
            "type":"Public Place"
        }
    ],
    "sg:phone":"+32 71 86 17 39",
    "sg:postcode":"6030",
    "sg:province":"Hainaut",
    "sg:tags":[
        "gendarmerie"
    ],
    "wof:name":"Police F\u00c9d\u00c9rale/federale Politie",
    "wof:placetype":"venue"
},
  "geometry": {"coordinates":[4.4139690399,50.4255981445],"type":"Point"}
}