{
  "type": "Feature",
  "properties": {
    "iso:country":"BE",
    "sg:address":"Nieuwbeekstraat 35",
    "sg:city":"Aalst",
    "sg:orig_category":"Organisations politiques",
    "sg:phone":"+32 53 21 13 27",
    "sg:postcode":"9300",
    "sg:province":"Oost-Vlaanderen",
    "wof:name":"Kommunistische Partij",
    "wof:placetype":"venue"
},
  "geometry": {"coordinates":[4.0298099518,50.936290741],"type":"Point"}
}