{
  "type": "Feature",
  "properties": {
    "addr:full":"Sint-katelijnevest 16-24 Antwerpen Antwerpen 2000",
    "addr:postcode":"16-24;2000",
    "addr:street":"Sint-Katelijnevest",
    "iso:country":"BE",
    "sg:address":"Sint-katelijnevest 16-24",
    "sg:city":"Antwerpen",
    "sg:classifiers":[
        {
            "category":"Professional",
            "subcategory":"Computer Services",
            "type":"Services"
        }
    ],
    "sg:phone":"+32 3 232 02 89",
    "sg:postcode":"2000",
    "sg:province":"Antwerpen",
    "sg:tags":[
        "-",
        "processing",
        "data",
        "printer"
    ],
    "wof:name":"Dahlgren-heirbaut",
    "wof:placetype":"venue"
},
  "geometry": {"coordinates":[4.4050388336,51.2206802368],"type":"Point"}
}