{
  "type": "Feature",
  "properties": {
    "iso:country":"BE",
    "sg:address":"Vremdesesteenweg 174",
    "sg:city":"Boechout",
    "sg:orig_category":"Rundveehouders",
    "sg:phone":"+32 3 455 99 84",
    "sg:postcode":"2530",
    "sg:province":"Antwerpen",
    "wof:name":"Fran\u00c7ois Maes",
    "wof:placetype":"venue"
},
  "geometry": {"coordinates":[4.5072622299,51.167755127],"type":"Point"}
}