{
  "type": "Feature",
  "properties": {
    "iso:country":"BE",
    "sg:address":"Kanegemdorp 6",
    "sg:city":"Tielt",
    "sg:orig_category":"Journaux",
    "sg:phone":"+32 51 68 84 09",
    "sg:postcode":"8700",
    "sg:province":"West-Vlaanderen",
    "wof:name":"Yvonne De Waelsche",
    "wof:placetype":"venue"
},
  "geometry": {"coordinates":[3.4022080898,51.0134391785],"type":"Point"}
}