{
  "type": "Feature",
  "properties": {
    "iso:country":"BE",
    "sg:address":"Dorpsstraat 90ba",
    "sg:city":"Oudenburg",
    "sg:orig_category":"Elektrische installaties voor woningen",
    "sg:phone":"+32 59 26 62 60",
    "sg:postcode":"8460",
    "sg:province":"West-Vlaanderen",
    "wof:name":"Eric Casneuf",
    "wof:placetype":"venue"
},
  "geometry": {"coordinates":[3.0023450851,51.1840553284],"type":"Point"}
}