{
  "type": "Feature",
  "properties": {
    "addr:full":"Noorderlaan 83 Antwerpen Antwerpen 2030",
    "addr:housenumber":"83",
    "addr:postcode":"2030",
    "addr:street":"Noorderlaan",
    "iso:country":"BE",
    "sg:address":"Noorderlaan 83",
    "sg:city":"Antwerpen",
    "sg:orig_category":"IJzerwaren, bouw- and verfmaterialen Onderdelen and accessoires voertuigen Gh",
    "sg:phone":"+32 3 545 90 80",
    "sg:postcode":"2030",
    "sg:province":"Antwerpen",
    "wof:name":"Fabory Center Antwerpen",
    "wof:placetype":"venue"
},
  "geometry": {"coordinates":[4.4198851585,51.2554740906],"type":"Point"}
}