{
  "type": "Feature",
  "properties": {
    "addr:full":"Groendreef 109-110 Gent Oost-Vlaanderen 9000",
    "addr:housenumber":"109-110",
    "addr:postcode":"9000",
    "addr:street":"Groendreef;Oost-Vlaanderen",
    "iso:country":"BE",
    "sg:address":"Groendreef 109-110",
    "sg:city":"Gent",
    "sg:classifiers":[
        {
            "category":"Real Estate",
            "subcategory":"Architect",
            "type":"Services"
        }
    ],
    "sg:phone":"+32 9 330 69 10",
    "sg:postcode":"9000",
    "sg:province":"Oost-Vlaanderen",
    "wof:name":"Van Overbeke K",
    "wof:placetype":"venue"
},
  "geometry": {"coordinates":[3.7010400295,51.0637664795],"type":"Point"}
}