{
  "type": "Feature",
  "properties": {
    "addr:full":"Stenestraat 63 Buggenhout Oost-Vlaanderen 9255",
    "addr:housenumber":"63",
    "addr:postcode":"9255",
    "addr:street":"Stenestraat",
    "iso:country":"BE",
    "sg:address":"Stenestraat 63",
    "sg:city":"Buggenhout",
    "sg:classifiers":[
        {
            "category":"Building & Trades",
            "subcategory":"Landscaping Services",
            "type":"Services"
        }
    ],
    "sg:phone":"+32 52 35 41 69",
    "sg:postcode":"9255",
    "sg:province":"Oost-Vlaanderen",
    "sg:tags":[
        "gardening",
        "garden",
        "maintenance"
    ],
    "wof:name":"Goossens",
    "wof:placetype":"venue"
},
  "geometry": {"coordinates":[4.1849331856,50.9966239929],"type":"Point"}
}