{
  "type": "Feature",
  "properties": {
    "addr:full":"Rue De Neufvilles 70 Soignies Hainaut 7060",
    "addr:housenumber":"70",
    "addr:postcode":"7060",
    "addr:street":"Rue De Neufvilles",
    "iso:country":"BE",
    "sg:address":"Rue De Neufvilles 70",
    "sg:city":"Soignies",
    "sg:classifiers":[
        {
            "category":"Health Services",
            "subcategory":"Health Practitioner",
            "type":"Services"
        }
    ],
    "sg:phone":"+32 67 33 26 74",
    "sg:postcode":"7060",
    "sg:province":"Hainaut",
    "sg:tags":[
        "physiotherapist"
    ],
    "wof:name":"Guerin Beatrice",
    "wof:placetype":"venue"
},
  "geometry": {"coordinates":[4.0643057823,50.5790939331],"type":"Point"}
}