{
  "type": "Feature",
  "properties": {
    "addr:full":"Hoogstraat 31 Boom Antwerpen 2850",
    "addr:housenumber":"31",
    "addr:postcode":"2850",
    "addr:street":"Hoogstraat",
    "iso:country":"BE",
    "sg:address":"Hoogstraat 31",
    "sg:city":"Boom",
    "sg:orig_category":"Solariums",
    "sg:phone":"+32 3 843 30 71",
    "sg:postcode":"2850",
    "sg:province":"Antwerpen",
    "wof:name":"Sun & Nailstudio Oase",
    "wof:placetype":"venue"
},
  "geometry": {"coordinates":[4.3656821251,51.0859489441],"type":"Point"}
}