{
  "type": "Feature",
  "properties": {
    "addr:full":"Leonardo Da Vinci Laan 15 Diegem Vlaams-Brabant 1831",
    "addr:housenumber":"15",
    "addr:postcode":"1831",
    "addr:street":"Leonardo;Vinci Laan",
    "iso:country":"BE",
    "sg:address":"Leonardo Da Vinci Laan 15",
    "sg:city":"Diegem",
    "sg:classifiers":[
        {
            "category":"Real Estate",
            "subcategory":"Real Estate Operator",
            "type":"Services"
        }
    ],
    "sg:phone":"+32 2 719 12 11",
    "sg:postcode":"1831",
    "sg:province":"Vlaams-Brabant",
    "sg:tags":[
        "application",
        "asp",
        "provider"
    ],
    "wof:name":"Oracle Belgium/luxembourg",
    "wof:placetype":"venue"
},
  "geometry": {"coordinates":[4.4359431267,50.8944854736],"type":"Point"}
}