{
  "type": "Feature",
  "properties": {
    "iso:country":"BE",
    "sg:address":"Roeselarestraat 56",
    "sg:city":"Kortemark (zarren-werken)",
    "sg:orig_category":"Non-Classified Establishments",
    "sg:postcode":"8610",
    "sg:province":"West-Vlaanderen",
    "wof:name":"Transport R Vandemoortel",
    "wof:placetype":"venue"
},
  "geometry": {"coordinates":[2.9908061028,50.9915618896],"type":"Point"}
}