{
  "type": "Feature",
  "properties": {
    "iso:country":"BE",
    "sg:address":"Route De Brienne 22",
    "sg:city":"Bouillon (bellevaux)",
    "sg:classifiers":[
        {
            "category":"Building & Trades",
            "subcategory":"Construction",
            "type":"Services"
        }
    ],
    "sg:phone":"+32 61 46 89 22",
    "sg:postcode":"6834",
    "sg:province":"Luxembourg",
    "sg:tags":[
        "carpenter"
    ],
    "wof:name":"Mary P",
    "wof:placetype":"venue"
},
  "geometry": {"coordinates":[5.1092801094,49.8381462097],"type":"Point"}
}