{
  "type": "Feature",
  "properties": {
    "addr:full":"Langstraat 32 Wellen Limburg 3830",
    "addr:housenumber":"32",
    "addr:postcode":"3830",
    "addr:street":"Langstraat",
    "iso:country":"BE",
    "sg:address":"Langstraat 32",
    "sg:city":"Wellen",
    "sg:orig_category":"Fruitteelt",
    "sg:phone":"+32 12 74 55 80",
    "sg:postcode":"3830",
    "sg:province":"Limburg",
    "wof:name":"Neon",
    "wof:placetype":"venue"
},
  "geometry": {"coordinates":[5.3092069626,50.8187522888],"type":"Point"}
}