{
  "type": "Feature",
  "properties": {
    "addr:full":"Rue Xhauflaire 153 Dison Li\u00e8ge 4820",
    "addr:housenumber":"153",
    "addr:postcode":"4820",
    "addr:street":"Rue Xhauflaire",
    "iso:country":"BE",
    "sg:address":"Rue Xhauflaire 153",
    "sg:city":"Dison",
    "sg:classifiers":[
        {
            "category":"Professional",
            "subcategory":"Printing & Photocopies",
            "type":"Services"
        }
    ],
    "sg:phone":"+32 87 31 28 47",
    "sg:postcode":"4820",
    "sg:province":"Li\u00e8ge",
    "sg:tags":[
        "-",
        "offset"
    ],
    "wof:name":"Sabel Print Sa",
    "wof:placetype":"venue"
},
  "geometry": {"coordinates":[5.863255024,50.6102333069],"type":"Point"}
}