{
  "type": "Feature",
  "properties": {
    "iso:country":"BE",
    "sg:address":"Bavikhoofsestraat 96",
    "sg:city":"Kuurne",
    "sg:classifiers":[
        {
            "category":"Shopping",
            "subcategory":"Florist",
            "type":"Retail Goods"
        }
    ],
    "sg:phone":"+32 56 71 87 79",
    "sg:postcode":"8520",
    "sg:province":"West-Vlaanderen",
    "wof:name":"Verbeke-tytgat",
    "wof:placetype":"venue"
},
  "geometry": {"coordinates":[3.291893959,50.856262207],"type":"Point"}
}