{
  "type": "Feature",
  "properties": {
    "addr:full":"Avenue Alb. Opsomer 4 Mont-de-l'enclus (orroir) Hainaut 7750",
    "addr:housenumber":"4",
    "addr:postcode":"7750",
    "addr:street":"Avenue Alb. Opsomer;Orroir Hainaut",
    "iso:country":"BE",
    "sg:address":"Avenue Alb. Opsomer 4",
    "sg:city":"Mont-de-l'enclus (orroir)",
    "sg:classifiers":[
        {
            "category":"Shopping",
            "subcategory":"Clothing, Apparel, & Fashions",
            "type":"Retail Goods"
        }
    ],
    "sg:phone":"+32 69 54 95 10",
    "sg:postcode":"7750",
    "sg:province":"Hainaut",
    "sg:tags":[
        "lady",
        "clothing",
        "-"
    ],
    "wof:name":"Sciovani Fashion Sprl",
    "wof:placetype":"venue"
},
  "geometry": {"coordinates":[2.6025109291,46.3370933533],"type":"Point"}
}