{
  "type": "Feature",
  "properties": {
    "addr:full":"Chauss\u00c9e De Malines 256 Wezembeek-oppem Vlaams-Brabant 1970",
    "addr:housenumber":"256",
    "addr:postcode":"1970",
    "addr:street":"Chausse\u0301E De Malines",
    "iso:country":"BE",
    "sg:address":"Chauss\u00c9e De Malines 256",
    "sg:city":"Wezembeek-oppem",
    "sg:orig_category":"Entretien and r\u00e9parations de voitures",
    "sg:phone":"+32 2 731 63 94",
    "sg:postcode":"1970",
    "sg:province":"Vlaams-Brabant",
    "wof:name":"Imo Car Wash",
    "wof:placetype":"venue"
},
  "geometry": {"coordinates":[4.4937500954,50.8400688171],"type":"Point"}
}