{
  "type": "Feature",
  "properties": {
    "iso:country":"BE",
    "sg:address":"Vierhuizenstraat 6",
    "sg:city":"Leuven (wilsele)",
    "sg:classifiers":[
        {
            "category":"Professional",
            "subcategory":"Management & Consulting",
            "type":"Services"
        }
    ],
    "sg:phone":"+32 16 44 80 83",
    "sg:postcode":"3012",
    "sg:province":"Vlaams-Brabant",
    "sg:tags":[
        "consultant"
    ],
    "wof:name":"Anthoon G Training Services",
    "wof:placetype":"venue"
},
  "geometry": {"coordinates":[4.7315239906,50.930606842],"type":"Point"}
}