{
  "type": "Feature",
  "properties": {
    "addr:full":"Chauss\u00e9e De Mons 209 Braine-le-comte Hainaut 7090",
    "addr:housenumber":"209",
    "addr:postcode":"7090",
    "addr:street":"Chausse\u0301E De Mons",
    "iso:country":"BE",
    "sg:address":"Chauss\u00e9e De Mons 209",
    "sg:city":"Braine-le-comte",
    "sg:classifiers":[
        {
            "category":"Shopping",
            "subcategory":"Antiques",
            "type":"Retail Goods"
        }
    ],
    "sg:phone":"+32 67 55 77 28",
    "sg:postcode":"7090",
    "sg:province":"Hainaut",
    "wof:name":"Marchal J",
    "wof:placetype":"venue"
},
  "geometry": {"coordinates":[4.108725071,50.595085144],"type":"Point"}
}