{
  "type": "Feature",
  "properties": {
    "addr:full":"Rue D'enines 1a Ramillies (huppaye) Brabant Wallon 1367",
    "addr:housenumber":"1a",
    "addr:postcode":"1367",
    "addr:street":"Rue D'Enines;Wallon",
    "iso:country":"BE",
    "sg:address":"Rue D'enines 1a",
    "sg:city":"Ramillies (huppaye)",
    "sg:classifiers":[
        {
            "category":"Building & Trades",
            "subcategory":"Landscaping Services",
            "type":"Services"
        }
    ],
    "sg:phone":"+32 10 81 56 86",
    "sg:postcode":"1367",
    "sg:province":"Brabant Wallon",
    "sg:tags":[
        "handicraft"
    ],
    "wof:name":"Arti-show",
    "wof:placetype":"venue"
},
  "geometry": {"coordinates":[4.9036808014,50.6954193115],"type":"Point"}
}