{
  "type": "Feature",
  "properties": {
    "iso:country":"BE",
    "sg:address":"Rue De Soignies 183b",
    "sg:city":"Ath (maffle)",
    "sg:classifiers":[
        {
            "category":"Structure",
            "subcategory":"Office Building",
            "type":"Public Place"
        }
    ],
    "sg:phone":"+32 68 84 04 57",
    "sg:postcode":"7810",
    "sg:province":"Hainaut",
    "sg:tags":[
        "roofing",
        "slate"
    ],
    "wof:name":"Haublin Sprl",
    "wof:placetype":"venue"
},
  "geometry": {"coordinates":[3.8022899628,50.6149749756],"type":"Point"}
}