{
  "type": "Feature",
  "properties": {
    "iso:country":"BE",
    "sg:address":"Van Pulstraat 34bb",
    "sg:city":"Brecht",
    "sg:orig_category":"Services de Nettoyage and de D\u00e9sinfection",
    "sg:phone":"+32 3 288 64 07",
    "sg:postcode":"2960",
    "sg:province":"Antwerpen",
    "wof:name":"W.v.v. Clean",
    "wof:placetype":"venue"
},
  "geometry": {"coordinates":[4.6472058296,51.3441047668],"type":"Point"}
}