{
  "type": "Feature",
  "properties": {
    "addr:full":"Kerkstraat 18 Oostrozebeke West-Vlaanderen 8780",
    "addr:housenumber":"18",
    "addr:postcode":"8780",
    "addr:street":"Kerkstraat",
    "iso:country":"BE",
    "sg:address":"Kerkstraat 18",
    "sg:city":"Oostrozebeke",
    "sg:orig_category":"Installation \u00e9lectrique r\u00e9sidentielle",
    "sg:phone":"+32 56 66 60 39",
    "sg:postcode":"8780",
    "sg:province":"West-Vlaanderen",
    "wof:name":"Jozef Vanoverschelde",
    "wof:placetype":"venue"
},
  "geometry": {"coordinates":[3.3361129761,50.9210891724],"type":"Point"}
}