{
  "type": "Feature",
  "properties": {
    "addr:full":"Han 23 Tintigny Luxembourg 6730",
    "addr:housenumber":"23",
    "addr:postcode":"6730",
    "addr:street":"Han",
    "iso:country":"BE",
    "sg:address":"Han 23",
    "sg:city":"Tintigny",
    "sg:orig_category":"Rundveehouders",
    "sg:phone":"+32 63 44 42 03",
    "sg:postcode":"6730",
    "sg:province":"Luxembourg",
    "wof:name":"Servais",
    "wof:placetype":"venue"
},
  "geometry": {"coordinates":[5.5262727737,49.6809234619],"type":"Point"}
}