{
  "type": "Feature",
  "properties": {
    "addr:full":"Sluizerweg 8 Riemst Limburg 3770",
    "addr:housenumber":"8",
    "addr:postcode":"3770",
    "addr:street":"Sluizerweg",
    "iso:country":"BE",
    "sg:address":"Sluizerweg 8",
    "sg:city":"Riemst",
    "sg:orig_category":"Fruitteelt",
    "sg:phone":"+32 12 23 41 83",
    "sg:postcode":"3770",
    "sg:province":"Limburg",
    "wof:name":"Jean Oben",
    "wof:placetype":"venue"
},
  "geometry": {"coordinates":[5.5559720993,50.7809524536],"type":"Point"}
}