{
  "type": "Feature",
  "properties": {
    "iso:country":"BE",
    "sg:address":"Watermolenweg 1",
    "sg:city":"Grobbendonk",
    "sg:classifiers":[
        {
            "category":"Utilities",
            "subcategory":"Refuse",
            "type":"Services"
        }
    ],
    "sg:phone":"+32 14 51 10 73",
    "sg:postcode":"2280",
    "sg:province":"Antwerpen",
    "sg:tags":[
        "miller"
    ],
    "wof:name":"Van Hool F",
    "wof:placetype":"venue"
},
  "geometry": {"coordinates":[4.7680702209,51.1858711243],"type":"Point"}
}