{
  "type": "Feature",
  "properties": {
    "iso:country":"BE",
    "sg:address":"Doorniksewijk 186",
    "sg:city":"Kortrijk",
    "sg:classifiers":[
        {
            "category":"Fast Food",
            "type":"Food & Drink"
        }
    ],
    "sg:phone":"+32 56 21 66 90",
    "sg:postcode":"8500",
    "sg:province":"West-Vlaanderen",
    "sg:tags":[
        "meeneem",
        "restaurant"
    ],
    "wof:name":"\u00b4t Kanon",
    "wof:placetype":"venue"
},
  "geometry": {"coordinates":[3.2700591087,50.816860199],"type":"Point"}
}