{
  "type": "Feature",
  "properties": {
    "addr:full":"Rue Barre Saint-brice Tournai Hainaut 7500",
    "addr:postcode":"7500",
    "addr:street":"Rue Barre",
    "iso:country":"BE",
    "sg:address":"Rue Barre Saint-brice",
    "sg:city":"Tournai",
    "sg:orig_category":"Opticiens",
    "sg:phone":"+32 69 88 33 12",
    "sg:postcode":"7500",
    "sg:province":"Hainaut",
    "wof:name":"Point De Mire",
    "wof:placetype":"venue"
},
  "geometry": {"coordinates":[3.3945679665,50.6078491211],"type":"Point"}
}