{
  "type": "Feature",
  "properties": {
    "addr:full":"Chemin Des Archiducs 66 Namur Namur 5100",
    "addr:housenumber":"66",
    "addr:postcode":"5100",
    "addr:street":"Chemin Des Archiducs",
    "iso:country":"BE",
    "sg:address":"Chemin Des Archiducs 66",
    "sg:city":"Namur",
    "sg:orig_category":"M\u00e9decins and sp\u00e9cialistes",
    "sg:phone":"+32 81 46 24 20",
    "sg:postcode":"5100",
    "sg:province":"Namur",
    "wof:name":"Marie Petit",
    "wof:placetype":"venue"
},
  "geometry": {"coordinates":[4.8544669151,50.421836853],"type":"Point"}
}