{
  "type": "Feature",
  "properties": {
    "iso:country":"BE",
    "sg:address":"Wezerenstraat 106",
    "sg:city":"Landen",
    "sg:orig_category":"Eleveurs de bovins",
    "sg:phone":"+32 11 88 20 60",
    "sg:postcode":"3401",
    "sg:province":"Vlaams-Brabant",
    "wof:name":"Jaak Berghmans",
    "wof:placetype":"venue"
},
  "geometry": {"coordinates":[5.0912699699,50.7356071472],"type":"Point"}
}