{
  "type": "Feature",
  "properties": {
    "addr:full":"Lambroeckstraat 35 Dendermonde (oudegem) Oost-Vlaanderen 9200",
    "addr:housenumber":"35",
    "addr:postcode":"9200",
    "addr:street":"Lambroeckstraat",
    "iso:country":"BE",
    "sg:address":"Lambroeckstraat 35",
    "sg:city":"Dendermonde (oudegem)",
    "sg:classifiers":[
        {
            "category":"Banks & Credit Unions",
            "subcategory":"Investment Brokerage",
            "type":"Services"
        }
    ],
    "sg:phone":"+32 52 22 33 44",
    "sg:postcode":"9200",
    "sg:province":"Oost-Vlaanderen",
    "wof:name":"Pensaert M",
    "wof:placetype":"venue"
},
  "geometry": {"coordinates":[4.0983099937,51.0315208435],"type":"Point"}
}