{
  "type": "Feature",
  "properties": {
    "iso:country":"BE",
    "sg:address":"Molsebaan 75",
    "sg:city":"Dessel",
    "sg:classifiers":[
        {
            "category":"Professional",
            "subcategory":"Management & Consulting",
            "type":"Services"
        }
    ],
    "sg:phone":"+32 14 37 73 58",
    "sg:postcode":"2480",
    "sg:province":"Antwerpen",
    "sg:tags":[
        "consultant"
    ],
    "wof:name":"Moonen Bedrijfsadvisering Bvba",
    "wof:placetype":"venue"
},
  "geometry": {"coordinates":[5.1133527756,51.2347831726],"type":"Point"}
}