{
  "type": "Feature",
  "properties": {
    "addr:full":"Nieuwelaan 21 Merchtem (brussegem) Vlaams-Brabant 1785",
    "addr:housenumber":"21",
    "addr:postcode":"1785",
    "addr:street":"Nieuwelaan",
    "iso:country":"BE",
    "sg:address":"Nieuwelaan 21",
    "sg:city":"Merchtem (brussegem)",
    "sg:classifiers":[
        {
            "category":"Professional",
            "subcategory":"Lawyer & Legal Services",
            "type":"Services"
        }
    ],
    "sg:phone":"+32 2 461 26 20",
    "sg:postcode":"1785",
    "sg:province":"Vlaams-Brabant",
    "wof:name":"De Valck D",
    "wof:placetype":"venue"
},
  "geometry": {"coordinates":[4.2265000343,50.982219696],"type":"Point"}
}