{
  "type": "Feature",
  "properties": {
    "addr:full":"Chauss\u00e9e De Wavre 828 Bruxelles (etterbeek) Bruxelles-Capitale 1040",
    "addr:housenumber":"828",
    "addr:postcode":"1040",
    "addr:street":"Chausse\u0301E De Wavre",
    "iso:country":"BE",
    "sg:address":"Chauss\u00e9e De Wavre 828",
    "sg:city":"Bruxelles (etterbeek)",
    "sg:classifiers":[
        {
            "category":"Food & Beverages",
            "subcategory":"Groceries & Convenience Stores",
            "type":"Retail Goods"
        }
    ],
    "sg:phone":"+32 2 649 62 97",
    "sg:postcode":"1040",
    "sg:province":"Bruxelles-Capitale",
    "sg:tags":[
        "grocer"
    ],
    "wof:name":"Vanden Berghe J",
    "wof:placetype":"venue"
},
  "geometry": {"coordinates":[4.3929772377,50.8288574219],"type":"Point"}
}