{
  "type": "Feature",
  "properties": {
    "iso:country":"BE",
    "sg:address":"Turnhoutsebaan 328",
    "sg:city":"Wijnegem",
    "sg:orig_category":"Pain, p\u00e2tisseries and confiseries",
    "sg:phone":"+32 3 353 61 50",
    "sg:postcode":"2110",
    "sg:province":"Antwerpen",
    "wof:name":"Bakkerij Lefebvre",
    "wof:placetype":"venue"
},
  "geometry": {"coordinates":[4.5179347992,51.2269744873],"type":"Point"}
}