{
  "type": "Feature",
  "properties": {
    "iso:country":"BE",
    "sg:address":"Alfons Pieterslaan 80",
    "sg:city":"Oostende",
    "sg:classifiers":[
        {
            "category":"Manufacturing",
            "subcategory":"Textiles",
            "type":"Manufacturing & Wholesale Goods"
        }
    ],
    "sg:phone":"+32 59 50 44 78",
    "sg:postcode":"8400",
    "sg:province":"West-Vlaanderen",
    "wof:name":"Gordaform",
    "wof:placetype":"venue"
},
  "geometry": {"coordinates":[2.9118440151,51.2253684998],"type":"Point"}
}