{
  "type": "Feature",
  "properties": {
    "addr:full":"Rue Du Grand Duc 47 Bruxelles (etterbeek) Bruxelles-Capitale 1040",
    "addr:housenumber":"47",
    "addr:postcode":"1040",
    "addr:street":"Rue Du Grand Duc",
    "iso:country":"BE",
    "sg:address":"Rue Du Grand Duc 47",
    "sg:city":"Bruxelles (etterbeek)",
    "sg:classifiers":[
        {
            "category":"Building & Trades",
            "subcategory":"Equipment Rental",
            "type":"Services"
        }
    ],
    "sg:phone":"+32 2 648 83 92",
    "sg:postcode":"1040",
    "sg:province":"Bruxelles-Capitale",
    "sg:tags":[
        "tableware",
        "-"
    ],
    "wof:name":"Chaise Dor\u00e9e (la) Sprl",
    "wof:placetype":"venue"
},
  "geometry": {"coordinates":[4.3845081329,50.8326683044],"type":"Point"}
}