{
  "type": "Feature",
  "properties": {
    "addr:full":"Rue Jacquet 2 Rochefort Namur 5580",
    "addr:housenumber":"2",
    "addr:postcode":"5580",
    "addr:street":"Rue Jacquet",
    "iso:country":"BE",
    "sg:address":"Rue Jacquet 2",
    "sg:city":"Rochefort",
    "sg:classifiers":[
        {
            "category":"Communications",
            "subcategory":"Film & Video Production",
            "type":"Services"
        }
    ],
    "sg:phone":"+32 84 21 46 68",
    "sg:postcode":"5580",
    "sg:province":"Namur",
    "sg:tags":[
        "hiring",
        "-"
    ],
    "wof:name":"Splash Vid\u00e9o",
    "wof:placetype":"venue"
},
  "geometry": {"coordinates":[5.2225618362,50.1572189331],"type":"Point"}
}