{
  "type": "Feature",
  "properties": {
    "iso:country":"BE",
    "sg:address":"Frans Tijsmanstunnel",
    "sg:city":"Antwerpen",
    "sg:orig_category":"Non-Classified Establishments",
    "sg:phone":"+32 3 560 32 11",
    "sg:postcode":"2040",
    "sg:province":"Antwerpen",
    "wof:name":"Degussa Antwerpen Nv",
    "wof:placetype":"venue"
},
  "geometry": {"coordinates":[4.3203020096,51.3086166382],"type":"Point"}
}