{
  "type": "Feature",
  "properties": {
    "iso:country":"BE",
    "sg:address":"Korte Vinkestraat 2",
    "sg:city":"Wevelgem",
    "sg:classifiers":[
        {
            "category":"Food & Beverages",
            "subcategory":"Fruits & Vegetables",
            "type":"Retail Goods"
        }
    ],
    "sg:phone":"+32 56 40 38 65",
    "sg:postcode":"8560",
    "sg:province":"West-Vlaanderen",
    "sg:tags":[
        "groenten"
    ],
    "wof:name":"Sabine Ponseele",
    "wof:placetype":"venue"
},
  "geometry": {"coordinates":[3.1900980473,50.8222885132],"type":"Point"}
}