{
  "type": "Feature",
  "properties": {
    "addr:full":"Kielsbroek 4b70 Antwerpen Antwerpen 2020",
    "addr:housenumber":"4b70",
    "addr:postcode":"2020",
    "addr:street":"Kielsbroek",
    "iso:country":"BE",
    "sg:address":"Kielsbroek 4b70",
    "sg:city":"Antwerpen",
    "sg:orig_category":"Voedingsspeciaalzaken",
    "sg:phone":"+32 3 248 28 54",
    "sg:postcode":"2020",
    "sg:province":"Antwerpen",
    "wof:name":"Fa. Frank",
    "wof:placetype":"venue"
},
  "geometry": {"coordinates":[4.3710751534,51.1964530945],"type":"Point"}
}