{
  "type": "Feature",
  "properties": {
    "iso:country":"BE",
    "sg:address":"Lossingstraat 146",
    "sg:city":"Schoten",
    "sg:orig_category":"Non-Classified Establishments",
    "sg:phone":"+32 3 685 20 34",
    "sg:postcode":"2900",
    "sg:province":"Antwerpen",
    "wof:name":"Mykko",
    "wof:placetype":"venue"
},
  "geometry": {"coordinates":[4.5094671249,51.2554092407],"type":"Point"}
}