{
  "type": "Feature",
  "properties": {
    "addr:full":"Grand'route 87 Mont-saint-guibert (corbais) Brabant Wallon 1435",
    "addr:housenumber":"87",
    "addr:postcode":"1435",
    "addr:street":"Grand'Route;Wallon",
    "iso:country":"BE",
    "sg:address":"Grand'route 87",
    "sg:city":"Mont-saint-guibert (corbais)",
    "sg:classifiers":[
        {
            "category":"Home & Garden",
            "subcategory":"Home Furnishings",
            "type":"Retail Goods"
        }
    ],
    "sg:phone":"+32 10 65 80 29",
    "sg:postcode":"1435",
    "sg:province":"Brabant Wallon",
    "sg:tags":[
        "-",
        "furniture"
    ],
    "wof:name":"Specialiste Du Pin Massif (le)",
    "wof:placetype":"venue"
},
  "geometry": {"coordinates":[4.6107521057,50.6339874268],"type":"Point"}
}