{
  "type": "Feature",
  "properties": {
    "iso:country":"BE",
    "sg:address":"Nijvelsedreef 178",
    "sg:city":"Oudergem/auderghem",
    "sg:orig_category":"Artsen and specialisten",
    "sg:phone":"+32 2 672 34 14",
    "sg:postcode":"1160",
    "sg:province":"Bruxelles-Capitale",
    "wof:name":"Christine Delhal",
    "wof:placetype":"venue"
},
  "geometry": {"coordinates":[4.4097299576,50.8240509033],"type":"Point"}
}