{
  "type": "Feature",
  "properties": {
    "iso:country":"BE",
    "sg:address":"Rue De La Gare 16",
    "sg:city":"Qui\u00e9vrain",
    "sg:classifiers":[
        {
            "category":"Health Services",
            "subcategory":"Health Practitioner",
            "type":"Services"
        }
    ],
    "sg:phone":"+32 65 45 76 60",
    "sg:postcode":"7380",
    "sg:province":"Hainaut",
    "sg:tags":[
        "physiotherapist"
    ],
    "wof:name":"Dordain V",
    "wof:placetype":"venue"
},
  "geometry": {"coordinates":[3.6850819588,50.4084625244],"type":"Point"}
}