{
  "type": "Feature",
  "properties": {
    "addr:full":"E. Vlieberghlaan 21 Overpelt Limburg 3900",
    "addr:housenumber":"21",
    "addr:postcode":"3900",
    "addr:street":"E. Vlieberghlaan",
    "iso:country":"BE",
    "sg:address":"E. Vlieberghlaan 21",
    "sg:city":"Overpelt",
    "sg:orig_category":"Traitement and rev\u00eatement des m\u00e9taux",
    "sg:phone":"+32 11 64 84 59",
    "sg:postcode":"3900",
    "sg:province":"Limburg",
    "wof:name":"Huklo",
    "wof:placetype":"venue"
},
  "geometry": {"coordinates":[5.3788499832,51.226184845],"type":"Point"}
}