{
  "type": "Feature",
  "properties": {
    "addr:full":"Avenue Des P\u00e9tunias 9 Kraainem Vlaams-Brabant 1950",
    "addr:housenumber":"9",
    "addr:postcode":"1950",
    "addr:street":"Avenue Des Pe\u0301Tunias",
    "iso:country":"BE",
    "sg:address":"Avenue Des P\u00e9tunias 9",
    "sg:city":"Kraainem",
    "sg:classifiers":[
        {
            "category":"Social Services",
            "subcategory":"Job Training",
            "type":"Services"
        }
    ],
    "sg:phone":"+32 2 721 04 15",
    "sg:postcode":"1950",
    "sg:province":"Vlaams-Brabant",
    "sg:tags":[
        "personnel"
    ],
    "wof:name":"Diamond Learning",
    "wof:placetype":"venue"
},
  "geometry": {"coordinates":[4.4586381912,50.8544692993],"type":"Point"}
}