{
  "type": "Feature",
  "properties": {
    "addr:full":"Place Xhov\u00c9mont 4 Verviers Li\u00e8ge 4800",
    "addr:housenumber":"4",
    "addr:postcode":"4800",
    "addr:street":"Place Xhove\u0301Mont",
    "iso:country":"BE",
    "sg:address":"Place Xhov\u00c9mont 4",
    "sg:city":"Verviers",
    "sg:orig_category":"Pain, p\u00e2tisseries and confiseries",
    "sg:phone":"+32 87 35 28 06",
    "sg:postcode":"4800",
    "sg:province":"Li\u00e8ge",
    "wof:name":"P\u00c2tisserie St.martin",
    "wof:placetype":"venue"
},
  "geometry": {"coordinates":[5.8594508171,50.5917663574],"type":"Point"}
}