{
  "type": "Feature",
  "properties": {
    "addr:full":"Rue Henri Van Zuylen 54 Bruxelles (uccle) Bruxelles-Capitale 1180",
    "addr:housenumber":"54",
    "addr:postcode":"1180",
    "addr:street":"Rue Henri Van Zuylen",
    "iso:country":"BE",
    "sg:address":"Rue Henri Van Zuylen 54",
    "sg:city":"Bruxelles (uccle)",
    "sg:classifiers":[
        {
            "category":"Health Services",
            "subcategory":"Health Practitioner",
            "type":"Services"
        }
    ],
    "sg:phone":"+32 2 375 07 62",
    "sg:postcode":"1180",
    "sg:province":"Bruxelles-Capitale",
    "sg:tags":[
        "physiotherapist"
    ],
    "wof:name":"Hermans J",
    "wof:placetype":"venue"
},
  "geometry": {"coordinates":[4.3396167755,50.7977790833],"type":"Point"}
}