{
  "type": "Feature",
  "properties": {
    "iso:country":"BE",
    "sg:address":"Maarkendries 14",
    "sg:city":"Maarkedal (etikhove)",
    "sg:classifiers":[
        {
            "category":"Health Services",
            "subcategory":"Health Practitioner",
            "type":"Services"
        }
    ],
    "sg:phone":"+32 55 30 32 30",
    "sg:postcode":"9680",
    "sg:province":"Oost-Vlaanderen",
    "sg:tags":[
        "physiotherapist"
    ],
    "wof:name":"Declercq Eddy",
    "wof:placetype":"venue"
},
  "geometry": {"coordinates":[3.6212110519,50.8170623779],"type":"Point"}
}