{
  "type": "Feature",
  "properties": {
    "addr:full":"Vismarkt 29 Tessenderlo Limburg 3980",
    "addr:housenumber":"29",
    "addr:postcode":"3980",
    "addr:street":"Vismarkt",
    "iso:country":"BE",
    "sg:address":"Vismarkt 29",
    "sg:city":"Tessenderlo",
    "sg:orig_category":"Avocats and conseillers juridiques",
    "sg:phone":"+32 13 67 28 26",
    "sg:postcode":"3980",
    "sg:province":"Limburg",
    "wof:name":"Theo Macours",
    "wof:placetype":"venue"
},
  "geometry": {"coordinates":[5.0903120041,51.0706672668],"type":"Point"}
}