{
  "type": "Feature",
  "properties": {
    "iso:country":"BE",
    "sg:address":"Zandberg 4",
    "sg:city":"Heuvelland (de Klijte)",
    "sg:classifiers":[
        {
            "category":"Building & Trades",
            "subcategory":"Landscaping Services",
            "type":"Services"
        }
    ],
    "sg:phone":"+32 57 44 71 70",
    "sg:postcode":"8954",
    "sg:province":"West-Vlaanderen",
    "sg:tags":[
        "gardening",
        "garden",
        "maintenance"
    ],
    "wof:name":"Van Poucke O",
    "wof:placetype":"venue"
},
  "geometry": {"coordinates":[2.7796530724,50.8003349304],"type":"Point"}
}