{
  "type": "Feature",
  "properties": {
    "iso:country":"BE",
    "sg:address":"Brusselsestweeg 413",
    "sg:city":"Zemst",
    "sg:orig_category":"Herstellingen and onderhoud van auto's",
    "sg:phone":"+32 15 61 66 52",
    "sg:postcode":"1980",
    "sg:province":"Vlaams-Brabant",
    "wof:name":"Edd Cars",
    "wof:placetype":"venue"
},
  "geometry": {"coordinates":[4.4645547867,50.9849433899],"type":"Point"}
}