{
  "type": "Feature",
  "properties": {
    "addr:full":"Rue De L'arbre B\u00e9nit 16 Bruxelles (ixelles) Bruxelles-Capitale 1050",
    "addr:housenumber":"16",
    "addr:postcode":"1050",
    "addr:street":"Rue De L'Arbre Be\u0301Nit",
    "iso:country":"BE",
    "sg:address":"Rue De L'arbre B\u00e9nit 16",
    "sg:city":"Bruxelles (ixelles)",
    "sg:classifiers":[
        {
            "category":"Professional",
            "subcategory":"Computer Services",
            "type":"Services"
        }
    ],
    "sg:phone":"+32 2 511 17 31",
    "sg:postcode":"1050",
    "sg:province":"Bruxelles-Capitale",
    "sg:tags":[
        "-",
        "processing",
        "data",
        "software"
    ],
    "wof:name":"Ao International Sa",
    "wof:placetype":"venue"
},
  "geometry": {"coordinates":[4.3639941216,50.8342475891],"type":"Point"}
}