{
  "type": "Feature",
  "properties": {
    "iso:country":"BE",
    "sg:address":"Poekestraat 102",
    "sg:city":"Ruiselede",
    "sg:orig_category":"Boucheries",
    "sg:phone":"+32 9 374 68 47",
    "sg:postcode":"8755",
    "sg:province":"West-Vlaanderen",
    "wof:name":"Mabel-meat",
    "wof:placetype":"venue"
},
  "geometry": {"coordinates":[3.4281580448,51.0435447693],"type":"Point"}
}