{
  "type": "Feature",
  "properties": {
    "iso:country":"BE",
    "sg:address":"Ossogne 43",
    "sg:city":"Havelange",
    "sg:orig_category":"Eleveurs de bovins",
    "sg:phone":"+32 83 63 38 65",
    "sg:postcode":"5370",
    "sg:province":"Namur",
    "wof:name":"Eric Maes",
    "wof:placetype":"venue"
},
  "geometry": {"coordinates":[5.2163510323,50.4018363953],"type":"Point"}
}