{
  "type": "Feature",
  "properties": {
    "addr:full":"Oude Staatsbaan 80 Maldegem Oost-Vlaanderen 9991",
    "addr:housenumber":"80",
    "addr:postcode":"9991",
    "addr:street":"Oude Staatsbaan",
    "iso:country":"BE",
    "sg:address":"Oude Staatsbaan 80",
    "sg:city":"Maldegem",
    "sg:classifiers":[
        {
            "category":"Fast Food",
            "type":"Food & Drink"
        }
    ],
    "sg:phone":"+32 50 71 84 18",
    "sg:postcode":"9991",
    "sg:province":"Oost-Vlaanderen",
    "sg:tags":[
        "meeneem",
        "restaurant"
    ],
    "wof:name":"Frituur Raf",
    "wof:placetype":"venue"
},
  "geometry": {"coordinates":[3.5015699863,51.204914093],"type":"Point"}
}