{
  "type": "Feature",
  "properties": {
    "addr:full":"Nestor De Ti\u00c8restraat 213 Oudenaarde Oost-Vlaanderen 9700",
    "addr:housenumber":"213",
    "addr:postcode":"9700",
    "addr:street":"Nestor De Tie\u0300Restraat",
    "iso:country":"BE",
    "sg:address":"Nestor De Ti\u00c8restraat 213",
    "sg:city":"Oudenaarde",
    "sg:orig_category":"Slagers",
    "sg:phone":"+32 55 31 14 81",
    "sg:postcode":"9700",
    "sg:province":"Oost-Vlaanderen",
    "wof:name":"Beenhouwerij Luc",
    "wof:placetype":"venue"
},
  "geometry": {"coordinates":[3.6219890118,50.869720459],"type":"Point"}
}