{
  "type": "Feature",
  "properties": {
    "addr:full":"Rue De Verdun 521 Brussel/bruxelles Bruxelles-Capitale 1130",
    "addr:housenumber":"521",
    "addr:postcode":"1130",
    "addr:street":"Rue De Verdun;/",
    "iso:country":"BE",
    "sg:address":"Rue De Verdun 521",
    "sg:city":"Brussel/bruxelles",
    "sg:orig_category":"Cr\u00e8ches and garderies d'enfants",
    "sg:phone":"+32 2 242 57 08",
    "sg:postcode":"1130",
    "sg:province":"Bruxelles-Capitale",
    "wof:name":"Kribbe Lentebloempjes",
    "wof:placetype":"venue"
},
  "geometry": {"coordinates":[4.4197530746,50.8948631287],"type":"Point"}
}