{
  "type": "Feature",
  "properties": {
    "iso:country":"BE",
    "sg:address":"Hooghaag 24",
    "sg:city":"Hamont-achel",
    "sg:orig_category":"Pleisterwerk",
    "sg:phone":"+32 11 66 11 28",
    "sg:postcode":"3930",
    "sg:province":"Limburg",
    "wof:name":"Jozef Breemans",
    "wof:placetype":"venue"
},
  "geometry": {"coordinates":[5.4745898247,51.2498245239],"type":"Point"}
}