{
  "type": "Feature",
  "properties": {
    "addr:full":"Graaf Pierre De Brieylaan 17 Sint-michiels West-Vlaanderen 8200",
    "addr:housenumber":"17",
    "addr:postcode":"8200",
    "addr:street":"Graaf Pierre De Brieylaan",
    "iso:country":"BE",
    "sg:address":"Graaf Pierre De Brieylaan 17",
    "sg:city":"Sint-michiels",
    "sg:classifiers":[
        {
            "category":"Communications",
            "subcategory":"Film & Video Production",
            "type":"Services"
        }
    ],
    "sg:phone":"+32 50 38 58 26",
    "sg:postcode":"8200",
    "sg:province":"West-Vlaanderen",
    "sg:tags":[
        "workshop",
        "graphic"
    ],
    "wof:name":"Buromac",
    "wof:placetype":"venue"
},
  "geometry": {"coordinates":[3.1949551105,51.1865997314],"type":"Point"}
}