{
  "type": "Feature",
  "properties": {
    "iso:country":"BE",
    "sg:address":"Rue Baron Lheureux 9",
    "sg:city":"Colfontaine",
    "sg:orig_category":"Travaux de finition and nettoyage de b\u00e2timents",
    "sg:phone":"+32 65 66 11 45",
    "sg:postcode":"7340",
    "sg:province":"Hainaut",
    "wof:name":"Befumo",
    "wof:placetype":"venue"
},
  "geometry": {"coordinates":[3.8645169735,50.4081382751],"type":"Point"}
}