{
  "type": "Feature",
  "properties": {
    "addr:full":"Spoorwegln 44 Sint-niklaas Oost-Vlaanderen 9100",
    "addr:housenumber":"44",
    "addr:postcode":"9100",
    "addr:street":"Spoorwegln",
    "iso:country":"BE",
    "sg:address":"Spoorwegln 44",
    "sg:city":"Sint-niklaas",
    "sg:classifiers":[
        {
            "category":"Professional",
            "subcategory":"Engineering",
            "type":"Services"
        }
    ],
    "sg:phone":"+32 3 776 39 45",
    "sg:postcode":"9100",
    "sg:province":"Oost-Vlaanderen",
    "sg:tags":[
        "machine",
        "-",
        "mechanical"
    ],
    "wof:name":"H De Maesschalck Nv",
    "wof:placetype":"venue"
},
  "geometry": {"coordinates":[4.1363539696,51.1690216064],"type":"Point"}
}