{
  "type": "Feature",
  "properties": {
    "iso:country":"BE",
    "sg:address":"Avenue Des Arts 24 Box 21",
    "sg:city":"Bruxelles",
    "sg:classifiers":[
        {
            "category":"Social Services",
            "type":"Services"
        }
    ],
    "sg:phone":"+32 2 230 90 66",
    "sg:postcode":"1000",
    "sg:province":"Bruxelles-Capitale",
    "sg:tags":[
        "handicapped",
        "-"
    ],
    "wof:name":"Blindenzorg Licht & Liefde Brussel",
    "wof:placetype":"venue"
},
  "geometry": {"coordinates":[4.3690280914,50.8457374573],"type":"Point"}
}