{
  "type": "Feature",
  "properties": {
    "iso:country":"BE",
    "sg:address":"Alfons Braeckmanlaan 117",
    "sg:city":"Gent (sint-amandsberg)",
    "sg:classifiers":[
        {
            "category":"Real Estate",
            "subcategory":"Architect",
            "type":"Services"
        }
    ],
    "sg:phone":"+32 9 228 68 01",
    "sg:postcode":"9040",
    "sg:province":"Oost-Vlaanderen",
    "wof:name":"Peeren Marc Architektenbureau Bvba",
    "wof:placetype":"venue"
},
  "geometry": {"coordinates":[3.771337986,51.0639915466],"type":"Point"}
}