{
  "type": "Feature",
  "properties": {
    "addr:full":"Pr\u00e9 Lemaire 12 Limbourg Li\u00e8ge 4830",
    "addr:housenumber":"12",
    "addr:postcode":"4830",
    "addr:street":"Pre\u0301 Lemaire",
    "iso:country":"BE",
    "sg:address":"Pr\u00e9 Lemaire 12",
    "sg:city":"Limbourg",
    "sg:classifiers":[
        {
            "category":"Building & Trades",
            "subcategory":"Electrical",
            "type":"Services"
        }
    ],
    "sg:phone":"+32 87 76 40 44",
    "sg:postcode":"4830",
    "sg:province":"Li\u00e8ge",
    "sg:tags":[
        "electric",
        "-",
        "housewiring",
        "contractor"
    ],
    "wof:name":"Halin J-p",
    "wof:placetype":"venue"
},
  "geometry": {"coordinates":[5.9326028824,50.5979347229],"type":"Point"}
}