{
  "type": "Feature",
  "properties": {
    "addr:full":"Hoogdorpsstraat 36 Box 2 Alken Limburg 3570",
    "addr:housenumber":"36;2",
    "addr:postcode":"3570",
    "addr:street":"Hoogdorpsstraat;Box",
    "iso:country":"BE",
    "sg:address":"Hoogdorpsstraat 36 Box 2",
    "sg:city":"Alken",
    "sg:classifiers":[
        {
            "category":"Social Services",
            "type":"Services"
        }
    ],
    "sg:phone":"+32 11 59 39 21",
    "sg:postcode":"3570",
    "sg:province":"Limburg",
    "wof:name":"Team (pwa Werkwinkel)",
    "wof:placetype":"venue"
},
  "geometry": {"coordinates":[5.3056139946,50.8751869202],"type":"Point"}
}