{
  "type": "Feature",
  "properties": {
    "iso:country":"BE",
    "sg:address":"Burg. Vercruysselaan 14",
    "sg:city":"Kortrijk",
    "sg:orig_category":"Dranken Dranken Gh",
    "sg:phone":"+32 56 35 65 11",
    "sg:postcode":"8500",
    "sg:province":"West-Vlaanderen",
    "wof:name":"De Clerck Paul",
    "wof:placetype":"venue"
},
  "geometry": {"coordinates":[3.2660939693,50.8354988098],"type":"Point"}
}