{
  "type": "Feature",
  "properties": {
    "addr:full":"Avenue Raymond Brassinne 30 Braine L'alleud (braine-l'alleud) Brabant Wallon 1420",
    "addr:housenumber":"30",
    "addr:postcode":"1420",
    "addr:street":"Avenue Raymond Brassinne",
    "iso:country":"BE",
    "sg:address":"Avenue Raymond Brassinne 30",
    "sg:city":"Braine L'alleud (braine-l'alleud)",
    "sg:classifiers":[
        {
            "category":"Personal",
            "subcategory":"Beauty Salon",
            "type":"Services"
        }
    ],
    "sg:phone":"+32 2 384 20 30",
    "sg:postcode":"1420",
    "sg:province":"Brabant Wallon",
    "sg:tags":[
        "lady",
        "-",
        "hairdressing"
    ],
    "wof:name":"Cr\u00e9atif",
    "wof:placetype":"venue"
},
  "geometry": {"coordinates":[-0.7004899979,47.369140625],"type":"Point"}
}