{
  "type": "Feature",
  "properties": {
    "iso:country":"BE",
    "sg:address":"Terbeck 19",
    "sg:city":"Kortenaken",
    "sg:orig_category":"Fruitteelt Varkenskwekers",
    "sg:phone":"+32 16 77 79 75",
    "sg:postcode":"3472",
    "sg:province":"Vlaams-Brabant",
    "wof:name":"Marc Strouven",
    "wof:placetype":"venue"
},
  "geometry": {"coordinates":[5.0061092377,50.8914260864],"type":"Point"}
}