{
  "type": "Feature",
  "properties": {
    "iso:country":"BE",
    "sg:address":"Zoutwerf 14",
    "sg:city":"Mechelen",
    "sg:orig_category":"Fotografen and fotostudio's",
    "sg:phone":"+32 15 41 40 93",
    "sg:postcode":"2800",
    "sg:province":"Antwerpen",
    "wof:name":"Frans Geys",
    "wof:placetype":"venue"
},
  "geometry": {"coordinates":[4.4783902168,51.025177002],"type":"Point"}
}