{
  "type": "Feature",
  "properties": {
    "addr:full":"Rue Des Cloquettes 3 Mettet Namur 5640",
    "addr:housenumber":"3",
    "addr:postcode":"5640",
    "addr:street":"Rue Des Cloquettes",
    "iso:country":"BE",
    "sg:address":"Rue Des Cloquettes 3",
    "sg:city":"Mettet",
    "sg:classifiers":[
        {
            "category":"Health Services",
            "subcategory":"Health Practitioner",
            "type":"Services"
        }
    ],
    "sg:phone":"+32 71 72 66 91",
    "sg:postcode":"5640",
    "sg:province":"Namur",
    "sg:tags":[
        "physiotherapist"
    ],
    "wof:name":"Van Den Bergh K",
    "wof:placetype":"venue"
},
  "geometry": {"coordinates":[4.6607170105,50.3162765503],"type":"Point"}
}