{
  "type": "Feature",
  "properties": {
    "iso:country":"BE",
    "sg:address":"Tramstraat 24",
    "sg:city":"Oostkamp",
    "sg:classifiers":[
        {
            "category":"Food & Beverages",
            "subcategory":"Fruits & Vegetables",
            "type":"Retail Goods"
        }
    ],
    "sg:phone":"+32 50 27 52 49",
    "sg:postcode":"8020",
    "sg:province":"West-Vlaanderen",
    "sg:tags":[
        "l\u00e9gumes"
    ],
    "wof:name":"Suzanne Zutterman",
    "wof:placetype":"venue"
},
  "geometry": {"coordinates":[3.2159669399,51.0977706909],"type":"Point"}
}