{
  "type": "Feature",
  "properties": {
    "addr:full":"Rue De La Terre \u00e0 Briques 23 Tournai (blandain - Hertain) Hainaut 7522",
    "addr:housenumber":"23",
    "addr:postcode":"7522",
    "addr:street":"Rue De La Terre A\u0300 Briques;Hainaut",
    "iso:country":"BE",
    "sg:address":"Rue De La Terre \u00e0 Briques 23",
    "sg:city":"Tournai (blandain - Hertain)",
    "sg:classifiers":[
        {
            "category":"Utilities",
            "subcategory":"Fuel Oil & Lpg",
            "type":"Services"
        }
    ],
    "sg:phone":"+32 69 22 12 21",
    "sg:postcode":"7522",
    "sg:province":"Hainaut",
    "wof:name":"Comptoir Poelier Et Charbonnier",
    "wof:placetype":"venue"
},
  "geometry": {"coordinates":[3.3338780403,50.6130218506],"type":"Point"}
}