{
  "type": "Feature",
  "properties": {
    "addr:full":"Kapittelstraat 3 Oudenaarde Oost-Vlaanderen 9700",
    "addr:housenumber":"3",
    "addr:postcode":"9700",
    "addr:street":"Kapittelstraat",
    "iso:country":"BE",
    "sg:address":"Kapittelstraat 3",
    "sg:city":"Oudenaarde",
    "sg:classifiers":[
        {
            "category":"Cafe",
            "type":"Food & Drink"
        }
    ],
    "sg:phone":"+32 55 31 73 24",
    "sg:postcode":"9700",
    "sg:province":"Oost-Vlaanderen",
    "sg:tags":[
        "caf\u00e9s"
    ],
    "wof:name":"Caf\u00c9 De Kring",
    "wof:placetype":"venue"
},
  "geometry": {"coordinates":[3.6085999012,50.842590332],"type":"Point"}
}