{
  "type": "Feature",
  "properties": {
    "iso:country":"BE",
    "sg:address":"Chauss\u00e9e De Waterloo 244",
    "sg:city":"Rhode-saint-gen\u00e8se",
    "sg:classifiers":[
        {
            "category":"Retail",
            "subcategory":"Car Wash",
            "type":"Services"
        }
    ],
    "sg:phone":"+32 2 358 32 39",
    "sg:postcode":"1640",
    "sg:province":"Vlaams-Brabant",
    "sg:tags":[
        "automobile",
        "washing",
        "-",
        "truck"
    ],
    "wof:name":"Maral",
    "wof:placetype":"venue"
},
  "geometry": {"coordinates":[4.3943958282,50.7413482666],"type":"Point"}
}