{
  "type": "Feature",
  "properties": {
    "addr:full":"Torhoutsesteenweg 171-173 Oostende West-Vlaanderen 8400",
    "addr:housenumber":"171-173",
    "addr:postcode":"8400",
    "addr:street":"Torhoutsesteenweg",
    "iso:country":"BE",
    "sg:address":"Torhoutsesteenweg 171-173",
    "sg:city":"Oostende",
    "sg:classifiers":[
        {
            "category":"Home & Garden",
            "subcategory":"Household Appliances",
            "type":"Retail Goods"
        }
    ],
    "sg:phone":"+32 59 70 41 19",
    "sg:postcode":"8400",
    "sg:province":"West-Vlaanderen",
    "sg:tags":[
        "repair",
        "mainten",
        "-",
        "electric"
    ],
    "wof:name":"Steven Comfort Bvba",
    "wof:placetype":"venue"
},
  "geometry": {"coordinates":[2.9078650475,51.2206344604],"type":"Point"}
}