{
  "type": "Feature",
  "properties": {
    "iso:country":"BE",
    "sg:address":"Rue Docteur Romedenne 72",
    "sg:city":"Sambreville",
    "sg:orig_category":"Belastingconsulenten Diverse juridische dienstverlening",
    "sg:phone":"+32 71 77 74 04",
    "sg:postcode":"5060",
    "sg:province":"Namur",
    "wof:name":"Stefano Di Bono",
    "wof:placetype":"venue"
},
  "geometry": {"coordinates":[4.6285200119,50.4448738098],"type":"Point"}
}