{
  "type": "Feature",
  "properties": {
    "addr:full":"Stationsstraat 57 Maldegem Oost-Vlaanderen 9990",
    "addr:housenumber":"57",
    "addr:postcode":"9990",
    "addr:street":"Stationsstraat",
    "iso:country":"BE",
    "sg:address":"Stationsstraat 57",
    "sg:city":"Maldegem",
    "sg:orig_category":"Banken and kredietinstellingen Belastingconsulenten Boekhouders Diverse juridische dienstverlening V",
    "sg:phone":"+32 50 71 13 17",
    "sg:postcode":"9990",
    "sg:province":"Oost-Vlaanderen",
    "wof:name":"Beroepskrediet",
    "wof:placetype":"venue"
},
  "geometry": {"coordinates":[3.4491729736,51.2059059143],"type":"Point"}
}