{
  "type": "Feature",
  "properties": {
    "iso:country":"BE",
    "sg:address":"Wareslagestraat 43",
    "sg:city":"Waasmunster",
    "sg:orig_category":"Artiesten and kunstenaars",
    "sg:phone":"+32 52 46 17 25",
    "sg:postcode":"9250",
    "sg:province":"Oost-Vlaanderen",
    "wof:name":"Jerome Mets",
    "wof:placetype":"venue"
},
  "geometry": {"coordinates":[4.0972571373,51.1115646362],"type":"Point"}
}