{
  "type": "Feature",
  "properties": {
    "addr:full":"Rue Hautbiermont 40 Walhain (nil-saint-vincent-saint-martin) Brabant Wallon 1457",
    "addr:housenumber":"40",
    "addr:postcode":"1457",
    "addr:street":"Rue Hautbiermont;Wallon",
    "iso:country":"BE",
    "sg:address":"Rue Hautbiermont 40",
    "sg:city":"Walhain (nil-saint-vincent-saint-martin)",
    "sg:orig_category":"Non-Classified Establishments",
    "sg:phone":"+32 10 65 12 32",
    "sg:postcode":"1457",
    "sg:province":"Brabant Wallon",
    "wof:name":"Dairy Based Food Ingredients",
    "wof:placetype":"venue"
},
  "geometry": {"coordinates":[4.6597061157,50.6362113953],"type":"Point"}
}