{
  "type": "Feature",
  "properties": {
    "iso:country":"BE",
    "sg:address":"Meensesteenweg 304",
    "sg:city":"Roeselare",
    "sg:orig_category":"RESTAURANTS: SALLES DE CONF\u00c9RENCES AND DE R\u00c9CEPTIONS. ALIMENTATION SP\u00c9CIALIS\u00c9E. CATERING AND ORGANIS",
    "sg:phone":"+32 51 22 72 09",
    "sg:postcode":"8800",
    "sg:province":"West-Vlaanderen",
    "wof:name":"De Rijselpoort",
    "wof:placetype":"venue"
},
  "geometry": {"coordinates":[3.119492054,50.9310760498],"type":"Point"}
}