{
  "type": "Feature",
  "properties": {
    "addr:full":"Rue Mal Foch 23 Fl\u00e9malle Li\u00e8ge 4400",
    "addr:housenumber":"23",
    "addr:postcode":"4400",
    "addr:street":"Rue Mal Foch",
    "iso:country":"BE",
    "sg:address":"Rue Mal Foch 23",
    "sg:city":"Fl\u00e9malle",
    "sg:classifiers":[
        {
            "category":"Transit Center",
            "subcategory":"Freight",
            "type":"Transportation"
        }
    ],
    "sg:phone":"+32 4 231 35 35",
    "sg:postcode":"4400",
    "sg:province":"Li\u00e8ge",
    "sg:tags":[
        "metallurgy",
        "pipe",
        "metalworking",
        "sheet"
    ],
    "wof:name":"Tubemeuse-industries S.a.",
    "wof:placetype":"venue"
},
  "geometry": {"coordinates":[5.4576430321,50.5693130493],"type":"Point"}
}