{
  "type": "Feature",
  "properties": {
    "addr:full":"Senthout 21 Duffel Antwerpen 2570",
    "addr:housenumber":"21",
    "addr:postcode":"2570",
    "addr:street":"Senthout",
    "iso:country":"BE",
    "sg:address":"Senthout 21",
    "sg:city":"Duffel",
    "sg:orig_category":"Installation de menuiserie en bois and plastique",
    "sg:phone":"+32 15 31 17 37",
    "sg:postcode":"2570",
    "sg:province":"Antwerpen",
    "wof:name":"Modelmakerij Thijs",
    "wof:placetype":"venue"
},
  "geometry": {"coordinates":[4.4996628761,51.1082725525],"type":"Point"}
}