{
  "type": "Feature",
  "properties": {
    "addr:full":"Wiekevorstsesteenweg 38 Heist-op-den-berg Antwerpen 2220",
    "addr:housenumber":"38",
    "addr:postcode":"2220",
    "addr:street":"Wiekevorstsesteenweg",
    "iso:country":"BE",
    "sg:address":"Wiekevorstsesteenweg 38",
    "sg:city":"Heist-op-den-berg",
    "sg:classifiers":[
        {
            "category":"Farming",
            "subcategory":"Fish & Marine Products",
            "type":"Manufacturing & Wholesale Goods"
        }
    ],
    "sg:phone":"+32 15 22 24 25",
    "sg:postcode":"2220",
    "sg:province":"Antwerpen",
    "sg:tags":[
        "animal",
        "food",
        "related",
        "grain",
        "cereal",
        "breeding"
    ],
    "wof:name":"Impextraco Nv",
    "wof:placetype":"venue"
},
  "geometry": {"coordinates":[4.7785468102,51.0863952637],"type":"Point"}
}