{
  "type": "Feature",
  "properties": {
    "iso:country":"BE",
    "sg:address":"Rue De La Montagne 51",
    "sg:city":"Charleroi",
    "sg:orig_category":"Mobistar Centres Telecommunicatieapparaten",
    "sg:phone":"+32 71 30 96 86",
    "sg:postcode":"6000",
    "sg:province":"Hainaut",
    "wof:name":"Mobistar Center Brison",
    "wof:placetype":"venue"
},
  "geometry": {"coordinates":[4.4430799484,50.4102401733],"type":"Point"}
}