{
  "type": "Feature",
  "properties": {
    "iso:country":"BE",
    "sg:address":"Groeningenlei 1",
    "sg:city":"Aartselaar",
    "sg:orig_category":"Beheer onroerend goed Immobili\u00ebnkantoren",
    "sg:phone":"+32 3 887 95 00",
    "sg:postcode":"2630",
    "sg:province":"Antwerpen",
    "wof:name":"Medical & Profess. Build",
    "wof:placetype":"venue"
},
  "geometry": {"coordinates":[4.4033207893,51.1384963989],"type":"Point"}
}