{
  "type": "Feature",
  "properties": {
    "addr:full":"Geulincxstraat 27 Antwerpen Antwerpen 2060",
    "addr:housenumber":"27",
    "addr:postcode":"2060",
    "addr:street":"Geulincxstraat",
    "iso:country":"BE",
    "sg:address":"Geulincxstraat 27",
    "sg:city":"Antwerpen",
    "sg:classifiers":[
        {
            "category":"Tea Room",
            "subcategory":"None",
            "type":"Food & Drink"
        }
    ],
    "sg:phone":"+32 3 226 14 97",
    "sg:postcode":"2060",
    "sg:province":"Antwerpen",
    "wof:name":"Overkaent (den)",
    "wof:placetype":"venue"
},
  "geometry": {"coordinates":[4.4159479141,51.2272453308],"type":"Point"}
}