{
  "type": "Feature",
  "properties": {
    "addr:full":"Dweirsweg 1 Sint-laureins Oost-Vlaanderen 9980",
    "addr:housenumber":"1",
    "addr:postcode":"9980",
    "addr:street":"Dweirsweg",
    "iso:country":"BE",
    "sg:address":"Dweirsweg 1",
    "sg:city":"Sint-laureins",
    "sg:orig_category":"Slagers",
    "sg:phone":"+32 9 377 02 95",
    "sg:postcode":"9980",
    "sg:province":"Oost-Vlaanderen",
    "wof:name":"William Van Kerrebroeck",
    "wof:placetype":"venue"
},
  "geometry": {"coordinates":[3.544770956,51.222454071],"type":"Point"}
}