{
  "type": "Feature",
  "properties": {
    "addr:full":"Rue Quoesimodes 2 Amay Li\u00e8ge 4540",
    "addr:housenumber":"2",
    "addr:postcode":"4540",
    "addr:street":"Rue Quoesimodes",
    "iso:country":"BE",
    "sg:address":"Rue Quoesimodes 2",
    "sg:city":"Amay",
    "sg:orig_category":"Paramedische behandelingen",
    "sg:phone":"+32 85 31 75 34",
    "sg:postcode":"4540",
    "sg:province":"Li\u00e8ge",
    "wof:name":"F. Gilles",
    "wof:placetype":"venue"
},
  "geometry": {"coordinates":[5.3120732307,50.5452461243],"type":"Point"}
}