{
  "type": "Feature",
  "properties": {
    "addr:full":"Hoogstraat 11 Oudenaarde Oost-Vlaanderen 9700",
    "addr:housenumber":"11",
    "addr:postcode":"9700",
    "addr:street":"Hoogstraat",
    "iso:country":"BE",
    "sg:address":"Hoogstraat 11",
    "sg:city":"Oudenaarde",
    "sg:classifiers":[
        {
            "category":"Shopping",
            "subcategory":"Clothing, Apparel, & Fashions",
            "type":"Retail Goods"
        }
    ],
    "sg:phone":"+32 55 30 50 64",
    "sg:postcode":"9700",
    "sg:province":"Oost-Vlaanderen",
    "sg:tags":[
        "lady",
        "clothing",
        "-"
    ],
    "wof:name":"Pauline",
    "wof:placetype":"venue"
},
  "geometry": {"coordinates":[3.6034231186,50.844127655],"type":"Point"}
}