{
  "type": "Feature",
  "properties": {
    "iso:country":"BE",
    "sg:address":"Bijkhoeveln 2",
    "sg:city":"Wijnegem",
    "sg:classifiers":[
        {
            "category":"Professional",
            "subcategory":"Engineering",
            "type":"Services"
        }
    ],
    "sg:phone":"+32 3 326 33 33",
    "sg:postcode":"2110",
    "sg:province":"Antwerpen",
    "sg:tags":[
        "machine",
        "-",
        "mechanical"
    ],
    "wof:name":"Schotmans & Dedecker (desco) Nv",
    "wof:placetype":"venue"
},
  "geometry": {"coordinates":[4.4919347763,51.2352294922],"type":"Point"}
}