{
  "type": "Feature",
  "properties": {
    "addr:full":"Kolonel Begaultlaan 3 Leuven (wilsele) Vlaams-Brabant 3012",
    "addr:housenumber":"3",
    "addr:postcode":"3012",
    "addr:street":"Kolonel Begaultlaan",
    "iso:country":"BE",
    "sg:address":"Kolonel Begaultlaan 3",
    "sg:city":"Leuven (wilsele)",
    "sg:classifiers":[
        {
            "category":"Government",
            "subcategory":"Post Office",
            "type":"Public Place"
        }
    ],
    "sg:phone":"+32 16 29 46 39",
    "sg:postcode":"3012",
    "sg:province":"Vlaams-Brabant",
    "sg:tags":[
        "parkinggarages",
        "access",
        "-",
        "installation"
    ],
    "wof:name":"City Parking",
    "wof:placetype":"venue"
},
  "geometry": {"coordinates":[4.7059111595,50.8886985779],"type":"Point"}
}