{
  "type": "Feature",
  "properties": {
    "iso:country":"BE",
    "sg:address":"Pauwstraat 107",
    "sg:city":"Beveren",
    "sg:orig_category":"Architectes",
    "sg:phone":"+32 3 775 36 92",
    "sg:postcode":"9120",
    "sg:province":"Oost-Vlaanderen",
    "wof:name":"Steven Goossens",
    "wof:placetype":"venue"
},
  "geometry": {"coordinates":[4.295882225,51.2151489258],"type":"Point"}
}