{
  "type": "Feature",
  "properties": {
    "iso:country":"BE",
    "sg:address":"Nieuwe Boekhoutestraat 64",
    "sg:city":"Assenede (bassevelde)",
    "sg:classifiers":[
        {
            "category":"Parking",
            "subcategory":"Lot",
            "type":"Transportation"
        }
    ],
    "sg:phone":"+32 9 373 50 41",
    "sg:postcode":"9968",
    "sg:province":"Oost-Vlaanderen",
    "sg:tags":[
        "parking-places",
        "laying-out"
    ],
    "wof:name":"Chalmet H",
    "wof:placetype":"venue"
},
  "geometry": {"coordinates":[3.6900401115,51.2343482971],"type":"Point"}
}