{
  "type": "Feature",
  "properties": {
    "addr:full":"Herdersstraat 71 Roeselare West-Vlaanderen 8800",
    "addr:housenumber":"71",
    "addr:postcode":"8800",
    "addr:street":"Herdersstraat",
    "iso:country":"BE",
    "sg:address":"Herdersstraat 71",
    "sg:city":"Roeselare",
    "sg:classifiers":[
        {
            "category":"Building & Trades",
            "subcategory":"Construction",
            "type":"Services"
        }
    ],
    "sg:phone":"+32 51 20 76 32",
    "sg:postcode":"8800",
    "sg:province":"West-Vlaanderen",
    "sg:tags":[
        "carpenter"
    ],
    "wof:name":"Vandecappelle W",
    "wof:placetype":"venue"
},
  "geometry": {"coordinates":[3.143611908,50.9400062561],"type":"Point"}
}