{
  "type": "Feature",
  "properties": {
    "iso:country":"BE",
    "sg:address":"Peperstraat 76c",
    "sg:city":"Wetteren",
    "sg:orig_category":"Fitnesscentra",
    "sg:phone":"+32 9 369 91 93",
    "sg:postcode":"9230",
    "sg:province":"Oost-Vlaanderen",
    "wof:name":"Peppers Gym",
    "wof:placetype":"venue"
},
  "geometry": {"coordinates":[3.8736929893,51.0080375671],"type":"Point"}
}