{
  "type": "Feature",
  "properties": {
    "addr:full":"Omstraat 48bb Kortessem Limburg 3720",
    "addr:housenumber":"48bb",
    "addr:postcode":"3720",
    "addr:street":"Omstraat",
    "iso:country":"BE",
    "sg:address":"Omstraat 48bb",
    "sg:city":"Kortessem",
    "sg:orig_category":"Experts-comptables",
    "sg:phone":"+32 11 37 52 51",
    "sg:postcode":"3720",
    "sg:province":"Limburg",
    "wof:name":"Paul Nelissen",
    "wof:placetype":"venue"
},
  "geometry": {"coordinates":[5.3825359344,50.8626823425],"type":"Point"}
}