{
  "type": "Feature",
  "properties": {
    "addr:full":"Provincialebaan 80 Buggenhout Oost-Vlaanderen 9255",
    "addr:housenumber":"80",
    "addr:postcode":"9255",
    "addr:street":"Provincialebaan",
    "iso:country":"BE",
    "sg:address":"Provincialebaan 80",
    "sg:city":"Buggenhout",
    "sg:orig_category":"Disquaires",
    "sg:phone":"+32 52 33 71 92",
    "sg:postcode":"9255",
    "sg:province":"Oost-Vlaanderen",
    "wof:name":"Zerouali Jaouad",
    "wof:placetype":"venue"
},
  "geometry": {"coordinates":[4.1861429214,51.02967453],"type":"Point"}
}