{
  "type": "Feature",
  "properties": {
    "addr:full":"Ildefonse Vandammestraat 5 Hoeilaart Vlaams-Brabant 1560",
    "addr:housenumber":"5",
    "addr:postcode":"1560",
    "addr:street":"Ildefonse Vandammestraat",
    "iso:country":"BE",
    "sg:address":"Ildefonse Vandammestraat 5",
    "sg:city":"Hoeilaart",
    "sg:classifiers":[
        {
            "category":"Professional",
            "subcategory":"Computer Services",
            "type":"Services"
        }
    ],
    "sg:phone":"+32 2 658 20 11",
    "sg:postcode":"1560",
    "sg:province":"Vlaams-Brabant",
    "sg:tags":[
        "-",
        "processing",
        "data",
        "software"
    ],
    "wof:name":"Spacebel",
    "wof:placetype":"venue"
},
  "geometry": {"coordinates":[4.4488220215,50.7656822205],"type":"Point"}
}