{
  "type": "Feature",
  "properties": {
    "addr:full":"H. Dom. Saviolaan 6 Dilbeek Vlaams-Brabant 1700",
    "addr:housenumber":"6",
    "addr:postcode":"1700",
    "addr:street":"Saviolaan",
    "iso:country":"BE",
    "sg:address":"H. Dom. Saviolaan 6",
    "sg:city":"Dilbeek",
    "sg:orig_category":"Pain, p\u00e2tisseries and confiseries",
    "sg:phone":"+32 2 466 36 15",
    "sg:postcode":"1700",
    "sg:province":"Vlaams-Brabant",
    "wof:name":"Locus-josse",
    "wof:placetype":"venue"
},
  "geometry": {"coordinates":[4.2445168495,50.8623352051],"type":"Point"}
}