{
  "type": "Feature",
  "properties": {
    "addr:full":"Rue Du Poirier 15 Ecaussinnes Hainaut 7191",
    "addr:housenumber":"15",
    "addr:postcode":"7191",
    "addr:street":"Rue Du Poirier;Hainaut",
    "iso:country":"BE",
    "sg:address":"Rue Du Poirier 15",
    "sg:city":"Ecaussinnes",
    "sg:classifiers":[
        {
            "category":"Arena",
            "subcategory":"Sports Club",
            "type":"Entertainment"
        }
    ],
    "sg:phone":"+32 67 44 24 68",
    "sg:postcode":"7191",
    "sg:province":"Hainaut",
    "sg:tags":[
        "de"
    ],
    "wof:name":"Odenat",
    "wof:placetype":"venue"
},
  "geometry": {"coordinates":[4.2085361481,50.5837059021],"type":"Point"}
}