{
  "type": "Feature",
  "properties": {
    "addr:full":"Musschaverstraat 40 Nevele (landegem) Oost-Vlaanderen 9850",
    "addr:housenumber":"40",
    "addr:postcode":"9850",
    "addr:street":"Musschaverstraat",
    "iso:country":"BE",
    "sg:address":"Musschaverstraat 40",
    "sg:city":"Nevele (landegem)",
    "sg:classifiers":[
        {
            "category":"Building & Trades",
            "subcategory":"Landscaping Services",
            "type":"Services"
        }
    ],
    "sg:phone":"+32 9 371 95 68",
    "sg:postcode":"9850",
    "sg:province":"Oost-Vlaanderen",
    "sg:tags":[
        "-",
        "lopping",
        "work",
        "tree",
        "felling"
    ],
    "wof:name":"Bisschop Christophe",
    "wof:placetype":"venue"
},
  "geometry": {"coordinates":[3.6070299149,51.06300354],"type":"Point"}
}