{
  "type": "Feature",
  "properties": {
    "iso:country":"BE",
    "sg:address":"Rue Emmanuel Lutte 17",
    "sg:city":"Genappe",
    "sg:orig_category":"Banken and kredietinstellingen",
    "sg:phone":"+32 67 79 40 00",
    "sg:postcode":"1470",
    "sg:province":"Brabant Wallon",
    "wof:name":"Bbl",
    "wof:placetype":"venue"
},
  "geometry": {"coordinates":[4.4511780739,50.611530304],"type":"Point"}
}