{
  "type": "Feature",
  "properties": {
    "addr:full":"Ten Bosse 1 Vloesberg/flobecq Hainaut 7880",
    "addr:housenumber":"1",
    "addr:postcode":"7880",
    "addr:street":"Ten Bosse",
    "iso:country":"BE",
    "sg:address":"Ten Bosse 1",
    "sg:city":"Vloesberg/flobecq",
    "sg:orig_category":"Schoonheidssalons",
    "sg:phone":"+32 68 44 71 30",
    "sg:postcode":"7880",
    "sg:province":"Hainaut",
    "wof:name":"Anne Desourmeaux",
    "wof:placetype":"venue"
},
  "geometry": {"coordinates":[3.7384300232,50.7368011475],"type":"Point"}
}