{
  "type": "Feature",
  "properties": {
    "iso:country":"BE",
    "sg:address":"Leeuwenstraat 8",
    "sg:city":"Brasschaat",
    "sg:orig_category":"HUISBRANDOLIE",
    "sg:phone":"+32 3 651 85 41",
    "sg:postcode":"2930",
    "sg:province":"Antwerpen",
    "wof:name":"Aernouts",
    "wof:placetype":"venue"
},
  "geometry": {"coordinates":[4.4823307991,51.3024101257],"type":"Point"}
}