{
  "type": "Feature",
  "properties": {
    "addr:full":"Aachener Strasse 74 Eupen/eupen Li\u00e8ge 4700",
    "addr:housenumber":"74",
    "addr:postcode":"4700",
    "addr:street":"Aachener Strasse",
    "iso:country":"BE",
    "sg:address":"Aachener Strasse 74",
    "sg:city":"Eupen/eupen",
    "sg:orig_category":"Landmeters",
    "sg:phone":"+32 87 74 45 09",
    "sg:postcode":"4700",
    "sg:province":"Li\u00e8ge",
    "wof:name":"Jean-marie Jacobs",
    "wof:placetype":"venue"
},
  "geometry": {"coordinates":[6.1348800659,50.5989990234],"type":"Point"}
}