{
  "type": "Feature",
  "properties": {
    "iso:country":"BE",
    "sg:address":"Rempart Des J\u00e9suites 55",
    "sg:city":"Marche-en-famenne",
    "sg:classifiers":[
        {
            "category":"Health Services",
            "subcategory":"Doctor",
            "type":"Services"
        }
    ],
    "sg:phone":"+32 84 31 19 06",
    "sg:postcode":"6900",
    "sg:province":"Luxembourg",
    "sg:tags":[
        "medicinephysicians",
        "surgeon"
    ],
    "wof:name":"Gilles J",
    "wof:placetype":"venue"
},
  "geometry": {"coordinates":[5.3460841179,50.2280921936],"type":"Point"}
}