{
  "type": "Feature",
  "properties": {
    "iso:country":"BE",
    "sg:address":"Vontstraat 53",
    "sg:city":"Oudenaarde",
    "sg:classifiers":[
        {
            "category":"Education",
            "subcategory":"School",
            "type":"Public Place"
        }
    ],
    "sg:phone":"+32 55 30 18 85",
    "sg:postcode":"9700",
    "sg:province":"Oost-Vlaanderen",
    "sg:tags":[
        "primary"
    ],
    "wof:name":"Katholiek Onderwijs",
    "wof:placetype":"venue"
},
  "geometry": {"coordinates":[3.6056079865,50.8309059143],"type":"Point"}
}