{
  "type": "Feature",
  "properties": {
    "iso:country":"BE",
    "sg:address":"Avenue De La Gare 85",
    "sg:city":"Hotton",
    "sg:classifiers":[
        {
            "category":"Shopping",
            "subcategory":"Florist",
            "type":"Retail Goods"
        }
    ],
    "sg:phone":"+32 84 46 73 32",
    "sg:postcode":"6990",
    "sg:province":"Luxembourg",
    "wof:name":"Mille Fleurs (aux)",
    "wof:placetype":"venue"
},
  "geometry": {"coordinates":[5.439209938,50.2756614685],"type":"Point"}
}