{
  "type": "Feature",
  "properties": {
    "addr:full":"Rue Du Centre 50 Yvoir Namur 5530",
    "addr:housenumber":"50",
    "addr:postcode":"5530",
    "addr:street":"Rue Du Centre",
    "iso:country":"BE",
    "sg:address":"Rue Du Centre 50",
    "sg:city":"Yvoir",
    "sg:orig_category":"Herstellingen and onderhoud van auto's",
    "sg:phone":"+32 81 41 20 85",
    "sg:postcode":"5530",
    "sg:province":"Namur",
    "wof:name":"Carrosserie Champenois B.",
    "wof:placetype":"venue"
},
  "geometry": {"coordinates":[4.9036140442,50.3529052734],"type":"Point"}
}