{
  "type": "Feature",
  "properties": {
    "iso:country":"BE",
    "sg:address":"Genkerbaan 20",
    "sg:city":"Zonhoven",
    "sg:classifiers":[
        {
            "category":"Real Estate",
            "subcategory":"Architect",
            "type":"Services"
        }
    ],
    "sg:phone":"+32 11 81 73 73",
    "sg:postcode":"3520",
    "sg:province":"Limburg",
    "wof:name":"Jacobs J P",
    "wof:placetype":"venue"
},
  "geometry": {"coordinates":[5.3706560135,50.9910354614],"type":"Point"}
}