{
  "type": "Feature",
  "properties": {
    "iso:country":"BE",
    "sg:address":"Gentsesteenweg 622",
    "sg:city":"Waregem",
    "sg:orig_category":"Metalen and ertsen Gh",
    "sg:phone":"+32 56 60 81 30",
    "sg:postcode":"8793",
    "sg:province":"West-Vlaanderen",
    "wof:name":"D'hont P.",
    "wof:placetype":"venue"
},
  "geometry": {"coordinates":[3.4139590263,50.9051780701],"type":"Point"}
}