{
  "type": "Feature",
  "properties": {
    "addr:full":"Vrijheid 56 Bus1 Arendonk Antwerpen 2370",
    "addr:housenumber":"56 bus1",
    "addr:postcode":"2370",
    "addr:street":"Vrijheid",
    "iso:country":"BE",
    "sg:address":"Vrijheid 56 Bus1",
    "sg:city":"Arendonk",
    "sg:orig_category":"Biblioth\u00e8ques and archives publiques",
    "sg:phone":"+32 14 67 16 14",
    "sg:postcode":"2370",
    "sg:province":"Antwerpen",
    "wof:name":"Openbare Bibliotheek",
    "wof:placetype":"venue"
},
  "geometry": {"coordinates":[5.086771965,51.3202438354],"type":"Point"}
}