{
  "type": "Feature",
  "properties": {
    "iso:country":"BE",
    "sg:address":"Stapelstraat 31",
    "sg:city":"Sint-truiden",
    "sg:classifiers":[
        {
            "category":"Shopping",
            "subcategory":"Shoes",
            "type":"Retail Goods"
        }
    ],
    "sg:phone":"+32 11 68 24 34",
    "sg:postcode":"3800",
    "sg:province":"Limburg",
    "sg:tags":[
        "slipper",
        "-"
    ],
    "wof:name":"Sumor",
    "wof:placetype":"venue"
},
  "geometry": {"coordinates":[5.1817722321,50.8156433105],"type":"Point"}
}