{
  "type": "Feature",
  "properties": {
    "iso:country":"BE",
    "sg:address":"Antwerpsedreef 90",
    "sg:city":"Zoersel",
    "sg:classifiers":[
        {
            "category":"Manufacturing",
            "subcategory":"Metals",
            "type":"Manufacturing & Wholesale Goods"
        }
    ],
    "sg:phone":"+32 3 383 36 34",
    "sg:postcode":"2980",
    "sg:province":"Antwerpen",
    "sg:tags":[
        "ironwork"
    ],
    "wof:name":"Boeckx R",
    "wof:placetype":"venue"
},
  "geometry": {"coordinates":[4.6660108566,51.2643241882],"type":"Point"}
}