{
  "type": "Feature",
  "properties": {
    "addr:full":"Broekstraat 2-501 Oudenaarde Oost-Vlaanderen 9700",
    "addr:postcode":"2-501;9700",
    "addr:street":"Broekstraat",
    "iso:country":"BE",
    "sg:address":"Broekstraat 2-501",
    "sg:city":"Oudenaarde",
    "sg:classifiers":[
        {
            "category":"Professional",
            "subcategory":"Computer Services",
            "type":"Services"
        }
    ],
    "sg:phone":"+32 485 36 74 01",
    "sg:postcode":"9700",
    "sg:province":"Oost-Vlaanderen",
    "sg:tags":[
        "-",
        "processing",
        "data"
    ],
    "wof:name":"Marathon Computers",
    "wof:placetype":"venue"
},
  "geometry": {"coordinates":[3.611989975,50.8585891724],"type":"Point"}
}