{
  "type": "Feature",
  "properties": {
    "addr:full":"Chauss\u00e9e De Huy 212c Chaumont-gistoux Brabant Wallon 1325",
    "addr:housenumber":"212c",
    "addr:postcode":"1325",
    "addr:street":"Chausse\u0301E De Huy",
    "iso:country":"BE",
    "sg:address":"Chauss\u00e9e De Huy 212c",
    "sg:city":"Chaumont-gistoux",
    "sg:classifiers":[
        {
            "category":"Shopping",
            "subcategory":"Florist",
            "type":"Retail Goods"
        }
    ],
    "sg:phone":"+32 10 84 66 53",
    "sg:postcode":"1325",
    "sg:province":"Brabant Wallon",
    "wof:name":"Hellebore",
    "wof:placetype":"venue"
},
  "geometry": {"coordinates":[4.6932210922,50.6852874756],"type":"Point"}
}