{
  "type": "Feature",
  "properties": {
    "iso:country":"BE",
    "sg:address":"21",
    "sg:city":"Hofeinde 2350 Vosselaar",
    "sg:classifiers":[
        {
            "category":"Shopping",
            "type":"Retail Goods"
        }
    ],
    "sg:phone":"+32 14 61 12 60",
    "sg:postcode":"21",
    "sg:tags":[
        "metallurgy",
        "finished",
        "-",
        "metalworking",
        "metallic"
    ],
    "wof:name":"Huis Cuylaerts Bvba",
    "wof:placetype":"venue"
},
  "geometry": {"coordinates":[4.8742051125,51.3262786865],"type":"Point"}
}