{
  "type": "Feature",
  "properties": {
    "iso:country":"BE",
    "sg:address":"Chauss\u00e9e De Waterloo 843",
    "sg:city":"Bruxelles (uccle)",
    "sg:classifiers":[
        {
            "category":"Utilities",
            "subcategory":"Telephone",
            "type":"Services"
        }
    ],
    "sg:phone":"+32 2 373 98 98",
    "sg:postcode":"1180",
    "sg:province":"Bruxelles-Capitale",
    "sg:tags":[
        "recording",
        "machine",
        "answering"
    ],
    "wof:name":"Nipco",
    "wof:placetype":"venue"
},
  "geometry": {"coordinates":[4.3692688942,50.8096389771],"type":"Point"}
}