{
  "type": "Feature",
  "properties": {
    "addr:full":"Stationsstraat 101 Sint-niklaas Oost-Vlaanderen 9100",
    "addr:housenumber":"101",
    "addr:postcode":"9100",
    "addr:street":"Stationsstraat",
    "iso:country":"BE",
    "sg:address":"Stationsstraat 101",
    "sg:city":"Sint-niklaas",
    "sg:orig_category":"Herstelling horloges and juwelen",
    "sg:phone":"+32 3 777 02 93",
    "sg:postcode":"9100",
    "sg:province":"Oost-Vlaanderen",
    "wof:name":"Saxon",
    "wof:placetype":"venue"
},
  "geometry": {"coordinates":[4.1424689293,51.1689338684],"type":"Point"}
}