{
  "type": "Feature",
  "properties": {
    "iso:country":"BE",
    "sg:address":"Rue Bois Des Fosses 13-1",
    "sg:city":"Orp-jauche (enines)",
    "sg:classifiers":[
        {
            "category":"Real Estate",
            "subcategory":"Architect",
            "type":"Services"
        }
    ],
    "sg:phone":"+32 19 63 73 67",
    "sg:postcode":"1350",
    "sg:province":"Brabant Wallon",
    "wof:name":"Nelis B",
    "wof:placetype":"venue"
},
  "geometry": {"coordinates":[4.9269108772,50.68907547],"type":"Point"}
}