{
  "type": "Feature",
  "properties": {
    "addr:full":"De Donckerstraat 7 Gistel West-Vlaanderen 8470",
    "addr:housenumber":"7",
    "addr:postcode":"8470",
    "addr:street":"De Donckerstraat",
    "iso:country":"BE",
    "sg:address":"De Donckerstraat 7",
    "sg:city":"Gistel",
    "sg:orig_category":"Alimentation sp\u00e9cialis\u00e9e",
    "sg:phone":"+32 59 27 42 99",
    "sg:postcode":"8470",
    "sg:province":"West-Vlaanderen",
    "wof:name":"Manna",
    "wof:placetype":"venue"
},
  "geometry": {"coordinates":[2.9629991055,51.1551780701],"type":"Point"}
}