{
  "type": "Feature",
  "properties": {
    "addr:full":"Tongersesteenweg 191 Borgloon Limburg 3840",
    "addr:housenumber":"191",
    "addr:postcode":"3840",
    "addr:street":"Tongersesteenweg",
    "iso:country":"BE",
    "sg:address":"Tongersesteenweg 191",
    "sg:city":"Borgloon",
    "sg:orig_category":"Plomberie, chauffage and installations sanitaires",
    "sg:phone":"+32 12 74 66 01",
    "sg:postcode":"3840",
    "sg:province":"Limburg",
    "wof:name":"Aaste Plus",
    "wof:placetype":"venue"
},
  "geometry": {"coordinates":[5.3623399734,50.7977905273],"type":"Point"}
}