{
  "type": "Feature",
  "properties": {
    "iso:country":"BE",
    "sg:address":"Rue Piconette 12",
    "sg:city":"Ciney",
    "sg:orig_category":"Herstelling leer and schoeisel",
    "sg:phone":"+32 83 21 50 86",
    "sg:postcode":"5590",
    "sg:province":"Namur",
    "wof:name":"A. Ronval",
    "wof:placetype":"venue"
},
  "geometry": {"coordinates":[5.1035118103,50.2977867126],"type":"Point"}
}