{
  "type": "Feature",
  "properties": {
    "iso:country":"BE",
    "sg:address":"Luxemburger Strasse 85a",
    "sg:city":"Sankt Vith",
    "sg:classifiers":[
        {
            "category":"Retail",
            "subcategory":"Auto Repair",
            "type":"Services"
        }
    ],
    "sg:phone":"+32 80 22 62 70",
    "sg:postcode":"4780",
    "sg:province":"Li\u00e8ge",
    "sg:tags":[
        "breakdown",
        "automobile",
        "-",
        "recovery"
    ],
    "wof:name":"Garage-d\u00e9pannage E42",
    "wof:placetype":"venue"
},
  "geometry": {"coordinates":[6.115696907,50.2696876526],"type":"Point"}
}