{
  "type": "Feature",
  "properties": {
    "iso:country":"BE",
    "sg:address":"Bredestraat 56",
    "sg:city":"Ronse/renaix",
    "sg:orig_category":"Woningbouw",
    "sg:phone":"+32 55 30 01 31",
    "sg:postcode":"9600",
    "sg:province":"Oost-Vlaanderen",
    "wof:name":"C. De Langhe",
    "wof:placetype":"venue"
},
  "geometry": {"coordinates":[3.6103849411,50.7474708557],"type":"Point"}
}