{
  "type": "Feature",
  "properties": {
    "iso:country":"BE",
    "sg:address":"Braambeslei 22",
    "sg:city":"Kapellen",
    "sg:orig_category":"D\u00e9corateurs d'int\u00e9rieur. Eclairage et \u00e9quipements du foyer",
    "sg:phone":"+32 3 666 21 61",
    "sg:postcode":"2950",
    "sg:province":"Antwerpen",
    "wof:name":"Gert Willemen",
    "wof:placetype":"venue"
},
  "geometry": {"coordinates":[4.4558210373,51.355266571],"type":"Point"}
}