{
  "type": "Feature",
  "properties": {
    "iso:country":"BE",
    "sg:address":"Roeselarebaan 2",
    "sg:city":"Lichtervelde",
    "sg:orig_category":"Non-foodwinkels",
    "sg:phone":"+32 51 72 47 80",
    "sg:postcode":"8810",
    "sg:province":"West-Vlaanderen",
    "wof:name":"Batjeshoek",
    "wof:placetype":"venue"
},
  "geometry": {"coordinates":[3.1119730473,51.0232429504],"type":"Point"}
}