{
  "type": "Feature",
  "properties": {
    "addr:full":"Avenue Daniel Boon 71 Bruxelles (auderghem) Bruxelles-Capitale 1160",
    "addr:housenumber":"71",
    "addr:postcode":"1160",
    "addr:street":"Avenue Daniel Boon",
    "iso:country":"BE",
    "sg:address":"Avenue Daniel Boon 71",
    "sg:city":"Bruxelles (auderghem)",
    "sg:classifiers":[
        {
            "category":"Retail",
            "subcategory":"Event Space",
            "type":"Services"
        }
    ],
    "sg:phone":"+32 70 23 36 73",
    "sg:postcode":"1160",
    "sg:province":"Bruxelles-Capitale",
    "sg:tags":[
        "organisation"
    ],
    "wof:name":"Mosaic Sprl",
    "wof:placetype":"venue"
},
  "geometry": {"coordinates":[4.4310998917,50.8091201782],"type":"Point"}
}