{
  "type": "Feature",
  "properties": {
    "addr:full":"Bakensgoed 2 Aalter Oost-Vlaanderen 9880",
    "addr:housenumber":"2",
    "addr:postcode":"9880",
    "addr:street":"Bakensgoed",
    "iso:country":"BE",
    "sg:address":"Bakensgoed 2",
    "sg:city":"Aalter",
    "sg:orig_category":"Eleveurs de bovins. Eleveurs and marchands de porcs",
    "sg:phone":"+32 9 374 15 70",
    "sg:postcode":"9880",
    "sg:province":"Oost-Vlaanderen",
    "wof:name":"Lanckriet A. & Al.",
    "wof:placetype":"venue"
},
  "geometry": {"coordinates":[3.3514459133,51.1001968384],"type":"Point"}
}