{
  "type": "Feature",
  "properties": {
    "iso:country":"BE",
    "sg:address":"Rue De La Dr\u00cave 45",
    "sg:city":"Clavier",
    "sg:orig_category":"Entretien and r\u00e9parations de voitures",
    "sg:phone":"+32 86 34 49 96",
    "sg:postcode":"4560",
    "sg:province":"Li\u00e8ge",
    "wof:name":"Luc Ronvaux",
    "wof:placetype":"venue"
},
  "geometry": {"coordinates":[5.3588900566,50.4297294617],"type":"Point"}
}