{
  "type": "Feature",
  "properties": {
    "addr:full":"Rue Coenraets 77 Saint-gilles Bruxelles-Capitale 1060",
    "addr:housenumber":"77",
    "addr:postcode":"1060",
    "addr:street":"Rue Coenraets",
    "iso:country":"BE",
    "sg:address":"Rue Coenraets 77",
    "sg:city":"Saint-gilles",
    "sg:orig_category":"Farmaceutische producten Gh",
    "sg:phone":"+32 2 535 06 30",
    "sg:postcode":"1060",
    "sg:province":"Bruxelles-Capitale",
    "wof:name":"Hegelbach M\u00c9dical",
    "wof:placetype":"venue"
},
  "geometry": {"coordinates":[4.3382868767,50.8313522339],"type":"Point"}
}