{
  "type": "Feature",
  "properties": {
    "addr:full":"Rue Africaine 108 Sint-gillis/saint-gilles Bruxelles-Capitale 1060",
    "addr:housenumber":"108",
    "addr:postcode":"1060",
    "addr:street":"Rue Africaine",
    "iso:country":"BE",
    "sg:address":"Rue Africaine 108",
    "sg:city":"Sint-gillis/saint-gilles",
    "sg:classifiers":[
        {
            "category":"Restaurant",
            "type":"Food & Drink"
        }
    ],
    "sg:phone":"+32 2 534 53 14",
    "sg:postcode":"1060",
    "sg:province":"Bruxelles-Capitale",
    "wof:name":"Le Pain Press\u00c9",
    "wof:placetype":"venue"
},
  "geometry": {"coordinates":[4.3581027985,50.8253517151],"type":"Point"}
}