{
  "type": "Feature",
  "properties": {
    "iso:country":"BE",
    "sg:address":"Rue De Limbourg 43",
    "sg:city":"Verviers",
    "sg:classifiers":[
        {
            "category":"Shopping",
            "subcategory":"Photographic Equipment",
            "type":"Retail Goods"
        }
    ],
    "sg:postcode":"4800",
    "sg:province":"Li\u00e8ge",
    "sg:tags":[
        "whol",
        "-",
        "mfg&",
        "accessory"
    ],
    "wof:name":"Pentax Benelux Bv",
    "wof:placetype":"venue"
},
  "geometry": {"coordinates":[4.7722997665,51.5907592773],"type":"Point"}
}