{
  "type": "Feature",
  "properties": {
    "iso:country":"BE",
    "sg:address":"Bouwelsesteenweg 10",
    "sg:city":"Nijlen",
    "sg:orig_category":"Poissonniers and \u00e9caillers",
    "sg:phone":"+32 3 481 84 39",
    "sg:postcode":"2560",
    "sg:province":"Antwerpen",
    "wof:name":"Het Vismijntje",
    "wof:placetype":"venue"
},
  "geometry": {"coordinates":[4.674328804,51.1624946594],"type":"Point"}
}