{
  "type": "Feature",
  "properties": {
    "iso:country":"BE",
    "sg:address":"Zur Dom\u00c4ne 37",
    "sg:city":"B\u00dctgenbach/butgenbach",
    "sg:classifiers":[
        {
            "category":"Restaurant",
            "type":"Food & Drink"
        }
    ],
    "sg:phone":"+32 80 64 28 33",
    "sg:postcode":"4750",
    "sg:province":"Li\u00e8ge",
    "sg:tags":[
        "caf\u00e9s",
        "\u00e0",
        "emporter",
        "fast"
    ],
    "wof:name":"Zum Grunen Jager Caf\u00c9",
    "wof:placetype":"venue"
},
  "geometry": {"coordinates":[6.2206501961,50.457408905],"type":"Point"}
}