{
  "type": "Feature",
  "properties": {
    "addr:full":"Rue De La Broucheterre 129 Charleroi Hainaut 6000",
    "addr:housenumber":"129",
    "addr:postcode":"6000",
    "addr:street":"Rue De La Broucheterre;Hainaut",
    "iso:country":"BE",
    "sg:address":"Rue De La Broucheterre 129",
    "sg:city":"Charleroi",
    "sg:classifiers":[
        {
            "category":"Building & Trades",
            "subcategory":"Electrical",
            "type":"Services"
        }
    ],
    "sg:phone":"+32 71 32 03 20",
    "sg:postcode":"6000",
    "sg:province":"Hainaut",
    "sg:tags":[
        "tool",
        "electric"
    ],
    "wof:name":"Metabo-gregoire & Cie",
    "wof:placetype":"venue"
},
  "geometry": {"coordinates":[4.4445171356,50.4197120667],"type":"Point"}
}