{
  "type": "Feature",
  "properties": {
    "iso:country":"BE",
    "sg:address":"Heieinde 22",
    "sg:city":"Vosselaar",
    "sg:orig_category":"Assurances. Agences immobili\u00e8res. Pr\u00eats hypoth\u00e9caires and cr\u00e9dits immobiliers. Cr\u00e9dit \u00e0 la consommat",
    "sg:phone":"+32 14 61 51 51",
    "sg:postcode":"2350",
    "sg:province":"Antwerpen",
    "wof:name":"Mannaerts",
    "wof:placetype":"venue"
},
  "geometry": {"coordinates":[4.8852729797,51.3032951355],"type":"Point"}
}