{
  "type": "Feature",
  "properties": {
    "iso:country":"BE",
    "sg:address":"Dekenijstraat 79",
    "sg:city":"Ukkel/uccle",
    "sg:orig_category":"Begrafeniswezen",
    "sg:phone":"+32 2 344 09 17",
    "sg:postcode":"1180",
    "sg:province":"Bruxelles-Capitale",
    "wof:name":"Fun\u00c9railles Melchior",
    "wof:placetype":"venue"
},
  "geometry": {"coordinates":[4.3404722214,50.8030281067],"type":"Point"}
}