{
  "type": "Feature",
  "properties": {
    "iso:country":"BE",
    "sg:address":"Chauss\u00c9e De Saint-amand 133",
    "sg:city":"Tournai",
    "sg:orig_category":"Boekhouders",
    "sg:phone":"+32 69 21 50 89",
    "sg:postcode":"7500",
    "sg:province":"Hainaut",
    "wof:name":"Eric Gardavoir",
    "wof:placetype":"venue"
},
  "geometry": {"coordinates":[3.4000060558,50.5946884155],"type":"Point"}
}