{
  "type": "Feature",
  "properties": {
    "iso:country":"BE",
    "sg:address":"Hogestraat 35",
    "sg:city":"Kortemark",
    "sg:orig_category":"HERSTELLING ELEKTRISCHE HUISHOUDAPPARATEN Huishoudapparaten, televisies and radio's",
    "sg:phone":"+32 51 56 61 19",
    "sg:postcode":"8610",
    "sg:province":"West-Vlaanderen",
    "wof:name":"Electro Vdb - Roland Bulcke",
    "wof:placetype":"venue"
},
  "geometry": {"coordinates":[3.0078439713,51.0482139587],"type":"Point"}
}