{
  "type": "Feature",
  "properties": {
    "addr:full":"Rue Omer Lion 1 Seneffe Hainaut 7181",
    "addr:housenumber":"1",
    "addr:postcode":"7181",
    "addr:street":"Rue Omer Lion",
    "iso:country":"BE",
    "sg:address":"Rue Omer Lion 1",
    "sg:city":"Seneffe",
    "sg:orig_category":"Loodgieterij, verwarming and sanitaire installaties",
    "sg:phone":"+32 67 87 74 28",
    "sg:postcode":"7181",
    "sg:province":"Hainaut",
    "wof:name":"Jean-pierre Boisseaux",
    "wof:placetype":"venue"
},
  "geometry": {"coordinates":[4.2729001045,50.5685386658],"type":"Point"}
}