{
  "type": "Feature",
  "properties": {
    "iso:country":"BE",
    "sg:address":"Stefaniestraat 32",
    "sg:city":"Antwerpen",
    "sg:orig_category":"Avocats and conseillers juridiques",
    "sg:phone":"+32 3 237 61 77",
    "sg:postcode":"2018",
    "sg:province":"Antwerpen",
    "wof:name":"E. Clynmans",
    "wof:placetype":"venue"
},
  "geometry": {"coordinates":[4.4026632309,51.2047653198],"type":"Point"}
}