{
  "type": "Feature",
  "properties": {
    "iso:country":"BE",
    "sg:address":"Rue De Marcinelle 35",
    "sg:city":"Charleroi",
    "sg:classifiers":[
        {
            "category":"Shopping",
            "subcategory":"Books",
            "type":"Retail Goods"
        }
    ],
    "sg:phone":"+32 71 30 15 92",
    "sg:postcode":"6000",
    "sg:province":"Hainaut",
    "sg:tags":[
        "bookseller"
    ],
    "wof:name":"Autant Savoir",
    "wof:placetype":"venue"
},
  "geometry": {"coordinates":[4.4439401627,50.4066352844],"type":"Point"}
}