{
  "type": "Feature",
  "properties": {
    "addr:full":"Kerkstraat 96 Buggenhout Oost-Vlaanderen 9255",
    "addr:housenumber":"96",
    "addr:postcode":"9255",
    "addr:street":"Kerkstraat",
    "iso:country":"BE",
    "sg:address":"Kerkstraat 96",
    "sg:city":"Buggenhout",
    "sg:classifiers":[
        {
            "category":"Brewery",
            "type":"Food & Drink"
        }
    ],
    "sg:phone":"+32 52 33 23 23",
    "sg:postcode":"9255",
    "sg:province":"Oost-Vlaanderen",
    "wof:name":"Kwak-karmeliet-deus Brouwerij Bosteels Nv",
    "wof:placetype":"venue"
},
  "geometry": {"coordinates":[4.2018399239,51.0136108398],"type":"Point"}
}