{
  "type": "Feature",
  "properties": {
    "addr:full":"Rue De M\u00e9rode 293 Bruxelles (forest) Bruxelles-Capitale 1190",
    "addr:housenumber":"293",
    "addr:postcode":"1190",
    "addr:street":"Rue De Me\u0301Rode",
    "iso:country":"BE",
    "sg:address":"Rue De M\u00e9rode 293",
    "sg:city":"Bruxelles (forest)",
    "sg:classifiers":[
        {
            "category":"Building & Trades",
            "subcategory":"Plumbing",
            "type":"Services"
        }
    ],
    "sg:phone":"+32 477 33 16 44",
    "sg:postcode":"1190",
    "sg:province":"Bruxelles-Capitale",
    "sg:tags":[
        "contractor"
    ],
    "wof:name":"B.a. Tech.",
    "wof:placetype":"venue"
},
  "geometry": {"coordinates":[4.330242157,50.8280181885],"type":"Point"}
}