{
  "type": "Feature",
  "properties": {
    "addr:full":"Kerkdreef 3 Gent Oost-Vlaanderen 9051",
    "addr:housenumber":"3",
    "addr:postcode":"9051",
    "addr:street":"Kerkdreef;Oost-Vlaanderen",
    "iso:country":"BE",
    "sg:address":"Kerkdreef 3",
    "sg:city":"Gent",
    "sg:orig_category":"Banques and organismes de cr\u00e9dit",
    "sg:phone":"+32 9 220 33 11",
    "sg:postcode":"9051",
    "sg:province":"Oost-Vlaanderen",
    "wof:name":"V.d.k. Spaarbank",
    "wof:placetype":"venue"
},
  "geometry": {"coordinates":[3.6695430279,51.023109436],"type":"Point"}
}