{
  "type": "Feature",
  "properties": {
    "iso:country":"BE",
    "sg:address":"Generaal Lartiguelaan 43",
    "sg:city":"Sint-lambrechts-woluwe/woluwe-saint-lambert",
    "sg:orig_category":"Artsen and specialisten",
    "sg:phone":"+32 2 734 01 73",
    "sg:postcode":"1200",
    "sg:province":"Bruxelles-Capitale",
    "wof:name":"Louis Gallez",
    "wof:placetype":"venue"
},
  "geometry": {"coordinates":[4.4094491005,50.8463401794],"type":"Point"}
}