{
  "type": "Feature",
  "properties": {
    "addr:full":"Avenue De L'arm\u00c9e 131 Etterbeek Bruxelles-Capitale 1040",
    "addr:housenumber":"131",
    "addr:postcode":"1040",
    "addr:street":"Avenue De L'Arme \u0301E",
    "iso:country":"BE",
    "sg:address":"Avenue De L'arm\u00c9e 131",
    "sg:city":"Etterbeek",
    "sg:classifiers":[
        {
            "category":"Restaurant",
            "type":"Food & Drink"
        }
    ],
    "sg:phone":"+32 2 736 93 10",
    "sg:postcode":"1040",
    "sg:province":"Bruxelles-Capitale",
    "wof:name":"Au Nouveau Pont",
    "wof:placetype":"venue"
},
  "geometry": {"coordinates":[4.4024600983,50.8338317871],"type":"Point"}
}