{
  "type": "Feature",
  "properties": {
    "addr:full":"Rue B\u00e8churon 32 Chaudfontaine (vaux-sous-ch\u00e8vremont) Li\u00e8ge 4051",
    "addr:housenumber":"32",
    "addr:postcode":"4051",
    "addr:street":"Rue Be\u0300Churon",
    "iso:country":"BE",
    "sg:address":"Rue B\u00e8churon 32",
    "sg:city":"Chaudfontaine (vaux-sous-ch\u00e8vremont)",
    "sg:classifiers":[
        {
            "category":"Building & Trades",
            "subcategory":"Electrical",
            "type":"Services"
        }
    ],
    "sg:phone":"+32 4 361 25 57",
    "sg:postcode":"4051",
    "sg:province":"Li\u00e8ge",
    "sg:tags":[
        "-",
        "electric",
        "contractor"
    ],
    "wof:name":"Sutera G",
    "wof:placetype":"venue"
},
  "geometry": {"coordinates":[5.6276159286,50.6086883545],"type":"Point"}
}