{
  "type": "Feature",
  "properties": {
    "iso:country":"BE",
    "sg:address":"Rue De L'amigo 1",
    "sg:city":"Brussel/bruxelles",
    "sg:orig_category":"H\u00f4tels. Restaurants",
    "sg:phone":"+32 2 547 47 16",
    "sg:postcode":"1000",
    "sg:province":"Bruxelles-Capitale",
    "wof:name":"H\u00d4tel Amigo",
    "wof:placetype":"venue"
},
  "geometry": {"coordinates":[4.3513269424,50.8462028503],"type":"Point"}
}