{
  "type": "Feature",
  "properties": {
    "addr:full":"Rue De Maestricht 69 Vis\u00e9 Li\u00e8ge 4600",
    "addr:housenumber":"69",
    "addr:postcode":"4600",
    "addr:street":"Rue De Maestricht",
    "iso:country":"BE",
    "sg:address":"Rue De Maestricht 69",
    "sg:city":"Vis\u00e9",
    "sg:classifiers":[
        {
            "category":"Shopping",
            "subcategory":"Pets & Pet Supplies",
            "type":"Retail Goods"
        }
    ],
    "sg:phone":"+32 4 379 51 01",
    "sg:postcode":"4600",
    "sg:province":"Li\u00e8ge",
    "sg:tags":[
        "-",
        "foundry"
    ],
    "wof:name":"M.c.technics",
    "wof:placetype":"venue"
},
  "geometry": {"coordinates":[5.7012619972,50.7445373535],"type":"Point"}
}