{
  "type": "Feature",
  "properties": {
    "addr:full":"Avenue De Tervueren 206 Bruxelles (woluwe-saint-pierre) Bruxelles-Capitale 1150",
    "addr:housenumber":"206",
    "addr:postcode":"1150",
    "addr:street":"Avenue De Tervueren",
    "iso:country":"BE",
    "sg:address":"Avenue De Tervueren 206",
    "sg:city":"Bruxelles (woluwe-saint-pierre)",
    "sg:classifiers":[
        {
            "category":"Banks & Credit Unions",
            "subcategory":"Investment Brokerage",
            "type":"Services"
        }
    ],
    "sg:phone":"+32 2 770 08 45",
    "sg:postcode":"1150",
    "sg:province":"Bruxelles-Capitale",
    "wof:name":"I F M Sprl Consulting",
    "wof:placetype":"venue"
},
  "geometry": {"coordinates":[4.4138088226,50.8365631104],"type":"Point"}
}