{
  "type": "Feature",
  "properties": {
    "iso:country":"BE",
    "sg:address":"Marais De L'eglise 16",
    "sg:city":"Brunehaut (laplaigne)",
    "sg:classifiers":[
        {
            "category":"Bars & Pubs",
            "type":"Food & Drink"
        }
    ],
    "sg:phone":"+32 69 34 41 44",
    "sg:postcode":"7622",
    "sg:province":"Hainaut",
    "wof:name":"Central (au)",
    "wof:placetype":"venue"
},
  "geometry": {"coordinates":[3.4467909336,50.5194740295],"type":"Point"}
}