{
  "type": "Feature",
  "properties": {
    "iso:country":"BE",
    "sg:address":"Rue Du Val Notre-dame 329",
    "sg:city":"Wanze (moha)",
    "sg:classifiers":[
        {
            "category":"Taxi",
            "type":"Transportation"
        }
    ],
    "sg:phone":"+32 85 23 23 23",
    "sg:postcode":"4520",
    "sg:province":"Li\u00e8ge",
    "sg:tags":[
        "taxicab"
    ],
    "wof:name":"Taxi Pascal",
    "wof:placetype":"venue"
},
  "geometry": {"coordinates":[5.1877908707,50.5508384705],"type":"Point"}
}