{
  "type": "Feature",
  "properties": {
    "iso:country":"BE",
    "sg:address":"Zottegemstraat 32",
    "sg:city":"Opwijk (mazenzele)",
    "sg:classifiers":[
        {
            "category":"Building & Trades",
            "subcategory":"Construction",
            "type":"Services"
        }
    ],
    "sg:phone":"+32 52 35 02 86",
    "sg:postcode":"1745",
    "sg:province":"Vlaams-Brabant",
    "sg:tags":[
        "carpenter"
    ],
    "wof:name":"Sacr\u00e9 G",
    "wof:placetype":"venue"
},
  "geometry": {"coordinates":[4.1650271416,50.9448051453],"type":"Point"}
}