{
  "type": "Feature",
  "properties": {
    "addr:full":"Wielsbekestraat 61 Oostrozebeke West-Vlaanderen 8780",
    "addr:housenumber":"61",
    "addr:postcode":"8780",
    "addr:street":"Wielsbekestraat",
    "iso:country":"BE",
    "sg:address":"Wielsbekestraat 61",
    "sg:city":"Oostrozebeke",
    "sg:classifiers":[
        {
            "category":"Banks & Credit Unions",
            "subcategory":"Investment Brokerage",
            "type":"Services"
        }
    ],
    "sg:phone":"+32 56 66 78 75",
    "sg:postcode":"8780",
    "sg:province":"West-Vlaanderen",
    "sg:tags":[
        "printing",
        "-"
    ],
    "wof:name":"Devos Luc Bvba",
    "wof:placetype":"venue"
},
  "geometry": {"coordinates":[3.3437759876,50.920211792],"type":"Point"}
}