{
  "type": "Feature",
  "properties": {
    "addr:full":"Violetstraat 70 Antwerpen Antwerpen 2060",
    "addr:housenumber":"70",
    "addr:postcode":"2060",
    "addr:street":"Violetstraat",
    "iso:country":"BE",
    "sg:address":"Violetstraat 70",
    "sg:city":"Antwerpen",
    "sg:classifiers":[
        {
            "category":"Bars & Pubs",
            "type":"Food & Drink"
        }
    ],
    "sg:phone":"+32 3 272 31 57",
    "sg:postcode":"2060",
    "sg:province":"Antwerpen",
    "wof:name":"Trixy",
    "wof:placetype":"venue"
},
  "geometry": {"coordinates":[4.4338111877,51.2215194702],"type":"Point"}
}