{
  "type": "Feature",
  "properties": {
    "addr:full":"Brusselsestraat 80 Dendermonde Oost-Vlaanderen 9200",
    "addr:housenumber":"80",
    "addr:postcode":"9200",
    "addr:street":"Brusselsestraat;Oost-Vlaanderen",
    "iso:country":"BE",
    "sg:address":"Brusselsestraat 80",
    "sg:city":"Dendermonde",
    "sg:classifiers":[
        {
            "category":"Shopping",
            "subcategory":"Clothing, Apparel, & Fashions",
            "type":"Retail Goods"
        }
    ],
    "sg:phone":"+32 52 22 39 84",
    "sg:postcode":"9200",
    "sg:province":"Oost-Vlaanderen",
    "sg:tags":[
        "bathing-",
        "beachwear"
    ],
    "wof:name":"Barbara",
    "wof:placetype":"venue"
},
  "geometry": {"coordinates":[4.1005182266,51.026638031],"type":"Point"}
}