{
  "type": "Feature",
  "properties": {
    "iso:country":"BE",
    "sg:address":"De Bruwaan 45",
    "sg:city":"Oudenaarde",
    "sg:orig_category":"Beschutte werkplaatsen Drukkerijen and copyshops",
    "sg:phone":"+32 55 31 13 45",
    "sg:postcode":"9700",
    "sg:province":"Oost-Vlaanderen",
    "wof:name":"Beschutte Werkpl. Aarova",
    "wof:placetype":"venue"
},
  "geometry": {"coordinates":[3.6085999012,50.842590332],"type":"Point"}
}