{
  "type": "Feature",
  "properties": {
    "addr:full":"Molenstraat 38 Hamme Oost-Vlaanderen 9220",
    "addr:housenumber":"38",
    "addr:postcode":"9220",
    "addr:street":"Molenstraat",
    "iso:country":"BE",
    "sg:address":"Molenstraat 38",
    "sg:city":"Hamme",
    "sg:orig_category":"Benzinestations and brandstoffen Herstellingen and onderhoud van auto's Voertuigen",
    "sg:phone":"+32 52 47 76 87",
    "sg:postcode":"9220",
    "sg:province":"Oost-Vlaanderen",
    "wof:name":"Garage Claus",
    "wof:placetype":"venue"
},
  "geometry": {"coordinates":[4.1490621567,51.0622596741],"type":"Point"}
}