{
  "type": "Feature",
  "properties": {
    "addr:full":"Kromstraat 19 Tongeren (piringen) Limburg 3700",
    "addr:housenumber":"19",
    "addr:postcode":"3700",
    "addr:street":"Kromstraat",
    "iso:country":"BE",
    "sg:address":"Kromstraat 19",
    "sg:city":"Tongeren (piringen)",
    "sg:classifiers":[
        {
            "category":"Personal",
            "subcategory":"Beauty Salon",
            "type":"Services"
        }
    ],
    "sg:phone":"+32 12 23 01 46",
    "sg:postcode":"3700",
    "sg:province":"Limburg",
    "sg:tags":[
        "lady",
        "-",
        "hairdressing"
    ],
    "wof:name":"D'huys M",
    "wof:placetype":"venue"
},
  "geometry": {"coordinates":[5.4636240005,50.7807197571],"type":"Point"}
}