{
  "type": "Feature",
  "properties": {
    "addr:full":"Heldergemstraat 144 Haaltert (heldergem) Oost-Vlaanderen 9450",
    "addr:housenumber":"144",
    "addr:postcode":"9450",
    "addr:street":"Heldergemstraat",
    "iso:country":"BE",
    "sg:address":"Heldergemstraat 144",
    "sg:city":"Haaltert (heldergem)",
    "sg:classifiers":[
        {
            "category":"Bars & Pubs",
            "type":"Food & Drink"
        }
    ],
    "sg:phone":"+32 53 62 45 95",
    "sg:postcode":"9450",
    "sg:province":"Oost-Vlaanderen",
    "wof:name":"Rally",
    "wof:placetype":"venue"
},
  "geometry": {"coordinates":[3.955550909,50.8799858093],"type":"Point"}
}