{
  "type": "Feature",
  "properties": {
    "iso:country":"BE",
    "sg:address":"Leuvensesteenweg 388",
    "sg:city":"Schaarbeek/schaerbeek",
    "sg:orig_category":"MEUBELONTWERP AND -INSTALLATIE",
    "sg:phone":"+32 2 733 72 68",
    "sg:postcode":"1030",
    "sg:province":"Bruxelles-Capitale",
    "wof:name":"Il Villagio De Mobilis",
    "wof:placetype":"venue"
},
  "geometry": {"coordinates":[4.3859639168,50.8517913818],"type":"Point"}
}