{
  "type": "Feature",
  "properties": {
    "addr:full":"Rue Nestor Falise 141 Courcelles Hainaut 6180",
    "addr:housenumber":"141",
    "addr:postcode":"6180",
    "addr:street":"Rue Nestor Falise",
    "iso:country":"BE",
    "sg:address":"Rue Nestor Falise 141",
    "sg:city":"Courcelles",
    "sg:classifiers":[
        {
            "category":"Personal",
            "subcategory":"Beauty Salon",
            "type":"Services"
        }
    ],
    "sg:phone":"+32 71 45 41 05",
    "sg:postcode":"6180",
    "sg:province":"Hainaut",
    "sg:tags":[
        "de",
        "coiffure"
    ],
    "wof:name":"Georgette Joris",
    "wof:placetype":"venue"
},
  "geometry": {"coordinates":[4.3859148026,50.4550247192],"type":"Point"}
}