{
  "type": "Feature",
  "properties": {
    "iso:country":"BE",
    "sg:address":"Rue Franklin Roosevelt 257",
    "sg:city":"Trooz (fraipont)",
    "sg:classifiers":[
        {
            "category":"Professional",
            "subcategory":"Testing Lab",
            "type":"Services"
        }
    ],
    "sg:phone":"+32 87 26 81 53",
    "sg:postcode":"4870",
    "sg:province":"Li\u00e8ge",
    "sg:tags":[
        "chemist"
    ],
    "wof:name":"Paternotte G",
    "wof:placetype":"venue"
},
  "geometry": {"coordinates":[5.7390198708,50.5716247559],"type":"Point"}
}