{
  "type": "Feature",
  "properties": {
    "addr:full":"Avenue Louis Piedboeuf 18 Chaudfontaine (embourg) Li\u00e8ge 4053",
    "addr:housenumber":"18",
    "addr:postcode":"4053",
    "addr:street":"Avenue Louis Piedboeuf",
    "iso:country":"BE",
    "sg:address":"Avenue Louis Piedboeuf 18",
    "sg:city":"Chaudfontaine (embourg)",
    "sg:classifiers":[
        {
            "category":"Health Services",
            "subcategory":"Health Practitioner",
            "type":"Services"
        }
    ],
    "sg:phone":"+32 4 365 38 93",
    "sg:postcode":"4053",
    "sg:province":"Li\u00e8ge",
    "sg:tags":[
        "physiotherapist"
    ],
    "wof:name":"Bol D",
    "wof:placetype":"venue"
},
  "geometry": {"coordinates":[5.6022181511,50.5883369446],"type":"Point"}
}