{
  "type": "Feature",
  "properties": {
    "iso:country":"BE",
    "sg:address":"Abdijhoek 10",
    "sg:city":"Zedelgem (loppem)",
    "sg:classifiers":[
        {
            "category":"Real Estate",
            "subcategory":"Architect",
            "type":"Services"
        }
    ],
    "sg:phone":"+32 50 38 81 78",
    "sg:postcode":"8210",
    "sg:province":"West-Vlaanderen",
    "wof:name":"Favril J",
    "wof:placetype":"venue"
},
  "geometry": {"coordinates":[3.1528949738,51.1511306763],"type":"Point"}
}