{
  "type": "Feature",
  "properties": {
    "iso:country":"BE",
    "sg:address":"Rue Des Vall\u00e9es 5",
    "sg:city":"Celles",
    "sg:classifiers":[
        {
            "category":"Wholesale",
            "subcategory":"Fruits & Vegetables",
            "type":"Manufacturing & Wholesale Goods"
        }
    ],
    "sg:phone":"+32 69 45 46 09",
    "sg:postcode":"7760",
    "sg:province":"Hainaut",
    "sg:tags":[
        "whol",
        "-",
        "potato"
    ],
    "wof:name":"Soci\u00e9t\u00e9 Des Vall\u00e9es Sa",
    "wof:placetype":"venue"
},
  "geometry": {"coordinates":[3.4299449921,50.705783844],"type":"Point"}
}