{
  "type": "Feature",
  "properties": {
    "addr:full":"Heygemstraat 9 Dilbeek Vlaams-Brabant 1700",
    "addr:housenumber":"9",
    "addr:postcode":"1700",
    "addr:street":"Heygemstraat",
    "iso:country":"BE",
    "sg:address":"Heygemstraat 9",
    "sg:city":"Dilbeek",
    "sg:orig_category":"Pain, p\u00e2tisseries and confiseries",
    "sg:phone":"+32 2 569 01 70",
    "sg:postcode":"1700",
    "sg:province":"Vlaams-Brabant",
    "wof:name":"Quinaux",
    "wof:placetype":"venue"
},
  "geometry": {"coordinates":[4.2177491188,50.8563461304],"type":"Point"}
}