{
  "type": "Feature",
  "properties": {
    "iso:country":"BE",
    "sg:address":"Maloulaan 43",
    "sg:city":"Ieper",
    "sg:classifiers":[
        {
            "category":"Professional",
            "subcategory":"Accounting & Tax Preparation",
            "type":"Services"
        }
    ],
    "sg:phone":"+32 57 21 93 38",
    "sg:postcode":"8900",
    "sg:province":"West-Vlaanderen",
    "sg:tags":[
        "accountant"
    ],
    "wof:name":"Abv Accountants",
    "wof:placetype":"venue"
},
  "geometry": {"coordinates":[2.8764181137,50.8508529663],"type":"Point"}
}