{
  "type": "Feature",
  "properties": {
    "addr:full":"Avenue Des Epic\u00e9as 10 Neupr\u00e9 (neuville-en-condroz) Li\u00e8ge 4121",
    "addr:housenumber":"10",
    "addr:postcode":"4121",
    "addr:street":"Avenue Des Epice\u0301As",
    "iso:country":"BE",
    "sg:address":"Avenue Des Epic\u00e9as 10",
    "sg:city":"Neupr\u00e9 (neuville-en-condroz)",
    "sg:classifiers":[
        {
            "category":"Health Services",
            "subcategory":"Doctor",
            "type":"Services"
        }
    ],
    "sg:phone":"+32 4 371 44 29",
    "sg:postcode":"4121",
    "sg:province":"Li\u00e8ge",
    "sg:tags":[
        "medicinephysicians",
        "surgeon"
    ],
    "wof:name":"Borsu Annette",
    "wof:placetype":"venue"
},
  "geometry": {"coordinates":[5.473233223,50.5456619263],"type":"Point"}
}