{
  "type": "Feature",
  "properties": {
    "iso:country":"BE",
    "sg:address":"Boulevard De Smet De Naeyer 32",
    "sg:city":"Bruxelles (jette)",
    "sg:orig_category":"Non-Classified Establishments",
    "sg:phone":"+32 2 522 34 88",
    "sg:postcode":"1090",
    "sg:province":"Bruxelles-Capitale",
    "wof:name":"Toma Confection Sprl",
    "wof:placetype":"venue"
},
  "geometry": {"coordinates":[4.3275589943,50.8720092773],"type":"Point"}
}