{
  "type": "Feature",
  "properties": {
    "addr:full":"Rue Du Cimeti\u00c8re 17 Charleroi Hainaut 6042",
    "addr:housenumber":"17",
    "addr:postcode":"6042",
    "addr:street":"Rue Du Cimetie\u0300Re;Hainaut",
    "iso:country":"BE",
    "sg:address":"Rue Du Cimeti\u00c8re 17",
    "sg:city":"Charleroi",
    "sg:orig_category":"Dakwerken",
    "sg:phone":"+32 71 30 38 23",
    "sg:postcode":"6042",
    "sg:province":"Hainaut",
    "wof:name":"A. Lagneau",
    "wof:placetype":"venue"
},
  "geometry": {"coordinates":[4.4694027901,50.3879432678],"type":"Point"}
}