{
  "type": "Feature",
  "properties": {
    "iso:country":"BE",
    "sg:address":"Rue Des Carrelages",
    "sg:city":"La Louviere",
    "sg:orig_category":"Sportclubs",
    "sg:phone":"+32 64 22 27 47",
    "sg:postcode":"7100",
    "sg:province":"Hainaut",
    "wof:name":"Royal Tennis",
    "wof:placetype":"venue"
},
  "geometry": {"coordinates":[4.1917948723,50.482383728],"type":"Point"}
}