{
  "type": "Feature",
  "properties": {
    "addr:full":"Rue M\u00e9trin Vin\u00e2ve 65 Oupeye (houtain-saint-sim\u00e9on) Li\u00e8ge 4682",
    "addr:housenumber":"65",
    "addr:postcode":"4682",
    "addr:street":"Rue Me\u0301Trin Vina\u0302Ve;Houtain-Saint-Sime\u0301On",
    "iso:country":"BE",
    "sg:address":"Rue M\u00e9trin Vin\u00e2ve 65",
    "sg:city":"Oupeye (houtain-saint-sim\u00e9on)",
    "sg:classifiers":[
        {
            "category":"Food & Beverages",
            "subcategory":"Supermarket",
            "type":"Retail Goods"
        }
    ],
    "sg:phone":"+32 4 286 48 63",
    "sg:postcode":"4682",
    "sg:province":"Li\u00e8ge",
    "sg:tags":[
        "department",
        "store"
    ],
    "wof:name":"Houtain Distribution",
    "wof:placetype":"venue"
},
  "geometry": {"coordinates":[5.6338701248,50.7312393188],"type":"Point"}
}