{
  "type": "Feature",
  "properties": {
    "addr:full":"Pieter Van Isackerlaan 1ba Antwerpen Antwerpen 2100",
    "addr:housenumber":"1ba",
    "addr:postcode":"2100",
    "addr:street":"Pieter Van Isackerlaan",
    "iso:country":"BE",
    "sg:address":"Pieter Van Isackerlaan 1ba",
    "sg:city":"Antwerpen",
    "sg:orig_category":"Activit\u00e9s d\u00b4action sociale sans h\u00e9bergement",
    "sg:phone":"+32 3 366 16 36",
    "sg:postcode":"2100",
    "sg:province":"Antwerpen",
    "wof:name":"Vclb-centrum",
    "wof:placetype":"venue"
},
  "geometry": {"coordinates":[4.4586100578,51.2203941345],"type":"Point"}
}