{
  "type": "Feature",
  "properties": {
    "iso:country":"BE",
    "sg:address":"Baarleveldestraat 8",
    "sg:city":"Gent",
    "sg:orig_category":"Diepvriesproducten Gh",
    "sg:phone":"+32 9 216 61 16",
    "sg:postcode":"9031",
    "sg:province":"Oost-Vlaanderen",
    "wof:name":"O' Cool",
    "wof:placetype":"venue"
},
  "geometry": {"coordinates":[3.6238110065,51.0397338867],"type":"Point"}
}