{
  "type": "Feature",
  "properties": {
    "iso:country":"BE",
    "sg:address":"Wijvestraat 23",
    "sg:city":"Zonhoven",
    "sg:orig_category":"Gespecialiseerde residenti\u00eble bouw",
    "sg:phone":"+32 11 81 77 31",
    "sg:postcode":"3520",
    "sg:province":"Limburg",
    "wof:name":"Johan Tielens",
    "wof:placetype":"venue"
},
  "geometry": {"coordinates":[5.3417282104,50.9895172119],"type":"Point"}
}