{
  "type": "Feature",
  "properties": {
    "addr:full":"Westkerkestraat 171 Ichtegem West-Vlaanderen 8480",
    "addr:housenumber":"171",
    "addr:postcode":"8480",
    "addr:street":"Westkerkestraat",
    "iso:country":"BE",
    "sg:address":"Westkerkestraat 171",
    "sg:city":"Ichtegem",
    "sg:orig_category":"Plomberie, chauffage and installations sanitaires",
    "sg:phone":"+32 59 29 90 22",
    "sg:postcode":"8480",
    "sg:province":"West-Vlaanderen",
    "wof:name":"Verschoore",
    "wof:placetype":"venue"
},
  "geometry": {"coordinates":[3.0257310867,51.1399421692],"type":"Point"}
}