{
  "type": "Feature",
  "properties": {
    "addr:full":"Rue Louis Micheroux 34 Fleron Li\u00e8ge 4620",
    "addr:housenumber":"34",
    "addr:postcode":"4620",
    "addr:street":"Rue Louis Micheroux",
    "iso:country":"BE",
    "sg:address":"Rue Louis Micheroux 34",
    "sg:city":"Fleron",
    "sg:orig_category":"Jeux and jouets. Grands magasins. Hypermarch\u00e9s",
    "sg:phone":"+32 4 355 86 11",
    "sg:postcode":"4620",
    "sg:province":"Li\u00e8ge",
    "wof:name":"G.b. Maxi Fleron",
    "wof:placetype":"venue"
},
  "geometry": {"coordinates":[5.6807179451,50.6156196594],"type":"Point"}
}