{
  "type": "Feature",
  "properties": {
    "addr:full":"Avenue De Cortenbergh 85 Bruxelles Bruxelles-Capitale 1000",
    "addr:housenumber":"85",
    "addr:postcode":"1000",
    "addr:street":"Avenue De Cortenbergh",
    "iso:country":"BE",
    "sg:address":"Avenue De Cortenbergh 85",
    "sg:city":"Bruxelles",
    "sg:classifiers":[
        {
            "category":"Social Services",
            "subcategory":"Child Care",
            "type":"Services"
        }
    ],
    "sg:phone":"+32 2 736 81 28",
    "sg:postcode":"1000",
    "sg:province":"Bruxelles-Capitale",
    "sg:tags":[
        "home"
    ],
    "wof:name":"Cl\u00e9 (la) Home",
    "wof:placetype":"venue"
},
  "geometry": {"coordinates":[4.3900542259,50.844959259],"type":"Point"}
}