{
  "type": "Feature",
  "properties": {
    "addr:full":"Dijkstraat 33 Dessel Antwerpen 2480",
    "addr:housenumber":"33",
    "addr:postcode":"2480",
    "addr:street":"Dijkstraat",
    "iso:country":"BE",
    "sg:address":"Dijkstraat 33",
    "sg:city":"Dessel",
    "sg:classifiers":[
        {
            "category":"Real Estate",
            "subcategory":"Surveying",
            "type":"Services"
        }
    ],
    "sg:phone":"+32 479 36 98 13",
    "sg:postcode":"2480",
    "sg:province":"Antwerpen",
    "sg:tags":[
        "surveyor",
        "land"
    ],
    "wof:name":"Van Den Kerchove H",
    "wof:placetype":"venue"
},
  "geometry": {"coordinates":[5.1217498779,51.2353668213],"type":"Point"}
}