{
  "type": "Feature",
  "properties": {
    "iso:country":"BE",
    "sg:address":"Rue Hocheporte 29",
    "sg:city":"Li\u00c8ge",
    "sg:orig_category":"Artiesten and kunstenaars",
    "sg:phone":"+32 4 223 60 01",
    "sg:postcode":"4000",
    "sg:province":"Li\u00e8ge",
    "wof:name":"Emile Olivier",
    "wof:placetype":"venue"
},
  "geometry": {"coordinates":[5.5650610924,50.64635849],"type":"Point"}
}