{
  "type": "Feature",
  "properties": {
    "iso:country":"BE",
    "sg:address":"Splethagestraat 10",
    "sg:city":"Oostkamp",
    "sg:classifiers":[
        {
            "category":"Arena",
            "subcategory":"Sports Club",
            "type":"Entertainment"
        }
    ],
    "sg:phone":"+32 50 82 20 81",
    "sg:postcode":"8020",
    "sg:province":"West-Vlaanderen",
    "sg:tags":[
        "de"
    ],
    "wof:name":"B.b.c. Oostkampse Merels",
    "wof:placetype":"venue"
},
  "geometry": {"coordinates":[3.2313570976,51.1515884399],"type":"Point"}
}