{
  "type": "Feature",
  "properties": {
    "iso:country":"BE",
    "sg:address":"Wijnendaelestraat 130",
    "sg:city":"Diksmuide (groot)",
    "sg:orig_category":"Artistes ind\u00e9pendants",
    "sg:phone":"+32 51 51 14 64",
    "sg:postcode":"8600",
    "sg:province":"West-Vlaanderen",
    "wof:name":"Magyar Tzigane Orkest",
    "wof:placetype":"venue"
},
  "geometry": {"coordinates":[2.9072699547,51.061668396],"type":"Point"}
}