{
  "type": "Feature",
  "properties": {
    "iso:country":"BE",
    "sg:address":"Chemin Des Gras Pr\u00c9s 6",
    "sg:city":"Anderlues",
    "sg:orig_category":"Artsen and specialisten",
    "sg:phone":"+32 71 52 26 91",
    "sg:postcode":"6150",
    "sg:province":"Hainaut",
    "wof:name":"Eric Pieron",
    "wof:placetype":"venue"
},
  "geometry": {"coordinates":[4.2486591339,50.3967247009],"type":"Point"}
}