{
  "type": "Feature",
  "properties": {
    "iso:country":"BE",
    "sg:address":"Rue Des Canonniers 2",
    "sg:city":"Mons",
    "sg:orig_category":"M\u00e9decins and sp\u00e9cialistes",
    "sg:phone":"+32 65 31 76 66",
    "sg:postcode":"7000",
    "sg:province":"Hainaut",
    "wof:name":"Michel Roger",
    "wof:placetype":"venue"
},
  "geometry": {"coordinates":[3.9482090473,50.4476051331],"type":"Point"}
}