{
  "type": "Feature",
  "properties": {
    "iso:country":"BE",
    "sg:address":"Chausste De Ninove 1054",
    "sg:city":"Sint-jans-molenbeek/molenbeek-saint-jean",
    "sg:orig_category":"Tabac. Journaux. Librairies",
    "sg:phone":"+32 2 521 35 67",
    "sg:postcode":"1080",
    "sg:province":"Bruxelles-Capitale",
    "wof:name":"Chez Marleen",
    "wof:placetype":"venue"
},
  "geometry": {"coordinates":[4.2902622223,50.8461418152],"type":"Point"}
}