{
  "type": "Feature",
  "properties": {
    "addr:full":"Rue Sainte-walburge 343 Li\u00c8ge Li\u00e8ge 4000",
    "addr:housenumber":"343",
    "addr:postcode":"4000",
    "addr:street":"Rue Sainte-Walburge",
    "iso:country":"BE",
    "sg:address":"Rue Sainte-walburge 343",
    "sg:city":"Li\u00c8ge",
    "sg:orig_category":"Boucheries",
    "sg:phone":"+32 4 226 92 12",
    "sg:postcode":"4000",
    "sg:province":"Li\u00e8ge",
    "wof:name":"Renmans",
    "wof:placetype":"venue"
},
  "geometry": {"coordinates":[5.5488967896,50.6332817078],"type":"Point"}
}