{
  "type": "Feature",
  "properties": {
    "addr:full":"Bloemenstraat 9 Riemst (vlijtingen) Limburg 3770",
    "addr:housenumber":"9",
    "addr:postcode":"3770",
    "addr:street":"Bloemenstraat",
    "iso:country":"BE",
    "sg:address":"Bloemenstraat 9",
    "sg:city":"Riemst (vlijtingen)",
    "sg:classifiers":[
        {
            "category":"Real Estate",
            "subcategory":"Architect",
            "type":"Services"
        }
    ],
    "sg:phone":"+32 12 45 24 02",
    "sg:postcode":"3770",
    "sg:province":"Limburg",
    "wof:name":"Mingels L",
    "wof:placetype":"venue"
},
  "geometry": {"coordinates":[5.5847258568,50.8287200928],"type":"Point"}
}