{
  "type": "Feature",
  "properties": {
    "addr:full":"Rue Du Brutia 7 Gembloux-sur-orneau (gembloux) Namur 5030",
    "addr:housenumber":"7",
    "addr:postcode":"5030",
    "addr:street":"Rue Du Brutia;Namur",
    "iso:country":"BE",
    "sg:address":"Rue Du Brutia 7",
    "sg:city":"Gembloux-sur-orneau (gembloux)",
    "sg:classifiers":[
        {
            "category":"Health Services",
            "subcategory":"Health Practitioner",
            "type":"Services"
        }
    ],
    "sg:phone":"+32 81 61 05 79",
    "sg:postcode":"5030",
    "sg:province":"Namur",
    "sg:tags":[
        "physiotherapist"
    ],
    "wof:name":"Grolet D",
    "wof:placetype":"venue"
},
  "geometry": {"coordinates":[4.6941189766,50.5506095886],"type":"Point"}
}