{
  "type": "Feature",
  "properties": {
    "addr:full":"Meiboomstraat 4d Wingene West-Vlaanderen 8750",
    "addr:housenumber":"4d",
    "addr:postcode":"8750",
    "addr:street":"Meiboomstraat",
    "iso:country":"BE",
    "sg:address":"Meiboomstraat 4d",
    "sg:city":"Wingene",
    "sg:orig_category":"Tuinen",
    "sg:phone":"+32 51 61 19 89",
    "sg:postcode":"8750",
    "sg:province":"West-Vlaanderen",
    "wof:name":"Soens G",
    "wof:placetype":"venue"
},
  "geometry": {"coordinates":[3.2077019215,51.0323257446],"type":"Point"}
}