{
  "type": "Feature",
  "properties": {
    "iso:country":"BE",
    "sg:address":"Sint-corneliusstraat 21",
    "sg:city":"Zedelgem",
    "sg:orig_category":"Woningbouw",
    "sg:phone":"+32 50 27 51 61",
    "sg:postcode":"8210",
    "sg:province":"West-Vlaanderen",
    "wof:name":"Paul Vanbelle",
    "wof:placetype":"venue"
},
  "geometry": {"coordinates":[3.1314458847,51.1422119141],"type":"Point"}
}