{
  "type": "Feature",
  "properties": {
    "iso:country":"BE",
    "sg:address":"Westerlosesteenweg 2ba",
    "sg:city":"Heist-op-den-berg",
    "sg:classifiers":[
        {
            "category":"Autos & Motor Vehicles",
            "subcategory":"Fuel & Gas Station",
            "type":"Retail Goods"
        }
    ],
    "sg:phone":"+32 15 24 45 96",
    "sg:postcode":"2220",
    "sg:province":"Antwerpen",
    "sg:tags":[
        "stations-service",
        "carburants"
    ],
    "wof:name":"Texaco",
    "wof:placetype":"venue"
},
  "geometry": {"coordinates":[4.7365541458,51.0729408264],"type":"Point"}
}