{
  "type": "Feature",
  "properties": {
    "iso:country":"BE",
    "sg:address":"Grootheide 86",
    "sg:city":"Bornem",
    "sg:classifiers":[
        {
            "category":"Banks & Credit Unions",
            "subcategory":"Bureau De Change",
            "type":"Services"
        }
    ],
    "sg:phone":"+32 3 899 37 21",
    "sg:postcode":"2880",
    "sg:province":"Antwerpen",
    "sg:tags":[
        "model",
        "scale",
        "-"
    ],
    "wof:name":"De Keersmaecker W",
    "wof:placetype":"venue"
},
  "geometry": {"coordinates":[4.2216777802,51.089214325],"type":"Point"}
}