{
  "type": "Feature",
  "properties": {
    "addr:full":"Rue De Termogne 55 Faimes Li\u00e8ge 4317",
    "addr:housenumber":"55",
    "addr:postcode":"4317",
    "addr:street":"Rue De Termogne",
    "iso:country":"BE",
    "sg:address":"Rue De Termogne 55",
    "sg:city":"Faimes",
    "sg:orig_category":"Varkenskwekers",
    "sg:phone":"+32 19 33 21 85",
    "sg:postcode":"4317",
    "sg:province":"Li\u00e8ge",
    "wof:name":"Fumal Gustave & Josephine",
    "wof:placetype":"venue"
},
  "geometry": {"coordinates":[5.2277069092,50.6570243835],"type":"Point"}
}