{
  "type": "Feature",
  "properties": {
    "iso:country":"BE",
    "sg:address":"Klosterstrasse 6",
    "sg:city":"Eupen",
    "sg:classifiers":[
        {
            "category":"Bakery",
            "type":"Food & Drink"
        }
    ],
    "sg:phone":"+32 87 74 21 19",
    "sg:postcode":"4700",
    "sg:province":"Li\u00e8ge",
    "sg:tags":[
        "confectioner",
        "baker"
    ],
    "wof:name":"Matadi Sprlu",
    "wof:placetype":"venue"
},
  "geometry": {"coordinates":[6.0306081772,50.6319274902],"type":"Point"}
}