{
  "type": "Feature",
  "properties": {
    "addr:full":"Denayerlaan 89 Vorst/forest Bruxelles-Capitale 1190",
    "addr:housenumber":"89",
    "addr:postcode":"1190",
    "addr:street":"Denayerlaan;/ Forest",
    "iso:country":"BE",
    "sg:address":"Denayerlaan 89",
    "sg:city":"Vorst/forest",
    "sg:orig_category":"Artsen and specialisten",
    "sg:phone":"+32 2 660 05 04",
    "sg:postcode":"1190",
    "sg:province":"Bruxelles-Capitale",
    "wof:name":"Daniel Couvreur",
    "wof:placetype":"venue"
},
  "geometry": {"coordinates":[4.3209381104,50.8070526123],"type":"Point"}
}