{
  "type": "Feature",
  "properties": {
    "iso:country":"BE",
    "sg:address":"Rue Francisco Ferrer 55",
    "sg:city":"Farciennes",
    "sg:orig_category":"Schoonheidssalons",
    "sg:phone":"+32 71 38 32 56",
    "sg:postcode":"6240",
    "sg:province":"Hainaut",
    "wof:name":"La Fontaine De Jouvence",
    "wof:placetype":"venue"
},
  "geometry": {"coordinates":[4.5547018051,50.4244766235],"type":"Point"}
}