{
  "type": "Feature",
  "properties": {
    "addr:full":"Henri Brounsstraat 57 Machelen Vlaams-Brabant 1830",
    "addr:housenumber":"57",
    "addr:postcode":"1830",
    "addr:street":"Henri Brounsstraat",
    "iso:country":"BE",
    "sg:address":"Henri Brounsstraat 57",
    "sg:city":"Machelen",
    "sg:orig_category":"Brood, gebak and snoepgoed",
    "sg:phone":"+32 2 253 66 01",
    "sg:postcode":"1830",
    "sg:province":"Vlaams-Brabant",
    "wof:name":"Bakkerij Chris & Andr\u00c9",
    "wof:placetype":"venue"
},
  "geometry": {"coordinates":[4.4320068359,50.9085731506],"type":"Point"}
}