{
  "type": "Feature",
  "properties": {
    "iso:country":"BE",
    "sg:address":"Chauss\u00c9e De Charleroi 24",
    "sg:city":"Perwez",
    "sg:orig_category":"Zuivelproducten and spijsolie Gh",
    "sg:phone":"+32 81 65 50 79",
    "sg:postcode":"1360",
    "sg:province":"Brabant Wallon",
    "wof:name":"Godfriaux Et Cie",
    "wof:placetype":"venue"
},
  "geometry": {"coordinates":[4.7820382118,50.6383552551],"type":"Point"}
}