{
  "type": "Feature",
  "properties": {
    "addr:full":"Gezusters Lovelingstraat 2 Nevele Oost-Vlaanderen 9850",
    "addr:housenumber":"2",
    "addr:postcode":"9850",
    "addr:street":"Lovelingstraat",
    "iso:country":"BE",
    "sg:address":"Gezusters Lovelingstraat 2",
    "sg:city":"Nevele",
    "sg:orig_category":"Supermarkten",
    "sg:phone":"+32 9 371 82 45",
    "sg:postcode":"9850",
    "sg:province":"Oost-Vlaanderen",
    "wof:name":"Dravo Nevele",
    "wof:placetype":"venue"
},
  "geometry": {"coordinates":[3.5481600761,51.0351791382],"type":"Point"}
}