{
  "type": "Feature",
  "properties": {
    "iso:country":"BE",
    "sg:address":"Rue Du Grand Tige 16",
    "sg:city":"Erpent",
    "sg:classifiers":[
        {
            "category":"Sports & Exercise",
            "subcategory":"Playing Field",
            "type":"Entertainment"
        }
    ],
    "sg:phone":"+32 81 30 18 68",
    "sg:postcode":"5101",
    "sg:province":"Namur",
    "sg:tags":[
        "application",
        "programming"
    ],
    "wof:name":"Erg\u00e9lec S.p.r.l.",
    "wof:placetype":"venue"
},
  "geometry": {"coordinates":[4.8981370926,50.4504165649],"type":"Point"}
}