{
  "type": "Feature",
  "properties": {
    "addr:full":"Brechtsebaan 151 Brasschaat Antwerpen 2930",
    "addr:housenumber":"151",
    "addr:postcode":"2930",
    "addr:street":"Brechtsebaan",
    "iso:country":"BE",
    "sg:address":"Brechtsebaan 151",
    "sg:city":"Brasschaat",
    "sg:orig_category":"Tuinen",
    "sg:phone":"+32 3 633 22 88",
    "sg:postcode":"2930",
    "sg:province":"Antwerpen",
    "wof:name":"Niesz Ch.",
    "wof:placetype":"venue"
},
  "geometry": {"coordinates":[4.5334849358,51.3272399902],"type":"Point"}
}