{
  "type": "Feature",
  "properties": {
    "addr:full":"Rue De La Motte 2 Soignies (thieusies) Hainaut 7061",
    "addr:housenumber":"2",
    "addr:postcode":"7061",
    "addr:street":"Rue De La Motte",
    "iso:country":"BE",
    "sg:address":"Rue De La Motte 2",
    "sg:city":"Soignies (thieusies)",
    "sg:classifiers":[
        {
            "category":"Bars & Pubs",
            "type":"Food & Drink"
        }
    ],
    "sg:phone":"+32 65 72 38 08",
    "sg:postcode":"7061",
    "sg:province":"Hainaut",
    "wof:name":"Metropole",
    "wof:placetype":"venue"
},
  "geometry": {"coordinates":[4.0133500099,50.5159416199],"type":"Point"}
}