{
  "type": "Feature",
  "properties": {
    "iso:country":"BE",
    "sg:address":"Rue Des Fagnes 4",
    "sg:city":"Rendeux",
    "sg:orig_category":"Parfumeries",
    "sg:phone":"+32 84 47 83 62",
    "sg:postcode":"6987",
    "sg:province":"Luxembourg",
    "wof:name":"Evelyne Bougnet",
    "wof:placetype":"venue"
},
  "geometry": {"coordinates":[5.5193037987,50.2578277588],"type":"Point"}
}