{
  "type": "Feature",
  "properties": {
    "addr:full":"Fortlaan 45 Gent Oost-Vlaanderen 9000",
    "addr:housenumber":"45",
    "addr:postcode":"9000",
    "addr:street":"Fortlaan;Oost-Vlaanderen",
    "iso:country":"BE",
    "sg:address":"Fortlaan 45",
    "sg:city":"Gent",
    "sg:orig_category":"Artsen and specialisten",
    "sg:phone":"+32 9 220 50 44",
    "sg:postcode":"9000",
    "sg:province":"Oost-Vlaanderen",
    "wof:name":"Ingrid Martens",
    "wof:placetype":"venue"
},
  "geometry": {"coordinates":[3.7175850868,51.0357666016],"type":"Point"}
}