{
  "type": "Feature",
  "properties": {
    "addr:full":"Meensesteenweg 715 Roeselare West-Vlaanderen 8800",
    "addr:housenumber":"715",
    "addr:postcode":"8800",
    "addr:street":"Meensesteenweg",
    "iso:country":"BE",
    "sg:address":"Meensesteenweg 715",
    "sg:city":"Roeselare",
    "sg:orig_category":"Enseignement maternel and primaire",
    "sg:phone":"+32 56 50 21 13",
    "sg:postcode":"8800",
    "sg:province":"West-Vlaanderen",
    "wof:name":"Vrije Basisschool",
    "wof:placetype":"venue"
},
  "geometry": {"coordinates":[3.1144180298,50.8932723999],"type":"Point"}
}