{
  "type": "Feature",
  "properties": {
    "addr:full":"Stadenstraat 29 Kortemark West-Vlaanderen 8610",
    "addr:housenumber":"29",
    "addr:postcode":"8610",
    "addr:street":"Stadenstraat",
    "iso:country":"BE",
    "sg:address":"Stadenstraat 29",
    "sg:city":"Kortemark",
    "sg:orig_category":"Banken and kredietinstellingen Levensverzekeringsmaatschappijen Verzekeringen vastgoed Verzekeringsm",
    "sg:phone":"+32 51 56 72 28",
    "sg:postcode":"8610",
    "sg:province":"West-Vlaanderen",
    "wof:name":"Mercator Bank",
    "wof:placetype":"venue"
},
  "geometry": {"coordinates":[2.9616520405,51.0162086487],"type":"Point"}
}