{
  "type": "Feature",
  "properties": {
    "addr:full":"Eegene 2 Dendermonde Oost-Vlaanderen 9200",
    "addr:housenumber":"2",
    "addr:postcode":"9200",
    "addr:street":"Eegene;Oost-Vlaanderen",
    "iso:country":"BE",
    "sg:address":"Eegene 2",
    "sg:city":"Dendermonde",
    "sg:orig_category":"Serres and speciale beglazing",
    "sg:phone":"+32 52 21 41 87",
    "sg:postcode":"9200",
    "sg:province":"Oost-Vlaanderen",
    "wof:name":"Duq-glas",
    "wof:placetype":"venue"
},
  "geometry": {"coordinates":[4.0231099129,51.0087814331],"type":"Point"}
}