{
  "type": "Feature",
  "properties": {
    "iso:country":"BE",
    "sg:address":"Kloosterstraat 40",
    "sg:city":"Beringen",
    "sg:orig_category":"Advocaten and juridische adviseurs",
    "sg:phone":"+32 11 42 76 27",
    "sg:postcode":"3583",
    "sg:province":"Limburg",
    "wof:name":"Chris Huysmans",
    "wof:placetype":"venue"
},
  "geometry": {"coordinates":[5.1706700325,51.0389442444],"type":"Point"}
}