{
  "type": "Feature",
  "properties": {
    "addr:full":"Moregemplein 6 Wortegem-petegem Oost-Vlaanderen 9790",
    "addr:housenumber":"6",
    "addr:postcode":"9790",
    "addr:street":"Moregemplein",
    "iso:country":"BE",
    "sg:address":"Moregemplein 6",
    "sg:city":"Wortegem-petegem",
    "sg:classifiers":[
        {
            "category":"Restaurant",
            "type":"Food & Drink"
        }
    ],
    "sg:phone":"+32 55 30 00 20",
    "sg:postcode":"9790",
    "sg:province":"Oost-Vlaanderen",
    "wof:name":"De Vierschaar",
    "wof:placetype":"venue"
},
  "geometry": {"coordinates":[3.5615489483,50.8505172729],"type":"Point"}
}