{
  "type": "Feature",
  "properties": {
    "addr:full":"Rue De La Semois 30 Etalle Luxembourg 6741",
    "addr:housenumber":"30",
    "addr:postcode":"6741",
    "addr:street":"Rue De La Semois",
    "iso:country":"BE",
    "sg:address":"Rue De La Semois 30",
    "sg:city":"Etalle",
    "sg:orig_category":"Eleveurs and marchands de porcs",
    "sg:phone":"+32 63 45 56 58",
    "sg:postcode":"6741",
    "sg:province":"Luxembourg",
    "wof:name":"Jean-michel Chavez",
    "wof:placetype":"venue"
},
  "geometry": {"coordinates":[5.6562709808,49.6700782776],"type":"Point"}
}