{
  "type": "Feature",
  "properties": {
    "addr:full":"Rue De Tilff 81 Li\u00c8ge Li\u00e8ge 4031",
    "addr:housenumber":"81",
    "addr:postcode":"4031",
    "addr:street":"Rue De Tilff",
    "iso:country":"BE",
    "sg:address":"Rue De Tilff 81",
    "sg:city":"Li\u00c8ge",
    "sg:orig_category":"Plomberie, chauffage and installations sanitaires",
    "sg:phone":"+32 4 366 06 02",
    "sg:postcode":"4031",
    "sg:province":"Li\u00e8ge",
    "wof:name":"T. Vandermeulen",
    "wof:placetype":"venue"
},
  "geometry": {"coordinates":[5.6040058136,50.6077766418],"type":"Point"}
}