{
  "type": "Feature",
  "properties": {
    "addr:full":"Rue De La Forge 38 Aubange Luxembourg 6792",
    "addr:housenumber":"38",
    "addr:postcode":"6792",
    "addr:street":"Rue De La Forge",
    "iso:country":"BE",
    "sg:address":"Rue De La Forge 38",
    "sg:city":"Aubange",
    "sg:orig_category":"Plomberie, chauffage and installations sanitaires",
    "sg:phone":"+32 63 38 83 86",
    "sg:postcode":"6792",
    "sg:province":"Luxembourg",
    "wof:name":"Severo Serafini",
    "wof:placetype":"venue"
},
  "geometry": {"coordinates":[5.741268158,49.5594177246],"type":"Point"}
}