{
  "type": "Feature",
  "properties": {
    "addr:full":"Route De Paliseul 7 Bouillon Luxembourg 6830",
    "addr:housenumber":"7",
    "addr:postcode":"6830",
    "addr:street":"Route De Paliseul",
    "iso:country":"BE",
    "sg:address":"Route De Paliseul 7",
    "sg:city":"Bouillon",
    "sg:classifiers":[
        {
            "category":"Building & Trades",
            "subcategory":"Electrical",
            "type":"Services"
        }
    ],
    "sg:phone":"+32 61 46 77 91",
    "sg:postcode":"6830",
    "sg:province":"Luxembourg",
    "sg:tags":[
        "tool",
        "electric"
    ],
    "wof:name":"Allard & Fils Sa",
    "wof:placetype":"venue"
},
  "geometry": {"coordinates":[5.0766439438,49.7997627258],"type":"Point"}
}