{
  "type": "Feature",
  "properties": {
    "addr:full":"Stationsstraat 105 Tessenderlo Limburg 3980",
    "addr:housenumber":"105",
    "addr:postcode":"3980",
    "addr:street":"Stationsstraat",
    "iso:country":"BE",
    "sg:address":"Stationsstraat 105",
    "sg:city":"Tessenderlo",
    "sg:orig_category":"V\u00eatements",
    "sg:phone":"+32 13 67 43 86",
    "sg:postcode":"3980",
    "sg:province":"Limburg",
    "wof:name":"The Bandshop",
    "wof:placetype":"venue"
},
  "geometry": {"coordinates":[5.0969672203,51.0672111511],"type":"Point"}
}