{
  "type": "Feature",
  "properties": {
    "iso:country":"BE",
    "sg:address":"41",
    "sg:city":"Rue De La Croix-rouge 7740 Pecq",
    "sg:classifiers":[
        {
            "category":"Building & Trades",
            "subcategory":"Construction",
            "type":"Services"
        }
    ],
    "sg:phone":"+32 69 55 68 21",
    "sg:postcode":"41",
    "sg:tags":[
        "work",
        "public"
    ],
    "wof:name":"Herphelin Paul Sa",
    "wof:placetype":"venue"
},
  "geometry": {"coordinates":[3.3401150703,50.6871261597],"type":"Point"}
}