{
  "type": "Feature",
  "properties": {
    "iso:country":"BE",
    "sg:address":"Varkensmarkt 46-48",
    "sg:city":"Diepenbeek",
    "sg:classifiers":[
        {
            "category":"Insurance",
            "subcategory":"Insurance Agent",
            "type":"Services"
        }
    ],
    "sg:phone":"+32 11 32 34 31",
    "sg:postcode":"3590",
    "sg:province":"Limburg",
    "sg:tags":[
        "broker"
    ],
    "wof:name":"Voets Zakenkantoor Nv",
    "wof:placetype":"venue"
},
  "geometry": {"coordinates":[5.4171900749,50.9072189331],"type":"Point"}
}