{
  "type": "Feature",
  "properties": {
    "addr:full":"Doornstraat 0 Poperinge West-Vlaanderen 8970",
    "addr:housenumber":"0",
    "addr:postcode":"8970",
    "addr:street":"Doornstraat",
    "iso:country":"BE",
    "sg:address":"Doornstraat 0",
    "sg:city":"Poperinge",
    "sg:orig_category":"DIVERSE RECREATIEVE ACTIVITEITEN",
    "sg:phone":"+32 57 33 40 81",
    "sg:postcode":"8970",
    "sg:province":"West-Vlaanderen",
    "wof:name":"De Piepauw",
    "wof:placetype":"venue"
},
  "geometry": {"coordinates":[2.7266860008,50.857460022],"type":"Point"}
}