{
  "type": "Feature",
  "properties": {
    "addr:full":"Handelstraat 13 Landen Vlaams-Brabant 3401",
    "addr:housenumber":"13",
    "addr:postcode":"3401",
    "addr:street":"Handelstraat",
    "iso:country":"BE",
    "sg:address":"Handelstraat 13",
    "sg:city":"Landen",
    "sg:orig_category":"Enseignement maternel and primaire",
    "sg:phone":"+32 11 88 36 92",
    "sg:postcode":"3401",
    "sg:province":"Vlaams-Brabant",
    "wof:name":"Gemeentel. Kleuterschool",
    "wof:placetype":"venue"
},
  "geometry": {"coordinates":[5.0623030663,50.7288970947],"type":"Point"}
}