{
  "type": "Feature",
  "properties": {
    "iso:country":"BE",
    "sg:address":"Tervuursesteenweg 242",
    "sg:city":"Zemst (hofstade)",
    "sg:classifiers":[
        {
            "category":"Personal",
            "subcategory":"Beauty Salon",
            "type":"Services"
        }
    ],
    "sg:phone":"+32 15 61 25 62",
    "sg:postcode":"1981",
    "sg:province":"Vlaams-Brabant",
    "sg:tags":[
        "lady",
        "-",
        "hairdressing"
    ],
    "wof:name":"Guy",
    "wof:placetype":"venue"
},
  "geometry": {"coordinates":[4.4926967621,50.991268158],"type":"Point"}
}