{
  "type": "Feature",
  "properties": {
    "iso:country":"BE",
    "sg:address":"Moorstraat 0",
    "sg:city":"Nevele",
    "sg:orig_category":"Quincailleries",
    "sg:phone":"+32 9 282 77 96",
    "sg:postcode":"9850",
    "sg:province":"Oost-Vlaanderen",
    "wof:name":"Robby",
    "wof:placetype":"venue"
},
  "geometry": {"coordinates":[3.5796999931,51.0550193787],"type":"Point"}
}