{
  "type": "Feature",
  "properties": {
    "addr:full":"Lichtaartseweg 65 Olen Antwerpen 2250",
    "addr:housenumber":"65",
    "addr:postcode":"2250",
    "addr:street":"Lichtaartseweg",
    "iso:country":"BE",
    "sg:address":"Lichtaartseweg 65",
    "sg:city":"Olen",
    "sg:classifiers":[
        {
            "category":"Building & Trades",
            "subcategory":"Pest Control",
            "type":"Services"
        }
    ],
    "sg:phone":"+32 14 21 15 32",
    "sg:postcode":"2250",
    "sg:province":"Antwerpen",
    "sg:tags":[
        "painting",
        "contractor"
    ],
    "wof:name":"Meylemans Bvba",
    "wof:placetype":"venue"
},
  "geometry": {"coordinates":[4.9013881683,51.1794891357],"type":"Point"}
}