{
  "type": "Feature",
  "properties": {
    "iso:country":"BE",
    "sg:address":"Marktplein 18",
    "sg:city":"Nieuwpoort",
    "sg:classifiers":[
        {
            "category":"Bars & Pubs",
            "type":"Food & Drink"
        }
    ],
    "sg:phone":"+32 58 24 31 16",
    "sg:postcode":"8620",
    "sg:province":"West-Vlaanderen",
    "sg:tags":[
        "tavern"
    ],
    "wof:name":"de Luwte",
    "wof:placetype":"venue"
},
  "geometry": {"coordinates":[2.7516729832,51.1298103333],"type":"Point"}
}