{
  "type": "Feature",
  "properties": {
    "addr:full":"Kapelstraat 1 Ledegem West-Vlaanderen 8880",
    "addr:housenumber":"1",
    "addr:postcode":"8880",
    "addr:street":"Kapelstraat",
    "iso:country":"BE",
    "sg:address":"Kapelstraat 1",
    "sg:city":"Ledegem",
    "sg:orig_category":"Artsen and specialisten",
    "sg:phone":"+32 56 50 99 66",
    "sg:postcode":"8880",
    "sg:province":"West-Vlaanderen",
    "wof:name":"P. Vandecandelaere",
    "wof:placetype":"venue"
},
  "geometry": {"coordinates":[3.1770269871,50.8735923767],"type":"Point"}
}