{
  "type": "Feature",
  "properties": {
    "iso:country":"BE",
    "sg:address":"Weversstraat 24",
    "sg:city":"Asse",
    "sg:orig_category":"Agences de voyages",
    "sg:phone":"+32 2 453 15 35",
    "sg:postcode":"1730",
    "sg:province":"Vlaams-Brabant",
    "wof:name":"Jupiter Travel",
    "wof:placetype":"venue"
},
  "geometry": {"coordinates":[4.2024688721,50.9092178345],"type":"Point"}
}