{
  "type": "Feature",
  "properties": {
    "addr:full":"Barbeellaan 28 Oudergem/auderghem Bruxelles-Capitale 1160",
    "addr:housenumber":"28",
    "addr:postcode":"1160",
    "addr:street":"Barbeellaan;/",
    "iso:country":"BE",
    "sg:address":"Barbeellaan 28",
    "sg:city":"Oudergem/auderghem",
    "sg:orig_category":"Marktonderzoekbureaus",
    "sg:phone":"+32 2 679 01 91",
    "sg:postcode":"1160",
    "sg:province":"Bruxelles-Capitale",
    "wof:name":"T.v. Times",
    "wof:placetype":"venue"
},
  "geometry": {"coordinates":[4.4077711105,50.8129882812],"type":"Point"}
}