{
  "type": "Feature",
  "properties": {
    "addr:full":"Place Camille Lemonnier 3 La Hulpe Brabant Wallon 1310",
    "addr:housenumber":"3",
    "addr:postcode":"1310",
    "addr:street":"Place Camille Lemonnier",
    "iso:country":"BE",
    "sg:address":"Place Camille Lemonnier 3",
    "sg:city":"La Hulpe",
    "sg:classifiers":[
        {
            "category":"Cafe",
            "type":"Food & Drink"
        }
    ],
    "sg:phone":"+32 2 653 73 62",
    "sg:postcode":"1310",
    "sg:province":"Brabant Wallon",
    "sg:tags":[
        "caf\u00e9s"
    ],
    "wof:name":"Caf\u00c9 Des P\u00c9cheurs",
    "wof:placetype":"venue"
},
  "geometry": {"coordinates":[4.4931688309,50.7334060669],"type":"Point"}
}