{
  "type": "Feature",
  "properties": {
    "iso:country":"BE",
    "sg:address":"Hoogboomsteenweg 123",
    "sg:city":"Kapellen",
    "sg:classifiers":[
        {
            "category":"Cafe",
            "type":"Food & Drink"
        }
    ],
    "sg:phone":"+32 3 665 18 37",
    "sg:postcode":"2950",
    "sg:province":"Antwerpen",
    "sg:tags":[
        "caf\u00e9s"
    ],
    "wof:name":"Caf\u00c9 De Nachtwacht",
    "wof:placetype":"venue"
},
  "geometry": {"coordinates":[4.4518141747,51.3121261597],"type":"Point"}
}