{
  "type": "Feature",
  "properties": {
    "iso:country":"BE",
    "sg:address":"Venecoln 15",
    "sg:city":"Aalter",
    "sg:orig_category":"Location de v\u00e9hicules sauf voitures",
    "sg:phone":"+32 9 374 78 77",
    "sg:postcode":"9880",
    "sg:province":"Oost-Vlaanderen",
    "wof:name":"G.t.f. Latre-stevens",
    "wof:placetype":"venue"
},
  "geometry": {"coordinates":[3.4482300282,51.0872917175],"type":"Point"}
}