{
  "type": "Feature",
  "properties": {
    "addr:full":"Rue Du Mus\u00c9e 75bd Etalle Luxembourg 6743",
    "addr:housenumber":"75bd",
    "addr:postcode":"6743",
    "addr:street":"Rue Du Muse\u0301E",
    "iso:country":"BE",
    "sg:address":"Rue Du Mus\u00c9e 75bd",
    "sg:city":"Etalle",
    "sg:orig_category":"G\u00e9om\u00e8tres",
    "sg:phone":"+32 63 45 57 82",
    "sg:postcode":"6743",
    "sg:province":"Luxembourg",
    "wof:name":"Bernard Dellacherie",
    "wof:placetype":"venue"
},
  "geometry": {"coordinates":[5.5948181152,49.6454582214],"type":"Point"}
}