{
  "type": "Feature",
  "properties": {
    "addr:full":"Impestraat 35 Erpe-mere Oost-Vlaanderen 9420",
    "addr:housenumber":"35",
    "addr:postcode":"9420",
    "addr:street":"Impestraat",
    "iso:country":"BE",
    "sg:address":"Impestraat 35",
    "sg:city":"Erpe-mere",
    "sg:orig_category":"Rundveehouders",
    "sg:phone":"+32 53 80 58 71",
    "sg:postcode":"9420",
    "sg:province":"Oost-Vlaanderen",
    "wof:name":"Hubert Scheerlinck",
    "wof:placetype":"venue"
},
  "geometry": {"coordinates":[3.948071003,50.9515419006],"type":"Point"}
}