{
  "type": "Feature",
  "properties": {
    "iso:country":"BE",
    "sg:address":"R\u00c9sidence Cl\u00c9 Des Champs 73bb",
    "sg:city":"La Louviere",
    "sg:orig_category":"G\u00e9om\u00e8tres",
    "sg:phone":"+32 64 66 27 70",
    "sg:postcode":"7110",
    "sg:province":"Hainaut",
    "wof:name":"Marcel Gobert",
    "wof:placetype":"venue"
},
  "geometry": {"coordinates":[4.1930761337,50.4710083008],"type":"Point"}
}