{
  "type": "Feature",
  "properties": {
    "iso:country":"BE",
    "sg:address":"Brusselbaan 181",
    "sg:city":"Affligem (hekelgem)",
    "sg:classifiers":[
        {
            "category":"Recreation",
            "subcategory":"Dance Hall",
            "type":"Entertainment"
        }
    ],
    "sg:phone":"+32 53 41 68 50",
    "sg:postcode":"1790",
    "sg:province":"Vlaams-Brabant",
    "sg:tags":[
        "discotheque"
    ],
    "wof:name":"Kleinen Beer (den)",
    "wof:placetype":"venue"
},
  "geometry": {"coordinates":[4.1114649773,50.9127120972],"type":"Point"}
}