{
  "type": "Feature",
  "properties": {
    "addr:full":"Kruisstraat 6 Temse Oost-Vlaanderen 9140",
    "addr:housenumber":"6",
    "addr:postcode":"9140",
    "addr:street":"Kruisstraat",
    "iso:country":"BE",
    "sg:address":"Kruisstraat 6",
    "sg:city":"Temse",
    "sg:orig_category":"Production de films, t\u00e9l\u00e9films and vid\u00e9os",
    "sg:phone":"+32 3 771 51 99",
    "sg:postcode":"9140",
    "sg:province":"Oost-Vlaanderen",
    "wof:name":"Mediaservice Tv",
    "wof:placetype":"venue"
},
  "geometry": {"coordinates":[4.2256808281,51.1353721619],"type":"Point"}
}