{
  "type": "Feature",
  "properties": {
    "addr:full":"Rue Du Bois Des R\u00c2ves 66 La Louviere Hainaut 7110",
    "addr:housenumber":"66",
    "addr:postcode":"7110",
    "addr:street":"Rue Du Bois Des Ra\u0302Ves",
    "iso:country":"BE",
    "sg:address":"Rue Du Bois Des R\u00c2ves 66",
    "sg:city":"La Louviere",
    "sg:orig_category":"Artsen and specialisten",
    "sg:phone":"+32 64 28 17 60",
    "sg:postcode":"7110",
    "sg:province":"Hainaut",
    "wof:name":"Jean-paul G\u00c9rardy",
    "wof:placetype":"venue"
},
  "geometry": {"coordinates":[4.1505050659,50.4826698303],"type":"Point"}
}