{
  "type": "Feature",
  "properties": {
    "addr:full":"Steenweg Op Jette 450 Jette/jette Bruxelles-Capitale 1090",
    "addr:housenumber":"450",
    "addr:postcode":"1090",
    "addr:street":"Steenweg Op Jette",
    "iso:country":"BE",
    "sg:address":"Steenweg Op Jette 450",
    "sg:city":"Jette/jette",
    "sg:orig_category":"Boekbinderijen and afwerking",
    "sg:phone":"+32 2 425 28 93",
    "sg:postcode":"1090",
    "sg:province":"Bruxelles-Capitale",
    "wof:name":"Brochage Vande Velde P.",
    "wof:placetype":"venue"
},
  "geometry": {"coordinates":[4.3286027908,50.8684043884],"type":"Point"}
}