{
  "type": "Feature",
  "properties": {
    "addr:full":"Rozenstraat 107 Wevelgem (moorsele) West-Vlaanderen 8560",
    "addr:housenumber":"107",
    "addr:postcode":"8560",
    "addr:street":"Rozenstraat",
    "iso:country":"BE",
    "sg:address":"Rozenstraat 107",
    "sg:city":"Wevelgem (moorsele)",
    "sg:classifiers":[
        {
            "category":"Banks & Credit Unions",
            "subcategory":"Investment Brokerage",
            "type":"Services"
        }
    ],
    "sg:phone":"+32 56 41 83 59",
    "sg:postcode":"8560",
    "sg:province":"West-Vlaanderen",
    "sg:tags":[
        "repair",
        "-",
        "installation",
        "sanitary",
        "article"
    ],
    "wof:name":"Acke-noppe Bvba",
    "wof:placetype":"venue"
},
  "geometry": {"coordinates":[3.1704421043,50.8431053162],"type":"Point"}
}