{
  "type": "Feature",
  "properties": {
    "iso:country":"BE",
    "sg:address":"Rue L Van Beethoven 37",
    "sg:city":"Anderlecht",
    "sg:orig_category":"Blanchisseries and teintureries",
    "sg:phone":"+32 2 523 74 37",
    "sg:postcode":"1070",
    "sg:province":"Bruxelles-Capitale",
    "wof:name":"Washcenter Beethoven",
    "wof:placetype":"venue"
},
  "geometry": {"coordinates":[4.2977142334,50.8297996521],"type":"Point"}
}