{
  "type": "Feature",
  "properties": {
    "iso:country":"BE",
    "sg:address":"Heiken 86a",
    "sg:city":"Brecht (sint-lenaarts)",
    "sg:orig_category":"Non-Classified Establishments",
    "sg:phone":"+32 3 313 74 30",
    "sg:postcode":"2960",
    "sg:province":"Antwerpen",
    "wof:name":"Konings-event Service Bvba",
    "wof:placetype":"venue"
},
  "geometry": {"coordinates":[4.5586080551,51.300163269],"type":"Point"}
}