{
  "type": "Feature",
  "properties": {
    "addr:full":"Kloosterstraat 95 Zedelgem West-Vlaanderen 8210",
    "addr:housenumber":"95",
    "addr:postcode":"8210",
    "addr:street":"Kloosterstraat",
    "iso:country":"BE",
    "sg:address":"Kloosterstraat 95",
    "sg:city":"Zedelgem",
    "sg:orig_category":"Sportclubs",
    "sg:phone":"+32 50 27 50 34",
    "sg:postcode":"8210",
    "sg:province":"West-Vlaanderen",
    "wof:name":"Wandelcl. Vier Op Een Rij",
    "wof:placetype":"venue"
},
  "geometry": {"coordinates":[3.1458399296,51.1376457214],"type":"Point"}
}