{
  "type": "Feature",
  "properties": {
    "iso:country":"BE",
    "sg:address":"Rue De L'etang 27",
    "sg:city":"Aubange (halanzy)",
    "sg:classifiers":[
        {
            "category":"Health Services",
            "subcategory":"Doctor",
            "type":"Services"
        }
    ],
    "sg:phone":"+32 63 38 52 54",
    "sg:postcode":"6792",
    "sg:province":"Luxembourg",
    "sg:tags":[
        "medicinephysicians",
        "surgeon"
    ],
    "wof:name":"Lippens Nathalie",
    "wof:placetype":"venue"
},
  "geometry": {"coordinates":[5.751229763,49.5752716064],"type":"Point"}
}