{
  "type": "Feature",
  "properties": {
    "iso:country":"BE",
    "sg:address":"Rommelsweg 59",
    "sg:city":"Sint-laureins",
    "sg:orig_category":"Activit\u00e9s diverses d'imprimerie",
    "sg:phone":"+32 9 379 00 94",
    "sg:postcode":"9980",
    "sg:province":"Oost-Vlaanderen",
    "wof:name":"Grietje Schelstraete",
    "wof:placetype":"venue"
},
  "geometry": {"coordinates":[3.5258100033,51.238571167],"type":"Point"}
}