{
  "type": "Feature",
  "properties": {
    "addr:full":"Troonstraat 218 Elsene/ixelles Bruxelles-Capitale 1050",
    "addr:housenumber":"218",
    "addr:postcode":"1050",
    "addr:street":"Troonstraat",
    "iso:country":"BE",
    "sg:address":"Troonstraat 218",
    "sg:city":"Elsene/ixelles",
    "sg:orig_category":"Hoger onderwijs",
    "sg:phone":"+32 2 649 14 47",
    "sg:postcode":"1050",
    "sg:province":"Bruxelles-Capitale",
    "wof:name":"I.s.c.a.m.",
    "wof:placetype":"venue"
},
  "geometry": {"coordinates":[4.3744091988,50.8336257935],"type":"Point"}
}