{
  "type": "Feature",
  "properties": {
    "addr:full":"Rue Des Urbanistes 5 Li\u00c8ge Li\u00e8ge 4000",
    "addr:housenumber":"5",
    "addr:postcode":"4000",
    "addr:street":"Rue Des Urbanistes",
    "iso:country":"BE",
    "sg:address":"Rue Des Urbanistes 5",
    "sg:city":"Li\u00c8ge",
    "sg:classifiers":[
        {
            "category":"Insurance",
            "subcategory":"Life Insurance",
            "type":"Services"
        }
    ],
    "sg:phone":"+32 4 343 72 62",
    "sg:postcode":"4000",
    "sg:province":"Li\u00e8ge",
    "sg:tags":[
        "assurance"
    ],
    "wof:name":"Alderson D.",
    "wof:placetype":"venue"
},
  "geometry": {"coordinates":[5.5665287971,50.641002655],"type":"Point"}
}