{
  "type": "Feature",
  "properties": {
    "addr:full":"Schotelven 89 Arendonk Antwerpen 2370",
    "addr:housenumber":"89",
    "addr:postcode":"2370",
    "addr:street":"Schotelven",
    "iso:country":"BE",
    "sg:address":"Schotelven 89",
    "sg:city":"Arendonk",
    "sg:orig_category":"Antiquit\u00e9s",
    "sg:phone":"+32 14 67 18 38",
    "sg:postcode":"2370",
    "sg:province":"Antwerpen",
    "wof:name":"Jean-philippe Lepsch",
    "wof:placetype":"venue"
},
  "geometry": {"coordinates":[5.0582900047,51.3143501282],"type":"Point"}
}