{
  "type": "Feature",
  "properties": {
    "iso:country":"BE",
    "sg:address":"Rue Xhav\u00e9e 70",
    "sg:city":"Verviers",
    "sg:classifiers":[
        {
            "category":"Shopping",
            "subcategory":"Crafts & Fabrics",
            "type":"Retail Goods"
        }
    ],
    "sg:phone":"+32 87 33 95 10",
    "sg:postcode":"4800",
    "sg:province":"Li\u00e8ge",
    "sg:tags":[
        "ceramic"
    ],
    "wof:name":"Kairis G",
    "wof:placetype":"venue"
},
  "geometry": {"coordinates":[5.8584008217,50.5911979675],"type":"Point"}
}