{
  "type": "Feature",
  "properties": {
    "addr:full":"Rue Colonel Chaltin 32bte 17 Bruxelles Bruxelles-Capitale 1180",
    "addr:housenumber":"32bte 17",
    "addr:postcode":"1180",
    "addr:street":"Rue Colonel Chaltin",
    "iso:country":"BE",
    "sg:address":"Rue Colonel Chaltin 32bte 17",
    "sg:city":"Bruxelles",
    "sg:classifiers":[
        {
            "category":"Shopping",
            "subcategory":"Pharmacy",
            "type":"Retail Goods"
        }
    ],
    "sg:phone":"+32 2 375 47 66",
    "sg:postcode":"1180",
    "sg:province":"Bruxelles-Capitale",
    "sg:tags":[
        "preparation",
        "pharmaceutical"
    ],
    "wof:name":"Texital S.p.r.l.",
    "wof:placetype":"venue"
},
  "geometry": {"coordinates":[4.3430500031,50.7971153259],"type":"Point"}
}