{
  "type": "Feature",
  "properties": {
    "addr:full":"Steenweg Op Tielen 43 Turnhout Antwerpen 2300",
    "addr:housenumber":"43",
    "addr:postcode":"2300",
    "addr:street":"Steenweg Op Tielen",
    "iso:country":"BE",
    "sg:address":"Steenweg Op Tielen 43",
    "sg:city":"Turnhout",
    "sg:classifiers":[
        {
            "category":"Arena",
            "subcategory":"Sports Club",
            "type":"Entertainment"
        }
    ],
    "sg:phone":"+32 14 43 02 83",
    "sg:postcode":"2300",
    "sg:province":"Antwerpen",
    "wof:name":"Taxandria (tennisclub)",
    "wof:placetype":"venue"
},
  "geometry": {"coordinates":[4.9356322289,51.3041725159],"type":"Point"}
}