{
  "type": "Feature",
  "properties": {
    "addr:full":"Avenue Du Derby 4 Elsene/ixelles Bruxelles-Capitale 1050",
    "addr:housenumber":"4",
    "addr:postcode":"1050",
    "addr:street":"Avenue Du Derby",
    "iso:country":"BE",
    "sg:address":"Avenue Du Derby 4",
    "sg:city":"Elsene/ixelles",
    "sg:orig_category":"M\u00e9decins and sp\u00e9cialistes",
    "sg:phone":"+32 2 647 96 04",
    "sg:postcode":"1050",
    "sg:province":"Bruxelles-Capitale",
    "wof:name":"Samuel Levi",
    "wof:placetype":"venue"
},
  "geometry": {"coordinates":[4.388212204,50.805606842],"type":"Point"}
}