{
  "type": "Feature",
  "properties": {
    "addr:full":"Hazelarenlaan 52 Hasselt Limburg 3500",
    "addr:housenumber":"52",
    "addr:postcode":"3500",
    "addr:street":"Hazelarenlaan",
    "iso:country":"BE",
    "sg:address":"Hazelarenlaan 52",
    "sg:city":"Hasselt",
    "sg:classifiers":[
        {
            "category":"Transit Center",
            "subcategory":"Passenger",
            "type":"Transportation"
        }
    ],
    "sg:phone":"+32 11 24 11 40",
    "sg:postcode":"3500",
    "sg:province":"Limburg",
    "sg:tags":[
        "recorder",
        "time"
    ],
    "wof:name":"Standalone Time Systems",
    "wof:placetype":"venue"
},
  "geometry": {"coordinates":[5.3548932076,50.9455184937],"type":"Point"}
}