{
  "type": "Feature",
  "properties": {
    "iso:country":"BE",
    "sg:address":"Beukendreef 63",
    "sg:city":"Aalst",
    "sg:orig_category":"Kapsalons",
    "sg:phone":"+32 53 77 15 57",
    "sg:postcode":"9300",
    "sg:province":"Oost-Vlaanderen",
    "wof:name":"Coiffure Lucienne",
    "wof:placetype":"venue"
},
  "geometry": {"coordinates":[4.0610032082,50.933921814],"type":"Point"}
}