{
  "type": "Feature",
  "properties": {
    "addr:full":"Place Des Trieux 13 Cerfontaine (daussois) Namur 5630",
    "addr:housenumber":"13",
    "addr:postcode":"5630",
    "addr:street":"Place Des Trieux",
    "iso:country":"BE",
    "sg:address":"Place Des Trieux 13",
    "sg:city":"Cerfontaine (daussois)",
    "sg:classifiers":[
        {
            "category":"Health Services",
            "subcategory":"Doctor",
            "type":"Services"
        }
    ],
    "sg:phone":"+32 71 61 15 31",
    "sg:postcode":"5630",
    "sg:province":"Namur",
    "sg:tags":[
        "medicinephysicians",
        "surgeon"
    ],
    "wof:name":"Hody Jean-marc",
    "wof:placetype":"venue"
},
  "geometry": {"coordinates":[4.4591908455,50.2195358276],"type":"Point"}
}