{
  "type": "Feature",
  "properties": {
    "iso:country":"BE",
    "sg:address":"Reigerlostraat 15",
    "sg:city":"Beernem",
    "sg:classifiers":[
        {
            "category":"Banks & Credit Unions",
            "subcategory":"Bank",
            "type":"Services"
        }
    ],
    "sg:phone":"+32 50 78 84 59",
    "sg:postcode":"8730",
    "sg:province":"West-Vlaanderen",
    "sg:tags":[
        "savings-banks"
    ],
    "wof:name":"Sierens R",
    "wof:placetype":"venue"
},
  "geometry": {"coordinates":[3.3222990036,51.1184120178],"type":"Point"}
}