{
  "type": "Feature",
  "properties": {
    "iso:country":"BE",
    "sg:address":"Schoterweg 236",
    "sg:city":"Tessenderlo",
    "sg:classifiers":[
        {
            "category":"Manufacturing",
            "subcategory":"Textiles",
            "type":"Manufacturing & Wholesale Goods"
        }
    ],
    "sg:phone":"+32 13 66 11 18",
    "sg:postcode":"3980",
    "sg:province":"Limburg",
    "sg:tags":[
        "retail",
        "-"
    ],
    "wof:name":"Camps M",
    "wof:placetype":"venue"
},
  "geometry": {"coordinates":[5.0565400124,51.0672416687],"type":"Point"}
}