{
  "type": "Feature",
  "properties": {
    "iso:country":"BE",
    "sg:address":"Preterstraat 7",
    "sg:city":"Rotselaar",
    "sg:orig_category":"Producteurs de l\u00e9gumes",
    "sg:phone":"+32 16 53 10 54",
    "sg:postcode":"3118",
    "sg:province":"Vlaams-Brabant",
    "wof:name":"Wim Van Espen",
    "wof:placetype":"venue"
},
  "geometry": {"coordinates":[4.6940898895,50.970489502],"type":"Point"}
}