{
  "type": "Feature",
  "properties": {
    "iso:country":"BE",
    "sg:address":"Lange Zoutstraat 10",
    "sg:city":"Aalst",
    "sg:orig_category":"Bagage and lederwaren Dameskledingzaken Herenkledingzaken Schoenen",
    "sg:phone":"+32 53 78 52 33",
    "sg:postcode":"9300",
    "sg:province":"Oost-Vlaanderen",
    "wof:name":"The Buffalo Shoe",
    "wof:placetype":"venue"
},
  "geometry": {"coordinates":[4.0394659042,50.9378433228],"type":"Point"}
}