{
  "type": "Feature",
  "properties": {
    "addr:full":"Montgomerystraat 22 Edingen/enghien Hainaut 7850",
    "addr:housenumber":"22",
    "addr:postcode":"7850",
    "addr:street":"Montgomerystraat",
    "iso:country":"BE",
    "sg:address":"Montgomerystraat 22",
    "sg:city":"Edingen/enghien",
    "sg:orig_category":"Schoonheidssalons",
    "sg:phone":"+32 2 395 72 22",
    "sg:postcode":"7850",
    "sg:province":"Hainaut",
    "wof:name":"Le Jardin De Marie",
    "wof:placetype":"venue"
},
  "geometry": {"coordinates":[4.0375170708,50.6929664612],"type":"Point"}
}