{
  "type": "Feature",
  "properties": {
    "iso:country":"BE",
    "sg:address":"Rue Emile Cuvelier 11",
    "sg:city":"Namur",
    "sg:orig_category":"Huishoudapparaten, televisies and radio's",
    "sg:phone":"+32 81 22 16 09",
    "sg:postcode":"5000",
    "sg:province":"Namur",
    "wof:name":"Hi-fi Vid\u00c9o Namur",
    "wof:placetype":"venue"
},
  "geometry": {"coordinates":[4.8674798012,50.4640007019],"type":"Point"}
}