{
  "type": "Feature",
  "properties": {
    "iso:country":"BE",
    "sg:address":"Rue Du Coq D'aousse 7",
    "sg:city":"Thuin",
    "sg:orig_category":"Installatie van houten of kunststof schrijnwerk",
    "sg:phone":"+32 71 59 03 47",
    "sg:postcode":"6530",
    "sg:province":"Hainaut",
    "wof:name":"Bury Fr\u00c8res",
    "wof:placetype":"venue"
},
  "geometry": {"coordinates":[4.2463340759,50.3030395508],"type":"Point"}
}