{
  "type": "Feature",
  "properties": {
    "iso:country":"BE",
    "sg:address":"Frans Van Kalkenlaan 3b33",
    "sg:city":"Anderlecht/anderlecht",
    "sg:orig_category":"Sportclubs",
    "sg:phone":"+32 2 520 95 09",
    "sg:postcode":"1070",
    "sg:province":"Bruxelles-Capitale",
    "wof:name":"Petanque Forestoise",
    "wof:placetype":"venue"
},
  "geometry": {"coordinates":[4.3045191765,50.8274002075],"type":"Point"}
}