{
  "type": "Feature",
  "properties": {
    "iso:country":"BE",
    "sg:address":"Gistelsteenweg 218a",
    "sg:city":"Jabbeke",
    "sg:classifiers":[
        {
            "category":"Shopping",
            "subcategory":"Florist",
            "type":"Retail Goods"
        }
    ],
    "sg:phone":"+32 50 81 11 56",
    "sg:postcode":"8490",
    "sg:province":"West-Vlaanderen",
    "wof:name":"Vandevelde's Bloemenparadijs",
    "wof:placetype":"venue"
},
  "geometry": {"coordinates":[3.1105320454,51.1793174744],"type":"Point"}
}