{
  "type": "Feature",
  "properties": {
    "iso:country":"BE",
    "sg:address":"Rue De Huy 2",
    "sg:city":"Burdinne",
    "sg:orig_category":"Boucheries",
    "sg:phone":"+32 85 71 32 11",
    "sg:postcode":"4210",
    "sg:province":"Li\u00e8ge",
    "wof:name":"Christian Bertrand",
    "wof:placetype":"venue"
},
  "geometry": {"coordinates":[5.0731258392,50.5833244324],"type":"Point"}
}