{
  "type": "Feature",
  "properties": {
    "addr:full":"Rue Du P\u00c2quier 0 Li\u00c8ge Li\u00e8ge 4020",
    "addr:housenumber":"0",
    "addr:postcode":"4020",
    "addr:street":"Rue Du Pa\u0302Quier",
    "iso:country":"BE",
    "sg:address":"Rue Du P\u00c2quier 0",
    "sg:city":"Li\u00c8ge",
    "sg:orig_category":"Installatie van houten of kunststof schrijnwerk",
    "sg:phone":"+32 4 343 55 01",
    "sg:postcode":"4020",
    "sg:province":"Li\u00e8ge",
    "wof:name":"Giesbers",
    "wof:placetype":"venue"
},
  "geometry": {"coordinates":[5.5816311836,50.6432113647],"type":"Point"}
}