{
  "type": "Feature",
  "properties": {
    "iso:country":"BE",
    "sg:address":"Markt 7",
    "sg:city":"Oudenaarde",
    "sg:classifiers":[
        {
            "category":"Bars & Pubs",
            "type":"Food & Drink"
        }
    ],
    "sg:phone":"+32 55 23 94 56",
    "sg:postcode":"9700",
    "sg:province":"Oost-Vlaanderen",
    "wof:name":"Gelijk ('t)",
    "wof:placetype":"venue"
},
  "geometry": {"coordinates":[3.6045689583,50.8435211182],"type":"Point"}
}