{
  "type": "Feature",
  "properties": {
    "iso:country":"BE",
    "sg:address":"Avenue De La G\u00c9ronst\u00c8re 86",
    "sg:city":"Spa",
    "sg:orig_category":"Epuration des eaux",
    "sg:phone":"+32 80 78 65 12",
    "sg:postcode":"4900",
    "sg:province":"Li\u00e8ge",
    "wof:name":"Hydrotop",
    "wof:placetype":"venue"
},
  "geometry": {"coordinates":[5.8712658882,50.4815254211],"type":"Point"}
}