{
  "type": "Feature",
  "properties": {
    "iso:country":"BE",
    "sg:address":"Statielei 26",
    "sg:city":"Mortsel",
    "sg:classifiers":[
        {
            "category":"Shopping",
            "subcategory":"Shoes",
            "type":"Retail Goods"
        }
    ],
    "sg:phone":"+32 3 449 85 91",
    "sg:postcode":"2640",
    "sg:province":"Antwerpen",
    "sg:tags":[
        "slipper",
        "-"
    ],
    "wof:name":"Krien",
    "wof:placetype":"venue"
},
  "geometry": {"coordinates":[4.452188015,51.1703605652],"type":"Point"}
}