{
  "type": "Feature",
  "properties": {
    "iso:country":"BE",
    "sg:address":"Rue Du Molinay 107",
    "sg:city":"Seraing",
    "sg:orig_category":"Medische and orthopedische apparaten Schoenen",
    "sg:phone":"+32 4 337 35 93",
    "sg:postcode":"4100",
    "sg:province":"Li\u00e8ge",
    "wof:name":"A.c.s. Orthotec",
    "wof:placetype":"venue"
},
  "geometry": {"coordinates":[5.5145587921,50.6066055298],"type":"Point"}
}