{
  "type": "Feature",
  "properties": {
    "addr:full":"Evangeliestraat 63 Hamme Oost-Vlaanderen 9220",
    "addr:housenumber":"63",
    "addr:postcode":"9220",
    "addr:street":"Evangeliestraat",
    "iso:country":"BE",
    "sg:address":"Evangeliestraat 63",
    "sg:city":"Hamme",
    "sg:orig_category":"Entretien and r\u00e9parations de voitures",
    "sg:phone":"+32 52 47 70 52",
    "sg:postcode":"9220",
    "sg:province":"Oost-Vlaanderen",
    "wof:name":"Marc Philips",
    "wof:placetype":"venue"
},
  "geometry": {"coordinates":[4.1231760979,51.0952301025],"type":"Point"}
}