{
  "type": "Feature",
  "properties": {
    "addr:full":"Markt 12 Meulebeke West-Vlaanderen 8760",
    "addr:housenumber":"12",
    "addr:postcode":"8760",
    "addr:street":"Markt",
    "iso:country":"BE",
    "sg:address":"Markt 12",
    "sg:city":"Meulebeke",
    "sg:orig_category":"Banques and organismes de cr\u00e9dit",
    "sg:phone":"+32 51 48 79 41",
    "sg:postcode":"8760",
    "sg:province":"West-Vlaanderen",
    "wof:name":"Mercator Bank",
    "wof:placetype":"venue"
},
  "geometry": {"coordinates":[3.2887279987,50.9503860474],"type":"Point"}
}