{
  "type": "Feature",
  "properties": {
    "iso:country":"BE",
    "sg:address":"Rue Notre-dame 10",
    "sg:city":"Binche",
    "sg:classifiers":[
        {
            "category":"Communications",
            "subcategory":"Film & Video Production",
            "type":"Services"
        }
    ],
    "sg:phone":"+32 64 36 62 32",
    "sg:postcode":"7130",
    "sg:province":"Hainaut",
    "sg:tags":[
        "verhuur",
        "cassette",
        "audio",
        "platen",
        "cd's"
    ],
    "wof:name":"Vid\u00c9o D.r.",
    "wof:placetype":"venue"
},
  "geometry": {"coordinates":[4.1655840874,50.4113807678],"type":"Point"}
}