{
  "type": "Feature",
  "properties": {
    "addr:full":"Rue Louis Hap 194 Bruxelles (etterbeek) Bruxelles-Capitale 1040",
    "addr:housenumber":"194",
    "addr:postcode":"1040",
    "addr:street":"Rue Louis Hap",
    "iso:country":"BE",
    "sg:address":"Rue Louis Hap 194",
    "sg:city":"Bruxelles (etterbeek)",
    "sg:classifiers":[
        {
            "category":"Health Services",
            "subcategory":"Doctor",
            "type":"Services"
        }
    ],
    "sg:phone":"+32 2 732 39 45",
    "sg:postcode":"1040",
    "sg:province":"Bruxelles-Capitale",
    "sg:tags":[
        "medicinephysicians",
        "surgeon"
    ],
    "wof:name":"Lenaerts Ph",
    "wof:placetype":"venue"
},
  "geometry": {"coordinates":[4.3932862282,50.8366622925],"type":"Point"}
}