{
  "type": "Feature",
  "properties": {
    "addr:full":"Ruyterhoekstraat 23 Kortemark West-Vlaanderen 8610",
    "addr:housenumber":"23",
    "addr:postcode":"8610",
    "addr:street":"Ruyterhoekstraat",
    "iso:country":"BE",
    "sg:address":"Ruyterhoekstraat 23",
    "sg:city":"Kortemark",
    "sg:classifiers":[
        {
            "category":"Cafe",
            "type":"Food & Drink"
        }
    ],
    "sg:phone":"+32 51 57 13 15",
    "sg:postcode":"8610",
    "sg:province":"West-Vlaanderen",
    "sg:tags":[
        "caf\u00e9s"
    ],
    "wof:name":"Caf\u00c9 Den Hert",
    "wof:placetype":"venue"
},
  "geometry": {"coordinates":[2.9401550293,51.0063095093],"type":"Point"}
}