{
  "type": "Feature",
  "properties": {
    "addr:full":"Lodewijk De Raetstraat 36 Lommel Limburg 3920",
    "addr:housenumber":"36",
    "addr:postcode":"3920",
    "addr:street":"Lodewijk De Raetstraat",
    "iso:country":"BE",
    "sg:address":"Lodewijk De Raetstraat 36",
    "sg:city":"Lommel",
    "sg:orig_category":"D\u00e9taillants en pi\u00e8ces and accessoires de voitures",
    "sg:phone":"+32 11 54 58 56",
    "sg:postcode":"3920",
    "sg:province":"Limburg",
    "wof:name":"Bandencentrale Largo",
    "wof:placetype":"venue"
},
  "geometry": {"coordinates":[5.2788729668,51.2200241089],"type":"Point"}
}