{
  "type": "Feature",
  "properties": {
    "addr:full":"Rue De Grand-rechain 7 Verviers Li\u00e8ge 4800",
    "addr:housenumber":"7",
    "addr:postcode":"4800",
    "addr:street":"Rue De Grand-Rechain",
    "iso:country":"BE",
    "sg:address":"Rue De Grand-rechain 7",
    "sg:city":"Verviers",
    "sg:orig_category":"Elektrische installaties voor woningen Loodgieterij, verwarming and sanitaire installaties",
    "sg:phone":"+32 87 33 18 16",
    "sg:postcode":"4800",
    "sg:province":"Li\u00e8ge",
    "wof:name":"Alix Denis",
    "wof:placetype":"venue"
},
  "geometry": {"coordinates":[5.8315849304,50.6126976013],"type":"Point"}
}