{
  "type": "Feature",
  "properties": {
    "addr:full":"Papenstraat 11 Linter (neerlinter) Vlaams-Brabant 3350",
    "addr:housenumber":"11",
    "addr:postcode":"3350",
    "addr:street":"Papenstraat",
    "iso:country":"BE",
    "sg:address":"Papenstraat 11",
    "sg:city":"Linter (neerlinter)",
    "sg:classifiers":[
        {
            "category":"Banks & Credit Unions",
            "subcategory":"Investment Brokerage",
            "type":"Services"
        }
    ],
    "sg:phone":"+32 2 774 91 11",
    "sg:postcode":"3350",
    "sg:province":"Vlaams-Brabant",
    "sg:tags":[
        "auditor"
    ],
    "wof:name":"Weymeersch C",
    "wof:placetype":"venue"
},
  "geometry": {"coordinates":[5.0643911362,50.8061676025],"type":"Point"}
}