{
  "type": "Feature",
  "properties": {
    "iso:country":"BE",
    "sg:address":"Chauss\u00c9e De Marche 20",
    "sg:city":"Seneffe",
    "sg:orig_category":"Salles de conf\u00e9rences and de r\u00e9ceptions",
    "sg:phone":"+32 67 87 90 29",
    "sg:postcode":"7181",
    "sg:province":"Hainaut",
    "wof:name":"Ch\u00c2teau De Miremont",
    "wof:placetype":"venue"
},
  "geometry": {"coordinates":[4.2380971909,50.561630249],"type":"Point"}
}