{
  "type": "Feature",
  "properties": {
    "addr:full":"Lindenlaan 38 Beerse Antwerpen 2340",
    "addr:housenumber":"38",
    "addr:postcode":"2340",
    "addr:street":"Lindenlaan",
    "iso:country":"BE",
    "sg:address":"Lindenlaan 38",
    "sg:city":"Beerse",
    "sg:classifiers":[
        {
            "category":"Shopping",
            "subcategory":"Clothing, Apparel, & Fashions",
            "type":"Retail Goods"
        }
    ],
    "sg:phone":"+32 14 61 51 05",
    "sg:postcode":"2340",
    "sg:province":"Antwerpen",
    "sg:tags":[
        "boutique"
    ],
    "wof:name":"Jump",
    "wof:placetype":"venue"
},
  "geometry": {"coordinates":[4.85227108,51.3193130493],"type":"Point"}
}