{
  "type": "Feature",
  "properties": {
    "addr:full":"Moulin De Payenne 23 Houyet Namur 5562",
    "addr:housenumber":"23",
    "addr:postcode":"5562",
    "addr:street":"Moulin De Payenne",
    "iso:country":"BE",
    "sg:address":"Moulin De Payenne 23",
    "sg:city":"Houyet",
    "sg:classifiers":[
        {
            "category":"Travel",
            "subcategory":"Hotels & Motels",
            "type":"Entertainment"
        }
    ],
    "sg:phone":"+32 82 66 63 54",
    "sg:postcode":"5562",
    "sg:province":"Namur",
    "sg:tags":[
        "restaurant"
    ],
    "wof:name":"Hostellerie Les Grisons",
    "wof:placetype":"venue"
},
  "geometry": {"coordinates":[5.028632164,50.2086982727],"type":"Point"}
}