{
  "type": "Feature",
  "properties": {
    "addr:full":"Dorpsstraat 34 Zonhoven Limburg 3520",
    "addr:housenumber":"34",
    "addr:postcode":"3520",
    "addr:street":"Dorpsstraat",
    "iso:country":"BE",
    "sg:address":"Dorpsstraat 34",
    "sg:city":"Zonhoven",
    "sg:classifiers":[
        {
            "category":"Food & Beverages",
            "subcategory":"Candy",
            "type":"Retail Goods"
        }
    ],
    "sg:phone":"+32 11 81 81 33",
    "sg:postcode":"3520",
    "sg:province":"Limburg",
    "wof:name":"Elise Confiserie",
    "wof:placetype":"venue"
},
  "geometry": {"coordinates":[5.3684949875,50.9925117493],"type":"Point"}
}