{
  "type": "Feature",
  "properties": {
    "iso:country":"BE",
    "sg:address":"Rue Pourri Pont 276",
    "sg:city":"Ohey (haillot)",
    "sg:classifiers":[
        {
            "category":"Home & Garden",
            "subcategory":"Hardware",
            "type":"Retail Goods"
        }
    ],
    "sg:phone":"+32 4 349 48 79",
    "sg:postcode":"5351",
    "sg:province":"Namur",
    "sg:tags":[
        "gate",
        "opener",
        "door",
        "automatic"
    ],
    "wof:name":"Applications - Acces - Automatiques",
    "wof:placetype":"venue"
},
  "geometry": {"coordinates":[5.1297850609,50.458316803],"type":"Point"}
}