{
  "type": "Feature",
  "properties": {
    "addr:full":"Avenue Notre-dame 91 Evere Bruxelles-Capitale 1140",
    "addr:housenumber":"91",
    "addr:postcode":"1140",
    "addr:street":"Avenue Notre-Dame",
    "iso:country":"BE",
    "sg:address":"Avenue Notre-dame 91",
    "sg:city":"Evere",
    "sg:orig_category":"Supermarch\u00e9s",
    "sg:phone":"+32 2 245 34 18",
    "sg:postcode":"1140",
    "sg:province":"Bruxelles-Capitale",
    "wof:name":"Gema",
    "wof:placetype":"venue"
},
  "geometry": {"coordinates":[4.3993639946,50.8711471558],"type":"Point"}
}