{
  "type": "Feature",
  "properties": {
    "addr:full":"Rue Du Domaine De Waroux 5 Awans Li\u00e8ge 4340",
    "addr:housenumber":"5",
    "addr:postcode":"4340",
    "addr:street":"Rue Du Domaine De Waroux",
    "iso:country":"BE",
    "sg:address":"Rue Du Domaine De Waroux 5",
    "sg:city":"Awans",
    "sg:orig_category":"Sportclubs",
    "sg:phone":"+32 4 246 32 61",
    "sg:postcode":"4340",
    "sg:province":"Li\u00e8ge",
    "wof:name":"La Savate Alleuroise",
    "wof:placetype":"venue"
},
  "geometry": {"coordinates":[5.484459877,50.67552948],"type":"Point"}
}