{
  "type": "Feature",
  "properties": {
    "addr:full":"Korte Gasthuisstraat 1 Turnhout Antwerpen 2300",
    "addr:housenumber":"1",
    "addr:postcode":"2300",
    "addr:street":"Korte Gasthuisstraat",
    "iso:country":"BE",
    "sg:address":"Korte Gasthuisstraat 1",
    "sg:city":"Turnhout",
    "sg:classifiers":[
        {
            "category":"Professional",
            "subcategory":"Art Services",
            "type":"Services"
        }
    ],
    "sg:phone":"+32 14 41 37 35",
    "sg:postcode":"2300",
    "sg:province":"Antwerpen",
    "sg:tags":[
        "model",
        "manufacturer"
    ],
    "wof:name":"Christiaensen",
    "wof:placetype":"venue"
},
  "geometry": {"coordinates":[4.9478998184,51.3222808838],"type":"Point"}
}