{
  "type": "Feature",
  "properties": {
    "addr:full":"Rue D'ormont 26a Tournai (kain) Hainaut 7540",
    "addr:housenumber":"26a",
    "addr:postcode":"7540",
    "addr:street":"Rue D'Ormont",
    "iso:country":"BE",
    "sg:address":"Rue D'ormont 26a",
    "sg:city":"Tournai (kain)",
    "sg:classifiers":[
        {
            "category":"Professional",
            "subcategory":"Accounting & Tax Preparation",
            "type":"Services"
        }
    ],
    "sg:phone":"+32 69 22 11 46",
    "sg:postcode":"7540",
    "sg:province":"Hainaut",
    "sg:tags":[
        "bookkeeper"
    ],
    "wof:name":"Collie S",
    "wof:placetype":"venue"
},
  "geometry": {"coordinates":[3.3704679012,50.6353225708],"type":"Point"}
}