{
  "type": "Feature",
  "properties": {
    "iso:country":"BE",
    "sg:address":"Itterbeekse Laan 159",
    "sg:city":"Anderlecht",
    "sg:orig_category":"Kapsalons",
    "sg:phone":"+32 2 521 86 94",
    "sg:postcode":"1070",
    "sg:province":"Bruxelles-Capitale",
    "wof:name":"Nicole",
    "wof:placetype":"venue"
},
  "geometry": {"coordinates":[4.2907919884,50.8350257874],"type":"Point"}
}