{
  "type": "Feature",
  "properties": {
    "iso:country":"BE",
    "sg:address":"Av W.-a-mozart 1a",
    "sg:city":"Drogenbos",
    "sg:classifiers":[
        {
            "category":"Professional",
            "subcategory":"Engineering",
            "type":"Services"
        }
    ],
    "sg:phone":"+32 2 331 22 66",
    "sg:postcode":"1620",
    "sg:province":"Vlaams-Brabant",
    "sg:tags":[
        "machine",
        "-",
        "mechanical"
    ],
    "wof:name":"Mts Benelux Sa",
    "wof:placetype":"venue"
},
  "geometry": {"coordinates":[4.3174529076,50.7868804932],"type":"Point"}
}