{
  "type": "Feature",
  "properties": {
    "iso:country":"BE",
    "sg:address":"Rue Les Hauts Du Ry Ternel 32",
    "sg:city":"Ittre (haut-ittre)",
    "sg:classifiers":[
        {
            "category":"Retail",
            "subcategory":"Auto Repair",
            "type":"Services"
        }
    ],
    "sg:phone":"+32 67 21 92 89",
    "sg:postcode":"1461",
    "sg:province":"Brabant Wallon",
    "sg:tags":[
        "garage"
    ],
    "wof:name":"V's Car",
    "wof:placetype":"venue"
},
  "geometry": {"coordinates":[4.2974472046,50.6534690857],"type":"Point"}
}