{
  "type": "Feature",
  "properties": {
    "iso:country":"BE",
    "sg:address":"Rue Du Bouxthay 226",
    "sg:city":"Herstal",
    "sg:orig_category":"Installation \u00e9lectrique r\u00e9sidentielle",
    "sg:phone":"+32 4 227 81 47",
    "sg:postcode":"4041",
    "sg:province":"Li\u00e8ge",
    "wof:name":"Trigelis",
    "wof:placetype":"venue"
},
  "geometry": {"coordinates":[5.5849199295,50.6724891663],"type":"Point"}
}