{
  "type": "Feature",
  "properties": {
    "addr:full":"Parijsstraat 34-36 Leuven Vlaams-Brabant 3000",
    "addr:postcode":"34-36;3000",
    "addr:street":"Parijsstraat",
    "iso:country":"BE",
    "sg:address":"Parijsstraat 34-36",
    "sg:city":"Leuven",
    "sg:classifiers":[
        {
            "category":"Restaurant",
            "type":"Food & Drink"
        }
    ],
    "sg:phone":"+32 476 73 34 20",
    "sg:postcode":"3000",
    "sg:province":"Vlaams-Brabant",
    "wof:name":"Kapsiki",
    "wof:placetype":"venue"
},
  "geometry": {"coordinates":[4.6987137794,50.8783187866],"type":"Point"}
}