{
  "type": "Feature",
  "properties": {
    "addr:full":"Rue Haute 64 Ottignies-louvain-la-neuve (louvain-la-neuve) Brabant Wallon 1348",
    "addr:housenumber":"64",
    "addr:postcode":"1348",
    "addr:street":"Rue Haute",
    "iso:country":"BE",
    "sg:address":"Rue Haute 64",
    "sg:city":"Ottignies-louvain-la-neuve (louvain-la-neuve)",
    "sg:classifiers":[
        {
            "category":"Real Estate",
            "subcategory":"Real Estate Services",
            "type":"Services"
        }
    ],
    "sg:phone":"+32 476 30 81 27",
    "sg:postcode":"1348",
    "sg:province":"Brabant Wallon",
    "wof:name":"Mediane Immobiliere",
    "wof:placetype":"venue"
},
  "geometry": {"coordinates":[4.6038107872,50.6693763733],"type":"Point"}
}