{
  "type": "Feature",
  "properties": {
    "addr:full":"Frans Vekemansstraat 162 Brussel/bruxelles Bruxelles-Capitale 1120",
    "addr:housenumber":"162",
    "addr:postcode":"1120",
    "addr:street":"Frans Vekemansstraat;/",
    "iso:country":"BE",
    "sg:address":"Frans Vekemansstraat 162",
    "sg:city":"Brussel/bruxelles",
    "sg:orig_category":"Huishoudapparaten, televisies and radio's",
    "sg:phone":"+32 2 268 56 17",
    "sg:postcode":"1120",
    "sg:province":"Bruxelles-Capitale",
    "wof:name":"C.e.e.r.e.m.",
    "wof:placetype":"venue"
},
  "geometry": {"coordinates":[4.3982248306,50.9002685547],"type":"Point"}
}