{
  "type": "Feature",
  "properties": {
    "addr:full":"Leuvensesteenweg 454 Aarschot (gelrode) Vlaams-Brabant 3200",
    "addr:housenumber":"454",
    "addr:postcode":"3200",
    "addr:street":"Leuvensesteenweg",
    "iso:country":"BE",
    "sg:address":"Leuvensesteenweg 454",
    "sg:city":"Aarschot (gelrode)",
    "sg:classifiers":[
        {
            "category":"Manufacturing",
            "subcategory":"Motor Vehicles & Parts",
            "type":"Manufacturing & Wholesale Goods"
        }
    ],
    "sg:phone":"+32 16 56 64 17",
    "sg:postcode":"3200",
    "sg:province":"Vlaams-Brabant",
    "sg:tags":[
        "body",
        "automobile",
        "construction",
        "-"
    ],
    "wof:name":"Valkenaers Paul",
    "wof:placetype":"venue"
},
  "geometry": {"coordinates":[4.8045201302,50.9734306335],"type":"Point"}
}