{
  "type": "Feature",
  "properties": {
    "addr:full":"Rue De La R\u00c9sistance 75 Tournai Hainaut 7540",
    "addr:housenumber":"75",
    "addr:postcode":"7540",
    "addr:street":"Rue De La Re\u0301Sistance",
    "iso:country":"BE",
    "sg:address":"Rue De La R\u00c9sistance 75",
    "sg:city":"Tournai",
    "sg:orig_category":"Rundveehouders",
    "sg:phone":"+32 69 22 46 59",
    "sg:postcode":"7540",
    "sg:province":"Hainaut",
    "wof:name":"Jacques Dupont",
    "wof:placetype":"venue"
},
  "geometry": {"coordinates":[3.3837969303,50.645904541],"type":"Point"}
}