{
  "type": "Feature",
  "properties": {
    "addr:full":"Place Terdelt 2 Bruxelles (schaerbeek) Bruxelles-Capitale 1030",
    "addr:housenumber":"2",
    "addr:postcode":"1030",
    "addr:street":"Place Terdelt",
    "iso:country":"BE",
    "sg:address":"Place Terdelt 2",
    "sg:city":"Bruxelles (schaerbeek)",
    "sg:classifiers":[
        {
            "category":"Real Estate",
            "subcategory":"Architect",
            "type":"Services"
        }
    ],
    "sg:phone":"+32 2 268 05 37",
    "sg:postcode":"1030",
    "sg:province":"Bruxelles-Capitale",
    "wof:name":"Roche G",
    "wof:placetype":"venue"
},
  "geometry": {"coordinates":[4.3896551132,50.8680648804],"type":"Point"}
}