{
  "type": "Feature",
  "properties": {
    "addr:full":"Tuinwijk 17 Brecht (sint-lenaarts) Antwerpen 2960",
    "addr:housenumber":"17",
    "addr:postcode":"2960",
    "addr:street":"Tuinwijk",
    "iso:country":"BE",
    "sg:address":"Tuinwijk 17",
    "sg:city":"Brecht (sint-lenaarts)",
    "sg:classifiers":[
        {
            "category":"Real Estate",
            "subcategory":"Architect",
            "type":"Services"
        }
    ],
    "sg:phone":"+32 3 313 60 71",
    "sg:postcode":"2960",
    "sg:province":"Antwerpen",
    "wof:name":"Mertens G",
    "wof:placetype":"venue"
},
  "geometry": {"coordinates":[4.6415200233,51.3512115479],"type":"Point"}
}