{
  "type": "Feature",
  "properties": {
    "addr:full":"Bredabaan 366 Brasschaat Antwerpen 2930",
    "addr:housenumber":"366",
    "addr:postcode":"2930",
    "addr:street":"Bredabaan",
    "iso:country":"BE",
    "sg:address":"Bredabaan 366",
    "sg:city":"Brasschaat",
    "sg:classifiers":[
        {
            "category":"Cafe",
            "type":"Food & Drink"
        }
    ],
    "sg:phone":"+32 3 653 36 80",
    "sg:postcode":"2930",
    "sg:province":"Antwerpen",
    "sg:tags":[
        "snack-bars"
    ],
    "wof:name":"Florentine",
    "wof:placetype":"venue"
},
  "geometry": {"coordinates":[4.4950380325,51.2936134338],"type":"Point"}
}