{
  "type": "Feature",
  "properties": {
    "iso:country":"BE",
    "sg:address":"Rue Du Wez 4",
    "sg:city":"Vaux-sur-sure",
    "sg:orig_category":"Enseignement maternel and primaire",
    "sg:phone":"+32 61 25 60 86",
    "sg:postcode":"6640",
    "sg:province":"Luxembourg",
    "wof:name":"Ecole Fond. Communale",
    "wof:placetype":"venue"
},
  "geometry": {"coordinates":[5.5667748451,49.9100532532],"type":"Point"}
}