{
  "type": "Feature",
  "properties": {
    "addr:full":"Vinave D'ile 30 Li\u00c8ge Li\u00e8ge 4000",
    "addr:housenumber":"30",
    "addr:postcode":"4000",
    "addr:street":"Vinave D'Ile",
    "iso:country":"BE",
    "sg:address":"Vinave D'ile 30",
    "sg:city":"Li\u00c8ge",
    "sg:orig_category":"Chaussures",
    "sg:phone":"+32 4 223 31 94",
    "sg:postcode":"4000",
    "sg:province":"Li\u00e8ge",
    "wof:name":"Foot Locker",
    "wof:placetype":"venue"
},
  "geometry": {"coordinates":[5.5709090233,50.6414833069],"type":"Point"}
}