{
  "type": "Feature",
  "properties": {
    "iso:country":"BE",
    "sg:address":"Avenue Louis Lepoutre 109",
    "sg:city":"Elsene/ixelles",
    "sg:orig_category":"Antiquit\u00e9s",
    "sg:phone":"+32 2 343 02 10",
    "sg:postcode":"1050",
    "sg:province":"Bruxelles-Capitale",
    "wof:name":"Maison Chamarande",
    "wof:placetype":"venue"
},
  "geometry": {"coordinates":[4.3551039696,50.8178710938],"type":"Point"}
}