{
  "type": "Feature",
  "properties": {
    "addr:full":"Parc Artisanal De Blegny Bl\u00e9gny (barchon) Li\u00e8ge 4671",
    "addr:postcode":"4671",
    "iso:country":"BE",
    "sg:address":"Parc Artisanal De Blegny",
    "sg:city":"Bl\u00e9gny (barchon)",
    "sg:classifiers":[
        {
            "category":"Professional",
            "subcategory":"Management & Consulting",
            "type":"Services"
        }
    ],
    "sg:phone":"+32 4 387 87 27",
    "sg:postcode":"4671",
    "sg:province":"Li\u00e8ge",
    "sg:tags":[
        "consultant"
    ],
    "wof:name":"Jigam Sprl",
    "wof:placetype":"venue"
},
  "geometry": {"coordinates":[5.6961750984,50.6634635925],"type":"Point"}
}