{
  "type": "Feature",
  "properties": {
    "addr:full":"Rue De Tombrouck 6 Luingne/luingne Hainaut 7700",
    "addr:housenumber":"6",
    "addr:postcode":"7700",
    "addr:street":"Rue De Tombrouck;Hainaut",
    "iso:country":"BE",
    "sg:address":"Rue De Tombrouck 6",
    "sg:city":"Luingne/luingne",
    "sg:classifiers":[
        {
            "category":"Restaurant",
            "type":"Food & Drink"
        }
    ],
    "sg:phone":"+32 56 33 00 55",
    "sg:postcode":"7700",
    "sg:province":"Hainaut",
    "wof:name":"Le Bistro Des Anges",
    "wof:placetype":"venue"
},
  "geometry": {"coordinates":[3.2583289146,50.7411308289],"type":"Point"}
}