{
  "type": "Feature",
  "properties": {
    "addr:full":"Keienstraat 1 Overijse Vlaams-Brabant 3090",
    "addr:housenumber":"1",
    "addr:postcode":"3090",
    "addr:street":"Keienstraat",
    "iso:country":"BE",
    "sg:address":"Keienstraat 1",
    "sg:city":"Overijse",
    "sg:orig_category":"Producteurs de fruits",
    "sg:phone":"+32 2 687 31 79",
    "sg:postcode":"3090",
    "sg:province":"Vlaams-Brabant",
    "wof:name":"Remi Coddens",
    "wof:placetype":"venue"
},
  "geometry": {"coordinates":[4.5217599869,50.7475090027],"type":"Point"}
}