{
  "type": "Feature",
  "properties": {
    "iso:country":"BE",
    "sg:address":"Biesakkerlaan 1",
    "sg:city":"Meerhout",
    "sg:orig_category":"Artsen and specialisten",
    "sg:phone":"+32 14 30 03 44",
    "sg:postcode":"2450",
    "sg:province":"Antwerpen",
    "wof:name":"J. Vorlat",
    "wof:placetype":"venue"
},
  "geometry": {"coordinates":[5.0720639229,51.1288490295],"type":"Point"}
}