{
  "type": "Feature",
  "properties": {
    "addr:full":"Sint-annaplein 35 Gent Oost-Vlaanderen 9000",
    "addr:housenumber":"35",
    "addr:postcode":"9000",
    "addr:street":"Sint-Annaplein;Oost-Vlaanderen",
    "iso:country":"BE",
    "sg:address":"Sint-annaplein 35",
    "sg:city":"Gent",
    "sg:orig_category":"Artsen and specialisten",
    "sg:phone":"+32 9 225 21 47",
    "sg:postcode":"9000",
    "sg:province":"Oost-Vlaanderen",
    "wof:name":"Luc Van Houtte",
    "wof:placetype":"venue"
},
  "geometry": {"coordinates":[3.733741045,51.0469894409],"type":"Point"}
}