{
  "type": "Feature",
  "properties": {
    "addr:full":"Zauwerstraat 18 Laarne Oost-Vlaanderen 9270",
    "addr:housenumber":"18",
    "addr:postcode":"9270",
    "addr:street":"Zauwerstraat",
    "iso:country":"BE",
    "sg:address":"Zauwerstraat 18",
    "sg:city":"Laarne",
    "sg:orig_category":"Eleveurs de bovins",
    "sg:phone":"+32 9 367 87 29",
    "sg:postcode":"9270",
    "sg:province":"Oost-Vlaanderen",
    "wof:name":"Honore Bruggeman",
    "wof:placetype":"venue"
},
  "geometry": {"coordinates":[3.9204089642,51.0585021973],"type":"Point"}
}