{
  "type": "Feature",
  "properties": {
    "iso:country":"BE",
    "sg:address":"Rue De La Ruche 13",
    "sg:city":"Bruxelles (schaerbeek)",
    "sg:classifiers":[
        {
            "category":"Manufacturing",
            "subcategory":"Textiles",
            "type":"Manufacturing & Wholesale Goods"
        }
    ],
    "sg:phone":"+32 2 215 34 81",
    "sg:postcode":"1030",
    "sg:province":"Bruxelles-Capitale",
    "sg:tags":[
        "retail",
        "-"
    ],
    "wof:name":"Silberberg",
    "wof:placetype":"venue"
},
  "geometry": {"coordinates":[4.3735990524,50.8625488281],"type":"Point"}
}