{
  "type": "Feature",
  "properties": {
    "addr:full":"Rue Du Commerce 18 Chatelet Hainaut 6200",
    "addr:housenumber":"18",
    "addr:postcode":"6200",
    "addr:street":"Rue Du Commerce;Hainaut",
    "iso:country":"BE",
    "sg:address":"Rue Du Commerce 18",
    "sg:city":"Chatelet",
    "sg:orig_category":"CD's, cassettes and platen Fotografen and fotostudio's",
    "sg:phone":"+32 71 39 47 16",
    "sg:postcode":"6200",
    "sg:province":"Hainaut",
    "wof:name":"La Page Blanche",
    "wof:placetype":"venue"
},
  "geometry": {"coordinates":[4.5211901665,50.4050712585],"type":"Point"}
}