{
  "type": "Feature",
  "properties": {
    "addr:full":"Bakelaarstraat 61 Mechelen Antwerpen 2800",
    "addr:housenumber":"61",
    "addr:postcode":"2800",
    "addr:street":"Bakelaarstraat",
    "iso:country":"BE",
    "sg:address":"Bakelaarstraat 61",
    "sg:city":"Mechelen",
    "sg:classifiers":[
        {
            "category":"Personal",
            "subcategory":"Beauty Salon",
            "type":"Services"
        }
    ],
    "sg:phone":"+32 15 21 88 99",
    "sg:postcode":"2800",
    "sg:province":"Antwerpen",
    "sg:tags":[
        "de",
        "coiffure"
    ],
    "wof:name":"Coiffure Nicole",
    "wof:placetype":"venue"
},
  "geometry": {"coordinates":[4.4888601303,51.031955719],"type":"Point"}
}