{
  "type": "Feature",
  "properties": {
    "iso:country":"BE",
    "sg:address":"Vinktstraat 29",
    "sg:city":"Tielt (aarsele)",
    "sg:classifiers":[
        {
            "category":"Personal",
            "subcategory":"Beauty Salon",
            "type":"Services"
        }
    ],
    "sg:phone":"+32 51 63 56 77",
    "sg:postcode":"8700",
    "sg:province":"West-Vlaanderen",
    "sg:tags":[
        "lady",
        "-",
        "hairdressing"
    ],
    "wof:name":"Bethuyne R",
    "wof:placetype":"venue"
},
  "geometry": {"coordinates":[3.422866106,50.998046875],"type":"Point"}
}