{
  "type": "Feature",
  "properties": {
    "addr:full":"Biezeweg 6 Wetteren Oost-Vlaanderen 9230",
    "addr:housenumber":"6",
    "addr:postcode":"9230",
    "addr:street":"Biezeweg",
    "iso:country":"BE",
    "sg:address":"Biezeweg 6",
    "sg:city":"Wetteren",
    "sg:orig_category":"Fa\u00e7ade Construction, Fa\u00e7ade Lining Services",
    "sg:phone":"+32 9 252 26 00",
    "sg:postcode":"9230",
    "sg:province":"Oost-Vlaanderen",
    "wof:name":"Houtconstructies Wyckaert Nv",
    "wof:placetype":"venue"
},
  "geometry": {"coordinates":[3.8384399414,50.9895782471],"type":"Point"}
}