{
  "type": "Feature",
  "properties": {
    "iso:country":"BE",
    "sg:address":"Koning Leopoldlaan 129",
    "sg:city":"Lommel",
    "sg:classifiers":[
        {
            "category":"Social Services",
            "subcategory":"Job Training",
            "type":"Services"
        }
    ],
    "sg:phone":"+32 11 54 58 23",
    "sg:postcode":"3920",
    "sg:province":"Limburg",
    "sg:tags":[
        "condiment",
        "spice"
    ],
    "wof:name":"Mertens Nv",
    "wof:placetype":"venue"
},
  "geometry": {"coordinates":[5.3243489265,51.2299346924],"type":"Point"}
}