{
  "type": "Feature",
  "properties": {
    "iso:country":"BE",
    "sg:address":"Dambrugstraat 5",
    "sg:city":"Beveren",
    "sg:classifiers":[
        {
            "category":"Arena",
            "subcategory":"Sports Club",
            "type":"Entertainment"
        }
    ],
    "sg:phone":"+32 3 775 58 87",
    "sg:postcode":"9120",
    "sg:province":"Oost-Vlaanderen",
    "sg:tags":[
        "de"
    ],
    "wof:name":"Ttc Melsele",
    "wof:placetype":"venue"
},
  "geometry": {"coordinates":[4.282626152,51.2220573425],"type":"Point"}
}