{
  "type": "Feature",
  "properties": {
    "addr:full":"Jamin\u00e9straat 44 Tongeren Limburg 3700",
    "addr:housenumber":"44",
    "addr:postcode":"3700",
    "addr:street":"Jamine\u0301Straat",
    "iso:country":"BE",
    "sg:address":"Jamin\u00e9straat 44",
    "sg:city":"Tongeren",
    "sg:classifiers":[
        {
            "category":"Shopping",
            "subcategory":"Shoes",
            "type":"Retail Goods"
        }
    ],
    "sg:phone":"+32 12 26 24 68",
    "sg:postcode":"3700",
    "sg:province":"Limburg",
    "sg:tags":[
        "slipper",
        "-"
    ],
    "wof:name":"Mara Nv",
    "wof:placetype":"venue"
},
  "geometry": {"coordinates":[5.4730548859,50.7831306458],"type":"Point"}
}