{
  "type": "Feature",
  "properties": {
    "iso:country":"BE",
    "sg:address":"Krijgslaan 59",
    "sg:city":"Gent",
    "sg:classifiers":[
        {
            "category":"Insurance",
            "subcategory":"Insurance Agent",
            "type":"Services"
        }
    ],
    "sg:phone":"+32 9 222 68 58",
    "sg:postcode":"9000",
    "sg:province":"Oost-Vlaanderen",
    "sg:tags":[
        "verzekeringsmakelaars",
        "expert"
    ],
    "wof:name":"Bureau Van Den Driessche",
    "wof:placetype":"venue"
},
  "geometry": {"coordinates":[3.7205629349,51.0343933105],"type":"Point"}
}