{
  "type": "Feature",
  "properties": {
    "addr:full":"Rue Adolphe-sax 84 Dinant Namur 5500",
    "addr:housenumber":"84",
    "addr:postcode":"5500",
    "addr:street":"Rue Adolphe-Sax",
    "iso:country":"BE",
    "sg:address":"Rue Adolphe-sax 84",
    "sg:city":"Dinant",
    "sg:orig_category":"Apotheken",
    "sg:phone":"+32 82 22 23 55",
    "sg:postcode":"5500",
    "sg:province":"Namur",
    "wof:name":"Catherine Leleu",
    "wof:placetype":"venue"
},
  "geometry": {"coordinates":[4.9099531174,50.2625465393],"type":"Point"}
}