{
  "type": "Feature",
  "properties": {
    "iso:country":"BE",
    "sg:address":"Hofveld 11",
    "sg:city":"Asse",
    "sg:classifiers":[
        {
            "category":"Health Services",
            "subcategory":"Dentist",
            "type":"Services"
        }
    ],
    "sg:phone":"+32 2 452 81 47",
    "sg:postcode":"1730",
    "sg:province":"Vlaams-Brabant",
    "wof:name":"Pletinckx E",
    "wof:placetype":"venue"
},
  "geometry": {"coordinates":[4.1946558952,50.9087753296],"type":"Point"}
}