{
  "type": "Feature",
  "properties": {
    "iso:country":"BE",
    "sg:address":"Rue De Pr\u00c9e 7a",
    "sg:city":"Mettet",
    "sg:orig_category":"Vitrage",
    "sg:phone":"+32 71 72 87 42",
    "sg:postcode":"5640",
    "sg:province":"Namur",
    "wof:name":"Claude Carpet",
    "wof:placetype":"venue"
},
  "geometry": {"coordinates":[4.6010951996,50.3246650696],"type":"Point"}
}