{
  "type": "Feature",
  "properties": {
    "addr:full":"Boerenkrijglaan 148 Westerlo Antwerpen 2260",
    "addr:housenumber":"148",
    "addr:postcode":"2260",
    "addr:street":"Boerenkrijglaan",
    "iso:country":"BE",
    "sg:address":"Boerenkrijglaan 148",
    "sg:city":"Westerlo",
    "sg:classifiers":[
        {
            "category":"Fast Food",
            "type":"Food & Drink"
        }
    ],
    "sg:phone":"+32 14 54 93 00",
    "sg:postcode":"2260",
    "sg:province":"Antwerpen",
    "sg:tags":[
        "\u00c0",
        "emporter",
        "restaurants"
    ],
    "wof:name":"Pita",
    "wof:placetype":"venue"
},
  "geometry": {"coordinates":[4.9108672142,51.0974807739],"type":"Point"}
}