{
  "type": "Feature",
  "properties": {
    "iso:country":"BE",
    "sg:address":"Rue Grande 6",
    "sg:city":"Saint-ghislain",
    "sg:orig_category":"Antiek Herstelling and restauratie van meubelen",
    "sg:phone":"+32 65 78 23 51",
    "sg:postcode":"7330",
    "sg:province":"Hainaut",
    "wof:name":"Antiquit\u00c9s Naphtaline",
    "wof:placetype":"venue"
},
  "geometry": {"coordinates":[3.8197588921,50.4472389221],"type":"Point"}
}