{
  "type": "Feature",
  "properties": {
    "iso:country":"BE",
    "sg:address":"Rue De Givet 65",
    "sg:city":"Beauraing",
    "sg:orig_category":"Fotogravure and zetwerk",
    "sg:phone":"+32 82 71 33 61",
    "sg:postcode":"5570",
    "sg:province":"Namur",
    "wof:name":"Multi-caracteres",
    "wof:placetype":"venue"
},
  "geometry": {"coordinates":[4.9495410919,50.1125831604],"type":"Point"}
}