{
  "type": "Feature",
  "properties": {
    "addr:full":"Grootebaan 9 Haacht Vlaams-Brabant 3150",
    "addr:housenumber":"9",
    "addr:postcode":"3150",
    "addr:street":"Grootebaan",
    "iso:country":"BE",
    "sg:address":"Grootebaan 9",
    "sg:city":"Haacht",
    "sg:classifiers":[
        {
            "category":"Insurance",
            "subcategory":"Life Insurance",
            "type":"Services"
        }
    ],
    "sg:phone":"+32 15 73 07 22",
    "sg:postcode":"3150",
    "sg:province":"Vlaams-Brabant",
    "sg:tags":[
        "assurance"
    ],
    "wof:name":"Assurad Nv",
    "wof:placetype":"venue"
},
  "geometry": {"coordinates":[4.6384358406,50.9577827454],"type":"Point"}
}