{
  "type": "Feature",
  "properties": {
    "iso:country":"BE",
    "sg:address":"Avenue F. Roosevelt 78 -",
    "sg:city":"Brussels",
    "sg:classifiers":[
        {
            "category":"Professional",
            "subcategory":"Art Services",
            "type":"Services"
        }
    ],
    "sg:phone":"+32 2 648 61 40",
    "sg:postcode":"1050",
    "sg:province":"Bruxelles-Capitale",
    "sg:tags":[
        "export-import"
    ],
    "wof:name":"Niger Embassy",
    "wof:placetype":"venue"
},
  "geometry": {"coordinates":[4.3834052086,50.8098297119],"type":"Point"}
}