{
  "type": "Feature",
  "properties": {
    "addr:full":"Mexicostraat 48 Ichtegem West-Vlaanderen 8480",
    "addr:housenumber":"48",
    "addr:postcode":"8480",
    "addr:street":"Mexicostraat",
    "iso:country":"BE",
    "sg:address":"Mexicostraat 48",
    "sg:city":"Ichtegem",
    "sg:classifiers":[
        {
            "category":"Professional",
            "subcategory":"Lawyer & Legal Services",
            "type":"Services"
        }
    ],
    "sg:phone":"+32 51 58 27 98",
    "sg:postcode":"8480",
    "sg:province":"West-Vlaanderen",
    "wof:name":"Deschoenmaker Kati",
    "wof:placetype":"venue"
},
  "geometry": {"coordinates":[3.0090639591,51.0884017944],"type":"Point"}
}