{
  "type": "Feature",
  "properties": {
    "addr:full":"Statiestraat 11 Mol Antwerpen 2400",
    "addr:housenumber":"11",
    "addr:postcode":"2400",
    "addr:street":"Statiestraat",
    "iso:country":"BE",
    "sg:address":"Statiestraat 11",
    "sg:city":"Mol",
    "sg:classifiers":[
        {
            "category":"Shopping",
            "subcategory":"Clothing, Apparel, & Fashions",
            "type":"Retail Goods"
        }
    ],
    "sg:phone":"+32 14 31 03 92",
    "sg:postcode":"2400",
    "sg:province":"Antwerpen",
    "sg:tags":[
        "ondergoed",
        "lingerie"
    ],
    "wof:name":"Huis Silhouette",
    "wof:placetype":"venue"
},
  "geometry": {"coordinates":[5.1170978546,51.1912193298],"type":"Point"}
}