{
  "type": "Feature",
  "properties": {
    "iso:country":"BE",
    "sg:address":"Rue Saint-roche 8",
    "sg:city":"Gerpinnes",
    "sg:orig_category":"Boekhouders",
    "sg:phone":"+32 71 50 40 87",
    "sg:postcode":"6280",
    "sg:province":"Hainaut",
    "wof:name":"De Martelaere Fabrice",
    "wof:placetype":"venue"
},
  "geometry": {"coordinates":[4.5276851654,50.3365364075],"type":"Point"}
}