{
  "type": "Feature",
  "properties": {
    "iso:country":"BE",
    "sg:address":"Magere Schorre 6",
    "sg:city":"Knokke-heist",
    "sg:orig_category":"Artsen and specialisten",
    "sg:phone":"+32 50 60 11 09",
    "sg:postcode":"8300",
    "sg:province":"West-Vlaanderen",
    "wof:name":"Maria Rodgers",
    "wof:placetype":"venue"
},
  "geometry": {"coordinates":[3.2985100746,51.3402748108],"type":"Point"}
}