{
  "type": "Feature",
  "properties": {
    "addr:full":"Terschuerenlaan 30 Ledegem West-Vlaanderen 8880",
    "addr:housenumber":"30",
    "addr:postcode":"8880",
    "addr:street":"Terschuerenlaan",
    "iso:country":"BE",
    "sg:address":"Terschuerenlaan 30",
    "sg:city":"Ledegem",
    "sg:orig_category":"Woningbouw",
    "sg:phone":"+32 56 50 16 24",
    "sg:postcode":"8880",
    "sg:province":"West-Vlaanderen",
    "wof:name":"Patrick Vansteenhuyse",
    "wof:placetype":"venue"
},
  "geometry": {"coordinates":[3.1789839268,50.8727874756],"type":"Point"}
}