{
  "type": "Feature",
  "properties": {
    "iso:country":"BE",
    "sg:address":"Gladiolenstraat 29",
    "sg:city":"Sint-niklaas",
    "sg:classifiers":[
        {
            "category":"Fast Food",
            "type":"Food & Drink"
        }
    ],
    "sg:phone":"+32 3 766 46 01",
    "sg:postcode":"9100",
    "sg:province":"Oost-Vlaanderen",
    "sg:tags":[
        "meeneem",
        "restaurant"
    ],
    "wof:name":"Wong's Garden",
    "wof:placetype":"venue"
},
  "geometry": {"coordinates":[4.1581168175,51.1607818604],"type":"Point"}
}