{
  "type": "Feature",
  "properties": {
    "iso:country":"BE",
    "sg:address":"Philipslaan 5",
    "sg:city":"Leuven",
    "sg:classifiers":[
        {
            "category":"Manufacturing",
            "subcategory":"Lumber",
            "type":"Manufacturing & Wholesale Goods"
        }
    ],
    "sg:phone":"+32 16 25 07 93",
    "sg:postcode":"3000",
    "sg:province":"Vlaams-Brabant",
    "sg:tags":[
        "timber"
    ],
    "wof:name":"Huens C",
    "wof:placetype":"venue"
},
  "geometry": {"coordinates":[4.7317700386,50.8672714233],"type":"Point"}
}