{
  "type": "Feature",
  "properties": {
    "addr:full":"Wippelgem Dorp 51 Evergem Oost-Vlaanderen 9940",
    "addr:housenumber":"51",
    "addr:postcode":"9940",
    "addr:street":"Wippelgem Dorp;Oost-Vlaanderen",
    "iso:country":"BE",
    "sg:address":"Wippelgem Dorp 51",
    "sg:city":"Evergem",
    "sg:classifiers":[
        {
            "category":"Building & Trades",
            "subcategory":"Pest Control",
            "type":"Services"
        }
    ],
    "sg:phone":"+32 9 357 57 31",
    "sg:postcode":"9940",
    "sg:province":"Oost-Vlaanderen",
    "sg:tags":[
        "painting",
        "contractor"
    ],
    "wof:name":"De Vos E",
    "wof:placetype":"venue"
},
  "geometry": {"coordinates":[3.7313189507,51.1407012939],"type":"Point"}
}