{
  "type": "Feature",
  "properties": {
    "addr:full":"Rozenstraat 28 Box 2 Hasselt Limburg 3500",
    "addr:housenumber":"28;2",
    "addr:postcode":"3500",
    "addr:street":"Rozenstraat;Box",
    "iso:country":"BE",
    "sg:address":"Rozenstraat 28 Box 2",
    "sg:city":"Hasselt",
    "sg:classifiers":[
        {
            "category":"Professional",
            "subcategory":"Lawyer & Legal Services",
            "type":"Services"
        }
    ],
    "sg:phone":"+32 11 25 34 30",
    "sg:postcode":"3500",
    "sg:province":"Limburg",
    "wof:name":"Spaas Michel",
    "wof:placetype":"venue"
},
  "geometry": {"coordinates":[5.3297581673,50.9340934753],"type":"Point"}
}