{
  "type": "Feature",
  "properties": {
    "iso:country":"BE",
    "sg:address":"Chauss\u00c9e De Nivelles 12c",
    "sg:city":"Sombreffe",
    "sg:orig_category":"Slagers",
    "sg:phone":"+32 71 88 80 06",
    "sg:postcode":"5140",
    "sg:province":"Namur",
    "wof:name":"Bouffioux-burteau",
    "wof:placetype":"venue"
},
  "geometry": {"coordinates":[4.6126251221,50.5247764587],"type":"Point"}
}