{
  "type": "Feature",
  "properties": {
    "addr:full":"Karmstraat 100 Tielt West-Vlaanderen 8700",
    "addr:housenumber":"100",
    "addr:postcode":"8700",
    "addr:street":"Karmstraat",
    "iso:country":"BE",
    "sg:address":"Karmstraat 100",
    "sg:city":"Tielt",
    "sg:orig_category":"Mobiele kappers",
    "sg:phone":"+32 51 63 75 48",
    "sg:postcode":"8700",
    "sg:province":"West-Vlaanderen",
    "wof:name":"Nancy Huys",
    "wof:placetype":"venue"
},
  "geometry": {"coordinates":[3.3892509937,50.9827537537],"type":"Point"}
}