{
  "type": "Feature",
  "properties": {
    "iso:country":"BE",
    "sg:address":"Dokter Van Raemdonckstraat 30",
    "sg:city":"Sint-niklaas",
    "sg:classifiers":[
        {
            "category":"Fast Food",
            "type":"Food & Drink"
        }
    ],
    "sg:phone":"+32 3 766 22 83",
    "sg:postcode":"9100",
    "sg:province":"Oost-Vlaanderen",
    "sg:tags":[
        "fried",
        "stand",
        "potato"
    ],
    "wof:name":"Hoekske('t) Bvba",
    "wof:placetype":"venue"
},
  "geometry": {"coordinates":[4.153470993,51.1692695618],"type":"Point"}
}