{
  "type": "Feature",
  "properties": {
    "iso:country":"BE",
    "sg:address":"Hof Ten Berg 30b7",
    "sg:city":"Sint-lambrechts-woluwe/woluwe-saint-lambert",
    "sg:orig_category":"M\u00e9decins and sp\u00e9cialistes",
    "sg:phone":"+32 2 779 24 25",
    "sg:postcode":"1200",
    "sg:province":"Bruxelles-Capitale",
    "wof:name":"Jean D.j. Convent",
    "wof:placetype":"venue"
},
  "geometry": {"coordinates":[4.4434518814,50.8563842773],"type":"Point"}
}