{
  "type": "Feature",
  "properties": {
    "iso:country":"BE",
    "sg:address":"Edgard Tinelstraat 31",
    "sg:city":"Sint-lievens-houtem",
    "sg:orig_category":"Opticiens",
    "sg:phone":"+32 53 62 72 92",
    "sg:postcode":"9520",
    "sg:province":"Oost-Vlaanderen",
    "wof:name":"Philip Van Den Bossche",
    "wof:placetype":"venue"
},
  "geometry": {"coordinates":[3.8603711128,50.9201850891],"type":"Point"}
}