{
  "type": "Feature",
  "properties": {
    "addr:full":"Boulevard Reyers 118 Brussel/bruxelles Bruxelles-Capitale 1030",
    "addr:housenumber":"118",
    "addr:postcode":"1030",
    "addr:street":"Boulevard Reyers;/",
    "iso:country":"BE",
    "sg:address":"Boulevard Reyers 118",
    "sg:city":"Brussel/bruxelles",
    "sg:orig_category":"Installation de menuiserie m\u00e9tallique. Peinture. Rev\u00eatements pour sols and murs",
    "sg:phone":"+32 2 732 44 11",
    "sg:postcode":"1030",
    "sg:province":"Bruxelles-Capitale",
    "wof:name":"Pastel Services",
    "wof:placetype":"venue"
},
  "geometry": {"coordinates":[4.3749351501,50.8680000305],"type":"Point"}
}