{
  "type": "Feature",
  "properties": {
    "iso:country":"BE",
    "sg:address":"Avenue J. B. Nothomb 77",
    "sg:city":"Arlon",
    "sg:orig_category":"Artsen and specialisten",
    "sg:phone":"+32 63 22 25 25",
    "sg:postcode":"6700",
    "sg:province":"Luxembourg",
    "wof:name":"D. Jean",
    "wof:placetype":"venue"
},
  "geometry": {"coordinates":[5.8062591553,49.6818351746],"type":"Point"}
}