{
  "type": "Feature",
  "properties": {
    "iso:country":"BE",
    "sg:address":"Grote Baan 20",
    "sg:city":"Hasselt (kuringen)",
    "sg:orig_category":"Newspapers, magazines, periodicals - Distribution",
    "sg:phone":"+32 11 25 08 20",
    "sg:postcode":"3511",
    "sg:province":"Limburg",
    "wof:name":"Krantenshop Johnny",
    "wof:placetype":"venue"
},
  "geometry": {"coordinates":[5.3049521446,50.9404678345],"type":"Point"}
}