{
  "type": "Feature",
  "properties": {
    "addr:full":"Spoorwegstraat 92 Dendermonde Oost-Vlaanderen 9200",
    "addr:housenumber":"92",
    "addr:postcode":"9200",
    "addr:street":"Spoorwegstraat;Oost-Vlaanderen",
    "iso:country":"BE",
    "sg:address":"Spoorwegstraat 92",
    "sg:city":"Dendermonde",
    "sg:orig_category":"Woningbouw",
    "sg:phone":"+32 52 21 50 68",
    "sg:postcode":"9200",
    "sg:province":"Oost-Vlaanderen",
    "wof:name":"Johan Van Den Abbeele",
    "wof:placetype":"venue"
},
  "geometry": {"coordinates":[4.120308876,51.0244941711],"type":"Point"}
}