{
  "type": "Feature",
  "properties": {
    "addr:full":"Korte Gasthuisstraat 12 Antwerpen Antwerpen 2000",
    "addr:housenumber":"12",
    "addr:postcode":"2000",
    "addr:street":"Korte Gasthuisstraat",
    "iso:country":"BE",
    "sg:address":"Korte Gasthuisstraat 12",
    "sg:city":"Antwerpen",
    "sg:classifiers":[
        {
            "category":"Personal",
            "subcategory":"Beauty Salon",
            "type":"Services"
        }
    ],
    "sg:phone":"+32 3 233 04 99",
    "sg:postcode":"2000",
    "sg:province":"Antwerpen",
    "sg:tags":[
        "de",
        "coiffure"
    ],
    "wof:name":"Gilson Hair Fashion",
    "wof:placetype":"venue"
},
  "geometry": {"coordinates":[4.4039611816,51.2170753479],"type":"Point"}
}