{
  "type": "Feature",
  "properties": {
    "iso:country":"BE",
    "sg:address":"Albert I Laan 35",
    "sg:city":"Beringen",
    "sg:orig_category":"Installatie van houten of kunststof schrijnwerk Plaatsen van vloer- and muurbekleding Schilders Verl",
    "sg:phone":"+32 11 42 60 01",
    "sg:postcode":"3582",
    "sg:province":"Limburg",
    "wof:name":"Moons Rob Interieurs",
    "wof:placetype":"venue"
},
  "geometry": {"coordinates":[5.2708749771,51.0595359802],"type":"Point"}
}