{
  "type": "Feature",
  "properties": {
    "iso:country":"BE",
    "sg:address":"Seringenstraat 55",
    "sg:city":"Roeselare",
    "sg:orig_category":"Cr\u00e8ches and garderies d'enfants",
    "sg:phone":"+32 51 20 22 35",
    "sg:postcode":"8800",
    "sg:province":"West-Vlaanderen",
    "wof:name":"Kribbe Bloemenhove",
    "wof:placetype":"venue"
},
  "geometry": {"coordinates":[3.1353979111,50.940322876],"type":"Point"}
}