{
  "type": "Feature",
  "properties": {
    "addr:full":"Quai Aux Huitres 17 Wavre Brabant Wallon 1300",
    "addr:housenumber":"17;1300",
    "addr:street":"Quai Aux Huitres",
    "iso:country":"BE",
    "sg:address":"Quai Aux Huitres 17",
    "sg:city":"Wavre",
    "sg:orig_category":"Paramedische behandelingen",
    "sg:phone":"+32 10 22 29 74",
    "sg:postcode":"1300",
    "sg:province":"Brabant Wallon",
    "wof:name":"Steenbeek",
    "wof:placetype":"venue"
},
  "geometry": {"coordinates":[4.6116471291,50.7148628235],"type":"Point"}
}