{
  "type": "Feature",
  "properties": {
    "addr:full":"Galileistraat 10 Diksmuide West-Vlaanderen 8600",
    "addr:housenumber":"10",
    "addr:postcode":"8600",
    "addr:street":"Galileistraat",
    "iso:country":"BE",
    "sg:address":"Galileistraat 10",
    "sg:city":"Diksmuide",
    "sg:orig_category":"Rundveehouders Varkenskwekers",
    "sg:phone":"+32 51 50 12 78",
    "sg:postcode":"8600",
    "sg:province":"West-Vlaanderen",
    "wof:name":"Etienne Beuselinck",
    "wof:placetype":"venue"
},
  "geometry": {"coordinates":[2.858232975,51.0406265259],"type":"Point"}
}