{
  "type": "Feature",
  "properties": {
    "iso:country":"BE",
    "sg:address":"Meulebekestraat 76",
    "sg:city":"Pittem",
    "sg:orig_category":"Producteurs de l\u00e9gumes. Producteurs de fruits",
    "sg:phone":"+32 51 46 63 73",
    "sg:postcode":"8740",
    "sg:province":"West-Vlaanderen",
    "wof:name":"Daniel Defour",
    "wof:placetype":"venue"
},
  "geometry": {"coordinates":[3.2707169056,50.9785995483],"type":"Point"}
}