{
  "type": "Feature",
  "properties": {
    "iso:country":"BE",
    "sg:address":"Marktstraat 18",
    "sg:city":"Hoeselt",
    "sg:orig_category":"Installation de menuiserie en bois and plastique",
    "sg:phone":"+32 12 23 36 88",
    "sg:postcode":"3730",
    "sg:province":"Limburg",
    "wof:name":"Gilbert Mathijs",
    "wof:placetype":"venue"
},
  "geometry": {"coordinates":[5.4488048553,50.8288421631],"type":"Point"}
}