{
  "type": "Feature",
  "properties": {
    "addr:full":"Rue Grande 65 Farciennes Hainaut 6240",
    "addr:housenumber":"65",
    "addr:postcode":"6240",
    "addr:street":"Rue Grande",
    "iso:country":"BE",
    "sg:address":"Rue Grande 65",
    "sg:city":"Farciennes",
    "sg:orig_category":"Banques and organismes de cr\u00e9dit",
    "sg:phone":"+32 71 38 01 95",
    "sg:postcode":"6240",
    "sg:province":"Hainaut",
    "wof:name":"Fortis",
    "wof:placetype":"venue"
},
  "geometry": {"coordinates":[4.5516600609,50.426700592],"type":"Point"}
}