{
  "type": "Feature",
  "properties": {
    "addr:full":"Rue D'alaumont 10 Lasne (couture-saint-germain) Brabant Wallon 1380",
    "addr:housenumber":"10",
    "addr:postcode":"1380",
    "addr:street":"Rue D'Alaumont;Wallon",
    "iso:country":"BE",
    "sg:address":"Rue D'alaumont 10",
    "sg:city":"Lasne (couture-saint-germain)",
    "sg:classifiers":[
        {
            "category":"Professional",
            "subcategory":"Accounting & Tax Preparation",
            "type":"Services"
        }
    ],
    "sg:phone":"+32 2 772 44 45",
    "sg:postcode":"1380",
    "sg:province":"Brabant Wallon",
    "sg:tags":[
        "accountant"
    ],
    "wof:name":"Msc Consult Scprl",
    "wof:placetype":"venue"
},
  "geometry": {"coordinates":[4.4785528183,50.6605644226],"type":"Point"}
}