{
  "type": "Feature",
  "properties": {
    "addr:full":"Bar F Du Fourstr 4 Turnhout Antwerpen 2300",
    "addr:housenumber":"4",
    "addr:postcode":"2300",
    "iso:country":"BE",
    "sg:address":"Bar F Du Fourstr 4",
    "sg:city":"Turnhout",
    "sg:classifiers":[
        {
            "category":"Shopping",
            "subcategory":"Crafts & Fabrics",
            "type":"Retail Goods"
        }
    ],
    "sg:phone":"+32 14 42 03 96",
    "sg:postcode":"2300",
    "sg:province":"Antwerpen",
    "sg:tags":[
        "graphic",
        "art",
        "supply",
        "-",
        "painting",
        "drawing"
    ],
    "wof:name":"Indigo",
    "wof:placetype":"venue"
},
  "geometry": {"coordinates":[4.9501838684,51.3236274719],"type":"Point"}
}