{
  "type": "Feature",
  "properties": {
    "iso:country":"BE",
    "sg:address":"Abbeelstraat 27",
    "sg:city":"Aalst",
    "sg:orig_category":"Sportclubs",
    "sg:phone":"+32 53 78 06 34",
    "sg:postcode":"9300",
    "sg:province":"Oost-Vlaanderen",
    "wof:name":"V.w.b.-v.t.b.",
    "wof:placetype":"venue"
},
  "geometry": {"coordinates":[4.0240049362,50.9449882507],"type":"Point"}
}