{
  "type": "Feature",
  "properties": {
    "iso:country":"BE",
    "sg:address":"Meiboomlaan 3b8",
    "sg:city":"Roeselare",
    "sg:classifiers":[
        {
            "category":"Arena",
            "subcategory":"Sports Club",
            "type":"Entertainment"
        }
    ],
    "sg:phone":"+32 51 22 83 94",
    "sg:postcode":"8800",
    "sg:province":"West-Vlaanderen",
    "sg:tags":[
        "de"
    ],
    "wof:name":"Veloclub De Mandelzoenen Roeselare",
    "wof:placetype":"venue"
},
  "geometry": {"coordinates":[3.1194820404,50.93491745],"type":"Point"}
}