{
  "type": "Feature",
  "properties": {
    "addr:full":"Koestraat 59 Herenthout Antwerpen 2270",
    "addr:housenumber":"59",
    "addr:postcode":"2270",
    "addr:street":"Koestraat",
    "iso:country":"BE",
    "sg:address":"Koestraat 59",
    "sg:city":"Herenthout",
    "sg:orig_category":"Kapsalons",
    "sg:phone":"+32 14 51 65 83",
    "sg:postcode":"2270",
    "sg:province":"Antwerpen",
    "wof:name":"Coiffure Van Den Bruel",
    "wof:placetype":"venue"
},
  "geometry": {"coordinates":[4.7588229179,51.1427383423],"type":"Point"}
}