{
  "type": "Feature",
  "properties": {
    "iso:country":"BE",
    "sg:address":"Moerenstraat 79",
    "sg:city":"Arendonk",
    "sg:orig_category":"Rundveehouders",
    "sg:phone":"+32 14 67 71 53",
    "sg:postcode":"2370",
    "sg:province":"Antwerpen",
    "wof:name":"Louis Oeyen",
    "wof:placetype":"venue"
},
  "geometry": {"coordinates":[5.1137099266,51.3194503784],"type":"Point"}
}