{
  "type": "Feature",
  "properties": {
    "iso:country":"BE",
    "sg:address":"Rue Ariste Caussin 95",
    "sg:city":"Dinant",
    "sg:classifiers":[
        {
            "category":"Food & Beverages",
            "subcategory":"Groceries & Convenience Stores",
            "type":"Retail Goods"
        }
    ],
    "sg:phone":"+32 82 22 37 62",
    "sg:postcode":"5500",
    "sg:province":"Namur",
    "sg:tags":[
        "grocer"
    ],
    "wof:name":"R\u00e9gine & Patrick Sprl",
    "wof:placetype":"venue"
},
  "geometry": {"coordinates":[4.9138331413,50.2388496399],"type":"Point"}
}