{
  "type": "Feature",
  "properties": {
    "addr:full":"Rue Du S\u00c9woir 121 Lens Hainaut 7870",
    "addr:housenumber":"121",
    "addr:postcode":"7870",
    "addr:street":"Rue Du Se\u0301Woir",
    "iso:country":"BE",
    "sg:address":"Rue Du S\u00c9woir 121",
    "sg:city":"Lens",
    "sg:orig_category":"V\u00eatements",
    "sg:phone":"+32 65 23 53 08",
    "sg:postcode":"7870",
    "sg:province":"Hainaut",
    "wof:name":"Eurolux Services",
    "wof:placetype":"venue"
},
  "geometry": {"coordinates":[3.9032120705,50.5495147705],"type":"Point"}
}