{
  "type": "Feature",
  "properties": {
    "iso:country":"BE",
    "sg:address":"Gaston Baertstraat 17",
    "sg:city":"Deinze (sint-martens-leerne)",
    "sg:classifiers":[
        {
            "category":"Health Services",
            "subcategory":"Doctor",
            "type":"Services"
        }
    ],
    "sg:phone":"+32 9 282 68 62",
    "sg:postcode":"9800",
    "sg:province":"Oost-Vlaanderen",
    "sg:tags":[
        "psychotherapist",
        "psychoanalyst"
    ],
    "wof:name":"De Groote H",
    "wof:placetype":"venue"
},
  "geometry": {"coordinates":[3.5824329853,51.0155715942],"type":"Point"}
}