{
  "type": "Feature",
  "properties": {
    "iso:country":"BE",
    "sg:address":"Kapellestraat 8",
    "sg:city":"Herne",
    "sg:classifiers":[
        {
            "category":"Personal",
            "subcategory":"Beauty Salon",
            "type":"Services"
        }
    ],
    "sg:phone":"+32 2 396 20 33",
    "sg:postcode":"1540",
    "sg:province":"Vlaams-Brabant",
    "sg:tags":[
        "de",
        "coiffure"
    ],
    "wof:name":"Christian Catereels",
    "wof:placetype":"venue"
},
  "geometry": {"coordinates":[4.0304298401,50.7273788452],"type":"Point"}
}