{
  "type": "Feature",
  "properties": {
    "iso:country":"BE",
    "sg:address":"Moorselstraat 182",
    "sg:city":"Tervuren",
    "sg:orig_category":"Herstelling aan huis van huishoudartikelen Loodgieterij, verwarming and sanitaire installaties",
    "sg:phone":"+32 2 767 89 71",
    "sg:postcode":"3080",
    "sg:province":"Vlaams-Brabant",
    "wof:name":"Adc Concept",
    "wof:placetype":"venue"
},
  "geometry": {"coordinates":[4.538672924,50.8537940979],"type":"Point"}
}