{
  "type": "Feature",
  "properties": {
    "addr:full":"Waterloose Steenweg 44 Sint-genesius-rode/rhode-saint-gen\u00c8se Vlaams-Brabant 1640",
    "addr:housenumber":"44",
    "addr:postcode":"1640",
    "addr:street":"Waterloose Steenweg",
    "iso:country":"BE",
    "sg:address":"Waterloose Steenweg 44",
    "sg:city":"Sint-genesius-rode/rhode-saint-gen\u00c8se",
    "sg:orig_category":"Industri\u00eble elektrische installaties",
    "sg:phone":"+32 2 358 59 86",
    "sg:postcode":"1640",
    "sg:province":"Vlaams-Brabant",
    "wof:name":"Euromove",
    "wof:placetype":"venue"
},
  "geometry": {"coordinates":[4.3837800026,50.7607765198],"type":"Point"}
}