{
  "type": "Feature",
  "properties": {
    "iso:country":"BE",
    "sg:address":"Route De Mons 143",
    "sg:city":"Erquelinnes",
    "sg:orig_category":"Brood, gebak and snoepgoed",
    "sg:phone":"+32 71 55 56 64",
    "sg:postcode":"6560",
    "sg:province":"Hainaut",
    "wof:name":"Jean-marc Marcelle",
    "wof:placetype":"venue"
},
  "geometry": {"coordinates":[4.1395797729,50.3097991943],"type":"Point"}
}