{
  "type": "Feature",
  "properties": {
    "addr:full":"Klein Ravels 75 Ravels Antwerpen 2380",
    "addr:housenumber":"75",
    "addr:postcode":"2380",
    "addr:street":"Klein Ravels",
    "iso:country":"BE",
    "sg:address":"Klein Ravels 75",
    "sg:city":"Ravels",
    "sg:orig_category":"M\u00e9decines alternatives",
    "sg:phone":"+32 14 65 06 28",
    "sg:postcode":"2380",
    "sg:province":"Antwerpen",
    "wof:name":"Di\u00cbtist Devue C.",
    "wof:placetype":"venue"
},
  "geometry": {"coordinates":[4.9909567833,51.3778457642],"type":"Point"}
}