{
  "type": "Feature",
  "properties": {
    "addr:full":"Augustijnslei 9 Brasschaat Antwerpen 2930",
    "addr:housenumber":"9",
    "addr:postcode":"2930",
    "addr:street":"Augustijnslei",
    "iso:country":"BE",
    "sg:address":"Augustijnslei 9",
    "sg:city":"Brasschaat",
    "sg:orig_category":"Assurances. Bureaux de poste",
    "sg:phone":"+32 3 651 88 20",
    "sg:postcode":"2930",
    "sg:province":"Antwerpen",
    "wof:name":"De Post",
    "wof:placetype":"venue"
},
  "geometry": {"coordinates":[4.4908428192,51.2905578613],"type":"Point"}
}