{
  "type": "Feature",
  "properties": {
    "addr:full":"Rue Paul Devigne 25 Bruxelles (schaerbeek) Bruxelles-Capitale 1030",
    "addr:housenumber":"25",
    "addr:postcode":"1030",
    "addr:street":"Rue Paul Devigne",
    "iso:country":"BE",
    "sg:address":"Rue Paul Devigne 25",
    "sg:city":"Bruxelles (schaerbeek)",
    "sg:classifiers":[
        {
            "category":"Retail",
            "subcategory":"Auto Repair",
            "type":"Services"
        }
    ],
    "sg:phone":"+32 2 216 73 25",
    "sg:postcode":"1030",
    "sg:province":"Bruxelles-Capitale",
    "sg:tags":[
        "garage"
    ],
    "wof:name":"Marc Garage Sprl",
    "wof:placetype":"venue"
},
  "geometry": {"coordinates":[4.3883428574,50.8580551147],"type":"Point"}
}