{
  "type": "Feature",
  "properties": {
    "addr:full":"Heizegemweg 7 Antwerpen Antwerpen 2030",
    "addr:housenumber":"7",
    "addr:postcode":"2030",
    "addr:street":"Heizegemweg",
    "iso:country":"BE",
    "sg:address":"Heizegemweg 7",
    "sg:city":"Antwerpen",
    "sg:classifiers":[
        {
            "category":"Professional",
            "type":"Services"
        }
    ],
    "sg:phone":"+32 3 542 63 05",
    "sg:postcode":"2030",
    "sg:province":"Antwerpen",
    "sg:tags":[
        "transport"
    ],
    "wof:name":"Brabo & Co Nv",
    "wof:placetype":"venue"
},
  "geometry": {"coordinates":[4.3761591911,51.2671051025],"type":"Point"}
}