{
  "type": "Feature",
  "properties": {
    "addr:full":"Gellenberg 106 Lubbeek Vlaams-Brabant 3210",
    "addr:housenumber":"106",
    "addr:postcode":"3210",
    "addr:street":"Gellenberg",
    "iso:country":"BE",
    "sg:address":"Gellenberg 106",
    "sg:city":"Lubbeek",
    "sg:orig_category":"Taxi's Taxi's speciale diensten",
    "sg:phone":"+32 16 62 11 48",
    "sg:postcode":"3210",
    "sg:province":"Vlaams-Brabant",
    "wof:name":"G. Ydens",
    "wof:placetype":"venue"
},
  "geometry": {"coordinates":[4.8345141411,50.8905105591],"type":"Point"}
}