{
  "type": "Feature",
  "properties": {
    "addr:full":"Milcampslaan 84 Schaarbeek/schaerbeek Bruxelles-Capitale 1030",
    "addr:housenumber":"84",
    "addr:postcode":"1030",
    "addr:street":"Milcampslaan",
    "iso:country":"BE",
    "sg:address":"Milcampslaan 84",
    "sg:city":"Schaarbeek/schaerbeek",
    "sg:orig_category":"Apotheken",
    "sg:phone":"+32 2 733 73 46",
    "sg:postcode":"1030",
    "sg:province":"Bruxelles-Capitale",
    "wof:name":"Multipharma",
    "wof:placetype":"venue"
},
  "geometry": {"coordinates":[4.3940048218,50.8501625061],"type":"Point"}
}