{
  "type": "Feature",
  "properties": {
    "addr:full":"Weg Naar As 31 Genk Limburg 3600",
    "addr:housenumber":"31",
    "addr:postcode":"3600",
    "addr:street":"Weg Naar As",
    "iso:country":"BE",
    "sg:address":"Weg Naar As 31",
    "sg:city":"Genk",
    "sg:classifiers":[
        {
            "category":"Health Services",
            "subcategory":"Doctor",
            "type":"Services"
        }
    ],
    "sg:phone":"+32 89 32 90 32",
    "sg:postcode":"3600",
    "sg:province":"Limburg",
    "sg:tags":[
        "medicinephysicians",
        "surgeon"
    ],
    "wof:name":"Jaspers H",
    "wof:placetype":"venue"
},
  "geometry": {"coordinates":[5.5340800285,50.982219696],"type":"Point"}
}