{
  "type": "Feature",
  "properties": {
    "iso:country":"BE",
    "sg:address":"Bevrijdingslaan 137",
    "sg:city":"Gent",
    "sg:classifiers":[
        {
            "category":"Cemetery",
            "type":"Public Place"
        }
    ],
    "sg:phone":"+32 9 227 78 76",
    "sg:postcode":"9000",
    "sg:province":"Oost-Vlaanderen",
    "sg:tags":[
        "crematory"
    ],
    "wof:name":"Verniers J",
    "wof:placetype":"venue"
},
  "geometry": {"coordinates":[3.6988580227,51.0623817444],"type":"Point"}
}