{
  "type": "Feature",
  "properties": {
    "iso:country":"BE",
    "sg:address":"Schuilhoekstraat 8",
    "sg:city":"Sint-gillis-waas",
    "sg:orig_category":"Rundveehouders",
    "sg:phone":"+32 3 770 74 00",
    "sg:postcode":"9170",
    "sg:province":"Oost-Vlaanderen",
    "wof:name":"Bert Waterschoot",
    "wof:placetype":"venue"
},
  "geometry": {"coordinates":[4.1557102203,51.2052688599],"type":"Point"}
}