{
  "type": "Feature",
  "properties": {
    "addr:full":"Herestraat 167 Zonhoven Limburg 3520",
    "addr:housenumber":"167",
    "addr:postcode":"3520",
    "addr:street":"Herestraat",
    "iso:country":"BE",
    "sg:address":"Herestraat 167",
    "sg:city":"Zonhoven",
    "sg:orig_category":"HERSTELLING ELEKTRISCHE HUISHOUDAPPARATEN Huishoudapparaten, televisies and radio's",
    "sg:phone":"+32 11 81 57 75",
    "sg:postcode":"3520",
    "sg:province":"Limburg",
    "wof:name":"Ronny Polmans",
    "wof:placetype":"venue"
},
  "geometry": {"coordinates":[5.3899841309,50.9908370972],"type":"Point"}
}