{
  "type": "Feature",
  "properties": {
    "addr:full":"Rue Vaux 378 Trooz Li\u00e8ge 4870",
    "addr:housenumber":"378",
    "addr:postcode":"4870",
    "addr:street":"Rue Vaux",
    "iso:country":"BE",
    "sg:address":"Rue Vaux 378",
    "sg:city":"Trooz",
    "sg:orig_category":"Landmeters",
    "sg:phone":"+32 87 26 70 70",
    "sg:postcode":"4870",
    "sg:province":"Li\u00e8ge",
    "wof:name":"Ferdinand Dehousse",
    "wof:placetype":"venue"
},
  "geometry": {"coordinates":[5.7343401909,50.5855255127],"type":"Point"}
}