{
  "type": "Feature",
  "properties": {
    "addr:full":"Bruggestraat 41 Tielt West-Vlaanderen 8700",
    "addr:housenumber":"41",
    "addr:postcode":"8700",
    "addr:street":"Bruggestraat",
    "iso:country":"BE",
    "sg:address":"Bruggestraat 41",
    "sg:city":"Tielt",
    "sg:classifiers":[
        {
            "category":"Real Estate",
            "subcategory":"Architect",
            "type":"Services"
        }
    ],
    "sg:phone":"+32 51 40 03 14",
    "sg:postcode":"8700",
    "sg:province":"West-Vlaanderen",
    "wof:name":"Deleu M",
    "wof:placetype":"venue"
},
  "geometry": {"coordinates":[3.3254179955,51.0015029907],"type":"Point"}
}