{
  "type": "Feature",
  "properties": {
    "iso:country":"BE",
    "sg:address":"Groentemarkt 12",
    "sg:city":"Lokeren",
    "sg:orig_category":"Kapsalons",
    "sg:phone":"+32 9 348 04 46",
    "sg:postcode":"9160",
    "sg:province":"Oost-Vlaanderen",
    "wof:name":"Kreatos",
    "wof:placetype":"venue"
},
  "geometry": {"coordinates":[3.9880518913,51.1038970947],"type":"Point"}
}