{
  "type": "Feature",
  "properties": {
    "iso:country":"BE",
    "sg:address":"Rue Paul Vassart 36",
    "sg:city":"Fleurus",
    "sg:orig_category":"Elektrische installaties voor woningen",
    "sg:phone":"+32 71 81 81 19",
    "sg:postcode":"6220",
    "sg:province":"Hainaut",
    "wof:name":"Dominique Poulain",
    "wof:placetype":"venue"
},
  "geometry": {"coordinates":[4.5491728783,50.4847297668],"type":"Point"}
}