{
  "type": "Feature",
  "properties": {
    "addr:full":"Grote Steenweg 121a Zulte (olsene) Oost-Vlaanderen 9870",
    "addr:housenumber":"121a",
    "addr:postcode":"9870",
    "addr:street":"Grote Steenweg",
    "iso:country":"BE",
    "sg:address":"Grote Steenweg 121a",
    "sg:city":"Zulte (olsene)",
    "sg:classifiers":[
        {
            "category":"Professional",
            "subcategory":"Art Services",
            "type":"Services"
        }
    ],
    "sg:phone":"+32 9 388 83 35",
    "sg:postcode":"9870",
    "sg:province":"Oost-Vlaanderen",
    "sg:tags":[
        "photographer"
    ],
    "wof:name":"Foto Andr\u00e9",
    "wof:placetype":"venue"
},
  "geometry": {"coordinates":[3.4628899097,50.9343109131],"type":"Point"}
}