{
  "type": "Feature",
  "properties": {
    "iso:country":"BE",
    "sg:address":"Ankerstraat 59",
    "sg:city":"Sint-niklaas",
    "sg:orig_category":"V\u00eatements pour b\u00e9b\u00e9s and enfants",
    "sg:phone":"+32 3 777 79 19",
    "sg:postcode":"9100",
    "sg:province":"Oost-Vlaanderen",
    "wof:name":"Huis Kwispel",
    "wof:placetype":"venue"
},
  "geometry": {"coordinates":[4.1457247734,51.1656837463],"type":"Point"}
}