{
  "type": "Feature",
  "properties": {
    "addr:full":"Rue Champ Du Monceau 17 Les Bons Villers Hainaut 6210",
    "addr:housenumber":"17",
    "addr:postcode":"6210",
    "addr:street":"Rue Champ Du Monceau",
    "iso:country":"BE",
    "sg:address":"Rue Champ Du Monceau 17",
    "sg:city":"Les Bons Villers",
    "sg:classifiers":[
        {
            "category":"Arena",
            "subcategory":"Sports Club",
            "type":"Entertainment"
        }
    ],
    "sg:phone":"+32 71 85 31 96",
    "sg:postcode":"6210",
    "sg:province":"Hainaut",
    "sg:tags":[
        "de"
    ],
    "wof:name":"V.c. Lodelinsart",
    "wof:placetype":"venue"
},
  "geometry": {"coordinates":[4.4511561394,50.5378227234],"type":"Point"}
}