{
  "type": "Feature",
  "properties": {
    "addr:full":"Witvenstraat 57 Stabroek Antwerpen 2940",
    "addr:housenumber":"57",
    "addr:postcode":"2940",
    "addr:street":"Witvenstraat",
    "iso:country":"BE",
    "sg:address":"Witvenstraat 57",
    "sg:city":"Stabroek",
    "sg:classifiers":[
        {
            "category":"Organizations",
            "subcategory":"Community Association",
            "type":"Services"
        }
    ],
    "sg:phone":"+32 3 664 87 18",
    "sg:postcode":"2940",
    "sg:province":"Antwerpen",
    "sg:tags":[
        "organisation"
    ],
    "wof:name":"Jeugdhuis \u00b4t Stabhoe",
    "wof:placetype":"venue"
},
  "geometry": {"coordinates":[4.3649148941,51.331943512],"type":"Point"}
}