{
  "type": "Feature",
  "properties": {
    "iso:country":"BE",
    "sg:address":"P.i. Taymansstraat 101",
    "sg:city":"Overijse",
    "sg:orig_category":"Producteurs de fruits",
    "sg:phone":"+32 2 687 62 80",
    "sg:postcode":"3090",
    "sg:province":"Vlaams-Brabant",
    "wof:name":"Romain Nedergedaelt",
    "wof:placetype":"venue"
},
  "geometry": {"coordinates":[4.535132885,50.7808380127],"type":"Point"}
}