{
  "type": "Feature",
  "properties": {
    "iso:country":"BE",
    "sg:address":"Rue De Ciney 8",
    "sg:city":"Ohey",
    "sg:classifiers":[
        {
            "category":"Bus Stop",
            "subcategory":"None",
            "type":"Transportation"
        }
    ],
    "sg:phone":"+32 85 61 60 20",
    "sg:postcode":"5350",
    "sg:province":"Namur",
    "sg:tags":[
        "public",
        "transport"
    ],
    "wof:name":"Tec Namur-luxembourg",
    "wof:placetype":"venue"
},
  "geometry": {"coordinates":[5.1256837845,50.4298706055],"type":"Point"}
}