{
  "type": "Feature",
  "properties": {
    "iso:country":"BE",
    "sg:address":"Rue Guillaume Boline 9",
    "sg:city":"Braives (fallais)",
    "sg:classifiers":[
        {
            "category":"Professional",
            "subcategory":"Computer Services",
            "type":"Services"
        }
    ],
    "sg:phone":"+32 479 43 01 70",
    "sg:postcode":"4260",
    "sg:province":"Li\u00e8ge",
    "sg:tags":[
        "network"
    ],
    "wof:name":"Wasatec Informatique",
    "wof:placetype":"venue"
},
  "geometry": {"coordinates":[5.1756157875,50.6104621887],"type":"Point"}
}