{
  "type": "Feature",
  "properties": {
    "iso:country":"BE",
    "sg:address":"Bilkhaeghelaan 22",
    "sg:city":"Waregem",
    "sg:orig_category":"Gespecialiseerde niet-residenti\u00eble bouw",
    "sg:phone":"+32 56 60 14 77",
    "sg:postcode":"8790",
    "sg:province":"West-Vlaanderen",
    "wof:name":"Algoet",
    "wof:placetype":"venue"
},
  "geometry": {"coordinates":[3.4138200283,50.8968696594],"type":"Point"}
}