{
  "type": "Feature",
  "properties": {
    "iso:country":"BE",
    "sg:address":"Houtmolenstraat 56",
    "sg:city":"Overpelt",
    "sg:classifiers":[
        {
            "category":"Bakery",
            "type":"Food & Drink"
        }
    ],
    "sg:phone":"+32 11 64 20 48",
    "sg:postcode":"3900",
    "sg:province":"Limburg",
    "sg:tags":[
        "confectioner",
        "baker"
    ],
    "wof:name":"Schonkeren Bvba",
    "wof:placetype":"venue"
},
  "geometry": {"coordinates":[5.420817852,51.218044281],"type":"Point"}
}