{
  "type": "Feature",
  "properties": {
    "addr:full":"Kopshoeven 22 Lommel Limburg 3920",
    "addr:housenumber":"22",
    "addr:postcode":"3920",
    "addr:street":"Kopshoeven",
    "iso:country":"BE",
    "sg:address":"Kopshoeven 22",
    "sg:city":"Lommel",
    "sg:classifiers":[
        {
            "category":"Health Services",
            "subcategory":"Health Practitioner",
            "type":"Services"
        }
    ],
    "sg:phone":"+32 11 54 21 26",
    "sg:postcode":"3920",
    "sg:province":"Limburg",
    "sg:tags":[
        "physiotherapist"
    ],
    "wof:name":"Claes Philippe",
    "wof:placetype":"venue"
},
  "geometry": {"coordinates":[5.2999248505,51.2274703979],"type":"Point"}
}