{
  "type": "Feature",
  "properties": {
    "iso:country":"BE",
    "sg:address":"Dorpsstraat 55",
    "sg:city":"Berlaar",
    "sg:classifiers":[
        {
            "category":"Social Services",
            "subcategory":"Job Training",
            "type":"Services"
        }
    ],
    "sg:phone":"+32 3 482 46 64",
    "sg:postcode":"2590",
    "sg:province":"Antwerpen",
    "sg:tags":[
        "personnel",
        "-selection",
        "recruitment"
    ],
    "wof:name":"Banen Team Belgi\u00eb-regio Antwerpen",
    "wof:placetype":"venue"
},
  "geometry": {"coordinates":[4.6520671844,51.116985321],"type":"Point"}
}