{
  "type": "Feature",
  "properties": {
    "iso:country":"BE",
    "sg:address":"Sint-willibrordusplein 26",
    "sg:city":"Heusden-zolder (heusden)",
    "sg:classifiers":[
        {
            "category":"Shopping",
            "subcategory":"Photographic Equipment",
            "type":"Retail Goods"
        }
    ],
    "sg:phone":"+32 11 43 78 90",
    "sg:postcode":"3550",
    "sg:province":"Limburg",
    "sg:tags":[
        "supplie",
        "billiard",
        "-"
    ],
    "wof:name":"Vlaamse Pool Billiard Federatie Limburg Vzw",
    "wof:placetype":"venue"
},
  "geometry": {"coordinates":[5.280684948,51.0330352783],"type":"Point"}
}