{
  "type": "Feature",
  "properties": {
    "iso:country":"BE",
    "sg:address":"Le Reposoir 7",
    "sg:city":"Manage",
    "sg:orig_category":"Woningbouw",
    "sg:phone":"+32 64 55 91 48",
    "sg:postcode":"7170",
    "sg:province":"Hainaut",
    "wof:name":"Ceschin",
    "wof:placetype":"venue"
},
  "geometry": {"coordinates":[4.232211113,50.4790763855],"type":"Point"}
}