{
  "type": "Feature",
  "properties": {
    "addr:full":"Blijde-inkomststraat 3 Antwerpen Antwerpen 2140",
    "addr:housenumber":"3",
    "addr:postcode":"2140",
    "addr:street":"Blijde-Inkomststraat",
    "iso:country":"BE",
    "sg:address":"Blijde-inkomststraat 3",
    "sg:city":"Antwerpen",
    "sg:orig_category":"Maatschappelijke dienstverlening",
    "sg:phone":"+32 3 236 26 80",
    "sg:postcode":"2140",
    "sg:province":"Antwerpen",
    "wof:name":"Vclb-centrum",
    "wof:placetype":"venue"
},
  "geometry": {"coordinates":[4.4332199097,51.2137565613],"type":"Point"}
}