{
  "type": "Feature",
  "properties": {
    "addr:full":"Avenue De L'union 25bc Ans Li\u00e8ge 4432",
    "addr:housenumber":"25bc",
    "addr:postcode":"4432",
    "addr:street":"Avenue De L'Union",
    "iso:country":"BE",
    "sg:address":"Avenue De L'union 25bc",
    "sg:city":"Ans",
    "sg:orig_category":"Epiceries",
    "sg:phone":"+32 4 247 08 73",
    "sg:postcode":"4432",
    "sg:province":"Li\u00e8ge",
    "wof:name":"L.g.l.",
    "wof:placetype":"venue"
},
  "geometry": {"coordinates":[5.5242800713,50.6659317017],"type":"Point"}
}