{
  "type": "Feature",
  "properties": {
    "addr:full":"Chauss\u00e9e De Drogenbos 187 Bruxelles (uccle) Bruxelles-Capitale 1180",
    "addr:housenumber":"187",
    "addr:postcode":"1180",
    "addr:street":"Chausse\u0301E De Drogenbos",
    "iso:country":"BE",
    "sg:address":"Chauss\u00e9e De Drogenbos 187",
    "sg:city":"Bruxelles (uccle)",
    "sg:classifiers":[
        {
            "category":"Wholesale",
            "subcategory":"Chemicals & Plastics",
            "type":"Manufacturing & Wholesale Goods"
        }
    ],
    "sg:phone":"+32 2 332 32 55",
    "sg:postcode":"1180",
    "sg:province":"Bruxelles-Capitale",
    "sg:tags":[
        "packing"
    ],
    "wof:name":"Transfobel Plastics Nv",
    "wof:placetype":"venue"
},
  "geometry": {"coordinates":[4.322704792,50.7863349915],"type":"Point"}
}