{
  "type": "Feature",
  "properties": {
    "iso:country":"BE",
    "sg:address":"Steenweg Op Oosthoven 152b1",
    "sg:city":"Turnhout",
    "sg:orig_category":"Studios photographiques. Bijouteries and horlogeries",
    "sg:phone":"+32 14 43 76 58",
    "sg:postcode":"2300",
    "sg:province":"Antwerpen",
    "wof:name":"Fons Dehouwer",
    "wof:placetype":"venue"
},
  "geometry": {"coordinates":[4.9560461044,51.3310508728],"type":"Point"}
}