{
  "type": "Feature",
  "properties": {
    "addr:full":"Grootzand 80 Dendermonde Oost-Vlaanderen 9200",
    "addr:housenumber":"80",
    "addr:postcode":"9200",
    "addr:street":"Grootzand;Oost-Vlaanderen",
    "iso:country":"BE",
    "sg:address":"Grootzand 80",
    "sg:city":"Dendermonde",
    "sg:orig_category":"Produits surgel\u00e9s Pain, p\u00e2tisseries and confiseries",
    "sg:phone":"+32 52 21 90 74",
    "sg:postcode":"9200",
    "sg:province":"Oost-Vlaanderen",
    "wof:name":"De Vershoek",
    "wof:placetype":"venue"
},
  "geometry": {"coordinates":[4.106593132,51.0453834534],"type":"Point"}
}