{
  "type": "Feature",
  "properties": {
    "addr:full":"Pioenstraat 7 Brugge (assebroek) West-Vlaanderen 8310",
    "addr:housenumber":"7",
    "addr:postcode":"8310",
    "addr:street":"Pioenstraat",
    "iso:country":"BE",
    "sg:address":"Pioenstraat 7",
    "sg:city":"Brugge (assebroek)",
    "sg:classifiers":[
        {
            "category":"Building & Trades",
            "subcategory":"Electrical",
            "type":"Services"
        }
    ],
    "sg:phone":"+32 50 35 71 56",
    "sg:postcode":"8310",
    "sg:province":"West-Vlaanderen",
    "sg:tags":[
        "-",
        "electric",
        "contractor"
    ],
    "wof:name":"Devos K",
    "wof:placetype":"venue"
},
  "geometry": {"coordinates":[3.2381539345,51.1956520081],"type":"Point"}
}