{
  "type": "Feature",
  "properties": {
    "iso:country":"BE",
    "sg:address":"Rue Du Commerce 9",
    "sg:city":"Pont-a-celles",
    "sg:orig_category":"Avocats and conseillers juridiques",
    "sg:phone":"+32 71 84 55 52",
    "sg:postcode":"6238",
    "sg:province":"Hainaut",
    "wof:name":"J. Renson",
    "wof:placetype":"venue"
},
  "geometry": {"coordinates":[4.3920850754,50.508895874],"type":"Point"}
}