{
  "type": "Feature",
  "properties": {
    "iso:country":"BE",
    "sg:address":"Zalmstraat 80",
    "sg:city":"Gent",
    "sg:orig_category":"Fotografen and fotostudio's",
    "sg:phone":"+32 9 233 80 78",
    "sg:postcode":"9000",
    "sg:province":"Oost-Vlaanderen",
    "wof:name":"Marc Hoflack",
    "wof:placetype":"venue"
},
  "geometry": {"coordinates":[3.7444720268,51.0466346741],"type":"Point"}
}