{
  "type": "Feature",
  "properties": {
    "addr:full":"Chemin Du Vieux Comt\u00c9 4 Tournai Hainaut 7542",
    "addr:housenumber":"4",
    "addr:postcode":"7542",
    "addr:street":"Chemin Du Vieux Comte\u0301",
    "iso:country":"BE",
    "sg:address":"Chemin Du Vieux Comt\u00c9 4",
    "sg:city":"Tournai",
    "sg:orig_category":"Traitements param\u00e9dicaux",
    "sg:phone":"+32 69 85 92 35",
    "sg:postcode":"7542",
    "sg:province":"Hainaut",
    "wof:name":"R. Deffontaines",
    "wof:placetype":"venue"
},
  "geometry": {"coordinates":[3.4130489826,50.6610031128],"type":"Point"}
}