{
  "type": "Feature",
  "properties": {
    "addr:full":"Chauss\u00e9e De Wavre 102 Bruxelles (ixelles) Bruxelles-Capitale 1050",
    "addr:housenumber":"102",
    "addr:postcode":"1050",
    "addr:street":"Chausse\u0301E De Wavre",
    "iso:country":"BE",
    "sg:address":"Chauss\u00e9e De Wavre 102",
    "sg:city":"Bruxelles (ixelles)",
    "sg:classifiers":[
        {
            "category":"Personal",
            "subcategory":"Beauty Salon",
            "type":"Services"
        }
    ],
    "sg:phone":"+32 2 511 40 44",
    "sg:postcode":"1050",
    "sg:province":"Bruxelles-Capitale",
    "sg:tags":[
        "lady",
        "-",
        "hairdressing"
    ],
    "wof:name":"Big'es Coiffure",
    "wof:placetype":"venue"
},
  "geometry": {"coordinates":[4.3668851852,50.8366584778],"type":"Point"}
}