{
  "type": "Feature",
  "properties": {
    "iso:country":"BE",
    "sg:address":"Vaartlaan 8",
    "sg:city":"Brecht",
    "sg:classifiers":[
        {
            "category":"Arena",
            "subcategory":"Sports Club",
            "type":"Entertainment"
        }
    ],
    "sg:phone":"+32 3 636 11 91",
    "sg:postcode":"2960",
    "sg:province":"Antwerpen",
    "sg:tags":[
        "de"
    ],
    "wof:name":"Sint Job Yacht Club",
    "wof:placetype":"venue"
},
  "geometry": {"coordinates":[4.6441230774,51.3472747803],"type":"Point"}
}