{
  "type": "Feature",
  "properties": {
    "addr:full":"Rue Des Abbesses 11 Vorst/forest Bruxelles-Capitale 1190",
    "addr:housenumber":"11",
    "addr:postcode":"1190",
    "addr:street":"Rue Des Abbesses;/ Forest",
    "iso:country":"BE",
    "sg:address":"Rue Des Abbesses 11",
    "sg:city":"Vorst/forest",
    "sg:orig_category":"Maisons de repos and r\u00e9sidences",
    "sg:phone":"+32 2 344 64 21",
    "sg:postcode":"1190",
    "sg:province":"Bruxelles-Capitale",
    "wof:name":"R\u00c9sidence St.denis",
    "wof:placetype":"venue"
},
  "geometry": {"coordinates":[4.3181958199,50.8121757507],"type":"Point"}
}