{
  "type": "Feature",
  "properties": {
    "iso:country":"BE",
    "sg:address":"Rue Des Cheminots 15",
    "sg:city":"Moeskroen/mouscron",
    "sg:orig_category":"Centres de relaxation and bien-\u00eatre. Instituts de beaut\u00e9",
    "sg:phone":"+32 56 84 29 70",
    "sg:postcode":"7712",
    "sg:province":"Hainaut",
    "wof:name":"Institut Charmance",
    "wof:placetype":"venue"
},
  "geometry": {"coordinates":[3.2535879612,50.714931488],"type":"Point"}
}