{
  "type": "Feature",
  "properties": {
    "addr:full":"Kleine Moorsledestraat 12 Ledegem West-Vlaanderen 8880",
    "addr:housenumber":"12",
    "addr:postcode":"8880",
    "addr:street":"Kleine Moorsledestraat",
    "iso:country":"BE",
    "sg:address":"Kleine Moorsledestraat 12",
    "sg:city":"Ledegem",
    "sg:orig_category":"Rundveehouders Varkenskwekers",
    "sg:phone":"+32 56 50 01 56",
    "sg:postcode":"8880",
    "sg:province":"West-Vlaanderen",
    "wof:name":"Andre Deleu",
    "wof:placetype":"venue"
},
  "geometry": {"coordinates":[3.1088559628,50.8764915466],"type":"Point"}
}