{
  "type": "Feature",
  "properties": {
    "iso:country":"BE",
    "sg:address":"Rue Haute Pr\u00c9alle 16",
    "sg:city":"Herstal",
    "sg:orig_category":"Woningbouw",
    "sg:phone":"+32 4 264 13 75",
    "sg:postcode":"4040",
    "sg:province":"Li\u00e8ge",
    "wof:name":"Renovat Batiments",
    "wof:placetype":"venue"
},
  "geometry": {"coordinates":[5.6181230545,50.6698799133],"type":"Point"}
}