{
  "type": "Feature",
  "properties": {
    "addr:full":"Rue Taverne De Maire 2 Tournai Hainaut 7503",
    "addr:housenumber":"2",
    "addr:postcode":"7503",
    "addr:street":"Rue Taverne De Maire",
    "iso:country":"BE",
    "sg:address":"Rue Taverne De Maire 2",
    "sg:city":"Tournai",
    "sg:orig_category":"Boucheries",
    "sg:phone":"+32 69 21 13 93",
    "sg:postcode":"7503",
    "sg:province":"Hainaut",
    "wof:name":"Renmans",
    "wof:placetype":"venue"
},
  "geometry": {"coordinates":[3.3782989979,50.6128120422],"type":"Point"}
}