{
  "type": "Feature",
  "properties": {
    "addr:full":"Place Communale 14 Silly Hainaut 7830",
    "addr:housenumber":"14",
    "addr:postcode":"7830",
    "addr:street":"Place Communale",
    "iso:country":"BE",
    "sg:address":"Place Communale 14",
    "sg:city":"Silly",
    "sg:orig_category":"Boucheries",
    "sg:phone":"+32 68 55 31 11",
    "sg:postcode":"7830",
    "sg:province":"Hainaut",
    "wof:name":"Fa. Crusiau Liban",
    "wof:placetype":"venue"
},
  "geometry": {"coordinates":[3.9237210751,50.6488418579],"type":"Point"}
}