{
  "type": "Feature",
  "properties": {
    "addr:full":"Oranjestraat 23a Box 18 Antwerpen Antwerpen 2060",
    "addr:housenumber":"23a box 18",
    "addr:postcode":"2060",
    "addr:street":"Oranjestraat",
    "iso:country":"BE",
    "sg:address":"Oranjestraat 23a Box 18",
    "sg:city":"Antwerpen",
    "sg:classifiers":[
        {
            "category":"Airport",
            "subcategory":"General Aviation",
            "type":"Transportation"
        }
    ],
    "sg:phone":"+32 3 233 33 32",
    "sg:postcode":"2060",
    "sg:province":"Antwerpen",
    "sg:tags":[
        "transport"
    ],
    "wof:name":"Rapid Tax",
    "wof:placetype":"venue"
},
  "geometry": {"coordinates":[4.4198431969,51.2274398804],"type":"Point"}
}