{
  "type": "Feature",
  "properties": {
    "iso:country":"BE",
    "sg:address":"Rue L\u00e9on Th\u00e9odor 146",
    "sg:city":"Jette",
    "sg:classifiers":[
        {
            "category":"Manufacturing",
            "subcategory":"Paper Products",
            "type":"Manufacturing & Wholesale Goods"
        }
    ],
    "sg:phone":"+32 2 426 22 31",
    "sg:postcode":"1090",
    "sg:province":"Bruxelles-Capitale",
    "sg:tags":[
        "finished",
        "cardboard",
        "-"
    ],
    "wof:name":"Imprimerie Emile De Boeck Sprl",
    "wof:placetype":"venue"
},
  "geometry": {"coordinates":[4.328207016,50.8772087097],"type":"Point"}
}