{
  "type": "Feature",
  "properties": {
    "iso:country":"BE",
    "sg:address":"Gravin De Merodestraat 45",
    "sg:city":"Westerlo",
    "sg:classifiers":[
        {
            "category":"Shopping",
            "subcategory":"Jewelry",
            "type":"Retail Goods"
        }
    ],
    "sg:phone":"+32 16 69 79 19",
    "sg:postcode":"2260",
    "sg:province":"Antwerpen",
    "sg:tags":[
        "fab",
        "bijou"
    ],
    "wof:name":"Lieve Stroeckx",
    "wof:placetype":"venue"
},
  "geometry": {"coordinates":[4.9106450081,51.0869255066],"type":"Point"}
}