{
  "type": "Feature",
  "properties": {
    "addr:full":"Zammelseweg 1a Geel Antwerpen 2440",
    "addr:housenumber":"1a",
    "addr:postcode":"2440",
    "addr:street":"Zammelseweg",
    "iso:country":"BE",
    "sg:address":"Zammelseweg 1a",
    "sg:city":"Geel",
    "sg:classifiers":[
        {
            "category":"Health Services",
            "subcategory":"Nursing And Care Facility",
            "type":"Services"
        }
    ],
    "sg:phone":"+32 14 86 83 43",
    "sg:postcode":"2440",
    "sg:province":"Antwerpen",
    "sg:tags":[
        "home",
        "rest"
    ],
    "wof:name":"Huis Perrekes Vzw",
    "wof:placetype":"venue"
},
  "geometry": {"coordinates":[4.9757227898,51.1083297729],"type":"Point"}
}