{
  "type": "Feature",
  "properties": {
    "iso:country":"BE",
    "sg:address":"Koning Albertstraat 125",
    "sg:city":"Ravels (weelde)",
    "sg:classifiers":[
        {
            "category":"Bars & Pubs",
            "type":"Food & Drink"
        }
    ],
    "sg:phone":"+32 14 65 94 48",
    "sg:postcode":"2381",
    "sg:province":"Antwerpen",
    "wof:name":"Dijk (den)",
    "wof:placetype":"venue"
},
  "geometry": {"coordinates":[4.9994158745,51.4106712341],"type":"Point"}
}