{
  "type": "Feature",
  "properties": {
    "addr:full":"Kattespoelstraat 3 Beerse Antwerpen 2340",
    "addr:housenumber":"3",
    "addr:postcode":"2340",
    "addr:street":"Kattespoelstraat",
    "iso:country":"BE",
    "sg:address":"Kattespoelstraat 3",
    "sg:city":"Beerse",
    "sg:orig_category":"Kruideniers Slagers",
    "sg:phone":"+32 14 61 73 72",
    "sg:postcode":"2340",
    "sg:province":"Antwerpen",
    "wof:name":"Supermarkt",
    "wof:placetype":"venue"
},
  "geometry": {"coordinates":[4.8689470291,51.3193244934],"type":"Point"}
}