{
  "type": "Feature",
  "properties": {
    "addr:full":"Rue Du Berceau 62 Villers-la-ville Brabant Wallon 1495",
    "addr:housenumber":"62",
    "addr:postcode":"1495",
    "addr:street":"Rue Du Berceau",
    "iso:country":"BE",
    "sg:address":"Rue Du Berceau 62",
    "sg:city":"Villers-la-ville",
    "sg:orig_category":"HERSTELLING ELEKTRISCHE HUISHOUDAPPARATEN Huishoudapparaten, televisies and radio's",
    "sg:phone":"+32 71 87 93 28",
    "sg:postcode":"1495",
    "sg:province":"Brabant Wallon",
    "wof:name":"Fonteyn",
    "wof:placetype":"venue"
},
  "geometry": {"coordinates":[4.530477047,50.5786132812],"type":"Point"}
}