{
  "type": "Feature",
  "properties": {
    "iso:country":"BE",
    "sg:address":"Hansbekestraat 27",
    "sg:city":"Nevele",
    "sg:orig_category":"Rundveehouders Varkenskwekers",
    "sg:phone":"+32 9 371 75 94",
    "sg:postcode":"9850",
    "sg:province":"Oost-Vlaanderen",
    "wof:name":"Patrick De Vreeze",
    "wof:placetype":"venue"
},
  "geometry": {"coordinates":[3.5585379601,51.0732460022],"type":"Point"}
}