{
  "type": "Feature",
  "properties": {
    "iso:country":"BE",
    "sg:address":"Franklin Rooseveltlaan 124",
    "sg:city":"Vilvoorde",
    "sg:classifiers":[
        {
            "category":"Building & Trades",
            "subcategory":"Equipment Rental",
            "type":"Services"
        }
    ],
    "sg:phone":"+32 2 252 30 18",
    "sg:postcode":"1800",
    "sg:province":"Vlaams-Brabant",
    "sg:tags":[
        "sound",
        "-",
        "system"
    ],
    "wof:name":"D.e.s. Bvba",
    "wof:placetype":"venue"
},
  "geometry": {"coordinates":[4.4261279106,50.9300994873],"type":"Point"}
}