{
  "type": "Feature",
  "properties": {
    "iso:country":"BE",
    "sg:address":"Rue Des Paquerettes 2",
    "sg:city":"Oupeye",
    "sg:orig_category":"Sportclubs",
    "sg:phone":"+32 4 278 57 43",
    "sg:postcode":"4680",
    "sg:province":"Li\u00e8ge",
    "wof:name":"J.c. Herm\u00c9e",
    "wof:placetype":"venue"
},
  "geometry": {"coordinates":[5.6182799339,50.7029914856],"type":"Point"}
}