{
  "type": "Feature",
  "properties": {
    "iso:country":"BE",
    "sg:address":"Rue Hector Fontaine 39",
    "sg:city":"Beloeil",
    "sg:orig_category":"Studios photographiques. Laboratoires photographiques. Equipement photographique",
    "sg:phone":"+32 69 57 87 20",
    "sg:postcode":"7973",
    "sg:province":"Hainaut",
    "wof:name":"Michel Plasschaert",
    "wof:placetype":"venue"
},
  "geometry": {"coordinates":[3.7125480175,50.5003242493],"type":"Point"}
}