{
  "type": "Feature",
  "properties": {
    "addr:full":"Driehoekstr 79 Kerksken Oost-Vlaanderen 9451",
    "addr:housenumber":"79",
    "addr:postcode":"9451",
    "addr:street":"Driehoekstr",
    "iso:country":"BE",
    "sg:address":"Driehoekstr 79",
    "sg:city":"Kerksken",
    "sg:classifiers":[
        {
            "category":"Banks & Credit Unions",
            "subcategory":"Bank",
            "type":"Services"
        }
    ],
    "sg:phone":"+32 53 83 15 04",
    "sg:postcode":"9451",
    "sg:province":"Oost-Vlaanderen",
    "wof:name":"G\u00e9n\u00e9rale De Banque Sa",
    "wof:placetype":"venue"
},
  "geometry": {"coordinates":[3.9824500084,50.8868293762],"type":"Point"}
}