{
  "type": "Feature",
  "properties": {
    "addr:full":"Grand Rue 61 Sivry-rance Hainaut 6470",
    "addr:housenumber":"61",
    "addr:postcode":"6470",
    "addr:street":"Grand Rue",
    "iso:country":"BE",
    "sg:address":"Grand Rue 61",
    "sg:city":"Sivry-rance",
    "sg:orig_category":"Kapsalons",
    "sg:phone":"+32 60 41 20 69",
    "sg:postcode":"6470",
    "sg:province":"Hainaut",
    "wof:name":"Raymond Matot",
    "wof:placetype":"venue"
},
  "geometry": {"coordinates":[4.2739768028,50.1426124573],"type":"Point"}
}