{
  "type": "Feature",
  "properties": {
    "addr:full":"De Vilanderstraat 17 Aalst Oost-Vlaanderen 9300",
    "addr:housenumber":"17",
    "addr:postcode":"9300",
    "addr:street":"Vilanderstraat",
    "iso:country":"BE",
    "sg:address":"De Vilanderstraat 17",
    "sg:city":"Aalst",
    "sg:classifiers":[
        {
            "category":"Real Estate",
            "subcategory":"Architect",
            "type":"Services"
        }
    ],
    "sg:phone":"+32 53 77 76 52",
    "sg:postcode":"9300",
    "sg:province":"Oost-Vlaanderen",
    "wof:name":"Van Den Eynde S",
    "wof:placetype":"venue"
},
  "geometry": {"coordinates":[4.0466451645,50.9341087341],"type":"Point"}
}