{
  "type": "Feature",
  "properties": {
    "iso:country":"BE",
    "sg:address":"Koningsstraat 37",
    "sg:city":"Leopoldsburg",
    "sg:orig_category":"Diverse kredietdiensten",
    "sg:postcode":"3970",
    "sg:province":"Limburg",
    "wof:name":"Bancontact-mister Cash",
    "wof:placetype":"venue"
},
  "geometry": {"coordinates":[5.2596759796,51.1163291931],"type":"Point"}
}