{
  "type": "Feature",
  "properties": {
    "iso:country":"BE",
    "sg:address":"Sint-maartenplein 3",
    "sg:city":"Hasselt",
    "sg:orig_category":"Banques and organismes de cr\u00e9dit",
    "sg:phone":"+32 11 31 32 88",
    "sg:postcode":"3512",
    "sg:province":"Limburg",
    "wof:name":"Fortis",
    "wof:placetype":"venue"
},
  "geometry": {"coordinates":[5.2483258247,50.9166564941],"type":"Point"}
}