{
  "type": "Feature",
  "properties": {
    "iso:country":"BE",
    "sg:address":"Geelsebaan 44 Box 3",
    "sg:city":"Kasterlee",
    "sg:classifiers":[
        {
            "category":"Real Estate",
            "subcategory":"Architect",
            "type":"Services"
        }
    ],
    "sg:phone":"+32 14 85 36 12",
    "sg:postcode":"2460",
    "sg:province":"Antwerpen",
    "wof:name":"Van Olmen F",
    "wof:placetype":"venue"
},
  "geometry": {"coordinates":[4.9685769081,51.2377891541],"type":"Point"}
}