{
  "type": "Feature",
  "properties": {
    "addr:full":"Aldestraat 18 Hasselt Limburg 3500",
    "addr:housenumber":"18",
    "addr:postcode":"3500",
    "addr:street":"Aldestraat",
    "iso:country":"BE",
    "sg:address":"Aldestraat 18",
    "sg:city":"Hasselt",
    "sg:classifiers":[
        {
            "category":"Shopping",
            "subcategory":"Shoes",
            "type":"Retail Goods"
        }
    ],
    "sg:phone":"+32 11 22 82 60",
    "sg:postcode":"3500",
    "sg:province":"Limburg",
    "sg:tags":[
        "slipper",
        "-"
    ],
    "wof:name":"Zwitsers Huis",
    "wof:placetype":"venue"
},
  "geometry": {"coordinates":[5.3365430832,50.9302253723],"type":"Point"}
}