{
  "type": "Feature",
  "properties": {
    "addr:full":"Rue Du G\u00e9n\u00e9ral Leman 6 Leuze-en-hainaut Hainaut 7900",
    "addr:housenumber":"6",
    "addr:postcode":"7900",
    "addr:street":"Rue Du Ge\u0301Ne\u0301Ral Leman",
    "iso:country":"BE",
    "sg:address":"Rue Du G\u00e9n\u00e9ral Leman 6",
    "sg:city":"Leuze-en-hainaut",
    "sg:classifiers":[
        {
            "category":"Shopping",
            "subcategory":"Stationery & Office Supplies",
            "type":"Retail Goods"
        }
    ],
    "sg:phone":"+32 69 66 56 08",
    "sg:postcode":"7900",
    "sg:province":"Hainaut",
    "wof:name":"Tour (de La)",
    "wof:placetype":"venue"
},
  "geometry": {"coordinates":[3.6193950176,50.6011810303],"type":"Point"}
}