{
  "type": "Feature",
  "properties": {
    "addr:full":"R. Van Elewijk/elewijkstraat 61 Strombeek-bever Vlaams-Brabant 1853",
    "addr:housenumber":"61",
    "addr:postcode":"1853",
    "addr:street":"R.;Elewijkstraat",
    "iso:country":"BE",
    "sg:address":"R. Van Elewijk/elewijkstraat 61",
    "sg:city":"Strombeek-bever",
    "sg:classifiers":[
        {
            "category":"Professional",
            "subcategory":"Computer Services",
            "type":"Services"
        }
    ],
    "sg:phone":"+32 2 267 28 03",
    "sg:postcode":"1853",
    "sg:province":"Vlaams-Brabant",
    "sg:tags":[
        "information",
        "technology",
        "software"
    ],
    "wof:name":"Bob Software Bruxelles",
    "wof:placetype":"venue"
},
  "geometry": {"coordinates":[4.3527231216,50.9039497375],"type":"Point"}
}