{
  "type": "Feature",
  "properties": {
    "iso:country":"BE",
    "sg:address":"Rue De Carignan 11",
    "sg:city":"Florenville",
    "sg:classifiers":[
        {
            "category":"Airport",
            "subcategory":"International",
            "type":"Transportation"
        }
    ],
    "sg:phone":"+32 61 31 55 74",
    "sg:postcode":"6820",
    "sg:province":"Luxembourg",
    "sg:tags":[
        "-",
        "transport"
    ],
    "wof:name":"Wilmes Tony Sprl",
    "wof:placetype":"venue"
},
  "geometry": {"coordinates":[5.3028931618,49.6970329285],"type":"Point"}
}