{
  "type": "Feature",
  "properties": {
    "iso:country":"BE",
    "sg:address":"Bosstraat 43",
    "sg:city":"Lede",
    "sg:orig_category":"Plomberie, chauffage and installations sanitaires",
    "sg:phone":"+32 53 21 43 09",
    "sg:postcode":"9340",
    "sg:province":"Oost-Vlaanderen",
    "wof:name":"Braeckman Geert",
    "wof:placetype":"venue"
},
  "geometry": {"coordinates":[4.0018868446,50.9664649963],"type":"Point"}
}