{
  "type": "Feature",
  "properties": {
    "iso:country":"BE",
    "sg:address":"23",
    "sg:city":"Oosterring 3600 Genk",
    "sg:classifiers":[
        {
            "category":"Autos & Motor Vehicles",
            "subcategory":"Automobile Sales",
            "type":"Retail Goods"
        }
    ],
    "sg:phone":"+32 89 62 38 00",
    "sg:postcode":"23",
    "sg:tags":[
        "equipment",
        "motor-cars",
        "transport"
    ],
    "wof:name":"Terberg Specials Belgium Nv",
    "wof:placetype":"venue"
},
  "geometry": {"coordinates":[5.5324568748,50.9220542908],"type":"Point"}
}