{
  "type": "Feature",
  "properties": {
    "addr:full":"Heksteelstraat 40 Brakel Oost-Vlaanderen 9660",
    "addr:housenumber":"40",
    "addr:postcode":"9660",
    "addr:street":"Heksteelstraat",
    "iso:country":"BE",
    "sg:address":"Heksteelstraat 40",
    "sg:city":"Brakel",
    "sg:classifiers":[
        {
            "category":"Insurance",
            "subcategory":"Insurance Agent",
            "type":"Services"
        }
    ],
    "sg:phone":"+32 55 42 45 00",
    "sg:postcode":"9660",
    "sg:province":"Oost-Vlaanderen",
    "sg:tags":[
        "verzekeringsmakelaars",
        "expert"
    ],
    "wof:name":"Kantoor De Groote W.",
    "wof:placetype":"venue"
},
  "geometry": {"coordinates":[3.7642250061,50.8031082153],"type":"Point"}
}