{
  "type": "Feature",
  "properties": {
    "iso:country":"BE",
    "sg:address":"Avenue Albert 44",
    "sg:city":"Wezembeek-oppem",
    "sg:classifiers":[
        {
            "category":"Education",
            "subcategory":"School",
            "type":"Public Place"
        }
    ],
    "sg:phone":"+32 2 767 35 49",
    "sg:postcode":"1970",
    "sg:province":"Vlaams-Brabant",
    "sg:tags":[
        "secondary"
    ],
    "wof:name":"H Hartcollege Tervuren-mr Moriau",
    "wof:placetype":"venue"
},
  "geometry": {"coordinates":[4.5064969063,50.8314361572],"type":"Point"}
}