{
  "type": "Feature",
  "properties": {
    "addr:full":"Smetstraat 25 Hasselt Limburg 3501",
    "addr:housenumber":"25",
    "addr:postcode":"3501",
    "addr:street":"Smetstraat",
    "iso:country":"BE",
    "sg:address":"Smetstraat 25",
    "sg:city":"Hasselt",
    "sg:orig_category":"Schoonheidssalons",
    "sg:phone":"+32 11 37 13 45",
    "sg:postcode":"3501",
    "sg:province":"Limburg",
    "wof:name":"Monique Motmans",
    "wof:placetype":"venue"
},
  "geometry": {"coordinates":[5.3496479988,50.8830375671],"type":"Point"}
}