{
  "type": "Feature",
  "properties": {
    "iso:country":"BE",
    "sg:address":"Prinses Jos.-charlotteln 15",
    "sg:city":"Sint-niklaas",
    "sg:orig_category":"Agences de presse",
    "sg:phone":"+32 3 766 18 92",
    "sg:postcode":"9100",
    "sg:province":"Oost-Vlaanderen",
    "wof:name":"Yves Vrebos",
    "wof:placetype":"venue"
},
  "geometry": {"coordinates":[4.1461119652,51.153629303],"type":"Point"}
}