{
  "type": "Feature",
  "properties": {
    "addr:full":"Grotestraat 33 Glabbeek Vlaams-Brabant 3380",
    "addr:housenumber":"33",
    "addr:postcode":"3380",
    "addr:street":"Grotestraat",
    "iso:country":"BE",
    "sg:address":"Grotestraat 33",
    "sg:city":"Glabbeek",
    "sg:classifiers":[
        {
            "category":"Government",
            "subcategory":"Police Station",
            "type":"Public Place"
        }
    ],
    "sg:phone":"+32 16 77 29 39",
    "sg:postcode":"3380",
    "sg:province":"Vlaams-Brabant",
    "sg:tags":[
        "gendarmerie"
    ],
    "wof:name":"Federale Politie",
    "wof:placetype":"venue"
},
  "geometry": {"coordinates":[4.956507206,50.8720664978],"type":"Point"}
}