{
  "type": "Feature",
  "properties": {
    "iso:country":"BE",
    "sg:address":"Rennevoortstraat 42",
    "sg:city":"Ledegem",
    "sg:orig_category":"Production de films, t\u00e9l\u00e9films and vid\u00e9os. Studios photographiques",
    "sg:phone":"+32 56 50 40 79",
    "sg:postcode":"8880",
    "sg:province":"West-Vlaanderen",
    "wof:name":"Solar",
    "wof:placetype":"venue"
},
  "geometry": {"coordinates":[3.158757925,50.8835639954],"type":"Point"}
}