{
  "type": "Feature",
  "properties": {
    "iso:country":"BE",
    "sg:address":"Bredabaan 296",
    "sg:city":"Brasschaat",
    "sg:classifiers":[
        {
            "category":"Personal",
            "type":"Services"
        }
    ],
    "sg:phone":"+32 3 651 44 10",
    "sg:postcode":"2930",
    "sg:province":"Antwerpen",
    "sg:tags":[
        "party",
        "planning"
    ],
    "wof:name":"Chopin",
    "wof:placetype":"venue"
},
  "geometry": {"coordinates":[4.492816925,51.2911376953],"type":"Point"}
}