{
  "type": "Feature",
  "properties": {
    "addr:full":"Rue Des Combattants 68 Wavre (bierges) Brabant Wallon 1301",
    "addr:housenumber":"68;1301",
    "addr:street":"Rue Des Combattants",
    "iso:country":"BE",
    "sg:address":"Rue Des Combattants 68",
    "sg:city":"Wavre (bierges)",
    "sg:classifiers":[
        {
            "category":"Food & Beverages",
            "subcategory":"Fruits & Vegetables",
            "type":"Retail Goods"
        }
    ],
    "sg:phone":"+32 10 41 34 09",
    "sg:postcode":"1301",
    "sg:province":"Brabant Wallon",
    "sg:tags":[
        "-"
    ],
    "wof:name":"Au Panier D'or",
    "wof:placetype":"venue"
},
  "geometry": {"coordinates":[4.5815758705,50.7121505737],"type":"Point"}
}