{
  "type": "Feature",
  "properties": {
    "iso:country":"BE",
    "sg:address":"Rue Du Chemineau 42",
    "sg:city":"Qui\u00c9vrain",
    "sg:classifiers":[
        {
            "category":"Arena",
            "subcategory":"Sports Club",
            "type":"Entertainment"
        }
    ],
    "sg:phone":"+32 65 45 77 50",
    "sg:postcode":"7380",
    "sg:province":"Hainaut",
    "sg:tags":[
        "terrain",
        "hors",
        "de",
        "installation",
        "sportifs"
    ],
    "wof:name":"R.u.s. Quievrain",
    "wof:placetype":"venue"
},
  "geometry": {"coordinates":[3.6882219315,50.4032516479],"type":"Point"}
}