{
  "type": "Feature",
  "properties": {
    "addr:full":"Lapseheide 5 Tessenderlo Limburg 3980",
    "addr:housenumber":"5",
    "addr:postcode":"3980",
    "addr:street":"Lapseheide",
    "iso:country":"BE",
    "sg:address":"Lapseheide 5",
    "sg:city":"Tessenderlo",
    "sg:orig_category":"M\u00e9decins and sp\u00e9cialistes",
    "sg:phone":"+32 13 66 75 73",
    "sg:postcode":"3980",
    "sg:province":"Limburg",
    "wof:name":"Guillaumine Vrijens",
    "wof:placetype":"venue"
},
  "geometry": {"coordinates":[5.0759119987,51.0267562866],"type":"Point"}
}