{
  "type": "Feature",
  "properties": {
    "addr:full":"Avenue De Vaud\u00c9mont 20 Braine-l\u00b4alleud Brabant Wallon 1420",
    "addr:housenumber":"20",
    "addr:postcode":"1420",
    "addr:street":"Avenue De Vaude\u0301Mont;Brabant Wallon",
    "iso:country":"BE",
    "sg:address":"Avenue De Vaud\u00c9mont 20",
    "sg:city":"Braine-l\u00b4alleud",
    "sg:orig_category":"Sportclubs Sportterreinen and installaties behalve sportcentra",
    "sg:phone":"+32 2 384 19 46",
    "sg:postcode":"1420",
    "sg:province":"Brabant Wallon",
    "wof:name":"Group. Arb. De La Dodaine",
    "wof:placetype":"venue"
},
  "geometry": {"coordinates":[4.3808898926,50.6829490662],"type":"Point"}
}