{
  "type": "Feature",
  "properties": {
    "addr:full":"Speltreep 38 Assenede Oost-Vlaanderen 9960",
    "addr:housenumber":"38",
    "addr:postcode":"9960",
    "addr:street":"Speltreep",
    "iso:country":"BE",
    "sg:address":"Speltreep 38",
    "sg:city":"Assenede",
    "sg:classifiers":[
        {
            "category":"Banks & Credit Unions",
            "subcategory":"Investment Brokerage",
            "type":"Services"
        }
    ],
    "sg:phone":"+32 9 344 38 66",
    "sg:postcode":"9960",
    "sg:province":"Oost-Vlaanderen",
    "sg:tags":[
        "ladies'",
        "tailor",
        "tailoresses",
        "-",
        "clothing"
    ],
    "wof:name":"Patricia",
    "wof:placetype":"venue"
},
  "geometry": {"coordinates":[3.7601308823,51.2047233582],"type":"Point"}
}