{
  "type": "Feature",
  "properties": {
    "addr:full":"Volderstraat 59 Oeselgem West-Vlaanderen 8720",
    "addr:housenumber":"59",
    "addr:postcode":"8720",
    "addr:street":"Volderstraat",
    "iso:country":"BE",
    "sg:address":"Volderstraat 59",
    "sg:city":"Oeselgem",
    "sg:orig_category":"Vitrage",
    "sg:phone":"+32 9 388 98 28",
    "sg:postcode":"8720",
    "sg:province":"West-Vlaanderen",
    "wof:name":"Baudoncq",
    "wof:placetype":"venue"
},
  "geometry": {"coordinates":[3.4285569191,50.947467804],"type":"Point"}
}