{
  "type": "Feature",
  "properties": {
    "addr:full":"Montagne Au Chaudron 7 Sint-pieters-woluwe/woluwe-saint-pierre Bruxelles-Capitale 1150",
    "addr:housenumber":"7",
    "addr:postcode":"1150",
    "addr:street":"Montagne Au Chaudron;/",
    "iso:country":"BE",
    "sg:address":"Montagne Au Chaudron 7",
    "sg:city":"Sint-pieters-woluwe/woluwe-saint-pierre",
    "sg:orig_category":"M\u00e9decins and sp\u00e9cialistes",
    "sg:phone":"+32 2 772 64 53",
    "sg:postcode":"1150",
    "sg:province":"Bruxelles-Capitale",
    "wof:name":"Agnes Mazic",
    "wof:placetype":"venue"
},
  "geometry": {"coordinates":[4.4518618584,50.8389053345],"type":"Point"}
}