{
  "type": "Feature",
  "properties": {
    "iso:country":"BE",
    "sg:address":"Norbert Neeckxlaan 197",
    "sg:city":"Lommel",
    "sg:classifiers":[
        {
            "category":"Real Estate",
            "subcategory":"Real Estate Services",
            "type":"Services"
        }
    ],
    "sg:phone":"+32 11 64 31 29",
    "sg:postcode":"3920",
    "sg:province":"Limburg",
    "wof:name":"Immo Crea",
    "wof:placetype":"venue"
},
  "geometry": {"coordinates":[5.3531541824,51.2203979492],"type":"Point"}
}