{
  "type": "Feature",
  "properties": {
    "iso:country":"BE",
    "sg:address":"Rue De La Rivi\u00e8re 2",
    "sg:city":"Habay (rulles)",
    "sg:classifiers":[
        {
            "category":"Sports & Exercise",
            "subcategory":"Stables",
            "type":"Entertainment"
        }
    ],
    "sg:phone":"+32 63 41 21 54",
    "sg:postcode":"6724",
    "sg:province":"Luxembourg",
    "sg:tags":[
        "riding",
        "school"
    ],
    "wof:name":"Cenne Equestre Du Pigeon",
    "wof:placetype":"venue"
},
  "geometry": {"coordinates":[5.5597100258,49.7180557251],"type":"Point"}
}