{
  "type": "Feature",
  "properties": {
    "addr:full":"Route De Lessines 250 Ath Hainaut 7800",
    "addr:housenumber":"250",
    "addr:postcode":"7800",
    "addr:street":"Route De Lessines",
    "iso:country":"BE",
    "sg:address":"Route De Lessines 250",
    "sg:city":"Ath",
    "sg:classifiers":[
        {
            "category":"Wholesale",
            "subcategory":"Sporting Goods",
            "type":"Manufacturing & Wholesale Goods"
        }
    ],
    "sg:phone":"+32 68 28 10 68",
    "sg:postcode":"7800",
    "sg:province":"Hainaut",
    "sg:tags":[
        "sport-",
        "kampeermateriaal"
    ],
    "wof:name":"Lejeune",
    "wof:placetype":"venue"
},
  "geometry": {"coordinates":[3.7920100689,50.6412696838],"type":"Point"}
}