{
  "type": "Feature",
  "properties": {
    "iso:country":"BE",
    "sg:address":"Rijksweg 285",
    "sg:city":"Maasmechelen",
    "sg:orig_category":"Radioproductie and uitzendingen",
    "sg:phone":"+32 89 76 54 05",
    "sg:postcode":"3630",
    "sg:province":"Limburg",
    "wof:name":"Radio Rmc",
    "wof:placetype":"venue"
},
  "geometry": {"coordinates":[5.6981730461,50.9715194702],"type":"Point"}
}