{
  "type": "Feature",
  "properties": {
    "addr:full":"Rue De Fournes 8 Brunehaut Hainaut 7620",
    "addr:housenumber":"8",
    "addr:postcode":"7620",
    "addr:street":"Rue De Fournes",
    "iso:country":"BE",
    "sg:address":"Rue De Fournes 8",
    "sg:city":"Brunehaut",
    "sg:orig_category":"Eleveurs de bovins",
    "sg:phone":"+32 69 34 47 63",
    "sg:postcode":"7620",
    "sg:province":"Hainaut",
    "wof:name":"Jean Bertholet",
    "wof:placetype":"venue"
},
  "geometry": {"coordinates":[3.410640955,50.5091743469],"type":"Point"}
}