{
  "type": "Feature",
  "properties": {
    "addr:full":"Solvynsstraat 5 Antwerpen Antwerpen 2018",
    "addr:housenumber":"5",
    "addr:postcode":"2018",
    "addr:street":"Solvynsstraat",
    "iso:country":"BE",
    "sg:address":"Solvynsstraat 5",
    "sg:city":"Antwerpen",
    "sg:orig_category":"Advocaten and juridische adviseurs",
    "sg:phone":"+32 3 248 37 17",
    "sg:postcode":"2018",
    "sg:province":"Antwerpen",
    "wof:name":"R. De Koninck",
    "wof:placetype":"venue"
},
  "geometry": {"coordinates":[4.4024329185,51.2074317932],"type":"Point"}
}