{
  "type": "Feature",
  "properties": {
    "iso:country":"BE",
    "sg:address":"Rozenlaan 8",
    "sg:city":"Alken",
    "sg:classifiers":[
        {
            "category":"Autos & Motor Vehicles",
            "subcategory":"Fuel & Gas Station",
            "type":"Retail Goods"
        }
    ],
    "sg:phone":"+32 11 59 21 01",
    "sg:postcode":"3570",
    "sg:province":"Limburg",
    "sg:tags":[
        "stations-service",
        "carburants"
    ],
    "wof:name":"Marc Francois",
    "wof:placetype":"venue"
},
  "geometry": {"coordinates":[5.2992200851,50.8801612854],"type":"Point"}
}