{
  "type": "Feature",
  "properties": {
    "addr:full":"Rue Hov\u00e9mont 96 Theux Li\u00e8ge 4910",
    "addr:housenumber":"96",
    "addr:postcode":"4910",
    "addr:street":"Rue Hove\u0301Mont",
    "iso:country":"BE",
    "sg:address":"Rue Hov\u00e9mont 96",
    "sg:city":"Theux",
    "sg:classifiers":[
        {
            "category":"Shopping",
            "subcategory":"Antiques",
            "type":"Retail Goods"
        }
    ],
    "sg:phone":"+32 87 34 07 26",
    "sg:postcode":"4910",
    "sg:province":"Li\u00e8ge",
    "wof:name":"Masset J",
    "wof:placetype":"venue"
},
  "geometry": {"coordinates":[5.8150987625,50.5328979492],"type":"Point"}
}