{
  "type": "Feature",
  "properties": {
    "iso:country":"BE",
    "sg:address":"Opitterkiezel 27",
    "sg:city":"Bree",
    "sg:orig_category":"D\u00e9taillants en pi\u00e8ces and accessoires de voitures",
    "sg:phone":"+32 89 47 17 64",
    "sg:postcode":"3960",
    "sg:province":"Limburg",
    "wof:name":"Autolux",
    "wof:placetype":"venue"
},
  "geometry": {"coordinates":[5.6090950966,51.1365280151],"type":"Point"}
}