{
  "type": "Feature",
  "properties": {
    "addr:full":"Baronstraat 11 Middelkerke (westende) West-Vlaanderen 8434",
    "addr:housenumber":"11",
    "addr:postcode":"8434",
    "addr:street":"Baronstraat",
    "iso:country":"BE",
    "sg:address":"Baronstraat 11",
    "sg:city":"Middelkerke (westende)",
    "sg:classifiers":[
        {
            "category":"Parking",
            "subcategory":"Lot",
            "type":"Transportation"
        }
    ],
    "sg:phone":"+32 58 23 66 91",
    "sg:postcode":"8434",
    "sg:province":"West-Vlaanderen",
    "sg:tags":[
        "parking-places",
        "laying-out"
    ],
    "wof:name":"Norre E-degraeve",
    "wof:placetype":"venue"
},
  "geometry": {"coordinates":[2.7569050789,51.1488685608],"type":"Point"}
}