{
  "type": "Feature",
  "properties": {
    "iso:country":"BE",
    "sg:address":"Biekorfstraat 1",
    "sg:city":"Antwerpen",
    "sg:orig_category":"Artiesten and kunstenaars",
    "sg:phone":"+32 3 213 01 87",
    "sg:postcode":"2060",
    "sg:province":"Antwerpen",
    "wof:name":"Ben Tesseur",
    "wof:placetype":"venue"
},
  "geometry": {"coordinates":[4.4227528572,51.2275505066],"type":"Point"}
}