{
  "type": "Feature",
  "properties": {
    "addr:full":"De Bavaylei 104a Vilvoorde Vlaams-Brabant 1800",
    "addr:housenumber":"104a",
    "addr:postcode":"1800",
    "addr:street":"De Bavaylei",
    "iso:country":"BE",
    "sg:address":"De Bavaylei 104a",
    "sg:city":"Vilvoorde",
    "sg:classifiers":[
        {
            "category":"Retail",
            "subcategory":"Auto Repair",
            "type":"Services"
        }
    ],
    "sg:phone":"+32 2 251 59 17",
    "sg:postcode":"1800",
    "sg:province":"Vlaams-Brabant",
    "sg:tags":[
        "automobile-body"
    ],
    "wof:name":"J D S Bvba",
    "wof:placetype":"venue"
},
  "geometry": {"coordinates":[4.4383897781,50.9324798584],"type":"Point"}
}