{
  "type": "Feature",
  "properties": {
    "iso:country":"BE",
    "sg:address":"Woestendorp 39",
    "sg:city":"Vleteren (woesten)",
    "sg:classifiers":[
        {
            "category":"Wholesale",
            "subcategory":"Machinery & Supplies",
            "type":"Manufacturing & Wholesale Goods"
        }
    ],
    "sg:phone":"+32 57 42 35 95",
    "sg:postcode":"8640",
    "sg:province":"West-Vlaanderen",
    "sg:tags":[
        "agricultural",
        "tractor"
    ],
    "wof:name":"Tractomat Nv",
    "wof:placetype":"venue"
},
  "geometry": {"coordinates":[2.7884690762,50.9011764526],"type":"Point"}
}