{
  "type": "Feature",
  "properties": {
    "iso:country":"BE",
    "sg:address":"Merksemsebaan 179-183",
    "sg:city":"Wijnegem",
    "sg:classifiers":[
        {
            "category":"Wholesale",
            "subcategory":"Beer",
            "type":"Manufacturing & Wholesale Goods"
        }
    ],
    "sg:phone":"+32 3 353 00 94",
    "sg:postcode":"2110",
    "sg:province":"Antwerpen",
    "sg:tags":[
        "ale",
        "-"
    ],
    "wof:name":"Wijnegemse Drankenhal Bvba",
    "wof:placetype":"venue"
},
  "geometry": {"coordinates":[4.5082149506,51.2301902771],"type":"Point"}
}