{
  "type": "Feature",
  "properties": {
    "addr:full":"Burgemeester Meirsonstraat 25a Destelbergen Oost-Vlaanderen 9070",
    "addr:housenumber":"25a",
    "addr:postcode":"9070",
    "addr:street":"Burgemeester Meirsonstraat",
    "iso:country":"BE",
    "sg:address":"Burgemeester Meirsonstraat 25a",
    "sg:city":"Destelbergen",
    "sg:classifiers":[
        {
            "category":"Real Estate",
            "subcategory":"Architect",
            "type":"Services"
        }
    ],
    "sg:phone":"+32 9 231 40 10",
    "sg:postcode":"9070",
    "sg:province":"Oost-Vlaanderen",
    "wof:name":"Naessens G",
    "wof:placetype":"venue"
},
  "geometry": {"coordinates":[3.7625029087,51.0532722473],"type":"Point"}
}