{
  "type": "Feature",
  "properties": {
    "addr:full":"Boulevard Emile Bockstael 104 Bruxelles Bruxelles-Capitale 1020",
    "addr:housenumber":"104",
    "addr:postcode":"1020",
    "addr:street":"Boulevard Emile Bockstael",
    "iso:country":"BE",
    "sg:address":"Boulevard Emile Bockstael 104",
    "sg:city":"Bruxelles",
    "sg:classifiers":[
        {
            "category":"Professional",
            "subcategory":"Detective & Security Services",
            "type":"Services"
        }
    ],
    "sg:phone":"+32 2 424 37 68",
    "sg:postcode":"1020",
    "sg:province":"Bruxelles-Capitale",
    "sg:tags":[
        "door",
        "videophones",
        "operating",
        "equipment"
    ],
    "wof:name":"Sab-i-lec Sprl",
    "wof:placetype":"venue"
},
  "geometry": {"coordinates":[4.3450479507,50.8725776672],"type":"Point"}
}