{
  "type": "Feature",
  "properties": {
    "iso:country":"BE",
    "sg:address":"Rue Sous Le Bois 6",
    "sg:city":"Sambreville",
    "sg:orig_category":"Entretien and r\u00e9parations de voitures. D\u00e9taillants en pi\u00e8ces and accessoires de voitures",
    "sg:phone":"+32 71 77 30 36",
    "sg:postcode":"5060",
    "sg:province":"Namur",
    "wof:name":"Giorgio Poli",
    "wof:placetype":"venue"
},
  "geometry": {"coordinates":[4.6374168396,50.4524002075],"type":"Point"}
}