{
  "type": "Feature",
  "properties": {
    "addr:full":"Rodestraat 29 Antwerpen Antwerpen 2000",
    "addr:housenumber":"29",
    "addr:postcode":"2000",
    "addr:street":"Rodestraat",
    "iso:country":"BE",
    "sg:address":"Rodestraat 29",
    "sg:city":"Antwerpen",
    "sg:orig_category":"Agences d'exp\u00e9dition",
    "sg:phone":"+32 9 213 09 50",
    "sg:postcode":"2000",
    "sg:province":"Antwerpen",
    "wof:name":"Pamimpex",
    "wof:placetype":"venue"
},
  "geometry": {"coordinates":[4.4140129089,51.2232322693],"type":"Point"}
}