{
  "type": "Feature",
  "properties": {
    "addr:full":"Gistelsteenweg 4 Varsenare West-Vlaanderen 8490",
    "addr:housenumber":"4",
    "addr:postcode":"8490",
    "addr:street":"Gistelsteenweg",
    "iso:country":"BE",
    "sg:address":"Gistelsteenweg 4",
    "sg:city":"Varsenare",
    "sg:classifiers":[
        {
            "category":"Autos & Motor Vehicles",
            "subcategory":"Automobile Sales",
            "type":"Retail Goods"
        }
    ],
    "sg:phone":"+32 50 38 60 92",
    "sg:postcode":"8490",
    "sg:province":"West-Vlaanderen",
    "sg:tags":[
        "equipment",
        "industrial",
        "transport"
    ],
    "wof:name":"Autohandel & Garage Booy Bvba",
    "wof:placetype":"venue"
},
  "geometry": {"coordinates":[3.1588931084,51.1921577454],"type":"Point"}
}