{
  "type": "Feature",
  "properties": {
    "addr:full":"Halveweg 74 Zonhoven Limburg 3520",
    "addr:housenumber":"74",
    "addr:postcode":"3520",
    "addr:street":"Halveweg",
    "iso:country":"BE",
    "sg:address":"Halveweg 74",
    "sg:city":"Zonhoven",
    "sg:orig_category":"Banken and kredietinstellingen",
    "sg:phone":"+32 11 81 31 73",
    "sg:postcode":"3520",
    "sg:province":"Limburg",
    "wof:name":"Fortis",
    "wof:placetype":"venue"
},
  "geometry": {"coordinates":[5.3415808678,50.9943351746],"type":"Point"}
}