{
  "type": "Feature",
  "properties": {
    "addr:full":"Diestersteenweg 210 Diest (kaggevinne) Vlaams-Brabant 3293",
    "addr:housenumber":"210",
    "addr:postcode":"3293",
    "addr:street":"Diestersteenweg",
    "iso:country":"BE",
    "sg:address":"Diestersteenweg 210",
    "sg:city":"Diest (kaggevinne)",
    "sg:classifiers":[
        {
            "category":"Building & Trades",
            "subcategory":"Landscaping Services",
            "type":"Services"
        }
    ],
    "sg:phone":"+32 13 33 40 03",
    "sg:postcode":"3293",
    "sg:province":"Vlaams-Brabant",
    "sg:tags":[
        "gardening",
        "garden",
        "maintenance"
    ],
    "wof:name":"Reynders M",
    "wof:placetype":"venue"
},
  "geometry": {"coordinates":[5.0231890678,50.9792861938],"type":"Point"}
}