{
  "type": "Feature",
  "properties": {
    "addr:full":"Place Du Petit Sablon 13 Bruxelles Bruxelles-Capitale 1000",
    "addr:housenumber":"13",
    "addr:postcode":"1000",
    "addr:street":"Place Du Petit Sablon",
    "iso:country":"BE",
    "sg:address":"Place Du Petit Sablon 13",
    "sg:city":"Bruxelles",
    "sg:classifiers":[
        {
            "category":"Professional",
            "subcategory":"Lawyer & Legal Services",
            "type":"Services"
        }
    ],
    "sg:phone":"+32 2 512 55 31",
    "sg:postcode":"1000",
    "sg:province":"Bruxelles-Capitale",
    "wof:name":"Poumay M",
    "wof:placetype":"venue"
},
  "geometry": {"coordinates":[4.3562021255,50.8392677307],"type":"Point"}
}