{
  "type": "Feature",
  "properties": {
    "addr:full":"Rue Vanderstichelen 42 Bruxelles (molenbeek-saint-jean) Bruxelles-Capitale 1080",
    "addr:housenumber":"42",
    "addr:postcode":"1080",
    "addr:street":"Rue Vanderstichelen",
    "iso:country":"BE",
    "sg:address":"Rue Vanderstichelen 42",
    "sg:city":"Bruxelles (molenbeek-saint-jean)",
    "sg:classifiers":[
        {
            "category":"Manufacturing",
            "subcategory":"Furniture",
            "type":"Manufacturing & Wholesale Goods"
        }
    ],
    "sg:phone":"+32 2 425 40 28",
    "sg:postcode":"1080",
    "sg:province":"Bruxelles-Capitale",
    "sg:tags":[
        "made",
        "-",
        "custom"
    ],
    "wof:name":"Claude Aerts",
    "wof:placetype":"venue"
},
  "geometry": {"coordinates":[4.3411679268,50.8623466492],"type":"Point"}
}