{
  "type": "Feature",
  "properties": {
    "addr:full":"Oostrozebeeksestraat 160 Wielsbeke (ooigem) West-Vlaanderen 8710",
    "addr:housenumber":"160",
    "addr:postcode":"8710",
    "addr:street":"Oostrozebeeksestraat",
    "iso:country":"BE",
    "sg:address":"Oostrozebeeksestraat 160",
    "sg:city":"Wielsbeke (ooigem)",
    "sg:classifiers":[
        {
            "category":"Food & Beverages",
            "subcategory":"Supermarket",
            "type":"Retail Goods"
        }
    ],
    "sg:phone":"+32 56 67 63 00",
    "sg:postcode":"8710",
    "sg:province":"West-Vlaanderen",
    "sg:tags":[
        "frozen",
        "-"
    ],
    "wof:name":"Crop's Nv",
    "wof:placetype":"venue"
},
  "geometry": {"coordinates":[3.3281259537,50.9058189392],"type":"Point"}
}