{
  "type": "Feature",
  "properties": {
    "addr:full":"Schepdaelstraat 11 Herne (herfelingen) Vlaams-Brabant 1540",
    "addr:housenumber":"11",
    "addr:postcode":"1540",
    "addr:street":"Schepdaelstraat",
    "iso:country":"BE",
    "sg:address":"Schepdaelstraat 11",
    "sg:city":"Herne (herfelingen)",
    "sg:classifiers":[
        {
            "category":"Home & Garden",
            "subcategory":"Garden Supply",
            "type":"Retail Goods"
        }
    ],
    "sg:phone":"+32 54 56 81 06",
    "sg:postcode":"1540",
    "sg:province":"Vlaams-Brabant",
    "sg:tags":[
        "machine",
        "agricultural",
        "-"
    ],
    "wof:name":"Mersch Gebr",
    "wof:placetype":"venue"
},
  "geometry": {"coordinates":[4.0678348541,50.7378463745],"type":"Point"}
}