{
  "type": "Feature",
  "properties": {
    "iso:country":"BE",
    "sg:address":"Rue De L'abbaye 35",
    "sg:city":"Elsene/ixelles",
    "sg:orig_category":"Avocats and conseillers juridiques",
    "sg:phone":"+32 2 646 97 74",
    "sg:postcode":"1050",
    "sg:province":"Bruxelles-Capitale",
    "wof:name":"S. Vanwelkenhuysen",
    "wof:placetype":"venue"
},
  "geometry": {"coordinates":[4.3681378365,50.8192367554],"type":"Point"}
}