{
  "type": "Feature",
  "properties": {
    "addr:full":"Oude Luikerbaan 107 Box 1 Hasselt Limburg 3500",
    "addr:housenumber":"107;1",
    "addr:postcode":"3500",
    "addr:street":"Oude Luikerbaan;Box",
    "iso:country":"BE",
    "sg:address":"Oude Luikerbaan 107 Box 1",
    "sg:city":"Hasselt",
    "sg:classifiers":[
        {
            "category":"Building & Trades",
            "subcategory":"Construction",
            "type":"Services"
        }
    ],
    "sg:phone":"+32 11 87 46 87",
    "sg:postcode":"3500",
    "sg:province":"Limburg",
    "sg:tags":[
        "installation",
        "-",
        "central",
        "heating"
    ],
    "wof:name":"4 Technics Bvba",
    "wof:placetype":"venue"
},
  "geometry": {"coordinates":[5.3483929634,50.9185905457],"type":"Point"}
}