{
  "type": "Feature",
  "properties": {
    "addr:full":"Boulevard De La Dodaine 30 Nivelles Brabant Wallon 1400",
    "addr:housenumber":"30",
    "addr:postcode":"1400",
    "addr:street":"Boulevard De La Dodaine",
    "iso:country":"BE",
    "sg:address":"Boulevard De La Dodaine 30",
    "sg:city":"Nivelles",
    "sg:orig_category":"Artsen and specialisten",
    "sg:phone":"+32 67 84 09 29",
    "sg:postcode":"1400",
    "sg:province":"Brabant Wallon",
    "wof:name":"Dominique Dourte",
    "wof:placetype":"venue"
},
  "geometry": {"coordinates":[4.3211460114,50.5941200256],"type":"Point"}
}