{
  "type": "Feature",
  "properties": {
    "addr:full":"Rue G\u00e9n\u00e9ral De Gaulle 15 La Hulpe Brabant Wallon 1310",
    "addr:housenumber":"15",
    "addr:postcode":"1310",
    "addr:street":"Rue Ge\u0301Ne\u0301Ral De Gaulle",
    "iso:country":"BE",
    "sg:address":"Rue G\u00e9n\u00e9ral De Gaulle 15",
    "sg:city":"La Hulpe",
    "sg:classifiers":[
        {
            "category":"Shopping",
            "subcategory":"Florist",
            "type":"Retail Goods"
        }
    ],
    "sg:phone":"+32 2 653 24 66",
    "sg:postcode":"1310",
    "sg:province":"Brabant Wallon",
    "wof:name":"Fleurs Francis",
    "wof:placetype":"venue"
},
  "geometry": {"coordinates":[4.4876728058,50.7349510193],"type":"Point"}
}