{
  "type": "Feature",
  "properties": {
    "iso:country":"BE",
    "sg:address":"Zemstseweg 23bbis",
    "sg:city":"Mechelen",
    "sg:orig_category":"Boekhouders",
    "sg:postcode":"2811",
    "sg:province":"Antwerpen",
    "wof:name":"Carolina Van Ryckeghem",
    "wof:placetype":"venue"
},
  "geometry": {"coordinates":[4.4409418106,51.0118408203],"type":"Point"}
}