{
  "type": "Feature",
  "properties": {
    "iso:country":"BE",
    "sg:address":"Vossekotstraat 11",
    "sg:city":"Sint-niklaas",
    "sg:classifiers":[
        {
            "category":"Bars & Pubs",
            "type":"Food & Drink"
        }
    ],
    "sg:phone":"+32 3 776 91 79",
    "sg:postcode":"9100",
    "sg:province":"Oost-Vlaanderen",
    "wof:name":"Zilvervoske ('t)",
    "wof:placetype":"venue"
},
  "geometry": {"coordinates":[4.1942272186,51.17760849],"type":"Point"}
}