{
  "type": "Feature",
  "properties": {
    "addr:full":"Kouterweg 14 Affligem Vlaams-Brabant 1790",
    "addr:housenumber":"14",
    "addr:postcode":"1790",
    "addr:street":"Kouterweg",
    "iso:country":"BE",
    "sg:address":"Kouterweg 14",
    "sg:city":"Affligem",
    "sg:orig_category":"Bloemen and planten Gh",
    "sg:phone":"+32 53 66 75 00",
    "sg:postcode":"1790",
    "sg:province":"Vlaams-Brabant",
    "wof:name":"Christiaens",
    "wof:placetype":"venue"
},
  "geometry": {"coordinates":[4.1059179306,50.9079360962],"type":"Point"}
}