{
  "type": "Feature",
  "properties": {
    "addr:full":"Oude Kasteeldreef 26 Maldegem Oost-Vlaanderen 9990",
    "addr:housenumber":"26",
    "addr:postcode":"9990",
    "addr:street":"Oude Kasteeldreef",
    "iso:country":"BE",
    "sg:address":"Oude Kasteeldreef 26",
    "sg:city":"Maldegem",
    "sg:classifiers":[
        {
            "category":"Retail",
            "subcategory":"Auto Repair",
            "type":"Services"
        }
    ],
    "sg:phone":"+32 50 71 07 61",
    "sg:postcode":"9990",
    "sg:province":"Oost-Vlaanderen",
    "sg:tags":[
        "automobile",
        "-",
        "wrecking"
    ],
    "wof:name":"Annogrange Ltd",
    "wof:placetype":"venue"
},
  "geometry": {"coordinates":[3.4272360802,51.205368042],"type":"Point"}
}