{
  "type": "Feature",
  "properties": {
    "addr:full":"Rue Gr\u00c9try 61 Li\u00c8ge Li\u00e8ge 4020",
    "addr:housenumber":"61",
    "addr:postcode":"4020",
    "addr:street":"Rue Gre\u0301Try",
    "iso:country":"BE",
    "sg:address":"Rue Gr\u00c9try 61",
    "sg:city":"Li\u00c8ge",
    "sg:orig_category":"Pain, p\u00e2tisseries and confiseries",
    "sg:phone":"+32 4 343 43 22",
    "sg:postcode":"4020",
    "sg:province":"Li\u00e8ge",
    "wof:name":"Anne-marie Hubin",
    "wof:placetype":"venue"
},
  "geometry": {"coordinates":[5.5807828903,50.6355171204],"type":"Point"}
}