{
  "type": "Feature",
  "properties": {
    "addr:full":"Ottegemsestraat 98 Zwevegem West-Vlaanderen 8550",
    "addr:housenumber":"98",
    "addr:postcode":"8550",
    "addr:street":"Ottegemsestraat",
    "iso:country":"BE",
    "sg:address":"Ottegemsestraat 98",
    "sg:city":"Zwevegem",
    "sg:orig_category":"Keukens and Keukenapparatuur MEUBELONTWERP AND -INSTALLATIE MHK De Keukenspecialist Meubelzaken, won",
    "sg:phone":"+32 56 70 69 63",
    "sg:postcode":"8550",
    "sg:province":"West-Vlaanderen",
    "wof:name":"Idee Home Deconinck Bvba",
    "wof:placetype":"venue"
},
  "geometry": {"coordinates":[3.3398079872,50.8134346008],"type":"Point"}
}