{
  "type": "Feature",
  "properties": {
    "addr:full":"Rue Baron Lambert 30 Bruxelles (etterbeek) Bruxelles-Capitale 1040",
    "addr:housenumber":"30",
    "addr:postcode":"1040",
    "addr:street":"Rue Baron Lambert",
    "iso:country":"BE",
    "sg:address":"Rue Baron Lambert 30",
    "sg:city":"Bruxelles (etterbeek)",
    "sg:classifiers":[
        {
            "category":"Bars & Pubs",
            "type":"Food & Drink"
        }
    ],
    "sg:phone":"+32 2 733 37 19",
    "sg:postcode":"1040",
    "sg:province":"Bruxelles-Capitale",
    "wof:name":"Ardennes (des)",
    "wof:placetype":"venue"
},
  "geometry": {"coordinates":[4.3890337944,50.835193634],"type":"Point"}
}