{
  "type": "Feature",
  "properties": {
    "addr:full":"Grand'rue 16 Gembloux-sur-orneau (gembloux) Namur 5030",
    "addr:housenumber":"16",
    "addr:postcode":"5030",
    "addr:street":"Grand'Rue;Namur",
    "iso:country":"BE",
    "sg:address":"Grand'rue 16",
    "sg:city":"Gembloux-sur-orneau (gembloux)",
    "sg:classifiers":[
        {
            "category":"Shopping",
            "subcategory":"Clothing, Apparel, & Fashions",
            "type":"Retail Goods"
        }
    ],
    "sg:phone":"+32 81 61 15 54",
    "sg:postcode":"5030",
    "sg:province":"Namur",
    "sg:tags":[
        "underwear",
        "lingerie",
        "-"
    ],
    "wof:name":"Secrets Cach\u00e9s",
    "wof:placetype":"venue"
},
  "geometry": {"coordinates":[4.6945400238,50.5666313171],"type":"Point"}
}