{
  "type": "Feature",
  "properties": {
    "iso:country":"BE",
    "sg:address":"Ernest Ourystraat 36",
    "sg:city":"Hoegaarden",
    "sg:orig_category":"Sportclubs",
    "sg:phone":"+32 16 76 75 58",
    "sg:postcode":"3320",
    "sg:province":"Vlaams-Brabant",
    "wof:name":"Hoegaardse Duivenbond",
    "wof:placetype":"venue"
},
  "geometry": {"coordinates":[4.8963971138,50.7739944458],"type":"Point"}
}