{
  "type": "Feature",
  "properties": {
    "addr:full":"Bruul 68 Geel Antwerpen 2440",
    "addr:housenumber":"68",
    "addr:postcode":"2440",
    "addr:street":"Bruul",
    "iso:country":"BE",
    "sg:address":"Bruul 68",
    "sg:city":"Geel",
    "sg:classifiers":[
        {
            "category":"Insurance",
            "subcategory":"Insurance Agent",
            "type":"Services"
        }
    ],
    "sg:phone":"+32 14 58 35 63",
    "sg:postcode":"2440",
    "sg:province":"Antwerpen",
    "sg:tags":[
        "verzekeringsmakelaars",
        "expert"
    ],
    "wof:name":"Berghmans",
    "wof:placetype":"venue"
},
  "geometry": {"coordinates":[5.0489997864,51.1650886536],"type":"Point"}
}