{
  "type": "Feature",
  "properties": {
    "addr:full":"Rue De Valenciennes 273 Bernissart Hainaut 7320",
    "addr:housenumber":"273",
    "addr:postcode":"7320",
    "addr:street":"Rue De Valenciennes",
    "iso:country":"BE",
    "sg:address":"Rue De Valenciennes 273",
    "sg:city":"Bernissart",
    "sg:orig_category":"Kansspelen",
    "sg:phone":"+32 69 57 64 94",
    "sg:postcode":"7320",
    "sg:province":"Hainaut",
    "wof:name":"Ladbroke",
    "wof:placetype":"venue"
},
  "geometry": {"coordinates":[3.6348559856,50.476688385],"type":"Point"}
}