{
  "type": "Feature",
  "properties": {
    "addr:full":"Dorpsstraat 3 Box 5 Leopoldsburg (heppen) Limburg 3971",
    "addr:housenumber":"3;5",
    "addr:postcode":"3971",
    "addr:street":"Dorpsstraat;Box",
    "iso:country":"BE",
    "sg:address":"Dorpsstraat 3 Box 5",
    "sg:city":"Leopoldsburg (heppen)",
    "sg:classifiers":[
        {
            "category":"Health Services",
            "subcategory":"Health Practitioner",
            "type":"Services"
        }
    ],
    "sg:phone":"+32 11 34 37 39",
    "sg:postcode":"3971",
    "sg:province":"Limburg",
    "sg:tags":[
        "physiotherapist"
    ],
    "wof:name":"Giegas Gerda",
    "wof:placetype":"venue"
},
  "geometry": {"coordinates":[5.2289648056,51.108921051],"type":"Point"}
}