{
  "type": "Feature",
  "properties": {
    "addr:full":"Heultjedorp 35 Westerlo Antwerpen 2260",
    "addr:housenumber":"35",
    "addr:postcode":"2260",
    "addr:street":"Heultjedorp",
    "iso:country":"BE",
    "sg:address":"Heultjedorp 35",
    "sg:city":"Westerlo",
    "sg:classifiers":[
        {
            "category":"Bars & Pubs",
            "type":"Food & Drink"
        }
    ],
    "sg:phone":"+32 16 69 90 39",
    "sg:postcode":"2260",
    "sg:province":"Antwerpen",
    "sg:tags":[
        "tavern"
    ],
    "wof:name":"Hof Ter Linde",
    "wof:placetype":"venue"
},
  "geometry": {"coordinates":[4.8400688171,51.0901985168],"type":"Point"}
}