{
  "type": "Feature",
  "properties": {
    "addr:full":"Rue De La Solitude 37 Rummilies Hainaut 7540",
    "addr:housenumber":"37",
    "addr:postcode":"7540",
    "addr:street":"Rue De La Solitude;Hainaut",
    "iso:country":"BE",
    "sg:address":"Rue De La Solitude 37",
    "sg:city":"Rummilies",
    "sg:orig_category":"Royal Canin. Eleveurs d'animaux domestiques. Services pour animaux domestiques. Animaux domestiques ",
    "sg:phone":"+32 69 22 93 66",
    "sg:postcode":"7540",
    "sg:province":"Hainaut",
    "wof:name":"Lamblin",
    "wof:placetype":"venue"
},
  "geometry": {"coordinates":[3.4307830334,50.6185913086],"type":"Point"}
}