{
  "type": "Feature",
  "properties": {
    "addr:full":"Rue Lambot 6 Aiseau Hainaut 6250",
    "addr:housenumber":"6",
    "addr:postcode":"6250",
    "addr:street":"Rue Lambot;Hainaut",
    "iso:country":"BE",
    "sg:address":"Rue Lambot 6",
    "sg:city":"Aiseau",
    "sg:classifiers":[
        {
            "category":"Manufacturing",
            "subcategory":"Motor Vehicles & Parts",
            "type":"Manufacturing & Wholesale Goods"
        }
    ],
    "sg:phone":"+32 71 77 35 31",
    "sg:postcode":"6250",
    "sg:province":"Hainaut",
    "sg:tags":[
        "precision",
        "mechanic"
    ],
    "wof:name":"Murrieri S.p.r.l.",
    "wof:placetype":"venue"
},
  "geometry": {"coordinates":[4.5866799355,50.4250183105],"type":"Point"}
}