{
  "type": "Feature",
  "properties": {
    "addr:full":"Pliniuswal 24 Tongeren Limburg 3700",
    "addr:housenumber":"24",
    "addr:postcode":"3700",
    "addr:street":"Pliniuswal",
    "iso:country":"BE",
    "sg:address":"Pliniuswal 24",
    "sg:city":"Tongeren",
    "sg:classifiers":[
        {
            "category":"Health Services",
            "subcategory":"Dentist",
            "type":"Services"
        }
    ],
    "sg:phone":"+32 11 22 66 66",
    "sg:postcode":"3700",
    "sg:province":"Limburg",
    "wof:name":"Jorissen-berx Patricia",
    "wof:placetype":"venue"
},
  "geometry": {"coordinates":[5.4613380432,50.7830429077],"type":"Point"}
}