{
  "type": "Feature",
  "properties": {
    "iso:country":"BE",
    "sg:address":"Place De La Gare 26",
    "sg:city":"Spa",
    "sg:orig_category":"Treinen and spoorwegen",
    "sg:phone":"+32 87 30 88 23",
    "sg:postcode":"4900",
    "sg:province":"Li\u00e8ge",
    "wof:name":"Gare De Spa",
    "wof:placetype":"venue"
},
  "geometry": {"coordinates":[5.8559699059,50.4905509949],"type":"Point"}
}