{
  "type": "Feature",
  "properties": {
    "iso:country":"BE",
    "sg:address":"Floraplein 5",
    "sg:city":"Merelbeke",
    "sg:orig_category":"Disneyland Parijs Reisbureaus",
    "sg:phone":"+32 9 210 85 85",
    "sg:postcode":"9820",
    "sg:province":"Oost-Vlaanderen",
    "wof:name":"Europareizen-euroclub",
    "wof:placetype":"venue"
},
  "geometry": {"coordinates":[3.7596230507,51.0178108215],"type":"Point"}
}