{
  "type": "Feature",
  "properties": {
    "addr:full":"Rue De Renesse 10 Spa Li\u00e8ge 4900",
    "addr:housenumber":"10",
    "addr:postcode":"4900",
    "addr:street":"Rue De Renesse",
    "iso:country":"BE",
    "sg:address":"Rue De Renesse 10",
    "sg:city":"Spa",
    "sg:orig_category":"Autoverhuur",
    "sg:phone":"+32 87 77 32 32",
    "sg:postcode":"4900",
    "sg:province":"Li\u00e8ge",
    "wof:name":"Ranzy",
    "wof:placetype":"venue"
},
  "geometry": {"coordinates":[5.8690538406,50.4897499084],"type":"Point"}
}