{
  "type": "Feature",
  "properties": {
    "iso:country":"BE",
    "sg:address":"Rue Du Mignawez 37",
    "sg:city":"Hannut",
    "sg:orig_category":"Maisons de vacances",
    "sg:phone":"+32 19 51 44 12",
    "sg:postcode":"4280",
    "sg:province":"Li\u00e8ge",
    "wof:name":"Li Mignawez",
    "wof:placetype":"venue"
},
  "geometry": {"coordinates":[5.0526218414,50.6619415283],"type":"Point"}
}