{
  "type": "Feature",
  "properties": {
    "iso:country":"BE",
    "sg:address":"Square De L\u00b4arbal\u00c8te 9",
    "sg:city":"Watermaal-bosvoorde/watermael-boitsfort",
    "sg:orig_category":"M\u00e9decins and sp\u00e9cialistes",
    "sg:phone":"+32 2 673 44 34",
    "sg:postcode":"1170",
    "sg:province":"Bruxelles-Capitale",
    "wof:name":"Paul Schmit",
    "wof:placetype":"venue"
},
  "geometry": {"coordinates":[4.4081320763,50.8012199402],"type":"Point"}
}