{
  "type": "Feature",
  "properties": {
    "iso:country":"BE",
    "sg:address":"Le Nouveau Monde 3a",
    "sg:city":"Momignies (macquenoise)",
    "sg:classifiers":[
        {
            "category":"Building & Trades",
            "subcategory":"Landscaping Services",
            "type":"Services"
        }
    ],
    "sg:phone":"+32 60 51 13 55",
    "sg:postcode":"6593",
    "sg:province":"Hainaut",
    "sg:tags":[
        "gardening",
        "garden",
        "maintenance"
    ],
    "wof:name":"Heusschen B",
    "wof:placetype":"venue"
},
  "geometry": {"coordinates":[4.1591801643,49.990070343],"type":"Point"}
}