{
  "type": "Feature",
  "properties": {
    "addr:full":"Kruisvaardersstraat 111 Mouscron (herseaux) Hainaut 7712",
    "addr:housenumber":"111",
    "addr:postcode":"7712",
    "addr:street":"Kruisvaardersstraat",
    "iso:country":"BE",
    "sg:address":"Kruisvaardersstraat 111",
    "sg:city":"Mouscron (herseaux)",
    "sg:classifiers":[
        {
            "category":"Health Services",
            "subcategory":"Dentist",
            "type":"Services"
        }
    ],
    "sg:phone":"+32 56 34 37 57",
    "sg:postcode":"7712",
    "sg:province":"Hainaut",
    "wof:name":"Loiseau M-p",
    "wof:placetype":"venue"
},
  "geometry": {"coordinates":[3.2374789715,50.7187156677],"type":"Point"}
}