{
  "type": "Feature",
  "properties": {
    "iso:country":"BE",
    "sg:address":"Begonialaan 8",
    "sg:city":"Schilde",
    "sg:orig_category":"Dameskledingzaken Verzekeringsmakelaars and experts",
    "sg:phone":"+32 3 685 18 64",
    "sg:postcode":"2970",
    "sg:province":"Antwerpen",
    "wof:name":"Bureau Cordemans Luc",
    "wof:placetype":"venue"
},
  "geometry": {"coordinates":[4.5542211533,51.2424507141],"type":"Point"}
}