{
  "type": "Feature",
  "properties": {
    "addr:full":"Rue De Chiny 2 Florenville (lacuisine) Luxembourg 6821",
    "addr:housenumber":"2",
    "addr:postcode":"6821",
    "addr:street":"Rue De Chiny",
    "iso:country":"BE",
    "sg:address":"Rue De Chiny 2",
    "sg:city":"Florenville (lacuisine)",
    "sg:classifiers":[
        {
            "category":"Travel",
            "subcategory":"Hotels & Motels",
            "type":"Entertainment"
        }
    ],
    "sg:phone":"+32 61 31 10 39",
    "sg:postcode":"6821",
    "sg:province":"Luxembourg",
    "wof:name":"Roseraie (la)",
    "wof:placetype":"venue"
},
  "geometry": {"coordinates":[5.3263549805,49.7111968994],"type":"Point"}
}