{
  "type": "Feature",
  "properties": {
    "addr:full":"Perenstraat 12 Antwerpen Antwerpen 2060",
    "addr:housenumber":"12",
    "addr:postcode":"2060",
    "addr:street":"Perenstraat",
    "iso:country":"BE",
    "sg:address":"Perenstraat 12",
    "sg:city":"Antwerpen",
    "sg:orig_category":"M\u00e9decins and sp\u00e9cialistes",
    "sg:phone":"+32 3 235 90 76",
    "sg:postcode":"2060",
    "sg:province":"Antwerpen",
    "wof:name":"E. Schoofs",
    "wof:placetype":"venue"
},
  "geometry": {"coordinates":[4.4299612045,51.2220077515],"type":"Point"}
}