{
  "type": "Feature",
  "properties": {
    "addr:full":"Avenue Des Armures 81 Bruxelles (forest) Bruxelles-Capitale 1190",
    "addr:housenumber":"81",
    "addr:postcode":"1190",
    "addr:street":"Avenue Des Armures",
    "iso:country":"BE",
    "sg:address":"Avenue Des Armures 81",
    "sg:city":"Bruxelles (forest)",
    "sg:classifiers":[
        {
            "category":"Health Services",
            "subcategory":"Health Practitioner",
            "type":"Services"
        }
    ],
    "sg:phone":"+32 2 343 76 91",
    "sg:postcode":"1190",
    "sg:province":"Bruxelles-Capitale",
    "sg:tags":[
        "physiotherapist"
    ],
    "wof:name":"Knop Chantal",
    "wof:placetype":"venue"
},
  "geometry": {"coordinates":[4.3355522156,50.8139839172],"type":"Point"}
}