{
  "type": "Feature",
  "properties": {
    "iso:country":"BE",
    "sg:address":"Appelmansstraat 25bw37",
    "sg:city":"Antwerpen",
    "sg:orig_category":"Horloges, m\u00e9taux pr\u00e9cieux and bijoux Bijoux Fab. Bijouteries and horlogeries",
    "sg:phone":"+32 3 232 93 14",
    "sg:postcode":"2018",
    "sg:province":"Antwerpen",
    "wof:name":"Point D\u00b4or",
    "wof:placetype":"venue"
},
  "geometry": {"coordinates":[4.4175648689,51.2166061401],"type":"Point"}
}