{
  "type": "Feature",
  "properties": {
    "addr:full":"Stapelstraat 100 Sint-truiden Limburg 3800",
    "addr:housenumber":"100",
    "addr:postcode":"3800",
    "addr:street":"Stapelstraat",
    "iso:country":"BE",
    "sg:address":"Stapelstraat 100",
    "sg:city":"Sint-truiden",
    "sg:classifiers":[
        {
            "category":"Shopping",
            "subcategory":"Clothing, Apparel, & Fashions",
            "type":"Retail Goods"
        }
    ],
    "sg:phone":"+32 11 68 38 43",
    "sg:postcode":"3800",
    "sg:province":"Limburg",
    "sg:tags":[
        "clothing",
        "-",
        "gentleman"
    ],
    "wof:name":"Capri",
    "wof:placetype":"venue"
},
  "geometry": {"coordinates":[5.1805539131,50.8156166077],"type":"Point"}
}