{
  "type": "Feature",
  "properties": {
    "iso:country":"BE",
    "sg:address":"Ch De Marche 718",
    "sg:city":"Naminne",
    "sg:classifiers":[
        {
            "category":"Autos & Motor Vehicles",
            "subcategory":"Automobile Sales",
            "type":"Retail Goods"
        }
    ],
    "sg:phone":"+32 81 40 24 24",
    "sg:postcode":"5100",
    "sg:province":"Namur",
    "sg:tags":[
        "equipment",
        "motor-cars",
        "transport"
    ],
    "wof:name":"Monauto Sa",
    "wof:placetype":"venue"
},
  "geometry": {"coordinates":[13.0062303543,43.3291816711],"type":"Point"}
}