{
  "type": "Feature",
  "properties": {
    "addr:full":"Wijnstraat 17 Ronse/renaix Oost-Vlaanderen 9600",
    "addr:housenumber":"17",
    "addr:postcode":"9600",
    "addr:street":"Wijnstraat",
    "iso:country":"BE",
    "sg:address":"Wijnstraat 17",
    "sg:city":"Ronse/renaix",
    "sg:orig_category":"Antiek Tweedehandsgoederen",
    "sg:phone":"+32 55 20 98 48",
    "sg:postcode":"9600",
    "sg:province":"Oost-Vlaanderen",
    "wof:name":"Autrefois",
    "wof:placetype":"venue"
},
  "geometry": {"coordinates":[3.5986089706,50.7482566833],"type":"Point"}
}