{
  "type": "Feature",
  "properties": {
    "addr:full":"Hinnenstraat 1 Stekene Oost-Vlaanderen 9190",
    "addr:housenumber":"1",
    "addr:postcode":"9190",
    "addr:street":"Hinnenstraat",
    "iso:country":"BE",
    "sg:address":"Hinnenstraat 1",
    "sg:city":"Stekene",
    "sg:orig_category":"Eleveurs and marchands de porcs",
    "sg:phone":"+32 3 779 75 45",
    "sg:postcode":"9190",
    "sg:province":"Oost-Vlaanderen",
    "wof:name":"Koppen Gebroeders",
    "wof:placetype":"venue"
},
  "geometry": {"coordinates":[4.0010762215,51.2065162659],"type":"Point"}
}