{
  "type": "Feature",
  "properties": {
    "addr:full":"Rue Du Dr. Edmond Isaac 68 Quaregnon Hainaut 7390",
    "addr:housenumber":"68",
    "addr:postcode":"7390",
    "addr:street":"Rue Du Dr. Edmond Isaac",
    "iso:country":"BE",
    "sg:address":"Rue Du Dr. Edmond Isaac 68",
    "sg:city":"Quaregnon",
    "sg:orig_category":"Enseignement maternel and primaire",
    "sg:phone":"+32 65 77 07 22",
    "sg:postcode":"7390",
    "sg:province":"Hainaut",
    "wof:name":"Ecole Fond. Communale",
    "wof:placetype":"venue"
},
  "geometry": {"coordinates":[3.8651049137,50.4428939819],"type":"Point"}
}