{
  "type": "Feature",
  "properties": {
    "addr:full":"Avenue Charles Woeste 74 Jette Bruxelles-Capitale 1090",
    "addr:housenumber":"74",
    "addr:postcode":"1090",
    "addr:street":"Avenue Charles Woeste",
    "iso:country":"BE",
    "sg:address":"Avenue Charles Woeste 74",
    "sg:city":"Jette",
    "sg:orig_category":"Agences immobili\u00e8res. Administration d'immeubles. Assurances",
    "sg:phone":"+32 2 427 46 74",
    "sg:postcode":"1090",
    "sg:province":"Bruxelles-Capitale",
    "wof:name":"Setadi",
    "wof:placetype":"venue"
},
  "geometry": {"coordinates":[4.3334469795,50.8767662048],"type":"Point"}
}