{
  "type": "Feature",
  "properties": {
    "addr:full":"Rue De Ransart 94 Fleurus Hainaut 6220",
    "addr:housenumber":"94",
    "addr:postcode":"6220",
    "addr:street":"Rue De Ransart",
    "iso:country":"BE",
    "sg:address":"Rue De Ransart 94",
    "sg:city":"Fleurus",
    "sg:orig_category":"Studios photographiques",
    "sg:phone":"+32 71 85 24 40",
    "sg:postcode":"6220",
    "sg:province":"Hainaut",
    "wof:name":"Jean-marc Derese",
    "wof:placetype":"venue"
},
  "geometry": {"coordinates":[4.4900221825,50.4750556946],"type":"Point"}
}