{
  "type": "Feature",
  "properties": {
    "iso:country":"BE",
    "sg:address":"Ernest Van Dijckkaai 10",
    "sg:city":"Antwerpen",
    "sg:orig_category":"Levensverzekeringsmaatschappijen Verzekeringen vastgoed",
    "sg:phone":"+32 3 225 20 00",
    "sg:postcode":"2000",
    "sg:province":"Antwerpen",
    "wof:name":"Hamburg Mannheimer Cons.",
    "wof:placetype":"venue"
},
  "geometry": {"coordinates":[4.3974308968,51.2213478088],"type":"Point"}
}