{
  "type": "Feature",
  "properties": {
    "addr:full":"Nijverheidslaan 13 Sint-truiden Limburg 3800",
    "addr:housenumber":"13",
    "addr:postcode":"3800",
    "addr:street":"Nijverheidslaan",
    "iso:country":"BE",
    "sg:address":"Nijverheidslaan 13",
    "sg:city":"Sint-truiden",
    "sg:classifiers":[
        {
            "category":"Wholesale",
            "subcategory":"Hardware",
            "type":"Manufacturing & Wholesale Goods"
        }
    ],
    "sg:phone":"+32 11 48 55 04",
    "sg:postcode":"3800",
    "sg:province":"Limburg",
    "sg:tags":[
        "lubricating",
        "compound"
    ],
    "wof:name":"Dp-oil Nv",
    "wof:placetype":"venue"
},
  "geometry": {"coordinates":[5.2129797935,50.8143386841],"type":"Point"}
}