{
  "type": "Feature",
  "properties": {
    "iso:country":"BE",
    "sg:address":"Bareelstraat 79",
    "sg:city":"Geraardsbergen (idegem)",
    "sg:classifiers":[
        {
            "category":"Bakery",
            "type":"Food & Drink"
        }
    ],
    "sg:phone":"+32 54 50 15 15",
    "sg:postcode":"9506",
    "sg:province":"Oost-Vlaanderen",
    "sg:tags":[
        "confectioner",
        "baker"
    ],
    "wof:name":"Callens",
    "wof:placetype":"venue"
},
  "geometry": {"coordinates":[3.8985300064,50.7987060547],"type":"Point"}
}