{
  "type": "Feature",
  "properties": {
    "iso:country":"BE",
    "sg:address":"47",
    "sg:city":"Rue Bollinckx 1070 Bruxelles",
    "sg:classifiers":[
        {
            "category":"Wholesale",
            "subcategory":"Drugs",
            "type":"Manufacturing & Wholesale Goods"
        }
    ],
    "sg:phone":"+32 2 522 37 81",
    "sg:postcode":"47",
    "sg:tags":[
        "chemical",
        "pharmaceutical"
    ],
    "wof:name":"Ateliers De Metallisation De La Senne Sa",
    "wof:placetype":"venue"
},
  "geometry": {"coordinates":[4.303800106,50.8213157654],"type":"Point"}
}