{
  "type": "Feature",
  "properties": {
    "iso:country":"BE",
    "sg:address":"Gemeenteplaats 5",
    "sg:city":"Brecht",
    "sg:orig_category":"Banques and organismes de cr\u00e9dit",
    "sg:phone":"+32 3 313 98 51",
    "sg:postcode":"2960",
    "sg:province":"Antwerpen",
    "wof:name":"Bacob",
    "wof:placetype":"venue"
},
  "geometry": {"coordinates":[4.6432609558,51.3506011963],"type":"Point"}
}