{
  "type": "Feature",
  "properties": {
    "addr:full":"Karperstraat 4 Sint-jans-molenbeek/molenbeek-saint-jean Bruxelles-Capitale 1080",
    "addr:housenumber":"4",
    "addr:postcode":"1080",
    "addr:street":"Karperstraat",
    "iso:country":"BE",
    "sg:address":"Karperstraat 4",
    "sg:city":"Sint-jans-molenbeek/molenbeek-saint-jean",
    "sg:orig_category":"Kapsalons",
    "sg:phone":"+32 2 411 55 28",
    "sg:postcode":"1080",
    "sg:province":"Bruxelles-Capitale",
    "wof:name":"Coiffure Lucr\u00c8ce",
    "wof:placetype":"venue"
},
  "geometry": {"coordinates":[4.3329901695,50.8568077087],"type":"Point"}
}