{
  "type": "Feature",
  "properties": {
    "iso:country":"BE",
    "sg:address":"Chauss\u00c9e De Waterloo 217",
    "sg:city":"Sint-gillis/saint-gilles",
    "sg:orig_category":"RESTAURANTS: CAF\u00c9S",
    "sg:phone":"+32 2 539 28 04",
    "sg:postcode":"1060",
    "sg:province":"Bruxelles-Capitale",
    "wof:name":"Le Waterloo",
    "wof:placetype":"venue"
},
  "geometry": {"coordinates":[4.3473758698,50.8255157471],"type":"Point"}
}