{
  "type": "Feature",
  "properties": {
    "iso:country":"BE",
    "sg:address":"Gouden Kruispunt 1",
    "sg:city":"Tielt-winge",
    "sg:orig_category":"Mat\u00e9riel de T\u00e9l\u00e9communication. Electrom\u00e9nager, t\u00e9l\u00e9visions and radios. R\u00e9parations d'appareils \u00e9lect",
    "sg:phone":"+32 16 64 03 70",
    "sg:postcode":"3390",
    "sg:province":"Vlaams-Brabant",
    "wof:name":"Kr\u00cbfel",
    "wof:placetype":"venue"
},
  "geometry": {"coordinates":[4.8727779388,50.9049797058],"type":"Point"}
}