{
  "type": "Feature",
  "properties": {
    "addr:full":"Rogierlaan 155 Brussel/bruxelles Bruxelles-Capitale 1030",
    "addr:housenumber":"155",
    "addr:postcode":"1030",
    "addr:street":"Rogierlaan;/",
    "iso:country":"BE",
    "sg:address":"Rogierlaan 155",
    "sg:city":"Brussel/bruxelles",
    "sg:orig_category":"Banken and kredietinstellingen",
    "sg:phone":"+32 2 241 89 60",
    "sg:postcode":"1030",
    "sg:province":"Bruxelles-Capitale",
    "wof:name":"Fortis",
    "wof:placetype":"venue"
},
  "geometry": {"coordinates":[4.3802809715,50.8586883545],"type":"Point"}
}