{
  "type": "Feature",
  "properties": {
    "iso:country":"BE",
    "sg:address":"Stationsstraat 42",
    "sg:city":"Herent",
    "sg:orig_category":"Services fun\u00e9raires",
    "sg:phone":"+32 16 48 81 22",
    "sg:postcode":"3020",
    "sg:province":"Vlaams-Brabant",
    "wof:name":"Begrafenissen Van Roey L.",
    "wof:placetype":"venue"
},
  "geometry": {"coordinates":[4.6282858849,50.9011917114],"type":"Point"}
}