{
  "type": "Feature",
  "properties": {
    "addr:full":"Sint-antoniusstraat 12 Meulebeke West-Vlaanderen 8760",
    "addr:housenumber":"12",
    "addr:postcode":"8760",
    "addr:street":"Sint-Antoniusstraat",
    "iso:country":"BE",
    "sg:address":"Sint-antoniusstraat 12",
    "sg:city":"Meulebeke",
    "sg:orig_category":"Installation de menuiserie m\u00e9tallique",
    "sg:phone":"+32 51 48 56 85",
    "sg:postcode":"8760",
    "sg:province":"West-Vlaanderen",
    "wof:name":"Wim Vandenbussche",
    "wof:placetype":"venue"
},
  "geometry": {"coordinates":[3.243103981,50.9626274109],"type":"Point"}
}