{
  "type": "Feature",
  "properties": {
    "addr:full":"George Dit Marchalstraat 1m Koekelberg Bruxelles-Capitale 1081",
    "addr:housenumber":"1m",
    "addr:postcode":"1081",
    "addr:street":"George Dit Marchalstraat",
    "iso:country":"BE",
    "sg:address":"George Dit Marchalstraat 1m",
    "sg:city":"Koekelberg",
    "sg:orig_category":"Schoonmaakbedrijven and ongediertebestrijding",
    "sg:phone":"+32 2 414 92 45",
    "sg:postcode":"1081",
    "sg:province":"Bruxelles-Capitale",
    "wof:name":"Abdelhak Mouhsine",
    "wof:placetype":"venue"
},
  "geometry": {"coordinates":[4.3316469193,50.8610534668],"type":"Point"}
}