{
  "type": "Feature",
  "properties": {
    "addr:full":"Kuipersstraat 13 Antwerpen Antwerpen 2000",
    "addr:housenumber":"13",
    "addr:postcode":"2000",
    "addr:street":"Kuipersstraat",
    "iso:country":"BE",
    "sg:address":"Kuipersstraat 13",
    "sg:city":"Antwerpen",
    "sg:classifiers":[
        {
            "category":"Health Services",
            "subcategory":"Health Practitioner",
            "type":"Services"
        }
    ],
    "sg:phone":"+32 3 226 93 16",
    "sg:postcode":"2000",
    "sg:province":"Antwerpen",
    "sg:tags":[
        "physiotherapist"
    ],
    "wof:name":"Bauning Nathalie",
    "wof:placetype":"venue"
},
  "geometry": {"coordinates":[4.3990240097,51.2224502563],"type":"Point"}
}