{
  "type": "Feature",
  "properties": {
    "iso:country":"BE",
    "sg:address":"Kleine Wouwer 28",
    "sg:city":"Meise",
    "sg:classifiers":[
        {
            "category":"Professional",
            "subcategory":"Computer Services",
            "type":"Services"
        }
    ],
    "sg:phone":"+32 475 93 16 89",
    "sg:postcode":"1860",
    "sg:province":"Vlaams-Brabant",
    "sg:tags":[
        "-",
        "processing",
        "data",
        "software"
    ],
    "wof:name":"Bailleul Consulting Bvba",
    "wof:placetype":"venue"
},
  "geometry": {"coordinates":[4.3197751045,50.9367256165],"type":"Point"}
}