{
  "type": "Feature",
  "properties": {
    "addr:full":"Rue De L'argonne 22 Sint-gillis/saint-gilles Bruxelles-Capitale 1060",
    "addr:housenumber":"22",
    "addr:postcode":"1060",
    "addr:street":"Rue De L'Argonne",
    "iso:country":"BE",
    "sg:address":"Rue De L'argonne 22",
    "sg:city":"Sint-gillis/saint-gilles",
    "sg:classifiers":[
        {
            "category":"Restaurant",
            "type":"Food & Drink"
        }
    ],
    "sg:phone":"+32 2 538 21 13",
    "sg:postcode":"1060",
    "sg:province":"Bruxelles-Capitale",
    "wof:name":"Ath\u00c8nes",
    "wof:placetype":"venue"
},
  "geometry": {"coordinates":[4.3404860497,50.8372764587],"type":"Point"}
}