{
  "type": "Feature",
  "properties": {
    "addr:full":"Avenue Marius Meur\u00e9e 36 Charleroi (marcinelle) Hainaut 6001",
    "addr:housenumber":"36",
    "addr:postcode":"6001",
    "addr:street":"Avenue Marius Meure\u0301E",
    "iso:country":"BE",
    "sg:address":"Avenue Marius Meur\u00e9e 36",
    "sg:city":"Charleroi (marcinelle)",
    "sg:classifiers":[
        {
            "category":"Home & Garden",
            "subcategory":"Building Materials",
            "type":"Retail Goods"
        }
    ],
    "sg:phone":"+32 71 36 10 66",
    "sg:postcode":"6001",
    "sg:province":"Hainaut",
    "sg:tags":[
        "wall",
        "cupboard"
    ],
    "wof:name":"Galeries Ideal",
    "wof:placetype":"venue"
},
  "geometry": {"coordinates":[4.4471859932,50.4012260437],"type":"Point"}
}