{
  "type": "Feature",
  "properties": {
    "iso:country":"BE",
    "sg:address":"Lijsterstraat 24",
    "sg:city":"Berlaar",
    "sg:classifiers":[
        {
            "category":"Wholesale",
            "subcategory":"Farm Supplies",
            "type":"Manufacturing & Wholesale Goods"
        }
    ],
    "sg:phone":"+32 3 482 16 69",
    "sg:postcode":"2590",
    "sg:province":"Antwerpen",
    "sg:tags":[
        "agricultural",
        "part",
        "spare",
        "machinery",
        "accessory"
    ],
    "wof:name":"Hws B.v.b.a.",
    "wof:placetype":"venue"
},
  "geometry": {"coordinates":[4.6388292313,51.1121864319],"type":"Point"}
}