{
  "type": "Feature",
  "properties": {
    "iso:country":"BE",
    "sg:address":"Avenue De L'or\u00e9e 25",
    "sg:city":"Bruxelles (ixelles)",
    "sg:classifiers":[
        {
            "category":"Transit Center",
            "subcategory":"Freight",
            "type":"Transportation"
        }
    ],
    "sg:phone":"+32 2 648 18 42",
    "sg:postcode":"1050",
    "sg:province":"Bruxelles-Capitale",
    "sg:tags":[
        "import",
        "export",
        "-"
    ],
    "wof:name":"Adecor Sprl",
    "wof:placetype":"venue"
},
  "geometry": {"coordinates":[4.3857798576,50.8104133606],"type":"Point"}
}