{
  "type": "Feature",
  "properties": {
    "addr:full":"Lamstraat 1 Sint-niklaas Oost-Vlaanderen 9100",
    "addr:housenumber":"1",
    "addr:postcode":"9100",
    "addr:street":"Lamstraat",
    "iso:country":"BE",
    "sg:address":"Lamstraat 1",
    "sg:city":"Sint-niklaas",
    "sg:orig_category":"Boucheries",
    "sg:phone":"+32 3 766 38 27",
    "sg:postcode":"9100",
    "sg:province":"Oost-Vlaanderen",
    "wof:name":"Buurtslagers",
    "wof:placetype":"venue"
},
  "geometry": {"coordinates":[4.1521410942,51.1670341492],"type":"Point"}
}