{
  "type": "Feature",
  "properties": {
    "iso:country":"BE",
    "sg:address":"Kasteeldreef 1ba",
    "sg:city":"Oostkamp",
    "sg:orig_category":"Activit\u00e9s diverses d'imprimerie",
    "sg:phone":"+32 50 28 13 42",
    "sg:postcode":"8020",
    "sg:province":"West-Vlaanderen",
    "wof:name":"Johannes De Cock",
    "wof:placetype":"venue"
},
  "geometry": {"coordinates":[3.2702510357,51.102142334],"type":"Point"}
}