{
  "type": "Feature",
  "properties": {
    "iso:country":"BE",
    "sg:address":"Rechtstraat 70",
    "sg:city":"Lokeren",
    "sg:orig_category":"Eleveurs de bovins",
    "sg:phone":"+32 9 346 97 00",
    "sg:postcode":"9160",
    "sg:province":"Oost-Vlaanderen",
    "wof:name":"Jozef Van Damme",
    "wof:placetype":"venue"
},
  "geometry": {"coordinates":[3.940737009,51.1414756775],"type":"Point"}
}