{
  "type": "Feature",
  "properties": {
    "iso:country":"BE",
    "sg:address":"Helipoststraat 37",
    "sg:city":"Hasselt",
    "sg:orig_category":"Postkantoren Verzekeringsmakelaars and experts",
    "sg:phone":"+32 11 27 32 30",
    "sg:postcode":"3500",
    "sg:province":"Limburg",
    "wof:name":"De Post",
    "wof:placetype":"venue"
},
  "geometry": {"coordinates":[5.324297905,50.9236602783],"type":"Point"}
}