{
  "type": "Feature",
  "properties": {
    "iso:country":"BE",
    "sg:address":"Antwerpsesteenweg 335",
    "sg:city":"Malle",
    "sg:orig_category":"Supermarkten",
    "sg:phone":"+32 3 312 00 72",
    "sg:postcode":"2390",
    "sg:province":"Antwerpen",
    "wof:name":"Unic",
    "wof:placetype":"venue"
},
  "geometry": {"coordinates":[4.687128067,51.2972373962],"type":"Point"}
}