{
  "type": "Feature",
  "properties": {
    "addr:full":"Peter Benoitstraat 30 Antwerpen Antwerpen 2018",
    "addr:housenumber":"30",
    "addr:postcode":"2018",
    "addr:street":"Peter Benoitstraat",
    "iso:country":"BE",
    "sg:address":"Peter Benoitstraat 30",
    "sg:city":"Antwerpen",
    "sg:orig_category":"Artsen and specialisten",
    "sg:phone":"+32 3 238 24 37",
    "sg:postcode":"2018",
    "sg:province":"Antwerpen",
    "wof:name":"J. De Munck",
    "wof:placetype":"venue"
},
  "geometry": {"coordinates":[4.408531189,51.2045173645],"type":"Point"}
}