{
  "type": "Feature",
  "properties": {
    "iso:country":"BE",
    "sg:address":"Blekerijstraat 75",
    "sg:city":"Gent",
    "sg:orig_category":"Dakwerken",
    "sg:phone":"+32 9 225 47 75",
    "sg:postcode":"9000",
    "sg:province":"Oost-Vlaanderen",
    "wof:name":"Dewaelsche En Zonen",
    "wof:placetype":"venue"
},
  "geometry": {"coordinates":[3.7326099873,51.0597686768],"type":"Point"}
}