{
  "type": "Feature",
  "properties": {
    "addr:full":"Terlicht 112 Haaltert Oost-Vlaanderen 9451",
    "addr:housenumber":"112",
    "addr:postcode":"9451",
    "addr:street":"Terlicht",
    "iso:country":"BE",
    "sg:address":"Terlicht 112",
    "sg:city":"Haaltert",
    "sg:classifiers":[
        {
            "category":"Cafe",
            "type":"Food & Drink"
        }
    ],
    "sg:phone":"+32 53 83 70 20",
    "sg:postcode":"9451",
    "sg:province":"Oost-Vlaanderen",
    "sg:tags":[
        "caf\u00e9s"
    ],
    "wof:name":"Fabienne Van Schelvergem",
    "wof:placetype":"venue"
},
  "geometry": {"coordinates":[3.9749670029,50.8806991577],"type":"Point"}
}