{
  "type": "Feature",
  "properties": {
    "iso:country":"BE",
    "sg:address":"Voorstraat 97",
    "sg:city":"Kaprijke",
    "sg:orig_category":"Meubles D\u00e9taillants, Am\u00e9nagement de B\u00e2timents et de Cuisines",
    "sg:phone":"+32 9 373 66 54",
    "sg:postcode":"9970",
    "sg:province":"Oost-Vlaanderen",
    "wof:name":"Meub.de Busscher Maledrie",
    "wof:placetype":"venue"
},
  "geometry": {"coordinates":[3.6086800098,51.2183570862],"type":"Point"}
}