{
  "type": "Feature",
  "properties": {
    "iso:country":"BE",
    "sg:address":"Boomse Steenweg 356",
    "sg:city":"Antwerpen",
    "sg:classifiers":[
        {
            "category":"Bars & Pubs",
            "type":"Food & Drink"
        }
    ],
    "sg:phone":"+32 3 238 07 77",
    "sg:postcode":"2020",
    "sg:province":"Antwerpen",
    "wof:name":"Bristol",
    "wof:placetype":"venue"
},
  "geometry": {"coordinates":[4.3876438141,51.1872215271],"type":"Point"}
}