{
  "type": "Feature",
  "properties": {
    "iso:country":"BE",
    "sg:address":"Bogaerdenstraat 25a",
    "sg:city":"Zoutleeuw",
    "sg:classifiers":[
        {
            "category":"Personal",
            "subcategory":"Beauty Salon",
            "type":"Services"
        }
    ],
    "sg:phone":"+32 11 78 01 32",
    "sg:postcode":"3440",
    "sg:province":"Vlaams-Brabant",
    "sg:tags":[
        "lady",
        "-",
        "hairdressing"
    ],
    "wof:name":"Boyen M",
    "wof:placetype":"venue"
},
  "geometry": {"coordinates":[5.1042709351,50.835018158],"type":"Point"}
}