{
  "type": "Feature",
  "properties": {
    "addr:full":"Place De La Petite Suisse 10 Bruxelles (ixelles) Bruxelles-Capitale 1050",
    "addr:housenumber":"10",
    "addr:postcode":"1050",
    "addr:street":"Place De La Petite Suisse",
    "iso:country":"BE",
    "sg:address":"Place De La Petite Suisse 10",
    "sg:city":"Bruxelles (ixelles)",
    "sg:classifiers":[
        {
            "category":"Personal",
            "subcategory":"Barber",
            "type":"Services"
        }
    ],
    "sg:phone":"+32 2 649 02 96",
    "sg:postcode":"1050",
    "sg:province":"Bruxelles-Capitale",
    "sg:tags":[
        "gentleman",
        "salon",
        "-",
        "hairdressing"
    ],
    "wof:name":"Jean-pierre",
    "wof:placetype":"venue"
},
  "geometry": {"coordinates":[4.4064021111,50.8637771606],"type":"Point"}
}