{
  "type": "Feature",
  "properties": {
    "iso:country":"BE",
    "sg:address":"Krekelstraat 11",
    "sg:city":"Gent (zwijnaarde)",
    "sg:classifiers":[
        {
            "category":"Home & Garden",
            "subcategory":"Carpets & Floor Coverings",
            "type":"Retail Goods"
        }
    ],
    "sg:phone":"+32 9 222 50 65",
    "sg:postcode":"9052",
    "sg:province":"Oost-Vlaanderen",
    "sg:tags":[
        "layer",
        "mosaicists"
    ],
    "wof:name":"De Schuyter A",
    "wof:placetype":"venue"
},
  "geometry": {"coordinates":[3.7167270184,51.0002937317],"type":"Point"}
}