{
  "type": "Feature",
  "properties": {
    "addr:full":"Provinciebaan 29 Bekkevoort Vlaams-Brabant 3460",
    "addr:housenumber":"29",
    "addr:postcode":"3460",
    "addr:street":"Provinciebaan",
    "iso:country":"BE",
    "sg:address":"Provinciebaan 29",
    "sg:city":"Bekkevoort",
    "sg:orig_category":"Eleveurs and marchands de porcs",
    "sg:phone":"+32 13 33 39 34",
    "sg:postcode":"3460",
    "sg:province":"Vlaams-Brabant",
    "wof:name":"Gustaaf Das",
    "wof:placetype":"venue"
},
  "geometry": {"coordinates":[4.9885201454,50.9324188232],"type":"Point"}
}