{
  "type": "Feature",
  "properties": {
    "addr:full":"Chrysantenstraat 6 Merelbeke Oost-Vlaanderen 9820",
    "addr:housenumber":"6",
    "addr:postcode":"9820",
    "addr:street":"Chrysantenstraat",
    "iso:country":"BE",
    "sg:address":"Chrysantenstraat 6",
    "sg:city":"Merelbeke",
    "sg:orig_category":"Supermarkten",
    "sg:postcode":"9820",
    "sg:province":"Oost-Vlaanderen",
    "wof:name":"Aldi",
    "wof:placetype":"venue"
},
  "geometry": {"coordinates":[3.7522509098,51.002040863],"type":"Point"}
}