{
  "type": "Feature",
  "properties": {
    "iso:country":"BE",
    "sg:address":"Place De La Gendarmerie 8",
    "sg:city":"Saint-hubert",
    "sg:orig_category":"Plaatsen van vloer- and muurbekleding Schilders",
    "sg:phone":"+32 61 61 28 51",
    "sg:postcode":"6870",
    "sg:province":"Luxembourg",
    "wof:name":"Decor Style",
    "wof:placetype":"venue"
},
  "geometry": {"coordinates":[5.3769168854,50.0280914307],"type":"Point"}
}