{
  "type": "Feature",
  "properties": {
    "iso:country":"BE",
    "sg:address":"Rue De Landelies 72",
    "sg:city":"Charleroi",
    "sg:classifiers":[
        {
            "category":"Fast Food",
            "type":"Food & Drink"
        }
    ],
    "sg:phone":"+32 71 32 95 68",
    "sg:postcode":"6031",
    "sg:province":"Hainaut",
    "sg:tags":[
        "\u00c0",
        "restaurants",
        "emporter",
        "restaurant"
    ],
    "wof:name":"Restaurant Tony",
    "wof:placetype":"venue"
},
  "geometry": {"coordinates":[4.38022995,50.4121742249],"type":"Point"}
}