{
  "type": "Feature",
  "properties": {
    "addr:full":"Rue Haute Sauveni\u00c8re 39 Li\u00c8ge Li\u00e8ge 4000",
    "addr:housenumber":"39",
    "addr:postcode":"4000",
    "addr:street":"Rue Haute Sauvenie\u0300Re",
    "iso:country":"BE",
    "sg:address":"Rue Haute Sauveni\u00c8re 39",
    "sg:city":"Li\u00c8ge",
    "sg:classifiers":[
        {
            "category":"Restaurant",
            "type":"Food & Drink"
        }
    ],
    "sg:phone":"+32 4 237 04 54",
    "sg:postcode":"4000",
    "sg:province":"Li\u00e8ge",
    "wof:name":"Chez Philippe",
    "wof:placetype":"venue"
},
  "geometry": {"coordinates":[5.5679988861,50.6439476013],"type":"Point"}
}