{
  "type": "Feature",
  "properties": {
    "addr:full":"Rue Du Cougereau 7 Cerfontaine Namur 5630",
    "addr:housenumber":"7",
    "addr:postcode":"5630",
    "addr:street":"Rue Du Cougereau",
    "iso:country":"BE",
    "sg:address":"Rue Du Cougereau 7",
    "sg:city":"Cerfontaine",
    "sg:orig_category":"G\u00e9om\u00e8tres",
    "sg:phone":"+32 71 64 47 88",
    "sg:postcode":"5630",
    "sg:province":"Namur",
    "wof:name":"Jean-luc Hublet",
    "wof:placetype":"venue"
},
  "geometry": {"coordinates":[4.4016599655,50.1672668457],"type":"Point"}
}