{
  "type": "Feature",
  "properties": {
    "addr:full":"Rue Du Bemel 21 Bruxelles (woluwe-saint-pierre) Bruxelles-Capitale 1150",
    "addr:housenumber":"21",
    "addr:postcode":"1150",
    "addr:street":"Rue Du Bemel",
    "iso:country":"BE",
    "sg:address":"Rue Du Bemel 21",
    "sg:city":"Bruxelles (woluwe-saint-pierre)",
    "sg:classifiers":[
        {
            "category":"Museum",
            "type":"Entertainment"
        }
    ],
    "sg:phone":"+32 2 770 53 33",
    "sg:postcode":"1150",
    "sg:province":"Bruxelles-Capitale",
    "wof:name":"Bibliotheca Wittockiana Asbl",
    "wof:placetype":"venue"
},
  "geometry": {"coordinates":[4.4209008217,50.8323707581],"type":"Point"}
}