{
  "type": "Feature",
  "properties": {
    "addr:full":"Place Du Docteur-hollenfeltz 5 Arlon Luxembourg 6700",
    "addr:housenumber":"5",
    "addr:postcode":"6700",
    "addr:street":"Place Du Docteur-Hollenfeltz",
    "iso:country":"BE",
    "sg:address":"Place Du Docteur-hollenfeltz 5",
    "sg:city":"Arlon",
    "sg:classifiers":[
        {
            "category":"Bars & Pubs",
            "type":"Food & Drink"
        }
    ],
    "sg:phone":"+32 63 21 70 12",
    "sg:postcode":"6700",
    "sg:province":"Luxembourg",
    "wof:name":"V\u00e9nitien (le)",
    "wof:placetype":"venue"
},
  "geometry": {"coordinates":[5.8132019043,49.6839790344],"type":"Point"}
}