{
  "type": "Feature",
  "properties": {
    "iso:country":"BE",
    "sg:address":"Hoogstadestraat 61",
    "sg:city":"Alveringem",
    "sg:classifiers":[
        {
            "category":"Restaurant",
            "type":"Food & Drink"
        }
    ],
    "sg:phone":"+32 58 28 87 13",
    "sg:postcode":"8690",
    "sg:province":"West-Vlaanderen",
    "wof:name":"De Leylander",
    "wof:placetype":"venue"
},
  "geometry": {"coordinates":[2.6855099201,51.0007591248],"type":"Point"}
}