{
  "type": "Feature",
  "properties": {
    "iso:country":"BE",
    "sg:address":"Rue Biomont 15",
    "sg:city":"Herve (battice)",
    "sg:classifiers":[
        {
            "category":"Manufacturing",
            "subcategory":"Tools & Machinery",
            "type":"Manufacturing & Wholesale Goods"
        }
    ],
    "sg:phone":"+32 87 67 81 47",
    "sg:postcode":"4651",
    "sg:province":"Li\u00e8ge",
    "sg:tags":[
        "machine"
    ],
    "wof:name":"Delde Engineering Sprl",
    "wof:placetype":"venue"
},
  "geometry": {"coordinates":[5.7994837761,50.6161193848],"type":"Point"}
}