{
  "type": "Feature",
  "properties": {
    "iso:country":"BE",
    "sg:address":"Houmont 10",
    "sg:city":"Sainte-ode",
    "sg:orig_category":"Salles de conf\u00e9rences and de r\u00e9ceptions",
    "sg:phone":"+32 61 26 61 74",
    "sg:postcode":"6680",
    "sg:province":"Luxembourg",
    "wof:name":"Salle Des F\u00cates",
    "wof:placetype":"venue"
},
  "geometry": {"coordinates":[5.5304489136,50.0108299255],"type":"Point"}
}