{
  "type": "Feature",
  "properties": {
    "addr:full":"Ringlaan 15 Koekelare West-Vlaanderen 8680",
    "addr:housenumber":"15",
    "addr:postcode":"8680",
    "addr:street":"Ringlaan",
    "iso:country":"BE",
    "sg:address":"Ringlaan 15",
    "sg:city":"Koekelare",
    "sg:orig_category":"Rev\u00eatements pour sols and murs. Peinture",
    "sg:phone":"+32 51 58 85 13",
    "sg:postcode":"8680",
    "sg:province":"West-Vlaanderen",
    "wof:name":"Crevits A.",
    "wof:placetype":"venue"
},
  "geometry": {"coordinates":[2.9785439968,51.0927886963],"type":"Point"}
}