{
  "type": "Feature",
  "properties": {
    "iso:country":"BE",
    "sg:address":"Rue De Housse 2",
    "sg:city":"Vise",
    "sg:classifiers":[
        {
            "category":"Cafe",
            "type":"Food & Drink"
        }
    ],
    "sg:phone":"+32 4 379 56 34",
    "sg:postcode":"4600",
    "sg:province":"Li\u00e8ge",
    "sg:tags":[
        "caf\u00e9s"
    ],
    "wof:name":"Simon W. & Thomas C.",
    "wof:placetype":"venue"
},
  "geometry": {"coordinates":[5.6996150017,50.7163467407],"type":"Point"}
}