{
  "type": "Feature",
  "properties": {
    "addr:full":"Chauss\u00e9e De Wavre 255 Bruxelles (ixelles) Bruxelles-Capitale 1050",
    "addr:housenumber":"255",
    "addr:postcode":"1050",
    "addr:street":"Chausse\u0301E De Wavre",
    "iso:country":"BE",
    "sg:address":"Chauss\u00e9e De Wavre 255",
    "sg:city":"Bruxelles (ixelles)",
    "sg:classifiers":[
        {
            "category":"Home & Garden",
            "subcategory":"Kitchen Supply",
            "type":"Retail Goods"
        }
    ],
    "sg:phone":"+32 2 648 11 14",
    "sg:postcode":"1050",
    "sg:province":"Bruxelles-Capitale",
    "sg:tags":[
        "installation"
    ],
    "wof:name":"De Wolf R & J Nv",
    "wof:placetype":"venue"
},
  "geometry": {"coordinates":[4.376625061,50.8357048035],"type":"Point"}
}