{
  "type": "Feature",
  "properties": {
    "addr:full":"Nijverheidskaai 37 Sint-amandsberg Oost-Vlaanderen 9040",
    "addr:housenumber":"37",
    "addr:postcode":"9040",
    "addr:street":"Nijverheidskaai",
    "iso:country":"BE",
    "sg:address":"Nijverheidskaai 37",
    "sg:city":"Sint-amandsberg",
    "sg:classifiers":[
        {
            "category":"Food & Beverages",
            "subcategory":"Groceries & Convenience Stores",
            "type":"Retail Goods"
        }
    ],
    "sg:phone":"+32 9 228 21 09",
    "sg:postcode":"9040",
    "sg:province":"Oost-Vlaanderen",
    "sg:tags":[
        "product",
        "related"
    ],
    "wof:name":"E M Discount Nv",
    "wof:placetype":"venue"
},
  "geometry": {"coordinates":[3.7628440857,51.0492095947],"type":"Point"}
}