{
  "type": "Feature",
  "properties": {
    "iso:country":"BE",
    "sg:address":"Ververijstraat 15",
    "sg:city":"Gent",
    "sg:classifiers":[
        {
            "category":"Social Services",
            "type":"Services"
        }
    ],
    "sg:phone":"+32 9 218 88 99",
    "sg:postcode":"9000",
    "sg:province":"Oost-Vlaanderen",
    "wof:name":"Oxfam Wereldwinkels Vzw",
    "wof:placetype":"venue"
},
  "geometry": {"coordinates":[3.7449018955,51.0529823303],"type":"Point"}
}