{
  "type": "Feature",
  "properties": {
    "addr:full":"Hendrik Consciencelaan 177 Evere/evere Bruxelles-Capitale 1140",
    "addr:housenumber":"177",
    "addr:postcode":"1140",
    "addr:street":"Hendrik Consciencelaan",
    "iso:country":"BE",
    "sg:address":"Hendrik Consciencelaan 177",
    "sg:city":"Evere/evere",
    "sg:orig_category":"Industri\u00eble wasserijen and droogkuis",
    "sg:phone":"+32 2 241 60 12",
    "sg:postcode":"1140",
    "sg:province":"Bruxelles-Capitale",
    "wof:name":"Conscience Clean",
    "wof:placetype":"venue"
},
  "geometry": {"coordinates":[4.4000120163,50.8723564148],"type":"Point"}
}