{
  "type": "Feature",
  "properties": {
    "iso:country":"BE",
    "sg:address":"Beekhoekstraat 3",
    "sg:city":"Lint",
    "sg:classifiers":[
        {
            "category":"Professional",
            "subcategory":"Lawyer & Legal Services",
            "type":"Services"
        }
    ],
    "sg:phone":"+32 3 454 39 67",
    "sg:postcode":"2547",
    "sg:province":"Antwerpen",
    "wof:name":"Van Regenmortel A",
    "wof:placetype":"venue"
},
  "geometry": {"coordinates":[4.4866909981,51.1347808838],"type":"Point"}
}