{
  "type": "Feature",
  "properties": {
    "iso:country":"BE",
    "sg:address":"Meiboomstraat 38",
    "sg:city":"Beernem",
    "sg:orig_category":"Instituts de beaut\u00e9",
    "sg:phone":"+32 50 78 11 14",
    "sg:postcode":"8730",
    "sg:province":"West-Vlaanderen",
    "wof:name":"Katrien Viaene",
    "wof:placetype":"venue"
},
  "geometry": {"coordinates":[3.3448059559,51.1408004761],"type":"Point"}
}