{
  "type": "Feature",
  "properties": {
    "addr:full":"Eedgenotenstraat 29 Brussel/bruxelles Bruxelles-Capitale 1000",
    "addr:housenumber":"29",
    "addr:postcode":"1000",
    "addr:street":"Eedgenotenstraat;/",
    "iso:country":"BE",
    "sg:address":"Eedgenotenstraat 29",
    "sg:city":"Brussel/bruxelles",
    "sg:orig_category":"Reclamebureaus",
    "sg:phone":"+32 2 735 55 56",
    "sg:postcode":"1000",
    "sg:province":"Bruxelles-Capitale",
    "wof:name":"Bureau Persuasion",
    "wof:placetype":"venue"
},
  "geometry": {"coordinates":[4.3846387863,50.8488388062],"type":"Point"}
}