{
  "type": "Feature",
  "properties": {
    "addr:full":"Jozef Hendrickxstraat 197 Schoten Antwerpen 2900",
    "addr:housenumber":"197",
    "addr:postcode":"2900",
    "addr:street":"Jozef Hendrickxstraat",
    "iso:country":"BE",
    "sg:address":"Jozef Hendrickxstraat 197",
    "sg:city":"Schoten",
    "sg:classifiers":[
        {
            "category":"Restaurant",
            "type":"Food & Drink"
        }
    ],
    "sg:phone":"+32 3 658 32 26",
    "sg:postcode":"2900",
    "sg:province":"Antwerpen",
    "sg:tags":[
        "caf\u00e9s"
    ],
    "wof:name":"Taverne Salamander",
    "wof:placetype":"venue"
},
  "geometry": {"coordinates":[4.4861798286,51.2493896484],"type":"Point"}
}