{
  "type": "Feature",
  "properties": {
    "iso:country":"BE",
    "sg:address":"Britselei 23",
    "sg:city":"Antwerpen",
    "sg:orig_category":"Groenten and fruit Gh",
    "sg:phone":"+32 3 224 75 75",
    "sg:postcode":"2000",
    "sg:province":"Antwerpen",
    "wof:name":"Inter Verde",
    "wof:placetype":"venue"
},
  "geometry": {"coordinates":[4.406539917,51.2098236084],"type":"Point"}
}