{
  "type": "Feature",
  "properties": {
    "addr:full":"Hille 169f Wingene (zwevezele) West-Vlaanderen 8750",
    "addr:housenumber":"169f",
    "addr:postcode":"8750",
    "addr:street":"Hille",
    "iso:country":"BE",
    "sg:address":"Hille 169f",
    "sg:city":"Wingene (zwevezele)",
    "sg:orig_category":"Non-Classified Establishments",
    "sg:phone":"+32 51 61 12 81",
    "sg:postcode":"8750",
    "sg:province":"West-Vlaanderen",
    "wof:name":"Vienne Philippe Nv",
    "wof:placetype":"venue"
},
  "geometry": {"coordinates":[3.2266900539,51.0430870056],"type":"Point"}
}