{
  "type": "Feature",
  "properties": {
    "addr:full":"Rue Niton 11 Fleron Li\u00e8ge 4623",
    "addr:housenumber":"11",
    "addr:postcode":"4623",
    "addr:street":"Rue Niton",
    "iso:country":"BE",
    "sg:address":"Rue Niton 11",
    "sg:city":"Fleron",
    "sg:orig_category":"Activit\u00e9s diverses d'imprimerie",
    "sg:phone":"+32 4 358 78 37",
    "sg:postcode":"4623",
    "sg:province":"Li\u00e8ge",
    "wof:name":"Michel Demez",
    "wof:placetype":"venue"
},
  "geometry": {"coordinates":[5.6805930138,50.6031150818],"type":"Point"}
}