{
  "type": "Feature",
  "properties": {
    "iso:country":"BE",
    "sg:address":"Kasteelbrakelsesteenweg 101",
    "sg:city":"Halle (lembeek)",
    "sg:classifiers":[
        {
            "category":"Bars & Pubs",
            "type":"Food & Drink"
        }
    ],
    "sg:phone":"+32 2 360 00 16",
    "sg:postcode":"1502",
    "sg:province":"Vlaams-Brabant",
    "wof:name":"Nieuwe Ballon (in De)",
    "wof:placetype":"venue"
},
  "geometry": {"coordinates":[4.2355341911,50.7036209106],"type":"Point"}
}