{
  "type": "Feature",
  "properties": {
    "iso:country":"BE",
    "sg:address":"Hospitaalstraat 25",
    "sg:city":"Bilzen",
    "sg:classifiers":[
        {
            "category":"Real Estate",
            "subcategory":"Surveying",
            "type":"Services"
        }
    ],
    "sg:phone":"+32 89 51 55 53",
    "sg:postcode":"3740",
    "sg:province":"Limburg",
    "sg:tags":[
        "surveyor",
        "land"
    ],
    "wof:name":"Ritzen L",
    "wof:placetype":"venue"
},
  "geometry": {"coordinates":[5.5126857758,50.8706474304],"type":"Point"}
}