{
  "type": "Feature",
  "properties": {
    "iso:country":"BE",
    "sg:address":"Rue De Hesbaye 35",
    "sg:city":"Donceel (limont)",
    "sg:classifiers":[
        {
            "category":"Bars & Pubs",
            "type":"Food & Drink"
        }
    ],
    "sg:phone":"+32 19 54 43 55",
    "sg:postcode":"4357",
    "sg:province":"Li\u00e8ge",
    "wof:name":"Hesbaye (le)",
    "wof:placetype":"venue"
},
  "geometry": {"coordinates":[5.310737133,50.6616973877],"type":"Point"}
}