{
  "type": "Feature",
  "properties": {
    "iso:country":"BE",
    "sg:address":"Stationsdreef 8",
    "sg:city":"Roeselare",
    "sg:orig_category":"Advocaten and juridische adviseurs",
    "sg:phone":"+32 51 24 44 10",
    "sg:postcode":"8800",
    "sg:province":"West-Vlaanderen",
    "wof:name":"Arnold Van Tyghem",
    "wof:placetype":"venue"
},
  "geometry": {"coordinates":[3.1284239292,50.9522171021],"type":"Point"}
}