{
  "type": "Feature",
  "properties": {
    "addr:full":"Avenue De Tervueren 36 Etterbeek/etterbeek Bruxelles-Capitale 1040",
    "addr:housenumber":"36",
    "addr:postcode":"1040",
    "addr:street":"Avenue De Tervueren",
    "iso:country":"BE",
    "sg:address":"Avenue De Tervueren 36",
    "sg:city":"Etterbeek/etterbeek",
    "sg:classifiers":[
        {
            "category":"Restaurant",
            "type":"Food & Drink"
        }
    ],
    "sg:phone":"+32 2 736 74 57",
    "sg:postcode":"1040",
    "sg:province":"Bruxelles-Capitale",
    "wof:name":"Le Brasilla",
    "wof:placetype":"venue"
},
  "geometry": {"coordinates":[4.4008579254,50.8390960693],"type":"Point"}
}