{
  "type": "Feature",
  "properties": {
    "iso:country":"BE",
    "sg:address":"Hoeledensebaan 224",
    "sg:city":"Kortenaken",
    "sg:classifiers":[
        {
            "category":"Shopping",
            "subcategory":"Crafts & Fabrics",
            "type":"Retail Goods"
        }
    ],
    "sg:phone":"+32 16 77 04 90",
    "sg:postcode":"3471",
    "sg:province":"Vlaams-Brabant",
    "sg:tags":[
        "textile",
        "linen",
        "clothing"
    ],
    "wof:name":"Hoebrechts Confectieatelier Bvba",
    "wof:placetype":"venue"
},
  "geometry": {"coordinates":[5.0151758194,50.883605957],"type":"Point"}
}