{
  "type": "Feature",
  "properties": {
    "iso:country":"BE",
    "sg:address":"Rue Albert Ier 108",
    "sg:city":"Mettet",
    "sg:orig_category":"R\u00e9parations and entretien de motos. Motos. V\u00e9los. Entretien and r\u00e9parations de voitures",
    "sg:phone":"+32 71 72 70 22",
    "sg:postcode":"5640",
    "sg:province":"Namur",
    "wof:name":"Garage Verkempinck",
    "wof:placetype":"venue"
},
  "geometry": {"coordinates":[4.6561961174,50.3262519836],"type":"Point"}
}