{
  "type": "Feature",
  "properties": {
    "addr:full":"Nijverheidskaai 123 Sint-jans-molenbeek/molenbeek-saint-jean Bruxelles-Capitale 1080",
    "addr:housenumber":"123",
    "addr:postcode":"1080",
    "addr:street":"Nijverheidskaai",
    "iso:country":"BE",
    "sg:address":"Nijverheidskaai 123",
    "sg:city":"Sint-jans-molenbeek/molenbeek-saint-jean",
    "sg:orig_category":"Computers Fab Computers and computerapparatuur Kantoormateriaal Gh",
    "sg:phone":"+32 2 522 00 05",
    "sg:postcode":"1080",
    "sg:province":"Bruxelles-Capitale",
    "wof:name":"Centauri",
    "wof:placetype":"venue"
},
  "geometry": {"coordinates":[4.3262238503,50.8448600769],"type":"Point"}
}