{
  "type": "Feature",
  "properties": {
    "addr:full":"Rue Des D\u00c9port\u00c9s 112 Libin Luxembourg 6890",
    "addr:housenumber":"112",
    "addr:postcode":"6890",
    "addr:street":"Rue Des De\u0301Porte\u0301S",
    "iso:country":"BE",
    "sg:address":"Rue Des D\u00c9port\u00c9s 112",
    "sg:city":"Libin",
    "sg:orig_category":"Eleveurs de bovins",
    "sg:phone":"+32 61 22 39 72",
    "sg:postcode":"6890",
    "sg:province":"Luxembourg",
    "wof:name":"Maurice Otjacques",
    "wof:placetype":"venue"
},
  "geometry": {"coordinates":[5.2777218819,49.9232521057],"type":"Point"}
}