{
  "type": "Feature",
  "properties": {
    "addr:full":"Rue De Nivelles 34 Rixensart Brabant Wallon 1330",
    "addr:housenumber":"34",
    "addr:postcode":"1330",
    "addr:street":"Rue De Nivelles;Wallon",
    "iso:country":"BE",
    "sg:address":"Rue De Nivelles 34",
    "sg:city":"Rixensart",
    "sg:classifiers":[
        {
            "category":"Professional",
            "subcategory":"Computer Services",
            "type":"Services"
        }
    ],
    "sg:phone":"+32 2 653 80 83",
    "sg:postcode":"1330",
    "sg:province":"Brabant Wallon",
    "sg:tags":[
        "-",
        "processing",
        "data",
        "software"
    ],
    "wof:name":"Perspectives Sprl",
    "wof:placetype":"venue"
},
  "geometry": {"coordinates":[4.5183157921,50.7021064758],"type":"Point"}
}