{
  "type": "Feature",
  "properties": {
    "iso:country":"BE",
    "sg:address":"Steenweg Op Sevendonk 60",
    "sg:city":"Oud-turnhout",
    "sg:classifiers":[
        {
            "category":"Home & Garden",
            "subcategory":"Household Appliances",
            "type":"Retail Goods"
        }
    ],
    "sg:phone":"+32 14 45 48 12",
    "sg:postcode":"2360",
    "sg:province":"Antwerpen",
    "sg:tags":[
        "repair",
        "mainten",
        "-",
        "electric"
    ],
    "wof:name":"De Pauw D",
    "wof:placetype":"venue"
},
  "geometry": {"coordinates":[4.9798297882,51.315448761],"type":"Point"}
}