{
  "type": "Feature",
  "properties": {
    "iso:country":"BE",
    "sg:address":"Kerkstraat 69",
    "sg:city":"Lommel",
    "sg:orig_category":"Pain, p\u00e2tisseries and confiseries",
    "sg:phone":"+32 11 54 01 16",
    "sg:postcode":"3920",
    "sg:province":"Limburg",
    "wof:name":"Alfred Sevens",
    "wof:placetype":"venue"
},
  "geometry": {"coordinates":[5.3133559227,51.22889328],"type":"Point"}
}