{
  "type": "Feature",
  "properties": {
    "addr:full":"Beversesteenweg 447 Roeselare West-Vlaanderen 8800",
    "addr:housenumber":"447",
    "addr:postcode":"8800",
    "addr:street":"Beversesteenweg",
    "iso:country":"BE",
    "sg:address":"Beversesteenweg 447",
    "sg:city":"Roeselare",
    "sg:orig_category":"Banques and organismes de cr\u00e9dit",
    "sg:phone":"+32 51 20 12 47",
    "sg:postcode":"8800",
    "sg:province":"West-Vlaanderen",
    "wof:name":"Kbc",
    "wof:placetype":"venue"
},
  "geometry": {"coordinates":[3.1597049236,50.9739112854],"type":"Point"}
}