{
  "type": "Feature",
  "properties": {
    "addr:full":"Rue Du Pr\u00e9sident 36 Namur Namur 5000",
    "addr:housenumber":"36",
    "addr:postcode":"5000",
    "addr:street":"Rue Du Pre\u0301Sident",
    "iso:country":"BE",
    "sg:address":"Rue Du Pr\u00e9sident 36",
    "sg:city":"Namur",
    "sg:classifiers":[
        {
            "category":"Professional",
            "type":"Services"
        }
    ],
    "sg:phone":"+32 81 22 69 15",
    "sg:postcode":"5000",
    "sg:province":"Namur",
    "sg:tags":[
        "entertainer"
    ],
    "wof:name":"Atelier Quinot",
    "wof:placetype":"venue"
},
  "geometry": {"coordinates":[4.8635292053,50.4622573853],"type":"Point"}
}