{
  "type": "Feature",
  "properties": {
    "iso:country":"BE",
    "sg:address":"Rue Du Septi\u00e8me R. I. C. 311",
    "sg:city":"Tintigny (bellefontaine)",
    "sg:classifiers":[
        {
            "category":"Building & Trades",
            "subcategory":"Landscaping Services",
            "type":"Services"
        }
    ],
    "sg:phone":"+32 63 44 45 13",
    "sg:postcode":"6730",
    "sg:province":"Luxembourg",
    "sg:tags":[
        "access",
        "pond",
        "laying-out",
        "-"
    ],
    "wof:name":"Arnould Dany & Fils",
    "wof:placetype":"venue"
},
  "geometry": {"coordinates":[5.4925441742,49.6717185974],"type":"Point"}
}