{
  "type": "Feature",
  "properties": {
    "iso:country":"BE",
    "sg:address":"Goswin De Stassartstraat 17",
    "sg:city":"Mechelen",
    "sg:classifiers":[
        {
            "category":"Health Services",
            "subcategory":"Doctor",
            "type":"Services"
        }
    ],
    "sg:phone":"+32 15 20 06 50",
    "sg:postcode":"2800",
    "sg:province":"Antwerpen",
    "sg:tags":[
        "medicinephysicians",
        "surgeon"
    ],
    "wof:name":"Deluster Rudi",
    "wof:placetype":"venue"
},
  "geometry": {"coordinates":[4.4798159599,51.0310974121],"type":"Point"}
}