{
  "type": "Feature",
  "properties": {
    "iso:country":"BE",
    "sg:address":"Domstraat 22",
    "sg:city":"Sint-pieters-leeuw",
    "sg:classifiers":[
        {
            "category":"Cafe",
            "type":"Food & Drink"
        }
    ],
    "sg:phone":"+32 2 569 32 44",
    "sg:postcode":"1602",
    "sg:province":"Vlaams-Brabant",
    "sg:tags":[
        "caf\u00e9s"
    ],
    "wof:name":"Caf\u00c9 In De Kiek",
    "wof:placetype":"venue"
},
  "geometry": {"coordinates":[4.2496418953,50.808052063],"type":"Point"}
}