{
  "type": "Feature",
  "properties": {
    "addr:full":"Place Des Wallons 10 Li\u00e8ge 1 Li\u00e8ge 4000",
    "addr:housenumber":"10;1",
    "addr:postcode":"4000",
    "addr:street":"Place Des Wallons",
    "iso:country":"BE",
    "sg:address":"Place Des Wallons 10",
    "sg:city":"Li\u00e8ge 1",
    "sg:classifiers":[
        {
            "category":"Personal",
            "subcategory":"Barber",
            "type":"Services"
        }
    ],
    "sg:phone":"+32 4 252 78 51",
    "sg:postcode":"4000",
    "sg:province":"Li\u00e8ge",
    "sg:tags":[
        "gentleman",
        "salon",
        "-",
        "hairdressing"
    ],
    "wof:name":"Fiorino",
    "wof:placetype":"venue"
},
  "geometry": {"coordinates":[5.5595507622,50.6315612793],"type":"Point"}
}