{
  "type": "Feature",
  "properties": {
    "iso:country":"BE",
    "sg:address":"Kleine Nieuwedijkstraat 3",
    "sg:city":"Mechelen",
    "sg:classifiers":[
        {
            "category":"Building & Trades",
            "subcategory":"Landscaping Services",
            "type":"Services"
        }
    ],
    "sg:phone":"+32 15 34 07 93",
    "sg:postcode":"2800",
    "sg:province":"Antwerpen",
    "sg:tags":[
        "gardening",
        "garden",
        "maintenance"
    ],
    "wof:name":"Tuinontwerp Verde",
    "wof:placetype":"venue"
},
  "geometry": {"coordinates":[4.4873280525,51.0361099243],"type":"Point"}
}