{
  "type": "Feature",
  "properties": {
    "iso:country":"BE",
    "sg:address":"Vindictivelaan 23",
    "sg:city":"Oostende",
    "sg:classifiers":[
        {
            "category":"Professional",
            "subcategory":"Computer Services",
            "type":"Services"
        }
    ],
    "sg:phone":"+32 59 29 05 33",
    "sg:postcode":"8400",
    "sg:province":"West-Vlaanderen",
    "sg:tags":[
        "repair",
        "processing",
        "-",
        "maintenance",
        "data"
    ],
    "wof:name":"Chukky Computers",
    "wof:placetype":"venue"
},
  "geometry": {"coordinates":[2.9225459099,51.228515625],"type":"Point"}
}