{
  "type": "Feature",
  "properties": {
    "addr:full":"Manestraat 28 Roeselare West-Vlaanderen 8800",
    "addr:housenumber":"28",
    "addr:postcode":"8800",
    "addr:street":"Manestraat",
    "iso:country":"BE",
    "sg:address":"Manestraat 28",
    "sg:city":"Roeselare",
    "sg:classifiers":[
        {
            "category":"Real Estate",
            "subcategory":"Real Estate Services",
            "type":"Services"
        }
    ],
    "sg:phone":"+32 51 22 79 11",
    "sg:postcode":"8800",
    "sg:province":"West-Vlaanderen",
    "wof:name":"Imtrade Bvba",
    "wof:placetype":"venue"
},
  "geometry": {"coordinates":[3.1224370003,50.9449424744],"type":"Point"}
}