{
  "type": "Feature",
  "properties": {
    "addr:full":"Avenue Des Cerisiers 33 Bruxelles (schaerbeek) Bruxelles-Capitale 1030",
    "addr:housenumber":"33",
    "addr:postcode":"1030",
    "addr:street":"Avenue Des Cerisiers",
    "iso:country":"BE",
    "sg:address":"Avenue Des Cerisiers 33",
    "sg:city":"Bruxelles (schaerbeek)",
    "sg:classifiers":[
        {
            "category":"Home & Garden",
            "subcategory":"Kitchen Supply",
            "type":"Retail Goods"
        }
    ],
    "sg:phone":"+32 2 736 90 94",
    "sg:postcode":"1030",
    "sg:province":"Bruxelles-Capitale",
    "sg:tags":[
        "installation"
    ],
    "wof:name":"American K",
    "wof:placetype":"venue"
},
  "geometry": {"coordinates":[4.4047670364,50.8483734131],"type":"Point"}
}