{
  "type": "Feature",
  "properties": {
    "addr:full":"Tervuursesteenweg 49 Mechelen Antwerpen 2800",
    "addr:housenumber":"49",
    "addr:postcode":"2800",
    "addr:street":"Tervuursesteenweg",
    "iso:country":"BE",
    "sg:address":"Tervuursesteenweg 49",
    "sg:city":"Mechelen",
    "sg:orig_category":"Newspapers, magazines, periodicals - Distribution",
    "sg:phone":"+32 15 41 10 28",
    "sg:postcode":"2800",
    "sg:province":"Antwerpen",
    "wof:name":"Elma",
    "wof:placetype":"venue"
},
  "geometry": {"coordinates":[4.4837350845,51.0123519897],"type":"Point"}
}