{
  "type": "Feature",
  "properties": {
    "addr:full":"Linthoutstraat 5 Merchtem (brussegem) Vlaams-Brabant 1785",
    "addr:housenumber":"5",
    "addr:postcode":"1785",
    "addr:street":"Linthoutstraat",
    "iso:country":"BE",
    "sg:address":"Linthoutstraat 5",
    "sg:city":"Merchtem (brussegem)",
    "sg:classifiers":[
        {
            "category":"Food & Beverages",
            "subcategory":"Liquor & Beverages",
            "type":"Retail Goods"
        }
    ],
    "sg:phone":"+32 2 460 19 45",
    "sg:postcode":"1785",
    "sg:province":"Vlaams-Brabant",
    "sg:tags":[
        "-",
        "spirit",
        "wine"
    ],
    "wof:name":"Vinikus",
    "wof:placetype":"venue"
},
  "geometry": {"coordinates":[4.2765779495,50.958946228],"type":"Point"}
}