{
  "type": "Feature",
  "properties": {
    "addr:full":"Interleuvenlaan 62 Leuven (heverlee) Vlaams-Brabant 3001",
    "addr:housenumber":"62",
    "addr:postcode":"3001",
    "addr:street":"Interleuvenlaan",
    "iso:country":"BE",
    "sg:address":"Interleuvenlaan 62",
    "sg:city":"Leuven (heverlee)",
    "sg:classifiers":[
        {
            "category":"Utilities",
            "subcategory":"Telephone",
            "type":"Services"
        }
    ],
    "sg:phone":"+32 475 74 08 84",
    "sg:postcode":"3001",
    "sg:province":"Vlaams-Brabant",
    "sg:tags":[
        "-",
        "internet"
    ],
    "wof:name":"Articulate Online",
    "wof:placetype":"venue"
},
  "geometry": {"coordinates":[4.7360210419,50.849067688],"type":"Point"}
}