{
  "type": "Feature",
  "properties": {
    "addr:full":"Sint-rochusstraat 37 Halle Vlaams-Brabant 1500",
    "addr:housenumber":"37",
    "addr:postcode":"1500",
    "addr:street":"Sint-Rochusstraat",
    "iso:country":"BE",
    "sg:address":"Sint-rochusstraat 37",
    "sg:city":"Halle",
    "sg:classifiers":[
        {
            "category":"Shopping",
            "subcategory":"Clothing, Apparel, & Fashions",
            "type":"Retail Goods"
        }
    ],
    "sg:phone":"+32 2 356 72 49",
    "sg:postcode":"1500",
    "sg:province":"Vlaams-Brabant",
    "sg:tags":[
        "ondergoed",
        "lingerie"
    ],
    "wof:name":"Orpha Decremer",
    "wof:placetype":"venue"
},
  "geometry": {"coordinates":[4.2399520874,50.7312736511],"type":"Point"}
}