{
  "type": "Feature",
  "properties": {
    "addr:full":"Hendrik Baelskaai 34 Oostende West-Vlaanderen 8400",
    "addr:housenumber":"34",
    "addr:postcode":"8400",
    "iso:country":"BE",
    "sg:address":"Hendrik Baelskaai 34",
    "sg:city":"Oostende",
    "sg:classifiers":[
        {
            "category":"Train Station",
            "subcategory":"Rail",
            "type":"Transportation"
        }
    ],
    "sg:phone":"+32 59 32 00 79",
    "sg:postcode":"8400",
    "sg:province":"West-Vlaanderen",
    "sg:tags":[
        "ship",
        "chandler"
    ],
    "wof:name":"Pintelon Bonded Stores",
    "wof:placetype":"venue"
},
  "geometry": {"coordinates":[2.9366641045,51.2319526672],"type":"Point"}
}