{
  "type": "Feature",
  "properties": {
    "iso:country":"BE",
    "sg:address":"Rue Jules Destr\u00e9e 128",
    "sg:city":"Charleroi (marcinelle)",
    "sg:classifiers":[
        {
            "category":"Parking",
            "subcategory":"Bicycle",
            "type":"Transportation"
        }
    ],
    "sg:phone":"+32 71 36 30 53",
    "sg:postcode":"6001",
    "sg:province":"Hainaut",
    "sg:tags":[
        "chiropodist"
    ],
    "wof:name":"Meert M",
    "wof:placetype":"venue"
},
  "geometry": {"coordinates":[4.4543781281,50.392993927],"type":"Point"}
}