{
  "type": "Feature",
  "properties": {
    "addr:full":"Grote Zavel 4 Brussel/bruxelles Bruxelles-Capitale 1000",
    "addr:housenumber":"4",
    "addr:postcode":"1000",
    "addr:street":"Grote Zavel;/",
    "iso:country":"BE",
    "sg:address":"Grote Zavel 4",
    "sg:city":"Brussel/bruxelles",
    "sg:orig_category":"Dameskledingzaken Herenkledingzaken",
    "sg:phone":"+32 2 512 23 67",
    "sg:postcode":"1000",
    "sg:province":"Bruxelles-Capitale",
    "wof:name":"Deman",
    "wof:placetype":"venue"
},
  "geometry": {"coordinates":[4.3544101715,50.8415336609],"type":"Point"}
}