{
  "type": "Feature",
  "properties": {
    "iso:country":"BE",
    "sg:address":"Stationsstraat 12",
    "sg:city":"Stekene",
    "sg:classifiers":[
        {
            "category":"Restaurant",
            "type":"Food & Drink"
        }
    ],
    "sg:phone":"+32 3 789 08 84",
    "sg:postcode":"9190",
    "sg:province":"Oost-Vlaanderen",
    "wof:name":"Hof Van Eden",
    "wof:placetype":"venue"
},
  "geometry": {"coordinates":[4.0752840042,51.2066688538],"type":"Point"}
}