{
  "type": "Feature",
  "properties": {
    "addr:full":"Schapenbaan 42 Ternat Vlaams-Brabant 1741",
    "addr:housenumber":"42",
    "addr:postcode":"1741",
    "addr:street":"Schapenbaan",
    "iso:country":"BE",
    "sg:address":"Schapenbaan 42",
    "sg:city":"Ternat",
    "sg:orig_category":"Installation de menuiserie en bois and plastique",
    "sg:phone":"+32 2 582 61 01",
    "sg:postcode":"1741",
    "sg:province":"Vlaams-Brabant",
    "wof:name":"Martin Van Beneden",
    "wof:placetype":"venue"
},
  "geometry": {"coordinates":[4.1772542,50.8489227295],"type":"Point"}
}