{
  "type": "Feature",
  "properties": {
    "iso:country":"BE",
    "sg:address":"Boskant 22a",
    "sg:city":"Meise (wolvertem)",
    "sg:orig_category":"Non-Classified Establishments",
    "sg:phone":"+32 52 30 94 02",
    "sg:postcode":"1861",
    "sg:province":"Vlaams-Brabant",
    "wof:name":"Rik Segers Bvba",
    "wof:placetype":"venue"
},
  "geometry": {"coordinates":[4.3190040588,50.989025116],"type":"Point"}
}