{
  "type": "Feature",
  "properties": {
    "addr:full":"Rue Du Berceau 42 Peruwelz Hainaut 7600",
    "addr:housenumber":"42",
    "addr:postcode":"7600",
    "addr:street":"Rue Du Berceau;Hainaut",
    "iso:country":"BE",
    "sg:address":"Rue Du Berceau 42",
    "sg:city":"Peruwelz",
    "sg:classifiers":[
        {
            "category":"Professional",
            "subcategory":"Accounting & Tax Preparation",
            "type":"Services"
        }
    ],
    "sg:phone":"+32 69 77 17 15",
    "sg:postcode":"7600",
    "sg:province":"Hainaut",
    "sg:tags":[
        "accountant"
    ],
    "wof:name":"Jean Wattecamps",
    "wof:placetype":"venue"
},
  "geometry": {"coordinates":[3.5912110806,50.5031356812],"type":"Point"}
}