{
  "type": "Feature",
  "properties": {
    "iso:country":"BE",
    "sg:address":"65",
    "sg:city":"Zwaarveld 9220 Hamme",
    "sg:classifiers":[
        {
            "category":"Manufacturing",
            "subcategory":"Rubber & Plastics",
            "type":"Manufacturing & Wholesale Goods"
        }
    ],
    "sg:phone":"+32 52 47 76 24",
    "sg:postcode":"65",
    "wof:name":"Inno-plast Nv",
    "wof:placetype":"venue"
},
  "geometry": {"coordinates":[4.1366839409,51.0759086609],"type":"Point"}
}