{
  "type": "Feature",
  "properties": {
    "addr:full":"Langestraat 24 Gooik Vlaams-Brabant 1755",
    "addr:housenumber":"24",
    "addr:postcode":"1755",
    "addr:street":"Langestraat",
    "iso:country":"BE",
    "sg:address":"Langestraat 24",
    "sg:city":"Gooik",
    "sg:orig_category":"Jardinage",
    "sg:phone":"+32 54 56 72 62",
    "sg:postcode":"1755",
    "sg:province":"Vlaams-Brabant",
    "wof:name":"Avau Boudewijn",
    "wof:placetype":"venue"
},
  "geometry": {"coordinates":[4.1051859856,50.7586936951],"type":"Point"}
}