{
  "type": "Feature",
  "properties": {
    "iso:country":"BE",
    "sg:address":"Abdijstraat 29",
    "sg:city":"Antwerpen",
    "sg:classifiers":[
        {
            "category":"Shopping",
            "subcategory":"Gifts & Souvenirs",
            "type":"Retail Goods"
        }
    ],
    "sg:phone":"+32 3 257 34 01",
    "sg:postcode":"2020",
    "sg:province":"Antwerpen",
    "sg:tags":[
        "-"
    ],
    "wof:name":"Super Stunt Shop",
    "wof:placetype":"venue"
},
  "geometry": {"coordinates":[4.3797330856,51.189907074],"type":"Point"}
}