{
  "type": "Feature",
  "properties": {
    "addr:full":"Place De L'ondine 12 Louvain Brabant Wallon 1348",
    "addr:housenumber":"12",
    "addr:postcode":"1348",
    "addr:street":"Place De L'Ondine",
    "iso:country":"BE",
    "sg:address":"Place De L'ondine 12",
    "sg:city":"Louvain",
    "sg:orig_category":"Blanchisseries and teintureries",
    "sg:phone":"+32 81 61 29 62",
    "sg:postcode":"1348",
    "sg:province":"Brabant Wallon",
    "wof:name":"Lavoir De L'ondine",
    "wof:placetype":"venue"
},
  "geometry": {"coordinates":[4.703690052,50.8793487549],"type":"Point"}
}