{
  "type": "Feature",
  "properties": {
    "addr:full":"Gaversesteenweg 224b1 Deinze Oost-Vlaanderen 9800",
    "addr:housenumber":"224b1",
    "addr:postcode":"9800",
    "addr:street":"Gaversesteenweg",
    "iso:country":"BE",
    "sg:address":"Gaversesteenweg 224b1",
    "sg:city":"Deinze",
    "sg:orig_category":"Bloemen and planten",
    "sg:phone":"+32 9 386 19 65",
    "sg:postcode":"9800",
    "sg:province":"Oost-Vlaanderen",
    "wof:name":"Huis Van Kerrebroeck",
    "wof:placetype":"venue"
},
  "geometry": {"coordinates":[3.530174017,50.9863166809],"type":"Point"}
}