{
  "type": "Feature",
  "properties": {
    "addr:full":"Brugsevaart 80 Nieuwpoort West-Vlaanderen 8620",
    "addr:housenumber":"80",
    "addr:postcode":"8620",
    "addr:street":"Brugsevaart",
    "iso:country":"BE",
    "sg:address":"Brugsevaart 80",
    "sg:city":"Nieuwpoort",
    "sg:orig_category":"Herstellingen and onderhoud van auto's Onderdelen and accessoires voor auto's",
    "sg:phone":"+32 58 23 65 22",
    "sg:postcode":"8620",
    "sg:province":"West-Vlaanderen",
    "wof:name":"Eddy Decan",
    "wof:placetype":"venue"
},
  "geometry": {"coordinates":[2.7853078842,51.1445846558],"type":"Point"}
}