{
  "type": "Feature",
  "properties": {
    "addr:full":"Olenseweg 125 Westerlo Antwerpen 2260",
    "addr:housenumber":"125",
    "addr:postcode":"2260",
    "addr:street":"Olenseweg",
    "iso:country":"BE",
    "sg:address":"Olenseweg 125",
    "sg:city":"Westerlo",
    "sg:orig_category":"Slaughter-Houses, Abattoirs",
    "sg:phone":"+32 14 26 46 11",
    "sg:postcode":"2260",
    "sg:province":"Antwerpen",
    "wof:name":"Slachthuis Appels Westerlo Nv",
    "wof:placetype":"venue"
},
  "geometry": {"coordinates":[4.869289875,51.1049690247],"type":"Point"}
}