{
  "type": "Feature",
  "properties": {
    "addr:full":"Place D'herchies 12 Jurbise Hainaut 7050",
    "addr:housenumber":"12",
    "addr:postcode":"7050",
    "addr:street":"Place D'Herchies",
    "iso:country":"BE",
    "sg:address":"Place D'herchies 12",
    "sg:city":"Jurbise",
    "sg:orig_category":"Electrom\u00e9nager, t\u00e9l\u00e9visions and radios. R\u00e9parations d'appareils \u00e9lectrom\u00e9nagers",
    "sg:phone":"+32 65 22 51 32",
    "sg:postcode":"7050",
    "sg:province":"Hainaut",
    "wof:name":"Electro-services",
    "wof:placetype":"venue"
},
  "geometry": {"coordinates":[3.8854579926,50.505317688],"type":"Point"}
}