{
  "type": "Feature",
  "properties": {
    "iso:country":"BE",
    "sg:address":"Schellekensberg 21",
    "sg:city":"Diest",
    "sg:orig_category":"Sportclubs",
    "sg:phone":"+32 13 32 29 40",
    "sg:postcode":"3290",
    "sg:province":"Vlaams-Brabant",
    "wof:name":"W.s.c.'samen Sterk' Diest",
    "wof:placetype":"venue"
},
  "geometry": {"coordinates":[5.1077718735,51.0181541443],"type":"Point"}
}