{
  "type": "Feature",
  "properties": {
    "addr:full":"Rue Potaarde 35 Sint-agatha-berchem Bruxelles-Capitale 1082",
    "addr:housenumber":"35",
    "addr:postcode":"1082",
    "addr:street":"Rue Potaarde",
    "iso:country":"BE",
    "sg:address":"Rue Potaarde 35",
    "sg:city":"Sint-agatha-berchem",
    "sg:orig_category":"Installation \u00e9lectrique r\u00e9sidentielle. Construction de maisons",
    "sg:phone":"+32 2 468 22 94",
    "sg:postcode":"1082",
    "sg:province":"Bruxelles-Capitale",
    "wof:name":"Ruebens Marc",
    "wof:placetype":"venue"
},
  "geometry": {"coordinates":[4.2815151215,50.865814209],"type":"Point"}
}