{
  "type": "Feature",
  "properties": {
    "iso:country":"BE",
    "sg:address":"Vijfstraten 113",
    "sg:city":"Sint-niklaas",
    "sg:orig_category":"Plaatsen van vloer- and muurbekleding Schilders",
    "sg:phone":"+32 3 776 48 67",
    "sg:postcode":"9100",
    "sg:province":"Oost-Vlaanderen",
    "wof:name":"Theo Piessens",
    "wof:placetype":"venue"
},
  "geometry": {"coordinates":[4.1528348923,51.1766967773],"type":"Point"}
}