{
  "type": "Feature",
  "properties": {
    "addr:full":"Rode Beukendreef 12 Sint-martens-latem (deurle) Oost-Vlaanderen 9831",
    "addr:housenumber":"12",
    "addr:postcode":"9831",
    "addr:street":"Rode Beukendreef;Deurle",
    "iso:country":"BE",
    "sg:address":"Rode Beukendreef 12",
    "sg:city":"Sint-martens-latem (deurle)",
    "sg:classifiers":[
        {
            "category":"Building & Trades",
            "subcategory":"Construction",
            "type":"Services"
        }
    ],
    "sg:phone":"+32 9 280 88 22",
    "sg:postcode":"9831",
    "sg:province":"Oost-Vlaanderen",
    "sg:tags":[
        "surveyor",
        "-"
    ],
    "wof:name":"A.v.i.m.",
    "wof:placetype":"venue"
},
  "geometry": {"coordinates":[3.6106660366,51.0096664429],"type":"Point"}
}