{
  "type": "Feature",
  "properties": {
    "iso:country":"BE",
    "sg:address":"Oude Zilverbergstraat 38",
    "sg:city":"Roeselare (rumbeke)",
    "sg:classifiers":[
        {
            "category":"Utilities",
            "subcategory":"Fuel Oil & Lpg",
            "type":"Services"
        }
    ],
    "sg:phone":"+32 51 20 35 17",
    "sg:postcode":"8800",
    "sg:province":"West-Vlaanderen",
    "wof:name":"Vanhecke A",
    "wof:placetype":"venue"
},
  "geometry": {"coordinates":[3.1205589771,50.9216079712],"type":"Point"}
}