{
  "type": "Feature",
  "properties": {
    "addr:full":"Av. De La Rochefoucauld 11 Rixensart Brabant Wallon 1330",
    "addr:housenumber":"11",
    "addr:postcode":"1330",
    "addr:street":"Av. De La Rochefoucauld;Wallon",
    "iso:country":"BE",
    "sg:address":"Av. De La Rochefoucauld 11",
    "sg:city":"Rixensart",
    "sg:classifiers":[
        {
            "category":"Personal",
            "subcategory":"Beauty Salon",
            "type":"Services"
        }
    ],
    "sg:phone":"+32 2 653 81 20",
    "sg:postcode":"1330",
    "sg:province":"Brabant Wallon",
    "sg:tags":[
        "de",
        "coiffure"
    ],
    "wof:name":"S\u00c9verine Careme",
    "wof:placetype":"venue"
},
  "geometry": {"coordinates":[4.533782959,50.717048645],"type":"Point"}
}