{
  "type": "Feature",
  "properties": {
    "addr:full":"Bergstraat 4 Londerzeel Vlaams-Brabant 1840",
    "addr:housenumber":"4",
    "addr:postcode":"1840",
    "addr:street":"Bergstraat",
    "iso:country":"BE",
    "sg:address":"Bergstraat 4",
    "sg:city":"Londerzeel",
    "sg:orig_category":"Epiceries",
    "sg:phone":"+32 52 30 42 86",
    "sg:postcode":"1840",
    "sg:province":"Vlaams-Brabant",
    "wof:name":"Carl Van Doren",
    "wof:placetype":"venue"
},
  "geometry": {"coordinates":[4.323237896,51.0067214966],"type":"Point"}
}