{
  "type": "Feature",
  "properties": {
    "addr:full":"Kraaienheuvel 13 Kapellen Antwerpen 2950",
    "addr:housenumber":"13",
    "addr:postcode":"2950",
    "addr:street":"Kraaienheuvel",
    "iso:country":"BE",
    "sg:address":"Kraaienheuvel 13",
    "sg:city":"Kapellen",
    "sg:orig_category":"Immobili\u00ebnkantoren",
    "sg:phone":"+32 3 665 42 39",
    "sg:postcode":"2950",
    "sg:province":"Antwerpen",
    "wof:name":"Living Abroad",
    "wof:placetype":"venue"
},
  "geometry": {"coordinates":[4.4498000145,51.3069534302],"type":"Point"}
}