{
  "type": "Feature",
  "properties": {
    "iso:country":"BE",
    "sg:address":"Avenue Du Monument 5",
    "sg:city":"Marche-en-famenne",
    "sg:classifiers":[
        {
            "category":"Real Estate",
            "subcategory":"Real Estate Services",
            "type":"Services"
        }
    ],
    "sg:phone":"+32 84 31 30 00",
    "sg:postcode":"6900",
    "sg:province":"Luxembourg",
    "wof:name":"Select'home Sa",
    "wof:placetype":"venue"
},
  "geometry": {"coordinates":[5.342936039,50.2249488831],"type":"Point"}
}