{
  "type": "Feature",
  "properties": {
    "addr:full":"Hoogpoort 41 Gent Oost-Vlaanderen 9000",
    "addr:housenumber":"41",
    "addr:postcode":"9000",
    "addr:street":"Hoogpoort;Oost-Vlaanderen",
    "iso:country":"BE",
    "sg:address":"Hoogpoort 41",
    "sg:city":"Gent",
    "sg:classifiers":[
        {
            "category":"Cafe",
            "type":"Food & Drink"
        }
    ],
    "sg:phone":"+32 9 233 71 70",
    "sg:postcode":"9000",
    "sg:province":"Oost-Vlaanderen",
    "sg:tags":[
        "caf\u00e9s"
    ],
    "wof:name":"Sous-sol",
    "wof:placetype":"venue"
},
  "geometry": {"coordinates":[3.7244720459,51.0549850464],"type":"Point"}
}