{
  "type": "Feature",
  "properties": {
    "addr:full":"Emile Verhaerenlaan 16 Knokke-heist West-Vlaanderen 8300",
    "addr:housenumber":"16",
    "addr:postcode":"8300",
    "addr:street":"Emile Verhaerenlaan",
    "iso:country":"BE",
    "sg:address":"Emile Verhaerenlaan 16",
    "sg:city":"Knokke-heist",
    "sg:orig_category":"Pain, p\u00e2tisseries and confiseries",
    "sg:phone":"+32 50 60 23 95",
    "sg:postcode":"8300",
    "sg:province":"West-Vlaanderen",
    "wof:name":"Bakkerij Bl\u00c9 D'or",
    "wof:placetype":"venue"
},
  "geometry": {"coordinates":[3.287694931,51.3467254639],"type":"Point"}
}