{
  "type": "Feature",
  "properties": {
    "addr:full":"Neringenweg 4 Leuven Vlaams-Brabant 3001",
    "addr:housenumber":"4",
    "addr:postcode":"3001",
    "addr:street":"Neringenweg",
    "iso:country":"BE",
    "sg:address":"Neringenweg 4",
    "sg:city":"Leuven",
    "sg:classifiers":[
        {
            "category":"Insurance",
            "subcategory":"Insurance Agent",
            "type":"Services"
        }
    ],
    "sg:phone":"+32 16 40 02 59",
    "sg:postcode":"3001",
    "sg:province":"Vlaams-Brabant",
    "sg:tags":[
        "verzekeringsmakelaars",
        "expert"
    ],
    "wof:name":"M. Delcon",
    "wof:placetype":"venue"
},
  "geometry": {"coordinates":[4.714509964,50.8461112976],"type":"Point"}
}