{
  "type": "Feature",
  "properties": {
    "iso:country":"BE",
    "sg:address":"Kwadepoelstraat 19be",
    "sg:city":"Zwevegem",
    "sg:orig_category":"Experts-comptables",
    "sg:phone":"+32 56 75 66 00",
    "sg:postcode":"8550",
    "sg:province":"West-Vlaanderen",
    "wof:name":"Marc Debrouwere",
    "wof:placetype":"venue"
},
  "geometry": {"coordinates":[3.3291831017,50.8108253479],"type":"Point"}
}