{
  "type": "Feature",
  "properties": {
    "addr:full":"Blauwstraat 22-24 Boom Antwerpen 2850",
    "addr:housenumber":"22-24",
    "addr:postcode":"2850",
    "addr:street":"Blauwstraat",
    "iso:country":"BE",
    "sg:address":"Blauwstraat 22-24",
    "sg:city":"Boom",
    "sg:classifiers":[
        {
            "category":"Shopping",
            "subcategory":"Shoes",
            "type":"Retail Goods"
        }
    ],
    "sg:phone":"+32 3 843 26 00",
    "sg:postcode":"2850",
    "sg:province":"Antwerpen",
    "sg:tags":[
        "slipper",
        "-"
    ],
    "wof:name":"Perron 1 Bvba",
    "wof:placetype":"venue"
},
  "geometry": {"coordinates":[4.3671178818,51.0862312317],"type":"Point"}
}