{
  "type": "Feature",
  "properties": {
    "iso:country":"BE",
    "sg:address":"Turnhoutsebaan 168",
    "sg:city":"Schilde",
    "sg:orig_category":"Sportclubs",
    "sg:phone":"+32 3 393 31 11",
    "sg:postcode":"2970",
    "sg:province":"Antwerpen",
    "wof:name":"Petanque Ons Tijdverdrijf",
    "wof:placetype":"venue"
},
  "geometry": {"coordinates":[4.575065136,51.2376289368],"type":"Point"}
}