{
  "type": "Feature",
  "properties": {
    "iso:country":"BE",
    "sg:address":"Spanjestraat 5-7",
    "sg:city":"Roeselare",
    "sg:classifiers":[
        {
            "category":"Restaurant",
            "type":"Food & Drink"
        }
    ],
    "sg:phone":"+32 51 20 19 15",
    "sg:postcode":"8800",
    "sg:province":"West-Vlaanderen",
    "sg:tags":[
        "organisatie",
        "feesten",
        "van",
        "catering"
    ],
    "wof:name":"Salon Lybeer",
    "wof:placetype":"venue"
},
  "geometry": {"coordinates":[3.1321480274,50.9469490051],"type":"Point"}
}