{
  "type": "Feature",
  "properties": {
    "iso:country":"BE",
    "sg:address":"Vogelhoekstraat 55",
    "sg:city":"Gent (gentbrugge)",
    "sg:classifiers":[
        {
            "category":"Health Services",
            "subcategory":"Dentist",
            "type":"Services"
        }
    ],
    "sg:phone":"+32 9 230 10 93",
    "sg:postcode":"9050",
    "sg:province":"Oost-Vlaanderen",
    "wof:name":"Vandenoostende Eric",
    "wof:placetype":"venue"
},
  "geometry": {"coordinates":[3.7675011158,51.0258407593],"type":"Point"}
}