{
  "type": "Feature",
  "properties": {
    "iso:country":"BE",
    "sg:address":"Goochelaarstraat 26",
    "sg:city":"Sint-laureins",
    "sg:orig_category":"Rundveehouders Varkenskwekers",
    "sg:phone":"+32 9 379 87 00",
    "sg:postcode":"9980",
    "sg:province":"Oost-Vlaanderen",
    "wof:name":"Wilfried Boelens",
    "wof:placetype":"venue"
},
  "geometry": {"coordinates":[3.574021101,51.2380981445],"type":"Point"}
}