{
  "type": "Feature",
  "properties": {
    "iso:country":"BE",
    "sg:address":"Stoubach 2a",
    "sg:city":"Burg-reuland/burg-reuland",
    "sg:classifiers":[
        {
            "category":"Travel",
            "subcategory":"Hotels & Motels",
            "type":"Entertainment"
        }
    ],
    "sg:phone":"+32 80 32 94 31",
    "sg:postcode":"4790",
    "sg:province":"Li\u00e8ge",
    "wof:name":"Pension Hubertus",
    "wof:placetype":"venue"
},
  "geometry": {"coordinates":[6.1431598663,50.1748886108],"type":"Point"}
}