{
  "type": "Feature",
  "properties": {
    "addr:full":"Otterstraat 53 Turnhout Antwerpen 2300",
    "addr:housenumber":"53",
    "addr:postcode":"2300",
    "addr:street":"Otterstraat",
    "iso:country":"BE",
    "sg:address":"Otterstraat 53",
    "sg:city":"Turnhout",
    "sg:classifiers":[
        {
            "category":"Home & Garden",
            "subcategory":"Home Furnishings",
            "type":"Retail Goods"
        }
    ],
    "sg:phone":"+32 14 43 69 34",
    "sg:postcode":"2300",
    "sg:province":"Antwerpen",
    "sg:tags":[
        "-",
        "bed",
        "mattress"
    ],
    "wof:name":"D&s Slaapconfort",
    "wof:placetype":"venue"
},
  "geometry": {"coordinates":[4.9526901245,51.3222732544],"type":"Point"}
}