{
  "type": "Feature",
  "properties": {
    "addr:full":"Rue A. Beaupain 18 Jalhay 4885",
    "addr:housenumber":"18",
    "addr:postcode":"4885",
    "addr:street":"Rue A. Beaupain",
    "iso:country":"BE",
    "sg:address":"Rue A. Beaupain 18",
    "sg:city":"Jalhay",
    "sg:orig_category":"M\u00e9decines alternatives",
    "sg:phone":"+32 87 47 45 41",
    "sg:postcode":"4885",
    "wof:name":"Vinciane Drouven",
    "wof:placetype":"venue"
},
  "geometry": {"coordinates":[5.9721798897,50.5571899414],"type":"Point"}
}