{
  "type": "Feature",
  "properties": {
    "iso:country":"BE",
    "sg:address":"Avenue A. Buyl 68",
    "sg:city":"Bruxelles-ixelles",
    "sg:orig_category":"Voedingsspeciaalzaken",
    "sg:phone":"+32 2 647 88 60",
    "sg:postcode":"1050",
    "sg:province":"Bruxelles-Capitale",
    "wof:name":"Shanti \u00c9picerie Naturelle & Restaurant",
    "wof:placetype":"venue"
},
  "geometry": {"coordinates":[4.3667850494,50.8326339722],"type":"Point"}
}