{
  "type": "Feature",
  "properties": {
    "iso:country":"BE",
    "sg:address":"Rue Francourt 55",
    "sg:city":"Jodoigne",
    "sg:orig_category":"Film-, tv- and videoproductie",
    "sg:phone":"+32 10 81 57 88",
    "sg:postcode":"1370",
    "sg:province":"Brabant Wallon",
    "wof:name":"Legendes Productions",
    "wof:placetype":"venue"
},
  "geometry": {"coordinates":[4.8379349709,50.72838974],"type":"Point"}
}