{
  "type": "Feature",
  "properties": {
    "addr:full":"Zwijndrechtsestraat 15-17 Zwijndrecht (burcht) Antwerpen 2070",
    "addr:housenumber":"15-17",
    "addr:postcode":"2070",
    "addr:street":"Zwijndrechtsestraat;Burcht",
    "iso:country":"BE",
    "sg:address":"Zwijndrechtsestraat 15-17",
    "sg:city":"Zwijndrecht (burcht)",
    "sg:classifiers":[
        {
            "category":"Shopping",
            "subcategory":"Crafts & Fabrics",
            "type":"Retail Goods"
        }
    ],
    "sg:phone":"+32 3 252 74 22",
    "sg:postcode":"2070",
    "sg:province":"Antwerpen",
    "sg:tags":[
        "hi-fi",
        "equipment",
        "stereophonic",
        "-"
    ],
    "wof:name":"Van Der Linden M",
    "wof:placetype":"venue"
},
  "geometry": {"coordinates":[4.3476629257,51.2040863037],"type":"Point"}
}