{
  "type": "Feature",
  "properties": {
    "iso:country":"BE",
    "sg:address":"Groenstraat 24",
    "sg:city":"Neerpelt",
    "sg:classifiers":[
        {
            "category":"Shopping",
            "subcategory":"Luggage & Leather Goods",
            "type":"Retail Goods"
        }
    ],
    "sg:phone":"+32 11 66 41 21",
    "sg:postcode":"3910",
    "sg:province":"Limburg",
    "sg:tags":[
        "-"
    ],
    "wof:name":"Piacere",
    "wof:placetype":"venue"
},
  "geometry": {"coordinates":[5.433672905,51.2294921875],"type":"Point"}
}