{
  "type": "Feature",
  "properties": {
    "iso:country":"BE",
    "sg:address":"Binnenweg 9",
    "sg:city":"Duffel",
    "sg:orig_category":"Epiceries",
    "sg:phone":"+32 15 32 13 39",
    "sg:postcode":"2570",
    "sg:province":"Antwerpen",
    "wof:name":"Benny Eyckmans",
    "wof:placetype":"venue"
},
  "geometry": {"coordinates":[4.5141711235,51.0963249207],"type":"Point"}
}