{
  "type": "Feature",
  "properties": {
    "iso:country":"BE",
    "sg:address":"Rue De Mons 100",
    "sg:city":"Beloeil",
    "sg:classifiers":[
        {
            "category":"Farming",
            "subcategory":"Livestock Farm",
            "type":"Manufacturing & Wholesale Goods"
        }
    ],
    "sg:phone":"+32 69 68 95 37",
    "sg:postcode":"7970",
    "sg:province":"Hainaut",
    "sg:tags":[
        "buyer"
    ],
    "wof:name":"Dumont R Sa",
    "wof:placetype":"venue"
},
  "geometry": {"coordinates":[3.7382040024,50.5441055298],"type":"Point"}
}