{
  "type": "Feature",
  "properties": {
    "addr:full":"Papaard 6 Putte Vlaams-Brabant 1650",
    "addr:housenumber":"6",
    "addr:postcode":"1650",
    "addr:street":"Papaard",
    "iso:country":"BE",
    "sg:address":"Papaard 6",
    "sg:city":"Putte",
    "sg:orig_category":"Diverse organisaties and verenigingen",
    "sg:phone":"+32 2 378 28 73",
    "sg:postcode":"1650",
    "sg:province":"Vlaams-Brabant",
    "wof:name":"Imagine",
    "wof:placetype":"venue"
},
  "geometry": {"coordinates":[4.3932499886,51.3596992493],"type":"Point"}
}