{
  "type": "Feature",
  "properties": {
    "iso:country":"BE",
    "sg:address":"Rue Cl\u00c8rue 54",
    "sg:city":"La Roche-en-ardenne",
    "sg:orig_category":"Antiek",
    "sg:phone":"+32 84 41 20 44",
    "sg:postcode":"6980",
    "sg:province":"Luxembourg",
    "wof:name":"Les Curiosit\u00c9s",
    "wof:placetype":"venue"
},
  "geometry": {"coordinates":[5.5773839951,50.181602478],"type":"Point"}
}