{
  "type": "Feature",
  "properties": {
    "addr:full":"Rue De L'etang 8 Sivry-rance Hainaut 6470",
    "addr:housenumber":"8",
    "addr:postcode":"6470",
    "addr:street":"Rue De L'Etang",
    "iso:country":"BE",
    "sg:address":"Rue De L'etang 8",
    "sg:city":"Sivry-rance",
    "sg:classifiers":[
        {
            "category":"Restaurant",
            "type":"Food & Drink"
        }
    ],
    "sg:phone":"+32 60 45 56 42",
    "sg:postcode":"6470",
    "sg:province":"Hainaut",
    "wof:name":"Les Monts Roses",
    "wof:placetype":"venue"
},
  "geometry": {"coordinates":[4.2156701088,50.167930603],"type":"Point"}
}