{
  "type": "Feature",
  "properties": {
    "addr:full":"Copernicusstraat 119 Ukkel/uccle Bruxelles-Capitale 1180",
    "addr:housenumber":"119",
    "addr:postcode":"1180",
    "addr:street":"Copernicusstraat;/",
    "iso:country":"BE",
    "sg:address":"Copernicusstraat 119",
    "sg:city":"Ukkel/uccle",
    "sg:orig_category":"Tuinen",
    "sg:phone":"+32 2 374 36 01",
    "sg:postcode":"1180",
    "sg:province":"Bruxelles-Capitale",
    "wof:name":"M\u00c9tiers D\u00b4arbres",
    "wof:placetype":"venue"
},
  "geometry": {"coordinates":[4.3643651009,50.7957077026],"type":"Point"}
}