{
  "type": "Feature",
  "properties": {
    "iso:country":"BE",
    "sg:address":"Dorpsstraat 75",
    "sg:city":"Herk-de-stad",
    "sg:orig_category":"Artsen and specialisten",
    "sg:phone":"+32 13 44 29 35",
    "sg:postcode":"3540",
    "sg:province":"Limburg",
    "wof:name":"E. Vandersmissen",
    "wof:placetype":"venue"
},
  "geometry": {"coordinates":[5.1368942261,50.9349708557],"type":"Point"}
}