{
  "type": "Feature",
  "properties": {
    "addr:full":"Commissaris Neyskenslaan 7 Diest Vlaams-Brabant 3290",
    "addr:housenumber":"7",
    "addr:postcode":"3290",
    "addr:street":"Commissaris Neyskenslaan",
    "iso:country":"BE",
    "sg:address":"Commissaris Neyskenslaan 7",
    "sg:city":"Diest",
    "sg:classifiers":[
        {
            "category":"Home & Garden",
            "subcategory":"Home Furnishings",
            "type":"Retail Goods"
        }
    ],
    "sg:phone":"+32 13 31 14 53",
    "sg:postcode":"3290",
    "sg:province":"Vlaams-Brabant",
    "sg:tags":[
        "-",
        "furniture"
    ],
    "wof:name":"Meubart Nv",
    "wof:placetype":"venue"
},
  "geometry": {"coordinates":[5.0553388596,50.9795265198],"type":"Point"}
}