{
  "type": "Feature",
  "properties": {
    "iso:country":"BE",
    "sg:address":"Boulevard De La Dodaine 40",
    "sg:city":"Nivelles",
    "sg:orig_category":"Artsen and specialisten",
    "sg:phone":"+32 67 84 07 08",
    "sg:postcode":"1400",
    "sg:province":"Brabant Wallon",
    "wof:name":"Sabine Van Causenbroeck",
    "wof:placetype":"venue"
},
  "geometry": {"coordinates":[4.321639061,50.5941123962],"type":"Point"}
}