{
  "type": "Feature",
  "properties": {
    "addr:full":"Grand Route 13 (nationale 4) Corbais Brabant Wallon 1435",
    "addr:housenumber":"1435",
    "addr:street":"Grand Route 13 Nationale 4 Corbais Brabant Wallon",
    "iso:country":"BE",
    "sg:address":"Grand Route 13 (nationale 4)",
    "sg:city":"Corbais",
    "sg:orig_category":"Animaux domestiques and accessoires",
    "sg:phone":"+32 10 65 67 97",
    "sg:postcode":"1435",
    "sg:province":"Brabant Wallon",
    "wof:name":"Poils & Plumes",
    "wof:placetype":"venue"
},
  "geometry": {"coordinates":[4.644162178,50.6462554932],"type":"Point"}
}