{
  "type": "Feature",
  "properties": {
    "iso:country":"BE",
    "sg:address":"Cornet De Grezstraat 18",
    "sg:city":"Sint-joost-ten-node/saint-josse-ten-noode",
    "sg:classifiers":[
        {
            "category":"Cafe",
            "type":"Food & Drink"
        }
    ],
    "sg:phone":"+32 2 219 50 84",
    "sg:postcode":"1210",
    "sg:province":"Bruxelles-Capitale",
    "sg:tags":[
        "caf\u00e9s"
    ],
    "wof:name":"Zafer",
    "wof:placetype":"venue"
},
  "geometry": {"coordinates":[4.3690948486,50.8571357727],"type":"Point"}
}