{
  "type": "Feature",
  "properties": {
    "iso:country":"BE",
    "sg:address":"Bredabaan 439",
    "sg:city":"Brasschaat",
    "sg:orig_category":"Pain, p\u00e2tisseries and confiseries",
    "sg:phone":"+32 3 651 82 06",
    "sg:postcode":"2930",
    "sg:province":"Antwerpen",
    "wof:name":"Bakkerij Salsmans",
    "wof:placetype":"venue"
},
  "geometry": {"coordinates":[4.4942321777,51.2920417786],"type":"Point"}
}