{
  "type": "Feature",
  "properties": {
    "iso:country":"BE",
    "sg:address":"Rue Saint-hubert 170",
    "sg:city":"Namur",
    "sg:orig_category":"Catering and organisatie van feesten Levering aan huis restaurants",
    "sg:phone":"+32 81 30 59 42",
    "sg:postcode":"5100",
    "sg:province":"Namur",
    "wof:name":"Etienne Bouche",
    "wof:placetype":"venue"
},
  "geometry": {"coordinates":[4.88586092,50.4273071289],"type":"Point"}
}