{
  "type": "Feature",
  "properties": {
    "iso:country":"BE",
    "sg:address":"Zonnestraat 13",
    "sg:city":"Aalst",
    "sg:orig_category":"Juwelen and horloges",
    "sg:phone":"+32 53 78 55 67",
    "sg:postcode":"9300",
    "sg:province":"Oost-Vlaanderen",
    "wof:name":"Matthieu",
    "wof:placetype":"venue"
},
  "geometry": {"coordinates":[4.0391259193,50.9348335266],"type":"Point"}
}