{
  "type": "Feature",
  "properties": {
    "addr:full":"Rue Pont \u00e0 Migneloux 35 Charleroi (gosselies) Hainaut 6041",
    "addr:housenumber":"35",
    "addr:postcode":"6041",
    "addr:street":"Rue Pont A\u0300 Migneloux",
    "iso:country":"BE",
    "sg:address":"Rue Pont \u00e0 Migneloux 35",
    "sg:city":"Charleroi (gosselies)",
    "sg:classifiers":[
        {
            "category":"Wholesale",
            "subcategory":"Fruits & Vegetables",
            "type":"Manufacturing & Wholesale Goods"
        }
    ],
    "sg:phone":"+32 71 85 15 47",
    "sg:postcode":"6041",
    "sg:province":"Hainaut",
    "sg:tags":[
        "whol",
        "-"
    ],
    "wof:name":"Sabbe Sa",
    "wof:placetype":"venue"
},
  "geometry": {"coordinates":[4.4314317703,50.4685935974],"type":"Point"}
}