{
  "type": "Feature",
  "properties": {
    "addr:full":"Antwerpsesteenweg 505 Gent Oost-Vlaanderen 9040",
    "addr:housenumber":"505",
    "addr:postcode":"9040",
    "addr:street":"Antwerpsesteenweg;Oost-Vlaanderen",
    "iso:country":"BE",
    "sg:address":"Antwerpsesteenweg 505",
    "sg:city":"Gent",
    "sg:orig_category":"Pain, p\u00e2tisseries and confiseries",
    "sg:phone":"+32 9 229 11 06",
    "sg:postcode":"9040",
    "sg:province":"Oost-Vlaanderen",
    "wof:name":"Bakkerij Gunter",
    "wof:placetype":"venue"
},
  "geometry": {"coordinates":[3.7590448856,51.0670890808],"type":"Point"}
}