{
  "type": "Feature",
  "properties": {
    "iso:country":"BE",
    "sg:address":"R Wiertz 60a",
    "sg:city":"Bruxelles",
    "sg:classifiers":[
        {
            "category":"Banks & Credit Unions",
            "subcategory":"Investment Brokerage",
            "type":"Services"
        }
    ],
    "sg:phone":"+32 2 284 20 05",
    "sg:postcode":"1047",
    "sg:tags":[
        "development",
        "economic",
        "institution"
    ],
    "wof:name":"Parlement Europ\u00e9en",
    "wof:placetype":"venue"
},
  "geometry": {"coordinates":[4.3750600815,50.8380813599],"type":"Point"}
}