{
  "type": "Feature",
  "properties": {
    "addr:full":"Rue Du Tr\u00f4ne 108 Bruxelles (ixelles) Bruxelles-Capitale 1050",
    "addr:housenumber":"108",
    "addr:postcode":"1050",
    "addr:street":"Rue Du Tro\u0302Ne",
    "iso:country":"BE",
    "sg:address":"Rue Du Tr\u00f4ne 108",
    "sg:city":"Bruxelles (ixelles)",
    "sg:classifiers":[
        {
            "category":"Organizations",
            "subcategory":"Community Association",
            "type":"Services"
        }
    ],
    "sg:phone":"+32 2 227 08 40",
    "sg:postcode":"1050",
    "sg:province":"Bruxelles-Capitale",
    "sg:tags":[
        "cultural"
    ],
    "wof:name":"British Council (the)",
    "wof:placetype":"venue"
},
  "geometry": {"coordinates":[4.3695778847,50.8371696472],"type":"Point"}
}