{
  "type": "Feature",
  "properties": {
    "iso:country":"BE",
    "sg:address":"Grand\u00b4rue 143",
    "sg:city":"Charleroi",
    "sg:orig_category":"Textiel",
    "sg:phone":"+32 71 42 34 46",
    "sg:postcode":"6000",
    "sg:province":"Hainaut",
    "wof:name":"Maison Bath & Bubbles",
    "wof:placetype":"venue"
},
  "geometry": {"coordinates":[4.4573750496,50.4203147888],"type":"Point"}
}