{
  "type": "Feature",
  "properties": {
    "addr:full":"Berchemstraat 102 Kluisbergen Oost-Vlaanderen 9690",
    "addr:housenumber":"102",
    "addr:postcode":"9690",
    "addr:street":"Berchemstraat",
    "iso:country":"BE",
    "sg:address":"Berchemstraat 102",
    "sg:city":"Kluisbergen",
    "sg:orig_category":"Enseignement artistique",
    "sg:phone":"+32 55 38 60 65",
    "sg:postcode":"9690",
    "sg:province":"Oost-Vlaanderen",
    "wof:name":"Muziek- & Tekenacademie",
    "wof:placetype":"venue"
},
  "geometry": {"coordinates":[3.5189189911,50.7936935425],"type":"Point"}
}