{
  "type": "Feature",
  "properties": {
    "addr:full":"Geluwestraat 9 Wervik West-Vlaanderen 8940",
    "addr:housenumber":"9",
    "addr:postcode":"8940",
    "addr:street":"Geluwestraat",
    "iso:country":"BE",
    "sg:address":"Geluwestraat 9",
    "sg:city":"Wervik",
    "sg:orig_category":"Supermarch\u00e9s",
    "sg:phone":"+32 56 31 35 30",
    "sg:postcode":"8940",
    "sg:province":"West-Vlaanderen",
    "wof:name":"Battard",
    "wof:placetype":"venue"
},
  "geometry": {"coordinates":[3.0450150967,50.7842674255],"type":"Point"}
}