{
  "type": "Feature",
  "properties": {
    "iso:country":"BE",
    "sg:address":"Rue Laurent-delvaux 38",
    "sg:city":"Nivelles",
    "sg:orig_category":"M\u00e9decins and sp\u00e9cialistes",
    "sg:phone":"+32 67 21 20 44",
    "sg:postcode":"1400",
    "sg:province":"Brabant Wallon",
    "wof:name":"Bernard Van Durme",
    "wof:placetype":"venue"
},
  "geometry": {"coordinates":[4.3287339211,50.6014709473],"type":"Point"}
}