{
  "type": "Feature",
  "properties": {
    "iso:country":"BE",
    "sg:address":"Rue Du Coll\u00e8ge 1",
    "sg:city":"Eghez\u00e9e",
    "sg:classifiers":[
        {
            "category":"Health Services",
            "subcategory":"Doctor",
            "type":"Services"
        }
    ],
    "sg:phone":"+32 81 81 33 91",
    "sg:postcode":"5310",
    "sg:province":"Namur",
    "sg:tags":[
        "medicinephysicians",
        "surgeon"
    ],
    "wof:name":"Blouard Philippe",
    "wof:placetype":"venue"
},
  "geometry": {"coordinates":[4.9096999168,50.5939216614],"type":"Point"}
}