{
  "type": "Feature",
  "properties": {
    "iso:country":"BE",
    "sg:address":"Rue Grande Chenevi\u00c8re 49",
    "sg:city":"Charleroi",
    "sg:orig_category":"Antiek",
    "sg:phone":"+32 71 36 74 35",
    "sg:postcode":"6001",
    "sg:province":"Hainaut",
    "wof:name":"Dominique Bodart",
    "wof:placetype":"venue"
},
  "geometry": {"coordinates":[4.4437150955,50.390411377],"type":"Point"}
}