{
  "type": "Feature",
  "properties": {
    "addr:full":"Nieuwbrugstraat 9 Aalst Oost-Vlaanderen 9300",
    "addr:housenumber":"9",
    "addr:postcode":"9300",
    "addr:street":"Nieuwbrugstraat",
    "iso:country":"BE",
    "sg:address":"Nieuwbrugstraat 9",
    "sg:city":"Aalst",
    "sg:classifiers":[
        {
            "category":"Fast Food",
            "type":"Food & Drink"
        }
    ],
    "sg:phone":"+32 53 70 60 70",
    "sg:postcode":"9300",
    "sg:province":"Oost-Vlaanderen",
    "sg:tags":[
        "meeneem",
        "restaurant"
    ],
    "wof:name":"Tupper-friet",
    "wof:placetype":"venue"
},
  "geometry": {"coordinates":[4.0402550697,50.945854187],"type":"Point"}
}