{
  "type": "Feature",
  "properties": {
    "addr:full":"Rue P\u00e9trias 142 Ham-sur-heure-nalinnes (nalinnes) Hainaut 6120",
    "addr:housenumber":"142",
    "addr:postcode":"6120",
    "addr:street":"Rue Pe\u0301Trias;Hainaut",
    "iso:country":"BE",
    "sg:address":"Rue P\u00e9trias 142",
    "sg:city":"Ham-sur-heure-nalinnes (nalinnes)",
    "sg:classifiers":[
        {
            "category":"Building & Trades",
            "subcategory":"Construction",
            "type":"Services"
        }
    ],
    "sg:phone":"+32 71 21 91 57",
    "sg:postcode":"6120",
    "sg:province":"Hainaut",
    "sg:tags":[
        "installation",
        "-",
        "central",
        "heating"
    ],
    "wof:name":"Marlaire P (ets)",
    "wof:placetype":"venue"
},
  "geometry": {"coordinates":[4.4403538704,50.3441162109],"type":"Point"}
}