{
  "type": "Feature",
  "properties": {
    "addr:full":"Rue De L'escadron 8ba Etterbeek Bruxelles-Capitale 1040",
    "addr:postcode":"1040",
    "addr:street":"Rue De L'Escadron 8Ba",
    "iso:country":"BE",
    "sg:address":"Rue De L'escadron 8ba",
    "sg:city":"Etterbeek",
    "sg:orig_category":"Banques and organismes de cr\u00e9dit",
    "sg:phone":"+32 2 733 46 20",
    "sg:postcode":"1040",
    "sg:province":"Bruxelles-Capitale",
    "wof:name":"Dexia",
    "wof:placetype":"venue"
},
  "geometry": {"coordinates":[4.4039292336,50.8320045471],"type":"Point"}
}