{
  "type": "Feature",
  "properties": {
    "iso:country":"BE",
    "sg:address":"Steenweg 4",
    "sg:city":"Opwijk",
    "sg:classifiers":[
        {
            "category":"Food & Beverages",
            "subcategory":"Fruits & Vegetables",
            "type":"Retail Goods"
        }
    ],
    "sg:phone":"+32 52 35 55 19",
    "sg:postcode":"1745",
    "sg:province":"Vlaams-Brabant",
    "sg:tags":[
        "groenten"
    ],
    "wof:name":"Kris",
    "wof:placetype":"venue"
},
  "geometry": {"coordinates":[4.1738810539,50.9390907288],"type":"Point"}
}