{
  "type": "Feature",
  "properties": {
    "iso:country":"BE",
    "sg:address":"Village 29",
    "sg:city":"Olne",
    "sg:orig_category":"Enseignement maternel and primaire",
    "sg:phone":"+32 87 26 88 60",
    "sg:postcode":"4877",
    "sg:province":"Li\u00e8ge",
    "wof:name":"E.f.l. St.louis",
    "wof:placetype":"venue"
},
  "geometry": {"coordinates":[5.7469301224,50.5904426575],"type":"Point"}
}