{
  "type": "Feature",
  "properties": {
    "iso:country":"BE",
    "sg:address":"Rue Kelle 110",
    "sg:city":"Sint-pieters-woluwe/woluwe-saint-pierre",
    "sg:classifiers":[
        {
            "category":"Personal",
            "subcategory":"Beauty Salon",
            "type":"Services"
        }
    ],
    "sg:phone":"+32 2 762 75 89",
    "sg:postcode":"1150",
    "sg:province":"Bruxelles-Capitale",
    "sg:tags":[
        "de",
        "coiffure"
    ],
    "wof:name":"Coiffure Le Brushin",
    "wof:placetype":"venue"
},
  "geometry": {"coordinates":[4.4382858276,50.8333702087],"type":"Point"}
}