{
  "type": "Feature",
  "properties": {
    "iso:country":"BE",
    "sg:address":"Kortrijkstraat 434",
    "sg:city":"Wevelgem",
    "sg:classifiers":[
        {
            "category":"Building & Trades",
            "subcategory":"Landscaping Services",
            "type":"Services"
        }
    ],
    "sg:phone":"+32 56 37 33 66",
    "sg:postcode":"8560",
    "sg:province":"West-Vlaanderen",
    "sg:tags":[
        "gardening",
        "garden",
        "maintenance"
    ],
    "wof:name":"Vanpoucke C",
    "wof:placetype":"venue"
},
  "geometry": {"coordinates":[3.214979887,50.817653656],"type":"Point"}
}