{
  "type": "Feature",
  "properties": {
    "iso:country":"BE",
    "sg:address":"Industriepark Balendijk 2013",
    "sg:city":"Lommel",
    "sg:classifiers":[
        {
            "category":"Home & Garden",
            "subcategory":"Building Materials",
            "type":"Retail Goods"
        }
    ],
    "sg:phone":"+32 11 54 29 20",
    "sg:postcode":"3920",
    "sg:province":"Limburg",
    "sg:tags":[
        "article",
        "-",
        "do-it-yourself"
    ],
    "wof:name":"Kristof Doe-het-zelf",
    "wof:placetype":"venue"
},
  "geometry": {"coordinates":[5.2664217949,51.2146186829],"type":"Point"}
}