{
  "type": "Feature",
  "properties": {
    "iso:country":"BE",
    "sg:address":"Rue Hermon Croix 25",
    "sg:city":"Andenne",
    "sg:orig_category":"Goederenvervoer over de weg",
    "sg:phone":"+32 85 84 15 69",
    "sg:postcode":"5300",
    "sg:province":"Namur",
    "wof:name":"Transanden",
    "wof:placetype":"venue"
},
  "geometry": {"coordinates":[5.1045808792,50.4837913513],"type":"Point"}
}