{
  "type": "Feature",
  "properties": {
    "addr:full":"Rue De Boh\u00c9mont 75 Bertrix Luxembourg 6880",
    "addr:housenumber":"75",
    "addr:postcode":"6880",
    "addr:street":"Rue De Bohe\u0301Mont",
    "iso:country":"BE",
    "sg:address":"Rue De Boh\u00c9mont 75",
    "sg:city":"Bertrix",
    "sg:orig_category":"Diverse bouwafwerking and reiniging",
    "sg:phone":"+32 61 41 11 36",
    "sg:postcode":"6880",
    "sg:province":"Luxembourg",
    "wof:name":"Immobili\u00c8re Ponrol",
    "wof:placetype":"venue"
},
  "geometry": {"coordinates":[5.2610931396,49.8480644226],"type":"Point"}
}