{
  "type": "Feature",
  "properties": {
    "iso:country":"BE",
    "sg:address":"Grote Ieperstraat 138",
    "sg:city":"Wevelgem (gullegem)",
    "sg:classifiers":[
        {
            "category":"Retail",
            "subcategory":"Auto Repair",
            "type":"Services"
        }
    ],
    "sg:phone":"+32 56 42 54 82",
    "sg:postcode":"8560",
    "sg:province":"West-Vlaanderen",
    "sg:tags":[
        "garage"
    ],
    "wof:name":"Garage Maelfait",
    "wof:placetype":"venue"
},
  "geometry": {"coordinates":[3.1987490654,50.8361854553],"type":"Point"}
}