{
  "type": "Feature",
  "properties": {
    "addr:full":"Schorpioenstraat 9 Antwerpen Antwerpen 2018",
    "addr:housenumber":"9",
    "addr:postcode":"2018",
    "addr:street":"Schorpioenstraat",
    "iso:country":"BE",
    "sg:address":"Schorpioenstraat 9",
    "sg:city":"Antwerpen",
    "sg:orig_category":"Artistes ind\u00e9pendants",
    "sg:phone":"+32 3 272 10 69",
    "sg:postcode":"2018",
    "sg:province":"Antwerpen",
    "wof:name":"Eddy Stevens",
    "wof:placetype":"venue"
},
  "geometry": {"coordinates":[4.4333128929,51.2079048157],"type":"Point"}
}