{
  "type": "Feature",
  "properties": {
    "addr:full":"Rue De Temploux 28 Jemeppe-sur-sambre Namur 5190",
    "addr:housenumber":"28",
    "addr:postcode":"5190",
    "addr:street":"Rue De Temploux",
    "iso:country":"BE",
    "sg:address":"Rue De Temploux 28",
    "sg:city":"Jemeppe-sur-sambre",
    "sg:orig_category":"M\u00e9decins and sp\u00e9cialistes",
    "sg:phone":"+32 71 78 65 49",
    "sg:postcode":"5190",
    "sg:province":"Namur",
    "wof:name":"P. Stiernet",
    "wof:placetype":"venue"
},
  "geometry": {"coordinates":[4.7123889923,50.4820556641],"type":"Point"}
}