{
  "type": "Feature",
  "properties": {
    "addr:full":"Langerheide 22 Haacht Vlaams-Brabant 3150",
    "addr:housenumber":"22",
    "addr:postcode":"3150",
    "addr:street":"Langerheide",
    "iso:country":"BE",
    "sg:address":"Langerheide 22",
    "sg:city":"Haacht",
    "sg:classifiers":[
        {
            "category":"Communications",
            "subcategory":"Film & Video Production",
            "type":"Services"
        }
    ],
    "sg:phone":"+32 16 60 37 31",
    "sg:postcode":"3150",
    "sg:province":"Vlaams-Brabant",
    "sg:tags":[
        "material",
        "audio-visual"
    ],
    "wof:name":"Jc Electronics Center Bvba",
    "wof:placetype":"venue"
},
  "geometry": {"coordinates":[4.6224689484,50.9759216309],"type":"Point"}
}