{
  "type": "Feature",
  "properties": {
    "iso:country":"BE",
    "sg:address":"Rue Du Plagniau 19",
    "sg:city":"Rixensart",
    "sg:classifiers":[
        {
            "category":"Cafe",
            "type":"Food & Drink"
        }
    ],
    "sg:phone":"+32 2 654 03 56",
    "sg:postcode":"1330",
    "sg:province":"Brabant Wallon",
    "sg:tags":[
        "caf\u00e9s"
    ],
    "wof:name":"Bowlhill",
    "wof:placetype":"venue"
},
  "geometry": {"coordinates":[4.5340647697,50.7215042114],"type":"Point"}
}