{
  "type": "Feature",
  "properties": {
    "addr:full":"Steenlandlaan 45 Stabroek Antwerpen 2940",
    "addr:housenumber":"45",
    "addr:postcode":"2940",
    "addr:street":"Steenlandlaan",
    "iso:country":"BE",
    "sg:address":"Steenlandlaan 45",
    "sg:city":"Stabroek",
    "sg:classifiers":[
        {
            "category":"Professional",
            "subcategory":"Advertising",
            "type":"Services"
        }
    ],
    "sg:phone":"+32 3 664 82 44",
    "sg:postcode":"2940",
    "sg:province":"Antwerpen",
    "sg:tags":[
        "painter"
    ],
    "wof:name":"Cleiren W",
    "wof:placetype":"venue"
},
  "geometry": {"coordinates":[4.3910508156,51.3488273621],"type":"Point"}
}