{
  "type": "Feature",
  "properties": {
    "iso:country":"BE",
    "sg:address":"Brusselbaan 102",
    "sg:city":"Affligem (hekelgem)",
    "sg:classifiers":[
        {
            "category":"Bakery",
            "type":"Food & Drink"
        }
    ],
    "sg:phone":"+32 53 67 11 69",
    "sg:postcode":"1790",
    "sg:province":"Vlaams-Brabant",
    "sg:tags":[
        "confectioner",
        "baker"
    ],
    "wof:name":"Schellinck",
    "wof:placetype":"venue"
},
  "geometry": {"coordinates":[4.1057391167,50.9131164551],"type":"Point"}
}