{
  "type": "Feature",
  "properties": {
    "addr:full":"Rue Du Cerisier 23 Court-saint-etienne Brabant Wallon 1490",
    "addr:housenumber":"23;1490",
    "addr:street":"Rue Du Cerisier",
    "iso:country":"BE",
    "sg:address":"Rue Du Cerisier 23",
    "sg:city":"Court-saint-etienne",
    "sg:orig_category":"Dierenartsen",
    "sg:phone":"+32 10 61 21 38",
    "sg:postcode":"1490",
    "sg:province":"Brabant Wallon",
    "wof:name":"Yves Colin",
    "wof:placetype":"venue"
},
  "geometry": {"coordinates":[4.530960083,50.6075057983],"type":"Point"}
}