{
  "type": "Feature",
  "properties": {
    "iso:country":"BE",
    "sg:address":"Liersesteenweg 112",
    "sg:city":"Lint",
    "sg:classifiers":[
        {
            "category":"Bars & Pubs",
            "type":"Food & Drink"
        }
    ],
    "sg:phone":"+32 3 455 86 43",
    "sg:postcode":"2547",
    "sg:province":"Antwerpen",
    "sg:tags":[
        "tavern"
    ],
    "wof:name":"Den Eyck Bvba",
    "wof:placetype":"venue"
},
  "geometry": {"coordinates":[4.5018949509,51.1268692017],"type":"Point"}
}