{
  "type": "Feature",
  "properties": {
    "iso:country":"BE",
    "sg:address":"Avenue Marius Meur\u00e9e 23",
    "sg:city":"Charleroi (marcinelle)",
    "sg:classifiers":[
        {
            "category":"Health Services",
            "subcategory":"Health Practitioner",
            "type":"Services"
        }
    ],
    "sg:phone":"+32 71 36 73 92",
    "sg:postcode":"6001",
    "sg:province":"Hainaut",
    "sg:tags":[
        "psychologist"
    ],
    "wof:name":"Ligot-sauvage N",
    "wof:placetype":"venue"
},
  "geometry": {"coordinates":[4.4472560883,50.4008522034],"type":"Point"}
}