{
  "type": "Feature",
  "properties": {
    "addr:full":"Avenue Dailly 214 Bruxelles (schaerbeek) Bruxelles-Capitale 1030",
    "addr:housenumber":"214",
    "addr:postcode":"1030",
    "addr:street":"Avenue Dailly",
    "iso:country":"BE",
    "sg:address":"Avenue Dailly 214",
    "sg:city":"Bruxelles (schaerbeek)",
    "sg:classifiers":[
        {
            "category":"Retail",
            "subcategory":"Auto Repair",
            "type":"Services"
        }
    ],
    "sg:phone":"+32 2 743 35 10",
    "sg:postcode":"1030",
    "sg:province":"Bruxelles-Capitale",
    "sg:tags":[
        "automobile-body"
    ],
    "wof:name":"Verfaille",
    "wof:placetype":"venue"
},
  "geometry": {"coordinates":[4.3874368668,50.8528022766],"type":"Point"}
}