{
  "type": "Feature",
  "properties": {
    "addr:full":"Rue Du Couvent 4 Eupen Li\u00e8ge 4700",
    "addr:housenumber":"4",
    "addr:postcode":"4700",
    "addr:street":"Rue Du Couvent",
    "iso:country":"BE",
    "sg:address":"Rue Du Couvent 4",
    "sg:city":"Eupen",
    "sg:classifiers":[
        {
            "category":"Food & Beverages",
            "subcategory":"Fruits & Vegetables",
            "type":"Retail Goods"
        }
    ],
    "sg:phone":"+32 87 74 21 92",
    "sg:postcode":"4700",
    "sg:province":"Li\u00e8ge",
    "sg:tags":[
        "l\u00e9gumes"
    ],
    "wof:name":"Jose Wouters",
    "wof:placetype":"venue"
},
  "geometry": {"coordinates":[6.0305857658,50.6319503784],"type":"Point"}
}