{
  "type": "Feature",
  "properties": {
    "addr:full":"Rue De La Station 52 Seraing Li\u00e8ge 4101",
    "addr:housenumber":"52",
    "addr:postcode":"4101",
    "addr:street":"Rue De La Station",
    "iso:country":"BE",
    "sg:address":"Rue De La Station 52",
    "sg:city":"Seraing",
    "sg:orig_category":"Banken and kredietinstellingen",
    "sg:phone":"+32 4 233 11 28",
    "sg:postcode":"4101",
    "sg:province":"Li\u00e8ge",
    "wof:name":"Bacob",
    "wof:placetype":"venue"
},
  "geometry": {"coordinates":[5.4999141693,50.6159858704],"type":"Point"}
}