{
  "type": "Feature",
  "properties": {
    "iso:country":"BE",
    "sg:address":"Grotenhoutln 2",
    "sg:city":"Turnhout",
    "sg:classifiers":[
        {
            "category":"Professional",
            "type":"Services"
        }
    ],
    "sg:phone":"+32 14 42 46 01",
    "sg:postcode":"2300",
    "sg:province":"Antwerpen",
    "sg:tags":[
        "transport",
        "road"
    ],
    "wof:name":"J Gilis - Cos Nv",
    "wof:placetype":"venue"
},
  "geometry": {"coordinates":[4.9137239456,51.2881317139],"type":"Point"}
}