{
  "type": "Feature",
  "properties": {
    "iso:country":"BE",
    "sg:address":"Rue Du Ch\u00e2teau 30",
    "sg:city":"Renaix",
    "sg:classifiers":[
        {
            "category":"Health Services",
            "subcategory":"Dentist",
            "type":"Services"
        }
    ],
    "sg:phone":"+32 55 21 37 85",
    "sg:postcode":"9600",
    "sg:province":"Oost-Vlaanderen",
    "wof:name":"Delghust Yves",
    "wof:placetype":"venue"
},
  "geometry": {"coordinates":[3.5949919224,50.7469787598],"type":"Point"}
}