{
  "type": "Feature",
  "properties": {
    "iso:country":"BE",
    "sg:address":"Centre 38",
    "sg:city":"Thimister-clermont (thimister)",
    "sg:classifiers":[
        {
            "category":"Bakery",
            "type":"Food & Drink"
        }
    ],
    "sg:phone":"+32 87 44 61 21",
    "sg:postcode":"4890",
    "sg:province":"Li\u00e8ge",
    "sg:tags":[
        "confectioner",
        "baker"
    ],
    "wof:name":"Collin F",
    "wof:placetype":"venue"
},
  "geometry": {"coordinates":[5.8639798164,50.6545372009],"type":"Point"}
}