{
  "type": "Feature",
  "properties": {
    "iso:country":"BE",
    "sg:address":"Van Aelbrouckstraat 26",
    "sg:city":"Zottegem",
    "sg:classifiers":[
        {
            "category":"Cinema",
            "subcategory":"Movie Rental",
            "type":"Entertainment"
        }
    ],
    "sg:phone":"+32 9 360 78 95",
    "sg:postcode":"9620",
    "sg:province":"Oost-Vlaanderen",
    "sg:tags":[
        "de",
        "cassette",
        "location",
        "vid\u00e9o",
        "audio"
    ],
    "wof:name":"Freddy's Video",
    "wof:placetype":"venue"
},
  "geometry": {"coordinates":[3.8136689663,50.8667945862],"type":"Point"}
}