{
  "type": "Feature",
  "properties": {
    "addr:full":"Rue De L'eglise 7 Rhode-saint-gen\u00e8se Vlaams-Brabant 1640",
    "addr:housenumber":"7",
    "addr:postcode":"1640",
    "addr:street":"Rue De L'Eglise",
    "iso:country":"BE",
    "sg:address":"Rue De L'eglise 7",
    "sg:city":"Rhode-saint-gen\u00e8se",
    "sg:classifiers":[
        {
            "category":"Shopping",
            "subcategory":"Clothing, Apparel, & Fashions",
            "type":"Retail Goods"
        }
    ],
    "sg:phone":"+32 2 380 87 09",
    "sg:postcode":"1640",
    "sg:province":"Vlaams-Brabant",
    "sg:tags":[
        "lady",
        "clothing",
        "-"
    ],
    "wof:name":"Pata'chou Boetiek Nv",
    "wof:placetype":"venue"
},
  "geometry": {"coordinates":[4.3463711739,50.744808197],"type":"Point"}
}