{
  "type": "Feature",
  "properties": {
    "addr:full":"Vierkeerstraat 128 Zwevegem West-Vlaanderen 8551",
    "addr:housenumber":"128",
    "addr:postcode":"8551",
    "addr:street":"Vierkeerstraat",
    "iso:country":"BE",
    "sg:address":"Vierkeerstraat 128",
    "sg:city":"Zwevegem",
    "sg:orig_category":"Fruits and l\u00e9gumes. Eleveurs de bovins",
    "sg:phone":"+32 56 77 75 07",
    "sg:postcode":"8551",
    "sg:province":"West-Vlaanderen",
    "wof:name":"Bert Lateur",
    "wof:placetype":"venue"
},
  "geometry": {"coordinates":[3.4109840393,50.782283783],"type":"Point"}
}