{
  "type": "Feature",
  "properties": {
    "iso:country":"BE",
    "sg:address":"Strijmeers 25a",
    "sg:city":"Sint-lievens-houtem (vlierzele)",
    "sg:classifiers":[
        {
            "category":"Professional",
            "subcategory":"Computer Services",
            "type":"Services"
        }
    ],
    "sg:phone":"+32 53 80 66 90",
    "sg:postcode":"9520",
    "sg:province":"Oost-Vlaanderen",
    "sg:tags":[
        "-",
        "processing",
        "data",
        "software"
    ],
    "wof:name":"Leus-ware Bvba",
    "wof:placetype":"venue"
},
  "geometry": {"coordinates":[3.9141299725,50.9461746216],"type":"Point"}
}