{
  "type": "Feature",
  "properties": {
    "addr:full":"Stationsstraat 265 Liedekerke Vlaams-Brabant 1770",
    "addr:housenumber":"265",
    "addr:postcode":"1770",
    "addr:street":"Stationsstraat;Vlaams-Brabant",
    "iso:country":"BE",
    "sg:address":"Stationsstraat 265",
    "sg:city":"Liedekerke",
    "sg:orig_category":"Entretien and r\u00e9parations de voitures",
    "sg:phone":"+32 53 67 04 90",
    "sg:postcode":"1770",
    "sg:province":"Vlaams-Brabant",
    "wof:name":"Ernest Van Den Bossche",
    "wof:placetype":"venue"
},
  "geometry": {"coordinates":[4.0923781395,50.8772315979],"type":"Point"}
}