{
  "type": "Feature",
  "properties": {
    "iso:country":"BE",
    "sg:address":"Rue Des Pieds D'alouette 39",
    "sg:city":"Namur (naninne)",
    "sg:classifiers":[
        {
            "category":"Government",
            "subcategory":"Fire Station",
            "type":"Public Place"
        }
    ],
    "sg:phone":"+32 81 40 01 19",
    "sg:postcode":"5100",
    "sg:province":"Namur",
    "sg:tags":[
        "detection",
        "installation",
        "material",
        "-"
    ],
    "wof:name":"Somati Sud Sa",
    "wof:placetype":"venue"
},
  "geometry": {"coordinates":[4.9245581627,50.4265937805],"type":"Point"}
}