{
  "type": "Feature",
  "properties": {
    "iso:country":"BE",
    "sg:address":"Ed. Schelfhoutstraat 7",
    "sg:city":"Liedekerke",
    "sg:orig_category":"Fleurs and plantes",
    "sg:phone":"+32 53 67 37 47",
    "sg:postcode":"1770",
    "sg:province":"Vlaams-Brabant",
    "wof:name":"De Mesmacker P. W. S.",
    "wof:placetype":"venue"
},
  "geometry": {"coordinates":[4.0970478058,50.8667449951],"type":"Point"}
}