{
  "type": "Feature",
  "properties": {
    "addr:full":"Rue Joseph Bolle 53 Farciennes Hainaut 6240",
    "addr:housenumber":"53",
    "addr:postcode":"6240",
    "addr:street":"Rue Joseph Bolle",
    "iso:country":"BE",
    "sg:address":"Rue Joseph Bolle 53",
    "sg:city":"Farciennes",
    "sg:classifiers":[
        {
            "category":"Arena",
            "subcategory":"Sports Club",
            "type":"Entertainment"
        }
    ],
    "sg:phone":"+32 71 39 10 28",
    "sg:postcode":"6240",
    "sg:province":"Hainaut",
    "sg:tags":[
        "terrain",
        "hors",
        "de",
        "installation",
        "sportifs"
    ],
    "wof:name":"R.f.c. Farciennes",
    "wof:placetype":"venue"
},
  "geometry": {"coordinates":[4.5511860847,50.4298858643],"type":"Point"}
}