{
  "type": "Feature",
  "properties": {
    "addr:full":"Leuzestraat 16 Kortrijk West-Vlaanderen 8510",
    "addr:housenumber":"16",
    "addr:postcode":"8510",
    "addr:street":"Leuzestraat",
    "iso:country":"BE",
    "sg:address":"Leuzestraat 16",
    "sg:city":"Kortrijk",
    "sg:orig_category":"Avocats and conseillers juridiques",
    "sg:phone":"+32 56 25 60 07",
    "sg:postcode":"8510",
    "sg:province":"West-Vlaanderen",
    "wof:name":"L. Vanhoutte",
    "wof:placetype":"venue"
},
  "geometry": {"coordinates":[3.2928109169,50.7759475708],"type":"Point"}
}