{
  "type": "Feature",
  "properties": {
    "addr:full":"Menenstraat 203 Wevelgem West-Vlaanderen 8560",
    "addr:housenumber":"203",
    "addr:postcode":"8560",
    "addr:street":"Menenstraat",
    "iso:country":"BE",
    "sg:address":"Menenstraat 203",
    "sg:city":"Wevelgem",
    "sg:classifiers":[
        {
            "category":"Personal",
            "subcategory":"Massage",
            "type":"Services"
        }
    ],
    "sg:phone":"+32 56 42 00 54",
    "sg:postcode":"8560",
    "sg:province":"West-Vlaanderen",
    "wof:name":"Lagos",
    "wof:placetype":"venue"
},
  "geometry": {"coordinates":[3.1684710979,50.8048171997],"type":"Point"}
}