{
  "type": "Feature",
  "properties": {
    "iso:country":"BE",
    "sg:address":"Kinstraat 4",
    "sg:city":"Riemst",
    "sg:orig_category":"V\u00e9los",
    "sg:phone":"+32 12 45 18 22",
    "sg:postcode":"3770",
    "sg:province":"Limburg",
    "wof:name":"Hubertus Nassen",
    "wof:placetype":"venue"
},
  "geometry": {"coordinates":[5.5901770592,50.8326835632],"type":"Point"}
}