{
  "type": "Feature",
  "properties": {
    "iso:country":"BE",
    "sg:address":"Rue De Ch\u00c2telet 12",
    "sg:city":"Philippeville",
    "sg:orig_category":"Pisciculture",
    "sg:phone":"+32 71 66 60 24",
    "sg:postcode":"5600",
    "sg:province":"Namur",
    "wof:name":"Pisciculture Du Ry Des Pr\u00c9s",
    "wof:placetype":"venue"
},
  "geometry": {"coordinates":[4.6061701775,50.1923789978],"type":"Point"}
}