{
  "type": "Feature",
  "properties": {
    "iso:country":"BE",
    "sg:address":"Chauss\u00e9e De Mons 362-364",
    "sg:city":"Bruxelles (anderlecht)",
    "sg:classifiers":[
        {
            "category":"Recreation",
            "subcategory":"Fishing",
            "type":"Entertainment"
        }
    ],
    "sg:phone":"+32 2 523 81 50",
    "sg:postcode":"1070",
    "sg:province":"Bruxelles-Capitale",
    "sg:tags":[
        "tackle"
    ],
    "wof:name":"Blondiau N",
    "wof:placetype":"venue"
},
  "geometry": {"coordinates":[4.3200078011,50.8377761841],"type":"Point"}
}