{
  "type": "Feature",
  "properties": {
    "addr:full":"Rue Emile Vandervelde 58 Pepinster Li\u00e8ge 4860",
    "addr:housenumber":"58",
    "addr:postcode":"4860",
    "addr:street":"Rue Emile Vandervelde",
    "iso:country":"BE",
    "sg:address":"Rue Emile Vandervelde 58",
    "sg:city":"Pepinster",
    "sg:orig_category":"Tweedehandsgoederen",
    "sg:phone":"+32 87 46 95 01",
    "sg:postcode":"4860",
    "sg:province":"Li\u00e8ge",
    "wof:name":"Maison Parall\u00c8les",
    "wof:placetype":"venue"
},
  "geometry": {"coordinates":[5.8237948418,50.5787200928],"type":"Point"}
}