{
  "type": "Feature",
  "properties": {
    "addr:full":"Maastrichterweg 15a Genk Limburg 3600",
    "addr:housenumber":"15a",
    "addr:postcode":"3600",
    "addr:street":"Maastrichterweg",
    "iso:country":"BE",
    "sg:address":"Maastrichterweg 15a",
    "sg:city":"Genk",
    "sg:classifiers":[
        {
            "category":"Travel",
            "subcategory":"Travel Agent",
            "type":"Entertainment"
        }
    ],
    "sg:phone":"+32 89 30 63 74",
    "sg:postcode":"3600",
    "sg:province":"Limburg",
    "sg:tags":[
        "agency"
    ],
    "wof:name":"Pirres Club",
    "wof:placetype":"venue"
},
  "geometry": {"coordinates":[5.5132651329,50.9551925659],"type":"Point"}
}