{
  "type": "Feature",
  "properties": {
    "addr:full":"Square Henri Rey 10 Bruxelles (anderlecht) Bruxelles-Capitale 1070",
    "addr:housenumber":"10",
    "addr:postcode":"1070",
    "addr:street":"Square Henri Rey",
    "iso:country":"BE",
    "sg:address":"Square Henri Rey 10",
    "sg:city":"Bruxelles (anderlecht)",
    "sg:classifiers":[
        {
            "category":"Quarry",
            "type":"Physical Feature"
        }
    ],
    "sg:phone":"+32 2 524 50 24",
    "sg:postcode":"1070",
    "sg:province":"Bruxelles-Capitale",
    "sg:tags":[
        "granite",
        "work",
        "marble"
    ],
    "wof:name":"Damaso Pietro & Mardinian",
    "wof:placetype":"venue"
},
  "geometry": {"coordinates":[4.305325985,50.8439788818],"type":"Point"}
}