{
  "type": "Feature",
  "properties": {
    "iso:country":"BE",
    "sg:address":"Avenue Jules Henin 4",
    "sg:city":"Charleroi",
    "sg:classifiers":[
        {
            "category":"Cafe",
            "type":"Food & Drink"
        }
    ],
    "sg:phone":"+32 71 31 26 26",
    "sg:postcode":"6000",
    "sg:province":"Hainaut",
    "sg:tags":[
        "snack-bars"
    ],
    "wof:name":"L'encas",
    "wof:placetype":"venue"
},
  "geometry": {"coordinates":[4.4491782188,50.4162368774],"type":"Point"}
}