{
  "type": "Feature",
  "properties": {
    "addr:full":"Rue De La Libert\u00e9 69 Tournai (rumillies - Mourcourt) Hainaut 7540",
    "addr:housenumber":"69",
    "addr:postcode":"7540",
    "addr:street":"Rue De La Liberte\u0301;Hainaut",
    "iso:country":"BE",
    "sg:address":"Rue De La Libert\u00e9 69",
    "sg:city":"Tournai (rumillies - Mourcourt)",
    "sg:classifiers":[
        {
            "category":"Organizations",
            "subcategory":"Professional Association",
            "type":"Services"
        }
    ],
    "sg:phone":"+32 69 84 19 59",
    "sg:postcode":"7540",
    "sg:province":"Hainaut",
    "sg:tags":[
        "trade-union",
        "federation"
    ],
    "wof:name":"Routiers De Belgique-solidaroutier Asbl Asbl",
    "wof:placetype":"venue"
},
  "geometry": {"coordinates":[3.4163610935,50.6165351868],"type":"Point"}
}