{
  "type": "Feature",
  "properties": {
    "iso:country":"BE",
    "sg:address":"Rue De Lambermont 13",
    "sg:city":"Verviers",
    "sg:orig_category":"Secretariaatsdiensten",
    "sg:phone":"+32 87 31 11 32",
    "sg:postcode":"4800",
    "sg:province":"Li\u00e8ge",
    "wof:name":"Bureau Schonbrodt",
    "wof:placetype":"venue"
},
  "geometry": {"coordinates":[5.8442749977,50.5940284729],"type":"Point"}
}