{
  "type": "Feature",
  "properties": {
    "iso:country":"BE",
    "sg:address":"Tiensestraat 157",
    "sg:city":"Leuven",
    "sg:orig_category":"Imprimeries and copyshops",
    "sg:phone":"+32 16 22 35 70",
    "sg:postcode":"3000",
    "sg:province":"Vlaams-Brabant",
    "wof:name":"J Reekmans - Vink",
    "wof:placetype":"venue"
},
  "geometry": {"coordinates":[4.7098841667,50.8753089905],"type":"Point"}
}