{
  "type": "Feature",
  "properties": {
    "iso:country":"BE",
    "sg:address":"Av.g\u00c9n.dos.de St.georges 1",
    "sg:city":"Elsene/ixelles",
    "sg:orig_category":"M\u00e9decins and sp\u00e9cialistes",
    "sg:phone":"+32 2 647 86 11",
    "sg:postcode":"1050",
    "sg:province":"Bruxelles-Capitale",
    "wof:name":"Louis Hesbeen",
    "wof:placetype":"venue"
},
  "geometry": {"coordinates":[4.3692221642,50.8191757202],"type":"Point"}
}