{
  "type": "Feature",
  "properties": {
    "addr:full":"Sint-andriesplein 22 Antwerpen Antwerpen 2000",
    "addr:housenumber":"22",
    "addr:postcode":"2000",
    "addr:street":"Sint-Andriesplein",
    "iso:country":"BE",
    "sg:address":"Sint-andriesplein 22",
    "sg:city":"Antwerpen",
    "sg:orig_category":"Openbare bibliotheken and archieven",
    "sg:phone":"+32 3 238 28 60",
    "sg:postcode":"2000",
    "sg:province":"Antwerpen",
    "wof:name":"Stedelijke Openbare Bibliotheek",
    "wof:placetype":"venue"
},
  "geometry": {"coordinates":[4.3962769508,51.2146835327],"type":"Point"}
}