{
  "type": "Feature",
  "properties": {
    "addr:full":"Rue Joseph Lizon 16 Chievres Hainaut 7950",
    "addr:housenumber":"16",
    "addr:postcode":"7950",
    "addr:street":"Rue Joseph Lizon;Hainaut",
    "iso:country":"BE",
    "sg:address":"Rue Joseph Lizon 16",
    "sg:city":"Chievres",
    "sg:orig_category":"Rundveehouders",
    "sg:phone":"+32 69 68 95 34",
    "sg:postcode":"7950",
    "sg:province":"Hainaut",
    "wof:name":"Dath Jean Et Vincent",
    "wof:placetype":"venue"
},
  "geometry": {"coordinates":[3.8069698811,50.5864601135],"type":"Point"}
}