{
  "type": "Feature",
  "properties": {
    "addr:full":"Avenue Du Roi Albert 18 Bruxelles (berchem-sainte-agathe) Bruxelles-Capitale 1082",
    "addr:housenumber":"18",
    "addr:postcode":"1082",
    "addr:street":"Avenue Du Roi Albert",
    "iso:country":"BE",
    "sg:address":"Avenue Du Roi Albert 18",
    "sg:city":"Bruxelles (berchem-sainte-agathe)",
    "sg:classifiers":[
        {
            "category":"Arena",
            "subcategory":"Sports Club",
            "type":"Entertainment"
        }
    ],
    "sg:phone":"+32 2 469 08 87",
    "sg:postcode":"1082",
    "sg:province":"Bruxelles-Capitale",
    "sg:tags":[
        "martial art",
        "accessory"
    ],
    "wof:name":"Oshu-kiy Kobudo Okinawa",
    "wof:placetype":"venue"
},
  "geometry": {"coordinates":[4.2954120636,50.8643722534],"type":"Point"}
}