{
  "type": "Feature",
  "properties": {
    "addr:full":"Ringlaan 7 Zandhoven Antwerpen 2240",
    "addr:housenumber":"7",
    "addr:postcode":"2240",
    "addr:street":"Ringlaan",
    "iso:country":"BE",
    "sg:address":"Ringlaan 7",
    "sg:city":"Zandhoven",
    "sg:classifiers":[
        {
            "category":"Professional",
            "subcategory":"Accounting & Tax Preparation",
            "type":"Services"
        }
    ],
    "sg:phone":"+32 3 466 00 91",
    "sg:postcode":"2240",
    "sg:province":"Antwerpen",
    "sg:tags":[
        "bookkeeper"
    ],
    "wof:name":"Marien Bouwens V",
    "wof:placetype":"venue"
},
  "geometry": {"coordinates":[4.6538848877,51.207698822],"type":"Point"}
}