{
  "type": "Feature",
  "properties": {
    "addr:full":"Domien Ingelsstraat 1 Gent Oost-Vlaanderen 9031",
    "addr:housenumber":"1",
    "addr:postcode":"9031",
    "addr:street":"Ingelsstraat;Oost-Vlaanderen",
    "iso:country":"BE",
    "sg:address":"Domien Ingelsstraat 1",
    "sg:city":"Gent",
    "sg:classifiers":[
        {
            "category":"Shopping",
            "subcategory":"Clothing, Apparel, & Fashions",
            "type":"Retail Goods"
        }
    ],
    "sg:phone":"+32 9 227 03 86",
    "sg:postcode":"9031",
    "sg:province":"Oost-Vlaanderen",
    "sg:tags":[
        "lingerie",
        "sous-v\u00eatements"
    ],
    "wof:name":"Huis Sjaroo",
    "wof:placetype":"venue"
},
  "geometry": {"coordinates":[3.664110899,51.0508613586],"type":"Point"}
}