{
  "type": "Feature",
  "properties": {
    "addr:full":"Valkhoeve 18 Diest Vlaams-Brabant 3290",
    "addr:housenumber":"18",
    "addr:postcode":"3290",
    "addr:street":"Valkhoeve",
    "iso:country":"BE",
    "sg:address":"Valkhoeve 18",
    "sg:city":"Diest",
    "sg:orig_category":"Epiceries",
    "sg:phone":"+32 13 67 24 75",
    "sg:postcode":"3290",
    "sg:province":"Vlaams-Brabant",
    "wof:name":"Tecno",
    "wof:placetype":"venue"
},
  "geometry": {"coordinates":[5.0998730659,51.0364379883],"type":"Point"}
}