{
  "type": "Feature",
  "properties": {
    "addr:full":"Orreux 5 Sainte-ode Luxembourg 6680",
    "addr:housenumber":"5",
    "addr:postcode":"6680",
    "addr:street":"Orreux",
    "iso:country":"BE",
    "sg:address":"Orreux 5",
    "sg:city":"Sainte-ode",
    "sg:orig_category":"Eleveurs de bovins",
    "sg:phone":"+32 61 68 80 33",
    "sg:postcode":"6680",
    "sg:province":"Luxembourg",
    "wof:name":"Jacques Dubuisson",
    "wof:placetype":"venue"
},
  "geometry": {"coordinates":[5.5425138474,50.0348243713],"type":"Point"}
}