{
  "type": "Feature",
  "properties": {
    "addr:full":"Dorpsstraat 38 Sint-martens-latem (deurle) Oost-Vlaanderen 9831",
    "addr:housenumber":"38",
    "addr:postcode":"9831",
    "addr:street":"Dorpsstraat",
    "iso:country":"BE",
    "sg:address":"Dorpsstraat 38",
    "sg:city":"Sint-martens-latem (deurle)",
    "sg:classifiers":[
        {
            "category":"Retail",
            "subcategory":"Auto Repair",
            "type":"Services"
        }
    ],
    "sg:phone":"+32 9 282 37 21",
    "sg:postcode":"9831",
    "sg:province":"Oost-Vlaanderen",
    "sg:tags":[
        "garage"
    ],
    "wof:name":"Dhuyvetter P",
    "wof:placetype":"venue"
},
  "geometry": {"coordinates":[3.6048519611,51.0052566528],"type":"Point"}
}