{
  "type": "Feature",
  "properties": {
    "addr:full":"Rue Alphonse Vanr\u00d4me 74 Morlanwelz Hainaut 7141",
    "addr:housenumber":"74",
    "addr:postcode":"7141",
    "addr:street":"Rue Alphonse Vanro\u0302Me",
    "iso:country":"BE",
    "sg:address":"Rue Alphonse Vanr\u00d4me 74",
    "sg:city":"Morlanwelz",
    "sg:orig_category":"Artsen and specialisten",
    "sg:phone":"+32 64 45 18 14",
    "sg:postcode":"7141",
    "sg:province":"Hainaut",
    "wof:name":"C. Philippart",
    "wof:placetype":"venue"
},
  "geometry": {"coordinates":[4.2496762276,50.4477462769],"type":"Point"}
}