{
  "type": "Feature",
  "properties": {
    "iso:country":"BE",
    "sg:address":"Tuinbouwstraat 10",
    "sg:city":"Wommelgem",
    "sg:orig_category":"Groententeelt",
    "sg:phone":"+32 3 353 79 83",
    "sg:postcode":"2160",
    "sg:province":"Antwerpen",
    "wof:name":"Frans Hoes",
    "wof:placetype":"venue"
},
  "geometry": {"coordinates":[4.5074238777,51.1970863342],"type":"Point"}
}