{
  "type": "Feature",
  "properties": {
    "addr:full":"De Leescorfstraat 21 Antwerpen (borgerhout) Antwerpen 2140",
    "addr:housenumber":"21",
    "addr:postcode":"2140",
    "addr:street":"Leescorfstraat",
    "iso:country":"BE",
    "sg:address":"De Leescorfstraat 21",
    "sg:city":"Antwerpen (borgerhout)",
    "sg:classifiers":[
        {
            "category":"Professional",
            "subcategory":"Accounting & Tax Preparation",
            "type":"Services"
        }
    ],
    "sg:phone":"+32 3 236 32 32",
    "sg:postcode":"2140",
    "sg:province":"Antwerpen",
    "sg:tags":[
        "accountant"
    ],
    "wof:name":"Verrept M",
    "wof:placetype":"venue"
},
  "geometry": {"coordinates":[4.4332199097,51.2137565613],"type":"Point"}
}