{
  "type": "Feature",
  "properties": {
    "addr:full":"14 Lisseweegse Steenweg 8380 Brugge Zeebrugge 14",
    "addr:housenumber":"14;14",
    "addr:postcode":"8380",
    "addr:street":"Lisseweegse Steenweg;Zeebrugge",
    "iso:country":"BE",
    "sg:address":"14",
    "sg:city":"Lisseweegse Steenweg 8380 Brugge Zeebrugge",
    "sg:classifiers":[
        {
            "category":"Manufacturing",
            "subcategory":"Glass & Minerals",
            "type":"Manufacturing & Wholesale Goods"
        }
    ],
    "sg:phone":"+32 50 54 38 88",
    "sg:postcode":"14",
    "sg:tags":[
        "building",
        "material"
    ],
    "wof:name":"Seapane Nv",
    "wof:placetype":"venue"
},
  "geometry": {"coordinates":[3.1969299316,51.3099441528],"type":"Point"}
}