{
  "type": "Feature",
  "properties": {
    "iso:country":"BE",
    "sg:address":"Sint-elisabethstraat 21",
    "sg:city":"Beveren",
    "sg:orig_category":"Meubles D\u00e9taillants, Am\u00e9nagement de B\u00e2timents et de Cuisines",
    "sg:phone":"+32 3 755 19 22",
    "sg:postcode":"9120",
    "sg:province":"Oost-Vlaanderen",
    "wof:name":"Meubelen Hispano America",
    "wof:placetype":"venue"
},
  "geometry": {"coordinates":[4.2856030464,51.2210464478],"type":"Point"}
}