{
  "type": "Feature",
  "properties": {
    "iso:country":"BE",
    "sg:address":"Aalststraat 180",
    "sg:city":"Oudenaarde",
    "sg:orig_category":"Enseignement maternel and primaire",
    "sg:phone":"+32 55 31 50 73",
    "sg:postcode":"9700",
    "sg:province":"Oost-Vlaanderen",
    "wof:name":"B.s.g.o. Abraham Hans",
    "wof:placetype":"venue"
},
  "geometry": {"coordinates":[3.6085319519,50.8351402283],"type":"Point"}
}