{
  "type": "Feature",
  "properties": {
    "iso:country":"BE",
    "sg:address":"Sneppestraat 5",
    "sg:city":"Wevelgem",
    "sg:orig_category":"Blanchisseries and teintureries",
    "sg:phone":"+32 56 53 27 20",
    "sg:postcode":"8560",
    "sg:province":"West-Vlaanderen",
    "wof:name":"C&c Invest",
    "wof:placetype":"venue"
},
  "geometry": {"coordinates":[3.1479709148,50.8052940369],"type":"Point"}
}