{
  "type": "Feature",
  "properties": {
    "iso:country":"BE",
    "sg:address":"Place Nicola\u00ef 6",
    "sg:city":"Aubel",
    "sg:classifiers":[
        {
            "category":"Real Estate",
            "subcategory":"Architect",
            "type":"Services"
        }
    ],
    "sg:phone":"+32 495 24 77 92",
    "sg:postcode":"4880",
    "sg:province":"Li\u00e8ge",
    "wof:name":"Don\u00e9a J-p",
    "wof:placetype":"venue"
},
  "geometry": {"coordinates":[5.8584327698,50.7050476074],"type":"Point"}
}