{
  "type": "Feature",
  "properties": {
    "iso:country":"BE",
    "sg:address":"Flierenbos 56",
    "sg:city":"Arendonk",
    "sg:orig_category":"Sportclubs Sportterreinen and installaties behalve sportcentra",
    "sg:phone":"+32 14 67 29 56",
    "sg:postcode":"2370",
    "sg:province":"Antwerpen",
    "wof:name":"F.c. Vrij Arendonk",
    "wof:placetype":"venue"
},
  "geometry": {"coordinates":[5.0952329636,51.3342437744],"type":"Point"}
}