{
  "type": "Feature",
  "properties": {
    "addr:full":"Lebeke 44 Haaltert (denderhoutem) Oost-Vlaanderen 9450",
    "addr:housenumber":"44",
    "addr:postcode":"9450",
    "addr:street":"Lebeke",
    "iso:country":"BE",
    "sg:address":"Lebeke 44",
    "sg:city":"Haaltert (denderhoutem)",
    "sg:classifiers":[
        {
            "category":"Shopping",
            "subcategory":"Bicycles & Sporting Goods",
            "type":"Retail Goods"
        }
    ],
    "sg:phone":"+32 54 32 07 19",
    "sg:postcode":"9450",
    "sg:province":"Oost-Vlaanderen",
    "sg:tags":[
        "-"
    ],
    "wof:name":"Coppens R",
    "wof:placetype":"venue"
},
  "geometry": {"coordinates":[4.0024838448,50.8668060303],"type":"Point"}
}