{
  "type": "Feature",
  "properties": {
    "addr:full":"Lieven Gevaertplein 5a Oostkamp West-Vlaanderen 8020",
    "addr:housenumber":"5a",
    "addr:postcode":"8020",
    "addr:street":"Gevaertplein",
    "iso:country":"BE",
    "sg:address":"Lieven Gevaertplein 5a",
    "sg:city":"Oostkamp",
    "sg:classifiers":[
        {
            "category":"Farming",
            "subcategory":"Fish & Marine Products",
            "type":"Manufacturing & Wholesale Goods"
        }
    ],
    "sg:phone":"+32 50 59 89 80",
    "sg:postcode":"8020",
    "sg:province":"West-Vlaanderen",
    "sg:tags":[
        "retail",
        "-",
        "shellfish"
    ],
    "wof:name":"Vishuis ('t)",
    "wof:placetype":"venue"
},
  "geometry": {"coordinates":[3.2323100567,51.1369094849],"type":"Point"}
}