{
  "type": "Feature",
  "properties": {
    "addr:full":"Industrieterrein 1 Diest Vlaams-Brabant 3290",
    "addr:housenumber":"1",
    "addr:postcode":"3290",
    "addr:street":"Industrieterrein",
    "iso:country":"BE",
    "sg:address":"Industrieterrein 1",
    "sg:city":"Diest",
    "sg:classifiers":[
        {
            "category":"Building & Trades",
            "subcategory":"Equipment Rental",
            "type":"Services"
        }
    ],
    "sg:phone":"+32 13 31 33 75",
    "sg:postcode":"3290",
    "sg:province":"Vlaams-Brabant",
    "sg:tags":[
        "use",
        "apparatus",
        "tool",
        "-",
        "professional",
        "machines"
    ],
    "wof:name":"De Bruycker O",
    "wof:placetype":"venue"
},
  "geometry": {"coordinates":[5.0751109123,50.9639320374],"type":"Point"}
}