{
  "type": "Feature",
  "properties": {
    "addr:full":"Spildoornstraat 16 Desselgem West-Vlaanderen 8792",
    "addr:housenumber":"16",
    "addr:postcode":"8792",
    "addr:street":"Spildoornstraat;West-Vlaanderen",
    "iso:country":"BE",
    "sg:address":"Spildoornstraat 16",
    "sg:city":"Desselgem",
    "sg:classifiers":[
        {
            "category":"Professional",
            "subcategory":"Engineering",
            "type":"Services"
        }
    ],
    "sg:phone":"+32 56 71 19 37",
    "sg:postcode":"8792",
    "sg:province":"West-Vlaanderen",
    "sg:tags":[
        "road",
        "surfacing",
        "asphalt",
        "highway"
    ],
    "wof:name":"Jozef Vanden Buverie & Co Nv",
    "wof:placetype":"venue"
},
  "geometry": {"coordinates":[3.3703548908,50.8936767578],"type":"Point"}
}