{
  "type": "Feature",
  "properties": {
    "addr:full":"Fonteinstraat 27 Temse Oost-Vlaanderen 9140",
    "addr:housenumber":"27",
    "addr:postcode":"9140",
    "addr:street":"Fonteinstraat",
    "iso:country":"BE",
    "sg:address":"Fonteinstraat 27",
    "sg:city":"Temse",
    "sg:orig_category":"Goederenvervoer over de weg Verhuisdiensten",
    "sg:phone":"+32 3 711 11 05",
    "sg:postcode":"9140",
    "sg:province":"Oost-Vlaanderen",
    "wof:name":"Kurt Robberecht",
    "wof:placetype":"venue"
},
  "geometry": {"coordinates":[4.2303929329,51.1251296997],"type":"Point"}
}