{
  "type": "Feature",
  "properties": {
    "addr:full":"Broekstraat 83a Hamme Oost-Vlaanderen 9220",
    "addr:housenumber":"83a",
    "addr:postcode":"9220",
    "addr:street":"Broekstraat",
    "iso:country":"BE",
    "sg:address":"Broekstraat 83a",
    "sg:city":"Hamme",
    "sg:classifiers":[
        {
            "category":"Manufacturing",
            "subcategory":"Building Materials",
            "type":"Manufacturing & Wholesale Goods"
        }
    ],
    "sg:phone":"+32 52 47 35 42",
    "sg:postcode":"9220",
    "sg:province":"Oost-Vlaanderen",
    "sg:tags":[
        "fixture",
        "store"
    ],
    "wof:name":"Manfo Algemene Inrichtingen",
    "wof:placetype":"venue"
},
  "geometry": {"coordinates":[4.1590738297,51.0895767212],"type":"Point"}
}