{
  "type": "Feature",
  "properties": {
    "iso:country":"BE",
    "sg:address":"Rue De La Gaillarde 3",
    "sg:city":"Saint-servais",
    "sg:orig_category":"Installation \u00e9lectrique r\u00e9sidentielle",
    "sg:phone":"+32 81 73 51 56",
    "sg:postcode":"5002",
    "sg:province":"Namur",
    "wof:name":"Brumagne De Meersman",
    "wof:placetype":"venue"
},
  "geometry": {"coordinates":[4.8304867744,50.4738311768],"type":"Point"}
}