{
  "type": "Feature",
  "properties": {
    "addr:full":"Rue De La Frete 35 Ramillies Brabant Wallon 1367",
    "addr:housenumber":"35",
    "addr:postcode":"1367",
    "addr:street":"Rue De La Frete",
    "iso:country":"BE",
    "sg:address":"Rue De La Frete 35",
    "sg:city":"Ramillies",
    "sg:classifiers":[
        {
            "category":"Banks & Credit Unions",
            "subcategory":"Bureau De Change",
            "type":"Services"
        }
    ],
    "sg:phone":"+32 2 524 18 53",
    "sg:postcode":"1367",
    "sg:province":"Brabant Wallon",
    "sg:tags":[
        "solution",
        "complete",
        "internet"
    ],
    "wof:name":"In2creation",
    "wof:placetype":"venue"
},
  "geometry": {"coordinates":[4.9187102318,50.6306381226],"type":"Point"}
}