{
  "type": "Feature",
  "properties": {
    "iso:country":"BE",
    "sg:address":"Lange Ommegangstraat 37",
    "sg:city":"Erpe-mere",
    "sg:classifiers":[
        {
            "category":"Shopping",
            "subcategory":"Clothing, Apparel, & Fashions",
            "type":"Retail Goods"
        }
    ],
    "sg:phone":"+32 53 80 13 01",
    "sg:postcode":"9420",
    "sg:province":"Oost-Vlaanderen",
    "sg:tags":[
        "blouse",
        "ladies'",
        "dress"
    ],
    "wof:name":"Mobecon B.v.b.a.",
    "wof:placetype":"venue"
},
  "geometry": {"coordinates":[3.9845480919,50.9280776978],"type":"Point"}
}