{
  "type": "Feature",
  "properties": {
    "iso:country":"BE",
    "sg:address":"Rue David Van Bever 36",
    "sg:city":"Bruxelles (woluwe-saint-pierre)",
    "sg:classifiers":[
        {
            "category":"Health Services",
            "subcategory":"Health Practitioner",
            "type":"Services"
        }
    ],
    "sg:phone":"+32 2 772 02 82",
    "sg:postcode":"1150",
    "sg:province":"Bruxelles-Capitale",
    "sg:tags":[
        "psychologist"
    ],
    "wof:name":"Lescalier Grosjean I",
    "wof:placetype":"venue"
},
  "geometry": {"coordinates":[4.4402022362,50.832824707],"type":"Point"}
}