{
  "type": "Feature",
  "properties": {
    "iso:country":"BE",
    "sg:address":"Louizalaan 8-10",
    "sg:city":"Brussel (brussel)",
    "sg:orig_category":"Dameskledingzaken",
    "sg:phone":"+32 2 536 00 50",
    "sg:postcode":"1050",
    "sg:province":"Bruxelles-Capitale",
    "wof:name":"Zara",
    "wof:placetype":"venue"
},
  "geometry": {"coordinates":[4.3560428619,50.8350830078],"type":"Point"}
}