{
  "type": "Feature",
  "properties": {
    "iso:country":"BE",
    "sg:address":"Place Du March\u00c9 1",
    "sg:city":"Fosses-la-ville",
    "sg:orig_category":"Openbare veiligheid",
    "sg:phone":"+32 71 71 10 70",
    "sg:postcode":"5070",
    "sg:province":"Namur",
    "wof:name":"Police F\u00c9d\u00c9rale",
    "wof:placetype":"venue"
},
  "geometry": {"coordinates":[4.6967329979,50.3970565796],"type":"Point"}
}