{
  "type": "Feature",
  "properties": {
    "iso:country":"BE",
    "sg:address":"Sint-goriksplein 6",
    "sg:city":"Edegem",
    "sg:orig_category":"Instituts de beaut\u00e9. Salons de coiffure",
    "sg:phone":"+32 3 458 46 02",
    "sg:postcode":"2650",
    "sg:province":"Antwerpen",
    "wof:name":"Instituut Bellisimo",
    "wof:placetype":"venue"
},
  "geometry": {"coordinates":[4.4541392326,51.1492729187],"type":"Point"}
}