{
  "type": "Feature",
  "properties": {
    "iso:country":"BE",
    "sg:address":"Rue De L'abreuvoir 8",
    "sg:city":"Herbeumont (saint-m\u00e9dard)",
    "sg:classifiers":[
        {
            "category":"Sports & Exercise",
            "subcategory":"Stables",
            "type":"Entertainment"
        }
    ],
    "sg:phone":"+32 475 97 11 86",
    "sg:postcode":"6887",
    "sg:province":"Luxembourg",
    "sg:tags":[
        "riding",
        "school"
    ],
    "wof:name":"Mini Furguy (le) Sprl",
    "wof:placetype":"venue"
},
  "geometry": {"coordinates":[5.3150248528,49.822177887],"type":"Point"}
}