{
  "type": "Feature",
  "properties": {
    "iso:country":"BE",
    "sg:address":"Rue De L'industrie 20",
    "sg:city":"Nivelles",
    "sg:classifiers":[
        {
            "category":"Autos & Motor Vehicles",
            "subcategory":"Auto Supplies",
            "type":"Retail Goods"
        }
    ],
    "sg:phone":"+32 67 88 37 53",
    "sg:postcode":"1400",
    "sg:province":"Brabant Wallon",
    "sg:tags":[
        "industrial",
        "vibrator",
        "-"
    ],
    "wof:name":"Carrier Europe",
    "wof:placetype":"venue"
},
  "geometry": {"coordinates":[4.3556470871,50.5864639282],"type":"Point"}
}