{
  "type": "Feature",
  "properties": {
    "addr:full":"Fernand Tonnetgaarde 25 Jette Bruxelles-Capitale 1090",
    "addr:housenumber":"25",
    "addr:postcode":"1090",
    "addr:street":"Fernand Tonnetgaarde",
    "iso:country":"BE",
    "sg:address":"Fernand Tonnetgaarde 25",
    "sg:city":"Jette",
    "sg:orig_category":"Rusthuizen and serviceflats",
    "sg:phone":"+32 2 479 71 35",
    "sg:postcode":"1090",
    "sg:province":"Bruxelles-Capitale",
    "wof:name":"Home L'emeraude",
    "wof:placetype":"venue"
},
  "geometry": {"coordinates":[4.3202362061,50.8920555115],"type":"Point"}
}