{
  "type": "Feature",
  "properties": {
    "addr:full":"Raymond Lauwersstraat 27 Hoeilaart Vlaams-Brabant 1560",
    "addr:housenumber":"27",
    "addr:postcode":"1560",
    "addr:street":"Raymond Lauwersstraat",
    "iso:country":"BE",
    "sg:address":"Raymond Lauwersstraat 27",
    "sg:city":"Hoeilaart",
    "sg:orig_category":"Producteurs de fruits",
    "sg:phone":"+32 2 657 09 69",
    "sg:postcode":"1560",
    "sg:province":"Vlaams-Brabant",
    "wof:name":"Van Ranst-blommaert",
    "wof:placetype":"venue"
},
  "geometry": {"coordinates":[4.4826011658,50.7678527832],"type":"Point"}
}