{
  "type": "Feature",
  "properties": {
    "iso:country":"BE",
    "sg:address":"Jef Buyckxstraat 148",
    "sg:city":"Turnhout",
    "sg:orig_category":"Slagers",
    "sg:phone":"+32 14 42 12 40",
    "sg:postcode":"2300",
    "sg:province":"Antwerpen",
    "wof:name":"Kippenpaleis",
    "wof:placetype":"venue"
},
  "geometry": {"coordinates":[4.9323329926,51.3049812317],"type":"Point"}
}