{
  "type": "Feature",
  "properties": {
    "addr:full":"Kerkstraat 54 Oud-turnhout Antwerpen 2360",
    "addr:housenumber":"54",
    "addr:postcode":"2360",
    "addr:street":"Kerkstraat",
    "iso:country":"BE",
    "sg:address":"Kerkstraat 54",
    "sg:city":"Oud-turnhout",
    "sg:classifiers":[
        {
            "category":"Communications",
            "subcategory":"Film & Video Production",
            "type":"Services"
        }
    ],
    "sg:phone":"+32 14 46 00 62",
    "sg:postcode":"2360",
    "sg:province":"Antwerpen",
    "sg:tags":[
        "platen",
        "cassette",
        "cd's"
    ],
    "wof:name":"Stealth Records",
    "wof:placetype":"venue"
},
  "geometry": {"coordinates":[4.9825592041,51.3217506409],"type":"Point"}
}