{
  "type": "Feature",
  "properties": {
    "addr:full":"Rue D'aix-la-chapelle 12 Raeren Li\u00e8ge 4731",
    "addr:housenumber":"12",
    "addr:postcode":"4731",
    "addr:street":"Rue D'Aix-La-Chapelle",
    "iso:country":"BE",
    "sg:address":"Rue D'aix-la-chapelle 12",
    "sg:city":"Raeren",
    "sg:orig_category":"Banques and organismes de cr\u00e9dit",
    "sg:phone":"+32 87 85 82 40",
    "sg:postcode":"4731",
    "sg:province":"Li\u00e8ge",
    "wof:name":"Kbc",
    "wof:placetype":"venue"
},
  "geometry": {"coordinates":[6.0476951599,50.6756477356],"type":"Point"}
}