{
  "type": "Feature",
  "properties": {
    "iso:country":"BE",
    "sg:address":"Oude Schansstraat 32",
    "sg:city":"Halen",
    "sg:orig_category":"Baby- and kinderkleding",
    "sg:phone":"+32 13 31 48 13",
    "sg:postcode":"3545",
    "sg:province":"Limburg",
    "wof:name":"Anne Corthouts",
    "wof:placetype":"venue"
},
  "geometry": {"coordinates":[5.0961589813,50.9835929871],"type":"Point"}
}