{
  "type": "Feature",
  "properties": {
    "iso:country":"BE",
    "sg:address":"Korte Rabotstraat 5",
    "sg:city":"Evergem",
    "sg:orig_category":"Animations diverses",
    "sg:phone":"+32 9 253 64 58",
    "sg:postcode":"9940",
    "sg:province":"Oost-Vlaanderen",
    "wof:name":"Ami Circusprodukties",
    "wof:placetype":"venue"
},
  "geometry": {"coordinates":[3.6573491096,51.0950431824],"type":"Point"}
}