{
  "type": "Feature",
  "properties": {
    "addr:full":"Hoeksken 34 Evergem Oost-Vlaanderen 9940",
    "addr:housenumber":"34",
    "addr:postcode":"9940",
    "addr:street":"Hoeksken;Oost-Vlaanderen",
    "iso:country":"BE",
    "sg:address":"Hoeksken 34",
    "sg:city":"Evergem",
    "sg:classifiers":[
        {
            "category":"Building & Trades",
            "subcategory":"Pest Control",
            "type":"Services"
        }
    ],
    "sg:phone":"+32 9 258 13 82",
    "sg:postcode":"9940",
    "sg:province":"Oost-Vlaanderen",
    "sg:tags":[
        "painting",
        "contractor"
    ],
    "wof:name":"Versprille D",
    "wof:placetype":"venue"
},
  "geometry": {"coordinates":[3.7062489986,51.1103401184],"type":"Point"}
}