{
  "type": "Feature",
  "properties": {
    "iso:country":"BE",
    "sg:address":"Rue De Bouillon 13b",
    "sg:city":"Bievre",
    "sg:orig_category":"Verbruikerskredietinstellingen",
    "sg:phone":"+32 61 51 25 36",
    "sg:postcode":"5555",
    "sg:province":"Namur",
    "wof:name":"Sowafina",
    "wof:placetype":"venue"
},
  "geometry": {"coordinates":[5.0200648308,49.9400024414],"type":"Point"}
}