{
  "type": "Feature",
  "properties": {
    "iso:country":"BE",
    "sg:address":"Rue Du Viaduc 69",
    "sg:city":"Tournai",
    "sg:orig_category":"Grands magasins",
    "sg:phone":"+32 69 22 36 27",
    "sg:postcode":"7500",
    "sg:province":"Hainaut",
    "wof:name":"Jean Soyez",
    "wof:placetype":"venue"
},
  "geometry": {"coordinates":[3.3928129673,50.6173858643],"type":"Point"}
}