{
  "type": "Feature",
  "properties": {
    "iso:country":"BE",
    "sg:address":"Sluizeken 28",
    "sg:city":"Gent",
    "sg:orig_category":"Zalen voor culturele evenementen",
    "sg:phone":"+32 9 224 35 55",
    "sg:postcode":"9000",
    "sg:province":"Oost-Vlaanderen",
    "wof:name":"Oudburg Art",
    "wof:placetype":"venue"
},
  "geometry": {"coordinates":[3.725071907,51.059753418],"type":"Point"}
}