{
  "type": "Feature",
  "properties": {
    "addr:full":"Boulevard De La Cambre 26 Bruxelles Bruxelles-Capitale 1000",
    "addr:housenumber":"26",
    "addr:postcode":"1000",
    "addr:street":"Boulevard De La Cambre",
    "iso:country":"BE",
    "sg:address":"Boulevard De La Cambre 26",
    "sg:city":"Bruxelles",
    "sg:classifiers":[
        {
            "category":"Health Services",
            "subcategory":"Doctor",
            "type":"Services"
        }
    ],
    "sg:phone":"+32 2 644 21 58",
    "sg:postcode":"1000",
    "sg:province":"Bruxelles-Capitale",
    "sg:tags":[
        "medicinephysicians",
        "surgeon"
    ],
    "wof:name":"Jabry S",
    "wof:placetype":"venue"
},
  "geometry": {"coordinates":[4.3754010201,50.8160514832],"type":"Point"}
}