{
  "type": "Feature",
  "properties": {
    "iso:country":"BE",
    "sg:address":"Rue Winston-churchill 173",
    "sg:city":"Bressoux",
    "sg:orig_category":"D\u00e9taillants en pi\u00e8ces and accessoires de voitures",
    "sg:phone":"+32 4 342 15 97",
    "sg:postcode":"4020",
    "sg:province":"Li\u00e8ge",
    "wof:name":"Station Du Pneu",
    "wof:placetype":"venue"
},
  "geometry": {"coordinates":[5.6021127701,50.6411056519],"type":"Point"}
}