{
  "type": "Feature",
  "properties": {
    "addr:full":"Roterijstraat 67 Kuurne West-Vlaanderen 8520",
    "addr:housenumber":"67",
    "addr:postcode":"8520",
    "addr:street":"Roterijstraat",
    "iso:country":"BE",
    "sg:address":"Roterijstraat 67",
    "sg:city":"Kuurne",
    "sg:classifiers":[
        {
            "category":"Building & Trades",
            "subcategory":"Electrical",
            "type":"Services"
        }
    ],
    "sg:phone":"+32 56 51 62 18",
    "sg:postcode":"8520",
    "sg:province":"West-Vlaanderen",
    "sg:tags":[
        "electric",
        "-",
        "housewiring",
        "contractor"
    ],
    "wof:name":"De Cruyenaere J",
    "wof:placetype":"venue"
},
  "geometry": {"coordinates":[3.2805280685,50.844783783],"type":"Point"}
}