{
  "type": "Feature",
  "properties": {
    "iso:country":"BE",
    "sg:address":"Rue Herbert Hoover 27",
    "sg:city":"Ch\u00e2telet (ch\u00e2telineau)",
    "sg:classifiers":[
        {
            "category":"Health Services",
            "subcategory":"Dentist",
            "type":"Services"
        }
    ],
    "sg:phone":"+32 71 38 37 49",
    "sg:postcode":"6200",
    "sg:province":"Hainaut",
    "wof:name":"Piret E",
    "wof:placetype":"venue"
},
  "geometry": {"coordinates":[4.5207700729,50.4122314453],"type":"Point"}
}