{
  "type": "Feature",
  "properties": {
    "addr:full":"Eeksken 85 Opwijk Vlaams-Brabant 1745",
    "addr:housenumber":"85",
    "addr:postcode":"1745",
    "addr:street":"Eeksken",
    "iso:country":"BE",
    "sg:address":"Eeksken 85",
    "sg:city":"Opwijk",
    "sg:orig_category":"Mat\u00e9riaux de construction Gr",
    "sg:phone":"+32 52 35 83 28",
    "sg:postcode":"1745",
    "sg:province":"Vlaams-Brabant",
    "wof:name":"Van Biesen - Everaert",
    "wof:placetype":"venue"
},
  "geometry": {"coordinates":[4.1720290184,50.9812240601],"type":"Point"}
}