{
  "type": "Feature",
  "properties": {
    "addr:full":"Hogenstraat 71 Geetbets Vlaams-Brabant 3450",
    "addr:housenumber":"71",
    "addr:postcode":"3450",
    "addr:street":"Hogenstraat",
    "iso:country":"BE",
    "sg:address":"Hogenstraat 71",
    "sg:city":"Geetbets",
    "sg:orig_category":"Epiceries",
    "sg:phone":"+32 11 58 71 24",
    "sg:postcode":"3450",
    "sg:province":"Vlaams-Brabant",
    "wof:name":"Huis Vandepoel-beeten",
    "wof:placetype":"venue"
},
  "geometry": {"coordinates":[5.0805640221,50.8825187683],"type":"Point"}
}