{
  "type": "Feature",
  "properties": {
    "iso:country":"BE",
    "sg:address":"Avenue Montefiore 4",
    "sg:city":"Esneux",
    "sg:orig_category":"Schoenen",
    "sg:phone":"+32 4 380 14 59",
    "sg:postcode":"4130",
    "sg:province":"Li\u00e8ge",
    "wof:name":"Maison Nicolay",
    "wof:placetype":"venue"
},
  "geometry": {"coordinates":[5.5662298203,50.5319480896],"type":"Point"}
}