{
  "type": "Feature",
  "properties": {
    "iso:country":"BE",
    "sg:address":"Waterstraat 13",
    "sg:city":"Ingelmunster",
    "sg:classifiers":[
        {
            "category":"Animal Shelter",
            "type":"Public Place"
        }
    ],
    "sg:phone":"+32 51 30 27 12",
    "sg:postcode":"8770",
    "sg:province":"West-Vlaanderen",
    "sg:tags":[
        "nutrition",
        "husbandry"
    ],
    "wof:name":"Valora Voeders Nv",
    "wof:placetype":"venue"
},
  "geometry": {"coordinates":[3.2510750294,50.9175834656],"type":"Point"}
}