{
  "type": "Feature",
  "properties": {
    "iso:country":"BE",
    "sg:address":"Cyriel Buyssestraat 24",
    "sg:city":"Anderlecht/anderlecht",
    "sg:orig_category":"Artsen and specialisten",
    "sg:phone":"+32 2 523 31 34",
    "sg:postcode":"1070",
    "sg:province":"Bruxelles-Capitale",
    "wof:name":"C. Vanwelde",
    "wof:placetype":"venue"
},
  "geometry": {"coordinates":[4.3054480553,50.8397827148],"type":"Point"}
}