{
  "type": "Feature",
  "properties": {
    "addr:full":"Rue Des Fraisiers 34 Li\u00e8ge 1 Li\u00e8ge 4000",
    "addr:housenumber":"34;1",
    "addr:postcode":"4000",
    "addr:street":"Rue Des Fraisiers",
    "iso:country":"BE",
    "sg:address":"Rue Des Fraisiers 34",
    "sg:city":"Li\u00e8ge 1",
    "sg:classifiers":[
        {
            "category":"Building & Trades",
            "subcategory":"Construction",
            "type":"Services"
        }
    ],
    "sg:phone":"+32 496 50 67 45",
    "sg:postcode":"4000",
    "sg:province":"Li\u00e8ge",
    "sg:tags":[
        "industrial",
        "design"
    ],
    "wof:name":"Loudordesign",
    "wof:placetype":"venue"
},
  "geometry": {"coordinates":[5.5943770409,50.6654777527],"type":"Point"}
}