{
  "type": "Feature",
  "properties": {
    "addr:full":"Vilvoordelaan 153ba Zaventem Vlaams-Brabant 1930",
    "addr:housenumber":"153ba",
    "addr:postcode":"1930",
    "addr:street":"Vilvoordelaan",
    "iso:country":"BE",
    "sg:address":"Vilvoordelaan 153ba",
    "sg:city":"Zaventem",
    "sg:orig_category":"Luchtvaart volgens dienstregeling",
    "sg:phone":"+32 2 712 64 28",
    "sg:postcode":"1930",
    "sg:province":"Vlaams-Brabant",
    "wof:name":"Ukraine Intern. Airlines",
    "wof:placetype":"venue"
},
  "geometry": {"coordinates":[4.4713082314,50.8933067322],"type":"Point"}
}