{
  "type": "Feature",
  "properties": {
    "iso:country":"BE",
    "sg:address":"Deuzeldlaan 48",
    "sg:city":"Schoten",
    "sg:classifiers":[
        {
            "category":"Professional",
            "subcategory":"Engineering",
            "type":"Services"
        }
    ],
    "sg:phone":"+32 3 647 24 06",
    "sg:postcode":"2900",
    "sg:province":"Antwerpen",
    "sg:tags":[
        "-"
    ],
    "wof:name":"Gima Bvba",
    "wof:placetype":"venue"
},
  "geometry": {"coordinates":[4.4666290283,51.2451248169],"type":"Point"}
}