{
  "type": "Feature",
  "properties": {
    "addr:full":"Rietschoorvelden 20 Merksem Antwerpen 2170",
    "addr:housenumber":"20",
    "addr:postcode":"2170",
    "addr:street":"Rietschoorvelden",
    "iso:country":"BE",
    "sg:address":"Rietschoorvelden 20",
    "sg:city":"Merksem",
    "sg:classifiers":[
        {
            "category":"Manufacturing",
            "subcategory":"Metals",
            "type":"Manufacturing & Wholesale Goods"
        }
    ],
    "sg:phone":"+32 3 640 93 22",
    "sg:postcode":"2170",
    "sg:province":"Antwerpen",
    "sg:tags":[
        "metallurgy",
        "metalworking"
    ],
    "wof:name":"Baubur Nv",
    "wof:placetype":"venue"
},
  "geometry": {"coordinates":[4.4287090302,51.2472076416],"type":"Point"}
}