{
  "type": "Feature",
  "properties": {
    "addr:full":"Pas Pacheco 44b3 Brussel/bruxelles Bruxelles-Capitale 1000",
    "addr:housenumber":"44b3",
    "addr:postcode":"1000",
    "addr:street":"Pas Pacheco;/",
    "iso:country":"BE",
    "sg:address":"Pas Pacheco 44b3",
    "sg:city":"Brussel/bruxelles",
    "sg:orig_category":"Agences de voyages",
    "sg:phone":"+32 2 223 18 15",
    "sg:postcode":"1000",
    "sg:province":"Bruxelles-Capitale",
    "wof:name":"Carlson Wagonlit Travel",
    "wof:placetype":"venue"
},
  "geometry": {"coordinates":[4.3626542091,50.8531723022],"type":"Point"}
}