{
  "type": "Feature",
  "properties": {
    "iso:country":"BE",
    "sg:address":"Zoellaan 86",
    "sg:city":"Haacht",
    "sg:orig_category":"Sportclubs",
    "sg:phone":"+32 16 60 22 87",
    "sg:postcode":"3150",
    "sg:province":"Vlaams-Brabant",
    "wof:name":"Plezante Duivenmelkers",
    "wof:placetype":"venue"
},
  "geometry": {"coordinates":[4.6321997643,50.9788742065],"type":"Point"}
}