{
  "type": "Feature",
  "properties": {
    "addr:full":"Retieseweg 100b Geel Antwerpen 2440",
    "addr:housenumber":"100b",
    "addr:postcode":"2440",
    "addr:street":"Retieseweg",
    "iso:country":"BE",
    "sg:address":"Retieseweg 100b",
    "sg:city":"Geel",
    "sg:classifiers":[
        {
            "category":"Farming",
            "subcategory":"Livestock Farm",
            "type":"Manufacturing & Wholesale Goods"
        }
    ],
    "sg:phone":"+32 14 58 55 22",
    "sg:postcode":"2440",
    "sg:province":"Antwerpen",
    "sg:tags":[
        "buyer"
    ],
    "wof:name":"Kerckhofs L",
    "wof:placetype":"venue"
},
  "geometry": {"coordinates":[5.030769825,51.1990699768],"type":"Point"}
}