{
  "type": "Feature",
  "properties": {
    "iso:country":"BE",
    "sg:address":"Avenue Du Pesage 81 Box 10",
    "sg:city":"Bruxelles (ixelles)",
    "sg:classifiers":[
        {
            "category":"Professional",
            "subcategory":"Accounting & Tax Preparation",
            "type":"Services"
        }
    ],
    "sg:phone":"+32 2 640 87 96",
    "sg:postcode":"1050",
    "sg:province":"Bruxelles-Capitale",
    "sg:tags":[
        "accountant"
    ],
    "wof:name":"Louppe J",
    "wof:placetype":"venue"
},
  "geometry": {"coordinates":[4.3873939514,50.8076896667],"type":"Point"}
}