{
  "type": "Feature",
  "properties": {
    "addr:full":"Rue Pierre Michaux 74 Oupeye (vivegnis) Li\u00e8ge 4683",
    "addr:housenumber":"74",
    "addr:postcode":"4683",
    "addr:street":"Rue Pierre Michaux;Vivegnis",
    "iso:country":"BE",
    "sg:address":"Rue Pierre Michaux 74",
    "sg:city":"Oupeye (vivegnis)",
    "sg:classifiers":[
        {
            "category":"Autos & Motor Vehicles",
            "subcategory":"Recreational Vehicle Sales",
            "type":"Retail Goods"
        }
    ],
    "sg:phone":"+32 4 240 14 10",
    "sg:postcode":"4683",
    "sg:province":"Li\u00e8ge",
    "sg:tags":[
        "caravan",
        "accessory"
    ],
    "wof:name":"Eifelland-siesta Caravanes",
    "wof:placetype":"venue"
},
  "geometry": {"coordinates":[5.647465229,50.6922645569],"type":"Point"}
}