{
  "type": "Feature",
  "properties": {
    "iso:country":"BE",
    "sg:address":"Stationsstraat 49",
    "sg:city":"Sint-niklaas",
    "sg:orig_category":"Dameskledingzaken",
    "sg:phone":"+32 3 777 83 57",
    "sg:postcode":"9100",
    "sg:province":"Oost-Vlaanderen",
    "wof:name":"M&s Mode",
    "wof:placetype":"venue"
},
  "geometry": {"coordinates":[4.1419229507,51.1665763855],"type":"Point"}
}