{
  "type": "Feature",
  "properties": {
    "addr:full":"Reneubois 11 Herve Li\u00e8ge 4652",
    "addr:housenumber":"11",
    "addr:postcode":"4652",
    "addr:street":"Reneubois",
    "iso:country":"BE",
    "sg:address":"Reneubois 11",
    "sg:city":"Herve",
    "sg:orig_category":"Herstellingen and onderhoud van auto's",
    "sg:phone":"+32 87 67 50 53",
    "sg:postcode":"4652",
    "sg:province":"Li\u00e8ge",
    "wof:name":"Garage Charpentier",
    "wof:placetype":"venue"
},
  "geometry": {"coordinates":[5.7804818153,50.6042518616],"type":"Point"}
}