{
  "type": "Feature",
  "properties": {
    "iso:country":"BE",
    "sg:address":"Lisperstraat 109",
    "sg:city":"Lier",
    "sg:classifiers":[
        {
            "category":"Health Services",
            "subcategory":"Health Practitioner",
            "type":"Services"
        }
    ],
    "sg:phone":"+32 3 488 50 11",
    "sg:postcode":"2500",
    "sg:province":"Antwerpen",
    "sg:tags":[
        "physiotherapist"
    ],
    "wof:name":"Crets Frank",
    "wof:placetype":"venue"
},
  "geometry": {"coordinates":[4.5710191727,51.1344566345],"type":"Point"}
}