{
  "type": "Feature",
  "properties": {
    "addr:full":"Moerbeekstraat 12 Ichtegem West-Vlaanderen 8480",
    "addr:housenumber":"12",
    "addr:postcode":"8480",
    "addr:street":"Moerbeekstraat",
    "iso:country":"BE",
    "sg:address":"Moerbeekstraat 12",
    "sg:city":"Ichtegem",
    "sg:orig_category":"Varkenskwekers",
    "sg:phone":"+32 59 29 92 54",
    "sg:postcode":"8480",
    "sg:province":"West-Vlaanderen",
    "wof:name":"Rik Dewanckele",
    "wof:placetype":"venue"
},
  "geometry": {"coordinates":[2.998349905,51.1266975403],"type":"Point"}
}