{
  "type": "Feature",
  "properties": {
    "addr:full":"Toekomststraat 6 Oostkamp (hertsberge) West-Vlaanderen 8020",
    "addr:housenumber":"6",
    "addr:postcode":"8020",
    "addr:street":"Toekomststraat",
    "iso:country":"BE",
    "sg:address":"Toekomststraat 6",
    "sg:city":"Oostkamp (hertsberge)",
    "sg:classifiers":[
        {
            "category":"Health Services",
            "subcategory":"Health Practitioner",
            "type":"Services"
        }
    ],
    "sg:phone":"+32 50 27 85 67",
    "sg:postcode":"8020",
    "sg:province":"West-Vlaanderen",
    "sg:tags":[
        "physiotherapist"
    ],
    "wof:name":"Vanneste C",
    "wof:placetype":"venue"
},
  "geometry": {"coordinates":[3.2738521099,51.104385376],"type":"Point"}
}