{
  "type": "Feature",
  "properties": {
    "iso:country":"BE",
    "sg:address":"Nieuwstraat 2",
    "sg:city":"Buggenhout",
    "sg:orig_category":"Overheidsdiensten",
    "sg:phone":"+32 52 33 95 03",
    "sg:postcode":"9255",
    "sg:province":"Oost-Vlaanderen",
    "wof:name":"Gemeentebestuur",
    "wof:placetype":"venue"
},
  "geometry": {"coordinates":[4.2020750046,51.0151443481],"type":"Point"}
}