{
  "type": "Feature",
  "properties": {
    "iso:country":"BE",
    "sg:address":"Mariakerkelaan 190",
    "sg:city":"Oostende",
    "sg:orig_category":"Administration d'immeubles",
    "sg:phone":"+32 59 50 75 25",
    "sg:postcode":"8400",
    "sg:province":"West-Vlaanderen",
    "wof:name":"Sodiba",
    "wof:placetype":"venue"
},
  "geometry": {"coordinates":[2.9029068947,51.2119216919],"type":"Point"}
}