{
  "type": "Feature",
  "properties": {
    "addr:full":"Rue St Eloi 12 Waremme Li\u00e8ge 4300",
    "addr:housenumber":"12",
    "addr:postcode":"4300",
    "addr:street":"Rue St Eloi",
    "iso:country":"BE",
    "sg:address":"Rue St Eloi 12",
    "sg:city":"Waremme",
    "sg:orig_category":"Royal Canin. C\u00e9r\u00e9ales and aliments pour animaux Animaux domestiques and accessoires",
    "sg:phone":"+32 19 32 35 09",
    "sg:postcode":"4300",
    "sg:province":"Li\u00e8ge",
    "wof:name":"La Goujeonniere",
    "wof:placetype":"venue"
},
  "geometry": {"coordinates":[5.2661938667,50.6962394714],"type":"Point"}
}