{
  "type": "Feature",
  "properties": {
    "addr:full":"Steenweg Op Deinze 19 Aalter Oost-Vlaanderen 9880",
    "addr:housenumber":"19",
    "addr:postcode":"9880",
    "addr:street":"Steenweg Op Deinze",
    "iso:country":"BE",
    "sg:address":"Steenweg Op Deinze 19",
    "sg:city":"Aalter",
    "sg:classifiers":[
        {
            "category":"Building & Trades",
            "subcategory":"Electrical",
            "type":"Services"
        }
    ],
    "sg:phone":"+32 9 374 32 66",
    "sg:postcode":"9880",
    "sg:province":"Oost-Vlaanderen",
    "sg:tags":[
        "electric",
        "-",
        "housewiring",
        "contractor"
    ],
    "wof:name":"Sucaet E",
    "wof:placetype":"venue"
},
  "geometry": {"coordinates":[3.4529550076,51.0708122253],"type":"Point"}
}