{
  "type": "Feature",
  "properties": {
    "addr:full":"Industrieweg-noord 1182 Opglabbeek Limburg 3660",
    "addr:housenumber":"1182",
    "addr:postcode":"opglabbeek;3660",
    "iso:country":"BE",
    "sg:address":"Industrieweg-noord 1182",
    "sg:city":"Opglabbeek",
    "sg:classifiers":[
        {
            "category":"Utilities",
            "subcategory":"Mobile Phone",
            "type":"Services"
        }
    ],
    "sg:phone":"+32 89 85 58 90",
    "sg:postcode":"3660",
    "sg:province":"Limburg",
    "sg:tags":[
        "punching",
        "cnc"
    ],
    "wof:name":"Metra B.v.b.a.",
    "wof:placetype":"venue"
},
  "geometry": {"coordinates":[5.5556268692,51.0401229858],"type":"Point"}
}