{
  "type": "Feature",
  "properties": {
    "iso:country":"BE",
    "sg:address":"Rue Albert Ier 21",
    "sg:city":"Saint-georges-sur-meuse",
    "sg:orig_category":"Rundveehouders",
    "sg:phone":"+32 4 259 51 93",
    "sg:postcode":"4470",
    "sg:province":"Li\u00e8ge",
    "wof:name":"Marie Gendebien",
    "wof:placetype":"venue"
},
  "geometry": {"coordinates":[5.3560681343,50.6004219055],"type":"Point"}
}