{
  "type": "Feature",
  "properties": {
    "addr:full":"Baanstknokstraat 78 Waregem West-Vlaanderen 8790",
    "addr:housenumber":"78",
    "addr:postcode":"8790",
    "addr:street":"Baanstknokstraat",
    "iso:country":"BE",
    "sg:address":"Baanstknokstraat 78",
    "sg:city":"Waregem",
    "sg:orig_category":"Entretien and r\u00e9parations de voitures",
    "sg:phone":"+32 56 60 63 37",
    "sg:postcode":"8790",
    "sg:province":"West-Vlaanderen",
    "wof:name":"Christiaan Claeys",
    "wof:placetype":"venue"
},
  "geometry": {"coordinates":[3.4106431007,50.8921546936],"type":"Point"}
}