{
  "type": "Feature",
  "properties": {
    "iso:country":"BE",
    "sg:address":"Rue De L'ecole 27",
    "sg:city":"Brunehaut",
    "sg:orig_category":"Enseignement maternel and primaire",
    "sg:phone":"+32 69 34 61 70",
    "sg:postcode":"7620",
    "sg:province":"Hainaut",
    "wof:name":"Ecole Prim. Communale",
    "wof:placetype":"venue"
},
  "geometry": {"coordinates":[3.3927299976,50.5330581665],"type":"Point"}
}