{
  "type": "Feature",
  "properties": {
    "iso:country":"BE",
    "sg:address":"Rue De Fiennes 86",
    "sg:city":"Anderlecht/anderlecht",
    "sg:orig_category":"Jeux de hasard",
    "sg:phone":"+32 2 523 97 36",
    "sg:postcode":"1070",
    "sg:province":"Bruxelles-Capitale",
    "wof:name":"Tierc\u00c9 Franco-belge",
    "wof:placetype":"venue"
},
  "geometry": {"coordinates":[4.3307361603,50.8392333984],"type":"Point"}
}