{
  "type": "Feature",
  "properties": {
    "iso:country":"BE",
    "sg:address":"Chauss\u00c9e De Wavre 235",
    "sg:city":"Elsene/ixelles",
    "sg:orig_category":"Epiceries",
    "sg:phone":"+32 2 644 24 62",
    "sg:postcode":"1050",
    "sg:province":"Bruxelles-Capitale",
    "wof:name":"Ets. Libert D.",
    "wof:placetype":"venue"
},
  "geometry": {"coordinates":[4.3760280609,50.8356552124],"type":"Point"}
}