{
  "type": "Feature",
  "properties": {
    "addr:full":"Pastoorslindestraat 17 Box 4 Lanaken Limburg 3620",
    "addr:housenumber":"17;4",
    "addr:postcode":"3620",
    "addr:street":"Pastoorslindestraat;Box",
    "iso:country":"BE",
    "sg:address":"Pastoorslindestraat 17 Box 4",
    "sg:city":"Lanaken",
    "sg:classifiers":[
        {
            "category":"Arts & Performance",
            "subcategory":"Music",
            "type":"Entertainment"
        }
    ],
    "sg:phone":"+32 89 73 28 69",
    "sg:postcode":"3620",
    "sg:province":"Limburg",
    "sg:tags":[
        "disc-jockeys"
    ],
    "wof:name":"Willems Produkties",
    "wof:placetype":"venue"
},
  "geometry": {"coordinates":[5.6325478554,50.89087677],"type":"Point"}
}