{
  "type": "Feature",
  "properties": {
    "iso:country":"BE",
    "sg:address":"Kamiel Wautersstraat 9",
    "sg:city":"Temse",
    "sg:orig_category":"S\u00e9lection de personnel and placement",
    "sg:phone":"+32 3 710 13 63",
    "sg:postcode":"9140",
    "sg:province":"Oost-Vlaanderen",
    "wof:name":"Pwa Temse",
    "wof:placetype":"venue"
},
  "geometry": {"coordinates":[4.2142829895,51.1246681213],"type":"Point"}
}