{
  "type": "Feature",
  "properties": {
    "addr:full":"Wijnbergstraat 115 Wevelgem West-Vlaanderen 8560",
    "addr:housenumber":"115",
    "addr:postcode":"8560",
    "addr:street":"Wijnbergstraat",
    "iso:country":"BE",
    "sg:address":"Wijnbergstraat 115",
    "sg:city":"Wevelgem",
    "sg:orig_category":"Plaatsen van vloer- and muurbekleding Schilders",
    "sg:phone":"+32 56 40 20 77",
    "sg:postcode":"8560",
    "sg:province":"West-Vlaanderen",
    "wof:name":"Franck Rigolle",
    "wof:placetype":"venue"
},
  "geometry": {"coordinates":[3.1707110405,50.8190956116],"type":"Point"}
}