{
  "type": "Feature",
  "properties": {
    "iso:country":"BE",
    "sg:address":"Hoge Kaart 273",
    "sg:city":"Brasschaat",
    "sg:classifiers":[
        {
            "category":"Retail",
            "subcategory":"Repair Shop",
            "type":"Services"
        }
    ],
    "sg:phone":"+32 3 644 23 98",
    "sg:postcode":"2930",
    "sg:province":"Antwerpen",
    "sg:tags":[
        "car",
        "equipment"
    ],
    "wof:name":"Leda B.v.b.a.",
    "wof:placetype":"venue"
},
  "geometry": {"coordinates":[4.4943971634,51.3134002686],"type":"Point"}
}