{
  "type": "Feature",
  "properties": {
    "addr:full":"Leuvensesteenweg 353a Boutersem Vlaams-Brabant 3370",
    "addr:housenumber":"353a",
    "addr:postcode":"3370",
    "addr:street":"Leuvensesteenweg",
    "iso:country":"BE",
    "sg:address":"Leuvensesteenweg 353a",
    "sg:city":"Boutersem",
    "sg:classifiers":[
        {
            "category":"Fast Food",
            "type":"Food & Drink"
        }
    ],
    "sg:phone":"+32 16 73 40 25",
    "sg:postcode":"3370",
    "sg:province":"Vlaams-Brabant",
    "sg:tags":[
        "fried",
        "stand",
        "potato"
    ],
    "wof:name":"Sonia",
    "wof:placetype":"venue"
},
  "geometry": {"coordinates":[4.8352708817,50.841003418],"type":"Point"}
}