{
  "type": "Feature",
  "properties": {
    "addr:full":"Rue De La Montagne 12 Walcourt Namur 5650",
    "addr:housenumber":"12",
    "addr:postcode":"5650",
    "addr:street":"Rue De La Montagne",
    "iso:country":"BE",
    "sg:address":"Rue De La Montagne 12",
    "sg:city":"Walcourt",
    "sg:classifiers":[
        {
            "category":"Insurance",
            "subcategory":"Life Insurance",
            "type":"Services"
        }
    ],
    "sg:phone":"+32 71 61 15 62",
    "sg:postcode":"5650",
    "sg:province":"Namur",
    "sg:tags":[
        "assurance"
    ],
    "wof:name":"Werion J. P.",
    "wof:placetype":"venue"
},
  "geometry": {"coordinates":[4.4331622124,50.2537307739],"type":"Point"}
}