{
  "type": "Feature",
  "properties": {
    "iso:country":"BE",
    "sg:address":"Mont Saint-martin 17",
    "sg:city":"Li\u00c8ge",
    "sg:classifiers":[
        {
            "category":"Insurance",
            "subcategory":"Life Insurance",
            "type":"Services"
        }
    ],
    "sg:phone":"+32 4 223 22 83",
    "sg:postcode":"4000",
    "sg:province":"Li\u00e8ge",
    "sg:tags":[
        "assurance"
    ],
    "wof:name":"A. Ophoven",
    "wof:placetype":"venue"
},
  "geometry": {"coordinates":[5.5665869713,50.6446495056],"type":"Point"}
}