{
  "type": "Feature",
  "properties": {
    "addr:full":"Rue De L'ecluse 2 Beauvechain Brabant Wallon 1320",
    "addr:housenumber":"2",
    "addr:postcode":"1320",
    "addr:street":"Rue De L'Ecluse",
    "iso:country":"BE",
    "sg:address":"Rue De L'ecluse 2",
    "sg:city":"Beauvechain",
    "sg:orig_category":"Non-Classified Establishments",
    "sg:phone":"+32 10 81 83 60",
    "sg:postcode":"1320",
    "sg:province":"Brabant Wallon",
    "wof:name":"Parabolic Biologicals",
    "wof:placetype":"venue"
},
  "geometry": {"coordinates":[4.7696018219,50.7834472656],"type":"Point"}
}