{
  "type": "Feature",
  "properties": {
    "addr:full":"Aarschotsesteenweg 46 Rotselaar Vlaams-Brabant 3110",
    "addr:housenumber":"46",
    "addr:postcode":"3110",
    "addr:street":"Aarschotsesteenweg",
    "iso:country":"BE",
    "sg:address":"Aarschotsesteenweg 46",
    "sg:city":"Rotselaar",
    "sg:classifiers":[
        {
            "category":"Professional",
            "subcategory":"Testing Lab",
            "type":"Services"
        }
    ],
    "sg:phone":"+32 16 44 42 52",
    "sg:postcode":"3110",
    "sg:province":"Vlaams-Brabant",
    "sg:tags":[
        "chemist"
    ],
    "wof:name":"Libbrecht H",
    "wof:placetype":"venue"
},
  "geometry": {"coordinates":[4.741174221,50.9417076111],"type":"Point"}
}