{
  "type": "Feature",
  "properties": {
    "iso:country":"BE",
    "sg:address":"Langerloweg 57",
    "sg:city":"Genk",
    "sg:classifiers":[
        {
            "category":"Personal",
            "subcategory":"Beauty Salon",
            "type":"Services"
        }
    ],
    "sg:phone":"+32 89 30 30 84",
    "sg:postcode":"3600",
    "sg:province":"Limburg",
    "sg:tags":[
        "lady",
        "-",
        "hairdressing"
    ],
    "wof:name":"J P H P",
    "wof:placetype":"venue"
},
  "geometry": {"coordinates":[5.4972929955,50.949760437],"type":"Point"}
}