{
  "type": "Feature",
  "properties": {
    "addr:full":"Orbanlaan 209b13 Sint-pieters-woluwe Bruxelles-Capitale 1150",
    "addr:housenumber":"209b13",
    "addr:postcode":"1150",
    "addr:street":"Orbanlaan",
    "iso:country":"BE",
    "sg:address":"Orbanlaan 209b13",
    "sg:city":"Sint-pieters-woluwe",
    "sg:orig_category":"Industri\u00eble and commerci\u00eble bouw Woningbouw",
    "sg:phone":"+32 2 779 15 44",
    "sg:postcode":"1150",
    "sg:province":"Bruxelles-Capitale",
    "wof:name":"Orban Entreprises G\u00c9n\u00c9rales",
    "wof:placetype":"venue"
},
  "geometry": {"coordinates":[4.4634342194,50.8379592896],"type":"Point"}
}