{
  "type": "Feature",
  "properties": {
    "addr:full":"Rue Des Brasseries 54 Colfontaine (p\u00e2turages) Hainaut 7340",
    "addr:housenumber":"54",
    "addr:postcode":"7340",
    "addr:street":"Rue Des Brasseries",
    "iso:country":"BE",
    "sg:address":"Rue Des Brasseries 54",
    "sg:city":"Colfontaine (p\u00e2turages)",
    "sg:classifiers":[
        {
            "category":"Communications",
            "subcategory":"Radio Station",
            "type":"Services"
        }
    ],
    "sg:phone":"+32 65 67 79 03",
    "sg:postcode":"7340",
    "sg:province":"Hainaut",
    "sg:tags":[
        "local"
    ],
    "wof:name":"Radio-fraternit\u00e9",
    "wof:placetype":"venue"
},
  "geometry": {"coordinates":[3.86657691,50.4120445251],"type":"Point"}
}