{
  "type": "Feature",
  "properties": {
    "iso:country":"BE",
    "sg:address":"Acacialaan 97",
    "sg:city":"Herentals",
    "sg:classifiers":[
        {
            "category":"Building & Trades",
            "subcategory":"Construction",
            "type":"Services"
        }
    ],
    "sg:phone":"+32 14 21 19 08",
    "sg:postcode":"2200",
    "sg:province":"Antwerpen",
    "sg:tags":[
        "installation",
        "-",
        "central",
        "heating"
    ],
    "wof:name":"Van Hemelen P",
    "wof:placetype":"venue"
},
  "geometry": {"coordinates":[4.8359928131,51.1582717896],"type":"Point"}
}