{
  "type": "Feature",
  "properties": {
    "addr:full":"Avenue Rogier 308 Schaarbeek/schaerbeek Bruxelles-Capitale 1030",
    "addr:housenumber":"308",
    "addr:postcode":"1030",
    "addr:street":"Avenue Rogier",
    "iso:country":"BE",
    "sg:address":"Avenue Rogier 308",
    "sg:city":"Schaarbeek/schaerbeek",
    "sg:orig_category":"Avocats and conseillers juridiques",
    "sg:phone":"+32 2 242 61 66",
    "sg:postcode":"1030",
    "sg:province":"Bruxelles-Capitale",
    "wof:name":"Ph. Vanden Auweele",
    "wof:placetype":"venue"
},
  "geometry": {"coordinates":[4.3929982185,50.8562469482],"type":"Point"}
}