{
  "type": "Feature",
  "properties": {
    "addr:full":"Place Eug\u00e8ne Derbaix 22 Binche Hainaut 7130",
    "addr:housenumber":"22",
    "addr:postcode":"7130",
    "addr:street":"Place Euge\u0300Ne Derbaix",
    "iso:country":"BE",
    "sg:address":"Place Eug\u00e8ne Derbaix 22",
    "sg:city":"Binche",
    "sg:classifiers":[
        {
            "category":"Health Services",
            "subcategory":"Doctor",
            "type":"Services"
        }
    ],
    "sg:phone":"+32 64 33 28 03",
    "sg:postcode":"7130",
    "sg:province":"Hainaut",
    "sg:tags":[
        "medicinephysicians",
        "surgeon"
    ],
    "wof:name":"De Lanoit Eric",
    "wof:placetype":"venue"
},
  "geometry": {"coordinates":[4.1716599464,50.4090995789],"type":"Point"}
}