{
  "type": "Feature",
  "properties": {
    "addr:full":"Dorperberg 8 Maaseik (opoeteren) Limburg 3680",
    "addr:housenumber":"8",
    "addr:postcode":"3680",
    "addr:street":"Dorperberg",
    "iso:country":"BE",
    "sg:address":"Dorperberg 8",
    "sg:city":"Maaseik (opoeteren)",
    "sg:classifiers":[
        {
            "category":"Education",
            "subcategory":"Special Training",
            "type":"Public Place"
        }
    ],
    "sg:phone":"+32 89 86 88 59",
    "sg:postcode":"3680",
    "sg:province":"Limburg",
    "sg:tags":[
        "-",
        "processing",
        "data"
    ],
    "wof:name":"Goyens L",
    "wof:placetype":"venue"
},
  "geometry": {"coordinates":[5.791285038,51.0954208374],"type":"Point"}
}