{
  "type": "Feature",
  "properties": {
    "addr:full":"Donkerstraat 10 Bonheiden Antwerpen 2820",
    "addr:housenumber":"10",
    "addr:postcode":"2820",
    "addr:street":"Donkerstraat",
    "iso:country":"BE",
    "sg:address":"Donkerstraat 10",
    "sg:city":"Bonheiden",
    "sg:orig_category":"Producteurs de l\u00e9gumes",
    "sg:phone":"+32 15 51 15 69",
    "sg:postcode":"2820",
    "sg:province":"Antwerpen",
    "wof:name":"Renilda Geens",
    "wof:placetype":"venue"
},
  "geometry": {"coordinates":[4.5496602058,51.0218009949],"type":"Point"}
}