{
  "type": "Feature",
  "properties": {
    "addr:full":"Rue F. Letroye 16 Wavre Brabant Wallon 1300",
    "addr:housenumber":"16;1300",
    "addr:street":"Rue F. Letroye",
    "iso:country":"BE",
    "sg:address":"Rue F. Letroye 16",
    "sg:city":"Wavre",
    "sg:orig_category":"Cr\u00e9dits divers",
    "sg:postcode":"1300",
    "sg:province":"Brabant Wallon",
    "wof:name":"Postomat Wavre",
    "wof:placetype":"venue"
},
  "geometry": {"coordinates":[4.614522934,50.7147407532],"type":"Point"}
}