{
  "type": "Feature",
  "properties": {
    "addr:full":"Brederodestraat 26 Antwerpen Antwerpen 2018",
    "addr:housenumber":"26",
    "addr:postcode":"2018",
    "addr:street":"Brederodestraat",
    "iso:country":"BE",
    "sg:address":"Brederodestraat 26",
    "sg:city":"Antwerpen",
    "sg:orig_category":"Banques and organismes de cr\u00e9dit",
    "sg:phone":"+32 3 237 15 55",
    "sg:postcode":"2018",
    "sg:province":"Antwerpen",
    "wof:name":"Bacob",
    "wof:placetype":"venue"
},
  "geometry": {"coordinates":[4.3959970474,51.2058792114],"type":"Point"}
}