{
  "type": "Feature",
  "properties": {
    "iso:country":"BE",
    "sg:address":"Broekstraat 220",
    "sg:city":"Oudenaarde",
    "sg:orig_category":"Herstellingen and onderhoud van auto's",
    "sg:phone":"+32 55 31 73 42",
    "sg:postcode":"9700",
    "sg:province":"Oost-Vlaanderen",
    "wof:name":"Carrosserie Antonie",
    "wof:placetype":"venue"
},
  "geometry": {"coordinates":[3.6088500023,50.8561592102],"type":"Point"}
}