{
  "type": "Feature",
  "properties": {
    "addr:full":"Hompr\u00c9 6 Vaux-sur-s\u00dbre Luxembourg 6640",
    "addr:housenumber":"6",
    "addr:postcode":"6640",
    "addr:street":"Hompre\u0301",
    "iso:country":"BE",
    "sg:address":"Hompr\u00c9 6",
    "sg:city":"Vaux-sur-s\u00dbre",
    "sg:classifiers":[
        {
            "category":"Restaurant",
            "type":"Food & Drink"
        }
    ],
    "sg:phone":"+32 61 26 73 51",
    "sg:postcode":"6640",
    "sg:province":"Luxembourg",
    "wof:name":"Lac De La Strange",
    "wof:placetype":"venue"
},
  "geometry": {"coordinates":[5.5671000481,49.91065979],"type":"Point"}
}