{
  "type": "Feature",
  "properties": {
    "iso:country":"BE",
    "sg:address":"Rue De La Basse Marihaye 264",
    "sg:city":"Seraing",
    "sg:classifiers":[
        {
            "category":"Professional",
            "subcategory":"Accounting & Tax Preparation",
            "type":"Services"
        }
    ],
    "sg:phone":"+32 4 337 89 69",
    "sg:postcode":"4100",
    "sg:province":"Li\u00e8ge",
    "sg:tags":[
        "bookkeeper"
    ],
    "wof:name":"B.s.j.",
    "wof:placetype":"venue"
},
  "geometry": {"coordinates":[5.4927759171,50.6004638672],"type":"Point"}
}