{
  "type": "Feature",
  "properties": {
    "addr:full":"Kerkstraat 7 De Haan (wenduine) West-Vlaanderen 8420",
    "addr:housenumber":"7",
    "addr:postcode":"8420",
    "addr:street":"Kerkstraat",
    "iso:country":"BE",
    "sg:address":"Kerkstraat 7",
    "sg:city":"De Haan (wenduine)",
    "sg:classifiers":[
        {
            "category":"Professional",
            "subcategory":"Testing Lab",
            "type":"Services"
        }
    ],
    "sg:phone":"+32 50 41 18 46",
    "sg:postcode":"8420",
    "sg:province":"West-Vlaanderen",
    "sg:tags":[
        "chemist"
    ],
    "wof:name":"Waelkens J-p",
    "wof:placetype":"venue"
},
  "geometry": {"coordinates":[3.0792551041,51.3008422852],"type":"Point"}
}