{
  "type": "Feature",
  "properties": {
    "addr:full":"Zeldertstraat 9 Overpelt Limburg 3900",
    "addr:housenumber":"9",
    "addr:postcode":"3900",
    "addr:street":"Zeldertstraat",
    "iso:country":"BE",
    "sg:address":"Zeldertstraat 9",
    "sg:city":"Overpelt",
    "sg:classifiers":[
        {
            "category":"Arena",
            "subcategory":"Sports Club",
            "type":"Entertainment"
        }
    ],
    "sg:phone":"+32 11 64 94 98",
    "sg:postcode":"3900",
    "sg:province":"Limburg",
    "sg:tags":[
        "de"
    ],
    "wof:name":"De Bokkerijder Bc Fv",
    "wof:placetype":"venue"
},
  "geometry": {"coordinates":[5.4245018959,51.2169342041],"type":"Point"}
}