{
  "type": "Feature",
  "properties": {
    "addr:full":"Sint-anna 12a Hamme Oost-Vlaanderen 9220",
    "addr:housenumber":"12a",
    "addr:postcode":"9220",
    "addr:street":"Sint-Anna",
    "iso:country":"BE",
    "sg:address":"Sint-anna 12a",
    "sg:city":"Hamme",
    "sg:orig_category":"D\u00e9molition d\u00b4immeubles and terrassements. Ramassage and traitement des d\u00e9chets m\u00e9nagers",
    "sg:phone":"+32 52 47 72 59",
    "sg:postcode":"9220",
    "sg:province":"Oost-Vlaanderen",
    "wof:name":"Gebroeders Van Gaeveren",
    "wof:placetype":"venue"
},
  "geometry": {"coordinates":[4.0915188789,51.0947303772],"type":"Point"}
}