{
  "type": "Feature",
  "properties": {
    "addr:full":"Aarschotsesteenweg 224 Rotselaar (wezemaal) Vlaams-Brabant 3111",
    "addr:housenumber":"224",
    "addr:postcode":"3111",
    "addr:street":"Aarschotsesteenweg",
    "iso:country":"BE",
    "sg:address":"Aarschotsesteenweg 224",
    "sg:city":"Rotselaar (wezemaal)",
    "sg:classifiers":[
        {
            "category":"Autos & Motor Vehicles",
            "subcategory":"Automobile Sales",
            "type":"Retail Goods"
        }
    ],
    "sg:phone":"+32 16 58 24 24",
    "sg:postcode":"3111",
    "sg:province":"Vlaams-Brabant",
    "sg:tags":[
        "car",
        "used",
        "-"
    ],
    "wof:name":"Garage Segers Bvba",
    "wof:placetype":"venue"
},
  "geometry": {"coordinates":[4.7558479309,50.9503479004],"type":"Point"}
}