{
  "type": "Feature",
  "properties": {
    "iso:country":"BE",
    "sg:address":"Tuchthuisstraat 40",
    "sg:city":"Vilvoorde",
    "sg:orig_category":"Advocaten and juridische adviseurs",
    "sg:phone":"+32 2 253 34 65",
    "sg:postcode":"1800",
    "sg:province":"Vlaams-Brabant",
    "wof:name":"C. Rowe",
    "wof:placetype":"venue"
},
  "geometry": {"coordinates":[4.4240431786,50.925075531],"type":"Point"}
}