{
  "type": "Feature",
  "properties": {
    "iso:country":"BE",
    "sg:address":"Elizabetlaan 251",
    "sg:city":"Knokke-heist",
    "sg:orig_category":"Fleurs and plantes",
    "sg:phone":"+32 50 51 33 33",
    "sg:postcode":"8301",
    "sg:province":"West-Vlaanderen",
    "wof:name":"Lemahieu",
    "wof:placetype":"venue"
},
  "geometry": {"coordinates":[3.2665710449,51.3431243896],"type":"Point"}
}