{
  "type": "Feature",
  "properties": {
    "iso:country":"BE",
    "sg:address":"Rue Adolphe Doneux 50",
    "sg:city":"Eghez\u00e9e (bolinne)",
    "sg:classifiers":[
        {
            "category":"Professional",
            "subcategory":"Computer Services",
            "type":"Services"
        }
    ],
    "sg:phone":"+32 81 81 23 64",
    "sg:postcode":"5310",
    "sg:province":"Namur",
    "sg:tags":[
        "-",
        "processing",
        "data",
        "software"
    ],
    "wof:name":"Henry Pierre Ets",
    "wof:placetype":"venue"
},
  "geometry": {"coordinates":[4.9310779572,50.6003074646],"type":"Point"}
}