{
  "type": "Feature",
  "properties": {
    "iso:country":"BE",
    "sg:address":"Molsesteenweg 83",
    "sg:city":"Balen",
    "sg:orig_category":"Syst\u00e8mes de t\u00e9l\u00e9communications",
    "sg:phone":"+32 14 81 51 01",
    "sg:postcode":"2490",
    "sg:province":"Antwerpen",
    "wof:name":"Cts",
    "wof:placetype":"venue"
},
  "geometry": {"coordinates":[5.1429018974,51.1736068726],"type":"Point"}
}