{
  "type": "Feature",
  "properties": {
    "addr:full":"Kapucijnenvoer 217 Leuven Vlaams-Brabant 3000",
    "addr:housenumber":"217",
    "addr:postcode":"3000",
    "addr:street":"Kapucijnenvoer",
    "iso:country":"BE",
    "sg:address":"Kapucijnenvoer 217",
    "sg:city":"Leuven",
    "sg:orig_category":"Produits surgel\u00e9s Gr",
    "sg:phone":"+32 16 23 72 78",
    "sg:postcode":"3000",
    "sg:province":"Vlaams-Brabant",
    "wof:name":"Christine Perdieus",
    "wof:placetype":"venue"
},
  "geometry": {"coordinates":[4.6915540695,50.8735313416],"type":"Point"}
}