{
  "type": "Feature",
  "properties": {
    "iso:country":"BE",
    "sg:address":"Stoomtuigstraat 6",
    "sg:city":"Hooglede",
    "sg:orig_category":"Ordinateurs and \u00e9quipement informatique. R\u00e9alisation de programmes and logiciels",
    "sg:phone":"+32 51 24 87 42",
    "sg:postcode":"8830",
    "sg:province":"West-Vlaanderen",
    "wof:name":"Element",
    "wof:placetype":"venue"
},
  "geometry": {"coordinates":[3.1200199127,50.9833641052],"type":"Point"}
}