{
  "type": "Feature",
  "properties": {
    "iso:country":"BE",
    "sg:address":"Molderdijk 51",
    "sg:city":"Mol",
    "sg:classifiers":[
        {
            "category":"Social Services",
            "subcategory":"Child Care",
            "type":"Services"
        }
    ],
    "sg:phone":"+32 14 31 77 44",
    "sg:postcode":"2400",
    "sg:province":"Antwerpen",
    "sg:tags":[
        "baby",
        "nursery",
        "day",
        "sitting"
    ],
    "wof:name":"Krekeltje('t)",
    "wof:placetype":"venue"
},
  "geometry": {"coordinates":[5.1174788475,51.1829185486],"type":"Point"}
}