{
  "type": "Feature",
  "properties": {
    "addr:full":"Molenstraat 227 Lokeren Oost-Vlaanderen 9160",
    "addr:housenumber":"227",
    "addr:postcode":"9160",
    "addr:street":"Molenstraat",
    "iso:country":"BE",
    "sg:address":"Molenstraat 227",
    "sg:city":"Lokeren",
    "sg:classifiers":[
        {
            "category":"Wholesale",
            "subcategory":"Fruits & Vegetables",
            "type":"Manufacturing & Wholesale Goods"
        }
    ],
    "sg:phone":"+32 9 339 02 59",
    "sg:postcode":"9160",
    "sg:province":"Oost-Vlaanderen",
    "sg:tags":[
        "whol",
        "-"
    ],
    "wof:name":"De Heyn",
    "wof:placetype":"venue"
},
  "geometry": {"coordinates":[3.9975030422,51.0986442566],"type":"Point"}
}