{
  "type": "Feature",
  "properties": {
    "addr:full":"Edisonlaan 6 Wavre Brabant Wallon 1300",
    "addr:housenumber":"6;1300",
    "addr:street":"Edisonlaan",
    "iso:country":"BE",
    "sg:address":"Edisonlaan 6",
    "sg:city":"Wavre",
    "sg:orig_category":"Etalage- and showroomontwerpers Kantoor- and winkelmeubelen Fab Organisatie van beurzen, congressen ",
    "sg:phone":"+32 10 24 27 77",
    "sg:postcode":"1300",
    "sg:province":"Brabant Wallon",
    "wof:name":"Conceptexpo Project",
    "wof:placetype":"venue"
},
  "geometry": {"coordinates":[4.6116552353,50.7134132385],"type":"Point"}
}