{
  "type": "Feature",
  "properties": {
    "addr:full":"Vaartstraat 8 Leuven Vlaams-Brabant 3000",
    "addr:housenumber":"8",
    "addr:postcode":"3000",
    "addr:street":"Vaartstraat",
    "iso:country":"BE",
    "sg:address":"Vaartstraat 8",
    "sg:city":"Leuven",
    "sg:classifiers":[
        {
            "category":"Shopping",
            "subcategory":"Clothing, Apparel, & Fashions",
            "type":"Retail Goods"
        }
    ],
    "sg:phone":"+32 16 58 45 84",
    "sg:postcode":"3000",
    "sg:province":"Vlaams-Brabant",
    "sg:tags":[
        "boutique"
    ],
    "wof:name":"Anna",
    "wof:placetype":"venue"
},
  "geometry": {"coordinates":[4.7032442093,50.8802490234],"type":"Point"}
}