{
  "type": "Feature",
  "properties": {
    "addr:full":"Kapellensteenweg 247 Kalmthout Antwerpen 2920",
    "addr:housenumber":"247",
    "addr:postcode":"2920",
    "addr:street":"Kapellensteenweg",
    "iso:country":"BE",
    "sg:address":"Kapellensteenweg 247",
    "sg:city":"Kalmthout",
    "sg:orig_category":"Baby- and kinderkleding Dameskledingzaken Herenkledingzaken",
    "sg:phone":"+32 3 666 83 62",
    "sg:postcode":"2920",
    "sg:province":"Antwerpen",
    "wof:name":"Modecenter Rommens",
    "wof:placetype":"venue"
},
  "geometry": {"coordinates":[4.4749059677,51.3785362244],"type":"Point"}
}