{
  "type": "Feature",
  "properties": {
    "addr:full":"Munthofstraat 167 Sint-gillis/saint-gilles Bruxelles-Capitale 1060",
    "addr:housenumber":"167",
    "addr:postcode":"1060",
    "addr:street":"Munthofstraat",
    "iso:country":"BE",
    "sg:address":"Munthofstraat 167",
    "sg:city":"Sint-gillis/saint-gilles",
    "sg:orig_category":"Plaatsen van vloer- and muurbekleding Schilders",
    "sg:phone":"+32 2 538 24 58",
    "sg:postcode":"1060",
    "sg:province":"Bruxelles-Capitale",
    "wof:name":"Art Mural",
    "wof:placetype":"venue"
},
  "geometry": {"coordinates":[4.3452048302,50.8277015686],"type":"Point"}
}