{
  "type": "Feature",
  "properties": {
    "iso:country":"BE",
    "sg:address":"Troonplaats 4",
    "sg:city":"Antwerpen",
    "sg:classifiers":[
        {
            "category":"Manufacturing",
            "subcategory":"Furniture",
            "type":"Manufacturing & Wholesale Goods"
        }
    ],
    "sg:phone":"+32 3 289 02 36",
    "sg:postcode":"2018",
    "sg:province":"Antwerpen",
    "sg:tags":[
        "made",
        "-",
        "custom"
    ],
    "wof:name":"Braat D",
    "wof:placetype":"venue"
},
  "geometry": {"coordinates":[4.392250061,51.2033195496],"type":"Point"}
}