{
  "type": "Feature",
  "properties": {
    "iso:country":"BE",
    "sg:address":"Route De L'etat 82",
    "sg:city":"Villers-la-tour",
    "sg:classifiers":[
        {
            "category":"Building & Trades",
            "subcategory":"Landscaping Services",
            "type":"Services"
        }
    ],
    "sg:phone":"+32 60 21 12 68",
    "sg:postcode":"6460",
    "sg:province":"Hainaut",
    "sg:tags":[
        "earth",
        "moving"
    ],
    "wof:name":"Les Entretreprises Jules Delid S.p.r.l.",
    "wof:placetype":"venue"
},
  "geometry": {"coordinates":[4.2641019821,50.027256012],"type":"Point"}
}