{
  "type": "Feature",
  "properties": {
    "addr:full":"Meensesteenweg 66 Kortrijk West-Vlaanderen 8500",
    "addr:housenumber":"66",
    "addr:postcode":"8500",
    "addr:street":"Meensesteenweg",
    "iso:country":"BE",
    "sg:address":"Meensesteenweg 66",
    "sg:city":"Kortrijk",
    "sg:classifiers":[
        {
            "category":"Military Area",
            "subcategory":"Air Force Base",
            "type":"Public Place"
        }
    ],
    "sg:phone":"+32 56 37 42 56",
    "sg:postcode":"8500",
    "sg:province":"West-Vlaanderen",
    "sg:tags":[
        "commerce",
        "gr",
        "equipement",
        "de",
        "\u00e9v\u00e9nements",
        "pour",
        "diver",
        "mat\u00e9riel",
        "location",
        "banquet"
    ],
    "wof:name":"Fa. Remmerie F. & C.",
    "wof:placetype":"venue"
},
  "geometry": {"coordinates":[3.250385046,50.8302459717],"type":"Point"}
}