{
  "type": "Feature",
  "properties": {
    "iso:country":"BE",
    "sg:address":"Rue Wattimez Haut 65",
    "sg:city":"Les Bons Villers (r\u00eaves)",
    "sg:classifiers":[
        {
            "category":"Health Services",
            "subcategory":"Medical Lab",
            "type":"Services"
        }
    ],
    "sg:phone":"+32 71 84 59 76",
    "sg:postcode":"6210",
    "sg:province":"Hainaut",
    "sg:tags":[
        "laboratory",
        "study",
        "-",
        "installation"
    ],
    "wof:name":"High Technology Services",
    "wof:placetype":"venue"
},
  "geometry": {"coordinates":[4.484855175,50.5268325806],"type":"Point"}
}