{
  "type": "Feature",
  "properties": {
    "iso:country":"BE",
    "sg:address":"Hamontweg 110",
    "sg:city":"Maaseik",
    "sg:orig_category":"Brood, gebak and snoepgoed",
    "sg:phone":"+32 89 56 41 76",
    "sg:postcode":"3680",
    "sg:province":"Limburg",
    "wof:name":"Frank Pernot",
    "wof:placetype":"venue"
},
  "geometry": {"coordinates":[5.8051099777,51.1023139954],"type":"Point"}
}