{
  "type": "Feature",
  "properties": {
    "addr:full":"Leuvensesteenweg 19 Tervuren Vlaams-Brabant 3080",
    "addr:housenumber":"19",
    "addr:postcode":"3080",
    "addr:street":"Leuvensesteenweg",
    "iso:country":"BE",
    "sg:address":"Leuvensesteenweg 19",
    "sg:city":"Tervuren",
    "sg:classifiers":[
        {
            "category":"Education",
            "subcategory":"School",
            "type":"Public Place"
        }
    ],
    "sg:phone":"+32 2 766 04 30",
    "sg:postcode":"3080",
    "sg:province":"Vlaams-Brabant",
    "sg:tags":[
        "-",
        "private"
    ],
    "wof:name":"The British School Of Brussels",
    "wof:placetype":"venue"
},
  "geometry": {"coordinates":[4.5183181763,50.8311347961],"type":"Point"}
}