{
  "type": "Feature",
  "properties": {
    "addr:full":"Naamsesteenweg 13 Sint-truiden Limburg 3800",
    "addr:housenumber":"13",
    "addr:postcode":"3800",
    "addr:street":"Naamsesteenweg",
    "iso:country":"BE",
    "sg:address":"Naamsesteenweg 13",
    "sg:city":"Sint-truiden",
    "sg:classifiers":[
        {
            "category":"Personal",
            "subcategory":"Beauty Salon",
            "type":"Services"
        }
    ],
    "sg:phone":"+32 11 68 77 33",
    "sg:postcode":"3800",
    "sg:province":"Limburg",
    "sg:tags":[
        "de",
        "coiffure"
    ],
    "wof:name":"Jeannine Knaepen",
    "wof:placetype":"venue"
},
  "geometry": {"coordinates":[5.1841721535,50.812713623],"type":"Point"}
}