{
  "type": "Feature",
  "properties": {
    "addr:full":"Lariksenlaan 52 Oostende West-Vlaanderen 8400",
    "addr:housenumber":"52",
    "addr:postcode":"8400",
    "addr:street":"Lariksenlaan",
    "iso:country":"BE",
    "sg:address":"Lariksenlaan 52",
    "sg:city":"Oostende",
    "sg:classifiers":[
        {
            "category":"Health Services",
            "subcategory":"Health Practitioner",
            "type":"Services"
        }
    ],
    "sg:phone":"+32 59 50 37 33",
    "sg:postcode":"8400",
    "sg:province":"West-Vlaanderen",
    "sg:tags":[
        "physiotherapist"
    ],
    "wof:name":"Van Acker Paul",
    "wof:placetype":"venue"
},
  "geometry": {"coordinates":[2.9016470909,51.2106399536],"type":"Point"}
}