{
  "type": "Feature",
  "properties": {
    "addr:full":"Boulevard Dolez 45 Mons Hainaut 7000",
    "addr:housenumber":"45",
    "addr:postcode":"7000",
    "addr:street":"Boulevard Dolez;Hainaut",
    "iso:country":"BE",
    "sg:address":"Boulevard Dolez 45",
    "sg:city":"Mons",
    "sg:orig_category":"Beveiligingsdiensten and bewakingsbedrijven Industri\u00eble elektrische installaties",
    "sg:phone":"+32 65 34 83 40",
    "sg:postcode":"7000",
    "sg:province":"Hainaut",
    "wof:name":"Eagle Security Intern.",
    "wof:placetype":"venue"
},
  "geometry": {"coordinates":[3.958053112,50.450843811],"type":"Point"}
}