{
  "type": "Feature",
  "properties": {
    "iso:country":"BE",
    "sg:address":"Boslaan 1",
    "sg:city":"Dilbeek",
    "sg:orig_category":"Ordinateurs and \u00e9quipement informatique",
    "sg:phone":"+32 2 466 52 20",
    "sg:postcode":"1700",
    "sg:province":"Vlaams-Brabant",
    "wof:name":"Papelo",
    "wof:placetype":"venue"
},
  "geometry": {"coordinates":[4.2377300262,50.8712081909],"type":"Point"}
}