{
  "type": "Feature",
  "properties": {
    "addr:full":"Hoogstraat 118 Niel-bij-as Limburg 3668",
    "addr:housenumber":"118",
    "addr:postcode":"3668",
    "addr:street":"Hoogstraat;Limburg",
    "iso:country":"BE",
    "sg:address":"Hoogstraat 118",
    "sg:city":"Niel-bij-as",
    "sg:classifiers":[
        {
            "category":"Shopping",
            "subcategory":"Bicycles & Sporting Goods",
            "type":"Retail Goods"
        }
    ],
    "sg:phone":"+32 89 75 13 61",
    "sg:postcode":"3668",
    "sg:province":"Limburg",
    "sg:tags":[
        "-"
    ],
    "wof:name":"Rubelli-sport",
    "wof:placetype":"venue"
},
  "geometry": {"coordinates":[5.6011309624,51.01537323],"type":"Point"}
}