{
  "type": "Feature",
  "properties": {
    "iso:country":"BE",
    "sg:address":"Malmedyer Strasse 74",
    "sg:city":"Sankt Vith",
    "sg:classifiers":[
        {
            "category":"Professional",
            "subcategory":"Credit Reporting & Collection",
            "type":"Services"
        }
    ],
    "sg:phone":"+32 80 22 83 45",
    "sg:postcode":"4780",
    "sg:province":"Li\u00e8ge",
    "sg:tags":[
        "bailiff"
    ],
    "wof:name":"Thannen H",
    "wof:placetype":"venue"
},
  "geometry": {"coordinates":[6.1200828552,50.2867622375],"type":"Point"}
}