{
  "type": "Feature",
  "properties": {
    "addr:full":"Rue De Namur 143 Binche Hainaut 7134",
    "addr:housenumber":"143",
    "addr:postcode":"7134",
    "addr:street":"Rue De Namur",
    "iso:country":"BE",
    "sg:address":"Rue De Namur 143",
    "sg:city":"Binche",
    "sg:classifiers":[
        {
            "category":"Insurance",
            "subcategory":"Insurance Agent",
            "type":"Services"
        }
    ],
    "sg:phone":"+32 64 33 01 57",
    "sg:postcode":"7134",
    "sg:province":"Hainaut",
    "sg:tags":[
        "verzekeringsmakelaars",
        "expert"
    ],
    "wof:name":"Europ \u00b4assur",
    "wof:placetype":"venue"
},
  "geometry": {"coordinates":[4.2081799507,50.4274215698],"type":"Point"}
}