{
  "type": "Feature",
  "properties": {
    "addr:full":"Chemin Fontaine-l'eveque 19 Nivelles Brabant Wallon 1400",
    "addr:housenumber":"19",
    "addr:postcode":"1400",
    "addr:street":"Chemin Fontaine-L'Eveque",
    "iso:country":"BE",
    "sg:address":"Chemin Fontaine-l'eveque 19",
    "sg:city":"Nivelles",
    "sg:orig_category":"Pharmaciens",
    "sg:phone":"+32 67 21 26 18",
    "sg:postcode":"1400",
    "sg:province":"Brabant Wallon",
    "wof:name":"Marie-christine Myttenaere",
    "wof:placetype":"venue"
},
  "geometry": {"coordinates":[4.3162198067,50.5851097107],"type":"Point"}
}