{
  "type": "Feature",
  "properties": {
    "addr:full":"Dokter De Witteplein 0 Dendermonde Oost-Vlaanderen 9200",
    "addr:housenumber":"0",
    "addr:postcode":"9200",
    "addr:street":"Dokter De Witteplein;Oost-Vlaanderen",
    "iso:country":"BE",
    "sg:address":"Dokter De Witteplein 0",
    "sg:city":"Dendermonde",
    "sg:orig_category":"Enseignement maternel and primaire",
    "sg:phone":"+32 52 21 31 30",
    "sg:postcode":"9200",
    "sg:province":"Oost-Vlaanderen",
    "wof:name":"Vrije Kleuterschool",
    "wof:placetype":"venue"
},
  "geometry": {"coordinates":[4.1126728058,51.0150718689],"type":"Point"}
}