{
  "type": "Feature",
  "properties": {
    "iso:country":"BE",
    "sg:address":"Rue De Dison 36",
    "sg:city":"Verviers",
    "sg:orig_category":"Plomberie, chauffage and installations sanitaires. Mat\u00e9riaux de construction Gr",
    "sg:phone":"+32 87 33 13 69",
    "sg:postcode":"4800",
    "sg:province":"Li\u00e8ge",
    "wof:name":"F. Claessens & Fils",
    "wof:placetype":"venue"
},
  "geometry": {"coordinates":[5.8594508171,50.5917663574],"type":"Point"}
}