{
  "type": "Feature",
  "properties": {
    "iso:country":"BE",
    "sg:address":"Rue Max Lambert 9",
    "sg:city":"Charleroi (marchienne-au-pont)",
    "sg:classifiers":[
        {
            "category":"Government",
            "subcategory":"Fire Station",
            "type":"Public Place"
        }
    ],
    "sg:phone":"+32 71 51 80 65",
    "sg:postcode":"6030",
    "sg:province":"Hainaut",
    "sg:tags":[
        "installation",
        "-",
        "air conditioning"
    ],
    "wof:name":"Plasolux",
    "wof:placetype":"venue"
},
  "geometry": {"coordinates":[4.3920049667,50.3985939026],"type":"Point"}
}