{
  "type": "Feature",
  "properties": {
    "addr:full":"Pastoor Paquaylaan 23 Heusden-zolder (heusden) Limburg 3550",
    "addr:housenumber":"23",
    "addr:postcode":"3550",
    "addr:street":"Pastoor Paquaylaan",
    "iso:country":"BE",
    "sg:address":"Pastoor Paquaylaan 23",
    "sg:city":"Heusden-zolder (heusden)",
    "sg:classifiers":[
        {
            "category":"Shopping",
            "subcategory":"Musical Instruments",
            "type":"Retail Goods"
        }
    ],
    "sg:phone":"+32 11 57 24 72",
    "sg:postcode":"3550",
    "sg:province":"Limburg",
    "sg:tags":[
        "-"
    ],
    "wof:name":"Opsteyn H",
    "wof:placetype":"venue"
},
  "geometry": {"coordinates":[5.302216053,51.0422286987],"type":"Point"}
}