{
  "type": "Feature",
  "properties": {
    "addr:full":"Itegemseweg 88 Heist-op-den-berg (wiekevorst) Antwerpen 2222",
    "addr:housenumber":"88",
    "addr:postcode":"2222",
    "addr:street":"Itegemseweg",
    "iso:country":"BE",
    "sg:address":"Itegemseweg 88",
    "sg:city":"Heist-op-den-berg (wiekevorst)",
    "sg:classifiers":[
        {
            "category":"Structure",
            "subcategory":"Bridge",
            "type":"Public Place"
        }
    ],
    "sg:phone":"+32 14 26 59 05",
    "sg:postcode":"2222",
    "sg:province":"Antwerpen",
    "sg:tags":[
        "sanitary",
        "cabin",
        "unit"
    ],
    "wof:name":"Daneels",
    "wof:placetype":"venue"
},
  "geometry": {"coordinates":[4.7292399406,51.1032218933],"type":"Point"}
}