{
  "type": "Feature",
  "properties": {
    "addr:full":"Brugsesteenweg 157-159 Kuurne West-Vlaanderen 8520",
    "addr:housenumber":"157-159",
    "addr:postcode":"8520",
    "addr:street":"Brugsesteenweg",
    "iso:country":"BE",
    "sg:address":"Brugsesteenweg 157-159",
    "sg:city":"Kuurne",
    "sg:orig_category":"Winkelinrichting and handelsuitrusting Gh",
    "sg:phone":"+32 56 35 45 55",
    "sg:postcode":"8520",
    "sg:province":"West-Vlaanderen",
    "wof:name":"Verhaeghe",
    "wof:placetype":"venue"
},
  "geometry": {"coordinates":[3.2698619366,50.8541297913],"type":"Point"}
}