{
  "type": "Feature",
  "properties": {
    "iso:country":"BE",
    "sg:address":"Groenstraat 21 Box 3",
    "sg:city":"De Pinte",
    "sg:classifiers":[
        {
            "category":"Banks & Credit Unions",
            "subcategory":"Investment Brokerage",
            "type":"Services"
        }
    ],
    "sg:phone":"+32 9 281 21 14",
    "sg:postcode":"9840",
    "sg:province":"Oost-Vlaanderen",
    "sg:tags":[
        "printing",
        "-"
    ],
    "wof:name":"Speybroeck G",
    "wof:placetype":"venue"
},
  "geometry": {"coordinates":[3.6457169056,50.9938392639],"type":"Point"}
}