{
  "type": "Feature",
  "properties": {
    "addr:full":"Marktplein 17 Neerpelt Limburg 3910",
    "addr:housenumber":"17",
    "addr:postcode":"3910",
    "addr:street":"Marktplein",
    "iso:country":"BE",
    "sg:address":"Marktplein 17",
    "sg:city":"Neerpelt",
    "sg:orig_category":"Agences d\u00b4interim and personnel temporaire",
    "sg:phone":"+32 11 66 61 46",
    "sg:postcode":"3910",
    "sg:province":"Limburg",
    "wof:name":"Asb Interim",
    "wof:placetype":"venue"
},
  "geometry": {"coordinates":[5.4314889908,51.2290344238],"type":"Point"}
}