{
  "type": "Feature",
  "properties": {
    "iso:country":"BE",
    "sg:address":"Universiteitslaan 19",
    "sg:city":"Kortrijk",
    "sg:orig_category":"M\u00e9decins and sp\u00e9cialistes",
    "sg:phone":"+32 56 20 39 33",
    "sg:postcode":"8500",
    "sg:province":"West-Vlaanderen",
    "wof:name":"Johan Colpaert",
    "wof:placetype":"venue"
},
  "geometry": {"coordinates":[3.2848660946,50.807964325],"type":"Point"}
}