{
  "type": "Feature",
  "properties": {
    "addr:full":"Ooststraat 37 Veurne West-Vlaanderen 8630",
    "addr:housenumber":"37",
    "addr:postcode":"8630",
    "addr:street":"Ooststraat",
    "iso:country":"BE",
    "sg:address":"Ooststraat 37",
    "sg:city":"Veurne",
    "sg:orig_category":"V\u00eatements",
    "sg:phone":"+32 58 31 17 30",
    "sg:postcode":"8630",
    "sg:province":"West-Vlaanderen",
    "wof:name":"Fa. Hermine",
    "wof:placetype":"venue"
},
  "geometry": {"coordinates":[2.6650929451,51.072719574],"type":"Point"}
}