{
  "type": "Feature",
  "properties": {
    "addr:full":"Kuurnsestraat 59 Harelbeke (hulste) West-Vlaanderen 8531",
    "addr:housenumber":"59",
    "addr:postcode":"8531",
    "addr:street":"Kuurnsestraat",
    "iso:country":"BE",
    "sg:address":"Kuurnsestraat 59",
    "sg:city":"Harelbeke (hulste)",
    "sg:classifiers":[
        {
            "category":"Fast Food",
            "type":"Food & Drink"
        }
    ],
    "sg:phone":"+32 56 72 52 90",
    "sg:postcode":"8531",
    "sg:province":"West-Vlaanderen",
    "sg:tags":[
        "fried",
        "stand",
        "potato"
    ],
    "wof:name":"Sleewaert N",
    "wof:placetype":"venue"
},
  "geometry": {"coordinates":[3.2970221043,50.8775558472],"type":"Point"}
}