{
  "type": "Feature",
  "properties": {
    "addr:full":"Rederijkersstraat 7 Wevelgem West-Vlaanderen 8560",
    "addr:housenumber":"7",
    "addr:postcode":"8560",
    "addr:street":"Rederijkersstraat",
    "iso:country":"BE",
    "sg:address":"Rederijkersstraat 7",
    "sg:city":"Wevelgem",
    "sg:orig_category":"Kapsalons",
    "sg:phone":"+32 56 41 40 22",
    "sg:postcode":"8560",
    "sg:province":"West-Vlaanderen",
    "wof:name":"Coiffure Martine",
    "wof:placetype":"venue"
},
  "geometry": {"coordinates":[3.200824976,50.8431816101],"type":"Point"}
}