{
  "type": "Feature",
  "properties": {
    "addr:full":"Kloosterpoort 8 Peer Limburg 3990",
    "addr:housenumber":"8",
    "addr:postcode":"3990",
    "addr:street":"Kloosterpoort",
    "iso:country":"BE",
    "sg:address":"Kloosterpoort 8",
    "sg:city":"Peer",
    "sg:orig_category":"Alternatieve geneeskunde Rundveehouders",
    "sg:phone":"+32 11 63 37 89",
    "sg:postcode":"3990",
    "sg:province":"Limburg",
    "wof:name":"Lutgart Vanderlocht",
    "wof:placetype":"venue"
},
  "geometry": {"coordinates":[5.4536480904,51.1283493042],"type":"Point"}
}