{
  "type": "Feature",
  "properties": {
    "iso:country":"BE",
    "sg:address":"Rue Albert-marchal 6",
    "sg:city":"Gedinne",
    "sg:orig_category":"Brood, gebak and snoepgoed",
    "sg:phone":"+32 61 58 95 00",
    "sg:postcode":"5575",
    "sg:province":"Namur",
    "wof:name":"Jean-luc Baijot",
    "wof:placetype":"venue"
},
  "geometry": {"coordinates":[4.9364190102,49.9808044434],"type":"Point"}
}