{
  "type": "Feature",
  "properties": {
    "addr:full":"Leeuwerikstraat 55 Mol Antwerpen 2400",
    "addr:housenumber":"55",
    "addr:postcode":"2400",
    "addr:street":"Leeuwerikstraat",
    "iso:country":"BE",
    "sg:address":"Leeuwerikstraat 55",
    "sg:city":"Mol",
    "sg:classifiers":[
        {
            "category":"Health Services",
            "subcategory":"Dentist",
            "type":"Services"
        }
    ],
    "sg:phone":"+32 14 31 48 38",
    "sg:postcode":"2400",
    "sg:province":"Antwerpen",
    "wof:name":"Wijnants P",
    "wof:placetype":"venue"
},
  "geometry": {"coordinates":[5.0860199928,51.1877632141],"type":"Point"}
}