{
  "type": "Feature",
  "properties": {
    "iso:country":"BE",
    "sg:address":"Chemin De Bas Ransbeck 50a",
    "sg:city":"Lasne (ohain)",
    "sg:classifiers":[
        {
            "category":"Professional",
            "subcategory":"Accounting & Tax Preparation",
            "type":"Services"
        }
    ],
    "sg:phone":"+32 2 354 18 47",
    "sg:postcode":"1380",
    "sg:province":"Brabant Wallon",
    "sg:tags":[
        "bookkeeper"
    ],
    "wof:name":"Godefroi C",
    "wof:placetype":"venue"
},
  "geometry": {"coordinates":[4.4470047951,50.7060813904],"type":"Point"}
}