{
  "type": "Feature",
  "properties": {
    "iso:country":"BE",
    "sg:address":"Ringshoppingcenter 213b",
    "sg:city":"Kortrijk",
    "sg:classifiers":[
        {
            "category":"Shopping",
            "subcategory":"Clothing, Apparel, & Fashions",
            "type":"Retail Goods"
        }
    ],
    "sg:phone":"+32 56 35 07 79",
    "sg:postcode":"8500",
    "sg:province":"West-Vlaanderen",
    "sg:tags":[
        "-",
        "clothing",
        "child"
    ],
    "wof:name":"Junior Style",
    "wof:placetype":"venue"
},
  "geometry": {"coordinates":[3.2650549412,50.827999115],"type":"Point"}
}