{
  "type": "Feature",
  "properties": {
    "addr:full":"Theo De Belderlaan 5 Zandhoven Antwerpen 2240",
    "addr:housenumber":"5",
    "addr:postcode":"2240",
    "addr:street":"Theo De Belderlaan",
    "iso:country":"BE",
    "sg:address":"Theo De Belderlaan 5",
    "sg:city":"Zandhoven",
    "sg:orig_category":"Kapsalons",
    "sg:phone":"+32 3 484 47 10",
    "sg:postcode":"2240",
    "sg:province":"Antwerpen",
    "wof:name":"Christ Van De Peer",
    "wof:placetype":"venue"
},
  "geometry": {"coordinates":[4.6870250702,51.2315216064],"type":"Point"}
}