{
  "type": "Feature",
  "properties": {
    "iso:country":"BE",
    "sg:address":"Rue Haas 63",
    "sg:city":"Eupen",
    "sg:classifiers":[
        {
            "category":"Restaurant",
            "type":"Food & Drink"
        }
    ],
    "sg:phone":"+32 87 55 31 27",
    "sg:postcode":"4700",
    "sg:province":"Li\u00e8ge",
    "wof:name":"Restaurant Vis\u00c9",
    "wof:placetype":"venue"
},
  "geometry": {"coordinates":[6.0390291214,50.6223068237],"type":"Point"}
}