{
  "type": "Feature",
  "properties": {
    "iso:country":"BE",
    "sg:address":"Rue Bodeghem 88",
    "sg:city":"Brussel/bruxelles",
    "sg:orig_category":"Salles de conf\u00e9rences and de r\u00e9ceptions",
    "sg:phone":"+32 2 512 17 03",
    "sg:postcode":"1000",
    "sg:province":"Bruxelles-Capitale",
    "wof:name":"La Salle Senko",
    "wof:placetype":"venue"
},
  "geometry": {"coordinates":[4.3405818939,50.8429718018],"type":"Point"}
}