{
  "type": "Feature",
  "properties": {
    "addr:full":"Hoge Mauw 16c Arendonk Antwerpen 2370",
    "addr:housenumber":"16c",
    "addr:postcode":"2370",
    "addr:street":"Hoge Mauw",
    "iso:country":"BE",
    "sg:address":"Hoge Mauw 16c",
    "sg:city":"Arendonk",
    "sg:classifiers":[
        {
            "category":"Health Services",
            "subcategory":"Nursing And Care Facility",
            "type":"Services"
        }
    ],
    "sg:phone":"+32 14 67 81 88",
    "sg:postcode":"2370",
    "sg:province":"Antwerpen",
    "sg:tags":[
        "access",
        "equipment",
        "hospital",
        "-"
    ],
    "wof:name":"Schell Industries Nv",
    "wof:placetype":"venue"
},
  "geometry": {"coordinates":[5.1107811928,51.3016052246],"type":"Point"}
}