{
  "type": "Feature",
  "properties": {
    "iso:country":"BE",
    "sg:address":"Gentsestraat 11",
    "sg:city":"Moorslede",
    "sg:classifiers":[
        {
            "category":"Retail",
            "subcategory":"Auto Repair",
            "type":"Services"
        }
    ],
    "sg:phone":"+32 51 77 76 70",
    "sg:postcode":"8890",
    "sg:province":"West-Vlaanderen",
    "sg:tags":[
        "garage"
    ],
    "wof:name":"Vander Stichele",
    "wof:placetype":"venue"
},
  "geometry": {"coordinates":[3.0696249008,50.8937721252],"type":"Point"}
}