{
  "type": "Feature",
  "properties": {
    "addr:full":"Gounodstraat 7 Box 4 Antwerpen Antwerpen 2018",
    "addr:housenumber":"7;4",
    "addr:postcode":"2018",
    "addr:street":"Gounodstraat;Box",
    "iso:country":"BE",
    "sg:address":"Gounodstraat 7 Box 4",
    "sg:city":"Antwerpen",
    "sg:classifiers":[
        {
            "category":"Professional",
            "subcategory":"Management & Consulting",
            "type":"Services"
        }
    ],
    "sg:phone":"+32 3 237 71 23",
    "sg:postcode":"2018",
    "sg:province":"Antwerpen",
    "sg:tags":[
        "tax-consultants"
    ],
    "wof:name":"Coninx J",
    "wof:placetype":"venue"
},
  "geometry": {"coordinates":[4.4093132019,51.2056770325],"type":"Point"}
}