{
  "type": "Feature",
  "properties": {
    "addr:full":"Rue Des Coquelicots 1 Ans (loncin) Li\u00e8ge 4431",
    "addr:housenumber":"1",
    "addr:postcode":"4431",
    "addr:street":"Rue Des Coquelicots",
    "iso:country":"BE",
    "sg:address":"Rue Des Coquelicots 1",
    "sg:city":"Ans (loncin)",
    "sg:classifiers":[
        {
            "category":"Health Services",
            "subcategory":"Doctor",
            "type":"Services"
        }
    ],
    "sg:phone":"+32 4 263 79 65",
    "sg:postcode":"4431",
    "sg:province":"Li\u00e8ge",
    "sg:tags":[
        "medicinephysicians",
        "surgeon"
    ],
    "wof:name":"Collard Marcel",
    "wof:placetype":"venue"
},
  "geometry": {"coordinates":[5.4946551323,50.6761398315],"type":"Point"}
}