{
  "type": "Feature",
  "properties": {
    "iso:country":"BE",
    "sg:address":"B.c.rots. De Hertaingln 10",
    "sg:city":"Maldegem",
    "sg:orig_category":"Travaux de pl\u00e2trage",
    "sg:phone":"+32 50 71 70 22",
    "sg:postcode":"9990",
    "sg:province":"Oost-Vlaanderen",
    "wof:name":"Romain Vander Haeghen",
    "wof:placetype":"venue"
},
  "geometry": {"coordinates":[3.4483320713,51.2094421387],"type":"Point"}
}