{
  "type": "Feature",
  "properties": {
    "addr:full":"Boomsesteenweg 460 Antwerpen (wilrijk) Antwerpen 2610",
    "addr:housenumber":"460",
    "addr:postcode":"2610",
    "addr:street":"Boomsesteenweg;Antwerpen",
    "iso:country":"BE",
    "sg:address":"Boomsesteenweg 460",
    "sg:city":"Antwerpen (wilrijk)",
    "sg:orig_category":"Newspapers, magazines, periodicals - Publishers",
    "sg:phone":"+32 900 10 600",
    "sg:postcode":"2610",
    "sg:province":"Antwerpen",
    "wof:name":"Koopjeskrant Nv",
    "wof:placetype":"venue"
},
  "geometry": {"coordinates":[4.3887591362,51.1844863892],"type":"Point"}
}