{
  "type": "Feature",
  "properties": {
    "addr:full":"Nieuwmoer Dorp 34-36 Kalmthout Antwerpen 2920",
    "addr:housenumber":"34-36",
    "addr:postcode":"2920",
    "addr:street":"Nieuwmoer Dorp",
    "iso:country":"BE",
    "sg:address":"Nieuwmoer Dorp 34-36",
    "sg:city":"Kalmthout",
    "sg:classifiers":[
        {
            "category":"Building & Trades",
            "subcategory":"Pest Control",
            "type":"Services"
        }
    ],
    "sg:phone":"+32 3 667 27 31",
    "sg:postcode":"2920",
    "sg:province":"Antwerpen",
    "sg:tags":[
        "painting",
        "contractor"
    ],
    "wof:name":"Oerlemans E",
    "wof:placetype":"venue"
},
  "geometry": {"coordinates":[4.5159978867,51.4324264526],"type":"Point"}
}