{
  "type": "Feature",
  "properties": {
    "addr:full":"Torhoutsesteenweg 206 Oostende West-Vlaanderen 8400",
    "addr:housenumber":"206",
    "addr:postcode":"8400",
    "addr:street":"Torhoutsesteenweg",
    "iso:country":"BE",
    "sg:address":"Torhoutsesteenweg 206",
    "sg:city":"Oostende",
    "sg:orig_category":"Avocats and conseillers juridiques",
    "sg:phone":"+32 59 50 99 36",
    "sg:postcode":"8400",
    "sg:province":"West-Vlaanderen",
    "wof:name":"I. Sercu",
    "wof:placetype":"venue"
},
  "geometry": {"coordinates":[2.9077649117,51.2185325623],"type":"Point"}
}