{
  "type": "Feature",
  "properties": {
    "addr:full":"Gentsesteenweg 10 Deinze Oost-Vlaanderen 9800",
    "addr:housenumber":"10",
    "addr:postcode":"9800",
    "addr:street":"Gentsesteenweg",
    "iso:country":"BE",
    "sg:address":"Gentsesteenweg 10",
    "sg:city":"Deinze",
    "sg:classifiers":[
        {
            "category":"Shopping",
            "subcategory":"Hobbies, Toys, & Games",
            "type":"Retail Goods"
        }
    ],
    "sg:phone":"+32 9 386 10 48",
    "sg:postcode":"9800",
    "sg:province":"Oost-Vlaanderen",
    "sg:tags":[
        "product",
        "miscellaneous",
        "entertainment"
    ],
    "wof:name":"La Carrosserie Enfantine Nv",
    "wof:placetype":"venue"
},
  "geometry": {"coordinates":[3.5376150608,50.9801254272],"type":"Point"}
}