{
  "type": "Feature",
  "properties": {
    "addr:full":"Rue De Huy 168b Ohey (groot) Namur 5350",
    "addr:housenumber":"168b",
    "addr:postcode":"5350",
    "addr:street":"Rue De Huy;Groot Namur",
    "iso:country":"BE",
    "sg:address":"Rue De Huy 168b",
    "sg:city":"Ohey (groot)",
    "sg:orig_category":"Boissons. Brasseries",
    "sg:phone":"+32 85 61 16 13",
    "sg:postcode":"5350",
    "sg:province":"Namur",
    "wof:name":"Brasserie Francois",
    "wof:placetype":"venue"
},
  "geometry": {"coordinates":[5.1272091866,50.4306793213],"type":"Point"}
}