{
  "type": "Feature",
  "properties": {
    "iso:country":"BE",
    "sg:address":"Krijgsbaan 108",
    "sg:city":"Temse",
    "sg:orig_category":"Krantenwinkels Rookartikelen",
    "sg:phone":"+32 3 771 31 43",
    "sg:postcode":"9140",
    "sg:province":"Oost-Vlaanderen",
    "wof:name":"Huis 't Boeksken",
    "wof:placetype":"venue"
},
  "geometry": {"coordinates":[4.228758812,51.1290283203],"type":"Point"}
}