{
  "type": "Feature",
  "properties": {
    "addr:full":"Dorekenstraat 15 Lennik Vlaams-Brabant 1750",
    "addr:housenumber":"15;1750",
    "addr:street":"Dorekenstraat;Vlaams-Brabant",
    "iso:country":"BE",
    "sg:address":"Dorekenstraat 15",
    "sg:city":"Lennik",
    "sg:orig_category":"Traitements param\u00e9dicaux",
    "sg:phone":"+32 2 532 13 11",
    "sg:postcode":"1750",
    "sg:province":"Vlaams-Brabant",
    "wof:name":"Martine O",
    "wof:placetype":"venue"
},
  "geometry": {"coordinates":[4.1682691574,50.8112754822],"type":"Point"}
}