{
  "type": "Feature",
  "properties": {
    "addr:full":"Boulevard De La Sauveni\u00c8re 142 Liege Li\u00e8ge 4000",
    "addr:housenumber":"142",
    "addr:postcode":"4000",
    "addr:street":"Boulevard De La Sauvenie\u0300Re",
    "iso:country":"BE",
    "sg:address":"Boulevard De La Sauveni\u00c8re 142",
    "sg:city":"Liege",
    "sg:orig_category":"Restaurants Ruimtes voor conferenties, recepties and feesten",
    "sg:phone":"+32 4 232 18 18",
    "sg:postcode":"4000",
    "sg:province":"Li\u00e8ge",
    "wof:name":"Le Bruit Qui Court",
    "wof:placetype":"venue"
},
  "geometry": {"coordinates":[5.5670690536,50.6412124634],"type":"Point"}
}