{
  "type": "Feature",
  "properties": {
    "addr:full":"Krokussenlaan 14 Beringen (paal) Limburg 3583",
    "addr:housenumber":"14",
    "addr:postcode":"3583",
    "addr:street":"Krokussenlaan",
    "iso:country":"BE",
    "sg:address":"Krokussenlaan 14",
    "sg:city":"Beringen (paal)",
    "sg:classifiers":[
        {
            "category":"Home & Garden",
            "subcategory":"Carpets & Floor Coverings",
            "type":"Retail Goods"
        }
    ],
    "sg:phone":"+32 11 42 77 82",
    "sg:postcode":"3583",
    "sg:province":"Limburg",
    "sg:tags":[
        "layer",
        "mosaicists"
    ],
    "wof:name":"Elsen & Jaspers Bvba",
    "wof:placetype":"venue"
},
  "geometry": {"coordinates":[5.1706700325,51.0389442444],"type":"Point"}
}