{
  "type": "Feature",
  "properties": {
    "iso:country":"BE",
    "sg:address":"Knesselarestraat 90",
    "sg:city":"Beernem",
    "sg:orig_category":"Rev\u00eatements pour sols and murs",
    "sg:phone":"+32 50 78 11 15",
    "sg:postcode":"8730",
    "sg:province":"West-Vlaanderen",
    "wof:name":"Marc Maenhout",
    "wof:placetype":"venue"
},
  "geometry": {"coordinates":[3.346987009,51.16771698],"type":"Point"}
}