{
  "type": "Feature",
  "properties": {
    "addr:full":"Vinkenstraat 2 Middelkerke West-Vlaanderen 8432",
    "addr:housenumber":"2",
    "addr:postcode":"8432",
    "addr:street":"Vinkenstraat",
    "iso:country":"BE",
    "sg:address":"Vinkenstraat 2",
    "sg:city":"Middelkerke",
    "sg:orig_category":"Alternatieve geneeskunde",
    "sg:phone":"+32 59 30 59 39",
    "sg:postcode":"8432",
    "sg:province":"West-Vlaanderen",
    "wof:name":"Carine Focke",
    "wof:placetype":"venue"
},
  "geometry": {"coordinates":[2.8822350502,51.1772422791],"type":"Point"}
}