{
  "type": "Feature",
  "properties": {
    "addr:full":"Rue Du Ruisseau 13b1 Donceel Li\u00e8ge 4357",
    "addr:housenumber":"13b1",
    "addr:postcode":"4357",
    "addr:street":"Rue Du Ruisseau",
    "iso:country":"BE",
    "sg:address":"Rue Du Ruisseau 13b1",
    "sg:city":"Donceel",
    "sg:orig_category":"Traitements param\u00e9dicaux",
    "sg:phone":"+32 4 259 42 76",
    "sg:postcode":"4357",
    "sg:province":"Li\u00e8ge",
    "wof:name":"I. Gutierrez",
    "wof:placetype":"venue"
},
  "geometry": {"coordinates":[5.3211331367,50.6375198364],"type":"Point"}
}