{
  "type": "Feature",
  "properties": {
    "addr:full":"Avenue D'orbaix 43 Bruxelles (uccle) Bruxelles-Capitale 1180",
    "addr:housenumber":"43",
    "addr:postcode":"1180",
    "addr:street":"Avenue D'Orbaix",
    "iso:country":"BE",
    "sg:address":"Avenue D'orbaix 43",
    "sg:city":"Bruxelles (uccle)",
    "sg:classifiers":[
        {
            "category":"Manufacturing",
            "subcategory":"Food",
            "type":"Manufacturing & Wholesale Goods"
        }
    ],
    "sg:phone":"+32 2 375 56 47",
    "sg:postcode":"1180",
    "sg:province":"Bruxelles-Capitale",
    "sg:tags":[
        "industry",
        "-",
        "ingredient"
    ],
    "wof:name":"Miltner Ing Hans F Sprl",
    "wof:placetype":"venue"
},
  "geometry": {"coordinates":[4.3704428673,50.7882385254],"type":"Point"}
}