{
  "type": "Feature",
  "properties": {
    "addr:full":"Rue De Vis\u00e9 506 Li\u00e8ge 1 (wandre) Li\u00e8ge 4020",
    "addr:housenumber":"506;1",
    "addr:postcode":"4020",
    "addr:street":"Rue De Vise\u0301",
    "iso:country":"BE",
    "sg:address":"Rue De Vis\u00e9 506",
    "sg:city":"Li\u00e8ge 1 (wandre)",
    "sg:classifiers":[
        {
            "category":"Building & Trades",
            "subcategory":"Electrical",
            "type":"Services"
        }
    ],
    "sg:phone":"+32 4 362 54 28",
    "sg:postcode":"4020",
    "sg:province":"Li\u00e8ge",
    "sg:tags":[
        "electric",
        "-",
        "housewiring",
        "contractor"
    ],
    "wof:name":"Fil\u00e9e D",
    "wof:placetype":"venue"
},
  "geometry": {"coordinates":[5.6517729759,50.6581764221],"type":"Point"}
}