{
  "type": "Feature",
  "properties": {
    "addr:full":"Rue Du Pr\u00c9v\u00d4t 123 Elsene/ixelles Bruxelles-Capitale 1050",
    "addr:housenumber":"123",
    "addr:postcode":"1050",
    "addr:street":"Rue Du Pre\u0301Vo\u0302T",
    "iso:country":"BE",
    "sg:address":"Rue Du Pr\u00c9v\u00d4t 123",
    "sg:city":"Elsene/ixelles",
    "sg:orig_category":"Architectes",
    "sg:phone":"+32 2 345 12 34",
    "sg:postcode":"1050",
    "sg:province":"Bruxelles-Capitale",
    "wof:name":"Albert Dewalque",
    "wof:placetype":"venue"
},
  "geometry": {"coordinates":[4.3618497849,50.8204994202],"type":"Point"}
}