{
  "type": "Feature",
  "properties": {
    "addr:full":"Grootheide 113 Bornem Antwerpen 2880",
    "addr:housenumber":"113",
    "addr:postcode":"2880",
    "addr:street":"Grootheide",
    "iso:country":"BE",
    "sg:address":"Grootheide 113",
    "sg:city":"Bornem",
    "sg:classifiers":[
        {
            "category":"Arena",
            "subcategory":"Sports Club",
            "type":"Entertainment"
        }
    ],
    "sg:phone":"+32 3 889 45 03",
    "sg:postcode":"2880",
    "sg:province":"Antwerpen",
    "sg:tags":[
        "de"
    ],
    "wof:name":"Shoto Karate-do",
    "wof:placetype":"venue"
},
  "geometry": {"coordinates":[4.2220492363,51.0885391235],"type":"Point"}
}