{
  "type": "Feature",
  "properties": {
    "addr:full":"Terreststraat 1 Houthulst West-Vlaanderen 8650",
    "addr:housenumber":"1",
    "addr:postcode":"8650",
    "addr:street":"Terreststraat",
    "iso:country":"BE",
    "sg:address":"Terreststraat 1",
    "sg:city":"Houthulst",
    "sg:classifiers":[
        {
            "category":"Shopping",
            "subcategory":"Florist",
            "type":"Retail Goods"
        }
    ],
    "sg:phone":"+32 51 70 25 73",
    "sg:postcode":"8650",
    "sg:province":"West-Vlaanderen",
    "wof:name":"Bloemen Cindy",
    "wof:placetype":"venue"
},
  "geometry": {"coordinates":[2.9506158829,50.9785804749],"type":"Point"}
}