{
  "type": "Feature",
  "properties": {
    "addr:full":"Ch\u00c9e De Philippeville 212 Gerpinnes Hainaut 6280",
    "addr:housenumber":"212",
    "addr:postcode":"6280",
    "addr:street":"Hainaut",
    "iso:country":"BE",
    "sg:address":"Ch\u00c9e De Philippeville 212",
    "sg:city":"Gerpinnes",
    "sg:orig_category":"Caravans, aanhangwagens and opleggers Woningbouw",
    "sg:phone":"+32 71 22 13 73",
    "sg:postcode":"6280",
    "sg:province":"Hainaut",
    "wof:name":"Euro-caravaning",
    "wof:placetype":"venue"
},
  "geometry": {"coordinates":[4.4726500511,50.3463096619],"type":"Point"}
}