{
  "type": "Feature",
  "properties": {
    "iso:country":"BE",
    "sg:address":"Rue Jean Jaur\u00c8s 180",
    "sg:city":"Charleroi",
    "sg:orig_category":"Apotheken",
    "sg:phone":"+32 71 32 77 63",
    "sg:postcode":"6061",
    "sg:province":"Hainaut",
    "wof:name":"Pharmac",
    "wof:placetype":"venue"
},
  "geometry": {"coordinates":[4.4260010719,50.4208335876],"type":"Point"}
}