{
  "type": "Feature",
  "properties": {
    "addr:full":"Jan De Cordesstraat 63 Putte Antwerpen 2580",
    "addr:housenumber":"63",
    "addr:postcode":"2580",
    "addr:street":"Jan De Cordesstraat",
    "iso:country":"BE",
    "sg:address":"Jan De Cordesstraat 63",
    "sg:city":"Putte",
    "sg:classifiers":[
        {
            "category":"Insurance",
            "subcategory":"Life Insurance",
            "type":"Services"
        }
    ],
    "sg:phone":"+32 15 76 08 42",
    "sg:postcode":"2580",
    "sg:province":"Antwerpen",
    "sg:tags":[
        "assurance"
    ],
    "wof:name":"De Belser",
    "wof:placetype":"venue"
},
  "geometry": {"coordinates":[4.6632828712,51.0607719421],"type":"Point"}
}