{
  "type": "Feature",
  "properties": {
    "addr:full":"Chauss\u00e9e De Bruxelles 307 Waterloo Brabant Wallon 1410",
    "addr:housenumber":"307",
    "addr:postcode":"1410",
    "addr:street":"Chausse\u0301E De Bruxelles",
    "iso:country":"BE",
    "sg:address":"Chauss\u00e9e De Bruxelles 307",
    "sg:city":"Waterloo",
    "sg:classifiers":[
        {
            "category":"Professional",
            "subcategory":"Detective & Security Services",
            "type":"Services"
        }
    ],
    "sg:phone":"+32 2 354 96 95",
    "sg:postcode":"1410",
    "sg:province":"Brabant Wallon",
    "sg:tags":[
        "access-control",
        "system"
    ],
    "wof:name":"Alarm Group Vag",
    "wof:placetype":"venue"
},
  "geometry": {"coordinates":[4.4016571045,50.7080955505],"type":"Point"}
}