{
  "type": "Feature",
  "properties": {
    "addr:full":"Sint Jozefstraat 39 Antwerpen Antwerpen 2018",
    "addr:housenumber":"39",
    "addr:postcode":"2018",
    "addr:street":"Sint Jozefstraat",
    "iso:country":"BE",
    "sg:address":"Sint Jozefstraat 39",
    "sg:city":"Antwerpen",
    "sg:orig_category":"Centres de relaxation and bien-\u00eatre",
    "sg:phone":"+32 3 226 17 90",
    "sg:postcode":"2018",
    "sg:province":"Antwerpen",
    "wof:name":"Sprakenis Lennert",
    "wof:placetype":"venue"
},
  "geometry": {"coordinates":[4.4130020142,51.2074165344],"type":"Point"}
}