{
  "type": "Feature",
  "properties": {
    "addr:full":"Rue Puccini 71 Bruxelles (anderlecht) Bruxelles-Capitale 1070",
    "addr:housenumber":"71",
    "addr:postcode":"1070",
    "addr:street":"Rue Puccini",
    "iso:country":"BE",
    "sg:address":"Rue Puccini 71",
    "sg:city":"Bruxelles (anderlecht)",
    "sg:classifiers":[
        {
            "category":"Professional",
            "subcategory":"Art Services",
            "type":"Services"
        }
    ],
    "sg:phone":"+32 2 524 22 12",
    "sg:postcode":"1070",
    "sg:province":"Bruxelles-Capitale",
    "sg:tags":[
        "graphic",
        "designer"
    ],
    "wof:name":"Cardoen Y",
    "wof:placetype":"venue"
},
  "geometry": {"coordinates":[4.3042888641,50.8449172974],"type":"Point"}
}