{
  "type": "Feature",
  "properties": {
    "iso:country":"BE",
    "sg:address":"Rue Des Giroflees 18",
    "sg:city":"Namur",
    "sg:orig_category":"Plomberie, chauffage and installations sanitaires",
    "sg:phone":"+32 81 73 45 14",
    "sg:postcode":"5002",
    "sg:province":"Namur",
    "wof:name":"Lebeau Philippe",
    "wof:placetype":"venue"
},
  "geometry": {"coordinates":[4.8462319374,50.4782791138],"type":"Point"}
}