{
  "type": "Feature",
  "properties": {
    "iso:country":"BE",
    "sg:address":"Dennenweg 74",
    "sg:city":"Schoten",
    "sg:classifiers":[
        {
            "category":"Arena",
            "subcategory":"Sports Club",
            "type":"Entertainment"
        }
    ],
    "sg:phone":"+32 3 652 03 65",
    "sg:postcode":"2900",
    "sg:province":"Antwerpen",
    "sg:tags":[
        "de"
    ],
    "wof:name":"Zwemclub Schoten",
    "wof:placetype":"venue"
},
  "geometry": {"coordinates":[4.5310702324,51.2687988281],"type":"Point"}
}