{
  "type": "Feature",
  "properties": {
    "addr:full":"Rue De Luxensart 16 Seneffe (petit-roeulx-lez-nivelles) Hainaut 7181",
    "addr:housenumber":"16",
    "addr:postcode":"7181",
    "addr:street":"Rue De Luxensart",
    "iso:country":"BE",
    "sg:address":"Rue De Luxensart 16",
    "sg:city":"Seneffe (petit-roeulx-lez-nivelles)",
    "sg:classifiers":[
        {
            "category":"Building & Trades",
            "subcategory":"Landscaping Services",
            "type":"Services"
        }
    ],
    "sg:phone":"+32 67 87 70 77",
    "sg:postcode":"7181",
    "sg:province":"Hainaut",
    "sg:tags":[
        "gardening",
        "garden",
        "maintenance"
    ],
    "wof:name":"Destrait L",
    "wof:placetype":"venue"
},
  "geometry": {"coordinates":[4.2589969635,50.5626296997],"type":"Point"}
}