{
  "type": "Feature",
  "properties": {
    "addr:full":"Chauss\u00e9e De Namur 96 Incourt (glimes) Brabant Wallon 1315",
    "addr:housenumber":"96",
    "addr:postcode":"1315",
    "addr:street":"Chausse\u0301E De Namur;Wallon",
    "iso:country":"BE",
    "sg:address":"Chauss\u00e9e De Namur 96",
    "sg:city":"Incourt (glimes)",
    "sg:classifiers":[
        {
            "category":"Retail",
            "subcategory":"Auto Repair",
            "type":"Services"
        }
    ],
    "sg:phone":"+32 10 88 87 79",
    "sg:postcode":"1315",
    "sg:province":"Brabant Wallon",
    "sg:tags":[
        "garage"
    ],
    "wof:name":"Chaussee (garage De La)",
    "wof:placetype":"venue"
},
  "geometry": {"coordinates":[4.8057761192,50.6939430237],"type":"Point"}
}