{
  "type": "Feature",
  "properties": {
    "iso:country":"BE",
    "sg:address":"Weg Naar As 9b3",
    "sg:city":"Genk",
    "sg:orig_category":"Immobili\u00ebnkantoren Vakantiehuizen",
    "sg:phone":"+32 89 30 42 38",
    "sg:postcode":"3600",
    "sg:province":"Limburg",
    "wof:name":"V En P Vastgoed",
    "wof:placetype":"venue"
},
  "geometry": {"coordinates":[5.508600235,50.9670448303],"type":"Point"}
}