{
  "type": "Feature",
  "properties": {
    "addr:full":"Rue De La Boulangerie 2 Mons Hainaut 7000",
    "addr:housenumber":"2",
    "addr:postcode":"7000",
    "addr:street":"Rue De La Boulangerie;Hainaut",
    "iso:country":"BE",
    "sg:address":"Rue De La Boulangerie 2",
    "sg:city":"Mons",
    "sg:classifiers":[
        {
            "category":"Arena",
            "subcategory":"Sports Club",
            "type":"Entertainment"
        }
    ],
    "sg:phone":"+32 65 31 38 42",
    "sg:postcode":"7000",
    "sg:province":"Hainaut",
    "wof:name":"P\u00e9tanque Montoise (la) Asbl",
    "wof:placetype":"venue"
},
  "geometry": {"coordinates":[3.9501600266,50.447101593],"type":"Point"}
}