{
  "type": "Feature",
  "properties": {
    "iso:country":"BE",
    "sg:address":"Molendreef 59",
    "sg:city":"Sint-niklaas",
    "sg:orig_category":"Kapsalons",
    "sg:phone":"+32 3 772 52 79",
    "sg:postcode":"9111",
    "sg:province":"Oost-Vlaanderen",
    "wof:name":"Berlinda Van Bocxlaer",
    "wof:placetype":"venue"
},
  "geometry": {"coordinates":[4.0926370621,51.1485023499],"type":"Point"}
}