{
  "type": "Feature",
  "properties": {
    "iso:country":"BE",
    "sg:address":"Basiliekstraat 95",
    "sg:city":"Halle",
    "sg:classifiers":[
        {
            "category":"Shopping",
            "subcategory":"Clothing, Apparel, & Fashions",
            "type":"Retail Goods"
        }
    ],
    "sg:phone":"+32 2 361 39 99",
    "sg:postcode":"1500",
    "sg:province":"Vlaams-Brabant",
    "sg:tags":[
        "-",
        "clothing",
        "child"
    ],
    "wof:name":"Kid Cool Halle",
    "wof:placetype":"venue"
},
  "geometry": {"coordinates":[4.2362031937,50.7339935303],"type":"Point"}
}