{
  "type": "Feature",
  "properties": {
    "addr:full":"En Laixheau 2 Herstal Li\u00e8ge 4040",
    "addr:housenumber":"2",
    "addr:postcode":"4040",
    "iso:country":"BE",
    "sg:address":"En Laixheau 2",
    "sg:city":"Herstal",
    "sg:classifiers":[
        {
            "category":"Food & Beverages",
            "subcategory":"Groceries & Convenience Stores",
            "type":"Retail Goods"
        }
    ],
    "sg:phone":"+32 4 248 16 68",
    "sg:postcode":"4040",
    "sg:province":"Li\u00e8ge",
    "sg:tags":[
        "grocer"
    ],
    "wof:name":"Keyfood Sa\u00efd",
    "wof:placetype":"venue"
},
  "geometry": {"coordinates":[5.6293301582,50.6665115356],"type":"Point"}
}