{
  "type": "Feature",
  "properties": {
    "iso:country":"BE",
    "sg:address":"Pontfortsedijk 34",
    "sg:city":"Retie",
    "sg:orig_category":"V\u00e9t\u00e9rinaires",
    "sg:phone":"+32 14 37 11 33",
    "sg:postcode":"2470",
    "sg:province":"Antwerpen",
    "wof:name":"Geert Van Loock",
    "wof:placetype":"venue"
},
  "geometry": {"coordinates":[5.0550570488,51.2493476868],"type":"Point"}
}