{
  "type": "Feature",
  "properties": {
    "iso:country":"BE",
    "sg:address":"Rue De Maestricht 48",
    "sg:city":"Herve (battice)",
    "sg:classifiers":[
        {
            "category":"Building & Trades",
            "subcategory":"Cleaning & Sanitation",
            "type":"Services"
        }
    ],
    "sg:phone":"+32 87 69 27 50",
    "sg:postcode":"4651",
    "sg:province":"Li\u00e8ge",
    "sg:tags":[
        "-",
        "installation",
        "room",
        "clean",
        "supply"
    ],
    "wof:name":"Applicair Sa",
    "wof:placetype":"venue"
},
  "geometry": {"coordinates":[5.8000397682,50.6537094116],"type":"Point"}
}