{
  "type": "Feature",
  "properties": {
    "iso:country":"BE",
    "sg:address":"Rue Du Pont 6",
    "sg:city":"Theux",
    "sg:orig_category":"Pharmaciens",
    "sg:phone":"+32 87 54 18 08",
    "sg:postcode":"4910",
    "sg:province":"Li\u00e8ge",
    "wof:name":"A. Hody",
    "wof:placetype":"venue"
},
  "geometry": {"coordinates":[5.8134407997,50.536655426],"type":"Point"}
}