{
  "type": "Feature",
  "properties": {
    "addr:full":"Pulsebaan 50/3 Zandhoven Antwerpen 2242",
    "addr:housenumber":"50 / 3",
    "addr:postcode":"2242",
    "addr:street":"Pulsebaan",
    "iso:country":"BE",
    "sg:address":"Pulsebaan 50/3",
    "sg:city":"Zandhoven",
    "sg:orig_category":"Installation \u00e9lectrique r\u00e9sidentielle",
    "sg:phone":"+32 3 464 12 96",
    "sg:postcode":"2242",
    "sg:province":"Antwerpen",
    "wof:name":"Eletec",
    "wof:placetype":"venue"
},
  "geometry": {"coordinates":[4.6940460205,51.2122764587],"type":"Point"}
}