{
  "type": "Feature",
  "properties": {
    "addr:full":"Galgestraat 10 Langemark-poelkapelle West-Vlaanderen 8920",
    "addr:housenumber":"10",
    "addr:postcode":"8920",
    "addr:street":"Galgestraat",
    "iso:country":"BE",
    "sg:address":"Galgestraat 10",
    "sg:city":"Langemark-poelkapelle",
    "sg:orig_category":"Eleveurs de bovins",
    "sg:phone":"+32 57 48 82 48",
    "sg:postcode":"8920",
    "sg:province":"West-Vlaanderen",
    "wof:name":"Geert Quaghebeur",
    "wof:placetype":"venue"
},
  "geometry": {"coordinates":[2.919770956,50.9132423401],"type":"Point"}
}