{
  "type": "Feature",
  "properties": {
    "iso:country":"BE",
    "sg:address":"Helvetiastraat 47",
    "sg:city":"Koksijde",
    "sg:orig_category":"S\u00e9lection de personnel and placement",
    "sg:phone":"+32 58 51 87 85",
    "sg:postcode":"8670",
    "sg:province":"West-Vlaanderen",
    "wof:name":"Pwa Koksijde",
    "wof:placetype":"venue"
},
  "geometry": {"coordinates":[2.6413710117,51.106300354],"type":"Point"}
}