{
  "type": "Feature",
  "properties": {
    "addr:full":"Rue De Jemeppe 54 Ans (loncin) Li\u00e8ge 4431",
    "addr:housenumber":"54",
    "addr:postcode":"4431",
    "addr:street":"Rue De Jemeppe",
    "iso:country":"BE",
    "sg:address":"Rue De Jemeppe 54",
    "sg:city":"Ans (loncin)",
    "sg:classifiers":[
        {
            "category":"Retail",
            "subcategory":"Veterinary Services",
            "type":"Services"
        }
    ],
    "sg:phone":"+32 4 239 00 61",
    "sg:postcode":"4431",
    "sg:province":"Li\u00e8ge",
    "sg:tags":[
        "veterinarian"
    ],
    "wof:name":"Joly P",
    "wof:placetype":"venue"
},
  "geometry": {"coordinates":[5.5021262169,50.6648254395],"type":"Point"}
}