{
  "type": "Feature",
  "properties": {
    "iso:country":"BE",
    "sg:address":"Nachtegaallaan 14",
    "sg:city":"Maldegem (adegem)",
    "sg:classifiers":[
        {
            "category":"Social Services",
            "type":"Services"
        }
    ],
    "sg:phone":"+32 9 378 06 58",
    "sg:postcode":"9991",
    "sg:province":"Oost-Vlaanderen",
    "wof:name":"Belgische Federatie Tegen Kanker Vzw",
    "wof:placetype":"venue"
},
  "geometry": {"coordinates":[3.5116569996,51.2037734985],"type":"Point"}
}