{
  "type": "Feature",
  "properties": {
    "addr:full":"Schrieksesteenweg 87 Heist-op-den-berg (booischot) Antwerpen 2221",
    "addr:housenumber":"87",
    "addr:postcode":"2221",
    "addr:street":"Schrieksesteenweg",
    "iso:country":"BE",
    "sg:address":"Schrieksesteenweg 87",
    "sg:city":"Heist-op-den-berg (booischot)",
    "sg:orig_category":"Autombile concessionaires",
    "sg:phone":"+32 15 22 24 28",
    "sg:postcode":"2221",
    "sg:province":"Antwerpen",
    "wof:name":"Gar Jennes Bvba",
    "wof:placetype":"venue"
},
  "geometry": {"coordinates":[4.7739758492,51.0512428284],"type":"Point"}
}