{
  "type": "Feature",
  "properties": {
    "iso:country":"BE",
    "sg:address":"Rue D'arlon 59",
    "sg:city":"Virton",
    "sg:orig_category":"Epiceries. Supermarch\u00e9s",
    "sg:phone":"+32 63 57 92 78",
    "sg:postcode":"6760",
    "sg:province":"Luxembourg",
    "wof:name":"Delhaize",
    "wof:placetype":"venue"
},
  "geometry": {"coordinates":[5.5548248291,49.580078125],"type":"Point"}
}