{
  "type": "Feature",
  "properties": {
    "iso:country":"BE",
    "sg:address":"Park Ter Heide 27",
    "sg:city":"Scherpenheuvel-zichem",
    "sg:classifiers":[
        {
            "category":"Cinema",
            "subcategory":"Movie Rental",
            "type":"Entertainment"
        }
    ],
    "sg:phone":"+32 13 77 76 93",
    "sg:postcode":"3271",
    "sg:province":"Vlaams-Brabant",
    "sg:tags":[
        "de",
        "cassette",
        "location",
        "vid\u00e9o",
        "audio"
    ],
    "wof:name":"Hilde Van Kerckhoven",
    "wof:placetype":"venue"
},
  "geometry": {"coordinates":[4.9928312302,51.0218734741],"type":"Point"}
}