{
  "type": "Feature",
  "properties": {
    "iso:country":"BE",
    "sg:address":"Grote Doelstraat 12",
    "sg:city":"Bonheiden",
    "sg:classifiers":[
        {
            "category":"Building & Trades",
            "subcategory":"Construction",
            "type":"Services"
        }
    ],
    "sg:phone":"+32 15 55 37 23",
    "sg:postcode":"2820",
    "sg:province":"Antwerpen",
    "sg:tags":[
        "carpenter"
    ],
    "wof:name":"Dirickx-verschoren",
    "wof:placetype":"venue"
},
  "geometry": {"coordinates":[4.554983139,51.0266799927],"type":"Point"}
}