{
  "type": "Feature",
  "properties": {
    "iso:country":"BE",
    "sg:address":"Mieregoed 27",
    "sg:city":"De Pinte",
    "sg:classifiers":[
        {
            "category":"Professional",
            "subcategory":"Management & Consulting",
            "type":"Services"
        }
    ],
    "sg:phone":"+32 9 222 90 47",
    "sg:postcode":"9840",
    "sg:province":"Oost-Vlaanderen",
    "sg:tags":[
        "consultant"
    ],
    "wof:name":"Smekens M",
    "wof:placetype":"venue"
},
  "geometry": {"coordinates":[3.6746220589,50.9934043884],"type":"Point"}
}