{
  "type": "Feature",
  "properties": {
    "iso:country":"BE",
    "sg:address":"Pardostraat 4",
    "sg:city":"Damme (sijsele)",
    "sg:classifiers":[
        {
            "category":"Communications",
            "subcategory":"Television Station",
            "type":"Services"
        }
    ],
    "sg:phone":"+32 50 35 88 74",
    "sg:postcode":"8340",
    "sg:province":"West-Vlaanderen",
    "sg:tags":[
        "report",
        "video"
    ],
    "wof:name":"Digitale Video Produkties",
    "wof:placetype":"venue"
},
  "geometry": {"coordinates":[3.3185389042,51.2047615051],"type":"Point"}
}