{
  "type": "Feature",
  "properties": {
    "iso:country":"BE",
    "sg:address":"Impasse Reizer 6",
    "sg:city":"Aubange",
    "sg:classifiers":[
        {
            "category":"Arena",
            "subcategory":"Sports Club",
            "type":"Entertainment"
        }
    ],
    "sg:phone":"+32 63 37 11 80",
    "sg:postcode":"6790",
    "sg:province":"Luxembourg",
    "sg:tags":[
        "terrain",
        "hors",
        "de",
        "installation",
        "sportifs"
    ],
    "wof:name":"C.c.s. Finances",
    "wof:placetype":"venue"
},
  "geometry": {"coordinates":[5.797249794,49.5639190674],"type":"Point"}
}