{
  "type": "Feature",
  "properties": {
    "addr:full":"Vanackerestraat 20 Wevelgem West-Vlaanderen 8560",
    "addr:housenumber":"20",
    "addr:postcode":"8560",
    "addr:street":"Vanackerestraat",
    "iso:country":"BE",
    "sg:address":"Vanackerestraat 20",
    "sg:city":"Wevelgem",
    "sg:orig_category":"Openbare bibliotheken and archieven",
    "sg:phone":"+32 56 43 35 40",
    "sg:postcode":"8560",
    "sg:province":"West-Vlaanderen",
    "wof:name":"Openbare Bibliotheek",
    "wof:placetype":"venue"
},
  "geometry": {"coordinates":[3.1808269024,50.8083953857],"type":"Point"}
}