{
  "type": "Feature",
  "properties": {
    "iso:country":"BE",
    "sg:address":"Place De L'hotel De Ville 7",
    "sg:city":"Gembloux",
    "sg:orig_category":"Epiceries",
    "sg:phone":"+32 81 60 18 67",
    "sg:postcode":"5030",
    "sg:province":"Namur",
    "wof:name":"Night And Day",
    "wof:placetype":"venue"
},
  "geometry": {"coordinates":[4.6945400238,50.5666313171],"type":"Point"}
}