{
  "type": "Feature",
  "properties": {
    "iso:country":"BE",
    "sg:address":"Rue Albert Cl\u00e9ment 4",
    "sg:city":"Neufch\u00e2teau",
    "sg:classifiers":[
        {
            "category":"Insurance",
            "subcategory":"Insurance Agent",
            "type":"Services"
        }
    ],
    "sg:phone":"+32 61 27 91 03",
    "sg:postcode":"6840",
    "sg:province":"Luxembourg",
    "sg:tags":[
        "broker"
    ],
    "wof:name":"Kemp Assurances",
    "wof:placetype":"venue"
},
  "geometry": {"coordinates":[5.4349141121,49.841709137],"type":"Point"}
}