{
  "type": "Feature",
  "properties": {
    "addr:full":"Kirchplatz 4 Kelmis Li\u00e8ge 4720",
    "addr:housenumber":"4",
    "addr:postcode":"4720",
    "addr:street":"Kirchplatz",
    "iso:country":"BE",
    "sg:address":"Kirchplatz 4",
    "sg:city":"Kelmis",
    "sg:classifiers":[
        {
            "category":"Health Services",
            "subcategory":"Dentist",
            "type":"Services"
        }
    ],
    "sg:phone":"+32 87 65 70 63",
    "sg:postcode":"4720",
    "sg:province":"Li\u00e8ge",
    "wof:name":"Dumon Albert",
    "wof:placetype":"venue"
},
  "geometry": {"coordinates":[6.0150160789,50.7153778076],"type":"Point"}
}