{
  "type": "Feature",
  "properties": {
    "iso:country":"BE",
    "sg:address":"Rue De Tr\u00e8ves 31",
    "sg:city":"Bruxelles (etterbeek)",
    "sg:classifiers":[
        {
            "category":"Organizations",
            "subcategory":"Professional Association",
            "type":"Services"
        }
    ],
    "sg:phone":"+32 2 285 02 11",
    "sg:postcode":"1040",
    "sg:province":"Bruxelles-Capitale",
    "sg:tags":[
        "trade-union",
        "federation"
    ],
    "wof:name":"C.s.c. Batiment & Industrie",
    "wof:placetype":"venue"
},
  "geometry": {"coordinates":[4.3750629425,50.8421630859],"type":"Point"}
}