{
  "type": "Feature",
  "properties": {
    "addr:full":"Bulskampstraat 41 Veurne West-Vlaanderen 8630",
    "addr:housenumber":"41",
    "addr:postcode":"8630",
    "addr:street":"Bulskampstraat",
    "iso:country":"BE",
    "sg:address":"Bulskampstraat 41",
    "sg:city":"Veurne",
    "sg:orig_category":"Enseignement maternel and primaire",
    "sg:phone":"+32 58 31 39 52",
    "sg:postcode":"8630",
    "sg:province":"West-Vlaanderen",
    "wof:name":"Vrije Basisschool",
    "wof:placetype":"venue"
},
  "geometry": {"coordinates":[2.6489899158,51.0528793335],"type":"Point"}
}