{
  "type": "Feature",
  "properties": {
    "iso:country":"BE",
    "sg:address":"Rue Basse 13",
    "sg:city":"Assesse",
    "sg:classifiers":[
        {
            "category":"Restaurant",
            "type":"Food & Drink"
        }
    ],
    "sg:phone":"+32 83 69 91 33",
    "sg:postcode":"5332",
    "sg:province":"Namur",
    "wof:name":"Taverne Au Vieux Ch\u00c2teau",
    "wof:placetype":"venue"
},
  "geometry": {"coordinates":[4.9615221024,50.3509521484],"type":"Point"}
}