{
  "type": "Feature",
  "properties": {
    "iso:country":"BE",
    "sg:address":"Peperstraat 108",
    "sg:city":"Eeklo",
    "sg:orig_category":"Technische and wetenschappelijke instrumenten Fab",
    "sg:phone":"+32 9 378 29 39",
    "sg:postcode":"9900",
    "sg:province":"Oost-Vlaanderen",
    "wof:name":"Labo Supplies Belgium",
    "wof:placetype":"venue"
},
  "geometry": {"coordinates":[3.5719339848,51.2112007141],"type":"Point"}
}