{
  "type": "Feature",
  "properties": {
    "addr:full":"Zonnebeekseweg 67 Ieper West-Vlaanderen 8900",
    "addr:housenumber":"67",
    "addr:postcode":"8900",
    "addr:street":"Zonnebeekseweg",
    "iso:country":"BE",
    "sg:address":"Zonnebeekseweg 67",
    "sg:city":"Ieper",
    "sg:classifiers":[
        {
            "category":"Retail",
            "subcategory":"Auto Repair",
            "type":"Services"
        }
    ],
    "sg:phone":"+32 57 20 28 27",
    "sg:postcode":"8900",
    "sg:province":"West-Vlaanderen",
    "sg:tags":[
        "garage"
    ],
    "wof:name":"Soenen G",
    "wof:placetype":"venue"
},
  "geometry": {"coordinates":[2.8972849846,50.8547210693],"type":"Point"}
}