{
  "type": "Feature",
  "properties": {
    "iso:country":"BE",
    "sg:address":"Boektsestraat 30a",
    "sg:city":"Steenokkerzeel (perk)",
    "sg:classifiers":[
        {
            "category":"Building & Trades",
            "subcategory":"Electrical",
            "type":"Services"
        }
    ],
    "sg:phone":"+32 15 62 74 00",
    "sg:postcode":"1820",
    "sg:province":"Vlaams-Brabant",
    "sg:tags":[
        "heating"
    ],
    "wof:name":"Br\u00e9ban Bvba",
    "wof:placetype":"venue"
},
  "geometry": {"coordinates":[4.4979400635,50.9555702209],"type":"Point"}
}