{
  "type": "Feature",
  "properties": {
    "iso:country":"BE",
    "sg:address":"Duffelsesteenweg 69",
    "sg:city":"Lint",
    "sg:orig_category":"Newspapers, magazines, periodicals - Distribution",
    "sg:phone":"+32 3 455 17 30",
    "sg:postcode":"2547",
    "sg:province":"Antwerpen",
    "wof:name":"Mavi Papers Bvba",
    "wof:placetype":"venue"
},
  "geometry": {"coordinates":[4.4954519272,51.1245384216],"type":"Point"}
}