{
  "type": "Feature",
  "properties": {
    "addr:full":"Montleban 59 Gouvy Luxembourg 6674",
    "addr:housenumber":"59",
    "addr:postcode":"6674",
    "addr:street":"Montleban",
    "iso:country":"BE",
    "sg:address":"Montleban 59",
    "sg:city":"Gouvy",
    "sg:orig_category":"Rundveehouders",
    "sg:phone":"+32 80 51 77 29",
    "sg:postcode":"6674",
    "sg:province":"Luxembourg",
    "wof:name":"Vincent Octave",
    "wof:placetype":"venue"
},
  "geometry": {"coordinates":[5.83670187,50.1897964478],"type":"Point"}
}