{
  "type": "Feature",
  "properties": {
    "iso:country":"BE",
    "sg:address":"Dreveneind 15",
    "sg:city":"Essen",
    "sg:orig_category":"Passagiersvervoer over de weg",
    "sg:phone":"+32 3 236 77 03",
    "sg:postcode":"2910",
    "sg:province":"Antwerpen",
    "wof:name":"Muys Reizen",
    "wof:placetype":"venue"
},
  "geometry": {"coordinates":[4.5041818619,51.4690170288],"type":"Point"}
}