{
  "type": "Feature",
  "properties": {
    "addr:full":"Rue Fran\u00c7ois Vekemans 22 Bruxelles Bruxelles-Capitale 1120",
    "addr:housenumber":"22",
    "addr:postcode":"1120",
    "addr:street":"Rue Franc\u0327Ois Vekemans",
    "iso:country":"BE",
    "sg:address":"Rue Fran\u00c7ois Vekemans 22",
    "sg:city":"Bruxelles",
    "sg:classifiers":[
        {
            "category":"Insurance",
            "subcategory":"Life Insurance",
            "type":"Services"
        }
    ],
    "sg:phone":"+32 2 268 04 93",
    "sg:postcode":"1120",
    "sg:province":"Bruxelles-Capitale",
    "sg:tags":[
        "assurance"
    ],
    "wof:name":"Bureau Maurice Willems",
    "wof:placetype":"venue"
},
  "geometry": {"coordinates":[4.3916501999,50.8961448669],"type":"Point"}
}