{
  "type": "Feature",
  "properties": {
    "addr:full":"Aartshertogstraat 30 Oostende West-Vlaanderen 8400",
    "addr:housenumber":"30",
    "addr:postcode":"8400",
    "addr:street":"Aartshertogstraat",
    "iso:country":"BE",
    "sg:address":"Aartshertogstraat 30",
    "sg:city":"Oostende",
    "sg:orig_category":"Herstellingen and onderhoud van auto's",
    "sg:phone":"+32 59 50 23 93",
    "sg:postcode":"8400",
    "sg:province":"West-Vlaanderen",
    "wof:name":"L. Van Mieghem",
    "wof:placetype":"venue"
},
  "geometry": {"coordinates":[2.9179749489,51.2290153503],"type":"Point"}
}