{
  "type": "Feature",
  "properties": {
    "iso:country":"BE",
    "sg:address":"Antwerpsesteenweg 484",
    "sg:city":"Malle (oostmalle)",
    "sg:classifiers":[
        {
            "category":"Transit Center",
            "subcategory":"Freight",
            "type":"Transportation"
        }
    ],
    "sg:phone":"+32 3 312 39 02",
    "sg:postcode":"2390",
    "sg:province":"Antwerpen",
    "sg:tags":[
        "import",
        "export",
        "-"
    ],
    "wof:name":"Cothema Belgi\u00eb Nv",
    "wof:placetype":"venue"
},
  "geometry": {"coordinates":[4.6712532043,51.2881546021],"type":"Point"}
}