{
  "type": "Feature",
  "properties": {
    "iso:country":"BE",
    "sg:address":"Parc M\u00c9nobu 453",
    "sg:city":"Theux",
    "sg:orig_category":"Isolatiewerk Winkelinrichting and handelsuitrusting Gh",
    "sg:phone":"+32 87 37 67 56",
    "sg:postcode":"4910",
    "sg:province":"Li\u00e8ge",
    "wof:name":"Jean-luc Comans",
    "wof:placetype":"venue"
},
  "geometry": {"coordinates":[5.7691221237,50.4932937622],"type":"Point"}
}