{
  "type": "Feature",
  "properties": {
    "iso:country":"BE",
    "sg:address":"Rue J Destr\u00c9e 8",
    "sg:city":"Ans",
    "sg:orig_category":"SMEEDWERK, METAALBEWERKING AND POEDERMETALLURGIE",
    "sg:phone":"+32 4 263 24 84",
    "sg:postcode":"4431",
    "sg:province":"Li\u00e8ge",
    "wof:name":"Melon L",
    "wof:placetype":"venue"
},
  "geometry": {"coordinates":[5.499227047,50.6641082764],"type":"Point"}
}