{
  "type": "Feature",
  "properties": {
    "addr:full":"Ooievaarsstraat 30 Antwerpen Antwerpen 2060",
    "addr:housenumber":"30",
    "addr:postcode":"2060",
    "addr:street":"Ooievaarsstraat",
    "iso:country":"BE",
    "sg:address":"Ooievaarsstraat 30",
    "sg:city":"Antwerpen",
    "sg:classifiers":[
        {
            "category":"Professional",
            "type":"Services"
        }
    ],
    "sg:phone":"+32 3 235 39 14",
    "sg:postcode":"2060",
    "sg:province":"Antwerpen",
    "sg:tags":[
        "surveyor",
        "-",
        "valuer"
    ],
    "wof:name":"C S B Bvba",
    "wof:placetype":"venue"
},
  "geometry": {"coordinates":[4.4379339218,51.2201805115],"type":"Point"}
}