{
  "type": "Feature",
  "properties": {
    "addr:full":"Roterijstraat 129 Waregem West-Vlaanderen 8790",
    "addr:housenumber":"129",
    "addr:postcode":"8790",
    "addr:street":"Roterijstraat",
    "iso:country":"BE",
    "sg:address":"Roterijstraat 129",
    "sg:city":"Waregem",
    "sg:classifiers":[
        {
            "category":"Landmark",
            "subcategory":"Memorial",
            "type":"Public Place"
        }
    ],
    "sg:phone":"+32 56 32 67 79",
    "sg:postcode":"8790",
    "sg:province":"West-Vlaanderen",
    "sg:tags":[
        "-",
        "monument"
    ],
    "wof:name":"Vandendriessche M",
    "wof:placetype":"venue"
},
  "geometry": {"coordinates":[3.4061419964,50.8943252563],"type":"Point"}
}