{
  "type": "Feature",
  "properties": {
    "addr:full":"Chauss\u00e9e De Tirlemont 7 Wanze Li\u00e8ge 4520",
    "addr:housenumber":"7",
    "addr:postcode":"4520",
    "addr:street":"Chausse\u0301E De Tirlemont",
    "iso:country":"BE",
    "sg:address":"Chauss\u00e9e De Tirlemont 7",
    "sg:city":"Wanze",
    "sg:classifiers":[
        {
            "category":"Health Services",
            "subcategory":"Dentist",
            "type":"Services"
        }
    ],
    "sg:phone":"+32 85 23 41 83",
    "sg:postcode":"4520",
    "sg:province":"Li\u00e8ge",
    "wof:name":"L\u00e9onard C\u00e9cile",
    "wof:placetype":"venue"
},
  "geometry": {"coordinates":[5.2190442085,50.5322151184],"type":"Point"}
}