{
  "type": "Feature",
  "properties": {
    "iso:country":"BE",
    "sg:address":"Grotstraat 41",
    "sg:city":"Wuustwezel",
    "sg:orig_category":"Catering and organisatie van feesten",
    "sg:phone":"+32 3 663 55 18",
    "sg:postcode":"2990",
    "sg:province":"Antwerpen",
    "wof:name":"Guido Elst",
    "wof:placetype":"venue"
},
  "geometry": {"coordinates":[4.5993771553,51.3888626099],"type":"Point"}
}