{
  "type": "Feature",
  "properties": {
    "addr:full":"Grand'rue 31 Habay Luxembourg 6724",
    "addr:housenumber":"31",
    "addr:postcode":"6724",
    "addr:street":"Grand'Rue",
    "iso:country":"BE",
    "sg:address":"Grand'rue 31",
    "sg:city":"Habay",
    "sg:orig_category":"Salons de coiffure. Centres de relaxation and bien-\u00eatre",
    "sg:phone":"+32 63 41 23 97",
    "sg:postcode":"6724",
    "sg:province":"Luxembourg",
    "wof:name":"Coiffure Espace",
    "wof:placetype":"venue"
},
  "geometry": {"coordinates":[5.5386037827,49.7265663147],"type":"Point"}
}