{
  "type": "Feature",
  "properties": {
    "iso:country":"BE",
    "sg:address":"Burgemeester Achiel Heymanstraat 79",
    "sg:city":"Temse (tielrode)",
    "sg:classifiers":[
        {
            "category":"Real Estate",
            "subcategory":"Architect",
            "type":"Services"
        }
    ],
    "sg:phone":"+32 3 771 14 57",
    "sg:postcode":"9140",
    "sg:province":"Oost-Vlaanderen",
    "wof:name":"Spiessens L",
    "wof:placetype":"venue"
},
  "geometry": {"coordinates":[4.1810407639,51.1146659851],"type":"Point"}
}