{
  "type": "Feature",
  "properties": {
    "iso:country":"BE",
    "sg:address":"Avenue De Maire 2",
    "sg:city":"Tournai",
    "sg:classifiers":[
        {
            "category":"Taxi",
            "type":"Transportation"
        }
    ],
    "sg:phone":"+32 495 22 28 79",
    "sg:postcode":"7500",
    "sg:province":"Hainaut",
    "sg:tags":[
        "taxi's"
    ],
    "wof:name":"Charly Taxi",
    "wof:placetype":"venue"
},
  "geometry": {"coordinates":[3.3782989979,50.6128120422],"type":"Point"}
}