{
  "type": "Feature",
  "properties": {
    "iso:country":"BE",
    "sg:address":"Graaf Joseph De Meeusstraat 8",
    "sg:city":"Overijse",
    "sg:classifiers":[
        {
            "category":"Communications",
            "type":"Services"
        }
    ],
    "sg:phone":"+32 2 657 34 73",
    "sg:postcode":"3090",
    "sg:province":"Vlaams-Brabant",
    "sg:tags":[
        "translator"
    ],
    "wof:name":"Edge Multilingual Translating, Copywriting & Technical Writing",
    "wof:placetype":"venue"
},
  "geometry": {"coordinates":[4.4861049652,50.7916870117],"type":"Point"}
}