{
  "type": "Feature",
  "properties": {
    "addr:full":"Dreve Richelle 161b23-24 Waterloo Brabant Wallon 1410",
    "addr:postcode":"1410",
    "addr:street":"Dreve;161B23-24",
    "iso:country":"BE",
    "sg:address":"Dreve Richelle 161b23-24",
    "sg:city":"Waterloo",
    "sg:classifiers":[
        {
            "category":"Farming",
            "subcategory":"Fish & Marine Products",
            "type":"Manufacturing & Wholesale Goods"
        }
    ],
    "sg:phone":"+32 2 352 72 00",
    "sg:postcode":"1410",
    "sg:province":"Brabant Wallon",
    "sg:tags":[
        "incontinence"
    ],
    "wof:name":"Conva Tec-a Division Of Bristol Myers Squibb S.a.",
    "wof:placetype":"venue"
},
  "geometry": {"coordinates":[4.4104981422,50.7075843811],"type":"Point"}
}