{
  "type": "Feature",
  "properties": {
    "iso:country":"BE",
    "sg:address":"Rue De Maubeuge 22",
    "sg:city":"Colfontaine",
    "sg:orig_category":"Plomberie, chauffage and installations sanitaires",
    "sg:phone":"+32 65 66 29 65",
    "sg:postcode":"7340",
    "sg:province":"Hainaut",
    "wof:name":"Fe. Richard",
    "wof:placetype":"venue"
},
  "geometry": {"coordinates":[3.8544480801,50.4118614197],"type":"Point"}
}