{
  "type": "Feature",
  "properties": {
    "addr:full":"Lippenslaan 90 Knokke-heist West-Vlaanderen 8300",
    "addr:housenumber":"90",
    "addr:postcode":"8300",
    "addr:street":"Lippenslaan",
    "iso:country":"BE",
    "sg:address":"Lippenslaan 90",
    "sg:city":"Knokke-heist",
    "sg:orig_category":"R\u00e9parations d'horloges, montres and bijoux. Bijouteries and horlogeries",
    "sg:phone":"+32 50 60 53 31",
    "sg:postcode":"8300",
    "sg:province":"West-Vlaanderen",
    "wof:name":"Geert Flama",
    "wof:placetype":"venue"
},
  "geometry": {"coordinates":[3.2883179188,51.3443031311],"type":"Point"}
}