{
  "type": "Feature",
  "properties": {
    "iso:country":"BE",
    "sg:address":"Rue De Houdain 17",
    "sg:city":"Mons",
    "sg:orig_category":"Non-Classified Establishments",
    "sg:phone":"+32 65 31 59 73",
    "sg:postcode":"7000",
    "sg:province":"Hainaut",
    "wof:name":"Cr\u00e9ations Cosmetiques Sa",
    "wof:placetype":"venue"
},
  "geometry": {"coordinates":[3.9522309303,50.4519691467],"type":"Point"}
}