{
  "type": "Feature",
  "properties": {
    "addr:full":"Pannenstraat 58 Knokke-heist (heist-aan-zee) West-Vlaanderen 8301",
    "addr:housenumber":"58",
    "addr:postcode":"8301",
    "addr:street":"Pannenstraat",
    "iso:country":"BE",
    "sg:address":"Pannenstraat 58",
    "sg:city":"Knokke-heist (heist-aan-zee)",
    "sg:classifiers":[
        {
            "category":"Bars & Pubs",
            "type":"Food & Drink"
        }
    ],
    "sg:phone":"+32 50 51 03 93",
    "sg:postcode":"8301",
    "sg:province":"West-Vlaanderen",
    "wof:name":"Oosthoek Caf\u00e9",
    "wof:placetype":"venue"
},
  "geometry": {"coordinates":[3.2639000416,51.3396911621],"type":"Point"}
}