{
  "type": "Feature",
  "properties": {
    "addr:full":"Knaptandstraat 1 Lokeren Oost-Vlaanderen 9160",
    "addr:housenumber":"1",
    "addr:postcode":"9160",
    "addr:street":"Knaptandstraat",
    "iso:country":"BE",
    "sg:address":"Knaptandstraat 1",
    "sg:city":"Lokeren",
    "sg:classifiers":[
        {
            "category":"Arena",
            "subcategory":"Sports Club",
            "type":"Entertainment"
        }
    ],
    "sg:phone":"+32 9 348 13 51",
    "sg:postcode":"9160",
    "sg:province":"Oost-Vlaanderen",
    "wof:name":"The Classics",
    "wof:placetype":"venue"
},
  "geometry": {"coordinates":[3.9841110706,51.1013259888],"type":"Point"}
}