{
  "type": "Feature",
  "properties": {
    "addr:full":"Platte Lostraat 346 Leuven (kessel-lo) Vlaams-Brabant 3010",
    "addr:housenumber":"346",
    "addr:postcode":"3010",
    "addr:street":"Platte Lostraat",
    "iso:country":"BE",
    "sg:address":"Platte Lostraat 346",
    "sg:city":"Leuven (kessel-lo)",
    "sg:classifiers":[
        {
            "category":"Food & Beverages",
            "subcategory":"Specialty",
            "type":"Retail Goods"
        }
    ],
    "sg:phone":"+32 16 25 26 14",
    "sg:postcode":"3010",
    "sg:province":"Vlaams-Brabant",
    "sg:tags":[
        "health",
        "dietary",
        "-",
        "biological"
    ],
    "wof:name":"Kamperfoelie",
    "wof:placetype":"venue"
},
  "geometry": {"coordinates":[4.7304501534,50.889755249],"type":"Point"}
}