{
  "type": "Feature",
  "properties": {
    "iso:country":"BE",
    "sg:address":"Ch De Tubize 483a",
    "sg:city":"Braine-lalleud",
    "sg:classifiers":[
        {
            "category":"Manufacturing",
            "subcategory":"Building Materials",
            "type":"Manufacturing & Wholesale Goods"
        }
    ],
    "sg:phone":"+32 2 384 25 35",
    "sg:postcode":"1420",
    "sg:province":"Brabant Wallon",
    "sg:tags":[
        "glass",
        "ceramic"
    ],
    "wof:name":"All-loc Sa",
    "wof:placetype":"venue"
},
  "geometry": {"coordinates":[4.3305020332,50.6930198669],"type":"Point"}
}