{
  "type": "Feature",
  "properties": {
    "addr:full":"Bronstraat 11 Geraardsbergen (waarbeke) Oost-Vlaanderen 9506",
    "addr:housenumber":"11",
    "addr:postcode":"9506",
    "addr:street":"Bronstraat",
    "iso:country":"BE",
    "sg:address":"Bronstraat 11",
    "sg:city":"Geraardsbergen (waarbeke)",
    "sg:classifiers":[
        {
            "category":"Professional",
            "subcategory":"Secretarial Services",
            "type":"Services"
        }
    ],
    "sg:phone":"+32 54 34 17 70",
    "sg:postcode":"9506",
    "sg:province":"Oost-Vlaanderen",
    "sg:tags":[
        "firm"
    ],
    "wof:name":"Waarbeke General Services",
    "wof:placetype":"venue"
},
  "geometry": {"coordinates":[3.9723949432,50.7773323059],"type":"Point"}
}