{
  "type": "Feature",
  "properties": {
    "iso:country":"BE",
    "sg:address":"De Burburestraat 1",
    "sg:city":"Antwerpen",
    "sg:orig_category":"Ordinateurs and \u00e9quipement informatique",
    "sg:phone":"+32 3 241 09 00",
    "sg:postcode":"2000",
    "sg:province":"Antwerpen",
    "wof:name":"Studio Lascaux",
    "wof:placetype":"venue"
},
  "geometry": {"coordinates":[4.3906202316,51.2096786499],"type":"Point"}
}