{
  "type": "Feature",
  "properties": {
    "iso:country":"BE",
    "sg:address":"Rue D'havr\u00c9 109",
    "sg:city":"Mons",
    "sg:classifiers":[
        {
            "category":"Cafe",
            "type":"Food & Drink"
        }
    ],
    "sg:phone":"+32 65 84 16 06",
    "sg:postcode":"7000",
    "sg:province":"Hainaut",
    "sg:tags":[
        "caf\u00e9s"
    ],
    "wof:name":"Caf\u00c9 Le Saint-nicolas",
    "wof:placetype":"venue"
},
  "geometry": {"coordinates":[3.9575610161,50.4540481567],"type":"Point"}
}