{
  "type": "Feature",
  "properties": {
    "iso:country":"BE",
    "sg:address":"Rue De Spa 31",
    "sg:city":"Ciney",
    "sg:orig_category":"P\u00e9pini\u00e9ristes. Constructions non r\u00e9sidentielles sp\u00e9cifiques. Entreprises de travail adapt\u00e9. Installa",
    "sg:phone":"+32 83 23 17 80",
    "sg:postcode":"5590",
    "sg:province":"Namur",
    "wof:name":"Village No 3",
    "wof:placetype":"venue"
},
  "geometry": {"coordinates":[5.1437492371,50.2727661133],"type":"Point"}
}