{
  "type": "Feature",
  "properties": {
    "addr:full":"Brusselsesteenweg 191 Melle Oost-Vlaanderen 9090",
    "addr:housenumber":"191",
    "addr:postcode":"9090",
    "addr:street":"Brusselsesteenweg",
    "iso:country":"BE",
    "sg:address":"Brusselsesteenweg 191",
    "sg:city":"Melle",
    "sg:classifiers":[
        {
            "category":"Government",
            "subcategory":"Fire Station",
            "type":"Public Place"
        }
    ],
    "sg:phone":"+32 9 232 59 45",
    "sg:postcode":"9090",
    "sg:province":"Oost-Vlaanderen",
    "sg:tags":[
        "packard",
        "nec",
        "bell"
    ],
    "wof:name":"Win Computers",
    "wof:placetype":"venue"
},
  "geometry": {"coordinates":[3.7910470963,51.0105628967],"type":"Point"}
}