{
  "type": "Feature",
  "properties": {
    "addr:full":"Engelstraat 32 Ichtegem West-Vlaanderen 8480",
    "addr:housenumber":"32",
    "addr:postcode":"8480",
    "addr:street":"Engelstraat",
    "iso:country":"BE",
    "sg:address":"Engelstraat 32",
    "sg:city":"Ichtegem",
    "sg:classifiers":[
        {
            "category":"Food & Beverages",
            "subcategory":"Meat & Fish",
            "type":"Retail Goods"
        }
    ],
    "sg:phone":"+32 51 58 23 03",
    "sg:postcode":"8480",
    "sg:province":"West-Vlaanderen",
    "sg:tags":[
        "vi",
        "zeevruchten"
    ],
    "wof:name":"Alain Gosselin",
    "wof:placetype":"venue"
},
  "geometry": {"coordinates":[3.0138709545,51.093082428],"type":"Point"}
}