{
  "type": "Feature",
  "properties": {
    "addr:full":"Rue Paul Janson 202 Gr\u00c2ce-hollogne Li\u00e8ge 4460",
    "addr:housenumber":"202",
    "addr:postcode":"4460",
    "addr:street":"Rue Paul Janson",
    "iso:country":"BE",
    "sg:address":"Rue Paul Janson 202",
    "sg:city":"Gr\u00c2ce-hollogne",
    "sg:orig_category":"Traitements param\u00e9dicaux",
    "sg:phone":"+32 4 233 13 84",
    "sg:postcode":"4460",
    "sg:province":"Li\u00e8ge",
    "wof:name":"Y. Straat",
    "wof:placetype":"venue"
},
  "geometry": {"coordinates":[5.5015501976,50.6315536499],"type":"Point"}
}