{
  "type": "Feature",
  "properties": {
    "iso:country":"BE",
    "sg:address":"Geistingen 26",
    "sg:city":"Kinrooi (ophoven)",
    "sg:classifiers":[
        {
            "category":"Health Services",
            "subcategory":"Health Practitioner",
            "type":"Services"
        }
    ],
    "sg:phone":"+32 89 57 25 16",
    "sg:postcode":"3640",
    "sg:province":"Limburg",
    "sg:tags":[
        "physiotherapist"
    ],
    "wof:name":"Knabben Peter",
    "wof:placetype":"venue"
},
  "geometry": {"coordinates":[5.8082442284,51.1322212219],"type":"Point"}
}