{
  "type": "Feature",
  "properties": {
    "addr:full":"Avenue P. Gilsom 470 Drogenbos Vlaams-Brabant 1620",
    "addr:housenumber":"470",
    "addr:postcode":"1620",
    "addr:street":"Avenue P. Gilsom",
    "iso:country":"BE",
    "sg:address":"Avenue P. Gilsom 470",
    "sg:city":"Drogenbos",
    "sg:orig_category":"Diverse machines voor de nijverheid Gh",
    "sg:phone":"+32 3 377 00 71",
    "sg:postcode":"1620",
    "sg:province":"Vlaams-Brabant",
    "wof:name":"Lincoln Smitveld Belgium",
    "wof:placetype":"venue"
},
  "geometry": {"coordinates":[4.3174529076,50.7868804932],"type":"Point"}
}