{
  "type": "Feature",
  "properties": {
    "iso:country":"BE",
    "sg:address":"Nieuwstraat 29",
    "sg:city":"Beringen",
    "sg:classifiers":[
        {
            "category":"Cafe",
            "type":"Food & Drink"
        }
    ],
    "sg:phone":"+32 11 42 60 76",
    "sg:postcode":"3581",
    "sg:province":"Limburg",
    "sg:tags":[
        "caf\u00e9s"
    ],
    "wof:name":"Louis Dries",
    "wof:placetype":"venue"
},
  "geometry": {"coordinates":[5.2219600677,51.0745315552],"type":"Point"}
}