{
  "type": "Feature",
  "properties": {
    "addr:full":"Gentweg 43 Kaprijke Oost-Vlaanderen 9971",
    "addr:housenumber":"43",
    "addr:postcode":"9971",
    "addr:street":"Gentweg",
    "iso:country":"BE",
    "sg:address":"Gentweg 43",
    "sg:city":"Kaprijke",
    "sg:orig_category":"Producteurs de l\u00e9gumes. Fruits and l\u00e9gumes Gr",
    "sg:phone":"+32 9 377 24 52",
    "sg:postcode":"9971",
    "sg:province":"Oost-Vlaanderen",
    "wof:name":"Bernard Pattyn",
    "wof:placetype":"venue"
},
  "geometry": {"coordinates":[3.6357660294,51.1942138672],"type":"Point"}
}