{
  "type": "Feature",
  "properties": {
    "addr:full":"Antwerpsestraat 103 Mortsel Antwerpen 2640",
    "addr:housenumber":"103",
    "addr:postcode":"2640",
    "addr:street":"Antwerpsestraat",
    "iso:country":"BE",
    "sg:address":"Antwerpsestraat 103",
    "sg:city":"Mortsel",
    "sg:orig_category":"D\u00e9taillants en pi\u00e8ces and accessoires de voitures. Mat\u00e9riel de T\u00e9l\u00e9communication",
    "sg:phone":"+32 3 449 73 35",
    "sg:postcode":"2640",
    "sg:province":"Antwerpen",
    "wof:name":"Mobitel",
    "wof:placetype":"venue"
},
  "geometry": {"coordinates":[4.4434571266,51.1734962463],"type":"Point"}
}