{
  "type": "Feature",
  "properties": {
    "iso:country":"BE",
    "sg:address":"Warande 15ba",
    "sg:city":"Sint-laureins",
    "sg:orig_category":"Binnenhuisarchitecten",
    "sg:phone":"+32 9 379 90 20",
    "sg:postcode":"9982",
    "sg:province":"Oost-Vlaanderen",
    "wof:name":"Rik Muylle",
    "wof:placetype":"venue"
},
  "geometry": {"coordinates":[3.5907709599,51.2458992004],"type":"Point"}
}