{
  "type": "Feature",
  "properties": {
    "addr:full":"Rue Elisielle 35 Honnelles Hainaut 7387",
    "addr:housenumber":"35",
    "addr:postcode":"7387",
    "addr:street":"Rue Elisielle;Hainaut",
    "iso:country":"BE",
    "sg:address":"Rue Elisielle 35",
    "sg:city":"Honnelles",
    "sg:classifiers":[
        {
            "category":"Arena",
            "subcategory":"Sports Club",
            "type":"Entertainment"
        }
    ],
    "sg:phone":"+32 65 75 96 18",
    "sg:postcode":"7387",
    "sg:province":"Hainaut",
    "sg:tags":[
        "de"
    ],
    "wof:name":"W.c. Comit\u00c9 F\u00cates Angrois",
    "wof:placetype":"venue"
},
  "geometry": {"coordinates":[3.6959619522,50.3661155701],"type":"Point"}
}