{
  "type": "Feature",
  "properties": {
    "iso:country":"BE",
    "sg:address":"De Fierlantstraat 155ba",
    "sg:city":"Vorst/forest",
    "sg:orig_category":"Reclamebureaus",
    "sg:phone":"+32 2 347 08 62",
    "sg:postcode":"1190",
    "sg:province":"Bruxelles-Capitale",
    "wof:name":"N. Langerman",
    "wof:placetype":"venue"
},
  "geometry": {"coordinates":[4.331884861,50.8236045837],"type":"Point"}
}