{
  "type": "Feature",
  "properties": {
    "addr:full":"Dalstraat 80 Mol Antwerpen 2400",
    "addr:housenumber":"80",
    "addr:postcode":"2400",
    "addr:street":"Dalstraat",
    "iso:country":"BE",
    "sg:address":"Dalstraat 80",
    "sg:city":"Mol",
    "sg:classifiers":[
        {
            "category":"Building & Trades",
            "subcategory":"Construction",
            "type":"Services"
        }
    ],
    "sg:phone":"+32 14 31 06 05",
    "sg:postcode":"2400",
    "sg:province":"Antwerpen",
    "sg:tags":[
        "carpenter"
    ],
    "wof:name":"Bogaerts",
    "wof:placetype":"venue"
},
  "geometry": {"coordinates":[5.1346740723,51.2016639709],"type":"Point"}
}