{
  "type": "Feature",
  "properties": {
    "addr:full":"Bredabaan 985 Brasschaat Antwerpen 2930",
    "addr:housenumber":"985",
    "addr:postcode":"2930",
    "addr:street":"Bredabaan",
    "iso:country":"BE",
    "sg:address":"Bredabaan 985",
    "sg:city":"Brasschaat",
    "sg:orig_category":"Avocats and conseillers juridiques",
    "sg:phone":"+32 3 633 30 77",
    "sg:postcode":"2930",
    "sg:province":"Antwerpen",
    "wof:name":"W. Leyssens",
    "wof:placetype":"venue"
},
  "geometry": {"coordinates":[4.5191688538,51.3207359314],"type":"Point"}
}