{
  "type": "Feature",
  "properties": {
    "addr:full":"Meybroekstraat 77 Hasselt (kermt) Limburg 3510",
    "addr:housenumber":"77",
    "addr:postcode":"3510",
    "addr:street":"Meybroekstraat",
    "iso:country":"BE",
    "sg:address":"Meybroekstraat 77",
    "sg:city":"Hasselt (kermt)",
    "sg:classifiers":[
        {
            "category":"Professional",
            "subcategory":"Accounting & Tax Preparation",
            "type":"Services"
        }
    ],
    "sg:phone":"+32 11 25 60 68",
    "sg:postcode":"3510",
    "sg:province":"Limburg",
    "sg:tags":[
        "accountant"
    ],
    "wof:name":"Gijbels D",
    "wof:placetype":"venue"
},
  "geometry": {"coordinates":[5.2531552315,50.9474906921],"type":"Point"}
}