{
  "type": "Feature",
  "properties": {
    "iso:country":"BE",
    "sg:address":"Rue Darchis 1a",
    "sg:city":"Li\u00e8ge 1",
    "sg:classifiers":[
        {
            "category":"Health Services",
            "subcategory":"Doctor",
            "type":"Services"
        }
    ],
    "sg:phone":"+32 4 365 44 66",
    "sg:postcode":"4000",
    "sg:province":"Li\u00e8ge",
    "sg:tags":[
        "medicinephysicians",
        "surgeon"
    ],
    "wof:name":"Bar\u00e9 Jean-louis",
    "wof:placetype":"venue"
},
  "geometry": {"coordinates":[5.5673651695,50.6371154785],"type":"Point"}
}