{
  "type": "Feature",
  "properties": {
    "addr:full":"Oostnieuwkerksesteenweg 124 Roeselare West-Vlaanderen 8800",
    "addr:housenumber":"124",
    "addr:postcode":"8800",
    "addr:street":"Oostnieuwkerksesteenweg",
    "iso:country":"BE",
    "sg:address":"Oostnieuwkerksesteenweg 124",
    "sg:city":"Roeselare",
    "sg:orig_category":"Tuinen",
    "sg:phone":"+32 51 21 00 82",
    "sg:postcode":"8800",
    "sg:province":"West-Vlaanderen",
    "wof:name":"Degraeve Tuinen",
    "wof:placetype":"venue"
},
  "geometry": {"coordinates":[3.099118948,50.9467811584],"type":"Point"}
}