{
  "type": "Feature",
  "properties": {
    "addr:full":"Drift 31 De Haan West-Vlaanderen 8420",
    "addr:housenumber":"31",
    "addr:postcode":"8420",
    "addr:street":"Drift",
    "iso:country":"BE",
    "sg:address":"Drift 31",
    "sg:city":"De Haan",
    "sg:orig_category":"G\u00e9om\u00e8tres",
    "sg:phone":"+32 50 41 43 60",
    "sg:postcode":"8420",
    "sg:province":"West-Vlaanderen",
    "wof:name":"De Craemer Patrick",
    "wof:placetype":"venue"
},
  "geometry": {"coordinates":[3.0309100151,51.2717056274],"type":"Point"}
}