{
  "type": "Feature",
  "properties": {
    "iso:country":"BE",
    "sg:address":"Kleine Vos 5",
    "sg:city":"Dilbeek",
    "sg:classifiers":[
        {
            "category":"Real Estate",
            "subcategory":"Architect",
            "type":"Services"
        }
    ],
    "sg:phone":"+32 2 466 84 57",
    "sg:postcode":"1700",
    "sg:province":"Vlaams-Brabant",
    "wof:name":"Peeters K",
    "wof:placetype":"venue"
},
  "geometry": {"coordinates":[4.2401981354,50.8626251221],"type":"Point"}
}