{
  "type": "Feature",
  "properties": {
    "iso:country":"BE",
    "sg:address":"Chauss\u00c9e De Lessines 184",
    "sg:city":"Soignies",
    "sg:orig_category":"Eleveurs de bovins",
    "sg:phone":"+32 67 45 83 29",
    "sg:postcode":"7060",
    "sg:province":"Hainaut",
    "wof:name":"Henri Dewinne",
    "wof:placetype":"venue"
},
  "geometry": {"coordinates":[4.0551600456,50.5896911621],"type":"Point"}
}