{
  "type": "Feature",
  "properties": {
    "iso:country":"BE",
    "sg:address":"Broekstraat 45",
    "sg:city":"Diest",
    "sg:classifiers":[
        {
            "category":"Food & Beverages",
            "subcategory":"Fruits & Vegetables",
            "type":"Retail Goods"
        }
    ],
    "sg:phone":"+32 13 32 88 68",
    "sg:postcode":"3294",
    "sg:province":"Vlaams-Brabant",
    "sg:tags":[
        "l\u00e9gumes"
    ],
    "wof:name":"D & D",
    "wof:placetype":"venue"
},
  "geometry": {"coordinates":[5.0159769058,50.9996185303],"type":"Point"}
}