{
  "type": "Feature",
  "properties": {
    "iso:country":"BE",
    "sg:address":"Avenue Paul Hymans 126 Box 13",
    "sg:city":"Bruxelles (woluwe-saint-lambert)",
    "sg:classifiers":[
        {
            "category":"Wholesale",
            "subcategory":"Books, Periodicals, & Newspapers",
            "type":"Manufacturing & Wholesale Goods"
        }
    ],
    "sg:phone":"+32 2 779 17 40",
    "sg:postcode":"1200",
    "sg:province":"Bruxelles-Capitale",
    "sg:tags":[
        "publisher"
    ],
    "wof:name":"Libellus Benelux",
    "wof:placetype":"venue"
},
  "geometry": {"coordinates":[4.4352459908,50.8469276428],"type":"Point"}
}