{
  "type": "Feature",
  "properties": {
    "addr:full":"Rue Henri Lema\u00cetre 19 Namur Namur 5000",
    "addr:housenumber":"19",
    "addr:postcode":"5000",
    "addr:street":"Rue Henri Lemai\u0302Tre",
    "iso:country":"BE",
    "sg:address":"Rue Henri Lema\u00cetre 19",
    "sg:city":"Namur",
    "sg:orig_category":"Maisons de repos and r\u00e9sidences",
    "sg:phone":"+32 81 73 81 84",
    "sg:postcode":"5000",
    "sg:province":"Namur",
    "wof:name":"Home A L'edelweiss",
    "wof:placetype":"venue"
},
  "geometry": {"coordinates":[4.8538627625,50.4655532837],"type":"Point"}
}