{
  "type": "Feature",
  "properties": {
    "addr:full":"Avenue Des Cerisiers 23 Pecq Hainaut 7740",
    "addr:housenumber":"23",
    "addr:postcode":"7740",
    "addr:street":"Avenue Des Cerisiers",
    "iso:country":"BE",
    "sg:address":"Avenue Des Cerisiers 23",
    "sg:city":"Pecq",
    "sg:classifiers":[
        {
            "category":"Professional",
            "subcategory":"Accounting & Tax Preparation",
            "type":"Services"
        }
    ],
    "sg:phone":"+32 69 55 91 42",
    "sg:postcode":"7740",
    "sg:province":"Hainaut",
    "sg:tags":[
        "accountant"
    ],
    "wof:name":"Laurent Hautecoeur",
    "wof:placetype":"venue"
},
  "geometry": {"coordinates":[3.3346369267,50.6838722229],"type":"Point"}
}