{
  "type": "Feature",
  "properties": {
    "iso:country":"BE",
    "sg:address":"Schaapstraat 8",
    "sg:city":"Zwevegem (heestert)",
    "sg:classifiers":[
        {
            "category":"Social Services",
            "subcategory":"Job Training",
            "type":"Services"
        }
    ],
    "sg:phone":"+32 56 64 56 18",
    "sg:postcode":"8551",
    "sg:province":"West-Vlaanderen",
    "sg:tags":[
        "coordinator",
        "safety"
    ],
    "wof:name":"Vecovan Comm. V.",
    "wof:placetype":"venue"
},
  "geometry": {"coordinates":[3.4109840393,50.782283783],"type":"Point"}
}