{
  "type": "Feature",
  "properties": {
    "addr:full":"Napoleonsdijk 2 Bocholt Limburg 3950",
    "addr:housenumber":"2",
    "addr:postcode":"3950",
    "addr:street":"Napoleonsdijk",
    "iso:country":"BE",
    "sg:address":"Napoleonsdijk 2",
    "sg:city":"Bocholt",
    "sg:orig_category":"Groententeelt",
    "sg:phone":"+32 89 46 48 69",
    "sg:postcode":"3950",
    "sg:province":"Limburg",
    "wof:name":"Marcel Bloemen",
    "wof:placetype":"venue"
},
  "geometry": {"coordinates":[5.6310019493,51.1871910095],"type":"Point"}
}