{
  "type": "Feature",
  "properties": {
    "addr:full":"Rondehuisjesdreef 6 Gent (drongen) Oost-Vlaanderen 9031",
    "addr:housenumber":"6",
    "addr:postcode":"9031",
    "addr:street":"Rondehuisjesdreef",
    "iso:country":"BE",
    "sg:address":"Rondehuisjesdreef 6",
    "sg:city":"Gent (drongen)",
    "sg:classifiers":[
        {
            "category":"Shopping",
            "subcategory":"Discount & Variety Stores",
            "type":"Retail Goods"
        }
    ],
    "sg:phone":"+32 9 227 68 63",
    "sg:postcode":"9031",
    "sg:province":"Oost-Vlaanderen",
    "sg:tags":[
        "shop",
        "clearers",
        "curiosity",
        "furniture"
    ],
    "wof:name":"Brocante Le Bibelot",
    "wof:placetype":"venue"
},
  "geometry": {"coordinates":[3.6610510349,51.0513763428],"type":"Point"}
}