{
  "type": "Feature",
  "properties": {
    "addr:full":"Cit\u00c9 De Bayemont 1 Charleroi Hainaut 6040",
    "addr:housenumber":"1",
    "addr:postcode":"6040",
    "addr:street":"Cite\u0301 De Bayemont;Hainaut",
    "iso:country":"BE",
    "sg:address":"Cit\u00c9 De Bayemont 1",
    "sg:city":"Charleroi",
    "sg:orig_category":"Installation de serres, double vitrage and fen\u00eatres. Installation de menuiserie m\u00e9tallique. Installa",
    "sg:phone":"+32 71 32 28 33",
    "sg:postcode":"6040",
    "sg:province":"Hainaut",
    "wof:name":"Petroons",
    "wof:placetype":"venue"
},
  "geometry": {"coordinates":[4.413392067,50.4337425232],"type":"Point"}
}