{
  "type": "Feature",
  "properties": {
    "iso:country":"BE",
    "sg:address":"Lange Zoutstraat 41bb",
    "sg:city":"Aalst",
    "sg:orig_category":"Chaussures. V\u00eatements",
    "sg:phone":"+32 53 78 85 60",
    "sg:postcode":"9300",
    "sg:province":"Oost-Vlaanderen",
    "wof:name":"Pronti",
    "wof:placetype":"venue"
},
  "geometry": {"coordinates":[4.0394001007,50.9368476868],"type":"Point"}
}