{
  "type": "Feature",
  "properties": {
    "iso:country":"BE",
    "sg:address":"Drogenbroodstraat 71",
    "sg:city":"Evergem",
    "sg:orig_category":"Plaatsen van vloer- and muurbekleding Speciaalzaken Vloer- and muurbekleding",
    "sg:phone":"+32 9 357 40 40",
    "sg:postcode":"9940",
    "sg:province":"Oost-Vlaanderen",
    "wof:name":"Willems",
    "wof:placetype":"venue"
},
  "geometry": {"coordinates":[3.7329099178,51.1344909668],"type":"Point"}
}