{
  "type": "Feature",
  "properties": {
    "addr:full":"Steenweg Op Turnhout 35 Oud-turnhout Antwerpen 2360",
    "addr:housenumber":"35",
    "addr:postcode":"2360",
    "addr:street":"Steenweg Op Turnhout",
    "iso:country":"BE",
    "sg:address":"Steenweg Op Turnhout 35",
    "sg:city":"Oud-turnhout",
    "sg:classifiers":[
        {
            "category":"Shopping",
            "subcategory":"Crafts & Fabrics",
            "type":"Retail Goods"
        }
    ],
    "sg:phone":"+32 14 45 34 25",
    "sg:postcode":"2360",
    "sg:province":"Antwerpen",
    "sg:tags":[
        "textile",
        "clothing"
    ],
    "wof:name":"J & H Bvba",
    "wof:placetype":"venue"
},
  "geometry": {"coordinates":[4.9782361984,51.3192977905],"type":"Point"}
}