{
  "type": "Feature",
  "properties": {
    "iso:country":"BE",
    "sg:address":"Rue De L'egalit\u00c9 222",
    "sg:city":"Seraing",
    "sg:orig_category":"Pharmaciens",
    "sg:phone":"+32 4 336 59 32",
    "sg:postcode":"4102",
    "sg:province":"Li\u00e8ge",
    "wof:name":"L. Petit",
    "wof:placetype":"venue"
},
  "geometry": {"coordinates":[5.5376629829,50.5966262817],"type":"Point"}
}