{
  "type": "Feature",
  "properties": {
    "iso:country":"BE",
    "sg:address":"Avenue De La Couronne 416",
    "sg:city":"Elsene/ixelles",
    "sg:orig_category":"Imprimeries and copyshops",
    "sg:phone":"+32 2 648 76 05",
    "sg:postcode":"1050",
    "sg:province":"Bruxelles-Capitale",
    "wof:name":"Copies Prima",
    "wof:placetype":"venue"
},
  "geometry": {"coordinates":[4.3890829086,50.8218231201],"type":"Point"}
}