{
  "type": "Feature",
  "properties": {
    "addr:full":"Gasthuisstraat 46 Turnhout Antwerpen 2300",
    "addr:housenumber":"46",
    "addr:postcode":"2300",
    "addr:street":"Gasthuisstraat",
    "iso:country":"BE",
    "sg:address":"Gasthuisstraat 46",
    "sg:city":"Turnhout",
    "sg:classifiers":[
        {
            "category":"Shopping",
            "subcategory":"Beauty & Cosmetics",
            "type":"Retail Goods"
        }
    ],
    "sg:phone":"+32 14 41 61 99",
    "sg:postcode":"2300",
    "sg:province":"Antwerpen",
    "sg:tags":[
        "-",
        "perfumery"
    ],
    "wof:name":"Evabel",
    "wof:placetype":"venue"
},
  "geometry": {"coordinates":[4.9448480606,51.3224983215],"type":"Point"}
}