{
  "type": "Feature",
  "properties": {
    "addr:full":"Papiermolenstraat 103 Geraardsbergen Oost-Vlaanderen 9500",
    "addr:housenumber":"103",
    "addr:postcode":"9500",
    "addr:street":"Papiermolenstraat",
    "iso:country":"BE",
    "sg:address":"Papiermolenstraat 103",
    "sg:city":"Geraardsbergen",
    "sg:classifiers":[
        {
            "category":"Education",
            "subcategory":"School",
            "type":"Public Place"
        }
    ],
    "sg:phone":"+32 54 41 21 88",
    "sg:postcode":"9500",
    "sg:province":"Oost-Vlaanderen",
    "sg:tags":[
        "secondary"
    ],
    "wof:name":"Koninklijk Techn Atheneum Geraardsbergen",
    "wof:placetype":"venue"
},
  "geometry": {"coordinates":[3.8698399067,50.7702789307],"type":"Point"}
}