{
  "type": "Feature",
  "properties": {
    "iso:country":"BE",
    "sg:address":"Tramweglei 35",
    "sg:city":"Lier",
    "sg:classifiers":[
        {
            "category":"Communications",
            "subcategory":"Newspaper",
            "type":"Services"
        }
    ],
    "sg:phone":"+32 3 480 07 34",
    "sg:postcode":"2500",
    "sg:province":"Antwerpen",
    "sg:tags":[
        "paper",
        "local",
        "free"
    ],
    "wof:name":"Het Reclameblad Voor Groot Lier",
    "wof:placetype":"venue"
},
  "geometry": {"coordinates":[4.5588641167,51.1348381042],"type":"Point"}
}