{
  "type": "Feature",
  "properties": {
    "iso:country":"BE",
    "sg:address":"Doornstraat 25",
    "sg:city":"De Panne",
    "sg:orig_category":"Travaux de pl\u00e2trage",
    "sg:phone":"+32 58 41 35 58",
    "sg:postcode":"8660",
    "sg:province":"West-Vlaanderen",
    "wof:name":"Thomas & Zonen",
    "wof:placetype":"venue"
},
  "geometry": {"coordinates":[2.59613204,51.0710029602],"type":"Point"}
}