{
  "type": "Feature",
  "properties": {
    "addr:full":"Maaltekouter 3 Gent Oost-Vlaanderen 9051",
    "addr:housenumber":"3",
    "addr:postcode":"9051",
    "addr:street":"Maaltekouter;Oost-Vlaanderen",
    "iso:country":"BE",
    "sg:address":"Maaltekouter 3",
    "sg:city":"Gent",
    "sg:orig_category":"Maisons de repos and r\u00e9sidences",
    "sg:phone":"+32 9 240 11 41",
    "sg:postcode":"9051",
    "sg:province":"Oost-Vlaanderen",
    "wof:name":"Residences Restel",
    "wof:placetype":"venue"
},
  "geometry": {"coordinates":[3.6882390976,51.0253486633],"type":"Point"}
}