{
  "type": "Feature",
  "properties": {
    "addr:full":"Rue Saint-roch 22bc Chaumont-gistoux Brabant Wallon 1325",
    "addr:housenumber":"22bc",
    "addr:postcode":"1325",
    "addr:street":"Rue Saint-Roch",
    "iso:country":"BE",
    "sg:address":"Rue Saint-roch 22bc",
    "sg:city":"Chaumont-gistoux",
    "sg:orig_category":"Dranken",
    "sg:phone":"+32 10 68 92 30",
    "sg:postcode":"1325",
    "sg:province":"Brabant Wallon",
    "wof:name":"Les Vins Du Rh\u00d4ne",
    "wof:placetype":"venue"
},
  "geometry": {"coordinates":[4.6825990677,50.6867752075],"type":"Point"}
}