{
  "type": "Feature",
  "properties": {
    "iso:country":"BE",
    "sg:address":"Pee\u00cbrweg 35",
    "sg:city":"Tongeren",
    "sg:orig_category":"Loodgieterij, verwarming and sanitaire installaties",
    "sg:phone":"+32 12 23 13 20",
    "sg:postcode":"3700",
    "sg:province":"Limburg",
    "wof:name":"Joseph Valle",
    "wof:placetype":"venue"
},
  "geometry": {"coordinates":[5.4977807999,50.749130249],"type":"Point"}
}