{
  "type": "Feature",
  "properties": {
    "addr:full":"Rue Augustin Melsens 17 Chi\u00e8vres (huissignies) Hainaut 7950",
    "addr:housenumber":"17",
    "addr:postcode":"7950",
    "addr:street":"Rue Augustin Melsens",
    "iso:country":"BE",
    "sg:address":"Rue Augustin Melsens 17",
    "sg:city":"Chi\u00e8vres (huissignies)",
    "sg:classifiers":[
        {
            "category":"Personal",
            "subcategory":"Nail Salon",
            "type":"Services"
        }
    ],
    "sg:phone":"+32 69 68 94 04",
    "sg:postcode":"7950",
    "sg:province":"Hainaut",
    "sg:tags":[
        "pedicure"
    ],
    "wof:name":"Laventure V",
    "wof:placetype":"venue"
},
  "geometry": {"coordinates":[3.7475039959,50.5651893616],"type":"Point"}
}