{
  "type": "Feature",
  "properties": {
    "addr:full":"15-17 Ambachtsweg Merelbeke Oost-Vlaanderen 9820",
    "addr:housenumber":"15-17",
    "addr:postcode":"9820",
    "addr:street":"Ambachtsweg",
    "iso:country":"BE",
    "sg:address":"15-17 Ambachtsweg",
    "sg:city":"Merelbeke",
    "sg:classifiers":[
        {
            "category":"Manufacturing",
            "subcategory":"Motor Vehicles & Parts",
            "type":"Manufacturing & Wholesale Goods"
        }
    ],
    "sg:phone":"+32 67 49 37 40",
    "sg:postcode":"9820",
    "sg:province":"Oost-Vlaanderen",
    "sg:tags":[
        "engine",
        "machine",
        "engineering",
        "-",
        "mechanical"
    ],
    "wof:name":"Avd Belgium Sprl",
    "wof:placetype":"venue"
},
  "geometry": {"coordinates":[4.3821101189,50.5902900696],"type":"Point"}
}