{
  "type": "Feature",
  "properties": {
    "addr:full":"Broekstraat 3 Tielt-winge Vlaams-Brabant 3390",
    "addr:housenumber":"3",
    "addr:postcode":"3390",
    "addr:street":"Broekstraat",
    "iso:country":"BE",
    "sg:address":"Broekstraat 3",
    "sg:city":"Tielt-winge",
    "sg:orig_category":"Traitements param\u00e9dicaux",
    "sg:phone":"+32 16 63 57 97",
    "sg:postcode":"3390",
    "sg:province":"Vlaams-Brabant",
    "wof:name":"C. De Rijk",
    "wof:placetype":"venue"
},
  "geometry": {"coordinates":[4.9236731529,50.9366989136],"type":"Point"}
}