{
  "type": "Feature",
  "properties": {
    "iso:country":"BE",
    "sg:address":"Blockmansstraat 31",
    "sg:city":"Kortenberg",
    "sg:classifiers":[
        {
            "category":"Cafe",
            "type":"Food & Drink"
        }
    ],
    "sg:phone":"+32 2 757 61 95",
    "sg:postcode":"3070",
    "sg:province":"Vlaams-Brabant",
    "sg:tags":[
        "caf\u00e9s"
    ],
    "wof:name":"Hadermann M.-verbelen I.",
    "wof:placetype":"venue"
},
  "geometry": {"coordinates":[4.5409841537,50.8885993958],"type":"Point"}
}