{
  "type": "Feature",
  "properties": {
    "iso:country":"BE",
    "sg:address":"Pontstraat 17",
    "sg:city":"Boortmeerbeek",
    "sg:classifiers":[
        {
            "category":"Building & Trades",
            "subcategory":"Landscaping Services",
            "type":"Services"
        }
    ],
    "sg:phone":"+32 15 51 29 76",
    "sg:postcode":"3190",
    "sg:province":"Vlaams-Brabant",
    "sg:tags":[
        "gardening",
        "garden",
        "maintenance"
    ],
    "wof:name":"Tuinen Vanlangendonck",
    "wof:placetype":"venue"
},
  "geometry": {"coordinates":[4.5610618591,50.9757614136],"type":"Point"}
}