{
  "type": "Feature",
  "properties": {
    "addr:full":"Rue Basse Hermalle 51 Vis\u00e9 Li\u00e8ge 4600",
    "addr:housenumber":"51",
    "addr:postcode":"4600",
    "addr:street":"Rue Basse Hermalle",
    "iso:country":"BE",
    "sg:address":"Rue Basse Hermalle 51",
    "sg:city":"Vis\u00e9",
    "sg:classifiers":[
        {
            "category":"Health Services",
            "subcategory":"Nursing And Care Facility",
            "type":"Services"
        }
    ],
    "sg:phone":"+32 4 379 80 03",
    "sg:postcode":"4600",
    "sg:province":"Li\u00e8ge",
    "sg:tags":[
        "home"
    ],
    "wof:name":"Legrand-paquot A-l",
    "wof:placetype":"venue"
},
  "geometry": {"coordinates":[5.6890130043,50.7338066101],"type":"Point"}
}