{
  "type": "Feature",
  "properties": {
    "addr:full":"Rue L\u00e9on Cuissez 45 Bruxelles (ixelles) Bruxelles-Capitale 1050",
    "addr:housenumber":"45",
    "addr:postcode":"1050",
    "addr:street":"Rue Le\u0301On Cuissez",
    "iso:country":"BE",
    "sg:address":"Rue L\u00e9on Cuissez 45",
    "sg:city":"Bruxelles (ixelles)",
    "sg:classifiers":[
        {
            "category":"Professional",
            "subcategory":"Computer Services",
            "type":"Services"
        }
    ],
    "sg:phone":"+32 2 649 41 91",
    "sg:postcode":"1050",
    "sg:province":"Bruxelles-Capitale",
    "sg:tags":[
        "-",
        "processing",
        "data"
    ],
    "wof:name":"Garance Monserrat",
    "wof:placetype":"venue"
},
  "geometry": {"coordinates":[4.3805570602,50.8239440918],"type":"Point"}
}