{
  "type": "Feature",
  "properties": {
    "iso:country":"BE",
    "sg:address":"Tervuursesteenweg 275",
    "sg:city":"Steenokkerzeel",
    "sg:orig_category":"Pain, p\u00e2tisseries and confiseries",
    "sg:phone":"+32 2 751 94 09",
    "sg:postcode":"1820",
    "sg:province":"Vlaams-Brabant",
    "wof:name":"Bakkerij Macharis",
    "wof:placetype":"venue"
},
  "geometry": {"coordinates":[4.5021147728,50.9186973572],"type":"Point"}
}