{
  "type": "Feature",
  "properties": {
    "iso:country":"BE",
    "sg:address":"Stationsstraat 10",
    "sg:city":"Essen",
    "sg:orig_category":"Banken and kredietinstellingen Verzekeringsmakelaars and experts",
    "sg:phone":"+32 3 667 33 90",
    "sg:postcode":"2910",
    "sg:province":"Antwerpen",
    "wof:name":"N.m.k.n.",
    "wof:placetype":"venue"
},
  "geometry": {"coordinates":[4.4675631523,51.4675292969],"type":"Point"}
}