{
  "type": "Feature",
  "properties": {
    "addr:full":"Karel Picqu\u00e9laan 6 Deinze Oost-Vlaanderen 9800",
    "addr:housenumber":"6",
    "addr:postcode":"9800",
    "addr:street":"Karel Picque\u0301Laan",
    "iso:country":"BE",
    "sg:address":"Karel Picqu\u00e9laan 6",
    "sg:city":"Deinze",
    "sg:classifiers":[
        {
            "category":"Building & Trades",
            "subcategory":"Electrical",
            "type":"Services"
        }
    ],
    "sg:phone":"+32 9 386 26 49",
    "sg:postcode":"9800",
    "sg:province":"Oost-Vlaanderen",
    "sg:tags":[
        "electric",
        "-",
        "housewiring",
        "contractor"
    ],
    "wof:name":"Mortier E",
    "wof:placetype":"venue"
},
  "geometry": {"coordinates":[3.5314939022,50.985786438],"type":"Point"}
}