{
  "type": "Feature",
  "properties": {
    "iso:country":"BE",
    "sg:address":"Peperstraat 34",
    "sg:city":"Herzele",
    "sg:orig_category":"Eclairage et \u00e9quipements du foyer. Textiles",
    "sg:phone":"+32 53 62 25 45",
    "sg:postcode":"9550",
    "sg:province":"Oost-Vlaanderen",
    "wof:name":"Huis De Cock",
    "wof:placetype":"venue"
},
  "geometry": {"coordinates":[3.8951261044,50.8846588135],"type":"Point"}
}