{
  "type": "Feature",
  "properties": {
    "addr:full":"Avenue De Tervueren 235 Sint-pieters-woluwe/woluwe-saint-pierre Bruxelles-Capitale 1150",
    "addr:housenumber":"235",
    "addr:postcode":"1150",
    "addr:street":"Avenue De Tervueren;/",
    "iso:country":"BE",
    "sg:address":"Avenue De Tervueren 235",
    "sg:city":"Sint-pieters-woluwe/woluwe-saint-pierre",
    "sg:orig_category":"H\u00f4tels",
    "sg:phone":"+32 2 762 80 91",
    "sg:postcode":"1150",
    "sg:province":"Bruxelles-Capitale",
    "wof:name":"H\u00d4tel Parachute",
    "wof:placetype":"venue"
},
  "geometry": {"coordinates":[4.4123592377,50.8360366821],"type":"Point"}
}