{
  "type": "Feature",
  "properties": {
    "iso:country":"BE",
    "sg:address":"Rue De Val D\u00b4away 7",
    "sg:city":"Virton",
    "sg:orig_category":"Opel Bedrijfsvoertuigen",
    "sg:phone":"+32 63 58 27 81",
    "sg:postcode":"6760",
    "sg:province":"Luxembourg",
    "wof:name":"Paul Fran\u00c7ois Garage",
    "wof:placetype":"venue"
},
  "geometry": {"coordinates":[5.532597065,49.5754776001],"type":"Point"}
}