{
  "type": "Feature",
  "properties": {
    "iso:country":"BE",
    "sg:address":"Roeselaarsestraat 594",
    "sg:city":"Izegem",
    "sg:orig_category":"Marktonderzoekbureaus Reclamebureaus",
    "sg:phone":"+32 51 33 54 00",
    "sg:postcode":"8870",
    "sg:province":"West-Vlaanderen",
    "wof:name":"Reclamebureau Artex",
    "wof:placetype":"venue"
},
  "geometry": {"coordinates":[3.1861870289,50.9263725281],"type":"Point"}
}