{
  "type": "Feature",
  "properties": {
    "addr:full":"Baron Opsomerlaan 63 Lier Antwerpen 2500",
    "addr:housenumber":"63",
    "addr:postcode":"2500",
    "addr:street":"Baron Opsomerlaan",
    "iso:country":"BE",
    "sg:address":"Baron Opsomerlaan 63",
    "sg:city":"Lier",
    "sg:classifiers":[
        {
            "category":"Building & Trades",
            "subcategory":"Equipment Rental",
            "type":"Services"
        }
    ],
    "sg:phone":"+32 3 480 70 56",
    "sg:postcode":"2500",
    "sg:province":"Antwerpen",
    "sg:tags":[
        "sound",
        "-",
        "system"
    ],
    "wof:name":"Audiakoestiek Geluidsversterking",
    "wof:placetype":"venue"
},
  "geometry": {"coordinates":[4.5618581772,51.1310081482],"type":"Point"}
}