{
  "type": "Feature",
  "properties": {
    "iso:country":"BE",
    "sg:address":"Ten Edestraat 26",
    "sg:city":"Gavere",
    "sg:orig_category":"Elektrische installaties voor woningen",
    "sg:phone":"+32 9 384 48 17",
    "sg:postcode":"9890",
    "sg:province":"Oost-Vlaanderen",
    "wof:name":"Scholiers Patrick",
    "wof:placetype":"venue"
},
  "geometry": {"coordinates":[3.681442976,50.9349365234],"type":"Point"}
}