{
  "type": "Feature",
  "properties": {
    "iso:country":"BE",
    "sg:address":"Rijkmakerlaan 11",
    "sg:city":"Essen",
    "sg:orig_category":"Verhuur cateringmateriaal and evenementuitrusting Verhuur diverse uitrustingen",
    "sg:phone":"+32 3 677 02 07",
    "sg:postcode":"2910",
    "sg:province":"Antwerpen",
    "wof:name":"Verwater Verhuur",
    "wof:placetype":"venue"
},
  "geometry": {"coordinates":[4.4990620613,51.4455375671],"type":"Point"}
}