{
  "type": "Feature",
  "properties": {
    "addr:full":"Chauss\u00e9e D'arlon 131 Neufch\u00e2teau (hamipr\u00e9) Luxembourg 6840",
    "addr:housenumber":"131",
    "addr:postcode":"6840",
    "addr:street":"Chausse\u0301E D'Arlon",
    "iso:country":"BE",
    "sg:address":"Chauss\u00e9e D'arlon 131",
    "sg:city":"Neufch\u00e2teau (hamipr\u00e9)",
    "sg:classifiers":[
        {
            "category":"Retail",
            "subcategory":"Auto Rental",
            "type":"Services"
        }
    ],
    "sg:phone":"+32 61 27 91 60",
    "sg:postcode":"6840",
    "sg:province":"Luxembourg",
    "sg:tags":[
        "van",
        "hire",
        "-",
        "truck"
    ],
    "wof:name":"Bourguignon Transports",
    "wof:placetype":"venue"
},
  "geometry": {"coordinates":[5.4605407715,49.8371734619],"type":"Point"}
}