{
  "type": "Feature",
  "properties": {
    "iso:country":"BE",
    "sg:address":"Akkerstraat 54",
    "sg:city":"Hooglede",
    "sg:orig_category":"Eleveurs de bovins",
    "sg:phone":"+32 51 20 36 17",
    "sg:postcode":"8830",
    "sg:province":"West-Vlaanderen",
    "wof:name":"Jozef Comptdaer",
    "wof:placetype":"venue"
},
  "geometry": {"coordinates":[3.0730080605,50.9731025696],"type":"Point"}
}