{
  "type": "Feature",
  "properties": {
    "addr:full":"Diksmuidestraat 2 Middelkerke West-Vlaanderen 8433",
    "addr:housenumber":"2",
    "addr:postcode":"8433",
    "addr:street":"Diksmuidestraat",
    "iso:country":"BE",
    "sg:address":"Diksmuidestraat 2",
    "sg:city":"Middelkerke",
    "sg:orig_category":"Brood, gebak and snoepgoed",
    "sg:phone":"+32 59 30 12 57",
    "sg:postcode":"8433",
    "sg:province":"West-Vlaanderen",
    "wof:name":"Bakkerij David-maekelberg",
    "wof:placetype":"venue"
},
  "geometry": {"coordinates":[2.8860800266,51.1183242798],"type":"Point"}
}