{
  "type": "Feature",
  "properties": {
    "iso:country":"BE",
    "sg:address":"Drogenbroodstraat 8-10",
    "sg:city":"Aalter",
    "sg:classifiers":[
        {
            "category":"Professional",
            "subcategory":"Management & Consulting",
            "type":"Services"
        }
    ],
    "sg:phone":"+32 9 374 04 06",
    "sg:postcode":"9880",
    "sg:province":"Oost-Vlaanderen",
    "sg:tags":[
        "consultant",
        "law"
    ],
    "wof:name":"Coopman L",
    "wof:placetype":"venue"
},
  "geometry": {"coordinates":[3.4455120564,51.0956802368],"type":"Point"}
}