{
  "type": "Feature",
  "properties": {
    "addr:full":"Oude Baan 262 Maasmechelen Limburg 3630",
    "addr:housenumber":"262",
    "addr:postcode":"3630",
    "addr:street":"Oude Baan",
    "iso:country":"BE",
    "sg:address":"Oude Baan 262",
    "sg:city":"Maasmechelen",
    "sg:classifiers":[
        {
            "category":"Cafe",
            "type":"Food & Drink"
        }
    ],
    "sg:phone":"+32 89 76 25 71",
    "sg:postcode":"3630",
    "sg:province":"Limburg",
    "sg:tags":[
        "caf\u00e9s"
    ],
    "wof:name":"Quinta Capriotti",
    "wof:placetype":"venue"
},
  "geometry": {"coordinates":[5.6876797676,50.9746131897],"type":"Point"}
}