{
  "type": "Feature",
  "properties": {
    "addr:full":"Muiten 9 Buggenhout Oost-Vlaanderen 9255",
    "addr:housenumber":"9",
    "addr:postcode":"9255",
    "addr:street":"Muiten",
    "iso:country":"BE",
    "sg:address":"Muiten 9",
    "sg:city":"Buggenhout",
    "sg:classifiers":[
        {
            "category":"Home & Garden",
            "subcategory":"Carpets & Floor Coverings",
            "type":"Retail Goods"
        }
    ],
    "sg:phone":"+32 52 35 48 11",
    "sg:postcode":"9255",
    "sg:province":"Oost-Vlaanderen",
    "sg:tags":[
        "layer",
        "mosaicists"
    ],
    "wof:name":"Maes",
    "wof:placetype":"venue"
},
  "geometry": {"coordinates":[4.1858501434,50.9884681702],"type":"Point"}
}