{
  "type": "Feature",
  "properties": {
    "addr:full":"Oudenaaksestraat 20 Lennik (gaasbeek) Vlaams-Brabant 1750",
    "addr:housenumber":"20",
    "addr:postcode":"1750",
    "addr:street":"Oudenaaksestraat",
    "iso:country":"BE",
    "sg:address":"Oudenaaksestraat 20",
    "sg:city":"Lennik (gaasbeek)",
    "sg:classifiers":[
        {
            "category":"Food & Beverages",
            "subcategory":"Meat & Fish",
            "type":"Retail Goods"
        }
    ],
    "sg:phone":"+32 2 532 40 33",
    "sg:postcode":"1750",
    "sg:province":"Vlaams-Brabant",
    "sg:tags":[
        "-",
        "livestock"
    ],
    "wof:name":"De Baerdemaeker",
    "wof:placetype":"venue"
},
  "geometry": {"coordinates":[4.1894979477,50.7933387756],"type":"Point"}
}