{
  "type": "Feature",
  "properties": {
    "addr:full":"Brandstraat 173 Mol Antwerpen 2400",
    "addr:housenumber":"173",
    "addr:postcode":"2400",
    "addr:street":"Brandstraat",
    "iso:country":"BE",
    "sg:address":"Brandstraat 173",
    "sg:city":"Mol",
    "sg:classifiers":[
        {
            "category":"Building & Trades",
            "subcategory":"Construction",
            "type":"Services"
        }
    ],
    "sg:phone":"+32 14 31 80 68",
    "sg:postcode":"2400",
    "sg:province":"Antwerpen",
    "sg:tags":[
        "paper",
        "hanger"
    ],
    "wof:name":"Claes Pascal Decoratie Bvba",
    "wof:placetype":"venue"
},
  "geometry": {"coordinates":[5.1285300255,51.1968803406],"type":"Point"}
}