{
  "type": "Feature",
  "properties": {
    "iso:country":"BE",
    "sg:address":"Avenue Charles Woeste 237",
    "sg:city":"Bruxelles (jette)",
    "sg:classifiers":[
        {
            "category":"Bakery",
            "type":"Food & Drink"
        }
    ],
    "sg:phone":"+32 2 426 22 86",
    "sg:postcode":"1090",
    "sg:province":"Bruxelles-Capitale",
    "sg:tags":[
        "confectioner",
        "baker"
    ],
    "wof:name":"Grenson",
    "wof:placetype":"venue"
},
  "geometry": {"coordinates":[4.3345298767,50.8710098267],"type":"Point"}
}