{
  "type": "Feature",
  "properties": {
    "addr:full":"Avenue De La Clairi\u00e8re 15 La Hulpe Brabant Wallon 1310",
    "addr:housenumber":"15",
    "addr:postcode":"1310",
    "addr:street":"Avenue De La Clairie\u0300Re",
    "iso:country":"BE",
    "sg:address":"Avenue De La Clairi\u00e8re 15",
    "sg:city":"La Hulpe",
    "sg:classifiers":[
        {
            "category":"Professional",
            "subcategory":"Management & Consulting",
            "type":"Services"
        }
    ],
    "sg:phone":"+32 2 652 25 34",
    "sg:postcode":"1310",
    "sg:province":"Brabant Wallon",
    "sg:tags":[
        "consultant",
        "agency",
        "advertising"
    ],
    "wof:name":"Deadline Production",
    "wof:placetype":"venue"
},
  "geometry": {"coordinates":[4.4989218712,50.7403831482],"type":"Point"}
}