{
  "type": "Feature",
  "properties": {
    "addr:full":"Rue De La Houill\u00c8re 72 Saint-nicolas Li\u00e8ge 4420",
    "addr:housenumber":"72",
    "addr:postcode":"4420",
    "addr:street":"Rue De La Houille\u0300Re",
    "iso:country":"BE",
    "sg:address":"Rue De La Houill\u00c8re 72",
    "sg:city":"Saint-nicolas",
    "sg:orig_category":"Advocaten and juridische adviseurs",
    "sg:phone":"+32 4 252 67 58",
    "sg:postcode":"4420",
    "sg:province":"Li\u00e8ge",
    "wof:name":"S. Moreau",
    "wof:placetype":"venue"
},
  "geometry": {"coordinates":[5.5433011055,50.6261978149],"type":"Point"}
}