{
  "type": "Feature",
  "properties": {
    "addr:full":"Guido Gezellelaan 35 Menen West-Vlaanderen 8930",
    "addr:housenumber":"35",
    "addr:postcode":"8930",
    "addr:street":"Guido Gezellelaan",
    "iso:country":"BE",
    "sg:address":"Guido Gezellelaan 35",
    "sg:city":"Menen",
    "sg:orig_category":"Installation \u00e9lectrique r\u00e9sidentielle",
    "sg:phone":"+32 56 51 13 86",
    "sg:postcode":"8930",
    "sg:province":"West-Vlaanderen",
    "wof:name":"Pierre Brouckaert",
    "wof:placetype":"venue"
},
  "geometry": {"coordinates":[3.1099510193,50.8008880615],"type":"Point"}
}