{
  "type": "Feature",
  "properties": {
    "iso:country":"BE",
    "sg:address":"Riedekens 193",
    "sg:city":"Oudenaarde",
    "sg:orig_category":"Diverse grafische activiteiten",
    "sg:phone":"+32 55 31 85 61",
    "sg:postcode":"9700",
    "sg:province":"Oost-Vlaanderen",
    "wof:name":"Pierre Vandermeersch",
    "wof:placetype":"venue"
},
  "geometry": {"coordinates":[3.6299901009,50.8513336182],"type":"Point"}
}