{
  "type": "Feature",
  "properties": {
    "iso:country":"BE",
    "sg:address":"Pennemanstraat 62",
    "sg:city":"Deinze (astene)",
    "sg:classifiers":[
        {
            "category":"Personal",
            "subcategory":"Beauty Salon",
            "type":"Services"
        }
    ],
    "sg:phone":"+32 9 386 32 65",
    "sg:postcode":"9800",
    "sg:province":"Oost-Vlaanderen",
    "sg:tags":[
        "lady",
        "-",
        "hairdressing"
    ],
    "wof:name":"Silhouette",
    "wof:placetype":"venue"
},
  "geometry": {"coordinates":[3.5735719204,50.9819526672],"type":"Point"}
}