{
  "type": "Feature",
  "properties": {
    "iso:country":"BE",
    "sg:address":"Minckelersstr 48a",
    "sg:city":"Leuven",
    "sg:classifiers":[
        {
            "category":"Banks & Credit Unions",
            "subcategory":"Bank",
            "type":"Services"
        }
    ],
    "sg:phone":"+32 16 29 01 01",
    "sg:postcode":"3000",
    "sg:province":"Vlaams-Brabant",
    "wof:name":"Caisse Nationale De, Cr\u00e9dit Professionnel",
    "wof:placetype":"venue"
},
  "geometry": {"coordinates":[4.7068371773,50.8828811646],"type":"Point"}
}