{
  "type": "Feature",
  "properties": {
    "iso:country":"BE",
    "sg:address":"Place Albert I 0",
    "sg:city":"Waterloo",
    "sg:orig_category":"Enseignement secondaire g\u00e9n\u00e9ral. Enseignement secondaire technique and professionnel",
    "sg:phone":"+32 2 354 01 86",
    "sg:postcode":"1410",
    "sg:province":"Brabant Wallon",
    "wof:name":"Institut Sacr\u00c9s-coeurs",
    "wof:placetype":"venue"
},
  "geometry": {"coordinates":[4.396835804,50.7177467346],"type":"Point"}
}