{
  "type": "Feature",
  "properties": {
    "iso:country":"BE",
    "sg:address":"Klingedijkstraat 128",
    "sg:city":"Sint-gillis-waas",
    "sg:classifiers":[
        {
            "category":"Autos & Motor Vehicles",
            "subcategory":"Fuel & Gas Station",
            "type":"Retail Goods"
        }
    ],
    "sg:phone":"+32 3 770 56 72",
    "sg:postcode":"9170",
    "sg:province":"Oost-Vlaanderen",
    "sg:tags":[
        "stations-service",
        "carburants"
    ],
    "wof:name":"Garage Warrens",
    "wof:placetype":"venue"
},
  "geometry": {"coordinates":[4.0867948532,51.2486228943],"type":"Point"}
}