{
  "type": "Feature",
  "properties": {
    "iso:country":"BE",
    "sg:address":"Dijkstraat 15",
    "sg:city":"Assenede",
    "sg:orig_category":"Activit\u00e9s r\u00e9cr\u00e9atives diverses",
    "sg:phone":"+32 9 344 65 89",
    "sg:postcode":"9960",
    "sg:province":"Oost-Vlaanderen",
    "wof:name":"K.v.b.p. Filas",
    "wof:placetype":"venue"
},
  "geometry": {"coordinates":[3.7568030357,51.2304992676],"type":"Point"}
}