{
  "type": "Feature",
  "properties": {
    "iso:country":"BE",
    "sg:address":"Rue De Tourinne 2",
    "sg:city":"Geer",
    "sg:orig_category":"Rundveehouders",
    "sg:phone":"+32 19 58 80 72",
    "sg:postcode":"4250",
    "sg:province":"Li\u00e8ge",
    "wof:name":"Delathuy",
    "wof:placetype":"venue"
},
  "geometry": {"coordinates":[5.155875206,50.6627388],"type":"Point"}
}