{
  "type": "Feature",
  "properties": {
    "addr:full":"Rue Ernest Solvay 197 Morlanwelz (carni\u00e8res) Hainaut 7141",
    "addr:housenumber":"197",
    "addr:postcode":"7141",
    "addr:street":"Rue Ernest Solvay",
    "iso:country":"BE",
    "sg:address":"Rue Ernest Solvay 197",
    "sg:city":"Morlanwelz (carni\u00e8res)",
    "sg:classifiers":[
        {
            "category":"Food & Beverages",
            "subcategory":"Groceries & Convenience Stores",
            "type":"Retail Goods"
        }
    ],
    "sg:phone":"+32 64 44 38 09",
    "sg:postcode":"7141",
    "sg:province":"Hainaut",
    "sg:tags":[
        "grocer"
    ],
    "wof:name":"Maria (chez)",
    "wof:placetype":"venue"
},
  "geometry": {"coordinates":[4.2571730614,50.4499092102],"type":"Point"}
}