{
  "type": "Feature",
  "properties": {
    "addr:full":"Grand'route 79 Fexhe-le-haut-clocher Li\u00e8ge 4347",
    "addr:housenumber":"79",
    "addr:postcode":"4347",
    "addr:street":"Grand'Route",
    "iso:country":"BE",
    "sg:address":"Grand'route 79",
    "sg:city":"Fexhe-le-haut-clocher",
    "sg:orig_category":"Gespecialiseerde residenti\u00eble bouw",
    "sg:phone":"+32 4 250 23 43",
    "sg:postcode":"4347",
    "sg:province":"Li\u00e8ge",
    "wof:name":"Meo Mario",
    "wof:placetype":"venue"
},
  "geometry": {"coordinates":[5.3987898827,50.6656417847],"type":"Point"}
}