{
  "type": "Feature",
  "properties": {
    "addr:full":"Doolstraat 24 Lille Antwerpen 2275",
    "addr:housenumber":"24",
    "addr:postcode":"2275",
    "addr:street":"Doolstraat",
    "iso:country":"BE",
    "sg:address":"Doolstraat 24",
    "sg:city":"Lille",
    "sg:orig_category":"Installation de menuiserie en bois and plastique",
    "sg:phone":"+32 14 55 64 07",
    "sg:postcode":"2275",
    "sg:province":"Antwerpen",
    "wof:name":"Thys",
    "wof:placetype":"venue"
},
  "geometry": {"coordinates":[4.8689780235,51.2622375488],"type":"Point"}
}