{
  "type": "Feature",
  "properties": {
    "iso:country":"BE",
    "sg:address":"Speienstraat 14",
    "sg:city":"Oostkamp",
    "sg:orig_category":"Huishoudapparaten, televisies and radio's",
    "sg:phone":"+32 50 27 65 01",
    "sg:postcode":"8020",
    "sg:province":"West-Vlaanderen",
    "wof:name":"Frank Desmet",
    "wof:placetype":"venue"
},
  "geometry": {"coordinates":[3.1653370857,51.0727615356],"type":"Point"}
}