{
  "type": "Feature",
  "properties": {
    "iso:country":"BE",
    "sg:address":"Tieboutslaan 1",
    "sg:city":"Anzegem",
    "sg:classifiers":[
        {
            "category":"Cafe",
            "type":"Food & Drink"
        }
    ],
    "sg:phone":"+32 56 68 02 83",
    "sg:postcode":"8573",
    "sg:province":"West-Vlaanderen",
    "sg:tags":[
        "caf\u00e9s"
    ],
    "wof:name":"Wim Loontjens",
    "wof:placetype":"venue"
},
  "geometry": {"coordinates":[3.4639930725,50.806842804],"type":"Point"}
}