{
  "type": "Feature",
  "properties": {
    "addr:full":"Ch De Mons 702 Leeuw-saint-pierre Vlaams-Brabant 1600",
    "addr:housenumber":"702;1600",
    "addr:street":"Ch De Mons;Vlaams-Brabant",
    "iso:country":"BE",
    "sg:address":"Ch De Mons 702",
    "sg:city":"Leeuw-saint-pierre",
    "sg:classifiers":[
        {
            "category":"Professional",
            "type":"Services"
        }
    ],
    "sg:phone":"+32 2 410 04 80",
    "sg:postcode":"1600",
    "sg:province":"Vlaams-Brabant",
    "sg:tags":[
        "transport",
        "road"
    ],
    "wof:name":"Fremersdorff Et Fils Sprl",
    "wof:placetype":"venue"
},
  "geometry": {"coordinates":[4.2540001869,50.7666397095],"type":"Point"}
}