{
  "type": "Feature",
  "properties": {
    "addr:full":"Rue Gheude 8 Bruxelles (anderlecht) Bruxelles-Capitale 1070",
    "addr:housenumber":"8",
    "addr:postcode":"1070",
    "addr:street":"Rue Gheude",
    "iso:country":"BE",
    "sg:address":"Rue Gheude 8",
    "sg:city":"Bruxelles (anderlecht)",
    "sg:classifiers":[
        {
            "category":"Personal",
            "subcategory":"Psychics & Astrologers",
            "type":"Services"
        }
    ],
    "sg:phone":"+32 2 522 04 90",
    "sg:postcode":"1070",
    "sg:province":"Bruxelles-Capitale",
    "sg:tags":[
        "astrology"
    ],
    "wof:name":"Aldemar",
    "wof:placetype":"venue"
},
  "geometry": {"coordinates":[4.3341140747,50.8431777954],"type":"Point"}
}