{
  "type": "Feature",
  "properties": {
    "addr:full":"Lebeaustraat 53 Brussel/bruxelles Bruxelles-Capitale 1000",
    "addr:housenumber":"53",
    "addr:postcode":"1000",
    "addr:street":"Lebeaustraat;/",
    "iso:country":"BE",
    "sg:address":"Lebeaustraat 53",
    "sg:city":"Brussel/bruxelles",
    "sg:orig_category":"Antiek Decoratieve kunst and kunstbenodigdheden Zalen voor culturele evenementen",
    "sg:phone":"+32 2 511 32 53",
    "sg:postcode":"1000",
    "sg:province":"Bruxelles-Capitale",
    "wof:name":"Galerie A.b.c.",
    "wof:placetype":"venue"
},
  "geometry": {"coordinates":[4.3539028168,50.8422050476],"type":"Point"}
}