{
  "type": "Feature",
  "properties": {
    "iso:country":"BE",
    "sg:address":"Lindestraat 41",
    "sg:city":"Maldegem",
    "sg:orig_category":"Dierenartsen",
    "sg:phone":"+32 50 71 10 36",
    "sg:postcode":"9990",
    "sg:province":"Oost-Vlaanderen",
    "wof:name":"Rene Coppejans",
    "wof:placetype":"venue"
},
  "geometry": {"coordinates":[3.4693620205,51.1892242432],"type":"Point"}
}