{
  "type": "Feature",
  "properties": {
    "addr:full":"Chauss\u00c9e De Ninove 744 Anderlecht/anderlecht Bruxelles-Capitale 1070",
    "addr:housenumber":"744",
    "addr:postcode":"1070",
    "addr:street":"Chausse\u0301E De Ninove",
    "iso:country":"BE",
    "sg:address":"Chauss\u00c9e De Ninove 744",
    "sg:city":"Anderlecht/anderlecht",
    "sg:classifiers":[
        {
            "category":"Autos & Motor Vehicles",
            "subcategory":"Fuel & Gas Station",
            "type":"Retail Goods"
        }
    ],
    "sg:phone":"+32 2 521 35 14",
    "sg:postcode":"1070",
    "sg:province":"Bruxelles-Capitale",
    "sg:tags":[
        "stations-service",
        "carburants"
    ],
    "wof:name":"Jet",
    "wof:placetype":"venue"
},
  "geometry": {"coordinates":[4.2951211929,50.8463973999],"type":"Point"}
}