{
  "type": "Feature",
  "properties": {
    "iso:country":"BE",
    "sg:address":"Eikenlei 73",
    "sg:city":"Brecht",
    "sg:orig_category":"Tuinen",
    "sg:phone":"+32 3 663 78 00",
    "sg:postcode":"2960",
    "sg:province":"Antwerpen",
    "wof:name":"Gillenia",
    "wof:placetype":"venue"
},
  "geometry": {"coordinates":[4.5599541664,51.3004608154],"type":"Point"}
}