{
  "type": "Feature",
  "properties": {
    "iso:country":"BE",
    "sg:address":"Rue Herreuse 12",
    "sg:city":"Momignies",
    "sg:classifiers":[
        {
            "category":"Personal",
            "subcategory":"Barber",
            "type":"Services"
        }
    ],
    "sg:phone":"+32 60 51 18 67",
    "sg:postcode":"6590",
    "sg:province":"Hainaut",
    "sg:tags":[
        "gentleman",
        "salon",
        "-",
        "hairdressing"
    ],
    "wof:name":"Chez Christian",
    "wof:placetype":"venue"
},
  "geometry": {"coordinates":[4.1734361649,50.0306587219],"type":"Point"}
}