{
  "type": "Feature",
  "properties": {
    "iso:country":"BE",
    "sg:address":"Klein-hulststraat 17",
    "sg:city":"Sint-niklaas",
    "sg:classifiers":[
        {
            "category":"Retail",
            "subcategory":"Laundry & Dry Cleaning",
            "type":"Services"
        }
    ],
    "sg:phone":"+32 3 776 10 67",
    "sg:postcode":"9100",
    "sg:province":"Oost-Vlaanderen",
    "sg:tags":[
        "self",
        "-"
    ],
    "wof:name":"Comby Clean",
    "wof:placetype":"venue"
},
  "geometry": {"coordinates":[4.1488962173,51.1677894592],"type":"Point"}
}