{
  "type": "Feature",
  "properties": {
    "addr:full":"Grimbergsesteenweg 62 Grimbergen Vlaams-Brabant 1850",
    "addr:housenumber":"62",
    "addr:postcode":"1850",
    "addr:street":"Grimbergsesteenweg",
    "iso:country":"BE",
    "sg:address":"Grimbergsesteenweg 62",
    "sg:city":"Grimbergen",
    "sg:orig_category":"Peinture. Rev\u00eatements pour sols and murs",
    "sg:phone":"+32 2 267 01 82",
    "sg:postcode":"1850",
    "sg:province":"Vlaams-Brabant",
    "wof:name":"Andre Patoor",
    "wof:placetype":"venue"
},
  "geometry": {"coordinates":[4.3622398376,50.9188804626],"type":"Point"}
}