{
  "type": "Feature",
  "properties": {
    "iso:country":"BE",
    "sg:address":"Kerselarenlaan 35",
    "sg:city":"Liedekerke",
    "sg:classifiers":[
        {
            "category":"Professional",
            "subcategory":"Accounting & Tax Preparation",
            "type":"Services"
        }
    ],
    "sg:phone":"+32 53 66 07 06",
    "sg:postcode":"1770",
    "sg:province":"Vlaams-Brabant",
    "sg:tags":[
        "bookkeeper"
    ],
    "wof:name":"Dekens M",
    "wof:placetype":"venue"
},
  "geometry": {"coordinates":[4.0815901756,50.8708457947],"type":"Point"}
}