{
  "type": "Feature",
  "properties": {
    "addr:full":"Sint-hubertusstraat 5 Houthulst West-Vlaanderen 8650",
    "addr:housenumber":"5",
    "addr:postcode":"8650",
    "addr:street":"Sint-Hubertusstraat",
    "iso:country":"BE",
    "sg:address":"Sint-hubertusstraat 5",
    "sg:city":"Houthulst",
    "sg:classifiers":[
        {
            "category":"Home & Garden",
            "subcategory":"Household Appliances",
            "type":"Retail Goods"
        }
    ],
    "sg:phone":"+32 51 70 24 21",
    "sg:postcode":"8650",
    "sg:province":"West-Vlaanderen",
    "sg:tags":[
        "repair",
        "mainten",
        "-",
        "electric"
    ],
    "wof:name":"Abeel",
    "wof:placetype":"venue"
},
  "geometry": {"coordinates":[2.9318380356,50.9736938477],"type":"Point"}
}