{
  "type": "Feature",
  "properties": {
    "iso:country":"BE",
    "sg:address":"Rue Du Fief 62",
    "sg:city":"Anderlues",
    "sg:orig_category":"Eleveurs de bovins",
    "sg:phone":"+32 71 52 45 49",
    "sg:postcode":"6150",
    "sg:province":"Hainaut",
    "wof:name":"Lucien Malengrez",
    "wof:placetype":"venue"
},
  "geometry": {"coordinates":[4.2788038254,50.395362854],"type":"Point"}
}