{
  "type": "Feature",
  "properties": {
    "iso:country":"BE",
    "sg:address":"Van Cromphoutstraat 2",
    "sg:city":"Wetteren",
    "sg:orig_category":"Pharmaciens",
    "sg:phone":"+32 9 369 02 21",
    "sg:postcode":"9230",
    "sg:province":"Oost-Vlaanderen",
    "wof:name":"Apoth. Maudens-de Backer",
    "wof:placetype":"venue"
},
  "geometry": {"coordinates":[3.8845779896,51.0068435669],"type":"Point"}
}