{
  "type": "Feature",
  "properties": {
    "iso:country":"BE",
    "sg:address":"Gentsesteenweg 101",
    "sg:city":"Wetteren",
    "sg:classifiers":[
        {
            "category":"Shopping",
            "subcategory":"Hobbies, Toys, & Games",
            "type":"Retail Goods"
        }
    ],
    "sg:phone":"+32 9 365 66 40",
    "sg:postcode":"9230",
    "sg:province":"Oost-Vlaanderen",
    "sg:tags":[
        "toy",
        "-"
    ],
    "wof:name":"Fun",
    "wof:placetype":"venue"
},
  "geometry": {"coordinates":[3.8707990646,51.000125885],"type":"Point"}
}