{
  "type": "Feature",
  "properties": {
    "iso:country":"BE",
    "sg:address":"Pontstraat 75",
    "sg:city":"Zwevegem (heestert)",
    "sg:classifiers":[
        {
            "category":"Sports & Exercise",
            "subcategory":"Skate Park",
            "type":"Entertainment"
        }
    ],
    "sg:phone":"+32 56 77 71 97",
    "sg:postcode":"8551",
    "sg:province":"West-Vlaanderen",
    "sg:tags":[
        "mushroom"
    ],
    "wof:name":"Desrumaux L",
    "wof:placetype":"venue"
},
  "geometry": {"coordinates":[3.4052898884,50.8053894043],"type":"Point"}
}