{
  "type": "Feature",
  "properties": {
    "addr:full":"Lievenshoeklaan 29 Kapellen Antwerpen 2950",
    "addr:housenumber":"29",
    "addr:postcode":"2950",
    "addr:street":"Lievenshoeklaan",
    "iso:country":"BE",
    "sg:address":"Lievenshoeklaan 29",
    "sg:city":"Kapellen",
    "sg:orig_category":"Schoonheidssalons",
    "sg:phone":"+32 3 664 88 48",
    "sg:postcode":"2950",
    "sg:province":"Antwerpen",
    "wof:name":"Christiane Van Eyck",
    "wof:placetype":"venue"
},
  "geometry": {"coordinates":[4.4475841522,51.3283805847],"type":"Point"}
}