{
  "type": "Feature",
  "properties": {
    "addr:full":"Gen. Lemanstraat 48 Menen West-Vlaanderen 8930",
    "addr:housenumber":"48",
    "addr:postcode":"8930",
    "addr:street":"Gen. Lemanstraat",
    "iso:country":"BE",
    "sg:address":"Gen. Lemanstraat 48",
    "sg:city":"Menen",
    "sg:classifiers":[
        {
            "category":"Personal",
            "subcategory":"Beauty Salon",
            "type":"Services"
        }
    ],
    "sg:phone":"+32 56 51 37 67",
    "sg:postcode":"8930",
    "sg:province":"West-Vlaanderen",
    "sg:tags":[
        "de",
        "coiffure"
    ],
    "wof:name":"Devolder Ingrid & Magda",
    "wof:placetype":"venue"
},
  "geometry": {"coordinates":[3.108453989,50.797908783],"type":"Point"}
}