{
  "type": "Feature",
  "properties": {
    "addr:full":"Magnoliastraat 2 Houthalen-helchteren Limburg 3530",
    "addr:housenumber":"2",
    "addr:postcode":"3530",
    "addr:street":"Magnoliastraat",
    "iso:country":"BE",
    "sg:address":"Magnoliastraat 2",
    "sg:city":"Houthalen-helchteren",
    "sg:classifiers":[
        {
            "category":"Cafe",
            "type":"Food & Drink"
        }
    ],
    "sg:phone":"+32 89 38 24 02",
    "sg:postcode":"3530",
    "sg:province":"Limburg",
    "sg:tags":[
        "caf\u00e9s"
    ],
    "wof:name":"Caf\u00c9 String",
    "wof:placetype":"venue"
},
  "geometry": {"coordinates":[5.4791111946,51.0188140869],"type":"Point"}
}