{
  "type": "Feature",
  "properties": {
    "addr:full":"Rue Du Culot 21b Beauvechain (tourinnes-la-grosse) Brabant Wallon 1320",
    "addr:housenumber":"21b",
    "addr:postcode":"1320",
    "addr:street":"Rue Du Culot;Wallon",
    "iso:country":"BE",
    "sg:address":"Rue Du Culot 21b",
    "sg:city":"Beauvechain (tourinnes-la-grosse)",
    "sg:classifiers":[
        {
            "category":"Personal",
            "subcategory":"Beauty Salon",
            "type":"Services"
        }
    ],
    "sg:phone":"+32 10 86 04 47",
    "sg:postcode":"1320",
    "sg:province":"Brabant Wallon",
    "sg:tags":[
        "lady",
        "-",
        "hairdressing"
    ],
    "wof:name":"Nelly",
    "wof:placetype":"venue"
},
  "geometry": {"coordinates":[4.7447009087,50.7863616943],"type":"Point"}
}