{
  "type": "Feature",
  "properties": {
    "iso:country":"BE",
    "sg:address":"Graaf D'ursellaan 53",
    "sg:city":"Knokke-heist",
    "sg:classifiers":[
        {
            "category":"Shopping",
            "subcategory":"Clothing, Apparel, & Fashions",
            "type":"Retail Goods"
        }
    ],
    "sg:phone":"+32 50 51 68 05",
    "sg:postcode":"8301",
    "sg:province":"West-Vlaanderen",
    "sg:tags":[
        "v\u00eatements",
        "pour",
        "dame"
    ],
    "wof:name":"Scara",
    "wof:placetype":"venue"
},
  "geometry": {"coordinates":[3.2460141182,51.3403892517],"type":"Point"}
}