{
  "type": "Feature",
  "properties": {
    "iso:country":"BE",
    "sg:address":"Voortstraat 39",
    "sg:city":"Beringen",
    "sg:classifiers":[
        {
            "category":"Manufacturing",
            "subcategory":"Furniture",
            "type":"Manufacturing & Wholesale Goods"
        }
    ],
    "sg:phone":"+32 11 42 58 13",
    "sg:postcode":"3580",
    "sg:province":"Limburg",
    "sg:tags":[
        "made",
        "-",
        "custom"
    ],
    "wof:name":"Beerten J",
    "wof:placetype":"venue"
},
  "geometry": {"coordinates":[5.2141928673,51.0570411682],"type":"Point"}
}