{
  "type": "Feature",
  "properties": {
    "addr:full":"Rue De La Vignette 93 Oudergem/auderghem Bruxelles-Capitale 1160",
    "addr:housenumber":"93",
    "addr:postcode":"1160",
    "addr:street":"Rue De La Vignette;/",
    "iso:country":"BE",
    "sg:address":"Rue De La Vignette 93",
    "sg:city":"Oudergem/auderghem",
    "sg:orig_category":"Plomberie, chauffage and installations sanitaires",
    "sg:phone":"+32 495 33 85 98",
    "sg:postcode":"1160",
    "sg:province":"Bruxelles-Capitale",
    "wof:name":"R.m.s",
    "wof:placetype":"venue"
},
  "geometry": {"coordinates":[4.4226760864,50.8156242371],"type":"Point"}
}