{
  "type": "Feature",
  "properties": {
    "iso:country":"BE",
    "sg:address":"Grote Markt 61",
    "sg:city":"Sint-niklaas",
    "sg:orig_category":"Instituts de beaut\u00e9",
    "sg:phone":"+32 3 777 65 59",
    "sg:postcode":"9100",
    "sg:province":"Oost-Vlaanderen",
    "wof:name":"Instituut Ionia",
    "wof:placetype":"venue"
},
  "geometry": {"coordinates":[4.1409869194,51.1650848389],"type":"Point"}
}