{
  "type": "Feature",
  "properties": {
    "iso:country":"BE",
    "sg:address":"Rue Du Namr\u00c9e 20",
    "sg:city":"Bertrix",
    "sg:classifiers":[
        {
            "category":"Arena",
            "subcategory":"Sports Club",
            "type":"Entertainment"
        }
    ],
    "sg:phone":"+32 61 41 23 06",
    "sg:postcode":"6880",
    "sg:province":"Luxembourg",
    "sg:tags":[
        "terrain",
        "hors",
        "de",
        "installation",
        "sportifs"
    ],
    "wof:name":"Ent. Jehonvilloise",
    "wof:placetype":"venue"
},
  "geometry": {"coordinates":[5.2124700546,49.8692016602],"type":"Point"}
}