{
  "type": "Feature",
  "properties": {
    "addr:full":"Nieuwstraat 80 Geel Antwerpen 2440",
    "addr:housenumber":"80",
    "addr:postcode":"2440",
    "addr:street":"Nieuwstraat",
    "iso:country":"BE",
    "sg:address":"Nieuwstraat 80",
    "sg:city":"Geel",
    "sg:classifiers":[
        {
            "category":"Shopping",
            "subcategory":"Clothing, Apparel, & Fashions",
            "type":"Retail Goods"
        }
    ],
    "sg:phone":"+32 14 58 42 25",
    "sg:postcode":"2440",
    "sg:province":"Antwerpen",
    "sg:tags":[
        "underwear",
        "lingerie",
        "-"
    ],
    "wof:name":"Kris",
    "wof:placetype":"venue"
},
  "geometry": {"coordinates":[4.9940910339,51.1633529663],"type":"Point"}
}