{
  "type": "Feature",
  "properties": {
    "addr:full":"Rue L\u00e9opold 3 Gembloux-sur-orneau (gembloux) Namur 5030",
    "addr:housenumber":"3",
    "addr:postcode":"5030",
    "addr:street":"Rue Le\u0301Opold;Namur",
    "iso:country":"BE",
    "sg:address":"Rue L\u00e9opold 3",
    "sg:city":"Gembloux-sur-orneau (gembloux)",
    "sg:classifiers":[
        {
            "category":"Shopping",
            "subcategory":"Shoes",
            "type":"Retail Goods"
        }
    ],
    "sg:phone":"+32 81 61 05 26",
    "sg:postcode":"5030",
    "sg:province":"Namur",
    "sg:tags":[
        "slipper",
        "-"
    ],
    "wof:name":"Pas Sage",
    "wof:placetype":"venue"
},
  "geometry": {"coordinates":[4.6932630539,50.5600242615],"type":"Point"}
}