{
  "type": "Feature",
  "properties": {
    "addr:full":"Rue Du Centre 2a Assesse (sorinne-la-longue) Namur 5333",
    "addr:housenumber":"2a",
    "addr:postcode":"5333",
    "addr:street":"Rue Du Centre",
    "iso:country":"BE",
    "sg:address":"Rue Du Centre 2a",
    "sg:city":"Assesse (sorinne-la-longue)",
    "sg:classifiers":[
        {
            "category":"Shopping",
            "subcategory":"Pets & Pet Supplies",
            "type":"Retail Goods"
        }
    ],
    "sg:phone":"+32 83 65 59 58",
    "sg:postcode":"5333",
    "sg:province":"Namur",
    "sg:tags":[
        "horseriding"
    ],
    "wof:name":"Equimat Sprl",
    "wof:placetype":"venue"
},
  "geometry": {"coordinates":[5.0093860626,50.3836479187],"type":"Point"}
}