{
  "type": "Feature",
  "properties": {
    "iso:country":"BE",
    "sg:address":"Brugsesteenweg 140",
    "sg:city":"Blankenberge",
    "sg:orig_category":"Produits \u00e0 base de pommes de terre Fruits and l\u00e9gumes Gr",
    "sg:phone":"+32 50 41 19 87",
    "sg:postcode":"8370",
    "sg:province":"West-Vlaanderen",
    "wof:name":"Grand Service",
    "wof:placetype":"venue"
},
  "geometry": {"coordinates":[3.1343250275,51.3109512329],"type":"Point"}
}