{
  "type": "Feature",
  "properties": {
    "addr:full":"Dorpstraat 42 Antwerpen Antwerpen 2040",
    "addr:housenumber":"42",
    "addr:postcode":"2040",
    "addr:street":"Dorpstraat",
    "iso:country":"BE",
    "sg:address":"Dorpstraat 42",
    "sg:city":"Antwerpen",
    "sg:orig_category":"Openbare veiligheid",
    "sg:phone":"+32 3 568 60 14",
    "sg:postcode":"2040",
    "sg:province":"Antwerpen",
    "wof:name":"Federale Politie",
    "wof:placetype":"venue"
},
  "geometry": {"coordinates":[4.3134999275,51.3459701538],"type":"Point"}
}