{
  "type": "Feature",
  "properties": {
    "iso:country":"BE",
    "sg:address":"Rue Reppe 49",
    "sg:city":"Andenne",
    "sg:orig_category":"Eclairage et \u00e9quipements du foyer",
    "sg:phone":"+32 85 82 55 42",
    "sg:postcode":"5300",
    "sg:province":"Namur",
    "wof:name":"Amc Belgium Jarmin-liben",
    "wof:placetype":"venue"
},
  "geometry": {"coordinates":[5.0944299698,50.4796218872],"type":"Point"}
}