{
  "type": "Feature",
  "properties": {
    "addr:full":"Korenlaan 4 Brasschaat Antwerpen 2930",
    "addr:housenumber":"4",
    "addr:postcode":"2930",
    "addr:street":"Korenlaan",
    "iso:country":"BE",
    "sg:address":"Korenlaan 4",
    "sg:city":"Brasschaat",
    "sg:classifiers":[
        {
            "category":"Professional",
            "subcategory":"Computer Services",
            "type":"Services"
        }
    ],
    "sg:phone":"+32 3 633 07 36",
    "sg:postcode":"2930",
    "sg:province":"Antwerpen",
    "sg:tags":[
        "-",
        "processing",
        "data",
        "software"
    ],
    "wof:name":"Zenko Bvba",
    "wof:placetype":"venue"
},
  "geometry": {"coordinates":[4.5207400322,51.3153381348],"type":"Point"}
}