{
  "type": "Feature",
  "properties": {
    "addr:full":"Clos Des Trigonelles 1 Box 9 Bruxelles Bruxelles-Capitale 1120",
    "addr:housenumber":"1;9",
    "addr:postcode":"1120",
    "addr:street":"Clos Des Trigonelles;Box",
    "iso:country":"BE",
    "sg:address":"Clos Des Trigonelles 1 Box 9",
    "sg:city":"Bruxelles",
    "sg:classifiers":[
        {
            "category":"Home & Garden",
            "subcategory":"Home Furnishings",
            "type":"Retail Goods"
        }
    ],
    "sg:phone":"+32 2 268 35 36",
    "sg:postcode":"1120",
    "sg:province":"Bruxelles-Capitale",
    "sg:tags":[
        "interior",
        "decoration"
    ],
    "wof:name":"Weidner C",
    "wof:placetype":"venue"
},
  "geometry": {"coordinates":[4.3841519356,50.9003753662],"type":"Point"}
}