{
  "type": "Feature",
  "properties": {
    "iso:country":"BE",
    "sg:address":"Blommeke 11",
    "sg:city":"Beernem",
    "sg:orig_category":"Eleveurs de bovins. Eleveurs and marchands de porcs",
    "sg:phone":"+32 50 78 99 20",
    "sg:postcode":"8730",
    "sg:province":"West-Vlaanderen",
    "wof:name":"Lucien Lips",
    "wof:placetype":"venue"
},
  "geometry": {"coordinates":[3.3082299232,51.1225891113],"type":"Point"}
}