{
  "type": "Feature",
  "properties": {
    "iso:country":"BE",
    "sg:address":"Place Paul Pastur 25",
    "sg:city":"Anderlues",
    "sg:classifiers":[
        {
            "category":"Food & Beverages",
            "subcategory":"Fruits & Vegetables",
            "type":"Retail Goods"
        }
    ],
    "sg:phone":"+32 71 54 52 10",
    "sg:postcode":"6150",
    "sg:province":"Hainaut",
    "sg:tags":[
        "groenten"
    ],
    "wof:name":"Jef Fruits",
    "wof:placetype":"venue"
},
  "geometry": {"coordinates":[4.2706899643,50.4079093933],"type":"Point"}
}