{
  "type": "Feature",
  "properties": {
    "iso:country":"BE",
    "sg:address":"Robbesrodestraat 4",
    "sg:city":"Bekkevoort",
    "sg:orig_category":"Installation \u00e9lectrique r\u00e9sidentielle",
    "sg:phone":"+32 13 33 57 13",
    "sg:postcode":"3460",
    "sg:province":"Vlaams-Brabant",
    "wof:name":"Cyriel Frederickx",
    "wof:placetype":"venue"
},
  "geometry": {"coordinates":[4.9675397873,50.9421882629],"type":"Point"}
}