{
  "type": "Feature",
  "properties": {
    "iso:country":"BE",
    "sg:address":"Rue De La Poterie 22",
    "sg:city":"Chimay",
    "sg:orig_category":"Installation de menuiserie en bois and plastique. Travail and traitement du bois",
    "sg:phone":"+32 60 21 38 42",
    "sg:postcode":"6464",
    "sg:province":"Hainaut",
    "wof:name":"La Thierache",
    "wof:placetype":"venue"
},
  "geometry": {"coordinates":[4.3282661438,50.0261154175],"type":"Point"}
}