{
  "type": "Feature",
  "properties": {
    "iso:country":"BE",
    "sg:address":"Mechelsesteenweg 635",
    "sg:city":"Herent",
    "sg:classifiers":[
        {
            "category":"Cafe",
            "type":"Food & Drink"
        }
    ],
    "sg:phone":"+32 16 29 77 29",
    "sg:postcode":"3020",
    "sg:province":"Vlaams-Brabant",
    "sg:tags":[
        "snack-bars"
    ],
    "wof:name":"Martino Snack & Sandwichbar",
    "wof:placetype":"venue"
},
  "geometry": {"coordinates":[4.6872601509,50.8951911926],"type":"Point"}
}