{
  "type": "Feature",
  "properties": {
    "iso:country":"BE",
    "sg:address":"Richard Caluwaertstraat 36",
    "sg:city":"Eikevliet (bornem)",
    "sg:orig_category":"Meubles D\u00e9taillants, Am\u00e9nagement de B\u00e2timents et de Cuisines",
    "sg:phone":"+32 3 899 37 47",
    "sg:postcode":"2880",
    "sg:province":"Antwerpen",
    "wof:name":"Hypnos Waterbedden Eikevliet",
    "wof:placetype":"venue"
},
  "geometry": {"coordinates":[4.3032660484,51.0940284729],"type":"Point"}
}