{
  "type": "Feature",
  "properties": {
    "addr:full":"Avenue Reine Elisabeth 21 Oupeye Li\u00e8ge 4684",
    "addr:housenumber":"21",
    "addr:postcode":"4684",
    "addr:street":"Avenue Reine Elisabeth",
    "iso:country":"BE",
    "sg:address":"Avenue Reine Elisabeth 21",
    "sg:city":"Oupeye",
    "sg:orig_category":"Onderdelen and accessoires voor auto's",
    "sg:phone":"+32 4 379 55 37",
    "sg:postcode":"4684",
    "sg:province":"Li\u00e8ge",
    "wof:name":"Fe. Ledouppe",
    "wof:placetype":"venue"
},
  "geometry": {"coordinates":[5.6706080437,50.7341041565],"type":"Point"}
}