{
  "type": "Feature",
  "properties": {
    "addr:full":"Hoogkamerstraat 301 Temse Oost-Vlaanderen 9140",
    "addr:housenumber":"301",
    "addr:postcode":"9140",
    "addr:street":"Hoogkamerstraat",
    "iso:country":"BE",
    "sg:address":"Hoogkamerstraat 301",
    "sg:city":"Temse",
    "sg:orig_category":"Kapsalons",
    "sg:phone":"+32 3 771 11 52",
    "sg:postcode":"9140",
    "sg:province":"Oost-Vlaanderen",
    "wof:name":"Coiffure Danielle",
    "wof:placetype":"venue"
},
  "geometry": {"coordinates":[4.1915001869,51.1325416565],"type":"Point"}
}