{
  "type": "Feature",
  "properties": {
    "addr:full":"Oude Molsebaan 17 Balen Antwerpen 2490",
    "addr:housenumber":"17",
    "addr:postcode":"2490",
    "addr:street":"Oude Molsebaan",
    "iso:country":"BE",
    "sg:address":"Oude Molsebaan 17",
    "sg:city":"Balen",
    "sg:orig_category":"Verhuur cateringmateriaal and evenementuitrusting Winkelinrichting and handelsuitrusting Gh",
    "sg:phone":"+32 14 81 46 14",
    "sg:postcode":"2490",
    "sg:province":"Antwerpen",
    "wof:name":"Acca Container Service",
    "wof:placetype":"venue"
},
  "geometry": {"coordinates":[5.1524100304,51.1714401245],"type":"Point"}
}