{
  "type": "Feature",
  "properties": {
    "addr:full":"Rue De La Sainte-face 2-3 Aiseau-presles Hainaut 6250",
    "addr:housenumber":"2-3",
    "addr:postcode":"6250",
    "addr:street":"Rue De La Sainte-Face;Hainaut",
    "iso:country":"BE",
    "sg:address":"Rue De La Sainte-face 2-3",
    "sg:city":"Aiseau-presles",
    "sg:orig_category":"Sociale huisvestingsmaatschappijen",
    "sg:phone":"+32 71 39 05 66",
    "sg:postcode":"6250",
    "sg:province":"Hainaut",
    "wof:name":"H.b.m. D'aiseau-presles",
    "wof:placetype":"venue"
},
  "geometry": {"coordinates":[4.5466837883,50.4095230103],"type":"Point"}
}