{
  "type": "Feature",
  "properties": {
    "addr:full":"George Bergmannlaan 29 Elsene/ixelles Bruxelles-Capitale 1050",
    "addr:housenumber":"29",
    "addr:postcode":"1050",
    "addr:street":"George Bergmannlaan",
    "iso:country":"BE",
    "sg:address":"George Bergmannlaan 29",
    "sg:city":"Elsene/ixelles",
    "sg:orig_category":"Advocaten and juridische adviseurs",
    "sg:phone":"+32 2 673 61 63",
    "sg:postcode":"1050",
    "sg:province":"Bruxelles-Capitale",
    "wof:name":"S\u00c9verine Lamey",
    "wof:placetype":"venue"
},
  "geometry": {"coordinates":[4.3924951553,50.8096580505],"type":"Point"}
}