{
  "type": "Feature",
  "properties": {
    "iso:country":"BE",
    "sg:address":"Heidestraat 77",
    "sg:city":"Opglabbeek",
    "sg:classifiers":[
        {
            "category":"Personal",
            "subcategory":"Beauty Salon",
            "type":"Services"
        }
    ],
    "sg:phone":"+32 89 85 77 69",
    "sg:postcode":"3660",
    "sg:province":"Limburg",
    "sg:tags":[
        "lady",
        "-",
        "hairdressing"
    ],
    "wof:name":"Haarmode Maddy",
    "wof:placetype":"venue"
},
  "geometry": {"coordinates":[5.5815591812,51.0295257568],"type":"Point"}
}