{
  "type": "Feature",
  "properties": {
    "iso:country":"BE",
    "sg:address":"Jan Frans Stynenlei 25",
    "sg:city":"Borsbeek",
    "sg:orig_category":"Fietsen",
    "sg:phone":"+32 3 322 46 34",
    "sg:postcode":"2150",
    "sg:province":"Antwerpen",
    "wof:name":"Dirk Minjauw",
    "wof:placetype":"venue"
},
  "geometry": {"coordinates":[4.4871449471,51.1945114136],"type":"Point"}
}