{
  "type": "Feature",
  "properties": {
    "iso:country":"BE",
    "sg:address":"Azalealaan 8",
    "sg:city":"Moorslede (dadizele)",
    "sg:classifiers":[
        {
            "category":"Personal",
            "subcategory":"Beauty Salon",
            "type":"Services"
        }
    ],
    "sg:phone":"+32 56 50 08 66",
    "sg:postcode":"8890",
    "sg:province":"West-Vlaanderen",
    "sg:tags":[
        "lady",
        "-",
        "hairdressing"
    ],
    "wof:name":"Rita",
    "wof:placetype":"venue"
},
  "geometry": {"coordinates":[3.1021840572,50.8507423401],"type":"Point"}
}