{
  "type": "Feature",
  "properties": {
    "addr:full":"Boterstraat 9 Ieper West-Vlaanderen 8900",
    "addr:housenumber":"9",
    "addr:postcode":"8900",
    "addr:street":"Boterstraat",
    "iso:country":"BE",
    "sg:address":"Boterstraat 9",
    "sg:city":"Ieper",
    "sg:classifiers":[
        {
            "category":"Shopping",
            "subcategory":"Jewelry",
            "type":"Retail Goods"
        }
    ],
    "sg:phone":"+32 57 20 10 43",
    "sg:postcode":"8900",
    "sg:province":"West-Vlaanderen",
    "sg:tags":[
        "jeweller",
        "-"
    ],
    "wof:name":"Vandromme J",
    "wof:placetype":"venue"
},
  "geometry": {"coordinates":[2.8841218948,50.8503723145],"type":"Point"}
}