{
  "type": "Feature",
  "properties": {
    "addr:full":"Isenbaertstraat 94 Jabbeke (snellegem) West-Vlaanderen 8490",
    "addr:housenumber":"94",
    "addr:postcode":"8490",
    "addr:street":"Isenbaertstraat",
    "iso:country":"BE",
    "sg:address":"Isenbaertstraat 94",
    "sg:city":"Jabbeke (snellegem)",
    "sg:classifiers":[
        {
            "category":"Farming",
            "subcategory":"Crops",
            "type":"Manufacturing & Wholesale Goods"
        }
    ],
    "sg:phone":"+32 50 81 14 16",
    "sg:postcode":"8490",
    "sg:province":"West-Vlaanderen",
    "sg:tags":[
        "vegetable",
        "fruit",
        "-",
        "grower"
    ],
    "wof:name":"Franco J",
    "wof:placetype":"venue"
},
  "geometry": {"coordinates":[3.1118500233,51.1777610779],"type":"Point"}
}