{
  "type": "Feature",
  "properties": {
    "iso:country":"BE",
    "sg:address":"Bilzerweg 29",
    "sg:city":"Zutendaal",
    "sg:orig_category":"D\u00e9molition d\u00b4immeubles and terrassements",
    "sg:phone":"+32 89 61 25 46",
    "sg:postcode":"3690",
    "sg:province":"Limburg",
    "wof:name":"Menten Gebroeders",
    "wof:placetype":"venue"
},
  "geometry": {"coordinates":[5.548227787,50.9211769104],"type":"Point"}
}