{
  "type": "Feature",
  "properties": {
    "iso:country":"BE",
    "sg:address":"Kortelakestraat 22",
    "sg:city":"Geraardsbergen (overboelare)",
    "sg:classifiers":[
        {
            "category":"Retail",
            "subcategory":"Animal Services",
            "type":"Services"
        }
    ],
    "sg:phone":"+32 495 27 49 58",
    "sg:postcode":"9500",
    "sg:province":"Oost-Vlaanderen",
    "sg:tags":[
        "farrier"
    ],
    "wof:name":"Verspeet M",
    "wof:placetype":"venue"
},
  "geometry": {"coordinates":[3.856730938,50.7576637268],"type":"Point"}
}