{
  "type": "Feature",
  "properties": {
    "iso:country":"BE",
    "sg:address":"Av. Du Prince H\u00c9ritier 164",
    "sg:city":"Sint-lambrechts-woluwe/woluwe-saint-lambert",
    "sg:orig_category":"Agences de publicit\u00e9. Imprimeries and copyshops. Articles de f\u00eate, farces and attrapes",
    "sg:phone":"+32 2 736 92 80",
    "sg:postcode":"1200",
    "sg:province":"Bruxelles-Capitale",
    "wof:name":"Artemis",
    "wof:placetype":"venue"
},
  "geometry": {"coordinates":[4.4092922211,50.84582901],"type":"Point"}
}