{
  "type": "Feature",
  "properties": {
    "addr:full":"Rue Clair Matin 49 Eghez\u00c9e Namur 5310",
    "addr:housenumber":"49",
    "addr:postcode":"5310",
    "addr:street":"Rue Clair Matin",
    "iso:country":"BE",
    "sg:address":"Rue Clair Matin 49",
    "sg:city":"Eghez\u00c9e",
    "sg:orig_category":"Alternatieve geneeskunde",
    "sg:phone":"+32 81 81 11 11",
    "sg:postcode":"5310",
    "sg:province":"Namur",
    "wof:name":"M. Van Achter",
    "wof:placetype":"venue"
},
  "geometry": {"coordinates":[4.907886982,50.5996856689],"type":"Point"}
}