{
  "type": "Feature",
  "properties": {
    "addr:full":"Rottdriescherstrasse 95 Lontzen/lontzen Li\u00e8ge 4710",
    "addr:housenumber":"95",
    "addr:postcode":"4710",
    "addr:street":"Rottdriescherstrasse",
    "iso:country":"BE",
    "sg:address":"Rottdriescherstrasse 95",
    "sg:city":"Lontzen/lontzen",
    "sg:orig_category":"Woningbouw",
    "sg:phone":"+32 87 88 21 86",
    "sg:postcode":"4710",
    "sg:province":"Li\u00e8ge",
    "wof:name":"Fe. Bativa",
    "wof:placetype":"venue"
},
  "geometry": {"coordinates":[5.9910178185,50.670009613],"type":"Point"}
}