{
  "type": "Feature",
  "properties": {
    "addr:full":"Sint-amandstraat 1 Meulebeke West-Vlaanderen 8760",
    "addr:housenumber":"1",
    "addr:postcode":"8760",
    "addr:street":"Sint-Amandstraat",
    "iso:country":"BE",
    "sg:address":"Sint-amandstraat 1",
    "sg:city":"Meulebeke",
    "sg:orig_category":"Varkenskwekers",
    "sg:phone":"+32 56 66 66 85",
    "sg:postcode":"8760",
    "sg:province":"West-Vlaanderen",
    "wof:name":"Hendrik De Meulemeester",
    "wof:placetype":"venue"
},
  "geometry": {"coordinates":[3.3103098869,50.9249649048],"type":"Point"}
}