{
  "type": "Feature",
  "properties": {
    "addr:full":"Parkbos 17 Geraardsbergen (ophasselt) Oost-Vlaanderen 9500",
    "addr:housenumber":"17",
    "addr:postcode":"9500",
    "addr:street":"Parkbos",
    "iso:country":"BE",
    "sg:address":"Parkbos 17",
    "sg:city":"Geraardsbergen (ophasselt)",
    "sg:classifiers":[
        {
            "category":"Parking",
            "subcategory":"Garage",
            "type":"Transportation"
        }
    ],
    "sg:phone":"+32 9 360 64 68",
    "sg:postcode":"9500",
    "sg:province":"Oost-Vlaanderen",
    "sg:tags":[
        "truck",
        "-",
        "dump",
        "transport"
    ],
    "wof:name":"Depo Trans Bvba",
    "wof:placetype":"venue"
},
  "geometry": {"coordinates":[3.8843801022,50.7716445923],"type":"Point"}
}