{
  "type": "Feature",
  "properties": {
    "iso:country":"BE",
    "sg:address":"Rue Des Noyers 82",
    "sg:city":"Namur",
    "sg:orig_category":"Airconditioning and ventilatie Loodgieterij, verwarming and sanitaire installaties",
    "sg:phone":"+32 81 74 20 37",
    "sg:postcode":"5000",
    "sg:province":"Namur",
    "wof:name":"Pascal Schmite",
    "wof:placetype":"venue"
},
  "geometry": {"coordinates":[4.8442869186,50.4564971924],"type":"Point"}
}