{
  "type": "Feature",
  "properties": {
    "addr:full":"Rue D'havr\u00c9 30 Mons Hainaut 7000",
    "addr:housenumber":"30",
    "addr:postcode":"7000",
    "addr:street":"Rue D'Havre \u0301;Hainaut",
    "iso:country":"BE",
    "sg:address":"Rue D'havr\u00c9 30",
    "sg:city":"Mons",
    "sg:orig_category":"V\u00eatements pour b\u00e9b\u00e9s and enfants",
    "sg:phone":"+32 65 31 68 36",
    "sg:postcode":"7000",
    "sg:province":"Hainaut",
    "wof:name":"La Marmaille",
    "wof:placetype":"venue"
},
  "geometry": {"coordinates":[3.9536960125,50.4536361694],"type":"Point"}
}