{
  "type": "Feature",
  "properties": {
    "iso:country":"BE",
    "sg:address":"Avenue Lavoisier 1",
    "sg:city":"Wavre",
    "sg:classifiers":[
        {
            "category":"Manufacturing",
            "subcategory":"Tools & Machinery",
            "type":"Manufacturing & Wholesale Goods"
        }
    ],
    "sg:phone":"+32 10 23 05 09",
    "sg:postcode":"1300",
    "sg:province":"Brabant Wallon",
    "sg:tags":[
        "machine"
    ],
    "wof:name":"Osg Aimo Sa-nv (a.i.m.o.)",
    "wof:placetype":"venue"
},
  "geometry": {"coordinates":[4.5971140862,50.7357025146],"type":"Point"}
}