{
  "type": "Feature",
  "properties": {
    "iso:country":"BE",
    "sg:address":"Zeedijk 122",
    "sg:city":"Oostende",
    "sg:orig_category":"Evaluation and estimation de biens immobiliers. Maisons de vacances. Administration d'immeubles. Age",
    "sg:phone":"+32 59 70 75 21",
    "sg:postcode":"8400",
    "sg:province":"West-Vlaanderen",
    "wof:name":"Era Bureau Waldorf",
    "wof:placetype":"venue"
},
  "geometry": {"coordinates":[2.8900818825,51.2212867737],"type":"Point"}
}