{
  "type": "Feature",
  "properties": {
    "addr:full":"Avenue De La Salm 35 Vielsalm Luxembourg 6690",
    "addr:housenumber":"35",
    "addr:postcode":"6690",
    "addr:street":"Avenue De La Salm",
    "iso:country":"BE",
    "sg:address":"Avenue De La Salm 35",
    "sg:city":"Vielsalm",
    "sg:orig_category":"Maroquinerie and articles de voyage. Eclairage et \u00e9quipements du foyer",
    "sg:phone":"+32 80 21 63 39",
    "sg:postcode":"6690",
    "sg:province":"Luxembourg",
    "wof:name":"Bazar De La Salm",
    "wof:placetype":"venue"
},
  "geometry": {"coordinates":[5.9121642113,50.2804069519],"type":"Point"}
}