{
  "type": "Feature",
  "properties": {
    "iso:country":"BE",
    "sg:address":"Breugellaan 18",
    "sg:city":"Maldegem",
    "sg:orig_category":"Dierenartsen",
    "sg:phone":"+32 50 71 77 51",
    "sg:postcode":"9990",
    "sg:province":"Oost-Vlaanderen",
    "wof:name":"Peter Dhont",
    "wof:placetype":"venue"
},
  "geometry": {"coordinates":[3.4364960194,51.2147254944],"type":"Point"}
}