{
  "type": "Feature",
  "properties": {
    "addr:full":"Avenue Marius Meur\u00e9e 68 Charleroi (marcinelle) Hainaut 6001",
    "addr:housenumber":"68",
    "addr:postcode":"6001",
    "addr:street":"Avenue Marius Meure\u0301E",
    "iso:country":"BE",
    "sg:address":"Avenue Marius Meur\u00e9e 68",
    "sg:city":"Charleroi (marcinelle)",
    "sg:classifiers":[
        {
            "category":"Health Services",
            "subcategory":"Dentist",
            "type":"Services"
        }
    ],
    "sg:phone":"+32 71 36 31 07",
    "sg:postcode":"6001",
    "sg:province":"Hainaut",
    "wof:name":"Wastiau Gerard",
    "wof:placetype":"venue"
},
  "geometry": {"coordinates":[4.4457831383,50.4015159607],"type":"Point"}
}