{
  "type": "Feature",
  "properties": {
    "addr:full":"Christiaan Pallemansstraat 46 Kapellen Antwerpen 2950",
    "addr:housenumber":"46",
    "addr:postcode":"2950",
    "addr:street":"Christiaan Pallemansstraat",
    "iso:country":"BE",
    "sg:address":"Christiaan Pallemansstraat 46",
    "sg:city":"Kapellen",
    "sg:classifiers":[
        {
            "category":"Building & Trades",
            "subcategory":"Landscaping Services",
            "type":"Services"
        }
    ],
    "sg:phone":"+32 3 605 39 05",
    "sg:postcode":"2950",
    "sg:province":"Antwerpen",
    "sg:tags":[
        "architect",
        "landscape"
    ],
    "wof:name":"Vrebosch J",
    "wof:placetype":"venue"
},
  "geometry": {"coordinates":[4.4310541153,51.3162307739],"type":"Point"}
}