{
  "type": "Feature",
  "properties": {
    "addr:full":"Beiaardlaan 40 Grimbergen Vlaams-Brabant 1850",
    "addr:housenumber":"40",
    "addr:postcode":"1850",
    "addr:street":"Beiaardlaan",
    "iso:country":"BE",
    "sg:address":"Beiaardlaan 40",
    "sg:city":"Grimbergen",
    "sg:classifiers":[
        {
            "category":"Professional",
            "subcategory":"Lawyer & Legal Services",
            "type":"Services"
        }
    ],
    "sg:phone":"+32 2 269 13 92",
    "sg:postcode":"1850",
    "sg:province":"Vlaams-Brabant",
    "sg:tags":[
        "notary"
    ],
    "wof:name":"Verelst A",
    "wof:placetype":"venue"
},
  "geometry": {"coordinates":[4.3671197891,50.93516922],"type":"Point"}
}