{
  "type": "Feature",
  "properties": {
    "addr:full":"Prinsenhoflaan 33 Maaseik Limburg 3680",
    "addr:housenumber":"33",
    "addr:postcode":"3680",
    "addr:street":"Prinsenhoflaan",
    "iso:country":"BE",
    "sg:address":"Prinsenhoflaan 33",
    "sg:city":"Maaseik",
    "sg:orig_category":"Activit\u00e9s d\u00b4action sociale sans h\u00e9bergement",
    "sg:phone":"+32 89 56 32 30",
    "sg:postcode":"3680",
    "sg:province":"Limburg",
    "wof:name":"Vclb-centrum",
    "wof:placetype":"venue"
},
  "geometry": {"coordinates":[5.7876901627,51.0945396423],"type":"Point"}
}