{
  "type": "Feature",
  "properties": {
    "addr:full":"Dreefstraat 1 Sint-lievens-houtem Oost-Vlaanderen 9520",
    "addr:housenumber":"1",
    "addr:postcode":"9520",
    "addr:street":"Dreefstraat;Oost-Vlaanderen",
    "iso:country":"BE",
    "sg:address":"Dreefstraat 1",
    "sg:city":"Sint-lievens-houtem",
    "sg:orig_category":"Rusthuizen and serviceflats",
    "sg:phone":"+32 53 62 35 60",
    "sg:postcode":"9520",
    "sg:province":"Oost-Vlaanderen",
    "wof:name":"Huize St.alfons",
    "wof:placetype":"venue"
},
  "geometry": {"coordinates":[3.8749220371,50.9466934204],"type":"Point"}
}