{
  "type": "Feature",
  "properties": {
    "addr:full":"Rue De Lille 1 Comines-warneton (warneton) Hainaut 7784",
    "addr:housenumber":"1",
    "addr:postcode":"7784",
    "addr:street":"Rue De Lille",
    "iso:country":"BE",
    "sg:address":"Rue De Lille 1",
    "sg:city":"Comines-warneton (warneton)",
    "sg:classifiers":[
        {
            "category":"Professional",
            "subcategory":"Testing Lab",
            "type":"Services"
        }
    ],
    "sg:phone":"+32 56 55 56 17",
    "sg:postcode":"7784",
    "sg:province":"Hainaut",
    "sg:tags":[
        "chemist"
    ],
    "wof:name":"Dumortier J",
    "wof:placetype":"venue"
},
  "geometry": {"coordinates":[2.9483098984,50.752620697],"type":"Point"}
}