{
  "type": "Feature",
  "properties": {
    "addr:full":"Wijngaardveld 22a Aalst Oost-Vlaanderen 9300",
    "addr:housenumber":"22a",
    "addr:postcode":"9300",
    "addr:street":"Wijngaardveld",
    "iso:country":"BE",
    "sg:address":"Wijngaardveld 22a",
    "sg:city":"Aalst",
    "sg:classifiers":[
        {
            "category":"Professional",
            "subcategory":"Engineering",
            "type":"Services"
        }
    ],
    "sg:phone":"+32 53 77 32 66",
    "sg:postcode":"9300",
    "sg:province":"Oost-Vlaanderen",
    "sg:tags":[
        "technical",
        "industrial",
        "-",
        "subcontracting"
    ],
    "wof:name":"Industrial Service Nv",
    "wof:placetype":"venue"
},
  "geometry": {"coordinates":[4.0399589539,50.9567527771],"type":"Point"}
}