{
  "type": "Feature",
  "properties": {
    "addr:full":"Rue Du Centre 14 Florennes Namur 5620",
    "addr:housenumber":"14",
    "addr:postcode":"5620",
    "addr:street":"Rue Du Centre",
    "iso:country":"BE",
    "sg:address":"Rue Du Centre 14",
    "sg:city":"Florennes",
    "sg:orig_category":"Jardinage",
    "sg:phone":"+32 82 68 92 23",
    "sg:postcode":"5620",
    "sg:province":"Namur",
    "wof:name":"Raboz\u00c9e",
    "wof:placetype":"venue"
},
  "geometry": {"coordinates":[4.7138791084,50.2487258911],"type":"Point"}
}