{
  "type": "Feature",
  "properties": {
    "addr:full":"Oude Zeedijkstraat 6 Kortemark West-Vlaanderen 8610",
    "addr:housenumber":"6",
    "addr:postcode":"8610",
    "addr:street":"Oude Zeedijkstraat",
    "iso:country":"BE",
    "sg:address":"Oude Zeedijkstraat 6",
    "sg:city":"Kortemark",
    "sg:classifiers":[
        {
            "category":"Building & Trades",
            "subcategory":"Landscaping Services",
            "type":"Services"
        }
    ],
    "sg:phone":"+32 475 76 91 57",
    "sg:postcode":"8610",
    "sg:province":"West-Vlaanderen",
    "sg:tags":[
        "gardening",
        "garden",
        "maintenance"
    ],
    "wof:name":"Casier T",
    "wof:placetype":"venue"
},
  "geometry": {"coordinates":[3.0622758865,51.0221786499],"type":"Point"}
}