{
  "type": "Feature",
  "properties": {
    "iso:country":"BE",
    "sg:address":"Rue Franklin 5",
    "sg:city":"Brussel/bruxelles",
    "sg:classifiers":[
        {
            "category":"Restaurant",
            "type":"Food & Drink"
        }
    ],
    "sg:phone":"+32 2 735 18 76",
    "sg:postcode":"1000",
    "sg:province":"Bruxelles-Capitale",
    "sg:tags":[
        "de",
        "organisation",
        "\u00e0",
        "fast",
        "catering",
        "emporter",
        "f\u00eates",
        "restaurants"
    ],
    "wof:name":"Pizza Da Michel",
    "wof:placetype":"venue"
},
  "geometry": {"coordinates":[4.3843111992,50.844165802],"type":"Point"}
}