{
  "type": "Feature",
  "properties": {
    "addr:full":"Parkstraat 79 Leuven Vlaams-Brabant 3000",
    "addr:housenumber":"79",
    "addr:postcode":"3000",
    "addr:street":"Parkstraat",
    "iso:country":"BE",
    "sg:address":"Parkstraat 79",
    "sg:city":"Leuven",
    "sg:orig_category":"Brood, gebak and snoepgoed",
    "sg:phone":"+32 16 22 89 79",
    "sg:postcode":"3000",
    "sg:province":"Vlaams-Brabant",
    "wof:name":"Lodewijk Serneels",
    "wof:placetype":"venue"
},
  "geometry": {"coordinates":[4.702931881,50.8728752136],"type":"Point"}
}