{
  "type": "Feature",
  "properties": {
    "iso:country":"BE",
    "sg:address":"Voie De Saive 22",
    "sg:city":"Soumagne",
    "sg:orig_category":"HUISBRANDOLIE",
    "sg:phone":"+32 4 377 55 46",
    "sg:postcode":"4630",
    "sg:province":"Li\u00e8ge",
    "wof:name":"Fabien Doyen",
    "wof:placetype":"venue"
},
  "geometry": {"coordinates":[5.7472958565,50.6121063232],"type":"Point"}
}