{
  "type": "Feature",
  "properties": {
    "addr:full":"Z.i. Rue Champeau 32 Montignies-sur-sambre Hainaut 6061",
    "addr:housenumber":"z.i.;32",
    "addr:postcode":"6061",
    "addr:street":"Rue Champeau",
    "iso:country":"BE",
    "sg:address":"Z.i. Rue Champeau 32",
    "sg:city":"Montignies-sur-sambre",
    "sg:classifiers":[
        {
            "category":"Government",
            "subcategory":"Post Office",
            "type":"Public Place"
        }
    ],
    "sg:phone":"+32 71 30 96 56",
    "sg:postcode":"6061",
    "sg:province":"Hainaut",
    "sg:tags":[
        "mould",
        "part",
        "casting",
        "resin"
    ],
    "wof:name":"Modelage M\u00e9canique Gailly S.a.",
    "wof:placetype":"venue"
},
  "geometry": {"coordinates":[4.4942169189,50.403263092],"type":"Point"}
}