{
  "type": "Feature",
  "properties": {
    "iso:country":"BE",
    "sg:address":"Dormaalstraat 14",
    "sg:city":"Zoutleeuw",
    "sg:orig_category":"Producteurs de fruits",
    "sg:phone":"+32 11 78 11 73",
    "sg:postcode":"3440",
    "sg:province":"Vlaams-Brabant",
    "wof:name":"Oscar Gielen",
    "wof:placetype":"venue"
},
  "geometry": {"coordinates":[5.1097459793,50.8044128418],"type":"Point"}
}