{
  "type": "Feature",
  "properties": {
    "addr:full":"A. De Beusscherplein Zaventem Vlaams-Brabant 1933",
    "addr:postcode":"1933",
    "addr:street":"A.;Vlaams-Brabant",
    "iso:country":"BE",
    "sg:address":"A. De Beusscherplein",
    "sg:city":"Zaventem",
    "sg:classifiers":[
        {
            "category":"Fast Food",
            "type":"Food & Drink"
        }
    ],
    "sg:postcode":"1933",
    "sg:province":"Vlaams-Brabant",
    "sg:tags":[
        "meeneem",
        "restaurant"
    ],
    "wof:name":"Fran\u00c7oise & Werner",
    "wof:placetype":"venue"
},
  "geometry": {"coordinates":[4.514070034,50.8613243103],"type":"Point"}
}