{
  "type": "Feature",
  "properties": {
    "addr:full":"Hagedoornlaan 11 Ukkel/uccle Bruxelles-Capitale 1180",
    "addr:housenumber":"11",
    "addr:postcode":"1180",
    "addr:street":"Hagedoornlaan;/",
    "iso:country":"BE",
    "sg:address":"Hagedoornlaan 11",
    "sg:city":"Ukkel/uccle",
    "sg:orig_category":"Immobili\u00ebnkantoren",
    "sg:phone":"+32 2 358 36 52",
    "sg:postcode":"1180",
    "sg:province":"Bruxelles-Capitale",
    "wof:name":"Bureau Oostens",
    "wof:placetype":"venue"
},
  "geometry": {"coordinates":[4.3809089661,50.7778167725],"type":"Point"}
}