{
  "type": "Feature",
  "properties": {
    "addr:full":"Olmenstraat 36 Oostkamp West-Vlaanderen 8020",
    "addr:housenumber":"36",
    "addr:postcode":"8020",
    "addr:street":"Olmenstraat",
    "iso:country":"BE",
    "sg:address":"Olmenstraat 36",
    "sg:city":"Oostkamp",
    "sg:classifiers":[
        {
            "category":"Health Services",
            "subcategory":"Doctor",
            "type":"Services"
        }
    ],
    "sg:phone":"+32 50 36 23 90",
    "sg:postcode":"8020",
    "sg:province":"West-Vlaanderen",
    "sg:tags":[
        "medicinephysicians",
        "surgeon"
    ],
    "wof:name":"De Brabanter Griet",
    "wof:placetype":"venue"
},
  "geometry": {"coordinates":[3.2431559563,51.1787033081],"type":"Point"}
}