{
  "type": "Feature",
  "properties": {
    "addr:full":"Koningin Fabiolastraat 12 Wevelgem West-Vlaanderen 8560",
    "addr:housenumber":"12",
    "addr:postcode":"8560",
    "addr:street":"Koningin Fabiolastraat",
    "iso:country":"BE",
    "sg:address":"Koningin Fabiolastraat 12",
    "sg:city":"Wevelgem",
    "sg:orig_category":"Banken and kredietinstellingen",
    "sg:phone":"+32 56 41 14 18",
    "sg:postcode":"8560",
    "sg:province":"West-Vlaanderen",
    "wof:name":"Bank Van Roeselare",
    "wof:placetype":"venue"
},
  "geometry": {"coordinates":[3.2036850452,50.8422813416],"type":"Point"}
}