{
  "type": "Feature",
  "properties": {
    "iso:country":"BE",
    "sg:address":"Kruiskenstraat 32",
    "sg:city":"Sint-laureins",
    "sg:orig_category":"Installation \u00e9lectrique r\u00e9sidentielle",
    "sg:phone":"+32 9 379 84 86",
    "sg:postcode":"9980",
    "sg:province":"Oost-Vlaanderen",
    "wof:name":"Dobbelaere Christiaan",
    "wof:placetype":"venue"
},
  "geometry": {"coordinates":[3.5527288914,51.232460022],"type":"Point"}
}