{
  "type": "Feature",
  "properties": {
    "addr:full":"Avenue Michel Ange 73 Bruxelles Bruxelles-Capitale 1000",
    "addr:housenumber":"73",
    "addr:postcode":"1000",
    "addr:street":"Avenue Michel Ange",
    "iso:country":"BE",
    "sg:address":"Avenue Michel Ange 73",
    "sg:city":"Bruxelles",
    "sg:classifiers":[
        {
            "category":"Insurance",
            "subcategory":"Insurance Agent",
            "type":"Services"
        }
    ],
    "sg:phone":"+32 2 734 20 35",
    "sg:postcode":"1000",
    "sg:province":"Bruxelles-Capitale",
    "sg:tags":[
        "broker"
    ],
    "wof:name":"Curran T",
    "wof:placetype":"venue"
},
  "geometry": {"coordinates":[4.3863301277,50.8441925049],"type":"Point"}
}