{
  "type": "Feature",
  "properties": {
    "addr:full":"Place Du Jeu De Balle 67 Brussel/bruxelles Bruxelles-Capitale 1000",
    "addr:housenumber":"67",
    "addr:postcode":"1000",
    "addr:street":"Place Du Jeu De Balle;/",
    "iso:country":"BE",
    "sg:address":"Place Du Jeu De Balle 67",
    "sg:city":"Brussel/bruxelles",
    "sg:orig_category":"Antiquit\u00e9s",
    "sg:phone":"+32 2 512 85 29",
    "sg:postcode":"1000",
    "sg:province":"Bruxelles-Capitale",
    "wof:name":"Collections-livres",
    "wof:placetype":"venue"
},
  "geometry": {"coordinates":[4.3448400497,50.8366699219],"type":"Point"}
}