{
  "type": "Feature",
  "properties": {
    "iso:country":"BE",
    "sg:address":"W. Cobergherstraat 2",
    "sg:city":"Veurne",
    "sg:orig_category":"Eleveurs and marchands de porcs",
    "sg:phone":"+32 58 29 95 47",
    "sg:postcode":"8630",
    "sg:province":"West-Vlaanderen",
    "wof:name":"Luc Desimpel",
    "wof:placetype":"venue"
},
  "geometry": {"coordinates":[2.6096229553,51.026725769],"type":"Point"}
}