{
  "type": "Feature",
  "properties": {
    "addr:full":"Lippenslaan 316 Knokke-heist West-Vlaanderen 8300",
    "addr:housenumber":"316",
    "addr:postcode":"8300",
    "addr:street":"Lippenslaan",
    "iso:country":"BE",
    "sg:address":"Lippenslaan 316",
    "sg:city":"Knokke-heist",
    "sg:orig_category":"Chaussures. V\u00eatements pour Dames. V\u00eatements pour b\u00e9b\u00e9s and enfants. V\u00eatements pour Hommes",
    "sg:phone":"+32 50 61 55 38",
    "sg:postcode":"8300",
    "sg:province":"West-Vlaanderen",
    "wof:name":"Koperino",
    "wof:placetype":"venue"
},
  "geometry": {"coordinates":[3.2887101173,51.3489112854],"type":"Point"}
}