{
  "type": "Feature",
  "properties": {
    "addr:full":"Koningin Astridlaan 25 Kalmthout Antwerpen 2920",
    "addr:housenumber":"25",
    "addr:postcode":"2920",
    "addr:street":"Koningin Astridlaan",
    "iso:country":"BE",
    "sg:address":"Koningin Astridlaan 25",
    "sg:city":"Kalmthout",
    "sg:orig_category":"Diverse bedrijfsbeheeradviesbureaus",
    "sg:phone":"+32 3 666 10 40",
    "sg:postcode":"2920",
    "sg:province":"Antwerpen",
    "wof:name":"View & Vision",
    "wof:placetype":"venue"
},
  "geometry": {"coordinates":[4.4570450783,51.3695716858],"type":"Point"}
}