{
  "type": "Feature",
  "properties": {
    "addr:full":"Avenue Emile Vandervelde 152 Chatelet Hainaut 6200",
    "addr:housenumber":"152",
    "addr:postcode":"chatelet;6200",
    "addr:street":"Avenue Emile Vandervelde",
    "iso:country":"BE",
    "sg:address":"Avenue Emile Vandervelde 152",
    "sg:city":"Chatelet",
    "sg:orig_category":"Pain, p\u00e2tisseries and confiseries",
    "sg:phone":"+32 71 38 67 89",
    "sg:postcode":"6200",
    "sg:province":"Hainaut",
    "wof:name":"Camille Robas",
    "wof:placetype":"venue"
},
  "geometry": {"coordinates":[4.5205302238,50.396320343],"type":"Point"}
}