{
  "type": "Feature",
  "properties": {
    "addr:full":"Rue De L'amiti\u00c9 2 Wavre Brabant Wallon 1300",
    "addr:housenumber":"2;1300",
    "addr:street":"Rue De L'Amitie \u0301",
    "iso:country":"BE",
    "sg:address":"Rue De L'amiti\u00c9 2",
    "sg:city":"Wavre",
    "sg:orig_category":"Enseignement maternel and primaire",
    "sg:phone":"+32 10 41 84 00",
    "sg:postcode":"1300",
    "sg:province":"Brabant Wallon",
    "wof:name":"Ecole Fond. Communale",
    "wof:placetype":"venue"
},
  "geometry": {"coordinates":[4.5757641792,50.6956443787],"type":"Point"}
}