{
  "type": "Feature",
  "properties": {
    "addr:full":"Rue De La Poudri\u00c8re 14 Namur Namur 5100",
    "addr:housenumber":"14",
    "addr:postcode":"5100",
    "addr:street":"Rue De La Poudrie\u0300Re",
    "iso:country":"BE",
    "sg:address":"Rue De La Poudri\u00c8re 14",
    "sg:city":"Namur",
    "sg:orig_category":"Supermarkten",
    "sg:phone":"+32 81 30 68 78",
    "sg:postcode":"5100",
    "sg:province":"Namur",
    "wof:name":"Champion",
    "wof:placetype":"venue"
},
  "geometry": {"coordinates":[4.8713750839,50.4566345215],"type":"Point"}
}