{
  "type": "Feature",
  "properties": {
    "iso:country":"BE",
    "sg:address":"Tiensestraat 207",
    "sg:city":"Leuven",
    "sg:classifiers":[
        {
            "category":"Professional",
            "subcategory":"Art Services",
            "type":"Services"
        }
    ],
    "sg:phone":"+32 16 23 77 67",
    "sg:postcode":"3000",
    "sg:province":"Vlaams-Brabant",
    "sg:tags":[
        "photographer"
    ],
    "wof:name":"Van Eeckhout Luk (fotostudio)",
    "wof:placetype":"venue"
},
  "geometry": {"coordinates":[4.7119231224,50.8745117188],"type":"Point"}
}