{
  "type": "Feature",
  "properties": {
    "iso:country":"BE",
    "sg:address":"Driesstraat 8bb",
    "sg:city":"Wielsbeke",
    "sg:orig_category":"Quincailleries. Bois Gr",
    "sg:phone":"+32 56 66 70 15",
    "sg:postcode":"8710",
    "sg:province":"West-Vlaanderen",
    "wof:name":"Desmet & Cie Transports",
    "wof:placetype":"venue"
},
  "geometry": {"coordinates":[3.3679959774,50.9144821167],"type":"Point"}
}