{
  "type": "Feature",
  "properties": {
    "addr:full":"Markt 23 Assenede Oost-Vlaanderen 9960",
    "addr:housenumber":"23",
    "addr:postcode":"9960",
    "addr:street":"Markt",
    "iso:country":"BE",
    "sg:address":"Markt 23",
    "sg:city":"Assenede",
    "sg:orig_category":"Banques and organismes de cr\u00e9dit",
    "sg:phone":"+32 9 344 52 19",
    "sg:postcode":"9960",
    "sg:province":"Oost-Vlaanderen",
    "wof:name":"Dexia",
    "wof:placetype":"venue"
},
  "geometry": {"coordinates":[3.7533829212,51.2274360657],"type":"Point"}
}