{
  "type": "Feature",
  "properties": {
    "iso:country":"BE",
    "sg:address":"Place De La R\u00c9sistance 9",
    "sg:city":"Moeskroen/mouscron",
    "sg:orig_category":"Boucheries",
    "sg:phone":"+32 56 48 83 28",
    "sg:postcode":"7711",
    "sg:province":"Hainaut",
    "wof:name":"Vandenborre & Courtens",
    "wof:placetype":"venue"
},
  "geometry": {"coordinates":[3.3053660393,50.7282295227],"type":"Point"}
}