{
  "type": "Feature",
  "properties": {
    "addr:full":"Langestraat 23 Zottegem Oost-Vlaanderen 9620",
    "addr:housenumber":"23",
    "addr:postcode":"9620",
    "addr:street":"Langestraat",
    "iso:country":"BE",
    "sg:address":"Langestraat 23",
    "sg:city":"Zottegem",
    "sg:classifiers":[
        {
            "category":"Building & Trades",
            "subcategory":"Construction",
            "type":"Services"
        }
    ],
    "sg:phone":"+32 9 360 28 75",
    "sg:postcode":"9620",
    "sg:province":"Oost-Vlaanderen",
    "sg:tags":[
        "truss-makers"
    ],
    "wof:name":"Claes M-a",
    "wof:placetype":"venue"
},
  "geometry": {"coordinates":[3.8112111092,50.871181488],"type":"Point"}
}