{
  "type": "Feature",
  "properties": {
    "addr:full":"Rijselsestraat 143 Ieper West-Vlaanderen 8900",
    "addr:housenumber":"143",
    "addr:postcode":"8900",
    "addr:street":"Rijselsestraat",
    "iso:country":"BE",
    "sg:address":"Rijselsestraat 143",
    "sg:city":"Ieper",
    "sg:orig_category":"Pain, p\u00e2tisseries and confiseries",
    "sg:phone":"+32 57 20 96 12",
    "sg:postcode":"8900",
    "sg:province":"West-Vlaanderen",
    "wof:name":"Bakkerij Herv\u00c9",
    "wof:placetype":"venue"
},
  "geometry": {"coordinates":[2.8905529976,50.8448944092],"type":"Point"}
}