{
  "type": "Feature",
  "properties": {
    "iso:country":"BE",
    "sg:address":"Rue Du Parc 3",
    "sg:city":"Chapelle-lez-herlaimont",
    "sg:orig_category":"Diverse kredietdiensten",
    "sg:postcode":"7160",
    "sg:province":"Hainaut",
    "wof:name":"Postomat Chapelle-lez-herlaimont",
    "wof:placetype":"venue"
},
  "geometry": {"coordinates":[4.2833127975,50.4691314697],"type":"Point"}
}