{
  "type": "Feature",
  "properties": {
    "addr:full":"Rue Des Carri\u00e8res 1 Charleroi (marchienne-au-pont) Hainaut 6030",
    "addr:housenumber":"1",
    "addr:postcode":"6030",
    "addr:street":"Rue Des Carrie\u0300Res",
    "iso:country":"BE",
    "sg:address":"Rue Des Carri\u00e8res 1",
    "sg:city":"Charleroi (marchienne-au-pont)",
    "sg:classifiers":[
        {
            "category":"Manufacturing",
            "subcategory":"Metals",
            "type":"Manufacturing & Wholesale Goods"
        }
    ],
    "sg:phone":"+32 71 51 16 01",
    "sg:postcode":"6030",
    "sg:province":"Hainaut",
    "sg:tags":[
        "working"
    ],
    "wof:name":"Traitement Thermique Belge Division Marchienne-au-pont",
    "wof:placetype":"venue"
},
  "geometry": {"coordinates":[4.3978500366,50.3973999023],"type":"Point"}
}