{
  "type": "Feature",
  "properties": {
    "iso:country":"BE",
    "sg:address":"Avenue Paul Deschanel 84",
    "sg:city":"Schaarbeek/schaerbeek",
    "sg:orig_category":"M\u00e9decins and sp\u00e9cialistes",
    "sg:phone":"+32 2 245 48 75",
    "sg:postcode":"1030",
    "sg:province":"Bruxelles-Capitale",
    "wof:name":"Fabienne Liebens",
    "wof:placetype":"venue"
},
  "geometry": {"coordinates":[4.3796730042,50.860168457],"type":"Point"}
}