{
  "type": "Feature",
  "properties": {
    "iso:country":"BE",
    "sg:address":"Wapenaarteinde 40",
    "sg:city":"Sint-niklaas",
    "sg:orig_category":"Eleveurs and marchands de porcs",
    "sg:phone":"+32 9 348 64 85",
    "sg:postcode":"9112",
    "sg:province":"Oost-Vlaanderen",
    "wof:name":"Jozef Goethals",
    "wof:placetype":"venue"
},
  "geometry": {"coordinates":[3.9895598888,51.1457710266],"type":"Point"}
}