{
  "type": "Feature",
  "properties": {
    "addr:full":"Avenue Du Chant D'oiseau 124 Bruxelles (woluwe-saint-pierre) Bruxelles-Capitale 1150",
    "addr:housenumber":"124",
    "addr:postcode":"1150",
    "addr:street":"Avenue Du Chant D'Oiseau",
    "iso:country":"BE",
    "sg:address":"Avenue Du Chant D'oiseau 124",
    "sg:city":"Bruxelles (woluwe-saint-pierre)",
    "sg:classifiers":[
        {
            "category":"Professional",
            "subcategory":"Art Services",
            "type":"Services"
        }
    ],
    "sg:phone":"+32 2 675 25 03",
    "sg:postcode":"1150",
    "sg:province":"Bruxelles-Capitale",
    "sg:tags":[
        "-",
        "painter",
        "artist"
    ],
    "wof:name":"Ghobert M",
    "wof:placetype":"venue"
},
  "geometry": {"coordinates":[4.411960125,50.8225479126],"type":"Point"}
}