{
  "type": "Feature",
  "properties": {
    "addr:full":"Rue De Menin 248 Mouscron Hainaut 7700",
    "addr:housenumber":"248",
    "addr:postcode":"7700",
    "addr:street":"Rue De Menin",
    "iso:country":"BE",
    "sg:address":"Rue De Menin 248",
    "sg:city":"Mouscron",
    "sg:classifiers":[
        {
            "category":"Quarry",
            "type":"Physical Feature"
        }
    ],
    "sg:phone":"+32 56 33 06 89",
    "sg:postcode":"7700",
    "sg:province":"Hainaut",
    "sg:tags":[
        "granite",
        "work",
        "marble"
    ],
    "wof:name":"Vansype J-l",
    "wof:placetype":"venue"
},
  "geometry": {"coordinates":[3.2076239586,50.7504997253],"type":"Point"}
}