{
  "type": "Feature",
  "properties": {
    "addr:full":"Rue De Soulme 78 Florennes (morville) Namur 5620",
    "addr:housenumber":"78",
    "addr:postcode":"5620",
    "addr:street":"Rue De Soulme",
    "iso:country":"BE",
    "sg:address":"Rue De Soulme 78",
    "sg:city":"Florennes (morville)",
    "sg:classifiers":[
        {
            "category":"Banks & Credit Unions",
            "subcategory":"Investment Brokerage",
            "type":"Services"
        }
    ],
    "sg:phone":"+32 82 21 94 71",
    "sg:postcode":"5620",
    "sg:province":"Namur",
    "sg:tags":[
        "repair",
        "-",
        "installation",
        "sanitary",
        "article"
    ],
    "wof:name":"Dhondt Dirk",
    "wof:placetype":"venue"
},
  "geometry": {"coordinates":[4.7457008362,50.2336540222],"type":"Point"}
}