{
  "type": "Feature",
  "properties": {
    "iso:country":"BE",
    "sg:address":"Nieuwe Baan 60a",
    "sg:city":"Hoeselt",
    "sg:orig_category":"Sportclubs",
    "sg:phone":"+32 12 23 45 10",
    "sg:postcode":"3730",
    "sg:province":"Limburg",
    "wof:name":"W.c. De Vrijheid Alt-hoeselt",
    "wof:placetype":"venue"
},
  "geometry": {"coordinates":[5.4841628075,50.8244132996],"type":"Point"}
}