{
  "type": "Feature",
  "properties": {
    "iso:country":"BE",
    "sg:address":"Vieux-remparts 4",
    "sg:city":"Renaix",
    "sg:classifiers":[
        {
            "category":"Shopping",
            "subcategory":"Clothing, Apparel, & Fashions",
            "type":"Retail Goods"
        }
    ],
    "sg:phone":"+32 55 23 91 67",
    "sg:postcode":"9600",
    "sg:province":"Oost-Vlaanderen",
    "sg:tags":[
        "boutique"
    ],
    "wof:name":"F\u00e9line",
    "wof:placetype":"venue"
},
  "geometry": {"coordinates":[3.6002221107,50.7464408875],"type":"Point"}
}