{
  "type": "Feature",
  "properties": {
    "addr:full":"Chauss\u00c9e De Lille 303 Moeskroen/mouscron Hainaut 7700",
    "addr:housenumber":"303",
    "addr:postcode":"7700",
    "addr:street":"Chausse\u0301E De Lille",
    "iso:country":"BE",
    "sg:address":"Chauss\u00c9e De Lille 303",
    "sg:city":"Moeskroen/mouscron",
    "sg:orig_category":"Journaux. Tabac",
    "sg:phone":"+32 56 34 80 41",
    "sg:postcode":"7700",
    "sg:province":"Hainaut",
    "wof:name":"Press Center",
    "wof:placetype":"venue"
},
  "geometry": {"coordinates":[3.2323200703,50.7400932312],"type":"Point"}
}