{
  "type": "Feature",
  "properties": {
    "addr:full":"Stationsstraat 45 Gistel West-Vlaanderen 8470",
    "addr:housenumber":"45",
    "addr:postcode":"8470",
    "addr:street":"Stationsstraat",
    "iso:country":"BE",
    "sg:address":"Stationsstraat 45",
    "sg:city":"Gistel",
    "sg:orig_category":"Boucheries",
    "sg:phone":"+32 59 27 85 78",
    "sg:postcode":"8470",
    "sg:province":"West-Vlaanderen",
    "wof:name":"Joel Loontjens",
    "wof:placetype":"venue"
},
  "geometry": {"coordinates":[2.9641709328,51.1551055908],"type":"Point"}
}