{
  "type": "Feature",
  "properties": {
    "iso:country":"BE",
    "sg:address":"Canadaplein 1",
    "sg:city":"Oostende",
    "sg:classifiers":[
        {
            "category":"Professional",
            "subcategory":"Accounting & Tax Preparation",
            "type":"Services"
        }
    ],
    "sg:phone":"+32 59 51 44 28",
    "sg:postcode":"8400",
    "sg:province":"West-Vlaanderen",
    "sg:tags":[
        "accountant"
    ],
    "wof:name":"Vercruysse J",
    "wof:placetype":"venue"
},
  "geometry": {"coordinates":[2.9168040752,51.227432251],"type":"Point"}
}