{
  "type": "Feature",
  "properties": {
    "iso:country":"BE",
    "sg:address":"Archimedesstraat 15",
    "sg:city":"Oostende (stene)",
    "sg:classifiers":[
        {
            "category":"Utilities",
            "subcategory":"Mobile Phone",
            "type":"Services"
        }
    ],
    "sg:phone":"+32 59 80 70 80",
    "sg:postcode":"8400",
    "sg:province":"West-Vlaanderen",
    "sg:tags":[
        "access",
        "gsm",
        "-",
        "apparatus"
    ],
    "wof:name":"Stratyx Business Solutions",
    "wof:placetype":"venue"
},
  "geometry": {"coordinates":[2.9416429996,51.2117118835],"type":"Point"}
}