{
  "type": "Feature",
  "properties": {
    "iso:country":"BE",
    "sg:address":"Rollegemstraat 14",
    "sg:city":"Ledegem",
    "sg:classifiers":[
        {
            "category":"Bakery",
            "type":"Food & Drink"
        }
    ],
    "sg:phone":"+32 56 50 34 56",
    "sg:postcode":"8880",
    "sg:province":"West-Vlaanderen",
    "sg:tags":[
        "confectioner",
        "baker"
    ],
    "wof:name":"Vansteenkiste J",
    "wof:placetype":"venue"
},
  "geometry": {"coordinates":[3.1281740665,50.855304718],"type":"Point"}
}