{
  "type": "Feature",
  "properties": {
    "addr:full":"Avenue Adolphe Buyl 164 Elsene/ixelles Bruxelles-Capitale 1050",
    "addr:housenumber":"164",
    "addr:postcode":"1050",
    "addr:street":"Avenue Adolphe Buyl",
    "iso:country":"BE",
    "sg:address":"Avenue Adolphe Buyl 164",
    "sg:city":"Elsene/ixelles",
    "sg:orig_category":"M\u00e9decins and sp\u00e9cialistes",
    "sg:phone":"+32 2 351 14 60",
    "sg:postcode":"1050",
    "sg:province":"Bruxelles-Capitale",
    "wof:name":"Bertrand Ninove",
    "wof:placetype":"venue"
},
  "geometry": {"coordinates":[4.3851971626,50.8128852844],"type":"Point"}
}