{
  "type": "Feature",
  "properties": {
    "iso:country":"BE",
    "sg:address":"Rue De Luxensart 42",
    "sg:city":"Seneffe",
    "sg:orig_category":"Rundveehouders",
    "sg:phone":"+32 67 87 71 79",
    "sg:postcode":"7181",
    "sg:province":"Hainaut",
    "wof:name":"Didier Hans",
    "wof:placetype":"venue"
},
  "geometry": {"coordinates":[4.2589969635,50.5626296997],"type":"Point"}
}