{
  "type": "Feature",
  "properties": {
    "iso:country":"BE",
    "sg:address":"Quai De-gaulle 4",
    "sg:city":"Li\u00e8ge 1 (li\u00e8ge 2)",
    "sg:classifiers":[
        {
            "category":"Real Estate",
            "subcategory":"Architect",
            "type":"Services"
        }
    ],
    "sg:phone":"+32 4 342 72 95",
    "sg:postcode":"4020",
    "sg:province":"Li\u00e8ge",
    "wof:name":"Noirhomme L",
    "wof:placetype":"venue"
},
  "geometry": {"coordinates":[5.5797390938,50.6428947449],"type":"Point"}
}