{
  "type": "Feature",
  "properties": {
    "addr:full":"Zuidstraat 23 Jabbeke West-Vlaanderen 8490",
    "addr:housenumber":"23",
    "addr:postcode":"8490",
    "addr:street":"Zuidstraat",
    "iso:country":"BE",
    "sg:address":"Zuidstraat 23",
    "sg:city":"Jabbeke",
    "sg:orig_category":"Mat\u00e9riaux de construction Combustibles. D\u00e9molition d\u00b4immeubles and terrassements",
    "sg:phone":"+32 50 81 17 41",
    "sg:postcode":"8490",
    "sg:province":"West-Vlaanderen",
    "wof:name":"Vanhove & Derieuw",
    "wof:placetype":"venue"
},
  "geometry": {"coordinates":[3.0868599415,51.1789321899],"type":"Point"}
}