{
  "type": "Feature",
  "properties": {
    "addr:full":"Keerken 1 Lokeren Oost-Vlaanderen 9160",
    "addr:housenumber":"1",
    "addr:postcode":"9160",
    "addr:street":"Keerken",
    "iso:country":"BE",
    "sg:address":"Keerken 1",
    "sg:city":"Lokeren",
    "sg:orig_category":"Sportclubs",
    "sg:phone":"+32 9 348 33 51",
    "sg:postcode":"9160",
    "sg:province":"Oost-Vlaanderen",
    "wof:name":"Lokerse Badmintonclub",
    "wof:placetype":"venue"
},
  "geometry": {"coordinates":[3.9864850044,51.1047401428],"type":"Point"}
}