{
  "type": "Feature",
  "properties": {
    "iso:country":"BE",
    "sg:address":"Rue De Malvoisin 37",
    "sg:city":"Gedinne",
    "sg:orig_category":"Avocats and conseillers juridiques",
    "sg:phone":"+32 61 58 93 43",
    "sg:postcode":"5575",
    "sg:province":"Namur",
    "wof:name":"Nadine Vanlishout",
    "wof:placetype":"venue"
},
  "geometry": {"coordinates":[4.9510598183,50.000125885],"type":"Point"}
}