{
  "type": "Feature",
  "properties": {
    "addr:full":"Doornpark 12 Beveren Oost-Vlaanderen 9120",
    "addr:housenumber":"12",
    "addr:postcode":"9120",
    "addr:street":"Doornpark",
    "iso:country":"BE",
    "sg:address":"Doornpark 12",
    "sg:city":"Beveren",
    "sg:orig_category":"Zuivelproducten",
    "sg:phone":"+32 3 775 45 97",
    "sg:postcode":"9120",
    "sg:province":"Oost-Vlaanderen",
    "wof:name":"De Bock",
    "wof:placetype":"venue"
},
  "geometry": {"coordinates":[4.2143502235,51.1976356506],"type":"Point"}
}