{
  "type": "Feature",
  "properties": {
    "addr:full":"Chauss\u00e9e De Renaix 96 Frasnes-lez-anvaing (dergneau) Hainaut 7912",
    "addr:housenumber":"96",
    "addr:postcode":"7912",
    "addr:street":"Chausse\u0301E De Renaix",
    "iso:country":"BE",
    "sg:address":"Chauss\u00e9e De Renaix 96",
    "sg:city":"Frasnes-lez-anvaing (dergneau)",
    "sg:classifiers":[
        {
            "category":"Autos & Motor Vehicles",
            "subcategory":"Automobile Sales",
            "type":"Retail Goods"
        }
    ],
    "sg:phone":"+32 69 76 85 41",
    "sg:postcode":"7912",
    "sg:province":"Hainaut",
    "sg:tags":[
        "car",
        "used",
        "-"
    ],
    "wof:name":"Foret J",
    "wof:placetype":"venue"
},
  "geometry": {"coordinates":[3.5797669888,50.7096061707],"type":"Point"}
}