{
  "type": "Feature",
  "properties": {
    "addr:full":"Rue Louis Pi\u00c9rard 46 Quaregnon Hainaut 7390",
    "addr:housenumber":"46",
    "addr:postcode":"7390",
    "addr:street":"Rue Louis Pie\u0301Rard",
    "iso:country":"BE",
    "sg:address":"Rue Louis Pi\u00c9rard 46",
    "sg:city":"Quaregnon",
    "sg:orig_category":"M\u00e9decins and sp\u00e9cialistes",
    "sg:phone":"+32 65 88 53 59",
    "sg:postcode":"7390",
    "sg:province":"Hainaut",
    "wof:name":"Ladislau Szegedi",
    "wof:placetype":"venue"
},
  "geometry": {"coordinates":[3.8810911179,50.4239692688],"type":"Point"}
}