{
  "type": "Feature",
  "properties": {
    "addr:full":"Rue Saint-jean 27 Anderlues Hainaut 6150",
    "addr:housenumber":"27",
    "addr:postcode":"6150",
    "addr:street":"Rue Saint-Jean",
    "iso:country":"BE",
    "sg:address":"Rue Saint-jean 27",
    "sg:city":"Anderlues",
    "sg:classifiers":[
        {
            "category":"Banks & Credit Unions",
            "subcategory":"Investment Brokerage",
            "type":"Services"
        }
    ],
    "sg:phone":"+32 71 52 14 80",
    "sg:postcode":"6150",
    "sg:province":"Hainaut",
    "sg:tags":[
        "railroad",
        "work"
    ],
    "wof:name":"Railconstruct Nv",
    "wof:placetype":"venue"
},
  "geometry": {"coordinates":[4.2839818001,50.4037322998],"type":"Point"}
}