{
  "type": "Feature",
  "properties": {
    "iso:country":"BE",
    "sg:address":"Edward Staintonstraat 60",
    "sg:city":"Heusden-zolder (heusden)",
    "sg:classifiers":[
        {
            "category":"Health Services",
            "subcategory":"Doctor",
            "type":"Services"
        }
    ],
    "sg:phone":"+32 11 57 14 86",
    "sg:postcode":"3550",
    "sg:province":"Limburg",
    "sg:tags":[
        "medicinephysicians",
        "surgeon"
    ],
    "wof:name":"Gerits Roger",
    "wof:placetype":"venue"
},
  "geometry": {"coordinates":[5.3072729111,51.0400123596],"type":"Point"}
}