{
  "type": "Feature",
  "properties": {
    "addr:full":"Rue D'otreppe 60 Fernelmont Namur 5380",
    "addr:housenumber":"60",
    "addr:postcode":"5380",
    "addr:street":"Rue D'Otreppe",
    "iso:country":"BE",
    "sg:address":"Rue D'otreppe 60",
    "sg:city":"Fernelmont",
    "sg:classifiers":[
        {
            "category":"Food & Beverages",
            "subcategory":"Fruits & Vegetables",
            "type":"Retail Goods"
        }
    ],
    "sg:phone":"+32 81 83 33 66",
    "sg:postcode":"5380",
    "sg:province":"Namur",
    "sg:tags":[
        "groenten"
    ],
    "wof:name":"E.v.h.",
    "wof:placetype":"venue"
},
  "geometry": {"coordinates":[5.0312790871,50.562122345],"type":"Point"}
}