{
  "type": "Feature",
  "properties": {
    "addr:full":"Rue Hector Denis 163 Saint-nicolas (montegn\u00e9e) Li\u00e8ge 4420",
    "addr:housenumber":"163",
    "addr:postcode":"4420",
    "addr:street":"Rue Hector Denis;Montegne\u0301E",
    "iso:country":"BE",
    "sg:address":"Rue Hector Denis 163",
    "sg:city":"Saint-nicolas (montegn\u00e9e)",
    "sg:classifiers":[
        {
            "category":"Retail",
            "subcategory":"Repair Shop",
            "type":"Services"
        }
    ],
    "sg:phone":"+32 4 263 47 45",
    "sg:postcode":"4420",
    "sg:province":"Li\u00e8ge",
    "sg:tags":[
        "-",
        "mainten",
        "watch",
        "clock"
    ],
    "wof:name":"Pr\u00e9cision Horlog\u00e8re (la)",
    "wof:placetype":"venue"
},
  "geometry": {"coordinates":[5.5271649361,50.6436843872],"type":"Point"}
}