{
  "type": "Feature",
  "properties": {
    "addr:full":"Avenue Charles Michiels 170 Box 4 Bruxelles (watermael-boitsfort) Bruxelles-Capitale 1170",
    "addr:housenumber":"170;4",
    "addr:postcode":"1170",
    "addr:street":"Avenue Charles Michiels;Box",
    "iso:country":"BE",
    "sg:address":"Avenue Charles Michiels 170 Box 4",
    "sg:city":"Bruxelles (watermael-boitsfort)",
    "sg:classifiers":[
        {
            "category":"Professional",
            "subcategory":"Lawyer & Legal Services",
            "type":"Services"
        }
    ],
    "sg:phone":"+32 2 660 54 33",
    "sg:postcode":"1170",
    "sg:province":"Bruxelles-Capitale",
    "wof:name":"Bienfait Andr\u00e9",
    "wof:placetype":"venue"
},
  "geometry": {"coordinates":[4.4043598175,50.8147544861],"type":"Point"}
}