{
  "type": "Feature",
  "properties": {
    "addr:full":"Hemelingenstraat 40bb 1 Tongeren Limburg 3700",
    "addr:housenumber":"40bb 1",
    "addr:postcode":"3700",
    "addr:street":"Hemelingenstraat",
    "iso:country":"BE",
    "sg:address":"Hemelingenstraat 40bb 1",
    "sg:city":"Tongeren",
    "sg:orig_category":"Bagage and lederwaren Schoenen",
    "sg:phone":"+32 12 23 84 29",
    "sg:postcode":"3700",
    "sg:province":"Limburg",
    "wof:name":"Nadia Bortels",
    "wof:placetype":"venue"
},
  "geometry": {"coordinates":[5.462211132,50.7816925049],"type":"Point"}
}