{
  "type": "Feature",
  "properties": {
    "iso:country":"BE",
    "sg:address":"Ieperstr 15",
    "sg:city":"Lo-reninge",
    "sg:classifiers":[
        {
            "category":"Bakery",
            "type":"Food & Drink"
        }
    ],
    "sg:phone":"+32 57 40 02 13",
    "sg:postcode":"8647",
    "sg:province":"West-Vlaanderen",
    "sg:tags":[
        "cake",
        "product",
        "related",
        "bread"
    ],
    "wof:name":"Lemahieu Henri M.",
    "wof:placetype":"venue"
},
  "geometry": {"coordinates":[2.7901170254,50.9449272156],"type":"Point"}
}