{
  "type": "Feature",
  "properties": {
    "addr:full":"Industrieweg 134 Gent Oost-Vlaanderen 9030",
    "addr:housenumber":"134",
    "addr:postcode":"9030",
    "addr:street":"Industrieweg;Oost-Vlaanderen",
    "iso:country":"BE",
    "sg:address":"Industrieweg 134",
    "sg:city":"Gent",
    "sg:orig_category":"Supermarkten",
    "sg:phone":"+32 9 237 28 11",
    "sg:postcode":"9030",
    "sg:province":"Oost-Vlaanderen",
    "wof:name":"Profi Noord",
    "wof:placetype":"venue"
},
  "geometry": {"coordinates":[3.6860890388,51.0896911621],"type":"Point"}
}