{
  "type": "Feature",
  "properties": {
    "addr:full":"Stationsstraat 84 Alken Limburg 3570",
    "addr:housenumber":"84",
    "addr:postcode":"3570",
    "addr:street":"Stationsstraat",
    "iso:country":"BE",
    "sg:address":"Stationsstraat 84",
    "sg:city":"Alken",
    "sg:classifiers":[
        {
            "category":"Insurance",
            "subcategory":"Insurance Agent",
            "type":"Services"
        }
    ],
    "sg:postcode":"3570",
    "sg:province":"Limburg",
    "sg:tags":[
        "broker"
    ],
    "wof:name":"Martens & Co Bvba",
    "wof:placetype":"venue"
},
  "geometry": {"coordinates":[5.2966661453,50.8847694397],"type":"Point"}
}