{
  "type": "Feature",
  "properties": {
    "iso:country":"BE",
    "sg:address":"Rue Grande 13",
    "sg:city":"Grace-hollogne",
    "sg:orig_category":"Location de logements sociaux",
    "sg:phone":"+32 4 234 75 75",
    "sg:postcode":"4460",
    "sg:province":"Li\u00e8ge",
    "wof:name":"Notre Logis",
    "wof:placetype":"venue"
},
  "geometry": {"coordinates":[5.4761371613,50.6330718994],"type":"Point"}
}