{
  "type": "Feature",
  "properties": {
    "iso:country":"BE",
    "sg:address":"Kerkstraat 24",
    "sg:city":"Ravels",
    "sg:orig_category":"Enseignement maternel and primaire",
    "sg:phone":"+32 14 65 63 86",
    "sg:postcode":"2380",
    "sg:province":"Antwerpen",
    "wof:name":"Gemeentel. Lagere School",
    "wof:placetype":"venue"
},
  "geometry": {"coordinates":[4.9954872131,51.3721466064],"type":"Point"}
}