{
  "type": "Feature",
  "properties": {
    "addr:full":"Ooievaarsdreef 11 Schoten Antwerpen 2900",
    "addr:housenumber":"11",
    "addr:postcode":"2900",
    "addr:street":"Ooievaarsdreef",
    "iso:country":"BE",
    "sg:address":"Ooievaarsdreef 11",
    "sg:city":"Schoten",
    "sg:classifiers":[
        {
            "category":"Manufacturing",
            "subcategory":"Food",
            "type":"Manufacturing & Wholesale Goods"
        }
    ],
    "sg:phone":"+32 3 651 85 55",
    "sg:postcode":"2900",
    "sg:province":"Antwerpen",
    "sg:tags":[
        "industry",
        "-",
        "ingredient"
    ],
    "wof:name":"Hoogenboom-agrarische Producten Nv",
    "wof:placetype":"venue"
},
  "geometry": {"coordinates":[4.5003228188,51.2775535583],"type":"Point"}
}