{
  "type": "Feature",
  "properties": {
    "addr:full":"Veemarkt 44 Tienen Vlaams-Brabant 3300",
    "addr:housenumber":"44",
    "addr:postcode":"3300",
    "addr:street":"Veemarkt",
    "iso:country":"BE",
    "sg:address":"Veemarkt 44",
    "sg:city":"Tienen",
    "sg:classifiers":[
        {
            "category":"Restaurant",
            "type":"Food & Drink"
        }
    ],
    "sg:phone":"+32 16 82 00 18",
    "sg:postcode":"3300",
    "sg:province":"Vlaams-Brabant",
    "sg:tags":[
        "caf\u00e9s"
    ],
    "wof:name":"Pub",
    "wof:placetype":"venue"
},
  "geometry": {"coordinates":[4.9405179024,50.805770874],"type":"Point"}
}