{
  "type": "Feature",
  "properties": {
    "addr:full":"Poel 41 Haaltert (denderhoutem) Oost-Vlaanderen 9450",
    "addr:housenumber":"41",
    "addr:postcode":"9450",
    "addr:street":"Poel",
    "iso:country":"BE",
    "sg:address":"Poel 41",
    "sg:city":"Haaltert (denderhoutem)",
    "sg:classifiers":[
        {
            "category":"Building & Trades",
            "subcategory":"Electrical",
            "type":"Services"
        }
    ],
    "sg:phone":"+32 54 33 36 90",
    "sg:postcode":"9450",
    "sg:province":"Oost-Vlaanderen",
    "sg:tags":[
        "electric",
        "-",
        "housewiring",
        "contractor"
    ],
    "wof:name":"Muylaert Johan Bvba",
    "wof:placetype":"venue"
},
  "geometry": {"coordinates":[4.0243701935,50.8694839478],"type":"Point"}
}