{
  "type": "Feature",
  "properties": {
    "addr:full":"Montignystraat 24 Antwerpen Antwerpen 2018",
    "addr:housenumber":"24",
    "addr:postcode":"2018",
    "addr:street":"Montignystraat",
    "iso:country":"BE",
    "sg:address":"Montignystraat 24",
    "sg:city":"Antwerpen",
    "sg:classifiers":[
        {
            "category":"Bars & Pubs",
            "type":"Food & Drink"
        }
    ],
    "sg:phone":"+32 3 248 03 68",
    "sg:postcode":"2018",
    "sg:province":"Antwerpen",
    "wof:name":"Bieke ('t)",
    "wof:placetype":"venue"
},
  "geometry": {"coordinates":[4.3920350075,51.2046051025],"type":"Point"}
}