{
  "type": "Feature",
  "properties": {
    "iso:country":"BE",
    "sg:address":"Rozengaard 44",
    "sg:city":"Diest",
    "sg:orig_category":"Enseignement secondaire technique and professionnel",
    "sg:phone":"+32 13 35 01 90",
    "sg:postcode":"3290",
    "sg:province":"Vlaams-Brabant",
    "wof:name":"Instituut Mariendaal",
    "wof:placetype":"venue"
},
  "geometry": {"coordinates":[5.0575699806,50.9813041687],"type":"Point"}
}