{
  "type": "Feature",
  "properties": {
    "iso:country":"BE",
    "sg:address":"Stationsstraat 12",
    "sg:city":"Aalst",
    "sg:orig_category":"Artsen and specialisten",
    "sg:phone":"+32 53 21 68 39",
    "sg:postcode":"9300",
    "sg:province":"Oost-Vlaanderen",
    "wof:name":"Guy Sallet",
    "wof:placetype":"venue"
},
  "geometry": {"coordinates":[4.0373649597,50.9418144226],"type":"Point"}
}