{
  "type": "Feature",
  "properties": {
    "addr:full":"Vichtseweg 230 Waregem West-Vlaanderen 8790",
    "addr:housenumber":"230",
    "addr:postcode":"8790",
    "iso:country":"BE",
    "sg:address":"Vichtseweg 230",
    "sg:city":"Waregem",
    "sg:orig_category":"Non-Classified Establishments",
    "sg:phone":"+32 56 77 73 87",
    "sg:postcode":"8790",
    "sg:province":"West-Vlaanderen",
    "wof:name":"Weverij Kuipershof Bvba",
    "wof:placetype":"venue"
},
  "geometry": {"coordinates":[3.406881094,50.8477592468],"type":"Point"}
}