{
  "type": "Feature",
  "properties": {
    "iso:country":"BE",
    "sg:address":"Kriesberg 11",
    "sg:city":"Holsbeek",
    "sg:orig_category":"Producteurs de l\u00e9gumes",
    "sg:phone":"+32 16 56 00 84",
    "sg:postcode":"3221",
    "sg:province":"Vlaams-Brabant",
    "wof:name":"Paul Van Den Bosch",
    "wof:placetype":"venue"
},
  "geometry": {"coordinates":[4.8470840454,50.9536476135],"type":"Point"}
}