{
  "type": "Feature",
  "properties": {
    "iso:country":"BE",
    "sg:address":"Malibranstraat 27",
    "sg:city":"Elsene/ixelles",
    "sg:classifiers":[
        {
            "category":"Communications",
            "subcategory":"Television Station",
            "type":"Services"
        }
    ],
    "sg:phone":"+32 2 646 28 50",
    "sg:postcode":"1050",
    "sg:province":"Bruxelles-Capitale",
    "sg:tags":[
        "video",
        "audio",
        "verhuur"
    ],
    "wof:name":"Le Vid\u00c9o Plus",
    "wof:placetype":"venue"
},
  "geometry": {"coordinates":[4.3729457855,50.8294754028],"type":"Point"}
}