{
  "type": "Feature",
  "properties": {
    "addr:full":"Rue Fran\u00e7ois Vekemans 218 Bruxelles Bruxelles-Capitale 1120",
    "addr:housenumber":"218",
    "addr:postcode":"1120",
    "addr:street":"Rue Franc\u0327Ois Vekemans",
    "iso:country":"BE",
    "sg:address":"Rue Fran\u00e7ois Vekemans 218",
    "sg:city":"Bruxelles",
    "sg:classifiers":[
        {
            "category":"Professional",
            "subcategory":"Lawyer & Legal Services",
            "type":"Services"
        }
    ],
    "sg:phone":"+32 2 262 05 50",
    "sg:postcode":"1120",
    "sg:province":"Bruxelles-Capitale",
    "sg:tags":[
        "notary"
    ],
    "wof:name":"Knops H",
    "wof:placetype":"venue"
},
  "geometry": {"coordinates":[4.3833150864,50.8948364258],"type":"Point"}
}