{
  "type": "Feature",
  "properties": {
    "addr:full":"Louisegalerij 6 Elsene/ixelles Bruxelles-Capitale 1050",
    "addr:housenumber":"6",
    "addr:postcode":"1050",
    "addr:street":"Louisegalerij",
    "iso:country":"BE",
    "sg:address":"Louisegalerij 6",
    "sg:city":"Elsene/ixelles",
    "sg:classifiers":[
        {
            "category":"Shopping",
            "subcategory":"Clothing, Apparel, & Fashions",
            "type":"Retail Goods"
        }
    ],
    "sg:phone":"+32 2 511 09 39",
    "sg:postcode":"1050",
    "sg:province":"Bruxelles-Capitale",
    "sg:tags":[
        "ondergoed",
        "lingerie"
    ],
    "wof:name":"Airstream",
    "wof:placetype":"venue"
},
  "geometry": {"coordinates":[4.3578901291,50.8365783691],"type":"Point"}
}