{
  "type": "Feature",
  "properties": {
    "addr:full":"Rue Des Ecoles 60 Li\u00e8ge 1 (angleur) Li\u00e8ge 4031",
    "addr:housenumber":"60;1",
    "addr:postcode":"4031",
    "addr:street":"Rue Des Ecoles",
    "iso:country":"BE",
    "sg:address":"Rue Des Ecoles 60",
    "sg:city":"Li\u00e8ge 1 (angleur)",
    "sg:orig_category":"Non-Classified Establishments",
    "sg:phone":"+32 4 343 68 58",
    "sg:postcode":"4031",
    "sg:province":"Li\u00e8ge",
    "wof:name":"Fery F",
    "wof:placetype":"venue"
},
  "geometry": {"coordinates":[5.5815420151,50.61302948],"type":"Point"}
}