{
  "type": "Feature",
  "properties": {
    "iso:country":"BE",
    "sg:address":"Vaartkom 31 Box 301",
    "sg:city":"Leuven",
    "sg:classifiers":[
        {
            "category":"Arts & Performance",
            "subcategory":"Theater",
            "type":"Entertainment"
        }
    ],
    "sg:phone":"+32 16 23 15 98",
    "sg:postcode":"3000",
    "sg:province":"Vlaams-Brabant",
    "sg:tags":[
        "concert-halls",
        "theatre"
    ],
    "wof:name":"Amusements Theater Leuven",
    "wof:placetype":"venue"
},
  "geometry": {"coordinates":[4.7035150528,50.8877601624],"type":"Point"}
}