{
  "type": "Feature",
  "properties": {
    "iso:country":"BE",
    "sg:address":"Place Des Combattants 3",
    "sg:city":"Yvoir",
    "sg:orig_category":"Slagers",
    "sg:phone":"+32 82 61 11 45",
    "sg:postcode":"5530",
    "sg:province":"Namur",
    "wof:name":"Boucherie Richir",
    "wof:placetype":"venue"
},
  "geometry": {"coordinates":[4.8781189919,50.327293396],"type":"Point"}
}