{
  "type": "Feature",
  "properties": {
    "addr:full":"Hasseltsestraat 47 Diest Vlaams-Brabant 3290",
    "addr:housenumber":"47",
    "addr:postcode":"3290",
    "addr:street":"Hasseltsestraat",
    "iso:country":"BE",
    "sg:address":"Hasseltsestraat 47",
    "sg:city":"Diest",
    "sg:classifiers":[
        {
            "category":"Autos & Motor Vehicles",
            "subcategory":"Boat Sales",
            "type":"Retail Goods"
        }
    ],
    "sg:phone":"+32 13 33 31 70",
    "sg:postcode":"3290",
    "sg:province":"Vlaams-Brabant",
    "sg:tags":[
        "balloon"
    ],
    "wof:name":"Beauty Flower",
    "wof:placetype":"venue"
},
  "geometry": {"coordinates":[5.0534858704,50.9809455872],"type":"Point"}
}