{
  "type": "Feature",
  "properties": {
    "addr:full":"Belingstraat 15 Sint-truiden Limburg 3800",
    "addr:housenumber":"15",
    "addr:postcode":"3800",
    "addr:street":"Belingstraat",
    "iso:country":"BE",
    "sg:address":"Belingstraat 15",
    "sg:city":"Sint-truiden",
    "sg:orig_category":"M\u00e9decins and sp\u00e9cialistes",
    "sg:phone":"+32 11 69 15 77",
    "sg:postcode":"3800",
    "sg:province":"Limburg",
    "wof:name":"Daniel Nickmans",
    "wof:placetype":"venue"
},
  "geometry": {"coordinates":[5.2164411545,50.793258667],"type":"Point"}
}