{
  "type": "Feature",
  "properties": {
    "iso:country":"BE",
    "sg:address":"Berlaarsestraat 24",
    "sg:city":"Lier",
    "sg:classifiers":[
        {
            "category":"Personal",
            "type":"Services"
        }
    ],
    "sg:phone":"+32 3 491 84 90",
    "sg:postcode":"2500",
    "sg:province":"Antwerpen",
    "sg:tags":[
        "party",
        "planning"
    ],
    "wof:name":"Moriaen (de)",
    "wof:placetype":"venue"
},
  "geometry": {"coordinates":[4.5761461258,51.1296920776],"type":"Point"}
}