{
  "type": "Feature",
  "properties": {
    "iso:country":"BE",
    "sg:address":"Koning Albertplein 5",
    "sg:city":"De Panne",
    "sg:classifiers":[
        {
            "category":"Real Estate",
            "subcategory":"Real Estate Services",
            "type":"Services"
        }
    ],
    "sg:phone":"+32 58 41 50 23",
    "sg:postcode":"8660",
    "sg:province":"West-Vlaanderen",
    "wof:name":"Grey Bvba",
    "wof:placetype":"venue"
},
  "geometry": {"coordinates":[2.5894370079,51.1020240784],"type":"Point"}
}