{
  "type": "Feature",
  "properties": {
    "iso:country":"BE",
    "sg:address":"Kerkhofblommenstraat 4",
    "sg:city":"Staden",
    "sg:orig_category":"M\u00e9decins and sp\u00e9cialistes",
    "sg:phone":"+32 51 70 27 05",
    "sg:postcode":"8840",
    "sg:province":"West-Vlaanderen",
    "wof:name":"Patrick Vandewalle",
    "wof:placetype":"venue"
},
  "geometry": {"coordinates":[3.0197880268,50.9715042114],"type":"Point"}
}