{
  "type": "Feature",
  "properties": {
    "addr:full":"Dorpstraat 13 Antwerpen Antwerpen 2180",
    "addr:housenumber":"13",
    "addr:postcode":"2180",
    "addr:street":"Dorpstraat",
    "iso:country":"BE",
    "sg:address":"Dorpstraat 13",
    "sg:city":"Antwerpen",
    "sg:orig_category":"Banken and kredietinstellingen",
    "sg:phone":"+32 3 541 07 01",
    "sg:postcode":"2180",
    "sg:province":"Antwerpen",
    "wof:name":"Groep Argenta",
    "wof:placetype":"venue"
},
  "geometry": {"coordinates":[4.4182572365,51.2778625488],"type":"Point"}
}