{
  "type": "Feature",
  "properties": {
    "addr:full":"De Fierlantstraat 9 Zaventem (sterrebeek) Vlaams-Brabant 1933",
    "addr:housenumber":"9",
    "addr:postcode":"1933",
    "addr:street":"De Fierlantstraat",
    "iso:country":"BE",
    "sg:address":"De Fierlantstraat 9",
    "sg:city":"Zaventem (sterrebeek)",
    "sg:classifiers":[
        {
            "category":"Social Services",
            "subcategory":"Job Training",
            "type":"Services"
        }
    ],
    "sg:phone":"+32 2 731 26 97",
    "sg:postcode":"1933",
    "sg:province":"Vlaams-Brabant",
    "sg:tags":[
        "interpreter"
    ],
    "wof:name":"Dechamps A",
    "wof:placetype":"venue"
},
  "geometry": {"coordinates":[4.5046658516,50.8518066406],"type":"Point"}
}