{
  "type": "Feature",
  "properties": {
    "iso:country":"BE",
    "sg:address":"Ganzenbollaan 30",
    "sg:city":"Kontich",
    "sg:classifiers":[
        {
            "category":"Government",
            "subcategory":"Fire Station",
            "type":"Public Place"
        }
    ],
    "sg:phone":"+32 3 830 31 91",
    "sg:postcode":"2550",
    "sg:province":"Antwerpen",
    "sg:tags":[
        "supraregional",
        "plant",
        "installation",
        "heating"
    ],
    "wof:name":"Abati Nv",
    "wof:placetype":"venue"
},
  "geometry": {"coordinates":[4.3816761971,51.1716346741],"type":"Point"}
}