{
  "type": "Feature",
  "properties": {
    "addr:full":"Durmelaan 90 Lokeren Oost-Vlaanderen 9160",
    "addr:housenumber":"90",
    "addr:postcode":"9160",
    "addr:street":"Durmelaan",
    "iso:country":"BE",
    "sg:address":"Durmelaan 90",
    "sg:city":"Lokeren",
    "sg:orig_category":"Advocaten and juridische adviseurs",
    "sg:phone":"+32 9 348 61 93",
    "sg:postcode":"9160",
    "sg:province":"Oost-Vlaanderen",
    "wof:name":"A. Boeykens",
    "wof:placetype":"venue"
},
  "geometry": {"coordinates":[3.9816360474,51.1044311523],"type":"Point"}
}