{
  "type": "Feature",
  "properties": {
    "addr:full":"Chauss\u00c9e De Willemeau 149 Tournai Hainaut 7500",
    "addr:housenumber":"149",
    "addr:postcode":"7500",
    "addr:street":"Chausse\u0301E De Willemeau",
    "iso:country":"BE",
    "sg:address":"Chauss\u00c9e De Willemeau 149",
    "sg:city":"Tournai",
    "sg:orig_category":"Plomberie, chauffage and installations sanitaires. Charpentes and couvertures",
    "sg:phone":"+32 69 64 85 39",
    "sg:postcode":"7500",
    "sg:province":"Hainaut",
    "wof:name":"Francis Dauchy",
    "wof:placetype":"venue"
},
  "geometry": {"coordinates":[3.378084898,50.5955810547],"type":"Point"}
}