{
  "type": "Feature",
  "properties": {
    "addr:full":"Parc Industriel De La Vall\u00c9e Du Hain 37 Wauthier-braine Brabant Wallon 1440",
    "addr:housenumber":"37",
    "addr:postcode":"1440",
    "addr:street":"Parc Industriel De La Valle\u0301E Du Hain",
    "iso:country":"BE",
    "sg:address":"Parc Industriel De La Vall\u00c9e Du Hain 37",
    "sg:city":"Wauthier-braine",
    "sg:orig_category":"Non-Classified Establishments",
    "sg:phone":"+32 2 367 14 11",
    "sg:postcode":"1440",
    "sg:province":"Brabant Wallon",
    "wof:name":"D'ieteren Sport",
    "wof:placetype":"venue"
},
  "geometry": {"coordinates":[4.2687120438,50.6824455261],"type":"Point"}
}