{
  "type": "Feature",
  "properties": {
    "iso:country":"BE",
    "sg:address":"Rue Des Clairetchamps 13",
    "sg:city":"Erez\u00e9e",
    "sg:classifiers":[
        {
            "category":"Travel",
            "subcategory":"Resort",
            "type":"Entertainment"
        }
    ],
    "sg:phone":"+32 86 47 73 93",
    "sg:postcode":"6997",
    "sg:province":"Luxembourg",
    "sg:tags":[
        "vacation"
    ],
    "wof:name":"Ecole De Clerheid",
    "wof:placetype":"venue"
},
  "geometry": {"coordinates":[5.5950450897,50.2961425781],"type":"Point"}
}