{
  "type": "Feature",
  "properties": {
    "iso:country":"BE",
    "sg:address":"Rue Felix Close 59",
    "sg:city":"Theux",
    "sg:orig_category":"Entretien and r\u00e9parations de voitures",
    "sg:phone":"+32 87 22 75 05",
    "sg:postcode":"4910",
    "sg:province":"Li\u00e8ge",
    "wof:name":"Carrosserie Hasard L & Fils",
    "wof:placetype":"venue"
},
  "geometry": {"coordinates":[5.8130488396,50.5356216431],"type":"Point"}
}