{
  "type": "Feature",
  "properties": {
    "iso:country":"BE",
    "sg:address":"Rechtestraat 58",
    "sg:city":"Lille",
    "sg:orig_category":"Mat\u00e9riel de contr\u00f4le des processus industriels Fab. Installation \u00e9lectrique industrielle",
    "sg:phone":"+32 14 88 22 88",
    "sg:postcode":"2275",
    "sg:province":"Antwerpen",
    "wof:name":"Mesens Electro",
    "wof:placetype":"venue"
},
  "geometry": {"coordinates":[4.8234667778,51.2411994934],"type":"Point"}
}