{
  "type": "Feature",
  "properties": {
    "iso:country":"BE",
    "sg:address":"Dr\u00e8ve Richelle 158c",
    "sg:city":"Waterloo",
    "sg:classifiers":[
        {
            "category":"Professional",
            "subcategory":"Art Services",
            "type":"Services"
        }
    ],
    "sg:phone":"+32 2 353 02 65",
    "sg:postcode":"1410",
    "sg:province":"Brabant Wallon",
    "sg:tags":[
        "photographer"
    ],
    "wof:name":"Espace Color",
    "wof:placetype":"venue"
},
  "geometry": {"coordinates":[4.4168481827,50.704498291],"type":"Point"}
}