{
  "type": "Feature",
  "properties": {
    "addr:full":"Nieuwe Kouterstraat 21 Bornem Antwerpen 2880",
    "addr:housenumber":"21",
    "addr:postcode":"2880",
    "addr:street":"Nieuwe Kouterstraat",
    "iso:country":"BE",
    "sg:address":"Nieuwe Kouterstraat 21",
    "sg:city":"Bornem",
    "sg:classifiers":[
        {
            "category":"Retail",
            "subcategory":"Animal Services",
            "type":"Services"
        }
    ],
    "sg:phone":"+32 3 889 06 06",
    "sg:postcode":"2880",
    "sg:province":"Antwerpen",
    "sg:tags":[
        "grooming",
        "-",
        "dog"
    ],
    "wof:name":"Poedeltje ('t)",
    "wof:placetype":"venue"
},
  "geometry": {"coordinates":[4.2388138771,51.098739624],"type":"Point"}
}