{
  "type": "Feature",
  "properties": {
    "addr:full":"Monnikenhofstraat 285 Antwerpen Antwerpen 2040",
    "addr:housenumber":"285",
    "addr:postcode":"2040",
    "addr:street":"Monnikenhofstraat",
    "iso:country":"BE",
    "sg:address":"Monnikenhofstraat 285",
    "sg:city":"Antwerpen",
    "sg:classifiers":[
        {
            "category":"Professional",
            "type":"Services"
        }
    ],
    "sg:phone":"+32 3 568 09 68",
    "sg:postcode":"2040",
    "sg:province":"Antwerpen",
    "sg:tags":[
        "entertainer"
    ],
    "wof:name":"Cirkusvereniging Rio",
    "wof:placetype":"venue"
},
  "geometry": {"coordinates":[4.3317799568,51.3528785706],"type":"Point"}
}