{
  "type": "Feature",
  "properties": {
    "addr:full":"Tervuursesteenweg 253 Leuven (heverlee) Vlaams-Brabant 3001",
    "addr:housenumber":"253",
    "addr:postcode":"3001",
    "addr:street":"Tervuursesteenweg",
    "iso:country":"BE",
    "sg:address":"Tervuursesteenweg 253",
    "sg:city":"Leuven (heverlee)",
    "sg:classifiers":[
        {
            "category":"Health Services",
            "subcategory":"Health Practitioner",
            "type":"Services"
        }
    ],
    "sg:phone":"+32 16 23 69 69",
    "sg:postcode":"3001",
    "sg:province":"Vlaams-Brabant",
    "sg:tags":[
        "physiotherapist"
    ],
    "wof:name":"Van Cleemput Elisabeth",
    "wof:placetype":"venue"
},
  "geometry": {"coordinates":[4.671831131,50.8741874695],"type":"Point"}
}