{
  "type": "Feature",
  "properties": {
    "iso:country":"BE",
    "sg:address":"Hoogstraat 46",
    "sg:city":"Sint-gillis-waas",
    "sg:orig_category":"Telecommunicatieapparaten Telecommunicatiesystemen",
    "sg:phone":"+32 3 777 67 80",
    "sg:postcode":"9170",
    "sg:province":"Oost-Vlaanderen",
    "wof:name":"Audility Europe",
    "wof:placetype":"venue"
},
  "geometry": {"coordinates":[4.11729002,51.1910514832],"type":"Point"}
}