{
  "type": "Feature",
  "properties": {
    "addr:full":"Meentakstraat 2a Meulebeke West-Vlaanderen 8760",
    "addr:housenumber":"2a",
    "addr:postcode":"8760",
    "addr:street":"Meentakstraat",
    "iso:country":"BE",
    "sg:address":"Meentakstraat 2a",
    "sg:city":"Meulebeke",
    "sg:classifiers":[
        {
            "category":"Shopping",
            "subcategory":"Discount & Variety Stores",
            "type":"Retail Goods"
        }
    ],
    "sg:phone":"+32 51 48 89 41",
    "sg:postcode":"8760",
    "sg:province":"West-Vlaanderen",
    "sg:tags":[
        "fur",
        "-",
        "storage"
    ],
    "wof:name":"Parmentier",
    "wof:placetype":"venue"
},
  "geometry": {"coordinates":[3.2999830246,50.9577102661],"type":"Point"}
}