{
  "type": "Feature",
  "properties": {
    "addr:full":"Rue Picot 12 Anderlues Hainaut 6150",
    "addr:housenumber":"12",
    "addr:postcode":"6150",
    "addr:street":"Rue Picot",
    "iso:country":"BE",
    "sg:address":"Rue Picot 12",
    "sg:city":"Anderlues",
    "sg:classifiers":[
        {
            "category":"Insurance",
            "subcategory":"Life Insurance",
            "type":"Services"
        }
    ],
    "sg:phone":"+32 71 52 61 67",
    "sg:postcode":"6150",
    "sg:province":"Hainaut",
    "sg:tags":[
        "assurance"
    ],
    "wof:name":"Impras",
    "wof:placetype":"venue"
},
  "geometry": {"coordinates":[4.265127182,50.4138374329],"type":"Point"}
}