{
  "type": "Feature",
  "properties": {
    "addr:full":"Rue Junius Massau 19 Charleroi Hainaut 6041",
    "addr:housenumber":"19",
    "addr:postcode":"6041",
    "addr:street":"Rue Junius Massau;Hainaut",
    "iso:country":"BE",
    "sg:address":"Rue Junius Massau 19",
    "sg:city":"Charleroi",
    "sg:orig_category":"Herstelling and restauratie van meubelen Meubelzaken, woning- and keukeninrichting",
    "sg:phone":"+32 71 35 83 87",
    "sg:postcode":"6041",
    "sg:province":"Hainaut",
    "wof:name":"Thierry Schollaert",
    "wof:placetype":"venue"
},
  "geometry": {"coordinates":[4.4279909134,50.4655418396],"type":"Point"}
}