{
  "type": "Feature",
  "properties": {
    "addr:full":"Kanadezenlaan 65 Kalmthout Antwerpen 2920",
    "addr:housenumber":"65",
    "addr:postcode":"2920",
    "addr:street":"Kanadezenlaan",
    "iso:country":"BE",
    "sg:address":"Kanadezenlaan 65",
    "sg:city":"Kalmthout",
    "sg:classifiers":[
        {
            "category":"Building & Trades",
            "subcategory":"Landscaping Services",
            "type":"Services"
        }
    ],
    "sg:phone":"+32 3 666 82 82",
    "sg:postcode":"2920",
    "sg:province":"Antwerpen",
    "sg:tags":[
        "gardening",
        "garden",
        "maintenance"
    ],
    "wof:name":"Callens H",
    "wof:placetype":"venue"
},
  "geometry": {"coordinates":[4.4519882202,51.362071991],"type":"Point"}
}