{
  "type": "Feature",
  "properties": {
    "addr:full":"Poperingestraat 27ba Heuvelland West-Vlaanderen 8954",
    "addr:housenumber":"27ba",
    "addr:postcode":"8954",
    "addr:street":"Poperingestraat",
    "iso:country":"BE",
    "sg:address":"Poperingestraat 27ba",
    "sg:city":"Heuvelland",
    "sg:orig_category":"Rundveehouders",
    "sg:phone":"+32 57 44 52 96",
    "sg:postcode":"8954",
    "sg:province":"West-Vlaanderen",
    "wof:name":"Johan Verdonck",
    "wof:placetype":"venue"
},
  "geometry": {"coordinates":[2.7313148975,50.8226890564],"type":"Point"}
}