{
  "type": "Feature",
  "properties": {
    "iso:country":"BE",
    "sg:address":"Rubensstraat 138",
    "sg:city":"Turnhout",
    "sg:classifiers":[
        {
            "category":"Communications",
            "subcategory":"Film & Video Production",
            "type":"Services"
        }
    ],
    "sg:phone":"+32 14 41 32 35",
    "sg:postcode":"2300",
    "sg:province":"Antwerpen",
    "sg:tags":[
        "hiring",
        "-"
    ],
    "wof:name":"Bellvideo",
    "wof:placetype":"venue"
},
  "geometry": {"coordinates":[4.9438328743,51.3148155212],"type":"Point"}
}