{
  "type": "Feature",
  "properties": {
    "iso:country":"BE",
    "sg:address":"Vriendschapsstraat 73",
    "sg:city":"Overijse",
    "sg:classifiers":[
        {
            "category":"Recreation",
            "type":"Entertainment"
        }
    ],
    "sg:phone":"+32 2 687 87 00",
    "sg:postcode":"3090",
    "sg:province":"Vlaams-Brabant",
    "sg:tags":[
        "diver",
        "amusement"
    ],
    "wof:name":"Promuzika Likala-moto",
    "wof:placetype":"venue"
},
  "geometry": {"coordinates":[4.5105199814,50.7768707275],"type":"Point"}
}