{
  "type": "Feature",
  "properties": {
    "iso:country":"BE",
    "sg:address":"Gentstraat 187",
    "sg:city":"Gent",
    "sg:orig_category":"Verplichte sociale verzekeringen",
    "sg:phone":"+32 9 251 52 49",
    "sg:postcode":"9041",
    "sg:province":"Oost-Vlaanderen",
    "wof:name":"Bond Moyson",
    "wof:placetype":"venue"
},
  "geometry": {"coordinates":[3.7579550743,51.0932235718],"type":"Point"}
}