{
  "type": "Feature",
  "properties": {
    "addr:full":"Rue Emile Cuvelier 12 Namur Namur 5000",
    "addr:housenumber":"12",
    "addr:postcode":"5000",
    "addr:street":"Rue Emile Cuvelier",
    "iso:country":"BE",
    "sg:address":"Rue Emile Cuvelier 12",
    "sg:city":"Namur",
    "sg:classifiers":[
        {
            "category":"Banks & Credit Unions",
            "subcategory":"Investment Brokerage",
            "type":"Services"
        }
    ],
    "sg:phone":"+32 81 23 14 67",
    "sg:postcode":"5000",
    "sg:province":"Namur",
    "sg:tags":[
        "jean",
        "casual",
        "wear"
    ],
    "wof:name":"Zapi Jeans",
    "wof:placetype":"venue"
},
  "geometry": {"coordinates":[4.8670139313,50.4644546509],"type":"Point"}
}