{
  "type": "Feature",
  "properties": {
    "iso:country":"BE",
    "sg:address":"Olmenweg 3-5",
    "sg:city":"Maaseik",
    "sg:classifiers":[
        {
            "category":"Autos & Motor Vehicles",
            "subcategory":"Automobile Sales",
            "type":"Retail Goods"
        }
    ],
    "sg:phone":"+32 89 56 49 55",
    "sg:postcode":"3680",
    "sg:province":"Limburg",
    "sg:tags":[
        "equipment",
        "industrial",
        "transport"
    ],
    "wof:name":"Atm Aanhangwagenfabriek Nv",
    "wof:placetype":"venue"
},
  "geometry": {"coordinates":[5.7831168175,51.1016044617],"type":"Point"}
}