{
  "type": "Feature",
  "properties": {
    "iso:country":"BE",
    "sg:address":"Beauregard 0",
    "sg:city":"Rochefort",
    "sg:orig_category":"Rundveehouders Verzekeringsmakelaars and experts",
    "sg:phone":"+32 84 21 11 62",
    "sg:postcode":"5580",
    "sg:province":"Namur",
    "wof:name":"Jean-fran\u00c7ois Everard De Harzir",
    "wof:placetype":"venue"
},
  "geometry": {"coordinates":[5.2235188484,50.1573982239],"type":"Point"}
}