{
  "type": "Feature",
  "properties": {
    "iso:country":"BE",
    "sg:address":"Rue Du Poncha 19",
    "sg:city":"Walhain",
    "sg:orig_category":"M\u00e9decins and sp\u00e9cialistes",
    "sg:phone":"+32 10 65 67 46",
    "sg:postcode":"1457",
    "sg:province":"Brabant Wallon",
    "wof:name":"Anne Puttemans",
    "wof:placetype":"venue"
},
  "geometry": {"coordinates":[4.6688051224,50.6359977722],"type":"Point"}
}