{
  "type": "Feature",
  "properties": {
    "iso:country":"BE",
    "sg:address":"Thonissenlaan 40",
    "sg:city":"Hasselt",
    "sg:classifiers":[
        {
            "category":"Professional",
            "subcategory":"Management & Consulting",
            "type":"Services"
        }
    ],
    "sg:phone":"+32 11 24 98 62",
    "sg:postcode":"3500",
    "sg:province":"Limburg",
    "sg:tags":[
        "consultant",
        "law"
    ],
    "wof:name":"De Voorzorg Federatie Der Zelfstandigen",
    "wof:placetype":"venue"
},
  "geometry": {"coordinates":[5.335267067,50.9329147339],"type":"Point"}
}