{
  "type": "Feature",
  "properties": {
    "addr:full":"Lierseweg 73 Herentals Antwerpen 2200",
    "addr:housenumber":"73",
    "addr:postcode":"2200",
    "addr:street":"Lierseweg",
    "iso:country":"BE",
    "sg:address":"Lierseweg 73",
    "sg:city":"Herentals",
    "sg:orig_category":"Royal Canin",
    "sg:phone":"+32 14 21 92 00",
    "sg:postcode":"2200",
    "sg:province":"Antwerpen",
    "wof:name":"Dierenparadijs",
    "wof:placetype":"venue"
},
  "geometry": {"coordinates":[4.8262081146,51.1759223938],"type":"Point"}
}