{
  "type": "Feature",
  "properties": {
    "addr:full":"Rue De France 85 Sint-gillis Bruxelles-Capitale 1060",
    "addr:housenumber":"85",
    "addr:postcode":"1060",
    "addr:street":"Rue De France",
    "iso:country":"BE",
    "sg:address":"Rue De France 85",
    "sg:city":"Sint-gillis",
    "sg:orig_category":"Parfumeries",
    "sg:phone":"+32 2 527 88 09",
    "sg:postcode":"1060",
    "sg:province":"Bruxelles-Capitale",
    "wof:name":"The Body Shop",
    "wof:placetype":"venue"
},
  "geometry": {"coordinates":[4.3331050873,50.8352851868],"type":"Point"}
}