{
  "type": "Feature",
  "properties": {
    "iso:country":"BE",
    "sg:address":"Alsembergsesteenweg 43",
    "sg:city":"Linkebeek",
    "sg:orig_category":"Rusthuizen and serviceflats",
    "sg:phone":"+32 2 377 08 19",
    "sg:postcode":"1630",
    "sg:province":"Vlaams-Brabant",
    "wof:name":"Rusthuis Avondvrede",
    "wof:placetype":"venue"
},
  "geometry": {"coordinates":[4.3260569572,50.7762336731],"type":"Point"}
}