{
  "type": "Feature",
  "properties": {
    "addr:full":"Lange Lozanastraat 188 Antwerpen Antwerpen 2018",
    "addr:housenumber":"188",
    "addr:postcode":"2018",
    "addr:street":"Lange Lozanastraat",
    "iso:country":"BE",
    "sg:address":"Lange Lozanastraat 188",
    "sg:city":"Antwerpen",
    "sg:classifiers":[
        {
            "category":"Professional",
            "subcategory":"Computer Services",
            "type":"Services"
        }
    ],
    "sg:phone":"+32 3 248 50 80",
    "sg:postcode":"2018",
    "sg:province":"Antwerpen",
    "sg:tags":[
        "-",
        "processing",
        "data"
    ],
    "wof:name":"Antwerp Cd Center Bvba",
    "wof:placetype":"venue"
},
  "geometry": {"coordinates":[4.4060459137,51.2011375427],"type":"Point"}
}