{
  "type": "Feature",
  "properties": {
    "iso:country":"BE",
    "sg:address":"Rue Des Carmes 17",
    "sg:city":"Vis\u00e9",
    "sg:classifiers":[
        {
            "category":"Health Services",
            "subcategory":"Health Practitioner",
            "type":"Services"
        }
    ],
    "sg:phone":"+32 4 379 19 55",
    "sg:postcode":"4600",
    "sg:province":"Li\u00e8ge",
    "sg:tags":[
        "physiotherapist"
    ],
    "wof:name":"Warnotte Christine",
    "wof:placetype":"venue"
},
  "geometry": {"coordinates":[5.6870098114,50.7405509949],"type":"Point"}
}