{
  "type": "Feature",
  "properties": {
    "addr:full":"Rue Ernest Allard 7 Bruxelles Bruxelles-Capitale 1000",
    "addr:housenumber":"7",
    "addr:postcode":"1000",
    "addr:street":"Rue Ernest Allard",
    "iso:country":"BE",
    "sg:address":"Rue Ernest Allard 7",
    "sg:city":"Bruxelles",
    "sg:classifiers":[
        {
            "category":"Shopping",
            "subcategory":"Antiques",
            "type":"Retail Goods"
        }
    ],
    "sg:phone":"+32 2 514 25 41",
    "sg:postcode":"1000",
    "sg:province":"Bruxelles-Capitale",
    "wof:name":"Dominique",
    "wof:placetype":"venue"
},
  "geometry": {"coordinates":[4.3547029495,50.8403892517],"type":"Point"}
}