{
  "type": "Feature",
  "properties": {
    "iso:country":"BE",
    "sg:address":"Hollebeek 23 Bb",
    "sg:city":"Temse",
    "sg:orig_category":"Gespecialiseerde residenti\u00eble bouw Woningbouw",
    "sg:phone":"+32 3 771 38 27",
    "sg:postcode":"9140",
    "sg:province":"Oost-Vlaanderen",
    "wof:name":"De Loose B.",
    "wof:placetype":"venue"
},
  "geometry": {"coordinates":[4.2143149376,51.1247558594],"type":"Point"}
}