{
  "type": "Feature",
  "properties": {
    "iso:country":"BE",
    "sg:address":"Liefdestraat 1",
    "sg:city":"Tienen",
    "sg:classifiers":[
        {
            "category":"Social Services",
            "type":"Services"
        }
    ],
    "sg:phone":"+32 16 81 90 67",
    "sg:postcode":"3300",
    "sg:province":"Vlaams-Brabant",
    "wof:name":"Hestia Vzw",
    "wof:placetype":"venue"
},
  "geometry": {"coordinates":[4.9431099892,50.8082618713],"type":"Point"}
}