{
  "type": "Feature",
  "properties": {
    "iso:country":"BE",
    "sg:address":"Steenweg Op Leopoldsburg 8",
    "sg:city":"Balen",
    "sg:orig_category":"Herstellingen and onderhoud van auto's Voertuigen",
    "sg:phone":"+32 14 81 28 07",
    "sg:postcode":"2490",
    "sg:province":"Antwerpen",
    "wof:name":"Jozef Geboers",
    "wof:placetype":"venue"
},
  "geometry": {"coordinates":[5.2379307747,51.1353340149],"type":"Point"}
}