{
  "type": "Feature",
  "properties": {
    "addr:full":"Dumontstraat 33 Hoegaarden Vlaams-Brabant 3320",
    "addr:housenumber":"33",
    "addr:postcode":"3320",
    "addr:street":"Dumontstraat",
    "iso:country":"BE",
    "sg:address":"Dumontstraat 33",
    "sg:city":"Hoegaarden",
    "sg:orig_category":"Textiles. Eclairage et \u00e9quipements du foyer",
    "sg:phone":"+32 16 76 65 66",
    "sg:postcode":"3320",
    "sg:province":"Vlaams-Brabant",
    "wof:name":"Gordijnenhuis Marina",
    "wof:placetype":"venue"
},
  "geometry": {"coordinates":[4.8875842094,50.7760162354],"type":"Point"}
}