{
  "type": "Feature",
  "properties": {
    "addr:full":"August Nobelsstraat 9 Sint-niklaas Oost-Vlaanderen 9100",
    "addr:housenumber":"9",
    "addr:postcode":"9100",
    "addr:street":"Nobelsstraat",
    "iso:country":"BE",
    "sg:address":"August Nobelsstraat 9",
    "sg:city":"Sint-niklaas",
    "sg:classifiers":[
        {
            "category":"Professional",
            "subcategory":"Printing & Photocopies",
            "type":"Services"
        }
    ],
    "sg:phone":"+32 3 776 07 83",
    "sg:postcode":"9100",
    "sg:province":"Oost-Vlaanderen",
    "sg:tags":[
        "trophy",
        "medal"
    ],
    "wof:name":"Bonne & Verbeke Bvba",
    "wof:placetype":"venue"
},
  "geometry": {"coordinates":[4.1453781128,51.1609191895],"type":"Point"}
}