{
  "type": "Feature",
  "properties": {
    "addr:full":"Brekelen 61 Wuustwezel Antwerpen 2990",
    "addr:housenumber":"61",
    "addr:postcode":"2990",
    "addr:street":"Brekelen",
    "iso:country":"BE",
    "sg:address":"Brekelen 61",
    "sg:city":"Wuustwezel",
    "sg:orig_category":"Eleveurs and marchands de porcs. Eleveurs de bovins",
    "sg:phone":"+32 3 669 73 28",
    "sg:postcode":"2990",
    "sg:province":"Antwerpen",
    "wof:name":"Anthonissen Jan & Rudy",
    "wof:placetype":"venue"
},
  "geometry": {"coordinates":[4.5741219521,51.3854751587],"type":"Point"}
}