{
  "type": "Feature",
  "properties": {
    "iso:country":"BE",
    "sg:address":"Bevingen-centrum 111",
    "sg:city":"Sint-truiden",
    "sg:orig_category":"Fruitteelt",
    "sg:phone":"+32 11 69 51 97",
    "sg:postcode":"3800",
    "sg:province":"Limburg",
    "wof:name":"Koen Biets",
    "wof:placetype":"venue"
},
  "geometry": {"coordinates":[5.1936469078,50.837310791],"type":"Point"}
}