{
  "type": "Feature",
  "properties": {
    "addr:full":"Guldensporenlaan 15 Heusden-zolder (zolder) Limburg 3550",
    "addr:housenumber":"15",
    "addr:postcode":"3550",
    "addr:street":"Guldensporenlaan",
    "iso:country":"BE",
    "sg:address":"Guldensporenlaan 15",
    "sg:city":"Heusden-zolder (zolder)",
    "sg:classifiers":[
        {
            "category":"Building & Trades",
            "subcategory":"Landscaping Services",
            "type":"Services"
        }
    ],
    "sg:phone":"+32 11 53 72 63",
    "sg:postcode":"3550",
    "sg:province":"Limburg",
    "sg:tags":[
        "gardening",
        "garden",
        "maintenance"
    ],
    "wof:name":"Beerten Peter Tuinontwerpen",
    "wof:placetype":"venue"
},
  "geometry": {"coordinates":[5.2900500298,51.0081710815],"type":"Point"}
}