{
  "type": "Feature",
  "properties": {
    "addr:full":"Avenue Roi Albert 640 Mons (jemappes) Hainaut 7012",
    "addr:housenumber":"640",
    "addr:postcode":"7012",
    "addr:street":"Avenue Roi Albert",
    "iso:country":"BE",
    "sg:address":"Avenue Roi Albert 640",
    "sg:city":"Mons (jemappes)",
    "sg:classifiers":[
        {
            "category":"Retail",
            "subcategory":"Auto Repair",
            "type":"Services"
        }
    ],
    "sg:phone":"+32 65 82 56 67",
    "sg:postcode":"7012",
    "sg:province":"Hainaut",
    "sg:tags":[
        "garage"
    ],
    "wof:name":"Dehiles",
    "wof:placetype":"venue"
},
  "geometry": {"coordinates":[3.8894600868,50.4481964111],"type":"Point"}
}