{
  "type": "Feature",
  "properties": {
    "addr:full":"Werkhuizenkaai 16 Brussel (brussel) Bruxelles-Capitale 1000",
    "addr:housenumber":"16",
    "addr:postcode":"1000",
    "addr:street":"Werkhuizenkaai",
    "iso:country":"BE",
    "sg:address":"Werkhuizenkaai 16",
    "sg:city":"Brussel (brussel)",
    "sg:orig_category":"Elektriciteitsproductie and -distributie",
    "sg:phone":"+32 2 274 31 11",
    "sg:postcode":"1000",
    "sg:province":"Bruxelles-Capitale",
    "wof:name":"Electrabel",
    "wof:placetype":"venue"
},
  "geometry": {"coordinates":[4.3628602028,50.8746185303],"type":"Point"}
}