{
  "type": "Feature",
  "properties": {
    "iso:country":"BE",
    "sg:address":"A. Blommaertstraat 11",
    "sg:city":"Wuustwezel",
    "sg:orig_category":"Herstellingen motorfietsen Motorfietsen",
    "sg:phone":"+32 3 669 69 49",
    "sg:postcode":"2990",
    "sg:province":"Antwerpen",
    "wof:name":"Motorhandel Jos Vermeeren",
    "wof:placetype":"venue"
},
  "geometry": {"coordinates":[4.5992050171,51.3940467834],"type":"Point"}
}