{
  "type": "Feature",
  "properties": {
    "addr:full":"Diestersteenweg 114 Diest (kaggevinne) Vlaams-Brabant 3293",
    "addr:housenumber":"114",
    "addr:postcode":"3293",
    "addr:street":"Diestersteenweg",
    "iso:country":"BE",
    "sg:address":"Diestersteenweg 114",
    "sg:city":"Diest (kaggevinne)",
    "sg:classifiers":[
        {
            "category":"Health Services",
            "subcategory":"Doctor",
            "type":"Services"
        }
    ],
    "sg:phone":"+32 13 33 60 98",
    "sg:postcode":"3293",
    "sg:province":"Vlaams-Brabant",
    "sg:tags":[
        "medicinephysicians",
        "surgeon"
    ],
    "wof:name":"Marchal A",
    "wof:placetype":"venue"
},
  "geometry": {"coordinates":[5.0367951393,50.9798164368],"type":"Point"}
}