{
  "type": "Feature",
  "properties": {
    "addr:full":"Rue Des Raines 119 Verviers Li\u00e8ge 4800",
    "addr:housenumber":"119",
    "addr:postcode":"4800",
    "addr:street":"Rue Des Raines",
    "iso:country":"BE",
    "sg:address":"Rue Des Raines 119",
    "sg:city":"Verviers",
    "sg:classifiers":[
        {
            "category":"Food & Beverages",
            "subcategory":"Groceries & Convenience Stores",
            "type":"Retail Goods"
        }
    ],
    "sg:phone":"+32 87 66 27 80",
    "sg:postcode":"4800",
    "sg:province":"Li\u00e8ge",
    "sg:tags":[
        "grocer"
    ],
    "wof:name":"Malaika Scrl",
    "wof:placetype":"venue"
},
  "geometry": {"coordinates":[5.8654880524,50.5944328308],"type":"Point"}
}