{
  "type": "Feature",
  "properties": {
    "addr:full":"Quai D'arona 22 Huy Li\u00e8ge 4500",
    "addr:housenumber":"22",
    "addr:postcode":"4500",
    "addr:street":"Quai D'Arona",
    "iso:country":"BE",
    "sg:address":"Quai D'arona 22",
    "sg:city":"Huy",
    "sg:classifiers":[
        {
            "category":"Fast Food",
            "type":"Food & Drink"
        }
    ],
    "sg:phone":"+32 85 21 65 40",
    "sg:postcode":"4500",
    "sg:province":"Li\u00e8ge",
    "sg:tags":[
        "fried",
        "stand",
        "potato"
    ],
    "wof:name":"Chalet (le)",
    "wof:placetype":"venue"
},
  "geometry": {"coordinates":[5.2558231354,50.5346488953],"type":"Point"}
}