{
  "type": "Feature",
  "properties": {
    "iso:country":"BE",
    "sg:address":"Rue Grande 15",
    "sg:city":"Dinant",
    "sg:classifiers":[
        {
            "category":"Building & Trades",
            "subcategory":"Equipment Rental",
            "type":"Services"
        }
    ],
    "sg:phone":"+32 82 22 47 44",
    "sg:postcode":"5500",
    "sg:province":"Namur",
    "sg:tags":[
        "use",
        "apparatus",
        "tool",
        "-",
        "professional",
        "machines"
    ],
    "wof:name":"Christy Location",
    "wof:placetype":"venue"
},
  "geometry": {"coordinates":[4.9159388542,50.2565841675],"type":"Point"}
}