{
  "type": "Feature",
  "properties": {
    "addr:full":"Isabellaplein 7 Scherpenheuvel-zichem Vlaams-Brabant 3270",
    "addr:housenumber":"7",
    "addr:postcode":"3270",
    "addr:street":"Isabellaplein",
    "iso:country":"BE",
    "sg:address":"Isabellaplein 7",
    "sg:city":"Scherpenheuvel-zichem",
    "sg:orig_category":"Dameskledingzaken",
    "sg:phone":"+32 13 77 82 55",
    "sg:postcode":"3270",
    "sg:province":"Vlaams-Brabant",
    "wof:name":"De Gouden Leeuw",
    "wof:placetype":"venue"
},
  "geometry": {"coordinates":[4.9790902138,50.9785232544],"type":"Point"}
}