{
  "type": "Feature",
  "properties": {
    "addr:full":"Rue De Gourgues 25 Peruwelz Hainaut 7608",
    "addr:housenumber":"25",
    "addr:postcode":"7608",
    "addr:street":"Rue De Gourgues;Hainaut",
    "iso:country":"BE",
    "sg:address":"Rue De Gourgues 25",
    "sg:city":"Peruwelz",
    "sg:classifiers":[
        {
            "category":"Personal",
            "subcategory":"Beauty Salon",
            "type":"Services"
        }
    ],
    "sg:phone":"+32 69 77 43 28",
    "sg:postcode":"7608",
    "sg:province":"Hainaut",
    "sg:tags":[
        "de",
        "coiffure"
    ],
    "wof:name":"Colette Duprez",
    "wof:placetype":"venue"
},
  "geometry": {"coordinates":[3.5306990147,50.5096511841],"type":"Point"}
}