{
  "type": "Feature",
  "properties": {
    "addr:full":"Rue De Rixensart 4 Rixensart Brabant Wallon 1332",
    "addr:housenumber":"4",
    "addr:postcode":"1332",
    "addr:street":"Rue De Rixensart;Wallon",
    "iso:country":"BE",
    "sg:address":"Rue De Rixensart 4",
    "sg:city":"Rixensart",
    "sg:orig_category":"Boekhouders",
    "sg:phone":"+32 2 672 52 47",
    "sg:postcode":"1332",
    "sg:province":"Brabant Wallon",
    "wof:name":"Eric Haulot",
    "wof:placetype":"venue"
},
  "geometry": {"coordinates":[4.513106823,50.7235412598],"type":"Point"}
}