{
  "type": "Feature",
  "properties": {
    "addr:full":"Sint-jozefstraat 4 Temse Oost-Vlaanderen 9140",
    "addr:housenumber":"4",
    "addr:postcode":"9140",
    "addr:street":"Sint-Jozefstraat",
    "iso:country":"BE",
    "sg:address":"Sint-jozefstraat 4",
    "sg:city":"Temse",
    "sg:orig_category":"Artistes ind\u00e9pendants",
    "sg:phone":"+32 3 771 52 43",
    "sg:postcode":"9140",
    "sg:province":"Oost-Vlaanderen",
    "wof:name":"Patrick Harris",
    "wof:placetype":"venue"
},
  "geometry": {"coordinates":[4.1745610237,51.1120491028],"type":"Point"}
}