{
  "type": "Feature",
  "properties": {
    "addr:full":"Dijkstraat 44 Bornem (weert) Antwerpen 2880",
    "addr:housenumber":"44",
    "addr:postcode":"2880",
    "addr:street":"Dijkstraat",
    "iso:country":"BE",
    "sg:address":"Dijkstraat 44",
    "sg:city":"Bornem (weert)",
    "sg:classifiers":[
        {
            "category":"Building & Trades",
            "subcategory":"Plumbing",
            "type":"Services"
        }
    ],
    "sg:phone":"+32 3 889 18 37",
    "sg:postcode":"2880",
    "sg:province":"Antwerpen",
    "sg:tags":[
        "pipe",
        "drain",
        "unblocking"
    ],
    "wof:name":"Ruimdienst Van Bogaert-seghers",
    "wof:placetype":"venue"
},
  "geometry": {"coordinates":[4.205737114,51.1141586304],"type":"Point"}
}