{
  "type": "Feature",
  "properties": {
    "addr:full":"Rue D'aix La Chapelle 324-326 Eupen/eupen Li\u00e8ge 4701",
    "addr:postcode":"324-326;4701",
    "addr:street":"Rue D'Aix",
    "iso:country":"BE",
    "sg:address":"Rue D'aix La Chapelle 324-326",
    "sg:city":"Eupen/eupen",
    "sg:orig_category":"Entretien and r\u00e9parations de voitures. V\u00e9hicules automobiles",
    "sg:phone":"+32 87 55 31 74",
    "sg:postcode":"4701",
    "sg:province":"Li\u00e8ge",
    "wof:name":"Garage Lesmeister/lesmeister",
    "wof:placetype":"venue"
},
  "geometry": {"coordinates":[6.0404901505,50.6520996094],"type":"Point"}
}