{
  "type": "Feature",
  "properties": {
    "iso:country":"BE",
    "sg:address":"Veurnseweg 580",
    "sg:city":"Ieper (elverdinge)",
    "sg:classifiers":[
        {
            "category":"Shopping",
            "subcategory":"Bicycles & Sporting Goods",
            "type":"Retail Goods"
        }
    ],
    "sg:phone":"+32 57 42 26 34",
    "sg:postcode":"8906",
    "sg:province":"West-Vlaanderen",
    "sg:tags":[
        "-"
    ],
    "wof:name":"Carpentier D",
    "wof:placetype":"venue"
},
  "geometry": {"coordinates":[2.8131508827,50.8866004944],"type":"Point"}
}