{
  "type": "Feature",
  "properties": {
    "addr:full":"All\u00c9e Du Long Pr\u00c9 12 Waremme Li\u00e8ge 4300",
    "addr:housenumber":"12",
    "addr:postcode":"4300",
    "addr:street":"Alle\u0301E Du Long Pre\u0301",
    "iso:country":"BE",
    "sg:address":"All\u00c9e Du Long Pr\u00c9 12",
    "sg:city":"Waremme",
    "sg:orig_category":"Activit\u00e9s d\u00b4action sociale sans h\u00e9bergement",
    "sg:phone":"+32 19 32 55 43",
    "sg:postcode":"4300",
    "sg:province":"Li\u00e8ge",
    "wof:name":"Rode Kruis Gingelom",
    "wof:placetype":"venue"
},
  "geometry": {"coordinates":[5.2638440132,50.7033882141],"type":"Point"}
}