{
  "type": "Feature",
  "properties": {
    "iso:country":"BE",
    "sg:address":"Grote Baan 47",
    "sg:city":"Herk-de-stad",
    "sg:orig_category":"HUISBRANDOLIE",
    "sg:phone":"+32 13 44 13 67",
    "sg:postcode":"3540",
    "sg:province":"Limburg",
    "wof:name":"Maria Vangompel",
    "wof:placetype":"venue"
},
  "geometry": {"coordinates":[5.1310582161,50.9470329285],"type":"Point"}
}