{
  "type": "Feature",
  "properties": {
    "iso:country":"BE",
    "sg:address":"Molhemstraat 69",
    "sg:city":"Peer",
    "sg:classifiers":[
        {
            "category":"Home & Garden",
            "subcategory":"Carpets & Floor Coverings",
            "type":"Retail Goods"
        }
    ],
    "sg:phone":"+32 11 63 44 41",
    "sg:postcode":"3990",
    "sg:province":"Limburg",
    "sg:tags":[
        "tile"
    ],
    "wof:name":"Ceyssens J",
    "wof:placetype":"venue"
},
  "geometry": {"coordinates":[5.4318990707,51.139251709],"type":"Point"}
}