{
  "type": "Feature",
  "properties": {
    "addr:full":"Rue De Marche 30-32 Bastogne Luxembourg 6600",
    "addr:postcode":"30-32;6600",
    "addr:street":"Rue De Marche",
    "iso:country":"BE",
    "sg:address":"Rue De Marche 30-32",
    "sg:city":"Bastogne",
    "sg:classifiers":[
        {
            "category":"Insurance",
            "subcategory":"Insurance Agent",
            "type":"Services"
        }
    ],
    "sg:phone":"+32 61 21 47 27",
    "sg:postcode":"6600",
    "sg:province":"Luxembourg",
    "sg:tags":[
        "broker"
    ],
    "wof:name":"Spoiden Ch & Cie",
    "wof:placetype":"venue"
},
  "geometry": {"coordinates":[5.7114911079,50.0017700195],"type":"Point"}
}