{
  "type": "Feature",
  "properties": {
    "addr:full":"Beverseaardeweg 63 Roeselare West-Vlaanderen 8800",
    "addr:housenumber":"63",
    "addr:postcode":"8800",
    "addr:street":"Beverseaardeweg",
    "iso:country":"BE",
    "sg:address":"Beverseaardeweg 63",
    "sg:city":"Roeselare",
    "sg:orig_category":"Alimentation sp\u00e9cialis\u00e9e. Epiceries",
    "sg:phone":"+32 51 22 29 18",
    "sg:postcode":"8800",
    "sg:province":"West-Vlaanderen",
    "wof:name":"Huis De Pimpernel",
    "wof:placetype":"venue"
},
  "geometry": {"coordinates":[3.1387789249,50.9562454224],"type":"Point"}
}