{
  "type": "Feature",
  "properties": {
    "addr:full":"Rue Aviateur Thieffry 36 Bruxelles (etterbeek) Bruxelles-Capitale 1040",
    "addr:housenumber":"36",
    "addr:postcode":"1040",
    "addr:street":"Rue Aviateur Thieffry",
    "iso:country":"BE",
    "sg:address":"Rue Aviateur Thieffry 36",
    "sg:city":"Bruxelles (etterbeek)",
    "sg:classifiers":[
        {
            "category":"Professional",
            "subcategory":"Art Services",
            "type":"Services"
        }
    ],
    "sg:phone":"+32 2 734 16 58",
    "sg:postcode":"1040",
    "sg:province":"Bruxelles-Capitale",
    "sg:tags":[
        "photographer"
    ],
    "wof:name":"Speltdoorn Et Fils",
    "wof:placetype":"venue"
},
  "geometry": {"coordinates":[4.4016251564,50.8311920166],"type":"Point"}
}