{
  "type": "Feature",
  "properties": {
    "iso:country":"BE",
    "sg:address":"Rue Toussaint Gerkens 16",
    "sg:city":"Chaudfontaine (beaufays)",
    "sg:classifiers":[
        {
            "category":"Retail",
            "subcategory":"Funeral Services",
            "type":"Services"
        }
    ],
    "sg:phone":"+32 4 368 56 04",
    "sg:postcode":"4052",
    "sg:province":"Li\u00e8ge",
    "sg:tags":[
        "director"
    ],
    "wof:name":"Funepierre & Dethier",
    "wof:placetype":"venue"
},
  "geometry": {"coordinates":[5.6397161484,50.5575485229],"type":"Point"}
}