{
  "type": "Feature",
  "properties": {
    "iso:country":"BE",
    "sg:address":"38",
    "sg:city":"Rue Outre 7910 Anvaing",
    "sg:classifiers":[
        {
            "category":"Food Court",
            "type":"Food & Drink"
        }
    ],
    "sg:phone":"+32 69 86 61 80",
    "sg:postcode":"38",
    "sg:tags":[
        "product",
        "related"
    ],
    "wof:name":"Delaunoy-ergo Sa",
    "wof:placetype":"venue"
},
  "geometry": {"coordinates":[3.5575020313,50.6845550537],"type":"Point"}
}