{
  "type": "Feature",
  "properties": {
    "addr:full":"Chemin De Messe 6 Wavre Brabant Wallon 1300",
    "addr:housenumber":"6;1300",
    "addr:street":"Chemin De Messe",
    "iso:country":"BE",
    "sg:address":"Chemin De Messe 6",
    "sg:city":"Wavre",
    "sg:orig_category":"Boekenuitgeverijen",
    "sg:phone":"+32 10 41 27 34",
    "sg:postcode":"1300",
    "sg:province":"Brabant Wallon",
    "wof:name":"Luc Baudoux",
    "wof:placetype":"venue"
},
  "geometry": {"coordinates":[4.6064190865,50.7169151306],"type":"Point"}
}