{
  "type": "Feature",
  "properties": {
    "iso:country":"BE",
    "sg:address":"Nieuwstraat 26",
    "sg:city":"Izegem",
    "sg:orig_category":"Fiduciairies",
    "sg:phone":"+32 51 31 95 50",
    "sg:postcode":"8870",
    "sg:province":"West-Vlaanderen",
    "wof:name":"Aartco Bvba",
    "wof:placetype":"venue"
},
  "geometry": {"coordinates":[3.2137029171,50.9192352295],"type":"Point"}
}