{
  "type": "Feature",
  "properties": {
    "iso:country":"BE",
    "sg:address":"Oud-strijdersstraat 76",
    "sg:city":"Herent",
    "sg:classifiers":[
        {
            "category":"Health Services",
            "subcategory":"Doctor",
            "type":"Services"
        }
    ],
    "sg:phone":"+32 16 22 66 70",
    "sg:postcode":"3020",
    "sg:province":"Vlaams-Brabant",
    "sg:tags":[
        "medicinephysicians",
        "surgeon"
    ],
    "wof:name":"Denolf Bart",
    "wof:placetype":"venue"
},
  "geometry": {"coordinates":[4.6708841324,50.9082489014],"type":"Point"}
}