{
  "type": "Feature",
  "properties": {
    "addr:full":"Noordstraat 119 Maldegem Oost-Vlaanderen 9990",
    "addr:housenumber":"119",
    "addr:postcode":"9990",
    "addr:street":"Noordstraat",
    "iso:country":"BE",
    "sg:address":"Noordstraat 119",
    "sg:city":"Maldegem",
    "sg:orig_category":"Slagers",
    "sg:phone":"+32 50 71 13 57",
    "sg:postcode":"9990",
    "sg:province":"Oost-Vlaanderen",
    "wof:name":"O. De Baere",
    "wof:placetype":"venue"
},
  "geometry": {"coordinates":[3.4470829964,51.2132987976],"type":"Point"}
}