{
  "type": "Feature",
  "properties": {
    "iso:country":"BE",
    "sg:address":"Rassel 29",
    "sg:city":"Wemmel",
    "sg:classifiers":[
        {
            "category":"Home & Garden",
            "subcategory":"Carpets & Floor Coverings",
            "type":"Retail Goods"
        }
    ],
    "sg:phone":"+32 2 460 34 89",
    "sg:postcode":"1780",
    "sg:province":"Vlaams-Brabant",
    "sg:tags":[
        "delivery",
        "-",
        "van"
    ],
    "wof:name":"Gar Car Van Campenhout F",
    "wof:placetype":"venue"
},
  "geometry": {"coordinates":[4.2984700203,50.9098587036],"type":"Point"}
}