{
  "type": "Feature",
  "properties": {
    "addr:full":"Rue Des Enhauts 34 Le Roeulx (ville-sur-haine) Hainaut 7070",
    "addr:housenumber":"34",
    "addr:postcode":"7070",
    "addr:street":"Rue Des Enhauts",
    "iso:country":"BE",
    "sg:address":"Rue Des Enhauts 34",
    "sg:city":"Le Roeulx (ville-sur-haine)",
    "sg:classifiers":[
        {
            "category":"Building & Trades",
            "subcategory":"Electrical",
            "type":"Services"
        }
    ],
    "sg:phone":"+32 65 87 27 12",
    "sg:postcode":"7070",
    "sg:province":"Hainaut",
    "sg:tags":[
        "electric",
        "-",
        "housewiring",
        "contractor"
    ],
    "wof:name":"Paindavoine D",
    "wof:placetype":"venue"
},
  "geometry": {"coordinates":[4.0662970543,50.4771270752],"type":"Point"}
}