{
  "type": "Feature",
  "properties": {
    "addr:full":"Hameau De Kin 48 Aywaille Li\u00e8ge 4920",
    "addr:housenumber":"48",
    "addr:postcode":"4920",
    "addr:street":"Hameau De Kin",
    "iso:country":"BE",
    "sg:address":"Hameau De Kin 48",
    "sg:city":"Aywaille",
    "sg:orig_category":"Sportclubs",
    "sg:phone":"+32 4 384 82 73",
    "sg:postcode":"4920",
    "sg:province":"Li\u00e8ge",
    "wof:name":"V.b. Gambrinus",
    "wof:placetype":"venue"
},
  "geometry": {"coordinates":[5.692029953,50.4668998718],"type":"Point"}
}