{
  "type": "Feature",
  "properties": {
    "addr:full":"Avekapellestraat 21 Veurne West-Vlaanderen 8630",
    "addr:housenumber":"21",
    "addr:postcode":"8630",
    "addr:street":"Avekapellestraat",
    "iso:country":"BE",
    "sg:address":"Avekapellestraat 21",
    "sg:city":"Veurne",
    "sg:orig_category":"Rundveehouders",
    "sg:phone":"+32 58 31 25 51",
    "sg:postcode":"8630",
    "sg:province":"West-Vlaanderen",
    "wof:name":"Henk Vandewalle",
    "wof:placetype":"venue"
},
  "geometry": {"coordinates":[2.7309670448,51.069103241],"type":"Point"}
}