{
  "type": "Feature",
  "properties": {
    "iso:country":"BE",
    "sg:address":"Rue Salinas 10",
    "sg:city":"Fernelmont",
    "sg:orig_category":"Architectes",
    "sg:phone":"+32 81 83 52 00",
    "sg:postcode":"5380",
    "sg:province":"Namur",
    "wof:name":"Laurence Collignon",
    "wof:placetype":"venue"
},
  "geometry": {"coordinates":[4.9752669334,50.5489654541],"type":"Point"}
}