{
  "type": "Feature",
  "properties": {
    "iso:country":"BE",
    "sg:address":"Ham 115",
    "sg:city":"Gent",
    "sg:orig_category":"Meubelzaken, woning- and keukeninrichting",
    "sg:phone":"+32 9 225 83 28",
    "sg:postcode":"9000",
    "sg:province":"Oost-Vlaanderen",
    "wof:name":"Maria Slot",
    "wof:placetype":"venue"
},
  "geometry": {"coordinates":[3.7332999706,51.0597572327],"type":"Point"}
}