{
  "type": "Feature",
  "properties": {
    "iso:country":"BE",
    "sg:address":"Merendreedorp 21",
    "sg:city":"Nevele",
    "sg:orig_category":"Dameskledingzaken",
    "sg:phone":"+32 9 371 79 69",
    "sg:postcode":"9850",
    "sg:province":"Oost-Vlaanderen",
    "wof:name":"Huis Bo",
    "wof:placetype":"venue"
},
  "geometry": {"coordinates":[3.5769639015,51.0775032043],"type":"Point"}
}