{
  "type": "Feature",
  "properties": {
    "addr:full":"Steenweg Op Gelrode 60 Rotselaar Vlaams-Brabant 3110",
    "addr:housenumber":"60",
    "addr:postcode":"3110",
    "addr:street":"Steenweg Op Gelrode",
    "iso:country":"BE",
    "sg:address":"Steenweg Op Gelrode 60",
    "sg:city":"Rotselaar",
    "sg:orig_category":"M\u00e9decins and sp\u00e9cialistes",
    "sg:phone":"+32 16 58 22 81",
    "sg:postcode":"3110",
    "sg:province":"Vlaams-Brabant",
    "wof:name":"J. Verbelen",
    "wof:placetype":"venue"
},
  "geometry": {"coordinates":[4.7461972237,50.9695549011],"type":"Point"}
}