{
  "type": "Feature",
  "properties": {
    "iso:country":"BE",
    "sg:address":"Hundelgemsesteenweg 500",
    "sg:city":"Merelbeke",
    "sg:classifiers":[
        {
            "category":"Shopping",
            "subcategory":"Shoes",
            "type":"Retail Goods"
        }
    ],
    "sg:phone":"+32 9 230 38 87",
    "sg:postcode":"9820",
    "sg:province":"Oost-Vlaanderen",
    "sg:tags":[
        "slipper",
        "-"
    ],
    "wof:name":"Mero Shoe",
    "wof:placetype":"venue"
},
  "geometry": {"coordinates":[3.7509300709,51.0010108948],"type":"Point"}
}