{
  "type": "Feature",
  "properties": {
    "addr:full":"Rue Du Fichaux Pont-a-celles Hainaut 6230",
    "addr:postcode":"6230",
    "addr:street":"Rue Du Fichaux Pont-A-Celles Hainaut",
    "iso:country":"BE",
    "sg:address":"Rue Du Fichaux",
    "sg:city":"Pont-a-celles",
    "sg:orig_category":"Royal Canin. Animaux domestiques and accessoires",
    "sg:phone":"+32 71 84 41 97",
    "sg:postcode":"6230",
    "sg:province":"Hainaut",
    "wof:name":"Sibille",
    "wof:placetype":"venue"
},
  "geometry": {"coordinates":[4.3552980423,50.5144042969],"type":"Point"}
}