{
  "type": "Feature",
  "properties": {
    "addr:full":"Van Halmaelelei 3 Brasschaat Antwerpen 2930",
    "addr:housenumber":"3",
    "addr:postcode":"2930",
    "iso:country":"BE",
    "sg:address":"Van Halmaelelei 3",
    "sg:city":"Brasschaat",
    "sg:orig_category":"Meubles Fab",
    "sg:phone":"+32 3 644 77 88",
    "sg:postcode":"2930",
    "sg:province":"Antwerpen",
    "wof:name":"Ceti",
    "wof:placetype":"venue"
},
  "geometry": {"coordinates":[4.4544868469,51.2796173096],"type":"Point"}
}