{
  "type": "Feature",
  "properties": {
    "iso:country":"BE",
    "sg:address":"Pastoor Van Neylenstraat 6",
    "sg:city":"Geel",
    "sg:classifiers":[
        {
            "category":"Shopping",
            "subcategory":"Baby Store",
            "type":"Retail Goods"
        }
    ],
    "sg:phone":"+32 14 58 93 77",
    "sg:postcode":"2440",
    "sg:province":"Antwerpen",
    "sg:tags":[
        "article",
        "b\u00e9b\u00e9s",
        "pour"
    ],
    "wof:name":"Luc Gilis",
    "wof:placetype":"venue"
},
  "geometry": {"coordinates":[4.9968328476,51.1618041992],"type":"Point"}
}