{
  "type": "Feature",
  "properties": {
    "addr:full":"Smissebroek 20 Wellen Limburg 3830",
    "addr:housenumber":"20",
    "addr:postcode":"3830",
    "addr:street":"Smissebroek",
    "iso:country":"BE",
    "sg:address":"Smissebroek 20",
    "sg:city":"Wellen",
    "sg:classifiers":[
        {
            "category":"Home & Garden",
            "subcategory":"Household Appliances",
            "type":"Retail Goods"
        }
    ],
    "sg:phone":"+32 12 74 56 09",
    "sg:postcode":"3830",
    "sg:province":"Limburg",
    "sg:tags":[
        "repair",
        "mainten",
        "-",
        "electric"
    ],
    "wof:name":"Nijs I",
    "wof:placetype":"venue"
},
  "geometry": {"coordinates":[5.3254327774,50.8325233459],"type":"Point"}
}