{
  "type": "Feature",
  "properties": {
    "addr:full":"Statiestraat 14 Kalmthout Antwerpen 2920",
    "addr:housenumber":"14",
    "addr:postcode":"2920",
    "addr:street":"Statiestraat",
    "iso:country":"BE",
    "sg:address":"Statiestraat 14",
    "sg:city":"Kalmthout",
    "sg:orig_category":"Artsen and specialisten",
    "sg:phone":"+32 3 666 81 25",
    "sg:postcode":"2920",
    "sg:province":"Antwerpen",
    "wof:name":"Denise G.g. Haeverans",
    "wof:placetype":"venue"
},
  "geometry": {"coordinates":[4.4733119011,51.3939208984],"type":"Point"}
}