{
  "type": "Feature",
  "properties": {
    "addr:full":"Keizerstraat 4 Tielt West-Vlaanderen 8700",
    "addr:housenumber":"4",
    "addr:postcode":"8700",
    "addr:street":"Keizerstraat",
    "iso:country":"BE",
    "sg:address":"Keizerstraat 4",
    "sg:city":"Tielt",
    "sg:orig_category":"Muziekinstrumenten",
    "sg:phone":"+32 51 68 70 17",
    "sg:postcode":"8700",
    "sg:province":"West-Vlaanderen",
    "wof:name":"Jean-marie Herman",
    "wof:placetype":"venue"
},
  "geometry": {"coordinates":[3.4026269913,51.0138206482],"type":"Point"}
}