{
  "type": "Feature",
  "properties": {
    "iso:country":"BE",
    "sg:address":"Tolhuislaan 128",
    "sg:city":"Gent",
    "sg:orig_category":"Pharmaciens",
    "sg:phone":"+32 9 223 21 60",
    "sg:postcode":"9000",
    "sg:province":"Oost-Vlaanderen",
    "wof:name":"M. Van Vlaenderen",
    "wof:placetype":"venue"
},
  "geometry": {"coordinates":[3.7267808914,51.0648956299],"type":"Point"}
}