{
  "type": "Feature",
  "properties": {
    "addr:full":"Chauss\u00c9e De Ninove 332 Anderlecht Bruxelles-Capitale 1070",
    "addr:housenumber":"332",
    "addr:postcode":"1070",
    "addr:street":"Chausse\u0301E De Ninove",
    "iso:country":"BE",
    "sg:address":"Chauss\u00c9e De Ninove 332",
    "sg:city":"Anderlecht",
    "sg:classifiers":[
        {
            "category":"Fast Food",
            "type":"Food & Drink"
        }
    ],
    "sg:phone":"+32 2 522 56 08",
    "sg:postcode":"1070",
    "sg:province":"Bruxelles-Capitale",
    "sg:tags":[
        "\u00c0",
        "emporter",
        "restaurants"
    ],
    "wof:name":"Bui Van Kim",
    "wof:placetype":"venue"
},
  "geometry": {"coordinates":[4.3138718605,50.848033905],"type":"Point"}
}