{
  "type": "Feature",
  "properties": {
    "addr:full":"Naamsevest 40 Leuven Vlaams-Brabant 3000",
    "addr:housenumber":"40",
    "addr:postcode":"3000",
    "addr:street":"Naamsevest",
    "iso:country":"BE",
    "sg:address":"Naamsevest 40",
    "sg:city":"Leuven",
    "sg:classifiers":[
        {
            "category":"Place Of Worship",
            "subcategory":"Church",
            "type":"Public Place"
        }
    ],
    "sg:phone":"+32 16 23 77 70",
    "sg:postcode":"3000",
    "sg:province":"Vlaams-Brabant",
    "sg:tags":[
        "furnishing",
        "supply"
    ],
    "wof:name":"Casier G",
    "wof:placetype":"venue"
},
  "geometry": {"coordinates":[4.6997928619,50.8684997559],"type":"Point"}
}