{
  "type": "Feature",
  "properties": {
    "addr:full":"Bierweg 14 Aalter Oost-Vlaanderen 9880",
    "addr:housenumber":"14",
    "addr:postcode":"9880",
    "addr:street":"Bierweg",
    "iso:country":"BE",
    "sg:address":"Bierweg 14",
    "sg:city":"Aalter",
    "sg:classifiers":[
        {
            "category":"Professional",
            "subcategory":"Accounting & Tax Preparation",
            "type":"Services"
        }
    ],
    "sg:phone":"+32 9 325 03 18",
    "sg:postcode":"9880",
    "sg:province":"Oost-Vlaanderen",
    "sg:tags":[
        "accountant"
    ],
    "wof:name":"Van De Velde K",
    "wof:placetype":"venue"
},
  "geometry": {"coordinates":[3.4419960976,51.0850067139],"type":"Point"}
}