{
  "type": "Feature",
  "properties": {
    "addr:full":"Neststraat 14 Gent Oost-Vlaanderen 9051",
    "addr:housenumber":"14",
    "addr:postcode":"9051",
    "addr:street":"Neststraat;Oost-Vlaanderen",
    "iso:country":"BE",
    "sg:address":"Neststraat 14",
    "sg:city":"Gent",
    "sg:orig_category":"Dakwerken Loodgieterij, verwarming and sanitaire installaties Schoonmaakbedrijven and ongediertebest",
    "sg:phone":"+32 475 97 39 83",
    "sg:postcode":"9051",
    "sg:province":"Oost-Vlaanderen",
    "wof:name":"Harry Malter",
    "wof:placetype":"venue"
},
  "geometry": {"coordinates":[3.6667599678,51.0248641968],"type":"Point"}
}