{
  "type": "Feature",
  "properties": {
    "addr:full":"Route De Mettet Florennes Namur 5620",
    "addr:postcode":"5620",
    "addr:street":"Route De Mettet",
    "iso:country":"BE",
    "sg:address":"Route De Mettet",
    "sg:city":"Florennes",
    "sg:orig_category":"Supermarkten",
    "sg:postcode":"5620",
    "sg:province":"Namur",
    "wof:name":"Aldi",
    "wof:placetype":"venue"
},
  "geometry": {"coordinates":[4.6088452339,50.2564544678],"type":"Point"}
}