{
  "type": "Feature",
  "properties": {
    "addr:full":"Prins Albertlaan 42 Oostende West-Vlaanderen 8400",
    "addr:housenumber":"42",
    "addr:postcode":"8400",
    "addr:street":"Prins Albertlaan",
    "iso:country":"BE",
    "sg:address":"Prins Albertlaan 42",
    "sg:city":"Oostende",
    "sg:classifiers":[
        {
            "category":"Professional",
            "subcategory":"Testing Lab",
            "type":"Services"
        }
    ],
    "sg:phone":"+32 59 32 23 95",
    "sg:postcode":"8400",
    "sg:province":"West-Vlaanderen",
    "sg:tags":[
        "chemist"
    ],
    "wof:name":"Vantyghem E",
    "wof:placetype":"venue"
},
  "geometry": {"coordinates":[2.9451808929,51.22240448],"type":"Point"}
}