{
  "type": "Feature",
  "properties": {
    "addr:full":"Julius Dooghelaan 15 Brugge (sint-kruis) West-Vlaanderen 8310",
    "addr:housenumber":"15",
    "addr:postcode":"8310",
    "addr:street":"Dooghelaan",
    "iso:country":"BE",
    "sg:address":"Julius Dooghelaan 15",
    "sg:city":"Brugge (sint-kruis)",
    "sg:classifiers":[
        {
            "category":"Building & Trades",
            "subcategory":"Electrical",
            "type":"Services"
        }
    ],
    "sg:phone":"+32 50 35 58 70",
    "sg:postcode":"8310",
    "sg:province":"West-Vlaanderen",
    "sg:tags":[
        "electric",
        "-",
        "housewiring",
        "contractor"
    ],
    "wof:name":"Druwel F",
    "wof:placetype":"venue"
},
  "geometry": {"coordinates":[3.2425560951,51.2167625427],"type":"Point"}
}