{
  "type": "Feature",
  "properties": {
    "iso:country":"BE",
    "sg:address":"Betlehem 2",
    "sg:city":"Menen",
    "sg:classifiers":[
        {
            "category":"Communications",
            "subcategory":"Radio Station",
            "type":"Services"
        }
    ],
    "sg:phone":"+32 56 51 76 28",
    "sg:postcode":"8930",
    "sg:province":"West-Vlaanderen",
    "sg:tags":[
        "diffusion",
        "production",
        "de",
        "programme"
    ],
    "wof:name":"Radio Pallieter",
    "wof:placetype":"venue"
},
  "geometry": {"coordinates":[3.0972950459,50.791267395],"type":"Point"}
}