{
  "type": "Feature",
  "properties": {
    "addr:full":"Waterwalstraat 3 Ruiselede West-Vlaanderen 8755",
    "addr:housenumber":"3",
    "addr:postcode":"8755",
    "addr:street":"Waterwalstraat",
    "iso:country":"BE",
    "sg:address":"Waterwalstraat 3",
    "sg:city":"Ruiselede",
    "sg:orig_category":"Rundveehouders Varkenskwekers",
    "sg:phone":"+32 51 68 84 25",
    "sg:postcode":"8755",
    "sg:province":"West-Vlaanderen",
    "wof:name":"Noel Demarez",
    "wof:placetype":"venue"
},
  "geometry": {"coordinates":[3.3674190044,51.0392112732],"type":"Point"}
}