{
  "type": "Feature",
  "properties": {
    "addr:full":"Hoevenzavellaan 81 Genk (waterschei) Limburg 3600",
    "addr:housenumber":"81",
    "addr:postcode":"3600",
    "addr:street":"Hoevenzavellaan",
    "iso:country":"BE",
    "sg:address":"Hoevenzavellaan 81",
    "sg:city":"Genk (waterschei)",
    "sg:classifiers":[
        {
            "category":"Shopping",
            "type":"Retail Goods"
        }
    ],
    "sg:phone":"+32 89 70 15 17",
    "sg:postcode":"3600",
    "sg:province":"Limburg",
    "sg:tags":[
        "product",
        "cleaning",
        "maintenance"
    ],
    "wof:name":"Chrisal",
    "wof:placetype":"venue"
},
  "geometry": {"coordinates":[5.5070772171,51.0009765625],"type":"Point"}
}