{
  "type": "Feature",
  "properties": {
    "iso:country":"BE",
    "sg:address":"Rue De La Cr\u00e8te 19",
    "sg:city":"Namur",
    "sg:classifiers":[
        {
            "category":"Social Services",
            "subcategory":"Job Training",
            "type":"Services"
        }
    ],
    "sg:phone":"+32 81 30 72 98",
    "sg:postcode":"5000",
    "sg:province":"Namur",
    "sg:tags":[
        "interpreter"
    ],
    "wof:name":"Lingua T Sc",
    "wof:placetype":"venue"
},
  "geometry": {"coordinates":[4.8679490089,50.4764404297],"type":"Point"}
}