{
  "type": "Feature",
  "properties": {
    "addr:full":"Herenboslaan 33 Lier Antwerpen 2500",
    "addr:housenumber":"33",
    "addr:postcode":"2500",
    "addr:street":"Herenboslaan",
    "iso:country":"BE",
    "sg:address":"Herenboslaan 33",
    "sg:city":"Lier",
    "sg:classifiers":[
        {
            "category":"Arena",
            "subcategory":"Sports Club",
            "type":"Entertainment"
        }
    ],
    "sg:phone":"+32 3 482 27 35",
    "sg:postcode":"2500",
    "sg:province":"Antwerpen",
    "sg:tags":[
        "de"
    ],
    "wof:name":"Kon. Lierse Turnkring",
    "wof:placetype":"venue"
},
  "geometry": {"coordinates":[4.6069002151,51.0934410095],"type":"Point"}
}