{
  "type": "Feature",
  "properties": {
    "addr:full":"Sint-katelijnestraat 5 Mechelen Antwerpen 2800",
    "addr:housenumber":"5",
    "addr:postcode":"2800",
    "addr:street":"Sint-Katelijnestraat",
    "iso:country":"BE",
    "sg:address":"Sint-katelijnestraat 5",
    "sg:city":"Mechelen",
    "sg:classifiers":[
        {
            "category":"Shopping",
            "subcategory":"Gifts & Souvenirs",
            "type":"Retail Goods"
        }
    ],
    "sg:phone":"+32 15 20 29 47",
    "sg:postcode":"2800",
    "sg:province":"Antwerpen",
    "sg:tags":[
        "-"
    ],
    "wof:name":"Vijgenboom (de)",
    "wof:placetype":"venue"
},
  "geometry": {"coordinates":[4.4774918556,51.0294761658],"type":"Point"}
}