{
  "type": "Feature",
  "properties": {
    "addr:full":"Vrijheid 157 Hoogstraten Antwerpen 2320",
    "addr:housenumber":"157",
    "addr:postcode":"2320",
    "addr:street":"Vrijheid",
    "iso:country":"BE",
    "sg:address":"Vrijheid 157",
    "sg:city":"Hoogstraten",
    "sg:orig_category":"Banken and kredietinstellingen",
    "sg:phone":"+32 3 314 70 32",
    "sg:postcode":"2320",
    "sg:province":"Antwerpen",
    "wof:name":"Bbl",
    "wof:placetype":"venue"
},
  "geometry": {"coordinates":[4.7610621452,51.4003486633],"type":"Point"}
}