{
  "type": "Feature",
  "properties": {
    "iso:country":"BE",
    "sg:address":"August Lenaertsstraat 9",
    "sg:city":"Mechelen",
    "sg:classifiers":[
        {
            "category":"Arena",
            "subcategory":"Sports Club",
            "type":"Entertainment"
        }
    ],
    "sg:phone":"+32 15 41 88 99",
    "sg:postcode":"2812",
    "sg:province":"Antwerpen",
    "sg:tags":[
        "de"
    ],
    "wof:name":"Snelle Vlucht",
    "wof:placetype":"venue"
},
  "geometry": {"coordinates":[4.5147871971,51.0101242065],"type":"Point"}
}