{
  "type": "Feature",
  "properties": {
    "iso:country":"BE",
    "sg:address":"Neerstraat",
    "sg:city":"Tessenderlo",
    "sg:classifiers":[
        {
            "category":"Bars & Pubs",
            "type":"Food & Drink"
        }
    ],
    "sg:phone":"+32 13 66 82 65",
    "sg:postcode":"3980",
    "sg:province":"Limburg",
    "wof:name":"De Voordyker Sporthal",
    "wof:placetype":"venue"
},
  "geometry": {"coordinates":[5.090294838,51.0772018433],"type":"Point"}
}