{
  "type": "Feature",
  "properties": {
    "addr:full":"Rue G. Reynen 144 Ans Li\u00e8ge 4432",
    "addr:housenumber":"144",
    "addr:postcode":"4432",
    "addr:street":"Rue G. Reynen",
    "iso:country":"BE",
    "sg:address":"Rue G. Reynen 144",
    "sg:city":"Ans",
    "sg:orig_category":"Boekhouders",
    "sg:phone":"+32 4 263 07 00",
    "sg:postcode":"4432",
    "sg:province":"Li\u00e8ge",
    "wof:name":"Belleflamme Ernest",
    "wof:placetype":"venue"
},
  "geometry": {"coordinates":[5.5143690109,50.677772522],"type":"Point"}
}