{
  "type": "Feature",
  "properties": {
    "addr:full":"Nieuwstraat 88 Lummen Limburg 3560",
    "addr:housenumber":"88",
    "addr:postcode":"3560",
    "addr:street":"Nieuwstraat",
    "iso:country":"BE",
    "sg:address":"Nieuwstraat 88",
    "sg:city":"Lummen",
    "sg:classifiers":[
        {
            "category":"Home & Garden",
            "subcategory":"Carpets & Floor Coverings",
            "type":"Retail Goods"
        }
    ],
    "sg:phone":"+32 11 42 12 42",
    "sg:postcode":"3560",
    "sg:province":"Limburg",
    "sg:tags":[
        "armoring"
    ],
    "wof:name":"Vc Chape",
    "wof:placetype":"venue"
},
  "geometry": {"coordinates":[5.223233223,51.0103378296],"type":"Point"}
}