{
  "type": "Feature",
  "properties": {
    "addr:full":"Elsleukenstraat 39 Langdorp Vlaams-Brabant 3201",
    "addr:housenumber":"39",
    "addr:postcode":"3201",
    "addr:street":"Elsleukenstraat",
    "iso:country":"BE",
    "sg:address":"Elsleukenstraat 39",
    "sg:city":"Langdorp",
    "sg:orig_category":"Travaux de pl\u00e2trage",
    "sg:phone":"+32 475 23 79 56",
    "sg:postcode":"3201",
    "sg:province":"Vlaams-Brabant",
    "wof:name":"Garello Jozef",
    "wof:placetype":"venue"
},
  "geometry": {"coordinates":[4.9099979401,51.0188980103],"type":"Point"}
}