{
  "type": "Feature",
  "properties": {
    "addr:full":"Rue Henri De Dinant 12 Li\u00e8ge 1 (li\u00e8ge 2) Li\u00e8ge 4020",
    "addr:housenumber":"12;1;2",
    "addr:postcode":"4020",
    "addr:street":"Rue Henri De Dinant",
    "iso:country":"BE",
    "sg:address":"Rue Henri De Dinant 12",
    "sg:city":"Li\u00e8ge 1 (li\u00e8ge 2)",
    "sg:classifiers":[
        {
            "category":"Community Center",
            "type":"Public Place"
        }
    ],
    "sg:phone":"+32 4 343 56 50",
    "sg:postcode":"4020",
    "sg:province":"Li\u00e8ge",
    "sg:tags":[
        "medical"
    ],
    "wof:name":"Cabinet D'imagerie Medicale Dr Renoy Sprl Sprl",
    "wof:placetype":"venue"
},
  "geometry": {"coordinates":[5.5834441185,50.6413955688],"type":"Point"}
}