{
  "type": "Feature",
  "properties": {
    "addr:full":"Le-brouc 2 Helecine Brabant Wallon 1357",
    "addr:housenumber":"2",
    "addr:postcode":"1357",
    "addr:street":"Le-Brouc",
    "iso:country":"BE",
    "sg:address":"Le-brouc 2",
    "sg:city":"Helecine",
    "sg:orig_category":"Overheidsdiensten",
    "sg:phone":"+32 19 65 59 59",
    "sg:postcode":"1357",
    "sg:province":"Brabant Wallon",
    "wof:name":"C.p.a.s.",
    "wof:placetype":"venue"
},
  "geometry": {"coordinates":[4.9908790588,50.7578887939],"type":"Point"}
}