{
  "type": "Feature",
  "properties": {
    "addr:full":"Gaversstraat 21 Harelbeke West-Vlaanderen 8530",
    "addr:housenumber":"21",
    "addr:postcode":"8530",
    "addr:street":"Gaversstraat",
    "iso:country":"BE",
    "sg:address":"Gaversstraat 21",
    "sg:city":"Harelbeke",
    "sg:orig_category":"Supermarkten",
    "sg:phone":"+32 56 70 53 86",
    "sg:postcode":"8530",
    "sg:province":"West-Vlaanderen",
    "wof:name":"Unic",
    "wof:placetype":"venue"
},
  "geometry": {"coordinates":[3.3163700104,50.8541793823],"type":"Point"}
}