{
  "type": "Feature",
  "properties": {
    "iso:country":"BE",
    "sg:address":"Beverdijk 31",
    "sg:city":"Haacht",
    "sg:orig_category":"Installation \u00e9lectrique r\u00e9sidentielle",
    "sg:phone":"+32 16 60 78 55",
    "sg:postcode":"3150",
    "sg:province":"Vlaams-Brabant",
    "wof:name":"Building Inform. Systems",
    "wof:placetype":"venue"
},
  "geometry": {"coordinates":[4.6092538834,50.9791297913],"type":"Point"}
}