{
  "type": "Feature",
  "properties": {
    "addr:full":"Rue De Livourne 66 Bruxelles Bruxelles-Capitale 1000",
    "addr:housenumber":"66",
    "addr:postcode":"1000",
    "addr:street":"Rue De Livourne",
    "iso:country":"BE",
    "sg:address":"Rue De Livourne 66",
    "sg:city":"Bruxelles",
    "sg:classifiers":[
        {
            "category":"Professional",
            "subcategory":"Management & Consulting",
            "type":"Services"
        }
    ],
    "sg:phone":"+32 2 537 21 55",
    "sg:postcode":"1000",
    "sg:province":"Bruxelles-Capitale",
    "sg:tags":[
        "consultant"
    ],
    "wof:name":"Smp International Sprl",
    "wof:placetype":"venue"
},
  "geometry": {"coordinates":[4.3601379395,50.8291397095],"type":"Point"}
}