{
  "type": "Feature",
  "properties": {
    "addr:full":"Oostendse Steenweg 3 Brugge West-Vlaanderen 8000",
    "addr:housenumber":"3",
    "addr:postcode":"8000",
    "addr:street":"Oostendse Steenweg",
    "iso:country":"BE",
    "sg:address":"Oostendse Steenweg 3",
    "sg:city":"Brugge",
    "sg:classifiers":[
        {
            "category":"Health Services",
            "subcategory":"Dentist",
            "type":"Services"
        }
    ],
    "sg:phone":"+32 50 31 55 75",
    "sg:postcode":"8000",
    "sg:province":"West-Vlaanderen",
    "wof:name":"De Bus Geert",
    "wof:placetype":"venue"
},
  "geometry": {"coordinates":[3.2241659164,51.2083015442],"type":"Point"}
}