{
  "type": "Feature",
  "properties": {
    "addr:full":"Stationlaan 49 Tongeren Limburg 3700",
    "addr:housenumber":"49",
    "addr:postcode":"3700",
    "addr:street":"Stationlaan",
    "iso:country":"BE",
    "sg:address":"Stationlaan 49",
    "sg:city":"Tongeren",
    "sg:orig_category":"Fleurs and plantes",
    "sg:phone":"+32 12 23 74 82",
    "sg:postcode":"3700",
    "sg:province":"Limburg",
    "wof:name":"Aalsmeer Bleomenhuis",
    "wof:placetype":"venue"
},
  "geometry": {"coordinates":[5.4729189873,50.7836532593],"type":"Point"}
}