{
  "type": "Feature",
  "properties": {
    "addr:full":"Zandstraat 121 Zoersel Antwerpen 2980",
    "addr:housenumber":"121",
    "addr:postcode":"2980",
    "addr:street":"Zandstraat",
    "iso:country":"BE",
    "sg:address":"Zandstraat 121",
    "sg:city":"Zoersel",
    "sg:classifiers":[
        {
            "category":"Insurance",
            "subcategory":"Life Insurance",
            "type":"Services"
        }
    ],
    "sg:phone":"+32 3 309 18 10",
    "sg:postcode":"2980",
    "sg:province":"Antwerpen",
    "sg:tags":[
        "assurance"
    ],
    "wof:name":"Kennis Dirk",
    "wof:placetype":"venue"
},
  "geometry": {"coordinates":[4.7112312317,51.2603340149],"type":"Point"}
}