{
  "type": "Feature",
  "properties": {
    "iso:country":"BE",
    "sg:address":"Rue Neuve 7b42",
    "sg:city":"Herve",
    "sg:orig_category":"Textiel",
    "sg:phone":"+32 87 67 85 52",
    "sg:postcode":"4650",
    "sg:province":"Li\u00e8ge",
    "wof:name":"Maison La Boutonnifre",
    "wof:placetype":"venue"
},
  "geometry": {"coordinates":[5.79190588,50.6387062073],"type":"Point"}
}