{
  "type": "Feature",
  "properties": {
    "addr:full":"Meerhoutstraat 29 Ham (kwaadmechelen) Limburg 3945",
    "addr:housenumber":"29",
    "addr:postcode":"kwaadmechelen;3945",
    "addr:street":"Meerhoutstraat",
    "iso:country":"BE",
    "sg:address":"Meerhoutstraat 29",
    "sg:city":"Ham (kwaadmechelen)",
    "sg:classifiers":[
        {
            "category":"Food & Beverages",
            "subcategory":"Groceries & Convenience Stores",
            "type":"Retail Goods"
        }
    ],
    "sg:phone":"+32 13 66 22 40",
    "sg:postcode":"3945",
    "sg:province":"Limburg",
    "sg:tags":[
        "baker",
        "-",
        "ingredient"
    ],
    "wof:name":"Merout Nv",
    "wof:placetype":"venue"
},
  "geometry": {"coordinates":[5.1776199341,51.1046104431],"type":"Point"}
}