{
  "type": "Feature",
  "properties": {
    "iso:country":"BE",
    "sg:address":"Rue Quinaux 36",
    "sg:city":"Schaarbeek/schaerbeek",
    "sg:orig_category":"G\u00e9om\u00e8tres",
    "sg:phone":"+32 2 241 05 27",
    "sg:postcode":"1030",
    "sg:province":"Bruxelles-Capitale",
    "wof:name":"A. Hubert",
    "wof:placetype":"venue"
},
  "geometry": {"coordinates":[4.3720622063,50.8690109253],"type":"Point"}
}