{
  "type": "Feature",
  "properties": {
    "iso:country":"BE",
    "sg:address":"Kipdorp 57",
    "sg:city":"Antwerpen",
    "sg:classifiers":[
        {
            "category":"Professional",
            "subcategory":"Employment Agencies",
            "type":"Services"
        }
    ],
    "sg:phone":"+32 3 204 08 11",
    "sg:postcode":"2000",
    "sg:province":"Antwerpen",
    "sg:tags":[
        "shipping"
    ],
    "wof:name":"Inchcape Shipping Services Nv",
    "wof:placetype":"venue"
},
  "geometry": {"coordinates":[4.4096961021,51.22082901],"type":"Point"}
}