{
  "type": "Feature",
  "properties": {
    "iso:country":"BE",
    "sg:address":"Rechtestraat 18",
    "sg:city":"Lier",
    "sg:classifiers":[
        {
            "category":"Professional",
            "subcategory":"Printing & Photocopies",
            "type":"Services"
        }
    ],
    "sg:phone":"+32 3 488 48 48",
    "sg:postcode":"2500",
    "sg:province":"Antwerpen",
    "sg:tags":[
        "-",
        "offset"
    ],
    "wof:name":"Vekemans L",
    "wof:placetype":"venue"
},
  "geometry": {"coordinates":[4.5718989372,51.1300964355],"type":"Point"}
}