{
  "type": "Feature",
  "properties": {
    "addr:full":"Postelweg 3 Balen Antwerpen 2490",
    "addr:housenumber":"3",
    "addr:postcode":"2490",
    "addr:street":"Postelweg",
    "iso:country":"BE",
    "sg:address":"Postelweg 3",
    "sg:city":"Balen",
    "sg:orig_category":"Etablissements Erotiques",
    "sg:phone":"+32 14 81 38 53",
    "sg:postcode":"2490",
    "sg:province":"Antwerpen",
    "wof:name":"Robert Van Elsen",
    "wof:placetype":"venue"
},
  "geometry": {"coordinates":[5.1815972328,51.1975746155],"type":"Point"}
}