{
  "type": "Feature",
  "properties": {
    "iso:country":"BE",
    "sg:address":"Leopold Ii Straat 47",
    "sg:city":"Sint-truiden",
    "sg:orig_category":"Advocaten and juridische adviseurs",
    "sg:phone":"+32 11 68 43 70",
    "sg:postcode":"3800",
    "sg:province":"Limburg",
    "wof:name":"Els Speelman",
    "wof:placetype":"venue"
},
  "geometry": {"coordinates":[5.1795229912,50.8173942566],"type":"Point"}
}