{
  "type": "Feature",
  "properties": {
    "iso:country":"BE",
    "sg:address":"Vijfhuizen 10",
    "sg:city":"Erpe-mere",
    "sg:classifiers":[
        {
            "category":"Shopping",
            "type":"Retail Goods"
        }
    ],
    "sg:phone":"+32 53 80 28 03",
    "sg:postcode":"9420",
    "sg:province":"Oost-Vlaanderen",
    "sg:tags":[
        "metallurgy",
        "finished",
        "-",
        "metalworking",
        "metallic"
    ],
    "wof:name":"Meert Bvba",
    "wof:placetype":"venue"
},
  "geometry": {"coordinates":[3.9930820465,50.9419937134],"type":"Point"}
}