{
  "type": "Feature",
  "properties": {
    "iso:country":"BE",
    "sg:address":"Rue Ren\u00c9 Detiste 21",
    "sg:city":"Hannut",
    "sg:classifiers":[
        {
            "category":"Personal",
            "subcategory":"Beauty Salon",
            "type":"Services"
        }
    ],
    "sg:phone":"+32 19 63 52 42",
    "sg:postcode":"4280",
    "sg:province":"Li\u00e8ge",
    "sg:tags":[
        "de",
        "coiffure"
    ],
    "wof:name":"Coiffure Aux Ciseaux D'or",
    "wof:placetype":"venue"
},
  "geometry": {"coordinates":[5.0345158577,50.6944541931],"type":"Point"}
}