{
  "type": "Feature",
  "properties": {
    "addr:full":"Leopoldstraat 28 Zwevegem West-Vlaanderen 8550",
    "addr:housenumber":"28",
    "addr:postcode":"8550",
    "addr:street":"Leopoldstraat",
    "iso:country":"BE",
    "sg:address":"Leopoldstraat 28",
    "sg:city":"Zwevegem",
    "sg:classifiers":[
        {
            "category":"Arts & Performance",
            "subcategory":"Comedy Club",
            "type":"Entertainment"
        }
    ],
    "sg:phone":"+32 56 75 53 14",
    "sg:postcode":"8550",
    "sg:province":"West-Vlaanderen",
    "sg:tags":[
        "gown",
        "dressing"
    ],
    "wof:name":"Brittania Parmentier B.v.b.a.",
    "wof:placetype":"venue"
},
  "geometry": {"coordinates":[3.3367409706,50.8115921021],"type":"Point"}
}