{
  "type": "Feature",
  "properties": {
    "iso:country":"BE",
    "sg:address":"Rue Des J\u00c9suites 49",
    "sg:city":"Tournai",
    "sg:orig_category":"Autoverhuur Verhuisdiensten",
    "sg:phone":"+32 69 22 48 16",
    "sg:postcode":"7500",
    "sg:province":"Hainaut",
    "wof:name":"Europcar",
    "wof:placetype":"venue"
},
  "geometry": {"coordinates":[3.3905100822,50.6035690308],"type":"Point"}
}