{
  "type": "Feature",
  "properties": {
    "addr:full":"Rue De Namur 168 Nivelles Brabant Wallon 1400",
    "addr:housenumber":"168",
    "addr:postcode":"1400",
    "addr:street":"Rue De Namur",
    "iso:country":"BE",
    "sg:address":"Rue De Namur 168",
    "sg:city":"Nivelles",
    "sg:classifiers":[
        {
            "category":"Real Estate",
            "subcategory":"Real Estate Services",
            "type":"Services"
        }
    ],
    "sg:phone":"+32 67 84 10 44",
    "sg:postcode":"1400",
    "sg:province":"Brabant Wallon",
    "wof:name":"Immo Aclot Sprl",
    "wof:placetype":"venue"
},
  "geometry": {"coordinates":[4.3407859802,50.5991172791],"type":"Point"}
}