{
  "type": "Feature",
  "properties": {
    "addr:full":"Kattestraat 26 Aalst Oost-Vlaanderen 9300",
    "addr:housenumber":"26",
    "addr:postcode":"9300",
    "addr:street":"Kattestraat",
    "iso:country":"BE",
    "sg:address":"Kattestraat 26",
    "sg:city":"Aalst",
    "sg:classifiers":[
        {
            "category":"Shopping",
            "subcategory":"Computers & Home Electronics",
            "type":"Retail Goods"
        }
    ],
    "sg:phone":"+32 53 21 62 98",
    "sg:postcode":"9300",
    "sg:province":"Oost-Vlaanderen",
    "sg:tags":[
        "shop",
        "base",
        "telecommunicatieapparaten"
    ],
    "wof:name":"Base Aalst",
    "wof:placetype":"venue"
},
  "geometry": {"coordinates":[4.037733078,50.9391059875],"type":"Point"}
}