{
  "type": "Feature",
  "properties": {
    "addr:full":"Rue De Philippeville 89 Ham-sur-heure-nalinnes Hainaut 6120",
    "addr:housenumber":"89",
    "addr:postcode":"6120",
    "addr:street":"Rue De Philippeville;Hainaut",
    "iso:country":"BE",
    "sg:address":"Rue De Philippeville 89",
    "sg:city":"Ham-sur-heure-nalinnes",
    "sg:orig_category":"Installation \u00e9lectrique r\u00e9sidentielle. Syst\u00e8mes de t\u00e9l\u00e9communications. Meubles D\u00e9taillants, Am\u00e9nagem",
    "sg:phone":"+32 71 22 92 11",
    "sg:postcode":"6120",
    "sg:province":"Hainaut",
    "wof:name":"Muyle",
    "wof:placetype":"venue"
},
  "geometry": {"coordinates":[4.4749770164,50.3359146118],"type":"Point"}
}