{
  "type": "Feature",
  "properties": {
    "iso:country":"BE",
    "sg:address":"Rue De La Haute Folie 76",
    "sg:city":"Soignies (naast)",
    "sg:classifiers":[
        {
            "category":"Shopping",
            "subcategory":"Clothing, Apparel, & Fashions",
            "type":"Retail Goods"
        }
    ],
    "sg:phone":"+32 67 33 49 87",
    "sg:postcode":"7062",
    "sg:province":"Hainaut",
    "sg:tags":[
        "boutique"
    ],
    "wof:name":"Guelette Y",
    "wof:placetype":"venue"
},
  "geometry": {"coordinates":[4.0969619751,50.5497665405],"type":"Point"}
}