{
  "type": "Feature",
  "properties": {
    "iso:country":"BE",
    "sg:address":"Stationsstraat 168",
    "sg:city":"Lanaken",
    "sg:classifiers":[
        {
            "category":"Cafe",
            "type":"Food & Drink"
        }
    ],
    "sg:phone":"+32 89 71 62 38",
    "sg:postcode":"3620",
    "sg:province":"Limburg",
    "sg:tags":[
        "caf\u00e9s"
    ],
    "wof:name":"Lisette Thijs",
    "wof:placetype":"venue"
},
  "geometry": {"coordinates":[5.643029213,50.8865013123],"type":"Point"}
}