{
  "type": "Feature",
  "properties": {
    "iso:country":"BE",
    "sg:address":"Antwerpsesteenweg 57",
    "sg:city":"Rumst",
    "sg:classifiers":[
        {
            "category":"Wholesale",
            "subcategory":"Vending Machines",
            "type":"Manufacturing & Wholesale Goods"
        }
    ],
    "sg:phone":"+32 15 34 54 05",
    "sg:postcode":"2840",
    "sg:province":"Antwerpen",
    "sg:tags":[
        "-",
        "electric",
        "motor"
    ],
    "wof:name":"Electrobobinage J.d. Bvba",
    "wof:placetype":"venue"
},
  "geometry": {"coordinates":[4.4513840675,51.0930252075],"type":"Point"}
}