{
  "type": "Feature",
  "properties": {
    "iso:country":"BE",
    "sg:address":"Chemin De La Renarderie 4",
    "sg:city":"Frasnes-lez-anvaing",
    "sg:orig_category":"Jardinage",
    "sg:phone":"+32 69 76 72 13",
    "sg:postcode":"7910",
    "sg:province":"Hainaut",
    "wof:name":"Verhaeghe F.",
    "wof:placetype":"venue"
},
  "geometry": {"coordinates":[3.5400490761,50.7072792053],"type":"Point"}
}