{
  "type": "Feature",
  "properties": {
    "addr:full":"Skaldenstraat 1 Gent Oost-Vlaanderen 9042",
    "addr:housenumber":"1",
    "addr:postcode":"9042",
    "addr:street":"Skaldenstraat;Oost-Vlaanderen",
    "iso:country":"BE",
    "sg:address":"Skaldenstraat 1",
    "sg:city":"Gent",
    "sg:classifiers":[
        {
            "category":"Industrial Area",
            "type":"Public Place"
        }
    ],
    "sg:phone":"+32 9 255 02 11",
    "sg:postcode":"9042",
    "sg:province":"Oost-Vlaanderen",
    "sg:tags":[
        "coal"
    ],
    "wof:name":"A. Vloeberghs Nv",
    "wof:placetype":"venue"
},
  "geometry": {"coordinates":[3.7816700935,51.1223831177],"type":"Point"}
}