{
  "type": "Feature",
  "properties": {
    "iso:country":"BE",
    "sg:address":"Rue De Gare De Ramillies 14",
    "sg:city":"Ramillies",
    "sg:orig_category":"Banken and kredietinstellingen",
    "sg:phone":"+32 81 87 73 38",
    "sg:postcode":"1367",
    "sg:province":"Brabant Wallon",
    "wof:name":"Dexia",
    "wof:placetype":"venue"
},
  "geometry": {"coordinates":[4.8984518051,50.6551971436],"type":"Point"}
}