{
  "type": "Feature",
  "properties": {
    "iso:country":"BE",
    "sg:address":"Rue Arnold Trillet 177",
    "sg:city":"Soumagne",
    "sg:orig_category":"Installation de menuiserie en bois and plastique",
    "sg:phone":"+32 4 377 37 27",
    "sg:postcode":"4630",
    "sg:province":"Li\u00e8ge",
    "wof:name":"Rudy Chapelle",
    "wof:placetype":"venue"
},
  "geometry": {"coordinates":[5.7302799225,50.6236915588],"type":"Point"}
}