{
  "type": "Feature",
  "properties": {
    "addr:full":"Rue Grande Fontaine 112 Libin (villance) Luxembourg 6890",
    "addr:housenumber":"112",
    "addr:postcode":"6890",
    "addr:street":"Rue Grande Fontaine",
    "iso:country":"BE",
    "sg:address":"Rue Grande Fontaine 112",
    "sg:city":"Libin (villance)",
    "sg:classifiers":[
        {
            "category":"Health Services",
            "subcategory":"Health Practitioner",
            "type":"Services"
        }
    ],
    "sg:phone":"+32 61 65 66 20",
    "sg:postcode":"6890",
    "sg:province":"Luxembourg",
    "sg:tags":[
        "physiotherapist"
    ],
    "wof:name":"Arnould V",
    "wof:placetype":"venue"
},
  "geometry": {"coordinates":[5.2217001915,49.9708557129],"type":"Point"}
}