{
  "type": "Feature",
  "properties": {
    "iso:country":"BE",
    "sg:address":"Kapelhof 25",
    "sg:city":"Kasterlee",
    "sg:orig_category":"Afval and schroot Gh",
    "sg:phone":"+32 14 55 76 47",
    "sg:postcode":"2460",
    "sg:province":"Antwerpen",
    "wof:name":"Fa. Harz\u00c9",
    "wof:placetype":"venue"
},
  "geometry": {"coordinates":[4.9630599022,51.2418136597],"type":"Point"}
}