{
  "type": "Feature",
  "properties": {
    "addr:full":"Diestsevest 23 Leuven Vlaams-Brabant 3000",
    "addr:housenumber":"23",
    "addr:postcode":"3000",
    "addr:street":"Diestsevest",
    "iso:country":"BE",
    "sg:address":"Diestsevest 23",
    "sg:city":"Leuven",
    "sg:classifiers":[
        {
            "category":"Insurance",
            "subcategory":"Insurance Agent",
            "type":"Services"
        }
    ],
    "sg:phone":"+32 16 23 40 40",
    "sg:postcode":"3000",
    "sg:province":"Vlaams-Brabant",
    "sg:tags":[
        "broker"
    ],
    "wof:name":"Verdru G",
    "wof:placetype":"venue"
},
  "geometry": {"coordinates":[4.7133231163,50.8825492859],"type":"Point"}
}