{
  "type": "Feature",
  "properties": {
    "iso:country":"BE",
    "sg:address":"Korte Meer 0",
    "sg:city":"Gent",
    "sg:orig_category":"Services annexes des transports terrestres",
    "sg:phone":"+32 9 223 87 12",
    "sg:postcode":"9000",
    "sg:province":"Oost-Vlaanderen",
    "wof:name":"Parkeergarage Center",
    "wof:placetype":"venue"
},
  "geometry": {"coordinates":[3.7229139805,51.0517539978],"type":"Point"}
}