{
  "type": "Feature",
  "properties": {
    "iso:country":"BE",
    "sg:address":"Rue De La Vesdre 15",
    "sg:city":"Trooz",
    "sg:classifiers":[
        {
            "category":"Arena",
            "subcategory":"Sports Club",
            "type":"Entertainment"
        }
    ],
    "sg:phone":"+32 4 351 64 37",
    "sg:postcode":"4870",
    "sg:province":"Li\u00e8ge",
    "sg:tags":[
        "de"
    ],
    "wof:name":"P.c. Chaudfontaine",
    "wof:placetype":"venue"
},
  "geometry": {"coordinates":[5.6648840904,50.5796165466],"type":"Point"}
}