{
  "type": "Feature",
  "properties": {
    "addr:full":"Brillat-savarinlaan 38 Elsene/ixelles Bruxelles-Capitale 1050",
    "addr:housenumber":"38",
    "addr:postcode":"1050",
    "addr:street":"Brillat-Savarinlaan",
    "iso:country":"BE",
    "sg:address":"Brillat-savarinlaan 38",
    "sg:city":"Elsene/ixelles",
    "sg:orig_category":"Elektrische installaties voor woningen",
    "sg:phone":"+32 2 649 55 98",
    "sg:postcode":"1050",
    "sg:province":"Bruxelles-Capitale",
    "wof:name":"Gevaert",
    "wof:placetype":"venue"
},
  "geometry": {"coordinates":[4.3868942261,50.8167686462],"type":"Point"}
}