{
  "type": "Feature",
  "properties": {
    "iso:country":"BE",
    "sg:address":"Chauss\u00c9e De Bruxelles 71",
    "sg:city":"Wemmel",
    "sg:orig_category":"M\u00e9decines alternatives",
    "sg:phone":"+32 2 460 36 38",
    "sg:postcode":"1780",
    "sg:province":"Vlaams-Brabant",
    "wof:name":"Urbain Jean Yves",
    "wof:placetype":"venue"
},
  "geometry": {"coordinates":[4.3077201843,50.9062614441],"type":"Point"}
}