{
  "type": "Feature",
  "properties": {
    "iso:country":"BE",
    "sg:address":"Chaussee De Marche 511",
    "sg:city":"Erpent",
    "sg:classifiers":[
        {
            "category":"Professional",
            "subcategory":"Credit Reporting & Collection",
            "type":"Services"
        }
    ],
    "sg:phone":"+32 81 30 12 58",
    "sg:postcode":"5101",
    "sg:province":"Namur",
    "sg:tags":[
        "debt",
        "agency"
    ],
    "wof:name":"Fiduciaire Du Sud S.a.",
    "wof:placetype":"venue"
},
  "geometry": {"coordinates":[4.9014492035,50.4444847107],"type":"Point"}
}