{
  "type": "Feature",
  "properties": {
    "iso:country":"BE",
    "sg:address":"8900",
    "sg:city":"Ieper",
    "sg:classifiers":[
        {
            "category":"Health Services",
            "subcategory":"Hospital",
            "type":"Services"
        }
    ],
    "sg:phone":"+32 57 20 82 82",
    "sg:postcode":"8900",
    "sg:province":"West-Vlaanderen",
    "sg:tags":[
        "ambulance"
    ],
    "wof:name":"Ambulance First-care",
    "wof:placetype":"venue"
},
  "geometry": {"coordinates":[2.8933401108,50.8585014343],"type":"Point"}
}