{
  "type": "Feature",
  "properties": {
    "iso:country":"BE",
    "sg:address":"Molenstraat 11",
    "sg:city":"Herentals",
    "sg:classifiers":[
        {
            "category":"Fast Food",
            "type":"Food & Drink"
        }
    ],
    "sg:phone":"+32 14 26 36 15",
    "sg:postcode":"2200",
    "sg:province":"Antwerpen",
    "sg:tags":[
        "meeneem",
        "restaurant"
    ],
    "wof:name":"Hong Kong",
    "wof:placetype":"venue"
},
  "geometry": {"coordinates":[4.8308730125,51.1766967773],"type":"Point"}
}