{
  "type": "Feature",
  "properties": {
    "iso:country":"BE",
    "sg:address":"Slangstraat 11",
    "sg:city":"Hamme",
    "sg:orig_category":"Boekbinderijen and afwerking Drukkerijen and copyshops Krantenuitgeverijen Tijdschriftenuitgeverijen",
    "sg:phone":"+32 52 47 72 32",
    "sg:postcode":"9220",
    "sg:province":"Oost-Vlaanderen",
    "wof:name":"Janssens",
    "wof:placetype":"venue"
},
  "geometry": {"coordinates":[4.1360778809,51.0955886841],"type":"Point"}
}