{
  "type": "Feature",
  "properties": {
    "addr:full":"Rue Vanderkindere 442 Ukkel/uccle Bruxelles-Capitale 1180",
    "addr:housenumber":"442",
    "addr:postcode":"1180",
    "addr:street":"Rue Vanderkindere;/",
    "iso:country":"BE",
    "sg:address":"Rue Vanderkindere 442",
    "sg:city":"Ukkel/uccle",
    "sg:orig_category":"Entretien and r\u00e9parations de voitures. D\u00e9taillants en pi\u00e8ces and accessoires de voitures",
    "sg:phone":"+32 2 345 69 79",
    "sg:postcode":"1180",
    "sg:province":"Bruxelles-Capitale",
    "wof:name":"Midas",
    "wof:placetype":"venue"
},
  "geometry": {"coordinates":[4.3604240417,50.814491272],"type":"Point"}
}