{
  "type": "Feature",
  "properties": {
    "iso:country":"BE",
    "sg:address":"Bistweg 2",
    "sg:city":"Boechout",
    "sg:orig_category":"Biblioth\u00e8ques and archives publiques",
    "sg:phone":"+32 3 460 06 92",
    "sg:postcode":"2530",
    "sg:province":"Antwerpen",
    "wof:name":"Openbare Bibliotheek",
    "wof:placetype":"venue"
},
  "geometry": {"coordinates":[4.4939131737,51.1583442688],"type":"Point"}
}