{
  "type": "Feature",
  "properties": {
    "addr:full":"Statiestraat 42 Ternat Vlaams-Brabant 1740",
    "addr:housenumber":"42",
    "addr:postcode":"1740",
    "addr:street":"Statiestraat",
    "iso:country":"BE",
    "sg:address":"Statiestraat 42",
    "sg:city":"Ternat",
    "sg:orig_category":"S\u00e9curit\u00e9 sociale",
    "sg:phone":"+32 2 582 38 11",
    "sg:postcode":"1740",
    "sg:province":"Vlaams-Brabant",
    "wof:name":"St.michielsbond",
    "wof:placetype":"venue"
},
  "geometry": {"coordinates":[4.1742129326,50.8707008362],"type":"Point"}
}