{
  "type": "Feature",
  "properties": {
    "addr:full":"Kloosterheide 4a Brecht (sint-lenaarts) Antwerpen 2960",
    "addr:housenumber":"4a",
    "addr:postcode":"2960",
    "addr:street":"Kloosterheide",
    "iso:country":"BE",
    "sg:address":"Kloosterheide 4a",
    "sg:city":"Brecht (sint-lenaarts)",
    "sg:classifiers":[
        {
            "category":"Building & Trades",
            "subcategory":"Equipment Rental",
            "type":"Services"
        }
    ],
    "sg:phone":"+32 3 315 18 38",
    "sg:postcode":"2960",
    "sg:province":"Antwerpen",
    "sg:tags":[
        "crane",
        "-"
    ],
    "wof:name":"Agb Donckers Bvba",
    "wof:placetype":"venue"
},
  "geometry": {"coordinates":[4.6415200233,51.3512115479],"type":"Point"}
}