{
  "type": "Feature",
  "properties": {
    "addr:full":"Dennenlaan 63 Antwerpen Antwerpen 2610",
    "addr:housenumber":"63",
    "addr:postcode":"2610",
    "addr:street":"Dennenlaan",
    "iso:country":"BE",
    "sg:address":"Dennenlaan 63",
    "sg:city":"Antwerpen",
    "sg:orig_category":"Kapsalons",
    "sg:phone":"+32 3 827 07 52",
    "sg:postcode":"2610",
    "sg:province":"Antwerpen",
    "wof:name":"Coiffure Pachan",
    "wof:placetype":"venue"
},
  "geometry": {"coordinates":[4.4068617821,51.1744651794],"type":"Point"}
}