{
  "type": "Feature",
  "properties": {
    "addr:full":"Rue Froide Bise 39 Villers-la-ville Brabant Wallon 1495",
    "addr:housenumber":"39",
    "addr:postcode":"1495",
    "addr:street":"Rue Froide Bise",
    "iso:country":"BE",
    "sg:address":"Rue Froide Bise 39",
    "sg:city":"Villers-la-ville",
    "sg:classifiers":[
        {
            "category":"Building & Trades",
            "subcategory":"Landscaping Services",
            "type":"Services"
        }
    ],
    "sg:phone":"+32 71 87 91 54",
    "sg:postcode":"1495",
    "sg:province":"Brabant Wallon",
    "sg:tags":[
        "gardening",
        "garden",
        "maintenance"
    ],
    "wof:name":"Lacroix W",
    "wof:placetype":"venue"
},
  "geometry": {"coordinates":[4.5361418724,50.5741882324],"type":"Point"}
}