{
  "type": "Feature",
  "properties": {
    "iso:country":"BE",
    "sg:address":"De Keyserlei 3-4",
    "sg:city":"Antwerpen",
    "sg:classifiers":[
        {
            "category":"Shopping",
            "subcategory":"Clothing, Apparel, & Fashions",
            "type":"Retail Goods"
        }
    ],
    "sg:phone":"+32 3 232 49 42",
    "sg:postcode":"2018",
    "sg:province":"Antwerpen",
    "sg:tags":[
        "clothing",
        "-",
        "gentleman"
    ],
    "wof:name":"Avenue's Men Shop Bvba",
    "wof:placetype":"venue"
},
  "geometry": {"coordinates":[4.4160628319,51.2180252075],"type":"Point"}
}