{
  "type": "Feature",
  "properties": {
    "iso:country":"BE",
    "sg:address":"Industrieweg 17",
    "sg:city":"Hoogstraten",
    "sg:classifiers":[
        {
            "category":"Manufacturing",
            "subcategory":"Paper Products",
            "type":"Manufacturing & Wholesale Goods"
        }
    ],
    "sg:phone":"+32 3 314 71 20",
    "sg:postcode":"2320",
    "sg:province":"Antwerpen",
    "sg:tags":[
        "packaging",
        "material",
        "-",
        "cardboard"
    ],
    "wof:name":"Kappa Interbox Nv",
    "wof:placetype":"venue"
},
  "geometry": {"coordinates":[4.7343888283,51.3890914917],"type":"Point"}
}