{
  "type": "Feature",
  "properties": {
    "addr:full":"Wulfhoek 8 Nevele Oost-Vlaanderen 9850",
    "addr:housenumber":"8",
    "addr:postcode":"9850",
    "addr:street":"Wulfhoek",
    "iso:country":"BE",
    "sg:address":"Wulfhoek 8",
    "sg:city":"Nevele",
    "sg:orig_category":"Fruitteelt Rundveehouders Varkenskwekers",
    "sg:phone":"+32 9 371 59 63",
    "sg:postcode":"9850",
    "sg:province":"Oost-Vlaanderen",
    "wof:name":"Willy De Vreese",
    "wof:placetype":"venue"
},
  "geometry": {"coordinates":[3.5427238941,51.0532646179],"type":"Point"}
}