{
  "type": "Feature",
  "properties": {
    "iso:country":"BE",
    "sg:address":"Edmond Van Beverenplein 24",
    "sg:city":"Gent-centrum",
    "sg:orig_category":"Avocats and conseillers juridiques. Balie van Gent. Avocats and conseillers juridiques",
    "sg:phone":"+32 9 226 90 54",
    "sg:postcode":"9000",
    "sg:province":"Oost-Vlaanderen",
    "wof:name":"Castelein Karel",
    "wof:placetype":"venue"
},
  "geometry": {"coordinates":[3.710064888,51.0726966858],"type":"Point"}
}