{
  "type": "Feature",
  "properties": {
    "addr:full":"Rue Du G\u00c9n\u00c9ral De Gaulle 75 Courcelles Hainaut 6180",
    "addr:housenumber":"75",
    "addr:postcode":"6180",
    "addr:street":"Rue Du Ge\u0301Ne\u0301Ral De Gaulle",
    "iso:country":"BE",
    "sg:address":"Rue Du G\u00c9n\u00c9ral De Gaulle 75",
    "sg:city":"Courcelles",
    "sg:orig_category":"Pain, p\u00e2tisseries and confiseries",
    "sg:phone":"+32 71 45 17 64",
    "sg:postcode":"6180",
    "sg:province":"Hainaut",
    "wof:name":"P\u00c2tisserie Schamp & Fils",
    "wof:placetype":"venue"
},
  "geometry": {"coordinates":[4.3812761307,50.4565086365],"type":"Point"}
}