{
  "type": "Feature",
  "properties": {
    "addr:full":"Rue De La R\u00e9gence 1 Li\u00e8ge 1 Li\u00e8ge 4000",
    "addr:housenumber":"1;1",
    "addr:postcode":"4000",
    "addr:street":"Rue De La Re\u0301Gence",
    "iso:country":"BE",
    "sg:address":"Rue De La R\u00e9gence 1",
    "sg:city":"Li\u00e8ge 1",
    "sg:classifiers":[
        {
            "category":"Retail",
            "subcategory":"Repair Shop",
            "type":"Services"
        }
    ],
    "sg:phone":"+32 4 222 16 23",
    "sg:postcode":"4000",
    "sg:province":"Li\u00e8ge",
    "sg:tags":[
        "-",
        "mainten",
        "watch",
        "clock"
    ],
    "wof:name":"Kuypers",
    "wof:placetype":"venue"
},
  "geometry": {"coordinates":[5.5727500916,50.6431159973],"type":"Point"}
}