{
  "type": "Feature",
  "properties": {
    "addr:full":"Avenue De La Houssi\u00e8re 76 Braine-le-comte Hainaut 7090",
    "addr:housenumber":"76",
    "addr:postcode":"7090",
    "addr:street":"Avenue De La Houssie\u0300Re",
    "iso:country":"BE",
    "sg:address":"Avenue De La Houssi\u00e8re 76",
    "sg:city":"Braine-le-comte",
    "sg:classifiers":[
        {
            "category":"Social Services",
            "type":"Services"
        }
    ],
    "sg:phone":"+32 67 55 75 75",
    "sg:postcode":"7090",
    "sg:province":"Hainaut",
    "wof:name":"Geb Asbl-maison Du Transit",
    "wof:placetype":"venue"
},
  "geometry": {"coordinates":[4.1508798599,50.6101608276],"type":"Point"}
}