{
  "type": "Feature",
  "properties": {
    "addr:full":"Rue J. B. Stouffs 1 G\u00e9nval Brabant Wallon 1332",
    "addr:housenumber":"1;1332",
    "addr:street":"Rue J. B. Stouffs;Brabant Wallon",
    "iso:country":"BE",
    "sg:address":"Rue J. B. Stouffs 1",
    "sg:city":"G\u00e9nval",
    "sg:classifiers":[
        {
            "category":"Wholesale",
            "subcategory":"Machinery & Supplies",
            "type":"Manufacturing & Wholesale Goods"
        }
    ],
    "sg:phone":"+32 2 356 67 82",
    "sg:postcode":"1332",
    "sg:province":"Brabant Wallon",
    "sg:tags":[
        "food",
        "processing",
        "-",
        "machine",
        "equipment",
        "engineering",
        "mechanical"
    ],
    "wof:name":"Acemal Sa",
    "wof:placetype":"venue"
},
  "geometry": {"coordinates":[4.4990200996,50.7135810852],"type":"Point"}
}