{
  "type": "Feature",
  "properties": {
    "addr:full":"Rue De La Ferme Rose 16 Tubize Brabant Wallon 1480",
    "addr:housenumber":"16",
    "addr:postcode":"1480",
    "addr:street":"Rue De La Ferme Rose;Wallon",
    "iso:country":"BE",
    "sg:address":"Rue De La Ferme Rose 16",
    "sg:city":"Tubize",
    "sg:orig_category":"Reclamebureaus",
    "sg:phone":"+32 2 355 27 11",
    "sg:postcode":"1480",
    "sg:province":"Brabant Wallon",
    "wof:name":"A.t.a.",
    "wof:placetype":"venue"
},
  "geometry": {"coordinates":[4.1885027885,50.6942520142],"type":"Point"}
}