{
  "type": "Feature",
  "properties": {
    "iso:country":"BE",
    "sg:address":"Sint - Gudulastraat 54 Box 2",
    "sg:city":"Aalst",
    "sg:classifiers":[
        {
            "category":"Health Services",
            "subcategory":"Nursing And Care Facility",
            "type":"Services"
        }
    ],
    "sg:phone":"+32 53 70 08 21",
    "sg:postcode":"9300",
    "sg:province":"Oost-Vlaanderen",
    "sg:tags":[
        "home"
    ],
    "wof:name":"Cattoir R",
    "wof:placetype":"venue"
},
  "geometry": {"coordinates":[4.049033165,50.9452171326],"type":"Point"}
}