{
  "type": "Feature",
  "properties": {
    "addr:full":"Rue De La Fontaine 38 Braine-l\u00b4alleud Brabant Wallon 1420",
    "addr:housenumber":"38",
    "addr:postcode":"1420",
    "addr:street":"Rue De La Fontaine;Brabant Wallon",
    "iso:country":"BE",
    "sg:address":"Rue De La Fontaine 38",
    "sg:city":"Braine-l\u00b4alleud",
    "sg:orig_category":"Autoverhuur",
    "sg:phone":"+32 2 387 06 94",
    "sg:postcode":"1420",
    "sg:province":"Brabant Wallon",
    "wof:name":"Fe. Locarolo",
    "wof:placetype":"venue"
},
  "geometry": {"coordinates":[4.3520588875,50.6987533569],"type":"Point"}
}