{
  "type": "Feature",
  "properties": {
    "iso:country":"BE",
    "sg:address":"Dambruggestraat 320",
    "sg:city":"Antwerpen",
    "sg:orig_category":"Quincailleries. Drogueries",
    "sg:phone":"+32 3 225 23 95",
    "sg:postcode":"2060",
    "sg:province":"Antwerpen",
    "wof:name":"Ronny Hendrickx",
    "wof:placetype":"venue"
},
  "geometry": {"coordinates":[4.4216961861,51.2285957336],"type":"Point"}
}