{
  "type": "Feature",
  "properties": {
    "iso:country":"BE",
    "sg:address":"Avenue Jean Brusselmans 12 Box 19",
    "sg:city":"Bruxelles (evere)",
    "sg:classifiers":[
        {
            "category":"Personal",
            "subcategory":"Nail Salon",
            "type":"Services"
        }
    ],
    "sg:phone":"+32 2 705 14 06",
    "sg:postcode":"1140",
    "sg:province":"Bruxelles-Capitale",
    "sg:tags":[
        "pedicure"
    ],
    "wof:name":"Annick",
    "wof:placetype":"venue"
},
  "geometry": {"coordinates":[4.4150300026,50.8595466614],"type":"Point"}
}