{
  "type": "Feature",
  "properties": {
    "iso:country":"BE",
    "sg:address":"Jan Stobbaertslaan 10",
    "sg:city":"Schaarbeek/schaerbeek",
    "sg:orig_category":"Apotheken",
    "sg:phone":"+32 2 241 36 68",
    "sg:postcode":"1030",
    "sg:province":"Bruxelles-Capitale",
    "wof:name":"Pharm.delecluyse-de Visch",
    "wof:placetype":"venue"
},
  "geometry": {"coordinates":[4.3851828575,50.8582649231],"type":"Point"}
}