{
  "type": "Feature",
  "properties": {
    "iso:country":"BE",
    "sg:address":"Vanlaerebekelaan 6",
    "sg:city":"Jabbeke",
    "sg:orig_category":"Industri\u00eble elektrische installaties Spuittoestellen Fab",
    "sg:phone":"+32 50 81 58 81",
    "sg:postcode":"8490",
    "sg:province":"West-Vlaanderen",
    "wof:name":"Domus Electronics",
    "wof:placetype":"venue"
},
  "geometry": {"coordinates":[3.0962760448,51.1864013672],"type":"Point"}
}