{
  "type": "Feature",
  "properties": {
    "iso:country":"BE",
    "sg:address":"Kleine Sint-jansstraat 19",
    "sg:city":"Kortrijk",
    "sg:orig_category":"Industri\u00eble wasserijen and droogkuis Wasserijen, Reiniging and Droogkuis",
    "sg:phone":"+32 56 21 61 37",
    "sg:postcode":"8500",
    "sg:province":"West-Vlaanderen",
    "wof:name":"Press Ex Press",
    "wof:placetype":"venue"
},
  "geometry": {"coordinates":[3.2718069553,50.8264274597],"type":"Point"}
}