{
  "type": "Feature",
  "properties": {
    "iso:country":"BE",
    "sg:address":"Hertjen 116",
    "sg:city":"Sint-niklaas",
    "sg:orig_category":"Imprimeries and copyshops",
    "sg:phone":"+32 3 777 94 05",
    "sg:postcode":"9100",
    "sg:province":"Oost-Vlaanderen",
    "wof:name":"Andre Verheyen",
    "wof:placetype":"venue"
},
  "geometry": {"coordinates":[4.1647639275,51.1561431885],"type":"Point"}
}