{
  "type": "Feature",
  "properties": {
    "addr:full":"Schrijnwerkersstraat 1 Antwerpen Antwerpen 2000",
    "addr:housenumber":"1",
    "addr:postcode":"2000",
    "addr:street":"Schrijnwerkersstraat",
    "iso:country":"BE",
    "sg:address":"Schrijnwerkersstraat 1",
    "sg:city":"Antwerpen",
    "sg:orig_category":"Pain, p\u00e2tisseries and confiseries",
    "sg:phone":"+32 3 231 94 06",
    "sg:postcode":"2000",
    "sg:province":"Antwerpen",
    "wof:name":"Godiva",
    "wof:placetype":"venue"
},
  "geometry": {"coordinates":[4.4038500786,51.2182197571],"type":"Point"}
}