{
  "type": "Feature",
  "properties": {
    "iso:country":"BE",
    "sg:address":"Veneti\u00cblaan 55",
    "sg:city":"Harelbeke",
    "sg:orig_category":"Installatie van houten of kunststof schrijnwerk Plaatsen van vloer- and muurbekleding Schilders Vloe",
    "sg:phone":"+32 56 73 73 11",
    "sg:postcode":"8530",
    "sg:province":"West-Vlaanderen",
    "wof:name":"Lano Project Division",
    "wof:placetype":"venue"
},
  "geometry": {"coordinates":[3.3006150723,50.8317260742],"type":"Point"}
}