{
  "type": "Feature",
  "properties": {
    "addr:full":"Vrijdagmarkt 15 Brugge West-Vlaanderen 8000",
    "addr:housenumber":"15",
    "addr:postcode":"8000",
    "addr:street":"Vrijdagmarkt",
    "iso:country":"BE",
    "sg:address":"Vrijdagmarkt 15",
    "sg:city":"Brugge",
    "sg:classifiers":[
        {
            "category":"Bars & Pubs",
            "type":"Food & Drink"
        }
    ],
    "sg:phone":"+32 50 33 33 40",
    "sg:postcode":"8000",
    "sg:province":"West-Vlaanderen",
    "sg:tags":[
        "tavern"
    ],
    "wof:name":"Brugs Hemeltje",
    "wof:placetype":"venue"
},
  "geometry": {"coordinates":[3.2166650295,51.2054367065],"type":"Point"}
}