{
  "type": "Feature",
  "properties": {
    "addr:full":"Alfred Algoetstraat 17 Lennik Vlaams-Brabant 1750",
    "addr:housenumber":"17;1750",
    "addr:street":"Algoetstraat;Vlaams-Brabant",
    "iso:country":"BE",
    "sg:address":"Alfred Algoetstraat 17",
    "sg:city":"Lennik",
    "sg:orig_category":"Banken and kredietinstellingen",
    "sg:phone":"+32 2 532 56 02",
    "sg:postcode":"1750",
    "sg:province":"Vlaams-Brabant",
    "wof:name":"Kbc",
    "wof:placetype":"venue"
},
  "geometry": {"coordinates":[4.1566181183,50.8057022095],"type":"Point"}
}