{
  "type": "Feature",
  "properties": {
    "addr:full":"Leuvensesteenweg 36 Boortmeerbeek Vlaams-Brabant 3191",
    "addr:housenumber":"36",
    "addr:postcode":"3191",
    "addr:street":"Leuvensesteenweg",
    "iso:country":"BE",
    "sg:address":"Leuvensesteenweg 36",
    "sg:city":"Boortmeerbeek",
    "sg:orig_category":"Articles de jardin",
    "sg:phone":"+32 15 52 80 28",
    "sg:postcode":"3191",
    "sg:province":"Vlaams-Brabant",
    "wof:name":"Andries Garden Center",
    "wof:placetype":"venue"
},
  "geometry": {"coordinates":[4.5349931717,50.992515564],"type":"Point"}
}