{
  "type": "Feature",
  "properties": {
    "addr:full":"Mesesstraat 35 Turnhout Antwerpen 2300",
    "addr:housenumber":"35",
    "addr:postcode":"2300",
    "addr:street":"Mesesstraat",
    "iso:country":"BE",
    "sg:address":"Mesesstraat 35",
    "sg:city":"Turnhout",
    "sg:orig_category":"Artiesten and kunstenaars",
    "sg:phone":"+32 14 41 01 25",
    "sg:postcode":"2300",
    "sg:province":"Antwerpen",
    "wof:name":"Pats Airbrush",
    "wof:placetype":"venue"
},
  "geometry": {"coordinates":[4.951212883,51.331401825],"type":"Point"}
}