{
  "type": "Feature",
  "properties": {
    "addr:full":"Gentsestw 1299 Brussel Bruxelles-Capitale 1082",
    "addr:postcode":"1299;1082",
    "iso:country":"BE",
    "sg:address":"Gentsestw 1299",
    "sg:city":"Brussel",
    "sg:classifiers":[
        {
            "category":"Shopping",
            "subcategory":"Crafts & Fabrics",
            "type":"Retail Goods"
        }
    ],
    "sg:phone":"+32 2 465 74 02",
    "sg:postcode":"1082",
    "sg:province":"Bruxelles-Capitale",
    "sg:tags":[
        "textile",
        "clothing"
    ],
    "wof:name":"Nostex Nv",
    "wof:placetype":"venue"
},
  "geometry": {"coordinates":[4.2927818298,50.8689537048],"type":"Point"}
}