{
  "type": "Feature",
  "properties": {
    "addr:full":"Ooststraat 46 Veurne West-Vlaanderen 8630",
    "addr:housenumber":"46",
    "addr:postcode":"8630",
    "addr:street":"Ooststraat",
    "iso:country":"BE",
    "sg:address":"Ooststraat 46",
    "sg:city":"Veurne",
    "sg:classifiers":[
        {
            "category":"Farming",
            "subcategory":"Fish & Marine Products",
            "type":"Manufacturing & Wholesale Goods"
        }
    ],
    "sg:phone":"+32 58 28 75 95",
    "sg:postcode":"8630",
    "sg:province":"West-Vlaanderen",
    "sg:tags":[
        "retail",
        "-",
        "shellfish"
    ],
    "wof:name":"Koraal (de)",
    "wof:placetype":"venue"
},
  "geometry": {"coordinates":[2.664798975,51.0729637146],"type":"Point"}
}