{
  "type": "Feature",
  "properties": {
    "addr:full":"Kortrijksestraat 11 Ardooie West-Vlaanderen 8850",
    "addr:housenumber":"11",
    "addr:postcode":"8850",
    "addr:street":"Kortrijksestraat",
    "iso:country":"BE",
    "sg:address":"Kortrijksestraat 11",
    "sg:city":"Ardooie",
    "sg:orig_category":"Verplichte sociale verzekeringen",
    "sg:phone":"+32 51 74 81 35",
    "sg:postcode":"8850",
    "sg:province":"West-Vlaanderen",
    "wof:name":"Onafhankelijk Ziekenfonds",
    "wof:placetype":"venue"
},
  "geometry": {"coordinates":[3.1981461048,50.9778862],"type":"Point"}
}