{
  "type": "Feature",
  "properties": {
    "iso:country":"BE",
    "sg:address":"Lerrekensstraat 32 B",
    "sg:city":"Heist-op-den-berg",
    "sg:orig_category":"Miscellaneous Products",
    "sg:phone":"+32 15 24 55 55",
    "sg:postcode":"2220",
    "sg:province":"Antwerpen",
    "wof:name":"Luxbross Nv",
    "wof:placetype":"venue"
},
  "geometry": {"coordinates":[4.7044901848,51.0603027344],"type":"Point"}
}