{
  "type": "Feature",
  "properties": {
    "iso:country":"BE",
    "sg:address":"Driftweg 177",
    "sg:city":"Bredene",
    "sg:orig_category":"Kapsalons",
    "sg:phone":"+32 59 32 47 32",
    "sg:postcode":"8450",
    "sg:province":"West-Vlaanderen",
    "wof:name":"Coiffure Lorna",
    "wof:placetype":"venue"
},
  "geometry": {"coordinates":[2.958812952,51.246723175],"type":"Point"}
}