{
  "type": "Feature",
  "properties": {
    "iso:country":"BE",
    "sg:address":"Rue Dandois 106",
    "sg:city":"Charleroi",
    "sg:orig_category":"Forge, Moulage and Profilage des M\u00e9taux",
    "sg:phone":"+32 71 34 21 35",
    "sg:postcode":"6043",
    "sg:province":"Hainaut",
    "wof:name":"Claudio Battistelli",
    "wof:placetype":"venue"
},
  "geometry": {"coordinates":[4.4839549065,50.4479637146],"type":"Point"}
}