{
  "type": "Feature",
  "properties": {
    "iso:country":"BE",
    "sg:address":"Frederik Burvenichstraat 13",
    "sg:city":"Gent",
    "sg:orig_category":"Herstelling horloges and juwelen Juwelen and horloges",
    "sg:phone":"+32 9 230 80 20",
    "sg:postcode":"9050",
    "sg:province":"Oost-Vlaanderen",
    "wof:name":"Huis Doolaege",
    "wof:placetype":"venue"
},
  "geometry": {"coordinates":[3.7471549511,51.0390434265],"type":"Point"}
}