{
  "type": "Feature",
  "properties": {
    "addr:full":"Beurtkaai Roeselare West-Vlaanderen 8800",
    "addr:postcode":"8800",
    "addr:street":"West-Vlaanderen",
    "iso:country":"BE",
    "sg:address":"Beurtkaai",
    "sg:city":"Roeselare",
    "sg:orig_category":"Watersport-, Sport- and Kampeerbenodigdheden Verhuur",
    "sg:phone":"+32 51 20 16 37",
    "sg:postcode":"8800",
    "sg:province":"West-Vlaanderen",
    "wof:name":"Atlantis",
    "wof:placetype":"venue"
},
  "geometry": {"coordinates":[3.1513750553,50.9461593628],"type":"Point"}
}