{
  "type": "Feature",
  "properties": {
    "iso:country":"BE",
    "sg:address":"Rue De L'arsenal 57",
    "sg:city":"Pont-\u00e0-celles",
    "sg:classifiers":[
        {
            "category":"Health Services",
            "subcategory":"Health Practitioner",
            "type":"Services"
        }
    ],
    "sg:phone":"+32 477 32 47 18",
    "sg:postcode":"6230",
    "sg:province":"Hainaut",
    "sg:tags":[
        "physiotherapist"
    ],
    "wof:name":"Fauquez C",
    "wof:placetype":"venue"
},
  "geometry": {"coordinates":[4.3833608627,50.5038986206],"type":"Point"}
}