{
  "type": "Feature",
  "properties": {
    "addr:full":"Heuvelstraat 24 Hoogstraten Antwerpen 2320",
    "addr:housenumber":"24",
    "addr:postcode":"2320",
    "addr:street":"Heuvelstraat",
    "iso:country":"BE",
    "sg:address":"Heuvelstraat 24",
    "sg:city":"Hoogstraten",
    "sg:orig_category":"Eleveurs and marchands de porcs",
    "sg:phone":"+32 3 314 77 61",
    "sg:postcode":"2320",
    "sg:province":"Antwerpen",
    "wof:name":"Jozef Schrauwen",
    "wof:placetype":"venue"
},
  "geometry": {"coordinates":[4.7417330742,51.3913459778],"type":"Point"}
}