{
  "type": "Feature",
  "properties": {
    "iso:country":"BE",
    "sg:address":"Lindestraat 21",
    "sg:city":"Alveringem (beveren-aan-de-ijzer)",
    "sg:classifiers":[
        {
            "category":"Bars & Pubs",
            "type":"Food & Drink"
        }
    ],
    "sg:phone":"+32 57 30 00 03",
    "sg:postcode":"8691",
    "sg:province":"West-Vlaanderen",
    "wof:name":"Kruisstraat (de)",
    "wof:placetype":"venue"
},
  "geometry": {"coordinates":[2.666574955,50.9520263672],"type":"Point"}
}