{
  "type": "Feature",
  "properties": {
    "iso:country":"BE",
    "sg:address":"Rue Du Tige De Moxhe 10a",
    "sg:city":"Hannut (avin)",
    "sg:classifiers":[
        {
            "category":"Retail",
            "subcategory":"Repair Shop",
            "type":"Services"
        }
    ],
    "sg:phone":"+32 19 69 95 35",
    "sg:postcode":"4280",
    "sg:province":"Li\u00e8ge",
    "sg:tags":[
        "radio",
        "television",
        "-",
        "maintenance"
    ],
    "wof:name":"Wautelet F",
    "wof:placetype":"venue"
},
  "geometry": {"coordinates":[5.078950882,50.6262321472],"type":"Point"}
}