{
  "type": "Feature",
  "properties": {
    "addr:full":"Huybergsebaan 80 Essen Antwerpen 2910",
    "addr:housenumber":"80",
    "addr:postcode":"2910",
    "addr:street":"Huybergsebaan",
    "iso:country":"BE",
    "sg:address":"Huybergsebaan 80",
    "sg:city":"Essen",
    "sg:classifiers":[
        {
            "category":"Autos & Motor Vehicles",
            "subcategory":"Recreational Vehicle Sales",
            "type":"Retail Goods"
        }
    ],
    "sg:phone":"+32 3 667 36 35",
    "sg:postcode":"2910",
    "sg:province":"Antwerpen",
    "sg:tags":[
        "saw"
    ],
    "wof:name":"Aerden Willy Bvba",
    "wof:placetype":"venue"
},
  "geometry": {"coordinates":[4.4236001968,51.4282913208],"type":"Point"}
}