{
  "type": "Feature",
  "properties": {
    "iso:country":"BE",
    "sg:address":"Rue De L'arbre B\u00c9nit 127",
    "sg:city":"Elsene/ixelles",
    "sg:orig_category":"Artistes ind\u00e9pendants",
    "sg:phone":"+32 2 647 20 72",
    "sg:postcode":"1050",
    "sg:province":"Bruxelles-Capitale",
    "wof:name":"Alessandro Filippini",
    "wof:placetype":"venue"
},
  "geometry": {"coordinates":[4.3638558388,50.8302955627],"type":"Point"}
}