{
  "type": "Feature",
  "properties": {
    "addr:full":"Jan Van Rijswijcklaan 24 Antwerpen Antwerpen 2018",
    "addr:housenumber":"24",
    "addr:postcode":"2018",
    "addr:street":"Jan Van Rijswijcklaan",
    "iso:country":"BE",
    "sg:address":"Jan Van Rijswijcklaan 24",
    "sg:city":"Antwerpen",
    "sg:classifiers":[
        {
            "category":"Professional",
            "subcategory":"Lawyer & Legal Services",
            "type":"Services"
        }
    ],
    "sg:phone":"+32 3 216 27 36",
    "sg:postcode":"2018",
    "sg:province":"Antwerpen",
    "sg:tags":[
        "notary"
    ],
    "wof:name":"Van Nuffel M",
    "wof:placetype":"venue"
},
  "geometry": {"coordinates":[4.4086380005,51.198009491],"type":"Point"}
}