{
  "type": "Feature",
  "properties": {
    "iso:country":"BE",
    "sg:address":"Sanderusstraat 26",
    "sg:city":"Antwerpen",
    "sg:classifiers":[
        {
            "category":"Wholesale",
            "subcategory":"Construction Materials",
            "type":"Manufacturing & Wholesale Goods"
        }
    ],
    "sg:phone":"+32 3 238 98 54",
    "sg:postcode":"2018",
    "sg:province":"Antwerpen",
    "sg:tags":[
        "bandaging",
        "materials",
        "dressing"
    ],
    "wof:name":"Greco Nv",
    "wof:placetype":"venue"
},
  "geometry": {"coordinates":[4.4053030014,51.2082061768],"type":"Point"}
}