{
  "type": "Feature",
  "properties": {
    "addr:full":"Rue Du Vieux Sourdiau 37 Binche Hainaut 7130",
    "addr:housenumber":"37",
    "addr:postcode":"7130",
    "addr:street":"Rue Du Vieux Sourdiau",
    "iso:country":"BE",
    "sg:address":"Rue Du Vieux Sourdiau 37",
    "sg:city":"Binche",
    "sg:orig_category":"Traitements param\u00e9dicaux",
    "sg:phone":"+32 64 37 05 87",
    "sg:postcode":"7130",
    "sg:province":"Hainaut",
    "wof:name":"Annabel Debaise",
    "wof:placetype":"venue"
},
  "geometry": {"coordinates":[4.1704149246,50.4112167358],"type":"Point"}
}