{
  "type": "Feature",
  "properties": {
    "addr:full":"Huisblokken 39 Balen Antwerpen 2490",
    "addr:housenumber":"39",
    "addr:postcode":"2490",
    "addr:street":"Huisblokken",
    "iso:country":"BE",
    "sg:address":"Huisblokken 39",
    "sg:city":"Balen",
    "sg:classifiers":[
        {
            "category":"Utilities",
            "subcategory":"Water",
            "type":"Services"
        }
    ],
    "sg:phone":"+32 476 53 23 80",
    "sg:postcode":"2490",
    "sg:province":"Antwerpen",
    "sg:tags":[
        "purification"
    ],
    "wof:name":"Bio Waterrecycling Technology",
    "wof:placetype":"venue"
},
  "geometry": {"coordinates":[5.1680059433,51.1709327698],"type":"Point"}
}