{
  "type": "Feature",
  "properties": {
    "iso:country":"BE",
    "sg:address":"Nieuwe Molenstraat 118",
    "sg:city":"Sint-niklaas",
    "sg:orig_category":"Domotics",
    "sg:phone":"+32 3 778 18 27",
    "sg:postcode":"9100",
    "sg:province":"Oost-Vlaanderen",
    "wof:name":"Smet Kamiel Elektro Nv",
    "wof:placetype":"venue"
},
  "geometry": {"coordinates":[4.1564850807,51.1737480164],"type":"Point"}
}