{
  "type": "Feature",
  "properties": {
    "iso:country":"BE",
    "sg:address":"Av Des Arts 20",
    "sg:city":"Bruxelles",
    "sg:classifiers":[
        {
            "category":"Professional",
            "subcategory":"Business Services",
            "type":"Services"
        }
    ],
    "sg:phone":"+32 2 230 59 70",
    "sg:postcode":"1000",
    "sg:province":"Bruxelles-Capitale",
    "sg:tags":[
        "body",
        "advice"
    ],
    "wof:name":"Comite Belge Pour L'unicef",
    "wof:placetype":"venue"
},
  "geometry": {"coordinates":[4.3693652153,50.8462715149],"type":"Point"}
}