{
  "type": "Feature",
  "properties": {
    "iso:country":"BE",
    "sg:address":"Molenweg 109",
    "sg:city":"Willebroek",
    "sg:orig_category":"Apparatus, Containers, Tanks, Boilers, High-Pressure",
    "sg:phone":"+32 3 860 20 11",
    "sg:postcode":"2830",
    "sg:province":"Antwerpen",
    "wof:name":"G&g International Nv",
    "wof:placetype":"venue"
},
  "geometry": {"coordinates":[4.3631439209,51.048248291],"type":"Point"}
}