{
  "type": "Feature",
  "properties": {
    "addr:full":"Rue Beussart 42 Villers-la-ville (marbais) Brabant Wallon 1495",
    "addr:housenumber":"42",
    "addr:postcode":"1495",
    "addr:street":"Rue Beussart",
    "iso:country":"BE",
    "sg:address":"Rue Beussart 42",
    "sg:city":"Villers-la-ville (marbais)",
    "sg:classifiers":[
        {
            "category":"Health Services",
            "subcategory":"Health Practitioner",
            "type":"Services"
        }
    ],
    "sg:phone":"+32 71 87 47 33",
    "sg:postcode":"1495",
    "sg:province":"Brabant Wallon",
    "sg:tags":[
        "psychologist"
    ],
    "wof:name":"Ballon V\u00e9ronique",
    "wof:placetype":"venue"
},
  "geometry": {"coordinates":[4.530477047,50.5786132812],"type":"Point"}
}