{
  "type": "Feature",
  "properties": {
    "iso:country":"BE",
    "sg:address":"Battelsesteenweg 493",
    "sg:city":"Mechelen",
    "sg:orig_category":"Brood, gebak and snoepgoed",
    "sg:phone":"+32 15 27 20 60",
    "sg:postcode":"2800",
    "sg:province":"Antwerpen",
    "wof:name":"Monique Staal",
    "wof:placetype":"venue"
},
  "geometry": {"coordinates":[4.4493598938,51.0387191772],"type":"Point"}
}