{
  "type": "Feature",
  "properties": {
    "iso:country":"BE",
    "sg:address":"Prins Albertlaan 76",
    "sg:city":"Oostende",
    "sg:classifiers":[
        {
            "category":"Health Services",
            "subcategory":"Health Practitioner",
            "type":"Services"
        }
    ],
    "sg:phone":"+32 59 32 11 86",
    "sg:postcode":"8400",
    "sg:province":"West-Vlaanderen",
    "sg:tags":[
        "physiotherapist"
    ],
    "wof:name":"Debaene L",
    "wof:placetype":"venue"
},
  "geometry": {"coordinates":[2.9484729767,51.2216949463],"type":"Point"}
}