{
  "type": "Feature",
  "properties": {
    "addr:full":"Luzery 13a Bastogne (noville) Luxembourg 6600",
    "addr:housenumber":"13a",
    "addr:postcode":"6600",
    "addr:street":"Luzery",
    "iso:country":"BE",
    "sg:address":"Luzery 13a",
    "sg:city":"Bastogne (noville)",
    "sg:classifiers":[
        {
            "category":"Banks & Credit Unions",
            "subcategory":"Investment Brokerage",
            "type":"Services"
        }
    ],
    "sg:phone":"+32 61 21 02 40",
    "sg:postcode":"6600",
    "sg:province":"Luxembourg",
    "sg:tags":[
        "printing",
        "-"
    ],
    "wof:name":"Imprimerie Schmitz & Gofflot Sprl",
    "wof:placetype":"venue"
},
  "geometry": {"coordinates":[5.724668026,50.0147132874],"type":"Point"}
}