{
  "type": "Feature",
  "properties": {
    "iso:country":"BE",
    "sg:address":"Wissenstraat 24",
    "sg:city":"Dendermonde (sint-gillis-bij-dendermonde)",
    "sg:classifiers":[
        {
            "category":"Ferry Terminal",
            "type":"Transportation"
        }
    ],
    "sg:phone":"+32 52 25 99 10",
    "sg:postcode":"9200",
    "sg:province":"Oost-Vlaanderen",
    "sg:tags":[
        "mast",
        "pylon"
    ],
    "wof:name":"Armamast Nv",
    "wof:placetype":"venue"
},
  "geometry": {"coordinates":[4.147195816,51.0261535645],"type":"Point"}
}