{
  "type": "Feature",
  "properties": {
    "iso:country":"BE",
    "sg:address":"Bois Notre-dame 26",
    "sg:city":"Marche-en-famenne",
    "sg:classifiers":[
        {
            "category":"Health Services",
            "subcategory":"Doctor",
            "type":"Services"
        }
    ],
    "sg:phone":"+32 84 31 47 09",
    "sg:postcode":"6900",
    "sg:province":"Luxembourg",
    "sg:tags":[
        "medicinephysicians",
        "surgeon"
    ],
    "wof:name":"Dubuc J-e",
    "wof:placetype":"venue"
},
  "geometry": {"coordinates":[5.3283309937,50.2265548706],"type":"Point"}
}