{
  "type": "Feature",
  "properties": {
    "iso:country":"BE",
    "sg:address":"Place Sainte-barbe 2",
    "sg:city":"Ottignies-louvain-la-neuve",
    "sg:orig_category":"Enseignement sup\u00e9rieur",
    "sg:phone":"+32 10 47 31 50",
    "sg:postcode":"1348",
    "sg:province":"Brabant Wallon",
    "wof:name":"U.c.l.-d\u00c9partement Ingi",
    "wof:placetype":"venue"
},
  "geometry": {"coordinates":[4.6218490601,50.6686096191],"type":"Point"}
}