{
  "type": "Feature",
  "properties": {
    "addr:full":"Rue De L'industrie 12 Nivelles Brabant Wallon 1400",
    "addr:housenumber":"12",
    "addr:postcode":"1400",
    "addr:street":"Rue De L'Industrie",
    "iso:country":"BE",
    "sg:address":"Rue De L'industrie 12",
    "sg:city":"Nivelles",
    "sg:classifiers":[
        {
            "category":"Shopping",
            "subcategory":"Stationery & Office Supplies",
            "type":"Retail Goods"
        }
    ],
    "sg:phone":"+32 67 28 76 11",
    "sg:postcode":"1400",
    "sg:province":"Brabant Wallon",
    "sg:tags":[
        "adhesive",
        "label"
    ],
    "wof:name":"Alfac S.a.",
    "wof:placetype":"venue"
},
  "geometry": {"coordinates":[4.3582730293,50.5919532776],"type":"Point"}
}