{
  "type": "Feature",
  "properties": {
    "addr:full":"Geralaan Brugge (sint-kruis) West-Vlaanderen 8310",
    "addr:postcode":"8310",
    "addr:street":"Geralaan",
    "iso:country":"BE",
    "sg:address":"Geralaan",
    "sg:city":"Brugge (sint-kruis)",
    "sg:classifiers":[
        {
            "category":"Arena",
            "subcategory":"Sports Club",
            "type":"Entertainment"
        }
    ],
    "sg:phone":"+32 50 33 39 15",
    "sg:postcode":"8310",
    "sg:province":"West-Vlaanderen",
    "wof:name":"Cerkelladies Brugge",
    "wof:placetype":"venue"
},
  "geometry": {"coordinates":[3.2452750206,51.2189216614],"type":"Point"}
}