{
  "type": "Feature",
  "properties": {
    "iso:country":"BE",
    "sg:address":"Stationsplein 18",
    "sg:city":"Lokeren",
    "sg:orig_category":"Agents artistiques",
    "sg:phone":"+32 9 348 15 33",
    "sg:postcode":"9160",
    "sg:province":"Oost-Vlaanderen",
    "wof:name":"Ozma Music Ware",
    "wof:placetype":"venue"
},
  "geometry": {"coordinates":[3.9885230064,51.1077384949],"type":"Point"}
}