{
  "type": "Feature",
  "properties": {
    "addr:full":"Mechelsesteenweg 33 Hove Antwerpen 2540",
    "addr:housenumber":"33",
    "addr:postcode":"2540",
    "addr:street":"Mechelsesteenweg",
    "iso:country":"BE",
    "sg:address":"Mechelsesteenweg 33",
    "sg:city":"Hove",
    "sg:orig_category":"Agences de publicit\u00e9",
    "sg:phone":"+32 3 454 13 82",
    "sg:postcode":"2540",
    "sg:province":"Antwerpen",
    "wof:name":"Bavaco Lettering",
    "wof:placetype":"venue"
},
  "geometry": {"coordinates":[4.4639320374,51.1481208801],"type":"Point"}
}