{
  "type": "Feature",
  "properties": {
    "addr:full":"Hijfte-center 31 Lochristi Oost-Vlaanderen 9080",
    "addr:housenumber":"31",
    "addr:postcode":"9080",
    "addr:street":"Hijfte-Center",
    "iso:country":"BE",
    "sg:address":"Hijfte-center 31",
    "sg:city":"Lochristi",
    "sg:classifiers":[
        {
            "category":"Cafe",
            "type":"Food & Drink"
        }
    ],
    "sg:phone":"+32 9 355 05 73",
    "sg:postcode":"9080",
    "sg:province":"Oost-Vlaanderen",
    "sg:tags":[
        "caf\u00e9s"
    ],
    "wof:name":"Caf\u00c9 Center",
    "wof:placetype":"venue"
},
  "geometry": {"coordinates":[3.8093531132,51.1106147766],"type":"Point"}
}