{
  "type": "Feature",
  "properties": {
    "addr:full":"Heilige Geeststraat 1 Brugge West-Vlaanderen 8000",
    "addr:housenumber":"1",
    "addr:postcode":"8000",
    "addr:street":"Heilige Geeststraat",
    "iso:country":"BE",
    "sg:address":"Heilige Geeststraat 1",
    "sg:city":"Brugge",
    "sg:classifiers":[
        {
            "category":"Travel",
            "subcategory":"Hotels & Motels",
            "type":"Entertainment"
        }
    ],
    "sg:phone":"+32 50 34 30 01",
    "sg:postcode":"8000",
    "sg:province":"West-Vlaanderen",
    "sg:tags":[
        "restaurant"
    ],
    "wof:name":"De Castillion",
    "wof:placetype":"venue"
},
  "geometry": {"coordinates":[3.2223830223,51.2053413391],"type":"Point"}
}