{
  "type": "Feature",
  "properties": {
    "addr:full":"Luitenant Philippartstraat 20 Steenokkerzeel (melsbroek) Vlaams-Brabant 1820",
    "addr:housenumber":"20",
    "addr:postcode":"1820",
    "addr:street":"Luitenant Philippartstraat",
    "iso:country":"BE",
    "sg:address":"Luitenant Philippartstraat 20",
    "sg:city":"Steenokkerzeel (melsbroek)",
    "sg:classifiers":[
        {
            "category":"Bakery",
            "type":"Food & Drink"
        }
    ],
    "sg:phone":"+32 2 751 42 91",
    "sg:postcode":"1820",
    "sg:province":"Vlaams-Brabant",
    "sg:tags":[
        "confectioner",
        "baker"
    ],
    "wof:name":"Fred",
    "wof:placetype":"venue"
},
  "geometry": {"coordinates":[4.4755849838,50.9109916687],"type":"Point"}
}