{
  "type": "Feature",
  "properties": {
    "addr:full":"Rue Augustin Delporte 4 Elsene/ixelles Bruxelles-Capitale 1050",
    "addr:housenumber":"4",
    "addr:postcode":"1050",
    "addr:street":"Rue Augustin Delporte",
    "iso:country":"BE",
    "sg:address":"Rue Augustin Delporte 4",
    "sg:city":"Elsene/ixelles",
    "sg:orig_category":"Evaluation and estimation de biens immobiliers. Agences immobili\u00e8res",
    "sg:phone":"+32 2 649 24 81",
    "sg:postcode":"1050",
    "sg:province":"Bruxelles-Capitale",
    "wof:name":"Jean Roberti",
    "wof:placetype":"venue"
},
  "geometry": {"coordinates":[4.3847951889,50.8246688843],"type":"Point"}
}