{
  "type": "Feature",
  "properties": {
    "iso:country":"BE",
    "sg:address":"Herentalsebaan 618",
    "sg:city":"Wommelgem",
    "sg:orig_category":"Textiles divers Fab. V\u00eatements, chaussures and accessoires Gr",
    "sg:phone":"+32 3 354 27 29",
    "sg:postcode":"2160",
    "sg:province":"Antwerpen",
    "wof:name":"Top Logo",
    "wof:placetype":"venue"
},
  "geometry": {"coordinates":[4.5188679695,51.1976203918],"type":"Point"}
}