{
  "type": "Feature",
  "properties": {
    "addr:full":"Stationsstraat 77 Ledegem West-Vlaanderen 8880",
    "addr:housenumber":"77",
    "addr:postcode":"8880",
    "addr:street":"Stationsstraat",
    "iso:country":"BE",
    "sg:address":"Stationsstraat 77",
    "sg:city":"Ledegem",
    "sg:orig_category":"S\u00e9curit\u00e9 sociale",
    "sg:phone":"+32 56 50 37 74",
    "sg:postcode":"8880",
    "sg:province":"West-Vlaanderen",
    "wof:name":"Christelijke Mutualiteit",
    "wof:placetype":"venue"
},
  "geometry": {"coordinates":[3.1224200726,50.8566589355],"type":"Point"}
}