{
  "type": "Feature",
  "properties": {
    "iso:country":"BE",
    "sg:address":"Place Roi-albert-ier 21",
    "sg:city":"Rochefort",
    "sg:orig_category":"Catering and organisation de f\u00eates. Restaurants fast food and \u00e0 emporter. Restaurants. H\u00f4tels",
    "sg:phone":"+32 84 21 10 36",
    "sg:postcode":"5580",
    "sg:province":"Namur",
    "wof:name":"Le Limbourg",
    "wof:placetype":"venue"
},
  "geometry": {"coordinates":[5.2231411934,50.1583595276],"type":"Point"}
}