{
  "type": "Feature",
  "properties": {
    "iso:country":"BE",
    "sg:address":"Chemin De L'ardoisier",
    "sg:city":"Soignies",
    "sg:classifiers":[
        {
            "category":"Social Services",
            "subcategory":"Job Training",
            "type":"Services"
        }
    ],
    "sg:phone":"+32 67 33 22 98",
    "sg:postcode":"7060",
    "sg:province":"Hainaut",
    "sg:tags":[
        "de",
        "terrain",
        "camping"
    ],
    "wof:name":"P\u00c9che Petite Irlande",
    "wof:placetype":"venue"
},
  "geometry": {"coordinates":[4.0202550888,50.5997009277],"type":"Point"}
}