{
  "type": "Feature",
  "properties": {
    "iso:country":"BE",
    "sg:address":"Rue De Marchienne 76",
    "sg:city":"Montigny-le-tilleul",
    "sg:orig_category":"Installatie van houten of kunststof schrijnwerk Woningbouw",
    "sg:phone":"+32 71 51 02 19",
    "sg:postcode":"6110",
    "sg:province":"Hainaut",
    "wof:name":"A.f. Construct",
    "wof:placetype":"venue"
},
  "geometry": {"coordinates":[4.380833149,50.382068634],"type":"Point"}
}