{
  "type": "Feature",
  "properties": {
    "addr:full":"Ploegstraat 10 Retie Antwerpen 2470",
    "addr:housenumber":"10",
    "addr:postcode":"2470",
    "addr:street":"Ploegstraat",
    "iso:country":"BE",
    "sg:address":"Ploegstraat 10",
    "sg:city":"Retie",
    "sg:orig_category":"Woningbouw",
    "sg:phone":"+32 14 37 85 59",
    "sg:postcode":"2470",
    "sg:province":"Antwerpen",
    "wof:name":"De Bruyn Hugo",
    "wof:placetype":"venue"
},
  "geometry": {"coordinates":[5.0825572014,51.2660865784],"type":"Point"}
}