{
  "type": "Feature",
  "properties": {
    "iso:country":"BE",
    "sg:address":"Rotterdamstraat 33",
    "sg:city":"Antwerpen",
    "sg:classifiers":[
        {
            "category":"Professional",
            "subcategory":"Detective & Security Services",
            "type":"Services"
        }
    ],
    "sg:phone":"+32 3 229 18 40",
    "sg:postcode":"2060",
    "sg:province":"Antwerpen",
    "sg:tags":[
        "access-control",
        "system"
    ],
    "wof:name":"Lt Advice Nv",
    "wof:placetype":"venue"
},
  "geometry": {"coordinates":[4.4187779427,51.2239456177],"type":"Point"}
}