{
  "type": "Feature",
  "properties": {
    "addr:full":"Monseigneur Ladeuzeplein 32 Leuven Vlaams-Brabant 3000",
    "addr:housenumber":"32",
    "addr:postcode":"3000",
    "addr:street":"Monseigneur Ladeuzeplein",
    "iso:country":"BE",
    "sg:address":"Monseigneur Ladeuzeplein 32",
    "sg:city":"Leuven",
    "sg:classifiers":[
        {
            "category":"Food & Beverages",
            "subcategory":"Fruits & Vegetables",
            "type":"Retail Goods"
        }
    ],
    "sg:phone":"+32 16 22 81 84",
    "sg:postcode":"3000",
    "sg:province":"Vlaams-Brabant",
    "sg:tags":[
        "-"
    ],
    "wof:name":"Primeurs Demeyer",
    "wof:placetype":"venue"
},
  "geometry": {"coordinates":[4.7056341171,50.8782806396],"type":"Point"}
}