{
  "type": "Feature",
  "properties": {
    "addr:full":"Vredelaan 134 Houthalen-helchteren Limburg 3530",
    "addr:housenumber":"134",
    "addr:postcode":"3530",
    "addr:street":"Vredelaan",
    "iso:country":"BE",
    "sg:address":"Vredelaan 134",
    "sg:city":"Houthalen-helchteren",
    "sg:orig_category":"Schoenen",
    "sg:phone":"+32 11 60 53 10",
    "sg:postcode":"3530",
    "sg:province":"Limburg",
    "wof:name":"Brantano",
    "wof:placetype":"venue"
},
  "geometry": {"coordinates":[5.3749299049,51.0319519043],"type":"Point"}
}