{
  "type": "Feature",
  "properties": {
    "addr:full":"Wingerstraat 30 Tielt-winge Vlaams-Brabant 3390",
    "addr:housenumber":"30",
    "addr:postcode":"3390",
    "addr:street":"Wingerstraat",
    "iso:country":"BE",
    "sg:address":"Wingerstraat 30",
    "sg:city":"Tielt-winge",
    "sg:orig_category":"Film-, tv- and videoproductie",
    "sg:phone":"+32 16 64 08 72",
    "sg:postcode":"3390",
    "sg:province":"Vlaams-Brabant",
    "wof:name":"Video Prodockxions",
    "wof:placetype":"venue"
},
  "geometry": {"coordinates":[4.876458168,50.914981842],"type":"Point"}
}