{
  "type": "Feature",
  "properties": {
    "addr:full":"Rue Des Bois 31 Rumes Hainaut 7618",
    "addr:housenumber":"31",
    "addr:postcode":"7618",
    "addr:street":"Rue Des Bois",
    "iso:country":"BE",
    "sg:address":"Rue Des Bois 31",
    "sg:city":"Rumes",
    "sg:orig_category":"Enseignement maternel and primaire",
    "sg:phone":"+32 69 64 88 92",
    "sg:postcode":"7618",
    "sg:province":"Hainaut",
    "wof:name":"Ecole Fondamentale",
    "wof:placetype":"venue"
},
  "geometry": {"coordinates":[3.3408849239,50.5473861694],"type":"Point"}
}