{
  "type": "Feature",
  "properties": {
    "iso:country":"BE",
    "sg:address":"Vieille Rue Du Moulin 205",
    "sg:city":"Ukkel/uccle",
    "sg:classifiers":[
        {
            "category":"Recreation",
            "type":"Entertainment"
        }
    ],
    "sg:phone":"+32 2 375 14 61",
    "sg:postcode":"1180",
    "sg:province":"Bruxelles-Capitale",
    "sg:tags":[
        "diver",
        "amusement"
    ],
    "wof:name":"Maurice Le Gaulois",
    "wof:placetype":"venue"
},
  "geometry": {"coordinates":[4.3686761856,50.7900009155],"type":"Point"}
}