{
  "type": "Feature",
  "properties": {
    "addr:full":"Casinostraat 3a Sint-niklaas Oost-Vlaanderen 9100",
    "addr:housenumber":"3a",
    "addr:postcode":"9100",
    "addr:street":"Casinostraat",
    "iso:country":"BE",
    "sg:address":"Casinostraat 3a",
    "sg:city":"Sint-niklaas",
    "sg:classifiers":[
        {
            "category":"Building & Trades",
            "subcategory":"Construction",
            "type":"Services"
        }
    ],
    "sg:phone":"+32 3 776 20 90",
    "sg:postcode":"9100",
    "sg:province":"Oost-Vlaanderen",
    "sg:tags":[
        "truss-makers"
    ],
    "wof:name":"Medizi Bvba",
    "wof:placetype":"venue"
},
  "geometry": {"coordinates":[4.1417517662,51.1686210632],"type":"Point"}
}