{
  "type": "Feature",
  "properties": {
    "addr:full":"Boeschepestraat 92 Poperinge West-Vlaanderen 8970",
    "addr:housenumber":"92",
    "addr:postcode":"8970",
    "addr:street":"Boeschepestraat",
    "iso:country":"BE",
    "sg:address":"Boeschepestraat 92",
    "sg:city":"Poperinge",
    "sg:classifiers":[
        {
            "category":"Professional",
            "subcategory":"Management & Consulting",
            "type":"Services"
        }
    ],
    "sg:phone":"+32 57 33 88 50",
    "sg:postcode":"8970",
    "sg:province":"West-Vlaanderen",
    "sg:tags":[
        "tax-consultants"
    ],
    "wof:name":"Kesteloot H",
    "wof:placetype":"venue"
},
  "geometry": {"coordinates":[2.7211239338,50.8496742249],"type":"Point"}
}