{
  "type": "Feature",
  "properties": {
    "addr:full":"L. De Raetlaan 36 Izegem (kachtem) West-Vlaanderen 8870",
    "addr:housenumber":"36",
    "addr:postcode":"8870",
    "addr:street":"L. De Raetlaan",
    "iso:country":"BE",
    "sg:address":"L. De Raetlaan 36",
    "sg:city":"Izegem (kachtem)",
    "sg:classifiers":[
        {
            "category":"Building & Trades",
            "subcategory":"Construction",
            "type":"Services"
        }
    ],
    "sg:phone":"+32 51 30 74 49",
    "sg:postcode":"8870",
    "sg:province":"West-Vlaanderen",
    "sg:tags":[
        "carpenter"
    ],
    "wof:name":"Gsi",
    "wof:placetype":"venue"
},
  "geometry": {"coordinates":[3.2146790028,50.9205284119],"type":"Point"}
}