{
  "type": "Feature",
  "properties": {
    "addr:full":"Puntstraat 46 Geel Antwerpen 2440",
    "addr:housenumber":"46",
    "addr:postcode":"2440",
    "addr:street":"Puntstraat",
    "iso:country":"BE",
    "sg:address":"Puntstraat 46",
    "sg:city":"Geel",
    "sg:orig_category":"Betonnen bouwelementen Fab IJzerwaren, bouw- and verfmaterialen",
    "sg:phone":"+32 14 58 83 62",
    "sg:postcode":"2440",
    "sg:province":"Antwerpen",
    "wof:name":"Guido Boeckx",
    "wof:placetype":"venue"
},
  "geometry": {"coordinates":[4.9381680489,51.1386108398],"type":"Point"}
}