{
  "type": "Feature",
  "properties": {
    "addr:full":"Chauss\u00c9e De Louvain 81 Sint-joost-ten-node/saint-josse-ten-noode Bruxelles-Capitale 1210",
    "addr:housenumber":"81",
    "addr:postcode":"1210",
    "addr:street":"Chausse\u0301E De Louvain",
    "iso:country":"BE",
    "sg:address":"Chauss\u00c9e De Louvain 81",
    "sg:city":"Sint-joost-ten-node/saint-josse-ten-noode",
    "sg:orig_category":"Pharmaciens",
    "sg:phone":"+32 2 219 19 84",
    "sg:postcode":"1210",
    "sg:province":"Bruxelles-Capitale",
    "wof:name":"Multipharma",
    "wof:placetype":"venue"
},
  "geometry": {"coordinates":[4.3736920357,50.8499832153],"type":"Point"}
}