{
  "type": "Feature",
  "properties": {
    "addr:full":"Isenbaertlei 63 Brasschaat Antwerpen 2930",
    "addr:housenumber":"63",
    "addr:postcode":"2930",
    "addr:street":"Isenbaertlei",
    "iso:country":"BE",
    "sg:address":"Isenbaertlei 63",
    "sg:city":"Brasschaat",
    "sg:classifiers":[
        {
            "category":"Professional",
            "type":"Services"
        }
    ],
    "sg:phone":"+32 3 653 13 63",
    "sg:postcode":"2930",
    "sg:province":"Antwerpen",
    "sg:tags":[
        "surveyor",
        "-",
        "valuer"
    ],
    "wof:name":"Domus Expertise",
    "wof:placetype":"venue"
},
  "geometry": {"coordinates":[4.509303093,51.2952766418],"type":"Point"}
}