{
  "type": "Feature",
  "properties": {
    "addr:full":"Rue Tombeux 48 Donceel (haneffe) Li\u00e8ge 4357",
    "addr:housenumber":"48",
    "addr:postcode":"4357",
    "addr:street":"Rue Tombeux;Haneffe",
    "iso:country":"BE",
    "sg:address":"Rue Tombeux 48",
    "sg:city":"Donceel (haneffe)",
    "sg:classifiers":[
        {
            "category":"Professional",
            "subcategory":"Accounting & Tax Preparation",
            "type":"Services"
        }
    ],
    "sg:phone":"+32 475 45 02 03",
    "sg:postcode":"4357",
    "sg:province":"Li\u00e8ge",
    "sg:tags":[
        "accountant"
    ],
    "wof:name":"Pollers H",
    "wof:placetype":"venue"
},
  "geometry": {"coordinates":[5.3295259476,50.6389427185],"type":"Point"}
}