{
  "type": "Feature",
  "properties": {
    "addr:full":"Lindanusstraat 19 Dendermonde Oost-Vlaanderen 9200",
    "addr:housenumber":"19",
    "addr:postcode":"9200",
    "addr:street":"Lindanusstraat;Oost-Vlaanderen",
    "iso:country":"BE",
    "sg:address":"Lindanusstraat 19",
    "sg:city":"Dendermonde",
    "sg:classifiers":[
        {
            "category":"Cemetery",
            "type":"Public Place"
        }
    ],
    "sg:phone":"+32 52 21 30 25",
    "sg:postcode":"9200",
    "sg:province":"Oost-Vlaanderen",
    "sg:tags":[
        "crematory"
    ],
    "wof:name":"Rouwcentrum Bogaert Cv",
    "wof:placetype":"venue"
},
  "geometry": {"coordinates":[4.1026268005,51.0289764404],"type":"Point"}
}