{
  "type": "Feature",
  "properties": {
    "iso:country":"BE",
    "sg:address":"Leupegemstraat 17",
    "sg:city":"Oudenaarde",
    "sg:classifiers":[
        {
            "category":"Health Services",
            "subcategory":"Health Practitioner",
            "type":"Services"
        }
    ],
    "sg:phone":"+32 55 31 46 70",
    "sg:postcode":"9700",
    "sg:province":"Oost-Vlaanderen",
    "sg:tags":[
        "physiotherapist"
    ],
    "wof:name":"Verhaert Mia",
    "wof:placetype":"venue"
},
  "geometry": {"coordinates":[3.6066460609,50.834400177],"type":"Point"}
}