{
  "type": "Feature",
  "properties": {
    "addr:full":"Nationalestraat 65 Antwerpen Antwerpen 2000",
    "addr:housenumber":"65",
    "addr:postcode":"2000",
    "addr:street":"Nationalestraat",
    "iso:country":"BE",
    "sg:address":"Nationalestraat 65",
    "sg:city":"Antwerpen",
    "sg:orig_category":"V\u00eatements. V\u00eatements pour Dames",
    "sg:phone":"+32 3 233 02 65",
    "sg:postcode":"2000",
    "sg:province":"Antwerpen",
    "wof:name":"Huis Mondial",
    "wof:placetype":"venue"
},
  "geometry": {"coordinates":[4.3990659714,51.2154655457],"type":"Point"}
}