{
  "type": "Feature",
  "properties": {
    "addr:full":"Fazantenin 1 B2 Meise Vlaams-Brabant 1860",
    "addr:housenumber":"1 b2",
    "addr:postcode":"1860",
    "addr:street":"Fazantenin",
    "iso:country":"BE",
    "sg:address":"Fazantenin 1 B2",
    "sg:city":"Meise",
    "sg:orig_category":"Mat\u00e9riel de T\u00e9l\u00e9communication",
    "sg:phone":"+32 2 270 86 28",
    "sg:postcode":"1860",
    "sg:province":"Vlaams-Brabant",
    "wof:name":"Eurodaq",
    "wof:placetype":"venue"
},
  "geometry": {"coordinates":[4.3299398422,50.9351844788],"type":"Point"}
}