{
  "type": "Feature",
  "properties": {
    "addr:full":"Mesenstraat 185 Comines-warneton (warneton) Hainaut 7784",
    "addr:housenumber":"185",
    "addr:postcode":"7784",
    "addr:street":"Mesenstraat",
    "iso:country":"BE",
    "sg:address":"Mesenstraat 185",
    "sg:city":"Comines-warneton (warneton)",
    "sg:classifiers":[
        {
            "category":"Farming",
            "subcategory":"Livestock Farm",
            "type":"Manufacturing & Wholesale Goods"
        }
    ],
    "sg:phone":"+32 56 58 85 39",
    "sg:postcode":"7784",
    "sg:province":"Hainaut",
    "sg:tags":[
        "buyer"
    ],
    "wof:name":"Blondeel R",
    "wof:placetype":"venue"
},
  "geometry": {"coordinates":[2.8922579288,50.7520027161],"type":"Point"}
}