{
  "type": "Feature",
  "properties": {
    "addr:full":"Noordkaai 10 Izegem West-Vlaanderen 8870",
    "addr:housenumber":"10",
    "addr:postcode":"8870",
    "addr:street":"Noordkaai",
    "iso:country":"BE",
    "sg:address":"Noordkaai 10",
    "sg:city":"Izegem",
    "sg:classifiers":[
        {
            "category":"Parking",
            "subcategory":"Lot",
            "type":"Transportation"
        }
    ],
    "sg:phone":"+32 51 31 66 36",
    "sg:postcode":"8870",
    "sg:province":"West-Vlaanderen",
    "sg:tags":[
        "food",
        "tank",
        "-",
        "transport"
    ],
    "wof:name":"Ghekiere Transport Bvba",
    "wof:placetype":"venue"
},
  "geometry": {"coordinates":[3.2046780586,50.9254875183],"type":"Point"}
}