{
  "type": "Feature",
  "properties": {
    "addr:full":"Kerkstraat 7 Melle Oost-Vlaanderen 9090",
    "addr:housenumber":"7",
    "addr:postcode":"9090",
    "addr:street":"Kerkstraat",
    "iso:country":"BE",
    "sg:address":"Kerkstraat 7",
    "sg:city":"Melle",
    "sg:orig_category":"V\u00eatements pour Hommes. V\u00eatements pour Dames",
    "sg:phone":"+32 9 252 10 63",
    "sg:postcode":"9090",
    "sg:province":"Oost-Vlaanderen",
    "wof:name":"Huis De Mulder",
    "wof:placetype":"venue"
},
  "geometry": {"coordinates":[3.8006489277,51.0038909912],"type":"Point"}
}