{
  "type": "Feature",
  "properties": {
    "iso:country":"BE",
    "sg:address":"Rue Sainte-croix 26",
    "sg:city":"Arlon",
    "sg:orig_category":"Loodgieterij, verwarming and sanitaire installaties",
    "sg:phone":"+32 63 21 67 54",
    "sg:postcode":"6700",
    "sg:province":"Luxembourg",
    "wof:name":"Jean-luc Dametto",
    "wof:placetype":"venue"
},
  "geometry": {"coordinates":[5.8090000153,49.6896934509],"type":"Point"}
}