{
  "type": "Feature",
  "properties": {
    "addr:full":"Kouterstraat 12ba Nevele Oost-Vlaanderen 9850",
    "addr:housenumber":"12ba",
    "addr:postcode":"9850",
    "addr:street":"Kouterstraat",
    "iso:country":"BE",
    "sg:address":"Kouterstraat 12ba",
    "sg:city":"Nevele",
    "sg:orig_category":"Installatie van metalen schrijnwerk Verhuur voertuigen behalve auto's",
    "sg:phone":"+32 9 386 28 11",
    "sg:postcode":"9850",
    "sg:province":"Oost-Vlaanderen",
    "wof:name":"De Winter",
    "wof:placetype":"venue"
},
  "geometry": {"coordinates":[3.5529139042,51.0129585266],"type":"Point"}
}