{
  "type": "Feature",
  "properties": {
    "addr:full":"Stadsplein 9 Bree Limburg 3960",
    "addr:housenumber":"9",
    "addr:postcode":"3960",
    "addr:street":"Stadsplein",
    "iso:country":"BE",
    "sg:address":"Stadsplein 9",
    "sg:city":"Bree",
    "sg:orig_category":"Banques and organismes de cr\u00e9dit",
    "sg:phone":"+32 89 46 14 40",
    "sg:postcode":"3960",
    "sg:province":"Limburg",
    "wof:name":"Bbl",
    "wof:placetype":"venue"
},
  "geometry": {"coordinates":[5.5970540047,51.1397399902],"type":"Point"}
}