{
  "type": "Feature",
  "properties": {
    "addr:full":"Avenue Du Jonc 64 Bruxelles (forest) Bruxelles-Capitale 1190",
    "addr:housenumber":"64",
    "addr:postcode":"1190",
    "addr:street":"Avenue Du Jonc",
    "iso:country":"BE",
    "sg:address":"Avenue Du Jonc 64",
    "sg:city":"Bruxelles (forest)",
    "sg:orig_category":"Non-Classified Establishments",
    "sg:phone":"+32 2 376 74 17",
    "sg:postcode":"1190",
    "sg:province":"Bruxelles-Capitale",
    "wof:name":"Carra Sprl",
    "wof:placetype":"venue"
},
  "geometry": {"coordinates":[4.3240327835,50.8057403564],"type":"Point"}
}