{
  "type": "Feature",
  "properties": {
    "addr:full":"Quai De Coronmeuse 37 Luik Li\u00e8ge 4000",
    "addr:housenumber":"37",
    "addr:postcode":"4000",
    "addr:street":"Quai De Coronmeuse",
    "iso:country":"BE",
    "sg:address":"Quai De Coronmeuse 37",
    "sg:city":"Luik",
    "sg:orig_category":"Equipement divers pour commerces Mobilier and \u00e9quipement m\u00e9nager Gr",
    "sg:phone":"+32 4 227 44 44",
    "sg:postcode":"4000",
    "sg:province":"Li\u00e8ge",
    "wof:name":"Foodmat Occasion",
    "wof:placetype":"venue"
},
  "geometry": {"coordinates":[5.6094098091,50.6545524597],"type":"Point"}
}