{
  "type": "Feature",
  "properties": {
    "addr:full":"Chemin Du Vieux Pont 21b Leuze-en-hainaut Hainaut 7900",
    "addr:housenumber":"21b",
    "addr:postcode":"7900",
    "addr:street":"Chemin Du Vieux Pont",
    "iso:country":"BE",
    "sg:address":"Chemin Du Vieux Pont 21b",
    "sg:city":"Leuze-en-hainaut",
    "sg:classifiers":[
        {
            "category":"Retail",
            "subcategory":"Laundry & Dry Cleaning",
            "type":"Services"
        }
    ],
    "sg:phone":"+32 69 66 31 09",
    "sg:postcode":"7900",
    "sg:province":"Hainaut",
    "wof:name":"Aubert - Blanche Neige",
    "wof:placetype":"venue"
},
  "geometry": {"coordinates":[3.6270480156,50.6018218994],"type":"Point"}
}