{
  "type": "Feature",
  "properties": {
    "addr:full":"Avenue Flor\u00c9al 4 Rebecq Brabant Wallon 1430",
    "addr:housenumber":"4",
    "addr:postcode":"1430",
    "addr:street":"Avenue Flore\u0301Al",
    "iso:country":"BE",
    "sg:address":"Avenue Flor\u00c9al 4",
    "sg:city":"Rebecq",
    "sg:classifiers":[
        {
            "category":"Arena",
            "subcategory":"Sports Club",
            "type":"Entertainment"
        }
    ],
    "sg:phone":"+32 67 63 60 47",
    "sg:postcode":"1430",
    "sg:province":"Brabant Wallon",
    "sg:tags":[
        "de"
    ],
    "wof:name":"B.b.c. Rebecq",
    "wof:placetype":"venue"
},
  "geometry": {"coordinates":[4.1379737854,50.6609306335],"type":"Point"}
}