{
  "type": "Feature",
  "properties": {
    "iso:country":"BE",
    "sg:address":"Rue De L'espinette 17",
    "sg:city":"Hotton",
    "sg:orig_category":"Maisons de vacances",
    "sg:phone":"+32 84 46 74 64",
    "sg:postcode":"6990",
    "sg:province":"Luxembourg",
    "wof:name":"Destinne Michel",
    "wof:placetype":"venue"
},
  "geometry": {"coordinates":[5.4837517738,50.285736084],"type":"Point"}
}