{
  "type": "Feature",
  "properties": {
    "addr:full":"Rue De La Victoire 8 Bruxelles (saint-gilles) Bruxelles-Capitale 1060",
    "addr:housenumber":"8",
    "addr:postcode":"1060",
    "addr:street":"Rue De La Victoire",
    "iso:country":"BE",
    "sg:address":"Rue De La Victoire 8",
    "sg:city":"Bruxelles (saint-gilles)",
    "sg:classifiers":[
        {
            "category":"Personal",
            "subcategory":"Barber",
            "type":"Services"
        }
    ],
    "sg:phone":"+32 2 538 07 56",
    "sg:postcode":"1060",
    "sg:province":"Bruxelles-Capitale",
    "sg:tags":[
        "gentleman",
        "salon",
        "-",
        "hairdressing"
    ],
    "wof:name":"Victory",
    "wof:placetype":"venue"
},
  "geometry": {"coordinates":[4.3458862305,50.8324394226],"type":"Point"}
}