{
  "type": "Feature",
  "properties": {
    "addr:full":"Beernemstraat 33 Beernem West-Vlaanderen 8730",
    "addr:housenumber":"33",
    "addr:postcode":"8730",
    "addr:street":"Beernemstraat",
    "iso:country":"BE",
    "sg:address":"Beernemstraat 33",
    "sg:city":"Beernem",
    "sg:classifiers":[
        {
            "category":"Cafe",
            "type":"Food & Drink"
        }
    ],
    "sg:phone":"+32 50 78 97 86",
    "sg:postcode":"8730",
    "sg:province":"West-Vlaanderen",
    "sg:tags":[
        "caf\u00e9s"
    ],
    "wof:name":"Voetbalver Cercle Oedelem",
    "wof:placetype":"venue"
},
  "geometry": {"coordinates":[3.3393120766,51.1663131714],"type":"Point"}
}