{
  "type": "Feature",
  "properties": {
    "addr:full":"Sint-niklaasberg 1 Aarschot Vlaams-Brabant 3200",
    "addr:housenumber":"1",
    "addr:postcode":"3200",
    "addr:street":"Sint-Niklaasberg",
    "iso:country":"BE",
    "sg:address":"Sint-niklaasberg 1",
    "sg:city":"Aarschot",
    "sg:classifiers":[
        {
            "category":"Insurance",
            "subcategory":"Insurance Agent",
            "type":"Services"
        }
    ],
    "sg:phone":"+32 16 56 37 42",
    "sg:postcode":"3200",
    "sg:province":"Vlaams-Brabant",
    "sg:tags":[
        "broker"
    ],
    "wof:name":"Dienstencentrum Verbeeck-pieters",
    "wof:placetype":"venue"
},
  "geometry": {"coordinates":[4.8302369118,50.9838523865],"type":"Point"}
}