{
  "type": "Feature",
  "properties": {
    "addr:full":"Lossing 21 Westerlo Antwerpen 2260",
    "addr:housenumber":"21",
    "addr:postcode":"2260",
    "addr:street":"Lossing",
    "iso:country":"BE",
    "sg:address":"Lossing 21",
    "sg:city":"Westerlo",
    "sg:classifiers":[
        {
            "category":"Bakery",
            "type":"Food & Drink"
        }
    ],
    "sg:phone":"+32 15 22 50 88",
    "sg:postcode":"2260",
    "sg:province":"Antwerpen",
    "sg:tags":[
        "cake",
        "product",
        "related",
        "bread"
    ],
    "wof:name":"Eco Biscuits Nv",
    "wof:placetype":"venue"
},
  "geometry": {"coordinates":[4.8227181435,51.0927467346],"type":"Point"}
}