{
  "type": "Feature",
  "properties": {
    "iso:country":"BE",
    "sg:address":"Henri Van Heurckstraat 19",
    "sg:city":"Antwerpen",
    "sg:classifiers":[
        {
            "category":"Real Estate",
            "subcategory":"Developer",
            "type":"Services"
        }
    ],
    "sg:phone":"+32 3 231 47 50",
    "sg:postcode":"2000",
    "sg:province":"Antwerpen",
    "sg:tags":[
        "project"
    ],
    "wof:name":"London & York Properties Nv",
    "wof:placetype":"venue"
},
  "geometry": {"coordinates":[4.408531189,51.2140541077],"type":"Point"}
}