{
  "type": "Feature",
  "properties": {
    "iso:country":"BE",
    "sg:address":"Kempischesteenweg 276",
    "sg:city":"Hasselt",
    "sg:orig_category":"Rundveehouders Zuivelproducten",
    "sg:phone":"+32 11 21 12 13",
    "sg:postcode":"3500",
    "sg:province":"Limburg",
    "wof:name":"Jules Vandickelen",
    "wof:placetype":"venue"
},
  "geometry": {"coordinates":[5.3410902023,50.9396095276],"type":"Point"}
}