{
  "type": "Feature",
  "properties": {
    "addr:full":"Avenue De Forest 26 Rochefort Namur 5580",
    "addr:housenumber":"26",
    "addr:postcode":"5580",
    "addr:street":"Avenue De Forest",
    "iso:country":"BE",
    "sg:address":"Avenue De Forest 26",
    "sg:city":"Rochefort",
    "sg:classifiers":[
        {
            "category":"Shopping",
            "subcategory":"Florist",
            "type":"Retail Goods"
        }
    ],
    "sg:phone":"+32 84 21 41 68",
    "sg:postcode":"5580",
    "sg:province":"Namur",
    "wof:name":"Joli-bois (le)",
    "wof:placetype":"venue"
},
  "geometry": {"coordinates":[5.2213602066,50.1582717896],"type":"Point"}
}