{
  "type": "Feature",
  "properties": {
    "addr:full":"Bevrijdingslaan 31 As Limburg 3665",
    "addr:housenumber":"31",
    "addr:postcode":"3665",
    "addr:street":"Bevrijdingslaan",
    "iso:country":"BE",
    "sg:address":"Bevrijdingslaan 31",
    "sg:city":"As",
    "sg:classifiers":[
        {
            "category":"Health Services",
            "subcategory":"Health Practitioner",
            "type":"Services"
        }
    ],
    "sg:phone":"+32 89 65 93 92",
    "sg:postcode":"3665",
    "sg:province":"Limburg",
    "sg:tags":[
        "physiotherapist"
    ],
    "wof:name":"Vangrinsven M-l",
    "wof:placetype":"venue"
},
  "geometry": {"coordinates":[5.5870380402,51.0057907104],"type":"Point"}
}