{
  "type": "Feature",
  "properties": {
    "iso:country":"BE",
    "sg:address":"Clos Du Drossart 1ba",
    "sg:city":"Ukkel/uccle",
    "sg:orig_category":"G\u00e9om\u00e8tres",
    "sg:phone":"+32 2 374 47 48",
    "sg:postcode":"1180",
    "sg:province":"Bruxelles-Capitale",
    "wof:name":"Pierre Quetstroey",
    "wof:placetype":"venue"
},
  "geometry": {"coordinates":[4.353263855,50.7933654785],"type":"Point"}
}