{
  "type": "Feature",
  "properties": {
    "iso:country":"BE",
    "sg:address":"Lostraat 2c",
    "sg:city":"Wingene (zwevezele)",
    "sg:classifiers":[
        {
            "category":"Retail",
            "subcategory":"Veterinary Services",
            "type":"Services"
        }
    ],
    "sg:phone":"+32 51 61 29 23",
    "sg:postcode":"8750",
    "sg:province":"West-Vlaanderen",
    "sg:tags":[
        "veterinarian"
    ],
    "wof:name":"Dejonckheere E",
    "wof:placetype":"venue"
},
  "geometry": {"coordinates":[3.2269399166,51.0521507263],"type":"Point"}
}