{
  "type": "Feature",
  "properties": {
    "iso:country":"BE",
    "sg:address":"R De L'ecole 17",
    "sg:city":"Saintes",
    "sg:classifiers":[
        {
            "category":"Professional",
            "type":"Services"
        }
    ],
    "sg:phone":"+32 2 355 64 36",
    "sg:postcode":"1480",
    "sg:province":"Brabant Wallon",
    "sg:tags":[
        "transport",
        "road"
    ],
    "wof:name":"Transport Walravens",
    "wof:placetype":"venue"
},
  "geometry": {"coordinates":[4.153190136,50.7045898438],"type":"Point"}
}