{
  "type": "Feature",
  "properties": {
    "iso:country":"BE",
    "sg:address":"Rue Moreau 42",
    "sg:city":"Herve",
    "sg:orig_category":"Kapsalons",
    "sg:phone":"+32 87 67 50 90",
    "sg:postcode":"4650",
    "sg:province":"Li\u00e8ge",
    "wof:name":"Coiffure Acedo Diffusion",
    "wof:placetype":"venue"
},
  "geometry": {"coordinates":[5.7940139771,50.6436157227],"type":"Point"}
}