{
  "type": "Feature",
  "properties": {
    "iso:country":"BE",
    "sg:address":"Staatsbaan 119",
    "sg:city":"Zulte",
    "sg:orig_category":"Pharmaciens",
    "sg:phone":"+32 9 388 86 61",
    "sg:postcode":"9870",
    "sg:province":"Oost-Vlaanderen",
    "wof:name":"Goessaert",
    "wof:placetype":"venue"
},
  "geometry": {"coordinates":[3.4454510212,50.9224967957],"type":"Point"}
}