{
  "type": "Feature",
  "properties": {
    "iso:country":"BE",
    "sg:address":"Xavier De Cocklaan 44",
    "sg:city":"Sint-martens-latem (deurle)",
    "sg:orig_category":"Non-Classified Establishments",
    "sg:phone":"+32 9 282 32 27",
    "sg:postcode":"9831",
    "sg:province":"Oost-Vlaanderen",
    "wof:name":"Jesco",
    "wof:placetype":"venue"
},
  "geometry": {"coordinates":[3.6166980267,51.0021133423],"type":"Point"}
}