{
  "type": "Feature",
  "properties": {
    "iso:country":"BE",
    "sg:address":"Avelgemstraat 200",
    "sg:city":"Zwevegem",
    "sg:classifiers":[
        {
            "category":"Home & Garden",
            "subcategory":"Home Furnishings",
            "type":"Retail Goods"
        }
    ],
    "sg:phone":"+32 56 75 51 40",
    "sg:postcode":"8550",
    "sg:province":"West-Vlaanderen",
    "sg:tags":[
        "interior",
        "decoration"
    ],
    "wof:name":"Matton & Zn Bvba",
    "wof:placetype":"venue"
},
  "geometry": {"coordinates":[3.3479480743,50.8013420105],"type":"Point"}
}