{
  "type": "Feature",
  "properties": {
    "addr:full":"Mathias Van Den Gheynlaan 30 Leuven Vlaams-Brabant 3000",
    "addr:housenumber":"30",
    "addr:postcode":"3000",
    "addr:street":"Mathias Van Den Gheynlaan",
    "iso:country":"BE",
    "sg:address":"Mathias Van Den Gheynlaan 30",
    "sg:city":"Leuven",
    "sg:classifiers":[
        {
            "category":"Professional",
            "subcategory":"Accounting & Tax Preparation",
            "type":"Services"
        }
    ],
    "sg:phone":"+32 16 29 32 00",
    "sg:postcode":"3000",
    "sg:province":"Vlaams-Brabant",
    "sg:tags":[
        "bookkeeper"
    ],
    "wof:name":"Goedseels H",
    "wof:placetype":"venue"
},
  "geometry": {"coordinates":[4.7058110237,50.8826560974],"type":"Point"}
}