{
  "type": "Feature",
  "properties": {
    "addr:full":"Rue Adolphe-sax 55 Dinant Namur 5500",
    "addr:housenumber":"55",
    "addr:postcode":"5500",
    "addr:street":"Rue Adolphe-Sax",
    "iso:country":"BE",
    "sg:address":"Rue Adolphe-sax 55",
    "sg:city":"Dinant",
    "sg:orig_category":"Centres de relaxation and bien-\u00eatre. Instituts de beaut\u00e9",
    "sg:phone":"+32 82 22 66 57",
    "sg:postcode":"5500",
    "sg:province":"Namur",
    "wof:name":"Institut Ath\u00c9na",
    "wof:placetype":"venue"
},
  "geometry": {"coordinates":[4.9104628563,50.2624320984],"type":"Point"}
}