{
  "type": "Feature",
  "properties": {
    "addr:full":"Tervuursesteenweg 117 Bertem Vlaams-Brabant 3060",
    "addr:housenumber":"117",
    "addr:postcode":"3060",
    "addr:street":"Tervuursesteenweg",
    "iso:country":"BE",
    "sg:address":"Tervuursesteenweg 117",
    "sg:city":"Bertem",
    "sg:orig_category":"Banques and organismes de cr\u00e9dit",
    "sg:phone":"+32 16 49 07 49",
    "sg:postcode":"3060",
    "sg:province":"Vlaams-Brabant",
    "wof:name":"Verlico",
    "wof:placetype":"venue"
},
  "geometry": {"coordinates":[4.6315979958,50.8658714294],"type":"Point"}
}