{
  "type": "Feature",
  "properties": {
    "addr:full":"Kloosterstraat 3r Gent (drongen) Oost-Vlaanderen 9031",
    "addr:housenumber":"3r",
    "addr:postcode":"9031",
    "addr:street":"Kloosterstraat",
    "iso:country":"BE",
    "sg:address":"Kloosterstraat 3r",
    "sg:city":"Gent (drongen)",
    "sg:classifiers":[
        {
            "category":"Manufacturing",
            "subcategory":"Electronics",
            "type":"Manufacturing & Wholesale Goods"
        }
    ],
    "sg:phone":"+32 9 282 04 10",
    "sg:postcode":"9031",
    "sg:province":"Oost-Vlaanderen",
    "sg:tags":[
        "telecommunication",
        "system"
    ],
    "wof:name":"Wolcom",
    "wof:placetype":"venue"
},
  "geometry": {"coordinates":[3.6180300713,51.0374603271],"type":"Point"}
}