{
  "type": "Feature",
  "properties": {
    "addr:full":"Place D\u00b4anvaing 12 Frasnes-lez-anvaing Hainaut 7910",
    "addr:housenumber":"12",
    "addr:postcode":"7910",
    "addr:street":"Place D\u00b4Anvaing",
    "iso:country":"BE",
    "sg:address":"Place D\u00b4anvaing 12",
    "sg:city":"Frasnes-lez-anvaing",
    "sg:classifiers":[
        {
            "category":"Cafe",
            "type":"Food & Drink"
        }
    ],
    "sg:phone":"+32 69 86 86 95",
    "sg:postcode":"7910",
    "sg:province":"Hainaut",
    "sg:tags":[
        "caf\u00e9s"
    ],
    "wof:name":"Caf\u00c9 L\u00b4anvinois",
    "wof:placetype":"venue"
},
  "geometry": {"coordinates":[3.5632250309,50.6847953796],"type":"Point"}
}