{
  "type": "Feature",
  "properties": {
    "addr:full":"Niklaas Desparsstraat 3 Brugge West-Vlaanderen 8000",
    "addr:housenumber":"3",
    "addr:postcode":"8000",
    "addr:street":"Niklaas Desparsstraat",
    "iso:country":"BE",
    "sg:address":"Niklaas Desparsstraat 3",
    "sg:city":"Brugge",
    "sg:orig_category":"Antiek Meubelzaken, woning- and keukeninrichting",
    "sg:phone":"+32 50 34 92 26",
    "sg:postcode":"8000",
    "sg:province":"West-Vlaanderen",
    "wof:name":"Emily & Nous",
    "wof:placetype":"venue"
},
  "geometry": {"coordinates":[3.2232029438,51.2098121643],"type":"Point"}
}