{
  "type": "Feature",
  "properties": {
    "iso:country":"BE",
    "sg:address":"Bergstr 39",
    "sg:city":"Ham",
    "sg:classifiers":[
        {
            "category":"Wholesale",
            "subcategory":"Machinery & Supplies",
            "type":"Manufacturing & Wholesale Goods"
        }
    ],
    "sg:phone":"+32 13 67 01 60",
    "sg:postcode":"3945",
    "sg:province":"Limburg",
    "sg:tags":[
        "equipment",
        "optical",
        "precision",
        "instrument"
    ],
    "wof:name":"Macdermid Imaging Technology Belgium Nv",
    "wof:placetype":"venue"
},
  "geometry": {"coordinates":[5.1776199341,51.1046104431],"type":"Point"}
}