{
  "type": "Feature",
  "properties": {
    "iso:country":"BE",
    "sg:address":"Rue Du Castiau 51",
    "sg:city":"Qu\u00e9vy (givry)",
    "sg:classifiers":[
        {
            "category":"Insurance",
            "subcategory":"Insurance Agent",
            "type":"Services"
        }
    ],
    "sg:phone":"+32 65 58 92 30",
    "sg:postcode":"7041",
    "sg:province":"Hainaut",
    "sg:tags":[
        "broker"
    ],
    "wof:name":"Deghislage Assurances Sprl",
    "wof:placetype":"venue"
},
  "geometry": {"coordinates":[4.0359840393,50.3752098083],"type":"Point"}
}