{
  "type": "Feature",
  "properties": {
    "iso:country":"BE",
    "sg:address":"Rue De Gilly 287",
    "sg:city":"Charleroi",
    "sg:orig_category":"Dakwerken Loodgieterij, verwarming and sanitaire installaties",
    "sg:phone":"+32 71 65 55 45",
    "sg:postcode":"6010",
    "sg:province":"Hainaut",
    "wof:name":"Horney A.",
    "wof:placetype":"venue"
},
  "geometry": {"coordinates":[4.4680199623,50.3871917725],"type":"Point"}
}