{
  "type": "Feature",
  "properties": {
    "iso:country":"BE",
    "sg:address":"Buizerstraat 12",
    "sg:city":"Retie",
    "sg:classifiers":[
        {
            "category":"Health Services",
            "subcategory":"Health Practitioner",
            "type":"Services"
        }
    ],
    "sg:phone":"+32 14 37 02 67",
    "sg:postcode":"2470",
    "sg:province":"Antwerpen",
    "sg:tags":[
        "physiotherapist"
    ],
    "wof:name":"Peeters Ronny",
    "wof:placetype":"venue"
},
  "geometry": {"coordinates":[5.1223511696,51.273109436],"type":"Point"}
}