{
  "type": "Feature",
  "properties": {
    "iso:country":"BE",
    "sg:address":"Sint-paulusplaats 26",
    "sg:city":"Antwerpen",
    "sg:classifiers":[
        {
            "category":"Communications",
            "subcategory":"News Services",
            "type":"Services"
        }
    ],
    "sg:phone":"+32 3 225 15 52",
    "sg:postcode":"2000",
    "sg:province":"Antwerpen",
    "sg:tags":[
        "illustrator"
    ],
    "wof:name":"Van Gimst J",
    "wof:placetype":"venue"
},
  "geometry": {"coordinates":[4.4022011757,51.2242965698],"type":"Point"}
}