{
  "type": "Feature",
  "properties": {
    "addr:full":"Th. Van Cauwenberghslei 30-35 Schoten Antwerpen 2900",
    "addr:postcode":"30-35;2900",
    "addr:street":"Th. Van Cauwenberghslei",
    "iso:country":"BE",
    "sg:address":"Th. Van Cauwenberghslei 30-35",
    "sg:city":"Schoten",
    "sg:orig_category":"Microsoft. Mat\u00e9riel de T\u00e9l\u00e9communication. Eclairage et \u00e9quipements du foyer",
    "sg:phone":"+32 3 658 49 82",
    "sg:postcode":"2900",
    "sg:province":"Antwerpen",
    "wof:name":"Van Uffelen Electro",
    "wof:placetype":"venue"
},
  "geometry": {"coordinates":[4.5028271675,51.2524147034],"type":"Point"}
}