{
  "type": "Feature",
  "properties": {
    "addr:full":"Statiestraat 53a Mol Antwerpen 2400",
    "addr:housenumber":"53a",
    "addr:postcode":"2400",
    "addr:street":"Statiestraat",
    "iso:country":"BE",
    "sg:address":"Statiestraat 53a",
    "sg:city":"Mol",
    "sg:orig_category":"Supermarkten",
    "sg:phone":"+32 14 33 06 11",
    "sg:postcode":"2400",
    "sg:province":"Antwerpen",
    "wof:name":"Super Gb",
    "wof:placetype":"venue"
},
  "geometry": {"coordinates":[5.1170978546,51.1912193298],"type":"Point"}
}