{
  "type": "Feature",
  "properties": {
    "iso:country":"BE",
    "sg:address":"Westdijk 140",
    "sg:city":"Willebroek",
    "sg:orig_category":"Mat\u00e9riaux de construction Gr",
    "sg:phone":"+32 3 886 31 08",
    "sg:postcode":"2830",
    "sg:province":"Antwerpen",
    "wof:name":"Coatings Service Center",
    "wof:placetype":"venue"
},
  "geometry": {"coordinates":[4.3615899086,51.0541610718],"type":"Point"}
}