{
  "type": "Feature",
  "properties": {
    "addr:full":"Boonvennestraat 1 Berlare Oost-Vlaanderen 9290",
    "addr:housenumber":"1",
    "addr:postcode":"9290",
    "addr:street":"Boonvennestraat",
    "iso:country":"BE",
    "sg:address":"Boonvennestraat 1",
    "sg:city":"Berlare",
    "sg:orig_category":"Bouwmaterialen Gh Dakwerken Loodgieterij, verwarming and sanitaire installaties",
    "sg:phone":"+32 52 42 24 27",
    "sg:postcode":"9290",
    "sg:province":"Oost-Vlaanderen",
    "wof:name":"Van Den Abbeele Maurits",
    "wof:placetype":"venue"
},
  "geometry": {"coordinates":[4.0016407967,51.0167388916],"type":"Point"}
}