{
  "type": "Feature",
  "properties": {
    "addr:full":"Basiliekstraat 47 Halle Vlaams-Brabant 1500",
    "addr:housenumber":"47",
    "addr:postcode":"1500",
    "addr:street":"Basiliekstraat",
    "iso:country":"BE",
    "sg:address":"Basiliekstraat 47",
    "sg:city":"Halle",
    "sg:orig_category":"Base Shops. Mat\u00e9riel de T\u00e9l\u00e9communication",
    "sg:phone":"+32 2 356 47 80",
    "sg:postcode":"1500",
    "sg:province":"Vlaams-Brabant",
    "wof:name":"Base Halle",
    "wof:placetype":"venue"
},
  "geometry": {"coordinates":[4.2361707687,50.7349014282],"type":"Point"}
}