{
  "type": "Feature",
  "properties": {
    "iso:country":"BE",
    "sg:address":"Kerkstraat 29",
    "sg:city":"Oostrozebeke",
    "sg:orig_category":"Boucheries",
    "sg:phone":"+32 56 66 85 50",
    "sg:postcode":"8780",
    "sg:province":"West-Vlaanderen",
    "wof:name":"Beenhouwerijen Buyse",
    "wof:placetype":"venue"
},
  "geometry": {"coordinates":[3.3364551067,50.9214019775],"type":"Point"}
}