{
  "type": "Feature",
  "properties": {
    "iso:country":"BE",
    "sg:address":"Sint-guduladreef 14",
    "sg:city":"Merchtem",
    "sg:classifiers":[
        {
            "category":"Arena",
            "subcategory":"Sports Club",
            "type":"Entertainment"
        }
    ],
    "sg:phone":"+32 2 460 26 28",
    "sg:postcode":"1785",
    "sg:province":"Vlaams-Brabant",
    "sg:tags":[
        "de"
    ],
    "wof:name":"W.c. De Snelle Vogel",
    "wof:placetype":"venue"
},
  "geometry": {"coordinates":[4.2801361084,50.9191093445],"type":"Point"}
}