{
  "type": "Feature",
  "properties": {
    "iso:country":"BE",
    "sg:address":"Coupurestraat 15",
    "sg:city":"Denderleeuw",
    "sg:classifiers":[
        {
            "category":"Insurance",
            "subcategory":"Insurance Agent",
            "type":"Services"
        }
    ],
    "sg:phone":"+32 53 68 16 85",
    "sg:postcode":"9470",
    "sg:province":"Oost-Vlaanderen",
    "sg:tags":[
        "broker"
    ],
    "wof:name":"Jacobs Kantoor",
    "wof:placetype":"venue"
},
  "geometry": {"coordinates":[4.0733661652,50.8854141235],"type":"Point"}
}