{
  "type": "Feature",
  "properties": {
    "addr:full":"Rue Des Ardennes 49 Messancy Luxembourg 6780",
    "addr:housenumber":"49",
    "addr:postcode":"6780",
    "addr:street":"Rue Des Ardennes",
    "iso:country":"BE",
    "sg:address":"Rue Des Ardennes 49",
    "sg:city":"Messancy",
    "sg:orig_category":"Erotische Etablissementen",
    "sg:phone":"+32 63 22 38 37",
    "sg:postcode":"6780",
    "sg:province":"Luxembourg",
    "wof:name":"Safari Bar",
    "wof:placetype":"venue"
},
  "geometry": {"coordinates":[5.8100800514,49.6082191467],"type":"Point"}
}