{
  "type": "Feature",
  "properties": {
    "iso:country":"BE",
    "sg:address":"Houthulstseweg 104",
    "sg:city":"Langemark-poelkapelle (poelkapelle)",
    "sg:classifiers":[
        {
            "category":"Personal",
            "subcategory":"Shoe Repair & Shine",
            "type":"Services"
        }
    ],
    "sg:phone":"+32 57 48 86 57",
    "sg:postcode":"8920",
    "sg:province":"West-Vlaanderen",
    "sg:tags":[
        "shoemaker"
    ],
    "wof:name":"Baccarne J",
    "wof:placetype":"venue"
},
  "geometry": {"coordinates":[2.9421160221,50.935710907],"type":"Point"}
}