{
  "type": "Feature",
  "properties": {
    "iso:country":"BE",
    "sg:address":"Molenberg 10",
    "sg:city":"Bonheiden",
    "sg:orig_category":"Begrafeniswezen",
    "sg:phone":"+32 475 69 81 11",
    "sg:postcode":"2820",
    "sg:province":"Antwerpen",
    "wof:name":"Verschooten Guido",
    "wof:placetype":"venue"
},
  "geometry": {"coordinates":[4.568529129,51.0169258118],"type":"Point"}
}