{
  "type": "Feature",
  "properties": {
    "addr:full":"'t Lindeke 8 Ledegem West-Vlaanderen 8880",
    "addr:housenumber":"8",
    "addr:postcode":"8880",
    "addr:street":"' T Lindeke",
    "iso:country":"BE",
    "sg:address":"'t Lindeke 8",
    "sg:city":"Ledegem",
    "sg:orig_category":"V\u00e9hicules automobiles. Entretien and r\u00e9parations de voitures",
    "sg:phone":"+32 56 50 25 60",
    "sg:postcode":"8880",
    "sg:province":"West-Vlaanderen",
    "wof:name":"Danny Haezebrouck",
    "wof:placetype":"venue"
},
  "geometry": {"coordinates":[3.1787469387,50.8665084839],"type":"Point"}
}