{
  "type": "Feature",
  "properties": {
    "addr:full":"Kaaskerkestraat 22 Diksmuide West-Vlaanderen 8600",
    "addr:housenumber":"22",
    "addr:postcode":"8600",
    "addr:street":"Kaaskerkestraat",
    "iso:country":"BE",
    "sg:address":"Kaaskerkestraat 22",
    "sg:city":"Diksmuide",
    "sg:orig_category":"Algemeen secundair onderwijs Technisch and beroeps secundair onderwijs",
    "sg:phone":"+32 51 51 92 51",
    "sg:postcode":"8600",
    "sg:province":"West-Vlaanderen",
    "wof:name":"Koninklijk Atheneum",
    "wof:placetype":"venue"
},
  "geometry": {"coordinates":[2.8271460533,51.0384979248],"type":"Point"}
}