{
  "type": "Feature",
  "properties": {
    "iso:country":"BE",
    "sg:address":"Rue Solvay 66",
    "sg:city":"Chapelle-lez-herlaimont",
    "sg:orig_category":"Swatch. Bijouteries and horlogeries. R\u00e9parations d'horloges, montres and bijoux",
    "sg:phone":"+32 64 44 54 49",
    "sg:postcode":"7160",
    "sg:province":"Hainaut",
    "wof:name":"Huart Jacqueline",
    "wof:placetype":"venue"
},
  "geometry": {"coordinates":[4.2809891701,50.4709396362],"type":"Point"}
}