{
  "type": "Feature",
  "properties": {
    "addr:full":"Avenue Du Beau S\u00e9jour 60 Braine-le-ch\u00e2teau Brabant Wallon 1440",
    "addr:housenumber":"60",
    "addr:postcode":"1440",
    "addr:street":"Avenue Du Beau Se\u0301Jour",
    "iso:country":"BE",
    "sg:address":"Avenue Du Beau S\u00e9jour 60",
    "sg:city":"Braine-le-ch\u00e2teau",
    "sg:classifiers":[
        {
            "category":"Professional",
            "subcategory":"Accounting & Tax Preparation",
            "type":"Services"
        }
    ],
    "sg:phone":"+32 2 366 94 83",
    "sg:postcode":"1440",
    "sg:province":"Brabant Wallon",
    "sg:tags":[
        "bookkeeper"
    ],
    "wof:name":"Fiscoden Sprl",
    "wof:placetype":"venue"
},
  "geometry": {"coordinates":[4.2925200462,50.6856803894],"type":"Point"}
}