{
  "type": "Feature",
  "properties": {
    "addr:full":"De Heuf 25 Overpelt Limburg 3900",
    "addr:housenumber":"25",
    "addr:postcode":"3900",
    "addr:street":"De Heuf",
    "iso:country":"BE",
    "sg:address":"De Heuf 25",
    "sg:city":"Overpelt",
    "sg:orig_category":"M\u00e9decines alternatives",
    "sg:phone":"+32 11 80 38 23",
    "sg:postcode":"3900",
    "sg:province":"Limburg",
    "wof:name":"Figuur 2000",
    "wof:placetype":"venue"
},
  "geometry": {"coordinates":[5.4210939407,51.2126960754],"type":"Point"}
}