{
  "type": "Feature",
  "properties": {
    "iso:country":"BE",
    "sg:address":"Industrielaan 6",
    "sg:city":"Kuurne",
    "sg:classifiers":[
        {
            "category":"Shopping",
            "subcategory":"Clothing, Apparel, & Fashions",
            "type":"Retail Goods"
        }
    ],
    "sg:phone":"+32 56 35 37 55",
    "sg:postcode":"8520",
    "sg:province":"West-Vlaanderen",
    "sg:tags":[
        "children's",
        "clothing"
    ],
    "wof:name":"Juventas Nv",
    "wof:placetype":"venue"
},
  "geometry": {"coordinates":[3.2631781101,50.8559036255],"type":"Point"}
}