{
  "type": "Feature",
  "properties": {
    "addr:full":"Grotstraat 57 As Limburg 3668",
    "addr:housenumber":"57",
    "addr:postcode":"3668",
    "addr:street":"Grotstraat",
    "iso:country":"BE",
    "sg:address":"Grotstraat 57",
    "sg:city":"As",
    "sg:classifiers":[
        {
            "category":"Personal",
            "subcategory":"Beauty Salon",
            "type":"Services"
        }
    ],
    "sg:phone":"+32 89 65 83 01",
    "sg:postcode":"3668",
    "sg:province":"Limburg",
    "sg:tags":[
        "de",
        "coiffure"
    ],
    "wof:name":"Marleen Bijnens",
    "wof:placetype":"venue"
},
  "geometry": {"coordinates":[5.5997591019,51.0207023621],"type":"Point"}
}