{
  "type": "Feature",
  "properties": {
    "addr:full":"Onder-den-toren 4 Mechelen Antwerpen 2800",
    "addr:housenumber":"4",
    "addr:postcode":"2800",
    "addr:street":"Onder-Den-Toren",
    "iso:country":"BE",
    "sg:address":"Onder-den-toren 4",
    "sg:city":"Mechelen",
    "sg:classifiers":[
        {
            "category":"Fast Food",
            "type":"Food & Drink"
        }
    ],
    "sg:phone":"+32 15 20 23 93",
    "sg:postcode":"2800",
    "sg:province":"Antwerpen",
    "sg:tags":[
        "huis",
        "aan",
        "levering",
        "meeneem",
        "restaurant"
    ],
    "wof:name":"Onder Den Toren",
    "wof:placetype":"venue"
},
  "geometry": {"coordinates":[4.4784798622,51.0284881592],"type":"Point"}
}