{
  "type": "Feature",
  "properties": {
    "iso:country":"BE",
    "sg:address":"Stationsstraat 82",
    "sg:city":"Liedekerke",
    "sg:classifiers":[
        {
            "category":"Bars & Pubs",
            "type":"Food & Drink"
        }
    ],
    "sg:phone":"+32 53 66 45 00",
    "sg:postcode":"1770",
    "sg:province":"Vlaams-Brabant",
    "sg:tags":[
        "tavern"
    ],
    "wof:name":"Kronieksken ('t)",
    "wof:placetype":"venue"
},
  "geometry": {"coordinates":[4.0852627754,50.873462677],"type":"Point"}
}