{
  "type": "Feature",
  "properties": {
    "iso:country":"BE",
    "sg:address":"Hoogstraat 17",
    "sg:city":"Boom",
    "sg:classifiers":[
        {
            "category":"Shopping",
            "subcategory":"Clothing, Apparel, & Fashions",
            "type":"Retail Goods"
        }
    ],
    "sg:phone":"+32 3 888 18 90",
    "sg:postcode":"2850",
    "sg:province":"Antwerpen",
    "sg:tags":[
        "textile",
        "accessory",
        "clothing",
        "clothes"
    ],
    "wof:name":"Van Den Bril A Bvba",
    "wof:placetype":"venue"
},
  "geometry": {"coordinates":[4.3650150299,51.0859642029],"type":"Point"}
}