{
  "type": "Feature",
  "properties": {
    "iso:country":"BE",
    "sg:address":"Place Andr\u00c9 Ryckmans 3",
    "sg:city":"Namur",
    "sg:classifiers":[
        {
            "category":"Insurance",
            "subcategory":"Life Insurance",
            "type":"Services"
        }
    ],
    "sg:phone":"+32 81 74 77 47",
    "sg:postcode":"5000",
    "sg:province":"Namur",
    "sg:tags":[
        "assurance"
    ],
    "wof:name":"C. Seghin",
    "wof:placetype":"venue"
},
  "geometry": {"coordinates":[4.8506169319,50.4667129517],"type":"Point"}
}