{
  "type": "Feature",
  "properties": {
    "addr:full":"Korenbloemstraat 5 Turnhout Antwerpen 2300",
    "addr:housenumber":"5",
    "addr:postcode":"2300",
    "addr:street":"Korenbloemstraat",
    "iso:country":"BE",
    "sg:address":"Korenbloemstraat 5",
    "sg:city":"Turnhout",
    "sg:classifiers":[
        {
            "category":"Freight",
            "type":"Transportation"
        }
    ],
    "sg:phone":"+32 14 42 16 42",
    "sg:postcode":"2300",
    "sg:province":"Antwerpen",
    "sg:tags":[
        "-",
        "transport"
    ],
    "wof:name":"Sneyers E",
    "wof:placetype":"venue"
},
  "geometry": {"coordinates":[4.9315600395,51.3146133423],"type":"Point"}
}