{
  "type": "Feature",
  "properties": {
    "iso:country":"BE",
    "sg:address":"Avenue Des Combattants 30",
    "sg:city":"Court-saint-etienne",
    "sg:orig_category":"Sondages and enqu\u00eates",
    "sg:phone":"+32 10 61 77 04",
    "sg:postcode":"1490",
    "sg:province":"Brabant Wallon",
    "wof:name":"Strate & Go",
    "wof:placetype":"venue"
},
  "geometry": {"coordinates":[4.5636568069,50.6518440247],"type":"Point"}
}