{
  "type": "Feature",
  "properties": {
    "addr:full":"Wellingstraat 152 Beernem West-Vlaanderen 8730",
    "addr:housenumber":"152",
    "addr:postcode":"8730",
    "addr:street":"Wellingstraat",
    "iso:country":"BE",
    "sg:address":"Wellingstraat 152",
    "sg:city":"Beernem",
    "sg:orig_category":"Installation de menuiserie en bois and plastique",
    "sg:phone":"+32 50 78 93 10",
    "sg:postcode":"8730",
    "sg:province":"West-Vlaanderen",
    "wof:name":"Guy Appermans",
    "wof:placetype":"venue"
},
  "geometry": {"coordinates":[3.29271698,51.1277389526],"type":"Point"}
}