{
  "type": "Feature",
  "properties": {
    "addr:full":"Rue Belliard 97 Brussel/bruxelles 1047",
    "addr:housenumber":"97",
    "addr:postcode":"1047",
    "addr:street":"Rue Belliard;/ Bruxelles",
    "iso:country":"BE",
    "sg:address":"Rue Belliard 97",
    "sg:city":"Brussel/bruxelles",
    "sg:orig_category":"Banques and organismes de cr\u00e9dit",
    "sg:phone":"+32 2 230 58 40",
    "sg:postcode":"1047",
    "wof:name":"Cbc",
    "wof:placetype":"venue"
},
  "geometry": {"coordinates":[4.3812599182,50.8415908813],"type":"Point"}
}