{
  "type": "Feature",
  "properties": {
    "iso:country":"BE",
    "sg:address":"Calvariestraat 2",
    "sg:city":"Wervik",
    "sg:orig_category":"Rundveehouders",
    "sg:phone":"+32 56 31 11 61",
    "sg:postcode":"8940",
    "sg:province":"West-Vlaanderen",
    "wof:name":"Noel Vantomme",
    "wof:placetype":"venue"
},
  "geometry": {"coordinates":[3.0647969246,50.8003692627],"type":"Point"}
}