{
  "type": "Feature",
  "properties": {
    "iso:country":"BE",
    "sg:address":"Franchommelaan 128 Box 4",
    "sg:city":"Blankenberge",
    "sg:classifiers":[
        {
            "category":"Professional",
            "subcategory":"Printing & Photocopies",
            "type":"Services"
        }
    ],
    "sg:phone":"+32 50 42 38 29",
    "sg:postcode":"8370",
    "sg:province":"West-Vlaanderen",
    "sg:tags":[
        "machine",
        "equipment"
    ],
    "wof:name":"Umaco Nv",
    "wof:placetype":"venue"
},
  "geometry": {"coordinates":[3.1210749149,51.3142127991],"type":"Point"}
}