{
  "type": "Feature",
  "properties": {
    "addr:full":"Boulevard Emile Bockstael 34 Bruxelles Bruxelles-Capitale 1020",
    "addr:housenumber":"34",
    "addr:postcode":"1020",
    "addr:street":"Boulevard Emile Bockstael",
    "iso:country":"BE",
    "sg:address":"Boulevard Emile Bockstael 34",
    "sg:city":"Bruxelles",
    "sg:classifiers":[
        {
            "category":"Utilities",
            "subcategory":"Refuse",
            "type":"Services"
        }
    ],
    "sg:phone":"+32 2 425 66 88",
    "sg:postcode":"1020",
    "sg:province":"Bruxelles-Capitale",
    "sg:tags":[
        "removal"
    ],
    "wof:name":"Action Transport",
    "wof:placetype":"venue"
},
  "geometry": {"coordinates":[4.3435702324,50.8709869385],"type":"Point"}
}