{
  "type": "Feature",
  "properties": {
    "addr:full":"De Goudvink 36 Schilde ('s Gravenwezel) Antwerpen 2970",
    "addr:housenumber":"36",
    "addr:postcode":"2970",
    "addr:street":"De Goudvink;S",
    "iso:country":"BE",
    "sg:address":"De Goudvink 36",
    "sg:city":"Schilde ('s Gravenwezel)",
    "sg:classifiers":[
        {
            "category":"Professional",
            "subcategory":"Advertising",
            "type":"Services"
        }
    ],
    "sg:phone":"+32 3 685 49 24",
    "sg:postcode":"2970",
    "sg:province":"Antwerpen",
    "sg:tags":[
        "item",
        "-",
        "business",
        "gift",
        "promotional"
    ],
    "wof:name":"Gift And Event Services Bvba",
    "wof:placetype":"venue"
},
  "geometry": {"coordinates":[4.5415501595,51.2496337891],"type":"Point"}
}