{
  "type": "Feature",
  "properties": {
    "addr:full":"Chemin Entre Deux Bancs 8 Nassogne (ambly) Luxembourg 6953",
    "addr:housenumber":"8",
    "addr:postcode":"6953",
    "addr:street":"Chemin Entre;Bancs",
    "iso:country":"BE",
    "sg:address":"Chemin Entre Deux Bancs 8",
    "sg:city":"Nassogne (ambly)",
    "sg:classifiers":[
        {
            "category":"Real Estate",
            "subcategory":"Architect",
            "type":"Services"
        }
    ],
    "sg:phone":"+32 84 22 22 57",
    "sg:postcode":"6953",
    "sg:province":"Luxembourg",
    "wof:name":"Hausmann F",
    "wof:placetype":"venue"
},
  "geometry": {"coordinates":[5.3101811409,50.1439819336],"type":"Point"}
}