{
  "type": "Feature",
  "properties": {
    "iso:country":"BE",
    "sg:address":"Ijsbroekstraat 7",
    "sg:city":"Geraardsbergen (schendelbeke)",
    "sg:classifiers":[
        {
            "category":"Food & Beverages",
            "subcategory":"Groceries & Convenience Stores",
            "type":"Retail Goods"
        }
    ],
    "sg:phone":"+32 54 41 13 27",
    "sg:postcode":"9506",
    "sg:province":"Oost-Vlaanderen",
    "sg:tags":[
        "grocer"
    ],
    "wof:name":"Lutan",
    "wof:placetype":"venue"
},
  "geometry": {"coordinates":[3.8985300064,50.7987060547],"type":"Point"}
}