{
  "type": "Feature",
  "properties": {
    "iso:country":"BE",
    "sg:address":"Rue De Gourdinne 98",
    "sg:city":"Ham-sur-heure-nalinnes (nalinnes)",
    "sg:classifiers":[
        {
            "category":"Professional",
            "type":"Services"
        }
    ],
    "sg:phone":"+32 71 21 51 11",
    "sg:postcode":"6120",
    "sg:province":"Hainaut",
    "sg:tags":[
        "sharpening"
    ],
    "wof:name":"Centre D'affutage",
    "wof:placetype":"venue"
},
  "geometry": {"coordinates":[4.4484920502,50.3163719177],"type":"Point"}
}