{
  "type": "Feature",
  "properties": {
    "addr:full":"Oudestraat 6b Heist-op-den-berg Antwerpen 2220",
    "addr:housenumber":"6b",
    "addr:postcode":"2220",
    "addr:street":"Oudestraat",
    "iso:country":"BE",
    "sg:address":"Oudestraat 6b",
    "sg:city":"Heist-op-den-berg",
    "sg:classifiers":[
        {
            "category":"Arena",
            "subcategory":"Sports Club",
            "type":"Entertainment"
        }
    ],
    "sg:phone":"+32 477 58 63 95",
    "sg:postcode":"2220",
    "sg:province":"Antwerpen",
    "wof:name":"Ritmica Gymgroep",
    "wof:placetype":"venue"
},
  "geometry": {"coordinates":[4.7437171936,51.0694084167],"type":"Point"}
}