{
  "type": "Feature",
  "properties": {
    "iso:country":"BE",
    "sg:address":"Spijker 92",
    "sg:city":"Essen",
    "sg:orig_category":"V\u00e9t\u00e9rinaires",
    "sg:phone":"+32 3 667 25 82",
    "sg:postcode":"2910",
    "sg:province":"Antwerpen",
    "wof:name":"Ludovicus Van Loon",
    "wof:placetype":"venue"
},
  "geometry": {"coordinates":[4.4746780396,51.4506721497],"type":"Point"}
}