{
  "type": "Feature",
  "properties": {
    "iso:country":"BE",
    "sg:address":"Boomstraat 82",
    "sg:city":"Bornem",
    "sg:classifiers":[
        {
            "category":"Shopping",
            "subcategory":"Clothing, Apparel, & Fashions",
            "type":"Retail Goods"
        }
    ],
    "sg:phone":"+32 3 899 44 42",
    "sg:postcode":"2880",
    "sg:province":"Antwerpen",
    "sg:tags":[
        "lady",
        "clothing",
        "-"
    ],
    "wof:name":"Sarah Pacini",
    "wof:placetype":"venue"
},
  "geometry": {"coordinates":[4.2329211235,51.0970954895],"type":"Point"}
}