{
  "type": "Feature",
  "properties": {
    "iso:country":"BE",
    "sg:address":"Rue Edouard Deknoop 81",
    "sg:city":"Evere/evere",
    "sg:orig_category":"Artistes ind\u00e9pendants",
    "sg:phone":"+32 2 242 25 00",
    "sg:postcode":"1140",
    "sg:province":"Bruxelles-Capitale",
    "wof:name":"Marc Deschrijvere",
    "wof:placetype":"venue"
},
  "geometry": {"coordinates":[4.3995351791,50.8722305298],"type":"Point"}
}