{
  "type": "Feature",
  "properties": {
    "iso:country":"BE",
    "sg:address":"Kortrijkstraat 48",
    "sg:city":"Ingelmunster",
    "sg:orig_category":"Mat\u00e9riel de T\u00e9l\u00e9communication",
    "sg:phone":"+32 51 31 11 58",
    "sg:postcode":"8770",
    "sg:province":"West-Vlaanderen",
    "wof:name":"Vandekerckhove Vdk Mobile",
    "wof:placetype":"venue"
},
  "geometry": {"coordinates":[3.2582359314,50.9106063843],"type":"Point"}
}