{
  "type": "Feature",
  "properties": {
    "iso:country":"BE",
    "sg:address":"Stationsstraat 16",
    "sg:city":"Waarschoot",
    "sg:orig_category":"Dranken",
    "sg:phone":"+32 9 377 13 49",
    "sg:postcode":"9950",
    "sg:province":"Oost-Vlaanderen",
    "wof:name":"Nik Braeckman",
    "wof:placetype":"venue"
},
  "geometry": {"coordinates":[3.6076109409,51.1513938904],"type":"Point"}
}