{
  "type": "Feature",
  "properties": {
    "addr:full":"Rue De La Gare 123 Bertrix Luxembourg 6880",
    "addr:housenumber":"123",
    "addr:postcode":"6880",
    "addr:street":"Rue De La Gare",
    "iso:country":"BE",
    "sg:address":"Rue De La Gare 123",
    "sg:city":"Bertrix",
    "sg:classifiers":[
        {
            "category":"Fast Food",
            "type":"Food & Drink"
        }
    ],
    "sg:phone":"+32 61 41 23 54",
    "sg:postcode":"6880",
    "sg:province":"Luxembourg",
    "sg:tags":[
        "\u00c0",
        "emporter",
        "restaurants"
    ],
    "wof:name":"Au Bon Acceuil",
    "wof:placetype":"venue"
},
  "geometry": {"coordinates":[5.2632818222,49.8546905518],"type":"Point"}
}