{
  "type": "Feature",
  "properties": {
    "iso:country":"BE",
    "sg:address":"Warande 57",
    "sg:city":"Brakel (nederbrakel)",
    "sg:classifiers":[
        {
            "category":"Professional",
            "subcategory":"Testing Lab",
            "type":"Services"
        }
    ],
    "sg:phone":"+32 55 42 40 94",
    "sg:postcode":"9660",
    "sg:province":"Oost-Vlaanderen",
    "sg:tags":[
        "laboratory",
        "medical"
    ],
    "wof:name":"Medisch Laboratorium Zov",
    "wof:placetype":"venue"
},
  "geometry": {"coordinates":[3.770647049,50.8013839722],"type":"Point"}
}