{
  "type": "Feature",
  "properties": {
    "addr:full":"Spaanse Weg 2 Sint-pieters-leeuw Vlaams-Brabant 1600",
    "addr:housenumber":"2",
    "addr:postcode":"1600",
    "addr:street":"Spaanse Weg",
    "iso:country":"BE",
    "sg:address":"Spaanse Weg 2",
    "sg:city":"Sint-pieters-leeuw",
    "sg:classifiers":[
        {
            "category":"Bars & Pubs",
            "type":"Food & Drink"
        }
    ],
    "sg:phone":"+32 2 377 35 49",
    "sg:postcode":"1600",
    "sg:province":"Vlaams-Brabant",
    "wof:name":"Vissershof ('t)",
    "wof:placetype":"venue"
},
  "geometry": {"coordinates":[4.2759227753,50.7946128845],"type":"Point"}
}