{
  "type": "Feature",
  "properties": {
    "addr:full":"Generaal Eisenhowerlaan 26 Schaarbeek/schaerbeek Bruxelles-Capitale 1030",
    "addr:housenumber":"26",
    "addr:postcode":"1030",
    "addr:street":"Generaal Eisenhowerlaan",
    "iso:country":"BE",
    "sg:address":"Generaal Eisenhowerlaan 26",
    "sg:city":"Schaarbeek/schaerbeek",
    "sg:orig_category":"Advocaten and juridische adviseurs",
    "sg:phone":"+32 2 241 49 46",
    "sg:postcode":"1030",
    "sg:province":"Bruxelles-Capitale",
    "wof:name":"Br. Wets",
    "wof:placetype":"venue"
},
  "geometry": {"coordinates":[4.3823070526,50.8593063354],"type":"Point"}
}