{
  "type": "Feature",
  "properties": {
    "addr:full":"Rue Du Commerce 14 Seraing Li\u00e8ge 4100",
    "addr:housenumber":"14",
    "addr:postcode":"4100",
    "addr:street":"Rue Du Commerce",
    "iso:country":"BE",
    "sg:address":"Rue Du Commerce 14",
    "sg:city":"Seraing",
    "sg:classifiers":[
        {
            "category":"Education",
            "subcategory":"Special Training",
            "type":"Public Place"
        }
    ],
    "sg:phone":"+32 4 330 73 52",
    "sg:postcode":"4100",
    "sg:province":"Li\u00e8ge",
    "sg:tags":[
        "professional"
    ],
    "wof:name":"Cefap",
    "wof:placetype":"venue"
},
  "geometry": {"coordinates":[5.5082201958,50.6128807068],"type":"Point"}
}