{
  "type": "Feature",
  "properties": {
    "iso:country":"BE",
    "sg:address":"Rue Monseigneur Descamps 2",
    "sg:city":"Celles (escanaffles)",
    "sg:classifiers":[
        {
            "category":"Bakery",
            "type":"Food & Drink"
        }
    ],
    "sg:phone":"+32 69 45 57 28",
    "sg:postcode":"7760",
    "sg:province":"Hainaut",
    "sg:tags":[
        "confectioner",
        "baker"
    ],
    "wof:name":"Coin Gourmand",
    "wof:placetype":"venue"
},
  "geometry": {"coordinates":[3.4483110905,50.7539901733],"type":"Point"}
}