{
  "type": "Feature",
  "properties": {
    "addr:full":"Markt 68 Lokeren Oost-Vlaanderen 9160",
    "addr:housenumber":"68",
    "addr:postcode":"9160",
    "addr:street":"Markt",
    "iso:country":"BE",
    "sg:address":"Markt 68",
    "sg:city":"Lokeren",
    "sg:classifiers":[
        {
            "category":"Bars & Pubs",
            "type":"Food & Drink"
        }
    ],
    "sg:phone":"+32 9 348 33 13",
    "sg:postcode":"9160",
    "sg:province":"Oost-Vlaanderen",
    "wof:name":"Balans",
    "wof:placetype":"venue"
},
  "geometry": {"coordinates":[3.9902079105,51.1039619446],"type":"Point"}
}