{
  "type": "Feature",
  "properties": {
    "addr:full":"Rode Kruisstraat 14 Oud-turnhout Antwerpen 2360",
    "addr:housenumber":"14",
    "addr:postcode":"2360",
    "addr:street":"Rode Kruisstraat",
    "iso:country":"BE",
    "sg:address":"Rode Kruisstraat 14",
    "sg:city":"Oud-turnhout",
    "sg:orig_category":"Rev\u00eatements pour sols and murs",
    "sg:phone":"+32 14 45 08 70",
    "sg:postcode":"2360",
    "sg:province":"Antwerpen",
    "wof:name":"Erik Proost",
    "wof:placetype":"venue"
},
  "geometry": {"coordinates":[4.9804339409,51.3216438293],"type":"Point"}
}