{
  "type": "Feature",
  "properties": {
    "addr:full":"Hasseltse Dreef 84 Hasselt (stevoort) Limburg 3512",
    "addr:housenumber":"84",
    "addr:postcode":"3512",
    "addr:street":"Dreef",
    "iso:country":"BE",
    "sg:address":"Hasseltse Dreef 84",
    "sg:city":"Hasselt (stevoort)",
    "sg:classifiers":[
        {
            "category":"Real Estate",
            "subcategory":"Architect",
            "type":"Services"
        }
    ],
    "sg:phone":"+32 11 59 12 04",
    "sg:postcode":"3512",
    "sg:province":"Limburg",
    "wof:name":"Roux H",
    "wof:placetype":"venue"
},
  "geometry": {"coordinates":[5.2604289055,50.9181594849],"type":"Point"}
}