{
  "type": "Feature",
  "properties": {
    "addr:full":"Rue D'anethan 33 Schaarbeek/schaerbeek Bruxelles-Capitale 1030",
    "addr:housenumber":"33",
    "addr:postcode":"1030",
    "addr:street":"Rue D'Anethan",
    "iso:country":"BE",
    "sg:address":"Rue D'anethan 33",
    "sg:city":"Schaarbeek/schaerbeek",
    "sg:orig_category":"Enseignement sup\u00e9rieur",
    "sg:phone":"+32 2 216 21 96",
    "sg:postcode":"1030",
    "sg:province":"Bruxelles-Capitale",
    "wof:name":"Hogesch.wetenschap-kunst",
    "wof:placetype":"venue"
},
  "geometry": {"coordinates":[4.3741130829,50.8728637695],"type":"Point"}
}