{
  "type": "Feature",
  "properties": {
    "iso:country":"BE",
    "sg:address":"Markt 6ba2",
    "sg:city":"Moerbeke",
    "sg:orig_category":"Kapsalons",
    "sg:phone":"+32 9 346 72 78",
    "sg:postcode":"9180",
    "sg:province":"Oost-Vlaanderen",
    "wof:name":"Hairclub Dirk De Witte",
    "wof:placetype":"venue"
},
  "geometry": {"coordinates":[3.9420149326,51.1741905212],"type":"Point"}
}