{
  "type": "Feature",
  "properties": {
    "iso:country":"BE",
    "sg:address":"Boomgaardstraat 37",
    "sg:city":"Leuven (wilsele)",
    "sg:classifiers":[
        {
            "category":"Health Services",
            "subcategory":"Dentist",
            "type":"Services"
        }
    ],
    "sg:phone":"+32 16 44 63 45",
    "sg:postcode":"3012",
    "sg:province":"Vlaams-Brabant",
    "wof:name":"Gysemans Jan",
    "wof:placetype":"venue"
},
  "geometry": {"coordinates":[4.7216382027,50.9204216003],"type":"Point"}
}