{
  "type": "Feature",
  "properties": {
    "iso:country":"BE",
    "sg:address":"Rue De Nimy 94",
    "sg:city":"Mons",
    "sg:classifiers":[
        {
            "category":"Home & Garden",
            "subcategory":"Home Furnishings",
            "type":"Retail Goods"
        }
    ],
    "sg:phone":"+32 68 45 50 92",
    "sg:postcode":"7000",
    "sg:province":"Hainaut",
    "sg:tags":[
        "interior",
        "decoration"
    ],
    "wof:name":"Langedock M",
    "wof:placetype":"venue"
},
  "geometry": {"coordinates":[3.9556529522,50.4580726624],"type":"Point"}
}