{
  "type": "Feature",
  "properties": {
    "addr:full":"Rue Omer-pi\u00c9rard 141 Gembloux Namur 5030",
    "addr:housenumber":"141",
    "addr:postcode":"5030",
    "addr:street":"Rue Omer-Pie\u0301Rard;Namur",
    "iso:country":"BE",
    "sg:address":"Rue Omer-pi\u00c9rard 141",
    "sg:city":"Gembloux",
    "sg:orig_category":"Eleveurs de bovins. Eleveurs and marchands de porcs",
    "sg:phone":"+32 81 61 21 03",
    "sg:postcode":"5030",
    "sg:province":"Namur",
    "wof:name":"Daniel Gilet",
    "wof:placetype":"venue"
},
  "geometry": {"coordinates":[4.6628079414,50.5917320251],"type":"Point"}
}