{
  "type": "Feature",
  "properties": {
    "iso:country":"BE",
    "sg:address":"Camille Van Der Cruyssenstraat 31",
    "sg:city":"Nevele",
    "sg:classifiers":[
        {
            "category":"Home & Garden",
            "subcategory":"Home Furnishings",
            "type":"Retail Goods"
        }
    ],
    "sg:phone":"+32 9 371 83 44",
    "sg:postcode":"9850",
    "sg:province":"Oost-Vlaanderen",
    "sg:tags":[
        "interior",
        "decoration"
    ],
    "wof:name":"Creaflor Woonwinkel & Decoratie",
    "wof:placetype":"venue"
},
  "geometry": {"coordinates":[3.5498800278,51.0351638794],"type":"Point"}
}