{
  "type": "Feature",
  "properties": {
    "addr:full":"Weverstraat 69 Boechout Antwerpen 2530",
    "addr:housenumber":"69",
    "addr:postcode":"2530",
    "addr:street":"Weverstraat",
    "iso:country":"BE",
    "sg:address":"Weverstraat 69",
    "sg:city":"Boechout",
    "sg:classifiers":[
        {
            "category":"Banks & Credit Unions",
            "subcategory":"Investment Brokerage",
            "type":"Services"
        }
    ],
    "sg:phone":"+32 3 455 80 63",
    "sg:postcode":"2530",
    "sg:province":"Antwerpen",
    "sg:tags":[
        "auditor"
    ],
    "wof:name":"Loots J P",
    "wof:placetype":"venue"
},
  "geometry": {"coordinates":[4.511469841,51.1822814941],"type":"Point"}
}