{
  "type": "Feature",
  "properties": {
    "addr:full":"Leuvensesteenweg 492 Mechelen Antwerpen 2812",
    "addr:housenumber":"492",
    "addr:postcode":"2812",
    "addr:street":"Leuvensesteenweg",
    "iso:country":"BE",
    "sg:address":"Leuvensesteenweg 492",
    "sg:city":"Mechelen",
    "sg:orig_category":"V\u00e9los. Jeux and jouets. Tabac. Journaux",
    "sg:phone":"+32 15 43 05 30",
    "sg:postcode":"2812",
    "sg:province":"Antwerpen",
    "wof:name":"'t Winkeltje",
    "wof:placetype":"venue"
},
  "geometry": {"coordinates":[4.5110898018,51.0079193115],"type":"Point"}
}