{
  "type": "Feature",
  "properties": {
    "iso:country":"BE",
    "sg:address":"Heuvel 12",
    "sg:city":"Oudenaarde",
    "sg:orig_category":"Goederenvervoer over de weg HUISBRANDOLIE",
    "sg:phone":"+32 55 31 17 05",
    "sg:postcode":"9700",
    "sg:province":"Oost-Vlaanderen",
    "wof:name":"Fa. Deconinck Frank",
    "wof:placetype":"venue"
},
  "geometry": {"coordinates":[3.6426699162,50.8859214783],"type":"Point"}
}