{
  "type": "Feature",
  "properties": {
    "iso:country":"BE",
    "sg:address":"Muveld 3",
    "sg:city":"Houthalen-helchteren",
    "sg:orig_category":"Drogisterijen",
    "sg:phone":"+32 11 52 18 16",
    "sg:postcode":"3530",
    "sg:province":"Limburg",
    "wof:name":"Guido Donne",
    "wof:placetype":"venue"
},
  "geometry": {"coordinates":[5.3719201088,51.0310020447],"type":"Point"}
}