{
  "type": "Feature",
  "properties": {
    "iso:country":"BE",
    "sg:address":"Wollestraat 32",
    "sg:city":"Oostkamp",
    "sg:orig_category":"SMEEDWERK, METAALBEWERKING AND POEDERMETALLURGIE",
    "sg:phone":"+32 50 82 29 75",
    "sg:postcode":"8020",
    "sg:province":"West-Vlaanderen",
    "wof:name":"Schouteet E&j",
    "wof:placetype":"venue"
},
  "geometry": {"coordinates":[3.255918026,51.1388931274],"type":"Point"}
}