{
  "type": "Feature",
  "properties": {
    "iso:country":"BE",
    "sg:address":"Rue De La Roche 31b",
    "sg:city":"Bastogne",
    "sg:classifiers":[
        {
            "category":"Home & Garden",
            "subcategory":"Furniture",
            "type":"Retail Goods"
        }
    ],
    "sg:phone":"+32 61 21 85 76",
    "sg:postcode":"6600",
    "sg:province":"Luxembourg",
    "sg:tags":[
        "used",
        "-"
    ],
    "wof:name":"Lavoir L'entrep'eau",
    "wof:placetype":"venue"
},
  "geometry": {"coordinates":[5.7170968056,50.0089912415],"type":"Point"}
}