{
  "type": "Feature",
  "properties": {
    "addr:full":"Vlamingstraat 15 Sint-laureins Oost-Vlaanderen 9980",
    "addr:housenumber":"15",
    "addr:postcode":"9980",
    "addr:street":"Vlamingstraat",
    "iso:country":"BE",
    "sg:address":"Vlamingstraat 15",
    "sg:city":"Sint-laureins",
    "sg:classifiers":[
        {
            "category":"Health Services",
            "subcategory":"Health Practitioner",
            "type":"Services"
        }
    ],
    "sg:phone":"+32 478 96 10 34",
    "sg:postcode":"9980",
    "sg:province":"Oost-Vlaanderen",
    "sg:tags":[
        "physiotherapist"
    ],
    "wof:name":"De Craene Isabel",
    "wof:placetype":"venue"
},
  "geometry": {"coordinates":[3.5290830135,51.2421798706],"type":"Point"}
}