{
  "type": "Feature",
  "properties": {
    "addr:full":"Rue Jean Stassart 18 Crisnee Li\u00e8ge 4367",
    "addr:housenumber":"18",
    "addr:postcode":"4367",
    "addr:street":"Rue Jean Stassart",
    "iso:country":"BE",
    "sg:address":"Rue Jean Stassart 18",
    "sg:city":"Crisnee",
    "sg:orig_category":"Alimentation sp\u00e9cialis\u00e9e",
    "sg:phone":"+32 4 257 64 19",
    "sg:postcode":"4367",
    "sg:province":"Li\u00e8ge",
    "wof:name":"Thierry Razier",
    "wof:placetype":"venue"
},
  "geometry": {"coordinates":[5.3924517632,50.7111968994],"type":"Point"}
}