{
  "type": "Feature",
  "properties": {
    "iso:country":"BE",
    "sg:address":"Rue Gabrielle 17",
    "sg:city":"Rhode-saint-gen\u00e8se",
    "sg:classifiers":[
        {
            "category":"Utilities",
            "subcategory":"Water",
            "type":"Services"
        }
    ],
    "sg:phone":"+32 2 380 45 81",
    "sg:postcode":"1640",
    "sg:province":"Vlaams-Brabant",
    "sg:tags":[
        "warm",
        "-",
        "heating",
        "air"
    ],
    "wof:name":"Vanden Bossche F",
    "wof:placetype":"venue"
},
  "geometry": {"coordinates":[4.3611741066,50.7426261902],"type":"Point"}
}