{
  "type": "Feature",
  "properties": {
    "iso:country":"BE",
    "sg:address":"Place Franklin Roosevelt 31",
    "sg:city":"Ronse/renaix",
    "sg:orig_category":"Pain, p\u00e2tisseries and confiseries",
    "sg:phone":"+32 55 21 58 21",
    "sg:postcode":"9600",
    "sg:province":"Oost-Vlaanderen",
    "wof:name":"Hermes Pralines",
    "wof:placetype":"venue"
},
  "geometry": {"coordinates":[3.5996921062,50.7467689514],"type":"Point"}
}