{
  "type": "Feature",
  "properties": {
    "addr:full":"Avenue Du Dixi\u00e8me-de-ligne 103 Arlon Luxembourg 6700",
    "addr:housenumber":"103",
    "addr:postcode":"6700",
    "addr:street":"Avenue Du Dixie\u0300Me-De-Ligne",
    "iso:country":"BE",
    "sg:address":"Avenue Du Dixi\u00e8me-de-ligne 103",
    "sg:city":"Arlon",
    "sg:classifiers":[
        {
            "category":"Health Services",
            "subcategory":"Health Practitioner",
            "type":"Services"
        }
    ],
    "sg:phone":"+32 63 22 26 36",
    "sg:postcode":"6700",
    "sg:province":"Luxembourg",
    "sg:tags":[
        "physiotherapist"
    ],
    "wof:name":"Nevraumont L",
    "wof:placetype":"venue"
},
  "geometry": {"coordinates":[5.8203349113,49.6863098145],"type":"Point"}
}