{
  "type": "Feature",
  "properties": {
    "addr:full":"Steenweg Op Gierle 228/3 Turnhout Antwerpen 2300",
    "addr:housenumber":"228 / 3",
    "addr:postcode":"2300",
    "addr:street":"Steenweg Op Gierle",
    "iso:country":"BE",
    "sg:address":"Steenweg Op Gierle 228/3",
    "sg:city":"Turnhout",
    "sg:orig_category":"Stations-service and carburants. V\u00e9hicules automobiles. Entretien and r\u00e9parations de voitures",
    "sg:phone":"+32 14 41 35 94",
    "sg:postcode":"2300",
    "sg:province":"Antwerpen",
    "wof:name":"Garage Kenis",
    "wof:placetype":"venue"
},
  "geometry": {"coordinates":[4.9219031334,51.3102340698],"type":"Point"}
}