{
  "type": "Feature",
  "properties": {
    "iso:country":"BE",
    "sg:address":"Sur Le Ban 42",
    "sg:city":"Rochefort (lessive)",
    "sg:classifiers":[
        {
            "category":"Building & Trades",
            "subcategory":"Cleaning & Sanitation",
            "type":"Services"
        }
    ],
    "sg:phone":"+32 84 37 84 40",
    "sg:postcode":"5580",
    "sg:province":"Namur",
    "sg:tags":[
        "fa\u00e7ade",
        "maintenance"
    ],
    "wof:name":"Godfrind Jean",
    "wof:placetype":"venue"
},
  "geometry": {"coordinates":[5.1639299393,50.1254959106],"type":"Point"}
}