{
  "type": "Feature",
  "properties": {
    "addr:full":"Rue Du Croupet 21 Bassenge Li\u00e8ge 4690",
    "addr:housenumber":"21",
    "addr:postcode":"4690",
    "addr:street":"Rue Du Croupet",
    "iso:country":"BE",
    "sg:address":"Rue Du Croupet 21",
    "sg:city":"Bassenge",
    "sg:classifiers":[
        {
            "category":"Restaurant",
            "type":"Food & Drink"
        }
    ],
    "sg:phone":"+32 4 286 57 37",
    "sg:postcode":"4690",
    "sg:province":"Li\u00e8ge",
    "wof:name":"Restaurant Sirena Ii",
    "wof:placetype":"venue"
},
  "geometry": {"coordinates":[5.5739488602,50.7543907166],"type":"Point"}
}