{
  "type": "Feature",
  "properties": {
    "addr:full":"Rue Grande 21 Quievrain Hainaut 7380",
    "addr:housenumber":"21",
    "addr:postcode":"7380",
    "addr:street":"Rue Grande;Hainaut",
    "iso:country":"BE",
    "sg:address":"Rue Grande 21",
    "sg:city":"Quievrain",
    "sg:orig_category":"Algemeen secundair onderwijs Technisch and beroeps secundair onderwijs",
    "sg:phone":"+32 65 45 06 20",
    "sg:postcode":"7380",
    "sg:province":"Hainaut",
    "wof:name":"Centre Scolaire Don Bosco",
    "wof:placetype":"venue"
},
  "geometry": {"coordinates":[3.6828789711,50.406829834],"type":"Point"}
}