{
  "type": "Feature",
  "properties": {
    "addr:full":"Place Communale 1 Orp-jauche Brabant Wallon 1350",
    "addr:housenumber":"1",
    "addr:postcode":"1350",
    "addr:street":"Place Communale",
    "iso:country":"BE",
    "sg:address":"Place Communale 1",
    "sg:city":"Orp-jauche",
    "sg:orig_category":"Overheidsdiensten Toeristische diensten",
    "sg:phone":"+32 19 63 02 10",
    "sg:postcode":"1350",
    "sg:province":"Brabant Wallon",
    "wof:name":"Office Du Tourisme",
    "wof:placetype":"venue"
},
  "geometry": {"coordinates":[4.97920084,50.6738891602],"type":"Point"}
}