{
  "type": "Feature",
  "properties": {
    "addr:full":"Bulskampstraat 104 Veurne West-Vlaanderen 8630",
    "addr:housenumber":"104",
    "addr:postcode":"8630",
    "addr:street":"Bulskampstraat",
    "iso:country":"BE",
    "sg:address":"Bulskampstraat 104",
    "sg:city":"Veurne",
    "sg:orig_category":"Elektrische installaties voor woningen",
    "sg:phone":"+32 58 31 19 51",
    "sg:postcode":"8630",
    "sg:province":"West-Vlaanderen",
    "wof:name":"Elektro Gantois",
    "wof:placetype":"venue"
},
  "geometry": {"coordinates":[2.6489899158,51.0528793335],"type":"Point"}
}