{
  "type": "Feature",
  "properties": {
    "iso:country":"BE",
    "sg:address":"Avenue Wielemans Ceuppens 37",
    "sg:city":"Bruxelles (forest)",
    "sg:classifiers":[
        {
            "category":"Personal",
            "subcategory":"Beauty Salon",
            "type":"Services"
        }
    ],
    "sg:phone":"+32 2 344 93 03",
    "sg:postcode":"1190",
    "sg:province":"Bruxelles-Capitale",
    "wof:name":"Harmonie",
    "wof:placetype":"venue"
},
  "geometry": {"coordinates":[4.3282799721,50.8240280151],"type":"Point"}
}