{
  "type": "Feature",
  "properties": {
    "iso:country":"BE",
    "sg:address":"Bookmolenstraat 27",
    "sg:city":"Zele",
    "sg:orig_category":"Boucheries",
    "sg:phone":"+32 52 44 51 46",
    "sg:postcode":"9240",
    "sg:province":"Oost-Vlaanderen",
    "wof:name":"Beenhouwerij Hoogewys",
    "wof:placetype":"venue"
},
  "geometry": {"coordinates":[4.040102005,51.0703315735],"type":"Point"}
}