{
  "type": "Feature",
  "properties": {
    "addr:full":"Rue De Mont 281 Dison Li\u00e8ge 4820",
    "addr:housenumber":"281",
    "addr:postcode":"4820",
    "addr:street":"Rue De Mont",
    "iso:country":"BE",
    "sg:address":"Rue De Mont 281",
    "sg:city":"Dison",
    "sg:orig_category":"Eleveurs de bovins",
    "sg:phone":"+32 87 44 67 46",
    "sg:postcode":"4820",
    "sg:province":"Li\u00e8ge",
    "wof:name":"Pierre Gelis",
    "wof:placetype":"venue"
},
  "geometry": {"coordinates":[5.8636689186,50.6219062805],"type":"Point"}
}