{
  "type": "Feature",
  "properties": {
    "addr:full":"Lucien Hendrickxlei 24 Borsbeek Antwerpen 2150",
    "addr:housenumber":"24",
    "addr:postcode":"2150",
    "addr:street":"Lucien Hendrickxlei",
    "iso:country":"BE",
    "sg:address":"Lucien Hendrickxlei 24",
    "sg:city":"Borsbeek",
    "sg:orig_category":"Plomberie, chauffage and installations sanitaires. Mat\u00e9riel pour plomberie and chauffage Gr",
    "sg:phone":"+32 3 322 40 17",
    "sg:postcode":"2150",
    "sg:province":"Antwerpen",
    "wof:name":"Ab Aquabest",
    "wof:placetype":"venue"
},
  "geometry": {"coordinates":[4.4869608879,51.1914978027],"type":"Point"}
}