{
  "type": "Feature",
  "properties": {
    "addr:full":"Sportlaan 15 Meerhout Antwerpen 2450",
    "addr:housenumber":"15",
    "addr:postcode":"2450",
    "addr:street":"Sportlaan",
    "iso:country":"BE",
    "sg:address":"Sportlaan 15",
    "sg:city":"Meerhout",
    "sg:orig_category":"Agences d\u00b4interim and personnel temporaire",
    "sg:phone":"+32 14 30 38 61",
    "sg:postcode":"2450",
    "sg:province":"Antwerpen",
    "wof:name":"Tech-interim",
    "wof:placetype":"venue"
},
  "geometry": {"coordinates":[5.0690178871,51.1285400391],"type":"Point"}
}