{
  "type": "Feature",
  "properties": {
    "iso:country":"BE",
    "sg:address":"Rue De Grand Bigard 256",
    "sg:city":"Bruxelles (berchem-sainte-agathe)",
    "sg:classifiers":[
        {
            "category":"Home & Garden",
            "subcategory":"Kitchen Supply",
            "type":"Retail Goods"
        }
    ],
    "sg:phone":"+32 2 468 35 79",
    "sg:postcode":"1082",
    "sg:province":"Bruxelles-Capitale",
    "sg:tags":[
        "equipment",
        "baker",
        "-"
    ],
    "wof:name":"H V D Bvba",
    "wof:placetype":"venue"
},
  "geometry": {"coordinates":[4.2948160172,50.8603858948],"type":"Point"}
}