{
  "type": "Feature",
  "properties": {
    "iso:country":"BE",
    "sg:address":"Lobbensestraat 165",
    "sg:city":"Scherpenheuvel-zichem",
    "sg:orig_category":"Pain, p\u00e2tisseries and confiseries",
    "sg:phone":"+32 13 77 20 18",
    "sg:postcode":"3271",
    "sg:province":"Vlaams-Brabant",
    "wof:name":"Reinaert De Vos",
    "wof:placetype":"venue"
},
  "geometry": {"coordinates":[4.9540610313,50.9854621887],"type":"Point"}
}