{
  "type": "Feature",
  "properties": {
    "addr:full":"Avenue Lambeau 146 Sint-lambrechts-woluwe/woluwe-saint-lambert Bruxelles-Capitale 1200",
    "addr:housenumber":"146;/",
    "addr:postcode":"1200",
    "addr:street":"Avenue Lambeau;Sint-Lambrechts-Woluwe",
    "iso:country":"BE",
    "sg:address":"Avenue Lambeau 146",
    "sg:city":"Sint-lambrechts-woluwe/woluwe-saint-lambert",
    "sg:orig_category":"Avocats and conseillers juridiques",
    "sg:phone":"+32 2 736 12 26",
    "sg:postcode":"1200",
    "sg:province":"Bruxelles-Capitale",
    "wof:name":"S. Goethals",
    "wof:placetype":"venue"
},
  "geometry": {"coordinates":[4.4058070183,50.8445091248],"type":"Point"}
}