{
  "type": "Feature",
  "properties": {
    "addr:full":"Ninoofsesteenweg 55 Roosdaal Vlaams-Brabant 1760",
    "addr:housenumber":"55",
    "addr:postcode":"1760",
    "addr:street":"Ninoofsesteenweg",
    "iso:country":"BE",
    "sg:address":"Ninoofsesteenweg 55",
    "sg:city":"Roosdaal",
    "sg:classifiers":[
        {
            "category":"Professional",
            "subcategory":"Engineering",
            "type":"Services"
        }
    ],
    "sg:phone":"+32 54 32 67 53",
    "sg:postcode":"1760",
    "sg:province":"Vlaams-Brabant",
    "sg:tags":[
        "-"
    ],
    "wof:name":"Timmermans M",
    "wof:placetype":"venue"
},
  "geometry": {"coordinates":[4.0744271278,50.8435707092],"type":"Point"}
}