{
  "type": "Feature",
  "properties": {
    "iso:country":"BE",
    "sg:address":"Den Hert 9a",
    "sg:city":"Lille (groot)",
    "sg:classifiers":[
        {
            "category":"Personal",
            "subcategory":"Beauty Salon",
            "type":"Services"
        }
    ],
    "sg:phone":"+32 3 312 57 92",
    "sg:postcode":"2275",
    "sg:province":"Antwerpen",
    "sg:tags":[
        "de",
        "coiffure"
    ],
    "wof:name":"Alain",
    "wof:placetype":"venue"
},
  "geometry": {"coordinates":[4.7864499092,51.2632293701],"type":"Point"}
}