{
  "type": "Feature",
  "properties": {
    "iso:country":"BE",
    "sg:address":"Rue F\u00c9licien Godinasse 3",
    "sg:city":"Nandrin",
    "sg:orig_category":"Mus\u00e9es and patrimoine culturel",
    "sg:phone":"+32 85 51 11 57",
    "sg:postcode":"4550",
    "sg:province":"Li\u00e8ge",
    "wof:name":"Elan Fond. Chr. Blavier",
    "wof:placetype":"venue"
},
  "geometry": {"coordinates":[5.4190149307,50.5071563721],"type":"Point"}
}