{
  "type": "Feature",
  "properties": {
    "addr:full":"Zuidstraat 3 Veurne West-Vlaanderen 8630",
    "addr:housenumber":"3",
    "addr:postcode":"8630",
    "addr:street":"Zuidstraat",
    "iso:country":"BE",
    "sg:address":"Zuidstraat 3",
    "sg:city":"Veurne",
    "sg:orig_category":"V\u00eatements pour b\u00e9b\u00e9s and enfants. V\u00eatements pour Hommes. Eclairage et \u00e9quipements du foyer. V\u00eatement",
    "sg:phone":"+32 58 31 13 39",
    "sg:postcode":"8630",
    "sg:province":"West-Vlaanderen",
    "wof:name":"Huis Claerhoudt",
    "wof:placetype":"venue"
},
  "geometry": {"coordinates":[2.6613790989,51.0718345642],"type":"Point"}
}