{
  "type": "Feature",
  "properties": {
    "iso:country":"BE",
    "sg:address":"Laurierstraat 20",
    "sg:city":"Lebbeke",
    "sg:orig_category":"Cr\u00e9meries",
    "sg:phone":"+32 52 41 06 67",
    "sg:postcode":"9280",
    "sg:province":"Oost-Vlaanderen",
    "wof:name":"C. Mannaert",
    "wof:placetype":"venue"
},
  "geometry": {"coordinates":[4.1295337677,50.9989776611],"type":"Point"}
}