{
  "type": "Feature",
  "properties": {
    "iso:country":"BE",
    "sg:address":"Zur Dom\u00e4ne 39a",
    "sg:city":"B\u00fctgenbach",
    "sg:classifiers":[
        {
            "category":"Home & Garden",
            "subcategory":"Carpets & Floor Coverings",
            "type":"Retail Goods"
        }
    ],
    "sg:phone":"+32 80 64 05 60",
    "sg:postcode":"4750",
    "sg:province":"Li\u00e8ge",
    "sg:tags":[
        "tile"
    ],
    "wof:name":"Stoffels Sprlu",
    "wof:placetype":"venue"
},
  "geometry": {"coordinates":[6.2238960266,50.4108276367],"type":"Point"}
}