{
  "type": "Feature",
  "properties": {
    "iso:country":"BE",
    "sg:address":"Neerpedestraat 318",
    "sg:city":"Anderlecht/anderlecht",
    "sg:orig_category":"Dierenartsen",
    "sg:phone":"+32 2 520 76 05",
    "sg:postcode":"1070",
    "sg:province":"Bruxelles-Capitale",
    "wof:name":"Philippe Patriarche",
    "wof:placetype":"venue"
},
  "geometry": {"coordinates":[4.2872247696,50.8296394348],"type":"Point"}
}