{
  "type": "Feature",
  "properties": {
    "addr:full":"Rue Des Chartreux 14 Brussel/bruxelles Bruxelles-Capitale 1000",
    "addr:housenumber":"14",
    "addr:postcode":"1000",
    "addr:street":"Rue Des Chartreux;/",
    "iso:country":"BE",
    "sg:address":"Rue Des Chartreux 14",
    "sg:city":"Brussel/bruxelles",
    "sg:orig_category":"Bijouteries and horlogeries",
    "sg:phone":"+32 2 512 98 68",
    "sg:postcode":"1000",
    "sg:province":"Bruxelles-Capitale",
    "wof:name":"Boussart J-jacq&patr&pasc",
    "wof:placetype":"venue"
},
  "geometry": {"coordinates":[4.3471422195,50.8487014771],"type":"Point"}
}