{
  "type": "Feature",
  "properties": {
    "iso:country":"BE",
    "sg:address":"Rue Frans Hals 152",
    "sg:city":"Anderlecht",
    "sg:orig_category":"M\u00e9decins and sp\u00e9cialistes",
    "sg:phone":"+32 2 522 76 84",
    "sg:postcode":"1070",
    "sg:province":"Bruxelles-Capitale",
    "wof:name":"Manke Dika",
    "wof:placetype":"venue"
},
  "geometry": {"coordinates":[4.2902212143,50.8261756897],"type":"Point"}
}