{
  "type": "Feature",
  "properties": {
    "iso:country":"BE",
    "sg:address":"Tombestraat 27",
    "sg:city":"Bilzen (hees)",
    "sg:classifiers":[
        {
            "category":"Health Services",
            "subcategory":"Health Practitioner",
            "type":"Services"
        }
    ],
    "sg:phone":"+32 12 45 33 85",
    "sg:postcode":"3740",
    "sg:province":"Limburg",
    "sg:tags":[
        "physiotherapist"
    ],
    "wof:name":"Vrancken H",
    "wof:placetype":"venue"
},
  "geometry": {"coordinates":[5.6052389145,50.8486747742],"type":"Point"}
}