{
  "type": "Feature",
  "properties": {
    "addr:full":"Geelsebaan 4 Tessenderlo Limburg 3980",
    "addr:housenumber":"4",
    "addr:postcode":"3980",
    "addr:street":"Geelsebaan",
    "iso:country":"BE",
    "sg:address":"Geelsebaan 4",
    "sg:city":"Tessenderlo",
    "sg:orig_category":"Paramedische behandelingen",
    "sg:phone":"+32 13 66 50 28",
    "sg:postcode":"3980",
    "sg:province":"Limburg",
    "wof:name":"Thuiszorg",
    "wof:placetype":"venue"
},
  "geometry": {"coordinates":[5.0876178741,51.0700149536],"type":"Point"}
}