{
  "type": "Feature",
  "properties": {
    "addr:full":"Pierre Hap Lemaitrestr. 43 Etterbeek/etterbeek Bruxelles-Capitale 1040",
    "addr:housenumber":"43",
    "addr:postcode":"1040",
    "iso:country":"BE",
    "sg:address":"Pierre Hap Lemaitrestr. 43",
    "sg:city":"Etterbeek/etterbeek",
    "sg:orig_category":"Verlichting and huishoudartikelen",
    "sg:phone":"+32 2 644 35 19",
    "sg:postcode":"1040",
    "sg:province":"Bruxelles-Capitale",
    "wof:name":"Pascal Jaenen",
    "wof:placetype":"venue"
},
  "geometry": {"coordinates":[4.3858771324,50.8269538879],"type":"Point"}
}