{
  "type": "Feature",
  "properties": {
    "addr:full":"Rue Courtejoie 13bb Ciney Namur 5590",
    "addr:housenumber":"13bb",
    "addr:postcode":"5590",
    "addr:street":"Rue Courtejoie",
    "iso:country":"BE",
    "sg:address":"Rue Courtejoie 13bb",
    "sg:city":"Ciney",
    "sg:classifiers":[
        {
            "category":"Manufacturing",
            "subcategory":"Textiles",
            "type":"Manufacturing & Wholesale Goods"
        }
    ],
    "sg:phone":"+32 83 21 48 26",
    "sg:postcode":"5590",
    "sg:province":"Namur",
    "wof:name":"Bouton D'or",
    "wof:placetype":"venue"
},
  "geometry": {"coordinates":[5.1011338234,50.294921875],"type":"Point"}
}