{
  "type": "Feature",
  "properties": {
    "addr:full":"Chauss\u00c9e De Louvain 467 Schaarbeek/schaerbeek Bruxelles-Capitale 1030",
    "addr:housenumber":"467",
    "addr:postcode":"1030",
    "addr:street":"Chausse\u0301E De Louvain",
    "iso:country":"BE",
    "sg:address":"Chauss\u00c9e De Louvain 467",
    "sg:city":"Schaarbeek/schaerbeek",
    "sg:orig_category":"Quincailleries",
    "sg:phone":"+32 2 735 37 32",
    "sg:postcode":"1030",
    "sg:province":"Bruxelles-Capitale",
    "wof:name":"Brico",
    "wof:placetype":"venue"
},
  "geometry": {"coordinates":[4.3954100609,50.8544311523],"type":"Point"}
}