{
  "type": "Feature",
  "properties": {
    "iso:country":"BE",
    "sg:address":"Avenue Des Ardennes 8",
    "sg:city":"Esneux",
    "sg:classifiers":[
        {
            "category":"Banks & Credit Unions",
            "subcategory":"Investment Brokerage",
            "type":"Services"
        }
    ],
    "sg:phone":"+32 4 388 27 67",
    "sg:postcode":"4130",
    "sg:province":"Li\u00e8ge",
    "sg:tags":[
        "article",
        "b\u00e9b\u00e9s",
        "v\u00eatements",
        "pour",
        "dame"
    ],
    "wof:name":"Baby Room",
    "wof:placetype":"venue"
},
  "geometry": {"coordinates":[5.5760259628,50.5642852783],"type":"Point"}
}