{
  "type": "Feature",
  "properties": {
    "addr:full":"Enclus Du Haut 41 Mont-de-l'enclus (orroir) Hainaut 7750",
    "addr:housenumber":"41",
    "addr:postcode":"7750",
    "addr:street":"Mont-De-L'Enclus Orroir Hainaut",
    "iso:country":"BE",
    "sg:address":"Enclus Du Haut 41",
    "sg:city":"Mont-de-l'enclus (orroir)",
    "sg:classifiers":[
        {
            "category":"Bars & Pubs",
            "type":"Food & Drink"
        }
    ],
    "sg:phone":"+32 69 45 45 85",
    "sg:postcode":"7750",
    "sg:province":"Hainaut",
    "wof:name":"Palace",
    "wof:placetype":"venue"
},
  "geometry": {"coordinates":[5.7178230286,47.0204772949],"type":"Point"}
}