{
  "type": "Feature",
  "properties": {
    "iso:country":"BE",
    "sg:address":"Avenue Jean Jaur\u00e8s 14",
    "sg:city":"Courcelles",
    "sg:classifiers":[
        {
            "category":"Professional",
            "subcategory":"Lawyer & Legal Services",
            "type":"Services"
        }
    ],
    "sg:phone":"+32 71 45 99 86",
    "sg:postcode":"6180",
    "sg:province":"Hainaut",
    "wof:name":"Lippens B",
    "wof:placetype":"venue"
},
  "geometry": {"coordinates":[4.3748459816,50.4592437744],"type":"Point"}
}