{
  "type": "Feature",
  "properties": {
    "addr:full":"Avenue Charles-quint 147 Bruxelles Bruxelles-Capitale 1082",
    "addr:housenumber":"147",
    "addr:postcode":"1082",
    "addr:street":"Avenue Charles-Quint",
    "iso:country":"BE",
    "sg:address":"Avenue Charles-quint 147",
    "sg:city":"Bruxelles",
    "sg:orig_category":"Ordinateurs and \u00e9quipement informatique",
    "sg:phone":"+32 2 463 12 71",
    "sg:postcode":"1082",
    "sg:province":"Bruxelles-Capitale",
    "wof:name":"Fast-byte-system",
    "wof:placetype":"venue"
},
  "geometry": {"coordinates":[4.3092451096,50.8691329956],"type":"Point"}
}