{
  "type": "Feature",
  "properties": {
    "addr:full":"Tomberg 65 Sint-lambrechts-woluwe/woluwe-saint-lambert Bruxelles-Capitale 1200",
    "addr:housenumber":"65",
    "addr:postcode":"1200",
    "addr:street":"Tomberg",
    "iso:country":"BE",
    "sg:address":"Tomberg 65",
    "sg:city":"Sint-lambrechts-woluwe/woluwe-saint-lambert",
    "sg:orig_category":"Kantoormateriaal Krantenwinkels Rookartikelen",
    "sg:phone":"+32 2 770 53 16",
    "sg:postcode":"1200",
    "sg:province":"Bruxelles-Capitale",
    "wof:name":"Librairie Du Poseidon",
    "wof:placetype":"venue"
},
  "geometry": {"coordinates":[4.4289669991,50.8417892456],"type":"Point"}
}