{
  "type": "Feature",
  "properties": {
    "addr:full":"Rue Seyler 78 Arlon Luxembourg 6700",
    "addr:housenumber":"78",
    "addr:postcode":"6700",
    "addr:street":"Rue Seyler",
    "iso:country":"BE",
    "sg:address":"Rue Seyler 78",
    "sg:city":"Arlon",
    "sg:orig_category":"G\u00e9om\u00e8tres",
    "sg:phone":"+32 63 22 22 79",
    "sg:postcode":"6700",
    "sg:province":"Luxembourg",
    "wof:name":"Bernard Baisir",
    "wof:placetype":"venue"
},
  "geometry": {"coordinates":[5.8078842163,49.6873054504],"type":"Point"}
}