{
  "type": "Feature",
  "properties": {
    "iso:country":"BE",
    "sg:address":"Rue Du Bosquet 32",
    "sg:city":"Nandrin",
    "sg:orig_category":"Dakwerken Installatie van houten of kunststof schrijnwerk",
    "sg:phone":"+32 4 371 27 76",
    "sg:postcode":"4550",
    "sg:province":"Li\u00e8ge",
    "wof:name":"Michel Daulne",
    "wof:placetype":"venue"
},
  "geometry": {"coordinates":[5.419421196,50.5283660889],"type":"Point"}
}