{
  "type": "Feature",
  "properties": {
    "iso:country":"BE",
    "sg:address":"Rue Du Petit Pont 11",
    "sg:city":"Moeskroen/mouscron",
    "sg:orig_category":"Rev\u00eatements de sols and murs. Rev\u00eatements pour sols and murs",
    "sg:phone":"+32 56 33 18 06",
    "sg:postcode":"7712",
    "sg:province":"Hainaut",
    "wof:name":"Hooreman",
    "wof:placetype":"venue"
},
  "geometry": {"coordinates":[3.2535879612,50.714931488],"type":"Point"}
}