{
  "type": "Feature",
  "properties": {
    "addr:full":"Rue De Thiribut 30 Fernelmont Namur 5380",
    "addr:housenumber":"30",
    "addr:postcode":"5380",
    "addr:street":"Rue De Thiribut",
    "iso:country":"BE",
    "sg:address":"Rue De Thiribut 30",
    "sg:city":"Fernelmont",
    "sg:orig_category":"Varkenskwekers",
    "sg:phone":"+32 81 83 33 93",
    "sg:postcode":"5380",
    "sg:province":"Namur",
    "wof:name":"Jean-philippe Frogneux",
    "wof:placetype":"venue"
},
  "geometry": {"coordinates":[4.9861078262,50.5531463623],"type":"Point"}
}