{
  "type": "Feature",
  "properties": {
    "addr:full":"Avenue Albert Premier 217 Namur Namur 5000",
    "addr:housenumber":"217",
    "addr:postcode":"5000",
    "addr:street":"Avenue Albert Premier",
    "iso:country":"BE",
    "sg:address":"Avenue Albert Premier 217",
    "sg:city":"Namur",
    "sg:orig_category":"Ordinateurs and \u00e9quipement informatique. Jeux and jouets. Mat\u00e9riel de T\u00e9l\u00e9communication",
    "sg:phone":"+32 476 29 85 10",
    "sg:postcode":"5000",
    "sg:province":"Namur",
    "wof:name":"D&d Computer Phone",
    "wof:placetype":"venue"
},
  "geometry": {"coordinates":[4.8903341293,50.4671783447],"type":"Point"}
}