{
  "type": "Feature",
  "properties": {
    "addr:full":"Beversesteenweg 251 Roeselare West-Vlaanderen 8800",
    "addr:housenumber":"251",
    "addr:postcode":"8800",
    "addr:street":"Beversesteenweg",
    "iso:country":"BE",
    "sg:address":"Beversesteenweg 251",
    "sg:city":"Roeselare",
    "sg:classifiers":[
        {
            "category":"Manufacturing",
            "subcategory":"Signs",
            "type":"Manufacturing & Wholesale Goods"
        }
    ],
    "sg:phone":"+32 51 22 08 24",
    "sg:postcode":"8800",
    "sg:province":"West-Vlaanderen",
    "sg:tags":[
        "signalling",
        "yard",
        "road"
    ],
    "wof:name":"Arisco Nv",
    "wof:placetype":"venue"
},
  "geometry": {"coordinates":[3.1325480938,50.9600906372],"type":"Point"}
}