{
  "type": "Feature",
  "properties": {
    "iso:country":"BE",
    "sg:address":"Rue De La Croisette 94",
    "sg:city":"Courcelles",
    "sg:classifiers":[
        {
            "category":"Wholesale",
            "subcategory":"Machinery & Supplies",
            "type":"Manufacturing & Wholesale Goods"
        }
    ],
    "sg:phone":"+32 495 48 17 82",
    "sg:postcode":"6180",
    "sg:province":"Hainaut",
    "sg:tags":[
        "refrigeration",
        "-",
        "industrial",
        "commercial",
        "equipment"
    ],
    "wof:name":"Fritech Bg Sprl",
    "wof:placetype":"venue"
},
  "geometry": {"coordinates":[4.3386220932,50.4571037292],"type":"Point"}
}