{
  "type": "Feature",
  "properties": {
    "iso:country":"BE",
    "sg:address":"Place Aux Foires 23",
    "sg:city":"Durbuy",
    "sg:classifiers":[
        {
            "category":"Bars & Pubs",
            "type":"Food & Drink"
        }
    ],
    "sg:phone":"+32 86 21 16 81",
    "sg:postcode":"6940",
    "sg:province":"Luxembourg",
    "wof:name":"Esplanade (l')",
    "wof:placetype":"venue"
},
  "geometry": {"coordinates":[5.4561800957,50.3515777588],"type":"Point"}
}