{
  "type": "Feature",
  "properties": {
    "addr:full":"Galerie Du Roi 17-19 Bruxelles Bruxelles-Capitale 1000",
    "addr:postcode":"17-19;1000",
    "addr:street":"Galerie Du Roi",
    "iso:country":"BE",
    "sg:address":"Galerie Du Roi 17-19",
    "sg:city":"Bruxelles",
    "sg:classifiers":[
        {
            "category":"Wholesale",
            "subcategory":"Books, Periodicals, & Newspapers",
            "type":"Manufacturing & Wholesale Goods"
        }
    ],
    "sg:phone":"+32 2 503 42 25",
    "sg:postcode":"1000",
    "sg:province":"Bruxelles-Capitale",
    "sg:tags":[
        "publisher"
    ],
    "wof:name":"Jnf Production",
    "wof:placetype":"venue"
},
  "geometry": {"coordinates":[4.3331408501,50.8311767578],"type":"Point"}
}