{
  "type": "Feature",
  "properties": {
    "addr:full":"Route De Becco 27 Theux Li\u00e8ge 4910",
    "addr:housenumber":"27",
    "addr:postcode":"4910",
    "addr:street":"Route De Becco",
    "iso:country":"BE",
    "sg:address":"Route De Becco 27",
    "sg:city":"Theux",
    "sg:orig_category":"Medische apparatuur, orthopedische artikelen and prothesen Fab",
    "sg:phone":"+32 87 54 22 91",
    "sg:postcode":"4910",
    "sg:province":"Li\u00e8ge",
    "wof:name":"Jean-pierre Warnotte",
    "wof:placetype":"venue"
},
  "geometry": {"coordinates":[5.8144030571,50.5162315369],"type":"Point"}
}