{
  "type": "Feature",
  "properties": {
    "addr:full":"Rue Du Clocher 35 Etterbeek/etterbeek Bruxelles-Capitale 1040",
    "addr:housenumber":"35",
    "addr:postcode":"1040",
    "addr:street":"Rue Du Clocher",
    "iso:country":"BE",
    "sg:address":"Rue Du Clocher 35",
    "sg:city":"Etterbeek/etterbeek",
    "sg:orig_category":"Salles de spectacles",
    "sg:phone":"+32 2 732 38 44",
    "sg:postcode":"1040",
    "sg:province":"Bruxelles-Capitale",
    "wof:name":"Th\u00c9\u00c2tre Court S\u00c9jour",
    "wof:placetype":"venue"
},
  "geometry": {"coordinates":[4.3878908157,50.8376274109],"type":"Point"}
}