{
  "type": "Feature",
  "properties": {
    "iso:country":"BE",
    "sg:address":"Kasteelstraat 174",
    "sg:city":"Tielt",
    "sg:orig_category":"Sportclubs",
    "sg:phone":"+32 51 40 48 33",
    "sg:postcode":"8700",
    "sg:province":"West-Vlaanderen",
    "wof:name":"W.t.c. Tielt Sportief",
    "wof:placetype":"venue"
},
  "geometry": {"coordinates":[3.3183829784,50.9910469055],"type":"Point"}
}