{
  "type": "Feature",
  "properties": {
    "addr:full":"Muilenstraat 242 Liedekerke Vlaams-Brabant 1770",
    "addr:housenumber":"242",
    "addr:postcode":"1770",
    "addr:street":"Muilenstraat;Vlaams-Brabant",
    "iso:country":"BE",
    "sg:address":"Muilenstraat 242",
    "sg:city":"Liedekerke",
    "sg:classifiers":[
        {
            "category":"Health Services",
            "subcategory":"Health Practitioner",
            "type":"Services"
        }
    ],
    "sg:phone":"+32 53 68 44 79",
    "sg:postcode":"1770",
    "sg:province":"Vlaams-Brabant",
    "sg:tags":[
        "physiotherapist"
    ],
    "wof:name":"De Vos Piet",
    "wof:placetype":"venue"
},
  "geometry": {"coordinates":[4.1032099724,50.8796958923],"type":"Point"}
}