{
  "type": "Feature",
  "properties": {
    "iso:country":"BE",
    "sg:address":"Peperstraat 85",
    "sg:city":"Kampenhout",
    "sg:orig_category":"Passagiersvervoer over de weg Reisbureaus",
    "sg:phone":"+32 16 65 67 32",
    "sg:postcode":"1910",
    "sg:province":"Vlaams-Brabant",
    "wof:name":"Pardon Autocars",
    "wof:placetype":"venue"
},
  "geometry": {"coordinates":[4.5624952316,50.9214439392],"type":"Point"}
}