{
  "type": "Feature",
  "properties": {
    "addr:full":"Edingsesteenweg 66a Herne (sint-pieters-kapelle) Vlaams-Brabant 1541",
    "addr:housenumber":"66a",
    "addr:postcode":"1541",
    "addr:street":"Edingsesteenweg",
    "iso:country":"BE",
    "sg:address":"Edingsesteenweg 66a",
    "sg:city":"Herne (sint-pieters-kapelle)",
    "sg:classifiers":[
        {
            "category":"Insurance",
            "subcategory":"Insurance Agent",
            "type":"Services"
        }
    ],
    "sg:phone":"+32 2 396 09 69",
    "sg:postcode":"1541",
    "sg:province":"Vlaams-Brabant",
    "sg:tags":[
        "broker"
    ],
    "wof:name":"Reygaerts Assur Bvba",
    "wof:placetype":"venue"
},
  "geometry": {"coordinates":[4.0315170288,50.702671051],"type":"Point"}
}