{
  "type": "Feature",
  "properties": {
    "addr:full":"Markt 62 Box 10 Deinze Oost-Vlaanderen 9800",
    "addr:housenumber":"62 box 10",
    "addr:postcode":"9800",
    "addr:street":"Markt",
    "iso:country":"BE",
    "sg:address":"Markt 62 Box 10",
    "sg:city":"Deinze",
    "sg:classifiers":[
        {
            "category":"Professional",
            "subcategory":"Accounting & Tax Preparation",
            "type":"Services"
        }
    ],
    "sg:phone":"+32 9 380 85 08",
    "sg:postcode":"9800",
    "sg:province":"Oost-Vlaanderen",
    "sg:tags":[
        "bookkeeper"
    ],
    "wof:name":"Thomas M",
    "wof:placetype":"venue"
},
  "geometry": {"coordinates":[3.5265769958,50.9840698242],"type":"Point"}
}