{
  "type": "Feature",
  "properties": {
    "iso:country":"BE",
    "sg:address":"Rue Emmmanuel Hiel 19",
    "sg:city":"Schaarbeek/schaerbeek",
    "sg:orig_category":"M\u00e9decins and sp\u00e9cialistes",
    "sg:phone":"+32 2 241 95 51",
    "sg:postcode":"1030",
    "sg:province":"Bruxelles-Capitale",
    "wof:name":"A. Sasse",
    "wof:placetype":"venue"
},
  "geometry": {"coordinates":[4.3715939522,50.8665733337],"type":"Point"}
}