{
  "type": "Feature",
  "properties": {
    "iso:country":"BE",
    "sg:address":"Rue Du Village 60",
    "sg:city":"Gr\u00e2ce-hollogne (velroux)",
    "sg:classifiers":[
        {
            "category":"Building & Trades",
            "subcategory":"Cleaning & Sanitation",
            "type":"Services"
        }
    ],
    "sg:postcode":"4460",
    "sg:province":"Li\u00e8ge",
    "sg:tags":[
        "blast"
    ],
    "wof:name":"Neujean M",
    "wof:placetype":"venue"
},
  "geometry": {"coordinates":[5.4280757904,50.6396713257],"type":"Point"}
}