{
  "type": "Feature",
  "properties": {
    "addr:full":"Nijverheidslaan 1/596 Opglabbeek Limburg 3660",
    "addr:housenumber":"1 / 596",
    "addr:postcode":"3660",
    "addr:street":"Nijverheidslaan",
    "iso:country":"BE",
    "sg:address":"Nijverheidslaan 1/596",
    "sg:city":"Opglabbeek",
    "sg:classifiers":[
        {
            "category":"Structure",
            "subcategory":"Bridge",
            "type":"Public Place"
        }
    ],
    "sg:phone":"+32 89 85 54 11",
    "sg:postcode":"3660",
    "sg:province":"Limburg",
    "sg:tags":[
        "staircase",
        "handrail"
    ],
    "wof:name":"Secla B.v.b.a.",
    "wof:placetype":"venue"
},
  "geometry": {"coordinates":[5.5363087654,51.0392875671],"type":"Point"}
}