{
  "type": "Feature",
  "properties": {
    "iso:country":"BE",
    "sg:address":"Middelweg 233",
    "sg:city":"Leuven (heverlee)",
    "sg:classifiers":[
        {
            "category":"Health Services",
            "subcategory":"Doctor",
            "type":"Services"
        }
    ],
    "sg:phone":"+32 16 40 50 74",
    "sg:postcode":"3001",
    "sg:province":"Vlaams-Brabant",
    "sg:tags":[
        "medicinephysicians",
        "surgeon"
    ],
    "wof:name":"Gruwez Jacques",
    "wof:placetype":"venue"
},
  "geometry": {"coordinates":[4.6903262138,50.8510818481],"type":"Point"}
}