{
  "type": "Feature",
  "properties": {
    "addr:full":"Rue F\u00e9lix Dutry 5 Beaumont Hainaut 6500",
    "addr:housenumber":"5",
    "addr:postcode":"6500",
    "addr:street":"Rue Fe\u0301Lix Dutry;Hainaut",
    "iso:country":"BE",
    "sg:address":"Rue F\u00e9lix Dutry 5",
    "sg:city":"Beaumont",
    "sg:classifiers":[
        {
            "category":"Shopping",
            "subcategory":"Books",
            "type":"Retail Goods"
        }
    ],
    "sg:phone":"+32 71 58 92 00",
    "sg:postcode":"6500",
    "sg:province":"Hainaut",
    "sg:tags":[
        "bookseller"
    ],
    "wof:name":"Petit March\u00e9 (librairie Du)",
    "wof:placetype":"venue"
},
  "geometry": {"coordinates":[4.2371101379,50.2357749939],"type":"Point"}
}