{
  "type": "Feature",
  "properties": {
    "iso:country":"BE",
    "sg:address":"Rue Du Presbyt\u00e8re 28",
    "sg:city":"Bruxelles (molenbeek-saint-jean)",
    "sg:classifiers":[
        {
            "category":"Farming",
            "subcategory":"Poultry Farm",
            "type":"Manufacturing & Wholesale Goods"
        }
    ],
    "sg:phone":"+32 2 410 74 47",
    "sg:postcode":"1080",
    "sg:province":"Bruxelles-Capitale",
    "sg:tags":[
        "rabbit",
        "slaughterhouse"
    ],
    "wof:name":"Alfarrouj",
    "wof:placetype":"venue"
},
  "geometry": {"coordinates":[4.3385958672,50.8568382263],"type":"Point"}
}