{
  "type": "Feature",
  "properties": {
    "addr:full":"Mechelsesteenweg 660 Vilvoorde Vlaams-Brabant 1800",
    "addr:housenumber":"660",
    "addr:postcode":"1800",
    "addr:street":"Mechelsesteenweg",
    "iso:country":"BE",
    "sg:address":"Mechelsesteenweg 660",
    "sg:city":"Vilvoorde",
    "sg:orig_category":"Pi\u00e8ces and accessoires de v\u00e9hicules automobiles Gr",
    "sg:phone":"+32 2 252 58 89",
    "sg:postcode":"1800",
    "sg:province":"Vlaams-Brabant",
    "wof:name":"Fa. Donaldson",
    "wof:placetype":"venue"
},
  "geometry": {"coordinates":[4.4476919174,50.9486694336],"type":"Point"}
}