{
  "type": "Feature",
  "properties": {
    "addr:full":"Place Dumon 1 Sint-pieters-woluwe/woluwe-sai Bruxelles-Capitale 1150",
    "addr:housenumber":"1",
    "addr:postcode":"1150",
    "addr:street":"Place Dumon",
    "iso:country":"BE",
    "sg:address":"Place Dumon 1",
    "sg:city":"Sint-pieters-woluwe/woluwe-sai",
    "sg:orig_category":"Banques and organismes de cr\u00e9dit",
    "sg:phone":"+32 2 779 20 60",
    "sg:postcode":"1150",
    "sg:province":"Bruxelles-Capitale",
    "wof:name":"Bbl",
    "wof:placetype":"venue"
},
  "geometry": {"coordinates":[4.4648599625,50.8392753601],"type":"Point"}
}