{
  "type": "Feature",
  "properties": {
    "addr:full":"Rue Grand\u00b4route 442 Beyne-heusay Li\u00e8ge 4610",
    "addr:housenumber":"442",
    "addr:postcode":"4610",
    "addr:street":"Rue Grand\u00b4Route",
    "iso:country":"BE",
    "sg:address":"Rue Grand\u00b4route 442",
    "sg:city":"Beyne-heusay",
    "sg:orig_category":"Brood, gebak and snoepgoed",
    "sg:phone":"+32 4 358 36 12",
    "sg:postcode":"4610",
    "sg:province":"Li\u00e8ge",
    "wof:name":"Au Panier Gourmand",
    "wof:placetype":"venue"
},
  "geometry": {"coordinates":[5.664285183,50.6182556152],"type":"Point"}
}