{
  "type": "Feature",
  "properties": {
    "addr:full":"Sint-michielsplein 12-14 Roeselare West-Vlaanderen 8800",
    "addr:housenumber":"12-14",
    "addr:postcode":"8800",
    "addr:street":"Sint-Michielsplein",
    "iso:country":"BE",
    "sg:address":"Sint-michielsplein 12-14",
    "sg:city":"Roeselare",
    "sg:classifiers":[
        {
            "category":"Shopping",
            "subcategory":"Clothing, Apparel, & Fashions",
            "type":"Retail Goods"
        }
    ],
    "sg:phone":"+32 51 24 40 10",
    "sg:postcode":"8800",
    "sg:province":"West-Vlaanderen",
    "sg:tags":[
        "boutique"
    ],
    "wof:name":"Baerts",
    "wof:placetype":"venue"
},
  "geometry": {"coordinates":[3.1232540607,50.9439430237],"type":"Point"}
}