{
  "type": "Feature",
  "properties": {
    "addr:full":"Place Du Prieur\u00c9 1 Charleroi Hainaut 6040",
    "addr:housenumber":"1",
    "addr:postcode":"6040",
    "addr:street":"Place Du Prieure\u0301;Hainaut",
    "iso:country":"BE",
    "sg:address":"Place Du Prieur\u00c9 1",
    "sg:city":"Charleroi",
    "sg:orig_category":"Instellingen voor probleemkinderen Kindertehuizen Maatschappelijke dienstverlening",
    "sg:phone":"+32 71 35 34 76",
    "sg:postcode":"6040",
    "sg:province":"Hainaut",
    "wof:name":"Maison Des Eclaireurs",
    "wof:placetype":"venue"
},
  "geometry": {"coordinates":[4.4063811302,50.4456672668],"type":"Point"}
}