{
  "type": "Feature",
  "properties": {
    "addr:full":"Rue Des Roches 43 Walcourt Namur 5651",
    "addr:housenumber":"43",
    "addr:postcode":"5651",
    "addr:street":"Rue Des Roches",
    "iso:country":"BE",
    "sg:address":"Rue Des Roches 43",
    "sg:city":"Walcourt",
    "sg:classifiers":[
        {
            "category":"Communications",
            "subcategory":"Television Station",
            "type":"Services"
        }
    ],
    "sg:phone":"+32 71 65 56 57",
    "sg:postcode":"5651",
    "sg:province":"Namur",
    "sg:tags":[
        "video",
        "audio",
        "verhuur"
    ],
    "wof:name":"Vid\u00c9o Star",
    "wof:placetype":"venue"
},
  "geometry": {"coordinates":[4.4262080193,50.2824401855],"type":"Point"}
}