{
  "type": "Feature",
  "properties": {
    "addr:full":"Rue Du Tchaurnia 2 Houyet Namur 5560",
    "addr:housenumber":"2",
    "addr:postcode":"5560",
    "addr:street":"Rue Du Tchaurnia",
    "iso:country":"BE",
    "sg:address":"Rue Du Tchaurnia 2",
    "sg:city":"Houyet",
    "sg:orig_category":"RESTAURANTS: POUR COLLECTIVIT\u00c9S",
    "sg:phone":"+32 82 74 48 31",
    "sg:postcode":"5560",
    "sg:province":"Namur",
    "wof:name":"Alimental",
    "wof:placetype":"venue"
},
  "geometry": {"coordinates":[4.8924050331,50.1668701172],"type":"Point"}
}