{
  "type": "Feature",
  "properties": {
    "addr:full":"Rue Du Parc Industriel Marche-en-famenne Luxembourg 6900",
    "addr:postcode":"6900",
    "addr:street":"Rue Du Parc Industriel",
    "iso:country":"BE",
    "sg:address":"Rue Du Parc Industriel",
    "sg:city":"Marche-en-famenne",
    "sg:orig_category":"Blanchisseries and teintureries",
    "sg:phone":"+32 84 31 22 13",
    "sg:postcode":"6900",
    "sg:province":"Luxembourg",
    "wof:name":"Bauche Blanchisserie",
    "wof:placetype":"venue"
},
  "geometry": {"coordinates":[5.3210101128,50.2177276611],"type":"Point"}
}