{
  "type": "Feature",
  "properties": {
    "iso:country":"BE",
    "sg:address":"Av. Commandant Lothaire 61",
    "sg:city":"Etterbeek/etterbeek",
    "sg:orig_category":"M\u00e9decins and sp\u00e9cialistes",
    "sg:phone":"+32 2 735 21 00",
    "sg:postcode":"1040",
    "sg:province":"Bruxelles-Capitale",
    "wof:name":"Yvonne Dandoy",
    "wof:placetype":"venue"
},
  "geometry": {"coordinates":[4.4048118591,50.8281593323],"type":"Point"}
}