{
  "type": "Feature",
  "properties": {
    "addr:full":"Rue De Pietrain 39 Jodoigne Brabant Wallon 1370",
    "addr:housenumber":"39",
    "addr:postcode":"1370",
    "addr:street":"Rue De Pietrain",
    "iso:country":"BE",
    "sg:address":"Rue De Pietrain 39",
    "sg:city":"Jodoigne",
    "sg:orig_category":"Quincailleries",
    "sg:phone":"+32 10 81 07 49",
    "sg:postcode":"1370",
    "sg:province":"Brabant Wallon",
    "wof:name":"Super Bois Jodoigne",
    "wof:placetype":"venue"
},
  "geometry": {"coordinates":[4.8753738403,50.724281311],"type":"Point"}
}