{
  "type": "Feature",
  "properties": {
    "addr:full":"Rue Alphonse Poullet 32a Moeskroen/mouscron Hainaut 7711",
    "addr:housenumber":"32a",
    "addr:postcode":"7711",
    "addr:street":"Rue Alphonse Poullet",
    "iso:country":"BE",
    "sg:address":"Rue Alphonse Poullet 32a",
    "sg:city":"Moeskroen/mouscron",
    "sg:orig_category":"Animations diverses",
    "sg:phone":"+32 56 48 60 85",
    "sg:postcode":"7711",
    "sg:province":"Hainaut",
    "wof:name":"Abc D\u00c9cor",
    "wof:placetype":"venue"
},
  "geometry": {"coordinates":[3.3047819138,50.7295684814],"type":"Point"}
}