{
  "type": "Feature",
  "properties": {
    "addr:full":"Grote Baan 332 Drogenbos Vlaams-Brabant 1620",
    "addr:housenumber":"332",
    "addr:postcode":"1620",
    "addr:street":"Grote Baan",
    "iso:country":"BE",
    "sg:address":"Grote Baan 332",
    "sg:city":"Drogenbos",
    "sg:orig_category":"Herstellingen and onderhoud van auto's Voertuigen",
    "sg:phone":"+32 2 334 40 40",
    "sg:postcode":"1620",
    "sg:province":"Vlaams-Brabant",
    "wof:name":"Dancar Technic",
    "wof:placetype":"venue"
},
  "geometry": {"coordinates":[4.3116779327,50.7897033691],"type":"Point"}
}