{
  "type": "Feature",
  "properties": {
    "addr:full":"Kleerkopersstraat 39 Brussel/bruxelles Bruxelles-Capitale 1000",
    "addr:housenumber":"39",
    "addr:postcode":"1000",
    "addr:street":"Kleerkopersstraat;/",
    "iso:country":"BE",
    "sg:address":"Kleerkopersstraat 39",
    "sg:city":"Brussel/bruxelles",
    "sg:orig_category":"Dameskledingzaken",
    "sg:phone":"+32 2 218 22 38",
    "sg:postcode":"1000",
    "sg:province":"Bruxelles-Capitale",
    "wof:name":"Rochar Couture",
    "wof:placetype":"venue"
},
  "geometry": {"coordinates":[4.3528017998,50.8490562439],"type":"Point"}
}