{
  "type": "Feature",
  "properties": {
    "iso:country":"BE",
    "sg:address":"Avenue Baron Seutin 7",
    "sg:city":"Waterloo",
    "sg:orig_category":"Airconditioning and ventilatie Herstelling aan huis van huishoudartikelen Loodgieterij, verwarming a",
    "sg:phone":"+32 2 384 87 93",
    "sg:postcode":"1410",
    "sg:province":"Brabant Wallon",
    "wof:name":"Thermitra",
    "wof:placetype":"venue"
},
  "geometry": {"coordinates":[4.3735098839,50.7040176392],"type":"Point"}
}