{
  "type": "Feature",
  "properties": {
    "iso:country":"BE",
    "sg:address":"7",
    "sg:city":"Ondernemingenstraat 8630 Veurne",
    "sg:classifiers":[
        {
            "category":"Wholesale",
            "subcategory":"Meat",
            "type":"Manufacturing & Wholesale Goods"
        }
    ],
    "sg:phone":"+32 58 31 00 31",
    "sg:postcode":"7",
    "sg:tags":[
        "food",
        "cooked",
        "product",
        "related"
    ],
    "wof:name":"Mortier Catering Nv",
    "wof:placetype":"venue"
},
  "geometry": {"coordinates":[2.677850008,51.0620689392],"type":"Point"}
}