{
  "type": "Feature",
  "properties": {
    "iso:country":"BE",
    "sg:address":"Beukenstraat 10",
    "sg:city":"Houthalen-helchteren (houthalen)",
    "sg:classifiers":[
        {
            "category":"Wholesale",
            "subcategory":"Books, Periodicals, & Newspapers",
            "type":"Manufacturing & Wholesale Goods"
        }
    ],
    "sg:phone":"+32 11 60 21 34",
    "sg:postcode":"3530",
    "sg:province":"Limburg",
    "sg:tags":[
        "publisher"
    ],
    "wof:name":"I.p.p. Nv",
    "wof:placetype":"venue"
},
  "geometry": {"coordinates":[5.3905382156,51.0216369629],"type":"Point"}
}