{
  "type": "Feature",
  "properties": {
    "addr:full":"Wilsonstraat 37 Sint-katelijne-waver Antwerpen 2860",
    "addr:housenumber":"37",
    "addr:postcode":"2860",
    "addr:street":"Wilsonstraat",
    "iso:country":"BE",
    "sg:address":"Wilsonstraat 37",
    "sg:city":"Sint-katelijne-waver",
    "sg:orig_category":"Pain, p\u00e2tisseries and confiseries",
    "sg:phone":"+32 15 31 01 73",
    "sg:postcode":"2860",
    "sg:province":"Antwerpen",
    "wof:name":"Angele Smulders",
    "wof:placetype":"venue"
},
  "geometry": {"coordinates":[4.5342588425,51.0729598999],"type":"Point"}
}