{
  "type": "Feature",
  "properties": {
    "addr:full":"Schatting 8 Zedelgem West-Vlaanderen 8210",
    "addr:housenumber":"8",
    "addr:postcode":"8210",
    "addr:street":"Schatting",
    "iso:country":"BE",
    "sg:address":"Schatting 8",
    "sg:city":"Zedelgem",
    "sg:classifiers":[
        {
            "category":"Wholesale",
            "subcategory":"Farm Supplies",
            "type":"Manufacturing & Wholesale Goods"
        }
    ],
    "sg:phone":"+32 50 20 94 97",
    "sg:postcode":"8210",
    "sg:province":"West-Vlaanderen",
    "sg:tags":[
        "machine",
        "agricoles",
        "mat\u00e9riel",
        "gr"
    ],
    "wof:name":"Van Laecke Luc",
    "wof:placetype":"venue"
},
  "geometry": {"coordinates":[3.1444959641,51.1366462708],"type":"Point"}
}