{
  "type": "Feature",
  "properties": {
    "iso:country":"BE",
    "sg:address":"Rue De Valenciennes 424",
    "sg:city":"Boussu",
    "sg:classifiers":[
        {
            "category":"Retail",
            "subcategory":"Veterinary Services",
            "type":"Services"
        }
    ],
    "sg:phone":"+32 65 77 77 12",
    "sg:postcode":"7300",
    "sg:province":"Hainaut",
    "sg:tags":[
        "veterinarian"
    ],
    "wof:name":"Godin V",
    "wof:placetype":"venue"
},
  "geometry": {"coordinates":[3.8066599369,50.4320602417],"type":"Point"}
}