{
  "type": "Feature",
  "properties": {
    "iso:country":"BE",
    "sg:address":"Prins-bischopssingel 25",
    "sg:city":"Hasselt",
    "sg:orig_category":"Belastingconsulenten Diverse juridische dienstverlening Verzekeringsmakelaars and experts",
    "sg:phone":"+32 11 27 31 23",
    "sg:postcode":"3500",
    "sg:province":"Limburg",
    "wof:name":"Bureau Kusters",
    "wof:placetype":"venue"
},
  "geometry": {"coordinates":[5.3434062004,50.9147796631],"type":"Point"}
}