{
  "type": "Feature",
  "properties": {
    "addr:full":"Rue De La Croisette 48 Hannut Li\u00e8ge 4280",
    "addr:housenumber":"48",
    "addr:postcode":"4280",
    "addr:street":"Rue De La Croisette",
    "iso:country":"BE",
    "sg:address":"Rue De La Croisette 48",
    "sg:city":"Hannut",
    "sg:classifiers":[
        {
            "category":"Farming",
            "subcategory":"Livestock Farm",
            "type":"Manufacturing & Wholesale Goods"
        }
    ],
    "sg:phone":"+32 495 23 29 40",
    "sg:postcode":"4280",
    "sg:province":"Li\u00e8ge",
    "sg:tags":[
        "stud"
    ],
    "wof:name":"Horse Perform B\u00e9n\u00e9lux",
    "wof:placetype":"venue"
},
  "geometry": {"coordinates":[5.065196991,50.6608505249],"type":"Point"}
}