{
  "type": "Feature",
  "properties": {
    "iso:country":"BE",
    "sg:address":"Britse Lei 94 Box 71",
    "sg:city":"Antwerpen",
    "sg:classifiers":[
        {
            "category":"Professional",
            "subcategory":"Lawyer & Legal Services",
            "type":"Services"
        }
    ],
    "sg:phone":"+32 3 234 33 57",
    "sg:postcode":"2000",
    "sg:province":"Antwerpen",
    "wof:name":"Vandemeulebroucke P",
    "wof:placetype":"venue"
},
  "geometry": {"coordinates":[4.4031801224,51.2092208862],"type":"Point"}
}