{
  "type": "Feature",
  "properties": {
    "addr:full":"Rue Du Vingt-huit Juin 1919 118 Courcelles Hainaut 6180",
    "addr:housenumber":"118",
    "addr:postcode":"6180",
    "addr:street":"Rue Du Vingt-Huit Juin 1919",
    "iso:country":"BE",
    "sg:address":"Rue Du Vingt-huit Juin 1919 118",
    "sg:city":"Courcelles",
    "sg:classifiers":[
        {
            "category":"Health Services",
            "subcategory":"Health Practitioner",
            "type":"Services"
        }
    ],
    "sg:phone":"+32 71 45 62 03",
    "sg:postcode":"6180",
    "sg:province":"Hainaut",
    "sg:tags":[
        "physiotherapist"
    ],
    "wof:name":"Velghe Laurent",
    "wof:placetype":"venue"
},
  "geometry": {"coordinates":[4.3662309647,50.461807251],"type":"Point"}
}