{
  "type": "Feature",
  "properties": {
    "iso:country":"BE",
    "sg:address":"Klaterstraat 35",
    "sg:city":"Rijkevorsel",
    "sg:classifiers":[
        {
            "category":"Wholesale",
            "subcategory":"Plants",
            "type":"Manufacturing & Wholesale Goods"
        }
    ],
    "sg:phone":"+32 3 314 61 20",
    "sg:postcode":"2310",
    "sg:province":"Antwerpen",
    "sg:tags":[
        "decoration",
        "flower",
        "-"
    ],
    "wof:name":"Groene Schort (de)",
    "wof:placetype":"venue"
},
  "geometry": {"coordinates":[4.7704811096,51.3641471863],"type":"Point"}
}