{
  "type": "Feature",
  "properties": {
    "addr:full":"Naaldweg 79 Beringen (koersel) Limburg 3582",
    "addr:housenumber":"79",
    "addr:postcode":"3582",
    "addr:street":"Naaldweg",
    "iso:country":"BE",
    "sg:address":"Naaldweg 79",
    "sg:city":"Beringen (koersel)",
    "sg:classifiers":[
        {
            "category":"Home & Garden",
            "subcategory":"Carpets & Floor Coverings",
            "type":"Retail Goods"
        }
    ],
    "sg:phone":"+32 11 43 44 21",
    "sg:postcode":"3582",
    "sg:province":"Limburg",
    "sg:tags":[
        "layer",
        "mosaicists"
    ],
    "wof:name":"Thoelen D Bvba",
    "wof:placetype":"venue"
},
  "geometry": {"coordinates":[5.2708749771,51.0595359802],"type":"Point"}
}