{
  "type": "Feature",
  "properties": {
    "iso:country":"BE",
    "sg:address":"Memorial De Mardasson",
    "sg:city":"Bastogne",
    "sg:classifiers":[
        {
            "category":"Museum",
            "type":"Entertainment"
        }
    ],
    "sg:phone":"+32 61 21 14 13",
    "sg:postcode":"6600",
    "sg:province":"Luxembourg",
    "wof:name":"Bastogne Historical Center",
    "wof:placetype":"venue"
},
  "geometry": {"coordinates":[5.7373328209,50.0110855103],"type":"Point"}
}