{
  "type": "Feature",
  "properties": {
    "iso:country":"BE",
    "sg:address":"Pieter De Smetstraat 14",
    "sg:city":"Lokeren",
    "sg:orig_category":"Non-Classified Establishments",
    "sg:phone":"+32 9 349 09 44",
    "sg:postcode":"9160",
    "sg:province":"Oost-Vlaanderen",
    "wof:name":"Anti Slip Labo Bvba",
    "wof:placetype":"venue"
},
  "geometry": {"coordinates":[3.9968950748,51.0912513733],"type":"Point"}
}