{
  "type": "Feature",
  "properties": {
    "iso:country":"BE",
    "sg:address":"Lattenklieversstraat 140",
    "sg:city":"Beernem (sint-joris)",
    "sg:classifiers":[
        {
            "category":"Banks & Credit Unions",
            "subcategory":"Financial Services",
            "type":"Services"
        }
    ],
    "sg:phone":"+32 50 79 20 38",
    "sg:postcode":"8730",
    "sg:province":"West-Vlaanderen",
    "sg:tags":[
        "loan",
        "mortgage"
    ],
    "wof:name":"Stock R",
    "wof:placetype":"venue"
},
  "geometry": {"coordinates":[3.358134985,51.1261749268],"type":"Point"}
}