{
  "type": "Feature",
  "properties": {
    "iso:country":"BE",
    "sg:address":"Lange Beeldekensstraat 298-302",
    "sg:city":"Antwerpen",
    "sg:classifiers":[
        {
            "category":"Food & Beverages",
            "subcategory":"Supermarket",
            "type":"Retail Goods"
        }
    ],
    "sg:phone":"+32 3 271 12 11",
    "sg:postcode":"2060",
    "sg:province":"Antwerpen",
    "sg:tags":[
        "department",
        "store"
    ],
    "wof:name":"Proxy Stuivenberg Bvba",
    "wof:placetype":"venue"
},
  "geometry": {"coordinates":[4.4356031418,51.2221183777],"type":"Point"}
}