{
  "type": "Feature",
  "properties": {
    "addr:full":"Hondstraat 83 Tielt West-Vlaanderen 8700",
    "addr:housenumber":"83",
    "addr:postcode":"8700",
    "addr:street":"Hondstraat",
    "iso:country":"BE",
    "sg:address":"Hondstraat 83",
    "sg:city":"Tielt",
    "sg:classifiers":[
        {
            "category":"Health Services",
            "subcategory":"Doctor",
            "type":"Services"
        }
    ],
    "sg:phone":"+32 51 40 25 26",
    "sg:postcode":"8700",
    "sg:province":"West-Vlaanderen",
    "sg:tags":[
        "medicinephysicians",
        "surgeon"
    ],
    "wof:name":"Heeman J",
    "wof:placetype":"venue"
},
  "geometry": {"coordinates":[3.3089981079,51.0022239685],"type":"Point"}
}