{
  "type": "Feature",
  "properties": {
    "addr:full":"Rue Des Grands Carmes 17 Bruxelles Bruxelles-Capitale 1000",
    "addr:housenumber":"17",
    "addr:postcode":"1000",
    "addr:street":"Rue Des Grands Carmes",
    "iso:country":"BE",
    "sg:address":"Rue Des Grands Carmes 17",
    "sg:city":"Bruxelles",
    "sg:classifiers":[
        {
            "category":"Shopping",
            "subcategory":"Books",
            "type":"Retail Goods"
        }
    ],
    "sg:phone":"+32 2 511 61 40",
    "sg:postcode":"1000",
    "sg:province":"Bruxelles-Capitale",
    "sg:tags":[
        "antiquarian",
        "trade"
    ],
    "wof:name":"De Slegte (boekhandel)",
    "wof:placetype":"venue"
},
  "geometry": {"coordinates":[4.3487858772,50.8453102112],"type":"Point"}
}