{
  "type": "Feature",
  "properties": {
    "iso:country":"BE",
    "sg:address":"Quai Du Halage 37",
    "sg:city":"Saint-nicolas (tilleur)",
    "sg:classifiers":[
        {
            "category":"Autos & Motor Vehicles",
            "subcategory":"Automobile Sales",
            "type":"Retail Goods"
        }
    ],
    "sg:phone":"+32 4 233 81 81",
    "sg:postcode":"4420",
    "sg:province":"Li\u00e8ge",
    "sg:tags":[
        "car",
        "used",
        "-"
    ],
    "wof:name":"Lba Motors Sprl",
    "wof:placetype":"venue"
},
  "geometry": {"coordinates":[5.5211100578,50.6184806824],"type":"Point"}
}