{
  "type": "Feature",
  "properties": {
    "iso:country":"BE",
    "sg:address":"Pallekensbergstraat 40",
    "sg:city":"Hasselt (kuringen)",
    "sg:classifiers":[
        {
            "category":"Building & Trades",
            "subcategory":"Pest Control",
            "type":"Services"
        }
    ],
    "sg:phone":"+32 11 23 22 16",
    "sg:postcode":"3511",
    "sg:province":"Limburg",
    "sg:tags":[
        "painting",
        "contractor"
    ],
    "wof:name":"Schildersbedrijf Cox Bvba",
    "wof:placetype":"venue"
},
  "geometry": {"coordinates":[5.3034238815,50.9432487488],"type":"Point"}
}