{
  "type": "Feature",
  "properties": {
    "addr:full":"Rijksweg 259 Maasmechelen Limburg 3630",
    "addr:housenumber":"259",
    "addr:postcode":"3630",
    "addr:street":"Rijksweg",
    "iso:country":"BE",
    "sg:address":"Rijksweg 259",
    "sg:city":"Maasmechelen",
    "sg:classifiers":[
        {
            "category":"Insurance",
            "subcategory":"Life Insurance",
            "type":"Services"
        }
    ],
    "sg:phone":"+32 89 76 09 37",
    "sg:postcode":"3630",
    "sg:province":"Limburg",
    "sg:tags":[
        "assurance"
    ],
    "wof:name":"Kantoor Leona",
    "wof:placetype":"venue"
},
  "geometry": {"coordinates":[5.6986460686,50.9727325439],"type":"Point"}
}