{
  "type": "Feature",
  "properties": {
    "addr:full":"Boomgaardstraat 20 Zemst Vlaams-Brabant 1981",
    "addr:housenumber":"20",
    "addr:postcode":"1981",
    "addr:street":"Boomgaardstraat;Vlaams-Brabant",
    "iso:country":"BE",
    "sg:address":"Boomgaardstraat 20",
    "sg:city":"Zemst",
    "sg:classifiers":[
        {
            "category":"Arena",
            "subcategory":"Sports Club",
            "type":"Entertainment"
        }
    ],
    "sg:phone":"+32 15 61 35 95",
    "sg:postcode":"1981",
    "sg:province":"Vlaams-Brabant",
    "sg:tags":[
        "de"
    ],
    "wof:name":"B.c. Union St.gillis",
    "wof:placetype":"venue"
},
  "geometry": {"coordinates":[4.5123667717,50.9942436218],"type":"Point"}
}