{
  "type": "Feature",
  "properties": {
    "iso:country":"BE",
    "sg:address":"Route De Beaumont 57a",
    "sg:city":"Thuin (thuillies)",
    "sg:classifiers":[
        {
            "category":"Building & Trades",
            "subcategory":"Cleaning & Sanitation",
            "type":"Services"
        }
    ],
    "sg:phone":"+32 71 53 42 86",
    "sg:postcode":"6536",
    "sg:province":"Hainaut",
    "sg:tags":[
        "equipment",
        "industrial",
        "maintenance"
    ],
    "wof:name":"Servotte M (ets)",
    "wof:placetype":"venue"
},
  "geometry": {"coordinates":[4.3365578651,50.3192329407],"type":"Point"}
}