{
  "type": "Feature",
  "properties": {
    "addr:full":"Rue De L\u00b4abbaye 35 Ath Hainaut 7800",
    "addr:housenumber":"35",
    "addr:postcode":"7800",
    "addr:street":"Rue De L\u00b4Abbaye",
    "iso:country":"BE",
    "sg:address":"Rue De L\u00b4abbaye 35",
    "sg:city":"Ath",
    "sg:orig_category":"Incassobureaus and kredietcontrole",
    "sg:phone":"+32 68 28 07 68",
    "sg:postcode":"7800",
    "sg:province":"Hainaut",
    "wof:name":"Alnath",
    "wof:placetype":"venue"
},
  "geometry": {"coordinates":[3.7868330479,50.6352424622],"type":"Point"}
}