{
  "type": "Feature",
  "properties": {
    "iso:country":"BE",
    "sg:address":"Rue De La Procession 75ba/1",
    "sg:city":"Anderlecht/anderlecht",
    "sg:orig_category":"Epiceries",
    "sg:phone":"+32 2 520 47 01",
    "sg:postcode":"1070",
    "sg:province":"Bruxelles-Capitale",
    "wof:name":"Marie-paule Van Helden",
    "wof:placetype":"venue"
},
  "geometry": {"coordinates":[4.3031520844,50.8350143433],"type":"Point"}
}