{
  "type": "Feature",
  "properties": {
    "iso:country":"BE",
    "sg:address":"Steenweg 338",
    "sg:city":"Denderleeuw",
    "sg:orig_category":"Winkelinrichting and handelsuitrusting Gh",
    "sg:phone":"+32 53 66 47 07",
    "sg:postcode":"9470",
    "sg:province":"Oost-Vlaanderen",
    "wof:name":"Leon Raman",
    "wof:placetype":"venue"
},
  "geometry": {"coordinates":[4.0633158684,50.8920822144],"type":"Point"}
}