{
  "type": "Feature",
  "properties": {
    "addr:full":"Kachtemsestraat 96 Izegem West-Vlaanderen 8870",
    "addr:housenumber":"96",
    "addr:postcode":"8870",
    "addr:street":"Kachtemsestraat",
    "iso:country":"BE",
    "sg:address":"Kachtemsestraat 96",
    "sg:city":"Izegem",
    "sg:classifiers":[
        {
            "category":"Retail",
            "subcategory":"Veterinary Services",
            "type":"Services"
        }
    ],
    "sg:phone":"+32 51 30 39 51",
    "sg:postcode":"8870",
    "sg:province":"West-Vlaanderen",
    "sg:tags":[
        "veterinarian"
    ],
    "wof:name":"Deraedt C",
    "wof:placetype":"venue"
},
  "geometry": {"coordinates":[3.2026469707,50.9311294556],"type":"Point"}
}