{
  "type": "Feature",
  "properties": {
    "iso:country":"BE",
    "sg:address":"Diksmuidsestraat 69",
    "sg:city":"Ieper",
    "sg:classifiers":[
        {
            "category":"Shopping",
            "subcategory":"Clothing, Apparel, & Fashions",
            "type":"Retail Goods"
        }
    ],
    "sg:phone":"+32 57 21 30 12",
    "sg:postcode":"8900",
    "sg:province":"West-Vlaanderen",
    "sg:tags":[
        "v\u00eatements",
        "pour",
        "dame"
    ],
    "wof:name":"Huis Do-kri-do",
    "wof:placetype":"venue"
},
  "geometry": {"coordinates":[2.8863248825,50.8539886475],"type":"Point"}
}