{
  "type": "Feature",
  "properties": {
    "addr:full":"Brugsesteenweg 2a Hulste West-Vlaanderen 8531",
    "addr:housenumber":"2a",
    "addr:postcode":"8531",
    "addr:street":"Brugsesteenweg",
    "iso:country":"BE",
    "sg:address":"Brugsesteenweg 2a",
    "sg:city":"Hulste",
    "sg:classifiers":[
        {
            "category":"Manufacturing",
            "subcategory":"Motor Vehicles & Parts",
            "type":"Manufacturing & Wholesale Goods"
        }
    ],
    "sg:phone":"+32 56 70 01 01",
    "sg:postcode":"8531",
    "sg:province":"West-Vlaanderen",
    "sg:tags":[
        "engine",
        "industrial",
        "tran",
        "-",
        "machine",
        "engineering",
        "mechanical",
        "motor-cars"
    ],
    "wof:name":"Freindix",
    "wof:placetype":"venue"
},
  "geometry": {"coordinates":[3.2725629807,50.8811035156],"type":"Point"}
}