{
  "type": "Feature",
  "properties": {
    "addr:full":"Rue Sainte-anne 34 Namur (naninne) Namur 5100",
    "addr:housenumber":"34",
    "addr:postcode":"5100",
    "addr:street":"Rue Sainte-Anne",
    "iso:country":"BE",
    "sg:address":"Rue Sainte-anne 34",
    "sg:city":"Namur (naninne)",
    "sg:classifiers":[
        {
            "category":"Manufacturing",
            "subcategory":"Metals",
            "type":"Manufacturing & Wholesale Goods"
        }
    ],
    "sg:postcode":"5100",
    "sg:province":"Namur",
    "sg:tags":[
        "work",
        "sheet"
    ],
    "wof:name":"De Bolle Guillaume Sprl",
    "wof:placetype":"venue"
},
  "geometry": {"coordinates":[4.9099760056,50.419834137],"type":"Point"}
}