{
  "type": "Feature",
  "properties": {
    "iso:country":"BE",
    "sg:address":"Kerkem 18",
    "sg:city":"Aalter",
    "sg:orig_category":"Elektrische installaties voor woningen",
    "sg:phone":"+32 9 375 04 35",
    "sg:postcode":"9880",
    "sg:province":"Oost-Vlaanderen",
    "wof:name":"Hans De Roo",
    "wof:placetype":"venue"
},
  "geometry": {"coordinates":[3.4474771023,51.0804252625],"type":"Point"}
}