{
  "type": "Feature",
  "properties": {
    "addr:full":"Sint-pietersstraat 32 Maasmechelen (leut) Limburg 3630",
    "addr:housenumber":"32",
    "addr:postcode":"3630",
    "addr:street":"Sint-Pietersstraat",
    "iso:country":"BE",
    "sg:address":"Sint-pietersstraat 32",
    "sg:city":"Maasmechelen (leut)",
    "sg:orig_category":"Non-Classified Establishments",
    "sg:phone":"+32 89 75 50 63",
    "sg:postcode":"3630",
    "sg:province":"Limburg",
    "wof:name":"Breuls Vleeshandel",
    "wof:placetype":"venue"
},
  "geometry": {"coordinates":[5.7353591919,50.9903526306],"type":"Point"}
}