{
  "type": "Feature",
  "properties": {
    "addr:full":"Goorbosstraat 74 Wuustwezel Antwerpen 2990",
    "addr:housenumber":"74",
    "addr:postcode":"2990",
    "addr:street":"Goorbosstraat",
    "iso:country":"BE",
    "sg:address":"Goorbosstraat 74",
    "sg:city":"Wuustwezel",
    "sg:orig_category":"Eleveurs and marchands de porcs",
    "sg:phone":"+32 3 663 10 43",
    "sg:postcode":"2990",
    "sg:province":"Antwerpen",
    "wof:name":"Ludovicus Pleysier",
    "wof:placetype":"venue"
},
  "geometry": {"coordinates":[4.5240459442,51.360786438],"type":"Point"}
}