{
  "type": "Feature",
  "properties": {
    "addr:full":"Rue De Tamines 11 Sambreville (velaine-sur-sambre) Namur 5060",
    "addr:housenumber":"11",
    "addr:postcode":"5060",
    "addr:street":"Rue De Tamines",
    "iso:country":"BE",
    "sg:address":"Rue De Tamines 11",
    "sg:city":"Sambreville (velaine-sur-sambre)",
    "sg:classifiers":[
        {
            "category":"Home & Garden",
            "subcategory":"Building Materials",
            "type":"Retail Goods"
        }
    ],
    "sg:phone":"+32 71 77 14 66",
    "sg:postcode":"5060",
    "sg:province":"Namur",
    "sg:tags":[
        "window"
    ],
    "wof:name":"Loutte Ets",
    "wof:placetype":"venue"
},
  "geometry": {"coordinates":[4.6285200119,50.4448738098],"type":"Point"}
}