{
  "type": "Feature",
  "properties": {
    "addr:full":"Mouterijstraat 71 Beringen Limburg 3582",
    "addr:housenumber":"71",
    "addr:postcode":"3582",
    "addr:street":"Mouterijstraat",
    "iso:country":"BE",
    "sg:address":"Mouterijstraat 71",
    "sg:city":"Beringen",
    "sg:orig_category":"Gespecialiseerde residenti\u00eble bouw",
    "sg:phone":"+32 11 42 83 30",
    "sg:postcode":"3582",
    "sg:province":"Limburg",
    "wof:name":"Joseph Schraeyen",
    "wof:placetype":"venue"
},
  "geometry": {"coordinates":[5.2708749771,51.0595359802],"type":"Point"}
}