{
  "type": "Feature",
  "properties": {
    "iso:country":"BE",
    "sg:address":"Rue Du Centenaire 62",
    "sg:city":"Sombreffe",
    "sg:orig_category":"HUISBRANDOLIE",
    "sg:phone":"+32 71 88 80 91",
    "sg:postcode":"5140",
    "sg:province":"Namur",
    "wof:name":"Barette & Fils",
    "wof:placetype":"venue"
},
  "geometry": {"coordinates":[4.5724802017,50.5121688843],"type":"Point"}
}