{
  "type": "Feature",
  "properties": {
    "addr:full":"Dumontlaan 114 Genk Limburg 3600",
    "addr:housenumber":"114",
    "addr:postcode":"3600",
    "addr:street":"Dumontlaan",
    "iso:country":"BE",
    "sg:address":"Dumontlaan 114",
    "sg:city":"Genk",
    "sg:orig_category":"Quincailleries",
    "sg:phone":"+32 89 38 30 41",
    "sg:postcode":"3600",
    "sg:province":"Limburg",
    "wof:name":"Brico",
    "wof:placetype":"venue"
},
  "geometry": {"coordinates":[5.5344090462,50.9926719666],"type":"Point"}
}