{
  "type": "Feature",
  "properties": {
    "iso:country":"BE",
    "sg:address":"Veldstraat 7",
    "sg:city":"Torhout",
    "sg:orig_category":"Eleveurs and marchands de porcs",
    "sg:phone":"+32 50 21 49 65",
    "sg:postcode":"8820",
    "sg:province":"West-Vlaanderen",
    "wof:name":"Roger Dejonghe",
    "wof:placetype":"venue"
},
  "geometry": {"coordinates":[3.0684790611,51.0706100464],"type":"Point"}
}