{
  "type": "Feature",
  "properties": {
    "addr:full":"Antwerpsesteenweg 273 Kapellen Antwerpen 2950",
    "addr:housenumber":"273",
    "addr:postcode":"2950",
    "addr:street":"Antwerpsesteenweg",
    "iso:country":"BE",
    "sg:address":"Antwerpsesteenweg 273",
    "sg:city":"Kapellen",
    "sg:orig_category":"Art and fournitures artistiques",
    "sg:phone":"+32 3 605 02 71",
    "sg:postcode":"2950",
    "sg:province":"Antwerpen",
    "wof:name":"Simone Van Hool",
    "wof:placetype":"venue"
},
  "geometry": {"coordinates":[4.4377012253,51.3014221191],"type":"Point"}
}