{
  "type": "Feature",
  "properties": {
    "iso:country":"BE",
    "sg:address":"Avenue Prince De Li\u00c8ge 54",
    "sg:city":"Namur",
    "sg:orig_category":"Services de Nettoyage and de D\u00e9sinfection. Restauration pour collectivit\u00e9s",
    "sg:phone":"+32 81 32 77 77",
    "sg:postcode":"5100",
    "sg:province":"Namur",
    "wof:name":"General Office Maintenance",
    "wof:placetype":"venue"
},
  "geometry": {"coordinates":[4.8713750839,50.4566345215],"type":"Point"}
}