{
  "type": "Feature",
  "properties": {
    "iso:country":"BE",
    "sg:address":"Tramstraat 61",
    "sg:city":"Gent (zwijnaarde)",
    "sg:classifiers":[
        {
            "category":"Organizations",
            "subcategory":"Professional Association",
            "type":"Services"
        }
    ],
    "sg:phone":"+32 9 244 98 11",
    "sg:postcode":"9052",
    "sg:province":"Oost-Vlaanderen",
    "sg:tags":[
        "trade-union",
        "federation"
    ],
    "wof:name":"Agoria Oost-& West-vlaanderen",
    "wof:placetype":"venue"
},
  "geometry": {"coordinates":[3.7167270184,51.0002937317],"type":"Point"}
}