{
  "type": "Feature",
  "properties": {
    "addr:full":"Oude Borgwormseweg 1 Sint-truiden Limburg 3800",
    "addr:housenumber":"1",
    "addr:postcode":"3800",
    "addr:street":"Oude Borgwormseweg",
    "iso:country":"BE",
    "sg:address":"Oude Borgwormseweg 1",
    "sg:city":"Sint-truiden",
    "sg:orig_category":"Producteurs de fruits",
    "sg:phone":"+32 11 68 83 84",
    "sg:postcode":"3800",
    "sg:province":"Limburg",
    "wof:name":"Maximilien Smeers",
    "wof:placetype":"venue"
},
  "geometry": {"coordinates":[5.2090249062,50.7900238037],"type":"Point"}
}