{
  "type": "Feature",
  "properties": {
    "iso:country":"BE",
    "sg:address":"Rue Des Combattants 55",
    "sg:city":"Brunehaut",
    "sg:orig_category":"Services de Nettoyage and de D\u00e9sinfection. Plomberie, chauffage and installations sanitaires",
    "sg:phone":"+32 69 34 62 78",
    "sg:postcode":"7620",
    "sg:province":"Hainaut",
    "wof:name":"Guy Petit",
    "wof:placetype":"venue"
},
  "geometry": {"coordinates":[3.4211480618,50.5165557861],"type":"Point"}
}