{
  "type": "Feature",
  "properties": {
    "iso:country":"BE",
    "sg:address":"Prins Boudewijnlaan 70",
    "sg:city":"Sint-niklaas",
    "sg:classifiers":[
        {
            "category":"Home & Garden",
            "subcategory":"Home Furnishings",
            "type":"Retail Goods"
        }
    ],
    "sg:phone":"+32 3 777 93 65",
    "sg:postcode":"9100",
    "sg:province":"Oost-Vlaanderen",
    "sg:tags":[
        "interior",
        "decoration"
    ],
    "wof:name":"Steenssens Bvba",
    "wof:placetype":"venue"
},
  "geometry": {"coordinates":[4.1649479866,51.1613464355],"type":"Point"}
}