{
  "type": "Feature",
  "properties": {
    "addr:full":"Leopoldstr 97 Mechelen Antwerpen 2800",
    "addr:housenumber":"97",
    "addr:postcode":"2800",
    "addr:street":"Leopoldstr",
    "iso:country":"BE",
    "sg:address":"Leopoldstr 97",
    "sg:city":"Mechelen",
    "sg:classifiers":[
        {
            "category":"Transit Center",
            "subcategory":"Freight",
            "type":"Transportation"
        }
    ],
    "sg:phone":"+32 15 45 15 50",
    "sg:postcode":"2800",
    "sg:province":"Antwerpen",
    "sg:tags":[
        "metallurgy",
        "pipe",
        "metalworking",
        "sheet"
    ],
    "wof:name":"Bometal Nv",
    "wof:placetype":"venue"
},
  "geometry": {"coordinates":[4.4812450409,51.0185241699],"type":"Point"}
}