{
  "type": "Feature",
  "properties": {
    "iso:country":"BE",
    "sg:address":"Nijverheidsstr. 3 Zi Kloosterveld 1",
    "sg:city":"Brecht",
    "sg:classifiers":[
        {
            "category":"Professional",
            "subcategory":"Computer Services",
            "type":"Services"
        }
    ],
    "sg:phone":"+32 3 663 68 63",
    "sg:postcode":"2960",
    "sg:province":"Antwerpen",
    "sg:tags":[
        "information",
        "technology",
        "software"
    ],
    "wof:name":"Kluwer Software Nv",
    "wof:placetype":"venue"
},
  "geometry": {"coordinates":[4.5584278107,51.3009872437],"type":"Point"}
}