{
  "type": "Feature",
  "properties": {
    "addr:full":"Braamstraat 48 Mol Antwerpen 2400",
    "addr:housenumber":"48",
    "addr:postcode":"2400",
    "addr:street":"Braamstraat",
    "iso:country":"BE",
    "sg:address":"Braamstraat 48",
    "sg:city":"Mol",
    "sg:orig_category":"Mat\u00e9riel m\u00e9dical and orthop\u00e9dique and proth\u00e8ses Fab",
    "sg:phone":"+32 14 31 32 71",
    "sg:postcode":"2400",
    "sg:province":"Antwerpen",
    "wof:name":"Labo Jef Heyns",
    "wof:placetype":"venue"
},
  "geometry": {"coordinates":[5.144288063,51.1920051575],"type":"Point"}
}