{
  "type": "Feature",
  "properties": {
    "addr:full":"Rue Lairesse 31 Li\u00e8ge 1 (li\u00e8ge 2) Li\u00e8ge 4020",
    "addr:housenumber":"31;1;2",
    "addr:postcode":"4020",
    "addr:street":"Rue Lairesse",
    "iso:country":"BE",
    "sg:address":"Rue Lairesse 31",
    "sg:city":"Li\u00e8ge 1 (li\u00e8ge 2)",
    "sg:classifiers":[
        {
            "category":"Professional",
            "subcategory":"Accounting & Tax Preparation",
            "type":"Services"
        }
    ],
    "sg:phone":"+32 4 349 10 72",
    "sg:postcode":"4020",
    "sg:province":"Li\u00e8ge",
    "sg:tags":[
        "bookkeeper"
    ],
    "wof:name":"Angesco Sa",
    "wof:placetype":"venue"
},
  "geometry": {"coordinates":[5.5865092278,50.6357574463],"type":"Point"}
}