{
  "type": "Feature",
  "properties": {
    "addr:full":"Rue Haute-marexhe 174 Herstal Li\u00e8ge 4040",
    "addr:housenumber":"174",
    "addr:postcode":"4040",
    "addr:street":"Rue Haute-Marexhe",
    "iso:country":"BE",
    "sg:address":"Rue Haute-marexhe 174",
    "sg:city":"Herstal",
    "sg:classifiers":[
        {
            "category":"Health Services",
            "subcategory":"Health Practitioner",
            "type":"Services"
        }
    ],
    "sg:phone":"+32 4 264 98 72",
    "sg:postcode":"4040",
    "sg:province":"Li\u00e8ge",
    "sg:tags":[
        "physiotherapist"
    ],
    "wof:name":"Loos A",
    "wof:placetype":"venue"
},
  "geometry": {"coordinates":[5.6190810204,50.6557312012],"type":"Point"}
}