{
  "type": "Feature",
  "properties": {
    "addr:full":"Quai De Veeweyde 65 Bruxelles (anderlecht) Bruxelles-Capitale 1070",
    "addr:housenumber":"65",
    "addr:postcode":"1070",
    "addr:street":"Quai De Veeweyde",
    "iso:country":"BE",
    "sg:address":"Quai De Veeweyde 65",
    "sg:city":"Bruxelles (anderlecht)",
    "sg:classifiers":[
        {
            "category":"Arena",
            "subcategory":"Sports Club",
            "type":"Entertainment"
        }
    ],
    "sg:phone":"+32 2 523 80 48",
    "sg:postcode":"1070",
    "sg:province":"Bruxelles-Capitale",
    "wof:name":"Cercle Des Regates De Bruxelles",
    "wof:placetype":"venue"
},
  "geometry": {"coordinates":[4.3054318428,50.8316230774],"type":"Point"}
}