{
  "type": "Feature",
  "properties": {
    "iso:country":"BE",
    "sg:address":"Dorpsstraat 212b2",
    "sg:city":"Overpelt",
    "sg:orig_category":"Banken and kredietinstellingen",
    "sg:phone":"+32 11 64 77 86",
    "sg:postcode":"3900",
    "sg:province":"Limburg",
    "wof:name":"Groep Argenta",
    "wof:placetype":"venue"
},
  "geometry": {"coordinates":[5.4185352325,51.2093391418],"type":"Point"}
}