{
  "type": "Feature",
  "properties": {
    "iso:country":"BE",
    "sg:address":"Ozo 6",
    "sg:city":"Durbuy (izier)",
    "sg:classifiers":[
        {
            "category":"Health Services",
            "subcategory":"Medical Lab",
            "type":"Services"
        }
    ],
    "sg:phone":"+32 86 40 05 79",
    "sg:postcode":"6941",
    "sg:province":"Luxembourg",
    "sg:tags":[
        "laboratory",
        "dental"
    ],
    "wof:name":"Batta R",
    "wof:placetype":"venue"
},
  "geometry": {"coordinates":[5.524184227,50.3770332336],"type":"Point"}
}