{
  "type": "Feature",
  "properties": {
    "addr:full":"Sol Paradis 3 Ferrieres Li\u00e8ge 4190",
    "addr:housenumber":"3",
    "addr:postcode":"4190",
    "addr:street":"Paradis",
    "iso:country":"BE",
    "sg:address":"Sol Paradis 3",
    "sg:city":"Ferrieres",
    "sg:orig_category":"Offices du tourisme",
    "sg:phone":"+32 86 40 03 79",
    "sg:postcode":"4190",
    "sg:province":"Li\u00e8ge",
    "wof:name":"Syndicat D'initiative",
    "wof:placetype":"venue"
},
  "geometry": {"coordinates":[5.5766820908,50.4052352905],"type":"Point"}
}