{
  "type": "Feature",
  "properties": {
    "iso:country":"BE",
    "sg:address":"Vervlotenweg 66bd",
    "sg:city":"Oudenburg",
    "sg:orig_category":"Boucheries",
    "sg:phone":"+32 59 26 64 01",
    "sg:postcode":"8460",
    "sg:province":"West-Vlaanderen",
    "wof:name":"Giovanni Denolf",
    "wof:placetype":"venue"
},
  "geometry": {"coordinates":[3.0023450851,51.1840553284],"type":"Point"}
}