{
  "type": "Feature",
  "properties": {
    "addr:full":"La Bruy\u00e8re 72 Andenne (bonneville) Namur 5300",
    "addr:housenumber":"72",
    "addr:postcode":"5300",
    "addr:street":"La Bruye\u0300Re",
    "iso:country":"BE",
    "sg:address":"La Bruy\u00e8re 72",
    "sg:city":"Andenne (bonneville)",
    "sg:classifiers":[
        {
            "category":"Education",
            "subcategory":"Special Training",
            "type":"Public Place"
        }
    ],
    "sg:phone":"+32 81 58 20 62",
    "sg:postcode":"5300",
    "sg:province":"Namur",
    "sg:tags":[
        "-",
        "processing",
        "data"
    ],
    "wof:name":"Hoolans D",
    "wof:placetype":"venue"
},
  "geometry": {"coordinates":[5.0296931267,50.4696006775],"type":"Point"}
}