{
  "type": "Feature",
  "properties": {
    "iso:country":"BE",
    "sg:address":"Hombeeksesteenweg 182",
    "sg:city":"Mechelen",
    "sg:classifiers":[
        {
            "category":"Personal",
            "subcategory":"Shoe Repair & Shine",
            "type":"Services"
        }
    ],
    "sg:phone":"+32 15 41 74 86",
    "sg:postcode":"2800",
    "sg:province":"Antwerpen",
    "sg:tags":[
        "shoemaker"
    ],
    "wof:name":"Gulden Leest (de)",
    "wof:placetype":"venue"
},
  "geometry": {"coordinates":[4.4677000046,51.0179519653],"type":"Point"}
}