{
  "type": "Feature",
  "properties": {
    "iso:country":"BE",
    "sg:address":"Berkendallaan 188",
    "sg:city":"Vilvoorde",
    "sg:classifiers":[
        {
            "category":"Cafe",
            "type":"Food & Drink"
        }
    ],
    "sg:phone":"+32 2 267 89 96",
    "sg:postcode":"1800",
    "sg:province":"Vlaams-Brabant",
    "sg:tags":[
        "caf\u00e9s"
    ],
    "wof:name":"Khadija Bouchrit",
    "wof:placetype":"venue"
},
  "geometry": {"coordinates":[4.3644919395,50.9018478394],"type":"Point"}
}