{
  "type": "Feature",
  "properties": {
    "addr:full":"Peerstraat 3 Gent Oost-Vlaanderen 9000",
    "addr:housenumber":"3",
    "addr:postcode":"9000",
    "addr:street":"Peerstraat;Oost-Vlaanderen",
    "iso:country":"BE",
    "sg:address":"Peerstraat 3",
    "sg:city":"Gent",
    "sg:classifiers":[
        {
            "category":"Government",
            "subcategory":"Police Station",
            "type":"Public Place"
        }
    ],
    "sg:phone":"+32 9 266 66 55",
    "sg:postcode":"9000",
    "sg:province":"Oost-Vlaanderen",
    "sg:tags":[
        "gendarmerie"
    ],
    "wof:name":"Federale Politie",
    "wof:placetype":"venue"
},
  "geometry": {"coordinates":[3.6922130585,51.0591773987],"type":"Point"}
}