{
  "type": "Feature",
  "properties": {
    "iso:country":"BE",
    "sg:address":"Rue De Maizeret 144",
    "sg:city":"Namur (loyers)",
    "sg:classifiers":[
        {
            "category":"Health Services",
            "subcategory":"Health Practitioner",
            "type":"Services"
        }
    ],
    "sg:phone":"+32 81 58 85 27",
    "sg:postcode":"5101",
    "sg:province":"Namur",
    "sg:tags":[
        "physiotherapist"
    ],
    "wof:name":"Fiasse Maurice",
    "wof:placetype":"venue"
},
  "geometry": {"coordinates":[4.904815197,50.4481887817],"type":"Point"}
}