{
  "type": "Feature",
  "properties": {
    "addr:full":"Kastanjelaan 33 Kasterlee (lichtaart) Antwerpen 2460",
    "addr:housenumber":"33",
    "addr:postcode":"2460",
    "addr:street":"Kastanjelaan",
    "iso:country":"BE",
    "sg:address":"Kastanjelaan 33",
    "sg:city":"Kasterlee (lichtaart)",
    "sg:classifiers":[
        {
            "category":"Transit Center",
            "subcategory":"Freight",
            "type":"Transportation"
        }
    ],
    "sg:phone":"+32 14 55 54 56",
    "sg:postcode":"2460",
    "sg:province":"Antwerpen",
    "sg:tags":[
        "import",
        "export",
        "-"
    ],
    "wof:name":"V D Management Bvba",
    "wof:placetype":"venue"
},
  "geometry": {"coordinates":[5.0313248634,51.2633361816],"type":"Point"}
}