{
  "type": "Feature",
  "properties": {
    "iso:country":"BE",
    "sg:address":"Rue G\u00c9n\u00c9ral Capiaumont 33",
    "sg:city":"Etterbeek/etterbeek",
    "sg:orig_category":"Experts-comptables",
    "sg:phone":"+32 2 647 89 06",
    "sg:postcode":"1040",
    "sg:province":"Bruxelles-Capitale",
    "wof:name":"Jean-paul Dubois",
    "wof:placetype":"venue"
},
  "geometry": {"coordinates":[4.3831701279,50.8319396973],"type":"Point"}
}