{
  "type": "Feature",
  "properties": {
    "iso:country":"BE",
    "sg:address":"Veldeken 107",
    "sg:city":"Zele",
    "sg:orig_category":"Architectes",
    "sg:phone":"+32 52 45 22 80",
    "sg:postcode":"9240",
    "sg:province":"Oost-Vlaanderen",
    "wof:name":"Christiaan D\u00b4herde",
    "wof:placetype":"venue"
},
  "geometry": {"coordinates":[4.0453181267,51.0549812317],"type":"Point"}
}