{
  "type": "Feature",
  "properties": {
    "addr:full":"Dorpstr 49 Laarne Oost-Vlaanderen 9270",
    "addr:housenumber":"49",
    "addr:postcode":"9270",
    "addr:street":"Dorpstr",
    "iso:country":"BE",
    "sg:address":"Dorpstr 49",
    "sg:city":"Laarne",
    "sg:classifiers":[
        {
            "category":"Banks & Credit Unions",
            "subcategory":"Bank",
            "type":"Services"
        }
    ],
    "sg:phone":"+32 55 69 21 99",
    "sg:postcode":"9270",
    "sg:province":"Oost-Vlaanderen",
    "wof:name":"Gemeentekrediet",
    "wof:placetype":"venue"
},
  "geometry": {"coordinates":[3.8477900028,51.0291900635],"type":"Point"}
}