{
  "type": "Feature",
  "properties": {
    "iso:country":"BE",
    "sg:address":"Hodonk 25",
    "sg:city":"Retie",
    "sg:classifiers":[
        {
            "category":"Building & Trades",
            "subcategory":"Electrical",
            "type":"Services"
        }
    ],
    "sg:phone":"+32 14 37 84 62",
    "sg:postcode":"2470",
    "sg:province":"Antwerpen",
    "sg:tags":[
        "electric",
        "-",
        "housewiring",
        "contractor"
    ],
    "wof:name":"Van Bael H",
    "wof:placetype":"venue"
},
  "geometry": {"coordinates":[5.119617939,51.2725448608],"type":"Point"}
}