{
  "type": "Feature",
  "properties": {
    "addr:full":"Dompel 19 Herentals Antwerpen 2200",
    "addr:housenumber":"19",
    "addr:postcode":"2200",
    "addr:street":"Dompel",
    "iso:country":"BE",
    "sg:address":"Dompel 19",
    "sg:city":"Herentals",
    "sg:orig_category":"Plaatsen van vloer- and muurbekleding Schilders Verhuur bouwmachines",
    "sg:phone":"+32 14 22 35 44",
    "sg:postcode":"2200",
    "sg:province":"Antwerpen",
    "wof:name":"A.i.s.",
    "wof:placetype":"venue"
},
  "geometry": {"coordinates":[4.7980318069,51.1664352417],"type":"Point"}
}