{
  "type": "Feature",
  "properties": {
    "iso:country":"BE",
    "sg:address":"Leestraat 10",
    "sg:city":"Sint-niklaas",
    "sg:orig_category":"Plomberie, chauffage and installations sanitaires",
    "sg:phone":"+32 3 772 27 05",
    "sg:postcode":"9112",
    "sg:province":"Oost-Vlaanderen",
    "wof:name":"Walter Keppens",
    "wof:placetype":"venue"
},
  "geometry": {"coordinates":[4.0198078156,51.1396484375],"type":"Point"}
}