{
  "type": "Feature",
  "properties": {
    "iso:country":"BE",
    "sg:address":"Place Ferrer 5",
    "sg:city":"Charleroi",
    "sg:orig_category":"M\u00e9decins and sp\u00e9cialistes",
    "sg:phone":"+32 71 71 45 40",
    "sg:postcode":"6060",
    "sg:province":"Hainaut",
    "wof:name":"Andr\u00c9 Pirlot",
    "wof:placetype":"venue"
},
  "geometry": {"coordinates":[4.4448361397,50.4067077637],"type":"Point"}
}