{
  "type": "Feature",
  "properties": {
    "addr:full":"Grote Markt 15 Kortrijk West-Vlaanderen 8500",
    "addr:housenumber":"15",
    "addr:postcode":"8500",
    "addr:street":"Grote Markt",
    "iso:country":"BE",
    "sg:address":"Grote Markt 15",
    "sg:city":"Kortrijk",
    "sg:classifiers":[
        {
            "category":"Fast Food",
            "type":"Food & Drink"
        }
    ],
    "sg:phone":"+32 56 25 98 54",
    "sg:postcode":"8500",
    "sg:province":"West-Vlaanderen",
    "sg:tags":[
        "fried",
        "stand",
        "potato"
    ],
    "wof:name":"L.l.",
    "wof:placetype":"venue"
},
  "geometry": {"coordinates":[3.2664530277,50.82787323],"type":"Point"}
}