{
  "type": "Feature",
  "properties": {
    "iso:country":"BE",
    "sg:address":"Tieltstraat 17",
    "sg:city":"Ruiselede",
    "sg:orig_category":"Dierenartsen",
    "sg:phone":"+32 51 68 84 11",
    "sg:postcode":"8755",
    "sg:province":"West-Vlaanderen",
    "wof:name":"Marc Dedeurwaerdere",
    "wof:placetype":"venue"
},
  "geometry": {"coordinates":[3.3970561028,51.0377502441],"type":"Point"}
}