{
  "type": "Feature",
  "properties": {
    "iso:country":"BE",
    "sg:address":"Doorniksesteenweg 3b",
    "sg:city":"Avelgem",
    "sg:orig_category":"Non-Classified Establishments",
    "sg:phone":"+32 56 75 70 91",
    "sg:postcode":"8580",
    "sg:province":"West-Vlaanderen",
    "wof:name":"Chocoladeboetiek (de)",
    "wof:placetype":"venue"
},
  "geometry": {"coordinates":[3.445027113,50.7759056091],"type":"Point"}
}