{
  "type": "Feature",
  "properties": {
    "addr:full":"Chamb\u00c9rystraat 45 Etterbeek/etterbeek Bruxelles-Capitale 1040",
    "addr:housenumber":"45",
    "addr:postcode":"1040",
    "addr:street":"Chambe\u0301Rystraat",
    "iso:country":"BE",
    "sg:address":"Chamb\u00c9rystraat 45",
    "sg:city":"Etterbeek/etterbeek",
    "sg:orig_category":"Woningbouw",
    "sg:phone":"+32 2 387 19 00",
    "sg:postcode":"1040",
    "sg:province":"Bruxelles-Capitale",
    "wof:name":"Cogopa",
    "wof:placetype":"venue"
},
  "geometry": {"coordinates":[4.3881998062,50.8298721313],"type":"Point"}
}