{
  "type": "Feature",
  "properties": {
    "iso:country":"BE",
    "sg:address":"Lange Beeldekensstraat 97",
    "sg:city":"Antwerpen",
    "sg:orig_category":"Studios photographiques",
    "sg:phone":"+32 3 235 11 50",
    "sg:postcode":"2060",
    "sg:province":"Antwerpen",
    "wof:name":"Duerinck Foto",
    "wof:placetype":"venue"
},
  "geometry": {"coordinates":[4.4261450768,51.2217063904],"type":"Point"}
}