{
  "type": "Feature",
  "properties": {
    "addr:full":"Tongerlodorp 33 Westerlo Antwerpen 2260",
    "addr:housenumber":"33",
    "addr:postcode":"2260",
    "addr:street":"Tongerlodorp",
    "iso:country":"BE",
    "sg:address":"Tongerlodorp 33",
    "sg:city":"Westerlo",
    "sg:classifiers":[
        {
            "category":"Restaurant",
            "type":"Food & Drink"
        }
    ],
    "sg:phone":"+32 14 54 44 47",
    "sg:postcode":"2260",
    "sg:province":"Antwerpen",
    "wof:name":"De Variant",
    "wof:placetype":"venue"
},
  "geometry": {"coordinates":[4.9145941734,51.1077041626],"type":"Point"}
}