{
  "type": "Feature",
  "properties": {
    "iso:country":"BE",
    "sg:address":"Boulevard Audent 38",
    "sg:city":"Charleroi",
    "sg:classifiers":[
        {
            "category":"Health Services",
            "subcategory":"Doctor",
            "type":"Services"
        }
    ],
    "sg:phone":"+32 71 32 60 44",
    "sg:postcode":"6000",
    "sg:province":"Hainaut",
    "sg:tags":[
        "medicinephysicians",
        "surgeon"
    ],
    "wof:name":"Dethier Jacques",
    "wof:placetype":"venue"
},
  "geometry": {"coordinates":[4.4462127686,50.4091033936],"type":"Point"}
}