{
  "type": "Feature",
  "properties": {
    "addr:full":"Processieweg 19 Torhout (wijnendale) West-Vlaanderen 8820",
    "addr:housenumber":"19",
    "addr:postcode":"8820",
    "addr:street":"Processieweg",
    "iso:country":"BE",
    "sg:address":"Processieweg 19",
    "sg:city":"Torhout (wijnendale)",
    "sg:classifiers":[
        {
            "category":"Real Estate",
            "subcategory":"Architect",
            "type":"Services"
        }
    ],
    "sg:phone":"+32 50 21 10 43",
    "sg:postcode":"8820",
    "sg:province":"West-Vlaanderen",
    "wof:name":"Naert R",
    "wof:placetype":"venue"
},
  "geometry": {"coordinates":[3.06752491,51.1008796692],"type":"Point"}
}