{
  "type": "Feature",
  "properties": {
    "addr:full":"Rue De Limal 41 Rixensart Brabant Wallon 1330",
    "addr:housenumber":"41",
    "addr:postcode":"1330",
    "addr:street":"Rue De Limal;Wallon",
    "iso:country":"BE",
    "sg:address":"Rue De Limal 41",
    "sg:city":"Rixensart",
    "sg:classifiers":[
        {
            "category":"Real Estate",
            "subcategory":"Surveying",
            "type":"Services"
        }
    ],
    "sg:phone":"+32 2 653 38 52",
    "sg:postcode":"1330",
    "sg:province":"Brabant Wallon",
    "sg:tags":[
        "surveyor",
        "land"
    ],
    "wof:name":"Van Der Vennet A-j",
    "wof:placetype":"venue"
},
  "geometry": {"coordinates":[4.5358948708,50.706287384],"type":"Point"}
}