{
  "type": "Feature",
  "properties": {
    "addr:full":"5330 Assesse (groot) Namur 5330",
    "addr:postcode":"5330;5330",
    "addr:street":"Groot Namur",
    "iso:country":"BE",
    "sg:address":"5330",
    "sg:city":"Assesse (groot)",
    "sg:orig_category":"Pharmaciens",
    "sg:phone":"+32 900 10 500",
    "sg:postcode":"5330",
    "sg:province":"Namur",
    "wof:name":"Pharmacies De Garde",
    "wof:placetype":"venue"
},
  "geometry": {"coordinates":[4.9397602081,50.3817405701],"type":"Point"}
}