{
  "type": "Feature",
  "properties": {
    "iso:country":"BE",
    "sg:address":"Rue Simonon 8",
    "sg:city":"Li\u00e8ge",
    "sg:classifiers":[
        {
            "category":"Manufacturing",
            "subcategory":"Food",
            "type":"Manufacturing & Wholesale Goods"
        }
    ],
    "sg:phone":"+32 4 252 70 41",
    "sg:postcode":"4000",
    "sg:province":"Li\u00e8ge",
    "sg:tags":[
        "industry",
        "additive"
    ],
    "wof:name":"Synaco Chemicals S.a.",
    "wof:placetype":"venue"
},
  "geometry": {"coordinates":[5.5648751259,50.6288986206],"type":"Point"}
}