{
  "type": "Feature",
  "properties": {
    "addr:full":"Rue Des Ecoles 39 Tournai (kain) Hainaut 7540",
    "addr:housenumber":"39",
    "addr:postcode":"7540",
    "addr:street":"Rue Des Ecoles",
    "iso:country":"BE",
    "sg:address":"Rue Des Ecoles 39",
    "sg:city":"Tournai (kain)",
    "sg:classifiers":[
        {
            "category":"Health Services",
            "subcategory":"Health Practitioner",
            "type":"Services"
        }
    ],
    "sg:phone":"+32 69 21 23 15",
    "sg:postcode":"7540",
    "sg:province":"Hainaut",
    "sg:tags":[
        "physiotherapist"
    ],
    "wof:name":"Ramu A",
    "wof:placetype":"venue"
},
  "geometry": {"coordinates":[3.3940711021,50.6264724731],"type":"Point"}
}