{
  "type": "Feature",
  "properties": {
    "addr:full":"Hoogstraat 11 Beerse Antwerpen 2340",
    "addr:housenumber":"11",
    "addr:postcode":"2340",
    "addr:street":"Hoogstraat",
    "iso:country":"BE",
    "sg:address":"Hoogstraat 11",
    "sg:city":"Beerse",
    "sg:classifiers":[
        {
            "category":"Fast Food",
            "type":"Food & Drink"
        }
    ],
    "sg:phone":"+32 3 312 44 40",
    "sg:postcode":"2340",
    "sg:province":"Antwerpen",
    "sg:tags":[
        "meeneem",
        "restaurant"
    ],
    "wof:name":"Frituur",
    "wof:placetype":"venue"
},
  "geometry": {"coordinates":[4.7799401283,51.2951545715],"type":"Point"}
}