{
  "type": "Feature",
  "properties": {
    "iso:country":"BE",
    "sg:address":"Rue Malibran 91",
    "sg:city":"Bruxelles (ixelles)",
    "sg:classifiers":[
        {
            "category":"Food & Beverages",
            "subcategory":"Groceries & Convenience Stores",
            "type":"Retail Goods"
        }
    ],
    "sg:phone":"+32 2 647 00 84",
    "sg:postcode":"1050",
    "sg:province":"Bruxelles-Capitale",
    "sg:tags":[
        "grocer"
    ],
    "wof:name":"Jardin Du Monde Exotique (au)",
    "wof:placetype":"venue"
},
  "geometry": {"coordinates":[4.3742289543,50.8316917419],"type":"Point"}
}