{
  "type": "Feature",
  "properties": {
    "addr:full":"Stationstraat 49 Moorslede West-Vlaanderen 8890",
    "addr:housenumber":"49",
    "addr:postcode":"8890",
    "addr:street":"Stationstraat",
    "iso:country":"BE",
    "sg:address":"Stationstraat 49",
    "sg:city":"Moorslede",
    "sg:orig_category":"Enseignement maternel and primaire",
    "sg:phone":"+32 51 77 22 68",
    "sg:postcode":"8890",
    "sg:province":"West-Vlaanderen",
    "wof:name":"Vrije Basisschool",
    "wof:placetype":"venue"
},
  "geometry": {"coordinates":[3.0553619862,50.8918685913],"type":"Point"}
}