{
  "type": "Feature",
  "properties": {
    "iso:country":"BE",
    "sg:address":"Rue Des Fusill\u00e9s 63",
    "sg:city":"Court-saint-etienne",
    "sg:classifiers":[
        {
            "category":"Autos & Motor Vehicles",
            "subcategory":"Automobile Sales",
            "type":"Retail Goods"
        }
    ],
    "sg:phone":"+32 10 61 58 04",
    "sg:postcode":"1490",
    "sg:province":"Brabant Wallon",
    "sg:tags":[
        "car",
        "used",
        "-"
    ],
    "wof:name":"Paquet C",
    "wof:placetype":"venue"
},
  "geometry": {"coordinates":[4.5494608879,50.6497344971],"type":"Point"}
}