{
  "type": "Feature",
  "properties": {
    "addr:full":"Brouwersstraat 16 Hamont-achel (hamont) Limburg 3930",
    "addr:housenumber":"16",
    "addr:postcode":"3930",
    "addr:street":"Brouwersstraat",
    "iso:country":"BE",
    "sg:address":"Brouwersstraat 16",
    "sg:city":"Hamont-achel (hamont)",
    "sg:classifiers":[
        {
            "category":"Professional",
            "subcategory":"Lawyer & Legal Services",
            "type":"Services"
        }
    ],
    "sg:phone":"+32 11 62 19 39",
    "sg:postcode":"3930",
    "sg:province":"Limburg",
    "sg:tags":[
        "notary"
    ],
    "wof:name":"Cuppens W",
    "wof:placetype":"venue"
},
  "geometry": {"coordinates":[5.5450549126,51.2511863708],"type":"Point"}
}