{
  "type": "Feature",
  "properties": {
    "addr:full":"Vennen 25 Herentals Antwerpen 2200",
    "addr:housenumber":"25",
    "addr:postcode":"2200",
    "addr:street":"Vennen",
    "iso:country":"BE",
    "sg:address":"Vennen 25",
    "sg:city":"Herentals",
    "sg:orig_category":"Installation de menuiserie m\u00e9tallique",
    "sg:phone":"+32 14 21 88 32",
    "sg:postcode":"2200",
    "sg:province":"Antwerpen",
    "wof:name":"Bc Ingenieursbureau",
    "wof:placetype":"venue"
},
  "geometry": {"coordinates":[4.8442268372,51.1680450439],"type":"Point"}
}