{
  "type": "Feature",
  "properties": {
    "iso:country":"BE",
    "sg:address":"Antwerpsestraat 97",
    "sg:city":"Boom",
    "sg:orig_category":"Bars Packard Bell Nec",
    "sg:phone":"+32 3 880 69 69",
    "sg:postcode":"2850",
    "sg:province":"Antwerpen",
    "wof:name":"Riverside Multimedia",
    "wof:placetype":"venue"
},
  "geometry": {"coordinates":[4.365377903,51.0893287659],"type":"Point"}
}