{
  "type": "Feature",
  "properties": {
    "addr:full":"G. Gezellelaan 12 Heusden-zolder Limburg 3550",
    "addr:housenumber":"12",
    "addr:postcode":"3550",
    "addr:street":"G. Gezellelaan",
    "iso:country":"BE",
    "sg:address":"G. Gezellelaan 12",
    "sg:city":"Heusden-zolder",
    "sg:orig_category":"Advocaten and juridische adviseurs",
    "sg:phone":"+32 11 42 40 53",
    "sg:postcode":"3550",
    "sg:province":"Limburg",
    "wof:name":"I. Valgaeren",
    "wof:placetype":"venue"
},
  "geometry": {"coordinates":[5.2796840668,51.0325317383],"type":"Point"}
}