{
  "type": "Feature",
  "properties": {
    "iso:country":"BE",
    "sg:address":"Meensestraat 13",
    "sg:city":"Ieper",
    "sg:orig_category":"V\u00eatements pour b\u00e9b\u00e9s and enfants",
    "sg:phone":"+32 57 20 78 17",
    "sg:postcode":"8900",
    "sg:province":"West-Vlaanderen",
    "wof:name":"Huis Octopus",
    "wof:placetype":"venue"
},
  "geometry": {"coordinates":[2.8886640072,50.8516273499],"type":"Point"}
}