{
  "type": "Feature",
  "properties": {
    "iso:country":"BE",
    "sg:address":"Rue De La Monnaie 4",
    "sg:city":"Namur",
    "sg:classifiers":[
        {
            "category":"Bars & Pubs",
            "type":"Food & Drink"
        }
    ],
    "sg:phone":"+32 81 23 19 82",
    "sg:postcode":"5000",
    "sg:province":"Namur",
    "sg:tags":[
        "tavern"
    ],
    "wof:name":"Loburg",
    "wof:placetype":"venue"
},
  "geometry": {"coordinates":[4.866751194,50.4634056091],"type":"Point"}
}