{
  "type": "Feature",
  "properties": {
    "addr:full":"Rue Saint-adalbert 9ba Li\u00c8ge Li\u00e8ge 4000",
    "addr:housenumber":"9ba",
    "addr:postcode":"4000",
    "addr:street":"Rue Saint-Adalbert",
    "iso:country":"BE",
    "sg:address":"Rue Saint-adalbert 9ba",
    "sg:city":"Li\u00c8ge",
    "sg:orig_category":"Maroquinerie and articles de voyage",
    "sg:phone":"+32 4 223 29 70",
    "sg:postcode":"4000",
    "sg:province":"Li\u00e8ge",
    "wof:name":"Maison Donna In Piu",
    "wof:placetype":"venue"
},
  "geometry": {"coordinates":[5.5695748329,50.6421699524],"type":"Point"}
}