{
  "type": "Feature",
  "properties": {
    "iso:country":"BE",
    "sg:address":"Meensesteenweg 214",
    "sg:city":"Izegem",
    "sg:classifiers":[
        {
            "category":"Wholesale",
            "subcategory":"Beer",
            "type":"Manufacturing & Wholesale Goods"
        }
    ],
    "sg:phone":"+32 51 30 39 20",
    "sg:postcode":"8870",
    "sg:province":"West-Vlaanderen",
    "sg:tags":[
        "ale",
        "-"
    ],
    "wof:name":"Saelens B",
    "wof:placetype":"venue"
},
  "geometry": {"coordinates":[3.1919341087,50.901473999],"type":"Point"}
}