{
  "type": "Feature",
  "properties": {
    "addr:full":"Maastrichterstraat 78 Tongeren Limburg 3700",
    "addr:housenumber":"78",
    "addr:postcode":"3700",
    "addr:street":"Maastrichterstraat",
    "iso:country":"BE",
    "sg:address":"Maastrichterstraat 78",
    "sg:city":"Tongeren",
    "sg:orig_category":"Alimentation sp\u00e9cialis\u00e9e",
    "sg:phone":"+32 12 23 14 74",
    "sg:postcode":"3700",
    "sg:province":"Limburg",
    "wof:name":"Nv Rullingen",
    "wof:placetype":"venue"
},
  "geometry": {"coordinates":[5.4669032097,50.7825012207],"type":"Point"}
}