{
  "type": "Feature",
  "properties": {
    "addr:full":"Avenue Eug\u00e8ne Plasky 204 Box 1 Bruxelles (schaerbeek) Bruxelles-Capitale 1030",
    "addr:housenumber":"204;1",
    "addr:postcode":"1030",
    "addr:street":"Avenue Euge\u0300Ne Plasky;Box",
    "iso:country":"BE",
    "sg:address":"Avenue Eug\u00e8ne Plasky 204 Box 1",
    "sg:city":"Bruxelles (schaerbeek)",
    "sg:classifiers":[
        {
            "category":"Health Services",
            "subcategory":"Dentist",
            "type":"Services"
        }
    ],
    "sg:phone":"+32 2 736 25 74",
    "sg:postcode":"1030",
    "sg:province":"Bruxelles-Capitale",
    "wof:name":"Moraux V\u00e9ronique",
    "wof:placetype":"venue"
},
  "geometry": {"coordinates":[4.3974051476,50.8536872864],"type":"Point"}
}