{
  "type": "Feature",
  "properties": {
    "addr:full":"Houthulststraat 100 Staden West-Vlaanderen 8840",
    "addr:housenumber":"100",
    "addr:postcode":"8840",
    "addr:street":"Houthulststraat",
    "iso:country":"BE",
    "sg:address":"Houthulststraat 100",
    "sg:city":"Staden",
    "sg:classifiers":[
        {
            "category":"Health Services",
            "subcategory":"Health Practitioner",
            "type":"Services"
        }
    ],
    "sg:phone":"+32 51 70 27 82",
    "sg:postcode":"8840",
    "sg:province":"West-Vlaanderen",
    "sg:tags":[
        "physiotherapist"
    ],
    "wof:name":"Pieters Rosanne",
    "wof:placetype":"venue"
},
  "geometry": {"coordinates":[2.9949429035,50.9718894958],"type":"Point"}
}