{
  "type": "Feature",
  "properties": {
    "iso:country":"BE",
    "sg:address":"Avenue De La Concorde 166",
    "sg:city":"Seraing",
    "sg:classifiers":[
        {
            "category":"Wholesale",
            "subcategory":"Auto Parts",
            "type":"Manufacturing & Wholesale Goods"
        }
    ],
    "sg:phone":"+32 4 336 68 07",
    "sg:postcode":"4100",
    "sg:province":"Li\u00e8ge",
    "sg:tags":[
        "body",
        "automobile",
        "supply",
        "equipment"
    ],
    "wof:name":"Arnone Sa",
    "wof:placetype":"venue"
},
  "geometry": {"coordinates":[5.5013980865,50.5963439941],"type":"Point"}
}