{
  "type": "Feature",
  "properties": {
    "iso:country":"BE",
    "sg:address":"Pretstraat 15",
    "sg:city":"Destelbergen (heusden)",
    "sg:classifiers":[
        {
            "category":"Health Services",
            "subcategory":"Health Practitioner",
            "type":"Services"
        }
    ],
    "sg:phone":"+32 9 230 60 49",
    "sg:postcode":"9070",
    "sg:province":"Oost-Vlaanderen",
    "sg:tags":[
        "physiotherapist"
    ],
    "wof:name":"Guily Christine",
    "wof:placetype":"venue"
},
  "geometry": {"coordinates":[3.8088309765,51.0357398987],"type":"Point"}
}