{
  "type": "Feature",
  "properties": {
    "addr:full":"Turnhoutsebaan 296 Mol Antwerpen 2400",
    "addr:housenumber":"296",
    "addr:postcode":"2400",
    "addr:street":"Turnhoutsebaan",
    "iso:country":"BE",
    "sg:address":"Turnhoutsebaan 296",
    "sg:city":"Mol",
    "sg:classifiers":[
        {
            "category":"Health Services",
            "subcategory":"Health Practitioner",
            "type":"Services"
        }
    ],
    "sg:phone":"+32 14 31 60 45",
    "sg:postcode":"2400",
    "sg:province":"Antwerpen",
    "sg:tags":[
        "physiotherapist"
    ],
    "wof:name":"Stijven Guy",
    "wof:placetype":"venue"
},
  "geometry": {"coordinates":[5.1153898239,51.1961212158],"type":"Point"}
}