{
  "type": "Feature",
  "properties": {
    "addr:full":"Maastrichterstraat 307 Bilzen Limburg 3740",
    "addr:housenumber":"307",
    "addr:postcode":"3740",
    "addr:street":"Maastrichterstraat",
    "iso:country":"BE",
    "sg:address":"Maastrichterstraat 307",
    "sg:city":"Bilzen",
    "sg:orig_category":"Installation \u00e9lectrique r\u00e9sidentielle",
    "sg:phone":"+32 89 49 11 61",
    "sg:postcode":"3740",
    "sg:province":"Limburg",
    "wof:name":"Danny Moors",
    "wof:placetype":"venue"
},
  "geometry": {"coordinates":[5.5271902084,50.8648300171],"type":"Point"}
}