{
  "type": "Feature",
  "properties": {
    "addr:full":"Rue Haute 19 Frasnes-lez-anvaing Hainaut 7911",
    "addr:housenumber":"19",
    "addr:postcode":"7911",
    "addr:street":"Rue Haute",
    "iso:country":"BE",
    "sg:address":"Rue Haute 19",
    "sg:city":"Frasnes-lez-anvaing",
    "sg:orig_category":"M\u00e9decins and sp\u00e9cialistes",
    "sg:phone":"+32 69 86 75 45",
    "sg:postcode":"7911",
    "sg:province":"Hainaut",
    "wof:name":"Philippe Mourin",
    "wof:placetype":"venue"
},
  "geometry": {"coordinates":[3.6200909615,50.6673851013],"type":"Point"}
}