{
  "type": "Feature",
  "properties": {
    "addr:full":"Wijngaardstraat 34 Izegem West-Vlaanderen 8870",
    "addr:housenumber":"34",
    "addr:postcode":"8870",
    "addr:street":"Wijngaardstraat",
    "iso:country":"BE",
    "sg:address":"Wijngaardstraat 34",
    "sg:city":"Izegem",
    "sg:classifiers":[
        {
            "category":"Retail",
            "subcategory":"Laundry & Dry Cleaning",
            "type":"Services"
        }
    ],
    "sg:phone":"+32 51 30 06 50",
    "sg:postcode":"8870",
    "sg:province":"West-Vlaanderen",
    "sg:tags":[
        "dyer",
        "cleaner"
    ],
    "wof:name":"Rap En Rein",
    "wof:placetype":"venue"
},
  "geometry": {"coordinates":[3.2130010128,50.9196968079],"type":"Point"}
}