{
  "type": "Feature",
  "properties": {
    "iso:country":"BE",
    "sg:address":"Liersesteenweg 29",
    "sg:city":"Heist-op-den-berg (booischot)",
    "sg:classifiers":[
        {
            "category":"Recreation",
            "subcategory":"Fishing",
            "type":"Entertainment"
        }
    ],
    "sg:phone":"+32 15 22 58 93",
    "sg:postcode":"2221",
    "sg:province":"Antwerpen",
    "sg:tags":[
        "tackle"
    ],
    "wof:name":"V D S Fly Fishing Tackle",
    "wof:placetype":"venue"
},
  "geometry": {"coordinates":[4.7739758492,51.0512428284],"type":"Point"}
}