{
  "type": "Feature",
  "properties": {
    "addr:full":"Edward Vlietinckstraat 11 Oostende West-Vlaanderen 8400",
    "addr:housenumber":"11",
    "addr:postcode":"8400",
    "addr:street":"Vlietinckstraat",
    "iso:country":"BE",
    "sg:address":"Edward Vlietinckstraat 11",
    "sg:city":"Oostende",
    "sg:orig_category":"Herstellingen and onderhoud van auto's Herstellingen motorfietsen Onderdelen and accessoires voor au",
    "sg:phone":"+32 59 80 92 30",
    "sg:postcode":"8400",
    "sg:province":"West-Vlaanderen",
    "wof:name":"N.l. Car Design",
    "wof:placetype":"venue"
},
  "geometry": {"coordinates":[2.9370551109,51.2073707581],"type":"Point"}
}