{
  "type": "Feature",
  "properties": {
    "addr:full":"Chauss\u00c9e De Braine-le-comte 102 Nivelles Brabant Wallon 1400",
    "addr:housenumber":"102",
    "addr:postcode":"1400",
    "addr:street":"Chausse\u0301E De Braine-Le-Comte",
    "iso:country":"BE",
    "sg:address":"Chauss\u00c9e De Braine-le-comte 102",
    "sg:city":"Nivelles",
    "sg:orig_category":"Catering and organisatie van feesten Hotels Restaurants Ruimtes voor conferenties, recepties and fee",
    "sg:phone":"+32 67 22 01 18",
    "sg:postcode":"1400",
    "sg:province":"Brabant Wallon",
    "wof:name":"Restaurant Ferme De Grambais",
    "wof:placetype":"venue"
},
  "geometry": {"coordinates":[4.303358078,50.5992012024],"type":"Point"}
}