{
  "type": "Feature",
  "properties": {
    "addr:full":"Rue Du Chantier 13 Bruxelles Bruxelles-Capitale 1000",
    "addr:housenumber":"13",
    "addr:postcode":"1000",
    "addr:street":"Rue Du Chantier",
    "iso:country":"BE",
    "sg:address":"Rue Du Chantier 13",
    "sg:city":"Bruxelles",
    "sg:classifiers":[
        {
            "category":"Communications",
            "subcategory":"Film & Video Production",
            "type":"Services"
        }
    ],
    "sg:phone":"+32 2 229 00 03",
    "sg:postcode":"1000",
    "sg:province":"Bruxelles-Capitale",
    "sg:tags":[
        "hiring",
        "distribution"
    ],
    "wof:name":"Argos Vzw",
    "wof:placetype":"venue"
},
  "geometry": {"coordinates":[4.3497018814,50.8565979004],"type":"Point"}
}