{
  "type": "Feature",
  "properties": {
    "addr:full":"Voorstraat 40 Kaprijke Oost-Vlaanderen 9970",
    "addr:housenumber":"40",
    "addr:postcode":"9970",
    "addr:street":"Voorstraat",
    "iso:country":"BE",
    "sg:address":"Voorstraat 40",
    "sg:city":"Kaprijke",
    "sg:classifiers":[
        {
            "category":"Arena",
            "subcategory":"Sports Club",
            "type":"Entertainment"
        }
    ],
    "sg:phone":"+32 9 373 81 59",
    "sg:postcode":"9970",
    "sg:province":"Oost-Vlaanderen",
    "sg:tags":[
        "terrain",
        "hors",
        "de",
        "installation",
        "sportifs"
    ],
    "wof:name":"F.c. Kaprijke-bentille",
    "wof:placetype":"venue"
},
  "geometry": {"coordinates":[3.6120629311,51.2179260254],"type":"Point"}
}