{
  "type": "Feature",
  "properties": {
    "addr:full":"Gentseheerweg 78 Izegem West-Vlaanderen 8870",
    "addr:housenumber":"78",
    "addr:postcode":"8870",
    "addr:street":"Gentseheerweg",
    "iso:country":"BE",
    "sg:address":"Gentseheerweg 78",
    "sg:city":"Izegem",
    "sg:classifiers":[
        {
            "category":"Wholesale",
            "subcategory":"Meat",
            "type":"Manufacturing & Wholesale Goods"
        }
    ],
    "sg:phone":"+32 51 31 19 33",
    "sg:postcode":"8870",
    "sg:province":"West-Vlaanderen",
    "sg:tags":[
        "abattoir"
    ],
    "wof:name":"E.e.g. Slachthuis Verbist Nv",
    "wof:placetype":"venue"
},
  "geometry": {"coordinates":[3.2311520576,50.9167823792],"type":"Point"}
}