{
  "type": "Feature",
  "properties": {
    "addr:full":"Monnikenhofstraat 20 Antwerpen Antwerpen 2040",
    "addr:housenumber":"20",
    "addr:postcode":"2040",
    "addr:street":"Monnikenhofstraat",
    "iso:country":"BE",
    "sg:address":"Monnikenhofstraat 20",
    "sg:city":"Antwerpen",
    "sg:orig_category":"Diverse bouwafwerking and reiniging",
    "sg:phone":"+32 3 569 98 32",
    "sg:postcode":"2040",
    "sg:province":"Antwerpen",
    "wof:name":"Delen Pat",
    "wof:placetype":"venue"
},
  "geometry": {"coordinates":[4.3280501366,51.3489608765],"type":"Point"}
}