{
  "type": "Feature",
  "properties": {
    "iso:country":"BE",
    "sg:address":"Sterrestraat 57",
    "sg:city":"Kortrijk",
    "sg:orig_category":"Afvalwaterverwerking and ontstoppingsdiensten Huisvuilophaling and -verwerking",
    "sg:phone":"+32 56 42 41 50",
    "sg:postcode":"8511",
    "sg:province":"West-Vlaanderen",
    "wof:name":"Saniflex",
    "wof:placetype":"venue"
},
  "geometry": {"coordinates":[3.2259099483,50.7753295898],"type":"Point"}
}