{
  "type": "Feature",
  "properties": {
    "addr:full":"Boulevard Des Invalides 69 Auderghem (bruxelles) Bruxelles-Capitale 1160",
    "addr:housenumber":"69",
    "addr:postcode":"1160",
    "addr:street":"Boulevard Des Invalides",
    "iso:country":"BE",
    "sg:address":"Boulevard Des Invalides 69",
    "sg:city":"Auderghem (bruxelles)",
    "sg:classifiers":[
        {
            "category":"Personal",
            "subcategory":"Beauty Salon",
            "type":"Services"
        }
    ],
    "sg:phone":"+32 2 675 95 38",
    "sg:postcode":"1160",
    "sg:province":"Bruxelles-Capitale",
    "sg:tags":[
        "de",
        "coiffure"
    ],
    "wof:name":"Imagin'hair",
    "wof:placetype":"venue"
},
  "geometry": {"coordinates":[4.4146342278,50.8168563843],"type":"Point"}
}