{
  "type": "Feature",
  "properties": {
    "iso:country":"BE",
    "sg:address":"Gospertstrasse 89",
    "sg:city":"Eupen",
    "sg:classifiers":[
        {
            "category":"Shopping",
            "subcategory":"Shoes",
            "type":"Retail Goods"
        }
    ],
    "sg:phone":"+32 87 74 24 42",
    "sg:postcode":"4700",
    "sg:province":"Li\u00e8ge",
    "sg:tags":[
        "slipper",
        "-"
    ],
    "wof:name":"Mommer",
    "wof:placetype":"venue"
},
  "geometry": {"coordinates":[6.0368709564,50.6325416565],"type":"Point"}
}