{
  "type": "Feature",
  "properties": {
    "iso:country":"BE",
    "sg:address":"A. De Taeyelaan 36",
    "sg:city":"Harelbeke",
    "sg:orig_category":"G\u00e9om\u00e8tres",
    "sg:phone":"+32 56 71 63 57",
    "sg:postcode":"8531",
    "sg:province":"West-Vlaanderen",
    "wof:name":"Luc Vandorpe",
    "wof:placetype":"venue"
},
  "geometry": {"coordinates":[3.3104400635,50.8748130798],"type":"Point"}
}