{
  "type": "Feature",
  "properties": {
    "addr:full":"Rue De Louveign\u00e9 15 Chaudfontaine (beaufays) Li\u00e8ge 4052",
    "addr:housenumber":"15",
    "addr:postcode":"4052",
    "addr:street":"Rue De Louveigne\u0301;Beaufays",
    "iso:country":"BE",
    "sg:address":"Rue De Louveign\u00e9 15",
    "sg:city":"Chaudfontaine (beaufays)",
    "sg:classifiers":[
        {
            "category":"Retail",
            "subcategory":"Veterinary Services",
            "type":"Services"
        }
    ],
    "sg:phone":"+32 4 368 87 82",
    "sg:postcode":"4052",
    "sg:province":"Li\u00e8ge",
    "sg:tags":[
        "veterinarian"
    ],
    "wof:name":"Luksenburg J",
    "wof:placetype":"venue"
},
  "geometry": {"coordinates":[5.6392202377,50.5586051941],"type":"Point"}
}