{
  "type": "Feature",
  "properties": {
    "addr:full":"Langeveldstraat 64 Ukkel/uccle Bruxelles-Capitale 1180",
    "addr:housenumber":"64",
    "addr:postcode":"1180",
    "addr:street":"Langeveldstraat;/",
    "iso:country":"BE",
    "sg:address":"Langeveldstraat 64",
    "sg:city":"Ukkel/uccle",
    "sg:orig_category":"Advocaten and juridische adviseurs",
    "sg:phone":"+32 2 374 72 37",
    "sg:postcode":"1180",
    "sg:province":"Bruxelles-Capitale",
    "wof:name":"A. Postelnicu",
    "wof:placetype":"venue"
},
  "geometry": {"coordinates":[4.3614830971,50.8065338135],"type":"Point"}
}