{
  "type": "Feature",
  "properties": {
    "iso:country":"BE",
    "sg:address":"Rue De Ten Brielen 104",
    "sg:city":"Comines-warneton (comines)",
    "sg:classifiers":[
        {
            "category":"Health Services",
            "subcategory":"Dentist",
            "type":"Services"
        }
    ],
    "sg:phone":"+32 56 55 57 37",
    "sg:postcode":"7780",
    "sg:province":"Hainaut",
    "wof:name":"Demeulenaere P",
    "wof:placetype":"venue"
},
  "geometry": {"coordinates":[2.9967899323,50.7743797302],"type":"Point"}
}