{
  "type": "Feature",
  "properties": {
    "addr:full":"Rue Lacherez 34 Anderlues Hainaut 6150",
    "addr:housenumber":"34",
    "addr:postcode":"6150",
    "addr:street":"Rue Lacherez",
    "iso:country":"BE",
    "sg:address":"Rue Lacherez 34",
    "sg:city":"Anderlues",
    "sg:orig_category":"Non-Classified Establishments",
    "sg:phone":"+32 71 54 58 87",
    "sg:postcode":"6150",
    "sg:province":"Hainaut",
    "wof:name":"Lilliputiens (les)",
    "wof:placetype":"venue"
},
  "geometry": {"coordinates":[4.2664527893,50.4133834839],"type":"Point"}
}