{
  "type": "Feature",
  "properties": {
    "iso:country":"BE",
    "sg:address":"Kerkstraat 24ba",
    "sg:city":"Lommel",
    "sg:orig_category":"Opticiens",
    "sg:phone":"+32 11 54 27 59",
    "sg:postcode":"3920",
    "sg:province":"Limburg",
    "wof:name":"Optiek Jo Van Kerckhoven",
    "wof:placetype":"venue"
},
  "geometry": {"coordinates":[5.311065197,51.2299728394],"type":"Point"}
}