{
  "type": "Feature",
  "properties": {
    "addr:full":"Huidevettersstraat 52 Antwerpen Antwerpen 2000",
    "addr:housenumber":"52",
    "addr:postcode":"2000",
    "addr:street":"Huidevettersstraat",
    "iso:country":"BE",
    "sg:address":"Huidevettersstraat 52",
    "sg:city":"Antwerpen",
    "sg:orig_category":"Instituts de beaut\u00e9",
    "sg:phone":"+32 3 213 39 30",
    "sg:postcode":"2000",
    "sg:province":"Antwerpen",
    "wof:name":"Beauty Foot Center Ahava",
    "wof:placetype":"venue"
},
  "geometry": {"coordinates":[4.4050741196,51.216468811],"type":"Point"}
}