{
  "type": "Feature",
  "properties": {
    "addr:full":"Route De Spa 63 Remouchamps Li\u00e8ge 4920",
    "addr:housenumber":"63",
    "addr:postcode":"4920",
    "addr:street":"Route De Spa",
    "iso:country":"BE",
    "sg:address":"Route De Spa 63",
    "sg:city":"Remouchamps",
    "sg:orig_category":"Jardinage",
    "sg:phone":"+32 4 384 75 21",
    "sg:postcode":"4920",
    "sg:province":"Li\u00e8ge",
    "wof:name":"Thonard Jean-marc",
    "wof:placetype":"venue"
},
  "geometry": {"coordinates":[5.724501133,50.47631073],"type":"Point"}
}