{
  "type": "Feature",
  "properties": {
    "iso:country":"BE",
    "sg:address":"Benonchamps 23",
    "sg:city":"Bastogne",
    "sg:orig_category":"Artistes ind\u00e9pendants",
    "sg:phone":"+32 61 21 49 83",
    "sg:postcode":"6600",
    "sg:province":"Luxembourg",
    "wof:name":"Jean-marc Salmon",
    "wof:placetype":"venue"
},
  "geometry": {"coordinates":[5.7148199081,50.0007820129],"type":"Point"}
}