{
  "type": "Feature",
  "properties": {
    "addr:full":"Hoveniersstraat 53 Antwerpen Antwerpen 2018",
    "addr:housenumber":"53",
    "addr:postcode":"2018",
    "addr:street":"Hoveniersstraat",
    "iso:country":"BE",
    "sg:address":"Hoveniersstraat 53",
    "sg:city":"Antwerpen",
    "sg:classifiers":[
        {
            "category":"Shopping",
            "subcategory":"Jewelry",
            "type":"Retail Goods"
        }
    ],
    "sg:phone":"+32 3 231 95 96",
    "sg:postcode":"2018",
    "sg:province":"Antwerpen",
    "sg:tags":[
        "diamond",
        "-"
    ],
    "wof:name":"Diamond Cutters Antwerp Nv",
    "wof:placetype":"venue"
},
  "geometry": {"coordinates":[4.4188599586,51.2144813538],"type":"Point"}
}