{
  "type": "Feature",
  "properties": {
    "addr:full":"Europark-noord 31a Sint-niklaas Oost-Vlaanderen 9100",
    "addr:housenumber":"31a",
    "addr:postcode":"9100",
    "addr:street":"Europark-Noord",
    "iso:country":"BE",
    "sg:address":"Europark-noord 31a",
    "sg:city":"Sint-niklaas",
    "sg:classifiers":[
        {
            "category":"Professional",
            "subcategory":"Testing Lab",
            "type":"Services"
        }
    ],
    "sg:phone":"+32 3 610 43 00",
    "sg:postcode":"9100",
    "sg:province":"Oost-Vlaanderen",
    "sg:tags":[
        "chemist"
    ],
    "wof:name":"Farmad Nv",
    "wof:placetype":"venue"
},
  "geometry": {"coordinates":[4.1665477753,51.1682167053],"type":"Point"}
}