{
  "type": "Feature",
  "properties": {
    "addr:full":"Molenwegel 15 Ardooie West-Vlaanderen 8851",
    "addr:housenumber":"15",
    "addr:postcode":"8851",
    "addr:street":"Molenwegel",
    "iso:country":"BE",
    "sg:address":"Molenwegel 15",
    "sg:city":"Ardooie",
    "sg:orig_category":"Alternatieve geneeskunde",
    "sg:phone":"+32 51 74 42 85",
    "sg:postcode":"8851",
    "sg:province":"West-Vlaanderen",
    "wof:name":"C. Callewaert",
    "wof:placetype":"venue"
},
  "geometry": {"coordinates":[3.2129709721,51.0024147034],"type":"Point"}
}