{
  "type": "Feature",
  "properties": {
    "addr:full":"Rue De La Mutualit\u00c9 57a Uccle Bruxelles-Capitale 1180",
    "addr:housenumber":"57a",
    "addr:postcode":"1180",
    "addr:street":"Rue De La Mutualite\u0301",
    "iso:country":"BE",
    "sg:address":"Rue De La Mutualit\u00c9 57a",
    "sg:city":"Uccle",
    "sg:orig_category":"Cr\u00e9meries. Restaurants",
    "sg:phone":"+32 2 344 70 81",
    "sg:postcode":"1180",
    "sg:province":"Bruxelles-Capitale",
    "wof:name":"Glacier Zizi",
    "wof:placetype":"venue"
},
  "geometry": {"coordinates":[4.3448748589,50.8136100769],"type":"Point"}
}