{
  "type": "Feature",
  "properties": {
    "iso:country":"BE",
    "sg:address":"Beverlo Dorp 23",
    "sg:city":"Beringen (beverlo)",
    "sg:classifiers":[
        {
            "category":"Shopping",
            "subcategory":"Clothing, Apparel, & Fashions",
            "type":"Retail Goods"
        }
    ],
    "sg:phone":"+32 11 34 22 49",
    "sg:postcode":"3581",
    "sg:province":"Limburg",
    "sg:tags":[
        "underwear",
        "lingerie",
        "-"
    ],
    "wof:name":"Veronique",
    "wof:placetype":"venue"
},
  "geometry": {"coordinates":[5.2208609581,51.0879325867],"type":"Point"}
}