{
  "type": "Feature",
  "properties": {
    "addr:full":"Dijver 7 Brugge West-Vlaanderen 8000",
    "addr:housenumber":"7",
    "addr:postcode":"8000",
    "addr:street":"Dijver",
    "iso:country":"BE",
    "sg:address":"Dijver 7",
    "sg:city":"Brugge",
    "sg:classifiers":[
        {
            "category":"Travel",
            "subcategory":"Hotels & Motels",
            "type":"Entertainment"
        }
    ],
    "sg:phone":"+32 50 34 36 91",
    "sg:postcode":"8000",
    "sg:province":"West-Vlaanderen",
    "wof:name":"Hotel De Tuilerie\u00ebn",
    "wof:placetype":"venue"
},
  "geometry": {"coordinates":[3.22656703,51.2063331604],"type":"Point"}
}