{
  "type": "Feature",
  "properties": {
    "iso:country":"BE",
    "sg:address":"Terbermenweg 1",
    "sg:city":"Herk-de-stad",
    "sg:classifiers":[
        {
            "category":"Health Services",
            "subcategory":"Dentist",
            "type":"Services"
        }
    ],
    "sg:phone":"+32 13 55 12 12",
    "sg:postcode":"3540",
    "sg:province":"Limburg",
    "wof:name":"Vandersmissen Bryan",
    "wof:placetype":"venue"
},
  "geometry": {"coordinates":[5.1938619614,50.903175354],"type":"Point"}
}