{
  "type": "Feature",
  "properties": {
    "iso:country":"BE",
    "sg:address":"Rue Mabotte 217",
    "sg:city":"Seraing",
    "sg:classifiers":[
        {
            "category":"Insurance",
            "subcategory":"Life Insurance",
            "type":"Services"
        }
    ],
    "sg:phone":"+32 4 233 90 68",
    "sg:postcode":"4101",
    "sg:province":"Li\u00e8ge",
    "sg:tags":[
        "assurance"
    ],
    "wof:name":"Bureau Masciarelli",
    "wof:placetype":"venue"
},
  "geometry": {"coordinates":[5.5225491524,50.6248817444],"type":"Point"}
}