{
  "type": "Feature",
  "properties": {
    "addr:full":"Salom\u00c9laan 2 Sint-pieters-woluwe/woluwe-saint-pierre Bruxelles-Capitale 1150",
    "addr:housenumber":"2",
    "addr:postcode":"1150",
    "addr:street":"Salome\u0301Laan;/",
    "iso:country":"BE",
    "sg:address":"Salom\u00c9laan 2",
    "sg:city":"Sint-pieters-woluwe/woluwe-saint-pierre",
    "sg:classifiers":[
        {
            "category":"Cafe",
            "type":"Food & Drink"
        }
    ],
    "sg:phone":"+32 2 771 50 41",
    "sg:postcode":"1150",
    "sg:province":"Bruxelles-Capitale",
    "sg:tags":[
        "caf\u00e9s"
    ],
    "wof:name":"Ass.sport.woluwe St.p.",
    "wof:placetype":"venue"
},
  "geometry": {"coordinates":[4.4548330307,50.8308067322],"type":"Point"}
}