{
  "type": "Feature",
  "properties": {
    "iso:country":"BE",
    "sg:address":"Rue Du Textile 3",
    "sg:city":"Comines-warneton (comines)",
    "sg:classifiers":[
        {
            "category":"Retail",
            "subcategory":"Auto Repair",
            "type":"Services"
        }
    ],
    "sg:phone":"+32 56 55 42 80",
    "sg:postcode":"7780",
    "sg:province":"Hainaut",
    "sg:tags":[
        "automobile-body"
    ],
    "wof:name":"Carlac-vandamme",
    "wof:placetype":"venue"
},
  "geometry": {"coordinates":[3.0195250511,50.7782669067],"type":"Point"}
}