{
  "type": "Feature",
  "properties": {
    "iso:country":"BE",
    "sg:address":"Grand Rue 100",
    "sg:city":"Montigny",
    "sg:classifiers":[
        {
            "category":"Banks & Credit Unions",
            "subcategory":"Bank",
            "type":"Services"
        }
    ],
    "sg:phone":"+32 60 32 57 31",
    "sg:postcode":"6080",
    "wof:name":"Banque Bruxelles Lambert Sa",
    "wof:placetype":"venue"
},
  "geometry": {"coordinates":[5.9572701454,51.2357597351],"type":"Point"}
}