{
  "type": "Feature",
  "properties": {
    "iso:country":"BE",
    "sg:address":"Rozebeeksestraat 29",
    "sg:city":"Lendelede",
    "sg:classifiers":[
        {
            "category":"Banks & Credit Unions",
            "subcategory":"Bank",
            "type":"Services"
        }
    ],
    "sg:phone":"+32 51 30 32 96",
    "sg:postcode":"8860",
    "sg:province":"West-Vlaanderen",
    "sg:tags":[
        "savings-banks"
    ],
    "wof:name":"Bruneel",
    "wof:placetype":"venue"
},
  "geometry": {"coordinates":[3.2425460815,50.8876266479],"type":"Point"}
}