{
  "type": "Feature",
  "properties": {
    "iso:country":"BE",
    "sg:address":"Rue De L\u00b4etang 35",
    "sg:city":"Ans",
    "sg:orig_category":"Diverse bouwafwerking and reiniging",
    "sg:phone":"+32 4 257 60 29",
    "sg:postcode":"4432",
    "sg:province":"Li\u00e8ge",
    "wof:name":"Bollaerts Ent",
    "wof:placetype":"venue"
},
  "geometry": {"coordinates":[5.4798798561,50.700553894],"type":"Point"}
}