{
  "type": "Feature",
  "properties": {
    "addr:full":"Rue Du Panorama Theux Li\u00e8ge 4910",
    "addr:postcode":"4910",
    "addr:street":"Rue Du Panorama",
    "iso:country":"BE",
    "sg:address":"Rue Du Panorama",
    "sg:city":"Theux",
    "sg:classifiers":[
        {
            "category":"Recreation",
            "subcategory":"Campground",
            "type":"Entertainment"
        }
    ],
    "sg:phone":"+32 87 54 26 27",
    "sg:postcode":"4910",
    "sg:province":"Li\u00e8ge",
    "sg:tags":[
        "site",
        "camping"
    ],
    "wof:name":"R.s.i Theux (camping Du)",
    "wof:placetype":"venue"
},
  "geometry": {"coordinates":[5.807972908,50.5376167297],"type":"Point"}
}