{
  "type": "Feature",
  "properties": {
    "iso:country":"BE",
    "sg:address":"Rue De La Commune 25",
    "sg:city":"Sint-joost-ten-node/saint-josse-ten-noode",
    "sg:orig_category":"Editeurs de journaux. Salles de spectacles. Editeurs de revues and p\u00e9riodiques",
    "sg:phone":"+32 2 217 08 82",
    "sg:postcode":"1210",
    "sg:province":"Bruxelles-Capitale",
    "wof:name":"Centrum Ten Noey",
    "wof:placetype":"venue"
},
  "geometry": {"coordinates":[4.3724570274,50.8512878418],"type":"Point"}
}