{
  "type": "Feature",
  "properties": {
    "addr:full":"Stationsstraat 38 Oosterzele Oost-Vlaanderen 9860",
    "addr:housenumber":"38",
    "addr:postcode":"9860",
    "addr:street":"Stationsstraat;Oost-Vlaanderen",
    "iso:country":"BE",
    "sg:address":"Stationsstraat 38",
    "sg:city":"Oosterzele",
    "sg:orig_category":"Banken and kredietinstellingen",
    "sg:phone":"+32 9 362 57 08",
    "sg:postcode":"9860",
    "sg:province":"Oost-Vlaanderen",
    "wof:name":"Anhyp",
    "wof:placetype":"venue"
},
  "geometry": {"coordinates":[3.7816689014,50.9379043579],"type":"Point"}
}