{
  "type": "Feature",
  "properties": {
    "iso:country":"BE",
    "sg:address":"Passtraat 171",
    "sg:city":"Geel",
    "sg:orig_category":"V\u00e9los. Motos",
    "sg:phone":"+32 14 58 89 57",
    "sg:postcode":"2440",
    "sg:province":"Antwerpen",
    "wof:name":"Karel Boeckx",
    "wof:placetype":"venue"
},
  "geometry": {"coordinates":[4.985850811,51.1569747925],"type":"Point"}
}