{
  "type": "Feature",
  "properties": {
    "iso:country":"BE",
    "sg:address":"Rue De Richelle 11",
    "sg:city":"Vise",
    "sg:orig_category":"Pain, p\u00e2tisseries and confiseries",
    "sg:phone":"+32 4 379 16 13",
    "sg:postcode":"4600",
    "sg:province":"Li\u00e8ge",
    "wof:name":"Dessart Fr\u00c8res & Fils",
    "wof:placetype":"venue"
},
  "geometry": {"coordinates":[5.6970949173,50.7290229797],"type":"Point"}
}