{
  "type": "Feature",
  "properties": {
    "addr:full":"Poststraat 17 Lebbeke Oost-Vlaanderen 9280",
    "addr:housenumber":"17",
    "addr:postcode":"9280",
    "addr:street":"Poststraat",
    "iso:country":"BE",
    "sg:address":"Poststraat 17",
    "sg:city":"Lebbeke",
    "sg:classifiers":[
        {
            "category":"Organizations",
            "subcategory":"Community Association",
            "type":"Services"
        }
    ],
    "sg:phone":"+32 52 41 24 16",
    "sg:postcode":"9280",
    "sg:province":"Oost-Vlaanderen",
    "sg:tags":[
        "cultural"
    ],
    "wof:name":"Incar Dansspektakel Vzw",
    "wof:placetype":"venue"
},
  "geometry": {"coordinates":[4.1328949928,51.0002784729],"type":"Point"}
}