{
  "type": "Feature",
  "properties": {
    "addr:full":"Nieuwpoortsteenweg 155 Koksijde (oostduinkerke) West-Vlaanderen 8670",
    "addr:housenumber":"155",
    "addr:postcode":"8670",
    "addr:street":"Nieuwpoortsteenweg",
    "iso:country":"BE",
    "sg:address":"Nieuwpoortsteenweg 155",
    "sg:city":"Koksijde (oostduinkerke)",
    "sg:classifiers":[
        {
            "category":"Real Estate",
            "subcategory":"Architect",
            "type":"Services"
        }
    ],
    "sg:phone":"+32 58 23 27 23",
    "sg:postcode":"8670",
    "sg:province":"West-Vlaanderen",
    "wof:name":"Arschoot L",
    "wof:placetype":"venue"
},
  "geometry": {"coordinates":[2.7082099915,51.1224594116],"type":"Point"}
}