{
  "type": "Feature",
  "properties": {
    "iso:country":"BE",
    "sg:address":"Square Du Bastion 1ba",
    "sg:city":"Elsene/ixelles",
    "sg:orig_category":"Avocats and conseillers juridiques",
    "sg:phone":"+32 2 289 64 64",
    "sg:postcode":"1050",
    "sg:province":"Bruxelles-Capitale",
    "wof:name":"Ga\u00cbtane Schmitz",
    "wof:placetype":"venue"
},
  "geometry": {"coordinates":[4.3623490334,50.8380203247],"type":"Point"}
}