{
  "type": "Feature",
  "properties": {
    "addr:full":"Place Saint-nicolas 261 Li\u00e8ge 1 Li\u00e8ge 4000",
    "addr:housenumber":"261;1",
    "addr:postcode":"4000",
    "addr:street":"Place Saint-Nicolas",
    "iso:country":"BE",
    "sg:address":"Place Saint-nicolas 261",
    "sg:city":"Li\u00e8ge 1",
    "sg:classifiers":[
        {
            "category":"Personal",
            "type":"Services"
        }
    ],
    "sg:phone":"+32 4 226 05 62",
    "sg:postcode":"4000",
    "sg:province":"Li\u00e8ge",
    "sg:tags":[
        "clothing",
        "men's",
        "tailor",
        "-"
    ],
    "wof:name":"Constant Mary",
    "wof:placetype":"venue"
},
  "geometry": {"coordinates":[5.5424160957,50.6386680603],"type":"Point"}
}