{
  "type": "Feature",
  "properties": {
    "addr:full":"Beekstraat 149a Willebroek (tisselt) Antwerpen 2830",
    "addr:housenumber":"149a",
    "addr:postcode":"2830",
    "addr:street":"Beekstraat",
    "iso:country":"BE",
    "sg:address":"Beekstraat 149a",
    "sg:city":"Willebroek (tisselt)",
    "sg:classifiers":[
        {
            "category":"Structure",
            "subcategory":"Building",
            "type":"Public Place"
        }
    ],
    "sg:phone":"+32 15 71 11 51",
    "sg:postcode":"2830",
    "sg:province":"Antwerpen",
    "sg:tags":[
        "door"
    ],
    "wof:name":"Multi-industries Bvba",
    "wof:placetype":"venue"
},
  "geometry": {"coordinates":[4.3403759003,51.0271530151],"type":"Point"}
}