{
  "type": "Feature",
  "properties": {
    "addr:full":"De Linde 24 Zonnebeke West-Vlaanderen 8980",
    "addr:housenumber":"24",
    "addr:postcode":"8980",
    "addr:street":"De Linde",
    "iso:country":"BE",
    "sg:address":"De Linde 24",
    "sg:city":"Zonnebeke",
    "sg:orig_category":"Quincailleries",
    "sg:phone":"+32 57 46 83 05",
    "sg:postcode":"8980",
    "sg:province":"West-Vlaanderen",
    "wof:name":"Fa. Debouck",
    "wof:placetype":"venue"
},
  "geometry": {"coordinates":[2.9880099297,50.8364753723],"type":"Point"}
}