{
  "type": "Feature",
  "properties": {
    "addr:full":"Kortrijkstraat 119a Zwevegem West-Vlaanderen 8550",
    "addr:housenumber":"119a",
    "addr:postcode":"8550",
    "addr:street":"Kortrijkstraat",
    "iso:country":"BE",
    "sg:address":"Kortrijkstraat 119a",
    "sg:city":"Zwevegem",
    "sg:orig_category":"Non-Classified Establishments",
    "sg:phone":"+32 56 75 62 74",
    "sg:postcode":"8550",
    "sg:province":"West-Vlaanderen",
    "wof:name":"Alva Light Bvba",
    "wof:placetype":"venue"
},
  "geometry": {"coordinates":[3.3191299438,50.8145828247],"type":"Point"}
}