{
  "type": "Feature",
  "properties": {
    "addr:full":"Kattendansstraat 83 Hasselt Limburg 3500",
    "addr:housenumber":"83",
    "addr:postcode":"3500",
    "addr:street":"Kattendansstraat",
    "iso:country":"BE",
    "sg:address":"Kattendansstraat 83",
    "sg:city":"Hasselt",
    "sg:orig_category":"Rev\u00eatements de sols and murs",
    "sg:phone":"+32 11 27 56 71",
    "sg:postcode":"3500",
    "sg:province":"Limburg",
    "wof:name":"Stone Constructing",
    "wof:placetype":"venue"
},
  "geometry": {"coordinates":[5.3326320648,50.8992996216],"type":"Point"}
}