{
  "type": "Feature",
  "properties": {
    "iso:country":"BE",
    "sg:address":"Frederik De Merodestraat 87",
    "sg:city":"Mechelen",
    "sg:classifiers":[
        {
            "category":"Shopping",
            "subcategory":"Musical Instruments",
            "type":"Retail Goods"
        }
    ],
    "sg:phone":"+32 15 20 49 17",
    "sg:postcode":"2800",
    "sg:province":"Antwerpen",
    "sg:tags":[
        "-"
    ],
    "wof:name":"B.c. Brass",
    "wof:placetype":"venue"
},
  "geometry": {"coordinates":[4.4829688072,51.0319709778],"type":"Point"}
}