{
  "type": "Feature",
  "properties": {
    "addr:full":"Damhertlaan 4 Watermaal-bosvoorde/watermael-boitsfort Bruxelles-Capitale 1170",
    "addr:housenumber":"4",
    "addr:postcode":"1170",
    "addr:street":"Damhertlaan",
    "iso:country":"BE",
    "sg:address":"Damhertlaan 4",
    "sg:city":"Watermaal-bosvoorde/watermael-boitsfort",
    "sg:orig_category":"Artsen and specialisten",
    "sg:phone":"+32 2 660 91 99",
    "sg:postcode":"1170",
    "sg:province":"Bruxelles-Capitale",
    "wof:name":"Dominique Lison",
    "wof:placetype":"venue"
},
  "geometry": {"coordinates":[4.4202308655,50.8055305481],"type":"Point"}
}