{
  "type": "Feature",
  "properties": {
    "addr:full":"Rue Royale 55 Box 16 Bruxelles Bruxelles-Capitale 1000",
    "addr:housenumber":"55 box 16",
    "addr:postcode":"1000",
    "addr:street":"Rue Royale",
    "iso:country":"BE",
    "sg:address":"Rue Royale 55 Box 16",
    "sg:city":"Bruxelles",
    "sg:classifiers":[
        {
            "category":"Building & Trades",
            "subcategory":"Electrical",
            "type":"Services"
        }
    ],
    "sg:phone":"+32 2 223 13 67",
    "sg:postcode":"1000",
    "sg:province":"Bruxelles-Capitale",
    "sg:tags":[
        "-",
        "electric",
        "contractor"
    ],
    "wof:name":"Cardib",
    "wof:placetype":"venue"
},
  "geometry": {"coordinates":[4.363902092,50.8493156433],"type":"Point"}
}