{
  "type": "Feature",
  "properties": {
    "iso:country":"BE",
    "sg:address":"Station 59",
    "sg:city":"Gedinne",
    "sg:orig_category":"Entretien et r\u00e9parations de v\u00e9hicules \u00e0 domicile",
    "sg:phone":"+32 475 55 68 62",
    "sg:postcode":"5575",
    "sg:province":"Namur",
    "wof:name":"Albert Garage",
    "wof:placetype":"venue"
},
  "geometry": {"coordinates":[4.9788370132,49.9825592041],"type":"Point"}
}