{
  "type": "Feature",
  "properties": {
    "addr:full":"Malmedyer Strasse 118 Sankt Vith Li\u00e8ge 4780",
    "addr:housenumber":"118",
    "addr:postcode":"4780",
    "addr:street":"Malmedyer Strasse",
    "iso:country":"BE",
    "sg:address":"Malmedyer Strasse 118",
    "sg:city":"Sankt Vith",
    "sg:classifiers":[
        {
            "category":"Retail",
            "subcategory":"Auto Repair",
            "type":"Services"
        }
    ],
    "sg:phone":"+32 80 22 89 21",
    "sg:postcode":"4780",
    "sg:province":"Li\u00e8ge",
    "sg:tags":[
        "garage"
    ],
    "wof:name":"Plattes H",
    "wof:placetype":"venue"
},
  "geometry": {"coordinates":[6.1181330681,50.2906646729],"type":"Point"}
}