{
  "type": "Feature",
  "properties": {
    "addr:full":"Tarwestraat 15 Oostende West-Vlaanderen 8400",
    "addr:housenumber":"15",
    "addr:postcode":"8400",
    "addr:street":"Tarwestraat",
    "iso:country":"BE",
    "sg:address":"Tarwestraat 15",
    "sg:city":"Oostende",
    "sg:orig_category":"Activit\u00e9s r\u00e9cr\u00e9atives diverses",
    "sg:phone":"+32 59 50 43 10",
    "sg:postcode":"8400",
    "sg:province":"West-Vlaanderen",
    "wof:name":"Postzegelclub De Westhoek",
    "wof:placetype":"venue"
},
  "geometry": {"coordinates":[2.9114460945,51.2191963196],"type":"Point"}
}