{
  "type": "Feature",
  "properties": {
    "iso:country":"BE",
    "sg:address":"Pliniuswal 30",
    "sg:city":"Tongeren",
    "sg:orig_category":"Parfumeries. Salons de coiffure",
    "sg:phone":"+32 12 23 03 93",
    "sg:postcode":"3700",
    "sg:province":"Limburg",
    "wof:name":"Hair-studio",
    "wof:placetype":"venue"
},
  "geometry": {"coordinates":[5.4616031647,50.7831611633],"type":"Point"}
}