{
  "type": "Feature",
  "properties": {
    "iso:country":"BE",
    "sg:address":"Ten Bosse 122",
    "sg:city":"Zottegem",
    "sg:orig_category":"Elektrische installaties voor woningen",
    "sg:phone":"+32 9 360 27 19",
    "sg:postcode":"9620",
    "sg:province":"Oost-Vlaanderen",
    "wof:name":"A Pede",
    "wof:placetype":"venue"
},
  "geometry": {"coordinates":[3.7920250893,50.8457260132],"type":"Point"}
}