{
  "type": "Feature",
  "properties": {
    "addr:full":"Dennenlaan 14b5 Dilbeek Vlaams-Brabant 1700",
    "addr:housenumber":"14b5",
    "addr:postcode":"1700",
    "addr:street":"Dennenlaan",
    "iso:country":"BE",
    "sg:address":"Dennenlaan 14b5",
    "sg:city":"Dilbeek",
    "sg:orig_category":"Administration d'immeubles",
    "sg:phone":"+32 2 569 75 67",
    "sg:postcode":"1700",
    "sg:province":"Vlaams-Brabant",
    "wof:name":"Michel Henno",
    "wof:placetype":"venue"
},
  "geometry": {"coordinates":[4.2572159767,50.8416442871],"type":"Point"}
}