{
  "type": "Feature",
  "properties": {
    "addr:full":"Rue De Gilly 366 Ch\u00e2telet (ch\u00e2telineau) Hainaut 6200",
    "addr:housenumber":"366",
    "addr:postcode":"6200",
    "addr:street":"Rue De Gilly",
    "iso:country":"BE",
    "sg:address":"Rue De Gilly 366",
    "sg:city":"Ch\u00e2telet (ch\u00e2telineau)",
    "sg:classifiers":[
        {
            "category":"Building & Trades",
            "subcategory":"Construction",
            "type":"Services"
        }
    ],
    "sg:phone":"+32 71 38 30 09",
    "sg:postcode":"6200",
    "sg:province":"Hainaut",
    "sg:tags":[
        "installation",
        "-",
        "central",
        "heating"
    ],
    "wof:name":"Nizet",
    "wof:placetype":"venue"
},
  "geometry": {"coordinates":[4.5041370392,50.4115905762],"type":"Point"}
}