{
  "type": "Feature",
  "properties": {
    "addr:full":"Liersesteenweg 477 Mechelen Antwerpen 2800",
    "addr:housenumber":"477",
    "addr:postcode":"2800",
    "addr:street":"Liersesteenweg",
    "iso:country":"BE",
    "sg:address":"Liersesteenweg 477",
    "sg:city":"Mechelen",
    "sg:classifiers":[
        {
            "category":"Retail",
            "subcategory":"Auto Repair",
            "type":"Services"
        }
    ],
    "sg:phone":"+32 15 20 49 88",
    "sg:postcode":"2800",
    "sg:province":"Antwerpen",
    "sg:tags":[
        "automobile-body"
    ],
    "wof:name":"Opsomer Bvba",
    "wof:placetype":"venue"
},
  "geometry": {"coordinates":[4.4802727699,51.0520324707],"type":"Point"}
}