{
  "type": "Feature",
  "properties": {
    "addr:full":"Koekelarestraat 62 Kortemark (groot) West-Vlaanderen 8610",
    "addr:housenumber":"62",
    "addr:postcode":"8610",
    "addr:street":"Koekelarestraat;Groot West-Vlaanderen",
    "iso:country":"BE",
    "sg:address":"Koekelarestraat 62",
    "sg:city":"Kortemark (groot)",
    "sg:orig_category":"Bouwmaterialen Gh",
    "sg:phone":"+32 51 56 69 59",
    "sg:postcode":"8610",
    "sg:province":"West-Vlaanderen",
    "wof:name":"Waeyaert - Vermeersch Nv",
    "wof:placetype":"venue"
},
  "geometry": {"coordinates":[3.0178599358,51.0503807068],"type":"Point"}
}