{
  "type": "Feature",
  "properties": {
    "addr:full":"Rue Buissonvaux 6a Waremme Li\u00e8ge 4300",
    "addr:housenumber":"6a",
    "addr:postcode":"4300",
    "addr:street":"Rue Buissonvaux",
    "iso:country":"BE",
    "sg:address":"Rue Buissonvaux 6a",
    "sg:city":"Waremme",
    "sg:classifiers":[
        {
            "category":"Professional",
            "subcategory":"Lawyer & Legal Services",
            "type":"Services"
        }
    ],
    "sg:phone":"+32 19 32 83 93",
    "sg:postcode":"4300",
    "sg:province":"Li\u00e8ge",
    "wof:name":"Ma\u00eetre Hannosset Etienne",
    "wof:placetype":"venue"
},
  "geometry": {"coordinates":[5.2517161369,50.6857795715],"type":"Point"}
}