{
  "type": "Feature",
  "properties": {
    "addr:full":"Meulestraat 16-18 Sint-lievens-houtem (bavegem) Oost-Vlaanderen 9520",
    "addr:housenumber":"16-18",
    "addr:postcode":"9520",
    "addr:street":"Meulestraat",
    "iso:country":"BE",
    "sg:address":"Meulestraat 16-18",
    "sg:city":"Sint-lievens-houtem (bavegem)",
    "sg:classifiers":[
        {
            "category":"Freight",
            "type":"Transportation"
        }
    ],
    "sg:phone":"+32 9 362 55 05",
    "sg:postcode":"9520",
    "sg:province":"Oost-Vlaanderen",
    "sg:tags":[
        "-",
        "refrigerated",
        "transport"
    ],
    "wof:name":"Defotrans Nv",
    "wof:placetype":"venue"
},
  "geometry": {"coordinates":[3.8618760109,50.9436035156],"type":"Point"}
}