{
  "type": "Feature",
  "properties": {
    "addr:full":"Chauss\u00c9e De Helmet 134 Schaarbeek/schaerbeek Bruxelles-Capitale 1030",
    "addr:housenumber":"134",
    "addr:postcode":"1030",
    "addr:street":"Chausse\u0301E De Helmet",
    "iso:country":"BE",
    "sg:address":"Chauss\u00c9e De Helmet 134",
    "sg:city":"Schaarbeek/schaerbeek",
    "sg:orig_category":"Pain, p\u00e2tisseries and confiseries",
    "sg:phone":"+32 2 215 85 59",
    "sg:postcode":"1030",
    "sg:province":"Bruxelles-Capitale",
    "wof:name":"Helmet Cadeau",
    "wof:placetype":"venue"
},
  "geometry": {"coordinates":[4.3851270676,50.8718147278],"type":"Point"}
}