{
  "type": "Feature",
  "properties": {
    "addr:full":"Rue Joseph Dupont 10 Bruxelles Bruxelles-Capitale 1000",
    "addr:housenumber":"10",
    "addr:postcode":"1000",
    "addr:street":"Rue Joseph Dupont",
    "iso:country":"BE",
    "sg:address":"Rue Joseph Dupont 10",
    "sg:city":"Bruxelles",
    "sg:classifiers":[
        {
            "category":"Professional",
            "subcategory":"Management & Consulting",
            "type":"Services"
        }
    ],
    "sg:phone":"+32 2 514 32 98",
    "sg:postcode":"1000",
    "sg:province":"Bruxelles-Capitale",
    "sg:tags":[
        "consultant",
        "law"
    ],
    "wof:name":"Holsters A",
    "wof:placetype":"venue"
},
  "geometry": {"coordinates":[4.3554530144,50.8384170532],"type":"Point"}
}