{
  "type": "Feature",
  "properties": {
    "addr:full":"Sint-michielskaai 31 Antwerpen Antwerpen 2000",
    "addr:housenumber":"31",
    "addr:postcode":"2000",
    "addr:street":"Sint-Michielskaai",
    "iso:country":"BE",
    "sg:address":"Sint-michielskaai 31",
    "sg:city":"Antwerpen",
    "sg:classifiers":[
        {
            "category":"Banks & Credit Unions",
            "subcategory":"Financial Services",
            "type":"Services"
        }
    ],
    "sg:phone":"+32 3 260 94 30",
    "sg:postcode":"2000",
    "sg:province":"Antwerpen",
    "sg:tags":[
        "financing"
    ],
    "wof:name":"Sokrema Nv",
    "wof:placetype":"venue"
},
  "geometry": {"coordinates":[4.3919901848,51.2139472961],"type":"Point"}
}