{
  "type": "Feature",
  "properties": {
    "iso:country":"BE",
    "sg:address":"Dokter Vanderhoeydonckstraat 52",
    "sg:city":"Lummen",
    "sg:classifiers":[
        {
            "category":"Bars & Pubs",
            "type":"Food & Drink"
        }
    ],
    "sg:phone":"+32 13 53 15 88",
    "sg:postcode":"3560",
    "sg:province":"Limburg",
    "sg:tags":[
        "tavern"
    ],
    "wof:name":"Vreehof",
    "wof:placetype":"venue"
},
  "geometry": {"coordinates":[5.199447155,50.9853172302],"type":"Point"}
}