{
  "type": "Feature",
  "properties": {
    "addr:full":"Papegaailaan 1 Antwerpen (deurne) Antwerpen 2100",
    "addr:housenumber":"1",
    "addr:postcode":"2100",
    "addr:street":"Papegaailaan",
    "iso:country":"BE",
    "sg:address":"Papegaailaan 1",
    "sg:city":"Antwerpen (deurne)",
    "sg:classifiers":[
        {
            "category":"Building & Trades",
            "subcategory":"Plumbing",
            "type":"Services"
        }
    ],
    "sg:phone":"+32 3 322 45 32",
    "sg:postcode":"2100",
    "sg:province":"Antwerpen",
    "sg:tags":[
        "contractor"
    ],
    "wof:name":"Van Den Bulck Ben",
    "wof:placetype":"venue"
},
  "geometry": {"coordinates":[4.4586100578,51.2203941345],"type":"Point"}
}