{
  "type": "Feature",
  "properties": {
    "iso:country":"BE",
    "sg:address":"Noordstraat 64",
    "sg:city":"Middelkerke",
    "sg:orig_category":"Industri\u00eble elektrische installaties",
    "sg:phone":"+32 58 23 61 01",
    "sg:postcode":"8434",
    "sg:province":"West-Vlaanderen",
    "wof:name":"Liftcontrol",
    "wof:placetype":"venue"
},
  "geometry": {"coordinates":[2.7569050789,51.1488685608],"type":"Point"}
}