{
  "type": "Feature",
  "properties": {
    "addr:full":"Groenstraat 10 Assenede Oost-Vlaanderen 9960",
    "addr:housenumber":"10",
    "addr:postcode":"9960",
    "addr:street":"Groenstraat",
    "iso:country":"BE",
    "sg:address":"Groenstraat 10",
    "sg:city":"Assenede",
    "sg:classifiers":[
        {
            "category":"Food & Beverages",
            "subcategory":"Dairy",
            "type":"Retail Goods"
        }
    ],
    "sg:phone":"+32 9 344 74 93",
    "sg:postcode":"9960",
    "sg:province":"Oost-Vlaanderen",
    "sg:tags":[
        "product",
        "-"
    ],
    "wof:name":"Mussche",
    "wof:placetype":"venue"
},
  "geometry": {"coordinates":[3.7494950294,51.2223243713],"type":"Point"}
}