{
  "type": "Feature",
  "properties": {
    "iso:country":"BE",
    "sg:address":"Chauss\u00c9e De Gand 615",
    "sg:city":"Sint-jans-molenbeek/molenbeek-saint-jean",
    "sg:orig_category":"Produits pharmaceutiques Fab",
    "sg:phone":"+32 2 464 06 88",
    "sg:postcode":"1080",
    "sg:province":"Bruxelles-Capitale",
    "wof:name":"Diff. Exclusive Pharmacie",
    "wof:placetype":"venue"
},
  "geometry": {"coordinates":[4.3064389229,50.8605194092],"type":"Point"}
}