{
  "type": "Feature",
  "properties": {
    "iso:country":"BE",
    "sg:address":"Cantincrodelaan 62",
    "sg:city":"Borsbeek",
    "sg:orig_category":"Sportclubs",
    "sg:phone":"+32 3 321 41 36",
    "sg:postcode":"2150",
    "sg:province":"Antwerpen",
    "wof:name":"Amateurs Bc Fv",
    "wof:placetype":"venue"
},
  "geometry": {"coordinates":[4.4781551361,51.200843811],"type":"Point"}
}