{
  "type": "Feature",
  "properties": {
    "iso:country":"BE",
    "sg:address":"Clos Du Moustier 52",
    "sg:city":"Jurbise",
    "sg:orig_category":"Activit\u00e9s r\u00e9cr\u00e9atives diverses",
    "sg:phone":"+32 65 22 67 66",
    "sg:postcode":"7050",
    "sg:province":"Hainaut",
    "wof:name":"Cercle De Bridge De Mons",
    "wof:placetype":"venue"
},
  "geometry": {"coordinates":[3.904517889,50.5334701538],"type":"Point"}
}