{
  "type": "Feature",
  "properties": {
    "addr:full":"Gebroeders Van Raemdonckstraat 2 Temse Oost-Vlaanderen 9140",
    "addr:housenumber":"2",
    "addr:postcode":"9140",
    "addr:street":"Gebroeders Van Raemdonckstraat",
    "iso:country":"BE",
    "sg:address":"Gebroeders Van Raemdonckstraat 2",
    "sg:city":"Temse",
    "sg:orig_category":"Informaticaconsulenten",
    "sg:phone":"+32 3 771 51 32",
    "sg:postcode":"9140",
    "sg:province":"Oost-Vlaanderen",
    "wof:name":"J-consult",
    "wof:placetype":"venue"
},
  "geometry": {"coordinates":[4.21185112,51.1313972473],"type":"Point"}
}