{
  "type": "Feature",
  "properties": {
    "iso:country":"BE",
    "sg:address":"Quai De Coronmeuse 1",
    "sg:city":"Li\u00e8ge 1",
    "sg:classifiers":[
        {
            "category":"Building & Trades",
            "subcategory":"Construction",
            "type":"Services"
        }
    ],
    "sg:phone":"+32 4 227 56 55",
    "sg:postcode":"4000",
    "sg:province":"Li\u00e8ge",
    "sg:tags":[
        "glazier"
    ],
    "wof:name":"Atlas-vitres",
    "wof:placetype":"venue"
},
  "geometry": {"coordinates":[5.6000781059,50.6505813599],"type":"Point"}
}