{
  "type": "Feature",
  "properties": {
    "addr:full":"De Spildoren 39 Schilde Antwerpen 2970",
    "addr:housenumber":"39",
    "addr:postcode":"2970",
    "iso:country":"BE",
    "sg:address":"De Spildoren 39",
    "sg:city":"Schilde",
    "sg:classifiers":[
        {
            "category":"Professional",
            "type":"Services"
        }
    ],
    "sg:phone":"+32 3 383 12 33",
    "sg:postcode":"2970",
    "sg:province":"Antwerpen",
    "sg:tags":[
        "aux",
        "diver",
        "personnes"
    ],
    "wof:name":"Gie Van Opstal",
    "wof:placetype":"venue"
},
  "geometry": {"coordinates":[4.5940771103,51.2409439087],"type":"Point"}
}