{
  "type": "Feature",
  "properties": {
    "iso:country":"BE",
    "sg:address":"Rue De Crotteux 84",
    "sg:city":"Gr\u00e2ce-hollogne (gr\u00e2ce-berleur)",
    "sg:classifiers":[
        {
            "category":"Health Services",
            "subcategory":"Health Practitioner",
            "type":"Services"
        }
    ],
    "sg:phone":"+32 4 234 29 71",
    "sg:postcode":"4460",
    "sg:province":"Li\u00e8ge",
    "sg:tags":[
        "physiotherapist"
    ],
    "wof:name":"Bertrand Fr\u00e9d\u00e9ric",
    "wof:placetype":"venue"
},
  "geometry": {"coordinates":[5.4493341446,50.6308326721],"type":"Point"}
}