{
  "type": "Feature",
  "properties": {
    "addr:full":"Hochstrasse 94 Eupen Li\u00e8ge 4700",
    "addr:housenumber":"94",
    "addr:postcode":"4700",
    "addr:street":"Hochstrasse",
    "iso:country":"BE",
    "sg:address":"Hochstrasse 94",
    "sg:city":"Eupen",
    "sg:classifiers":[
        {
            "category":"Health Services",
            "subcategory":"Health Practitioner",
            "type":"Services"
        }
    ],
    "sg:phone":"+32 87 56 00 88",
    "sg:postcode":"4700",
    "sg:province":"Li\u00e8ge",
    "sg:tags":[
        "alternative",
        "therapy",
        "treatment"
    ],
    "wof:name":"Belgischer Verband F\u00fcr Kinesiologie Goe",
    "wof:placetype":"venue"
},
  "geometry": {"coordinates":[6.0180950165,50.6369934082],"type":"Point"}
}