{
  "type": "Feature",
  "properties": {
    "addr:full":"Gooreind 1 Geel Antwerpen 2440",
    "addr:housenumber":"1",
    "addr:postcode":"2440",
    "addr:street":"Gooreind",
    "iso:country":"BE",
    "sg:address":"Gooreind 1",
    "sg:city":"Geel",
    "sg:classifiers":[
        {
            "category":"Fast Food",
            "type":"Food & Drink"
        }
    ],
    "sg:phone":"+32 14 58 10 78",
    "sg:postcode":"2440",
    "sg:province":"Antwerpen",
    "sg:tags":[
        "meeneem",
        "restaurant"
    ],
    "wof:name":"Frituur Chris",
    "wof:placetype":"venue"
},
  "geometry": {"coordinates":[4.9769291878,51.1731147766],"type":"Point"}
}