{
  "type": "Feature",
  "properties": {
    "addr:full":"Rue De La Vanne 37 Brussel/bruxelles Bruxelles-Capitale 1000",
    "addr:housenumber":"37",
    "addr:postcode":"1000",
    "addr:street":"Rue De La Vanne;/",
    "iso:country":"BE",
    "sg:address":"Rue De La Vanne 37",
    "sg:city":"Brussel/bruxelles",
    "sg:orig_category":"M\u00e9decins and sp\u00e9cialistes",
    "sg:phone":"+32 2 649 40 07",
    "sg:postcode":"1000",
    "sg:province":"Bruxelles-Capitale",
    "wof:name":"C\u00c9cile La Haye",
    "wof:placetype":"venue"
},
  "geometry": {"coordinates":[4.3651390076,50.8287315369],"type":"Point"}
}