{
  "type": "Feature",
  "properties": {
    "iso:country":"BE",
    "sg:address":"Bosstraat 91",
    "sg:city":"Maaseik",
    "sg:orig_category":"Cr\u00e9meries",
    "sg:phone":"+32 89 56 66 08",
    "sg:postcode":"3680",
    "sg:province":"Limburg",
    "wof:name":"Huis Kieesplank",
    "wof:placetype":"venue"
},
  "geometry": {"coordinates":[5.786960125,51.0957756042],"type":"Point"}
}