{
  "type": "Feature",
  "properties": {
    "addr:full":"Vaartstraat 1 Herentals Antwerpen 2200",
    "addr:housenumber":"1",
    "addr:postcode":"2200",
    "addr:street":"Vaartstraat",
    "iso:country":"BE",
    "sg:address":"Vaartstraat 1",
    "sg:city":"Herentals",
    "sg:classifiers":[
        {
            "category":"Personal",
            "subcategory":"Barber",
            "type":"Services"
        }
    ],
    "sg:phone":"+32 14 23 07 17",
    "sg:postcode":"2200",
    "sg:province":"Antwerpen",
    "sg:tags":[
        "gentleman",
        "salon",
        "-",
        "hairdressing"
    ],
    "wof:name":"Gianfranco Hairways Bvba",
    "wof:placetype":"venue"
},
  "geometry": {"coordinates":[4.8322601318,51.1797103882],"type":"Point"}
}