{
  "type": "Feature",
  "properties": {
    "addr:full":"Ren\u00c9 Declercqlaan 9 Harelbeke West-Vlaanderen 8530",
    "addr:housenumber":"9",
    "addr:postcode":"8530",
    "addr:street":"Rene\u0301 Declercqlaan",
    "iso:country":"BE",
    "sg:address":"Ren\u00c9 Declercqlaan 9",
    "sg:city":"Harelbeke",
    "sg:orig_category":"Artistes ind\u00e9pendants",
    "sg:phone":"+32 56 71 43 82",
    "sg:postcode":"8530",
    "sg:province":"West-Vlaanderen",
    "wof:name":"Deschuymere",
    "wof:placetype":"venue"
},
  "geometry": {"coordinates":[3.3024680614,50.848033905],"type":"Point"}
}