{
  "type": "Feature",
  "properties": {
    "iso:country":"BE",
    "sg:address":"Corneel Smitslei 98",
    "sg:city":"Borsbeek",
    "sg:orig_category":"Kinderopvang",
    "sg:phone":"+32 3 321 43 14",
    "sg:postcode":"2150",
    "sg:province":"Antwerpen",
    "wof:name":"Kwebbeltje Kinderopvang",
    "wof:placetype":"venue"
},
  "geometry": {"coordinates":[4.4834299088,51.1965751648],"type":"Point"}
}