{
  "type": "Feature",
  "properties": {
    "addr:full":"Sylvain Dupuislaan 387 Anderlecht/anderlecht Bruxelles-Capitale 1070",
    "addr:housenumber":"387",
    "addr:postcode":"1070",
    "addr:street":"Sylvain Dupuislaan",
    "iso:country":"BE",
    "sg:address":"Sylvain Dupuislaan 387",
    "sg:city":"Anderlecht/anderlecht",
    "sg:orig_category":"Postkantoren Verzekeringsmakelaars and experts",
    "sg:phone":"+32 2 524 33 45",
    "sg:postcode":"1070",
    "sg:province":"Bruxelles-Capitale",
    "wof:name":"De Post",
    "wof:placetype":"venue"
},
  "geometry": {"coordinates":[4.2868690491,50.837978363],"type":"Point"}
}