{
  "type": "Feature",
  "properties": {
    "iso:country":"BE",
    "sg:address":"Albert Lancasterlaan 95",
    "sg:city":"Ukkel/uccle",
    "sg:orig_category":"Artsen and specialisten",
    "sg:phone":"+32 2 375 08 55",
    "sg:postcode":"1180",
    "sg:province":"Bruxelles-Capitale",
    "wof:name":"D. Wathar",
    "wof:placetype":"venue"
},
  "geometry": {"coordinates":[4.366092205,50.7968139648],"type":"Point"}
}