{
  "type": "Feature",
  "properties": {
    "iso:country":"BE",
    "sg:address":"Goorstraat 61",
    "sg:city":"Retie",
    "sg:orig_category":"Eleveurs de bovins",
    "sg:phone":"+32 14 37 29 15",
    "sg:postcode":"2470",
    "sg:province":"Antwerpen",
    "wof:name":"Maria Gevers",
    "wof:placetype":"venue"
},
  "geometry": {"coordinates":[5.1168990135,51.2852210999],"type":"Point"}
}