{
  "type": "Feature",
  "properties": {
    "iso:country":"BE",
    "sg:address":"Grotestraat 407",
    "sg:city":"Maasmechelen",
    "sg:orig_category":"SMEEDWERK, METAALBEWERKING AND POEDERMETALLURGIE Sport- and kampeermateriaal",
    "sg:phone":"+32 89 77 25 43",
    "sg:postcode":"3631",
    "sg:province":"Limburg",
    "wof:name":"Penninger",
    "wof:placetype":"venue"
},
  "geometry": {"coordinates":[5.7239232063,50.9423713684],"type":"Point"}
}