{
  "type": "Feature",
  "properties": {
    "addr:full":"Schoolstraat 40 Oosterzele Oost-Vlaanderen 9860",
    "addr:housenumber":"40",
    "addr:postcode":"9860",
    "addr:street":"Schoolstraat;Oost-Vlaanderen",
    "iso:country":"BE",
    "sg:address":"Schoolstraat 40",
    "sg:city":"Oosterzele",
    "sg:classifiers":[
        {
            "category":"Arena",
            "subcategory":"Sports Club",
            "type":"Entertainment"
        }
    ],
    "sg:phone":"+32 9 362 75 98",
    "sg:postcode":"9860",
    "sg:province":"Oost-Vlaanderen",
    "sg:tags":[
        "terrain",
        "hors",
        "de",
        "installation",
        "sportifs"
    ],
    "wof:name":"Voorwaarts Gijzenzele",
    "wof:placetype":"venue"
},
  "geometry": {"coordinates":[3.816701889,50.970085144],"type":"Point"}
}