{
  "type": "Feature",
  "properties": {
    "iso:country":"BE",
    "sg:address":"Rue De La Gare 23",
    "sg:city":"Beauraing",
    "sg:classifiers":[
        {
            "category":"Shopping",
            "subcategory":"Books",
            "type":"Retail Goods"
        }
    ],
    "sg:phone":"+32 82 71 13 56",
    "sg:postcode":"5570",
    "sg:province":"Namur",
    "sg:tags":[
        "bookseller"
    ],
    "wof:name":"Gare (librairie De)",
    "wof:placetype":"venue"
},
  "geometry": {"coordinates":[4.9563989639,50.1144294739],"type":"Point"}
}