{
  "type": "Feature",
  "properties": {
    "addr:full":"Kiefhoekstraat 6ba2 Hechtel-eksel Limburg 3941",
    "addr:postcode":"3941",
    "addr:street":"Kiefhoekstraat 6Ba2",
    "iso:country":"BE",
    "sg:address":"Kiefhoekstraat 6ba2",
    "sg:city":"Hechtel-eksel",
    "sg:orig_category":"Metaalbehandeling and -bekleding",
    "sg:phone":"+32 11 73 00 33",
    "sg:postcode":"3941",
    "sg:province":"Limburg",
    "wof:name":"D.f.e.",
    "wof:placetype":"venue"
},
  "geometry": {"coordinates":[5.3326120377,51.1607246399],"type":"Point"}
}