{
  "type": "Feature",
  "properties": {
    "addr:full":"Rue Ernest Solvay 19 Les Bons Villers (mellet) Hainaut 6211",
    "addr:housenumber":"19",
    "addr:postcode":"6211",
    "addr:street":"Rue Ernest Solvay",
    "iso:country":"BE",
    "sg:address":"Rue Ernest Solvay 19",
    "sg:city":"Les Bons Villers (mellet)",
    "sg:classifiers":[
        {
            "category":"Freight",
            "type":"Transportation"
        }
    ],
    "sg:phone":"+32 71 85 14 03",
    "sg:postcode":"6211",
    "sg:province":"Hainaut",
    "sg:tags":[
        "-",
        "transport"
    ],
    "wof:name":"Phil-transports",
    "wof:placetype":"venue"
},
  "geometry": {"coordinates":[4.4791898727,50.5055961609],"type":"Point"}
}