{
  "type": "Feature",
  "properties": {
    "iso:country":"BE",
    "sg:address":"Rijksweg 403",
    "sg:city":"Dilsen-stokkem",
    "sg:orig_category":"HERSTELLING ELEKTRISCHE HUISHOUDAPPARATEN Herstelling aan huis van elektrische huishoudapparaten Hui",
    "sg:phone":"+32 89 75 51 88",
    "sg:postcode":"3650",
    "sg:province":"Limburg",
    "wof:name":"Rogier Van Der Velden",
    "wof:placetype":"venue"
},
  "geometry": {"coordinates":[5.7279539108,51.0316810608],"type":"Point"}
}