{
  "type": "Feature",
  "properties": {
    "iso:country":"BE",
    "sg:address":"Mont Le Soie 1",
    "sg:city":"Vielsalm (grand-halleux)",
    "sg:classifiers":[
        {
            "category":"Organizations",
            "subcategory":"Professional Association",
            "type":"Services"
        }
    ],
    "sg:phone":"+32 80 21 65 56",
    "sg:postcode":"6698",
    "sg:province":"Luxembourg",
    "sg:tags":[
        "trade-union",
        "federation"
    ],
    "wof:name":"Centre Europeen Du Cheval De Mont-le-soie Asbl",
    "wof:placetype":"venue"
},
  "geometry": {"coordinates":[5.908053875,50.3257751465],"type":"Point"}
}