{
  "type": "Feature",
  "properties": {
    "iso:country":"BE",
    "sg:address":"Val Du Fierain 42",
    "sg:city":"Pepinster",
    "sg:classifiers":[
        {
            "category":"Cafe",
            "type":"Food & Drink"
        }
    ],
    "sg:phone":"+32 87 46 94 03",
    "sg:postcode":"4860",
    "sg:province":"Li\u00e8ge",
    "sg:tags":[
        "caf\u00e9s"
    ],
    "wof:name":"Caf\u00c9 Aux Routiers",
    "wof:placetype":"venue"
},
  "geometry": {"coordinates":[5.8160238266,50.5856933594],"type":"Point"}
}