{
  "type": "Feature",
  "properties": {
    "addr:full":"Chauss\u00e9e Brunehault 27 Leuze-en-hainaut (blicquy) Hainaut 7903",
    "addr:housenumber":"27;7903",
    "addr:street":"Chausse\u0301E Brunehault;Blicquy Hainaut",
    "iso:country":"BE",
    "sg:address":"Chauss\u00e9e Brunehault 27",
    "sg:city":"Leuze-en-hainaut (blicquy)",
    "sg:classifiers":[
        {
            "category":"Building & Trades",
            "subcategory":"Construction",
            "type":"Services"
        }
    ],
    "sg:phone":"+32 69 66 58 10",
    "sg:postcode":"7903",
    "sg:province":"Hainaut",
    "sg:tags":[
        "stucco",
        "contractor"
    ],
    "wof:name":"Ducastel Serge & Fils",
    "wof:placetype":"venue"
},
  "geometry": {"coordinates":[3.6920371056,50.5879631042],"type":"Point"}
}