{
  "type": "Feature",
  "properties": {
    "iso:country":"BE",
    "sg:address":"Franklin Rooseveltplaats 12",
    "sg:city":"Antwerpen",
    "sg:classifiers":[
        {
            "category":"Banks & Credit Unions",
            "subcategory":"Investment Brokerage",
            "type":"Services"
        }
    ],
    "sg:phone":"+32 3 287 64 50",
    "sg:postcode":"2060",
    "sg:province":"Antwerpen",
    "sg:tags":[
        "development",
        "application",
        "software"
    ],
    "wof:name":"Sail Labs B.v.b.a.",
    "wof:placetype":"venue"
},
  "geometry": {"coordinates":[4.4162101746,51.1994094849],"type":"Point"}
}