{
  "type": "Feature",
  "properties": {
    "addr:full":"Avenue Reine Elisabeth 59 Wemmel Vlaams-Brabant 1780",
    "addr:housenumber":"59",
    "addr:postcode":"1780",
    "addr:street":"Avenue Reine Elisabeth;Vlaams-Brabant",
    "iso:country":"BE",
    "sg:address":"Avenue Reine Elisabeth 59",
    "sg:city":"Wemmel",
    "sg:classifiers":[
        {
            "category":"Building & Trades",
            "subcategory":"Construction",
            "type":"Services"
        }
    ],
    "sg:phone":"+32 2 460 10 01",
    "sg:postcode":"1780",
    "sg:province":"Vlaams-Brabant",
    "sg:tags":[
        "builder",
        "chimney"
    ],
    "wof:name":"Mg Entreprises",
    "wof:placetype":"venue"
},
  "geometry": {"coordinates":[4.3258748055,50.9007492065],"type":"Point"}
}