{
  "type": "Feature",
  "properties": {
    "iso:country":"BE",
    "sg:address":"Pelgrim 38",
    "sg:city":"Oosterzele (scheldewindeke)",
    "sg:classifiers":[
        {
            "category":"Health Services",
            "subcategory":"Doctor",
            "type":"Services"
        }
    ],
    "sg:phone":"+32 9 362 99 39",
    "sg:postcode":"9860",
    "sg:province":"Oost-Vlaanderen",
    "sg:tags":[
        "medicinephysicians",
        "surgeon"
    ],
    "wof:name":"De Keyser Moniek",
    "wof:placetype":"venue"
},
  "geometry": {"coordinates":[3.787225008,50.9390106201],"type":"Point"}
}