{
  "type": "Feature",
  "properties": {
    "iso:country":"BE",
    "sg:address":"Place Du Marais 78",
    "sg:city":"Theux",
    "sg:orig_category":"V\u00e9hicules automobiles. Stations-service and carburants",
    "sg:phone":"+32 87 37 66 60",
    "sg:postcode":"4910",
    "sg:province":"Li\u00e8ge",
    "wof:name":"Garage Costa",
    "wof:placetype":"venue"
},
  "geometry": {"coordinates":[5.7895798683,50.4882888794],"type":"Point"}
}