{
  "type": "Feature",
  "properties": {
    "addr:full":"Klaverbladstraat 7 Lummen Limburg 3560",
    "addr:housenumber":"7",
    "addr:postcode":"3560",
    "addr:street":"Klaverbladstraat",
    "iso:country":"BE",
    "sg:address":"Klaverbladstraat 7",
    "sg:city":"Lummen",
    "sg:classifiers":[
        {
            "category":"Organizations",
            "subcategory":"Professional Association",
            "type":"Services"
        }
    ],
    "sg:phone":"+32 13 52 16 16",
    "sg:postcode":"3560",
    "sg:province":"Limburg",
    "sg:tags":[
        "organisation",
        "seminar"
    ],
    "wof:name":"Intermotel *** Nv",
    "wof:placetype":"venue"
},
  "geometry": {"coordinates":[5.2274580002,50.9971885681],"type":"Point"}
}