{
  "type": "Feature",
  "properties": {
    "addr:full":"Dorp 103 Assenede Oost-Vlaanderen 9968",
    "addr:housenumber":"103",
    "addr:postcode":"9968",
    "addr:street":"Dorp",
    "iso:country":"BE",
    "sg:address":"Dorp 103",
    "sg:city":"Assenede",
    "sg:orig_category":"Banques and organismes de cr\u00e9dit",
    "sg:phone":"+32 9 373 71 55",
    "sg:postcode":"9968",
    "sg:province":"Oost-Vlaanderen",
    "wof:name":"Dexia",
    "wof:placetype":"venue"
},
  "geometry": {"coordinates":[3.6887938976,51.1923027039],"type":"Point"}
}