{
  "type": "Feature",
  "properties": {
    "iso:country":"BE",
    "sg:address":"Dageraadplaats 26",
    "sg:city":"Antwerpen",
    "sg:classifiers":[
        {
            "category":"Restaurant",
            "type":"Food & Drink"
        }
    ],
    "sg:phone":"+32 3 272 15 41",
    "sg:postcode":"2018",
    "sg:province":"Antwerpen",
    "wof:name":"Amon",
    "wof:placetype":"venue"
},
  "geometry": {"coordinates":[4.4294800758,51.2072143555],"type":"Point"}
}