{
  "type": "Feature",
  "properties": {
    "addr:full":"Rue De La Ture 4b1 Tournai Hainaut 7500",
    "addr:housenumber":"4b1",
    "addr:postcode":"7500",
    "addr:street":"Rue De La Ture",
    "iso:country":"BE",
    "sg:address":"Rue De La Ture 4b1",
    "sg:city":"Tournai",
    "sg:orig_category":"Architecten",
    "sg:phone":"+32 476 34 80 19",
    "sg:postcode":"7500",
    "sg:province":"Hainaut",
    "wof:name":"Nicolas Lorent",
    "wof:placetype":"venue"
},
  "geometry": {"coordinates":[3.3901000023,50.6044006348],"type":"Point"}
}