{
  "type": "Feature",
  "properties": {
    "addr:full":"Markt 62 Lokeren (groot) Oost-Vlaanderen 9160",
    "addr:housenumber":"62",
    "addr:postcode":"9160",
    "addr:street":"Markt;Lokeren Groot Oost-Vlaanderen",
    "iso:country":"BE",
    "sg:address":"Markt 62",
    "sg:city":"Lokeren (groot)",
    "sg:orig_category":"Industri\u00eble wasserijen and droogkuis",
    "sg:phone":"+32 9 348 17 91",
    "sg:postcode":"9160",
    "sg:province":"Oost-Vlaanderen",
    "wof:name":"Sneeuwwitje",
    "wof:placetype":"venue"
},
  "geometry": {"coordinates":[3.990801096,51.1037940979],"type":"Point"}
}