{
  "type": "Feature",
  "properties": {
    "iso:country":"BE",
    "sg:address":"Lusstraat 9",
    "sg:city":"Erpe-mere (burst)",
    "sg:classifiers":[
        {
            "category":"Personal",
            "subcategory":"Beauty Salon",
            "type":"Services"
        }
    ],
    "sg:phone":"+32 53 63 16 12",
    "sg:postcode":"9420",
    "sg:province":"Oost-Vlaanderen",
    "wof:name":"Bovijn A",
    "wof:placetype":"venue"
},
  "geometry": {"coordinates":[3.9234390259,50.9047737122],"type":"Point"}
}