{
  "type": "Feature",
  "properties": {
    "iso:country":"BE",
    "sg:address":"Berlaarbaan 244",
    "sg:city":"Sint-katelijne-waver",
    "sg:orig_category":"Sportclubs",
    "sg:phone":"+32 15 31 75 11",
    "sg:postcode":"2861",
    "sg:province":"Antwerpen",
    "wof:name":"Wandelclub De Kadodders",
    "wof:placetype":"venue"
},
  "geometry": {"coordinates":[4.5487117767,51.0546531677],"type":"Point"}
}