{
  "type": "Feature",
  "properties": {
    "iso:country":"BE",
    "sg:address":"August Van Putlei 56",
    "sg:city":"Borsbeek",
    "sg:orig_category":"Enseignement maternel and primaire",
    "sg:phone":"+32 3 322 67 72",
    "sg:postcode":"2150",
    "sg:province":"Antwerpen",
    "wof:name":"Vrije Kleuterschool",
    "wof:placetype":"venue"
},
  "geometry": {"coordinates":[4.4766287804,51.1965751648],"type":"Point"}
}