{
  "type": "Feature",
  "properties": {
    "addr:full":"Vestingstraat 59-63 B1 Antwerpen Antwerpen 2018",
    "addr:housenumber":"59-63 b1",
    "addr:postcode":"2018",
    "addr:street":"Vestingstraat",
    "iso:country":"BE",
    "sg:address":"Vestingstraat 59-63 B1",
    "sg:city":"Antwerpen",
    "sg:orig_category":"Pearl Jewellery",
    "sg:phone":"+32 3 233 93 99",
    "sg:postcode":"2018",
    "sg:province":"Antwerpen",
    "wof:name":"Continental Pearls Corporation B.v.b.a.",
    "wof:placetype":"venue"
},
  "geometry": {"coordinates":[4.3372468948,51.3139419556],"type":"Point"}
}