{
  "type": "Feature",
  "properties": {
    "addr:full":"Brugsesteenweg 492 Gent (mariakerke) Oost-Vlaanderen 9030",
    "addr:housenumber":"492",
    "addr:postcode":"9030",
    "addr:street":"Brugsesteenweg",
    "iso:country":"BE",
    "sg:address":"Brugsesteenweg 492",
    "sg:city":"Gent (mariakerke)",
    "sg:classifiers":[
        {
            "category":"Communications",
            "subcategory":"Film & Video Production",
            "type":"Services"
        }
    ],
    "sg:phone":"+32 9 227 37 29",
    "sg:postcode":"9030",
    "sg:province":"Oost-Vlaanderen",
    "sg:tags":[
        "hiring",
        "-"
    ],
    "wof:name":"Videotheek Inge",
    "wof:placetype":"venue"
},
  "geometry": {"coordinates":[3.6817250252,51.0708465576],"type":"Point"}
}