{
  "type": "Feature",
  "properties": {
    "addr:full":"Antwerpsesteenweg 199 Malle Antwerpen 2390",
    "addr:housenumber":"199",
    "addr:postcode":"2390",
    "addr:street":"Antwerpsesteenweg",
    "iso:country":"BE",
    "sg:address":"Antwerpsesteenweg 199",
    "sg:city":"Malle",
    "sg:orig_category":"Paramedische behandelingen",
    "sg:phone":"+32 3 309 21 53",
    "sg:postcode":"2390",
    "sg:province":"Antwerpen",
    "wof:name":"S. Verheyen",
    "wof:placetype":"venue"
},
  "geometry": {"coordinates":[4.6973280907,51.2969322205],"type":"Point"}
}