{
  "type": "Feature",
  "properties": {
    "addr:full":"Turnhoutsebaan 75a Retie Antwerpen 2470",
    "addr:housenumber":"75a",
    "addr:postcode":"2470",
    "addr:street":"Turnhoutsebaan",
    "iso:country":"BE",
    "sg:address":"Turnhoutsebaan 75a",
    "sg:city":"Retie",
    "sg:classifiers":[
        {
            "category":"Autos & Motor Vehicles",
            "subcategory":"Recreational Vehicle Sales",
            "type":"Retail Goods"
        }
    ],
    "sg:phone":"+32 14 37 20 32",
    "sg:postcode":"2470",
    "sg:province":"Antwerpen",
    "sg:tags":[
        "automobile",
        "-",
        "tuning"
    ],
    "wof:name":"Bandencenter Van Gorp",
    "wof:placetype":"venue"
},
  "geometry": {"coordinates":[5.0740761757,51.2727851868],"type":"Point"}
}