{
  "type": "Feature",
  "properties": {
    "addr:full":"Rozenberg 162b1 Mol Antwerpen 2400",
    "addr:housenumber":"162b1",
    "addr:postcode":"2400",
    "addr:street":"Rozenberg",
    "iso:country":"BE",
    "sg:address":"Rozenberg 162b1",
    "sg:city":"Mol",
    "sg:classifiers":[
        {
            "category":"Restaurant",
            "type":"Food & Drink"
        }
    ],
    "sg:phone":"+32 14 32 29 66",
    "sg:postcode":"2400",
    "sg:province":"Antwerpen",
    "wof:name":"\u00b4t Stepke",
    "wof:placetype":"venue"
},
  "geometry": {"coordinates":[5.1209959984,51.1885528564],"type":"Point"}
}