{
  "type": "Feature",
  "properties": {
    "addr:full":"Rue Arthur Roelandt 21 Moeskroen/mouscron Hainaut 7711",
    "addr:housenumber":"21",
    "addr:postcode":"7711",
    "addr:street":"Rue Arthur Roelandt",
    "iso:country":"BE",
    "sg:address":"Rue Arthur Roelandt 21",
    "sg:city":"Moeskroen/mouscron",
    "sg:orig_category":"Maroquinerie and articles de voyage. Chaussures",
    "sg:phone":"+32 56 48 91 31",
    "sg:postcode":"7711",
    "sg:province":"Hainaut",
    "wof:name":"Chantal Duhamel",
    "wof:placetype":"venue"
},
  "geometry": {"coordinates":[3.3037159443,50.7275810242],"type":"Point"}
}