{
  "type": "Feature",
  "properties": {
    "addr:full":"Grote Markt 48 Tienen Vlaams-Brabant 3300",
    "addr:housenumber":"48",
    "addr:postcode":"3300",
    "addr:street":"Grote Markt",
    "iso:country":"BE",
    "sg:address":"Grote Markt 48",
    "sg:city":"Tienen",
    "sg:classifiers":[
        {
            "category":"Banks & Credit Unions",
            "subcategory":"Bank",
            "type":"Services"
        }
    ],
    "sg:phone":"+32 16 81 22 12",
    "sg:postcode":"3300",
    "sg:province":"Vlaams-Brabant",
    "wof:name":"Gemeentekrediet",
    "wof:placetype":"venue"
},
  "geometry": {"coordinates":[4.935959816,50.8077812195],"type":"Point"}
}