{
  "type": "Feature",
  "properties": {
    "addr:full":"Zwaantje 37 Kester Vlaams-Brabant 1755",
    "addr:housenumber":"37",
    "addr:postcode":"1755",
    "addr:street":"Zwaantje",
    "iso:country":"BE",
    "sg:address":"Zwaantje 37",
    "sg:city":"Kester",
    "sg:orig_category":"Rotational Drives",
    "sg:phone":"+32 2 356 77 86",
    "sg:postcode":"1755",
    "sg:province":"Vlaams-Brabant",
    "wof:name":"Vanden Daele B.v.b.a.",
    "wof:placetype":"venue"
},
  "geometry": {"coordinates":[4.1395659447,50.7570648193],"type":"Point"}
}