{
  "type": "Feature",
  "properties": {
    "iso:country":"BE",
    "sg:address":"Smisstraat 43",
    "sg:city":"Halle",
    "sg:classifiers":[
        {
            "category":"Professional",
            "subcategory":"Management & Consulting",
            "type":"Services"
        }
    ],
    "sg:phone":"+32 2 360 09 56",
    "sg:postcode":"1500",
    "sg:province":"Vlaams-Brabant",
    "sg:tags":[
        "consultant"
    ],
    "wof:name":"Assutech Bvba",
    "wof:placetype":"venue"
},
  "geometry": {"coordinates":[4.1963858604,50.7601890564],"type":"Point"}
}