{
  "type": "Feature",
  "properties": {
    "iso:country":"BE",
    "sg:address":"Van Goethemstraat 102",
    "sg:city":"Merelbeke",
    "sg:classifiers":[
        {
            "category":"Professional",
            "subcategory":"Computer Services",
            "type":"Services"
        }
    ],
    "sg:phone":"+32 9 230 95 04",
    "sg:postcode":"9820",
    "sg:province":"Oost-Vlaanderen",
    "sg:tags":[
        "-",
        "processing",
        "data",
        "software"
    ],
    "wof:name":"Dvinnings",
    "wof:placetype":"venue"
},
  "geometry": {"coordinates":[3.7561619282,51.0189170837],"type":"Point"}
}