{
  "type": "Feature",
  "properties": {
    "iso:country":"BE",
    "sg:address":"Rue Des Fleuristes 27",
    "sg:city":"Sint-agatha-berchem/berchem-sainte-agathe",
    "sg:orig_category":"M\u00e9decins and sp\u00e9cialistes",
    "sg:phone":"+32 475 55 82 11",
    "sg:postcode":"1082",
    "sg:province":"Bruxelles-Capitale",
    "wof:name":"Sophie De Roock",
    "wof:placetype":"venue"
},
  "geometry": {"coordinates":[4.2931909561,50.8665351868],"type":"Point"}
}