{
  "type": "Feature",
  "properties": {
    "addr:full":"Roeselarestraat 63 Staden West-Vlaanderen 8840",
    "addr:housenumber":"63",
    "addr:postcode":"8840",
    "addr:street":"Roeselarestraat",
    "iso:country":"BE",
    "sg:address":"Roeselarestraat 63",
    "sg:city":"Staden",
    "sg:orig_category":"Opticiens",
    "sg:phone":"+32 51 22 96 99",
    "sg:postcode":"8840",
    "sg:province":"West-Vlaanderen",
    "wof:name":"Saskia Bruneel",
    "wof:placetype":"venue"
},
  "geometry": {"coordinates":[3.0643379688,50.9420318604],"type":"Point"}
}