{
  "type": "Feature",
  "properties": {
    "addr:full":"Rue De Payot 20a Lasne (lasne-chapelle-saint-lambert) Brabant Wallon 1380",
    "addr:housenumber":"20a",
    "addr:postcode":"1380",
    "addr:street":"Rue De Payot;Wallon",
    "iso:country":"BE",
    "sg:address":"Rue De Payot 20a",
    "sg:city":"Lasne (lasne-chapelle-saint-lambert)",
    "sg:classifiers":[
        {
            "category":"Shopping",
            "subcategory":"Party Supplies",
            "type":"Retail Goods"
        }
    ],
    "sg:phone":"+32 2 633 68 39",
    "sg:postcode":"1380",
    "sg:province":"Brabant Wallon",
    "sg:tags":[
        "easter",
        "christmas"
    ],
    "wof:name":"Etalage Campens",
    "wof:placetype":"venue"
},
  "geometry": {"coordinates":[4.4597578049,50.6723747253],"type":"Point"}
}