{
  "type": "Feature",
  "properties": {
    "iso:country":"BE",
    "sg:address":"Alsembergse Steenweg 111",
    "sg:city":"Sint-gillis/saint-gilles",
    "sg:orig_category":"Persagentschappen",
    "sg:phone":"+32 2 538 57 27",
    "sg:postcode":"1060",
    "sg:province":"Bruxelles-Capitale",
    "wof:name":"Laure De Hesselle",
    "wof:placetype":"venue"
},
  "geometry": {"coordinates":[4.3427629471,50.8232650757],"type":"Point"}
}