{
  "type": "Feature",
  "properties": {
    "addr:full":"Rue Marcel Vandy 23 Namur Namur 5020",
    "addr:housenumber":"23",
    "addr:postcode":"5020",
    "addr:street":"Rue Marcel Vandy",
    "iso:country":"BE",
    "sg:address":"Rue Marcel Vandy 23",
    "sg:city":"Namur",
    "sg:orig_category":"Apotheken",
    "sg:phone":"+32 81 73 99 48",
    "sg:postcode":"5020",
    "sg:province":"Namur",
    "wof:name":"Jean-marc Sabaux",
    "wof:placetype":"venue"
},
  "geometry": {"coordinates":[4.7952418327,50.4352035522],"type":"Point"}
}