{
  "type": "Feature",
  "properties": {
    "addr:full":"Diestsesteenweg 9 Tienen Vlaams-Brabant 3300",
    "addr:housenumber":"9",
    "addr:postcode":"3300",
    "addr:street":"Diestsesteenweg",
    "iso:country":"BE",
    "sg:address":"Diestsesteenweg 9",
    "sg:city":"Tienen",
    "sg:orig_category":"Apotheken",
    "sg:phone":"+32 16 81 13 35",
    "sg:postcode":"3300",
    "sg:province":"Vlaams-Brabant",
    "wof:name":"Julius Grammet",
    "wof:placetype":"venue"
},
  "geometry": {"coordinates":[4.9351801872,50.8136978149],"type":"Point"}
}