{
  "type": "Feature",
  "properties": {
    "addr:full":"Ooigemstraat 12 Meulebeke West-Vlaanderen 8760",
    "addr:housenumber":"12",
    "addr:postcode":"8760",
    "addr:street":"Ooigemstraat",
    "iso:country":"BE",
    "sg:address":"Ooigemstraat 12",
    "sg:city":"Meulebeke",
    "sg:orig_category":"Avocats and conseillers juridiques",
    "sg:phone":"+32 51 48 92 21",
    "sg:postcode":"8760",
    "sg:province":"West-Vlaanderen",
    "wof:name":"H. Dedeurwaerdere",
    "wof:placetype":"venue"
},
  "geometry": {"coordinates":[3.2985498905,50.9329414368],"type":"Point"}
}