{
  "type": "Feature",
  "properties": {
    "addr:full":"Place Communale 6 Ham-sur-heure-nalinnes Hainaut 6120",
    "addr:housenumber":"6",
    "addr:postcode":"6120",
    "addr:street":"Place Communale;Hainaut",
    "iso:country":"BE",
    "sg:address":"Place Communale 6",
    "sg:city":"Ham-sur-heure-nalinnes",
    "sg:classifiers":[
        {
            "category":"Restaurant",
            "type":"Food & Drink"
        }
    ],
    "sg:phone":"+32 71 21 68 94",
    "sg:postcode":"6120",
    "sg:province":"Hainaut",
    "wof:name":"Le Lothy",
    "wof:placetype":"venue"
},
  "geometry": {"coordinates":[4.4122409821,50.3522796631],"type":"Point"}
}