{
  "type": "Feature",
  "properties": {
    "iso:country":"BE",
    "sg:address":"Kosterstraat 65",
    "sg:city":"Lille (gierle)",
    "sg:classifiers":[
        {
            "category":"Home & Garden",
            "subcategory":"Carpets & Floor Coverings",
            "type":"Retail Goods"
        }
    ],
    "sg:phone":"+32 14 55 29 38",
    "sg:postcode":"2275",
    "sg:province":"Antwerpen",
    "sg:tags":[
        "parquet"
    ],
    "wof:name":"Janssens A",
    "wof:placetype":"venue"
},
  "geometry": {"coordinates":[4.8750801086,51.2700843811],"type":"Point"}
}