{
  "type": "Feature",
  "properties": {
    "iso:country":"BE",
    "sg:address":"Rue Brialmont 13",
    "sg:city":"Seraing",
    "sg:classifiers":[
        {
            "category":"Cafe",
            "type":"Food & Drink"
        }
    ],
    "sg:phone":"+32 4 336 66 16",
    "sg:postcode":"4100",
    "sg:province":"Li\u00e8ge",
    "sg:tags":[
        "caf\u00e9s"
    ],
    "wof:name":"S.i.s.",
    "wof:placetype":"venue"
},
  "geometry": {"coordinates":[5.5092658997,50.6149291992],"type":"Point"}
}