{
  "type": "Feature",
  "properties": {
    "addr:full":"Kattestraat 25a Sint-amands (oppuurs) Antwerpen 2890",
    "addr:housenumber":"25a",
    "addr:postcode":"2890",
    "addr:street":"Kattestraat",
    "iso:country":"BE",
    "sg:address":"Kattestraat 25a",
    "sg:city":"Sint-amands (oppuurs)",
    "sg:classifiers":[
        {
            "category":"Health Services",
            "subcategory":"Dentist",
            "type":"Services"
        }
    ],
    "sg:phone":"+32 486 67 70 58",
    "sg:postcode":"2890",
    "sg:province":"Antwerpen",
    "wof:name":"Feys Frederik",
    "wof:placetype":"venue"
},
  "geometry": {"coordinates":[4.2454209328,51.0694999695],"type":"Point"}
}