{
  "type": "Feature",
  "properties": {
    "iso:country":"BE",
    "sg:address":"Quai De La Goffe 39",
    "sg:city":"Li\u00c8ge",
    "sg:classifiers":[
        {
            "category":"Cafe",
            "type":"Food & Drink"
        }
    ],
    "sg:phone":"+32 4 223 11 84",
    "sg:postcode":"4000",
    "sg:province":"Li\u00e8ge",
    "sg:tags":[
        "caf\u00e9s"
    ],
    "wof:name":"Caf\u00c9 La Cit\u00c9",
    "wof:placetype":"venue"
},
  "geometry": {"coordinates":[5.5790328979,50.6449508667],"type":"Point"}
}