{
  "type": "Feature",
  "properties": {
    "iso:country":"BE",
    "sg:address":"Gistelse Steenweg 190",
    "sg:city":"Brugge (sint-andries)",
    "sg:classifiers":[
        {
            "category":"Communications",
            "subcategory":"Film & Video Production",
            "type":"Services"
        }
    ],
    "sg:phone":"+32 50 38 63 66",
    "sg:postcode":"8200",
    "sg:province":"West-Vlaanderen",
    "sg:tags":[
        "producer",
        "realizators"
    ],
    "wof:name":"Studio Bal Gehakt Bvba",
    "wof:placetype":"venue"
},
  "geometry": {"coordinates":[3.1991159916,51.2012023926],"type":"Point"}
}