{
  "type": "Feature",
  "properties": {
    "addr:full":"Kortrijksepoortstraat 178 Gent Oost-Vlaanderen 9000",
    "addr:housenumber":"178",
    "addr:postcode":"9000",
    "addr:street":"Kortrijksepoortstraat;Oost-Vlaanderen",
    "iso:country":"BE",
    "sg:address":"Kortrijksepoortstraat 178",
    "sg:city":"Gent",
    "sg:classifiers":[
        {
            "category":"Bars & Pubs",
            "type":"Food & Drink"
        }
    ],
    "sg:phone":"+32 9 330 63 82",
    "sg:postcode":"9000",
    "sg:province":"Oost-Vlaanderen",
    "wof:name":"Condor",
    "wof:placetype":"venue"
},
  "geometry": {"coordinates":[3.7218370438,51.0447654724],"type":"Point"}
}