{
  "type": "Feature",
  "properties": {
    "addr:full":"Koningstraat 16 Wevelgem West-Vlaanderen 8560",
    "addr:housenumber":"16",
    "addr:postcode":"8560",
    "addr:street":"Koningstraat",
    "iso:country":"BE",
    "sg:address":"Koningstraat 16",
    "sg:city":"Wevelgem",
    "sg:orig_category":"Eleveurs de bovins. Eleveurs and marchands de porcs",
    "sg:phone":"+32 56 41 40 67",
    "sg:postcode":"8560",
    "sg:province":"West-Vlaanderen",
    "wof:name":"Ghislain Vandenberghe",
    "wof:placetype":"venue"
},
  "geometry": {"coordinates":[3.1589710712,50.8087921143],"type":"Point"}
}