{
  "type": "Feature",
  "properties": {
    "iso:country":"BE",
    "sg:address":"Place Saint-paul 7b",
    "sg:city":"Li\u00e8ge 1",
    "sg:classifiers":[
        {
            "category":"Health Services",
            "subcategory":"Health Practitioner",
            "type":"Services"
        }
    ],
    "sg:phone":"+32 4 223 37 23",
    "sg:postcode":"4000",
    "sg:province":"Li\u00e8ge",
    "sg:tags":[
        "osteopath"
    ],
    "wof:name":"Geelkens G",
    "wof:placetype":"venue"
},
  "geometry": {"coordinates":[5.5709261894,50.6393661499],"type":"Point"}
}