{
  "type": "Feature",
  "properties": {
    "addr:full":"Prins Albertlaan 109 Izegem West-Vlaanderen 8870",
    "addr:housenumber":"109",
    "addr:postcode":"8870",
    "addr:street":"Prins Albertlaan",
    "iso:country":"BE",
    "sg:address":"Prins Albertlaan 109",
    "sg:city":"Izegem",
    "sg:orig_category":"Installatie van houten of kunststof schrijnwerk Installatie van metalen schrijnwerk MEUBELONTWERP AN",
    "sg:phone":"+32 51 31 51 36",
    "sg:postcode":"8870",
    "sg:province":"West-Vlaanderen",
    "wof:name":"Lieven Vandemoortele",
    "wof:placetype":"venue"
},
  "geometry": {"coordinates":[3.1853458881,50.9282455444],"type":"Point"}
}