{
  "type": "Feature",
  "properties": {
    "iso:country":"BE",
    "sg:address":"Waterloose Steenweg 801",
    "sg:city":"Ukkel/uccle",
    "sg:orig_category":"Kapsalons",
    "sg:phone":"+32 2 343 37 47",
    "sg:postcode":"1180",
    "sg:province":"Bruxelles-Capitale",
    "wof:name":"Philippe",
    "wof:placetype":"venue"
},
  "geometry": {"coordinates":[4.3685331345,50.8112373352],"type":"Point"}
}