{
  "type": "Feature",
  "properties": {
    "iso:country":"BE",
    "sg:address":"Pastoriestraat 50",
    "sg:city":"Haacht",
    "sg:orig_category":"Catering and organisatie van feesten Ruimtes voor conferenties, recepties and feesten",
    "sg:phone":"+32 16 44 36 40",
    "sg:postcode":"3150",
    "sg:province":"Vlaams-Brabant",
    "wof:name":"Feesstzaal Tiendenschuur",
    "wof:placetype":"venue"
},
  "geometry": {"coordinates":[4.6789169312,50.9557418823],"type":"Point"}
}