{
  "type": "Feature",
  "properties": {
    "addr:full":"Spitaalpoortstraat 30 Gent Oost-Vlaanderen 9000",
    "addr:housenumber":"30",
    "addr:postcode":"9000",
    "addr:street":"Spitaalpoortstraat;Oost-Vlaanderen",
    "iso:country":"BE",
    "sg:address":"Spitaalpoortstraat 30",
    "sg:city":"Gent",
    "sg:classifiers":[
        {
            "category":"Building & Trades",
            "subcategory":"Cleaning & Sanitation",
            "type":"Services"
        }
    ],
    "sg:phone":"+32 486 10 21 74",
    "sg:postcode":"9000",
    "sg:province":"Oost-Vlaanderen",
    "sg:tags":[
        "janitor"
    ],
    "wof:name":"A Action Cleaning",
    "wof:placetype":"venue"
},
  "geometry": {"coordinates":[3.7436289787,51.0586433411],"type":"Point"}
}