{
  "type": "Feature",
  "properties": {
    "iso:country":"BE",
    "sg:address":"'t Vlietje 17",
    "sg:city":"Mechelen",
    "sg:classifiers":[
        {
            "category":"Government",
            "subcategory":"Fire Station",
            "type":"Public Place"
        }
    ],
    "sg:phone":"+32 15 20 18 79",
    "sg:postcode":"2800",
    "sg:province":"Antwerpen",
    "sg:tags":[
        "water",
        "restoration",
        "damage"
    ],
    "wof:name":"Crabeels A & Zoon Nv",
    "wof:placetype":"venue"
},
  "geometry": {"coordinates":[4.4847998619,51.0273017883],"type":"Point"}
}