{
  "type": "Feature",
  "properties": {
    "addr:full":"Bredestraat 22 Lede Oost-Vlaanderen 9340",
    "addr:housenumber":"22",
    "addr:postcode":"9340",
    "addr:street":"Bredestraat",
    "iso:country":"BE",
    "sg:address":"Bredestraat 22",
    "sg:city":"Lede",
    "sg:orig_category":"Kapsalons",
    "sg:phone":"+32 53 80 32 79",
    "sg:postcode":"9340",
    "sg:province":"Oost-Vlaanderen",
    "wof:name":"Leonard Verdonck",
    "wof:placetype":"venue"
},
  "geometry": {"coordinates":[3.9543600082,50.9754600525],"type":"Point"}
}