{
  "type": "Feature",
  "properties": {
    "addr:full":"Rue Van Oost 34 Bruxelles (schaerbeek) Bruxelles-Capitale 1030",
    "addr:housenumber":"34",
    "addr:postcode":"1030",
    "addr:street":"Rue Van Oost",
    "iso:country":"BE",
    "sg:address":"Rue Van Oost 34",
    "sg:city":"Bruxelles (schaerbeek)",
    "sg:classifiers":[
        {
            "category":"Professional",
            "subcategory":"Computer Services",
            "type":"Services"
        }
    ],
    "sg:phone":"+32 2 240 02 61",
    "sg:postcode":"1030",
    "sg:province":"Bruxelles-Capitale",
    "sg:tags":[
        "network"
    ],
    "wof:name":"A.b.t. & S. Sa-nv",
    "wof:placetype":"venue"
},
  "geometry": {"coordinates":[4.373363018,50.8706130981],"type":"Point"}
}