{
  "type": "Feature",
  "properties": {
    "addr:full":"Rue De Daverdisse 62 Libin (redu) Luxembourg 6890",
    "addr:housenumber":"62",
    "addr:postcode":"6890",
    "addr:street":"Rue De Daverdisse",
    "iso:country":"BE",
    "sg:address":"Rue De Daverdisse 62",
    "sg:city":"Libin (redu)",
    "sg:classifiers":[
        {
            "category":"Food & Beverages",
            "subcategory":"Fruits & Vegetables",
            "type":"Retail Goods"
        }
    ],
    "sg:phone":"+32 61 65 66 41",
    "sg:postcode":"6890",
    "sg:province":"Luxembourg",
    "sg:tags":[
        "-"
    ],
    "wof:name":"Domaine De La Framboisi\u00e8re",
    "wof:placetype":"venue"
},
  "geometry": {"coordinates":[5.2562999725,49.9827537537],"type":"Point"}
}