{
  "type": "Feature",
  "properties": {
    "iso:country":"BE",
    "sg:address":"Rue C\u00c9lestin-thiry 1",
    "sg:city":"Floreffe",
    "sg:orig_category":"Boucheries",
    "sg:phone":"+32 81 44 43 05",
    "sg:postcode":"5150",
    "sg:province":"Namur",
    "wof:name":"Jose Waregne",
    "wof:placetype":"venue"
},
  "geometry": {"coordinates":[4.7601590157,50.4352416992],"type":"Point"}
}