{
  "type": "Feature",
  "properties": {
    "addr:full":"Rue De La Carpi\u00e8re 5 Virton (ethe) Luxembourg 6760",
    "addr:housenumber":"5",
    "addr:postcode":"6760",
    "addr:street":"Rue De La Carpie\u0300Re",
    "iso:country":"BE",
    "sg:address":"Rue De La Carpi\u00e8re 5",
    "sg:city":"Virton (ethe)",
    "sg:classifiers":[
        {
            "category":"Health Services",
            "subcategory":"Doctor",
            "type":"Services"
        }
    ],
    "sg:phone":"+32 63 57 76 96",
    "sg:postcode":"6760",
    "sg:province":"Luxembourg",
    "sg:tags":[
        "medicinephysicians",
        "surgeon"
    ],
    "wof:name":"Authelet Claude",
    "wof:placetype":"venue"
},
  "geometry": {"coordinates":[5.5801692009,49.5786018372],"type":"Point"}
}