{
  "type": "Feature",
  "properties": {
    "iso:country":"BE",
    "sg:address":"Blekerijstraat 1",
    "sg:city":"Kruishoutem",
    "sg:orig_category":"Kapsalons",
    "sg:phone":"+32 9 383 52 03",
    "sg:postcode":"9770",
    "sg:province":"Oost-Vlaanderen",
    "wof:name":"Coiffure Nelly",
    "wof:placetype":"venue"
},
  "geometry": {"coordinates":[3.5270500183,50.9030799866],"type":"Point"}
}