{
  "type": "Feature",
  "properties": {
    "addr:full":"Deken Adamsstraat 19 Turnhout Antwerpen 2300",
    "addr:housenumber":"19",
    "addr:postcode":"2300",
    "addr:street":"Deken Adamsstraat",
    "iso:country":"BE",
    "sg:address":"Deken Adamsstraat 19",
    "sg:city":"Turnhout",
    "sg:orig_category":"Opticiens",
    "sg:phone":"+32 14 41 49 72",
    "sg:postcode":"2300",
    "sg:province":"Antwerpen",
    "wof:name":"Josephus Zwijsen",
    "wof:placetype":"venue"
},
  "geometry": {"coordinates":[4.9462819099,51.3203735352],"type":"Point"}
}