{
  "type": "Feature",
  "properties": {
    "addr:full":"Gemeentestraat 21 Duffel Antwerpen 2570",
    "addr:housenumber":"21",
    "addr:postcode":"2570",
    "addr:street":"Gemeentestraat",
    "iso:country":"BE",
    "sg:address":"Gemeentestraat 21",
    "sg:city":"Duffel",
    "sg:orig_category":"Openbare veiligheid",
    "sg:phone":"+32 15 31 12 01",
    "sg:postcode":"2570",
    "sg:province":"Antwerpen",
    "wof:name":"Federale Politie",
    "wof:placetype":"venue"
},
  "geometry": {"coordinates":[4.5060491562,51.0949935913],"type":"Point"}
}