{
  "type": "Feature",
  "properties": {
    "addr:full":"Rue De La Marcelle 29 Couvin Namur 5660",
    "addr:housenumber":"29",
    "addr:postcode":"5660",
    "addr:street":"Rue De La Marcelle",
    "iso:country":"BE",
    "sg:address":"Rue De La Marcelle 29",
    "sg:city":"Couvin",
    "sg:classifiers":[
        {
            "category":"Fast Food",
            "type":"Food & Drink"
        }
    ],
    "sg:phone":"+32 60 34 92 38",
    "sg:postcode":"5660",
    "sg:province":"Namur",
    "sg:tags":[
        "\u00c0",
        "emporter",
        "restaurants"
    ],
    "wof:name":"Pita Couvinoise",
    "wof:placetype":"venue"
},
  "geometry": {"coordinates":[4.496969223,50.048915863],"type":"Point"}
}