{
  "type": "Feature",
  "properties": {
    "iso:country":"BE",
    "sg:address":"Rue Du Monast\u00c8re 26",
    "sg:city":"Brussel/bruxelles",
    "sg:orig_category":"Avocats and conseillers juridiques",
    "sg:phone":"+32 2 646 78 95",
    "sg:postcode":"1000",
    "sg:province":"Bruxelles-Capitale",
    "wof:name":"Greta Parmentier",
    "wof:placetype":"venue"
},
  "geometry": {"coordinates":[4.3724980354,50.8204994202],"type":"Point"}
}