{
  "type": "Feature",
  "properties": {
    "addr:full":"Borgwal 14 Brussel/bruxelles Bruxelles-Capitale 1000",
    "addr:housenumber":"14",
    "addr:postcode":"1000",
    "addr:street":"Borgwal;/",
    "iso:country":"BE",
    "sg:address":"Borgwal 14",
    "sg:city":"Brussel/bruxelles",
    "sg:classifiers":[
        {
            "category":"Bars & Pubs",
            "type":"Food & Drink"
        }
    ],
    "sg:phone":"+32 2 513 73 08",
    "sg:postcode":"1000",
    "sg:province":"Bruxelles-Capitale",
    "wof:name":"Acrobat",
    "wof:placetype":"venue"
},
  "geometry": {"coordinates":[4.3477268219,50.8477172852],"type":"Point"}
}