{
  "type": "Feature",
  "properties": {
    "addr:full":"Rue Du Mont-blanc 14 Sint-gillis/saint-gilles Bruxelles-Capitale 1060",
    "addr:housenumber":"14",
    "addr:postcode":"1060",
    "addr:street":"Rue Du Mont-Blanc",
    "iso:country":"BE",
    "sg:address":"Rue Du Mont-blanc 14",
    "sg:city":"Sint-gillis/saint-gilles",
    "sg:orig_category":"Artistes ind\u00e9pendants",
    "sg:phone":"+32 2 537 19 26",
    "sg:postcode":"1060",
    "sg:province":"Bruxelles-Capitale",
    "wof:name":"Carl Prevot",
    "wof:placetype":"venue"
},
  "geometry": {"coordinates":[4.3496417999,50.8284912109],"type":"Point"}
}