{
  "type": "Feature",
  "properties": {
    "iso:country":"BE",
    "sg:address":"Pothoekstraat 119",
    "sg:city":"Antwerpen",
    "sg:classifiers":[
        {
            "category":"Health Services",
            "subcategory":"Health Practitioner",
            "type":"Services"
        }
    ],
    "sg:phone":"+32 3 235 90 71",
    "sg:postcode":"2060",
    "sg:province":"Antwerpen",
    "sg:tags":[
        "physiotherapist"
    ],
    "wof:name":"Moerman A",
    "wof:placetype":"venue"
},
  "geometry": {"coordinates":[4.4364547729,51.2253761292],"type":"Point"}
}