{
  "type": "Feature",
  "properties": {
    "iso:country":"BE",
    "sg:address":"Rue Du Stordoir 10",
    "sg:city":"La Bruyere",
    "sg:orig_category":"Slagers",
    "sg:phone":"+32 81 56 62 59",
    "sg:postcode":"5081",
    "sg:province":"Namur",
    "wof:name":"Jules Denison",
    "wof:placetype":"venue"
},
  "geometry": {"coordinates":[4.7834620476,50.536365509],"type":"Point"}
}