{
  "type": "Feature",
  "properties": {
    "addr:full":"Rue Th\u00e9odore De Cuyper 6a Bruxelles (woluwe-saint-lambert) Bruxelles-Capitale 1200",
    "addr:housenumber":"6a",
    "addr:postcode":"1200",
    "addr:street":"Rue The\u0301Odore De Cuyper",
    "iso:country":"BE",
    "sg:address":"Rue Th\u00e9odore De Cuyper 6a",
    "sg:city":"Bruxelles (woluwe-saint-lambert)",
    "sg:classifiers":[
        {
            "category":"Health Services",
            "subcategory":"Dentist",
            "type":"Services"
        }
    ],
    "sg:phone":"+32 2 762 32 14",
    "sg:postcode":"1200",
    "sg:province":"Bruxelles-Capitale",
    "wof:name":"Dujardin S",
    "wof:placetype":"venue"
},
  "geometry": {"coordinates":[4.4317259789,50.8493537903],"type":"Point"}
}