{
  "type": "Feature",
  "properties": {
    "addr:full":"Dennenlaan 12 Hove Antwerpen 2540",
    "addr:housenumber":"12",
    "addr:postcode":"2540",
    "addr:street":"Dennenlaan",
    "iso:country":"BE",
    "sg:address":"Dennenlaan 12",
    "sg:city":"Hove",
    "sg:orig_category":"Radioproductie and uitzendingen",
    "sg:phone":"+32 3 455 27 35",
    "sg:postcode":"2540",
    "sg:province":"Antwerpen",
    "wof:name":"Radio Frekwent",
    "wof:placetype":"venue"
},
  "geometry": {"coordinates":[4.4710378647,51.1428565979],"type":"Point"}
}