{
  "type": "Feature",
  "properties": {
    "addr:full":"Chauss\u00c9e De Waterloo 182 Namur Namur 5002",
    "addr:housenumber":"182",
    "addr:postcode":"5002",
    "addr:street":"Chausse\u0301E De Waterloo",
    "iso:country":"BE",
    "sg:address":"Chauss\u00c9e De Waterloo 182",
    "sg:city":"Namur",
    "sg:orig_category":"Verplichte sociale verzekeringen",
    "sg:phone":"+32 81 72 92 11",
    "sg:postcode":"5002",
    "sg:province":"Namur",
    "wof:name":"F\u00c9d.mutualiste Socialiste",
    "wof:placetype":"venue"
},
  "geometry": {"coordinates":[4.8462319374,50.4782791138],"type":"Point"}
}