{
  "type": "Feature",
  "properties": {
    "iso:country":"BE",
    "sg:address":"Place Communale 26b",
    "sg:city":"Manage (bois-d'haine)",
    "sg:classifiers":[
        {
            "category":"Shopping",
            "subcategory":"Clothing, Apparel, & Fashions",
            "type":"Retail Goods"
        }
    ],
    "sg:phone":"+32 64 55 73 15",
    "sg:postcode":"7170",
    "sg:province":"Hainaut",
    "sg:tags":[
        "milliner"
    ],
    "wof:name":"Mercerie Les 2 Mains",
    "wof:placetype":"venue"
},
  "geometry": {"coordinates":[4.2327899933,50.5008239746],"type":"Point"}
}