{
  "type": "Feature",
  "properties": {
    "addr:full":"Zeedijk-het Zoute 682 Knokke-heist (knokke) West-Vlaanderen 8300",
    "addr:housenumber":"682",
    "addr:postcode":"8300",
    "addr:street":"Zoute",
    "iso:country":"BE",
    "sg:address":"Zeedijk-het Zoute 682",
    "sg:city":"Knokke-heist (knokke)",
    "sg:classifiers":[
        {
            "category":"Bars & Pubs",
            "type":"Food & Drink"
        }
    ],
    "sg:phone":"+32 50 61 05 70",
    "sg:postcode":"8300",
    "sg:province":"West-Vlaanderen",
    "sg:tags":[
        "tavern"
    ],
    "wof:name":"Bercy",
    "wof:placetype":"venue"
},
  "geometry": {"coordinates":[3.3267199993,51.3504714966],"type":"Point"}
}