{
  "type": "Feature",
  "properties": {
    "addr:full":"Rue De La Durenne 2 Frasnes-lez-anvaing Hainaut 7912",
    "addr:housenumber":"2",
    "addr:postcode":"7912",
    "addr:street":"Rue De La Durenne",
    "iso:country":"BE",
    "sg:address":"Rue De La Durenne 2",
    "sg:city":"Frasnes-lez-anvaing",
    "sg:orig_category":"Jardinage",
    "sg:phone":"+32 69 76 70 73",
    "sg:postcode":"7912",
    "sg:province":"Hainaut",
    "wof:name":"Carlier A",
    "wof:placetype":"venue"
},
  "geometry": {"coordinates":[3.6131141186,50.723941803],"type":"Point"}
}