{
  "type": "Feature",
  "properties": {
    "addr:full":"Avenue De Norvege 1 Malmedy Li\u00e8ge 4960",
    "addr:housenumber":"1",
    "addr:postcode":"4960",
    "addr:street":"Avenue De Norvege",
    "iso:country":"BE",
    "sg:address":"Avenue De Norvege 1",
    "sg:city":"Malmedy",
    "sg:classifiers":[
        {
            "category":"Food & Beverages",
            "subcategory":"Meat & Fish",
            "type":"Retail Goods"
        }
    ],
    "sg:phone":"+32 3 230 43 64",
    "sg:postcode":"4960",
    "sg:province":"Li\u00e8ge",
    "sg:tags":[
        "preserves",
        "delicacy"
    ],
    "wof:name":"Norway Foods Europe Nv",
    "wof:placetype":"venue"
},
  "geometry": {"coordinates":[4.4239487648,51.1784362793],"type":"Point"}
}