{
  "type": "Feature",
  "properties": {
    "addr:full":"Rue Longue 175 Jodoigne Brabant Wallon 1370",
    "addr:postcode":"175;1370",
    "addr:street":"Rue Longue",
    "iso:country":"BE",
    "sg:address":"Rue Longue 175",
    "sg:city":"Jodoigne",
    "sg:orig_category":"Landmeters",
    "sg:phone":"+32 10 81 35 20",
    "sg:postcode":"1370",
    "sg:province":"Brabant Wallon",
    "wof:name":"Luc Libert",
    "wof:placetype":"venue"
},
  "geometry": {"coordinates":[4.9314770699,50.7321281433],"type":"Point"}
}