{
  "type": "Feature",
  "properties": {
    "iso:country":"BE",
    "sg:address":"Hogeweg 42",
    "sg:city":"Berlare",
    "sg:orig_category":"Eleveurs de bovins. Eleveurs and marchands de porcs",
    "sg:phone":"+32 52 42 38 47",
    "sg:postcode":"9290",
    "sg:province":"Oost-Vlaanderen",
    "wof:name":"Maurits Peleman",
    "wof:placetype":"venue"
},
  "geometry": {"coordinates":[4.0171780586,51.0264587402],"type":"Point"}
}