{
  "type": "Feature",
  "properties": {
    "addr:full":"Tieltstraat 10 Brugge West-Vlaanderen 8851",
    "addr:housenumber":"10",
    "addr:postcode":"8851",
    "addr:street":"Tieltstraat",
    "iso:country":"BE",
    "sg:address":"Tieltstraat 10",
    "sg:city":"Brugge",
    "sg:orig_category":"HUISBRANDOLIE",
    "sg:phone":"+32 51 74 42 63",
    "sg:postcode":"8851",
    "sg:province":"West-Vlaanderen",
    "wof:name":"Benoot J. Brandstoffen",
    "wof:placetype":"venue"
},
  "geometry": {"coordinates":[3.2107729912,51.0019798279],"type":"Point"}
}