{
  "type": "Feature",
  "properties": {
    "addr:full":"Chauss\u00e9e De Wavre 675 Bruxelles (etterbeek) Bruxelles-Capitale 1040",
    "addr:housenumber":"675",
    "addr:postcode":"1040",
    "addr:street":"Chausse\u0301E De Wavre",
    "iso:country":"BE",
    "sg:address":"Chauss\u00e9e De Wavre 675",
    "sg:city":"Bruxelles (etterbeek)",
    "sg:classifiers":[
        {
            "category":"Shopping",
            "subcategory":"Clothing, Apparel, & Fashions",
            "type":"Retail Goods"
        }
    ],
    "sg:phone":"+32 2 648 63 96",
    "sg:postcode":"1040",
    "sg:province":"Bruxelles-Capitale",
    "sg:tags":[
        "underwear",
        "lingerie",
        "-"
    ],
    "wof:name":"Philippars Sprl",
    "wof:placetype":"venue"
},
  "geometry": {"coordinates":[4.390499115,50.8299446106],"type":"Point"}
}