{
  "type": "Feature",
  "properties": {
    "iso:country":"BE",
    "sg:address":"Bredabaan 369",
    "sg:city":"Brasschaat",
    "sg:orig_category":"Smokers' supplies",
    "sg:phone":"+32 3 651 78 21",
    "sg:postcode":"2930",
    "sg:province":"Antwerpen",
    "wof:name":"Hofmans L",
    "wof:placetype":"venue"
},
  "geometry": {"coordinates":[4.4912471771,51.2897377014],"type":"Point"}
}