{
  "type": "Feature",
  "properties": {
    "addr:full":"Kerktorenstraat 6 Machelen Vlaams-Brabant 1831",
    "addr:housenumber":"6",
    "addr:postcode":"1831",
    "addr:street":"Kerktorenstraat",
    "iso:country":"BE",
    "sg:address":"Kerktorenstraat 6",
    "sg:city":"Machelen",
    "sg:orig_category":"Slagers",
    "sg:phone":"+32 2 720 08 40",
    "sg:postcode":"1831",
    "sg:province":"Vlaams-Brabant",
    "wof:name":"Slagerij Plasschaert",
    "wof:placetype":"venue"
},
  "geometry": {"coordinates":[4.434568882,50.8945426941],"type":"Point"}
}