{
  "type": "Feature",
  "properties": {
    "addr:full":"Kanadezenlaan 3 Kalmthout Antwerpen 2920",
    "addr:housenumber":"3",
    "addr:postcode":"2920",
    "addr:street":"Kanadezenlaan",
    "iso:country":"BE",
    "sg:address":"Kanadezenlaan 3",
    "sg:city":"Kalmthout",
    "sg:classifiers":[
        {
            "category":"Building & Trades",
            "subcategory":"Landscaping Services",
            "type":"Services"
        }
    ],
    "sg:phone":"+32 3 666 37 02",
    "sg:postcode":"2920",
    "sg:province":"Antwerpen",
    "sg:tags":[
        "gardening",
        "garden",
        "maintenance"
    ],
    "wof:name":"Van Den Bogaert Tuinen Bvba",
    "wof:placetype":"venue"
},
  "geometry": {"coordinates":[4.4591741562,51.3640480042],"type":"Point"}
}