{
  "type": "Feature",
  "properties": {
    "addr:full":"Laar 158 Geel Antwerpen 2440",
    "addr:housenumber":"158",
    "addr:postcode":"2440",
    "addr:street":"Laar",
    "iso:country":"BE",
    "sg:address":"Laar 158",
    "sg:city":"Geel",
    "sg:orig_category":"Rev\u00eatements de sols and murs. Rev\u00eatements pour sols and murs",
    "sg:phone":"+32 14 58 67 34",
    "sg:postcode":"2440",
    "sg:province":"Antwerpen",
    "wof:name":"'t Geels Tegelhuis",
    "wof:placetype":"venue"
},
  "geometry": {"coordinates":[5.0140810013,51.1592903137],"type":"Point"}
}