{
  "type": "Feature",
  "properties": {
    "iso:country":"BE",
    "sg:address":"Wolvertemsesteenweg 92",
    "sg:city":"Grimbergen",
    "sg:orig_category":"Diverse kredietdiensten",
    "sg:postcode":"1850",
    "sg:province":"Vlaams-Brabant",
    "wof:name":"Bancontact-mister Cash",
    "wof:placetype":"venue"
},
  "geometry": {"coordinates":[4.3659749031,50.9359054565],"type":"Point"}
}