{
  "type": "Feature",
  "properties": {
    "iso:country":"BE",
    "sg:address":"Congresstraat 22",
    "sg:city":"Antwerpen",
    "sg:orig_category":"Non-Classified Establishments",
    "sg:phone":"+32 3 235 41 19",
    "sg:postcode":"2060",
    "sg:province":"Antwerpen",
    "wof:name":"Marche Persan (au)",
    "wof:placetype":"venue"
},
  "geometry": {"coordinates":[4.4256949425,51.2182388306],"type":"Point"}
}