{
  "type": "Feature",
  "properties": {
    "addr:full":"Bredabaan 324 Brasschaat Antwerpen 2930",
    "addr:housenumber":"324",
    "addr:postcode":"2930",
    "addr:street":"Bredabaan",
    "iso:country":"BE",
    "sg:address":"Bredabaan 324",
    "sg:city":"Brasschaat",
    "sg:classifiers":[
        {
            "category":"Shopping",
            "subcategory":"Luggage & Leather Goods",
            "type":"Retail Goods"
        }
    ],
    "sg:phone":"+32 3 653 58 47",
    "sg:postcode":"2930",
    "sg:province":"Antwerpen",
    "sg:tags":[
        "-"
    ],
    "wof:name":"Chic Simple",
    "wof:placetype":"venue"
},
  "geometry": {"coordinates":[4.4935221672,51.2918052673],"type":"Point"}
}