{
  "type": "Feature",
  "properties": {
    "iso:country":"BE",
    "sg:address":"Volksplein 16c",
    "sg:city":"Kortrijk",
    "sg:orig_category":"Imprimeries and copyshops",
    "sg:phone":"+32 56 22 27 29",
    "sg:postcode":"8500",
    "sg:province":"West-Vlaanderen",
    "wof:name":"Beyaert Andre & Zonen",
    "wof:placetype":"venue"
},
  "geometry": {"coordinates":[3.2719299793,50.8201217651],"type":"Point"}
}