{
  "type": "Feature",
  "properties": {
    "addr:full":"Keizershoek 340a Kontich Antwerpen 2550",
    "addr:housenumber":"340a",
    "addr:postcode":"2550",
    "addr:street":"Keizershoek",
    "iso:country":"BE",
    "sg:address":"Keizershoek 340a",
    "sg:city":"Kontich",
    "sg:orig_category":"Charpentes and couvertures",
    "sg:phone":"+32 3 457 78 31",
    "sg:postcode":"2550",
    "sg:province":"Antwerpen",
    "wof:name":"Dakvak",
    "wof:placetype":"venue"
},
  "geometry": {"coordinates":[4.4136657715,51.1214179993],"type":"Point"}
}