{
  "type": "Feature",
  "properties": {
    "iso:country":"BE",
    "sg:address":"Molenstraat 124",
    "sg:city":"Sint-katelijne-waver",
    "sg:orig_category":"Bloemen and planten Gh Groententeelt",
    "sg:phone":"+32 15 75 60 57",
    "sg:postcode":"2861",
    "sg:province":"Antwerpen",
    "wof:name":"Paul Jacobs",
    "wof:placetype":"venue"
},
  "geometry": {"coordinates":[4.5990681648,51.0646858215],"type":"Point"}
}