{
  "type": "Feature",
  "properties": {
    "iso:country":"BE",
    "sg:address":"Beekstraat 31",
    "sg:city":"Lede",
    "sg:orig_category":"Epiceries",
    "sg:phone":"+32 9 369 12 48",
    "sg:postcode":"9340",
    "sg:province":"Oost-Vlaanderen",
    "wof:name":"Christine Sergeant",
    "wof:placetype":"venue"
},
  "geometry": {"coordinates":[3.8962619305,50.9603347778],"type":"Point"}
}