{
  "type": "Feature",
  "properties": {
    "addr:full":"Dolfijnkaai 5 Kortrijk West-Vlaanderen 8500",
    "addr:housenumber":"5",
    "addr:postcode":"8500",
    "addr:street":"Dolfijnkaai",
    "iso:country":"BE",
    "sg:address":"Dolfijnkaai 5",
    "sg:city":"Kortrijk",
    "sg:orig_category":"Advocaten and juridische adviseurs",
    "sg:phone":"+32 56 22 10 90",
    "sg:postcode":"8500",
    "sg:province":"West-Vlaanderen",
    "wof:name":"P. Vieren",
    "wof:placetype":"venue"
},
  "geometry": {"coordinates":[3.2639560699,50.8293228149],"type":"Point"}
}