{
  "type": "Feature",
  "properties": {
    "addr:full":"Rue Du Cheval Blanc 29 Pont-\u00e0-celles (luttre) Hainaut 6238",
    "addr:housenumber":"29",
    "addr:postcode":"6238",
    "addr:street":"Rue Du Cheval Blanc",
    "iso:country":"BE",
    "sg:address":"Rue Du Cheval Blanc 29",
    "sg:city":"Pont-\u00e0-celles (luttre)",
    "sg:classifiers":[
        {
            "category":"Building & Trades",
            "subcategory":"Construction",
            "type":"Services"
        }
    ],
    "sg:phone":"+32 71 84 36 90",
    "sg:postcode":"6238",
    "sg:province":"Hainaut",
    "sg:tags":[
        "stair"
    ],
    "wof:name":"Debeque Kinda Sprl",
    "wof:placetype":"venue"
},
  "geometry": {"coordinates":[4.3906188011,50.504573822],"type":"Point"}
}