{
  "type": "Feature",
  "properties": {
    "addr:full":"Coupure Rechts 164c-d Gent Oost-Vlaanderen 9000",
    "addr:postcode":"9000",
    "addr:street":"Coupure Rechts 164C-D",
    "iso:country":"BE",
    "sg:address":"Coupure Rechts 164c-d",
    "sg:city":"Gent",
    "sg:classifiers":[
        {
            "category":"Community Center",
            "type":"Public Place"
        }
    ],
    "sg:phone":"+32 9 269 94 94",
    "sg:postcode":"9000",
    "sg:province":"Oost-Vlaanderen",
    "sg:tags":[
        "medical"
    ],
    "wof:name":"Coupure Centrum Voor Plastische Chirurgie",
    "wof:placetype":"venue"
},
  "geometry": {"coordinates":[3.7285690308,51.0556335449],"type":"Point"}
}