{
  "type": "Feature",
  "properties": {
    "addr:full":"Rue De La Casquette 16 Li\u00c8ge Li\u00e8ge 4000",
    "addr:housenumber":"16",
    "addr:postcode":"4000",
    "addr:street":"Rue De La Casquette",
    "iso:country":"BE",
    "sg:address":"Rue De La Casquette 16",
    "sg:city":"Li\u00c8ge",
    "sg:orig_category":"Tabac",
    "sg:phone":"+32 4 223 16 18",
    "sg:postcode":"4000",
    "sg:province":"Li\u00e8ge",
    "wof:name":"Le Tabavin",
    "wof:placetype":"venue"
},
  "geometry": {"coordinates":[5.5686388016,50.6425247192],"type":"Point"}
}