{
  "type": "Feature",
  "properties": {
    "iso:country":"BE",
    "sg:address":"Wilgenlaan 13",
    "sg:city":"Wielsbeke",
    "sg:orig_category":"Elektrische installaties voor woningen",
    "sg:phone":"+32 56 66 50 36",
    "sg:postcode":"8710",
    "sg:province":"West-Vlaanderen",
    "wof:name":"Rudy Van Oosthuyze",
    "wof:placetype":"venue"
},
  "geometry": {"coordinates":[3.3283278942,50.8956871033],"type":"Point"}
}