{
  "type": "Feature",
  "properties": {
    "iso:country":"BE",
    "sg:address":"Rue De Battice 20",
    "sg:city":"Aubel",
    "sg:classifiers":[
        {
            "category":"Professional",
            "subcategory":"Printing & Photocopies",
            "type":"Services"
        }
    ],
    "sg:phone":"+32 71 28 36 11",
    "sg:postcode":"4880",
    "sg:province":"Li\u00e8ge",
    "sg:tags":[
        "offset"
    ],
    "wof:name":"Imprimerie Bietlot S.a.",
    "wof:placetype":"venue"
},
  "geometry": {"coordinates":[4.4908227921,50.4357414246],"type":"Point"}
}