{
  "type": "Feature",
  "properties": {
    "addr:full":"27 Moerbroek (i.z.) 2270 Herenthout 27",
    "addr:housenumber":"27;27",
    "addr:postcode":"2270",
    "addr:street":"Moerbroek I.Z.",
    "iso:country":"BE",
    "sg:address":"27",
    "sg:city":"Moerbroek (i.z.) 2270 Herenthout",
    "sg:classifiers":[
        {
            "category":"Shopping",
            "type":"Retail Goods"
        }
    ],
    "sg:phone":"+32 14 22 07 70",
    "sg:postcode":"27",
    "sg:tags":[
        "metallurgy",
        "finished",
        "-",
        "metalworking",
        "metallic"
    ],
    "wof:name":"Eurowheel Bvba",
    "wof:placetype":"venue"
},
  "geometry": {"coordinates":[4.7977900505,51.1535949707],"type":"Point"}
}