{
  "type": "Feature",
  "properties": {
    "iso:country":"BE",
    "sg:address":"Rue De La Metallurgie 35",
    "sg:city":"Villers-le-bouillet",
    "sg:classifiers":[
        {
            "category":"Transit Center",
            "subcategory":"Freight",
            "type":"Transportation"
        }
    ],
    "sg:phone":"+32 4 259 93 43",
    "sg:postcode":"4530",
    "sg:province":"Li\u00e8ge",
    "sg:tags":[
        "forwarding",
        "agency"
    ],
    "wof:name":"Demonty S.a.",
    "wof:placetype":"venue"
},
  "geometry": {"coordinates":[5.2622499466,50.5809020996],"type":"Point"}
}