{
  "type": "Feature",
  "properties": {
    "addr:full":"Rue Des Combattants Et D\u00e9port\u00e9s 10 Thuin (thuillies) Hainaut 6536",
    "addr:housenumber":"10",
    "addr:postcode":"6536",
    "addr:street":"Rue Des Combattants Et De\u0301Porte\u0301S",
    "iso:country":"BE",
    "sg:address":"Rue Des Combattants Et D\u00e9port\u00e9s 10",
    "sg:city":"Thuin (thuillies)",
    "sg:classifiers":[
        {
            "category":"Professional",
            "subcategory":"Printing & Photocopies",
            "type":"Services"
        }
    ],
    "sg:phone":"+32 71 53 37 23",
    "sg:postcode":"6536",
    "sg:province":"Hainaut",
    "sg:tags":[
        "-",
        "offset"
    ],
    "wof:name":"Blondiaux",
    "wof:placetype":"venue"
},
  "geometry": {"coordinates":[4.3310408592,50.2948760986],"type":"Point"}
}