{
  "type": "Feature",
  "properties": {
    "addr:full":"Avenue Reine Astrid 144 Spa Li\u00e8ge 4900",
    "addr:housenumber":"144",
    "addr:postcode":"4900",
    "addr:street":"Avenue Reine Astrid",
    "iso:country":"BE",
    "sg:address":"Avenue Reine Astrid 144",
    "sg:city":"Spa",
    "sg:orig_category":"Antiek",
    "sg:phone":"+32 87 77 46 75",
    "sg:postcode":"4900",
    "sg:province":"Li\u00e8ge",
    "wof:name":"Arnaud De Spa",
    "wof:placetype":"venue"
},
  "geometry": {"coordinates":[5.8531718254,50.4909133911],"type":"Point"}
}