{
  "type": "Feature",
  "properties": {
    "addr:full":"Avenue Albert Drossart 14 Orp-jauche Brabant Wallon 1350",
    "addr:housenumber":"14",
    "addr:postcode":"1350",
    "addr:street":"Avenue Albert Drossart",
    "iso:country":"BE",
    "sg:address":"Avenue Albert Drossart 14",
    "sg:city":"Orp-jauche",
    "sg:orig_category":"Slagers",
    "sg:phone":"+32 19 63 31 80",
    "sg:postcode":"1350",
    "sg:province":"Brabant Wallon",
    "wof:name":"Christiane Francis",
    "wof:placetype":"venue"
},
  "geometry": {"coordinates":[4.97920084,50.6738891602],"type":"Point"}
}