{
  "type": "Feature",
  "properties": {
    "addr:full":"Spaarstraat 87 Leuven Vlaams-Brabant 3010",
    "addr:housenumber":"87",
    "addr:postcode":"3010",
    "addr:street":"Spaarstraat",
    "iso:country":"BE",
    "sg:address":"Spaarstraat 87",
    "sg:city":"Leuven",
    "sg:classifiers":[
        {
            "category":"Insurance",
            "subcategory":"Life Insurance",
            "type":"Services"
        }
    ],
    "sg:phone":"+32 16 26 00 84",
    "sg:postcode":"3010",
    "sg:province":"Vlaams-Brabant",
    "sg:tags":[
        "assurance"
    ],
    "wof:name":"Madebra",
    "wof:placetype":"venue"
},
  "geometry": {"coordinates":[4.7304501534,50.889755249],"type":"Point"}
}