{
  "type": "Feature",
  "properties": {
    "iso:country":"BE",
    "sg:address":"Groenestraat 18ba",
    "sg:city":"Kortemark",
    "sg:orig_category":"V\u00e9t\u00e9rinaires",
    "sg:phone":"+32 51 56 75 14",
    "sg:postcode":"8610",
    "sg:province":"West-Vlaanderen",
    "wof:name":"Arthur Denys",
    "wof:placetype":"venue"
},
  "geometry": {"coordinates":[3.0050399303,51.0168113708],"type":"Point"}
}