{
  "type": "Feature",
  "properties": {
    "addr:full":"Blasiusstraat 65 Poperinge West-Vlaanderen 8972",
    "addr:housenumber":"65",
    "addr:postcode":"8972",
    "addr:street":"Blasiusstraat",
    "iso:country":"BE",
    "sg:address":"Blasiusstraat 65",
    "sg:city":"Poperinge",
    "sg:classifiers":[
        {
            "category":"Banks & Credit Unions",
            "subcategory":"Investment Brokerage",
            "type":"Services"
        }
    ],
    "sg:phone":"+32 57 30 09 55",
    "sg:postcode":"8972",
    "sg:province":"West-Vlaanderen",
    "sg:tags":[
        "pension"
    ],
    "wof:name":"D'oude Hoeve",
    "wof:placetype":"venue"
},
  "geometry": {"coordinates":[2.6732769012,50.8973731995],"type":"Point"}
}