{
  "type": "Feature",
  "properties": {
    "addr:full":"Hollestraat 31 Leuven (heverlee) Vlaams-Brabant 3001",
    "addr:housenumber":"31",
    "addr:postcode":"3001",
    "addr:street":"Hollestraat",
    "iso:country":"BE",
    "sg:address":"Hollestraat 31",
    "sg:city":"Leuven (heverlee)",
    "sg:classifiers":[
        {
            "category":"Education",
            "subcategory":"Dance Studio",
            "type":"Public Place"
        }
    ],
    "sg:phone":"+32 16 29 03 32",
    "sg:postcode":"3001",
    "sg:province":"Vlaams-Brabant",
    "sg:tags":[
        "school",
        "dancing"
    ],
    "wof:name":"Danscentrum Aike Raes Vzw",
    "wof:placetype":"venue"
},
  "geometry": {"coordinates":[4.6861419678,50.8740501404],"type":"Point"}
}