{
  "type": "Feature",
  "properties": {
    "addr:full":"Grote Roeselarestraat 4 Meulebeke West-Vlaanderen 8760",
    "addr:housenumber":"4",
    "addr:postcode":"8760",
    "addr:street":"Grote Roeselarestraat",
    "iso:country":"BE",
    "sg:address":"Grote Roeselarestraat 4",
    "sg:city":"Meulebeke",
    "sg:orig_category":"Eleveurs and marchands de porcs",
    "sg:phone":"+32 51 48 74 60",
    "sg:postcode":"8760",
    "sg:province":"West-Vlaanderen",
    "wof:name":"Dirk Devlamynck",
    "wof:placetype":"venue"
},
  "geometry": {"coordinates":[3.2606489658,50.9505271912],"type":"Point"}
}