{
  "type": "Feature",
  "properties": {
    "addr:full":"Route Des Xhawirs 128 Herve Li\u00e8ge 4652",
    "addr:housenumber":"128",
    "addr:postcode":"4652",
    "addr:street":"Route Des Xhawirs",
    "iso:country":"BE",
    "sg:address":"Route Des Xhawirs 128",
    "sg:city":"Herve",
    "sg:orig_category":"Pleisterwerk",
    "sg:phone":"+32 87 66 04 85",
    "sg:postcode":"4652",
    "sg:province":"Li\u00e8ge",
    "wof:name":"David Englebert",
    "wof:placetype":"venue"
},
  "geometry": {"coordinates":[5.7804818153,50.6042518616],"type":"Point"}
}