{
  "type": "Feature",
  "properties": {
    "addr:full":"Avenue Reine Astrid 99 Limbourg (bilstain) Li\u00e8ge 4831",
    "addr:housenumber":"99",
    "addr:postcode":"4831",
    "addr:street":"Avenue Reine Astrid;Bilstain",
    "iso:country":"BE",
    "sg:address":"Avenue Reine Astrid 99",
    "sg:city":"Limbourg (bilstain)",
    "sg:classifiers":[
        {
            "category":"Manufacturing",
            "subcategory":"Tools & Machinery",
            "type":"Manufacturing & Wholesale Goods"
        }
    ],
    "sg:phone":"+32 87 76 32 71",
    "sg:postcode":"4831",
    "sg:province":"Li\u00e8ge",
    "sg:tags":[
        "builder"
    ],
    "wof:name":"Efgeco",
    "wof:placetype":"venue"
},
  "geometry": {"coordinates":[5.9324541092,50.6154823303],"type":"Point"}
}