{
  "type": "Feature",
  "properties": {
    "addr:full":"Le Bois De Feluy 2 Seneffe Hainaut 7181",
    "addr:housenumber":"2",
    "addr:postcode":"7181",
    "addr:street":"Le Bois De Feluy",
    "iso:country":"BE",
    "sg:address":"Le Bois De Feluy 2",
    "sg:city":"Seneffe",
    "sg:orig_category":"Eleveurs de bovins",
    "sg:phone":"+32 67 87 73 39",
    "sg:postcode":"7181",
    "sg:province":"Hainaut",
    "wof:name":"Andre Brouckaert",
    "wof:placetype":"venue"
},
  "geometry": {"coordinates":[4.2355780602,50.5422515869],"type":"Point"}
}