{
  "type": "Feature",
  "properties": {
    "iso:country":"BE",
    "sg:address":"Neervelpsestraat 50",
    "sg:city":"Bierbeek",
    "sg:classifiers":[
        {
            "category":"Sports & Exercise",
            "subcategory":"Sports Center",
            "type":"Entertainment"
        }
    ],
    "sg:phone":"+32 16 73 37 50",
    "sg:postcode":"3360",
    "sg:province":"Vlaams-Brabant",
    "sg:tags":[
        "installation",
        "sportifs",
        "club",
        "de",
        "terrain",
        "hors",
        "caf\u00e9s"
    ],
    "wof:name":"V.c. Jong Neervelp",
    "wof:placetype":"venue"
},
  "geometry": {"coordinates":[4.7968888283,50.8230705261],"type":"Point"}
}