{
  "type": "Feature",
  "properties": {
    "iso:country":"BE",
    "sg:address":"Rue Arthur Descamps 156",
    "sg:city":"Colfontaine",
    "sg:orig_category":"V\u00e9t\u00e9rinaires",
    "sg:phone":"+32 65 67 23 93",
    "sg:postcode":"7340",
    "sg:province":"Hainaut",
    "wof:name":"Monique Dekoster",
    "wof:placetype":"venue"
},
  "geometry": {"coordinates":[3.8581309319,50.3981323242],"type":"Point"}
}