{
  "type": "Feature",
  "properties": {
    "iso:country":"BE",
    "sg:address":"Rue De Verviers 32",
    "sg:city":"Li\u00c8ge",
    "sg:orig_category":"Artiesten and kunstenaars",
    "sg:phone":"+32 4 343 48 03",
    "sg:postcode":"4020",
    "sg:province":"Li\u00e8ge",
    "wof:name":"Herman",
    "wof:placetype":"venue"
},
  "geometry": {"coordinates":[5.5852870941,50.6229858398],"type":"Point"}
}