{
  "type": "Feature",
  "properties": {
    "iso:country":"BE",
    "sg:address":"Hovesteenseweg 7",
    "sg:city":"Meerhout",
    "sg:classifiers":[
        {
            "category":"Health Services",
            "subcategory":"Health Practitioner",
            "type":"Services"
        }
    ],
    "sg:phone":"+32 14 30 92 93",
    "sg:postcode":"2450",
    "sg:province":"Antwerpen",
    "sg:tags":[
        "physiotherapist"
    ],
    "wof:name":"Van Gossum & Debie Bvba",
    "wof:placetype":"venue"
},
  "geometry": {"coordinates":[5.1108698845,51.1109085083],"type":"Point"}
}