{
  "type": "Feature",
  "properties": {
    "addr:full":"Rue De La Vall\u00e9e 27a Sambreville (velaine-sur-sambre) Namur 5060",
    "addr:housenumber":"27a",
    "addr:postcode":"5060",
    "addr:street":"Rue De La Valle\u0301E",
    "iso:country":"BE",
    "sg:address":"Rue De La Vall\u00e9e 27a",
    "sg:city":"Sambreville (velaine-sur-sambre)",
    "sg:classifiers":[
        {
            "category":"Health Services",
            "subcategory":"Dentist",
            "type":"Services"
        }
    ],
    "sg:phone":"+32 71 77 71 26",
    "sg:postcode":"5060",
    "sg:province":"Namur",
    "wof:name":"Devalck Jc",
    "wof:placetype":"venue"
},
  "geometry": {"coordinates":[4.6285200119,50.4448738098],"type":"Point"}
}