{
  "type": "Feature",
  "properties": {
    "addr:full":"Vredestraat 88d Kontich Antwerpen 2550",
    "addr:housenumber":"88d",
    "addr:postcode":"2550",
    "addr:street":"Vredestraat",
    "iso:country":"BE",
    "sg:address":"Vredestraat 88d",
    "sg:city":"Kontich",
    "sg:classifiers":[
        {
            "category":"Professional",
            "subcategory":"Accounting & Tax Preparation",
            "type":"Services"
        }
    ],
    "sg:phone":"+32 3 455 61 31",
    "sg:postcode":"2550",
    "sg:province":"Antwerpen",
    "sg:tags":[
        "bookkeeper"
    ],
    "wof:name":"Verhaert J-l",
    "wof:placetype":"venue"
},
  "geometry": {"coordinates":[4.46398592,51.1462783813],"type":"Point"}
}