{
  "type": "Feature",
  "properties": {
    "addr:full":"Kerkeblok 14 Herentals Antwerpen 2200",
    "addr:housenumber":"14",
    "addr:postcode":"2200",
    "addr:street":"Kerkeblok",
    "iso:country":"BE",
    "sg:address":"Kerkeblok 14",
    "sg:city":"Herentals",
    "sg:classifiers":[
        {
            "category":"Arena",
            "subcategory":"Sports Club",
            "type":"Entertainment"
        }
    ],
    "sg:phone":"+32 14 26 20 66",
    "sg:postcode":"2200",
    "sg:province":"Antwerpen",
    "sg:tags":[
        "de"
    ],
    "wof:name":"W.s.c. Noorderwijk",
    "wof:placetype":"venue"
},
  "geometry": {"coordinates":[4.8442749977,51.1394233704],"type":"Point"}
}