{
  "type": "Feature",
  "properties": {
    "addr:full":"Rue Reine Astrid 49 Welkenraedt/welkenraedt Li\u00e8ge 4840",
    "addr:housenumber":"49",
    "addr:postcode":"4840",
    "addr:street":"Rue Reine Astrid",
    "iso:country":"BE",
    "sg:address":"Rue Reine Astrid 49",
    "sg:city":"Welkenraedt/welkenraedt",
    "sg:orig_category":"Krantenwinkels Rookartikelen",
    "sg:phone":"+32 87 88 02 34",
    "sg:postcode":"4840",
    "sg:province":"Li\u00e8ge",
    "wof:name":"Librairie Ir\u00c8ne",
    "wof:placetype":"venue"
},
  "geometry": {"coordinates":[5.9796700478,50.6616210938],"type":"Point"}
}