{
  "type": "Feature",
  "properties": {
    "addr:full":"Karel Van De Woestijnestraat 18 Oostende West-Vlaanderen 8400",
    "addr:housenumber":"18",
    "addr:postcode":"8400",
    "addr:street":"Karel Van De Woestijnestraat",
    "iso:country":"BE",
    "sg:address":"Karel Van De Woestijnestraat 18",
    "sg:city":"Oostende",
    "sg:classifiers":[
        {
            "category":"Health Services",
            "subcategory":"Dentist",
            "type":"Services"
        }
    ],
    "sg:phone":"+32 59 50 52 65",
    "sg:postcode":"8400",
    "sg:province":"West-Vlaanderen",
    "wof:name":"De Nys Marc",
    "wof:placetype":"venue"
},
  "geometry": {"coordinates":[2.9070620537,51.2196121216],"type":"Point"}
}