{
  "type": "Feature",
  "properties": {
    "addr:full":"Atletenlaan 24-25 Brussel/bruxelles Bruxelles-Capitale 1020",
    "addr:postcode":"24-25;/ bruxelles;1020",
    "addr:street":"Atletenlaan",
    "iso:country":"BE",
    "sg:address":"Atletenlaan 24-25",
    "sg:city":"Brussel/bruxelles",
    "sg:classifiers":[
        {
            "category":"Bars & Pubs",
            "type":"Food & Drink"
        }
    ],
    "sg:phone":"+32 2 479 17 44",
    "sg:postcode":"1020",
    "sg:province":"Bruxelles-Capitale",
    "sg:tags":[
        "restaurant"
    ],
    "wof:name":"Po Boy",
    "wof:placetype":"venue"
},
  "geometry": {"coordinates":[4.3344650269,50.8972969055],"type":"Point"}
}