{
  "type": "Feature",
  "properties": {
    "addr:full":"Deinsesteenweg 177 Kruishoutem Oost-Vlaanderen 9770",
    "addr:housenumber":"177",
    "addr:postcode":"9770",
    "addr:street":"Deinsesteenweg",
    "iso:country":"BE",
    "sg:address":"Deinsesteenweg 177",
    "sg:city":"Kruishoutem",
    "sg:classifiers":[
        {
            "category":"Building & Trades",
            "subcategory":"Electrical",
            "type":"Services"
        }
    ],
    "sg:phone":"+32 9 386 12 21",
    "sg:postcode":"9770",
    "sg:province":"Oost-Vlaanderen",
    "sg:tags":[
        "electric",
        "-",
        "housewiring",
        "contractor"
    ],
    "wof:name":"De Baere Elektro Bvba",
    "wof:placetype":"venue"
},
  "geometry": {"coordinates":[3.5372760296,50.9326820374],"type":"Point"}
}