{
  "type": "Feature",
  "properties": {
    "addr:full":"Lange Gang 27 Antwerpen Antwerpen 2000",
    "addr:housenumber":"27",
    "addr:postcode":"2000",
    "addr:street":"Lange Gang",
    "iso:country":"BE",
    "sg:address":"Lange Gang 27",
    "sg:city":"Antwerpen",
    "sg:classifiers":[
        {
            "category":"Restaurant",
            "type":"Food & Drink"
        }
    ],
    "sg:phone":"+32 3 231 61 11",
    "sg:postcode":"2000",
    "sg:province":"Antwerpen",
    "sg:tags":[
        "caf\u00e9s"
    ],
    "wof:name":"Taverne De Gang",
    "wof:placetype":"venue"
},
  "geometry": {"coordinates":[4.412115097,51.2163047791],"type":"Point"}
}