{
  "type": "Feature",
  "properties": {
    "addr:full":"De Smet De Naeyerlaan 3 De Haan (wenduine) West-Vlaanderen 8420",
    "addr:housenumber":"3",
    "addr:postcode":"8420",
    "addr:street":"De Smet De Naeyerlaan",
    "iso:country":"BE",
    "sg:address":"De Smet De Naeyerlaan 3",
    "sg:city":"De Haan (wenduine)",
    "sg:classifiers":[
        {
            "category":"Shopping",
            "subcategory":"Florist",
            "type":"Retail Goods"
        }
    ],
    "sg:phone":"+32 50 42 44 66",
    "sg:postcode":"8420",
    "sg:province":"West-Vlaanderen",
    "wof:name":"Creaflor",
    "wof:placetype":"venue"
},
  "geometry": {"coordinates":[3.0799629688,51.3012313843],"type":"Point"}
}