{
  "type": "Feature",
  "properties": {
    "addr:full":"Jef Vandermeulenstraat 37 Gent (gentbrugge) Oost-Vlaanderen 9050",
    "addr:housenumber":"37",
    "addr:postcode":"9050",
    "addr:street":"Jef Vandermeulenstraat",
    "iso:country":"BE",
    "sg:address":"Jef Vandermeulenstraat 37",
    "sg:city":"Gent (gentbrugge)",
    "sg:classifiers":[
        {
            "category":"Personal",
            "subcategory":"Beauty Salon",
            "type":"Services"
        }
    ],
    "sg:phone":"+32 9 230 16 00",
    "sg:postcode":"9050",
    "sg:province":"Oost-Vlaanderen",
    "sg:tags":[
        "lady",
        "-",
        "hairdressing"
    ],
    "wof:name":"Linea",
    "wof:placetype":"venue"
},
  "geometry": {"coordinates":[3.7581920624,51.0422515869],"type":"Point"}
}