{
  "type": "Feature",
  "properties": {
    "iso:country":"BE",
    "sg:address":"Wijngaardstraat 22",
    "sg:city":"Brugge",
    "sg:classifiers":[
        {
            "category":"Shopping",
            "subcategory":"Crafts & Fabrics",
            "type":"Retail Goods"
        }
    ],
    "sg:phone":"+32 50 34 37 92",
    "sg:postcode":"8000",
    "sg:province":"West-Vlaanderen",
    "sg:tags":[
        "ceramic"
    ],
    "wof:name":"Kasper Keramiek",
    "wof:placetype":"venue"
},
  "geometry": {"coordinates":[3.2246599197,51.2019195557],"type":"Point"}
}