{
  "type": "Feature",
  "properties": {
    "addr:full":"Rue Emile Vandervelde 26 Celles (borlez) Li\u00e8ge 4317",
    "addr:housenumber":"26",
    "addr:postcode":"4317",
    "addr:street":"Rue Emile Vandervelde",
    "iso:country":"BE",
    "sg:address":"Rue Emile Vandervelde 26",
    "sg:city":"Celles (borlez)",
    "sg:orig_category":"Non-Classified Establishments",
    "sg:phone":"+32 19 56 69 78",
    "sg:postcode":"4317",
    "sg:province":"Li\u00e8ge",
    "wof:name":"Delchambre J-c",
    "wof:placetype":"venue"
},
  "geometry": {"coordinates":[5.2618951797,50.6657218933],"type":"Point"}
}