{
  "type": "Feature",
  "properties": {
    "iso:country":"BE",
    "sg:address":"Rue Des Combattants 3",
    "sg:city":"Erezee",
    "sg:classifiers":[
        {
            "category":"Restaurant",
            "type":"Food & Drink"
        }
    ],
    "sg:phone":"+32 86 47 72 65",
    "sg:postcode":"6997",
    "sg:province":"Luxembourg",
    "sg:tags":[
        "caf\u00e9s",
        "h\u00f4tels"
    ],
    "wof:name":"Le Liry",
    "wof:placetype":"venue"
},
  "geometry": {"coordinates":[5.5584588051,50.2921104431],"type":"Point"}
}