{
  "type": "Feature",
  "properties": {
    "addr:full":"Grote Steenweg 193 Lede Oost-Vlaanderen 9340",
    "addr:housenumber":"193",
    "addr:postcode":"9340",
    "addr:street":"Grote Steenweg",
    "iso:country":"BE",
    "sg:address":"Grote Steenweg 193",
    "sg:city":"Lede",
    "sg:orig_category":"Apotheken",
    "sg:phone":"+32 9 369 02 39",
    "sg:postcode":"9340",
    "sg:province":"Oost-Vlaanderen",
    "wof:name":"Apotheek Asselman",
    "wof:placetype":"venue"
},
  "geometry": {"coordinates":[4.0117402077,50.9629211426],"type":"Point"}
}