{
  "type": "Feature",
  "properties": {
    "iso:country":"BE",
    "sg:address":"Rue Fran\u00c7ois Chefnay 49",
    "sg:city":"Fl\u00c9malle",
    "sg:orig_category":"Mat\u00e9riel m\u00e9dical and orthop\u00e9dique and proth\u00e8ses Fab",
    "sg:phone":"+32 4 275 18 68",
    "sg:postcode":"4400",
    "sg:province":"Li\u00e8ge",
    "wof:name":"Pierre Ligot",
    "wof:placetype":"venue"
},
  "geometry": {"coordinates":[5.4576430321,50.5693130493],"type":"Point"}
}