{
  "type": "Feature",
  "properties": {
    "addr:full":"Adriaan Sanderslei 70 Aartselaar Antwerpen 2630",
    "addr:housenumber":"70",
    "addr:postcode":"2630",
    "addr:street":"Adriaan Sanderslei",
    "iso:country":"BE",
    "sg:address":"Adriaan Sanderslei 70",
    "sg:city":"Aartselaar",
    "sg:classifiers":[
        {
            "category":"Health Services",
            "subcategory":"Dentist",
            "type":"Services"
        }
    ],
    "sg:phone":"+32 3 887 73 86",
    "sg:postcode":"2630",
    "sg:province":"Antwerpen",
    "wof:name":"Versluys R",
    "wof:placetype":"venue"
},
  "geometry": {"coordinates":[4.3901071548,51.1334915161],"type":"Point"}
}