{
  "type": "Feature",
  "properties": {
    "iso:country":"BE",
    "sg:address":"Rue De Renory 41",
    "sg:city":"Li\u00c8ge",
    "sg:orig_category":"Jeux de hasard",
    "sg:phone":"+32 4 343 50 25",
    "sg:postcode":"4031",
    "sg:province":"Li\u00e8ge",
    "wof:name":"Tierc\u00c9 Franco Belge",
    "wof:placetype":"venue"
},
  "geometry": {"coordinates":[5.5594201088,50.6039390564],"type":"Point"}
}