{
  "type": "Feature",
  "properties": {
    "iso:country":"BE",
    "sg:address":"Lippenslaan 308",
    "sg:city":"Knokke-heist",
    "sg:orig_category":"Boucheries",
    "sg:phone":"+32 50 61 14 41",
    "sg:postcode":"8300",
    "sg:province":"West-Vlaanderen",
    "wof:name":"Beenhouwerij Vanhil",
    "wof:placetype":"venue"
},
  "geometry": {"coordinates":[3.2887101173,51.3489112854],"type":"Point"}
}