{
  "type": "Feature",
  "properties": {
    "addr:full":"Rue Pierre-joseph Dum\u00e9nil 7 Box 12 Mons Hainaut 7000",
    "addr:housenumber":"7 box 12",
    "addr:postcode":"7000",
    "addr:street":"Rue Pierre-Joseph Dume\u0301Nil;Hainaut",
    "iso:country":"BE",
    "sg:address":"Rue Pierre-joseph Dum\u00e9nil 7 Box 12",
    "sg:city":"Mons",
    "sg:classifiers":[
        {
            "category":"Real Estate",
            "subcategory":"Architect",
            "type":"Services"
        }
    ],
    "sg:phone":"+32 65 33 81 67",
    "sg:postcode":"7000",
    "sg:province":"Hainaut",
    "wof:name":"Conseil De L'ordre Des Architectes De La Province De Hainaut",
    "wof:placetype":"venue"
},
  "geometry": {"coordinates":[3.9559180737,50.4601325989],"type":"Point"}
}