{
  "type": "Feature",
  "properties": {
    "iso:country":"BE",
    "sg:address":"Rue Du Tr\u00d4ne 125",
    "sg:city":"Elsene/ixelles",
    "sg:classifiers":[
        {
            "category":"Organizations",
            "subcategory":"Community Association",
            "type":"Services"
        }
    ],
    "sg:phone":"+32 2 507 88 33",
    "sg:postcode":"1050",
    "sg:province":"Bruxelles-Capitale",
    "sg:tags":[
        "organisation"
    ],
    "wof:name":"Jefi Jeugdfilmdienst",
    "wof:placetype":"venue"
},
  "geometry": {"coordinates":[4.370598793,50.8363304138],"type":"Point"}
}