{
  "type": "Feature",
  "properties": {
    "addr:full":"Avenue Royale 20 Mouscron Hainaut 7700",
    "addr:housenumber":"20",
    "addr:postcode":"7700",
    "addr:street":"Avenue Royale",
    "iso:country":"BE",
    "sg:address":"Avenue Royale 20",
    "sg:city":"Mouscron",
    "sg:classifiers":[
        {
            "category":"Building & Trades",
            "subcategory":"Construction",
            "type":"Services"
        }
    ],
    "sg:phone":"+32 495 20 99 93",
    "sg:postcode":"7700",
    "sg:province":"Hainaut",
    "sg:tags":[
        "installation",
        "-",
        "central",
        "heating"
    ],
    "wof:name":"Le F\u00e8vre Fr\u00e9d\u00e9ric Sprl",
    "wof:placetype":"venue"
},
  "geometry": {"coordinates":[3.2201499939,50.7461128235],"type":"Point"}
}