{
  "type": "Feature",
  "properties": {
    "addr:full":"Rommersheide F 8 Brecht Antwerpen 2960",
    "addr:housenumber":"8",
    "addr:postcode":"2960",
    "iso:country":"BE",
    "sg:address":"Rommersheide F 8",
    "sg:city":"Brecht",
    "sg:orig_category":"Clubs de sport. Ecoles de pilotage de bateaux and d\u00b4avions",
    "sg:phone":"+32 3 663 11 55",
    "sg:postcode":"2960",
    "sg:province":"Antwerpen",
    "wof:name":"Aero Club Van Brasschaat",
    "wof:placetype":"venue"
},
  "geometry": {"coordinates":[4.5660538673,51.3210906982],"type":"Point"}
}