{
  "type": "Feature",
  "properties": {
    "iso:country":"BE",
    "sg:address":"Rue Du March\u00e9 Aux Herbes 60",
    "sg:city":"Bruxelles",
    "sg:classifiers":[
        {
            "category":"Shopping",
            "subcategory":"Hobbies, Toys, & Games",
            "type":"Retail Goods"
        }
    ],
    "sg:phone":"+32 2 512 48 93",
    "sg:postcode":"1000",
    "sg:province":"Bruxelles-Capitale",
    "sg:tags":[
        "toy",
        "-"
    ],
    "wof:name":"Brand Sprl",
    "wof:placetype":"venue"
},
  "geometry": {"coordinates":[4.3532562256,50.84740448],"type":"Point"}
}