{
  "type": "Feature",
  "properties": {
    "iso:country":"BE",
    "sg:address":"Boulevard Des Fusill\u00e9s 9",
    "sg:city":"Renaix",
    "sg:orig_category":"Non-Classified Establishments",
    "sg:phone":"+32 55 21 13 48",
    "sg:postcode":"9600",
    "sg:province":"Oost-Vlaanderen",
    "wof:name":"De Visscher E",
    "wof:placetype":"venue"
},
  "geometry": {"coordinates":[3.5974090099,50.7426795959],"type":"Point"}
}