{
  "type": "Feature",
  "properties": {
    "iso:country":"BE",
    "sg:address":"Mechelsesteenweg 14",
    "sg:city":"Antwerpen",
    "sg:classifiers":[
        {
            "category":"Shopping",
            "subcategory":"Jewelry",
            "type":"Retail Goods"
        }
    ],
    "sg:phone":"+32 3 707 22 32",
    "sg:postcode":"2000",
    "sg:province":"Antwerpen",
    "sg:tags":[
        "-",
        "imitation"
    ],
    "wof:name":"Anthony Vof",
    "wof:placetype":"venue"
},
  "geometry": {"coordinates":[4.4073958397,51.2115287781],"type":"Point"}
}