{
  "type": "Feature",
  "properties": {
    "addr:full":"Rue Xavier De Bue 37 Bruxelles (uccle) Bruxelles-Capitale 1180",
    "addr:housenumber":"37",
    "addr:postcode":"1180",
    "addr:street":"Rue Xavier De Bue",
    "iso:country":"BE",
    "sg:address":"Rue Xavier De Bue 37",
    "sg:city":"Bruxelles (uccle)",
    "sg:classifiers":[
        {
            "category":"Food & Beverages",
            "subcategory":"Meat & Fish",
            "type":"Retail Goods"
        }
    ],
    "sg:phone":"+32 2 344 99 45",
    "sg:postcode":"1180",
    "sg:province":"Bruxelles-Capitale",
    "sg:tags":[
        "poultry",
        "whol",
        "game",
        "-"
    ],
    "wof:name":"Cabus Maison",
    "wof:placetype":"venue"
},
  "geometry": {"coordinates":[4.337182045,50.8032951355],"type":"Point"}
}