{
  "type": "Feature",
  "properties": {
    "addr:full":"De Keer 15 Wommelgem Antwerpen 2160",
    "addr:housenumber":"15",
    "addr:postcode":"2160",
    "addr:street":"De",
    "iso:country":"BE",
    "sg:address":"De Keer 15",
    "sg:city":"Wommelgem",
    "sg:orig_category":"Afbraak- and draineerwerken",
    "sg:phone":"+32 3 353 14 67",
    "sg:postcode":"2160",
    "sg:province":"Antwerpen",
    "wof:name":"Afbraakwerken J. Verheyen",
    "wof:placetype":"venue"
},
  "geometry": {"coordinates":[4.5408921242,51.2129821777],"type":"Point"}
}