{
  "type": "Feature",
  "properties": {
    "addr:full":"Avenue Du Centenaire 6 Beauvechain (hamme-mille) Brabant Wallon 1320",
    "addr:housenumber":"6",
    "addr:postcode":"1320",
    "addr:street":"Avenue Du Centenaire",
    "iso:country":"BE",
    "sg:address":"Avenue Du Centenaire 6",
    "sg:city":"Beauvechain (hamme-mille)",
    "sg:classifiers":[
        {
            "category":"Retail",
            "subcategory":"Auto Repair",
            "type":"Services"
        }
    ],
    "sg:phone":"+32 10 86 60 92",
    "sg:postcode":"1320",
    "sg:province":"Brabant Wallon",
    "sg:tags":[
        "automobile-body"
    ],
    "wof:name":"Gar C Cornelis & Fils Sprl",
    "wof:placetype":"venue"
},
  "geometry": {"coordinates":[4.7165470123,50.7787590027],"type":"Point"}
}