{
  "type": "Feature",
  "properties": {
    "addr:full":"Hullekenstraat 15 Dendermonde Oost-Vlaanderen 9200",
    "addr:housenumber":"15",
    "addr:postcode":"9200",
    "addr:street":"Hullekenstraat;Oost-Vlaanderen",
    "iso:country":"BE",
    "sg:address":"Hullekenstraat 15",
    "sg:city":"Dendermonde",
    "sg:orig_category":"Artiesten and kunstenaars Herstelling and restauratie van meubelen",
    "sg:phone":"+32 52 21 24 89",
    "sg:postcode":"9200",
    "sg:province":"Oost-Vlaanderen",
    "wof:name":"Huis Joos",
    "wof:placetype":"venue"
},
  "geometry": {"coordinates":[4.1161231995,51.0237007141],"type":"Point"}
}