{
  "type": "Feature",
  "properties": {
    "iso:country":"BE",
    "sg:address":"Rue Du Trieu Du Loup 73",
    "sg:city":"Cerfontaine",
    "sg:orig_category":"Installation de menuiserie en bois and plastique",
    "sg:phone":"+32 71 64 47 12",
    "sg:postcode":"5630",
    "sg:province":"Namur",
    "wof:name":"Charles Janssens",
    "wof:placetype":"venue"
},
  "geometry": {"coordinates":[4.4688630104,50.1740875244],"type":"Point"}
}