{
  "type": "Feature",
  "properties": {
    "addr:full":"Pl.franklin D. Roosevelt 6 Courcelles Hainaut 6180",
    "addr:housenumber":"6",
    "addr:postcode":"6180",
    "addr:street":"Roosevelt",
    "iso:country":"BE",
    "sg:address":"Pl.franklin D. Roosevelt 6",
    "sg:city":"Courcelles",
    "sg:orig_category":"Pharmaciens",
    "sg:phone":"+32 71 45 01 67",
    "sg:postcode":"6180",
    "sg:province":"Hainaut",
    "wof:name":"Multipharma",
    "wof:placetype":"venue"
},
  "geometry": {"coordinates":[4.379802227,50.4604148865],"type":"Point"}
}