{
  "type": "Feature",
  "properties": {
    "addr:full":"Kouterbaan 18 Lebbeke Oost-Vlaanderen 9280",
    "addr:housenumber":"18",
    "addr:postcode":"9280",
    "addr:street":"Kouterbaan",
    "iso:country":"BE",
    "sg:address":"Kouterbaan 18",
    "sg:city":"Lebbeke",
    "sg:orig_category":"HUISBRANDOLIE",
    "sg:phone":"+32 475 97 93 93",
    "sg:postcode":"9280",
    "sg:province":"Oost-Vlaanderen",
    "wof:name":"Dendermazout",
    "wof:placetype":"venue"
},
  "geometry": {"coordinates":[4.1209869385,50.997795105],"type":"Point"}
}