{
  "type": "Feature",
  "properties": {
    "addr:full":"Sint-pieterstraat 14 Izegem West-Vlaanderen 8870",
    "addr:housenumber":"14",
    "addr:postcode":"8870",
    "addr:street":"Sint-Pieterstraat",
    "iso:country":"BE",
    "sg:address":"Sint-pieterstraat 14",
    "sg:city":"Izegem",
    "sg:orig_category":"Cr\u00e9meries",
    "sg:phone":"+32 51 30 05 40",
    "sg:postcode":"8870",
    "sg:province":"West-Vlaanderen",
    "wof:name":"Claerhout",
    "wof:placetype":"venue"
},
  "geometry": {"coordinates":[3.2143270969,50.9159622192],"type":"Point"}
}