{
  "type": "Feature",
  "properties": {
    "iso:country":"BE",
    "sg:address":"Avenue Du Grand Cortil 42",
    "sg:city":"Ottignies-louvain-la-neuve (louvain-la-neuve)",
    "sg:classifiers":[
        {
            "category":"Health Services",
            "subcategory":"Health Practitioner",
            "type":"Services"
        }
    ],
    "sg:phone":"+32 479 44 84 16",
    "sg:postcode":"1348",
    "sg:province":"Brabant Wallon",
    "sg:tags":[
        "physiotherapist"
    ],
    "wof:name":"Lequeux Charlotte",
    "wof:placetype":"venue"
},
  "geometry": {"coordinates":[4.6043410301,50.6680526733],"type":"Point"}
}