{
  "type": "Feature",
  "properties": {
    "addr:full":"Hertogstraat 155 Box 301 Leuven (heverlee) Vlaams-Brabant 3001",
    "addr:housenumber":"155;301",
    "addr:postcode":"3001",
    "addr:street":"Hertogstraat;Box",
    "iso:country":"BE",
    "sg:address":"Hertogstraat 155 Box 301",
    "sg:city":"Leuven (heverlee)",
    "sg:classifiers":[
        {
            "category":"Professional",
            "subcategory":"Art Services",
            "type":"Services"
        }
    ],
    "sg:phone":"+32 16 40 41 00",
    "sg:postcode":"3001",
    "sg:province":"Vlaams-Brabant",
    "sg:tags":[
        "interior",
        "designer"
    ],
    "wof:name":"Weemaels B",
    "wof:placetype":"venue"
},
  "geometry": {"coordinates":[4.7001390457,50.859287262],"type":"Point"}
}