{
  "type": "Feature",
  "properties": {
    "iso:country":"BE",
    "sg:address":"Hagelkruisakker 50",
    "sg:city":"Wuustwezel",
    "sg:classifiers":[
        {
            "category":"Health Services",
            "subcategory":"Doctor",
            "type":"Services"
        }
    ],
    "sg:phone":"+32 3 669 84 45",
    "sg:postcode":"2990",
    "sg:province":"Antwerpen",
    "sg:tags":[
        "psychotherapist",
        "psychoanalyst"
    ],
    "wof:name":"Sekwens",
    "wof:placetype":"venue"
},
  "geometry": {"coordinates":[4.5951700211,51.3929481506],"type":"Point"}
}