{
  "type": "Feature",
  "properties": {
    "addr:full":"Helkijnstraat 47 Box 2 Zwevegem (sint-denijs) West-Vlaanderen 8554",
    "addr:housenumber":"47;2",
    "addr:postcode":"8554",
    "addr:street":"Helkijnstraat;Box",
    "iso:country":"BE",
    "sg:address":"Helkijnstraat 47 Box 2",
    "sg:city":"Zwevegem (sint-denijs)",
    "sg:classifiers":[
        {
            "category":"Banks & Credit Unions",
            "subcategory":"Bank",
            "type":"Services"
        }
    ],
    "sg:phone":"+32 56 45 64 37",
    "sg:postcode":"8554",
    "sg:province":"West-Vlaanderen",
    "sg:tags":[
        "savings-banks"
    ],
    "wof:name":"Mercator Bank",
    "wof:placetype":"venue"
},
  "geometry": {"coordinates":[3.3706920147,50.7496185303],"type":"Point"}
}