{
  "type": "Feature",
  "properties": {
    "iso:country":"BE",
    "sg:address":"Hoogstraat 16",
    "sg:city":"Beringen",
    "sg:orig_category":"Enseignement maternel and primaire",
    "sg:phone":"+32 11 42 55 29",
    "sg:postcode":"3580",
    "sg:province":"Limburg",
    "wof:name":"Vrije Basisschool",
    "wof:placetype":"venue"
},
  "geometry": {"coordinates":[5.2227911949,51.0480995178],"type":"Point"}
}