{
  "type": "Feature",
  "properties": {
    "addr:full":"Molensteenstraat 4 Bierbeek Vlaams-Brabant 3360",
    "addr:housenumber":"4",
    "addr:postcode":"3360",
    "addr:street":"Molensteenstraat",
    "iso:country":"BE",
    "sg:address":"Molensteenstraat 4",
    "sg:city":"Bierbeek",
    "sg:classifiers":[
        {
            "category":"Retail",
            "subcategory":"Veterinary Services",
            "type":"Services"
        }
    ],
    "sg:phone":"+32 16 73 51 27",
    "sg:postcode":"3360",
    "sg:province":"Vlaams-Brabant",
    "sg:tags":[
        "veterinarian"
    ],
    "wof:name":"Scarceriaux P",
    "wof:placetype":"venue"
},
  "geometry": {"coordinates":[4.8036899567,50.8176803589],"type":"Point"}
}