{
  "type": "Feature",
  "properties": {
    "iso:country":"BE",
    "sg:address":"Boulevard Anspach 126",
    "sg:city":"Brussel/bruxelles",
    "sg:orig_category":"Boekhandels Restaurants",
    "sg:phone":"+32 2 513 01 86",
    "sg:postcode":"1000",
    "sg:province":"Bruxelles-Capitale",
    "wof:name":"Jem Diffusion",
    "wof:placetype":"venue"
},
  "geometry": {"coordinates":[4.348405838,50.8469581604],"type":"Point"}
}