{
  "type": "Feature",
  "properties": {
    "addr:full":"Jubelfeestlaan 141 Sint-jans-molenbeek Bruxelles-Capitale 1080",
    "addr:housenumber":"141",
    "addr:postcode":"1080",
    "addr:street":"Jubelfeestlaan",
    "iso:country":"BE",
    "sg:address":"Jubelfeestlaan 141",
    "sg:city":"Sint-jans-molenbeek",
    "sg:orig_category":"V\u00eatements",
    "sg:phone":"+32 2 428 34 34",
    "sg:postcode":"1080",
    "sg:province":"Bruxelles-Capitale",
    "wof:name":"Trade Fashion",
    "wof:placetype":"venue"
},
  "geometry": {"coordinates":[4.3402791023,50.8667831421],"type":"Point"}
}