{
  "type": "Feature",
  "properties": {
    "iso:country":"BE",
    "sg:address":"Bellaertstraat 87",
    "sg:city":"Lede",
    "sg:orig_category":"Dierenartsen",
    "sg:phone":"+32 53 80 01 39",
    "sg:postcode":"9340",
    "sg:province":"Oost-Vlaanderen",
    "wof:name":"Alain Vijverman",
    "wof:placetype":"venue"
},
  "geometry": {"coordinates":[3.9828240871,50.9608917236],"type":"Point"}
}