{
  "type": "Feature",
  "properties": {
    "addr:full":"Pontweg 57 Lokeren Oost-Vlaanderen 9160",
    "addr:housenumber":"57",
    "addr:postcode":"9160",
    "addr:street":"Pontweg",
    "iso:country":"BE",
    "sg:address":"Pontweg 57",
    "sg:city":"Lokeren",
    "sg:classifiers":[
        {
            "category":"Professional",
            "subcategory":"Accounting & Tax Preparation",
            "type":"Services"
        }
    ],
    "sg:phone":"+32 9 348 60 80",
    "sg:postcode":"9160",
    "sg:province":"Oost-Vlaanderen",
    "sg:tags":[
        "accountant"
    ],
    "wof:name":"Loufs E",
    "wof:placetype":"venue"
},
  "geometry": {"coordinates":[3.9971160889,51.1306648254],"type":"Point"}
}