{
  "type": "Feature",
  "properties": {
    "iso:country":"BE",
    "sg:address":"Boulevard Jean-de-wilde 67",
    "sg:city":"Li\u00c8ge",
    "sg:orig_category":"Benzinestations and brandstoffen Herstellingen and onderhoud van auto's",
    "sg:phone":"+32 4 225 18 88",
    "sg:postcode":"4000",
    "sg:province":"Li\u00e8ge",
    "wof:name":"Garage Guzzo Angelo",
    "wof:placetype":"venue"
},
  "geometry": {"coordinates":[5.5675210953,50.661693573],"type":"Point"}
}