{
  "type": "Feature",
  "properties": {
    "iso:country":"BE",
    "sg:address":"Jef Buyckxstraat 40",
    "sg:city":"Turnhout",
    "sg:orig_category":"Plaatsen van vloer- and muurbekleding Schilders",
    "sg:phone":"+32 14 42 31 30",
    "sg:postcode":"2300",
    "sg:province":"Antwerpen",
    "wof:name":"Willy Evrard",
    "wof:placetype":"venue"
},
  "geometry": {"coordinates":[4.9320502281,51.3072891235],"type":"Point"}
}