{
  "type": "Feature",
  "properties": {
    "iso:country":"BE",
    "sg:address":"Rue Des Montis 10",
    "sg:city":"Anhee",
    "sg:orig_category":"Woningbouw",
    "sg:phone":"+32 82 69 95 88",
    "sg:postcode":"5537",
    "sg:province":"Namur",
    "wof:name":"Pierre Bouffioux",
    "wof:placetype":"venue"
},
  "geometry": {"coordinates":[4.7471451759,50.3016967773],"type":"Point"}
}