{
  "type": "Feature",
  "properties": {
    "addr:full":"Parkstraat 31 Sint-niklaas Oost-Vlaanderen 9100",
    "addr:housenumber":"31",
    "addr:postcode":"9100",
    "addr:street":"Parkstraat",
    "iso:country":"BE",
    "sg:address":"Parkstraat 31",
    "sg:city":"Sint-niklaas",
    "sg:classifiers":[
        {
            "category":"Shopping",
            "subcategory":"Stationery & Office Supplies",
            "type":"Retail Goods"
        }
    ],
    "sg:phone":"+32 3 776 64 15",
    "sg:postcode":"9100",
    "sg:province":"Oost-Vlaanderen",
    "sg:tags":[
        "-"
    ],
    "wof:name":"Van Der Borght Bvba",
    "wof:placetype":"venue"
},
  "geometry": {"coordinates":[4.144616127,51.161655426],"type":"Point"}
}