{
  "type": "Feature",
  "properties": {
    "iso:country":"BE",
    "sg:address":"Rue De Luxembourg 85",
    "sg:city":"Marche-en-famenne",
    "sg:orig_category":"Assistances juridiques. Conseillers fiscaux",
    "sg:phone":"+32 84 31 32 48",
    "sg:postcode":"6900",
    "sg:province":"Luxembourg",
    "wof:name":"Mollers A.",
    "wof:placetype":"venue"
},
  "geometry": {"coordinates":[5.3454070091,50.220954895],"type":"Point"}
}