{
  "type": "Feature",
  "properties": {
    "addr:full":"Place Du Nord Michel Levie Charleroi Hainaut 6000",
    "addr:postcode":"6000",
    "addr:street":"Place Du Nord Michel",
    "iso:country":"BE",
    "sg:address":"Place Du Nord Michel Levie",
    "sg:city":"Charleroi",
    "sg:classifiers":[
        {
            "category":"Bakery",
            "type":"Food & Drink"
        }
    ],
    "sg:phone":"+32 71 42 25 04",
    "sg:postcode":"6000",
    "sg:province":"Hainaut",
    "sg:tags":[
        "confectioner",
        "baker"
    ],
    "wof:name":"Vertommen",
    "wof:placetype":"venue"
},
  "geometry": {"coordinates":[4.4575600624,50.4229660034],"type":"Point"}
}