{
  "type": "Feature",
  "properties": {
    "iso:country":"BE",
    "sg:address":"Bogaardestraat 72",
    "sg:city":"Maldegem",
    "sg:orig_category":"Boucheries",
    "sg:phone":"+32 50 71 10 60",
    "sg:postcode":"9990",
    "sg:province":"Oost-Vlaanderen",
    "wof:name":"Eric De Backer",
    "wof:placetype":"venue"
},
  "geometry": {"coordinates":[3.439344883,51.2071914673],"type":"Point"}
}