{
  "type": "Feature",
  "properties": {
    "addr:full":"Warandestraat 34 Gooik Vlaams-Brabant 1755",
    "addr:housenumber":"34",
    "addr:postcode":"1755",
    "addr:street":"Warandestraat",
    "iso:country":"BE",
    "sg:address":"Warandestraat 34",
    "sg:city":"Gooik",
    "sg:classifiers":[
        {
            "category":"Travel",
            "subcategory":"Hotels & Motels",
            "type":"Entertainment"
        }
    ],
    "sg:phone":"+32 54 56 61 04",
    "sg:postcode":"1755",
    "sg:province":"Vlaams-Brabant",
    "sg:tags":[
        "pension"
    ],
    "wof:name":"Hoevehotel Warandehof",
    "wof:placetype":"venue"
},
  "geometry": {"coordinates":[4.0752477646,50.7743759155],"type":"Point"}
}