{
  "type": "Feature",
  "properties": {
    "addr:full":"Weg Naar As 54 Box 12 Genk Limburg 3600",
    "addr:housenumber":"54 box 12",
    "addr:postcode":"3600",
    "addr:street":"Weg Naar As",
    "iso:country":"BE",
    "sg:address":"Weg Naar As 54 Box 12",
    "sg:city":"Genk",
    "sg:classifiers":[
        {
            "category":"Health Services",
            "subcategory":"Hospital",
            "type":"Services"
        }
    ],
    "sg:phone":"+32 89 32 97 72",
    "sg:postcode":"3600",
    "sg:province":"Limburg",
    "wof:name":"Medisch-sociaal Opvangcentrum Voor Drugverslaafden Limburg",
    "wof:placetype":"venue"
},
  "geometry": {"coordinates":[5.5110201836,50.9685668945],"type":"Point"}
}