{
  "type": "Feature",
  "properties": {
    "iso:country":"BE",
    "sg:address":"Aarschotsesteenweg 152",
    "sg:city":"Tienen",
    "sg:orig_category":"Charpentes and couvertures",
    "sg:phone":"+32 16 81 49 22",
    "sg:postcode":"3300",
    "sg:province":"Vlaams-Brabant",
    "wof:name":"Maupin S",
    "wof:placetype":"venue"
},
  "geometry": {"coordinates":[4.9264202118,50.816696167],"type":"Point"}
}