{
  "type": "Feature",
  "properties": {
    "iso:country":"BE",
    "sg:address":"Van Benedenlaan 26",
    "sg:city":"Mechelen",
    "sg:orig_category":"Banken and kredietinstellingen",
    "sg:phone":"+32 15 40 93 22",
    "sg:postcode":"2800",
    "sg:province":"Antwerpen",
    "wof:name":"Fortis",
    "wof:placetype":"venue"
},
  "geometry": {"coordinates":[4.4747290611,51.0211906433],"type":"Point"}
}