{
  "type": "Feature",
  "properties": {
    "addr:full":"Chauss\u00c9e Brunehaut 401 Beloeil Hainaut 7972",
    "addr:housenumber":"401",
    "addr:postcode":"7972",
    "addr:street":"Chausse\u0301E Brunehaut",
    "iso:country":"BE",
    "sg:address":"Chauss\u00c9e Brunehaut 401",
    "sg:city":"Beloeil",
    "sg:orig_category":"Boucheries",
    "sg:phone":"+32 69 68 92 81",
    "sg:postcode":"7972",
    "sg:province":"Hainaut",
    "wof:name":"G. Wanwert",
    "wof:placetype":"venue"
},
  "geometry": {"coordinates":[3.690320015,50.5523414612],"type":"Point"}
}