{
  "type": "Feature",
  "properties": {
    "iso:country":"BE",
    "sg:address":"Bredabaan 186",
    "sg:city":"Brasschaat",
    "sg:orig_category":"Journaux. Tabac",
    "sg:phone":"+32 3 651 84 85",
    "sg:postcode":"2930",
    "sg:province":"Antwerpen",
    "wof:name":"Attache",
    "wof:placetype":"venue"
},
  "geometry": {"coordinates":[4.4872980118,51.2881851196],"type":"Point"}
}