{
  "type": "Feature",
  "properties": {
    "addr:full":"Archiefstraat 34 Watermaal-bosvoorde/watermael-boitsfort Bruxelles-Capitale 1170",
    "addr:housenumber":"34",
    "addr:postcode":"1170",
    "addr:street":"Archiefstraat",
    "iso:country":"BE",
    "sg:address":"Archiefstraat 34",
    "sg:city":"Watermaal-bosvoorde/watermael-boitsfort",
    "sg:orig_category":"Sportclubs",
    "sg:phone":"+32 2 672 22 70",
    "sg:postcode":"1170",
    "sg:province":"Bruxelles-Capitale",
    "wof:name":"H.c. Woluwe St.pierre",
    "wof:placetype":"venue"
},
  "geometry": {"coordinates":[4.4038739204,50.7986106873],"type":"Point"}
}