{
  "type": "Feature",
  "properties": {
    "addr:full":"Vindictivelaan 10 Oostende West-Vlaanderen 8400",
    "addr:housenumber":"10",
    "addr:postcode":"8400",
    "addr:street":"Vindictivelaan",
    "iso:country":"BE",
    "sg:address":"Vindictivelaan 10",
    "sg:city":"Oostende",
    "sg:classifiers":[
        {
            "category":"Communications",
            "subcategory":"Film & Video Production",
            "type":"Services"
        }
    ],
    "sg:phone":"+32 59 80 56 49",
    "sg:postcode":"8400",
    "sg:province":"West-Vlaanderen",
    "sg:tags":[
        "platen",
        "cassette",
        "cd's"
    ],
    "wof:name":"Compact Center Mercator",
    "wof:placetype":"venue"
},
  "geometry": {"coordinates":[2.9195520878,51.2276878357],"type":"Point"}
}