{
  "type": "Feature",
  "properties": {
    "iso:country":"BE",
    "sg:address":"Avenue Des Alli\u00c9s 26",
    "sg:city":"Charleroi",
    "sg:orig_category":"Mobilier and \u00e9quipement m\u00e9nager Librairies. Fournitures de bureau",
    "sg:phone":"+32 71 32 86 95",
    "sg:postcode":"6000",
    "sg:province":"Hainaut",
    "wof:name":"Alvan",
    "wof:placetype":"venue"
},
  "geometry": {"coordinates":[4.4389309883,50.4110107422],"type":"Point"}
}