{
  "type": "Feature",
  "properties": {
    "iso:country":"BE",
    "sg:address":"Avenue Du Progr\u00c8s 19",
    "sg:city":"Ans",
    "sg:orig_category":"Equipements divers pour l\u00b4industrie Gr",
    "sg:phone":"+32 4 263 38 30",
    "sg:postcode":"4432",
    "sg:province":"Li\u00e8ge",
    "wof:name":"Staf Oerlikon",
    "wof:placetype":"venue"
},
  "geometry": {"coordinates":[5.5307908058,50.6721878052],"type":"Point"}
}