{
  "type": "Feature",
  "properties": {
    "iso:country":"BE",
    "sg:address":"Rue De Bois D'haine 39",
    "sg:city":"La Louviere",
    "sg:orig_category":"Artsen and specialisten",
    "sg:phone":"+32 64 22 87 73",
    "sg:postcode":"7100",
    "sg:province":"Hainaut",
    "wof:name":"Emile Bonte",
    "wof:placetype":"venue"
},
  "geometry": {"coordinates":[4.1915230751,50.4550361633],"type":"Point"}
}