{
  "type": "Feature",
  "properties": {
    "iso:country":"BE",
    "sg:address":"Baljuwstraat 102",
    "sg:city":"Elsene/ixelles",
    "sg:orig_category":"Juwelen and horloges Verlichting and huishoudartikelen",
    "sg:phone":"+32 2 538 63 26",
    "sg:postcode":"1050",
    "sg:province":"Bruxelles-Capitale",
    "wof:name":"Maison Lune Apr\u00c8s Lune",
    "wof:placetype":"venue"
},
  "geometry": {"coordinates":[4.3591799736,50.8252601624],"type":"Point"}
}