{
  "type": "Feature",
  "properties": {
    "iso:country":"BE",
    "sg:address":"Rue Grande 62",
    "sg:city":"Couvin (br\u00fbly)",
    "sg:classifiers":[
        {
            "category":"Autos & Motor Vehicles",
            "subcategory":"Automobile Sales",
            "type":"Retail Goods"
        }
    ],
    "sg:phone":"+32 60 37 88 47",
    "sg:postcode":"5660",
    "sg:province":"Namur",
    "sg:tags":[
        "car",
        "used",
        "-"
    ],
    "wof:name":"Colinet Garage",
    "wof:placetype":"venue"
},
  "geometry": {"coordinates":[4.524928093,49.9697113037],"type":"Point"}
}