{
  "type": "Feature",
  "properties": {
    "iso:country":"BE",
    "sg:address":"Parc De Hoctaisart 8",
    "sg:city":"Spa",
    "sg:orig_category":"Schoonmaakbedrijven and ongediertebestrijding",
    "sg:phone":"+32 87 77 32 51",
    "sg:postcode":"4900",
    "sg:province":"Li\u00e8ge",
    "wof:name":"Jean Schener",
    "wof:placetype":"venue"
},
  "geometry": {"coordinates":[5.8581118584,50.4765739441],"type":"Point"}
}