{
  "type": "Feature",
  "properties": {
    "addr:full":"Rue Georges Rodenbach 11 Tournai Hainaut 7500",
    "addr:housenumber":"11",
    "addr:postcode":"7500",
    "addr:street":"Rue Georges Rodenbach",
    "iso:country":"BE",
    "sg:address":"Rue Georges Rodenbach 11",
    "sg:city":"Tournai",
    "sg:classifiers":[
        {
            "category":"Retail",
            "subcategory":"Veterinary Services",
            "type":"Services"
        }
    ],
    "sg:phone":"+32 69 22 02 58",
    "sg:postcode":"7500",
    "sg:province":"Hainaut",
    "sg:tags":[
        "veterinarian"
    ],
    "wof:name":"Samain D",
    "wof:placetype":"venue"
},
  "geometry": {"coordinates":[3.3726539612,50.6124954224],"type":"Point"}
}