{
  "type": "Feature",
  "properties": {
    "iso:country":"BE",
    "sg:address":"Steenweg Op Turnhout 11b4",
    "sg:city":"Merksplas",
    "sg:orig_category":"Advocaten and juridische adviseurs",
    "sg:phone":"+32 14 63 42 00",
    "sg:postcode":"2330",
    "sg:province":"Antwerpen",
    "wof:name":"M. Mampay",
    "wof:placetype":"venue"
},
  "geometry": {"coordinates":[4.8651189804,51.3539161682],"type":"Point"}
}