{
  "type": "Feature",
  "properties": {
    "iso:country":"BE",
    "sg:address":"Avenue Leopold Iii 18",
    "sg:city":"Binche (bray)",
    "sg:classifiers":[
        {
            "category":"Building & Trades",
            "subcategory":"Cleaning & Sanitation",
            "type":"Services"
        }
    ],
    "sg:phone":"+32 64 33 12 20",
    "sg:postcode":"7130",
    "sg:province":"Hainaut",
    "sg:tags":[
        "-",
        "installation",
        "room",
        "clean",
        "supply"
    ],
    "wof:name":"Cleanroom Manufacturing System",
    "wof:placetype":"venue"
},
  "geometry": {"coordinates":[4.1644802094,50.4119110107],"type":"Point"}
}