{
  "type": "Feature",
  "properties": {
    "iso:country":"BE",
    "sg:address":"Rue Mont L\u00c9va 15",
    "sg:city":"Amay",
    "sg:orig_category":"Traitements param\u00e9dicaux",
    "sg:phone":"+32 85 31 32 48",
    "sg:postcode":"4540",
    "sg:province":"Li\u00e8ge",
    "wof:name":"Michel Resimont",
    "wof:placetype":"venue"
},
  "geometry": {"coordinates":[5.3180990219,50.5478668213],"type":"Point"}
}