{
  "type": "Feature",
  "properties": {
    "addr:full":"Rue De L\u00b4et\u00c9 100 Elsene/ixelles Bruxelles-Capitale 1050",
    "addr:housenumber":"100",
    "addr:postcode":"1050",
    "addr:street":"Rue De L\u00b4Ete\u0301",
    "iso:country":"BE",
    "sg:address":"Rue De L\u00b4et\u00c9 100",
    "sg:city":"Elsene/ixelles",
    "sg:orig_category":"Instituts pour adultes moins valides",
    "sg:phone":"+32 2 649 25 45",
    "sg:postcode":"1050",
    "sg:province":"Bruxelles-Capitale",
    "wof:name":"La Foresti\u00c8re",
    "wof:placetype":"venue"
},
  "geometry": {"coordinates":[4.3898229599,50.8182373047],"type":"Point"}
}