{
  "type": "Feature",
  "properties": {
    "addr:full":"Heiendestraat 52 Lokeren Oost-Vlaanderen 9160",
    "addr:housenumber":"52",
    "addr:postcode":"9160",
    "addr:street":"Heiendestraat",
    "iso:country":"BE",
    "sg:address":"Heiendestraat 52",
    "sg:city":"Lokeren",
    "sg:orig_category":"Boekhouders",
    "sg:phone":"+32 9 349 27 27",
    "sg:postcode":"9160",
    "sg:province":"Oost-Vlaanderen",
    "wof:name":"Helmut Vandenhove",
    "wof:placetype":"venue"
},
  "geometry": {"coordinates":[3.9528870583,51.083656311],"type":"Point"}
}