{
  "type": "Feature",
  "properties": {
    "addr:full":"Cesarlaan 11 Tongeren Limburg 3700",
    "addr:housenumber":"11",
    "addr:postcode":"3700",
    "addr:street":"Cesarlaan",
    "iso:country":"BE",
    "sg:address":"Cesarlaan 11",
    "sg:city":"Tongeren",
    "sg:orig_category":"Dierenartsen",
    "sg:phone":"+32 12 23 30 99",
    "sg:postcode":"3700",
    "sg:province":"Limburg",
    "wof:name":"Jozef Van Den Noortgate",
    "wof:placetype":"venue"
},
  "geometry": {"coordinates":[5.4617238045,50.7861366272],"type":"Point"}
}