{
  "type": "Feature",
  "properties": {
    "iso:country":"BE",
    "sg:address":"Salvatorstraat 20",
    "sg:city":"Hasselt",
    "sg:orig_category":"Enseignement sup\u00e9rieur",
    "sg:phone":"+32 11 28 82 60",
    "sg:postcode":"3500",
    "sg:province":"Limburg",
    "wof:name":"K.h.-dep. Gezondheidszorg",
    "wof:placetype":"venue"
},
  "geometry": {"coordinates":[5.344534874,50.9130706787],"type":"Point"}
}