{
  "type": "Feature",
  "properties": {
    "addr:full":"Rue Mont Coup\u00e9 3 Le Roeulx (ville-sur-haine) Hainaut 7070",
    "addr:housenumber":"3",
    "addr:postcode":"7070",
    "addr:street":"Rue Mont Coupe\u0301",
    "iso:country":"BE",
    "sg:address":"Rue Mont Coup\u00e9 3",
    "sg:city":"Le Roeulx (ville-sur-haine)",
    "sg:classifiers":[
        {
            "category":"Building & Trades",
            "subcategory":"Construction",
            "type":"Services"
        }
    ],
    "sg:phone":"+32 64 66 29 56",
    "sg:postcode":"7070",
    "sg:province":"Hainaut",
    "sg:tags":[
        "carpenter"
    ],
    "wof:name":"Bipli Sc",
    "wof:placetype":"venue"
},
  "geometry": {"coordinates":[4.0633740425,50.4961433411],"type":"Point"}
}