{
  "type": "Feature",
  "properties": {
    "addr:full":"Avenue Armand Huysmans 60 Elsene/ixelles Bruxelles-Capitale 1050",
    "addr:housenumber":"60",
    "addr:postcode":"1050",
    "addr:street":"Avenue Armand Huysmans",
    "iso:country":"BE",
    "sg:address":"Avenue Armand Huysmans 60",
    "sg:city":"Elsene/ixelles",
    "sg:orig_category":"Architectes",
    "sg:phone":"+32 2 648 20 92",
    "sg:postcode":"1050",
    "sg:province":"Bruxelles-Capitale",
    "wof:name":"Fe. Leloup D.ph.n.",
    "wof:placetype":"venue"
},
  "geometry": {"coordinates":[4.3864917755,50.8134155273],"type":"Point"}
}