{
  "type": "Feature",
  "properties": {
    "addr:full":"Fonteinestraat 33 Tielt West-Vlaanderen 8700",
    "addr:housenumber":"33",
    "addr:postcode":"8700",
    "addr:street":"Fonteinestraat",
    "iso:country":"BE",
    "sg:address":"Fonteinestraat 33",
    "sg:city":"Tielt",
    "sg:classifiers":[
        {
            "category":"Arena",
            "subcategory":"Sports Club",
            "type":"Entertainment"
        }
    ],
    "sg:phone":"+32 51 40 70 23",
    "sg:postcode":"8700",
    "sg:province":"West-Vlaanderen",
    "sg:tags":[
        "de"
    ],
    "wof:name":"Tieltse Zwemclub",
    "wof:placetype":"venue"
},
  "geometry": {"coordinates":[3.314496994,51.0006217957],"type":"Point"}
}