{
  "type": "Feature",
  "properties": {
    "addr:full":"Avenue De Maire 23 Tournai Hainaut 7500",
    "addr:housenumber":"23",
    "addr:postcode":"7500",
    "addr:street":"Avenue De Maire",
    "iso:country":"BE",
    "sg:address":"Avenue De Maire 23",
    "sg:city":"Tournai",
    "sg:orig_category":"Jeux and jouets",
    "sg:phone":"+32 69 22 57 57",
    "sg:postcode":"7500",
    "sg:province":"Hainaut",
    "wof:name":"Megaland",
    "wof:placetype":"venue"
},
  "geometry": {"coordinates":[3.3776459694,50.6132545471],"type":"Point"}
}