{
  "type": "Feature",
  "properties": {
    "iso:country":"BE",
    "sg:address":"Vaartstraat 4",
    "sg:city":"Genk",
    "sg:classifiers":[
        {
            "category":"Real Estate",
            "subcategory":"Developer",
            "type":"Services"
        }
    ],
    "sg:phone":"+32 89 30 35 58",
    "sg:postcode":"3600",
    "sg:province":"Limburg",
    "sg:tags":[
        "plomberie",
        "chauffage",
        "mat\u00e9riel",
        "gr",
        "pour"
    ],
    "wof:name":"Fa. Olymp-benelux",
    "wof:placetype":"venue"
},
  "geometry": {"coordinates":[5.471739769,50.9443206787],"type":"Point"}
}