{
  "type": "Feature",
  "properties": {
    "addr:full":"Beche 50 Vielsalm Luxembourg 6690",
    "addr:housenumber":"50",
    "addr:postcode":"6690",
    "addr:street":"Beche",
    "iso:country":"BE",
    "sg:address":"Beche 50",
    "sg:city":"Vielsalm",
    "sg:orig_category":"Herstellingen and onderhoud van auto's",
    "sg:phone":"+32 80 21 55 62",
    "sg:postcode":"6690",
    "sg:province":"Luxembourg",
    "wof:name":"Jean-marie Lesenfants",
    "wof:placetype":"venue"
},
  "geometry": {"coordinates":[5.9244952202,50.2652397156],"type":"Point"}
}