{
  "type": "Feature",
  "properties": {
    "addr:full":"Grand'place 38 Ath Hainaut 7800",
    "addr:housenumber":"38",
    "addr:postcode":"7800",
    "addr:street":"Grand'Place",
    "iso:country":"BE",
    "sg:address":"Grand'place 38",
    "sg:city":"Ath",
    "sg:classifiers":[
        {
            "category":"Bars & Pubs",
            "type":"Food & Drink"
        }
    ],
    "sg:phone":"+32 68 28 60 91",
    "sg:postcode":"7800",
    "sg:province":"Hainaut",
    "sg:tags":[
        "tavern"
    ],
    "wof:name":"La R\u00e9gence",
    "wof:placetype":"venue"
},
  "geometry": {"coordinates":[3.7767679691,50.6313171387],"type":"Point"}
}