{
  "type": "Feature",
  "properties": {
    "iso:country":"BE",
    "sg:address":"Quai Jean-baptiste-culot 5",
    "sg:city":"Dinant",
    "sg:orig_category":"M\u00e9decins and sp\u00e9cialistes",
    "sg:phone":"+32 82 22 48 66",
    "sg:postcode":"5500",
    "sg:province":"Namur",
    "wof:name":"G. Foss\u00c9",
    "wof:placetype":"venue"
},
  "geometry": {"coordinates":[4.9087572098,50.2631721497],"type":"Point"}
}