{
  "type": "Feature",
  "properties": {
    "iso:country":"BE",
    "sg:address":"Patatestraat 44",
    "sg:city":"Meise (wolvertem)",
    "sg:classifiers":[
        {
            "category":"Food & Beverages",
            "subcategory":"Dairy",
            "type":"Retail Goods"
        }
    ],
    "sg:phone":"+32 52 30 90 34",
    "sg:postcode":"1861",
    "sg:province":"Vlaams-Brabant",
    "sg:tags":[
        "product",
        "-"
    ],
    "wof:name":"Buggenhout M",
    "wof:placetype":"venue"
},
  "geometry": {"coordinates":[4.3267598152,50.9830207825],"type":"Point"}
}