{
  "type": "Feature",
  "properties": {
    "addr:full":"Woodrow Wilsonplein 244 Box 4 Gent Oost-Vlaanderen 9000",
    "addr:housenumber":"244;4",
    "addr:postcode":"9000",
    "addr:street":"Woodrow Wilsonplein;Box;Oost-Vlaanderen",
    "iso:country":"BE",
    "sg:address":"Woodrow Wilsonplein 244 Box 4",
    "sg:city":"Gent",
    "sg:classifiers":[
        {
            "category":"Bars & Pubs",
            "type":"Food & Drink"
        }
    ],
    "sg:phone":"+32 9 233 25 65",
    "sg:postcode":"9000",
    "sg:province":"Oost-Vlaanderen",
    "sg:tags":[
        "tavern"
    ],
    "wof:name":"'t Zuid (brasserie)",
    "wof:placetype":"venue"
},
  "geometry": {"coordinates":[3.7307770252,51.0483512878],"type":"Point"}
}