{
  "type": "Feature",
  "properties": {
    "addr:full":"Oliebergstraat 20 Zulte Oost-Vlaanderen 9870",
    "addr:housenumber":"20",
    "addr:postcode":"9870",
    "addr:street":"Oliebergstraat",
    "iso:country":"BE",
    "sg:address":"Oliebergstraat 20",
    "sg:city":"Zulte",
    "sg:orig_category":"Installatie van houten of kunststof schrijnwerk",
    "sg:phone":"+32 9 388 98 24",
    "sg:postcode":"9870",
    "sg:province":"Oost-Vlaanderen",
    "wof:name":"Daniel De Boever",
    "wof:placetype":"venue"
},
  "geometry": {"coordinates":[3.4619309902,50.9402656555],"type":"Point"}
}