{
  "type": "Feature",
  "properties": {
    "iso:country":"BE",
    "sg:address":"Petite Rue Du Moulin 1",
    "sg:city":"Perwijs",
    "sg:classifiers":[
        {
            "category":"Arena",
            "subcategory":"Sports Club",
            "type":"Entertainment"
        }
    ],
    "sg:phone":"+32 81 65 64 28",
    "sg:postcode":"1360",
    "sg:province":"Brabant Wallon",
    "sg:tags":[
        "de"
    ],
    "wof:name":"Orbais Cycliste - Orbais",
    "wof:placetype":"venue"
},
  "geometry": {"coordinates":[4.769920826,50.6444816589],"type":"Point"}
}