{
  "type": "Feature",
  "properties": {
    "iso:country":"BE",
    "sg:address":"Rue Du Moulin 6",
    "sg:city":"Soumagne",
    "sg:orig_category":"Location de biens divers. Equipement divers pour commerces Location de mat\u00e9riel pour banquets and \u00e9v",
    "sg:phone":"+32 4 377 17 08",
    "sg:postcode":"4630",
    "sg:province":"Li\u00e8ge",
    "wof:name":"Location Babette",
    "wof:placetype":"venue"
},
  "geometry": {"coordinates":[5.7539157867,50.61378479],"type":"Point"}
}