{
  "type": "Feature",
  "properties": {
    "addr:full":"Rue Arbre \u00e0 Limont 1 Lessines (papignies) Hainaut 7861",
    "addr:housenumber":"1",
    "addr:postcode":"7861",
    "addr:street":"Rue Arbre A\u0300 Limont",
    "iso:country":"BE",
    "sg:address":"Rue Arbre \u00e0 Limont 1",
    "sg:city":"Lessines (papignies)",
    "sg:classifiers":[
        {
            "category":"Real Estate",
            "subcategory":"Real Estate Services",
            "type":"Services"
        }
    ],
    "sg:phone":"+32 68 33 72 74",
    "sg:postcode":"7861",
    "sg:province":"Hainaut",
    "wof:name":"Demolder J-l",
    "wof:placetype":"venue"
},
  "geometry": {"coordinates":[3.773154974,50.6967849731],"type":"Point"}
}