{
  "type": "Feature",
  "properties": {
    "iso:country":"BE",
    "sg:address":"Hogeweg 136",
    "sg:city":"Menen",
    "sg:orig_category":"Instituts de beaut\u00e9",
    "sg:phone":"+32 56 51 52 80",
    "sg:postcode":"8930",
    "sg:province":"West-Vlaanderen",
    "wof:name":"Instituut Stragier",
    "wof:placetype":"venue"
},
  "geometry": {"coordinates":[3.1052310467,50.7964134216],"type":"Point"}
}