{
  "type": "Feature",
  "properties": {
    "addr:full":"Vlietestraat 12 Harelbeke West-Vlaanderen 8531",
    "addr:housenumber":"12",
    "addr:postcode":"8531",
    "addr:street":"Vlietestraat",
    "iso:country":"BE",
    "sg:address":"Vlietestraat 12",
    "sg:city":"Harelbeke",
    "sg:orig_category":"Pain, p\u00e2tisseries and confiseries",
    "sg:phone":"+32 56 71 31 61",
    "sg:postcode":"8531",
    "sg:province":"West-Vlaanderen",
    "wof:name":"Ronny Lapeirre",
    "wof:placetype":"venue"
},
  "geometry": {"coordinates":[3.3105568886,50.8760871887],"type":"Point"}
}