{
  "type": "Feature",
  "properties": {
    "iso:country":"BE",
    "sg:address":"Chauss\u00c9e De Bruxelles 90",
    "sg:city":"Wavre",
    "sg:orig_category":"Dakwerken",
    "sg:phone":"+32 10 22 81 71",
    "sg:postcode":"1300",
    "sg:province":"Brabant Wallon",
    "wof:name":"Ecotoiture",
    "wof:placetype":"venue"
},
  "geometry": {"coordinates":[4.6074099541,50.721824646],"type":"Point"}
}