{
  "type": "Feature",
  "properties": {
    "iso:country":"BE",
    "sg:address":"Deinsesteenweg 3",
    "sg:city":"Tielt",
    "sg:classifiers":[
        {
            "category":"Autos & Motor Vehicles",
            "subcategory":"Fuel & Gas Station",
            "type":"Retail Goods"
        }
    ],
    "sg:phone":"+32 51 40 21 95",
    "sg:postcode":"8700",
    "sg:province":"West-Vlaanderen",
    "wof:name":"Vandemaele F",
    "wof:placetype":"venue"
},
  "geometry": {"coordinates":[3.3489029408,50.9972953796],"type":"Point"}
}