{
  "type": "Feature",
  "properties": {
    "addr:full":"Rue Winston Churchill 281-283 Courcelles Hainaut 6180",
    "addr:postcode":"281-283;6180",
    "addr:street":"Rue Winston Churchill",
    "iso:country":"BE",
    "sg:address":"Rue Winston Churchill 281-283",
    "sg:city":"Courcelles",
    "sg:classifiers":[
        {
            "category":"Manufacturing",
            "subcategory":"Motor Vehicles & Parts",
            "type":"Manufacturing & Wholesale Goods"
        }
    ],
    "sg:phone":"+32 71 46 16 00",
    "sg:postcode":"6180",
    "sg:province":"Hainaut",
    "sg:tags":[
        "bearing"
    ],
    "wof:name":"Evrard C.m.",
    "wof:placetype":"venue"
},
  "geometry": {"coordinates":[4.393778801,50.4632415771],"type":"Point"}
}