{
  "type": "Feature",
  "properties": {
    "addr:full":"Praatstraat 5 Beernem (oedelem) West-Vlaanderen 8730",
    "addr:housenumber":"5",
    "addr:postcode":"8730",
    "addr:street":"Praatstraat",
    "iso:country":"BE",
    "sg:address":"Praatstraat 5",
    "sg:city":"Beernem (oedelem)",
    "sg:classifiers":[
        {
            "category":"Building & Trades",
            "subcategory":"Landscaping Services",
            "type":"Services"
        }
    ],
    "sg:phone":"+32 50 79 10 85",
    "sg:postcode":"8730",
    "sg:province":"West-Vlaanderen",
    "sg:tags":[
        "gardening",
        "garden",
        "maintenance"
    ],
    "wof:name":"Michielssens S",
    "wof:placetype":"venue"
},
  "geometry": {"coordinates":[3.3475859165,51.1838645935],"type":"Point"}
}