{
  "type": "Feature",
  "properties": {
    "addr:full":"Sluis 167a Mol Antwerpen 2400",
    "addr:housenumber":"167a",
    "addr:postcode":"2400",
    "addr:street":"Sluis",
    "iso:country":"BE",
    "sg:address":"Sluis 167a",
    "sg:city":"Mol",
    "sg:classifiers":[
        {
            "category":"Health Services",
            "subcategory":"Doctor",
            "type":"Services"
        }
    ],
    "sg:phone":"+32 14 31 37 73",
    "sg:postcode":"2400",
    "sg:province":"Antwerpen",
    "sg:tags":[
        "medicinephysicians",
        "surgeon"
    ],
    "wof:name":"Damen G",
    "wof:placetype":"venue"
},
  "geometry": {"coordinates":[5.1341900826,51.2111816406],"type":"Point"}
}