{
  "type": "Feature",
  "properties": {
    "addr:full":"Avenue Pr\u00c9 Des Agneaux 25 Oudergem/auderghem Bruxelles-Capitale 1160",
    "addr:housenumber":"25",
    "addr:postcode":"1160",
    "addr:street":"Avenue Pre\u0301 Des Agneaux;/",
    "iso:country":"BE",
    "sg:address":"Avenue Pr\u00c9 Des Agneaux 25",
    "sg:city":"Oudergem/auderghem",
    "sg:orig_category":"Pain, p\u00e2tisseries and confiseries",
    "sg:phone":"+32 2 673 36 16",
    "sg:postcode":"1160",
    "sg:province":"Bruxelles-Capitale",
    "wof:name":"Au Pays De L\u00b4epeautre",
    "wof:placetype":"venue"
},
  "geometry": {"coordinates":[4.4220170975,50.8108673096],"type":"Point"}
}