{
  "type": "Feature",
  "properties": {
    "addr:full":"Chauss\u00e9e D'houthem 142 Comines-warneton (houthem) Hainaut 7781",
    "addr:housenumber":"142",
    "addr:postcode":"7781",
    "addr:street":"Chausse\u0301E D'Houthem;Houthem Hainaut",
    "iso:country":"BE",
    "sg:address":"Chauss\u00e9e D'houthem 142",
    "sg:city":"Comines-warneton (houthem)",
    "sg:classifiers":[
        {
            "category":"Bakery",
            "type":"Food & Drink"
        }
    ],
    "sg:phone":"+32 56 55 59 61",
    "sg:postcode":"7781",
    "sg:province":"Hainaut",
    "sg:tags":[
        "confectioner",
        "baker"
    ],
    "wof:name":"Jos\u00e9 Et Nadia",
    "wof:placetype":"venue"
},
  "geometry": {"coordinates":[2.9642269611,50.7869949341],"type":"Point"}
}