{
  "type": "Feature",
  "properties": {
    "iso:country":"BE",
    "sg:address":"D'oultremontlei 28",
    "sg:city":"Brasschaat",
    "sg:orig_category":"V\u00eatements pour b\u00e9b\u00e9s and enfants",
    "sg:phone":"+32 3 651 64 09",
    "sg:postcode":"2930",
    "sg:province":"Antwerpen",
    "wof:name":"Jiff",
    "wof:placetype":"venue"
},
  "geometry": {"coordinates":[4.4612641335,51.291267395],"type":"Point"}
}