{
  "type": "Feature",
  "properties": {
    "addr:full":"Kasteelstraat 47 Antwerpen Antwerpen 2000",
    "addr:housenumber":"47",
    "addr:postcode":"2000",
    "addr:street":"Kasteelstraat",
    "iso:country":"BE",
    "sg:address":"Kasteelstraat 47",
    "sg:city":"Antwerpen",
    "sg:orig_category":"Services fun\u00e9raires",
    "sg:phone":"+32 3 234 23 74",
    "sg:postcode":"2000",
    "sg:province":"Antwerpen",
    "wof:name":"Begrafenissen Bogaers J.",
    "wof:placetype":"venue"
},
  "geometry": {"coordinates":[4.3924307823,51.2065582275],"type":"Point"}
}