{
  "type": "Feature",
  "properties": {
    "addr:full":"Rue St Remacle 5 Li\u00e8ge Li\u00e8ge 4020",
    "addr:housenumber":"5",
    "addr:postcode":"4020",
    "addr:street":"Rue St Remacle",
    "iso:country":"BE",
    "sg:address":"Rue St Remacle 5",
    "sg:city":"Li\u00e8ge",
    "sg:orig_category":"Agriculture and Livestock Dairy products Food and Related Products",
    "sg:phone":"+32 4 343 02 35",
    "sg:postcode":"4020",
    "sg:province":"Li\u00e8ge",
    "wof:name":"Marcel Jamin Sa",
    "wof:placetype":"venue"
},
  "geometry": {"coordinates":[5.5893149376,50.6370124817],"type":"Point"}
}