{
  "type": "Feature",
  "properties": {
    "iso:country":"BE",
    "sg:address":"Mont Des Arts 5",
    "sg:city":"Bruxelles",
    "sg:orig_category":"Agences de voyages",
    "sg:phone":"+32 2 511 92 09",
    "sg:postcode":"1000",
    "sg:province":"Bruxelles-Capitale",
    "wof:name":"Holidayland",
    "wof:placetype":"venue"
},
  "geometry": {"coordinates":[4.343392849,50.8433418274],"type":"Point"}
}