{
  "type": "Feature",
  "properties": {
    "addr:full":"Rue Fonds De For\u00eat 14 Fl\u00e9ron (magn\u00e9e) Li\u00e8ge 4623",
    "addr:housenumber":"14",
    "addr:postcode":"4623",
    "addr:street":"Rue Fonds De Fore\u0302T",
    "iso:country":"BE",
    "sg:address":"Rue Fonds De For\u00eat 14",
    "sg:city":"Fl\u00e9ron (magn\u00e9e)",
    "sg:classifiers":[
        {
            "category":"Professional",
            "subcategory":"Engineering",
            "type":"Services"
        }
    ],
    "sg:phone":"+32 4 355 87 50",
    "sg:postcode":"4623",
    "sg:province":"Li\u00e8ge",
    "sg:tags":[
        "technical",
        "industrial",
        "-",
        "subcontracting"
    ],
    "wof:name":"S T I Sa",
    "wof:placetype":"venue"
},
  "geometry": {"coordinates":[5.6838269234,50.6018867493],"type":"Point"}
}