{
  "type": "Feature",
  "properties": {
    "addr:full":"Steenweg 114ba Alken Limburg 3570",
    "addr:housenumber":"114ba",
    "addr:postcode":"3570",
    "addr:street":"Steenweg",
    "iso:country":"BE",
    "sg:address":"Steenweg 114ba",
    "sg:city":"Alken",
    "sg:classifiers":[
        {
            "category":"Communications",
            "subcategory":"Film & Video Production",
            "type":"Services"
        }
    ],
    "sg:phone":"+32 11 31 25 67",
    "sg:postcode":"3570",
    "sg:province":"Limburg",
    "sg:tags":[
        "platen",
        "cassette",
        "cd's"
    ],
    "wof:name":"Musicclub",
    "wof:placetype":"venue"
},
  "geometry": {"coordinates":[5.2907910347,50.8895874023],"type":"Point"}
}