{
  "type": "Feature",
  "properties": {
    "addr:full":"Drapstraat 78 Nazareth Oost-Vlaanderen 9810",
    "addr:housenumber":"78",
    "addr:postcode":"9810",
    "addr:street":"Drapstraat",
    "iso:country":"BE",
    "sg:address":"Drapstraat 78",
    "sg:city":"Nazareth",
    "sg:orig_category":"Enseignement maternel and primaire",
    "sg:phone":"+32 9 385 48 28",
    "sg:postcode":"9810",
    "sg:province":"Oost-Vlaanderen",
    "wof:name":"Gemeentelijke Basisschool",
    "wof:placetype":"venue"
},
  "geometry": {"coordinates":[3.6100161076,50.9583053589],"type":"Point"}
}