{
  "type": "Feature",
  "properties": {
    "addr:full":"Avenue Prince Baudouin 14 Wemmel/wemmel Vlaams-Brabant 1780",
    "addr:housenumber":"14",
    "addr:postcode":"1780",
    "addr:street":"Avenue Prince Baudouin",
    "iso:country":"BE",
    "sg:address":"Avenue Prince Baudouin 14",
    "sg:city":"Wemmel/wemmel",
    "sg:orig_category":"M\u00e9decins and sp\u00e9cialistes",
    "sg:phone":"+32 2 462 06 75",
    "sg:postcode":"1780",
    "sg:province":"Vlaams-Brabant",
    "wof:name":"Consultatiebur.jonge Kind",
    "wof:placetype":"venue"
},
  "geometry": {"coordinates":[4.3070898056,50.9067382812],"type":"Point"}
}