{
  "type": "Feature",
  "properties": {
    "addr:full":"Gasmeterstraat 32 Sint-niklaas Oost-Vlaanderen 9100",
    "addr:housenumber":"32",
    "addr:postcode":"9100",
    "addr:street":"Gasmeterstraat",
    "iso:country":"BE",
    "sg:address":"Gasmeterstraat 32",
    "sg:city":"Sint-niklaas",
    "sg:orig_category":"Jardinage",
    "sg:phone":"+32 3 776 17 92",
    "sg:postcode":"9100",
    "sg:province":"Oost-Vlaanderen",
    "wof:name":"Bureau Nerf",
    "wof:placetype":"venue"
},
  "geometry": {"coordinates":[4.1372117996,51.1700973511],"type":"Point"}
}