{
  "type": "Feature",
  "properties": {
    "iso:country":"BE",
    "sg:address":"Rue Cornuhaut 1",
    "sg:city":"Tournai",
    "sg:classifiers":[
        {
            "category":"Arena",
            "subcategory":"Sports Club",
            "type":"Entertainment"
        }
    ],
    "sg:phone":"+32 69 64 91 71",
    "sg:postcode":"7502",
    "sg:province":"Hainaut",
    "sg:tags":[
        "terrain",
        "hors",
        "de",
        "installation",
        "sportifs"
    ],
    "wof:name":"F.c. Esplechin",
    "wof:placetype":"venue"
},
  "geometry": {"coordinates":[3.3085699081,50.5760307312],"type":"Point"}
}