{
  "type": "Feature",
  "properties": {
    "iso:country":"BE",
    "sg:address":"Avenue Des Pinsons 6",
    "sg:city":"Waterloo",
    "sg:orig_category":"Fotografen and fotostudio's",
    "sg:phone":"+32 2 354 93 98",
    "sg:postcode":"1410",
    "sg:province":"Brabant Wallon",
    "wof:name":"Christian Verlent",
    "wof:placetype":"venue"
},
  "geometry": {"coordinates":[4.4007620811,50.7232475281],"type":"Point"}
}