{
  "type": "Feature",
  "properties": {
    "addr:full":"Kortrijksesteenweg 90f Sint-martens-latem Oost-Vlaanderen 9830",
    "addr:housenumber":"90f",
    "addr:postcode":"9830",
    "addr:street":"Kortrijksesteenweg",
    "iso:country":"BE",
    "sg:address":"Kortrijksesteenweg 90f",
    "sg:city":"Sint-martens-latem",
    "sg:classifiers":[
        {
            "category":"Professional",
            "subcategory":"Management & Consulting",
            "type":"Services"
        }
    ],
    "sg:phone":"+32 9 280 01 90",
    "sg:postcode":"9830",
    "sg:province":"Oost-Vlaanderen",
    "sg:tags":[
        "tax-consultants"
    ],
    "wof:name":"Heylens L",
    "wof:placetype":"venue"
},
  "geometry": {"coordinates":[3.6403179169,51.0120239258],"type":"Point"}
}