{
  "type": "Feature",
  "properties": {
    "addr:full":"Broekstraat 50 Destelbergen (heusden) Oost-Vlaanderen 9070",
    "addr:housenumber":"50",
    "addr:postcode":"9070",
    "addr:street":"Broekstraat",
    "iso:country":"BE",
    "sg:address":"Broekstraat 50",
    "sg:city":"Destelbergen (heusden)",
    "sg:classifiers":[
        {
            "category":"Manufacturing",
            "subcategory":"Textiles",
            "type":"Manufacturing & Wholesale Goods"
        }
    ],
    "sg:phone":"+32 9 231 74 75",
    "sg:postcode":"9070",
    "sg:province":"Oost-Vlaanderen",
    "sg:tags":[
        "machinery"
    ],
    "wof:name":"Altum Nv",
    "wof:placetype":"venue"
},
  "geometry": {"coordinates":[3.8254039288,51.0248985291],"type":"Point"}
}