{
  "type": "Feature",
  "properties": {
    "iso:country":"BE",
    "sg:address":"Weg Naar As 201",
    "sg:city":"Opglabbeek",
    "sg:orig_category":"Voertuigen",
    "sg:phone":"+32 89 85 88 88",
    "sg:postcode":"3660",
    "sg:province":"Limburg",
    "wof:name":"Garage Geebelen",
    "wof:placetype":"venue"
},
  "geometry": {"coordinates":[5.5814681053,51.0229911804],"type":"Point"}
}