{
  "type": "Feature",
  "properties": {
    "addr:full":"Rue Ferrer 197 Tubize Brabant Wallon 1480",
    "addr:housenumber":"197",
    "addr:postcode":"1480",
    "addr:street":"Rue Ferrer;Wallon",
    "iso:country":"BE",
    "sg:address":"Rue Ferrer 197",
    "sg:city":"Tubize",
    "sg:orig_category":"Poissonniers and \u00e9caillers",
    "sg:phone":"+32 2 355 55 36",
    "sg:postcode":"1480",
    "sg:province":"Brabant Wallon",
    "wof:name":"Andre Marin",
    "wof:placetype":"venue"
},
  "geometry": {"coordinates":[4.1943621635,50.6882324219],"type":"Point"}
}