{
  "type": "Feature",
  "properties": {
    "iso:country":"BE",
    "sg:address":"Kapelseweg 172",
    "sg:city":"Mechelen",
    "sg:orig_category":"Groententeelt",
    "sg:phone":"+32 15 42 35 87",
    "sg:postcode":"2811",
    "sg:province":"Antwerpen",
    "wof:name":"Albert Schillemans",
    "wof:placetype":"venue"
},
  "geometry": {"coordinates":[4.4055328369,51.0173606873],"type":"Point"}
}