{
  "type": "Feature",
  "properties": {
    "addr:full":"Kruishei 10 Geel Antwerpen 2440",
    "addr:housenumber":"10",
    "addr:postcode":"2440",
    "addr:street":"Kruishei",
    "iso:country":"BE",
    "sg:address":"Kruishei 10",
    "sg:city":"Geel",
    "sg:classifiers":[
        {
            "category":"Arena",
            "subcategory":"Sports Club",
            "type":"Entertainment"
        }
    ],
    "sg:phone":"+32 14 54 03 39",
    "sg:postcode":"2440",
    "sg:province":"Antwerpen",
    "sg:tags":[
        "de"
    ],
    "wof:name":"T.c. Sportec Geel",
    "wof:placetype":"venue"
},
  "geometry": {"coordinates":[4.9457411766,51.1021957397],"type":"Point"}
}