{
  "type": "Feature",
  "properties": {
    "addr:full":"Haantjeslei 68 Anvers (grand) Antwerpen 2018",
    "addr:housenumber":"68",
    "addr:postcode":"2018",
    "addr:street":"Haantjeslei;Grand Antwerpen",
    "iso:country":"BE",
    "sg:address":"Haantjeslei 68",
    "sg:city":"Anvers (grand)",
    "sg:orig_category":"Diverse bedrijfsbeheeradviesbureaus",
    "sg:phone":"+32 3 259 05 11",
    "sg:postcode":"2018",
    "sg:province":"Antwerpen",
    "wof:name":"Faceo Belgium",
    "wof:placetype":"venue"
},
  "geometry": {"coordinates":[4.3997302055,51.2025108337],"type":"Point"}
}