{
  "type": "Feature",
  "properties": {
    "addr:full":"Neerstraat 6 Lovendegem (vinderhoute) Oost-Vlaanderen 9921",
    "addr:housenumber":"6",
    "addr:postcode":"9921",
    "addr:street":"Neerstraat",
    "iso:country":"BE",
    "sg:address":"Neerstraat 6",
    "sg:city":"Lovendegem (vinderhoute)",
    "sg:classifiers":[
        {
            "category":"Professional",
            "subcategory":"Management & Consulting",
            "type":"Services"
        }
    ],
    "sg:phone":"+32 9 226 07 28",
    "sg:postcode":"9921",
    "sg:province":"Oost-Vlaanderen",
    "sg:tags":[
        "consultant"
    ],
    "wof:name":"Management Consultants R. Verpoest & Co Bvba",
    "wof:placetype":"venue"
},
  "geometry": {"coordinates":[3.6390209198,51.0880889893],"type":"Point"}
}