{
  "type": "Feature",
  "properties": {
    "addr:full":"Vyvestraat 22 Staden West-Vlaanderen 8840",
    "addr:housenumber":"22",
    "addr:postcode":"8840",
    "addr:street":"Vyvestraat",
    "iso:country":"BE",
    "sg:address":"Vyvestraat 22",
    "sg:city":"Staden",
    "sg:orig_category":"Produits laitiers and huiles comestibles Cr\u00e9meries",
    "sg:phone":"+32 51 22 82 98",
    "sg:postcode":"8840",
    "sg:province":"West-Vlaanderen",
    "wof:name":"Miss Ma\u00cfs",
    "wof:placetype":"venue"
},
  "geometry": {"coordinates":[3.0690469742,50.9391098022],"type":"Point"}
}