{
  "type": "Feature",
  "properties": {
    "addr:full":"Vlaanderenstraat 24 Aalst Oost-Vlaanderen 9300",
    "addr:housenumber":"24",
    "addr:postcode":"9300",
    "addr:street":"Vlaanderenstraat",
    "iso:country":"BE",
    "sg:address":"Vlaanderenstraat 24",
    "sg:city":"Aalst",
    "sg:orig_category":"Bioscopen",
    "sg:phone":"+32 53 21 40 48",
    "sg:postcode":"9300",
    "sg:province":"Oost-Vlaanderen",
    "wof:name":"Feestpaleis",
    "wof:placetype":"venue"
},
  "geometry": {"coordinates":[4.0321311951,50.9377937317],"type":"Point"}
}