{
  "type": "Feature",
  "properties": {
    "iso:country":"BE",
    "sg:address":"Gieterijstraat 49",
    "sg:city":"Sint-pieters-leeuw (ruisbroek)",
    "sg:classifiers":[
        {
            "category":"Manufacturing",
            "subcategory":"Soap",
            "type":"Manufacturing & Wholesale Goods"
        }
    ],
    "sg:phone":"+32 2 331 41 93",
    "sg:postcode":"1601",
    "sg:province":"Vlaams-Brabant",
    "sg:tags":[
        "dispenser",
        "automatic",
        "towel"
    ],
    "wof:name":"Cleanmatic",
    "wof:placetype":"venue"
},
  "geometry": {"coordinates":[4.2977218628,50.7917976379],"type":"Point"}
}