{
  "type": "Feature",
  "properties": {
    "addr:full":"Heilanders 54 Vosselaar Antwerpen 2350",
    "addr:housenumber":"54",
    "addr:postcode":"2350",
    "addr:street":"Heilanders",
    "iso:country":"BE",
    "sg:address":"Heilanders 54",
    "sg:city":"Vosselaar",
    "sg:classifiers":[
        {
            "category":"Bakery",
            "type":"Food & Drink"
        }
    ],
    "sg:phone":"+32 14 61 38 50",
    "sg:postcode":"2350",
    "sg:province":"Antwerpen",
    "sg:tags":[
        "confectioner",
        "baker"
    ],
    "wof:name":"Sas",
    "wof:placetype":"venue"
},
  "geometry": {"coordinates":[4.8805007935,51.3062705994],"type":"Point"}
}