{
  "type": "Feature",
  "properties": {
    "iso:country":"BE",
    "sg:address":"Burg. Heymansplein 40",
    "sg:city":"Beringen",
    "sg:orig_category":"Fitnesscentra",
    "sg:phone":"+32 11 39 21 97",
    "sg:postcode":"3581",
    "sg:province":"Limburg",
    "wof:name":"I.t.s.",
    "wof:placetype":"venue"
},
  "geometry": {"coordinates":[5.2228298187,51.0881996155],"type":"Point"}
}