{
  "type": "Feature",
  "properties": {
    "iso:country":"BE",
    "sg:address":"Leopold Vanderkelenstr. 26",
    "sg:city":"Leuven",
    "sg:orig_category":"Kapsalons",
    "sg:phone":"+32 16 22 35 48",
    "sg:postcode":"3000",
    "sg:province":"Vlaams-Brabant",
    "wof:name":"Charles Stevens",
    "wof:placetype":"venue"
},
  "geometry": {"coordinates":[4.704706192,50.8788108826],"type":"Point"}
}