{
  "type": "Feature",
  "properties": {
    "addr:full":"Vanderschrickstraat 3 Sint-gillis/saint-gilles Bruxelles-Capitale 1060",
    "addr:housenumber":"3",
    "addr:postcode":"1060",
    "addr:street":"Vanderschrickstraat",
    "iso:country":"BE",
    "sg:address":"Vanderschrickstraat 3",
    "sg:city":"Sint-gillis/saint-gilles",
    "sg:orig_category":"Artsen and specialisten",
    "sg:phone":"+32 2 538 04 15",
    "sg:postcode":"1060",
    "sg:province":"Bruxelles-Capitale",
    "wof:name":"Abdelaziz Elouehabi",
    "wof:placetype":"venue"
},
  "geometry": {"coordinates":[4.3444418907,50.8318862915],"type":"Point"}
}