{
  "type": "Feature",
  "properties": {
    "iso:country":"BE",
    "sg:address":"75 Avenue De Cortenbergh -",
    "sg:city":"Brussels",
    "sg:classifiers":[
        {
            "category":"Professional",
            "subcategory":"Art Services",
            "type":"Services"
        }
    ],
    "sg:phone":"+32 2 737 57 00",
    "sg:postcode":"1000",
    "sg:province":"Bruxelles-Capitale",
    "sg:tags":[
        "export-import"
    ],
    "wof:name":"Luxembourg Embassy",
    "wof:placetype":"venue"
},
  "geometry": {"coordinates":[4.3867998123,50.8436317444],"type":"Point"}
}