{
  "type": "Feature",
  "properties": {
    "iso:country":"BE",
    "sg:address":"Brabantdam 106",
    "sg:city":"Gent",
    "sg:classifiers":[
        {
            "category":"Cinema",
            "subcategory":"Movie Theater",
            "type":"Entertainment"
        }
    ],
    "sg:phone":"+32 9 233 50 93",
    "sg:postcode":"9000",
    "sg:province":"Oost-Vlaanderen",
    "wof:name":"Abc",
    "wof:placetype":"venue"
},
  "geometry": {"coordinates":[3.7314770222,51.0497360229],"type":"Point"}
}