{
  "type": "Feature",
  "properties": {
    "addr:full":"Assesteenweg 9c Asse (mollem) Vlaams-Brabant 1730",
    "addr:housenumber":"9c",
    "addr:postcode":"1730",
    "addr:street":"Assesteenweg",
    "iso:country":"BE",
    "sg:address":"Assesteenweg 9c",
    "sg:city":"Asse (mollem)",
    "sg:classifiers":[
        {
            "category":"Wholesale",
            "subcategory":"Vending Machines",
            "type":"Manufacturing & Wholesale Goods"
        }
    ],
    "sg:phone":"+32 2 452 20 05",
    "sg:postcode":"1730",
    "sg:province":"Vlaams-Brabant",
    "sg:tags":[
        "automobile",
        "-",
        "radiator"
    ],
    "wof:name":"A.r.d.",
    "wof:placetype":"venue"
},
  "geometry": {"coordinates":[4.1594591141,50.9177627563],"type":"Point"}
}