{
  "type": "Feature",
  "properties": {
    "iso:country":"BE",
    "sg:address":"Hoogkamerstraat 34",
    "sg:city":"Sint-niklaas",
    "sg:orig_category":"Grossistes divers",
    "sg:phone":"+32 3 778 03 36",
    "sg:postcode":"9100",
    "sg:province":"Oost-Vlaanderen",
    "wof:name":"Ken's",
    "wof:placetype":"venue"
},
  "geometry": {"coordinates":[4.1810379028,51.1454696655],"type":"Point"}
}