{
  "type": "Feature",
  "properties": {
    "addr:full":"Moerkerkse Steenweg 279 Brugge West-Vlaanderen 8310",
    "addr:housenumber":"279",
    "addr:postcode":"8310",
    "addr:street":"Moerkerkse Steenweg",
    "iso:country":"BE",
    "sg:address":"Moerkerkse Steenweg 279",
    "sg:city":"Brugge",
    "sg:orig_category":"Foto-uitrusting Fotografen and fotostudio's",
    "sg:phone":"+32 50 37 47 65",
    "sg:postcode":"8310",
    "sg:province":"West-Vlaanderen",
    "wof:name":"Stephan Van Everbroeck",
    "wof:placetype":"venue"
},
  "geometry": {"coordinates":[3.2549140453,51.2140083313],"type":"Point"}
}