{
  "type": "Feature",
  "properties": {
    "addr:full":"Koekoekstraat 31 Riemst 3711",
    "addr:housenumber":"31",
    "addr:postcode":"3711",
    "addr:street":"Koekoekstraat",
    "iso:country":"BE",
    "sg:address":"Koekoekstraat 31",
    "sg:city":"Riemst",
    "sg:orig_category":"Aanleg van wegen, sportterreinen and vliegvelden Plaatsen van vloer- and muurbekleding",
    "sg:phone":"+32 12 23 95 28",
    "sg:postcode":"3711",
    "wof:name":"Jackers",
    "wof:placetype":"venue"
},
  "geometry": {"coordinates":[9.6317062378,59.1376953125],"type":"Point"}
}