{
  "type": "Feature",
  "properties": {
    "iso:country":"BE",
    "sg:address":"Vrijheidstraat 6ba",
    "sg:city":"Aalst",
    "sg:classifiers":[
        {
            "category":"Cafe",
            "type":"Food & Drink"
        }
    ],
    "sg:phone":"+32 53 77 87 16",
    "sg:postcode":"9320",
    "sg:province":"Oost-Vlaanderen",
    "sg:tags":[
        "caf\u00e9s"
    ],
    "wof:name":"S K Erembodegem",
    "wof:placetype":"venue"
},
  "geometry": {"coordinates":[4.0356669426,50.9406013489],"type":"Point"}
}