{
  "type": "Feature",
  "properties": {
    "iso:country":"BE",
    "sg:address":"Avenue Fabiola 43",
    "sg:city":"Gerpinnes",
    "sg:orig_category":"Informaticaconsulenten",
    "sg:phone":"+32 71 50 35 50",
    "sg:postcode":"6280",
    "sg:province":"Hainaut",
    "wof:name":"Soft 33",
    "wof:placetype":"venue"
},
  "geometry": {"coordinates":[4.5197601318,50.3380241394],"type":"Point"}
}