{
  "type": "Feature",
  "properties": {
    "iso:country":"BE",
    "sg:address":"Slijpstraat 1",
    "sg:city":"Ieper (voormezele)",
    "sg:classifiers":[
        {
            "category":"Juice Bar",
            "subcategory":"None",
            "type":"Food & Drink"
        }
    ],
    "sg:phone":"+32 57 36 30 20",
    "sg:postcode":"8902",
    "sg:province":"West-Vlaanderen",
    "sg:tags":[
        "fruit",
        "syrup"
    ],
    "wof:name":"Tuinsappen Lombarts Calville",
    "wof:placetype":"venue"
},
  "geometry": {"coordinates":[2.8696539402,50.8101272583],"type":"Point"}
}