{
  "type": "Feature",
  "properties": {
    "addr:full":"Kerkstraat 43 Kuurne West-Vlaanderen 8520",
    "addr:housenumber":"43",
    "addr:postcode":"8520",
    "addr:street":"Kerkstraat",
    "iso:country":"BE",
    "sg:address":"Kerkstraat 43",
    "sg:city":"Kuurne",
    "sg:classifiers":[
        {
            "category":"Shopping",
            "subcategory":"Florist",
            "type":"Retail Goods"
        }
    ],
    "sg:phone":"+32 56 70 66 70",
    "sg:postcode":"8520",
    "sg:province":"West-Vlaanderen",
    "wof:name":"Botanic",
    "wof:placetype":"venue"
},
  "geometry": {"coordinates":[3.2867889404,50.8533401489],"type":"Point"}
}