{
  "type": "Feature",
  "properties": {
    "iso:country":"BE",
    "sg:address":"Rue Rompr\u00e9 14",
    "sg:city":"La Roche-en-ardenne",
    "sg:classifiers":[
        {
            "category":"Professional",
            "subcategory":"Credit Reporting & Collection",
            "type":"Services"
        }
    ],
    "sg:phone":"+32 84 41 29 19",
    "sg:postcode":"6980",
    "sg:province":"Luxembourg",
    "sg:tags":[
        "bailiff"
    ],
    "wof:name":"Louis A",
    "wof:placetype":"venue"
},
  "geometry": {"coordinates":[5.5778617859,50.1809501648],"type":"Point"}
}