{
  "type": "Feature",
  "properties": {
    "iso:country":"BE",
    "sg:address":"Hoogstraat 47",
    "sg:city":"Haaltert",
    "sg:classifiers":[
        {
            "category":"Health Services",
            "subcategory":"Dentist",
            "type":"Services"
        }
    ],
    "sg:phone":"+32 53 83 12 45",
    "sg:postcode":"9450",
    "sg:province":"Oost-Vlaanderen",
    "wof:name":"Van Overwaele Lea",
    "wof:placetype":"venue"
},
  "geometry": {"coordinates":[4.00400877,50.899646759],"type":"Point"}
}