{
  "type": "Feature",
  "properties": {
    "iso:country":"BE",
    "sg:address":"Korspelsesteenweg 46",
    "sg:city":"Beringen",
    "sg:orig_category":"Installatie van metalen schrijnwerk",
    "sg:phone":"+32 11 34 10 54",
    "sg:postcode":"3581",
    "sg:province":"Limburg",
    "wof:name":"Mathieu Vandeloo",
    "wof:placetype":"venue"
},
  "geometry": {"coordinates":[5.2283158302,51.0886878967],"type":"Point"}
}