{
  "type": "Feature",
  "properties": {
    "iso:country":"BE",
    "sg:address":"Chauss\u00c9e D'houdeng 195",
    "sg:city":"Le Roeulx",
    "sg:orig_category":"Mat\u00e9riel de contr\u00f4le des processus industriels Fab",
    "sg:phone":"+32 64 67 18 28",
    "sg:postcode":"7070",
    "sg:province":"Hainaut",
    "wof:name":"Labs Electronic",
    "wof:placetype":"venue"
},
  "geometry": {"coordinates":[4.1238870621,50.4984741211],"type":"Point"}
}