{
  "type": "Feature",
  "properties": {
    "addr:full":"Gentsestraat 12 Izegem West-Vlaanderen 8870",
    "addr:housenumber":"12",
    "addr:postcode":"8870",
    "addr:street":"Gentsestraat",
    "iso:country":"BE",
    "sg:address":"Gentsestraat 12",
    "sg:city":"Izegem",
    "sg:classifiers":[
        {
            "category":"Education",
            "subcategory":"Music School",
            "type":"Public Place"
        }
    ],
    "sg:phone":"+32 51 31 17 98",
    "sg:postcode":"8870",
    "sg:province":"West-Vlaanderen",
    "sg:tags":[
        "-",
        "teacher",
        "private"
    ],
    "wof:name":"Stemvork (de)",
    "wof:placetype":"venue"
},
  "geometry": {"coordinates":[3.2151401043,50.9175682068],"type":"Point"}
}