{
  "type": "Feature",
  "properties": {
    "iso:country":"BE",
    "sg:address":"Faubourg De Namur 91",
    "sg:city":"Nivelles",
    "sg:orig_category":"Banken and kredietinstellingen",
    "sg:phone":"+32 67 21 40 18",
    "sg:postcode":"1400",
    "sg:province":"Brabant Wallon",
    "wof:name":"Bbl",
    "wof:placetype":"venue"
},
  "geometry": {"coordinates":[4.3412818909,50.5995407104],"type":"Point"}
}