{
  "type": "Feature",
  "properties": {
    "iso:country":"BE",
    "sg:address":"Reepstraat 15",
    "sg:city":"Geraardsbergen (nederboelare)",
    "sg:classifiers":[
        {
            "category":"Recreation",
            "subcategory":"Arcade",
            "type":"Entertainment"
        }
    ],
    "sg:phone":"+32 54 41 30 34",
    "sg:postcode":"9500",
    "sg:province":"Oost-Vlaanderen",
    "sg:tags":[
        "machine",
        "amusement"
    ],
    "wof:name":"Carion",
    "wof:placetype":"venue"
},
  "geometry": {"coordinates":[3.8718280792,50.7749099731],"type":"Point"}
}