{
  "type": "Feature",
  "properties": {
    "addr:full":"Zoning De Baillonville 5 Somme-leuze Namur 5377",
    "addr:housenumber":"5",
    "addr:postcode":"5377",
    "addr:street":"Zoning;Baillonville",
    "iso:country":"BE",
    "sg:address":"Zoning De Baillonville 5",
    "sg:city":"Somme-leuze",
    "sg:classifiers":[
        {
            "category":"Building & Trades",
            "subcategory":"Electrical",
            "type":"Services"
        }
    ],
    "sg:phone":"+32 84 32 12 32",
    "sg:postcode":"5377",
    "sg:province":"Namur",
    "sg:tags":[
        "conditionn\u00e9",
        "equipement",
        "chauffage",
        "commer",
        "pour",
        "air",
        "ventilation",
        "mat\u00e9riel",
        "plomberie",
        "diver"
    ],
    "wof:name":"Laurent",
    "wof:placetype":"venue"
},
  "geometry": {"coordinates":[5.3698949814,50.3404350281],"type":"Point"}
}