{
  "type": "Feature",
  "properties": {
    "addr:full":"Molenveldstraat 27 Lebbeke Oost-Vlaanderen 9280",
    "addr:housenumber":"27",
    "addr:postcode":"9280",
    "addr:street":"Molenveldstraat",
    "iso:country":"BE",
    "sg:address":"Molenveldstraat 27",
    "sg:city":"Lebbeke",
    "sg:orig_category":"Catering and organisation de f\u00eates. Salles de conf\u00e9rences and de r\u00e9ceptions. Restaurants",
    "sg:phone":"+32 52 41 16 71",
    "sg:postcode":"9280",
    "sg:province":"Oost-Vlaanderen",
    "wof:name":"De Snuiver Restaurant",
    "wof:placetype":"venue"
},
  "geometry": {"coordinates":[4.094742775,50.9994926453],"type":"Point"}
}