{
  "type": "Feature",
  "properties": {
    "iso:country":"BE",
    "sg:address":"Meershoven 15 Box 1",
    "sg:city":"Bilzen",
    "sg:classifiers":[
        {
            "category":"Real Estate",
            "subcategory":"Developer",
            "type":"Services"
        }
    ],
    "sg:phone":"+32 89 62 17 20",
    "sg:postcode":"3740",
    "sg:province":"Limburg",
    "sg:tags":[
        "project"
    ],
    "wof:name":"Prosell Buildings Bvba",
    "wof:placetype":"venue"
},
  "geometry": {"coordinates":[5.5239701271,50.8738708496],"type":"Point"}
}