{
  "type": "Feature",
  "properties": {
    "addr:full":"Fabrikantenstraat 30 Moeskroen/mouscron Hainaut 7700",
    "addr:housenumber":"30",
    "addr:postcode":"7700",
    "addr:street":"Fabrikantenstraat",
    "iso:country":"BE",
    "sg:address":"Fabrikantenstraat 30",
    "sg:city":"Moeskroen/mouscron",
    "sg:classifiers":[
        {
            "category":"Insurance",
            "subcategory":"Insurance Agent",
            "type":"Services"
        }
    ],
    "sg:phone":"+32 56 84 37 18",
    "sg:postcode":"7700",
    "sg:province":"Hainaut",
    "sg:tags":[
        "verzekeringsmakelaars",
        "expert"
    ],
    "wof:name":"P&v",
    "wof:placetype":"venue"
},
  "geometry": {"coordinates":[3.2323200703,50.7400932312],"type":"Point"}
}