{
  "type": "Feature",
  "properties": {
    "addr:full":"Beernemsteenweg 50 Wingene West-Vlaanderen 8750",
    "addr:housenumber":"50",
    "addr:postcode":"8750",
    "addr:street":"Beernemsteenweg",
    "iso:country":"BE",
    "sg:address":"Beernemsteenweg 50",
    "sg:city":"Wingene",
    "sg:orig_category":"Maisons de vacances",
    "sg:phone":"+32 51 65 60 36",
    "sg:postcode":"8750",
    "sg:province":"West-Vlaanderen",
    "wof:name":"Devlieghere J",
    "wof:placetype":"venue"
},
  "geometry": {"coordinates":[3.2781839371,51.0625305176],"type":"Point"}
}