{
  "type": "Feature",
  "properties": {
    "iso:country":"BE",
    "sg:address":"Perstraat 68",
    "sg:city":"Beveren",
    "sg:orig_category":"Bouwmaterialen Gh Loodgieterij, verwarming and sanitaire installaties Zwembadinstallatie",
    "sg:phone":"+32 3 755 30 78",
    "sg:postcode":"9120",
    "sg:province":"Oost-Vlaanderen",
    "wof:name":"Jim's Pool Shop",
    "wof:placetype":"venue"
},
  "geometry": {"coordinates":[4.2443060875,51.1741828918],"type":"Point"}
}