{
  "type": "Feature",
  "properties": {
    "addr:full":"Rue Des Goulettes 1 Wellin Luxembourg 6920",
    "addr:housenumber":"1",
    "addr:postcode":"6920",
    "addr:street":"Rue Des Goulettes",
    "iso:country":"BE",
    "sg:address":"Rue Des Goulettes 1",
    "sg:city":"Wellin",
    "sg:classifiers":[
        {
            "category":"Food & Beverages",
            "subcategory":"Farmers Market",
            "type":"Retail Goods"
        }
    ],
    "sg:phone":"+32 84 38 98 73",
    "sg:postcode":"6920",
    "sg:province":"Luxembourg",
    "sg:tags":[
        "honey",
        "whol",
        "-"
    ],
    "wof:name":"Promiel Asbl",
    "wof:placetype":"venue"
},
  "geometry": {"coordinates":[5.1103200912,50.0782966614],"type":"Point"}
}