{
  "type": "Feature",
  "properties": {
    "addr:full":"Rue De Plainevaux 81 Seraing Li\u00e8ge 4100",
    "addr:housenumber":"81",
    "addr:postcode":"4100",
    "addr:street":"Rue De Plainevaux",
    "iso:country":"BE",
    "sg:address":"Rue De Plainevaux 81",
    "sg:city":"Seraing",
    "sg:orig_category":"M\u00e9decins and sp\u00e9cialistes",
    "sg:phone":"+32 4 338 36 86",
    "sg:postcode":"4100",
    "sg:province":"Li\u00e8ge",
    "wof:name":"Robert Gvozdenovic",
    "wof:placetype":"venue"
},
  "geometry": {"coordinates":[5.5068049431,50.5843429565],"type":"Point"}
}