{
  "type": "Feature",
  "properties": {
    "addr:full":"Izegemstraat 56 Ingelmunster West-Vlaanderen 8770",
    "addr:housenumber":"56",
    "addr:postcode":"8770",
    "addr:street":"Izegemstraat",
    "iso:country":"BE",
    "sg:address":"Izegemstraat 56",
    "sg:city":"Ingelmunster",
    "sg:classifiers":[
        {
            "category":"Personal",
            "subcategory":"Beauty Salon",
            "type":"Services"
        }
    ],
    "sg:phone":"+32 51 30 17 12",
    "sg:postcode":"8770",
    "sg:province":"West-Vlaanderen",
    "sg:tags":[
        "de",
        "coiffure"
    ],
    "wof:name":"Coiffure Sylvere",
    "wof:placetype":"venue"
},
  "geometry": {"coordinates":[3.2528820038,50.9149436951],"type":"Point"}
}