{
  "type": "Feature",
  "properties": {
    "iso:country":"BE",
    "sg:address":"Dr\u00c8ve Des Alli\u00c9s 9ba",
    "sg:city":"Thuin",
    "sg:orig_category":"Maatschappelijke dienstverlening",
    "sg:phone":"+32 71 59 15 64",
    "sg:postcode":"6530",
    "sg:province":"Hainaut",
    "wof:name":"Centre P.m.s.",
    "wof:placetype":"venue"
},
  "geometry": {"coordinates":[4.2947912216,50.3401870728],"type":"Point"}
}