{
  "type": "Feature",
  "properties": {
    "iso:country":"BE",
    "sg:address":"Rue Des Rivageois 1a",
    "sg:city":"Li\u00e8ge 1",
    "sg:classifiers":[
        {
            "category":"Utilities",
            "subcategory":"Cable",
            "type":"Services"
        }
    ],
    "sg:phone":"+32 4 252 75 73",
    "sg:postcode":"4000",
    "sg:province":"Li\u00e8ge",
    "sg:tags":[
        "wire",
        "electric"
    ],
    "wof:name":"Telec Sa",
    "wof:placetype":"venue"
},
  "geometry": {"coordinates":[5.5760908127,50.6236114502],"type":"Point"}
}