{
  "type": "Feature",
  "properties": {
    "addr:full":"Heirweg 82 Kuurne West-Vlaanderen 8520",
    "addr:housenumber":"82",
    "addr:postcode":"8520",
    "addr:street":"Heirweg",
    "iso:country":"BE",
    "sg:address":"Heirweg 82",
    "sg:city":"Kuurne",
    "sg:classifiers":[
        {
            "category":"Manufacturing",
            "subcategory":"Tools & Machinery",
            "type":"Manufacturing & Wholesale Goods"
        }
    ],
    "sg:phone":"+32 2 251 11 27",
    "sg:postcode":"8520",
    "sg:province":"West-Vlaanderen",
    "sg:tags":[
        "boring",
        "drilling"
    ],
    "wof:name":"Rampelberg Somers Nv",
    "wof:placetype":"venue"
},
  "geometry": {"coordinates":[4.4364748001,50.9134140015],"type":"Point"}
}