{
  "type": "Feature",
  "properties": {
    "iso:country":"BE",
    "sg:address":"Jan Roomsstraat 2",
    "sg:city":"Gent",
    "sg:orig_category":"Epiceries",
    "sg:phone":"+32 9 228 33 61",
    "sg:postcode":"9040",
    "sg:province":"Oost-Vlaanderen",
    "wof:name":"N Aelterman",
    "wof:placetype":"venue"
},
  "geometry": {"coordinates":[3.749710083,51.0584526062],"type":"Point"}
}