{
  "type": "Feature",
  "properties": {
    "addr:full":"Ouren 38 Burg-reuland/burg-reuland Li\u00e8ge 4790",
    "addr:housenumber":"38",
    "addr:postcode":"4790",
    "addr:street":"Ouren",
    "iso:country":"BE",
    "sg:address":"Ouren 38",
    "sg:city":"Burg-reuland/burg-reuland",
    "sg:orig_category":"Herstelling leer and schoeisel",
    "sg:phone":"+32 80 32 92 22",
    "sg:postcode":"4790",
    "sg:province":"Li\u00e8ge",
    "wof:name":"Konrad Belling",
    "wof:placetype":"venue"
},
  "geometry": {"coordinates":[6.1354861259,50.139175415],"type":"Point"}
}