{
  "type": "Feature",
  "properties": {
    "addr:full":"Rue Lesbroussart 44 Bruxelles (ixelles) Bruxelles-Capitale 1050",
    "addr:housenumber":"44",
    "addr:postcode":"1050",
    "addr:street":"Rue Lesbroussart",
    "iso:country":"BE",
    "sg:address":"Rue Lesbroussart 44",
    "sg:city":"Bruxelles (ixelles)",
    "sg:classifiers":[
        {
            "category":"Building & Trades",
            "subcategory":"Construction",
            "type":"Services"
        }
    ],
    "sg:phone":"+32 2 640 43 33",
    "sg:postcode":"1050",
    "sg:province":"Bruxelles-Capitale",
    "sg:tags":[
        "industrial",
        "design"
    ],
    "wof:name":"Preumont N",
    "wof:placetype":"venue"
},
  "geometry": {"coordinates":[4.3690929413,50.8275794983],"type":"Point"}
}