{
  "type": "Feature",
  "properties": {
    "iso:country":"BE",
    "sg:address":"Pullaarsteenweg 17",
    "sg:city":"Puurs (ruisbroek)",
    "sg:classifiers":[
        {
            "category":"Home & Garden",
            "subcategory":"Kitchen Supply",
            "type":"Retail Goods"
        }
    ],
    "sg:phone":"+32 3 886 54 19",
    "sg:postcode":"2870",
    "sg:province":"Antwerpen",
    "sg:tags":[
        "installation"
    ],
    "wof:name":"Gaio Keukens Belgi\u00eb",
    "wof:placetype":"venue"
},
  "geometry": {"coordinates":[4.3248882294,51.0788383484],"type":"Point"}
}