{
  "type": "Feature",
  "properties": {
    "iso:country":"BE",
    "sg:address":"All\u00e9e Des Houx 28",
    "sg:city":"Oupeye (herm\u00e9e)",
    "sg:classifiers":[
        {
            "category":"Health Services",
            "subcategory":"Health Practitioner",
            "type":"Services"
        }
    ],
    "sg:phone":"+32 4 278 58 30",
    "sg:postcode":"4680",
    "sg:province":"Li\u00e8ge",
    "sg:tags":[
        "therapist",
        "speech"
    ],
    "wof:name":"Gustin-etienne",
    "wof:placetype":"venue"
},
  "geometry": {"coordinates":[5.6444120407,50.7089729309],"type":"Point"}
}