{
  "type": "Feature",
  "properties": {
    "iso:country":"BE",
    "sg:address":"Prekersstraat 71",
    "sg:city":"Antwerpen",
    "sg:classifiers":[
        {
            "category":"Health Services",
            "subcategory":"Health Practitioner",
            "type":"Services"
        }
    ],
    "sg:phone":"+32 3 237 50 67",
    "sg:postcode":"2000",
    "sg:province":"Antwerpen",
    "sg:tags":[
        "physiotherapist"
    ],
    "wof:name":"Verheyen E",
    "wof:placetype":"venue"
},
  "geometry": {"coordinates":[4.3974127769,51.2140693665],"type":"Point"}
}