{
  "type": "Feature",
  "properties": {
    "iso:country":"BE",
    "sg:address":"Van Schoonbekestraat 143",
    "sg:city":"Antwerpen",
    "sg:orig_category":"Hoger onderwijs",
    "sg:phone":"+32 3 237 77 67",
    "sg:postcode":"2018",
    "sg:province":"Antwerpen",
    "wof:name":"A.k.h.i.v.",
    "wof:placetype":"venue"
},
  "geometry": {"coordinates":[4.4034590721,51.1992454529],"type":"Point"}
}