{
  "type": "Feature",
  "properties": {
    "addr:full":"Rue Albert Ier 175 Erquelinnes Hainaut 6560",
    "addr:housenumber":"175",
    "addr:postcode":"6560",
    "addr:street":"Rue Albert Ier",
    "iso:country":"BE",
    "sg:address":"Rue Albert Ier 175",
    "sg:city":"Erquelinnes",
    "sg:orig_category":"Banques and organismes de cr\u00e9dit",
    "sg:phone":"+32 71 55 67 55",
    "sg:postcode":"6560",
    "sg:province":"Hainaut",
    "wof:name":"Dexia",
    "wof:placetype":"venue"
},
  "geometry": {"coordinates":[4.1163201332,50.3063735962],"type":"Point"}
}