{
  "type": "Feature",
  "properties": {
    "iso:country":"BE",
    "sg:address":"Rue Des 4 Seigneuries 1",
    "sg:city":"Courcelles",
    "sg:orig_category":"Apotheken",
    "sg:phone":"+32 71 46 15 35",
    "sg:postcode":"6180",
    "sg:province":"Hainaut",
    "wof:name":"Pharmacie 4 Seigneuries",
    "wof:placetype":"venue"
},
  "geometry": {"coordinates":[4.3580307961,50.4362182617],"type":"Point"}
}