{
  "type": "Feature",
  "properties": {
    "iso:country":"BE",
    "sg:address":"Kernielerweg 59",
    "sg:city":"Borgloon",
    "sg:classifiers":[
        {
            "category":"Wholesale",
            "subcategory":"Fruits & Vegetables",
            "type":"Manufacturing & Wholesale Goods"
        }
    ],
    "sg:phone":"+32 12 74 14 92",
    "sg:postcode":"3840",
    "sg:province":"Limburg",
    "sg:tags":[
        "whol",
        "-"
    ],
    "wof:name":"Vergro Nv",
    "wof:placetype":"venue"
},
  "geometry": {"coordinates":[5.3590898514,50.8081207275],"type":"Point"}
}