{
  "type": "Feature",
  "properties": {
    "addr:full":"G. Mertensstraat 14 Liedekerke Vlaams-Brabant 1770",
    "addr:housenumber":"14",
    "addr:postcode":"1770",
    "addr:street":"G. Mertensstraat;Vlaams-Brabant",
    "iso:country":"BE",
    "sg:address":"G. Mertensstraat 14",
    "sg:city":"Liedekerke",
    "sg:orig_category":"Rundveehouders Textiel",
    "sg:phone":"+32 53 66 64 97",
    "sg:postcode":"1770",
    "sg:province":"Vlaams-Brabant",
    "wof:name":"Stefaan Schouppe",
    "wof:placetype":"venue"
},
  "geometry": {"coordinates":[4.0814599991,50.8704414368],"type":"Point"}
}