{
  "type": "Feature",
  "properties": {
    "addr:full":"Bergeneindestraat 31ba Geetbets Vlaams-Brabant 3454",
    "addr:housenumber":"31ba",
    "addr:postcode":"3454",
    "addr:street":"Bergeneindestraat",
    "iso:country":"BE",
    "sg:address":"Bergeneindestraat 31ba",
    "sg:city":"Geetbets",
    "sg:orig_category":"Traitements param\u00e9dicaux",
    "sg:phone":"+32 11 58 10 22",
    "sg:postcode":"3454",
    "sg:province":"Vlaams-Brabant",
    "wof:name":"R. Deferm",
    "wof:placetype":"venue"
},
  "geometry": {"coordinates":[5.1768960953,50.9038772583],"type":"Point"}
}