{
  "type": "Feature",
  "properties": {
    "addr:full":"Mechelsebaan 193 Duffel Antwerpen 2570",
    "addr:housenumber":"193",
    "addr:postcode":"2570",
    "addr:street":"Mechelsebaan",
    "iso:country":"BE",
    "sg:address":"Mechelsebaan 193",
    "sg:city":"Duffel",
    "sg:classifiers":[
        {
            "category":"Autos & Motor Vehicles",
            "subcategory":"Automobile Sales",
            "type":"Retail Goods"
        }
    ],
    "sg:phone":"+32 15 31 49 17",
    "sg:postcode":"2570",
    "sg:province":"Antwerpen",
    "sg:tags":[
        "car",
        "used",
        "-"
    ],
    "wof:name":"Christoffel",
    "wof:placetype":"venue"
},
  "geometry": {"coordinates":[4.4954681396,51.0800704956],"type":"Point"}
}