{
  "type": "Feature",
  "properties": {
    "iso:country":"BE",
    "sg:address":"Hogeweg 141",
    "sg:city":"Stabroek",
    "sg:orig_category":"Dakwerken Woningbouw",
    "sg:phone":"+32 3 664 56 43",
    "sg:postcode":"2940",
    "sg:province":"Antwerpen",
    "wof:name":"Palinckx J.",
    "wof:placetype":"venue"
},
  "geometry": {"coordinates":[4.395720005,51.314201355],"type":"Point"}
}