{
  "type": "Feature",
  "properties": {
    "iso:country":"BE",
    "sg:address":"Rue Lesbroussart 50",
    "sg:city":"Elsene/ixelles",
    "sg:orig_category":"IJzerwaren, bouw- and verfmaterialen Pleisterwerk Verlichting and huishoudartikelen",
    "sg:phone":"+32 2 648 08 05",
    "sg:postcode":"1050",
    "sg:province":"Bruxelles-Capitale",
    "wof:name":"Gesso",
    "wof:placetype":"venue"
},
  "geometry": {"coordinates":[4.3686699867,50.8276329041],"type":"Point"}
}