{
  "type": "Feature",
  "properties": {
    "addr:full":"Rue De La Cit\u00e9 2 Verviers Li\u00e8ge 4800",
    "addr:housenumber":"2",
    "addr:postcode":"4800",
    "addr:street":"Rue De La Cite\u0301",
    "iso:country":"BE",
    "sg:address":"Rue De La Cit\u00e9 2",
    "sg:city":"Verviers",
    "sg:classifiers":[
        {
            "category":"Social Services",
            "type":"Services"
        }
    ],
    "sg:phone":"+32 87 35 24 50",
    "sg:postcode":"4800",
    "sg:province":"Li\u00e8ge",
    "wof:name":"M.i.r.e.v.",
    "wof:placetype":"venue"
},
  "geometry": {"coordinates":[5.8767619133,50.5962295532],"type":"Point"}
}