{
  "type": "Feature",
  "properties": {
    "iso:country":"BE",
    "sg:address":"Hoekplein 1",
    "sg:city":"Zaventem",
    "sg:classifiers":[
        {
            "category":"Professional",
            "subcategory":"Management & Consulting",
            "type":"Services"
        }
    ],
    "sg:phone":"+32 2 725 21 21",
    "sg:postcode":"1930",
    "sg:province":"Vlaams-Brabant",
    "sg:tags":[
        "consultant",
        "agency",
        "advertising"
    ],
    "wof:name":"Incognito Brussels Nv",
    "wof:placetype":"venue"
},
  "geometry": {"coordinates":[4.4625740051,50.8891677856],"type":"Point"}
}