{
  "type": "Feature",
  "properties": {
    "addr:full":"Avenue De La Porte De Hal 19 Bruxelles (saint-gilles) Bruxelles-Capitale 1060",
    "addr:housenumber":"19",
    "addr:postcode":"1060",
    "addr:street":"Avenue De La Porte De Hal",
    "iso:country":"BE",
    "sg:address":"Avenue De La Porte De Hal 19",
    "sg:city":"Bruxelles (saint-gilles)",
    "sg:classifiers":[
        {
            "category":"Bars & Pubs",
            "type":"Food & Drink"
        }
    ],
    "sg:phone":"+32 2 537 51 56",
    "sg:postcode":"1060",
    "sg:province":"Bruxelles-Capitale",
    "wof:name":"Coin (le)",
    "wof:placetype":"venue"
},
  "geometry": {"coordinates":[4.3453397751,50.8265914917],"type":"Point"}
}