{
  "type": "Feature",
  "properties": {
    "iso:country":"BE",
    "sg:address":"Zakstraat 48b",
    "sg:city":"Ranst",
    "sg:orig_category":"Equipement divers pour commerces Installation de menuiserie en bois and plastique",
    "sg:phone":"+32 3 485 78 99",
    "sg:postcode":"2520",
    "sg:province":"Antwerpen",
    "wof:name":"Bossaerts",
    "wof:placetype":"venue"
},
  "geometry": {"coordinates":[4.5778570175,51.1978187561],"type":"Point"}
}