{
  "type": "Feature",
  "properties": {
    "addr:full":"Quai Saint-l\u00c9onard 79 Li\u00c8ge Li\u00e8ge 4000",
    "addr:housenumber":"79",
    "addr:postcode":"4000",
    "addr:street":"Quai Saint-Le\u0301Onard",
    "iso:country":"BE",
    "sg:address":"Quai Saint-l\u00c9onard 79",
    "sg:city":"Li\u00c8ge",
    "sg:orig_category":"Entretien and r\u00e9parations de voitures",
    "sg:phone":"+32 4 227 18 02",
    "sg:postcode":"4000",
    "sg:province":"Li\u00e8ge",
    "wof:name":"Carglass",
    "wof:placetype":"venue"
},
  "geometry": {"coordinates":[5.5985608101,50.6499023438],"type":"Point"}
}