{
  "type": "Feature",
  "properties": {
    "addr:full":"Rue Des B\u00c9gonias 5 Watermaal-bosvoorde/watermael- Bruxelles-Capitale 1170",
    "addr:housenumber":"5",
    "addr:postcode":"1170",
    "addr:street":"Rue Des Be\u0301Gonias",
    "iso:country":"BE",
    "sg:address":"Rue Des B\u00c9gonias 5",
    "sg:city":"Watermaal-bosvoorde/watermael-",
    "sg:orig_category":"Banques and organismes de cr\u00e9dit",
    "sg:phone":"+32 2 660 69 94",
    "sg:postcode":"1170",
    "sg:province":"Bruxelles-Capitale",
    "wof:name":"Fortis",
    "wof:placetype":"venue"
},
  "geometry": {"coordinates":[4.4041399956,50.8091392517],"type":"Point"}
}