{
  "type": "Feature",
  "properties": {
    "addr:full":"Rue Des Terminals 5 Athus Luxembourg 6791",
    "addr:housenumber":"5",
    "addr:postcode":"6791",
    "addr:street":"Rue Des Terminals",
    "iso:country":"BE",
    "sg:address":"Rue Des Terminals 5",
    "sg:city":"Athus",
    "sg:classifiers":[
        {
            "category":"Autos & Motor Vehicles",
            "subcategory":"Automobile Sales",
            "type":"Retail Goods"
        }
    ],
    "sg:phone":"+32 63 38 83 16",
    "sg:postcode":"6791",
    "sg:province":"Luxembourg",
    "sg:tags":[
        "equipment",
        "industrial",
        "transport"
    ],
    "wof:name":"Trax Nv",
    "wof:placetype":"venue"
},
  "geometry": {"coordinates":[5.832379818,49.5573616028],"type":"Point"}
}