{
  "type": "Feature",
  "properties": {
    "iso:country":"BE",
    "sg:address":"De Damhouderestraat 16",
    "sg:city":"Antwerpen",
    "sg:classifiers":[
        {
            "category":"Organizations",
            "subcategory":"Community Association",
            "type":"Services"
        }
    ],
    "sg:phone":"+32 3 237 74 77",
    "sg:postcode":"2018",
    "sg:province":"Antwerpen",
    "sg:tags":[
        "cultural"
    ],
    "wof:name":"Thelman Institute Vzw",
    "wof:placetype":"venue"
},
  "geometry": {"coordinates":[4.40483284,51.2079658508],"type":"Point"}
}