{
  "type": "Feature",
  "properties": {
    "addr:full":"Chemin Du Peiffeschoff 101 Arlon Luxembourg 6700",
    "addr:housenumber":"101",
    "addr:postcode":"6700",
    "addr:street":"Chemin Du Peiffeschoff",
    "iso:country":"BE",
    "sg:address":"Chemin Du Peiffeschoff 101",
    "sg:city":"Arlon",
    "sg:orig_category":"Elektrische installaties voor woningen",
    "sg:phone":"+32 63 22 49 87",
    "sg:postcode":"6700",
    "sg:province":"Luxembourg",
    "wof:name":"Elie Lambre",
    "wof:placetype":"venue"
},
  "geometry": {"coordinates":[5.8429021835,49.6964187622],"type":"Point"}
}