{
  "type": "Feature",
  "properties": {
    "iso:country":"BE",
    "sg:address":"Rue Joseph Dufrane 10",
    "sg:city":"Frameries",
    "sg:orig_category":"Artsen and specialisten",
    "sg:phone":"+32 65 67 38 84",
    "sg:postcode":"7080",
    "sg:province":"Hainaut",
    "wof:name":"Jean-jacques Muny",
    "wof:placetype":"venue"
},
  "geometry": {"coordinates":[3.892359972,50.4073944092],"type":"Point"}
}