{
  "type": "Feature",
  "properties": {
    "iso:country":"BE",
    "sg:address":"Clos Saint-roch 13",
    "sg:city":"Waterloo",
    "sg:orig_category":"Artsen and specialisten",
    "sg:phone":"+32 2 354 62 63",
    "sg:postcode":"1410",
    "sg:province":"Brabant Wallon",
    "wof:name":"Jacques Bastenier",
    "wof:placetype":"venue"
},
  "geometry": {"coordinates":[4.3982381821,50.699672699],"type":"Point"}
}