{
  "type": "Feature",
  "properties": {
    "iso:country":"BE",
    "sg:address":"Brederodestraat 85",
    "sg:city":"Antwerpen",
    "sg:orig_category":"Diverse kredietdiensten",
    "sg:postcode":"2018",
    "sg:province":"Antwerpen",
    "wof:name":"Bancontact-mister Cash",
    "wof:placetype":"venue"
},
  "geometry": {"coordinates":[4.3952307701,51.2046165466],"type":"Point"}
}