{
  "type": "Feature",
  "properties": {
    "iso:country":"BE",
    "sg:address":"Admiraal Ronarchstraat 27",
    "sg:city":"Diksmuide",
    "sg:classifiers":[
        {
            "category":"Autos & Motor Vehicles",
            "subcategory":"Motorcycle Sales",
            "type":"Retail Goods"
        }
    ],
    "sg:phone":"+32 51 50 03 77",
    "sg:postcode":"8600",
    "sg:province":"West-Vlaanderen",
    "sg:tags":[
        "scooter",
        "-",
        "moped"
    ],
    "wof:name":"Stragier L",
    "wof:placetype":"venue"
},
  "geometry": {"coordinates":[2.8661339283,51.0319595337],"type":"Point"}
}