{
  "type": "Feature",
  "properties": {
    "addr:full":"Sint-jorisstraat 6 Kortrijk West-Vlaanderen 8500",
    "addr:housenumber":"6",
    "addr:postcode":"8500",
    "addr:street":"Sint-Jorisstraat",
    "iso:country":"BE",
    "sg:address":"Sint-jorisstraat 6",
    "sg:city":"Kortrijk",
    "sg:orig_category":"Effectenmakelaars and vermogensbeheer",
    "sg:phone":"+32 56 21 40 35",
    "sg:postcode":"8500",
    "sg:province":"West-Vlaanderen",
    "wof:name":"Lawaisse M-ph & Co",
    "wof:placetype":"venue"
},
  "geometry": {"coordinates":[3.2663578987,50.8250427246],"type":"Point"}
}