{
  "type": "Feature",
  "properties": {
    "addr:full":"Avenue Reine Astrid 256 Verviers (heusy) Li\u00e8ge 4802",
    "addr:housenumber":"256",
    "addr:postcode":"4802",
    "addr:street":"Avenue Reine Astrid",
    "iso:country":"BE",
    "sg:address":"Avenue Reine Astrid 256",
    "sg:city":"Verviers (heusy)",
    "sg:classifiers":[
        {
            "category":"Bars & Pubs",
            "type":"Food & Drink"
        }
    ],
    "sg:phone":"+32 87 22 97 71",
    "sg:postcode":"4802",
    "sg:province":"Li\u00e8ge",
    "wof:name":"Joe'bar Team Sprl",
    "wof:placetype":"venue"
},
  "geometry": {"coordinates":[5.8866991997,50.5832557678],"type":"Point"}
}