{
  "type": "Feature",
  "properties": {
    "iso:country":"BE",
    "sg:address":"Leuvensesteenweg 250a",
    "sg:city":"Vilvoorde",
    "sg:classifiers":[
        {
            "category":"Banks & Credit Unions",
            "subcategory":"Bureau De Change",
            "type":"Services"
        }
    ],
    "sg:phone":"+32 2 257 02 00",
    "sg:postcode":"1800",
    "sg:province":"Vlaams-Brabant",
    "sg:tags":[
        "regulating",
        "system"
    ],
    "wof:name":"Geveke Industrial Nv",
    "wof:placetype":"venue"
},
  "geometry": {"coordinates":[4.4499659538,50.9239959717],"type":"Point"}
}