{
  "type": "Feature",
  "properties": {
    "iso:country":"BE",
    "sg:address":"Rue De La Brasserie 54",
    "sg:city":"Linkebeek",
    "sg:classifiers":[
        {
            "category":"Professional",
            "subcategory":"Art Services",
            "type":"Services"
        }
    ],
    "sg:phone":"+32 2 377 41 11",
    "sg:postcode":"1630",
    "sg:province":"Vlaams-Brabant",
    "sg:tags":[
        "-",
        "painter",
        "artist"
    ],
    "wof:name":"Roig J",
    "wof:placetype":"venue"
},
  "geometry": {"coordinates":[4.3269739151,50.7782516479],"type":"Point"}
}