{
  "type": "Feature",
  "properties": {
    "iso:country":"BE",
    "sg:address":"Heldenhuldelaan 90",
    "sg:city":"Mortsel",
    "sg:classifiers":[
        {
            "category":"Professional",
            "subcategory":"Accounting & Tax Preparation",
            "type":"Services"
        }
    ],
    "sg:phone":"+32 3 440 88 79",
    "sg:postcode":"2640",
    "sg:province":"Antwerpen",
    "sg:tags":[
        "accountant"
    ],
    "wof:name":"De Jonghe R",
    "wof:placetype":"venue"
},
  "geometry": {"coordinates":[4.4687438011,51.1732368469],"type":"Point"}
}