{
  "type": "Feature",
  "properties": {
    "addr:full":"Midzomer 4 Schilde Antwerpen 2970",
    "addr:housenumber":"4",
    "addr:postcode":"2970",
    "addr:street":"Midzomer",
    "iso:country":"BE",
    "sg:address":"Midzomer 4",
    "sg:city":"Schilde",
    "sg:classifiers":[
        {
            "category":"Shopping Center",
            "type":"Public Place"
        }
    ],
    "sg:phone":"+32 3 685 59 03",
    "sg:postcode":"2970",
    "sg:province":"Antwerpen",
    "sg:tags":[
        "enseignement",
        "formation"
    ],
    "wof:name":"Bureau Pelgrims",
    "wof:placetype":"venue"
},
  "geometry": {"coordinates":[4.5645051003,51.2711296082],"type":"Point"}
}