{
  "type": "Feature",
  "properties": {
    "iso:country":"BE",
    "sg:address":"Rue Des Trieux 10",
    "sg:city":"Aiseau-presles (aiseau)",
    "sg:classifiers":[
        {
            "category":"Health Services",
            "subcategory":"Dentist",
            "type":"Services"
        }
    ],
    "sg:phone":"+32 71 76 08 21",
    "sg:postcode":"6250",
    "sg:province":"Hainaut",
    "wof:name":"Siernicki Nicole",
    "wof:placetype":"venue"
},
  "geometry": {"coordinates":[4.5810909271,50.4064903259],"type":"Point"}
}