{
  "type": "Feature",
  "properties": {
    "iso:country":"BE",
    "sg:address":"Avenue Baziel De Craene 6",
    "sg:city":"Wemmel",
    "sg:orig_category":"R\u00e9parations de chaussures and articles en cuir",
    "sg:phone":"+32 2 460 55 80",
    "sg:postcode":"1780",
    "sg:province":"Vlaams-Brabant",
    "wof:name":"Jean-philippe Hellinckx",
    "wof:placetype":"venue"
},
  "geometry": {"coordinates":[4.293489933,50.9042434692],"type":"Point"}
}