{
  "type": "Feature",
  "properties": {
    "iso:country":"BE",
    "sg:address":"Molenstraat 53a",
    "sg:city":"Zottegem",
    "sg:classifiers":[
        {
            "category":"Arena",
            "subcategory":"Sports Club",
            "type":"Entertainment"
        }
    ],
    "sg:phone":"+32 9 360 89 14",
    "sg:postcode":"9620",
    "sg:province":"Oost-Vlaanderen",
    "sg:tags":[
        "de"
    ],
    "wof:name":"Ren Shin Geraardsbergen",
    "wof:placetype":"venue"
},
  "geometry": {"coordinates":[3.8105928898,50.8678436279],"type":"Point"}
}