{
  "type": "Feature",
  "properties": {
    "iso:country":"BE",
    "sg:address":"Noordlaan 27",
    "sg:city":"Kuurne",
    "sg:classifiers":[
        {
            "category":"Autos & Motor Vehicles",
            "subcategory":"Auto Supplies",
            "type":"Retail Goods"
        }
    ],
    "sg:phone":"+32 56 37 15 52",
    "sg:postcode":"8520",
    "sg:province":"West-Vlaanderen",
    "sg:tags":[
        "machine",
        "laundry",
        "-"
    ],
    "wof:name":"Laco Machinery Nv",
    "wof:placetype":"venue"
},
  "geometry": {"coordinates":[3.2611010075,50.8611106873],"type":"Point"}
}