{
  "type": "Feature",
  "properties": {
    "iso:country":"BE",
    "sg:address":"Rue Winamplanche 760",
    "sg:city":"Theux (la Reid)",
    "sg:classifiers":[
        {
            "category":"Building & Trades",
            "subcategory":"Cleaning & Sanitation",
            "type":"Services"
        }
    ],
    "sg:phone":"+32 87 37 67 86",
    "sg:postcode":"4910",
    "sg:province":"Li\u00e8ge",
    "sg:tags":[
        "sweep",
        "chimney"
    ],
    "wof:name":"L\u00e9ger J-m",
    "wof:placetype":"venue"
},
  "geometry": {"coordinates":[5.8208799362,50.4792709351],"type":"Point"}
}