{
  "type": "Feature",
  "properties": {
    "addr:full":"Stalenstraat 163 Genk (waterschei) Limburg 3600",
    "addr:housenumber":"163",
    "addr:postcode":"3600",
    "addr:street":"Stalenstraat",
    "iso:country":"BE",
    "sg:address":"Stalenstraat 163",
    "sg:city":"Genk (waterschei)",
    "sg:classifiers":[
        {
            "category":"Transit Center",
            "subcategory":"Freight",
            "type":"Transportation"
        }
    ],
    "sg:phone":"+32 89 46 50 76",
    "sg:postcode":"3600",
    "sg:province":"Limburg",
    "sg:tags":[
        "import",
        "export",
        "-"
    ],
    "wof:name":"Bey Tex Bvba",
    "wof:placetype":"venue"
},
  "geometry": {"coordinates":[5.5175409317,50.9928092957],"type":"Point"}
}