{
  "type": "Feature",
  "properties": {
    "addr:full":"Chauss\u00c9e De Mons 22 Nivelles Brabant Wallon 1400",
    "addr:housenumber":"22",
    "addr:postcode":"1400",
    "addr:street":"Chausse\u0301E De Mons",
    "iso:country":"BE",
    "sg:address":"Chauss\u00c9e De Mons 22",
    "sg:city":"Nivelles",
    "sg:orig_category":"Activit\u00e9s r\u00e9cr\u00e9atives diverses",
    "sg:phone":"+32 67 21 87 21",
    "sg:postcode":"1400",
    "sg:province":"Brabant Wallon",
    "wof:name":"Le Pion Du Roi Nivelles",
    "wof:placetype":"venue"
},
  "geometry": {"coordinates":[4.3078727722,50.5880661011],"type":"Point"}
}