{
  "type": "Feature",
  "properties": {
    "iso:country":"BE",
    "sg:address":"Coghenlaan 70",
    "sg:city":"Ukkel/uccle",
    "sg:orig_category":"Kapsalons",
    "sg:phone":"+32 2 345 52 78",
    "sg:postcode":"1180",
    "sg:province":"Bruxelles-Capitale",
    "wof:name":"Jean-luc Coiffure",
    "wof:placetype":"venue"
},
  "geometry": {"coordinates":[4.3406839371,50.8114929199],"type":"Point"}
}