{
  "type": "Feature",
  "properties": {
    "iso:country":"BE",
    "sg:address":"Felix Aertgeertsstraat 28",
    "sg:city":"Tremelo",
    "sg:orig_category":"Binnenhuisarchitecten Installatie van houten of kunststof schrijnwerk Meubelzaken, woning- and keuke",
    "sg:phone":"+32 16 53 03 81",
    "sg:postcode":"3128",
    "sg:province":"Vlaams-Brabant",
    "wof:name":"Benjo-interieur",
    "wof:placetype":"venue"
},
  "geometry": {"coordinates":[4.7552471161,51.0109024048],"type":"Point"}
}