{
  "type": "Feature",
  "properties": {
    "iso:country":"BE",
    "sg:address":"Hasseltweg 74",
    "sg:city":"Genk",
    "sg:orig_category":"R\u00e9parations d'appareils \u00e9lectrom\u00e9nagers. Electrom\u00e9nager, t\u00e9l\u00e9visions and radios",
    "sg:phone":"+32 89 30 50 77",
    "sg:postcode":"3600",
    "sg:province":"Limburg",
    "wof:name":"Best-sellers",
    "wof:placetype":"venue"
},
  "geometry": {"coordinates":[5.469107151,50.9634475708],"type":"Point"}
}