{
  "type": "Feature",
  "properties": {
    "addr:full":"Singel 2 Lille Antwerpen 2275",
    "addr:housenumber":"2",
    "addr:postcode":"2275",
    "addr:street":"Singel",
    "iso:country":"BE",
    "sg:address":"Singel 2",
    "sg:city":"Lille",
    "sg:orig_category":"Banques and organismes de cr\u00e9dit",
    "sg:phone":"+32 14 55 16 85",
    "sg:postcode":"2275",
    "sg:province":"Antwerpen",
    "wof:name":"Landbouwkrediet",
    "wof:placetype":"venue"
},
  "geometry": {"coordinates":[4.8674449921,51.2667427063],"type":"Point"}
}