{
  "type": "Feature",
  "properties": {
    "addr:full":"Place Pierre Lemarchand 7 Theux (polleur) Li\u00e8ge 4910",
    "addr:housenumber":"7",
    "addr:postcode":"4910",
    "addr:street":"Place Pierre Lemarchand",
    "iso:country":"BE",
    "sg:address":"Place Pierre Lemarchand 7",
    "sg:city":"Theux (polleur)",
    "sg:orig_category":"Non-Classified Establishments",
    "sg:phone":"+32 87 22 43 06",
    "sg:postcode":"4910",
    "sg:province":"Li\u00e8ge",
    "wof:name":"Moulin Renard Sa",
    "wof:placetype":"venue"
},
  "geometry": {"coordinates":[5.8921031952,50.555015564],"type":"Point"}
}