{
  "type": "Feature",
  "properties": {
    "iso:country":"BE",
    "sg:address":"Rue Du Centre 17",
    "sg:city":"Geer",
    "sg:orig_category":"Fleurs and plantes",
    "sg:phone":"+32 19 32 70 53",
    "sg:postcode":"4250",
    "sg:province":"Li\u00e8ge",
    "wof:name":"La Fontaine Fleurie",
    "wof:placetype":"venue"
},
  "geometry": {"coordinates":[5.2114257812,50.6744232178],"type":"Point"}
}