{
  "type": "Feature",
  "properties": {
    "iso:country":"BE",
    "sg:address":"Charleroise Steenweg 182",
    "sg:city":"Sint-gillis/saint-gilles",
    "sg:orig_category":"Artsen and specialisten",
    "sg:phone":"+32 2 538 85 21",
    "sg:postcode":"1060",
    "sg:province":"Bruxelles-Capitale",
    "wof:name":"E. Sellematos",
    "wof:placetype":"venue"
},
  "geometry": {"coordinates":[4.3547010422,50.8250961304],"type":"Point"}
}