{
  "type": "Feature",
  "properties": {
    "iso:country":"BE",
    "sg:address":"Ulbeekstraat 42b2",
    "sg:city":"Wellen",
    "sg:orig_category":"HUISBRANDOLIE Paramedische behandelingen",
    "sg:phone":"+32 11 31 24 75",
    "sg:postcode":"3832",
    "sg:province":"Limburg",
    "wof:name":"E. Houbrechts",
    "wof:placetype":"venue"
},
  "geometry": {"coordinates":[5.3034801483,50.8444442749],"type":"Point"}
}