{
  "type": "Feature",
  "properties": {
    "addr:full":"Dries 48 Lede Oost-Vlaanderen 9340",
    "addr:housenumber":"48",
    "addr:postcode":"9340",
    "addr:street":"Dries",
    "iso:country":"BE",
    "sg:address":"Dries 48",
    "sg:city":"Lede",
    "sg:orig_category":"M\u00e9decins and sp\u00e9cialistes",
    "sg:phone":"+32 9 369 28 48",
    "sg:postcode":"9340",
    "sg:province":"Oost-Vlaanderen",
    "wof:name":"L. Van Hove",
    "wof:placetype":"venue"
},
  "geometry": {"coordinates":[3.8923490047,50.9627342224],"type":"Point"}
}