{
  "type": "Feature",
  "properties": {
    "addr:full":"Fruithoflaan 37 Berchem Antwerpen 2600",
    "addr:housenumber":"37",
    "addr:postcode":"2600",
    "addr:street":"Fruithoflaan;Antwerpen",
    "iso:country":"BE",
    "sg:address":"Fruithoflaan 37",
    "sg:city":"Berchem",
    "sg:classifiers":[
        {
            "category":"Banks & Credit Unions",
            "subcategory":"Bank",
            "type":"Services"
        }
    ],
    "sg:phone":"+32 3 440 18 60",
    "sg:postcode":"2600",
    "sg:province":"Antwerpen",
    "wof:name":"Aslk-cger Bank",
    "wof:placetype":"venue"
},
  "geometry": {"coordinates":[4.4370269775,51.1818389893],"type":"Point"}
}