{
  "type": "Feature",
  "properties": {
    "iso:country":"BE",
    "sg:address":"Zevenbergen 70",
    "sg:city":"Lier",
    "sg:classifiers":[
        {
            "category":"Organizations",
            "subcategory":"Community Association",
            "type":"Services"
        }
    ],
    "sg:phone":"+32 3 488 58 01",
    "sg:postcode":"2500",
    "sg:province":"Antwerpen",
    "sg:tags":[
        "cultural"
    ],
    "wof:name":"Amici",
    "wof:placetype":"venue"
},
  "geometry": {"coordinates":[4.537774086,51.1432991028],"type":"Point"}
}