{
  "type": "Feature",
  "properties": {
    "addr:full":"Gouwberg 39 Schilde Antwerpen 2970",
    "addr:housenumber":"39",
    "addr:postcode":"2970",
    "addr:street":"Gouwberg",
    "iso:country":"BE",
    "sg:address":"Gouwberg 39",
    "sg:city":"Schilde",
    "sg:orig_category":"Tuinen",
    "sg:phone":"+32 3 353 69 25",
    "sg:postcode":"2970",
    "sg:province":"Antwerpen",
    "wof:name":"Gupa",
    "wof:placetype":"venue"
},
  "geometry": {"coordinates":[4.5572500229,51.2337646484],"type":"Point"}
}