{
  "type": "Feature",
  "properties": {
    "addr:full":"Antoine Dansaertstraat 24 Brussel/bruxelles Bruxelles-Capitale 1000",
    "addr:housenumber":"24",
    "addr:postcode":"1000",
    "addr:street":"Antoine Dansaertstraat;/",
    "iso:country":"BE",
    "sg:address":"Antoine Dansaertstraat 24",
    "sg:city":"Brussel/bruxelles",
    "sg:orig_category":"Binnenhuisarchitecten",
    "sg:phone":"+32 2 513 02 70",
    "sg:postcode":"1000",
    "sg:province":"Bruxelles-Capitale",
    "wof:name":"Filip Huyghe",
    "wof:placetype":"venue"
},
  "geometry": {"coordinates":[4.3472290039,50.8492584229],"type":"Point"}
}