{
  "type": "Feature",
  "properties": {
    "addr:full":"Chauss\u00e9e De Wavre 864 Bruxelles (etterbeek) Bruxelles-Capitale 1040",
    "addr:housenumber":"864",
    "addr:postcode":"1040",
    "addr:street":"Chausse\u0301E De Wavre",
    "iso:country":"BE",
    "sg:address":"Chauss\u00e9e De Wavre 864",
    "sg:city":"Bruxelles (etterbeek)",
    "sg:classifiers":[
        {
            "category":"Professional",
            "subcategory":"Secretarial Services",
            "type":"Services"
        }
    ],
    "sg:phone":"+32 2 629 08 60",
    "sg:postcode":"1040",
    "sg:province":"Bruxelles-Capitale",
    "sg:tags":[
        "delivery",
        "messenger"
    ],
    "wof:name":"Mpm",
    "wof:placetype":"venue"
},
  "geometry": {"coordinates":[4.3940210342,50.8282318115],"type":"Point"}
}