{
  "type": "Feature",
  "properties": {
    "addr:full":"Rue Des Nations Unies 129 Ans (alleur) Li\u00e8ge 4432",
    "addr:housenumber":"129",
    "addr:postcode":"4432",
    "addr:street":"Rue Des Nations Unies",
    "iso:country":"BE",
    "sg:address":"Rue Des Nations Unies 129",
    "sg:city":"Ans (alleur)",
    "sg:classifiers":[
        {
            "category":"Retail",
            "subcategory":"Repair Shop",
            "type":"Services"
        }
    ],
    "sg:phone":"+32 4 263 13 61",
    "sg:postcode":"4432",
    "sg:province":"Li\u00e8ge",
    "sg:tags":[
        "radio",
        "television",
        "-",
        "maintenance"
    ],
    "wof:name":"A.v.d.",
    "wof:placetype":"venue"
},
  "geometry": {"coordinates":[5.5207080841,50.6658935547],"type":"Point"}
}