{
  "type": "Feature",
  "properties": {
    "iso:country":"BE",
    "sg:address":"Liefkemoreslaan 21",
    "sg:city":"Bredene",
    "sg:classifiers":[
        {
            "category":"Food & Beverages",
            "subcategory":"Fruits & Vegetables",
            "type":"Retail Goods"
        }
    ],
    "sg:phone":"+32 59 32 49 26",
    "sg:postcode":"8450",
    "sg:province":"West-Vlaanderen",
    "sg:tags":[
        "l\u00e9gumes"
    ],
    "wof:name":"Pascal Hoorelbeke",
    "wof:placetype":"venue"
},
  "geometry": {"coordinates":[2.9575529099,51.2373504639],"type":"Point"}
}