{
  "type": "Feature",
  "properties": {
    "iso:country":"BE",
    "sg:address":"Rue Auguste Renard 4",
    "sg:city":"Floreffe",
    "sg:classifiers":[
        {
            "category":"Food & Beverages",
            "subcategory":"Cheese",
            "type":"Retail Goods"
        }
    ],
    "sg:phone":"+32 81 44 47 64",
    "sg:postcode":"5150",
    "sg:province":"Namur",
    "sg:tags":[
        "-"
    ],
    "wof:name":"Laurette (chez)",
    "wof:placetype":"venue"
},
  "geometry": {"coordinates":[4.7600569725,50.435131073],"type":"Point"}
}