{
  "type": "Feature",
  "properties": {
    "addr:full":"Veldstraat 33 Oostkamp West-Vlaanderen 8020",
    "addr:housenumber":"33",
    "addr:postcode":"8020",
    "addr:street":"Veldstraat",
    "iso:country":"BE",
    "sg:address":"Veldstraat 33",
    "sg:city":"Oostkamp",
    "sg:classifiers":[
        {
            "category":"Real Estate",
            "subcategory":"Architect",
            "type":"Services"
        }
    ],
    "sg:phone":"+32 50 82 62 11",
    "sg:postcode":"8020",
    "sg:province":"West-Vlaanderen",
    "wof:name":"Deruwe P",
    "wof:placetype":"venue"
},
  "geometry": {"coordinates":[3.2663400173,51.1649703979],"type":"Point"}
}