{
  "type": "Feature",
  "properties": {
    "addr:full":"Grand'place 29 Quaregnon Hainaut 7390",
    "addr:housenumber":"29",
    "addr:postcode":"7390",
    "addr:street":"Grand'Place",
    "iso:country":"BE",
    "sg:address":"Grand'place 29",
    "sg:city":"Quaregnon",
    "sg:orig_category":"Banques and organismes de cr\u00e9dit",
    "sg:phone":"+32 65 78 41 60",
    "sg:postcode":"7390",
    "sg:province":"Hainaut",
    "wof:name":"Dexia",
    "wof:placetype":"venue"
},
  "geometry": {"coordinates":[3.8655259609,50.4423751831],"type":"Point"}
}