{
  "type": "Feature",
  "properties": {
    "addr:full":"Mortinsart 15 Etalle Luxembourg 6740",
    "addr:housenumber":"15",
    "addr:postcode":"6740",
    "addr:street":"Mortinsart",
    "iso:country":"BE",
    "sg:address":"Mortinsart 15",
    "sg:city":"Etalle",
    "sg:orig_category":"Eleveurs de bovins",
    "sg:phone":"+32 63 41 11 54",
    "sg:postcode":"6740",
    "sg:province":"Luxembourg",
    "wof:name":"Henry Thiry",
    "wof:placetype":"venue"
},
  "geometry": {"coordinates":[5.5877799988,49.7048072815],"type":"Point"}
}