{
  "type": "Feature",
  "properties": {
    "addr:full":"Place Du Grand Sablon 14 Brussel/bruxelles Bruxelles-Capitale 1000",
    "addr:housenumber":"14",
    "addr:postcode":"1000",
    "addr:street":"Place Du Grand Sablon;/",
    "iso:country":"BE",
    "sg:address":"Place Du Grand Sablon 14",
    "sg:city":"Brussel/bruxelles",
    "sg:orig_category":"Antiquit\u00e9s",
    "sg:phone":"+32 2 512 14 17",
    "sg:postcode":"1000",
    "sg:province":"Bruxelles-Capitale",
    "wof:name":"Maison Villars",
    "wof:placetype":"venue"
},
  "geometry": {"coordinates":[4.3550639153,50.8411636353],"type":"Point"}
}