{
  "type": "Feature",
  "properties": {
    "iso:country":"BE",
    "sg:address":"Veemarkt 28",
    "sg:city":"Mechelen",
    "sg:orig_category":"Baby- and kinderkleding Dameskledingzaken Herenkledingzaken Textiel",
    "sg:phone":"+32 15 21 11 15",
    "sg:postcode":"2800",
    "sg:province":"Antwerpen",
    "wof:name":"Wibra",
    "wof:placetype":"venue"
},
  "geometry": {"coordinates":[4.4842371941,51.0287742615],"type":"Point"}
}