{
  "type": "Feature",
  "properties": {
    "iso:country":"BE",
    "sg:address":"Dokter Adriaan Martenslaan 5",
    "sg:city":"Deinze (astene)",
    "sg:classifiers":[
        {
            "category":"Real Estate",
            "subcategory":"Architect",
            "type":"Services"
        }
    ],
    "sg:phone":"+32 9 386 25 43",
    "sg:postcode":"9800",
    "sg:province":"Oost-Vlaanderen",
    "wof:name":"Bollez P",
    "wof:placetype":"venue"
},
  "geometry": {"coordinates":[3.5206100941,50.9896316528],"type":"Point"}
}