{
  "type": "Feature",
  "properties": {
    "iso:country":"BE",
    "sg:address":"Hotelstraat 5b7a",
    "sg:city":"Westerlo",
    "sg:orig_category":"Electrom\u00e9nager, t\u00e9l\u00e9visions and radios. R\u00e9parations d'appareils \u00e9lectrom\u00e9nagers",
    "sg:phone":"+32 14 59 16 42",
    "sg:postcode":"2260",
    "sg:province":"Antwerpen",
    "wof:name":"Eldi",
    "wof:placetype":"venue"
},
  "geometry": {"coordinates":[4.9402132034,51.1318626404],"type":"Point"}
}