{
  "type": "Feature",
  "properties": {
    "addr:full":"Rue Du Vingt-quatre Ao\u00fbt 13a Virton (latour) Luxembourg 6761",
    "addr:housenumber":"13a",
    "addr:postcode":"6761",
    "addr:street":"Rue Du Vingt-Quatre Aou\u0302T;Latour",
    "iso:country":"BE",
    "sg:address":"Rue Du Vingt-quatre Ao\u00fbt 13a",
    "sg:city":"Virton (latour)",
    "sg:classifiers":[
        {
            "category":"Retail",
            "subcategory":"Auto Repair",
            "type":"Services"
        }
    ],
    "sg:phone":"+32 63 58 38 11",
    "sg:postcode":"6761",
    "sg:province":"Luxembourg",
    "sg:tags":[
        "garage"
    ],
    "wof:name":"Boulanger A",
    "wof:placetype":"venue"
},
  "geometry": {"coordinates":[5.571158886,49.5583076477],"type":"Point"}
}