{
  "type": "Feature",
  "properties": {
    "iso:country":"BE",
    "sg:address":"Sint-stevenstraat 51ba",
    "sg:city":"Zelzate",
    "sg:orig_category":"Rundveehouders Varkenskwekers",
    "sg:phone":"+32 9 345 69 18",
    "sg:postcode":"9060",
    "sg:province":"Oost-Vlaanderen",
    "wof:name":"Yvan Van De Velde",
    "wof:placetype":"venue"
},
  "geometry": {"coordinates":[3.8189139366,51.2078704834],"type":"Point"}
}