{
  "type": "Feature",
  "properties": {
    "addr:full":"Tieltse Baan 86 Aarschot Vlaams-Brabant 3200",
    "addr:housenumber":"86",
    "addr:postcode":"3200",
    "addr:street":"Tieltse Baan",
    "iso:country":"BE",
    "sg:address":"Tieltse Baan 86",
    "sg:city":"Aarschot",
    "sg:orig_category":"Installation \u00e9lectrique r\u00e9sidentielle",
    "sg:phone":"+32 16 56 25 49",
    "sg:postcode":"3200",
    "sg:province":"Vlaams-Brabant",
    "wof:name":"Luc Buvens",
    "wof:placetype":"venue"
},
  "geometry": {"coordinates":[4.848856926,50.9704437256],"type":"Point"}
}