{
  "type": "Feature",
  "properties": {
    "iso:country":"BE",
    "sg:address":"Ernest Van Dijckkaai 18",
    "sg:city":"Antwerpen",
    "sg:classifiers":[
        {
            "category":"Bars & Pubs",
            "type":"Food & Drink"
        }
    ],
    "sg:phone":"+32 3 213 38 53",
    "sg:postcode":"2000",
    "sg:province":"Antwerpen",
    "wof:name":"Nef\u00e9li",
    "wof:placetype":"venue"
},
  "geometry": {"coordinates":[4.3962850571,51.2198638916],"type":"Point"}
}