{
  "type": "Feature",
  "properties": {
    "iso:country":"BE",
    "sg:address":"Peerderbaan 96",
    "sg:city":"Bree",
    "sg:classifiers":[
        {
            "category":"Shopping",
            "subcategory":"Crafts & Fabrics",
            "type":"Retail Goods"
        }
    ],
    "sg:phone":"+32 9 228 26 42",
    "sg:postcode":"3960",
    "sg:province":"Limburg",
    "sg:tags":[
        "trade",
        "timber"
    ],
    "wof:name":"R. Impens Houthandel Nv",
    "wof:placetype":"venue"
},
  "geometry": {"coordinates":[3.7527799606,51.0646476746],"type":"Point"}
}