{
  "type": "Feature",
  "properties": {
    "iso:country":"BE",
    "sg:address":"Hof Te Bollebeekln 5",
    "sg:city":"Mollem",
    "sg:classifiers":[
        {
            "category":"Professional",
            "subcategory":"Printing & Photocopies",
            "type":"Services"
        }
    ],
    "sg:phone":"+32 2 454 15 17",
    "sg:postcode":"1730",
    "sg:province":"Vlaams-Brabant",
    "sg:tags":[
        "publishing"
    ],
    "wof:name":"Polypress Nv",
    "wof:placetype":"venue"
},
  "geometry": {"coordinates":[4.2393269539,50.9193191528],"type":"Point"}
}