{
  "type": "Feature",
  "properties": {
    "addr:full":"Chauss\u00c9e De Boondael 427 Elsene/ixelles Bruxelles-Capitale 1050",
    "addr:housenumber":"427",
    "addr:postcode":"1050",
    "addr:street":"Chausse\u0301E De Boondael",
    "iso:country":"BE",
    "sg:address":"Chauss\u00c9e De Boondael 427",
    "sg:city":"Elsene/ixelles",
    "sg:classifiers":[
        {
            "category":"Shopping",
            "subcategory":"Clothing, Apparel, & Fashions",
            "type":"Retail Goods"
        }
    ],
    "sg:phone":"+32 2 649 46 17",
    "sg:postcode":"1050",
    "sg:province":"Bruxelles-Capitale",
    "sg:tags":[
        "lingerie",
        "sous-v\u00eatements"
    ],
    "wof:name":"La Boutique De Sophie",
    "wof:placetype":"venue"
},
  "geometry": {"coordinates":[4.3885188103,50.8171081543],"type":"Point"}
}