{
  "type": "Feature",
  "properties": {
    "addr:full":"Joseph Druezstraat 16 Ganshoren/ganshoren Bruxelles-Capitale 1083",
    "addr:housenumber":"16",
    "addr:postcode":"1083",
    "addr:street":"Joseph Druezstraat",
    "iso:country":"BE",
    "sg:address":"Joseph Druezstraat 16",
    "sg:city":"Ganshoren/ganshoren",
    "sg:orig_category":"Fotografen and fotostudio's",
    "sg:phone":"+32 2 428 01 63",
    "sg:postcode":"1083",
    "sg:province":"Bruxelles-Capitale",
    "wof:name":"Thierry Dachelet",
    "wof:placetype":"venue"
},
  "geometry": {"coordinates":[4.317261219,50.8718719482],"type":"Point"}
}