{
  "type": "Feature",
  "properties": {
    "iso:country":"BE",
    "sg:address":"Noorderlaan 107",
    "sg:city":"Antwerpen",
    "sg:classifiers":[
        {
            "category":"Professional",
            "subcategory":"Testing Lab",
            "type":"Services"
        }
    ],
    "sg:phone":"+32 3 541 97 47",
    "sg:postcode":"2030",
    "sg:province":"Antwerpen",
    "sg:tags":[
        "laboratory",
        "-"
    ],
    "wof:name":"Schelde Lab Antwerpen",
    "wof:placetype":"venue"
},
  "geometry": {"coordinates":[4.4186329842,51.2616500854],"type":"Point"}
}