{
  "type": "Feature",
  "properties": {
    "iso:country":"BE",
    "sg:address":"Place Andr\u00c9 Ryckmans 17",
    "sg:city":"Namur",
    "sg:classifiers":[
        {
            "category":"Cafe",
            "type":"Food & Drink"
        }
    ],
    "sg:phone":"+32 81 73 89 75",
    "sg:postcode":"5000",
    "sg:province":"Namur",
    "sg:tags":[
        "caf\u00e9s"
    ],
    "wof:name":"Sopa Fitore",
    "wof:placetype":"venue"
},
  "geometry": {"coordinates":[4.849916935,50.466796875],"type":"Point"}
}