{
  "type": "Feature",
  "properties": {
    "iso:country":"BE",
    "sg:address":"Oude Baan 65",
    "sg:city":"Maasmechelen (eisden)",
    "sg:classifiers":[
        {
            "category":"Banks & Credit Unions",
            "subcategory":"Investment Brokerage",
            "type":"Services"
        }
    ],
    "sg:phone":"+32 89 76 42 89",
    "sg:postcode":"3630",
    "sg:province":"Limburg",
    "sg:tags":[
        "coil",
        "electric",
        "winding"
    ],
    "wof:name":"Henry A",
    "wof:placetype":"venue"
},
  "geometry": {"coordinates":[5.6935558319,50.9858322144],"type":"Point"}
}