{
  "type": "Feature",
  "properties": {
    "iso:country":"BE",
    "sg:address":"Rue De La Station 35",
    "sg:city":"La Bruyere",
    "sg:orig_category":"Journaux. Tabac",
    "sg:phone":"+32 81 56 88 93",
    "sg:postcode":"5080",
    "sg:province":"Namur",
    "wof:name":"Librairie Swalens",
    "wof:placetype":"venue"
},
  "geometry": {"coordinates":[4.8035330772,50.5013580322],"type":"Point"}
}