{
  "type": "Feature",
  "properties": {
    "addr:full":"Rue De Filipesti 5 Soumagne Li\u00e8ge 4630",
    "addr:housenumber":"5",
    "addr:postcode":"4630",
    "addr:street":"Rue De Filipesti",
    "iso:country":"BE",
    "sg:address":"Rue De Filipesti 5",
    "sg:city":"Soumagne",
    "sg:classifiers":[
        {
            "category":"Retail",
            "subcategory":"Car Wash",
            "type":"Services"
        }
    ],
    "sg:phone":"+32 4 355 13 30",
    "sg:postcode":"4630",
    "sg:province":"Li\u00e8ge",
    "sg:tags":[
        "automobile",
        "washing",
        "-",
        "truck"
    ],
    "wof:name":"Car Wash Service Mobile",
    "wof:placetype":"venue"
},
  "geometry": {"coordinates":[5.7518110275,50.6123771667],"type":"Point"}
}