{
  "type": "Feature",
  "properties": {
    "iso:country":"BE",
    "sg:address":"Boulevard De La Sauveni\u00e8re 158",
    "sg:city":"Li\u00e8ge 1",
    "sg:classifiers":[
        {
            "category":"Travel",
            "subcategory":"Travel Agent",
            "type":"Entertainment"
        }
    ],
    "sg:phone":"+32 4 221 27 27",
    "sg:postcode":"4000",
    "sg:province":"Li\u00e8ge",
    "sg:tags":[
        "agency"
    ],
    "wof:name":"Halloween",
    "wof:placetype":"venue"
},
  "geometry": {"coordinates":[5.5675549507,50.6408691406],"type":"Point"}
}