{
  "type": "Feature",
  "properties": {
    "iso:country":"BE",
    "sg:address":"Schaaflaan 21",
    "sg:city":"Zandhoven",
    "sg:orig_category":"Installatie van houten of kunststof schrijnwerk MEUBELONTWERP AND -INSTALLATIE",
    "sg:phone":"+32 3 484 51 97",
    "sg:postcode":"2242",
    "sg:province":"Antwerpen",
    "wof:name":"Caluwe Keukenontwerp",
    "wof:placetype":"venue"
},
  "geometry": {"coordinates":[4.6976671219,51.2191162109],"type":"Point"}
}