{
  "type": "Feature",
  "properties": {
    "iso:country":"BE",
    "sg:address":"Sint-paulusstraat 41",
    "sg:city":"Antwerpen",
    "sg:orig_category":"Boekenuitgeverijen Diverse grafische activiteiten",
    "sg:phone":"+32 3 227 26 40",
    "sg:postcode":"2000",
    "sg:province":"Antwerpen",
    "wof:name":"Barends En Pijnappel",
    "wof:placetype":"venue"
},
  "geometry": {"coordinates":[4.4028868675,51.2241325378],"type":"Point"}
}