{
  "type": "Feature",
  "properties": {
    "iso:country":"BE",
    "sg:address":"Chauss\u00c9e D'alsemberg 706",
    "sg:city":"Ukkel/uccle",
    "sg:orig_category":"Ordinateurs and \u00e9quipement informatique. E-activit\u00e9s. Mat\u00e9riel de T\u00e9l\u00e9communication",
    "sg:phone":"+32 2 345 40 43",
    "sg:postcode":"1180",
    "sg:province":"Bruxelles-Capitale",
    "wof:name":"Gsm Planet",
    "wof:placetype":"venue"
},
  "geometry": {"coordinates":[4.3368787766,50.8022117615],"type":"Point"}
}