{
  "type": "Feature",
  "properties": {
    "iso:country":"BE",
    "sg:address":"Ovenveldstraat 9",
    "sg:city":"Melle",
    "sg:classifiers":[
        {
            "category":"Arena",
            "subcategory":"Sports Club",
            "type":"Entertainment"
        }
    ],
    "sg:phone":"+32 9 252 41 42",
    "sg:postcode":"9090",
    "sg:province":"Oost-Vlaanderen",
    "sg:tags":[
        "de"
    ],
    "wof:name":"Pc Verbroedering",
    "wof:placetype":"venue"
},
  "geometry": {"coordinates":[3.802259922,50.9957618713],"type":"Point"}
}