{
  "type": "Feature",
  "properties": {
    "addr:full":"Avenue Louis David 55 Waterloo Brabant Wallon 1410",
    "addr:housenumber":"55",
    "addr:postcode":"1410",
    "addr:street":"Avenue Louis David",
    "iso:country":"BE",
    "sg:address":"Avenue Louis David 55",
    "sg:city":"Waterloo",
    "sg:classifiers":[
        {
            "category":"Health Services",
            "subcategory":"Doctor",
            "type":"Services"
        }
    ],
    "sg:phone":"+32 2 387 07 66",
    "sg:postcode":"1410",
    "sg:province":"Brabant Wallon",
    "sg:tags":[
        "medicinephysicians",
        "surgeon"
    ],
    "wof:name":"Emponza L",
    "wof:placetype":"venue"
},
  "geometry": {"coordinates":[4.3987159729,50.6899261475],"type":"Point"}
}