{
  "type": "Feature",
  "properties": {
    "addr:full":"Place D'italie 5b21 Li\u00c8ge Li\u00e8ge 4020",
    "addr:housenumber":"5b21",
    "addr:postcode":"4020",
    "addr:street":"Place D'Italie",
    "iso:country":"BE",
    "sg:address":"Place D'italie 5b21",
    "sg:city":"Li\u00c8ge",
    "sg:orig_category":"Boekenuitgeverijen",
    "sg:phone":"+32 4 343 80 96",
    "sg:postcode":"4020",
    "sg:province":"Li\u00e8ge",
    "wof:name":"Marie Chabot",
    "wof:placetype":"venue"
},
  "geometry": {"coordinates":[5.5746598244,50.632434845],"type":"Point"}
}