{
  "type": "Feature",
  "properties": {
    "addr:full":"Rue De Tubize 12e Ittre (virginal-samme) Brabant Wallon 1460",
    "addr:housenumber":"12e;1460",
    "addr:street":"Rue De Tubize",
    "iso:country":"BE",
    "sg:address":"Rue De Tubize 12e",
    "sg:city":"Ittre (virginal-samme)",
    "sg:classifiers":[
        {
            "category":"Banks & Credit Unions",
            "subcategory":"Investment Brokerage",
            "type":"Services"
        }
    ],
    "sg:phone":"+32 67 64 66 96",
    "sg:postcode":"1460",
    "sg:province":"Brabant Wallon",
    "sg:tags":[
        "printing",
        "-"
    ],
    "wof:name":"Alphascript Sa",
    "wof:placetype":"venue"
},
  "geometry": {"coordinates":[4.2163081169,50.653842926],"type":"Point"}
}