{
  "type": "Feature",
  "properties": {
    "iso:country":"BE",
    "sg:address":"Schoolstraat 3",
    "sg:city":"Houthulst",
    "sg:orig_category":"Afval and schroot Gh",
    "sg:phone":"+32 51 70 33 02",
    "sg:postcode":"8650",
    "sg:province":"West-Vlaanderen",
    "wof:name":"Jean-pierre Clauw",
    "wof:placetype":"venue"
},
  "geometry": {"coordinates":[2.9388580322,50.9780426025],"type":"Point"}
}