{
  "type": "Feature",
  "properties": {
    "addr:full":"Avenue Adolphe Lacombl\u00e9 69 Bruxelles (schaerbeek) Bruxelles-Capitale 1030",
    "addr:housenumber":"69",
    "addr:postcode":"1030",
    "addr:street":"Avenue Adolphe Lacomble\u0301",
    "iso:country":"BE",
    "sg:address":"Avenue Adolphe Lacombl\u00e9 69",
    "sg:city":"Bruxelles (schaerbeek)",
    "sg:classifiers":[
        {
            "category":"Social Services",
            "type":"Services"
        }
    ],
    "sg:phone":"+32 2 735 24 24",
    "sg:postcode":"1030",
    "sg:province":"Bruxelles-Capitale",
    "wof:name":"F\u00e9d\u00e9ration De L'aide & Des Soins \u00e0 Domicile",
    "wof:placetype":"venue"
},
  "geometry": {"coordinates":[4.3987298012,50.8483276367],"type":"Point"}
}