{
  "type": "Feature",
  "properties": {
    "addr:full":"Oostmeersdreef 55 Deinze Oost-Vlaanderen 9800",
    "addr:housenumber":"55",
    "addr:postcode":"9800",
    "addr:street":"Oostmeersdreef",
    "iso:country":"BE",
    "sg:address":"Oostmeersdreef 55",
    "sg:city":"Deinze",
    "sg:orig_category":"Afval and schroot Gh",
    "sg:phone":"+32 9 386 23 13",
    "sg:postcode":"9800",
    "sg:province":"Oost-Vlaanderen",
    "wof:name":"Raoul Baetsle",
    "wof:placetype":"venue"
},
  "geometry": {"coordinates":[3.5362648964,50.9828643799],"type":"Point"}
}