{
  "type": "Feature",
  "properties": {
    "addr:full":"Bondgenotenlaan 105 Leuven Vlaams-Brabant 3000",
    "addr:housenumber":"105",
    "addr:postcode":"3000",
    "addr:street":"Bondgenotenlaan",
    "iso:country":"BE",
    "sg:address":"Bondgenotenlaan 105",
    "sg:city":"Leuven",
    "sg:orig_category":"V\u00eatements pour Hommes",
    "sg:phone":"+32 16 22 27 12",
    "sg:postcode":"3000",
    "sg:province":"Vlaams-Brabant",
    "wof:name":"Adam's",
    "wof:placetype":"venue"
},
  "geometry": {"coordinates":[4.7096819878,50.8804283142],"type":"Point"}
}