{
  "type": "Feature",
  "properties": {
    "addr:full":"Henri Duchatelstraat 165 Moeskroen/mouscron Hainaut 7700",
    "addr:housenumber":"165",
    "addr:postcode":"7700",
    "addr:street":"Henri Duchatelstraat",
    "iso:country":"BE",
    "sg:address":"Henri Duchatelstraat 165",
    "sg:city":"Moeskroen/mouscron",
    "sg:classifiers":[
        {
            "category":"Professional",
            "subcategory":"Accounting & Tax Preparation",
            "type":"Services"
        }
    ],
    "sg:phone":"+32 56 34 41 14",
    "sg:postcode":"7700",
    "sg:province":"Hainaut",
    "sg:tags":[
        "accountant"
    ],
    "wof:name":"F. Maroy",
    "wof:placetype":"venue"
},
  "geometry": {"coordinates":[3.2323200703,50.7400932312],"type":"Point"}
}