{
  "type": "Feature",
  "properties": {
    "iso:country":"BE",
    "sg:address":"Dennenlaan 9",
    "sg:city":"Vorselaar",
    "sg:orig_category":"Instituts de beaut\u00e9",
    "sg:phone":"+32 14 50 15 98",
    "sg:postcode":"2290",
    "sg:province":"Antwerpen",
    "wof:name":"Instituut Christel",
    "wof:placetype":"venue"
},
  "geometry": {"coordinates":[4.7822980881,51.2074508667],"type":"Point"}
}