{
  "type": "Feature",
  "properties": {
    "iso:country":"BE",
    "sg:address":"Sint-amandsstraat 150b",
    "sg:city":"Grimbergen",
    "sg:orig_category":"Kapsalons",
    "sg:phone":"+32 2 267 19 13",
    "sg:postcode":"1853",
    "sg:province":"Vlaams-Brabant",
    "wof:name":"Alain K",
    "wof:placetype":"venue"
},
  "geometry": {"coordinates":[4.3601942062,50.9054374695],"type":"Point"}
}