{
  "type": "Feature",
  "properties": {
    "addr:full":"Jokerstraat 27 Turnhout Antwerpen 2300",
    "addr:housenumber":"27",
    "addr:postcode":"2300",
    "addr:street":"Jokerstraat",
    "iso:country":"BE",
    "sg:address":"Jokerstraat 27",
    "sg:city":"Turnhout",
    "sg:orig_category":"Dierenartsen",
    "sg:phone":"+32 14 43 85 60",
    "sg:postcode":"2300",
    "sg:province":"Antwerpen",
    "wof:name":"M. Engelen",
    "wof:placetype":"venue"
},
  "geometry": {"coordinates":[4.9171218872,51.3107681274],"type":"Point"}
}