{
  "type": "Feature",
  "properties": {
    "addr:full":"Rue De Theux 15 Olne Li\u00e8ge 4877",
    "addr:housenumber":"15",
    "addr:postcode":"4877",
    "addr:street":"Rue De Theux",
    "iso:country":"BE",
    "sg:address":"Rue De Theux 15",
    "sg:city":"Olne",
    "sg:orig_category":"Slagers",
    "sg:phone":"+32 4 358 54 51",
    "sg:postcode":"4877",
    "sg:province":"Li\u00e8ge",
    "wof:name":"Jacques Hanlet",
    "wof:placetype":"venue"
},
  "geometry": {"coordinates":[5.7166008949,50.6042327881],"type":"Point"}
}