{
  "type": "Feature",
  "properties": {
    "iso:country":"BE",
    "sg:address":"Rue De Tillier 17",
    "sg:city":"Fernelmont (marchovelette)",
    "sg:classifiers":[
        {
            "category":"Health Services",
            "subcategory":"Health Practitioner",
            "type":"Services"
        }
    ],
    "sg:phone":"+32 81 21 00 89",
    "sg:postcode":"5380",
    "sg:province":"Namur",
    "sg:tags":[
        "physiotherapist"
    ],
    "wof:name":"Dewulf B\u00e9n\u00e9dicte",
    "wof:placetype":"venue"
},
  "geometry": {"coordinates":[4.9413361549,50.5264282227],"type":"Point"}
}