{
  "type": "Feature",
  "properties": {
    "iso:country":"BE",
    "sg:address":"Rue Edouard Stuckens 160",
    "sg:city":"Bruxelles (evere)",
    "sg:classifiers":[
        {
            "category":"Personal",
            "subcategory":"Nail Salon",
            "type":"Services"
        }
    ],
    "sg:phone":"+32 2 215 40 95",
    "sg:postcode":"1140",
    "sg:province":"Bruxelles-Capitale",
    "sg:tags":[
        "pedicure"
    ],
    "wof:name":"Vandenschrik Ch",
    "wof:placetype":"venue"
},
  "geometry": {"coordinates":[4.4001479149,50.8765983582],"type":"Point"}
}