{
  "type": "Feature",
  "properties": {
    "addr:full":"Rue Du Parc 15b51 Li\u00c8ge Li\u00e8ge 4020",
    "addr:housenumber":"15b51",
    "addr:postcode":"4020",
    "addr:street":"Rue Du Parc",
    "iso:country":"BE",
    "sg:address":"Rue Du Parc 15b51",
    "sg:city":"Li\u00c8ge",
    "sg:orig_category":"Artsen and specialisten",
    "sg:phone":"+32 4 342 87 89",
    "sg:postcode":"4020",
    "sg:province":"Li\u00e8ge",
    "wof:name":"Yves Kaisin",
    "wof:placetype":"venue"
},
  "geometry": {"coordinates":[5.5753102303,50.6317405701],"type":"Point"}
}