{
  "type": "Feature",
  "properties": {
    "addr:full":"Rue Du Pont Du Christ 42 Wavre Brabant Wallon 1300",
    "addr:housenumber":"42;1300",
    "addr:street":"Rue Du Pont Du Christ",
    "iso:country":"BE",
    "sg:address":"Rue Du Pont Du Christ 42",
    "sg:city":"Wavre",
    "sg:orig_category":"Textiles. Souvenirs and objets artisanaux",
    "sg:phone":"+32 10 22 22 78",
    "sg:postcode":"1300",
    "sg:province":"Brabant Wallon",
    "wof:name":"Jeu De Dames",
    "wof:placetype":"venue"
},
  "geometry": {"coordinates":[4.6094608307,50.7158088684],"type":"Point"}
}