{
  "type": "Feature",
  "properties": {
    "iso:country":"BE",
    "sg:address":"Lepelstraat 52b",
    "sg:city":"Leuven",
    "sg:orig_category":"R\u00e9alisation de programmes and logiciels",
    "sg:phone":"+32 477 80 50 21",
    "sg:postcode":"3000",
    "sg:province":"Vlaams-Brabant",
    "wof:name":"Vector Bross",
    "wof:placetype":"venue"
},
  "geometry": {"coordinates":[4.708381176,50.8807525635],"type":"Point"}
}