{
  "type": "Feature",
  "properties": {
    "addr:full":"Avenue Nellie Melba 54 Anderlecht Bruxelles-Capitale 1070",
    "addr:housenumber":"54",
    "addr:postcode":"1070",
    "addr:street":"Avenue Nellie Melba",
    "iso:country":"BE",
    "sg:address":"Avenue Nellie Melba 54",
    "sg:city":"Anderlecht",
    "sg:classifiers":[
        {
            "category":"Autos & Motor Vehicles",
            "subcategory":"Fuel & Gas Station",
            "type":"Retail Goods"
        }
    ],
    "sg:phone":"+32 2 522 91 15",
    "sg:postcode":"1070",
    "sg:province":"Bruxelles-Capitale",
    "sg:tags":[
        "stations-service",
        "carburants"
    ],
    "wof:name":"Bp",
    "wof:placetype":"venue"
},
  "geometry": {"coordinates":[4.2936120033,50.8294906616],"type":"Point"}
}