{
  "type": "Feature",
  "properties": {
    "addr:full":"Bas-puison 78 Nivelles Brabant Wallon 1400",
    "addr:housenumber":"78",
    "addr:postcode":"1400",
    "addr:street":"Bas-Puison",
    "iso:country":"BE",
    "sg:address":"Bas-puison 78",
    "sg:city":"Nivelles",
    "sg:orig_category":"Rundveehouders",
    "sg:phone":"+32 67 21 35 81",
    "sg:postcode":"1400",
    "sg:province":"Brabant Wallon",
    "wof:name":"Vandemaele Robert & Eddy",
    "wof:placetype":"venue"
},
  "geometry": {"coordinates":[4.2868680954,50.5879707336],"type":"Point"}
}