{
  "type": "Feature",
  "properties": {
    "iso:country":"BE",
    "sg:address":"Rue Pr\u00c9al 8",
    "sg:city":"Erezee",
    "sg:classifiers":[
        {
            "category":"Restaurant",
            "type":"Food & Drink"
        }
    ],
    "sg:phone":"+32 86 47 70 44",
    "sg:postcode":"6997",
    "sg:province":"Luxembourg",
    "wof:name":"Fant\u00d4me",
    "wof:placetype":"venue"
},
  "geometry": {"coordinates":[5.5588469505,50.2911453247],"type":"Point"}
}