{
  "type": "Feature",
  "properties": {
    "addr:full":"Trichelhoek 10 Laakdal Antwerpen 2430",
    "addr:housenumber":"10",
    "addr:postcode":"2430",
    "addr:street":"Trichelhoek",
    "iso:country":"BE",
    "sg:address":"Trichelhoek 10",
    "sg:city":"Laakdal",
    "sg:orig_category":"Sportclubs Sportterreinen and installaties behalve sportcentra",
    "sg:phone":"+32 14 86 79 55",
    "sg:postcode":"2430",
    "sg:province":"Antwerpen",
    "wof:name":"F.c. St.dymphna Zammel",
    "wof:placetype":"venue"
},
  "geometry": {"coordinates":[5.0687851906,51.0857543945],"type":"Point"}
}