{
  "type": "Feature",
  "properties": {
    "iso:country":"BE",
    "sg:address":"Gelovigenstraat 35",
    "sg:city":"Ukkel/uccle",
    "sg:orig_category":"Drukkerijen and copyshops Immobili\u00ebnkantoren",
    "sg:phone":"+32 2 347 54 30",
    "sg:postcode":"1180",
    "sg:province":"Bruxelles-Capitale",
    "wof:name":"Byll Number Two",
    "wof:placetype":"venue"
},
  "geometry": {"coordinates":[4.3386750221,50.8025550842],"type":"Point"}
}