{
  "type": "Feature",
  "properties": {
    "iso:country":"BE",
    "sg:address":"Turnhoutsebaan 136",
    "sg:city":"Wijnegem",
    "sg:classifiers":[
        {
            "category":"Health Services",
            "subcategory":"Doctor",
            "type":"Services"
        }
    ],
    "sg:phone":"+32 3 354 46 02",
    "sg:postcode":"2110",
    "sg:province":"Antwerpen",
    "sg:tags":[
        "medicinephysicians",
        "surgeon"
    ],
    "wof:name":"Martens Adri",
    "wof:placetype":"venue"
},
  "geometry": {"coordinates":[4.5083580017,51.2252082825],"type":"Point"}
}