{
  "type": "Feature",
  "properties": {
    "addr:full":"Place Eug\u00c8ne Keym 41 Watermaal-bosvoorde/watermael-boitsfort Bruxelles-Capitale 1170",
    "addr:housenumber":"41",
    "addr:postcode":"1170",
    "addr:street":"Place Euge\u0300Ne Keym",
    "iso:country":"BE",
    "sg:address":"Place Eug\u00c8ne Keym 41",
    "sg:city":"Watermaal-bosvoorde/watermael-boitsfort",
    "sg:orig_category":"Banques and organismes de cr\u00e9dit",
    "sg:phone":"+32 2 672 67 96",
    "sg:postcode":"1170",
    "sg:province":"Bruxelles-Capitale",
    "wof:name":"Cbc",
    "wof:placetype":"venue"
},
  "geometry": {"coordinates":[4.4028940201,50.8091583252],"type":"Point"}
}