{
  "type": "Feature",
  "properties": {
    "addr:full":"Hertogstraat 85 Leuven (heverlee) Vlaams-Brabant 3001",
    "addr:housenumber":"85",
    "addr:postcode":"3001",
    "addr:street":"Hertogstraat",
    "iso:country":"BE",
    "sg:address":"Hertogstraat 85",
    "sg:city":"Leuven (heverlee)",
    "sg:orig_category":"Newspapers, magazines, periodicals - Distribution",
    "sg:phone":"+32 16 40 49 50",
    "sg:postcode":"3001",
    "sg:province":"Vlaams-Brabant",
    "wof:name":"Jadic Bvba",
    "wof:placetype":"venue"
},
  "geometry": {"coordinates":[4.6972379684,50.8611183167],"type":"Point"}
}