{
  "type": "Feature",
  "properties": {
    "addr:full":"Stationsstraat 5 Zottegem Oost-Vlaanderen 9620",
    "addr:housenumber":"5",
    "addr:postcode":"9620",
    "addr:street":"Stationsstraat",
    "iso:country":"BE",
    "sg:address":"Stationsstraat 5",
    "sg:city":"Zottegem",
    "sg:classifiers":[
        {
            "category":"Shopping",
            "subcategory":"Clothing, Apparel, & Fashions",
            "type":"Retail Goods"
        }
    ],
    "sg:phone":"+32 9 360 04 79",
    "sg:postcode":"9620",
    "sg:province":"Oost-Vlaanderen",
    "sg:tags":[
        "wear",
        "mourning"
    ],
    "wof:name":"Antonius Kleding Bvba",
    "wof:placetype":"venue"
},
  "geometry": {"coordinates":[3.8119690418,50.8691062927],"type":"Point"}
}