{
  "type": "Feature",
  "properties": {
    "addr:full":"Noor-brabant Laan 6 Turnhout Antwerpen 2300",
    "addr:housenumber":"6",
    "addr:postcode":"2300",
    "addr:street":"Laan",
    "iso:country":"BE",
    "sg:address":"Noor-brabant Laan 6",
    "sg:city":"Turnhout",
    "sg:classifiers":[
        {
            "category":"Professional",
            "subcategory":"Computer Services",
            "type":"Services"
        }
    ],
    "sg:phone":"+32 14 45 28 31",
    "sg:postcode":"2300",
    "sg:province":"Antwerpen",
    "sg:tags":[
        "kantoormateriaal",
        "fab",
        "computerapparatuur",
        "microsoft",
        "gh"
    ],
    "wof:name":"Datasoft Solutions",
    "wof:placetype":"venue"
},
  "geometry": {"coordinates":[4.9673089981,51.3250656128],"type":"Point"}
}