{
  "type": "Feature",
  "properties": {
    "addr:full":"Baron Ruzettelaan 403 Brugge (assebroek) West-Vlaanderen 8310",
    "addr:housenumber":"403",
    "addr:postcode":"8310",
    "addr:street":"Baron Ruzettelaan",
    "iso:country":"BE",
    "sg:address":"Baron Ruzettelaan 403",
    "sg:city":"Brugge (assebroek)",
    "sg:classifiers":[
        {
            "category":"Health Services",
            "subcategory":"Doctor",
            "type":"Services"
        }
    ],
    "sg:phone":"+32 50 37 22 31",
    "sg:postcode":"8310",
    "sg:province":"West-Vlaanderen",
    "sg:tags":[
        "medicinephysicians",
        "surgeon"
    ],
    "wof:name":"Hamerijck M",
    "wof:placetype":"venue"
},
  "geometry": {"coordinates":[3.2342998981,51.1849594116],"type":"Point"}
}