{
  "type": "Feature",
  "properties": {
    "addr:full":"Rue G\u00c9ry Everaerts 26 Wavre Brabant Wallon 1300",
    "addr:housenumber":"26;1300",
    "addr:street":"Rue Ge\u0301Ry Everaerts",
    "iso:country":"BE",
    "sg:address":"Rue G\u00c9ry Everaerts 26",
    "sg:city":"Wavre",
    "sg:orig_category":"Installation de menuiserie m\u00e9tallique",
    "sg:phone":"+32 10 41 12 19",
    "sg:postcode":"1300",
    "sg:province":"Brabant Wallon",
    "wof:name":"D. M. Habitat",
    "wof:placetype":"venue"
},
  "geometry": {"coordinates":[4.5807189941,50.690246582],"type":"Point"}
}