{
  "type": "Feature",
  "properties": {
    "addr:full":"Rue Entre Deux Portes 4-6 Huy Li\u00e8ge 4500",
    "addr:housenumber":"4-6",
    "addr:postcode":"4500",
    "addr:street":"Rue Entre Deux Portes",
    "iso:country":"BE",
    "sg:address":"Rue Entre Deux Portes 4-6",
    "sg:city":"Huy",
    "sg:classifiers":[
        {
            "category":"Restaurant",
            "type":"Food & Drink"
        }
    ],
    "sg:phone":"+32 85 23 24 53",
    "sg:postcode":"4500",
    "sg:province":"Li\u00e8ge",
    "wof:name":"Pizzeria Mamma Mia",
    "wof:placetype":"venue"
},
  "geometry": {"coordinates":[5.2301669121,50.5251121521],"type":"Point"}
}