{
  "type": "Feature",
  "properties": {
    "addr:full":"Vennstrasse 3 B\u00dctgenbach/b\u00dctgenbach Li\u00e8ge 4750",
    "addr:housenumber":"3",
    "addr:postcode":"4750",
    "addr:street":"Vennstrasse",
    "iso:country":"BE",
    "sg:address":"Vennstrasse 3",
    "sg:city":"B\u00dctgenbach/b\u00dctgenbach",
    "sg:orig_category":"Rundveehouders",
    "sg:phone":"+32 80 44 61 15",
    "sg:postcode":"4750",
    "sg:province":"Li\u00e8ge",
    "wof:name":"Hubert Noel",
    "wof:placetype":"venue"
},
  "geometry": {"coordinates":[6.1915798187,50.4477806091],"type":"Point"}
}