{
  "type": "Feature",
  "properties": {
    "addr:full":"Helen Bosstraat 74 Linter (orsmaal-gussenhoven) Vlaams-Brabant 3350",
    "addr:housenumber":"74",
    "addr:postcode":"3350",
    "addr:street":"Helen Bosstraat",
    "iso:country":"BE",
    "sg:address":"Helen Bosstraat 74",
    "sg:city":"Linter (orsmaal-gussenhoven)",
    "sg:classifiers":[
        {
            "category":"Personal",
            "subcategory":"Beauty Salon",
            "type":"Services"
        }
    ],
    "sg:phone":"+32 11 78 30 53",
    "sg:postcode":"3350",
    "sg:province":"Vlaams-Brabant",
    "sg:tags":[
        "lady",
        "-",
        "hairdressing"
    ],
    "wof:name":"Johan",
    "wof:placetype":"venue"
},
  "geometry": {"coordinates":[5.0674209595,50.8068161011],"type":"Point"}
}