{
  "type": "Feature",
  "properties": {
    "iso:country":"BE",
    "sg:address":"Rue Du Calvaire 38",
    "sg:city":"Floreffe (frani\u00e8re)",
    "sg:classifiers":[
        {
            "category":"Retail",
            "subcategory":"Event Space",
            "type":"Services"
        }
    ],
    "sg:phone":"+32 81 44 65 51",
    "sg:postcode":"5150",
    "sg:province":"Namur",
    "sg:tags":[
        "organisation"
    ],
    "wof:name":"Toussaint R",
    "wof:placetype":"venue"
},
  "geometry": {"coordinates":[4.7231168747,50.435295105],"type":"Point"}
}