{
  "type": "Feature",
  "properties": {
    "addr:full":"Oude Baan 19 Dendermonde Oost-Vlaanderen 9200",
    "addr:housenumber":"19",
    "addr:postcode":"9200",
    "addr:street":"Oude Baan;Oost-Vlaanderen",
    "iso:country":"BE",
    "sg:address":"Oude Baan 19",
    "sg:city":"Dendermonde",
    "sg:orig_category":"Diverse bouwafwerking and reiniging",
    "sg:phone":"+32 52 22 37 76",
    "sg:postcode":"9200",
    "sg:province":"Oost-Vlaanderen",
    "wof:name":"Verspeet Georges",
    "wof:placetype":"venue"
},
  "geometry": {"coordinates":[4.1001691818,51.0285491943],"type":"Point"}
}