{
  "type": "Feature",
  "properties": {
    "addr:full":"Rue Omalius 82 Ciney Namur 5590",
    "addr:housenumber":"82",
    "addr:postcode":"5590",
    "addr:street":"Rue Omalius",
    "iso:country":"BE",
    "sg:address":"Rue Omalius 82",
    "sg:city":"Ciney",
    "sg:orig_category":"Installatie van houten of kunststof schrijnwerk",
    "sg:phone":"+32 83 21 16 21",
    "sg:postcode":"5590",
    "sg:province":"Namur",
    "wof:name":"Pierre Theatre",
    "wof:placetype":"venue"
},
  "geometry": {"coordinates":[5.0949587822,50.2965087891],"type":"Point"}
}