{
  "type": "Feature",
  "properties": {
    "iso:country":"BE",
    "sg:address":"Tessenderloseweg 27",
    "sg:city":"Diest (deurne)",
    "sg:classifiers":[
        {
            "category":"Building & Trades",
            "subcategory":"Plumbing",
            "type":"Services"
        }
    ],
    "sg:phone":"+32 13 67 87 01",
    "sg:postcode":"3290",
    "sg:province":"Vlaams-Brabant",
    "sg:tags":[
        "repair",
        "mainten",
        "-",
        "central",
        "heating"
    ],
    "wof:name":"All In Service Bvba",
    "wof:placetype":"venue"
},
  "geometry": {"coordinates":[5.0868601799,51.0425567627],"type":"Point"}
}