{
  "type": "Feature",
  "properties": {
    "iso:country":"BE",
    "sg:address":"Leikensweg 20",
    "sg:city":"Eeklo",
    "sg:orig_category":"Meubelzaken, woning- and keukeninrichting",
    "sg:phone":"+32 9 377 40 11",
    "sg:postcode":"9900",
    "sg:province":"Oost-Vlaanderen",
    "wof:name":"William De Craene",
    "wof:placetype":"venue"
},
  "geometry": {"coordinates":[3.555713892,51.1746101379],"type":"Point"}
}