{
  "type": "Feature",
  "properties": {
    "iso:country":"BE",
    "sg:address":"Teerlingstraat 1",
    "sg:city":"Roeselare",
    "sg:classifiers":[
        {
            "category":"Parking",
            "subcategory":"Bicycle",
            "type":"Transportation"
        }
    ],
    "sg:phone":"+32 478 40 49 64",
    "sg:postcode":"8800",
    "sg:province":"West-Vlaanderen",
    "sg:tags":[
        "chiropodist"
    ],
    "wof:name":"Lefebvre A",
    "wof:placetype":"venue"
},
  "geometry": {"coordinates":[3.1258399487,50.9499816895],"type":"Point"}
}