{
  "type": "Feature",
  "properties": {
    "addr:full":"Rue Jardon 4 Verviers Li\u00e8ge 4800",
    "addr:housenumber":"4",
    "addr:postcode":"4800",
    "addr:street":"Rue Jardon",
    "iso:country":"BE",
    "sg:address":"Rue Jardon 4",
    "sg:city":"Verviers",
    "sg:classifiers":[
        {
            "category":"Shopping",
            "subcategory":"Clothing, Apparel, & Fashions",
            "type":"Retail Goods"
        }
    ],
    "sg:phone":"+32 87 68 17 07",
    "sg:postcode":"4800",
    "sg:province":"Li\u00e8ge",
    "sg:tags":[
        "boutique"
    ],
    "wof:name":"Recto Verso",
    "wof:placetype":"venue"
},
  "geometry": {"coordinates":[5.8568911552,50.5918083191],"type":"Point"}
}