{
  "type": "Feature",
  "properties": {
    "iso:country":"BE",
    "sg:address":"Blokkersdijkstraat 26",
    "sg:city":"Zwijndrecht",
    "sg:orig_category":"Agences de publicit\u00e9",
    "sg:phone":"+32 3 252 47 41",
    "sg:postcode":"2070",
    "sg:province":"Antwerpen",
    "wof:name":"Walter Vergauwen",
    "wof:placetype":"venue"
},
  "geometry": {"coordinates":[4.3360300064,51.2232513428],"type":"Point"}
}