{
  "type": "Feature",
  "properties": {
    "addr:full":"Rue Des Scieries 8 Waimes/waimes Li\u00e8ge 4950",
    "addr:housenumber":"8",
    "addr:postcode":"4950",
    "addr:street":"Rue Des Scieries",
    "iso:country":"BE",
    "sg:address":"Rue Des Scieries 8",
    "sg:city":"Waimes/waimes",
    "sg:classifiers":[
        {
            "category":"Arena",
            "subcategory":"Sports Club",
            "type":"Entertainment"
        }
    ],
    "sg:phone":"+32 80 44 60 79",
    "sg:postcode":"4950",
    "sg:province":"Li\u00e8ge",
    "sg:tags":[
        "de"
    ],
    "wof:name":"Gymnastique De Waimes",
    "wof:placetype":"venue"
},
  "geometry": {"coordinates":[6.1406908035,50.4036178589],"type":"Point"}
}