{
  "type": "Feature",
  "properties": {
    "addr:full":"Oude Veldstraat 7 Gent Oost-Vlaanderen 9041",
    "addr:housenumber":"7",
    "addr:postcode":"9041",
    "addr:street":"Oude Veldstraat;Oost-Vlaanderen",
    "iso:country":"BE",
    "sg:address":"Oude Veldstraat 7",
    "sg:city":"Gent",
    "sg:orig_category":"Persagentschappen",
    "sg:phone":"+32 9 251 59 67",
    "sg:postcode":"9041",
    "sg:province":"Oost-Vlaanderen",
    "wof:name":"Thomas Siffer",
    "wof:placetype":"venue"
},
  "geometry": {"coordinates":[3.7772409916,51.0992736816],"type":"Point"}
}