{
  "type": "Feature",
  "properties": {
    "addr:full":"Westerlosesteenweg 195 Herselt Antwerpen 2230",
    "addr:housenumber":"195",
    "addr:postcode":"2230",
    "addr:street":"Westerlosesteenweg",
    "iso:country":"BE",
    "sg:address":"Westerlosesteenweg 195",
    "sg:city":"Herselt",
    "sg:orig_category":"Meubelzaken, woning- and keukeninrichting",
    "sg:phone":"+32 14 54 40 36",
    "sg:postcode":"2230",
    "sg:province":"Antwerpen",
    "wof:name":"Codek",
    "wof:placetype":"venue"
},
  "geometry": {"coordinates":[4.8923602104,51.0659103394],"type":"Point"}
}