{
  "type": "Feature",
  "properties": {
    "addr:full":"Kartuizerlei 1 Evergem (ertvelde) Oost-Vlaanderen 9940",
    "addr:housenumber":"1",
    "addr:postcode":"9940",
    "addr:street":"Kartuizerlei;Ertvelde Oost-Vlaanderen",
    "iso:country":"BE",
    "sg:address":"Kartuizerlei 1",
    "sg:city":"Evergem (ertvelde)",
    "sg:classifiers":[
        {
            "category":"Communications",
            "type":"Services"
        }
    ],
    "sg:phone":"+32 9 344 21 72",
    "sg:postcode":"9940",
    "sg:province":"Oost-Vlaanderen",
    "sg:tags":[
        "translator"
    ],
    "wof:name":"Coutant X",
    "wof:placetype":"venue"
},
  "geometry": {"coordinates":[3.7490260601,51.1885948181],"type":"Point"}
}