{
  "type": "Feature",
  "properties": {
    "addr:full":"Royaertstraat 8 Antwerpen Antwerpen 2610",
    "addr:housenumber":"8",
    "addr:postcode":"2610",
    "addr:street":"Royaertstraat",
    "iso:country":"BE",
    "sg:address":"Royaertstraat 8",
    "sg:city":"Antwerpen",
    "sg:orig_category":"Kunststofrecipi\u00ebnten and -verpakkingen Fab",
    "sg:phone":"+32 3 448 06 66",
    "sg:postcode":"2610",
    "sg:province":"Antwerpen",
    "wof:name":"Flexo Pack",
    "wof:placetype":"venue"
},
  "geometry": {"coordinates":[4.3946051598,51.1691131592],"type":"Point"}
}