{
  "type": "Feature",
  "properties": {
    "iso:country":"BE",
    "sg:address":"Waarloossteenweg 77",
    "sg:city":"Duffel",
    "sg:orig_category":"Artsen and specialisten",
    "sg:phone":"+32 15 31 55 44",
    "sg:postcode":"2570",
    "sg:province":"Antwerpen",
    "wof:name":"H. Haezaert",
    "wof:placetype":"venue"
},
  "geometry": {"coordinates":[4.4814801216,51.100112915],"type":"Point"}
}