{
  "type": "Feature",
  "properties": {
    "addr:full":"Rue De Habay 0 Etalle Luxembourg 6741",
    "addr:housenumber":"0",
    "addr:postcode":"6741",
    "addr:street":"Rue De Habay",
    "iso:country":"BE",
    "sg:address":"Rue De Habay 0",
    "sg:city":"Etalle",
    "sg:orig_category":"Diverse meubelen Fab MEUBELONTWERP AND -INSTALLATIE",
    "sg:phone":"+32 63 45 53 19",
    "sg:postcode":"6741",
    "sg:province":"Luxembourg",
    "wof:name":"Atelier Prot\u00c9g\u00c9 Stallbois",
    "wof:placetype":"venue"
},
  "geometry": {"coordinates":[5.6673212051,49.6705703735],"type":"Point"}
}