{
  "type": "Feature",
  "properties": {
    "addr:full":"Rue De Chateau Hotton Luxembourg 6990",
    "addr:postcode":"6990",
    "addr:street":"Rue De Chateau",
    "iso:country":"BE",
    "sg:address":"Rue De Chateau",
    "sg:city":"Hotton",
    "sg:orig_category":"Installation de menuiserie en bois and plastique",
    "sg:phone":"+32 84 46 76 53",
    "sg:postcode":"6990",
    "sg:province":"Luxembourg",
    "wof:name":"De Harlez H.",
    "wof:placetype":"venue"
},
  "geometry": {"coordinates":[5.399960041,50.3041648865],"type":"Point"}
}