{
  "type": "Feature",
  "properties": {
    "addr:full":"Molenheide 13 Puurs Antwerpen 2870",
    "addr:housenumber":"13",
    "addr:postcode":"2870",
    "addr:street":"Molenheide",
    "iso:country":"BE",
    "sg:address":"Molenheide 13",
    "sg:city":"Puurs",
    "sg:classifiers":[
        {
            "category":"Arena",
            "subcategory":"Sports Club",
            "type":"Entertainment"
        }
    ],
    "sg:phone":"+32 3 886 80 05",
    "sg:postcode":"2870",
    "sg:province":"Antwerpen",
    "sg:tags":[
        "terrain",
        "hors",
        "de",
        "installation",
        "sportifs"
    ],
    "wof:name":"O.b. Breendonk",
    "wof:placetype":"venue"
},
  "geometry": {"coordinates":[4.288175106,51.0728912354],"type":"Point"}
}