{
  "type": "Feature",
  "properties": {
    "addr:full":"Rue Du Trieu 88 Mouscron (dottignies) Hainaut 7711",
    "addr:housenumber":"88",
    "addr:postcode":"7711",
    "addr:street":"Rue Du Trieu",
    "iso:country":"BE",
    "sg:address":"Rue Du Trieu 88",
    "sg:city":"Mouscron (dottignies)",
    "sg:classifiers":[
        {
            "category":"Personal",
            "subcategory":"Shoe Repair & Shine",
            "type":"Services"
        }
    ],
    "sg:phone":"+32 56 48 73 81",
    "sg:postcode":"7711",
    "sg:province":"Hainaut",
    "sg:tags":[
        "shoemaker"
    ],
    "wof:name":"Vandenbulcke F",
    "wof:placetype":"venue"
},
  "geometry": {"coordinates":[3.3140029907,50.7225494385],"type":"Point"}
}