{
  "type": "Feature",
  "properties": {
    "addr:full":"White-chateaustraat 4 Ieper West-Vlaanderen 8900",
    "addr:housenumber":"4",
    "addr:postcode":"8900",
    "addr:street":"White-Chateaustraat",
    "iso:country":"BE",
    "sg:address":"White-chateaustraat 4",
    "sg:city":"Ieper",
    "sg:orig_category":"Services pour animaux domestiques",
    "sg:phone":"+32 57 21 76 54",
    "sg:postcode":"8900",
    "sg:province":"West-Vlaanderen",
    "wof:name":"Trimsalon Sabine",
    "wof:placetype":"venue"
},
  "geometry": {"coordinates":[2.912307024,50.8508148193],"type":"Point"}
}