{
  "type": "Feature",
  "properties": {
    "iso:country":"BE",
    "sg:address":"Gentsestraat 224",
    "sg:city":"Geraardsbergen",
    "sg:classifiers":[
        {
            "category":"Insurance",
            "subcategory":"Life Insurance",
            "type":"Services"
        }
    ],
    "sg:phone":"+32 54 41 11 75",
    "sg:postcode":"9500",
    "sg:province":"Oost-Vlaanderen",
    "sg:tags":[
        "assurance"
    ],
    "wof:name":"Zakenkantoor Vereecken",
    "wof:placetype":"venue"
},
  "geometry": {"coordinates":[3.8755450249,50.7772941589],"type":"Point"}
}