{
  "type": "Feature",
  "properties": {
    "iso:country":"BE",
    "sg:address":"Grotweg 9",
    "sg:city":"Geel",
    "sg:classifiers":[
        {
            "category":"Professional",
            "subcategory":"Computer Services",
            "type":"Services"
        }
    ],
    "sg:phone":"+32 14 72 39 80",
    "sg:postcode":"2440",
    "sg:province":"Antwerpen",
    "sg:tags":[
        "-",
        "processing",
        "data",
        "software"
    ],
    "wof:name":"Secomnet Bvba",
    "wof:placetype":"venue"
},
  "geometry": {"coordinates":[4.9426088333,51.122844696],"type":"Point"}
}