{
  "type": "Feature",
  "properties": {
    "iso:country":"BE",
    "sg:address":"Mechelsesteenweg 42",
    "sg:city":"Edegem",
    "sg:orig_category":"Chaussures",
    "sg:phone":"+32 3 457 91 88",
    "sg:postcode":"2650",
    "sg:province":"Antwerpen",
    "wof:name":"Siesta",
    "wof:placetype":"venue"
},
  "geometry": {"coordinates":[4.462747097,51.1475410461],"type":"Point"}
}