{
  "type": "Feature",
  "properties": {
    "iso:country":"BE",
    "sg:address":"Rue Joseph Lambillotte 138bb",
    "sg:city":"Charleroi",
    "sg:orig_category":"Animaux domestiques and accessoires",
    "sg:phone":"+32 71 37 47 30",
    "sg:postcode":"6040",
    "sg:province":"Hainaut",
    "wof:name":"Alliance Cichlid",
    "wof:placetype":"venue"
},
  "geometry": {"coordinates":[4.4297218323,50.4337882996],"type":"Point"}
}