{
  "type": "Feature",
  "properties": {
    "addr:full":"Kesseldorp 42ba Nijlen Antwerpen 2560",
    "addr:housenumber":"42ba",
    "addr:postcode":"2560",
    "addr:street":"Kesseldorp",
    "iso:country":"BE",
    "sg:address":"Kesseldorp 42ba",
    "sg:city":"Nijlen",
    "sg:orig_category":"Enseignement maternel and primaire",
    "sg:phone":"+32 3 480 35 95",
    "sg:postcode":"2560",
    "sg:province":"Antwerpen",
    "wof:name":"Gemeentelijke Basisschool",
    "wof:placetype":"venue"
},
  "geometry": {"coordinates":[4.6279149055,51.1387825012],"type":"Point"}
}