{
  "type": "Feature",
  "properties": {
    "iso:country":"BE",
    "sg:address":"Klerkenstraat 37",
    "sg:city":"Langemark-poelkapelle (langemark)",
    "sg:orig_category":"Cafetarias and selfservice restaurants",
    "sg:phone":"+32 57 48 61 23",
    "sg:postcode":"8920",
    "sg:province":"West-Vlaanderen",
    "wof:name":"Cafetaria Sporthal",
    "wof:placetype":"venue"
},
  "geometry": {"coordinates":[2.9296720028,50.9334259033],"type":"Point"}
}