{
  "type": "Feature",
  "properties": {
    "iso:country":"BE",
    "sg:address":"Rue De La Gare 61-63",
    "sg:city":"Bertrix",
    "sg:classifiers":[
        {
            "category":"Fast Food",
            "type":"Food & Drink"
        }
    ],
    "sg:phone":"+32 61 41 54 12",
    "sg:postcode":"6880",
    "sg:province":"Luxembourg",
    "sg:tags":[
        "meeneem",
        "restaurant"
    ],
    "wof:name":"Bella Italia",
    "wof:placetype":"venue"
},
  "geometry": {"coordinates":[5.2620439529,49.8565864563],"type":"Point"}
}