{
  "type": "Feature",
  "properties": {
    "addr:full":"Rue Des Fran\u00e7ais 235 Ans Li\u00e8ge 4430",
    "addr:housenumber":"235",
    "addr:postcode":"4430",
    "addr:street":"Rue Des Franc\u0327Ais",
    "iso:country":"BE",
    "sg:address":"Rue Des Fran\u00e7ais 235",
    "sg:city":"Ans",
    "sg:classifiers":[
        {
            "category":"Freight",
            "type":"Transportation"
        }
    ],
    "sg:phone":"+32 4 263 07 38",
    "sg:postcode":"4430",
    "sg:province":"Li\u00e8ge",
    "sg:tags":[
        "-",
        "transport"
    ],
    "wof:name":"Rigo M",
    "wof:placetype":"venue"
},
  "geometry": {"coordinates":[5.5354647636,50.6628417969],"type":"Point"}
}