{
  "type": "Feature",
  "properties": {
    "addr:full":"Haneveldlaan 92 Grimbergen Vlaams-Brabant 1850",
    "addr:housenumber":"92",
    "addr:postcode":"1850",
    "addr:street":"Haneveldlaan",
    "iso:country":"BE",
    "sg:address":"Haneveldlaan 92",
    "sg:city":"Grimbergen",
    "sg:orig_category":"Diverse grafische activiteiten",
    "sg:phone":"+32 2 267 86 73",
    "sg:postcode":"1850",
    "sg:province":"Vlaams-Brabant",
    "wof:name":"Filip Le Roy En Partners",
    "wof:placetype":"venue"
},
  "geometry": {"coordinates":[4.3667340279,50.9158096313],"type":"Point"}
}