{
  "type": "Feature",
  "properties": {
    "addr:full":"Kleine Bosweg 24 Beveren Oost-Vlaanderen 9120",
    "addr:housenumber":"24",
    "addr:postcode":"9120",
    "addr:street":"Kleine Bosweg",
    "iso:country":"BE",
    "sg:address":"Kleine Bosweg 24",
    "sg:city":"Beveren",
    "sg:orig_category":"Openbare veiligheid",
    "sg:phone":"+32 3 775 70 19",
    "sg:postcode":"9120",
    "sg:province":"Oost-Vlaanderen",
    "wof:name":"Federale Politie/police F\u00c9d\u00c9rale",
    "wof:placetype":"venue"
},
  "geometry": {"coordinates":[4.2593021393,51.2096176147],"type":"Point"}
}