{
  "type": "Feature",
  "properties": {
    "addr:full":"Rue Sohier 49 Charleroi (jumet) Hainaut 6040",
    "addr:housenumber":"49",
    "addr:postcode":"6040",
    "addr:street":"Rue Sohier",
    "iso:country":"BE",
    "sg:address":"Rue Sohier 49",
    "sg:city":"Charleroi (jumet)",
    "sg:classifiers":[
        {
            "category":"Parking",
            "subcategory":"Bicycle",
            "type":"Transportation"
        }
    ],
    "sg:phone":"+32 485 73 63 77",
    "sg:postcode":"6040",
    "sg:province":"Hainaut",
    "sg:tags":[
        "chiropodist"
    ],
    "wof:name":"Savestre B",
    "wof:placetype":"venue"
},
  "geometry": {"coordinates":[4.4164619446,50.4394836426],"type":"Point"}
}