{
  "type": "Feature",
  "properties": {
    "addr:full":"Reizigersstraat 101 Tienen Vlaams-Brabant 3300",
    "addr:housenumber":"101",
    "addr:postcode":"3300",
    "addr:street":"Reizigersstraat",
    "iso:country":"BE",
    "sg:address":"Reizigersstraat 101",
    "sg:city":"Tienen",
    "sg:classifiers":[
        {
            "category":"Communications",
            "subcategory":"Radio Station",
            "type":"Services"
        }
    ],
    "sg:phone":"+32 11 78 04 39",
    "sg:postcode":"3300",
    "sg:province":"Vlaams-Brabant",
    "sg:tags":[
        "diffusion",
        "production",
        "de",
        "programme"
    ],
    "wof:name":"Radio C.r.s.",
    "wof:placetype":"venue"
},
  "geometry": {"coordinates":[4.9448862076,50.8030738831],"type":"Point"}
}