{
  "type": "Feature",
  "properties": {
    "addr:full":"Rue Professeur Mahaim 28 Li\u00c8ge Li\u00e8ge 4000",
    "addr:housenumber":"28",
    "addr:postcode":"4000",
    "addr:street":"Rue Professeur Mahaim",
    "iso:country":"BE",
    "sg:address":"Rue Professeur Mahaim 28",
    "sg:city":"Li\u00c8ge",
    "sg:orig_category":"Charpentes and couvertures. Plomberie, chauffage and installations sanitaires",
    "sg:phone":"+32 4 253 03 84",
    "sg:postcode":"4000",
    "sg:province":"Li\u00e8ge",
    "wof:name":"Fe. Ubags & Fils",
    "wof:placetype":"venue"
},
  "geometry": {"coordinates":[5.5593419075,50.6171455383],"type":"Point"}
}