{
  "type": "Feature",
  "properties": {
    "addr:full":"Rue Du Petit Briffoeil 12 P\u00e9ruwelz (wasmes-audemez-briffoeil) Hainaut 7604",
    "addr:housenumber":"12",
    "addr:postcode":"7604",
    "addr:street":"Rue Du Petit Briffoeil;Hainaut",
    "iso:country":"BE",
    "sg:address":"Rue Du Petit Briffoeil 12",
    "sg:city":"P\u00e9ruwelz (wasmes-audemez-briffoeil)",
    "sg:classifiers":[
        {
            "category":"Health Services",
            "subcategory":"Nursing And Care Facility",
            "type":"Services"
        }
    ],
    "sg:phone":"+32 69 77 70 27",
    "sg:postcode":"7604",
    "sg:province":"Hainaut",
    "sg:tags":[
        "home"
    ],
    "wof:name":"Loor M",
    "wof:placetype":"venue"
},
  "geometry": {"coordinates":[3.5583720207,50.5573501587],"type":"Point"}
}