{
  "type": "Feature",
  "properties": {
    "addr:full":"Pas 157 Geel Antwerpen 2440",
    "addr:housenumber":"157",
    "addr:postcode":"2440",
    "addr:street":"Pas",
    "iso:country":"BE",
    "sg:address":"Pas 157",
    "sg:city":"Geel",
    "sg:classifiers":[
        {
            "category":"Insurance",
            "subcategory":"Insurance Agent",
            "type":"Services"
        }
    ],
    "sg:phone":"+32 14 58 14 14",
    "sg:postcode":"2440",
    "sg:province":"Antwerpen",
    "sg:tags":[
        "broker"
    ],
    "wof:name":"Quality Insurance Services",
    "wof:placetype":"venue"
},
  "geometry": {"coordinates":[4.9872469902,51.1574859619],"type":"Point"}
}