{
  "type": "Feature",
  "properties": {
    "addr:full":"Leterweg 23 Bilzen Limburg 3740",
    "addr:housenumber":"23",
    "addr:postcode":"3740",
    "addr:street":"Leterweg",
    "iso:country":"BE",
    "sg:address":"Leterweg 23",
    "sg:city":"Bilzen",
    "sg:orig_category":"Artsen and specialisten",
    "sg:phone":"+32 89 41 36 70",
    "sg:postcode":"3740",
    "sg:province":"Limburg",
    "wof:name":"Wilfried Odeurs",
    "wof:placetype":"venue"
},
  "geometry": {"coordinates":[5.5184102058,50.8634223938],"type":"Point"}
}