{
  "type": "Feature",
  "properties": {
    "iso:country":"BE",
    "sg:address":"Rue Du Broeck 124",
    "sg:city":"Bruxelles (anderlecht)",
    "sg:classifiers":[
        {
            "category":"Shopping",
            "subcategory":"Antiques",
            "type":"Retail Goods"
        }
    ],
    "sg:phone":"+32 2 523 42 80",
    "sg:postcode":"1070",
    "sg:province":"Bruxelles-Capitale",
    "sg:tags":[
        "restoration"
    ],
    "wof:name":"Durenne D",
    "wof:placetype":"venue"
},
  "geometry": {"coordinates":[4.2995500565,50.8378868103],"type":"Point"}
}