{
  "type": "Feature",
  "properties": {
    "addr:full":"Terlicht 25 Haaltert (kerksken) Oost-Vlaanderen 9451",
    "addr:housenumber":"25",
    "addr:postcode":"9451",
    "addr:street":"Terlicht",
    "iso:country":"BE",
    "sg:address":"Terlicht 25",
    "sg:city":"Haaltert (kerksken)",
    "sg:classifiers":[
        {
            "category":"Home & Garden",
            "subcategory":"Home Furnishings",
            "type":"Retail Goods"
        }
    ],
    "sg:phone":"+32 53 83 00 34",
    "sg:postcode":"9451",
    "sg:province":"Oost-Vlaanderen",
    "sg:tags":[
        "interior",
        "decoration"
    ],
    "wof:name":"Valbusko Cv",
    "wof:placetype":"venue"
},
  "geometry": {"coordinates":[3.99208498,50.8902664185],"type":"Point"}
}