{
  "type": "Feature",
  "properties": {
    "iso:country":"BE",
    "sg:address":"Pandenstraat 4 Box 7",
    "sg:city":"Zutendaal",
    "sg:classifiers":[
        {
            "category":"Home & Garden",
            "subcategory":"Carpets & Floor Coverings",
            "type":"Retail Goods"
        }
    ],
    "sg:phone":"+32 89 62 27 52",
    "sg:postcode":"3690",
    "sg:province":"Limburg",
    "sg:tags":[
        "armoring"
    ],
    "wof:name":"Mauro",
    "wof:placetype":"venue"
},
  "geometry": {"coordinates":[5.5753750801,50.9341011047],"type":"Point"}
}