{
  "type": "Feature",
  "properties": {
    "iso:country":"BE",
    "sg:address":"Avenue Pirson 12",
    "sg:city":"Manage (bois-d'haine)",
    "sg:classifiers":[
        {
            "category":"Education",
            "subcategory":"Special Training",
            "type":"Public Place"
        }
    ],
    "sg:phone":"+32 64 52 00 50",
    "sg:postcode":"7170",
    "sg:province":"Hainaut",
    "sg:tags":[
        "professional"
    ],
    "wof:name":"Institut De Formation M\u00e9tal Hainaut Namur",
    "wof:placetype":"venue"
},
  "geometry": {"coordinates":[4.2327899933,50.5008239746],"type":"Point"}
}