{
  "type": "Feature",
  "properties": {
    "addr:full":"Middenstraat 20 Balen Antwerpen 2490",
    "addr:housenumber":"20",
    "addr:postcode":"2490",
    "addr:street":"Middenstraat",
    "iso:country":"BE",
    "sg:address":"Middenstraat 20",
    "sg:city":"Balen",
    "sg:orig_category":"Installation de menuiserie en bois and plastique",
    "sg:phone":"+32 14 81 11 47",
    "sg:postcode":"2490",
    "sg:province":"Antwerpen",
    "wof:name":"Luc Sannen",
    "wof:placetype":"venue"
},
  "geometry": {"coordinates":[5.2339010239,51.1865615845],"type":"Point"}
}