{
  "type": "Feature",
  "properties": {
    "iso:country":"BE",
    "sg:address":"Bellestraat 89",
    "sg:city":"Sint-niklaas",
    "sg:orig_category":"Algemeen secundair onderwijs",
    "sg:phone":"+32 3 776 46 65",
    "sg:postcode":"9100",
    "sg:province":"Oost-Vlaanderen",
    "wof:name":"S.b.s.o.",
    "wof:placetype":"venue"
},
  "geometry": {"coordinates":[4.1779351234,51.1754493713],"type":"Point"}
}