{
  "type": "Feature",
  "properties": {
    "addr:full":"Av Gabrielle Petit 2 Brugelette (groot) Hainaut 7940",
    "addr:housenumber":"2",
    "addr:postcode":"7940",
    "addr:street":"Av Gabrielle Petit;Groot Hainaut",
    "iso:country":"BE",
    "sg:address":"Av Gabrielle Petit 2",
    "sg:city":"Brugelette (groot)",
    "sg:orig_category":"Diverse juridische dienstverlening",
    "sg:phone":"+32 68 45 60 31",
    "sg:postcode":"7940",
    "sg:province":"Hainaut",
    "wof:name":"Office Parette (fred Maes)",
    "wof:placetype":"venue"
},
  "geometry": {"coordinates":[3.8518309593,50.5941467285],"type":"Point"}
}