{
  "type": "Feature",
  "properties": {
    "addr:full":"Rodendijk 32 Zoersel Antwerpen 2980",
    "addr:housenumber":"32",
    "addr:postcode":"2980",
    "addr:street":"Rodendijk",
    "iso:country":"BE",
    "sg:address":"Rodendijk 32",
    "sg:city":"Zoersel",
    "sg:orig_category":"RESTAURANTS: SALLES DE CONF\u00c9RENCES AND DE R\u00c9CEPTIONS",
    "sg:phone":"+32 3 309 28 00",
    "sg:postcode":"2980",
    "sg:province":"Antwerpen",
    "wof:name":"Den Boer Van Zoersel",
    "wof:placetype":"venue"
},
  "geometry": {"coordinates":[4.7083501816,51.2525596619],"type":"Point"}
}