{
  "type": "Feature",
  "properties": {
    "addr:full":"Zwarte Vijversstraat 35 Sint-jans-molenbeek/molenbeek-saint-jean Bruxelles-Capitale 1080",
    "addr:housenumber":"35",
    "addr:postcode":"1080",
    "addr:street":"Zwarte Vijversstraat",
    "iso:country":"BE",
    "sg:address":"Zwarte Vijversstraat 35",
    "sg:city":"Sint-jans-molenbeek/molenbeek-saint-jean",
    "sg:orig_category":"Installatie van houten of kunststof schrijnwerk",
    "sg:phone":"+32 2 410 60 68",
    "sg:postcode":"1080",
    "sg:province":"Bruxelles-Capitale",
    "wof:name":"Jan Loomans/j. Loomans",
    "wof:placetype":"venue"
},
  "geometry": {"coordinates":[4.3300251961,50.8563156128],"type":"Point"}
}