{
  "type": "Feature",
  "properties": {
    "addr:full":"Rue Du Viaduc 22 Dalhem Li\u00e8ge 4607",
    "addr:housenumber":"22",
    "addr:postcode":"4607",
    "addr:street":"Rue Du Viaduc",
    "iso:country":"BE",
    "sg:address":"Rue Du Viaduc 22",
    "sg:city":"Dalhem",
    "sg:orig_category":"Textiel",
    "sg:phone":"+32 4 379 73 73",
    "sg:postcode":"4607",
    "sg:province":"Li\u00e8ge",
    "wof:name":"Yvan Aussems",
    "wof:placetype":"venue"
},
  "geometry": {"coordinates":[5.7297010422,50.7425918579],"type":"Point"}
}