{
  "type": "Feature",
  "properties": {
    "addr:full":"Rue Du Triot-masbore 1 Wellin Luxembourg 6920",
    "addr:housenumber":"1",
    "addr:postcode":"6920",
    "addr:street":"Rue Du Triot-Masbore",
    "iso:country":"BE",
    "sg:address":"Rue Du Triot-masbore 1",
    "sg:city":"Wellin",
    "sg:orig_category":"Pleisterwerk",
    "sg:phone":"+32 84 38 84 14",
    "sg:postcode":"6920",
    "sg:province":"Luxembourg",
    "wof:name":"Gauthier",
    "wof:placetype":"venue"
},
  "geometry": {"coordinates":[5.1192951202,50.0790596008],"type":"Point"}
}