{
  "type": "Feature",
  "properties": {
    "addr:full":"Amerikalei 220b30 Antwerpen Antwerpen 2000",
    "addr:housenumber":"220b30",
    "addr:postcode":"2000",
    "addr:street":"Amerikalei",
    "iso:country":"BE",
    "sg:address":"Amerikalei 220b30",
    "sg:city":"Antwerpen",
    "sg:orig_category":"Organisation de salons, expositions and bourses. Location de mat\u00e9riel pour banquets and \u00e9v\u00e9nements",
    "sg:phone":"+32 3 227 31 61",
    "sg:postcode":"2000",
    "sg:province":"Antwerpen",
    "wof:name":"B.h.v. Expo Group",
    "wof:placetype":"venue"
},
  "geometry": {"coordinates":[4.389482975,51.2050323486],"type":"Point"}
}