{
  "type": "Feature",
  "properties": {
    "addr:full":"Heuvelstraat 101 Geraardsbergen Oost-Vlaanderen 9500",
    "addr:housenumber":"101",
    "addr:postcode":"9500",
    "addr:street":"Heuvelstraat",
    "iso:country":"BE",
    "sg:address":"Heuvelstraat 101",
    "sg:city":"Geraardsbergen",
    "sg:orig_category":"Rev\u00eatements pour sols and murs. Peinture",
    "sg:phone":"+32 54 41 46 13",
    "sg:postcode":"9500",
    "sg:province":"Oost-Vlaanderen",
    "wof:name":"Alain Delhoux",
    "wof:placetype":"venue"
},
  "geometry": {"coordinates":[3.9023010731,50.7502555847],"type":"Point"}
}