{
  "type": "Feature",
  "properties": {
    "iso:country":"BE",
    "sg:address":"Oudstrijderslaan 97",
    "sg:city":"Kraainem",
    "sg:orig_category":"Boekhandels Krantenwinkels Rookartikelen",
    "sg:phone":"+32 2 720 94 32",
    "sg:postcode":"1950",
    "sg:province":"Vlaams-Brabant",
    "wof:name":"Dynamic",
    "wof:placetype":"venue"
},
  "geometry": {"coordinates":[4.4559869766,50.8651199341],"type":"Point"}
}