{
  "type": "Feature",
  "properties": {
    "iso:country":"BE",
    "sg:address":"Kapellestraat 72",
    "sg:city":"Hamme",
    "sg:classifiers":[
        {
            "category":"Shopping",
            "subcategory":"Luggage & Leather Goods",
            "type":"Retail Goods"
        }
    ],
    "sg:phone":"+32 52 47 88 98",
    "sg:postcode":"9220",
    "sg:province":"Oost-Vlaanderen",
    "sg:tags":[
        "-"
    ],
    "wof:name":"Rooms Lederwaren",
    "wof:placetype":"venue"
},
  "geometry": {"coordinates":[4.141409874,51.0959739685],"type":"Point"}
}