{
  "type": "Feature",
  "properties": {
    "addr:full":"Werkendam 100 Oud-turnhout Antwerpen 2360",
    "addr:housenumber":"100",
    "addr:postcode":"2360",
    "addr:street":"Werkendam",
    "iso:country":"BE",
    "sg:address":"Werkendam 100",
    "sg:city":"Oud-turnhout",
    "sg:classifiers":[
        {
            "category":"Health Services",
            "subcategory":"Health Practitioner",
            "type":"Services"
        }
    ],
    "sg:phone":"+32 14 42 93 69",
    "sg:postcode":"2360",
    "sg:province":"Antwerpen",
    "sg:tags":[
        "physiotherapist"
    ],
    "wof:name":"Neeckx A",
    "wof:placetype":"venue"
},
  "geometry": {"coordinates":[4.9708352089,51.3516311646],"type":"Point"}
}