{
  "type": "Feature",
  "properties": {
    "iso:country":"BE",
    "sg:address":"Biezenstraat 1",
    "sg:city":"Retie",
    "sg:orig_category":"Antiek Meubelzaken, woning- and keukeninrichting",
    "sg:phone":"+32 14 37 05 42",
    "sg:postcode":"2470",
    "sg:province":"Antwerpen",
    "wof:name":"Timeless Trading",
    "wof:placetype":"venue"
},
  "geometry": {"coordinates":[5.0687398911,51.2763748169],"type":"Point"}
}