{
  "type": "Feature",
  "properties": {
    "addr:full":"Bellevaux 6 Malmedy (bellevaux-lignueville) Li\u00e8ge 4960",
    "addr:housenumber":"6",
    "addr:postcode":"4960",
    "addr:street":"Bellevaux",
    "iso:country":"BE",
    "sg:address":"Bellevaux 6",
    "sg:city":"Malmedy (bellevaux-lignueville)",
    "sg:classifiers":[
        {
            "category":"Farming",
            "subcategory":"Fish & Marine Products",
            "type":"Manufacturing & Wholesale Goods"
        }
    ],
    "sg:phone":"+32 80 33 92 91",
    "sg:postcode":"4960",
    "sg:province":"Li\u00e8ge",
    "sg:tags":[
        "equipment",
        "fishery"
    ],
    "wof:name":"Etang Du Menhir",
    "wof:placetype":"venue"
},
  "geometry": {"coordinates":[6.026061058,50.4218788147],"type":"Point"}
}