{
  "type": "Feature",
  "properties": {
    "iso:country":"BE",
    "sg:address":"Rue D'assenois 62",
    "sg:city":"Bastogne",
    "sg:orig_category":"Dranken",
    "sg:phone":"+32 61 21 44 19",
    "sg:postcode":"6600",
    "sg:province":"Luxembourg",
    "wof:name":"Ghislain Wenkin",
    "wof:placetype":"venue"
},
  "geometry": {"coordinates":[5.710395813,49.9958305359],"type":"Point"}
}