{
  "type": "Feature",
  "properties": {
    "addr:full":"Boulevard Joseph Tirou 24b1 Charleroi Hainaut 6000",
    "addr:housenumber":"24b1",
    "addr:postcode":"6000",
    "addr:street":"Boulevard Joseph Tirou;Hainaut",
    "iso:country":"BE",
    "sg:address":"Boulevard Joseph Tirou 24b1",
    "sg:city":"Charleroi",
    "sg:orig_category":"Avocats and conseillers juridiques",
    "sg:phone":"+32 71 32 98 83",
    "sg:postcode":"6000",
    "sg:province":"Hainaut",
    "wof:name":"Jacqueline Leonard",
    "wof:placetype":"venue"
},
  "geometry": {"coordinates":[4.439385891,50.408367157],"type":"Point"}
}