{
  "type": "Feature",
  "properties": {
    "iso:country":"BE",
    "sg:address":"Thier-de-luzery 7",
    "sg:city":"Bastogne",
    "sg:orig_category":"M\u00e9decins and sp\u00e9cialistes",
    "sg:phone":"+32 61 21 33 15",
    "sg:postcode":"6600",
    "sg:province":"Luxembourg",
    "wof:name":"A. Colin",
    "wof:placetype":"venue"
},
  "geometry": {"coordinates":[5.7239837646,50.0141181946],"type":"Point"}
}