{
  "type": "Feature",
  "properties": {
    "addr:full":"Route De La Basse Sambre 103b13 Charleroi Hainaut 6060",
    "addr:housenumber":"103b13",
    "addr:postcode":"6060",
    "addr:street":"Route De La Basse Sambre;Hainaut",
    "iso:country":"BE",
    "sg:address":"Route De La Basse Sambre 103b13",
    "sg:city":"Charleroi",
    "sg:orig_category":"Gespecialiseerde residenti\u00eble bouw Loodgieterij, verwarming and sanitaire installaties Schoonmaakbed",
    "sg:phone":"+32 71 41 20 15",
    "sg:postcode":"6060",
    "sg:province":"Hainaut",
    "wof:name":"Citymo",
    "wof:placetype":"venue"
},
  "geometry": {"coordinates":[4.4880981445,50.4251937866],"type":"Point"}
}