{
  "type": "Feature",
  "properties": {
    "iso:country":"BE",
    "sg:address":"Chauss\u00c9e De Hannut 48",
    "sg:city":"Jodoigne",
    "sg:orig_category":"Landmeters",
    "sg:phone":"+32 10 81 23 47",
    "sg:postcode":"1370",
    "sg:province":"Brabant Wallon",
    "wof:name":"Jean-marie Cornet",
    "wof:placetype":"venue"
},
  "geometry": {"coordinates":[4.8811349869,50.7195472717],"type":"Point"}
}