{
  "type": "Feature",
  "properties": {
    "iso:country":"BE",
    "sg:address":"Rue Henry Leroy 2",
    "sg:city":"Soignies",
    "sg:orig_category":"M\u00e9decins and sp\u00e9cialistes",
    "sg:phone":"+32 67 33 32 37",
    "sg:postcode":"7060",
    "sg:province":"Hainaut",
    "wof:name":"Jean-pierre Van Bunnen",
    "wof:placetype":"venue"
},
  "geometry": {"coordinates":[4.0706119537,50.5799713135],"type":"Point"}
}