{
  "type": "Feature",
  "properties": {
    "iso:country":"BE",
    "sg:address":"Rue Basse Hollande 51",
    "sg:city":"Jodoigne (saint-remy-geest)",
    "sg:classifiers":[
        {
            "category":"Professional",
            "subcategory":"Accounting & Tax Preparation",
            "type":"Services"
        }
    ],
    "sg:phone":"+32 10 81 19 40",
    "sg:postcode":"1370",
    "sg:province":"Brabant Wallon",
    "sg:tags":[
        "bookkeeper"
    ],
    "wof:name":"Dehaut T",
    "wof:placetype":"venue"
},
  "geometry": {"coordinates":[4.8618369102,50.7404975891],"type":"Point"}
}