{
  "type": "Feature",
  "properties": {
    "addr:full":"Avenue Des Sept Bonniers 80 Ukkel/uccle Bruxelles-Capitale 1180",
    "addr:housenumber":"80",
    "addr:postcode":"1180",
    "addr:street":"Avenue Des Sept Bonniers;/",
    "iso:country":"BE",
    "sg:address":"Avenue Des Sept Bonniers 80",
    "sg:city":"Ukkel/uccle",
    "sg:orig_category":"Banques and organismes de cr\u00e9dit",
    "sg:phone":"+32 2 345 12 31",
    "sg:postcode":"1180",
    "sg:province":"Bruxelles-Capitale",
    "wof:name":"Anhyp",
    "wof:placetype":"venue"
},
  "geometry": {"coordinates":[4.3363699913,50.813369751],"type":"Point"}
}