{
  "type": "Feature",
  "properties": {
    "addr:full":"Rue De La Semois 146ba Etalle Luxembourg 6741",
    "addr:postcode":"6741",
    "addr:street":"Rue De La Semois 146Ba",
    "iso:country":"BE",
    "sg:address":"Rue De La Semois 146ba",
    "sg:city":"Etalle",
    "sg:orig_category":"Eleveurs de bovins",
    "sg:phone":"+32 63 45 63 69",
    "sg:postcode":"6741",
    "sg:province":"Luxembourg",
    "wof:name":"Jean Simonet",
    "wof:placetype":"venue"
},
  "geometry": {"coordinates":[5.6562709808,49.6700782776],"type":"Point"}
}