{
  "type": "Feature",
  "properties": {
    "addr:full":"Rue Derri\u00e8re La Gare 12 Malmedy Li\u00e8ge 4960",
    "addr:housenumber":"12",
    "addr:postcode":"4960",
    "addr:street":"Rue Derrie\u0300Re La Gare",
    "iso:country":"BE",
    "sg:address":"Rue Derri\u00e8re La Gare 12",
    "sg:city":"Malmedy",
    "sg:classifiers":[
        {
            "category":"Education",
            "subcategory":"School",
            "type":"Public Place"
        }
    ],
    "sg:phone":"+32 80 79 15 15",
    "sg:postcode":"4960",
    "sg:province":"Li\u00e8ge",
    "sg:tags":[
        "secondary"
    ],
    "wof:name":"Inst Notre-dame",
    "wof:placetype":"venue"
},
  "geometry": {"coordinates":[6.0325698853,50.4240684509],"type":"Point"}
}