{
  "type": "Feature",
  "properties": {
    "addr:full":"Rue G\u00e9n\u00e9ral Lotz 7 Box 7 Bruxelles (uccle) Bruxelles-Capitale 1180",
    "addr:housenumber":"7;7",
    "addr:postcode":"1180",
    "addr:street":"Rue Ge\u0301Ne\u0301Ral Lotz;Box",
    "iso:country":"BE",
    "sg:address":"Rue G\u00e9n\u00e9ral Lotz 7 Box 7",
    "sg:city":"Bruxelles (uccle)",
    "sg:classifiers":[
        {
            "category":"Professional",
            "subcategory":"Lawyer & Legal Services",
            "type":"Services"
        }
    ],
    "sg:phone":"+32 2 343 02 97",
    "sg:postcode":"1180",
    "sg:province":"Bruxelles-Capitale",
    "wof:name":"Peere V\u00e9ronique",
    "wof:placetype":"venue"
},
  "geometry": {"coordinates":[4.3575348854,50.8152503967],"type":"Point"}
}