{
  "type": "Feature",
  "properties": {
    "iso:country":"BE",
    "sg:address":"Boulevard Industriel 26",
    "sg:city":"Bruxelles (anderlecht)",
    "sg:classifiers":[
        {
            "category":"Science Facility",
            "type":"Public Place"
        }
    ],
    "sg:phone":"+32 2 558 59 90",
    "sg:postcode":"1070",
    "sg:province":"Bruxelles-Capitale",
    "sg:tags":[
        "equipment",
        "industrial",
        "-",
        "drying"
    ],
    "wof:name":"Ventilex Bv",
    "wof:placetype":"venue"
},
  "geometry": {"coordinates":[4.3128371239,50.8261909485],"type":"Point"}
}