{
  "type": "Feature",
  "properties": {
    "iso:country":"BE",
    "sg:address":"Lyceumstraat 11",
    "sg:city":"Houthalen-helchteren",
    "sg:orig_category":"Algemeen secundair onderwijs",
    "sg:phone":"+32 11 52 44 19",
    "sg:postcode":"3530",
    "sg:province":"Limburg",
    "wof:name":"Algemeen Vrij Secundair Onderwijs",
    "wof:placetype":"venue"
},
  "geometry": {"coordinates":[5.3719201088,51.0310020447],"type":"Point"}
}