{
  "type": "Feature",
  "properties": {
    "iso:country":"BE",
    "sg:address":"Avenue De L\u00b4europe 64",
    "sg:city":"Charleroi",
    "sg:orig_category":"Articles de camping and de sport. Timbres, monnaies and troph\u00e9es",
    "sg:phone":"+32 71 30 36 80",
    "sg:postcode":"6000",
    "sg:province":"Hainaut",
    "wof:name":"Maison Walter Wear",
    "wof:placetype":"venue"
},
  "geometry": {"coordinates":[4.439912796,50.4120826721],"type":"Point"}
}