{
  "type": "Feature",
  "properties": {
    "iso:country":"BE",
    "sg:address":"Deinsesteenweg 125",
    "sg:city":"Kruishoutem",
    "sg:orig_category":"M\u00e9decins and sp\u00e9cialistes",
    "sg:phone":"+32 9 386 94 44",
    "sg:postcode":"9770",
    "sg:province":"Oost-Vlaanderen",
    "wof:name":"Quentin Vanneste",
    "wof:placetype":"venue"
},
  "geometry": {"coordinates":[3.5341091156,50.9285316467],"type":"Point"}
}