{
  "type": "Feature",
  "properties": {
    "addr:full":"Heilige-geeststraat 3 Lier Antwerpen 2500",
    "addr:housenumber":"3",
    "addr:postcode":"2500",
    "addr:street":"Heilige-Geeststraat",
    "iso:country":"BE",
    "sg:address":"Heilige-geeststraat 3",
    "sg:city":"Lier",
    "sg:classifiers":[
        {
            "category":"Shopping",
            "subcategory":"Baby Store",
            "type":"Retail Goods"
        }
    ],
    "sg:phone":"+32 3 488 37 07",
    "sg:postcode":"2500",
    "sg:province":"Antwerpen",
    "sg:tags":[
        "-",
        "accessory"
    ],
    "wof:name":"Trottinette",
    "wof:placetype":"venue"
},
  "geometry": {"coordinates":[4.5741500854,51.1303863525],"type":"Point"}
}