{
  "type": "Feature",
  "properties": {
    "addr:full":"Kapellestraat 9 Bredene West-Vlaanderen 8450",
    "addr:housenumber":"9",
    "addr:postcode":"8450",
    "addr:street":"Kapellestraat",
    "iso:country":"BE",
    "sg:address":"Kapellestraat 9",
    "sg:city":"Bredene",
    "sg:classifiers":[
        {
            "category":"Cafe",
            "type":"Food & Drink"
        }
    ],
    "sg:phone":"+32 59 32 06 62",
    "sg:postcode":"8450",
    "sg:province":"West-Vlaanderen",
    "sg:tags":[
        "caf\u00e9s"
    ],
    "wof:name":"Caf\u00c9 Sporting",
    "wof:placetype":"venue"
},
  "geometry": {"coordinates":[2.9621760845,51.2478561401],"type":"Point"}
}