{
  "type": "Feature",
  "properties": {
    "addr:full":"Avenue De Juillet 62 Bruxelles (woluwe-saint-lambert) Bruxelles-Capitale 1200",
    "addr:housenumber":"62",
    "addr:postcode":"1200",
    "addr:street":"Avenue De Juillet",
    "iso:country":"BE",
    "sg:address":"Avenue De Juillet 62",
    "sg:city":"Bruxelles (woluwe-saint-lambert)",
    "sg:classifiers":[
        {
            "category":"Professional",
            "subcategory":"Printing & Photocopies",
            "type":"Services"
        }
    ],
    "sg:phone":"+32 2 771 16 34",
    "sg:postcode":"1200",
    "sg:province":"Bruxelles-Capitale",
    "sg:tags":[
        "-",
        "publishing",
        "desktop"
    ],
    "wof:name":"Big Ben Media",
    "wof:placetype":"venue"
},
  "geometry": {"coordinates":[4.4137477875,50.8477745056],"type":"Point"}
}