{
  "type": "Feature",
  "properties": {
    "iso:country":"BE",
    "sg:address":"Rue Du Vieux Chemin 13",
    "sg:city":"Wavre",
    "sg:classifiers":[
        {
            "category":"Health Services",
            "subcategory":"Doctor",
            "type":"Services"
        }
    ],
    "sg:phone":"+32 475 32 35 80",
    "sg:postcode":"1300",
    "sg:province":"Brabant Wallon",
    "sg:tags":[
        "medicinephysicians",
        "surgeon"
    ],
    "wof:name":"Bastin Christophe",
    "wof:placetype":"venue"
},
  "geometry": {"coordinates":[4.628923893,50.7234191895],"type":"Point"}
}