{
  "type": "Feature",
  "properties": {
    "iso:country":"BE",
    "sg:address":"Spalaan 49",
    "sg:city":"Oostende",
    "sg:orig_category":"Sportclubs Sportterreinen and installaties behalve sportcentra",
    "sg:phone":"+32 59 70 92 46",
    "sg:postcode":"8400",
    "sg:province":"West-Vlaanderen",
    "wof:name":"Vanneste Genootsch. Oost.",
    "wof:placetype":"venue"
},
  "geometry": {"coordinates":[2.9126999378,51.2312583923],"type":"Point"}
}