{
  "type": "Feature",
  "properties": {
    "iso:country":"BE",
    "sg:address":"Vinkenstraat 22",
    "sg:city":"Middelkerke",
    "sg:orig_category":"Jardins botaniques, zoologiques, observatoires and r\u00e9serves naturelles",
    "sg:phone":"+32 59 30 57 96",
    "sg:postcode":"8432",
    "sg:province":"West-Vlaanderen",
    "wof:name":"Schuddebeurze Middelkerke",
    "wof:placetype":"venue"
},
  "geometry": {"coordinates":[2.883562088,51.1765480042],"type":"Point"}
}