{
  "type": "Feature",
  "properties": {
    "iso:country":"BE",
    "sg:address":"Rue Fernand Neuray 59",
    "sg:city":"Bruxelles (ixelles)",
    "sg:classifiers":[
        {
            "category":"Home & Garden",
            "subcategory":"Home Furnishings",
            "type":"Retail Goods"
        }
    ],
    "sg:phone":"+32 2 344 05 72",
    "sg:postcode":"1050",
    "sg:province":"Bruxelles-Capitale",
    "sg:tags":[
        "curtain",
        "-",
        "fixture"
    ],
    "wof:name":"Interieurs & Drapis Scrl",
    "wof:placetype":"venue"
},
  "geometry": {"coordinates":[4.3554382324,50.8195877075],"type":"Point"}
}