{
  "type": "Feature",
  "properties": {
    "iso:country":"BE",
    "sg:address":"Rue De Bl\u00e9zy 6a",
    "sg:city":"Bertrix",
    "sg:classifiers":[
        {
            "category":"Education",
            "subcategory":"Dance Studio",
            "type":"Public Place"
        }
    ],
    "sg:phone":"+32 61 41 18 16",
    "sg:postcode":"6880",
    "sg:province":"Luxembourg",
    "sg:tags":[
        "pallet"
    ],
    "wof:name":"Saupont (le)",
    "wof:placetype":"venue"
},
  "geometry": {"coordinates":[5.2614970207,49.8548049927],"type":"Point"}
}