{
  "type": "Feature",
  "properties": {
    "addr:full":"Sint-martens-latemlaan 1 Kortrijk West-Vlaanderen 8500",
    "addr:housenumber":"1",
    "addr:postcode":"8500",
    "addr:street":"Sint-Martens-Latemlaan",
    "iso:country":"BE",
    "sg:address":"Sint-martens-latemlaan 1",
    "sg:city":"Kortrijk",
    "sg:classifiers":[
        {
            "category":"Sports & Exercise",
            "subcategory":"Sports Center",
            "type":"Entertainment"
        }
    ],
    "sg:phone":"+32 56 20 59 44",
    "sg:postcode":"8500",
    "sg:province":"West-Vlaanderen",
    "sg:tags":[
        "terrain",
        "hors",
        "de",
        "installation",
        "sportifs"
    ],
    "wof:name":"Provinciaal Zwembad",
    "wof:placetype":"venue"
},
  "geometry": {"coordinates":[3.2490780354,50.8233299255],"type":"Point"}
}