{
  "type": "Feature",
  "properties": {
    "iso:country":"BE",
    "sg:address":"Karrestraat 42",
    "sg:city":"Wevelgem (moorsele)",
    "sg:classifiers":[
        {
            "category":"Health Services",
            "subcategory":"Health Practitioner",
            "type":"Services"
        }
    ],
    "sg:phone":"+32 56 41 64 30",
    "sg:postcode":"8560",
    "sg:province":"West-Vlaanderen",
    "sg:tags":[
        "physiotherapist"
    ],
    "wof:name":"Commeyne Gerda",
    "wof:placetype":"venue"
},
  "geometry": {"coordinates":[3.1645560265,50.8361854553],"type":"Point"}
}