{
  "type": "Feature",
  "properties": {
    "iso:country":"BE",
    "sg:address":"Geelsebaan 85",
    "sg:city":"Kasterlee",
    "sg:classifiers":[
        {
            "category":"Bars & Pubs",
            "type":"Food & Drink"
        }
    ],
    "sg:phone":"+32 14 85 04 64",
    "sg:postcode":"2460",
    "sg:province":"Antwerpen",
    "wof:name":"Bergenhof Bvba",
    "wof:placetype":"venue"
},
  "geometry": {"coordinates":[4.9711728096,51.2354278564],"type":"Point"}
}