{
  "type": "Feature",
  "properties": {
    "addr:full":"Koningin Astridlaan 28 Hasselt (groot) Limburg 3500",
    "addr:housenumber":"28",
    "addr:postcode":"3500",
    "addr:street":"Koningin Astridlaan;Groot Limburg",
    "iso:country":"BE",
    "sg:address":"Koningin Astridlaan 28",
    "sg:city":"Hasselt (groot)",
    "sg:orig_category":"Etablissements Erotiques",
    "sg:phone":"+32 11 22 61 81",
    "sg:postcode":"3500",
    "sg:province":"Limburg",
    "wof:name":"Massagecenter",
    "wof:placetype":"venue"
},
  "geometry": {"coordinates":[5.3315210342,50.9312057495],"type":"Point"}
}