{
  "type": "Feature",
  "properties": {
    "addr:full":"Rue De Philippeville 87 Ham-sur-heure-nalinnes (nalinnes) Hainaut 6120",
    "addr:housenumber":"87",
    "addr:postcode":"6120",
    "addr:street":"Rue De Philippeville",
    "iso:country":"BE",
    "sg:address":"Rue De Philippeville 87",
    "sg:city":"Ham-sur-heure-nalinnes (nalinnes)",
    "sg:classifiers":[
        {
            "category":"Community Center",
            "subcategory":"Youth",
            "type":"Public Place"
        }
    ],
    "sg:phone":"+32 2 721 69 89",
    "sg:postcode":"6120",
    "sg:province":"Hainaut",
    "sg:tags":[
        "parasol",
        "umbrella"
    ],
    "wof:name":"Baille J Ets Sprl",
    "wof:placetype":"venue"
},
  "geometry": {"coordinates":[4.4749622345,50.3360404968],"type":"Point"}
}