{
  "type": "Feature",
  "properties": {
    "iso:country":"BE",
    "sg:address":"Place De La Bruy\u00e8re 1",
    "sg:city":"Jodoigne",
    "sg:classifiers":[
        {
            "category":"Health Services",
            "subcategory":"Dentist",
            "type":"Services"
        }
    ],
    "sg:phone":"+32 10 81 05 50",
    "sg:postcode":"1370",
    "sg:province":"Brabant Wallon",
    "wof:name":"Seha V",
    "wof:placetype":"venue"
},
  "geometry": {"coordinates":[4.8684082031,50.7245025635],"type":"Point"}
}