{
  "type": "Feature",
  "properties": {
    "iso:country":"BE",
    "sg:address":"Rue Du Bierchamps 73-5",
    "sg:city":"Charleroi (marcinelle)",
    "sg:classifiers":[
        {
            "category":"Professional",
            "subcategory":"Art Services",
            "type":"Services"
        }
    ],
    "sg:phone":"+32 71 21 50 82",
    "sg:postcode":"6001",
    "sg:province":"Hainaut",
    "sg:tags":[
        "interior",
        "designer"
    ],
    "wof:name":"Dallenogare M",
    "wof:placetype":"venue"
},
  "geometry": {"coordinates":[4.4394021034,50.3997192383],"type":"Point"}
}