{
  "type": "Feature",
  "properties": {
    "iso:country":"BE",
    "sg:address":"Oostlangeweg 11",
    "sg:city":"Beveren",
    "sg:orig_category":"Rundveehouders Varkenskwekers",
    "sg:phone":"+32 3 575 84 63",
    "sg:postcode":"9130",
    "sg:province":"Oost-Vlaanderen",
    "wof:name":"Gilbert Van Mol",
    "wof:placetype":"venue"
},
  "geometry": {"coordinates":[4.175344944,51.2897109985],"type":"Point"}
}