{
  "type": "Feature",
  "properties": {
    "iso:country":"BE",
    "sg:address":"Rue Darchis 1ba",
    "sg:city":"Li\u00c8ge",
    "sg:orig_category":"Avocats and conseillers juridiques",
    "sg:phone":"+32 4 222 09 76",
    "sg:postcode":"4000",
    "sg:province":"Li\u00e8ge",
    "wof:name":"Ren\u00c9 Jeurissen",
    "wof:placetype":"venue"
},
  "geometry": {"coordinates":[5.5672311783,50.6370773315],"type":"Point"}
}