{
  "type": "Feature",
  "properties": {
    "iso:country":"BE",
    "sg:address":"Kipdorpvest 24",
    "sg:city":"Antwerpen",
    "sg:classifiers":[
        {
            "category":"Education",
            "subcategory":"University",
            "type":"Public Place"
        }
    ],
    "sg:phone":"+32 3 233 37 90",
    "sg:postcode":"2000",
    "sg:province":"Antwerpen",
    "sg:tags":[
        "adult"
    ],
    "wof:name":"Stedelijk Centrum Voor Volwassenenonderwijs",
    "wof:placetype":"venue"
},
  "geometry": {"coordinates":[4.4144740105,51.2187004089],"type":"Point"}
}