{
  "type": "Feature",
  "properties": {
    "addr:full":"Assesteenweg 118 Ternat Vlaams-Brabant 1742",
    "addr:housenumber":"118",
    "addr:postcode":"1742",
    "addr:street":"Assesteenweg",
    "iso:country":"BE",
    "sg:address":"Assesteenweg 118",
    "sg:city":"Ternat",
    "sg:orig_category":"Slagers",
    "sg:phone":"+32 2 582 17 55",
    "sg:postcode":"1742",
    "sg:province":"Vlaams-Brabant",
    "wof:name":"Jean Van Lysebeth",
    "wof:placetype":"venue"
},
  "geometry": {"coordinates":[4.1555399895,50.8733253479],"type":"Point"}
}