{
  "type": "Feature",
  "properties": {
    "iso:country":"BE",
    "sg:address":"Landweg 13",
    "sg:city":"Kinrooi (ophoven)",
    "sg:classifiers":[
        {
            "category":"Home & Garden",
            "subcategory":"Home Furnishings",
            "type":"Retail Goods"
        }
    ],
    "sg:phone":"+32 89 56 58 57",
    "sg:postcode":"3640",
    "sg:province":"Limburg",
    "sg:tags":[
        "interior",
        "decoration"
    ],
    "wof:name":"Penders Interieur Bvba",
    "wof:placetype":"venue"
},
  "geometry": {"coordinates":[5.7926311493,51.1228179932],"type":"Point"}
}