{
  "type": "Feature",
  "properties": {
    "addr:full":"Rue Du Panama 37 Aiseau-presles Hainaut 6250",
    "addr:housenumber":"37",
    "addr:postcode":"6250",
    "addr:street":"Rue Du Panama;Hainaut",
    "iso:country":"BE",
    "sg:address":"Rue Du Panama 37",
    "sg:city":"Aiseau-presles",
    "sg:orig_category":"Charpentes and couvertures",
    "sg:phone":"+32 71 76 18 44",
    "sg:postcode":"6250",
    "sg:province":"Hainaut",
    "wof:name":"Dani\u00cbl Henrotin",
    "wof:placetype":"venue"
},
  "geometry": {"coordinates":[4.5838418007,50.4237594604],"type":"Point"}
}