{
  "type": "Feature",
  "properties": {
    "addr:full":"Grotestraat 23 De Haan (klemskerke) West-Vlaanderen 8420",
    "addr:housenumber":"23",
    "addr:postcode":"8420",
    "addr:street":"Grotestraat",
    "iso:country":"BE",
    "sg:address":"Grotestraat 23",
    "sg:city":"De Haan (klemskerke)",
    "sg:classifiers":[
        {
            "category":"Health Services",
            "subcategory":"Doctor",
            "type":"Services"
        }
    ],
    "sg:phone":"+32 59 23 38 07",
    "sg:postcode":"8420",
    "sg:province":"West-Vlaanderen",
    "sg:tags":[
        "medicinephysicians",
        "surgeon"
    ],
    "wof:name":"Himpe M",
    "wof:placetype":"venue"
},
  "geometry": {"coordinates":[3.0358901024,51.270740509],"type":"Point"}
}