{
  "type": "Feature",
  "properties": {
    "addr:full":"Chauss\u00e9e Du Roeulx 1253 Mons (havr\u00e9) Hainaut 7021",
    "addr:housenumber":"1253",
    "addr:postcode":"7021",
    "addr:street":"Chausse\u0301E Du Roeulx",
    "iso:country":"BE",
    "sg:address":"Chauss\u00e9e Du Roeulx 1253",
    "sg:city":"Mons (havr\u00e9)",
    "sg:classifiers":[
        {
            "category":"Health Services",
            "subcategory":"Nursing And Care Facility",
            "type":"Services"
        }
    ],
    "sg:phone":"+32 65 87 10 10",
    "sg:postcode":"7021",
    "sg:province":"Hainaut",
    "sg:tags":[
        "home",
        "rest"
    ],
    "wof:name":"Roses (les)",
    "wof:placetype":"venue"
},
  "geometry": {"coordinates":[4.0562500954,50.4683494568],"type":"Point"}
}