{
  "type": "Feature",
  "properties": {
    "iso:country":"BE",
    "sg:address":"Rue Du Forgeron 8",
    "sg:city":"Mouscron (dottignies)",
    "sg:classifiers":[
        {
            "category":"Building & Trades",
            "subcategory":"Plumbing",
            "type":"Services"
        }
    ],
    "sg:phone":"+32 56 48 94 14",
    "sg:postcode":"7711",
    "sg:province":"Hainaut",
    "sg:tags":[
        "repair",
        "mainten",
        "-",
        "central",
        "heating"
    ],
    "wof:name":"Deffrennes",
    "wof:placetype":"venue"
},
  "geometry": {"coordinates":[3.2995998859,50.7315635681],"type":"Point"}
}