{
  "type": "Feature",
  "properties": {
    "iso:country":"BE",
    "sg:address":"Rue De L'eglise 4",
    "sg:city":"Trois-ponts",
    "sg:orig_category":"Kapsalons",
    "sg:phone":"+32 80 68 47 52",
    "sg:postcode":"4983",
    "sg:province":"Li\u00e8ge",
    "wof:name":"M Lejeune",
    "wof:placetype":"venue"
},
  "geometry": {"coordinates":[5.824860096,50.3591346741],"type":"Point"}
}