{
  "type": "Feature",
  "properties": {
    "iso:country":"BE",
    "sg:address":"Place Du Champ De Mars 5b2",
    "sg:city":"Elsene/ixelles",
    "sg:orig_category":"Agences immobili\u00e8res",
    "sg:phone":"+32 2 512 31 61",
    "sg:postcode":"1050",
    "sg:province":"Bruxelles-Capitale",
    "wof:name":"Bur. Roosevelt Management",
    "wof:placetype":"venue"
},
  "geometry": {"coordinates":[4.3629989624,50.838344574],"type":"Point"}
}