{
  "type": "Feature",
  "properties": {
    "addr:full":"Doelstraat 13 Halen Limburg 3545",
    "addr:housenumber":"13",
    "addr:postcode":"3545",
    "addr:street":"Doelstraat",
    "iso:country":"BE",
    "sg:address":"Doelstraat 13",
    "sg:city":"Halen",
    "sg:classifiers":[
        {
            "category":"Professional",
            "subcategory":"Art Services",
            "type":"Services"
        }
    ],
    "sg:phone":"+32 13 44 19 02",
    "sg:postcode":"3545",
    "sg:province":"Limburg",
    "sg:tags":[
        "picture",
        "framer"
    ],
    "wof:name":"Durwael I",
    "wof:placetype":"venue"
},
  "geometry": {"coordinates":[5.1118168831,50.9477958679],"type":"Point"}
}