{
  "type": "Feature",
  "properties": {
    "addr:full":"Rue Des Grosses Pierres 3 Namur Namur 5101",
    "addr:housenumber":"3",
    "addr:postcode":"5101",
    "addr:street":"Rue Des Grosses Pierres",
    "iso:country":"BE",
    "sg:address":"Rue Des Grosses Pierres 3",
    "sg:city":"Namur",
    "sg:orig_category":"Installatie van houten of kunststof schrijnwerk",
    "sg:phone":"+32 81 58 84 74",
    "sg:postcode":"5101",
    "sg:province":"Namur",
    "wof:name":"Luc Martin",
    "wof:placetype":"venue"
},
  "geometry": {"coordinates":[4.9492201805,50.4777488708],"type":"Point"}
}