{
  "type": "Feature",
  "properties": {
    "iso:country":"BE",
    "sg:address":"Kleutersbaan 13",
    "sg:city":"Halle",
    "sg:classifiers":[
        {
            "category":"Arena",
            "subcategory":"Sports Club",
            "type":"Entertainment"
        }
    ],
    "sg:phone":"+32 2 356 88 05",
    "sg:postcode":"1501",
    "sg:province":"Vlaams-Brabant",
    "sg:tags":[
        "de"
    ],
    "wof:name":"Borgel T.k.",
    "wof:placetype":"venue"
},
  "geometry": {"coordinates":[4.2537550926,50.7394371033],"type":"Point"}
}