{
  "type": "Feature",
  "properties": {
    "iso:country":"BE",
    "sg:address":"Rue Des P\u00cacheries 79",
    "sg:city":"Watermaal-bosvoorde/watermael-boitsfort",
    "sg:orig_category":"M\u00e9decins and sp\u00e9cialistes",
    "sg:phone":"+32 2 673 11 83",
    "sg:postcode":"1170",
    "sg:province":"Bruxelles-Capitale",
    "wof:name":"Marc Vermeulen",
    "wof:placetype":"venue"
},
  "geometry": {"coordinates":[4.409760952,50.8124465942],"type":"Point"}
}