{
  "type": "Feature",
  "properties": {
    "iso:country":"BE",
    "sg:address":"Rue Albert Ier 91",
    "sg:city":"Dison",
    "sg:orig_category":"Bloemen and planten",
    "sg:phone":"+32 87 31 11 82",
    "sg:postcode":"4820",
    "sg:province":"Li\u00e8ge",
    "wof:name":"L'ile Aux Fleurs",
    "wof:placetype":"venue"
},
  "geometry": {"coordinates":[5.8543801308,50.6090698242],"type":"Point"}
}