{
  "type": "Feature",
  "properties": {
    "iso:country":"BE",
    "sg:address":"Kolonel Picquartlaan 39",
    "sg:city":"Schaarbeek/schaerbeek",
    "sg:orig_category":"Artsen and specialisten",
    "sg:phone":"+32 2 216 71 20",
    "sg:postcode":"1030",
    "sg:province":"Bruxelles-Capitale",
    "wof:name":"Diane Kleinermans",
    "wof:placetype":"venue"
},
  "geometry": {"coordinates":[4.3826389313,50.8775749207],"type":"Point"}
}