{
  "type": "Feature",
  "properties": {
    "iso:country":"BE",
    "sg:address":"Koning Leopold I-straat 10",
    "sg:city":"Leuven",
    "sg:classifiers":[
        {
            "category":"Health Services",
            "subcategory":"Dentist",
            "type":"Services"
        }
    ],
    "sg:phone":"+32 16 22 85 17",
    "sg:postcode":"3000",
    "sg:province":"Vlaams-Brabant",
    "wof:name":"Borgers Eleonora (echtg Triau)",
    "wof:placetype":"venue"
},
  "geometry": {"coordinates":[4.708024025,50.8787307739],"type":"Point"}
}