{
  "type": "Feature",
  "properties": {
    "iso:country":"BE",
    "sg:address":"Hertjen 69",
    "sg:city":"Sint-niklaas",
    "sg:classifiers":[
        {
            "category":"Fast Food",
            "type":"Food & Drink"
        }
    ],
    "sg:phone":"+32 3 776 95 62",
    "sg:postcode":"9100",
    "sg:province":"Oost-Vlaanderen",
    "sg:tags":[
        "fried",
        "stand",
        "potato"
    ],
    "wof:name":"Hertjen ('t)",
    "wof:placetype":"venue"
},
  "geometry": {"coordinates":[4.162211895,51.1570281982],"type":"Point"}
}