{
  "type": "Feature",
  "properties": {
    "addr:full":"Sint-ursmarusstraat 74 Dendermonde Oost-Vlaanderen 9200",
    "addr:housenumber":"74",
    "addr:postcode":"9200",
    "addr:street":"Sint-Ursmarusstraat;Oost-Vlaanderen",
    "iso:country":"BE",
    "sg:address":"Sint-ursmarusstraat 74",
    "sg:city":"Dendermonde",
    "sg:orig_category":"Artistes ind\u00e9pendants",
    "sg:phone":"+32 52 34 10 27",
    "sg:postcode":"9200",
    "sg:province":"Oost-Vlaanderen",
    "wof:name":"Atelier 74",
    "wof:placetype":"venue"
},
  "geometry": {"coordinates":[4.0983099937,51.0315208435],"type":"Point"}
}