{
  "type": "Feature",
  "properties": {
    "addr:full":"Chemin Des Skippes 24 Ath Hainaut 7823",
    "addr:housenumber":"24",
    "addr:postcode":"7823",
    "addr:street":"Chemin Des Skippes",
    "iso:country":"BE",
    "sg:address":"Chemin Des Skippes 24",
    "sg:city":"Ath",
    "sg:orig_category":"Rundveehouders",
    "sg:phone":"+32 68 55 22 85",
    "sg:postcode":"7823",
    "sg:province":"Hainaut",
    "wof:name":"Raphael Parein",
    "wof:placetype":"venue"
},
  "geometry": {"coordinates":[3.881305933,50.6412010193],"type":"Point"}
}