{
  "type": "Feature",
  "properties": {
    "addr:full":"Rue De La Forge 6 Momignies Hainaut 6596",
    "addr:housenumber":"6",
    "addr:postcode":"6596",
    "addr:street":"Rue De La Forge;Hainaut",
    "iso:country":"BE",
    "sg:address":"Rue De La Forge 6",
    "sg:city":"Momignies",
    "sg:orig_category":"Rundveehouders",
    "sg:phone":"+32 60 51 13 62",
    "sg:postcode":"6596",
    "sg:province":"Hainaut",
    "wof:name":"Marie Huhn",
    "wof:placetype":"venue"
},
  "geometry": {"coordinates":[4.2530479431,49.9684715271],"type":"Point"}
}