{
  "type": "Feature",
  "properties": {
    "iso:country":"BE",
    "sg:address":"Lange Lozanastraat 106",
    "sg:city":"Antwerpen",
    "sg:classifiers":[
        {
            "category":"Professional",
            "subcategory":"Lawyer & Legal Services",
            "type":"Services"
        }
    ],
    "sg:phone":"+32 3 238 80 40",
    "sg:postcode":"2018",
    "sg:province":"Antwerpen",
    "wof:name":"Blancke B",
    "wof:placetype":"venue"
},
  "geometry": {"coordinates":[4.4047398567,51.2034912109],"type":"Point"}
}