{
  "type": "Feature",
  "properties": {
    "iso:country":"BE",
    "sg:address":"Bloemtuinenlaan 33",
    "sg:city":"Brussel/bruxelles",
    "sg:orig_category":"Production de films, t\u00e9l\u00e9films and vid\u00e9os",
    "sg:phone":"+32 2 726 89 19",
    "sg:postcode":"1030",
    "sg:province":"Bruxelles-Capitale",
    "wof:name":"Itp",
    "wof:placetype":"venue"
},
  "geometry": {"coordinates":[4.3992910385,50.8602104187],"type":"Point"}
}