{
  "type": "Feature",
  "properties": {
    "addr:full":"Landbouwstraat 45 Zaventem Vlaams-Brabant 1930",
    "addr:housenumber":"45",
    "addr:postcode":"1930",
    "addr:street":"Landbouwstraat",
    "iso:country":"BE",
    "sg:address":"Landbouwstraat 45",
    "sg:city":"Zaventem",
    "sg:orig_category":"M\u00e9decins and sp\u00e9cialistes",
    "sg:phone":"+32 2 721 22 31",
    "sg:postcode":"1930",
    "sg:province":"Vlaams-Brabant",
    "wof:name":"Marc Artoos",
    "wof:placetype":"venue"
},
  "geometry": {"coordinates":[4.4755167961,50.8855552673],"type":"Point"}
}