{
  "type": "Feature",
  "properties": {
    "addr:full":"Wittemolenstraat 68 Wevelgem West-Vlaanderen 8560",
    "addr:housenumber":"68",
    "addr:postcode":"8560",
    "addr:street":"Wittemolenstraat",
    "iso:country":"BE",
    "sg:address":"Wittemolenstraat 68",
    "sg:city":"Wevelgem",
    "sg:orig_category":"Charpentes and couvertures",
    "sg:phone":"+32 56 41 47 42",
    "sg:postcode":"8560",
    "sg:province":"West-Vlaanderen",
    "wof:name":"Eric Steelandt",
    "wof:placetype":"venue"
},
  "geometry": {"coordinates":[3.1581261158,50.8364906311],"type":"Point"}
}