{
  "type": "Feature",
  "properties": {
    "addr:full":"Jesusstraat 26 Antwerpen Antwerpen 2000",
    "addr:housenumber":"26",
    "addr:postcode":"2000",
    "addr:street":"Jesusstraat",
    "iso:country":"BE",
    "sg:address":"Jesusstraat 26",
    "sg:city":"Antwerpen",
    "sg:orig_category":"Cr\u00e9dits divers",
    "sg:postcode":"2000",
    "sg:province":"Antwerpen",
    "wof:name":"Postomat Antwerpen",
    "wof:placetype":"venue"
},
  "geometry": {"coordinates":[4.4140591621,51.2190742493],"type":"Point"}
}