{
  "type": "Feature",
  "properties": {
    "addr:full":"Heirbaan 155 Zwijndrecht Antwerpen 2070",
    "addr:housenumber":"155",
    "addr:postcode":"2070",
    "addr:street":"Heirbaan",
    "iso:country":"BE",
    "sg:address":"Heirbaan 155",
    "sg:city":"Zwijndrecht",
    "sg:orig_category":"Messageries",
    "sg:phone":"+32 3 254 06 30",
    "sg:postcode":"2070",
    "sg:province":"Antwerpen",
    "wof:name":"Caro Express",
    "wof:placetype":"venue"
},
  "geometry": {"coordinates":[4.3329629898,51.1996994019],"type":"Point"}
}