{
  "type": "Feature",
  "properties": {
    "addr:full":"Heidestraat 19ba Ternat Vlaams-Brabant 1742",
    "addr:housenumber":"19ba",
    "addr:postcode":"1742",
    "addr:street":"Heidestraat",
    "iso:country":"BE",
    "sg:address":"Heidestraat 19ba",
    "sg:city":"Ternat",
    "sg:orig_category":"Boekhouders",
    "sg:phone":"+32 2 582 79 99",
    "sg:postcode":"1742",
    "sg:province":"Vlaams-Brabant",
    "wof:name":"Patrick Vanhie",
    "wof:placetype":"venue"
},
  "geometry": {"coordinates":[4.1468381882,50.8713607788],"type":"Point"}
}