{
  "type": "Feature",
  "properties": {
    "addr:full":"Rue De Stavelot 3 Li\u00c8ge Li\u00e8ge 4020",
    "addr:housenumber":"3",
    "addr:postcode":"4020",
    "addr:street":"Rue De Stavelot",
    "iso:country":"BE",
    "sg:address":"Rue De Stavelot 3",
    "sg:city":"Li\u00c8ge",
    "sg:orig_category":"Apotheken",
    "sg:phone":"+32 4 343 29 06",
    "sg:postcode":"4020",
    "sg:province":"Li\u00e8ge",
    "wof:name":"Pharmacie Des Vennes",
    "wof:placetype":"venue"
},
  "geometry": {"coordinates":[5.5891170502,50.6217346191],"type":"Point"}
}