{
  "type": "Feature",
  "properties": {
    "iso:country":"BE",
    "sg:address":"Rue Des Noisetiers 20",
    "sg:city":"Namur (vedrin - Daussoulx)",
    "sg:classifiers":[
        {
            "category":"Food & Beverages",
            "subcategory":"Specialty",
            "type":"Retail Goods"
        }
    ],
    "sg:phone":"+32 81 21 18 73",
    "sg:postcode":"5020",
    "sg:province":"Namur",
    "sg:tags":[
        "health",
        "dietary",
        "-",
        "biological"
    ],
    "wof:name":"Santoline",
    "wof:placetype":"venue"
},
  "geometry": {"coordinates":[4.8661050797,50.4805641174],"type":"Point"}
}