{
  "type": "Feature",
  "properties": {
    "iso:country":"BE",
    "sg:address":"Place Gilles G\u00c9rard 33",
    "sg:city":"Herstal",
    "sg:orig_category":"Apotheken",
    "sg:phone":"+32 4 227 03 17",
    "sg:postcode":"4041",
    "sg:province":"Li\u00e8ge",
    "wof:name":"Marie Bluth",
    "wof:placetype":"venue"
},
  "geometry": {"coordinates":[5.5841298103,50.6729850769],"type":"Point"}
}