{
  "type": "Feature",
  "properties": {
    "iso:country":"BE",
    "sg:address":"Nationalestraat 75",
    "sg:city":"Antwerpen",
    "sg:orig_category":"Textiel Verlichting and huishoudartikelen",
    "sg:phone":"+32 3 213 06 76",
    "sg:postcode":"2000",
    "sg:province":"Antwerpen",
    "wof:name":"Behang En Zo",
    "wof:placetype":"venue"
},
  "geometry": {"coordinates":[4.3988480568,51.2150230408],"type":"Point"}
}