{
  "type": "Feature",
  "properties": {
    "addr:full":"Leuvestraat 37 Aalst Oost-Vlaanderen 9320",
    "addr:housenumber":"37",
    "addr:postcode":"9320",
    "addr:street":"Leuvestraat",
    "iso:country":"BE",
    "sg:address":"Leuvestraat 37",
    "sg:city":"Aalst",
    "sg:orig_category":"Enseignement maternel and primaire",
    "sg:phone":"+32 53 78 26 21",
    "sg:postcode":"9320",
    "sg:province":"Oost-Vlaanderen",
    "wof:name":"Basisschool",
    "wof:placetype":"venue"
},
  "geometry": {"coordinates":[4.0553851128,50.9209976196],"type":"Point"}
}