{
  "type": "Feature",
  "properties": {
    "iso:country":"BE",
    "sg:address":"Rue Des Ardennes 2",
    "sg:city":"Beauraing",
    "sg:orig_category":"Banken and kredietinstellingen",
    "sg:phone":"+32 82 71 14 11",
    "sg:postcode":"5570",
    "sg:province":"Namur",
    "wof:name":"Dexia",
    "wof:placetype":"venue"
},
  "geometry": {"coordinates":[4.8551487923,50.0667915344],"type":"Point"}
}