{
  "type": "Feature",
  "properties": {
    "iso:country":"BE",
    "sg:address":"Vredebaan 30",
    "sg:city":"Mortsel",
    "sg:orig_category":"Articles de sport, camping and jouets Gr",
    "sg:phone":"+32 3 449 94 76",
    "sg:postcode":"2640",
    "sg:province":"Antwerpen",
    "wof:name":"Ch. Heusdens",
    "wof:placetype":"venue"
},
  "geometry": {"coordinates":[4.4420127869,51.1724853516],"type":"Point"}
}