{
  "type": "Feature",
  "properties": {
    "iso:country":"BE",
    "sg:address":"Dr. Adriaan Martenslaan 77",
    "sg:city":"Deinze",
    "sg:orig_category":"Tuinen",
    "sg:phone":"+32 9 386 17 16",
    "sg:postcode":"9800",
    "sg:province":"Oost-Vlaanderen",
    "wof:name":"Karel Eerdekens",
    "wof:placetype":"venue"
},
  "geometry": {"coordinates":[3.5206100941,50.9896316528],"type":"Point"}
}