{
  "type": "Feature",
  "properties": {
    "iso:country":"BE",
    "sg:address":"Luikersteenweg 328",
    "sg:city":"Sint-truiden",
    "sg:orig_category":"Fruitteelt Varkenskwekers",
    "sg:phone":"+32 11 68 78 45",
    "sg:postcode":"3800",
    "sg:province":"Limburg",
    "wof:name":"Joseph Gennez",
    "wof:placetype":"venue"
},
  "geometry": {"coordinates":[5.2029700279,50.8036193848],"type":"Point"}
}