{
  "type": "Feature",
  "properties": {
    "addr:full":"Molenstraat 16 Peer Limburg 3990",
    "addr:housenumber":"16",
    "addr:postcode":"3990",
    "addr:street":"Molenstraat",
    "iso:country":"BE",
    "sg:address":"Molenstraat 16",
    "sg:city":"Peer",
    "sg:classifiers":[
        {
            "category":"Health Services",
            "subcategory":"Dentist",
            "type":"Services"
        }
    ],
    "sg:phone":"+32 11 63 26 28",
    "sg:postcode":"3990",
    "sg:province":"Limburg",
    "wof:name":"Meynen Patrick",
    "wof:placetype":"venue"
},
  "geometry": {"coordinates":[5.4601669312,51.1327705383],"type":"Point"}
}