{
  "type": "Feature",
  "properties": {
    "iso:country":"BE",
    "sg:address":"Rue De Ch\u00e8vremont 43",
    "sg:city":"Anderlues",
    "sg:classifiers":[
        {
            "category":"Food & Beverages",
            "subcategory":"Groceries & Convenience Stores",
            "type":"Retail Goods"
        }
    ],
    "sg:phone":"+32 71 52 42 07",
    "sg:postcode":"6150",
    "sg:province":"Hainaut",
    "sg:tags":[
        "grocer"
    ],
    "wof:name":"Moureaux J",
    "wof:placetype":"venue"
},
  "geometry": {"coordinates":[4.257753849,50.416721344],"type":"Point"}
}