{
  "type": "Feature",
  "properties": {
    "addr:full":"J. Mattheessenstraat 60 Hove Antwerpen 2540",
    "addr:housenumber":"60",
    "addr:postcode":"2540",
    "addr:street":"Mattheessenstraat",
    "iso:country":"BE",
    "sg:address":"J. Mattheessenstraat 60",
    "sg:city":"Hove",
    "sg:classifiers":[
        {
            "category":"Science Facility",
            "type":"Public Place"
        }
    ],
    "sg:phone":"+32 3 455 24 93",
    "sg:postcode":"2540",
    "sg:province":"Antwerpen",
    "sg:tags":[
        "recherche",
        "en",
        "physique",
        "naturelles"
    ],
    "wof:name":"Volkssterrenwacht Urania",
    "wof:placetype":"venue"
},
  "geometry": {"coordinates":[4.4662380219,51.1452598572],"type":"Point"}
}