{
  "type": "Feature",
  "properties": {
    "addr:full":"All\u00c9e Des Vignes 1 Grez-doiceau Brabant Wallon 1390",
    "addr:housenumber":"1",
    "addr:postcode":"1390",
    "addr:street":"Alle\u0301E Des Vignes",
    "iso:country":"BE",
    "sg:address":"All\u00c9e Des Vignes 1",
    "sg:city":"Grez-doiceau",
    "sg:orig_category":"Dakwerken",
    "sg:phone":"+32 10 84 16 01",
    "sg:postcode":"1390",
    "sg:province":"Brabant Wallon",
    "wof:name":"Rene Taveirne",
    "wof:placetype":"venue"
},
  "geometry": {"coordinates":[4.7006201744,50.7395896912],"type":"Point"}
}