{
  "type": "Feature",
  "properties": {
    "addr:full":"Treemblok 2 Schilde ('s Gravenwezel) Antwerpen 2970",
    "addr:housenumber":"2",
    "addr:postcode":"2970",
    "addr:street":"Treemblok;S",
    "iso:country":"BE",
    "sg:address":"Treemblok 2",
    "sg:city":"Schilde ('s Gravenwezel)",
    "sg:classifiers":[
        {
            "category":"Insurance",
            "subcategory":"Insurance Agent",
            "type":"Services"
        }
    ],
    "sg:phone":"+32 3 658 15 24",
    "sg:postcode":"2970",
    "sg:province":"Antwerpen",
    "sg:tags":[
        "broker"
    ],
    "wof:name":"Algy Cvba",
    "wof:placetype":"venue"
},
  "geometry": {"coordinates":[4.5798120499,51.2392082214],"type":"Point"}
}