{
  "type": "Feature",
  "properties": {
    "iso:country":"BE",
    "sg:address":"Place Reine Astrid 8",
    "sg:city":"Tournai",
    "sg:classifiers":[
        {
            "category":"Health Services",
            "subcategory":"Dentist",
            "type":"Services"
        }
    ],
    "sg:phone":"+32 69 23 22 80",
    "sg:postcode":"7500",
    "sg:province":"Hainaut",
    "wof:name":"Dochy Michel",
    "wof:placetype":"venue"
},
  "geometry": {"coordinates":[3.3888189793,50.6039657593],"type":"Point"}
}