{
  "type": "Feature",
  "properties": {
    "addr:full":"Groenstraat 2 Glabbeek Vlaams-Brabant 3381",
    "addr:housenumber":"2",
    "addr:postcode":"3381",
    "addr:street":"Groenstraat",
    "iso:country":"BE",
    "sg:address":"Groenstraat 2",
    "sg:city":"Glabbeek",
    "sg:orig_category":"Producteurs de fruits",
    "sg:phone":"+32 16 77 90 71",
    "sg:postcode":"3381",
    "sg:province":"Vlaams-Brabant",
    "wof:name":"Veulemans Fruit",
    "wof:placetype":"venue"
},
  "geometry": {"coordinates":[4.9542479515,50.8938522339],"type":"Point"}
}