{
  "type": "Feature",
  "properties": {
    "addr:full":"Chauss\u00e9e De Jolimont 271 La Louvi\u00e8re (haine-saint-pierre) Hainaut 7100",
    "addr:housenumber":"271",
    "addr:postcode":"7100",
    "addr:street":"Chausse\u0301E De Jolimont",
    "iso:country":"BE",
    "sg:address":"Chauss\u00e9e De Jolimont 271",
    "sg:city":"La Louvi\u00e8re (haine-saint-pierre)",
    "sg:classifiers":[
        {
            "category":"Fast Food",
            "type":"Food & Drink"
        }
    ],
    "sg:phone":"+32 64 22 42 92",
    "sg:postcode":"7100",
    "sg:province":"Hainaut",
    "sg:tags":[
        "fried",
        "stand",
        "potato"
    ],
    "wof:name":"Bonne Frite (la)",
    "wof:placetype":"venue"
},
  "geometry": {"coordinates":[4.21398592,50.470413208],"type":"Point"}
}