{
  "type": "Feature",
  "properties": {
    "addr:full":"Plaatsstraat 18 Galmaarden (tollembeek) Vlaams-Brabant 1570",
    "addr:housenumber":"18",
    "addr:postcode":"1570",
    "addr:street":"Plaatsstraat",
    "iso:country":"BE",
    "sg:address":"Plaatsstraat 18",
    "sg:city":"Galmaarden (tollembeek)",
    "sg:orig_category":"Newspapers, magazines, periodicals - Distribution",
    "sg:phone":"+32 54 58 64 98",
    "sg:postcode":"1570",
    "sg:province":"Vlaams-Brabant",
    "wof:name":"La Gazzetta",
    "wof:placetype":"venue"
},
  "geometry": {"coordinates":[4.0043568611,50.7418251038],"type":"Point"}
}