{
  "type": "Feature",
  "properties": {
    "addr:full":"Rue Grande 39 Boussu Hainaut 7301",
    "addr:housenumber":"39",
    "addr:postcode":"7301",
    "addr:street":"Rue Grande",
    "iso:country":"BE",
    "sg:address":"Rue Grande 39",
    "sg:city":"Boussu",
    "sg:classifiers":[
        {
            "category":"Cafe",
            "type":"Food & Drink"
        }
    ],
    "sg:phone":"+32 65 77 05 57",
    "sg:postcode":"7301",
    "sg:province":"Hainaut",
    "sg:tags":[
        "caf\u00e9s"
    ],
    "wof:name":"Caf\u00c9 Ind\u00c9pendant",
    "wof:placetype":"venue"
},
  "geometry": {"coordinates":[3.8257451057,50.4362258911],"type":"Point"}
}