{
  "type": "Feature",
  "properties": {
    "iso:country":"BE",
    "sg:address":"Kortrijksepoortstraat 9",
    "sg:city":"Gent",
    "sg:orig_category":"V\u00eatements. Maroquinerie and articles de voyage. Sous-v\u00eatements and lingerie",
    "sg:phone":"+32 9 233 44 83",
    "sg:postcode":"9000",
    "sg:province":"Oost-Vlaanderen",
    "wof:name":"Boothill Shop",
    "wof:placetype":"venue"
},
  "geometry": {"coordinates":[3.7223300934,51.0458717346],"type":"Point"}
}