{
  "type": "Feature",
  "properties": {
    "iso:country":"BE",
    "sg:address":"Sint-laurentiusstraat 37",
    "sg:city":"Maasmechelen",
    "sg:orig_category":"Elektrische installaties voor woningen",
    "sg:phone":"+32 89 75 10 09",
    "sg:postcode":"3630",
    "sg:province":"Limburg",
    "wof:name":"Frank Opdekamp",
    "wof:placetype":"venue"
},
  "geometry": {"coordinates":[5.7480912209,51.0002365112],"type":"Point"}
}