{
  "type": "Feature",
  "properties": {
    "iso:country":"BE",
    "sg:address":"Korte Gasthuisstraat 57",
    "sg:city":"Turnhout",
    "sg:classifiers":[
        {
            "category":"Food & Beverages",
            "subcategory":"Meat & Fish",
            "type":"Retail Goods"
        }
    ],
    "sg:phone":"+32 14 41 16 58",
    "sg:postcode":"2300",
    "sg:province":"Antwerpen",
    "sg:tags":[
        "poultry",
        "whol",
        "game",
        "-"
    ],
    "wof:name":"Cornelissen Michel",
    "wof:placetype":"venue"
},
  "geometry": {"coordinates":[4.9440221786,51.322303772],"type":"Point"}
}