{
  "type": "Feature",
  "properties": {
    "addr:full":"Rue P\u00e8re De Deken 48 Bruxelles (etterbeek) Bruxelles-Capitale 1040",
    "addr:housenumber":"48",
    "addr:postcode":"1040",
    "addr:street":"Rue Pe\u0300Re De Deken",
    "iso:country":"BE",
    "sg:address":"Rue P\u00e8re De Deken 48",
    "sg:city":"Bruxelles (etterbeek)",
    "sg:classifiers":[
        {
            "category":"Health Services",
            "subcategory":"Health Practitioner",
            "type":"Services"
        }
    ],
    "sg:phone":"+32 2 736 30 93",
    "sg:postcode":"1040",
    "sg:province":"Bruxelles-Capitale",
    "sg:tags":[
        "physiotherapist"
    ],
    "wof:name":"Mols Fran\u00e7ois",
    "wof:placetype":"venue"
},
  "geometry": {"coordinates":[4.4019808769,50.8354415894],"type":"Point"}
}