{
  "type": "Feature",
  "properties": {
    "iso:country":"BE",
    "sg:address":"Poelstraat 37",
    "sg:city":"Merelbeke",
    "sg:classifiers":[
        {
            "category":"Social Services",
            "subcategory":"Retirement Home",
            "type":"Services"
        }
    ],
    "sg:phone":"+32 9 210 71 27",
    "sg:postcode":"9820",
    "sg:province":"Oost-Vlaanderen",
    "sg:tags":[
        "residence"
    ],
    "wof:name":"Residentie Molenhoek",
    "wof:placetype":"venue"
},
  "geometry": {"coordinates":[3.750191927,50.9880218506],"type":"Point"}
}