{
  "type": "Feature",
  "properties": {
    "addr:full":"Schatting 64 Zedelgem West-Vlaanderen 8210",
    "addr:housenumber":"64",
    "addr:postcode":"8210",
    "addr:street":"Schatting",
    "iso:country":"BE",
    "sg:address":"Schatting 64",
    "sg:city":"Zedelgem",
    "sg:orig_category":"Metaalbehandeling and -bekleding",
    "sg:phone":"+32 50 24 00 70",
    "sg:postcode":"8210",
    "sg:province":"West-Vlaanderen",
    "wof:name":"P.m.c.",
    "wof:placetype":"venue"
},
  "geometry": {"coordinates":[3.1428699493,51.1376419067],"type":"Point"}
}