{
  "type": "Feature",
  "properties": {
    "iso:country":"BE",
    "sg:address":"Rue Les Gottes 19",
    "sg:city":"Modave (str\u00e9e-lez-huy)",
    "sg:classifiers":[
        {
            "category":"Farming",
            "subcategory":"Livestock Farm",
            "type":"Manufacturing & Wholesale Goods"
        }
    ],
    "sg:phone":"+32 85 51 27 17",
    "sg:postcode":"4577",
    "sg:province":"Li\u00e8ge",
    "sg:tags":[
        "buyer"
    ],
    "wof:name":"Orban J",
    "wof:placetype":"venue"
},
  "geometry": {"coordinates":[5.3136191368,50.505027771],"type":"Point"}
}