{
  "type": "Feature",
  "properties": {
    "iso:country":"BE",
    "sg:address":"Paalstraat 275",
    "sg:city":"Schoten",
    "sg:orig_category":"Supermarkten",
    "sg:phone":"+32 3 685 40 60",
    "sg:postcode":"2900",
    "sg:province":"Antwerpen",
    "wof:name":"Colruyt",
    "wof:placetype":"venue"
},
  "geometry": {"coordinates":[4.5061349869,51.2593307495],"type":"Point"}
}