{
  "type": "Feature",
  "properties": {
    "addr:full":"Snipweg 17 Koksijde (oostduinkerke) West-Vlaanderen 8670",
    "addr:housenumber":"17",
    "addr:postcode":"8670",
    "addr:street":"Snipweg",
    "iso:country":"BE",
    "sg:address":"Snipweg 17",
    "sg:city":"Koksijde (oostduinkerke)",
    "sg:classifiers":[
        {
            "category":"Professional",
            "subcategory":"Management & Consulting",
            "type":"Services"
        }
    ],
    "sg:phone":"+32 58 51 73 95",
    "sg:postcode":"8670",
    "sg:province":"West-Vlaanderen",
    "sg:tags":[
        "consultant"
    ],
    "wof:name":"Avr Knowledge",
    "wof:placetype":"venue"
},
  "geometry": {"coordinates":[2.6789999008,51.1255187988],"type":"Point"}
}