{
  "type": "Feature",
  "properties": {
    "iso:country":"BE",
    "sg:address":"Rue De La Lini\u00e8re 12",
    "sg:city":"Bruxelles (saint-gilles)",
    "sg:orig_category":"Solar protection - Inside",
    "sg:phone":"+32 2 537 28 35",
    "sg:postcode":"1060",
    "sg:province":"Bruxelles-Capitale",
    "wof:name":"Flex Sprl",
    "wof:placetype":"venue"
},
  "geometry": {"coordinates":[4.3475198746,50.8322639465],"type":"Point"}
}