{
  "type": "Feature",
  "properties": {
    "iso:country":"BE",
    "sg:address":"Quai De Rome",
    "sg:city":"Liege",
    "sg:orig_category":"Verbruikerskredietinstellingen",
    "sg:phone":"+32 4 361 32 00",
    "sg:postcode":"4000",
    "sg:province":"Li\u00e8ge",
    "wof:name":"Ab Cr\u00c9dit",
    "wof:placetype":"venue"
},
  "geometry": {"coordinates":[5.5778341293,50.6201210022],"type":"Point"}
}