{
  "type": "Feature",
  "properties": {
    "iso:country":"BE",
    "sg:address":"Polenlaan 24a",
    "sg:city":"Stekene",
    "sg:classifiers":[
        {
            "category":"Shopping",
            "subcategory":"Optician",
            "type":"Retail Goods"
        }
    ],
    "sg:phone":"+32 3 779 84 56",
    "sg:postcode":"9190",
    "sg:province":"Oost-Vlaanderen",
    "sg:tags":[
        "-"
    ],
    "wof:name":"Oosterlinck E",
    "wof:placetype":"venue"
},
  "geometry": {"coordinates":[4.0422301292,51.2068328857],"type":"Point"}
}