{
  "type": "Feature",
  "properties": {
    "addr:full":"Rue Neuve 62 Braine-le-comte Hainaut 7090",
    "addr:housenumber":"62",
    "addr:postcode":"7090",
    "addr:street":"Rue Neuve",
    "iso:country":"BE",
    "sg:address":"Rue Neuve 62",
    "sg:city":"Braine-le-comte",
    "sg:orig_category":"Woningbouw",
    "sg:phone":"+32 67 56 10 90",
    "sg:postcode":"7090",
    "sg:province":"Hainaut",
    "wof:name":"Coup De Pouce \u00c0 L'emploi",
    "wof:placetype":"venue"
},
  "geometry": {"coordinates":[4.1338858604,50.602935791],"type":"Point"}
}