{
  "type": "Feature",
  "properties": {
    "iso:country":"BE",
    "sg:address":"Hauwerstraat 63",
    "sg:city":"Buggenhout",
    "sg:classifiers":[
        {
            "category":"Home & Garden",
            "subcategory":"Garden Supply",
            "type":"Retail Goods"
        }
    ],
    "sg:phone":"+32 52 33 27 28",
    "sg:postcode":"9255",
    "sg:province":"Oost-Vlaanderen",
    "wof:name":"Muyshondt W",
    "wof:placetype":"venue"
},
  "geometry": {"coordinates":[4.1830601692,51.0165214539],"type":"Point"}
}