{
  "type": "Feature",
  "properties": {
    "iso:country":"BE",
    "sg:address":"Stationsplein 10",
    "sg:city":"Roeselare",
    "sg:classifiers":[
        {
            "category":"Bakery",
            "type":"Food & Drink"
        }
    ],
    "sg:phone":"+32 51 20 64 60",
    "sg:postcode":"8800",
    "sg:province":"West-Vlaanderen",
    "sg:tags":[
        "confectioner",
        "baker"
    ],
    "wof:name":"Java",
    "wof:placetype":"venue"
},
  "geometry": {"coordinates":[3.1295809746,50.9485092163],"type":"Point"}
}