{
  "type": "Feature",
  "properties": {
    "addr:full":"Bruinbergstraat 11 Beernem West-Vlaanderen 8730",
    "addr:housenumber":"11",
    "addr:postcode":"8730",
    "addr:street":"Bruinbergstraat",
    "iso:country":"BE",
    "sg:address":"Bruinbergstraat 11",
    "sg:city":"Beernem",
    "sg:orig_category":"Rundveehouders",
    "sg:phone":"+32 50 78 91 69",
    "sg:postcode":"8730",
    "sg:province":"West-Vlaanderen",
    "wof:name":"Dirk Dhaens",
    "wof:placetype":"venue"
},
  "geometry": {"coordinates":[3.3980119228,51.1597175598],"type":"Point"}
}