{
  "type": "Feature",
  "properties": {
    "iso:country":"BE",
    "sg:address":"Leuvensesteenweg 123",
    "sg:city":"Kortenberg",
    "sg:classifiers":[
        {
            "category":"Bars & Pubs",
            "type":"Food & Drink"
        }
    ],
    "sg:phone":"+32 2 757 17 19",
    "sg:postcode":"3070",
    "sg:province":"Vlaams-Brabant",
    "wof:name":"Rivi",
    "wof:placetype":"venue"
},
  "geometry": {"coordinates":[4.5280132294,50.8840332031],"type":"Point"}
}