{
  "type": "Feature",
  "properties": {
    "addr:full":"Geenmeerstraat 25 Lummen Limburg 3560",
    "addr:housenumber":"25",
    "addr:postcode":"3560",
    "addr:street":"Geenmeerstraat",
    "iso:country":"BE",
    "sg:address":"Geenmeerstraat 25",
    "sg:city":"Lummen",
    "sg:orig_category":"Eleveurs and marchands de porcs. Eleveurs de bovins",
    "sg:phone":"+32 13 33 40 00",
    "sg:postcode":"3560",
    "sg:province":"Limburg",
    "wof:name":"Rene Vaes",
    "wof:placetype":"venue"
},
  "geometry": {"coordinates":[5.1928048134,50.9866790771],"type":"Point"}
}