{
  "type": "Feature",
  "properties": {
    "iso:country":"BE",
    "sg:address":"Diggieweg 26",
    "sg:city":"Brakel",
    "sg:orig_category":"Woningbouw",
    "sg:phone":"+32 55 42 23 63",
    "sg:postcode":"9660",
    "sg:province":"Oost-Vlaanderen",
    "wof:name":"Ghislain Maes",
    "wof:placetype":"venue"
},
  "geometry": {"coordinates":[3.7453389168,50.8010749817],"type":"Point"}
}