{
  "type": "Feature",
  "properties": {
    "addr:full":"Rue Adolphe Dumont 1 Vaux-sous-ch\u00e8vremont Li\u00e8ge 4051",
    "addr:housenumber":"1",
    "addr:postcode":"4051",
    "addr:street":"Rue Adolphe Dumont",
    "iso:country":"BE",
    "sg:address":"Rue Adolphe Dumont 1",
    "sg:city":"Vaux-sous-ch\u00e8vremont",
    "sg:classifiers":[
        {
            "category":"Banks & Credit Unions",
            "subcategory":"Investment Brokerage",
            "type":"Services"
        }
    ],
    "sg:phone":"+32 4 361 76 17",
    "sg:postcode":"4051",
    "sg:province":"Li\u00e8ge",
    "sg:tags":[
        "mill",
        "ball"
    ],
    "wof:name":"Magotteaux International S.a.",
    "wof:placetype":"venue"
},
  "geometry": {"coordinates":[5.6394028664,50.6037368774],"type":"Point"}
}