{
  "type": "Feature",
  "properties": {
    "iso:country":"BE",
    "sg:address":"Veenzijde 71z",
    "sg:city":"Lille (gierle)",
    "sg:classifiers":[
        {
            "category":"Farming",
            "subcategory":"Crops",
            "type":"Manufacturing & Wholesale Goods"
        }
    ],
    "sg:phone":"+32 14 55 39 36",
    "sg:postcode":"2275",
    "sg:province":"Antwerpen",
    "sg:tags":[
        "vegetable",
        "fruit",
        "-",
        "grower"
    ],
    "wof:name":"Tops R",
    "wof:placetype":"venue"
},
  "geometry": {"coordinates":[4.8632779121,51.2556915283],"type":"Point"}
}