{
  "type": "Feature",
  "properties": {
    "addr:full":"Albert I Laan 98 Koksijde (oostduinkerke) West-Vlaanderen 8670",
    "addr:housenumber":"98",
    "addr:postcode":"8670",
    "addr:street":"Albert I Laan",
    "iso:country":"BE",
    "sg:address":"Albert I Laan 98",
    "sg:city":"Koksijde (oostduinkerke)",
    "sg:classifiers":[
        {
            "category":"Travel",
            "subcategory":"Hotels & Motels",
            "type":"Entertainment"
        }
    ],
    "sg:phone":"+32 58 51 71 06",
    "sg:postcode":"8670",
    "sg:province":"West-Vlaanderen",
    "wof:name":"Ter Yde",
    "wof:placetype":"venue"
},
  "geometry": {"coordinates":[2.6739280224,51.1326560974],"type":"Point"}
}