{
  "type": "Feature",
  "properties": {
    "addr:full":"Turnhoutsebaan 38 Tessenderlo Limburg 3980",
    "addr:housenumber":"38",
    "addr:postcode":"3980",
    "addr:street":"Turnhoutsebaan",
    "iso:country":"BE",
    "sg:address":"Turnhoutsebaan 38",
    "sg:city":"Tessenderlo",
    "sg:orig_category":"Huisdieren and benodigdheden Royal Canin",
    "sg:phone":"+32 13 77 10 19",
    "sg:postcode":"3980",
    "sg:province":"Limburg",
    "wof:name":"Dierenparadijs",
    "wof:placetype":"venue"
},
  "geometry": {"coordinates":[5.0107898712,51.0363121033],"type":"Point"}
}