{
  "type": "Feature",
  "properties": {
    "addr:full":"Rue Emile Schmuck 9 Baelen Li\u00e8ge 4837",
    "addr:housenumber":"9",
    "addr:postcode":"4837",
    "addr:street":"Rue Emile Schmuck",
    "iso:country":"BE",
    "sg:address":"Rue Emile Schmuck 9",
    "sg:city":"Baelen",
    "sg:orig_category":"Charpentes and couvertures",
    "sg:phone":"+32 87 76 34 74",
    "sg:postcode":"4837",
    "sg:province":"Li\u00e8ge",
    "wof:name":"Franz Claassens",
    "wof:placetype":"venue"
},
  "geometry": {"coordinates":[5.9753451347,50.6312561035],"type":"Point"}
}