{
  "type": "Feature",
  "properties": {
    "addr:full":"Rue Lloyd Georges 9 Ch\u00e2telet (ch\u00e2telineau) Hainaut 6200",
    "addr:housenumber":"9",
    "addr:postcode":"6200",
    "addr:street":"Rue Lloyd Georges",
    "iso:country":"BE",
    "sg:address":"Rue Lloyd Georges 9",
    "sg:city":"Ch\u00e2telet (ch\u00e2telineau)",
    "sg:classifiers":[
        {
            "category":"Retail",
            "subcategory":"Veterinary Services",
            "type":"Services"
        }
    ],
    "sg:phone":"+32 71 40 46 12",
    "sg:postcode":"6200",
    "sg:province":"Hainaut",
    "sg:tags":[
        "veterinarian"
    ],
    "wof:name":"Godfroi E",
    "wof:placetype":"venue"
},
  "geometry": {"coordinates":[4.5191631317,50.4125976562],"type":"Point"}
}