{
  "type": "Feature",
  "properties": {
    "addr:full":"Avenue Georges Henri 375 Bruxelles (woluwe-saint-lambert) Bruxelles-Capitale 1200",
    "addr:housenumber":"375",
    "addr:postcode":"1200",
    "addr:street":"Avenue Georges Henri",
    "iso:country":"BE",
    "sg:address":"Avenue Georges Henri 375",
    "sg:city":"Bruxelles (woluwe-saint-lambert)",
    "sg:classifiers":[
        {
            "category":"Shopping",
            "subcategory":"Musical Instruments",
            "type":"Retail Goods"
        }
    ],
    "sg:phone":"+32 2 736 85 74",
    "sg:postcode":"1200",
    "sg:province":"Bruxelles-Capitale",
    "sg:tags":[
        "optical"
    ],
    "wof:name":"Istas (ets)-delhaye Vision Sprl",
    "wof:placetype":"venue"
},
  "geometry": {"coordinates":[4.4084858894,50.8426895142],"type":"Point"}
}