{
  "type": "Feature",
  "properties": {
    "addr:full":"Rue Fr\u00e9d\u00e9ric-nyst 59 Li\u00e8ge 1 (li\u00e8ge 2) Li\u00e8ge 4020",
    "addr:housenumber":"59;1;2",
    "addr:postcode":"4020",
    "addr:street":"Rue Fre\u0301De\u0301Ric-Nyst",
    "iso:country":"BE",
    "sg:address":"Rue Fr\u00e9d\u00e9ric-nyst 59",
    "sg:city":"Li\u00e8ge 1 (li\u00e8ge 2)",
    "sg:classifiers":[
        {
            "category":"Building & Trades",
            "subcategory":"Pest Control",
            "type":"Services"
        }
    ],
    "sg:phone":"+32 4 341 52 35",
    "sg:postcode":"4020",
    "sg:province":"Li\u00e8ge",
    "sg:tags":[
        "painting",
        "contractor"
    ],
    "wof:name":"Marechal V",
    "wof:placetype":"venue"
},
  "geometry": {"coordinates":[5.5919837952,50.6374511719],"type":"Point"}
}