{
  "type": "Feature",
  "properties": {
    "addr:full":"Rode Hoevelaan 78 Stabroek Antwerpen 2940",
    "addr:housenumber":"78",
    "addr:postcode":"2940",
    "addr:street":"Rode Hoevelaan",
    "iso:country":"BE",
    "sg:address":"Rode Hoevelaan 78",
    "sg:city":"Stabroek",
    "sg:classifiers":[
        {
            "category":"Health Services",
            "subcategory":"Health Practitioner",
            "type":"Services"
        }
    ],
    "sg:phone":"+32 3 568 85 35",
    "sg:postcode":"2940",
    "sg:province":"Antwerpen",
    "sg:tags":[
        "dietitian"
    ],
    "wof:name":"Adviesbureau Gracilis",
    "wof:placetype":"venue"
},
  "geometry": {"coordinates":[4.3841648102,51.3289222717],"type":"Point"}
}