{
  "type": "Feature",
  "properties": {
    "addr:full":"Rue Du Wimpelberg 197 Bruxelles Bruxelles-Capitale 1120",
    "addr:housenumber":"197",
    "addr:postcode":"1120",
    "addr:street":"Rue Du Wimpelberg",
    "iso:country":"BE",
    "sg:address":"Rue Du Wimpelberg 197",
    "sg:city":"Bruxelles",
    "sg:classifiers":[
        {
            "category":"Social Services",
            "type":"Services"
        }
    ],
    "sg:phone":"+32 2 268 41 13",
    "sg:postcode":"1120",
    "sg:province":"Bruxelles-Capitale",
    "sg:tags":[
        "handicapped",
        "-"
    ],
    "wof:name":"Potelier (le) Asbl",
    "wof:placetype":"venue"
},
  "geometry": {"coordinates":[4.3858160973,50.8997039795],"type":"Point"}
}