{
  "type": "Feature",
  "properties": {
    "iso:country":"BE",
    "sg:address":"Mechelsesteenweg 111-5",
    "sg:city":"Mortsel",
    "sg:classifiers":[
        {
            "category":"Communications",
            "subcategory":"News Services",
            "type":"Services"
        }
    ],
    "sg:phone":"+32 3 440 33 93",
    "sg:postcode":"2640",
    "sg:province":"Antwerpen",
    "sg:tags":[
        "agency"
    ],
    "wof:name":"Pressscript Bvba",
    "wof:placetype":"venue"
},
  "geometry": {"coordinates":[4.4540481567,51.1661262512],"type":"Point"}
}