{
  "type": "Feature",
  "properties": {
    "addr:full":"Rue Pierre Hans 4bd Charleroi Hainaut 6040",
    "addr:housenumber":"4bd",
    "addr:postcode":"6040",
    "addr:street":"Rue Pierre Hans;Hainaut",
    "iso:country":"BE",
    "sg:address":"Rue Pierre Hans 4bd",
    "sg:city":"Charleroi",
    "sg:orig_category":"Installatie van houten of kunststof schrijnwerk Installatie van metalen schrijnwerk",
    "sg:phone":"+32 71 37 33 81",
    "sg:postcode":"6040",
    "sg:province":"Hainaut",
    "wof:name":"Volet-technic",
    "wof:placetype":"venue"
},
  "geometry": {"coordinates":[4.4395999908,50.4371795654],"type":"Point"}
}