{
  "type": "Feature",
  "properties": {
    "addr:full":"Slakweidestraat 3 Maasmechelen Limburg 3630",
    "addr:housenumber":"3",
    "addr:postcode":"3630",
    "addr:street":"Slakweidestraat",
    "iso:country":"BE",
    "sg:address":"Slakweidestraat 3",
    "sg:city":"Maasmechelen",
    "sg:orig_category":"Houtbewerking and -behandeling",
    "sg:phone":"+32 89 77 15 73",
    "sg:postcode":"3630",
    "sg:province":"Limburg",
    "wof:name":"Hout Service",
    "wof:placetype":"venue"
},
  "geometry": {"coordinates":[5.7024979591,50.9512252808],"type":"Point"}
}