{
  "type": "Feature",
  "properties": {
    "addr:full":"Nouvelle Route 39 Ans Li\u00e8ge 4432",
    "addr:postcode":"4432",
    "addr:street":"Nouvelle Route 39",
    "iso:country":"BE",
    "sg:address":"Nouvelle Route 39",
    "sg:city":"Ans",
    "sg:orig_category":"Dranken",
    "sg:phone":"+32 4 257 64 30",
    "sg:postcode":"4432",
    "sg:province":"Li\u00e8ge",
    "wof:name":"D.l.e. Vins",
    "wof:placetype":"venue"
},
  "geometry": {"coordinates":[5.4870538712,50.7004776001],"type":"Point"}
}