{
  "type": "Feature",
  "properties": {
    "iso:country":"BE",
    "sg:address":"Rue D\u00c9sir\u00c9 Seutin 20",
    "sg:city":"Braine-le-chateau",
    "sg:classifiers":[
        {
            "category":"Personal",
            "subcategory":"Beauty Salon",
            "type":"Services"
        }
    ],
    "sg:phone":"+32 2 366 18 44",
    "sg:postcode":"1440",
    "sg:province":"Brabant Wallon",
    "sg:tags":[
        "de",
        "coiffure"
    ],
    "wof:name":"Coiffure M.c.",
    "wof:placetype":"venue"
},
  "geometry": {"coordinates":[4.3013877869,50.6790657043],"type":"Point"}
}