{
  "type": "Feature",
  "properties": {
    "addr:full":"Sint-bernardsesteenweg 481 Antwerpen Antwerpen 2660",
    "addr:housenumber":"481",
    "addr:postcode":"2660",
    "addr:street":"Sint-Bernardsesteenweg",
    "iso:country":"BE",
    "sg:address":"Sint-bernardsesteenweg 481",
    "sg:city":"Antwerpen",
    "sg:orig_category":"Transports routiers de marchandises",
    "sg:phone":"+32 3 828 32 47",
    "sg:postcode":"2660",
    "sg:province":"Antwerpen",
    "wof:name":"D.l.e. Trans",
    "wof:placetype":"venue"
},
  "geometry": {"coordinates":[4.3397898674,51.1732788086],"type":"Point"}
}