{
  "type": "Feature",
  "properties": {
    "addr:full":"Rue Des Cl\u00e9matites 8 Neupr\u00e9 (neuville-en-condroz) Li\u00e8ge 4121",
    "addr:housenumber":"8",
    "addr:postcode":"4121",
    "addr:street":"Rue Des Cle\u0301Matites",
    "iso:country":"BE",
    "sg:address":"Rue Des Cl\u00e9matites 8",
    "sg:city":"Neupr\u00e9 (neuville-en-condroz)",
    "sg:classifiers":[
        {
            "category":"Food & Beverages",
            "subcategory":"Supermarket",
            "type":"Retail Goods"
        }
    ],
    "sg:phone":"+32 4 371 54 19",
    "sg:postcode":"4121",
    "sg:province":"Li\u00e8ge",
    "sg:tags":[
        "frozen",
        "-"
    ],
    "wof:name":"Garnier (lyon) Sa",
    "wof:placetype":"venue"
},
  "geometry": {"coordinates":[5.4846258163,50.5470237732],"type":"Point"}
}