{
  "type": "Feature",
  "properties": {
    "iso:country":"BE",
    "sg:address":"Drongensestw 49",
    "sg:city":"Gent",
    "sg:classifiers":[
        {
            "category":"Shopping",
            "type":"Retail Goods"
        }
    ],
    "sg:phone":"+32 9 226 63 26",
    "sg:postcode":"9000",
    "sg:province":"Oost-Vlaanderen",
    "sg:tags":[
        "metallurgy",
        "finished",
        "-",
        "metalworking",
        "metallic"
    ],
    "wof:name":"A. Vervaet Brussel Cv",
    "wof:placetype":"venue"
},
  "geometry": {"coordinates":[3.7001819611,51.056892395],"type":"Point"}
}