{
  "type": "Feature",
  "properties": {
    "iso:country":"BE",
    "sg:address":"Kerkstraat 22",
    "sg:city":"De Haan (wenduine)",
    "sg:classifiers":[
        {
            "category":"Travel",
            "subcategory":"Resort",
            "type":"Entertainment"
        }
    ],
    "sg:phone":"+32 50 41 16 47",
    "sg:postcode":"8420",
    "sg:province":"West-Vlaanderen",
    "sg:tags":[
        "rental",
        "accomodation",
        "holiday",
        "-"
    ],
    "wof:name":"Agence Goens Bvba",
    "wof:placetype":"venue"
},
  "geometry": {"coordinates":[3.0331459045,51.2727775574],"type":"Point"}
}