{
  "type": "Feature",
  "properties": {
    "addr:full":"Rue Du Moulin 11 Namur (dave) Namur 5100",
    "addr:housenumber":"11",
    "addr:postcode":"5100",
    "addr:street":"Rue Du Moulin",
    "iso:country":"BE",
    "sg:address":"Rue Du Moulin 11",
    "sg:city":"Namur (dave)",
    "sg:classifiers":[
        {
            "category":"Communications",
            "type":"Services"
        }
    ],
    "sg:phone":"+32 81 41 43 38",
    "sg:postcode":"5100",
    "sg:province":"Namur",
    "sg:tags":[
        "translator"
    ],
    "wof:name":"Balthazart B",
    "wof:placetype":"venue"
},
  "geometry": {"coordinates":[4.8713750839,50.4566345215],"type":"Point"}
}