{
  "type": "Feature",
  "properties": {
    "addr:full":"Chauss\u00c9e De Li\u00c8ge 94bd Herve Li\u00e8ge 4652",
    "addr:housenumber":"94bd",
    "addr:postcode":"4652",
    "addr:street":"Chausse\u0301E De Lie\u0300Ge",
    "iso:country":"BE",
    "sg:address":"Chauss\u00c9e De Li\u00c8ge 94bd",
    "sg:city":"Herve",
    "sg:orig_category":"Artsen and specialisten",
    "sg:phone":"+32 87 66 20 96",
    "sg:postcode":"4652",
    "sg:province":"Li\u00e8ge",
    "wof:name":"B\u00c9n\u00c9dicte Derkenne",
    "wof:placetype":"venue"
},
  "geometry": {"coordinates":[5.766685009,50.6177024841],"type":"Point"}
}