{
  "type": "Feature",
  "properties": {
    "iso:country":"BE",
    "sg:address":"Rue Jules Blondeau 28",
    "sg:city":"Ecaussinnes",
    "sg:orig_category":"Brood, gebak and snoepgoed",
    "sg:phone":"+32 67 44 22 13",
    "sg:postcode":"7190",
    "sg:province":"Hainaut",
    "wof:name":"Alain Delfosse",
    "wof:placetype":"venue"
},
  "geometry": {"coordinates":[4.1477241516,50.5633926392],"type":"Point"}
}