{
  "type": "Feature",
  "properties": {
    "iso:country":"BE",
    "sg:address":"Grand-place 23",
    "sg:city":"Mons",
    "sg:orig_category":"Rechtbanken",
    "sg:phone":"+32 65 31 61 91",
    "sg:postcode":"7000",
    "sg:province":"Hainaut",
    "wof:name":"Cour D'appel",
    "wof:placetype":"venue"
},
  "geometry": {"coordinates":[3.952133894,50.4548492432],"type":"Point"}
}