{
  "type": "Feature",
  "properties": {
    "iso:country":"BE",
    "sg:address":"Rue Du Try 6bb",
    "sg:city":"Namur",
    "sg:orig_category":"M\u00e9decins and sp\u00e9cialistes",
    "sg:phone":"+32 81 21 41 19",
    "sg:postcode":"5021",
    "sg:province":"Namur",
    "wof:name":"Fran\u00c7oise Mouchet",
    "wof:placetype":"venue"
},
  "geometry": {"coordinates":[4.9253940582,50.4947776794],"type":"Point"}
}