{
  "type": "Feature",
  "properties": {
    "iso:country":"BE",
    "sg:address":"Rue Des Fortifications 38",
    "sg:city":"Sint-gillis",
    "sg:orig_category":"Forge, Moulage and Profilage des M\u00e9taux. Constructions non r\u00e9sidentielles sp\u00e9cifiques",
    "sg:phone":"+32 2 537 08 35",
    "sg:postcode":"1060",
    "sg:province":"Bruxelles-Capitale",
    "wof:name":"Cmp Robert",
    "wof:placetype":"venue"
},
  "geometry": {"coordinates":[4.3423900604,50.8283500671],"type":"Point"}
}