{
  "type": "Feature",
  "properties": {
    "iso:country":"BE",
    "sg:address":"Rue D'obigies 10ba",
    "sg:city":"Tournai",
    "sg:orig_category":"Elektrische installaties voor woningen SMEEDWERK, METAALBEWERKING AND POEDERMETALLURGIE",
    "sg:phone":"+32 69 85 99 05",
    "sg:postcode":"7543",
    "sg:province":"Hainaut",
    "wof:name":"Fe. Allara",
    "wof:placetype":"venue"
},
  "geometry": {"coordinates":[3.4311621189,50.6586074829],"type":"Point"}
}