{
  "type": "Feature",
  "properties": {
    "iso:country":"BE",
    "sg:address":"Louveterie 96",
    "sg:city":"Limbourg",
    "sg:orig_category":"Eleveurs de bovins",
    "sg:phone":"+32 87 64 70 49",
    "sg:postcode":"4830",
    "sg:province":"Li\u00e8ge",
    "wof:name":"Jean-claude Geron",
    "wof:placetype":"venue"
},
  "geometry": {"coordinates":[5.9355378151,50.5827064514],"type":"Point"}
}