{
  "type": "Feature",
  "properties": {
    "addr:full":"Lennes 175 Hastiere Namur 5540",
    "addr:housenumber":"175",
    "addr:postcode":"5540",
    "addr:street":"Lennes;Namur",
    "iso:country":"BE",
    "sg:address":"Lennes 175",
    "sg:city":"Hastiere",
    "sg:orig_category":"Eleveurs de bovins",
    "sg:phone":"+32 82 64 63 31",
    "sg:postcode":"5540",
    "sg:province":"Namur",
    "wof:name":"Lebrun Freres",
    "wof:placetype":"venue"
},
  "geometry": {"coordinates":[4.8664569855,50.2177429199],"type":"Point"}
}