{
  "type": "Feature",
  "properties": {
    "addr:full":"Grand'rue 49 Tintigny Luxembourg 6730",
    "addr:housenumber":"49",
    "addr:postcode":"6730",
    "addr:street":"Grand'Rue",
    "iso:country":"BE",
    "sg:address":"Grand'rue 49",
    "sg:city":"Tintigny",
    "sg:classifiers":[
        {
            "category":"Professional",
            "subcategory":"Art Services",
            "type":"Services"
        }
    ],
    "sg:phone":"+32 63 44 40 14",
    "sg:postcode":"6730",
    "sg:province":"Luxembourg",
    "sg:tags":[
        "-",
        "furniture"
    ],
    "wof:name":"Jacquemin P",
    "wof:placetype":"venue"
},
  "geometry": {"coordinates":[5.519217968,49.6826286316],"type":"Point"}
}