{
  "type": "Feature",
  "properties": {
    "addr:full":"H. Consciencestraat 3 Koksijde West-Vlaanderen 8670",
    "addr:housenumber":"3",
    "addr:postcode":"8670",
    "addr:street":"Consciencestraat",
    "iso:country":"BE",
    "sg:address":"H. Consciencestraat 3",
    "sg:city":"Koksijde",
    "sg:orig_category":"Schoenen",
    "sg:phone":"+32 58 52 00 58",
    "sg:postcode":"8670",
    "sg:province":"West-Vlaanderen",
    "wof:name":"Frans Nieulandt",
    "wof:placetype":"venue"
},
  "geometry": {"coordinates":[2.628027916,51.1181373596],"type":"Point"}
}