{
  "type": "Feature",
  "properties": {
    "iso:country":"BE",
    "sg:address":"Einde Were 242",
    "sg:city":"Gent",
    "sg:classifiers":[
        {
            "category":"Education",
            "subcategory":"Special Training",
            "type":"Public Place"
        }
    ],
    "sg:phone":"+32 9 265 84 84",
    "sg:postcode":"9000",
    "sg:province":"Oost-Vlaanderen",
    "sg:tags":[
        "-",
        "processing",
        "data"
    ],
    "wof:name":"Graphic Lettering Nv",
    "wof:placetype":"venue"
},
  "geometry": {"coordinates":[3.7012040615,51.0516548157],"type":"Point"}
}