{
  "type": "Feature",
  "properties": {
    "iso:country":"BE",
    "sg:address":"Adolphe Mathieustraat 64",
    "sg:city":"Elsene/ixelles",
    "sg:orig_category":"Schoonmaakbedrijven and ongediertebestrijding",
    "sg:phone":"+32 2 646 31 34",
    "sg:postcode":"1050",
    "sg:province":"Bruxelles-Capitale",
    "wof:name":"Jose Albuquerque Castro",
    "wof:placetype":"venue"
},
  "geometry": {"coordinates":[4.3813581467,50.8245315552],"type":"Point"}
}