{
  "type": "Feature",
  "properties": {
    "addr:full":"Pelikaansstraat 62 Antwerpen Antwerpen 2018",
    "addr:housenumber":"62",
    "addr:postcode":"2018",
    "addr:street":"Pelikaansstraat",
    "iso:country":"BE",
    "sg:address":"Pelikaansstraat 62",
    "sg:city":"Antwerpen",
    "sg:orig_category":"Diverse intermediaire producten Gh",
    "sg:phone":"+32 3 226 22 27",
    "sg:postcode":"2018",
    "sg:province":"Antwerpen",
    "wof:name":"Caradiam",
    "wof:placetype":"venue"
},
  "geometry": {"coordinates":[4.4202280045,51.2150268555],"type":"Point"}
}