{
  "type": "Feature",
  "properties": {
    "addr:full":"Harelbeekstraat 121 Zwevegem West-Vlaanderen 8550",
    "addr:housenumber":"121",
    "addr:postcode":"8550",
    "addr:street":"Harelbeekstraat",
    "iso:country":"BE",
    "sg:address":"Harelbeekstraat 121",
    "sg:city":"Zwevegem",
    "sg:classifiers":[
        {
            "category":"Real Estate",
            "subcategory":"Surveying",
            "type":"Services"
        }
    ],
    "sg:phone":"+32 56 75 37 35",
    "sg:postcode":"8550",
    "sg:province":"West-Vlaanderen",
    "sg:tags":[
        "lettering",
        "letter"
    ],
    "wof:name":"Sign & Design",
    "wof:placetype":"venue"
},
  "geometry": {"coordinates":[3.3264110088,50.8198394775],"type":"Point"}
}