{
  "type": "Feature",
  "properties": {
    "iso:country":"BE",
    "sg:address":"Koning Albertstraat 1",
    "sg:city":"Diest",
    "sg:classifiers":[
        {
            "category":"Restaurant",
            "type":"Food & Drink"
        }
    ],
    "sg:phone":"+32 13 32 21 74",
    "sg:postcode":"3290",
    "sg:province":"Vlaams-Brabant",
    "wof:name":"In De Beiaard",
    "wof:placetype":"venue"
},
  "geometry": {"coordinates":[5.0518608093,50.9849319458],"type":"Point"}
}