{
  "type": "Feature",
  "properties": {
    "addr:full":"Turnhoutsebaan 314 Schilde Antwerpen 2970",
    "addr:housenumber":"314",
    "addr:postcode":"2970",
    "addr:street":"Turnhoutsebaan",
    "iso:country":"BE",
    "sg:address":"Turnhoutsebaan 314",
    "sg:city":"Schilde",
    "sg:orig_category":"M\u00e9decins and sp\u00e9cialistes",
    "sg:phone":"+32 3 385 22 30",
    "sg:postcode":"2970",
    "sg:province":"Antwerpen",
    "wof:name":"I. Pairon",
    "wof:placetype":"venue"
},
  "geometry": {"coordinates":[4.5844230652,51.2411231995],"type":"Point"}
}