{
  "type": "Feature",
  "properties": {
    "iso:country":"BE",
    "sg:address":"Buschstrasse 12",
    "sg:city":"Kelmis/la Calamine",
    "sg:orig_category":"M\u00e9decins and sp\u00e9cialistes",
    "sg:phone":"+32 87 65 76 59",
    "sg:postcode":"4728",
    "sg:province":"Li\u00e8ge",
    "wof:name":"Joseph Braun",
    "wof:placetype":"venue"
},
  "geometry": {"coordinates":[6.0450167656,50.7190170288],"type":"Point"}
}