{
  "type": "Feature",
  "properties": {
    "iso:country":"BE",
    "sg:address":"Kortebosstraat 12",
    "sg:city":"Nazareth",
    "sg:orig_category":"Secretariaatsdiensten",
    "sg:phone":"+32 9 385 55 55",
    "sg:postcode":"9810",
    "sg:province":"Oost-Vlaanderen",
    "wof:name":"Fa. Vanhalst",
    "wof:placetype":"venue"
},
  "geometry": {"coordinates":[3.6519100666,50.9730033875],"type":"Point"}
}