{
  "type": "Feature",
  "properties": {
    "iso:country":"BE",
    "sg:address":"Place Wilson 116",
    "sg:city":"Chatelet",
    "sg:classifiers":[
        {
            "category":"Health Services",
            "subcategory":"Nursing And Care Facility",
            "type":"Services"
        }
    ],
    "sg:phone":"+32 71 24 32 36",
    "sg:postcode":"6200",
    "sg:province":"Hainaut",
    "sg:tags":[
        "public"
    ],
    "wof:name":"Administration Communale",
    "wof:placetype":"venue"
},
  "geometry": {"coordinates":[4.51836586,50.4160385132],"type":"Point"}
}