{
  "type": "Feature",
  "properties": {
    "addr:full":"Rue Mathias 59 Braine-le-ch\u00c2teau Brabant Wallon 1440",
    "addr:housenumber":"59",
    "addr:postcode":"1440",
    "addr:street":"Rue Mathias",
    "iso:country":"BE",
    "sg:address":"Rue Mathias 59",
    "sg:city":"Braine-le-ch\u00c2teau",
    "sg:orig_category":"Installatie van houten of kunststof schrijnwerk",
    "sg:phone":"+32 2 366 99 34",
    "sg:postcode":"1440",
    "sg:province":"Brabant Wallon",
    "wof:name":"Fe. Marenga",
    "wof:placetype":"venue"
},
  "geometry": {"coordinates":[4.2607140541,50.6950454712],"type":"Point"}
}