{
  "type": "Feature",
  "properties": {
    "iso:country":"BE",
    "sg:address":"Wijngaardstraat 35",
    "sg:city":"Dilbeek",
    "sg:orig_category":"Dranken",
    "sg:phone":"+32 2 569 22 63",
    "sg:postcode":"1703",
    "sg:province":"Vlaams-Brabant",
    "wof:name":"Marcellus Van Cauter",
    "wof:placetype":"venue"
},
  "geometry": {"coordinates":[4.1982970238,50.8409194946],"type":"Point"}
}