{
  "type": "Feature",
  "properties": {
    "iso:country":"BE",
    "sg:address":"Wontergemstraat 31",
    "sg:city":"Dentergem",
    "sg:orig_category":"R\u00e9alisation de programmes and logiciels",
    "sg:phone":"+32 51 63 61 35",
    "sg:postcode":"8720",
    "sg:province":"West-Vlaanderen",
    "wof:name":"B-scene",
    "wof:placetype":"venue"
},
  "geometry": {"coordinates":[3.422082901,50.9632873535],"type":"Point"}
}