{
  "type": "Feature",
  "properties": {
    "iso:country":"BE",
    "sg:address":"Eeckhoutstraat 47",
    "sg:city":"Aalst (hofstade)",
    "sg:classifiers":[
        {
            "category":"Retail",
            "subcategory":"Animal Services",
            "type":"Services"
        }
    ],
    "sg:phone":"+32 53 21 14 63",
    "sg:postcode":"9308",
    "sg:province":"Oost-Vlaanderen",
    "sg:tags":[
        "grooming",
        "-",
        "dog"
    ],
    "wof:name":"Black Beauty",
    "wof:placetype":"venue"
},
  "geometry": {"coordinates":[4.1316890717,50.9273796082],"type":"Point"}
}