{
  "type": "Feature",
  "properties": {
    "addr:full":"Evendael 15 Herzele Oost-Vlaanderen 9550",
    "addr:housenumber":"15",
    "addr:postcode":"9550",
    "addr:street":"Evendael;Oost-Vlaanderen",
    "iso:country":"BE",
    "sg:address":"Evendael 15",
    "sg:city":"Herzele",
    "sg:classifiers":[
        {
            "category":"Arts & Performance",
            "subcategory":"Art Gallery",
            "type":"Entertainment"
        }
    ],
    "sg:phone":"+32 53 62 23 78",
    "sg:postcode":"9550",
    "sg:province":"Oost-Vlaanderen",
    "sg:tags":[
        "rendering"
    ],
    "wof:name":"De Lombaert F",
    "wof:placetype":"venue"
},
  "geometry": {"coordinates":[3.8935029507,50.8834877014],"type":"Point"}
}