{
  "type": "Feature",
  "properties": {
    "addr:full":"Avenue Louise 419 Brussel/bruxelles Bruxelles-Capitale 1050",
    "addr:housenumber":"419",
    "addr:postcode":"1050",
    "addr:street":"Avenue Louise;/",
    "iso:country":"BE",
    "sg:address":"Avenue Louise 419",
    "sg:city":"Brussel/bruxelles",
    "sg:orig_category":"V\u00eatements. Location de v\u00eatements, chaussures and textiles. V\u00eatements sur mesure Fab",
    "sg:phone":"+32 2 639 14 40",
    "sg:postcode":"1050",
    "sg:province":"Bruxelles-Capitale",
    "wof:name":"Old England",
    "wof:placetype":"venue"
},
  "geometry": {"coordinates":[4.355919838,50.8357810974],"type":"Point"}
}