{
  "type": "Feature",
  "properties": {
    "iso:country":"BE",
    "sg:address":"Rue De La Ri\u00e8ze 49",
    "sg:city":"Couvin (cul-des-sarts)",
    "sg:classifiers":[
        {
            "category":"Shopping",
            "subcategory":"Computers & Home Electronics",
            "type":"Retail Goods"
        }
    ],
    "sg:phone":"+32 60 37 70 16",
    "sg:postcode":"5660",
    "sg:province":"Namur",
    "sg:tags":[
        "-",
        "television",
        "radio"
    ],
    "wof:name":"Laurent P",
    "wof:placetype":"venue"
},
  "geometry": {"coordinates":[4.4592900276,49.963470459],"type":"Point"}
}