{
  "type": "Feature",
  "properties": {
    "iso:country":"BE",
    "sg:address":"Hollandstraat 47",
    "sg:city":"Sint-gillis/saint-gilles",
    "sg:orig_category":"Voertuigen",
    "sg:phone":"+32 2 534 02 86",
    "sg:postcode":"1060",
    "sg:province":"Bruxelles-Capitale",
    "wof:name":"Districar",
    "wof:placetype":"venue"
},
  "geometry": {"coordinates":[4.3395681381,50.8341598511],"type":"Point"}
}