{
  "type": "Feature",
  "properties": {
    "addr:full":"Mettenveld 42 Genk Limburg 3600",
    "addr:housenumber":"42",
    "addr:postcode":"3600",
    "addr:street":"Mettenveld",
    "iso:country":"BE",
    "sg:address":"Mettenveld 42",
    "sg:city":"Genk",
    "sg:classifiers":[
        {
            "category":"Communications",
            "subcategory":"Television Station",
            "type":"Services"
        }
    ],
    "sg:phone":"+32 89 35 50 63",
    "sg:postcode":"3600",
    "sg:province":"Limburg",
    "sg:tags":[
        "video",
        "audio",
        "verhuur"
    ],
    "wof:name":"Fantasia",
    "wof:placetype":"venue"
},
  "geometry": {"coordinates":[5.5264167786,50.9718437195],"type":"Point"}
}