{
  "type": "Feature",
  "properties": {
    "iso:country":"BE",
    "sg:address":"Rue De Goz\u00c9e 587",
    "sg:city":"Montigny-le-tilleul",
    "sg:orig_category":"Meubelzaken, woning- and keukeninrichting",
    "sg:phone":"+32 71 51 19 41",
    "sg:postcode":"6110",
    "sg:province":"Hainaut",
    "wof:name":"Fabrimeuble",
    "wof:placetype":"venue"
},
  "geometry": {"coordinates":[4.3638148308,50.3691139221],"type":"Point"}
}