{
  "type": "Feature",
  "properties": {
    "iso:country":"BE",
    "sg:address":"Regentieplein 13",
    "sg:city":"Sint-niklaas",
    "sg:classifiers":[
        {
            "category":"Health Services",
            "subcategory":"Health Practitioner",
            "type":"Services"
        }
    ],
    "sg:phone":"+32 3 776 52 55",
    "sg:postcode":"9100",
    "sg:province":"Oost-Vlaanderen",
    "sg:tags":[
        "physiotherapist"
    ],
    "wof:name":"Pauwels Johan",
    "wof:placetype":"venue"
},
  "geometry": {"coordinates":[4.1454291344,51.1683959961],"type":"Point"}
}