{
  "type": "Feature",
  "properties": {
    "addr:full":"Prins Van Everbergstraat 7 Kortenberg Vlaams-Brabant 3078",
    "addr:housenumber":"7",
    "addr:postcode":"3078",
    "addr:street":"Prins Van Everbergstraat;Vlaams-Brabant",
    "iso:country":"BE",
    "sg:address":"Prins Van Everbergstraat 7",
    "sg:city":"Kortenberg",
    "sg:orig_category":"Groententeelt",
    "sg:phone":"+32 2 759 92 27",
    "sg:postcode":"3078",
    "sg:province":"Vlaams-Brabant",
    "wof:name":"Van Grunderbeeck Gustaaf",
    "wof:placetype":"venue"
},
  "geometry": {"coordinates":[4.5711278915,50.8766670227],"type":"Point"}
}