{
  "type": "Feature",
  "properties": {
    "iso:country":"BE",
    "sg:address":"Scheidingsstraat 2",
    "sg:city":"Erpe-mere (mere)",
    "sg:classifiers":[
        {
            "category":"Education",
            "subcategory":"Special Training",
            "type":"Public Place"
        }
    ],
    "sg:phone":"+32 53 83 26 76",
    "sg:postcode":"9420",
    "sg:province":"Oost-Vlaanderen",
    "sg:tags":[
        "-",
        "processing",
        "data"
    ],
    "wof:name":"Hoffelinck M",
    "wof:placetype":"venue"
},
  "geometry": {"coordinates":[3.9667971134,50.9200630188],"type":"Point"}
}