{
  "type": "Feature",
  "properties": {
    "addr:full":"Parc Industriel 1 Ciney Namur 5590",
    "addr:housenumber":"1",
    "addr:postcode":"5590",
    "addr:street":"Parc Industriel",
    "iso:country":"BE",
    "sg:address":"Parc Industriel 1",
    "sg:city":"Ciney",
    "sg:orig_category":"Installatie van houten of kunststof schrijnwerk",
    "sg:phone":"+32 83 21 46 77",
    "sg:postcode":"5590",
    "sg:province":"Namur",
    "wof:name":"Kalbet",
    "wof:placetype":"venue"
},
  "geometry": {"coordinates":[5.0915799141,50.2924880981],"type":"Point"}
}