{
  "type": "Feature",
  "properties": {
    "iso:country":"BE",
    "sg:address":"Rue Des Forges 17",
    "sg:city":"Fosses-la-ville",
    "sg:classifiers":[
        {
            "category":"Personal",
            "subcategory":"Beauty Salon",
            "type":"Services"
        }
    ],
    "sg:phone":"+32 71 71 27 56",
    "sg:postcode":"5070",
    "sg:province":"Namur",
    "sg:tags":[
        "lady",
        "-",
        "hairdressing"
    ],
    "wof:name":"Molle N",
    "wof:placetype":"venue"
},
  "geometry": {"coordinates":[4.6865181923,50.3908500671],"type":"Point"}
}