{
  "type": "Feature",
  "properties": {
    "addr:full":"Mieksebaan 97 Brecht Antwerpen 2960",
    "addr:housenumber":"97",
    "addr:postcode":"2960",
    "addr:street":"Mieksebaan",
    "iso:country":"BE",
    "sg:address":"Mieksebaan 97",
    "sg:city":"Brecht",
    "sg:classifiers":[
        {
            "category":"Professional",
            "subcategory":"Computer Services",
            "type":"Services"
        }
    ],
    "sg:phone":"+32 3 663 30 20",
    "sg:postcode":"2960",
    "sg:province":"Antwerpen",
    "sg:tags":[
        "-",
        "processing",
        "data"
    ],
    "wof:name":"Dacom Nv",
    "wof:placetype":"venue"
},
  "geometry": {"coordinates":[4.5805602074,51.3247299194],"type":"Point"}
}