{
  "type": "Feature",
  "properties": {
    "addr:full":"110 Gentsestr Moorslede West-Vlaanderen 8890",
    "addr:housenumber":"110",
    "addr:postcode":"8890",
    "addr:street":"Gentsestr",
    "iso:country":"BE",
    "sg:address":"110 Gentsestr",
    "sg:city":"Moorslede",
    "sg:classifiers":[
        {
            "category":"Home & Garden",
            "subcategory":"Furniture",
            "type":"Retail Goods"
        }
    ],
    "sg:phone":"+32 51 78 08 08",
    "sg:postcode":"8890",
    "sg:province":"West-Vlaanderen",
    "sg:tags":[
        "household",
        "wood"
    ],
    "wof:name":"Verfaillie Gebr Meubelfabriek Nv",
    "wof:placetype":"venue"
},
  "geometry": {"coordinates":[3.0720899105,50.8941917419],"type":"Point"}
}