{
  "type": "Feature",
  "properties": {
    "iso:country":"BE",
    "sg:address":"Rue De Deminche 93",
    "sg:city":"Floreffe (frani\u00e8re)",
    "sg:classifiers":[
        {
            "category":"Professional",
            "subcategory":"Management & Consulting",
            "type":"Services"
        }
    ],
    "sg:phone":"+32 81 20 77 92",
    "sg:postcode":"5150",
    "sg:province":"Namur",
    "sg:tags":[
        "tax-consultants"
    ],
    "wof:name":"Englebert J-c",
    "wof:placetype":"venue"
},
  "geometry": {"coordinates":[4.718665123,50.4322433472],"type":"Point"}
}