{
  "type": "Feature",
  "properties": {
    "iso:country":"BE",
    "sg:address":"Avenue Louise 526",
    "sg:city":"Bruxelles (ixelles)",
    "sg:classifiers":[
        {
            "category":"Travel",
            "subcategory":"Travel Agent",
            "type":"Entertainment"
        }
    ],
    "sg:phone":"+32 2 648 60 24",
    "sg:postcode":"1050",
    "sg:province":"Bruxelles-Capitale",
    "sg:tags":[
        "agency"
    ],
    "wof:name":"Belgian Travel House Sa",
    "wof:placetype":"venue"
},
  "geometry": {"coordinates":[4.3572201729,50.8337287903],"type":"Point"}
}