{
  "type": "Feature",
  "properties": {
    "addr:full":"Rue Laurent Vandenhoven 56 Bruxelles (evere) Bruxelles-Capitale 1140",
    "addr:housenumber":"56",
    "addr:postcode":"1140",
    "addr:street":"Rue Laurent Vandenhoven",
    "iso:country":"BE",
    "sg:address":"Rue Laurent Vandenhoven 56",
    "sg:city":"Bruxelles (evere)",
    "sg:classifiers":[
        {
            "category":"Home & Garden",
            "subcategory":"Hardware",
            "type":"Retail Goods"
        }
    ],
    "sg:phone":"+32 2 242 55 02",
    "sg:postcode":"1140",
    "sg:province":"Bruxelles-Capitale",
    "sg:tags":[
        "-"
    ],
    "wof:name":"Springfix Sprl",
    "wof:placetype":"venue"
},
  "geometry": {"coordinates":[4.4054589272,50.8822059631],"type":"Point"}
}