{
  "type": "Feature",
  "properties": {
    "iso:country":"BE",
    "sg:address":"Avenue Alphonse Allard 105",
    "sg:city":"Braine-l'alleud",
    "sg:orig_category":"Algemeen secundair onderwijs Kleuter- en basisonderwijs",
    "sg:phone":"+32 2 384 55 11",
    "sg:postcode":"1420",
    "sg:province":"Brabant Wallon",
    "wof:name":"Ecole Fondamentale",
    "wof:placetype":"venue"
},
  "geometry": {"coordinates":[-0.7004899979,47.369140625],"type":"Point"}
}