{
  "type": "Feature",
  "properties": {
    "iso:country":"BE",
    "sg:address":"Europark-noord 31",
    "sg:city":"Sint-niklaas",
    "sg:orig_category":"Filter Bags",
    "sg:phone":"+32 3 778 18 17",
    "sg:postcode":"9100",
    "sg:province":"Oost-Vlaanderen",
    "wof:name":"Melitta Nv",
    "wof:placetype":"venue"
},
  "geometry": {"coordinates":[4.1665477753,51.1682167053],"type":"Point"}
}