{
  "type": "Feature",
  "properties": {
    "addr:full":"Place Du Roi Albert 1er 21 Marche-en-famenne Luxembourg 6900",
    "addr:housenumber":"21",
    "addr:postcode":"6900",
    "addr:street":"Place Du Roi Albert 1Er",
    "iso:country":"BE",
    "sg:address":"Place Du Roi Albert 1er 21",
    "sg:city":"Marche-en-famenne",
    "sg:classifiers":[
        {
            "category":"Restaurant",
            "type":"Food & Drink"
        }
    ],
    "sg:phone":"+32 84 31 61 81",
    "sg:postcode":"6900",
    "sg:province":"Luxembourg",
    "wof:name":"Des Arts",
    "wof:placetype":"venue"
},
  "geometry": {"coordinates":[5.3433837891,50.2278594971],"type":"Point"}
}