{
  "type": "Feature",
  "properties": {
    "iso:country":"BE",
    "sg:address":"Kortrijksesteenweg 26",
    "sg:city":"Harelbeke",
    "sg:orig_category":"Journaux",
    "sg:phone":"+32 56 71 99 24",
    "sg:postcode":"8530",
    "sg:province":"West-Vlaanderen",
    "wof:name":"Dagbladhandel - Tierce",
    "wof:placetype":"venue"
},
  "geometry": {"coordinates":[3.3036360741,50.8512573242],"type":"Point"}
}