{
  "type": "Feature",
  "properties": {
    "iso:country":"BE",
    "sg:address":"Rue Van Eyck 11c",
    "sg:city":"Bruxelles (ixelles)",
    "sg:classifiers":[
        {
            "category":"Professional",
            "subcategory":"Accounting & Tax Preparation",
            "type":"Services"
        }
    ],
    "sg:phone":"+32 2 644 15 67",
    "sg:postcode":"1050",
    "sg:province":"Bruxelles-Capitale",
    "sg:tags":[
        "bookkeeper"
    ],
    "wof:name":"De Vaucleroy C",
    "wof:placetype":"venue"
},
  "geometry": {"coordinates":[4.3672199249,50.8203735352],"type":"Point"}
}