{
  "type": "Feature",
  "properties": {
    "iso:country":"BE",
    "sg:address":"Val Du Puits 17",
    "sg:city":"Grez-doiceau (bossut-gottechain)",
    "sg:classifiers":[
        {
            "category":"Manufacturing",
            "subcategory":"Metals",
            "type":"Manufacturing & Wholesale Goods"
        }
    ],
    "sg:phone":"+32 475 41 16 44",
    "sg:postcode":"1390",
    "sg:province":"Brabant Wallon",
    "sg:tags":[
        "sheet",
        "machinery",
        "working"
    ],
    "wof:name":"Schumacher Sprl",
    "wof:placetype":"venue"
},
  "geometry": {"coordinates":[4.6909341812,50.7594604492],"type":"Point"}
}