{
  "type": "Feature",
  "properties": {
    "addr:full":"Zandweg Naar Zerkegem 13 Jabbeke (snellegem) West-Vlaanderen 8490",
    "addr:housenumber":"13",
    "addr:postcode":"8490",
    "addr:street":"Zandweg Naar Zerkegem",
    "iso:country":"BE",
    "sg:address":"Zandweg Naar Zerkegem 13",
    "sg:city":"Jabbeke (snellegem)",
    "sg:classifiers":[
        {
            "category":"Wholesale",
            "subcategory":"Plants",
            "type":"Manufacturing & Wholesale Goods"
        }
    ],
    "sg:phone":"+32 50 81 36 24",
    "sg:postcode":"8490",
    "sg:province":"West-Vlaanderen",
    "sg:tags":[
        "whol",
        "flower",
        "-",
        "grower"
    ],
    "wof:name":"Meuleman",
    "wof:placetype":"venue"
},
  "geometry": {"coordinates":[3.0864429474,51.1782531738],"type":"Point"}
}