{
  "type": "Feature",
  "properties": {
    "iso:country":"BE",
    "sg:address":"Chauss\u00e9e De Charleroi 123",
    "sg:city":"Fosses-la-ville (vitrival)",
    "sg:classifiers":[
        {
            "category":"Professional",
            "subcategory":"Printing & Photocopies",
            "type":"Services"
        }
    ],
    "sg:phone":"+32 71 71 28 87",
    "sg:postcode":"5070",
    "sg:province":"Namur",
    "sg:tags":[
        "-",
        "offset"
    ],
    "wof:name":"Nouvelles Imprimeries Fossoises Sprl",
    "wof:placetype":"venue"
},
  "geometry": {"coordinates":[4.6720647812,50.3931503296],"type":"Point"}
}