{
  "type": "Feature",
  "properties": {
    "iso:country":"BE",
    "sg:address":"Koning Albertstraat 38",
    "sg:city":"Eeklo",
    "sg:classifiers":[
        {
            "category":"Personal",
            "subcategory":"Beauty Salon",
            "type":"Services"
        }
    ],
    "sg:phone":"+32 9 377 99 44",
    "sg:postcode":"9900",
    "sg:province":"Oost-Vlaanderen",
    "wof:name":"Beauty-home",
    "wof:placetype":"venue"
},
  "geometry": {"coordinates":[3.5616769791,51.1854858398],"type":"Point"}
}