{
  "type": "Feature",
  "properties": {
    "iso:country":"BE",
    "sg:address":"Boelare 2",
    "sg:city":"Oudenaarde",
    "sg:orig_category":"V\u00e9t\u00e9rinaires",
    "sg:phone":"+32 55 38 77 77",
    "sg:postcode":"9700",
    "sg:province":"Oost-Vlaanderen",
    "wof:name":"Johan Verlinden",
    "wof:placetype":"venue"
},
  "geometry": {"coordinates":[3.5594739914,50.7955436707],"type":"Point"}
}