{
  "type": "Feature",
  "properties": {
    "addr:full":"Witteweg 90 Komen-waasten/comines-warneton Hainaut 7782",
    "addr:housenumber":"90",
    "addr:postcode":"7782",
    "addr:street":"Witteweg",
    "iso:country":"BE",
    "sg:address":"Witteweg 90",
    "sg:city":"Komen-waasten/comines-warneton",
    "sg:orig_category":"Supermarkten",
    "sg:postcode":"7782",
    "sg:province":"Hainaut",
    "wof:name":"Aldi",
    "wof:placetype":"venue"
},
  "geometry": {"coordinates":[2.8795371056,50.7278747559],"type":"Point"}
}