{
  "type": "Feature",
  "properties": {
    "addr:full":"A.j. Slegerslaan 65b3 Sint-lambrechts-woluwe/woluwe-saint-lambert Bruxelles-Capitale 1200",
    "addr:housenumber":"65b3",
    "addr:postcode":"1200",
    "addr:street":"A.J. Slegerslaan",
    "iso:country":"BE",
    "sg:address":"A.j. Slegerslaan 65b3",
    "sg:city":"Sint-lambrechts-woluwe/woluwe-saint-lambert",
    "sg:orig_category":"Advocaten and juridische adviseurs",
    "sg:phone":"+32 2 776 02 60",
    "sg:postcode":"1200",
    "sg:province":"Bruxelles-Capitale",
    "wof:name":"L. Morelle",
    "wof:placetype":"venue"
},
  "geometry": {"coordinates":[4.4281778336,50.8408927917],"type":"Point"}
}