{
  "type": "Feature",
  "properties": {
    "iso:country":"BE",
    "sg:address":"Rue De La Saboterie 24",
    "sg:city":"Momignies (seloignes)",
    "sg:classifiers":[
        {
            "category":"Restaurant",
            "type":"Food & Drink"
        }
    ],
    "sg:phone":"+32 60 51 25 21",
    "sg:postcode":"6596",
    "sg:province":"Hainaut",
    "sg:tags":[
        "industrial",
        "kitchen",
        "catering"
    ],
    "wof:name":"Escargots De S'lognes",
    "wof:placetype":"venue"
},
  "geometry": {"coordinates":[4.2576899529,50.0019721985],"type":"Point"}
}