{
  "type": "Feature",
  "properties": {
    "iso:country":"BE",
    "sg:address":"Vlamingenstraat 2",
    "sg:city":"Jette/jette",
    "sg:orig_category":"Elektrische installaties voor woningen",
    "sg:phone":"+32 2 426 00 04",
    "sg:postcode":"1090",
    "sg:province":"Bruxelles-Capitale",
    "wof:name":"Henri Florin",
    "wof:placetype":"venue"
},
  "geometry": {"coordinates":[4.3248291016,50.8753471375],"type":"Point"}
}