{
  "type": "Feature",
  "properties": {
    "iso:country":"BE",
    "sg:address":"Oude Staatsbaan 60",
    "sg:city":"Zomergem",
    "sg:classifiers":[
        {
            "category":"Home & Garden",
            "subcategory":"Home Furnishings",
            "type":"Retail Goods"
        }
    ],
    "sg:phone":"+32 9 372 77 55",
    "sg:postcode":"9930",
    "sg:province":"Oost-Vlaanderen",
    "sg:tags":[
        "interior",
        "decoration"
    ],
    "wof:name":"Decosfeer Debbaut",
    "wof:placetype":"venue"
},
  "geometry": {"coordinates":[3.6016180515,51.1330337524],"type":"Point"}
}