{
  "type": "Feature",
  "properties": {
    "addr:full":"Heide 162 Lommel Limburg 3920",
    "addr:housenumber":"162",
    "addr:postcode":"3920",
    "addr:street":"Heide",
    "iso:country":"BE",
    "sg:address":"Heide 162",
    "sg:city":"Lommel",
    "sg:classifiers":[
        {
            "category":"Farming",
            "subcategory":"Farm & Veterinary Services",
            "type":"Manufacturing & Wholesale Goods"
        }
    ],
    "sg:phone":"+32 11 55 10 23",
    "sg:postcode":"3920",
    "sg:province":"Limburg",
    "sg:tags":[
        "agricultural",
        "contractor"
    ],
    "wof:name":"Huysmans Loonbedrijf",
    "wof:placetype":"venue"
},
  "geometry": {"coordinates":[5.3265447617,51.2421684265],"type":"Point"}
}