{
  "type": "Feature",
  "properties": {
    "iso:country":"BE",
    "sg:address":"Gemeentestraat 4",
    "sg:city":"Turnhout",
    "sg:classifiers":[
        {
            "category":"Professional",
            "subcategory":"Lawyer & Legal Services",
            "type":"Services"
        }
    ],
    "sg:phone":"+32 14 42 26 63",
    "sg:postcode":"2300",
    "sg:province":"Antwerpen",
    "wof:name":"Wilmots Rik",
    "wof:placetype":"venue"
},
  "geometry": {"coordinates":[4.9424982071,51.3232917786],"type":"Point"}
}