{
  "type": "Feature",
  "properties": {
    "iso:country":"BE",
    "sg:address":"Hoogveld 63",
    "sg:city":"Dendermonde",
    "sg:classifiers":[
        {
            "category":"Professional",
            "type":"Services"
        }
    ],
    "sg:phone":"+32 52 22 50 50",
    "sg:postcode":"9200",
    "sg:province":"Oost-Vlaanderen",
    "sg:tags":[
        "transport"
    ],
    "wof:name":"Van Mulders-ballon B.v.b.a.",
    "wof:placetype":"venue"
},
  "geometry": {"coordinates":[4.1400718689,51.029132843],"type":"Point"}
}