{
  "type": "Feature",
  "properties": {
    "addr:full":"Chee De Binche 101 Mons Hainaut 7000",
    "addr:housenumber":"101",
    "addr:postcode":"7000",
    "addr:street":"Chee;Hainaut",
    "iso:country":"BE",
    "sg:address":"Chee De Binche 101",
    "sg:city":"Mons",
    "sg:classifiers":[
        {
            "category":"Banks & Credit Unions",
            "subcategory":"Bank",
            "type":"Services"
        }
    ],
    "sg:phone":"+32 65 35 66 11",
    "sg:postcode":"7000",
    "sg:province":"Hainaut",
    "wof:name":"Banque Cr\u00e9dit Commercial",
    "wof:placetype":"venue"
},
  "geometry": {"coordinates":[3.9737520218,50.4527206421],"type":"Point"}
}