{
  "type": "Feature",
  "properties": {
    "addr:full":"Rue Des Ecoles 199 Mons (obourg) Hainaut 7034",
    "addr:housenumber":"199",
    "addr:postcode":"7034",
    "addr:street":"Rue Des Ecoles",
    "iso:country":"BE",
    "sg:address":"Rue Des Ecoles 199",
    "sg:city":"Mons (obourg)",
    "sg:classifiers":[
        {
            "category":"Autos & Motor Vehicles",
            "subcategory":"Automobile Sales",
            "type":"Retail Goods"
        }
    ],
    "sg:phone":"+32 65 84 77 61",
    "sg:postcode":"7034",
    "sg:province":"Hainaut",
    "sg:tags":[
        "car",
        "used",
        "-"
    ],
    "wof:name":"Gadget",
    "wof:placetype":"venue"
},
  "geometry": {"coordinates":[4.0086159706,50.4765396118],"type":"Point"}
}