{
  "type": "Feature",
  "properties": {
    "addr:full":"Grotstraat 22 Bilzen (beverst) Limburg 3740",
    "addr:housenumber":"22",
    "addr:postcode":"3740",
    "addr:street":"Grotstraat",
    "iso:country":"BE",
    "sg:address":"Grotstraat 22",
    "sg:city":"Bilzen (beverst)",
    "sg:classifiers":[
        {
            "category":"Building & Trades",
            "subcategory":"Landscaping Services",
            "type":"Services"
        }
    ],
    "sg:phone":"+32 89 51 51 99",
    "sg:postcode":"3740",
    "sg:province":"Limburg",
    "sg:tags":[
        "slaughterer"
    ],
    "wof:name":"Groven E",
    "wof:placetype":"venue"
},
  "geometry": {"coordinates":[5.4825649261,50.9042663574],"type":"Point"}
}