{
  "type": "Feature",
  "properties": {
    "iso:country":"BE",
    "sg:address":"Rue Neuve 41",
    "sg:city":"Charleroi (grand)",
    "sg:orig_category":"Biens d'occasion",
    "sg:phone":"+32 71 30 06 98",
    "sg:postcode":"6000",
    "sg:province":"Hainaut",
    "wof:name":"Boutique Anthony",
    "wof:placetype":"venue"
},
  "geometry": {"coordinates":[4.445376873,50.4131851196],"type":"Point"}
}