{
  "type": "Feature",
  "properties": {
    "addr:full":"Kruisabeelstraat 33 Aalst Oost-Vlaanderen 9310",
    "addr:housenumber":"33",
    "addr:postcode":"9310",
    "addr:street":"Kruisabeelstraat",
    "iso:country":"BE",
    "sg:address":"Kruisabeelstraat 33",
    "sg:city":"Aalst",
    "sg:orig_category":"Producteurs de fruits. Fleurs and plantes",
    "sg:phone":"+32 53 70 08 64",
    "sg:postcode":"9310",
    "sg:province":"Oost-Vlaanderen",
    "wof:name":"Jozef Van Weyenbergh",
    "wof:placetype":"venue"
},
  "geometry": {"coordinates":[4.0935130119,50.9647521973],"type":"Point"}
}