{
  "type": "Feature",
  "properties": {
    "addr:full":"Geraardsbergsestraat 1 Aalst Oost-Vlaanderen 9300",
    "addr:housenumber":"1",
    "addr:postcode":"9300",
    "addr:street":"Geraardsbergsestraat",
    "iso:country":"BE",
    "sg:address":"Geraardsbergsestraat 1",
    "sg:city":"Aalst",
    "sg:classifiers":[
        {
            "category":"Shopping",
            "subcategory":"Clothing, Apparel, & Fashions",
            "type":"Retail Goods"
        }
    ],
    "sg:phone":"+32 53 77 48 54",
    "sg:postcode":"9300",
    "sg:province":"Oost-Vlaanderen",
    "sg:tags":[
        "-",
        "fur"
    ],
    "wof:name":"Kelly Furs",
    "wof:placetype":"venue"
},
  "geometry": {"coordinates":[4.0373568535,50.9345664978],"type":"Point"}
}