{
  "type": "Feature",
  "properties": {
    "addr:full":"Bruggestraat 8 Ingelmunster West-Vlaanderen 8770",
    "addr:housenumber":"8",
    "addr:postcode":"8770",
    "addr:street":"Bruggestraat",
    "iso:country":"BE",
    "sg:address":"Bruggestraat 8",
    "sg:city":"Ingelmunster",
    "sg:classifiers":[
        {
            "category":"Manufacturing",
            "subcategory":"Printing",
            "type":"Manufacturing & Wholesale Goods"
        }
    ],
    "sg:phone":"+32 51 31 53 53",
    "sg:postcode":"8770",
    "sg:province":"West-Vlaanderen",
    "sg:tags":[
        "textile",
        "-"
    ],
    "wof:name":"S.p.i.n",
    "wof:placetype":"venue"
},
  "geometry": {"coordinates":[3.2538020611,50.9208068848],"type":"Point"}
}