{
  "type": "Feature",
  "properties": {
    "iso:country":"BE",
    "sg:address":"Grensstraat 7",
    "sg:city":"Ruiselede",
    "sg:orig_category":"Producteurs de fruits. Eleveurs de bovins. Eleveurs and marchands de porcs",
    "sg:phone":"+32 51 68 86 94",
    "sg:postcode":"8755",
    "sg:province":"West-Vlaanderen",
    "wof:name":"Jose Martens",
    "wof:placetype":"venue"
},
  "geometry": {"coordinates":[3.4327778816,51.0475730896],"type":"Point"}
}