{
  "type": "Feature",
  "properties": {
    "addr:full":"Avenue De L'etang 2 Wavre Brabant Wallon 1300",
    "addr:housenumber":"2;1300",
    "addr:street":"Avenue De L'Etang",
    "iso:country":"BE",
    "sg:address":"Avenue De L'etang 2",
    "sg:city":"Wavre",
    "sg:classifiers":[
        {
            "category":"Health Services",
            "subcategory":"Doctor",
            "type":"Services"
        }
    ],
    "sg:phone":"+32 10 22 40 15",
    "sg:postcode":"1300",
    "sg:province":"Brabant Wallon",
    "sg:tags":[
        "medicinephysicians",
        "surgeon"
    ],
    "wof:name":"Absil Bruno",
    "wof:placetype":"venue"
},
  "geometry": {"coordinates":[4.6219520569,50.7096405029],"type":"Point"}
}