{
  "type": "Feature",
  "properties": {
    "iso:country":"BE",
    "sg:address":"Rue De La Montagne 144",
    "sg:city":"Mouscron (herseaux)",
    "sg:classifiers":[
        {
            "category":"Insurance",
            "subcategory":"Insurance Agent",
            "type":"Services"
        }
    ],
    "sg:phone":"+32 56 33 00 56",
    "sg:postcode":"7712",
    "sg:province":"Hainaut",
    "sg:tags":[
        "broker"
    ],
    "wof:name":"Ait O",
    "wof:placetype":"venue"
},
  "geometry": {"coordinates":[3.2307560444,50.7358436584],"type":"Point"}
}