{
  "type": "Feature",
  "properties": {
    "addr:full":"Mont 21 Theux Li\u00e8ge 4910",
    "addr:housenumber":"21",
    "addr:postcode":"4910",
    "addr:street":"Mont",
    "iso:country":"BE",
    "sg:address":"Mont 21",
    "sg:city":"Theux",
    "sg:orig_category":"Woningbouw",
    "sg:phone":"+32 87 54 22 46",
    "sg:postcode":"4910",
    "sg:province":"Li\u00e8ge",
    "wof:name":"Entreprises J-m Hennen",
    "wof:placetype":"venue"
},
  "geometry": {"coordinates":[5.7910108566,50.5333251953],"type":"Point"}
}