{
  "type": "Feature",
  "properties": {
    "addr:full":"Kaaskerkestraat 49 Diksmuide West-Vlaanderen 8600",
    "addr:housenumber":"49",
    "addr:postcode":"8600",
    "addr:street":"Kaaskerkestraat",
    "iso:country":"BE",
    "sg:address":"Kaaskerkestraat 49",
    "sg:city":"Diksmuide",
    "sg:classifiers":[
        {
            "category":"Autos & Motor Vehicles",
            "subcategory":"Automobile Sales",
            "type":"Retail Goods"
        }
    ],
    "sg:phone":"+32 51 50 00 83",
    "sg:postcode":"8600",
    "sg:province":"West-Vlaanderen",
    "sg:tags":[
        "car",
        "used",
        "-"
    ],
    "wof:name":"Traisnel Garage",
    "wof:placetype":"venue"
},
  "geometry": {"coordinates":[2.8304400444,51.0372085571],"type":"Point"}
}