{
  "type": "Feature",
  "properties": {
    "iso:country":"BE",
    "sg:address":"Weverstraat 2",
    "sg:city":"Meeuwen-gruitrode (ellikom)",
    "sg:classifiers":[
        {
            "category":"Shopping",
            "subcategory":"Clothing, Apparel, & Fashions",
            "type":"Retail Goods"
        }
    ],
    "sg:phone":"+32 11 63 42 45",
    "sg:postcode":"3670",
    "sg:province":"Limburg",
    "sg:tags":[
        "clothing",
        "-",
        "gentleman"
    ],
    "wof:name":"Simons 4",
    "wof:placetype":"venue"
},
  "geometry": {"coordinates":[5.5205497742,51.0963516235],"type":"Point"}
}