{
  "type": "Feature",
  "properties": {
    "addr:full":"Torhoutse Steenweg 132 Brugge West-Vlaanderen 8200",
    "addr:housenumber":"132",
    "addr:postcode":"8200",
    "addr:street":"Torhoutse Steenweg",
    "iso:country":"BE",
    "sg:address":"Torhoutse Steenweg 132",
    "sg:city":"Brugge",
    "sg:orig_category":"S\u00e9curit\u00e9 sociale",
    "sg:phone":"+32 50 40 60 80",
    "sg:postcode":"8200",
    "sg:province":"West-Vlaanderen",
    "wof:name":"Vlaams Neutraal Ziekenf.",
    "wof:placetype":"venue"
},
  "geometry": {"coordinates":[3.2027449608,51.1989173889],"type":"Point"}
}