{
  "type": "Feature",
  "properties": {
    "addr:full":"Laekenveld 12 Wemmel Vlaams-Brabant 1780",
    "addr:housenumber":"12",
    "addr:postcode":"1780",
    "addr:street":"Laekenveld;Vlaams-Brabant",
    "iso:country":"BE",
    "sg:address":"Laekenveld 12",
    "sg:city":"Wemmel",
    "sg:classifiers":[
        {
            "category":"Professional",
            "subcategory":"Management & Consulting",
            "type":"Services"
        }
    ],
    "sg:phone":"+32 2 426 94 82",
    "sg:postcode":"1780",
    "sg:province":"Vlaams-Brabant",
    "sg:tags":[
        "consultant",
        "promotion",
        "-",
        "sale"
    ],
    "wof:name":"Me Too Sprl",
    "wof:placetype":"venue"
},
  "geometry": {"coordinates":[4.3236761093,50.9026374817],"type":"Point"}
}