{
  "type": "Feature",
  "properties": {
    "iso:country":"BE",
    "sg:address":"Diestsesteenweg 20-22",
    "sg:city":"Pellenberg",
    "sg:classifiers":[
        {
            "category":"Home & Garden",
            "subcategory":"Carpets & Floor Coverings",
            "type":"Retail Goods"
        }
    ],
    "sg:phone":"+32 16 25 22 60",
    "sg:postcode":"3212",
    "sg:province":"Vlaams-Brabant",
    "sg:tags":[
        "carpeting"
    ],
    "wof:name":"Gulisano B.v.b.a.",
    "wof:placetype":"venue"
},
  "geometry": {"coordinates":[4.7903199196,50.8912582397],"type":"Point"}
}