{
  "type": "Feature",
  "properties": {
    "iso:country":"BE",
    "sg:address":"Geistingen 7",
    "sg:city":"Kinrooi",
    "sg:classifiers":[
        {
            "category":"Cafe",
            "type":"Food & Drink"
        }
    ],
    "sg:phone":"+32 89 56 83 52",
    "sg:postcode":"3640",
    "sg:province":"Limburg",
    "sg:tags":[
        "caf\u00e9s"
    ],
    "wof:name":"David Craeghs",
    "wof:placetype":"venue"
},
  "geometry": {"coordinates":[5.8052821159,51.1315917969],"type":"Point"}
}