{
  "type": "Feature",
  "properties": {
    "addr:full":"18 Rue Bodenbroek 1000 Bruxelles 18",
    "addr:housenumber":"18",
    "addr:postcode":"1000;18",
    "addr:street":"Rue Bodenbroek",
    "iso:country":"BE",
    "sg:address":"18",
    "sg:city":"Rue Bodenbroek 1000 Bruxelles",
    "sg:classifiers":[
        {
            "category":"Travel",
            "subcategory":"Hotels & Motels",
            "type":"Entertainment"
        }
    ],
    "sg:phone":"+32 2 512 87 51",
    "sg:postcode":"18",
    "sg:tags":[
        "hotels",
        "business",
        "restaurant"
    ],
    "wof:name":"Lecailler Du Palais Royal Sa",
    "wof:placetype":"venue"
},
  "geometry": {"coordinates":[4.356470108,50.8407058716],"type":"Point"}
}