{
  "type": "Feature",
  "properties": {
    "addr:full":"Kasteelstraat 3 Zonnebeke (geluveld) West-Vlaanderen 8980",
    "addr:housenumber":"3",
    "addr:postcode":"8980",
    "addr:street":"Kasteelstraat",
    "iso:country":"BE",
    "sg:address":"Kasteelstraat 3",
    "sg:city":"Zonnebeke (geluveld)",
    "sg:classifiers":[
        {
            "category":"Building & Trades",
            "subcategory":"Construction",
            "type":"Services"
        }
    ],
    "sg:phone":"+32 57 46 73 43",
    "sg:postcode":"8980",
    "sg:province":"West-Vlaanderen",
    "sg:tags":[
        "stair"
    ],
    "wof:name":"Delmar Prefabtrappen Nv",
    "wof:placetype":"venue"
},
  "geometry": {"coordinates":[2.9549179077,50.8482933044],"type":"Point"}
}