{
  "type": "Feature",
  "properties": {
    "iso:country":"BE",
    "sg:address":"Otegemstraat 42",
    "sg:city":"Zwevegem",
    "sg:orig_category":"Pharmaciens",
    "sg:phone":"+32 56 75 52 74",
    "sg:postcode":"8550",
    "sg:province":"West-Vlaanderen",
    "wof:name":"Apotheek Windels",
    "wof:placetype":"venue"
},
  "geometry": {"coordinates":[3.3360219002,50.8126564026],"type":"Point"}
}