{
  "type": "Feature",
  "properties": {
    "iso:country":"BE",
    "sg:address":"Rue Emile Carlier 112",
    "sg:city":"Bernissart",
    "sg:orig_category":"Kapsalons",
    "sg:phone":"+32 69 56 00 34",
    "sg:postcode":"7321",
    "sg:province":"Hainaut",
    "wof:name":"Coiffure Jose",
    "wof:placetype":"venue"
},
  "geometry": {"coordinates":[3.6748840809,50.4944038391],"type":"Point"}
}