{
  "type": "Feature",
  "properties": {
    "addr:full":"Hertestraat 8 Sint-niklaas Oost-Vlaanderen 9100",
    "addr:housenumber":"8",
    "addr:postcode":"9100",
    "addr:street":"Hertestraat",
    "iso:country":"BE",
    "sg:address":"Hertestraat 8",
    "sg:city":"Sint-niklaas",
    "sg:orig_category":"Alternatieve geneeskunde",
    "sg:phone":"+32 3 766 14 13",
    "sg:postcode":"9100",
    "sg:province":"Oost-Vlaanderen",
    "wof:name":"Maruschka Van Puymbroeck",
    "wof:placetype":"venue"
},
  "geometry": {"coordinates":[4.1618819237,51.1557807922],"type":"Point"}
}