{
  "type": "Feature",
  "properties": {
    "addr:full":"Rue De L'industrie 21 Fl\u00e9malle Li\u00e8ge 4400",
    "addr:housenumber":"21",
    "addr:postcode":"4400",
    "addr:street":"Rue De L'Industrie",
    "iso:country":"BE",
    "sg:address":"Rue De L'industrie 21",
    "sg:city":"Fl\u00e9malle",
    "sg:classifiers":[
        {
            "category":"Building & Trades",
            "subcategory":"Construction",
            "type":"Services"
        }
    ],
    "sg:phone":"+32 4 233 23 22",
    "sg:postcode":"4400",
    "sg:province":"Li\u00e8ge",
    "sg:tags":[
        "stucco",
        "contractor"
    ],
    "wof:name":"Magain Dominique",
    "wof:placetype":"venue"
},
  "geometry": {"coordinates":[5.458302021,50.5935516357],"type":"Point"}
}