{
  "type": "Feature",
  "properties": {
    "iso:country":"BE",
    "sg:address":"Avenue De La Reine 33",
    "sg:city":"Schaarbeek/schaerbeek",
    "sg:orig_category":"M\u00e9decins and sp\u00e9cialistes",
    "sg:phone":"+32 2 242 52 43",
    "sg:postcode":"1030",
    "sg:province":"Bruxelles-Capitale",
    "wof:name":"Yolande Drisch",
    "wof:placetype":"venue"
},
  "geometry": {"coordinates":[4.3652281761,50.8651008606],"type":"Point"}
}