{
  "type": "Feature",
  "properties": {
    "addr:full":"Daillylaan 214 Schaarbeek/schaerbeek Bruxelles-Capitale 1030",
    "addr:housenumber":"214",
    "addr:postcode":"1030",
    "addr:street":"Daillylaan",
    "iso:country":"BE",
    "sg:address":"Daillylaan 214",
    "sg:city":"Schaarbeek/schaerbeek",
    "sg:orig_category":"Autoverhuur Herstellingen and onderhoud van auto's",
    "sg:phone":"+32 2 736 39 44",
    "sg:postcode":"1030",
    "sg:province":"Bruxelles-Capitale",
    "wof:name":"Garage De Bruxelles",
    "wof:placetype":"venue"
},
  "geometry": {"coordinates":[4.3874368668,50.8528022766],"type":"Point"}
}