{
  "type": "Feature",
  "properties": {
    "iso:country":"BE",
    "sg:address":"Quai Godefroid Kurth 66",
    "sg:city":"Li\u00c8ge",
    "sg:orig_category":"Artsen and specialisten",
    "sg:phone":"+32 4 344 04 28",
    "sg:postcode":"4020",
    "sg:province":"Li\u00e8ge",
    "wof:name":"Nacera Layachi",
    "wof:placetype":"venue"
},
  "geometry": {"coordinates":[5.5935230255,50.6469154358],"type":"Point"}
}