{
  "type": "Feature",
  "properties": {
    "iso:country":"BE",
    "sg:address":"Vital De Costerstraat 42",
    "sg:city":"Leuven",
    "sg:orig_category":"Diverse kredietdiensten",
    "sg:postcode":"3000",
    "sg:province":"Vlaams-Brabant",
    "wof:name":"Bancontact-mister Cash",
    "wof:placetype":"venue"
},
  "geometry": {"coordinates":[4.7046442032,50.881401062],"type":"Point"}
}