{
  "type": "Feature",
  "properties": {
    "iso:country":"BE",
    "sg:address":"Rooilandgaarde 6",
    "sg:city":"Sint-pieters-woluwe/woluwe-saint-pierre",
    "sg:orig_category":"Immobili\u00ebnkantoren",
    "sg:phone":"+32 2 772 80 53",
    "sg:postcode":"1150",
    "sg:province":"Bruxelles-Capitale",
    "wof:name":"C.g.i.s.- Sylvie Rubinstein",
    "wof:placetype":"venue"
},
  "geometry": {"coordinates":[4.4667010307,50.8331832886],"type":"Point"}
}