{
  "type": "Feature",
  "properties": {
    "iso:country":"BE",
    "sg:address":"Ch\u00c9e Gabrielle Richet 199",
    "sg:city":"Lessines",
    "sg:orig_category":"Pi\u00e8ces and accessoires de v\u00e9hicules automobiles D\u00e9taillants en pi\u00e8ces and accessoires de voitures",
    "sg:phone":"+32 68 33 34 87",
    "sg:postcode":"7860",
    "sg:province":"Hainaut",
    "wof:name":"Cars Technique Auto",
    "wof:placetype":"venue"
},
  "geometry": {"coordinates":[3.8487250805,50.6986999512],"type":"Point"}
}