{
  "type": "Feature",
  "properties": {
    "iso:country":"BE",
    "sg:address":"Binnenveld 13",
    "sg:city":"Laakdal",
    "sg:orig_category":"Bouwmaterialen Gh Dakwerken Installatie van houten of kunststof schrijnwerk",
    "sg:phone":"+32 14 84 02 73",
    "sg:postcode":"2431",
    "sg:province":"Antwerpen",
    "wof:name":"Dakwerken Ronny Govarts",
    "wof:placetype":"venue"
},
  "geometry": {"coordinates":[4.978828907,51.0712547302],"type":"Point"}
}