{
  "type": "Feature",
  "properties": {
    "iso:country":"BE",
    "sg:address":"Merchtemsesteenweg 38",
    "sg:city":"Meise",
    "sg:orig_category":"Slagers",
    "sg:phone":"+32 2 269 09 44",
    "sg:postcode":"1861",
    "sg:province":"Vlaams-Brabant",
    "wof:name":"Paul Clijmans",
    "wof:placetype":"venue"
},
  "geometry": {"coordinates":[4.3044629097,50.9513053894],"type":"Point"}
}