{
  "type": "Feature",
  "properties": {
    "iso:country":"BE",
    "sg:address":"Kasteelhoek 31",
    "sg:city":"Beernem",
    "sg:orig_category":"Artistes ind\u00e9pendants",
    "sg:phone":"+32 50 79 15 15",
    "sg:postcode":"8730",
    "sg:province":"West-Vlaanderen",
    "wof:name":"P. Teerlinck",
    "wof:placetype":"venue"
},
  "geometry": {"coordinates":[3.305918932,51.1497344971],"type":"Point"}
}