{
  "type": "Feature",
  "properties": {
    "addr:full":"Rue Du Paradis 45 Ans (xhendremael) Li\u00e8ge 4432",
    "addr:housenumber":"45",
    "addr:postcode":"4432",
    "addr:street":"Rue Du Paradis;Xhendremael",
    "iso:country":"BE",
    "sg:address":"Rue Du Paradis 45",
    "sg:city":"Ans (xhendremael)",
    "sg:classifiers":[
        {
            "category":"Professional",
            "subcategory":"Testing Lab",
            "type":"Services"
        }
    ],
    "sg:phone":"+32 4 257 45 44",
    "sg:postcode":"4432",
    "sg:province":"Li\u00e8ge",
    "sg:tags":[
        "chemist"
    ],
    "wof:name":"Clarinval",
    "wof:placetype":"venue"
},
  "geometry": {"coordinates":[5.4851841927,50.7028694153],"type":"Point"}
}