{
  "type": "Feature",
  "properties": {
    "iso:country":"BE",
    "sg:address":"Hertogenweg 14",
    "sg:city":"Tervuren",
    "sg:classifiers":[
        {
            "category":"Banks & Credit Unions",
            "subcategory":"Investment Brokerage",
            "type":"Services"
        }
    ],
    "sg:phone":"+32 2 767 84 14",
    "sg:postcode":"3080",
    "sg:province":"Vlaams-Brabant",
    "sg:tags":[
        "auditor"
    ],
    "wof:name":"Blackwell M",
    "wof:placetype":"venue"
},
  "geometry": {"coordinates":[4.5029740334,50.8267326355],"type":"Point"}
}