{
  "type": "Feature",
  "properties": {
    "addr:full":"Houtlandstraat 3 Assenede Oost-Vlaanderen 9960",
    "addr:housenumber":"3",
    "addr:postcode":"9960",
    "addr:street":"Houtlandstraat",
    "iso:country":"BE",
    "sg:address":"Houtlandstraat 3",
    "sg:city":"Assenede",
    "sg:classifiers":[
        {
            "category":"Arena",
            "subcategory":"Sports Club",
            "type":"Entertainment"
        }
    ],
    "sg:phone":"+32 9 344 04 81",
    "sg:postcode":"9960",
    "sg:province":"Oost-Vlaanderen",
    "sg:tags":[
        "de"
    ],
    "wof:name":"V.c. Assenede",
    "wof:placetype":"venue"
},
  "geometry": {"coordinates":[3.7580940723,51.2123908997],"type":"Point"}
}