{
  "type": "Feature",
  "properties": {
    "addr:full":"Avenue De Maire 134 Tournai Hainaut 7500",
    "addr:housenumber":"134",
    "addr:postcode":"7500",
    "addr:street":"Avenue De Maire",
    "iso:country":"BE",
    "sg:address":"Avenue De Maire 134",
    "sg:city":"Tournai",
    "sg:classifiers":[
        {
            "category":"Sports & Exercise",
            "subcategory":"Sports Center",
            "type":"Entertainment"
        }
    ],
    "sg:phone":"+32 69 23 28 08",
    "sg:postcode":"7500",
    "sg:province":"Hainaut",
    "sg:tags":[
        "de",
        "fitness"
    ],
    "wof:name":"Espace Forme",
    "wof:placetype":"venue"
},
  "geometry": {"coordinates":[3.3735809326,50.6163597107],"type":"Point"}
}