{
  "type": "Feature",
  "properties": {
    "addr:full":"Emiel Verhaerenlaan 69 Gent Oost-Vlaanderen 9050",
    "addr:housenumber":"69",
    "addr:postcode":"9050",
    "addr:street":"Emiel Verhaerenlaan;Oost-Vlaanderen",
    "iso:country":"BE",
    "sg:address":"Emiel Verhaerenlaan 69",
    "sg:city":"Gent",
    "sg:orig_category":"M\u00e9decines alternatives",
    "sg:phone":"+32 9 230 64 89",
    "sg:postcode":"9050",
    "sg:province":"Oost-Vlaanderen",
    "wof:name":"S. Segers",
    "wof:placetype":"venue"
},
  "geometry": {"coordinates":[3.7658939362,51.0340080261],"type":"Point"}
}