{
  "type": "Feature",
  "properties": {
    "iso:country":"BE",
    "sg:address":"Vennestraat 140",
    "sg:city":"Genk",
    "sg:orig_category":"Verplichte sociale verzekeringen",
    "sg:phone":"+32 89 35 25 76",
    "sg:postcode":"3600",
    "sg:province":"Limburg",
    "wof:name":"De Voorzorg",
    "wof:placetype":"venue"
},
  "geometry": {"coordinates":[5.490196228,50.9779663086],"type":"Point"}
}