{
  "type": "Feature",
  "properties": {
    "iso:country":"BE",
    "sg:address":"Berkhoevelaan 6",
    "sg:city":"Duffel",
    "sg:orig_category":"M\u00e9decins and sp\u00e9cialistes",
    "sg:phone":"+32 15 31 12 39",
    "sg:postcode":"2570",
    "sg:province":"Antwerpen",
    "wof:name":"D. Van Winkel",
    "wof:placetype":"venue"
},
  "geometry": {"coordinates":[4.5116848946,51.089931488],"type":"Point"}
}