{
  "type": "Feature",
  "properties": {
    "iso:country":"BE",
    "sg:address":"Oude Baan 1",
    "sg:city":"Bonheiden",
    "sg:orig_category":"Mat\u00e9riel m\u00e9dical and orthop\u00e9dique and proth\u00e8ses Fab",
    "sg:phone":"+32 15 55 41 59",
    "sg:postcode":"2820",
    "sg:province":"Antwerpen",
    "wof:name":"Labo Bosmans",
    "wof:placetype":"venue"
},
  "geometry": {"coordinates":[4.5267901421,51.0339508057],"type":"Point"}
}