{
  "type": "Feature",
  "properties": {
    "iso:country":"BE",
    "sg:address":"Camille D'hav\u00e9straat 43",
    "sg:city":"Gent (sint-amandsberg)",
    "sg:classifiers":[
        {
            "category":"Banks & Credit Unions",
            "subcategory":"Investment Brokerage",
            "type":"Services"
        }
    ],
    "sg:phone":"+32 9 238 35 76",
    "sg:postcode":"9040",
    "sg:province":"Oost-Vlaanderen",
    "sg:tags":[
        "auditor"
    ],
    "wof:name":"Blommaert J",
    "wof:placetype":"venue"
},
  "geometry": {"coordinates":[3.7825300694,51.0706977844],"type":"Point"}
}