{
  "type": "Feature",
  "properties": {
    "iso:country":"BE",
    "sg:address":"Tweebruggenstraat 2",
    "sg:city":"Oostende",
    "sg:orig_category":"Instituts pour enfants en difficult\u00e9. Orphelinats",
    "sg:phone":"+32 59 32 01 67",
    "sg:postcode":"8400",
    "sg:province":"West-Vlaanderen",
    "wof:name":"Vrienden De Bolle",
    "wof:placetype":"venue"
},
  "geometry": {"coordinates":[2.9396259785,51.2212028503],"type":"Point"}
}