{
  "type": "Feature",
  "properties": {
    "iso:country":"BE",
    "sg:address":"Vuilstraat 5",
    "sg:city":"Geraardsbergen",
    "sg:classifiers":[
        {
            "category":"Cafe",
            "type":"Food & Drink"
        }
    ],
    "sg:phone":"+32 54 50 20 31",
    "sg:postcode":"9506",
    "sg:province":"Oost-Vlaanderen",
    "sg:tags":[
        "caf\u00e9s"
    ],
    "wof:name":"Caf\u00c9 't Buitenbeentje",
    "wof:placetype":"venue"
},
  "geometry": {"coordinates":[3.9175620079,50.815322876],"type":"Point"}
}