{
  "type": "Feature",
  "properties": {
    "iso:country":"BE",
    "sg:address":"Rue Georges Leclercq 78",
    "sg:city":"Bruxelles (forest)",
    "sg:classifiers":[
        {
            "category":"Professional",
            "subcategory":"Accounting & Tax Preparation",
            "type":"Services"
        }
    ],
    "sg:phone":"+32 2 347 26 45",
    "sg:postcode":"1190",
    "sg:province":"Bruxelles-Capitale",
    "sg:tags":[
        "bookkeeper"
    ],
    "wof:name":"El Mouch M",
    "wof:placetype":"venue"
},
  "geometry": {"coordinates":[4.3238492012,50.821849823],"type":"Point"}
}