{
  "type": "Feature",
  "properties": {
    "addr:full":"Boomstraat 90 Bornem Antwerpen 2880",
    "addr:housenumber":"90",
    "addr:postcode":"2880",
    "addr:street":"Boomstraat",
    "iso:country":"BE",
    "sg:address":"Boomstraat 90",
    "sg:city":"Bornem",
    "sg:classifiers":[
        {
            "category":"Shopping",
            "subcategory":"Beauty & Cosmetics",
            "type":"Retail Goods"
        }
    ],
    "sg:phone":"+32 3 889 51 30",
    "sg:postcode":"2880",
    "sg:province":"Antwerpen",
    "sg:tags":[
        "-",
        "perfumery"
    ],
    "wof:name":"Verhofste",
    "wof:placetype":"venue"
},
  "geometry": {"coordinates":[4.2328357697,51.0969047546],"type":"Point"}
}