{
  "type": "Feature",
  "properties": {
    "addr:full":"Rue De Charleroi 18 Nivelles Brabant Wallon 1400",
    "addr:housenumber":"18",
    "addr:postcode":"1400",
    "addr:street":"Rue De Charleroi",
    "iso:country":"BE",
    "sg:address":"Rue De Charleroi 18",
    "sg:city":"Nivelles",
    "sg:classifiers":[
        {
            "category":"Building & Trades",
            "subcategory":"Landscaping Services",
            "type":"Services"
        }
    ],
    "sg:phone":"+32 67 21 66 99",
    "sg:postcode":"1400",
    "sg:province":"Brabant Wallon",
    "sg:tags":[
        "gardening",
        "garden",
        "maintenance"
    ],
    "wof:name":"De Montpellier D'annevoie H",
    "wof:placetype":"venue"
},
  "geometry": {"coordinates":[4.326939106,50.5961647034],"type":"Point"}
}