{
  "type": "Feature",
  "properties": {
    "addr:full":"Tuinlaan 34 Sint-niklaas (belsele) Oost-Vlaanderen 9111",
    "addr:housenumber":"34",
    "addr:postcode":"9111",
    "addr:street":"Tuinlaan",
    "iso:country":"BE",
    "sg:address":"Tuinlaan 34",
    "sg:city":"Sint-niklaas (belsele)",
    "sg:classifiers":[
        {
            "category":"Airport",
            "subcategory":"International",
            "type":"Transportation"
        }
    ],
    "sg:phone":"+32 3 722 09 00",
    "sg:postcode":"9111",
    "sg:province":"Oost-Vlaanderen",
    "sg:tags":[
        "-",
        "transport"
    ],
    "wof:name":"C.i.t. Transport Nv",
    "wof:placetype":"venue"
},
  "geometry": {"coordinates":[4.1064548492,51.1510391235],"type":"Point"}
}