{
  "type": "Feature",
  "properties": {
    "addr:full":"Kerkstraat 90 Vrasene Oost-Vlaanderen 9120",
    "addr:housenumber":"90",
    "addr:postcode":"9120",
    "addr:street":"Kerkstraat;Oost-Vlaanderen",
    "iso:country":"BE",
    "sg:address":"Kerkstraat 90",
    "sg:city":"Vrasene",
    "sg:classifiers":[
        {
            "category":"Manufacturing",
            "subcategory":"Motor Vehicles & Parts",
            "type":"Manufacturing & Wholesale Goods"
        }
    ],
    "sg:phone":"+32 3 755 09 45",
    "sg:postcode":"9120",
    "sg:province":"Oost-Vlaanderen",
    "sg:tags":[
        "large",
        "industry",
        "construction",
        "agriculture",
        "tyre"
    ],
    "wof:name":"Atb Nv",
    "wof:placetype":"venue"
},
  "geometry": {"coordinates":[4.1950788498,51.2117462158],"type":"Point"}
}