{
  "type": "Feature",
  "properties": {
    "addr:full":"Orchidee\u00cbnlaan 45 Hamont-achel Limburg 3930",
    "addr:housenumber":"45",
    "addr:postcode":"3930",
    "addr:street":"Orchideee\u0308Nlaan",
    "iso:country":"BE",
    "sg:address":"Orchidee\u00cbnlaan 45",
    "sg:city":"Hamont-achel",
    "sg:orig_category":"Muziekinstrumenten",
    "sg:phone":"+32 11 64 21 93",
    "sg:postcode":"3930",
    "sg:province":"Limburg",
    "wof:name":"Piano Atelier Willy Peters",
    "wof:placetype":"venue"
},
  "geometry": {"coordinates":[5.493144989,51.2541160583],"type":"Point"}
}