{
  "type": "Feature",
  "properties": {
    "iso:country":"BE",
    "sg:address":"Paardestraat 40",
    "sg:city":"Bornem",
    "sg:orig_category":"Diverse voedingsmiddelen Gh",
    "sg:phone":"+32 52 34 33 68",
    "sg:postcode":"2880",
    "sg:province":"Antwerpen",
    "wof:name":"Palinghandel Borremans",
    "wof:placetype":"venue"
},
  "geometry": {"coordinates":[4.192305088,51.0648269653],"type":"Point"}
}