{
  "type": "Feature",
  "properties": {
    "iso:country":"BE",
    "sg:address":"Chauss\u00e9e De Bascoup 115",
    "sg:city":"Anderlues",
    "sg:classifiers":[
        {
            "category":"Autos & Motor Vehicles",
            "subcategory":"Automobile Sales",
            "type":"Retail Goods"
        }
    ],
    "sg:phone":"+32 71 54 82 71",
    "sg:postcode":"6150",
    "sg:province":"Hainaut",
    "sg:tags":[
        "car",
        "used",
        "-"
    ],
    "wof:name":"Auto Anderlues Sa",
    "wof:placetype":"venue"
},
  "geometry": {"coordinates":[4.2827010155,50.4136695862],"type":"Point"}
}