{
  "type": "Feature",
  "properties": {
    "iso:country":"BE",
    "sg:address":"Rue De Bertaimont 1",
    "sg:city":"Mons",
    "sg:orig_category":"Cr\u00e8ches and garderies d'enfants",
    "sg:phone":"+32 65 36 17 54",
    "sg:postcode":"7000",
    "sg:province":"Hainaut",
    "wof:name":"Gard\u00c9rie Ape",
    "wof:placetype":"venue"
},
  "geometry": {"coordinates":[3.949311018,50.4491386414],"type":"Point"}
}