{
  "type": "Feature",
  "properties": {
    "addr:full":"Alfons Braeckmanlaan 202 Gent (sint-amandsberg) Oost-Vlaanderen 9040",
    "addr:housenumber":"202",
    "addr:postcode":"9040",
    "addr:street":"Braeckmanlaan",
    "iso:country":"BE",
    "sg:address":"Alfons Braeckmanlaan 202",
    "sg:city":"Gent (sint-amandsberg)",
    "sg:classifiers":[
        {
            "category":"Professional",
            "subcategory":"Testing Lab",
            "type":"Services"
        }
    ],
    "sg:phone":"+32 9 228 43 05",
    "sg:postcode":"9040",
    "sg:province":"Oost-Vlaanderen",
    "sg:tags":[
        "chemist"
    ],
    "wof:name":"Haghedooren V",
    "wof:placetype":"venue"
},
  "geometry": {"coordinates":[3.7752969265,51.064666748],"type":"Point"}
}