{
  "type": "Feature",
  "properties": {
    "addr:full":"Rue De Maubeuge 170 Erquelinnes Hainaut 6560",
    "addr:housenumber":"170",
    "addr:postcode":"6560",
    "addr:street":"Rue De Maubeuge",
    "iso:country":"BE",
    "sg:address":"Rue De Maubeuge 170",
    "sg:city":"Erquelinnes",
    "sg:classifiers":[
        {
            "category":"Social Services",
            "type":"Services"
        }
    ],
    "sg:phone":"+32 71 55 56 55",
    "sg:postcode":"6560",
    "sg:province":"Hainaut",
    "wof:name":"I M P Le Brasier",
    "wof:placetype":"venue"
},
  "geometry": {"coordinates":[4.1094050407,50.3077392578],"type":"Point"}
}