{
  "type": "Feature",
  "properties": {
    "iso:country":"BE",
    "sg:address":"Fortstraat 7",
    "sg:city":"Berlare (overmere)",
    "sg:classifiers":[
        {
            "category":"Personal",
            "subcategory":"Beauty Salon",
            "type":"Services"
        }
    ],
    "sg:phone":"+32 9 367 62 03",
    "sg:postcode":"9290",
    "sg:province":"Oost-Vlaanderen",
    "wof:name":"Manuelle Parfumerie",
    "wof:placetype":"venue"
},
  "geometry": {"coordinates":[3.953742981,51.046672821],"type":"Point"}
}