{
  "type": "Feature",
  "properties": {
    "addr:full":"Tjampenstraat 5 Anzegem West-Vlaanderen 8570",
    "addr:housenumber":"5",
    "addr:postcode":"8570",
    "addr:street":"Tjampenstraat",
    "iso:country":"BE",
    "sg:address":"Tjampenstraat 5",
    "sg:city":"Anzegem",
    "sg:orig_category":"Eleveurs and marchands de porcs",
    "sg:phone":"+32 56 68 75 83",
    "sg:postcode":"8570",
    "sg:province":"West-Vlaanderen",
    "wof:name":"Paul Vererfven",
    "wof:placetype":"venue"
},
  "geometry": {"coordinates":[3.4457809925,50.8216705322],"type":"Point"}
}