{
  "type": "Feature",
  "properties": {
    "iso:country":"BE",
    "sg:address":"Rue Andr\u00e9 Masquelier 7-9",
    "sg:city":"Mons",
    "sg:classifiers":[
        {
            "category":"Shopping",
            "subcategory":"Computers & Home Electronics",
            "type":"Retail Goods"
        }
    ],
    "sg:phone":"+32 65 33 70 62",
    "sg:postcode":"7000",
    "sg:province":"Hainaut",
    "sg:tags":[
        "-",
        "television",
        "radio"
    ],
    "wof:name":"Meuret",
    "wof:placetype":"venue"
},
  "geometry": {"coordinates":[3.9443280697,50.4515838623],"type":"Point"}
}