{
  "type": "Feature",
  "properties": {
    "addr:full":"Graaf D'ursellaan 44 Knokke-heist (heist-aan-zee) West-Vlaanderen 8301",
    "addr:housenumber":"44",
    "addr:postcode":"8301",
    "addr:street":"Graaf D'Ursellaan",
    "iso:country":"BE",
    "sg:address":"Graaf D'ursellaan 44",
    "sg:city":"Knokke-heist (heist-aan-zee)",
    "sg:classifiers":[
        {
            "category":"Shopping",
            "subcategory":"Optician",
            "type":"Retail Goods"
        }
    ],
    "sg:phone":"+32 50 51 93 52",
    "sg:postcode":"8301",
    "sg:province":"West-Vlaanderen",
    "sg:tags":[
        "-"
    ],
    "wof:name":"Snauwaert Optics",
    "wof:placetype":"venue"
},
  "geometry": {"coordinates":[3.2449319363,51.3404426575],"type":"Point"}
}