{
  "type": "Feature",
  "properties": {
    "addr:full":"Avenue De Merode 137 Rixensart Brabant Wallon 1330",
    "addr:housenumber":"137",
    "addr:postcode":"1330",
    "addr:street":"Avenue De Merode;Wallon",
    "iso:country":"BE",
    "sg:address":"Avenue De Merode 137",
    "sg:city":"Rixensart",
    "sg:classifiers":[
        {
            "category":"Health Services",
            "subcategory":"Health Practitioner",
            "type":"Services"
        }
    ],
    "sg:phone":"+32 2 652 20 26",
    "sg:postcode":"1330",
    "sg:province":"Brabant Wallon",
    "sg:tags":[
        "physiotherapist"
    ],
    "wof:name":"Thirion Anne",
    "wof:placetype":"venue"
},
  "geometry": {"coordinates":[4.5165839195,50.7117118835],"type":"Point"}
}