{
  "type": "Feature",
  "properties": {
    "iso:country":"BE",
    "sg:address":"Stelensedijk 4",
    "sg:city":"Geel",
    "sg:orig_category":"Eleveurs d'animaux divers",
    "sg:phone":"+32 14 86 77 45",
    "sg:postcode":"2440",
    "sg:province":"Antwerpen",
    "wof:name":"De Dikke Dar",
    "wof:placetype":"venue"
},
  "geometry": {"coordinates":[4.987195015,51.1569633484],"type":"Point"}
}