{
  "type": "Feature",
  "properties": {
    "addr:full":"Comm. Edm. Ameyestraat 1ba Deerlijk West-Vlaanderen 8540",
    "addr:postcode":"8540",
    "addr:street":"Ameyestraat",
    "iso:country":"BE",
    "sg:address":"Comm. Edm. Ameyestraat 1ba",
    "sg:city":"Deerlijk",
    "sg:orig_category":"Meubelzaken, woning- and keukeninrichting",
    "sg:phone":"+32 56 72 59 12",
    "sg:postcode":"8540",
    "sg:province":"West-Vlaanderen",
    "wof:name":"Kris Vandenbogaerde",
    "wof:placetype":"venue"
},
  "geometry": {"coordinates":[3.3538069725,50.8535995483],"type":"Point"}
}