{
  "type": "Feature",
  "properties": {
    "addr:full":"Rue De Gedinne 42 Gedinne (sart-custinne) Namur 5575",
    "addr:housenumber":"42",
    "addr:postcode":"5575",
    "addr:street":"Rue De Gedinne",
    "iso:country":"BE",
    "sg:address":"Rue De Gedinne 42",
    "sg:city":"Gedinne (sart-custinne)",
    "sg:classifiers":[
        {
            "category":"Banks & Credit Unions",
            "subcategory":"Investment Brokerage",
            "type":"Services"
        }
    ],
    "sg:phone":"+32 61 58 93 37",
    "sg:postcode":"5575",
    "sg:province":"Namur",
    "sg:tags":[
        "repair",
        "-",
        "installation",
        "sanitary",
        "article"
    ],
    "wof:name":"Lambot J F",
    "wof:placetype":"venue"
},
  "geometry": {"coordinates":[4.9287548065,49.9885673523],"type":"Point"}
}