{
  "type": "Feature",
  "properties": {
    "addr:full":"Avenue Nouvelle 39 Bruxelles (etterbeek) Bruxelles-Capitale 1040",
    "addr:housenumber":"39",
    "addr:postcode":"1040",
    "addr:street":"Avenue Nouvelle",
    "iso:country":"BE",
    "sg:address":"Avenue Nouvelle 39",
    "sg:city":"Bruxelles (etterbeek)",
    "sg:classifiers":[
        {
            "category":"Manufacturing",
            "subcategory":"Tools & Machinery",
            "type":"Manufacturing & Wholesale Goods"
        }
    ],
    "sg:phone":"+32 2 648 14 79",
    "sg:postcode":"1040",
    "sg:province":"Bruxelles-Capitale",
    "sg:tags":[
        "scale"
    ],
    "wof:name":"Anubis",
    "wof:placetype":"venue"
},
  "geometry": {"coordinates":[4.3813109398,50.8292961121],"type":"Point"}
}