{
  "type": "Feature",
  "properties": {
    "addr:full":"Rijselstraat 8 Menen West-Vlaanderen 8930",
    "addr:housenumber":"8",
    "addr:postcode":"8930",
    "addr:street":"Rijselstraat",
    "iso:country":"BE",
    "sg:address":"Rijselstraat 8",
    "sg:city":"Menen",
    "sg:orig_category":"Parfumeries. Drogueries",
    "sg:phone":"+32 56 51 52 21",
    "sg:postcode":"8930",
    "sg:province":"West-Vlaanderen",
    "wof:name":"Kruidvat",
    "wof:placetype":"venue"
},
  "geometry": {"coordinates":[3.1219289303,50.7958908081],"type":"Point"}
}