{
  "type": "Feature",
  "properties": {
    "iso:country":"BE",
    "sg:address":"'t Vaartje 10",
    "sg:city":"Knokke-heist (westkapelle)",
    "sg:classifiers":[
        {
            "category":"Real Estate",
            "subcategory":"Architect",
            "type":"Services"
        }
    ],
    "sg:phone":"+32 50 60 25 98",
    "sg:postcode":"8300",
    "sg:province":"West-Vlaanderen",
    "wof:name":"Vander Elst M",
    "wof:placetype":"venue"
},
  "geometry": {"coordinates":[3.2932159901,51.3358268738],"type":"Point"}
}