{
  "type": "Feature",
  "properties": {
    "addr:full":"Avenue Wanderpepen 3 Binche Hainaut 7130",
    "addr:housenumber":"3",
    "addr:postcode":"7130",
    "addr:street":"Avenue Wanderpepen",
    "iso:country":"BE",
    "sg:address":"Avenue Wanderpepen 3",
    "sg:city":"Binche",
    "sg:classifiers":[
        {
            "category":"Shopping",
            "subcategory":"Clothing, Apparel, & Fashions",
            "type":"Retail Goods"
        }
    ],
    "sg:phone":"+32 64 33 45 15",
    "sg:postcode":"7130",
    "sg:province":"Hainaut",
    "sg:tags":[
        "boutique"
    ],
    "wof:name":"Louise Rosa Sprl",
    "wof:placetype":"venue"
},
  "geometry": {"coordinates":[4.1677818298,50.4120063782],"type":"Point"}
}