{
  "type": "Feature",
  "properties": {
    "iso:country":"BE",
    "sg:address":"Rue De L'heribus 58",
    "sg:city":"Mons",
    "sg:orig_category":"Epiceries",
    "sg:phone":"+32 65 35 39 66",
    "sg:postcode":"7022",
    "sg:province":"Hainaut",
    "wof:name":"Maison Scandari",
    "wof:placetype":"venue"
},
  "geometry": {"coordinates":[3.9428110123,50.4245948792],"type":"Point"}
}