{
  "type": "Feature",
  "properties": {
    "iso:country":"BE",
    "sg:address":"Biestjeslos 13",
    "sg:city":"Gavere (vurste)",
    "sg:classifiers":[
        {
            "category":"Wholesale",
            "subcategory":"Plants",
            "type":"Manufacturing & Wholesale Goods"
        }
    ],
    "sg:phone":"+32 9 384 27 42",
    "sg:postcode":"9890",
    "sg:province":"Oost-Vlaanderen",
    "sg:tags":[
        "whol",
        "flower",
        "-",
        "grower"
    ],
    "wof:name":"Vandewalle Hugo Bloemisterij",
    "wof:placetype":"venue"
},
  "geometry": {"coordinates":[3.6588599682,50.9283752441],"type":"Point"}
}