{
  "type": "Feature",
  "properties": {
    "iso:country":"BE",
    "sg:address":"Brusselsesteenweg 528",
    "sg:city":"Mechelen",
    "sg:classifiers":[
        {
            "category":"Home & Garden",
            "subcategory":"Carpets & Floor Coverings",
            "type":"Retail Goods"
        }
    ],
    "sg:phone":"+32 15 42 31 51",
    "sg:postcode":"2800",
    "sg:province":"Antwerpen",
    "sg:tags":[
        "-",
        "rug"
    ],
    "wof:name":"Liekens Tapijten",
    "wof:placetype":"venue"
},
  "geometry": {"coordinates":[4.4738969803,50.9982376099],"type":"Point"}
}