{
  "type": "Feature",
  "properties": {
    "addr:full":"Dendermondsesteenweg 122 Puurs Antwerpen 2870",
    "addr:housenumber":"122",
    "addr:postcode":"2870",
    "addr:street":"Dendermondsesteenweg",
    "iso:country":"BE",
    "sg:address":"Dendermondsesteenweg 122",
    "sg:city":"Puurs",
    "sg:orig_category":"Producteurs de l\u00e9gumes",
    "sg:phone":"+32 3 889 47 06",
    "sg:postcode":"2870",
    "sg:province":"Antwerpen",
    "wof:name":"Freddy De Smedt",
    "wof:placetype":"venue"
},
  "geometry": {"coordinates":[4.3288798332,51.0583305359],"type":"Point"}
}