{
  "type": "Feature",
  "properties": {
    "addr:full":"Kasteeldreef 16 Zoersel Antwerpen 2980",
    "addr:housenumber":"16",
    "addr:postcode":"2980",
    "addr:street":"Kasteeldreef",
    "iso:country":"BE",
    "sg:address":"Kasteeldreef 16",
    "sg:city":"Zoersel",
    "sg:orig_category":"Secr\u00e9tariats",
    "sg:phone":"+32 3 383 69 53",
    "sg:postcode":"2980",
    "sg:province":"Antwerpen",
    "wof:name":"Raedschelders",
    "wof:placetype":"venue"
},
  "geometry": {"coordinates":[4.713435173,51.269985199],"type":"Point"}
}