{
  "type": "Feature",
  "properties": {
    "addr:full":"Siemenslaan Oostkamp West-Vlaanderen 8020",
    "addr:postcode":"8020",
    "addr:street":"Siemenslaan",
    "iso:country":"BE",
    "sg:address":"Siemenslaan",
    "sg:city":"Oostkamp",
    "sg:orig_category":"Gestion des d\u00e9charges and sites d\u00e9finitifs de stockage",
    "sg:phone":"+32 50 84 03 22",
    "sg:postcode":"8020",
    "sg:province":"West-Vlaanderen",
    "wof:name":"Containerpark Oostkamp",
    "wof:placetype":"venue"
},
  "geometry": {"coordinates":[3.2328689098,51.1474723816],"type":"Point"}
}