{
  "type": "Feature",
  "properties": {
    "iso:country":"BE",
    "sg:address":"Avenue Jean-baptiste Nothomb 75",
    "sg:city":"Arlon",
    "sg:classifiers":[
        {
            "category":"Professional",
            "subcategory":"Lawyer & Legal Services",
            "type":"Services"
        }
    ],
    "sg:phone":"+32 63 23 60 10",
    "sg:postcode":"6700",
    "sg:province":"Luxembourg",
    "wof:name":"Noirhomme C",
    "wof:placetype":"venue"
},
  "geometry": {"coordinates":[5.8065600395,49.6818885803],"type":"Point"}
}