{
  "type": "Feature",
  "properties": {
    "addr:full":"De Pannestraat 31b Veurne West-Vlaanderen 8630",
    "addr:housenumber":"31b",
    "addr:postcode":"8630",
    "addr:street":"De Pannestraat",
    "iso:country":"BE",
    "sg:address":"De Pannestraat 31b",
    "sg:city":"Veurne",
    "sg:orig_category":"Non-Classified Establishments",
    "sg:phone":"+32 58 31 22 09",
    "sg:postcode":"8630",
    "sg:province":"West-Vlaanderen",
    "wof:name":"Wim`s Bikes Center",
    "wof:placetype":"venue"
},
  "geometry": {"coordinates":[2.6586380005,51.0748710632],"type":"Point"}
}