{
  "type": "Feature",
  "properties": {
    "addr:full":"Rue De La Croix De Pierre 85 Bruxelles (saint-gilles) Bruxelles-Capitale 1060",
    "addr:housenumber":"85",
    "addr:postcode":"1060",
    "addr:street":"Rue De La Croix De Pierre",
    "iso:country":"BE",
    "sg:address":"Rue De La Croix De Pierre 85",
    "sg:city":"Bruxelles (saint-gilles)",
    "sg:orig_category":"Non-Classified Establishments",
    "sg:phone":"+32 2 534 34 58",
    "sg:postcode":"1060",
    "sg:province":"Bruxelles-Capitale",
    "wof:name":"Dilco",
    "wof:placetype":"venue"
},
  "geometry": {"coordinates":[4.3517460823,50.8287315369],"type":"Point"}
}