{
  "type": "Feature",
  "properties": {
    "addr:full":"Pastoor Dergentstraat 5 Aarschot (gelrode) Vlaams-Brabant 3200",
    "addr:housenumber":"5",
    "addr:postcode":"3200",
    "addr:street":"Pastoor Dergentstraat",
    "iso:country":"BE",
    "sg:address":"Pastoor Dergentstraat 5",
    "sg:city":"Aarschot (gelrode)",
    "sg:classifiers":[
        {
            "category":"Professional",
            "subcategory":"Testing Lab",
            "type":"Services"
        }
    ],
    "sg:phone":"+32 16 56 93 77",
    "sg:postcode":"3200",
    "sg:province":"Vlaams-Brabant",
    "sg:tags":[
        "chemist"
    ],
    "wof:name":"Geyskens C",
    "wof:placetype":"venue"
},
  "geometry": {"coordinates":[4.8322482109,50.986541748],"type":"Point"}
}