{
  "type": "Feature",
  "properties": {
    "addr:full":"Winkelstraat 10 Lanaken Limburg 3620",
    "addr:housenumber":"10",
    "addr:postcode":"3620",
    "addr:street":"Winkelstraat",
    "iso:country":"BE",
    "sg:address":"Winkelstraat 10",
    "sg:city":"Lanaken",
    "sg:classifiers":[
        {
            "category":"Shopping",
            "subcategory":"Jewelry",
            "type":"Retail Goods"
        }
    ],
    "sg:phone":"+32 89 73 15 73",
    "sg:postcode":"3620",
    "sg:province":"Limburg",
    "sg:tags":[
        "-",
        "imitation"
    ],
    "wof:name":"Twice As Nice",
    "wof:placetype":"venue"
},
  "geometry": {"coordinates":[5.649283886,50.8884391785],"type":"Point"}
}