{
  "type": "Feature",
  "properties": {
    "addr:full":"Sylvain Dupuisstraat 30 Knokke-heist (knokke) West-Vlaanderen 8300",
    "addr:housenumber":"30",
    "addr:postcode":"8300",
    "addr:street":"Sylvain Dupuisstraat",
    "iso:country":"BE",
    "sg:address":"Sylvain Dupuisstraat 30",
    "sg:city":"Knokke-heist (knokke)",
    "sg:classifiers":[
        {
            "category":"Health Services",
            "subcategory":"Doctor",
            "type":"Services"
        }
    ],
    "sg:phone":"+32 50 60 90 62",
    "sg:postcode":"8300",
    "sg:province":"West-Vlaanderen",
    "sg:tags":[
        "medicinephysicians",
        "surgeon"
    ],
    "wof:name":"Den Blauwen N",
    "wof:placetype":"venue"
},
  "geometry": {"coordinates":[3.287694931,51.3467254639],"type":"Point"}
}