{
  "type": "Feature",
  "properties": {
    "iso:country":"BE",
    "sg:address":"Canadalaan 61",
    "sg:city":"Gistel",
    "sg:classifiers":[
        {
            "category":"Taxi",
            "type":"Transportation"
        }
    ],
    "sg:phone":"+32 59 27 57 45",
    "sg:postcode":"8470",
    "sg:province":"West-Vlaanderen",
    "sg:tags":[
        "taxi's"
    ],
    "wof:name":"Mike",
    "wof:placetype":"venue"
},
  "geometry": {"coordinates":[2.9588038921,51.1575088501],"type":"Point"}
}