{
  "type": "Feature",
  "properties": {
    "addr:full":"Lokerhoutstraat 77 Lokeren Oost-Vlaanderen 9160",
    "addr:housenumber":"77",
    "addr:postcode":"9160",
    "addr:street":"Lokerhoutstraat",
    "iso:country":"BE",
    "sg:address":"Lokerhoutstraat 77",
    "sg:city":"Lokeren",
    "sg:classifiers":[
        {
            "category":"Personal",
            "subcategory":"Beauty Salon",
            "type":"Services"
        }
    ],
    "sg:phone":"+32 9 348 61 24",
    "sg:postcode":"9160",
    "sg:province":"Oost-Vlaanderen",
    "sg:tags":[
        "de",
        "coiffure"
    ],
    "wof:name":"Coiffure Patrick",
    "wof:placetype":"venue"
},
  "geometry": {"coordinates":[3.9956610203,51.095451355],"type":"Point"}
}