{
  "type": "Feature",
  "properties": {
    "iso:country":"BE",
    "sg:address":"Place L\u00e9opold 9",
    "sg:city":"Namur",
    "sg:classifiers":[
        {
            "category":"Professional",
            "subcategory":"Testing Lab",
            "type":"Services"
        }
    ],
    "sg:phone":"+32 81 22 98 46",
    "sg:postcode":"5000",
    "sg:province":"Namur",
    "sg:tags":[
        "chemist"
    ],
    "wof:name":"Vesale",
    "wof:placetype":"venue"
},
  "geometry": {"coordinates":[4.8683800697,50.4685783386],"type":"Point"}
}