{
  "type": "Feature",
  "properties": {
    "iso:country":"BE",
    "sg:address":"Brabantdam 49",
    "sg:city":"Gent",
    "sg:orig_category":"Foto-uitrusting Huishoudapparaten, televisies and radio's Telecommunicatieapparaten",
    "sg:phone":"+32 9 233 46 91",
    "sg:postcode":"9000",
    "sg:province":"Oost-Vlaanderen",
    "wof:name":"Photo Hall",
    "wof:placetype":"venue"
},
  "geometry": {"coordinates":[3.7291469574,51.0504188538],"type":"Point"}
}