{
  "type": "Feature",
  "properties": {
    "addr:full":"Rue Des Puits L'eau 33 Tournai Hainaut 7500",
    "addr:housenumber":"33",
    "addr:postcode":"7500",
    "addr:street":"Rue Des Puits L'Eau",
    "iso:country":"BE",
    "sg:address":"Rue Des Puits L'eau 33",
    "sg:city":"Tournai",
    "sg:classifiers":[
        {
            "category":"Retail",
            "subcategory":"Laundry & Dry Cleaning",
            "type":"Services"
        }
    ],
    "sg:phone":"+32 69 22 33 48",
    "sg:postcode":"7500",
    "sg:province":"Hainaut",
    "sg:tags":[
        "knitwear",
        "-"
    ],
    "wof:name":"Degand A",
    "wof:placetype":"venue"
},
  "geometry": {"coordinates":[3.3914549351,50.605884552],"type":"Point"}
}