{
  "type": "Feature",
  "properties": {
    "addr:full":"Houtstraat 16 Zulte Oost-Vlaanderen 9870",
    "addr:housenumber":"16",
    "addr:postcode":"9870",
    "addr:street":"Houtstraat",
    "iso:country":"BE",
    "sg:address":"Houtstraat 16",
    "sg:city":"Zulte",
    "sg:orig_category":"Woningbouw",
    "sg:phone":"+32 9 388 75 75",
    "sg:postcode":"9870",
    "sg:province":"Oost-Vlaanderen",
    "wof:name":"Vanthuyne",
    "wof:placetype":"venue"
},
  "geometry": {"coordinates":[3.4639968872,50.9269371033],"type":"Point"}
}