{
  "type": "Feature",
  "properties": {
    "addr:full":"Heidelaan 24 De Haan (klemskerke) West-Vlaanderen 8420",
    "addr:housenumber":"24",
    "addr:postcode":"8420",
    "addr:street":"Heidelaan",
    "iso:country":"BE",
    "sg:address":"Heidelaan 24",
    "sg:city":"De Haan (klemskerke)",
    "sg:classifiers":[
        {
            "category":"Education",
            "subcategory":"School",
            "type":"Public Place"
        }
    ],
    "sg:phone":"+32 59 23 77 05",
    "sg:postcode":"8420",
    "sg:province":"West-Vlaanderen",
    "sg:tags":[
        "primary"
    ],
    "wof:name":"Heideschool",
    "wof:placetype":"venue"
},
  "geometry": {"coordinates":[3.0040800571,51.2593536377],"type":"Point"}
}