{
  "type": "Feature",
  "properties": {
    "addr:full":"Kerkom-dorp 118 Sint-truiden Limburg 3800",
    "addr:housenumber":"118",
    "addr:postcode":"3800",
    "addr:street":"Sint-Truiden Limburg",
    "iso:country":"BE",
    "sg:address":"Kerkom-dorp 118",
    "sg:city":"Sint-truiden",
    "sg:classifiers":[
        {
            "category":"Arena",
            "subcategory":"Sports Club",
            "type":"Entertainment"
        }
    ],
    "sg:phone":"+32 11 67 38 59",
    "sg:postcode":"3800",
    "sg:province":"Limburg",
    "sg:tags":[
        "de"
    ],
    "wof:name":"Wtc Sint-martinus",
    "wof:placetype":"venue"
},
  "geometry": {"coordinates":[5.1835999489,50.7727775574],"type":"Point"}
}