{
  "type": "Feature",
  "properties": {
    "iso:country":"BE",
    "sg:address":"Prof.o.rubbrechtstraat 19",
    "sg:city":"Poperinge",
    "sg:orig_category":"Artsen and specialisten",
    "sg:phone":"+32 57 30 03 38",
    "sg:postcode":"8972",
    "sg:province":"West-Vlaanderen",
    "wof:name":"Hugo Neuville",
    "wof:placetype":"venue"
},
  "geometry": {"coordinates":[2.6248309612,50.9186134338],"type":"Point"}
}