{
  "type": "Feature",
  "properties": {
    "iso:country":"BE",
    "sg:address":"Adolphe Maxlaan 132",
    "sg:city":"Brussel/bruxelles",
    "sg:orig_category":"Seksshops",
    "sg:phone":"+32 2 223 05 31",
    "sg:postcode":"1000",
    "sg:province":"Bruxelles-Capitale",
    "wof:name":"Discount X",
    "wof:placetype":"venue"
},
  "geometry": {"coordinates":[4.3568048477,50.8547706604],"type":"Point"}
}