{
  "type": "Feature",
  "properties": {
    "iso:country":"BE",
    "sg:address":"Rue Petit Navarre 31",
    "sg:city":"Bouillon",
    "sg:orig_category":"Watersport-, Sport- and Kampeerbenodigdheden Verhuur",
    "sg:phone":"+32 475 24 74 23",
    "sg:postcode":"6830",
    "sg:province":"Luxembourg",
    "wof:name":"Semois Kayaks",
    "wof:placetype":"venue"
},
  "geometry": {"coordinates":[5.0741910934,49.7846717834],"type":"Point"}
}