{
  "type": "Feature",
  "properties": {
    "iso:country":"BE",
    "sg:address":"Warandestraat 80",
    "sg:city":"Wevelgem",
    "sg:orig_category":"Produits \u00e0 base de pommes de terre Fruits and l\u00e9gumes Gr",
    "sg:phone":"+32 56 41 24 92",
    "sg:postcode":"8560",
    "sg:province":"West-Vlaanderen",
    "wof:name":"Berghman",
    "wof:placetype":"venue"
},
  "geometry": {"coordinates":[3.1668291092,50.8359336853],"type":"Point"}
}