{
  "type": "Feature",
  "properties": {
    "iso:country":"BE",
    "sg:address":"Rue Du Terminus 3",
    "sg:city":"Berloz",
    "sg:orig_category":"Brood, gebak and snoepgoed",
    "sg:phone":"+32 19 32 37 15",
    "sg:postcode":"4257",
    "sg:province":"Li\u00e8ge",
    "wof:name":"Gerard Brouet",
    "wof:placetype":"venue"
},
  "geometry": {"coordinates":[5.2165970802,50.6962661743],"type":"Point"}
}