{
  "type": "Feature",
  "properties": {
    "iso:country":"BE",
    "sg:address":"Route De Lamorm\u00e9nil 21",
    "sg:city":"Manhay (dochamps)",
    "sg:classifiers":[
        {
            "category":"Government",
            "subcategory":"Department Of Motor Vehicles",
            "type":"Public Place"
        }
    ],
    "sg:phone":"+32 86 45 51 92",
    "sg:postcode":"6960",
    "sg:province":"Luxembourg",
    "sg:tags":[
        "planing",
        "wood",
        "sawing"
    ],
    "wof:name":"Scierie De Dochamps",
    "wof:placetype":"venue"
},
  "geometry": {"coordinates":[5.5982298851,50.2552986145],"type":"Point"}
}