{
  "type": "Feature",
  "properties": {
    "iso:country":"BE",
    "sg:address":"Heldenlaan 55",
    "sg:city":"Zottegem",
    "sg:orig_category":"Alimentation sp\u00e9cialis\u00e9e. Epiceries",
    "sg:phone":"+32 9 361 14 54",
    "sg:postcode":"9620",
    "sg:province":"Oost-Vlaanderen",
    "wof:name":"\u00b4t Gastronoompje",
    "wof:placetype":"venue"
},
  "geometry": {"coordinates":[3.8106460571,50.8699645996],"type":"Point"}
}