{
  "type": "Feature",
  "properties": {
    "iso:country":"BE",
    "sg:address":"Grotstraat 15",
    "sg:city":"Arendonk",
    "sg:classifiers":[
        {
            "category":"Banks & Credit Unions",
            "subcategory":"Investment Brokerage",
            "type":"Services"
        }
    ],
    "sg:phone":"+32 14 67 91 09",
    "sg:postcode":"2370",
    "sg:province":"Antwerpen",
    "sg:tags":[
        "rental",
        "-",
        "yacht",
        "boat",
        "pleasure"
    ],
    "wof:name":"Charterlux Bvba",
    "wof:placetype":"venue"
},
  "geometry": {"coordinates":[5.0794649124,51.3259887695],"type":"Point"}
}