{
  "type": "Feature",
  "properties": {
    "iso:country":"BE",
    "sg:address":"Burgemeester Potiaulaan 46",
    "sg:city":"Dendermonde",
    "sg:orig_category":"Brood, gebak and snoepgoed",
    "sg:phone":"+32 52 21 15 49",
    "sg:postcode":"9200",
    "sg:province":"Oost-Vlaanderen",
    "wof:name":"F. De Cock",
    "wof:placetype":"venue"
},
  "geometry": {"coordinates":[4.1125679016,51.0203437805],"type":"Point"}
}