{
  "type": "Feature",
  "properties": {
    "iso:country":"BE",
    "sg:address":"Molenstraat 78",
    "sg:city":"Gavere",
    "sg:classifiers":[
        {
            "category":"Retail",
            "subcategory":"Auto Repair",
            "type":"Services"
        }
    ],
    "sg:phone":"+32 9 384 22 83",
    "sg:postcode":"9890",
    "sg:province":"Oost-Vlaanderen",
    "sg:tags":[
        "garage"
    ],
    "wof:name":"Contreras Nv",
    "wof:placetype":"venue"
},
  "geometry": {"coordinates":[3.6709189415,50.9252586365],"type":"Point"}
}