{
  "type": "Feature",
  "properties": {
    "iso:country":"BE",
    "sg:address":"Chauss\u00e9e De Namur 389",
    "sg:city":"Eghez\u00e9e (waret-la-chauss\u00e9e)",
    "sg:classifiers":[
        {
            "category":"Retail",
            "subcategory":"Auto Repair",
            "type":"Services"
        }
    ],
    "sg:phone":"+32 81 51 10 27",
    "sg:postcode":"5310",
    "sg:province":"Namur",
    "sg:tags":[
        "garage"
    ],
    "wof:name":"Carpiaux Sa",
    "wof:placetype":"venue"
},
  "geometry": {"coordinates":[4.9103899002,50.5753898621],"type":"Point"}
}