{
  "type": "Feature",
  "properties": {
    "iso:country":"BE",
    "sg:address":"Leuvensesteenweg 755",
    "sg:city":"Mechelen",
    "sg:classifiers":[
        {
            "category":"Bars & Pubs",
            "type":"Food & Drink"
        }
    ],
    "sg:phone":"+32 15 51 10 37",
    "sg:postcode":"2800",
    "sg:province":"Antwerpen",
    "wof:name":"Florial",
    "wof:placetype":"venue"
},
  "geometry": {"coordinates":[4.4995799065,51.0152511597],"type":"Point"}
}