{
  "type": "Feature",
  "properties": {
    "iso:country":"BE",
    "sg:address":"Rue De Fl\u00e9malle-grande 40",
    "sg:city":"Fl\u00e9malle",
    "sg:classifiers":[
        {
            "category":"Personal",
            "subcategory":"Barber",
            "type":"Services"
        }
    ],
    "sg:phone":"+32 4 234 02 80",
    "sg:postcode":"4400",
    "sg:province":"Li\u00e8ge",
    "sg:tags":[
        "gentleman",
        "salon",
        "-",
        "hairdressing"
    ],
    "wof:name":"L\u00e9onard Coiffure",
    "wof:placetype":"venue"
},
  "geometry": {"coordinates":[5.4796562195,50.6059570312],"type":"Point"}
}