{
  "type": "Feature",
  "properties": {
    "iso:country":"BE",
    "sg:address":"Place Georges Hubin 3",
    "sg:city":"Modave",
    "sg:orig_category":"Openbare veiligheid",
    "sg:phone":"+32 85 41 27 23",
    "sg:postcode":"4577",
    "sg:province":"Li\u00e8ge",
    "wof:name":"Police F\u00c9d\u00c9rale",
    "wof:placetype":"venue"
},
  "geometry": {"coordinates":[5.297961235,50.4830245972],"type":"Point"}
}