{
  "type": "Feature",
  "properties": {
    "iso:country":"BE",
    "sg:address":"Battelsesteenweg 455d",
    "sg:city":"Mechelen",
    "sg:classifiers":[
        {
            "category":"Shopping",
            "subcategory":"Books",
            "type":"Retail Goods"
        }
    ],
    "sg:phone":"+32 15 28 54 40",
    "sg:postcode":"2800",
    "sg:province":"Antwerpen",
    "sg:tags":[
        "bookseller"
    ],
    "wof:name":"Asdu International Nv",
    "wof:placetype":"venue"
},
  "geometry": {"coordinates":[4.450094223,51.0380706787],"type":"Point"}
}