{
  "type": "Feature",
  "properties": {
    "iso:country":"BE",
    "sg:address":"Rue Saint-lambert 9",
    "sg:city":"Walhain",
    "sg:orig_category":"Algemeen secundair onderwijs",
    "sg:phone":"+32 10 65 85 08",
    "sg:postcode":"1457",
    "sg:province":"Brabant Wallon",
    "wof:name":"Ecole Jean Bosco",
    "wof:placetype":"venue"
},
  "geometry": {"coordinates":[4.7109651566,50.6405067444],"type":"Point"}
}