{
  "type": "Feature",
  "properties": {
    "addr:full":"Rue Des Tanneurs 19 Estaimpuis Hainaut 7730",
    "addr:housenumber":"19",
    "addr:postcode":"7730",
    "addr:street":"Rue Des Tanneurs;Hainaut",
    "iso:country":"BE",
    "sg:address":"Rue Des Tanneurs 19",
    "sg:city":"Estaimpuis",
    "sg:orig_category":"Rijscholen",
    "sg:phone":"+32 69 55 61 90",
    "sg:postcode":"7730",
    "sg:province":"Hainaut",
    "wof:name":"Auto Ecole Rousseau",
    "wof:placetype":"venue"
},
  "geometry": {"coordinates":[3.2735199928,50.6673164368],"type":"Point"}
}