{
  "type": "Feature",
  "properties": {
    "addr:full":"Schuiferskapellestraat 64 Pittem West-Vlaanderen 8740",
    "addr:housenumber":"64",
    "addr:postcode":"8740",
    "addr:street":"Schuiferskapellestraat",
    "iso:country":"BE",
    "sg:address":"Schuiferskapellestraat 64",
    "sg:city":"Pittem",
    "sg:orig_category":"Fabrication and montage de mobilier. Installation de menuiserie en bois and plastique",
    "sg:phone":"+32 51 46 60 05",
    "sg:postcode":"8740",
    "sg:province":"West-Vlaanderen",
    "wof:name":"Stefaan Verbecke",
    "wof:placetype":"venue"
},
  "geometry": {"coordinates":[3.2693190575,50.9996948242],"type":"Point"}
}