{
  "type": "Feature",
  "properties": {
    "iso:country":"BE",
    "sg:address":"Eeksken 46",
    "sg:city":"Opwijk",
    "sg:orig_category":"ACCOUNTANTS Belastingconsulenten Boekhouders Diverse juridische dienstverlening",
    "sg:phone":"+32 52 35 87 28",
    "sg:postcode":"1745",
    "sg:province":"Vlaams-Brabant",
    "wof:name":"Sofisbo Zakenkantoor",
    "wof:placetype":"venue"
},
  "geometry": {"coordinates":[4.1762599945,50.9792747498],"type":"Point"}
}