{
  "type": "Feature",
  "properties": {
    "addr:full":"Avenue Des Hirondelles 56 Ottignies-louvain-la-neuve (c\u00e9roux-mousty) Brabant Wallon 1341",
    "addr:housenumber":"56",
    "addr:postcode":"1341",
    "addr:street":"Avenue Des Hirondelles;Wallon",
    "iso:country":"BE",
    "sg:address":"Avenue Des Hirondelles 56",
    "sg:city":"Ottignies-louvain-la-neuve (c\u00e9roux-mousty)",
    "sg:classifiers":[
        {
            "category":"Professional",
            "subcategory":"Computer Services",
            "type":"Services"
        }
    ],
    "sg:phone":"+32 10 61 18 31",
    "sg:postcode":"1341",
    "sg:province":"Brabant Wallon",
    "sg:tags":[
        "-",
        "processing",
        "data"
    ],
    "wof:name":"Andy Informatique",
    "wof:placetype":"venue"
},
  "geometry": {"coordinates":[4.5627598763,50.6583099365],"type":"Point"}
}