{
  "type": "Feature",
  "properties": {
    "addr:full":"Gaston Oomslaan 14 Beringen Limburg 3581",
    "addr:housenumber":"14",
    "addr:postcode":"3581",
    "addr:street":"Gaston Oomslaan",
    "iso:country":"BE",
    "sg:address":"Gaston Oomslaan 14",
    "sg:city":"Beringen",
    "sg:orig_category":"Alternatieve geneeskunde",
    "sg:phone":"+32 11 34 87 34",
    "sg:postcode":"3581",
    "sg:province":"Limburg",
    "wof:name":"Beatrijs Claes",
    "wof:placetype":"venue"
},
  "geometry": {"coordinates":[5.2246851921,51.0872573853],"type":"Point"}
}