{
  "type": "Feature",
  "properties": {
    "addr:full":"Westmeerbeeksesteenweg 36 Herselt Antwerpen 2230",
    "addr:housenumber":"36",
    "addr:postcode":"2230",
    "addr:street":"Westmeerbeeksesteenweg",
    "iso:country":"BE",
    "sg:address":"Westmeerbeeksesteenweg 36",
    "sg:city":"Herselt",
    "sg:orig_category":"Artsen and specialisten",
    "sg:phone":"+32 16 68 05 60",
    "sg:postcode":"2230",
    "sg:province":"Antwerpen",
    "wof:name":"Kris Van Der Mieren",
    "wof:placetype":"venue"
},
  "geometry": {"coordinates":[4.8318481445,51.0343475342],"type":"Point"}
}