{
  "type": "Feature",
  "properties": {
    "iso:country":"BE",
    "sg:address":"Tiensevest 2",
    "sg:city":"Leuven",
    "sg:classifiers":[
        {
            "category":"Wholesale",
            "subcategory":"Wine & Distilled Alcoholic Beverages",
            "type":"Manufacturing & Wholesale Goods"
        }
    ],
    "sg:phone":"+32 16 29 33 03",
    "sg:postcode":"3000",
    "sg:province":"Vlaams-Brabant",
    "sg:tags":[
        "whol",
        "-",
        "spirit",
        "mfg"
    ],
    "wof:name":"Vini Scotton",
    "wof:placetype":"venue"
},
  "geometry": {"coordinates":[4.702837944,50.8789291382],"type":"Point"}
}