{
  "type": "Feature",
  "properties": {
    "addr:full":"Rue De La Chapelle 115 Nandrin Li\u00e8ge 4550",
    "addr:housenumber":"115",
    "addr:postcode":"4550",
    "addr:street":"Rue De La Chapelle",
    "iso:country":"BE",
    "sg:address":"Rue De La Chapelle 115",
    "sg:city":"Nandrin",
    "sg:orig_category":"Medische apparatuur, orthopedische artikelen and prothesen Fab",
    "sg:phone":"+32 475 92 62 82",
    "sg:postcode":"4550",
    "sg:province":"Li\u00e8ge",
    "wof:name":"Chrome Labor",
    "wof:placetype":"venue"
},
  "geometry": {"coordinates":[5.376308918,50.5112495422],"type":"Point"}
}