{
  "type": "Feature",
  "properties": {
    "iso:country":"BE",
    "sg:address":"Rue Longue 12",
    "sg:city":"Viroinval",
    "sg:orig_category":"DIVERSE RECREATIEVE ACTIVITEITEN",
    "sg:phone":"+32 60 31 10 14",
    "sg:postcode":"5670",
    "sg:province":"Namur",
    "wof:name":"Ass. Philat\u00c9l. Viroinval",
    "wof:placetype":"venue"
},
  "geometry": {"coordinates":[4.5484700203,50.0728607178],"type":"Point"}
}