{
  "type": "Feature",
  "properties": {
    "addr:full":"Professor Rubbrechtstraat 42 Poperinge (roesbrugge-haringe) West-Vlaanderen 8972",
    "addr:housenumber":"42",
    "addr:postcode":"8972",
    "addr:street":"Professor Rubbrechtstraat",
    "iso:country":"BE",
    "sg:address":"Professor Rubbrechtstraat 42",
    "sg:city":"Poperinge (roesbrugge-haringe)",
    "sg:classifiers":[
        {
            "category":"Wholesale",
            "subcategory":"Beer",
            "type":"Manufacturing & Wholesale Goods"
        }
    ],
    "sg:phone":"+32 57 30 02 90",
    "sg:postcode":"8972",
    "sg:province":"West-Vlaanderen",
    "sg:tags":[
        "ale",
        "-"
    ],
    "wof:name":"Deheegher H",
    "wof:placetype":"venue"
},
  "geometry": {"coordinates":[2.625469923,50.9183540344],"type":"Point"}
}