{
  "type": "Feature",
  "properties": {
    "iso:country":"BE",
    "sg:address":"Rue Paul Pastur 16",
    "sg:city":"Courcelles",
    "sg:orig_category":"Artsen and specialisten",
    "sg:phone":"+32 71 46 21 44",
    "sg:postcode":"6180",
    "sg:province":"Hainaut",
    "wof:name":"Georges Michalakis",
    "wof:placetype":"venue"
},
  "geometry": {"coordinates":[4.3814368248,50.4588279724],"type":"Point"}
}