{
  "type": "Feature",
  "properties": {
    "iso:country":"BE",
    "sg:address":"Strijdersstraat 3",
    "sg:city":"Komen-waasten/comines-warneton",
    "sg:orig_category":"Advocaten and juridische adviseurs",
    "sg:phone":"+32 56 55 40 50",
    "sg:postcode":"7780",
    "sg:province":"Hainaut",
    "wof:name":"V\u00c9ronique Raveschot",
    "wof:placetype":"venue"
},
  "geometry": {"coordinates":[2.9984300137,50.7863311768],"type":"Point"}
}