{
  "type": "Feature",
  "properties": {
    "iso:country":"BE",
    "sg:address":"Sint-amandsstraat 44",
    "sg:city":"Grimbergen",
    "sg:orig_category":"Industri\u00eble wasserijen and droogkuis",
    "sg:phone":"+32 2 267 11 07",
    "sg:postcode":"1853",
    "sg:province":"Vlaams-Brabant",
    "wof:name":"Seghers",
    "wof:placetype":"venue"
},
  "geometry": {"coordinates":[4.3578419685,50.9088172913],"type":"Point"}
}