{
  "type": "Feature",
  "properties": {
    "addr:full":"Hoevestraat 8 Tremelo Vlaams-Brabant 3120",
    "addr:housenumber":"8",
    "addr:postcode":"3120",
    "addr:street":"Hoevestraat",
    "iso:country":"BE",
    "sg:address":"Hoevestraat 8",
    "sg:city":"Tremelo",
    "sg:orig_category":"Groententeelt Rundveehouders",
    "sg:phone":"+32 16 53 58 40",
    "sg:postcode":"3120",
    "sg:province":"Vlaams-Brabant",
    "wof:name":"Jozef Van Doorslaer",
    "wof:placetype":"venue"
},
  "geometry": {"coordinates":[4.7351927757,50.9840965271],"type":"Point"}
}