{
  "type": "Feature",
  "properties": {
    "addr:full":"Zellestraat 1 Grobbendonk Antwerpen 2288",
    "addr:housenumber":"1",
    "addr:postcode":"2288",
    "addr:street":"Zellestraat",
    "iso:country":"BE",
    "sg:address":"Zellestraat 1",
    "sg:city":"Grobbendonk",
    "sg:orig_category":"Mat\u00e9riel m\u00e9dical and orthop\u00e9dique and proth\u00e8ses Fab",
    "sg:phone":"+32 14 51 36 03",
    "sg:postcode":"2288",
    "sg:province":"Antwerpen",
    "wof:name":"Naegels Dentaal",
    "wof:placetype":"venue"
},
  "geometry": {"coordinates":[4.7571458817,51.1640548706],"type":"Point"}
}