{
  "type": "Feature",
  "properties": {
    "addr:full":"Rue De L'h\u00f4tel Des Monnaies 138 Bruxelles (saint-gilles) Bruxelles-Capitale 1060",
    "addr:housenumber":"138",
    "addr:postcode":"1060",
    "addr:street":"Rue De L'Ho;Des Monnaies",
    "iso:country":"BE",
    "sg:address":"Rue De L'h\u00f4tel Des Monnaies 138",
    "sg:city":"Bruxelles (saint-gilles)",
    "sg:classifiers":[
        {
            "category":"Professional",
            "subcategory":"Accounting & Tax Preparation",
            "type":"Services"
        }
    ],
    "sg:phone":"+32 2 537 55 34",
    "sg:postcode":"1060",
    "sg:province":"Bruxelles-Capitale",
    "sg:tags":[
        "bookkeeper"
    ],
    "wof:name":"Saez Alvarez J-c",
    "wof:placetype":"venue"
},
  "geometry": {"coordinates":[4.3466229439,50.8288917542],"type":"Point"}
}