{
  "type": "Feature",
  "properties": {
    "addr:full":"Bisschopsweyerstraat 37 Alken Limburg 3570",
    "addr:housenumber":"37",
    "addr:postcode":"3570",
    "addr:street":"Bisschopsweyerstraat",
    "iso:country":"BE",
    "sg:address":"Bisschopsweyerstraat 37",
    "sg:city":"Alken",
    "sg:orig_category":"Agences de relations publiques. Agences de publicit\u00e9. Bureaux d'\u00e9tudes de march\u00e9. Sondages and enqu\u00ea",
    "sg:phone":"+32 11 31 65 72",
    "sg:postcode":"3570",
    "sg:province":"Limburg",
    "wof:name":"R.c.a.",
    "wof:placetype":"venue"
},
  "geometry": {"coordinates":[5.2714409828,50.8611946106],"type":"Point"}
}