{
  "type": "Feature",
  "properties": {
    "iso:country":"BE",
    "sg:address":"Vosbroekstraat 12",
    "sg:city":"Oosterzele",
    "sg:orig_category":"Sportclubs",
    "sg:phone":"+32 9 362 01 51",
    "sg:postcode":"9860",
    "sg:province":"Oost-Vlaanderen",
    "wof:name":"Recht Vooruit",
    "wof:placetype":"venue"
},
  "geometry": {"coordinates":[3.795445919,50.9204597473],"type":"Point"}
}