{
  "type": "Feature",
  "properties": {
    "iso:country":"BE",
    "sg:address":"Rue Winston Churchill 99",
    "sg:city":"Courcelles",
    "sg:classifiers":[
        {
            "category":"Professional",
            "subcategory":"Art Services",
            "type":"Services"
        }
    ],
    "sg:phone":"+32 71 45 59 39",
    "sg:postcode":"6180",
    "sg:province":"Hainaut",
    "sg:tags":[
        "children's",
        "animation"
    ],
    "wof:name":"Amis D'houdini Asbl (les)",
    "wof:placetype":"venue"
},
  "geometry": {"coordinates":[4.3854980469,50.4613723755],"type":"Point"}
}