{
  "type": "Feature",
  "properties": {
    "addr:full":"Wervikstraat 31bb Wervik West-Vlaanderen 8940",
    "addr:housenumber":"31bb",
    "addr:postcode":"8940",
    "addr:street":"Wervikstraat",
    "iso:country":"BE",
    "sg:address":"Wervikstraat 31bb",
    "sg:city":"Wervik",
    "sg:orig_category":"Installatie van houten of kunststof schrijnwerk Installatie van metalen schrijnwerk",
    "sg:phone":"+32 56 51 55 79",
    "sg:postcode":"8940",
    "sg:province":"West-Vlaanderen",
    "wof:name":"Francovera",
    "wof:placetype":"venue"
},
  "geometry": {"coordinates":[3.0988600254,50.8160171509],"type":"Point"}
}