{
  "type": "Feature",
  "properties": {
    "addr:full":"Rue Cayauderie 195 Charleroi Hainaut 6000",
    "addr:housenumber":"195",
    "addr:postcode":"6000",
    "addr:street":"Rue Cayauderie;Hainaut",
    "iso:country":"BE",
    "sg:address":"Rue Cayauderie 195",
    "sg:city":"Charleroi",
    "sg:orig_category":"Artsen and specialisten",
    "sg:phone":"+32 71 41 71 51",
    "sg:postcode":"6000",
    "sg:province":"Hainaut",
    "wof:name":"Philippe Cloquet",
    "wof:placetype":"venue"
},
  "geometry": {"coordinates":[4.4562129974,50.4256668091],"type":"Point"}
}