{
  "type": "Feature",
  "properties": {
    "iso:country":"BE",
    "sg:address":"Sint-sebastiaanstraat 5",
    "sg:city":"Beveren",
    "sg:orig_category":"Alimentation sp\u00e9cialis\u00e9e",
    "sg:phone":"+32 3 775 30 20",
    "sg:postcode":"9120",
    "sg:province":"Oost-Vlaanderen",
    "wof:name":"Gilberte Suy",
    "wof:placetype":"venue"
},
  "geometry": {"coordinates":[4.2578802109,51.2202072144],"type":"Point"}
}