{
  "type": "Feature",
  "properties": {
    "iso:country":"BE",
    "sg:address":"Rue Buisson-aux-loups 11",
    "sg:city":"Nivelles",
    "sg:orig_category":"Imprimeries and copyshops. Reliure and finition. Secr\u00e9tariats",
    "sg:phone":"+32 67 21 27 74",
    "sg:postcode":"1400",
    "sg:province":"Brabant Wallon",
    "wof:name":"Imprimerie Dubrai",
    "wof:placetype":"venue"
},
  "geometry": {"coordinates":[4.3513221741,50.5910186768],"type":"Point"}
}