{
  "type": "Feature",
  "properties": {
    "iso:country":"BE",
    "sg:address":"W\u00c9rystraat 24",
    "sg:city":"Elsene/ixelles",
    "sg:orig_category":"Fotografen and fotostudio's",
    "sg:phone":"+32 2 646 81 89",
    "sg:postcode":"1050",
    "sg:province":"Bruxelles-Capitale",
    "wof:name":"M.d.a.",
    "wof:placetype":"venue"
},
  "geometry": {"coordinates":[4.3758711815,50.83152771],"type":"Point"}
}