{
  "type": "Feature",
  "properties": {
    "addr:full":"Keerstraat 12 Tongeren Limburg 3700",
    "addr:housenumber":"12",
    "addr:postcode":"3700",
    "addr:street":"Keerstraat",
    "iso:country":"BE",
    "sg:address":"Keerstraat 12",
    "sg:city":"Tongeren",
    "sg:classifiers":[
        {
            "category":"Arena",
            "subcategory":"Sports Club",
            "type":"Entertainment"
        }
    ],
    "sg:phone":"+32 12 23 50 45",
    "sg:postcode":"3700",
    "sg:province":"Limburg",
    "sg:tags":[
        "terrain",
        "hors",
        "de",
        "installation",
        "sportifs"
    ],
    "wof:name":"K.v.c. Hoger-op Mal",
    "wof:placetype":"venue"
},
  "geometry": {"coordinates":[5.5170230865,50.7732658386],"type":"Point"}
}