{
  "type": "Feature",
  "properties": {
    "iso:country":"BE",
    "sg:address":"Vlaamsekaai 19",
    "sg:city":"Antwerpen",
    "sg:orig_category":"Agences d'exp\u00e9dition",
    "sg:phone":"+32 3 257 24 94",
    "sg:postcode":"2000",
    "sg:province":"Antwerpen",
    "wof:name":"Trade Wind",
    "wof:placetype":"venue"
},
  "geometry": {"coordinates":[4.3926157951,51.2110481262],"type":"Point"}
}