{
  "type": "Feature",
  "properties": {
    "iso:country":"BE",
    "sg:address":"Avenue De France 116",
    "sg:city":"Marche-en-famenne",
    "sg:classifiers":[
        {
            "category":"Retail",
            "subcategory":"Auto Repair",
            "type":"Services"
        }
    ],
    "sg:phone":"+32 84 31 21 26",
    "sg:postcode":"6900",
    "sg:province":"Luxembourg",
    "sg:tags":[
        "garage"
    ],
    "wof:name":"Garage Houyoux J & Fils",
    "wof:placetype":"venue"
},
  "geometry": {"coordinates":[5.329390049,50.2111358643],"type":"Point"}
}