{
  "type": "Feature",
  "properties": {
    "iso:country":"BE",
    "sg:address":"Rechtstraat 26",
    "sg:city":"Gent (desteldonk)",
    "sg:classifiers":[
        {
            "category":"Banks & Credit Unions",
            "subcategory":"Bank",
            "type":"Services"
        }
    ],
    "sg:phone":"+32 9 355 73 56",
    "sg:postcode":"9042",
    "sg:province":"Oost-Vlaanderen",
    "sg:tags":[
        "savings-banks"
    ],
    "wof:name":"Van Der Cruyssen",
    "wof:placetype":"venue"
},
  "geometry": {"coordinates":[3.7816700935,51.1223831177],"type":"Point"}
}