{
  "type": "Feature",
  "properties": {
    "iso:country":"BE",
    "sg:address":"Rue Am\u00c9ricaine 61-65",
    "sg:city":"Bruxelles-ixelles",
    "sg:orig_category":"Mat\u00e9riel de T\u00e9l\u00e9communication",
    "sg:phone":"+32 2 538 29 80",
    "sg:postcode":"1050",
    "sg:province":"Bruxelles-Capitale",
    "wof:name":"Arwac",
    "wof:placetype":"venue"
},
  "geometry": {"coordinates":[4.3576860428,50.8235092163],"type":"Point"}
}