{
  "type": "Feature",
  "properties": {
    "addr:full":"Wijngaardstraat 13 Box B Grobbendonk Antwerpen 2280",
    "addr:housenumber":"13 box b",
    "addr:postcode":"2280",
    "addr:street":"Wijngaardstraat",
    "iso:country":"BE",
    "sg:address":"Wijngaardstraat 13 Box B",
    "sg:city":"Grobbendonk",
    "sg:classifiers":[
        {
            "category":"Building & Trades",
            "subcategory":"Cleaning & Sanitation",
            "type":"Services"
        }
    ],
    "sg:phone":"+32 14 51 36 80",
    "sg:postcode":"2280",
    "sg:province":"Antwerpen",
    "sg:tags":[
        "fa\u00e7ade",
        "maintenance"
    ],
    "wof:name":"Cambre H",
    "wof:placetype":"venue"
},
  "geometry": {"coordinates":[4.7386469841,51.188659668],"type":"Point"}
}