{
  "type": "Feature",
  "properties": {
    "iso:country":"BE",
    "sg:address":"Dorpsweg 3",
    "sg:city":"Malle",
    "sg:orig_category":"Assurances. G\u00e9om\u00e8tres",
    "sg:phone":"+32 3 312 07 58",
    "sg:postcode":"2390",
    "sg:province":"Antwerpen",
    "wof:name":"De Vrij",
    "wof:placetype":"venue"
},
  "geometry": {"coordinates":[4.7322239876,51.3018722534],"type":"Point"}
}