{
  "type": "Feature",
  "properties": {
    "iso:country":"BE",
    "sg:address":"Sint-bernardse Steenweg 100",
    "sg:city":"Hemiksem",
    "sg:classifiers":[
        {
            "category":"Professional",
            "subcategory":"Lawyer & Legal Services",
            "type":"Services"
        }
    ],
    "sg:phone":"+32 3 887 45 09",
    "sg:postcode":"2620",
    "sg:province":"Antwerpen",
    "sg:tags":[
        "notary"
    ],
    "wof:name":"Hellemans H",
    "wof:placetype":"venue"
},
  "geometry": {"coordinates":[4.3352060318,51.1314849854],"type":"Point"}
}