{
  "type": "Feature",
  "properties": {
    "addr:full":"Place Des Tilleuls 1 Andenne Namur 5300",
    "addr:housenumber":"1",
    "addr:postcode":"5300",
    "addr:street":"Place Des Tilleuls",
    "iso:country":"BE",
    "sg:address":"Place Des Tilleuls 1",
    "sg:city":"Andenne",
    "sg:orig_category":"Opvangtehuizen and vluchthuizen",
    "sg:phone":"+32 85 84 10 57",
    "sg:postcode":"5300",
    "sg:province":"Namur",
    "wof:name":"A.c.t.e.",
    "wof:placetype":"venue"
},
  "geometry": {"coordinates":[5.0971498489,50.489238739],"type":"Point"}
}