{
  "type": "Feature",
  "properties": {
    "addr:full":"Hoogleedsesteenweg 91 Roeselare West-Vlaanderen 8800",
    "addr:housenumber":"91",
    "addr:postcode":"8800",
    "addr:street":"Hoogleedsesteenweg",
    "iso:country":"BE",
    "sg:address":"Hoogleedsesteenweg 91",
    "sg:city":"Roeselare",
    "sg:orig_category":"Kapsalons",
    "sg:phone":"+32 51 22 81 73",
    "sg:postcode":"8800",
    "sg:province":"West-Vlaanderen",
    "wof:name":"Coiffure Chelsea",
    "wof:placetype":"venue"
},
  "geometry": {"coordinates":[3.117413044,50.952671051],"type":"Point"}
}