{
  "type": "Feature",
  "properties": {
    "iso:country":"BE",
    "sg:address":"Rue Emile Vandervelde 96",
    "sg:city":"Fleron",
    "sg:orig_category":"Epiceries",
    "sg:phone":"+32 4 355 11 66",
    "sg:postcode":"4624",
    "sg:province":"Li\u00e8ge",
    "wof:name":"Alain Burnet",
    "wof:placetype":"venue"
},
  "geometry": {"coordinates":[5.6716690063,50.6120033264],"type":"Point"}
}