{
  "type": "Feature",
  "properties": {
    "addr:full":"Chauss\u00c9e De Louvain 61 Eghez\u00c9e Namur 5310",
    "addr:housenumber":"61",
    "addr:postcode":"5310",
    "addr:street":"Chausse\u0301E De Louvain",
    "iso:country":"BE",
    "sg:address":"Chauss\u00c9e De Louvain 61",
    "sg:city":"Eghez\u00c9e",
    "sg:orig_category":"Avocats and conseillers juridiques",
    "sg:phone":"+32 81 81 32 77",
    "sg:postcode":"5310",
    "sg:province":"Namur",
    "wof:name":"C. Crappe",
    "wof:placetype":"venue"
},
  "geometry": {"coordinates":[4.9084458351,50.5951805115],"type":"Point"}
}