{
  "type": "Feature",
  "properties": {
    "iso:country":"BE",
    "sg:address":"Rue Emile Muselle 15",
    "sg:city":"Berloz",
    "sg:classifiers":[
        {
            "category":"Farming",
            "subcategory":"Farm & Veterinary Services",
            "type":"Manufacturing & Wholesale Goods"
        }
    ],
    "sg:phone":"+32 19 32 20 82",
    "sg:postcode":"4257",
    "sg:province":"Li\u00e8ge",
    "sg:tags":[
        "agricultural",
        "contractor"
    ],
    "wof:name":"Robert G",
    "wof:placetype":"venue"
},
  "geometry": {"coordinates":[5.2110648155,50.700881958],"type":"Point"}
}