{
  "type": "Feature",
  "properties": {
    "addr:full":"Warotstraat 29 Herent Vlaams-Brabant 3020",
    "addr:housenumber":"29",
    "addr:postcode":"3020",
    "addr:street":"Warotstraat",
    "iso:country":"BE",
    "sg:address":"Warotstraat 29",
    "sg:city":"Herent",
    "sg:orig_category":"Artsen and specialisten",
    "sg:phone":"+32 16 48 00 95",
    "sg:postcode":"3020",
    "sg:province":"Vlaams-Brabant",
    "wof:name":"D. Hermans",
    "wof:placetype":"venue"
},
  "geometry": {"coordinates":[4.6749200821,50.9079055786],"type":"Point"}
}