{
  "type": "Feature",
  "properties": {
    "addr:full":"Barzestraat 23 Harelbeke West-Vlaanderen 8531",
    "addr:housenumber":"23",
    "addr:postcode":"8531",
    "addr:street":"Barzestraat",
    "iso:country":"BE",
    "sg:address":"Barzestraat 23",
    "sg:city":"Harelbeke",
    "sg:orig_category":"Herstellingen and onderhoud van auto's",
    "sg:phone":"+32 56 66 89 88",
    "sg:postcode":"8531",
    "sg:province":"West-Vlaanderen",
    "wof:name":"Ambucar",
    "wof:placetype":"venue"
},
  "geometry": {"coordinates":[3.2774190903,50.8930282593],"type":"Point"}
}