{
  "type": "Feature",
  "properties": {
    "iso:country":"BE",
    "sg:address":"Leuvense Steenweg 10",
    "sg:city":"Boortmeerbeek (hever)",
    "sg:classifiers":[
        {
            "category":"Insurance",
            "subcategory":"Insurance Agent",
            "type":"Services"
        }
    ],
    "sg:phone":"+32 15 52 04 54",
    "sg:postcode":"3191",
    "sg:province":"Vlaams-Brabant",
    "sg:tags":[
        "broker"
    ],
    "wof:name":"Van Campenhout Wim Bvba",
    "wof:placetype":"venue"
},
  "geometry": {"coordinates":[4.5334200859,50.9937095642],"type":"Point"}
}