{
  "type": "Feature",
  "properties": {
    "addr:full":"Boulevard Leopold Ii 75 Bruxelles (molenbeek-saint-jean) Bruxelles-Capitale 1080",
    "addr:housenumber":"75",
    "addr:postcode":"1080",
    "addr:street":"Boulevard Leopold Ii",
    "iso:country":"BE",
    "sg:address":"Boulevard Leopold Ii 75",
    "sg:city":"Bruxelles (molenbeek-saint-jean)",
    "sg:classifiers":[
        {
            "category":"Professional",
            "subcategory":"Testing Lab",
            "type":"Services"
        }
    ],
    "sg:phone":"+32 2 426 09 01",
    "sg:postcode":"1080",
    "sg:province":"Bruxelles-Capitale",
    "sg:tags":[
        "chemist"
    ],
    "wof:name":"Karahisarli Y",
    "wof:placetype":"venue"
},
  "geometry": {"coordinates":[4.3413381577,50.8604011536],"type":"Point"}
}