{
  "type": "Feature",
  "properties": {
    "addr:full":"Rue De La Station 17 Lobbes Hainaut 6540",
    "addr:housenumber":"17",
    "addr:postcode":"6540",
    "addr:street":"Rue De La Station",
    "iso:country":"BE",
    "sg:address":"Rue De La Station 17",
    "sg:city":"Lobbes",
    "sg:orig_category":"Opvangtehuizen and vluchthuizen",
    "sg:phone":"+32 71 59 96 65",
    "sg:postcode":"6540",
    "sg:province":"Hainaut",
    "wof:name":"Centre De Service Social",
    "wof:placetype":"venue"
},
  "geometry": {"coordinates":[4.2624440193,50.3456001282],"type":"Point"}
}