{
  "type": "Feature",
  "properties": {
    "iso:country":"BE",
    "sg:address":"Rue Des Pr\u00c9s 1",
    "sg:city":"Braine-le-comte",
    "sg:orig_category":"Eleveurs de bovins",
    "sg:phone":"+32 67 63 78 76",
    "sg:postcode":"7090",
    "sg:province":"Hainaut",
    "wof:name":"Noel Termotte",
    "wof:placetype":"venue"
},
  "geometry": {"coordinates":[4.095085144,50.6619224548],"type":"Point"}
}