{
  "type": "Feature",
  "properties": {
    "addr:full":"Zandpoortvest 39 Mechelen Antwerpen 2800",
    "addr:housenumber":"39",
    "addr:postcode":"2800",
    "addr:street":"Zandpoortvest",
    "iso:country":"BE",
    "sg:address":"Zandpoortvest 39",
    "sg:city":"Mechelen",
    "sg:classifiers":[
        {
            "category":"Bars & Pubs",
            "type":"Food & Drink"
        }
    ],
    "sg:phone":"+32 15 33 13 75",
    "sg:postcode":"2800",
    "sg:province":"Antwerpen",
    "wof:name":"Student (de)",
    "wof:placetype":"venue"
},
  "geometry": {"coordinates":[4.4876561165,51.0240974426],"type":"Point"}
}