{
  "type": "Feature",
  "properties": {
    "addr:full":"Rue De Borlon 8 Somme-leuze Namur 5377",
    "addr:housenumber":"8",
    "addr:postcode":"5377",
    "addr:street":"Rue De Borlon",
    "iso:country":"BE",
    "sg:address":"Rue De Borlon 8",
    "sg:city":"Somme-leuze",
    "sg:orig_category":"Installation de menuiserie en bois and plastique",
    "sg:phone":"+32 86 34 40 57",
    "sg:postcode":"5377",
    "sg:province":"Namur",
    "wof:name":"Luc Dodet",
    "wof:placetype":"venue"
},
  "geometry": {"coordinates":[5.3698949814,50.3404350281],"type":"Point"}
}