{
  "type": "Feature",
  "properties": {
    "addr:full":"Sentier De La Meunerie 58 Hannut Li\u00e8ge 4280",
    "addr:housenumber":"58",
    "addr:postcode":"4280",
    "addr:street":"Sentier De La Meunerie",
    "iso:country":"BE",
    "sg:address":"Sentier De La Meunerie 58",
    "sg:city":"Hannut",
    "sg:orig_category":"Vakantiehuizen",
    "sg:phone":"+32 19 69 92 39",
    "sg:postcode":"4280",
    "sg:province":"Li\u00e8ge",
    "wof:name":"Moulin De Moxhe",
    "wof:placetype":"venue"
},
  "geometry": {"coordinates":[5.0599031448,50.6288986206],"type":"Point"}
}