{
  "type": "Feature",
  "properties": {
    "iso:country":"BE",
    "sg:address":"Rue Du Pont Du Christ 12",
    "sg:city":"Wavre",
    "sg:orig_category":"Rev\u00eatements de sols and murs",
    "sg:phone":"+32 10 22 22 22",
    "sg:postcode":"1300",
    "sg:province":"Brabant Wallon",
    "wof:name":"Maison Sadra\u00c9e",
    "wof:placetype":"venue"
},
  "geometry": {"coordinates":[4.6102437973,50.7151222229],"type":"Point"}
}