{
  "type": "Feature",
  "properties": {
    "iso:country":"BE",
    "sg:address":"Hofveldstraat 51",
    "sg:city":"Maarkedal",
    "sg:orig_category":"Banques and organismes de cr\u00e9dit",
    "sg:phone":"+32 55 45 61 34",
    "sg:postcode":"9688",
    "sg:province":"Oost-Vlaanderen",
    "wof:name":"Kbc",
    "wof:placetype":"venue"
},
  "geometry": {"coordinates":[3.6761569977,50.8026161194],"type":"Point"}
}