{
  "type": "Feature",
  "properties": {
    "addr:full":"Chemin \u00c0 Rocs 29 Soignies Hainaut 7060",
    "addr:housenumber":"29",
    "addr:postcode":"7060",
    "addr:street":"Chemin A\u0300 Rocs",
    "iso:country":"BE",
    "sg:address":"Chemin \u00c0 Rocs 29",
    "sg:city":"Soignies",
    "sg:orig_category":"Rundveehouders",
    "sg:phone":"+32 67 33 03 77",
    "sg:postcode":"7060",
    "sg:province":"Hainaut",
    "wof:name":"Francois Schneiders",
    "wof:placetype":"venue"
},
  "geometry": {"coordinates":[4.0724000931,50.5779037476],"type":"Point"}
}