{
  "type": "Feature",
  "properties": {
    "addr:full":"Zilverbergstraat 37 Moorslede West-Vlaanderen 8890",
    "addr:housenumber":"37",
    "addr:postcode":"8890",
    "addr:street":"Zilverbergstraat",
    "iso:country":"BE",
    "sg:address":"Zilverbergstraat 37",
    "sg:city":"Moorslede",
    "sg:orig_category":"Installatie van houten of kunststof schrijnwerk",
    "sg:phone":"+32 51 77 26 26",
    "sg:postcode":"8890",
    "sg:province":"West-Vlaanderen",
    "wof:name":"Ramen Lesage Jan",
    "wof:placetype":"venue"
},
  "geometry": {"coordinates":[3.092895031,50.9119529724],"type":"Point"}
}