{
  "type": "Feature",
  "properties": {
    "addr:full":"Volkslaan 41 Menen West-Vlaanderen 8930",
    "addr:housenumber":"41",
    "addr:postcode":"8930",
    "addr:street":"Volkslaan",
    "iso:country":"BE",
    "sg:address":"Volkslaan 41",
    "sg:city":"Menen",
    "sg:classifiers":[
        {
            "category":"Taxi",
            "type":"Transportation"
        }
    ],
    "sg:phone":"+32 56 51 22 41",
    "sg:postcode":"8930",
    "sg:province":"West-Vlaanderen",
    "wof:name":"Taxi Claude",
    "wof:placetype":"venue"
},
  "geometry": {"coordinates":[3.1168138981,50.8063354492],"type":"Point"}
}