{
  "type": "Feature",
  "properties": {
    "addr:full":"Rue Des Amuges 30 Farciennes Hainaut 6240",
    "addr:housenumber":"30",
    "addr:postcode":"6240",
    "addr:street":"Rue Des Amuges",
    "iso:country":"BE",
    "sg:address":"Rue Des Amuges 30",
    "sg:city":"Farciennes",
    "sg:classifiers":[
        {
            "category":"Arena",
            "subcategory":"Sports Club",
            "type":"Entertainment"
        }
    ],
    "sg:phone":"+32 71 39 34 39",
    "sg:postcode":"6240",
    "sg:province":"Hainaut",
    "sg:tags":[
        "de"
    ],
    "wof:name":"Tra\u00cene-savates Mon.s.sam.",
    "wof:placetype":"venue"
},
  "geometry": {"coordinates":[4.5375061035,50.4279899597],"type":"Point"}
}