{
  "type": "Feature",
  "properties": {
    "addr:full":"Meersstraat 180 Destelbergen (heusden) Oost-Vlaanderen 9070",
    "addr:housenumber":"180",
    "addr:postcode":"9070",
    "addr:street":"Meersstraat",
    "iso:country":"BE",
    "sg:address":"Meersstraat 180",
    "sg:city":"Destelbergen (heusden)",
    "sg:classifiers":[
        {
            "category":"Retail",
            "subcategory":"Auto Repair",
            "type":"Services"
        }
    ],
    "sg:phone":"+32 9 230 62 87",
    "sg:postcode":"9070",
    "sg:province":"Oost-Vlaanderen",
    "sg:tags":[
        "garage"
    ],
    "wof:name":"Raman M",
    "wof:placetype":"venue"
},
  "geometry": {"coordinates":[3.7952749729,51.0432701111],"type":"Point"}
}