{
  "type": "Feature",
  "properties": {
    "addr:full":"Ringlaan 23 Houthalen-helchteren Limburg 3530",
    "addr:housenumber":"23",
    "addr:postcode":"3530",
    "addr:street":"Ringlaan",
    "iso:country":"BE",
    "sg:address":"Ringlaan 23",
    "sg:city":"Houthalen-helchteren",
    "sg:orig_category":"Loodgieterij, verwarming and sanitaire installaties",
    "sg:phone":"+32 11 52 55 87",
    "sg:postcode":"3530",
    "sg:province":"Limburg",
    "wof:name":"Marsili Gebrs",
    "wof:placetype":"venue"
},
  "geometry": {"coordinates":[5.3804411888,51.0320777893],"type":"Point"}
}