{
  "type": "Feature",
  "properties": {
    "iso:country":"BE",
    "sg:address":"Remichampagne 41",
    "sg:city":"Vaux-sur-sure",
    "sg:orig_category":"Eleveurs de bovins",
    "sg:phone":"+32 61 26 62 21",
    "sg:postcode":"6640",
    "sg:province":"Luxembourg",
    "wof:name":"Lambert P. & Lambert G.",
    "wof:placetype":"venue"
},
  "geometry": {"coordinates":[5.6407427788,49.9376029968],"type":"Point"}
}