{
  "type": "Feature",
  "properties": {
    "addr:full":"Rue De La Lib\u00c9ration 59 Rochefort Namur 5580",
    "addr:housenumber":"59",
    "addr:postcode":"5580",
    "addr:street":"Rue De La Libe\u0301Ration",
    "iso:country":"BE",
    "sg:address":"Rue De La Lib\u00c9ration 59",
    "sg:city":"Rochefort",
    "sg:orig_category":"Catering and organisatie van feesten Fast food and meeneem restaurants Restaurants",
    "sg:phone":"+32 84 21 26 53",
    "sg:postcode":"5580",
    "sg:province":"Namur",
    "wof:name":"La Porte Des Ardennes",
    "wof:placetype":"venue"
},
  "geometry": {"coordinates":[5.2117199898,50.1658592224],"type":"Point"}
}