{
  "type": "Feature",
  "properties": {
    "iso:country":"BE",
    "sg:address":"Stokeikstraat 18",
    "sg:city":"Genk (waterschei)",
    "sg:classifiers":[
        {
            "category":"Insurance",
            "subcategory":"Insurance Agent",
            "type":"Services"
        }
    ],
    "sg:phone":"+32 89 38 55 14",
    "sg:postcode":"3600",
    "sg:province":"Limburg",
    "sg:tags":[
        "broker"
    ],
    "wof:name":"Wetzels P",
    "wof:placetype":"venue"
},
  "geometry": {"coordinates":[5.4935188293,51.016418457],"type":"Point"}
}