{
  "type": "Feature",
  "properties": {
    "iso:country":"BE",
    "sg:address":"Halleweg 1ba",
    "sg:city":"Halle",
    "sg:orig_category":"M\u00e9decins and sp\u00e9cialistes",
    "sg:phone":"+32 2 361 16 50",
    "sg:postcode":"1500",
    "sg:province":"Vlaams-Brabant",
    "wof:name":"Consultatiebur.jonge Kind",
    "wof:placetype":"venue"
},
  "geometry": {"coordinates":[4.2434039116,50.7288246155],"type":"Point"}
}