{
  "type": "Feature",
  "properties": {
    "iso:country":"BE",
    "sg:address":"Rue Albert 37",
    "sg:city":"Tournai",
    "sg:orig_category":"Chaussures",
    "sg:phone":"+32 69 22 25 86",
    "sg:postcode":"7540",
    "sg:province":"Hainaut",
    "wof:name":"Rita Dumoulin",
    "wof:placetype":"venue"
},
  "geometry": {"coordinates":[3.3906190395,50.6246452332],"type":"Point"}
}