{
  "type": "Feature",
  "properties": {
    "addr:full":"Rue De La Clef 1 Fleron Li\u00e8ge 4621",
    "addr:housenumber":"1",
    "addr:postcode":"4621",
    "addr:street":"Rue De La Clef",
    "iso:country":"BE",
    "sg:address":"Rue De La Clef 1",
    "sg:city":"Fleron",
    "sg:classifiers":[
        {
            "category":"Fast Food",
            "type":"Food & Drink"
        }
    ],
    "sg:phone":"+32 4 355 09 09",
    "sg:postcode":"4621",
    "sg:province":"Li\u00e8ge",
    "sg:tags":[
        "meeneem",
        "restaurant"
    ],
    "wof:name":"Quick",
    "wof:placetype":"venue"
},
  "geometry": {"coordinates":[5.6880822182,50.6147499084],"type":"Point"}
}