{
  "type": "Feature",
  "properties": {
    "addr:full":"Chauss\u00c9e De Dinant 2 Profondeville Namur 5170",
    "addr:housenumber":"2",
    "addr:postcode":"5170",
    "addr:street":"Chausse\u0301E De Dinant",
    "iso:country":"BE",
    "sg:address":"Chauss\u00c9e De Dinant 2",
    "sg:city":"Profondeville",
    "sg:classifiers":[
        {
            "category":"Health Services",
            "subcategory":"Nursing And Care Facility",
            "type":"Services"
        }
    ],
    "sg:phone":"+32 81 42 02 10",
    "sg:postcode":"5170",
    "sg:province":"Namur",
    "sg:tags":[
        "public"
    ],
    "wof:name":"Administration Communale",
    "wof:placetype":"venue"
},
  "geometry": {"coordinates":[4.8689570427,50.3777542114],"type":"Point"}
}