{
  "type": "Feature",
  "properties": {
    "iso:country":"BE",
    "sg:address":"Rue De S\u00e9vign\u00e9 1a",
    "sg:city":"Bruxelles (anderlecht)",
    "sg:classifiers":[
        {
            "category":"Social Services",
            "type":"Services"
        }
    ],
    "sg:phone":"+32 2 523 08 71",
    "sg:postcode":"1070",
    "sg:province":"Bruxelles-Capitale",
    "wof:name":"Cercle D'education Physique & Morale De Moortebeek",
    "wof:placetype":"venue"
},
  "geometry": {"coordinates":[4.2907419205,50.8450508118],"type":"Point"}
}