{
  "type": "Feature",
  "properties": {
    "addr:full":"A. Mervilliestraat 11 Zedelgem (aartrijke) West-Vlaanderen 8211",
    "addr:housenumber":"11",
    "addr:postcode":"8211",
    "addr:street":"Mervilliestraat",
    "iso:country":"BE",
    "sg:address":"A. Mervilliestraat 11",
    "sg:city":"Zedelgem (aartrijke)",
    "sg:classifiers":[
        {
            "category":"Social Services",
            "subcategory":"Child Care",
            "type":"Services"
        }
    ],
    "sg:phone":"+32 50 20 04 72",
    "sg:postcode":"8211",
    "sg:province":"West-Vlaanderen",
    "sg:tags":[
        "baby",
        "nursery",
        "day",
        "sitting"
    ],
    "wof:name":"Kaboutertje('t)",
    "wof:placetype":"venue"
},
  "geometry": {"coordinates":[3.0889649391,51.1200408936],"type":"Point"}
}