{
  "type": "Feature",
  "properties": {
    "iso:country":"BE",
    "sg:address":"Kroonstraat 82",
    "sg:city":"Beringen (beverlo)",
    "sg:classifiers":[
        {
            "category":"Food & Beverages",
            "subcategory":"Groceries & Convenience Stores",
            "type":"Retail Goods"
        }
    ],
    "sg:phone":"+32 11 40 31 79",
    "sg:postcode":"3581",
    "sg:province":"Limburg",
    "sg:tags":[
        "grocer"
    ],
    "wof:name":"Winkeltje ('t)",
    "wof:placetype":"venue"
},
  "geometry": {"coordinates":[5.2681798935,51.0915412903],"type":"Point"}
}