{
  "type": "Feature",
  "properties": {
    "addr:full":"Nieuwstraat 1 Haacht (wespelaar) Vlaams-Brabant 3150",
    "addr:housenumber":"1",
    "addr:postcode":"3150",
    "addr:street":"Nieuwstraat",
    "iso:country":"BE",
    "sg:address":"Nieuwstraat 1",
    "sg:city":"Haacht (wespelaar)",
    "sg:classifiers":[
        {
            "category":"Social Services",
            "subcategory":"Child Care",
            "type":"Services"
        }
    ],
    "sg:phone":"+32 16 60 00 30",
    "sg:postcode":"3150",
    "sg:province":"Vlaams-Brabant",
    "sg:tags":[
        "baby",
        "nursery",
        "day",
        "sitting"
    ],
    "wof:name":"Het Wespennestje Vzw",
    "wof:placetype":"venue"
},
  "geometry": {"coordinates":[4.6328611374,50.9593238831],"type":"Point"}
}