{
  "type": "Feature",
  "properties": {
    "addr:full":"Boulevard De Waterloo 90 Bruxelles Bruxelles-Capitale 1000",
    "addr:housenumber":"90",
    "addr:postcode":"1000",
    "addr:street":"Boulevard De Waterloo",
    "iso:country":"BE",
    "sg:address":"Boulevard De Waterloo 90",
    "sg:city":"Bruxelles",
    "sg:classifiers":[
        {
            "category":"Professional",
            "subcategory":"Engineering",
            "type":"Services"
        }
    ],
    "sg:phone":"+32 2 511 03 03",
    "sg:postcode":"1000",
    "sg:province":"Bruxelles-Capitale",
    "sg:tags":[
        "-"
    ],
    "wof:name":"Mens & Ruimte Nv",
    "wof:placetype":"venue"
},
  "geometry": {"coordinates":[4.3512392044,50.8346366882],"type":"Point"}
}