{
  "type": "Feature",
  "properties": {
    "iso:country":"BE",
    "sg:address":"Hamsestraat 11",
    "sg:city":"Balen",
    "sg:classifiers":[
        {
            "category":"Personal",
            "subcategory":"Beauty Salon",
            "type":"Services"
        }
    ],
    "sg:phone":"+32 11 34 35 77",
    "sg:postcode":"2491",
    "sg:province":"Antwerpen",
    "sg:tags":[
        "de",
        "coiffure"
    ],
    "wof:name":"Hilde Regout",
    "wof:placetype":"venue"
},
  "geometry": {"coordinates":[5.1800198555,51.1289253235],"type":"Point"}
}