{
  "type": "Feature",
  "properties": {
    "iso:country":"BE",
    "sg:address":"Kokkelbeekstraat 43",
    "sg:city":"Sint-niklaas",
    "sg:orig_category":"Disneyland Paris. Agences de voyages",
    "sg:phone":"+32 3 776 38 95",
    "sg:postcode":"9100",
    "sg:province":"Oost-Vlaanderen",
    "wof:name":"V.t.b.",
    "wof:placetype":"venue"
},
  "geometry": {"coordinates":[4.1417908669,51.1622238159],"type":"Point"}
}