{
  "type": "Feature",
  "properties": {
    "addr:full":"Oude Eekhoutstraat 4 Ardooie West-Vlaanderen 8850",
    "addr:housenumber":"4",
    "addr:postcode":"8850",
    "addr:street":"Oude Eekhoutstraat",
    "iso:country":"BE",
    "sg:address":"Oude Eekhoutstraat 4",
    "sg:city":"Ardooie",
    "sg:classifiers":[
        {
            "category":"Home & Garden",
            "subcategory":"Building Materials",
            "type":"Retail Goods"
        }
    ],
    "sg:phone":"+32 51 74 47 83",
    "sg:postcode":"8850",
    "sg:province":"West-Vlaanderen",
    "sg:tags":[
        "window"
    ],
    "wof:name":"Alu-decock Bvba",
    "wof:placetype":"venue"
},
  "geometry": {"coordinates":[3.2005279064,50.9810752869],"type":"Point"}
}