{
  "type": "Feature",
  "properties": {
    "iso:country":"BE",
    "sg:address":"Paleisstraat 146",
    "sg:city":"Antwerpen",
    "sg:classifiers":[
        {
            "category":"Fast Food",
            "type":"Food & Drink"
        }
    ],
    "sg:phone":"+32 3 238 34 85",
    "sg:postcode":"2018",
    "sg:province":"Antwerpen",
    "sg:tags":[
        "meeneem",
        "restaurant"
    ],
    "wof:name":"Rapido",
    "wof:placetype":"venue"
},
  "geometry": {"coordinates":[4.3959708214,51.2047615051],"type":"Point"}
}