{
  "type": "Feature",
  "properties": {
    "iso:country":"BE",
    "sg:address":"Molenstraat 27a",
    "sg:city":"Scherpenheuvel-zichem (scherpenheuvel)",
    "sg:classifiers":[
        {
            "category":"Home & Garden",
            "subcategory":"Carpets & Floor Coverings",
            "type":"Retail Goods"
        }
    ],
    "sg:phone":"+32 13 78 40 01",
    "sg:postcode":"3270",
    "sg:province":"Vlaams-Brabant",
    "sg:tags":[
        "parquet"
    ],
    "wof:name":"Parkethuis (het) Interieurschrijnwerkerij",
    "wof:placetype":"venue"
},
  "geometry": {"coordinates":[4.9790902138,50.9785232544],"type":"Point"}
}