{
  "type": "Feature",
  "properties": {
    "iso:country":"BE",
    "sg:address":"Karel Van Lotharingenstraat 4",
    "sg:city":"Leuven",
    "sg:classifiers":[
        {
            "category":"Real Estate",
            "subcategory":"Surveying",
            "type":"Services"
        }
    ],
    "sg:phone":"+32 16 20 41 98",
    "sg:postcode":"3000",
    "sg:province":"Vlaams-Brabant",
    "sg:tags":[
        "surveyor",
        "land"
    ],
    "wof:name":"Casier Patrick Studiebureau Bvba",
    "wof:placetype":"venue"
},
  "geometry": {"coordinates":[4.6999897957,50.8822975159],"type":"Point"}
}