{
  "type": "Feature",
  "properties": {
    "addr:full":"Bargelaan 12 Beernem West-Vlaanderen 8730",
    "addr:housenumber":"12",
    "addr:postcode":"8730",
    "addr:street":"Bargelaan",
    "iso:country":"BE",
    "sg:address":"Bargelaan 12",
    "sg:city":"Beernem",
    "sg:orig_category":"Enseignement maternel and primaire",
    "sg:phone":"+32 50 78 83 07",
    "sg:postcode":"8730",
    "sg:province":"West-Vlaanderen",
    "wof:name":"Vrije Lagere School",
    "wof:placetype":"venue"
},
  "geometry": {"coordinates":[3.3389499187,51.1367988586],"type":"Point"}
}