{
  "type": "Feature",
  "properties": {
    "iso:country":"BE",
    "sg:address":"Brusselstraat 63",
    "sg:city":"Ninove",
    "sg:orig_category":"Apotheken",
    "sg:phone":"+32 54 33 37 80",
    "sg:postcode":"9400",
    "sg:province":"Oost-Vlaanderen",
    "wof:name":"Van Gyseghem",
    "wof:placetype":"venue"
},
  "geometry": {"coordinates":[4.0246300697,50.8284378052],"type":"Point"}
}