{
  "type": "Feature",
  "properties": {
    "addr:full":"Leugstraat 48 Aartselaar Antwerpen 2630",
    "addr:housenumber":"48",
    "addr:postcode":"2630",
    "addr:street":"Leugstraat",
    "iso:country":"BE",
    "sg:address":"Leugstraat 48",
    "sg:city":"Aartselaar",
    "sg:orig_category":"Installation \u00e9lectrique r\u00e9sidentielle",
    "sg:phone":"+32 475 36 06 79",
    "sg:postcode":"2630",
    "sg:province":"Antwerpen",
    "wof:name":"Elektro Gode",
    "wof:placetype":"venue"
},
  "geometry": {"coordinates":[4.3793911934,51.1315536499],"type":"Point"}
}