{
  "type": "Feature",
  "properties": {
    "iso:country":"BE",
    "sg:address":"Kasteelstraat 93-95",
    "sg:city":"Roeselare",
    "sg:orig_category":"Non-Classified Establishments",
    "sg:phone":"+32 51 24 08 84",
    "sg:postcode":"8800",
    "sg:province":"West-Vlaanderen",
    "wof:name":"Beeusaert",
    "wof:placetype":"venue"
},
  "geometry": {"coordinates":[3.1294589043,50.9329338074],"type":"Point"}
}