{
  "type": "Feature",
  "properties": {
    "iso:country":"BE",
    "sg:address":"Brugsestraat 167",
    "sg:city":"Ingelmunster",
    "sg:orig_category":"Royal Canin",
    "sg:phone":"+32 51 30 96 77",
    "sg:postcode":"8770",
    "sg:province":"West-Vlaanderen",
    "wof:name":"Supra Bazar",
    "wof:placetype":"venue"
},
  "geometry": {"coordinates":[3.2560250759,50.9203109741],"type":"Point"}
}