{
  "type": "Feature",
  "properties": {
    "addr:full":"Rue De Philippeville 18ba Hamois Namur 5360",
    "addr:housenumber":"18ba",
    "addr:postcode":"5360",
    "addr:street":"Rue De Philippeville",
    "iso:country":"BE",
    "sg:address":"Rue De Philippeville 18ba",
    "sg:city":"Hamois",
    "sg:orig_category":"Plomberie, chauffage and installations sanitaires",
    "sg:phone":"+32 83 61 26 15",
    "sg:postcode":"5360",
    "sg:province":"Namur",
    "wof:name":"Jean Coppens",
    "wof:placetype":"venue"
},
  "geometry": {"coordinates":[5.1768488884,50.3449554443],"type":"Point"}
}