{
  "type": "Feature",
  "properties": {
    "addr:full":"Dorp 20 Aalst Oost-Vlaanderen 9310",
    "addr:housenumber":"20",
    "addr:postcode":"9310",
    "addr:street":"Dorp",
    "iso:country":"BE",
    "sg:address":"Dorp 20",
    "sg:city":"Aalst",
    "sg:orig_category":"Banques and organismes de cr\u00e9dit",
    "sg:phone":"+32 53 77 95 02",
    "sg:postcode":"9310",
    "sg:province":"Oost-Vlaanderen",
    "wof:name":"Fortis",
    "wof:placetype":"venue"
},
  "geometry": {"coordinates":[4.098400116,50.9477767944],"type":"Point"}
}