{
  "type": "Feature",
  "properties": {
    "addr:full":"Rue Du March\u00c9 Aux Porcs 25 Brussel/bruxelles Bruxelles-Capitale 1000",
    "addr:housenumber":"25",
    "addr:postcode":"1000",
    "addr:street":"Rue Du Marche\u0301 Aux Porcs;/",
    "iso:country":"BE",
    "sg:address":"Rue Du March\u00c9 Aux Porcs 25",
    "sg:city":"Brussel/bruxelles",
    "sg:classifiers":[
        {
            "category":"Fast Food",
            "type":"Food & Drink"
        }
    ],
    "sg:phone":"+32 2 513 02 87",
    "sg:postcode":"1000",
    "sg:province":"Bruxelles-Capitale",
    "sg:tags":[
        "restaurant",
        "\u00c0",
        "domicile",
        "emporter",
        "livraison",
        "restaurants"
    ],
    "wof:name":"Au Cheval Marin",
    "wof:placetype":"venue"
},
  "geometry": {"coordinates":[4.3464488983,50.8535346985],"type":"Point"}
}