{
  "type": "Feature",
  "properties": {
    "addr:full":"Herentalse Steenweg 79 Grobbendonk Antwerpen 2280",
    "addr:housenumber":"79",
    "addr:postcode":"2280",
    "addr:street":"Herentalse Steenweg",
    "iso:country":"BE",
    "sg:address":"Herentalse Steenweg 79",
    "sg:city":"Grobbendonk",
    "sg:classifiers":[
        {
            "category":"Retail",
            "subcategory":"Car Wash",
            "type":"Services"
        }
    ],
    "sg:phone":"+32 14 51 96 60",
    "sg:postcode":"2280",
    "sg:province":"Antwerpen",
    "sg:tags":[
        "automobile",
        "washing",
        "-",
        "truck"
    ],
    "wof:name":"Octopus Soft-wash",
    "wof:placetype":"venue"
},
  "geometry": {"coordinates":[4.7669401169,51.1770210266],"type":"Point"}
}