{
  "type": "Feature",
  "properties": {
    "addr:full":"Avenue L\u00e9on Jouret 27-29 Ath Hainaut 7800",
    "addr:housenumber":"27-29",
    "addr:postcode":"7800",
    "addr:street":"Avenue Le\u0301On Jouret",
    "iso:country":"BE",
    "sg:address":"Avenue L\u00e9on Jouret 27-29",
    "sg:city":"Ath",
    "sg:classifiers":[
        {
            "category":"Health Services",
            "subcategory":"Doctor",
            "type":"Services"
        }
    ],
    "sg:phone":"+32 68 28 38 75",
    "sg:postcode":"7800",
    "sg:province":"Hainaut",
    "sg:tags":[
        "medicinephysicians",
        "surgeon"
    ],
    "wof:name":"Louant P-h",
    "wof:placetype":"venue"
},
  "geometry": {"coordinates":[3.7837779522,50.6345252991],"type":"Point"}
}