{
  "type": "Feature",
  "properties": {
    "addr:full":"Rijselstraat 137 Menen West-Vlaanderen 8930",
    "addr:housenumber":"137",
    "addr:postcode":"8930",
    "addr:street":"Rijselstraat",
    "iso:country":"BE",
    "sg:address":"Rijselstraat 137",
    "sg:city":"Menen",
    "sg:orig_category":"Benzinestations and brandstoffen HUISBRANDOLIE Onderdelen and accessoires voor auto's",
    "sg:phone":"+32 56 51 29 06",
    "sg:postcode":"8930",
    "sg:province":"West-Vlaanderen",
    "wof:name":"Auto Rallye Center",
    "wof:placetype":"venue"
},
  "geometry": {"coordinates":[3.1252810955,50.7902832031],"type":"Point"}
}