{
  "type": "Feature",
  "properties": {
    "addr:full":"Torteldreef 40 Keerbergen Vlaams-Brabant 3140",
    "addr:housenumber":"40",
    "addr:postcode":"3140",
    "addr:street":"Torteldreef",
    "iso:country":"BE",
    "sg:address":"Torteldreef 40",
    "sg:city":"Keerbergen",
    "sg:classifiers":[
        {
            "category":"Health Services",
            "subcategory":"Health Practitioner",
            "type":"Services"
        }
    ],
    "sg:phone":"+32 15 51 32 61",
    "sg:postcode":"3140",
    "sg:province":"Vlaams-Brabant",
    "sg:tags":[
        "physiotherapist"
    ],
    "wof:name":"Sijmus W",
    "wof:placetype":"venue"
},
  "geometry": {"coordinates":[4.6575880051,51.0053100586],"type":"Point"}
}