{
  "type": "Feature",
  "properties": {
    "iso:country":"BE",
    "sg:address":"Marktplein 9",
    "sg:city":"Kuurne",
    "sg:orig_category":"Offices du tourisme",
    "sg:phone":"+32 56 73 71 12",
    "sg:postcode":"8520",
    "sg:province":"West-Vlaanderen",
    "wof:name":"Dienst Voor Toerisme",
    "wof:placetype":"venue"
},
  "geometry": {"coordinates":[3.2872600555,50.8502311707],"type":"Point"}
}