{
  "type": "Feature",
  "properties": {
    "addr:full":"Louis Gribaumontlaan 99b1 Sint-lambrechts-woluwe/woluwe-saint-lambert Bruxelles-Capitale 1200",
    "addr:housenumber":"99b1",
    "addr:postcode":"1200",
    "addr:street":"Louis Gribaumontlaan",
    "iso:country":"BE",
    "sg:address":"Louis Gribaumontlaan 99b1",
    "sg:city":"Sint-lambrechts-woluwe/woluwe-saint-lambert",
    "sg:orig_category":"Bouwmaterialen Gh",
    "sg:phone":"+32 2 770 35 44",
    "sg:postcode":"1200",
    "sg:province":"Bruxelles-Capitale",
    "wof:name":"Insulco",
    "wof:placetype":"venue"
},
  "geometry": {"coordinates":[4.4170160294,50.8394088745],"type":"Point"}
}