{
  "type": "Feature",
  "properties": {
    "addr:full":"Rue Robert Schuman 24 Ans (alleur) Li\u00e8ge 4432",
    "addr:housenumber":"24",
    "addr:postcode":"4432",
    "addr:street":"Rue Robert Schuman",
    "iso:country":"BE",
    "sg:address":"Rue Robert Schuman 24",
    "sg:city":"Ans (alleur)",
    "sg:classifiers":[
        {
            "category":"Building & Trades",
            "subcategory":"Landscaping Services",
            "type":"Services"
        }
    ],
    "sg:phone":"+32 4 263 10 67",
    "sg:postcode":"4432",
    "sg:province":"Li\u00e8ge",
    "sg:tags":[
        "gardening",
        "garden",
        "maintenance"
    ],
    "wof:name":"Franquet P",
    "wof:placetype":"venue"
},
  "geometry": {"coordinates":[5.5115189552,50.6684951782],"type":"Point"}
}