{
  "type": "Feature",
  "properties": {
    "addr:full":"Diestsesteenweg 52 Box 8 Leuven (kessel-lo) Vlaams-Brabant 3010",
    "addr:housenumber":"52;8",
    "addr:postcode":"3010",
    "addr:street":"Diestsesteenweg;Box",
    "iso:country":"BE",
    "sg:address":"Diestsesteenweg 52 Box 8",
    "sg:city":"Leuven (kessel-lo)",
    "sg:classifiers":[
        {
            "category":"Social Services",
            "type":"Services"
        }
    ],
    "sg:phone":"+32 16 26 73 88",
    "sg:postcode":"3010",
    "sg:province":"Vlaams-Brabant",
    "wof:name":"Provinciaal Integratiecentrum Vlaams Brabant",
    "wof:placetype":"venue"
},
  "geometry": {"coordinates":[4.713447094,50.8832244873],"type":"Point"}
}