{
  "type": "Feature",
  "properties": {
    "iso:country":"BE",
    "sg:address":"Diksmuidse Boterweg 13",
    "sg:city":"Ardooie",
    "sg:orig_category":"M\u00e9decins and sp\u00e9cialistes",
    "sg:phone":"+32 51 74 68 20",
    "sg:postcode":"8851",
    "sg:province":"West-Vlaanderen",
    "wof:name":"Hilde Vandelanotte",
    "wof:placetype":"venue"
},
  "geometry": {"coordinates":[3.2073431015,51.0029716492],"type":"Point"}
}