{
  "type": "Feature",
  "properties": {
    "addr:full":"Grote Baan 153 Aalst Oost-Vlaanderen 9310",
    "addr:housenumber":"153",
    "addr:postcode":"9310",
    "addr:street":"Grote Baan",
    "iso:country":"BE",
    "sg:address":"Grote Baan 153",
    "sg:city":"Aalst",
    "sg:orig_category":"Airconditioning and ventilatie Elektrische installaties voor woningen Loodgieterij and centrale verw",
    "sg:phone":"+32 53 78 17 93",
    "sg:postcode":"9310",
    "sg:province":"Oost-Vlaanderen",
    "wof:name":"Everaert & Co",
    "wof:placetype":"venue"
},
  "geometry": {"coordinates":[4.0642561913,50.9684333801],"type":"Point"}
}