{
  "type": "Feature",
  "properties": {
    "iso:country":"BE",
    "sg:address":"Kortrijkstraat 467",
    "sg:city":"Menen",
    "sg:classifiers":[
        {
            "category":"Real Estate",
            "subcategory":"Architect",
            "type":"Services"
        }
    ],
    "sg:phone":"+32 56 53 20 04",
    "sg:postcode":"8930",
    "sg:province":"West-Vlaanderen",
    "wof:name":"Waegemans V",
    "wof:placetype":"venue"
},
  "geometry": {"coordinates":[3.1416840553,50.7993736267],"type":"Point"}
}