{
  "type": "Feature",
  "properties": {
    "addr:full":"Boulevard Louis Mettewie 71 Box 91 Bruxelles (molenbeek-saint-jean) Bruxelles-Capitale 1080",
    "addr:housenumber":"71 box 91",
    "addr:postcode":"1080",
    "addr:street":"Boulevard Louis Mettewie",
    "iso:country":"BE",
    "sg:address":"Boulevard Louis Mettewie 71 Box 91",
    "sg:city":"Bruxelles (molenbeek-saint-jean)",
    "sg:classifiers":[
        {
            "category":"Real Estate",
            "subcategory":"Architect",
            "type":"Services"
        }
    ],
    "sg:phone":"+32 2 469 40 35",
    "sg:postcode":"1080",
    "sg:province":"Bruxelles-Capitale",
    "wof:name":"Bogaert F",
    "wof:placetype":"venue"
},
  "geometry": {"coordinates":[4.3053088188,50.8547325134],"type":"Point"}
}