{
  "type": "Feature",
  "properties": {
    "iso:country":"BE",
    "sg:address":"Koning Alberstraat 203",
    "sg:city":"Mechelen",
    "sg:orig_category":"Forge, Moulage and Profilage des M\u00e9taux",
    "sg:phone":"+32 475 68 41 20",
    "sg:postcode":"2800",
    "sg:province":"Antwerpen",
    "wof:name":"Bollen M",
    "wof:placetype":"venue"
},
  "geometry": {"coordinates":[4.4737811089,51.0221099854],"type":"Point"}
}