{
  "type": "Feature",
  "properties": {
    "addr:full":"Rue Des Ecoles 85 Vis\u00e9 Li\u00e8ge 4600",
    "addr:housenumber":"85",
    "addr:postcode":"4600",
    "addr:street":"Rue Des Ecoles",
    "iso:country":"BE",
    "sg:address":"Rue Des Ecoles 85",
    "sg:city":"Vis\u00e9",
    "sg:classifiers":[
        {
            "category":"Health Services",
            "subcategory":"Dentist",
            "type":"Services"
        }
    ],
    "sg:phone":"+32 4 379 28 10",
    "sg:postcode":"4600",
    "sg:province":"Li\u00e8ge",
    "wof:name":"Renson Bruno",
    "wof:placetype":"venue"
},
  "geometry": {"coordinates":[5.685573101,50.741607666],"type":"Point"}
}