{
  "type": "Feature",
  "properties": {
    "iso:country":"BE",
    "sg:address":"Industrielaan 1",
    "sg:city":"Ieper",
    "sg:orig_category":"Entreprises de travail adapt\u00e9",
    "sg:phone":"+32 57 21 89 19",
    "sg:postcode":"8900",
    "sg:province":"West-Vlaanderen",
    "wof:name":"Westlandia",
    "wof:placetype":"venue"
},
  "geometry": {"coordinates":[2.8878269196,50.8513641357],"type":"Point"}
}