{
  "type": "Feature",
  "properties": {
    "iso:country":"BE",
    "sg:address":"Wijndriesstraat 12",
    "sg:city":"Bekkevoort",
    "sg:classifiers":[
        {
            "category":"Wholesale",
            "subcategory":"Fruits & Vegetables",
            "type":"Manufacturing & Wholesale Goods"
        }
    ],
    "sg:phone":"+32 16 77 97 58",
    "sg:postcode":"3460",
    "sg:province":"Vlaams-Brabant",
    "sg:tags":[
        "whol",
        "-"
    ],
    "wof:name":"Devos-theunis S",
    "wof:placetype":"venue"
},
  "geometry": {"coordinates":[4.966591835,50.9290733337],"type":"Point"}
}