{
  "type": "Feature",
  "properties": {
    "iso:country":"BE",
    "sg:address":"Lieverstedestraat 23",
    "sg:city":"Oostkamp",
    "sg:classifiers":[
        {
            "category":"Manufacturing",
            "subcategory":"Building Materials",
            "type":"Manufacturing & Wholesale Goods"
        }
    ],
    "sg:phone":"+32 50 82 75 66",
    "sg:postcode":"8020",
    "sg:province":"West-Vlaanderen",
    "sg:tags":[
        "fixture",
        "store"
    ],
    "wof:name":"Euro Design Apoteek Inrichtingen Bvba",
    "wof:placetype":"venue"
},
  "geometry": {"coordinates":[3.2518110275,51.168838501],"type":"Point"}
}