{
  "type": "Feature",
  "properties": {
    "addr:full":"Opitterstraat 26ba Bree Limburg 3960",
    "addr:housenumber":"26ba",
    "addr:postcode":"3960",
    "addr:street":"Opitterstraat",
    "iso:country":"BE",
    "sg:address":"Opitterstraat 26ba",
    "sg:city":"Bree",
    "sg:orig_category":"Eclairage et \u00e9quipements du foyer",
    "sg:phone":"+32 89 47 27 56",
    "sg:postcode":"3960",
    "sg:province":"Limburg",
    "wof:name":"Huis Patio",
    "wof:placetype":"venue"
},
  "geometry": {"coordinates":[5.6028819084,51.1394767761],"type":"Point"}
}