{
  "type": "Feature",
  "properties": {
    "addr:full":"Rue De Gerpinnes 36 Walcourt (tarcienne) Namur 5651",
    "addr:housenumber":"36",
    "addr:postcode":"5651",
    "addr:street":"Rue De Gerpinnes",
    "iso:country":"BE",
    "sg:address":"Rue De Gerpinnes 36",
    "sg:city":"Walcourt (tarcienne)",
    "sg:classifiers":[
        {
            "category":"Farming",
            "subcategory":"Farm & Veterinary Services",
            "type":"Manufacturing & Wholesale Goods"
        }
    ],
    "sg:phone":"+32 71 22 03 77",
    "sg:postcode":"5651",
    "sg:province":"Namur",
    "sg:tags":[
        "agricultural",
        "contractor"
    ],
    "wof:name":"Vinwac Scris",
    "wof:placetype":"venue"
},
  "geometry": {"coordinates":[4.4262080193,50.2824401855],"type":"Point"}
}