{
  "type": "Feature",
  "properties": {
    "iso:country":"BE",
    "sg:address":"Rue Du Parc 22",
    "sg:city":"La Louviere",
    "sg:orig_category":"Dierenartsen",
    "sg:phone":"+32 64 22 75 93",
    "sg:postcode":"7100",
    "sg:province":"Hainaut",
    "wof:name":"Aime Navet",
    "wof:placetype":"venue"
},
  "geometry": {"coordinates":[4.1918091774,50.475528717],"type":"Point"}
}