{
  "type": "Feature",
  "properties": {
    "addr:full":"Jubelfeestlaan 5b1 Sint-jans-molenbeek/molenbeek-saint-jean Bruxelles-Capitale 1080",
    "addr:housenumber":"5b1",
    "addr:postcode":"1080",
    "addr:street":"Jubelfeestlaan",
    "iso:country":"BE",
    "sg:address":"Jubelfeestlaan 5b1",
    "sg:city":"Sint-jans-molenbeek/molenbeek-saint-jean",
    "sg:orig_category":"Slagers",
    "sg:phone":"+32 2 425 17 25",
    "sg:postcode":"1080",
    "sg:province":"Bruxelles-Capitale",
    "wof:name":"Boucherie Gilbert",
    "wof:placetype":"venue"
},
  "geometry": {"coordinates":[4.3385601044,50.8613166809],"type":"Point"}
}