{
  "type": "Feature",
  "properties": {
    "addr:full":"Rue Albert 1er 79 Engis Li\u00e8ge 4480",
    "addr:housenumber":"79",
    "addr:postcode":"4480",
    "addr:street":"Rue Albert 1Er",
    "iso:country":"BE",
    "sg:address":"Rue Albert 1er 79",
    "sg:city":"Engis",
    "sg:orig_category":"Fotografen and fotostudio's",
    "sg:phone":"+32 4 275 40 69",
    "sg:postcode":"4480",
    "sg:province":"Li\u00e8ge",
    "wof:name":"Michel Evrard",
    "wof:placetype":"venue"
},
  "geometry": {"coordinates":[5.4050841331,50.5825614929],"type":"Point"}
}