{
  "type": "Feature",
  "properties": {
    "iso:country":"BE",
    "sg:address":"Bronstraat 119",
    "sg:city":"Sint-gillis/saint-gilles",
    "sg:orig_category":"Antiek",
    "sg:phone":"+32 2 538 63 30",
    "sg:postcode":"1060",
    "sg:province":"Bruxelles-Capitale",
    "wof:name":"Geoffrey Turner",
    "wof:placetype":"venue"
},
  "geometry": {"coordinates":[4.3555860519,50.8301811218],"type":"Point"}
}