{
  "type": "Feature",
  "properties": {
    "iso:country":"BE",
    "sg:address":"Boulevard De L'humanit\u00e9 102",
    "sg:city":"Bruxelles (forest)",
    "sg:classifiers":[
        {
            "category":"Professional",
            "subcategory":"Management & Consulting",
            "type":"Services"
        }
    ],
    "sg:phone":"+32 2 340 72 40",
    "sg:postcode":"1190",
    "sg:province":"Bruxelles-Capitale",
    "sg:tags":[
        "marketing",
        "-",
        "direct",
        "consultant"
    ],
    "wof:name":"Framar International",
    "wof:placetype":"venue"
},
  "geometry": {"coordinates":[4.3150248528,50.820728302],"type":"Point"}
}