{
  "type": "Feature",
  "properties": {
    "addr:full":"Goedlevenstraat 25 Gent Oost-Vlaanderen 9041",
    "addr:housenumber":"25",
    "addr:postcode":"9041",
    "addr:street":"Goedlevenstraat;Oost-Vlaanderen",
    "iso:country":"BE",
    "sg:address":"Goedlevenstraat 25",
    "sg:city":"Gent",
    "sg:orig_category":"V\u00e9los",
    "sg:phone":"+32 9 251 52 86",
    "sg:postcode":"9041",
    "sg:province":"Oost-Vlaanderen",
    "wof:name":"Danny Genetello",
    "wof:placetype":"venue"
},
  "geometry": {"coordinates":[3.7626008987,51.079158783],"type":"Point"}
}