{
  "type": "Feature",
  "properties": {
    "addr:full":"Kruisstraat 2b Ternat Vlaams-Brabant 1740",
    "addr:housenumber":"2b",
    "addr:postcode":"1740",
    "addr:street":"Kruisstraat",
    "iso:country":"BE",
    "sg:address":"Kruisstraat 2b",
    "sg:city":"Ternat",
    "sg:classifiers":[
        {
            "category":"Farming",
            "subcategory":"Farm & Veterinary Services",
            "type":"Manufacturing & Wholesale Goods"
        }
    ],
    "sg:phone":"+32 2 582 33 80",
    "sg:postcode":"1740",
    "sg:province":"Vlaams-Brabant",
    "sg:tags":[
        "agricultural",
        "contractor"
    ],
    "wof:name":"Pauwels L",
    "wof:placetype":"venue"
},
  "geometry": {"coordinates":[4.1637749672,50.8644065857],"type":"Point"}
}