{
  "type": "Feature",
  "properties": {
    "addr:full":"Leopoldstr 16 Leuven Vlaams-Brabant 3000",
    "addr:housenumber":"16",
    "addr:postcode":"3000",
    "addr:street":"Leopoldstr",
    "iso:country":"BE",
    "sg:address":"Leopoldstr 16",
    "sg:city":"Leuven",
    "sg:classifiers":[
        {
            "category":"Banks & Credit Unions",
            "subcategory":"Bank",
            "type":"Services"
        }
    ],
    "sg:phone":"+32 16 22 61 36",
    "sg:postcode":"3000",
    "sg:province":"Vlaams-Brabant",
    "wof:name":"Caisse Nationale De, Cr\u00e9dit Professionnel",
    "wof:placetype":"venue"
},
  "geometry": {"coordinates":[4.7103028297,50.8813323975],"type":"Point"}
}