{
  "type": "Feature",
  "properties": {
    "iso:country":"BE",
    "sg:address":"Sparappelstraat 76",
    "sg:city":"Torhout (wijnendale)",
    "sg:classifiers":[
        {
            "category":"Personal",
            "subcategory":"Beauty Salon",
            "type":"Services"
        }
    ],
    "sg:phone":"+32 50 21 39 75",
    "sg:postcode":"8820",
    "sg:province":"West-Vlaanderen",
    "sg:tags":[
        "lady",
        "-",
        "hairdressing"
    ],
    "wof:name":"Gwenny",
    "wof:placetype":"venue"
},
  "geometry": {"coordinates":[3.0714299679,51.0987052917],"type":"Point"}
}