{
  "type": "Feature",
  "properties": {
    "addr:full":"Chauss\u00c9e De Mons 1 Anderlecht Bruxelles-Capitale 1070",
    "addr:housenumber":"1",
    "addr:postcode":"1070",
    "addr:street":"Chausse\u0301E De Mons",
    "iso:country":"BE",
    "sg:address":"Chauss\u00c9e De Mons 1",
    "sg:city":"Anderlecht",
    "sg:classifiers":[
        {
            "category":"Taxi",
            "type":"Transportation"
        }
    ],
    "sg:phone":"+32 75309326",
    "sg:postcode":"1070",
    "sg:province":"Bruxelles-Capitale",
    "sg:tags":[
        "taxi's"
    ],
    "wof:name":"Derbel",
    "wof:placetype":"venue"
},
  "geometry": {"coordinates":[4.289150238,50.8082733154],"type":"Point"}
}