{
  "type": "Feature",
  "properties": {
    "addr:full":"Rue Du Champ De L'eglise 24 Brussel/bruxelles Bruxelles-Capitale 1020",
    "addr:housenumber":"24",
    "addr:postcode":"1020",
    "addr:street":"Rue Du Champ De L'Eglise;/",
    "iso:country":"BE",
    "sg:address":"Rue Du Champ De L'eglise 24",
    "sg:city":"Brussel/bruxelles",
    "sg:orig_category":"Entretien and r\u00e9parations de voitures",
    "sg:phone":"+32 2 426 66 72",
    "sg:postcode":"1020",
    "sg:province":"Bruxelles-Capitale",
    "wof:name":"Carrosserie Simeone",
    "wof:placetype":"venue"
},
  "geometry": {"coordinates":[4.3544092178,50.8764686584],"type":"Point"}
}