{
  "type": "Feature",
  "properties": {
    "iso:country":"BE",
    "sg:address":"Rte De Mons-maubeuge 67",
    "sg:city":"Quevy",
    "sg:orig_category":"Dancings and bo\u00eetes de nuit",
    "sg:phone":"+32 65 56 82 80",
    "sg:postcode":"7041",
    "sg:province":"Hainaut",
    "wof:name":"The Pitch",
    "wof:placetype":"venue"
},
  "geometry": {"coordinates":[3.9671039581,50.3641281128],"type":"Point"}
}