{
  "type": "Feature",
  "properties": {
    "addr:full":"Maurice Des Ombiauxstr. 8 Bruxelles Bruxelles-Capitale 1030",
    "addr:housenumber":"8",
    "addr:postcode":"1030",
    "addr:street":"Maurice Des Ombiauxstr.",
    "iso:country":"BE",
    "sg:address":"Maurice Des Ombiauxstr. 8",
    "sg:city":"Bruxelles",
    "sg:orig_category":"Software ontwikkeling and ontwerp",
    "sg:phone":"+32 2 215 20 50",
    "sg:postcode":"1030",
    "sg:province":"Bruxelles-Capitale",
    "wof:name":"Fijico Electronics",
    "wof:placetype":"venue"
},
  "geometry": {"coordinates":[4.3782300949,50.8762130737],"type":"Point"}
}