{
  "type": "Feature",
  "properties": {
    "addr:full":"Brakelsesteenweg 552 Ninove (voorde) Oost-Vlaanderen 9400",
    "addr:housenumber":"552",
    "addr:postcode":"9400",
    "addr:street":"Brakelsesteenweg;Voorde Oost-Vlaanderen",
    "iso:country":"BE",
    "sg:address":"Brakelsesteenweg 552",
    "sg:city":"Ninove (voorde)",
    "sg:orig_category":"Autombile concessionaires",
    "sg:phone":"+32 54 50 07 77",
    "sg:postcode":"9400",
    "sg:province":"Oost-Vlaanderen",
    "wof:name":"Neckebroeck E",
    "wof:placetype":"venue"
},
  "geometry": {"coordinates":[4.0039701462,50.8359107971],"type":"Point"}
}