{
  "type": "Feature",
  "properties": {
    "iso:country":"BE",
    "sg:address":"Windmolenstraat 39",
    "sg:city":"Evere",
    "sg:orig_category":"Sportclubs",
    "sg:phone":"+32 2 726 01 63",
    "sg:postcode":"1140",
    "sg:province":"Bruxelles-Capitale",
    "wof:name":"Judo Budokan",
    "wof:placetype":"venue"
},
  "geometry": {"coordinates":[4.3964910507,50.8736953735],"type":"Point"}
}