{
  "type": "Feature",
  "properties": {
    "addr:full":"Bovelingenstraat 410 Heers Limburg 3870",
    "addr:housenumber":"410",
    "addr:postcode":"3870",
    "addr:street":"Bovelingenstraat",
    "iso:country":"BE",
    "sg:address":"Bovelingenstraat 410",
    "sg:city":"Heers",
    "sg:orig_category":"Bloemen and planten",
    "sg:phone":"+32 11 48 42 47",
    "sg:postcode":"3870",
    "sg:province":"Limburg",
    "wof:name":"Ph. Broeckx",
    "wof:placetype":"venue"
},
  "geometry": {"coordinates":[5.2562952042,50.7238769531],"type":"Point"}
}