{
  "type": "Feature",
  "properties": {
    "addr:full":"Torenstraat 62 Rotselaar Vlaams-Brabant 3110",
    "addr:housenumber":"62",
    "addr:postcode":"3110",
    "addr:street":"Torenstraat",
    "iso:country":"BE",
    "sg:address":"Torenstraat 62",
    "sg:city":"Rotselaar",
    "sg:orig_category":"Enseignement maternel and primaire",
    "sg:phone":"+32 16 44 90 46",
    "sg:postcode":"3110",
    "sg:province":"Vlaams-Brabant",
    "wof:name":"Vrije Basisschool",
    "wof:placetype":"venue"
},
  "geometry": {"coordinates":[4.7162871361,50.9536209106],"type":"Point"}
}