{
  "type": "Feature",
  "properties": {
    "addr:full":"Rue Saint-roch 71 Sambreville (falisolle) Namur 5060",
    "addr:housenumber":"71",
    "addr:postcode":"5060",
    "addr:street":"Rue Saint-Roch",
    "iso:country":"BE",
    "sg:address":"Rue Saint-roch 71",
    "sg:city":"Sambreville (falisolle)",
    "sg:classifiers":[
        {
            "category":"Autos & Motor Vehicles",
            "subcategory":"Automobile Sales",
            "type":"Retail Goods"
        }
    ],
    "sg:phone":"+32 71 74 06 99",
    "sg:postcode":"5060",
    "sg:province":"Namur",
    "sg:tags":[
        "motorhomes",
        "accessory"
    ],
    "wof:name":"Passion 4 X 4",
    "wof:placetype":"venue"
},
  "geometry": {"coordinates":[4.6168951988,50.4120903015],"type":"Point"}
}