{
  "type": "Feature",
  "properties": {
    "addr:full":"Matrouwstraat 57 Brakel Oost-Vlaanderen 9661",
    "addr:housenumber":"57",
    "addr:postcode":"9661",
    "addr:street":"Matrouwstraat",
    "iso:country":"BE",
    "sg:address":"Matrouwstraat 57",
    "sg:city":"Brakel",
    "sg:classifiers":[
        {
            "category":"Arena",
            "subcategory":"Sports Club",
            "type":"Entertainment"
        }
    ],
    "sg:phone":"+32 55 42 84 27",
    "sg:postcode":"9661",
    "sg:province":"Oost-Vlaanderen",
    "sg:tags":[
        "de"
    ],
    "wof:name":"Onder Ons - Parike",
    "wof:placetype":"venue"
},
  "geometry": {"coordinates":[3.7979419231,50.793762207],"type":"Point"}
}