{
  "type": "Feature",
  "properties": {
    "addr:full":"Westergemstraat 65 Gent (wondelgem) Oost-Vlaanderen 9032",
    "addr:housenumber":"65",
    "addr:postcode":"9032",
    "addr:street":"Westergemstraat",
    "iso:country":"BE",
    "sg:address":"Westergemstraat 65",
    "sg:city":"Gent (wondelgem)",
    "sg:classifiers":[
        {
            "category":"Home & Garden",
            "subcategory":"Hardware",
            "type":"Retail Goods"
        }
    ],
    "sg:phone":"+32 9 226 26 88",
    "sg:postcode":"9032",
    "sg:province":"Oost-Vlaanderen",
    "sg:tags":[
        "-"
    ],
    "wof:name":"Danau R",
    "wof:placetype":"venue"
},
  "geometry": {"coordinates":[3.7162549496,51.0900535583],"type":"Point"}
}