{
  "type": "Feature",
  "properties": {
    "iso:country":"BE",
    "sg:address":"Rue Paul Pastur 2b23",
    "sg:city":"Charleroi",
    "sg:orig_category":"Experts-comptables",
    "sg:phone":"+32 71 81 31 15",
    "sg:postcode":"6041",
    "sg:province":"Hainaut",
    "wof:name":"Stephan Moratti",
    "wof:placetype":"venue"
},
  "geometry": {"coordinates":[4.4636101723,50.3808135986],"type":"Point"}
}