{
  "type": "Feature",
  "properties": {
    "iso:country":"BE",
    "sg:address":"Vaartstraat 150",
    "sg:city":"Balen",
    "sg:classifiers":[
        {
            "category":"Government",
            "subcategory":"Fire Station",
            "type":"Public Place"
        }
    ],
    "sg:phone":"+32 3 324 68 52",
    "sg:postcode":"2490",
    "sg:province":"Antwerpen",
    "sg:tags":[
        "supraregional",
        "plant",
        "installation",
        "heating"
    ],
    "wof:name":"Willems B.v.b.a.",
    "wof:placetype":"venue"
},
  "geometry": {"coordinates":[4.4645719528,51.224067688],"type":"Point"}
}