{
  "type": "Feature",
  "properties": {
    "addr:full":"Korte Steenstraat 16 Kortrijk West-Vlaanderen 8500",
    "addr:housenumber":"16",
    "addr:postcode":"8500",
    "addr:street":"Korte Steenstraat",
    "iso:country":"BE",
    "sg:address":"Korte Steenstraat 16",
    "sg:city":"Kortrijk",
    "sg:orig_category":"Eclairage et \u00e9quipements du foyer. Souvenirs and objets artisanaux",
    "sg:phone":"+32 56 21 48 18",
    "sg:postcode":"8500",
    "sg:province":"West-Vlaanderen",
    "wof:name":"Casa",
    "wof:placetype":"venue"
},
  "geometry": {"coordinates":[3.2677850723,50.8266906738],"type":"Point"}
}