{
  "type": "Feature",
  "properties": {
    "addr:full":"Pensstraat 26 Destelbergen (heusden) Oost-Vlaanderen 9070",
    "addr:housenumber":"26",
    "addr:postcode":"9070",
    "addr:street":"Pensstraat",
    "iso:country":"BE",
    "sg:address":"Pensstraat 26",
    "sg:city":"Destelbergen (heusden)",
    "sg:classifiers":[
        {
            "category":"Health Services",
            "subcategory":"Health Practitioner",
            "type":"Services"
        }
    ],
    "sg:phone":"+32 9 231 95 49",
    "sg:postcode":"9070",
    "sg:province":"Oost-Vlaanderen",
    "sg:tags":[
        "physiotherapist"
    ],
    "wof:name":"De Rocker Dirk",
    "wof:placetype":"venue"
},
  "geometry": {"coordinates":[3.8056149483,51.0262336731],"type":"Point"}
}