{
  "type": "Feature",
  "properties": {
    "iso:country":"BE",
    "sg:address":"St.martensommegangstraat 22",
    "sg:city":"Hamme",
    "sg:orig_category":"S\u00e9curit\u00e9 sociale",
    "sg:phone":"+32 52 47 16 93",
    "sg:postcode":"9220",
    "sg:province":"Oost-Vlaanderen",
    "wof:name":"Christelijke Mutualiteit",
    "wof:placetype":"venue"
},
  "geometry": {"coordinates":[4.1516242027,51.0645179749],"type":"Point"}
}