{
  "type": "Feature",
  "properties": {
    "addr:full":"Kortrijksesteenweg 100 Gent Oost-Vlaanderen 9000",
    "addr:housenumber":"100",
    "addr:postcode":"9000",
    "addr:street":"Kortrijksesteenweg;Oost-Vlaanderen",
    "iso:country":"BE",
    "sg:address":"Kortrijksesteenweg 100",
    "sg:city":"Gent",
    "sg:classifiers":[
        {
            "category":"Wholesale",
            "subcategory":"Wine & Distilled Alcoholic Beverages",
            "type":"Manufacturing & Wholesale Goods"
        }
    ],
    "sg:phone":"+32 9 245 34 27",
    "sg:postcode":"9000",
    "sg:province":"Oost-Vlaanderen",
    "sg:tags":[
        "whol",
        "-",
        "spirit",
        "mfg"
    ],
    "wof:name":"Sylvin",
    "wof:placetype":"venue"
},
  "geometry": {"coordinates":[3.7172970772,51.0406341553],"type":"Point"}
}