{
  "type": "Feature",
  "properties": {
    "addr:full":"Fonteinstraat 1 Brugge West-Vlaanderen 8000",
    "addr:housenumber":"1",
    "addr:postcode":"8000",
    "addr:street":"Fonteinstraat",
    "iso:country":"BE",
    "sg:address":"Fonteinstraat 1",
    "sg:city":"Brugge",
    "sg:orig_category":"M\u00e9decins and sp\u00e9cialistes",
    "sg:phone":"+32 50 34 91 10",
    "sg:postcode":"8000",
    "sg:province":"West-Vlaanderen",
    "wof:name":"Kathleen Houtteman",
    "wof:placetype":"venue"
},
  "geometry": {"coordinates":[3.2158949375,51.202507019],"type":"Point"}
}