{
  "type": "Feature",
  "properties": {
    "iso:country":"BE",
    "sg:address":"De Pintelaan 262a",
    "sg:city":"Gent",
    "sg:orig_category":"Projectontwikkelaars Woningbouw",
    "sg:phone":"+32 9 222 21 42",
    "sg:postcode":"9000",
    "sg:province":"Oost-Vlaanderen",
    "wof:name":"Scaldimo Promoties",
    "wof:placetype":"venue"
},
  "geometry": {"coordinates":[3.7088069916,51.0217094421],"type":"Point"}
}