{
  "type": "Feature",
  "properties": {
    "addr:full":"Rue D\u00b4orbey 4 Fosses-la-ville Namur 5070",
    "addr:housenumber":"4",
    "addr:postcode":"5070",
    "addr:street":"Rue D\u00b4Orbey",
    "iso:country":"BE",
    "sg:address":"Rue D\u00b4orbey 4",
    "sg:city":"Fosses-la-ville",
    "sg:orig_category":"Rev\u00eatements pour sols and murs",
    "sg:phone":"+32 71 71 46 27",
    "sg:postcode":"5070",
    "sg:province":"Namur",
    "wof:name":"Ets. Callaert",
    "wof:placetype":"venue"
},
  "geometry": {"coordinates":[4.6958098412,50.3965301514],"type":"Point"}
}