{
  "type": "Feature",
  "properties": {
    "iso:country":"BE",
    "sg:address":"Place Du March\u00e9 10",
    "sg:city":"La Roche-en-ardenne",
    "sg:classifiers":[
        {
            "category":"Real Estate",
            "subcategory":"Real Estate Services",
            "type":"Services"
        }
    ],
    "sg:phone":"+32 84 44 00 33",
    "sg:postcode":"6980",
    "sg:province":"Luxembourg",
    "wof:name":"Bureau Immobilier Ardennais Sa",
    "wof:placetype":"venue"
},
  "geometry": {"coordinates":[5.575106144,50.1818618774],"type":"Point"}
}