{
  "type": "Feature",
  "properties": {
    "iso:country":"BE",
    "sg:address":"Boudewijnlaan 6",
    "sg:city":"Heist-op-den-berg",
    "sg:classifiers":[
        {
            "category":"Real Estate",
            "subcategory":"Architect",
            "type":"Services"
        }
    ],
    "sg:phone":"+32 15 24 96 00",
    "sg:postcode":"2220",
    "sg:province":"Antwerpen",
    "wof:name":"Nauwelaerts B",
    "wof:placetype":"venue"
},
  "geometry": {"coordinates":[4.7141690254,51.0737991333],"type":"Point"}
}