{
  "type": "Feature",
  "properties": {
    "addr:full":"Kareelstraat 130 Aalst Oost-Vlaanderen 9300",
    "addr:housenumber":"130",
    "addr:postcode":"9300",
    "addr:street":"Kareelstraat",
    "iso:country":"BE",
    "sg:address":"Kareelstraat 130",
    "sg:city":"Aalst",
    "sg:orig_category":"Schoenen",
    "sg:phone":"+32 53 21 13 01",
    "sg:postcode":"9300",
    "sg:province":"Oost-Vlaanderen",
    "wof:name":"Schoencenter Soufri",
    "wof:placetype":"venue"
},
  "geometry": {"coordinates":[4.0316848755,50.9235343933],"type":"Point"}
}