{
  "type": "Feature",
  "properties": {
    "addr:full":"Rue Du Centre 1 Sprimont Li\u00e8ge 4140",
    "addr:housenumber":"1",
    "addr:postcode":"4140",
    "addr:street":"Rue Du Centre",
    "iso:country":"BE",
    "sg:address":"Rue Du Centre 1",
    "sg:city":"Sprimont",
    "sg:orig_category":"Openbare veiligheid",
    "sg:phone":"+32 4 382 18 50",
    "sg:postcode":"4140",
    "sg:province":"Li\u00e8ge",
    "wof:name":"Police F\u00c9d\u00c9rale/federale Politie",
    "wof:placetype":"venue"
},
  "geometry": {"coordinates":[5.662569046,50.5060348511],"type":"Point"}
}