{
  "type": "Feature",
  "properties": {
    "addr:full":"Aquilonlaan 4 Sint-lambrechts-woluwe/woluwe-saint-lambert Bruxelles-Capitale 1200",
    "addr:housenumber":"4",
    "addr:postcode":"1200",
    "addr:street":"Aquilonlaan",
    "iso:country":"BE",
    "sg:address":"Aquilonlaan 4",
    "sg:city":"Sint-lambrechts-woluwe/woluwe-saint-lambert",
    "sg:orig_category":"Schoonheidssalons",
    "sg:phone":"+32 2 762 87 09",
    "sg:postcode":"1200",
    "sg:province":"Bruxelles-Capitale",
    "wof:name":"Martine Baert",
    "wof:placetype":"venue"
},
  "geometry": {"coordinates":[4.439286232,50.8515434265],"type":"Point"}
}