{
  "type": "Feature",
  "properties": {
    "addr:full":"Rue Dourlet 27a-27b Charleroi Hainaut 6000",
    "addr:housenumber":"27a-27b",
    "addr:postcode":"6000",
    "addr:street":"Rue Dourlet;Hainaut",
    "iso:country":"BE",
    "sg:address":"Rue Dourlet 27a-27b",
    "sg:city":"Charleroi",
    "sg:orig_category":"Artsen and specialisten Astrologen, grafologen and mediums Werk and personeelsselectie",
    "sg:phone":"+32 71 41 10 26",
    "sg:postcode":"6000",
    "sg:province":"Hainaut",
    "wof:name":"Centre Bastin",
    "wof:placetype":"venue"
},
  "geometry": {"coordinates":[4.4525637627,50.418598175],"type":"Point"}
}