{
  "type": "Feature",
  "properties": {
    "addr:full":"Torhoutsesteenweg 164 Zedelgem West-Vlaanderen 8210",
    "addr:housenumber":"164",
    "addr:postcode":"8210",
    "addr:street":"Torhoutsesteenweg",
    "iso:country":"BE",
    "sg:address":"Torhoutsesteenweg 164",
    "sg:city":"Zedelgem",
    "sg:classifiers":[
        {
            "category":"Bars & Pubs",
            "type":"Food & Drink"
        }
    ],
    "sg:phone":"+32 50 20 08 08",
    "sg:postcode":"8210",
    "sg:province":"West-Vlaanderen",
    "sg:tags":[
        "tavern"
    ],
    "wof:name":"Rembrandt",
    "wof:placetype":"venue"
},
  "geometry": {"coordinates":[3.1576468945,51.1365127563],"type":"Point"}
}