{
  "type": "Feature",
  "properties": {
    "iso:country":"BE",
    "sg:address":"Houba De Strooperlaan 242",
    "sg:city":"Brussel/bruxelles",
    "sg:orig_category":"Rusthuizen and serviceflats",
    "sg:phone":"+32 2 478 07 35",
    "sg:postcode":"1020",
    "sg:province":"Bruxelles-Capitale",
    "wof:name":"R\u00c9sidence Atomium",
    "wof:placetype":"venue"
},
  "geometry": {"coordinates":[4.3347868919,50.891330719],"type":"Point"}
}