{
  "type": "Feature",
  "properties": {
    "addr:full":"Blokt 20 Herenthout Antwerpen 2270",
    "addr:housenumber":"20",
    "addr:postcode":"2270",
    "addr:street":"Blokt",
    "iso:country":"BE",
    "sg:address":"Blokt 20",
    "sg:city":"Herenthout",
    "sg:orig_category":"Eleveurs and marchands de porcs. Eleveurs de bovins",
    "sg:phone":"+32 14 51 56 74",
    "sg:postcode":"2270",
    "sg:province":"Antwerpen",
    "wof:name":"Jozef Van Looy",
    "wof:placetype":"venue"
},
  "geometry": {"coordinates":[4.7424068451,51.149684906],"type":"Point"}
}