{
  "type": "Feature",
  "properties": {
    "addr:full":"Abelestationsplein 27 Poperinge West-Vlaanderen 8970",
    "addr:housenumber":"27",
    "addr:postcode":"8970",
    "addr:street":"Abelestationsplein",
    "iso:country":"BE",
    "sg:address":"Abelestationsplein 27",
    "sg:city":"Poperinge",
    "sg:classifiers":[
        {
            "category":"Cafe",
            "type":"Food & Drink"
        }
    ],
    "sg:phone":"+32 57 33 60 27",
    "sg:postcode":"8970",
    "sg:province":"West-Vlaanderen",
    "sg:tags":[
        "caf\u00e9s"
    ],
    "wof:name":"Valerie Samyn",
    "wof:placetype":"venue"
},
  "geometry": {"coordinates":[2.6798970699,50.8189811707],"type":"Point"}
}