{
  "type": "Feature",
  "properties": {
    "addr:full":"Boterhoek 14 Sint-katelijne-waver Antwerpen 2861",
    "addr:housenumber":"14",
    "addr:postcode":"2861",
    "addr:street":"Boterhoek",
    "iso:country":"BE",
    "sg:address":"Boterhoek 14",
    "sg:city":"Sint-katelijne-waver",
    "sg:orig_category":"Producteurs de l\u00e9gumes",
    "sg:phone":"+32 15 75 64 34",
    "sg:postcode":"2861",
    "sg:province":"Antwerpen",
    "wof:name":"Paul Van Goolen",
    "wof:placetype":"venue"
},
  "geometry": {"coordinates":[4.5920028687,51.0734901428],"type":"Point"}
}