{
  "type": "Feature",
  "properties": {
    "iso:country":"BE",
    "sg:address":"Sint-luciestraat 3",
    "sg:city":"Rijkevorsel",
    "sg:orig_category":"Eleveurs de bovins",
    "sg:phone":"+32 3 314 86 27",
    "sg:postcode":"2310",
    "sg:province":"Antwerpen",
    "wof:name":"Ludovicus Fransen",
    "wof:placetype":"venue"
},
  "geometry": {"coordinates":[4.7572798729,51.3532447815],"type":"Point"}
}