{
  "type": "Feature",
  "properties": {
    "iso:country":"BE",
    "sg:address":"Leopoldlaan 17",
    "sg:city":"Ninove",
    "sg:orig_category":"Advocaten and juridische adviseurs",
    "sg:phone":"+32 54 33 53 50",
    "sg:postcode":"9400",
    "sg:province":"Oost-Vlaanderen",
    "wof:name":"Tania Ghysens",
    "wof:placetype":"venue"
},
  "geometry": {"coordinates":[4.0223078728,50.8268814087],"type":"Point"}
}