{
  "type": "Feature",
  "properties": {
    "addr:full":"Sint-katelijnestraat 107 Mechelen Antwerpen 2800",
    "addr:housenumber":"107",
    "addr:postcode":"2800",
    "addr:street":"Sint-Katelijnestraat",
    "iso:country":"BE",
    "sg:address":"Sint-katelijnestraat 107",
    "sg:city":"Mechelen",
    "sg:orig_category":"Epiceries",
    "sg:phone":"+32 15 34 40 77",
    "sg:postcode":"2800",
    "sg:province":"Antwerpen",
    "wof:name":"Bismillah Familia",
    "wof:placetype":"venue"
},
  "geometry": {"coordinates":[4.4754538536,51.0324516296],"type":"Point"}
}