{
  "type": "Feature",
  "properties": {
    "iso:country":"BE",
    "sg:address":"Rue Du Commerce 12-9",
    "sg:city":"Nivelles",
    "sg:classifiers":[
        {
            "category":"Social Services",
            "subcategory":"Job Training",
            "type":"Services"
        }
    ],
    "sg:phone":"+32 67 21 94 30",
    "sg:postcode":"1400",
    "sg:province":"Brabant Wallon",
    "sg:tags":[
        "personnel",
        "-selection",
        "recruitment"
    ],
    "wof:name":"J-l Consultants Benelux Sc",
    "wof:placetype":"venue"
},
  "geometry": {"coordinates":[4.3641891479,50.5885505676],"type":"Point"}
}