{
  "type": "Feature",
  "properties": {
    "iso:country":"BE",
    "sg:address":"Avenue Th\u00c9o Verbeeck 2",
    "sg:city":"Anderlecht",
    "sg:classifiers":[
        {
            "category":"Shopping",
            "subcategory":"Bicycles & Sporting Goods",
            "type":"Retail Goods"
        }
    ],
    "sg:phone":"+32 2 523 50 90",
    "sg:postcode":"1070",
    "sg:province":"Bruxelles-Capitale",
    "sg:tags":[
        "article",
        "de",
        "sport",
        "camping"
    ],
    "wof:name":"Winners",
    "wof:placetype":"venue"
},
  "geometry": {"coordinates":[4.2988052368,50.8351020813],"type":"Point"}
}