{
  "type": "Feature",
  "properties": {
    "addr:full":"Mechelsesteenweg 136 Zaventem (sterrebeek) Vlaams-Brabant 1933",
    "addr:housenumber":"136",
    "addr:postcode":"1933",
    "addr:street":"Mechelsesteenweg",
    "iso:country":"BE",
    "sg:address":"Mechelsesteenweg 136",
    "sg:city":"Zaventem (sterrebeek)",
    "sg:classifiers":[
        {
            "category":"Shopping",
            "subcategory":"Optician",
            "type":"Retail Goods"
        }
    ],
    "sg:phone":"+32 2 731 03 77",
    "sg:postcode":"1933",
    "sg:province":"Vlaams-Brabant",
    "sg:tags":[
        "-"
    ],
    "wof:name":"Optic Joos",
    "wof:placetype":"venue"
},
  "geometry": {"coordinates":[4.5136151314,50.8592567444],"type":"Point"}
}