{
  "type": "Feature",
  "properties": {
    "iso:country":"BE",
    "sg:address":"Brusselsesteenweg 523",
    "sg:city":"Overijse",
    "sg:orig_category":"Poissonniers and \u00e9caillers",
    "sg:phone":"+32 2 657 45 11",
    "sg:postcode":"3090",
    "sg:province":"Vlaams-Brabant",
    "wof:name":"Marc Vergauts",
    "wof:placetype":"venue"
},
  "geometry": {"coordinates":[4.5082998276,50.7829399109],"type":"Point"}
}