{
  "type": "Feature",
  "properties": {
    "iso:country":"BE",
    "sg:address":"Rue Gr\u00c9try 66d",
    "sg:city":"Li\u00c8ge",
    "sg:orig_category":"Art and fournitures artistiques. Eclairage et \u00e9quipements du foyer. Jeux and jouets. Souvenirs and o",
    "sg:phone":"+32 4 344 47 83",
    "sg:postcode":"4020",
    "sg:province":"Li\u00e8ge",
    "wof:name":"Blokker",
    "wof:placetype":"venue"
},
  "geometry": {"coordinates":[5.5814900398,50.6344223022],"type":"Point"}
}