{
  "type": "Feature",
  "properties": {
    "addr:full":"Wasserijstraat 10 Diepenbeek Limburg 3590",
    "addr:housenumber":"10",
    "addr:postcode":"3590",
    "addr:street":"Wasserijstraat",
    "iso:country":"BE",
    "sg:address":"Wasserijstraat 10",
    "sg:city":"Diepenbeek",
    "sg:orig_category":"Belastingconsulenten Boekhouders Diverse juridische dienstverlening",
    "sg:phone":"+32 11 32 40 04",
    "sg:postcode":"3590",
    "sg:province":"Limburg",
    "wof:name":"Zakenkantoor Lemmens & Zn",
    "wof:placetype":"venue"
},
  "geometry": {"coordinates":[5.4518818855,50.9260826111],"type":"Point"}
}