{
  "type": "Feature",
  "properties": {
    "addr:full":"Wijnheuvelenstraat 41 Sint-joost-ten-node/saint-josse-ten-noode Bruxelles-Capitale 1210",
    "addr:housenumber":"41",
    "addr:postcode":"1210",
    "addr:street":"Wijnheuvelenstraat",
    "iso:country":"BE",
    "sg:address":"Wijnheuvelenstraat 41",
    "sg:city":"Sint-joost-ten-node/saint-josse-ten-noode",
    "sg:orig_category":"Divers amusement Zalen voor culturele evenementen",
    "sg:phone":"+32 2 217 88 08",
    "sg:postcode":"1210",
    "sg:province":"Bruxelles-Capitale",
    "wof:name":"Th\u00c9\u00c2tre De Galafronie",
    "wof:placetype":"venue"
},
  "geometry": {"coordinates":[4.3744001389,50.8554191589],"type":"Point"}
}