{
  "type": "Feature",
  "properties": {
    "iso:country":"BE",
    "sg:address":"Heirbaan 309",
    "sg:city":"Lanaken",
    "sg:orig_category":"Location d'appareils audio-visuels. Animations diverses",
    "sg:phone":"+32 89 73 21 67",
    "sg:postcode":"3621",
    "sg:province":"Limburg",
    "wof:name":"Music Point Productions",
    "wof:placetype":"venue"
},
  "geometry": {"coordinates":[5.6829857826,50.925239563],"type":"Point"}
}