{
  "type": "Feature",
  "properties": {
    "addr:full":"Molenbaan 5 Baarle-hertog Antwerpen 2387",
    "addr:housenumber":"5",
    "addr:postcode":"2387",
    "addr:street":"Molenbaan",
    "iso:country":"BE",
    "sg:address":"Molenbaan 5",
    "sg:city":"Baarle-hertog",
    "sg:orig_category":"Herstellingen and onderhoud van auto's",
    "sg:phone":"+32 14 69 91 67",
    "sg:postcode":"2387",
    "sg:province":"Antwerpen",
    "wof:name":"Braspenning",
    "wof:placetype":"venue"
},
  "geometry": {"coordinates":[4.9319310188,51.4417266846],"type":"Point"}
}