{
  "type": "Feature",
  "properties": {
    "iso:country":"BE",
    "sg:address":"Sint-odradastraat 36",
    "sg:city":"Mol",
    "sg:orig_category":"Sportclubs Sportterreinen and installaties behalve sportcentra",
    "sg:phone":"+32 14 31 82 46",
    "sg:postcode":"2400",
    "sg:province":"Antwerpen",
    "wof:name":"K.f.c. Ezaart Sport Mol",
    "wof:placetype":"venue"
},
  "geometry": {"coordinates":[5.0790100098,51.1860542297],"type":"Point"}
}