{
  "type": "Feature",
  "properties": {
    "addr:full":"Avenue Lambermont 31 Ottignies-louvain-la-neuve Brabant Wallon 1342",
    "addr:housenumber":"31",
    "addr:postcode":"1342",
    "addr:street":"Avenue Lambermont",
    "iso:country":"BE",
    "sg:address":"Avenue Lambermont 31",
    "sg:city":"Ottignies-louvain-la-neuve",
    "sg:orig_category":"Landmeters and schatters",
    "sg:phone":"+32 10 41 93 49",
    "sg:postcode":"1342",
    "sg:province":"Brabant Wallon",
    "wof:name":"L. Ladri\u00c8re",
    "wof:placetype":"venue"
},
  "geometry": {"coordinates":[4.5444340706,50.6883850098],"type":"Point"}
}