{
  "type": "Feature",
  "properties": {
    "iso:country":"BE",
    "sg:address":"Rue Gilles Galler 22-24",
    "sg:city":"Li\u00e8ge 1 (sclessin)",
    "sg:classifiers":[
        {
            "category":"Manufacturing",
            "subcategory":"Metals",
            "type":"Manufacturing & Wholesale Goods"
        }
    ],
    "sg:phone":"+32 4 235 47 20",
    "sg:postcode":"4000",
    "sg:province":"Li\u00e8ge",
    "sg:tags":[
        "treatment",
        "surface"
    ],
    "wof:name":"Nitruration Moderne Sa",
    "wof:placetype":"venue"
},
  "geometry": {"coordinates":[5.538394928,50.609539032],"type":"Point"}
}