{
  "type": "Feature",
  "properties": {
    "addr:full":"Rue Petit Champ 63 Mons Hainaut 7012",
    "addr:housenumber":"63",
    "addr:postcode":"7012",
    "addr:street":"Rue Petit Champ;Hainaut",
    "iso:country":"BE",
    "sg:address":"Rue Petit Champ 63",
    "sg:city":"Mons",
    "sg:orig_category":"Kapsalons",
    "sg:phone":"+32 65 82 33 42",
    "sg:postcode":"7012",
    "sg:province":"Hainaut",
    "wof:name":"Coiffure Marie-paule",
    "wof:placetype":"venue"
},
  "geometry": {"coordinates":[3.8894600868,50.4481964111],"type":"Point"}
}