{
  "type": "Feature",
  "properties": {
    "iso:country":"BE",
    "sg:address":"Rue Auguste Lannoye 4",
    "sg:city":"Mont-saint-guibert",
    "sg:classifiers":[
        {
            "category":"Manufacturing",
            "subcategory":"Printing",
            "type":"Manufacturing & Wholesale Goods"
        }
    ],
    "sg:postcode":"1435",
    "sg:province":"Brabant Wallon",
    "sg:tags":[
        "paper",
        "waste"
    ],
    "wof:name":"Devriendt.recycling.sa Sa",
    "wof:placetype":"venue"
},
  "geometry": {"coordinates":[4.6052317619,50.638874054],"type":"Point"}
}