{
  "type": "Feature",
  "properties": {
    "addr:full":"Rue Pont-\u00e0-la-pont-faulx 19 P\u00e9ruwelz Hainaut 7600",
    "addr:housenumber":"19",
    "addr:postcode":"7600",
    "addr:street":"Rue Pont-A\u0300-La-Pont-Faulx",
    "iso:country":"BE",
    "sg:address":"Rue Pont-\u00e0-la-pont-faulx 19",
    "sg:city":"P\u00e9ruwelz",
    "sg:classifiers":[
        {
            "category":"Utilities",
            "subcategory":"Mobile Phone",
            "type":"Services"
        }
    ],
    "sg:phone":"+32 69 58 05 37",
    "sg:postcode":"7600",
    "sg:province":"Hainaut",
    "sg:tags":[
        "access",
        "gsm",
        "-",
        "apparatus"
    ],
    "wof:name":"Gsm Center",
    "wof:placetype":"venue"
},
  "geometry": {"coordinates":[3.5946381092,50.5108222961],"type":"Point"}
}