{
  "type": "Feature",
  "properties": {
    "addr:full":"Avenue G\u00e9n\u00e9ral Baron Empain 29 Bruxelles (woluwe-saint-pierre) Bruxelles-Capitale 1150",
    "addr:housenumber":"29",
    "addr:postcode":"1150",
    "addr:street":"Avenue Ge\u0301Ne\u0301Ral Baron Empain",
    "iso:country":"BE",
    "sg:address":"Avenue G\u00e9n\u00e9ral Baron Empain 29",
    "sg:city":"Bruxelles (woluwe-saint-pierre)",
    "sg:classifiers":[
        {
            "category":"Professional",
            "subcategory":"Accounting & Tax Preparation",
            "type":"Services"
        }
    ],
    "sg:phone":"+32 2 762 34 13",
    "sg:postcode":"1150",
    "sg:province":"Bruxelles-Capitale",
    "sg:tags":[
        "accountant"
    ],
    "wof:name":"Francq R",
    "wof:placetype":"venue"
},
  "geometry": {"coordinates":[4.4396858215,50.8247642517],"type":"Point"}
}