{
  "type": "Feature",
  "properties": {
    "iso:country":"BE",
    "sg:address":"Rue Bois Du Prince",
    "sg:city":"Mettet",
    "sg:classifiers":[
        {
            "category":"Building & Trades",
            "subcategory":"Construction",
            "type":"Services"
        }
    ],
    "sg:phone":"+32 71 72 90 23",
    "sg:postcode":"5640",
    "sg:province":"Namur",
    "sg:tags":[
        "installation",
        "-",
        "central",
        "heating"
    ],
    "wof:name":"Poncelet Sprl",
    "wof:placetype":"venue"
},
  "geometry": {"coordinates":[4.6477079391,50.3417167664],"type":"Point"}
}