{
  "type": "Feature",
  "properties": {
    "addr:full":"Rijksweg 65 Harelbeke West-Vlaanderen 8531",
    "addr:housenumber":"65",
    "addr:postcode":"8531",
    "addr:street":"Rijksweg",
    "iso:country":"BE",
    "sg:address":"Rijksweg 65",
    "sg:city":"Harelbeke",
    "sg:orig_category":"D\u00e9taillants en pi\u00e8ces and accessoires de voitures. Equipements pour la construction Pi\u00e8ces and acces",
    "sg:phone":"+32 56 71 04 38",
    "sg:postcode":"8531",
    "sg:province":"West-Vlaanderen",
    "wof:name":"B.m.s.t.",
    "wof:placetype":"venue"
},
  "geometry": {"coordinates":[3.3104400635,50.8748130798],"type":"Point"}
}