{
  "type": "Feature",
  "properties": {
    "iso:country":"BE",
    "sg:address":"Rue Alphonse Gilles 8",
    "sg:city":"Aywaille",
    "sg:orig_category":"M\u00e9decins and sp\u00e9cialistes",
    "sg:phone":"+32 4 384 51 78",
    "sg:postcode":"4920",
    "sg:province":"Li\u00e8ge",
    "wof:name":"Mireille Leyens",
    "wof:placetype":"venue"
},
  "geometry": {"coordinates":[5.6729359627,50.4733772278],"type":"Point"}
}