{
  "type": "Feature",
  "properties": {
    "addr:full":"Matrozenlaan 5 Nieuwpoort West-Vlaanderen 8620",
    "addr:housenumber":"5",
    "addr:postcode":"8620",
    "addr:street":"Matrozenlaan",
    "iso:country":"BE",
    "sg:address":"Matrozenlaan 5",
    "sg:city":"Nieuwpoort",
    "sg:orig_category":"Kampeerterreinen",
    "sg:phone":"+32 58 23 37 59",
    "sg:postcode":"8620",
    "sg:province":"West-Vlaanderen",
    "wof:name":"Gudrun Deseure",
    "wof:placetype":"venue"
},
  "geometry": {"coordinates":[2.746776104,51.1554107666],"type":"Point"}
}