{
  "type": "Feature",
  "properties": {
    "iso:country":"BE",
    "sg:address":"Dellestraat 10",
    "sg:city":"Lummen",
    "sg:classifiers":[
        {
            "category":"Utilities",
            "subcategory":"Recycling",
            "type":"Services"
        }
    ],
    "sg:phone":"+32 13 53 06 60",
    "sg:postcode":"3560",
    "sg:province":"Limburg",
    "wof:name":"G.r.l. Glasrecyclage",
    "wof:placetype":"venue"
},
  "geometry": {"coordinates":[5.2368569374,50.9927558899],"type":"Point"}
}