{
  "type": "Feature",
  "properties": {
    "addr:full":"Heymansdries 39 Sint-genesius-rode/rhode-saint-gen\u00c8se Vlaams-Brabant 1640",
    "addr:housenumber":"39",
    "addr:postcode":"1640",
    "addr:street":"Heymansdries",
    "iso:country":"BE",
    "sg:address":"Heymansdries 39",
    "sg:city":"Sint-genesius-rode/rhode-saint-gen\u00c8se",
    "sg:classifiers":[
        {
            "category":"Arena",
            "subcategory":"Sports Club",
            "type":"Entertainment"
        }
    ],
    "sg:phone":"+32 495 75 36 41",
    "sg:postcode":"1640",
    "sg:province":"Vlaams-Brabant",
    "sg:tags":[
        "de"
    ],
    "wof:name":"Waterloo Natation",
    "wof:placetype":"venue"
},
  "geometry": {"coordinates":[4.3622150421,50.7363395691],"type":"Point"}
}