{
  "type": "Feature",
  "properties": {
    "addr:full":"Zilverdennenlaan 7 Lanaken Limburg 3620",
    "addr:housenumber":"7",
    "addr:postcode":"3620",
    "addr:street":"Zilverdennenlaan",
    "iso:country":"BE",
    "sg:address":"Zilverdennenlaan 7",
    "sg:city":"Lanaken",
    "sg:orig_category":"Kapsalons",
    "sg:phone":"+32 89 71 12 41",
    "sg:postcode":"3620",
    "sg:province":"Limburg",
    "wof:name":"Marie-jeanne Colla",
    "wof:placetype":"venue"
},
  "geometry": {"coordinates":[5.6551351547,50.8912277222],"type":"Point"}
}