{
  "type": "Feature",
  "properties": {
    "iso:country":"BE",
    "sg:address":"Rue De Ninove 46",
    "sg:city":"Jemelle",
    "sg:orig_category":"Chaussures",
    "sg:phone":"+32 84 21 15 48",
    "sg:postcode":"5580",
    "sg:province":"Namur",
    "wof:name":"Les Brodequins",
    "wof:placetype":"venue"
},
  "geometry": {"coordinates":[5.2605772018,50.1628723145],"type":"Point"}
}