{
  "type": "Feature",
  "properties": {
    "iso:country":"BE",
    "sg:address":"Rue P.dubois 34",
    "sg:city":"Daverdisse",
    "sg:orig_category":"Binnenhuisarchitecten",
    "sg:phone":"+32 84 38 95 02",
    "sg:postcode":"6929",
    "sg:province":"Luxembourg",
    "wof:name":"Genevi\u00c8ve Migeal De Cartier",
    "wof:placetype":"venue"
},
  "geometry": {"coordinates":[5.1179409027,50.0208740234],"type":"Point"}
}