{
  "type": "Feature",
  "properties": {
    "addr:full":"Rue Reine Astrid 40 Engis Li\u00e8ge 4480",
    "addr:housenumber":"40",
    "addr:postcode":"4480",
    "addr:street":"Rue Reine Astrid",
    "iso:country":"BE",
    "sg:address":"Rue Reine Astrid 40",
    "sg:city":"Engis",
    "sg:orig_category":"Enseignement maternel and primaire",
    "sg:phone":"+32 4 275 28 78",
    "sg:postcode":"4480",
    "sg:province":"Li\u00e8ge",
    "wof:name":"Ecole Fond. Communale",
    "wof:placetype":"venue"
},
  "geometry": {"coordinates":[5.402905941,50.5848999023],"type":"Point"}
}