{
  "type": "Feature",
  "properties": {
    "addr:full":"Avenue Emile Gryson 1 Bruxelles (anderlecht) Bruxelles-Capitale 1070",
    "addr:housenumber":"1",
    "addr:postcode":"1070",
    "addr:street":"Avenue Emile Gryson",
    "iso:country":"BE",
    "sg:address":"Avenue Emile Gryson 1",
    "sg:city":"Bruxelles (anderlecht)",
    "sg:classifiers":[
        {
            "category":"Education",
            "subcategory":"School",
            "type":"Public Place"
        }
    ],
    "sg:phone":"+32 2 526 76 00",
    "sg:postcode":"1070",
    "sg:province":"Bruxelles-Capitale",
    "sg:tags":[
        "secondary"
    ],
    "wof:name":"Elishout",
    "wof:placetype":"venue"
},
  "geometry": {"coordinates":[4.2954311371,50.8161201477],"type":"Point"}
}