{
  "type": "Feature",
  "properties": {
    "iso:country":"BE",
    "sg:address":"Lombardsijdestraat 3 Box 3",
    "sg:city":"Nieuwpoort",
    "sg:classifiers":[
        {
            "category":"Shopping",
            "subcategory":"Clothing, Apparel, & Fashions",
            "type":"Retail Goods"
        }
    ],
    "sg:phone":"+32 58 24 33 27",
    "sg:postcode":"8620",
    "sg:province":"West-Vlaanderen",
    "sg:tags":[
        "underwear",
        "lingerie",
        "-"
    ],
    "wof:name":"Larissa Lingerie",
    "wof:placetype":"venue"
},
  "geometry": {"coordinates":[2.722151041,51.1511611938],"type":"Point"}
}