{
  "type": "Feature",
  "properties": {
    "addr:full":"Rue Louis Mar\u00e9chal 99a Oreye Li\u00e8ge 4360",
    "addr:housenumber":"99a",
    "addr:postcode":"4360",
    "addr:street":"Rue Louis Mare\u0301Chal",
    "iso:country":"BE",
    "sg:address":"Rue Louis Mar\u00e9chal 99a",
    "sg:city":"Oreye",
    "sg:classifiers":[
        {
            "category":"Manufacturing",
            "subcategory":"Lumber",
            "type":"Manufacturing & Wholesale Goods"
        }
    ],
    "sg:phone":"+32 19 67 71 86",
    "sg:postcode":"4360",
    "sg:province":"Li\u00e8ge",
    "sg:tags":[
        "timber"
    ],
    "wof:name":"Renard Bois",
    "wof:placetype":"venue"
},
  "geometry": {"coordinates":[5.3350710869,50.7027587891],"type":"Point"}
}