{
  "type": "Feature",
  "properties": {
    "iso:country":"BE",
    "sg:address":"Steenweg 98",
    "sg:city":"Heers",
    "sg:classifiers":[
        {
            "category":"Food & Beverages",
            "subcategory":"Meat & Fish",
            "type":"Retail Goods"
        }
    ],
    "sg:phone":"+32 11 48 51 49",
    "sg:postcode":"3870",
    "sg:province":"Limburg",
    "sg:tags":[
        "poultry",
        "whol",
        "game",
        "-"
    ],
    "wof:name":"Aleda Bvba",
    "wof:placetype":"venue"
},
  "geometry": {"coordinates":[5.2888760567,50.7536277771],"type":"Point"}
}