{
  "type": "Feature",
  "properties": {
    "addr:full":"Place Des Alli\u00c9s 2 Seneffe Hainaut 7180",
    "addr:housenumber":"2",
    "addr:postcode":"7180",
    "addr:street":"Place Des Allie\u0301S",
    "iso:country":"BE",
    "sg:address":"Place Des Alli\u00c9s 2",
    "sg:city":"Seneffe",
    "sg:orig_category":"M\u00e9decines alternatives",
    "sg:phone":"+32 64 54 15 41",
    "sg:postcode":"7180",
    "sg:province":"Hainaut",
    "wof:name":"Osteopathe Browet Olivier",
    "wof:placetype":"venue"
},
  "geometry": {"coordinates":[4.2555122375,50.5284729004],"type":"Point"}
}