{
  "type": "Feature",
  "properties": {
    "addr:full":"Hoogbuul Olen Antwerpen 2250",
    "addr:postcode":"2250",
    "addr:street":"Hoogbuul",
    "iso:country":"BE",
    "sg:address":"Hoogbuul",
    "sg:city":"Olen",
    "sg:orig_category":"Watersport-, Sport- and Kampeerbenodigdheden Verhuur",
    "sg:phone":"+32 11 39 21 92",
    "sg:postcode":"2250",
    "sg:province":"Antwerpen",
    "wof:name":"Gerro",
    "wof:placetype":"venue"
},
  "geometry": {"coordinates":[4.8931040764,51.1484642029],"type":"Point"}
}