{
  "type": "Feature",
  "properties": {
    "iso:country":"BE",
    "sg:address":"Hortensiastraat 5",
    "sg:city":"Antwerpen",
    "sg:classifiers":[
        {
            "category":"Insurance",
            "subcategory":"Life Insurance",
            "type":"Services"
        }
    ],
    "sg:phone":"+32 3 238 60 62",
    "sg:postcode":"2020",
    "sg:province":"Antwerpen",
    "sg:tags":[
        "assurance"
    ],
    "wof:name":"L. Gobin",
    "wof:placetype":"venue"
},
  "geometry": {"coordinates":[4.3933987617,51.1849517822],"type":"Point"}
}