{
  "type": "Feature",
  "properties": {
    "iso:country":"BE",
    "sg:address":"Chemin Morel 10",
    "sg:city":"Virton",
    "sg:orig_category":"Banques and organismes de cr\u00e9dit",
    "sg:phone":"+32 63 57 72 33",
    "sg:postcode":"6762",
    "sg:province":"Luxembourg",
    "wof:name":"Axa",
    "wof:placetype":"venue"
},
  "geometry": {"coordinates":[5.5332231522,49.5546951294],"type":"Point"}
}