{
  "type": "Feature",
  "properties": {
    "iso:country":"BE",
    "sg:address":"Moeskroenstraat 651",
    "sg:city":"Menen",
    "sg:classifiers":[
        {
            "category":"Food & Beverages",
            "subcategory":"Groceries & Convenience Stores",
            "type":"Retail Goods"
        }
    ],
    "sg:phone":"+32 56 40 20 43",
    "sg:postcode":"8930",
    "sg:province":"West-Vlaanderen",
    "sg:tags":[
        "grocer"
    ],
    "wof:name":"Samyn N",
    "wof:placetype":"venue"
},
  "geometry": {"coordinates":[3.1586298943,50.787361145],"type":"Point"}
}