{
  "type": "Feature",
  "properties": {
    "iso:country":"BE",
    "sg:address":"Rue De N\u00c9verl\u00c9 11",
    "sg:city":"Namur",
    "sg:orig_category":"R\u00e9alisation de programmes and logiciels. Conseils en syst\u00e8mes informatiques",
    "sg:phone":"+32 81 55 42 11",
    "sg:postcode":"5020",
    "sg:province":"Namur",
    "wof:name":"Siemens Nixdorf Train. C.",
    "wof:placetype":"venue"
},
  "geometry": {"coordinates":[4.8026847839,50.4923324585],"type":"Point"}
}