{
  "type": "Feature",
  "properties": {
    "addr:full":"Chauss\u00e9e De Courtrai 7 Tournai (ramegnies-chin) Hainaut 7520",
    "addr:housenumber":"7",
    "addr:postcode":"7520",
    "addr:street":"Chausse\u0301E De Courtrai",
    "iso:country":"BE",
    "sg:address":"Chauss\u00e9e De Courtrai 7",
    "sg:city":"Tournai (ramegnies-chin)",
    "sg:classifiers":[
        {
            "category":"Insurance",
            "subcategory":"Insurance Agent",
            "type":"Services"
        }
    ],
    "sg:phone":"+32 69 44 66 44",
    "sg:postcode":"7520",
    "sg:province":"Hainaut",
    "sg:tags":[
        "broker"
    ],
    "wof:name":"Claeyssens Assurances Sprl",
    "wof:placetype":"venue"
},
  "geometry": {"coordinates":[3.3871409893,50.6084289551],"type":"Point"}
}