{
  "type": "Feature",
  "properties": {
    "addr:full":"Rue De Ciney 16 Ohey Namur 5350",
    "addr:housenumber":"16",
    "addr:postcode":"5350",
    "addr:street":"Rue De Ciney",
    "iso:country":"BE",
    "sg:address":"Rue De Ciney 16",
    "sg:city":"Ohey",
    "sg:classifiers":[
        {
            "category":"Retail",
            "subcategory":"Veterinary Services",
            "type":"Services"
        }
    ],
    "sg:phone":"+32 85 61 29 49",
    "sg:postcode":"5350",
    "sg:province":"Namur",
    "sg:tags":[
        "veterinarian"
    ],
    "wof:name":"Crevits B",
    "wof:placetype":"venue"
},
  "geometry": {"coordinates":[5.1251568794,50.4332084656],"type":"Point"}
}