{
  "type": "Feature",
  "properties": {
    "addr:full":"Rue Des Clairisses 13 Tournai Hainaut 7500",
    "addr:housenumber":"13",
    "addr:postcode":"7500",
    "addr:street":"Rue Des Clairisses",
    "iso:country":"BE",
    "sg:address":"Rue Des Clairisses 13",
    "sg:city":"Tournai",
    "sg:classifiers":[
        {
            "category":"Health Services",
            "subcategory":"Hospital",
            "type":"Services"
        }
    ],
    "sg:phone":"+32 69 22 67 58",
    "sg:postcode":"7500",
    "sg:province":"Hainaut",
    "wof:name":"La Famille Heureuse",
    "wof:placetype":"venue"
},
  "geometry": {"coordinates":[3.3914680481,50.6055335999],"type":"Point"}
}