{
  "type": "Feature",
  "properties": {
    "addr:full":"Rue De La Tete D\u00b4or 5 Tournai Hainaut 7500",
    "addr:housenumber":"5",
    "addr:postcode":"7500",
    "addr:street":"Rue De La Tete D\u00b4Or",
    "iso:country":"BE",
    "sg:address":"Rue De La Tete D\u00b4or 5",
    "sg:city":"Tournai",
    "sg:classifiers":[
        {
            "category":"Personal",
            "subcategory":"Beauty Salon",
            "type":"Services"
        }
    ],
    "sg:phone":"+32 69 84 65 65",
    "sg:postcode":"7500",
    "sg:province":"Hainaut",
    "sg:tags":[
        "de",
        "coiffure"
    ],
    "wof:name":"Coiffure Lamanna D.",
    "wof:placetype":"venue"
},
  "geometry": {"coordinates":[3.3901059628,50.6053657532],"type":"Point"}
}