{
  "type": "Feature",
  "properties": {
    "iso:country":"BE",
    "sg:address":"Zilverstraat 43",
    "sg:city":"Brugge",
    "sg:orig_category":"Opvangtehuizen and vluchthuizen",
    "sg:phone":"+32 50 44 58 15",
    "sg:postcode":"8000",
    "sg:province":"West-Vlaanderen",
    "wof:name":"Dienst Maatschapp. Werk",
    "wof:placetype":"venue"
},
  "geometry": {"coordinates":[3.2207930088,51.2062072754],"type":"Point"}
}