{
  "type": "Feature",
  "properties": {
    "iso:country":"BE",
    "sg:address":"Rue De Birmingham 78-84",
    "sg:city":"Bruxelles (molenbeek-saint-jean)",
    "sg:classifiers":[
        {
            "category":"Retail",
            "subcategory":"Auto Repair",
            "type":"Services"
        }
    ],
    "sg:phone":"+32 2 410 11 94",
    "sg:postcode":"1080",
    "sg:province":"Bruxelles-Capitale",
    "sg:tags":[
        "automobile-body"
    ],
    "wof:name":"Carrosserie Dimacar Sprl",
    "wof:placetype":"venue"
},
  "geometry": {"coordinates":[4.3245801926,50.8464622498],"type":"Point"}
}