{
  "type": "Feature",
  "properties": {
    "addr:full":"Zuidlaan 113 Wetteren Oost-Vlaanderen 9230",
    "addr:housenumber":"113",
    "addr:postcode":"9230",
    "addr:street":"Zuidlaan",
    "iso:country":"BE",
    "sg:address":"Zuidlaan 113",
    "sg:city":"Wetteren",
    "sg:classifiers":[
        {
            "category":"Home & Garden",
            "subcategory":"Building Materials",
            "type":"Retail Goods"
        }
    ],
    "sg:phone":"+32 9 369 89 66",
    "sg:postcode":"9230",
    "sg:province":"Oost-Vlaanderen",
    "sg:tags":[
        "article",
        "-",
        "do-it-yourself"
    ],
    "wof:name":"Brico-wetteren",
    "wof:placetype":"venue"
},
  "geometry": {"coordinates":[3.8493950367,50.9890327454],"type":"Point"}
}