{
  "type": "Feature",
  "properties": {
    "iso:country":"BE",
    "sg:address":"Avenue Des Nymphes 17",
    "sg:city":"Watermaal-bosvoorde/watermael-boitsfort",
    "sg:classifiers":[
        {
            "category":"Arena",
            "subcategory":"Sports Club",
            "type":"Entertainment"
        }
    ],
    "sg:phone":"+32 2 660 21 67",
    "sg:postcode":"1170",
    "sg:province":"Bruxelles-Capitale",
    "sg:tags":[
        "terrain",
        "hors",
        "de",
        "installation",
        "sportifs"
    ],
    "wof:name":"F.c. Schneider",
    "wof:placetype":"venue"
},
  "geometry": {"coordinates":[4.4141159058,50.8056297302],"type":"Point"}
}