{
  "type": "Feature",
  "properties": {
    "addr:full":"Berlaarsesteenweg 128b1 Lier Antwerpen 2500",
    "addr:housenumber":"128b1",
    "addr:postcode":"2500",
    "addr:street":"Berlaarsesteenweg",
    "iso:country":"BE",
    "sg:address":"Berlaarsesteenweg 128b1",
    "sg:city":"Lier",
    "sg:orig_category":"Mat\u00e9riaux de construction Gr",
    "sg:phone":"+32 3 491 82 58",
    "sg:postcode":"2500",
    "sg:province":"Antwerpen",
    "wof:name":"Handelsonderneming Van Den Broeck",
    "wof:placetype":"venue"
},
  "geometry": {"coordinates":[4.5883798599,51.1283416748],"type":"Point"}
}