{
  "type": "Feature",
  "properties": {
    "addr:full":"Kolonel Dusartplein 29 Hasselt Limburg 3500",
    "addr:housenumber":"29",
    "addr:postcode":"3500",
    "addr:street":"Kolonel Dusartplein",
    "iso:country":"BE",
    "sg:address":"Kolonel Dusartplein 29",
    "sg:city":"Hasselt",
    "sg:orig_category":"M\u00e9decins and sp\u00e9cialistes",
    "sg:phone":"+32 11 22 55 53",
    "sg:postcode":"3500",
    "sg:province":"Limburg",
    "wof:name":"M. Papy",
    "wof:placetype":"venue"
},
  "geometry": {"coordinates":[5.3448171616,50.9316711426],"type":"Point"}
}