{
  "type": "Feature",
  "properties": {
    "iso:country":"BE",
    "sg:address":"Rue De La Paix 2",
    "sg:city":"Le Roeulx (thieu)",
    "sg:classifiers":[
        {
            "category":"Bars & Pubs",
            "type":"Food & Drink"
        }
    ],
    "sg:phone":"+32 64 66 46 79",
    "sg:postcode":"7070",
    "sg:province":"Hainaut",
    "wof:name":"Maison Du Peuple",
    "wof:placetype":"venue"
},
  "geometry": {"coordinates":[4.0936980247,50.4751281738],"type":"Point"}
}