{
  "type": "Feature",
  "properties": {
    "addr:full":"Chemin Aux Fraises 21 Pepinster Li\u00e8ge 4860",
    "addr:housenumber":"21",
    "addr:postcode":"4860",
    "addr:street":"Chemin Aux Fraises",
    "iso:country":"BE",
    "sg:address":"Chemin Aux Fraises 21",
    "sg:city":"Pepinster",
    "sg:classifiers":[
        {
            "category":"Building & Trades",
            "subcategory":"Plumbing",
            "type":"Services"
        }
    ],
    "sg:phone":"+32 87 46 11 34",
    "sg:postcode":"4860",
    "sg:province":"Li\u00e8ge",
    "sg:tags":[
        "contractor"
    ],
    "wof:name":"Benoit Mar\u00e9chal Sprl",
    "wof:placetype":"venue"
},
  "geometry": {"coordinates":[5.8032469749,50.5693511963],"type":"Point"}
}