{
  "type": "Feature",
  "properties": {
    "addr:full":"Rue Du Ch\u00eane 7 Oupeye Li\u00e8ge 4680",
    "addr:housenumber":"7",
    "addr:postcode":"4680",
    "addr:street":"Rue Du Che\u0302Ne",
    "iso:country":"BE",
    "sg:address":"Rue Du Ch\u00eane 7",
    "sg:city":"Oupeye",
    "sg:classifiers":[
        {
            "category":"Health Services",
            "subcategory":"Health Practitioner",
            "type":"Services"
        }
    ],
    "sg:phone":"+32 4 264 52 94",
    "sg:postcode":"4680",
    "sg:province":"Li\u00e8ge",
    "sg:tags":[
        "physiotherapist"
    ],
    "wof:name":"Brigode M",
    "wof:placetype":"venue"
},
  "geometry": {"coordinates":[5.6406068802,50.7077522278],"type":"Point"}
}