{
  "type": "Feature",
  "properties": {
    "iso:country":"BE",
    "sg:address":"Rue Des Tiennes 19",
    "sg:city":"Lasne (lasne-chapelle-saint-lambert)",
    "sg:classifiers":[
        {
            "category":"Professional",
            "subcategory":"Management & Consulting",
            "type":"Services"
        }
    ],
    "sg:phone":"+32 2 633 32 99",
    "sg:postcode":"1380",
    "sg:province":"Brabant Wallon",
    "sg:tags":[
        "consultant"
    ],
    "wof:name":"Cortes Sprl",
    "wof:placetype":"venue"
},
  "geometry": {"coordinates":[4.4896769524,50.6713943481],"type":"Point"}
}