{
  "type": "Feature",
  "properties": {
    "iso:country":"BE",
    "sg:address":"Kessel-losesteenweg 17",
    "sg:city":"Leuven",
    "sg:classifiers":[
        {
            "category":"Insurance",
            "subcategory":"Life Insurance",
            "type":"Services"
        }
    ],
    "sg:phone":"+32 16 44 53 79",
    "sg:postcode":"3012",
    "sg:province":"Vlaams-Brabant",
    "sg:tags":[
        "assurance"
    ],
    "wof:name":"Steeno",
    "wof:placetype":"venue"
},
  "geometry": {"coordinates":[4.7146291733,50.9098701477],"type":"Point"}
}