{
  "type": "Feature",
  "properties": {
    "iso:country":"BE",
    "sg:address":"Demerstraat 19",
    "sg:city":"Diest",
    "sg:orig_category":"V\u00eatements. V\u00eatements pour Hommes. V\u00eatements pour Dames",
    "sg:phone":"+32 13 31 13 30",
    "sg:postcode":"3290",
    "sg:province":"Vlaams-Brabant",
    "wof:name":"Smet",
    "wof:placetype":"venue"
},
  "geometry": {"coordinates":[5.0494961739,50.9860458374],"type":"Point"}
}