{
  "type": "Feature",
  "properties": {
    "iso:country":"BE",
    "sg:address":"Rozendalestraat 20",
    "sg:city":"Wingene",
    "sg:classifiers":[
        {
            "category":"Health Services",
            "subcategory":"Health Practitioner",
            "type":"Services"
        }
    ],
    "sg:phone":"+32 51 65 56 01",
    "sg:postcode":"8750",
    "sg:province":"West-Vlaanderen",
    "sg:tags":[
        "physiotherapist"
    ],
    "wof:name":"Janssens Jeroen",
    "wof:placetype":"venue"
},
  "geometry": {"coordinates":[3.2725110054,51.0602722168],"type":"Point"}
}