{
  "type": "Feature",
  "properties": {
    "addr:full":"Wielewaalstraat 3 Jabbeke West-Vlaanderen 8490",
    "addr:housenumber":"3",
    "addr:postcode":"8490",
    "addr:street":"Wielewaalstraat",
    "iso:country":"BE",
    "sg:address":"Wielewaalstraat 3",
    "sg:city":"Jabbeke",
    "sg:orig_category":"Administration d'immeubles",
    "sg:phone":"+32 50 81 39 55",
    "sg:postcode":"8490",
    "sg:province":"West-Vlaanderen",
    "wof:name":"Henry Vancanneyt",
    "wof:placetype":"venue"
},
  "geometry": {"coordinates":[3.0848789215,51.1870307922],"type":"Point"}
}