{
  "type": "Feature",
  "properties": {
    "addr:full":"Kadodderstraat 54 Mechelen Antwerpen 2800",
    "addr:housenumber":"54",
    "addr:postcode":"2800",
    "addr:street":"Kadodderstraat",
    "iso:country":"BE",
    "sg:address":"Kadodderstraat 54",
    "sg:city":"Mechelen",
    "sg:classifiers":[
        {
            "category":"Health Services",
            "subcategory":"Health Practitioner",
            "type":"Services"
        }
    ],
    "sg:phone":"+32 15 20 79 71",
    "sg:postcode":"2800",
    "sg:province":"Antwerpen",
    "sg:tags":[
        "physiotherapist"
    ],
    "wof:name":"Diels Ann",
    "wof:placetype":"venue"
},
  "geometry": {"coordinates":[4.4812397957,51.0451202393],"type":"Point"}
}