{
  "type": "Feature",
  "properties": {
    "iso:country":"BE",
    "sg:address":"Quai Du Brabant 4",
    "sg:city":"Charleroi",
    "sg:orig_category":"M\u00e9decins and sp\u00e9cialistes",
    "sg:phone":"+32 71 35 58 34",
    "sg:postcode":"6000",
    "sg:province":"Hainaut",
    "wof:name":"Daniel W\u00c9ry",
    "wof:placetype":"venue"
},
  "geometry": {"coordinates":[4.4398269653,50.4062271118],"type":"Point"}
}