{
  "type": "Feature",
  "properties": {
    "addr:full":"Rue Du Croquet 2 Tournai Hainaut 7540",
    "addr:housenumber":"2",
    "addr:postcode":"7540",
    "addr:street":"Rue Du Croquet",
    "iso:country":"BE",
    "sg:address":"Rue Du Croquet 2",
    "sg:city":"Tournai",
    "sg:orig_category":"Eleveurs de bovins",
    "sg:phone":"+32 69 22 54 36",
    "sg:postcode":"7540",
    "sg:province":"Hainaut",
    "wof:name":"Francis Desmet",
    "wof:placetype":"venue"
},
  "geometry": {"coordinates":[3.4427669048,50.6206970215],"type":"Point"}
}