{
  "type": "Feature",
  "properties": {
    "iso:country":"BE",
    "sg:address":"Industrieweg 17",
    "sg:city":"Heusden-zolder (zolder)",
    "sg:classifiers":[
        {
            "category":"Utilities",
            "subcategory":"Fuel Oil & Lpg",
            "type":"Services"
        }
    ],
    "sg:phone":"+32 13 53 21 65",
    "sg:postcode":"3550",
    "sg:province":"Limburg",
    "wof:name":"A Plus Oil",
    "wof:placetype":"venue"
},
  "geometry": {"coordinates":[5.2423510551,50.9933166504],"type":"Point"}
}