{
  "type": "Feature",
  "properties": {
    "addr:full":"Ninoofsestraat 23 Geraardsbergen (idegem) Oost-Vlaanderen 9506",
    "addr:housenumber":"23",
    "addr:postcode":"9506",
    "addr:street":"Ninoofsestraat",
    "iso:country":"BE",
    "sg:address":"Ninoofsestraat 23",
    "sg:city":"Geraardsbergen (idegem)",
    "sg:classifiers":[
        {
            "category":"Building & Trades",
            "subcategory":"Electrical",
            "type":"Services"
        }
    ],
    "sg:phone":"+32 54 50 06 18",
    "sg:postcode":"9506",
    "sg:province":"Oost-Vlaanderen",
    "sg:tags":[
        "heating"
    ],
    "wof:name":"E.w.r. Algemene Onderneming",
    "wof:placetype":"venue"
},
  "geometry": {"coordinates":[3.8985300064,50.7987060547],"type":"Point"}
}