{
  "type": "Feature",
  "properties": {
    "iso:country":"BE",
    "sg:address":"Rue Du G\u00e9n\u00e9ral Jacques 236",
    "sg:city":"Chaudfontaine (vaux-sous-ch\u00e8vremont)",
    "sg:classifiers":[
        {
            "category":"Arena",
            "subcategory":"Sports Club",
            "type":"Entertainment"
        }
    ],
    "sg:phone":"+32 4 361 08 20",
    "sg:postcode":"4051",
    "sg:province":"Li\u00e8ge",
    "wof:name":"Fort Aventures De Chaudfontaine",
    "wof:placetype":"venue"
},
  "geometry": {"coordinates":[5.6319870949,50.595199585],"type":"Point"}
}