{
  "type": "Feature",
  "properties": {
    "addr:full":"Avenue Des Ducs 50 Wezembeek-oppem Vlaams-Brabant 1970",
    "addr:housenumber":"50",
    "addr:postcode":"1970",
    "addr:street":"Avenue Des Ducs",
    "iso:country":"BE",
    "sg:address":"Avenue Des Ducs 50",
    "sg:city":"Wezembeek-oppem",
    "sg:classifiers":[
        {
            "category":"Health Services",
            "subcategory":"Health Practitioner",
            "type":"Services"
        }
    ],
    "sg:phone":"+32 2 731 95 31",
    "sg:postcode":"1970",
    "sg:province":"Vlaams-Brabant",
    "sg:tags":[
        "physiotherapist"
    ],
    "wof:name":"Mertens Monique",
    "wof:placetype":"venue"
},
  "geometry": {"coordinates":[4.478456974,50.8370704651],"type":"Point"}
}