{
  "type": "Feature",
  "properties": {
    "addr:full":"Rue Du Bemel 195 Sint-pieters-woluwe/woluwe-saint-pierre Bruxelles-Capitale 1150",
    "addr:housenumber":"195",
    "addr:postcode":"1150",
    "addr:street":"Rue Du Bemel;/",
    "iso:country":"BE",
    "sg:address":"Rue Du Bemel 195",
    "sg:city":"Sint-pieters-woluwe/woluwe-saint-pierre",
    "sg:orig_category":"S\u00e9curit\u00e9 sociale",
    "sg:phone":"+32 2 771 84 53",
    "sg:postcode":"1150",
    "sg:province":"Bruxelles-Capitale",
    "wof:name":"Onafh. Ziekenfonds 503/mutualit\u00c9 Libre",
    "wof:placetype":"venue"
},
  "geometry": {"coordinates":[4.412981987,50.830657959],"type":"Point"}
}