{
  "type": "Feature",
  "properties": {
    "iso:country":"BE",
    "sg:address":"Rue De Bruxelles 211",
    "sg:city":"Awans",
    "sg:classifiers":[
        {
            "category":"Personal",
            "subcategory":"Massage",
            "type":"Services"
        }
    ],
    "sg:phone":"+32 4 239 02 51",
    "sg:postcode":"4340",
    "sg:province":"Li\u00e8ge",
    "wof:name":"Vip",
    "wof:placetype":"venue"
},
  "geometry": {"coordinates":[5.4892649651,50.6727790833],"type":"Point"}
}