{
  "type": "Feature",
  "properties": {
    "addr:full":"Faubourg-saint-germain 75 Couvin Namur 5660",
    "addr:housenumber":"75",
    "addr:postcode":"5660",
    "addr:street":"Faubourg-Saint-Germain",
    "iso:country":"BE",
    "sg:address":"Faubourg-saint-germain 75",
    "sg:city":"Couvin",
    "sg:classifiers":[
        {
            "category":"Restaurant",
            "type":"Food & Drink"
        }
    ],
    "sg:phone":"+32 60 34 64 19",
    "sg:postcode":"5660",
    "sg:province":"Namur",
    "wof:name":"Restaurant L'arlecchino",
    "wof:placetype":"venue"
},
  "geometry": {"coordinates":[4.493929863,50.0523834229],"type":"Point"}
}