{
  "type": "Feature",
  "properties": {
    "iso:country":"BE",
    "sg:address":"Ieperstraat 12",
    "sg:city":"Kortemark",
    "sg:orig_category":"WAPENS AND MUNITIE",
    "sg:phone":"+32 51 56 77 34",
    "sg:postcode":"8610",
    "sg:province":"West-Vlaanderen",
    "wof:name":"Willy Declerck",
    "wof:placetype":"venue"
},
  "geometry": {"coordinates":[3.0629270077,51.02526474],"type":"Point"}
}