{
  "type": "Feature",
  "properties": {
    "addr:full":"Land Van Waaslaan 19 Gent Oost-Vlaanderen 9000",
    "addr:housenumber":"19",
    "addr:postcode":"9000",
    "addr:street":"Land Van Waaslaan;Oost-Vlaanderen",
    "iso:country":"BE",
    "sg:address":"Land Van Waaslaan 19",
    "sg:city":"Gent",
    "sg:classifiers":[
        {
            "category":"Personal",
            "subcategory":"Beauty Salon",
            "type":"Services"
        }
    ],
    "sg:phone":"+32 9 238 14 16",
    "sg:postcode":"9000",
    "sg:province":"Oost-Vlaanderen",
    "sg:tags":[
        "lady",
        "-",
        "hairdressing"
    ],
    "wof:name":"Kreatief",
    "wof:placetype":"venue"
},
  "geometry": {"coordinates":[3.7430310249,51.0577163696],"type":"Point"}
}