{
  "type": "Feature",
  "properties": {
    "iso:country":"BE",
    "sg:address":"Grand Chemin 128",
    "sg:city":"Tournai (b\u00e9clers - Thimougies)",
    "sg:classifiers":[
        {
            "category":"Freight",
            "type":"Transportation"
        }
    ],
    "sg:phone":"+32 69 54 63 84",
    "sg:postcode":"7532",
    "sg:province":"Hainaut",
    "sg:tags":[
        "-",
        "transport"
    ],
    "wof:name":"Masure D",
    "wof:placetype":"venue"
},
  "geometry": {"coordinates":[3.5020010471,50.6193389893],"type":"Point"}
}