{
  "type": "Feature",
  "properties": {
    "addr:full":"Gistelsteenweg 169 Varsenare West-Vlaanderen 8490",
    "addr:housenumber":"169",
    "addr:postcode":"8490",
    "addr:street":"Gistelsteenweg",
    "iso:country":"BE",
    "sg:address":"Gistelsteenweg 169",
    "sg:city":"Varsenare",
    "sg:classifiers":[
        {
            "category":"Food & Beverages",
            "subcategory":"Bakery",
            "type":"Retail Goods"
        }
    ],
    "sg:phone":"+32 50 38 80 29",
    "sg:postcode":"8490",
    "sg:province":"West-Vlaanderen",
    "sg:tags":[
        "biscuit"
    ],
    "wof:name":"Blomme Confiserie Nv",
    "wof:placetype":"venue"
},
  "geometry": {"coordinates":[3.1403450966,51.1825180054],"type":"Point"}
}