{
  "type": "Feature",
  "properties": {
    "iso:country":"BE",
    "sg:address":"Rue De Brabant 62",
    "sg:city":"Sint-joost-ten-node/saint-josse-ten-noode",
    "sg:classifiers":[
        {
            "category":"Health Services",
            "subcategory":"Nursing And Care Facility",
            "type":"Services"
        }
    ],
    "sg:phone":"+32 2 209 13 13",
    "sg:postcode":"1210",
    "sg:province":"Bruxelles-Capitale",
    "sg:tags":[
        "public"
    ],
    "wof:name":"C.a.p.a.c.",
    "wof:placetype":"venue"
},
  "geometry": {"coordinates":[4.3616981506,50.8576583862],"type":"Point"}
}