{
  "type": "Feature",
  "properties": {
    "addr:full":"Avenue Chantecler 44 Braine-l\u00b4alleud Brabant Wallon 1420",
    "addr:housenumber":"44",
    "addr:postcode":"1420",
    "addr:street":"Avenue Chantecler;Brabant Wallon",
    "iso:country":"BE",
    "sg:address":"Avenue Chantecler 44",
    "sg:city":"Braine-l\u00b4alleud",
    "sg:classifiers":[
        {
            "category":"Insurance",
            "subcategory":"Insurance Agent",
            "type":"Services"
        }
    ],
    "sg:phone":"+32 2 384 25 87",
    "sg:postcode":"1420",
    "sg:province":"Brabant Wallon",
    "sg:tags":[
        "verzekeringsmakelaars",
        "expert"
    ],
    "wof:name":"Pierre Oostens",
    "wof:placetype":"venue"
},
  "geometry": {"coordinates":[4.3741278648,50.6893959045],"type":"Point"}
}