{
  "type": "Feature",
  "properties": {
    "iso:country":"BE",
    "sg:address":"Rue Joseph Wauters 100 B",
    "sg:city":"Anderlues",
    "sg:classifiers":[
        {
            "category":"Cinema",
            "subcategory":"Movie Rental",
            "type":"Entertainment"
        }
    ],
    "sg:phone":"+32 71 54 36 04",
    "sg:postcode":"6150",
    "sg:province":"Hainaut",
    "sg:tags":[
        "de",
        "cassette",
        "location",
        "vid\u00e9o",
        "audio"
    ],
    "wof:name":"Vdcd",
    "wof:placetype":"venue"
},
  "geometry": {"coordinates":[4.2677669525,50.4108428955],"type":"Point"}
}