{
  "type": "Feature",
  "properties": {
    "addr:full":"Bosstraat 197 Hasselt Limburg 3500",
    "addr:housenumber":"197",
    "addr:postcode":"3500",
    "addr:street":"Bosstraat",
    "iso:country":"BE",
    "sg:address":"Bosstraat 197",
    "sg:city":"Hasselt",
    "sg:classifiers":[
        {
            "category":"Professional",
            "subcategory":"Lawyer & Legal Services",
            "type":"Services"
        }
    ],
    "sg:phone":"+32 11 22 50 19",
    "sg:postcode":"3500",
    "sg:province":"Limburg",
    "wof:name":"Fissette Guido",
    "wof:placetype":"venue"
},
  "geometry": {"coordinates":[5.3671331406,50.9284667969],"type":"Point"}
}