{
  "type": "Feature",
  "properties": {
    "addr:full":"De Theuxstraat 156b8 Etterbeek Bruxelles-Capitale 1040",
    "addr:housenumber":"156b8",
    "addr:postcode":"1040",
    "addr:street":"De Theuxstraat",
    "iso:country":"BE",
    "sg:address":"De Theuxstraat 156b8",
    "sg:city":"Etterbeek",
    "sg:orig_category":"Persagentschappen",
    "sg:phone":"+32 2 648 79 35",
    "sg:postcode":"1040",
    "sg:province":"Bruxelles-Capitale",
    "wof:name":"Sophie Knott",
    "wof:placetype":"venue"
},
  "geometry": {"coordinates":[4.3807501793,50.8306083679],"type":"Point"}
}