{
  "type": "Feature",
  "properties": {
    "addr:full":"Place Charles-bergh 0 Neufchateau Luxembourg 6840",
    "addr:housenumber":"0",
    "addr:postcode":"6840",
    "addr:street":"Place Charles-Bergh",
    "iso:country":"BE",
    "sg:address":"Place Charles-bergh 0",
    "sg:city":"Neufchateau",
    "sg:orig_category":"Openbare bibliotheken and archieven",
    "sg:phone":"+32 61 22 43 20",
    "sg:postcode":"6840",
    "sg:province":"Luxembourg",
    "wof:name":"Discobus",
    "wof:placetype":"venue"
},
  "geometry": {"coordinates":[5.4351868629,49.8419113159],"type":"Point"}
}