{
  "type": "Feature",
  "properties": {
    "addr:full":"Vertstr 91 Puurs Antwerpen 2870",
    "addr:housenumber":"91",
    "addr:postcode":"2870",
    "addr:street":"Vertstr",
    "iso:country":"BE",
    "sg:address":"Vertstr 91",
    "sg:city":"Puurs",
    "sg:classifiers":[
        {
            "category":"Professional",
            "type":"Services"
        }
    ],
    "sg:phone":"+32 52 38 11 11",
    "sg:postcode":"2870",
    "sg:province":"Antwerpen",
    "sg:tags":[
        "transport",
        "road"
    ],
    "wof:name":"Fiege Nv",
    "wof:placetype":"venue"
},
  "geometry": {"coordinates":[4.3236198425,51.0342254639],"type":"Point"}
}