{
  "type": "Feature",
  "properties": {
    "addr:full":"Rue De Vise 825 Li\u00e8ge Li\u00e8ge 4020",
    "addr:housenumber":"825",
    "addr:postcode":"4020",
    "addr:street":"Rue De Vise",
    "iso:country":"BE",
    "sg:address":"Rue De Vise 825",
    "sg:city":"Li\u00e8ge",
    "sg:classifiers":[
        {
            "category":"Personal",
            "subcategory":"Skin Care",
            "type":"Services"
        }
    ],
    "sg:phone":"+32 4 362 14 91",
    "sg:postcode":"4020",
    "sg:province":"Li\u00e8ge",
    "sg:tags":[
        "cleaning",
        "maintenance"
    ],
    "wof:name":"E.n.m. S.p.r.l.",
    "wof:placetype":"venue"
},
  "geometry": {"coordinates":[5.6344199181,50.6485900879],"type":"Point"}
}