{
  "type": "Feature",
  "properties": {
    "addr:full":"Beneluxlaan 8800z Vilvoorde Vlaams-Brabant 1800",
    "addr:housenumber":"8800z",
    "addr:postcode":"1800",
    "addr:street":"Beneluxlaan",
    "iso:country":"BE",
    "sg:address":"Beneluxlaan 8800z",
    "sg:city":"Vilvoorde",
    "sg:orig_category":"Radioproductie and uitzendingen",
    "sg:phone":"+32 2 252 23 23",
    "sg:postcode":"1800",
    "sg:province":"Vlaams-Brabant",
    "wof:name":"Radio Moetoen",
    "wof:placetype":"venue"
},
  "geometry": {"coordinates":[4.4030170441,50.9146156311],"type":"Point"}
}