{
  "type": "Feature",
  "properties": {
    "iso:country":"BE",
    "sg:address":"Postiljonstraat 9",
    "sg:city":"Ukkel/uccle",
    "sg:orig_category":"Apotheken",
    "sg:phone":"+32 2 344 30 52",
    "sg:postcode":"1180",
    "sg:province":"Bruxelles-Capitale",
    "wof:name":"Multipharma",
    "wof:placetype":"venue"
},
  "geometry": {"coordinates":[4.3394341469,50.8027992249],"type":"Point"}
}