{
  "type": "Feature",
  "properties": {
    "addr:full":"Kerhoek 20 Zomergem Oost-Vlaanderen 9930",
    "addr:housenumber":"20",
    "addr:postcode":"9930",
    "addr:street":"Kerhoek",
    "iso:country":"BE",
    "sg:address":"Kerhoek 20",
    "sg:city":"Zomergem",
    "sg:orig_category":"Eclairage et \u00e9quipements du foyer",
    "sg:phone":"+32 9 372 68 48",
    "sg:postcode":"9930",
    "sg:province":"Oost-Vlaanderen",
    "wof:name":"Leo Rombouts",
    "wof:placetype":"venue"
},
  "geometry": {"coordinates":[3.5801670551,51.125957489],"type":"Point"}
}