{
  "type": "Feature",
  "properties": {
    "iso:country":"BE",
    "sg:address":"Weggevoerdenstraat 119",
    "sg:city":"Leuven (wilsele)",
    "sg:classifiers":[
        {
            "category":"Freight",
            "type":"Transportation"
        }
    ],
    "sg:phone":"+32 16 44 89 70",
    "sg:postcode":"3012",
    "sg:province":"Vlaams-Brabant",
    "sg:tags":[
        "-",
        "transport"
    ],
    "wof:name":"Schoolmeesters Bvba",
    "wof:placetype":"venue"
},
  "geometry": {"coordinates":[4.712428093,50.9252281189],"type":"Point"}
}