{
  "type": "Feature",
  "properties": {
    "addr:full":"Rue Gachard 77 Bruxelles Bruxelles-Capitale 1000",
    "addr:housenumber":"77",
    "addr:postcode":"1000",
    "addr:street":"Rue Gachard",
    "iso:country":"BE",
    "sg:address":"Rue Gachard 77",
    "sg:city":"Bruxelles",
    "sg:classifiers":[
        {
            "category":"Communications",
            "subcategory":"Film & Video Production",
            "type":"Services"
        }
    ],
    "sg:phone":"+32 2 646 06 06",
    "sg:postcode":"1000",
    "sg:province":"Bruxelles-Capitale",
    "sg:tags":[
        "multimedia",
        "-",
        "system"
    ],
    "wof:name":"Limelight Laboratory Sprl",
    "wof:placetype":"venue"
},
  "geometry": {"coordinates":[4.3672018051,50.8255805969],"type":"Point"}
}