{
  "type": "Feature",
  "properties": {
    "iso:country":"BE",
    "sg:address":"Rue Joseph Wauters 120",
    "sg:city":"Engis",
    "sg:orig_category":"Phosphates, Phosphoric Acid Salts",
    "sg:phone":"+32 4 273 96 81",
    "sg:postcode":"4480",
    "sg:province":"Li\u00e8ge",
    "wof:name":"Europhos S.a.",
    "wof:placetype":"venue"
},
  "geometry": {"coordinates":[5.3980498314,50.5789489746],"type":"Point"}
}