{
  "type": "Feature",
  "properties": {
    "addr:full":"Route De Grupont 17 Saint-hubert Luxembourg 6870",
    "addr:housenumber":"17",
    "addr:postcode":"6870",
    "addr:street":"Route De Grupont",
    "iso:country":"BE",
    "sg:address":"Route De Grupont 17",
    "sg:city":"Saint-hubert",
    "sg:orig_category":"Loodgieterij, verwarming and sanitaire installaties",
    "sg:phone":"+32 61 61 13 53",
    "sg:postcode":"6870",
    "sg:province":"Luxembourg",
    "wof:name":"Charles De Laet",
    "wof:placetype":"venue"
},
  "geometry": {"coordinates":[5.362390995,50.0269241333],"type":"Point"}
}