{
  "type": "Feature",
  "properties": {
    "addr:full":"Grote Markt 21 Vilvoorde Vlaams-Brabant 1800",
    "addr:housenumber":"21",
    "addr:postcode":"1800",
    "addr:street":"Grote Markt",
    "iso:country":"BE",
    "sg:address":"Grote Markt 21",
    "sg:city":"Vilvoorde",
    "sg:classifiers":[
        {
            "category":"Health Services",
            "subcategory":"Doctor",
            "type":"Services"
        }
    ],
    "sg:phone":"+32 2 253 31 33",
    "sg:postcode":"1800",
    "sg:province":"Vlaams-Brabant",
    "sg:tags":[
        "medicinephysicians",
        "surgeon"
    ],
    "wof:name":"Martens Geert",
    "wof:placetype":"venue"
},
  "geometry": {"coordinates":[4.4231548309,50.928314209],"type":"Point"}
}