{
  "type": "Feature",
  "properties": {
    "iso:country":"BE",
    "sg:address":"Kortenhoekstraat 136",
    "sg:city":"Aalst",
    "sg:orig_category":"Installation \u00e9lectrique r\u00e9sidentielle",
    "sg:phone":"+32 53 78 04 07",
    "sg:postcode":"9308",
    "sg:province":"Oost-Vlaanderen",
    "wof:name":"Luc Veldeman",
    "wof:placetype":"venue"
},
  "geometry": {"coordinates":[4.0347590446,50.9603500366],"type":"Point"}
}