{
  "type": "Feature",
  "properties": {
    "iso:country":"BE",
    "sg:address":"Mielandweg 4",
    "sg:city":"Rijkevorsel",
    "sg:orig_category":"Rundveehouders Varkenskwekers",
    "sg:phone":"+32 3 312 20 09",
    "sg:postcode":"2310",
    "sg:province":"Antwerpen",
    "wof:name":"Mauritius Driesen",
    "wof:placetype":"venue"
},
  "geometry": {"coordinates":[4.7455530167,51.3360214233],"type":"Point"}
}