{
  "type": "Feature",
  "properties": {
    "iso:country":"BE",
    "sg:address":"Rue Du Centre 57",
    "sg:city":"Verviers",
    "sg:classifiers":[
        {
            "category":"Professional",
            "subcategory":"Computer Services",
            "type":"Services"
        }
    ],
    "sg:phone":"+32 87 29 37 70",
    "sg:postcode":"4800",
    "sg:province":"Li\u00e8ge",
    "sg:tags":[
        "network"
    ],
    "wof:name":"Microsoft-windows Nt De Tesor Computers",
    "wof:placetype":"venue"
},
  "geometry": {"coordinates":[5.8631501198,50.5893135071],"type":"Point"}
}