{
  "type": "Feature",
  "properties": {
    "iso:country":"BE",
    "sg:address":"Repingestraat 55",
    "sg:city":"Galmaarden",
    "sg:classifiers":[
        {
            "category":"Insurance",
            "subcategory":"Insurance Agent",
            "type":"Services"
        }
    ],
    "sg:phone":"+32 54 56 84 48",
    "sg:postcode":"1570",
    "sg:province":"Vlaams-Brabant",
    "sg:tags":[
        "verzekeringsmakelaars",
        "expert"
    ],
    "wof:name":"Bureau Persoons",
    "wof:placetype":"venue"
},
  "geometry": {"coordinates":[4.0130200386,50.7617149353],"type":"Point"}
}