{
  "type": "Feature",
  "properties": {
    "addr:full":"Burgemeester Marresbaan 1 Riemst (vlijtingen) Limburg 3770",
    "addr:housenumber":"1",
    "addr:postcode":"3770",
    "addr:street":"Burgemeester Marresbaan",
    "iso:country":"BE",
    "sg:address":"Burgemeester Marresbaan 1",
    "sg:city":"Riemst (vlijtingen)",
    "sg:classifiers":[
        {
            "category":"Bakery",
            "type":"Food & Drink"
        }
    ],
    "sg:phone":"+32 12 45 27 05",
    "sg:postcode":"3770",
    "sg:province":"Limburg",
    "sg:tags":[
        "confectioner",
        "baker"
    ],
    "wof:name":"Franssen Bakkerij Bvba",
    "wof:placetype":"venue"
},
  "geometry": {"coordinates":[5.6256151199,50.8247718811],"type":"Point"}
}