{
  "type": "Feature",
  "properties": {
    "iso:country":"BE",
    "sg:address":"Rue Des Chars-\u00c0-boeufs 12",
    "sg:city":"Vielsalm",
    "sg:orig_category":"Enseignement secondaire g\u00e9n\u00e9ral. Enseignement secondaire technique and professionnel. Biblioth\u00e8ques ",
    "sg:phone":"+32 80 21 62 08",
    "sg:postcode":"6690",
    "sg:province":"Luxembourg",
    "wof:name":"Institut Du Sacr\u00c9-coeur",
    "wof:placetype":"venue"
},
  "geometry": {"coordinates":[5.9208807945,50.2801971436],"type":"Point"}
}