{
  "type": "Feature",
  "properties": {
    "addr:full":"Avenue Du Diamant 156 Bruxelles (schaerbeek) Bruxelles-Capitale 1030",
    "addr:housenumber":"156",
    "addr:postcode":"1030",
    "addr:street":"Avenue Du Diamant",
    "iso:country":"BE",
    "sg:address":"Avenue Du Diamant 156",
    "sg:city":"Bruxelles (schaerbeek)",
    "sg:orig_category":"Non-Classified Establishments",
    "sg:phone":"+32 2 732 18 46",
    "sg:postcode":"1030",
    "sg:province":"Bruxelles-Capitale",
    "wof:name":"Aaa Performance Rental",
    "wof:placetype":"venue"
},
  "geometry": {"coordinates":[4.3986558914,50.8502502441],"type":"Point"}
}