{
  "type": "Feature",
  "properties": {
    "iso:country":"BE",
    "sg:address":"Duinkerkestraat 113",
    "sg:city":"Poperinge",
    "sg:classifiers":[
        {
            "category":"Retail",
            "subcategory":"Auto Repair",
            "type":"Services"
        }
    ],
    "sg:phone":"+32 57 33 80 98",
    "sg:postcode":"8970",
    "sg:province":"West-Vlaanderen",
    "sg:tags":[
        "automobile-body"
    ],
    "wof:name":"Noppe D",
    "wof:placetype":"venue"
},
  "geometry": {"coordinates":[2.7152740955,50.8556785583],"type":"Point"}
}