{
  "type": "Feature",
  "properties": {
    "iso:country":"BE",
    "sg:address":"Landuitstraat 110",
    "sg:city":"Denderleeuw",
    "sg:orig_category":"Rev\u00eatements pour sols and murs. Peinture",
    "sg:phone":"+32 53 68 22 40",
    "sg:postcode":"9470",
    "sg:province":"Oost-Vlaanderen",
    "wof:name":"Patrick Van De Gucht",
    "wof:placetype":"venue"
},
  "geometry": {"coordinates":[4.0680618286,50.8767280579],"type":"Point"}
}