{
  "type": "Feature",
  "properties": {
    "addr:full":"Kiekenstraat 7 Diksmuide West-Vlaanderen 8600",
    "addr:housenumber":"7",
    "addr:postcode":"8600",
    "addr:street":"Kiekenstraat",
    "iso:country":"BE",
    "sg:address":"Kiekenstraat 7",
    "sg:city":"Diksmuide",
    "sg:classifiers":[
        {
            "category":"Bars & Pubs",
            "type":"Food & Drink"
        }
    ],
    "sg:phone":"+32 51 50 22 83",
    "sg:postcode":"8600",
    "sg:province":"West-Vlaanderen",
    "wof:name":"De Engel",
    "wof:placetype":"venue"
},
  "geometry": {"coordinates":[2.8639259338,51.0337371826],"type":"Point"}
}