{
  "type": "Feature",
  "properties": {
    "iso:country":"BE",
    "sg:address":"Van Tichelenlei 24",
    "sg:city":"Wommelgem",
    "sg:orig_category":"Plomberie, chauffage and installations sanitaires",
    "sg:phone":"+32 3 353 00 19",
    "sg:postcode":"2160",
    "sg:province":"Antwerpen",
    "wof:name":"Schoemans Valere",
    "wof:placetype":"venue"
},
  "geometry": {"coordinates":[4.4956598282,51.2092514038],"type":"Point"}
}