{
  "type": "Feature",
  "properties": {
    "addr:full":"Riddersstraat 149 Leuven Vlaams-Brabant 3000",
    "addr:housenumber":"149",
    "addr:postcode":"3000",
    "addr:street":"Riddersstraat",
    "iso:country":"BE",
    "sg:address":"Riddersstraat 149",
    "sg:city":"Leuven",
    "sg:orig_category":"M\u00e9decins and sp\u00e9cialistes",
    "sg:phone":"+32 16 22 61 24",
    "sg:postcode":"3000",
    "sg:province":"Vlaams-Brabant",
    "wof:name":"Geernaert",
    "wof:placetype":"venue"
},
  "geometry": {"coordinates":[4.6926751137,50.8854751587],"type":"Point"}
}