{
  "type": "Feature",
  "properties": {
    "addr:full":"Regentieplein 30 Sint-niklaas Oost-Vlaanderen 9100",
    "addr:housenumber":"30",
    "addr:postcode":"9100",
    "addr:street":"Regentieplein",
    "iso:country":"BE",
    "sg:address":"Regentieplein 30",
    "sg:city":"Sint-niklaas",
    "sg:orig_category":"Herstelling leer and schoeisel",
    "sg:phone":"+32 3 776 85 08",
    "sg:postcode":"9100",
    "sg:province":"Oost-Vlaanderen",
    "wof:name":"Roger De Witte",
    "wof:placetype":"venue"
},
  "geometry": {"coordinates":[4.1453227997,51.1685943604],"type":"Point"}
}