{
  "type": "Feature",
  "properties": {
    "iso:country":"BE",
    "sg:address":"Slijkstraat 92",
    "sg:city":"Wuustwezel",
    "sg:orig_category":"Installatie van houten of kunststof schrijnwerk",
    "sg:phone":"+32 3 669 91 11",
    "sg:postcode":"2990",
    "sg:province":"Antwerpen",
    "wof:name":"Bevers",
    "wof:placetype":"venue"
},
  "geometry": {"coordinates":[4.5945339203,51.4007148743],"type":"Point"}
}