{
  "type": "Feature",
  "properties": {
    "addr:full":"Blauwkasteelstraat 126 Oostende West-Vlaanderen 8400",
    "addr:housenumber":"126",
    "addr:postcode":"8400",
    "addr:street":"Blauwkasteelstraat",
    "iso:country":"BE",
    "sg:address":"Blauwkasteelstraat 126",
    "sg:city":"Oostende",
    "sg:classifiers":[
        {
            "category":"Restaurant",
            "type":"Food & Drink"
        }
    ],
    "sg:phone":"+32 59 80 33 51",
    "sg:postcode":"8400",
    "sg:province":"West-Vlaanderen",
    "wof:name":"Snackbar Smoefelgatje",
    "wof:placetype":"venue"
},
  "geometry": {"coordinates":[2.9132568836,51.2164878845],"type":"Point"}
}