{
  "type": "Feature",
  "properties": {
    "addr:full":"Steenweg Op Gierle Turnhout Antwerpen 2300",
    "addr:postcode":"2300",
    "addr:street":"Steenweg Op Gierle",
    "iso:country":"BE",
    "sg:address":"Steenweg Op Gierle",
    "sg:city":"Turnhout",
    "sg:classifiers":[
        {
            "category":"Home & Garden",
            "subcategory":"Hardware",
            "type":"Retail Goods"
        }
    ],
    "sg:phone":"+32 14 41 84 16",
    "sg:postcode":"2300",
    "sg:province":"Antwerpen",
    "sg:tags":[
        "soldering",
        "equipment",
        "welding",
        "-",
        "supply"
    ],
    "wof:name":"Baudoin Turnhout",
    "wof:placetype":"venue"
},
  "geometry": {"coordinates":[4.9283127785,51.3143157959],"type":"Point"}
}