{
  "type": "Feature",
  "properties": {
    "iso:country":"BE",
    "sg:address":"Opitterkiezel 22",
    "sg:city":"Bree",
    "sg:classifiers":[
        {
            "category":"Professional",
            "subcategory":"Management & Consulting",
            "type":"Services"
        }
    ],
    "sg:phone":"+32 474 27 67 70",
    "sg:postcode":"3960",
    "sg:province":"Limburg",
    "sg:tags":[
        "-",
        "processing",
        "data",
        "consultant"
    ],
    "wof:name":"Dadasco",
    "wof:placetype":"venue"
},
  "geometry": {"coordinates":[5.6089019775,51.1362800598],"type":"Point"}
}