{
  "type": "Feature",
  "properties": {
    "addr:full":"Chauss\u00e9e De Malines 1 Wezembeek-oppem Vlaams-Brabant 1970",
    "addr:housenumber":"1",
    "addr:postcode":"1970",
    "addr:street":"Chausse\u0301E De Malines",
    "iso:country":"BE",
    "sg:address":"Chauss\u00e9e De Malines 1",
    "sg:city":"Wezembeek-oppem",
    "sg:classifiers":[
        {
            "category":"Autos & Motor Vehicles",
            "subcategory":"Auto Supplies",
            "type":"Retail Goods"
        }
    ],
    "sg:phone":"+32 2 763 03 35",
    "sg:postcode":"1970",
    "sg:province":"Vlaams-Brabant",
    "sg:tags":[
        "automobile",
        "-",
        "radio"
    ],
    "wof:name":"Lazer Hifi Sprl",
    "wof:placetype":"venue"
},
  "geometry": {"coordinates":[4.5024299622,50.8471298218],"type":"Point"}
}