{
  "type": "Feature",
  "properties": {
    "iso:country":"BE",
    "sg:address":"Chauss\u00e9e De Haecht 1226",
    "sg:city":"Bruxelles (evere)",
    "sg:classifiers":[
        {
            "category":"Insurance",
            "subcategory":"Insurance Agent",
            "type":"Services"
        }
    ],
    "sg:phone":"+32 2 245 07 53",
    "sg:postcode":"1140",
    "sg:province":"Bruxelles-Capitale",
    "sg:tags":[
        "-",
        "representative"
    ],
    "wof:name":"Surmont",
    "wof:placetype":"venue"
},
  "geometry": {"coordinates":[4.4077210426,50.8767089844],"type":"Point"}
}