{
  "type": "Feature",
  "properties": {
    "iso:country":"BE",
    "sg:address":"Wezestraat 38",
    "sg:city":"Izegem",
    "sg:classifiers":[
        {
            "category":"Manufacturing",
            "subcategory":"Rubber & Plastics",
            "type":"Manufacturing & Wholesale Goods"
        }
    ],
    "sg:phone":"+32 3 820 69 00",
    "sg:postcode":"8870",
    "sg:province":"West-Vlaanderen",
    "sg:tags":[
        "material"
    ],
    "wof:name":"Akatherm Benelux Nv",
    "wof:placetype":"venue"
},
  "geometry": {"coordinates":[4.3879880905,51.1596755981],"type":"Point"}
}