{
  "type": "Feature",
  "properties": {
    "addr:full":"Rue De La Malaise 16 Eghez\u00e9e (waret-la-chauss\u00e9e) Namur 5310",
    "addr:housenumber":"16",
    "addr:postcode":"5310",
    "addr:street":"Rue De La Malaise;Waret-La-Chausse\u0301E",
    "iso:country":"BE",
    "sg:address":"Rue De La Malaise 16",
    "sg:city":"Eghez\u00e9e (waret-la-chauss\u00e9e)",
    "sg:classifiers":[
        {
            "category":"Retail",
            "subcategory":"Veterinary Services",
            "type":"Services"
        }
    ],
    "sg:phone":"+32 81 51 22 22",
    "sg:postcode":"5310",
    "sg:province":"Namur",
    "sg:tags":[
        "veterinarian"
    ],
    "wof:name":"Pilotte P",
    "wof:placetype":"venue"
},
  "geometry": {"coordinates":[4.9133701324,50.5351867676],"type":"Point"}
}