{
  "type": "Feature",
  "properties": {
    "iso:country":"BE",
    "sg:address":"Zijdeweverijstraat 27",
    "sg:city":"Vorst/forest",
    "sg:orig_category":"Woningbouw",
    "sg:phone":"+32 2 376 39 07",
    "sg:postcode":"1190",
    "sg:province":"Bruxelles-Capitale",
    "wof:name":"Fe. Gillet & Co",
    "wof:placetype":"venue"
},
  "geometry": {"coordinates":[4.3122320175,50.805896759],"type":"Point"}
}