{
  "type": "Feature",
  "properties": {
    "iso:country":"BE",
    "sg:address":"Driekooien 31",
    "sg:city":"Lommel",
    "sg:classifiers":[
        {
            "category":"Manufacturing",
            "subcategory":"Motor Vehicles & Parts",
            "type":"Manufacturing & Wholesale Goods"
        }
    ],
    "sg:phone":"+32 11 40 19 14",
    "sg:postcode":"3920",
    "sg:province":"Limburg",
    "sg:tags":[
        "electromechanical",
        "component"
    ],
    "wof:name":"Pld-electronics Bvba",
    "wof:placetype":"venue"
},
  "geometry": {"coordinates":[5.2792630196,51.1711883545],"type":"Point"}
}