{
  "type": "Feature",
  "properties": {
    "addr:full":"Rue Du Roi Albert 185 Oupeye Li\u00e8ge 4680",
    "addr:housenumber":"185",
    "addr:postcode":"4680",
    "addr:street":"Rue Du Roi Albert",
    "iso:country":"BE",
    "sg:address":"Rue Du Roi Albert 185",
    "sg:city":"Oupeye",
    "sg:classifiers":[
        {
            "category":"Travel",
            "subcategory":"Travel Agent",
            "type":"Entertainment"
        }
    ],
    "sg:phone":"+32 4 264 63 24",
    "sg:postcode":"4680",
    "sg:province":"Li\u00e8ge",
    "sg:tags":[
        "agency"
    ],
    "wof:name":"Les Voyages Albatros",
    "wof:placetype":"venue"
},
  "geometry": {"coordinates":[5.6461701393,50.7083587646],"type":"Point"}
}