{
  "type": "Feature",
  "properties": {
    "iso:country":"BE",
    "sg:address":"Piet Akkerstraat 2",
    "sg:city":"Ruiselede",
    "sg:orig_category":"Royal Canin. Animaux domestiques and accessoires",
    "sg:phone":"+32 51 68 84 88",
    "sg:postcode":"8755",
    "sg:province":"West-Vlaanderen",
    "wof:name":"Aveve Tanghe Jan",
    "wof:placetype":"venue"
},
  "geometry": {"coordinates":[3.4147410393,51.0511703491],"type":"Point"}
}