{
  "type": "Feature",
  "properties": {
    "addr:full":"Rue Du Ch\u00c2teau D\u00b4eau 11 Neupre Li\u00e8ge 4121",
    "addr:housenumber":"11",
    "addr:postcode":"4121",
    "addr:street":"Rue Du Cha\u0302Teau D\u00b4Eau",
    "iso:country":"BE",
    "sg:address":"Rue Du Ch\u00c2teau D\u00b4eau 11",
    "sg:city":"Neupre",
    "sg:orig_category":"Jardinage. Animaux domestiques and accessoires",
    "sg:phone":"+32 4 372 04 70",
    "sg:postcode":"4121",
    "sg:province":"Li\u00e8ge",
    "wof:name":"Aqua Garden Center",
    "wof:placetype":"venue"
},
  "geometry": {"coordinates":[5.464951992,50.5402832031],"type":"Point"}
}