{
  "type": "Feature",
  "properties": {
    "addr:full":"Oudergemselaan 57 Etterbeek/etterbeek Bruxelles-Capitale 1040",
    "addr:housenumber":"57",
    "addr:postcode":"1040",
    "addr:street":"Oudergemselaan",
    "iso:country":"BE",
    "sg:address":"Oudergemselaan 57",
    "sg:city":"Etterbeek/etterbeek",
    "sg:orig_category":"Artsen and specialisten",
    "sg:phone":"+32 2 230 84 34",
    "sg:postcode":"1040",
    "sg:province":"Bruxelles-Capitale",
    "wof:name":"Fabienne Guyot",
    "wof:placetype":"venue"
},
  "geometry": {"coordinates":[4.3853039742,50.8394050598],"type":"Point"}
}