{
  "type": "Feature",
  "properties": {
    "iso:country":"BE",
    "sg:address":"Rijksweg 195",
    "sg:city":"Maasmechelen",
    "sg:classifiers":[
        {
            "category":"Professional",
            "subcategory":"Lawyer & Legal Services",
            "type":"Services"
        }
    ],
    "sg:phone":"+32 89 77 64 10",
    "sg:postcode":"3630",
    "sg:province":"Limburg",
    "wof:name":"Jansen Marc",
    "wof:placetype":"venue"
},
  "geometry": {"coordinates":[5.7006402016,50.9777984619],"type":"Point"}
}