{
  "type": "Feature",
  "properties": {
    "addr:full":"Cit\u00c9 Soucou 11 Rouvroy Luxembourg 6767",
    "addr:housenumber":"11",
    "addr:postcode":"6767",
    "addr:street":"Cite\u0301 Soucou",
    "iso:country":"BE",
    "sg:address":"Cit\u00c9 Soucou 11",
    "sg:city":"Rouvroy",
    "sg:orig_category":"Charpentes and couvertures",
    "sg:phone":"+32 63 57 03 26",
    "sg:postcode":"6767",
    "sg:province":"Luxembourg",
    "wof:name":"Jean Berdudeau",
    "wof:placetype":"venue"
},
  "geometry": {"coordinates":[5.4905800819,49.5384864807],"type":"Point"}
}