{
  "type": "Feature",
  "properties": {
    "iso:country":"BE",
    "sg:address":"Rue Du Centre 75",
    "sg:city":"Vaux-sur-s\u00fbre (sibret)",
    "sg:classifiers":[
        {
            "category":"Building & Trades",
            "subcategory":"Construction",
            "type":"Services"
        }
    ],
    "sg:phone":"+32 61 26 63 86",
    "sg:postcode":"6640",
    "sg:province":"Luxembourg",
    "sg:tags":[
        "stucco",
        "contractor"
    ],
    "wof:name":"Paulus Ph",
    "wof:placetype":"venue"
},
  "geometry": {"coordinates":[5.5671000481,49.91065979],"type":"Point"}
}