{
  "type": "Feature",
  "properties": {
    "iso:country":"BE",
    "sg:address":"Wingenesteenweg 1d",
    "sg:city":"Wingene (zwevezele)",
    "sg:classifiers":[
        {
            "category":"Bars & Pubs",
            "type":"Food & Drink"
        }
    ],
    "sg:phone":"+32 51 61 32 62",
    "sg:postcode":"8750",
    "sg:province":"West-Vlaanderen",
    "wof:name":"Den Hille",
    "wof:placetype":"venue"
},
  "geometry": {"coordinates":[3.2266221046,51.047492981],"type":"Point"}
}