{
  "type": "Feature",
  "properties": {
    "iso:country":"BE",
    "sg:address":"Verbieststraat 12",
    "sg:city":"Pittem",
    "sg:orig_category":"Studios photographiques",
    "sg:phone":"+32 51 46 73 72",
    "sg:postcode":"8740",
    "sg:province":"West-Vlaanderen",
    "wof:name":"Patrick Vaernewyck",
    "wof:placetype":"venue"
},
  "geometry": {"coordinates":[3.268362999,50.9939689636],"type":"Point"}
}