{
  "type": "Feature",
  "properties": {
    "addr:full":"Avenue De Scandiano 2 Tubize Brabant Wallon 1480",
    "addr:housenumber":"2",
    "addr:postcode":"1480",
    "addr:street":"Avenue De Scandiano;Wallon",
    "iso:country":"BE",
    "sg:address":"Avenue De Scandiano 2",
    "sg:city":"Tubize",
    "sg:classifiers":[
        {
            "category":"Community Center",
            "type":"Public Place"
        }
    ],
    "sg:phone":"+32 2 355 07 57",
    "sg:postcode":"1480",
    "sg:province":"Brabant Wallon",
    "sg:tags":[
        "medical"
    ],
    "wof:name":"Centre M\u00e9dical De La Haute Senne",
    "wof:placetype":"venue"
},
  "geometry": {"coordinates":[4.204018116,50.6934051514],"type":"Point"}
}