{
  "type": "Feature",
  "properties": {
    "addr:full":"Lintsesteenweg 8 Duffel Antwerpen 2570",
    "addr:housenumber":"8",
    "addr:postcode":"2570",
    "addr:street":"Lintsesteenweg",
    "iso:country":"BE",
    "sg:address":"Lintsesteenweg 8",
    "sg:city":"Duffel",
    "sg:classifiers":[
        {
            "category":"Government",
            "subcategory":"Department Of Motor Vehicles",
            "type":"Public Place"
        }
    ],
    "sg:phone":"+32 15 31 18 82",
    "sg:postcode":"2570",
    "sg:province":"Antwerpen",
    "sg:tags":[
        "equipment",
        "industrial",
        "transport",
        "motor-cars"
    ],
    "wof:name":"Vervloet Bvba",
    "wof:placetype":"venue"
},
  "geometry": {"coordinates":[4.5065307617,51.0994186401],"type":"Point"}
}