{
  "type": "Feature",
  "properties": {
    "iso:country":"BE",
    "sg:address":"Jagersdreef 15",
    "sg:city":"Schilde ('s Gravenwezel)",
    "sg:classifiers":[
        {
            "category":"Building & Trades",
            "subcategory":"Plumbing",
            "type":"Services"
        }
    ],
    "sg:phone":"+32 3 290 94 50",
    "sg:postcode":"2970",
    "sg:province":"Antwerpen",
    "sg:tags":[
        "repair",
        "mainten",
        "-",
        "central",
        "heating"
    ],
    "wof:name":"Willems & Partners Bvba",
    "wof:placetype":"venue"
},
  "geometry": {"coordinates":[4.5551300049,51.2257919312],"type":"Point"}
}