{
  "type": "Feature",
  "properties": {
    "addr:full":"Avenue De La Gare 193 Hotton Luxembourg 6990",
    "addr:housenumber":"193",
    "addr:postcode":"6990",
    "addr:street":"Avenue De La Gare",
    "iso:country":"BE",
    "sg:address":"Avenue De La Gare 193",
    "sg:city":"Hotton",
    "sg:orig_category":"Treinen and spoorwegen",
    "sg:phone":"+32 84 24 56 27",
    "sg:postcode":"6990",
    "sg:province":"Luxembourg",
    "wof:name":"Gare De Hotton",
    "wof:placetype":"venue"
},
  "geometry": {"coordinates":[5.439209938,50.2756614685],"type":"Point"}
}