{
  "type": "Feature",
  "properties": {
    "addr:full":"Rue Du Spinoy 30 La Bruy\u00c8re Namur 5080",
    "addr:housenumber":"30",
    "addr:postcode":"5080",
    "addr:street":"Rue Du Spinoy",
    "iso:country":"BE",
    "sg:address":"Rue Du Spinoy 30",
    "sg:city":"La Bruy\u00c8re",
    "sg:orig_category":"Slagers",
    "sg:phone":"+32 81 56 78 97",
    "sg:postcode":"5080",
    "sg:province":"Namur",
    "wof:name":"Boucherie Ries-leclercq",
    "wof:placetype":"venue"
},
  "geometry": {"coordinates":[4.7991709709,50.5039024353],"type":"Point"}
}