{
  "type": "Feature",
  "properties": {
    "iso:country":"BE",
    "sg:address":"Markt 15",
    "sg:city":"Gistel",
    "sg:orig_category":"Dansscholen",
    "sg:phone":"+32 59 27 44 39",
    "sg:postcode":"8470",
    "sg:province":"West-Vlaanderen",
    "wof:name":"Gestellae Ballet",
    "wof:placetype":"venue"
},
  "geometry": {"coordinates":[2.9678709507,51.1561698914],"type":"Point"}
}