{
  "type": "Feature",
  "properties": {
    "iso:country":"BE",
    "sg:address":"Smetledesteenweg 57",
    "sg:city":"Wetteren",
    "sg:classifiers":[
        {
            "category":"Building & Trades",
            "subcategory":"Landscaping Services",
            "type":"Services"
        }
    ],
    "sg:phone":"+32 9 369 87 07",
    "sg:postcode":"9230",
    "sg:province":"Oost-Vlaanderen",
    "sg:tags":[
        "gardening",
        "garden",
        "maintenance"
    ],
    "wof:name":"Haeseryn B",
    "wof:placetype":"venue"
},
  "geometry": {"coordinates":[3.8973600864,50.9947013855],"type":"Point"}
}