{
  "type": "Feature",
  "properties": {
    "iso:country":"BE",
    "sg:address":"Elseroux 50",
    "sg:city":"Thimister-clermont",
    "sg:orig_category":"Kapsalons",
    "sg:phone":"+32 87 44 56 20",
    "sg:postcode":"4890",
    "sg:province":"Li\u00e8ge",
    "wof:name":"Coiffure Fabienne",
    "wof:placetype":"venue"
},
  "geometry": {"coordinates":[5.8840408325,50.6593093872],"type":"Point"}
}