{
  "type": "Feature",
  "properties": {
    "iso:country":"BE",
    "sg:address":"Vlaschaard 46",
    "sg:city":"Zele",
    "sg:classifiers":[
        {
            "category":"Recreation",
            "subcategory":"Amusement Park",
            "type":"Entertainment"
        }
    ],
    "sg:phone":"+32 52 44 76 00",
    "sg:postcode":"9240",
    "sg:province":"Oost-Vlaanderen",
    "sg:tags":[
        "attraction",
        "-",
        "sale",
        "fair",
        "hiring"
    ],
    "wof:name":"Seat Line",
    "wof:placetype":"venue"
},
  "geometry": {"coordinates":[4.0111961365,51.0599937439],"type":"Point"}
}