{
  "type": "Feature",
  "properties": {
    "addr:full":"Rue Du Moulin 37 Hannut Li\u00e8ge 4280",
    "addr:housenumber":"37",
    "addr:postcode":"4280",
    "addr:street":"Rue Du Moulin",
    "iso:country":"BE",
    "sg:address":"Rue Du Moulin 37",
    "sg:city":"Hannut",
    "sg:classifiers":[
        {
            "category":"Health Services",
            "subcategory":"Health Practitioner",
            "type":"Services"
        }
    ],
    "sg:phone":"+32 19 51 42 53",
    "sg:postcode":"4280",
    "sg:province":"Li\u00e8ge",
    "sg:tags":[
        "physiotherapist"
    ],
    "wof:name":"Streel Baudouin",
    "wof:placetype":"venue"
},
  "geometry": {"coordinates":[5.0643692017,50.6769676208],"type":"Point"}
}