{
  "type": "Feature",
  "properties": {
    "iso:country":"BE",
    "sg:address":"Boulevard Du Nord 30",
    "sg:city":"Namur",
    "sg:classifiers":[
        {
            "category":"Cafe",
            "type":"Food & Drink"
        }
    ],
    "sg:phone":"+32 81 22 77 49",
    "sg:postcode":"5000",
    "sg:province":"Namur",
    "sg:tags":[
        "caf\u00e9s"
    ],
    "wof:name":"Annie Vandepoortaele",
    "wof:placetype":"venue"
},
  "geometry": {"coordinates":[4.8645558357,50.4702644348],"type":"Point"}
}