{
  "type": "Feature",
  "properties": {
    "iso:country":"BE",
    "sg:address":"Parkplein 2",
    "sg:city":"Zelzate",
    "sg:classifiers":[
        {
            "category":"Real Estate",
            "subcategory":"Real Estate Services",
            "type":"Services"
        }
    ],
    "sg:phone":"+32 476 89 85 95",
    "sg:postcode":"9060",
    "sg:province":"Oost-Vlaanderen",
    "wof:name":"De Veirman E",
    "wof:placetype":"venue"
},
  "geometry": {"coordinates":[3.8141870499,51.1934051514],"type":"Point"}
}