{
  "type": "Feature",
  "properties": {
    "addr:full":"Leopoldstraat 91 Mechelen Antwerpen 2800",
    "addr:housenumber":"91",
    "addr:postcode":"2800",
    "addr:street":"Leopoldstraat",
    "iso:country":"BE",
    "sg:address":"Leopoldstraat 91",
    "sg:city":"Mechelen",
    "sg:orig_category":"Advocaten and juridische adviseurs",
    "sg:phone":"+32 15 43 05 18",
    "sg:postcode":"2800",
    "sg:province":"Antwerpen",
    "wof:name":"A.m. Schuermans",
    "wof:placetype":"venue"
},
  "geometry": {"coordinates":[4.4809761047,51.0186576843],"type":"Point"}
}