{
  "type": "Feature",
  "properties": {
    "iso:country":"BE",
    "sg:address":"Balmoral 12",
    "sg:city":"Jalhay (sart)",
    "sg:classifiers":[
        {
            "category":"Building & Trades",
            "subcategory":"Plumbing",
            "type":"Services"
        }
    ],
    "sg:phone":"+32 87 47 45 17",
    "sg:postcode":"4845",
    "sg:province":"Li\u00e8ge",
    "sg:tags":[
        "pipe",
        "drain",
        "unblocking"
    ],
    "wof:name":"Gilson J",
    "wof:placetype":"venue"
},
  "geometry": {"coordinates":[5.9099001884,50.5158615112],"type":"Point"}
}