{
  "type": "Feature",
  "properties": {
    "iso:country":"BE",
    "sg:address":"Rue Jumer\u00c9e 10",
    "sg:city":"Villers-la-ville",
    "sg:orig_category":"R\u00e9cup\u00e9ration de mati\u00e8res m\u00e9talliques recyclables and d\u00e9molisseurs de voitures. Entretien et r\u00e9parati",
    "sg:phone":"+32 71 85 35 76",
    "sg:postcode":"1495",
    "sg:province":"Brabant Wallon",
    "wof:name":"Jacques Raeymaekers",
    "wof:placetype":"venue"
},
  "geometry": {"coordinates":[4.4878740311,50.5419044495],"type":"Point"}
}