{
  "type": "Feature",
  "properties": {
    "addr:full":"Rue Du Bien Etre 3 Bruxelles (anderlecht) Bruxelles-Capitale 1070",
    "addr:housenumber":"3",
    "addr:postcode":"1070",
    "addr:street":"Rue Du Bien Etre",
    "iso:country":"BE",
    "sg:address":"Rue Du Bien Etre 3",
    "sg:city":"Bruxelles (anderlecht)",
    "sg:classifiers":[
        {
            "category":"Professional",
            "subcategory":"Accounting & Tax Preparation",
            "type":"Services"
        }
    ],
    "sg:phone":"+32 2 522 93 94",
    "sg:postcode":"1070",
    "sg:province":"Bruxelles-Capitale",
    "sg:tags":[
        "bookkeeper"
    ],
    "wof:name":"Ascofisc Sprl",
    "wof:placetype":"venue"
},
  "geometry": {"coordinates":[4.3109130859,50.8481254578],"type":"Point"}
}