{
  "type": "Feature",
  "properties": {
    "iso:country":"BE",
    "sg:address":"Diesterstraat 69",
    "sg:city":"Sint-truiden",
    "sg:classifiers":[
        {
            "category":"Shopping",
            "subcategory":"Crafts & Fabrics",
            "type":"Retail Goods"
        }
    ],
    "sg:phone":"+32 11 68 43 12",
    "sg:postcode":"3800",
    "sg:province":"Limburg",
    "sg:tags":[
        "plant",
        "flower",
        "artificial"
    ],
    "wof:name":"E.d.l.",
    "wof:placetype":"venue"
},
  "geometry": {"coordinates":[5.1823000908,50.8187675476],"type":"Point"}
}