{
  "type": "Feature",
  "properties": {
    "iso:country":"BE",
    "sg:address":"Chauss\u00c9e De Saint-job 353b3",
    "sg:city":"Ukkel/uccle",
    "sg:orig_category":"Experts-comptables",
    "sg:phone":"+32 2 375 32 89",
    "sg:postcode":"1180",
    "sg:province":"Bruxelles-Capitale",
    "wof:name":"Carl Godart",
    "wof:placetype":"venue"
},
  "geometry": {"coordinates":[4.3473391533,50.7926254272],"type":"Point"}
}