{
  "type": "Feature",
  "properties": {
    "addr:full":"Hongersveldstraat 3 Dilbeek Vlaams-Brabant 1700",
    "addr:housenumber":"3",
    "addr:postcode":"1700",
    "addr:street":"Hongersveldstraat",
    "iso:country":"BE",
    "sg:address":"Hongersveldstraat 3",
    "sg:city":"Dilbeek",
    "sg:orig_category":"Eclairage et \u00e9quipements du foyer. Souvenirs and objets artisanaux",
    "sg:phone":"+32 2 463 25 01",
    "sg:postcode":"1700",
    "sg:province":"Vlaams-Brabant",
    "wof:name":"'t Kaartenhuisje",
    "wof:placetype":"venue"
},
  "geometry": {"coordinates":[4.2463231087,50.8568840027],"type":"Point"}
}