{
  "type": "Feature",
  "properties": {
    "iso:country":"BE",
    "sg:address":"Jantenstraat 7a",
    "sg:city":"Lummen",
    "sg:classifiers":[
        {
            "category":"Retail",
            "subcategory":"Animal Services",
            "type":"Services"
        }
    ],
    "sg:phone":"+32 11 43 28 64",
    "sg:postcode":"3560",
    "sg:province":"Limburg",
    "sg:tags":[
        "breeding",
        "selling",
        "-",
        "dog"
    ],
    "wof:name":"Rashonden Kennel Van Het Lumboshof",
    "wof:placetype":"venue"
},
  "geometry": {"coordinates":[5.2279372215,51.0065078735],"type":"Point"}
}