{
  "type": "Feature",
  "properties": {
    "iso:country":"BE",
    "sg:address":"Grote Heirenthoek 33",
    "sg:city":"Nevele",
    "sg:classifiers":[
        {
            "category":"Building & Trades",
            "subcategory":"Landscaping Services",
            "type":"Services"
        }
    ],
    "sg:phone":"+32 9 371 60 00",
    "sg:postcode":"9850",
    "sg:province":"Oost-Vlaanderen",
    "sg:tags":[
        "etude",
        "technique",
        "ing\u00e9nierie"
    ],
    "wof:name":"Van Tornhout",
    "wof:placetype":"venue"
},
  "geometry": {"coordinates":[3.5644209385,51.0617523193],"type":"Point"}
}