{
  "type": "Feature",
  "properties": {
    "iso:country":"BE",
    "sg:address":"Dendermondsesteenweg 144",
    "sg:city":"Lebbeke",
    "sg:orig_category":"Loodgieterij, verwarming and sanitaire installaties",
    "sg:phone":"+32 52 41 41 67",
    "sg:postcode":"9280",
    "sg:province":"Oost-Vlaanderen",
    "wof:name":"Fa. Kris",
    "wof:placetype":"venue"
},
  "geometry": {"coordinates":[4.1223301888,51.0058441162],"type":"Point"}
}