{
  "type": "Feature",
  "properties": {
    "iso:country":"BE",
    "sg:address":"Rue Praile 129",
    "sg:city":"Ham-sur-heure-nalinnes (nalinnes)",
    "sg:classifiers":[
        {
            "category":"Building & Trades",
            "subcategory":"Electrical",
            "type":"Services"
        }
    ],
    "sg:phone":"+32 71 21 79 65",
    "sg:postcode":"6120",
    "sg:province":"Hainaut",
    "sg:tags":[
        "electric",
        "-",
        "housewiring",
        "contractor"
    ],
    "wof:name":"Lannoy Philippe Electricite Sprl",
    "wof:placetype":"venue"
},
  "geometry": {"coordinates":[4.4608597755,50.3184814453],"type":"Point"}
}