{
  "type": "Feature",
  "properties": {
    "addr:full":"Luikersteenweg 185 Hasselt Limburg 3500",
    "addr:housenumber":"185",
    "addr:postcode":"3500",
    "addr:street":"Luikersteenweg",
    "iso:country":"BE",
    "sg:address":"Luikersteenweg 185",
    "sg:city":"Hasselt",
    "sg:classifiers":[
        {
            "category":"Manufacturing",
            "subcategory":"Electronics",
            "type":"Manufacturing & Wholesale Goods"
        }
    ],
    "sg:phone":"+32 11 27 28 00",
    "sg:postcode":"3500",
    "sg:province":"Limburg",
    "sg:tags":[
        "component",
        "-"
    ],
    "wof:name":"Lab Electronics Nv",
    "wof:placetype":"venue"
},
  "geometry": {"coordinates":[5.345495224,50.9179153442],"type":"Point"}
}