{
  "type": "Feature",
  "properties": {
    "addr:full":"Liersesteenweg 257 Sint-katelijne-waver Antwerpen 2860",
    "addr:housenumber":"257",
    "addr:postcode":"2860",
    "addr:street":"Liersesteenweg",
    "iso:country":"BE",
    "sg:address":"Liersesteenweg 257",
    "sg:city":"Sint-katelijne-waver",
    "sg:classifiers":[
        {
            "category":"Banks & Credit Unions",
            "subcategory":"Bureau De Change",
            "type":"Services"
        }
    ],
    "sg:phone":"+32 15 31 16 39",
    "sg:postcode":"2860",
    "sg:province":"Antwerpen",
    "sg:tags":[
        "-",
        "household",
        "gas"
    ],
    "wof:name":"Gazolux Bvba",
    "wof:placetype":"venue"
},
  "geometry": {"coordinates":[4.4861178398,51.0690765381],"type":"Point"}
}