{
  "type": "Feature",
  "properties": {
    "addr:full":"Veldhinweg 16 Zonhoven Limburg 3520",
    "addr:housenumber":"16",
    "addr:postcode":"3520",
    "addr:street":"Veldhinweg",
    "iso:country":"BE",
    "sg:address":"Veldhinweg 16",
    "sg:city":"Zonhoven",
    "sg:classifiers":[
        {
            "category":"Insurance",
            "subcategory":"Insurance Agent",
            "type":"Services"
        }
    ],
    "sg:phone":"+32 11 81 78 83",
    "sg:postcode":"3520",
    "sg:province":"Limburg",
    "sg:tags":[
        "-",
        "representative"
    ],
    "wof:name":"Abc - Consult Bvba",
    "wof:placetype":"venue"
},
  "geometry": {"coordinates":[5.3586630821,50.9914855957],"type":"Point"}
}