{
  "type": "Feature",
  "properties": {
    "iso:country":"BE",
    "sg:address":"Rue Des Ecoles 50",
    "sg:city":"Daverdisse",
    "sg:orig_category":"Enseignement maternel and primaire",
    "sg:phone":"+32 61 51 25 10",
    "sg:postcode":"6929",
    "sg:province":"Luxembourg",
    "wof:name":"Ecole Fond. Communale",
    "wof:placetype":"venue"
},
  "geometry": {"coordinates":[5.0619001389,49.9974746704],"type":"Point"}
}