{
  "type": "Feature",
  "properties": {
    "iso:country":"BE",
    "sg:address":"Kerkstraat 10",
    "sg:city":"Steenokkerzeel (melsbroek)",
    "sg:classifiers":[
        {
            "category":"Food & Beverages",
            "subcategory":"Groceries & Convenience Stores",
            "type":"Retail Goods"
        }
    ],
    "sg:phone":"+32 2 751 83 73",
    "sg:postcode":"1820",
    "sg:province":"Vlaams-Brabant",
    "sg:tags":[
        "grocer"
    ],
    "wof:name":"Winkeltje ('t)",
    "wof:placetype":"venue"
},
  "geometry": {"coordinates":[4.477314949,50.9155654907],"type":"Point"}
}