{
  "type": "Feature",
  "properties": {
    "iso:country":"BE",
    "sg:address":"Grotestraat 122",
    "sg:city":"Genk",
    "sg:classifiers":[
        {
            "category":"Professional",
            "subcategory":"Lawyer & Legal Services",
            "type":"Services"
        }
    ],
    "sg:phone":"+32 89 32 23 00",
    "sg:postcode":"3600",
    "sg:province":"Limburg",
    "wof:name":"Advocatenassociatie Adlex",
    "wof:placetype":"venue"
},
  "geometry": {"coordinates":[5.4910430908,50.9633560181],"type":"Point"}
}