{
  "type": "Feature",
  "properties": {
    "addr:full":"Damstraat 33 Buggenhout Oost-Vlaanderen 9255",
    "addr:housenumber":"33",
    "addr:postcode":"9255",
    "addr:street":"Damstraat",
    "iso:country":"BE",
    "sg:address":"Damstraat 33",
    "sg:city":"Buggenhout",
    "sg:classifiers":[
        {
            "category":"Insurance",
            "subcategory":"Life Insurance",
            "type":"Services"
        }
    ],
    "sg:phone":"+32 52 33 40 32",
    "sg:postcode":"9255",
    "sg:province":"Oost-Vlaanderen",
    "sg:tags":[
        "assurance"
    ],
    "wof:name":"Geert Van Der Wildt",
    "wof:placetype":"venue"
},
  "geometry": {"coordinates":[4.2142848969,51.0312347412],"type":"Point"}
}