{
  "type": "Feature",
  "properties": {
    "addr:full":"Koning Booudewijnlaan 2 Kortessem (groot) Limburg 3724",
    "addr:housenumber":"2",
    "addr:postcode":"3724",
    "addr:street":"Koning Booudewijnlaan;Groot Limburg",
    "iso:country":"BE",
    "sg:address":"Koning Booudewijnlaan 2",
    "sg:city":"Kortessem (groot)",
    "sg:orig_category":"Industri\u00eble elektrische installaties",
    "sg:phone":"+32 12 39 10 99",
    "sg:postcode":"3724",
    "sg:province":"Limburg",
    "wof:name":"A.c.t. Alarm",
    "wof:placetype":"venue"
},
  "geometry": {"coordinates":[5.428445816,50.8420639038],"type":"Point"}
}