{
  "type": "Feature",
  "properties": {
    "iso:country":"BE",
    "sg:address":"Collegestraat 122",
    "sg:city":"Elsene/ixelles",
    "sg:orig_category":"Installatie van metalen schrijnwerk SMEEDWERK, METAALBEWERKING AND POEDERMETALLURGIE",
    "sg:phone":"+32 2 647 38 12",
    "sg:postcode":"1050",
    "sg:province":"Bruxelles-Capitale",
    "wof:name":"Huart Fres",
    "wof:placetype":"venue"
},
  "geometry": {"coordinates":[4.3710541725,50.8314247131],"type":"Point"}
}