{
  "type": "Feature",
  "properties": {
    "iso:country":"BE",
    "sg:address":"Rue Du Bemel 122",
    "sg:city":"Sint-pieters-woluwe/woluwe-saint-pierre",
    "sg:orig_category":"Enseignement maternel and primaire",
    "sg:phone":"+32 2 779 04 11",
    "sg:postcode":"1150",
    "sg:province":"Bruxelles-Capitale",
    "wof:name":"Ecole Maternelle",
    "wof:placetype":"venue"
},
  "geometry": {"coordinates":[4.418035984,50.8311347961],"type":"Point"}
}