{
  "type": "Feature",
  "properties": {
    "iso:country":"BE",
    "sg:address":"Kruiskensheide 28",
    "sg:city":"Halle",
    "sg:orig_category":"Diensten voor huisdieren",
    "sg:phone":"+32 2 361 21 41",
    "sg:postcode":"1502",
    "sg:province":"Vlaams-Brabant",
    "wof:name":"Chez Buddy",
    "wof:placetype":"venue"
},
  "geometry": {"coordinates":[4.1996808052,50.7188186646],"type":"Point"}
}