{
  "type": "Feature",
  "properties": {
    "addr:full":"R\u00e9sidence Val De Mehaigne 1 Box 4 Wanze Li\u00e8ge 4520",
    "addr:housenumber":"1;4",
    "addr:postcode":"4520",
    "addr:street":"Box",
    "iso:country":"BE",
    "sg:address":"R\u00e9sidence Val De Mehaigne 1 Box 4",
    "sg:city":"Wanze",
    "sg:classifiers":[
        {
            "category":"Personal",
            "subcategory":"Beauty Salon",
            "type":"Services"
        }
    ],
    "sg:phone":"+32 85 23 42 32",
    "sg:postcode":"4520",
    "sg:province":"Li\u00e8ge",
    "wof:name":"Brin De Beaut\u00e9",
    "wof:placetype":"venue"
},
  "geometry": {"coordinates":[5.2187380791,50.5323410034],"type":"Point"}
}