{
  "type": "Feature",
  "properties": {
    "addr:full":"Sint-lambrechts Herkstraat 86 Hasselt (sint-lambrechts-herk) Limburg 3500",
    "addr:housenumber":"86",
    "addr:postcode":"3500",
    "addr:street":"Herkstraat",
    "iso:country":"BE",
    "sg:address":"Sint-lambrechts Herkstraat 86",
    "sg:city":"Hasselt (sint-lambrechts-herk)",
    "sg:classifiers":[
        {
            "category":"Bars & Pubs",
            "type":"Food & Drink"
        }
    ],
    "sg:phone":"+32 11 59 29 53",
    "sg:postcode":"3500",
    "sg:province":"Limburg",
    "sg:tags":[
        "tavern"
    ],
    "wof:name":"In Den Horst",
    "wof:placetype":"venue"
},
  "geometry": {"coordinates":[5.3054890633,50.9067077637],"type":"Point"}
}