{
  "type": "Feature",
  "properties": {
    "addr:full":"Voie Marschal Grouchy 18 Wavre Brabant Wallon 1300",
    "addr:housenumber":"18;1300",
    "addr:street":"Voie Marschal Grouchy",
    "iso:country":"BE",
    "sg:address":"Voie Marschal Grouchy 18",
    "sg:city":"Wavre",
    "sg:classifiers":[
        {
            "category":"Taxi",
            "type":"Transportation"
        }
    ],
    "sg:phone":"+32 10 45 22 22",
    "sg:postcode":"1300",
    "sg:province":"Brabant Wallon",
    "sg:tags":[
        "taxi's"
    ],
    "wof:name":"Artgens Taxis",
    "wof:placetype":"venue"
},
  "geometry": {"coordinates":[4.6210398674,50.6850814819],"type":"Point"}
}