{
  "type": "Feature",
  "properties": {
    "iso:country":"BE",
    "sg:address":"Rue De Plomcot 10",
    "sg:city":"Namur",
    "sg:orig_category":"Rev\u00eatements de sols and murs. Installation de menuiserie en bois and plastique. Installation de menu",
    "sg:phone":"+32 81 25 03 20",
    "sg:postcode":"5000",
    "sg:province":"Namur",
    "wof:name":"Carlier Bois",
    "wof:placetype":"venue"
},
  "geometry": {"coordinates":[4.8889231682,50.4678153992],"type":"Point"}
}