{
  "type": "Feature",
  "properties": {
    "addr:full":"All\u00e9e Des Muguets 12 Vis\u00e9 Li\u00e8ge 4600",
    "addr:housenumber":"12",
    "addr:postcode":"4600",
    "addr:street":"Alle\u0301E Des Muguets",
    "iso:country":"BE",
    "sg:address":"All\u00e9e Des Muguets 12",
    "sg:city":"Vis\u00e9",
    "sg:classifiers":[
        {
            "category":"Personal",
            "subcategory":"Nail Salon",
            "type":"Services"
        }
    ],
    "sg:phone":"+32 475 98 61 50",
    "sg:postcode":"4600",
    "sg:province":"Li\u00e8ge",
    "sg:tags":[
        "pedicure"
    ],
    "wof:name":"Cocco Suzy",
    "wof:placetype":"venue"
},
  "geometry": {"coordinates":[5.7014079094,50.7353134155],"type":"Point"}
}