{
  "type": "Feature",
  "properties": {
    "addr:full":"Brugstraat 18 Wetteren Oost-Vlaanderen 9230",
    "addr:housenumber":"18",
    "addr:postcode":"9230",
    "addr:street":"Brugstraat",
    "iso:country":"BE",
    "sg:address":"Brugstraat 18",
    "sg:city":"Wetteren",
    "sg:orig_category":"Animations diverses",
    "sg:phone":"+32 9 369 58 75",
    "sg:postcode":"9230",
    "sg:province":"Oost-Vlaanderen",
    "wof:name":"Amore's Discoteek",
    "wof:placetype":"venue"
},
  "geometry": {"coordinates":[3.8818619251,51.0080337524],"type":"Point"}
}