{
  "type": "Feature",
  "properties": {
    "iso:country":"BE",
    "sg:address":"Rue Du Bonnet 123",
    "sg:city":"Saint-nicolas",
    "sg:orig_category":"Loodgieterij, verwarming and sanitaire installaties",
    "sg:phone":"+32 4 226 84 44",
    "sg:postcode":"4420",
    "sg:province":"Li\u00e8ge",
    "wof:name":"Armand Spriet",
    "wof:placetype":"venue"
},
  "geometry": {"coordinates":[5.5282168388,50.6338539124],"type":"Point"}
}