{
  "type": "Feature",
  "properties": {
    "iso:country":"BE",
    "sg:address":"Brouwerijstraat 7",
    "sg:city":"Zwalm",
    "sg:orig_category":"Salles de conf\u00e9rences and de r\u00e9ceptions",
    "sg:phone":"+32 55 49 69 59",
    "sg:postcode":"9630",
    "sg:province":"Oost-Vlaanderen",
    "wof:name":"Poezenele",
    "wof:placetype":"venue"
},
  "geometry": {"coordinates":[3.7387599945,50.9047584534],"type":"Point"}
}