{
  "type": "Feature",
  "properties": {
    "iso:country":"BE",
    "sg:address":"Dr\u00e8ve Des Gendarmes 41",
    "sg:city":"Bruxelles (uccle)",
    "sg:orig_category":"Non-Classified Establishments",
    "sg:phone":"+32 2 374 35 82",
    "sg:postcode":"1180",
    "sg:province":"Bruxelles-Capitale",
    "wof:name":"J V H Eclairage Sprl",
    "wof:placetype":"venue"
},
  "geometry": {"coordinates":[4.3795380592,50.7957572937],"type":"Point"}
}