{
  "type": "Feature",
  "properties": {
    "iso:country":"BE",
    "sg:address":"Boomkwekerijstraat 4",
    "sg:city":"Moeskroen/mouscron",
    "sg:orig_category":"Plaatsen van vloer- and muurbekleding Schilders",
    "sg:phone":"+32 56 33 25 41",
    "sg:postcode":"7700",
    "sg:province":"Hainaut",
    "wof:name":"E. Ferlin",
    "wof:placetype":"venue"
},
  "geometry": {"coordinates":[3.2323200703,50.7400932312],"type":"Point"}
}