{
  "type": "Feature",
  "properties": {
    "addr:full":"Route Du Congr\u00c8s De Polleur 47 Theux Li\u00e8ge 4910",
    "addr:housenumber":"47",
    "addr:postcode":"4910",
    "addr:street":"Route Du Congre\u0300S De Polleur",
    "iso:country":"BE",
    "sg:address":"Route Du Congr\u00c8s De Polleur 47",
    "sg:city":"Theux",
    "sg:orig_category":"Installation \u00e9lectrique r\u00e9sidentielle. Ordinateurs and \u00e9quipement informatique",
    "sg:phone":"+32 87 54 19 82",
    "sg:postcode":"4910",
    "sg:province":"Li\u00e8ge",
    "wof:name":"Leonard Michael",
    "wof:placetype":"venue"
},
  "geometry": {"coordinates":[5.8312768936,50.5258674622],"type":"Point"}
}