{
  "type": "Feature",
  "properties": {
    "addr:full":"Rue De La Taille Des M\u00e8res 6 Mons (havr\u00e9) Hainaut 7021",
    "addr:housenumber":"6",
    "addr:postcode":"7021",
    "addr:street":"Rue De La Taille Des Me\u0300Res",
    "iso:country":"BE",
    "sg:address":"Rue De La Taille Des M\u00e8res 6",
    "sg:city":"Mons (havr\u00e9)",
    "sg:classifiers":[
        {
            "category":"Real Estate",
            "subcategory":"Architect",
            "type":"Services"
        }
    ],
    "sg:phone":"+32 65 87 41 57",
    "sg:postcode":"7021",
    "sg:province":"Hainaut",
    "wof:name":"Di Nunzio P",
    "wof:placetype":"venue"
},
  "geometry": {"coordinates":[4.0456829071,50.4640655518],"type":"Point"}
}