{
  "type": "Feature",
  "properties": {
    "iso:country":"BE",
    "sg:address":"Chauss\u00c9e Freddy Terwagne 128",
    "sg:city":"Amay",
    "sg:orig_category":"Eleveurs d'animaux domestiques. Services pour animaux domestiques",
    "sg:phone":"+32 85 31 24 21",
    "sg:postcode":"4540",
    "sg:province":"Li\u00e8ge",
    "wof:name":"Chenil La Chataigneraie",
    "wof:placetype":"venue"
},
  "geometry": {"coordinates":[5.3292059898,50.553527832],"type":"Point"}
}