{
  "type": "Feature",
  "properties": {
    "addr:full":"Zoning Industriel 4\u00e8me Rue 33 Charleroi (jumet) Hainaut 6040",
    "addr:housenumber":"4e\u0300me;33",
    "addr:postcode":"6040",
    "addr:street":"Zoning Industriel;Rue",
    "iso:country":"BE",
    "sg:address":"Zoning Industriel 4\u00e8me Rue 33",
    "sg:city":"Charleroi (jumet)",
    "sg:classifiers":[
        {
            "category":"Banks & Credit Unions",
            "subcategory":"Investment Brokerage",
            "type":"Services"
        }
    ],
    "sg:phone":"+32 71 37 69 19",
    "sg:postcode":"6040",
    "sg:province":"Hainaut",
    "sg:tags":[
        "remediation",
        "soil",
        "protection"
    ],
    "wof:name":"Envisan International Sa",
    "wof:placetype":"venue"
},
  "geometry": {"coordinates":[4.4245052338,50.4448814392],"type":"Point"}
}