{
  "type": "Feature",
  "properties": {
    "iso:country":"BE",
    "sg:address":"Grand Route 90",
    "sg:city":"Drogenbos",
    "sg:classifiers":[
        {
            "category":"Professional",
            "subcategory":"Testing Lab",
            "type":"Services"
        }
    ],
    "sg:phone":"+32 2 377 05 63",
    "sg:postcode":"1620",
    "sg:province":"Vlaams-Brabant",
    "sg:tags":[
        "chemist"
    ],
    "wof:name":"Diericx V",
    "wof:placetype":"venue"
},
  "geometry": {"coordinates":[4.3247799873,50.7804794312],"type":"Point"}
}