{
  "type": "Feature",
  "properties": {
    "addr:full":"Av. Eug\u00c8ne Mullendorff 91b4 Verviers Li\u00e8ge 4800",
    "addr:housenumber":"91b4",
    "addr:postcode":"4800",
    "addr:street":"Av. Euge\u0300Ne Mullendorff",
    "iso:country":"BE",
    "sg:address":"Av. Eug\u00c8ne Mullendorff 91b4",
    "sg:city":"Verviers",
    "sg:orig_category":"Artsen and specialisten",
    "sg:phone":"+32 87 31 18 25",
    "sg:postcode":"4800",
    "sg:province":"Li\u00e8ge",
    "wof:name":"Fran\u00c7oise Jason",
    "wof:placetype":"venue"
},
  "geometry": {"coordinates":[5.8703861237,50.588722229],"type":"Point"}
}