{
  "type": "Feature",
  "properties": {
    "addr:full":"Ronsestraat 125 Brakel Oost-Vlaanderen 9660",
    "addr:housenumber":"125",
    "addr:postcode":"9660",
    "addr:street":"Ronsestraat",
    "iso:country":"BE",
    "sg:address":"Ronsestraat 125",
    "sg:city":"Brakel",
    "sg:orig_category":"Loodgieterij, verwarming and sanitaire installaties",
    "sg:phone":"+32 55 42 26 63",
    "sg:postcode":"9660",
    "sg:province":"Oost-Vlaanderen",
    "wof:name":"Van Maeldergem",
    "wof:placetype":"venue"
},
  "geometry": {"coordinates":[3.7642250061,50.8031082153],"type":"Point"}
}