{
  "type": "Feature",
  "properties": {
    "addr:full":"Rue Des Moissons 10 Bouillon Luxembourg 6830",
    "addr:housenumber":"10",
    "addr:postcode":"6830",
    "addr:street":"Rue Des Moissons",
    "iso:country":"BE",
    "sg:address":"Rue Des Moissons 10",
    "sg:city":"Bouillon",
    "sg:classifiers":[
        {
            "category":"Cafe",
            "type":"Food & Drink"
        }
    ],
    "sg:phone":"+32 61 46 65 23",
    "sg:postcode":"6830",
    "sg:province":"Luxembourg",
    "sg:tags":[
        "caf\u00e9s"
    ],
    "wof:name":"Caf\u00c9 La Cabane",
    "wof:placetype":"venue"
},
  "geometry": {"coordinates":[5.0699849129,49.7954597473],"type":"Point"}
}