{
  "type": "Feature",
  "properties": {
    "iso:country":"BE",
    "sg:address":"Rue Garnier 2",
    "sg:city":"Tournai",
    "sg:classifiers":[
        {
            "category":"Insurance",
            "subcategory":"Insurance Agent",
            "type":"Services"
        }
    ],
    "sg:phone":"+32 69 21 52 02",
    "sg:postcode":"7500",
    "sg:province":"Hainaut",
    "sg:tags":[
        "broker"
    ],
    "wof:name":"Guevar Lelubre Vanderborght Ci",
    "wof:placetype":"venue"
},
  "geometry": {"coordinates":[3.3888781071,50.6046791077],"type":"Point"}
}