{
  "type": "Feature",
  "properties": {
    "iso:country":"BE",
    "sg:address":"Boulevard D'avroy 242",
    "sg:city":"Li\u00e8ge",
    "sg:orig_category":"Trade In Office Supplies",
    "sg:phone":"+32 4 252 00 71",
    "sg:postcode":"4000",
    "sg:province":"Li\u00e8ge",
    "wof:name":"Poncin S.c.",
    "wof:placetype":"venue"
},
  "geometry": {"coordinates":[5.5673332214,50.6316184998],"type":"Point"}
}