{
  "type": "Feature",
  "properties": {
    "iso:country":"BE",
    "sg:address":"Bleekveldstraat 7",
    "sg:city":"Overpelt",
    "sg:orig_category":"Installatie van houten of kunststof schrijnwerk Verlichting and huishoudartikelen",
    "sg:phone":"+32 11 66 26 91",
    "sg:postcode":"3900",
    "sg:province":"Limburg",
    "wof:name":"Interieurbouw Schevernels Jos",
    "wof:placetype":"venue"
},
  "geometry": {"coordinates":[5.4342851639,51.2086486816],"type":"Point"}
}