{
  "type": "Feature",
  "properties": {
    "iso:country":"BE",
    "sg:address":"Zwijndrechtsestraat 42",
    "sg:city":"Zwijndrecht (burcht)",
    "sg:classifiers":[
        {
            "category":"Personal",
            "subcategory":"Beauty Salon",
            "type":"Services"
        }
    ],
    "sg:phone":"+32 3 252 48 32",
    "sg:postcode":"2070",
    "sg:province":"Antwerpen",
    "sg:tags":[
        "lady",
        "-",
        "hairdressing"
    ],
    "wof:name":"Puls H",
    "wof:placetype":"venue"
},
  "geometry": {"coordinates":[4.3466382027,51.2050132751],"type":"Point"}
}