{
  "type": "Feature",
  "properties": {
    "iso:country":"BE",
    "sg:address":"Rue De Bascoup 378",
    "sg:city":"Manage",
    "sg:orig_category":"Brood, gebak and snoepgoed",
    "sg:phone":"+32 64 44 94 32",
    "sg:postcode":"7170",
    "sg:province":"Hainaut",
    "wof:name":"Sirault",
    "wof:placetype":"venue"
},
  "geometry": {"coordinates":[4.2539591789,50.4742126465],"type":"Point"}
}