{
  "type": "Feature",
  "properties": {
    "addr:full":"Dolezlaan 89 Ukkel/uccle Bruxelles-Capitale 1180",
    "addr:housenumber":"89",
    "addr:postcode":"1180",
    "addr:street":"Dolezlaan;/",
    "iso:country":"BE",
    "sg:address":"Dolezlaan 89",
    "sg:city":"Ukkel/uccle",
    "sg:orig_category":"Loodgieterij, verwarming and sanitaire installaties",
    "sg:phone":"+32 2 374 51 09",
    "sg:postcode":"1180",
    "sg:province":"Bruxelles-Capitale",
    "wof:name":"Maurice Merkpoel",
    "wof:placetype":"venue"
},
  "geometry": {"coordinates":[4.3586120605,50.7899971008],"type":"Point"}
}