{
  "type": "Feature",
  "properties": {
    "iso:country":"BE",
    "sg:address":"Rue Germinal 6",
    "sg:city":"Beyne-heusay",
    "sg:classifiers":[
        {
            "category":"Banks & Credit Unions",
            "subcategory":"Financial Services",
            "type":"Services"
        }
    ],
    "sg:phone":"+32 4 358 74 66",
    "sg:postcode":"4610",
    "sg:province":"Li\u00e8ge",
    "sg:tags":[
        "financing"
    ],
    "wof:name":"Amr",
    "wof:placetype":"venue"
},
  "geometry": {"coordinates":[5.6675748825,50.6211585999],"type":"Point"}
}