{
  "type": "Feature",
  "properties": {
    "iso:country":"BE",
    "sg:address":"Acacialaan 54",
    "sg:city":"Herent",
    "sg:orig_category":"Artsen and specialisten",
    "sg:phone":"+32 16 22 83 45",
    "sg:postcode":"3020",
    "sg:province":"Vlaams-Brabant",
    "wof:name":"Paul Michielsen",
    "wof:placetype":"venue"
},
  "geometry": {"coordinates":[4.6780500412,50.8936195374],"type":"Point"}
}