{
  "type": "Feature",
  "properties": {
    "iso:country":"BE",
    "sg:address":"Rue Joseph Wauters 152",
    "sg:city":"Charleroi",
    "sg:orig_category":"Industri\u00eble wasserijen and droogkuis",
    "sg:phone":"+32 71 31 79 57",
    "sg:postcode":"6020",
    "sg:province":"Hainaut",
    "wof:name":"Blanchisserie Voss",
    "wof:placetype":"venue"
},
  "geometry": {"coordinates":[4.4301037788,50.419960022],"type":"Point"}
}