{
  "type": "Feature",
  "properties": {
    "iso:country":"BE",
    "sg:address":"Kolveniersvest 9",
    "sg:city":"Lier",
    "sg:classifiers":[
        {
            "category":"Restaurant",
            "type":"Food & Drink"
        }
    ],
    "sg:phone":"+32 3 488 44 66",
    "sg:postcode":"2500",
    "sg:province":"Antwerpen",
    "wof:name":"Restaurant De Kolvenier",
    "wof:placetype":"venue"
},
  "geometry": {"coordinates":[4.5668458939,51.1319885254],"type":"Point"}
}