{
  "type": "Feature",
  "properties": {
    "iso:country":"BE",
    "sg:address":"Rue Bai-jouai 20",
    "sg:city":"Wellin",
    "sg:orig_category":"Artiesten and kunstenaars",
    "sg:phone":"+32 84 38 94 32",
    "sg:postcode":"6920",
    "sg:province":"Luxembourg",
    "wof:name":"Giovanna Cerrico",
    "wof:placetype":"venue"
},
  "geometry": {"coordinates":[5.1154389381,50.0784187317],"type":"Point"}
}