{
  "type": "Feature",
  "properties": {
    "addr:full":"Vandenbrandenstraat 33 Brussel/bruxelles Bruxelles-Capitale 1000",
    "addr:housenumber":"33",
    "addr:postcode":"1000",
    "addr:street":"Vandenbrandenstraat;/",
    "iso:country":"BE",
    "sg:address":"Vandenbrandenstraat 33",
    "sg:city":"Brussel/bruxelles",
    "sg:orig_category":"Plaatsen van vloer- and muurbekleding Schilders",
    "sg:phone":"+32 2 514 43 32",
    "sg:postcode":"1000",
    "sg:province":"Bruxelles-Capitale",
    "wof:name":"Samco Renovation",
    "wof:placetype":"venue"
},
  "geometry": {"coordinates":[4.3403367996,50.8511619568],"type":"Point"}
}