{
  "type": "Feature",
  "properties": {
    "addr:full":"Ouburg 48 Dendermonde Oost-Vlaanderen 9200",
    "addr:housenumber":"48",
    "addr:postcode":"9200",
    "addr:street":"Ouburg;Oost-Vlaanderen",
    "iso:country":"BE",
    "sg:address":"Ouburg 48",
    "sg:city":"Dendermonde",
    "sg:orig_category":"Installation de menuiserie m\u00e9tallique",
    "sg:phone":"+32 52 22 54 17",
    "sg:postcode":"9200",
    "sg:province":"Oost-Vlaanderen",
    "wof:name":"L. Ledegen",
    "wof:placetype":"venue"
},
  "geometry": {"coordinates":[4.1011428833,51.028755188],"type":"Point"}
}