{
  "type": "Feature",
  "properties": {
    "addr:full":"Quai De Longdoz 55bb Li\u00c8ge Li\u00e8ge 4020",
    "addr:housenumber":"55bb",
    "addr:postcode":"4020",
    "addr:street":"Quai De Longdoz",
    "iso:country":"BE",
    "sg:address":"Quai De Longdoz 55bb",
    "sg:city":"Li\u00c8ge",
    "sg:orig_category":"Rusthuizen and serviceflats",
    "sg:phone":"+32 4 342 43 58",
    "sg:postcode":"4020",
    "sg:province":"Li\u00e8ge",
    "wof:name":"R\u00c9sidence Belle-vue",
    "wof:placetype":"venue"
},
  "geometry": {"coordinates":[5.5822610855,50.6368141174],"type":"Point"}
}