{
  "type": "Feature",
  "properties": {
    "iso:country":"BE",
    "sg:address":"Bretheistraat 123 Box 3",
    "sg:city":"Genk",
    "sg:classifiers":[
        {
            "category":"Personal",
            "subcategory":"Beauty Salon",
            "type":"Services"
        }
    ],
    "sg:phone":"+32 89 36 78 40",
    "sg:postcode":"3600",
    "sg:province":"Limburg",
    "sg:tags":[
        "lady",
        "-",
        "hairdressing"
    ],
    "wof:name":"Hairdressing Zara",
    "wof:placetype":"venue"
},
  "geometry": {"coordinates":[5.5124697685,50.9711685181],"type":"Point"}
}