{
  "type": "Feature",
  "properties": {
    "addr:full":"Sint-antoniusstraat 131 Anzegem (ingooigem) West-Vlaanderen 8570",
    "addr:housenumber":"131",
    "addr:postcode":"8570",
    "addr:street":"Sint-Antoniusstraat",
    "iso:country":"BE",
    "sg:address":"Sint-antoniusstraat 131",
    "sg:city":"Anzegem (ingooigem)",
    "sg:classifiers":[
        {
            "category":"Social Services",
            "subcategory":"Child Care",
            "type":"Services"
        }
    ],
    "sg:phone":"+32 56 77 34 06",
    "sg:postcode":"8570",
    "sg:province":"West-Vlaanderen",
    "sg:tags":[
        "baby",
        "nursery",
        "day",
        "sitting"
    ],
    "wof:name":"Kiekeboe",
    "wof:placetype":"venue"
},
  "geometry": {"coordinates":[3.4232439995,50.835357666],"type":"Point"}
}