{
  "type": "Feature",
  "properties": {
    "iso:country":"BE",
    "sg:address":"Porseleinstraat 4",
    "sg:city":"Anderlecht",
    "sg:orig_category":"Zalen voor culturele evenementen",
    "sg:phone":"+32 2 521 76 52",
    "sg:postcode":"1070",
    "sg:province":"Bruxelles-Capitale",
    "wof:name":"Th\u00c9\u00c2tre Hypoth\u00c8sarts",
    "wof:placetype":"venue"
},
  "geometry": {"coordinates":[4.3056812286,50.8360786438],"type":"Point"}
}