{
  "type": "Feature",
  "properties": {
    "iso:country":"BE",
    "sg:address":"Hogenhovestraat 12",
    "sg:city":"Tielt (aarsele)",
    "sg:classifiers":[
        {
            "category":"Home & Garden",
            "subcategory":"Garden Supply",
            "type":"Retail Goods"
        }
    ],
    "sg:phone":"+32 51 63 59 41",
    "sg:postcode":"8700",
    "sg:province":"West-Vlaanderen",
    "wof:name":"Aveve-verbrugge Rik",
    "wof:placetype":"venue"
},
  "geometry": {"coordinates":[3.4193410873,50.9887046814],"type":"Point"}
}