{
  "type": "Feature",
  "properties": {
    "addr:full":"Rue Docq 36 Gembloux Namur 5030",
    "addr:housenumber":"36",
    "addr:postcode":"5030",
    "addr:street":"Rue Docq;Namur",
    "iso:country":"BE",
    "sg:address":"Rue Docq 36",
    "sg:city":"Gembloux",
    "sg:orig_category":"Sportclubs",
    "sg:phone":"+32 81 61 06 80",
    "sg:postcode":"5030",
    "sg:province":"Namur",
    "wof:name":"Club Loisirs 2 X 30",
    "wof:placetype":"venue"
},
  "geometry": {"coordinates":[4.6967730522,50.5607833862],"type":"Point"}
}