{
  "type": "Feature",
  "properties": {
    "iso:country":"BE",
    "sg:address":"Kattevennen 2a",
    "sg:city":"Genk",
    "sg:classifiers":[
        {
            "category":"Insurance",
            "subcategory":"Insurance Agent",
            "type":"Services"
        }
    ],
    "sg:phone":"+32 89 50 42 04",
    "sg:postcode":"3600",
    "sg:province":"Limburg",
    "sg:tags":[
        "broker"
    ],
    "wof:name":"A.i.c. Bvba",
    "wof:placetype":"venue"
},
  "geometry": {"coordinates":[5.5203380585,50.9633789062],"type":"Point"}
}