{
  "type": "Feature",
  "properties": {
    "addr:full":"Monseigneur Meulemanstraat 56 Sint-lievens-houtem Oost-Vlaanderen 9520",
    "addr:housenumber":"56",
    "addr:postcode":"9520",
    "addr:street":"Monseigneur Meulemanstraat",
    "iso:country":"BE",
    "sg:address":"Monseigneur Meulemanstraat 56",
    "sg:city":"Sint-lievens-houtem",
    "sg:classifiers":[
        {
            "category":"Health Services",
            "subcategory":"Health Practitioner",
            "type":"Services"
        }
    ],
    "sg:phone":"+32 53 62 93 09",
    "sg:postcode":"9520",
    "sg:province":"Oost-Vlaanderen",
    "sg:tags":[
        "physiotherapist"
    ],
    "wof:name":"De Winne An",
    "wof:placetype":"venue"
},
  "geometry": {"coordinates":[3.8489511013,50.9241294861],"type":"Point"}
}