{
  "type": "Feature",
  "properties": {
    "iso:country":"BE",
    "sg:address":"Place De La Gare 12",
    "sg:city":"Jemeppe-sur-sambre",
    "sg:orig_category":"Treinen and spoorwegen",
    "sg:phone":"+32 71 78 52 65",
    "sg:postcode":"5190",
    "sg:province":"Namur",
    "wof:name":"Gare De Moustier",
    "wof:placetype":"venue"
},
  "geometry": {"coordinates":[4.695371151,50.4531402588],"type":"Point"}
}