{
  "type": "Feature",
  "properties": {
    "iso:country":"BE",
    "sg:address":"Chaussee De Nivelles 46",
    "sg:city":"Mazy",
    "sg:classifiers":[
        {
            "category":"Home & Garden",
            "subcategory":"Building Materials",
            "type":"Retail Goods"
        }
    ],
    "sg:phone":"+32 81 63 36 64",
    "sg:postcode":"5032",
    "sg:province":"Namur",
    "sg:tags":[
        "veranda"
    ],
    "wof:name":"Volet Plus Confort Chassis",
    "wof:placetype":"venue"
},
  "geometry": {"coordinates":[4.6725320816,50.5144615173],"type":"Point"}
}