{
  "type": "Feature",
  "properties": {
    "addr:full":"Groteheidestraat 118 Beveren Oost-Vlaanderen 9120",
    "addr:housenumber":"118",
    "addr:postcode":"9120",
    "addr:street":"Groteheidestraat",
    "iso:country":"BE",
    "sg:address":"Groteheidestraat 118",
    "sg:city":"Beveren",
    "sg:orig_category":"Electrom\u00e9nager, t\u00e9l\u00e9visions and radios. Installation \u00e9lectrique r\u00e9sidentielle",
    "sg:phone":"+32 3 750 91 40",
    "sg:postcode":"9120",
    "sg:province":"Oost-Vlaanderen",
    "wof:name":"Leon Smet",
    "wof:placetype":"venue"
},
  "geometry": {"coordinates":[4.2242918015,51.2044944763],"type":"Point"}
}