{
  "type": "Feature",
  "properties": {
    "addr:full":"Schoolstraat 24ba Ichtegem West-Vlaanderen 8480",
    "addr:housenumber":"24ba",
    "addr:postcode":"8480",
    "addr:street":"Schoolstraat",
    "iso:country":"BE",
    "sg:address":"Schoolstraat 24ba",
    "sg:city":"Ichtegem",
    "sg:orig_category":"Boucheries",
    "sg:phone":"+32 50 21 65 29",
    "sg:postcode":"8480",
    "sg:province":"West-Vlaanderen",
    "wof:name":"Marc Standaert",
    "wof:placetype":"venue"
},
  "geometry": {"coordinates":[3.0562911034,51.0897331238],"type":"Point"}
}