{
  "type": "Feature",
  "properties": {
    "addr:full":"Dorpstraat 19 Gavere Oost-Vlaanderen 9890",
    "addr:housenumber":"19",
    "addr:postcode":"9890",
    "addr:street":"Dorpstraat",
    "iso:country":"BE",
    "sg:address":"Dorpstraat 19",
    "sg:city":"Gavere",
    "sg:orig_category":"HUISBRANDOLIE",
    "sg:phone":"+32 9 384 11 06",
    "sg:postcode":"9890",
    "sg:province":"Oost-Vlaanderen",
    "wof:name":"Marc Van Lierde",
    "wof:placetype":"venue"
},
  "geometry": {"coordinates":[3.6650829315,50.9433822632],"type":"Point"}
}