{
  "type": "Feature",
  "properties": {
    "iso:country":"BE",
    "sg:address":"Torhoutsestraat 323",
    "sg:city":"Oostkamp",
    "sg:classifiers":[
        {
            "category":"Cafe",
            "type":"Food & Drink"
        }
    ],
    "sg:phone":"+32 50 27 83 46",
    "sg:postcode":"8020",
    "sg:province":"West-Vlaanderen",
    "sg:tags":[
        "caf\u00e9s"
    ],
    "wof:name":"Caf\u00c9 Klakmolen",
    "wof:placetype":"venue"
},
  "geometry": {"coordinates":[3.1683809757,51.0756721497],"type":"Point"}
}