{
  "type": "Feature",
  "properties": {
    "iso:country":"BE",
    "sg:address":"Rue De Loncin 13",
    "sg:city":"Bruxelles (saint-gilles)",
    "sg:classifiers":[
        {
            "category":"Building & Trades",
            "subcategory":"Cleaning & Sanitation",
            "type":"Services"
        }
    ],
    "sg:phone":"+32 2 346 68 17",
    "sg:postcode":"1060",
    "sg:province":"Bruxelles-Capitale",
    "sg:tags":[
        "cleaner",
        "window"
    ],
    "wof:name":"I.t.s.",
    "wof:placetype":"venue"
},
  "geometry": {"coordinates":[4.3439741135,50.8246231079],"type":"Point"}
}