{
  "type": "Feature",
  "properties": {
    "addr:full":"Avenue Ch\u00c2teau De Walzin 2b9 Ukkel/uccle Bruxelles-Capitale 1180",
    "addr:housenumber":"2b9",
    "addr:postcode":"1180",
    "addr:street":"Avenue Cha\u0302Teau De Walzin;/",
    "iso:country":"BE",
    "sg:address":"Avenue Ch\u00c2teau De Walzin 2b9",
    "sg:city":"Ukkel/uccle",
    "sg:orig_category":"Administration d'immeubles",
    "sg:phone":"+32 2 345 90 75",
    "sg:postcode":"1180",
    "sg:province":"Bruxelles-Capitale",
    "wof:name":"B.g.i.s.",
    "wof:placetype":"venue"
},
  "geometry": {"coordinates":[4.3467001915,50.8072776794],"type":"Point"}
}