{
  "type": "Feature",
  "properties": {
    "iso:country":"BE",
    "sg:address":"Place Du Vingt Ao\u00dbt 24",
    "sg:city":"Liege",
    "sg:orig_category":"Diverse organisaties and verenigingen Kinderopvang aan huis",
    "sg:phone":"+32 4 366 31 99",
    "sg:postcode":"4000",
    "sg:province":"Li\u00e8ge",
    "wof:name":"F\u00c9d\u00c9ration Des Etudiants Travailleurs",
    "wof:placetype":"venue"
},
  "geometry": {"coordinates":[5.5750861168,50.6404533386],"type":"Point"}
}