{
  "type": "Feature",
  "properties": {
    "addr:full":"Chauss\u00e9e De Zellik 12 Bruxelles (berchem-sainte-agathe) Bruxelles-Capitale 1082",
    "addr:housenumber":"12",
    "addr:postcode":"1082",
    "addr:street":"Chausse\u0301E De Zellik",
    "iso:country":"BE",
    "sg:address":"Chauss\u00e9e De Zellik 12",
    "sg:city":"Bruxelles (berchem-sainte-agathe)",
    "sg:classifiers":[
        {
            "category":"Insurance",
            "subcategory":"Insurance Agent",
            "type":"Services"
        }
    ],
    "sg:phone":"+32 2 465 91 01",
    "sg:postcode":"1082",
    "sg:province":"Bruxelles-Capitale",
    "sg:tags":[
        "broker"
    ],
    "wof:name":"Protectas Nv",
    "wof:placetype":"venue"
},
  "geometry": {"coordinates":[4.2906780243,50.8697357178],"type":"Point"}
}