{
  "type": "Feature",
  "properties": {
    "addr:full":"Rue De L'espinette 6b Chapelle-lez-herlaimont (godarville) Hainaut 7160",
    "addr:housenumber":"6b",
    "addr:postcode":"7160",
    "addr:street":"Rue De L'Espinette",
    "iso:country":"BE",
    "sg:address":"Rue De L'espinette 6b",
    "sg:city":"Chapelle-lez-herlaimont (godarville)",
    "sg:classifiers":[
        {
            "category":"Retail",
            "subcategory":"Auto Repair",
            "type":"Services"
        }
    ],
    "sg:phone":"+32 64 44 23 79",
    "sg:postcode":"7160",
    "sg:province":"Hainaut",
    "sg:tags":[
        "automobile-body"
    ],
    "wof:name":"Russo Fioreavanti",
    "wof:placetype":"venue"
},
  "geometry": {"coordinates":[4.2905321121,50.4923858643],"type":"Point"}
}