{
  "type": "Feature",
  "properties": {
    "iso:country":"BE",
    "sg:address":"Avenue Louis Libert 8",
    "sg:city":"Aywaille",
    "sg:orig_category":"Kapsalons",
    "sg:phone":"+32 4 384 70 07",
    "sg:postcode":"4920",
    "sg:province":"Li\u00e8ge",
    "wof:name":"Coiffeur Sam",
    "wof:placetype":"venue"
},
  "geometry": {"coordinates":[5.6764879227,50.4735603333],"type":"Point"}
}