{
  "type": "Feature",
  "properties": {
    "iso:country":"BE",
    "sg:address":"Rue Des Egalots 9",
    "sg:city":"Fosses-la-ville",
    "sg:orig_category":"Sportclubs Sportterreinen and installaties behalve sportcentra",
    "sg:phone":"+32 71 71 36 83",
    "sg:postcode":"5070",
    "sg:province":"Namur",
    "wof:name":"R.u.s. Fossoise",
    "wof:placetype":"venue"
},
  "geometry": {"coordinates":[4.6961750984,50.3957252502],"type":"Point"}
}