{
  "type": "Feature",
  "properties": {
    "addr:full":"Zandhovensteenweg 44 Ranst (oelegem) Antwerpen 2520",
    "addr:housenumber":"44",
    "addr:postcode":"2520",
    "addr:street":"Zandhovensteenweg",
    "iso:country":"BE",
    "sg:address":"Zandhovensteenweg 44",
    "sg:city":"Ranst (oelegem)",
    "sg:classifiers":[
        {
            "category":"Building & Trades",
            "subcategory":"Pest Control",
            "type":"Services"
        }
    ],
    "sg:phone":"+32 3 383 19 62",
    "sg:postcode":"2520",
    "sg:province":"Antwerpen",
    "sg:tags":[
        "painting",
        "contractor"
    ],
    "wof:name":"Simons G",
    "wof:placetype":"venue"
},
  "geometry": {"coordinates":[4.6048741341,51.2107963562],"type":"Point"}
}