{
  "type": "Feature",
  "properties": {
    "addr:full":"Heirweg 44 Moerbeke (moerbeke-waas) Oost-Vlaanderen 9180",
    "addr:housenumber":"44",
    "addr:postcode":"9180",
    "addr:street":"Heirweg",
    "iso:country":"BE",
    "sg:address":"Heirweg 44",
    "sg:city":"Moerbeke (moerbeke-waas)",
    "sg:classifiers":[
        {
            "category":"Wholesale",
            "subcategory":"Beer",
            "type":"Manufacturing & Wholesale Goods"
        }
    ],
    "sg:phone":"+32 9 346 79 03",
    "sg:postcode":"9180",
    "sg:province":"Oost-Vlaanderen",
    "sg:tags":[
        "ale",
        "-"
    ],
    "wof:name":"Koudenborm",
    "wof:placetype":"venue"
},
  "geometry": {"coordinates":[3.9653201103,51.1743621826],"type":"Point"}
}