{
  "type": "Feature",
  "properties": {
    "addr:full":"Laurens De Metsstraat 72 Zottegem Oost-Vlaanderen 9620",
    "addr:housenumber":"72",
    "addr:postcode":"9620",
    "addr:street":"Laurens;Metsstraat",
    "iso:country":"BE",
    "sg:address":"Laurens De Metsstraat 72",
    "sg:city":"Zottegem",
    "sg:orig_category":"Non-Classified Establishments",
    "sg:phone":"+32 9 360 21 43",
    "sg:postcode":"9620",
    "sg:province":"Oost-Vlaanderen",
    "wof:name":"Pavao Martins Bvba",
    "wof:placetype":"venue"
},
  "geometry": {"coordinates":[3.8140540123,50.8716239929],"type":"Point"}
}