{
  "type": "Feature",
  "properties": {
    "addr:full":"Bunderbeeklaan 26 Kapellen (mariaburg) Antwerpen 2950",
    "addr:housenumber":"26",
    "addr:postcode":"2950",
    "addr:street":"Bunderbeeklaan",
    "iso:country":"BE",
    "sg:address":"Bunderbeeklaan 26",
    "sg:city":"Kapellen (mariaburg)",
    "sg:classifiers":[
        {
            "category":"Professional",
            "subcategory":"Advertising",
            "type":"Services"
        }
    ],
    "sg:phone":"+32 3 665 02 13",
    "sg:postcode":"2950",
    "sg:province":"Antwerpen",
    "sg:tags":[
        "item",
        "-",
        "business",
        "gift",
        "promotional"
    ],
    "wof:name":"Allied Dynamic Products",
    "wof:placetype":"venue"
},
  "geometry": {"coordinates":[4.4424610138,51.3100891113],"type":"Point"}
}