{
  "type": "Feature",
  "properties": {
    "addr:full":"Rue De L'institut 75 Rixensart Brabant Wallon 1330",
    "addr:housenumber":"75",
    "addr:postcode":"1330",
    "addr:street":"Rue De L'Institut;Wallon",
    "iso:country":"BE",
    "sg:address":"Rue De L'institut 75",
    "sg:city":"Rixensart",
    "sg:classifiers":[
        {
            "category":"Shopping",
            "subcategory":"Antiques",
            "type":"Retail Goods"
        }
    ],
    "sg:phone":"+32 2 653 96 10",
    "sg:postcode":"1330",
    "sg:province":"Brabant Wallon",
    "wof:name":"Mano Lopez",
    "wof:placetype":"venue"
},
  "geometry": {"coordinates":[4.5276031494,50.72215271],"type":"Point"}
}