{
  "type": "Feature",
  "properties": {
    "addr:full":"Leuvensesteenweg 47 Mechelen Antwerpen 2800",
    "addr:housenumber":"47",
    "addr:postcode":"2800",
    "addr:street":"Leuvensesteenweg",
    "iso:country":"BE",
    "sg:address":"Leuvensesteenweg 47",
    "sg:city":"Mechelen",
    "sg:orig_category":"Epiceries",
    "sg:phone":"+32 15 41 12 97",
    "sg:postcode":"2800",
    "sg:province":"Antwerpen",
    "wof:name":"Van Der Wildt",
    "wof:placetype":"venue"
},
  "geometry": {"coordinates":[4.4915962219,51.0205001831],"type":"Point"}
}