{
  "type": "Feature",
  "properties": {
    "addr:full":"Dorpsstraat 17-1 Bocholt Limburg 3950",
    "addr:housenumber":"17-1",
    "addr:postcode":"3950",
    "addr:street":"Dorpsstraat",
    "iso:country":"BE",
    "sg:address":"Dorpsstraat 17-1",
    "sg:city":"Bocholt",
    "sg:classifiers":[
        {
            "category":"Banks & Credit Unions",
            "subcategory":"Investment Brokerage",
            "type":"Services"
        }
    ],
    "sg:phone":"+32 89 46 28 78",
    "sg:postcode":"3950",
    "sg:province":"Limburg",
    "sg:tags":[
        "printing",
        "-"
    ],
    "wof:name":"Schetz",
    "wof:placetype":"venue"
},
  "geometry": {"coordinates":[5.5798001289,51.1734580994],"type":"Point"}
}