{
  "type": "Feature",
  "properties": {
    "addr:full":"Grand'rue 70 Gembloux-sur-orneau (gembloux) Namur 5030",
    "addr:housenumber":"70",
    "addr:postcode":"5030",
    "addr:street":"Grand'Rue;Namur",
    "iso:country":"BE",
    "sg:address":"Grand'rue 70",
    "sg:city":"Gembloux-sur-orneau (gembloux)",
    "sg:classifiers":[
        {
            "category":"Shopping",
            "subcategory":"Clothing, Apparel, & Fashions",
            "type":"Retail Goods"
        }
    ],
    "sg:phone":"+32 81 61 57 49",
    "sg:postcode":"5030",
    "sg:province":"Namur",
    "sg:tags":[
        "clothing",
        "-",
        "gentleman"
    ],
    "wof:name":"Dominique (chemiserie)",
    "wof:placetype":"venue"
},
  "geometry": {"coordinates":[4.6945400238,50.5666313171],"type":"Point"}
}