{
  "type": "Feature",
  "properties": {
    "iso:country":"BE",
    "sg:address":"Rue De La Victoire 122",
    "sg:city":"Bruxelles (saint-gilles)",
    "sg:orig_category":"Non-Classified Establishments",
    "sg:phone":"+32 2 520 11 64",
    "sg:postcode":"1060",
    "sg:province":"Bruxelles-Capitale",
    "wof:name":"Ag Lighting",
    "wof:placetype":"venue"
},
  "geometry": {"coordinates":[4.3503251076,50.8290786743],"type":"Point"}
}