{
  "type": "Feature",
  "properties": {
    "addr:full":"Place Francesco Ferrer 10 Charleroi Hainaut 6040",
    "addr:housenumber":"10",
    "addr:postcode":"6040",
    "addr:street":"Place Francesco Ferrer;Hainaut",
    "iso:country":"BE",
    "sg:address":"Place Francesco Ferrer 10",
    "sg:city":"Charleroi",
    "sg:classifiers":[
        {
            "category":"Food & Beverages",
            "subcategory":"Fruits & Vegetables",
            "type":"Retail Goods"
        }
    ],
    "sg:phone":"+32 71 37 58 31",
    "sg:postcode":"6040",
    "sg:province":"Hainaut",
    "sg:tags":[
        "l\u00e9gumes"
    ],
    "wof:name":"La Corbeille D'or",
    "wof:placetype":"venue"
},
  "geometry": {"coordinates":[4.3917818069,50.441318512],"type":"Point"}
}