{
  "type": "Feature",
  "properties": {
    "addr:full":"Avenue De La Libert\u00c9 101 Sint-jans-molenbeek/molenbeek-saint-jean Bruxelles-Capitale 1080",
    "addr:housenumber":"101",
    "addr:postcode":"1080",
    "addr:street":"Avenue De La Liberte\u0301",
    "iso:country":"BE",
    "sg:address":"Avenue De La Libert\u00c9 101",
    "sg:city":"Sint-jans-molenbeek/molenbeek-saint-jean",
    "sg:orig_category":"Reliure and finition",
    "sg:phone":"+32 2 414 42 72",
    "sg:postcode":"1080",
    "sg:province":"Bruxelles-Capitale",
    "wof:name":"Caroline Mardulyn",
    "wof:placetype":"venue"
},
  "geometry": {"coordinates":[4.3216881752,50.8615570068],"type":"Point"}
}