{
  "type": "Feature",
  "properties": {
    "addr:full":"Avenue Louise 341b8 Elsene/ixelles Bruxelles-Capitale 1050",
    "addr:housenumber":"341b8",
    "addr:postcode":"1050",
    "addr:street":"Avenue Louise",
    "iso:country":"BE",
    "sg:address":"Avenue Louise 341b8",
    "sg:city":"Elsene/ixelles",
    "sg:orig_category":"Avocats and conseillers juridiques",
    "sg:phone":"+32 2 627 14 11",
    "sg:postcode":"1050",
    "sg:province":"Bruxelles-Capitale",
    "wof:name":"Colinet F.",
    "wof:placetype":"venue"
},
  "geometry": {"coordinates":[4.355919838,50.8357810974],"type":"Point"}
}