{
  "type": "Feature",
  "properties": {
    "addr:full":"Melveren-centrum 148 Sint-truiden Limburg 3800",
    "addr:housenumber":"148",
    "addr:postcode":"sint-truiden;3800",
    "addr:street":"Melveren-Centrum",
    "iso:country":"BE",
    "sg:address":"Melveren-centrum 148",
    "sg:city":"Sint-truiden",
    "sg:orig_category":"Producteurs de fruits",
    "sg:phone":"+32 11 68 73 30",
    "sg:postcode":"3800",
    "sg:province":"Limburg",
    "wof:name":"Paul Koekelbergh",
    "wof:placetype":"venue"
},
  "geometry": {"coordinates":[5.1962499619,50.8356361389],"type":"Point"}
}