{
  "type": "Feature",
  "properties": {
    "addr:full":"Ketelstraat 12 Zoutleeuw Vlaams-Brabant 3440",
    "addr:housenumber":"12",
    "addr:postcode":"3440",
    "addr:street":"Ketelstraat;Vlaams-Brabant",
    "iso:country":"BE",
    "sg:address":"Ketelstraat 12",
    "sg:city":"Zoutleeuw",
    "sg:orig_category":"Eleveurs and marchands de porcs. Producteurs de l\u00e9gumes. Producteurs de fruits",
    "sg:phone":"+32 11 58 77 28",
    "sg:postcode":"3440",
    "sg:province":"Vlaams-Brabant",
    "wof:name":"Benedict Knops",
    "wof:placetype":"venue"
},
  "geometry": {"coordinates":[5.0690188408,50.873336792],"type":"Point"}
}