{
  "type": "Feature",
  "properties": {
    "iso:country":"BE",
    "sg:address":"Lode De Boningestraat 51",
    "sg:city":"Wevelgem",
    "sg:classifiers":[
        {
            "category":"Shopping",
            "subcategory":"Clothing, Apparel, & Fashions",
            "type":"Retail Goods"
        }
    ],
    "sg:phone":"+32 56 41 25 25",
    "sg:postcode":"8560",
    "sg:province":"West-Vlaanderen",
    "sg:tags":[
        "boutique"
    ],
    "wof:name":"Ticha",
    "wof:placetype":"venue"
},
  "geometry": {"coordinates":[3.1813590527,50.8102989197],"type":"Point"}
}