{
  "type": "Feature",
  "properties": {
    "iso:country":"BE",
    "sg:address":"Rue Bois Eloi 3",
    "sg:city":"Lasne",
    "sg:orig_category":"Maisons de vacances",
    "sg:phone":"+32 2 633 23 28",
    "sg:postcode":"1380",
    "sg:province":"Brabant Wallon",
    "wof:name":"G\u00cete Rural",
    "wof:placetype":"venue"
},
  "geometry": {"coordinates":[4.4710488319,50.6756210327],"type":"Point"}
}