{
  "type": "Feature",
  "properties": {
    "iso:country":"BE",
    "sg:address":"Haut-v\u00c2 16",
    "sg:city":"Manhay",
    "sg:orig_category":"Boekhouders Diverse bedrijfsbeheeradviesbureaus",
    "sg:phone":"+32 86 45 53 56",
    "sg:postcode":"6960",
    "sg:province":"Luxembourg",
    "wof:name":"Remy Gosset",
    "wof:placetype":"venue"
},
  "geometry": {"coordinates":[5.6754698753,50.291759491],"type":"Point"}
}