{
  "type": "Feature",
  "properties": {
    "addr:full":"Groenveldstraat 18 Leuven (heverlee) Vlaams-Brabant 3001",
    "addr:housenumber":"18",
    "addr:postcode":"3001",
    "addr:street":"Groenveldstraat",
    "iso:country":"BE",
    "sg:address":"Groenveldstraat 18",
    "sg:city":"Leuven (heverlee)",
    "sg:classifiers":[
        {
            "category":"Food & Beverages",
            "subcategory":"Dairy",
            "type":"Retail Goods"
        }
    ],
    "sg:phone":"+32 16 22 69 53",
    "sg:postcode":"3001",
    "sg:province":"Vlaams-Brabant",
    "sg:tags":[
        "product",
        "-"
    ],
    "wof:name":"Sellekaerts W",
    "wof:placetype":"venue"
},
  "geometry": {"coordinates":[4.6834812164,50.8761520386],"type":"Point"}
}