{
  "type": "Feature",
  "properties": {
    "iso:country":"BE",
    "sg:address":"Rolstraat 2",
    "sg:city":"Maasmechelen (boorsem)",
    "sg:orig_category":"Non-Classified Establishments",
    "sg:phone":"+32 89 71 39 80",
    "sg:postcode":"3631",
    "sg:province":"Limburg",
    "wof:name":"Thon\u00e9 Firma",
    "wof:placetype":"venue"
},
  "geometry": {"coordinates":[5.7239232063,50.9423713684],"type":"Point"}
}