{
  "type": "Feature",
  "properties": {
    "addr:full":"Rue De L'etat 5a Oupeye (houtain-saint-sim\u00e9on) Li\u00e8ge 4682",
    "addr:housenumber":"5a",
    "addr:postcode":"4682",
    "addr:street":"Rue De L'Etat;Houtain-Saint-Sime\u0301On",
    "iso:country":"BE",
    "sg:address":"Rue De L'etat 5a",
    "sg:city":"Oupeye (houtain-saint-sim\u00e9on)",
    "sg:classifiers":[
        {
            "category":"Wholesale",
            "subcategory":"Machinery & Supplies",
            "type":"Manufacturing & Wholesale Goods"
        }
    ],
    "sg:phone":"+32 4 377 56 47",
    "sg:postcode":"4682",
    "sg:province":"Li\u00e8ge",
    "sg:tags":[
        "refrigeration",
        "-",
        "industrial",
        "commercial",
        "equipment"
    ],
    "wof:name":"Etablissements Bouwir",
    "wof:placetype":"venue"
},
  "geometry": {"coordinates":[5.612475872,50.7499542236],"type":"Point"}
}