{
  "type": "Feature",
  "properties": {
    "addr:full":"Rue De Tournai 32 Moeskroen/mouscron Hainaut 7700",
    "addr:housenumber":"32",
    "addr:postcode":"7700",
    "addr:street":"Rue De Tournai",
    "iso:country":"BE",
    "sg:address":"Rue De Tournai 32",
    "sg:city":"Moeskroen/mouscron",
    "sg:orig_category":"Agences de voyages",
    "sg:phone":"+32 56 85 41 20",
    "sg:postcode":"7700",
    "sg:province":"Hainaut",
    "wof:name":"Voyages Montaine",
    "wof:placetype":"venue"
},
  "geometry": {"coordinates":[3.2323200703,50.7400932312],"type":"Point"}
}