{
  "type": "Feature",
  "properties": {
    "addr:full":"Rue Albert Ier 3 Hannut Li\u00e8ge 4280",
    "addr:housenumber":"3",
    "addr:postcode":"4280",
    "addr:street":"Rue Albert Ier",
    "iso:country":"BE",
    "sg:address":"Rue Albert Ier 3",
    "sg:city":"Hannut",
    "sg:orig_category":"Pain, p\u00e2tisseries and confiseries",
    "sg:phone":"+32 19 51 46 39",
    "sg:postcode":"4280",
    "sg:province":"Li\u00e8ge",
    "wof:name":"P\u00c2tisserie Couque Dor\u00c9e",
    "wof:placetype":"venue"
},
  "geometry": {"coordinates":[5.0819997787,50.6706695557],"type":"Point"}
}