{
  "type": "Feature",
  "properties": {
    "addr:full":"Nieuwstraat 11 Oud-turnhout Antwerpen 2360",
    "addr:housenumber":"11",
    "addr:postcode":"2360",
    "addr:street":"Nieuwstraat",
    "iso:country":"BE",
    "sg:address":"Nieuwstraat 11",
    "sg:city":"Oud-turnhout",
    "sg:classifiers":[
        {
            "category":"Arena",
            "subcategory":"Sports Club",
            "type":"Entertainment"
        }
    ],
    "sg:phone":"+32 14 42 46 10",
    "sg:postcode":"2360",
    "sg:province":"Antwerpen",
    "sg:tags":[
        "de"
    ],
    "wof:name":"V.c. Smash Oud-turnhout",
    "wof:placetype":"venue"
},
  "geometry": {"coordinates":[4.9741549492,51.3384284973],"type":"Point"}
}