{
  "type": "Feature",
  "properties": {
    "addr:full":"Garenmarkt 3 Brugge West-Vlaanderen 8000",
    "addr:housenumber":"3",
    "addr:postcode":"8000",
    "addr:street":"Garenmarkt",
    "iso:country":"BE",
    "sg:address":"Garenmarkt 3",
    "sg:city":"Brugge",
    "sg:orig_category":"Biens d'occasion",
    "sg:phone":"+32 50 33 37 33",
    "sg:postcode":"8000",
    "sg:province":"West-Vlaanderen",
    "wof:name":"Ctr Maatschappelijk Werk",
    "wof:placetype":"venue"
},
  "geometry": {"coordinates":[3.2295389175,51.2053947449],"type":"Point"}
}