{
  "type": "Feature",
  "properties": {
    "addr:full":"Rue Vandenhoven 3 Bruxelles (woluwe-saint-lambert) Bruxelles-Capitale 1200",
    "addr:housenumber":"3",
    "addr:postcode":"1200",
    "addr:street":"Rue Vandenhoven",
    "iso:country":"BE",
    "sg:address":"Rue Vandenhoven 3",
    "sg:city":"Bruxelles (woluwe-saint-lambert)",
    "sg:classifiers":[
        {
            "category":"Retail",
            "subcategory":"Event Space",
            "type":"Services"
        }
    ],
    "sg:postcode":"1200",
    "sg:province":"Bruxelles-Capitale",
    "sg:tags":[
        "organisation"
    ],
    "wof:name":"Grey Direct",
    "wof:placetype":"venue"
},
  "geometry": {"coordinates":[4.434237957,50.8386573792],"type":"Point"}
}