{
  "type": "Feature",
  "properties": {
    "addr:full":"Place Du Chef Lieu 10 Charleroi (jumet) Hainaut 6040",
    "addr:housenumber":"10",
    "addr:postcode":"6040",
    "addr:street":"Place Du Chef Lieu",
    "iso:country":"BE",
    "sg:address":"Place Du Chef Lieu 10",
    "sg:city":"Charleroi (jumet)",
    "sg:classifiers":[
        {
            "category":"Retail",
            "subcategory":"Funeral Services",
            "type":"Services"
        }
    ],
    "sg:phone":"+32 71 35 31 63",
    "sg:postcode":"6040",
    "sg:province":"Hainaut",
    "sg:tags":[
        "director"
    ],
    "wof:name":"Charles Pompes Fun\u00e8bres",
    "wof:placetype":"venue"
},
  "geometry": {"coordinates":[4.4258680344,50.451210022],"type":"Point"}
}