{
  "type": "Feature",
  "properties": {
    "iso:country":"BE",
    "sg:address":"Dodon\u00c9estraat 82",
    "sg:city":"Ukkel/uccle",
    "sg:orig_category":"Artsen and specialisten",
    "sg:phone":"+32 2 345 28 99",
    "sg:postcode":"1180",
    "sg:province":"Bruxelles-Capitale",
    "wof:name":"Ariel De Selys Longchamps",
    "wof:placetype":"venue"
},
  "geometry": {"coordinates":[4.3626909256,50.8133964539],"type":"Point"}
}