{
  "type": "Feature",
  "properties": {
    "iso:country":"BE",
    "sg:address":"Rooien 17",
    "sg:city":"Lille",
    "sg:orig_category":"Rundveehouders Varkenskwekers",
    "sg:phone":"+32 14 55 48 16",
    "sg:postcode":"2275",
    "sg:province":"Antwerpen",
    "wof:name":"Jozef Van Ouwenhuysen",
    "wof:placetype":"venue"
},
  "geometry": {"coordinates":[4.8911042213,51.2835121155],"type":"Point"}
}