{
  "type": "Feature",
  "properties": {
    "addr:full":"Rue Stroobants 48a Bruxelles (evere) Bruxelles-Capitale 1140",
    "addr:housenumber":"48a",
    "addr:postcode":"1140",
    "addr:street":"Rue Stroobants",
    "iso:country":"BE",
    "sg:address":"Rue Stroobants 48a",
    "sg:city":"Bruxelles (evere)",
    "sg:classifiers":[
        {
            "category":"Manufacturing",
            "subcategory":"Electronics",
            "type":"Manufacturing & Wholesale Goods"
        }
    ],
    "sg:phone":"+32 2 247 99 00",
    "sg:postcode":"1140",
    "sg:province":"Bruxelles-Capitale",
    "sg:tags":[
        "component",
        "-"
    ],
    "wof:name":"Fci Belgium",
    "wof:placetype":"venue"
},
  "geometry": {"coordinates":[4.3971171379,50.8794517517],"type":"Point"}
}