{
  "type": "Feature",
  "properties": {
    "addr:full":"Busleydenlaan 1ba Brussel/bruxelles Bruxelles-Capitale 1020",
    "addr:housenumber":"1ba",
    "addr:postcode":"1020",
    "addr:street":"Busleydenlaan;/",
    "iso:country":"BE",
    "sg:address":"Busleydenlaan 1ba",
    "sg:city":"Brussel/bruxelles",
    "sg:orig_category":"Opticiens",
    "sg:phone":"+32 2 268 56 00",
    "sg:postcode":"1020",
    "sg:province":"Bruxelles-Capitale",
    "wof:name":"Optique Hetzel",
    "wof:placetype":"venue"
},
  "geometry": {"coordinates":[4.358853817,50.8971710205],"type":"Point"}
}