{
  "type": "Feature",
  "properties": {
    "addr:full":"Denderhoutembaan 173 Ninove Oost-Vlaanderen 9400",
    "addr:housenumber":"173",
    "addr:postcode":"9400",
    "iso:country":"BE",
    "sg:address":"Denderhoutembaan 173",
    "sg:city":"Ninove",
    "sg:classifiers":[
        {
            "category":"Real Estate",
            "subcategory":"Real Estate Services",
            "type":"Services"
        }
    ],
    "sg:phone":"+32 54 33 26 78",
    "sg:postcode":"9400",
    "sg:province":"Oost-Vlaanderen",
    "wof:name":"Immobiliere Te Ruysbroeck",
    "wof:placetype":"venue"
},
  "geometry": {"coordinates":[4.0212731361,50.8466453552],"type":"Point"}
}