{
  "type": "Feature",
  "properties": {
    "addr:full":"Rue Brennet 17 Fleurus Hainaut 6220",
    "addr:housenumber":"17",
    "addr:postcode":"6220",
    "addr:street":"Rue Brennet",
    "iso:country":"BE",
    "sg:address":"Rue Brennet 17",
    "sg:city":"Fleurus",
    "sg:orig_category":"Catering and organisation de f\u00eates",
    "sg:phone":"+32 71 81 77 12",
    "sg:postcode":"6220",
    "sg:province":"Hainaut",
    "wof:name":"Daniel Barbaglia",
    "wof:placetype":"venue"
},
  "geometry": {"coordinates":[4.547396183,50.4766578674],"type":"Point"}
}