{
  "type": "Feature",
  "properties": {
    "addr:full":"A. Claeys-bouuaertlaan 3 Gent Oost-Vlaanderen 9030",
    "addr:housenumber":"3",
    "addr:postcode":"9030",
    "addr:street":"Oost-Vlaanderen",
    "iso:country":"BE",
    "sg:address":"A. Claeys-bouuaertlaan 3",
    "sg:city":"Gent",
    "sg:orig_category":"Bijouteries and horlogeries",
    "sg:phone":"+32 9 330 60 68",
    "sg:postcode":"9030",
    "sg:province":"Oost-Vlaanderen",
    "wof:name":"Maxim Jewels",
    "wof:placetype":"venue"
},
  "geometry": {"coordinates":[3.6745951176,51.072933197],"type":"Point"}
}