{
  "type": "Feature",
  "properties": {
    "iso:country":"BE",
    "sg:address":"Schulensebaan 1",
    "sg:city":"Lummen",
    "sg:classifiers":[
        {
            "category":"Personal",
            "subcategory":"Beauty Salon",
            "type":"Services"
        }
    ],
    "sg:phone":"+32 13 52 19 98",
    "sg:postcode":"3560",
    "sg:province":"Limburg",
    "sg:tags":[
        "lady",
        "-",
        "hairdressing"
    ],
    "wof:name":"Hairstudio Fernanda",
    "wof:placetype":"venue"
},
  "geometry": {"coordinates":[5.1921701431,50.9846305847],"type":"Point"}
}