{
  "type": "Feature",
  "properties": {
    "addr:full":"Battelsesteenweg 455-2a Mechelen Antwerpen 2800",
    "addr:housenumber":"455-2a",
    "addr:postcode":"2800",
    "addr:street":"Battelsesteenweg",
    "iso:country":"BE",
    "sg:address":"Battelsesteenweg 455-2a",
    "sg:city":"Mechelen",
    "sg:classifiers":[
        {
            "category":"Communications",
            "type":"Services"
        }
    ],
    "sg:phone":"+32 15 28 20 62",
    "sg:postcode":"2800",
    "sg:province":"Antwerpen",
    "sg:tags":[
        "data"
    ],
    "wof:name":"Akwadraat Networks Nv",
    "wof:placetype":"venue"
},
  "geometry": {"coordinates":[4.450094223,51.0380706787],"type":"Point"}
}