{
  "type": "Feature",
  "properties": {
    "iso:country":"BE",
    "sg:address":"Tervuursesteenweg 538",
    "sg:city":"Zemst (elewijt)",
    "sg:classifiers":[
        {
            "category":"Professional",
            "subcategory":"Accounting & Tax Preparation",
            "type":"Services"
        }
    ],
    "sg:phone":"+32 15 62 31 10",
    "sg:postcode":"1982",
    "sg:province":"Vlaams-Brabant",
    "sg:tags":[
        "bookkeeper"
    ],
    "wof:name":"Van Meerbeeck L",
    "wof:placetype":"venue"
},
  "geometry": {"coordinates":[4.5041208267,50.9766960144],"type":"Point"}
}