{
  "type": "Feature",
  "properties": {
    "addr:full":"82 Rue De Letat 6460 Villers-la-tour 82",
    "addr:housenumber":"82;82",
    "addr:postcode":"6460",
    "addr:street":"Rue De Letat;Villers-La-Tour",
    "iso:country":"BE",
    "sg:address":"82",
    "sg:city":"Rue De Letat 6460 Villers-la-tour",
    "sg:classifiers":[
        {
            "category":"Building & Trades",
            "subcategory":"Construction",
            "type":"Services"
        }
    ],
    "sg:phone":"+32 60 21 12 68",
    "sg:postcode":"82",
    "sg:tags":[
        "work",
        "public"
    ],
    "wof:name":"Entreprises Delid Jules Sprl",
    "wof:placetype":"venue"
},
  "geometry": {"coordinates":[4.3157711029,50.0477104187],"type":"Point"}
}