{
  "type": "Feature",
  "properties": {
    "iso:country":"BE",
    "sg:address":"Rue Des Foxhalles 2",
    "sg:city":"Verviers",
    "sg:orig_category":"Rookartikelen",
    "sg:phone":"+32 87 33 75 27",
    "sg:postcode":"4800",
    "sg:province":"Li\u00e8ge",
    "wof:name":"Albert Faniel",
    "wof:placetype":"venue"
},
  "geometry": {"coordinates":[5.853509903,50.596950531],"type":"Point"}
}