{
  "type": "Feature",
  "properties": {
    "iso:country":"BE",
    "sg:address":"Pontonstraat 2",
    "sg:city":"Oostende",
    "sg:classifiers":[
        {
            "category":"Personal",
            "subcategory":"Beauty Salon",
            "type":"Services"
        }
    ],
    "sg:phone":"+32 59 70 84 70",
    "sg:postcode":"8400",
    "sg:province":"West-Vlaanderen",
    "wof:name":"Atelier Jean-pierre Sand",
    "wof:placetype":"venue"
},
  "geometry": {"coordinates":[2.9233849049,51.2164001465],"type":"Point"}
}