{
  "type": "Feature",
  "properties": {
    "addr:full":"Place Marcel Degauquier 13 Lens (montignies-lez-lens) Hainaut 7870",
    "addr:housenumber":"13",
    "addr:postcode":"7870",
    "addr:street":"Place Marcel Degauquier",
    "iso:country":"BE",
    "sg:address":"Place Marcel Degauquier 13",
    "sg:city":"Lens (montignies-lez-lens)",
    "sg:classifiers":[
        {
            "category":"Home & Garden",
            "subcategory":"Garden Supply",
            "type":"Retail Goods"
        }
    ],
    "sg:phone":"+32 65 22 50 26",
    "sg:postcode":"7870",
    "sg:province":"Hainaut",
    "sg:tags":[
        "machine",
        "agricultural",
        "-"
    ],
    "wof:name":"Permanne A",
    "wof:placetype":"venue"
},
  "geometry": {"coordinates":[3.943762064,50.5644035339],"type":"Point"}
}