{
  "type": "Feature",
  "properties": {
    "addr:full":"Ankerstraat 2b4 Sint-niklaas Oost-Vlaanderen 9100",
    "addr:housenumber":"2b4",
    "addr:postcode":"9100",
    "addr:street":"Ankerstraat",
    "iso:country":"BE",
    "sg:address":"Ankerstraat 2b4",
    "sg:city":"Sint-niklaas",
    "sg:orig_category":"Jeux de hasard",
    "sg:phone":"+32 3 765 06 84",
    "sg:postcode":"9100",
    "sg:province":"Oost-Vlaanderen",
    "wof:name":"Circus Leisure",
    "wof:placetype":"venue"
},
  "geometry": {"coordinates":[4.1432499886,51.1653442383],"type":"Point"}
}