{
  "type": "Feature",
  "properties": {
    "iso:country":"BE",
    "sg:address":"Knaptandstraat 101w",
    "sg:city":"Lokeren",
    "sg:classifiers":[
        {
            "category":"Health Services",
            "subcategory":"Dentist",
            "type":"Services"
        }
    ],
    "sg:phone":"+32 9 348 35 99",
    "sg:postcode":"9160",
    "sg:province":"Oost-Vlaanderen",
    "wof:name":"Lamberechts E",
    "wof:placetype":"venue"
},
  "geometry": {"coordinates":[3.9845499992,51.1002311707],"type":"Point"}
}