{
  "type": "Feature",
  "properties": {
    "iso:country":"BE",
    "sg:address":"Mathieu De Layensplein 9",
    "sg:city":"Leuven",
    "sg:classifiers":[
        {
            "category":"Restaurant",
            "type":"Food & Drink"
        }
    ],
    "sg:phone":"+32 16 22 04 36",
    "sg:postcode":"3000",
    "sg:province":"Vlaams-Brabant",
    "sg:tags":[
        "caf\u00e9s"
    ],
    "wof:name":"Taverne Rodin's",
    "wof:placetype":"venue"
},
  "geometry": {"coordinates":[4.7004489899,50.8800239563],"type":"Point"}
}