{
  "type": "Feature",
  "properties": {
    "iso:country":"BE",
    "sg:address":"Parklaan 1",
    "sg:city":"Willebroek",
    "sg:orig_category":"Sportclubs",
    "sg:phone":"+32 3 886 74 97",
    "sg:postcode":"2830",
    "sg:province":"Antwerpen",
    "wof:name":"T.c. Willebroek",
    "wof:placetype":"venue"
},
  "geometry": {"coordinates":[4.3544039726,51.0547447205],"type":"Point"}
}