{
  "type": "Feature",
  "properties": {
    "addr:full":"Sint-elooiswinkelstraat 124 Roeselare West-Vlaanderen 8800",
    "addr:housenumber":"124",
    "addr:postcode":"8800",
    "iso:country":"BE",
    "sg:address":"Sint-elooiswinkelstraat 124",
    "sg:city":"Roeselare",
    "sg:orig_category":"Entretien and r\u00e9parations de voitures",
    "sg:phone":"+32 51 21 05 94",
    "sg:postcode":"8800",
    "sg:province":"West-Vlaanderen",
    "wof:name":"Carrosserie Caen",
    "wof:placetype":"venue"
},
  "geometry": {"coordinates":[3.1613609791,50.9001846313],"type":"Point"}
}