{
  "type": "Feature",
  "properties": {
    "addr:full":"Avenue Des Volontaires 199 Sint-pieters-woluwe/woluwe-saint-pierre Bruxelles-Capitale 1150",
    "addr:housenumber":"199",
    "addr:postcode":"1150",
    "addr:street":"Avenue Des Volontaires;/",
    "iso:country":"BE",
    "sg:address":"Avenue Des Volontaires 199",
    "sg:city":"Sint-pieters-woluwe/woluwe-saint-pierre",
    "sg:orig_category":"Pain, p\u00e2tisseries and confiseries",
    "sg:phone":"+32 2 736 51 21",
    "sg:postcode":"1150",
    "sg:province":"Bruxelles-Capitale",
    "wof:name":"Boulangerie Lybaert J.p.",
    "wof:placetype":"venue"
},
  "geometry": {"coordinates":[4.4071521759,50.8281593323],"type":"Point"}
}