{
  "type": "Feature",
  "properties": {
    "addr:full":"Ninoofsesteenweg 370 Dilbeek Vlaams-Brabant 1700",
    "addr:housenumber":"370",
    "addr:postcode":"1700",
    "addr:street":"Ninoofsesteenweg",
    "iso:country":"BE",
    "sg:address":"Ninoofsesteenweg 370",
    "sg:city":"Dilbeek",
    "sg:classifiers":[
        {
            "category":"Deli",
            "type":"Food & Drink"
        }
    ],
    "sg:phone":"+32 3 366 55 00",
    "sg:postcode":"1700",
    "sg:province":"Vlaams-Brabant",
    "sg:tags":[
        "delicatessen"
    ],
    "wof:name":"Dima Nv",
    "wof:placetype":"venue"
},
  "geometry": {"coordinates":[4.4613208771,51.2090301514],"type":"Point"}
}