{
  "type": "Feature",
  "properties": {
    "addr:full":"Rue Des Dames 26 Fleurus (wanferc\u00e9e-baulet) Hainaut 6224",
    "addr:housenumber":"26",
    "addr:postcode":"6224",
    "addr:street":"Rue Des Dames",
    "iso:country":"BE",
    "sg:address":"Rue Des Dames 26",
    "sg:city":"Fleurus (wanferc\u00e9e-baulet)",
    "sg:classifiers":[
        {
            "category":"Wholesale",
            "subcategory":"Machinery & Supplies",
            "type":"Manufacturing & Wholesale Goods"
        }
    ],
    "sg:phone":"+32 71 81 30 44",
    "sg:postcode":"6224",
    "sg:province":"Hainaut",
    "sg:tags":[
        "refrigeration",
        "-",
        "industrial",
        "commercial",
        "equipment"
    ],
    "wof:name":"Ernoud J-m",
    "wof:placetype":"venue"
},
  "geometry": {"coordinates":[4.5871281624,50.4671173096],"type":"Point"}
}