{
  "type": "Feature",
  "properties": {
    "iso:country":"BE",
    "sg:address":"Ternatsestraat 154",
    "sg:city":"Affligem",
    "sg:orig_category":"Installation \u00e9lectrique r\u00e9sidentielle",
    "sg:phone":"+32 2 582 08 05",
    "sg:postcode":"1790",
    "sg:province":"Vlaams-Brabant",
    "wof:name":"Johan Van Cauter",
    "wof:placetype":"venue"
},
  "geometry": {"coordinates":[4.1408791542,50.8945770264],"type":"Point"}
}