{
  "type": "Feature",
  "properties": {
    "addr:full":"Rue De L'autonomie 1 Anderlecht Bruxelles-Capitale 1070",
    "addr:housenumber":"1",
    "addr:postcode":"1070",
    "addr:street":"Rue De L'Autonomie",
    "iso:country":"BE",
    "sg:address":"Rue De L'autonomie 1",
    "sg:city":"Anderlecht",
    "sg:orig_category":"Ordinateurs and \u00e9quipement informatique",
    "sg:phone":"+32 2 523 56 61",
    "sg:postcode":"1070",
    "sg:province":"Bruxelles-Capitale",
    "wof:name":"Unipress Europe",
    "wof:placetype":"venue"
},
  "geometry": {"coordinates":[4.3385958672,50.8406944275],"type":"Point"}
}