{
  "type": "Feature",
  "properties": {
    "addr:full":"Route D\u00b4ath 261 Mons Hainaut 7020",
    "addr:housenumber":"261",
    "addr:postcode":"7020",
    "addr:street":"Route D\u00b4Ath;Hainaut",
    "iso:country":"BE",
    "sg:address":"Route D\u00b4ath 261",
    "sg:city":"Mons",
    "sg:orig_category":"Pain, p\u00e2tisseries and confiseries",
    "sg:phone":"+32 65 84 05 03",
    "sg:postcode":"7020",
    "sg:province":"Hainaut",
    "wof:name":"Ludovicus",
    "wof:placetype":"venue"
},
  "geometry": {"coordinates":[3.9553449154,50.4761772156],"type":"Point"}
}