{
  "type": "Feature",
  "properties": {
    "addr:full":"Kleistraat 173 Aartselaar Antwerpen 2630",
    "addr:housenumber":"173",
    "addr:postcode":"2630",
    "addr:street":"Kleistraat",
    "iso:country":"BE",
    "sg:address":"Kleistraat 173",
    "sg:city":"Aartselaar",
    "sg:orig_category":"Woningbouw",
    "sg:phone":"+32 3 887 71 77",
    "sg:postcode":"2630",
    "sg:province":"Antwerpen",
    "wof:name":"Willy De Clercq",
    "wof:placetype":"venue"
},
  "geometry": {"coordinates":[4.4018139839,51.1341629028],"type":"Point"}
}