{
  "type": "Feature",
  "properties": {
    "addr:full":"Kalve 34 Wachtebeke Oost-Vlaanderen 9185",
    "addr:housenumber":"34",
    "addr:postcode":"9185",
    "addr:street":"Kalve",
    "iso:country":"BE",
    "sg:address":"Kalve 34",
    "sg:city":"Wachtebeke",
    "sg:orig_category":"Dierentuinen, botanische tuinen, sterrenwachten and natuurreservaten",
    "sg:phone":"+32 9 345 91 18",
    "sg:postcode":"9185",
    "sg:province":"Oost-Vlaanderen",
    "wof:name":"Heidebos",
    "wof:placetype":"venue"
},
  "geometry": {"coordinates":[3.8770051003,51.1719398499],"type":"Point"}
}