{
  "type": "Feature",
  "properties": {
    "addr:full":"Velodroomstraat 127 Boom Antwerpen 2850",
    "addr:housenumber":"127",
    "addr:postcode":"2850",
    "addr:street":"Velodroomstraat",
    "iso:country":"BE",
    "sg:address":"Velodroomstraat 127",
    "sg:city":"Boom",
    "sg:classifiers":[
        {
            "category":"Home & Garden",
            "subcategory":"Carpets & Floor Coverings",
            "type":"Retail Goods"
        }
    ],
    "sg:phone":"+32 3 888 08 82",
    "sg:postcode":"2850",
    "sg:province":"Antwerpen",
    "sg:tags":[
        "tile"
    ],
    "wof:name":"Linotap Bvba",
    "wof:placetype":"venue"
},
  "geometry": {"coordinates":[4.3725419044,51.0946617126],"type":"Point"}
}