{
  "type": "Feature",
  "properties": {
    "iso:country":"BE",
    "sg:address":"Rue De Gramptinne 71",
    "sg:city":"Andenne",
    "sg:classifiers":[
        {
            "category":"Restaurant",
            "type":"Food & Drink"
        }
    ],
    "sg:phone":"+32 81 58 96 67",
    "sg:postcode":"5300",
    "sg:province":"Namur",
    "wof:name":"Le Refuge",
    "wof:placetype":"venue"
},
  "geometry": {"coordinates":[5.0003929138,50.4642105103],"type":"Point"}
}