{
  "type": "Feature",
  "properties": {
    "iso:country":"BE",
    "sg:address":"Schaarbeeklei 322",
    "sg:city":"Vilvoorde",
    "sg:orig_category":"Enseignement maternel and primaire",
    "sg:phone":"+32 2 251 27 33",
    "sg:postcode":"1800",
    "sg:province":"Vlaams-Brabant",
    "wof:name":"School",
    "wof:placetype":"venue"
},
  "geometry": {"coordinates":[4.4219660759,50.9162521362],"type":"Point"}
}