{
  "type": "Feature",
  "properties": {
    "addr:full":"Grote Baan 26 Haacht (groot) Vlaams-Brabant 3150",
    "addr:housenumber":"26",
    "addr:postcode":"3150",
    "addr:street":"Grote Baan;Groot Vlaams-Brabant",
    "iso:country":"BE",
    "sg:address":"Grote Baan 26",
    "sg:city":"Haacht (groot)",
    "sg:classifiers":[
        {
            "category":"Cafe",
            "type":"Food & Drink"
        }
    ],
    "sg:phone":"+32 16 60 95 14",
    "sg:postcode":"3150",
    "sg:province":"Vlaams-Brabant",
    "sg:tags":[
        "caf\u00e9s"
    ],
    "wof:name":"Jan Primus",
    "wof:placetype":"venue"
},
  "geometry": {"coordinates":[4.6350221634,50.9589729309],"type":"Point"}
}