{
  "type": "Feature",
  "properties": {
    "iso:country":"BE",
    "sg:address":"Rue Du Culot 6",
    "sg:city":"Gembloux-sur-orneau (gembloux)",
    "sg:classifiers":[
        {
            "category":"Shopping",
            "subcategory":"Florist",
            "type":"Retail Goods"
        }
    ],
    "sg:phone":"+32 81 61 37 29",
    "sg:postcode":"5030",
    "sg:province":"Namur",
    "wof:name":"Maure",
    "wof:placetype":"venue"
},
  "geometry": {"coordinates":[4.7232708931,50.589012146],"type":"Point"}
}