{
  "type": "Feature",
  "properties": {
    "iso:country":"BE",
    "sg:address":"Hofstraat 81",
    "sg:city":"Tessenderlo",
    "sg:classifiers":[
        {
            "category":"Structure",
            "subcategory":"Office Building",
            "type":"Public Place"
        }
    ],
    "sg:phone":"+32 13 67 52 27",
    "sg:postcode":"3980",
    "sg:province":"Limburg",
    "sg:tags":[
        "drawing"
    ],
    "wof:name":"Blomme L",
    "wof:placetype":"venue"
},
  "geometry": {"coordinates":[5.1239209175,51.0663146973],"type":"Point"}
}