{
  "type": "Feature",
  "properties": {
    "iso:country":"BE",
    "sg:address":"Zolderseweg 2",
    "sg:city":"Heusden-zolder",
    "sg:orig_category":"Bruids- and ceremoniekledij",
    "sg:phone":"+32 11 57 20 44",
    "sg:postcode":"3550",
    "sg:province":"Limburg",
    "wof:name":"De Wederik",
    "wof:placetype":"venue"
},
  "geometry": {"coordinates":[5.2990779877,51.0357627869],"type":"Point"}
}