{
  "type": "Feature",
  "properties": {
    "iso:country":"BE",
    "sg:address":"Zoning Industriel",
    "sg:city":"Couvin (mariembourg)",
    "sg:orig_category":"Non-Classified Establishments",
    "sg:phone":"+32 60 31 16 29",
    "sg:postcode":"5660",
    "sg:province":"Namur",
    "wof:name":"Vos Jp",
    "wof:placetype":"venue"
},
  "geometry": {"coordinates":[4.4955449104,50.1001853943],"type":"Point"}
}