{
  "type": "Feature",
  "properties": {
    "addr:full":"Rue Des Alli\u00c9s 41 Nassogne Luxembourg 6953",
    "addr:housenumber":"41",
    "addr:postcode":"6953",
    "addr:street":"Rue Des Allie\u0301S",
    "iso:country":"BE",
    "sg:address":"Rue Des Alli\u00c9s 41",
    "sg:city":"Nassogne",
    "sg:orig_category":"Enseignement maternel and primaire",
    "sg:phone":"+32 84 21 47 09",
    "sg:postcode":"6953",
    "sg:province":"Luxembourg",
    "wof:name":"Ecole Prim. Communale",
    "wof:placetype":"venue"
},
  "geometry": {"coordinates":[5.2800159454,50.1337661743],"type":"Point"}
}