{
  "type": "Feature",
  "properties": {
    "addr:full":"Avenue Franklin Roosevelt 73 Bruxelles (ixelles) Bruxelles-Capitale 1050",
    "addr:housenumber":"73",
    "addr:postcode":"1050",
    "addr:street":"Avenue Franklin Roosevelt",
    "iso:country":"BE",
    "sg:address":"Avenue Franklin Roosevelt 73",
    "sg:city":"Bruxelles (ixelles)",
    "sg:classifiers":[
        {
            "category":"Government",
            "subcategory":"Embassy",
            "type":"Public Place"
        }
    ],
    "sg:phone":"+32 2 640 60 00",
    "sg:postcode":"1050",
    "sg:province":"Bruxelles-Capitale",
    "sg:tags":[
        "consulate"
    ],
    "wof:name":"Emirats Arabes Unis",
    "wof:placetype":"venue"
},
  "geometry": {"coordinates":[4.3852472305,50.806476593],"type":"Point"}
}