{
  "type": "Feature",
  "properties": {
    "iso:country":"BE",
    "sg:address":"Emelgemsplein 1",
    "sg:city":"Izegem",
    "sg:orig_category":"Rijscholen",
    "sg:phone":"+32 51 20 09 48",
    "sg:postcode":"8870",
    "sg:province":"West-Vlaanderen",
    "wof:name":"Autorijschool Lust",
    "wof:placetype":"venue"
},
  "geometry": {"coordinates":[3.2290680408,50.9174575806],"type":"Point"}
}