{
  "type": "Feature",
  "properties": {
    "addr:full":"Louizastraat 39 Antwerpen Antwerpen 2000",
    "addr:housenumber":"39",
    "addr:postcode":"2000",
    "addr:street":"Louizastraat",
    "iso:country":"BE",
    "sg:address":"Louizastraat 39",
    "sg:city":"Antwerpen",
    "sg:orig_category":"Notaires",
    "sg:phone":"+32 3 232 45 25",
    "sg:postcode":"2000",
    "sg:province":"Antwerpen",
    "wof:name":"P. Van Meerbeeck",
    "wof:placetype":"venue"
},
  "geometry": {"coordinates":[4.4053602219,51.2104873657],"type":"Point"}
}