{
  "type": "Feature",
  "properties": {
    "iso:country":"BE",
    "sg:address":"Sportveldstraat 8",
    "sg:city":"Oud-turnhout",
    "sg:classifiers":[
        {
            "category":"Professional",
            "subcategory":"Computer Services",
            "type":"Services"
        }
    ],
    "sg:phone":"+32 14 42 72 20",
    "sg:postcode":"2360",
    "sg:province":"Antwerpen",
    "sg:tags":[
        "webdesign",
        "-",
        "internet"
    ],
    "wof:name":"Succes Net",
    "wof:placetype":"venue"
},
  "geometry": {"coordinates":[4.9883699417,51.3204879761],"type":"Point"}
}