{
  "type": "Feature",
  "properties": {
    "addr:full":"Place Du Perron 39 Theux Li\u00e8ge 4910",
    "addr:housenumber":"39",
    "addr:postcode":"4910",
    "addr:street":"Place Du Perron",
    "iso:country":"BE",
    "sg:address":"Place Du Perron 39",
    "sg:city":"Theux",
    "sg:classifiers":[
        {
            "category":"Shopping",
            "subcategory":"Books",
            "type":"Retail Goods"
        }
    ],
    "sg:phone":"+32 87 54 15 89",
    "sg:postcode":"4910",
    "sg:province":"Li\u00e8ge",
    "sg:tags":[
        "bookseller"
    ],
    "wof:name":"Librairie Du Perron",
    "wof:placetype":"venue"
},
  "geometry": {"coordinates":[5.8130698204,50.5348701477],"type":"Point"}
}