{
  "type": "Feature",
  "properties": {
    "iso:country":"BE",
    "sg:address":"Heurbeek 22",
    "sg:city":"Lubbeek",
    "sg:orig_category":"Producteurs de fruits",
    "sg:phone":"+32 16 63 56 52",
    "sg:postcode":"3210",
    "sg:province":"Vlaams-Brabant",
    "wof:name":"Philippe Paeyeneers",
    "wof:placetype":"venue"
},
  "geometry": {"coordinates":[4.858230114,50.874004364],"type":"Point"}
}