{
  "type": "Feature",
  "properties": {
    "addr:full":"Nieuwpoortsesteenweg 194 Oostende West-Vlaanderen 8400",
    "addr:housenumber":"194",
    "addr:postcode":"8400",
    "addr:street":"Nieuwpoortsesteenweg",
    "iso:country":"BE",
    "sg:address":"Nieuwpoortsesteenweg 194",
    "sg:city":"Oostende",
    "sg:orig_category":"Banken and kredietinstellingen",
    "sg:phone":"+32 59 70 73 02",
    "sg:postcode":"8400",
    "sg:province":"West-Vlaanderen",
    "wof:name":"Bbl",
    "wof:placetype":"venue"
},
  "geometry": {"coordinates":[2.9008779526,51.2208213806],"type":"Point"}
}