{
  "type": "Feature",
  "properties": {
    "addr:full":"Hostraat 61b5d Waregem West-Vlaanderen 8790",
    "addr:postcode":"8790",
    "addr:street":"Hostraat",
    "iso:country":"BE",
    "sg:address":"Hostraat 61b5d",
    "sg:city":"Waregem",
    "sg:orig_category":"Onderdelen and accessoires voertuigen Gh",
    "sg:phone":"+32 56 60 37 90",
    "sg:postcode":"8790",
    "sg:province":"West-Vlaanderen",
    "wof:name":"Bertec",
    "wof:placetype":"venue"
},
  "geometry": {"coordinates":[3.4370639324,50.8843345642],"type":"Point"}
}