{
  "type": "Feature",
  "properties": {
    "iso:country":"BE",
    "sg:address":"Rue Des Combattants 11-5",
    "sg:city":"Waremme",
    "sg:classifiers":[
        {
            "category":"Professional",
            "subcategory":"Detective & Security Services",
            "type":"Services"
        }
    ],
    "sg:phone":"+32 19 32 80 00",
    "sg:postcode":"4300",
    "sg:province":"Li\u00e8ge",
    "sg:tags":[
        "consultant"
    ],
    "wof:name":"Atv Securite Sprl",
    "wof:placetype":"venue"
},
  "geometry": {"coordinates":[5.2487897873,50.6954154968],"type":"Point"}
}