{
  "type": "Feature",
  "properties": {
    "addr:full":"Rue De La Navinne 201 Namen Namur 5020",
    "addr:housenumber":"201",
    "addr:postcode":"5020",
    "addr:street":"Rue De La Navinne",
    "iso:country":"BE",
    "sg:address":"Rue De La Navinne 201",
    "sg:city":"Namen",
    "sg:classifiers":[
        {
            "category":"Arena",
            "subcategory":"Sports Club",
            "type":"Entertainment"
        }
    ],
    "sg:phone":"+32 81 44 61 29",
    "sg:postcode":"5020",
    "sg:province":"Namur",
    "sg:tags":[
        "de"
    ],
    "wof:name":"Myriam Alexandre",
    "wof:placetype":"venue"
},
  "geometry": {"coordinates":[4.7952418327,50.4352035522],"type":"Point"}
}