{
  "type": "Feature",
  "properties": {
    "addr:full":"Stijn Streuvelslaan 1 Oostende West-Vlaanderen 8400",
    "addr:housenumber":"1",
    "addr:postcode":"8400",
    "addr:street":"Stijn Streuvelslaan",
    "iso:country":"BE",
    "sg:address":"Stijn Streuvelslaan 1",
    "sg:city":"Oostende",
    "sg:orig_category":"Artsen and specialisten",
    "sg:phone":"+32 59 70 73 15",
    "sg:postcode":"8400",
    "sg:province":"West-Vlaanderen",
    "wof:name":"Roger Claeys",
    "wof:placetype":"venue"
},
  "geometry": {"coordinates":[2.9164569378,51.2180480957],"type":"Point"}
}