{
  "type": "Feature",
  "properties": {
    "addr:full":"Chauss\u00c9e De Charleroi 67 Lasne Brabant Wallon 1380",
    "addr:housenumber":"67",
    "addr:postcode":"1380",
    "addr:street":"Chausse\u0301E De Charleroi",
    "iso:country":"BE",
    "sg:address":"Chauss\u00c9e De Charleroi 67",
    "sg:city":"Lasne",
    "sg:orig_category":"Eleveurs de bovins",
    "sg:phone":"+32 2 384 23 09",
    "sg:postcode":"1380",
    "sg:province":"Brabant Wallon",
    "wof:name":"Jeanne Ransquin",
    "wof:placetype":"venue"
},
  "geometry": {"coordinates":[4.415345192,50.6520004272],"type":"Point"}
}