{
  "type": "Feature",
  "properties": {
    "iso:country":"BE",
    "sg:address":"Warandestraat 66-68",
    "sg:city":"Turnhout",
    "sg:classifiers":[
        {
            "category":"Social Services",
            "subcategory":"Child Care",
            "type":"Services"
        }
    ],
    "sg:phone":"+32 14 41 30 56",
    "sg:postcode":"2300",
    "sg:province":"Antwerpen",
    "sg:tags":[
        "boy",
        "scout",
        "equipment"
    ],
    "wof:name":"Andantino",
    "wof:placetype":"venue"
},
  "geometry": {"coordinates":[4.9415597916,51.3242835999],"type":"Point"}
}