{
  "type": "Feature",
  "properties": {
    "addr:full":"Mageret 103 Bastogne (wardin) Luxembourg 6600",
    "addr:housenumber":"103",
    "addr:postcode":"6600",
    "addr:street":"Mageret",
    "iso:country":"BE",
    "sg:address":"Mageret 103",
    "sg:city":"Bastogne (wardin)",
    "sg:classifiers":[
        {
            "category":"Building & Trades",
            "subcategory":"Landscaping Services",
            "type":"Services"
        }
    ],
    "sg:phone":"+32 61 21 21 48",
    "sg:postcode":"6600",
    "sg:province":"Luxembourg",
    "sg:tags":[
        "forestry"
    ],
    "wof:name":"Detaille J",
    "wof:placetype":"venue"
},
  "geometry": {"coordinates":[5.7148199081,50.0007820129],"type":"Point"}
}