{
  "type": "Feature",
  "properties": {
    "addr:full":"Rue Grange Des Champs 68 Braine L'alleud (braine-l'alleud) Brabant Wallon 1420",
    "addr:housenumber":"68",
    "addr:postcode":"1420",
    "addr:street":"Rue Grange Des Champs",
    "iso:country":"BE",
    "sg:address":"Rue Grange Des Champs 68",
    "sg:city":"Braine L'alleud (braine-l'alleud)",
    "sg:classifiers":[
        {
            "category":"Building & Trades",
            "subcategory":"Pest Control",
            "type":"Services"
        }
    ],
    "sg:phone":"+32 475 73 88 46",
    "sg:postcode":"1420",
    "sg:province":"Brabant Wallon",
    "sg:tags":[
        "painting",
        "contractor"
    ],
    "wof:name":"Fior Luigi",
    "wof:placetype":"venue"
},
  "geometry": {"coordinates":[-0.8630650043,47.4144668579],"type":"Point"}
}