{
  "type": "Feature",
  "properties": {
    "iso:country":"BE",
    "sg:address":"Mitswegestraat 26",
    "sg:city":"Ichtegem",
    "sg:orig_category":"Installation de menuiserie en bois and plastique",
    "sg:phone":"+32 59 29 05 62",
    "sg:postcode":"8480",
    "sg:province":"West-Vlaanderen",
    "wof:name":"Atelier Duriez",
    "wof:placetype":"venue"
},
  "geometry": {"coordinates":[3.0440759659,51.1103515625],"type":"Point"}
}