{
  "type": "Feature",
  "properties": {
    "addr:full":"Avenue Wanderpepen 50 Binche Hainaut 7130",
    "addr:housenumber":"50",
    "addr:postcode":"7130",
    "addr:street":"Avenue Wanderpepen",
    "iso:country":"BE",
    "sg:address":"Avenue Wanderpepen 50",
    "sg:city":"Binche",
    "sg:orig_category":"DIVERSE RECREATIEVE ACTIVITEITEN",
    "sg:phone":"+32 64 33 60 95",
    "sg:postcode":"7130",
    "sg:province":"Hainaut",
    "wof:name":"Cercle D'echecs Binchois",
    "wof:placetype":"venue"
},
  "geometry": {"coordinates":[4.1702971458,50.4121055603],"type":"Point"}
}