{
  "type": "Feature",
  "properties": {
    "iso:country":"BE",
    "sg:address":"Bieststraat 20",
    "sg:city":"Grimbergen",
    "sg:orig_category":"Imprimeries and copyshops",
    "sg:phone":"+32 2 270 53 01",
    "sg:postcode":"1850",
    "sg:province":"Vlaams-Brabant",
    "wof:name":"Al Kopie",
    "wof:placetype":"venue"
},
  "geometry": {"coordinates":[4.3558158875,50.9367256165],"type":"Point"}
}