{
  "type": "Feature",
  "properties": {
    "addr:full":"Ringlaan 34 Kuurne West-Vlaanderen 8520",
    "addr:housenumber":"34",
    "addr:postcode":"8520",
    "addr:street":"Ringlaan",
    "iso:country":"BE",
    "sg:address":"Ringlaan 34",
    "sg:city":"Kuurne",
    "sg:orig_category":"R\u00e9parations d'horloges, montres and bijoux. Bijoux Fab. Souvenirs and objets artisanaux. Bijouteries",
    "sg:phone":"+32 56 57 07 26",
    "sg:postcode":"8520",
    "sg:province":"West-Vlaanderen",
    "wof:name":"Venizi",
    "wof:placetype":"venue"
},
  "geometry": {"coordinates":[3.2814209461,50.8413085938],"type":"Point"}
}