{
  "type": "Feature",
  "properties": {
    "iso:country":"BE",
    "sg:address":"Rue Constant Legr\u00e8ve 27",
    "sg:city":"Wavre (limal)",
    "sg:classifiers":[
        {
            "category":"Professional",
            "subcategory":"Business Services",
            "type":"Services"
        }
    ],
    "sg:phone":"+32 10 41 66 44",
    "sg:postcode":"1300",
    "sg:province":"Brabant Wallon",
    "sg:tags":[
        "automobile",
        "-",
        "assessor"
    ],
    "wof:name":"Mazy Pierre",
    "wof:placetype":"venue"
},
  "geometry": {"coordinates":[4.61124897,50.7159996033],"type":"Point"}
}