{
  "type": "Feature",
  "properties": {
    "iso:country":"BE",
    "sg:address":"Place Reine Astrid 1",
    "sg:city":"Tournai",
    "sg:classifiers":[
        {
            "category":"Health Services",
            "subcategory":"Health Practitioner",
            "type":"Services"
        }
    ],
    "sg:phone":"+32 69 84 58 18",
    "sg:postcode":"7500",
    "sg:province":"Hainaut",
    "sg:tags":[
        "osteopath"
    ],
    "wof:name":"Pieron A",
    "wof:placetype":"venue"
},
  "geometry": {"coordinates":[3.3881399632,50.6048316956],"type":"Point"}
}