{
  "type": "Feature",
  "properties": {
    "iso:country":"BE",
    "sg:address":"Landmeterstraat 2",
    "sg:city":"Sint-jans-molenbeek/molenbeek-saint-jean",
    "sg:orig_category":"Herstelling aan huis van huishoudartikelen Herstelling leer and schoeisel Herstellingswinkels voor d",
    "sg:phone":"+32 2 414 31 74",
    "sg:postcode":"1080",
    "sg:province":"Bruxelles-Capitale",
    "wof:name":"Cordonnerie Philippe",
    "wof:placetype":"venue"
},
  "geometry": {"coordinates":[4.3111548424,50.8524246216],"type":"Point"}
}