{
  "type": "Feature",
  "properties": {
    "addr:full":"Rue Auguste Lambiotte 138 Bruxelles (schaerbeek) Bruxelles-Capitale 1030",
    "addr:housenumber":"138",
    "addr:postcode":"1030",
    "addr:street":"Rue Auguste Lambiotte",
    "iso:country":"BE",
    "sg:address":"Rue Auguste Lambiotte 138",
    "sg:city":"Bruxelles (schaerbeek)",
    "sg:classifiers":[
        {
            "category":"Retail",
            "subcategory":"Auto Repair",
            "type":"Services"
        }
    ],
    "sg:phone":"+32 2 734 66 17",
    "sg:postcode":"1030",
    "sg:province":"Bruxelles-Capitale",
    "sg:tags":[
        "garage"
    ],
    "wof:name":"Cobalt 45 Sa",
    "wof:placetype":"venue"
},
  "geometry": {"coordinates":[4.3907198906,50.8538017273],"type":"Point"}
}