{
  "type": "Feature",
  "properties": {
    "iso:country":"BE",
    "sg:address":"Pottestraat 16",
    "sg:city":"Poperinge",
    "sg:classifiers":[
        {
            "category":"Professional",
            "subcategory":"Accounting & Tax Preparation",
            "type":"Services"
        }
    ],
    "sg:phone":"+32 57 33 46 09",
    "sg:postcode":"8970",
    "sg:province":"West-Vlaanderen",
    "sg:tags":[
        "accountant"
    ],
    "wof:name":"Dejonckheere M",
    "wof:placetype":"venue"
},
  "geometry": {"coordinates":[2.7224628925,50.8562736511],"type":"Point"}
}