{
  "type": "Feature",
  "properties": {
    "addr:full":"Rue Montgom\u00c9ry 23 Edingen/enghien Hainaut 7850",
    "addr:housenumber":"23",
    "addr:postcode":"7850",
    "addr:street":"Rue Montgome\u0301Ry",
    "iso:country":"BE",
    "sg:address":"Rue Montgom\u00c9ry 23",
    "sg:city":"Edingen/enghien",
    "sg:orig_category":"Poissonniers and \u00e9caillers",
    "sg:phone":"+32 2 395 37 13",
    "sg:postcode":"7850",
    "sg:province":"Hainaut",
    "wof:name":"Aux Douceurs Marines",
    "wof:placetype":"venue"
},
  "geometry": {"coordinates":[4.0374598503,50.69323349],"type":"Point"}
}