{
  "type": "Feature",
  "properties": {
    "addr:full":"Maloulaan 36 Ieper West-Vlaanderen 8900",
    "addr:housenumber":"36",
    "addr:postcode":"8900",
    "addr:street":"Maloulaan",
    "iso:country":"BE",
    "sg:address":"Maloulaan 36",
    "sg:city":"Ieper",
    "sg:classifiers":[
        {
            "category":"Professional",
            "subcategory":"Art Services",
            "type":"Services"
        }
    ],
    "sg:phone":"+32 57 21 25 12",
    "sg:postcode":"8900",
    "sg:province":"West-Vlaanderen",
    "sg:tags":[
        "interior",
        "designer"
    ],
    "wof:name":"Corne B",
    "wof:placetype":"venue"
},
  "geometry": {"coordinates":[2.8766479492,50.8510513306],"type":"Point"}
}