{
  "type": "Feature",
  "properties": {
    "iso:country":"BE",
    "sg:address":"Rue De La Gare 36",
    "sg:city":"Bertrix",
    "sg:classifiers":[
        {
            "category":"Banks & Credit Unions",
            "subcategory":"Bank",
            "type":"Services"
        }
    ],
    "sg:phone":"+32 61 41 33 92",
    "sg:postcode":"6800",
    "sg:province":"Luxembourg",
    "wof:name":"Alcredima-bce Nv",
    "wof:placetype":"venue"
},
  "geometry": {"coordinates":[5.2562689781,49.8548355103],"type":"Point"}
}