{
  "type": "Feature",
  "properties": {
    "addr:full":"Heultjedorp 7 Westerlo Antwerpen 2260",
    "addr:housenumber":"7",
    "addr:postcode":"2260",
    "addr:street":"Heultjedorp",
    "iso:country":"BE",
    "sg:address":"Heultjedorp 7",
    "sg:city":"Westerlo",
    "sg:orig_category":"Epiceries. Journaux",
    "sg:phone":"+32 16 69 95 10",
    "sg:postcode":"2260",
    "sg:province":"Antwerpen",
    "wof:name":"Huis Biesemans",
    "wof:placetype":"venue"
},
  "geometry": {"coordinates":[4.9112768173,51.0883636475],"type":"Point"}
}