{
  "type": "Feature",
  "properties": {
    "iso:country":"BE",
    "sg:address":"Monthouet 30",
    "sg:city":"Stoumont",
    "sg:classifiers":[
        {
            "category":"Building & Trades",
            "subcategory":"Landscaping Services",
            "type":"Services"
        }
    ],
    "sg:phone":"+32 80 78 52 00",
    "sg:postcode":"4987",
    "sg:province":"Li\u00e8ge",
    "sg:tags":[
        "gardening",
        "garden",
        "maintenance"
    ],
    "wof:name":"Sur Champ De Ria Scrl",
    "wof:placetype":"venue"
},
  "geometry": {"coordinates":[5.8138952255,50.4203224182],"type":"Point"}
}