{
  "type": "Feature",
  "properties": {
    "addr:full":"Stationsstraat 115 Waasmunster Oost-Vlaanderen 9250",
    "addr:housenumber":"115",
    "addr:postcode":"9250",
    "addr:street":"Stationsstraat",
    "iso:country":"BE",
    "sg:address":"Stationsstraat 115",
    "sg:city":"Waasmunster",
    "sg:classifiers":[
        {
            "category":"Health Services",
            "subcategory":"Health Practitioner",
            "type":"Services"
        }
    ],
    "sg:phone":"+32 52 46 01 15",
    "sg:postcode":"9250",
    "sg:province":"Oost-Vlaanderen",
    "sg:tags":[
        "physiotherapist"
    ],
    "wof:name":"Roggeman Frank",
    "wof:placetype":"venue"
},
  "geometry": {"coordinates":[4.09871912,51.1139755249],"type":"Point"}
}