{
  "type": "Feature",
  "properties": {
    "addr:full":"Kerkplein 5 Horebeke Oost-Vlaanderen 9667",
    "addr:housenumber":"5",
    "addr:postcode":"9667",
    "addr:street":"Kerkplein",
    "iso:country":"BE",
    "sg:address":"Kerkplein 5",
    "sg:city":"Horebeke",
    "sg:orig_category":"Groenten and fruit Gh",
    "sg:phone":"+32 55 45 67 34",
    "sg:postcode":"9667",
    "sg:province":"Oost-Vlaanderen",
    "wof:name":"Ostara",
    "wof:placetype":"venue"
},
  "geometry": {"coordinates":[3.6869909763,50.8393363953],"type":"Point"}
}