{
  "type": "Feature",
  "properties": {
    "addr:full":"Noorderlaan 111 Antwerpen Antwerpen 2030",
    "addr:housenumber":"111",
    "addr:postcode":"2030",
    "addr:street":"Noorderlaan",
    "iso:country":"BE",
    "sg:address":"Noorderlaan 111",
    "sg:city":"Antwerpen",
    "sg:classifiers":[
        {
            "category":"Home & Garden",
            "subcategory":"Household Appliances",
            "type":"Retail Goods"
        }
    ],
    "sg:phone":"+32 3 544 83 94",
    "sg:postcode":"2030",
    "sg:province":"Antwerpen",
    "sg:tags":[
        "heating",
        "apparatus"
    ],
    "wof:name":"Dryfast Bvba",
    "wof:placetype":"venue"
},
  "geometry": {"coordinates":[4.4181270599,51.2620811462],"type":"Point"}
}