{
  "type": "Feature",
  "properties": {
    "addr:full":"Avenue De La Cokerie 4 Li\u00c8ge Li\u00e8ge 4030",
    "addr:housenumber":"4",
    "addr:postcode":"4030",
    "addr:street":"Avenue De La Cokerie",
    "iso:country":"BE",
    "sg:address":"Avenue De La Cokerie 4",
    "sg:city":"Li\u00c8ge",
    "sg:orig_category":"Entretien and r\u00e9parations de voitures",
    "sg:phone":"+32 4 342 55 06",
    "sg:postcode":"4030",
    "sg:province":"Li\u00e8ge",
    "wof:name":"Garage Van Den Broucke",
    "wof:placetype":"venue"
},
  "geometry": {"coordinates":[5.6046648026,50.6188240051],"type":"Point"}
}