{
  "type": "Feature",
  "properties": {
    "iso:country":"BE",
    "sg:address":"Wezestraat 106",
    "sg:city":"Izegem",
    "sg:classifiers":[
        {
            "category":"Home & Garden",
            "subcategory":"Building Materials",
            "type":"Retail Goods"
        }
    ],
    "sg:phone":"+32 51 31 50 75",
    "sg:postcode":"8870",
    "sg:province":"West-Vlaanderen",
    "sg:tags":[
        "window"
    ],
    "wof:name":"Vandoorne Bvba",
    "wof:placetype":"venue"
},
  "geometry": {"coordinates":[3.2188460827,50.9419784546],"type":"Point"}
}