{
  "type": "Feature",
  "properties": {
    "addr:full":"Avenue De La Basilique 26 Sint-agatha-berchem/berchem-sainte-agathe Bruxelles-Capitale 1082",
    "addr:housenumber":"26",
    "addr:postcode":"1082",
    "addr:street":"Avenue De La Basilique",
    "iso:country":"BE",
    "sg:address":"Avenue De La Basilique 26",
    "sg:city":"Sint-agatha-berchem/berchem-sainte-agathe",
    "sg:orig_category":"Artistes ind\u00e9pendants",
    "sg:phone":"+32 2 468 38 46",
    "sg:postcode":"1082",
    "sg:province":"Bruxelles-Capitale",
    "wof:name":"Theves",
    "wof:placetype":"venue"
},
  "geometry": {"coordinates":[4.3018708229,50.8630065918],"type":"Point"}
}