{
  "type": "Feature",
  "properties": {
    "addr:full":"Kriekstraat 18 Heuvelland West-Vlaanderen 8956",
    "addr:housenumber":"18",
    "addr:postcode":"8956",
    "addr:street":"Kriekstraat",
    "iso:country":"BE",
    "sg:address":"Kriekstraat 18",
    "sg:city":"Heuvelland",
    "sg:orig_category":"Pluimveekwekers Voedingsspeciaalzaken",
    "sg:phone":"+32 57 44 40 55",
    "sg:postcode":"8956",
    "sg:province":"West-Vlaanderen",
    "wof:name":"Huis Bio-kip",
    "wof:placetype":"venue"
},
  "geometry": {"coordinates":[2.8469700813,50.8046531677],"type":"Point"}
}