{
  "type": "Feature",
  "properties": {
    "addr:full":"Avenue Rogier 33 Bruxelles (schaerbeek) Bruxelles-Capitale 1030",
    "addr:housenumber":"33",
    "addr:postcode":"1030",
    "addr:street":"Avenue Rogier",
    "iso:country":"BE",
    "sg:address":"Avenue Rogier 33",
    "sg:city":"Bruxelles (schaerbeek)",
    "sg:orig_category":"Non-Classified Establishments",
    "sg:phone":"+32 2 245 89 82",
    "sg:postcode":"1030",
    "sg:province":"Bruxelles-Capitale",
    "wof:name":"Belicia",
    "wof:placetype":"venue"
},
  "geometry": {"coordinates":[4.373208046,50.860244751],"type":"Point"}
}