{
  "type": "Feature",
  "properties": {
    "addr:full":"Comm Neyskenslaan 106 Diest Vlaams-Brabant 3290",
    "addr:housenumber":"106",
    "addr:postcode":"3290",
    "addr:street":"Neyskenslaan",
    "iso:country":"BE",
    "sg:address":"Comm Neyskenslaan 106",
    "sg:city":"Diest",
    "sg:classifiers":[
        {
            "category":"Building & Trades",
            "subcategory":"Landscaping Services",
            "type":"Services"
        }
    ],
    "sg:phone":"+32 13 31 16 88",
    "sg:postcode":"3290",
    "sg:province":"Vlaams-Brabant",
    "sg:tags":[
        "etude",
        "technique",
        "ing\u00e9nierie"
    ],
    "wof:name":"Arcopa",
    "wof:placetype":"venue"
},
  "geometry": {"coordinates":[5.050055027,50.979801178],"type":"Point"}
}