{
  "type": "Feature",
  "properties": {
    "addr:full":"Rietstraat 1 Bornem (hingene) Antwerpen 2880",
    "addr:housenumber":"1",
    "addr:postcode":"2880",
    "addr:street":"Rietstraat",
    "iso:country":"BE",
    "sg:address":"Rietstraat 1",
    "sg:city":"Bornem (hingene)",
    "sg:classifiers":[
        {
            "category":"Professional",
            "subcategory":"Engineering",
            "type":"Services"
        }
    ],
    "sg:phone":"+32 3 889 64 73",
    "sg:postcode":"2880",
    "sg:province":"Antwerpen",
    "sg:tags":[
        "technical",
        "equipment",
        "offices-"
    ],
    "wof:name":"Otico",
    "wof:placetype":"venue"
},
  "geometry": {"coordinates":[4.242205143,51.0998497009],"type":"Point"}
}