{
  "type": "Feature",
  "properties": {
    "addr:full":"Rue Des Chevaliers 6 Bruxelles (ixelles) Bruxelles-Capitale 1050",
    "addr:housenumber":"6",
    "addr:postcode":"1050",
    "addr:street":"Rue Des Chevaliers",
    "iso:country":"BE",
    "sg:address":"Rue Des Chevaliers 6",
    "sg:city":"Bruxelles (ixelles)",
    "sg:classifiers":[
        {
            "category":"Health Services",
            "subcategory":"Doctor",
            "type":"Services"
        }
    ],
    "sg:phone":"+32 2 511 67 64",
    "sg:postcode":"1050",
    "sg:province":"Bruxelles-Capitale",
    "sg:tags":[
        "medicinephysicians",
        "surgeon"
    ],
    "wof:name":"Brouwez J P",
    "wof:placetype":"venue"
},
  "geometry": {"coordinates":[4.3591151237,50.8368682861],"type":"Point"}
}