{
  "type": "Feature",
  "properties": {
    "iso:country":"BE",
    "sg:address":"Impedorp 1",
    "sg:city":"Lede",
    "sg:classifiers":[
        {
            "category":"Cafe",
            "type":"Food & Drink"
        }
    ],
    "sg:phone":"+32 53 80 46 16",
    "sg:postcode":"9340",
    "sg:province":"Oost-Vlaanderen",
    "sg:tags":[
        "caf\u00e9s"
    ],
    "wof:name":"Caf\u00c9 Buitenbeentje",
    "wof:placetype":"venue"
},
  "geometry": {"coordinates":[3.9519500732,50.9600486755],"type":"Point"}
}