{
  "type": "Feature",
  "properties": {
    "addr:full":"Rue De Bonne Esp\u00e9rance 12-201 Ottignies-louvain-la-neuve (louvain-la-neuve) Brabant Wallon 1348",
    "addr:postcode":"12-201;1348",
    "addr:street":"Rue De Bonne Espe\u0301Rance",
    "iso:country":"BE",
    "sg:address":"Rue De Bonne Esp\u00e9rance 12-201",
    "sg:city":"Ottignies-louvain-la-neuve (louvain-la-neuve)",
    "sg:classifiers":[
        {
            "category":"Real Estate",
            "subcategory":"Architect",
            "type":"Services"
        }
    ],
    "sg:phone":"+32 10 45 49 45",
    "sg:postcode":"1348",
    "sg:province":"Brabant Wallon",
    "wof:name":"Le Fevre A",
    "wof:placetype":"venue"
},
  "geometry": {"coordinates":[4.616915226,50.6760902405],"type":"Point"}
}