{
  "type": "Feature",
  "properties": {
    "addr:full":"Floridastraat 50 Willebroek Antwerpen 2830",
    "addr:housenumber":"50",
    "addr:postcode":"2830",
    "addr:street":"Floridastraat",
    "iso:country":"BE",
    "sg:address":"Floridastraat 50",
    "sg:city":"Willebroek",
    "sg:orig_category":"Artiesten and kunstenaars",
    "sg:phone":"+32 3 866 16 82",
    "sg:postcode":"2830",
    "sg:province":"Antwerpen",
    "wof:name":"Els Olaerts",
    "wof:placetype":"venue"
},
  "geometry": {"coordinates":[4.3607521057,51.0585861206],"type":"Point"}
}