{
  "type": "Feature",
  "properties": {
    "addr:full":"Bois De Mariomont 3 Jalhay Li\u00e8ge 4845",
    "addr:housenumber":"3",
    "addr:postcode":"4845",
    "addr:street":"Bois De Mariomont",
    "iso:country":"BE",
    "sg:address":"Bois De Mariomont 3",
    "sg:city":"Jalhay",
    "sg:classifiers":[
        {
            "category":"Health Services",
            "subcategory":"Health Practitioner",
            "type":"Services"
        }
    ],
    "sg:phone":"+32 87 22 59 56",
    "sg:postcode":"4845",
    "sg:province":"Li\u00e8ge",
    "sg:tags":[
        "physiotherapist"
    ],
    "wof:name":"Renard Cindy",
    "wof:placetype":"venue"
},
  "geometry": {"coordinates":[5.9047431946,50.58020401],"type":"Point"}
}