{
  "type": "Feature",
  "properties": {
    "addr:full":"Leopoldstraat 24 Box 4 Turnhout Antwerpen 2300",
    "addr:housenumber":"24;4",
    "addr:postcode":"2300",
    "addr:street":"Leopoldstraat;Box",
    "iso:country":"BE",
    "sg:address":"Leopoldstraat 24 Box 4",
    "sg:city":"Turnhout",
    "sg:classifiers":[
        {
            "category":"Social Services",
            "subcategory":"Child Care",
            "type":"Services"
        }
    ],
    "sg:phone":"+32 14 43 99 27",
    "sg:postcode":"2300",
    "sg:province":"Antwerpen",
    "sg:tags":[
        "baby",
        "nursery",
        "day",
        "sitting"
    ],
    "wof:name":"Dienst Opvanggezinnen",
    "wof:placetype":"venue"
},
  "geometry": {"coordinates":[4.9446988106,51.323223114],"type":"Point"}
}