{
  "type": "Feature",
  "properties": {
    "addr:full":"Dendermondsesteenweg 66 Willebroek Antwerpen 2830",
    "addr:housenumber":"66",
    "addr:postcode":"2830",
    "addr:street":"Dendermondsesteenweg",
    "iso:country":"BE",
    "sg:address":"Dendermondsesteenweg 66",
    "sg:city":"Willebroek",
    "sg:orig_category":"Banques and organismes de cr\u00e9dit",
    "sg:phone":"+32 3 886 89 35",
    "sg:postcode":"2830",
    "sg:province":"Antwerpen",
    "wof:name":"De Vaderlandsche",
    "wof:placetype":"venue"
},
  "geometry": {"coordinates":[4.3555212021,51.060256958],"type":"Point"}
}