{
  "type": "Feature",
  "properties": {
    "iso:country":"BE",
    "sg:address":"Brouwersstraat 18b5",
    "sg:city":"Neerpelt",
    "sg:orig_category":"Architecten",
    "sg:phone":"+32 11 64 29 57",
    "sg:postcode":"3910",
    "sg:province":"Limburg",
    "wof:name":"Ive Schildermans",
    "wof:placetype":"venue"
},
  "geometry": {"coordinates":[5.427781105,51.2285919189],"type":"Point"}
}