{
  "type": "Feature",
  "properties": {
    "addr:full":"Arendsstraat 76 Harelbeke West-Vlaanderen 8530",
    "addr:housenumber":"76",
    "addr:postcode":"8530",
    "addr:street":"Arendsstraat",
    "iso:country":"BE",
    "sg:address":"Arendsstraat 76",
    "sg:city":"Harelbeke",
    "sg:classifiers":[
        {
            "category":"Cafe",
            "type":"Food & Drink"
        }
    ],
    "sg:phone":"+32 56 71 96 63",
    "sg:postcode":"8530",
    "sg:province":"West-Vlaanderen",
    "sg:tags":[
        "caf\u00e9s"
    ],
    "wof:name":"Anna Laevens",
    "wof:placetype":"venue"
},
  "geometry": {"coordinates":[3.321393013,50.8547019958],"type":"Point"}
}