{
  "type": "Feature",
  "properties": {
    "addr:full":"Volpenswege 10 Evergem (sleidinge) Oost-Vlaanderen 9940",
    "addr:housenumber":"10",
    "addr:postcode":"9940",
    "addr:street":"Volpenswege",
    "iso:country":"BE",
    "sg:address":"Volpenswege 10",
    "sg:city":"Evergem (sleidinge)",
    "sg:classifiers":[
        {
            "category":"Wholesale",
            "subcategory":"Plants",
            "type":"Manufacturing & Wholesale Goods"
        }
    ],
    "sg:phone":"+32 9 357 34 88",
    "sg:postcode":"9940",
    "sg:province":"Oost-Vlaanderen",
    "sg:tags":[
        "whol",
        "flower",
        "-",
        "grower"
    ],
    "wof:name":"Van Herzeele R",
    "wof:placetype":"venue"
},
  "geometry": {"coordinates":[3.6962480545,51.1440544128],"type":"Point"}
}