{
  "type": "Feature",
  "properties": {
    "iso:country":"BE",
    "sg:address":"\u00b4t Serclaesdreef 12",
    "sg:city":"Wommelgem",
    "sg:orig_category":"Motos",
    "sg:phone":"+32 3 321 31 11",
    "sg:postcode":"2160",
    "sg:province":"Antwerpen",
    "wof:name":"G & D Service",
    "wof:placetype":"venue"
},
  "geometry": {"coordinates":[4.5039038658,51.1934242249],"type":"Point"}
}