{
  "type": "Feature",
  "properties": {
    "iso:country":"BE",
    "sg:address":"Jules Van Ooststraat 53",
    "sg:city":"Tielt (aarsele)",
    "sg:classifiers":[
        {
            "category":"Arena",
            "subcategory":"Sports Club",
            "type":"Entertainment"
        }
    ],
    "sg:phone":"+32 51 63 66 12",
    "sg:postcode":"8700",
    "sg:province":"West-Vlaanderen",
    "wof:name":"De Waaiberg",
    "wof:placetype":"venue"
},
  "geometry": {"coordinates":[3.4191260338,50.9994697571],"type":"Point"}
}