{
  "type": "Feature",
  "properties": {
    "addr:full":"Rue G\u00e9n\u00e9ral Leman 133 Bruxelles (etterbeek) Bruxelles-Capitale 1040",
    "addr:housenumber":"133",
    "addr:postcode":"1040",
    "addr:street":"Rue Ge\u0301Ne\u0301Ral Leman",
    "iso:country":"BE",
    "sg:address":"Rue G\u00e9n\u00e9ral Leman 133",
    "sg:city":"Bruxelles (etterbeek)",
    "sg:classifiers":[
        {
            "category":"Cafe",
            "type":"Food & Drink"
        }
    ],
    "sg:phone":"+32 477 59 95 86",
    "sg:postcode":"1040",
    "sg:province":"Bruxelles-Capitale",
    "sg:tags":[
        "snack-bars"
    ],
    "wof:name":"Royal Pita",
    "wof:placetype":"venue"
},
  "geometry": {"coordinates":[4.38773489,50.8366622925],"type":"Point"}
}