{
  "type": "Feature",
  "properties": {
    "iso:country":"BE",
    "sg:address":"Gen.geneesheer Deracheln 94b9",
    "sg:city":"Elsene/ixelles",
    "sg:orig_category":"Advocaten and juridische adviseurs",
    "sg:phone":"+32 2 640 15 99",
    "sg:postcode":"1050",
    "sg:province":"Bruxelles-Capitale",
    "wof:name":"J.p. Arends",
    "wof:placetype":"venue"
},
  "geometry": {"coordinates":[4.3882131577,50.8147201538],"type":"Point"}
}