{
  "type": "Feature",
  "properties": {
    "addr:full":"Rue Champ Pill\u00e9 77 Gr\u00e2ce-hollogne (hollogne-aux-pierres) Li\u00e8ge 4460",
    "addr:housenumber":"77",
    "addr:postcode":"4460",
    "addr:street":"Rue Champ Pille\u0301;Hollogne-Aux-Pierres",
    "iso:country":"BE",
    "sg:address":"Rue Champ Pill\u00e9 77",
    "sg:city":"Gr\u00e2ce-hollogne (hollogne-aux-pierres)",
    "sg:classifiers":[
        {
            "category":"Building & Trades",
            "subcategory":"Landscaping Services",
            "type":"Services"
        }
    ],
    "sg:phone":"+32 496 33 81 24",
    "sg:postcode":"4460",
    "sg:province":"Li\u00e8ge",
    "sg:tags":[
        "forestry"
    ],
    "wof:name":"Gregoor R",
    "wof:placetype":"venue"
},
  "geometry": {"coordinates":[5.4685702324,50.6329574585],"type":"Point"}
}