{
  "type": "Feature",
  "properties": {
    "addr:full":"Doorniksesteenweg 153 Kortrijk West-Vlaanderen 8500",
    "addr:housenumber":"153",
    "addr:postcode":"8500",
    "addr:street":"Doorniksesteenweg",
    "iso:country":"BE",
    "sg:address":"Doorniksesteenweg 153",
    "sg:city":"Kortrijk",
    "sg:classifiers":[
        {
            "category":"Bars & Pubs",
            "type":"Food & Drink"
        }
    ],
    "sg:phone":"+32 56 20 47 71",
    "sg:postcode":"8500",
    "sg:province":"West-Vlaanderen",
    "wof:name":"D'n Bross..",
    "wof:placetype":"venue"
},
  "geometry": {"coordinates":[3.2822310925,50.8051376343],"type":"Point"}
}