{
  "type": "Feature",
  "properties": {
    "iso:country":"BE",
    "sg:address":"Avenue Charle-albert 5",
    "sg:city":"Watermaal-bosvoorde/watermael-boitsfort",
    "sg:orig_category":"M\u00e9decins and sp\u00e9cialistes",
    "sg:phone":"+32 2 672 30 64",
    "sg:postcode":"1170",
    "sg:province":"Bruxelles-Capitale",
    "wof:name":"Sylvie Blondel",
    "wof:placetype":"venue"
},
  "geometry": {"coordinates":[4.4292740822,50.8016052246],"type":"Point"}
}