{
  "type": "Feature",
  "properties": {
    "iso:country":"BE",
    "sg:address":"Gerhagenstraat 74",
    "sg:city":"Tessenderlo",
    "sg:classifiers":[
        {
            "category":"Cafe",
            "type":"Food & Drink"
        }
    ],
    "sg:phone":"+32 13 66 18 82",
    "sg:postcode":"3980",
    "sg:province":"Limburg",
    "sg:tags":[
        "caf\u00e9s"
    ],
    "wof:name":"Breughelhof",
    "wof:placetype":"venue"
},
  "geometry": {"coordinates":[5.0806031227,51.0622901917],"type":"Point"}
}