{
  "type": "Feature",
  "properties": {
    "addr:full":"Hoogstraat 3 Blankenberge West-Vlaanderen 8370",
    "addr:housenumber":"3",
    "addr:postcode":"8370",
    "addr:street":"Hoogstraat",
    "iso:country":"BE",
    "sg:address":"Hoogstraat 3",
    "sg:city":"Blankenberge",
    "sg:classifiers":[
        {
            "category":"Fast Food",
            "type":"Food & Drink"
        }
    ],
    "sg:phone":"+32 50 42 56 10",
    "sg:postcode":"8370",
    "sg:province":"West-Vlaanderen",
    "sg:tags":[
        "fried",
        "stand",
        "potato"
    ],
    "wof:name":"Fast Food Favorite",
    "wof:placetype":"venue"
},
  "geometry": {"coordinates":[3.1292469501,51.3156356812],"type":"Point"}
}