{
  "type": "Feature",
  "properties": {
    "addr:full":"Rode Kruisstraat 16 Sint-niklaas Oost-Vlaanderen 9100",
    "addr:housenumber":"16",
    "addr:postcode":"9100",
    "addr:street":"Rode Kruisstraat",
    "iso:country":"BE",
    "sg:address":"Rode Kruisstraat 16",
    "sg:city":"Sint-niklaas",
    "sg:orig_category":"Artsen and specialisten",
    "sg:phone":"+32 3 776 22 15",
    "sg:postcode":"9100",
    "sg:province":"Oost-Vlaanderen",
    "wof:name":"Alfons Lisaerde",
    "wof:placetype":"venue"
},
  "geometry": {"coordinates":[4.1436448097,51.1745185852],"type":"Point"}
}