{
  "type": "Feature",
  "properties": {
    "addr:full":"Dorpsstraat 2-4 Middelkerke (leffinge) West-Vlaanderen 8432",
    "addr:housenumber":"2-4",
    "addr:postcode":"8432",
    "addr:street":"Dorpsstraat",
    "iso:country":"BE",
    "sg:address":"Dorpsstraat 2-4",
    "sg:city":"Middelkerke (leffinge)",
    "sg:classifiers":[
        {
            "category":"Professional",
            "type":"Services"
        }
    ],
    "sg:phone":"+32 59 30 00 15",
    "sg:postcode":"8432",
    "sg:province":"West-Vlaanderen",
    "sg:tags":[
        "equipment",
        "installation",
        "restaurants"
    ],
    "wof:name":"Casteleyn G",
    "wof:placetype":"venue"
},
  "geometry": {"coordinates":[2.8751521111,51.1741638184],"type":"Point"}
}