{
  "type": "Feature",
  "properties": {
    "addr:full":"Chauss\u00c9e De Waterloo 885 Ukkel/uccle Bruxelles-Capitale 1180",
    "addr:housenumber":"885",
    "addr:postcode":"1180",
    "addr:street":"Chausse\u0301E De Waterloo;/",
    "iso:country":"BE",
    "sg:address":"Chauss\u00c9e De Waterloo 885",
    "sg:city":"Ukkel/uccle",
    "sg:classifiers":[
        {
            "category":"Fast Food",
            "type":"Food & Drink"
        }
    ],
    "sg:phone":"+32 2 372 01 80",
    "sg:postcode":"1180",
    "sg:province":"Bruxelles-Capitale",
    "sg:tags":[
        "\u00c0",
        "restaurants",
        "emporter",
        "restaurant"
    ],
    "wof:name":"L'empereur De Chine",
    "wof:placetype":"venue"
},
  "geometry": {"coordinates":[4.3699250221,50.8087005615],"type":"Point"}
}