{
  "type": "Feature",
  "properties": {
    "addr:full":"Rue Sainte-caroline 20 Frameries Hainaut 7080",
    "addr:housenumber":"20",
    "addr:postcode":"7080",
    "addr:street":"Rue Sainte-Caroline",
    "iso:country":"BE",
    "sg:address":"Rue Sainte-caroline 20",
    "sg:city":"Frameries",
    "sg:orig_category":"Beautyfarms, relaxatie and lichamelijk welzijn Schoonheidssalons",
    "sg:phone":"+32 65 67 11 67",
    "sg:postcode":"7080",
    "sg:province":"Hainaut",
    "wof:name":"Solarium Anne Galhant",
    "wof:placetype":"venue"
},
  "geometry": {"coordinates":[3.8737590313,50.4091949463],"type":"Point"}
}