{
  "type": "Feature",
  "properties": {
    "iso:country":"BE",
    "sg:address":"Turnhoutsebaan 177",
    "sg:city":"Schilde",
    "sg:classifiers":[
        {
            "category":"Restaurant",
            "type":"Food & Drink"
        }
    ],
    "sg:phone":"+32 3 383 30 30",
    "sg:postcode":"2970",
    "sg:province":"Antwerpen",
    "wof:name":"Euryanthe",
    "wof:placetype":"venue"
},
  "geometry": {"coordinates":[4.5822629929,51.2405967712],"type":"Point"}
}