{
  "type": "Feature",
  "properties": {
    "iso:country":"BE",
    "sg:address":"Kere 10",
    "sg:city":"Waarschoot",
    "sg:orig_category":"Domotics",
    "sg:phone":"+32 9 378 13 40",
    "sg:postcode":"9950",
    "sg:province":"Oost-Vlaanderen",
    "wof:name":"Vdw Electronics",
    "wof:placetype":"venue"
},
  "geometry": {"coordinates":[3.5968708992,51.1546096802],"type":"Point"}
}