{
  "type": "Feature",
  "properties": {
    "iso:country":"BE",
    "sg:address":"Bellegemstraat 26be",
    "sg:city":"Zwevegem",
    "sg:orig_category":"V\u00e9t\u00e9rinaires",
    "sg:phone":"+32 56 75 85 35",
    "sg:postcode":"8550",
    "sg:province":"West-Vlaanderen",
    "wof:name":"Karine Devos",
    "wof:placetype":"venue"
},
  "geometry": {"coordinates":[3.3403069973,50.8004417419],"type":"Point"}
}