{
  "type": "Feature",
  "properties": {
    "addr:full":"Minderbroedersstraat 6 Sint-truiden Limburg 3800",
    "addr:housenumber":"6",
    "addr:postcode":"3800",
    "addr:street":"Minderbroedersstraat",
    "iso:country":"BE",
    "sg:address":"Minderbroedersstraat 6",
    "sg:city":"Sint-truiden",
    "sg:orig_category":"Beheer onroerend goed Immobili\u00ebnkantoren Woningbouw",
    "sg:phone":"+32 11 68 35 20",
    "sg:postcode":"3800",
    "sg:province":"Limburg",
    "wof:name":"A.b.c.",
    "wof:placetype":"venue"
},
  "geometry": {"coordinates":[5.1859931946,50.8144454956],"type":"Point"}
}