{
  "type": "Feature",
  "properties": {
    "iso:country":"BE",
    "sg:address":"Sint-jansveld 13",
    "sg:city":"Diest",
    "sg:orig_category":"Boekhouders",
    "sg:phone":"+32 13 31 28 07",
    "sg:postcode":"3290",
    "sg:province":"Vlaams-Brabant",
    "wof:name":"Ferdinand Hamels",
    "wof:placetype":"venue"
},
  "geometry": {"coordinates":[5.059276104,50.9827003479],"type":"Point"}
}