{
  "type": "Feature",
  "properties": {
    "iso:country":"BE",
    "sg:address":"Avenue Des Sept Bonniers 131",
    "sg:city":"Bruxelles (forest)",
    "sg:classifiers":[
        {
            "category":"Health Services",
            "subcategory":"Health Practitioner",
            "type":"Services"
        }
    ],
    "sg:phone":"+32 2 345 49 02",
    "sg:postcode":"1190",
    "sg:province":"Bruxelles-Capitale",
    "sg:tags":[
        "physiotherapist"
    ],
    "wof:name":"Constant M",
    "wof:placetype":"venue"
},
  "geometry": {"coordinates":[4.3336148262,50.8119773865],"type":"Point"}
}