{
  "type": "Feature",
  "properties": {
    "iso:country":"BE",
    "sg:address":"Oordeelstraat 7",
    "sg:city":"Baarle-hertog",
    "sg:orig_category":"Pluimveekwekers Rundveehouders",
    "sg:phone":"+32 14 69 91 80",
    "sg:postcode":"2387",
    "sg:province":"Antwerpen",
    "wof:name":"Henricus Tuytelaers",
    "wof:placetype":"venue"
},
  "geometry": {"coordinates":[4.9467439651,51.4485473633],"type":"Point"}
}