{
  "type": "Feature",
  "properties": {
    "iso:country":"BE",
    "sg:address":"Boulevard Emile De Laveleye 37",
    "sg:city":"Li\u00e8ge 1 (li\u00e8ge 2)",
    "sg:classifiers":[
        {
            "category":"Professional",
            "subcategory":"Testing Lab",
            "type":"Services"
        }
    ],
    "sg:phone":"+32 4 343 25 83",
    "sg:postcode":"4020",
    "sg:province":"Li\u00e8ge",
    "sg:tags":[
        "chemist"
    ],
    "wof:name":"Rollus N",
    "wof:placetype":"venue"
},
  "geometry": {"coordinates":[5.5825128555,50.6234283447],"type":"Point"}
}