{
  "type": "Feature",
  "properties": {
    "iso:country":"BE",
    "sg:address":"Molenstraat 15",
    "sg:city":"Blankenberge",
    "sg:classifiers":[
        {
            "category":"Professional",
            "subcategory":"Art Services",
            "type":"Services"
        }
    ],
    "sg:phone":"+32 50 41 20 64",
    "sg:postcode":"8370",
    "sg:province":"West-Vlaanderen",
    "sg:tags":[
        "photographer"
    ],
    "wof:name":"Studio Maro",
    "wof:placetype":"venue"
},
  "geometry": {"coordinates":[3.1293261051,51.3144340515],"type":"Point"}
}