{
  "type": "Feature",
  "properties": {
    "iso:country":"BE",
    "sg:address":"Opaaigem 113",
    "sg:city":"Erpe-mere",
    "sg:orig_category":"Artsen and specialisten",
    "sg:phone":"+32 53 62 39 19",
    "sg:postcode":"9420",
    "sg:province":"Oost-Vlaanderen",
    "wof:name":"Godelieve Liessens",
    "wof:placetype":"venue"
},
  "geometry": {"coordinates":[3.930036068,50.8960418701],"type":"Point"}
}