{
  "type": "Feature",
  "properties": {
    "iso:country":"BE",
    "sg:address":"Rue Olivier Gille 96",
    "sg:city":"Ch\u00e2telet",
    "sg:classifiers":[
        {
            "category":"Health Services",
            "subcategory":"Dentist",
            "type":"Services"
        }
    ],
    "sg:phone":"+32 71 39 03 99",
    "sg:postcode":"6200",
    "sg:province":"Hainaut",
    "wof:name":"Scippo Franco",
    "wof:placetype":"venue"
},
  "geometry": {"coordinates":[4.5337200165,50.4010620117],"type":"Point"}
}