{
  "type": "Feature",
  "properties": {
    "iso:country":"BE",
    "sg:address":"Rue De L'ermitage 63",
    "sg:city":"Neupr\u00e9 (neuville-en-condroz)",
    "sg:classifiers":[
        {
            "category":"Health Services",
            "subcategory":"Dentist",
            "type":"Services"
        }
    ],
    "sg:phone":"+32 4 371 38 00",
    "sg:postcode":"4121",
    "sg:province":"Li\u00e8ge",
    "wof:name":"Seijkens Guy",
    "wof:placetype":"venue"
},
  "geometry": {"coordinates":[5.4667901993,50.5547943115],"type":"Point"}
}