{
  "type": "Feature",
  "properties": {
    "iso:country":"BE",
    "sg:address":"Place Cardinal Mercier 20",
    "sg:city":"Wavre",
    "sg:classifiers":[
        {
            "category":"Shopping",
            "subcategory":"Books",
            "type":"Retail Goods"
        }
    ],
    "sg:phone":"+32 10 22 67 68",
    "sg:postcode":"1300",
    "sg:province":"Brabant Wallon",
    "sg:tags":[
        "bookseller"
    ],
    "wof:name":"Libraire A Plus D'un Titre",
    "wof:placetype":"venue"
},
  "geometry": {"coordinates":[4.6102042198,50.7166862488],"type":"Point"}
}