{
  "type": "Feature",
  "properties": {
    "addr:full":"Georges Henrilaan 477 Sint-lambrechts-woluwe/woluwe-saint-lambert Bruxelles-Capitale 1200",
    "addr:housenumber":"477",
    "addr:postcode":"1200",
    "addr:street":"Henrilaan",
    "iso:country":"BE",
    "sg:address":"Georges Henrilaan 477",
    "sg:city":"Sint-lambrechts-woluwe/woluwe-saint-lambert",
    "sg:orig_category":"Diverse grafische activiteiten",
    "sg:phone":"+32 2 735 59 51",
    "sg:postcode":"1200",
    "sg:province":"Bruxelles-Capitale",
    "wof:name":"Auquier Partners",
    "wof:placetype":"venue"
},
  "geometry": {"coordinates":[4.4042668343,50.8416786194],"type":"Point"}
}