{
  "type": "Feature",
  "properties": {
    "addr:full":"Muydt 13 Bever/bievene Vlaams-Brabant 1547",
    "addr:housenumber":"13;1547",
    "addr:street":"Muydt;Vlaams-Brabant",
    "iso:country":"BE",
    "sg:address":"Muydt 13",
    "sg:city":"Bever/bievene",
    "sg:orig_category":"Producteurs de l\u00e9gumes",
    "sg:phone":"+32 54 58 89 19",
    "sg:postcode":"1547",
    "sg:province":"Vlaams-Brabant",
    "wof:name":"Albert Vranckx",
    "wof:placetype":"venue"
},
  "geometry": {"coordinates":[3.9187800884,50.7026786804],"type":"Point"}
}