{
  "type": "Feature",
  "properties": {
    "iso:country":"BE",
    "sg:address":"Langerbruggestraat 111",
    "sg:city":"Gent",
    "sg:classifiers":[
        {
            "category":"Farming",
            "subcategory":"Fish & Marine Products",
            "type":"Manufacturing & Wholesale Goods"
        }
    ],
    "sg:phone":"+32 9 251 13 71",
    "sg:postcode":"9000",
    "sg:province":"Oost-Vlaanderen",
    "sg:tags":[
        "-",
        "pilot"
    ],
    "wof:name":"Eendracht Sv",
    "wof:placetype":"venue"
},
  "geometry": {"coordinates":[3.7519900799,51.1063308716],"type":"Point"}
}