{
  "type": "Feature",
  "properties": {
    "iso:country":"BE",
    "sg:address":"Schoolstraat 43",
    "sg:city":"Westerlo",
    "sg:classifiers":[
        {
            "category":"Parking",
            "subcategory":"Lot",
            "type":"Transportation"
        }
    ],
    "sg:phone":"+32 14 54 36 62",
    "sg:postcode":"2260",
    "sg:province":"Antwerpen",
    "sg:tags":[
        "parking-places",
        "laying-out"
    ],
    "wof:name":"Hendrickx",
    "wof:placetype":"venue"
},
  "geometry": {"coordinates":[4.8397240639,51.0835151672],"type":"Point"}
}