{
  "type": "Feature",
  "properties": {
    "iso:country":"BE",
    "sg:address":"Rue Louis Van Beethoven 56",
    "sg:city":"Anderlecht/anderlecht",
    "sg:orig_category":"Boucheries",
    "sg:phone":"+32 2 521 56 28",
    "sg:postcode":"1070",
    "sg:province":"Bruxelles-Capitale",
    "wof:name":"H. Baeke/hugo Baeke",
    "wof:placetype":"venue"
},
  "geometry": {"coordinates":[4.2971391678,50.8292694092],"type":"Point"}
}