{
  "type": "Feature",
  "properties": {
    "addr:full":"Promenade De L'alma 33 Brussel/bruxelles Bruxelles-Capitale 1200",
    "addr:housenumber":"33",
    "addr:postcode":"1200",
    "addr:street":"Promenade De L'Alma;/",
    "iso:country":"BE",
    "sg:address":"Promenade De L'alma 33",
    "sg:city":"Brussel/bruxelles",
    "sg:classifiers":[
        {
            "category":"Fast Food",
            "type":"Food & Drink"
        }
    ],
    "sg:phone":"+32 2 771 67 02",
    "sg:postcode":"1200",
    "sg:province":"Bruxelles-Capitale",
    "sg:tags":[
        "\u00c0",
        "emporter",
        "restaurants"
    ],
    "wof:name":"Rendez Fou",
    "wof:placetype":"venue"
},
  "geometry": {"coordinates":[4.4311299324,50.8484992981],"type":"Point"}
}