{
  "type": "Feature",
  "properties": {
    "addr:full":"4e Reg. Karabiniersstr. 32 Zonnebeke West-Vlaanderen 8980",
    "addr:housenumber":"32",
    "addr:postcode":"8980",
    "addr:street":"4E;Karabiniersstr.",
    "iso:country":"BE",
    "sg:address":"4e Reg. Karabiniersstr. 32",
    "sg:city":"Zonnebeke",
    "sg:orig_category":"Brood, gebak and snoepgoed",
    "sg:phone":"+32 51 77 14 83",
    "sg:postcode":"8980",
    "sg:province":"West-Vlaanderen",
    "wof:name":"Bakkerij De Korenaar",
    "wof:placetype":"venue"
},
  "geometry": {"coordinates":[2.9872550964,50.8730812073],"type":"Point"}
}