{
  "type": "Feature",
  "properties": {
    "addr:full":"Herentalsestr 45 Turnhout Antwerpen 2300",
    "addr:housenumber":"45",
    "addr:postcode":"2300",
    "addr:street":"Herentalsestr",
    "iso:country":"BE",
    "sg:address":"Herentalsestr 45",
    "sg:city":"Turnhout",
    "sg:classifiers":[
        {
            "category":"Banks & Credit Unions",
            "subcategory":"Bank",
            "type":"Services"
        }
    ],
    "sg:phone":"+32 14 42 23 83",
    "sg:postcode":"2300",
    "sg:province":"Antwerpen",
    "wof:name":"Gemeentekrediet",
    "wof:placetype":"venue"
},
  "geometry": {"coordinates":[4.9494338036,51.3206291199],"type":"Point"}
}