{
  "type": "Feature",
  "properties": {
    "iso:country":"BE",
    "sg:address":"Rue Du Vicinal 11",
    "sg:city":"Dalhem (neufch\u00e2teau (lez-vis\u00e9))",
    "sg:classifiers":[
        {
            "category":"Home & Garden",
            "subcategory":"Garden Supply",
            "type":"Retail Goods"
        }
    ],
    "sg:phone":"+32 4 376 62 72",
    "sg:postcode":"4608",
    "sg:province":"Li\u00e8ge",
    "sg:tags":[
        "machine",
        "agricultural",
        "-"
    ],
    "wof:name":"Baguette J",
    "wof:placetype":"venue"
},
  "geometry": {"coordinates":[5.7779669762,50.7188148499],"type":"Point"}
}