{
  "type": "Feature",
  "properties": {
    "iso:country":"BE",
    "sg:address":"Baeckelmansstraat 54",
    "sg:city":"Willebroek (tisselt)",
    "sg:classifiers":[
        {
            "category":"Retail",
            "subcategory":"Veterinary Services",
            "type":"Services"
        }
    ],
    "sg:phone":"+32 3 886 36 60",
    "sg:postcode":"2830",
    "sg:province":"Antwerpen",
    "sg:tags":[
        "veterinarian"
    ],
    "wof:name":"Reyniers R Bvba",
    "wof:placetype":"venue"
},
  "geometry": {"coordinates":[4.3536300659,51.035446167],"type":"Point"}
}