{
  "type": "Feature",
  "properties": {
    "iso:country":"BE",
    "sg:address":"Duinkerkestraat 20",
    "sg:city":"Veurne",
    "sg:classifiers":[
        {
            "category":"Health Services",
            "subcategory":"Dentist",
            "type":"Services"
        }
    ],
    "sg:phone":"+32 58 31 36 26",
    "sg:postcode":"8630",
    "sg:province":"West-Vlaanderen",
    "wof:name":"Dekervel G",
    "wof:placetype":"venue"
},
  "geometry": {"coordinates":[2.6602499485,51.0705718994],"type":"Point"}
}