{
  "type": "Feature",
  "properties": {
    "addr:full":"Chauss\u00c9e De Wavre 777 Etterbeek Bruxelles-Capitale 1040",
    "addr:housenumber":"777",
    "addr:postcode":"1040",
    "addr:street":"Chausse\u0301E De Wavre",
    "iso:country":"BE",
    "sg:address":"Chauss\u00c9e De Wavre 777",
    "sg:city":"Etterbeek",
    "sg:classifiers":[
        {
            "category":"Restaurant",
            "type":"Food & Drink"
        }
    ],
    "sg:phone":"+32 2 646 38 33",
    "sg:postcode":"1040",
    "sg:province":"Bruxelles-Capitale",
    "wof:name":"Snack Evia",
    "wof:placetype":"venue"
},
  "geometry": {"coordinates":[4.3927631378,50.8286743164],"type":"Point"}
}