{
  "type": "Feature",
  "properties": {
    "addr:full":"Goorstraat 57 Boortmeerbeek (hever) Vlaams-Brabant 3191",
    "addr:housenumber":"57",
    "addr:postcode":"3191",
    "addr:street":"Goorstraat",
    "iso:country":"BE",
    "sg:address":"Goorstraat 57",
    "sg:city":"Boortmeerbeek (hever)",
    "sg:classifiers":[
        {
            "category":"Health Services",
            "subcategory":"Doctor",
            "type":"Services"
        }
    ],
    "sg:phone":"+32 15 61 61 69",
    "sg:postcode":"3191",
    "sg:province":"Vlaams-Brabant",
    "sg:tags":[
        "psychotherapist",
        "psychoanalyst"
    ],
    "wof:name":"Wuyts A",
    "wof:placetype":"venue"
},
  "geometry": {"coordinates":[4.5311951637,50.9861526489],"type":"Point"}
}