{
  "type": "Feature",
  "properties": {
    "addr:full":"J. Creytensstraat 28 Beernem (oedelem) West-Vlaanderen 8730",
    "addr:housenumber":"28",
    "addr:postcode":"8730",
    "addr:street":"Creytensstraat",
    "iso:country":"BE",
    "sg:address":"J. Creytensstraat 28",
    "sg:city":"Beernem (oedelem)",
    "sg:classifiers":[
        {
            "category":"Shopping",
            "subcategory":"Bridal",
            "type":"Retail Goods"
        }
    ],
    "sg:phone":"+32 50 78 82 61",
    "sg:postcode":"8730",
    "sg:province":"West-Vlaanderen",
    "sg:tags":[
        "list",
        "-",
        "present",
        "wedding"
    ],
    "wof:name":"Dhoore F",
    "wof:placetype":"venue"
},
  "geometry": {"coordinates":[3.3358550072,51.1699447632],"type":"Point"}
}