{
  "type": "Feature",
  "properties": {
    "iso:country":"BE",
    "sg:address":"Rue Des Moulins 67",
    "sg:city":"Mouscron",
    "sg:classifiers":[
        {
            "category":"Home & Garden",
            "subcategory":"Furniture",
            "type":"Retail Goods"
        }
    ],
    "sg:phone":"+32 56 34 79 04",
    "sg:postcode":"7700",
    "sg:province":"Hainaut",
    "sg:tags":[
        "-"
    ],
    "wof:name":"Metal Design Belgium Sa",
    "wof:placetype":"venue"
},
  "geometry": {"coordinates":[3.2121059895,50.7413291931],"type":"Point"}
}