{
  "type": "Feature",
  "properties": {
    "addr:full":"Lakweg 21 Antwerpen Antwerpen 2020",
    "addr:housenumber":"21",
    "addr:postcode":"2020",
    "addr:street":"Lakweg",
    "iso:country":"BE",
    "sg:address":"Lakweg 21",
    "sg:city":"Antwerpen",
    "sg:classifiers":[
        {
            "category":"Bars & Pubs",
            "subcategory":"Oxygen Bar",
            "type":"Food & Drink"
        }
    ],
    "sg:phone":"+32 3 248 24 61",
    "sg:postcode":"2020",
    "sg:province":"Antwerpen",
    "sg:tags":[
        "warehouse",
        "-",
        "liquid"
    ],
    "wof:name":"International Oil",
    "wof:placetype":"venue"
},
  "geometry": {"coordinates":[4.3555831909,51.195476532],"type":"Point"}
}