{
  "type": "Feature",
  "properties": {
    "iso:country":"BE",
    "sg:address":"Aatsesteenweg 104",
    "sg:city":"Edingen/enghien",
    "sg:orig_category":"Plaatsen van vloer- and muurbekleding Vloer- and muurbekleding",
    "sg:phone":"+32 2 395 45 40",
    "sg:postcode":"7850",
    "sg:province":"Hainaut",
    "wof:name":"ets Christian Degreve",
    "wof:placetype":"venue"
},
  "geometry": {"coordinates":[4.0334601402,50.6914787292],"type":"Point"}
}