{
  "type": "Feature",
  "properties": {
    "iso:country":"BE",
    "sg:address":"Boulevard Mayence 12 Bo\u00eete 1",
    "sg:city":"Charleroi",
    "sg:classifiers":[
        {
            "category":"Social Services",
            "subcategory":"Job Training",
            "type":"Services"
        }
    ],
    "sg:phone":"+32 71 33 40 74",
    "sg:postcode":"6000",
    "sg:province":"Hainaut",
    "sg:tags":[
        "steel",
        "trade"
    ],
    "wof:name":"Cobelaciers S.a.",
    "wof:placetype":"venue"
},
  "geometry": {"coordinates":[4.4434351921,50.41015625],"type":"Point"}
}