{
  "type": "Feature",
  "properties": {
    "iso:country":"BE",
    "sg:address":"Boulevard A. Briand 42",
    "sg:city":"Bruxelles",
    "sg:orig_category":"Peinture",
    "sg:phone":"+32 2 523 64 55",
    "sg:postcode":"1070",
    "sg:province":"Bruxelles-Capitale",
    "wof:name":"New Paint Concept",
    "wof:placetype":"venue"
},
  "geometry": {"coordinates":[4.3012251854,50.8284988403],"type":"Point"}
}