{
  "type": "Feature",
  "properties": {
    "addr:full":"Avenue Des Nerviens 48 Wemmel Vlaams-Brabant 1780",
    "addr:housenumber":"48",
    "addr:postcode":"1780",
    "addr:street":"Avenue Des Nerviens;Vlaams-Brabant",
    "iso:country":"BE",
    "sg:address":"Avenue Des Nerviens 48",
    "sg:city":"Wemmel",
    "sg:classifiers":[
        {
            "category":"Personal",
            "subcategory":"Beauty Salon",
            "type":"Services"
        }
    ],
    "sg:phone":"+32 2 460 86 45",
    "sg:postcode":"1780",
    "sg:province":"Vlaams-Brabant",
    "sg:tags":[
        "slimming"
    ],
    "wof:name":"Lipo Line",
    "wof:placetype":"venue"
},
  "geometry": {"coordinates":[4.3192949295,50.9003791809],"type":"Point"}
}