{
  "type": "Feature",
  "properties": {
    "addr:full":"Rue Fran\u00e7ois Vervloet 171 Box 4 Bruxelles (uccle) Bruxelles-Capitale 1180",
    "addr:housenumber":"171;4",
    "addr:postcode":"1180",
    "addr:street":"Rue Franc\u0327Ois Vervloet;Box",
    "iso:country":"BE",
    "sg:address":"Rue Fran\u00e7ois Vervloet 171 Box 4",
    "sg:city":"Bruxelles (uccle)",
    "sg:classifiers":[
        {
            "category":"Professional",
            "subcategory":"Business Services",
            "type":"Services"
        }
    ],
    "sg:phone":"+32 2 376 13 40",
    "sg:postcode":"1180",
    "sg:province":"Bruxelles-Capitale",
    "sg:tags":[
        "bookkeeping"
    ],
    "wof:name":"Caisse De Pr\u00e9voyance",
    "wof:placetype":"venue"
},
  "geometry": {"coordinates":[4.3208918571,50.7881317139],"type":"Point"}
}