{
  "type": "Feature",
  "properties": {
    "addr:full":"Prins-bisschopssingel 3 Hasselt Limburg 3500",
    "addr:housenumber":"3",
    "addr:postcode":"3500",
    "addr:street":"Prins-Bisschopssingel",
    "iso:country":"BE",
    "sg:address":"Prins-bisschopssingel 3",
    "sg:city":"Hasselt",
    "sg:classifiers":[
        {
            "category":"Banks & Credit Unions",
            "subcategory":"Investment Brokerage",
            "type":"Services"
        }
    ],
    "sg:phone":"+32 475 76 08 24",
    "sg:postcode":"3500",
    "sg:province":"Limburg",
    "sg:tags":[
        "auditor"
    ],
    "wof:name":"Maris M",
    "wof:placetype":"venue"
},
  "geometry": {"coordinates":[5.3466439247,50.9161338806],"type":"Point"}
}