{
  "type": "Feature",
  "properties": {
    "iso:country":"BE",
    "sg:address":"Berkenstraat 12",
    "sg:city":"Zomergem",
    "sg:orig_category":"Woningbouw",
    "sg:phone":"+32 9 374 57 58",
    "sg:postcode":"9930",
    "sg:province":"Oost-Vlaanderen",
    "wof:name":"Julien Ally",
    "wof:placetype":"venue"
},
  "geometry": {"coordinates":[3.515832901,51.1157913208],"type":"Point"}
}