{
  "type": "Feature",
  "properties": {
    "iso:country":"BE",
    "sg:address":"Rue De La Fontaine 2",
    "sg:city":"Bruxelles",
    "sg:classifiers":[
        {
            "category":"Education",
            "subcategory":"School",
            "type":"Public Place"
        }
    ],
    "sg:phone":"+32 2 279 58 60",
    "sg:postcode":"1000",
    "sg:province":"Bruxelles-Capitale",
    "sg:tags":[
        "secondary"
    ],
    "wof:name":"Anneessens-funck Inst",
    "wof:placetype":"venue"
},
  "geometry": {"coordinates":[4.3422198296,50.8407440186],"type":"Point"}
}