{
  "type": "Feature",
  "properties": {
    "addr:full":"Rue Blaes 168 Bruxelles Bruxelles-Capitale 1000",
    "addr:housenumber":"168",
    "addr:postcode":"1000",
    "addr:street":"Rue Blaes",
    "iso:country":"BE",
    "sg:address":"Rue Blaes 168",
    "sg:city":"Bruxelles",
    "sg:classifiers":[
        {
            "category":"Shopping",
            "subcategory":"Antiques",
            "type":"Retail Goods"
        }
    ],
    "sg:phone":"+32 2 511 44 49",
    "sg:postcode":"1000",
    "sg:province":"Bruxelles-Capitale",
    "sg:tags":[
        "restoration"
    ],
    "wof:name":"Zagorac Z",
    "wof:placetype":"venue"
},
  "geometry": {"coordinates":[4.3470931053,50.8373908997],"type":"Point"}
}