{
  "type": "Feature",
  "properties": {
    "addr:full":"Cauwerburg 115 Blok K Temse Oost-Vlaanderen 9140",
    "addr:housenumber":"115 blok k",
    "addr:postcode":"9140",
    "iso:country":"BE",
    "sg:address":"Cauwerburg 115 Blok K",
    "sg:city":"Temse",
    "sg:orig_category":"Biens d'occasion",
    "sg:phone":"+32 3 771 45 15",
    "sg:postcode":"9140",
    "sg:province":"Oost-Vlaanderen",
    "wof:name":"Monatex",
    "wof:placetype":"venue"
},
  "geometry": {"coordinates":[4.2143149376,51.1247558594],"type":"Point"}
}