{
  "type": "Feature",
  "properties": {
    "addr:full":"Beverlosesteenweg 112b Beringen (paal) Limburg 3583",
    "addr:housenumber":"112b",
    "addr:postcode":"3583",
    "addr:street":"Beverlosesteenweg",
    "iso:country":"BE",
    "sg:address":"Beverlosesteenweg 112b",
    "sg:city":"Beringen (paal)",
    "sg:classifiers":[
        {
            "category":"Home & Garden",
            "subcategory":"Home Furnishings",
            "type":"Retail Goods"
        }
    ],
    "sg:phone":"+32 11 42 08 30",
    "sg:postcode":"3583",
    "sg:province":"Limburg",
    "sg:tags":[
        "-",
        "furniture"
    ],
    "wof:name":"Cachet Meubelen",
    "wof:placetype":"venue"
},
  "geometry": {"coordinates":[5.1706700325,51.0389442444],"type":"Point"}
}