{
  "type": "Feature",
  "properties": {
    "addr:full":"Rue Point Du Jour 30 Genappe (bousval) Brabant Wallon 1470",
    "addr:housenumber":"30",
    "addr:postcode":"1470",
    "addr:street":"Rue Point Du Jour;Wallon",
    "iso:country":"BE",
    "sg:address":"Rue Point Du Jour 30",
    "sg:city":"Genappe (bousval)",
    "sg:classifiers":[
        {
            "category":"Parking",
            "subcategory":"Garage",
            "type":"Transportation"
        }
    ],
    "sg:phone":"+32 10 61 49 30",
    "sg:postcode":"1470",
    "sg:province":"Brabant Wallon",
    "sg:tags":[
        "truck",
        "-",
        "dump",
        "transport"
    ],
    "wof:name":"Pastur",
    "wof:placetype":"venue"
},
  "geometry": {"coordinates":[4.5029478073,50.622505188],"type":"Point"}
}