{
  "type": "Feature",
  "properties": {
    "addr:full":"Route De Nam\u00cache 32 Eghezee Namur 5310",
    "addr:housenumber":"32",
    "addr:postcode":"5310",
    "addr:street":"Route De Name\u0302Che;Namur",
    "iso:country":"BE",
    "sg:address":"Route De Nam\u00cache 32",
    "sg:city":"Eghezee",
    "sg:orig_category":"Enseignement maternel and primaire",
    "sg:phone":"+32 81 51 26 54",
    "sg:postcode":"5310",
    "sg:province":"Namur",
    "wof:name":"E.f.l. St.martin",
    "wof:placetype":"venue"
},
  "geometry": {"coordinates":[4.9143261909,50.558467865],"type":"Point"}
}