{
  "type": "Feature",
  "properties": {
    "addr:full":"Rue De Vitrival 23 Fosses-la-ville Namur 5070",
    "addr:housenumber":"23",
    "addr:postcode":"5070",
    "addr:street":"Rue De Vitrival",
    "iso:country":"BE",
    "sg:address":"Rue De Vitrival 23",
    "sg:city":"Fosses-la-ville",
    "sg:orig_category":"Postkantoren Verzekeringsmakelaars and experts",
    "sg:phone":"+32 71 71 12 72",
    "sg:postcode":"5070",
    "sg:province":"Namur",
    "wof:name":"La Poste",
    "wof:placetype":"venue"
},
  "geometry": {"coordinates":[4.6948051453,50.3950920105],"type":"Point"}
}