{
  "type": "Feature",
  "properties": {
    "addr:full":"Hendekenstraat 1b Assenede Oost-Vlaanderen 9960",
    "addr:housenumber":"1b",
    "addr:postcode":"9960",
    "addr:street":"Hendekenstraat",
    "iso:country":"BE",
    "sg:address":"Hendekenstraat 1b",
    "sg:city":"Assenede",
    "sg:orig_category":"Gestion des d\u00e9charges and sites d\u00e9finitifs de stockage",
    "sg:phone":"+32 9 373 54 84",
    "sg:postcode":"9960",
    "sg:province":"Oost-Vlaanderen",
    "wof:name":"Containerpark Assenede",
    "wof:placetype":"venue"
},
  "geometry": {"coordinates":[3.7196850777,51.2131576538],"type":"Point"}
}