{
  "type": "Feature",
  "properties": {
    "addr:full":"Gebr. De Winterstraat 72 Lille Antwerpen 2275",
    "addr:housenumber":"72",
    "addr:postcode":"2275",
    "addr:street":"Winterstraat",
    "iso:country":"BE",
    "sg:address":"Gebr. De Winterstraat 72",
    "sg:city":"Lille",
    "sg:orig_category":"Gespecialiseerde residenti\u00eble bouw Woningbouw",
    "sg:phone":"+32 3 312 48 98",
    "sg:postcode":"2275",
    "sg:province":"Antwerpen",
    "wof:name":"Marcel Segers",
    "wof:placetype":"venue"
},
  "geometry": {"coordinates":[4.7975921631,51.2588920593],"type":"Point"}
}