{
  "type": "Feature",
  "properties": {
    "addr:full":"Franklin Rooseveltlaan 64 Waregem West-Vlaanderen 8790",
    "addr:housenumber":"64",
    "addr:postcode":"8790",
    "addr:street":"Franklin Rooseveltlaan",
    "iso:country":"BE",
    "sg:address":"Franklin Rooseveltlaan 64",
    "sg:city":"Waregem",
    "sg:orig_category":"Avocats and conseillers juridiques",
    "sg:phone":"+32 56 32 30 97",
    "sg:postcode":"8790",
    "sg:province":"West-Vlaanderen",
    "wof:name":"Frederique Vanryckeghem",
    "wof:placetype":"venue"
},
  "geometry": {"coordinates":[3.4385259151,50.8798370361],"type":"Point"}
}