{
  "type": "Feature",
  "properties": {
    "addr:full":"Rue Belle T\u00cate 18 Ecaussinnes Hainaut 7190",
    "addr:housenumber":"18",
    "addr:postcode":"7190",
    "addr:street":"Rue Belle Te\u0302Te;Hainaut",
    "iso:country":"BE",
    "sg:address":"Rue Belle T\u00cate 18",
    "sg:city":"Ecaussinnes",
    "sg:orig_category":"Pain, p\u00e2tisseries and confiseries",
    "sg:phone":"+32 67 44 32 64",
    "sg:postcode":"7190",
    "sg:province":"Hainaut",
    "wof:name":"Bernard Burion",
    "wof:placetype":"venue"
},
  "geometry": {"coordinates":[4.1514000893,50.5660171509],"type":"Point"}
}