{
  "type": "Feature",
  "properties": {
    "addr:full":"Venneweg 7 Hoogstraten Antwerpen 2321",
    "addr:housenumber":"7",
    "addr:postcode":"2321",
    "addr:street":"Venneweg",
    "iso:country":"BE",
    "sg:address":"Venneweg 7",
    "sg:city":"Hoogstraten",
    "sg:orig_category":"Fruitteelt Groententeelt",
    "sg:phone":"+32 3 315 90 68",
    "sg:postcode":"2321",
    "sg:province":"Antwerpen",
    "wof:name":"Frans Adriaensen",
    "wof:placetype":"venue"
},
  "geometry": {"coordinates":[4.7364802361,51.4305725098],"type":"Point"}
}