{
  "type": "Feature",
  "properties": {
    "addr:full":"Parklaan 10 Hove Antwerpen 2540",
    "addr:housenumber":"10",
    "addr:postcode":"2540",
    "addr:street":"Parklaan",
    "iso:country":"BE",
    "sg:address":"Parklaan 10",
    "sg:city":"Hove",
    "sg:orig_category":"Immobili\u00ebnkantoren",
    "sg:phone":"+32 3 455 60 03",
    "sg:postcode":"2540",
    "sg:province":"Antwerpen",
    "wof:name":"Jos Pauwels-immobilien",
    "wof:placetype":"venue"
},
  "geometry": {"coordinates":[4.4728279114,51.1465148926],"type":"Point"}
}