{
  "type": "Feature",
  "properties": {
    "iso:country":"BE",
    "sg:address":"Dorp-oost 43",
    "sg:city":"Lochristi",
    "sg:classifiers":[
        {
            "category":"Retail",
            "subcategory":"Auto Repair",
            "type":"Services"
        }
    ],
    "sg:phone":"+32 9 355 23 47",
    "sg:postcode":"9080",
    "sg:province":"Oost-Vlaanderen",
    "sg:tags":[
        "garage"
    ],
    "wof:name":"De Clercq H",
    "wof:placetype":"venue"
},
  "geometry": {"coordinates":[3.836961031,51.0973968506],"type":"Point"}
}