{
  "type": "Feature",
  "properties": {
    "iso:country":"BE",
    "sg:address":"Scheepvaartkaai 16a",
    "sg:city":"Hasselt",
    "sg:orig_category":"Non-Classified Establishments",
    "sg:phone":"+32 11 26 51 50",
    "sg:postcode":"3500",
    "sg:province":"Limburg",
    "wof:name":"Rigs Jeans Nv",
    "wof:placetype":"venue"
},
  "geometry": {"coordinates":[5.3563079834,50.9404525757],"type":"Point"}
}