{
  "type": "Feature",
  "properties": {
    "iso:country":"BE",
    "sg:address":"Avenue Du Bourgmestre Jean Materne 21-23",
    "sg:city":"Namur (jambes)",
    "sg:classifiers":[
        {
            "category":"Shopping",
            "subcategory":"Jewelry",
            "type":"Retail Goods"
        }
    ],
    "sg:phone":"+32 81 30 06 78",
    "sg:postcode":"5100",
    "sg:province":"Namur",
    "sg:tags":[
        "jeweller",
        "-"
    ],
    "wof:name":"Gerard Horlogerie Bijouterie",
    "wof:placetype":"venue"
},
  "geometry": {"coordinates":[4.8713750839,50.4566345215],"type":"Point"}
}