{
  "type": "Feature",
  "properties": {
    "addr:full":"Rue Des Hospices 48 Verviers Li\u00e8ge 4800",
    "addr:housenumber":"48",
    "addr:postcode":"4800",
    "addr:street":"Rue Des Hospices",
    "iso:country":"BE",
    "sg:address":"Rue Des Hospices 48",
    "sg:city":"Verviers",
    "sg:orig_category":"Journaux. Tabac",
    "sg:phone":"+32 87 33 88 61",
    "sg:postcode":"4800",
    "sg:province":"Li\u00e8ge",
    "wof:name":"Librairie Lassine-baltus",
    "wof:placetype":"venue"
},
  "geometry": {"coordinates":[5.8729848862,50.5963401794],"type":"Point"}
}