{
  "type": "Feature",
  "properties": {
    "iso:country":"BE",
    "sg:address":"Nieuwe Baan 23",
    "sg:city":"Oud-turnhout",
    "sg:orig_category":"Woningbouw",
    "sg:phone":"+32 14 45 44 52",
    "sg:postcode":"2360",
    "sg:province":"Antwerpen",
    "wof:name":"Jansens D",
    "wof:placetype":"venue"
},
  "geometry": {"coordinates":[4.9738049507,51.3384361267],"type":"Point"}
}