{
  "type": "Feature",
  "properties": {
    "iso:country":"BE",
    "sg:address":"Rue Du Brill 4",
    "sg:city":"Arlon",
    "sg:orig_category":"Enseignement maternel and primaire",
    "sg:phone":"+32 63 21 80 08",
    "sg:postcode":"6700",
    "sg:province":"Luxembourg",
    "wof:name":"Ecole Fond. Communale",
    "wof:placetype":"venue"
},
  "geometry": {"coordinates":[5.8340711594,49.6813011169],"type":"Point"}
}