{
  "type": "Feature",
  "properties": {
    "addr:full":"Dorp 68a Grobbendonk Antwerpen 2288",
    "addr:housenumber":"68a",
    "addr:postcode":"2288",
    "addr:street":"Dorp",
    "iso:country":"BE",
    "sg:address":"Dorp 68a",
    "sg:city":"Grobbendonk",
    "sg:orig_category":"Banques and organismes de cr\u00e9dit",
    "sg:phone":"+32 14 50 71 70",
    "sg:postcode":"2288",
    "sg:province":"Antwerpen",
    "wof:name":"Kbc",
    "wof:placetype":"venue"
},
  "geometry": {"coordinates":[4.7431621552,51.1689376831],"type":"Point"}
}