{
  "type": "Feature",
  "properties": {
    "iso:country":"BE",
    "sg:address":"Rue D'amberloup 30a",
    "sg:city":"Sainte-ode (lavacherie)",
    "sg:classifiers":[
        {
            "category":"Building & Trades",
            "subcategory":"Construction",
            "type":"Services"
        }
    ],
    "sg:phone":"+32 61 68 80 55",
    "sg:postcode":"6681",
    "sg:province":"Luxembourg",
    "sg:tags":[
        "installation",
        "-",
        "central",
        "heating"
    ],
    "wof:name":"Goosse Jean-louis",
    "wof:placetype":"venue"
},
  "geometry": {"coordinates":[5.5159201622,50.0489082336],"type":"Point"}
}