{
  "type": "Feature",
  "properties": {
    "addr:full":"Nieuwpoortlaan 7 De Panne West-Vlaanderen 8660",
    "addr:housenumber":"7",
    "addr:postcode":"8660",
    "addr:street":"Nieuwpoortlaan",
    "iso:country":"BE",
    "sg:address":"Nieuwpoortlaan 7",
    "sg:city":"De Panne",
    "sg:orig_category":"Boucheries",
    "sg:phone":"+32 58 41 17 27",
    "sg:postcode":"8660",
    "sg:province":"West-Vlaanderen",
    "wof:name":"Beenhouwerij St.hubert",
    "wof:placetype":"venue"
},
  "geometry": {"coordinates":[2.590775013,51.1030502319],"type":"Point"}
}