{
  "type": "Feature",
  "properties": {
    "iso:country":"BE",
    "sg:address":"Calusstraat 3",
    "sg:city":"Sint-laureins (watervliet)",
    "sg:classifiers":[
        {
            "category":"Building & Trades",
            "subcategory":"Plumbing",
            "type":"Services"
        }
    ],
    "sg:phone":"+32 9 379 05 15",
    "sg:postcode":"9988",
    "sg:province":"Oost-Vlaanderen",
    "sg:tags":[
        "repair",
        "mainten",
        "-",
        "central",
        "heating"
    ],
    "wof:name":"Haverbeke R",
    "wof:placetype":"venue"
},
  "geometry": {"coordinates":[3.6176741123,51.2759094238],"type":"Point"}
}