{
  "type": "Feature",
  "properties": {
    "iso:country":"BE",
    "sg:address":"Bosstraat 7",
    "sg:city":"Kortenberg",
    "sg:orig_category":"Woningbouw",
    "sg:phone":"+32 2 757 95 54",
    "sg:postcode":"3070",
    "sg:province":"Vlaams-Brabant",
    "wof:name":"Rebatim",
    "wof:placetype":"venue"
},
  "geometry": {"coordinates":[4.5388069153,50.8849525452],"type":"Point"}
}