{
  "type": "Feature",
  "properties": {
    "iso:country":"BE",
    "sg:address":"Rue Emile-gardez 4",
    "sg:city":"Paliseul",
    "sg:classifiers":[
        {
            "category":"Fast Food",
            "type":"Food & Drink"
        }
    ],
    "sg:phone":"+32 61 53 45 24",
    "sg:postcode":"6850",
    "sg:province":"Luxembourg",
    "sg:tags":[
        "restaurant",
        "\u00c0",
        "domicile",
        "emporter",
        "livraison",
        "restaurants"
    ],
    "wof:name":"Au Vieux Carlsbourg",
    "wof:placetype":"venue"
},
  "geometry": {"coordinates":[5.0814590454,49.8943023682],"type":"Point"}
}