{
  "type": "Feature",
  "properties": {
    "iso:country":"BE",
    "sg:address":"Linkhousestraat 2",
    "sg:city":"Halen",
    "sg:classifiers":[
        {
            "category":"Personal",
            "subcategory":"Beauty Salon",
            "type":"Services"
        }
    ],
    "sg:phone":"+32 13 44 31 83",
    "sg:postcode":"3545",
    "sg:province":"Limburg",
    "sg:tags":[
        "de",
        "coiffure"
    ],
    "wof:name":"Coiffure Siceaux",
    "wof:placetype":"venue"
},
  "geometry": {"coordinates":[5.1233229637,50.9781074524],"type":"Point"}
}