{
  "type": "Feature",
  "properties": {
    "iso:country":"BE",
    "sg:address":"Abdijstraat 215",
    "sg:city":"Antwerpen",
    "sg:classifiers":[
        {
            "category":"Food & Beverages",
            "subcategory":"Groceries & Convenience Stores",
            "type":"Retail Goods"
        }
    ],
    "sg:phone":"+32 3 237 05 06",
    "sg:postcode":"2020",
    "sg:province":"Antwerpen",
    "sg:tags":[
        "grocer"
    ],
    "wof:name":"Singh Voeding",
    "wof:placetype":"venue"
},
  "geometry": {"coordinates":[4.3857688904,51.1871414185],"type":"Point"}
}