{
  "type": "Feature",
  "properties": {
    "addr:full":"Chauss\u00e9e De Valenciennes 297 Ath (ormeignies) Hainaut 7802",
    "addr:housenumber":"297",
    "addr:postcode":"7802",
    "addr:street":"Chausse\u0301E De Valenciennes",
    "iso:country":"BE",
    "sg:address":"Chauss\u00e9e De Valenciennes 297",
    "sg:city":"Ath (ormeignies)",
    "sg:classifiers":[
        {
            "category":"Professional",
            "subcategory":"Testing Lab",
            "type":"Services"
        }
    ],
    "sg:phone":"+32 68 28 11 19",
    "sg:postcode":"7802",
    "sg:province":"Hainaut",
    "sg:tags":[
        "chemist"
    ],
    "wof:name":"Pharmacie D'ormeignies",
    "wof:placetype":"venue"
},
  "geometry": {"coordinates":[3.7527279854,50.5938110352],"type":"Point"}
}