{
  "type": "Feature",
  "properties": {
    "addr:full":"Havermarkt 25 Hasselt Limburg 3500",
    "addr:housenumber":"25",
    "addr:postcode":"3500",
    "addr:street":"Havermarkt",
    "iso:country":"BE",
    "sg:address":"Havermarkt 25",
    "sg:city":"Hasselt",
    "sg:orig_category":"Pharmaciens",
    "sg:phone":"+32 11 22 61 04",
    "sg:postcode":"3500",
    "sg:province":"Limburg",
    "wof:name":"Apoteek Havermarkt",
    "wof:placetype":"venue"
},
  "geometry": {"coordinates":[5.3352408409,50.929397583],"type":"Point"}
}