{
  "type": "Feature",
  "properties": {
    "addr:full":"Klappeistraat 85 Antwerpen Antwerpen 2060",
    "addr:housenumber":"85",
    "addr:postcode":"2060",
    "addr:street":"Klappeistraat",
    "iso:country":"BE",
    "sg:address":"Klappeistraat 85",
    "sg:city":"Antwerpen",
    "sg:orig_category":"Kapsalons",
    "sg:phone":"+32 3 235 05 40",
    "sg:postcode":"2060",
    "sg:province":"Antwerpen",
    "wof:name":"Coiffure Jozef",
    "wof:placetype":"venue"
},
  "geometry": {"coordinates":[4.4306359291,51.2196044922],"type":"Point"}
}