{
  "type": "Feature",
  "properties": {
    "iso:country":"BE",
    "sg:address":"Handzamestraat 152",
    "sg:city":"Kortemark",
    "sg:orig_category":"Sportcentra",
    "sg:phone":"+32 51 56 89 83",
    "sg:postcode":"8610",
    "sg:province":"West-Vlaanderen",
    "wof:name":"Sporthal Hansan",
    "wof:placetype":"venue"
},
  "geometry": {"coordinates":[3.0132200718,51.0251693726],"type":"Point"}
}