{
  "type": "Feature",
  "properties": {
    "iso:country":"BE",
    "sg:address":"Rue De Brabant 154",
    "sg:city":"Schaarbeek/schaerbeek",
    "sg:orig_category":"Rev\u00eatements de sols and murs",
    "sg:phone":"+32 2 218 44 91",
    "sg:postcode":"1030",
    "sg:province":"Bruxelles-Capitale",
    "wof:name":"Turkmen",
    "wof:placetype":"venue"
},
  "geometry": {"coordinates":[4.3632950783,50.8601493835],"type":"Point"}
}