{
  "type": "Feature",
  "properties": {
    "addr:full":"Schrieksesteenweg 55 Heist-op-den-berg Antwerpen 2221",
    "addr:housenumber":"55",
    "addr:postcode":"2221",
    "addr:street":"Schrieksesteenweg",
    "iso:country":"BE",
    "sg:address":"Schrieksesteenweg 55",
    "sg:city":"Heist-op-den-berg",
    "sg:classifiers":[
        {
            "category":"Autos & Motor Vehicles",
            "subcategory":"Fuel & Gas Station",
            "type":"Retail Goods"
        }
    ],
    "sg:phone":"+32 15 22 23 23",
    "sg:postcode":"2221",
    "sg:province":"Antwerpen",
    "sg:tags":[
        "stations-service",
        "carburants"
    ],
    "wof:name":"Emiel Vets",
    "wof:placetype":"venue"
},
  "geometry": {"coordinates":[4.7739758492,51.0512428284],"type":"Point"}
}