{
  "type": "Feature",
  "properties": {
    "addr:full":"Oude Tramweg 34a Bilzen Limburg 3740",
    "addr:housenumber":"34a",
    "addr:postcode":"3740",
    "addr:street":"Oude Tramweg",
    "iso:country":"BE",
    "sg:address":"Oude Tramweg 34a",
    "sg:city":"Bilzen",
    "sg:orig_category":"Herstelling horloges and juwelen",
    "sg:phone":"+32 89 50 35 62",
    "sg:postcode":"3740",
    "sg:province":"Limburg",
    "wof:name":"Patrick Hansen",
    "wof:placetype":"venue"
},
  "geometry": {"coordinates":[5.5222802162,50.893989563],"type":"Point"}
}