{
  "type": "Feature",
  "properties": {
    "addr:full":"Julius De Geyterstraat 3 Lede Oost-Vlaanderen 9340",
    "addr:housenumber":"3",
    "addr:postcode":"9340",
    "addr:street":"Julius De Geyterstraat",
    "iso:country":"BE",
    "sg:address":"Julius De Geyterstraat 3",
    "sg:city":"Lede",
    "sg:classifiers":[
        {
            "category":"Personal",
            "subcategory":"Beauty Salon",
            "type":"Services"
        }
    ],
    "sg:phone":"+32 53 80 03 12",
    "sg:postcode":"9340",
    "sg:province":"Oost-Vlaanderen",
    "sg:tags":[
        "de",
        "coiffure"
    ],
    "wof:name":"Nadia De Sutter",
    "wof:placetype":"venue"
},
  "geometry": {"coordinates":[3.9767849445,50.9653282166],"type":"Point"}
}