{
  "type": "Feature",
  "properties": {
    "iso:country":"BE",
    "sg:address":"Eyloschlaan 16",
    "sg:city":"Destelbergen",
    "sg:classifiers":[
        {
            "category":"Health Services",
            "subcategory":"Doctor",
            "type":"Services"
        }
    ],
    "sg:phone":"+32 9 228 72 27",
    "sg:postcode":"9070",
    "sg:province":"Oost-Vlaanderen",
    "sg:tags":[
        "medicinephysicians",
        "surgeon"
    ],
    "wof:name":"Delmeire Filip",
    "wof:placetype":"venue"
},
  "geometry": {"coordinates":[3.8027191162,51.067024231],"type":"Point"}
}