{
  "type": "Feature",
  "properties": {
    "addr:full":"Vossaardestraat 13a Wervik West-Vlaanderen 8940",
    "addr:housenumber":"13a",
    "addr:postcode":"8940",
    "addr:street":"Vossaardestraat",
    "iso:country":"BE",
    "sg:address":"Vossaardestraat 13a",
    "sg:city":"Wervik",
    "sg:orig_category":"Ergotherapists",
    "sg:phone":"+32 56 31 18 28",
    "sg:postcode":"8940",
    "sg:province":"West-Vlaanderen",
    "wof:name":"Blomme G",
    "wof:placetype":"venue"
},
  "geometry": {"coordinates":[3.0321719646,50.8171806335],"type":"Point"}
}