{
  "type": "Feature",
  "properties": {
    "iso:country":"BE",
    "sg:address":"Place Emile Vandervelde 11",
    "sg:city":"Bruxelles",
    "sg:classifiers":[
        {
            "category":"Professional",
            "subcategory":"Detective & Security Services",
            "type":"Services"
        }
    ],
    "sg:phone":"+32 2 507 27 98",
    "sg:postcode":"1000",
    "sg:province":"Bruxelles-Capitale",
    "sg:tags":[
        "guard"
    ],
    "wof:name":"Securilink",
    "wof:placetype":"venue"
},
  "geometry": {"coordinates":[4.3530049324,50.8411216736],"type":"Point"}
}