{
  "type": "Feature",
  "properties": {
    "iso:country":"BE",
    "sg:address":"Boomsesteenweg 89",
    "sg:city":"Willebroek",
    "sg:orig_category":"Traitements param\u00e9dicaux",
    "sg:phone":"+32 3 886 99 46",
    "sg:postcode":"2830",
    "sg:province":"Antwerpen",
    "wof:name":"De Rudder",
    "wof:placetype":"venue"
},
  "geometry": {"coordinates":[4.3605818748,51.0717468262],"type":"Point"}
}