{
  "type": "Feature",
  "properties": {
    "iso:country":"BE",
    "sg:address":"Noordlaan 33",
    "sg:city":"Kuurne",
    "sg:orig_category":"Drukkerijen and copyshops",
    "sg:phone":"+32 56 35 76 69",
    "sg:postcode":"8520",
    "sg:province":"West-Vlaanderen",
    "wof:name":"V.t.v. Print",
    "wof:placetype":"venue"
},
  "geometry": {"coordinates":[3.2626199722,50.8632888794],"type":"Point"}
}