{
  "type": "Feature",
  "properties": {
    "addr:full":"Kerkhofstraat 84 Boom Antwerpen 2850",
    "addr:housenumber":"84",
    "addr:postcode":"2850",
    "addr:street":"Kerkhofstraat",
    "iso:country":"BE",
    "sg:address":"Kerkhofstraat 84",
    "sg:city":"Boom",
    "sg:classifiers":[
        {
            "category":"Fast Food",
            "type":"Food & Drink"
        }
    ],
    "sg:phone":"+32 3 844 51 23",
    "sg:postcode":"2850",
    "sg:province":"Antwerpen",
    "sg:tags":[
        "\u00c0",
        "emporter",
        "restaurants"
    ],
    "wof:name":"Panda Keuken",
    "wof:placetype":"venue"
},
  "geometry": {"coordinates":[4.3728790283,51.0883598328],"type":"Point"}
}