{
  "type": "Feature",
  "properties": {
    "iso:country":"BE",
    "sg:address":"Minervastraat 6",
    "sg:city":"Zaventem",
    "sg:classifiers":[
        {
            "category":"Industrial Area",
            "type":"Public Place"
        }
    ],
    "sg:postcode":"1930",
    "sg:province":"Vlaams-Brabant",
    "sg:tags":[
        "-",
        "laser"
    ],
    "wof:name":"Baasel Benelux Bv",
    "wof:placetype":"venue"
},
  "geometry": {"coordinates":[23.4416999817,48.5007514954],"type":"Point"}
}