{
  "type": "Feature",
  "properties": {
    "iso:country":"BE",
    "sg:address":"Rue De Marcinelle 82",
    "sg:city":"Charleroi",
    "sg:classifiers":[
        {
            "category":"Travel",
            "subcategory":"Hotels & Motels",
            "type":"Entertainment"
        }
    ],
    "sg:phone":"+32 71 30 47 79",
    "sg:postcode":"6000",
    "sg:province":"Hainaut",
    "wof:name":"Orchidee (l')",
    "wof:placetype":"venue"
},
  "geometry": {"coordinates":[4.4466981888,50.4056587219],"type":"Point"}
}