{
  "type": "Feature",
  "properties": {
    "addr:full":"Bijlkenstraat 5 Nevele Oost-Vlaanderen 9850",
    "addr:housenumber":"5",
    "addr:postcode":"9850",
    "addr:street":"Bijlkenstraat",
    "iso:country":"BE",
    "sg:address":"Bijlkenstraat 5",
    "sg:city":"Nevele",
    "sg:classifiers":[
        {
            "category":"Farming",
            "subcategory":"Crops",
            "type":"Manufacturing & Wholesale Goods"
        }
    ],
    "sg:phone":"+32 9 371 80 38",
    "sg:postcode":"9850",
    "sg:province":"Oost-Vlaanderen",
    "sg:tags":[
        "vegetable",
        "fruit",
        "-",
        "grower"
    ],
    "wof:name":"Schelstraete D",
    "wof:placetype":"venue"
},
  "geometry": {"coordinates":[3.525988102,51.0396194458],"type":"Point"}
}