{
  "type": "Feature",
  "properties": {
    "addr:full":"Avenue De La Sauvagine 7 Box 103 Bruxelles (watermael-boitsfort) Bruxelles-Capitale 1170",
    "addr:housenumber":"7 box 103",
    "addr:postcode":"1170",
    "addr:street":"Avenue De La Sauvagine",
    "iso:country":"BE",
    "sg:address":"Avenue De La Sauvagine 7 Box 103",
    "sg:city":"Bruxelles (watermael-boitsfort)",
    "sg:classifiers":[
        {
            "category":"Transit Center",
            "subcategory":"Freight",
            "type":"Transportation"
        }
    ],
    "sg:phone":"+32 2 673 40 28",
    "sg:postcode":"1170",
    "sg:province":"Bruxelles-Capitale",
    "sg:tags":[
        "import",
        "export",
        "-"
    ],
    "wof:name":"Mobex Sprl",
    "wof:placetype":"venue"
},
  "geometry": {"coordinates":[4.4026060104,50.810382843],"type":"Point"}
}