{
  "type": "Feature",
  "properties": {
    "addr:full":"Rue Du Castillon 218 Quaregnon Hainaut 7390",
    "addr:housenumber":"218",
    "addr:postcode":"7390",
    "addr:street":"Rue Du Castillon",
    "iso:country":"BE",
    "sg:address":"Rue Du Castillon 218",
    "sg:city":"Quaregnon",
    "sg:orig_category":"Schoonheidssalons",
    "sg:phone":"+32 65 79 30 09",
    "sg:postcode":"7390",
    "sg:province":"Hainaut",
    "wof:name":"Sandrina Alaimo",
    "wof:placetype":"venue"
},
  "geometry": {"coordinates":[3.8761239052,50.4288902283],"type":"Point"}
}