{
  "type": "Feature",
  "properties": {
    "iso:country":"BE",
    "sg:address":"Route De Beaumont 154",
    "sg:city":"Thuillies",
    "sg:orig_category":"V\u00e9hicules automobiles",
    "sg:phone":"+32 71 53 49 39",
    "sg:postcode":"6536",
    "sg:province":"Hainaut",
    "wof:name":"Etablissement Antoine-volvo Thuillies",
    "wof:placetype":"venue"
},
  "geometry": {"coordinates":[4.3178348541,50.3023452759],"type":"Point"}
}