{
  "type": "Feature",
  "properties": {
    "addr:full":"Zirkstraat 32 Antwerpen Antwerpen 2000",
    "addr:housenumber":"32",
    "addr:postcode":"2000",
    "addr:street":"Zirkstraat",
    "iso:country":"BE",
    "sg:address":"Zirkstraat 32",
    "sg:city":"Antwerpen",
    "sg:orig_category":"Koerierbedrijven",
    "sg:phone":"+32 3 226 96 33",
    "sg:postcode":"2000",
    "sg:province":"Antwerpen",
    "wof:name":"A.c.x. Koerierdienst",
    "wof:placetype":"venue"
},
  "geometry": {"coordinates":[4.4014639854,51.2227668762],"type":"Point"}
}