{
  "type": "Feature",
  "properties": {
    "iso:country":"BE",
    "sg:address":"Achtermuide 56",
    "sg:city":"Gent",
    "sg:orig_category":"M\u00e9decins and sp\u00e9cialistes",
    "sg:phone":"+32 9 251 80 97",
    "sg:postcode":"9000",
    "sg:province":"Oost-Vlaanderen",
    "wof:name":"Abdulkadir Kara",
    "wof:placetype":"venue"
},
  "geometry": {"coordinates":[3.7312679291,51.0757102966],"type":"Point"}
}