{
  "type": "Feature",
  "properties": {
    "iso:country":"BE",
    "sg:address":"Sint-maartenplein 54",
    "sg:city":"Hasselt (stevoort)",
    "sg:classifiers":[
        {
            "category":"Health Services",
            "subcategory":"Health Practitioner",
            "type":"Services"
        }
    ],
    "sg:phone":"+32 11 31 24 60",
    "sg:postcode":"3512",
    "sg:province":"Limburg",
    "sg:tags":[
        "physiotherapist"
    ],
    "wof:name":"Bex Marina",
    "wof:placetype":"venue"
},
  "geometry": {"coordinates":[5.2480998039,50.9161300659],"type":"Point"}
}