{
  "type": "Feature",
  "properties": {
    "addr:full":"Langeveldstraat 23b Herent Vlaams-Brabant 3020",
    "addr:housenumber":"23b",
    "addr:postcode":"3020",
    "addr:street":"Langeveldstraat",
    "iso:country":"BE",
    "sg:address":"Langeveldstraat 23b",
    "sg:city":"Herent",
    "sg:classifiers":[
        {
            "category":"Banks & Credit Unions",
            "subcategory":"Investment Brokerage",
            "type":"Services"
        }
    ],
    "sg:phone":"+32 16 20 50 25",
    "sg:postcode":"3020",
    "sg:province":"Vlaams-Brabant",
    "sg:tags":[
        "repair",
        "-",
        "installation",
        "sanitary",
        "article"
    ],
    "wof:name":"Deridder D",
    "wof:placetype":"venue"
},
  "geometry": {"coordinates":[4.6902899742,50.9151687622],"type":"Point"}
}