{
  "type": "Feature",
  "properties": {
    "addr:full":"Rue D'havr\u00c9 59 Mons Hainaut 7000",
    "addr:housenumber":"59",
    "addr:postcode":"7000",
    "addr:street":"Rue D'Havre \u0301;Hainaut",
    "iso:country":"BE",
    "sg:address":"Rue D'havr\u00c9 59",
    "sg:city":"Mons",
    "sg:classifiers":[
        {
            "category":"Fast Food",
            "type":"Food & Drink"
        }
    ],
    "sg:phone":"+32 65 35 62 59",
    "sg:postcode":"7000",
    "sg:province":"Hainaut",
    "sg:tags":[
        "meeneem",
        "restaurant"
    ],
    "wof:name":"Gourmets D'asie",
    "wof:placetype":"venue"
},
  "geometry": {"coordinates":[3.9549760818,50.4538536072],"type":"Point"}
}