{
  "type": "Feature",
  "properties": {
    "addr:full":"Riddersstraat 159 Leuven Vlaams-Brabant 3000",
    "addr:housenumber":"159",
    "addr:postcode":"3000",
    "addr:street":"Riddersstraat",
    "iso:country":"BE",
    "sg:address":"Riddersstraat 159",
    "sg:city":"Leuven",
    "sg:orig_category":"Artsen and specialisten",
    "sg:phone":"+32 16 23 09 03",
    "sg:postcode":"3000",
    "sg:province":"Vlaams-Brabant",
    "wof:name":"Wijkgezondheidscentrum De Ridderbuurt",
    "wof:placetype":"venue"
},
  "geometry": {"coordinates":[4.693374157,50.8862037659],"type":"Point"}
}