{
  "type": "Feature",
  "properties": {
    "iso:country":"BE",
    "sg:address":"Karenveldstraat 34",
    "sg:city":"Opwijk",
    "sg:orig_category":"Gestion des d\u00e9charges and sites d\u00e9finitifs de stockage",
    "sg:phone":"+32 52 35 97 80",
    "sg:postcode":"1745",
    "sg:province":"Vlaams-Brabant",
    "wof:name":"Containerpark Opwijk",
    "wof:placetype":"venue"
},
  "geometry": {"coordinates":[4.1802229881,50.9679145813],"type":"Point"}
}