{
  "type": "Feature",
  "properties": {
    "addr:full":"Nieuwstraat 52 Willebroek Antwerpen 2830",
    "addr:housenumber":"52",
    "addr:postcode":"2830",
    "addr:street":"Nieuwstraat",
    "iso:country":"BE",
    "sg:address":"Nieuwstraat 52",
    "sg:city":"Willebroek",
    "sg:orig_category":"Medische apparatuur, orthopedische artikelen and prothesen Fab",
    "sg:phone":"+32 3 886 50 28",
    "sg:postcode":"2830",
    "sg:province":"Antwerpen",
    "wof:name":"Regudent",
    "wof:placetype":"venue"
},
  "geometry": {"coordinates":[4.3629078865,51.0604667664],"type":"Point"}
}