{
  "type": "Feature",
  "properties": {
    "addr:full":"Rue Du P\u00c9rr\u00c9on 121 Sprimont Li\u00e8ge 4141",
    "addr:housenumber":"121",
    "addr:postcode":"4141",
    "addr:street":"Rue Du Pe\u0301Rre\u0301On",
    "iso:country":"BE",
    "sg:address":"Rue Du P\u00c9rr\u00c9on 121",
    "sg:city":"Sprimont",
    "sg:orig_category":"Boekhouders",
    "sg:phone":"+32 4 360 00 23",
    "sg:postcode":"4141",
    "sg:province":"Li\u00e8ge",
    "wof:name":"P.y. Lacroix",
    "wof:placetype":"venue"
},
  "geometry": {"coordinates":[5.7180528641,50.5300064087],"type":"Point"}
}