{
  "type": "Feature",
  "properties": {
    "addr:full":"Sint-catharinastraat 51 Stabroek Antwerpen 2940",
    "addr:housenumber":"51",
    "addr:postcode":"2940",
    "addr:street":"Sint-Catharinastraat",
    "iso:country":"BE",
    "sg:address":"Sint-catharinastraat 51",
    "sg:city":"Stabroek",
    "sg:classifiers":[
        {
            "category":"Health Services",
            "subcategory":"Health Practitioner",
            "type":"Services"
        }
    ],
    "sg:phone":"+32 3 568 63 76",
    "sg:postcode":"2940",
    "sg:province":"Antwerpen",
    "sg:tags":[
        "physiotherapist"
    ],
    "wof:name":"Maas H",
    "wof:placetype":"venue"
},
  "geometry": {"coordinates":[4.3725762367,51.3329353333],"type":"Point"}
}