{
  "type": "Feature",
  "properties": {
    "addr:full":"Rue De Joie 144 Li\u00e8ge 1 Li\u00e8ge 4000",
    "addr:housenumber":"144;1",
    "addr:postcode":"4000",
    "addr:street":"Rue De Joie",
    "iso:country":"BE",
    "sg:address":"Rue De Joie 144",
    "sg:city":"Li\u00e8ge 1",
    "sg:classifiers":[
        {
            "category":"Health Services",
            "subcategory":"Health Practitioner",
            "type":"Services"
        }
    ],
    "sg:phone":"+32 4 252 11 56",
    "sg:postcode":"4000",
    "sg:province":"Li\u00e8ge",
    "sg:tags":[
        "physiotherapist"
    ],
    "wof:name":"Reynders Ph",
    "wof:placetype":"venue"
},
  "geometry": {"coordinates":[5.5561308861,50.6269073486],"type":"Point"}
}