{
  "type": "Feature",
  "properties": {
    "iso:country":"BE",
    "sg:address":"August Van Landeghemstraat 31",
    "sg:city":"Willebroek",
    "sg:classifiers":[
        {
            "category":"Shopping",
            "subcategory":"Shoes",
            "type":"Retail Goods"
        }
    ],
    "sg:phone":"+32 3 886 66 00",
    "sg:postcode":"2830",
    "sg:province":"Antwerpen",
    "sg:tags":[
        "slipper",
        "-"
    ],
    "wof:name":"De Wachter",
    "wof:placetype":"venue"
},
  "geometry": {"coordinates":[4.3604331017,51.0615196228],"type":"Point"}
}