{
  "type": "Feature",
  "properties": {
    "iso:country":"BE",
    "sg:address":"Chemin De L'andelaine 10",
    "sg:city":"Dalhem (warsage)",
    "sg:classifiers":[
        {
            "category":"Retail",
            "subcategory":"Auto Repair",
            "type":"Services"
        }
    ],
    "sg:phone":"+32 4 360 99 59",
    "sg:postcode":"4608",
    "sg:province":"Li\u00e8ge",
    "sg:tags":[
        "garage"
    ],
    "wof:name":"Auto-look",
    "wof:placetype":"venue"
},
  "geometry": {"coordinates":[5.7603049278,50.7351417542],"type":"Point"}
}