{
  "type": "Feature",
  "properties": {
    "addr:full":"Rue Arnold Delsupexhe 93 Herstal Li\u00e8ge 4040",
    "addr:housenumber":"93",
    "addr:postcode":"4040",
    "addr:street":"Rue Arnold Delsupexhe",
    "iso:country":"BE",
    "sg:address":"Rue Arnold Delsupexhe 93",
    "sg:city":"Herstal",
    "sg:classifiers":[
        {
            "category":"Building & Trades",
            "subcategory":"Plumbing",
            "type":"Services"
        }
    ],
    "sg:phone":"+32 4 248 16 29",
    "sg:postcode":"4040",
    "sg:province":"Li\u00e8ge",
    "sg:tags":[
        "diver",
        "commerce",
        "gr",
        "pour",
        "equipement"
    ],
    "wof:name":"Jacques Dohet",
    "wof:placetype":"venue"
},
  "geometry": {"coordinates":[5.6429319382,50.6843109131],"type":"Point"}
}