{
  "type": "Feature",
  "properties": {
    "iso:country":"BE",
    "sg:address":"Rue Puccini 60",
    "sg:city":"Anderlecht/anderlecht",
    "sg:classifiers":[
        {
            "category":"Arena",
            "subcategory":"Sports Club",
            "type":"Entertainment"
        }
    ],
    "sg:phone":"+32 2 523 49 88",
    "sg:postcode":"1070",
    "sg:province":"Bruxelles-Capitale",
    "sg:tags":[
        "de"
    ],
    "wof:name":"Gym Cl. Ancien. St.gilles",
    "wof:placetype":"venue"
},
  "geometry": {"coordinates":[4.3049907684,50.8449554443],"type":"Point"}
}