{
  "type": "Feature",
  "properties": {
    "addr:full":"Avenue Moli\u00e8re 296 Bruxelles (uccle) Bruxelles-Capitale 1180",
    "addr:housenumber":"296",
    "addr:postcode":"1180",
    "addr:street":"Avenue Molie\u0300Re",
    "iso:country":"BE",
    "sg:address":"Avenue Moli\u00e8re 296",
    "sg:city":"Bruxelles (uccle)",
    "sg:classifiers":[
        {
            "category":"Retail",
            "subcategory":"Veterinary Services",
            "type":"Services"
        }
    ],
    "sg:phone":"+32 2 344 84 15",
    "sg:postcode":"1180",
    "sg:province":"Bruxelles-Capitale",
    "sg:tags":[
        "veterinarian"
    ],
    "wof:name":"Garreyn S",
    "wof:placetype":"venue"
},
  "geometry": {"coordinates":[4.3622097969,50.8159332275],"type":"Point"}
}