{
  "type": "Feature",
  "properties": {
    "iso:country":"BE",
    "sg:address":"Baron De Gieylaan 74",
    "sg:city":"De Pinte",
    "sg:orig_category":"Boucheries",
    "sg:phone":"+32 9 282 38 81",
    "sg:postcode":"9840",
    "sg:province":"Oost-Vlaanderen",
    "wof:name":"Freddy Notebaert",
    "wof:placetype":"venue"
},
  "geometry": {"coordinates":[3.6584990025,50.9962844849],"type":"Point"}
}