{
  "type": "Feature",
  "properties": {
    "addr:full":"Brugsesteenweg 51 Oudenburg West-Vlaanderen 8460",
    "addr:housenumber":"51",
    "addr:postcode":"8460",
    "addr:street":"Brugsesteenweg",
    "iso:country":"BE",
    "sg:address":"Brugsesteenweg 51",
    "sg:city":"Oudenburg",
    "sg:orig_category":"G\u00e9om\u00e8tres",
    "sg:phone":"+32 59 26 81 81",
    "sg:postcode":"8460",
    "sg:province":"West-Vlaanderen",
    "wof:name":"Paul Deruyter",
    "wof:placetype":"venue"
},
  "geometry": {"coordinates":[3.0023450851,51.1840553284],"type":"Point"}
}