{
  "type": "Feature",
  "properties": {
    "addr:full":"Leuvense Steenweg 157 Boortmeerbeek (hever) Vlaams-Brabant 3191",
    "addr:housenumber":"157",
    "addr:postcode":"3191",
    "addr:street":"Leuvense Steenweg",
    "iso:country":"BE",
    "sg:address":"Leuvense Steenweg 157",
    "sg:city":"Boortmeerbeek (hever)",
    "sg:classifiers":[
        {
            "category":"Shopping",
            "subcategory":"Antiques",
            "type":"Retail Goods"
        }
    ],
    "sg:phone":"+32 15 51 74 00",
    "sg:postcode":"3191",
    "sg:province":"Vlaams-Brabant",
    "wof:name":"Ter Bronnen",
    "wof:placetype":"venue"
},
  "geometry": {"coordinates":[4.5566878319,50.9790687561],"type":"Point"}
}