{
  "type": "Feature",
  "properties": {
    "addr:full":"Veurtstraat 73bus 3 Breendonk Antwerpen 2870",
    "addr:housenumber":"3",
    "addr:postcode":"2870",
    "addr:street":"Veurtstraat;Breendonk Antwerpen",
    "iso:country":"BE",
    "sg:address":"Veurtstraat 73bus 3",
    "sg:city":"Breendonk",
    "sg:orig_category":"Whipped Cream For Toppings",
    "sg:phone":"+32 3 321 18 59",
    "sg:postcode":"2870",
    "sg:province":"Antwerpen",
    "wof:name":"Brouwers Nv",
    "wof:placetype":"venue"
},
  "geometry": {"coordinates":[4.4561080933,51.1953048706],"type":"Point"}
}