{
  "type": "Feature",
  "properties": {
    "iso:country":"BE",
    "sg:address":"Churchillaan 85",
    "sg:city":"Waregem",
    "sg:orig_category":"Maroquinerie and articles de voyage",
    "sg:phone":"+32 56 60 14 42",
    "sg:postcode":"8790",
    "sg:province":"West-Vlaanderen",
    "wof:name":"Tanghe",
    "wof:placetype":"venue"
},
  "geometry": {"coordinates":[3.4419879913,50.8902664185],"type":"Point"}
}