{
  "type": "Feature",
  "properties": {
    "addr:full":"Stationsstraat 59 Ledegem West-Vlaanderen 8880",
    "addr:housenumber":"59",
    "addr:postcode":"8880",
    "addr:street":"Stationsstraat",
    "iso:country":"BE",
    "sg:address":"Stationsstraat 59",
    "sg:city":"Ledegem",
    "sg:orig_category":"Apotheken",
    "sg:phone":"+32 56 50 90 62",
    "sg:postcode":"8880",
    "sg:province":"West-Vlaanderen",
    "wof:name":"Apotheek De Hoop",
    "wof:placetype":"venue"
},
  "geometry": {"coordinates":[3.1223609447,50.8561820984],"type":"Point"}
}