{
  "type": "Feature",
  "properties": {
    "iso:country":"BE",
    "sg:address":"Avenue Houba De Strooper 29",
    "sg:city":"Bruxelles",
    "sg:classifiers":[
        {
            "category":"Shopping",
            "subcategory":"Luggage & Leather Goods",
            "type":"Retail Goods"
        }
    ],
    "sg:phone":"+32 2 479 95 06",
    "sg:postcode":"1020",
    "sg:province":"Bruxelles-Capitale",
    "sg:tags":[
        "luggage-carriers"
    ],
    "wof:name":"Thule-central Pneus",
    "wof:placetype":"venue"
},
  "geometry": {"coordinates":[4.3414268494,50.8865852356],"type":"Point"}
}