{
  "type": "Feature",
  "properties": {
    "addr:full":"Stationsstraat 276a Dilbeek Vlaams-Brabant 1700",
    "addr:housenumber":"276a",
    "addr:postcode":"1700",
    "addr:street":"Stationsstraat",
    "iso:country":"BE",
    "sg:address":"Stationsstraat 276a",
    "sg:city":"Dilbeek",
    "sg:classifiers":[
        {
            "category":"Fast Food",
            "type":"Food & Drink"
        }
    ],
    "sg:phone":"+32 2 466 37 58",
    "sg:postcode":"1700",
    "sg:province":"Vlaams-Brabant",
    "sg:tags":[
        "meeneem",
        "restaurant"
    ],
    "wof:name":"The River Of Sring",
    "wof:placetype":"venue"
},
  "geometry": {"coordinates":[4.2452697754,50.8647270203],"type":"Point"}
}