{
  "type": "Feature",
  "properties": {
    "iso:country":"BE",
    "sg:address":"Rue L\u00b4apleit 6",
    "sg:city":"Huy",
    "sg:orig_category":"Herenkledingzaken",
    "sg:phone":"+32 85 23 64 70",
    "sg:postcode":"4500",
    "sg:province":"Li\u00e8ge",
    "wof:name":"Boutique Green Bay",
    "wof:placetype":"venue"
},
  "geometry": {"coordinates":[5.2403612137,50.5198249817],"type":"Point"}
}