{
  "type": "Feature",
  "properties": {
    "addr:full":"Rue Du Rabot 17 Jemeppe-sur-sambre (mornimont) Namur 5190",
    "addr:housenumber":"17",
    "addr:postcode":"5190",
    "addr:street":"Rue Du Rabot;Namur",
    "iso:country":"BE",
    "sg:address":"Rue Du Rabot 17",
    "sg:city":"Jemeppe-sur-sambre (mornimont)",
    "sg:classifiers":[
        {
            "category":"Professional",
            "subcategory":"Business Services",
            "type":"Services"
        }
    ],
    "sg:phone":"+32 71 78 90 17",
    "sg:postcode":"5190",
    "sg:province":"Namur",
    "sg:tags":[
        "firm"
    ],
    "wof:name":"Renier M",
    "wof:placetype":"venue"
},
  "geometry": {"coordinates":[4.6703448296,50.4645042419],"type":"Point"}
}