{
  "type": "Feature",
  "properties": {
    "iso:country":"BE",
    "sg:address":"Hagenbroeksesteenweg 45",
    "sg:city":"Lier",
    "sg:classifiers":[
        {
            "category":"Social Services",
            "subcategory":"Retirement Home",
            "type":"Services"
        }
    ],
    "sg:phone":"+32 3 480 31 35",
    "sg:postcode":"2500",
    "sg:province":"Antwerpen",
    "sg:tags":[
        "society",
        "protection",
        "animal"
    ],
    "wof:name":"Dierenbescherming District Lier Vzw",
    "wof:placetype":"venue"
},
  "geometry": {"coordinates":[4.5740890503,51.1458625793],"type":"Point"}
}