{
  "type": "Feature",
  "properties": {
    "iso:country":"BE",
    "sg:address":"Zultseweg 121",
    "sg:city":"Waregem",
    "sg:classifiers":[
        {
            "category":"Home & Garden",
            "subcategory":"Garden Supply",
            "type":"Retail Goods"
        }
    ],
    "sg:phone":"+32 56 60 26 30",
    "sg:postcode":"8790",
    "sg:province":"West-Vlaanderen",
    "wof:name":"Vansteenkiste M",
    "wof:placetype":"venue"
},
  "geometry": {"coordinates":[3.4413120747,50.8974952698],"type":"Point"}
}