{
  "type": "Feature",
  "properties": {
    "addr:full":"Kerkstraat 11 Lummen Limburg 3560",
    "addr:housenumber":"11",
    "addr:postcode":"3560",
    "addr:street":"Kerkstraat",
    "iso:country":"BE",
    "sg:address":"Kerkstraat 11",
    "sg:city":"Lummen",
    "sg:orig_category":"Lingerie and ondergoed Textiel Verlichting and huishoudartikelen",
    "sg:phone":"+32 13 52 12 20",
    "sg:postcode":"3560",
    "sg:province":"Limburg",
    "wof:name":"Huis Carmans",
    "wof:placetype":"venue"
},
  "geometry": {"coordinates":[5.1902370453,50.9858627319],"type":"Point"}
}