{
  "type": "Feature",
  "properties": {
    "addr:full":"Rue Des Ormeaux 15 Chimay Hainaut 6460",
    "addr:housenumber":"15",
    "addr:postcode":"6460",
    "addr:street":"Rue Des Ormeaux",
    "iso:country":"BE",
    "sg:address":"Rue Des Ormeaux 15",
    "sg:city":"Chimay",
    "sg:orig_category":"Instituts de beaut\u00e9",
    "sg:phone":"+32 60 21 53 73",
    "sg:postcode":"6460",
    "sg:province":"Hainaut",
    "wof:name":"Institut Carole Ligne",
    "wof:placetype":"venue"
},
  "geometry": {"coordinates":[4.3158869743,50.0478363037],"type":"Point"}
}