{
  "type": "Feature",
  "properties": {
    "iso:country":"BE",
    "sg:address":"Fazantenlaan 21 Box 8",
    "sg:city":"Meise",
    "sg:classifiers":[
        {
            "category":"Personal",
            "subcategory":"Beauty Salon",
            "type":"Services"
        }
    ],
    "sg:phone":"+32 2 270 19 15",
    "sg:postcode":"1860",
    "sg:province":"Vlaams-Brabant",
    "sg:tags":[
        "lady",
        "-",
        "hairdressing"
    ],
    "wof:name":"Hair-studio Marcoo",
    "wof:placetype":"venue"
},
  "geometry": {"coordinates":[4.341509819,50.9252891541],"type":"Point"}
}