{
  "type": "Feature",
  "properties": {
    "iso:country":"BE",
    "sg:address":"Rue De La Limite 121",
    "sg:city":"Court-saint-etienne",
    "sg:orig_category":"Activit\u00e9s r\u00e9cr\u00e9atives diverses",
    "sg:phone":"+32 10 61 35 23",
    "sg:postcode":"1490",
    "sg:province":"Brabant Wallon",
    "wof:name":"Philsteph",
    "wof:placetype":"venue"
},
  "geometry": {"coordinates":[4.5694231987,50.6521759033],"type":"Point"}
}