{
  "type": "Feature",
  "properties": {
    "addr:full":"Keizerstraat 32 Willebroek (blaasveld) Antwerpen 2830",
    "addr:housenumber":"32",
    "addr:postcode":"2830",
    "addr:street":"Keizerstraat",
    "iso:country":"BE",
    "sg:address":"Keizerstraat 32",
    "sg:city":"Willebroek (blaasveld)",
    "sg:classifiers":[
        {
            "category":"Insurance",
            "subcategory":"Insurance Agent",
            "type":"Services"
        }
    ],
    "sg:phone":"+32 3 886 69 59",
    "sg:postcode":"2830",
    "sg:province":"Antwerpen",
    "sg:tags":[
        "broker"
    ],
    "wof:name":"Cools J",
    "wof:placetype":"venue"
},
  "geometry": {"coordinates":[4.3748989105,51.0555496216],"type":"Point"}
}