{
  "type": "Feature",
  "properties": {
    "iso:country":"BE",
    "sg:address":"Rue Du Pilori 3",
    "sg:city":"P\u00e9ruwelz (brasmenil)",
    "sg:classifiers":[
        {
            "category":"Retail",
            "subcategory":"Veterinary Services",
            "type":"Services"
        }
    ],
    "sg:phone":"+32 69 78 02 66",
    "sg:postcode":"7604",
    "sg:province":"Hainaut",
    "sg:tags":[
        "veterinarian"
    ],
    "wof:name":"Eperjessy F",
    "wof:placetype":"venue"
},
  "geometry": {"coordinates":[3.5563900471,50.5373191833],"type":"Point"}
}