{
  "type": "Feature",
  "properties": {
    "addr:full":"Statielei 26 Box 40 Mortsel Antwerpen 2640",
    "addr:housenumber":"26 box 40",
    "addr:postcode":"2640",
    "addr:street":"Statielei",
    "iso:country":"BE",
    "sg:address":"Statielei 26 Box 40",
    "sg:city":"Mortsel",
    "sg:classifiers":[
        {
            "category":"Real Estate",
            "subcategory":"Surveying",
            "type":"Services"
        }
    ],
    "sg:phone":"+32 3 440 50 00",
    "sg:postcode":"2640",
    "sg:province":"Antwerpen",
    "sg:tags":[
        "surveyor",
        "land"
    ],
    "wof:name":"Vermeulen M",
    "wof:placetype":"venue"
},
  "geometry": {"coordinates":[4.452188015,51.1703605652],"type":"Point"}
}