{
  "type": "Feature",
  "properties": {
    "iso:country":"BE",
    "sg:address":"Aalterbaan 146",
    "sg:city":"Maldegem",
    "sg:orig_category":"Rev\u00eatements pour sols and murs. Peinture",
    "sg:phone":"+32 50 71 98 99",
    "sg:postcode":"9990",
    "sg:province":"Oost-Vlaanderen",
    "wof:name":"Adriaan Van Hulle",
    "wof:placetype":"venue"
},
  "geometry": {"coordinates":[3.4525520802,51.1998825073],"type":"Point"}
}