{
  "type": "Feature",
  "properties": {
    "iso:country":"BE",
    "sg:address":"Herseltsesteenweg 174",
    "sg:city":"Aarschot",
    "sg:classifiers":[
        {
            "category":"Education",
            "subcategory":"School",
            "type":"Public Place"
        }
    ],
    "sg:phone":"+32 16 69 55 87",
    "sg:postcode":"3200",
    "sg:province":"Vlaams-Brabant",
    "sg:tags":[
        "-",
        "private"
    ],
    "wof:name":"Babelachtig",
    "wof:placetype":"venue"
},
  "geometry": {"coordinates":[4.8357400894,51.0027389526],"type":"Point"}
}