{
  "type": "Feature",
  "properties": {
    "addr:full":"Oostrozebekestraat 139 Ingelmunster West-Vlaanderen 8770",
    "addr:housenumber":"139",
    "addr:postcode":"8770",
    "addr:street":"Oostrozebekestraat",
    "iso:country":"BE",
    "sg:address":"Oostrozebekestraat 139",
    "sg:city":"Ingelmunster",
    "sg:classifiers":[
        {
            "category":"Building & Trades",
            "subcategory":"Construction",
            "type":"Services"
        }
    ],
    "sg:phone":"+32 51 30 54 47",
    "sg:postcode":"8770",
    "sg:province":"West-Vlaanderen",
    "sg:tags":[
        "stucco",
        "contractor"
    ],
    "wof:name":"Tanghe Gebr Bvba",
    "wof:placetype":"venue"
},
  "geometry": {"coordinates":[3.2638950348,50.9194526672],"type":"Point"}
}