{
  "type": "Feature",
  "properties": {
    "addr:full":"Veldstraat 5 Staden West-Vlaanderen 8840",
    "addr:housenumber":"5",
    "addr:postcode":"8840",
    "addr:street":"Veldstraat",
    "iso:country":"BE",
    "sg:address":"Veldstraat 5",
    "sg:city":"Staden",
    "sg:orig_category":"Plantes and fleurs Gr",
    "sg:phone":"+32 51 24 10 40",
    "sg:postcode":"8840",
    "sg:province":"West-Vlaanderen",
    "wof:name":"Feys Filotrans",
    "wof:placetype":"venue"
},
  "geometry": {"coordinates":[3.0478219986,50.934047699],"type":"Point"}
}