{
  "type": "Feature",
  "properties": {
    "addr:full":"Kapelstraat 85 Deerlijk West-Vlaanderen 8540",
    "addr:housenumber":"85",
    "addr:postcode":"8540",
    "addr:street":"Kapelstraat",
    "iso:country":"BE",
    "sg:address":"Kapelstraat 85",
    "sg:city":"Deerlijk",
    "sg:classifiers":[
        {
            "category":"Arena",
            "subcategory":"Sports Club",
            "type":"Entertainment"
        }
    ],
    "sg:phone":"+32 56 77 79 57",
    "sg:postcode":"8540",
    "sg:province":"West-Vlaanderen",
    "sg:tags":[
        "de"
    ],
    "wof:name":"Wijkraad De Trompe",
    "wof:placetype":"venue"
},
  "geometry": {"coordinates":[3.3764550686,50.8183784485],"type":"Point"}
}