{
  "type": "Feature",
  "properties": {
    "iso:country":"BE",
    "sg:address":"Burchtdam 20",
    "sg:city":"Ninove",
    "sg:orig_category":"Begrafeniswezen",
    "sg:phone":"+32 54 33 22 31",
    "sg:postcode":"9400",
    "sg:province":"Oost-Vlaanderen",
    "wof:name":"Begrafenissen Galle R.",
    "wof:placetype":"venue"
},
  "geometry": {"coordinates":[4.023182869,50.834564209],"type":"Point"}
}