{
  "type": "Feature",
  "properties": {
    "iso:country":"BE",
    "sg:address":"Ster 51b",
    "sg:city":"Sint-niklaas",
    "sg:classifiers":[
        {
            "category":"Wholesale",
            "subcategory":"Wine & Distilled Alcoholic Beverages",
            "type":"Manufacturing & Wholesale Goods"
        }
    ],
    "sg:phone":"+32 3 776 59 49",
    "sg:postcode":"9100",
    "sg:province":"Oost-Vlaanderen",
    "sg:tags":[
        "whol",
        "-",
        "spirit",
        "mfg"
    ],
    "wof:name":"Den Ouden Advokaat",
    "wof:placetype":"venue"
},
  "geometry": {"coordinates":[4.1911411285,51.1779174805],"type":"Point"}
}