{
  "type": "Feature",
  "properties": {
    "iso:country":"BE",
    "sg:address":"Avenue Des Petits Champs 8",
    "sg:city":"Waterloo",
    "sg:classifiers":[
        {
            "category":"Professional",
            "subcategory":"Lawyer & Legal Services",
            "type":"Services"
        }
    ],
    "sg:phone":"+32 2 353 09 77",
    "sg:postcode":"1410",
    "sg:province":"Brabant Wallon",
    "wof:name":"Harmel M",
    "wof:placetype":"venue"
},
  "geometry": {"coordinates":[4.4003968239,50.7249717712],"type":"Point"}
}