{
  "type": "Feature",
  "properties": {
    "iso:country":"BE",
    "sg:address":"Boudewijnlaan 15",
    "sg:city":"Deerlijk",
    "sg:orig_category":"Experts-comptables",
    "sg:phone":"+32 56 71 68 55",
    "sg:postcode":"8540",
    "sg:province":"West-Vlaanderen",
    "wof:name":"Dujardin",
    "wof:placetype":"venue"
},
  "geometry": {"coordinates":[3.3512899876,50.8597640991],"type":"Point"}
}