{
  "type": "Feature",
  "properties": {
    "iso:country":"BE",
    "sg:address":"Rue De Grandrieu 2",
    "sg:city":"Beaumont",
    "sg:orig_category":"Landbouwmachines Gh",
    "sg:phone":"+32 71 58 82 05",
    "sg:postcode":"6500",
    "sg:province":"Hainaut",
    "wof:name":"Au Serv. De L'agriculture",
    "wof:placetype":"venue"
},
  "geometry": {"coordinates":[4.2372989655,50.240486145],"type":"Point"}
}