{
  "type": "Feature",
  "properties": {
    "addr:full":"Avenue D'auderghem 59ba Etterbeek Bruxelles-Capitale 1040",
    "addr:housenumber":"59ba",
    "addr:postcode":"1040",
    "addr:street":"Avenue D'Auderghem",
    "iso:country":"BE",
    "sg:address":"Avenue D'auderghem 59ba",
    "sg:city":"Etterbeek",
    "sg:classifiers":[
        {
            "category":"Insurance",
            "subcategory":"Life Insurance",
            "type":"Services"
        }
    ],
    "sg:phone":"+32 2 280 14 15",
    "sg:postcode":"1040",
    "sg:province":"Bruxelles-Capitale",
    "sg:tags":[
        "assurance"
    ],
    "wof:name":"Imvesta Finance",
    "wof:placetype":"venue"
},
  "geometry": {"coordinates":[4.3847961426,50.8403816223],"type":"Point"}
}