{
  "type": "Feature",
  "properties": {
    "addr:full":"Doolweg 5 Koekelare West-Vlaanderen 8680",
    "addr:housenumber":"5",
    "addr:postcode":"8680",
    "addr:street":"Doolweg",
    "iso:country":"BE",
    "sg:address":"Doolweg 5",
    "sg:city":"Koekelare",
    "sg:orig_category":"Varkenskwekers",
    "sg:phone":"+32 51 58 90 49",
    "sg:postcode":"8680",
    "sg:province":"West-Vlaanderen",
    "wof:name":"Andre Willaert",
    "wof:placetype":"venue"
},
  "geometry": {"coordinates":[2.9727370739,51.1085205078],"type":"Point"}
}