{
  "type": "Feature",
  "properties": {
    "iso:country":"BE",
    "sg:address":"Polderstraat 6",
    "sg:city":"Lokeren",
    "sg:orig_category":"Maisons de repos and r\u00e9sidences",
    "sg:phone":"+32 9 348 02 07",
    "sg:postcode":"9160",
    "sg:province":"Oost-Vlaanderen",
    "wof:name":"Residentie Ter Engelen",
    "wof:placetype":"venue"
},
  "geometry": {"coordinates":[4.0030798912,51.1002426147],"type":"Point"}
}