{
  "type": "Feature",
  "properties": {
    "iso:country":"BE",
    "sg:address":"Rue D\u00b4ogn\u00c9 20",
    "sg:city":"Sprimont",
    "sg:orig_category":"Meubles D\u00e9taillants, Am\u00e9nagement de B\u00e2timents et de Cuisines. Fabrication and montage de mobilier",
    "sg:phone":"+32 4 382 26 80",
    "sg:postcode":"4140",
    "sg:province":"Li\u00e8ge",
    "wof:name":"Top Cuisine",
    "wof:placetype":"venue"
},
  "geometry": {"coordinates":[5.6316142082,50.5144424438],"type":"Point"}
}