{
  "type": "Feature",
  "properties": {
    "addr:full":"Chemin Du Pont D'ancre 168b Lessines Hainaut 7860",
    "addr:housenumber":"168b",
    "addr:postcode":"7860",
    "addr:street":"Chemin Du Pont D'Ancre;Hainaut",
    "iso:country":"BE",
    "sg:address":"Chemin Du Pont D'ancre 168b",
    "sg:city":"Lessines",
    "sg:classifiers":[
        {
            "category":"Professional",
            "subcategory":"Accounting & Tax Preparation",
            "type":"Services"
        }
    ],
    "sg:phone":"+32 68 33 38 42",
    "sg:postcode":"7860",
    "sg:province":"Hainaut",
    "sg:tags":[
        "bookkeeper"
    ],
    "wof:name":"Fiduciaire Pont D'ancre",
    "wof:placetype":"venue"
},
  "geometry": {"coordinates":[3.8274929523,50.7204971313],"type":"Point"}
}