{
  "type": "Feature",
  "properties": {
    "addr:full":"Sint-niklaasstraat 9 Oostende West-Vlaanderen 8400",
    "addr:housenumber":"9",
    "addr:postcode":"8400",
    "addr:street":"Sint-Niklaasstraat",
    "iso:country":"BE",
    "sg:address":"Sint-niklaasstraat 9",
    "sg:city":"Oostende",
    "sg:orig_category":"Bars Fast food and meeneem restaurants Levering aan huis restaurants Restaurants",
    "sg:phone":"+32 59 80 92 77",
    "sg:postcode":"8400",
    "sg:province":"West-Vlaanderen",
    "wof:name":"Godetia Restaurant- Wijnbar",
    "wof:placetype":"venue"
},
  "geometry": {"coordinates":[2.9174859524,51.2338027954],"type":"Point"}
}