{
  "type": "Feature",
  "properties": {
    "addr:full":"Molenstraat 11 Maasmechelen (meeswijk) Limburg 3630",
    "addr:housenumber":"11",
    "addr:postcode":"3630",
    "addr:street":"Molenstraat",
    "iso:country":"BE",
    "sg:address":"Molenstraat 11",
    "sg:city":"Maasmechelen (meeswijk)",
    "sg:classifiers":[
        {
            "category":"Health Services",
            "subcategory":"Doctor",
            "type":"Services"
        }
    ],
    "sg:phone":"+32 89 79 24 76",
    "sg:postcode":"3630",
    "sg:province":"Limburg",
    "sg:tags":[
        "medicinephysicians",
        "surgeon"
    ],
    "wof:name":"Claessens L",
    "wof:placetype":"venue"
},
  "geometry": {"coordinates":[5.730298996,51.001789093],"type":"Point"}
}