{
  "type": "Feature",
  "properties": {
    "iso:country":"BE",
    "sg:address":"Rue Du Moulin \u00c0 Eau 6",
    "sg:city":"Binche",
    "sg:orig_category":"M\u00e9decins and sp\u00e9cialistes",
    "sg:phone":"+32 64 33 78 90",
    "sg:postcode":"7133",
    "sg:province":"Hainaut",
    "wof:name":"Michel Bughin",
    "wof:placetype":"venue"
},
  "geometry": {"coordinates":[4.2089209557,50.3880348206],"type":"Point"}
}