{
  "type": "Feature",
  "properties": {
    "addr:full":"Moerbroek 15-17 Herenthout Antwerpen 2270",
    "addr:postcode":"15-17;2270",
    "addr:street":"Moerbroek",
    "iso:country":"BE",
    "sg:address":"Moerbroek 15-17",
    "sg:city":"Herenthout",
    "sg:classifiers":[
        {
            "category":"Home & Garden",
            "subcategory":"Building Materials",
            "type":"Retail Goods"
        }
    ],
    "sg:phone":"+32 14 23 35 80",
    "sg:postcode":"2270",
    "sg:province":"Antwerpen",
    "sg:tags":[
        "house"
    ],
    "wof:name":"G & R Bvba",
    "wof:placetype":"venue"
},
  "geometry": {"coordinates":[4.7978601456,51.1535606384],"type":"Point"}
}