{
  "type": "Feature",
  "properties": {
    "iso:country":"BE",
    "sg:address":"Ambachtsweg 22",
    "sg:city":"Merelbeke",
    "sg:orig_category":"Non-Classified Establishments",
    "sg:phone":"+32 9 252 58 88",
    "sg:postcode":"9820",
    "sg:province":"Oost-Vlaanderen",
    "wof:name":"B-tech Sa",
    "wof:placetype":"venue"
},
  "geometry": {"coordinates":[3.7625639439,50.9927787781],"type":"Point"}
}