{
  "type": "Feature",
  "properties": {
    "addr:full":"Rue Du Gros M\u00c9dart 6 Chaumont-gistoux Brabant Wallon 1325",
    "addr:housenumber":"6",
    "addr:postcode":"1325",
    "addr:street":"Rue Du Gros Me\u0301Dart",
    "iso:country":"BE",
    "sg:address":"Rue Du Gros M\u00c9dart 6",
    "sg:city":"Chaumont-gistoux",
    "sg:orig_category":"Mat\u00e9riel m\u00e9dical and orthop\u00e9dique and proth\u00e8ses Fab",
    "sg:phone":"+32 10 68 05 00",
    "sg:postcode":"1325",
    "sg:province":"Brabant Wallon",
    "wof:name":"Van Ackere",
    "wof:placetype":"venue"
},
  "geometry": {"coordinates":[4.715157032,50.6796607971],"type":"Point"}
}