{
  "type": "Feature",
  "properties": {
    "addr:full":"Grand-place 9 Renaix Oost-Vlaanderen 9600",
    "addr:housenumber":"9",
    "addr:postcode":"9600",
    "addr:street":"Grand-Place",
    "iso:country":"BE",
    "sg:address":"Grand-place 9",
    "sg:city":"Renaix",
    "sg:classifiers":[
        {
            "category":"Bars & Pubs",
            "type":"Food & Drink"
        }
    ],
    "sg:phone":"+32 55 21 18 68",
    "sg:postcode":"9600",
    "sg:province":"Oost-Vlaanderen",
    "wof:name":"Pinel",
    "wof:placetype":"venue"
},
  "geometry": {"coordinates":[3.6018919945,50.7478981018],"type":"Point"}
}