{
  "type": "Feature",
  "properties": {
    "addr:full":"Ninoofsesteenweg 152 Pepingen Vlaams-Brabant 1670",
    "addr:housenumber":"152",
    "addr:postcode":"1670",
    "addr:street":"Ninoofsesteenweg",
    "iso:country":"BE",
    "sg:address":"Ninoofsesteenweg 152",
    "sg:city":"Pepingen",
    "sg:classifiers":[
        {
            "category":"Shopping",
            "subcategory":"Bicycles & Sporting Goods",
            "type":"Retail Goods"
        }
    ],
    "sg:phone":"+32 2 361 37 67",
    "sg:postcode":"1670",
    "sg:province":"Vlaams-Brabant",
    "sg:tags":[
        "-"
    ],
    "wof:name":"De Weghe L",
    "wof:placetype":"venue"
},
  "geometry": {"coordinates":[4.1551380157,50.7597465515],"type":"Point"}
}