{
  "type": "Feature",
  "properties": {
    "iso:country":"BE",
    "sg:address":"Smederijstraat 24",
    "sg:city":"Brecht (sint-job-in-'t Goor)",
    "sg:classifiers":[
        {
            "category":"Professional",
            "type":"Services"
        }
    ],
    "sg:phone":"+32 3 633 88 77",
    "sg:postcode":"2960",
    "sg:province":"Antwerpen",
    "sg:tags":[
        "forwarding",
        "agency"
    ],
    "wof:name":"Expedy Bvba",
    "wof:placetype":"venue"
},
  "geometry": {"coordinates":[4.5500807762,51.3004798889],"type":"Point"}
}