{
  "type": "Feature",
  "properties": {
    "addr:full":"Berrebroeckstraat 69 Ninove (groot) Oost-Vlaanderen 9400",
    "addr:housenumber":"69",
    "addr:postcode":"9400",
    "addr:street":"Berrebroeckstraat;Groot Oost-Vlaanderen",
    "iso:country":"BE",
    "sg:address":"Berrebroeckstraat 69",
    "sg:city":"Ninove (groot)",
    "sg:classifiers":[
        {
            "category":"Personal",
            "subcategory":"Beauty Salon",
            "type":"Services"
        }
    ],
    "sg:phone":"+32 54 33 31 29",
    "sg:postcode":"9400",
    "sg:province":"Oost-Vlaanderen",
    "sg:tags":[
        "de",
        "coiffure"
    ],
    "wof:name":"Coiffure Annick",
    "wof:placetype":"venue"
},
  "geometry": {"coordinates":[4.0232000351,50.8349113464],"type":"Point"}
}