{
  "type": "Feature",
  "properties": {
    "iso:country":"BE",
    "sg:address":"Kattestr 36",
    "sg:city":"Aalst (groot)",
    "sg:classifiers":[
        {
            "category":"Personal",
            "subcategory":"Beauty Salon",
            "type":"Services"
        }
    ],
    "sg:phone":"+32 53 21 12 07",
    "sg:postcode":"9300",
    "sg:province":"Oost-Vlaanderen",
    "sg:tags":[
        "de",
        "coiffure"
    ],
    "wof:name":"Olivier Dachkin",
    "wof:placetype":"venue"
},
  "geometry": {"coordinates":[4.037419796,50.9396362305],"type":"Point"}
}