{
  "type": "Feature",
  "properties": {
    "addr:full":"Boulevard Anspach 1 Brussel/bruxelles Bruxelles-Capitale 1000",
    "addr:housenumber":"1",
    "addr:postcode":"1000",
    "addr:street":"Boulevard Anspach;/",
    "iso:country":"BE",
    "sg:address":"Boulevard Anspach 1",
    "sg:city":"Brussel/bruxelles",
    "sg:classifiers":[
        {
            "category":"Insurance",
            "subcategory":"Life Insurance",
            "type":"Services"
        }
    ],
    "sg:phone":"+32 2 549 79 56",
    "sg:postcode":"1000",
    "sg:province":"Bruxelles-Capitale",
    "sg:tags":[
        "assurance"
    ],
    "wof:name":"Viaxis",
    "wof:placetype":"venue"
},
  "geometry": {"coordinates":[4.3520240784,50.8507995605],"type":"Point"}
}