{
  "type": "Feature",
  "properties": {
    "iso:country":"BE",
    "sg:address":"Rue De La Grande Campagne 6",
    "sg:city":"Boussu (hornu)",
    "sg:classifiers":[
        {
            "category":"Professional",
            "subcategory":"Computer Services",
            "type":"Services"
        }
    ],
    "sg:phone":"+32 65 71 52 11",
    "sg:postcode":"7301",
    "sg:province":"Hainaut",
    "sg:tags":[
        "-",
        "processing",
        "data",
        "software"
    ],
    "wof:name":"Cap Gemini Information Systems Management",
    "wof:placetype":"venue"
},
  "geometry": {"coordinates":[3.8257451057,50.4362258911],"type":"Point"}
}