{
  "type": "Feature",
  "properties": {
    "addr:full":"Stationsstraat 6 Kampenhout Vlaams-Brabant 1910",
    "addr:housenumber":"6",
    "addr:postcode":"1910",
    "addr:street":"Stationsstraat",
    "iso:country":"BE",
    "sg:address":"Stationsstraat 6",
    "sg:city":"Kampenhout",
    "sg:orig_category":"Imprimeries and copyshops",
    "sg:phone":"+32 16 65 14 27",
    "sg:postcode":"1910",
    "sg:province":"Vlaams-Brabant",
    "wof:name":"Kampo - Press",
    "wof:placetype":"venue"
},
  "geometry": {"coordinates":[4.5538911819,50.9413909912],"type":"Point"}
}