{
  "type": "Feature",
  "properties": {
    "addr:full":"Middelweg 92 Knesselare Oost-Vlaanderen 9910",
    "addr:housenumber":"92",
    "addr:postcode":"9910",
    "addr:street":"Middelweg;Oost-Vlaanderen",
    "iso:country":"BE",
    "sg:address":"Middelweg 92",
    "sg:city":"Knesselare",
    "sg:orig_category":"Groenten and fruit Gh",
    "sg:phone":"+32 9 374 10 76",
    "sg:postcode":"9910",
    "sg:province":"Oost-Vlaanderen",
    "wof:name":"Bonami",
    "wof:placetype":"venue"
},
  "geometry": {"coordinates":[3.460285902,51.1192779541],"type":"Point"}
}