{
  "type": "Feature",
  "properties": {
    "iso:country":"BE",
    "sg:address":"Heirbaan 286",
    "sg:city":"Hamme",
    "sg:orig_category":"Tweedehandsgoederen",
    "sg:phone":"+32 52 47 07 63",
    "sg:postcode":"9220",
    "sg:province":"Oost-Vlaanderen",
    "wof:name":"Tamytex International",
    "wof:placetype":"venue"
},
  "geometry": {"coordinates":[4.0975170135,51.070854187],"type":"Point"}
}