{
  "type": "Feature",
  "properties": {
    "addr:full":"Rue De La Grotte 1 Bouillon Luxembourg 6830",
    "addr:housenumber":"1",
    "addr:postcode":"6830",
    "addr:street":"Rue De La Grotte",
    "iso:country":"BE",
    "sg:address":"Rue De La Grotte 1",
    "sg:city":"Bouillon",
    "sg:classifiers":[
        {
            "category":"Insurance",
            "subcategory":"Insurance Agent",
            "type":"Services"
        }
    ],
    "sg:phone":"+32 61 46 72 40",
    "sg:postcode":"6830",
    "sg:province":"Luxembourg",
    "sg:tags":[
        "verzekeringsmakelaars",
        "expert"
    ],
    "wof:name":"M. Willeme",
    "wof:placetype":"venue"
},
  "geometry": {"coordinates":[5.0699849129,49.7954597473],"type":"Point"}
}