{
  "type": "Feature",
  "properties": {
    "addr:full":"Rue Guillaume Boline 10 Braives Li\u00e8ge 4260",
    "addr:housenumber":"10",
    "addr:postcode":"4260",
    "addr:street":"Rue Guillaume Boline",
    "iso:country":"BE",
    "sg:address":"Rue Guillaume Boline 10",
    "sg:city":"Braives",
    "sg:orig_category":"Rundveehouders",
    "sg:phone":"+32 19 69 96 33",
    "sg:postcode":"4260",
    "sg:province":"Li\u00e8ge",
    "wof:name":"Jean Dieudonne",
    "wof:placetype":"venue"
},
  "geometry": {"coordinates":[5.1756720543,50.6098937988],"type":"Point"}
}