{
  "type": "Feature",
  "properties": {
    "iso:country":"BE",
    "sg:address":"Herbesthalerstrasse 68",
    "sg:city":"Eupen",
    "sg:classifiers":[
        {
            "category":"Retail",
            "subcategory":"Auto Rental",
            "type":"Services"
        }
    ],
    "sg:phone":"+32 87 59 00 00",
    "sg:postcode":"4700",
    "sg:province":"Li\u00e8ge",
    "sg:tags":[
        "quality",
        "ok",
        "opel",
        "car"
    ],
    "wof:name":"J. Emontspool-eupen",
    "wof:placetype":"venue"
},
  "geometry": {"coordinates":[6.0225949287,50.6350822449],"type":"Point"}
}