{
  "type": "Feature",
  "properties": {
    "addr:full":"Rue Du Buissenet 31 P\u00e9ruwelz (brasmenil) Hainaut 7604",
    "addr:housenumber":"31",
    "addr:postcode":"7604",
    "addr:street":"Rue Du Buissenet",
    "iso:country":"BE",
    "sg:address":"Rue Du Buissenet 31",
    "sg:city":"P\u00e9ruwelz (brasmenil)",
    "sg:classifiers":[
        {
            "category":"Professional",
            "subcategory":"Accounting & Tax Preparation",
            "type":"Services"
        }
    ],
    "sg:phone":"+32 69 58 05 21",
    "sg:postcode":"7604",
    "sg:province":"Hainaut",
    "sg:tags":[
        "bookkeeper"
    ],
    "wof:name":"Delattre X",
    "wof:placetype":"venue"
},
  "geometry": {"coordinates":[3.552282095,50.5391273499],"type":"Point"}
}