{
  "type": "Feature",
  "properties": {
    "addr:full":"Rue Ambiorix 68 Li\u00e8ge 1 Li\u00e8ge 4000",
    "addr:housenumber":"68;1",
    "addr:postcode":"4000",
    "addr:street":"Rue Ambiorix",
    "iso:country":"BE",
    "sg:address":"Rue Ambiorix 68",
    "sg:city":"Li\u00e8ge 1",
    "sg:classifiers":[
        {
            "category":"Real Estate",
            "subcategory":"Surveying",
            "type":"Services"
        }
    ],
    "sg:phone":"+32 4 253 53 14",
    "sg:postcode":"4000",
    "sg:province":"Li\u00e8ge",
    "sg:tags":[
        "lettering",
        "letter"
    ],
    "wof:name":"Dardenne L",
    "wof:placetype":"venue"
},
  "geometry": {"coordinates":[5.5599179268,50.6299362183],"type":"Point"}
}