{
  "type": "Feature",
  "properties": {
    "addr:full":"Stokkelse Steenweg 280 Sint-lambrechts-woluwe/woluwe-saint-lambert Bruxelles-Capitale 1200",
    "addr:housenumber":"280",
    "addr:postcode":"1200",
    "addr:street":"Stokkelse Steenweg",
    "iso:country":"BE",
    "sg:address":"Stokkelse Steenweg 280",
    "sg:city":"Sint-lambrechts-woluwe/woluwe-saint-lambert",
    "sg:orig_category":"Huishoudapparaten, televisies and radio's",
    "sg:phone":"+32 2 770 91 25",
    "sg:postcode":"1200",
    "sg:province":"Bruxelles-Capitale",
    "wof:name":"Norbert Provoost",
    "wof:placetype":"venue"
},
  "geometry": {"coordinates":[4.4497518539,50.841468811],"type":"Point"}
}