{
  "type": "Feature",
  "properties": {
    "addr:full":"Terlicht 104 Haaltert Oost-Vlaanderen 9451",
    "addr:housenumber":"104",
    "addr:postcode":"9451",
    "addr:street":"Terlicht",
    "iso:country":"BE",
    "sg:address":"Terlicht 104",
    "sg:city":"Haaltert",
    "sg:orig_category":"Fabrication and montage de mobilier",
    "sg:phone":"+32 53 83 33 83",
    "sg:postcode":"9451",
    "sg:province":"Oost-Vlaanderen",
    "wof:name":"Guy Wynant",
    "wof:placetype":"venue"
},
  "geometry": {"coordinates":[3.9754369259,50.8813018799],"type":"Point"}
}