{
  "type": "Feature",
  "properties": {
    "addr:full":"All\u00e9e Saint-hubert 6 Gerpinnes (loverval) Hainaut 6280",
    "addr:housenumber":"6",
    "addr:postcode":"6280",
    "addr:street":"Alle\u0301E Saint-Hubert",
    "iso:country":"BE",
    "sg:address":"All\u00e9e Saint-hubert 6",
    "sg:city":"Gerpinnes (loverval)",
    "sg:classifiers":[
        {
            "category":"Health Services",
            "subcategory":"Doctor",
            "type":"Services"
        }
    ],
    "sg:phone":"+32 71 47 26 11",
    "sg:postcode":"6280",
    "sg:province":"Hainaut",
    "sg:tags":[
        "medicinephysicians",
        "surgeon"
    ],
    "wof:name":"Fievet D",
    "wof:placetype":"venue"
},
  "geometry": {"coordinates":[4.4723238945,50.3764305115],"type":"Point"}
}