{
  "type": "Feature",
  "properties": {
    "iso:country":"BE",
    "sg:address":"Rue De Quaregnon 31",
    "sg:city":"Mons",
    "sg:orig_category":"Bloemen and planten",
    "sg:phone":"+32 65 82 36 22",
    "sg:postcode":"7012",
    "sg:province":"Hainaut",
    "wof:name":"Maison Gueret J. & Fils",
    "wof:placetype":"venue"
},
  "geometry": {"coordinates":[3.8846271038,50.4185256958],"type":"Point"}
}