{
  "type": "Feature",
  "properties": {
    "iso:country":"BE",
    "sg:address":"Avenue Du Bois De La Cambre 49",
    "sg:city":"Elsene/ixelles",
    "sg:orig_category":"RESTAURANTS: POUR COLLECTIVIT\u00c9S. EQUIPEMENT DIVERS POUR COMMERCES LOCATION DE MAT\u00c9RIEL POUR BANQUETS",
    "sg:phone":"+32 2 672 78 64",
    "sg:postcode":"1050",
    "sg:province":"Bruxelles-Capitale",
    "wof:name":"Rouge, Noir Et Rose",
    "wof:placetype":"venue"
},
  "geometry": {"coordinates":[4.3951649666,50.8093528748],"type":"Point"}
}