{
  "type": "Feature",
  "properties": {
    "addr:full":"Avenue Du Prince D'orange 152 Bruxelles (uccle) Bruxelles-Capitale 1180",
    "addr:housenumber":"152",
    "addr:postcode":"1180",
    "addr:street":"Avenue Du Prince D'Orange",
    "iso:country":"BE",
    "sg:address":"Avenue Du Prince D'orange 152",
    "sg:city":"Bruxelles (uccle)",
    "sg:classifiers":[
        {
            "category":"Health Services",
            "subcategory":"Doctor",
            "type":"Services"
        }
    ],
    "sg:phone":"+32 2 372 01 37",
    "sg:postcode":"1180",
    "sg:province":"Bruxelles-Capitale",
    "sg:tags":[
        "medicinephysicians",
        "surgeon"
    ],
    "wof:name":"Baudrihaye M",
    "wof:placetype":"venue"
},
  "geometry": {"coordinates":[4.3628559113,50.7800254822],"type":"Point"}
}