{
  "type": "Feature",
  "properties": {
    "addr:full":"Buizegemlei 41 Edegem Antwerpen 2650",
    "addr:housenumber":"41",
    "addr:postcode":"2650",
    "addr:street":"Buizegemlei",
    "iso:country":"BE",
    "sg:address":"Buizegemlei 41",
    "sg:city":"Edegem",
    "sg:orig_category":"Vitrage",
    "sg:phone":"+32 3 457 37 15",
    "sg:postcode":"2650",
    "sg:province":"Antwerpen",
    "wof:name":"Calders A.",
    "wof:placetype":"venue"
},
  "geometry": {"coordinates":[4.4530677795,51.1500091553],"type":"Point"}
}