{
  "type": "Feature",
  "properties": {
    "iso:country":"BE",
    "sg:address":"Kiezegemstraat 3",
    "sg:city":"Tielt-winge (sint-joris-winge)",
    "sg:classifiers":[
        {
            "category":"Building & Trades",
            "subcategory":"Landscaping Services",
            "type":"Services"
        }
    ],
    "sg:phone":"+32 16 63 17 49",
    "sg:postcode":"3390",
    "sg:province":"Vlaams-Brabant",
    "sg:tags":[
        "gardening",
        "garden",
        "maintenance"
    ],
    "wof:name":"Dewit W",
    "wof:placetype":"venue"
},
  "geometry": {"coordinates":[4.8854560852,50.9009513855],"type":"Point"}
}