{
  "type": "Feature",
  "properties": {
    "addr:full":"Boogstraat 26 Zoersel Antwerpen 2980",
    "addr:housenumber":"26",
    "addr:postcode":"2980",
    "addr:street":"Boogstraat",
    "iso:country":"BE",
    "sg:address":"Boogstraat 26",
    "sg:city":"Zoersel",
    "sg:orig_category":"Advocaten and juridische adviseurs",
    "sg:phone":"+32 3 312 17 47",
    "sg:postcode":"2980",
    "sg:province":"Antwerpen",
    "wof:name":"Michael Olislaegers",
    "wof:placetype":"venue"
},
  "geometry": {"coordinates":[4.7084150314,51.2721443176],"type":"Point"}
}