{
  "type": "Feature",
  "properties": {
    "iso:country":"BE",
    "sg:address":"Rue De L\u00b4association 44ba",
    "sg:city":"Brussel/bruxelles",
    "sg:classifiers":[
        {
            "category":"Insurance",
            "subcategory":"Life Insurance",
            "type":"Services"
        }
    ],
    "sg:phone":"+32 2 210 82 11",
    "sg:postcode":"1000",
    "sg:province":"Bruxelles-Capitale",
    "sg:tags":[
        "assurance"
    ],
    "wof:name":"A.d.d.",
    "wof:placetype":"venue"
},
  "geometry": {"coordinates":[4.3661899567,50.8505592346],"type":"Point"}
}