{
  "type": "Feature",
  "properties": {
    "addr:full":"Beselarestraat 195 Zonnebeke West-Vlaanderen 8980",
    "addr:housenumber":"195",
    "addr:postcode":"8980",
    "addr:street":"Beselarestraat",
    "iso:country":"BE",
    "sg:address":"Beselarestraat 195",
    "sg:city":"Zonnebeke",
    "sg:orig_category":"V\u00e9los",
    "sg:phone":"+32 57 46 62 06",
    "sg:postcode":"8980",
    "sg:province":"West-Vlaanderen",
    "wof:name":"Dirk Depla",
    "wof:placetype":"venue"
},
  "geometry": {"coordinates":[3.0097019672,50.8606758118],"type":"Point"}
}