{
  "type": "Feature",
  "properties": {
    "iso:country":"BE",
    "sg:address":"Familie De Bayostraat 37",
    "sg:city":"Leuven",
    "sg:classifiers":[
        {
            "category":"Food & Beverages",
            "subcategory":"Groceries & Convenience Stores",
            "type":"Retail Goods"
        }
    ],
    "sg:phone":"+32 16 22 65 80",
    "sg:postcode":"3000",
    "sg:province":"Vlaams-Brabant",
    "sg:tags":[
        "grocer"
    ],
    "wof:name":"Vitamientje (het)",
    "wof:placetype":"venue"
},
  "geometry": {"coordinates":[4.7049350739,50.8696403503],"type":"Point"}
}