{
  "type": "Feature",
  "properties": {
    "iso:country":"BE",
    "sg:address":"Rue De L'industrie 234",
    "sg:city":"Frameries (la Bouverie)",
    "sg:classifiers":[
        {
            "category":"Retail",
            "subcategory":"Auto Repair",
            "type":"Services"
        }
    ],
    "sg:phone":"+32 65 67 13 07",
    "sg:postcode":"7080",
    "sg:province":"Hainaut",
    "sg:tags":[
        "garage"
    ],
    "wof:name":"Du Grand Trait (garage) Sc",
    "wof:placetype":"venue"
},
  "geometry": {"coordinates":[3.8837940693,50.4085578918],"type":"Point"}
}