{
  "type": "Feature",
  "properties": {
    "addr:full":"Rue Du Four 10 Braine L'alleud (braine-l'alleud) Brabant Wallon 1420",
    "addr:housenumber":"10",
    "addr:postcode":"1420",
    "addr:street":"Rue Du Four",
    "iso:country":"BE",
    "sg:address":"Rue Du Four 10",
    "sg:city":"Braine L'alleud (braine-l'alleud)",
    "sg:classifiers":[
        {
            "category":"Parking",
            "subcategory":"Lot",
            "type":"Transportation"
        }
    ],
    "sg:phone":"+32 2 385 00 46",
    "sg:postcode":"1420",
    "sg:province":"Brabant Wallon",
    "sg:tags":[
        "parking-places",
        "laying-out"
    ],
    "wof:name":"Jardinor",
    "wof:placetype":"venue"
},
  "geometry": {"coordinates":[-75.60595703120001,37.7877616882],"type":"Point"}
}