{
  "type": "Feature",
  "properties": {
    "addr:full":"Binnenhof 13 Menen West-Vlaanderen 8930",
    "addr:housenumber":"13",
    "addr:postcode":"8930",
    "addr:street":"Binnenhof",
    "iso:country":"BE",
    "sg:address":"Binnenhof 13",
    "sg:city":"Menen",
    "sg:orig_category":"Marketingbureaus Reclamebureaus",
    "sg:phone":"+32 56 51 19 37",
    "sg:postcode":"8930",
    "sg:province":"West-Vlaanderen",
    "wof:name":"Integrated Market. Comm.",
    "wof:placetype":"venue"
},
  "geometry": {"coordinates":[3.1092629433,50.7967948914],"type":"Point"}
}