{
  "type": "Feature",
  "properties": {
    "iso:country":"BE",
    "sg:address":"Rue De Sars 5bbis",
    "sg:city":"Quevy",
    "sg:classifiers":[
        {
            "category":"Cafe",
            "type":"Food & Drink"
        }
    ],
    "sg:phone":"+32 65 56 94 33",
    "sg:postcode":"7040",
    "sg:province":"Hainaut",
    "sg:tags":[
        "caf\u00e9s"
    ],
    "wof:name":"Salle Omnisport Severijns",
    "wof:placetype":"venue"
},
  "geometry": {"coordinates":[3.8934669495,50.3579216003],"type":"Point"}
}