{
  "type": "Feature",
  "properties": {
    "iso:country":"BE",
    "sg:address":"Kemmelstraat 58",
    "sg:city":"Heuvelland",
    "sg:classifiers":[
        {
            "category":"Arena",
            "subcategory":"Sports Club",
            "type":"Entertainment"
        }
    ],
    "sg:phone":"+32 57 44 52 48",
    "sg:postcode":"8956",
    "sg:province":"West-Vlaanderen",
    "sg:tags":[
        "de"
    ],
    "wof:name":"V.c. Avanti Loker",
    "wof:placetype":"venue"
},
  "geometry": {"coordinates":[2.8472409248,50.7955970764],"type":"Point"}
}