{
  "type": "Feature",
  "properties": {
    "addr:full":"Sint-gillisplein 13 Tienen Vlaams-Brabant 3300",
    "addr:housenumber":"13",
    "addr:postcode":"3300",
    "addr:street":"Sint-Gillisplein",
    "iso:country":"BE",
    "sg:address":"Sint-gillisplein 13",
    "sg:city":"Tienen",
    "sg:orig_category":"Banques and organismes de cr\u00e9dit. Assurances",
    "sg:phone":"+32 16 82 28 23",
    "sg:postcode":"3300",
    "sg:province":"Vlaams-Brabant",
    "wof:name":"Groep Argenta",
    "wof:placetype":"venue"
},
  "geometry": {"coordinates":[4.8875489235,50.8195228577],"type":"Point"}
}