{
  "type": "Feature",
  "properties": {
    "addr:full":"Rue De Merbes 10 Binche Hainaut 7130",
    "addr:housenumber":"10",
    "addr:postcode":"7130",
    "addr:street":"Rue De Merbes",
    "iso:country":"BE",
    "sg:address":"Rue De Merbes 10",
    "sg:city":"Binche",
    "sg:classifiers":[
        {
            "category":"Autos & Motor Vehicles",
            "subcategory":"Motorcycle Sales",
            "type":"Retail Goods"
        }
    ],
    "sg:phone":"+32 64 33 60 40",
    "sg:postcode":"7130",
    "sg:province":"Hainaut",
    "sg:tags":[
        "motorbike"
    ],
    "wof:name":"Laffineur L",
    "wof:placetype":"venue"
},
  "geometry": {"coordinates":[4.1711401939,50.4110565186],"type":"Point"}
}