{
  "type": "Feature",
  "properties": {
    "addr:full":"Rue Des Viviers 38 Erquelinnes Hainaut 6560",
    "addr:housenumber":"38",
    "addr:postcode":"6560",
    "addr:street":"Rue Des Viviers",
    "iso:country":"BE",
    "sg:address":"Rue Des Viviers 38",
    "sg:city":"Erquelinnes",
    "sg:orig_category":"Dierenartsen",
    "sg:phone":"+32 71 55 65 92",
    "sg:postcode":"6560",
    "sg:province":"Hainaut",
    "wof:name":"Jean-pierre Libotte",
    "wof:placetype":"venue"
},
  "geometry": {"coordinates":[4.1148209572,50.3143043518],"type":"Point"}
}