{
  "type": "Feature",
  "properties": {
    "iso:country":"BE",
    "sg:address":"Rue Ferrer 119",
    "sg:city":"Manage",
    "sg:orig_category":"Boucheries",
    "sg:phone":"+32 64 22 19 13",
    "sg:postcode":"7170",
    "sg:province":"Hainaut",
    "wof:name":"Stephane Herregodts",
    "wof:placetype":"venue"
},
  "geometry": {"coordinates":[4.2357521057,50.473991394],"type":"Point"}
}