{
  "type": "Feature",
  "properties": {
    "addr:full":"Kerkstraat 45 Ieper West-Vlaanderen 8900",
    "addr:housenumber":"45",
    "addr:postcode":"8900",
    "addr:street":"Kerkstraat",
    "iso:country":"BE",
    "sg:address":"Kerkstraat 45",
    "sg:city":"Ieper",
    "sg:orig_category":"Eleveurs de bovins. Eleveurs and marchands de porcs",
    "sg:phone":"+32 57 20 15 31",
    "sg:postcode":"8900",
    "sg:province":"West-Vlaanderen",
    "wof:name":"Walter Wicke",
    "wof:placetype":"venue"
},
  "geometry": {"coordinates":[2.8314640522,50.8123435974],"type":"Point"}
}