{
  "type": "Feature",
  "properties": {
    "addr:full":"Kortrijksesteenweg 17 Sint-martens-latem Oost-Vlaanderen 9830",
    "addr:housenumber":"17",
    "addr:postcode":"9830",
    "addr:street":"Kortrijksesteenweg",
    "iso:country":"BE",
    "sg:address":"Kortrijksesteenweg 17",
    "sg:city":"Sint-martens-latem",
    "sg:classifiers":[
        {
            "category":"Fast Food",
            "type":"Food & Drink"
        }
    ],
    "sg:phone":"+32 9 282 82 85",
    "sg:postcode":"9830",
    "sg:province":"Oost-Vlaanderen",
    "sg:tags":[
        "\u00c0",
        "restaurants",
        "emporter",
        "restaurant"
    ],
    "wof:name":"Tampopo",
    "wof:placetype":"venue"
},
  "geometry": {"coordinates":[3.6476809978,51.0138053894],"type":"Point"}
}