{
  "type": "Feature",
  "properties": {
    "iso:country":"BE",
    "sg:address":"Hoofdstraat 39",
    "sg:city":"Hechtel-eksel (eksel)",
    "sg:classifiers":[
        {
            "category":"Bars & Pubs",
            "type":"Food & Drink"
        }
    ],
    "sg:phone":"+32 11 73 62 22",
    "sg:postcode":"3941",
    "sg:province":"Limburg",
    "wof:name":"Magazijn ('t)",
    "wof:placetype":"venue"
},
  "geometry": {"coordinates":[5.3887009621,51.1502761841],"type":"Point"}
}