{
  "type": "Feature",
  "properties": {
    "iso:country":"BE",
    "sg:address":"Vremdesesteenweg 27",
    "sg:city":"Boechout",
    "sg:orig_category":"Woningbouw",
    "sg:phone":"+32 3 455 10 41",
    "sg:postcode":"2530",
    "sg:province":"Antwerpen",
    "wof:name":"Fonteyn",
    "wof:placetype":"venue"
},
  "geometry": {"coordinates":[4.5016260147,51.1649017334],"type":"Point"}
}