{
  "type": "Feature",
  "properties": {
    "iso:country":"BE",
    "sg:address":"Pater Domstraat 43",
    "sg:city":"Ranst",
    "sg:orig_category":"DIVERSE RECREATIEVE ACTIVITEITEN",
    "sg:phone":"+32 3 485 71 01",
    "sg:postcode":"2520",
    "sg:province":"Antwerpen",
    "wof:name":"Kon. Postzegelverz. Lier",
    "wof:placetype":"venue"
},
  "geometry": {"coordinates":[4.6062049866,51.1854743958],"type":"Point"}
}