{
  "type": "Feature",
  "properties": {
    "iso:country":"BE",
    "sg:address":"Vossensteert 1",
    "sg:city":"Brugge",
    "sg:orig_category":"Slagers",
    "sg:phone":"+32 50 35 03 72",
    "sg:postcode":"8310",
    "sg:province":"West-Vlaanderen",
    "wof:name":"Slagerij De Vossenhoek",
    "wof:placetype":"venue"
},
  "geometry": {"coordinates":[3.2551789284,51.202129364],"type":"Point"}
}