{
  "type": "Feature",
  "properties": {
    "addr:full":"Route De Val-dieu 30 Aubel Li\u00e8ge 4880",
    "addr:housenumber":"30",
    "addr:postcode":"4880",
    "addr:street":"Route De Val-Dieu",
    "iso:country":"BE",
    "sg:address":"Route De Val-dieu 30",
    "sg:city":"Aubel",
    "sg:classifiers":[
        {
            "category":"Arena",
            "subcategory":"Sports Club",
            "type":"Entertainment"
        }
    ],
    "sg:phone":"+32 87 68 85 43",
    "sg:postcode":"4880",
    "sg:province":"Li\u00e8ge",
    "sg:tags":[
        "terrain",
        "hors",
        "de",
        "installation",
        "sportifs"
    ],
    "wof:name":"R. Aubel F.c.",
    "wof:placetype":"venue"
},
  "geometry": {"coordinates":[5.8519501686,50.7088012695],"type":"Point"}
}