{
  "type": "Feature",
  "properties": {
    "addr:full":"Kouterveldstraat 4 Diegem Vlaams-Brabant 1831",
    "addr:housenumber":"4",
    "addr:postcode":"1831",
    "addr:street":"Kouterveldstraat",
    "iso:country":"BE",
    "sg:address":"Kouterveldstraat 4",
    "sg:city":"Diegem",
    "sg:classifiers":[
        {
            "category":"Retail",
            "subcategory":"Auto Rental",
            "type":"Services"
        }
    ],
    "sg:phone":"+32 2 672 38 01",
    "sg:postcode":"1831",
    "sg:province":"Vlaams-Brabant",
    "sg:tags":[
        "chauffeur",
        "automobile",
        "driven",
        "-",
        "car"
    ],
    "wof:name":"Pulmino Coaches Sprl",
    "wof:placetype":"venue"
},
  "geometry": {"coordinates":[4.4359431267,50.8944854736],"type":"Point"}
}