{
  "type": "Feature",
  "properties": {
    "iso:country":"BE",
    "sg:address":"Moeskroenstraat 687-689",
    "sg:city":"Menen",
    "sg:orig_category":"V\u00e9hicules automobiles",
    "sg:phone":"+32 56 41 24 93",
    "sg:postcode":"8930",
    "sg:province":"West-Vlaanderen",
    "wof:name":"William Devos",
    "wof:placetype":"venue"
},
  "geometry": {"coordinates":[3.1586298943,50.787361145],"type":"Point"}
}