{
  "type": "Feature",
  "properties": {
    "iso:country":"BE",
    "sg:address":"Kouterken 9",
    "sg:city":"Nevele",
    "sg:orig_category":"Kapsalons",
    "sg:phone":"+32 9 371 94 67",
    "sg:postcode":"9850",
    "sg:province":"Oost-Vlaanderen",
    "wof:name":"Aniana De Ketelaere",
    "wof:placetype":"venue"
},
  "geometry": {"coordinates":[3.534168005,51.0858268738],"type":"Point"}
}