{
  "type": "Feature",
  "properties": {
    "addr:full":"Suikerrui 30 Antwerpen Antwerpen 2000",
    "addr:housenumber":"30",
    "addr:postcode":"2000",
    "addr:street":"Suikerrui",
    "iso:country":"BE",
    "sg:address":"Suikerrui 30",
    "sg:city":"Antwerpen",
    "sg:classifiers":[
        {
            "category":"Restaurant",
            "type":"Food & Drink"
        }
    ],
    "sg:phone":"+32 3 232 03 40",
    "sg:postcode":"2000",
    "sg:province":"Antwerpen",
    "wof:name":"La Gondola",
    "wof:placetype":"venue"
},
  "geometry": {"coordinates":[4.3987460136,51.2207260132],"type":"Point"}
}