{
  "type": "Feature",
  "properties": {
    "addr:full":"Oostmalsesteenweg 93 Rijkevorsel Antwerpen 2310",
    "addr:housenumber":"93",
    "addr:postcode":"2310",
    "addr:street":"Oostmalsesteenweg",
    "iso:country":"BE",
    "sg:address":"Oostmalsesteenweg 93",
    "sg:city":"Rijkevorsel",
    "sg:classifiers":[
        {
            "category":"Cafe",
            "type":"Food & Drink"
        }
    ],
    "sg:phone":"+32 3 314 79 67",
    "sg:postcode":"2310",
    "sg:province":"Antwerpen",
    "sg:tags":[
        "caf\u00e9s"
    ],
    "wof:name":"Brouwershuis",
    "wof:placetype":"venue"
},
  "geometry": {"coordinates":[4.7566599846,51.3432426453],"type":"Point"}
}