{
  "type": "Feature",
  "properties": {
    "iso:country":"BE",
    "sg:address":"Oudemanstraat 15",
    "sg:city":"Londerzeel",
    "sg:classifiers":[
        {
            "category":"Building & Trades",
            "subcategory":"Plumbing",
            "type":"Services"
        }
    ],
    "sg:phone":"+32 3 366 46 46",
    "sg:postcode":"1840",
    "sg:province":"Vlaams-Brabant",
    "sg:tags":[
        "sale",
        "distributors"
    ],
    "wof:name":"Wetram Nv",
    "wof:placetype":"venue"
},
  "geometry": {"coordinates":[4.4604558945,51.2117652893],"type":"Point"}
}