{
  "type": "Feature",
  "properties": {
    "iso:country":"BE",
    "sg:address":"Koetsiersweg 67",
    "sg:city":"Lubbeek",
    "sg:orig_category":"Experts-comptables",
    "sg:phone":"+32 16 25 41 70",
    "sg:postcode":"3210",
    "sg:province":"Vlaams-Brabant",
    "wof:name":"A. Boelen",
    "wof:placetype":"venue"
},
  "geometry": {"coordinates":[4.7567830086,50.9007949829],"type":"Point"}
}