{
  "type": "Feature",
  "properties": {
    "addr:full":"Rue Du Ch\u00c2teau D'or 1 Ukkel/uccle Bruxelles-Capitale 1180",
    "addr:housenumber":"1",
    "addr:postcode":"1180",
    "addr:street":"Rue Du Cha\u0302Teau D'Or;/",
    "iso:country":"BE",
    "sg:address":"Rue Du Ch\u00c2teau D'or 1",
    "sg:city":"Ukkel/uccle",
    "sg:orig_category":"Benzinestations and brandstoffen Herstellingen and onderhoud van auto's",
    "sg:phone":"+32 2 376 21 92",
    "sg:postcode":"1180",
    "sg:province":"Bruxelles-Capitale",
    "wof:name":"Texaco",
    "wof:placetype":"venue"
},
  "geometry": {"coordinates":[4.3627800941,50.7902793884],"type":"Point"}
}