{
  "type": "Feature",
  "properties": {
    "iso:country":"BE",
    "sg:address":"Rue Du Waux-hall 5",
    "sg:city":"Spa",
    "sg:orig_category":"Foto-uitrusting Fotografen and fotostudio's",
    "sg:phone":"+32 87 77 42 16",
    "sg:postcode":"4900",
    "sg:province":"Li\u00e8ge",
    "wof:name":"Bontems Photos",
    "wof:placetype":"venue"
},
  "geometry": {"coordinates":[5.8679389954,50.4889984131],"type":"Point"}
}