{
  "type": "Feature",
  "properties": {
    "addr:full":"Rue Ferdinand Nicolay 203 Seraing Li\u00e8ge 4102",
    "addr:housenumber":"203",
    "addr:postcode":"4102",
    "addr:street":"Rue Ferdinand Nicolay",
    "iso:country":"BE",
    "sg:address":"Rue Ferdinand Nicolay 203",
    "sg:city":"Seraing",
    "sg:classifiers":[
        {
            "category":"Personal",
            "subcategory":"Beauty Salon",
            "type":"Services"
        }
    ],
    "sg:phone":"+32 4 337 60 34",
    "sg:postcode":"4102",
    "sg:province":"Li\u00e8ge",
    "sg:tags":[
        "de",
        "coiffure"
    ],
    "wof:name":"Coiffure Cr\u00c9ation",
    "wof:placetype":"venue"
},
  "geometry": {"coordinates":[5.5409698486,50.6042289734],"type":"Point"}
}