{
  "type": "Feature",
  "properties": {
    "iso:country":"BE",
    "sg:address":"Chauss\u00c9e De Jodoigne 2",
    "sg:city":"Incourt",
    "sg:classifiers":[
        {
            "category":"Restaurant",
            "type":"Food & Drink"
        }
    ],
    "sg:phone":"+32 10 88 90 17",
    "sg:postcode":"1315",
    "sg:province":"Brabant Wallon",
    "wof:name":"Le Jardin Des Gourmandises",
    "wof:placetype":"venue"
},
  "geometry": {"coordinates":[4.8261160851,50.6723327637],"type":"Point"}
}