{
  "type": "Feature",
  "properties": {
    "addr:full":"Grand Rue Chimay Hainaut 6460",
    "addr:postcode":"6460",
    "addr:street":"Grand Rue Chimay Hainaut",
    "iso:country":"BE",
    "sg:address":"Grand Rue",
    "sg:city":"Chimay",
    "sg:orig_category":"Tijdelijke werkgelegenheid and uitzendkantoren",
    "sg:phone":"+32 60 21 42 44",
    "sg:postcode":"6460",
    "sg:province":"Hainaut",
    "wof:name":"Randstad",
    "wof:placetype":"venue"
},
  "geometry": {"coordinates":[4.3146958351,50.0486946106],"type":"Point"}
}