{
  "type": "Feature",
  "properties": {
    "iso:country":"BE",
    "sg:address":"Tongersesteenweg 231",
    "sg:city":"Sint-truiden",
    "sg:orig_category":"Fruitteelt",
    "sg:phone":"+32 11 68 08 27",
    "sg:postcode":"3800",
    "sg:province":"Limburg",
    "wof:name":"Greta Swennen",
    "wof:placetype":"venue"
},
  "geometry": {"coordinates":[5.2143378258,50.8103065491],"type":"Point"}
}