{
  "type": "Feature",
  "properties": {
    "addr:full":"Tongersestraat 1 Bilzen Limburg 3740",
    "addr:housenumber":"1",
    "addr:postcode":"3740",
    "addr:street":"Tongersestraat",
    "iso:country":"BE",
    "sg:address":"Tongersestraat 1",
    "sg:city":"Bilzen",
    "sg:orig_category":"Epiceries",
    "sg:phone":"+32 89 41 20 04",
    "sg:postcode":"3740",
    "sg:province":"Limburg",
    "wof:name":"C. Ruysen",
    "wof:placetype":"venue"
},
  "geometry": {"coordinates":[5.508649826,50.8673782349],"type":"Point"}
}