{
  "type": "Feature",
  "properties": {
    "addr:full":"Rue Saint Gabriel 9 Lille 59800",
    "addr:housenumber":"9",
    "addr:postcode":"59800",
    "addr:street":"Rue Saint Gabriel",
    "iso:country":"BE",
    "sg:address":"Rue Saint Gabriel 9",
    "sg:city":"Lille",
    "sg:classifiers":[
        {
            "category":"Manufacturing",
            "subcategory":"Musical Instruments",
            "type":"Manufacturing & Wholesale Goods"
        }
    ],
    "sg:phone":"+33 3 20 55 57 58",
    "sg:postcode":"59800",
    "sg:tags":[
        "piano"
    ],
    "wof:name":"De Clercq Francis",
    "wof:placetype":"venue"
},
  "geometry": {"coordinates":[3.0802400112,50.6361885071],"type":"Point"}
}