{
  "type": "Feature",
  "properties": {
    "iso:country":"BE",
    "sg:address":"Rue Grande 3",
    "sg:city":"Rouvroy (torgny)",
    "sg:classifiers":[
        {
            "category":"Travel",
            "subcategory":"Resort",
            "type":"Entertainment"
        }
    ],
    "sg:phone":"+32 63 57 79 58",
    "sg:postcode":"6767",
    "sg:province":"Luxembourg",
    "sg:tags":[
        "rental",
        "accomodation",
        "holiday",
        "-"
    ],
    "wof:name":"Romanette (la)",
    "wof:placetype":"venue"
},
  "geometry": {"coordinates":[5.4905800819,49.5384864807],"type":"Point"}
}