{
  "type": "Feature",
  "properties": {
    "addr:full":"Hertog Van Brabantlaan 1 Landen Vlaams-Brabant 3400",
    "addr:housenumber":"1",
    "addr:postcode":"3400",
    "addr:street":"Hertog Van Brabantlaan",
    "iso:country":"BE",
    "sg:address":"Hertog Van Brabantlaan 1",
    "sg:city":"Landen",
    "sg:orig_category":"Artsen and specialisten",
    "sg:phone":"+32 11 88 34 93",
    "sg:postcode":"3400",
    "sg:province":"Vlaams-Brabant",
    "wof:name":"J. Wullaert",
    "wof:placetype":"venue"
},
  "geometry": {"coordinates":[5.0828051567,50.7571220398],"type":"Point"}
}