{
  "type": "Feature",
  "properties": {
    "iso:country":"BE",
    "sg:address":"Kruisabeel 28",
    "sg:city":"Lebbeke",
    "sg:orig_category":"Machines and mat\u00e9riel agricoles Services de Nettoyage and de D\u00e9sinfection",
    "sg:phone":"+32 53 77 19 28",
    "sg:postcode":"9280",
    "sg:province":"Oost-Vlaanderen",
    "wof:name":"Albien De Rauw",
    "wof:placetype":"venue"
},
  "geometry": {"coordinates":[4.0822439194,50.9722938538],"type":"Point"}
}