{
  "type": "Feature",
  "properties": {
    "iso:country":"BE",
    "sg:address":"Rue Du Coll\u00c8ge 27",
    "sg:city":"Elsene/ixelles",
    "sg:orig_category":"Salles de spectacles",
    "sg:phone":"+32 2 647 84 18",
    "sg:postcode":"1050",
    "sg:province":"Bruxelles-Capitale",
    "wof:name":"Colmant Art Gallery",
    "wof:placetype":"venue"
},
  "geometry": {"coordinates":[4.3691830635,50.832321167],"type":"Point"}
}