{
  "type": "Feature",
  "properties": {
    "addr:full":"Rue Des Mainagiers 11 Ath (isi\u00e8res) Hainaut 7822",
    "addr:housenumber":"11",
    "addr:postcode":"7822",
    "addr:street":"Rue Des Mainagiers",
    "iso:country":"BE",
    "sg:address":"Rue Des Mainagiers 11",
    "sg:city":"Ath (isi\u00e8res)",
    "sg:classifiers":[
        {
            "category":"Health Services",
            "subcategory":"Health Practitioner",
            "type":"Services"
        }
    ],
    "sg:phone":"+32 68 28 68 99",
    "sg:postcode":"7822",
    "sg:province":"Hainaut",
    "sg:tags":[
        "therapist",
        "speech"
    ],
    "wof:name":"Jourquin C",
    "wof:placetype":"venue"
},
  "geometry": {"coordinates":[3.8452620506,50.6482391357],"type":"Point"}
}