{
  "type": "Feature",
  "properties": {
    "addr:full":"Mechelbaan 22 Heist-op-den-berg Antwerpen 2221",
    "addr:housenumber":"22",
    "addr:postcode":"2221",
    "addr:street":"Mechelbaan",
    "iso:country":"BE",
    "sg:address":"Mechelbaan 22",
    "sg:city":"Heist-op-den-berg",
    "sg:orig_category":"Benzinestations and brandstoffen Herstellingen and onderhoud van auto's",
    "sg:phone":"+32 15 22 20 54",
    "sg:postcode":"2221",
    "sg:province":"Antwerpen",
    "wof:name":"Fina",
    "wof:placetype":"venue"
},
  "geometry": {"coordinates":[4.7739758492,51.0512428284],"type":"Point"}
}