{
  "type": "Feature",
  "properties": {
    "iso:country":"BE",
    "sg:address":"Stationsstraat 29",
    "sg:city":"Landen",
    "sg:orig_category":"Offices du tourisme",
    "sg:phone":"+32 11 88 03 16",
    "sg:postcode":"3400",
    "sg:province":"Vlaams-Brabant",
    "wof:name":"Dienst Voor Toerisme",
    "wof:placetype":"venue"
},
  "geometry": {"coordinates":[5.0813689232,50.7541885376],"type":"Point"}
}