{
  "type": "Feature",
  "properties": {
    "iso:country":"BE",
    "sg:address":"Avenue C. Thielemans 93",
    "sg:city":"Sint-pieters-woluwe/woluwe-sai",
    "sg:orig_category":"Genealogen",
    "sg:phone":"+32 2 772 50 27",
    "sg:postcode":"1150",
    "sg:province":"Bruxelles-Capitale",
    "wof:name":"Office G\u00c9n\u00c9alogique H\u00c9raldique De Belgique",
    "wof:placetype":"venue"
},
  "geometry": {"coordinates":[4.4274148941,50.8367805481],"type":"Point"}
}