{
  "type": "Feature",
  "properties": {
    "addr:full":"Gampelaeredreef 1 Deinze (groot) Oost-Vlaanderen 9800",
    "addr:housenumber":"1",
    "addr:postcode":"9800",
    "addr:street":"Gampelaeredreef;Groot Oost-Vlaanderen",
    "iso:country":"BE",
    "sg:address":"Gampelaeredreef 1",
    "sg:city":"Deinze (groot)",
    "sg:orig_category":"Supermarkten",
    "sg:phone":"+32 9 386 55 25",
    "sg:postcode":"9800",
    "sg:province":"Oost-Vlaanderen",
    "wof:name":"Colruyt",
    "wof:placetype":"venue"
},
  "geometry": {"coordinates":[3.5481801033,50.9809036255],"type":"Point"}
}