{
  "type": "Feature",
  "properties": {
    "addr:full":"Edward Verheyestraat 14 Knokke-heist West-Vlaanderen 8300",
    "addr:housenumber":"14",
    "addr:postcode":"8300",
    "addr:street":"Verheyestraat",
    "iso:country":"BE",
    "sg:address":"Edward Verheyestraat 14",
    "sg:city":"Knokke-heist",
    "sg:orig_category":"Centres sportifs",
    "sg:phone":"+32 50 63 04 80",
    "sg:postcode":"8300",
    "sg:province":"West-Vlaanderen",
    "wof:name":"Stedelijk Sportcentrum",
    "wof:placetype":"venue"
},
  "geometry": {"coordinates":[3.2896230221,51.3396110535],"type":"Point"}
}