{
  "type": "Feature",
  "properties": {
    "addr:full":"Hall Omnisports De Waterloo Waterloo Brabant Wallon 1410",
    "addr:postcode":"1410",
    "iso:country":"BE",
    "sg:address":"Hall Omnisports De Waterloo",
    "sg:city":"Waterloo",
    "sg:classifiers":[
        {
            "category":"Arena",
            "subcategory":"Sports Club",
            "type":"Entertainment"
        }
    ],
    "sg:phone":"+32 2 384 93 29",
    "sg:postcode":"1410",
    "sg:province":"Brabant Wallon",
    "sg:tags":[
        "de"
    ],
    "wof:name":"Korean Training Center",
    "wof:placetype":"venue"
},
  "geometry": {"coordinates":[4.4130501747,50.7078208923],"type":"Point"}
}