{
  "type": "Feature",
  "properties": {
    "iso:country":"BE",
    "sg:address":"Straatsburgdok-noordkaai 2",
    "sg:city":"Antwerpen",
    "sg:orig_category":"Salles de conf\u00e9rences and de r\u00e9ceptions",
    "sg:phone":"+32 3 541 38 67",
    "sg:postcode":"2030",
    "sg:province":"Antwerpen",
    "wof:name":"Schipperswelzijn",
    "wof:placetype":"venue"
},
  "geometry": {"coordinates":[4.4193887711,51.2422485352],"type":"Point"}
}