{
  "type": "Feature",
  "properties": {
    "addr:full":"Rue Saint-gilles 145 Li\u00e8ge 1 Li\u00e8ge 4000",
    "addr:housenumber":"145;1",
    "addr:postcode":"4000",
    "addr:street":"Rue Saint-Gilles",
    "iso:country":"BE",
    "sg:address":"Rue Saint-gilles 145",
    "sg:city":"Li\u00e8ge 1",
    "sg:classifiers":[
        {
            "category":"Shopping",
            "subcategory":"Gifts & Souvenirs",
            "type":"Retail Goods"
        }
    ],
    "sg:phone":"+32 4 223 68 80",
    "sg:postcode":"4000",
    "sg:province":"Li\u00e8ge",
    "sg:tags":[
        "-"
    ],
    "wof:name":"Andino",
    "wof:placetype":"venue"
},
  "geometry": {"coordinates":[5.5630841255,50.6378746033],"type":"Point"}
}