{
  "type": "Feature",
  "properties": {
    "addr:full":"Dendermondesteenweg 561 Destelbergen Oost-Vlaanderen 9070",
    "addr:housenumber":"561",
    "addr:postcode":"9070",
    "addr:street":"Dendermondesteenweg",
    "iso:country":"BE",
    "sg:address":"Dendermondesteenweg 561",
    "sg:city":"Destelbergen",
    "sg:classifiers":[
        {
            "category":"Wholesale",
            "subcategory":"Medical Equipment & Supplies",
            "type":"Manufacturing & Wholesale Goods"
        }
    ],
    "sg:phone":"+32 9 228 30 64",
    "sg:postcode":"9070",
    "sg:province":"Oost-Vlaanderen",
    "sg:tags":[
        "aid",
        "hearing"
    ],
    "wof:name":"De Merlier",
    "wof:placetype":"venue"
},
  "geometry": {"coordinates":[3.8069849014,51.0572776794],"type":"Point"}
}