{
  "type": "Feature",
  "properties": {
    "addr:full":"Stroekestraat 6 Riemst Limburg 3770",
    "addr:housenumber":"6",
    "addr:postcode":"3770",
    "addr:street":"Stroekestraat",
    "iso:country":"BE",
    "sg:address":"Stroekestraat 6",
    "sg:city":"Riemst",
    "sg:orig_category":"Travaux de pl\u00e2trage",
    "sg:phone":"+32 12 45 48 55",
    "sg:postcode":"3770",
    "sg:province":"Limburg",
    "wof:name":"Albert Froidmont",
    "wof:placetype":"venue"
},
  "geometry": {"coordinates":[5.5896477699,50.7892227173],"type":"Point"}
}