{
  "type": "Feature",
  "properties": {
    "iso:country":"BE",
    "sg:address":"Excelsiorln 45",
    "sg:city":"Zaventem",
    "sg:classifiers":[
        {
            "category":"Government",
            "subcategory":"Department Of Motor Vehicles",
            "type":"Public Place"
        }
    ],
    "sg:phone":"+32 2 725 93 93",
    "sg:postcode":"1930",
    "sg:province":"Vlaams-Brabant",
    "sg:tags":[
        "equipment",
        "industrial",
        "transport",
        "motor-cars"
    ],
    "wof:name":"Premier Industrial Belgium Nv",
    "wof:placetype":"venue"
},
  "geometry": {"coordinates":[4.4531731606,50.8829307556],"type":"Point"}
}