{
  "type": "Feature",
  "properties": {
    "addr:full":"Rue Rabelais 26 Ottignies-louvain-la-neuve (louvain-la-neuve) Brabant Wallon 1348",
    "addr:housenumber":"26",
    "addr:postcode":"1348",
    "addr:street":"Rue Rabelais",
    "iso:country":"BE",
    "sg:address":"Rue Rabelais 26",
    "sg:city":"Ottignies-louvain-la-neuve (louvain-la-neuve)",
    "sg:classifiers":[
        {
            "category":"Bars & Pubs",
            "type":"Food & Drink"
        }
    ],
    "sg:phone":"+32 10 45 12 38",
    "sg:postcode":"1348",
    "sg:province":"Brabant Wallon",
    "wof:name":"1900 (le)",
    "wof:placetype":"venue"
},
  "geometry": {"coordinates":[4.613093853,50.6691589355],"type":"Point"}
}