{
  "type": "Feature",
  "properties": {
    "iso:country":"BE",
    "sg:address":"Rue Du Nord 53",
    "sg:city":"Brussel/bruxelles",
    "sg:orig_category":"RESTAURANTS: LIVRAISON \u00c0 DOMICILE. RESTAURANTS",
    "sg:phone":"+32 2 219 76 85",
    "sg:postcode":"1000",
    "sg:province":"Bruxelles-Capitale",
    "wof:name":"Greedy Lunch",
    "wof:placetype":"venue"
},
  "geometry": {"coordinates":[4.3679060936,50.8505134583],"type":"Point"}
}