{
  "type": "Feature",
  "properties": {
    "addr:full":"Kerkstraat 25 De Haan (wenduine) West-Vlaanderen 8420",
    "addr:housenumber":"25",
    "addr:postcode":"8420",
    "addr:street":"Kerkstraat",
    "iso:country":"BE",
    "sg:address":"Kerkstraat 25",
    "sg:city":"De Haan (wenduine)",
    "sg:classifiers":[
        {
            "category":"Personal",
            "subcategory":"Beauty Salon",
            "type":"Services"
        }
    ],
    "sg:phone":"+32 50 41 21 41",
    "sg:postcode":"8420",
    "sg:province":"West-Vlaanderen",
    "sg:tags":[
        "lady",
        "-",
        "hairdressing"
    ],
    "wof:name":"Andre",
    "wof:placetype":"venue"
},
  "geometry": {"coordinates":[3.080053091,51.3002586365],"type":"Point"}
}