{
  "type": "Feature",
  "properties": {
    "addr:full":"Koningin Elisabethplein 29 Sint-niklaas Oost-Vlaanderen 9100",
    "addr:housenumber":"29",
    "addr:postcode":"9100",
    "addr:street":"Koningin Elisabethplein",
    "iso:country":"BE",
    "sg:address":"Koningin Elisabethplein 29",
    "sg:city":"Sint-niklaas",
    "sg:classifiers":[
        {
            "category":"Health Services",
            "subcategory":"Doctor",
            "type":"Services"
        }
    ],
    "sg:phone":"+32 3 777 11 18",
    "sg:postcode":"9100",
    "sg:province":"Oost-Vlaanderen",
    "sg:tags":[
        "medicinephysicians",
        "surgeon"
    ],
    "wof:name":"Boeckx L",
    "wof:placetype":"venue"
},
  "geometry": {"coordinates":[4.154156208,51.1716575623],"type":"Point"}
}