{
  "type": "Feature",
  "properties": {
    "addr:full":"Rue De Fleurus 9 Sombreffe Namur 5140",
    "addr:housenumber":"9",
    "addr:postcode":"5140",
    "addr:street":"Rue De Fleurus",
    "iso:country":"BE",
    "sg:address":"Rue De Fleurus 9",
    "sg:city":"Sombreffe",
    "sg:orig_category":"Warenhuizen",
    "sg:phone":"+32 71 41 90 79",
    "sg:postcode":"5140",
    "sg:province":"Namur",
    "wof:name":"Willy Devos",
    "wof:placetype":"venue"
},
  "geometry": {"coordinates":[4.6057400703,50.5255966187],"type":"Point"}
}