{
  "type": "Feature",
  "properties": {
    "iso:country":"BE",
    "sg:address":"Rue De L\u00b4atre 2",
    "sg:city":"Mons",
    "sg:orig_category":"Belastingconsulenten Diverse juridische dienstverlening",
    "sg:phone":"+32 65 36 11 07",
    "sg:postcode":"7000",
    "sg:province":"Hainaut",
    "wof:name":"Christophe Duliere",
    "wof:placetype":"venue"
},
  "geometry": {"coordinates":[3.9570720196,50.4550971985],"type":"Point"}
}