{
  "type": "Feature",
  "properties": {
    "iso:country":"BE",
    "sg:address":"Leuvenselaan 59",
    "sg:city":"Tienen",
    "sg:orig_category":"Equipement divers pour commerces Installation de menuiserie en bois and plastique",
    "sg:phone":"+32 16 82 25 95",
    "sg:postcode":"3300",
    "sg:province":"Vlaams-Brabant",
    "wof:name":"Dekeyzer Patrick",
    "wof:placetype":"venue"
},
  "geometry": {"coordinates":[4.9277048111,50.8104667664],"type":"Point"}
}