{
  "type": "Feature",
  "properties": {
    "addr:full":"Rue Des Hiercheuses 4 Charleroi (marcinelle) Hainaut 6001",
    "addr:housenumber":"4",
    "addr:postcode":"6001",
    "addr:street":"Rue Des Hiercheuses",
    "iso:country":"BE",
    "sg:address":"Rue Des Hiercheuses 4",
    "sg:city":"Charleroi (marcinelle)",
    "sg:orig_category":"Non-Classified Establishments",
    "sg:phone":"+32 71 47 27 67",
    "sg:postcode":"6001",
    "sg:province":"Hainaut",
    "wof:name":"Sorescol Services",
    "wof:placetype":"venue"
},
  "geometry": {"coordinates":[4.4400148392,50.3943481445],"type":"Point"}
}