{
  "type": "Feature",
  "properties": {
    "addr:full":"Weynesbaan 67 Bonheiden Antwerpen 2820",
    "addr:housenumber":"67",
    "addr:postcode":"2820",
    "addr:street":"Weynesbaan",
    "iso:country":"BE",
    "sg:address":"Weynesbaan 67",
    "sg:city":"Bonheiden",
    "sg:orig_category":"Gespecialiseerde residenti\u00eble bouw",
    "sg:phone":"+32 15 51 31 17",
    "sg:postcode":"2820",
    "sg:province":"Antwerpen",
    "wof:name":"Louis Cartuyvels",
    "wof:placetype":"venue"
},
  "geometry": {"coordinates":[4.602022171,51.0215835571],"type":"Point"}
}