{
  "type": "Feature",
  "properties": {
    "addr:full":"Collegebaan 19 Melle Oost-Vlaanderen 9090",
    "addr:housenumber":"19",
    "addr:postcode":"9090",
    "addr:street":"Collegebaan",
    "iso:country":"BE",
    "sg:address":"Collegebaan 19",
    "sg:city":"Melle",
    "sg:orig_category":"M\u00e9decins and sp\u00e9cialistes",
    "sg:phone":"+32 9 252 10 56",
    "sg:postcode":"9090",
    "sg:province":"Oost-Vlaanderen",
    "wof:name":"Odette Decraene",
    "wof:placetype":"venue"
},
  "geometry": {"coordinates":[3.8122940063,50.9984703064],"type":"Point"}
}