{
  "type": "Feature",
  "properties": {
    "addr:full":"Rue De L'institut 38 Soumagne (cerexhe-heuseux) Li\u00e8ge 4632",
    "addr:housenumber":"38",
    "addr:postcode":"4632",
    "addr:street":"Rue De L'Institut;Cerexhe-Heuseux",
    "iso:country":"BE",
    "sg:address":"Rue De L'institut 38",
    "sg:city":"Soumagne (cerexhe-heuseux)",
    "sg:classifiers":[
        {
            "category":"Autos & Motor Vehicles",
            "subcategory":"Automobile Sales",
            "type":"Retail Goods"
        }
    ],
    "sg:phone":"+32 4 377 52 33",
    "sg:postcode":"4632",
    "sg:province":"Li\u00e8ge",
    "sg:tags":[
        "car",
        "used",
        "-"
    ],
    "wof:name":"Gregoire",
    "wof:placetype":"venue"
},
  "geometry": {"coordinates":[5.7189922333,50.6556816101],"type":"Point"}
}