{
  "type": "Feature",
  "properties": {
    "addr:full":"Avenue De Stassart 3 Namur Namur 5000",
    "addr:housenumber":"3",
    "addr:postcode":"5000",
    "addr:street":"Avenue De Stassart",
    "iso:country":"BE",
    "sg:address":"Avenue De Stassart 3",
    "sg:city":"Namur",
    "sg:orig_category":"Advocaten and juridische adviseurs",
    "sg:phone":"+32 81 73 57 27",
    "sg:postcode":"5000",
    "sg:province":"Namur",
    "wof:name":"L. Remacle",
    "wof:placetype":"venue"
},
  "geometry": {"coordinates":[4.8552999496,50.4670410156],"type":"Point"}
}