{
  "type": "Feature",
  "properties": {
    "addr:full":"Keizersplein 46 Aalst Oost-Vlaanderen 9300",
    "addr:housenumber":"46",
    "addr:postcode":"9300",
    "addr:street":"Keizersplein",
    "iso:country":"BE",
    "sg:address":"Keizersplein 46",
    "sg:city":"Aalst",
    "sg:orig_category":"Avocats and conseillers juridiques",
    "sg:phone":"+32 53 78 29 20",
    "sg:postcode":"9300",
    "sg:province":"Oost-Vlaanderen",
    "wof:name":"Marc Ghysens",
    "wof:placetype":"venue"
},
  "geometry": {"coordinates":[4.0370550156,50.9364433289],"type":"Point"}
}