{
  "type": "Feature",
  "properties": {
    "addr:full":"Koopvaardijln 44-46 Gent Oost-Vlaanderen 9000",
    "addr:housenumber":"44-46",
    "addr:postcode":"9000",
    "addr:street":"Oost-Vlaanderen",
    "iso:country":"BE",
    "sg:address":"Koopvaardijln 44-46",
    "sg:city":"Gent",
    "sg:classifiers":[
        {
            "category":"Manufacturing",
            "subcategory":"Building Materials",
            "type":"Manufacturing & Wholesale Goods"
        }
    ],
    "sg:phone":"+32 9 223 60 66",
    "sg:postcode":"9000",
    "sg:province":"Oost-Vlaanderen",
    "sg:tags":[
        "glass",
        "ceramic"
    ],
    "wof:name":"J.oosterlinck En Zonen Nv",
    "wof:placetype":"venue"
},
  "geometry": {"coordinates":[3.7390449047,51.0601119995],"type":"Point"}
}