{
  "type": "Feature",
  "properties": {
    "addr:full":"Patrijzenlaan 20 Leuven (kessel-lo) Vlaams-Brabant 3010",
    "addr:housenumber":"20",
    "addr:postcode":"3010",
    "addr:street":"Patrijzenlaan",
    "iso:country":"BE",
    "sg:address":"Patrijzenlaan 20",
    "sg:city":"Leuven (kessel-lo)",
    "sg:classifiers":[
        {
            "category":"Shopping",
            "subcategory":"Gifts & Souvenirs",
            "type":"Retail Goods"
        }
    ],
    "sg:phone":"+32 2 466 10 12",
    "sg:postcode":"3010",
    "sg:province":"Vlaams-Brabant",
    "sg:tags":[
        "postcard",
        "picture",
        "greeting",
        "card"
    ],
    "wof:name":"A P B P",
    "wof:placetype":"venue"
},
  "geometry": {"coordinates":[4.7304501534,50.889755249],"type":"Point"}
}