{
  "type": "Feature",
  "properties": {
    "addr:full":"Avenue De Vaillampont 7 Nivelles (thines) Brabant Wallon 1402",
    "addr:housenumber":"7;1402",
    "addr:street":"Avenue De Vaillampont;Wallon",
    "iso:country":"BE",
    "sg:address":"Avenue De Vaillampont 7",
    "sg:city":"Nivelles (thines)",
    "sg:classifiers":[
        {
            "category":"Building & Trades",
            "subcategory":"Construction",
            "type":"Services"
        }
    ],
    "sg:phone":"+32 67 21 02 89",
    "sg:postcode":"1402",
    "sg:province":"Brabant Wallon",
    "sg:tags":[
        "installation",
        "-",
        "central",
        "heating"
    ],
    "wof:name":"Kiriako A",
    "wof:placetype":"venue"
},
  "geometry": {"coordinates":[4.3709468842,50.5924835205],"type":"Point"}
}