{
  "type": "Feature",
  "properties": {
    "addr:full":"Avenue Charles Quint 39 Bruxelles (ganshoren) Bruxelles-Capitale 1083",
    "addr:housenumber":"39",
    "addr:postcode":"1083",
    "addr:street":"Avenue Charles Quint",
    "iso:country":"BE",
    "sg:address":"Avenue Charles Quint 39",
    "sg:city":"Bruxelles (ganshoren)",
    "sg:classifiers":[
        {
            "category":"Home & Garden",
            "subcategory":"Carpets & Floor Coverings",
            "type":"Retail Goods"
        }
    ],
    "sg:phone":"+32 2 427 88 97",
    "sg:postcode":"1083",
    "sg:province":"Bruxelles-Capitale",
    "sg:tags":[
        "parquet"
    ],
    "wof:name":"Rolf Benz - Forme & Style",
    "wof:placetype":"venue"
},
  "geometry": {"coordinates":[4.3136029243,50.8679695129],"type":"Point"}
}