{
  "type": "Feature",
  "properties": {
    "iso:country":"BE",
    "sg:address":"Handelsstraat 60",
    "sg:city":"Roeselare",
    "sg:orig_category":"D\u00e9corateurs d'int\u00e9rieur",
    "sg:phone":"+32 51 24 64 62",
    "sg:postcode":"8800",
    "sg:province":"West-Vlaanderen",
    "wof:name":"Isabelle Vanderstichele",
    "wof:placetype":"venue"
},
  "geometry": {"coordinates":[3.1242909431,50.9556312561],"type":"Point"}
}