{
  "type": "Feature",
  "properties": {
    "addr:full":"Rue Des Moulins 24 Grez-doiceau Brabant Wallon 1390",
    "addr:housenumber":"24",
    "addr:postcode":"1390",
    "addr:street":"Rue Des Moulins",
    "iso:country":"BE",
    "sg:address":"Rue Des Moulins 24",
    "sg:city":"Grez-doiceau",
    "sg:orig_category":"Woningbouw",
    "sg:phone":"+32 10 84 12 78",
    "sg:postcode":"1390",
    "sg:province":"Brabant Wallon",
    "wof:name":"Malhove",
    "wof:placetype":"venue"
},
  "geometry": {"coordinates":[4.6806468964,50.7507286072],"type":"Point"}
}