{
  "type": "Feature",
  "properties": {
    "iso:country":"BE",
    "sg:address":"Rue De Cheumont 7",
    "sg:city":"Hamois",
    "sg:classifiers":[
        {
            "category":"Building & Trades",
            "subcategory":"Pest Control",
            "type":"Services"
        }
    ],
    "sg:phone":"+32 83 61 25 57",
    "sg:postcode":"5360",
    "sg:province":"Namur",
    "sg:tags":[
        "painting",
        "contractor"
    ],
    "wof:name":"Leclercq J-c",
    "wof:placetype":"venue"
},
  "geometry": {"coordinates":[5.1465997696,50.3414230347],"type":"Point"}
}