{
  "type": "Feature",
  "properties": {
    "iso:country":"BE",
    "sg:address":"Alkerweg 60",
    "sg:city":"Sint-truiden",
    "sg:classifiers":[
        {
            "category":"Autos & Motor Vehicles",
            "subcategory":"Automobile Sales",
            "type":"Retail Goods"
        }
    ],
    "sg:phone":"+32 11 68 28 37",
    "sg:postcode":"3800",
    "sg:province":"Limburg",
    "sg:tags":[
        "ceremony",
        "car"
    ],
    "wof:name":"Jaguar-norfolk",
    "wof:placetype":"venue"
},
  "geometry": {"coordinates":[5.2288351059,50.8429756165],"type":"Point"}
}