{
  "type": "Feature",
  "properties": {
    "iso:country":"BE",
    "sg:address":"Grand'rue 306",
    "sg:city":"Charleroi (montignies-sur-sambre)",
    "sg:classifiers":[
        {
            "category":"Health Services",
            "subcategory":"Dentist",
            "type":"Services"
        }
    ],
    "sg:phone":"+32 71 41 53 92",
    "sg:postcode":"6061",
    "sg:province":"Hainaut",
    "wof:name":"For\u00eat Didier",
    "wof:placetype":"venue"
},
  "geometry": {"coordinates":[4.459209919,50.4121246338],"type":"Point"}
}