{
  "type": "Feature",
  "properties": {
    "addr:full":"Nieuwstraat 89 Asse Vlaams-Brabant 1730",
    "addr:housenumber":"89",
    "addr:postcode":"1730",
    "addr:street":"Nieuwstraat",
    "iso:country":"BE",
    "sg:address":"Nieuwstraat 89",
    "sg:city":"Asse",
    "sg:classifiers":[
        {
            "category":"Fast Food",
            "type":"Food & Drink"
        }
    ],
    "sg:phone":"+32 2 452 97 88",
    "sg:postcode":"1730",
    "sg:province":"Vlaams-Brabant",
    "sg:tags":[
        "\u00c0",
        "restaurants",
        "emporter",
        "restaurant"
    ],
    "wof:name":"Hylios",
    "wof:placetype":"venue"
},
  "geometry": {"coordinates":[4.1931419373,50.9086952209],"type":"Point"}
}