{
  "type": "Feature",
  "properties": {
    "addr:full":"Bruy\u00e8res 84 Weismes Li\u00e8ge 4950",
    "addr:housenumber":"84",
    "addr:postcode":"4950",
    "addr:street":"Bruye\u0300Res",
    "iso:country":"BE",
    "sg:address":"Bruy\u00e8res 84",
    "sg:city":"Weismes",
    "sg:classifiers":[
        {
            "category":"Manufacturing",
            "subcategory":"Furniture",
            "type":"Manufacturing & Wholesale Goods"
        }
    ],
    "sg:phone":"+32 80 67 82 24",
    "sg:postcode":"4950",
    "sg:province":"Li\u00e8ge",
    "sg:tags":[
        "design",
        "-"
    ],
    "wof:name":"T\u00f6ller-van Leeuw S",
    "wof:placetype":"venue"
},
  "geometry": {"coordinates":[6.1125121117,50.4331016541],"type":"Point"}
}