{
  "type": "Feature",
  "properties": {
    "addr:full":"Georges Raeymaekersstr. 52 Schaarbeek/schaerbeek Bruxelles-Capitale 1030",
    "addr:housenumber":"52",
    "addr:postcode":"1030",
    "iso:country":"BE",
    "sg:address":"Georges Raeymaekersstr. 52",
    "sg:city":"Schaarbeek/schaerbeek",
    "sg:orig_category":"Geluidsopnames",
    "sg:phone":"+32 2 242 07 16",
    "sg:postcode":"1030",
    "sg:province":"Bruxelles-Capitale",
    "wof:name":"A.c.t.",
    "wof:placetype":"venue"
},
  "geometry": {"coordinates":[4.3917751312,50.8711128235],"type":"Point"}
}