{
  "type": "Feature",
  "properties": {
    "iso:country":"BE",
    "sg:address":"Bosstraat 84",
    "sg:city":"Boom",
    "sg:orig_category":"Brood, gebak and snoepgoed",
    "sg:phone":"+32 3 888 38 59",
    "sg:postcode":"2850",
    "sg:province":"Antwerpen",
    "wof:name":"Guy Apers",
    "wof:placetype":"venue"
},
  "geometry": {"coordinates":[4.3865418434,51.0860939026],"type":"Point"}
}