{
  "type": "Feature",
  "properties": {
    "iso:country":"BE",
    "sg:address":"Weverstraat 38",
    "sg:city":"Londerzeel",
    "sg:orig_category":"Goederenvervoer over de weg",
    "sg:phone":"+32 52 30 75 11",
    "sg:postcode":"1840",
    "sg:province":"Vlaams-Brabant",
    "wof:name":"Calberson Belgium",
    "wof:placetype":"venue"
},
  "geometry": {"coordinates":[4.3219609261,51.0153694153],"type":"Point"}
}