{
  "type": "Feature",
  "properties": {
    "addr:full":"Rummenweg 65 Sint-truiden Limburg 3800",
    "addr:housenumber":"65",
    "addr:postcode":"3800",
    "addr:street":"Rummenweg",
    "iso:country":"BE",
    "sg:address":"Rummenweg 65",
    "sg:city":"Sint-truiden",
    "sg:orig_category":"Plaatsen van vloer- and muurbekleding Schilders",
    "sg:phone":"+32 11 68 87 49",
    "sg:postcode":"3800",
    "sg:province":"Limburg",
    "wof:name":"R. Moens",
    "wof:placetype":"venue"
},
  "geometry": {"coordinates":[5.1817359924,50.8264961243],"type":"Point"}
}