{
  "type": "Feature",
  "properties": {
    "addr:full":"Chauss\u00c9e De Saint-job 570 Ukkel/uccle Bruxelles-Capitale 1180",
    "addr:housenumber":"570",
    "addr:postcode":"1180",
    "addr:street":"Chausse\u0301E De Saint-Job;/",
    "iso:country":"BE",
    "sg:address":"Chauss\u00c9e De Saint-job 570",
    "sg:city":"Ukkel/uccle",
    "sg:orig_category":"Salons de coiffure. Electrom\u00e9nager, t\u00e9l\u00e9visions and radios",
    "sg:phone":"+32 2 374 04 78",
    "sg:postcode":"1180",
    "sg:province":"Bruxelles-Capitale",
    "wof:name":"Chord Europe",
    "wof:placetype":"venue"
},
  "geometry": {"coordinates":[4.360806942,50.7928924561],"type":"Point"}
}