{
  "type": "Feature",
  "properties": {
    "addr:full":"Av De La Victoire 47 Saint-gilles (bruxelles) Bruxelles-Capitale 1060",
    "addr:housenumber":"47",
    "addr:postcode":"1060",
    "addr:street":"Av De La;Saint-Gilles Bruxelles",
    "iso:country":"BE",
    "sg:address":"Av De La Victoire 47",
    "sg:city":"Saint-gilles (bruxelles)",
    "sg:orig_category":"Kapsalons",
    "sg:phone":"+32 2 537 85 25",
    "sg:postcode":"1060",
    "sg:province":"Bruxelles-Capitale",
    "wof:name":"Catie",
    "wof:placetype":"venue"
},
  "geometry": {"coordinates":[4.3481221199,50.8303070068],"type":"Point"}
}