{
  "type": "Feature",
  "properties": {
    "iso:country":"BE",
    "sg:address":"Schuiferskapellestraat 83",
    "sg:city":"Pittem",
    "sg:orig_category":"Groententeelt",
    "sg:phone":"+32 51 46 63 07",
    "sg:postcode":"8740",
    "sg:province":"West-Vlaanderen",
    "wof:name":"Monique G.gryp-demeulenaere",
    "wof:placetype":"venue"
},
  "geometry": {"coordinates":[3.2805969715,51.0064506531],"type":"Point"}
}