{
  "type": "Feature",
  "properties": {
    "addr:full":"Rue Nicolas-spiroux 75 Li\u00e8ge 1 (grivegn\u00e9e) Li\u00e8ge 4030",
    "addr:housenumber":"75;1",
    "addr:postcode":"4030",
    "addr:street":"Rue Nicolas-Spiroux",
    "iso:country":"BE",
    "sg:address":"Rue Nicolas-spiroux 75",
    "sg:city":"Li\u00e8ge 1 (grivegn\u00e9e)",
    "sg:classifiers":[
        {
            "category":"Arena",
            "subcategory":"Sports Club",
            "type":"Entertainment"
        }
    ],
    "sg:phone":"+32 4 367 08 53",
    "sg:postcode":"4030",
    "sg:province":"Li\u00e8ge",
    "wof:name":"R.c.s.j. Grivegn\u00e9e Football",
    "wof:placetype":"venue"
},
  "geometry": {"coordinates":[5.6150240898,50.6266059875],"type":"Point"}
}