{
  "type": "Feature",
  "properties": {
    "addr:full":"Karekietenlaan 47 Leuven (kessel-lo) Vlaams-Brabant 3010",
    "addr:housenumber":"47",
    "addr:postcode":"3010",
    "addr:street":"Karekietenlaan",
    "iso:country":"BE",
    "sg:address":"Karekietenlaan 47",
    "sg:city":"Leuven (kessel-lo)",
    "sg:classifiers":[
        {
            "category":"Communications",
            "type":"Services"
        }
    ],
    "sg:phone":"+32 16 25 12 83",
    "sg:postcode":"3010",
    "sg:province":"Vlaams-Brabant",
    "sg:tags":[
        "translator"
    ],
    "wof:name":"Bekaert A",
    "wof:placetype":"venue"
},
  "geometry": {"coordinates":[4.7304501534,50.889755249],"type":"Point"}
}