{
  "type": "Feature",
  "properties": {
    "iso:country":"BE",
    "sg:address":"Provincieweg 33",
    "sg:city":"Gistel",
    "sg:orig_category":"Royal Canin. Animaux domestiques and accessoires",
    "sg:phone":"+32 59 27 80 06",
    "sg:postcode":"8470",
    "sg:province":"West-Vlaanderen",
    "wof:name":"Eurodogshop",
    "wof:placetype":"venue"
},
  "geometry": {"coordinates":[2.9749159813,51.1278915405],"type":"Point"}
}