{
  "type": "Feature",
  "properties": {
    "addr:full":"Demerwal 27 Bilzen Limburg 3740",
    "addr:housenumber":"27",
    "addr:postcode":"3740",
    "addr:street":"Demerwal",
    "iso:country":"BE",
    "sg:address":"Demerwal 27",
    "sg:city":"Bilzen",
    "sg:orig_category":"Traitements param\u00e9dicaux",
    "sg:phone":"+32 89 49 20 95",
    "sg:postcode":"3740",
    "sg:province":"Limburg",
    "wof:name":"Y. Cops",
    "wof:placetype":"venue"
},
  "geometry": {"coordinates":[5.51541996,50.8688201904],"type":"Point"}
}