{
  "type": "Feature",
  "properties": {
    "iso:country":"BE",
    "sg:address":"Rue Du Chevalet 32",
    "sg:city":"Louvain",
    "sg:orig_category":"Architecten",
    "sg:phone":"+32 10 45 64 44",
    "sg:postcode":"1348",
    "sg:province":"Brabant Wallon",
    "wof:name":"Urbs Architectes",
    "wof:placetype":"venue"
},
  "geometry": {"coordinates":[4.6059308052,50.6653594971],"type":"Point"}
}