{
  "type": "Feature",
  "properties": {
    "iso:country":"BE",
    "sg:address":"Houtstraat 22",
    "sg:city":"Maaseik",
    "sg:classifiers":[
        {
            "category":"Health Services",
            "subcategory":"Health Practitioner",
            "type":"Services"
        }
    ],
    "sg:phone":"+32 89 56 22 53",
    "sg:postcode":"3680",
    "sg:province":"Limburg",
    "sg:tags":[
        "physiotherapist"
    ],
    "wof:name":"Corstjens M",
    "wof:placetype":"venue"
},
  "geometry": {"coordinates":[5.7935137749,51.0933227539],"type":"Point"}
}