{
  "type": "Feature",
  "properties": {
    "addr:full":"Bruggestraat 37 Langemark-poelkapelle (poelkapelle) West-Vlaanderen 8920",
    "addr:housenumber":"37",
    "addr:postcode":"8920",
    "addr:street":"Bruggestraat",
    "iso:country":"BE",
    "sg:address":"Bruggestraat 37",
    "sg:city":"Langemark-poelkapelle (poelkapelle)",
    "sg:classifiers":[
        {
            "category":"Wholesale",
            "subcategory":"Meat",
            "type":"Manufacturing & Wholesale Goods"
        }
    ],
    "sg:phone":"+32 57 48 72 75",
    "sg:postcode":"8920",
    "sg:province":"West-Vlaanderen",
    "sg:tags":[
        "whol",
        "-"
    ],
    "wof:name":"Hivian Vleesgroothandel",
    "wof:placetype":"venue"
},
  "geometry": {"coordinates":[2.919770956,50.9132423401],"type":"Point"}
}