{
  "type": "Feature",
  "properties": {
    "iso:country":"BE",
    "sg:address":"Rue Du Centre 7",
    "sg:city":"Walhain (walhain-saint-paul)",
    "sg:classifiers":[
        {
            "category":"Health Services",
            "subcategory":"Health Practitioner",
            "type":"Services"
        }
    ],
    "sg:phone":"+32 10 65 02 08",
    "sg:postcode":"1457",
    "sg:province":"Brabant Wallon",
    "sg:tags":[
        "therapist",
        "speech"
    ],
    "wof:name":"Pironet M-n",
    "wof:placetype":"venue"
},
  "geometry": {"coordinates":[4.6942009926,50.616558075],"type":"Point"}
}