{
  "type": "Feature",
  "properties": {
    "iso:country":"BE",
    "sg:address":"Schoolstraat 19",
    "sg:city":"Boortmeerbeek",
    "sg:orig_category":"Effectenmakelaars and vermogensbeheer Verzekeringsmakelaars and experts",
    "sg:phone":"+32 15 51 64 25",
    "sg:postcode":"3190",
    "sg:province":"Vlaams-Brabant",
    "wof:name":"Verzekeringen Van Den Eynde",
    "wof:placetype":"venue"
},
  "geometry": {"coordinates":[4.5666241646,50.9741706848],"type":"Point"}
}