{
  "type": "Feature",
  "properties": {
    "addr:full":"Kalmthoutsesteenweg 31 Kapellen Antwerpen 2950",
    "addr:housenumber":"31",
    "addr:postcode":"2950",
    "addr:street":"Kalmthoutsesteenweg",
    "iso:country":"BE",
    "sg:address":"Kalmthoutsesteenweg 31",
    "sg:city":"Kapellen",
    "sg:orig_category":"Peinture. Eclairage et \u00e9quipements du foyer. Rev\u00eatements pour sols and murs. Installation de menuise",
    "sg:phone":"+32 3 605 57 39",
    "sg:postcode":"2950",
    "sg:province":"Antwerpen",
    "wof:name":"Van Tilburg-willems & Co",
    "wof:placetype":"venue"
},
  "geometry": {"coordinates":[4.4184861183,51.3296051025],"type":"Point"}
}