{
  "type": "Feature",
  "properties": {
    "addr:full":"Rue Longue 9 Beauvechain Brabant Wallon 1320",
    "addr:housenumber":"9",
    "addr:postcode":"1320",
    "addr:street":"Rue Longue",
    "iso:country":"BE",
    "sg:address":"Rue Longue 9",
    "sg:city":"Beauvechain",
    "sg:classifiers":[
        {
            "category":"Banks & Credit Unions",
            "subcategory":"Investment Brokerage",
            "type":"Services"
        }
    ],
    "sg:phone":"+32 10 86 72 42",
    "sg:postcode":"1320",
    "sg:province":"Brabant Wallon",
    "sg:tags":[
        "fence"
    ],
    "wof:name":"Bruynbroeck M",
    "wof:placetype":"venue"
},
  "geometry": {"coordinates":[4.8027172089,50.7704849243],"type":"Point"}
}