{
  "type": "Feature",
  "properties": {
    "addr:full":"Handbooghof 10 Halle Vlaams-Brabant 1500",
    "addr:housenumber":"10",
    "addr:postcode":"1500",
    "addr:street":"Handbooghof",
    "iso:country":"BE",
    "sg:address":"Handbooghof 10",
    "sg:city":"Halle",
    "sg:classifiers":[
        {
            "category":"Education",
            "subcategory":"School",
            "type":"Public Place"
        }
    ],
    "sg:phone":"+32 2 356 51 71",
    "sg:postcode":"1500",
    "sg:province":"Vlaams-Brabant",
    "sg:tags":[
        "primary"
    ],
    "wof:name":"Basisschool Heilig Hart",
    "wof:placetype":"venue"
},
  "geometry": {"coordinates":[4.2389302254,50.7348709106],"type":"Point"}
}