{
  "type": "Feature",
  "properties": {
    "iso:country":"BE",
    "sg:address":"Turnhoutsebaan 49",
    "sg:city":"Diest",
    "sg:classifiers":[
        {
            "category":"Food & Beverages",
            "subcategory":"Groceries & Convenience Stores",
            "type":"Retail Goods"
        }
    ],
    "sg:phone":"+32 13 32 30 50",
    "sg:postcode":"3290",
    "sg:province":"Vlaams-Brabant",
    "sg:tags":[
        "frozen",
        "goods",
        "baked"
    ],
    "wof:name":"Pastridor Nv",
    "wof:placetype":"venue"
},
  "geometry": {"coordinates":[5.0516438484,50.9926795959],"type":"Point"}
}