{
  "type": "Feature",
  "properties": {
    "iso:country":"BE",
    "sg:address":"Frederik Wouterslaan 2",
    "sg:city":"Kampenhout",
    "sg:orig_category":"Artsen and specialisten",
    "sg:phone":"+32 16 65 08 70",
    "sg:postcode":"1910",
    "sg:province":"Vlaams-Brabant",
    "wof:name":"P. De Hertogh",
    "wof:placetype":"venue"
},
  "geometry": {"coordinates":[4.5508828163,50.9421958923],"type":"Point"}
}