{
  "type": "Feature",
  "properties": {
    "iso:country":"BE",
    "sg:address":"Rue De Houdremont 3",
    "sg:city":"Bievre",
    "sg:orig_category":"Boucheries",
    "sg:phone":"+32 61 51 10 27",
    "sg:postcode":"5555",
    "sg:province":"Namur",
    "wof:name":"Patrick Compere",
    "wof:placetype":"venue"
},
  "geometry": {"coordinates":[5.0158782005,49.9412689209],"type":"Point"}
}