{
  "type": "Feature",
  "properties": {
    "iso:country":"BE",
    "sg:address":"Vroentestraat 83",
    "sg:city":"Hoegaarden",
    "sg:classifiers":[
        {
            "category":"Freight",
            "type":"Transportation"
        }
    ],
    "sg:phone":"+32 16 76 75 00",
    "sg:postcode":"3320",
    "sg:province":"Vlaams-Brabant",
    "sg:tags":[
        "-",
        "transport"
    ],
    "wof:name":"Taverniers E",
    "wof:placetype":"venue"
},
  "geometry": {"coordinates":[4.8981409073,50.7748336792],"type":"Point"}
}