{
  "type": "Feature",
  "properties": {
    "addr:full":"Chauss\u00c9e De Nivelles 12bb Sombreffe Namur 5140",
    "addr:housenumber":"12bb",
    "addr:postcode":"5140",
    "addr:street":"Chausse\u0301E De Nivelles",
    "iso:country":"BE",
    "sg:address":"Chauss\u00c9e De Nivelles 12bb",
    "sg:city":"Sombreffe",
    "sg:orig_category":"Banken and kredietinstellingen",
    "sg:phone":"+32 71 88 76 01",
    "sg:postcode":"5140",
    "sg:province":"Namur",
    "wof:name":"Bbl",
    "wof:placetype":"venue"
},
  "geometry": {"coordinates":[4.6126251221,50.5247764587],"type":"Point"}
}