{
  "type": "Feature",
  "properties": {
    "iso:country":"BE",
    "sg:address":"Klerkenstraat 15",
    "sg:city":"Langemark-poelkapelle",
    "sg:classifiers":[
        {
            "category":"Insurance",
            "subcategory":"Life Insurance",
            "type":"Services"
        }
    ],
    "sg:phone":"+32 57 48 81 33",
    "sg:postcode":"8920",
    "sg:province":"West-Vlaanderen",
    "sg:tags":[
        "assurance"
    ],
    "wof:name":"Frans Peene",
    "wof:placetype":"venue"
},
  "geometry": {"coordinates":[2.9296720028,50.9334259033],"type":"Point"}
}