{
  "type": "Feature",
  "properties": {
    "iso:country":"BE",
    "sg:address":"Rue Des Combattants 3",
    "sg:city":"Komen-waasten/comines-warneton",
    "sg:orig_category":"Avocats and conseillers juridiques",
    "sg:phone":"+32 56 55 40 50",
    "sg:postcode":"7780",
    "sg:province":"Hainaut",
    "wof:name":"V\u00c9ronique Raveschot",
    "wof:placetype":"venue"
},
  "geometry": {"coordinates":[2.9968349934,50.7715492249],"type":"Point"}
}