{
  "type": "Feature",
  "properties": {
    "addr:full":"Toekomstraat 42 Vilvoorde Vlaams-Brabant 1800",
    "addr:housenumber":"42",
    "addr:postcode":"1800",
    "addr:street":"Toekomstraat",
    "iso:country":"BE",
    "sg:address":"Toekomstraat 42",
    "sg:city":"Vilvoorde",
    "sg:orig_category":"Agences immobili\u00e8res. Evaluation and estimation de biens immobiliers",
    "sg:phone":"+32 2 251 27 47",
    "sg:postcode":"1800",
    "sg:province":"Vlaams-Brabant",
    "wof:name":"Emile Duculot",
    "wof:placetype":"venue"
},
  "geometry": {"coordinates":[4.4266848564,50.9292678833],"type":"Point"}
}