{
  "type": "Feature",
  "properties": {
    "iso:country":"BE",
    "sg:address":"H Baelskaai 25",
    "sg:city":"Oostende",
    "sg:orig_category":"Diverse opleidingen and onderwijs",
    "sg:phone":"+32 59 33 13 93",
    "sg:postcode":"8400",
    "sg:province":"West-Vlaanderen",
    "wof:name":"Vdab Training En Opleiding",
    "wof:placetype":"venue"
},
  "geometry": {"coordinates":[2.9352800846,51.2329292297],"type":"Point"}
}