{
  "type": "Feature",
  "properties": {
    "addr:full":"Avenue Gouverneur Bovesse 1 Namur Namur 5100",
    "addr:housenumber":"1",
    "addr:postcode":"5100",
    "addr:street":"Avenue;Bovesse",
    "iso:country":"BE",
    "sg:address":"Avenue Gouverneur Bovesse 1",
    "sg:city":"Namur",
    "sg:orig_category":"Installatie van houten of kunststof schrijnwerk Installatie van metalen schrijnwerk",
    "sg:phone":"+32 81 30 00 66",
    "sg:postcode":"5100",
    "sg:province":"Namur",
    "wof:name":"Belisol",
    "wof:placetype":"venue"
},
  "geometry": {"coordinates":[4.8713750839,50.4566345215],"type":"Point"}
}