{
  "type": "Feature",
  "properties": {
    "iso:country":"BE",
    "sg:address":"Millenstraat 43",
    "sg:city":"Bree",
    "sg:orig_category":"Studios photographiques",
    "sg:phone":"+32 89 47 17 49",
    "sg:postcode":"3960",
    "sg:province":"Limburg",
    "wof:name":"Anne-marie Tielens",
    "wof:placetype":"venue"
},
  "geometry": {"coordinates":[5.6074228287,51.139591217],"type":"Point"}
}