{
  "type": "Feature",
  "properties": {
    "addr:full":"Roesbruggestraat 70 Alveringem (beveren-aan-de-ijzer) West-Vlaanderen 8691",
    "addr:housenumber":"70",
    "addr:postcode":"8691",
    "addr:street":"Roesbruggestraat;Beveren-Aan-De-Ijzer West-Vlaanderen",
    "iso:country":"BE",
    "sg:address":"Roesbruggestraat 70",
    "sg:city":"Alveringem (beveren-aan-de-ijzer)",
    "sg:classifiers":[
        {
            "category":"Health Services",
            "subcategory":"Doctor",
            "type":"Services"
        }
    ],
    "sg:phone":"+32 57 30 06 37",
    "sg:postcode":"8691",
    "sg:province":"West-Vlaanderen",
    "sg:tags":[
        "medicinephysicians",
        "surgeon"
    ],
    "wof:name":"Cremmery Peter",
    "wof:placetype":"venue"
},
  "geometry": {"coordinates":[2.6181299686,50.925037384],"type":"Point"}
}