{
  "type": "Feature",
  "properties": {
    "iso:country":"BE",
    "sg:address":"Acaciadreef 2",
    "sg:city":"Zandhoven (pulle)",
    "sg:classifiers":[
        {
            "category":"Social Services",
            "subcategory":"Job Training",
            "type":"Services"
        }
    ],
    "sg:phone":"+32 3 484 43 03",
    "sg:postcode":"2243",
    "sg:province":"Antwerpen",
    "sg:tags":[
        "coordinator",
        "safety"
    ],
    "wof:name":"Cautereels",
    "wof:placetype":"venue"
},
  "geometry": {"coordinates":[4.6928038597,51.1929855347],"type":"Point"}
}