{
  "type": "Feature",
  "properties": {
    "addr:full":"Rue De Hautrage 39 Saint-ghislain Hainaut 7331",
    "addr:housenumber":"39",
    "addr:postcode":"7331",
    "addr:street":"Rue De Hautrage;Hainaut",
    "iso:country":"BE",
    "sg:address":"Rue De Hautrage 39",
    "sg:city":"Saint-ghislain",
    "sg:classifiers":[
        {
            "category":"Sports & Exercise",
            "subcategory":"Sports Center",
            "type":"Entertainment"
        }
    ],
    "sg:phone":"+32 65 64 39 76",
    "sg:postcode":"7331",
    "sg:province":"Hainaut",
    "sg:tags":[
        "terrain",
        "hors",
        "de",
        "installation",
        "sportifs"
    ],
    "wof:name":"Les Ecuries De L'eden",
    "wof:placetype":"venue"
},
  "geometry": {"coordinates":[3.8367199898,50.4720001221],"type":"Point"}
}