{
  "type": "Feature",
  "properties": {
    "iso:country":"BE",
    "sg:address":"Olmenstraat 40",
    "sg:city":"Neerpelt",
    "sg:classifiers":[
        {
            "category":"Farming",
            "subcategory":"Farm & Veterinary Services",
            "type":"Manufacturing & Wholesale Goods"
        }
    ],
    "sg:phone":"+32 11 64 38 93",
    "sg:postcode":"3910",
    "sg:province":"Limburg",
    "sg:tags":[
        "agricultural",
        "contractor"
    ],
    "wof:name":"Cuyvers H",
    "wof:placetype":"venue"
},
  "geometry": {"coordinates":[5.4562802315,51.2122993469],"type":"Point"}
}