{
  "type": "Feature",
  "properties": {
    "addr:full":"Rue Saint-jacques 11 Namur Namur 5000",
    "addr:housenumber":"11",
    "addr:postcode":"5000",
    "addr:street":"Rue Saint-Jacques",
    "iso:country":"BE",
    "sg:address":"Rue Saint-jacques 11",
    "sg:city":"Namur",
    "sg:orig_category":"V\u00eatements pour Hommes",
    "sg:phone":"+32 81 26 33 15",
    "sg:postcode":"5000",
    "sg:province":"Namur",
    "wof:name":"Nord-ouest",
    "wof:placetype":"venue"
},
  "geometry": {"coordinates":[4.8644418716,50.4648704529],"type":"Point"}
}