{
  "type": "Feature",
  "properties": {
    "addr:full":"Tereecken 1ba Assenede Oost-Vlaanderen 9968",
    "addr:postcode":"9968",
    "addr:street":"Tereecken;Oost-Vlaanderen",
    "iso:country":"BE",
    "sg:address":"Tereecken 1ba",
    "sg:city":"Assenede",
    "sg:orig_category":"Eleveurs de bovins",
    "sg:phone":"+32 9 343 07 83",
    "sg:postcode":"9968",
    "sg:province":"Oost-Vlaanderen",
    "wof:name":"Laurent Van De Velde",
    "wof:placetype":"venue"
},
  "geometry": {"coordinates":[3.7291550636,51.1865692139],"type":"Point"}
}