{
  "type": "Feature",
  "properties": {
    "addr:full":"Lokerse Baan 12 Sint-niklaas (belsele) Oost-Vlaanderen 9111",
    "addr:housenumber":"12",
    "addr:postcode":"9111",
    "addr:street":"Lokerse Baan",
    "iso:country":"BE",
    "sg:address":"Lokerse Baan 12",
    "sg:city":"Sint-niklaas (belsele)",
    "sg:classifiers":[
        {
            "category":"Manufacturing",
            "subcategory":"Furniture",
            "type":"Manufacturing & Wholesale Goods"
        }
    ],
    "sg:phone":"+32 3 722 92 90",
    "sg:postcode":"9111",
    "sg:province":"Oost-Vlaanderen",
    "sg:tags":[
        "design",
        "-"
    ],
    "wof:name":"Richter",
    "wof:placetype":"venue"
},
  "geometry": {"coordinates":[4.0770721436,51.1414680481],"type":"Point"}
}