{
  "type": "Feature",
  "properties": {
    "addr:full":"Markt 14 Brugge West-Vlaanderen 8000",
    "addr:housenumber":"14",
    "addr:postcode":"8000",
    "addr:street":"Markt",
    "iso:country":"BE",
    "sg:address":"Markt 14",
    "sg:city":"Brugge",
    "sg:classifiers":[
        {
            "category":"Fast Food",
            "type":"Food & Drink"
        }
    ],
    "sg:phone":"+32 50 33 19 79",
    "sg:postcode":"8000",
    "sg:province":"West-Vlaanderen",
    "sg:tags":[
        "\u00c0",
        "restaurants",
        "emporter",
        "restaurant"
    ],
    "wof:name":"Quick",
    "wof:placetype":"venue"
},
  "geometry": {"coordinates":[3.2239289284,51.2085151672],"type":"Point"}
}