{
  "type": "Feature",
  "properties": {
    "addr:full":"Wijngaardstraat 5a Grobbendonk Antwerpen 2280",
    "addr:housenumber":"5a",
    "addr:postcode":"2280",
    "addr:street":"Wijngaardstraat",
    "iso:country":"BE",
    "sg:address":"Wijngaardstraat 5a",
    "sg:city":"Grobbendonk",
    "sg:classifiers":[
        {
            "category":"Arena",
            "subcategory":"Sports Club",
            "type":"Entertainment"
        }
    ],
    "sg:phone":"+32 14 51 57 93",
    "sg:postcode":"2280",
    "sg:province":"Antwerpen",
    "sg:tags":[
        "de"
    ],
    "wof:name":"Grovo",
    "wof:placetype":"venue"
},
  "geometry": {"coordinates":[4.741174221,51.1959190369],"type":"Point"}
}