{
  "type": "Feature",
  "properties": {
    "iso:country":"BE",
    "sg:address":"Rue D'h\u00e9rinnes 46",
    "sg:city":"Enghien",
    "sg:classifiers":[
        {
            "category":"Retail",
            "subcategory":"Repair Shop",
            "type":"Services"
        }
    ],
    "sg:phone":"+32 2 395 44 10",
    "sg:postcode":"7850",
    "sg:province":"Hainaut",
    "sg:tags":[
        "-",
        "mainten",
        "watch",
        "clock"
    ],
    "wof:name":"Steenhaut",
    "wof:placetype":"venue"
},
  "geometry": {"coordinates":[4.0383911133,50.6945991516],"type":"Point"}
}