{
  "type": "Feature",
  "properties": {
    "iso:country":"BE",
    "sg:address":"Brusselsesteenweg 315",
    "sg:city":"Overijse",
    "sg:classifiers":[
        {
            "category":"Cafe",
            "type":"Food & Drink"
        }
    ],
    "sg:phone":"+32 2 306 78 06",
    "sg:postcode":"3090",
    "sg:province":"Vlaams-Brabant",
    "sg:tags":[
        "snack-bars"
    ],
    "wof:name":"Okaez Crazy Snack",
    "wof:placetype":"venue"
},
  "geometry": {"coordinates":[4.5137200356,50.7808799744],"type":"Point"}
}