{
  "type": "Feature",
  "properties": {
    "addr:full":"Herenthoutseweg 67 Herentals Antwerpen 2200",
    "addr:housenumber":"67",
    "addr:postcode":"2200",
    "addr:street":"Herenthoutseweg",
    "iso:country":"BE",
    "sg:address":"Herenthoutseweg 67",
    "sg:city":"Herentals",
    "sg:classifiers":[
        {
            "category":"Insurance",
            "subcategory":"Insurance Agent",
            "type":"Services"
        }
    ],
    "sg:phone":"+32 14 21 28 91",
    "sg:postcode":"2200",
    "sg:province":"Antwerpen",
    "sg:tags":[
        "broker"
    ],
    "wof:name":"Pluys Zakenkantoor Bvba",
    "wof:placetype":"venue"
},
  "geometry": {"coordinates":[4.8331799507,51.1722412109],"type":"Point"}
}