{
  "type": "Feature",
  "properties": {
    "addr:full":"Grande Place 1 Huy Li\u00e8ge 4500",
    "addr:housenumber":"1",
    "addr:postcode":"4500",
    "addr:street":"Grande Place",
    "iso:country":"BE",
    "sg:address":"Grande Place 1",
    "sg:city":"Huy",
    "sg:classifiers":[
        {
            "category":"Professional",
            "subcategory":"Business Services",
            "type":"Services"
        }
    ],
    "sg:phone":"+32 85 21 78 21",
    "sg:postcode":"4500",
    "sg:province":"Li\u00e8ge",
    "sg:tags":[
        "training",
        "advice"
    ],
    "wof:name":"College Bourgm & Echevins",
    "wof:placetype":"venue"
},
  "geometry": {"coordinates":[5.2411680222,50.5183486938],"type":"Point"}
}