{
  "type": "Feature",
  "properties": {
    "addr:full":"Schoonwinkelstraat 9 Hasselt (sint-lambrechts-herk) Limburg 3500",
    "addr:housenumber":"9",
    "addr:postcode":"3500",
    "addr:street":"Schoonwinkelstraat",
    "iso:country":"BE",
    "sg:address":"Schoonwinkelstraat 9",
    "sg:city":"Hasselt (sint-lambrechts-herk)",
    "sg:orig_category":"Non-Classified Establishments",
    "sg:phone":"+32 11 59 72 20",
    "sg:postcode":"3500",
    "sg:province":"Limburg",
    "wof:name":"Astraco",
    "wof:placetype":"venue"
},
  "geometry": {"coordinates":[5.3189401627,50.9011688232],"type":"Point"}
}