{
  "type": "Feature",
  "properties": {
    "addr:full":"Selsaetenstraat 50 Wommelgem Antwerpen 2160",
    "addr:housenumber":"50",
    "addr:postcode":"2160",
    "addr:street":"Selsaetenstraat",
    "iso:country":"BE",
    "sg:address":"Selsaetenstraat 50",
    "sg:city":"Wommelgem",
    "sg:classifiers":[
        {
            "category":"Health Services",
            "subcategory":"Nursing And Care Facility",
            "type":"Services"
        }
    ],
    "sg:phone":"+32 3 353 34 15",
    "sg:postcode":"2160",
    "sg:province":"Antwerpen",
    "sg:tags":[
        "home",
        "rest"
    ],
    "wof:name":"Rustoord Wommelgheem Vzw",
    "wof:placetype":"venue"
},
  "geometry": {"coordinates":[4.5288100243,51.1975898743],"type":"Point"}
}