{
  "type": "Feature",
  "properties": {
    "addr:full":"Vaartstraat 22 Box 3 Leuven Vlaams-Brabant 3000",
    "addr:housenumber":"22;3",
    "addr:postcode":"3000",
    "addr:street":"Vaartstraat;Box",
    "iso:country":"BE",
    "sg:address":"Vaartstraat 22 Box 3",
    "sg:city":"Leuven",
    "sg:classifiers":[
        {
            "category":"Professional",
            "subcategory":"Lawyer & Legal Services",
            "type":"Services"
        }
    ],
    "sg:phone":"+32 16 20 28 28",
    "sg:postcode":"3000",
    "sg:province":"Vlaams-Brabant",
    "wof:name":"Wuytack Gretel",
    "wof:placetype":"venue"
},
  "geometry": {"coordinates":[4.7021751404,50.8810119629],"type":"Point"}
}