{
  "type": "Feature",
  "properties": {
    "iso:country":"BE",
    "sg:address":"Huiperstraat 10",
    "sg:city":"Laakdal",
    "sg:orig_category":"Activit\u00e9s and \u00e9v\u00e9nements sportifs divers",
    "sg:phone":"+32 13 66 45 54",
    "sg:postcode":"2430",
    "sg:province":"Antwerpen",
    "wof:name":"Nijst Ferdy",
    "wof:placetype":"venue"
},
  "geometry": {"coordinates":[5.0338921547,51.0850067139],"type":"Point"}
}