{
  "type": "Feature",
  "properties": {
    "addr:full":"Spelonckvaart 104 Moerbeke Oost-Vlaanderen 9180",
    "addr:housenumber":"104",
    "addr:postcode":"9180",
    "iso:country":"BE",
    "sg:address":"Spelonckvaart 104",
    "sg:city":"Moerbeke",
    "sg:orig_category":"Eleveurs de bovins",
    "sg:phone":"+32 9 346 72 90",
    "sg:postcode":"9180",
    "sg:province":"Oost-Vlaanderen",
    "wof:name":"Cyriel Aper",
    "wof:placetype":"venue"
},
  "geometry": {"coordinates":[3.9698998928,51.1851806641],"type":"Point"}
}