{
  "type": "Feature",
  "properties": {
    "addr:full":"Rue Caporal Tr\u00c9signies 25 Mons Hainaut 7022",
    "addr:housenumber":"25",
    "addr:postcode":"7022",
    "addr:street":"Rue Caporal Tre\u0301Signies;Hainaut",
    "iso:country":"BE",
    "sg:address":"Rue Caporal Tr\u00c9signies 25",
    "sg:city":"Mons",
    "sg:orig_category":"Alternatieve geneeskunde Artsen and specialisten",
    "sg:phone":"+32 65 31 96 83",
    "sg:postcode":"7022",
    "sg:province":"Hainaut",
    "wof:name":"Jean-pierre Degrace",
    "wof:placetype":"venue"
},
  "geometry": {"coordinates":[3.9526720047,50.4363365173],"type":"Point"}
}