{
  "type": "Feature",
  "properties": {
    "addr:full":"Rue Edgard Doneux 12 Fl\u00e9malle Li\u00e8ge 4400",
    "addr:housenumber":"12",
    "addr:postcode":"4400",
    "addr:street":"Rue Edgard Doneux",
    "iso:country":"BE",
    "sg:address":"Rue Edgard Doneux 12",
    "sg:city":"Fl\u00e9malle",
    "sg:classifiers":[
        {
            "category":"Cafe",
            "type":"Food & Drink"
        }
    ],
    "sg:phone":"+32 4 233 15 28",
    "sg:postcode":"4400",
    "sg:province":"Li\u00e8ge",
    "sg:tags":[
        "snack-bars"
    ],
    "wof:name":"Piafette (la)",
    "wof:placetype":"venue"
},
  "geometry": {"coordinates":[5.4673280716,50.5988845825],"type":"Point"}
}