{
  "type": "Feature",
  "properties": {
    "addr:full":"Schaveystraat 3 Huldenberg Vlaams-Brabant 3040",
    "addr:housenumber":"3",
    "addr:postcode":"3040",
    "addr:street":"Schaveystraat",
    "iso:country":"BE",
    "sg:address":"Schaveystraat 3",
    "sg:city":"Huldenberg",
    "sg:orig_category":"Brood, gebak and snoepgoed",
    "sg:phone":"+32 16 47 71 38",
    "sg:postcode":"3040",
    "sg:province":"Vlaams-Brabant",
    "wof:name":"De Coster Emile",
    "wof:placetype":"venue"
},
  "geometry": {"coordinates":[4.6235098839,50.8151626587],"type":"Point"}
}