{
  "type": "Feature",
  "properties": {
    "iso:country":"BE",
    "sg:address":"Onze-lieve-vrouwstraat 20",
    "sg:city":"Maasmechelen",
    "sg:orig_category":"Informaticaconsulenten",
    "sg:phone":"+32 89 76 11 61",
    "sg:postcode":"3630",
    "sg:province":"Limburg",
    "wof:name":"International Sales Partners",
    "wof:placetype":"venue"
},
  "geometry": {"coordinates":[5.688475132,50.983253479],"type":"Point"}
}