{
  "type": "Feature",
  "properties": {
    "addr:full":"Adolphe Dupuichlaan 42 Ukkel/uccle Bruxelles-Capitale 1180",
    "addr:housenumber":"42",
    "addr:postcode":"1180",
    "addr:street":"Adolphe Dupuichlaan;/",
    "iso:country":"BE",
    "sg:address":"Adolphe Dupuichlaan 42",
    "sg:city":"Ukkel/uccle",
    "sg:orig_category":"Sportclubs",
    "sg:phone":"+32 2 344 36 66",
    "sg:postcode":"1180",
    "sg:province":"Bruxelles-Capitale",
    "wof:name":"Royal Leopold Club",
    "wof:placetype":"venue"
},
  "geometry": {"coordinates":[4.3515071869,50.8086357117],"type":"Point"}
}