{
  "type": "Feature",
  "properties": {
    "iso:country":"BE",
    "sg:address":"Veerlepad 1",
    "sg:city":"Herselt",
    "sg:classifiers":[
        {
            "category":"Real Estate",
            "subcategory":"Architect",
            "type":"Services"
        }
    ],
    "sg:phone":"+32 14 54 99 54",
    "sg:postcode":"2230",
    "sg:province":"Antwerpen",
    "wof:name":"Beylmakers G",
    "wof:placetype":"venue"
},
  "geometry": {"coordinates":[4.8873329163,51.0535011292],"type":"Point"}
}