{
  "type": "Feature",
  "properties": {
    "iso:country":"BE",
    "sg:address":"Bruulstraat 40",
    "sg:city":"Heist-op-den-berg",
    "sg:orig_category":"Eleveurs de bovins",
    "sg:phone":"+32 15 24 12 92",
    "sg:postcode":"2222",
    "sg:province":"Antwerpen",
    "wof:name":"Gladijs Van Den Bosch",
    "wof:placetype":"venue"
},
  "geometry": {"coordinates":[4.7292399406,51.1032218933],"type":"Point"}
}