{
  "type": "Feature",
  "properties": {
    "iso:country":"BE",
    "sg:address":"Rue L\u00c9on Charlier 70",
    "sg:city":"Wanze",
    "sg:orig_category":"Instituts de beaut\u00e9",
    "sg:phone":"+32 85 23 24 24",
    "sg:postcode":"4520",
    "sg:province":"Li\u00e8ge",
    "wof:name":"La Griffe De La Beaut\u00c9",
    "wof:placetype":"venue"
},
  "geometry": {"coordinates":[5.2036042213,50.5309104919],"type":"Point"}
}