{
  "type": "Feature",
  "properties": {
    "iso:country":"BE",
    "sg:address":"Gaaiendreef 3",
    "sg:city":"Schoten",
    "sg:orig_category":"M\u00e9decins and sp\u00e9cialistes",
    "sg:phone":"+32 3 290 45 89",
    "sg:postcode":"2900",
    "sg:province":"Antwerpen",
    "wof:name":"E. Cristens",
    "wof:placetype":"venue"
},
  "geometry": {"coordinates":[4.5099802017,51.2785873413],"type":"Point"}
}