{
  "type": "Feature",
  "properties": {
    "addr:full":"Rue Emile Deltenre 19 Frasnes-lez-anvaing Hainaut 7912",
    "addr:housenumber":"19",
    "addr:postcode":"7912",
    "addr:street":"Rue Emile Deltenre",
    "iso:country":"BE",
    "sg:address":"Rue Emile Deltenre 19",
    "sg:city":"Frasnes-lez-anvaing",
    "sg:orig_category":"Woningbouw",
    "sg:phone":"+32 69 76 89 52",
    "sg:postcode":"7912",
    "sg:province":"Hainaut",
    "wof:name":"Conil Freres",
    "wof:placetype":"venue"
},
  "geometry": {"coordinates":[3.5955610275,50.7094612122],"type":"Point"}
}