{
  "type": "Feature",
  "properties": {
    "iso:country":"BE",
    "sg:address":"Gorberstrasse 101",
    "sg:city":"Eupen",
    "sg:classifiers":[
        {
            "category":"Fast Food",
            "type":"Food & Drink"
        }
    ],
    "sg:phone":"+32 87 74 43 30",
    "sg:postcode":"4700",
    "sg:province":"Li\u00e8ge",
    "sg:tags":[
        "\u00c0",
        "emporter",
        "restaurants"
    ],
    "wof:name":"Saigon",
    "wof:placetype":"venue"
},
  "geometry": {"coordinates":[6.0296521187,50.6318206787],"type":"Point"}
}