{
  "type": "Feature",
  "properties": {
    "iso:country":"BE",
    "sg:address":"Rue Du Beau Site 25",
    "sg:city":"Fl\u00c9malle",
    "sg:orig_category":"Dansscholen",
    "sg:phone":"+32 4 228 08 48",
    "sg:postcode":"4400",
    "sg:province":"Li\u00e8ge",
    "wof:name":"K\u00b4dance Center",
    "wof:placetype":"venue"
},
  "geometry": {"coordinates":[5.4497580528,50.5975570679],"type":"Point"}
}