{
  "type": "Feature",
  "properties": {
    "addr:full":"Zone Industriele 1a Raeren Li\u00e8ge 4731",
    "addr:housenumber":"1a",
    "addr:postcode":"4731",
    "addr:street":"Zone Industriele",
    "iso:country":"BE",
    "sg:address":"Zone Industriele 1a",
    "sg:city":"Raeren",
    "sg:orig_category":"Gespecialiseerde residenti\u00eble bouw Installatie van metalen schrijnwerk",
    "sg:phone":"+32 87 85 34 66",
    "sg:postcode":"4731",
    "sg:province":"Li\u00e8ge",
    "wof:name":"Ardennes Clotures",
    "wof:placetype":"venue"
},
  "geometry": {"coordinates":[6.0827941895,50.6918411255],"type":"Point"}
}