{
  "type": "Feature",
  "properties": {
    "addr:full":"Rue De Wand 146 Bruxelles Bruxelles-Capitale 1020",
    "addr:housenumber":"146",
    "addr:postcode":"1020",
    "addr:street":"Rue De Wand",
    "iso:country":"BE",
    "sg:address":"Rue De Wand 146",
    "sg:city":"Bruxelles",
    "sg:classifiers":[
        {
            "category":"Personal",
            "subcategory":"Beauty Salon",
            "type":"Services"
        }
    ],
    "sg:phone":"+32 2 262 22 22",
    "sg:postcode":"1020",
    "sg:province":"Bruxelles-Capitale",
    "sg:tags":[
        "lady",
        "-",
        "hairdressing"
    ],
    "wof:name":"Planet'hair",
    "wof:placetype":"venue"
},
  "geometry": {"coordinates":[4.3603649139,50.900592804],"type":"Point"}
}