{
  "type": "Feature",
  "properties": {
    "iso:country":"BE",
    "sg:address":"Hoof 120",
    "sg:city":"Welkenraedt/welkenraedt",
    "sg:orig_category":"Rundveehouders",
    "sg:phone":"+32 87 44 64 25",
    "sg:postcode":"4841",
    "sg:province":"Li\u00e8ge",
    "wof:name":"Alphonse Kottgen",
    "wof:placetype":"venue"
},
  "geometry": {"coordinates":[5.9195780754,50.6508865356],"type":"Point"}
}