{
  "type": "Feature",
  "properties": {
    "addr:full":"Rue De La R\u00c9gence 15 Charleroi Hainaut 6000",
    "addr:housenumber":"15",
    "addr:postcode":"6000",
    "addr:street":"Rue De La Re\u0301Gence;Hainaut",
    "iso:country":"BE",
    "sg:address":"Rue De La R\u00c9gence 15",
    "sg:city":"Charleroi",
    "sg:orig_category":"Non-foodwinkels",
    "sg:phone":"+32 71 30 57 55",
    "sg:postcode":"6000",
    "sg:province":"Hainaut",
    "wof:name":"Terrifix",
    "wof:placetype":"venue"
},
  "geometry": {"coordinates":[4.4454779625,50.4124298096],"type":"Point"}
}