{
  "type": "Feature",
  "properties": {
    "addr:full":"Van Steenestraat 25 Brugge (assebroek) West-Vlaanderen 8310",
    "addr:housenumber":"25",
    "addr:postcode":"8310",
    "addr:street":"Steenestraat",
    "iso:country":"BE",
    "sg:address":"Van Steenestraat 25",
    "sg:city":"Brugge (assebroek)",
    "sg:classifiers":[
        {
            "category":"Personal",
            "subcategory":"Beauty Salon",
            "type":"Services"
        }
    ],
    "sg:phone":"+32 50 35 72 42",
    "sg:postcode":"8310",
    "sg:province":"West-Vlaanderen",
    "sg:tags":[
        "lady",
        "-",
        "hairdressing"
    ],
    "wof:name":"Michele Haar- & Bruinstudio",
    "wof:placetype":"venue"
},
  "geometry": {"coordinates":[3.2411329746,51.2003211975],"type":"Point"}
}