{
  "type": "Feature",
  "properties": {
    "addr:full":"Bornestraat 24 Nieuwerkerken Limburg 3850",
    "addr:housenumber":"24",
    "addr:postcode":"3850",
    "addr:street":"Bornestraat",
    "iso:country":"BE",
    "sg:address":"Bornestraat 24",
    "sg:city":"Nieuwerkerken",
    "sg:orig_category":"Producteurs de fruits",
    "sg:phone":"+32 11 69 28 07",
    "sg:postcode":"3850",
    "sg:province":"Limburg",
    "wof:name":"Koen Carolus",
    "wof:placetype":"venue"
},
  "geometry": {"coordinates":[5.1866288185,50.8612556458],"type":"Point"}
}