{
  "type": "Feature",
  "properties": {
    "addr:full":"Rumoldusstraat 84 Dilbeek (schepdaal) Vlaams-Brabant 1703",
    "addr:housenumber":"84",
    "addr:postcode":"1703",
    "addr:street":"Rumoldusstraat",
    "iso:country":"BE",
    "sg:address":"Rumoldusstraat 84",
    "sg:city":"Dilbeek (schepdaal)",
    "sg:classifiers":[
        {
            "category":"Freight",
            "type":"Transportation"
        }
    ],
    "sg:phone":"+32 2 569 23 02",
    "sg:postcode":"1703",
    "sg:province":"Vlaams-Brabant",
    "sg:tags":[
        "-",
        "transport"
    ],
    "wof:name":"Quinart En Zoon Bvba",
    "wof:placetype":"venue"
},
  "geometry": {"coordinates":[4.1948738098,50.8392028809],"type":"Point"}
}