{
  "type": "Feature",
  "properties": {
    "iso:country":"BE",
    "sg:address":"Poederleeseweg 115",
    "sg:city":"Lille",
    "sg:orig_category":"Installation de menuiserie en bois and plastique. Installation de menuiserie m\u00e9tallique",
    "sg:phone":"+32 14 88 26 00",
    "sg:postcode":"2275",
    "sg:province":"Antwerpen",
    "wof:name":"Veranda's De Kempen",
    "wof:placetype":"venue"
},
  "geometry": {"coordinates":[4.8298201561,51.2332801819],"type":"Point"}
}