{
  "type": "Feature",
  "properties": {
    "addr:full":"Oudestraat 99 Sint-katelijne-waver Antwerpen 2860",
    "addr:housenumber":"99",
    "addr:postcode":"2860",
    "addr:street":"Oudestraat",
    "iso:country":"BE",
    "sg:address":"Oudestraat 99",
    "sg:city":"Sint-katelijne-waver",
    "sg:orig_category":"Airconditioning and ventilatie",
    "sg:phone":"+32 15 55 29 42",
    "sg:postcode":"2860",
    "sg:province":"Antwerpen",
    "wof:name":"B.v.l.",
    "wof:placetype":"venue"
},
  "geometry": {"coordinates":[4.5160288811,51.0408439636],"type":"Point"}
}