{
  "type": "Feature",
  "properties": {
    "addr:full":"Stationsstraat 8 Jabbeke West-Vlaanderen 8490",
    "addr:housenumber":"8",
    "addr:postcode":"8490",
    "addr:street":"Stationsstraat",
    "iso:country":"BE",
    "sg:address":"Stationsstraat 8",
    "sg:city":"Jabbeke",
    "sg:classifiers":[
        {
            "category":"Wholesale",
            "subcategory":"Beer",
            "type":"Manufacturing & Wholesale Goods"
        }
    ],
    "sg:phone":"+32 50 81 11 23",
    "sg:postcode":"8490",
    "sg:province":"West-Vlaanderen",
    "sg:tags":[
        "ale",
        "-"
    ],
    "wof:name":"Van De Voorde R",
    "wof:placetype":"venue"
},
  "geometry": {"coordinates":[3.0947709084,51.1835403442],"type":"Point"}
}