{
  "type": "Feature",
  "properties": {
    "addr:full":"Mechelsesteenweg 528 Zaventem (nossegem) Vlaams-Brabant 1930",
    "addr:housenumber":"528",
    "addr:postcode":"1930",
    "addr:street":"Mechelsesteenweg",
    "iso:country":"BE",
    "sg:address":"Mechelsesteenweg 528",
    "sg:city":"Zaventem (nossegem)",
    "sg:classifiers":[
        {
            "category":"Food & Beverages",
            "subcategory":"Groceries & Convenience Stores",
            "type":"Retail Goods"
        }
    ],
    "sg:phone":"+32 2 759 68 57",
    "sg:postcode":"1930",
    "sg:province":"Vlaams-Brabant",
    "sg:tags":[
        "grocer"
    ],
    "wof:name":"W B Winkel",
    "wof:placetype":"venue"
},
  "geometry": {"coordinates":[4.5071439743,50.8812522888],"type":"Point"}
}