{
  "type": "Feature",
  "properties": {
    "iso:country":"BE",
    "sg:address":"Chaussee De Gand 503",
    "sg:city":"Bruxelles",
    "sg:classifiers":[
        {
            "category":"Professional",
            "subcategory":"Engineering",
            "type":"Services"
        }
    ],
    "sg:phone":"+32 2 414 70 80",
    "sg:postcode":"1080",
    "sg:province":"Bruxelles-Capitale",
    "sg:tags":[
        "technology",
        "cutting",
        "fine"
    ],
    "wof:name":"Amd S.p.r.l.",
    "wof:placetype":"venue"
},
  "geometry": {"coordinates":[4.3136110306,50.8587913513],"type":"Point"}
}