{
  "type": "Feature",
  "properties": {
    "iso:country":"BE",
    "sg:address":"Meusegemstraat 79",
    "sg:city":"Meise",
    "sg:orig_category":"Groententeelt Rundveehouders",
    "sg:phone":"+32 2 269 18 68",
    "sg:postcode":"1861",
    "sg:province":"Vlaams-Brabant",
    "wof:name":"Frans De Coninck",
    "wof:placetype":"venue"
},
  "geometry": {"coordinates":[4.288517952,50.9595527649],"type":"Point"}
}