{
  "type": "Feature",
  "properties": {
    "addr:full":"Rue D\u00b4anderlues 105 Thuin Hainaut 6530",
    "addr:housenumber":"105",
    "addr:postcode":"6530",
    "addr:street":"Rue D\u00b4Anderlues",
    "iso:country":"BE",
    "sg:address":"Rue D\u00b4anderlues 105",
    "sg:city":"Thuin",
    "sg:orig_category":"Instituts de beaut\u00e9",
    "sg:phone":"+32 475 30 94 48",
    "sg:postcode":"6530",
    "sg:province":"Hainaut",
    "wof:name":"L. Wilmus",
    "wof:placetype":"venue"
},
  "geometry": {"coordinates":[4.2850198746,50.3482246399],"type":"Point"}
}