{
  "type": "Feature",
  "properties": {
    "addr:full":"Avenue Des Arts 19f Bruxelles Bruxelles-Capitale 1000",
    "addr:housenumber":"19f",
    "addr:postcode":"1000",
    "addr:street":"Avenue Des Arts",
    "iso:country":"BE",
    "sg:address":"Avenue Des Arts 19f",
    "sg:city":"Bruxelles",
    "sg:classifiers":[
        {
            "category":"Professional",
            "subcategory":"Art Services",
            "type":"Services"
        }
    ],
    "sg:phone":"+32 2 219 04 84",
    "sg:postcode":"1000",
    "sg:province":"Bruxelles-Capitale",
    "sg:tags":[
        "realization",
        "audio-visual"
    ],
    "wof:name":"Cinergie Asbl",
    "wof:placetype":"venue"
},
  "geometry": {"coordinates":[4.369784832,50.8469467163],"type":"Point"}
}