{
  "type": "Feature",
  "properties": {
    "iso:country":"BE",
    "sg:address":"Amandus-de-vosstraat 4",
    "sg:city":"Geel",
    "sg:orig_category":"M\u00e9decins and sp\u00e9cialistes",
    "sg:phone":"+32 14 58 17 77",
    "sg:postcode":"2440",
    "sg:province":"Antwerpen",
    "wof:name":"J. Bakelants",
    "wof:placetype":"venue"
},
  "geometry": {"coordinates":[4.9998898506,51.163848877],"type":"Point"}
}