{
  "type": "Feature",
  "properties": {
    "addr:full":"Grand Route 106 Sprimont (rouvreux) Li\u00e8ge 4140",
    "addr:postcode":"4140",
    "addr:street":"Grand Route 106;Rouvreux",
    "iso:country":"BE",
    "sg:address":"Grand Route 106",
    "sg:city":"Sprimont (rouvreux)",
    "sg:classifiers":[
        {
            "category":"Travel",
            "subcategory":"Resort",
            "type":"Entertainment"
        }
    ],
    "sg:phone":"+32 4 384 32 28",
    "sg:postcode":"4140",
    "sg:province":"Li\u00e8ge",
    "sg:tags":[
        "vacation"
    ],
    "wof:name":"Perenta",
    "wof:placetype":"venue"
},
  "geometry": {"coordinates":[5.6684727669,50.4860916138],"type":"Point"}
}