{
  "type": "Feature",
  "properties": {
    "iso:country":"BE",
    "sg:address":"Rue De Tournai 61",
    "sg:city":"Hollain",
    "sg:orig_category":"Ordinateurs and \u00e9quipement informatique. R\u00e9alisation de programmes and logiciels",
    "sg:phone":"+32 69 34 52 09",
    "sg:postcode":"7620",
    "sg:province":"Hainaut",
    "wof:name":"Christian Fervaille",
    "wof:placetype":"venue"
},
  "geometry": {"coordinates":[3.4262800217,50.5412483215],"type":"Point"}
}