{
  "type": "Feature",
  "properties": {
    "addr:full":"Bosschelweg 68 Bocholt Limburg 3950",
    "addr:housenumber":"68",
    "addr:postcode":"3950",
    "addr:street":"Bosschelweg",
    "iso:country":"BE",
    "sg:address":"Bosschelweg 68",
    "sg:city":"Bocholt",
    "sg:orig_category":"Woningbouw",
    "sg:phone":"+32 11 62 11 78",
    "sg:postcode":"3950",
    "sg:province":"Limburg",
    "wof:name":"Mentens J",
    "wof:placetype":"venue"
},
  "geometry": {"coordinates":[5.516711235,51.1836624146],"type":"Point"}
}