{
  "type": "Feature",
  "properties": {
    "iso:country":"BE",
    "sg:address":"Rue Des Fontaines 51",
    "sg:city":"Wavre",
    "sg:classifiers":[
        {
            "category":"Home & Garden",
            "subcategory":"Furniture",
            "type":"Retail Goods"
        }
    ],
    "sg:phone":"+32 10 24 73 62",
    "sg:postcode":"1300",
    "sg:province":"Brabant Wallon",
    "sg:tags":[
        "-"
    ],
    "wof:name":"Decor Emoi Sa-ka International Sa",
    "wof:placetype":"venue"
},
  "geometry": {"coordinates":[4.6090598106,50.7144508362],"type":"Point"}
}