{
  "type": "Feature",
  "properties": {
    "iso:country":"BE",
    "sg:address":"Rue Du Couvent 6",
    "sg:city":"Plombi\u00e8res (montzen)",
    "sg:classifiers":[
        {
            "category":"Retail",
            "subcategory":"Auto Repair",
            "type":"Services"
        }
    ],
    "sg:phone":"+32 87 78 54 47",
    "sg:postcode":"4850",
    "sg:province":"Li\u00e8ge",
    "sg:tags":[
        "garage"
    ],
    "wof:name":"Malmendier",
    "wof:placetype":"venue"
},
  "geometry": {"coordinates":[5.9603528976,50.7369117737],"type":"Point"}
}