{
  "type": "Feature",
  "properties": {
    "iso:country":"BE",
    "sg:address":"Woluwelaan 56 B3",
    "sg:city":"Brussel",
    "sg:classifiers":[
        {
            "category":"Professional",
            "subcategory":"Advertising",
            "type":"Services"
        }
    ],
    "sg:phone":"+32 3 366 11 55",
    "sg:postcode":"1200",
    "sg:province":"Bruxelles-Capitale",
    "sg:tags":[
        "agency"
    ],
    "wof:name":"Du Bosch B.v.b.a.",
    "wof:placetype":"venue"
},
  "geometry": {"coordinates":[4.4522547722,51.2020645142],"type":"Point"}
}