{
  "type": "Feature",
  "properties": {
    "iso:country":"BE",
    "sg:address":"Klijtestraat 56",
    "sg:city":"Ieper",
    "sg:orig_category":"Eleveurs and marchands de porcs. Eleveurs de bovins",
    "sg:phone":"+32 57 42 20 18",
    "sg:postcode":"8906",
    "sg:province":"West-Vlaanderen",
    "wof:name":"Joost Danneels",
    "wof:placetype":"venue"
},
  "geometry": {"coordinates":[2.8038659096,50.8932113647],"type":"Point"}
}