{
  "type": "Feature",
  "properties": {
    "iso:country":"BE",
    "sg:address":"Vaartstraat 4 A",
    "sg:city":"Zandhoven",
    "sg:orig_category":"R\u00e9cup\u00e9ration de mati\u00e8res m\u00e9talliques recyclables and d\u00e9molisseurs de voitures. Entretien et r\u00e9parati",
    "sg:phone":"+32 3 464 03 10",
    "sg:postcode":"2240",
    "sg:province":"Antwerpen",
    "wof:name":"G.s. Takeldienst",
    "wof:placetype":"venue"
},
  "geometry": {"coordinates":[4.6431679726,51.197052002],"type":"Point"}
}