{
  "type": "Feature",
  "properties": {
    "iso:country":"BE",
    "sg:address":"Oude Liersebaan 125g",
    "sg:city":"Heist-op-den-berg",
    "sg:classifiers":[
        {
            "category":"Professional",
            "subcategory":"Accounting & Tax Preparation",
            "type":"Services"
        }
    ],
    "sg:phone":"+32 15 24 96 81",
    "sg:postcode":"2220",
    "sg:province":"Antwerpen",
    "sg:tags":[
        "accountant"
    ],
    "wof:name":"Verschueren W",
    "wof:placetype":"venue"
},
  "geometry": {"coordinates":[4.7366080284,51.0487098694],"type":"Point"}
}