{
  "type": "Feature",
  "properties": {
    "addr:full":"Aalststraat 132 Oudenaarde Oost-Vlaanderen 9700",
    "addr:housenumber":"132",
    "addr:postcode":"9700",
    "addr:street":"Aalststraat",
    "iso:country":"BE",
    "sg:address":"Aalststraat 132",
    "sg:city":"Oudenaarde",
    "sg:classifiers":[
        {
            "category":"Professional",
            "subcategory":"Accounting & Tax Preparation",
            "type":"Services"
        }
    ],
    "sg:phone":"+32 55 33 59 33",
    "sg:postcode":"9700",
    "sg:province":"Oost-Vlaanderen",
    "sg:tags":[
        "bookkeeper"
    ],
    "wof:name":"Nobels J",
    "wof:placetype":"venue"
},
  "geometry": {"coordinates":[3.6157650948,50.8415641785],"type":"Point"}
}