{
  "type": "Feature",
  "properties": {
    "addr:full":"Hoogledestraat 112 Kortemark West-Vlaanderen 8610",
    "addr:housenumber":"112",
    "addr:postcode":"8610",
    "addr:street":"Hoogledestraat",
    "iso:country":"BE",
    "sg:address":"Hoogledestraat 112",
    "sg:city":"Kortemark",
    "sg:classifiers":[
        {
            "category":"Arena",
            "subcategory":"Sports Club",
            "type":"Entertainment"
        }
    ],
    "sg:phone":"+32 51 56 75 24",
    "sg:postcode":"8610",
    "sg:province":"West-Vlaanderen",
    "sg:tags":[
        "de"
    ],
    "wof:name":"De Vliegersclub",
    "wof:placetype":"venue"
},
  "geometry": {"coordinates":[3.0492949486,51.0120773315],"type":"Point"}
}