{
  "type": "Feature",
  "properties": {
    "iso:country":"BE",
    "sg:address":"Odegemstraat 71",
    "sg:city":"Brugge",
    "sg:orig_category":"Huishoudapparaten, televisies and radio's Verhuur televisie- and audiovisuele apparatuur",
    "sg:phone":"+32 50 35 10 46",
    "sg:postcode":"8310",
    "sg:province":"West-Vlaanderen",
    "wof:name":"P.v.l.-sound",
    "wof:placetype":"venue"
},
  "geometry": {"coordinates":[3.2434980869,51.1907501221],"type":"Point"}
}