{
  "type": "Feature",
  "properties": {
    "iso:country":"BE",
    "sg:address":"Rue Des C\u00c9vennes 27",
    "sg:city":"Chaumont-gistoux",
    "sg:orig_category":"Diverse bouwafwerking and reiniging",
    "sg:phone":"+32 10 68 85 17",
    "sg:postcode":"1325",
    "sg:province":"Brabant Wallon",
    "wof:name":"Bernard Hills",
    "wof:placetype":"venue"
},
  "geometry": {"coordinates":[4.692756176,50.6937141418],"type":"Point"}
}