{
  "type": "Feature",
  "properties": {
    "addr:full":"Heiseneinde 57 Merksplas Antwerpen 2330",
    "addr:housenumber":"57",
    "addr:postcode":"2330",
    "addr:street":"Heiseneinde",
    "iso:country":"BE",
    "sg:address":"Heiseneinde 57",
    "sg:city":"Merksplas",
    "sg:orig_category":"Eleveurs de bovins",
    "sg:phone":"+32 14 63 35 59",
    "sg:postcode":"2330",
    "sg:province":"Antwerpen",
    "wof:name":"Jan Jacobs",
    "wof:placetype":"venue"
},
  "geometry": {"coordinates":[4.8577480316,51.3517913818],"type":"Point"}
}