{
  "type": "Feature",
  "properties": {
    "addr:full":"Groene Wandeling 9 Kontich Antwerpen 2550",
    "addr:housenumber":"9",
    "addr:postcode":"2550",
    "addr:street":"Groene Wandeling",
    "iso:country":"BE",
    "sg:address":"Groene Wandeling 9",
    "sg:city":"Kontich",
    "sg:orig_category":"Elektrische installaties voor woningen Herstellingswinkels voor diverse persoonlijke and huishoudart",
    "sg:phone":"+32 3 457 14 60",
    "sg:postcode":"2550",
    "sg:province":"Antwerpen",
    "wof:name":"Inter Securityservice",
    "wof:placetype":"venue"
},
  "geometry": {"coordinates":[4.4747619629,51.1238555908],"type":"Point"}
}