{
  "type": "Feature",
  "properties": {
    "addr:full":"Rue De Jupille 29 Beyne-heusay Li\u00e8ge 4610",
    "addr:housenumber":"29",
    "addr:postcode":"4610",
    "addr:street":"Rue De Jupille",
    "iso:country":"BE",
    "sg:address":"Rue De Jupille 29",
    "sg:city":"Beyne-heusay",
    "sg:orig_category":"Kapsalons",
    "sg:phone":"+32 4 367 20 29",
    "sg:postcode":"4610",
    "sg:province":"Li\u00e8ge",
    "wof:name":"Coiffure New Style",
    "wof:placetype":"venue"
},
  "geometry": {"coordinates":[5.6523370743,50.6240844727],"type":"Point"}
}