{
  "type": "Feature",
  "properties": {
    "iso:country":"BE",
    "sg:address":"Rue De Neufch\u00c2teau 18bb",
    "sg:city":"Libramont-chevigny",
    "sg:orig_category":"Herstellingen and onderhoud aan huis voor voertuigen Taxi's",
    "sg:phone":"+32 475 69 26 92",
    "sg:postcode":"6800",
    "sg:province":"Luxembourg",
    "wof:name":"Centre Ardenne D\u00c9pannage",
    "wof:placetype":"venue"
},
  "geometry": {"coordinates":[5.3761348724,49.9199943542],"type":"Point"}
}