{
  "type": "Feature",
  "properties": {
    "iso:country":"BE",
    "sg:address":"Rue Musin 3-5 Box 47",
    "sg:city":"Bruxelles (saint-josse-ten-noode)",
    "sg:classifiers":[
        {
            "category":"Health Services",
            "subcategory":"Doctor",
            "type":"Services"
        }
    ],
    "sg:phone":"+32 2 219 13 37",
    "sg:postcode":"1210",
    "sg:province":"Bruxelles-Capitale",
    "sg:tags":[
        "medicinephysicians",
        "surgeon"
    ],
    "wof:name":"Dragan Maria",
    "wof:placetype":"venue"
},
  "geometry": {"coordinates":[4.366133213,50.8555145264],"type":"Point"}
}