{
  "type": "Feature",
  "properties": {
    "addr:full":"Boulevard Anspach 99 Bruxelles Bruxelles-Capitale 1000",
    "addr:housenumber":"99",
    "addr:postcode":"1000",
    "addr:street":"Boulevard Anspach",
    "iso:country":"BE",
    "sg:address":"Boulevard Anspach 99",
    "sg:city":"Bruxelles",
    "sg:classifiers":[
        {
            "category":"Utilities",
            "subcategory":"Mobile Phone",
            "type":"Services"
        }
    ],
    "sg:phone":"+32 2 511 54 00",
    "sg:postcode":"1000",
    "sg:province":"Bruxelles-Capitale",
    "sg:tags":[
        "access",
        "gsm",
        "-",
        "apparatus"
    ],
    "wof:name":"Aidel Sprl",
    "wof:placetype":"venue"
},
  "geometry": {"coordinates":[4.3485279083,50.8474082947],"type":"Point"}
}