{
  "type": "Feature",
  "properties": {
    "iso:country":"BE",
    "sg:address":"Rue Basse 61",
    "sg:city":"Messancy (selange)",
    "sg:classifiers":[
        {
            "category":"Communications",
            "subcategory":"Television Station",
            "type":"Services"
        }
    ],
    "sg:phone":"+32 63 37 16 32",
    "sg:postcode":"6781",
    "sg:province":"Luxembourg",
    "sg:tags":[
        "report",
        "video"
    ],
    "wof:name":"Virep",
    "wof:placetype":"venue"
},
  "geometry": {"coordinates":[5.8550209999,49.6096305847],"type":"Point"}
}