{
  "type": "Feature",
  "properties": {
    "addr:full":"Dekenijstraat 17 Box 5 Kortenberg (erps-kwerps) Vlaams-Brabant 3071",
    "addr:housenumber":"17;5",
    "addr:postcode":"3071",
    "addr:street":"Dekenijstraat;Box",
    "iso:country":"BE",
    "sg:address":"Dekenijstraat 17 Box 5",
    "sg:city":"Kortenberg (erps-kwerps)",
    "sg:classifiers":[
        {
            "category":"Professional",
            "subcategory":"Art Services",
            "type":"Services"
        }
    ],
    "sg:phone":"+32 495 23 68 12",
    "sg:postcode":"3071",
    "sg:province":"Vlaams-Brabant",
    "sg:tags":[
        "designer",
        "display"
    ],
    "wof:name":"Fied",
    "wof:placetype":"venue"
},
  "geometry": {"coordinates":[4.5592041016,50.9029655457],"type":"Point"}
}