{
  "type": "Feature",
  "properties": {
    "iso:country":"BE",
    "sg:address":"Sentier De Blaugies 37",
    "sg:city":"Colfontaine",
    "sg:orig_category":"Rundveehouders",
    "sg:phone":"+32 65 63 13 04",
    "sg:postcode":"7340",
    "sg:province":"Hainaut",
    "wof:name":"Fernand Bertiaux",
    "wof:placetype":"venue"
},
  "geometry": {"coordinates":[3.8215000629,50.3985748291],"type":"Point"}
}