{
  "type": "Feature",
  "properties": {
    "addr:full":"Kapellestraat 25 Waarschoot Oost-Vlaanderen 9950",
    "addr:housenumber":"25",
    "addr:postcode":"9950",
    "addr:street":"Kapellestraat",
    "iso:country":"BE",
    "sg:address":"Kapellestraat 25",
    "sg:city":"Waarschoot",
    "sg:orig_category":"D\u00e9m\u00e9nagements. Combustibles",
    "sg:phone":"+32 9 377 02 70",
    "sg:postcode":"9950",
    "sg:province":"Oost-Vlaanderen",
    "wof:name":"De Vlieger & Co",
    "wof:placetype":"venue"
},
  "geometry": {"coordinates":[3.6140799522,51.159236908],"type":"Point"}
}