{
  "type": "Feature",
  "properties": {
    "iso:country":"BE",
    "sg:address":"Avenue Louis Pasteur 13",
    "sg:city":"Renaix",
    "sg:classifiers":[
        {
            "category":"Insurance",
            "subcategory":"Insurance Agent",
            "type":"Services"
        }
    ],
    "sg:phone":"+32 55 21 12 77",
    "sg:postcode":"9600",
    "sg:province":"Oost-Vlaanderen",
    "sg:tags":[
        "broker"
    ],
    "wof:name":"Reyntjens",
    "wof:placetype":"venue"
},
  "geometry": {"coordinates":[3.6073079109,50.7402648926],"type":"Point"}
}