{
  "type": "Feature",
  "properties": {
    "iso:country":"BE",
    "sg:address":"Rue Grand Fau 1",
    "sg:city":"Mettet",
    "sg:orig_category":"Biens d'occasion. Ordinateurs and \u00e9quipement informatique. Location de machines de bureau and mat\u00e9ri",
    "sg:phone":"+32 71 72 76 29",
    "sg:postcode":"5640",
    "sg:province":"Namur",
    "wof:name":"Bureau Neuronics",
    "wof:placetype":"venue"
},
  "geometry": {"coordinates":[4.6395568848,50.3472175598],"type":"Point"}
}