{
  "type": "Feature",
  "properties": {
    "addr:full":"Vlaamsekunstlaan 15 Antwerpen Antwerpen 2020",
    "addr:housenumber":"15",
    "addr:postcode":"2020",
    "addr:street":"Vlaamsekunstlaan",
    "iso:country":"BE",
    "sg:address":"Vlaamsekunstlaan 15",
    "sg:city":"Antwerpen",
    "sg:orig_category":"Eclairage et \u00e9quipements du foyer",
    "sg:phone":"+32 3 216 32 50",
    "sg:postcode":"2020",
    "sg:province":"Antwerpen",
    "wof:name":"Koster P",
    "wof:placetype":"venue"
},
  "geometry": {"coordinates":[4.3926348686,51.1894187927],"type":"Point"}
}