{
  "type": "Feature",
  "properties": {
    "iso:country":"BE",
    "sg:address":"Tarwestraat 135",
    "sg:city":"Oostende",
    "sg:classifiers":[
        {
            "category":"Professional",
            "subcategory":"Management & Consulting",
            "type":"Services"
        }
    ],
    "sg:phone":"+32 59 70 26 04",
    "sg:postcode":"8400",
    "sg:province":"West-Vlaanderen",
    "sg:tags":[
        "tax-consultants"
    ],
    "wof:name":"Devroe B Bvba",
    "wof:placetype":"venue"
},
  "geometry": {"coordinates":[2.9104230404,51.2154197693],"type":"Point"}
}