{
  "type": "Feature",
  "properties": {
    "addr:full":"Flor\u00c9allaan 84 Ukkel/uccle Bruxelles-Capitale 1180",
    "addr:housenumber":"84",
    "addr:postcode":"1180",
    "addr:street":"Flore\u0301Allaan;/",
    "iso:country":"BE",
    "sg:address":"Flor\u00c9allaan 84",
    "sg:city":"Ukkel/uccle",
    "sg:orig_category":"Openbare bibliotheken and archieven",
    "sg:phone":"+32 2 344 35 12",
    "sg:postcode":"1180",
    "sg:province":"Bruxelles-Capitale",
    "wof:name":"Ludo Mon Toit A Moi",
    "wof:placetype":"venue"
},
  "geometry": {"coordinates":[4.3403539658,50.8086929321],"type":"Point"}
}