{
  "type": "Feature",
  "properties": {
    "iso:country":"BE",
    "sg:address":"Kerkstraat 71",
    "sg:city":"Drogenbos/drogenbos",
    "sg:orig_category":"Artsen and specialisten",
    "sg:phone":"+32 2 377 57 30",
    "sg:postcode":"1620",
    "sg:province":"Vlaams-Brabant",
    "wof:name":"Willy De Ruydts",
    "wof:placetype":"venue"
},
  "geometry": {"coordinates":[4.318169117,50.7891426086],"type":"Point"}
}