{
  "type": "Feature",
  "properties": {
    "iso:country":"BE",
    "sg:address":"Liersstraat 7",
    "sg:city":"Genk",
    "sg:orig_category":"D\u00e9taillants en pi\u00e8ces and accessoires de voitures. Electrom\u00e9nager, t\u00e9l\u00e9visions and radios",
    "sg:phone":"+32 89 30 43 53",
    "sg:postcode":"3600",
    "sg:province":"Limburg",
    "wof:name":"E.t.c.",
    "wof:placetype":"venue"
},
  "geometry": {"coordinates":[5.4989938736,50.9521064758],"type":"Point"}
}