{
  "type": "Feature",
  "properties": {
    "addr:full":"Stenenmolenstraat 128 Mechelen Antwerpen 2800",
    "addr:housenumber":"128",
    "addr:postcode":"2800",
    "addr:street":"Stenenmolenstraat",
    "iso:country":"BE",
    "sg:address":"Stenenmolenstraat 128",
    "sg:city":"Mechelen",
    "sg:classifiers":[
        {
            "category":"Arena",
            "subcategory":"Sports Club",
            "type":"Entertainment"
        }
    ],
    "sg:phone":"+32 15 42 22 46",
    "sg:postcode":"2800",
    "sg:province":"Antwerpen",
    "wof:name":"Mavoc Mechelen",
    "wof:placetype":"venue"
},
  "geometry": {"coordinates":[4.4780020714,51.0095252991],"type":"Point"}
}