{
  "type": "Feature",
  "properties": {
    "addr:full":"Avenue Des Armures 44 Bruxelles (forest) Bruxelles-Capitale 1190",
    "addr:housenumber":"44",
    "addr:postcode":"1190",
    "addr:street":"Avenue Des Armures",
    "iso:country":"BE",
    "sg:address":"Avenue Des Armures 44",
    "sg:city":"Bruxelles (forest)",
    "sg:classifiers":[
        {
            "category":"Building & Trades",
            "subcategory":"Cleaning & Sanitation",
            "type":"Services"
        }
    ],
    "sg:phone":"+32 2 346 20 06",
    "sg:postcode":"1190",
    "sg:province":"Bruxelles-Capitale",
    "sg:tags":[
        "cleaner",
        "window"
    ],
    "wof:name":"Ames C",
    "wof:placetype":"venue"
},
  "geometry": {"coordinates":[4.3363161087,50.8148536682],"type":"Point"}
}