{
  "type": "Feature",
  "properties": {
    "addr:full":"Pollareveld 28 Meise Vlaams-Brabant 1861",
    "addr:housenumber":"28",
    "addr:postcode":"1861",
    "addr:street":"Pollareveld",
    "iso:country":"BE",
    "sg:address":"Pollareveld 28",
    "sg:city":"Meise",
    "sg:classifiers":[
        {
            "category":"Arena",
            "subcategory":"Sports Club",
            "type":"Entertainment"
        }
    ],
    "sg:phone":"+32 52 30 50 62",
    "sg:postcode":"1861",
    "sg:province":"Vlaams-Brabant",
    "sg:tags":[
        "de"
    ],
    "wof:name":"Jazz-gym",
    "wof:placetype":"venue"
},
  "geometry": {"coordinates":[4.3273038864,50.985710144],"type":"Point"}
}