{
  "type": "Feature",
  "properties": {
    "addr:full":"Sentier De L'eglise 65 Ch\u00e2telet (bouffioulx) Hainaut 6200",
    "addr:housenumber":"65",
    "addr:postcode":"6200",
    "addr:street":"Sentier De L'Eglise",
    "iso:country":"BE",
    "sg:address":"Sentier De L'eglise 65",
    "sg:city":"Ch\u00e2telet (bouffioulx)",
    "sg:classifiers":[
        {
            "category":"Health Services",
            "subcategory":"Health Practitioner",
            "type":"Services"
        }
    ],
    "sg:phone":"+32 71 38 27 94",
    "sg:postcode":"6200",
    "sg:province":"Hainaut",
    "sg:tags":[
        "physiotherapist"
    ],
    "wof:name":"Carlier Ludivine",
    "wof:placetype":"venue"
},
  "geometry": {"coordinates":[4.5093970299,50.3844223022],"type":"Point"}
}