{
  "type": "Feature",
  "properties": {
    "addr:full":"Rue Du Coumagne 24 Gerpinnes Hainaut 6280",
    "addr:housenumber":"24",
    "addr:postcode":"6280",
    "addr:street":"Rue Du Coumagne;Hainaut",
    "iso:country":"BE",
    "sg:address":"Rue Du Coumagne 24",
    "sg:city":"Gerpinnes",
    "sg:orig_category":"Landmeters and schatters",
    "sg:phone":"+32 71 50 18 77",
    "sg:postcode":"6280",
    "sg:province":"Hainaut",
    "wof:name":"Francis Mincke",
    "wof:placetype":"venue"
},
  "geometry": {"coordinates":[4.5706949234,50.3588294983],"type":"Point"}
}