{
  "type": "Feature",
  "properties": {
    "addr:full":"Steenweg Op Tielen 68 Turnhout Antwerpen 2300",
    "addr:housenumber":"68",
    "addr:postcode":"2300",
    "addr:street":"Steenweg Op Tielen",
    "iso:country":"BE",
    "sg:address":"Steenweg Op Tielen 68",
    "sg:city":"Turnhout",
    "sg:classifiers":[
        {
            "category":"Banks & Credit Unions",
            "subcategory":"Investment Brokerage",
            "type":"Services"
        }
    ],
    "sg:phone":"+32 14 40 25 00",
    "sg:postcode":"2300",
    "sg:province":"Antwerpen",
    "sg:tags":[
        "printing",
        "-"
    ],
    "wof:name":"Brepols Graphic Industries Nv",
    "wof:placetype":"venue"
},
  "geometry": {"coordinates":[4.9344968796,51.303440094],"type":"Point"}
}