{
  "type": "Feature",
  "properties": {
    "addr:full":"Jan Davidlaan 11 Lommel Limburg 3920",
    "addr:housenumber":"11",
    "addr:postcode":"3920",
    "addr:street":"Jan Davidlaan",
    "iso:country":"BE",
    "sg:address":"Jan Davidlaan 11",
    "sg:city":"Lommel",
    "sg:classifiers":[
        {
            "category":"Health Services",
            "subcategory":"Nursing And Care Facility",
            "type":"Services"
        }
    ],
    "sg:phone":"+32 11 54 10 17",
    "sg:postcode":"3920",
    "sg:province":"Limburg",
    "sg:tags":[
        "public"
    ],
    "wof:name":"O.c.m.w.",
    "wof:placetype":"venue"
},
  "geometry": {"coordinates":[5.2849860191,51.2290077209],"type":"Point"}
}