{
  "type": "Feature",
  "properties": {
    "addr:full":"Schomstraat 46 Beringen (koersel) Limburg 3582",
    "addr:housenumber":"46",
    "addr:postcode":"3582",
    "addr:street":"Schomstraat",
    "iso:country":"BE",
    "sg:address":"Schomstraat 46",
    "sg:city":"Beringen (koersel)",
    "sg:classifiers":[
        {
            "category":"Social Services",
            "subcategory":"Job Training",
            "type":"Services"
        }
    ],
    "sg:phone":"+32 11 43 44 75",
    "sg:postcode":"3582",
    "sg:province":"Limburg",
    "sg:tags":[
        "personnel"
    ],
    "wof:name":"Qualityconsultancy & Training",
    "wof:placetype":"venue"
},
  "geometry": {"coordinates":[5.2708749771,51.0595359802],"type":"Point"}
}