{
  "type": "Feature",
  "properties": {
    "addr:full":"Rue Neuve 71 Charleroi Hainaut 6061",
    "addr:housenumber":"71",
    "addr:postcode":"6061",
    "addr:street":"Rue Neuve;Hainaut",
    "iso:country":"BE",
    "sg:address":"Rue Neuve 71",
    "sg:city":"Charleroi",
    "sg:orig_category":"M\u00e9decins and sp\u00e9cialistes",
    "sg:phone":"+32 71 33 33 63",
    "sg:postcode":"6061",
    "sg:province":"Hainaut",
    "wof:name":"St\u00c9phane Beloy",
    "wof:placetype":"venue"
},
  "geometry": {"coordinates":[4.4554300308,50.4093399048],"type":"Point"}
}