{
  "type": "Feature",
  "properties": {
    "addr:full":"Orbanlaan 86 Sint-pieters-woluwe/woluwe-saint-pierre Bruxelles-Capitale 1150",
    "addr:housenumber":"86",
    "addr:postcode":"1150",
    "addr:street":"Orbanlaan;/",
    "iso:country":"BE",
    "sg:address":"Orbanlaan 86",
    "sg:city":"Sint-pieters-woluwe/woluwe-saint-pierre",
    "sg:orig_category":"Artsen and specialisten",
    "sg:phone":"+32 2 762 20 30",
    "sg:postcode":"1150",
    "sg:province":"Bruxelles-Capitale",
    "wof:name":"Raymond De Clercq",
    "wof:placetype":"venue"
},
  "geometry": {"coordinates":[4.455737114,50.834487915],"type":"Point"}
}