{
  "type": "Feature",
  "properties": {
    "iso:country":"BE",
    "sg:address":"Vijfhoek 3",
    "sg:city":"Mechelen",
    "sg:orig_category":"Agences d\u00b4interim and personnel temporaire",
    "sg:phone":"+32 15 41 29 75",
    "sg:postcode":"2800",
    "sg:province":"Antwerpen",
    "wof:name":"Creyf\u00b4s Interim",
    "wof:placetype":"venue"
},
  "geometry": {"coordinates":[4.482336998,51.0227241516],"type":"Point"}
}