{
  "type": "Feature",
  "properties": {
    "iso:country":"BE",
    "sg:address":"Koningin Astridlaan 1",
    "sg:city":"Edingen/enghien",
    "sg:orig_category":"Verplichte sociale verzekeringen",
    "sg:phone":"+32 2 395 34 31",
    "sg:postcode":"7850",
    "sg:province":"Hainaut",
    "wof:name":"Mutualit\u00c9 Lib\u00c9rale",
    "wof:placetype":"venue"
},
  "geometry": {"coordinates":[4.0413570404,50.694896698],"type":"Point"}
}