{
  "type": "Feature",
  "properties": {
    "addr:full":"F\u00c9lix Hapstraat 11 Etterbeek Bruxelles-Capitale 1040",
    "addr:housenumber":"11",
    "addr:postcode":"1040",
    "addr:street":"Fe\u0301Lix Hapstraat",
    "iso:country":"BE",
    "sg:address":"F\u00c9lix Hapstraat 11",
    "sg:city":"Etterbeek",
    "sg:orig_category":"Diverse zakelijke dienstverlening Organisatie van beurzen, congressen and tentoonstellingen Ruimtes ",
    "sg:phone":"+32 2 742 29 21",
    "sg:postcode":"1040",
    "sg:province":"Bruxelles-Capitale",
    "wof:name":"Le Bouche \u00c0 L\u00b4oreille",
    "wof:placetype":"venue"
},
  "geometry": {"coordinates":[4.3907089233,50.8369522095],"type":"Point"}
}