{
  "type": "Feature",
  "properties": {
    "iso:country":"BE",
    "sg:address":"Sint-blasiusstraat 28",
    "sg:city":"Roeselare",
    "sg:orig_category":"Installation de menuiserie en bois and plastique",
    "sg:phone":"+32 51 24 22 83",
    "sg:postcode":"8800",
    "sg:province":"West-Vlaanderen",
    "wof:name":"Kurt Samyn",
    "wof:placetype":"venue"
},
  "geometry": {"coordinates":[3.1512598991,50.9351997375],"type":"Point"}
}