{
  "type": "Feature",
  "properties": {
    "addr:full":"Tipstraat 28 Bilzen (beverst) Limburg 3740",
    "addr:housenumber":"28",
    "addr:postcode":"3740",
    "addr:street":"Tipstraat",
    "iso:country":"BE",
    "sg:address":"Tipstraat 28",
    "sg:city":"Bilzen (beverst)",
    "sg:classifiers":[
        {
            "category":"Retail",
            "subcategory":"Auto Repair",
            "type":"Services"
        }
    ],
    "sg:phone":"+32 89 61 46 11",
    "sg:postcode":"3740",
    "sg:province":"Limburg",
    "sg:tags":[
        "garage"
    ],
    "wof:name":"Intercars Beverst Bvba",
    "wof:placetype":"venue"
},
  "geometry": {"coordinates":[5.4593000412,50.8968200684],"type":"Point"}
}