{
  "type": "Feature",
  "properties": {
    "iso:country":"BE",
    "sg:address":"Arteveldestraat 165",
    "sg:city":"Brussel/bruxelles",
    "sg:classifiers":[
        {
            "category":"Restaurant",
            "type":"Food & Drink"
        }
    ],
    "sg:phone":"+32 2 513 41 23",
    "sg:postcode":"1000",
    "sg:province":"Bruxelles-Capitale",
    "sg:tags":[
        "caf\u00e9s"
    ],
    "wof:name":"L'arteveld",
    "wof:placetype":"venue"
},
  "geometry": {"coordinates":[4.3427810669,50.8462638855],"type":"Point"}
}