{
  "type": "Feature",
  "properties": {
    "iso:country":"BE",
    "sg:address":"Maststraat 51",
    "sg:city":"Essen",
    "sg:classifiers":[
        {
            "category":"Health Services",
            "subcategory":"Health Practitioner",
            "type":"Services"
        }
    ],
    "sg:phone":"+32 3 667 38 73",
    "sg:postcode":"2910",
    "sg:province":"Antwerpen",
    "sg:tags":[
        "physiotherapist"
    ],
    "wof:name":"Testers Jan",
    "wof:placetype":"venue"
},
  "geometry": {"coordinates":[4.4416928291,51.4538345337],"type":"Point"}
}