{
  "type": "Feature",
  "properties": {
    "iso:country":"BE",
    "sg:address":"Rue Des Crayas 17",
    "sg:city":"Viroinval",
    "sg:orig_category":"Woningbouw",
    "sg:phone":"+32 60 31 12 00",
    "sg:postcode":"5670",
    "sg:province":"Namur",
    "wof:name":"Serge Delers",
    "wof:placetype":"venue"
},
  "geometry": {"coordinates":[4.5502557755,50.0626602173],"type":"Point"}
}