{
  "type": "Feature",
  "properties": {
    "addr:full":"Rue Du Follet 11 Tournai (kain) Hainaut 7540",
    "addr:housenumber":"11",
    "addr:postcode":"7540",
    "addr:street":"Rue Du Follet",
    "iso:country":"BE",
    "sg:address":"Rue Du Follet 11",
    "sg:city":"Tournai (kain)",
    "sg:classifiers":[
        {
            "category":"Manufacturing",
            "subcategory":"Tools & Machinery",
            "type":"Manufacturing & Wholesale Goods"
        }
    ],
    "sg:phone":"+32 69 21 21 07",
    "sg:postcode":"7540",
    "sg:province":"Hainaut",
    "sg:tags":[
        "builder"
    ],
    "wof:name":"Atelier Lefebvre P & Fils Sprl",
    "wof:placetype":"venue"
},
  "geometry": {"coordinates":[3.413079977,50.6301193237],"type":"Point"}
}