{
  "type": "Feature",
  "properties": {
    "iso:country":"BE",
    "sg:address":"Rue De Ghlin 91",
    "sg:city":"Jurbise",
    "sg:classifiers":[
        {
            "category":"Retail",
            "subcategory":"Auto Repair",
            "type":"Services"
        }
    ],
    "sg:phone":"+32 65 22 57 10",
    "sg:postcode":"7050",
    "sg:province":"Hainaut",
    "sg:tags":[
        "automobile-body"
    ],
    "wof:name":"Huin F",
    "wof:placetype":"venue"
},
  "geometry": {"coordinates":[3.9090890884,50.5180015564],"type":"Point"}
}