{
  "type": "Feature",
  "properties": {
    "iso:country":"BE",
    "sg:address":"Hasseltsestraat 29",
    "sg:city":"Diest",
    "sg:orig_category":"Artsen and specialisten Maatschappelijke dienstverlening",
    "sg:phone":"+32 13 33 52 47",
    "sg:postcode":"3290",
    "sg:province":"Vlaams-Brabant",
    "wof:name":"Jac",
    "wof:placetype":"venue"
},
  "geometry": {"coordinates":[5.0531039238,50.9814949036],"type":"Point"}
}