{
  "type": "Feature",
  "properties": {
    "addr:full":"Rue Entre-deux-portes 10 Huy Li\u00e8ge 4500",
    "addr:housenumber":"10",
    "addr:postcode":"4500",
    "addr:street":"Rue Entre-Deux-Portes",
    "iso:country":"BE",
    "sg:address":"Rue Entre-deux-portes 10",
    "sg:city":"Huy",
    "sg:classifiers":[
        {
            "category":"Fast Food",
            "type":"Food & Drink"
        }
    ],
    "sg:phone":"+32 85 21 25 42",
    "sg:postcode":"4500",
    "sg:province":"Li\u00e8ge",
    "sg:tags":[
        "\u00c0",
        "emporter",
        "restaurants"
    ],
    "wof:name":"Traiteur Grande Muraille",
    "wof:placetype":"venue"
},
  "geometry": {"coordinates":[5.2300171852,50.5252838135],"type":"Point"}
}