{
  "type": "Feature",
  "properties": {
    "iso:country":"BE",
    "sg:address":"Chauss\u00c9e De Namur 24-26",
    "sg:city":"Charleroi",
    "sg:orig_category":"Entretien and r\u00e9parations de voitures",
    "sg:phone":"+32 71 41 19 26",
    "sg:postcode":"6061",
    "sg:province":"Hainaut",
    "wof:name":"Ets. M.wanet Et Fils S.a.",
    "wof:placetype":"venue"
},
  "geometry": {"coordinates":[4.4675598145,50.4221496582],"type":"Point"}
}