{
  "type": "Feature",
  "properties": {
    "addr:full":"Dorpsstraat 71 Deinze Oost-Vlaanderen 9800",
    "addr:housenumber":"71",
    "addr:postcode":"9800",
    "addr:street":"Dorpsstraat",
    "iso:country":"BE",
    "sg:address":"Dorpsstraat 71",
    "sg:city":"Deinze",
    "sg:orig_category":"Quincailleries. Electrom\u00e9nager, t\u00e9l\u00e9visions and radios",
    "sg:phone":"+32 9 386 31 69",
    "sg:postcode":"9800",
    "sg:province":"Oost-Vlaanderen",
    "wof:name":"Valere Cornelis",
    "wof:placetype":"venue"
},
  "geometry": {"coordinates":[3.530174017,50.9863166809],"type":"Point"}
}