{
  "type": "Feature",
  "properties": {
    "addr:full":"Rue De Fenal 5 Mettet Namur 5641",
    "addr:housenumber":"5",
    "addr:postcode":"5641",
    "addr:street":"Rue De Fenal",
    "iso:country":"BE",
    "sg:address":"Rue De Fenal 5",
    "sg:city":"Mettet",
    "sg:orig_category":"Houtbewerking and -behandeling Installatie van houten of kunststof schrijnwerk",
    "sg:phone":"+32 71 72 72 26",
    "sg:postcode":"5641",
    "sg:province":"Namur",
    "wof:name":"Masset",
    "wof:placetype":"venue"
},
  "geometry": {"coordinates":[4.7045512199,50.308807373],"type":"Point"}
}