{
  "type": "Feature",
  "properties": {
    "addr:full":"Steenweg Baarle 3 Ravels Antwerpen 2382",
    "addr:housenumber":"3",
    "addr:postcode":"2382",
    "addr:street":"Steenweg Baarle",
    "iso:country":"BE",
    "sg:address":"Steenweg Baarle 3",
    "sg:city":"Ravels",
    "sg:orig_category":"Imprimeries and copyshops",
    "sg:phone":"+32 14 65 67 79",
    "sg:postcode":"2382",
    "sg:province":"Antwerpen",
    "wof:name":"Filip Dockx",
    "wof:placetype":"venue"
},
  "geometry": {"coordinates":[5.0376381874,51.4490089417],"type":"Point"}
}