{
  "type": "Feature",
  "properties": {
    "addr:full":"Malmedyer Strasse 82 Eupen Li\u00e8ge 4700",
    "addr:housenumber":"82",
    "addr:postcode":"4700",
    "addr:street":"Malmedyer Strasse",
    "iso:country":"BE",
    "sg:address":"Malmedyer Strasse 82",
    "sg:city":"Eupen",
    "sg:classifiers":[
        {
            "category":"Building & Trades",
            "subcategory":"Landscaping Services",
            "type":"Services"
        }
    ],
    "sg:phone":"+32 87 55 61 32",
    "sg:postcode":"4700",
    "sg:province":"Li\u00e8ge",
    "sg:tags":[
        "forestry"
    ],
    "wof:name":"Johnen Sprl",
    "wof:placetype":"venue"
},
  "geometry": {"coordinates":[6.0359659195,50.6191291809],"type":"Point"}
}