{
  "type": "Feature",
  "properties": {
    "addr:full":"Route De Ti\u00c8ge 44 Spa Li\u00e8ge 4900",
    "addr:housenumber":"44",
    "addr:postcode":"4900",
    "addr:street":"Route De Tie\u0300Ge",
    "iso:country":"BE",
    "sg:address":"Route De Ti\u00c8ge 44",
    "sg:city":"Spa",
    "sg:orig_category":"Rusthuizen and serviceflats",
    "sg:phone":"+32 87 47 43 13",
    "sg:postcode":"4900",
    "sg:province":"Li\u00e8ge",
    "wof:name":"La Charmille",
    "wof:placetype":"venue"
},
  "geometry": {"coordinates":[5.8635501862,50.4911689758],"type":"Point"}
}