{
  "type": "Feature",
  "properties": {
    "addr:full":"Rue Moris 18 Sint-gillis/saint-gilles Bruxelles-Capitale 1060",
    "addr:housenumber":"18",
    "addr:postcode":"1060",
    "addr:street":"Rue Moris",
    "iso:country":"BE",
    "sg:address":"Rue Moris 18",
    "sg:city":"Sint-gillis/saint-gilles",
    "sg:orig_category":"Architectes",
    "sg:phone":"+32 2 534 43 08",
    "sg:postcode":"1060",
    "sg:province":"Bruxelles-Capitale",
    "wof:name":"Herv\u00c9 Dossin",
    "wof:placetype":"venue"
},
  "geometry": {"coordinates":[4.3533678055,50.8250732422],"type":"Point"}
}