{
  "type": "Feature",
  "properties": {
    "addr:full":"Rue Des Alli\u00e9s 52a Charleroi (goutroux) Hainaut 6030",
    "addr:housenumber":"52a",
    "addr:postcode":"6030",
    "addr:street":"Rue Des Allie\u0301S",
    "iso:country":"BE",
    "sg:address":"Rue Des Alli\u00e9s 52a",
    "sg:city":"Charleroi (goutroux)",
    "sg:classifiers":[
        {
            "category":"Building & Trades",
            "subcategory":"Construction",
            "type":"Services"
        }
    ],
    "sg:phone":"+32 71 54 46 34",
    "sg:postcode":"6030",
    "sg:province":"Hainaut",
    "sg:tags":[
        "installation",
        "-",
        "central",
        "heating"
    ],
    "wof:name":"Lemaitre Chauffage Sa",
    "wof:placetype":"venue"
},
  "geometry": {"coordinates":[4.3629631996,50.4099655151],"type":"Point"}
}