{
  "type": "Feature",
  "properties": {
    "addr:full":"Rue Colonel Bourg 66 Bruxelles (schaerbeek) Bruxelles-Capitale 1030",
    "addr:housenumber":"66",
    "addr:postcode":"1030",
    "addr:street":"Rue Colonel Bourg",
    "iso:country":"BE",
    "sg:address":"Rue Colonel Bourg 66",
    "sg:city":"Bruxelles (schaerbeek)",
    "sg:classifiers":[
        {
            "category":"Professional",
            "subcategory":"Lawyer & Legal Services",
            "type":"Services"
        }
    ],
    "sg:phone":"+32 2 346 88 72",
    "sg:postcode":"1030",
    "sg:province":"Bruxelles-Capitale",
    "wof:name":"Molenberg Isabelle",
    "wof:placetype":"venue"
},
  "geometry": {"coordinates":[4.4063677788,50.8518676758],"type":"Point"}
}