{
  "type": "Feature",
  "properties": {
    "iso:country":"BE",
    "sg:address":"Kortrijkstraat 14",
    "sg:city":"Zwevegem",
    "sg:orig_category":"Plaatsen van vloer- and muurbekleding Schilders",
    "sg:phone":"+32 56 75 85 39",
    "sg:postcode":"8550",
    "sg:province":"West-Vlaanderen",
    "wof:name":"Paul Deconinck",
    "wof:placetype":"venue"
},
  "geometry": {"coordinates":[3.3307220936,50.8127975464],"type":"Point"}
}