{
  "type": "Feature",
  "properties": {
    "iso:country":"BE",
    "sg:address":"R De L'abbaye 16",
    "sg:city":"Herstal",
    "sg:classifiers":[
        {
            "category":"Banks & Credit Unions",
            "subcategory":"Investment Brokerage",
            "type":"Services"
        }
    ],
    "sg:phone":"+32 4 264 58 97",
    "sg:postcode":"4040",
    "sg:province":"Li\u00e8ge",
    "sg:tags":[
        "-",
        "transport",
        "related"
    ],
    "wof:name":"Societe De Maintenance Industrielle Wertz Sa",
    "wof:placetype":"venue"
},
  "geometry": {"coordinates":[5.6287360191,50.6940498352],"type":"Point"}
}