{
  "type": "Feature",
  "properties": {
    "iso:country":"BE",
    "sg:address":"Gustaaflaan 13",
    "sg:city":"Sint-genesius-rode/rhode-saint-genese",
    "sg:orig_category":"Artsen and specialisten",
    "sg:phone":"+32 2 358 43 65",
    "sg:postcode":"1640",
    "sg:province":"Vlaams-Brabant",
    "wof:name":"E. Vamos",
    "wof:placetype":"venue"
},
  "geometry": {"coordinates":[4.3679308891,50.7538986206],"type":"Point"}
}