{
  "type": "Feature",
  "properties": {
    "iso:country":"BE",
    "sg:address":"Laarheidestraat 112",
    "sg:city":"Beersel",
    "sg:classifiers":[
        {
            "category":"Health Services",
            "subcategory":"Doctor",
            "type":"Services"
        }
    ],
    "sg:phone":"+32 2 345 51 64",
    "sg:postcode":"1650",
    "sg:province":"Vlaams-Brabant",
    "sg:tags":[
        "medicinephysicians",
        "surgeon"
    ],
    "wof:name":"Farr Ph",
    "wof:placetype":"venue"
},
  "geometry": {"coordinates":[4.3070020676,50.7608947754],"type":"Point"}
}