{
  "type": "Feature",
  "properties": {
    "iso:country":"BE",
    "sg:address":"Rue De L'avenir 26",
    "sg:city":"Grace-hollogne",
    "sg:orig_category":"Afvalophaling and -verwerking industrie, landbouw and bouwpuin Plaatsen van vloer- and muurbekleding",
    "sg:phone":"+32 4 239 64 64",
    "sg:postcode":"4460",
    "sg:province":"Li\u00e8ge",
    "wof:name":"Laurenty",
    "wof:placetype":"venue"
},
  "geometry": {"coordinates":[5.4930062294,50.6515541077],"type":"Point"}
}