{
  "type": "Feature",
  "properties": {
    "addr:full":"Place De Brasm\u00e9nil 4 P\u00e9ruwelz (brasmenil) Hainaut 7604",
    "addr:housenumber":"4",
    "addr:postcode":"7604",
    "addr:street":"Place De Brasme\u0301Nil",
    "iso:country":"BE",
    "sg:address":"Place De Brasm\u00e9nil 4",
    "sg:city":"P\u00e9ruwelz (brasmenil)",
    "sg:classifiers":[
        {
            "category":"Bars & Pubs",
            "type":"Food & Drink"
        }
    ],
    "sg:phone":"+32 69 77 03 28",
    "sg:postcode":"7604",
    "sg:province":"Hainaut",
    "wof:name":"Maison Du Peuple",
    "wof:placetype":"venue"
},
  "geometry": {"coordinates":[3.5471999645,50.5419311523],"type":"Point"}
}