{
  "type": "Feature",
  "properties": {
    "addr:full":"Veldstraat 39 Etterbeek Bruxelles-Capitale 1040",
    "addr:housenumber":"39",
    "addr:postcode":"1040",
    "addr:street":"Veldstraat",
    "iso:country":"BE",
    "sg:address":"Veldstraat 39",
    "sg:city":"Etterbeek",
    "sg:orig_category":"Supermarkten",
    "sg:phone":"+32 2 647 44 73",
    "sg:postcode":"1040",
    "sg:province":"Bruxelles-Capitale",
    "wof:name":"Gb Contact",
    "wof:placetype":"venue"
},
  "geometry": {"coordinates":[4.3917198181,50.8302726746],"type":"Point"}
}