{
  "type": "Feature",
  "properties": {
    "iso:country":"BE",
    "sg:address":"Westdorp 20",
    "sg:city":"Anzegem",
    "sg:orig_category":"Brood, gebak and snoepgoed",
    "sg:phone":"+32 56 68 95 08",
    "sg:postcode":"8573",
    "sg:province":"West-Vlaanderen",
    "wof:name":"Marcel Demeulemeester",
    "wof:placetype":"venue"
},
  "geometry": {"coordinates":[3.4740450382,50.808303833],"type":"Point"}
}