{
  "type": "Feature",
  "properties": {
    "iso:country":"BE",
    "sg:address":"Rue De France 3",
    "sg:city":"Verviers",
    "sg:orig_category":"Fotogravure and zetwerk Secretariaatsdiensten",
    "sg:phone":"+32 87 23 10 23",
    "sg:postcode":"4800",
    "sg:province":"Li\u00e8ge",
    "wof:name":"Daniel Fery-photogravure",
    "wof:placetype":"venue"
},
  "geometry": {"coordinates":[5.860640049,50.5880661011],"type":"Point"}
}