{
  "type": "Feature",
  "properties": {
    "addr:full":"Elisabethwal 27b1 Tongeren Limburg 3700",
    "addr:housenumber":"27b1",
    "addr:postcode":"3700",
    "addr:street":"Elisabethwal",
    "iso:country":"BE",
    "sg:address":"Elisabethwal 27b1",
    "sg:city":"Tongeren",
    "sg:orig_category":"Advocaten and juridische adviseurs",
    "sg:phone":"+32 12 39 08 88",
    "sg:postcode":"3700",
    "sg:province":"Limburg",
    "wof:name":"H. Janssen",
    "wof:placetype":"venue"
},
  "geometry": {"coordinates":[5.4599151611,50.7784042358],"type":"Point"}
}