{
  "type": "Feature",
  "properties": {
    "addr:full":"Bredabaan 55 Antwerpen Antwerpen 2170",
    "addr:housenumber":"55",
    "addr:postcode":"2170",
    "addr:street":"Bredabaan",
    "iso:country":"BE",
    "sg:address":"Bredabaan 55",
    "sg:city":"Antwerpen",
    "sg:orig_category":"Schoonmaakbedrijven and ongediertebestrijding",
    "sg:phone":"+32 3 644 25 28",
    "sg:postcode":"2170",
    "sg:province":"Antwerpen",
    "wof:name":"Speedy Cleaning",
    "wof:placetype":"venue"
},
  "geometry": {"coordinates":[4.4222221375,51.2336997986],"type":"Point"}
}