{
  "type": "Feature",
  "properties": {
    "addr:full":"Lichtaartseweg 207 Herentals Antwerpen 2200",
    "addr:housenumber":"207",
    "addr:postcode":"2200",
    "addr:street":"Lichtaartseweg",
    "iso:country":"BE",
    "sg:address":"Lichtaartseweg 207",
    "sg:city":"Herentals",
    "sg:orig_category":"Agences de presse",
    "sg:phone":"+32 14 23 31 11",
    "sg:postcode":"2200",
    "sg:province":"Antwerpen",
    "wof:name":"Karl Hendrickx",
    "wof:placetype":"venue"
},
  "geometry": {"coordinates":[4.8528661728,51.1948547363],"type":"Point"}
}