{
  "type": "Feature",
  "properties": {
    "iso:country":"BE",
    "sg:address":"Guido Gezellelaan 4",
    "sg:city":"Mechelen",
    "sg:classifiers":[
        {
            "category":"Fast Food",
            "type":"Food & Drink"
        }
    ],
    "sg:phone":"+32 15 33 97 01",
    "sg:postcode":"2800",
    "sg:province":"Antwerpen",
    "sg:tags":[
        "\u00c0",
        "emporter",
        "restaurants"
    ],
    "wof:name":"Mcdonald's",
    "wof:placetype":"venue"
},
  "geometry": {"coordinates":[4.4721908569,51.0323829651],"type":"Point"}
}