{
  "type": "Feature",
  "properties": {
    "addr:full":"Rue Du Rwanda 37 Verviers Li\u00e8ge 4801",
    "addr:housenumber":"37",
    "addr:postcode":"4801",
    "addr:street":"Rue Du Rwanda",
    "iso:country":"BE",
    "sg:address":"Rue Du Rwanda 37",
    "sg:city":"Verviers",
    "sg:orig_category":"Kapsalons",
    "sg:phone":"+32 87 22 87 77",
    "sg:postcode":"4801",
    "sg:province":"Li\u00e8ge",
    "wof:name":"Georges Grenier",
    "wof:placetype":"venue"
},
  "geometry": {"coordinates":[5.8930549622,50.5922393799],"type":"Point"}
}