{
  "type": "Feature",
  "properties": {
    "addr:full":"Fabriekstraat 9 Meeuwen-gruitrode (meeuwen) Limburg 3670",
    "addr:housenumber":"9",
    "addr:postcode":"3670",
    "addr:street":"Fabriekstraat",
    "iso:country":"BE",
    "sg:address":"Fabriekstraat 9",
    "sg:city":"Meeuwen-gruitrode (meeuwen)",
    "sg:classifiers":[
        {
            "category":"Retail",
            "subcategory":"Auto Repair",
            "type":"Services"
        }
    ],
    "sg:phone":"+32 11 79 40 50",
    "sg:postcode":"3670",
    "sg:province":"Limburg",
    "sg:tags":[
        "garage"
    ],
    "wof:name":"Schreurs",
    "wof:placetype":"venue"
},
  "geometry": {"coordinates":[5.5352449417,51.1035385132],"type":"Point"}
}