{
  "type": "Feature",
  "properties": {
    "iso:country":"BE",
    "sg:address":"Rue Paul-verlaine 7",
    "sg:city":"Paliseul",
    "sg:orig_category":"M\u00e9decins and sp\u00e9cialistes",
    "sg:phone":"+32 61 63 53 20",
    "sg:postcode":"6850",
    "sg:province":"Luxembourg",
    "wof:name":"Anne Legrand",
    "wof:placetype":"venue"
},
  "geometry": {"coordinates":[5.1348800659,49.9033813477],"type":"Point"}
}