{
  "type": "Feature",
  "properties": {
    "addr:full":"Avenue De Tervueren 270 Sint-pieters-woluwe/woluwe-saint-pierre Bruxelles-Capitale 1150",
    "addr:housenumber":"270",
    "addr:postcode":"1150",
    "addr:street":"Avenue De Tervueren;/",
    "iso:country":"BE",
    "sg:address":"Avenue De Tervueren 270",
    "sg:city":"Sint-pieters-woluwe/woluwe-saint-pierre",
    "sg:classifiers":[
        {
            "category":"Arena",
            "subcategory":"Sports Club",
            "type":"Entertainment"
        }
    ],
    "sg:phone":"+32 2 776 48 28",
    "sg:postcode":"1150",
    "sg:province":"Bruxelles-Capitale",
    "sg:tags":[
        "de"
    ],
    "wof:name":"M.u.g.s.",
    "wof:placetype":"venue"
},
  "geometry": {"coordinates":[4.4198570251,50.8352546692],"type":"Point"}
}