{
  "type": "Feature",
  "properties": {
    "addr:full":"Rue Jean Damard 19 Anthisnes Li\u00e8ge 4163",
    "addr:housenumber":"19",
    "addr:postcode":"4163",
    "addr:street":"Rue Jean Damard",
    "iso:country":"BE",
    "sg:address":"Rue Jean Damard 19",
    "sg:city":"Anthisnes",
    "sg:orig_category":"Installation \u00e9lectrique industrielle",
    "sg:phone":"+32 4 372 03 03",
    "sg:postcode":"4163",
    "sg:province":"Li\u00e8ge",
    "wof:name":"Firmin Dethier",
    "wof:placetype":"venue"
},
  "geometry": {"coordinates":[5.4722118378,50.5154495239],"type":"Point"}
}