{
  "type": "Feature",
  "properties": {
    "addr:full":"Eikelstraat 12 Heuvelland West-Vlaanderen 8950",
    "addr:housenumber":"12",
    "addr:postcode":"8950",
    "addr:street":"Eikelstraat",
    "iso:country":"BE",
    "sg:address":"Eikelstraat 12",
    "sg:city":"Heuvelland",
    "sg:orig_category":"Eleveurs de bovins. Eleveurs and marchands de porcs",
    "sg:phone":"+32 57 44 46 28",
    "sg:postcode":"8950",
    "sg:province":"West-Vlaanderen",
    "wof:name":"Etienne Deraedt",
    "wof:placetype":"venue"
},
  "geometry": {"coordinates":[2.8152329922,50.7360992432],"type":"Point"}
}