{
  "type": "Feature",
  "properties": {
    "iso:country":"BE",
    "sg:address":"Rue Du Bouly 3",
    "sg:city":"Assesse (sorinne-la-longue)",
    "sg:classifiers":[
        {
            "category":"Manufacturing",
            "subcategory":"Metals",
            "type":"Manufacturing & Wholesale Goods"
        }
    ],
    "sg:phone":"+32 83 65 61 03",
    "sg:postcode":"5333",
    "sg:province":"Namur",
    "sg:tags":[
        "ironwork"
    ],
    "wof:name":"Lamoline B",
    "wof:placetype":"venue"
},
  "geometry": {"coordinates":[5.0186910629,50.3879394531],"type":"Point"}
}