{
  "type": "Feature",
  "properties": {
    "addr:full":"Vissenakenstraat 489 Tienen Vlaams-Brabant 3300",
    "addr:housenumber":"489",
    "addr:postcode":"3300",
    "addr:street":"Vissenakenstraat",
    "iso:country":"BE",
    "sg:address":"Vissenakenstraat 489",
    "sg:city":"Tienen",
    "sg:classifiers":[
        {
            "category":"Insurance",
            "subcategory":"Insurance Agent",
            "type":"Services"
        }
    ],
    "sg:phone":"+32 16 82 34 44",
    "sg:postcode":"3300",
    "sg:province":"Vlaams-Brabant",
    "sg:tags":[
        "verzekeringsmakelaars",
        "expert"
    ],
    "wof:name":"Chantal Dumont",
    "wof:placetype":"venue"
},
  "geometry": {"coordinates":[4.9317598343,50.8275184631],"type":"Point"}
}