{
  "type": "Feature",
  "properties": {
    "addr:full":"Pas 31 Geel Antwerpen 2440",
    "addr:housenumber":"31",
    "addr:postcode":"2440",
    "addr:street":"Pas",
    "iso:country":"BE",
    "sg:address":"Pas 31",
    "sg:city":"Geel",
    "sg:classifiers":[
        {
            "category":"Home & Garden",
            "subcategory":"Carpets & Floor Coverings",
            "type":"Retail Goods"
        }
    ],
    "sg:phone":"+32 14 59 36 34",
    "sg:postcode":"2440",
    "sg:province":"Antwerpen",
    "sg:tags":[
        "wall",
        "interior",
        "decoration"
    ],
    "wof:name":"Erfurt & Sohn Belgium",
    "wof:placetype":"venue"
},
  "geometry": {"coordinates":[4.9898490906,51.1597595215],"type":"Point"}
}