{
  "type": "Feature",
  "properties": {
    "iso:country":"BE",
    "sg:address":"Ch De Bruxelles 100",
    "sg:city":"Dampremy",
    "sg:classifiers":[
        {
            "category":"Building & Trades",
            "subcategory":"Construction",
            "type":"Services"
        }
    ],
    "sg:phone":"+32 71 32 00 57",
    "sg:postcode":"6020",
    "sg:province":"Hainaut",
    "sg:tags":[
        "work",
        "public"
    ],
    "wof:name":"Delbrassinne Sa",
    "wof:placetype":"venue"
},
  "geometry": {"coordinates":[4.4385790825,50.4164772034],"type":"Point"}
}