{
  "type": "Feature",
  "properties": {
    "iso:country":"BE",
    "sg:address":"Grens 95",
    "sg:city":"Arendonk",
    "sg:classifiers":[
        {
            "category":"Restaurant",
            "type":"Food & Drink"
        }
    ],
    "sg:phone":"+32 14 67 70 98",
    "sg:postcode":"2370",
    "sg:province":"Antwerpen",
    "sg:tags":[
        "industrial",
        "kitchen",
        "catering"
    ],
    "wof:name":"Wouters K-helsen A Bvba",
    "wof:placetype":"venue"
},
  "geometry": {"coordinates":[5.1209859848,51.3476791382],"type":"Point"}
}