{
  "type": "Feature",
  "properties": {
    "iso:country":"BE",
    "sg:address":"Ballingstraat 78",
    "sg:city":"Overijse",
    "sg:classifiers":[
        {
            "category":"Structure",
            "subcategory":"Office Building",
            "type":"Public Place"
        }
    ],
    "sg:phone":"+32 2 688 24 28",
    "sg:postcode":"3090",
    "sg:province":"Vlaams-Brabant",
    "sg:tags":[
        "drawing"
    ],
    "wof:name":"Beaumesnil J",
    "wof:placetype":"venue"
},
  "geometry": {"coordinates":[4.5533471107,50.7923431396],"type":"Point"}
}