{
  "type": "Feature",
  "properties": {
    "iso:country":"BE",
    "sg:address":"Rue Du Tram 1",
    "sg:city":"Soignies",
    "sg:orig_category":"M\u00e9decins and sp\u00e9cialistes",
    "sg:phone":"+32 67 41 00 34",
    "sg:postcode":"7060",
    "sg:province":"Hainaut",
    "wof:name":"Stany Borremans",
    "wof:placetype":"venue"
},
  "geometry": {"coordinates":[4.0724000931,50.5779037476],"type":"Point"}
}