{
  "type": "Feature",
  "properties": {
    "addr:full":"Zandbeekstraat 16 Zwevegem West-Vlaanderen 8554",
    "addr:housenumber":"16",
    "addr:postcode":"8554",
    "addr:street":"Zandbeekstraat",
    "iso:country":"BE",
    "sg:address":"Zandbeekstraat 16",
    "sg:city":"Zwevegem",
    "sg:orig_category":"Services pour animaux domestiques",
    "sg:phone":"+32 56 45 72 85",
    "sg:postcode":"8554",
    "sg:province":"West-Vlaanderen",
    "wof:name":"De Witte Minouche",
    "wof:placetype":"venue"
},
  "geometry": {"coordinates":[3.3706920147,50.7496185303],"type":"Point"}
}