{
  "type": "Feature",
  "properties": {
    "addr:full":"Eiermarkt 8 Brugge West-Vlaanderen 8000",
    "addr:housenumber":"8",
    "addr:postcode":"8000",
    "addr:street":"Eiermarkt",
    "iso:country":"BE",
    "sg:address":"Eiermarkt 8",
    "sg:city":"Brugge",
    "sg:orig_category":"Geschenken and souvenirs Verlichting and huishoudartikelen",
    "sg:phone":"+32 50 33 76 00",
    "sg:postcode":"8000",
    "sg:province":"West-Vlaanderen",
    "wof:name":"Dhondt Studio Plus",
    "wof:placetype":"venue"
},
  "geometry": {"coordinates":[3.2232429981,51.2094802856],"type":"Point"}
}