{
  "type": "Feature",
  "properties": {
    "addr:full":"Marktweg 32bb Aalst Oost-Vlaanderen 9320",
    "addr:housenumber":"32bb",
    "addr:postcode":"9320",
    "addr:street":"Marktweg",
    "iso:country":"BE",
    "sg:address":"Marktweg 32bb",
    "sg:city":"Aalst",
    "sg:orig_category":"Schoonheidssalons",
    "sg:phone":"+32 53 70 56 73",
    "sg:postcode":"9320",
    "sg:province":"Oost-Vlaanderen",
    "wof:name":"E. Palsterman",
    "wof:placetype":"venue"
},
  "geometry": {"coordinates":[4.0553851128,50.9209976196],"type":"Point"}
}