{
  "type": "Feature",
  "properties": {
    "iso:country":"BE",
    "sg:address":"Brusselsesteenweg 513",
    "sg:city":"Asse",
    "sg:orig_category":"Pain, p\u00e2tisseries and confiseries",
    "sg:phone":"+32 2 466 87 77",
    "sg:postcode":"1731",
    "sg:province":"Vlaams-Brabant",
    "wof:name":"Bakkerij Martine",
    "wof:placetype":"venue"
},
  "geometry": {"coordinates":[4.2744569778,50.8844871521],"type":"Point"}
}