{
  "type": "Feature",
  "properties": {
    "addr:full":"Bogaertsheide 16 Nijlen (kessel) Antwerpen 2560",
    "addr:housenumber":"16",
    "addr:postcode":"2560",
    "addr:street":"Bogaertsheide",
    "iso:country":"BE",
    "sg:address":"Bogaertsheide 16",
    "sg:city":"Nijlen (kessel)",
    "sg:classifiers":[
        {
            "category":"Social Services",
            "type":"Services"
        }
    ],
    "sg:phone":"+32 3 480 31 84",
    "sg:postcode":"2560",
    "sg:province":"Antwerpen",
    "wof:name":"Amazone Mmm Vzw",
    "wof:placetype":"venue"
},
  "geometry": {"coordinates":[4.6533379555,51.1352882385],"type":"Point"}
}