{
  "type": "Feature",
  "properties": {
    "iso:country":"BE",
    "sg:address":"Izegemstraat 167",
    "sg:city":"Ingelmunster",
    "sg:classifiers":[
        {
            "category":"Personal",
            "subcategory":"Beauty Salon",
            "type":"Services"
        }
    ],
    "sg:phone":"+32 51 31 79 87",
    "sg:postcode":"8770",
    "sg:province":"West-Vlaanderen",
    "sg:tags":[
        "de",
        "coiffure"
    ],
    "wof:name":"Coiffure Duchess",
    "wof:placetype":"venue"
},
  "geometry": {"coordinates":[3.2461719513,50.9156913757],"type":"Point"}
}