{
  "type": "Feature",
  "properties": {
    "addr:full":"Rue Langeveld 111 Bruxelles (uccle) Bruxelles-Capitale 1180",
    "addr:housenumber":"111",
    "addr:postcode":"1180",
    "addr:street":"Rue Langeveld",
    "iso:country":"BE",
    "sg:address":"Rue Langeveld 111",
    "sg:city":"Bruxelles (uccle)",
    "sg:classifiers":[
        {
            "category":"Building & Trades",
            "subcategory":"Construction",
            "type":"Services"
        }
    ],
    "sg:phone":"+32 2 374 00 32",
    "sg:postcode":"1180",
    "sg:province":"Bruxelles-Capitale",
    "sg:tags":[
        "surveyor",
        "-"
    ],
    "wof:name":"Fibo Nv",
    "wof:placetype":"venue"
},
  "geometry": {"coordinates":[4.3657150269,50.8061141968],"type":"Point"}
}