{
  "type": "Feature",
  "properties": {
    "addr:full":"Rue Du Monument 114 Florennes Namur 5620",
    "addr:housenumber":"114",
    "addr:postcode":"5620",
    "addr:street":"Rue Du Monument",
    "iso:country":"BE",
    "sg:address":"Rue Du Monument 114",
    "sg:city":"Florennes",
    "sg:orig_category":"Elektrische installaties voor woningen",
    "sg:phone":"+32 82 68 82 62",
    "sg:postcode":"5620",
    "sg:province":"Namur",
    "wof:name":"Guy Bodson",
    "wof:placetype":"venue"
},
  "geometry": {"coordinates":[4.6880569458,50.2318954468],"type":"Point"}
}