{
  "type": "Feature",
  "properties": {
    "addr:full":"Edelweisstraat 50 Houthalen-helchteren (houthalen) Limburg 3530",
    "addr:housenumber":"50",
    "addr:postcode":"3530",
    "addr:street":"Edelweisstraat",
    "iso:country":"BE",
    "sg:address":"Edelweisstraat 50",
    "sg:city":"Houthalen-helchteren (houthalen)",
    "sg:classifiers":[
        {
            "category":"Building & Trades",
            "subcategory":"Electrical",
            "type":"Services"
        }
    ],
    "sg:phone":"+32 89 38 60 36",
    "sg:postcode":"3530",
    "sg:province":"Limburg",
    "sg:tags":[
        "electric",
        "-",
        "housewiring",
        "contractor"
    ],
    "wof:name":"Jonkmans",
    "wof:placetype":"venue"
},
  "geometry": {"coordinates":[5.4901528358,51.028717041],"type":"Point"}
}