{
  "type": "Feature",
  "properties": {
    "iso:country":"BE",
    "sg:address":"Rue De Brouck\u00c8re 96",
    "sg:city":"La Louviere",
    "sg:orig_category":"Drukkerijen and copyshops Krantenuitgeverijen Tijdschriftenuitgeverijen",
    "sg:phone":"+32 64 26 02 52",
    "sg:postcode":"7100",
    "sg:province":"Hainaut",
    "wof:name":"Cayoteu Presse N\u00d8 1",
    "wof:placetype":"venue"
},
  "geometry": {"coordinates":[4.1915631294,50.4804954529],"type":"Point"}
}