{
  "type": "Feature",
  "properties": {
    "addr:full":"Pannewinning 48 Heusden-zolder (zolder) Limburg 3550",
    "addr:housenumber":"48",
    "addr:postcode":"3550",
    "addr:street":"Pannewinning",
    "iso:country":"BE",
    "sg:address":"Pannewinning 48",
    "sg:city":"Heusden-zolder (zolder)",
    "sg:classifiers":[
        {
            "category":"Real Estate",
            "subcategory":"Architect",
            "type":"Services"
        }
    ],
    "sg:phone":"+32 11 25 48 60",
    "sg:postcode":"3550",
    "sg:province":"Limburg",
    "wof:name":"Zeelmaekers P",
    "wof:placetype":"venue"
},
  "geometry": {"coordinates":[5.2737269402,50.9765777588],"type":"Point"}
}