{
  "type": "Feature",
  "properties": {
    "iso:country":"BE",
    "sg:address":"Miksebaan 45",
    "sg:city":"Brasschaat",
    "sg:orig_category":"Diverse bouwafwerking and reiniging Woningbouw",
    "sg:phone":"+32 3 651 70 78",
    "sg:postcode":"2930",
    "sg:province":"Antwerpen",
    "wof:name":"Van Laerhoven",
    "wof:placetype":"venue"
},
  "geometry": {"coordinates":[4.4962291718,51.290019989],"type":"Point"}
}