{
  "type": "Feature",
  "properties": {
    "iso:country":"BE",
    "sg:address":"Ciepenstraat 19",
    "sg:city":"Izegem",
    "sg:classifiers":[
        {
            "category":"Insurance",
            "subcategory":"Insurance Agent",
            "type":"Services"
        }
    ],
    "sg:phone":"+32 51 31 78 84",
    "sg:postcode":"8870",
    "sg:province":"West-Vlaanderen",
    "sg:tags":[
        "verzekeringsmakelaars",
        "expert"
    ],
    "wof:name":"Bruggeman",
    "wof:placetype":"venue"
},
  "geometry": {"coordinates":[3.2174971104,50.9018135071],"type":"Point"}
}