{
  "type": "Feature",
  "properties": {
    "iso:country":"BE",
    "sg:address":"Tildonksesteenweg 73",
    "sg:city":"Herent",
    "sg:orig_category":"Supermarch\u00e9s",
    "sg:postcode":"3020",
    "sg:province":"Vlaams-Brabant",
    "wof:name":"Aldi",
    "wof:placetype":"venue"
},
  "geometry": {"coordinates":[4.6649680138,50.9116821289],"type":"Point"}
}