{
  "type": "Feature",
  "properties": {
    "iso:country":"BE",
    "sg:address":"Monnikenhofstraat 48",
    "sg:city":"Rumst (reet)",
    "sg:classifiers":[
        {
            "category":"Home & Garden",
            "subcategory":"Household Appliances",
            "type":"Retail Goods"
        }
    ],
    "sg:phone":"+32 3 888 06 78",
    "sg:postcode":"2840",
    "sg:province":"Antwerpen",
    "sg:tags":[
        "repair",
        "mainten",
        "-",
        "electric"
    ],
    "wof:name":"Electro Mees",
    "wof:placetype":"venue"
},
  "geometry": {"coordinates":[4.3909759521,51.1039428711],"type":"Point"}
}