{
  "type": "Feature",
  "properties": {
    "addr:full":"Potaardestraat 4 Kraainem/kraainem Vlaams-Brabant 1950",
    "addr:housenumber":"4",
    "addr:postcode":"1950",
    "addr:street":"Potaardestraat",
    "iso:country":"BE",
    "sg:address":"Potaardestraat 4",
    "sg:city":"Kraainem/kraainem",
    "sg:classifiers":[
        {
            "category":"Communications",
            "subcategory":"Film & Video Production",
            "type":"Services"
        }
    ],
    "sg:phone":"+32 2 731 63 62",
    "sg:postcode":"1950",
    "sg:province":"Vlaams-Brabant",
    "sg:tags":[
        "platen",
        "cassette",
        "cd's"
    ],
    "wof:name":"Mark Sound",
    "wof:placetype":"venue"
},
  "geometry": {"coordinates":[4.4672288895,50.8402938843],"type":"Point"}
}