{
  "type": "Feature",
  "properties": {
    "iso:country":"BE",
    "sg:address":"Place Ba\u00efaux 17",
    "sg:city":"Fleurus (wanferc\u00e9e-baulet)",
    "sg:classifiers":[
        {
            "category":"Professional",
            "subcategory":"Testing Lab",
            "type":"Services"
        }
    ],
    "sg:phone":"+32 71 81 14 48",
    "sg:postcode":"6224",
    "sg:province":"Hainaut",
    "sg:tags":[
        "chemist"
    ],
    "wof:name":"Quinet",
    "wof:placetype":"venue"
},
  "geometry": {"coordinates":[4.5885939598,50.4720726013],"type":"Point"}
}