{
  "type": "Feature",
  "properties": {
    "iso:country":"BE",
    "sg:address":"Polderstraat 11",
    "sg:city":"Mechelen",
    "sg:orig_category":"Dakwerken Elektrische installaties voor woningen Gespecialiseerde residenti\u00eble bouw Installatie van ",
    "sg:phone":"+32 15 26 09 88",
    "sg:postcode":"2800",
    "sg:province":"Antwerpen",
    "wof:name":"Dave Van Praet",
    "wof:placetype":"venue"
},
  "geometry": {"coordinates":[4.4680299759,51.0323219299],"type":"Point"}
}