{
  "type": "Feature",
  "properties": {
    "addr:full":"Meerskant 25 Lebbeke (denderbelle) Oost-Vlaanderen 9280",
    "addr:housenumber":"25",
    "addr:postcode":"9280",
    "addr:street":"Meerskant",
    "iso:country":"BE",
    "sg:address":"Meerskant 25",
    "sg:city":"Lebbeke (denderbelle)",
    "sg:classifiers":[
        {
            "category":"Home & Garden",
            "subcategory":"Home Furnishings",
            "type":"Retail Goods"
        }
    ],
    "sg:phone":"+32 52 41 58 30",
    "sg:postcode":"9280",
    "sg:province":"Oost-Vlaanderen",
    "sg:tags":[
        "interior",
        "decoration"
    ],
    "wof:name":"Marckx W",
    "wof:placetype":"venue"
},
  "geometry": {"coordinates":[4.0869441032,51.0000190735],"type":"Point"}
}