{
  "type": "Feature",
  "properties": {
    "addr:full":"So L'warhe 1 Malmedy/malmedy Li\u00e8ge 4960",
    "addr:housenumber":"1",
    "addr:postcode":"4960",
    "iso:country":"BE",
    "sg:address":"So L'warhe 1",
    "sg:city":"Malmedy/malmedy",
    "sg:orig_category":"Brood, gebak and snoepgoed",
    "sg:phone":"+32 80 33 06 49",
    "sg:postcode":"4960",
    "sg:province":"Li\u00e8ge",
    "wof:name":"Marc Fagnoul",
    "wof:placetype":"venue"
},
  "geometry": {"coordinates":[6.0701589584,50.4598388672],"type":"Point"}
}