{
  "type": "Feature",
  "properties": {
    "addr:full":"Rue Du Village 51 Sint-genesius-rode/rhode-saint-genese Vlaams-Brabant 1640",
    "addr:housenumber":"51",
    "addr:postcode":"1640",
    "addr:street":"Rue Du Village",
    "iso:country":"BE",
    "sg:address":"Rue Du Village 51",
    "sg:city":"Sint-genesius-rode/rhode-saint-genese",
    "sg:orig_category":"M\u00e9decins and sp\u00e9cialistes. M\u00e9decines alternatives",
    "sg:phone":"+32 2 381 20 63",
    "sg:postcode":"1640",
    "sg:province":"Vlaams-Brabant",
    "wof:name":"Johan De Geest",
    "wof:placetype":"venue"
},
  "geometry": {"coordinates":[4.3452339172,50.7458267212],"type":"Point"}
}