{
  "type": "Feature",
  "properties": {
    "iso:country":"BE",
    "sg:address":"Rue Du Bemel 149",
    "sg:city":"Sint-pieters-woluwe/woluwe-saint-pierre",
    "sg:orig_category":"Blanchisseries and teintureries",
    "sg:phone":"+32 2 771 57 10",
    "sg:postcode":"1150",
    "sg:province":"Bruxelles-Capitale",
    "wof:name":"La Com\u00c8te",
    "wof:placetype":"venue"
},
  "geometry": {"coordinates":[4.4147372246,50.8307113647],"type":"Point"}
}