{
  "type": "Feature",
  "properties": {
    "iso:country":"BE",
    "sg:address":"Rue Trieu Gossiaux 25",
    "sg:city":"Fleurus",
    "sg:orig_category":"Slagers",
    "sg:phone":"+32 71 81 27 20",
    "sg:postcode":"6224",
    "sg:province":"Hainaut",
    "wof:name":"Viandec",
    "wof:placetype":"venue"
},
  "geometry": {"coordinates":[4.5836968422,50.4653320312],"type":"Point"}
}