{
  "type": "Feature",
  "properties": {
    "addr:full":"Rue De Sart 67 Court-saint-etienne Brabant Wallon 1490",
    "addr:housenumber":"67;1490",
    "addr:street":"Rue De Sart",
    "iso:country":"BE",
    "sg:address":"Rue De Sart 67",
    "sg:city":"Court-saint-etienne",
    "sg:classifiers":[
        {
            "category":"Health Services",
            "subcategory":"Health Practitioner",
            "type":"Services"
        }
    ],
    "sg:phone":"+32 10 61 23 87",
    "sg:postcode":"1490",
    "sg:province":"Brabant Wallon",
    "sg:tags":[
        "physiotherapist"
    ],
    "wof:name":"Dupuis A-m",
    "wof:placetype":"venue"
},
  "geometry": {"coordinates":[4.5648999214,50.630771637],"type":"Point"}
}