{
  "type": "Feature",
  "properties": {
    "addr:full":"De Wissel 10 Koekelare West-Vlaanderen 8680",
    "addr:housenumber":"10",
    "addr:postcode":"8680",
    "addr:street":"De Wissel",
    "iso:country":"BE",
    "sg:address":"De Wissel 10",
    "sg:city":"Koekelare",
    "sg:orig_category":"Woningbouw",
    "sg:phone":"+32 51 58 47 06",
    "sg:postcode":"8680",
    "sg:province":"West-Vlaanderen",
    "wof:name":"Steven Verhelst",
    "wof:placetype":"venue"
},
  "geometry": {"coordinates":[2.9701659679,51.0921325684],"type":"Point"}
}