{
  "type": "Feature",
  "properties": {
    "iso:country":"BE",
    "sg:address":"Priesterhaagstraat 38",
    "sg:city":"Genk",
    "sg:orig_category":"Blanchisseries and teintureries",
    "sg:phone":"+32 89 35 52 16",
    "sg:postcode":"3600",
    "sg:province":"Limburg",
    "wof:name":"Wassalon Miele",
    "wof:placetype":"venue"
},
  "geometry": {"coordinates":[5.4994502068,50.9530754089],"type":"Point"}
}