{
  "type": "Feature",
  "properties": {
    "addr:full":"Liersesteenweg 333 Mortsel Antwerpen 2640",
    "addr:housenumber":"333",
    "addr:postcode":"2640",
    "addr:street":"Liersesteenweg",
    "iso:country":"BE",
    "sg:address":"Liersesteenweg 333",
    "sg:city":"Mortsel",
    "sg:orig_category":"Benzinestations and brandstoffen",
    "sg:phone":"+32 3 454 01 96",
    "sg:postcode":"2640",
    "sg:province":"Antwerpen",
    "wof:name":"Q8",
    "wof:placetype":"venue"
},
  "geometry": {"coordinates":[4.478662014,51.1681480408],"type":"Point"}
}