{
  "type": "Feature",
  "properties": {
    "iso:country":"BE",
    "sg:address":"Rue Falloise 34",
    "sg:city":"Anthisnes",
    "sg:orig_category":"Hout and afgeleiden Gh IJzerwaren, bouw- and verfmaterialen",
    "sg:phone":"+32 4 383 65 27",
    "sg:postcode":"4160",
    "sg:province":"Li\u00e8ge",
    "wof:name":"R\u00c9simont",
    "wof:placetype":"venue"
},
  "geometry": {"coordinates":[5.5215649605,50.4832458496],"type":"Point"}
}