{
  "type": "Feature",
  "properties": {
    "iso:country":"BE",
    "sg:address":"Van Overbekelaan 60b11",
    "sg:city":"Ganshoren/ganshoren",
    "sg:orig_category":"Artsen and specialisten",
    "sg:phone":"+32 2 428 93 75",
    "sg:postcode":"1083",
    "sg:province":"Bruxelles-Capitale",
    "wof:name":"Johan Vergote",
    "wof:placetype":"venue"
},
  "geometry": {"coordinates":[4.3149638176,50.8709602356],"type":"Point"}
}