{
  "type": "Feature",
  "properties": {
    "addr:full":"Rue De G\u00c9rouville 5 Meix-devant-virton Luxembourg 6769",
    "addr:housenumber":"5",
    "addr:postcode":"6769",
    "addr:street":"Rue De Ge\u0301Rouville",
    "iso:country":"BE",
    "sg:address":"Rue De G\u00c9rouville 5",
    "sg:city":"Meix-devant-virton",
    "sg:orig_category":"Werk and personeelsselectie",
    "sg:phone":"+32 63 57 80 51",
    "sg:postcode":"6769",
    "sg:province":"Luxembourg",
    "wof:name":"Ale",
    "wof:placetype":"venue"
},
  "geometry": {"coordinates":[5.4787969589,49.6045417786],"type":"Point"}
}