{
  "type": "Feature",
  "properties": {
    "addr:full":"Sprinkelestraat 1 Zutendaal Limburg 3690",
    "addr:housenumber":"1",
    "addr:postcode":"3690",
    "addr:street":"Sprinkelestraat",
    "iso:country":"BE",
    "sg:address":"Sprinkelestraat 1",
    "sg:city":"Zutendaal",
    "sg:orig_category":"RESTAURANTS: CAF\u00c9S",
    "sg:phone":"+32 89 62 24 26",
    "sg:postcode":"3690",
    "sg:province":"Limburg",
    "wof:name":"Taverne D\u00b4n Delper",
    "wof:placetype":"venue"
},
  "geometry": {"coordinates":[5.5723562241,50.9321022034],"type":"Point"}
}