{
  "type": "Feature",
  "properties": {
    "iso:country":"BE",
    "sg:address":"Kwinten 36",
    "sg:city":"Fourons (fouron-st.-martin)",
    "sg:classifiers":[
        {
            "category":"Organizations",
            "subcategory":"Community Association",
            "type":"Services"
        }
    ],
    "sg:phone":"+32 4 381 11 59",
    "sg:postcode":"3790",
    "sg:province":"Limburg",
    "sg:tags":[
        "cultural"
    ],
    "wof:name":"Vccv-het Veltmanshuis",
    "wof:placetype":"venue"
},
  "geometry": {"coordinates":[5.81351614,50.7496147156],"type":"Point"}
}