{
  "type": "Feature",
  "properties": {
    "addr:full":"Oosteneind 26a Kasterlee Antwerpen 2460",
    "addr:housenumber":"26a",
    "addr:postcode":"2460",
    "addr:street":"Oosteneind",
    "iso:country":"BE",
    "sg:address":"Oosteneind 26a",
    "sg:city":"Kasterlee",
    "sg:classifiers":[
        {
            "category":"Health Services",
            "subcategory":"Nursing And Care Facility",
            "type":"Services"
        }
    ],
    "sg:phone":"+32 14 85 00 94",
    "sg:postcode":"2460",
    "sg:province":"Antwerpen",
    "sg:tags":[
        "home"
    ],
    "wof:name":"Van Beek M",
    "wof:placetype":"venue"
},
  "geometry": {"coordinates":[4.9933252335,51.2379112244],"type":"Point"}
}