{
  "type": "Feature",
  "properties": {
    "addr:full":"Franklin Rooseveltlaan 349d Gent Oost-Vlaanderen 9000",
    "addr:housenumber":"349d",
    "addr:postcode":"9000",
    "addr:street":"Franklin Rooseveltlaan;Oost-Vlaanderen",
    "iso:country":"BE",
    "sg:address":"Franklin Rooseveltlaan 349d",
    "sg:city":"Gent",
    "sg:classifiers":[
        {
            "category":"Professional",
            "subcategory":"Computer Services",
            "type":"Services"
        }
    ],
    "sg:phone":"+32 9 265 02 70",
    "sg:postcode":"9000",
    "sg:province":"Oost-Vlaanderen",
    "sg:tags":[
        "-",
        "security",
        "processing",
        "data"
    ],
    "wof:name":"Securit Bvba",
    "wof:placetype":"venue"
},
  "geometry": {"coordinates":[3.730989933,51.0456314087],"type":"Point"}
}