{
  "type": "Feature",
  "properties": {
    "addr:full":"Rue Fran\u00e7ois Logen 6 Seraing (jemeppe-sur-meuse) Li\u00e8ge 4101",
    "addr:housenumber":"6",
    "addr:postcode":"4101",
    "addr:street":"Rue Franc\u0327Ois Logen;Jemeppe-Sur-Meuse",
    "iso:country":"BE",
    "sg:address":"Rue Fran\u00e7ois Logen 6",
    "sg:city":"Seraing (jemeppe-sur-meuse)",
    "sg:classifiers":[
        {
            "category":"Manufacturing",
            "subcategory":"Wood Products",
            "type":"Manufacturing & Wholesale Goods"
        }
    ],
    "sg:phone":"+32 4 233 94 34",
    "sg:postcode":"4101",
    "sg:province":"Li\u00e8ge",
    "sg:tags":[
        "preservation"
    ],
    "wof:name":"Francois",
    "wof:placetype":"venue"
},
  "geometry": {"coordinates":[5.4977121353,50.6123924255],"type":"Point"}
}