{
  "type": "Feature",
  "properties": {
    "addr:full":"Lanestraat 117 Overijse Vlaams-Brabant 3090",
    "addr:housenumber":"117",
    "addr:postcode":"3090",
    "addr:street":"Lanestraat",
    "iso:country":"BE",
    "sg:address":"Lanestraat 117",
    "sg:city":"Overijse",
    "sg:orig_category":"Airconditioning and ventilatie Winkelinrichting and handelsuitrusting Gh",
    "sg:phone":"+32 2 688 10 56",
    "sg:postcode":"3090",
    "sg:province":"Vlaams-Brabant",
    "wof:name":"Van Haute Cooling",
    "wof:placetype":"venue"
},
  "geometry": {"coordinates":[4.5690741539,50.753288269],"type":"Point"}
}