{
  "type": "Feature",
  "properties": {
    "addr:full":"Naamsestraat 100 Leuven Vlaams-Brabant 3000",
    "addr:housenumber":"100",
    "addr:postcode":"3000",
    "addr:street":"Naamsestraat",
    "iso:country":"BE",
    "sg:address":"Naamsestraat 100",
    "sg:city":"Leuven",
    "sg:orig_category":"Algemeen secundair onderwijs",
    "sg:phone":"+32 16 32 00 11",
    "sg:postcode":"3000",
    "sg:province":"Vlaams-Brabant",
    "wof:name":"Amerikaans College",
    "wof:placetype":"venue"
},
  "geometry": {"coordinates":[4.6996769905,50.8729133606],"type":"Point"}
}