{
  "type": "Feature",
  "properties": {
    "addr:full":"Voskapelstraat 175 Sterrebeek Vlaams-Brabant 1933",
    "addr:housenumber":"175",
    "addr:postcode":"1933",
    "addr:street":"Voskapelstraat",
    "iso:country":"BE",
    "sg:address":"Voskapelstraat 175",
    "sg:city":"Sterrebeek",
    "sg:orig_category":"D\u00e9m\u00e9nagements",
    "sg:phone":"+32 475 27 95 66",
    "sg:postcode":"1933",
    "sg:province":"Vlaams-Brabant",
    "wof:name":"Haegeman",
    "wof:placetype":"venue"
},
  "geometry": {"coordinates":[4.5244069099,50.8724975586],"type":"Point"}
}