{
  "type": "Feature",
  "properties": {
    "addr:full":"Gijsbeekstraat 29 Mechelen (hombeek) Antwerpen 2811",
    "addr:housenumber":"29",
    "addr:postcode":"2811",
    "addr:street":"Gijsbeekstraat",
    "iso:country":"BE",
    "sg:address":"Gijsbeekstraat 29",
    "sg:city":"Mechelen (hombeek)",
    "sg:classifiers":[
        {
            "category":"Parking",
            "subcategory":"Lot",
            "type":"Transportation"
        }
    ],
    "sg:phone":"+32 15 41 41 91",
    "sg:postcode":"2811",
    "sg:province":"Antwerpen",
    "sg:tags":[
        "parking-places",
        "laying-out"
    ],
    "wof:name":"De Maeyer Beton Bvba",
    "wof:placetype":"venue"
},
  "geometry": {"coordinates":[4.4204077721,51.0079040527],"type":"Point"}
}