{
  "type": "Feature",
  "properties": {
    "addr:full":"Dam 15 Kortrijk West-Vlaanderen 8500",
    "addr:housenumber":"15",
    "addr:postcode":"8500",
    "addr:street":"Dam",
    "iso:country":"BE",
    "sg:address":"Dam 15",
    "sg:city":"Kortrijk",
    "sg:orig_category":"M\u00e9decins and sp\u00e9cialistes",
    "sg:phone":"+32 56 22 57 32",
    "sg:postcode":"8500",
    "sg:province":"West-Vlaanderen",
    "wof:name":"Luc Derumeaux",
    "wof:placetype":"venue"
},
  "geometry": {"coordinates":[3.264467001,50.8318977356],"type":"Point"}
}