{
  "type": "Feature",
  "properties": {
    "addr:full":"Heihuizenstraat 4 As Limburg 3665",
    "addr:housenumber":"as",
    "addr:postcode":"3665",
    "addr:street":"Heihuizenstraat;Limburg",
    "iso:country":"BE",
    "sg:address":"Heihuizenstraat 4",
    "sg:city":"As",
    "sg:classifiers":[
        {
            "category":"Building & Trades",
            "subcategory":"Electrical",
            "type":"Services"
        }
    ],
    "sg:phone":"+32 89 65 92 36",
    "sg:postcode":"3665",
    "sg:province":"Limburg",
    "sg:tags":[
        "electric",
        "-",
        "housewiring",
        "contractor"
    ],
    "wof:name":"A.s.s.a.p. Bvba",
    "wof:placetype":"venue"
},
  "geometry": {"coordinates":[5.5673217773,51.0091896057],"type":"Point"}
}