{
  "type": "Feature",
  "properties": {
    "addr:full":"Route D'eghez\u00e9e 164 Jemeppe-sur-sambre Namur 5190",
    "addr:housenumber":"164",
    "addr:postcode":"jemeppe-sur-sambre;5190",
    "addr:street":"Route D'Egheze \u0301E",
    "iso:country":"BE",
    "sg:address":"Route D'eghez\u00e9e 164",
    "sg:city":"Jemeppe-sur-sambre",
    "sg:classifiers":[
        {
            "category":"Parking",
            "subcategory":"Garage",
            "type":"Transportation"
        }
    ],
    "sg:phone":"+32 71 78 77 74",
    "sg:postcode":"5190",
    "sg:province":"Namur",
    "sg:tags":[
        "truck",
        "-",
        "dump",
        "transport"
    ],
    "wof:name":"Gabelloni Sa",
    "wof:placetype":"venue"
},
  "geometry": {"coordinates":[4.6718869209,50.4726982117],"type":"Point"}
}