{
  "type": "Feature",
  "properties": {
    "addr:full":"Sint-jansbergstraat 9 Halen Limburg 3545",
    "addr:housenumber":"9",
    "addr:postcode":"3545",
    "addr:street":"Sint-Jansbergstraat",
    "iso:country":"BE",
    "sg:address":"Sint-jansbergstraat 9",
    "sg:city":"Halen",
    "sg:orig_category":"Divers amusement Diverse zakelijke dienstverlening Ruimtes voor conferenties, recepties and feesten",
    "sg:phone":"+32 13 46 14 71",
    "sg:postcode":"3545",
    "sg:province":"Limburg",
    "wof:name":"Sint-jansberg",
    "wof:placetype":"venue"
},
  "geometry": {"coordinates":[5.1127400398,50.9482154846],"type":"Point"}
}