{
  "type": "Feature",
  "properties": {
    "iso:country":"BE",
    "sg:address":"Gestelhoflei 10b",
    "sg:city":"Bonheiden",
    "sg:orig_category":"Gestion des d\u00e9charges and sites d\u00e9finitifs de stockage",
    "sg:phone":"+32 15 55 68 29",
    "sg:postcode":"2820",
    "sg:province":"Antwerpen",
    "wof:name":"Containerpark Bonheiden",
    "wof:placetype":"venue"
},
  "geometry": {"coordinates":[4.5307850838,51.0415115356],"type":"Point"}
}