{
  "type": "Feature",
  "properties": {
    "iso:country":"BE",
    "sg:address":"Jourdanstraat 14",
    "sg:city":"Sint-gillis/saint-gilles",
    "sg:classifiers":[
        {
            "category":"Restaurant",
            "type":"Food & Drink"
        }
    ],
    "sg:phone":"+32 2 534 75 20",
    "sg:postcode":"1060",
    "sg:province":"Bruxelles-Capitale",
    "wof:name":"Il Rinascimento",
    "wof:placetype":"venue"
},
  "geometry": {"coordinates":[4.3555111885,50.8345603943],"type":"Point"}
}