{
  "type": "Feature",
  "properties": {
    "iso:country":"BE",
    "sg:address":"Nieuwlandstraat 4b",
    "sg:city":"Oostende",
    "sg:classifiers":[
        {
            "category":"Health Services",
            "subcategory":"Health Practitioner",
            "type":"Services"
        }
    ],
    "sg:phone":"+32 59 29 82 16",
    "sg:postcode":"8400",
    "sg:province":"West-Vlaanderen",
    "sg:tags":[
        "osteopath"
    ],
    "wof:name":"Verhelle J",
    "wof:placetype":"venue"
},
  "geometry": {"coordinates":[2.9091711044,51.2183265686],"type":"Point"}
}