{
  "type": "Feature",
  "properties": {
    "addr:full":"Sint-benedictusstraat 14a Mortsel Antwerpen 2640",
    "addr:housenumber":"14a",
    "addr:postcode":"2640",
    "addr:street":"Sint-Benedictusstraat",
    "iso:country":"BE",
    "sg:address":"Sint-benedictusstraat 14a",
    "sg:city":"Mortsel",
    "sg:classifiers":[
        {
            "category":"Education",
            "subcategory":"School",
            "type":"Public Place"
        }
    ],
    "sg:phone":"+32 3 440 51 19",
    "sg:postcode":"2640",
    "sg:province":"Antwerpen",
    "sg:tags":[
        "primary"
    ],
    "wof:name":"De Tandem",
    "wof:placetype":"venue"
},
  "geometry": {"coordinates":[4.4620079994,51.1661109924],"type":"Point"}
}