{
  "type": "Feature",
  "properties": {
    "addr:full":"Hennemarkt 3 Tienen Vlaams-Brabant 3300",
    "addr:housenumber":"3",
    "addr:postcode":"3300",
    "addr:street":"Hennemarkt",
    "iso:country":"BE",
    "sg:address":"Hennemarkt 3",
    "sg:city":"Tienen",
    "sg:classifiers":[
        {
            "category":"Food & Beverages",
            "subcategory":"Fruits & Vegetables",
            "type":"Retail Goods"
        }
    ],
    "sg:phone":"+32 16 81 12 44",
    "sg:postcode":"3300",
    "sg:province":"Vlaams-Brabant",
    "sg:tags":[
        "-"
    ],
    "wof:name":"Windmoleke (in 't)",
    "wof:placetype":"venue"
},
  "geometry": {"coordinates":[4.9399580956,50.8063926697],"type":"Point"}
}