{
  "type": "Feature",
  "properties": {
    "iso:country":"BE",
    "sg:address":"Vogelzangstraat 101",
    "sg:city":"Stekene",
    "sg:orig_category":"Herstellingen and onderhoud van auto's",
    "sg:phone":"+32 3 789 00 10",
    "sg:postcode":"9190",
    "sg:province":"Oost-Vlaanderen",
    "wof:name":"Marc Marquet",
    "wof:placetype":"venue"
},
  "geometry": {"coordinates":[4.027589798,51.220249176],"type":"Point"}
}