{
  "type": "Feature",
  "properties": {
    "addr:full":"Hulstpoellaan 17 Tervuren Vlaams-Brabant 3080",
    "addr:housenumber":"17",
    "addr:postcode":"3080",
    "addr:street":"Hulstpoellaan",
    "iso:country":"BE",
    "sg:address":"Hulstpoellaan 17",
    "sg:city":"Tervuren",
    "sg:classifiers":[
        {
            "category":"Real Estate",
            "subcategory":"Architect",
            "type":"Services"
        }
    ],
    "sg:phone":"+32 2 767 70 99",
    "sg:postcode":"3080",
    "sg:province":"Vlaams-Brabant",
    "sg:tags":[
        "textile",
        "clothing"
    ],
    "wof:name":"Coltex Nv",
    "wof:placetype":"venue"
},
  "geometry": {"coordinates":[4.5322041512,50.851436615],"type":"Point"}
}