{
  "type": "Feature",
  "properties": {
    "iso:country":"BE",
    "sg:address":"Avenue Winston Churchill 24",
    "sg:city":"Dinant",
    "sg:classifiers":[
        {
            "category":"Bars & Pubs",
            "type":"Food & Drink"
        }
    ],
    "sg:phone":"+32 82 22 70 55",
    "sg:postcode":"5500",
    "sg:province":"Namur",
    "sg:tags":[
        "tavern"
    ],
    "wof:name":"Poste (de La)",
    "wof:placetype":"venue"
},
  "geometry": {"coordinates":[4.9128770828,50.2587928772],"type":"Point"}
}