{
  "type": "Feature",
  "properties": {
    "iso:country":"BE",
    "sg:address":"Onze-lieve-vrouwstraat 112",
    "sg:city":"Ravels",
    "sg:classifiers":[
        {
            "category":"Professional",
            "subcategory":"Accounting & Tax Preparation",
            "type":"Services"
        }
    ],
    "sg:phone":"+32 14 65 01 47",
    "sg:postcode":"2380",
    "sg:province":"Antwerpen",
    "sg:tags":[
        "accountant"
    ],
    "wof:name":"Van Looveren P",
    "wof:placetype":"venue"
},
  "geometry": {"coordinates":[4.9825239182,51.3779296875],"type":"Point"}
}