{
  "type": "Feature",
  "properties": {
    "addr:full":"Mosselgoren 117 Geel Antwerpen 2440",
    "addr:housenumber":"117",
    "addr:postcode":"2440",
    "addr:street":"Mosselgoren",
    "iso:country":"BE",
    "sg:address":"Mosselgoren 117",
    "sg:city":"Geel",
    "sg:classifiers":[
        {
            "category":"Home & Garden",
            "subcategory":"Carpets & Floor Coverings",
            "type":"Retail Goods"
        }
    ],
    "sg:phone":"+32 14 21 50 41",
    "sg:postcode":"2440",
    "sg:province":"Antwerpen",
    "sg:tags":[
        "tile"
    ],
    "wof:name":"Pauwels Bvba",
    "wof:placetype":"venue"
},
  "geometry": {"coordinates":[4.9294700623,51.1949310303],"type":"Point"}
}