{
  "type": "Feature",
  "properties": {
    "addr:full":"Bergense Steenweg 651 Anderlecht/anderlecht Bruxelles-Capitale 1070",
    "addr:housenumber":"651",
    "addr:postcode":"1070",
    "addr:street":"Bergense Steenweg",
    "iso:country":"BE",
    "sg:address":"Bergense Steenweg 651",
    "sg:city":"Anderlecht/anderlecht",
    "sg:classifiers":[
        {
            "category":"Cafe",
            "type":"Food & Drink"
        }
    ],
    "sg:phone":"+32 2 522 00 97",
    "sg:postcode":"1070",
    "sg:province":"Bruxelles-Capitale",
    "sg:tags":[
        "caf\u00e9s"
    ],
    "wof:name":"Caf\u00c9 Donald-francis",
    "wof:placetype":"venue"
},
  "geometry": {"coordinates":[4.310459137,50.8318214417],"type":"Point"}
}