{
  "type": "Feature",
  "properties": {
    "addr:full":"Mirfeld 34 Amel Li\u00e8ge 4770",
    "addr:housenumber":"34",
    "addr:postcode":"4770",
    "addr:street":"Mirfeld",
    "iso:country":"BE",
    "sg:address":"Mirfeld 34",
    "sg:city":"Amel",
    "sg:orig_category":"Maisons de vacances. D\u00e9molition d\u00b4immeubles and terrassements",
    "sg:phone":"+32 80 34 90 73",
    "sg:postcode":"4770",
    "sg:province":"Li\u00e8ge",
    "wof:name":"Mertens",
    "wof:placetype":"venue"
},
  "geometry": {"coordinates":[6.1689629555,50.3543167114],"type":"Point"}
}