{
  "type": "Feature",
  "properties": {
    "addr:full":"Rue Laoureux 32 Verviers Li\u00e8ge 4800",
    "addr:housenumber":"32",
    "addr:postcode":"4800",
    "addr:street":"Rue Laoureux",
    "iso:country":"BE",
    "sg:address":"Rue Laoureux 32",
    "sg:city":"Verviers",
    "sg:orig_category":"Non-Classified Establishments",
    "sg:phone":"+32 87 32 27 41",
    "sg:postcode":"4800",
    "sg:province":"Li\u00e8ge",
    "wof:name":"Centres Pms Libres 1 & 3",
    "wof:placetype":"venue"
},
  "geometry": {"coordinates":[5.864112854,50.5917778015],"type":"Point"}
}