{
  "type": "Feature",
  "properties": {
    "iso:country":"BE",
    "sg:address":"Kattestraat 30",
    "sg:city":"Oudenaarde",
    "sg:orig_category":"Non-Classified Establishments",
    "sg:phone":"+32 55 31 50 82",
    "sg:postcode":"9700",
    "sg:province":"Oost-Vlaanderen",
    "wof:name":"Jovilux Nv",
    "wof:placetype":"venue"
},
  "geometry": {"coordinates":[3.6055490971,50.8455810547],"type":"Point"}
}