{
  "type": "Feature",
  "properties": {
    "addr:full":"Rue De Neufvilles 445 Soignies Hainaut 7063",
    "addr:housenumber":"445",
    "addr:postcode":"7063",
    "addr:street":"Rue De Neufvilles",
    "iso:country":"BE",
    "sg:address":"Rue De Neufvilles 445",
    "sg:city":"Soignies",
    "sg:orig_category":"Traitement and rev\u00eatement des m\u00e9taux. Machines and mat\u00e9riel agricoles Gr",
    "sg:phone":"+32 67 33 42 19",
    "sg:postcode":"7063",
    "sg:province":"Hainaut",
    "wof:name":"Frebutte-bavay",
    "wof:placetype":"venue"
},
  "geometry": {"coordinates":[3.993940115,50.5837898254],"type":"Point"}
}