{
  "type": "Feature",
  "properties": {
    "iso:country":"BE",
    "sg:address":"Tivolistraat 146",
    "sg:city":"Oudenaarde",
    "sg:orig_category":"Plaatsen van vloer- and muurbekleding Schilders Verlichting and huishoudartikelen Vloer- and muurbek",
    "sg:phone":"+32 55 31 17 98",
    "sg:postcode":"9700",
    "sg:province":"Oost-Vlaanderen",
    "wof:name":"Carbonelle Gebroeders",
    "wof:placetype":"venue"
},
  "geometry": {"coordinates":[3.6275200844,50.8401489258],"type":"Point"}
}