{
  "type": "Feature",
  "properties": {
    "addr:full":"Rue De L\u00b4agolina 29 Verviers Li\u00e8ge 4801",
    "addr:housenumber":"29",
    "addr:postcode":"4801",
    "addr:street":"Rue De L\u00b4Agolina",
    "iso:country":"BE",
    "sg:address":"Rue De L\u00b4agolina 29",
    "sg:city":"Verviers",
    "sg:orig_category":"Herstellingen and onderhoud van auto's",
    "sg:phone":"+32 87 33 36 84",
    "sg:postcode":"4801",
    "sg:province":"Li\u00e8ge",
    "wof:name":"Vanderheyden Fr\u00c8res",
    "wof:placetype":"venue"
},
  "geometry": {"coordinates":[5.8777298927,50.586391449],"type":"Point"}
}