{
  "type": "Feature",
  "properties": {
    "iso:country":"BE",
    "sg:address":"Lange Ommegangstraat 32 Box 4",
    "sg:city":"Erpe-mere (erpe)",
    "sg:classifiers":[
        {
            "category":"Building & Trades",
            "subcategory":"Plumbing",
            "type":"Services"
        }
    ],
    "sg:phone":"+32 53 80 96 07",
    "sg:postcode":"9420",
    "sg:province":"Oost-Vlaanderen",
    "sg:tags":[
        "contractor"
    ],
    "wof:name":"D'herde K",
    "wof:placetype":"venue"
},
  "geometry": {"coordinates":[3.9856441021,50.9282188416],"type":"Point"}
}