{
  "type": "Feature",
  "properties": {
    "iso:country":"BE",
    "sg:address":"Kruisabeelstraat 109",
    "sg:city":"Aalst",
    "sg:classifiers":[
        {
            "category":"Cafe",
            "type":"Food & Drink"
        }
    ],
    "sg:phone":"+32 53 71 03 20",
    "sg:postcode":"9310",
    "sg:province":"Oost-Vlaanderen",
    "sg:tags":[
        "caf\u00e9s"
    ],
    "wof:name":"Caf\u00c9 Ons Hoeksken",
    "wof:placetype":"venue"
},
  "geometry": {"coordinates":[4.0863389969,50.9682922363],"type":"Point"}
}