{
  "type": "Feature",
  "properties": {
    "iso:country":"BE",
    "sg:address":"Rue De Baume 199",
    "sg:city":"La Louviere",
    "sg:orig_category":"Animations diverses",
    "sg:phone":"+32 64 22 99 00",
    "sg:postcode":"7100",
    "sg:province":"Hainaut",
    "wof:name":"Disco-dance",
    "wof:placetype":"venue"
},
  "geometry": {"coordinates":[4.2056970596,50.4730834961],"type":"Point"}
}