{
  "type": "Feature",
  "properties": {
    "addr:full":"Avenue Du Prince D'orange 231 Bruxelles (uccle) Bruxelles-Capitale 1180",
    "addr:housenumber":"231",
    "addr:postcode":"1180",
    "addr:street":"Avenue Du Prince D'Orange",
    "iso:country":"BE",
    "sg:address":"Avenue Du Prince D'orange 231",
    "sg:city":"Bruxelles (uccle)",
    "sg:classifiers":[
        {
            "category":"Health Services",
            "subcategory":"Doctor",
            "type":"Services"
        }
    ],
    "sg:phone":"+32 2 375 06 33",
    "sg:postcode":"1180",
    "sg:province":"Bruxelles-Capitale",
    "sg:tags":[
        "medicinephysicians",
        "surgeon"
    ],
    "wof:name":"Brachet E",
    "wof:placetype":"venue"
},
  "geometry": {"coordinates":[4.361410141,50.7820320129],"type":"Point"}
}