{
  "type": "Feature",
  "properties": {
    "addr:full":"Wouwerstraat 45 Heist-op-den-berg Antwerpen 2220",
    "addr:housenumber":"45",
    "addr:postcode":"2220",
    "addr:street":"Wouwerstraat",
    "iso:country":"BE",
    "sg:address":"Wouwerstraat 45",
    "sg:city":"Heist-op-den-berg",
    "sg:classifiers":[
        {
            "category":"Retail",
            "subcategory":"Auto Repair",
            "type":"Services"
        }
    ],
    "sg:phone":"+32 15 24 84 67",
    "sg:postcode":"2220",
    "sg:province":"Antwerpen",
    "sg:tags":[
        "automobile-body"
    ],
    "wof:name":"D B C Carrosseriecenter",
    "wof:placetype":"venue"
},
  "geometry": {"coordinates":[4.6974701881,51.061252594],"type":"Point"}
}