{
  "type": "Feature",
  "properties": {
    "iso:country":"BE",
    "sg:address":"Rue De La Marli\u00c8re 318",
    "sg:city":"Moeskroen/mouscron",
    "sg:orig_category":"Pain, p\u00e2tisseries and confiseries",
    "sg:phone":"+32 56 84 46 74",
    "sg:postcode":"7700",
    "sg:province":"Hainaut",
    "wof:name":"P\u00c2tisserie Fran\u00c7aise",
    "wof:placetype":"venue"
},
  "geometry": {"coordinates":[3.2323200703,50.7400932312],"type":"Point"}
}