{
  "type": "Feature",
  "properties": {
    "addr:full":"Wijngaardstraat 5b Kortrijk West-Vlaanderen 8500",
    "addr:housenumber":"5b",
    "addr:postcode":"8500",
    "addr:street":"Wijngaardstraat",
    "iso:country":"BE",
    "sg:address":"Wijngaardstraat 5b",
    "sg:city":"Kortrijk",
    "sg:classifiers":[
        {
            "category":"Shopping",
            "subcategory":"Clothing, Apparel, & Fashions",
            "type":"Retail Goods"
        }
    ],
    "sg:phone":"+32 56 21 86 89",
    "sg:postcode":"8500",
    "sg:province":"West-Vlaanderen",
    "sg:tags":[
        "underwear",
        "lingerie",
        "-"
    ],
    "wof:name":"Sexy Line Of Caroline (the)",
    "wof:placetype":"venue"
},
  "geometry": {"coordinates":[3.2691159248,50.8259429932],"type":"Point"}
}