{
  "type": "Feature",
  "properties": {
    "addr:full":"Klein Zottegem 51 Sint-lievens-houtem (vlierzele) Oost-Vlaanderen 9520",
    "addr:housenumber":"51",
    "addr:postcode":"9520",
    "addr:street":"Klein Zottegem",
    "iso:country":"BE",
    "sg:address":"Klein Zottegem 51",
    "sg:city":"Sint-lievens-houtem (vlierzele)",
    "sg:classifiers":[
        {
            "category":"Retail",
            "subcategory":"Auto Repair",
            "type":"Services"
        }
    ],
    "sg:phone":"+32 53 62 26 79",
    "sg:postcode":"9520",
    "sg:province":"Oost-Vlaanderen",
    "sg:tags":[
        "garage"
    ],
    "wof:name":"Garage Vliera-de Pauw",
    "wof:placetype":"venue"
},
  "geometry": {"coordinates":[3.8889451027,50.9275054932],"type":"Point"}
}