{
  "type": "Feature",
  "properties": {
    "addr:full":"Pb 144 Ninove Oost-Vlaanderen 9400",
    "addr:postcode":"9400",
    "addr:street":"Pb 144",
    "iso:country":"BE",
    "sg:address":"Pb 144",
    "sg:city":"Ninove",
    "sg:orig_category":"Boekhouders",
    "sg:phone":"+32 54 33 62 93",
    "sg:postcode":"9400",
    "sg:province":"Oost-Vlaanderen",
    "wof:name":"De Clercq Herman",
    "wof:placetype":"venue"
},
  "geometry": {"coordinates":[4.0232000351,50.8349113464],"type":"Point"}
}