{
  "type": "Feature",
  "properties": {
    "iso:country":"BE",
    "sg:address":"Rue Quevry 118",
    "sg:city":"Pont-\u00c0-celles",
    "sg:orig_category":"Boekhouders",
    "sg:phone":"+32 71 84 27 64",
    "sg:postcode":"6238",
    "sg:province":"Hainaut",
    "wof:name":"David Lievens",
    "wof:placetype":"venue"
},
  "geometry": {"coordinates":[4.3980460167,50.5143966675],"type":"Point"}
}