{
  "type": "Feature",
  "properties": {
    "addr:full":"Louisastraat 19 Oostende West-Vlaanderen 8400",
    "addr:housenumber":"19",
    "addr:postcode":"8400",
    "addr:street":"Louisastraat",
    "iso:country":"BE",
    "sg:address":"Louisastraat 19",
    "sg:city":"Oostende",
    "sg:orig_category":"H\u00f4tels. Restaurants",
    "sg:phone":"+32 59 70 09 28",
    "sg:postcode":"8400",
    "sg:province":"West-Vlaanderen",
    "wof:name":"Hotel Marion",
    "wof:placetype":"venue"
},
  "geometry": {"coordinates":[2.9171490669,51.2334632874],"type":"Point"}
}