{
  "type": "Feature",
  "properties": {
    "addr:full":"Bekaflaan 65 Aarschot Vlaams-Brabant 3200",
    "addr:housenumber":"65",
    "addr:postcode":"3200",
    "addr:street":"Bekaflaan",
    "iso:country":"BE",
    "sg:address":"Bekaflaan 65",
    "sg:city":"Aarschot",
    "sg:classifiers":[
        {
            "category":"Education",
            "subcategory":"School",
            "type":"Public Place"
        }
    ],
    "sg:phone":"+32 16 55 11 34",
    "sg:postcode":"3200",
    "sg:province":"Vlaams-Brabant",
    "sg:tags":[
        "primary"
    ],
    "wof:name":"St Jozefscollege",
    "wof:placetype":"venue"
},
  "geometry": {"coordinates":[4.8446888924,50.9865036011],"type":"Point"}
}