{
  "type": "Feature",
  "properties": {
    "addr:full":"Rue De L'etoile 101 Drogenbos Vlaams-Brabant 1620",
    "addr:housenumber":"101",
    "addr:postcode":"1620",
    "addr:street":"Rue De L'Etoile",
    "iso:country":"BE",
    "sg:address":"Rue De L'etoile 101",
    "sg:city":"Drogenbos",
    "sg:classifiers":[
        {
            "category":"Arena",
            "subcategory":"Sports Club",
            "type":"Entertainment"
        }
    ],
    "sg:phone":"+32 2 377 17 79",
    "sg:postcode":"1620",
    "sg:province":"Vlaams-Brabant",
    "sg:tags":[
        "de"
    ],
    "wof:name":"Ufac Uccle",
    "wof:placetype":"venue"
},
  "geometry": {"coordinates":[4.317343235,50.7903251648],"type":"Point"}
}