{
  "type": "Feature",
  "properties": {
    "addr:full":"Slangstraat 56 Hamme Oost-Vlaanderen 9220",
    "addr:housenumber":"56",
    "addr:postcode":"9220",
    "addr:street":"Slangstraat",
    "iso:country":"BE",
    "sg:address":"Slangstraat 56",
    "sg:city":"Hamme",
    "sg:orig_category":"Voedingsspeciaalzaken",
    "sg:phone":"+32 52 47 12 75",
    "sg:postcode":"9220",
    "sg:province":"Oost-Vlaanderen",
    "wof:name":"De Natuurwinkel",
    "wof:placetype":"venue"
},
  "geometry": {"coordinates":[4.1358728409,51.0932426453],"type":"Point"}
}