{
  "type": "Feature",
  "properties": {
    "addr:full":"Maldegemseweg 88a Knesselare Oost-Vlaanderen 9910",
    "addr:housenumber":"88a",
    "addr:postcode":"9910",
    "addr:street":"Maldegemseweg;Oost-Vlaanderen",
    "iso:country":"BE",
    "sg:address":"Maldegemseweg 88a",
    "sg:city":"Knesselare",
    "sg:orig_category":"Installatie van houten of kunststof schrijnwerk",
    "sg:phone":"+32 9 325 88 88",
    "sg:postcode":"9910",
    "sg:province":"Oost-Vlaanderen",
    "wof:name":"F. Speeckaert-mattheeuws",
    "wof:placetype":"venue"
},
  "geometry": {"coordinates":[3.4241240025,51.1415138245],"type":"Point"}
}