{
  "type": "Feature",
  "properties": {
    "iso:country":"BE",
    "sg:address":"Rue D'henripont 143",
    "sg:city":"Braine-le-comte (ronqui\u00e8res)",
    "sg:orig_category":"Non-Classified Establishments",
    "sg:phone":"+32 67 64 61 62",
    "sg:postcode":"7090",
    "sg:province":"Hainaut",
    "wof:name":"Lieds Ets",
    "wof:placetype":"venue"
},
  "geometry": {"coordinates":[4.0905909538,50.6249694824],"type":"Point"}
}