{
  "type": "Feature",
  "properties": {
    "iso:country":"BE",
    "sg:address":"Sint-idesbaldusstraat 27",
    "sg:city":"Veurne",
    "sg:classifiers":[
        {
            "category":"Retail",
            "subcategory":"Auto Repair",
            "type":"Services"
        }
    ],
    "sg:phone":"+32 58 31 18 07",
    "sg:postcode":"8630",
    "sg:province":"West-Vlaanderen",
    "sg:tags":[
        "garage"
    ],
    "wof:name":"Gar Van Hollebeke Nv",
    "wof:placetype":"venue"
},
  "geometry": {"coordinates":[2.651859045,51.0791435242],"type":"Point"}
}