{
  "type": "Feature",
  "properties": {
    "addr:full":"Eikenlaan 29 Kruibeke (bazel) Oost-Vlaanderen 9150",
    "addr:housenumber":"29",
    "addr:postcode":"9150",
    "addr:street":"Eikenlaan",
    "iso:country":"BE",
    "sg:address":"Eikenlaan 29",
    "sg:city":"Kruibeke (bazel)",
    "sg:classifiers":[
        {
            "category":"Professional",
            "subcategory":"Engineering",
            "type":"Services"
        }
    ],
    "sg:phone":"+32 3 740 03 10",
    "sg:postcode":"9150",
    "sg:province":"Oost-Vlaanderen",
    "sg:tags":[
        "-"
    ],
    "wof:name":"Belcance Bvba",
    "wof:placetype":"venue"
},
  "geometry": {"coordinates":[4.3009619713,51.1407814026],"type":"Point"}
}