{
  "type": "Feature",
  "properties": {
    "iso:country":"BE",
    "sg:address":"Jacques Paryslaan 22",
    "sg:city":"Evergem",
    "sg:orig_category":"Entretien and r\u00e9parations de voitures",
    "sg:phone":"+32 9 253 76 18",
    "sg:postcode":"9940",
    "sg:province":"Oost-Vlaanderen",
    "wof:name":"Van Schoubroek Motors",
    "wof:placetype":"venue"
},
  "geometry": {"coordinates":[3.7393610477,51.1389808655],"type":"Point"}
}