{
  "type": "Feature",
  "properties": {
    "iso:country":"BE",
    "sg:address":"Papestraat 53",
    "sg:city":"Ledegem",
    "sg:orig_category":"Quincailleries",
    "sg:phone":"+32 56 50 93 69",
    "sg:postcode":"8880",
    "sg:province":"West-Vlaanderen",
    "wof:name":"Vanhoutte Machinerie",
    "wof:placetype":"venue"
},
  "geometry": {"coordinates":[3.1163330078,50.8592376709],"type":"Point"}
}