{
  "type": "Feature",
  "properties": {
    "iso:country":"BE",
    "sg:address":"Pelgrimsstraat 25",
    "sg:city":"Antwerpen",
    "sg:orig_category":"Newspapers, magazines, periodicals - Distribution",
    "sg:phone":"+32 3 233 65 00",
    "sg:postcode":"2000",
    "sg:province":"Antwerpen",
    "wof:name":"Vadi",
    "wof:placetype":"venue"
},
  "geometry": {"coordinates":[4.3994469643,51.2193107605],"type":"Point"}
}