{
  "type": "Feature",
  "properties": {
    "addr:full":"Chauss\u00c9e De Nivelles 141 Sombreffe Namur 5140",
    "addr:housenumber":"141",
    "addr:postcode":"5140",
    "addr:street":"Chausse\u0301E De Nivelles",
    "iso:country":"BE",
    "sg:address":"Chauss\u00c9e De Nivelles 141",
    "sg:city":"Sombreffe",
    "sg:orig_category":"Stations-service and carburants. R\u00e9cup\u00e9ration de mati\u00e8res m\u00e9talliques recyclables and d\u00e9molisseurs d",
    "sg:phone":"+32 71 88 64 18",
    "sg:postcode":"5140",
    "sg:province":"Namur",
    "wof:name":"Garage Gardisseur",
    "wof:placetype":"venue"
},
  "geometry": {"coordinates":[4.5906791687,50.5282707214],"type":"Point"}
}