{
  "type": "Feature",
  "properties": {
    "iso:country":"BE",
    "sg:address":"Stationsstraat 303",
    "sg:city":"Ichtegem",
    "sg:orig_category":"Pain, p\u00e2tisseries and confiseries",
    "sg:phone":"+32 59 29 93 68",
    "sg:postcode":"8480",
    "sg:province":"West-Vlaanderen",
    "wof:name":"Marnix Geldhof",
    "wof:placetype":"venue"
},
  "geometry": {"coordinates":[3.0075318813,51.1244392395],"type":"Point"}
}