{
  "type": "Feature",
  "properties": {
    "addr:full":"Klossebos 7 Gent (zwijnaarde) Oost-Vlaanderen 9052",
    "addr:housenumber":"7",
    "addr:postcode":"9052",
    "addr:street":"Klossebos",
    "iso:country":"BE",
    "sg:address":"Klossebos 7",
    "sg:city":"Gent (zwijnaarde)",
    "sg:orig_category":"Non-Classified Establishments",
    "sg:phone":"+32 9 222 79 50",
    "sg:postcode":"9052",
    "sg:province":"Oost-Vlaanderen",
    "wof:name":"Minne-bonne Shoe",
    "wof:placetype":"venue"
},
  "geometry": {"coordinates":[3.7167270184,51.0002937317],"type":"Point"}
}