{
  "type": "Feature",
  "properties": {
    "addr:full":"Keernestraat 144 Herk-de-stad Limburg 3540",
    "addr:housenumber":"144",
    "addr:postcode":"3540",
    "addr:street":"Keernestraat",
    "iso:country":"BE",
    "sg:address":"Keernestraat 144",
    "sg:city":"Herk-de-stad",
    "sg:classifiers":[
        {
            "category":"Farming",
            "subcategory":"Crops",
            "type":"Manufacturing & Wholesale Goods"
        }
    ],
    "sg:phone":"+32 13 55 16 78",
    "sg:postcode":"3540",
    "sg:province":"Limburg",
    "sg:tags":[
        "vegetable",
        "fruit",
        "-",
        "grower"
    ],
    "wof:name":"Ruelens",
    "wof:placetype":"venue"
},
  "geometry": {"coordinates":[5.1578302383,50.9249687195],"type":"Point"}
}