{
  "type": "Feature",
  "properties": {
    "iso:country":"BE",
    "sg:address":"Slachthuiskaai 24",
    "sg:city":"Hasselt",
    "sg:classifiers":[
        {
            "category":"Professional",
            "subcategory":"Management & Consulting",
            "type":"Services"
        }
    ],
    "sg:phone":"+32 11 22 22 33",
    "sg:postcode":"3500",
    "sg:province":"Limburg",
    "sg:tags":[
        "tax-consultants"
    ],
    "wof:name":"Schoofs F",
    "wof:placetype":"venue"
},
  "geometry": {"coordinates":[5.3336238861,50.9427757263],"type":"Point"}
}