{
  "type": "Feature",
  "properties": {
    "iso:country":"BE",
    "sg:address":"Route Du Val 2a",
    "sg:city":"Clavier",
    "sg:classifiers":[
        {
            "category":"Home & Garden",
            "subcategory":"Hardware",
            "type":"Retail Goods"
        }
    ],
    "sg:phone":"+32 85 41 25 88",
    "sg:postcode":"4560",
    "sg:province":"Li\u00e8ge",
    "sg:tags":[
        "-"
    ],
    "wof:name":"Quincaillerie Du Val",
    "wof:placetype":"venue"
},
  "geometry": {"coordinates":[5.3165521622,50.4271697998],"type":"Point"}
}