{
  "type": "Feature",
  "properties": {
    "iso:country":"BE",
    "sg:address":"Rue Faider 16",
    "sg:city":"Sint-gillis/saint-gilles",
    "sg:orig_category":"Agences de relations publiques",
    "sg:phone":"+32 2 539 43 23",
    "sg:postcode":"1060",
    "sg:province":"Bruxelles-Capitale",
    "wof:name":"Bureau Du Bus De Warnaffe",
    "wof:placetype":"venue"
},
  "geometry": {"coordinates":[4.3568339348,50.8289756775],"type":"Point"}
}