{
  "type": "Feature",
  "properties": {
    "addr:full":"Ieperstraat 1 Menen West-Vlaanderen 8930",
    "addr:housenumber":"1",
    "addr:postcode":"8930",
    "addr:street":"Ieperstraat",
    "iso:country":"BE",
    "sg:address":"Ieperstraat 1",
    "sg:city":"Menen",
    "sg:orig_category":"Eclairage et \u00e9quipements du foyer. Biens d'occasion",
    "sg:phone":"+32 56 51 56 12",
    "sg:postcode":"8930",
    "sg:province":"West-Vlaanderen",
    "wof:name":"Oxfam Wereldwinkel",
    "wof:placetype":"venue"
},
  "geometry": {"coordinates":[3.1194860935,50.7963752747],"type":"Point"}
}