{
  "type": "Feature",
  "properties": {
    "addr:full":"Rue De Marchienne 13 Charleroi Hainaut 6000",
    "addr:housenumber":"13",
    "addr:postcode":"6000",
    "addr:street":"Rue De Marchienne;Hainaut",
    "iso:country":"BE",
    "sg:address":"Rue De Marchienne 13",
    "sg:city":"Charleroi",
    "sg:orig_category":"Slagers",
    "sg:phone":"+32 71 31 59 53",
    "sg:postcode":"6000",
    "sg:province":"Hainaut",
    "wof:name":"Boucherie Dewolf",
    "wof:placetype":"venue"
},
  "geometry": {"coordinates":[4.439991951,50.4077720642],"type":"Point"}
}