{
  "type": "Feature",
  "properties": {
    "addr:full":"Rue Du Centenaire 34 Charleroi Hainaut 6020",
    "addr:housenumber":"34",
    "addr:postcode":"6020",
    "addr:street":"Rue Du Centenaire;Hainaut",
    "iso:country":"BE",
    "sg:address":"Rue Du Centenaire 34",
    "sg:city":"Charleroi",
    "sg:orig_category":"D\u00e9taillants en pi\u00e8ces and accessoires de voitures",
    "sg:phone":"+32 71 31 73 32",
    "sg:postcode":"6020",
    "sg:province":"Hainaut",
    "wof:name":"Cools",
    "wof:placetype":"venue"
},
  "geometry": {"coordinates":[4.4251508713,50.4141998291],"type":"Point"}
}