{
  "type": "Feature",
  "properties": {
    "addr:full":"Rue De L'ecole 16 Rouvroy (harnoncourt) Luxembourg 6767",
    "addr:housenumber":"16",
    "addr:postcode":"6767",
    "addr:street":"Rue De L'Ecole",
    "iso:country":"BE",
    "sg:address":"Rue De L'ecole 16",
    "sg:city":"Rouvroy (harnoncourt)",
    "sg:orig_category":"Domotics",
    "sg:phone":"+32 63 58 21 25",
    "sg:postcode":"6767",
    "sg:province":"Luxembourg",
    "wof:name":"Wagner B",
    "wof:placetype":"venue"
},
  "geometry": {"coordinates":[2.9362690449,50.3975982666],"type":"Point"}
}