{
  "type": "Feature",
  "properties": {
    "addr:full":"Britselei 7b6 Antwerpen Antwerpen 2000",
    "addr:housenumber":"7b6",
    "addr:postcode":"2000",
    "addr:street":"Britselei",
    "iso:country":"BE",
    "sg:address":"Britselei 7b6",
    "sg:city":"Antwerpen",
    "sg:orig_category":"Boekhouders",
    "sg:phone":"+32 3 237 92 93",
    "sg:postcode":"2000",
    "sg:province":"Antwerpen",
    "wof:name":"Gunther Wendrickx",
    "wof:placetype":"venue"
},
  "geometry": {"coordinates":[4.4074568748,51.2105140686],"type":"Point"}
}