{
  "type": "Feature",
  "properties": {
    "iso:country":"BE",
    "sg:address":"Noorderlaan 83",
    "sg:city":"Antwerpen",
    "sg:classifiers":[
        {
            "category":"Manufacturing",
            "subcategory":"Tools & Machinery",
            "type":"Manufacturing & Wholesale Goods"
        }
    ],
    "sg:phone":"+32 3 545 90 80",
    "sg:postcode":"2030",
    "sg:province":"Antwerpen",
    "sg:tags":[
        "-"
    ],
    "wof:name":"Fabory Centre Antwerpen",
    "wof:placetype":"venue"
},
  "geometry": {"coordinates":[4.4198851585,51.2554740906],"type":"Point"}
}