{
  "type": "Feature",
  "properties": {
    "iso:country":"BE",
    "sg:address":"Stuivenbergbaan 170",
    "sg:city":"Mechelen",
    "sg:classifiers":[
        {
            "category":"Building & Trades",
            "subcategory":"Electrical",
            "type":"Services"
        }
    ],
    "sg:phone":"+32 15 33 76 31",
    "sg:postcode":"2800",
    "sg:province":"Antwerpen",
    "sg:tags":[
        "electric",
        "-",
        "housewiring",
        "contractor"
    ],
    "wof:name":"De Maeyer",
    "wof:placetype":"venue"
},
  "geometry": {"coordinates":[4.4688401222,51.0227813721],"type":"Point"}
}