{
  "type": "Feature",
  "properties": {
    "iso:country":"BE",
    "sg:address":"Rue Des Sarts 66a",
    "sg:city":"Charleroi (couillet)",
    "sg:orig_category":"Fiduciairies",
    "sg:phone":"+32 71 47 53 75",
    "sg:postcode":"6010",
    "sg:province":"Hainaut",
    "wof:name":"Derbeque J",
    "wof:placetype":"venue"
},
  "geometry": {"coordinates":[4.4722008705,50.3792800903],"type":"Point"}
}