{
  "type": "Feature",
  "properties": {
    "addr:full":"Nonnemeersstraat 19 Gent Oost-Vlaanderen 9000",
    "addr:housenumber":"19",
    "addr:postcode":"9000",
    "addr:street":"Nonnemeersstraat;Oost-Vlaanderen",
    "iso:country":"BE",
    "sg:address":"Nonnemeersstraat 19",
    "sg:city":"Gent",
    "sg:orig_category":"Volwassenenonderwijs",
    "sg:phone":"+32 9 267 12 99",
    "sg:postcode":"9000",
    "sg:province":"Oost-Vlaanderen",
    "wof:name":"Mercator-pcvo",
    "wof:placetype":"venue"
},
  "geometry": {"coordinates":[3.705878973,51.0438117981],"type":"Point"}
}