{
  "type": "Feature",
  "properties": {
    "addr:full":"Route Congr\u00c8s De Polleur 19 Theux Li\u00e8ge 4910",
    "addr:housenumber":"19",
    "addr:postcode":"4910",
    "addr:street":"Route Congre\u0300S De Polleur",
    "iso:country":"BE",
    "sg:address":"Route Congr\u00c8s De Polleur 19",
    "sg:city":"Theux",
    "sg:orig_category":"Dranken",
    "sg:phone":"+32 87 54 12 52",
    "sg:postcode":"4910",
    "sg:province":"Li\u00e8ge",
    "wof:name":"Andrien Drinks Drive-in",
    "wof:placetype":"venue"
},
  "geometry": {"coordinates":[5.8263897896,50.5261993408],"type":"Point"}
}