{
  "type": "Feature",
  "properties": {
    "iso:country":"BE",
    "sg:address":"Metro Luxemburg",
    "sg:city":"Bruxelles",
    "sg:classifiers":[
        {
            "category":"Cafe",
            "type":"Food & Drink"
        }
    ],
    "sg:phone":"+32 2 503 32 58",
    "sg:postcode":"1000",
    "sg:province":"Bruxelles-Capitale",
    "sg:tags":[
        "snack-bars"
    ],
    "wof:name":"Planet Sandwich",
    "wof:placetype":"venue"
},
  "geometry": {"coordinates":[4.3722000122,50.8394012451],"type":"Point"}
}