{
  "type": "Feature",
  "properties": {
    "iso:country":"BE",
    "sg:address":"Albertstraat 30",
    "sg:city":"Antwerpen",
    "sg:orig_category":"Produits interm\u00e9diaires Gr",
    "sg:phone":"+32 3 239 77 07",
    "sg:postcode":"2018",
    "sg:province":"Antwerpen",
    "wof:name":"Alexander Hochhauser",
    "wof:placetype":"venue"
},
  "geometry": {"coordinates":[4.4147129059,51.205165863],"type":"Point"}
}