{
  "type": "Feature",
  "properties": {
    "addr:full":"Rue Des Lattes 38 Cerfontaine Namur 5630",
    "addr:housenumber":"38",
    "addr:postcode":"5630",
    "addr:street":"Rue Des Lattes",
    "iso:country":"BE",
    "sg:address":"Rue Des Lattes 38",
    "sg:city":"Cerfontaine",
    "sg:orig_category":"Kapsalons",
    "sg:phone":"+32 71 61 26 38",
    "sg:postcode":"5630",
    "sg:province":"Namur",
    "wof:name":"Coiffure Val\u00c9rie",
    "wof:placetype":"venue"
},
  "geometry": {"coordinates":[4.4537158012,50.219367981],"type":"Point"}
}