{
  "type": "Feature",
  "properties": {
    "addr:full":"Stationsstraat 118-120 Ardooie West-Vlaanderen 8850",
    "addr:housenumber":"118-120",
    "addr:postcode":"8850",
    "addr:street":"Stationsstraat",
    "iso:country":"BE",
    "sg:address":"Stationsstraat 118-120",
    "sg:city":"Ardooie",
    "sg:classifiers":[
        {
            "category":"Mining & Drilling",
            "type":"Manufacturing & Wholesale Goods"
        }
    ],
    "sg:phone":"+32 51 74 59 99",
    "sg:postcode":"8850",
    "sg:province":"West-Vlaanderen",
    "sg:tags":[
        "boring",
        "well"
    ],
    "wof:name":"Deman-ameye J.l. Bvba-sprl",
    "wof:placetype":"venue"
},
  "geometry": {"coordinates":[3.2020709515,50.9831085205],"type":"Point"}
}