{
  "type": "Feature",
  "properties": {
    "iso:country":"BE",
    "sg:address":"Leopoldlei 7e",
    "sg:city":"Heist-op-den-berg",
    "sg:classifiers":[
        {
            "category":"Food & Beverages",
            "subcategory":"Specialty",
            "type":"Retail Goods"
        }
    ],
    "sg:phone":"+32 15 24 72 44",
    "sg:postcode":"2220",
    "sg:province":"Antwerpen",
    "sg:tags":[
        "health",
        "dietary",
        "-",
        "biological"
    ],
    "wof:name":"De Waterling-natuurvoeding Bvba",
    "wof:placetype":"venue"
},
  "geometry": {"coordinates":[4.7266488075,51.07629776],"type":"Point"}
}