{
  "type": "Feature",
  "properties": {
    "addr:full":"R Des M\u00fbriers 34 Jambes Namur 5100",
    "addr:housenumber":"34",
    "addr:postcode":"5100",
    "iso:country":"BE",
    "sg:address":"R Des M\u00fbriers 34",
    "sg:city":"Jambes",
    "sg:classifiers":[
        {
            "category":"Wholesale",
            "subcategory":"Machinery & Supplies",
            "type":"Manufacturing & Wholesale Goods"
        }
    ],
    "sg:phone":"+32 81 30 52 75",
    "sg:postcode":"5100",
    "sg:province":"Namur",
    "sg:tags":[
        "equipment",
        "precision"
    ],
    "wof:name":"Medical Chirurgical Medecins",
    "wof:placetype":"venue"
},
  "geometry": {"coordinates":[4.8868999481,50.4572868347],"type":"Point"}
}