{
  "type": "Feature",
  "properties": {
    "addr:full":"Basiliekstraat 69 Halle Vlaams-Brabant 1500",
    "addr:housenumber":"69",
    "addr:postcode":"1500",
    "addr:street":"Basiliekstraat",
    "iso:country":"BE",
    "sg:address":"Basiliekstraat 69",
    "sg:city":"Halle",
    "sg:orig_category":"R\u00e9parations de chaussures and articles en cuir",
    "sg:phone":"+32 2 356 20 18",
    "sg:postcode":"1500",
    "sg:province":"Vlaams-Brabant",
    "wof:name":"Schoenmakerij Fran-clo",
    "wof:placetype":"venue"
},
  "geometry": {"coordinates":[4.2360591888,50.7345542908],"type":"Point"}
}