{
  "type": "Feature",
  "properties": {
    "addr:full":"Rue Du Stade 5 Trooz Li\u00e8ge 4870",
    "addr:housenumber":"5",
    "addr:postcode":"4870",
    "addr:street":"Rue Du Stade",
    "iso:country":"BE",
    "sg:address":"Rue Du Stade 5",
    "sg:city":"Trooz",
    "sg:orig_category":"Kapsalons",
    "sg:phone":"+32 4 351 67 08",
    "sg:postcode":"4870",
    "sg:province":"Li\u00e8ge",
    "wof:name":"Coiffure Malek",
    "wof:placetype":"venue"
},
  "geometry": {"coordinates":[5.6632800102,50.5806312561],"type":"Point"}
}