{
  "type": "Feature",
  "properties": {
    "addr:full":"Haachtsesteenweg 1665 Brussel/bruxelles Bruxelles-Capitale 1130",
    "addr:postcode":"1665;/ bruxelles;1130",
    "addr:street":"Haachtsesteenweg",
    "iso:country":"BE",
    "sg:address":"Haachtsesteenweg 1665",
    "sg:city":"Brussel/bruxelles",
    "sg:orig_category":"IJzerwaren, bouw- and verfmaterialen Metalen and ertsen Gh Onderdelen and accessoires voertuigen Gh",
    "sg:phone":"+32 2 215 46 84",
    "sg:postcode":"1130",
    "sg:province":"Bruxelles-Capitale",
    "wof:name":"Meskens-coosemans",
    "wof:placetype":"venue"
},
  "geometry": {"coordinates":[4.4238591194,50.8878974915],"type":"Point"}
}