{
  "type": "Feature",
  "properties": {
    "addr:full":"Rue Cressonni\u00c8re 127 Fontaine-l\u00b4ev\u00caque Hainaut 6140",
    "addr:housenumber":"127",
    "addr:postcode":"6140",
    "addr:street":"Rue Cressonnie\u0300Re;Hainaut",
    "iso:country":"BE",
    "sg:address":"Rue Cressonni\u00c8re 127",
    "sg:city":"Fontaine-l\u00b4ev\u00caque",
    "sg:orig_category":"Herstellingen and onderhoud van auto's Voertuigen",
    "sg:phone":"+32 71 52 68 18",
    "sg:postcode":"6140",
    "sg:province":"Hainaut",
    "wof:name":"Garage Lebon",
    "wof:placetype":"venue"
},
  "geometry": {"coordinates":[4.3103098869,50.4106826782],"type":"Point"}
}