{
  "type": "Feature",
  "properties": {
    "iso:country":"BE",
    "sg:address":"Rue Grande 143",
    "sg:city":"La Louviere",
    "sg:orig_category":"Fleurs and plantes",
    "sg:phone":"+32 64 66 34 66",
    "sg:postcode":"7110",
    "sg:province":"Hainaut",
    "wof:name":"Maison Patricia",
    "wof:placetype":"venue"
},
  "geometry": {"coordinates":[4.1505050659,50.4826698303],"type":"Point"}
}