{
  "type": "Feature",
  "properties": {
    "iso:country":"BE",
    "sg:address":"Passage Pieter Van Aelst 2",
    "sg:city":"Aalst",
    "sg:orig_category":"Bagage and lederwaren Schoenen",
    "sg:phone":"+32 53 71 11 97",
    "sg:postcode":"9300",
    "sg:province":"Oost-Vlaanderen",
    "wof:name":"Ken",
    "wof:placetype":"venue"
},
  "geometry": {"coordinates":[4.0370321274,50.939125061],"type":"Point"}
}