{
  "type": "Feature",
  "properties": {
    "addr:full":"Chemin De Neerstalle 241 Bruxelles (forest) Bruxelles-Capitale 1190",
    "addr:housenumber":"241",
    "addr:postcode":"1190",
    "addr:street":"Chemin De Neerstalle",
    "iso:country":"BE",
    "sg:address":"Chemin De Neerstalle 241",
    "sg:city":"Bruxelles (forest)",
    "sg:classifiers":[
        {
            "category":"Building & Trades",
            "subcategory":"Plumbing",
            "type":"Services"
        }
    ],
    "sg:phone":"+32 495 38 81 81",
    "sg:postcode":"1190",
    "sg:province":"Bruxelles-Capitale",
    "sg:tags":[
        "contractor"
    ],
    "wof:name":"olivier Le Plombier",
    "wof:placetype":"venue"
},
  "geometry": {"coordinates":[4.3134689331,50.8043899536],"type":"Point"}
}