{
  "type": "Feature",
  "properties": {
    "addr:full":"Rue Du Chevet St.-pierre 5 Tournai Hainaut 7500",
    "addr:housenumber":"5",
    "addr:postcode":"7500",
    "addr:street":"Rue Du Chevet",
    "iso:country":"BE",
    "sg:address":"Rue Du Chevet St.-pierre 5",
    "sg:city":"Tournai",
    "sg:orig_category":"Pain, p\u00e2tisseries and confiseries",
    "sg:phone":"+32 69 22 24 93",
    "sg:postcode":"7500",
    "sg:province":"Hainaut",
    "wof:name":"P\u00c2tisserie Carlin-dario",
    "wof:placetype":"venue"
},
  "geometry": {"coordinates":[3.3916079998,50.6067504883],"type":"Point"}
}