{
  "type": "Feature",
  "properties": {
    "addr:full":"Place Elie Delferri\u00c8re 4 Charleroi Hainaut 6000",
    "addr:housenumber":"4",
    "addr:postcode":"6000",
    "addr:street":"Place Elie Delferrie\u0300Re;Hainaut",
    "iso:country":"BE",
    "sg:address":"Place Elie Delferri\u00c8re 4",
    "sg:city":"Charleroi",
    "sg:orig_category":"Centres de relaxation and bien-\u00eatre",
    "sg:phone":"+32 71 42 02 77",
    "sg:postcode":"6000",
    "sg:province":"Hainaut",
    "wof:name":"Solarium Eanness",
    "wof:placetype":"venue"
},
  "geometry": {"coordinates":[4.4524989128,50.4217681885],"type":"Point"}
}