{
  "type": "Feature",
  "properties": {
    "iso:country":"BE",
    "sg:address":"Lange Kroonstraat 19",
    "sg:city":"Boechout",
    "sg:orig_category":"Sportclubs",
    "sg:phone":"+32 3 454 42 56",
    "sg:postcode":"2530",
    "sg:province":"Antwerpen",
    "wof:name":"Deugd En Volharding",
    "wof:placetype":"venue"
},
  "geometry": {"coordinates":[4.4890189171,51.1618080139],"type":"Point"}
}