{
  "type": "Feature",
  "properties": {
    "iso:country":"BE",
    "sg:address":"Chinheid 4b",
    "sg:city":"Pepinster",
    "sg:classifiers":[
        {
            "category":"Retail",
            "subcategory":"Car Wash",
            "type":"Services"
        }
    ],
    "sg:phone":"+32 87 39 80 55",
    "sg:postcode":"4860",
    "sg:province":"Li\u00e8ge",
    "sg:tags":[
        "automobile",
        "washing",
        "-",
        "truck"
    ],
    "wof:name":"Lariotte S",
    "wof:placetype":"venue"
},
  "geometry": {"coordinates":[5.8116297722,50.5580482483],"type":"Point"}
}