{
  "type": "Feature",
  "properties": {
    "addr:full":"Prattenborgstraat 41 Scherpenheuvel-zichem (scherpenheuvel) Vlaams-Brabant 3270",
    "addr:housenumber":"41",
    "addr:postcode":"3270",
    "addr:street":"Prattenborgstraat",
    "iso:country":"BE",
    "sg:address":"Prattenborgstraat 41",
    "sg:city":"Scherpenheuvel-zichem (scherpenheuvel)",
    "sg:classifiers":[
        {
            "category":"Bakery",
            "type":"Food & Drink"
        }
    ],
    "sg:phone":"+32 13 77 15 54",
    "sg:postcode":"3270",
    "sg:province":"Vlaams-Brabant",
    "sg:tags":[
        "confectioner",
        "baker"
    ],
    "wof:name":"Erwin",
    "wof:placetype":"venue"
},
  "geometry": {"coordinates":[4.9770388603,50.9780349731],"type":"Point"}
}