{
  "type": "Feature",
  "properties": {
    "addr:full":"Kennedylaan 4 Sint-truiden Limburg 3800",
    "addr:housenumber":"4",
    "addr:postcode":"3800",
    "addr:street":"Kennedylaan",
    "iso:country":"BE",
    "sg:address":"Kennedylaan 4",
    "sg:city":"Sint-truiden",
    "sg:orig_category":"Epiceries",
    "sg:phone":"+32 11 69 81 38",
    "sg:postcode":"3800",
    "sg:province":"Limburg",
    "wof:name":"Delhaize",
    "wof:placetype":"venue"
},
  "geometry": {"coordinates":[5.1928792,50.8106269836],"type":"Point"}
}