{
  "type": "Feature",
  "properties": {
    "iso:country":"BE",
    "sg:address":"Marktplein 13-14",
    "sg:city":"De Panne",
    "sg:orig_category":"RESTAURANTS: H\u00d4TELS",
    "sg:phone":"+32 58 41 13 41",
    "sg:postcode":"8660",
    "sg:province":"West-Vlaanderen",
    "wof:name":"Cecil - Lantaern",
    "wof:placetype":"venue"
},
  "geometry": {"coordinates":[2.5929749012,51.098777771],"type":"Point"}
}