{
  "type": "Feature",
  "properties": {
    "addr:full":"Rue De La Grande Ronce 30 Ecaussines Hainaut 7191",
    "addr:housenumber":"30",
    "addr:postcode":"7191",
    "addr:street":"Rue De La Grande Ronce;Hainaut",
    "iso:country":"BE",
    "sg:address":"Rue De La Grande Ronce 30",
    "sg:city":"Ecaussines",
    "sg:orig_category":"Cuisines and Equipements de Cuisines. Meubles D\u00e9taillants, Am\u00e9nagement de B\u00e2timents et de Cuisines. ",
    "sg:phone":"+32 67 44 26 50",
    "sg:postcode":"7191",
    "sg:province":"Hainaut",
    "wof:name":"Jean Hamays S.a.",
    "wof:placetype":"venue"
},
  "geometry": {"coordinates":[-1.1633499861,45.7971115112],"type":"Point"}
}