{
  "type": "Feature",
  "properties": {
    "iso:country":"BE",
    "sg:address":"Rue Des Basjaunes 26",
    "sg:city":"Court-saint-etienne",
    "sg:classifiers":[
        {
            "category":"Professional",
            "subcategory":"Accounting & Tax Preparation",
            "type":"Services"
        }
    ],
    "sg:phone":"+32 10 61 52 07",
    "sg:postcode":"1490",
    "sg:province":"Brabant Wallon",
    "sg:tags":[
        "bookkeeper"
    ],
    "wof:name":"Sogefid Sprl",
    "wof:placetype":"venue"
},
  "geometry": {"coordinates":[4.5650019646,50.6261787415],"type":"Point"}
}