{
  "type": "Feature",
  "properties": {
    "iso:country":"BE",
    "sg:address":"Moerhoflaan 103",
    "sg:city":"Schilde",
    "sg:orig_category":"Reclamebureaus",
    "sg:phone":"+32 3 383 61 16",
    "sg:postcode":"2970",
    "sg:province":"Antwerpen",
    "wof:name":"Effekt Reklameadviseurs",
    "wof:placetype":"venue"
},
  "geometry": {"coordinates":[4.5873317719,51.2578315735],"type":"Point"}
}