{
  "type": "Feature",
  "properties": {
    "addr:full":"Diestsestraat 54 Scherpenheuvel-zichem (scherpenheuvel) Vlaams-Brabant 3270",
    "addr:housenumber":"54",
    "addr:postcode":"3270",
    "addr:street":"Diestsestraat",
    "iso:country":"BE",
    "sg:address":"Diestsestraat 54",
    "sg:city":"Scherpenheuvel-zichem (scherpenheuvel)",
    "sg:classifiers":[
        {
            "category":"Real Estate",
            "subcategory":"Surveying",
            "type":"Services"
        }
    ],
    "sg:phone":"+32 13 77 21 37",
    "sg:postcode":"3270",
    "sg:province":"Vlaams-Brabant",
    "sg:tags":[
        "surveyor",
        "land"
    ],
    "wof:name":"Buyckx C",
    "wof:placetype":"venue"
},
  "geometry": {"coordinates":[4.9882497787,50.978679657],"type":"Point"}
}