{
  "type": "Feature",
  "properties": {
    "iso:country":"BE",
    "sg:address":"Jan Breydelstraat 70",
    "sg:city":"Harelbeke",
    "sg:orig_category":"Brood, gebak and snoepgoed",
    "sg:phone":"+32 56 70 10 00",
    "sg:postcode":"8530",
    "sg:province":"West-Vlaanderen",
    "wof:name":"Martin Vanwynsberghe",
    "wof:placetype":"venue"
},
  "geometry": {"coordinates":[3.2964770794,50.8422431946],"type":"Point"}
}