{
  "type": "Feature",
  "properties": {
    "addr:full":"Prinsenbeemdlaan 19 Meise Vlaams-Brabant 1860",
    "addr:housenumber":"19",
    "addr:postcode":"1860",
    "addr:street":"Prinsenbeemdlaan",
    "iso:country":"BE",
    "sg:address":"Prinsenbeemdlaan 19",
    "sg:city":"Meise",
    "sg:classifiers":[
        {
            "category":"Arena",
            "subcategory":"Sports Club",
            "type":"Entertainment"
        }
    ],
    "sg:phone":"+32 2 269 33 29",
    "sg:postcode":"1860",
    "sg:province":"Vlaams-Brabant",
    "sg:tags":[
        "de"
    ],
    "wof:name":"Judokwai Yoshin",
    "wof:placetype":"venue"
},
  "geometry": {"coordinates":[4.3374471664,50.9285926819],"type":"Point"}
}