{
  "type": "Feature",
  "properties": {
    "addr:full":"Rue Du Commerce 2 Houyet Namur 5560",
    "addr:housenumber":"2",
    "addr:postcode":"5560",
    "addr:street":"Rue Du Commerce",
    "iso:country":"BE",
    "sg:address":"Rue Du Commerce 2",
    "sg:city":"Houyet",
    "sg:orig_category":"Boucheries",
    "sg:phone":"+32 82 74 43 92",
    "sg:postcode":"5560",
    "sg:province":"Namur",
    "wof:name":"Albert Godfrin",
    "wof:placetype":"venue"
},
  "geometry": {"coordinates":[4.8858251572,50.1681632996],"type":"Point"}
}