{
  "type": "Feature",
  "properties": {
    "addr:full":"Boulevard De La Meuse 42b4 Namur Namur 5100",
    "addr:housenumber":"42b4",
    "addr:postcode":"5100",
    "addr:street":"Boulevard De La Meuse",
    "iso:country":"BE",
    "sg:address":"Boulevard De La Meuse 42b4",
    "sg:city":"Namur",
    "sg:orig_category":"M\u00e9decins and sp\u00e9cialistes",
    "sg:phone":"+32 81 30 66 60",
    "sg:postcode":"5100",
    "sg:province":"Namur",
    "wof:name":"P. Mousset",
    "wof:placetype":"venue"
},
  "geometry": {"coordinates":[4.8713750839,50.4566345215],"type":"Point"}
}