{
  "type": "Feature",
  "properties": {
    "addr:full":"Rue Memling 9 Anderlecht Bruxelles-Capitale 1070",
    "addr:housenumber":"9",
    "addr:postcode":"1070",
    "addr:street":"Rue Memling",
    "iso:country":"BE",
    "sg:address":"Rue Memling 9",
    "sg:city":"Anderlecht",
    "sg:orig_category":"Travaux de pl\u00e2trage",
    "sg:phone":"+32 2 520 45 12",
    "sg:postcode":"1070",
    "sg:province":"Bruxelles-Capitale",
    "wof:name":"Reno-gyp",
    "wof:placetype":"venue"
},
  "geometry": {"coordinates":[4.3340392113,50.8413696289],"type":"Point"}
}