{
  "type": "Feature",
  "properties": {
    "addr:full":"Walpoortstraat 26 Gent Oost-Vlaanderen 9000",
    "addr:housenumber":"26",
    "addr:postcode":"9000",
    "addr:street":"Walpoortstraat;Oost-Vlaanderen",
    "iso:country":"BE",
    "sg:address":"Walpoortstraat 26",
    "sg:city":"Gent",
    "sg:orig_category":"Geschenken and souvenirs Verlichting and huishoudartikelen",
    "sg:phone":"+32 9 223 61 93",
    "sg:postcode":"9000",
    "sg:province":"Oost-Vlaanderen",
    "wof:name":"Katharina Bouckaert",
    "wof:placetype":"venue"
},
  "geometry": {"coordinates":[3.7269279957,51.0489425659],"type":"Point"}
}