{
  "type": "Feature",
  "properties": {
    "iso:country":"BE",
    "sg:address":"Maria-theresiastraat 90",
    "sg:city":"Leuven",
    "sg:orig_category":"Advocaten and juridische adviseurs",
    "sg:phone":"+32 16 22 12 12",
    "sg:postcode":"3000",
    "sg:province":"Vlaams-Brabant",
    "wof:name":"F. Norman",
    "wof:placetype":"venue"
},
  "geometry": {"coordinates":[4.7136640549,50.8794975281],"type":"Point"}
}