{
  "type": "Feature",
  "properties": {
    "iso:country":"BE",
    "sg:address":"Sint-jorislaan 32",
    "sg:city":"Herk-de-stad (schulen)",
    "sg:classifiers":[
        {
            "category":"Building & Trades",
            "subcategory":"Pest Control",
            "type":"Services"
        }
    ],
    "sg:phone":"+32 13 55 10 15",
    "sg:postcode":"3540",
    "sg:province":"Limburg",
    "sg:tags":[
        "painting",
        "contractor"
    ],
    "wof:name":"Martens Sammy Schilderwerken",
    "wof:placetype":"venue"
},
  "geometry": {"coordinates":[5.1897230148,50.9605560303],"type":"Point"}
}