{
  "type": "Feature",
  "properties": {
    "iso:country":"BE",
    "sg:address":"Avenue Des Lanciers 78",
    "sg:city":"Spa",
    "sg:classifiers":[
        {
            "category":"Fast Food",
            "type":"Food & Drink"
        }
    ],
    "sg:phone":"+32 87 77 47 02",
    "sg:postcode":"4900",
    "sg:province":"Li\u00e8ge",
    "sg:tags":[
        "fried",
        "stand",
        "potato"
    ],
    "wof:name":"Lanciers",
    "wof:placetype":"venue"
},
  "geometry": {"coordinates":[5.8511300087,50.4876403809],"type":"Point"}
}