{
  "type": "Feature",
  "properties": {
    "addr:full":"Rue Auguste Lambiotte 70 Bruxelles (schaerbeek) Bruxelles-Capitale 1030",
    "addr:housenumber":"70",
    "addr:postcode":"1030",
    "addr:street":"Rue Auguste Lambiotte",
    "iso:country":"BE",
    "sg:address":"Rue Auguste Lambiotte 70",
    "sg:city":"Bruxelles (schaerbeek)",
    "sg:classifiers":[
        {
            "category":"Building & Trades",
            "subcategory":"Cleaning & Sanitation",
            "type":"Services"
        }
    ],
    "sg:phone":"+32 2 215 88 83",
    "sg:postcode":"1030",
    "sg:province":"Bruxelles-Capitale",
    "sg:tags":[
        "janitor"
    ],
    "wof:name":"Brunet Sprl",
    "wof:placetype":"venue"
},
  "geometry": {"coordinates":[4.3889398575,50.8555335999],"type":"Point"}
}