{
  "type": "Feature",
  "properties": {
    "addr:full":"Kouterbaan 75 Denderleeuw Oost-Vlaanderen 9470",
    "addr:housenumber":"75",
    "addr:postcode":"9470",
    "addr:street":"Kouterbaan",
    "iso:country":"BE",
    "sg:address":"Kouterbaan 75",
    "sg:city":"Denderleeuw",
    "sg:orig_category":"Chaussures",
    "sg:phone":"+32 53 66 83 20",
    "sg:postcode":"9470",
    "sg:province":"Oost-Vlaanderen",
    "wof:name":"Ann-shoe",
    "wof:placetype":"venue"
},
  "geometry": {"coordinates":[4.0705227852,50.8895988464],"type":"Point"}
}