{
  "type": "Feature",
  "properties": {
    "iso:country":"BE",
    "sg:address":"Henry Fordlaan 11",
    "sg:city":"Genk",
    "sg:orig_category":"Mat\u00e9riel de contr\u00f4le des processus industriels Fab. Installation \u00e9lectrique r\u00e9sidentielle. Installat",
    "sg:phone":"+32 89 61 34 00",
    "sg:postcode":"3600",
    "sg:province":"Limburg",
    "wof:name":"G.t.i. Electro Thijs",
    "wof:placetype":"venue"
},
  "geometry": {"coordinates":[5.5050311089,50.9186096191],"type":"Point"}
}