{
  "type": "Feature",
  "properties": {
    "iso:country":"BE",
    "sg:address":"Hazelaardreef 16",
    "sg:city":"Grobbendonk",
    "sg:orig_category":"Artsen and specialisten",
    "sg:phone":"+32 14 51 15 14",
    "sg:postcode":"2280",
    "sg:province":"Antwerpen",
    "wof:name":"K. Bruyneel",
    "wof:placetype":"venue"
},
  "geometry": {"coordinates":[4.7205610275,51.1713104248],"type":"Point"}
}