{
  "type": "Feature",
  "properties": {
    "iso:country":"BE",
    "sg:address":"Prinsessestraat 159 Box 5",
    "sg:city":"Izegem",
    "sg:orig_category":"Non-Classified Establishments",
    "sg:phone":"+32 51 31 64 42",
    "sg:postcode":"8870",
    "sg:province":"West-Vlaanderen",
    "wof:name":"Semetier O",
    "wof:placetype":"venue"
},
  "geometry": {"coordinates":[3.2180769444,50.9236373901],"type":"Point"}
}