{
  "type": "Feature",
  "properties": {
    "iso:country":"BE",
    "sg:address":"Jan Frans Willemsstraat 10",
    "sg:city":"Boechout",
    "sg:orig_category":"Supermarkten Warenhuizen",
    "sg:phone":"+32 3 455 38 09",
    "sg:postcode":"2530",
    "sg:province":"Antwerpen",
    "wof:name":"Lumaco",
    "wof:placetype":"venue"
},
  "geometry": {"coordinates":[4.4935011864,51.162322998],"type":"Point"}
}