{
  "type": "Feature",
  "properties": {
    "addr:full":"Rue De La Tourtelle 26 Genappe Brabant Wallon 1476",
    "addr:housenumber":"26",
    "addr:postcode":"1476",
    "addr:street":"Rue De La Tourtelle;Wallon",
    "iso:country":"BE",
    "sg:address":"Rue De La Tourtelle 26",
    "sg:city":"Genappe",
    "sg:orig_category":"Verhuur televisie- and audiovisuele apparatuur",
    "sg:phone":"+32 67 77 37 03",
    "sg:postcode":"1476",
    "sg:province":"Brabant Wallon",
    "wof:name":"D.j. Sound",
    "wof:placetype":"venue"
},
  "geometry": {"coordinates":[4.4144701958,50.5812950134],"type":"Point"}
}