{
  "type": "Feature",
  "properties": {
    "addr:full":"Bruggestraat 81 Wingene West-Vlaanderen 8750",
    "addr:housenumber":"81",
    "addr:postcode":"8750",
    "addr:street":"Bruggestraat",
    "iso:country":"BE",
    "sg:address":"Bruggestraat 81",
    "sg:city":"Wingene",
    "sg:orig_category":"M\u00e9decins and sp\u00e9cialistes",
    "sg:phone":"+32 51 61 27 05",
    "sg:postcode":"8750",
    "sg:province":"West-Vlaanderen",
    "wof:name":"Johan Verhaeghe",
    "wof:placetype":"venue"
},
  "geometry": {"coordinates":[3.2712950706,51.0575904846],"type":"Point"}
}