{
  "type": "Feature",
  "properties": {
    "addr:full":"Ooievaarlaan 11 Deinze Oost-Vlaanderen 9800",
    "addr:housenumber":"11",
    "addr:postcode":"9800",
    "addr:street":"Ooievaarlaan",
    "iso:country":"BE",
    "sg:address":"Ooievaarlaan 11",
    "sg:city":"Deinze",
    "sg:orig_category":"Beautyfarms, relaxatie and lichamelijk welzijn Schoonheidssalons",
    "sg:phone":"+32 9 380 04 07",
    "sg:postcode":"9800",
    "sg:province":"Oost-Vlaanderen",
    "wof:name":"Beauty Studio",
    "wof:placetype":"venue"
},
  "geometry": {"coordinates":[3.530174017,50.9863166809],"type":"Point"}
}