{
  "type": "Feature",
  "properties": {
    "iso:country":"BE",
    "sg:address":"Kauwstraat 22",
    "sg:city":"Pittem",
    "sg:orig_category":"Epiceries",
    "sg:phone":"+32 51 46 77 17",
    "sg:postcode":"8740",
    "sg:province":"West-Vlaanderen",
    "wof:name":"Suzanna Vercoutere",
    "wof:placetype":"venue"
},
  "geometry": {"coordinates":[3.2639539242,50.9938011169],"type":"Point"}
}