{
  "type": "Feature",
  "properties": {
    "addr:full":"Medaerstraat 6 Dilsen-stokkem Limburg 3650",
    "addr:housenumber":"6",
    "addr:postcode":"3650",
    "addr:street":"Medaerstraat",
    "iso:country":"BE",
    "sg:address":"Medaerstraat 6",
    "sg:city":"Dilsen-stokkem",
    "sg:orig_category":"Pain, p\u00e2tisseries and confiseries",
    "sg:phone":"+32 89 75 68 78",
    "sg:postcode":"3650",
    "sg:province":"Limburg",
    "wof:name":"Patisserie Albert",
    "wof:placetype":"venue"
},
  "geometry": {"coordinates":[5.727396965,51.0364189148],"type":"Point"}
}