{
  "type": "Feature",
  "properties": {
    "iso:country":"BE",
    "sg:address":"Centrum Zuid 1",
    "sg:city":"Houthalen-helchteren",
    "sg:orig_category":"Papierwaren and schoolbenodigdheden Gh",
    "sg:phone":"+32 11 52 40 04",
    "sg:postcode":"3530",
    "sg:province":"Limburg",
    "wof:name":"Sipro",
    "wof:placetype":"venue"
},
  "geometry": {"coordinates":[5.3518128395,51.0194778442],"type":"Point"}
}