{
  "type": "Feature",
  "properties": {
    "addr:full":"Adriaan Walraevensstraat 2a Grimbergen Vlaams-Brabant 1850",
    "addr:housenumber":"2a",
    "addr:postcode":"1850",
    "addr:street":"Walraevensstraat",
    "iso:country":"BE",
    "sg:address":"Adriaan Walraevensstraat 2a",
    "sg:city":"Grimbergen",
    "sg:classifiers":[
        {
            "category":"Professional",
            "subcategory":"Management & Consulting",
            "type":"Services"
        }
    ],
    "sg:phone":"+32 2 253 84 12",
    "sg:postcode":"1850",
    "sg:province":"Vlaams-Brabant",
    "sg:tags":[
        "-",
        "processing",
        "data",
        "consultant"
    ],
    "wof:name":"Bormans G",
    "wof:placetype":"venue"
},
  "geometry": {"coordinates":[4.4076981544,50.9268722534],"type":"Point"}
}