{
  "type": "Feature",
  "properties": {
    "iso:country":"BE",
    "sg:address":"Herestr 5",
    "sg:city":"Leuven",
    "sg:classifiers":[
        {
            "category":"Wholesale",
            "subcategory":"Medical Equipment & Supplies",
            "type":"Manufacturing & Wholesale Goods"
        }
    ],
    "sg:phone":"+32 16 23 28 97",
    "sg:postcode":"3000",
    "sg:province":"Vlaams-Brabant",
    "sg:tags":[
        "instrument",
        "health",
        "-",
        "precision"
    ],
    "wof:name":"Vitatron Belgium Nv",
    "wof:placetype":"venue"
},
  "geometry": {"coordinates":[4.6815900803,50.8801002502],"type":"Point"}
}