{
  "type": "Feature",
  "properties": {
    "addr:full":"Rue Neuve 13 Pont-\u00e0-celles (luttre) Hainaut 6238",
    "addr:housenumber":"13",
    "addr:postcode":"6238",
    "addr:street":"Rue Neuve",
    "iso:country":"BE",
    "sg:address":"Rue Neuve 13",
    "sg:city":"Pont-\u00e0-celles (luttre)",
    "sg:classifiers":[
        {
            "category":"Building & Trades",
            "subcategory":"Construction",
            "type":"Services"
        }
    ],
    "sg:phone":"+32 71 84 44 53",
    "sg:postcode":"6238",
    "sg:province":"Hainaut",
    "sg:tags":[
        "carpenter"
    ],
    "wof:name":"Coulon",
    "wof:placetype":"venue"
},
  "geometry": {"coordinates":[4.4201931953,50.5158462524],"type":"Point"}
}