{
  "type": "Feature",
  "properties": {
    "iso:country":"BE",
    "sg:address":"Meensesteenweg 264",
    "sg:city":"Roeselare",
    "sg:classifiers":[
        {
            "category":"Autos & Motor Vehicles",
            "subcategory":"Fuel & Gas Station",
            "type":"Retail Goods"
        }
    ],
    "sg:phone":"+32 51 24 82 04",
    "sg:postcode":"8800",
    "sg:province":"West-Vlaanderen",
    "wof:name":"Degryse",
    "wof:placetype":"venue"
},
  "geometry": {"coordinates":[3.1200950146,50.9333610535],"type":"Point"}
}