{
  "type": "Feature",
  "properties": {
    "iso:country":"BE",
    "sg:address":"Beekstraat 2a",
    "sg:city":"Aalst (erembodegem)",
    "sg:classifiers":[
        {
            "category":"Professional",
            "subcategory":"Secretarial Services",
            "type":"Services"
        }
    ],
    "sg:phone":"+32 53 84 85 97",
    "sg:postcode":"9320",
    "sg:province":"Oost-Vlaanderen",
    "sg:tags":[
        "firm"
    ],
    "wof:name":"Fab",
    "wof:placetype":"venue"
},
  "geometry": {"coordinates":[4.0745978355,50.9450378418],"type":"Point"}
}