{
  "type": "Feature",
  "properties": {
    "iso:country":"BE",
    "sg:address":"Zandvoordsestraat 78",
    "sg:city":"Oudenburg",
    "sg:classifiers":[
        {
            "category":"Parking",
            "subcategory":"Lot",
            "type":"Transportation"
        }
    ],
    "sg:phone":"+32 59 26 69 13",
    "sg:postcode":"8460",
    "sg:province":"West-Vlaanderen",
    "sg:tags":[
        "parking-places",
        "laying-out"
    ],
    "wof:name":"Vandenbroucke U & R Bvba",
    "wof:placetype":"venue"
},
  "geometry": {"coordinates":[2.9964458942,51.1874198914],"type":"Point"}
}