{
  "type": "Feature",
  "properties": {
    "iso:country":"BE",
    "sg:address":"Helbeekplein 1 Box 31",
    "sg:city":"Hasselt",
    "sg:classifiers":[
        {
            "category":"Autos & Motor Vehicles",
            "subcategory":"Fuel & Gas Station",
            "type":"Retail Goods"
        }
    ],
    "sg:phone":"+32 11 27 10 29",
    "sg:postcode":"3500",
    "sg:province":"Limburg",
    "sg:tags":[
        "appliance",
        "mainten",
        "-"
    ],
    "wof:name":"Sani-scooter",
    "wof:placetype":"venue"
},
  "geometry": {"coordinates":[5.3416728973,50.9224319458],"type":"Point"}
}