{
  "type": "Feature",
  "properties": {
    "iso:country":"BE",
    "sg:address":"Staf Larochelaan 27bb",
    "sg:city":"Brecht",
    "sg:orig_category":"Fotografen and fotostudio's",
    "sg:phone":"+32 3 636 14 24",
    "sg:postcode":"2960",
    "sg:province":"Antwerpen",
    "wof:name":"Marc Van Bael",
    "wof:placetype":"venue"
},
  "geometry": {"coordinates":[4.5806908607,51.3027801514],"type":"Point"}
}