{
  "type": "Feature",
  "properties": {
    "addr:full":"Kapelsesteenweg 158 Brasschaat Antwerpen 2930",
    "addr:housenumber":"158",
    "addr:postcode":"2930",
    "addr:street":"Kapelsesteenweg",
    "iso:country":"BE",
    "sg:address":"Kapelsesteenweg 158",
    "sg:city":"Brasschaat",
    "sg:classifiers":[
        {
            "category":"Professional",
            "subcategory":"Accounting & Tax Preparation",
            "type":"Services"
        }
    ],
    "sg:phone":"+32 3 327 94 21",
    "sg:postcode":"2930",
    "sg:province":"Antwerpen",
    "sg:tags":[
        "bookkeeper"
    ],
    "wof:name":"Braeckmans H",
    "wof:placetype":"venue"
},
  "geometry": {"coordinates":[4.4546689987,51.2782287598],"type":"Point"}
}