{
  "type": "Feature",
  "properties": {
    "iso:country":"BE",
    "sg:address":"Kapellelei 19",
    "sg:city":"Mortsel",
    "sg:classifiers":[
        {
            "category":"Professional",
            "subcategory":"Art Services",
            "type":"Services"
        }
    ],
    "sg:phone":"+32 3 449 43 52",
    "sg:postcode":"2640",
    "sg:province":"Antwerpen",
    "sg:tags":[
        "sculptor"
    ],
    "wof:name":"Van Dongen O",
    "wof:placetype":"venue"
},
  "geometry": {"coordinates":[4.4522337914,51.181186676],"type":"Point"}
}