{
  "type": "Feature",
  "properties": {
    "addr:full":"Rue De La Montagne 89 Lontzen/lontzen Li\u00e8ge 4710",
    "addr:housenumber":"89",
    "addr:postcode":"4710",
    "addr:street":"Rue De La Montagne",
    "iso:country":"BE",
    "sg:address":"Rue De La Montagne 89",
    "sg:city":"Lontzen/lontzen",
    "sg:orig_category":"Instituts de beaut\u00e9",
    "sg:phone":"+32 87 65 65 64",
    "sg:postcode":"4710",
    "sg:province":"Li\u00e8ge",
    "wof:name":"Y. Willems",
    "wof:placetype":"venue"
},
  "geometry": {"coordinates":[6.0124731064,50.6865768433],"type":"Point"}
}