{
  "type": "Feature",
  "properties": {
    "iso:country":"BE",
    "sg:address":"Rue Du Centre 138",
    "sg:city":"Namur (saint-marc)",
    "sg:classifiers":[
        {
            "category":"Building & Trades",
            "subcategory":"Construction",
            "type":"Services"
        }
    ],
    "sg:phone":"+32 81 74 44 64",
    "sg:postcode":"5003",
    "sg:province":"Namur",
    "sg:tags":[
        "surveyor",
        "-"
    ],
    "wof:name":"Bureau Remacle",
    "wof:placetype":"venue"
},
  "geometry": {"coordinates":[4.8473348618,50.4915008545],"type":"Point"}
}