{
  "type": "Feature",
  "properties": {
    "iso:country":"BE",
    "sg:address":"Ledebergplein 45",
    "sg:city":"Gent (ledeberg)",
    "sg:classifiers":[
        {
            "category":"Real Estate",
            "subcategory":"Real Estate Services",
            "type":"Services"
        }
    ],
    "sg:phone":"+32 9 252 36 30",
    "sg:postcode":"9050",
    "sg:province":"Oost-Vlaanderen",
    "wof:name":"Kint & Co",
    "wof:placetype":"venue"
},
  "geometry": {"coordinates":[3.7416009903,51.0356674194],"type":"Point"}
}