{
  "type": "Feature",
  "properties": {
    "iso:country":"BE",
    "sg:address":"Chauss\u00e9e De La Hulpe 17a",
    "sg:city":"Bruxelles (uccle)",
    "sg:orig_category":"Non-Classified Establishments",
    "sg:phone":"+32 2 372 07 03",
    "sg:postcode":"1180",
    "sg:province":"Bruxelles-Capitale",
    "wof:name":"Select Form",
    "wof:placetype":"venue"
},
  "geometry": {"coordinates":[4.3769168854,50.7994041443],"type":"Point"}
}