{
  "type": "Feature",
  "properties": {
    "addr:full":"Diepestraat 38 Erpe-mere Oost-Vlaanderen 9420",
    "addr:housenumber":"38",
    "addr:postcode":"9420",
    "addr:street":"Diepestraat",
    "iso:country":"BE",
    "sg:address":"Diepestraat 38",
    "sg:city":"Erpe-mere",
    "sg:classifiers":[
        {
            "category":"Shopping",
            "subcategory":"Clothing, Apparel, & Fashions",
            "type":"Retail Goods"
        }
    ],
    "sg:phone":"+32 53 83 35 05",
    "sg:postcode":"9420",
    "sg:province":"Oost-Vlaanderen",
    "sg:tags":[
        "ondergoed",
        "lingerie"
    ],
    "wof:name":"Intimoda Engineering",
    "wof:placetype":"venue"
},
  "geometry": {"coordinates":[3.9685819149,50.9140357971],"type":"Point"}
}