{
  "type": "Feature",
  "properties": {
    "iso:country":"BE",
    "sg:address":"Maria-joannalaan 10",
    "sg:city":"Sint-genesius-rode/rhode-saint-gen\u00c8se",
    "sg:orig_category":"Architecten",
    "sg:phone":"+32 2 358 10 69",
    "sg:postcode":"1640",
    "sg:province":"Vlaams-Brabant",
    "wof:name":"F. Lenoble",
    "wof:placetype":"venue"
},
  "geometry": {"coordinates":[4.3930969238,50.7373962402],"type":"Point"}
}