{
  "type": "Feature",
  "properties": {
    "addr:full":"Rue Maria Thom\u00c9e 1 Ath Hainaut 7800",
    "addr:housenumber":"1",
    "addr:postcode":"7800",
    "addr:street":"Rue Maria Thome\u0301E",
    "iso:country":"BE",
    "sg:address":"Rue Maria Thom\u00c9e 1",
    "sg:city":"Ath",
    "sg:orig_category":"Artsen and specialisten",
    "sg:phone":"+32 68 26 26 26",
    "sg:postcode":"7800",
    "sg:province":"Hainaut",
    "wof:name":"Philippe Viseur",
    "wof:placetype":"venue"
},
  "geometry": {"coordinates":[3.7773780823,50.6344985962],"type":"Point"}
}