{
  "type": "Feature",
  "properties": {
    "iso:country":"BE",
    "sg:address":"Ringvaartstraat 38",
    "sg:city":"Merelbeke",
    "sg:orig_category":"Bloemen and planten",
    "sg:phone":"+32 9 230 62 58",
    "sg:postcode":"9820",
    "sg:province":"Oost-Vlaanderen",
    "wof:name":"R. Bondroit",
    "wof:placetype":"venue"
},
  "geometry": {"coordinates":[3.7561750412,51.0074501038],"type":"Point"}
}