{
  "type": "Feature",
  "properties": {
    "addr:full":"Rue Basse-wez 54 Li\u00c8ge Li\u00e8ge 4020",
    "addr:housenumber":"54",
    "addr:postcode":"4020",
    "addr:street":"Rue Basse-Wez",
    "iso:country":"BE",
    "sg:address":"Rue Basse-wez 54",
    "sg:city":"Li\u00c8ge",
    "sg:orig_category":"Enseignement maternel and primaire",
    "sg:phone":"+32 4 343 69 21",
    "sg:postcode":"4020",
    "sg:province":"Li\u00e8ge",
    "wof:name":"Ecole Fond. Communale",
    "wof:placetype":"venue"
},
  "geometry": {"coordinates":[5.5874128342,50.6361351013],"type":"Point"}
}