{
  "type": "Feature",
  "properties": {
    "iso:country":"BE",
    "sg:address":"Rue De La Molign\u00e9e 60",
    "sg:city":"Anh\u00e9e",
    "sg:classifiers":[
        {
            "category":"Manufacturing",
            "subcategory":"Metals",
            "type":"Manufacturing & Wholesale Goods"
        }
    ],
    "sg:phone":"+32 82 61 16 12",
    "sg:postcode":"5537",
    "sg:province":"Namur",
    "sg:tags":[
        "working"
    ],
    "wof:name":"Mecasoft Sa",
    "wof:placetype":"venue"
},
  "geometry": {"coordinates":[4.8516030312,50.3176269531],"type":"Point"}
}