{
  "type": "Feature",
  "properties": {
    "addr:full":"Schaagstraat 7 Anzegem West-Vlaanderen 8570",
    "addr:housenumber":"7",
    "addr:postcode":"8570",
    "addr:street":"Schaagstraat",
    "iso:country":"BE",
    "sg:address":"Schaagstraat 7",
    "sg:city":"Anzegem",
    "sg:orig_category":"Mat\u00e9riaux de construction Magasins sp\u00e9cialis\u00e9s. Rev\u00eatements pour sols and murs",
    "sg:phone":"+32 56 68 72 60",
    "sg:postcode":"8570",
    "sg:province":"West-Vlaanderen",
    "wof:name":"Jan Vancoppernolle",
    "wof:placetype":"venue"
},
  "geometry": {"coordinates":[3.4450819492,50.8498725891],"type":"Point"}
}