{
  "type": "Feature",
  "properties": {
    "addr:full":"Rue Ren\u00e9 Magritte 165 Lessines Hainaut 7860",
    "addr:housenumber":"165",
    "addr:postcode":"7860",
    "addr:street":"Rue Rene\u0301 Magritte;Hainaut",
    "iso:country":"BE",
    "sg:address":"Rue Ren\u00e9 Magritte 165",
    "sg:city":"Lessines",
    "sg:classifiers":[
        {
            "category":"Manufacturing",
            "subcategory":"Chemicals & Compounds",
            "type":"Manufacturing & Wholesale Goods"
        }
    ],
    "sg:phone":"+32 68 33 49 21",
    "sg:postcode":"7860",
    "sg:province":"Hainaut",
    "sg:tags":[
        "pharmaceutical",
        "chemistry",
        "-",
        "by-product"
    ],
    "wof:name":"Trenal Sa",
    "wof:placetype":"venue"
},
  "geometry": {"coordinates":[3.8405089378,50.7221221924],"type":"Point"}
}