{
  "type": "Feature",
  "properties": {
    "addr:full":"Marius Duch\u00c9straat 260 Vilvoorde Vlaams-Brabant 1800",
    "addr:housenumber":"260",
    "addr:postcode":"1800",
    "addr:street":"Duche\u0301Straat",
    "iso:country":"BE",
    "sg:address":"Marius Duch\u00c9straat 260",
    "sg:city":"Vilvoorde",
    "sg:orig_category":"Chemicali\u00ebn Gh",
    "sg:phone":"+32 2 255 62 11",
    "sg:postcode":"1800",
    "sg:province":"Vlaams-Brabant",
    "wof:name":"Tessenderlo Chemie",
    "wof:placetype":"venue"
},
  "geometry": {"coordinates":[4.4186000824,50.93542099],"type":"Point"}
}