{
  "type": "Feature",
  "properties": {
    "addr:full":"Osseghemstraat 53 Sint-jans-molenbeek/molenbeek-saint-jean Bruxelles-Capitale 1080",
    "addr:housenumber":"53",
    "addr:postcode":"1080",
    "addr:street":"Osseghemstraat",
    "iso:country":"BE",
    "sg:address":"Osseghemstraat 53",
    "sg:city":"Sint-jans-molenbeek/molenbeek-saint-jean",
    "sg:orig_category":"Huisdieren and benodigdheden",
    "sg:phone":"+32 2 412 25 27",
    "sg:postcode":"1080",
    "sg:province":"Bruxelles-Capitale",
    "wof:name":"Tom & Co",
    "wof:placetype":"venue"
},
  "geometry": {"coordinates":[4.3094248772,50.8540916443],"type":"Point"}
}