{
  "type": "Feature",
  "properties": {
    "iso:country":"BE",
    "sg:address":"F\u00e9ronstr\u00e9e 141",
    "sg:city":"Li\u00e8ge 1",
    "sg:classifiers":[
        {
            "category":"Professional",
            "subcategory":"Testing Lab",
            "type":"Services"
        }
    ],
    "sg:phone":"+32 4 222 05 54",
    "sg:postcode":"4000",
    "sg:province":"Li\u00e8ge",
    "sg:tags":[
        "chemist"
    ],
    "wof:name":"Saint-barth\u00e9l\u00e9my",
    "wof:placetype":"venue"
},
  "geometry": {"coordinates":[5.5833039284,50.6475028992],"type":"Point"}
}