{
  "type": "Feature",
  "properties": {
    "iso:country":"BE",
    "sg:address":"Rue Joseph Lef\u00e8vre 22",
    "sg:city":"Charleroi (marchienne-au-pont)",
    "sg:classifiers":[
        {
            "category":"Real Estate",
            "subcategory":"Real Estate Services",
            "type":"Services"
        }
    ],
    "sg:phone":"+32 71 56 26 61",
    "sg:postcode":"6030",
    "sg:province":"Hainaut",
    "sg:tags":[
        "-",
        "abroad"
    ],
    "wof:name":"Revazur",
    "wof:placetype":"venue"
},
  "geometry": {"coordinates":[4.3940491676,50.4037094116],"type":"Point"}
}