{
  "type": "Feature",
  "properties": {
    "iso:country":"BE",
    "sg:address":"Rue Mar\u00e9chal Foch 9",
    "sg:city":"Ch\u00e2telet (ch\u00e2telineau)",
    "sg:classifiers":[
        {
            "category":"Home & Garden",
            "subcategory":"Home Furnishings",
            "type":"Retail Goods"
        }
    ],
    "sg:phone":"+32 71 39 88 05",
    "sg:postcode":"6200",
    "sg:province":"Hainaut",
    "sg:tags":[
        "-",
        "furniture"
    ],
    "wof:name":"Pacha Mobella",
    "wof:placetype":"venue"
},
  "geometry": {"coordinates":[4.5186858177,50.4107971191],"type":"Point"}
}