{
  "type": "Feature",
  "properties": {
    "addr:full":"Hoveniersstr. 2 Antwerpen Antwerpen 2018",
    "addr:housenumber":"2",
    "addr:postcode":"2018",
    "addr:street":"Hoveniersstr.",
    "iso:country":"BE",
    "sg:address":"Hoveniersstr. 2",
    "sg:city":"Antwerpen",
    "sg:classifiers":[
        {
            "category":"Manufacturing",
            "subcategory":"Jewelry",
            "type":"Manufacturing & Wholesale Goods"
        }
    ],
    "sg:phone":"+32 3 233 65 59",
    "sg:postcode":"2018",
    "sg:province":"Antwerpen",
    "sg:tags":[
        "product",
        "miscellaneous",
        "jewellery"
    ],
    "wof:name":"Crisdiam Bvba",
    "wof:placetype":"venue"
},
  "geometry": {"coordinates":[4.418451786,51.2157592773],"type":"Point"}
}