{
  "type": "Feature",
  "properties": {
    "addr:full":"Rue Petit 5a Anh\u00e9e Namur 5537",
    "addr:housenumber":"5a",
    "addr:postcode":"5537",
    "addr:street":"Rue Petit",
    "iso:country":"BE",
    "sg:address":"Rue Petit 5a",
    "sg:city":"Anh\u00e9e",
    "sg:classifiers":[
        {
            "category":"Bars & Pubs",
            "type":"Food & Drink"
        }
    ],
    "sg:phone":"+32 82 61 32 89",
    "sg:postcode":"5537",
    "sg:province":"Namur",
    "sg:tags":[
        "tavern"
    ],
    "wof:name":"Mosan (taverne Le)",
    "wof:placetype":"venue"
},
  "geometry": {"coordinates":[4.8819060326,50.3102073669],"type":"Point"}
}