{
  "type": "Feature",
  "properties": {
    "iso:country":"BE",
    "sg:address":"Pater Vandemoerelaan 69-1",
    "sg:city":"De Haan (klemskerke)",
    "sg:classifiers":[
        {
            "category":"Home & Garden",
            "subcategory":"Carpets & Floor Coverings",
            "type":"Retail Goods"
        }
    ],
    "sg:phone":"+32 59 23 61 66",
    "sg:postcode":"8420",
    "sg:province":"West-Vlaanderen",
    "sg:tags":[
        "layer",
        "mosaicists"
    ],
    "wof:name":"Lameire N",
    "wof:placetype":"venue"
},
  "geometry": {"coordinates":[3.0320138931,51.267665863],"type":"Point"}
}