{
  "type": "Feature",
  "properties": {
    "addr:full":"Rue Du Blanc Pain 60 La Louvi\u00e8re (houdeng-goegnies) Hainaut 7110",
    "addr:housenumber":"60",
    "addr:postcode":"7110",
    "addr:street":"Rue Du Blanc Pain",
    "iso:country":"BE",
    "sg:address":"Rue Du Blanc Pain 60",
    "sg:city":"La Louvi\u00e8re (houdeng-goegnies)",
    "sg:classifiers":[
        {
            "category":"Manufacturing",
            "subcategory":"Tools & Machinery",
            "type":"Manufacturing & Wholesale Goods"
        }
    ],
    "sg:phone":"+32 64 22 41 80",
    "sg:postcode":"7110",
    "sg:province":"Hainaut",
    "sg:tags":[
        "builder"
    ],
    "wof:name":"Michel Fres Sa",
    "wof:placetype":"venue"
},
  "geometry": {"coordinates":[4.1505050659,50.4826698303],"type":"Point"}
}