{
  "type": "Feature",
  "properties": {
    "addr:full":"Bredestraat 26 Antwerpen Antwerpen 2000",
    "addr:housenumber":"26",
    "addr:postcode":"2000",
    "addr:street":"Bredestraat",
    "iso:country":"BE",
    "sg:address":"Bredestraat 26",
    "sg:city":"Antwerpen",
    "sg:orig_category":"Pharmaciens",
    "sg:phone":"+32 3 232 60 21",
    "sg:postcode":"2000",
    "sg:province":"Antwerpen",
    "wof:name":"Christine Filliers",
    "wof:placetype":"venue"
},
  "geometry": {"coordinates":[4.4019169807,51.2146263123],"type":"Point"}
}