{
  "type": "Feature",
  "properties": {
    "addr:full":"Papdijk 3 Moerbeke Oost-Vlaanderen 9180",
    "addr:housenumber":"3",
    "addr:postcode":"9180",
    "addr:street":"Papdijk",
    "iso:country":"BE",
    "sg:address":"Papdijk 3",
    "sg:city":"Moerbeke",
    "sg:orig_category":"Machines and mat\u00e9riel agricoles Eleveurs de bovins",
    "sg:phone":"+32 9 346 81 93",
    "sg:postcode":"9180",
    "sg:province":"Oost-Vlaanderen",
    "wof:name":"Roger De Keyser",
    "wof:placetype":"venue"
},
  "geometry": {"coordinates":[3.9247839451,51.201965332],"type":"Point"}
}