{
  "type": "Feature",
  "properties": {
    "iso:country":"BE",
    "sg:address":"Rue Hubert Halet 74",
    "sg:city":"Pepinster",
    "sg:classifiers":[
        {
            "category":"Retail",
            "subcategory":"Driving School",
            "type":"Services"
        }
    ],
    "sg:phone":"+32 87 37 68 80",
    "sg:postcode":"4860",
    "sg:province":"Li\u00e8ge",
    "sg:tags":[
        "automobile",
        "officially",
        "-",
        "recognized"
    ],
    "wof:name":"A.b.c. Auto Moto Ecole Sc",
    "wof:placetype":"venue"
},
  "geometry": {"coordinates":[5.8042068481,50.5698242188],"type":"Point"}
}