{
  "type": "Feature",
  "properties": {
    "iso:country":"BE",
    "sg:address":"Heysellaan 48",
    "sg:city":"Vilvoorde",
    "sg:classifiers":[
        {
            "category":"Manufacturing",
            "subcategory":"Food",
            "type":"Manufacturing & Wholesale Goods"
        }
    ],
    "sg:phone":"+32 2 267 75 48",
    "sg:postcode":"1800",
    "sg:province":"Vlaams-Brabant",
    "sg:tags":[
        "industry",
        "-",
        "ingredient"
    ],
    "wof:name":"Lievens International-lievamex Nv",
    "wof:placetype":"venue"
},
  "geometry": {"coordinates":[4.3713188171,50.901008606],"type":"Point"}
}