{
  "type": "Feature",
  "properties": {
    "iso:country":"BE",
    "sg:address":"Lostraat 1",
    "sg:city":"Machelen",
    "sg:classifiers":[
        {
            "category":"Cafe",
            "type":"Food & Drink"
        }
    ],
    "sg:phone":"+32 2 720 59 63",
    "sg:postcode":"1831",
    "sg:province":"Vlaams-Brabant",
    "sg:tags":[
        "caf\u00e9s"
    ],
    "wof:name":"Caf\u00c9 Diegem Lo",
    "wof:placetype":"venue"
},
  "geometry": {"coordinates":[4.4539170265,50.895072937],"type":"Point"}
}