{
  "type": "Feature",
  "properties": {
    "addr:full":"Avenue Des D\u00e9port\u00e9s 106 Fontaine-l'ev\u00eaque Hainaut 6140",
    "addr:housenumber":"106",
    "addr:postcode":"6140",
    "addr:street":"Avenue Des De\u0301Porte\u0301S;\u0302Que Hainaut",
    "iso:country":"BE",
    "sg:address":"Avenue Des D\u00e9port\u00e9s 106",
    "sg:city":"Fontaine-l'ev\u00eaque",
    "sg:classifiers":[
        {
            "category":"Building & Trades",
            "subcategory":"Construction",
            "type":"Services"
        }
    ],
    "sg:phone":"+32 71 51 31 71",
    "sg:postcode":"6140",
    "sg:province":"Hainaut",
    "sg:tags":[
        "work",
        "waterproofing"
    ],
    "wof:name":"Isotra Sprl",
    "wof:placetype":"venue"
},
  "geometry": {"coordinates":[-111.9644622803,46.2507972717],"type":"Point"}
}