{
  "type": "Feature",
  "properties": {
    "iso:country":"BE",
    "sg:address":"Henri Farmanstraat 2",
    "sg:city":"Gent",
    "sg:orig_category":"Goederenvervoer over de weg",
    "sg:phone":"+32 9 232 50 79",
    "sg:postcode":"9000",
    "sg:province":"Oost-Vlaanderen",
    "wof:name":"Bel - Cargo",
    "wof:placetype":"venue"
},
  "geometry": {"coordinates":[3.7458980083,51.0778770447],"type":"Point"}
}