{
  "type": "Feature",
  "properties": {
    "iso:country":"BE",
    "sg:address":"De Libottonstraat 16",
    "sg:city":"Hasselt (stevoort)",
    "sg:classifiers":[
        {
            "category":"Banks & Credit Unions",
            "subcategory":"Investment Brokerage",
            "type":"Services"
        }
    ],
    "sg:phone":"+32 11 59 14 26",
    "sg:postcode":"3512",
    "sg:province":"Limburg",
    "sg:tags":[
        "repair",
        "-",
        "installation",
        "sanitary",
        "article"
    ],
    "wof:name":"Liesens P",
    "wof:placetype":"venue"
},
  "geometry": {"coordinates":[5.2575440407,50.9201622009],"type":"Point"}
}