{
  "type": "Feature",
  "properties": {
    "iso:country":"BE",
    "sg:address":"Rue L\u00c9opold Dupuis 25",
    "sg:city":"La Louviere",
    "sg:orig_category":"Alternatieve geneeskunde Artsen and specialisten",
    "sg:phone":"+32 64 22 65 48",
    "sg:postcode":"7100",
    "sg:province":"Hainaut",
    "wof:name":"Jean Sohier",
    "wof:placetype":"venue"
},
  "geometry": {"coordinates":[4.1940732002,50.4728317261],"type":"Point"}
}