{
  "type": "Feature",
  "properties": {
    "iso:country":"BE",
    "sg:address":"Stationsstraat 87",
    "sg:city":"Erpe-mere",
    "sg:orig_category":"Kapsalons",
    "sg:phone":"+32 53 62 89 98",
    "sg:postcode":"9420",
    "sg:province":"Oost-Vlaanderen",
    "wof:name":"Coiffure Elsie",
    "wof:placetype":"venue"
},
  "geometry": {"coordinates":[3.9272799492,50.8992805481],"type":"Point"}
}