{
  "type": "Feature",
  "properties": {
    "addr:full":"Rue Wilmus 56 Courcelles Hainaut 6180",
    "addr:housenumber":"56",
    "addr:postcode":"6180",
    "addr:street":"Rue Wilmus",
    "iso:country":"BE",
    "sg:address":"Rue Wilmus 56",
    "sg:city":"Courcelles",
    "sg:classifiers":[
        {
            "category":"Building & Trades",
            "subcategory":"Electrical",
            "type":"Services"
        }
    ],
    "sg:phone":"+32 71 45 48 70",
    "sg:postcode":"6180",
    "sg:province":"Hainaut",
    "sg:tags":[
        "-",
        "electric",
        "contractor"
    ],
    "wof:name":"Hubeau & Fils Scrl",
    "wof:placetype":"venue"
},
  "geometry": {"coordinates":[4.3898792267,50.467300415],"type":"Point"}
}