{
  "type": "Feature",
  "properties": {
    "addr:full":"Georges Henrilaan 325 Sint-lambrechts-woluwe/woluwe-saint-lambert Bruxelles-Capitale 1200",
    "addr:housenumber":"325",
    "addr:postcode":"1200",
    "addr:street":"Henrilaan",
    "iso:country":"BE",
    "sg:address":"Georges Henrilaan 325",
    "sg:city":"Sint-lambrechts-woluwe/woluwe-saint-lambert",
    "sg:orig_category":"Brood, gebak and snoepgoed",
    "sg:phone":"+32 2 734 34 69",
    "sg:postcode":"1200",
    "sg:province":"Bruxelles-Capitale",
    "wof:name":"La Bastogne",
    "wof:placetype":"venue"
},
  "geometry": {"coordinates":[4.4105901718,50.8432617188],"type":"Point"}
}