{
  "type": "Feature",
  "properties": {
    "iso:country":"BE",
    "sg:address":"Stalenstraat 74b78",
    "sg:city":"Genk",
    "sg:orig_category":"Warenhuizen",
    "sg:phone":"+32 89 38 18 66",
    "sg:postcode":"3600",
    "sg:province":"Limburg",
    "wof:name":"Strabuco",
    "wof:placetype":"venue"
},
  "geometry": {"coordinates":[5.5185499191,50.9935188293],"type":"Point"}
}