{
  "type": "Feature",
  "properties": {
    "iso:country":"BE",
    "sg:address":"Grand'rue 209",
    "sg:city":"Trooz",
    "sg:classifiers":[
        {
            "category":"Personal",
            "subcategory":"Beauty Salon",
            "type":"Services"
        }
    ],
    "sg:phone":"+32 4 351 63 89",
    "sg:postcode":"4870",
    "sg:province":"Li\u00e8ge",
    "sg:tags":[
        "de",
        "coiffure"
    ],
    "wof:name":"Coiffure Art Et Beaut\u00c9",
    "wof:placetype":"venue"
},
  "geometry": {"coordinates":[5.6895260811,50.5719566345],"type":"Point"}
}