{
  "type": "Feature",
  "properties": {
    "iso:country":"BE",
    "sg:address":"Halensebaan 67",
    "sg:city":"Kortenaken",
    "sg:classifiers":[
        {
            "category":"Cafe",
            "type":"Food & Drink"
        }
    ],
    "sg:phone":"+32 16 77 77 07",
    "sg:postcode":"3473",
    "sg:province":"Vlaams-Brabant",
    "sg:tags":[
        "caf\u00e9s"
    ],
    "wof:name":"Jules Das",
    "wof:placetype":"venue"
},
  "geometry": {"coordinates":[4.9906601906,50.9205589294],"type":"Point"}
}