{
  "type": "Feature",
  "properties": {
    "addr:full":"Camp Romain 20 Wavre Brabant Wallon 1300",
    "addr:housenumber":"20;1300",
    "iso:country":"BE",
    "sg:address":"Camp Romain 20",
    "sg:city":"Wavre",
    "sg:orig_category":"Elektrische installaties voor woningen",
    "sg:phone":"+32 10 45 77 64",
    "sg:postcode":"1300",
    "sg:province":"Brabant Wallon",
    "wof:name":"Caupilec",
    "wof:placetype":"venue"
},
  "geometry": {"coordinates":[4.6125359535,50.727771759],"type":"Point"}
}