{
  "type": "Feature",
  "properties": {
    "addr:full":"Place Pierre De Coubertin 2 Ottignies-louvain-la-neuve (louvain-la-neuve) Brabant Wallon 1348",
    "addr:housenumber":"2",
    "addr:postcode":"1348",
    "addr:street":"Place Pierre De Coubertin",
    "iso:country":"BE",
    "sg:address":"Place Pierre De Coubertin 2",
    "sg:city":"Ottignies-louvain-la-neuve (louvain-la-neuve)",
    "sg:classifiers":[
        {
            "category":"Education",
            "subcategory":"University",
            "type":"Public Place"
        }
    ],
    "sg:phone":"+32 10 45 11 08",
    "sg:postcode":"1348",
    "sg:province":"Brabant Wallon",
    "sg:tags":[
        "higher"
    ],
    "wof:name":"Institut Superieur Europeen Charles Peguy De Tourisme Gestion Hoteliere & Creation D'ev\u00e9nements",
    "wof:placetype":"venue"
},
  "geometry": {"coordinates":[4.6066298485,50.670715332],"type":"Point"}
}