{
  "type": "Feature",
  "properties": {
    "addr:full":"Rue Des Palais 10 Bruxelles (schaerbeek) Bruxelles-Capitale 1030",
    "addr:housenumber":"10",
    "addr:postcode":"1030",
    "addr:street":"Rue Des Palais",
    "iso:country":"BE",
    "sg:address":"Rue Des Palais 10",
    "sg:city":"Bruxelles (schaerbeek)",
    "sg:classifiers":[
        {
            "category":"Community Center",
            "type":"Public Place"
        }
    ],
    "sg:phone":"+32 2 218 28 42",
    "sg:postcode":"1030",
    "sg:province":"Bruxelles-Capitale",
    "sg:tags":[
        "medical"
    ],
    "wof:name":"Maison M\u00e9dicale Du Nord Asbl",
    "wof:placetype":"venue"
},
  "geometry": {"coordinates":[4.3680720329,50.8588371277],"type":"Point"}
}