{
  "type": "Feature",
  "properties": {
    "iso:country":"BE",
    "sg:address":"Plantijstraat 10",
    "sg:city":"Oostende",
    "sg:orig_category":"Installatie van houten of kunststof schrijnwerk",
    "sg:phone":"+32 59 50 10 35",
    "sg:postcode":"8400",
    "sg:province":"West-Vlaanderen",
    "wof:name":"Vandaele",
    "wof:placetype":"venue"
},
  "geometry": {"coordinates":[2.9402089119,51.2127456665],"type":"Point"}
}