{
  "type": "Feature",
  "properties": {
    "iso:country":"BE",
    "sg:address":"Rue De L\u00b4institut 47",
    "sg:city":"Chiny",
    "sg:orig_category":"Enseignement secondaire technique and professionnel. Enseignement secondaire g\u00e9n\u00e9ral",
    "sg:phone":"+32 61 31 24 55",
    "sg:postcode":"6810",
    "sg:province":"Luxembourg",
    "wof:name":"Ath\u00c9n\u00c9e Royal Gilson",
    "wof:placetype":"venue"
},
  "geometry": {"coordinates":[5.3405580521,49.7382736206],"type":"Point"}
}