{
  "type": "Feature",
  "properties": {
    "addr:full":"Baraplein 18b2 Anderlecht Bruxelles-Capitale 1070",
    "addr:housenumber":"18b2",
    "addr:postcode":"1070",
    "addr:street":"Baraplein",
    "iso:country":"BE",
    "sg:address":"Baraplein 18b2",
    "sg:city":"Anderlecht",
    "sg:orig_category":"Boekhouders",
    "sg:phone":"+32 2 520 88 04",
    "sg:postcode":"1070",
    "sg:province":"Bruxelles-Capitale",
    "wof:name":"Pierre Lema Kamangu",
    "wof:placetype":"venue"
},
  "geometry": {"coordinates":[4.3349289894,50.8382606506],"type":"Point"}
}