{
  "type": "Feature",
  "properties": {
    "iso:country":"BE",
    "sg:address":"Kotseheide 2",
    "sg:city":"Schilde",
    "sg:orig_category":"Huisdierenkwekers",
    "sg:phone":"+32 3 385 00 38",
    "sg:postcode":"2970",
    "sg:province":"Antwerpen",
    "wof:name":"Wendevick Border Collies",
    "wof:placetype":"venue"
},
  "geometry": {"coordinates":[4.6266031265,51.2863121033],"type":"Point"}
}