{
  "type": "Feature",
  "properties": {
    "iso:country":"BE",
    "sg:address":"Belgi\u00cblei 23",
    "sg:city":"Antwerpen",
    "sg:classifiers":[
        {
            "category":"Shopping",
            "subcategory":"Clothing, Apparel, & Fashions",
            "type":"Retail Goods"
        }
    ],
    "sg:phone":"+32 3 230 11 75",
    "sg:postcode":"2018",
    "sg:province":"Antwerpen",
    "sg:tags":[
        "v\u00eatements",
        "pour",
        "dame"
    ],
    "wof:name":"Modissa",
    "wof:placetype":"venue"
},
  "geometry": {"coordinates":[4.422039032,51.2082366943],"type":"Point"}
}