{
  "type": "Feature",
  "properties": {
    "iso:country":"BE",
    "sg:address":"Longchamps 612",
    "sg:city":"Bertogne (longchamps)",
    "sg:classifiers":[
        {
            "category":"Building & Trades",
            "subcategory":"Landscaping Services",
            "type":"Services"
        }
    ],
    "sg:phone":"+32 61 21 83 72",
    "sg:postcode":"6688",
    "sg:province":"Luxembourg",
    "sg:tags":[
        "forestry"
    ],
    "wof:name":"De Lie S",
    "wof:placetype":"venue"
},
  "geometry": {"coordinates":[5.689948082,50.0525741577],"type":"Point"}
}