{
  "type": "Feature",
  "properties": {
    "iso:country":"BE",
    "sg:address":"Rue Bl\u00c9gissart 4",
    "sg:city":"Ham-sur-heure-nalinnes",
    "sg:classifiers":[
        {
            "category":"Personal",
            "subcategory":"Beauty Salon",
            "type":"Services"
        }
    ],
    "sg:phone":"+32 71 21 49 29",
    "sg:postcode":"6120",
    "sg:province":"Hainaut",
    "sg:tags":[
        "de",
        "coiffure"
    ],
    "wof:name":"Coiffure Style",
    "wof:placetype":"venue"
},
  "geometry": {"coordinates":[4.4422721863,50.3403625488],"type":"Point"}
}