{
  "type": "Feature",
  "properties": {
    "iso:country":"BE",
    "sg:address":"Bredestraat 128",
    "sg:city":"Gent",
    "sg:orig_category":"Afbraak- and draineerwerken HUISBRANDOLIE Huisvuilophaling and -verwerking",
    "sg:phone":"+32 9 251 07 67",
    "sg:postcode":"9041",
    "sg:province":"Oost-Vlaanderen",
    "wof:name":"Praet En Co",
    "wof:placetype":"venue"
},
  "geometry": {"coordinates":[3.7735540867,51.1030082703],"type":"Point"}
}