{
  "type": "Feature",
  "properties": {
    "addr:full":"Rue De La Maladrerie 2 Chiny Luxembourg 6810",
    "addr:housenumber":"2",
    "addr:postcode":"6810",
    "addr:street":"Rue De La Maladrerie",
    "iso:country":"BE",
    "sg:address":"Rue De La Maladrerie 2",
    "sg:city":"Chiny",
    "sg:classifiers":[
        {
            "category":"Insurance",
            "subcategory":"Life Insurance",
            "type":"Services"
        }
    ],
    "sg:phone":"+32 61 32 91 04",
    "sg:postcode":"6810",
    "sg:province":"Luxembourg",
    "sg:tags":[
        "assurance"
    ],
    "wof:name":"B.m.c.",
    "wof:placetype":"venue"
},
  "geometry": {"coordinates":[5.3405580521,49.7382736206],"type":"Point"}
}