{
  "type": "Feature",
  "properties": {
    "addr:full":"Hasseltsesteenweg 75 Tongeren Limburg 3700",
    "addr:housenumber":"75",
    "addr:postcode":"3700",
    "addr:street":"Hasseltsesteenweg",
    "iso:country":"BE",
    "sg:address":"Hasseltsesteenweg 75",
    "sg:city":"Tongeren",
    "sg:classifiers":[
        {
            "category":"Home & Garden",
            "subcategory":"Home Furnishings",
            "type":"Retail Goods"
        }
    ],
    "sg:phone":"+32 12 23 17 53",
    "sg:postcode":"3700",
    "sg:province":"Limburg",
    "sg:tags":[
        "-",
        "furniture"
    ],
    "wof:name":"Lama Bvba",
    "wof:placetype":"venue"
},
  "geometry": {"coordinates":[5.4570560455,50.7836647034],"type":"Point"}
}