{
  "type": "Feature",
  "properties": {
    "addr:full":"Place Du March\u00e9 32 Saint-hubert Luxembourg 6870",
    "addr:housenumber":"32",
    "addr:postcode":"6870",
    "addr:street":"Place Du Marche\u0301",
    "iso:country":"BE",
    "sg:address":"Place Du March\u00e9 32",
    "sg:city":"Saint-hubert",
    "sg:classifiers":[
        {
            "category":"Bars & Pubs",
            "type":"Food & Drink"
        }
    ],
    "sg:phone":"+32 61 61 12 25",
    "sg:postcode":"6870",
    "sg:province":"Luxembourg",
    "wof:name":"Rimbaud (le)",
    "wof:placetype":"venue"
},
  "geometry": {"coordinates":[5.3735728264,50.0255355835],"type":"Point"}
}