{
  "type": "Feature",
  "properties": {
    "iso:country":"BE",
    "sg:address":"Kiekenhaag 33",
    "sg:city":"Stekene",
    "sg:classifiers":[
        {
            "category":"Professional",
            "subcategory":"Accounting & Tax Preparation",
            "type":"Services"
        }
    ],
    "sg:phone":"+32 3 779 45 70",
    "sg:postcode":"9190",
    "sg:province":"Oost-Vlaanderen",
    "sg:tags":[
        "bookkeeper"
    ],
    "wof:name":"Cleyman J",
    "wof:placetype":"venue"
},
  "geometry": {"coordinates":[4.0404801369,51.2195777893],"type":"Point"}
}