{
  "type": "Feature",
  "properties": {
    "addr:full":"Koning Albertplein 12 De Panne West-Vlaanderen 8660",
    "addr:housenumber":"12",
    "addr:postcode":"8660",
    "addr:street":"Koning Albertplein",
    "iso:country":"BE",
    "sg:address":"Koning Albertplein 12",
    "sg:city":"De Panne",
    "sg:classifiers":[
        {
            "category":"Real Estate",
            "subcategory":"Real Estate Services",
            "type":"Services"
        }
    ],
    "sg:phone":"+32 58 41 20 60",
    "sg:postcode":"8660",
    "sg:province":"West-Vlaanderen",
    "sg:tags":[
        "boarding",
        "house"
    ],
    "wof:name":"Chalet Du Chien Vert",
    "wof:placetype":"venue"
},
  "geometry": {"coordinates":[2.5898549557,51.1018600464],"type":"Point"}
}