{
  "type": "Feature",
  "properties": {
    "addr:full":"Vuurkruisersstraat 39 Maasmechelen Limburg 3630",
    "addr:housenumber":"39",
    "addr:postcode":"3630",
    "addr:street":"Vuurkruisersstraat",
    "iso:country":"BE",
    "sg:address":"Vuurkruisersstraat 39",
    "sg:city":"Maasmechelen",
    "sg:orig_category":"Sportclubs",
    "sg:phone":"+32 89 76 32 99",
    "sg:postcode":"3630",
    "sg:province":"Limburg",
    "wof:name":"B.c. Maaskant",
    "wof:placetype":"venue"
},
  "geometry": {"coordinates":[5.6814799309,50.9625434875],"type":"Point"}
}