{
  "type": "Feature",
  "properties": {
    "addr:full":"Maison Du Bois Battice Li\u00e8ge 4651",
    "addr:postcode":"4651",
    "addr:street":"Du Bois",
    "iso:country":"BE",
    "sg:address":"Maison Du Bois",
    "sg:city":"Battice",
    "sg:classifiers":[
        {
            "category":"Restaurant",
            "type":"Food & Drink"
        }
    ],
    "sg:phone":"+32 87 67 49 19",
    "sg:postcode":"4651",
    "sg:province":"Li\u00e8ge",
    "wof:name":"Aux Etangs De La Vielle Ferme",
    "wof:placetype":"venue"
},
  "geometry": {"coordinates":[5.7809391022,50.6203575134],"type":"Point"}
}