{
  "type": "Feature",
  "properties": {
    "iso:country":"BE",
    "sg:address":"Rue De L\u00b4industrie 20",
    "sg:city":"Manage",
    "sg:orig_category":"Kinderopvang",
    "sg:phone":"+32 64 26 00 75",
    "sg:postcode":"7170",
    "sg:province":"Hainaut",
    "wof:name":"Les Pitchounets",
    "wof:placetype":"venue"
},
  "geometry": {"coordinates":[4.225880146,50.4775352478],"type":"Point"}
}