{
  "type": "Feature",
  "properties": {
    "addr:full":"'t Kloosterhof 59 Brugge (sint-michiels) West-Vlaanderen 8200",
    "addr:housenumber":"59",
    "addr:postcode":"8200",
    "addr:street":"' T Kloosterhof",
    "iso:country":"BE",
    "sg:address":"'t Kloosterhof 59",
    "sg:city":"Brugge (sint-michiels)",
    "sg:classifiers":[
        {
            "category":"Home & Garden",
            "subcategory":"Carpets & Floor Coverings",
            "type":"Retail Goods"
        }
    ],
    "sg:phone":"+32 50 39 00 57",
    "sg:postcode":"8200",
    "sg:province":"West-Vlaanderen",
    "sg:tags":[
        "-"
    ],
    "wof:name":"Devogelaere P",
    "wof:placetype":"venue"
},
  "geometry": {"coordinates":[3.2243320942,51.1762504578],"type":"Point"}
}