{
  "type": "Feature",
  "properties": {
    "iso:country":"BE",
    "sg:address":"Chauss\u00e9e De Valenciennes 58a",
    "sg:city":"Ath (irchonwelz)",
    "sg:classifiers":[
        {
            "category":"Professional",
            "subcategory":"Accounting & Tax Preparation",
            "type":"Services"
        }
    ],
    "sg:phone":"+32 68 28 63 44",
    "sg:postcode":"7801",
    "sg:province":"Hainaut",
    "sg:tags":[
        "bookkeeper"
    ],
    "wof:name":"Compta Services Sa",
    "wof:placetype":"venue"
},
  "geometry": {"coordinates":[3.7621150017,50.6197013855],"type":"Point"}
}