{
  "type": "Feature",
  "properties": {
    "iso:country":"BE",
    "sg:address":"Rue Grande 39",
    "sg:city":"Saint-ghislain",
    "sg:classifiers":[
        {
            "category":"Shopping",
            "subcategory":"Crafts & Fabrics",
            "type":"Retail Goods"
        }
    ],
    "sg:phone":"+32 65 78 40 17",
    "sg:postcode":"7330",
    "sg:province":"Hainaut",
    "sg:tags":[
        "graphic",
        "art",
        "supply",
        "-",
        "painting",
        "drawing"
    ],
    "wof:name":"Crayons",
    "wof:placetype":"venue"
},
  "geometry": {"coordinates":[3.8204340935,50.446105957],"type":"Point"}
}