{
  "type": "Feature",
  "properties": {
    "iso:country":"BE",
    "sg:address":"Markt 41",
    "sg:city":"Deinze",
    "sg:orig_category":"Herstelling and restauratie van meubelen Textiel Verlichting and huishoudartikelen",
    "sg:phone":"+32 9 386 33 04",
    "sg:postcode":"9800",
    "sg:province":"Oost-Vlaanderen",
    "wof:name":"Modecoupon",
    "wof:placetype":"venue"
},
  "geometry": {"coordinates":[3.5267050266,50.9849281311],"type":"Point"}
}