{
  "type": "Feature",
  "properties": {
    "addr:full":"Dr\u00c8ve Du S\u00c9n\u00c9chal 46 Ukkel/uccle Bruxelles-Capitale 1180",
    "addr:housenumber":"46",
    "addr:postcode":"1180",
    "addr:street":"Dre\u0300Ve Du Se\u0301Ne\u0301Chal;/",
    "iso:country":"BE",
    "sg:address":"Dr\u00c8ve Du S\u00c9n\u00c9chal 46",
    "sg:city":"Ukkel/uccle",
    "sg:orig_category":"Kinderopvang",
    "sg:phone":"+32 2 374 04 10",
    "sg:postcode":"1180",
    "sg:province":"Bruxelles-Capitale",
    "wof:name":"La F\u00c9e Clochette",
    "wof:placetype":"venue"
},
  "geometry": {"coordinates":[4.3753628731,50.7950325012],"type":"Point"}
}