{
  "type": "Feature",
  "properties": {
    "addr:full":"Rue De F\u00c9tinne 64 Li\u00c8ge Li\u00e8ge 4020",
    "addr:housenumber":"64",
    "addr:postcode":"4020",
    "addr:street":"Rue De Fe\u0301Tinne",
    "iso:country":"BE",
    "sg:address":"Rue De F\u00c9tinne 64",
    "sg:city":"Li\u00c8ge",
    "sg:orig_category":"Herstellingen and onderhoud van auto's",
    "sg:phone":"+32 4 342 55 75",
    "sg:postcode":"4020",
    "sg:province":"Li\u00e8ge",
    "wof:name":"Pierre Dorthu",
    "wof:placetype":"venue"
},
  "geometry": {"coordinates":[5.5820817947,50.6259002686],"type":"Point"}
}