{
  "type": "Feature",
  "properties": {
    "iso:country":"BE",
    "sg:address":"Place De Petit Rechain 21",
    "sg:city":"Verviers (petit-rechain)",
    "sg:classifiers":[
        {
            "category":"Professional",
            "subcategory":"Testing Lab",
            "type":"Services"
        }
    ],
    "sg:phone":"+32 87 33 32 69",
    "sg:postcode":"4800",
    "sg:province":"Li\u00e8ge",
    "sg:tags":[
        "chemist"
    ],
    "wof:name":"Classen A",
    "wof:placetype":"venue"
},
  "geometry": {"coordinates":[5.8330078125,50.6131477356],"type":"Point"}
}