{
  "type": "Feature",
  "properties": {
    "iso:country":"BE",
    "sg:address":"Biezenlaan 56",
    "sg:city":"Vorst/forest",
    "sg:orig_category":"Paramedische behandelingen",
    "sg:phone":"+32 2 376 54 07",
    "sg:postcode":"1190",
    "sg:province":"Bruxelles-Capitale",
    "wof:name":"M.p. Denis",
    "wof:placetype":"venue"
},
  "geometry": {"coordinates":[4.3246917725,50.805065155],"type":"Point"}
}