{
  "type": "Feature",
  "properties": {
    "iso:country":"BE",
    "sg:address":"Avenue Du Roi Albert 671",
    "sg:city":"Mons",
    "sg:orig_category":"Voedingsspeciaalzaken",
    "sg:phone":"+32 65 82 26 25",
    "sg:postcode":"7012",
    "sg:province":"Hainaut",
    "wof:name":"Hong Kong Express",
    "wof:placetype":"venue"
},
  "geometry": {"coordinates":[3.8894600868,50.4481964111],"type":"Point"}
}