{
  "type": "Feature",
  "properties": {
    "addr:full":"Chemin Du Gros Tienne 1 Lasne Brabant Wallon 1380",
    "addr:housenumber":"1",
    "addr:postcode":"1380",
    "addr:street":"Chemin Du Gros Tienne",
    "iso:country":"BE",
    "sg:address":"Chemin Du Gros Tienne 1",
    "sg:city":"Lasne",
    "sg:classifiers":[
        {
            "category":"Fast Food",
            "type":"Food & Drink"
        }
    ],
    "sg:phone":"+32 2 653 02 19",
    "sg:postcode":"1380",
    "sg:province":"Brabant Wallon",
    "sg:tags":[
        "meeneem",
        "restaurant"
    ],
    "wof:name":"La Nouvelle Orleans",
    "wof:placetype":"venue"
},
  "geometry": {"coordinates":[4.4875087738,50.7135047913],"type":"Point"}
}