{
  "type": "Feature",
  "properties": {
    "iso:country":"BE",
    "sg:address":"Avenue De Messidor 200",
    "sg:city":"Ukkel/uccle",
    "sg:orig_category":"Evaluation and estimation de biens immobiliers",
    "sg:phone":"+32 2 347 27 23",
    "sg:postcode":"1180",
    "sg:province":"Bruxelles-Capitale",
    "wof:name":"Van Raemdonck & Vennoten/van Raemdonck & Associes",
    "wof:placetype":"venue"
},
  "geometry": {"coordinates":[4.3486289978,50.8108024597],"type":"Point"}
}