{
  "type": "Feature",
  "properties": {
    "iso:country":"BE",
    "sg:address":"Ti\u00e8ge 4",
    "sg:city":"Jalhay (sart)",
    "sg:classifiers":[
        {
            "category":"Professional",
            "subcategory":"Accounting & Tax Preparation",
            "type":"Services"
        }
    ],
    "sg:phone":"+32 87 47 45 39",
    "sg:postcode":"4845",
    "sg:province":"Li\u00e8ge",
    "sg:tags":[
        "bookkeeper"
    ],
    "wof:name":"Mairlot J",
    "wof:placetype":"venue"
},
  "geometry": {"coordinates":[5.9181761742,50.5166778564],"type":"Point"}
}