{
  "type": "Feature",
  "properties": {
    "addr:full":"Avenue Astrid 2 Gerpinnes Hainaut 6280",
    "addr:housenumber":"2",
    "addr:postcode":"6280",
    "addr:street":"Avenue Astrid;Hainaut",
    "iso:country":"BE",
    "sg:address":"Avenue Astrid 2",
    "sg:city":"Gerpinnes",
    "sg:orig_category":"Assurances. Bureaux de poste",
    "sg:phone":"+32 71 50 10 07",
    "sg:postcode":"6280",
    "sg:province":"Hainaut",
    "wof:name":"La Poste",
    "wof:placetype":"venue"
},
  "geometry": {"coordinates":[4.5274090767,50.3373832703],"type":"Point"}
}