{
  "type": "Feature",
  "properties": {
    "addr:full":"Fr Rooseveltpl 18 Ronse Oost-Vlaanderen 9600",
    "addr:housenumber":"18",
    "addr:postcode":"9600",
    "iso:country":"BE",
    "sg:address":"Fr Rooseveltpl 18",
    "sg:city":"Ronse",
    "sg:classifiers":[
        {
            "category":"Banks & Credit Unions",
            "subcategory":"Bank",
            "type":"Services"
        }
    ],
    "sg:phone":"+32 55 21 45 75",
    "sg:postcode":"9600",
    "sg:province":"Oost-Vlaanderen",
    "wof:name":"Aslk-cger Bank",
    "wof:placetype":"venue"
},
  "geometry": {"coordinates":[3.5994179249,50.7464485168],"type":"Point"}
}