{
  "type": "Feature",
  "properties": {
    "iso:country":"BE",
    "sg:address":"Vaartstraat 1",
    "sg:city":"Oudenburg",
    "sg:orig_category":"Equipements pour la construction D\u00e9molition d\u00b4immeubles and terrassements. Construction de rev\u00eatemen",
    "sg:phone":"+32 59 26 67 74",
    "sg:postcode":"8460",
    "sg:province":"West-Vlaanderen",
    "wof:name":"Verhelst Aannemingen",
    "wof:placetype":"venue"
},
  "geometry": {"coordinates":[3.0013999939,51.1908340454],"type":"Point"}
}