{
  "type": "Feature",
  "properties": {
    "iso:country":"BE",
    "sg:address":"Heuvel 37a",
    "sg:city":"Putte",
    "sg:classifiers":[
        {
            "category":"Building & Trades",
            "subcategory":"Landscaping Services",
            "type":"Services"
        }
    ],
    "sg:phone":"+32 15 76 06 91",
    "sg:postcode":"2580",
    "sg:province":"Antwerpen",
    "sg:tags":[
        "architect",
        "landscape"
    ],
    "wof:name":"Van Aert J",
    "wof:placetype":"venue"
},
  "geometry": {"coordinates":[4.6313438416,51.0471534729],"type":"Point"}
}