{
  "type": "Feature",
  "properties": {
    "addr:full":"Valkenstraat 14 Londerzeel Vlaams-Brabant 1840",
    "addr:housenumber":"14",
    "addr:postcode":"1840",
    "addr:street":"Valkenstraat",
    "iso:country":"BE",
    "sg:address":"Valkenstraat 14",
    "sg:city":"Londerzeel",
    "sg:orig_category":"Rev\u00eatements pour sols and murs",
    "sg:phone":"+32 52 30 38 24",
    "sg:postcode":"1840",
    "sg:province":"Vlaams-Brabant",
    "wof:name":"Thielemans Kamiel Tegelwerken",
    "wof:placetype":"venue"
},
  "geometry": {"coordinates":[4.3015089035,51.012008667],"type":"Point"}
}