{
  "type": "Feature",
  "properties": {
    "addr:full":"Brandstraat 37 Lochristi (beervelde) Oost-Vlaanderen 9080",
    "addr:housenumber":"37",
    "addr:postcode":"9080",
    "addr:street":"Brandstraat",
    "iso:country":"BE",
    "sg:address":"Brandstraat 37",
    "sg:city":"Lochristi (beervelde)",
    "sg:classifiers":[
        {
            "category":"Shopping",
            "subcategory":"Clothing, Apparel, & Fashions",
            "type":"Retail Goods"
        }
    ],
    "sg:phone":"+32 9 355 11 46",
    "sg:postcode":"9080",
    "sg:province":"Oost-Vlaanderen",
    "sg:tags":[
        "organizer",
        "show"
    ],
    "wof:name":"Tony Houston Bvba",
    "wof:placetype":"venue"
},
  "geometry": {"coordinates":[3.8569009304,51.0688362122],"type":"Point"}
}