{
  "type": "Feature",
  "properties": {
    "iso:country":"BE",
    "sg:address":"Schophemerheide 283",
    "sg:city":"Voeren/fourons",
    "sg:orig_category":"Eleveurs de bovins",
    "sg:phone":"+32 4 381 02 27",
    "sg:postcode":"3798",
    "sg:province":"Limburg",
    "wof:name":"Henricus Eussen",
    "wof:placetype":"venue"
},
  "geometry": {"coordinates":[5.7866101265,50.7522315979],"type":"Point"}
}