{
  "type": "Feature",
  "properties": {
    "iso:country":"BE",
    "sg:address":"Keiemdorpsstraat 170",
    "sg:city":"Diksmuide",
    "sg:orig_category":"Eleveurs de bovins",
    "sg:phone":"+32 51 50 12 32",
    "sg:postcode":"8600",
    "sg:province":"West-Vlaanderen",
    "wof:name":"Jonckheere",
    "wof:placetype":"venue"
},
  "geometry": {"coordinates":[2.8882739544,51.0857124329],"type":"Point"}
}