{
  "type": "Feature",
  "properties": {
    "addr:full":"Rue Du Congo 171-173 Mouscron Hainaut 7700",
    "addr:postcode":"171-173;7700",
    "addr:street":"Rue Du Congo;Hainaut",
    "iso:country":"BE",
    "sg:address":"Rue Du Congo 171-173",
    "sg:city":"Mouscron",
    "sg:classifiers":[
        {
            "category":"Retail",
            "subcategory":"Repair Shop",
            "type":"Services"
        }
    ],
    "sg:phone":"+32 475 20 37 93",
    "sg:postcode":"7700",
    "sg:province":"Hainaut",
    "sg:tags":[
        "upholsterer"
    ],
    "wof:name":"Verfaillie D.s.",
    "wof:placetype":"venue"
},
  "geometry": {"coordinates":[3.2012419701,50.7341308594],"type":"Point"}
}