{
  "type": "Feature",
  "properties": {
    "iso:country":"BE",
    "sg:address":"Brusselsesteenweg 334",
    "sg:city":"Mechelen",
    "sg:classifiers":[
        {
            "category":"Manufacturing",
            "subcategory":"Rubber & Plastics",
            "type":"Manufacturing & Wholesale Goods"
        }
    ],
    "sg:phone":"+32 15 41 53 19",
    "sg:postcode":"2800",
    "sg:province":"Antwerpen",
    "sg:tags":[
        "machine",
        "processing"
    ],
    "wof:name":"Symbolic System Europe B.v.b.a.",
    "wof:placetype":"venue"
},
  "geometry": {"coordinates":[4.4741258621,51.011051178],"type":"Point"}
}