{
  "type": "Feature",
  "properties": {
    "addr:full":"Wolfsdonksteenweg 10 Aarschot Vlaams-Brabant 3201",
    "addr:housenumber":"10",
    "addr:postcode":"3201",
    "addr:street":"Wolfsdonksteenweg",
    "iso:country":"BE",
    "sg:address":"Wolfsdonksteenweg 10",
    "sg:city":"Aarschot",
    "sg:orig_category":"Meubles D\u00e9taillants, Am\u00e9nagement de B\u00e2timents et de Cuisines",
    "sg:phone":"+32 13 77 17 95",
    "sg:postcode":"3201",
    "sg:province":"Vlaams-Brabant",
    "wof:name":"Meubelen P.l.u.",
    "wof:placetype":"venue"
},
  "geometry": {"coordinates":[4.9185681343,51.0284957886],"type":"Point"}
}