{
  "type": "Feature",
  "properties": {
    "iso:country":"BE",
    "sg:address":"Keinkesstraat 9d",
    "sg:city":"Genk",
    "sg:orig_category":"Journaux. Tabac",
    "sg:phone":"+32 89 35 04 20",
    "sg:postcode":"3600",
    "sg:province":"Limburg",
    "wof:name":"Huis Johnny",
    "wof:placetype":"venue"
},
  "geometry": {"coordinates":[5.5027117729,50.9510498047],"type":"Point"}
}