{
  "type": "Feature",
  "properties": {
    "addr:full":"Rue Joseph Brand 123 Bruxelles (schaerbeek) Bruxelles-Capitale 1030",
    "addr:housenumber":"123",
    "addr:postcode":"1030",
    "addr:street":"Rue Joseph Brand",
    "iso:country":"BE",
    "sg:address":"Rue Joseph Brand 123",
    "sg:city":"Bruxelles (schaerbeek)",
    "sg:classifiers":[
        {
            "category":"Real Estate",
            "subcategory":"Architect",
            "type":"Services"
        }
    ],
    "sg:phone":"+32 2 216 81 21",
    "sg:postcode":"1030",
    "sg:province":"Bruxelles-Capitale",
    "wof:name":"Carlier V",
    "wof:placetype":"venue"
},
  "geometry": {"coordinates":[4.37626791,50.8639335632],"type":"Point"}
}