{
  "type": "Feature",
  "properties": {
    "iso:country":"BE",
    "sg:address":"Wezestraat 24",
    "sg:city":"Ardooie",
    "sg:classifiers":[
        {
            "category":"Parking",
            "subcategory":"Lot",
            "type":"Transportation"
        }
    ],
    "sg:phone":"+32 51 74 41 84",
    "sg:postcode":"8850",
    "sg:province":"West-Vlaanderen",
    "sg:tags":[
        "armoured",
        "door",
        "fireproof"
    ],
    "wof:name":"M.a.p. Bvba-sprl",
    "wof:placetype":"venue"
},
  "geometry": {"coordinates":[3.2104070187,50.9634437561],"type":"Point"}
}