{
  "type": "Feature",
  "properties": {
    "iso:country":"BE",
    "sg:address":"Hoekestraat 42",
    "sg:city":"Knokke-heist (westkapelle)",
    "sg:classifiers":[
        {
            "category":"Shopping",
            "subcategory":"Florist",
            "type":"Retail Goods"
        }
    ],
    "sg:phone":"+32 50 62 29 32",
    "sg:postcode":"8300",
    "sg:province":"West-Vlaanderen",
    "wof:name":"Margriet",
    "wof:placetype":"venue"
},
  "geometry": {"coordinates":[3.287694931,51.3467254639],"type":"Point"}
}