{
  "type": "Feature",
  "properties": {
    "addr:full":"Avenue De L\u00b4esp\u00c9rance 1 Fleurus Hainaut 6220",
    "addr:housenumber":"1",
    "addr:postcode":"6220",
    "addr:street":"Avenue De L\u00b4Espe\u0301Rance",
    "iso:country":"BE",
    "sg:address":"Avenue De L\u00b4esp\u00c9rance 1",
    "sg:city":"Fleurus",
    "sg:orig_category":"Hout and afgeleiden Gh IJzerwaren, bouw- and verfmaterialen",
    "sg:phone":"+32 71 80 08 55",
    "sg:postcode":"6220",
    "sg:province":"Hainaut",
    "wof:name":"United Agent",
    "wof:placetype":"venue"
},
  "geometry": {"coordinates":[4.5303349495,50.4511566162],"type":"Point"}
}