{
  "type": "Feature",
  "properties": {
    "iso:country":"BE",
    "sg:address":"Boulevard Emile Devreux 11 Box 7",
    "sg:city":"Charleroi",
    "sg:classifiers":[
        {
            "category":"Health Services",
            "subcategory":"Doctor",
            "type":"Services"
        }
    ],
    "sg:phone":"+32 71 30 40 58",
    "sg:postcode":"6000",
    "sg:province":"Hainaut",
    "sg:tags":[
        "medicinephysicians",
        "surgeon"
    ],
    "wof:name":"Carlaire J",
    "wof:placetype":"venue"
},
  "geometry": {"coordinates":[4.4489850998,50.4083023071],"type":"Point"}
}