{
  "type": "Feature",
  "properties": {
    "addr:full":"Rijkmakerlaan 25a Essen Antwerpen 2910",
    "addr:housenumber":"25a",
    "addr:postcode":"2910",
    "addr:street":"Rijkmakerlaan",
    "iso:country":"BE",
    "sg:address":"Rijkmakerlaan 25a",
    "sg:city":"Essen",
    "sg:orig_category":"Procesbesturingssystemen Fab",
    "sg:phone":"+32 3 627 08 27",
    "sg:postcode":"2910",
    "sg:province":"Antwerpen",
    "wof:name":"Stromag",
    "wof:placetype":"venue"
},
  "geometry": {"coordinates":[4.4999718666,51.4467124939],"type":"Point"}
}