{
  "type": "Feature",
  "properties": {
    "addr:full":"Brugsesteenweg 559 Roeselare West-Vlaanderen 8800",
    "addr:housenumber":"559",
    "addr:postcode":"8800",
    "addr:street":"Brugsesteenweg",
    "iso:country":"BE",
    "sg:address":"Brugsesteenweg 559",
    "sg:city":"Roeselare",
    "sg:orig_category":"V\u00e9hicules automobiles",
    "sg:phone":"+32 51 22 68 52",
    "sg:postcode":"8800",
    "sg:province":"West-Vlaanderen",
    "wof:name":"Nuyttens Trucks",
    "wof:placetype":"venue"
},
  "geometry": {"coordinates":[3.1191000938,50.9758415222],"type":"Point"}
}