{
  "type": "Feature",
  "properties": {
    "addr:full":"Lammer 4 Hasselt Limburg 3511",
    "addr:housenumber":"4",
    "addr:postcode":"3511",
    "addr:street":"Lammer",
    "iso:country":"BE",
    "sg:address":"Lammer 4",
    "sg:city":"Hasselt",
    "sg:orig_category":"Kapsalons",
    "sg:phone":"+32 11 25 05 92",
    "sg:postcode":"3511",
    "sg:province":"Limburg",
    "wof:name":"Coiffure Fanny",
    "wof:placetype":"venue"
},
  "geometry": {"coordinates":[5.3034238815,50.9432487488],"type":"Point"}
}