{
  "type": "Feature",
  "properties": {
    "iso:country":"BE",
    "sg:address":"H. Moeremanslaan 110",
    "sg:city":"Dilbeek",
    "sg:orig_category":"Agences d'exp\u00e9dition. Grands magasins",
    "sg:phone":"+32 2 466 42 77",
    "sg:postcode":"1700",
    "sg:province":"Vlaams-Brabant",
    "wof:name":"Tristar",
    "wof:placetype":"venue"
},
  "geometry": {"coordinates":[4.2755489349,50.8468437195],"type":"Point"}
}