{
  "type": "Feature",
  "properties": {
    "addr:full":"Koning Leopoldstraat 82 Lovendegem Oost-Vlaanderen 9920",
    "addr:housenumber":"82",
    "addr:postcode":"9920",
    "addr:street":"Koning Leopoldstraat",
    "iso:country":"BE",
    "sg:address":"Koning Leopoldstraat 82",
    "sg:city":"Lovendegem",
    "sg:classifiers":[
        {
            "category":"Farming",
            "subcategory":"Fish & Marine Products",
            "type":"Manufacturing & Wholesale Goods"
        }
    ],
    "sg:phone":"+32 9 372 95 11",
    "sg:postcode":"9920",
    "sg:province":"Oost-Vlaanderen",
    "sg:tags":[
        "animal",
        "food",
        "related",
        "grain",
        "cereal",
        "breeding"
    ],
    "wof:name":"Flip Flanders Ideal Pig Cv",
    "wof:placetype":"venue"
},
  "geometry": {"coordinates":[3.6421649456,51.0927352905],"type":"Point"}
}