{
  "type": "Feature",
  "properties": {
    "addr:full":"Stationsstraat 29 Asse Vlaams-Brabant 1730",
    "addr:housenumber":"29",
    "addr:postcode":"1730",
    "addr:street":"Stationsstraat",
    "iso:country":"BE",
    "sg:address":"Stationsstraat 29",
    "sg:city":"Asse",
    "sg:orig_category":"Non-Classified Establishments",
    "sg:phone":"+32 2 453 23 73",
    "sg:postcode":"1730",
    "sg:province":"Vlaams-Brabant",
    "wof:name":"B.e. Different Sprl",
    "wof:placetype":"venue"
},
  "geometry": {"coordinates":[4.2049927711,50.907787323],"type":"Point"}
}