{
  "type": "Feature",
  "properties": {
    "addr:full":"Avenue Moli\u00e8re 43 Wavre Brabant Wallon 1300",
    "addr:housenumber":"43;1300",
    "addr:street":"Avenue Molie\u0300Re",
    "iso:country":"BE",
    "sg:address":"Avenue Moli\u00e8re 43",
    "sg:city":"Wavre",
    "sg:classifiers":[
        {
            "category":"Professional",
            "subcategory":"Management & Consulting",
            "type":"Services"
        }
    ],
    "sg:phone":"+32 10 22 56 12",
    "sg:postcode":"1300",
    "sg:province":"Brabant Wallon",
    "sg:tags":[
        "consultant"
    ],
    "wof:name":"Proconsult Sprl",
    "wof:placetype":"venue"
},
  "geometry": {"coordinates":[4.6347308159,50.707233429],"type":"Point"}
}