{
  "type": "Feature",
  "properties": {
    "iso:country":"BE",
    "sg:address":"Place Joseph Thiry 18",
    "sg:city":"Aywaille",
    "sg:classifiers":[
        {
            "category":"Food & Beverages",
            "subcategory":"Fruits & Vegetables",
            "type":"Retail Goods"
        }
    ],
    "sg:phone":"+32 4 384 40 71",
    "sg:postcode":"4920",
    "sg:province":"Li\u00e8ge",
    "sg:tags":[
        "groenten"
    ],
    "wof:name":"Maison Maraude",
    "wof:placetype":"venue"
},
  "geometry": {"coordinates":[5.6754779816,50.4740867615],"type":"Point"}
}