{
  "type": "Feature",
  "properties": {
    "addr:full":"Nieuwstraat 56 Geraardsbergen Oost-Vlaanderen 9500",
    "addr:housenumber":"56",
    "addr:postcode":"9500",
    "addr:street":"Nieuwstraat",
    "iso:country":"BE",
    "sg:address":"Nieuwstraat 56",
    "sg:city":"Geraardsbergen",
    "sg:orig_category":"Radioproductie and uitzendingen",
    "sg:phone":"+32 54 41 61 75",
    "sg:postcode":"9500",
    "sg:province":"Oost-Vlaanderen",
    "wof:name":"M.i.g. Radio",
    "wof:placetype":"venue"
},
  "geometry": {"coordinates":[3.8805360794,50.7728652954],"type":"Point"}
}