{
  "type": "Feature",
  "properties": {
    "addr:full":"Arnhoutstraat 93 Sint-niklaas Oost-Vlaanderen 9111",
    "addr:housenumber":"93",
    "addr:postcode":"9111",
    "addr:street":"Arnhoutstraat",
    "iso:country":"BE",
    "sg:address":"Arnhoutstraat 93",
    "sg:city":"Sint-niklaas",
    "sg:orig_category":"Herstellingen and onderhoud van auto's",
    "sg:phone":"+32 3 776 05 34",
    "sg:postcode":"9111",
    "sg:province":"Oost-Vlaanderen",
    "wof:name":"Garage Govaerts",
    "wof:placetype":"venue"
},
  "geometry": {"coordinates":[4.115664959,51.1545257568],"type":"Point"}
}