{
  "type": "Feature",
  "properties": {
    "addr:full":"Rue Des Viaducs 201b2a Mons Hainaut 7020",
    "addr:postcode":"7020",
    "addr:street":"Rue Des Viaducs 201B2A;Hainaut",
    "iso:country":"BE",
    "sg:address":"Rue Des Viaducs 201b2a",
    "sg:city":"Mons",
    "sg:orig_category":"Architecten",
    "sg:phone":"+32 65 84 90 57",
    "sg:postcode":"7020",
    "sg:province":"Hainaut",
    "wof:name":"Thema",
    "wof:placetype":"venue"
},
  "geometry": {"coordinates":[3.9553449154,50.4761772156],"type":"Point"}
}