{
  "type": "Feature",
  "properties": {
    "iso:country":"BE",
    "sg:address":"Mechelsestraat 39",
    "sg:city":"Londerzeel",
    "sg:classifiers":[
        {
            "category":"Shopping",
            "subcategory":"Bicycles & Sporting Goods",
            "type":"Retail Goods"
        }
    ],
    "sg:phone":"+32 52 30 15 10",
    "sg:postcode":"1840",
    "sg:province":"Vlaams-Brabant",
    "sg:tags":[
        "-"
    ],
    "wof:name":"Vandenhoute M",
    "wof:placetype":"venue"
},
  "geometry": {"coordinates":[4.3055758476,51.0037345886],"type":"Point"}
}