{
  "type": "Feature",
  "properties": {
    "iso:country":"BE",
    "sg:address":"Deinsesteenweg 8",
    "sg:city":"Tielt",
    "sg:classifiers":[
        {
            "category":"Manufacturing",
            "subcategory":"Lumber",
            "type":"Manufacturing & Wholesale Goods"
        }
    ],
    "sg:phone":"+32 51 40 34 08",
    "sg:postcode":"8700",
    "sg:province":"West-Vlaanderen",
    "sg:tags":[
        "timber"
    ],
    "wof:name":"De Deurwaerder E & G",
    "wof:placetype":"venue"
},
  "geometry": {"coordinates":[3.3501260281,50.9974594116],"type":"Point"}
}