{
  "type": "Feature",
  "properties": {
    "addr:full":"Breulstraat 24 Moorslede West-Vlaanderen 8890",
    "addr:housenumber":"24",
    "addr:postcode":"8890",
    "addr:street":"Breulstraat",
    "iso:country":"BE",
    "sg:address":"Breulstraat 24",
    "sg:city":"Moorslede",
    "sg:classifiers":[
        {
            "category":"Bakery",
            "type":"Food & Drink"
        }
    ],
    "sg:phone":"+32 51 78 05 08",
    "sg:postcode":"8890",
    "sg:province":"West-Vlaanderen",
    "sg:tags":[
        "confectioner",
        "baker"
    ],
    "wof:name":"Fr\u00e9d\u00e9ric",
    "wof:placetype":"venue"
},
  "geometry": {"coordinates":[3.0646569729,50.8907699585],"type":"Point"}
}