{
  "type": "Feature",
  "properties": {
    "addr:full":"Dorp 64 Lommel Limburg 3920",
    "addr:housenumber":"64",
    "addr:postcode":"3920",
    "addr:street":"Dorp",
    "iso:country":"BE",
    "sg:address":"Dorp 64",
    "sg:city":"Lommel",
    "sg:classifiers":[
        {
            "category":"Bars & Pubs",
            "type":"Food & Drink"
        }
    ],
    "sg:phone":"+32 11 55 25 53",
    "sg:postcode":"3920",
    "sg:province":"Limburg",
    "wof:name":"Dundee's Bvba",
    "wof:placetype":"venue"
},
  "geometry": {"coordinates":[5.3067750931,51.2311210632],"type":"Point"}
}