{
  "type": "Feature",
  "properties": {
    "addr:full":"Rue Cl\u00c9menceau 28 Mons Hainaut 7012",
    "addr:housenumber":"28",
    "addr:postcode":"7012",
    "addr:street":"Rue Cle\u0301Menceau;Hainaut",
    "iso:country":"BE",
    "sg:address":"Rue Cl\u00c9menceau 28",
    "sg:city":"Mons",
    "sg:classifiers":[
        {
            "category":"Cafe",
            "type":"Food & Drink"
        }
    ],
    "sg:phone":"+32 65 88 61 69",
    "sg:postcode":"7012",
    "sg:province":"Hainaut",
    "sg:tags":[
        "caf\u00e9s"
    ],
    "wof:name":"Cercle Par. Rerum Novarum",
    "wof:placetype":"venue"
},
  "geometry": {"coordinates":[3.8894600868,50.4481964111],"type":"Point"}
}