{
  "type": "Feature",
  "properties": {
    "iso:country":"BE",
    "sg:address":"Chauss\u00c9e De Bruxelles 65",
    "sg:city":"Genappe",
    "sg:orig_category":"Voertuigen",
    "sg:phone":"+32 2 387 05 55",
    "sg:postcode":"1472",
    "sg:province":"Brabant Wallon",
    "wof:name":"A.c.i",
    "wof:placetype":"venue"
},
  "geometry": {"coordinates":[4.4168081284,50.6498069763],"type":"Point"}
}