{
  "type": "Feature",
  "properties": {
    "iso:country":"BE",
    "sg:address":"Nijverheidstraat 58",
    "sg:city":"Gent",
    "sg:orig_category":"Studios photographiques. Activit\u00e9s diverses d'imprimerie",
    "sg:phone":"+32 9 238 10 87",
    "sg:postcode":"9040",
    "sg:province":"Oost-Vlaanderen",
    "wof:name":"Katrien Daemers",
    "wof:placetype":"venue"
},
  "geometry": {"coordinates":[3.7447240353,51.0515403748],"type":"Point"}
}