{
  "type": "Feature",
  "properties": {
    "addr:full":"Rue Du Mar\u00e9chal Joffre 142 Colfontaine (wasmes) Hainaut 7340",
    "addr:housenumber":"142",
    "addr:postcode":"7340",
    "addr:street":"Rue Du Mare\u0301Chal Joffre",
    "iso:country":"BE",
    "sg:address":"Rue Du Mar\u00e9chal Joffre 142",
    "sg:city":"Colfontaine (wasmes)",
    "sg:classifiers":[
        {
            "category":"Health Services",
            "subcategory":"Health Practitioner",
            "type":"Services"
        }
    ],
    "sg:phone":"+32 65 46 59 27",
    "sg:postcode":"7340",
    "sg:province":"Hainaut",
    "sg:tags":[
        "therapist",
        "speech"
    ],
    "wof:name":"Mahieu N",
    "wof:placetype":"venue"
},
  "geometry": {"coordinates":[3.8456439972,50.4029273987],"type":"Point"}
}