{
  "type": "Feature",
  "properties": {
    "iso:country":"BE",
    "sg:address":"Rue De Villers 57e",
    "sg:city":"Tinlot",
    "sg:orig_category":"Installatie van houten of kunststof schrijnwerk",
    "sg:phone":"+32 85 51 17 44",
    "sg:postcode":"4557",
    "sg:province":"Li\u00e8ge",
    "wof:name":"Menuiserie Scrytoise",
    "wof:placetype":"venue"
},
  "geometry": {"coordinates":[5.3753452301,50.47864151],"type":"Point"}
}