{
  "type": "Feature",
  "properties": {
    "iso:country":"BE",
    "sg:address":"Rue De La Station 15",
    "sg:city":"Waterloo",
    "sg:classifiers":[
        {
            "category":"Retail",
            "subcategory":"Repair Shop",
            "type":"Services"
        }
    ],
    "sg:phone":"+32 2 354 88 62",
    "sg:postcode":"1410",
    "sg:province":"Brabant Wallon",
    "sg:tags":[
        "-",
        "clothing",
        "alteration"
    ],
    "wof:name":"Boite \u00e0 Couture",
    "wof:placetype":"venue"
},
  "geometry": {"coordinates":[4.3940701485,50.7171783447],"type":"Point"}
}