{
  "type": "Feature",
  "properties": {
    "addr:full":"Rue Bois-l\u00b4ev\u00caque 107 Li\u00c8ge Li\u00e8ge 4000",
    "addr:housenumber":"107",
    "addr:postcode":"4000",
    "addr:street":"Rue Bois-L\u00b4Eve\u0302Que",
    "iso:country":"BE",
    "sg:address":"Rue Bois-l\u00b4ev\u00caque 107",
    "sg:city":"Li\u00c8ge",
    "sg:orig_category":"Evaluation and estimation de biens immobiliers. Agences immobili\u00e8res",
    "sg:phone":"+32 4 252 21 52",
    "sg:postcode":"4000",
    "sg:province":"Li\u00e8ge",
    "wof:name":"Etienne Lahaye",
    "wof:placetype":"venue"
},
  "geometry": {"coordinates":[5.5590791702,50.6250457764],"type":"Point"}
}