{
  "type": "Feature",
  "properties": {
    "iso:country":"BE",
    "sg:address":"Bekaertlaan 6",
    "sg:city":"Dilsen-stokkem",
    "sg:classifiers":[
        {
            "category":"Building & Trades",
            "subcategory":"Construction",
            "type":"Services"
        }
    ],
    "sg:phone":"+32 9 228 27 98",
    "sg:postcode":"3650",
    "sg:province":"Limburg",
    "sg:tags":[
        "machine"
    ],
    "wof:name":"Jmb Nv",
    "wof:placetype":"venue"
},
  "geometry": {"coordinates":[3.7546079159,51.0522727966],"type":"Point"}
}