{
  "type": "Feature",
  "properties": {
    "iso:country":"BE",
    "sg:address":"Albert I Laan 36",
    "sg:city":"Veurne",
    "sg:orig_category":"Beheer van afvalopslag- and stortplaatsen Overheidsdiensten",
    "sg:phone":"+32 58 31 40 37",
    "sg:postcode":"8630",
    "sg:province":"West-Vlaanderen",
    "wof:name":"Containerpark Veurne-ivvo",
    "wof:placetype":"venue"
},
  "geometry": {"coordinates":[2.6734700203,51.0610198975],"type":"Point"}
}