{
  "type": "Feature",
  "properties": {
    "iso:country":"BE",
    "sg:address":"Rue De La Sauveni\u00c8re 141",
    "sg:city":"Spa",
    "sg:classifiers":[
        {
            "category":"Shopping Center",
            "type":"Public Place"
        }
    ],
    "sg:phone":"+32 87 77 23 11",
    "sg:postcode":"4900",
    "sg:province":"Li\u00e8ge",
    "sg:tags":[
        "de",
        "terrain",
        "camping",
        "restaurant"
    ],
    "wof:name":"Parc Des Sources",
    "wof:placetype":"venue"
},
  "geometry": {"coordinates":[5.8853821754,50.4849624634],"type":"Point"}
}