{
  "type": "Feature",
  "properties": {
    "iso:country":"BE",
    "sg:address":"Tijmlaan 20",
    "sg:city":"Sint-jans-molenbeek/molenbeek-saint-jean",
    "sg:orig_category":"Artsen and specialisten",
    "sg:phone":"+32 2 465 75 06",
    "sg:postcode":"1080",
    "sg:province":"Bruxelles-Capitale",
    "wof:name":"Walter Renier",
    "wof:placetype":"venue"
},
  "geometry": {"coordinates":[4.3039622307,50.8560638428],"type":"Point"}
}