{
  "type": "Feature",
  "properties": {
    "iso:country":"BE",
    "sg:address":"Rue Albert Ier 172",
    "sg:city":"Erquelinnes",
    "sg:orig_category":"Drogueries. Quincailleries",
    "sg:phone":"+32 71 55 65 53",
    "sg:postcode":"6560",
    "sg:province":"Hainaut",
    "wof:name":"Maison Brunot",
    "wof:placetype":"venue"
},
  "geometry": {"coordinates":[4.1171150208,50.3076095581],"type":"Point"}
}