{
  "type": "Feature",
  "properties": {
    "addr:full":"Rue J. Lahaye 80 Jette Bruxelles-Capitale 1090",
    "addr:housenumber":"80",
    "addr:postcode":"1090",
    "addr:street":"Rue J. Lahaye",
    "iso:country":"BE",
    "sg:address":"Rue J. Lahaye 80",
    "sg:city":"Jette",
    "sg:orig_category":"Fleurs and plantes",
    "sg:phone":"+32 2 425 19 94",
    "sg:postcode":"1090",
    "sg:province":"Bruxelles-Capitale",
    "wof:name":"Palais Des Fleurs",
    "wof:placetype":"venue"
},
  "geometry": {"coordinates":[4.3344721794,50.8793182373],"type":"Point"}
}