{
  "type": "Feature",
  "properties": {
    "addr:full":"Tennislaan 16 Koksijde West-Vlaanderen 8670",
    "addr:housenumber":"16",
    "addr:postcode":"8670",
    "addr:street":"Tennislaan",
    "iso:country":"BE",
    "sg:address":"Tennislaan 16",
    "sg:city":"Koksijde",
    "sg:orig_category":"M\u00e9decins and sp\u00e9cialistes",
    "sg:phone":"+32 58 51 72 23",
    "sg:postcode":"8670",
    "sg:province":"West-Vlaanderen",
    "wof:name":"Piet Kindts",
    "wof:placetype":"venue"
},
  "geometry": {"coordinates":[2.6179718971,51.107585907],"type":"Point"}
}