{
  "type": "Feature",
  "properties": {
    "addr:full":"Koningin Fabiolastraat 49 Wevelgem West-Vlaanderen 8560",
    "addr:housenumber":"49",
    "addr:postcode":"8560",
    "addr:street":"Koningin Fabiolastraat",
    "iso:country":"BE",
    "sg:address":"Koningin Fabiolastraat 49",
    "sg:city":"Wevelgem",
    "sg:orig_category":"Baby- and kinderkleding Dameskledingzaken Herenkledingzaken",
    "sg:phone":"+32 56 42 65 26",
    "sg:postcode":"8560",
    "sg:province":"West-Vlaanderen",
    "wof:name":"Promo Fashion",
    "wof:placetype":"venue"
},
  "geometry": {"coordinates":[3.1939198971,50.824508667],"type":"Point"}
}