{
  "type": "Feature",
  "properties": {
    "addr:full":"Rue Ernest Solvay 372 Li\u00e8ge 1 Li\u00e8ge 4000",
    "addr:housenumber":"372;1",
    "addr:postcode":"4000",
    "addr:street":"Rue Ernest Solvay",
    "iso:country":"BE",
    "sg:address":"Rue Ernest Solvay 372",
    "sg:city":"Li\u00e8ge 1",
    "sg:classifiers":[
        {
            "category":"Manufacturing",
            "subcategory":"Metals",
            "type":"Manufacturing & Wholesale Goods"
        }
    ],
    "sg:phone":"+32 4 234 72 67",
    "sg:postcode":"4000",
    "sg:province":"Li\u00e8ge",
    "sg:tags":[
        "foundry"
    ],
    "wof:name":"Marichal-ketin Sa",
    "wof:placetype":"venue"
},
  "geometry": {"coordinates":[5.5341320038,50.6139335632],"type":"Point"}
}