{
  "type": "Feature",
  "properties": {
    "addr:full":"Kerkhovensesteenweg 88 Lommel Limburg 3920",
    "addr:housenumber":"88",
    "addr:postcode":"3920",
    "addr:street":"Kerkhovensesteenweg",
    "iso:country":"BE",
    "sg:address":"Kerkhovensesteenweg 88",
    "sg:city":"Lommel",
    "sg:orig_category":"Non-Classified Establishments",
    "sg:phone":"+32 11 54 90 00",
    "sg:postcode":"3920",
    "sg:province":"Limburg",
    "wof:name":"Polypreen International Nv",
    "wof:placetype":"venue"
},
  "geometry": {"coordinates":[5.2995147705,51.1884803772],"type":"Point"}
}