{
  "type": "Feature",
  "properties": {
    "addr:full":"Steenbakkerstraat 40 Kortrijk West-Vlaanderen 8500",
    "addr:housenumber":"40",
    "addr:postcode":"8500",
    "addr:street":"Steenbakkerstraat",
    "iso:country":"BE",
    "sg:address":"Steenbakkerstraat 40",
    "sg:city":"Kortrijk",
    "sg:orig_category":"Woningbouw",
    "sg:phone":"+32 56 22 54 07",
    "sg:postcode":"8500",
    "sg:province":"West-Vlaanderen",
    "wof:name":"Derijcker Jp",
    "wof:placetype":"venue"
},
  "geometry": {"coordinates":[3.2862761021,50.8039169312],"type":"Point"}
}