{
  "type": "Feature",
  "properties": {
    "addr:full":"Koolmijnlaan 76 Beringen Limburg 3580",
    "addr:housenumber":"76",
    "addr:postcode":"3580",
    "addr:street":"Koolmijnlaan",
    "iso:country":"BE",
    "sg:address":"Koolmijnlaan 76",
    "sg:city":"Beringen",
    "sg:orig_category":"Ordinateurs and \u00e9quipement informatique",
    "sg:phone":"+32 11 45 34 03",
    "sg:postcode":"3580",
    "sg:province":"Limburg",
    "wof:name":"H & S Ware Comp. Beringen",
    "wof:placetype":"venue"
},
  "geometry": {"coordinates":[5.2228660583,51.0534744263],"type":"Point"}
}