{
  "type": "Feature",
  "properties": {
    "iso:country":"BE",
    "sg:address":"Rue Des Quatre-vents 94",
    "sg:city":"Charleroi",
    "sg:orig_category":"Dranken Meubelzaken, woning- and keukeninrichting",
    "sg:phone":"+32 71 65 57 16",
    "sg:postcode":"6010",
    "sg:province":"Hainaut",
    "wof:name":"Art-cad",
    "wof:placetype":"venue"
},
  "geometry": {"coordinates":[4.4672198296,50.3844604492],"type":"Point"}
}