{
  "type": "Feature",
  "properties": {
    "iso:country":"BE",
    "sg:address":"Zwevezeelsestraat 142",
    "sg:city":"Ardooie (koolskamp)",
    "sg:classifiers":[
        {
            "category":"Food & Beverages",
            "subcategory":"Supermarket",
            "type":"Retail Goods"
        }
    ],
    "sg:phone":"+32 51 61 06 20",
    "sg:postcode":"8851",
    "sg:province":"West-Vlaanderen",
    "sg:tags":[
        "frozen",
        "-"
    ],
    "wof:name":"Dujardin Foods Nv",
    "wof:placetype":"venue"
},
  "geometry": {"coordinates":[3.2087380886,51.0230255127],"type":"Point"}
}