{
  "type": "Feature",
  "properties": {
    "addr:full":"Stationsstraat 136 Liedekerke Vlaams-Brabant 1770",
    "addr:housenumber":"136",
    "addr:postcode":"1770",
    "addr:street":"Stationsstraat;Vlaams-Brabant",
    "iso:country":"BE",
    "sg:address":"Stationsstraat 136",
    "sg:city":"Liedekerke",
    "sg:classifiers":[
        {
            "category":"Personal",
            "subcategory":"Barber",
            "type":"Services"
        }
    ],
    "sg:phone":"+32 53 66 21 54",
    "sg:postcode":"1770",
    "sg:province":"Vlaams-Brabant",
    "sg:tags":[
        "gentleman",
        "salon",
        "-",
        "hairdressing"
    ],
    "wof:name":"Rudy",
    "wof:placetype":"venue"
},
  "geometry": {"coordinates":[4.0886030197,50.8744735718],"type":"Point"}
}