{
  "type": "Feature",
  "properties": {
    "addr:full":"Rue Arthur Warocqu\u00c9 88 La Louviere Hainaut 7100",
    "addr:housenumber":"88",
    "addr:postcode":"7100",
    "addr:street":"Rue Arthur Warocque\u0301",
    "iso:country":"BE",
    "sg:address":"Rue Arthur Warocqu\u00c9 88",
    "sg:city":"La Louviere",
    "sg:orig_category":"Activit\u00e9s d\u00b4action sociale sans h\u00e9bergement",
    "sg:phone":"+32 64 22 58 74",
    "sg:postcode":"7100",
    "sg:province":"Hainaut",
    "wof:name":"Centre P.m.s.",
    "wof:placetype":"venue"
},
  "geometry": {"coordinates":[4.1937742233,50.4761962891],"type":"Point"}
}