{
  "type": "Feature",
  "properties": {
    "addr:full":"Rue G\u00c9n\u00c9ral Jacques 8 C Vielsalm Luxembourg 6690",
    "addr:housenumber":"8 c",
    "addr:postcode":"6690",
    "addr:street":"Rue Ge\u0301Ne\u0301Ral Jacques",
    "iso:country":"BE",
    "sg:address":"Rue G\u00c9n\u00c9ral Jacques 8 C",
    "sg:city":"Vielsalm",
    "sg:orig_category":"Beautyfarms, relaxatie and lichamelijk welzijn Schoonheidssalons",
    "sg:phone":"+32 80 21 45 39",
    "sg:postcode":"6690",
    "sg:province":"Luxembourg",
    "wof:name":"Capital Beaut\u00c9",
    "wof:placetype":"venue"
},
  "geometry": {"coordinates":[5.9161391258,50.286819458],"type":"Point"}
}