{
  "type": "Feature",
  "properties": {
    "addr:full":"Koolmijnlaan 226 Beringen Limburg 3582",
    "addr:housenumber":"226",
    "addr:postcode":"3582",
    "addr:street":"Koolmijnlaan",
    "iso:country":"BE",
    "sg:address":"Koolmijnlaan 226",
    "sg:city":"Beringen",
    "sg:classifiers":[
        {
            "category":"Cafe",
            "type":"Food & Drink"
        }
    ],
    "sg:phone":"+32 11 42 05 92",
    "sg:postcode":"3582",
    "sg:province":"Limburg",
    "sg:tags":[
        "caf\u00e9s"
    ],
    "wof:name":"Ronnie Jacobs",
    "wof:placetype":"venue"
},
  "geometry": {"coordinates":[5.2202768326,51.072227478],"type":"Point"}
}