{
  "type": "Feature",
  "properties": {
    "addr:full":"Rue Henri Werrie 76 Jette Bruxelles-Capitale 1090",
    "addr:housenumber":"76",
    "addr:postcode":"1090",
    "addr:street":"Rue Henri Werrie",
    "iso:country":"BE",
    "sg:address":"Rue Henri Werrie 76",
    "sg:city":"Jette",
    "sg:classifiers":[
        {
            "category":"Sports & Exercise",
            "subcategory":"Sports Center",
            "type":"Entertainment"
        }
    ],
    "sg:phone":"+32 2 428 90 78",
    "sg:postcode":"1090",
    "sg:province":"Bruxelles-Capitale",
    "sg:tags":[
        "installation",
        "sportifs",
        "de",
        "terrain",
        "hors",
        "caf\u00e9s"
    ],
    "wof:name":"Ritz Bowling Center",
    "wof:placetype":"venue"
},
  "geometry": {"coordinates":[4.3271179199,50.8770675659],"type":"Point"}
}