{
  "type": "Feature",
  "properties": {
    "addr:full":"Schildebaan 26 Zandhoven Antwerpen 2240",
    "addr:housenumber":"26",
    "addr:postcode":"2240",
    "addr:street":"Schildebaan",
    "iso:country":"BE",
    "sg:address":"Schildebaan 26",
    "sg:city":"Zandhoven",
    "sg:classifiers":[
        {
            "category":"Building & Trades",
            "subcategory":"Landscaping Services",
            "type":"Services"
        }
    ],
    "sg:phone":"+32 3 464 03 81",
    "sg:postcode":"2240",
    "sg:province":"Antwerpen",
    "sg:tags":[
        "gardening",
        "garden",
        "maintenance"
    ],
    "wof:name":"Aarde Werk",
    "wof:placetype":"venue"
},
  "geometry": {"coordinates":[4.6531801224,51.2172393799],"type":"Point"}
}