{
  "type": "Feature",
  "properties": {
    "addr:full":"Centre Comm. Bay Bonnet 6b1 Fleron Li\u00e8ge 4620",
    "addr:postcode":"4620",
    "iso:country":"BE",
    "sg:address":"Centre Comm. Bay Bonnet 6b1",
    "sg:city":"Fleron",
    "sg:classifiers":[
        {
            "category":"Shopping",
            "subcategory":"Clothing, Apparel, & Fashions",
            "type":"Retail Goods"
        }
    ],
    "sg:phone":"+32 4 358 17 87",
    "sg:postcode":"4620",
    "sg:province":"Li\u00e8ge",
    "sg:tags":[
        "ondergoed",
        "lingerie"
    ],
    "wof:name":"Maison Frivolit\u00c9s",
    "wof:placetype":"venue"
},
  "geometry": {"coordinates":[5.6872401237,50.6125297546],"type":"Point"}
}