{
  "type": "Feature",
  "properties": {
    "addr:full":"Rue De Ten Brielen 8 Comines-warneton (comines) Hainaut 7780",
    "addr:housenumber":"8",
    "addr:postcode":"7780",
    "addr:street":"Rue De Ten Brielen",
    "iso:country":"BE",
    "sg:address":"Rue De Ten Brielen 8",
    "sg:city":"Comines-warneton (comines)",
    "sg:classifiers":[
        {
            "category":"Professional",
            "subcategory":"Lawyer & Legal Services",
            "type":"Services"
        }
    ],
    "sg:phone":"+32 56 55 76 46",
    "sg:postcode":"7780",
    "sg:province":"Hainaut",
    "wof:name":"Dujardin Francis",
    "wof:placetype":"venue"
},
  "geometry": {"coordinates":[2.9967899323,50.7743797302],"type":"Point"}
}