{
  "type": "Feature",
  "properties": {
    "addr:full":"Gasthuisstraat 53 Geraardsbergen Oost-Vlaanderen 9500",
    "addr:housenumber":"53",
    "addr:postcode":"9500",
    "addr:street":"Gasthuisstraat",
    "iso:country":"BE",
    "sg:address":"Gasthuisstraat 53",
    "sg:city":"Geraardsbergen",
    "sg:orig_category":"Dranken",
    "sg:phone":"+32 54 41 03 95",
    "sg:postcode":"9500",
    "sg:province":"Oost-Vlaanderen",
    "wof:name":"Huis Lemahieu",
    "wof:placetype":"venue"
},
  "geometry": {"coordinates":[3.8766479492,50.7704238892],"type":"Point"}
}