{
  "type": "Feature",
  "properties": {
    "addr:full":"Schoolstraat 30 Meeuwen-gruitrode Limburg 3670",
    "addr:housenumber":"30",
    "addr:postcode":"3670",
    "addr:street":"Schoolstraat",
    "iso:country":"BE",
    "sg:address":"Schoolstraat 30",
    "sg:city":"Meeuwen-gruitrode",
    "sg:orig_category":"Jeugdherbergen and berghutten",
    "sg:phone":"+32 11 63 40 64",
    "sg:postcode":"3670",
    "sg:province":"Limburg",
    "wof:name":"Kariboe",
    "wof:placetype":"venue"
},
  "geometry": {"coordinates":[5.5205497742,51.0963516235],"type":"Point"}
}