{
  "type": "Feature",
  "properties": {
    "addr:full":"Rue Des Capucins 8 Spa Li\u00e8ge 4900",
    "addr:housenumber":"8",
    "addr:postcode":"4900",
    "addr:street":"Rue Des Capucins",
    "iso:country":"BE",
    "sg:address":"Rue Des Capucins 8",
    "sg:city":"Spa",
    "sg:orig_category":"Enseignement maternel and primaire",
    "sg:phone":"+32 87 77 41 50",
    "sg:postcode":"4900",
    "sg:province":"Li\u00e8ge",
    "wof:name":"Ecole Fondamentale",
    "wof:placetype":"venue"
},
  "geometry": {"coordinates":[5.8655328751,50.4904670715],"type":"Point"}
}