{
  "type": "Feature",
  "properties": {
    "iso:country":"BE",
    "sg:address":"Molenheide 36",
    "sg:city":"Puurs (breendonk)",
    "sg:classifiers":[
        {
            "category":"Farming",
            "subcategory":"Livestock Farm",
            "type":"Manufacturing & Wholesale Goods"
        }
    ],
    "sg:phone":"+32 3 886 64 02",
    "sg:postcode":"2870",
    "sg:province":"Antwerpen",
    "sg:tags":[
        "buyer"
    ],
    "wof:name":"De Busschop A",
    "wof:placetype":"venue"
},
  "geometry": {"coordinates":[4.2875089645,51.072845459],"type":"Point"}
}