{
  "type": "Feature",
  "properties": {
    "iso:country":"BE",
    "sg:address":"Rozendal 120",
    "sg:city":"Tremelo",
    "sg:orig_category":"Dakwerken",
    "sg:phone":"+32 16 53 22 32",
    "sg:postcode":"3128",
    "sg:province":"Vlaams-Brabant",
    "wof:name":"Kamiel Van Woinsel",
    "wof:placetype":"venue"
},
  "geometry": {"coordinates":[4.7485017776,50.9976348877],"type":"Point"}
}