{
  "type": "Feature",
  "properties": {
    "addr:full":"Chauss\u00c9e De Charleroi 25 Charleroi Hainaut 6061",
    "addr:housenumber":"25",
    "addr:postcode":"6061",
    "addr:street":"Chausse\u0301E De Charleroi;Hainaut",
    "iso:country":"BE",
    "sg:address":"Chauss\u00c9e De Charleroi 25",
    "sg:city":"Charleroi",
    "sg:orig_category":"Banken and kredietinstellingen",
    "sg:phone":"+32 71 32 11 86",
    "sg:postcode":"6061",
    "sg:province":"Hainaut",
    "wof:name":"Bbl",
    "wof:placetype":"venue"
},
  "geometry": {"coordinates":[4.4776558876,50.4011154175],"type":"Point"}
}