{
  "type": "Feature",
  "properties": {
    "addr:full":"Rue Nouvelle Route 133b Engis Li\u00e8ge 4480",
    "addr:postcode":"4480",
    "addr:street":"Rue Nouvelle Route 133B",
    "iso:country":"BE",
    "sg:address":"Rue Nouvelle Route 133b",
    "sg:city":"Engis",
    "sg:classifiers":[
        {
            "category":"Health Services",
            "subcategory":"Doctor",
            "type":"Services"
        }
    ],
    "sg:phone":"+32 4 275 49 50",
    "sg:postcode":"4480",
    "sg:province":"Li\u00e8ge",
    "sg:tags":[
        "medicinephysicians",
        "surgeon"
    ],
    "wof:name":"Dupuis L",
    "wof:placetype":"venue"
},
  "geometry": {"coordinates":[5.3932528496,50.5827293396],"type":"Point"}
}