{
  "type": "Feature",
  "properties": {
    "iso:country":"BE",
    "sg:address":"Groenplaats 4",
    "sg:city":"Gingelom (montenaken)",
    "sg:classifiers":[
        {
            "category":"Retail",
            "subcategory":"Auto Repair",
            "type":"Services"
        }
    ],
    "sg:phone":"+32 11 88 22 84",
    "sg:postcode":"3890",
    "sg:province":"Limburg",
    "sg:tags":[
        "lpg",
        "automobile",
        "-",
        "system"
    ],
    "wof:name":"Chaetodon",
    "wof:placetype":"venue"
},
  "geometry": {"coordinates":[5.1469769478,50.718788147],"type":"Point"}
}