{
  "type": "Feature",
  "properties": {
    "addr:full":"Douveverblijf 48 Komen-waasten/comines-warneton Hainaut 7784",
    "addr:housenumber":"48;7784",
    "addr:street":"Douveverblijf",
    "iso:country":"BE",
    "sg:address":"Douveverblijf 48",
    "sg:city":"Komen-waasten/comines-warneton",
    "sg:orig_category":"Artiesten and kunstenaars",
    "sg:phone":"+32 56 58 83 01",
    "sg:postcode":"7784",
    "sg:province":"Hainaut",
    "wof:name":"Andre De Campenaere",
    "wof:placetype":"venue"
},
  "geometry": {"coordinates":[2.9385099411,50.738319397],"type":"Point"}
}