{
  "type": "Feature",
  "properties": {
    "iso:country":"BE",
    "sg:address":"Rue D'ans 140",
    "sg:city":"Li\u00c8ge",
    "sg:orig_category":"Meubles D\u00e9taillants, Am\u00e9nagement de B\u00e2timents et de Cuisines",
    "sg:phone":"+32 4 263 19 43",
    "sg:postcode":"4000",
    "sg:province":"Li\u00e8ge",
    "wof:name":"Mobigro",
    "wof:placetype":"venue"
},
  "geometry": {"coordinates":[5.5383172035,50.6366958618],"type":"Point"}
}