{
  "type": "Feature",
  "properties": {
    "iso:country":"BE",
    "sg:address":"Chauss\u00c9e De Dinant 747",
    "sg:city":"Namur",
    "sg:orig_category":"Advocaten and juridische adviseurs",
    "sg:phone":"+32 81 46 16 50",
    "sg:postcode":"5100",
    "sg:province":"Namur",
    "wof:name":"Anne Wittmann",
    "wof:placetype":"venue"
},
  "geometry": {"coordinates":[4.8674478531,50.4281692505],"type":"Point"}
}