{
  "type": "Feature",
  "properties": {
    "iso:country":"BE",
    "sg:address":"Warandestraat 44",
    "sg:city":"Turnhout",
    "sg:orig_category":"Tribunaux",
    "sg:phone":"+32 14 42 45 11",
    "sg:postcode":"2300",
    "sg:province":"Antwerpen",
    "wof:name":"Vredegerecht",
    "wof:placetype":"venue"
},
  "geometry": {"coordinates":[4.9405641556,51.3243484497],"type":"Point"}
}