{
  "type": "Feature",
  "properties": {
    "iso:country":"BE",
    "sg:address":"Peerdekouterstraat 9",
    "sg:city":"Wortegem-petegem",
    "sg:orig_category":"Rundveehouders",
    "sg:phone":"+32 56 60 54 01",
    "sg:postcode":"9790",
    "sg:province":"Oost-Vlaanderen",
    "wof:name":"Armand Van De Wege",
    "wof:placetype":"venue"
},
  "geometry": {"coordinates":[3.4861390591,50.8763618469],"type":"Point"}
}