{
  "type": "Feature",
  "properties": {
    "iso:country":"BE",
    "sg:address":"Reygaerdijkstraat 11",
    "sg:city":"Veurne",
    "sg:orig_category":"Rundveehouders",
    "sg:phone":"+32 58 31 14 47",
    "sg:postcode":"8630",
    "sg:province":"West-Vlaanderen",
    "wof:name":"Robert Gheldof",
    "wof:placetype":"venue"
},
  "geometry": {"coordinates":[2.7313230038,51.065071106],"type":"Point"}
}