{
  "type": "Feature",
  "properties": {
    "iso:country":"BE",
    "sg:address":"Villadreef 55",
    "sg:city":"Zemst (elewijt)",
    "sg:orig_category":"Non-Classified Establishments",
    "sg:phone":"+32 16 65 05 12",
    "sg:postcode":"1982",
    "sg:province":"Vlaams-Brabant",
    "wof:name":"Independent Promotions",
    "wof:placetype":"venue"
},
  "geometry": {"coordinates":[4.5073008537,50.9725723267],"type":"Point"}
}