{
  "type": "Feature",
  "properties": {
    "addr:full":"Avenue De La Closi\u00c8re 45 Waterloo Brabant Wallon 1410",
    "addr:housenumber":"45",
    "addr:postcode":"1410",
    "addr:street":"Avenue De La Closie\u0300Re",
    "iso:country":"BE",
    "sg:address":"Avenue De La Closi\u00c8re 45",
    "sg:city":"Waterloo",
    "sg:orig_category":"Plaatsen van vloer- and muurbekleding Schilders Vloer- and muurbekleding",
    "sg:phone":"+32 2 354 50 69",
    "sg:postcode":"1410",
    "sg:province":"Brabant Wallon",
    "wof:name":"Cecere D\u00c9cor",
    "wof:placetype":"venue"
},
  "geometry": {"coordinates":[4.3878359795,50.7116851807],"type":"Point"}
}