{
  "type": "Feature",
  "properties": {
    "addr:full":"Rue De Jupille 12 Vis\u00e9 Li\u00e8ge 4600",
    "addr:housenumber":"12",
    "addr:postcode":"4600",
    "addr:street":"Rue De Jupille",
    "iso:country":"BE",
    "sg:address":"Rue De Jupille 12",
    "sg:city":"Vis\u00e9",
    "sg:classifiers":[
        {
            "category":"Professional",
            "subcategory":"Advertising",
            "type":"Services"
        }
    ],
    "sg:phone":"+32 4 374 12 90",
    "sg:postcode":"4600",
    "sg:province":"Li\u00e8ge",
    "sg:tags":[
        "item",
        "-",
        "business",
        "gift",
        "promotional"
    ],
    "wof:name":"La Cave A Vins",
    "wof:placetype":"venue"
},
  "geometry": {"coordinates":[5.6953639984,50.7326393127],"type":"Point"}
}