{
  "type": "Feature",
  "properties": {
    "iso:country":"BE",
    "sg:address":"Luikstraat 9",
    "sg:city":"Antwerpen",
    "sg:classifiers":[
        {
            "category":"Restaurant",
            "type":"Food & Drink"
        }
    ],
    "sg:phone":"+32 3 238 77 50",
    "sg:postcode":"2000",
    "sg:province":"Antwerpen",
    "wof:name":"Het Groene Paard",
    "wof:placetype":"venue"
},
  "geometry": {"coordinates":[4.3893179893,51.2103271484],"type":"Point"}
}