{
  "type": "Feature",
  "properties": {
    "iso:country":"BE",
    "sg:address":"Chauss\u00c9e De Dinant 10",
    "sg:city":"Yvoir",
    "sg:orig_category":"H\u00f4tels",
    "sg:phone":"+32 83 69 01 54",
    "sg:postcode":"5530",
    "sg:province":"Namur",
    "wof:name":"Hotellerie Du Bocq",
    "wof:placetype":"venue"
},
  "geometry": {"coordinates":[5.0079679489,50.322052002],"type":"Point"}
}