{
  "type": "Feature",
  "properties": {
    "addr:full":"Kammenstraat 24 Essen Antwerpen 2910",
    "addr:housenumber":"24",
    "addr:postcode":"2910",
    "addr:street":"Kammenstraat",
    "iso:country":"BE",
    "sg:address":"Kammenstraat 24",
    "sg:city":"Essen",
    "sg:orig_category":"Producteurs de l\u00e9gumes",
    "sg:phone":"+32 3 667 50 70",
    "sg:postcode":"2910",
    "sg:province":"Antwerpen",
    "wof:name":"Ronny Stuyts",
    "wof:placetype":"venue"
},
  "geometry": {"coordinates":[4.458217144,51.4660339355],"type":"Point"}
}