{
  "type": "Feature",
  "properties": {
    "addr:full":"Rue De Dampremy 68 Charleroi Hainaut 6000",
    "addr:housenumber":"68",
    "addr:postcode":"6000",
    "addr:street":"Rue De Dampremy;Hainaut",
    "iso:country":"BE",
    "sg:address":"Rue De Dampremy 68",
    "sg:city":"Charleroi",
    "sg:classifiers":[
        {
            "category":"Bars & Pubs",
            "type":"Food & Drink"
        }
    ],
    "sg:phone":"+32 71 31 72 51",
    "sg:postcode":"6000",
    "sg:province":"Hainaut",
    "wof:name":"Walter (chez)",
    "wof:placetype":"venue"
},
  "geometry": {"coordinates":[4.4398908615,50.4091453552],"type":"Point"}
}