{
  "type": "Feature",
  "properties": {
    "addr:full":"Riemsterweg 299 Bilzen Limburg 3740",
    "addr:housenumber":"299",
    "addr:postcode":"3740",
    "iso:country":"BE",
    "sg:address":"Riemsterweg 299",
    "sg:city":"Bilzen",
    "sg:classifiers":[
        {
            "category":"Bakery",
            "type":"Food & Drink"
        }
    ],
    "sg:phone":"+32 89 41 17 48",
    "sg:postcode":"3740",
    "sg:province":"Limburg",
    "sg:tags":[
        "confectioner",
        "baker"
    ],
    "wof:name":"Gijsen A",
    "wof:placetype":"venue"
},
  "geometry": {"coordinates":[5.5292901993,50.8601989746],"type":"Point"}
}