{
  "type": "Feature",
  "properties": {
    "addr:full":"Budelpoort 1 Hamont-achel (hamont) Limburg 3930",
    "addr:housenumber":"1",
    "addr:postcode":"3930",
    "addr:street":"Budelpoort",
    "iso:country":"BE",
    "sg:address":"Budelpoort 1",
    "sg:city":"Hamont-achel (hamont)",
    "sg:orig_category":"Ice-cream parlours",
    "sg:phone":"+32 11 62 21 57",
    "sg:postcode":"3930",
    "sg:province":"Limburg",
    "wof:name":"Fifty-fifty",
    "wof:placetype":"venue"
},
  "geometry": {"coordinates":[5.5450549126,51.2511863708],"type":"Point"}
}