{
  "type": "Feature",
  "properties": {
    "iso:country":"BE",
    "sg:address":"Rue Vandervelde 48bb",
    "sg:city":"Chapelle-lez-herlaimont",
    "sg:orig_category":"Pharmaciens",
    "sg:phone":"+32 64 44 23 69",
    "sg:postcode":"7160",
    "sg:province":"Hainaut",
    "wof:name":"Pharmacie Lamblin-lambot",
    "wof:placetype":"venue"
},
  "geometry": {"coordinates":[4.2879447937,50.4732894897],"type":"Point"}
}