{
  "type": "Feature",
  "properties": {
    "iso:country":"BE",
    "sg:address":"Turnhoutsebaan 5a",
    "sg:city":"Schilde",
    "sg:classifiers":[
        {
            "category":"Bars & Pubs",
            "type":"Food & Drink"
        }
    ],
    "sg:phone":"+32 3 353 02 17",
    "sg:postcode":"2970",
    "sg:province":"Antwerpen",
    "sg:tags":[
        "tavern"
    ],
    "wof:name":"Erian Bvba",
    "wof:placetype":"venue"
},
  "geometry": {"coordinates":[4.5546140671,51.2321624756],"type":"Point"}
}