{
  "type": "Feature",
  "properties": {
    "addr:full":"Nieuwstraat 170 Diepenbeek Limburg 3590",
    "addr:housenumber":"170",
    "addr:postcode":"3590",
    "addr:street":"Nieuwstraat",
    "iso:country":"BE",
    "sg:address":"Nieuwstraat 170",
    "sg:city":"Diepenbeek",
    "sg:orig_category":"Meubelzaken, woning- and keukeninrichting",
    "sg:phone":"+32 11 32 43 40",
    "sg:postcode":"3590",
    "sg:province":"Limburg",
    "wof:name":"Meubelen Neven",
    "wof:placetype":"venue"
},
  "geometry": {"coordinates":[5.4554390907,50.9257621765],"type":"Point"}
}