{
  "type": "Feature",
  "properties": {
    "iso:country":"BE",
    "sg:address":"Rue Des Bois 2",
    "sg:city":"Estinnes",
    "sg:orig_category":"Rundveehouders",
    "sg:phone":"+32 64 77 12 66",
    "sg:postcode":"7120",
    "sg:province":"Hainaut",
    "wof:name":"Edmond Hocquet",
    "wof:placetype":"venue"
},
  "geometry": {"coordinates":[4.1386408806,50.3413734436],"type":"Point"}
}