{
  "type": "Feature",
  "properties": {
    "addr:full":"Rue De Houffalize 29 Houffalize (nadrin) Luxembourg 6660",
    "addr:housenumber":"29",
    "addr:postcode":"6660",
    "addr:street":"Rue De Houffalize",
    "iso:country":"BE",
    "sg:address":"Rue De Houffalize 29",
    "sg:city":"Houffalize (nadrin)",
    "sg:classifiers":[
        {
            "category":"Retail",
            "subcategory":"Auto Repair",
            "type":"Services"
        }
    ],
    "sg:phone":"+32 84 44 41 09",
    "sg:postcode":"6660",
    "sg:province":"Luxembourg",
    "sg:tags":[
        "garage"
    ],
    "wof:name":"Herou (garage Du)",
    "wof:placetype":"venue"
},
  "geometry": {"coordinates":[5.7902050018,50.1322784424],"type":"Point"}
}