{
  "type": "Feature",
  "properties": {
    "addr:full":"Rue Kindergeluk 14 Sint-jans-molenbeek/molenbeek-saint-jean Bruxelles-Capitale 1080",
    "addr:housenumber":"14",
    "addr:postcode":"1080",
    "addr:street":"Rue Kindergeluk",
    "iso:country":"BE",
    "sg:address":"Rue Kindergeluk 14",
    "sg:city":"Sint-jans-molenbeek/molenbeek-saint-jean",
    "sg:orig_category":"Traitements param\u00e9dicaux",
    "sg:phone":"+32 475 56 77 45",
    "sg:postcode":"1080",
    "sg:province":"Bruxelles-Capitale",
    "wof:name":"V. Charlier",
    "wof:placetype":"venue"
},
  "geometry": {"coordinates":[4.3176851273,50.8530693054],"type":"Point"}
}