{
  "type": "Feature",
  "properties": {
    "addr:full":"Place Du Joncquois 1 Honnelles (erquennes) Hainaut 7387",
    "addr:housenumber":"1",
    "addr:postcode":"7387",
    "addr:street":"Place Du Joncquois;Erquennes Hainaut",
    "iso:country":"BE",
    "sg:address":"Place Du Joncquois 1",
    "sg:city":"Honnelles (erquennes)",
    "sg:classifiers":[
        {
            "category":"Bars & Pubs",
            "type":"Food & Drink"
        }
    ],
    "sg:phone":"+32 65 63 29 11",
    "sg:postcode":"7387",
    "sg:province":"Hainaut",
    "wof:name":"Salon (le)",
    "wof:placetype":"venue"
},
  "geometry": {"coordinates":[3.6959199905,50.3683853149],"type":"Point"}
}