{
  "type": "Feature",
  "properties": {
    "addr:full":"Koning Albertstraat 60 Kuurne West-Vlaanderen 8520",
    "addr:housenumber":"60",
    "addr:postcode":"8520",
    "addr:street":"Koning Albertstraat",
    "iso:country":"BE",
    "sg:address":"Koning Albertstraat 60",
    "sg:city":"Kuurne",
    "sg:orig_category":"Pi\u00e8ces and accessoires de v\u00e9hicules automobiles D\u00e9taillants en pi\u00e8ces and accessoires de voitures",
    "sg:phone":"+32 56 71 59 16",
    "sg:postcode":"8520",
    "sg:province":"West-Vlaanderen",
    "wof:name":"Autocenter Vale",
    "wof:placetype":"venue"
},
  "geometry": {"coordinates":[3.2906880379,50.8504257202],"type":"Point"}
}