{
  "type": "Feature",
  "properties": {
    "iso:country":"BE",
    "sg:address":"Verbindingsdok Oostkaai 13 Box 4",
    "sg:city":"Antwerpen",
    "sg:classifiers":[
        {
            "category":"Insurance",
            "subcategory":"Insurance Agent",
            "type":"Services"
        }
    ],
    "sg:phone":"+32 3 470 23 09",
    "sg:postcode":"2000",
    "sg:province":"Antwerpen",
    "sg:tags":[
        "-",
        "representative"
    ],
    "wof:name":"Lloyd's C/o Theunis & D'hoine",
    "wof:placetype":"venue"
},
  "geometry": {"coordinates":[4.4080381393,51.2302360535],"type":"Point"}
}