{
  "type": "Feature",
  "properties": {
    "addr:full":"Ambachtenlaan 15 Leuven (heverlee) Vlaams-Brabant 3001",
    "addr:housenumber":"15",
    "addr:postcode":"3001",
    "addr:street":"Ambachtenlaan",
    "iso:country":"BE",
    "sg:address":"Ambachtenlaan 15",
    "sg:city":"Leuven (heverlee)",
    "sg:classifiers":[
        {
            "category":"Structure",
            "subcategory":"Office Building",
            "type":"Public Place"
        }
    ],
    "sg:phone":"+32 16 38 69 00",
    "sg:postcode":"3001",
    "sg:province":"Vlaams-Brabant",
    "sg:tags":[
        "-",
        "type",
        "door",
        "sliding",
        "overhead"
    ],
    "wof:name":"Nice Belgium Nv Nv",
    "wof:placetype":"venue"
},
  "geometry": {"coordinates":[4.716053009,50.8479118347],"type":"Point"}
}