{
  "type": "Feature",
  "properties": {
    "iso:country":"BE",
    "sg:address":"Rue De L'h\u00f4tel Communal 3",
    "sg:city":"Gr\u00e2ce-hollogne (hollogne-aux-pierres)",
    "sg:classifiers":[
        {
            "category":"Restaurant",
            "type":"Food & Drink"
        }
    ],
    "sg:phone":"+32 4 234 60 34",
    "sg:postcode":"4460",
    "sg:province":"Li\u00e8ge",
    "wof:name":"Fontanella (la)",
    "wof:placetype":"venue"
},
  "geometry": {"coordinates":[5.478512764,50.6324501038],"type":"Point"}
}