{
  "type": "Feature",
  "properties": {
    "iso:country":"BE",
    "sg:address":"Rue Motte 17",
    "sg:city":"Beaumont (str\u00e9e)",
    "sg:classifiers":[
        {
            "category":"Professional",
            "subcategory":"Testing Lab",
            "type":"Services"
        }
    ],
    "sg:phone":"+32 71 53 32 15",
    "sg:postcode":"6511",
    "sg:province":"Hainaut",
    "sg:tags":[
        "chemist"
    ],
    "wof:name":"Chauss\u00e9e F",
    "wof:placetype":"venue"
},
  "geometry": {"coordinates":[4.2958140373,50.2766494751],"type":"Point"}
}