{
  "type": "Feature",
  "properties": {
    "addr:full":"Leo De Bethuneln 95 Aalst Oost-Vlaanderen 9300",
    "addr:housenumber":"95",
    "addr:postcode":"9300",
    "addr:street":"Leo",
    "iso:country":"BE",
    "sg:address":"Leo De Bethuneln 95",
    "sg:city":"Aalst",
    "sg:classifiers":[
        {
            "category":"Banks & Credit Unions",
            "subcategory":"Bank",
            "type":"Services"
        }
    ],
    "sg:phone":"+32 53 77 48 50",
    "sg:postcode":"9300",
    "sg:province":"Oost-Vlaanderen",
    "wof:name":"Aslk-cger Bank",
    "wof:placetype":"venue"
},
  "geometry": {"coordinates":[4.031733036,50.9311790466],"type":"Point"}
}