{
  "type": "Feature",
  "properties": {
    "addr:full":"Chauss\u00e9e D'aelbeke 255 Mouscron Hainaut 7700",
    "addr:housenumber":"255",
    "addr:postcode":"7700",
    "addr:street":"Chausse\u0301E D'Aelbeke",
    "iso:country":"BE",
    "sg:address":"Chauss\u00e9e D'aelbeke 255",
    "sg:city":"Mouscron",
    "sg:classifiers":[
        {
            "category":"Professional",
            "type":"Services"
        }
    ],
    "sg:phone":"+32 56 33 05 19",
    "sg:postcode":"7700",
    "sg:province":"Hainaut",
    "sg:tags":[
        "packing",
        "-"
    ],
    "wof:name":"Papier Hova Sprl",
    "wof:placetype":"venue"
},
  "geometry": {"coordinates":[3.2202301025,50.7593345642],"type":"Point"}
}