{
  "type": "Feature",
  "properties": {
    "iso:country":"BE",
    "sg:address":"Chemin De Bavay 17",
    "sg:city":"Mons",
    "sg:orig_category":"Artsen and specialisten",
    "sg:phone":"+32 65 31 14 35",
    "sg:postcode":"7033",
    "sg:province":"Hainaut",
    "wof:name":"Nadine Persenaire",
    "wof:placetype":"venue"
},
  "geometry": {"coordinates":[3.9447491169,50.4377937317],"type":"Point"}
}