{
  "type": "Feature",
  "properties": {
    "addr:full":"Alsembergsesteenweg 173 Halle Vlaams-Brabant 1501",
    "addr:housenumber":"173",
    "addr:postcode":"1501",
    "addr:street":"Alsembergsesteenweg",
    "iso:country":"BE",
    "sg:address":"Alsembergsesteenweg 173",
    "sg:city":"Halle",
    "sg:orig_category":"Supermarkten",
    "sg:postcode":"1501",
    "sg:province":"Vlaams-Brabant",
    "wof:name":"Aldi",
    "wof:placetype":"venue"
},
  "geometry": {"coordinates":[4.2496151924,50.7407913208],"type":"Point"}
}