{
  "type": "Feature",
  "properties": {
    "iso:country":"BE",
    "sg:address":"Tijmlaan 16",
    "sg:city":"Waregem",
    "sg:orig_category":"Drukkerijen and copyshops Kleding, schoenen and accessoires Gh",
    "sg:phone":"+32 56 61 13 56",
    "sg:postcode":"8790",
    "sg:province":"West-Vlaanderen",
    "wof:name":"T-fashion",
    "wof:placetype":"venue"
},
  "geometry": {"coordinates":[3.4150500298,50.8937988281],"type":"Point"}
}