{
  "type": "Feature",
  "properties": {
    "addr:full":"Rue Berckmans 148 Bruxelles (saint-gilles) Bruxelles-Capitale 1060",
    "addr:housenumber":"148",
    "addr:postcode":"1060",
    "addr:street":"Rue Berckmans",
    "iso:country":"BE",
    "sg:address":"Rue Berckmans 148",
    "sg:city":"Bruxelles (saint-gilles)",
    "sg:classifiers":[
        {
            "category":"Organizations",
            "subcategory":"Professional Association",
            "type":"Services"
        }
    ],
    "sg:phone":"+32 2 534 26 81",
    "sg:postcode":"1060",
    "sg:province":"Bruxelles-Capitale",
    "sg:tags":[
        "trade-union",
        "federation"
    ],
    "wof:name":"Fondation Travail & Sant\u00e9",
    "wof:placetype":"venue"
},
  "geometry": {"coordinates":[4.349047184,50.832447052],"type":"Point"}
}