{
  "type": "Feature",
  "properties": {
    "addr:full":"Rue De La Siroperie 20 Eghez\u00e9e (liernu) Namur 5310",
    "addr:housenumber":"20",
    "addr:postcode":"5310",
    "addr:street":"Rue De La Siroperie;Liernu",
    "iso:country":"BE",
    "sg:address":"Rue De La Siroperie 20",
    "sg:city":"Eghez\u00e9e (liernu)",
    "sg:orig_category":"Ice-cream parlours",
    "sg:phone":"+32 81 65 68 86",
    "sg:postcode":"5310",
    "sg:province":"Namur",
    "wof:name":"Marchal M",
    "wof:placetype":"venue"
},
  "geometry": {"coordinates":[4.8352308273,50.5833244324],"type":"Point"}
}