{
  "type": "Feature",
  "properties": {
    "addr:full":"Roeselaarsestraat 503 Izegem West-Vlaanderen 8870",
    "addr:housenumber":"503",
    "addr:postcode":"8870",
    "addr:street":"Roeselaarsestraat",
    "iso:country":"BE",
    "sg:address":"Roeselaarsestraat 503",
    "sg:city":"Izegem",
    "sg:classifiers":[
        {
            "category":"Building & Trades",
            "subcategory":"Landfill",
            "type":"Services"
        }
    ],
    "sg:phone":"+32 3 321 17 26",
    "sg:postcode":"8870",
    "sg:province":"West-Vlaanderen",
    "sg:tags":[
        "floor",
        "laying",
        "parquet"
    ],
    "wof:name":"Parket Brabo Nv",
    "wof:placetype":"venue"
},
  "geometry": {"coordinates":[4.455947876,51.2061462402],"type":"Point"}
}