{
  "type": "Feature",
  "properties": {
    "addr:full":"Rue Neuve 111 Boussu Hainaut 7300",
    "addr:housenumber":"111",
    "addr:postcode":"7300",
    "addr:street":"Rue Neuve",
    "iso:country":"BE",
    "sg:address":"Rue Neuve 111",
    "sg:city":"Boussu",
    "sg:orig_category":"Produits surgel\u00e9s Gr",
    "sg:phone":"+32 65 78 79 54",
    "sg:postcode":"7300",
    "sg:province":"Hainaut",
    "wof:name":"Covee",
    "wof:placetype":"venue"
},
  "geometry": {"coordinates":[3.7926309109,50.4299240112],"type":"Point"}
}