{
  "type": "Feature",
  "properties": {
    "addr:full":"Oordegemsesteenweg 186 Wetteren Oost-Vlaanderen 9230",
    "addr:housenumber":"186",
    "addr:postcode":"9230",
    "addr:street":"Oordegemsesteenweg",
    "iso:country":"BE",
    "sg:address":"Oordegemsesteenweg 186",
    "sg:city":"Wetteren",
    "sg:classifiers":[
        {
            "category":"Shopping",
            "subcategory":"Baby Store",
            "type":"Retail Goods"
        }
    ],
    "sg:phone":"+32 9 369 44 90",
    "sg:postcode":"9230",
    "sg:province":"Oost-Vlaanderen",
    "sg:tags":[
        "hostess"
    ],
    "wof:name":"Sunny Side Up Bvba",
    "wof:placetype":"venue"
},
  "geometry": {"coordinates":[3.8856561184,50.9967346191],"type":"Point"}
}