{
  "type": "Feature",
  "properties": {
    "iso:country":"BE",
    "sg:address":"Rysseveldstraat 59",
    "sg:city":"Staden",
    "sg:classifiers":[
        {
            "category":"Home & Garden",
            "subcategory":"Carpets & Floor Coverings",
            "type":"Retail Goods"
        }
    ],
    "sg:phone":"+32 51 70 58 20",
    "sg:postcode":"8840",
    "sg:province":"West-Vlaanderen",
    "sg:tags":[
        "layer",
        "mosaicists"
    ],
    "wof:name":"Bernaert R",
    "wof:placetype":"venue"
},
  "geometry": {"coordinates":[3.0159959793,50.9684524536],"type":"Point"}
}