{
  "type": "Feature",
  "properties": {
    "iso:country":"BE",
    "sg:address":"August Van Landeghemstraat 7",
    "sg:city":"Willebroek",
    "sg:orig_category":"Opticiens",
    "sg:phone":"+32 3 886 63 30",
    "sg:postcode":"2830",
    "sg:province":"Antwerpen",
    "wof:name":"Trioptic",
    "wof:placetype":"venue"
},
  "geometry": {"coordinates":[4.3602571487,51.0609512329],"type":"Point"}
}