{
  "type": "Feature",
  "properties": {
    "addr:full":"Brielstraat 10 Beveren (melsele) Oost-Vlaanderen 9120",
    "addr:housenumber":"10",
    "addr:postcode":"9120",
    "addr:street":"Brielstraat",
    "iso:country":"BE",
    "sg:address":"Brielstraat 10",
    "sg:city":"Beveren (melsele)",
    "sg:classifiers":[
        {
            "category":"Building & Trades",
            "subcategory":"Landscaping Services",
            "type":"Services"
        }
    ],
    "sg:phone":"+32 3 755 39 12",
    "sg:postcode":"9120",
    "sg:province":"Oost-Vlaanderen",
    "sg:tags":[
        "gardening",
        "garden",
        "maintenance"
    ],
    "wof:name":"Laureys K",
    "wof:placetype":"venue"
},
  "geometry": {"coordinates":[4.2779870033,51.2322616577],"type":"Point"}
}