{
  "type": "Feature",
  "properties": {
    "addr:full":"Martelarenstraat 81 Mol Antwerpen 2400",
    "addr:housenumber":"81",
    "addr:postcode":"2400",
    "addr:street":"Martelarenstraat",
    "iso:country":"BE",
    "sg:address":"Martelarenstraat 81",
    "sg:city":"Mol",
    "sg:orig_category":"Industri\u00eble and commerci\u00eble bouw",
    "sg:phone":"+32 14 31 11 05",
    "sg:postcode":"2400",
    "sg:province":"Antwerpen",
    "wof:name":"Leon Heylen",
    "wof:placetype":"venue"
},
  "geometry": {"coordinates":[5.0982937813,51.1862487793],"type":"Point"}
}