{
  "type": "Feature",
  "properties": {
    "iso:country":"BE",
    "sg:address":"Warmifontaine 51",
    "sg:city":"Neufchateau",
    "sg:orig_category":"Boucheries",
    "sg:phone":"+32 61 27 72 65",
    "sg:postcode":"6840",
    "sg:province":"Luxembourg",
    "wof:name":"Evrard Noel",
    "wof:placetype":"venue"
},
  "geometry": {"coordinates":[5.4346451759,49.8411598206],"type":"Point"}
}