{
  "type": "Feature",
  "properties": {
    "addr:full":"Lange Zoutstraat 32 Aalst Oost-Vlaanderen 9300",
    "addr:housenumber":"32",
    "addr:postcode":"9300",
    "addr:street":"Lange Zoutstraat",
    "iso:country":"BE",
    "sg:address":"Lange Zoutstraat 32",
    "sg:city":"Aalst",
    "sg:orig_category":"V\u00eatements pour b\u00e9b\u00e9s and enfants",
    "sg:phone":"+32 53 21 34 73",
    "sg:postcode":"9300",
    "sg:province":"Oost-Vlaanderen",
    "wof:name":"Kid Cool",
    "wof:placetype":"venue"
},
  "geometry": {"coordinates":[4.0397481918,50.9370994568],"type":"Point"}
}