{
  "type": "Feature",
  "properties": {
    "iso:country":"BE",
    "sg:address":"Zevekoteheirweg 75",
    "sg:city":"Gistel",
    "sg:classifiers":[
        {
            "category":"Banks & Credit Unions",
            "subcategory":"Investment Brokerage",
            "type":"Services"
        }
    ],
    "sg:phone":"+32 59 27 69 47",
    "sg:postcode":"8470",
    "sg:province":"West-Vlaanderen",
    "sg:tags":[
        "ladies'",
        "tailor",
        "tailoresses",
        "-",
        "clothing"
    ],
    "wof:name":"Buyssens M",
    "wof:placetype":"venue"
},
  "geometry": {"coordinates":[2.9714570045,51.1515159607],"type":"Point"}
}