{
  "type": "Feature",
  "properties": {
    "iso:country":"BE",
    "sg:address":"Hezewijk 18",
    "sg:city":"Olen",
    "sg:classifiers":[
        {
            "category":"Personal",
            "type":"Services"
        }
    ],
    "sg:phone":"+32 14 26 52 56",
    "sg:postcode":"2250",
    "sg:province":"Antwerpen",
    "sg:tags":[
        "party",
        "planning"
    ],
    "wof:name":"De Vlier",
    "wof:placetype":"venue"
},
  "geometry": {"coordinates":[4.8446707726,51.1465797424],"type":"Point"}
}