{
  "type": "Feature",
  "properties": {
    "addr:full":"Merodestraat 37 Duffel Antwerpen 2570",
    "addr:housenumber":"37",
    "addr:postcode":"2570",
    "addr:street":"Merodestraat",
    "iso:country":"BE",
    "sg:address":"Merodestraat 37",
    "sg:city":"Duffel",
    "sg:classifiers":[
        {
            "category":"Health Services",
            "subcategory":"Dentist",
            "type":"Services"
        }
    ],
    "sg:phone":"+32 15 31 21 59",
    "sg:postcode":"2570",
    "sg:province":"Antwerpen",
    "wof:name":"Coosemans Bea",
    "wof:placetype":"venue"
},
  "geometry": {"coordinates":[4.5013799667,51.0975456238],"type":"Point"}
}