{
  "type": "Feature",
  "properties": {
    "addr:full":"Crapaurue 164 Verviers Li\u00e8ge 4800",
    "addr:housenumber":"164",
    "addr:postcode":"4800",
    "iso:country":"BE",
    "sg:address":"Crapaurue 164",
    "sg:city":"Verviers",
    "sg:classifiers":[
        {
            "category":"Food & Beverages",
            "subcategory":"Fruits & Vegetables",
            "type":"Retail Goods"
        }
    ],
    "sg:phone":"+32 87 31 79 88",
    "sg:postcode":"4800",
    "sg:province":"Li\u00e8ge",
    "sg:tags":[
        "l\u00e9gumes"
    ],
    "wof:name":"Primafruit",
    "wof:placetype":"venue"
},
  "geometry": {"coordinates":[5.862596035,50.5927772522],"type":"Point"}
}