{
  "type": "Feature",
  "properties": {
    "iso:country":"BE",
    "sg:address":"De Keyserlei 31",
    "sg:city":"Antwerpen",
    "sg:classifiers":[
        {
            "category":"Restaurant",
            "type":"Food & Drink"
        }
    ],
    "sg:phone":"+32 3 225 22 25",
    "sg:postcode":"2018",
    "sg:province":"Antwerpen",
    "wof:name":"Bella Vista",
    "wof:placetype":"venue"
},
  "geometry": {"coordinates":[4.4183859825,51.2176895142],"type":"Point"}
}