{
  "type": "Feature",
  "properties": {
    "addr:full":"Boudewijn Hapkenstraat 47 Zedelgem West-Vlaanderen 8210",
    "addr:housenumber":"47",
    "addr:postcode":"8210",
    "addr:street":"Hapkenstraat",
    "iso:country":"BE",
    "sg:address":"Boudewijn Hapkenstraat 47",
    "sg:city":"Zedelgem",
    "sg:orig_category":"Sportclubs Sportterreinen and installaties behalve sportcentra",
    "sg:phone":"+32 50 27 76 89",
    "sg:postcode":"8210",
    "sg:province":"West-Vlaanderen",
    "wof:name":"Sporda Dames V.v.",
    "wof:placetype":"venue"
},
  "geometry": {"coordinates":[3.1458399296,51.1376457214],"type":"Point"}
}