{
  "type": "Feature",
  "properties": {
    "iso:country":"BE",
    "sg:address":"Kaarderslaan 4",
    "sg:city":"Lokeren",
    "sg:classifiers":[
        {
            "category":"Food & Beverages",
            "subcategory":"Meat & Fish",
            "type":"Retail Goods"
        }
    ],
    "sg:phone":"+32 9 348 45 09",
    "sg:postcode":"9160",
    "sg:province":"Oost-Vlaanderen",
    "sg:tags":[
        "bacon",
        "ham"
    ],
    "wof:name":"Meat Supply Nv",
    "wof:placetype":"venue"
},
  "geometry": {"coordinates":[4.0190248489,51.1100502014],"type":"Point"}
}