{
  "type": "Feature",
  "properties": {
    "iso:country":"BE",
    "sg:address":"Brusselsesteenweg 412",
    "sg:city":"Gent (gentbrugge)",
    "sg:classifiers":[
        {
            "category":"Bars & Pubs",
            "type":"Food & Drink"
        }
    ],
    "sg:phone":"+32 9 232 14 79",
    "sg:postcode":"9050",
    "sg:province":"Oost-Vlaanderen",
    "wof:name":"Minty",
    "wof:placetype":"venue"
},
  "geometry": {"coordinates":[3.7457699776,51.0392189026],"type":"Point"}
}