{
  "type": "Feature",
  "properties": {
    "iso:country":"BE",
    "sg:address":"Eekhoornlaan 12",
    "sg:city":"Brecht",
    "sg:orig_category":"Non-Classified Establishments",
    "sg:phone":"+32 3 646 78 91",
    "sg:postcode":"2960",
    "sg:province":"Antwerpen",
    "wof:name":"Qmc Chemtrade",
    "wof:placetype":"venue"
},
  "geometry": {"coordinates":[4.5902180672,51.327041626],"type":"Point"}
}