{
  "type": "Feature",
  "properties": {
    "iso:country":"BE",
    "sg:address":"Hollebekestraat 8",
    "sg:city":"Heuvelland",
    "sg:orig_category":"Rundveehouders Varkenskwekers",
    "sg:phone":"+32 57 44 45 35",
    "sg:postcode":"8953",
    "sg:province":"West-Vlaanderen",
    "wof:name":"Etienne Gaudissabois",
    "wof:placetype":"venue"
},
  "geometry": {"coordinates":[2.8917529583,50.791267395],"type":"Point"}
}