{
  "type": "Feature",
  "properties": {
    "iso:country":"BE",
    "sg:address":"Chauss\u00c9e Reine Astrid 24",
    "sg:city":"Braine-l'alleud",
    "sg:orig_category":"Opticiens. Articles m\u00e9dicaux and orthop\u00e9diques",
    "sg:phone":"+32 2 384 06 19",
    "sg:postcode":"1420",
    "sg:province":"Brabant Wallon",
    "wof:name":"Decarnieres",
    "wof:placetype":"venue"
},
  "geometry": {"coordinates":[-0.7711730003,47.3931159973],"type":"Point"}
}