{
  "type": "Feature",
  "properties": {
    "addr:full":"Waverstraat 3a Aalst (moorsel) Oost-Vlaanderen 9310",
    "addr:housenumber":"3a",
    "addr:postcode":"9310",
    "addr:street":"Waverstraat;Moorsel Oost-Vlaanderen",
    "iso:country":"BE",
    "sg:address":"Waverstraat 3a",
    "sg:city":"Aalst (moorsel)",
    "sg:classifiers":[
        {
            "category":"Utilities",
            "subcategory":"Telephone",
            "type":"Services"
        }
    ],
    "sg:phone":"+32 53 21 59 53",
    "sg:postcode":"9310",
    "sg:province":"Oost-Vlaanderen",
    "sg:tags":[
        "karting",
        "accessory"
    ],
    "wof:name":"Aalst Indoorkarting",
    "wof:placetype":"venue"
},
  "geometry": {"coordinates":[4.0996470451,50.945400238],"type":"Point"}
}