{
  "type": "Feature",
  "properties": {
    "iso:country":"BE",
    "sg:address":"Gaarveldstraat 111",
    "sg:city":"Hasselt",
    "sg:orig_category":"Verplichte sociale verzekeringen",
    "sg:phone":"+32 11 27 15 47",
    "sg:postcode":"3500",
    "sg:province":"Limburg",
    "wof:name":"Christelijke Mutualiteit",
    "wof:placetype":"venue"
},
  "geometry": {"coordinates":[5.325220108,50.9260025024],"type":"Point"}
}