{
  "type": "Feature",
  "properties": {
    "iso:country":"BE",
    "sg:address":"Tomstraat 49",
    "sg:city":"Sint-truiden (brustem)",
    "sg:classifiers":[
        {
            "category":"Home & Garden",
            "subcategory":"Kitchen Supply",
            "type":"Retail Goods"
        }
    ],
    "sg:phone":"+32 11 68 99 42",
    "sg:postcode":"3800",
    "sg:province":"Limburg",
    "sg:tags":[
        "installation"
    ],
    "wof:name":"Kempenaers Nv",
    "wof:placetype":"venue"
},
  "geometry": {"coordinates":[5.229183197,50.8040962219],"type":"Point"}
}