{
  "type": "Feature",
  "properties": {
    "addr:full":"Rue Albert Meunier 104 Oudergem/auderghem Bruxelles-Capitale 1160",
    "addr:housenumber":"104",
    "addr:postcode":"1160",
    "addr:street":"Rue Albert Meunier;/",
    "iso:country":"BE",
    "sg:address":"Rue Albert Meunier 104",
    "sg:city":"Oudergem/auderghem",
    "sg:orig_category":"M\u00e9decins and sp\u00e9cialistes",
    "sg:phone":"+32 2 672 69 53",
    "sg:postcode":"1160",
    "sg:province":"Bruxelles-Capitale",
    "wof:name":"F. Donnelly",
    "wof:placetype":"venue"
},
  "geometry": {"coordinates":[4.4368958473,50.8097991943],"type":"Point"}
}