{
  "type": "Feature",
  "properties": {
    "addr:full":"Rue De La Brasserie 4 Assesse Namur 5330",
    "addr:housenumber":"4",
    "addr:postcode":"5330",
    "addr:street":"Rue De La Brasserie",
    "iso:country":"BE",
    "sg:address":"Rue De La Brasserie 4",
    "sg:city":"Assesse",
    "sg:orig_category":"Artsen and specialisten",
    "sg:phone":"+32 83 65 52 74",
    "sg:postcode":"5330",
    "sg:province":"Namur",
    "wof:name":"Pierre Canivet",
    "wof:placetype":"venue"
},
  "geometry": {"coordinates":[5.0249438286,50.3699684143],"type":"Point"}
}