{
  "type": "Feature",
  "properties": {
    "addr:full":"Avenue Du Roi Albert 181 Bruxelles Bruxelles-Capitale 1120",
    "addr:housenumber":"181",
    "addr:postcode":"1120",
    "addr:street":"Avenue Du Roi Albert",
    "iso:country":"BE",
    "sg:address":"Avenue Du Roi Albert 181",
    "sg:city":"Bruxelles",
    "sg:classifiers":[
        {
            "category":"Education",
            "subcategory":"School",
            "type":"Public Place"
        }
    ],
    "sg:phone":"+32 2 262 03 20",
    "sg:postcode":"1120",
    "sg:province":"Bruxelles-Capitale",
    "sg:tags":[
        "primary"
    ],
    "wof:name":"Medisch Pedagogisch Instituut Van Het Gemeenschapsonderwijs-heemschool \u00e9\u00e9n",
    "wof:placetype":"venue"
},
  "geometry": {"coordinates":[4.3772721291,50.8938407898],"type":"Point"}
}