{
  "type": "Feature",
  "properties": {
    "addr:full":"Baanvelden 2 Sint-katelijne-waver Antwerpen 2860",
    "addr:housenumber":"2",
    "addr:postcode":"2860",
    "addr:street":"Baanvelden",
    "iso:country":"BE",
    "sg:address":"Baanvelden 2",
    "sg:city":"Sint-katelijne-waver",
    "sg:orig_category":"Producteurs de l\u00e9gumes",
    "sg:phone":"+32 15 55 16 96",
    "sg:postcode":"2860",
    "sg:province":"Antwerpen",
    "wof:name":"Marcel Nauwelaerts",
    "wof:placetype":"venue"
},
  "geometry": {"coordinates":[4.5341367722,51.0491409302],"type":"Point"}
}