{
  "type": "Feature",
  "properties": {
    "iso:country":"BE",
    "sg:address":"Krombekeplein 22",
    "sg:city":"Poperinge (krombeke)",
    "sg:classifiers":[
        {
            "category":"Building & Trades",
            "subcategory":"Landscaping Services",
            "type":"Services"
        }
    ],
    "sg:phone":"+32 57 40 01 18",
    "sg:postcode":"8972",
    "sg:province":"West-Vlaanderen",
    "sg:tags":[
        "slaughterer"
    ],
    "wof:name":"Hardeman J",
    "wof:placetype":"venue"
},
  "geometry": {"coordinates":[2.6881039143,50.9150238037],"type":"Point"}
}