{
  "type": "Feature",
  "properties": {
    "addr:full":"Groenstraat 2 Izegem West-Vlaanderen 8870",
    "addr:housenumber":"2",
    "addr:postcode":"8870",
    "addr:street":"Groenstraat",
    "iso:country":"BE",
    "sg:address":"Groenstraat 2",
    "sg:city":"Izegem",
    "sg:orig_category":"Fiduciairies",
    "sg:phone":"+32 51 22 32 00",
    "sg:postcode":"8870",
    "sg:province":"West-Vlaanderen",
    "wof:name":"Wullaert B",
    "wof:placetype":"venue"
},
  "geometry": {"coordinates":[3.2189900875,50.9161262512],"type":"Point"}
}