{
  "type": "Feature",
  "properties": {
    "iso:country":"BE",
    "sg:address":"Rue Du Bois Des Pauvres 3",
    "sg:city":"Chastre (chastre-villeroux-blanmont)",
    "sg:classifiers":[
        {
            "category":"Home & Garden",
            "subcategory":"Building Materials",
            "type":"Retail Goods"
        }
    ],
    "sg:phone":"+32 10 65 07 43",
    "sg:postcode":"1450",
    "sg:province":"Brabant Wallon",
    "sg:tags":[
        "bathroom",
        "installation",
        "accessory"
    ],
    "wof:name":"Sani-foucart Sc",
    "wof:placetype":"venue"
},
  "geometry": {"coordinates":[4.6116552353,50.6081352234],"type":"Point"}
}