{
  "type": "Feature",
  "properties": {
    "iso:country":"BE",
    "sg:address":"Beisbroekdreef 25",
    "sg:city":"Brugge",
    "sg:classifiers":[
        {
            "category":"Banks & Credit Unions",
            "subcategory":"Investment Brokerage",
            "type":"Services"
        }
    ],
    "sg:phone":"+32 50 39 10 15",
    "sg:postcode":"8200",
    "sg:province":"West-Vlaanderen",
    "sg:tags":[
        "pension"
    ],
    "wof:name":"Rita Louwyck",
    "wof:placetype":"venue"
},
  "geometry": {"coordinates":[3.1904699802,51.1992111206],"type":"Point"}
}