{
  "type": "Feature",
  "properties": {
    "iso:country":"BE",
    "sg:address":"Prins De Salmlaan 2",
    "sg:city":"Overijse",
    "sg:classifiers":[
        {
            "category":"Government",
            "subcategory":"Office",
            "type":"Public Place"
        }
    ],
    "sg:phone":"+32 2 687 67 18",
    "sg:postcode":"3090",
    "sg:province":"Vlaams-Brabant",
    "sg:tags":[
        "chamber",
        "industry",
        "commerce"
    ],
    "wof:name":"Belgian-american Chamber Of Commerce",
    "wof:placetype":"venue"
},
  "geometry": {"coordinates":[4.5051112175,50.743522644],"type":"Point"}
}