{
  "type": "Feature",
  "properties": {
    "iso:country":"BE",
    "sg:address":"Rue Des Ardennes 1",
    "sg:city":"Beauraing",
    "sg:classifiers":[
        {
            "category":"Shopping",
            "subcategory":"Florist",
            "type":"Retail Goods"
        }
    ],
    "sg:phone":"+32 82 71 19 30",
    "sg:postcode":"5570",
    "sg:province":"Namur",
    "wof:name":"Fleurs De Fran\u00e7oise (les)",
    "wof:placetype":"venue"
},
  "geometry": {"coordinates":[4.9576969147,50.1081123352],"type":"Point"}
}