{
  "type": "Feature",
  "properties": {
    "iso:country":"BE",
    "sg:address":"Kerkhovenakker Laan A 6",
    "sg:city":"Brecht",
    "sg:classifiers":[
        {
            "category":"Farming",
            "subcategory":"Livestock Farm",
            "type":"Manufacturing & Wholesale Goods"
        }
    ],
    "sg:phone":"+32 3 313 84 72",
    "sg:postcode":"2960",
    "sg:province":"Antwerpen",
    "sg:tags":[
        "buyer"
    ],
    "wof:name":"De Meester E",
    "wof:placetype":"venue"
},
  "geometry": {"coordinates":[4.6454548836,51.3532829285],"type":"Point"}
}