{
  "type": "Feature",
  "properties": {
    "iso:country":"BE",
    "sg:address":"Elleboogstraat 7",
    "sg:city":"Willebroek (blaasveld)",
    "sg:classifiers":[
        {
            "category":"Professional",
            "subcategory":"Management & Consulting",
            "type":"Services"
        }
    ],
    "sg:phone":"+32 3 866 16 42",
    "sg:postcode":"2830",
    "sg:province":"Antwerpen",
    "sg:tags":[
        "consultant"
    ],
    "wof:name":"A B Extra",
    "wof:placetype":"venue"
},
  "geometry": {"coordinates":[4.3820447922,51.0471839905],"type":"Point"}
}