{
  "type": "Feature",
  "properties": {
    "iso:country":"BE",
    "sg:address":"Warnach 23bb",
    "sg:city":"Fauvillers",
    "sg:orig_category":"Eleveurs and marchands de porcs. Eleveurs de bovins",
    "sg:phone":"+32 63 60 07 26",
    "sg:postcode":"6637",
    "sg:province":"Luxembourg",
    "wof:name":"Leroy Raym & Leroy Jose",
    "wof:placetype":"venue"
},
  "geometry": {"coordinates":[5.7244701385,49.8651008606],"type":"Point"}
}