{
  "type": "Feature",
  "properties": {
    "addr:full":"Pastoor Wuytsstraat 52 Mol Antwerpen 2400",
    "addr:housenumber":"52",
    "addr:postcode":"2400",
    "addr:street":"Pastoor Wuytsstraat",
    "iso:country":"BE",
    "sg:address":"Pastoor Wuytsstraat 52",
    "sg:city":"Mol",
    "sg:classifiers":[
        {
            "category":"Building & Trades",
            "subcategory":"Construction",
            "type":"Services"
        }
    ],
    "sg:phone":"+32 14 71 65 40",
    "sg:postcode":"2400",
    "sg:province":"Antwerpen",
    "sg:tags":[
        "carpenter"
    ],
    "wof:name":"Vreys J",
    "wof:placetype":"venue"
},
  "geometry": {"coordinates":[5.1355051994,51.2099266052],"type":"Point"}
}