{
  "type": "Feature",
  "properties": {
    "addr:full":"Chauss\u00e9e De Wavre 150-1 Box 2 Perwez Brabant Wallon 1360",
    "addr:housenumber":"150-1;2",
    "addr:postcode":"1360",
    "addr:street":"Chausse\u0301E De Wavre;Box",
    "iso:country":"BE",
    "sg:address":"Chauss\u00e9e De Wavre 150-1 Box 2",
    "sg:city":"Perwez",
    "sg:classifiers":[
        {
            "category":"Insurance",
            "subcategory":"Insurance Agent",
            "type":"Services"
        }
    ],
    "sg:phone":"+32 81 65 86 15",
    "sg:postcode":"1360",
    "sg:province":"Brabant Wallon",
    "sg:tags":[
        "broker"
    ],
    "wof:name":"Libert Hussin",
    "wof:placetype":"venue"
},
  "geometry": {"coordinates":[4.8033800125,50.6295204163],"type":"Point"}
}