{
  "type": "Feature",
  "properties": {
    "iso:country":"BE",
    "sg:address":"Rue Hayeneux 176",
    "sg:city":"Herstal",
    "sg:orig_category":"Chaussures",
    "sg:phone":"+32 4 240 26 18",
    "sg:postcode":"4040",
    "sg:province":"Li\u00e8ge",
    "wof:name":"Promoshoe",
    "wof:placetype":"venue"
},
  "geometry": {"coordinates":[5.6145191193,50.6560440063],"type":"Point"}
}