{
  "type": "Feature",
  "properties": {
    "iso:country":"BE",
    "sg:address":"Zuidlaan 25-27",
    "sg:city":"Brussel/bruxelles",
    "sg:orig_category":"Politieke organisaties",
    "sg:phone":"+32 2 513 08 88",
    "sg:postcode":"1000",
    "sg:province":"Bruxelles-Capitale",
    "wof:name":"Vivant",
    "wof:placetype":"venue"
},
  "geometry": {"coordinates":[4.3399758339,50.8430137634],"type":"Point"}
}