{
  "type": "Feature",
  "properties": {
    "addr:full":"Kettingbrugweg 36 Bocholt Limburg 3950",
    "addr:housenumber":"36",
    "addr:postcode":"3950",
    "addr:street":"Kettingbrugweg",
    "iso:country":"BE",
    "sg:address":"Kettingbrugweg 36",
    "sg:city":"Bocholt",
    "sg:classifiers":[
        {
            "category":"Shopping",
            "type":"Retail Goods"
        }
    ],
    "sg:phone":"+32 89 46 93 90",
    "sg:postcode":"3950",
    "sg:province":"Limburg",
    "sg:tags":[
        "metallurgy",
        "finished",
        "-",
        "metalworking",
        "metallic"
    ],
    "wof:name":"Ajk Tankbouw Nv",
    "wof:placetype":"venue"
},
  "geometry": {"coordinates":[5.5217380524,51.2119522095],"type":"Point"}
}