{
  "type": "Feature",
  "properties": {
    "iso:country":"BE",
    "sg:address":"Rue Tierne \u00c0 Tartes 7",
    "sg:city":"La Louviere",
    "sg:orig_category":"Woningbouw",
    "sg:phone":"+32 64 28 08 39",
    "sg:postcode":"7100",
    "sg:province":"Hainaut",
    "wof:name":"Francesco Micciche",
    "wof:placetype":"venue"
},
  "geometry": {"coordinates":[4.2066922188,50.4881362915],"type":"Point"}
}