{
  "type": "Feature",
  "properties": {
    "addr:full":"Duivenstraat 67 Wervik West-Vlaanderen 8940",
    "addr:housenumber":"67",
    "addr:postcode":"8940",
    "addr:street":"Duivenstraat",
    "iso:country":"BE",
    "sg:address":"Duivenstraat 67",
    "sg:city":"Wervik",
    "sg:classifiers":[
        {
            "category":"Shopping",
            "subcategory":"Hobbies, Toys, & Games",
            "type":"Retail Goods"
        }
    ],
    "sg:phone":"+32 56 51 02 10",
    "sg:postcode":"8940",
    "sg:province":"West-Vlaanderen",
    "sg:tags":[
        "toy",
        "-"
    ],
    "wof:name":"Harlekijn (de)",
    "wof:placetype":"venue"
},
  "geometry": {"coordinates":[3.0397789478,50.780796051],"type":"Point"}
}