{
  "type": "Feature",
  "properties": {
    "iso:country":"BE",
    "sg:address":"Heirbaan 45",
    "sg:city":"Beveren",
    "sg:orig_category":"Fruitteelt",
    "sg:phone":"+32 3 775 58 65",
    "sg:postcode":"9120",
    "sg:province":"Oost-Vlaanderen",
    "wof:name":"Robert Verhelst",
    "wof:placetype":"venue"
},
  "geometry": {"coordinates":[4.2595458031,51.1825675964],"type":"Point"}
}