{
  "type": "Feature",
  "properties": {
    "addr:full":"Boerenkrijglaan 35 Berlare (overmere) Oost-Vlaanderen 9290",
    "addr:housenumber":"35",
    "addr:postcode":"9290",
    "addr:street":"Boerenkrijglaan",
    "iso:country":"BE",
    "sg:address":"Boerenkrijglaan 35",
    "sg:city":"Berlare (overmere)",
    "sg:classifiers":[
        {
            "category":"Banks & Credit Unions",
            "subcategory":"Investment Brokerage",
            "type":"Services"
        }
    ],
    "sg:phone":"+32 9 367 89 12",
    "sg:postcode":"9290",
    "sg:province":"Oost-Vlaanderen",
    "sg:tags":[
        "fence"
    ],
    "wof:name":"Goossens",
    "wof:placetype":"venue"
},
  "geometry": {"coordinates":[4.005710125,51.0165214539],"type":"Point"}
}