{
  "type": "Feature",
  "properties": {
    "iso:country":"BE",
    "sg:address":"Rue Du Cimeti\u00c8re 10",
    "sg:city":"Braine-le-chateau",
    "sg:orig_category":"Installatie van houten of kunststof schrijnwerk",
    "sg:phone":"+32 2 366 24 32",
    "sg:postcode":"1440",
    "sg:province":"Brabant Wallon",
    "wof:name":"Luyckx J",
    "wof:placetype":"venue"
},
  "geometry": {"coordinates":[4.2664141655,50.6729431152],"type":"Point"}
}