{
  "type": "Feature",
  "properties": {
    "addr:full":"Boulevard L\u00c9opold Ii 250 Koekelberg Bruxelles-Capitale 1081",
    "addr:housenumber":"250",
    "addr:postcode":"1081",
    "addr:street":"Boulevard Le\u0301Opold Ii",
    "iso:country":"BE",
    "sg:address":"Boulevard L\u00c9opold Ii 250",
    "sg:city":"Koekelberg",
    "sg:orig_category":"Activit\u00e9s r\u00e9cr\u00e9atives diverses",
    "sg:phone":"+32 2 414 24 26",
    "sg:postcode":"1081",
    "sg:province":"Bruxelles-Capitale",
    "wof:name":"Maison Stepman",
    "wof:placetype":"venue"
},
  "geometry": {"coordinates":[4.3321099281,50.8624420166],"type":"Point"}
}