{
  "type": "Feature",
  "properties": {
    "iso:country":"BE",
    "sg:address":"Rue De Samme 163",
    "sg:city":"Ittre",
    "sg:orig_category":"Agences immobili\u00e8res",
    "sg:phone":"+32 67 64 77 02",
    "sg:postcode":"1460",
    "sg:province":"Brabant Wallon",
    "wof:name":"Immo Decouvertes",
    "wof:placetype":"venue"
},
  "geometry": {"coordinates":[4.2308721542,50.6492500305],"type":"Point"}
}