{
  "type": "Feature",
  "properties": {
    "iso:country":"BE",
    "sg:address":"Rue Auguste Nicod\u00e8me 8",
    "sg:city":"La Louvi\u00e8re",
    "sg:classifiers":[
        {
            "category":"Building & Trades",
            "subcategory":"Construction",
            "type":"Services"
        }
    ],
    "sg:phone":"+32 64 21 56 19",
    "sg:postcode":"7100",
    "sg:province":"Hainaut",
    "sg:tags":[
        "stucco",
        "contractor"
    ],
    "wof:name":"Hennixdal (entrep Gen)",
    "wof:placetype":"venue"
},
  "geometry": {"coordinates":[4.2101302147,50.4847068787],"type":"Point"}
}