{
  "type": "Feature",
  "properties": {
    "addr:full":"Kortrijksestraat 334 Oostkamp West-Vlaanderen 8020",
    "addr:housenumber":"334",
    "addr:postcode":"8020",
    "addr:street":"Kortrijksestraat",
    "iso:country":"BE",
    "sg:address":"Kortrijksestraat 334",
    "sg:city":"Oostkamp",
    "sg:orig_category":"Apotheken",
    "sg:phone":"+32 50 27 72 89",
    "sg:postcode":"8020",
    "sg:province":"West-Vlaanderen",
    "wof:name":"Christine Latruwe",
    "wof:placetype":"venue"
},
  "geometry": {"coordinates":[3.2216351032,51.124584198],"type":"Point"}
}