{
  "type": "Feature",
  "properties": {
    "addr:full":"Rue Du Page 67 Elsene/ixelles Bruxelles-Capitale 1050",
    "addr:housenumber":"67",
    "addr:postcode":"1050",
    "addr:street":"Rue Du Page",
    "iso:country":"BE",
    "sg:address":"Rue Du Page 67",
    "sg:city":"Elsene/ixelles",
    "sg:orig_category":"Epiceries",
    "sg:phone":"+32 2 534 75 32",
    "sg:postcode":"1050",
    "sg:province":"Bruxelles-Capitale",
    "wof:name":"Maison Patiala",
    "wof:placetype":"venue"
},
  "geometry": {"coordinates":[4.3578300476,50.8227462769],"type":"Point"}
}