{
  "type": "Feature",
  "properties": {
    "addr:full":"Vossekotstraat 33 Sint-niklaas Oost-Vlaanderen 9100",
    "addr:housenumber":"33",
    "addr:postcode":"9100",
    "addr:street":"Vossekotstraat",
    "iso:country":"BE",
    "sg:address":"Vossekotstraat 33",
    "sg:city":"Sint-niklaas",
    "sg:classifiers":[
        {
            "category":"Insurance",
            "subcategory":"Life Insurance",
            "type":"Services"
        }
    ],
    "sg:phone":"+32 3 777 23 87",
    "sg:postcode":"9100",
    "sg:province":"Oost-Vlaanderen",
    "sg:tags":[
        "assurance"
    ],
    "wof:name":"R. Meeussen",
    "wof:placetype":"venue"
},
  "geometry": {"coordinates":[4.1967000961,51.1766090393],"type":"Point"}
}