{
  "type": "Feature",
  "properties": {
    "addr:full":"Antwerpsesteenweg 129 Rumst Antwerpen 2840",
    "addr:housenumber":"129",
    "addr:postcode":"2840",
    "addr:street":"Antwerpsesteenweg",
    "iso:country":"BE",
    "sg:address":"Antwerpsesteenweg 129",
    "sg:city":"Rumst",
    "sg:classifiers":[
        {
            "category":"Farming",
            "subcategory":"Crops",
            "type":"Manufacturing & Wholesale Goods"
        }
    ],
    "sg:phone":"+32 15 31 38 64",
    "sg:postcode":"2840",
    "sg:province":"Antwerpen",
    "sg:tags":[
        "vegetable",
        "fruit",
        "-",
        "grower"
    ],
    "wof:name":"Celis W",
    "wof:placetype":"venue"
},
  "geometry": {"coordinates":[4.4493288994,51.0984649658],"type":"Point"}
}