{
  "type": "Feature",
  "properties": {
    "addr:full":"Rue Saint-g\u00e9r\u00e9on 23 Lessines (deux-acren) Hainaut 7864",
    "addr:housenumber":"23",
    "addr:postcode":"7864",
    "addr:street":"Rue Saint-Ge\u0301Re\u0301On",
    "iso:country":"BE",
    "sg:address":"Rue Saint-g\u00e9r\u00e9on 23",
    "sg:city":"Lessines (deux-acren)",
    "sg:classifiers":[
        {
            "category":"Retail",
            "subcategory":"Auto Repair",
            "type":"Services"
        }
    ],
    "sg:phone":"+32 68 33 34 76",
    "sg:postcode":"7864",
    "sg:province":"Hainaut",
    "sg:tags":[
        "garage"
    ],
    "wof:name":"Leclercq A",
    "wof:placetype":"venue"
},
  "geometry": {"coordinates":[3.8488619328,50.7305297852],"type":"Point"}
}