{
  "type": "Feature",
  "properties": {
    "addr:full":"Rue De La Paix 49 Bruxelles (ixelles) Bruxelles-Capitale 1050",
    "addr:housenumber":"49",
    "addr:postcode":"1050",
    "addr:street":"Rue De La Paix",
    "iso:country":"BE",
    "sg:address":"Rue De La Paix 49",
    "sg:city":"Bruxelles (ixelles)",
    "sg:classifiers":[
        {
            "category":"Cafe",
            "type":"Food & Drink"
        }
    ],
    "sg:phone":"+32 2 512 11 36",
    "sg:postcode":"1050",
    "sg:province":"Bruxelles-Capitale",
    "sg:tags":[
        "snack-bars"
    ],
    "wof:name":"Boule Et Mie",
    "wof:placetype":"venue"
},
  "geometry": {"coordinates":[4.3661880493,50.8363189697],"type":"Point"}
}