{
  "type": "Feature",
  "properties": {
    "iso:country":"BE",
    "sg:address":"Rue De Binche 6",
    "sg:city":"Estinnes (estinnes-au-val)",
    "sg:classifiers":[
        {
            "category":"Health Services",
            "subcategory":"Doctor",
            "type":"Services"
        }
    ],
    "sg:phone":"+32 64 33 42 14",
    "sg:postcode":"7120",
    "sg:province":"Hainaut",
    "sg:tags":[
        "psychotherapist",
        "psychoanalyst"
    ],
    "wof:name":"Wanzoul H",
    "wof:placetype":"venue"
},
  "geometry": {"coordinates":[4.1066188812,50.4103355408],"type":"Point"}
}