{
  "type": "Feature",
  "properties": {
    "iso:country":"BE",
    "sg:address":"Rue Du Centre 173",
    "sg:city":"Viroinval",
    "sg:classifiers":[
        {
            "category":"Arena",
            "subcategory":"Sports Club",
            "type":"Entertainment"
        }
    ],
    "sg:phone":"+32 60 39 09 09",
    "sg:postcode":"5670",
    "sg:province":"Namur",
    "sg:tags":[
        "de"
    ],
    "wof:name":"Les Diables Rouges",
    "wof:placetype":"venue"
},
  "geometry": {"coordinates":[4.6358499527,50.0781517029],"type":"Point"}
}