{
  "type": "Feature",
  "properties": {
    "addr:full":"Voie De L'air Pur 269 Chaudfontaine Li\u00e8ge 4052",
    "addr:housenumber":"269",
    "addr:postcode":"4052",
    "addr:street":"Voie De L'Air Pur",
    "iso:country":"BE",
    "sg:address":"Voie De L'air Pur 269",
    "sg:city":"Chaudfontaine",
    "sg:orig_category":"Pi\u00e8ces and accessoires de v\u00e9hicules automobiles Gr",
    "sg:phone":"+32 4 368 88 77",
    "sg:postcode":"4052",
    "sg:province":"Li\u00e8ge",
    "wof:name":"Verviers Freins",
    "wof:placetype":"venue"
},
  "geometry": {"coordinates":[5.5817270279,50.6415977478],"type":"Point"}
}