{
  "type": "Feature",
  "properties": {
    "addr:full":"Tervuursesteenweg 167 Bertem Vlaams-Brabant 3060",
    "addr:housenumber":"167",
    "addr:postcode":"3060",
    "addr:street":"Tervuursesteenweg",
    "iso:country":"BE",
    "sg:address":"Tervuursesteenweg 167",
    "sg:city":"Bertem",
    "sg:classifiers":[
        {
            "category":"Building & Trades",
            "subcategory":"Electrical",
            "type":"Services"
        }
    ],
    "sg:phone":"+32 16 49 01 01",
    "sg:postcode":"3060",
    "sg:province":"Vlaams-Brabant",
    "sg:tags":[
        "plants",
        "plant",
        "industrial",
        "buildings",
        "construction"
    ],
    "wof:name":"Van Eycken B.v.b.a.",
    "wof:placetype":"venue"
},
  "geometry": {"coordinates":[4.6270561218,50.8647918701],"type":"Point"}
}