{
  "type": "Feature",
  "properties": {
    "addr:full":"Rue De La Station 169 Courcelles (gouy-lez-pi\u00e9ton) Hainaut 6181",
    "addr:housenumber":"169",
    "addr:postcode":"6181",
    "addr:street":"Rue De La Station",
    "iso:country":"BE",
    "sg:address":"Rue De La Station 169",
    "sg:city":"Courcelles (gouy-lez-pi\u00e9ton)",
    "sg:classifiers":[
        {
            "category":"Health Services",
            "subcategory":"Doctor",
            "type":"Services"
        }
    ],
    "sg:phone":"+32 71 84 24 03",
    "sg:postcode":"6181",
    "sg:province":"Hainaut",
    "sg:tags":[
        "medicinephysicians",
        "surgeon"
    ],
    "wof:name":"Lambert Pascale",
    "wof:placetype":"venue"
},
  "geometry": {"coordinates":[4.3262090683,50.4966201782],"type":"Point"}
}