{
  "type": "Feature",
  "properties": {
    "iso:country":"BE",
    "sg:address":"Place Du Samedi 12a",
    "sg:city":"Brussel",
    "sg:classifiers":[
        {
            "category":"Restaurant",
            "type":"Food & Drink"
        }
    ],
    "sg:phone":"+32 2 218 35 70",
    "sg:postcode":"1000",
    "sg:province":"Bruxelles-Capitale",
    "wof:name":"Le Greco Romain",
    "wof:placetype":"venue"
},
  "geometry": {"coordinates":[4.3506708145,50.8517570496],"type":"Point"}
}