{
  "type": "Feature",
  "properties": {
    "addr:full":"Elderbergstraat 4 Aalst Oost-Vlaanderen 9310",
    "addr:housenumber":"4",
    "addr:postcode":"9310",
    "addr:street":"Elderbergstraat",
    "iso:country":"BE",
    "sg:address":"Elderbergstraat 4",
    "sg:city":"Aalst",
    "sg:orig_category":"Quincailleries. Bois Gr",
    "sg:phone":"+32 53 78 99 95",
    "sg:postcode":"9310",
    "sg:province":"Oost-Vlaanderen",
    "wof:name":"Arti-wood",
    "wof:placetype":"venue"
},
  "geometry": {"coordinates":[4.1260437965,50.9506568909],"type":"Point"}
}