{
  "type": "Feature",
  "properties": {
    "addr:full":"Riddersstraat 4 Tongeren Limburg 3700",
    "addr:housenumber":"4",
    "addr:postcode":"3700",
    "addr:street":"Riddersstraat",
    "iso:country":"BE",
    "sg:address":"Riddersstraat 4",
    "sg:city":"Tongeren",
    "sg:orig_category":"Avocats and conseillers juridiques",
    "sg:phone":"+32 12 23 77 88",
    "sg:postcode":"3700",
    "sg:province":"Limburg",
    "wof:name":"Gert Hoessels",
    "wof:placetype":"venue"
},
  "geometry": {"coordinates":[5.4661960602,50.7805366516],"type":"Point"}
}