{
  "type": "Feature",
  "properties": {
    "addr:full":"Faubourg De Namur 17 Nivelles Brabant Wallon 1400",
    "addr:housenumber":"17",
    "addr:postcode":"1400",
    "addr:street":"Faubourg De Namur",
    "iso:country":"BE",
    "sg:address":"Faubourg De Namur 17",
    "sg:city":"Nivelles",
    "sg:orig_category":"Enseignement maternel and primaire",
    "sg:phone":"+32 67 21 39 31",
    "sg:postcode":"1400",
    "sg:province":"Brabant Wallon",
    "wof:name":"Ecole Fondamentale",
    "wof:placetype":"venue"
},
  "geometry": {"coordinates":[4.3369059563,50.5995407104],"type":"Point"}
}