{
  "type": "Feature",
  "properties": {
    "addr:full":"Casselsestraat 23 Ieper West-Vlaanderen 8908",
    "addr:housenumber":"23",
    "addr:postcode":"8908",
    "addr:street":"Casselsestraat",
    "iso:country":"BE",
    "sg:address":"Casselsestraat 23",
    "sg:city":"Ieper",
    "sg:orig_category":"D\u00e9molition d\u00b4immeubles and terrassements",
    "sg:phone":"+32 57 33 37 43",
    "sg:postcode":"8908",
    "sg:province":"West-Vlaanderen",
    "wof:name":"Frank Monkerhey",
    "wof:placetype":"venue"
},
  "geometry": {"coordinates":[2.8085649014,50.853931427],"type":"Point"}
}