{
  "type": "Feature",
  "properties": {
    "iso:country":"BE",
    "sg:address":"Rue De Wallonie 21",
    "sg:city":"Gr\u00e2ce-hollogne (gr\u00e2ce-berleur)",
    "sg:classifiers":[
        {
            "category":"Education",
            "subcategory":"Special Training",
            "type":"Public Place"
        }
    ],
    "sg:phone":"+32 4 247 81 11",
    "sg:postcode":"4460",
    "sg:province":"Li\u00e8ge",
    "sg:tags":[
        "professional"
    ],
    "wof:name":"Centre De Formation Construction",
    "wof:placetype":"venue"
},
  "geometry": {"coordinates":[5.4885988235,50.6537208557],"type":"Point"}
}