{
  "type": "Feature",
  "properties": {
    "iso:country":"BE",
    "sg:address":"Rue De La Chapelle 27",
    "sg:city":"Awans",
    "sg:orig_category":"Eclairage et \u00e9quipements du foyer. Drogueries",
    "sg:phone":"+32 4 257 46 63",
    "sg:postcode":"4340",
    "sg:province":"Li\u00e8ge",
    "wof:name":"Les Grenier Du Tige",
    "wof:placetype":"venue"
},
  "geometry": {"coordinates":[5.4479608536,50.7017974854],"type":"Point"}
}