{
  "type": "Feature",
  "properties": {
    "iso:country":"BE",
    "sg:address":"Rue Haute 20",
    "sg:city":"Oreye",
    "sg:classifiers":[
        {
            "category":"Personal",
            "subcategory":"Beauty Salon",
            "type":"Services"
        }
    ],
    "sg:phone":"+32 19 67 76 70",
    "sg:postcode":"4360",
    "sg:province":"Li\u00e8ge",
    "wof:name":"P\u00e9try L",
    "wof:placetype":"venue"
},
  "geometry": {"coordinates":[5.3365998268,50.7219734192],"type":"Point"}
}