{
  "type": "Feature",
  "properties": {
    "addr:full":"Rue Du Pavillon 83 Bruxelles (schaerbeek) Bruxelles-Capitale 1030",
    "addr:housenumber":"83",
    "addr:postcode":"1030",
    "addr:street":"Rue Du Pavillon",
    "iso:country":"BE",
    "sg:address":"Rue Du Pavillon 83",
    "sg:city":"Bruxelles (schaerbeek)",
    "sg:classifiers":[
        {
            "category":"Communications",
            "subcategory":"Film & Video Production",
            "type":"Services"
        }
    ],
    "sg:phone":"+32 2 242 02 94",
    "sg:postcode":"1030",
    "sg:province":"Bruxelles-Capitale",
    "sg:tags":[
        "sound",
        "recording",
        "studio"
    ],
    "wof:name":"Studio C.d.s",
    "wof:placetype":"venue"
},
  "geometry": {"coordinates":[4.3689961433,50.8695411682],"type":"Point"}
}