{
  "type": "Feature",
  "properties": {
    "addr:full":"Steenweg 156 Heers Limburg 3870",
    "addr:housenumber":"156",
    "addr:postcode":"3870",
    "addr:street":"Steenweg",
    "iso:country":"BE",
    "sg:address":"Steenweg 156",
    "sg:city":"Heers",
    "sg:classifiers":[
        {
            "category":"Government",
            "subcategory":"Police Station",
            "type":"Public Place"
        }
    ],
    "sg:phone":"+32 11 48 50 53",
    "sg:postcode":"3870",
    "sg:province":"Limburg",
    "sg:tags":[
        "gendarmerie"
    ],
    "wof:name":"Federale Politie",
    "wof:placetype":"venue"
},
  "geometry": {"coordinates":[5.2975821495,50.7500152588],"type":"Point"}
}