{
  "type": "Feature",
  "properties": {
    "iso:country":"BE",
    "sg:address":"Peyerstraat 3be",
    "sg:city":"Heist-op-den-berg",
    "sg:orig_category":"Instituts de beaut\u00e9",
    "sg:phone":"+32 15 23 67 43",
    "sg:postcode":"2223",
    "sg:province":"Antwerpen",
    "wof:name":"Marina Del Rincon",
    "wof:placetype":"venue"
},
  "geometry": {"coordinates":[4.7158617973,51.0196685791],"type":"Point"}
}