{
  "type": "Feature",
  "properties": {
    "addr:full":"Boerenkrijgsingel 38 Hasselt Limburg 3500",
    "addr:housenumber":"38",
    "addr:postcode":"3500",
    "addr:street":"Boerenkrijgsingel",
    "iso:country":"BE",
    "sg:address":"Boerenkrijgsingel 38",
    "sg:city":"Hasselt",
    "sg:classifiers":[
        {
            "category":"Professional",
            "subcategory":"Testing Lab",
            "type":"Services"
        }
    ],
    "sg:phone":"+32 11 23 15 45",
    "sg:postcode":"3500",
    "sg:province":"Limburg",
    "sg:tags":[
        "laboratory",
        "photographic",
        "film"
    ],
    "wof:name":"Foto Quality Colors",
    "wof:placetype":"venue"
},
  "geometry": {"coordinates":[5.318005085,50.9244499207],"type":"Point"}
}