{
  "type": "Feature",
  "properties": {
    "addr:full":"Mercatorstraat 79 Sint-niklaas Oost-Vlaanderen 9100",
    "addr:housenumber":"79",
    "addr:postcode":"9100",
    "addr:street":"Mercatorstraat",
    "iso:country":"BE",
    "sg:address":"Mercatorstraat 79",
    "sg:city":"Sint-niklaas",
    "sg:orig_category":"Non-Classified Establishments",
    "sg:phone":"+32 3 777 48 66",
    "sg:postcode":"9100",
    "sg:province":"Oost-Vlaanderen",
    "wof:name":"Eurotrend Bvba",
    "wof:placetype":"venue"
},
  "geometry": {"coordinates":[4.1470489502,51.1694374084],"type":"Point"}
}