{
  "type": "Feature",
  "properties": {
    "iso:country":"BE",
    "sg:address":"Gaverse Steenweg 144",
    "sg:city":"Oosterzele (scheldewindeke)",
    "sg:classifiers":[
        {
            "category":"Wholesale",
            "subcategory":"Plants",
            "type":"Manufacturing & Wholesale Goods"
        }
    ],
    "sg:phone":"+32 9 362 88 85",
    "sg:postcode":"9860",
    "sg:province":"Oost-Vlaanderen",
    "sg:tags":[
        "whol",
        "flower",
        "-",
        "grower"
    ],
    "wof:name":"Vertriest-van Damme Bvba",
    "wof:placetype":"venue"
},
  "geometry": {"coordinates":[3.7487950325,50.9307479858],"type":"Point"}
}