{
  "type": "Feature",
  "properties": {
    "iso:country":"BE",
    "sg:address":"Rietstraat 62",
    "sg:city":"Overpelt",
    "sg:orig_category":"Eleveurs de bovins",
    "sg:phone":"+32 11 66 15 35",
    "sg:postcode":"3900",
    "sg:province":"Limburg",
    "wof:name":"Schildermans Johan-jozef",
    "wof:placetype":"venue"
},
  "geometry": {"coordinates":[5.4213352203,51.2003440857],"type":"Point"}
}