{
  "type": "Feature",
  "properties": {
    "iso:country":"BE",
    "sg:address":"Bergbeemden 7",
    "sg:city":"Turnhout",
    "sg:classifiers":[
        {
            "category":"Personal",
            "subcategory":"Nail Salon",
            "type":"Services"
        }
    ],
    "sg:phone":"+32 14 41 52 47",
    "sg:postcode":"2300",
    "sg:province":"Antwerpen",
    "sg:tags":[
        "pedicure"
    ],
    "wof:name":"Fleerackers M",
    "wof:placetype":"venue"
},
  "geometry": {"coordinates":[4.9532628059,51.3089675903],"type":"Point"}
}