{
  "type": "Feature",
  "properties": {
    "addr:full":"Klein Laarstraat 25 Beveren Oost-Vlaanderen 9120",
    "addr:housenumber":"25",
    "addr:postcode":"9120",
    "addr:street":"Klein Laarstraat",
    "iso:country":"BE",
    "sg:address":"Klein Laarstraat 25",
    "sg:city":"Beveren",
    "sg:orig_category":"Rundveehouders Varkenskwekers",
    "sg:phone":"+32 3 775 88 68",
    "sg:postcode":"9120",
    "sg:province":"Oost-Vlaanderen",
    "wof:name":"Marc De Gendt",
    "wof:placetype":"venue"
},
  "geometry": {"coordinates":[4.1530900002,51.2140617371],"type":"Point"}
}