{
  "type": "Feature",
  "properties": {
    "iso:country":"BE",
    "sg:address":"Leeuwerkstraat 26",
    "sg:city":"De Pinte",
    "sg:orig_category":"Bloemen and planten",
    "sg:phone":"+32 9 282 34 49",
    "sg:postcode":"9840",
    "sg:province":"Oost-Vlaanderen",
    "wof:name":"De Vreese",
    "wof:placetype":"venue"
},
  "geometry": {"coordinates":[3.6366240978,50.986328125],"type":"Point"}
}