{
  "type": "Feature",
  "properties": {
    "addr:full":"Steenweg Op Turnhout 30 Oud-turnhout Antwerpen 2360",
    "addr:housenumber":"30",
    "addr:postcode":"2360",
    "addr:street":"Steenweg Op Turnhout",
    "iso:country":"BE",
    "sg:address":"Steenweg Op Turnhout 30",
    "sg:city":"Oud-turnhout",
    "sg:classifiers":[
        {
            "category":"Cafe",
            "type":"Food & Drink"
        }
    ],
    "sg:phone":"+32 14 45 05 71",
    "sg:postcode":"2360",
    "sg:province":"Antwerpen",
    "sg:tags":[
        "snack-bars"
    ],
    "wof:name":"Bosphorus",
    "wof:placetype":"venue"
},
  "geometry": {"coordinates":[4.9790740013,51.3192520142],"type":"Point"}
}