{
  "type": "Feature",
  "properties": {
    "addr:full":"Muldersdreef 38 Sint-martens-latem Oost-Vlaanderen 9831",
    "addr:housenumber":"38",
    "addr:postcode":"9831",
    "addr:street":"Muldersdreef",
    "iso:country":"BE",
    "sg:address":"Muldersdreef 38",
    "sg:city":"Sint-martens-latem",
    "sg:orig_category":"M\u00e9decins and sp\u00e9cialistes",
    "sg:phone":"+32 9 282 40 97",
    "sg:postcode":"9831",
    "sg:province":"Oost-Vlaanderen",
    "wof:name":"Ingeborg Dierickx",
    "wof:placetype":"venue"
},
  "geometry": {"coordinates":[3.6154770851,51.0057830811],"type":"Point"}
}