{
  "type": "Feature",
  "properties": {
    "addr:full":"Broekstraat 116 Gingelom Limburg 3890",
    "addr:housenumber":"116",
    "addr:postcode":"3890",
    "addr:street":"Broekstraat",
    "iso:country":"BE",
    "sg:address":"Broekstraat 116",
    "sg:city":"Gingelom",
    "sg:orig_category":"Fruitteelt",
    "sg:phone":"+32 11 48 67 42",
    "sg:postcode":"3890",
    "sg:province":"Limburg",
    "wof:name":"Christy Neven",
    "wof:placetype":"venue"
},
  "geometry": {"coordinates":[5.2090249062,50.7289237976],"type":"Point"}
}