{
  "type": "Feature",
  "properties": {
    "addr:full":"Rue Arthur Cosyn 1 Brussel/bruxelles Bruxelles-Capitale 1020",
    "addr:housenumber":"1",
    "addr:postcode":"1020",
    "addr:street":"Rue Arthur Cosyn;/",
    "iso:country":"BE",
    "sg:address":"Rue Arthur Cosyn 1",
    "sg:city":"Brussel/bruxelles",
    "sg:orig_category":"Plomberie, chauffage and installations sanitaires",
    "sg:phone":"+32 2 478 61 67",
    "sg:postcode":"1020",
    "sg:province":"Bruxelles-Capitale",
    "wof:name":"Gabriel Lezaire",
    "wof:placetype":"venue"
},
  "geometry": {"coordinates":[4.3577251434,50.8768348694],"type":"Point"}
}