{
  "type": "Feature",
  "properties": {
    "iso:country":"BE",
    "sg:address":"Avenue De Limburg Stirum 62",
    "sg:city":"Wemmel/wemmel",
    "sg:orig_category":"Avocats and conseillers juridiques",
    "sg:phone":"+32 2 460 51 87",
    "sg:postcode":"1780",
    "sg:province":"Vlaams-Brabant",
    "wof:name":"J. D'hollander",
    "wof:placetype":"venue"
},
  "geometry": {"coordinates":[4.3070898056,50.9067382812],"type":"Point"}
}