{
  "type": "Feature",
  "properties": {
    "iso:country":"BE",
    "sg:address":"Hulsterweg 82",
    "sg:city":"Tessenderlo",
    "sg:classifiers":[
        {
            "category":"Communications",
            "subcategory":"Film & Video Production",
            "type":"Services"
        }
    ],
    "sg:phone":"+32 13 66 18 84",
    "sg:postcode":"3980",
    "sg:province":"Limburg",
    "sg:tags":[
        "mirror"
    ],
    "wof:name":"Baldewijns Bvba",
    "wof:placetype":"venue"
},
  "geometry": {"coordinates":[5.1142559052,51.0684432983],"type":"Point"}
}