{
  "type": "Feature",
  "properties": {
    "iso:country":"BE",
    "sg:address":"Place 17a",
    "sg:city":"Jalhay",
    "sg:classifiers":[
        {
            "category":"Professional",
            "subcategory":"Testing Lab",
            "type":"Services"
        }
    ],
    "sg:phone":"+32 87 64 71 26",
    "sg:postcode":"4845",
    "sg:province":"Li\u00e8ge",
    "sg:tags":[
        "chemist"
    ],
    "wof:name":"Jalhay Sc (pharmacie De)",
    "wof:placetype":"venue"
},
  "geometry": {"coordinates":[5.9653158188,50.559135437],"type":"Point"}
}