{
  "type": "Feature",
  "properties": {
    "iso:country":"BE",
    "sg:address":"Brusselsesteenweg 333",
    "sg:city":"Melle",
    "sg:orig_category":"Notarissen",
    "sg:phone":"+32 9 252 10 51",
    "sg:postcode":"9090",
    "sg:province":"Oost-Vlaanderen",
    "wof:name":"Henri Rutsaert",
    "wof:placetype":"venue"
},
  "geometry": {"coordinates":[3.8020710945,51.0028610229],"type":"Point"}
}