{
  "type": "Feature",
  "properties": {
    "addr:full":"Molenstraat 5 Zwijndrecht Antwerpen 2070",
    "addr:housenumber":"5",
    "addr:postcode":"2070",
    "addr:street":"Molenstraat",
    "iso:country":"BE",
    "sg:address":"Molenstraat 5",
    "sg:city":"Zwijndrecht",
    "sg:orig_category":"Sportclubs",
    "sg:phone":"+32 3 253 06 23",
    "sg:postcode":"2070",
    "sg:province":"Antwerpen",
    "wof:name":"Chakuriki Hoboken-linker Oever",
    "wof:placetype":"venue"
},
  "geometry": {"coordinates":[4.3329019547,51.2212219238],"type":"Point"}
}