{
  "type": "Feature",
  "properties": {
    "iso:country":"BE",
    "sg:address":"Kempische Steenweg 142",
    "sg:city":"Hasselt",
    "sg:orig_category":"Solariums",
    "sg:phone":"+32 11 21 58 58",
    "sg:postcode":"3500",
    "sg:province":"Limburg",
    "wof:name":"Palm Azur Nv",
    "wof:placetype":"venue"
},
  "geometry": {"coordinates":[5.340734005,50.9390678406],"type":"Point"}
}