{
  "type": "Feature",
  "properties": {
    "iso:country":"BE",
    "sg:address":"Rue Plagne 19",
    "sg:city":"Sivry-rance",
    "sg:orig_category":"Eleveurs and marchands de porcs. Eleveurs de bovins",
    "sg:phone":"+32 60 45 51 68",
    "sg:postcode":"6470",
    "sg:province":"Hainaut",
    "wof:name":"Marcel Dutron",
    "wof:placetype":"venue"
},
  "geometry": {"coordinates":[4.2086439133,50.1899375916],"type":"Point"}
}