{
  "type": "Feature",
  "properties": {
    "addr:full":"Avenue Reine Astrid 1 Braine-le-ch\u00e2teau (wauthier-braine) Brabant Wallon 1440",
    "addr:housenumber":"1",
    "addr:postcode":"1440",
    "addr:street":"Avenue Reine Astrid",
    "iso:country":"BE",
    "sg:address":"Avenue Reine Astrid 1",
    "sg:city":"Braine-le-ch\u00e2teau (wauthier-braine)",
    "sg:classifiers":[
        {
            "category":"Professional",
            "subcategory":"Printing & Photocopies",
            "type":"Services"
        }
    ],
    "sg:phone":"+32 2 367 25 10",
    "sg:postcode":"1440",
    "sg:province":"Brabant Wallon",
    "sg:tags":[
        "digital"
    ],
    "wof:name":"Numeris Printing Sa",
    "wof:placetype":"venue"
},
  "geometry": {"coordinates":[4.3224840164,50.6905593872],"type":"Point"}
}