{
  "type": "Feature",
  "properties": {
    "iso:country":"BE",
    "sg:address":"Rue Florimond Letroye 3",
    "sg:city":"Wavre",
    "sg:classifiers":[
        {
            "category":"Autos & Motor Vehicles",
            "subcategory":"Auto Supplies",
            "type":"Retail Goods"
        }
    ],
    "sg:phone":"+32 10 22 32 85",
    "sg:postcode":"1300",
    "sg:province":"Brabant Wallon",
    "sg:tags":[
        "automobile",
        "alarm",
        "-",
        "system"
    ],
    "wof:name":"Ad Rosvelds",
    "wof:placetype":"venue"
},
  "geometry": {"coordinates":[4.6126928329,50.7151870728],"type":"Point"}
}