{
  "type": "Feature",
  "properties": {
    "addr:full":"Stationslaan 8 Steenokkerzeel Vlaams-Brabant 1820",
    "addr:housenumber":"8",
    "addr:postcode":"1820",
    "addr:street":"Stationslaan",
    "iso:country":"BE",
    "sg:address":"Stationslaan 8",
    "sg:city":"Steenokkerzeel",
    "sg:classifiers":[
        {
            "category":"Restaurant",
            "type":"Food & Drink"
        }
    ],
    "sg:phone":"+32 2 751 35 80",
    "sg:postcode":"1820",
    "sg:province":"Vlaams-Brabant",
    "wof:name":"Bistro Melde",
    "wof:placetype":"venue"
},
  "geometry": {"coordinates":[4.4757871628,50.9118423462],"type":"Point"}
}