{
  "type": "Feature",
  "properties": {
    "iso:country":"BE",
    "sg:address":"Vosselarestraat 9",
    "sg:city":"Nevele (landegem)",
    "sg:classifiers":[
        {
            "category":"Building & Trades",
            "subcategory":"Construction",
            "type":"Services"
        }
    ],
    "sg:phone":"+32 9 385 75 99",
    "sg:postcode":"9850",
    "sg:province":"Oost-Vlaanderen",
    "sg:tags":[
        "carpenter"
    ],
    "wof:name":"Casa-decor Bvba",
    "wof:placetype":"venue"
},
  "geometry": {"coordinates":[3.5727629662,51.0559425354],"type":"Point"}
}