{
  "type": "Feature",
  "properties": {
    "addr:full":"3 Leiseinde Turnhout Antwerpen 2300",
    "addr:housenumber":"3",
    "addr:postcode":"2300",
    "addr:street":"Leiseinde",
    "iso:country":"BE",
    "sg:address":"3 Leiseinde",
    "sg:city":"Turnhout",
    "sg:classifiers":[
        {
            "category":"Travel",
            "subcategory":"Hotels & Motels",
            "type":"Entertainment"
        }
    ],
    "sg:phone":"+32 14 41 98 85",
    "sg:postcode":"2300",
    "sg:province":"Antwerpen",
    "sg:tags":[
        "hotels",
        "business",
        "restaurant"
    ],
    "wof:name":"De Oude Eik Bvba",
    "wof:placetype":"venue"
},
  "geometry": {"coordinates":[4.9309248924,51.2839355469],"type":"Point"}
}