{
  "type": "Feature",
  "properties": {
    "iso:country":"BE",
    "sg:address":"Jozef Schijnsstraat 3 Box 15",
    "sg:city":"Kortenberg (erps-kwerps)",
    "sg:classifiers":[
        {
            "category":"Arts & Performance",
            "subcategory":"Music",
            "type":"Entertainment"
        }
    ],
    "sg:postcode":"3071",
    "sg:province":"Vlaams-Brabant",
    "sg:tags":[
        "disc-jockeys"
    ],
    "wof:name":"Szel Lazlo",
    "wof:placetype":"venue"
},
  "geometry": {"coordinates":[4.59126091,50.8940963745],"type":"Point"}
}