{
  "type": "Feature",
  "properties": {
    "iso:country":"BE",
    "sg:address":"Slachthuisstraat 30",
    "sg:city":"Turnhout",
    "sg:orig_category":"Reliure and finition",
    "sg:phone":"+32 14 41 91 10",
    "sg:postcode":"2300",
    "sg:province":"Antwerpen",
    "wof:name":"Ver-niet",
    "wof:placetype":"venue"
},
  "geometry": {"coordinates":[4.9242630005,51.3086891174],"type":"Point"}
}