{
  "type": "Feature",
  "properties": {
    "addr:full":"Begijnhof 8 Hoogstraten Antwerpen 2320",
    "addr:housenumber":"8",
    "addr:postcode":"2320",
    "addr:street":"Begijnhof",
    "iso:country":"BE",
    "sg:address":"Begijnhof 8",
    "sg:city":"Hoogstraten",
    "sg:classifiers":[
        {
            "category":"Autos & Motor Vehicles",
            "subcategory":"Automobile Sales",
            "type":"Retail Goods"
        }
    ],
    "sg:phone":"+32 3 315 80 52",
    "sg:postcode":"2320",
    "sg:province":"Antwerpen",
    "sg:tags":[
        "car",
        "used",
        "-"
    ],
    "wof:name":"Daems Auto's",
    "wof:placetype":"venue"
},
  "geometry": {"coordinates":[4.7626748085,51.4035148621],"type":"Point"}
}