{
  "type": "Feature",
  "properties": {
    "addr:full":"Chauss\u00e9e De Boondael 532 Bruxelles (ixelles) Bruxelles-Capitale 1050",
    "addr:housenumber":"532",
    "addr:postcode":"1050",
    "addr:street":"Chausse\u0301E De Boondael",
    "iso:country":"BE",
    "sg:address":"Chauss\u00e9e De Boondael 532",
    "sg:city":"Bruxelles (ixelles)",
    "sg:classifiers":[
        {
            "category":"Bars & Pubs",
            "type":"Food & Drink"
        }
    ],
    "sg:phone":"+32 2 649 85 28",
    "sg:postcode":"1050",
    "sg:province":"Bruxelles-Capitale",
    "wof:name":"Wildhorn (le)",
    "wof:placetype":"venue"
},
  "geometry": {"coordinates":[4.3916268349,50.8120155334],"type":"Point"}
}