{
  "type": "Feature",
  "properties": {
    "addr:full":"Rodenbachstraat 30 Vlamertinge West-Vlaanderen 8908",
    "addr:housenumber":"30",
    "addr:postcode":"8908",
    "addr:street":"Rodenbachstraat",
    "iso:country":"BE",
    "sg:address":"Rodenbachstraat 30",
    "sg:city":"Vlamertinge",
    "sg:classifiers":[
        {
            "category":"Building & Trades",
            "subcategory":"Construction",
            "type":"Services"
        }
    ],
    "sg:phone":"+32 3 828 56 56",
    "sg:postcode":"8908",
    "sg:province":"West-Vlaanderen",
    "sg:tags":[
        "operations",
        "hiring",
        "crane"
    ],
    "wof:name":"Van De Weghe Nv",
    "wof:placetype":"venue"
},
  "geometry": {"coordinates":[4.3822717667,51.1553955078],"type":"Point"}
}