{
  "type": "Feature",
  "properties": {
    "addr:full":"Lange-beemdenlaan 31 Leuven Vlaams-Brabant 3012",
    "addr:housenumber":"31",
    "addr:postcode":"3012",
    "addr:street":"Lange-Beemdenlaan",
    "iso:country":"BE",
    "sg:address":"Lange-beemdenlaan 31",
    "sg:city":"Leuven",
    "sg:classifiers":[
        {
            "category":"Insurance",
            "subcategory":"Life Insurance",
            "type":"Services"
        }
    ],
    "sg:phone":"+32 16 44 74 63",
    "sg:postcode":"3012",
    "sg:province":"Vlaams-Brabant",
    "sg:tags":[
        "assurance"
    ],
    "wof:name":"Lkc-makelaardij",
    "wof:placetype":"venue"
},
  "geometry": {"coordinates":[4.7102241516,50.9236373901],"type":"Point"}
}