{
  "type": "Feature",
  "properties": {
    "iso:country":"BE",
    "sg:address":"Hofkwartier 12",
    "sg:city":"Herentals",
    "sg:orig_category":"Kinderopvang",
    "sg:phone":"+32 14 23 17 18",
    "sg:postcode":"2200",
    "sg:province":"Antwerpen",
    "wof:name":"Hummeltjeshof",
    "wof:placetype":"venue"
},
  "geometry": {"coordinates":[4.83589077,51.1784706116],"type":"Point"}
}