{
  "type": "Feature",
  "properties": {
    "iso:country":"BE",
    "sg:address":"Desir\u00e9 Delcroixstraat 10",
    "sg:city":"Deinze",
    "sg:classifiers":[
        {
            "category":"Health Services",
            "subcategory":"Health Practitioner",
            "type":"Services"
        }
    ],
    "sg:phone":"+32 9 386 95 08",
    "sg:postcode":"9800",
    "sg:province":"Oost-Vlaanderen",
    "sg:tags":[
        "physiotherapist"
    ],
    "wof:name":"De Waele Bart",
    "wof:placetype":"venue"
},
  "geometry": {"coordinates":[3.5387790203,50.9853744507],"type":"Point"}
}