{
  "type": "Feature",
  "properties": {
    "iso:country":"BE",
    "sg:address":"Chauss\u00c9e De Bruxelles 90",
    "sg:city":"Soignies",
    "sg:orig_category":"Quincailleries",
    "sg:phone":"+32 65 72 87 05",
    "sg:postcode":"7061",
    "sg:province":"Hainaut",
    "wof:name":"Brico Mahieu",
    "wof:placetype":"venue"
},
  "geometry": {"coordinates":[4.0133500099,50.5159416199],"type":"Point"}
}