{
  "type": "Feature",
  "properties": {
    "iso:country":"BE",
    "sg:address":"Moli\u00c8relaan 134",
    "sg:city":"Elsene/ixelles",
    "sg:orig_category":"Film-, tv- and videoproductie",
    "sg:phone":"+32 2 346 66 16",
    "sg:postcode":"1050",
    "sg:province":"Bruxelles-Capitale",
    "wof:name":"Odyssee Productions",
    "wof:placetype":"venue"
},
  "geometry": {"coordinates":[4.3508758545,50.8160018921],"type":"Point"}
}