{
  "type": "Feature",
  "properties": {
    "iso:country":"BE",
    "sg:address":"Rue Caroline Provoyeur 2",
    "sg:city":"Frasnes-lez-anvaing",
    "sg:classifiers":[
        {
            "category":"Cafe",
            "type":"Food & Drink"
        }
    ],
    "sg:phone":"+32 69 76 95 05",
    "sg:postcode":"7912",
    "sg:province":"Hainaut",
    "sg:tags":[
        "caf\u00e9s"
    ],
    "wof:name":"Les Genets",
    "wof:placetype":"venue"
},
  "geometry": {"coordinates":[3.5916240215,50.7049064636],"type":"Point"}
}