{
  "type": "Feature",
  "properties": {
    "addr:full":"Stippelberg 214 Westerlo Antwerpen 2260",
    "addr:housenumber":"214",
    "addr:postcode":"2260",
    "addr:street":"Stippelberg",
    "iso:country":"BE",
    "sg:address":"Stippelberg 214",
    "sg:city":"Westerlo",
    "sg:classifiers":[
        {
            "category":"Communications",
            "subcategory":"Film & Video Production",
            "type":"Services"
        }
    ],
    "sg:phone":"+32 16 40 45 75",
    "sg:postcode":"2260",
    "sg:province":"Antwerpen",
    "sg:tags":[
        "hiring",
        "distribution"
    ],
    "wof:name":"Retrofilms Bvba",
    "wof:placetype":"venue"
},
  "geometry": {"coordinates":[4.8463401794,51.072769165],"type":"Point"}
}