{
  "type": "Feature",
  "properties": {
    "addr:full":"Avenue Rogier 89 Bruxelles (schaerbeek) Bruxelles-Capitale 1030",
    "addr:housenumber":"89",
    "addr:postcode":"1030",
    "addr:street":"Avenue Rogier",
    "iso:country":"BE",
    "sg:address":"Avenue Rogier 89",
    "sg:city":"Bruxelles (schaerbeek)",
    "sg:classifiers":[
        {
            "category":"Organizations",
            "subcategory":"Community Association",
            "type":"Services"
        }
    ],
    "sg:phone":"+32 2 215 49 28",
    "sg:postcode":"1030",
    "sg:province":"Bruxelles-Capitale",
    "sg:tags":[
        "cultural"
    ],
    "wof:name":"Erenler Asbl",
    "wof:placetype":"venue"
},
  "geometry": {"coordinates":[4.3759889603,50.85962677],"type":"Point"}
}