{
  "type": "Feature",
  "properties": {
    "iso:country":"BE",
    "sg:address":"Brabantstraat 200",
    "sg:city":"Schaarbeek/schaerbeek",
    "sg:orig_category":"Textiel",
    "sg:phone":"+32 2 218 64 23",
    "sg:postcode":"1030",
    "sg:province":"Bruxelles-Capitale",
    "wof:name":"Maison Diane",
    "wof:placetype":"venue"
},
  "geometry": {"coordinates":[4.3646378517,50.8615722656],"type":"Point"}
}