{
  "type": "Feature",
  "properties": {
    "iso:country":"BE",
    "sg:address":"Driekerkenstraat 29",
    "sg:city":"Kortrijk",
    "sg:orig_category":"Artsen and specialisten",
    "sg:phone":"+32 56 35 55 04",
    "sg:postcode":"8501",
    "sg:province":"West-Vlaanderen",
    "wof:name":"Philippe Derumeaux",
    "wof:placetype":"venue"
},
  "geometry": {"coordinates":[3.2282459736,50.8223419189],"type":"Point"}
}