{
  "type": "Feature",
  "properties": {
    "iso:country":"BE",
    "sg:address":"Pastoor Legrandstraat 8",
    "sg:city":"Leuven (wilsele)",
    "sg:classifiers":[
        {
            "category":"Wholesale",
            "subcategory":"Vending Machines",
            "type":"Manufacturing & Wholesale Goods"
        }
    ],
    "sg:phone":"+32 16 29 64 07",
    "sg:postcode":"3012",
    "sg:province":"Vlaams-Brabant",
    "sg:tags":[
        "pulley",
        "belting"
    ],
    "wof:name":"Peleman Bvba",
    "wof:placetype":"venue"
},
  "geometry": {"coordinates":[4.69871521,50.8927688599],"type":"Point"}
}