{
  "type": "Feature",
  "properties": {
    "addr:full":"Victor Braeckmanlaan 117 Gent (sint-amandsberg) Oost-Vlaanderen 9040",
    "addr:housenumber":"117",
    "addr:postcode":"9040",
    "addr:street":"Victor Braeckmanlaan",
    "iso:country":"BE",
    "sg:address":"Victor Braeckmanlaan 117",
    "sg:city":"Gent (sint-amandsberg)",
    "sg:classifiers":[
        {
            "category":"Health Services",
            "subcategory":"Health Practitioner",
            "type":"Services"
        }
    ],
    "sg:phone":"+32 9 228 99 21",
    "sg:postcode":"9040",
    "sg:province":"Oost-Vlaanderen",
    "sg:tags":[
        "physiotherapist"
    ],
    "wof:name":"De Vos Dirk",
    "wof:placetype":"venue"
},
  "geometry": {"coordinates":[3.7533938885,51.0600280762],"type":"Point"}
}