{
  "type": "Feature",
  "properties": {
    "iso:country":"BE",
    "sg:address":"Tweevoetjesweg 12",
    "sg:city":"Bilzen",
    "sg:classifiers":[
        {
            "category":"Cafe",
            "type":"Food & Drink"
        }
    ],
    "sg:phone":"+32 89 41 37 19",
    "sg:postcode":"3740",
    "sg:province":"Limburg",
    "sg:tags":[
        "caf\u00e9s"
    ],
    "wof:name":"Slaets Gunter En Ruggiero",
    "wof:placetype":"venue"
},
  "geometry": {"coordinates":[5.5229029655,50.8693656921],"type":"Point"}
}