{
  "type": "Feature",
  "properties": {
    "addr:full":"Plattesteen 13 Halle Vlaams-Brabant 1500",
    "addr:housenumber":"13",
    "addr:postcode":"1500",
    "addr:street":"Plattesteen",
    "iso:country":"BE",
    "sg:address":"Plattesteen 13",
    "sg:city":"Halle",
    "sg:orig_category":"Rundveehouders",
    "sg:phone":"+32 2 380 04 11",
    "sg:postcode":"1500",
    "sg:province":"Vlaams-Brabant",
    "wof:name":"Edouard Van Overstraeten",
    "wof:placetype":"venue"
},
  "geometry": {"coordinates":[4.2754888535,50.7185516357],"type":"Point"}
}