{
  "type": "Feature",
  "properties": {
    "addr:full":"Machelenstraat 177 Deinze (petegem-aan-de-leie) Oost-Vlaanderen 9800",
    "addr:housenumber":"177",
    "addr:postcode":"9800",
    "addr:street":"Machelenstraat;Oost-Vlaanderen",
    "iso:country":"BE",
    "sg:address":"Machelenstraat 177",
    "sg:city":"Deinze (petegem-aan-de-leie)",
    "sg:classifiers":[
        {
            "category":"Home & Garden",
            "subcategory":"Kitchen Supply",
            "type":"Retail Goods"
        }
    ],
    "sg:phone":"+32 9 386 53 29",
    "sg:postcode":"9800",
    "sg:province":"Oost-Vlaanderen",
    "sg:tags":[
        "installation"
    ],
    "wof:name":"Ovo Keukens",
    "wof:placetype":"venue"
},
  "geometry": {"coordinates":[3.5242800713,50.9765892029],"type":"Point"}
}