{
  "type": "Feature",
  "properties": {
    "addr:full":"Rue Nich\u00c9e Studieuse 7 Boussu Hainaut 7300",
    "addr:housenumber":"7",
    "addr:postcode":"7300",
    "addr:street":"Rue Niche\u0301E Studieuse",
    "iso:country":"BE",
    "sg:address":"Rue Nich\u00c9e Studieuse 7",
    "sg:city":"Boussu",
    "sg:orig_category":"Gasproductie and -distributie",
    "sg:phone":"+32 65 65 33 04",
    "sg:postcode":"7300",
    "sg:province":"Hainaut",
    "wof:name":"Desire Carlier",
    "wof:placetype":"venue"
},
  "geometry": {"coordinates":[3.7849121094,50.4117202759],"type":"Point"}
}