{
  "type": "Feature",
  "properties": {
    "iso:country":"BE",
    "sg:address":"Kasteelstraat 50",
    "sg:city":"Vleteren",
    "sg:orig_category":"Enseignement maternel and primaire",
    "sg:phone":"+32 57 40 08 67",
    "sg:postcode":"8640",
    "sg:province":"West-Vlaanderen",
    "wof:name":"Vrije Basisschool",
    "wof:placetype":"venue"
},
  "geometry": {"coordinates":[2.7376389503,50.9320106506],"type":"Point"}
}