{
  "type": "Feature",
  "properties": {
    "iso:country":"BE",
    "sg:address":"Rue Sainte-aldegonde 6",
    "sg:city":"Tournai",
    "sg:orig_category":"Slagers",
    "sg:phone":"+32 69 22 36 92",
    "sg:postcode":"7540",
    "sg:province":"Hainaut",
    "wof:name":"Paul Vanhoolandt",
    "wof:placetype":"venue"
},
  "geometry": {"coordinates":[3.3840470314,50.6298446655],"type":"Point"}
}