{
  "type": "Feature",
  "properties": {
    "addr:full":"Elsbosstraat 17 Dendermonde Oost-Vlaanderen 9200",
    "addr:housenumber":"17",
    "addr:postcode":"9200",
    "addr:street":"Elsbosstraat;Oost-Vlaanderen",
    "iso:country":"BE",
    "sg:address":"Elsbosstraat 17",
    "sg:city":"Dendermonde",
    "sg:orig_category":"Woningbouw",
    "sg:phone":"+32 52 21 90 94",
    "sg:postcode":"9200",
    "sg:province":"Oost-Vlaanderen",
    "wof:name":"Andr\u00c8 Vera",
    "wof:placetype":"venue"
},
  "geometry": {"coordinates":[4.1196990013,51.025100708],"type":"Point"}
}