{
  "type": "Feature",
  "properties": {
    "addr:full":"Kazernelaan 14 Houthalen-helchteren (helchteren) Limburg 3530",
    "addr:housenumber":"14",
    "addr:postcode":"3530",
    "addr:street":"Kazernelaan",
    "iso:country":"BE",
    "sg:address":"Kazernelaan 14",
    "sg:city":"Houthalen-helchteren (helchteren)",
    "sg:classifiers":[
        {
            "category":"Shopping",
            "subcategory":"Florist",
            "type":"Retail Goods"
        }
    ],
    "sg:phone":"+32 11 60 15 74",
    "sg:postcode":"3530",
    "sg:province":"Limburg",
    "wof:name":"Biedermeier (de)",
    "wof:placetype":"venue"
},
  "geometry": {"coordinates":[5.3719201088,51.0310020447],"type":"Point"}
}