{
  "type": "Feature",
  "properties": {
    "addr:full":"Avenue Du Centenaire 4 Nivelles Brabant Wallon 1400",
    "addr:housenumber":"4",
    "addr:postcode":"1400",
    "addr:street":"Avenue Du Centenaire",
    "iso:country":"BE",
    "sg:address":"Avenue Du Centenaire 4",
    "sg:city":"Nivelles",
    "sg:orig_category":"Advocaten and juridische adviseurs",
    "sg:phone":"+32 67 21 83 85",
    "sg:postcode":"1400",
    "sg:province":"Brabant Wallon",
    "wof:name":"J.l. Denis",
    "wof:placetype":"venue"
},
  "geometry": {"coordinates":[4.3329777718,50.5938148499],"type":"Point"}
}