{
  "type": "Feature",
  "properties": {
    "addr:full":"Dorpsstraat 17 Brugge (sint-michiels) West-Vlaanderen 8200",
    "addr:housenumber":"17",
    "addr:postcode":"8200",
    "addr:street":"Dorpsstraat",
    "iso:country":"BE",
    "sg:address":"Dorpsstraat 17",
    "sg:city":"Brugge (sint-michiels)",
    "sg:classifiers":[
        {
            "category":"Shopping",
            "subcategory":"Bicycles & Sporting Goods",
            "type":"Retail Goods"
        }
    ],
    "sg:phone":"+32 50 38 54 89",
    "sg:postcode":"8200",
    "sg:province":"West-Vlaanderen",
    "sg:tags":[
        "-"
    ],
    "wof:name":"Crappe K",
    "wof:placetype":"venue"
},
  "geometry": {"coordinates":[3.2133600712,51.1883010864],"type":"Point"}
}