{
  "type": "Feature",
  "properties": {
    "addr:full":"Veemarkt 13 Mechelen Antwerpen 2800",
    "addr:housenumber":"13",
    "addr:postcode":"2800",
    "addr:street":"Veemarkt",
    "iso:country":"BE",
    "sg:address":"Veemarkt 13",
    "sg:city":"Mechelen",
    "sg:classifiers":[
        {
            "category":"Shopping",
            "subcategory":"Pets & Pet Supplies",
            "type":"Retail Goods"
        }
    ],
    "sg:phone":"+32 15 27 00 29",
    "sg:postcode":"2800",
    "sg:province":"Antwerpen",
    "sg:tags":[
        "shop",
        "-"
    ],
    "wof:name":"Kakelnest ('t)",
    "wof:placetype":"venue"
},
  "geometry": {"coordinates":[4.483520031,51.0289535522],"type":"Point"}
}