{
  "type": "Feature",
  "properties": {
    "iso:country":"BE",
    "sg:address":"Eikestraat 38",
    "sg:city":"Mechelen",
    "sg:classifiers":[
        {
            "category":"Professional",
            "subcategory":"Management & Consulting",
            "type":"Services"
        }
    ],
    "sg:phone":"+32 15 33 75 63",
    "sg:postcode":"2800",
    "sg:province":"Antwerpen",
    "sg:tags":[
        "consultant"
    ],
    "wof:name":"A-tes",
    "wof:placetype":"venue"
},
  "geometry": {"coordinates":[4.4748687744,51.0439186096],"type":"Point"}
}