{
  "type": "Feature",
  "properties": {
    "addr:full":"Place Jules Mansart 24-25 La Louvi\u00e8re Hainaut 7100",
    "addr:housenumber":"24-25",
    "addr:postcode":"7100",
    "addr:street":"Place Jules Mansart",
    "iso:country":"BE",
    "sg:address":"Place Jules Mansart 24-25",
    "sg:city":"La Louvi\u00e8re",
    "sg:classifiers":[
        {
            "category":"Cafe",
            "type":"Food & Drink"
        }
    ],
    "sg:phone":"+32 64 21 70 89",
    "sg:postcode":"7100",
    "sg:province":"Hainaut",
    "sg:tags":[
        "snack-bars"
    ],
    "wof:name":"Centre (le Snack Du)",
    "wof:placetype":"venue"
},
  "geometry": {"coordinates":[4.1854400635,50.4752388],"type":"Point"}
}