{
  "type": "Feature",
  "properties": {
    "iso:country":"BE",
    "sg:address":"Rue Groeselenberg 200",
    "sg:city":"Bruxelles (uccle)",
    "sg:classifiers":[
        {
            "category":"Communications",
            "subcategory":"Film & Video Production",
            "type":"Services"
        }
    ],
    "sg:phone":"+32 2 375 77 37",
    "sg:postcode":"1180",
    "sg:province":"Bruxelles-Capitale",
    "sg:tags":[
        "movie",
        "maker"
    ],
    "wof:name":"Cinequation Sprl",
    "wof:placetype":"venue"
},
  "geometry": {"coordinates":[4.3568120003,50.8036422729],"type":"Point"}
}