{
  "type": "Feature",
  "properties": {
    "addr:full":"Pulsebaan 54 Zandhoven (pulderbos) Antwerpen 2242",
    "addr:housenumber":"54",
    "addr:postcode":"2242",
    "addr:street":"Pulsebaan",
    "iso:country":"BE",
    "sg:address":"Pulsebaan 54",
    "sg:city":"Zandhoven (pulderbos)",
    "sg:classifiers":[
        {
            "category":"Manufacturing",
            "subcategory":"Food",
            "type":"Manufacturing & Wholesale Goods"
        }
    ],
    "sg:phone":"+32 3 489 22 95",
    "sg:postcode":"2242",
    "sg:province":"Antwerpen",
    "sg:tags":[
        "equipment"
    ],
    "wof:name":"Denatec-lerco",
    "wof:placetype":"venue"
},
  "geometry": {"coordinates":[4.6949238777,51.2124328613],"type":"Point"}
}