{
  "type": "Feature",
  "properties": {
    "addr:full":"Kramersplein 15 Gent Oost-Vlaanderen 9000",
    "addr:housenumber":"15",
    "addr:postcode":"9000",
    "addr:street":"Kramersplein;Oost-Vlaanderen",
    "iso:country":"BE",
    "sg:address":"Kramersplein 15",
    "sg:city":"Gent",
    "sg:classifiers":[
        {
            "category":"Bars & Pubs",
            "type":"Food & Drink"
        }
    ],
    "sg:phone":"+32 9 329 04 19",
    "sg:postcode":"9000",
    "sg:province":"Oost-Vlaanderen",
    "wof:name":"Yucca",
    "wof:placetype":"venue"
},
  "geometry": {"coordinates":[3.7264940739,51.0413169861],"type":"Point"}
}