{
  "type": "Feature",
  "properties": {
    "addr:full":"Markt 22 Waregem West-Vlaanderen 8790",
    "addr:housenumber":"22",
    "addr:postcode":"8790",
    "addr:street":"Markt",
    "iso:country":"BE",
    "sg:address":"Markt 22",
    "sg:city":"Waregem",
    "sg:classifiers":[
        {
            "category":"Cafe",
            "type":"Food & Drink"
        }
    ],
    "sg:phone":"+32 56 60 11 97",
    "sg:postcode":"8790",
    "sg:province":"West-Vlaanderen",
    "sg:tags":[
        "caf\u00e9s"
    ],
    "wof:name":"De Gouden Leeuw",
    "wof:placetype":"venue"
},
  "geometry": {"coordinates":[3.4317800999,50.8867416382],"type":"Point"}
}