{
  "type": "Feature",
  "properties": {
    "addr:full":"Peperstraat 73 Eeklo Oost-Vlaanderen 9900",
    "addr:housenumber":"73",
    "addr:postcode":"9900",
    "addr:street":"Peperstraat",
    "iso:country":"BE",
    "sg:address":"Peperstraat 73",
    "sg:city":"Eeklo",
    "sg:orig_category":"Pain, p\u00e2tisseries and confiseries",
    "sg:phone":"+32 9 377 05 80",
    "sg:postcode":"9900",
    "sg:province":"Oost-Vlaanderen",
    "wof:name":"Confiserie De Clercq",
    "wof:placetype":"venue"
},
  "geometry": {"coordinates":[3.5720350742,51.2043762207],"type":"Point"}
}