{
  "type": "Feature",
  "properties": {
    "iso:country":"BE",
    "sg:address":"Beukenhofstraat 21",
    "sg:city":"Anzegem",
    "sg:orig_category":"Opticiens",
    "sg:phone":"+32 56 77 80 88",
    "sg:postcode":"8570",
    "sg:province":"West-Vlaanderen",
    "wof:name":"Optiek Synhaeve",
    "wof:placetype":"venue"
},
  "geometry": {"coordinates":[3.3987360001,50.8369293213],"type":"Point"}
}