{
  "type": "Feature",
  "properties": {
    "iso:country":"BE",
    "sg:address":"Rue De La Cornette 28",
    "sg:city":"Binche (buvrinnes)",
    "sg:classifiers":[
        {
            "category":"Health Services",
            "subcategory":"Doctor",
            "type":"Services"
        }
    ],
    "sg:phone":"+32 64 36 89 96",
    "sg:postcode":"7133",
    "sg:province":"Hainaut",
    "sg:tags":[
        "medicinephysicians",
        "surgeon"
    ],
    "wof:name":"Dachy Christian",
    "wof:placetype":"venue"
},
  "geometry": {"coordinates":[4.2089209557,50.3880348206],"type":"Point"}
}