{
  "type": "Feature",
  "properties": {
    "addr:full":"Imbeekstraat 16 Herne Vlaams-Brabant 1540",
    "addr:housenumber":"16",
    "addr:postcode":"1540",
    "addr:street":"Imbeekstraat",
    "iso:country":"BE",
    "sg:address":"Imbeekstraat 16",
    "sg:city":"Herne",
    "sg:classifiers":[
        {
            "category":"Building & Trades",
            "subcategory":"Construction",
            "type":"Services"
        }
    ],
    "sg:phone":"+32 2 396 28 20",
    "sg:postcode":"1540",
    "sg:province":"Vlaams-Brabant",
    "sg:tags":[
        "carpenter"
    ],
    "wof:name":"Decoster Jean-pierre & Zoon",
    "wof:placetype":"venue"
},
  "geometry": {"coordinates":[4.0112709999,50.7298431396],"type":"Point"}
}