{
  "type": "Feature",
  "properties": {
    "addr:full":"Frederik Sheidlaan 21 Aartselaar Antwerpen 2630",
    "addr:housenumber":"21",
    "addr:postcode":"2630",
    "addr:street":"Frederik Sheidlaan",
    "iso:country":"BE",
    "sg:address":"Frederik Sheidlaan 21",
    "sg:city":"Aartselaar",
    "sg:classifiers":[
        {
            "category":"Real Estate",
            "subcategory":"Architect",
            "type":"Services"
        }
    ],
    "sg:phone":"+32 3 887 39 73",
    "sg:postcode":"2630",
    "sg:province":"Antwerpen",
    "wof:name":"Van Der Stighelen R",
    "wof:placetype":"venue"
},
  "geometry": {"coordinates":[4.3810667992,51.1327095032],"type":"Point"}
}