{
  "type": "Feature",
  "properties": {
    "iso:country":"BE",
    "sg:address":"Rue H. Berge 38",
    "sg:city":"Bruxelles",
    "sg:orig_category":"Diverse bedrijfsbeheeradviesbureaus",
    "sg:phone":"+32 2 216 98 02",
    "sg:postcode":"1030",
    "sg:province":"Bruxelles-Capitale",
    "wof:name":"Flamme P.",
    "wof:placetype":"venue"
},
  "geometry": {"coordinates":[4.3756079674,50.8653373718],"type":"Point"}
}