{
  "type": "Feature",
  "properties": {
    "iso:country":"BE",
    "sg:address":"Steenstraat 49",
    "sg:city":"Brugge",
    "sg:orig_category":"Dameskledingzaken",
    "sg:phone":"+32 50 33 14 49",
    "sg:postcode":"8000",
    "sg:province":"West-Vlaanderen",
    "wof:name":"Pr\u00c9maman",
    "wof:placetype":"venue"
},
  "geometry": {"coordinates":[3.2229909897,51.2071533203],"type":"Point"}
}