{
  "type": "Feature",
  "properties": {
    "iso:country":"BE",
    "sg:address":"Westerlosesteenweg 100",
    "sg:city":"Heist-op-den-berg",
    "sg:orig_category":"Eleveurs de bovins",
    "sg:phone":"+32 15 24 90 04",
    "sg:postcode":"2220",
    "sg:province":"Antwerpen",
    "wof:name":"Gustaaf Verschueren",
    "wof:placetype":"venue"
},
  "geometry": {"coordinates":[4.755218029,51.0673141479],"type":"Point"}
}