{
  "type": "Feature",
  "properties": {
    "iso:country":"BE",
    "sg:address":"Meulenven 15",
    "sg:city":"Hamme",
    "sg:orig_category":"Notarissen",
    "sg:phone":"+32 13 61 07 20",
    "sg:postcode":"3945",
    "sg:province":"Limburg",
    "wof:name":"Vroninks M.",
    "wof:placetype":"venue"
},
  "geometry": {"coordinates":[5.1776199341,51.1046104431],"type":"Point"}
}