{
  "type": "Feature",
  "properties": {
    "addr:full":"Rue Des Orphelins 14 Soignies Hainaut 7060",
    "addr:housenumber":"14",
    "addr:postcode":"7060",
    "addr:street":"Rue Des Orphelins",
    "iso:country":"BE",
    "sg:address":"Rue Des Orphelins 14",
    "sg:city":"Soignies",
    "sg:orig_category":"Formation permanente",
    "sg:phone":"+32 67 33 28 99",
    "sg:postcode":"7060",
    "sg:province":"Hainaut",
    "wof:name":"Inst. Techn. Prom.sociale",
    "wof:placetype":"venue"
},
  "geometry": {"coordinates":[4.0695581436,50.5779685974],"type":"Point"}
}