{
  "type": "Feature",
  "properties": {
    "addr:full":"Chauss\u00c9e De Wavre 860 Etterbeek Bruxelles-Capitale 1040",
    "addr:housenumber":"860",
    "addr:postcode":"1040",
    "addr:street":"Chausse\u0301E De Wavre",
    "iso:country":"BE",
    "sg:address":"Chauss\u00c9e De Wavre 860",
    "sg:city":"Etterbeek",
    "sg:orig_category":"Schoonheidssalons",
    "sg:phone":"+32 2 649 17 83",
    "sg:postcode":"1040",
    "sg:province":"Bruxelles-Capitale",
    "wof:name":"Dream Nails /o.i.p",
    "wof:placetype":"venue"
},
  "geometry": {"coordinates":[4.3939452171,50.8282852173],"type":"Point"}
}