{
  "type": "Feature",
  "properties": {
    "iso:country":"BE",
    "sg:address":"Route De L'auneu 9",
    "sg:city":"Manhay (odeigne)",
    "sg:classifiers":[
        {
            "category":"Building & Trades",
            "subcategory":"Landscaping Services",
            "type":"Services"
        }
    ],
    "sg:phone":"+32 86 45 59 49",
    "sg:postcode":"6960",
    "sg:province":"Luxembourg",
    "sg:tags":[
        "gardening",
        "garden",
        "maintenance"
    ],
    "wof:name":"Monfort B",
    "wof:placetype":"venue"
},
  "geometry": {"coordinates":[5.6863360405,50.2587966919],"type":"Point"}
}