{
  "type": "Feature",
  "properties": {
    "iso:country":"BE",
    "sg:address":"De Villegas De Clercampstraat 56",
    "sg:city":"Grimbergen (strombeek-bever)",
    "sg:classifiers":[
        {
            "category":"Shopping",
            "subcategory":"Gifts & Souvenirs",
            "type":"Retail Goods"
        }
    ],
    "sg:phone":"+32 2 267 65 97",
    "sg:postcode":"1853",
    "sg:province":"Vlaams-Brabant",
    "sg:tags":[
        "-"
    ],
    "wof:name":"Pimpernel",
    "wof:placetype":"venue"
},
  "geometry": {"coordinates":[4.3516812325,50.9092750549],"type":"Point"}
}