{
  "type": "Feature",
  "properties": {
    "addr:full":"Boulevard Lambermont 191 Bruxelles (schaerbeek) Bruxelles-Capitale 1030",
    "addr:housenumber":"191",
    "addr:postcode":"1030",
    "addr:street":"Boulevard Lambermont",
    "iso:country":"BE",
    "sg:address":"Boulevard Lambermont 191",
    "sg:city":"Bruxelles (schaerbeek)",
    "sg:classifiers":[
        {
            "category":"Professional",
            "subcategory":"Art Services",
            "type":"Services"
        }
    ],
    "sg:phone":"+32 2 216 43 51",
    "sg:postcode":"1030",
    "sg:province":"Bruxelles-Capitale",
    "sg:tags":[
        "design",
        "packing",
        "-",
        "realization"
    ],
    "wof:name":"Design Et Production Sa",
    "wof:placetype":"venue"
},
  "geometry": {"coordinates":[4.3827490807,50.8702163696],"type":"Point"}
}