{
  "type": "Feature",
  "properties": {
    "iso:country":"BE",
    "sg:address":"Professor Dewulfstraat 9",
    "sg:city":"Poperinge",
    "sg:classifiers":[
        {
            "category":"Insurance",
            "subcategory":"Insurance Agent",
            "type":"Services"
        }
    ],
    "sg:phone":"+32 57 33 39 50",
    "sg:postcode":"8970",
    "sg:province":"West-Vlaanderen",
    "sg:tags":[
        "broker"
    ],
    "wof:name":"Naessens Nv",
    "wof:placetype":"venue"
},
  "geometry": {"coordinates":[2.7296659946,50.8537368774],"type":"Point"}
}