{
  "type": "Feature",
  "properties": {
    "addr:full":"Avenue De La Lib\u00c9ration 79 Fernelmont Namur 5380",
    "addr:housenumber":"79",
    "addr:postcode":"5380",
    "addr:street":"Avenue De La Libe\u0301Ration",
    "iso:country":"BE",
    "sg:address":"Avenue De La Lib\u00c9ration 79",
    "sg:city":"Fernelmont",
    "sg:orig_category":"Catering and organisation de f\u00eates",
    "sg:phone":"+32 81 83 45 20",
    "sg:postcode":"5380",
    "sg:province":"Namur",
    "wof:name":"Viviane Depas",
    "wof:placetype":"venue"
},
  "geometry": {"coordinates":[4.9861078262,50.5531463623],"type":"Point"}
}