{
  "type": "Feature",
  "properties": {
    "iso:country":"BE",
    "sg:address":"Noordhoekstraat 59",
    "sg:city":"De Panne",
    "sg:orig_category":"Mat\u00e9riel m\u00e9dical and orthop\u00e9dique and proth\u00e8ses Fab",
    "sg:phone":"+32 58 41 25 70",
    "sg:postcode":"8660",
    "sg:province":"West-Vlaanderen",
    "wof:name":"Willy Vanlerberghe",
    "wof:placetype":"venue"
},
  "geometry": {"coordinates":[2.6072409153,51.0757904053],"type":"Point"}
}