{
  "type": "Feature",
  "properties": {
    "addr:full":"Kloosterstraat 1b6 Antwerpen Antwerpen 2000",
    "addr:housenumber":"1b6",
    "addr:postcode":"2000",
    "addr:street":"Kloosterstraat",
    "iso:country":"BE",
    "sg:address":"Kloosterstraat 1b6",
    "sg:city":"Antwerpen",
    "sg:classifiers":[
        {
            "category":"Arena",
            "subcategory":"Sports Club",
            "type":"Entertainment"
        }
    ],
    "sg:phone":"+32 3 232 91 94",
    "sg:postcode":"2000",
    "sg:province":"Antwerpen",
    "sg:tags":[
        "de"
    ],
    "wof:name":"Kendo Antwerpen",
    "wof:placetype":"venue"
},
  "geometry": {"coordinates":[4.396009922,51.2173156738],"type":"Point"}
}