{
  "type": "Feature",
  "properties": {
    "addr:full":"Place Raoul Nachez 12 Charleroi (gosselies) Hainaut 6041",
    "addr:housenumber":"12",
    "addr:postcode":"6041",
    "addr:street":"Place Raoul Nachez",
    "iso:country":"BE",
    "sg:address":"Place Raoul Nachez 12",
    "sg:city":"Charleroi (gosselies)",
    "sg:classifiers":[
        {
            "category":"Social Services",
            "subcategory":"Child Care",
            "type":"Services"
        }
    ],
    "sg:phone":"+32 71 31 47 79",
    "sg:postcode":"6041",
    "sg:province":"Hainaut",
    "sg:tags":[
        "home"
    ],
    "wof:name":"Accueil (l') Asbl",
    "wof:placetype":"venue"
},
  "geometry": {"coordinates":[4.4314317703,50.4685935974],"type":"Point"}
}