{
  "type": "Feature",
  "properties": {
    "addr:full":"Rue Haute-wez 84 Li\u00e8ge 1 (grivegn\u00e9e) Li\u00e8ge 4030",
    "addr:housenumber":"84;1",
    "addr:postcode":"4030",
    "addr:street":"Rue Haute-Wez",
    "iso:country":"BE",
    "sg:address":"Rue Haute-wez 84",
    "sg:city":"Li\u00e8ge 1 (grivegn\u00e9e)",
    "sg:classifiers":[
        {
            "category":"Health Services",
            "subcategory":"Doctor",
            "type":"Services"
        }
    ],
    "sg:phone":"+32 4 341 15 88",
    "sg:postcode":"4030",
    "sg:province":"Li\u00e8ge",
    "sg:tags":[
        "psychotherapist",
        "psychoanalyst"
    ],
    "wof:name":"Soto Gustavo Sensus International",
    "wof:placetype":"venue"
},
  "geometry": {"coordinates":[5.5927090645,50.6251335144],"type":"Point"}
}