{
  "type": "Feature",
  "properties": {
    "iso:country":"BE",
    "sg:address":"Veldstraat 290",
    "sg:city":"Brasschaat",
    "sg:orig_category":"Non-Classified Establishments",
    "sg:phone":"+32 3 226 41 06",
    "sg:postcode":"2930",
    "sg:province":"Antwerpen",
    "wof:name":"Carrousel Nv",
    "wof:placetype":"venue"
},
  "geometry": {"coordinates":[4.4815602303,51.3014945984],"type":"Point"}
}