{
  "type": "Feature",
  "properties": {
    "iso:country":"BE",
    "sg:address":"Oppelsenweg 94",
    "sg:city":"Zonhoven",
    "sg:classifiers":[
        {
            "category":"Retail",
            "subcategory":"Veterinary Services",
            "type":"Services"
        }
    ],
    "sg:phone":"+32 11 81 50 87",
    "sg:postcode":"3520",
    "sg:province":"Limburg",
    "sg:tags":[
        "veterinarian"
    ],
    "wof:name":"Van Der Vliet F",
    "wof:placetype":"venue"
},
  "geometry": {"coordinates":[5.3946971893,50.9916114807],"type":"Point"}
}