{
  "type": "Feature",
  "properties": {
    "iso:country":"BE",
    "sg:address":"Lichtaartseweg 233",
    "sg:city":"Herentals",
    "sg:classifiers":[
        {
            "category":"Real Estate",
            "subcategory":"Real Estate Services",
            "type":"Services"
        }
    ],
    "sg:phone":"+32 14 21 21 33",
    "sg:postcode":"2200",
    "sg:province":"Antwerpen",
    "wof:name":"Ceulemans A",
    "wof:placetype":"venue"
},
  "geometry": {"coordinates":[4.8570837975,51.1958236694],"type":"Point"}
}