{
  "type": "Feature",
  "properties": {
    "addr:full":"Statiestraat 11 Riemst Limburg 3770",
    "addr:housenumber":"11",
    "addr:postcode":"3770",
    "addr:street":"Statiestraat",
    "iso:country":"BE",
    "sg:address":"Statiestraat 11",
    "sg:city":"Riemst",
    "sg:orig_category":"Assurances. Bureaux de poste",
    "sg:phone":"+32 12 45 11 77",
    "sg:postcode":"3770",
    "sg:province":"Limburg",
    "wof:name":"De Post",
    "wof:placetype":"venue"
},
  "geometry": {"coordinates":[5.5969901085,50.8109016418],"type":"Point"}
}