{
  "type": "Feature",
  "properties": {
    "iso:country":"BE",
    "sg:address":"Rue Des Gaillettes 3",
    "sg:city":"Herve (battice)",
    "sg:classifiers":[
        {
            "category":"Shopping",
            "subcategory":"Discount & Variety Stores",
            "type":"Retail Goods"
        }
    ],
    "sg:phone":"+32 87 69 29 12",
    "sg:postcode":"4651",
    "sg:province":"Li\u00e8ge",
    "sg:tags":[
        "warehouse",
        "-",
        "merchandise"
    ],
    "wof:name":"T.s.r.",
    "wof:placetype":"venue"
},
  "geometry": {"coordinates":[5.8131871223,50.6486358643],"type":"Point"}
}