{
  "type": "Feature",
  "properties": {
    "addr:full":"Rue Du Centre 54 Clavier Li\u00e8ge 4560",
    "addr:housenumber":"54",
    "addr:postcode":"4560",
    "addr:street":"Rue Du Centre",
    "iso:country":"BE",
    "sg:address":"Rue Du Centre 54",
    "sg:city":"Clavier",
    "sg:orig_category":"V\u00e9t\u00e9rinaires",
    "sg:phone":"+32 85 41 28 46",
    "sg:postcode":"4560",
    "sg:province":"Li\u00e8ge",
    "wof:name":"Yves Gielen",
    "wof:placetype":"venue"
},
  "geometry": {"coordinates":[5.3014497757,50.4160499573],"type":"Point"}
}