{
  "type": "Feature",
  "properties": {
    "addr:full":"Dendermondse Steenweg 138 Aalst Oost-Vlaanderen 9300",
    "addr:housenumber":"138",
    "addr:postcode":"9300",
    "addr:street":"Steenweg",
    "iso:country":"BE",
    "sg:address":"Dendermondse Steenweg 138",
    "sg:city":"Aalst",
    "sg:orig_category":"Antiquit\u00e9s. Bijouteries and horlogeries. R\u00e9parations d'horloges, montres and bijoux",
    "sg:phone":"+32 53 77 49 26",
    "sg:postcode":"9300",
    "sg:province":"Oost-Vlaanderen",
    "wof:name":"Arthur Abe",
    "wof:placetype":"venue"
},
  "geometry": {"coordinates":[4.0480899811,50.951839447],"type":"Point"}
}