{
  "type": "Feature",
  "properties": {
    "addr:full":"Sint-elooisstraat 6 Oostkamp West-Vlaanderen 8020",
    "addr:housenumber":"6",
    "addr:postcode":"8020",
    "addr:street":"Sint-Elooisstraat",
    "iso:country":"BE",
    "sg:address":"Sint-elooisstraat 6",
    "sg:city":"Oostkamp",
    "sg:orig_category":"Rev\u00eatements pour sols and murs. Drogueries. Peinture",
    "sg:phone":"+32 50 27 85 85",
    "sg:postcode":"8020",
    "sg:province":"West-Vlaanderen",
    "wof:name":"Michel Gernaey Christin",
    "wof:placetype":"venue"
},
  "geometry": {"coordinates":[3.2075119019,51.0963058472],"type":"Point"}
}