{
  "type": "Feature",
  "properties": {
    "iso:country":"BE",
    "sg:address":"Oude Vest 117",
    "sg:city":"Dendermonde",
    "sg:orig_category":"Instruments de musique",
    "sg:phone":"+32 52 21 00 19",
    "sg:postcode":"9200",
    "sg:province":"Oost-Vlaanderen",
    "wof:name":"Pianohandel Janssens",
    "wof:placetype":"venue"
},
  "geometry": {"coordinates":[4.1033768654,51.0300865173],"type":"Point"}
}