{
  "type": "Feature",
  "properties": {
    "iso:country":"BE",
    "sg:address":"Pastorijstraat 239",
    "sg:city":"Tienen",
    "sg:orig_category":"Kapsalons",
    "sg:phone":"+32 16 82 33 13",
    "sg:postcode":"3300",
    "sg:province":"Vlaams-Brabant",
    "wof:name":"Coiffure Wendy",
    "wof:placetype":"venue"
},
  "geometry": {"coordinates":[4.9216141701,50.7876091003],"type":"Point"}
}