{
  "type": "Feature",
  "properties": {
    "iso:country":"BE",
    "sg:address":"Rue De Tourcoing 108",
    "sg:city":"Mouscron",
    "sg:classifiers":[
        {
            "category":"Shopping",
            "subcategory":"Clothing, Apparel, & Fashions",
            "type":"Retail Goods"
        }
    ],
    "sg:phone":"+32 56 33 47 27",
    "sg:postcode":"7700",
    "sg:province":"Hainaut",
    "sg:tags":[
        "boutique"
    ],
    "wof:name":"Gavroche",
    "wof:placetype":"venue"
},
  "geometry": {"coordinates":[3.2097899914,50.7441291809],"type":"Point"}
}