{
  "type": "Feature",
  "properties": {
    "addr:full":"Stientjesstraat 6 Anzegem West-Vlaanderen 8570",
    "addr:housenumber":"6",
    "addr:postcode":"8570",
    "addr:street":"Stientjesstraat",
    "iso:country":"BE",
    "sg:address":"Stientjesstraat 6",
    "sg:city":"Anzegem",
    "sg:orig_category":"Non-Classified Establishments",
    "sg:phone":"+32 56 68 02 37",
    "sg:postcode":"8570",
    "sg:province":"West-Vlaanderen",
    "wof:name":"Luco Kaas Bvba",
    "wof:placetype":"venue"
},
  "geometry": {"coordinates":[3.4405829906,50.8468437195],"type":"Point"}
}