{
  "type": "Feature",
  "properties": {
    "iso:country":"BE",
    "sg:address":"Willibrordusstraat 14",
    "sg:city":"Ravels",
    "sg:classifiers":[
        {
            "category":"Insurance",
            "subcategory":"Insurance Agent",
            "type":"Services"
        }
    ],
    "sg:phone":"+32 14 65 95 26",
    "sg:postcode":"2382",
    "sg:province":"Antwerpen",
    "sg:tags":[
        "verzekeringsmakelaars",
        "expert"
    ],
    "wof:name":"Hans Ramsdonck",
    "wof:placetype":"venue"
},
  "geometry": {"coordinates":[5.041768074,51.4469108582],"type":"Point"}
}