{
  "type": "Feature",
  "properties": {
    "iso:country":"BE",
    "sg:address":"Rue Fontenelle 37",
    "sg:city":"Orp-jauche",
    "sg:orig_category":"Elektrische installaties voor woningen",
    "sg:phone":"+32 19 63 21 44",
    "sg:postcode":"1350",
    "sg:province":"Brabant Wallon",
    "wof:name":"Deco-elec",
    "wof:placetype":"venue"
},
  "geometry": {"coordinates":[4.97920084,50.6738891602],"type":"Point"}
}