{
  "type": "Feature",
  "properties": {
    "addr:full":"Kerkstraat 62-2 Lokeren Oost-Vlaanderen 9160",
    "addr:housenumber":"62-2",
    "addr:postcode":"9160",
    "addr:street":"Kerkstraat",
    "iso:country":"BE",
    "sg:address":"Kerkstraat 62-2",
    "sg:city":"Lokeren",
    "sg:classifiers":[
        {
            "category":"Shopping",
            "subcategory":"Clothing, Apparel, & Fashions",
            "type":"Retail Goods"
        }
    ],
    "sg:phone":"+32 9 339 07 00",
    "sg:postcode":"9160",
    "sg:province":"Oost-Vlaanderen",
    "sg:tags":[
        "-",
        "clothing",
        "child"
    ],
    "wof:name":"Tomasetti",
    "wof:placetype":"venue"
},
  "geometry": {"coordinates":[3.9939239025,51.1030235291],"type":"Point"}
}