{
  "type": "Feature",
  "properties": {
    "addr:full":"Oude Heerbaan 13 Aalst Oost-Vlaanderen 9300",
    "addr:housenumber":"13",
    "addr:postcode":"9300",
    "addr:street":"Oude Heerbaan",
    "iso:country":"BE",
    "sg:address":"Oude Heerbaan 13",
    "sg:city":"Aalst",
    "sg:classifiers":[
        {
            "category":"Personal",
            "subcategory":"Nail Salon",
            "type":"Services"
        }
    ],
    "sg:phone":"+32 53 77 65 39",
    "sg:postcode":"9300",
    "sg:province":"Oost-Vlaanderen",
    "sg:tags":[
        "pedicure"
    ],
    "wof:name":"Phaedra",
    "wof:placetype":"venue"
},
  "geometry": {"coordinates":[4.0004000664,50.9406814575],"type":"Point"}
}