{
  "type": "Feature",
  "properties": {
    "addr:full":"Hoogstraat 87 Meise Vlaams-Brabant 1861",
    "addr:housenumber":"87",
    "addr:postcode":"1861",
    "addr:street":"Hoogstraat",
    "iso:country":"BE",
    "sg:address":"Hoogstraat 87",
    "sg:city":"Meise",
    "sg:orig_category":"Postzegels, munten and trofee\u00ebn Sport- and kampeermateriaal",
    "sg:phone":"+32 2 269 31 75",
    "sg:postcode":"1861",
    "sg:province":"Vlaams-Brabant",
    "wof:name":"Sos Biljart - Cornelis",
    "wof:placetype":"venue"
},
  "geometry": {"coordinates":[4.3138542175,50.9542884827],"type":"Point"}
}