{
  "type": "Feature",
  "properties": {
    "addr:full":"Dammesteenweg 4 Damme West-Vlaanderen 8340",
    "addr:housenumber":"4",
    "addr:postcode":"8340",
    "addr:street":"Dammesteenweg",
    "iso:country":"BE",
    "sg:address":"Dammesteenweg 4",
    "sg:city":"Damme",
    "sg:classifiers":[
        {
            "category":"Personal",
            "type":"Services"
        }
    ],
    "sg:phone":"+32 50 33 07 56",
    "sg:postcode":"8340",
    "sg:province":"West-Vlaanderen",
    "sg:tags":[
        "party",
        "planning"
    ],
    "wof:name":"De Kleine Rietgans",
    "wof:placetype":"venue"
},
  "geometry": {"coordinates":[3.2762329578,51.2569541931],"type":"Point"}
}