{
  "type": "Feature",
  "properties": {
    "iso:country":"BE",
    "sg:address":"Rue De Merbes 194",
    "sg:city":"Binche",
    "sg:classifiers":[
        {
            "category":"Organizations",
            "subcategory":"Community Association",
            "type":"Services"
        }
    ],
    "sg:phone":"+32 64 34 18 56",
    "sg:postcode":"7130",
    "sg:province":"Hainaut",
    "sg:tags":[
        "environment",
        "organisation",
        "-"
    ],
    "wof:name":"Blondiau G",
    "wof:placetype":"venue"
},
  "geometry": {"coordinates":[4.1712818146,50.4045295715],"type":"Point"}
}