{
  "type": "Feature",
  "properties": {
    "iso:country":"BE",
    "sg:address":"Ch.de Saint-ghislain 49",
    "sg:city":"Chievres",
    "sg:orig_category":"Bloemen and planten Boomkwekerijen Tuinen",
    "sg:phone":"+32 68 65 74 84",
    "sg:postcode":"7950",
    "sg:province":"Hainaut",
    "wof:name":"Willy Galant",
    "wof:placetype":"venue"
},
  "geometry": {"coordinates":[3.805850029,50.5805587769],"type":"Point"}
}