{
  "type": "Feature",
  "properties": {
    "addr:full":"Rue Du Brouck 27 Juprelle Li\u00e8ge 4450",
    "addr:housenumber":"27",
    "addr:postcode":"4450",
    "addr:street":"Rue Du Brouck",
    "iso:country":"BE",
    "sg:address":"Rue Du Brouck 27",
    "sg:city":"Juprelle",
    "sg:classifiers":[
        {
            "category":"Cafe",
            "type":"Food & Drink"
        }
    ],
    "sg:phone":"+32 4 263 92 09",
    "sg:postcode":"4450",
    "sg:province":"Li\u00e8ge",
    "sg:tags":[
        "caf\u00e9s"
    ],
    "wof:name":"Yvan Kricfalusi",
    "wof:placetype":"venue"
},
  "geometry": {"coordinates":[5.5271511078,50.687374115],"type":"Point"}
}