{
  "type": "Feature",
  "properties": {
    "addr:full":"Tervuursevest 11 Leuven Vlaams-Brabant 3001",
    "addr:housenumber":"11",
    "addr:postcode":"3001",
    "addr:street":"Tervuursevest",
    "iso:country":"BE",
    "sg:address":"Tervuursevest 11",
    "sg:city":"Leuven",
    "sg:orig_category":"Agences de voyages",
    "sg:phone":"+32 16 22 07 53",
    "sg:postcode":"3001",
    "sg:province":"Vlaams-Brabant",
    "wof:name":"Reizen Universitas Int.",
    "wof:placetype":"venue"
},
  "geometry": {"coordinates":[4.6827630997,50.8766021729],"type":"Point"}
}