{
  "type": "Feature",
  "properties": {
    "addr:full":"Mezenstraat 8 Mechelen Antwerpen 2800",
    "addr:housenumber":"8",
    "addr:postcode":"2800",
    "addr:street":"Mezenstraat",
    "iso:country":"BE",
    "sg:address":"Mezenstraat 8",
    "sg:city":"Mechelen",
    "sg:orig_category":"Brood, gebak and snoepgoed",
    "sg:phone":"+32 15 20 28 41",
    "sg:postcode":"2800",
    "sg:province":"Antwerpen",
    "wof:name":"Ahmed Intizar",
    "wof:placetype":"venue"
},
  "geometry": {"coordinates":[4.4703598022,51.0488395691],"type":"Point"}
}