{
  "type": "Feature",
  "properties": {
    "addr:full":"Veldkruisstraat 14 Knesselare Oost-Vlaanderen 9910",
    "addr:housenumber":"14",
    "addr:postcode":"9910",
    "addr:street":"Veldkruisstraat;Oost-Vlaanderen",
    "iso:country":"BE",
    "sg:address":"Veldkruisstraat 14",
    "sg:city":"Knesselare",
    "sg:orig_category":"Eleveurs de volaille",
    "sg:phone":"+32 9 374 33 86",
    "sg:postcode":"9910",
    "sg:province":"Oost-Vlaanderen",
    "wof:name":"Marleen Wille",
    "wof:placetype":"venue"
},
  "geometry": {"coordinates":[3.5051300526,51.1302604675],"type":"Point"}
}