{
  "type": "Feature",
  "properties": {
    "iso:country":"BE",
    "sg:address":"Rue Grand\u00b4route 277",
    "sg:city":"Beyne-heusay",
    "sg:classifiers":[
        {
            "category":"Restaurant",
            "type":"Food & Drink"
        }
    ],
    "sg:phone":"+32 4 355 08 66",
    "sg:postcode":"4610",
    "sg:province":"Li\u00e8ge",
    "sg:tags":[
        "organisation",
        "de",
        "f\u00eates",
        "catering"
    ],
    "wof:name":"Restaurant Belmonte 2",
    "wof:placetype":"venue"
},
  "geometry": {"coordinates":[5.6595230103,50.6202468872],"type":"Point"}
}