{
  "type": "Feature",
  "properties": {
    "iso:country":"BE",
    "sg:address":"Boulevard Industriel 50",
    "sg:city":"Mouscron",
    "sg:classifiers":[
        {
            "category":"Bars & Pubs",
            "type":"Food & Drink"
        }
    ],
    "sg:phone":"+32 56 33 48 38",
    "sg:postcode":"7700",
    "sg:province":"Hainaut",
    "wof:name":"Brin D'zinc (au)",
    "wof:placetype":"venue"
},
  "geometry": {"coordinates":[3.2424299717,50.747428894],"type":"Point"}
}