{
  "type": "Feature",
  "properties": {
    "iso:country":"BE",
    "sg:address":"Kardinaal Cardijnstraat 21",
    "sg:city":"Lier",
    "sg:classifiers":[
        {
            "category":"Food & Beverages",
            "subcategory":"Dairy",
            "type":"Retail Goods"
        }
    ],
    "sg:phone":"+32 3 480 65 62",
    "sg:postcode":"2500",
    "sg:province":"Antwerpen",
    "sg:tags":[
        "product",
        "-"
    ],
    "wof:name":"Kennes W",
    "wof:placetype":"venue"
},
  "geometry": {"coordinates":[4.5774178505,51.1321105957],"type":"Point"}
}