{
  "type": "Feature",
  "properties": {
    "iso:country":"BE",
    "sg:address":"Centrum 1",
    "sg:city":"Herne",
    "sg:orig_category":"Pain, p\u00e2tisseries and confiseries",
    "sg:phone":"+32 2 396 20 42",
    "sg:postcode":"1540",
    "sg:province":"Vlaams-Brabant",
    "wof:name":"Bakkerij Edelweiss",
    "wof:placetype":"venue"
},
  "geometry": {"coordinates":[4.0267510414,50.7243461609],"type":"Point"}
}