{
  "type": "Feature",
  "properties": {
    "addr:full":"Industriepark E17/3 Lokeren Oost-Vlaanderen 9160",
    "addr:housenumber":"e17 / 3",
    "addr:postcode":"9160",
    "addr:street":"Industriepark;Lokeren Oost-Vlaanderen",
    "iso:country":"BE",
    "sg:address":"Industriepark E17/3",
    "sg:city":"Lokeren",
    "sg:orig_category":"Non-Classified Establishments",
    "sg:phone":"+32 9 353 91 11",
    "sg:postcode":"9160",
    "sg:province":"Oost-Vlaanderen",
    "wof:name":"Rittal Nv",
    "wof:placetype":"venue"
},
  "geometry": {"coordinates":[4.031619072,51.093547821],"type":"Point"}
}