{
  "type": "Feature",
  "properties": {
    "addr:full":"Pieter Van Reysschootlaan 2 Gent Oost-Vlaanderen 9051",
    "addr:housenumber":"2",
    "addr:postcode":"9051",
    "addr:street":"Pieter Van Reysschootlaan;Oost-Vlaanderen",
    "iso:country":"BE",
    "sg:address":"Pieter Van Reysschootlaan 2",
    "sg:city":"Gent",
    "sg:orig_category":"Avocats and conseillers juridiques",
    "sg:phone":"+32 9 220 20 00",
    "sg:postcode":"9051",
    "sg:province":"Oost-Vlaanderen",
    "wof:name":"Christophe Poppe",
    "wof:placetype":"venue"
},
  "geometry": {"coordinates":[3.6839799881,51.0187416077],"type":"Point"}
}