{
  "type": "Feature",
  "properties": {
    "iso:country":"BE",
    "sg:address":"Kortrijkstr 372",
    "sg:city":"Wevelgem",
    "sg:classifiers":[
        {
            "category":"Home & Garden",
            "subcategory":"Furniture",
            "type":"Retail Goods"
        }
    ],
    "sg:phone":"+32 56 41 74 27",
    "sg:postcode":"8560",
    "sg:province":"West-Vlaanderen",
    "sg:tags":[
        "household",
        "wood"
    ],
    "wof:name":"Lafosse Nv",
    "wof:placetype":"venue"
},
  "geometry": {"coordinates":[3.2086191177,50.8158683777],"type":"Point"}
}