{
  "type": "Feature",
  "properties": {
    "addr:full":"Gustaaf De Ridderstraat 6 Sint-niklaas Oost-Vlaanderen 9100",
    "addr:housenumber":"6",
    "addr:postcode":"9100",
    "addr:street":"Gustaaf De Ridderstraat",
    "iso:country":"BE",
    "sg:address":"Gustaaf De Ridderstraat 6",
    "sg:city":"Sint-niklaas",
    "sg:classifiers":[
        {
            "category":"Professional",
            "subcategory":"Lawyer & Legal Services",
            "type":"Services"
        }
    ],
    "sg:phone":"+32 3 766 36 02",
    "sg:postcode":"9100",
    "sg:province":"Oost-Vlaanderen",
    "wof:name":"Bogaerts Herman",
    "wof:placetype":"venue"
},
  "geometry": {"coordinates":[4.1632499695,51.1739044189],"type":"Point"}
}