{
  "type": "Feature",
  "properties": {
    "addr:full":"Mechelsesteenweg 195 Antwerpen Antwerpen 2018",
    "addr:housenumber":"195",
    "addr:postcode":"2018",
    "addr:street":"Mechelsesteenweg",
    "iso:country":"BE",
    "sg:address":"Mechelsesteenweg 195",
    "sg:city":"Antwerpen",
    "sg:orig_category":"Avocats and conseillers juridiques",
    "sg:phone":"+32 3 239 10 47",
    "sg:postcode":"2018",
    "sg:province":"Antwerpen",
    "wof:name":"Renate Proost",
    "wof:placetype":"venue"
},
  "geometry": {"coordinates":[4.4119668007,51.2034301758],"type":"Point"}
}