{
  "type": "Feature",
  "properties": {
    "iso:country":"BE",
    "sg:address":"Chauss\u00c9e De Bruxelles 16",
    "sg:city":"Vorst/forest",
    "sg:orig_category":"Pain, p\u00e2tisseries and confiseries",
    "sg:phone":"+32 2 376 91 25",
    "sg:postcode":"1190",
    "sg:province":"Bruxelles-Capitale",
    "wof:name":"Moujib",
    "wof:placetype":"venue"
},
  "geometry": {"coordinates":[4.3177819252,50.8107376099],"type":"Point"}
}