{
  "type": "Feature",
  "properties": {
    "addr:full":"Chauss\u00c9e De Bruxelles 255 Edingen/enghien Hainaut 7850",
    "addr:housenumber":"255",
    "addr:postcode":"7850",
    "addr:street":"Chausse\u0301E De Bruxelles",
    "iso:country":"BE",
    "sg:address":"Chauss\u00c9e De Bruxelles 255",
    "sg:city":"Edingen/enghien",
    "sg:orig_category":"Assurances. Agences de voyages",
    "sg:phone":"+32 2 395 69 59",
    "sg:postcode":"7850",
    "sg:province":"Hainaut",
    "wof:name":"Vannyvel Trips",
    "wof:placetype":"venue"
},
  "geometry": {"coordinates":[4.0693712234,50.6899375916],"type":"Point"}
}