{
  "type": "Feature",
  "properties": {
    "iso:country":"BE",
    "sg:address":"Moulin De Boiron 128",
    "sg:city":"Gedinne (sart-custinne)",
    "sg:classifiers":[
        {
            "category":"Travel",
            "subcategory":"Hotels & Motels",
            "type":"Entertainment"
        }
    ],
    "sg:phone":"+32 61 58 99 59",
    "sg:postcode":"5575",
    "sg:province":"Namur",
    "wof:name":"Moulin De Boiron ***",
    "wof:placetype":"venue"
},
  "geometry": {"coordinates":[4.905646801,49.9910125732],"type":"Point"}
}