{
  "type": "Feature",
  "properties": {
    "iso:country":"BE",
    "sg:address":"Blauwenhoek 2 Box 2",
    "sg:city":"Londerzeel",
    "sg:classifiers":[
        {
            "category":"Building & Trades",
            "subcategory":"Pest Control",
            "type":"Services"
        }
    ],
    "sg:phone":"+32 52 30 91 82",
    "sg:postcode":"1840",
    "sg:province":"Vlaams-Brabant",
    "sg:tags":[
        "painting",
        "contractor"
    ],
    "wof:name":"De Pauw E",
    "wof:placetype":"venue"
},
  "geometry": {"coordinates":[4.2942152023,51.0150413513],"type":"Point"}
}