{
  "type": "Feature",
  "properties": {
    "iso:country":"BE",
    "sg:address":"Chauss\u00c9e De Louvain 111",
    "sg:city":"Eghezee",
    "sg:classifiers":[
        {
            "category":"Fast Food",
            "type":"Food & Drink"
        }
    ],
    "sg:phone":"+32 81 81 32 28",
    "sg:postcode":"5310",
    "sg:province":"Namur",
    "sg:tags":[
        "\u00c0",
        "restaurants",
        "emporter",
        "restaurant"
    ],
    "wof:name":"Le Palais Du Dragon",
    "wof:placetype":"venue"
},
  "geometry": {"coordinates":[4.9027252197,50.6002693176],"type":"Point"}
}