{
  "type": "Feature",
  "properties": {
    "addr:full":"Markt 80 Temse Oost-Vlaanderen 9140",
    "addr:housenumber":"80",
    "addr:postcode":"9140",
    "addr:street":"Markt",
    "iso:country":"BE",
    "sg:address":"Markt 80",
    "sg:city":"Temse",
    "sg:orig_category":"Diverse kredietdiensten",
    "sg:postcode":"9140",
    "sg:province":"Oost-Vlaanderen",
    "wof:name":"Postomat Temse",
    "wof:placetype":"venue"
},
  "geometry": {"coordinates":[4.213203907,51.1244087219],"type":"Point"}
}