{
  "type": "Feature",
  "properties": {
    "addr:full":"Rue Longue 69 Chatelet Hainaut 6200",
    "addr:housenumber":"69",
    "addr:postcode":"6200",
    "addr:street":"Rue Longue;Hainaut",
    "iso:country":"BE",
    "sg:address":"Rue Longue 69",
    "sg:city":"Chatelet",
    "sg:orig_category":"Agences de presse",
    "sg:phone":"+32 71 50 26 79",
    "sg:postcode":"6200",
    "sg:province":"Hainaut",
    "wof:name":"Benoit Wattier",
    "wof:placetype":"venue"
},
  "geometry": {"coordinates":[4.495059967,50.374786377],"type":"Point"}
}