{
  "type": "Feature",
  "properties": {
    "iso:country":"BE",
    "sg:address":"Bisschopslaan 15",
    "sg:city":"Beerse",
    "sg:orig_category":"D\u00e9corateurs d'int\u00e9rieur",
    "sg:phone":"+32 14 61 94 90",
    "sg:postcode":"2340",
    "sg:province":"Antwerpen",
    "wof:name":"Fa. P. Plus",
    "wof:placetype":"venue"
},
  "geometry": {"coordinates":[4.8565039635,51.3157691956],"type":"Point"}
}