{
  "type": "Feature",
  "properties": {
    "addr:full":"Dellestraat 32 Lummen Limburg 3560",
    "addr:housenumber":"32",
    "addr:postcode":"3560",
    "addr:street":"Dellestraat",
    "iso:country":"BE",
    "sg:address":"Dellestraat 32",
    "sg:city":"Lummen",
    "sg:orig_category":"Materials For Aeronautics And Aerospace Applications",
    "sg:phone":"+32 13 53 01 11",
    "sg:postcode":"3560",
    "sg:province":"Limburg",
    "wof:name":"Sabca Limburg Nv",
    "wof:placetype":"venue"
},
  "geometry": {"coordinates":[5.2391901016,50.9896202087],"type":"Point"}
}