{
  "type": "Feature",
  "properties": {
    "iso:country":"BE",
    "sg:address":"Hutstraat 22",
    "sg:city":"Kampenhout",
    "sg:orig_category":"Diverse organisaties and verenigingen",
    "sg:phone":"+32 16 65 04 61",
    "sg:postcode":"1910",
    "sg:province":"Vlaams-Brabant",
    "wof:name":"Jeugdhuis Tonzent",
    "wof:placetype":"venue"
},
  "geometry": {"coordinates":[4.5822691917,50.9457931519],"type":"Point"}
}