{
  "type": "Feature",
  "properties": {
    "addr:full":"Mechelsesteenweg 93 Kampenhout Vlaams-Brabant 1910",
    "addr:housenumber":"93",
    "addr:postcode":"1910",
    "addr:street":"Mechelsesteenweg",
    "iso:country":"BE",
    "sg:address":"Mechelsesteenweg 93",
    "sg:city":"Kampenhout",
    "sg:orig_category":"Installation de menuiserie m\u00e9tallique",
    "sg:phone":"+32 16 60 43 96",
    "sg:postcode":"1910",
    "sg:province":"Vlaams-Brabant",
    "wof:name":"Nordex Deuren",
    "wof:placetype":"venue"
},
  "geometry": {"coordinates":[4.5837130547,50.9614105225],"type":"Point"}
}