{
  "type": "Feature",
  "properties": {
    "addr:full":"Oelegemsesteenweg 15 Ranst Antwerpen 2520",
    "addr:housenumber":"15",
    "addr:postcode":"2520",
    "addr:street":"Oelegemsesteenweg",
    "iso:country":"BE",
    "sg:address":"Oelegemsesteenweg 15",
    "sg:city":"Ranst",
    "sg:classifiers":[
        {
            "category":"Insurance",
            "subcategory":"Life Insurance",
            "type":"Services"
        }
    ],
    "sg:phone":"+32 3 475 10 81",
    "sg:postcode":"2520",
    "sg:province":"Antwerpen",
    "sg:tags":[
        "assurance"
    ],
    "wof:name":"Insure",
    "wof:placetype":"venue"
},
  "geometry": {"coordinates":[4.6026940346,51.1859016418],"type":"Point"}
}