{
  "type": "Feature",
  "properties": {
    "addr:full":"Haachtsesteenweg 213 Schaarbeek/schaerbeek Bruxelles-Capitale 1030",
    "addr:housenumber":"213",
    "addr:postcode":"1030",
    "addr:street":"Haachtsesteenweg",
    "iso:country":"BE",
    "sg:address":"Haachtsesteenweg 213",
    "sg:city":"Schaarbeek/schaerbeek",
    "sg:orig_category":"Slagers",
    "sg:phone":"+32 2 245 11 81",
    "sg:postcode":"1030",
    "sg:province":"Bruxelles-Capitale",
    "wof:name":"Fe. Urfali Ferhat",
    "wof:placetype":"venue"
},
  "geometry": {"coordinates":[4.3718280792,50.8614425659],"type":"Point"}
}