{
  "type": "Feature",
  "properties": {
    "iso:country":"BE",
    "sg:address":"Manaihant 30-32",
    "sg:city":"Verviers",
    "sg:orig_category":"Bouwmaterialen Gh",
    "sg:phone":"+32 87 67 50 50",
    "sg:postcode":"4800",
    "sg:province":"Li\u00e8ge",
    "wof:name":"Durechain",
    "wof:placetype":"venue"
},
  "geometry": {"coordinates":[5.8594508171,50.5917663574],"type":"Point"}
}