{
  "type": "Feature",
  "properties": {
    "addr:full":"Mgr. Callewaertlaan 2 Zwevegem West-Vlaanderen 8550",
    "addr:housenumber":"2",
    "addr:postcode":"8550",
    "addr:street":"Mgr. Callewaertlaan",
    "iso:country":"BE",
    "sg:address":"Mgr. Callewaertlaan 2",
    "sg:city":"Zwevegem",
    "sg:orig_category":"Ordinateurs and \u00e9quipement informatique",
    "sg:phone":"+32 56 75 68 17",
    "sg:postcode":"8550",
    "sg:province":"West-Vlaanderen",
    "wof:name":"De Craemere",
    "wof:placetype":"venue"
},
  "geometry": {"coordinates":[3.3282730579,50.8154907227],"type":"Point"}
}