{
  "type": "Feature",
  "properties": {
    "addr:full":"Galgestraat 6 Sint-truiden Limburg 3803",
    "addr:housenumber":"6",
    "addr:postcode":"3803",
    "addr:street":"Galgestraat",
    "iso:country":"BE",
    "sg:address":"Galgestraat 6",
    "sg:city":"Sint-truiden",
    "sg:orig_category":"Parfumeries",
    "sg:phone":"+32 11 68 77 06",
    "sg:postcode":"3803",
    "sg:province":"Limburg",
    "wof:name":"Edgard Dessers",
    "wof:placetype":"venue"
},
  "geometry": {"coordinates":[5.1465730667,50.8346138],"type":"Point"}
}