{
  "type": "Feature",
  "properties": {
    "addr:full":"Nieuwe St-annadreef 23 Sint-andries West-Vlaanderen 8200",
    "addr:housenumber":"23",
    "addr:postcode":"8200",
    "addr:street":"Nieuwe St-Annadreef",
    "iso:country":"BE",
    "sg:address":"Nieuwe St-annadreef 23",
    "sg:city":"Sint-andries",
    "sg:classifiers":[
        {
            "category":"Wholesale",
            "subcategory":"Office Equipment",
            "type":"Manufacturing & Wholesale Goods"
        }
    ],
    "sg:phone":"+32 50 40 45 30",
    "sg:postcode":"8200",
    "sg:province":"West-Vlaanderen",
    "sg:tags":[
        "development",
        "designing"
    ],
    "wof:name":"Ingenium Nv",
    "wof:placetype":"venue"
},
  "geometry": {"coordinates":[3.1730010509,51.1912498474],"type":"Point"}
}