{
  "type": "Feature",
  "properties": {
    "addr:full":"Begijnenstraat 28 Turnhout Antwerpen 2300",
    "addr:housenumber":"28",
    "addr:postcode":"2300",
    "addr:street":"Begijnenstraat",
    "iso:country":"BE",
    "sg:address":"Begijnenstraat 28",
    "sg:city":"Turnhout",
    "sg:classifiers":[
        {
            "category":"Museum",
            "type":"Entertainment"
        }
    ],
    "sg:phone":"+32 14 43 63 35",
    "sg:postcode":"2300",
    "sg:province":"Antwerpen",
    "wof:name":"Taxandria",
    "wof:placetype":"venue"
},
  "geometry": {"coordinates":[4.947414875,51.3246192932],"type":"Point"}
}