{
  "type": "Feature",
  "properties": {
    "iso:country":"BE",
    "sg:address":"24 Av Franklin Roosevelt",
    "sg:city":"Bruxelles",
    "sg:classifiers":[
        {
            "category":"Professional",
            "subcategory":"Business Services",
            "type":"Services"
        }
    ],
    "sg:phone":"+32 2 627 57 70",
    "sg:postcode":"1050",
    "sg:province":"Bruxelles-Capitale",
    "sg:tags":[
        "body",
        "advice"
    ],
    "wof:name":"Bureau Of International Recycling",
    "wof:placetype":"venue"
},
  "geometry": {"coordinates":[4.3786501884,50.8128662109],"type":"Point"}
}