{
  "type": "Feature",
  "properties": {
    "iso:country":"BE",
    "sg:address":"Avenue Des Combattants 66",
    "sg:city":"Court-saint-etienne",
    "sg:orig_category":"Diverse kredietdiensten",
    "sg:postcode":"1490",
    "sg:province":"Brabant Wallon",
    "wof:name":"Bancontact-mister Cash",
    "wof:placetype":"venue"
},
  "geometry": {"coordinates":[4.5626811981,50.6478347778],"type":"Point"}
}