{
  "type": "Feature",
  "properties": {
    "iso:country":"BE",
    "sg:address":"Avenue Des Grenadiers 4",
    "sg:city":"Elsene/ixelles",
    "sg:orig_category":"Production de films, t\u00e9l\u00e9films and vid\u00e9os",
    "sg:phone":"+32 2 660 02 05",
    "sg:postcode":"1050",
    "sg:province":"Bruxelles-Capitale",
    "wof:name":"Fabrice Saudoyez",
    "wof:placetype":"venue"
},
  "geometry": {"coordinates":[4.3904972076,50.810710907],"type":"Point"}
}