{
  "type": "Feature",
  "properties": {
    "addr:full":"Tuinbouwlaan 20 Dilbeek Vlaams-Brabant 1700",
    "addr:housenumber":"20",
    "addr:postcode":"1700",
    "addr:street":"Tuinbouwlaan",
    "iso:country":"BE",
    "sg:address":"Tuinbouwlaan 20",
    "sg:city":"Dilbeek",
    "sg:classifiers":[
        {
            "category":"Professional",
            "subcategory":"Management & Consulting",
            "type":"Services"
        }
    ],
    "sg:phone":"+32 2 569 41 88",
    "sg:postcode":"1700",
    "sg:province":"Vlaams-Brabant",
    "sg:tags":[
        "-",
        "processing",
        "data",
        "consultant"
    ],
    "wof:name":"Rodem Consulting Bvba",
    "wof:placetype":"venue"
},
  "geometry": {"coordinates":[4.2691059113,50.8414840698],"type":"Point"}
}