{
  "type": "Feature",
  "properties": {
    "addr:full":"Boulevard Ernest Solvay 539 Li\u00c8ge Li\u00e8ge 4000",
    "addr:housenumber":"539",
    "addr:postcode":"4000",
    "addr:street":"Boulevard Ernest Solvay",
    "iso:country":"BE",
    "sg:address":"Boulevard Ernest Solvay 539",
    "sg:city":"Li\u00c8ge",
    "sg:orig_category":"Diverse kredietdiensten",
    "sg:postcode":"4000",
    "sg:province":"Li\u00e8ge",
    "wof:name":"Bancontact-mister Cash",
    "wof:placetype":"venue"
},
  "geometry": {"coordinates":[5.595536232,50.6618232727],"type":"Point"}
}