{
  "type": "Feature",
  "properties": {
    "addr:full":"Rue De La Wallonie 12 Tournai Hainaut 7500",
    "addr:housenumber":"12",
    "addr:postcode":"7500",
    "addr:street":"Rue De La Wallonie",
    "iso:country":"BE",
    "sg:address":"Rue De La Wallonie 12",
    "sg:city":"Tournai",
    "sg:classifiers":[
        {
            "category":"Social Services",
            "subcategory":"Job Training",
            "type":"Services"
        }
    ],
    "sg:phone":"+32 69 84 02 60",
    "sg:postcode":"7500",
    "sg:province":"Hainaut",
    "sg:tags":[
        "personnel",
        "-selection",
        "recruitment"
    ],
    "wof:name":"Carl Adams Nv",
    "wof:placetype":"venue"
},
  "geometry": {"coordinates":[3.3889920712,50.6051597595],"type":"Point"}
}