{
  "type": "Feature",
  "properties": {
    "addr:full":"Rue De La Gare 19ba Bertrix Luxembourg 6880",
    "addr:housenumber":"19ba",
    "addr:postcode":"6880",
    "addr:street":"Rue De La Gare",
    "iso:country":"BE",
    "sg:address":"Rue De La Gare 19ba",
    "sg:city":"Bertrix",
    "sg:orig_category":"Assurances. Bureaux de poste",
    "sg:phone":"+32 61 41 13 11",
    "sg:postcode":"6880",
    "sg:province":"Luxembourg",
    "wof:name":"La Poste",
    "wof:placetype":"venue"
},
  "geometry": {"coordinates":[5.2539558411,49.8552055359],"type":"Point"}
}