{
  "type": "Feature",
  "properties": {
    "addr:full":"Albert 1-laan 230 Nieuwpoort West-Vlaanderen 8620",
    "addr:housenumber":"230",
    "addr:postcode":"8620",
    "addr:street":"Albert",
    "iso:country":"BE",
    "sg:address":"Albert 1-laan 230",
    "sg:city":"Nieuwpoort",
    "sg:orig_category":"Verlichting and huishoudartikelen",
    "sg:phone":"+32 58 24 26 24",
    "sg:postcode":"8620",
    "sg:province":"West-Vlaanderen",
    "wof:name":"Interieur Design Devos",
    "wof:placetype":"venue"
},
  "geometry": {"coordinates":[2.7124409676,51.1470069885],"type":"Point"}
}