{
  "type": "Feature",
  "properties": {
    "addr:full":"Kerkstraat 3 Baarle-hertog Antwerpen 2387",
    "addr:housenumber":"3",
    "addr:postcode":"2387",
    "addr:street":"Kerkstraat",
    "iso:country":"BE",
    "sg:address":"Kerkstraat 3",
    "sg:city":"Baarle-hertog",
    "sg:orig_category":"V\u00eatements pour Hommes",
    "sg:phone":"+32 14 69 94 05",
    "sg:postcode":"2387",
    "sg:province":"Antwerpen",
    "wof:name":"Pour Vous Madame",
    "wof:placetype":"venue"
},
  "geometry": {"coordinates":[4.9303388596,51.441986084],"type":"Point"}
}