{
  "type": "Feature",
  "properties": {
    "addr:full":"Rue Des Pr\u00c9s 3 Merbes-le-chateau Hainaut 6567",
    "addr:housenumber":"3",
    "addr:postcode":"6567",
    "addr:street":"Rue Des Pre\u0301S;Hainaut",
    "iso:country":"BE",
    "sg:address":"Rue Des Pr\u00c9s 3",
    "sg:city":"Merbes-le-chateau",
    "sg:orig_category":"Plomberie, chauffage and installations sanitaires. Installation de piscines. Installation de menuise",
    "sg:phone":"+32 71 55 78 17",
    "sg:postcode":"6567",
    "sg:province":"Hainaut",
    "wof:name":"Menuiserie Desalle- Deroo",
    "wof:placetype":"venue"
},
  "geometry": {"coordinates":[4.2112731934,50.3217964172],"type":"Point"}
}