{
  "type": "Feature",
  "properties": {
    "iso:country":"BE",
    "sg:address":"March\u00e9 Aux Herbes 25",
    "sg:city":"Mons",
    "sg:classifiers":[
        {
            "category":"Bars & Pubs",
            "type":"Food & Drink"
        }
    ],
    "sg:phone":"+32 65 33 79 97",
    "sg:postcode":"7000",
    "sg:province":"Hainaut",
    "wof:name":"Arnaque (l')",
    "wof:placetype":"venue"
},
  "geometry": {"coordinates":[3.9527060986,50.4529914856],"type":"Point"}
}