{
  "type": "Feature",
  "properties": {
    "addr:full":"Rue Saint-martin 106 L\u00e9glise (ebly) Luxembourg 6860",
    "addr:housenumber":"106",
    "addr:postcode":"6860",
    "addr:street":"Rue Saint-Martin",
    "iso:country":"BE",
    "sg:address":"Rue Saint-martin 106",
    "sg:city":"L\u00e9glise (ebly)",
    "sg:classifiers":[
        {
            "category":"Home & Garden",
            "subcategory":"Household Appliances",
            "type":"Retail Goods"
        }
    ],
    "sg:phone":"+32 61 25 53 32",
    "sg:postcode":"6860",
    "sg:province":"Luxembourg",
    "sg:tags":[
        "repair",
        "mainten",
        "-",
        "electric"
    ],
    "wof:name":"Bontemps Ph",
    "wof:placetype":"venue"
},
  "geometry": {"coordinates":[5.5340590477,49.8487205505],"type":"Point"}
}