{
  "type": "Feature",
  "properties": {
    "addr:full":"Kerkhovensesteenweg 7 Hechtel-eksel Limburg 3941",
    "addr:housenumber":"7",
    "addr:postcode":"3941",
    "addr:street":"Kerkhovensesteenweg",
    "iso:country":"BE",
    "sg:address":"Kerkhovensesteenweg 7",
    "sg:city":"Hechtel-eksel",
    "sg:classifiers":[
        {
            "category":"Arena",
            "subcategory":"Sports Club",
            "type":"Entertainment"
        }
    ],
    "sg:phone":"+32 11 40 22 27",
    "sg:postcode":"3941",
    "sg:province":"Limburg",
    "sg:tags":[
        "de"
    ],
    "wof:name":"Leopold I-stappers",
    "wof:placetype":"venue"
},
  "geometry": {"coordinates":[5.394862175,51.1539764404],"type":"Point"}
}