{
  "type": "Feature",
  "properties": {
    "addr:full":"Bredabaan 512 Brasschaat Antwerpen 2930",
    "addr:housenumber":"512",
    "addr:postcode":"2930",
    "addr:street":"Bredabaan",
    "iso:country":"BE",
    "sg:address":"Bredabaan 512",
    "sg:city":"Brasschaat",
    "sg:orig_category":"Meubelen, niet-elektrische huishoudapparaten and vloerbekleding Gh",
    "sg:phone":"+32 3 651 40 89",
    "sg:postcode":"2930",
    "sg:province":"Antwerpen",
    "wof:name":"Mondial M. Ex.",
    "wof:placetype":"venue"
},
  "geometry": {"coordinates":[4.500079155,51.2995491028],"type":"Point"}
}