{
  "type": "Feature",
  "properties": {
    "iso:country":"BE",
    "sg:address":"Rue Du Vin\u00c2ve 5",
    "sg:city":"Stavelot",
    "sg:classifiers":[
        {
            "category":"Cafe",
            "type":"Food & Drink"
        }
    ],
    "sg:phone":"+32 80 88 04 46",
    "sg:postcode":"4970",
    "sg:province":"Li\u00e8ge",
    "sg:tags":[
        "caf\u00e9s"
    ],
    "wof:name":"Yvette Liket",
    "wof:placetype":"venue"
},
  "geometry": {"coordinates":[5.9289608002,50.3940086365],"type":"Point"}
}