{
  "type": "Feature",
  "properties": {
    "iso:country":"BE",
    "sg:address":"Statiestraat 19",
    "sg:city":"Mol",
    "sg:orig_category":"Parfumeries",
    "sg:phone":"+32 14 31 03 39",
    "sg:postcode":"2400",
    "sg:province":"Antwerpen",
    "wof:name":"Parfumerie Christy",
    "wof:placetype":"venue"
},
  "geometry": {"coordinates":[5.1170978546,51.1912193298],"type":"Point"}
}