{
  "type": "Feature",
  "properties": {
    "addr:full":"Avenue Paul Pastur 361 Charleroi (mont-sur-marchienne) Hainaut 6032",
    "addr:housenumber":"361",
    "addr:postcode":"6032",
    "addr:street":"Avenue Paul Pastur",
    "iso:country":"BE",
    "sg:address":"Avenue Paul Pastur 361",
    "sg:city":"Charleroi (mont-sur-marchienne)",
    "sg:classifiers":[
        {
            "category":"Professional",
            "subcategory":"Computer Services",
            "type":"Services"
        }
    ],
    "sg:phone":"+32 71 28 62 22",
    "sg:postcode":"6032",
    "sg:province":"Hainaut",
    "sg:tags":[
        "-",
        "processing",
        "data",
        "software"
    ],
    "wof:name":"S.b.i.m. Sa",
    "wof:placetype":"venue"
},
  "geometry": {"coordinates":[4.4221520424,50.3980979919],"type":"Point"}
}