{
  "type": "Feature",
  "properties": {
    "iso:country":"BE",
    "sg:address":"Kapittellaan 27",
    "sg:city":"Meise",
    "sg:classifiers":[
        {
            "category":"Health Services",
            "subcategory":"Health Practitioner",
            "type":"Services"
        }
    ],
    "sg:phone":"+32 2 269 40 14",
    "sg:postcode":"1860",
    "sg:province":"Vlaams-Brabant",
    "sg:tags":[
        "physiotherapist"
    ],
    "wof:name":"Jansegers Dirk",
    "wof:placetype":"venue"
},
  "geometry": {"coordinates":[4.3341078758,50.9377975464],"type":"Point"}
}