{
  "type": "Feature",
  "properties": {
    "addr:full":"Kiezelweg 241 Lanaken Limburg 3620",
    "addr:housenumber":"241",
    "addr:postcode":"3620",
    "addr:street":"Kiezelweg",
    "iso:country":"BE",
    "sg:address":"Kiezelweg 241",
    "sg:city":"Lanaken",
    "sg:orig_category":"Banken and kredietinstellingen",
    "sg:phone":"+32 89 71 54 47",
    "sg:postcode":"3620",
    "sg:province":"Limburg",
    "wof:name":"Citibank",
    "wof:placetype":"venue"
},
  "geometry": {"coordinates":[5.6303129196,50.8812713623],"type":"Point"}
}