{
  "type": "Feature",
  "properties": {
    "iso:country":"BE",
    "sg:address":"Bredabaan 448",
    "sg:city":"Wuustwezel",
    "sg:orig_category":"Studios photographiques",
    "sg:phone":"+32 3 669 84 69",
    "sg:postcode":"2990",
    "sg:province":"Antwerpen",
    "wof:name":"Veerle Konings",
    "wof:placetype":"venue"
},
  "geometry": {"coordinates":[4.5922088623,51.3907432556],"type":"Point"}
}