{
  "type": "Feature",
  "properties": {
    "iso:country":"BE",
    "sg:address":"Vrijheid 41",
    "sg:city":"Arendonk",
    "sg:classifiers":[
        {
            "category":"Restaurant",
            "type":"Food & Drink"
        }
    ],
    "sg:phone":"+32 14 67 78 59",
    "sg:postcode":"2370",
    "sg:province":"Antwerpen",
    "wof:name":"Ijssalon Eskimo",
    "wof:placetype":"venue"
},
  "geometry": {"coordinates":[5.0880889893,51.3209686279],"type":"Point"}
}