{
  "type": "Feature",
  "properties": {
    "iso:country":"BE",
    "sg:address":"Duisburgsesteenweg 176",
    "sg:city":"Overijse",
    "sg:classifiers":[
        {
            "category":"Cafe",
            "type":"Food & Drink"
        }
    ],
    "sg:phone":"+32 2 687 73 05",
    "sg:postcode":"3090",
    "sg:province":"Vlaams-Brabant",
    "sg:tags":[
        "caf\u00e9s"
    ],
    "wof:name":"Jeannine Vanoverloop",
    "wof:placetype":"venue"
},
  "geometry": {"coordinates":[4.5501031876,50.799282074],"type":"Point"}
}