{
  "type": "Feature",
  "properties": {
    "addr:full":"Rue Des Fiefs 27 P\u00e9ruwelz (brasmenil) Hainaut 7604",
    "addr:housenumber":"27",
    "addr:postcode":"7604",
    "addr:street":"Rue Des Fiefs",
    "iso:country":"BE",
    "sg:address":"Rue Des Fiefs 27",
    "sg:city":"P\u00e9ruwelz (brasmenil)",
    "sg:classifiers":[
        {
            "category":"Home & Garden",
            "subcategory":"Kitchen Supply",
            "type":"Retail Goods"
        }
    ],
    "sg:phone":"+32 69 77 63 43",
    "sg:postcode":"7604",
    "sg:province":"Hainaut",
    "sg:tags":[
        "installation"
    ],
    "wof:name":"Paulet P",
    "wof:placetype":"venue"
},
  "geometry": {"coordinates":[3.5344200134,50.532699585],"type":"Point"}
}