{
  "type": "Feature",
  "properties": {
    "iso:country":"BE",
    "sg:address":"Bld De Smet De Naeyer 229",
    "sg:city":"Jette",
    "sg:orig_category":"Enseignement maternel and primaire",
    "sg:phone":"+32 2 427 28 56",
    "sg:postcode":"1090",
    "sg:province":"Bruxelles-Capitale",
    "wof:name":"E.f.l. St.pierre",
    "wof:placetype":"venue"
},
  "geometry": {"coordinates":[4.3308677673,50.8768577576],"type":"Point"}
}