{
  "type": "Feature",
  "properties": {
    "addr:full":"Dorp-oost 16 Lochristi Oost-Vlaanderen 9080",
    "addr:housenumber":"16",
    "addr:postcode":"9080",
    "addr:street":"Dorp-Oost",
    "iso:country":"BE",
    "sg:address":"Dorp-oost 16",
    "sg:city":"Lochristi",
    "sg:classifiers":[
        {
            "category":"Bakery",
            "type":"Food & Drink"
        }
    ],
    "sg:phone":"+32 9 355 50 89",
    "sg:postcode":"9080",
    "sg:province":"Oost-Vlaanderen",
    "sg:tags":[
        "confectioner",
        "baker"
    ],
    "wof:name":"De Waele",
    "wof:placetype":"venue"
},
  "geometry": {"coordinates":[3.8346860409,51.0965156555],"type":"Point"}
}