{
  "type": "Feature",
  "properties": {
    "iso:country":"BE",
    "sg:address":"Chauss\u00e9e De Dinant 357 Box 13",
    "sg:city":"Namur",
    "sg:classifiers":[
        {
            "category":"Real Estate",
            "subcategory":"Architect",
            "type":"Services"
        }
    ],
    "sg:phone":"+32 81 46 09 75",
    "sg:postcode":"5000",
    "sg:province":"Namur",
    "wof:name":"Honor\u00e9 J-c",
    "wof:placetype":"venue"
},
  "geometry": {"coordinates":[4.8592500687,50.4400291443],"type":"Point"}
}