{
  "type": "Feature",
  "properties": {
    "iso:country":"BE",
    "sg:address":"100",
    "sg:city":"Bd. Brand Whitlock 1200 Woluwe St Lambert",
    "sg:classifiers":[
        {
            "category":"Travel",
            "subcategory":"Hotels & Motels",
            "type":"Entertainment"
        }
    ],
    "sg:phone":"+32 2 735 56 55",
    "sg:postcode":"100",
    "sg:tags":[
        "hotels",
        "business",
        "restaurant"
    ],
    "wof:name":"Le Martin Pecheur Sa",
    "wof:placetype":"venue"
},
  "geometry": {"coordinates":[4.4052147865,50.8446617126],"type":"Point"}
}