{
  "type": "Feature",
  "properties": {
    "iso:country":"BE",
    "sg:address":"Veldstraat 118",
    "sg:city":"Brecht",
    "sg:classifiers":[
        {
            "category":"Freight",
            "type":"Transportation"
        }
    ],
    "sg:phone":"+32 3 313 89 59",
    "sg:postcode":"2960",
    "sg:province":"Antwerpen",
    "sg:tags":[
        "-",
        "transport"
    ],
    "wof:name":"Transzode",
    "wof:placetype":"venue"
},
  "geometry": {"coordinates":[4.6432352066,51.3686294556],"type":"Point"}
}