{
  "type": "Feature",
  "properties": {
    "addr:full":"Rue Sainte-quirin 1 Oupeye Li\u00e8ge 4682",
    "addr:housenumber":"1",
    "addr:postcode":"4682",
    "addr:street":"Rue Sainte-Quirin",
    "iso:country":"BE",
    "sg:address":"Rue Sainte-quirin 1",
    "sg:city":"Oupeye",
    "sg:orig_category":"Airconditioning and ventilatie Loodgieterij, verwarming and sanitaire installaties",
    "sg:phone":"+32 4 286 26 38",
    "sg:postcode":"4682",
    "sg:province":"Li\u00e8ge",
    "wof:name":"M.t.t.",
    "wof:placetype":"venue"
},
  "geometry": {"coordinates":[5.6338701248,50.7312393188],"type":"Point"}
}