{
  "type": "Feature",
  "properties": {
    "addr:full":"Oude Wijnendalestraat 58 Torhout West-Vlaanderen 8820",
    "addr:housenumber":"58",
    "addr:postcode":"8820",
    "addr:street":"Oude Wijnendalestraat",
    "iso:country":"BE",
    "sg:address":"Oude Wijnendalestraat 58",
    "sg:city":"Torhout",
    "sg:classifiers":[
        {
            "category":"Arena",
            "subcategory":"Sports Club",
            "type":"Entertainment"
        }
    ],
    "sg:phone":"+32 50 21 30 21",
    "sg:postcode":"8820",
    "sg:province":"West-Vlaanderen",
    "sg:tags":[
        "terrain",
        "hors",
        "de",
        "installation",
        "sportifs"
    ],
    "wof:name":"J.p. Mahu/ V.k. Koekelare",
    "wof:placetype":"venue"
},
  "geometry": {"coordinates":[3.0747458935,51.084815979],"type":"Point"}
}