{
  "type": "Feature",
  "properties": {
    "iso:country":"BE",
    "sg:address":"Molenstraat 159",
    "sg:city":"Roeselare",
    "sg:classifiers":[
        {
            "category":"Personal",
            "subcategory":"Nail Salon",
            "type":"Services"
        }
    ],
    "sg:phone":"+32 51 20 49 03",
    "sg:postcode":"8800",
    "sg:province":"West-Vlaanderen",
    "sg:tags":[
        "pedicure"
    ],
    "wof:name":"Vansteenkiste Mieke",
    "wof:placetype":"venue"
},
  "geometry": {"coordinates":[3.1104900837,50.9414558411],"type":"Point"}
}