{
  "type": "Feature",
  "properties": {
    "iso:country":"BE",
    "sg:address":"Avenue Minerve 5",
    "sg:city":"Bruxelles (forest)",
    "sg:classifiers":[
        {
            "category":"Shopping",
            "subcategory":"Clothing, Apparel, & Fashions",
            "type":"Retail Goods"
        }
    ],
    "sg:phone":"+32 2 343 28 46",
    "sg:postcode":"1190",
    "sg:province":"Bruxelles-Capitale",
    "sg:tags":[
        "designer",
        "stylist"
    ],
    "wof:name":"Atelier Retouche (l')",
    "wof:placetype":"venue"
},
  "geometry": {"coordinates":[4.3297610283,50.8108177185],"type":"Point"}
}