{
  "type": "Feature",
  "properties": {
    "iso:country":"BE",
    "sg:address":"Stockelsesteenweg 302",
    "sg:city":"Sint-pieters-woluwe",
    "sg:orig_category":"Beautyfarms, relaxatie and lichamelijk welzijn Elektrische huishoudapparaten, radio and televisie Gh",
    "sg:phone":"+32 2 772 10 77",
    "sg:postcode":"1150",
    "sg:province":"Bruxelles-Capitale",
    "wof:name":"Superfit",
    "wof:placetype":"venue"
},
  "geometry": {"coordinates":[4.4516501427,50.842048645],"type":"Point"}
}