{
  "type": "Feature",
  "properties": {
    "addr:full":"Naamsevest 33-1 Sint-truiden Limburg 3800",
    "addr:housenumber":"33-1",
    "addr:postcode":"3800",
    "addr:street":"Naamsevest",
    "iso:country":"BE",
    "sg:address":"Naamsevest 33-1",
    "sg:city":"Sint-truiden",
    "sg:classifiers":[
        {
            "category":"Real Estate",
            "subcategory":"Real Estate Services",
            "type":"Services"
        }
    ],
    "sg:phone":"+32 11 68 84 34",
    "sg:postcode":"3800",
    "sg:province":"Limburg",
    "wof:name":"Ipc Immo Bvba",
    "wof:placetype":"venue"
},
  "geometry": {"coordinates":[5.1878237724,50.8124694824],"type":"Point"}
}