{
  "type": "Feature",
  "properties": {
    "addr:full":"Sleepstraat 40 Gent Oost-Vlaanderen 9000",
    "addr:housenumber":"40",
    "addr:postcode":"9000",
    "addr:street":"Sleepstraat;Oost-Vlaanderen",
    "iso:country":"BE",
    "sg:address":"Sleepstraat 40",
    "sg:city":"Gent",
    "sg:orig_category":"Electrom\u00e9nager, t\u00e9l\u00e9visions and radios",
    "sg:phone":"+32 9 269 09 77",
    "sg:postcode":"9000",
    "sg:province":"Oost-Vlaanderen",
    "wof:name":"Electronic Partners",
    "wof:placetype":"venue"
},
  "geometry": {"coordinates":[3.7257730961,51.0605392456],"type":"Point"}
}