{
  "type": "Feature",
  "properties": {
    "addr:full":"Van Eyckstraat 51 Elsene/ixelles Bruxelles-Capitale 1050",
    "addr:housenumber":"51",
    "addr:postcode":"1050",
    "addr:street":"Van Eyckstraat",
    "iso:country":"BE",
    "sg:address":"Van Eyckstraat 51",
    "sg:city":"Elsene/ixelles",
    "sg:orig_category":"Boekhouders",
    "sg:phone":"+32 2 640 42 21",
    "sg:postcode":"1050",
    "sg:province":"Bruxelles-Capitale",
    "wof:name":"Cedric De Vaucleroy",
    "wof:placetype":"venue"
},
  "geometry": {"coordinates":[4.3688549995,50.8194732666],"type":"Point"}
}