{
  "type": "Feature",
  "properties": {
    "iso:country":"BE",
    "sg:address":"Rue Des D\u00e9port\u00e9s 99",
    "sg:city":"Arlon",
    "sg:classifiers":[
        {
            "category":"Health Services",
            "subcategory":"Doctor",
            "type":"Services"
        }
    ],
    "sg:phone":"+32 63 23 16 00",
    "sg:postcode":"6700",
    "sg:province":"Luxembourg",
    "sg:tags":[
        "medicinephysicians",
        "surgeon"
    ],
    "wof:name":"Kuitchoua Badjeu Jean-marc",
    "wof:placetype":"venue"
},
  "geometry": {"coordinates":[5.8208508492,49.6791954041],"type":"Point"}
}