{
  "type": "Feature",
  "properties": {
    "addr:full":"Robert Dansaertlaan 238 Groot-bijgaarden Vlaams-Brabant 1702",
    "addr:housenumber":"238",
    "addr:postcode":"groot-bijgaarden;1702",
    "addr:street":"Robert Dansaertlaan",
    "iso:country":"BE",
    "sg:address":"Robert Dansaertlaan 238",
    "sg:city":"Groot-bijgaarden",
    "sg:classifiers":[
        {
            "category":"Food & Beverages",
            "subcategory":"Meat & Fish",
            "type":"Retail Goods"
        }
    ],
    "sg:phone":"+32 2 466 71 76",
    "sg:postcode":"1702",
    "sg:province":"Vlaams-Brabant",
    "sg:tags":[
        "bacon",
        "ham"
    ],
    "wof:name":"Bdv Nv",
    "wof:placetype":"venue"
},
  "geometry": {"coordinates":[4.2590031624,50.8661117554],"type":"Point"}
}