{
  "type": "Feature",
  "properties": {
    "addr:full":"Kazandstraat 1 Pittem West-Vlaanderen 8740",
    "addr:housenumber":"1",
    "addr:postcode":"8740",
    "addr:street":"Kazandstraat",
    "iso:country":"BE",
    "sg:address":"Kazandstraat 1",
    "sg:city":"Pittem",
    "sg:orig_category":"Eleveurs de bovins",
    "sg:phone":"+32 51 40 50 89",
    "sg:postcode":"8740",
    "sg:province":"West-Vlaanderen",
    "wof:name":"Fokkerij De Mahoney",
    "wof:placetype":"venue"
},
  "geometry": {"coordinates":[3.2974200249,50.975769043],"type":"Point"}
}