{
  "type": "Feature",
  "properties": {
    "addr:full":"Nieuwstraat 20 Heist-op-den-berg Antwerpen 2222",
    "addr:housenumber":"20",
    "addr:postcode":"2222",
    "addr:street":"Nieuwstraat",
    "iso:country":"BE",
    "sg:address":"Nieuwstraat 20",
    "sg:city":"Heist-op-den-berg",
    "sg:classifiers":[
        {
            "category":"Insurance",
            "subcategory":"Life Insurance",
            "type":"Services"
        }
    ],
    "sg:phone":"+32 15 25 10 54",
    "sg:postcode":"2222",
    "sg:province":"Antwerpen",
    "sg:tags":[
        "assurance"
    ],
    "wof:name":"E. Milloen",
    "wof:placetype":"venue"
},
  "geometry": {"coordinates":[4.7262639999,51.1072006226],"type":"Point"}
}