{
  "type": "Feature",
  "properties": {
    "addr:full":"Rue Pont D'avroy 7 Liege-centre Li\u00e8ge 4000",
    "addr:housenumber":"7",
    "addr:postcode":"4000",
    "addr:street":"Rue Pont D'Avroy",
    "iso:country":"BE",
    "sg:address":"Rue Pont D'avroy 7",
    "sg:city":"Liege-centre",
    "sg:orig_category":"Opticiens Pearle Opticiens",
    "sg:phone":"+32 4 221 19 87",
    "sg:postcode":"4000",
    "sg:province":"Li\u00e8ge",
    "wof:name":"Pearle Opticiens",
    "wof:placetype":"venue"
},
  "geometry": {"coordinates":[1.0969179869,47.1787948608],"type":"Point"}
}