{
  "type": "Feature",
  "properties": {
    "iso:country":"BE",
    "sg:address":"Vlietstraat 3",
    "sg:city":"Linter (neerlinter)",
    "sg:classifiers":[
        {
            "category":"Building & Trades",
            "subcategory":"Locksmith",
            "type":"Services"
        }
    ],
    "sg:phone":"+32 11 78 13 41",
    "sg:postcode":"3350",
    "sg:province":"Vlaams-Brabant",
    "sg:tags":[
        "lock",
        "key"
    ],
    "wof:name":"Boffe Inbraakbeveiliging",
    "wof:placetype":"venue"
},
  "geometry": {"coordinates":[5.0643911362,50.8061676025],"type":"Point"}
}