{
  "type": "Feature",
  "properties": {
    "addr:full":"Industrieweg 12 Grobbendonk Antwerpen 2280",
    "addr:housenumber":"12",
    "addr:postcode":"2280",
    "addr:street":"Industrieweg",
    "iso:country":"BE",
    "sg:address":"Industrieweg 12",
    "sg:city":"Grobbendonk",
    "sg:classifiers":[
        {
            "category":"Professional",
            "subcategory":"Printing & Photocopies",
            "type":"Services"
        }
    ],
    "sg:phone":"+32 14 50 79 10",
    "sg:postcode":"2280",
    "sg:province":"Antwerpen",
    "sg:tags":[
        "engraving"
    ],
    "wof:name":"Mauquoy Medal Company",
    "wof:placetype":"venue"
},
  "geometry": {"coordinates":[4.7361121178,51.1788406372],"type":"Point"}
}