{
  "type": "Feature",
  "properties": {
    "addr:full":"Square Du Castel Fleuri 9 Watermaal-bosvoorde/watermael-boitsfort Bruxelles-Capitale 1170",
    "addr:housenumber":"9",
    "addr:postcode":"1170",
    "addr:street":"Square Du Castel Fleuri",
    "iso:country":"BE",
    "sg:address":"Square Du Castel Fleuri 9",
    "sg:city":"Watermaal-bosvoorde/watermael-boitsfort",
    "sg:orig_category":"Artistes ind\u00e9pendants",
    "sg:phone":"+32 2 660 86 04",
    "sg:postcode":"1170",
    "sg:province":"Bruxelles-Capitale",
    "wof:name":"Welsch",
    "wof:placetype":"venue"
},
  "geometry": {"coordinates":[4.4149560928,50.7985038757],"type":"Point"}
}