{
  "type": "Feature",
  "properties": {
    "iso:country":"BE",
    "sg:address":"Lauwstraat 100",
    "sg:city":"Tongeren (lauw)",
    "sg:classifiers":[
        {
            "category":"Professional",
            "subcategory":"Accounting & Tax Preparation",
            "type":"Services"
        }
    ],
    "sg:phone":"+32 12 23 78 30",
    "sg:postcode":"3700",
    "sg:province":"Limburg",
    "sg:tags":[
        "bookkeeper"
    ],
    "wof:name":"Dessers R",
    "wof:placetype":"venue"
},
  "geometry": {"coordinates":[5.4150881767,50.7395477295],"type":"Point"}
}