{
  "type": "Feature",
  "properties": {
    "addr:full":"Helpt Elkanderstraat 7 Wuustwezel Antwerpen 2990",
    "addr:housenumber":"7",
    "addr:postcode":"2990",
    "addr:street":"Helpt Elkanderstraat",
    "iso:country":"BE",
    "sg:address":"Helpt Elkanderstraat 7",
    "sg:city":"Wuustwezel",
    "sg:classifiers":[
        {
            "category":"Health Services",
            "subcategory":"Health Practitioner",
            "type":"Services"
        }
    ],
    "sg:phone":"+32 3 236 35 17",
    "sg:postcode":"2990",
    "sg:province":"Antwerpen",
    "sg:tags":[
        "therapist",
        "speech"
    ],
    "wof:name":"Bellens Sandy",
    "wof:placetype":"venue"
},
  "geometry": {"coordinates":[4.5440731049,51.3565177917],"type":"Point"}
}