{
  "type": "Feature",
  "properties": {
    "addr:full":"Vital Decosterstraat 89b2 Leuven Vlaams-Brabant 3000",
    "addr:housenumber":"89b2",
    "addr:postcode":"3000",
    "addr:street":"Vital Decosterstraat",
    "iso:country":"BE",
    "sg:address":"Vital Decosterstraat 89b2",
    "sg:city":"Leuven",
    "sg:orig_category":"Assistances juridiques. Conseillers fiscaux. Comptables",
    "sg:phone":"+32 16 23 58 73",
    "sg:postcode":"3000",
    "sg:province":"Vlaams-Brabant",
    "wof:name":"Fiscura",
    "wof:placetype":"venue"
},
  "geometry": {"coordinates":[4.7015500069,50.8828544617],"type":"Point"}
}