{
  "type": "Feature",
  "properties": {
    "addr:full":"Terlindenstraat 32 Herne Vlaams-Brabant 1540",
    "addr:housenumber":"32",
    "addr:postcode":"1540",
    "addr:street":"Terlindenstraat",
    "iso:country":"BE",
    "sg:address":"Terlindenstraat 32",
    "sg:city":"Herne",
    "sg:orig_category":"Eleveurs de bovins. Eleveurs and marchands de porcs",
    "sg:phone":"+32 2 396 28 42",
    "sg:postcode":"1540",
    "sg:province":"Vlaams-Brabant",
    "wof:name":"Nicole Elinckx",
    "wof:placetype":"venue"
},
  "geometry": {"coordinates":[4.098236084,50.73021698],"type":"Point"}
}