{
  "type": "Feature",
  "properties": {
    "iso:country":"BE",
    "sg:address":"Mandellaan 299",
    "sg:city":"Roeselare",
    "sg:classifiers":[
        {
            "category":"Building & Trades",
            "subcategory":"Cleaning & Sanitation",
            "type":"Services"
        }
    ],
    "sg:phone":"+32 51 22 16 44",
    "sg:postcode":"8800",
    "sg:province":"West-Vlaanderen",
    "sg:tags":[
        "janitor"
    ],
    "wof:name":"Cn Clean",
    "wof:placetype":"venue"
},
  "geometry": {"coordinates":[3.1427509785,50.9474449158],"type":"Point"}
}