{
  "type": "Feature",
  "properties": {
    "iso:country":"BE",
    "sg:address":"Avenue Du G\u00e9n\u00e9ral De Gaulle 142",
    "sg:city":"Mons",
    "sg:classifiers":[
        {
            "category":"Health Services",
            "subcategory":"Health Practitioner",
            "type":"Services"
        }
    ],
    "sg:phone":"+32 65 84 16 09",
    "sg:postcode":"7000",
    "sg:province":"Hainaut",
    "sg:tags":[
        "therapist",
        "speech"
    ],
    "wof:name":"Selvais M P",
    "wof:placetype":"venue"
},
  "geometry": {"coordinates":[3.9454700947,50.4411964417],"type":"Point"}
}