{
  "type": "Feature",
  "properties": {
    "addr:full":"Quai Godefroid-kurth 85 Li\u00e8ge 1 (li\u00e8ge 2) Li\u00e8ge 4020",
    "addr:housenumber":"85;1;2",
    "addr:postcode":"4020",
    "addr:street":"Quai Godefroid-Kurth",
    "iso:country":"BE",
    "sg:address":"Quai Godefroid-kurth 85",
    "sg:city":"Li\u00e8ge 1 (li\u00e8ge 2)",
    "sg:classifiers":[
        {
            "category":"Personal",
            "subcategory":"Barber",
            "type":"Services"
        }
    ],
    "sg:phone":"+32 4 343 76 14",
    "sg:postcode":"4020",
    "sg:province":"Li\u00e8ge",
    "sg:tags":[
        "gentleman",
        "salon",
        "-",
        "hairdressing"
    ],
    "wof:name":"Valmy Coiffure",
    "wof:placetype":"venue"
},
  "geometry": {"coordinates":[5.5953822136,50.6472206116],"type":"Point"}
}