{
  "type": "Feature",
  "properties": {
    "iso:country":"BE",
    "sg:address":"Gustaaf Schockaertstraat 10",
    "sg:city":"Zottegem",
    "sg:classifiers":[
        {
            "category":"Personal",
            "subcategory":"Beauty Salon",
            "type":"Services"
        }
    ],
    "sg:phone":"+32 9 360 51 60",
    "sg:postcode":"9620",
    "sg:province":"Oost-Vlaanderen",
    "sg:tags":[
        "de",
        "coiffure"
    ],
    "wof:name":"Coiffure Jean-marie",
    "wof:placetype":"venue"
},
  "geometry": {"coordinates":[3.8117990494,50.8670463562],"type":"Point"}
}