{
  "type": "Feature",
  "properties": {
    "iso:country":"BE",
    "sg:address":"Herbesthaler Strasse 130",
    "sg:city":"Eupen",
    "sg:classifiers":[
        {
            "category":"Government",
            "subcategory":"Department Of Motor Vehicles",
            "type":"Public Place"
        }
    ],
    "sg:phone":"+32 87 56 00 63",
    "sg:postcode":"4700",
    "sg:province":"Li\u00e8ge",
    "sg:tags":[
        "planing",
        "wood",
        "sawing"
    ],
    "wof:name":"Lance Sprl",
    "wof:placetype":"venue"
},
  "geometry": {"coordinates":[6.0166320801,50.6389007568],"type":"Point"}
}