{
  "type": "Feature",
  "properties": {
    "iso:country":"BE",
    "sg:address":"Kerkstraat 2",
    "sg:city":"Zoutleeuw",
    "sg:orig_category":"Plaatsen van vloer- and muurbekleding Schilders",
    "sg:phone":"+32 11 78 30 21",
    "sg:postcode":"3440",
    "sg:province":"Vlaams-Brabant",
    "wof:name":"Peter Renard",
    "wof:placetype":"venue"
},
  "geometry": {"coordinates":[5.0998091698,50.8072624207],"type":"Point"}
}