{
  "type": "Feature",
  "properties": {
    "addr:full":"Rue Fran\u00e7ois Vekemans 110 Bruxelles Bruxelles-Capitale 1120",
    "addr:housenumber":"110",
    "addr:postcode":"1120",
    "addr:street":"Rue Franc\u0327Ois Vekemans",
    "iso:country":"BE",
    "sg:address":"Rue Fran\u00e7ois Vekemans 110",
    "sg:city":"Bruxelles",
    "sg:classifiers":[
        {
            "category":"Shopping",
            "subcategory":"Books",
            "type":"Retail Goods"
        }
    ],
    "sg:phone":"+32 2 268 41 53",
    "sg:postcode":"1120",
    "sg:province":"Bruxelles-Capitale",
    "sg:tags":[
        "bookseller"
    ],
    "wof:name":"Neder Press",
    "wof:placetype":"venue"
},
  "geometry": {"coordinates":[4.3875951767,50.8952865601],"type":"Point"}
}