{
  "type": "Feature",
  "properties": {
    "iso:country":"BE",
    "sg:address":"Rue Marie Curie 37",
    "sg:city":"Ans (loncin)",
    "sg:classifiers":[
        {
            "category":"Home & Garden",
            "subcategory":"Carpets & Floor Coverings",
            "type":"Retail Goods"
        }
    ],
    "sg:phone":"+32 4 247 46 10",
    "sg:postcode":"4431",
    "sg:province":"Li\u00e8ge",
    "sg:tags":[
        "tile"
    ],
    "wof:name":"M\u00e9dixbel Sprl",
    "wof:placetype":"venue"
},
  "geometry": {"coordinates":[5.5024390221,50.6699371338],"type":"Point"}
}