{
  "type": "Feature",
  "properties": {
    "addr:full":"Driehoekstraat 75 Haaltert Oost-Vlaanderen 9451",
    "addr:housenumber":"75",
    "addr:postcode":"9451",
    "addr:street":"Driehoekstraat",
    "iso:country":"BE",
    "sg:address":"Driehoekstraat 75",
    "sg:city":"Haaltert",
    "sg:classifiers":[
        {
            "category":"Cafe",
            "type":"Food & Drink"
        }
    ],
    "sg:phone":"+32 53 83 97 69",
    "sg:postcode":"9451",
    "sg:province":"Oost-Vlaanderen",
    "sg:tags":[
        "caf\u00e9s"
    ],
    "wof:name":"Caf\u00c9 Roxy",
    "wof:placetype":"venue"
},
  "geometry": {"coordinates":[3.9824500084,50.8868293762],"type":"Point"}
}