{
  "type": "Feature",
  "properties": {
    "addr:full":"Trompestraat 23 Kruishoutem Oost-Vlaanderen 9770",
    "addr:housenumber":"23",
    "addr:postcode":"9770",
    "addr:street":"Trompestraat",
    "iso:country":"BE",
    "sg:address":"Trompestraat 23",
    "sg:city":"Kruishoutem",
    "sg:orig_category":"Non-Classified Establishments",
    "sg:phone":"+32 9 383 83 42",
    "sg:postcode":"9770",
    "sg:province":"Oost-Vlaanderen",
    "wof:name":"All Round Design Bvba",
    "wof:placetype":"venue"
},
  "geometry": {"coordinates":[3.5362548828,50.9177322388],"type":"Point"}
}