{
  "type": "Feature",
  "properties": {
    "addr:full":"Avenue Reine Astrid 175 Verviers (heusy) Li\u00e8ge 4802",
    "addr:housenumber":"175",
    "addr:postcode":"4802",
    "addr:street":"Avenue Reine Astrid",
    "iso:country":"BE",
    "sg:address":"Avenue Reine Astrid 175",
    "sg:city":"Verviers (heusy)",
    "sg:classifiers":[
        {
            "category":"Shopping",
            "subcategory":"Computers & Home Electronics",
            "type":"Retail Goods"
        }
    ],
    "sg:phone":"+32 87 22 95 15",
    "sg:postcode":"4802",
    "sg:province":"Li\u00e8ge",
    "sg:tags":[
        "-",
        "television",
        "radio"
    ],
    "wof:name":"Pirenne Leon Sprl",
    "wof:placetype":"venue"
},
  "geometry": {"coordinates":[5.8872442245,50.5832939148],"type":"Point"}
}