{
  "type": "Feature",
  "properties": {
    "iso:country":"BE",
    "sg:address":"Oudstrijdersstraat 98",
    "sg:city":"Ranst (oelegem)",
    "sg:classifiers":[
        {
            "category":"Health Services",
            "subcategory":"Health Practitioner",
            "type":"Services"
        }
    ],
    "sg:phone":"+32 3 383 47 04",
    "sg:postcode":"2520",
    "sg:province":"Antwerpen",
    "sg:tags":[
        "physiotherapist"
    ],
    "wof:name":"De Cordt A",
    "wof:placetype":"venue"
},
  "geometry": {"coordinates":[4.5894260406,51.2131958008],"type":"Point"}
}