{
  "type": "Feature",
  "properties": {
    "iso:country":"BE",
    "sg:address":"Rue Du Ch\u00c2teau Du Fay 2",
    "sg:city":"Sombreffe",
    "sg:orig_category":"Onderdelen and accessoires voor auto's",
    "sg:phone":"+32 71 80 01 42",
    "sg:postcode":"5140",
    "sg:province":"Namur",
    "wof:name":"Pneus 3 Provinces",
    "wof:placetype":"venue"
},
  "geometry": {"coordinates":[4.593006134,50.4869232178],"type":"Point"}
}