{
  "type": "Feature",
  "properties": {
    "iso:country":"BE",
    "sg:address":"Av. Houba De Strooper 692",
    "sg:city":"Brussel/bruxelles",
    "sg:orig_category":"Mat\u00e9riel de T\u00e9l\u00e9communication. D\u00e9taillants en pi\u00e8ces and accessoires de voitures. Machines and mat\u00e9r",
    "sg:phone":"+32 2 478 30 22",
    "sg:postcode":"1020",
    "sg:province":"Bruxelles-Capitale",
    "wof:name":"Jcb Belgium",
    "wof:placetype":"venue"
},
  "geometry": {"coordinates":[4.3284277916,50.8966178894],"type":"Point"}
}