{
  "type": "Feature",
  "properties": {
    "addr:full":"Rue Coquiamont 4 Hannut Li\u00e8ge 4280",
    "addr:housenumber":"4",
    "addr:postcode":"4280",
    "addr:street":"Rue Coquiamont",
    "iso:country":"BE",
    "sg:address":"Rue Coquiamont 4",
    "sg:city":"Hannut",
    "sg:orig_category":"Eleveurs and marchands de porcs",
    "sg:phone":"+32 81 85 54 51",
    "sg:postcode":"4280",
    "sg:province":"Li\u00e8ge",
    "wof:name":"Paul Pirard",
    "wof:placetype":"venue"
},
  "geometry": {"coordinates":[4.9957499504,50.6492233276],"type":"Point"}
}