{
  "type": "Feature",
  "properties": {
    "addr:full":"Sint-benedictusstraat 134 Mortsel Antwerpen 2640",
    "addr:housenumber":"134",
    "addr:postcode":"2640",
    "addr:street":"Sint-Benedictusstraat",
    "iso:country":"BE",
    "sg:address":"Sint-benedictusstraat 134",
    "sg:city":"Mortsel",
    "sg:orig_category":"D\u00e9corateurs d'int\u00e9rieur",
    "sg:phone":"+32 3 449 92 15",
    "sg:postcode":"2640",
    "sg:province":"Antwerpen",
    "wof:name":"Stefan Godart",
    "wof:placetype":"venue"
},
  "geometry": {"coordinates":[4.4573059082,51.169216156],"type":"Point"}
}