{
  "type": "Feature",
  "properties": {
    "iso:country":"BE",
    "sg:address":"Rue D'egypte 14",
    "sg:city":"Les Bons Villers (r\u00eaves)",
    "sg:classifiers":[
        {
            "category":"Communications",
            "type":"Services"
        }
    ],
    "sg:phone":"+32 71 84 77 28",
    "sg:postcode":"6210",
    "sg:province":"Hainaut",
    "sg:tags":[
        "translator"
    ],
    "wof:name":"Losson C",
    "wof:placetype":"venue"
},
  "geometry": {"coordinates":[4.4174461365,50.5389060974],"type":"Point"}
}