{
  "type": "Feature",
  "properties": {
    "iso:country":"BE",
    "sg:address":"Kouterstraat 18b1",
    "sg:city":"Beveren",
    "sg:classifiers":[
        {
            "category":"Arena",
            "subcategory":"Sports Club",
            "type":"Entertainment"
        }
    ],
    "sg:phone":"+32 3 755 09 51",
    "sg:postcode":"9120",
    "sg:province":"Oost-Vlaanderen",
    "sg:tags":[
        "de"
    ],
    "wof:name":"Wase Dkw Audio Auto Union",
    "wof:placetype":"venue"
},
  "geometry": {"coordinates":[4.1874260902,51.2188034058],"type":"Point"}
}