{
  "type": "Feature",
  "properties": {
    "addr:full":"Luikersteenweg 350 Heers Limburg 3870",
    "addr:housenumber":"350",
    "addr:postcode":"3870",
    "addr:street":"Luikersteenweg",
    "iso:country":"BE",
    "sg:address":"Luikersteenweg 350",
    "sg:city":"Heers",
    "sg:orig_category":"Autokeuringen",
    "sg:phone":"+32 11 48 52 06",
    "sg:postcode":"3870",
    "sg:province":"Limburg",
    "wof:name":"Autokeuring",
    "wof:placetype":"venue"
},
  "geometry": {"coordinates":[5.3017759323,50.752746582],"type":"Point"}
}