{
  "type": "Feature",
  "properties": {
    "iso:country":"BE",
    "sg:address":"Aartrijkestraat 38",
    "sg:city":"Torhout",
    "sg:orig_category":"Advocaten and juridische adviseurs",
    "sg:phone":"+32 50 22 14 04",
    "sg:postcode":"8820",
    "sg:province":"West-Vlaanderen",
    "wof:name":"Sandra Denoo",
    "wof:placetype":"venue"
},
  "geometry": {"coordinates":[3.100014925,51.0699653625],"type":"Point"}
}