{
  "type": "Feature",
  "properties": {
    "addr:full":"Rue De La D\u00c9portation 14 Binche Hainaut 7130",
    "addr:housenumber":"14",
    "addr:postcode":"7130",
    "addr:street":"Rue De La De\u0301Portation",
    "iso:country":"BE",
    "sg:address":"Rue De La D\u00c9portation 14",
    "sg:city":"Binche",
    "sg:orig_category":"Location de v\u00eatements, chaussures and textiles",
    "sg:phone":"+32 64 33 39 07",
    "sg:postcode":"7130",
    "sg:province":"Hainaut",
    "wof:name":"Karl Kersten (gilles De Binche)",
    "wof:placetype":"venue"
},
  "geometry": {"coordinates":[4.1718568802,50.4109725952],"type":"Point"}
}