{
  "type": "Feature",
  "properties": {
    "addr:full":"Rue Colbert 83 Lille 59800",
    "addr:housenumber":"83",
    "addr:postcode":"59800",
    "addr:street":"Rue Colbert",
    "iso:country":"BE",
    "sg:address":"Rue Colbert 83",
    "sg:city":"Lille",
    "sg:classifiers":[
        {
            "category":"Manufacturing",
            "subcategory":"Musical Instruments",
            "type":"Manufacturing & Wholesale Goods"
        }
    ],
    "sg:phone":"+33 3 20 57 06 06",
    "sg:postcode":"59800",
    "sg:tags":[
        "piano"
    ],
    "wof:name":"Maison Du Piano (la)",
    "wof:placetype":"venue"
},
  "geometry": {"coordinates":[3.0802400112,50.6361885071],"type":"Point"}
}