{
  "type": "Feature",
  "properties": {
    "addr:full":"Rue Abbesse 75 Walhain Brabant Wallon 1457",
    "addr:housenumber":"75;1457",
    "addr:street":"Rue Abbesse",
    "iso:country":"BE",
    "sg:address":"Rue Abbesse 75",
    "sg:city":"Walhain",
    "sg:orig_category":"Pain, p\u00e2tisseries and confiseries",
    "sg:phone":"+32 10 65 84 16",
    "sg:postcode":"1457",
    "sg:province":"Brabant Wallon",
    "wof:name":"Frumy",
    "wof:placetype":"venue"
},
  "geometry": {"coordinates":[4.6597399712,50.6363105774],"type":"Point"}
}