{
  "type": "Feature",
  "properties": {
    "addr:full":"Drongensesteenweg 39a Gent Oost-Vlaanderen 9000",
    "addr:housenumber":"39a",
    "addr:postcode":"9000",
    "addr:street":"Drongensesteenweg;Oost-Vlaanderen",
    "iso:country":"BE",
    "sg:address":"Drongensesteenweg 39a",
    "sg:city":"Gent",
    "sg:classifiers":[
        {
            "category":"Recreation",
            "subcategory":"Arcade",
            "type":"Entertainment"
        }
    ],
    "sg:phone":"+32 9 225 12 60",
    "sg:postcode":"9000",
    "sg:province":"Oost-Vlaanderen",
    "sg:tags":[
        "machine",
        "amusement"
    ],
    "wof:name":"Pascual Consult",
    "wof:placetype":"venue"
},
  "geometry": {"coordinates":[3.7006299496,51.0570755005],"type":"Point"}
}