{
  "type": "Feature",
  "properties": {
    "addr:full":"Dorpsstraat 41 Bilzen (eigenbilzen) Limburg 3740",
    "addr:housenumber":"41",
    "addr:postcode":"3740",
    "addr:street":"Dorpsstraat",
    "iso:country":"BE",
    "sg:address":"Dorpsstraat 41",
    "sg:city":"Bilzen (eigenbilzen)",
    "sg:classifiers":[
        {
            "category":"Banks & Credit Unions",
            "subcategory":"Bank",
            "type":"Services"
        }
    ],
    "sg:phone":"+32 89 41 26 69",
    "sg:postcode":"3740",
    "sg:province":"Limburg",
    "sg:tags":[
        "savings-banks"
    ],
    "wof:name":"Centea",
    "wof:placetype":"venue"
},
  "geometry": {"coordinates":[5.5752120018,50.8749046326],"type":"Point"}
}