{
  "type": "Feature",
  "properties": {
    "addr:full":"Kasteleinsstraat 32 Elsene/ixelles Bruxelles-Capitale 1050",
    "addr:housenumber":"32",
    "addr:postcode":"1050",
    "addr:street":"Kasteleinsstraat",
    "iso:country":"BE",
    "sg:address":"Kasteleinsstraat 32",
    "sg:city":"Elsene/ixelles",
    "sg:orig_category":"Immobili\u00ebnkantoren",
    "sg:phone":"+32 2 646 03 40",
    "sg:postcode":"1050",
    "sg:province":"Bruxelles-Capitale",
    "wof:name":"Bureau Wilhelm Et Cie",
    "wof:placetype":"venue"
},
  "geometry": {"coordinates":[4.3603777885,50.8242454529],"type":"Point"}
}