{
  "type": "Feature",
  "properties": {
    "addr:full":"Staakmolenstraat 63 Roeselare West-Vlaanderen 8800",
    "addr:housenumber":"63",
    "addr:postcode":"8800",
    "addr:street":"Staakmolenstraat",
    "iso:country":"BE",
    "sg:address":"Staakmolenstraat 63",
    "sg:city":"Roeselare",
    "sg:orig_category":"Architecten",
    "sg:phone":"+32 51 22 71 36",
    "sg:postcode":"8800",
    "sg:province":"West-Vlaanderen",
    "wof:name":"Frederik Dutry",
    "wof:placetype":"venue"
},
  "geometry": {"coordinates":[3.1307530403,50.9314460754],"type":"Point"}
}