{
  "type": "Feature",
  "properties": {
    "addr:full":"Rue De L'enseignement 60 Brussel/bruxelles Bruxelles-Capitale 1000",
    "addr:housenumber":"60",
    "addr:postcode":"1000",
    "addr:street":"Rue De L'Enseignement;/",
    "iso:country":"BE",
    "sg:address":"Rue De L'enseignement 60",
    "sg:city":"Brussel/bruxelles",
    "sg:orig_category":"Tabac",
    "sg:phone":"+32 2 218 37 79",
    "sg:postcode":"1000",
    "sg:province":"Bruxelles-Capitale",
    "wof:name":"Au Roi Du Cigare",
    "wof:placetype":"venue"
},
  "geometry": {"coordinates":[4.3643770218,50.8486251831],"type":"Point"}
}