{
  "type": "Feature",
  "properties": {
    "addr:full":"Rue Joseph Delhalle 37 Wanze Li\u00e8ge 4520",
    "addr:housenumber":"37",
    "addr:postcode":"4520",
    "addr:street":"Rue Joseph Delhalle",
    "iso:country":"BE",
    "sg:address":"Rue Joseph Delhalle 37",
    "sg:city":"Wanze",
    "sg:orig_category":"Landmeters",
    "sg:phone":"+32 85 21 39 62",
    "sg:postcode":"4520",
    "sg:province":"Li\u00e8ge",
    "wof:name":"Michel Matot",
    "wof:placetype":"venue"
},
  "geometry": {"coordinates":[5.21733284,50.5416793823],"type":"Point"}
}