{
  "type": "Feature",
  "properties": {
    "iso:country":"BE",
    "sg:address":"Rue Saint-jean-sart 7",
    "sg:city":"Aubel",
    "sg:orig_category":"Maisons de vacances",
    "sg:phone":"+32 87 68 76 28",
    "sg:postcode":"4880",
    "sg:province":"Li\u00e8ge",
    "wof:name":"G\u00cete Saint-jean",
    "wof:placetype":"venue"
},
  "geometry": {"coordinates":[5.8191299438,50.7045593262],"type":"Point"}
}