{
  "type": "Feature",
  "properties": {
    "addr:full":"Surister 73 Jalhay Li\u00e8ge 4845",
    "addr:housenumber":"73",
    "addr:postcode":"4845",
    "addr:street":"Surister",
    "iso:country":"BE",
    "sg:address":"Surister 73",
    "sg:city":"Jalhay",
    "sg:orig_category":"Installation de menuiserie en bois and plastique",
    "sg:phone":"+32 87 64 78 74",
    "sg:postcode":"4845",
    "sg:province":"Li\u00e8ge",
    "wof:name":"Joel Lechanteur",
    "wof:placetype":"venue"
},
  "geometry": {"coordinates":[5.9327812195,50.5631027222],"type":"Point"}
}