{
  "type": "Feature",
  "properties": {
    "addr:full":"Rue De La R\u00c9gence 34 Brussel/bruxelles Bruxelles-Capitale 1000",
    "addr:housenumber":"34",
    "addr:postcode":"1000",
    "addr:street":"Rue De La Re\u0301Gence;/",
    "iso:country":"BE",
    "sg:address":"Rue De La R\u00c9gence 34",
    "sg:city":"Brussel/bruxelles",
    "sg:orig_category":"Antiquit\u00e9s. Services divers aux entreprises",
    "sg:phone":"+32 2 511 05 13",
    "sg:postcode":"1000",
    "sg:province":"Bruxelles-Capitale",
    "wof:name":"Lemaire",
    "wof:placetype":"venue"
},
  "geometry": {"coordinates":[4.3545298576,50.8385696411],"type":"Point"}
}