{
  "type": "Feature",
  "properties": {
    "iso:country":"BE",
    "sg:address":"Vlamingenstraat 2",
    "sg:city":"Wervik",
    "sg:classifiers":[
        {
            "category":"Professional",
            "subcategory":"Art Services",
            "type":"Services"
        }
    ],
    "sg:phone":"+32 56 31 48 82",
    "sg:postcode":"8940",
    "sg:province":"West-Vlaanderen",
    "sg:tags":[
        "photographer"
    ],
    "wof:name":"Foto Folie",
    "wof:placetype":"venue"
},
  "geometry": {"coordinates":[3.0443398952,50.7795410156],"type":"Point"}
}