{
  "type": "Feature",
  "properties": {
    "iso:country":"BE",
    "sg:address":"Otteca 27",
    "sg:city":"Oostrozebeke",
    "sg:orig_category":"Varkenskwekers",
    "sg:phone":"+32 56 66 45 28",
    "sg:postcode":"8780",
    "sg:province":"West-Vlaanderen",
    "wof:name":"Rik Vromman",
    "wof:placetype":"venue"
},
  "geometry": {"coordinates":[3.2935390472,50.9103813171],"type":"Point"}
}