{
  "type": "Feature",
  "properties": {
    "addr:full":"Rue Bout Br\u00dbl\u00c9 20 Pont-a-celles Hainaut 6238",
    "addr:housenumber":"20",
    "addr:postcode":"6238",
    "addr:street":"Rue Bout Bru\u0302Le\u0301",
    "iso:country":"BE",
    "sg:address":"Rue Bout Br\u00dbl\u00c9 20",
    "sg:city":"Pont-a-celles",
    "sg:classifiers":[
        {
            "category":"Insurance",
            "subcategory":"Insurance Agent",
            "type":"Services"
        }
    ],
    "sg:phone":"+32 71 84 43 33",
    "sg:postcode":"6238",
    "sg:province":"Hainaut",
    "sg:tags":[
        "verzekeringsmakelaars",
        "expert"
    ],
    "wof:name":"Assurances Ghislain",
    "wof:placetype":"venue"
},
  "geometry": {"coordinates":[4.3987622261,50.5118980408],"type":"Point"}
}