{
  "type": "Feature",
  "properties": {
    "addr:full":"Lichtaartseweg 15 Olen Antwerpen 2250",
    "addr:housenumber":"15",
    "addr:postcode":"2250",
    "addr:street":"Lichtaartseweg",
    "iso:country":"BE",
    "sg:address":"Lichtaartseweg 15",
    "sg:city":"Olen",
    "sg:orig_category":"Fleurs and plantes. Combustibles. Installation de menuiserie m\u00e9tallique",
    "sg:phone":"+32 14 21 45 89",
    "sg:postcode":"2250",
    "sg:province":"Antwerpen",
    "wof:name":"Robert Van Hoof",
    "wof:placetype":"venue"
},
  "geometry": {"coordinates":[4.9022798538,51.1757278442],"type":"Point"}
}