{
  "type": "Feature",
  "properties": {
    "addr:full":"Avenue Des Sept Bonniers 121 Bruxelles (forest) Bruxelles-Capitale 1190",
    "addr:housenumber":"121",
    "addr:postcode":"1190",
    "addr:street":"Avenue Des Sept Bonniers",
    "iso:country":"BE",
    "sg:address":"Avenue Des Sept Bonniers 121",
    "sg:city":"Bruxelles (forest)",
    "sg:classifiers":[
        {
            "category":"Health Services",
            "subcategory":"Dentist",
            "type":"Services"
        }
    ],
    "sg:phone":"+32 2 345 31 04",
    "sg:postcode":"1190",
    "sg:province":"Bruxelles-Capitale",
    "wof:name":"Plichart Marc",
    "wof:placetype":"venue"
},
  "geometry": {"coordinates":[4.3338899612,50.81224823],"type":"Point"}
}