{
  "type": "Feature",
  "properties": {
    "iso:country":"BE",
    "sg:address":"8791",
    "sg:city":"Waregem (grand)",
    "sg:orig_category":"Pharmaciens",
    "sg:phone":"+32 900 10 500",
    "sg:postcode":"8791",
    "sg:province":"West-Vlaanderen",
    "wof:name":"Pharmacies De Garde",
    "wof:placetype":"venue"
},
  "geometry": {"coordinates":[3.3448400497,50.8731689453],"type":"Point"}
}