{
  "type": "Feature",
  "properties": {
    "addr:full":"Rue Cur\u00e9 Theys 17 Charleroi (jumet) Hainaut 6040",
    "addr:housenumber":"17",
    "addr:postcode":"6040",
    "addr:street":"Rue Cure\u0301 Theys",
    "iso:country":"BE",
    "sg:address":"Rue Cur\u00e9 Theys 17",
    "sg:city":"Charleroi (jumet)",
    "sg:classifiers":[
        {
            "category":"Professional",
            "type":"Services"
        }
    ],
    "sg:phone":"+32 71 37 53 95",
    "sg:postcode":"6040",
    "sg:province":"Hainaut",
    "sg:tags":[
        "entertainer"
    ],
    "wof:name":"Collignon C",
    "wof:placetype":"venue"
},
  "geometry": {"coordinates":[4.411468029,50.4368553162],"type":"Point"}
}