{
  "type": "Feature",
  "properties": {
    "addr:full":"Rue Haute Marcelle 43 Namur Namur 5000",
    "addr:housenumber":"43",
    "addr:postcode":"5000",
    "addr:street":"Rue Haute Marcelle",
    "iso:country":"BE",
    "sg:address":"Rue Haute Marcelle 43",
    "sg:city":"Namur",
    "sg:classifiers":[
        {
            "category":"Shopping",
            "subcategory":"Books",
            "type":"Retail Goods"
        }
    ],
    "sg:phone":"+32 81 22 93 14",
    "sg:postcode":"5000",
    "sg:province":"Namur",
    "sg:tags":[
        "antiquarian",
        "trade"
    ],
    "wof:name":"Regis",
    "wof:placetype":"venue"
},
  "geometry": {"coordinates":[4.8637099266,50.46434021],"type":"Point"}
}