{
  "type": "Feature",
  "properties": {
    "iso:country":"BE",
    "sg:address":"Lumbeekstraat 34",
    "sg:city":"Dilbeek",
    "sg:orig_category":"Installation de menuiserie m\u00e9tallique. Etudes techniques and ing\u00e9nierie. Installation de menuiserie ",
    "sg:phone":"+32 2 453 16 50",
    "sg:postcode":"1700",
    "sg:province":"Vlaams-Brabant",
    "wof:name":"All-in-decor",
    "wof:placetype":"venue"
},
  "geometry": {"coordinates":[4.2124948502,50.8825454712],"type":"Point"}
}