{
  "type": "Feature",
  "properties": {
    "addr:full":"Van Thorenburghlaan 14 Oosterzele (scheldewindeke) Oost-Vlaanderen 9860",
    "addr:housenumber":"14",
    "addr:postcode":"9860",
    "addr:street":"Thorenburghlaan",
    "iso:country":"BE",
    "sg:address":"Van Thorenburghlaan 14",
    "sg:city":"Oosterzele (scheldewindeke)",
    "sg:classifiers":[
        {
            "category":"Farming",
            "subcategory":"Livestock Farm",
            "type":"Manufacturing & Wholesale Goods"
        }
    ],
    "sg:phone":"+32 78 15 44 44",
    "sg:postcode":"9860",
    "sg:province":"Oost-Vlaanderen",
    "sg:tags":[
        "breeding"
    ],
    "wof:name":"Vlaamse Rundveeteelt Vereniging",
    "wof:placetype":"venue"
},
  "geometry": {"coordinates":[3.7860291004,50.949005127],"type":"Point"}
}