{
  "type": "Feature",
  "properties": {
    "iso:country":"BE",
    "sg:address":"Knollingstraat 24",
    "sg:city":"Ardooie",
    "sg:classifiers":[
        {
            "category":"Insurance",
            "subcategory":"Life Insurance",
            "type":"Services"
        }
    ],
    "sg:phone":"+32 51 20 90 25",
    "sg:postcode":"8850",
    "sg:province":"West-Vlaanderen",
    "sg:tags":[
        "assurance"
    ],
    "wof:name":"Kantoor Schelpe-huyghe",
    "wof:placetype":"venue"
},
  "geometry": {"coordinates":[3.1754200459,50.9532318115],"type":"Point"}
}