{
  "type": "Feature",
  "properties": {
    "iso:country":"BE",
    "sg:address":"Houba De Strooperlaan 13",
    "sg:city":"Brussel",
    "sg:orig_category":"Pain, p\u00e2tisseries and confiseries",
    "sg:phone":"+32 2 478 66 07",
    "sg:postcode":"1020",
    "sg:province":"Bruxelles-Capitale",
    "wof:name":"Au Savarin",
    "wof:placetype":"venue"
},
  "geometry": {"coordinates":[4.3425011635,50.8858680725],"type":"Point"}
}