{
  "type": "Feature",
  "properties": {
    "iso:country":"BE",
    "sg:address":"Sleidinge Dorp 87a",
    "sg:city":"Evergem (sleidinge)",
    "sg:classifiers":[
        {
            "category":"Shopping",
            "subcategory":"Shoes",
            "type":"Retail Goods"
        }
    ],
    "sg:phone":"+32 9 357 20 24",
    "sg:postcode":"9940",
    "sg:province":"Oost-Vlaanderen",
    "sg:tags":[
        "slipper",
        "-"
    ],
    "wof:name":"Toetie Foetie",
    "wof:placetype":"venue"
},
  "geometry": {"coordinates":[3.6799149513,51.1351776123],"type":"Point"}
}