{
  "type": "Feature",
  "properties": {
    "iso:country":"BE",
    "sg:address":"Beverstraat 53 B",
    "sg:city":"Oudenaarde",
    "sg:orig_category":"ACCOUNTANTS Belastingconsulenten Diverse juridische dienstverlening",
    "sg:phone":"+32 55 31 70 92",
    "sg:postcode":"9700",
    "sg:province":"Oost-Vlaanderen",
    "wof:name":"Marc Ottevaere",
    "wof:placetype":"venue"
},
  "geometry": {"coordinates":[3.5991470814,50.8490638733],"type":"Point"}
}