{
  "type": "Feature",
  "properties": {
    "addr:full":"Rue Linn\u00c9 86 Sint-joost-ten-node/saint-josse-ten-noode Bruxelles-Capitale 1210",
    "addr:housenumber":"86",
    "addr:postcode":"1210",
    "addr:street":"Rue Linne\u0301",
    "iso:country":"BE",
    "sg:address":"Rue Linn\u00c9 86",
    "sg:city":"Sint-joost-ten-node/saint-josse-ten-noode",
    "sg:classifiers":[
        {
            "category":"Cafe",
            "type":"Food & Drink"
        }
    ],
    "sg:phone":"+32 2 218 02 77",
    "sg:postcode":"1210",
    "sg:province":"Bruxelles-Capitale",
    "sg:tags":[
        "caf\u00e9s"
    ],
    "wof:name":"Caf\u00c9 Le Grisby",
    "wof:placetype":"venue"
},
  "geometry": {"coordinates":[4.363462925,50.8583450317],"type":"Point"}
}