{
  "type": "Feature",
  "properties": {
    "iso:country":"BE",
    "sg:address":"Tisseltstraat 76",
    "sg:city":"Kapelle-op-den-bos",
    "sg:orig_category":"Sportclubs Sportterreinen and installaties behalve sportcentra",
    "sg:phone":"+32 15 71 26 16",
    "sg:postcode":"1880",
    "sg:province":"Vlaams-Brabant",
    "wof:name":"K.v.c. Delta Londerzeel",
    "wof:placetype":"venue"
},
  "geometry": {"coordinates":[4.3369789124,51.0229187012],"type":"Point"}
}