{
  "type": "Feature",
  "properties": {
    "addr:full":"Rue De La Pierresse 12 Limbourg Li\u00e8ge 4834",
    "addr:housenumber":"12",
    "addr:postcode":"4834",
    "addr:street":"Rue De La Pierresse",
    "iso:country":"BE",
    "sg:address":"Rue De La Pierresse 12",
    "sg:city":"Limbourg",
    "sg:orig_category":"Rundveehouders",
    "sg:phone":"+32 87 76 28 68",
    "sg:postcode":"4834",
    "sg:province":"Li\u00e8ge",
    "wof:name":"Albert Lemmens",
    "wof:placetype":"venue"
},
  "geometry": {"coordinates":[5.9589920044,50.6022224426],"type":"Point"}
}