{
  "type": "Feature",
  "properties": {
    "addr:full":"Adelberg 80 Lommel Limburg 3920",
    "addr:housenumber":"80",
    "addr:postcode":"3920",
    "addr:street":"Adelberg",
    "iso:country":"BE",
    "sg:address":"Adelberg 80",
    "sg:city":"Lommel",
    "sg:orig_category":"Royal Canin. Animaux domestiques and accessoires",
    "sg:phone":"+32 11 54 43 67",
    "sg:postcode":"3920",
    "sg:province":"Limburg",
    "wof:name":"Jansen Frans",
    "wof:placetype":"venue"
},
  "geometry": {"coordinates":[5.3022761345,51.2332687378],"type":"Point"}
}