{
  "type": "Feature",
  "properties": {
    "addr:full":"Drie Sleutelsstraat 68 Aalst Oost-Vlaanderen 9300",
    "addr:housenumber":"68",
    "addr:postcode":"9300",
    "addr:street":"Sleutelsstraat",
    "iso:country":"BE",
    "sg:address":"Drie Sleutelsstraat 68",
    "sg:city":"Aalst",
    "sg:orig_category":"D\u00e9molition d\u00b4immeubles and terrassements",
    "sg:phone":"+32 53 71 05 69",
    "sg:postcode":"9300",
    "sg:province":"Oost-Vlaanderen",
    "wof:name":"Calli K",
    "wof:placetype":"venue"
},
  "geometry": {"coordinates":[4.0420942307,50.946937561],"type":"Point"}
}