{
  "type": "Feature",
  "properties": {
    "addr:full":"Sint-truidersteenweg 149 Hasselt Limburg 3500",
    "addr:housenumber":"149",
    "addr:postcode":"3500",
    "addr:street":"Sint-Truidersteenweg",
    "iso:country":"BE",
    "sg:address":"Sint-truidersteenweg 149",
    "sg:city":"Hasselt",
    "sg:orig_category":"Kapsalons",
    "sg:phone":"+32 11 27 37 94",
    "sg:postcode":"3500",
    "sg:province":"Limburg",
    "wof:name":"Coiffure Chris",
    "wof:placetype":"venue"
},
  "geometry": {"coordinates":[5.3311471939,50.9223136902],"type":"Point"}
}