{
  "type": "Feature",
  "properties": {
    "iso:country":"BE",
    "sg:address":"Haasdonksesteenweg 25",
    "sg:city":"Temse",
    "sg:classifiers":[
        {
            "category":"Health Services",
            "subcategory":"Health Practitioner",
            "type":"Services"
        }
    ],
    "sg:phone":"+32 3 771 68 00",
    "sg:postcode":"9140",
    "sg:province":"Oost-Vlaanderen",
    "sg:tags":[
        "physiotherapist"
    ],
    "wof:name":"Smet Annemie",
    "wof:placetype":"venue"
},
  "geometry": {"coordinates":[4.2102890015,51.1633262634],"type":"Point"}
}