{
  "type": "Feature",
  "properties": {
    "addr:full":"Leenakkerstraat 37 Waregem (beveren-leie) West-Vlaanderen 8791",
    "addr:housenumber":"37",
    "addr:postcode":"8791",
    "addr:street":"Leenakkerstraat",
    "iso:country":"BE",
    "sg:address":"Leenakkerstraat 37",
    "sg:city":"Waregem (beveren-leie)",
    "sg:classifiers":[
        {
            "category":"Personal",
            "subcategory":"Nail Salon",
            "type":"Services"
        }
    ],
    "sg:phone":"+32 56 25 68 63",
    "sg:postcode":"8791",
    "sg:province":"West-Vlaanderen",
    "sg:tags":[
        "pedicure"
    ],
    "wof:name":"Deriemaecker K",
    "wof:placetype":"venue"
},
  "geometry": {"coordinates":[3.3396499157,50.8676795959],"type":"Point"}
}