{
  "type": "Feature",
  "properties": {
    "iso:country":"BE",
    "sg:address":"Place Des Palais 7",
    "sg:city":"Bruxelles",
    "sg:classifiers":[
        {
            "category":"Organizations",
            "subcategory":"Community Association",
            "type":"Services"
        }
    ],
    "sg:phone":"+32 2 511 55 78",
    "sg:postcode":"1000",
    "sg:province":"Bruxelles-Capitale",
    "sg:tags":[
        "cultural"
    ],
    "wof:name":"Association Royale le Mus\u00e9e De La Dynastie",
    "wof:placetype":"venue"
},
  "geometry": {"coordinates":[4.3614358902,50.842716217],"type":"Point"}
}