{
  "type": "Feature",
  "properties": {
    "addr:full":"Kromme Waters 3 Waregem (sint-eloois-vijve) West-Vlaanderen 8793",
    "addr:housenumber":"3",
    "addr:postcode":"8793",
    "addr:street":"Kromme Waters",
    "iso:country":"BE",
    "sg:address":"Kromme Waters 3",
    "sg:city":"Waregem (sint-eloois-vijve)",
    "sg:classifiers":[
        {
            "category":"Building & Trades",
            "subcategory":"Pest Control",
            "type":"Services"
        }
    ],
    "sg:phone":"+32 56 32 31 01",
    "sg:postcode":"8793",
    "sg:province":"West-Vlaanderen",
    "sg:tags":[
        "painting",
        "contractor"
    ],
    "wof:name":"Devos P",
    "wof:placetype":"venue"
},
  "geometry": {"coordinates":[3.4123280048,50.9072303772],"type":"Point"}
}