{
  "type": "Feature",
  "properties": {
    "iso:country":"BE",
    "sg:address":"Kortrijkstraat 466",
    "sg:city":"Menen",
    "sg:orig_category":"Articles de sport, camping and jouets Gr",
    "sg:phone":"+32 56 53 20 35",
    "sg:postcode":"8930",
    "sg:province":"West-Vlaanderen",
    "wof:name":"Jural Company Belgium",
    "wof:placetype":"venue"
},
  "geometry": {"coordinates":[3.1412138939,50.7995796204],"type":"Point"}
}