{
  "type": "Feature",
  "properties": {
    "iso:country":"BE",
    "sg:address":"Nijverheidslaan 1",
    "sg:city":"Diest",
    "sg:orig_category":"Sondages and enqu\u00eates",
    "sg:phone":"+32 13 35 52 03",
    "sg:postcode":"3290",
    "sg:province":"Vlaams-Brabant",
    "wof:name":"Bureau Mercatron Direct",
    "wof:placetype":"venue"
},
  "geometry": {"coordinates":[5.0496058464,50.9899101257],"type":"Point"}
}