{
  "type": "Feature",
  "properties": {
    "iso:country":"BE",
    "sg:address":"Kapellendries 92",
    "sg:city":"Wetteren",
    "sg:orig_category":"Services pour animaux domestiques",
    "sg:phone":"+32 9 366 17 83",
    "sg:postcode":"9230",
    "sg:province":"Oost-Vlaanderen",
    "wof:name":"Sabine De Wilde",
    "wof:placetype":"venue"
},
  "geometry": {"coordinates":[3.8812389374,51.0124282837],"type":"Point"}
}