{
  "type": "Feature",
  "properties": {
    "addr:full":"Rue Saint-mon\u00c9gonde 40 Chimay Hainaut 6460",
    "addr:housenumber":"40",
    "addr:postcode":"6460",
    "addr:street":"Rue Saint-Mone\u0301Gonde",
    "iso:country":"BE",
    "sg:address":"Rue Saint-mon\u00c9gonde 40",
    "sg:city":"Chimay",
    "sg:orig_category":"Enseignement maternel and primaire",
    "sg:phone":"+32 60 21 27 30",
    "sg:postcode":"6460",
    "sg:province":"Hainaut",
    "wof:name":"Ecole Prim. Communale",
    "wof:placetype":"venue"
},
  "geometry": {"coordinates":[4.246945858,50.0562591553],"type":"Point"}
}