{
  "type": "Feature",
  "properties": {
    "iso:country":"BE",
    "sg:address":"Rooigemlaan 469",
    "sg:city":"Gent",
    "sg:classifiers":[
        {
            "category":"Professional",
            "subcategory":"Accounting & Tax Preparation",
            "type":"Services"
        }
    ],
    "sg:phone":"+32 9 227 88 77",
    "sg:postcode":"9000",
    "sg:province":"Oost-Vlaanderen",
    "sg:tags":[
        "accountant"
    ],
    "wof:name":"F. Saverwyns",
    "wof:placetype":"venue"
},
  "geometry": {"coordinates":[3.6945090294,51.0629043579],"type":"Point"}
}