{
  "type": "Feature",
  "properties": {
    "addr:full":"Rue Des Ecoles 35 Anderlues Hainaut 6150",
    "addr:housenumber":"35",
    "addr:postcode":"6150",
    "addr:street":"Rue Des Ecoles",
    "iso:country":"BE",
    "sg:address":"Rue Des Ecoles 35",
    "sg:city":"Anderlues",
    "sg:orig_category":"Afval and schroot Gh",
    "sg:phone":"+32 71 52 92 61",
    "sg:postcode":"6150",
    "sg:province":"Hainaut",
    "wof:name":"Ren\u00c9 De Muynck",
    "wof:placetype":"venue"
},
  "geometry": {"coordinates":[4.2712187767,50.3898925781],"type":"Point"}
}