{
  "type": "Feature",
  "properties": {
    "iso:country":"BE",
    "sg:address":"Marialoopsesteenweg 5",
    "sg:city":"Tielt",
    "sg:classifiers":[
        {
            "category":"Utilities",
            "subcategory":"Fuel Oil & Lpg",
            "type":"Services"
        }
    ],
    "sg:phone":"+32 51 40 12 98",
    "sg:postcode":"8700",
    "sg:province":"West-Vlaanderen",
    "wof:name":"Olinger Oil",
    "wof:placetype":"venue"
},
  "geometry": {"coordinates":[3.3287060261,50.9732055664],"type":"Point"}
}