{
  "type": "Feature",
  "properties": {
    "addr:full":"Tervurenlaan 0 Brussel Bruxelles-Capitale 1000",
    "addr:housenumber":"0",
    "addr:postcode":"1000",
    "addr:street":"Tervurenlaan",
    "iso:country":"BE",
    "sg:address":"Tervurenlaan 0",
    "sg:city":"Brussel",
    "sg:orig_category":"Diverse kredietdiensten",
    "sg:postcode":"1000",
    "sg:province":"Bruxelles-Capitale",
    "wof:name":"Bancontact-mister Cash",
    "wof:placetype":"venue"
},
  "geometry": {"coordinates":[4.3496851921,50.8483848572],"type":"Point"}
}