{
  "type": "Feature",
  "properties": {
    "addr:full":"Prinsenlaan 74bb Ravels Antwerpen 2381",
    "addr:housenumber":"74bb",
    "addr:postcode":"2381",
    "addr:street":"Prinsenlaan",
    "iso:country":"BE",
    "sg:address":"Prinsenlaan 74bb",
    "sg:city":"Ravels",
    "sg:orig_category":"Rundveehouders",
    "sg:phone":"+32 14 65 90 15",
    "sg:postcode":"2381",
    "sg:province":"Antwerpen",
    "wof:name":"Eric Timmermans",
    "wof:placetype":"venue"
},
  "geometry": {"coordinates":[5.006374836,51.4099845886],"type":"Point"}
}