{
  "type": "Feature",
  "properties": {
    "iso:country":"BE",
    "sg:address":"Torhoutsesteenweg 83",
    "sg:city":"Oostende",
    "sg:classifiers":[
        {
            "category":"Bars & Pubs",
            "type":"Food & Drink"
        }
    ],
    "sg:phone":"+32 59 50 41 62",
    "sg:postcode":"8400",
    "sg:province":"West-Vlaanderen",
    "wof:name":"Petit Venise",
    "wof:placetype":"venue"
},
  "geometry": {"coordinates":[2.9086360931,51.2236480713],"type":"Point"}
}