{
  "type": "Feature",
  "properties": {
    "iso:country":"BE",
    "sg:address":"Bergense Steenweg 368",
    "sg:city":"Anderlecht",
    "sg:orig_category":"Pleisterwerk",
    "sg:phone":"+32 2 521 80 74",
    "sg:postcode":"1070",
    "sg:province":"Bruxelles-Capitale",
    "wof:name":"Manuel Fonseca Marques",
    "wof:placetype":"venue"
},
  "geometry": {"coordinates":[4.3198161125,50.837688446],"type":"Point"}
}