{
  "type": "Feature",
  "properties": {
    "iso:country":"BE",
    "sg:address":"Rue Des Wallons 52",
    "sg:city":"Li\u00e8ge 1",
    "sg:classifiers":[
        {
            "category":"Health Services",
            "subcategory":"Dentist",
            "type":"Services"
        }
    ],
    "sg:phone":"+32 4 253 25 94",
    "sg:postcode":"4000",
    "sg:province":"Li\u00e8ge",
    "wof:name":"Rinkin J",
    "wof:placetype":"venue"
},
  "geometry": {"coordinates":[5.5578489304,50.6305923462],"type":"Point"}
}