{
  "type": "Feature",
  "properties": {
    "addr:full":"Chemin Hallaux 46 Wavre Brabant Wallon 1300",
    "addr:housenumber":"46;1300",
    "addr:street":"Chemin Hallaux",
    "iso:country":"BE",
    "sg:address":"Chemin Hallaux 46",
    "sg:city":"Wavre",
    "sg:classifiers":[
        {
            "category":"Home & Garden",
            "subcategory":"Hardware",
            "type":"Retail Goods"
        }
    ],
    "sg:phone":"+32 10 24 30 25",
    "sg:postcode":"1300",
    "sg:province":"Brabant Wallon",
    "sg:tags":[
        "equipment",
        "woodworking",
        "machinery"
    ],
    "wof:name":"Lengel\u00e9 A",
    "wof:placetype":"venue"
},
  "geometry": {"coordinates":[4.6007890701,50.7167320251],"type":"Point"}
}