{
  "type": "Feature",
  "properties": {
    "addr:full":"Plankstraat 1 Mechelen Antwerpen 2800",
    "addr:housenumber":"1",
    "addr:postcode":"2800",
    "addr:street":"Plankstraat",
    "iso:country":"BE",
    "sg:address":"Plankstraat 1",
    "sg:city":"Mechelen",
    "sg:orig_category":"Zalen voor culturele evenementen",
    "sg:phone":"+32 15 34 08 82",
    "sg:postcode":"2800",
    "sg:province":"Antwerpen",
    "wof:name":"Theater De Komeet",
    "wof:placetype":"venue"
},
  "geometry": {"coordinates":[4.4732708931,51.0294189453],"type":"Point"}
}