{
  "type": "Feature",
  "properties": {
    "iso:country":"BE",
    "sg:address":"Stasegemsesteenweg 1",
    "sg:city":"Kortrijk",
    "sg:classifiers":[
        {
            "category":"Shopping",
            "subcategory":"Crafts & Fabrics",
            "type":"Retail Goods"
        }
    ],
    "sg:phone":"+32 56 22 40 44",
    "sg:postcode":"8500",
    "sg:province":"West-Vlaanderen",
    "sg:tags":[
        "polishing",
        "cloth",
        "cleaning"
    ],
    "wof:name":"Floorpul International Nv",
    "wof:placetype":"venue"
},
  "geometry": {"coordinates":[3.2893440723,50.8310852051],"type":"Point"}
}