{
  "type": "Feature",
  "properties": {
    "addr:full":"Sint-agatha-berchemlaan 76b3 Koekelberg Bruxelles-Capitale 1081",
    "addr:housenumber":"76b3",
    "addr:postcode":"1081",
    "addr:street":"Sint-Agatha-Berchemlaan",
    "iso:country":"BE",
    "sg:address":"Sint-agatha-berchemlaan 76b3",
    "sg:city":"Koekelberg",
    "sg:orig_category":"Boekhouders",
    "sg:phone":"+32 2 414 76 79",
    "sg:postcode":"1081",
    "sg:province":"Bruxelles-Capitale",
    "wof:name":"Lucien Depoortere",
    "wof:placetype":"venue"
},
  "geometry": {"coordinates":[4.3086562157,50.8661499023],"type":"Point"}
}