{
  "type": "Feature",
  "properties": {
    "addr:full":"Rue Des Technologies 3 Villers-le-bouillet Li\u00e8ge 4530",
    "addr:housenumber":"3",
    "addr:postcode":"4530",
    "addr:street":"Rue Des Technologies",
    "iso:country":"BE",
    "sg:address":"Rue Des Technologies 3",
    "sg:city":"Villers-le-bouillet",
    "sg:classifiers":[
        {
            "category":"Home & Garden",
            "subcategory":"Building Materials",
            "type":"Retail Goods"
        }
    ],
    "sg:phone":"+32 4 259 42 12",
    "sg:postcode":"4530",
    "sg:province":"Li\u00e8ge",
    "sg:tags":[
        "window"
    ],
    "wof:name":"Ets Potty Sprl",
    "wof:placetype":"venue"
},
  "geometry": {"coordinates":[5.2609257698,50.5831336975],"type":"Point"}
}