{
  "type": "Feature",
  "properties": {
    "addr:full":"Grote Steenweg 127 Lede (oordegem) Oost-Vlaanderen 9340",
    "addr:housenumber":"127",
    "addr:postcode":"9340",
    "addr:street":"Grote Steenweg",
    "iso:country":"BE",
    "sg:address":"Grote Steenweg 127",
    "sg:city":"Lede (oordegem)",
    "sg:classifiers":[
        {
            "category":"Building & Trades",
            "subcategory":"Equipment Rental",
            "type":"Services"
        }
    ],
    "sg:phone":"+32 9 368 20 80",
    "sg:postcode":"9340",
    "sg:province":"Oost-Vlaanderen",
    "sg:tags":[
        "use",
        "apparatus",
        "tool",
        "-",
        "professional",
        "machines"
    ],
    "wof:name":"Favor All Rent Bvba",
    "wof:placetype":"venue"
},
  "geometry": {"coordinates":[3.8987050056,50.9578285217],"type":"Point"}
}