{
  "type": "Feature",
  "properties": {
    "addr:full":"R De Turin 14 Li\u00e8ge Li\u00e8ge 4020",
    "addr:housenumber":"14",
    "addr:postcode":"4020",
    "iso:country":"BE",
    "sg:address":"R De Turin 14",
    "sg:city":"Li\u00e8ge",
    "sg:classifiers":[
        {
            "category":"Professional",
            "subcategory":"Printing & Photocopies",
            "type":"Services"
        }
    ],
    "sg:phone":"+32 4 342 86 87",
    "sg:postcode":"4020",
    "sg:province":"Li\u00e8ge",
    "sg:tags":[
        "publishing"
    ],
    "wof:name":"C B A Music International",
    "wof:placetype":"venue"
},
  "geometry": {"coordinates":[5.5878429413,50.6207122803],"type":"Point"}
}