{
  "type": "Feature",
  "properties": {
    "iso:country":"BE",
    "sg:address":"Pastorijstraat 43",
    "sg:city":"Sint-niklaas",
    "sg:orig_category":"Paramedische behandelingen",
    "sg:phone":"+32 3 777 65 69",
    "sg:postcode":"9100",
    "sg:province":"Oost-Vlaanderen",
    "wof:name":"J. Van Raemdonck",
    "wof:placetype":"venue"
},
  "geometry": {"coordinates":[4.1730999947,51.1931800842],"type":"Point"}
}