{
  "type": "Feature",
  "properties": {
    "iso:country":"BE",
    "sg:address":"Rue Du Ch\u00c2teau 3",
    "sg:city":"Beloeil",
    "sg:orig_category":"Brood, gebak and snoepgoed",
    "sg:phone":"+32 69 68 94 28",
    "sg:postcode":"7970",
    "sg:province":"Hainaut",
    "wof:name":"Willy Mol",
    "wof:placetype":"venue"
},
  "geometry": {"coordinates":[3.733230114,50.5493888855],"type":"Point"}
}