{
  "type": "Feature",
  "properties": {
    "addr:full":"Rue Des Croix Du Feu 11 La Louviere Hainaut 7100",
    "addr:housenumber":"11",
    "addr:postcode":"7100",
    "addr:street":"Rue Des Croix Du Feu",
    "iso:country":"BE",
    "sg:address":"Rue Des Croix Du Feu 11",
    "sg:city":"La Louviere",
    "sg:classifiers":[
        {
            "category":"Arena",
            "subcategory":"Sports Club",
            "type":"Entertainment"
        }
    ],
    "sg:phone":"+32 64 28 05 71",
    "sg:postcode":"7100",
    "sg:province":"Hainaut",
    "sg:tags":[
        "terrain",
        "hors",
        "de",
        "installation",
        "sportifs"
    ],
    "wof:name":"S.p.p.h.",
    "wof:placetype":"venue"
},
  "geometry": {"coordinates":[4.2032680511,50.4787063599],"type":"Point"}
}