{
  "type": "Feature",
  "properties": {
    "addr:full":"Oude Bruggestraat 38 Wingene West-Vlaanderen 8750",
    "addr:housenumber":"38",
    "addr:postcode":"8750",
    "addr:street":"Oude Bruggestraat",
    "iso:country":"BE",
    "sg:address":"Oude Bruggestraat 38",
    "sg:city":"Wingene",
    "sg:orig_category":"Voertuigen",
    "sg:phone":"+32 51 65 50 47",
    "sg:postcode":"8750",
    "sg:province":"West-Vlaanderen",
    "wof:name":"Garage Kerckhove",
    "wof:placetype":"venue"
},
  "geometry": {"coordinates":[3.2746970654,51.058757782],"type":"Point"}
}