{
  "type": "Feature",
  "properties": {
    "addr:full":"Noordkustlaan 12 B Groot-bijgaarden Vlaams-Brabant 1702",
    "addr:housenumber":"12 b",
    "addr:postcode":"1702",
    "addr:street":"Noordkustlaan",
    "iso:country":"BE",
    "sg:address":"Noordkustlaan 12 B",
    "sg:city":"Groot-bijgaarden",
    "sg:classifiers":[
        {
            "category":"Organizations",
            "subcategory":"Labor Organization",
            "type":"Services"
        }
    ],
    "sg:phone":"+32 2 410 55 45",
    "sg:postcode":"1702",
    "sg:province":"Vlaams-Brabant",
    "sg:tags":[
        "work",
        "assembling",
        "assembly",
        "contract"
    ],
    "wof:name":"Henri Dupont S.p.r.l.",
    "wof:placetype":"venue"
},
  "geometry": {"coordinates":[4.2800650597,50.8753395081],"type":"Point"}
}