{
  "type": "Feature",
  "properties": {
    "addr:full":"Steenakkerstraat 129 Maasmechelen Limburg 3630",
    "addr:housenumber":"129",
    "addr:postcode":"3630",
    "addr:street":"Steenakkerstraat",
    "iso:country":"BE",
    "sg:address":"Steenakkerstraat 129",
    "sg:city":"Maasmechelen",
    "sg:orig_category":"Tuinen",
    "sg:phone":"+32 89 75 66 15",
    "sg:postcode":"3630",
    "sg:province":"Limburg",
    "wof:name":"Fa. Jeurissen & Zn",
    "wof:placetype":"venue"
},
  "geometry": {"coordinates":[5.6826601028,50.9683303833],"type":"Point"}
}