{
  "type": "Feature",
  "properties": {
    "addr:full":"Europastraat 2 Boom Antwerpen 2850",
    "addr:housenumber":"2",
    "addr:postcode":"2850",
    "addr:street":"Europastraat",
    "iso:country":"BE",
    "sg:address":"Europastraat 2",
    "sg:city":"Boom",
    "sg:orig_category":"Brood, gebak and snoepgoed",
    "sg:phone":"+32 3 888 28 59",
    "sg:postcode":"2850",
    "sg:province":"Antwerpen",
    "wof:name":"Bakkerij Mertens",
    "wof:placetype":"venue"
},
  "geometry": {"coordinates":[4.3780341148,51.1001586914],"type":"Point"}
}