{
  "type": "Feature",
  "properties": {
    "addr:full":"Akkerstraat 15 Scherpenheuvel-zichem Vlaams-Brabant 3270",
    "addr:housenumber":"15",
    "addr:postcode":"3270",
    "addr:street":"Akkerstraat",
    "iso:country":"BE",
    "sg:address":"Akkerstraat 15",
    "sg:city":"Scherpenheuvel-zichem",
    "sg:orig_category":"Services pour animaux domestiques",
    "sg:phone":"+32 13 77 26 14",
    "sg:postcode":"3270",
    "sg:province":"Vlaams-Brabant",
    "wof:name":"Goya",
    "wof:placetype":"venue"
},
  "geometry": {"coordinates":[4.9932899475,50.9738922119],"type":"Point"}
}