{
  "type": "Feature",
  "properties": {
    "addr:full":"Bld. Walter De Marvis 0 Tournai Hainaut 7500",
    "addr:housenumber":"0",
    "addr:postcode":"7500",
    "iso:country":"BE",
    "sg:address":"Bld. Walter De Marvis 0",
    "sg:city":"Tournai",
    "sg:orig_category":"R\u00e9parations de chaussures and articles en cuir",
    "sg:phone":"+32 69 84 27 60",
    "sg:postcode":"7500",
    "sg:province":"Hainaut",
    "wof:name":"Mister Minit",
    "wof:placetype":"venue"
},
  "geometry": {"coordinates":[3.4043729305,50.6042327881],"type":"Point"}
}