{
  "type": "Feature",
  "properties": {
    "iso:country":"BE",
    "sg:address":"Rue Saint-l\u00e9onard 267",
    "sg:city":"Li\u00e8ge 1",
    "sg:classifiers":[
        {
            "category":"Health Services",
            "subcategory":"Doctor",
            "type":"Services"
        }
    ],
    "sg:phone":"+32 495 20 20 21",
    "sg:postcode":"4000",
    "sg:province":"Li\u00e8ge",
    "sg:tags":[
        "orthopedist"
    ],
    "wof:name":"Ortho-domicile",
    "wof:placetype":"venue"
},
  "geometry": {"coordinates":[5.5966858864,50.6510925293],"type":"Point"}
}