{
  "type": "Feature",
  "properties": {
    "addr:full":"Michel Theysstraat 17 Box 2 Diest Vlaams-Brabant 3290",
    "addr:housenumber":"17;2",
    "addr:postcode":"3290",
    "addr:street":"Theysstraat;Box",
    "iso:country":"BE",
    "sg:address":"Michel Theysstraat 17 Box 2",
    "sg:city":"Diest",
    "sg:classifiers":[
        {
            "category":"Health Services",
            "subcategory":"Dentist",
            "type":"Services"
        }
    ],
    "sg:phone":"+32 13 32 22 06",
    "sg:postcode":"3290",
    "sg:province":"Vlaams-Brabant",
    "wof:name":"Smeets Jo",
    "wof:placetype":"venue"
},
  "geometry": {"coordinates":[5.0534029007,50.9868888855],"type":"Point"}
}