{
  "type": "Feature",
  "properties": {
    "iso:country":"BE",
    "sg:address":"Markt 18",
    "sg:city":"Eeklo",
    "sg:classifiers":[
        {
            "category":"Bars & Pubs",
            "type":"Food & Drink"
        }
    ],
    "sg:phone":"+32 9 378 18 18",
    "sg:postcode":"9900",
    "sg:province":"Oost-Vlaanderen",
    "wof:name":"Kabouterke ('t)",
    "wof:placetype":"venue"
},
  "geometry": {"coordinates":[3.5671598911,51.1846199036],"type":"Point"}
}