{
  "type": "Feature",
  "properties": {
    "addr:full":"Geraardsbergsesteenweg 140 Oosterzele Oost-Vlaanderen 9860",
    "addr:housenumber":"140",
    "addr:postcode":"9860",
    "addr:street":"Geraardsbergsesteenweg;Oost-Vlaanderen",
    "iso:country":"BE",
    "sg:address":"Geraardsbergsesteenweg 140",
    "sg:city":"Oosterzele",
    "sg:orig_category":"Loodgieterij, verwarming and sanitaire installaties",
    "sg:phone":"+32 9 362 87 71",
    "sg:postcode":"9860",
    "sg:province":"Oost-Vlaanderen",
    "wof:name":"De Munter",
    "wof:placetype":"venue"
},
  "geometry": {"coordinates":[3.8136410713,50.9478378296],"type":"Point"}
}