{
  "type": "Feature",
  "properties": {
    "addr:full":"Europaplein 5 Bierbeek Vlaams-Brabant 3360",
    "addr:housenumber":"5",
    "addr:postcode":"3360",
    "addr:street":"Europaplein",
    "iso:country":"BE",
    "sg:address":"Europaplein 5",
    "sg:city":"Bierbeek",
    "sg:orig_category":"Avocats and conseillers juridiques",
    "sg:phone":"+32 16 46 34 82",
    "sg:postcode":"3360",
    "sg:province":"Vlaams-Brabant",
    "wof:name":"J. Naulaerts",
    "wof:placetype":"venue"
},
  "geometry": {"coordinates":[4.7603230476,50.8696365356],"type":"Point"}
}