{
  "type": "Feature",
  "properties": {
    "addr:full":"Hoge Ziekenweg 7 Ieper West-Vlaanderen 8900",
    "addr:housenumber":"7",
    "addr:postcode":"8900",
    "addr:street":"Hoge Ziekenweg",
    "iso:country":"BE",
    "sg:address":"Hoge Ziekenweg 7",
    "sg:city":"Ieper",
    "sg:orig_category":"Varkenskwekers",
    "sg:phone":"+32 57 20 12 92",
    "sg:postcode":"8900",
    "sg:province":"West-Vlaanderen",
    "wof:name":"Bart Heyman",
    "wof:placetype":"venue"
},
  "geometry": {"coordinates":[2.8911750317,50.8734321594],"type":"Point"}
}