{
  "type": "Feature",
  "properties": {
    "addr:full":"Kouter 3 Zele Oost-Vlaanderen 9240",
    "addr:housenumber":"3",
    "addr:postcode":"9240",
    "addr:street":"Kouter",
    "iso:country":"BE",
    "sg:address":"Kouter 3",
    "sg:city":"Zele",
    "sg:orig_category":"Baby- and kinderkleding Babyspullen Dameskledingzaken",
    "sg:phone":"+32 52 44 51 70",
    "sg:postcode":"9240",
    "sg:province":"Oost-Vlaanderen",
    "wof:name":"Pr\u00c9maman",
    "wof:placetype":"venue"
},
  "geometry": {"coordinates":[4.0341382027,51.0661621094],"type":"Point"}
}