{
  "type": "Feature",
  "properties": {
    "addr:full":"Turfputten 6 Olen Antwerpen 2250",
    "addr:housenumber":"6",
    "addr:postcode":"2250",
    "addr:street":"Turfputten",
    "iso:country":"BE",
    "sg:address":"Turfputten 6",
    "sg:city":"Olen",
    "sg:classifiers":[
        {
            "category":"Utilities",
            "subcategory":"Refuse",
            "type":"Services"
        }
    ],
    "sg:phone":"+32 14 25 75 51",
    "sg:postcode":"2250",
    "sg:province":"Antwerpen",
    "sg:tags":[
        "catering"
    ],
    "wof:name":"Bell Food Bvba",
    "wof:placetype":"venue"
},
  "geometry": {"coordinates":[4.8964748383,51.1469993591],"type":"Point"}
}