{
  "type": "Feature",
  "properties": {
    "addr:full":"Frankrijklei 113 Antwerpen Antwerpen 2000",
    "addr:housenumber":"113",
    "addr:postcode":"2000",
    "addr:street":"Frankrijklei",
    "iso:country":"BE",
    "sg:address":"Frankrijklei 113",
    "sg:city":"Antwerpen",
    "sg:orig_category":"Banques and organismes de cr\u00e9dit",
    "sg:phone":"+32 3 232 71 78",
    "sg:postcode":"2000",
    "sg:province":"Antwerpen",
    "wof:name":"Bankunie",
    "wof:placetype":"venue"
},
  "geometry": {"coordinates":[4.41020298,51.2123947144],"type":"Point"}
}