{
  "type": "Feature",
  "properties": {
    "addr:full":"Place Saint-barth\u00c9lemy 6 Li\u00c8ge Li\u00e8ge 4000",
    "addr:housenumber":"6",
    "addr:postcode":"4000",
    "addr:street":"Place Saint-Barthe\u0301Lemy",
    "iso:country":"BE",
    "sg:address":"Place Saint-barth\u00c9lemy 6",
    "sg:city":"Li\u00c8ge",
    "sg:orig_category":"M\u00e9decins and sp\u00e9cialistes",
    "sg:phone":"+32 4 223 13 63",
    "sg:postcode":"4000",
    "sg:province":"Li\u00e8ge",
    "wof:name":"David Benrubi",
    "wof:placetype":"venue"
},
  "geometry": {"coordinates":[5.5821099281,50.6475486755],"type":"Point"}
}