{
  "type": "Feature",
  "properties": {
    "iso:country":"BE",
    "sg:address":"Rue M Van Lier 24",
    "sg:city":"Brussel",
    "sg:orig_category":"Secr\u00e9tariats",
    "sg:phone":"+32 2 523 38 09",
    "sg:postcode":"1070",
    "sg:province":"Bruxelles-Capitale",
    "wof:name":"Prosprict Consulting",
    "wof:placetype":"venue"
},
  "geometry": {"coordinates":[4.3277359009,50.8393554688],"type":"Point"}
}