{
  "type": "Feature",
  "properties": {
    "iso:country":"BE",
    "sg:address":"Nieuwstraat 8",
    "sg:city":"Meeuwen-gruitrode",
    "sg:orig_category":"Eleveurs de bovins",
    "sg:phone":"+32 89 85 22 53",
    "sg:postcode":"3670",
    "sg:province":"Limburg",
    "wof:name":"Rudi Vanreyten",
    "wof:placetype":"venue"
},
  "geometry": {"coordinates":[5.6164178848,51.0928382874],"type":"Point"}
}