{
  "type": "Feature",
  "properties": {
    "iso:country":"BE",
    "sg:address":"Pater Segersstraat 12",
    "sg:city":"Sint-niklaas",
    "sg:orig_category":"Quincailleries. Textiles. Rev\u00eatements de sols and murs. Drogueries. Eclairage et \u00e9quipements du foye",
    "sg:phone":"+32 3 776 70 26",
    "sg:postcode":"9100",
    "sg:province":"Oost-Vlaanderen",
    "wof:name":"Huyghe Decoratie",
    "wof:placetype":"venue"
},
  "geometry": {"coordinates":[4.137111187,51.1562652588],"type":"Point"}
}