{
  "type": "Feature",
  "properties": {
    "addr:full":"Grote Steenweg 481b1 Antwerpen Antwerpen 2600",
    "addr:housenumber":"481b1",
    "addr:postcode":"2600",
    "addr:street":"Grote Steenweg",
    "iso:country":"BE",
    "sg:address":"Grote Steenweg 481b1",
    "sg:city":"Antwerpen",
    "sg:orig_category":"Boekhouders",
    "sg:phone":"+32 3 239 76 25",
    "sg:postcode":"2600",
    "sg:province":"Antwerpen",
    "wof:name":"Jozef Wynants",
    "wof:placetype":"venue"
},
  "geometry": {"coordinates":[4.4174151421,51.1974411011],"type":"Point"}
}