{
  "type": "Feature",
  "properties": {
    "addr:full":"Impasse Macors 54 Li\u00e8ge 1 Li\u00e8ge 4000",
    "addr:housenumber":"54;1",
    "addr:postcode":"4000",
    "addr:street":"Impasse Macors",
    "iso:country":"BE",
    "sg:address":"Impasse Macors 54",
    "sg:city":"Li\u00e8ge 1",
    "sg:classifiers":[
        {
            "category":"Real Estate",
            "subcategory":"Architect",
            "type":"Services"
        }
    ],
    "sg:phone":"+32 4 228 06 33",
    "sg:postcode":"4000",
    "sg:province":"Li\u00e8ge",
    "wof:name":"Stassen J-m",
    "wof:placetype":"venue"
},
  "geometry": {"coordinates":[5.593018055,50.6553230286],"type":"Point"}
}