{
  "type": "Feature",
  "properties": {
    "addr:full":"Avenue De Luxembourg 20 Arlon Luxembourg 6700",
    "addr:housenumber":"20",
    "addr:postcode":"6700",
    "addr:street":"Avenue De Luxembourg",
    "iso:country":"BE",
    "sg:address":"Avenue De Luxembourg 20",
    "sg:city":"Arlon",
    "sg:classifiers":[
        {
            "category":"Personal",
            "subcategory":"Beauty Salon",
            "type":"Services"
        }
    ],
    "sg:phone":"+32 63 41 34 50",
    "sg:postcode":"6700",
    "sg:province":"Luxembourg",
    "sg:tags":[
        "lady",
        "-",
        "hairdressing"
    ],
    "wof:name":"Dachkin Olivier",
    "wof:placetype":"venue"
},
  "geometry": {"coordinates":[5.8226308823,49.6775093079],"type":"Point"}
}