{
  "type": "Feature",
  "properties": {
    "iso:country":"BE",
    "sg:address":"Kerkhofstraat 180",
    "sg:city":"Boom",
    "sg:orig_category":"Afval and schroot Gh Autoverhuur Goederenvervoer over de weg Verhuisdiensten",
    "sg:phone":"+32 3 888 18 65",
    "sg:postcode":"2850",
    "sg:province":"Antwerpen",
    "wof:name":"Boeckxstaens & Co",
    "wof:placetype":"venue"
},
  "geometry": {"coordinates":[4.3770508766,51.0919570923],"type":"Point"}
}