{
  "type": "Feature",
  "properties": {
    "iso:country":"BE",
    "sg:address":"Sint-rochusstraat 16",
    "sg:city":"Deerlijk",
    "sg:classifiers":[
        {
            "category":"Home & Garden",
            "subcategory":"Home Furnishings",
            "type":"Retail Goods"
        }
    ],
    "sg:phone":"+32 56 71 45 76",
    "sg:postcode":"8540",
    "sg:province":"West-Vlaanderen",
    "sg:tags":[
        "curtain",
        "-",
        "fixture"
    ],
    "wof:name":"Van De Walle E-decoric",
    "wof:placetype":"venue"
},
  "geometry": {"coordinates":[3.3586940765,50.8532409668],"type":"Point"}
}