{
  "type": "Feature",
  "properties": {
    "addr:full":"Cours Bonaparte 8 Villers-la-ville Brabant Wallon 1495",
    "addr:housenumber":"8",
    "addr:postcode":"1495",
    "addr:street":"Cours Bonaparte",
    "iso:country":"BE",
    "sg:address":"Cours Bonaparte 8",
    "sg:city":"Villers-la-ville",
    "sg:orig_category":"Diverse bedrijfsbeheeradviesbureaus",
    "sg:phone":"+32 67 77 18 21",
    "sg:postcode":"1495",
    "sg:province":"Brabant Wallon",
    "wof:name":"Heyse",
    "wof:placetype":"venue"
},
  "geometry": {"coordinates":[4.462887764,50.5726394653],"type":"Point"}
}