{
  "type": "Feature",
  "properties": {
    "iso:country":"BE",
    "sg:address":"Joseph Possozplein 40",
    "sg:city":"Halle",
    "sg:orig_category":"Auto-\u00e9coles",
    "sg:phone":"+32 2 356 24 49",
    "sg:postcode":"1500",
    "sg:province":"Vlaams-Brabant",
    "wof:name":"Stedelijke Rijschool",
    "wof:placetype":"venue"
},
  "geometry": {"coordinates":[4.2380809784,50.7357406616],"type":"Point"}
}