{
  "type": "Feature",
  "properties": {
    "addr:full":"Rue Bois Des Iles 15 Bruxelles (berchem-sainte-agathe) Bruxelles-Capitale 1082",
    "addr:housenumber":"15",
    "addr:postcode":"1082",
    "addr:street":"Rue Bois Des Iles",
    "iso:country":"BE",
    "sg:address":"Rue Bois Des Iles 15",
    "sg:city":"Bruxelles (berchem-sainte-agathe)",
    "sg:classifiers":[
        {
            "category":"Building & Trades",
            "subcategory":"Construction",
            "type":"Services"
        }
    ],
    "sg:phone":"+32 2 482 11 30",
    "sg:postcode":"1082",
    "sg:province":"Bruxelles-Capitale",
    "sg:tags":[
        "scaffolding"
    ],
    "wof:name":"Mercura Sa",
    "wof:placetype":"venue"
},
  "geometry": {"coordinates":[4.2918848991,50.8730888367],"type":"Point"}
}