{
  "type": "Feature",
  "properties": {
    "iso:country":"BE",
    "sg:address":"Zeelaan 86",
    "sg:city":"De Panne",
    "sg:orig_category":"Agences de voyages",
    "sg:phone":"+32 58 42 22 65",
    "sg:postcode":"8660",
    "sg:province":"West-Vlaanderen",
    "wof:name":"Bruneel Reizen",
    "wof:placetype":"venue"
},
  "geometry": {"coordinates":[2.5917420387,51.0983505249],"type":"Point"}
}