{
  "type": "Feature",
  "properties": {
    "addr:full":"Withofsstraat 2 Bilzen Limburg 3740",
    "addr:housenumber":"2",
    "addr:postcode":"3740",
    "addr:street":"Withofsstraat",
    "iso:country":"BE",
    "sg:address":"Withofsstraat 2",
    "sg:city":"Bilzen",
    "sg:orig_category":"Fleurs and plantes",
    "sg:phone":"+32 89 49 23 03",
    "sg:postcode":"3740",
    "sg:province":"Limburg",
    "wof:name":"Herman Vandecaetsbeek",
    "wof:placetype":"venue"
},
  "geometry": {"coordinates":[5.575756073,50.876209259],"type":"Point"}
}