{
  "type": "Feature",
  "properties": {
    "iso:country":"BE",
    "sg:address":"Avenue De La Vall\u00c9e 6",
    "sg:city":"Waterloo",
    "sg:orig_category":"Diverse grafische activiteiten Reclamebureaus",
    "sg:phone":"+32 2 354 21 98",
    "sg:postcode":"1410",
    "sg:province":"Brabant Wallon",
    "wof:name":"Leopold Renard",
    "wof:placetype":"venue"
},
  "geometry": {"coordinates":[4.359746933,50.715461731],"type":"Point"}
}