{
  "type": "Feature",
  "properties": {
    "addr:full":"Portugeesstraat 25 Affligem (teralfene) Vlaams-Brabant 1790",
    "addr:housenumber":"25",
    "addr:postcode":"1790",
    "addr:street":"Portugeesstraat",
    "iso:country":"BE",
    "sg:address":"Portugeesstraat 25",
    "sg:city":"Affligem (teralfene)",
    "sg:classifiers":[
        {
            "category":"Home & Garden",
            "subcategory":"Home Furnishings",
            "type":"Retail Goods"
        }
    ],
    "sg:phone":"+32 53 67 26 00",
    "sg:postcode":"1790",
    "sg:province":"Vlaams-Brabant",
    "sg:tags":[
        "interior",
        "decoration"
    ],
    "wof:name":"Asselman D",
    "wof:placetype":"venue"
},
  "geometry": {"coordinates":[4.1013789177,50.8877601624],"type":"Point"}
}