{
  "type": "Feature",
  "properties": {
    "addr:full":"Brugseweg 127 Langemark-poelkapelle West-Vlaanderen 8920",
    "addr:housenumber":"127",
    "addr:postcode":"8920",
    "addr:street":"Brugseweg",
    "iso:country":"BE",
    "sg:address":"Brugseweg 127",
    "sg:city":"Langemark-poelkapelle",
    "sg:orig_category":"Loodgieterij, verwarming and sanitaire installaties",
    "sg:phone":"+32 57 48 90 41",
    "sg:postcode":"8920",
    "sg:province":"West-Vlaanderen",
    "wof:name":"Rik Derycke",
    "wof:placetype":"venue"
},
  "geometry": {"coordinates":[2.9379899502,50.8924789429],"type":"Point"}
}