{
  "type": "Feature",
  "properties": {
    "addr:full":"Boulevard Pach\u00c9co 7 Brussel/bruxelles Bruxelles-Capitale 1000",
    "addr:housenumber":"7",
    "addr:postcode":"1000",
    "addr:street":"Boulevard Pache\u0301Co;/",
    "iso:country":"BE",
    "sg:address":"Boulevard Pach\u00c9co 7",
    "sg:city":"Brussel/bruxelles",
    "sg:classifiers":[
        {
            "category":"Autos & Motor Vehicles",
            "subcategory":"Fuel & Gas Station",
            "type":"Retail Goods"
        }
    ],
    "sg:phone":"+32 2 218 74 19",
    "sg:postcode":"1000",
    "sg:province":"Bruxelles-Capitale",
    "sg:tags":[
        "stations-service",
        "carburants"
    ],
    "wof:name":"Fina",
    "wof:placetype":"venue"
},
  "geometry": {"coordinates":[4.3622479439,50.8514556885],"type":"Point"}
}