{
  "type": "Feature",
  "properties": {
    "iso:country":"BE",
    "sg:address":"Grote Herreweg 181",
    "sg:city":"Kluisbergen",
    "sg:orig_category":"Journaux. Epiceries",
    "sg:phone":"+32 55 38 94 04",
    "sg:postcode":"9690",
    "sg:province":"Oost-Vlaanderen",
    "wof:name":"Veronique Verwee",
    "wof:placetype":"venue"
},
  "geometry": {"coordinates":[3.4899029732,50.7758636475],"type":"Point"}
}