{
  "type": "Feature",
  "properties": {
    "addr:full":"Kerkplein 7 Eeklo Oost-Vlaanderen 9900",
    "addr:housenumber":"7",
    "addr:postcode":"9900",
    "addr:street":"Kerkplein",
    "iso:country":"BE",
    "sg:address":"Kerkplein 7",
    "sg:city":"Eeklo",
    "sg:orig_category":"Kapsalons",
    "sg:phone":"+32 9 378 17 44",
    "sg:postcode":"9900",
    "sg:province":"Oost-Vlaanderen",
    "wof:name":"Salon Nadine",
    "wof:placetype":"venue"
},
  "geometry": {"coordinates":[3.5658171177,51.1852111816],"type":"Point"}
}