{
  "type": "Feature",
  "properties": {
    "addr:full":"Meerweg 14 Sint-pieters-leeuw Vlaams-Brabant 1601",
    "addr:housenumber":"14",
    "addr:postcode":"1601",
    "addr:street":"Meerweg",
    "iso:country":"BE",
    "sg:address":"Meerweg 14",
    "sg:city":"Sint-pieters-leeuw",
    "sg:orig_category":"Artistes ind\u00e9pendants",
    "sg:phone":"+32 2 377 45 05",
    "sg:postcode":"1601",
    "sg:province":"Vlaams-Brabant",
    "wof:name":"Charles Bonnewijn",
    "wof:placetype":"venue"
},
  "geometry": {"coordinates":[4.29185009,50.7896537781],"type":"Point"}
}