{
  "type": "Feature",
  "properties": {
    "addr:full":"Rue Henri Orban 2 Aywaille Li\u00e8ge 4920",
    "addr:housenumber":"2",
    "addr:postcode":"4920",
    "addr:street":"Rue Henri Orban",
    "iso:country":"BE",
    "sg:address":"Rue Henri Orban 2",
    "sg:city":"Aywaille",
    "sg:orig_category":"Kleding Schoenen Sport- and kampeermateriaal Watersport-, Sport- and Kampeerbenodigdheden Verhuur",
    "sg:phone":"+32 4 384 57 04",
    "sg:postcode":"4920",
    "sg:province":"Li\u00e8ge",
    "wof:name":"Intersport",
    "wof:placetype":"venue"
},
  "geometry": {"coordinates":[5.6745018959,50.4740409851],"type":"Point"}
}