{
  "type": "Feature",
  "properties": {
    "addr:full":"Ringln 6a Brecht Antwerpen 2960",
    "addr:housenumber":"6a",
    "addr:postcode":"2960",
    "addr:street":"Ringln",
    "iso:country":"BE",
    "sg:address":"Ringln 6a",
    "sg:city":"Brecht",
    "sg:classifiers":[
        {
            "category":"Professional",
            "type":"Services"
        }
    ],
    "sg:phone":"+32 3 313 50 00",
    "sg:postcode":"2960",
    "sg:province":"Antwerpen",
    "sg:tags":[
        "transport",
        "road"
    ],
    "wof:name":"J. Deckers En Zn Nv",
    "wof:placetype":"venue"
},
  "geometry": {"coordinates":[4.6415200233,51.3512115479],"type":"Point"}
}