{
  "type": "Feature",
  "properties": {
    "iso:country":"BE",
    "sg:address":"Chemin Ferme L'escole 53",
    "sg:city":"Soignies",
    "sg:orig_category":"Installation \u00e9lectrique r\u00e9sidentielle",
    "sg:phone":"+32 67 45 81 33",
    "sg:postcode":"7060",
    "sg:province":"Hainaut",
    "wof:name":"P.m.e. Service",
    "wof:placetype":"venue"
},
  "geometry": {"coordinates":[3.9962770939,50.6105041504],"type":"Point"}
}