{
  "type": "Feature",
  "properties": {
    "iso:country":"BE",
    "sg:address":"Pontstraat 3",
    "sg:city":"Deerlijk",
    "sg:orig_category":"Zuivelproducten",
    "sg:phone":"+32 56 71 12 22",
    "sg:postcode":"8540",
    "sg:province":"West-Vlaanderen",
    "wof:name":"Anita Depraetere",
    "wof:placetype":"venue"
},
  "geometry": {"coordinates":[3.3552320004,50.8515853882],"type":"Point"}
}