{
  "type": "Feature",
  "properties": {
    "iso:country":"BE",
    "sg:address":"Rue Des Ponts 21br3",
    "sg:city":"Tubize",
    "sg:orig_category":"D\u00e9corateurs d'int\u00e9rieur",
    "sg:phone":"+32 2 355 02 82",
    "sg:postcode":"1480",
    "sg:province":"Brabant Wallon",
    "wof:name":"Pierre Lebrun",
    "wof:placetype":"venue"
},
  "geometry": {"coordinates":[4.201941967,50.6895675659],"type":"Point"}
}