{
  "type": "Feature",
  "properties": {
    "iso:country":"BE",
    "sg:address":"Bredabaan 88ba",
    "sg:city":"Wuustwezel",
    "sg:orig_category":"Installatie van houten of kunststof schrijnwerk",
    "sg:phone":"+32 3 669 56 84",
    "sg:postcode":"2990",
    "sg:province":"Antwerpen",
    "wof:name":"Jan Embrechts",
    "wof:placetype":"venue"
},
  "geometry": {"coordinates":[4.5545501709,51.3597984314],"type":"Point"}
}