{
  "type": "Feature",
  "properties": {
    "iso:country":"BE",
    "sg:address":"Rue Du Mont Blanc 24",
    "sg:city":"Bruxelles (saint-gilles)",
    "sg:classifiers":[
        {
            "category":"Professional",
            "subcategory":"Art Services",
            "type":"Services"
        }
    ],
    "sg:phone":"+32 2 534 01 40",
    "sg:postcode":"1060",
    "sg:province":"Bruxelles-Capitale",
    "sg:tags":[
        "realization",
        "audio-visual"
    ],
    "wof:name":"Vannieu O",
    "wof:placetype":"venue"
},
  "geometry": {"coordinates":[4.3499331474,50.8283081055],"type":"Point"}
}