{
  "type": "Feature",
  "properties": {
    "addr:full":"Lierseweg 138 Herentals Antwerpen 2200",
    "addr:housenumber":"138",
    "addr:postcode":"2200",
    "addr:street":"Lierseweg",
    "iso:country":"BE",
    "sg:address":"Lierseweg 138",
    "sg:city":"Herentals",
    "sg:orig_category":"Entretien and r\u00e9parations de voitures. D\u00e9taillants en pi\u00e8ces and accessoires de voitures",
    "sg:phone":"+32 14 21 17 68",
    "sg:postcode":"2200",
    "sg:province":"Antwerpen",
    "wof:name":"Donckers Autobanden",
    "wof:placetype":"venue"
},
  "geometry": {"coordinates":[4.8230838776,51.1752815247],"type":"Point"}
}