{
  "type": "Feature",
  "properties": {
    "iso:country":"BE",
    "sg:address":"Rue De La Sablonni\u00e8re 18",
    "sg:city":"Bruxelles",
    "sg:classifiers":[
        {
            "category":"Organizations",
            "subcategory":"Non-profit Organization",
            "type":"Services"
        }
    ],
    "sg:phone":"+32 2 223 05 12",
    "sg:postcode":"1000",
    "sg:province":"Bruxelles-Capitale",
    "sg:tags":[
        "international",
        "organisation"
    ],
    "wof:name":"Le Monde Selon Les Femmes (ong)",
    "wof:placetype":"venue"
},
  "geometry": {"coordinates":[4.3665151596,50.8520393372],"type":"Point"}
}