{
  "type": "Feature",
  "properties": {
    "iso:country":"BE",
    "sg:address":"Chauss\u00e9e D'alsemberg 196",
    "sg:city":"Bruxelles (forest)",
    "sg:classifiers":[
        {
            "category":"Professional",
            "subcategory":"Testing Lab",
            "type":"Services"
        }
    ],
    "sg:phone":"+32 2 349 67 11",
    "sg:postcode":"1190",
    "sg:province":"Bruxelles-Capitale",
    "sg:tags":[
        "laboratory",
        "medical"
    ],
    "wof:name":"L B S",
    "wof:placetype":"venue"
},
  "geometry": {"coordinates":[4.3362002373,50.8246688843],"type":"Point"}
}