{
  "type": "Feature",
  "properties": {
    "iso:country":"BE",
    "sg:address":"Steenweg Op Gierle 100",
    "sg:city":"Turnhout",
    "sg:classifiers":[
        {
            "category":"Education",
            "subcategory":"Special Training",
            "type":"Public Place"
        }
    ],
    "sg:phone":"+32 14 40 01 00",
    "sg:postcode":"2300",
    "sg:province":"Antwerpen",
    "sg:tags":[
        "-",
        "processing",
        "data"
    ],
    "wof:name":"Cyberskills",
    "wof:placetype":"venue"
},
  "geometry": {"coordinates":[4.9299302101,51.3148002625],"type":"Point"}
}