{
  "type": "Feature",
  "properties": {
    "iso:country":"BE",
    "sg:address":"Rue Li\u00c9bin 78",
    "sg:city":"La Louvi\u00c8re",
    "sg:orig_category":"Installation \u00e9lectrique r\u00e9sidentielle",
    "sg:phone":"+32 64 84 81 04",
    "sg:postcode":"7110",
    "sg:province":"Hainaut",
    "wof:name":"Jaumot & Delaunois",
    "wof:placetype":"venue"
},
  "geometry": {"coordinates":[4.1505050659,50.4826698303],"type":"Point"}
}