{
  "type": "Feature",
  "properties": {
    "iso:country":"BE",
    "sg:address":"Avenue L\u00c9on Jouret 3",
    "sg:city":"Ath",
    "sg:orig_category":"Beautyfarms, relaxatie and lichamelijk welzijn Schoonheidssalons",
    "sg:phone":"+32 68 28 00 80",
    "sg:postcode":"7800",
    "sg:province":"Hainaut",
    "wof:name":"Ctre Esth\u00c9t. Anti-stress",
    "wof:placetype":"venue"
},
  "geometry": {"coordinates":[3.7834820747,50.6337242126],"type":"Point"}
}