{
  "type": "Feature",
  "properties": {
    "addr:full":"Provinciesteenweg 18 Haacht Vlaams-Brabant 3150",
    "addr:housenumber":"18",
    "addr:postcode":"3150",
    "addr:street":"Provinciesteenweg",
    "iso:country":"BE",
    "sg:address":"Provinciesteenweg 18",
    "sg:city":"Haacht",
    "sg:orig_category":"Newspapers, magazines, periodicals - Distribution",
    "sg:phone":"+32 16 60 87 46",
    "sg:postcode":"3150",
    "sg:province":"Vlaams-Brabant",
    "wof:name":"Krantenwinkel (de)",
    "wof:placetype":"venue"
},
  "geometry": {"coordinates":[4.6098418236,50.9650344849],"type":"Point"}
}