{
  "type": "Feature",
  "properties": {
    "addr:full":"Rue Des Clouteries 32 Fontaine-l'ev\u00eaque Hainaut 6140",
    "addr:housenumber":"32",
    "addr:postcode":"6140",
    "addr:street":"Rue Des Clouteries;\u0302Que Hainaut",
    "iso:country":"BE",
    "sg:address":"Rue Des Clouteries 32",
    "sg:city":"Fontaine-l'ev\u00eaque",
    "sg:classifiers":[
        {
            "category":"Health Services",
            "subcategory":"Health Practitioner",
            "type":"Services"
        }
    ],
    "sg:phone":"+32 495 54 17 29",
    "sg:postcode":"6140",
    "sg:province":"Hainaut",
    "sg:tags":[
        "physiotherapist"
    ],
    "wof:name":"Guyaux Johann",
    "wof:placetype":"venue"
},
  "geometry": {"coordinates":[-111.9644622803,46.2507972717],"type":"Point"}
}