{
  "type": "Feature",
  "properties": {
    "addr:full":"Merelstraat 20 Izegem West-Vlaanderen 8870",
    "addr:housenumber":"20",
    "addr:postcode":"8870",
    "addr:street":"Merelstraat",
    "iso:country":"BE",
    "sg:address":"Merelstraat 20",
    "sg:city":"Izegem",
    "sg:orig_category":"Gespecialiseerde residenti\u00eble bouw Plaatsen van vloer- and muurbekleding Woningbouw",
    "sg:phone":"+32 51 31 15 28",
    "sg:postcode":"8870",
    "sg:province":"West-Vlaanderen",
    "wof:name":"Filip Lioen",
    "wof:placetype":"venue"
},
  "geometry": {"coordinates":[3.227175951,50.9281616211],"type":"Point"}
}