{
  "type": "Feature",
  "properties": {
    "addr:full":"Rue Jules Destr\u00e9e 217 Quaregnon Hainaut 7390",
    "addr:housenumber":"217",
    "addr:postcode":"7390",
    "addr:street":"Rue Jules Destre\u0301E",
    "iso:country":"BE",
    "sg:address":"Rue Jules Destr\u00e9e 217",
    "sg:city":"Quaregnon",
    "sg:classifiers":[
        {
            "category":"Professional",
            "subcategory":"Testing Lab",
            "type":"Services"
        }
    ],
    "sg:phone":"+32 65 78 13 60",
    "sg:postcode":"7390",
    "sg:province":"Hainaut",
    "sg:tags":[
        "laboratory",
        "photographic",
        "film"
    ],
    "wof:name":"Look Photo Studio Bonnard",
    "wof:placetype":"venue"
},
  "geometry": {"coordinates":[3.8641901016,50.4444580078],"type":"Point"}
}