{
  "type": "Feature",
  "properties": {
    "iso:country":"BE",
    "sg:address":"Brusselsesteenweg 474",
    "sg:city":"Gent (ledeberg)",
    "sg:classifiers":[
        {
            "category":"Professional",
            "subcategory":"Management & Consulting",
            "type":"Services"
        }
    ],
    "sg:phone":"+32 9 232 54 74",
    "sg:postcode":"9050",
    "sg:province":"Oost-Vlaanderen",
    "sg:tags":[
        "consultant"
    ],
    "wof:name":"Rafico",
    "wof:placetype":"venue"
},
  "geometry": {"coordinates":[3.7471899986,51.0385093689],"type":"Point"}
}