{
  "type": "Feature",
  "properties": {
    "iso:country":"BE",
    "sg:address":"Rue Du Moulin 37",
    "sg:city":"Courcelles (gouy-lez-pi\u00e9ton)",
    "sg:classifiers":[
        {
            "category":"Building & Trades",
            "subcategory":"Equipment Rental",
            "type":"Services"
        }
    ],
    "sg:phone":"+32 71 84 49 29",
    "sg:postcode":"6181",
    "sg:province":"Hainaut",
    "sg:tags":[
        "use",
        "apparatus",
        "tool",
        "-",
        "professional",
        "machines"
    ],
    "wof:name":"T.t.g. Sprl",
    "wof:placetype":"venue"
},
  "geometry": {"coordinates":[4.3260369301,50.4941101074],"type":"Point"}
}