{
  "type": "Feature",
  "properties": {
    "iso:country":"BE",
    "sg:address":"Loeverstr 12",
    "sg:city":"Sint-gillis-waas",
    "sg:classifiers":[
        {
            "category":"Professional",
            "type":"Services"
        }
    ],
    "sg:phone":"+32 3 770 80 08",
    "sg:postcode":"9170",
    "sg:province":"Oost-Vlaanderen",
    "sg:tags":[
        "transport",
        "road"
    ],
    "wof:name":"Dullaert Eddy Nv",
    "wof:placetype":"venue"
},
  "geometry": {"coordinates":[4.0911741257,51.2143974304],"type":"Point"}
}