{
  "type": "Feature",
  "properties": {
    "addr:full":"Route D'herbesthal 323 Eupen Li\u00e8ge 4700",
    "addr:housenumber":"323",
    "addr:postcode":"4700",
    "addr:street":"Route D'Herbesthal",
    "iso:country":"BE",
    "sg:address":"Route D'herbesthal 323",
    "sg:city":"Eupen",
    "sg:orig_category":"Supermarch\u00e9s",
    "sg:phone":"+32 87 89 90 11",
    "sg:postcode":"4700",
    "sg:province":"Li\u00e8ge",
    "wof:name":"Flaronis",
    "wof:placetype":"venue"
},
  "geometry": {"coordinates":[6.0259408951,50.6333389282],"type":"Point"}
}