{
  "type": "Feature",
  "properties": {
    "iso:country":"BE",
    "sg:address":"Waterloose Steenweg 226",
    "sg:city":"Sint-gillis/saint-gilles",
    "sg:orig_category":"Diverse bouwafwerking and reiniging",
    "sg:phone":"+32 2 534 93 82",
    "sg:postcode":"1060",
    "sg:province":"Bruxelles-Capitale",
    "wof:name":"Da Silva",
    "wof:placetype":"venue"
},
  "geometry": {"coordinates":[4.345872879,50.8264503479],"type":"Point"}
}