{
  "type": "Feature",
  "properties": {
    "addr:full":"Stationsstraat 25 Essen Antwerpen 2910",
    "addr:housenumber":"25",
    "addr:postcode":"2910",
    "addr:street":"Stationsstraat",
    "iso:country":"BE",
    "sg:address":"Stationsstraat 25",
    "sg:city":"Essen",
    "sg:classifiers":[
        {
            "category":"Restaurant",
            "type":"Food & Drink"
        }
    ],
    "sg:phone":"+32 3 667 20 82",
    "sg:postcode":"2910",
    "sg:province":"Antwerpen",
    "wof:name":"Rommens",
    "wof:placetype":"venue"
},
  "geometry": {"coordinates":[4.4666042328,51.4668273926],"type":"Point"}
}