{
  "type": "Feature",
  "properties": {
    "iso:country":"BE",
    "sg:address":"Rue Des Combattants 26",
    "sg:city":"Braine-l\u00b4alleud",
    "sg:orig_category":"R\u00e9paration and restauration de meubles",
    "sg:phone":"+32 2 385 22 26",
    "sg:postcode":"1421",
    "sg:province":"Brabant Wallon",
    "wof:name":"La Clinique Du Meuble",
    "wof:placetype":"venue"
},
  "geometry": {"coordinates":[4.3468031883,50.6650161743],"type":"Point"}
}