{
  "type": "Feature",
  "properties": {
    "iso:country":"BE",
    "sg:address":"Avenue Des Alli\u00c9s 6",
    "sg:city":"Charleroi",
    "sg:orig_category":"Belastingconsulenten Diverse juridische dienstverlening",
    "sg:phone":"+32 71 32 61 57",
    "sg:postcode":"6000",
    "sg:province":"Hainaut",
    "wof:name":"R. & L.",
    "wof:placetype":"venue"
},
  "geometry": {"coordinates":[4.43998909,50.4106712341],"type":"Point"}
}