{
  "type": "Feature",
  "properties": {
    "addr:full":"Goevrouwestraat 5 Menen West-Vlaanderen 8930",
    "addr:housenumber":"5",
    "addr:postcode":"8930",
    "addr:street":"Goevrouwestraat",
    "iso:country":"BE",
    "sg:address":"Goevrouwestraat 5",
    "sg:city":"Menen",
    "sg:classifiers":[
        {
            "category":"Arena",
            "subcategory":"Sports Club",
            "type":"Entertainment"
        }
    ],
    "sg:phone":"+32 56 40 05 64",
    "sg:postcode":"8930",
    "sg:province":"West-Vlaanderen",
    "sg:tags":[
        "de"
    ],
    "wof:name":"V.c. Volare",
    "wof:placetype":"venue"
},
  "geometry": {"coordinates":[3.1209149361,50.7961845398],"type":"Point"}
}