{
  "type": "Feature",
  "properties": {
    "addr:full":"Neeroeterenstraat 7 Maaseik Limburg 3680",
    "addr:housenumber":"7",
    "addr:postcode":"3680",
    "addr:street":"Neeroeterenstraat",
    "iso:country":"BE",
    "sg:address":"Neeroeterenstraat 7",
    "sg:city":"Maaseik",
    "sg:classifiers":[
        {
            "category":"Shopping",
            "subcategory":"Clothing, Apparel, & Fashions",
            "type":"Retail Goods"
        }
    ],
    "sg:phone":"+32 89 86 42 69",
    "sg:postcode":"3680",
    "sg:province":"Limburg",
    "sg:tags":[
        "v\u00eatements",
        "pour",
        "dame"
    ],
    "wof:name":"Van Hoof Kleding",
    "wof:placetype":"venue"
},
  "geometry": {"coordinates":[5.791285038,51.0954208374],"type":"Point"}
}