{
  "type": "Feature",
  "properties": {
    "addr:full":"Ch De La Hulpe 181 Bte 2 Bruxelles Bruxelles-Capitale 1170",
    "addr:housenumber":"181;2",
    "addr:postcode":"1170",
    "addr:street":"Ch De La Hulpe;Bte",
    "iso:country":"BE",
    "sg:address":"Ch De La Hulpe 181 Bte 2",
    "sg:city":"Bruxelles",
    "sg:classifiers":[
        {
            "category":"Manufacturing",
            "subcategory":"Glass & Minerals",
            "type":"Manufacturing & Wholesale Goods"
        }
    ],
    "sg:phone":"+32 2 210 00 80",
    "sg:postcode":"1170",
    "sg:province":"Bruxelles-Capitale",
    "sg:tags":[
        "building",
        "material"
    ],
    "wof:name":"Industrie, Commerce, Plastique Sa",
    "wof:placetype":"venue"
},
  "geometry": {"coordinates":[4.4043002129,50.7956581116],"type":"Point"}
}