{
  "type": "Feature",
  "properties": {
    "iso:country":"BE",
    "sg:address":"Chemin De Rognon 24",
    "sg:city":"Braine-le-comte",
    "sg:orig_category":"Pensions de famille",
    "sg:phone":"+32 67 55 39 21",
    "sg:postcode":"7090",
    "sg:province":"Hainaut",
    "wof:name":"La Japonili\u00c8re",
    "wof:placetype":"venue"
},
  "geometry": {"coordinates":[4.0900268555,50.630695343],"type":"Point"}
}