{
  "type": "Feature",
  "properties": {
    "iso:country":"BE",
    "sg:address":"Veldlaan 12",
    "sg:city":"Kalmthout",
    "sg:orig_category":"Onderdelen and accessoires voor auto's",
    "sg:phone":"+32 3 666 20 25",
    "sg:postcode":"2920",
    "sg:province":"Antwerpen",
    "wof:name":"A.t.s.",
    "wof:placetype":"venue"
},
  "geometry": {"coordinates":[4.4693050385,51.3845481873],"type":"Point"}
}