{
  "type": "Feature",
  "properties": {
    "iso:country":"BE",
    "sg:address":"Chauss\u00c9e De Helmet 216",
    "sg:city":"Schaarbeek/schaerbeek",
    "sg:orig_category":"Enseignement maternel and primaire",
    "sg:phone":"+32 2 242 66 28",
    "sg:postcode":"1030",
    "sg:province":"Bruxelles-Capitale",
    "wof:name":"Vrije Basisschool",
    "wof:placetype":"venue"
},
  "geometry": {"coordinates":[4.3870210648,50.8734359741],"type":"Point"}
}