{
  "type": "Feature",
  "properties": {
    "iso:country":"BE",
    "sg:address":"Rue Des Genets 10",
    "sg:city":"Hamois",
    "sg:orig_category":"Herstelling leer and schoeisel",
    "sg:phone":"+32 83 61 17 43",
    "sg:postcode":"5360",
    "sg:province":"Namur",
    "wof:name":"Albert Hastir",
    "wof:placetype":"venue"
},
  "geometry": {"coordinates":[5.1862359047,50.3473243713],"type":"Point"}
}