{
  "type": "Feature",
  "properties": {
    "iso:country":"BE",
    "sg:address":"Swaenebeecklaan 8",
    "sg:city":"Schilde ('s Gravenwezel)",
    "sg:classifiers":[
        {
            "category":"Banks & Credit Unions",
            "subcategory":"Investment Brokerage",
            "type":"Services"
        }
    ],
    "sg:phone":"+32 3 383 66 16",
    "sg:postcode":"2970",
    "sg:province":"Antwerpen",
    "sg:tags":[
        "auditor"
    ],
    "wof:name":"Van Rie & Co, Bedrijfsrevisoren Bvba",
    "wof:placetype":"venue"
},
  "geometry": {"coordinates":[4.5787568092,51.2596969604],"type":"Point"}
}