{
  "type": "Feature",
  "properties": {
    "iso:country":"BE",
    "sg:address":"Wolfshaegen 184",
    "sg:city":"Huldenberg",
    "sg:orig_category":"Dierenartsen",
    "sg:phone":"+32 16 47 39 02",
    "sg:postcode":"3040",
    "sg:province":"Vlaams-Brabant",
    "wof:name":"Geert Vanden Bossche",
    "wof:placetype":"venue"
},
  "geometry": {"coordinates":[4.628868103,50.8064460754],"type":"Point"}
}