{
  "type": "Feature",
  "properties": {
    "addr:full":"Rooststraat 20 Meise Vlaams-Brabant 1860",
    "addr:housenumber":"20",
    "addr:postcode":"1860",
    "addr:street":"Rooststraat",
    "iso:country":"BE",
    "sg:address":"Rooststraat 20",
    "sg:city":"Meise",
    "sg:orig_category":"G\u00e9om\u00e8tres. Evaluation and estimation de biens immobiliers",
    "sg:phone":"+32 2 270 05 85",
    "sg:postcode":"1860",
    "sg:province":"Vlaams-Brabant",
    "wof:name":"Dries Vanderick",
    "wof:placetype":"venue"
},
  "geometry": {"coordinates":[4.3431339264,50.9322280884],"type":"Point"}
}