{
  "type": "Feature",
  "properties": {
    "iso:country":"BE",
    "sg:address":"Alfons Vandenboschstraat 1a",
    "sg:city":"Sint-pieters-leeuw",
    "sg:orig_category":"R\u00e9parations d'appareils \u00e9lectrom\u00e9nagers. Electrom\u00e9nager, t\u00e9l\u00e9visions and radios",
    "sg:phone":"+32 2 377 68 08",
    "sg:postcode":"1601",
    "sg:province":"Vlaams-Brabant",
    "wof:name":"Jean Christiaens",
    "wof:placetype":"venue"
},
  "geometry": {"coordinates":[4.2954101562,50.7857131958],"type":"Point"}
}