{
  "type": "Feature",
  "properties": {
    "iso:country":"BE",
    "sg:address":"Jonkh.p. Coppietersdreef 47",
    "sg:city":"Brugge",
    "sg:orig_category":"Koerierbedrijven Taxi's",
    "sg:phone":"+32 50 39 11 55",
    "sg:postcode":"8200",
    "sg:province":"West-Vlaanderen",
    "wof:name":"Taxi Abby Albert Autolux",
    "wof:placetype":"venue"
},
  "geometry": {"coordinates":[3.1969499588,51.1950492859],"type":"Point"}
}