{
  "type": "Feature",
  "properties": {
    "addr:full":"Kazernestraat 80b8 Brussel/bruxelles Bruxelles-Capitale 1000",
    "addr:housenumber":"80b8",
    "addr:postcode":"1000",
    "addr:street":"Kazernestraat;/",
    "iso:country":"BE",
    "sg:address":"Kazernestraat 80b8",
    "sg:city":"Brussel/bruxelles",
    "sg:orig_category":"Opinieonderzoekbureaus",
    "sg:phone":"+32 2 501 27 11",
    "sg:postcode":"1000",
    "sg:province":"Bruxelles-Capitale",
    "wof:name":"K.i. T\u00c9l\u00c9services",
    "wof:placetype":"venue"
},
  "geometry": {"coordinates":[4.3417711258,50.8417015076],"type":"Point"}
}