{
  "type": "Feature",
  "properties": {
    "iso:country":"BE",
    "sg:address":"Rue Joseph Dufrane 6",
    "sg:city":"Frameries",
    "sg:classifiers":[
        {
            "category":"Government",
            "subcategory":"Fire Station",
            "type":"Public Place"
        }
    ],
    "sg:phone":"+32 65 51 08 56",
    "sg:postcode":"7080",
    "sg:province":"Hainaut",
    "sg:tags":[
        "detection",
        "installation",
        "material",
        "-"
    ],
    "wof:name":"Prodelec",
    "wof:placetype":"venue"
},
  "geometry": {"coordinates":[3.892813921,50.4073181152],"type":"Point"}
}