{
  "type": "Feature",
  "properties": {
    "iso:country":"BE",
    "sg:address":"Rue Thier May 20",
    "sg:city":"Theux",
    "sg:classifiers":[
        {
            "category":"Real Estate",
            "subcategory":"Architect",
            "type":"Services"
        }
    ],
    "sg:phone":"+32 87 54 23 40",
    "sg:postcode":"4910",
    "sg:province":"Li\u00e8ge",
    "wof:name":"Sante Y",
    "wof:placetype":"venue"
},
  "geometry": {"coordinates":[5.8210139275,50.545173645],"type":"Point"}
}