{
  "type": "Feature",
  "properties": {
    "iso:country":"BE",
    "sg:address":"Edingsesteenweg 119",
    "sg:city":"Gooik",
    "sg:orig_category":"Brood, gebak and snoepgoed",
    "sg:phone":"+32 2 532 15 67",
    "sg:postcode":"1755",
    "sg:province":"Vlaams-Brabant",
    "wof:name":"Mada",
    "wof:placetype":"venue"
},
  "geometry": {"coordinates":[4.1263189316,50.7952651978],"type":"Point"}
}