{
  "type": "Feature",
  "properties": {
    "addr:full":"Kerkhofstraat 7 Buggenhout Oost-Vlaanderen 9255",
    "addr:housenumber":"7",
    "addr:postcode":"9255",
    "addr:street":"Kerkhofstraat",
    "iso:country":"BE",
    "sg:address":"Kerkhofstraat 7",
    "sg:city":"Buggenhout",
    "sg:orig_category":"Effectenmakelaars and vermogensbeheer Verzekeringsmakelaars and experts",
    "sg:phone":"+32 52 33 29 97",
    "sg:postcode":"9255",
    "sg:province":"Oost-Vlaanderen",
    "wof:name":"J. De Ridder En Co",
    "wof:placetype":"venue"
},
  "geometry": {"coordinates":[4.1957101822,51.0167808533],"type":"Point"}
}