{
  "type": "Feature",
  "properties": {
    "addr:full":"Michel Van Hammestraat 120 Brugge West-Vlaanderen 8310",
    "addr:housenumber":"120",
    "addr:postcode":"8310",
    "addr:street":"Michel Van Hammestraat",
    "iso:country":"BE",
    "sg:address":"Michel Van Hammestraat 120",
    "sg:city":"Brugge",
    "sg:orig_category":"Fleurs and plantes",
    "sg:phone":"+32 50 35 58 07",
    "sg:postcode":"8310",
    "sg:province":"West-Vlaanderen",
    "wof:name":"Fa. Brem",
    "wof:placetype":"venue"
},
  "geometry": {"coordinates":[3.2796599865,51.2128486633],"type":"Point"}
}