{
  "type": "Feature",
  "properties": {
    "addr:full":"Heidries 10 Hoogstraten Antwerpen 2320",
    "addr:housenumber":"10",
    "addr:postcode":"2320",
    "addr:street":"Heidries",
    "iso:country":"BE",
    "sg:address":"Heidries 10",
    "sg:city":"Hoogstraten",
    "sg:orig_category":"Mat\u00e9riaux de construction Gr",
    "sg:phone":"+32 3 340 20 60",
    "sg:postcode":"2320",
    "sg:province":"Antwerpen",
    "wof:name":"V.g.m.",
    "wof:placetype":"venue"
},
  "geometry": {"coordinates":[4.7663397789,51.3921852112],"type":"Point"}
}