{
  "type": "Feature",
  "properties": {
    "addr:full":"Sprietwegestraat 35 Brugge (sint-kruis) West-Vlaanderen 8310",
    "addr:housenumber":"35",
    "addr:postcode":"8310",
    "addr:street":"Sprietwegestraat",
    "iso:country":"BE",
    "sg:address":"Sprietwegestraat 35",
    "sg:city":"Brugge (sint-kruis)",
    "sg:classifiers":[
        {
            "category":"Health Services",
            "subcategory":"Health Practitioner",
            "type":"Services"
        }
    ],
    "sg:phone":"+32 50 37 42 27",
    "sg:postcode":"8310",
    "sg:province":"West-Vlaanderen",
    "sg:tags":[
        "alternative",
        "therapy",
        "treatment"
    ],
    "wof:name":"Larbouillat C",
    "wof:placetype":"venue"
},
  "geometry": {"coordinates":[3.2635629177,51.2058181763],"type":"Point"}
}