{
  "type": "Feature",
  "properties": {
    "addr:full":"Rue De France 24 Rochefort Namur 5580",
    "addr:housenumber":"24",
    "addr:postcode":"5580",
    "addr:street":"Rue De France",
    "iso:country":"BE",
    "sg:address":"Rue De France 24",
    "sg:city":"Rochefort",
    "sg:orig_category":"Plaatsen van vloer- and muurbekleding Woningbouw",
    "sg:phone":"+32 84 21 40 60",
    "sg:postcode":"5580",
    "sg:province":"Namur",
    "wof:name":"Ideal Home",
    "wof:placetype":"venue"
},
  "geometry": {"coordinates":[5.2217869759,50.1572265625],"type":"Point"}
}