{
  "type": "Feature",
  "properties": {
    "addr:full":"Leiestraat 3 Kortrijk West-Vlaanderen 8500",
    "addr:housenumber":"3",
    "addr:postcode":"8500",
    "addr:street":"Leiestraat",
    "iso:country":"BE",
    "sg:address":"Leiestraat 3",
    "sg:city":"Kortrijk",
    "sg:classifiers":[
        {
            "category":"Health Services",
            "subcategory":"Doctor",
            "type":"Services"
        }
    ],
    "sg:phone":"+32 56 22 15 11",
    "sg:postcode":"8500",
    "sg:province":"West-Vlaanderen",
    "sg:tags":[
        "orthopedist"
    ],
    "wof:name":"Medicura Nv",
    "wof:placetype":"venue"
},
  "geometry": {"coordinates":[3.2649760246,50.8281059265],"type":"Point"}
}