{
  "type": "Feature",
  "properties": {
    "addr:full":"Ertbrandstraat 235 Kapellen Antwerpen 2950",
    "addr:housenumber":"235",
    "addr:postcode":"2950",
    "addr:street":"Ertbrandstraat",
    "iso:country":"BE",
    "sg:address":"Ertbrandstraat 235",
    "sg:city":"Kapellen",
    "sg:classifiers":[
        {
            "category":"Fast Food",
            "type":"Food & Drink"
        }
    ],
    "sg:phone":"+32 3 664 47 07",
    "sg:postcode":"2950",
    "sg:province":"Antwerpen",
    "sg:tags":[
        "meeneem",
        "restaurant"
    ],
    "wof:name":"Pou Chan",
    "wof:placetype":"venue"
},
  "geometry": {"coordinates":[4.3995399475,51.3481712341],"type":"Point"}
}