{
  "type": "Feature",
  "properties": {
    "iso:country":"BE",
    "sg:address":"Leenbosstraat 45",
    "sg:city":"Hooglede",
    "sg:orig_category":"Producteurs de l\u00e9gumes. Eleveurs and marchands de porcs",
    "sg:phone":"+32 51 72 36 79",
    "sg:postcode":"8830",
    "sg:province":"West-Vlaanderen",
    "wof:name":"Carlos Ghekiere",
    "wof:placetype":"venue"
},
  "geometry": {"coordinates":[3.0711650848,51.0088691711],"type":"Point"}
}