{
  "type": "Feature",
  "properties": {
    "iso:country":"BE",
    "sg:address":"Willem De Blockstraat 1",
    "sg:city":"Bornem",
    "sg:orig_category":"Krantenwinkels Rookartikelen",
    "sg:phone":"+32 3 889 19 24",
    "sg:postcode":"2880",
    "sg:province":"Antwerpen",
    "wof:name":"Chris-boek-tiek",
    "wof:placetype":"venue"
},
  "geometry": {"coordinates":[4.2986807823,51.1065063477],"type":"Point"}
}