{
  "type": "Feature",
  "properties": {
    "addr:full":"Molenstraat 54 Boom Antwerpen 2850",
    "addr:housenumber":"54",
    "addr:postcode":"2850",
    "addr:street":"Molenstraat",
    "iso:country":"BE",
    "sg:address":"Molenstraat 54",
    "sg:city":"Boom",
    "sg:classifiers":[
        {
            "category":"Bars & Pubs",
            "type":"Food & Drink"
        }
    ],
    "sg:phone":"+32 3 844 66 94",
    "sg:postcode":"2850",
    "sg:province":"Antwerpen",
    "wof:name":"Zandplein",
    "wof:placetype":"venue"
},
  "geometry": {"coordinates":[4.3699231148,51.0909156799],"type":"Point"}
}