{
  "type": "Feature",
  "properties": {
    "iso:country":"BE",
    "sg:address":"Rue De L'industrie 12",
    "sg:city":"Charleroi",
    "sg:classifiers":[
        {
            "category":"Food & Beverages",
            "subcategory":"Fruits & Vegetables",
            "type":"Retail Goods"
        }
    ],
    "sg:phone":"+32 71 25 68 11",
    "sg:postcode":"6040",
    "sg:province":"Hainaut",
    "sg:tags":[
        "l\u00e9gumes",
        "gr"
    ],
    "wof:name":"Vercruyssen",
    "wof:placetype":"venue"
},
  "geometry": {"coordinates":[4.4688310623,50.4434585571],"type":"Point"}
}