{
  "type": "Feature",
  "properties": {
    "iso:country":"BE",
    "sg:address":"Grand Rue 51a",
    "sg:city":"Sivry-rance (rance)",
    "sg:classifiers":[
        {
            "category":"Education",
            "subcategory":"School",
            "type":"Public Place"
        }
    ],
    "sg:phone":"+32 60 41 23 57",
    "sg:postcode":"6470",
    "sg:province":"Hainaut",
    "sg:tags":[
        "secondary"
    ],
    "wof:name":"Acad\u00e9mie De La Botte Du Hainaut",
    "wof:placetype":"venue"
},
  "geometry": {"coordinates":[4.2734780312,50.142665863],"type":"Point"}
}