{
  "type": "Feature",
  "properties": {
    "addr:full":"Cardijnlaan 20 Grobbendonk Antwerpen 2288",
    "addr:housenumber":"20",
    "addr:postcode":"2288",
    "addr:street":"Cardijnlaan",
    "iso:country":"BE",
    "sg:address":"Cardijnlaan 20",
    "sg:city":"Grobbendonk",
    "sg:classifiers":[
        {
            "category":"Cafe",
            "type":"Food & Drink"
        }
    ],
    "sg:phone":"+32 14 51 30 41",
    "sg:postcode":"2288",
    "sg:province":"Antwerpen",
    "sg:tags":[
        "caf\u00e9s"
    ],
    "wof:name":"Carl Cloos",
    "wof:placetype":"venue"
},
  "geometry": {"coordinates":[4.7400779724,51.1694984436],"type":"Point"}
}