{
  "type": "Feature",
  "properties": {
    "addr:full":"Meerdorp 1 Hoogstraten Antwerpen 2321",
    "addr:housenumber":"1",
    "addr:postcode":"2321",
    "addr:street":"Meerdorp",
    "iso:country":"BE",
    "sg:address":"Meerdorp 1",
    "sg:city":"Hoogstraten",
    "sg:orig_category":"Journaux. Fournitures de bureau. Tabac",
    "sg:phone":"+32 3 315 82 56",
    "sg:postcode":"2321",
    "sg:province":"Antwerpen",
    "wof:name":"Mick Shop",
    "wof:placetype":"venue"
},
  "geometry": {"coordinates":[4.7366099358,51.442325592],"type":"Point"}
}