{
  "type": "Feature",
  "properties": {
    "addr:full":"Rue Saint-jacques 45 Li\u00c8ge Li\u00e8ge 4031",
    "addr:housenumber":"45",
    "addr:postcode":"4031",
    "addr:street":"Rue Saint-Jacques",
    "iso:country":"BE",
    "sg:address":"Rue Saint-jacques 45",
    "sg:city":"Li\u00c8ge",
    "sg:orig_category":"Quincailleries. Equipement divers pour commerces Air conditionn\u00e9 and ventilation",
    "sg:phone":"+32 4 367 69 43",
    "sg:postcode":"4031",
    "sg:province":"Li\u00e8ge",
    "wof:name":"R.s.p.",
    "wof:placetype":"venue"
},
  "geometry": {"coordinates":[5.6063799858,50.6113777161],"type":"Point"}
}