{
  "type": "Feature",
  "properties": {
    "addr:full":"Grand'place 23 Lessines Hainaut 7860",
    "addr:housenumber":"23",
    "addr:postcode":"7860",
    "addr:street":"Grand'Place;Hainaut",
    "iso:country":"BE",
    "sg:address":"Grand'place 23",
    "sg:city":"Lessines",
    "sg:classifiers":[
        {
            "category":"Communications",
            "subcategory":"Radio Station",
            "type":"Services"
        }
    ],
    "sg:phone":"+32 68 33 21 85",
    "sg:postcode":"7860",
    "sg:province":"Hainaut",
    "sg:tags":[
        "local"
    ],
    "wof:name":"Nostalgie Lessines",
    "wof:placetype":"venue"
},
  "geometry": {"coordinates":[3.8290889263,50.7124633789],"type":"Point"}
}