{
  "type": "Feature",
  "properties": {
    "addr:full":"Excelsiorlaan 40-42 Zaventem Vlaams-Brabant 1930",
    "addr:housenumber":"40-42",
    "addr:postcode":"1930",
    "addr:street":"Excelsiorlaan",
    "iso:country":"BE",
    "sg:address":"Excelsiorlaan 40-42",
    "sg:city":"Zaventem",
    "sg:classifiers":[
        {
            "category":"Manufacturing",
            "subcategory":"Chemicals & Compounds",
            "type":"Manufacturing & Wholesale Goods"
        }
    ],
    "sg:phone":"+32 2 712 02 30",
    "sg:postcode":"1930",
    "sg:province":"Vlaams-Brabant",
    "sg:tags":[
        "pharmaceutical",
        "product"
    ],
    "wof:name":"Leo Pharma Nv-sa",
    "wof:placetype":"venue"
},
  "geometry": {"coordinates":[4.456592083,50.8830528259],"type":"Point"}
}