{
  "type": "Feature",
  "properties": {
    "addr:full":"Steenweg Op Aalst 113 Opwijk Vlaams-Brabant 1745",
    "addr:housenumber":"113",
    "addr:postcode":"1745",
    "addr:street":"Steenweg Op Aalst",
    "iso:country":"BE",
    "sg:address":"Steenweg Op Aalst 113",
    "sg:city":"Opwijk",
    "sg:orig_category":"Producteurs de fruits",
    "sg:phone":"+32 52 35 48 24",
    "sg:postcode":"1745",
    "sg:province":"Vlaams-Brabant",
    "wof:name":"Frans Ringoot",
    "wof:placetype":"venue"
},
  "geometry": {"coordinates":[4.1548237801,50.9608840942],"type":"Point"}
}