{
  "type": "Feature",
  "properties": {
    "addr:full":"Markt 2 Gistel West-Vlaanderen 8470",
    "addr:housenumber":"2",
    "addr:postcode":"8470",
    "addr:street":"Markt",
    "iso:country":"BE",
    "sg:address":"Markt 2",
    "sg:city":"Gistel",
    "sg:classifiers":[
        {
            "category":"Cinema",
            "subcategory":"Movie Rental",
            "type":"Entertainment"
        }
    ],
    "sg:phone":"+32 59 27 48 58",
    "sg:postcode":"8470",
    "sg:province":"West-Vlaanderen",
    "sg:tags":[
        "de",
        "cassette",
        "location",
        "vid\u00e9o",
        "audio"
    ],
    "wof:name":"Videoscoop",
    "wof:placetype":"venue"
},
  "geometry": {"coordinates":[2.96707201,51.15650177],"type":"Point"}
}