{
  "type": "Feature",
  "properties": {
    "iso:country":"BE",
    "sg:address":"Chauss\u00c9e De La Hulpe 169",
    "sg:city":"Watermaal-bosvoorde/watermael-boitsfort",
    "sg:orig_category":"Cliniques and h\u00f4pitaux",
    "sg:phone":"+32 2 663 12 11",
    "sg:postcode":"1170",
    "sg:province":"Bruxelles-Capitale",
    "wof:name":"Stichting Ter Kameren",
    "wof:placetype":"venue"
},
  "geometry": {"coordinates":[4.4012179375,50.7960929871],"type":"Point"}
}