{
  "type": "Feature",
  "properties": {
    "iso:country":"BE",
    "sg:address":"Zuidhoekstraat 22",
    "sg:city":"Ledegem",
    "sg:classifiers":[
        {
            "category":"Personal",
            "subcategory":"Beauty Salon",
            "type":"Services"
        }
    ],
    "sg:phone":"+32 56 41 27 62",
    "sg:postcode":"8880",
    "sg:province":"West-Vlaanderen",
    "sg:tags":[
        "de",
        "coiffure"
    ],
    "wof:name":"Carine Vandemoortele",
    "wof:placetype":"venue"
},
  "geometry": {"coordinates":[3.1927371025,50.8609542847],"type":"Point"}
}