{
  "type": "Feature",
  "properties": {
    "addr:full":"Sluisstr 2 Ham Limburg 3945",
    "addr:housenumber":"2",
    "addr:postcode":"3945",
    "addr:street":"Sluisstr",
    "iso:country":"BE",
    "sg:address":"Sluisstr 2",
    "sg:city":"Ham",
    "sg:classifiers":[
        {
            "category":"Professional",
            "type":"Services"
        }
    ],
    "sg:phone":"+32 13 66 29 08",
    "sg:postcode":"3945",
    "sg:province":"Limburg",
    "sg:tags":[
        "transport",
        "road"
    ],
    "wof:name":"Antrago Transport & Distributie Nv",
    "wof:placetype":"venue"
},
  "geometry": {"coordinates":[5.1776199341,51.1046104431],"type":"Point"}
}