{
  "type": "Feature",
  "properties": {
    "iso:country":"BE",
    "sg:address":"Rue De Brabant 194",
    "sg:city":"Bruxelles (schaerbeek)",
    "sg:classifiers":[
        {
            "category":"Retail",
            "subcategory":"Self-service Laundry",
            "type":"Services"
        }
    ],
    "sg:phone":"+32 2 217 88 39",
    "sg:postcode":"1030",
    "sg:province":"Bruxelles-Capitale",
    "sg:tags":[
        "-",
        "outfit",
        "communion",
        "wear",
        "bridal",
        "rental",
        "formal"
    ],
    "wof:name":"Amira",
    "wof:placetype":"venue"
},
  "geometry": {"coordinates":[4.3645172119,50.8614311218],"type":"Point"}
}