{
  "type": "Feature",
  "properties": {
    "addr:full":"Madritten 8 Arendonk Antwerpen 2370",
    "addr:housenumber":"8",
    "addr:postcode":"2370",
    "addr:street":"Madritten",
    "iso:country":"BE",
    "sg:address":"Madritten 8",
    "sg:city":"Arendonk",
    "sg:classifiers":[
        {
            "category":"Wholesale",
            "subcategory":"Plants",
            "type":"Manufacturing & Wholesale Goods"
        }
    ],
    "sg:phone":"+32 14 67 84 69",
    "sg:postcode":"2370",
    "sg:province":"Antwerpen",
    "sg:tags":[
        "whol",
        "flower",
        "-",
        "grower"
    ],
    "wof:name":"Van Deuren G",
    "wof:placetype":"venue"
},
  "geometry": {"coordinates":[5.0862288475,51.3274726868],"type":"Point"}
}