{
  "type": "Feature",
  "properties": {
    "addr:full":"Hoepertingenstraat 22 Borgloon (hoepertingen) Limburg 3840",
    "addr:housenumber":"22",
    "addr:postcode":"3840",
    "addr:street":"Hoepertingenstraat",
    "iso:country":"BE",
    "sg:address":"Hoepertingenstraat 22",
    "sg:city":"Borgloon (hoepertingen)",
    "sg:classifiers":[
        {
            "category":"Professional",
            "subcategory":"Accounting & Tax Preparation",
            "type":"Services"
        }
    ],
    "sg:phone":"+32 495 51 33 85",
    "sg:postcode":"3840",
    "sg:province":"Limburg",
    "sg:tags":[
        "accountant"
    ],
    "wof:name":"Albert H",
    "wof:placetype":"venue"
},
  "geometry": {"coordinates":[5.3441700935,50.8012466431],"type":"Point"}
}