{
  "type": "Feature",
  "properties": {
    "addr:full":"Spinnerijkaai 67 Kortrijk West-Vlaanderen 8500",
    "addr:housenumber":"67",
    "addr:postcode":"8500",
    "addr:street":"Spinnerijkaai",
    "iso:country":"BE",
    "sg:address":"Spinnerijkaai 67",
    "sg:city":"Kortrijk",
    "sg:classifiers":[
        {
            "category":"Manufacturing",
            "subcategory":"Building Materials",
            "type":"Manufacturing & Wholesale Goods"
        }
    ],
    "sg:phone":"+32 56 21 24 73",
    "sg:postcode":"8500",
    "sg:province":"West-Vlaanderen",
    "sg:tags":[
        "fixture",
        "store"
    ],
    "wof:name":"Sintoplan Bvba",
    "wof:placetype":"venue"
},
  "geometry": {"coordinates":[3.2849171162,50.8315048218],"type":"Point"}
}