{
  "type": "Feature",
  "properties": {
    "addr:full":"Milostraat 56 Mol Antwerpen 2400",
    "addr:housenumber":"56",
    "addr:postcode":"2400",
    "addr:street":"Milostraat",
    "iso:country":"BE",
    "sg:address":"Milostraat 56",
    "sg:city":"Mol",
    "sg:orig_category":"Paramedische behandelingen",
    "sg:phone":"+32 14 32 28 82",
    "sg:postcode":"2400",
    "sg:province":"Antwerpen",
    "wof:name":"K. Paepen",
    "wof:placetype":"venue"
},
  "geometry": {"coordinates":[5.0727748871,51.1907615662],"type":"Point"}
}