{
  "type": "Feature",
  "properties": {
    "iso:country":"BE",
    "sg:address":"Rue Des Sandrinettes 4",
    "sg:city":"Mons",
    "sg:orig_category":"Landmeters and schatters",
    "sg:phone":"+32 65 33 91 27",
    "sg:postcode":"7033",
    "sg:province":"Hainaut",
    "wof:name":"Expertises Immobili\u00c8res A. Vansthertem",
    "wof:placetype":"venue"
},
  "geometry": {"coordinates":[3.9253261089,50.4366378784],"type":"Point"}
}