{
  "type": "Feature",
  "properties": {
    "addr:full":"Weg Op Bree 144 Meeuwen-gruitrode Limburg 3670",
    "addr:housenumber":"144",
    "addr:postcode":"3670",
    "addr:street":"Weg Op Bree",
    "iso:country":"BE",
    "sg:address":"Weg Op Bree 144",
    "sg:city":"Meeuwen-gruitrode",
    "sg:classifiers":[
        {
            "category":"Cafe",
            "type":"Food & Drink"
        }
    ],
    "sg:phone":"+32 89 46 52 57",
    "sg:postcode":"3670",
    "sg:province":"Limburg",
    "sg:tags":[
        "caf\u00e9s"
    ],
    "wof:name":"Theo Hendrix",
    "wof:placetype":"venue"
},
  "geometry": {"coordinates":[5.5519728661,51.1100959778],"type":"Point"}
}