{
  "type": "Feature",
  "properties": {
    "addr:full":"Pasmolenstraat 25 Mechelen Antwerpen 2800",
    "addr:housenumber":"25",
    "addr:postcode":"2800",
    "addr:street":"Pasmolenstraat",
    "iso:country":"BE",
    "sg:address":"Pasmolenstraat 25",
    "sg:city":"Mechelen",
    "sg:classifiers":[
        {
            "category":"Professional",
            "type":"Services"
        }
    ],
    "sg:phone":"+32 15 55 52 38",
    "sg:postcode":"2800",
    "sg:province":"Antwerpen",
    "sg:tags":[
        "surveyor",
        "-",
        "valuer"
    ],
    "wof:name":"Kavee Engineering",
    "wof:placetype":"venue"
},
  "geometry": {"coordinates":[4.4925398827,51.0349693298],"type":"Point"}
}