{
  "type": "Feature",
  "properties": {
    "iso:country":"BE",
    "sg:address":"Avenue Roi Baudouin 23",
    "sg:city":"Welkenraedt",
    "sg:classifiers":[
        {
            "category":"Building & Trades",
            "subcategory":"Electrical",
            "type":"Services"
        }
    ],
    "sg:phone":"+32 87 65 66 62",
    "sg:postcode":"4840",
    "sg:province":"Li\u00e8ge",
    "sg:tags":[
        "electric",
        "-",
        "housewiring",
        "contractor"
    ],
    "wof:name":"Nyssen A",
    "wof:placetype":"venue"
},
  "geometry": {"coordinates":[5.9654102325,50.6618385315],"type":"Point"}
}