{
  "type": "Feature",
  "properties": {
    "iso:country":"BE",
    "sg:address":"Tervatestraat 64",
    "sg:city":"Etterbeek",
    "sg:orig_category":"Fotografen and fotostudio's",
    "sg:phone":"+32 2 733 84 71",
    "sg:postcode":"1040",
    "sg:province":"Bruxelles-Capitale",
    "wof:name":"Marteaux S.",
    "wof:placetype":"venue"
},
  "geometry": {"coordinates":[4.4011278152,50.8300743103],"type":"Point"}
}