{
  "type": "Feature",
  "properties": {
    "iso:country":"BE",
    "sg:address":"Hundelgemsesteenweg 512",
    "sg:city":"Merelbeke",
    "sg:orig_category":"Herstelling leer and schoeisel",
    "sg:phone":"+32 9 231 74 02",
    "sg:postcode":"9820",
    "sg:province":"Oost-Vlaanderen",
    "wof:name":"Eli Eeman",
    "wof:placetype":"venue"
},
  "geometry": {"coordinates":[3.7505960464,51.0004425049],"type":"Point"}
}