{
  "type": "Feature",
  "properties": {
    "addr:full":"Bld De Smet De Naeyer 542 Brussel/bruxelles Bruxelles-Capitale 1020",
    "addr:housenumber":"542",
    "addr:postcode":"1020",
    "addr:street":"Bld De Smet De Naeyer;/",
    "iso:country":"BE",
    "sg:address":"Bld De Smet De Naeyer 542",
    "sg:city":"Brussel/bruxelles",
    "sg:orig_category":"Mat\u00e9riel m\u00e9dical and orthop\u00e9dique and proth\u00e8ses Fab",
    "sg:phone":"+32 2 478 46 58",
    "sg:postcode":"1020",
    "sg:province":"Bruxelles-Capitale",
    "wof:name":"Johannes Paschold",
    "wof:placetype":"venue"
},
  "geometry": {"coordinates":[4.3462300301,50.8855514526],"type":"Point"}
}