{
  "type": "Feature",
  "properties": {
    "addr:full":"Kwaenijkstraat 10 Boortmeerbeek Vlaams-Brabant 3191",
    "addr:housenumber":"10",
    "addr:postcode":"3191",
    "addr:street":"Kwaenijkstraat",
    "iso:country":"BE",
    "sg:address":"Kwaenijkstraat 10",
    "sg:city":"Boortmeerbeek",
    "sg:orig_category":"Banken and kredietinstellingen",
    "sg:phone":"+32 15 51 25 63",
    "sg:postcode":"3191",
    "sg:province":"Vlaams-Brabant",
    "wof:name":"Citibank",
    "wof:placetype":"venue"
},
  "geometry": {"coordinates":[4.537112236,50.9942016602],"type":"Point"}
}