{
  "type": "Feature",
  "properties": {
    "addr:full":"Kattestraat 51bb Heist-op-den-berg Antwerpen 2220",
    "addr:housenumber":"51bb",
    "addr:postcode":"2220",
    "addr:street":"Kattestraat",
    "iso:country":"BE",
    "sg:address":"Kattestraat 51bb",
    "sg:city":"Heist-op-den-berg",
    "sg:orig_category":"Boucheries",
    "sg:phone":"+32 15 24 16 01",
    "sg:postcode":"2220",
    "sg:province":"Antwerpen",
    "wof:name":"J. Cannaerts",
    "wof:placetype":"venue"
},
  "geometry": {"coordinates":[4.7174210548,51.0746994019],"type":"Point"}
}