{
  "type": "Feature",
  "properties": {
    "iso:country":"BE",
    "sg:address":"Waversebaan 240",
    "sg:city":"Oud-heverlee",
    "sg:classifiers":[
        {
            "category":"Professional",
            "subcategory":"Management & Consulting",
            "type":"Services"
        }
    ],
    "sg:phone":"+32 16 47 41 58",
    "sg:postcode":"3050",
    "sg:province":"Vlaams-Brabant",
    "sg:tags":[
        "tax-consultants"
    ],
    "wof:name":"Boon J",
    "wof:placetype":"venue"
},
  "geometry": {"coordinates":[4.6539850235,50.8260421753],"type":"Point"}
}