{
  "type": "Feature",
  "properties": {
    "addr:full":"Rue Du G\u00c9n\u00c9ral De Gaulle 4bb Courcelles Hainaut 6180",
    "addr:housenumber":"4bb",
    "addr:postcode":"6180",
    "addr:street":"Rue Du Ge\u0301Ne\u0301Ral De Gaulle",
    "iso:country":"BE",
    "sg:address":"Rue Du G\u00c9n\u00c9ral De Gaulle 4bb",
    "sg:city":"Courcelles",
    "sg:orig_category":"Cr\u00e9meries",
    "sg:phone":"+32 71 45 61 37",
    "sg:postcode":"6180",
    "sg:province":"Hainaut",
    "wof:name":"Le Fromager",
    "wof:placetype":"venue"
},
  "geometry": {"coordinates":[4.3800258636,50.4591026306],"type":"Point"}
}