{
  "type": "Feature",
  "properties": {
    "iso:country":"BE",
    "sg:address":"Oppemstraat 4",
    "sg:city":"Meise",
    "sg:orig_category":"M\u00e9decins and sp\u00e9cialistes",
    "sg:phone":"+32 2 270 05 11",
    "sg:postcode":"1861",
    "sg:province":"Vlaams-Brabant",
    "wof:name":"Fanny Huygens",
    "wof:placetype":"venue"
},
  "geometry": {"coordinates":[4.3088531494,50.9501228333],"type":"Point"}
}