{
  "type": "Feature",
  "properties": {
    "iso:country":"BE",
    "sg:address":"Ringlaan Noord 33",
    "sg:city":"De Haan",
    "sg:orig_category":"Pensions de famille",
    "sg:phone":"+32 59 23 52 67",
    "sg:postcode":"8420",
    "sg:province":"West-Vlaanderen",
    "wof:name":"Coenye Roland",
    "wof:placetype":"venue"
},
  "geometry": {"coordinates":[3.0252659321,51.2670440674],"type":"Point"}
}