{
  "type": "Feature",
  "properties": {
    "addr:full":"Wilgenstraat 111 Roeselare West-Vlaanderen 8800",
    "addr:housenumber":"111",
    "addr:postcode":"8800",
    "addr:street":"Wilgenstraat",
    "iso:country":"BE",
    "sg:address":"Wilgenstraat 111",
    "sg:city":"Roeselare",
    "sg:orig_category":"Producteurs de l\u00e9gumes",
    "sg:phone":"+32 51 20 27 34",
    "sg:postcode":"8800",
    "sg:province":"West-Vlaanderen",
    "wof:name":"Geert Vanderschaeghe",
    "wof:placetype":"venue"
},
  "geometry": {"coordinates":[3.1167271137,50.9374427795],"type":"Point"}
}