{
  "type": "Feature",
  "properties": {
    "addr:full":"Sint-jacobsstraat 45 Ieper West-Vlaanderen 8900",
    "addr:housenumber":"45",
    "addr:postcode":"8900",
    "addr:street":"Sint-Jacobsstraat",
    "iso:country":"BE",
    "sg:address":"Sint-jacobsstraat 45",
    "sg:city":"Ieper",
    "sg:orig_category":"Reclamebureaus",
    "sg:phone":"+32 57 21 68 48",
    "sg:postcode":"8900",
    "sg:province":"West-Vlaanderen",
    "wof:name":"Alpha & Omega",
    "wof:placetype":"venue"
},
  "geometry": {"coordinates":[2.8895881176,50.8498687744],"type":"Point"}
}