{
  "type": "Feature",
  "properties": {
    "addr:full":"Crokaertlaan 72 Sint-pieters-woluwe/woluwe-saint-pierre Bruxelles-Capitale 1150",
    "addr:housenumber":"72",
    "addr:postcode":"1150",
    "addr:street":"Crokaertlaan;/",
    "iso:country":"BE",
    "sg:address":"Crokaertlaan 72",
    "sg:city":"Sint-pieters-woluwe/woluwe-saint-pierre",
    "sg:orig_category":"Kapsalons",
    "sg:phone":"+32 2 771 45 28",
    "sg:postcode":"1150",
    "sg:province":"Bruxelles-Capitale",
    "wof:name":"Id\u00c9al (l')",
    "wof:placetype":"venue"
},
  "geometry": {"coordinates":[4.4602360725,50.8263969421],"type":"Point"}
}