{
  "type": "Feature",
  "properties": {
    "iso:country":"BE",
    "sg:address":"Rue Cornet De Grez 8",
    "sg:city":"Sint-joost-ten-node/saint-josse-ten-noode",
    "sg:orig_category":"Salles de spectacles",
    "sg:phone":"+32 2 218 43 55",
    "sg:postcode":"1210",
    "sg:province":"Bruxelles-Capitale",
    "wof:name":"Th\u00c9\u00c2tre D\u00c9p\u00d4t L\u00c9gal",
    "wof:placetype":"venue"
},
  "geometry": {"coordinates":[4.3684630394,50.8572654724],"type":"Point"}
}