{
  "type": "Feature",
  "properties": {
    "iso:country":"BE",
    "sg:address":"Rue Des Palmiers 45",
    "sg:city":"Bruxelles-woluwe-saint-pierre",
    "sg:orig_category":"Catering and organisatie van feesten",
    "sg:phone":"+32 2 734 86 45",
    "sg:postcode":"1150",
    "sg:province":"Bruxelles-Capitale",
    "wof:name":"Saveurs Et D\u00c9licatesses",
    "wof:placetype":"venue"
},
  "geometry": {"coordinates":[4.4073319435,50.826713562],"type":"Point"}
}