{
  "type": "Feature",
  "properties": {
    "addr:full":"Rue Des Crayats 17 Chimay (baileux) Hainaut 6464",
    "addr:housenumber":"17",
    "addr:postcode":"6464",
    "addr:street":"Rue Des Crayats",
    "iso:country":"BE",
    "sg:address":"Rue Des Crayats 17",
    "sg:city":"Chimay (baileux)",
    "sg:classifiers":[
        {
            "category":"Bars & Pubs",
            "type":"Food & Drink"
        }
    ],
    "sg:phone":"+32 60 21 10 10",
    "sg:postcode":"6464",
    "sg:province":"Hainaut",
    "wof:name":"Colombophile",
    "wof:placetype":"venue"
},
  "geometry": {"coordinates":[4.3754281998,50.0287666321],"type":"Point"}
}