{
  "type": "Feature",
  "properties": {
    "addr:full":"Chauss\u00c9e D'ophain 14 Braine-l'alleud Brabant Wallon 1420",
    "addr:housenumber":"14",
    "addr:postcode":"1420",
    "addr:street":"Chausse\u0301E D'Ophain",
    "iso:country":"BE",
    "sg:address":"Chauss\u00c9e D'ophain 14",
    "sg:city":"Braine-l'alleud",
    "sg:orig_category":"Tabac. Librairies. Fournitures de bureau. Journaux",
    "sg:phone":"+32 2 384 90 31",
    "sg:postcode":"1420",
    "sg:province":"Brabant Wallon",
    "wof:name":"Maison Bonaventure",
    "wof:placetype":"venue"
},
  "geometry": {"coordinates":[4.3260340691,50.6664619446],"type":"Point"}
}