{
  "type": "Feature",
  "properties": {
    "iso:country":"BE",
    "sg:address":"Kloosterstraat 6bd",
    "sg:city":"Gent",
    "sg:orig_category":"Enseignement maternel and primaire",
    "sg:phone":"+32 9 282 09 34",
    "sg:postcode":"9031",
    "sg:province":"Oost-Vlaanderen",
    "wof:name":"Bubao Rozemarijn",
    "wof:placetype":"venue"
},
  "geometry": {"coordinates":[3.6178729534,51.0385551453],"type":"Point"}
}