{
  "type": "Feature",
  "properties": {
    "iso:country":"BE",
    "sg:address":"Avenue Des Pagodes 11b1",
    "sg:city":"Brussel/bruxelles",
    "sg:orig_category":"Messageries",
    "sg:phone":"+32 2 242 53 69",
    "sg:postcode":"1020",
    "sg:province":"Bruxelles-Capitale",
    "wof:name":"Fast Boys",
    "wof:placetype":"venue"
},
  "geometry": {"coordinates":[4.375202179,50.8892555237],"type":"Point"}
}