{
  "type": "Feature",
  "properties": {
    "addr:full":"Chauss\u00c9e De Ch\u00c2telineau 223 Charleroi Hainaut 6061",
    "addr:housenumber":"223",
    "addr:postcode":"6061",
    "addr:street":"Chausse\u0301E De Cha\u0302Telineau;Hainaut",
    "iso:country":"BE",
    "sg:address":"Chauss\u00c9e De Ch\u00c2telineau 223",
    "sg:city":"Charleroi",
    "sg:orig_category":"Services de Nettoyage and de D\u00e9sinfection",
    "sg:phone":"+32 71 31 78 37",
    "sg:postcode":"6061",
    "sg:province":"Hainaut",
    "wof:name":"Ramonage F.l.",
    "wof:placetype":"venue"
},
  "geometry": {"coordinates":[4.4899878502,50.4036064148],"type":"Point"}
}