{
  "type": "Feature",
  "properties": {
    "iso:country":"BE",
    "sg:address":"Rue Des Masnuy 310",
    "sg:city":"Jurbise",
    "sg:orig_category":"Eleveurs de bovins",
    "sg:phone":"+32 65 22 90 06",
    "sg:postcode":"7050",
    "sg:province":"Hainaut",
    "wof:name":"Luc Lardinois",
    "wof:placetype":"venue"
},
  "geometry": {"coordinates":[3.926019907,50.5302886963],"type":"Point"}
}