{
  "type": "Feature",
  "properties": {
    "addr:full":"Lindenweg 2 Moorslede West-Vlaanderen 8890",
    "addr:housenumber":"2",
    "addr:postcode":"8890",
    "addr:street":"Lindenweg",
    "iso:country":"BE",
    "sg:address":"Lindenweg 2",
    "sg:city":"Moorslede",
    "sg:classifiers":[
        {
            "category":"Farming",
            "subcategory":"Crops",
            "type":"Manufacturing & Wholesale Goods"
        }
    ],
    "sg:phone":"+32 51 77 77 23",
    "sg:postcode":"8890",
    "sg:province":"West-Vlaanderen",
    "sg:tags":[
        "vegetable",
        "fruit",
        "agriculture",
        "livestock"
    ],
    "wof:name":"Dhr Willy Denolf",
    "wof:placetype":"venue"
},
  "geometry": {"coordinates":[3.0809030533,50.9143943787],"type":"Point"}
}