{
  "type": "Feature",
  "properties": {
    "iso:country":"BE",
    "sg:address":"Waterschaapstraat 14",
    "sg:city":"Galmaarden",
    "sg:orig_category":"Sportterreinen and installaties behalve sportcentra",
    "sg:phone":"+32 54 58 07 61",
    "sg:postcode":"1570",
    "sg:province":"Vlaams-Brabant",
    "wof:name":"Man\u00c8ge T Hof",
    "wof:placetype":"venue"
},
  "geometry": {"coordinates":[3.9470911026,50.7624397278],"type":"Point"}
}