{
  "type": "Feature",
  "properties": {
    "iso:country":"BE",
    "sg:address":"Quinten Matsijslei 34",
    "sg:city":"Antwerpen",
    "sg:orig_category":"Advocaten and juridische adviseurs",
    "sg:phone":"+32 3 213 97 80",
    "sg:postcode":"2018",
    "sg:province":"Antwerpen",
    "wof:name":"Eva Lipschutz",
    "wof:placetype":"venue"
},
  "geometry": {"coordinates":[4.417154789,51.2126846313],"type":"Point"}
}