{
  "type": "Feature",
  "properties": {
    "addr:full":"Industriestraat 14 Ruiselede West-Vlaanderen 8755",
    "addr:housenumber":"14",
    "addr:postcode":"8755",
    "addr:street":"Industriestraat",
    "iso:country":"BE",
    "sg:address":"Industriestraat 14",
    "sg:city":"Ruiselede",
    "sg:classifiers":[
        {
            "category":"Government",
            "subcategory":"Fire Station",
            "type":"Public Place"
        }
    ],
    "sg:phone":"+32 51 68 87 66",
    "sg:postcode":"8755",
    "sg:province":"West-Vlaanderen",
    "sg:tags":[
        "commerce",
        "conditionn\u00e9",
        "equipement",
        "pour",
        "air",
        "ventilation",
        "diver"
    ],
    "wof:name":"Peter Roose",
    "wof:placetype":"venue"
},
  "geometry": {"coordinates":[3.408700943,51.0464630127],"type":"Point"}
}