{
  "type": "Feature",
  "properties": {
    "iso:country":"BE",
    "sg:address":"Rue Georges Simpson 34",
    "sg:city":"Bruxelles",
    "sg:classifiers":[
        {
            "category":"Food & Beverages",
            "subcategory":"Bakery",
            "type":"Retail Goods"
        }
    ],
    "sg:phone":"+32 2 428 86 49",
    "sg:postcode":"1083",
    "sg:province":"Bruxelles-Capitale",
    "sg:tags":[
        "long-keeping",
        "pastry"
    ],
    "wof:name":"Sira S.a.",
    "wof:placetype":"venue"
},
  "geometry": {"coordinates":[4.3194270134,50.870262146],"type":"Point"}
}