{
  "type": "Feature",
  "properties": {
    "addr:full":"Brusselsesteenweg 265 Mechelen Antwerpen 2800",
    "addr:housenumber":"265",
    "addr:postcode":"2800",
    "addr:street":"Brusselsesteenweg",
    "iso:country":"BE",
    "sg:address":"Brusselsesteenweg 265",
    "sg:city":"Mechelen",
    "sg:classifiers":[
        {
            "category":"Professional",
            "subcategory":"Management & Consulting",
            "type":"Services"
        }
    ],
    "sg:phone":"+32 15 41 77 74",
    "sg:postcode":"2800",
    "sg:province":"Antwerpen",
    "sg:tags":[
        "consultant"
    ],
    "wof:name":"J.a.a. Martens Bvba",
    "wof:placetype":"venue"
},
  "geometry": {"coordinates":[4.473900795,51.0128555298],"type":"Point"}
}