{
  "type": "Feature",
  "properties": {
    "addr:full":"Chauss\u00e9e D'ivoz 3 Fl\u00e9malle (ivoz-ramet) Li\u00e8ge 4400",
    "addr:housenumber":"3",
    "addr:postcode":"4400",
    "addr:street":"Chausse\u0301E D'Ivoz;Ivoz-Ramet",
    "iso:country":"BE",
    "sg:address":"Chauss\u00e9e D'ivoz 3",
    "sg:city":"Fl\u00e9malle (ivoz-ramet)",
    "sg:classifiers":[
        {
            "category":"Bars & Pubs",
            "type":"Food & Drink"
        }
    ],
    "sg:phone":"+32 4 336 66 02",
    "sg:postcode":"4400",
    "sg:province":"Li\u00e8ge",
    "wof:name":"Fred",
    "wof:placetype":"venue"
},
  "geometry": {"coordinates":[5.4641079903,50.5885734558],"type":"Point"}
}