{
  "type": "Feature",
  "properties": {
    "addr:full":"Nazaretdreef 103 Lier Antwerpen 2500",
    "addr:housenumber":"103",
    "addr:postcode":"2500",
    "addr:street":"Nazaretdreef",
    "iso:country":"BE",
    "sg:address":"Nazaretdreef 103",
    "sg:city":"Lier",
    "sg:classifiers":[
        {
            "category":"Restaurant",
            "type":"Food & Drink"
        }
    ],
    "sg:phone":"+32 3 480 07 20",
    "sg:postcode":"2500",
    "sg:province":"Antwerpen",
    "sg:tags":[
        "caf\u00e9s"
    ],
    "wof:name":"De Oude Lier",
    "wof:placetype":"venue"
},
  "geometry": {"coordinates":[4.5826411247,51.1426506042],"type":"Point"}
}