{
  "type": "Feature",
  "properties": {
    "iso:country":"BE",
    "sg:address":"Antwerpsesteenweg 204",
    "sg:city":"Malle (westmalle)",
    "sg:classifiers":[
        {
            "category":"Health Services",
            "subcategory":"Dentist",
            "type":"Services"
        }
    ],
    "sg:phone":"+32 3 312 39 40",
    "sg:postcode":"2390",
    "sg:province":"Antwerpen",
    "wof:name":"Monballiu E",
    "wof:placetype":"venue"
},
  "geometry": {"coordinates":[4.6966710091,51.2970161438],"type":"Point"}
}