{
  "type": "Feature",
  "properties": {
    "addr:full":"Graanmarkt 5 Kortrijk West-Vlaanderen 8500",
    "addr:housenumber":"5",
    "addr:postcode":"8500",
    "addr:street":"Graanmarkt",
    "iso:country":"BE",
    "sg:address":"Graanmarkt 5",
    "sg:city":"Kortrijk",
    "sg:classifiers":[
        {
            "category":"Restaurant",
            "type":"Food & Drink"
        }
    ],
    "sg:phone":"+32 56 22 35 95",
    "sg:postcode":"8500",
    "sg:province":"West-Vlaanderen",
    "wof:name":"Da Gianni",
    "wof:placetype":"venue"
},
  "geometry": {"coordinates":[3.2655820847,50.8269042969],"type":"Point"}
}