{
  "type": "Feature",
  "properties": {
    "addr:full":"Rue L\u00e9on Theodor 5 Bruxelles (jette) Bruxelles-Capitale 1090",
    "addr:housenumber":"5",
    "addr:postcode":"1090",
    "addr:street":"Rue Le\u0301On Theodor",
    "iso:country":"BE",
    "sg:address":"Rue L\u00e9on Theodor 5",
    "sg:city":"Bruxelles (jette)",
    "sg:classifiers":[
        {
            "category":"Retail",
            "subcategory":"Repair Shop",
            "type":"Services"
        }
    ],
    "sg:phone":"+32 2 426 47 99",
    "sg:postcode":"1090",
    "sg:province":"Bruxelles-Capitale",
    "sg:tags":[
        "-",
        "mainten",
        "watch",
        "clock"
    ],
    "wof:name":"Dassy Sa",
    "wof:placetype":"venue"
},
  "geometry": {"coordinates":[4.3260030746,50.8733673096],"type":"Point"}
}