{
  "type": "Feature",
  "properties": {
    "addr:full":"Route Jean Xxiii 16 Baelen Li\u00e8ge 4837",
    "addr:housenumber":"16",
    "addr:postcode":"4837",
    "addr:street":"Route Jean Xxiii",
    "iso:country":"BE",
    "sg:address":"Route Jean Xxiii 16",
    "sg:city":"Baelen",
    "sg:orig_category":"Eclairage et \u00e9quipements du foyer. Installation de menuiserie m\u00e9tallique. Installation de menuiserie",
    "sg:phone":"+32 87 76 39 57",
    "sg:postcode":"4837",
    "sg:province":"Li\u00e8ge",
    "wof:name":"J. Ahn",
    "wof:placetype":"venue"
},
  "geometry": {"coordinates":[5.9742212296,50.628528595],"type":"Point"}
}