{
  "type": "Feature",
  "properties": {
    "iso:country":"BE",
    "sg:address":"Kortrijksesteenweg 777ba",
    "sg:city":"Gent",
    "sg:orig_category":"Agences immobili\u00e8res",
    "sg:phone":"+32 9 222 23 15",
    "sg:postcode":"9000",
    "sg:province":"Oost-Vlaanderen",
    "wof:name":"Bureau Ledeje",
    "wof:placetype":"venue"
},
  "geometry": {"coordinates":[3.7127079964,51.0288276672],"type":"Point"}
}