{
  "type": "Feature",
  "properties": {
    "iso:country":"BE",
    "sg:address":"Rue De L\u00b4h\u00d4tel De Ville 17",
    "sg:city":"Vielsalm",
    "sg:classifiers":[
        {
            "category":"Insurance",
            "subcategory":"Insurance Agent",
            "type":"Services"
        }
    ],
    "sg:phone":"+32 80 21 70 81",
    "sg:postcode":"6690",
    "sg:province":"Luxembourg",
    "sg:tags":[
        "verzekeringsmakelaars",
        "expert"
    ],
    "wof:name":"C. Caels",
    "wof:placetype":"venue"
},
  "geometry": {"coordinates":[5.9145870209,50.2834815979],"type":"Point"}
}