{
  "type": "Feature",
  "properties": {
    "addr:full":"Camille Lemonnierstraat 19 Elsene/ixelles Bruxelles-Capitale 1050",
    "addr:housenumber":"19",
    "addr:postcode":"1050",
    "addr:street":"Camille Lemonnierstraat",
    "iso:country":"BE",
    "sg:address":"Camille Lemonnierstraat 19",
    "sg:city":"Elsene/ixelles",
    "sg:orig_category":"Fotogravure and zetwerk",
    "sg:phone":"+32 2 345 67 67",
    "sg:postcode":"1050",
    "sg:province":"Bruxelles-Capitale",
    "wof:name":"C. Van Hacht",
    "wof:placetype":"venue"
},
  "geometry": {"coordinates":[4.3589229584,50.8190002441],"type":"Point"}
}