{
  "type": "Feature",
  "properties": {
    "iso:country":"BE",
    "sg:address":"Korte Gasthuisstraat 11",
    "sg:city":"Antwerpen",
    "sg:orig_category":"Brood, gebak and snoepgoed",
    "sg:phone":"+32 3 231 26 60",
    "sg:postcode":"2000",
    "sg:province":"Antwerpen",
    "wof:name":"Philip\u00b4s Biscuits",
    "wof:placetype":"venue"
},
  "geometry": {"coordinates":[4.4043679237,51.2171630859],"type":"Point"}
}