{
  "type": "Feature",
  "properties": {
    "iso:country":"BE",
    "sg:address":"Sint-janstraat 14",
    "sg:city":"Beringen",
    "sg:orig_category":"Brood, gebak and snoepgoed",
    "sg:phone":"+32 11 42 20 12",
    "sg:postcode":"3583",
    "sg:province":"Limburg",
    "wof:name":"Bakkerij Reynders Gebrs",
    "wof:placetype":"venue"
},
  "geometry": {"coordinates":[5.1744627953,51.0388717651],"type":"Point"}
}