{
  "type": "Feature",
  "properties": {
    "addr:full":"Rue Du Moulin 33 Virton Luxembourg 6760",
    "addr:housenumber":"33",
    "addr:postcode":"6760",
    "addr:street":"Rue Du Moulin",
    "iso:country":"BE",
    "sg:address":"Rue Du Moulin 33",
    "sg:city":"Virton",
    "sg:orig_category":"Rev\u00eatements de sols and murs. Installation de menuiserie m\u00e9tallique. Mat\u00e9riaux de construction Gr",
    "sg:phone":"+32 63 57 92 80",
    "sg:postcode":"6760",
    "sg:province":"Luxembourg",
    "wof:name":"Virton Mat\u00c9riaux",
    "wof:placetype":"venue"
},
  "geometry": {"coordinates":[5.5347781181,49.5654067993],"type":"Point"}
}