{
  "type": "Feature",
  "properties": {
    "iso:country":"BE",
    "sg:address":"Mandemakerstraat 4",
    "sg:city":"Hamme",
    "sg:classifiers":[
        {
            "category":"Cafe",
            "type":"Food & Drink"
        }
    ],
    "sg:phone":"+32 52 47 65 65",
    "sg:postcode":"9220",
    "sg:province":"Oost-Vlaanderen",
    "sg:tags":[
        "caf\u00e9s"
    ],
    "wof:name":"Caf\u00c9 Achter De Kerk",
    "wof:placetype":"venue"
},
  "geometry": {"coordinates":[4.1388697624,51.0983734131],"type":"Point"}
}