{
  "type": "Feature",
  "properties": {
    "iso:country":"BE",
    "sg:address":"Kwekerijstraat 1b",
    "sg:city":"Schilde",
    "sg:orig_category":"Services de Nettoyage and de D\u00e9sinfection. Plomberie, chauffage and installations sanitaires",
    "sg:phone":"+32 3 385 14 47",
    "sg:postcode":"2970",
    "sg:province":"Antwerpen",
    "wof:name":"Karlo Cools",
    "wof:placetype":"venue"
},
  "geometry": {"coordinates":[4.5865178108,51.2394142151],"type":"Point"}
}