{
  "type": "Feature",
  "properties": {
    "addr:full":"Oeveren 20 Baelen Li\u00e8ge 4837",
    "addr:housenumber":"20",
    "addr:postcode":"4837",
    "addr:street":"Oeveren",
    "iso:country":"BE",
    "sg:address":"Oeveren 20",
    "sg:city":"Baelen",
    "sg:classifiers":[
        {
            "category":"Shopping",
            "subcategory":"Clothing, Apparel, & Fashions",
            "type":"Retail Goods"
        }
    ],
    "sg:phone":"+32 87 76 21 71",
    "sg:postcode":"4837",
    "sg:province":"Li\u00e8ge",
    "sg:tags":[
        "purchase",
        "clothing",
        "-",
        "sale",
        "second-hand"
    ],
    "wof:name":"Recytextile Scrl",
    "wof:placetype":"venue"
},
  "geometry": {"coordinates":[5.9719800949,50.6337013245],"type":"Point"}
}