{
  "type": "Feature",
  "properties": {
    "addr:full":"Dorpstraat Stekene Oost-Vlaanderen 9190",
    "addr:postcode":"9190",
    "addr:street":"Dorpstraat",
    "iso:country":"BE",
    "sg:address":"Dorpstraat",
    "sg:city":"Stekene",
    "sg:orig_category":"Disneyland Parijs",
    "sg:phone":"+32 3 779 63 13",
    "sg:postcode":"9190",
    "sg:province":"Oost-Vlaanderen",
    "wof:name":"Ster Reizen",
    "wof:placetype":"venue"
},
  "geometry": {"coordinates":[4.040389061,51.2057342529],"type":"Point"}
}