{
  "type": "Feature",
  "properties": {
    "addr:full":"Place Cousin 21 Ecaussinnes (ecaussinnes-d'enghien) Hainaut 7190",
    "addr:housenumber":"21",
    "addr:postcode":"7190",
    "addr:street":"Place Cousin;Ecaussinnes-D'Enghien Hainaut",
    "iso:country":"BE",
    "sg:address":"Place Cousin 21",
    "sg:city":"Ecaussinnes (ecaussinnes-d'enghien)",
    "sg:classifiers":[
        {
            "category":"Communications",
            "subcategory":"Film & Video Production",
            "type":"Services"
        }
    ],
    "sg:phone":"+32 67 49 10 97",
    "sg:postcode":"7190",
    "sg:province":"Hainaut",
    "sg:tags":[
        "multimedia",
        "-",
        "system"
    ],
    "wof:name":"Cdr-crd",
    "wof:placetype":"venue"
},
  "geometry": {"coordinates":[4.1523389816,50.5616493225],"type":"Point"}
}