{
  "type": "Feature",
  "properties": {
    "addr:full":"Square De Molembisoul 3 Jodoigne Brabant Wallon 1370",
    "addr:housenumber":"3",
    "addr:postcode":"1370",
    "addr:street":"Square De Molembisoul",
    "iso:country":"BE",
    "sg:address":"Square De Molembisoul 3",
    "sg:city":"Jodoigne",
    "sg:orig_category":"Artistes ind\u00e9pendants",
    "sg:phone":"+32 10 81 00 72",
    "sg:postcode":"1370",
    "sg:province":"Brabant Wallon",
    "wof:name":"Suzanne Fabry",
    "wof:placetype":"venue"
},
  "geometry": {"coordinates":[4.8813409805,50.7199516296],"type":"Point"}
}