{
  "type": "Feature",
  "properties": {
    "addr:full":"Gravenbosstraat 42 Liedekerke Vlaams-Brabant 1770",
    "addr:housenumber":"42",
    "addr:postcode":"1770",
    "addr:street":"Gravenbosstraat;Vlaams-Brabant",
    "iso:country":"BE",
    "sg:address":"Gravenbosstraat 42",
    "sg:city":"Liedekerke",
    "sg:classifiers":[
        {
            "category":"Building & Trades",
            "subcategory":"Construction",
            "type":"Services"
        }
    ],
    "sg:phone":"+32 53 66 02 73",
    "sg:postcode":"1770",
    "sg:province":"Vlaams-Brabant",
    "sg:tags":[
        "carpenter"
    ],
    "wof:name":"Desco-de Swaef Constructie & Onderhoud",
    "wof:placetype":"venue"
},
  "geometry": {"coordinates":[4.1121897697,50.8609695435],"type":"Point"}
}