{
  "type": "Feature",
  "properties": {
    "iso:country":"BE",
    "sg:address":"Wuustwezelsteenweg 26",
    "sg:city":"Kalmthout",
    "sg:classifiers":[
        {
            "category":"Building & Trades",
            "subcategory":"Construction",
            "type":"Services"
        }
    ],
    "sg:phone":"+32 3 667 33 66",
    "sg:postcode":"2920",
    "sg:province":"Antwerpen",
    "sg:tags":[
        "carpenter"
    ],
    "wof:name":"De Koning Bvba",
    "wof:placetype":"venue"
},
  "geometry": {"coordinates":[4.5195388794,51.4291191101],"type":"Point"}
}