{
  "type": "Feature",
  "properties": {
    "iso:country":"BE",
    "sg:address":"Guido Gezellelaan 105",
    "sg:city":"Deinze",
    "sg:classifiers":[
        {
            "category":"Education",
            "subcategory":"School",
            "type":"Public Place"
        }
    ],
    "sg:phone":"+32 9 386 13 76",
    "sg:postcode":"9800",
    "sg:province":"Oost-Vlaanderen",
    "sg:tags":[
        "secondary"
    ],
    "wof:name":"St Hendriks En Zusters Maricollen Instituut",
    "wof:placetype":"venue"
},
  "geometry": {"coordinates":[3.533495903,50.981262207],"type":"Point"}
}