{
  "type": "Feature",
  "properties": {
    "addr:full":"Rue Charles-magnette 4bb Li\u00c8ge Li\u00e8ge 4000",
    "addr:housenumber":"4bb",
    "addr:postcode":"4000",
    "addr:street":"Rue Charles-Magnette",
    "iso:country":"BE",
    "sg:address":"Rue Charles-magnette 4bb",
    "sg:city":"Li\u00c8ge",
    "sg:orig_category":"Articles pour b\u00e9b\u00e9s. V\u00eatements pour b\u00e9b\u00e9s and enfants",
    "sg:phone":"+32 4 237 00 93",
    "sg:postcode":"4000",
    "sg:province":"Li\u00e8ge",
    "wof:name":"Gabrielle Guerin",
    "wof:placetype":"venue"
},
  "geometry": {"coordinates":[5.574133873,50.6411247253],"type":"Point"}
}