{
  "type": "Feature",
  "properties": {
    "iso:country":"BE",
    "sg:address":"Impasse De L'ange 1",
    "sg:city":"Li\u00c8ge",
    "sg:orig_category":"Artiesten and kunstenaars",
    "sg:phone":"+32 4 223 49 68",
    "sg:postcode":"4000",
    "sg:province":"Li\u00e8ge",
    "wof:name":"C. Charlier",
    "wof:placetype":"venue"
},
  "geometry": {"coordinates":[5.5802941322,50.6477088928],"type":"Point"}
}