{
  "type": "Feature",
  "properties": {
    "addr:full":"Voordestraat 20 Gent Oost-Vlaanderen 9041",
    "addr:housenumber":"20",
    "addr:postcode":"9041",
    "addr:street":"Voordestraat;Oost-Vlaanderen",
    "iso:country":"BE",
    "sg:address":"Voordestraat 20",
    "sg:city":"Gent",
    "sg:orig_category":"Rundveehouders",
    "sg:phone":"+32 9 355 56 65",
    "sg:postcode":"9041",
    "sg:province":"Oost-Vlaanderen",
    "wof:name":"Noe Van Den Bossche",
    "wof:placetype":"venue"
},
  "geometry": {"coordinates":[3.7999989986,51.0778884888],"type":"Point"}
}