{
  "type": "Feature",
  "properties": {
    "iso:country":"BE",
    "sg:address":"Rue De Saint-hubert 11",
    "sg:city":"Libramont-chevigny",
    "sg:orig_category":"Entretien and r\u00e9parations de voitures",
    "sg:phone":"+32 61 22 59 08",
    "sg:postcode":"6800",
    "sg:province":"Luxembourg",
    "wof:name":"Garage Gillet",
    "wof:placetype":"venue"
},
  "geometry": {"coordinates":[5.3499498367,49.9358711243],"type":"Point"}
}