{
  "type": "Feature",
  "properties": {
    "iso:country":"BE",
    "sg:address":"Oostendelaan 306",
    "sg:city":"Middelkerke",
    "sg:orig_category":"Electrom\u00e9nager, t\u00e9l\u00e9visions and radios. R\u00e9parations d'appareils \u00e9lectrom\u00e9nagers. Eclairage et \u00e9quipe",
    "sg:phone":"+32 59 31 44 00",
    "sg:postcode":"8430",
    "sg:province":"West-Vlaanderen",
    "wof:name":"Van Praag",
    "wof:placetype":"venue"
},
  "geometry": {"coordinates":[2.8412959576,51.1940231323],"type":"Point"}
}