{
  "type": "Feature",
  "properties": {
    "iso:country":"BE",
    "sg:address":"Weitingstraat 20",
    "sg:city":"Aalter (bellem)",
    "sg:classifiers":[
        {
            "category":"Building & Trades",
            "subcategory":"Electrical",
            "type":"Services"
        }
    ],
    "sg:phone":"+32 9 375 26 49",
    "sg:postcode":"9881",
    "sg:province":"Oost-Vlaanderen",
    "sg:tags":[
        "electric",
        "-",
        "housewiring",
        "contractor"
    ],
    "wof:name":"Bernaert F",
    "wof:placetype":"venue"
},
  "geometry": {"coordinates":[3.4995450974,51.0752677917],"type":"Point"}
}