{
  "type": "Feature",
  "properties": {
    "addr:full":"Zarren-lindestraat 49 Kortemark West-Vlaanderen 8610",
    "addr:housenumber":"49",
    "addr:postcode":"8610",
    "addr:street":"Zarren-Lindestraat",
    "iso:country":"BE",
    "sg:address":"Zarren-lindestraat 49",
    "sg:city":"Kortemark",
    "sg:orig_category":"Eleveurs and marchands de porcs. Eleveurs de bovins",
    "sg:phone":"+32 51 56 68 90",
    "sg:postcode":"8610",
    "sg:province":"West-Vlaanderen",
    "wof:name":"Antoine Devos",
    "wof:placetype":"venue"
},
  "geometry": {"coordinates":[2.9630770683,51.0052337646],"type":"Point"}
}