{
  "type": "Feature",
  "properties": {
    "addr:full":"Waterloose Steenweg 788 Ukkel/uccle Bruxelles-Capitale 1180",
    "addr:housenumber":"788",
    "addr:postcode":"1180",
    "addr:street":"Waterloose Steenweg;/",
    "iso:country":"BE",
    "sg:address":"Waterloose Steenweg 788",
    "sg:city":"Ukkel/uccle",
    "sg:orig_category":"Artsen and specialisten",
    "sg:phone":"+32 2 372 23 51",
    "sg:postcode":"1180",
    "sg:province":"Bruxelles-Capitale",
    "wof:name":"D. Barbieux",
    "wof:placetype":"venue"
},
  "geometry": {"coordinates":[4.3674502373,50.8146095276],"type":"Point"}
}