{
  "type": "Feature",
  "properties": {
    "iso:country":"BE",
    "sg:address":"Ridderschapslaan 15",
    "sg:city":"Brussel/bruxelles",
    "sg:orig_category":"Reclamebureaus",
    "sg:phone":"+32 2 640 48 57",
    "sg:postcode":"1040",
    "sg:province":"Bruxelles-Capitale",
    "wof:name":"United Networks",
    "wof:placetype":"venue"
},
  "geometry": {"coordinates":[4.39605093,50.8426170349],"type":"Point"}
}