{
  "type": "Feature",
  "properties": {
    "addr:full":". Aiseau-presles Hainaut 6250",
    "addr:postcode":"6250",
    "addr:street":"Hainaut",
    "iso:country":"BE",
    "sg:address":".",
    "sg:city":"Aiseau-presles",
    "sg:orig_category":"Apotheken",
    "sg:phone":"+32 900 10 500",
    "sg:postcode":"6250",
    "sg:province":"Hainaut",
    "wof:name":"Apothekers Van Wacht",
    "wof:placetype":"venue"
},
  "geometry": {"coordinates":[4.5863847733,50.40990448],"type":"Point"}
}