{
  "type": "Feature",
  "properties": {
    "addr:full":"Raadsherenstraat 3 Turnhout Antwerpen 2300",
    "addr:housenumber":"3",
    "addr:postcode":"2300",
    "addr:street":"Raadsherenstraat",
    "iso:country":"BE",
    "sg:address":"Raadsherenstraat 3",
    "sg:city":"Turnhout",
    "sg:orig_category":"Onderhoud van kantoor- and computeruitrusting",
    "sg:phone":"+32 14 40 07 11",
    "sg:postcode":"2300",
    "sg:province":"Antwerpen",
    "wof:name":"Magnetic Data Belgium",
    "wof:placetype":"venue"
},
  "geometry": {"coordinates":[4.9159450531,51.3049468994],"type":"Point"}
}