{
  "type": "Feature",
  "properties": {
    "addr:full":"Bistweg 46 Ranst Antwerpen 2520",
    "addr:housenumber":"46",
    "addr:postcode":"2520",
    "addr:street":"Bistweg",
    "iso:country":"BE",
    "sg:address":"Bistweg 46",
    "sg:city":"Ranst",
    "sg:orig_category":"Quincailleries",
    "sg:phone":"+32 3 475 07 16",
    "sg:postcode":"2520",
    "sg:province":"Antwerpen",
    "wof:name":"Fa. Bama",
    "wof:placetype":"venue"
},
  "geometry": {"coordinates":[4.5914101601,51.1884918213],"type":"Point"}
}