{
  "type": "Feature",
  "properties": {
    "iso:country":"BE",
    "sg:address":"Rue Nicolas Lambercy 4",
    "sg:city":"Aywaille",
    "sg:classifiers":[
        {
            "category":"Shopping",
            "subcategory":"Gifts & Souvenirs",
            "type":"Retail Goods"
        }
    ],
    "sg:phone":"+32 4 384 35 90",
    "sg:postcode":"4920",
    "sg:province":"Li\u00e8ge",
    "sg:tags":[
        "-"
    ],
    "wof:name":"C\u00f4t\u00e9 Provence",
    "wof:placetype":"venue"
},
  "geometry": {"coordinates":[5.6756329536,50.4733085632],"type":"Point"}
}