{
  "type": "Feature",
  "properties": {
    "iso:country":"BE",
    "sg:address":"Leegstraat 8",
    "sg:city":"Assenede",
    "sg:classifiers":[
        {
            "category":"Health Services",
            "subcategory":"Doctor",
            "type":"Services"
        }
    ],
    "sg:phone":"+32 9 344 85 89",
    "sg:postcode":"9960",
    "sg:province":"Oost-Vlaanderen",
    "sg:tags":[
        "medicinephysicians",
        "surgeon"
    ],
    "wof:name":"De Smet Dirk",
    "wof:placetype":"venue"
},
  "geometry": {"coordinates":[3.752010107,51.2284889221],"type":"Point"}
}