{
  "type": "Feature",
  "properties": {
    "addr:full":"Nijvelsebaan 162 Bertem (korbeek-dijle) Vlaams-Brabant 3060",
    "addr:housenumber":"162",
    "addr:postcode":"3060",
    "addr:street":"Nijvelsebaan",
    "iso:country":"BE",
    "sg:address":"Nijvelsebaan 162",
    "sg:city":"Bertem (korbeek-dijle)",
    "sg:classifiers":[
        {
            "category":"Professional",
            "subcategory":"Management & Consulting",
            "type":"Services"
        }
    ],
    "sg:phone":"+32 16 47 23 88",
    "sg:postcode":"3060",
    "sg:province":"Vlaams-Brabant",
    "sg:tags":[
        "consultant"
    ],
    "wof:name":"In Society Bvba",
    "wof:placetype":"venue"
},
  "geometry": {"coordinates":[4.6391620636,50.8400268555],"type":"Point"}
}