{
  "type": "Feature",
  "properties": {
    "addr:full":"Rue Lamarck 39 Li\u00c8ge Li\u00e8ge 4000",
    "addr:housenumber":"39",
    "addr:postcode":"4000",
    "addr:street":"Rue Lamarck",
    "iso:country":"BE",
    "sg:address":"Rue Lamarck 39",
    "sg:city":"Li\u00c8ge",
    "sg:orig_category":"Dakwerken",
    "sg:phone":"+32 4 227 62 59",
    "sg:postcode":"4000",
    "sg:province":"Li\u00e8ge",
    "wof:name":"Renoval Toiture",
    "wof:placetype":"venue"
},
  "geometry": {"coordinates":[5.5911240578,50.6515350342],"type":"Point"}
}