{
  "type": "Feature",
  "properties": {
    "addr:full":"Kortestraat 1 Leuven Vlaams-Brabant 3000",
    "addr:housenumber":"1",
    "addr:postcode":"3000",
    "addr:street":"Kortestraat",
    "iso:country":"BE",
    "sg:address":"Kortestraat 1",
    "sg:city":"Leuven",
    "sg:orig_category":"Kapsalons",
    "sg:phone":"+32 16 22 22 95",
    "sg:postcode":"3000",
    "sg:province":"Vlaams-Brabant",
    "wof:name":"Coiffure Hubert",
    "wof:placetype":"venue"
},
  "geometry": {"coordinates":[4.7001109123,50.8789367676],"type":"Point"}
}