{
  "type": "Feature",
  "properties": {
    "addr:full":"Tulpenlaan 26 Izegem West-Vlaanderen 8870",
    "addr:housenumber":"26",
    "addr:postcode":"8870",
    "addr:street":"Tulpenlaan",
    "iso:country":"BE",
    "sg:address":"Tulpenlaan 26",
    "sg:city":"Izegem",
    "sg:classifiers":[
        {
            "category":"Education",
            "subcategory":"Dance Studio",
            "type":"Public Place"
        }
    ],
    "sg:phone":"+32 51 30 54 55",
    "sg:postcode":"8870",
    "sg:province":"West-Vlaanderen",
    "sg:tags":[
        "school",
        "dancing"
    ],
    "wof:name":"Casaert L",
    "wof:placetype":"venue"
},
  "geometry": {"coordinates":[3.2123339176,50.9086532593],"type":"Point"}
}