{
  "type": "Feature",
  "properties": {
    "addr:full":"Rue Des Fripiers 12 Namur Namur 5000",
    "addr:housenumber":"12",
    "addr:postcode":"5000",
    "addr:street":"Rue Des Fripiers",
    "iso:country":"BE",
    "sg:address":"Rue Des Fripiers 12",
    "sg:city":"Namur",
    "sg:classifiers":[
        {
            "category":"Cafe",
            "type":"Food & Drink"
        }
    ],
    "sg:phone":"+32 81 23 04 16",
    "sg:postcode":"5000",
    "sg:province":"Namur",
    "sg:tags":[
        "snack-bars"
    ],
    "wof:name":"Pitta Gyros",
    "wof:placetype":"venue"
},
  "geometry": {"coordinates":[4.8655471802,50.4631195068],"type":"Point"}
}