{
  "type": "Feature",
  "properties": {
    "iso:country":"BE",
    "sg:address":"Dorpsplein 18",
    "sg:city":"Ledegem (sint-eloois-winkel)",
    "sg:classifiers":[
        {
            "category":"Bars & Pubs",
            "type":"Food & Drink"
        }
    ],
    "sg:phone":"+32 56 50 90 27",
    "sg:postcode":"8880",
    "sg:province":"West-Vlaanderen",
    "wof:name":"Oud Gemeentehuis",
    "wof:placetype":"venue"
},
  "geometry": {"coordinates":[3.1788549423,50.876449585],"type":"Point"}
}