{
  "type": "Feature",
  "properties": {
    "addr:full":"Boomkwekerijlaan 6 Sint-genesius-rode/rhode-saint-genese Vlaams-Brabant 1640",
    "addr:housenumber":"6",
    "addr:postcode":"1640",
    "addr:street":"Boomkwekerijlaan",
    "iso:country":"BE",
    "sg:address":"Boomkwekerijlaan 6",
    "sg:city":"Sint-genesius-rode/rhode-saint-genese",
    "sg:orig_category":"Computers and computerapparatuur Onderhoud van kantoor- and computeruitrusting",
    "sg:phone":"+32 2 381 05 79",
    "sg:postcode":"1640",
    "sg:province":"Vlaams-Brabant",
    "wof:name":"Double D Computers",
    "wof:placetype":"venue"
},
  "geometry": {"coordinates":[4.3593959808,50.751701355],"type":"Point"}
}