{
  "type": "Feature",
  "properties": {
    "addr:full":"Oudestraat 10 Zonhoven Limburg 3520",
    "addr:housenumber":"10",
    "addr:postcode":"3520",
    "addr:street":"Oudestraat",
    "iso:country":"BE",
    "sg:address":"Oudestraat 10",
    "sg:city":"Zonhoven",
    "sg:orig_category":"Beautyfarms, relaxatie and lichamelijk welzijn Schoonheidssalons",
    "sg:phone":"+32 11 81 44 04",
    "sg:postcode":"3520",
    "sg:province":"Limburg",
    "wof:name":"Lisette Gybels",
    "wof:placetype":"venue"
},
  "geometry": {"coordinates":[5.3583631516,51.0042991638],"type":"Point"}
}