{
  "type": "Feature",
  "properties": {
    "addr:full":"Heidestraat 52 Gent Oost-Vlaanderen 9050",
    "addr:housenumber":"52",
    "addr:postcode":"9050",
    "addr:street":"Heidestraat;Oost-Vlaanderen",
    "iso:country":"BE",
    "sg:address":"Heidestraat 52",
    "sg:city":"Gent",
    "sg:orig_category":"Parfumeries",
    "sg:phone":"+32 9 375 28 47",
    "sg:postcode":"9050",
    "sg:province":"Oost-Vlaanderen",
    "wof:name":"G. Bevers",
    "wof:placetype":"venue"
},
  "geometry": {"coordinates":[3.7549340725,51.028717041],"type":"Point"}
}