{
  "type": "Feature",
  "properties": {
    "addr:full":"Rue De Sirault 12 Jurbise Hainaut 7050",
    "addr:housenumber":"12",
    "addr:postcode":"7050",
    "addr:street":"Rue De Sirault",
    "iso:country":"BE",
    "sg:address":"Rue De Sirault 12",
    "sg:city":"Jurbise",
    "sg:orig_category":"G\u00e9om\u00e8tres",
    "sg:phone":"+32 65 22 73 66",
    "sg:postcode":"7050",
    "sg:province":"Hainaut",
    "wof:name":"Luc Leulier",
    "wof:placetype":"venue"
},
  "geometry": {"coordinates":[3.8482010365,50.5290870667],"type":"Point"}
}