{
  "type": "Feature",
  "properties": {
    "iso:country":"BE",
    "sg:address":"Moerstraat 56",
    "sg:city":"Wevelgem",
    "sg:classifiers":[
        {
            "category":"Professional",
            "subcategory":"Accounting & Tax Preparation",
            "type":"Services"
        }
    ],
    "sg:phone":"+32 56 42 41 51",
    "sg:postcode":"8560",
    "sg:province":"West-Vlaanderen",
    "sg:tags":[
        "bookkeeper"
    ],
    "wof:name":"Wevelgems Bur. Fiskaliteit",
    "wof:placetype":"venue"
},
  "geometry": {"coordinates":[3.1806979179,50.820476532],"type":"Point"}
}