{
  "type": "Feature",
  "properties": {
    "addr:full":"Kloosterstraat 183 Antwerpen Antwerpen 2000",
    "addr:housenumber":"183",
    "addr:postcode":"2000",
    "addr:street":"Kloosterstraat",
    "iso:country":"BE",
    "sg:address":"Kloosterstraat 183",
    "sg:city":"Antwerpen",
    "sg:orig_category":"Banken and kredietinstellingen",
    "sg:phone":"+32 3 237 62 94",
    "sg:postcode":"2000",
    "sg:province":"Antwerpen",
    "wof:name":"Bbl",
    "wof:placetype":"venue"
},
  "geometry": {"coordinates":[4.3942461014,51.212638855],"type":"Point"}
}