{
  "type": "Feature",
  "properties": {
    "addr:full":"Naamsesteenweg 210 Leuven Vlaams-Brabant 3001",
    "addr:housenumber":"210",
    "addr:postcode":"3001",
    "addr:street":"Naamsesteenweg",
    "iso:country":"BE",
    "sg:address":"Naamsesteenweg 210",
    "sg:city":"Leuven",
    "sg:orig_category":"Brood, gebak and snoepgoed",
    "sg:phone":"+32 16 40 59 97",
    "sg:postcode":"3001",
    "sg:province":"Vlaams-Brabant",
    "wof:name":"Bakkerij 't Kruimeltje",
    "wof:placetype":"venue"
},
  "geometry": {"coordinates":[4.6956791878,50.8612365723],"type":"Point"}
}