{
  "type": "Feature",
  "properties": {
    "addr:full":"Rue De La Villa Romaine 3 Nadrin Luxembourg 6660",
    "addr:housenumber":"3",
    "addr:postcode":"6660",
    "addr:street":"Rue De La Villa Romaine",
    "iso:country":"BE",
    "sg:address":"Rue De La Villa Romaine 3",
    "sg:city":"Nadrin",
    "sg:orig_category":"Diverse zakelijke dienstverlening Organisatie van beurzen, congressen and tentoonstellingen Sportact",
    "sg:phone":"+32 84 44 41 12",
    "sg:postcode":"6660",
    "sg:province":"Luxembourg",
    "wof:name":"Outdoor Centre",
    "wof:placetype":"venue"
},
  "geometry": {"coordinates":[5.68227005,50.1593208313],"type":"Point"}
}