{
  "type": "Feature",
  "properties": {
    "iso:country":"BE",
    "sg:address":"Noordstraat 55",
    "sg:city":"Veurne",
    "sg:classifiers":[
        {
            "category":"Real Estate",
            "subcategory":"Real Estate Services",
            "type":"Services"
        }
    ],
    "sg:phone":"+32 58 31 10 85",
    "sg:postcode":"8630",
    "sg:province":"West-Vlaanderen",
    "wof:name":"Caillimmo Cva",
    "wof:placetype":"venue"
},
  "geometry": {"coordinates":[2.6624588966,51.0748138428],"type":"Point"}
}