{
  "type": "Feature",
  "properties": {
    "iso:country":"BE",
    "sg:address":"Rue Pierre David 60",
    "sg:city":"Verviers",
    "sg:orig_category":"Kapsalons",
    "sg:phone":"+32 87 33 30 77",
    "sg:postcode":"4800",
    "sg:province":"Li\u00e8ge",
    "wof:name":"Josiane Louys",
    "wof:placetype":"venue"
},
  "geometry": {"coordinates":[5.8418412209,50.5885734558],"type":"Point"}
}