{
  "type": "Feature",
  "properties": {
    "addr:full":"Rue Capitaine-lekeux 28 Vielsalm Luxembourg 6698",
    "addr:housenumber":"28",
    "addr:postcode":"6698",
    "addr:street":"Rue Capitaine-Lekeux",
    "iso:country":"BE",
    "sg:address":"Rue Capitaine-lekeux 28",
    "sg:city":"Vielsalm",
    "sg:orig_category":"Supermarch\u00e9s",
    "sg:phone":"+32 80 21 65 47",
    "sg:postcode":"6698",
    "sg:province":"Luxembourg",
    "wof:name":"Louis Delhaize",
    "wof:placetype":"venue"
},
  "geometry": {"coordinates":[5.908053875,50.3257751465],"type":"Point"}
}