{
  "type": "Feature",
  "properties": {
    "iso:country":"BE",
    "sg:address":"Rue De Deminche 53",
    "sg:city":"Floreffe (frani\u00e8re)",
    "sg:orig_category":"Non-Classified Establishments",
    "sg:phone":"+32 81 44 19 11",
    "sg:postcode":"5150",
    "sg:province":"Namur",
    "wof:name":"Cir'art",
    "wof:placetype":"venue"
},
  "geometry": {"coordinates":[4.728372097,50.4368553162],"type":"Point"}
}