{
  "type": "Feature",
  "properties": {
    "iso:country":"BE",
    "sg:address":"Rue D\u00b4horrues 83",
    "sg:city":"Braine-le-comte",
    "sg:orig_category":"Centres sportifs",
    "sg:phone":"+32 67 56 09 08",
    "sg:postcode":"7090",
    "sg:province":"Hainaut",
    "wof:name":"Champ De La Lune",
    "wof:placetype":"venue"
},
  "geometry": {"coordinates":[4.1318178177,50.6109962463],"type":"Point"}
}