{
  "type": "Feature",
  "properties": {
    "iso:country":"BE",
    "sg:address":"Keistraat 127",
    "sg:city":"De Pinte",
    "sg:classifiers":[
        {
            "category":"Home & Garden",
            "subcategory":"Home Furnishings",
            "type":"Retail Goods"
        }
    ],
    "sg:phone":"+32 9 281 17 28",
    "sg:postcode":"9840",
    "sg:province":"Oost-Vlaanderen",
    "sg:tags":[
        "interior",
        "decoration"
    ],
    "wof:name":"Carels & Vande Weghe Nv",
    "wof:placetype":"venue"
},
  "geometry": {"coordinates":[3.6457550526,51.0030212402],"type":"Point"}
}