{
  "type": "Feature",
  "properties": {
    "addr:full":"Rue Du Vallon 7 Fl\u00e9ron (roms\u00e9e) Li\u00e8ge 4624",
    "addr:housenumber":"7",
    "addr:postcode":"4624",
    "addr:street":"Rue Du Vallon",
    "iso:country":"BE",
    "sg:address":"Rue Du Vallon 7",
    "sg:city":"Fl\u00e9ron (roms\u00e9e)",
    "sg:classifiers":[
        {
            "category":"Health Services",
            "subcategory":"Doctor",
            "type":"Services"
        }
    ],
    "sg:phone":"+32 4 358 66 66",
    "sg:postcode":"4624",
    "sg:province":"Li\u00e8ge",
    "sg:tags":[
        "medicinephysicians",
        "surgeon"
    ],
    "wof:name":"Collignon J",
    "wof:placetype":"venue"
},
  "geometry": {"coordinates":[5.6645078659,50.6016235352],"type":"Point"}
}