{
  "type": "Feature",
  "properties": {
    "iso:country":"BE",
    "sg:address":"Meierie 22",
    "sg:city":"Waregem",
    "sg:orig_category":"Loodgieterij, verwarming and sanitaire installaties",
    "sg:phone":"+32 56 71 32 12",
    "sg:postcode":"8792",
    "sg:province":"West-Vlaanderen",
    "wof:name":"Norman Tom",
    "wof:placetype":"venue"
},
  "geometry": {"coordinates":[3.3563020229,50.8825416565],"type":"Point"}
}