{
  "type": "Feature",
  "properties": {
    "iso:country":"BE",
    "sg:address":"Rue De La Tombe 146",
    "sg:city":"Charleroi",
    "sg:orig_category":"Artsen and specialisten",
    "sg:phone":"+32 71 36 77 66",
    "sg:postcode":"6032",
    "sg:province":"Hainaut",
    "wof:name":"V. Cogniaux",
    "wof:placetype":"venue"
},
  "geometry": {"coordinates":[4.4188947678,50.3900337219],"type":"Point"}
}