{
  "type": "Feature",
  "properties": {
    "addr:full":"Doorniksesteenweg 62 Avelgem West-Vlaanderen 8580",
    "addr:housenumber":"62",
    "addr:postcode":"8580",
    "addr:street":"Doorniksesteenweg",
    "iso:country":"BE",
    "sg:address":"Doorniksesteenweg 62",
    "sg:city":"Avelgem",
    "sg:classifiers":[
        {
            "category":"Shopping",
            "subcategory":"Clothing, Apparel, & Fashions",
            "type":"Retail Goods"
        }
    ],
    "sg:phone":"+32 56 64 77 29",
    "sg:postcode":"8580",
    "sg:province":"West-Vlaanderen",
    "sg:tags":[
        "-",
        "clothing",
        "child"
    ],
    "wof:name":"Clemence",
    "wof:placetype":"venue"
},
  "geometry": {"coordinates":[3.4442129135,50.7738952637],"type":"Point"}
}