{
  "type": "Feature",
  "properties": {
    "iso:country":"BE",
    "sg:address":"10",
    "sg:city":"Rue De Cambron 7870 Lens Hainaut",
    "sg:classifiers":[
        {
            "category":"Utilities",
            "type":"Services"
        }
    ],
    "sg:phone":"+32 65 22 54 32",
    "sg:postcode":"10",
    "sg:tags":[
        "raw",
        "energy",
        "material"
    ],
    "wof:name":"Martens Sa",
    "wof:placetype":"venue"
},
  "geometry": {"coordinates":[3.9027950764,50.5612068176],"type":"Point"}
}