{
  "type": "Feature",
  "properties": {
    "iso:country":"BE",
    "sg:address":"Gentsesteenweg 1187",
    "sg:city":"Sint-agatha-berchem/berchem-sainte-agathe",
    "sg:classifiers":[
        {
            "category":"Fast Food",
            "type":"Food & Drink"
        }
    ],
    "sg:phone":"+32 2 468 02 98",
    "sg:postcode":"1082",
    "sg:province":"Bruxelles-Capitale",
    "sg:tags":[
        "meeneem",
        "restaurant"
    ],
    "wof:name":"Restaurant Binh-minh",
    "wof:placetype":"venue"
},
  "geometry": {"coordinates":[4.2957110405,50.8660545349],"type":"Point"}
}