{
  "type": "Feature",
  "properties": {
    "addr:full":"Rue Gobert 2 Sivry-rance Hainaut 6470",
    "addr:housenumber":"2",
    "addr:postcode":"6470",
    "addr:street":"Rue Gobert",
    "iso:country":"BE",
    "sg:address":"Rue Gobert 2",
    "sg:city":"Sivry-rance",
    "sg:orig_category":"Eleveurs de bovins",
    "sg:phone":"+32 60 45 52 17",
    "sg:postcode":"6470",
    "sg:province":"Hainaut",
    "wof:name":"Raymond Descamps",
    "wof:placetype":"venue"
},
  "geometry": {"coordinates":[4.1762728691,50.2015457153],"type":"Point"}
}