{
  "type": "Feature",
  "properties": {
    "addr:full":"Chauss\u00c9e De Waterloo 85 Namur Namur 5000",
    "addr:housenumber":"85",
    "addr:postcode":"5000",
    "addr:street":"Chausse\u0301E De Waterloo",
    "iso:country":"BE",
    "sg:address":"Chauss\u00c9e De Waterloo 85",
    "sg:city":"Namur",
    "sg:classifiers":[
        {
            "category":"Insurance",
            "subcategory":"Insurance Agent",
            "type":"Services"
        }
    ],
    "sg:phone":"+32 81 73 09 13",
    "sg:postcode":"5000",
    "sg:province":"Namur",
    "sg:tags":[
        "verzekeringsmakelaars",
        "expert"
    ],
    "wof:name":"B.t.e.a.",
    "wof:placetype":"venue"
},
  "geometry": {"coordinates":[4.8480701447,50.4720611572],"type":"Point"}
}