{
  "type": "Feature",
  "properties": {
    "addr:full":"Gr\u00c9trystraat 52 Brussel/bruxelles Bruxelles-Capitale 1000",
    "addr:housenumber":"52",
    "addr:postcode":"1000",
    "addr:street":"Gre\u0301Trystraat;/",
    "iso:country":"BE",
    "sg:address":"Gr\u00c9trystraat 52",
    "sg:city":"Brussel/bruxelles",
    "sg:classifiers":[
        {
            "category":"Restaurant",
            "type":"Food & Drink"
        }
    ],
    "sg:phone":"+32 2 218 01 03",
    "sg:postcode":"1000",
    "sg:province":"Bruxelles-Capitale",
    "wof:name":"Nuits Saint-georges",
    "wof:placetype":"venue"
},
  "geometry": {"coordinates":[4.3531098366,50.8488044739],"type":"Point"}
}