{
  "type": "Feature",
  "properties": {
    "addr:full":"Sint-hubertusplein 54b3 Hasselt Limburg 3500",
    "addr:housenumber":"54b3",
    "addr:postcode":"3500",
    "addr:street":"Sint-Hubertusplein",
    "iso:country":"BE",
    "sg:address":"Sint-hubertusplein 54b3",
    "sg:city":"Hasselt",
    "sg:orig_category":"Installation \u00e9lectrique r\u00e9sidentielle",
    "sg:phone":"+32 11 28 32 13",
    "sg:postcode":"3500",
    "sg:province":"Limburg",
    "wof:name":"Eddy Bulen",
    "wof:placetype":"venue"
},
  "geometry": {"coordinates":[5.3258099556,50.9248580933],"type":"Point"}
}