{
  "type": "Feature",
  "properties": {
    "addr:full":"Rue Grande Bruy\u00c8re 21a Welkenraedt/welkenraedt Li\u00e8ge 4840",
    "addr:housenumber":"21a",
    "addr:postcode":"4840",
    "addr:street":"Rue Grande Bruye\u0300Re",
    "iso:country":"BE",
    "sg:address":"Rue Grande Bruy\u00c8re 21a",
    "sg:city":"Welkenraedt/welkenraedt",
    "sg:orig_category":"Goederenvervoer over de weg",
    "sg:phone":"+32 87 88 05 35",
    "sg:postcode":"4840",
    "sg:province":"Li\u00e8ge",
    "wof:name":"Lautermann & Cie",
    "wof:placetype":"venue"
},
  "geometry": {"coordinates":[5.9796700478,50.6616210938],"type":"Point"}
}