{
  "type": "Feature",
  "properties": {
    "iso:country":"BE",
    "sg:address":"Rue Charles Morren 12",
    "sg:city":"Li\u00e8ge 1",
    "sg:classifiers":[
        {
            "category":"Social Services",
            "type":"Services"
        }
    ],
    "sg:phone":"+32 4 252 75 75",
    "sg:postcode":"4000",
    "sg:province":"Li\u00e8ge",
    "wof:name":"En Famille",
    "wof:placetype":"venue"
},
  "geometry": {"coordinates":[5.5614299774,50.6326293945],"type":"Point"}
}