{
  "type": "Feature",
  "properties": {
    "addr:full":"Industriestraat 24a Eupen Li\u00e8ge 4700",
    "addr:housenumber":"24a",
    "addr:postcode":"4700",
    "addr:street":"Industriestraat",
    "iso:country":"BE",
    "sg:address":"Industriestraat 24a",
    "sg:city":"Eupen",
    "sg:orig_category":"Loodgieterij and centrale verwarming Gh",
    "sg:phone":"+32 87 59 39 90",
    "sg:postcode":"4700",
    "sg:province":"Li\u00e8ge",
    "wof:name":"B.t.v.c.",
    "wof:placetype":"venue"
},
  "geometry": {"coordinates":[6.0059399605,50.6399612427],"type":"Point"}
}