{
  "type": "Feature",
  "properties": {
    "iso:country":"BE",
    "sg:address":"Magermerriestraat 2",
    "sg:city":"Roeselare",
    "sg:classifiers":[
        {
            "category":"Personal",
            "subcategory":"Beauty Salon",
            "type":"Services"
        }
    ],
    "sg:phone":"+32 51 77 70 98",
    "sg:postcode":"8800",
    "sg:province":"West-Vlaanderen",
    "wof:name":"Aura",
    "wof:placetype":"venue"
},
  "geometry": {"coordinates":[3.0716669559,50.9240760803],"type":"Point"}
}