{
  "type": "Feature",
  "properties": {
    "addr:full":"Bell Telephonelaan 7a Geel Antwerpen 2440",
    "addr:housenumber":"7a",
    "addr:postcode":"2440",
    "addr:street":"Telephonelaan",
    "iso:country":"BE",
    "sg:address":"Bell Telephonelaan 7a",
    "sg:city":"Geel",
    "sg:classifiers":[
        {
            "category":"Retail",
            "subcategory":"Auto Repair",
            "type":"Services"
        }
    ],
    "sg:phone":"+32 14 59 38 70",
    "sg:postcode":"2440",
    "sg:province":"Antwerpen",
    "sg:tags":[
        "body",
        "car"
    ],
    "wof:name":"Carrosserie Verachtert Nv",
    "wof:placetype":"venue"
},
  "geometry": {"coordinates":[4.9552497864,51.1256904602],"type":"Point"}
}