{
  "type": "Feature",
  "properties": {
    "iso:country":"BE",
    "sg:address":"Kammenstraat 19",
    "sg:city":"Antwerpen",
    "sg:classifiers":[
        {
            "category":"Restaurant",
            "type":"Food & Drink"
        }
    ],
    "sg:phone":"+32 3 231 13 08",
    "sg:postcode":"2000",
    "sg:province":"Antwerpen",
    "wof:name":"Fresh 'n Fruity",
    "wof:placetype":"venue"
},
  "geometry": {"coordinates":[4.400428772,51.2179031372],"type":"Point"}
}