{
  "type": "Feature",
  "properties": {
    "iso:country":"BE",
    "sg:address":"Zeelmakersstraat 5",
    "sg:city":"Lennik",
    "sg:orig_category":"Diverse zakelijke dienstverlening",
    "sg:phone":"+32 2 532 22 88",
    "sg:postcode":"1750",
    "sg:province":"Vlaams-Brabant",
    "wof:name":"Belgian Trade Events Com",
    "wof:placetype":"venue"
},
  "geometry": {"coordinates":[4.1584668159,50.8034057617],"type":"Point"}
}