{
  "type": "Feature",
  "properties": {
    "iso:country":"BE",
    "sg:address":"Chauss\u00e9e D'alsemberg 897",
    "sg:city":"Bruxelles (uccle)",
    "sg:classifiers":[
        {
            "category":"Retail",
            "subcategory":"Auto Repair",
            "type":"Services"
        }
    ],
    "sg:phone":"+32 2 376 79 86",
    "sg:postcode":"1180",
    "sg:province":"Bruxelles-Capitale",
    "sg:tags":[
        "automobile-body"
    ],
    "wof:name":"Globe (carrosserie Du)",
    "wof:placetype":"venue"
},
  "geometry": {"coordinates":[4.336233139,50.7989463806],"type":"Point"}
}