{
  "type": "Feature",
  "properties": {
    "iso:country":"BE",
    "sg:address":"Klaregrachtstraat 57",
    "sg:city":"Izegem",
    "sg:orig_category":"Eleveurs de bovins",
    "sg:phone":"+32 51 30 07 84",
    "sg:postcode":"8870",
    "sg:province":"West-Vlaanderen",
    "wof:name":"M. Vandermersch",
    "wof:placetype":"venue"
},
  "geometry": {"coordinates":[3.1778509617,50.900062561],"type":"Point"}
}