{
  "type": "Feature",
  "properties": {
    "addr:full":"Rue Plantin 29 Bruxelles (anderlecht) Bruxelles-Capitale 1070",
    "addr:housenumber":"29",
    "addr:postcode":"1070",
    "addr:street":"Rue Plantin",
    "iso:country":"BE",
    "sg:address":"Rue Plantin 29",
    "sg:city":"Bruxelles (anderlecht)",
    "sg:classifiers":[
        {
            "category":"Social Services",
            "type":"Services"
        }
    ],
    "sg:phone":"+32 2 527 59 90",
    "sg:postcode":"1070",
    "sg:province":"Bruxelles-Capitale",
    "wof:name":"Cadtm Asbl",
    "wof:placetype":"venue"
},
  "geometry": {"coordinates":[4.3375477791,50.84324646],"type":"Point"}
}