{
  "type": "Feature",
  "properties": {
    "iso:country":"BE",
    "sg:address":"Izenbergestraat 167",
    "sg:city":"Alveringem",
    "sg:orig_category":"Eleveurs de bovins",
    "sg:phone":"+32 58 29 92 96",
    "sg:postcode":"8691",
    "sg:province":"West-Vlaanderen",
    "wof:name":"Noel Zoete",
    "wof:placetype":"venue"
},
  "geometry": {"coordinates":[2.6480140686,50.9930610657],"type":"Point"}
}