{
  "type": "Feature",
  "properties": {
    "iso:country":"BE",
    "sg:address":"Rue Entr\u00e9e Jacques 7",
    "sg:city":"Gembloux-sur-orneau (gembloux)",
    "sg:classifiers":[
        {
            "category":"Professional",
            "subcategory":"Detective & Security Services",
            "type":"Services"
        }
    ],
    "sg:phone":"+32 81 61 15 24",
    "sg:postcode":"5030",
    "sg:province":"Namur",
    "sg:tags":[
        "installation",
        "alarm",
        "-",
        "system"
    ],
    "wof:name":"Arc Express",
    "wof:placetype":"venue"
},
  "geometry": {"coordinates":[4.6884469986,50.5590133667],"type":"Point"}
}