{
  "type": "Feature",
  "properties": {
    "iso:country":"BE",
    "sg:address":"Avenue Seghers 74",
    "sg:city":"Koekelberg/koekelberg",
    "sg:orig_category":"Avocats and conseillers juridiques",
    "sg:phone":"+32 2 411 26 72",
    "sg:postcode":"1081",
    "sg:province":"Bruxelles-Capitale",
    "wof:name":"H.a. Peetermans",
    "wof:placetype":"venue"
},
  "geometry": {"coordinates":[4.3203668594,50.8637619019],"type":"Point"}
}