{
  "type": "Feature",
  "properties": {
    "addr:full":"Sint-denijslaan 177 Gent Oost-Vlaanderen 9000",
    "addr:housenumber":"177",
    "addr:postcode":"9000",
    "addr:street":"Oost-Vlaanderen",
    "iso:country":"BE",
    "sg:address":"Sint-denijslaan 177",
    "sg:city":"Gent",
    "sg:classifiers":[
        {
            "category":"Cafe",
            "type":"Food & Drink"
        }
    ],
    "sg:phone":"+32 9 222 34 28",
    "sg:postcode":"9000",
    "sg:province":"Oost-Vlaanderen",
    "sg:tags":[
        "caf\u00e9s"
    ],
    "wof:name":"Waegeman-bettesone",
    "wof:placetype":"venue"
},
  "geometry": {"coordinates":[3.7088079453,51.0349349976],"type":"Point"}
}