{
  "type": "Feature",
  "properties": {
    "addr:full":"Lodderstraat 8 Bornem (hingene) Antwerpen 2880",
    "addr:housenumber":"8",
    "addr:postcode":"2880",
    "addr:street":"Lodderstraat",
    "iso:country":"BE",
    "sg:address":"Lodderstraat 8",
    "sg:city":"Bornem (hingene)",
    "sg:classifiers":[
        {
            "category":"Home & Garden",
            "subcategory":"Home Furnishings",
            "type":"Retail Goods"
        }
    ],
    "sg:phone":"+32 3 889 81 18",
    "sg:postcode":"2880",
    "sg:province":"Antwerpen",
    "sg:tags":[
        "-",
        "furniture"
    ],
    "wof:name":"Rotan Van De Vliet Nv",
    "wof:placetype":"venue"
},
  "geometry": {"coordinates":[4.2745609283,51.0872917175],"type":"Point"}
}