{
  "type": "Feature",
  "properties": {
    "addr:full":"Rue De L'eglise 21bc Spa Li\u00e8ge 4900",
    "addr:housenumber":"21bc",
    "addr:postcode":"4900",
    "addr:street":"Rue De L'Eglise",
    "iso:country":"BE",
    "sg:address":"Rue De L'eglise 21bc",
    "sg:city":"Spa",
    "sg:orig_category":"Avocats and conseillers juridiques",
    "sg:phone":"+32 87 77 20 94",
    "sg:postcode":"4900",
    "sg:province":"Li\u00e8ge",
    "wof:name":"Annette Lecloux",
    "wof:placetype":"venue"
},
  "geometry": {"coordinates":[5.8635501862,50.4911689758],"type":"Point"}
}