{
  "type": "Feature",
  "properties": {
    "addr:full":"Rue De La Reunion 2 Mons Hainaut 7000",
    "addr:housenumber":"2",
    "addr:postcode":"7000",
    "addr:street":"Rue De La Reunion;Hainaut",
    "iso:country":"BE",
    "sg:address":"Rue De La Reunion 2",
    "sg:city":"Mons",
    "sg:classifiers":[
        {
            "category":"Professional",
            "subcategory":"Business Services",
            "type":"Services"
        }
    ],
    "sg:phone":"+32 65 40 17 00",
    "sg:postcode":"7000",
    "sg:province":"Hainaut",
    "sg:tags":[
        "consulting",
        "export"
    ],
    "wof:name":"Chambre De Commerce Et D'industrie Du Hainaut Si\u00e8ge Mons - Borinage A. S.b.l.",
    "wof:placetype":"venue"
},
  "geometry": {"coordinates":[3.9477350712,50.4528961182],"type":"Point"}
}