{
  "type": "Feature",
  "properties": {
    "addr:full":"De Becker-remyplein 18 Leuven Vlaams-Brabant 3010",
    "addr:housenumber":"18",
    "addr:postcode":"3010",
    "iso:country":"BE",
    "sg:address":"De Becker-remyplein 18",
    "sg:city":"Leuven",
    "sg:orig_category":"Banques and organismes de cr\u00e9dit",
    "sg:phone":"+32 16 35 05 01",
    "sg:postcode":"3010",
    "sg:province":"Vlaams-Brabant",
    "wof:name":"Centea",
    "wof:placetype":"venue"
},
  "geometry": {"coordinates":[4.7304501534,50.889755249],"type":"Point"}
}