{
  "type": "Feature",
  "properties": {
    "iso:country":"BE",
    "sg:address":"Blijkheerstraat 10",
    "sg:city":"Gooik",
    "sg:orig_category":"Plomberie, chauffage and installations sanitaires",
    "sg:phone":"+32 54 56 83 22",
    "sg:postcode":"1755",
    "sg:province":"Vlaams-Brabant",
    "wof:name":"Dirk Albert Dakwerken",
    "wof:placetype":"venue"
},
  "geometry": {"coordinates":[4.0537018776,50.7717285156],"type":"Point"}
}