{
  "type": "Feature",
  "properties": {
    "addr:full":"Meerskant 30 Laarne Oost-Vlaanderen 9270",
    "addr:housenumber":"30",
    "addr:postcode":"9270",
    "addr:street":"Meerskant",
    "iso:country":"BE",
    "sg:address":"Meerskant 30",
    "sg:city":"Laarne",
    "sg:classifiers":[
        {
            "category":"Health Services",
            "subcategory":"Health Practitioner",
            "type":"Services"
        }
    ],
    "sg:phone":"+32 9 231 64 38",
    "sg:postcode":"9270",
    "sg:province":"Oost-Vlaanderen",
    "sg:tags":[
        "therapist",
        "speech"
    ],
    "wof:name":"Praet M",
    "wof:placetype":"venue"
},
  "geometry": {"coordinates":[3.8351800442,51.0499801636],"type":"Point"}
}