{
  "type": "Feature",
  "properties": {
    "iso:country":"BE",
    "sg:address":"Nieuwe Dreef 37",
    "sg:city":"Beerse",
    "sg:classifiers":[
        {
            "category":"Manufacturing",
            "subcategory":"Metals",
            "type":"Manufacturing & Wholesale Goods"
        }
    ],
    "sg:phone":"+32 14 60 95 06",
    "sg:postcode":"2340",
    "sg:province":"Antwerpen",
    "sg:tags":[
        "metallurgy",
        "steel",
        "metalworking"
    ],
    "wof:name":"Coordinatiecentrum Concorde Services Nv",
    "wof:placetype":"venue"
},
  "geometry": {"coordinates":[4.8176598549,51.3172492981],"type":"Point"}
}