{
  "type": "Feature",
  "properties": {
    "iso:country":"BE",
    "sg:address":"Oostnieuwkerksesteenweg 8",
    "sg:city":"Roeselare",
    "sg:orig_category":"Plaatsen van vloer- and muurbekleding Schilders",
    "sg:phone":"+32 51 20 67 29",
    "sg:postcode":"8800",
    "sg:province":"West-Vlaanderen",
    "wof:name":"Huis Degryse",
    "wof:placetype":"venue"
},
  "geometry": {"coordinates":[3.1086230278,50.9480400085],"type":"Point"}
}