{
  "type": "Feature",
  "properties": {
    "addr:full":"Rue De Collarmont 56 Morlanwelz Hainaut 7141",
    "addr:housenumber":"56",
    "addr:postcode":"7141",
    "addr:street":"Rue De Collarmont",
    "iso:country":"BE",
    "sg:address":"Rue De Collarmont 56",
    "sg:city":"Morlanwelz",
    "sg:orig_category":"Secr\u00e9tariats. Composition and photogravure",
    "sg:phone":"+32 64 45 02 49",
    "sg:postcode":"7141",
    "sg:province":"Hainaut",
    "wof:name":"Objectif Photocomposition",
    "wof:placetype":"venue"
},
  "geometry": {"coordinates":[4.2556858063,50.4332313538],"type":"Point"}
}