{
  "type": "Feature",
  "properties": {
    "addr:full":"Kerkweg 39 Wielsbeke (ooigem) West-Vlaanderen 8710",
    "addr:housenumber":"39",
    "addr:postcode":"8710",
    "addr:street":"Kerkweg",
    "iso:country":"BE",
    "sg:address":"Kerkweg 39",
    "sg:city":"Wielsbeke (ooigem)",
    "sg:classifiers":[
        {
            "category":"Health Services",
            "subcategory":"Dentist",
            "type":"Services"
        }
    ],
    "sg:phone":"+32 56 66 85 40",
    "sg:postcode":"8710",
    "sg:province":"West-Vlaanderen",
    "wof:name":"Walcarius D",
    "wof:placetype":"venue"
},
  "geometry": {"coordinates":[3.331731081,50.8962783813],"type":"Point"}
}