{
  "type": "Feature",
  "properties": {
    "iso:country":"BE",
    "sg:address":"Place Victor Horta 67",
    "sg:city":"Ottignies-louvain-la-neuve (louvain-la-neuve)",
    "sg:classifiers":[
        {
            "category":"Retail",
            "subcategory":"Event Space",
            "type":"Services"
        }
    ],
    "sg:phone":"+32 10 45 79 81",
    "sg:postcode":"1348",
    "sg:province":"Brabant Wallon",
    "sg:tags":[
        "organisation"
    ],
    "wof:name":"Yellow Events",
    "wof:placetype":"venue"
},
  "geometry": {"coordinates":[4.6074800491,50.6633415222],"type":"Point"}
}