{
  "type": "Feature",
  "properties": {
    "addr:full":"Warandestraat 87 Turnhout Antwerpen 2300",
    "addr:housenumber":"87",
    "addr:postcode":"2300",
    "addr:street":"Warandestraat",
    "iso:country":"BE",
    "sg:address":"Warandestraat 87",
    "sg:city":"Turnhout",
    "sg:classifiers":[
        {
            "category":"Insurance",
            "subcategory":"Life Insurance",
            "type":"Services"
        }
    ],
    "sg:phone":"+32 14 42 53 32",
    "sg:postcode":"2300",
    "sg:province":"Antwerpen",
    "sg:tags":[
        "assurance"
    ],
    "wof:name":"Bureau Neefs Paul",
    "wof:placetype":"venue"
},
  "geometry": {"coordinates":[4.9413108826,51.3240318298],"type":"Point"}
}