{
  "type": "Feature",
  "properties": {
    "iso:country":"BE",
    "sg:address":"Aartrijkestraat 7",
    "sg:city":"Ichtegem",
    "sg:orig_category":"Peinture. Rev\u00eatements pour sols and murs",
    "sg:phone":"+32 59 29 06 72",
    "sg:postcode":"8480",
    "sg:province":"West-Vlaanderen",
    "wof:name":"Franck Vandewalle",
    "wof:placetype":"venue"
},
  "geometry": {"coordinates":[3.0276370049,51.1292457581],"type":"Point"}
}