{
  "type": "Feature",
  "properties": {
    "iso:country":"BE",
    "sg:address":"Place Verte 14",
    "sg:city":"Florennes",
    "sg:orig_category":"Bloemen and planten",
    "sg:phone":"+32 71 68 98 64",
    "sg:postcode":"5620",
    "sg:province":"Namur",
    "wof:name":"Florel",
    "wof:placetype":"venue"
},
  "geometry": {"coordinates":[4.605284214,50.2495079041],"type":"Point"}
}