{
  "type": "Feature",
  "properties": {
    "addr:full":"Paaistraat 5-11 Lier Antwerpen 2500",
    "addr:housenumber":"5-11",
    "addr:postcode":"2500",
    "addr:street":"Paaistraat",
    "iso:country":"BE",
    "sg:address":"Paaistraat 5-11",
    "sg:city":"Lier",
    "sg:orig_category":"Meubles Fab",
    "sg:phone":"+32 3 840 66 01",
    "sg:postcode":"2500",
    "sg:province":"Antwerpen",
    "wof:name":"Jvr Meubel",
    "wof:placetype":"venue"
},
  "geometry": {"coordinates":[4.5588731766,51.1509590149],"type":"Point"}
}