{
  "type": "Feature",
  "properties": {
    "addr:full":"Dorp 37 Herselt Antwerpen 2230",
    "addr:housenumber":"37",
    "addr:postcode":"2230",
    "addr:street":"Dorp",
    "iso:country":"BE",
    "sg:address":"Dorp 37",
    "sg:city":"Herselt",
    "sg:orig_category":"Verlichting and huishoudartikelen",
    "sg:phone":"+32 14 54 41 28",
    "sg:postcode":"2230",
    "sg:province":"Antwerpen",
    "wof:name":"Huis Bergen",
    "wof:placetype":"venue"
},
  "geometry": {"coordinates":[4.8806462288,51.0521392822],"type":"Point"}
}