{
  "type": "Feature",
  "properties": {
    "iso:country":"BE",
    "sg:address":"Rue De La Lib\u00c9ration 6",
    "sg:city":"Anthisnes",
    "sg:orig_category":"Entretien and r\u00e9parations de voitures",
    "sg:phone":"+32 4 383 65 98",
    "sg:postcode":"4160",
    "sg:province":"Li\u00e8ge",
    "wof:name":"Andre Jacques",
    "wof:placetype":"venue"
},
  "geometry": {"coordinates":[5.5144481659,50.4746170044],"type":"Point"}
}