{
  "type": "Feature",
  "properties": {
    "iso:country":"BE",
    "sg:address":"Alsembergse Steenweg 1207",
    "sg:city":"Ukkel/uccle",
    "sg:classifiers":[
        {
            "category":"Fast Food",
            "type":"Food & Drink"
        }
    ],
    "sg:phone":"+32 2 332 04 48",
    "sg:postcode":"1180",
    "sg:province":"Bruxelles-Capitale",
    "sg:tags":[
        "meeneem",
        "restaurant"
    ],
    "wof:name":"Friterie",
    "wof:placetype":"venue"
},
  "geometry": {"coordinates":[4.3287978172,50.7859382629],"type":"Point"}
}