{
  "type": "Feature",
  "properties": {
    "iso:country":"BE",
    "sg:address":"Rue De Pont \u00e0 Celles 5",
    "sg:city":"Courcelles (trazegnies)",
    "sg:classifiers":[
        {
            "category":"Personal",
            "subcategory":"Beauty Salon",
            "type":"Services"
        }
    ],
    "sg:phone":"+32 71 45 19 08",
    "sg:postcode":"6183",
    "sg:province":"Hainaut",
    "sg:tags":[
        "lady",
        "-",
        "hairdressing"
    ],
    "wof:name":"Pierquin M",
    "wof:placetype":"venue"
},
  "geometry": {"coordinates":[4.3360800743,50.4682197571],"type":"Point"}
}