{
  "type": "Feature",
  "properties": {
    "iso:country":"BE",
    "sg:address":"Rue De La Lib\u00c9ration 20bb",
    "sg:city":"Hastiere",
    "sg:orig_category":"Dansscholen",
    "sg:phone":"+32 82 64 48 86",
    "sg:postcode":"5540",
    "sg:province":"Namur",
    "wof:name":"Acad\u00c9mie De Danse Class.",
    "wof:placetype":"venue"
},
  "geometry": {"coordinates":[4.814218998,50.1954574585],"type":"Point"}
}