{
  "type": "Feature",
  "properties": {
    "addr:full":"Riemewegel 90 Evergem Oost-Vlaanderen 9940",
    "addr:housenumber":"90",
    "addr:postcode":"9940",
    "addr:street":"Riemewegel;Oost-Vlaanderen",
    "iso:country":"BE",
    "sg:address":"Riemewegel 90",
    "sg:city":"Evergem",
    "sg:orig_category":"Eleveurs de bovins",
    "sg:phone":"+32 9 344 01 10",
    "sg:postcode":"9940",
    "sg:province":"Oost-Vlaanderen",
    "wof:name":"Johan Van Hoecke",
    "wof:placetype":"venue"
},
  "geometry": {"coordinates":[3.7834210396,51.1732063293],"type":"Point"}
}