{
  "type": "Feature",
  "properties": {
    "addr:full":"Rue Des Brasseurs 61 Namur Namur 5000",
    "addr:housenumber":"61",
    "addr:postcode":"5000",
    "addr:street":"Rue Des Brasseurs",
    "iso:country":"BE",
    "sg:address":"Rue Des Brasseurs 61",
    "sg:city":"Namur",
    "sg:orig_category":"Catering and organisatie van feesten Fast food and meeneem restaurants Restaurants",
    "sg:phone":"+32 81 22 66 97",
    "sg:postcode":"5000",
    "sg:province":"Namur",
    "wof:name":"Aux Petits Brasseurs",
    "wof:placetype":"venue"
},
  "geometry": {"coordinates":[4.8653731346,50.4619789124],"type":"Point"}
}