{
  "type": "Feature",
  "properties": {
    "addr:full":"Mullemstraat 1 Waregem West-Vlaanderen 8793",
    "addr:housenumber":"1",
    "addr:postcode":"8793",
    "addr:street":"Mullemstraat",
    "iso:country":"BE",
    "sg:address":"Mullemstraat 1",
    "sg:city":"Waregem",
    "sg:orig_category":"Artistes ind\u00e9pendants",
    "sg:phone":"+32 56 60 34 54",
    "sg:postcode":"8793",
    "sg:province":"West-Vlaanderen",
    "wof:name":"Jozefa Seynaeve",
    "wof:placetype":"venue"
},
  "geometry": {"coordinates":[3.3887169361,50.8988723755],"type":"Point"}
}