{
  "type": "Feature",
  "properties": {
    "addr:full":"Ree\u00ebnlaan 46 Heusden-zolder (zolder) Limburg 3550",
    "addr:housenumber":"46",
    "addr:postcode":"3550",
    "addr:street":"Reee\u0308Nlaan",
    "iso:country":"BE",
    "sg:address":"Ree\u00ebnlaan 46",
    "sg:city":"Heusden-zolder (zolder)",
    "sg:classifiers":[
        {
            "category":"Personal",
            "subcategory":"Beauty Salon",
            "type":"Services"
        }
    ],
    "sg:phone":"+32 11 87 39 99",
    "sg:postcode":"3550",
    "sg:province":"Limburg",
    "sg:tags":[
        "product",
        "-",
        "apparatus"
    ],
    "wof:name":"Bruno Vassari Cosmetics",
    "wof:placetype":"venue"
},
  "geometry": {"coordinates":[5.267996788,50.9877052307],"type":"Point"}
}