{
  "type": "Feature",
  "properties": {
    "iso:country":"BE",
    "sg:address":"Zi Tournai-ouest",
    "sg:city":"Orcq-tournai",
    "sg:classifiers":[
        {
            "category":"Professional",
            "type":"Services"
        }
    ],
    "sg:phone":"+32 69 21 32 13",
    "sg:postcode":"7501",
    "sg:province":"Hainaut",
    "sg:tags":[
        "transport",
        "road"
    ],
    "wof:name":"Byl Transports Sa",
    "wof:placetype":"venue"
},
  "geometry": {"coordinates":[3.3437800407,50.6033706665],"type":"Point"}
}