{
  "type": "Feature",
  "properties": {
    "iso:country":"BE",
    "sg:address":"Rue Henri Van Hamme 125a",
    "sg:city":"Evere",
    "sg:orig_category":"Travaux d'isolation",
    "sg:phone":"+32 2 242 99 07",
    "sg:postcode":"1140",
    "sg:province":"Bruxelles-Capitale",
    "wof:name":"C.g. Gokas",
    "wof:placetype":"venue"
},
  "geometry": {"coordinates":[4.3977298737,50.8764762878],"type":"Point"}
}