{
  "type": "Feature",
  "properties": {
    "addr:full":"Erasme Ruelensvest 157 Leuven (heverlee) Vlaams-Brabant 3001",
    "addr:housenumber":"157",
    "addr:postcode":"3001",
    "addr:street":"Erasme Ruelensvest",
    "iso:country":"BE",
    "sg:address":"Erasme Ruelensvest 157",
    "sg:city":"Leuven (heverlee)",
    "sg:classifiers":[
        {
            "category":"Parking",
            "subcategory":"Garage",
            "type":"Transportation"
        }
    ],
    "sg:phone":"+32 16 28 49 90",
    "sg:postcode":"3001",
    "sg:province":"Vlaams-Brabant",
    "sg:tags":[
        "truck",
        "-",
        "dump",
        "transport"
    ],
    "wof:name":"Makatra Transportcentrale Bvba",
    "wof:placetype":"venue"
},
  "geometry": {"coordinates":[4.7065520287,50.8684997559],"type":"Point"}
}