{
  "type": "Feature",
  "properties": {
    "iso:country":"BE",
    "sg:address":"Tybaartstraat 2",
    "sg:city":"Sint-gillis-waas",
    "sg:orig_category":"Afbraak- and draineerwerken Woningbouw",
    "sg:phone":"+32 3 707 06 04",
    "sg:postcode":"9170",
    "sg:province":"Oost-Vlaanderen",
    "wof:name":"A.m.g.",
    "wof:placetype":"venue"
},
  "geometry": {"coordinates":[4.1110401154,51.2181015015],"type":"Point"}
}