{
  "type": "Feature",
  "properties": {
    "addr:full":"Halstraat 101 Heusden-zolder Limburg 3550",
    "addr:housenumber":"101",
    "addr:postcode":"3550",
    "addr:street":"Halstraat",
    "iso:country":"BE",
    "sg:address":"Halstraat 101",
    "sg:city":"Heusden-zolder",
    "sg:orig_category":"M\u00e9decins and sp\u00e9cialistes",
    "sg:phone":"+32 11 57 44 44",
    "sg:postcode":"3550",
    "sg:province":"Limburg",
    "wof:name":"C. Demeer",
    "wof:placetype":"venue"
},
  "geometry": {"coordinates":[5.3103981018,51.0499801636],"type":"Point"}
}