{
  "type": "Feature",
  "properties": {
    "iso:country":"BE",
    "sg:address":"Zandvoortstr 4",
    "sg:city":"Mechelen",
    "sg:classifiers":[
        {
            "category":"Manufacturing",
            "subcategory":"Tools & Machinery",
            "type":"Manufacturing & Wholesale Goods"
        }
    ],
    "sg:phone":"+32 15 29 46 11",
    "sg:postcode":"2800",
    "sg:province":"Antwerpen",
    "sg:tags":[
        "metallurgy",
        "metalworking"
    ],
    "wof:name":"Pitney Bowes Management Services Nv",
    "wof:placetype":"venue"
},
  "geometry": {"coordinates":[4.4465351105,51.0512313843],"type":"Point"}
}