{
  "type": "Feature",
  "properties": {
    "iso:country":"BE",
    "sg:address":"Assebroeklaan 88",
    "sg:city":"Brugge",
    "sg:orig_category":"Avocats and conseillers juridiques",
    "sg:phone":"+32 50 35 43 41",
    "sg:postcode":"8310",
    "sg:province":"West-Vlaanderen",
    "wof:name":"L. Verhoyen",
    "wof:placetype":"venue"
},
  "geometry": {"coordinates":[3.2470800877,51.2075538635],"type":"Point"}
}