{
  "type": "Feature",
  "properties": {
    "addr:full":"Rue Des Wagnons 50 Qui\u00e9vrain Hainaut 7380",
    "addr:housenumber":"50",
    "addr:postcode":"7380",
    "addr:street":"Rue Des Wagnons",
    "iso:country":"BE",
    "sg:address":"Rue Des Wagnons 50",
    "sg:city":"Qui\u00e9vrain",
    "sg:classifiers":[
        {
            "category":"Real Estate",
            "subcategory":"Surveying",
            "type":"Services"
        }
    ],
    "sg:phone":"+32 65 46 52 05",
    "sg:postcode":"7380",
    "sg:province":"Hainaut",
    "sg:tags":[
        "surveyor",
        "land"
    ],
    "wof:name":"Dehon O",
    "wof:placetype":"venue"
},
  "geometry": {"coordinates":[3.684210062,50.4027824402],"type":"Point"}
}