{
  "type": "Feature",
  "properties": {
    "iso:country":"BE",
    "sg:address":"Zone C Zoning",
    "sg:city":"Seneffe",
    "sg:orig_category":"Entretien and r\u00e9parations de voitures",
    "sg:phone":"+32 64 51 68 11",
    "sg:postcode":"7180",
    "sg:province":"Hainaut",
    "wof:name":"Axial",
    "wof:placetype":"venue"
},
  "geometry": {"coordinates":[4.2591218948,50.5296554565],"type":"Point"}
}