{
  "type": "Feature",
  "properties": {
    "addr:full":"Obusstraat 165 Anderlecht/anderlecht Bruxelles-Capitale 1070",
    "addr:housenumber":"165",
    "addr:postcode":"1070",
    "addr:street":"Obusstraat",
    "iso:country":"BE",
    "sg:address":"Obusstraat 165",
    "sg:city":"Anderlecht/anderlecht",
    "sg:orig_category":"Etalage- and showroomontwerpers",
    "sg:phone":"+32 2 522 19 60",
    "sg:postcode":"1070",
    "sg:province":"Bruxelles-Capitale",
    "wof:name":"Valerie Everaert",
    "wof:placetype":"venue"
},
  "geometry": {"coordinates":[4.3060731888,50.8419494629],"type":"Point"}
}