{
  "type": "Feature",
  "properties": {
    "iso:country":"BE",
    "sg:address":"Poeleweg 18",
    "sg:city":"Kasterlee (lichtaart)",
    "sg:classifiers":[
        {
            "category":"Banks & Credit Unions",
            "subcategory":"Investment Brokerage",
            "type":"Services"
        }
    ],
    "sg:phone":"+32 14 55 35 82",
    "sg:postcode":"2460",
    "sg:province":"Antwerpen",
    "sg:tags":[
        "repair",
        "-",
        "installation",
        "sanitary",
        "article"
    ],
    "wof:name":"Be Sanitair & Verwarming Bvba",
    "wof:placetype":"venue"
},
  "geometry": {"coordinates":[4.9188089371,51.2214622498],"type":"Point"}
}