{
  "type": "Feature",
  "properties": {
    "iso:country":"BE",
    "sg:address":"Avenue De La Biche 38",
    "sg:city":"Rixensart (genval)",
    "sg:classifiers":[
        {
            "category":"Social Services",
            "subcategory":"Job Training",
            "type":"Services"
        }
    ],
    "sg:phone":"+32 2 653 40 08",
    "sg:postcode":"1332",
    "sg:province":"Brabant Wallon",
    "sg:tags":[
        "personnel"
    ],
    "wof:name":"Demca Training And Consulting",
    "wof:placetype":"venue"
},
  "geometry": {"coordinates":[4.5101408958,50.7280464172],"type":"Point"}
}