{
  "type": "Feature",
  "properties": {
    "iso:country":"BE",
    "sg:address":"Rue Ternard 77",
    "sg:city":"Tubize",
    "sg:classifiers":[
        {
            "category":"Manufacturing",
            "subcategory":"Paper Products",
            "type":"Manufacturing & Wholesale Goods"
        }
    ],
    "sg:phone":"+32 2 355 79 61",
    "sg:postcode":"1480",
    "sg:province":"Brabant Wallon",
    "sg:tags":[
        "bag"
    ],
    "wof:name":"Frantschach Packaging Holding Belgium",
    "wof:placetype":"venue"
},
  "geometry": {"coordinates":[4.2047572136,50.6855201721],"type":"Point"}
}