{
  "type": "Feature",
  "properties": {
    "iso:country":"BE",
    "sg:address":"Brugsesteenweg 2",
    "sg:city":"Blankenberge",
    "sg:orig_category":"HERSTELLING ELEKTRISCHE HUISHOUDAPPARATEN Huishoudapparaten, televisies and radio's Telecommunicatie",
    "sg:phone":"+32 50 42 60 30",
    "sg:postcode":"8370",
    "sg:province":"West-Vlaanderen",
    "wof:name":"Electro Van Besien J.",
    "wof:placetype":"venue"
},
  "geometry": {"coordinates":[3.1343250275,51.3109512329],"type":"Point"}
}