{
  "type": "Feature",
  "properties": {
    "addr:full":"Rattevallestraat 25 Middelkerke West-Vlaanderen 8433",
    "addr:housenumber":"25",
    "addr:postcode":"8433",
    "addr:street":"Rattevallestraat",
    "iso:country":"BE",
    "sg:address":"Rattevallestraat 25",
    "sg:city":"Middelkerke",
    "sg:orig_category":"Binnenhuisarchitecten",
    "sg:phone":"+32 58 23 05 61",
    "sg:postcode":"8433",
    "sg:province":"West-Vlaanderen",
    "wof:name":"Frederik Blontrock",
    "wof:placetype":"venue"
},
  "geometry": {"coordinates":[2.8475210667,51.1547775269],"type":"Point"}
}