{
  "type": "Feature",
  "properties": {
    "iso:country":"BE",
    "sg:address":"Markt 88",
    "sg:city":"Deinze",
    "sg:classifiers":[
        {
            "category":"Utilities",
            "subcategory":"Telephone",
            "type":"Services"
        }
    ],
    "sg:postcode":"9800",
    "sg:province":"Oost-Vlaanderen",
    "sg:tags":[
        "-",
        "internet"
    ],
    "wof:name":"Gazet Van Deinze",
    "wof:placetype":"venue"
},
  "geometry": {"coordinates":[3.5249929428,50.9859619141],"type":"Point"}
}