{
  "type": "Feature",
  "properties": {
    "iso:country":"BE",
    "sg:address":"Route De Beaumont 39",
    "sg:city":"Lasne",
    "sg:orig_category":"Boekhouders",
    "sg:phone":"+32 2 633 41 36",
    "sg:postcode":"1380",
    "sg:province":"Brabant Wallon",
    "wof:name":"Marc Warreyn",
    "wof:placetype":"venue"
},
  "geometry": {"coordinates":[4.4971790314,50.6701126099],"type":"Point"}
}