{
  "type": "Feature",
  "properties": {
    "addr:full":"Rue Ferrer 32 Morlanwelz Hainaut 7141",
    "addr:housenumber":"32",
    "addr:postcode":"7141",
    "addr:street":"Rue Ferrer",
    "iso:country":"BE",
    "sg:address":"Rue Ferrer 32",
    "sg:city":"Morlanwelz",
    "sg:orig_category":"V\u00e9t\u00e9rinaires",
    "sg:phone":"+32 64 45 94 58",
    "sg:postcode":"7141",
    "sg:province":"Hainaut",
    "wof:name":"Nathalie Rassel",
    "wof:placetype":"venue"
},
  "geometry": {"coordinates":[4.2614507675,50.4515647888],"type":"Point"}
}