{
  "type": "Feature",
  "properties": {
    "addr:full":"Tervuursevest 58 Leuven Vlaams-Brabant 3000",
    "addr:housenumber":"58",
    "addr:postcode":"3000",
    "addr:street":"Tervuursevest",
    "iso:country":"BE",
    "sg:address":"Tervuursevest 58",
    "sg:city":"Leuven",
    "sg:orig_category":"Benzinestations and brandstoffen",
    "sg:phone":"+32 16 40 58 31",
    "sg:postcode":"3000",
    "sg:province":"Vlaams-Brabant",
    "wof:name":"Q8 Benzinestation",
    "wof:placetype":"venue"
},
  "geometry": {"coordinates":[4.6957259178,50.8696556091],"type":"Point"}
}