{
  "type": "Feature",
  "properties": {
    "iso:country":"BE",
    "sg:address":"Rue De La Hestre 111",
    "sg:city":"La Louviere",
    "sg:classifiers":[
        {
            "category":"Cafe",
            "type":"Food & Drink"
        }
    ],
    "sg:phone":"+32 64 26 21 83",
    "sg:postcode":"7100",
    "sg:province":"Hainaut",
    "sg:tags":[
        "caf\u00e9s"
    ],
    "wof:name":"Anne Godart",
    "wof:placetype":"venue"
},
  "geometry": {"coordinates":[4.1850848198,50.4748649597],"type":"Point"}
}