{
  "type": "Feature",
  "properties": {
    "iso:country":"BE",
    "sg:address":"Verviersstraat 15",
    "sg:city":"Antwerpen",
    "sg:classifiers":[
        {
            "category":"Organizations",
            "subcategory":"Community Association",
            "type":"Services"
        }
    ],
    "sg:phone":"+32 3 260 96 10",
    "sg:postcode":"2000",
    "sg:province":"Antwerpen",
    "sg:tags":[
        "cultural"
    ],
    "wof:name":"Villanella",
    "wof:placetype":"venue"
},
  "geometry": {"coordinates":[4.3873329163,51.2090377808],"type":"Point"}
}