{
  "type": "Feature",
  "properties": {
    "iso:country":"BE",
    "sg:address":"Demerstraat",
    "sg:city":"Lummen (linkhout)",
    "sg:classifiers":[
        {
            "category":"Government",
            "subcategory":"Office",
            "type":"Public Place"
        }
    ],
    "sg:phone":"+32 13 44 38 58",
    "sg:postcode":"3560",
    "sg:province":"Limburg",
    "sg:tags":[
        "-",
        "tourism",
        "federation"
    ],
    "wof:name":"Toerisme Midden-limburg Vzw I.s.m.-'vloot",
    "wof:placetype":"venue"
},
  "geometry": {"coordinates":[5.1396198273,50.963142395],"type":"Point"}
}