{
  "type": "Feature",
  "properties": {
    "addr:full":"Dorp-oost 77 Lochristi Oost-Vlaanderen 9080",
    "addr:housenumber":"77",
    "addr:postcode":"9080",
    "addr:street":"Dorp-Oost",
    "iso:country":"BE",
    "sg:address":"Dorp-oost 77",
    "sg:city":"Lochristi",
    "sg:classifiers":[
        {
            "category":"Retail",
            "subcategory":"Auto Repair",
            "type":"Services"
        }
    ],
    "sg:phone":"+32 9 355 52 41",
    "sg:postcode":"9080",
    "sg:province":"Oost-Vlaanderen",
    "sg:tags":[
        "garage"
    ],
    "wof:name":"Stubbe J",
    "wof:placetype":"venue"
},
  "geometry": {"coordinates":[3.8404700756,51.0983009338],"type":"Point"}
}