{
  "type": "Feature",
  "properties": {
    "iso:country":"BE",
    "sg:address":"Vagevuurstraat 88",
    "sg:city":"Menen",
    "sg:classifiers":[
        {
            "category":"Personal",
            "subcategory":"Beauty Salon",
            "type":"Services"
        }
    ],
    "sg:phone":"+32 56 41 87 93",
    "sg:postcode":"8930",
    "sg:province":"West-Vlaanderen",
    "sg:tags":[
        "de",
        "coiffure"
    ],
    "wof:name":"Coiffure St\u00c9phane",
    "wof:placetype":"venue"
},
  "geometry": {"coordinates":[3.1763129234,50.7589797974],"type":"Point"}
}