{
  "type": "Feature",
  "properties": {
    "addr:full":"Avenue Du Martin-p\u00cacheur 19b14 Watermaal-bosvoorde/watermael-boitsfort Bruxelles-Capitale 1170",
    "addr:housenumber":"19b14",
    "addr:postcode":"1170",
    "addr:street":"Avenue Du Martin-Pe\u0302Cheur",
    "iso:country":"BE",
    "sg:address":"Avenue Du Martin-p\u00cacheur 19b14",
    "sg:city":"Watermaal-bosvoorde/watermael-boitsfort",
    "sg:orig_category":"Administration d'immeubles",
    "sg:phone":"+32 2 673 08 79",
    "sg:postcode":"1170",
    "sg:province":"Bruxelles-Capitale",
    "wof:name":"Gestimass",
    "wof:placetype":"venue"
},
  "geometry": {"coordinates":[4.4023971558,50.8120689392],"type":"Point"}
}