{
  "type": "Feature",
  "properties": {
    "addr:full":"Rue Des Combattants 52 Bierges Brabant Wallon 1301",
    "addr:housenumber":"52;1301",
    "addr:street":"Rue Des Combattants",
    "iso:country":"BE",
    "sg:address":"Rue Des Combattants 52",
    "sg:city":"Bierges",
    "sg:classifiers":[
        {
            "category":"Wholesale",
            "subcategory":"Sporting Goods",
            "type":"Manufacturing & Wholesale Goods"
        }
    ],
    "sg:phone":"+32 10 41 21 41",
    "sg:postcode":"1301",
    "sg:province":"Brabant Wallon",
    "sg:tags":[
        "sport-",
        "kampeermateriaal"
    ],
    "wof:name":"Equi-passion Sellerie",
    "wof:placetype":"venue"
},
  "geometry": {"coordinates":[4.5810828209,50.7131156921],"type":"Point"}
}