{
  "type": "Feature",
  "properties": {
    "iso:country":"BE",
    "sg:address":"Scharestraat 4",
    "sg:city":"Ardooie",
    "sg:orig_category":"Varkenskwekers",
    "sg:phone":"+32 51 74 49 06",
    "sg:postcode":"8850",
    "sg:province":"West-Vlaanderen",
    "wof:name":"Andre Deforche",
    "wof:placetype":"venue"
},
  "geometry": {"coordinates":[3.1890659332,50.9859085083],"type":"Point"}
}