{
  "type": "Feature",
  "properties": {
    "iso:country":"BE",
    "sg:address":"Surdents 39",
    "sg:city":"Stembert (verviers)",
    "sg:orig_category":"Herstellingen and onderhoud van auto's",
    "sg:phone":"+32 87 35 58 89",
    "sg:postcode":"4801",
    "sg:province":"Li\u00e8ge",
    "wof:name":"Femacar Carrosserie",
    "wof:placetype":"venue"
},
  "geometry": {"coordinates":[5.9084768295,50.6080131531],"type":"Point"}
}