{
  "type": "Feature",
  "properties": {
    "iso:country":"BE",
    "sg:address":"Verbindingsstraat 5 Box A",
    "sg:city":"Wielsbeke",
    "sg:classifiers":[
        {
            "category":"Wholesale",
            "subcategory":"Hardware",
            "type":"Manufacturing & Wholesale Goods"
        }
    ],
    "sg:phone":"+32 56 66 60 28",
    "sg:postcode":"8710",
    "sg:province":"West-Vlaanderen",
    "sg:tags":[
        "lubricating",
        "compound"
    ],
    "wof:name":"Beel-vanden Avenne Nv",
    "wof:placetype":"venue"
},
  "geometry": {"coordinates":[3.3694550991,50.9095153809],"type":"Point"}
}