{
  "type": "Feature",
  "properties": {
    "iso:country":"BE",
    "sg:address":"Gijmelsesteenweg 268",
    "sg:city":"Aarschot",
    "sg:orig_category":"Location d'appareils audio-visuels",
    "sg:phone":"+32 16 56 55 08",
    "sg:postcode":"3201",
    "sg:province":"Vlaams-Brabant",
    "wof:name":"Fa. Who Cares",
    "wof:placetype":"venue"
},
  "geometry": {"coordinates":[4.8603157997,51.0090370178],"type":"Point"}
}