{
  "type": "Feature",
  "properties": {
    "addr:full":"Chauss\u00c9e De Mons 63 Ath Hainaut 7800",
    "addr:housenumber":"63",
    "addr:postcode":"7800",
    "addr:street":"Chausse\u0301E De Mons",
    "iso:country":"BE",
    "sg:address":"Chauss\u00c9e De Mons 63",
    "sg:city":"Ath",
    "sg:orig_category":"Boekhouders",
    "sg:postcode":"7800",
    "sg:province":"Hainaut",
    "wof:name":"Marie-fran\u00c7oise Masson",
    "wof:placetype":"venue"
},
  "geometry": {"coordinates":[3.7740049362,50.6247673035],"type":"Point"}
}