{
  "type": "Feature",
  "properties": {
    "addr:full":"Barcenal 12 Ciney Namur 5590",
    "addr:housenumber":"12",
    "addr:postcode":"5590",
    "addr:street":"Barcenal",
    "iso:country":"BE",
    "sg:address":"Barcenal 12",
    "sg:city":"Ciney",
    "sg:orig_category":"Editeurs d'enregistrements sonores",
    "sg:phone":"+32 83 21 76 51",
    "sg:postcode":"5590",
    "sg:province":"Namur",
    "wof:name":"Ciney Musique Session",
    "wof:placetype":"venue"
},
  "geometry": {"coordinates":[5.0910949707,50.275188446],"type":"Point"}
}