{
  "type": "Feature",
  "properties": {
    "iso:country":"BE",
    "sg:address":"Kerkstraat 75",
    "sg:city":"Kasterlee (tielen)",
    "sg:classifiers":[
        {
            "category":"Food & Beverages",
            "subcategory":"Groceries & Convenience Stores",
            "type":"Retail Goods"
        }
    ],
    "sg:phone":"+32 14 55 63 16",
    "sg:postcode":"2460",
    "sg:province":"Antwerpen",
    "sg:tags":[
        "grocer"
    ],
    "wof:name":"Spar-de Vershoek",
    "wof:placetype":"venue"
},
  "geometry": {"coordinates":[4.9039921761,51.2450408936],"type":"Point"}
}