{
  "type": "Feature",
  "properties": {
    "iso:country":"BE",
    "sg:address":"Rue Borrens 40",
    "sg:city":"Bruxelles (ixelles)",
    "sg:classifiers":[
        {
            "category":"Food & Beverages",
            "subcategory":"Chocolate",
            "type":"Retail Goods"
        }
    ],
    "sg:phone":"+32 2 647 04 37",
    "sg:postcode":"1050",
    "sg:province":"Bruxelles-Capitale",
    "sg:tags":[
        "confectionery",
        "-"
    ],
    "wof:name":"Vervacke",
    "wof:placetype":"venue"
},
  "geometry": {"coordinates":[4.3775911331,50.8264503479],"type":"Point"}
}