{
  "type": "Feature",
  "properties": {
    "addr:full":"Nati\u00ebnlaan 247 Knokke-heist (knokke) West-Vlaanderen 8300",
    "addr:housenumber":"247",
    "addr:postcode":"8300",
    "addr:street":"Natie\u0308Nlaan",
    "iso:country":"BE",
    "sg:address":"Nati\u00ebnlaan 247",
    "sg:city":"Knokke-heist (knokke)",
    "sg:classifiers":[
        {
            "category":"Manufacturing",
            "subcategory":"Furniture",
            "type":"Manufacturing & Wholesale Goods"
        }
    ],
    "sg:phone":"+32 50 60 60 60",
    "sg:postcode":"8300",
    "sg:province":"West-Vlaanderen",
    "sg:tags":[
        "design",
        "-"
    ],
    "wof:name":"Licht En Meubel Design",
    "wof:placetype":"venue"
},
  "geometry": {"coordinates":[3.2890501022,51.3361816406],"type":"Point"}
}