{
  "type": "Feature",
  "properties": {
    "iso:country":"BE",
    "sg:address":"Schoolstraat 27",
    "sg:city":"Gent",
    "sg:orig_category":"Enseignement maternel and primaire",
    "sg:phone":"+32 9 228 60 71",
    "sg:postcode":"9040",
    "sg:province":"Oost-Vlaanderen",
    "wof:name":"Basisschool Ten Berg",
    "wof:placetype":"venue"
},
  "geometry": {"coordinates":[3.7490160465,51.0597457886],"type":"Point"}
}