{
  "type": "Feature",
  "properties": {
    "iso:country":"BE",
    "sg:address":"Lijsterstraat 16",
    "sg:city":"Ardooie",
    "sg:orig_category":"Rev\u00eatements pour sols and murs. Peinture",
    "sg:phone":"+32 51 31 26 11",
    "sg:postcode":"8850",
    "sg:province":"West-Vlaanderen",
    "wof:name":"Geert Vanhoutte",
    "wof:placetype":"venue"
},
  "geometry": {"coordinates":[3.2079150677,50.9450492859],"type":"Point"}
}