{
  "type": "Feature",
  "properties": {
    "addr:full":"Place Des Chasseurs Ardennais 20 Bruxelles (schaerbeek) Bruxelles-Capitale 1030",
    "addr:housenumber":"20",
    "addr:postcode":"1030",
    "addr:street":"Place Des Chasseurs Ardennais",
    "iso:country":"BE",
    "sg:address":"Place Des Chasseurs Ardennais 20",
    "sg:city":"Bruxelles (schaerbeek)",
    "sg:classifiers":[
        {
            "category":"Professional",
            "subcategory":"Management & Consulting",
            "type":"Services"
        }
    ],
    "sg:phone":"+32 2 743 41 58",
    "sg:postcode":"1030",
    "sg:province":"Bruxelles-Capitale",
    "sg:tags":[
        "consultant"
    ],
    "wof:name":"Legal & Management Consultant Nv",
    "wof:placetype":"venue"
},
  "geometry": {"coordinates":[4.3902478218,50.8497047424],"type":"Point"}
}