{
  "type": "Feature",
  "properties": {
    "addr:full":"Scheldestraat 67 Zwevegem West-Vlaanderen 8553",
    "addr:housenumber":"67",
    "addr:postcode":"8553",
    "addr:street":"Scheldestraat",
    "iso:country":"BE",
    "sg:address":"Scheldestraat 67",
    "sg:city":"Zwevegem",
    "sg:orig_category":"Reliure and finition. Imprimeries and copyshops",
    "sg:phone":"+32 56 64 78 76",
    "sg:postcode":"8553",
    "sg:province":"West-Vlaanderen",
    "wof:name":"Sneldrukservice",
    "wof:placetype":"venue"
},
  "geometry": {"coordinates":[3.4302530289,50.7997283936],"type":"Point"}
}