{
  "type": "Feature",
  "properties": {
    "addr:full":"Jules Destr\u00e9elaan 29 Gent (gentbrugge) Oost-Vlaanderen 9050",
    "addr:housenumber":"29",
    "addr:postcode":"9050",
    "addr:street":"Destre\u0301Elaan",
    "iso:country":"BE",
    "sg:address":"Jules Destr\u00e9elaan 29",
    "sg:city":"Gent (gentbrugge)",
    "sg:classifiers":[
        {
            "category":"Health Services",
            "subcategory":"Health Practitioner",
            "type":"Services"
        }
    ],
    "sg:phone":"+32 9 231 46 98",
    "sg:postcode":"9050",
    "sg:province":"Oost-Vlaanderen",
    "sg:tags":[
        "therapist",
        "speech"
    ],
    "wof:name":"De Winter M",
    "wof:placetype":"venue"
},
  "geometry": {"coordinates":[3.7705519199,51.028301239],"type":"Point"}
}