{
  "type": "Feature",
  "properties": {
    "iso:country":"BE",
    "sg:address":"Chauss\u00e9e De Namur 332",
    "sg:city":"Gembloux-sur-orneau (beuzet)",
    "sg:classifiers":[
        {
            "category":"Shopping",
            "subcategory":"Antiques",
            "type":"Retail Goods"
        }
    ],
    "sg:phone":"+32 81 56 06 53",
    "sg:postcode":"5030",
    "sg:province":"Namur",
    "sg:tags":[
        "restoration"
    ],
    "wof:name":"Antiquit\u00e9s L'empire",
    "wof:placetype":"venue"
},
  "geometry": {"coordinates":[4.7371578217,50.5354232788],"type":"Point"}
}