{
  "type": "Feature",
  "properties": {
    "iso:country":"BE",
    "sg:address":"Chaussee De Chatelet 266",
    "sg:city":"Charleroi",
    "sg:orig_category":"Drukkerijen and copyshops",
    "sg:phone":"+32 71 58 78 54",
    "sg:postcode":"6042",
    "sg:province":"Hainaut",
    "wof:name":"Belgique Impression",
    "wof:placetype":"venue"
},
  "geometry": {"coordinates":[4.4490199089,50.4293518066],"type":"Point"}
}