{
  "type": "Feature",
  "properties": {
    "iso:country":"BE",
    "sg:address":"Rue Des Fusill\u00c9s 9",
    "sg:city":"Virton",
    "sg:orig_category":"Dierenartsen",
    "sg:phone":"+32 63 57 93 31",
    "sg:postcode":"6760",
    "sg:province":"Luxembourg",
    "wof:name":"Jean Dussard",
    "wof:placetype":"venue"
},
  "geometry": {"coordinates":[5.585832119,49.5780754089],"type":"Point"}
}