{
  "type": "Feature",
  "properties": {
    "addr:full":"Rue De Wynants 23 Bruxelles Bruxelles-Capitale 1000",
    "addr:housenumber":"23",
    "addr:postcode":"1000",
    "addr:street":"Rue De Wynants",
    "iso:country":"BE",
    "sg:address":"Rue De Wynants 23",
    "sg:city":"Bruxelles",
    "sg:classifiers":[
        {
            "category":"Professional",
            "subcategory":"Lawyer & Legal Services",
            "type":"Services"
        }
    ],
    "sg:phone":"+32 2 548 01 95",
    "sg:postcode":"1000",
    "sg:province":"Bruxelles-Capitale",
    "wof:name":"Chapelle Gr\u00e9gor",
    "wof:placetype":"venue"
},
  "geometry": {"coordinates":[4.3507180214,50.8355369568],"type":"Point"}
}