{
  "type": "Feature",
  "properties": {
    "addr:full":"Zogge 33 Hamme Oost-Vlaanderen 9220",
    "addr:housenumber":"33",
    "addr:postcode":"9220",
    "addr:street":"Zogge",
    "iso:country":"BE",
    "sg:address":"Zogge 33",
    "sg:city":"Hamme",
    "sg:classifiers":[
        {
            "category":"Shopping",
            "subcategory":"Bicycles & Sporting Goods",
            "type":"Retail Goods"
        }
    ],
    "sg:phone":"+32 52 47 41 85",
    "sg:postcode":"9220",
    "sg:province":"Oost-Vlaanderen",
    "sg:tags":[
        "tyre"
    ],
    "wof:name":"Van Kerckhove F",
    "wof:placetype":"venue"
},
  "geometry": {"coordinates":[4.1019320488,51.0793075562],"type":"Point"}
}