{
  "type": "Feature",
  "properties": {
    "iso:country":"BE",
    "sg:address":"Holstraat 19",
    "sg:city":"Gent",
    "sg:classifiers":[
        {
            "category":"Communications",
            "subcategory":"Film & Video Production",
            "type":"Services"
        }
    ],
    "sg:phone":"+32 9 269 99 66",
    "sg:postcode":"9000",
    "sg:province":"Oost-Vlaanderen",
    "sg:tags":[
        "multimedia",
        "-",
        "system"
    ],
    "wof:name":"Vartec",
    "wof:placetype":"venue"
},
  "geometry": {"coordinates":[3.7146189213,51.0540809631],"type":"Point"}
}