{
  "type": "Feature",
  "properties": {
    "addr:full":"Entrepotstraat 19 Sint-niklaas Oost-Vlaanderen 9100",
    "addr:housenumber":"19",
    "addr:postcode":"9100",
    "addr:street":"Entrepotstraat",
    "iso:country":"BE",
    "sg:address":"Entrepotstraat 19",
    "sg:city":"Sint-niklaas",
    "sg:classifiers":[
        {
            "category":"Professional",
            "type":"Services"
        }
    ],
    "sg:phone":"+32 3 777 87 88",
    "sg:postcode":"9100",
    "sg:province":"Oost-Vlaanderen",
    "sg:tags":[
        "packing",
        "-"
    ],
    "wof:name":"Van Den Branden",
    "wof:placetype":"venue"
},
  "geometry": {"coordinates":[4.1672339439,51.174987793],"type":"Point"}
}