{
  "type": "Feature",
  "properties": {
    "addr:full":"Grasmarkt 30 Brussel/bruxelles Bruxelles-Capitale 1000",
    "addr:housenumber":"30",
    "addr:postcode":"1000",
    "addr:street":"Grasmarkt;/",
    "iso:country":"BE",
    "sg:address":"Grasmarkt 30",
    "sg:city":"Brussel/bruxelles",
    "sg:orig_category":"Baby- and kinderkleding Babyspullen Dameskledingzaken",
    "sg:phone":"+32 2 511 24 82",
    "sg:postcode":"1000",
    "sg:province":"Bruxelles-Capitale",
    "wof:name":"Pr\u00c9maman",
    "wof:placetype":"venue"
},
  "geometry": {"coordinates":[4.3526058197,50.8478126526],"type":"Point"}
}