{
  "type": "Feature",
  "properties": {
    "iso:country":"BE",
    "sg:address":"Kievitsheide 3",
    "sg:city":"Rijkevorsel",
    "sg:classifiers":[
        {
            "category":"Home & Garden",
            "subcategory":"Building Materials",
            "type":"Retail Goods"
        }
    ],
    "sg:phone":"+32 3 309 26 81",
    "sg:postcode":"2310",
    "sg:province":"Antwerpen",
    "sg:tags":[
        "window"
    ],
    "wof:name":"Maegh R",
    "wof:placetype":"venue"
},
  "geometry": {"coordinates":[4.7860641479,51.3240623474],"type":"Point"}
}