{
  "type": "Feature",
  "properties": {
    "addr:full":"Molenstraat 86 Sint-katelijne-waver (onze-lieve-vrouw-waver) Antwerpen 2861",
    "addr:housenumber":"86",
    "addr:postcode":"2861",
    "addr:street":"Molenstraat",
    "iso:country":"BE",
    "sg:address":"Molenstraat 86",
    "sg:city":"Sint-katelijne-waver (onze-lieve-vrouw-waver)",
    "sg:classifiers":[
        {
            "category":"Wholesale",
            "subcategory":"Beer",
            "type":"Manufacturing & Wholesale Goods"
        }
    ],
    "sg:phone":"+32 15 75 79 65",
    "sg:postcode":"2861",
    "sg:province":"Antwerpen",
    "sg:tags":[
        "ale",
        "-"
    ],
    "wof:name":"Tielemans Eddy Bierhandel",
    "wof:placetype":"venue"
},
  "geometry": {"coordinates":[4.5918607712,51.063873291],"type":"Point"}
}