{
  "type": "Feature",
  "properties": {
    "iso:country":"BE",
    "sg:address":"Rue Du Monty 178",
    "sg:city":"Libin",
    "sg:classifiers":[
        {
            "category":"Health Services",
            "subcategory":"Health Practitioner",
            "type":"Services"
        }
    ],
    "sg:phone":"+32 61 65 56 07",
    "sg:postcode":"6890",
    "sg:province":"Luxembourg",
    "sg:tags":[
        "osteopath"
    ],
    "wof:name":"Baude M",
    "wof:placetype":"venue"
},
  "geometry": {"coordinates":[5.256456852,49.9857673645],"type":"Point"}
}