{
  "type": "Feature",
  "properties": {
    "iso:country":"BE",
    "sg:address":"Jan Van Rijswijcklaan 104",
    "sg:city":"Antwerpen",
    "sg:classifiers":[
        {
            "category":"Professional",
            "subcategory":"Management & Consulting",
            "type":"Services"
        }
    ],
    "sg:phone":"+32 3 248 68 55",
    "sg:postcode":"2018",
    "sg:province":"Antwerpen",
    "sg:tags":[
        "consultant"
    ],
    "wof:name":"Pro-actief Bvba",
    "wof:placetype":"venue"
},
  "geometry": {"coordinates":[4.4025330544,51.1946640015],"type":"Point"}
}