{
  "type": "Feature",
  "properties": {
    "iso:country":"BE",
    "sg:address":"Avenue Marie-jos\u00c9 100",
    "sg:city":"Sint-lambrechts-woluwe/woluwe-saint-lambert",
    "sg:orig_category":"M\u00e9decins and sp\u00e9cialistes",
    "sg:phone":"+32 2 735 07 69",
    "sg:postcode":"1200",
    "sg:province":"Bruxelles-Capitale",
    "wof:name":"Fiorella Brusco",
    "wof:placetype":"venue"
},
  "geometry": {"coordinates":[4.4091949463,50.8449058533],"type":"Point"}
}