{
  "type": "Feature",
  "properties": {
    "iso:country":"BE",
    "sg:address":"Avenue Paul Pastur 373",
    "sg:city":"Charleroi",
    "sg:orig_category":"Artsen and specialisten",
    "sg:phone":"+32 71 36 31 51",
    "sg:postcode":"6032",
    "sg:province":"Hainaut",
    "wof:name":"B\u00c9atrice Meert",
    "wof:placetype":"venue"
},
  "geometry": {"coordinates":[4.4233379364,50.3987579346],"type":"Point"}
}