{
  "type": "Feature",
  "properties": {
    "iso:country":"BE",
    "sg:address":"Avenue Gevaert 21",
    "sg:city":"Rixensart",
    "sg:orig_category":"Plomberie, chauffage and installations sanitaires",
    "sg:phone":"+32 2 653 84 86",
    "sg:postcode":"1332",
    "sg:province":"Brabant Wallon",
    "wof:name":"Fautray",
    "wof:placetype":"venue"
},
  "geometry": {"coordinates":[4.4974651337,50.7179641724],"type":"Point"}
}