{
  "type": "Feature",
  "properties": {
    "addr:full":"Chauss\u00e9e De Hal 149 Rhode-saint-gen\u00e8se Vlaams-Brabant 1640",
    "addr:housenumber":"149",
    "addr:postcode":"rhode-saint-gene\u0300se;1640",
    "addr:street":"Chausse\u0301E De Hal",
    "iso:country":"BE",
    "sg:address":"Chauss\u00e9e De Hal 149",
    "sg:city":"Rhode-saint-gen\u00e8se",
    "sg:classifiers":[
        {
            "category":"Communications",
            "type":"Services"
        }
    ],
    "sg:phone":"+32 2 381 05 57",
    "sg:postcode":"1640",
    "sg:province":"Vlaams-Brabant",
    "sg:tags":[
        "translator"
    ],
    "wof:name":"Vandebotermet",
    "wof:placetype":"venue"
},
  "geometry": {"coordinates":[4.3309869766,50.7373123169],"type":"Point"}
}