{
  "type": "Feature",
  "properties": {
    "iso:country":"BE",
    "sg:address":"Rue Du Coq 80",
    "sg:city":"Li\u00c8ge",
    "sg:orig_category":"M\u00e9decins and sp\u00e9cialistes",
    "sg:phone":"+32 4 226 30 05",
    "sg:postcode":"4000",
    "sg:province":"Li\u00e8ge",
    "wof:name":"L\u00c9on Leblanc",
    "wof:placetype":"venue"
},
  "geometry": {"coordinates":[5.5541849136,50.6466255188],"type":"Point"}
}