{
  "type": "Feature",
  "properties": {
    "iso:country":"BE",
    "sg:address":"Langemunte 25",
    "sg:city":"Lierde",
    "sg:orig_category":"Woningbouw",
    "sg:phone":"+32 55 42 22 05",
    "sg:postcode":"9570",
    "sg:province":"Oost-Vlaanderen",
    "wof:name":"Raphael De Wolf",
    "wof:placetype":"venue"
},
  "geometry": {"coordinates":[3.8464748859,50.8163146973],"type":"Point"}
}