{
  "type": "Feature",
  "properties": {
    "iso:country":"BE",
    "sg:address":"Bodegemstraat 15",
    "sg:city":"Ternat",
    "sg:orig_category":"Mat\u00e9riaux de construction Gr",
    "sg:phone":"+32 2 582 13 47",
    "sg:postcode":"1740",
    "sg:province":"Vlaams-Brabant",
    "wof:name":"De Marie",
    "wof:placetype":"venue"
},
  "geometry": {"coordinates":[4.1820011139,50.8698730469],"type":"Point"}
}