{
  "type": "Feature",
  "properties": {
    "iso:country":"BE",
    "sg:address":"Louizalaan 143",
    "sg:city":"Elsene",
    "sg:orig_category":"Chemicali\u00ebn Gh Farmaceutische bereidingen and geneesmiddelen Fab Technische and wetenschappelijke in",
    "sg:phone":"+32 2 535 63 11",
    "sg:postcode":"1050",
    "sg:province":"Bruxelles-Capitale",
    "wof:name":"Bayer",
    "wof:placetype":"venue"
},
  "geometry": {"coordinates":[4.3573069572,50.8343505859],"type":"Point"}
}