{
  "type": "Feature",
  "properties": {
    "addr:full":"Frans Van Cauwelaertlaan 179 Sint-niklaas Oost-Vlaanderen 9100",
    "addr:housenumber":"179",
    "addr:postcode":"9100",
    "addr:street":"Frans Van Cauwelaertlaan",
    "iso:country":"BE",
    "sg:address":"Frans Van Cauwelaertlaan 179",
    "sg:city":"Sint-niklaas",
    "sg:orig_category":"Diverse zakelijke dienstverlening",
    "sg:phone":"+32 3 776 90 77",
    "sg:postcode":"9100",
    "sg:province":"Oost-Vlaanderen",
    "wof:name":"Hoger Inst.kunstgeschied.",
    "wof:placetype":"venue"
},
  "geometry": {"coordinates":[4.1392641068,51.181728363],"type":"Point"}
}