{
  "type": "Feature",
  "properties": {
    "addr:full":"Dijkstraat 1ba Lokeren Oost-Vlaanderen 9160",
    "addr:housenumber":"1ba",
    "addr:postcode":"9160",
    "addr:street":"Dijkstraat",
    "iso:country":"BE",
    "sg:address":"Dijkstraat 1ba",
    "sg:city":"Lokeren",
    "sg:orig_category":"Verlichting and huishoudartikelen",
    "sg:phone":"+32 9 348 08 02",
    "sg:postcode":"9160",
    "sg:province":"Oost-Vlaanderen",
    "wof:name":"Tekna",
    "wof:placetype":"venue"
},
  "geometry": {"coordinates":[4.0152730942,51.0931053162],"type":"Point"}
}