{
  "type": "Feature",
  "properties": {
    "iso:country":"BE",
    "sg:address":"Aalterbaan 195",
    "sg:city":"Maldegem",
    "sg:orig_category":"Gespecialiseerde niet-residenti\u00eble bouw Loodgieterij, verwarming and sanitaire installaties",
    "sg:phone":"+32 50 71 22 14",
    "sg:postcode":"9990",
    "sg:province":"Oost-Vlaanderen",
    "wof:name":"Van Deynse",
    "wof:placetype":"venue"
},
  "geometry": {"coordinates":[3.4535219669,51.195854187],"type":"Point"}
}