{
  "type": "Feature",
  "properties": {
    "iso:country":"BE",
    "sg:address":"Hermelijn 18a",
    "sg:city":"Heist-op-den-berg (booischot)",
    "sg:classifiers":[
        {
            "category":"Home & Garden",
            "subcategory":"Furniture",
            "type":"Retail Goods"
        }
    ],
    "sg:phone":"+32 15 22 56 42",
    "sg:postcode":"2221",
    "sg:province":"Antwerpen",
    "sg:tags":[
        "small",
        "item",
        "-"
    ],
    "wof:name":"Scheirs J",
    "wof:placetype":"venue"
},
  "geometry": {"coordinates":[4.7739758492,51.0512428284],"type":"Point"}
}