{
  "type": "Feature",
  "properties": {
    "iso:country":"BE",
    "sg:address":"Knesselarestraat 182",
    "sg:city":"Beernem (oedelem)",
    "sg:classifiers":[
        {
            "category":"Bars & Pubs",
            "type":"Food & Drink"
        }
    ],
    "sg:phone":"+32 50 78 08 46",
    "sg:postcode":"8730",
    "sg:province":"West-Vlaanderen",
    "wof:name":"Den Hoorn",
    "wof:placetype":"venue"
},
  "geometry": {"coordinates":[3.3773429394,51.153755188],"type":"Point"}
}