{
  "type": "Feature",
  "properties": {
    "addr:full":"'s Herenbaan 91 Boom Antwerpen 2850",
    "addr:housenumber":"91",
    "addr:postcode":"2850",
    "addr:street":"' S Herenbaan",
    "iso:country":"BE",
    "sg:address":"'s Herenbaan 91",
    "sg:city":"Boom",
    "sg:classifiers":[
        {
            "category":"Health Services",
            "subcategory":"Doctor",
            "type":"Services"
        }
    ],
    "sg:phone":"+32 3 844 26 73",
    "sg:postcode":"2850",
    "sg:province":"Antwerpen",
    "sg:tags":[
        "medicinephysicians",
        "surgeon"
    ],
    "wof:name":"Henckes M",
    "wof:placetype":"venue"
},
  "geometry": {"coordinates":[4.3855428696,51.1022186279],"type":"Point"}
}