{
  "type": "Feature",
  "properties": {
    "addr:full":"Breestraat 62 Hasselt Limburg 3500",
    "addr:housenumber":"62",
    "addr:postcode":"3500",
    "addr:street":"Breestraat",
    "iso:country":"BE",
    "sg:address":"Breestraat 62",
    "sg:city":"Hasselt",
    "sg:classifiers":[
        {
            "category":"Real Estate",
            "subcategory":"Architect",
            "type":"Services"
        }
    ],
    "sg:phone":"+32 11 25 16 80",
    "sg:postcode":"3500",
    "sg:province":"Limburg",
    "wof:name":"Van Holm B",
    "wof:placetype":"venue"
},
  "geometry": {"coordinates":[5.3278541565,50.9368896484],"type":"Point"}
}