{
  "type": "Feature",
  "properties": {
    "iso:country":"BE",
    "sg:address":"Stationsstraat 1",
    "sg:city":"Aalst (erembodegem)",
    "sg:orig_category":"Non-Classified Establishments",
    "sg:phone":"+32 53 77 31 42",
    "sg:postcode":"9320",
    "sg:province":"Oost-Vlaanderen",
    "wof:name":"Polylight Belgium",
    "wof:placetype":"venue"
},
  "geometry": {"coordinates":[4.0370922089,50.9412994385],"type":"Point"}
}