{
  "type": "Feature",
  "properties": {
    "iso:country":"BE",
    "sg:address":"Boulevard Du Roi Albert 59",
    "sg:city":"Tournai",
    "sg:classifiers":[
        {
            "category":"Home & Garden",
            "subcategory":"Carpets & Floor Coverings",
            "type":"Retail Goods"
        }
    ],
    "sg:phone":"+32 69 35 33 73",
    "sg:postcode":"7500",
    "sg:province":"Hainaut",
    "sg:tags":[
        "tile"
    ],
    "wof:name":"Noppe E",
    "wof:placetype":"venue"
},
  "geometry": {"coordinates":[3.3955099583,50.6004486084],"type":"Point"}
}