{
  "type": "Feature",
  "properties": {
    "iso:country":"BE",
    "sg:address":"Plattanenlaan 70",
    "sg:city":"Zoersel",
    "sg:classifiers":[
        {
            "category":"Building & Trades",
            "subcategory":"Landscaping Services",
            "type":"Services"
        }
    ],
    "sg:phone":"+32 3 385 03 75",
    "sg:postcode":"2980",
    "sg:province":"Antwerpen",
    "sg:tags":[
        "etude",
        "technique",
        "ing\u00e9nierie"
    ],
    "wof:name":"Mertens W",
    "wof:placetype":"venue"
},
  "geometry": {"coordinates":[4.6631379128,51.2761573792],"type":"Point"}
}