{
  "type": "Feature",
  "properties": {
    "addr:full":"Schoutetstraat 4 Mechelen Antwerpen 2800",
    "addr:housenumber":"4",
    "addr:postcode":"2800",
    "addr:street":"Schoutetstraat",
    "iso:country":"BE",
    "sg:address":"Schoutetstraat 4",
    "sg:city":"Mechelen",
    "sg:classifiers":[
        {
            "category":"Home & Garden",
            "subcategory":"Home Furnishings",
            "type":"Retail Goods"
        }
    ],
    "sg:phone":"+32 15 21 02 60",
    "sg:postcode":"2800",
    "sg:province":"Antwerpen",
    "sg:tags":[
        "curtain",
        "-",
        "fixture"
    ],
    "wof:name":"Trendson Nv",
    "wof:placetype":"venue"
},
  "geometry": {"coordinates":[4.479323864,51.0308990479],"type":"Point"}
}