{
  "type": "Feature",
  "properties": {
    "addr:full":"Rue Du Moulin 51 Herbeumont (straimont) Luxembourg 6887",
    "addr:housenumber":"51",
    "addr:postcode":"6887",
    "addr:street":"Rue Du Moulin",
    "iso:country":"BE",
    "sg:address":"Rue Du Moulin 51",
    "sg:city":"Herbeumont (straimont)",
    "sg:classifiers":[
        {
            "category":"Health Services",
            "subcategory":"Health Practitioner",
            "type":"Services"
        }
    ],
    "sg:phone":"+32 61 27 91 82",
    "sg:postcode":"6887",
    "sg:province":"Luxembourg",
    "sg:tags":[
        "physiotherapist"
    ],
    "wof:name":"Poncin Fran\u00e7oise",
    "wof:placetype":"venue"
},
  "geometry": {"coordinates":[5.3827848434,49.7940139771],"type":"Point"}
}