{
  "type": "Feature",
  "properties": {
    "iso:country":"BE",
    "sg:address":"Boterstraat 30",
    "sg:city":"Ieper",
    "sg:classifiers":[
        {
            "category":"Food & Beverages",
            "subcategory":"Cheese",
            "type":"Retail Goods"
        }
    ],
    "sg:phone":"+32 57 20 19 15",
    "sg:postcode":"8900",
    "sg:province":"West-Vlaanderen",
    "sg:tags":[
        "-"
    ],
    "wof:name":"Kaashoeve (de)",
    "wof:placetype":"venue"
},
  "geometry": {"coordinates":[2.8831520081,50.8503761292],"type":"Point"}
}