{
  "type": "Feature",
  "properties": {
    "addr:full":"Durasweg 1 Zoutleeuw Vlaams-Brabant 3440",
    "addr:housenumber":"1",
    "addr:postcode":"3440",
    "addr:street":"Durasweg;Vlaams-Brabant",
    "iso:country":"BE",
    "sg:address":"Durasweg 1",
    "sg:city":"Zoutleeuw",
    "sg:classifiers":[
        {
            "category":"Cafe",
            "type":"Food & Drink"
        }
    ],
    "sg:phone":"+32 11 78 12 52",
    "sg:postcode":"3440",
    "sg:province":"Vlaams-Brabant",
    "sg:tags":[
        "caf\u00e9s"
    ],
    "wof:name":"Miranda Degeest",
    "wof:placetype":"venue"
},
  "geometry": {"coordinates":[5.1376519203,50.8500404358],"type":"Point"}
}