{
  "type": "Feature",
  "properties": {
    "addr:full":"Corbiestraat 28 Mol Antwerpen 2400",
    "addr:housenumber":"28",
    "addr:postcode":"2400",
    "addr:street":"Corbiestraat",
    "iso:country":"BE",
    "sg:address":"Corbiestraat 28",
    "sg:city":"Mol",
    "sg:orig_category":"Tweedehandsgoederen Verlichting and huishoudartikelen",
    "sg:phone":"+32 14 31 46 68",
    "sg:postcode":"2400",
    "sg:province":"Antwerpen",
    "wof:name":"Oxfam Wereldwinkel",
    "wof:placetype":"venue"
},
  "geometry": {"coordinates":[5.1167612076,51.1883964539],"type":"Point"}
}