{
  "type": "Feature",
  "properties": {
    "addr:full":"Cadzandstraat 8 Sint-niklaas (sinaai) Oost-Vlaanderen 9112",
    "addr:housenumber":"8",
    "addr:postcode":"9112",
    "addr:street":"Cadzandstraat;Oost-Vlaanderen",
    "iso:country":"BE",
    "sg:address":"Cadzandstraat 8",
    "sg:city":"Sint-niklaas (sinaai)",
    "sg:classifiers":[
        {
            "category":"Home & Garden",
            "subcategory":"Building Materials",
            "type":"Retail Goods"
        }
    ],
    "sg:phone":"+32 3 772 58 82",
    "sg:postcode":"9112",
    "sg:province":"Oost-Vlaanderen",
    "sg:tags":[
        "window"
    ],
    "wof:name":"Verberckmoes G",
    "wof:placetype":"venue"
},
  "geometry": {"coordinates":[4.0417251587,51.156879425],"type":"Point"}
}