{
  "type": "Feature",
  "properties": {
    "iso:country":"BE",
    "sg:address":"Vlasmarkt 14",
    "sg:city":"Dendermonde",
    "sg:classifiers":[
        {
            "category":"Shopping",
            "subcategory":"Clothing, Apparel, & Fashions",
            "type":"Retail Goods"
        }
    ],
    "sg:phone":"+32 52 21 49 88",
    "sg:postcode":"9200",
    "sg:province":"Oost-Vlaanderen",
    "sg:tags":[
        "v\u00eatements",
        "pour",
        "dame"
    ],
    "wof:name":"Huis Imago",
    "wof:placetype":"venue"
},
  "geometry": {"coordinates":[4.0989751816,51.0296134949],"type":"Point"}
}