{
  "type": "Feature",
  "properties": {
    "iso:country":"BE",
    "sg:address":"Bisschopslaan 68",
    "sg:city":"Beerse",
    "sg:orig_category":"Dierenartsen",
    "sg:phone":"+32 14 62 20 20",
    "sg:postcode":"2340",
    "sg:province":"Antwerpen",
    "wof:name":"B. Michiels",
    "wof:placetype":"venue"
},
  "geometry": {"coordinates":[4.8559861183,51.3132095337],"type":"Point"}
}