{
  "type": "Feature",
  "properties": {
    "iso:country":"BE",
    "sg:address":"Rue Du Village 26",
    "sg:city":"Hastiere",
    "sg:orig_category":"Eleveurs de bovins",
    "sg:phone":"+32 82 64 43 27",
    "sg:postcode":"5542",
    "sg:province":"Namur",
    "wof:name":"Fe. R\u00c9my",
    "wof:placetype":"venue"
},
  "geometry": {"coordinates":[4.8320360184,50.1884727478],"type":"Point"}
}