{
  "type": "Feature",
  "properties": {
    "iso:country":"BE",
    "sg:address":"Ringlaan 1",
    "sg:city":"Kuurne",
    "sg:orig_category":"Spuittoestellen Fab",
    "sg:phone":"+32 56 35 36 63",
    "sg:postcode":"8520",
    "sg:province":"West-Vlaanderen",
    "wof:name":"Aquaflam International",
    "wof:placetype":"venue"
},
  "geometry": {"coordinates":[3.2716701031,50.844493866],"type":"Point"}
}