{
  "type": "Feature",
  "properties": {
    "iso:country":"BE",
    "sg:address":"Chauss\u00e9e Du Risquons-tout 132",
    "sg:city":"Mouscron",
    "sg:classifiers":[
        {
            "category":"Bars & Pubs",
            "type":"Food & Drink"
        }
    ],
    "sg:phone":"+32 56 34 08 51",
    "sg:postcode":"7700",
    "sg:province":"Hainaut",
    "wof:name":"Cordial (le)",
    "wof:placetype":"venue"
},
  "geometry": {"coordinates":[3.2008850574,50.7455825806],"type":"Point"}
}