{
  "type": "Feature",
  "properties": {
    "addr:full":"Cardijnlaan 10 Aalter Oost-Vlaanderen 9880",
    "addr:housenumber":"10",
    "addr:postcode":"9880",
    "addr:street":"Cardijnlaan",
    "iso:country":"BE",
    "sg:address":"Cardijnlaan 10",
    "sg:city":"Aalter",
    "sg:orig_category":"Kapsalons Mobiele kappers",
    "sg:phone":"+32 9 374 16 22",
    "sg:postcode":"9880",
    "sg:province":"Oost-Vlaanderen",
    "wof:name":"Haarkapper Chris",
    "wof:placetype":"venue"
},
  "geometry": {"coordinates":[3.4301280975,51.1080360413],"type":"Point"}
}