{
  "type": "Feature",
  "properties": {
    "addr:full":"Dorp 23 Oud-turnhout Antwerpen 2360",
    "addr:housenumber":"23",
    "addr:postcode":"2360",
    "addr:street":"Dorp",
    "iso:country":"BE",
    "sg:address":"Dorp 23",
    "sg:city":"Oud-turnhout",
    "sg:classifiers":[
        {
            "category":"Shopping",
            "subcategory":"Optician",
            "type":"Retail Goods"
        }
    ],
    "sg:phone":"+32 14 45 01 65",
    "sg:postcode":"2360",
    "sg:province":"Antwerpen",
    "sg:tags":[
        "-"
    ],
    "wof:name":"Van Baelen A",
    "wof:placetype":"venue"
},
  "geometry": {"coordinates":[4.9818620682,51.3182487488],"type":"Point"}
}