{
  "type": "Feature",
  "properties": {
    "iso:country":"BE",
    "sg:address":"L\u00fctticherstrasse",
    "sg:city":"Lontzen",
    "sg:classifiers":[
        {
            "category":"Airport",
            "subcategory":"International",
            "type":"Transportation"
        }
    ],
    "sg:phone":"+32 87 78 97 89",
    "sg:postcode":"4710",
    "sg:province":"Li\u00e8ge",
    "sg:tags":[
        "transport"
    ],
    "wof:name":"Jennesco S.a.",
    "wof:placetype":"venue"
},
  "geometry": {"coordinates":[5.9659547806,50.694190979],"type":"Point"}
}