{
  "type": "Feature",
  "properties": {
    "addr:full":"Vijgeweidestraat 79/2 Mechelen Antwerpen 2800",
    "addr:housenumber":"79 / 2",
    "addr:postcode":"2800",
    "addr:street":"Vijgeweidestraat",
    "iso:country":"BE",
    "sg:address":"Vijgeweidestraat 79/2",
    "sg:city":"Mechelen",
    "sg:orig_category":"Installation \u00e9lectrique r\u00e9sidentielle",
    "sg:phone":"+32 15 43 10 69",
    "sg:postcode":"2800",
    "sg:province":"Antwerpen",
    "wof:name":"Vanhaegen B",
    "wof:placetype":"venue"
},
  "geometry": {"coordinates":[4.4644398689,51.0212097168],"type":"Point"}
}