{
  "type": "Feature",
  "properties": {
    "addr:full":"Oudstrijdersstraat 63 Ranst (oelegem) Antwerpen 2520",
    "addr:housenumber":"63",
    "addr:postcode":"2520",
    "addr:street":"Oudstrijdersstraat",
    "iso:country":"BE",
    "sg:address":"Oudstrijdersstraat 63",
    "sg:city":"Ranst (oelegem)",
    "sg:classifiers":[
        {
            "category":"Wholesale",
            "subcategory":"Fruits & Vegetables",
            "type":"Manufacturing & Wholesale Goods"
        }
    ],
    "sg:phone":"+32 3 383 16 80",
    "sg:postcode":"2520",
    "sg:province":"Antwerpen",
    "sg:tags":[
        "whol",
        "-"
    ],
    "wof:name":"Denckens W (fruithandel)",
    "wof:placetype":"venue"
},
  "geometry": {"coordinates":[4.5927028656,51.2124786377],"type":"Point"}
}