{
  "type": "Feature",
  "properties": {
    "iso:country":"BE",
    "sg:address":"Meersstraat 27",
    "sg:city":"Asse",
    "sg:orig_category":"Onderdelen and accessoires voor auto's",
    "sg:phone":"+32 2 453 13 07",
    "sg:postcode":"1730",
    "sg:province":"Vlaams-Brabant",
    "wof:name":"Mechanic International",
    "wof:placetype":"venue"
},
  "geometry": {"coordinates":[4.1969451904,50.9012298584],"type":"Point"}
}