{
  "type": "Feature",
  "properties": {
    "addr:full":"Route Des Ardennes 93bb Aywaille Li\u00e8ge 4920",
    "addr:housenumber":"93bb",
    "addr:postcode":"4920",
    "addr:street":"Route Des Ardennes",
    "iso:country":"BE",
    "sg:address":"Route Des Ardennes 93bb",
    "sg:city":"Aywaille",
    "sg:orig_category":"V\u00e9hicules automobiles. Entretien and r\u00e9parations de voitures",
    "sg:phone":"+32 4 384 60 75",
    "sg:postcode":"4920",
    "sg:province":"Li\u00e8ge",
    "wof:name":"Garage Dainef",
    "wof:placetype":"venue"
},
  "geometry": {"coordinates":[5.6776800156,50.4642791748],"type":"Point"}
}