{
  "type": "Feature",
  "properties": {
    "addr:full":"Boulevard Type 35 Mons (harmignies) Hainaut 7022",
    "addr:housenumber":"35",
    "addr:postcode":"7022",
    "addr:street":"Boulevard Type",
    "iso:country":"BE",
    "sg:address":"Boulevard Type 35",
    "sg:city":"Mons (harmignies)",
    "sg:classifiers":[
        {
            "category":"Freight",
            "type":"Transportation"
        }
    ],
    "sg:phone":"+32 65 58 76 90",
    "sg:postcode":"7022",
    "sg:province":"Hainaut",
    "sg:tags":[
        "-",
        "transport"
    ],
    "wof:name":"Vandendriessche P",
    "wof:placetype":"venue"
},
  "geometry": {"coordinates":[4.0038518906,50.400352478],"type":"Point"}
}