{
  "type": "Feature",
  "properties": {
    "iso:country":"BE",
    "sg:address":"Sint-annastraat 12",
    "sg:city":"Merelbeke",
    "sg:orig_category":"Diepvriesproducten Gh",
    "sg:phone":"+32 9 362 37 97",
    "sg:postcode":"9820",
    "sg:province":"Oost-Vlaanderen",
    "wof:name":"Schwing-foods",
    "wof:placetype":"venue"
},
  "geometry": {"coordinates":[3.7529881001,50.9640960693],"type":"Point"}
}