{
  "type": "Feature",
  "properties": {
    "iso:country":"BE",
    "sg:address":"Michel Theysstraat 52",
    "sg:city":"Diest",
    "sg:orig_category":"Boekhouders",
    "sg:phone":"+32 13 35 01 60",
    "sg:postcode":"3290",
    "sg:province":"Vlaams-Brabant",
    "wof:name":"Cecile Wouters",
    "wof:placetype":"venue"
},
  "geometry": {"coordinates":[5.0535330772,50.9874191284],"type":"Point"}
}