{
  "type": "Feature",
  "properties": {
    "iso:country":"BE",
    "sg:address":"Rue De L'harmonie 16",
    "sg:city":"Verviers",
    "sg:orig_category":"Geschenken and souvenirs Speelgoed Textiel Verlichting and huishoudartikelen",
    "sg:phone":"+32 87 35 52 24",
    "sg:postcode":"4800",
    "sg:province":"Li\u00e8ge",
    "wof:name":"Casa",
    "wof:placetype":"venue"
},
  "geometry": {"coordinates":[5.8755340576,50.5953216553],"type":"Point"}
}