{
  "type": "Feature",
  "properties": {
    "addr:full":"Rue Des Blanchisseries 9 Lens Hainaut 7870",
    "addr:housenumber":"9",
    "addr:postcode":"7870",
    "addr:street":"Rue Des Blanchisseries",
    "iso:country":"BE",
    "sg:address":"Rue Des Blanchisseries 9",
    "sg:city":"Lens",
    "sg:orig_category":"Eleveurs de bovins",
    "sg:phone":"+32 65 22 99 31",
    "sg:postcode":"7870",
    "sg:province":"Hainaut",
    "wof:name":"Roger Oreins",
    "wof:placetype":"venue"
},
  "geometry": {"coordinates":[3.8993489742,50.5490150452],"type":"Point"}
}