{
  "type": "Feature",
  "properties": {
    "addr:full":"Rue Bonne Alliance 3 Charleroi (mont-sur-marchienne) Hainaut 6032",
    "addr:housenumber":"3",
    "addr:postcode":"6032",
    "addr:street":"Rue Bonne Alliance",
    "iso:country":"BE",
    "sg:address":"Rue Bonne Alliance 3",
    "sg:city":"Charleroi (mont-sur-marchienne)",
    "sg:classifiers":[
        {
            "category":"Professional",
            "subcategory":"Art Services",
            "type":"Services"
        }
    ],
    "sg:phone":"+32 71 47 24 61",
    "sg:postcode":"6032",
    "sg:province":"Hainaut",
    "sg:tags":[
        "interior",
        "designer"
    ],
    "wof:name":"Annick Delvigne Decoration",
    "wof:placetype":"venue"
},
  "geometry": {"coordinates":[4.4105119705,50.3860054016],"type":"Point"}
}