{
  "type": "Feature",
  "properties": {
    "addr:full":"Maalderijstraat 4 Antwerpen Antwerpen 2000",
    "addr:housenumber":"4",
    "addr:postcode":"2000",
    "addr:street":"Maalderijstraat",
    "iso:country":"BE",
    "sg:address":"Maalderijstraat 4",
    "sg:city":"Antwerpen",
    "sg:classifiers":[
        {
            "category":"Restaurant",
            "type":"Food & Drink"
        }
    ],
    "sg:phone":"+32 3 226 15 93",
    "sg:postcode":"2000",
    "sg:province":"Antwerpen",
    "wof:name":"'t Putteke",
    "wof:placetype":"venue"
},
  "geometry": {"coordinates":[4.400053978,51.220916748],"type":"Point"}
}