{
  "type": "Feature",
  "properties": {
    "addr:full":"Rue De Cond\u00c9 67 Leuze-en-hainaut Hainaut 7900",
    "addr:housenumber":"67",
    "addr:postcode":"7900",
    "addr:street":"Rue De Conde\u0301",
    "iso:country":"BE",
    "sg:address":"Rue De Cond\u00c9 67",
    "sg:city":"Leuze-en-hainaut",
    "sg:orig_category":"Imprimeries and copyshops",
    "sg:phone":"+32 69 66 30 19",
    "sg:postcode":"7900",
    "sg:province":"Hainaut",
    "wof:name":"Imprimerie Deffrenne",
    "wof:placetype":"venue"
},
  "geometry": {"coordinates":[3.6173529625,50.5951690674],"type":"Point"}
}