{
  "type": "Feature",
  "properties": {
    "iso:country":"BE",
    "sg:address":"Rue De Rocroi 66",
    "sg:city":"Chimay",
    "sg:orig_category":"Producteurs de l\u00e9gumes",
    "sg:phone":"+32 60 21 38 68",
    "sg:postcode":"6464",
    "sg:province":"Hainaut",
    "wof:name":"Daniel Ramaekers",
    "wof:placetype":"venue"
},
  "geometry": {"coordinates":[4.3737411499,50.0224914551],"type":"Point"}
}