{
  "type": "Feature",
  "properties": {
    "iso:country":"BE",
    "sg:address":"Chauss\u00c9e De Tirlemont 42",
    "sg:city":"Jodoigne",
    "sg:orig_category":"Imprimeries and copyshops",
    "sg:phone":"+32 10 81 11 28",
    "sg:postcode":"1370",
    "sg:province":"Brabant Wallon",
    "wof:name":"Imprimerie Wilmart-gilles",
    "wof:placetype":"venue"
},
  "geometry": {"coordinates":[4.8734221458,50.7262191772],"type":"Point"}
}