{
  "type": "Feature",
  "properties": {
    "iso:country":"BE",
    "sg:address":"Bierbeekstraat 24",
    "sg:city":"Oud-heverlee (blanden)",
    "sg:classifiers":[
        {
            "category":"Wholesale",
            "subcategory":"Hardware",
            "type":"Manufacturing & Wholesale Goods"
        }
    ],
    "sg:phone":"+32 16 40 83 88",
    "sg:postcode":"3052",
    "sg:province":"Vlaams-Brabant",
    "sg:tags":[
        "lubricating",
        "compound"
    ],
    "wof:name":"Gilson & Desseyn Bvba",
    "wof:placetype":"venue"
},
  "geometry": {"coordinates":[4.7065820694,50.8258972168],"type":"Point"}
}