{
  "type": "Feature",
  "properties": {
    "addr:full":"Kouterstraat 82 Zwevegem West-Vlaanderen 8550",
    "addr:housenumber":"82",
    "addr:postcode":"8550",
    "addr:street":"Kouterstraat",
    "iso:country":"BE",
    "sg:address":"Kouterstraat 82",
    "sg:city":"Zwevegem",
    "sg:orig_category":"Paramedische behandelingen",
    "sg:phone":"+32 56 75 94 73",
    "sg:postcode":"8550",
    "sg:province":"West-Vlaanderen",
    "wof:name":"P. Loncke",
    "wof:placetype":"venue"
},
  "geometry": {"coordinates":[3.3406779766,50.8113327026],"type":"Point"}
}