{
  "type": "Feature",
  "properties": {
    "addr:full":"Vichtsesteenweg 44 Deerlijk West-Vlaanderen 8540",
    "addr:housenumber":"44",
    "addr:postcode":"8540",
    "addr:street":"Vichtsesteenweg",
    "iso:country":"BE",
    "sg:address":"Vichtsesteenweg 44",
    "sg:city":"Deerlijk",
    "sg:orig_category":"Verhuur diversen Winkelinrichting and handelsuitrusting Gh",
    "sg:phone":"+32 56 72 52 82",
    "sg:postcode":"8540",
    "sg:province":"West-Vlaanderen",
    "wof:name":"Steam Carousel",
    "wof:placetype":"venue"
},
  "geometry": {"coordinates":[3.3521909714,50.8535194397],"type":"Point"}
}