{
  "type": "Feature",
  "properties": {
    "addr:full":"Rue De L'h\u00f4tel De Ville 6 Sprimont Li\u00e8ge 4140",
    "addr:housenumber":"6",
    "addr:postcode":"4140",
    "addr:street":"Rue De L'Ho \u0302Tel De Ville",
    "iso:country":"BE",
    "sg:address":"Rue De L'h\u00f4tel De Ville 6",
    "sg:city":"Sprimont",
    "sg:classifiers":[
        {
            "category":"Communications",
            "type":"Services"
        }
    ],
    "sg:phone":"+32 4 382 10 73",
    "sg:postcode":"4140",
    "sg:province":"Li\u00e8ge",
    "sg:tags":[
        "translator"
    ],
    "wof:name":"Banaszkiewicz-balthazart J",
    "wof:placetype":"venue"
},
  "geometry": {"coordinates":[5.6614789963,50.5026741028],"type":"Point"}
}