{
  "type": "Feature",
  "properties": {
    "iso:country":"BE",
    "sg:address":"Botestraat 34",
    "sg:city":"Waregem",
    "sg:orig_category":"Kapsalons",
    "sg:phone":"+32 56 60 10 06",
    "sg:postcode":"8790",
    "sg:province":"West-Vlaanderen",
    "wof:name":"Theresia De Meester",
    "wof:placetype":"venue"
},
  "geometry": {"coordinates":[3.4090099335,50.8889198303],"type":"Point"}
}