{
  "type": "Feature",
  "properties": {
    "iso:country":"BE",
    "sg:address":"Lange Lozanastraat 176-182 Box 2",
    "sg:city":"Antwerpen",
    "sg:classifiers":[
        {
            "category":"Professional",
            "subcategory":"Accounting & Tax Preparation",
            "type":"Services"
        }
    ],
    "sg:phone":"+32 3 237 44 05",
    "sg:postcode":"2018",
    "sg:province":"Antwerpen",
    "sg:tags":[
        "accountant"
    ],
    "wof:name":"Atc-accountants Tax Consultants Bvba",
    "wof:placetype":"venue"
},
  "geometry": {"coordinates":[4.4058670998,51.2015151978],"type":"Point"}
}