{
  "type": "Feature",
  "properties": {
    "iso:country":"BE",
    "sg:address":"Pont Du Ch\u00eane 48",
    "sg:city":"Verviers",
    "sg:classifiers":[
        {
            "category":"Communications",
            "type":"Services"
        }
    ],
    "sg:phone":"+32 87 34 19 83",
    "sg:postcode":"4800",
    "sg:province":"Li\u00e8ge",
    "sg:tags":[
        "telecommunication"
    ],
    "wof:name":"Razzaq & Co",
    "wof:placetype":"venue"
},
  "geometry": {"coordinates":[5.8551898003,50.592300415],"type":"Point"}
}