{
  "type": "Feature",
  "properties": {
    "iso:country":"BE",
    "sg:address":"'s-meiersstraat 11",
    "sg:city":"Leuven",
    "sg:classifiers":[
        {
            "category":"Health Services",
            "subcategory":"Dentist",
            "type":"Services"
        }
    ],
    "sg:phone":"+32 16 23 05 84",
    "sg:postcode":"3000",
    "sg:province":"Vlaams-Brabant",
    "wof:name":"Dewever Annemie",
    "wof:placetype":"venue"
},
  "geometry": {"coordinates":[4.7024698257,50.8776741028],"type":"Point"}
}