{
  "type": "Feature",
  "properties": {
    "addr:full":"Oude Heirbaan 9 Deinze-grammene Oost-Vlaanderen 9800",
    "addr:housenumber":"9",
    "addr:postcode":"9800",
    "addr:street":"Oude Heirbaan;Oost-Vlaanderen",
    "iso:country":"BE",
    "sg:address":"Oude Heirbaan 9",
    "sg:city":"Deinze-grammene",
    "sg:classifiers":[
        {
            "category":"Manufacturing",
            "subcategory":"Lumber",
            "type":"Manufacturing & Wholesale Goods"
        }
    ],
    "sg:phone":"+32 51 63 33 12",
    "sg:postcode":"9800",
    "sg:province":"Oost-Vlaanderen",
    "sg:tags":[
        "overseas",
        "timber"
    ],
    "wof:name":"Etablissement Michels B.v.b.a.",
    "wof:placetype":"venue"
},
  "geometry": {"coordinates":[3.4825899601,50.9827575684],"type":"Point"}
}