{
  "type": "Feature",
  "properties": {
    "addr:full":"Koninginnelaan 115 Box 56-57 Maasmechelen (eisden) Limburg 3630",
    "addr:housenumber":"115 box 56-57",
    "addr:postcode":"3630",
    "addr:street":"Koninginnelaan",
    "iso:country":"BE",
    "sg:address":"Koninginnelaan 115 Box 56-57",
    "sg:city":"Maasmechelen (eisden)",
    "sg:classifiers":[
        {
            "category":"Shopping",
            "subcategory":"Bicycles & Sporting Goods",
            "type":"Retail Goods"
        }
    ],
    "sg:phone":"+32 89 46 57 22",
    "sg:postcode":"3630",
    "sg:province":"Limburg",
    "sg:tags":[
        "sport",
        "-"
    ],
    "wof:name":"A M D Schillaci Bvba",
    "wof:placetype":"venue"
},
  "geometry": {"coordinates":[5.6961350441,50.963848114],"type":"Point"}
}