{
  "type": "Feature",
  "properties": {
    "addr:full":"Rue De Goz\u00c9e 447 Montigny-le-tilleul Hainaut 6110",
    "addr:housenumber":"447",
    "addr:postcode":"6110",
    "addr:street":"Rue De Goze\u0301E",
    "iso:country":"BE",
    "sg:address":"Rue De Goz\u00c9e 447",
    "sg:city":"Montigny-le-tilleul",
    "sg:classifiers":[
        {
            "category":"Restaurant",
            "type":"Food & Drink"
        }
    ],
    "sg:phone":"+32 71 56 22 01",
    "sg:postcode":"6110",
    "sg:province":"Hainaut",
    "wof:name":"Snack Dutilleul",
    "wof:placetype":"venue"
},
  "geometry": {"coordinates":[4.3692178726,50.3766937256],"type":"Point"}
}