{
  "type": "Feature",
  "properties": {
    "addr:full":"Bergensesteenweg 71 Sint-pieters-leeuw Vlaams-Brabant 1600",
    "addr:housenumber":"71",
    "addr:postcode":"1600",
    "addr:street":"Bergensesteenweg",
    "iso:country":"BE",
    "sg:address":"Bergensesteenweg 71",
    "sg:city":"Sint-pieters-leeuw",
    "sg:orig_category":"Reclamebureaus",
    "sg:phone":"+32 2 377 94 23",
    "sg:postcode":"1600",
    "sg:province":"Vlaams-Brabant",
    "wof:name":"Fa. Helyx",
    "wof:placetype":"venue"
},
  "geometry": {"coordinates":[4.288998127,50.8053207397],"type":"Point"}
}