{
  "type": "Feature",
  "properties": {
    "addr:full":"Batticestraat 206 Voeren Limburg 3790",
    "addr:housenumber":"206",
    "addr:postcode":"3790",
    "addr:street":"Batticestraat",
    "iso:country":"BE",
    "sg:address":"Batticestraat 206",
    "sg:city":"Voeren",
    "sg:classifiers":[
        {
            "category":"Shopping",
            "subcategory":"Bicycles & Sporting Goods",
            "type":"Retail Goods"
        }
    ],
    "sg:phone":"+32 4 381 07 80",
    "sg:postcode":"3790",
    "sg:province":"Limburg",
    "sg:tags":[
        "article",
        "de",
        "sport",
        "camping"
    ],
    "wof:name":"Sluysmans",
    "wof:placetype":"venue"
},
  "geometry": {"coordinates":[5.8100881577,50.7484207153],"type":"Point"}
}