{
  "type": "Feature",
  "properties": {
    "iso:country":"BE",
    "sg:address":"Binsta 1",
    "sg:city":"Stavelot",
    "sg:orig_category":"DIVERSE RECREATIEVE ACTIVITEITEN",
    "sg:phone":"+32 80 86 25 08",
    "sg:postcode":"4970",
    "sg:province":"Li\u00e8ge",
    "wof:name":"Philaclub St.louis",
    "wof:placetype":"venue"
},
  "geometry": {"coordinates":[5.9728732109,50.4058303833],"type":"Point"}
}