{
  "type": "Feature",
  "properties": {
    "iso:country":"BE",
    "sg:address":"Zandstraat 10",
    "sg:city":"Bekkevoort (assent)",
    "sg:classifiers":[
        {
            "category":"Structure",
            "subcategory":"Building",
            "type":"Public Place"
        }
    ],
    "sg:phone":"+32 13 35 54 20",
    "sg:postcode":"3460",
    "sg:province":"Vlaams-Brabant",
    "sg:tags":[
        "door"
    ],
    "wof:name":"Bimex Nv",
    "wof:placetype":"venue"
},
  "geometry": {"coordinates":[5.0200281143,50.9547386169],"type":"Point"}
}