{
  "type": "Feature",
  "properties": {
    "iso:country":"BE",
    "sg:address":"Wakkensesteenweg 2",
    "sg:city":"Dentergem",
    "sg:classifiers":[
        {
            "category":"Tea Room",
            "subcategory":"None",
            "type":"Food & Drink"
        }
    ],
    "sg:phone":"+32 9 388 67 27",
    "sg:postcode":"8720",
    "sg:province":"West-Vlaanderen",
    "wof:name":"Pleintje ('t)",
    "wof:placetype":"venue"
},
  "geometry": {"coordinates":[3.4292290211,50.9336776733],"type":"Point"}
}