{
  "type": "Feature",
  "properties": {
    "iso:country":"BE",
    "sg:address":"Grand'rue 30",
    "sg:city":"Gembloux",
    "sg:orig_category":"Baby- and kinderkleding Dameskledingzaken",
    "sg:phone":"+32 81 61 20 95",
    "sg:postcode":"5030",
    "sg:province":"Namur",
    "wof:name":"Pr\u00c9maman",
    "wof:placetype":"venue"
},
  "geometry": {"coordinates":[4.6948981285,50.5607414246],"type":"Point"}
}