{
  "type": "Feature",
  "properties": {
    "iso:country":"BE",
    "sg:address":"Beverstraat 18",
    "sg:city":"Ninove",
    "sg:classifiers":[
        {
            "category":"Personal",
            "subcategory":"Beauty Salon",
            "type":"Services"
        }
    ],
    "sg:phone":"+32 54 32 81 11",
    "sg:postcode":"9400",
    "sg:province":"Oost-Vlaanderen",
    "wof:name":"Peeters Parfumerie",
    "wof:placetype":"venue"
},
  "geometry": {"coordinates":[4.021832943,50.8359336853],"type":"Point"}
}