{
  "type": "Feature",
  "properties": {
    "addr:full":"Rue Du Notariat 1a Silly Hainaut 7830",
    "addr:housenumber":"1a",
    "addr:postcode":"7830",
    "addr:street":"Rue Du Notariat",
    "iso:country":"BE",
    "sg:address":"Rue Du Notariat 1a",
    "sg:city":"Silly",
    "sg:classifiers":[
        {
            "category":"Real Estate",
            "subcategory":"Real Estate Services",
            "type":"Services"
        }
    ],
    "sg:phone":"+32 68 33 18 18",
    "sg:postcode":"7830",
    "sg:province":"Hainaut",
    "wof:name":"Carto Invest",
    "wof:placetype":"venue"
},
  "geometry": {"coordinates":[3.9244260788,50.6487045288],"type":"Point"}
}