{
  "type": "Feature",
  "properties": {
    "addr:full":"Avenue Des Fr\u00e8res Goemaere 95 Bruxelles (auderghem) Bruxelles-Capitale 1160",
    "addr:housenumber":"95",
    "addr:postcode":"1160",
    "addr:street":"Avenue Des Fre\u0300Res Goemaere",
    "iso:country":"BE",
    "sg:address":"Avenue Des Fr\u00e8res Goemaere 95",
    "sg:city":"Bruxelles (auderghem)",
    "sg:classifiers":[
        {
            "category":"Real Estate",
            "subcategory":"Architect",
            "type":"Services"
        }
    ],
    "sg:phone":"+32 2 675 41 88",
    "sg:postcode":"1160",
    "sg:province":"Bruxelles-Capitale",
    "wof:name":"Standaert G",
    "wof:placetype":"venue"
},
  "geometry": {"coordinates":[4.4358019829,50.810710907],"type":"Point"}
}