{
  "type": "Feature",
  "properties": {
    "iso:country":"BE",
    "sg:address":"Loostraat 48",
    "sg:city":"Kortessem (vliermaal)",
    "sg:classifiers":[
        {
            "category":"Retail",
            "subcategory":"Auto Repair",
            "type":"Services"
        }
    ],
    "sg:phone":"+32 12 26 35 95",
    "sg:postcode":"3724",
    "sg:province":"Limburg",
    "sg:tags":[
        "breakdown",
        "automobile",
        "-",
        "recovery"
    ],
    "wof:name":"Bas Takeldienst",
    "wof:placetype":"venue"
},
  "geometry": {"coordinates":[5.4252557755,50.8440284729],"type":"Point"}
}