{
  "type": "Feature",
  "properties": {
    "addr:full":"Rue Du Fays 25 Sprimont Li\u00e8ge 4140",
    "addr:housenumber":"25",
    "addr:postcode":"4140",
    "addr:street":"Rue Du Fays",
    "iso:country":"BE",
    "sg:address":"Rue Du Fays 25",
    "sg:city":"Sprimont",
    "sg:classifiers":[
        {
            "category":"Retail",
            "subcategory":"Animal Services",
            "type":"Services"
        }
    ],
    "sg:phone":"+32 4 384 89 50",
    "sg:postcode":"4140",
    "sg:province":"Li\u00e8ge",
    "sg:tags":[
        "farrier"
    ],
    "wof:name":"Sarlet J",
    "wof:placetype":"venue"
},
  "geometry": {"coordinates":[5.6263689995,50.5128593445],"type":"Point"}
}