{
  "type": "Feature",
  "properties": {
    "addr:full":"Gryspeerdts Hof 19 Roeselare West-Vlaanderen 8800",
    "addr:housenumber":"19",
    "addr:postcode":"8800",
    "addr:street":"Gryspeerdts Hof",
    "iso:country":"BE",
    "sg:address":"Gryspeerdts Hof 19",
    "sg:city":"Roeselare",
    "sg:classifiers":[
        {
            "category":"Health Services",
            "subcategory":"Health Practitioner",
            "type":"Services"
        }
    ],
    "sg:phone":"+32 51 22 98 46",
    "sg:postcode":"8800",
    "sg:province":"West-Vlaanderen",
    "sg:tags":[
        "physiotherapist"
    ],
    "wof:name":"Callewaert Veronique",
    "wof:placetype":"venue"
},
  "geometry": {"coordinates":[3.1188299656,50.959148407],"type":"Point"}
}