{
  "type": "Feature",
  "properties": {
    "iso:country":"BE",
    "sg:address":"Rue F\u00c9licien Tubiermont 18",
    "sg:city":"Genappe",
    "sg:orig_category":"Dakwerken",
    "sg:phone":"+32 67 77 27 54",
    "sg:postcode":"1472",
    "sg:province":"Brabant Wallon",
    "wof:name":"Georges Vanderlinck",
    "wof:placetype":"venue"
},
  "geometry": {"coordinates":[4.4387087822,50.6114006042],"type":"Point"}
}