{
  "type": "Feature",
  "properties": {
    "addr:full":"Schoollaan 7 Bredene West-Vlaanderen 8450",
    "addr:housenumber":"7",
    "addr:postcode":"8450",
    "addr:street":"Schoollaan",
    "iso:country":"BE",
    "sg:address":"Schoollaan 7",
    "sg:city":"Bredene",
    "sg:classifiers":[
        {
            "category":"Personal",
            "subcategory":"Nail Salon",
            "type":"Services"
        }
    ],
    "sg:phone":"+32 59 33 03 48",
    "sg:postcode":"8450",
    "sg:province":"West-Vlaanderen",
    "sg:tags":[
        "pedicure"
    ],
    "wof:name":"Sandra",
    "wof:placetype":"venue"
},
  "geometry": {"coordinates":[2.9654369354,51.241268158],"type":"Point"}
}