{
  "type": "Feature",
  "properties": {
    "addr:full":"Avenue De Versailles 200 Bruxelles Bruxelles-Capitale 1120",
    "addr:housenumber":"200",
    "addr:postcode":"1120",
    "addr:street":"Avenue De Versailles",
    "iso:country":"BE",
    "sg:address":"Avenue De Versailles 200",
    "sg:city":"Bruxelles",
    "sg:classifiers":[
        {
            "category":"Professional",
            "subcategory":"Advertising",
            "type":"Services"
        }
    ],
    "sg:phone":"+32 2 268 37 15",
    "sg:postcode":"1120",
    "sg:province":"Bruxelles-Capitale",
    "sg:tags":[
        "studio"
    ],
    "wof:name":"Pub Corn Corbiau",
    "wof:placetype":"venue"
},
  "geometry": {"coordinates":[4.3806939125,50.8966789246],"type":"Point"}
}