{
  "type": "Feature",
  "properties": {
    "iso:country":"BE",
    "sg:address":"Zomerpad 3a",
    "sg:city":"Knokke-heist (heist-aan-zee)",
    "sg:classifiers":[
        {
            "category":"Professional",
            "subcategory":"Art Services",
            "type":"Services"
        }
    ],
    "sg:phone":"+32 478 97 34 99",
    "sg:postcode":"8301",
    "sg:province":"West-Vlaanderen",
    "sg:tags":[
        "interior",
        "designer"
    ],
    "wof:name":"Christo Bvba",
    "wof:placetype":"venue"
},
  "geometry": {"coordinates":[3.2643918991,51.341632843],"type":"Point"}
}