{
  "type": "Feature",
  "properties": {
    "iso:country":"BE",
    "sg:address":"Boulevard De La Sauveni\u00c8re 132",
    "sg:city":"Li\u00c8ge",
    "sg:orig_category":"Gespecialiseerde residenti\u00eble bouw Woningbouw",
    "sg:phone":"+32 4 222 28 12",
    "sg:postcode":"4000",
    "sg:province":"Li\u00e8ge",
    "wof:name":"Co.be.pe",
    "wof:placetype":"venue"
},
  "geometry": {"coordinates":[5.5663428307,50.6417961121],"type":"Point"}
}