{
  "type": "Feature",
  "properties": {
    "addr:full":"Chauss\u00e9e De Mons 648-650 Bruxelles (anderlecht) Bruxelles-Capitale 1070",
    "addr:postcode":"648-650;1070",
    "addr:street":"Chausse\u0301E De Mons",
    "iso:country":"BE",
    "sg:address":"Chauss\u00e9e De Mons 648-650",
    "sg:city":"Bruxelles (anderlecht)",
    "sg:orig_category":"Autombile concessionaires",
    "sg:phone":"+32 2 522 54 16",
    "sg:postcode":"1070",
    "sg:province":"Bruxelles-Capitale",
    "wof:name":"J P S Motors Sprl",
    "wof:placetype":"venue"
},
  "geometry": {"coordinates":[4.3081569672,50.8300209045],"type":"Point"}
}