{
  "type": "Feature",
  "properties": {
    "addr:full":"Beatrijslaan 17 Grimbergen Vlaams-Brabant 1850",
    "addr:housenumber":"17",
    "addr:postcode":"1850",
    "addr:street":"Beatrijslaan",
    "iso:country":"BE",
    "sg:address":"Beatrijslaan 17",
    "sg:city":"Grimbergen",
    "sg:orig_category":"Maisons de repos and r\u00e9sidences",
    "sg:phone":"+32 2 267 18 73",
    "sg:postcode":"1850",
    "sg:province":"Vlaams-Brabant",
    "wof:name":"Anemoon",
    "wof:placetype":"venue"
},
  "geometry": {"coordinates":[4.3746099472,50.9419822693],"type":"Point"}
}