{
  "type": "Feature",
  "properties": {
    "addr:full":"Boterweegschaalstraat 4 Veurne West-Vlaanderen 8630",
    "addr:housenumber":"4",
    "addr:postcode":"8630",
    "addr:street":"Boterweegschaalstraat",
    "iso:country":"BE",
    "sg:address":"Boterweegschaalstraat 4",
    "sg:city":"Veurne",
    "sg:classifiers":[
        {
            "category":"Personal",
            "subcategory":"Beauty Salon",
            "type":"Services"
        }
    ],
    "sg:phone":"+32 58 31 39 78",
    "sg:postcode":"8630",
    "sg:province":"West-Vlaanderen",
    "wof:name":"Ellen",
    "wof:placetype":"venue"
},
  "geometry": {"coordinates":[2.6635379791,51.071685791],"type":"Point"}
}