{
  "type": "Feature",
  "properties": {
    "iso:country":"BE",
    "sg:address":"Rue De Rotheux 325",
    "sg:city":"Seraing",
    "sg:orig_category":"M\u00e9decins and sp\u00e9cialistes",
    "sg:phone":"+32 4 336 28 09",
    "sg:postcode":"4100",
    "sg:province":"Li\u00e8ge",
    "wof:name":"Daniel Pire",
    "wof:placetype":"venue"
},
  "geometry": {"coordinates":[5.502450943,50.5774726868],"type":"Point"}
}