{
  "type": "Feature",
  "properties": {
    "addr:full":"Postfach 1209 Troisdorf 5210",
    "addr:housenumber":"1209",
    "addr:postcode":"5210",
    "addr:street":"Postfach",
    "iso:country":"BE",
    "sg:address":"Postfach 1209",
    "sg:city":"Troisdorf",
    "sg:classifiers":[
        {
            "category":"Building & Trades",
            "subcategory":"Construction",
            "type":"Services"
        }
    ],
    "sg:phone":"+32 16 25 64 51",
    "sg:postcode":"5210",
    "sg:tags":[
        "roofing",
        "material",
        "-"
    ],
    "wof:name":"Dynamit Nobel Ag Hern Klh Gb B",
    "wof:placetype":"venue"
},
  "geometry": {"coordinates":[7.1534061432,50.8133506775],"type":"Point"}
}