{
  "type": "Feature",
  "properties": {
    "addr:full":"Noordlaan 28 Roeselare West-Vlaanderen 8800",
    "addr:housenumber":"28",
    "addr:postcode":"8800",
    "addr:street":"Noordlaan",
    "iso:country":"BE",
    "sg:address":"Noordlaan 28",
    "sg:city":"Roeselare",
    "sg:classifiers":[
        {
            "category":"Manufacturing",
            "subcategory":"Furniture",
            "type":"Manufacturing & Wholesale Goods"
        }
    ],
    "sg:phone":"+32 51 22 71 07",
    "sg:postcode":"8800",
    "sg:province":"West-Vlaanderen",
    "sg:tags":[
        "design",
        "-"
    ],
    "wof:name":"Samyn Bvba Wooninrichting Bvba",
    "wof:placetype":"venue"
},
  "geometry": {"coordinates":[3.1197268963,50.9562759399],"type":"Point"}
}