{
  "type": "Feature",
  "properties": {
    "iso:country":"BE",
    "sg:address":"Roeselarestraat 54",
    "sg:city":"Zonnebeke",
    "sg:classifiers":[
        {
            "category":"Banks & Credit Unions",
            "subcategory":"Bank",
            "type":"Services"
        }
    ],
    "sg:phone":"+32 51 77 97 39",
    "sg:postcode":"6888",
    "wof:name":"Bank Van Roeselare",
    "wof:placetype":"venue"
},
  "geometry": {"coordinates":[10.1083898544,47.2554588318],"type":"Point"}
}