{
  "type": "Feature",
  "properties": {
    "iso:country":"BE",
    "sg:address":"Wagenmakersstraat 62",
    "sg:city":"Kortrijk",
    "sg:classifiers":[
        {
            "category":"Wholesale",
            "subcategory":"Music Publishers",
            "type":"Manufacturing & Wholesale Goods"
        }
    ],
    "sg:phone":"+32 56 20 50 77",
    "sg:postcode":"8500",
    "sg:province":"West-Vlaanderen",
    "wof:name":"Pyromedia",
    "wof:placetype":"venue"
},
  "geometry": {"coordinates":[3.2742960453,50.8190536499],"type":"Point"}
}