{
  "type": "Feature",
  "properties": {
    "addr:full":"Chauss\u00e9e Bara 112 Braine L'alleud (braine-l'alleud) Brabant Wallon 1420",
    "addr:housenumber":"112",
    "addr:postcode":"1420",
    "addr:street":"Chausse\u0301E Bara",
    "iso:country":"BE",
    "sg:address":"Chauss\u00e9e Bara 112",
    "sg:city":"Braine L'alleud (braine-l'alleud)",
    "sg:orig_category":"Non-Classified Establishments",
    "sg:phone":"+32 2 386 42 60",
    "sg:postcode":"1420",
    "sg:province":"Brabant Wallon",
    "wof:name":"Daneels Y Ets",
    "wof:placetype":"venue"
},
  "geometry": {"coordinates":[-0.7711730003,47.3931159973],"type":"Point"}
}