{
  "type": "Feature",
  "properties": {
    "addr:full":"Zuidstationstraat 30 Gent Oost-Vlaanderen 9000",
    "addr:housenumber":"30",
    "addr:postcode":"9000",
    "addr:street":"Zuidstationstraat;Oost-Vlaanderen",
    "iso:country":"BE",
    "sg:address":"Zuidstationstraat 30",
    "sg:city":"Gent",
    "sg:classifiers":[
        {
            "category":"Professional",
            "subcategory":"Engineering",
            "type":"Services"
        }
    ],
    "sg:phone":"+32 9 235 75 00",
    "sg:postcode":"9000",
    "sg:province":"Oost-Vlaanderen",
    "sg:tags":[
        "civil",
        "offices-"
    ],
    "wof:name":"Spetsai Nv",
    "wof:placetype":"venue"
},
  "geometry": {"coordinates":[3.7326500416,51.0490226746],"type":"Point"}
}