{
  "type": "Feature",
  "properties": {
    "iso:country":"BE",
    "sg:address":"Pilatusveld 11",
    "sg:city":"Londerzeel",
    "sg:classifiers":[
        {
            "category":"Organizations",
            "subcategory":"Community Association",
            "type":"Services"
        }
    ],
    "sg:phone":"+32 52 30 10 87",
    "sg:postcode":"1840",
    "sg:province":"Vlaams-Brabant",
    "sg:tags":[
        "organisation"
    ],
    "wof:name":"Chiro Jongens Centrum",
    "wof:placetype":"venue"
},
  "geometry": {"coordinates":[4.31001091,51.0044898987],"type":"Point"}
}