{
  "type": "Feature",
  "properties": {
    "addr:full":"De Stappe 1 Mortsel Antwerpen 2640",
    "addr:housenumber":"1",
    "addr:postcode":"2640",
    "iso:country":"BE",
    "sg:address":"De Stappe 1",
    "sg:city":"Mortsel",
    "sg:classifiers":[
        {
            "category":"Health Services",
            "subcategory":"Doctor",
            "type":"Services"
        }
    ],
    "sg:phone":"+32 3 454 35 10",
    "sg:postcode":"2640",
    "sg:province":"Antwerpen",
    "sg:tags":[
        "medicinephysicians",
        "surgeon"
    ],
    "wof:name":"Adriaenssens V",
    "wof:placetype":"venue"
},
  "geometry": {"coordinates":[4.4698848724,51.164642334],"type":"Point"}
}