{
  "type": "Feature",
  "properties": {
    "iso:country":"BE",
    "sg:address":"Sint-denisplaats 15",
    "sg:city":"Veurne",
    "sg:orig_category":"Cafetarias and selfservice restaurants",
    "sg:phone":"+32 58 31 66 06",
    "sg:postcode":"8630",
    "sg:province":"West-Vlaanderen",
    "wof:name":"Cafetaria Zwembad",
    "wof:placetype":"venue"
},
  "geometry": {"coordinates":[2.6608729362,51.0701599121],"type":"Point"}
}