{
  "type": "Feature",
  "properties": {
    "iso:country":"BE",
    "sg:address":"Reinpadstraat 16",
    "sg:city":"Genk",
    "sg:orig_category":"M\u00e9decins and sp\u00e9cialistes",
    "sg:phone":"+32 89 35 54 45",
    "sg:postcode":"3600",
    "sg:province":"Limburg",
    "wof:name":"Marc Vanstraelen",
    "wof:placetype":"venue"
},
  "geometry": {"coordinates":[5.5029711723,50.9675292969],"type":"Point"}
}