{
  "type": "Feature",
  "properties": {
    "addr:full":"Gentse Heerweg 98 Waregem West-Vlaanderen 8790",
    "addr:housenumber":"98",
    "addr:postcode":"8790",
    "addr:street":"Gentse Heerweg",
    "iso:country":"BE",
    "sg:address":"Gentse Heerweg 98",
    "sg:city":"Waregem",
    "sg:orig_category":"Cabinets d\u00b4huissiers",
    "sg:phone":"+32 56 60 58 16",
    "sg:postcode":"8790",
    "sg:province":"West-Vlaanderen",
    "wof:name":"Dockers A",
    "wof:placetype":"venue"
},
  "geometry": {"coordinates":[3.4647080898,50.90234375],"type":"Point"}
}