{
  "type": "Feature",
  "properties": {
    "addr:full":"Pantserschipstr. 207 Gent Oost-Vlaanderen 9000",
    "addr:housenumber":"207",
    "addr:postcode":"9000",
    "addr:street":"Oost-Vlaanderen",
    "iso:country":"BE",
    "sg:address":"Pantserschipstr. 207",
    "sg:city":"Gent",
    "sg:classifiers":[
        {
            "category":"Manufacturing",
            "subcategory":"Chemicals & Compounds",
            "type":"Manufacturing & Wholesale Goods"
        }
    ],
    "sg:phone":"+32 9 254 14 11",
    "sg:postcode":"9000",
    "sg:province":"Oost-Vlaanderen",
    "sg:tags":[
        "pharmaceutical",
        "chemistry"
    ],
    "wof:name":"Taminco",
    "wof:placetype":"venue"
},
  "geometry": {"coordinates":[3.727866888,51.0922698975],"type":"Point"}
}