{
  "type": "Feature",
  "properties": {
    "addr:full":"Avenue Edmond Leburton 53 Waremme Li\u00e8ge 4300",
    "addr:housenumber":"53",
    "addr:postcode":"4300",
    "addr:street":"Avenue Edmond Leburton",
    "iso:country":"BE",
    "sg:address":"Avenue Edmond Leburton 53",
    "sg:city":"Waremme",
    "sg:orig_category":"Schoonheidssalons",
    "sg:phone":"+32 19 32 78 23",
    "sg:postcode":"4300",
    "sg:province":"Li\u00e8ge",
    "wof:name":"Espace Beaut\u00c9 Lutgard",
    "wof:placetype":"venue"
},
  "geometry": {"coordinates":[5.2607097626,50.698059082],"type":"Point"}
}