{
  "type": "Feature",
  "properties": {
    "iso:country":"BE",
    "sg:address":"Weibroekdreef 76",
    "sg:city":"Aalter",
    "sg:classifiers":[
        {
            "category":"Arena",
            "subcategory":"Sports Club",
            "type":"Entertainment"
        }
    ],
    "sg:phone":"+32 9 374 11 84",
    "sg:postcode":"9880",
    "sg:province":"Oost-Vlaanderen",
    "sg:tags":[
        "de"
    ],
    "wof:name":"V.c. De Velovrienden",
    "wof:placetype":"venue"
},
  "geometry": {"coordinates":[3.4603021145,51.0917892456],"type":"Point"}
}