{
  "type": "Feature",
  "properties": {
    "iso:country":"BE",
    "sg:address":"Rue De Grand Bry 18",
    "sg:city":"Montigny-le-tilleul",
    "sg:orig_category":"Artsen and specialisten",
    "sg:phone":"+32 71 51 80 09",
    "sg:postcode":"6110",
    "sg:province":"Hainaut",
    "wof:name":"Emile Dofny",
    "wof:placetype":"venue"
},
  "geometry": {"coordinates":[4.3658008575,50.3659591675],"type":"Point"}
}