{
  "type": "Feature",
  "properties": {
    "addr:full":"Avenue Nestor Plissart 6 Etterbeek Bruxelles-Capitale 1040",
    "addr:housenumber":"6",
    "addr:postcode":"1040",
    "addr:street":"Avenue Nestor Plissart",
    "iso:country":"BE",
    "sg:address":"Avenue Nestor Plissart 6",
    "sg:city":"Etterbeek",
    "sg:orig_category":"Maisons de repos and r\u00e9sidences",
    "sg:phone":"+32 2 735 48 46",
    "sg:postcode":"1040",
    "sg:province":"Bruxelles-Capitale",
    "wof:name":"R\u00c9sidence Les Myosotis",
    "wof:placetype":"venue"
},
  "geometry": {"coordinates":[4.4070949554,50.8321228027],"type":"Point"}
}