{
  "type": "Feature",
  "properties": {
    "iso:country":"BE",
    "sg:address":"Molenaarstraat 22",
    "sg:city":"Beringen",
    "sg:classifiers":[
        {
            "category":"Insurance",
            "subcategory":"Life Insurance",
            "type":"Services"
        }
    ],
    "sg:phone":"+32 11 34 22 07",
    "sg:postcode":"3581",
    "sg:province":"Limburg",
    "sg:tags":[
        "assurance"
    ],
    "wof:name":"F. Cruysberghs",
    "wof:placetype":"venue"
},
  "geometry": {"coordinates":[5.2228298187,51.0881996155],"type":"Point"}
}