{
  "type": "Feature",
  "properties": {
    "iso:country":"BE",
    "sg:address":"Miksebaan 64a",
    "sg:city":"Brasschaat",
    "sg:classifiers":[
        {
            "category":"Professional",
            "subcategory":"Management & Consulting",
            "type":"Services"
        }
    ],
    "sg:phone":"+32 3 653 52 51",
    "sg:postcode":"2930",
    "sg:province":"Antwerpen",
    "sg:tags":[
        "consultant",
        "agency",
        "advertising"
    ],
    "wof:name":"C.i.a. Europe Bvba",
    "wof:placetype":"venue"
},
  "geometry": {"coordinates":[4.5040149689,51.2916603088],"type":"Point"}
}