{
  "type": "Feature",
  "properties": {
    "addr:full":"Overstraat 43 Herent Vlaams-Brabant 3020",
    "addr:housenumber":"43",
    "addr:postcode":"3020",
    "addr:street":"Overstraat",
    "iso:country":"BE",
    "sg:address":"Overstraat 43",
    "sg:city":"Herent",
    "sg:orig_category":"Secretariaatsdiensten",
    "sg:phone":"+32 16 48 11 76",
    "sg:postcode":"3020",
    "sg:province":"Vlaams-Brabant",
    "wof:name":"Nc Support",
    "wof:placetype":"venue"
},
  "geometry": {"coordinates":[4.6749200821,50.9079055786],"type":"Point"}
}