{
  "type": "Feature",
  "properties": {
    "addr:full":"Rue Edouard Anseele 44 Quaregnon Hainaut 7390",
    "addr:housenumber":"44",
    "addr:postcode":"7390",
    "addr:street":"Rue Edouard Anseele",
    "iso:country":"BE",
    "sg:address":"Rue Edouard Anseele 44",
    "sg:city":"Quaregnon",
    "sg:orig_category":"Enseignement maternel and primaire",
    "sg:phone":"+32 65 78 36 58",
    "sg:postcode":"7390",
    "sg:province":"Hainaut",
    "wof:name":"Ecole Fondamentale Libre",
    "wof:placetype":"venue"
},
  "geometry": {"coordinates":[3.8686349392,50.4409980774],"type":"Point"}
}