{
  "type": "Feature",
  "properties": {
    "iso:country":"BE",
    "sg:address":"Prinses Elisabethlaan 20",
    "sg:city":"Brussel",
    "sg:orig_category":"Fotografen and fotostudio's Fotolaboratoria",
    "sg:phone":"+32 2 215 56 12",
    "sg:postcode":"1030",
    "sg:province":"Bruxelles-Capitale",
    "wof:name":"Bombaert P.",
    "wof:placetype":"venue"
},
  "geometry": {"coordinates":[4.3766322136,50.8722686768],"type":"Point"}
}