{
  "type": "Feature",
  "properties": {
    "addr:full":"Rue De La Cul\u00e9e 2 Nassogne (forri\u00e8res) Luxembourg 6953",
    "addr:housenumber":"2",
    "addr:postcode":"6953",
    "addr:street":"Rue De La Cule\u0301E",
    "iso:country":"BE",
    "sg:address":"Rue De La Cul\u00e9e 2",
    "sg:city":"Nassogne (forri\u00e8res)",
    "sg:classifiers":[
        {
            "category":"Personal",
            "subcategory":"Beauty Salon",
            "type":"Services"
        }
    ],
    "sg:phone":"+32 84 21 22 93",
    "sg:postcode":"6953",
    "sg:province":"Luxembourg",
    "sg:tags":[
        "lady",
        "-",
        "hairdressing"
    ],
    "wof:name":"Godfrin J & A",
    "wof:placetype":"venue"
},
  "geometry": {"coordinates":[5.2800917625,50.1356239319],"type":"Point"}
}