{
  "type": "Feature",
  "properties": {
    "iso:country":"BE",
    "sg:address":"Boulevard Emile Jacqmain 9b12",
    "sg:city":"Brussel/bruxelles",
    "sg:orig_category":"M\u00e9decins and sp\u00e9cialistes",
    "sg:phone":"+32 2 217 87 92",
    "sg:postcode":"1000",
    "sg:province":"Bruxelles-Capitale",
    "wof:name":"A. Rischa",
    "wof:placetype":"venue"
},
  "geometry": {"coordinates":[4.3534970284,50.8524703979],"type":"Point"}
}