{
  "type": "Feature",
  "properties": {
    "iso:country":"BE",
    "sg:address":"Boulevard De La Cense 72",
    "sg:city":"Waterloo",
    "sg:orig_category":"Diverse meubelen Fab IJzerwaren, bouw- and verfmaterialen MEUBELONTWERP AND -INSTALLATIE Meubelzaken",
    "sg:phone":"+32 2 351 36 16",
    "sg:postcode":"1410",
    "sg:province":"Brabant Wallon",
    "wof:name":"Bocage Concept",
    "wof:placetype":"venue"
},
  "geometry": {"coordinates":[4.3880848885,50.7062110901],"type":"Point"}
}