{
  "type": "Feature",
  "properties": {
    "addr:full":"Meulenven 16 Ham (kwaadmechelen) Limburg 3945",
    "addr:housenumber":"16",
    "addr:postcode":"kwaadmechelen;3945",
    "addr:street":"Meulenven",
    "iso:country":"BE",
    "sg:address":"Meulenven 16",
    "sg:city":"Ham (kwaadmechelen)",
    "sg:classifiers":[
        {
            "category":"Health Services",
            "subcategory":"Nursing And Care Facility",
            "type":"Services"
        }
    ],
    "sg:phone":"+32 13 67 14 96",
    "sg:postcode":"3945",
    "sg:province":"Limburg",
    "sg:tags":[
        "home",
        "rest"
    ],
    "wof:name":"Coham Nv",
    "wof:placetype":"venue"
},
  "geometry": {"coordinates":[5.1776199341,51.1046104431],"type":"Point"}
}