{
  "type": "Feature",
  "properties": {
    "iso:country":"BE",
    "sg:address":"Pallieterlaan 10",
    "sg:city":"Brecht",
    "sg:orig_category":"HUISBRANDOLIE",
    "sg:phone":"+32 3 636 47 07",
    "sg:postcode":"2960",
    "sg:province":"Antwerpen",
    "wof:name":"Jozef Peeters",
    "wof:placetype":"venue"
},
  "geometry": {"coordinates":[4.5745930672,51.3015975952],"type":"Point"}
}