{
  "type": "Feature",
  "properties": {
    "addr:full":"Rue Du Ch\u00c2teau 1 Herbeumont Luxembourg 6887",
    "addr:housenumber":"1",
    "addr:postcode":"6887",
    "addr:street":"Rue Du Cha\u0302Teau",
    "iso:country":"BE",
    "sg:address":"Rue Du Ch\u00c2teau 1",
    "sg:city":"Herbeumont",
    "sg:orig_category":"R\u00e9paration and restauration de meubles",
    "sg:phone":"+32 61 41 36 21",
    "sg:postcode":"6887",
    "sg:province":"Luxembourg",
    "wof:name":"Jean-luc Collignon",
    "wof:placetype":"venue"
},
  "geometry": {"coordinates":[5.2347750664,49.7794036865],"type":"Point"}
}