{
  "type": "Feature",
  "properties": {
    "iso:country":"BE",
    "sg:address":"Torhoutsesteenweg 88j",
    "sg:city":"Oostende",
    "sg:classifiers":[
        {
            "category":"Shopping",
            "subcategory":"Florist",
            "type":"Retail Goods"
        }
    ],
    "sg:phone":"+32 59 70 52 29",
    "sg:postcode":"8400",
    "sg:province":"West-Vlaanderen",
    "wof:name":"De Blomme",
    "wof:placetype":"venue"
},
  "geometry": {"coordinates":[2.9090878963,51.2237243652],"type":"Point"}
}