{
  "type": "Feature",
  "properties": {
    "iso:country":"BE",
    "sg:address":"Ruitersdreef 5",
    "sg:city":"Waregem",
    "sg:orig_category":"Salles de spectacles",
    "sg:phone":"+32 56 60 90 89",
    "sg:postcode":"8790",
    "sg:province":"West-Vlaanderen",
    "wof:name":"Zingende Sterren Waregem",
    "wof:placetype":"venue"
},
  "geometry": {"coordinates":[3.4462819099,50.8789482117],"type":"Point"}
}