{
  "type": "Feature",
  "properties": {
    "addr:full":"Rue De La Malgr\u00c9e 8 Anthisnes Li\u00e8ge 4163",
    "addr:housenumber":"8",
    "addr:postcode":"4163",
    "addr:street":"Rue De La Malgre\u0301E",
    "iso:country":"BE",
    "sg:address":"Rue De La Malgr\u00c9e 8",
    "sg:city":"Anthisnes",
    "sg:classifiers":[
        {
            "category":"Insurance",
            "subcategory":"Insurance Agent",
            "type":"Services"
        }
    ],
    "sg:phone":"+32 4 383 70 86",
    "sg:postcode":"4163",
    "sg:province":"Li\u00e8ge",
    "sg:tags":[
        "verzekeringsmakelaars",
        "expert"
    ],
    "wof:name":"Jos\u00c9 Marchand",
    "wof:placetype":"venue"
},
  "geometry": {"coordinates":[5.4695720673,50.4952926636],"type":"Point"}
}