{
  "type": "Feature",
  "properties": {
    "iso:country":"BE",
    "sg:address":"Rue De La Cambre 185",
    "sg:city":"Sint-pieters-woluwe",
    "sg:orig_category":"S\u00e9lection de personnel and placement",
    "sg:phone":"+32 2 771 33 41",
    "sg:postcode":"1150",
    "sg:province":"Bruxelles-Capitale",
    "wof:name":"B.s.o.",
    "wof:placetype":"venue"
},
  "geometry": {"coordinates":[4.4176211357,50.8383560181],"type":"Point"}
}