{
  "type": "Feature",
  "properties": {
    "iso:country":"BE",
    "sg:address":"Hoge Wegel 17",
    "sg:city":"Overpelt",
    "sg:classifiers":[
        {
            "category":"Arena",
            "subcategory":"Sports Club",
            "type":"Entertainment"
        }
    ],
    "sg:phone":"+32 11 80 28 51",
    "sg:postcode":"3900",
    "sg:province":"Limburg",
    "sg:tags":[
        "de"
    ],
    "wof:name":"Dameshandbalklub Overpelt",
    "wof:placetype":"venue"
},
  "geometry": {"coordinates":[5.4260311127,51.2060585022],"type":"Point"}
}