{
  "type": "Feature",
  "properties": {
    "addr:full":"Rue De L'ouvrage 2 Namur Namur 5000",
    "addr:housenumber":"2",
    "addr:postcode":"5000",
    "addr:street":"Rue De L'Ouvrage",
    "iso:country":"BE",
    "sg:address":"Rue De L'ouvrage 2",
    "sg:city":"Namur",
    "sg:classifiers":[
        {
            "category":"Restaurant",
            "type":"Food & Drink"
        }
    ],
    "sg:phone":"+32 81 22 66 48",
    "sg:postcode":"5000",
    "sg:province":"Namur",
    "wof:name":"Restaurant St.germain",
    "wof:placetype":"venue"
},
  "geometry": {"coordinates":[4.8636388779,50.4645423889],"type":"Point"}
}