{
  "type": "Feature",
  "properties": {
    "iso:country":"BE",
    "sg:address":"Hofeinde 1a",
    "sg:city":"Vosselaar",
    "sg:classifiers":[
        {
            "category":"Shopping",
            "subcategory":"Shoes",
            "type":"Retail Goods"
        }
    ],
    "sg:phone":"+32 14 61 78 52",
    "sg:postcode":"2350",
    "sg:province":"Antwerpen",
    "sg:tags":[
        "slipper",
        "-"
    ],
    "wof:name":"Vossenschoentje Bvba ('t)",
    "wof:placetype":"venue"
},
  "geometry": {"coordinates":[4.8849630356,51.3145332336],"type":"Point"}
}