{
  "type": "Feature",
  "properties": {
    "iso:country":"BE",
    "sg:address":"Industriepark 72",
    "sg:city":"Hulshout",
    "sg:classifiers":[
        {
            "category":"Shopping",
            "subcategory":"Stationery & Office Supplies",
            "type":"Retail Goods"
        }
    ],
    "sg:phone":"+32 15 22 34 67",
    "sg:postcode":"2235",
    "sg:province":"Antwerpen",
    "sg:tags":[
        "fab",
        "carton",
        "en",
        "papier",
        "emballages"
    ],
    "wof:name":"Verrydt",
    "wof:placetype":"venue"
},
  "geometry": {"coordinates":[4.8122901917,51.0780906677],"type":"Point"}
}