{
  "type": "Feature",
  "properties": {
    "iso:country":"BE",
    "sg:address":"Rue D'alvau 45",
    "sg:city":"Mont-saint-guibert (h\u00e9villers)",
    "sg:classifiers":[
        {
            "category":"Real Estate",
            "subcategory":"Architect",
            "type":"Services"
        }
    ],
    "sg:phone":"+32 10 65 15 88",
    "sg:postcode":"1435",
    "sg:province":"Brabant Wallon",
    "wof:name":"Berael C (mme)",
    "wof:placetype":"venue"
},
  "geometry": {"coordinates":[4.6273288727,50.6339912415],"type":"Point"}
}