{
  "type": "Feature",
  "properties": {
    "addr:full":"Plaats 1 Menen (rekkem) West-Vlaanderen 8930",
    "addr:housenumber":"1",
    "addr:postcode":"8930",
    "addr:street":"Plaats",
    "iso:country":"BE",
    "sg:address":"Plaats 1",
    "sg:city":"Menen (rekkem)",
    "sg:classifiers":[
        {
            "category":"Bars & Pubs",
            "type":"Food & Drink"
        }
    ],
    "sg:phone":"+32 56 41 14 85",
    "sg:postcode":"8930",
    "sg:province":"West-Vlaanderen",
    "wof:name":"Union (l')",
    "wof:placetype":"venue"
},
  "geometry": {"coordinates":[3.1631929874,50.7837371826],"type":"Point"}
}