{
  "type": "Feature",
  "properties": {
    "addr:full":"Rue Grande 136 Estinnes Hainaut 7120",
    "addr:housenumber":"136",
    "addr:postcode":"7120",
    "addr:street":"Rue Grande",
    "iso:country":"BE",
    "sg:address":"Rue Grande 136",
    "sg:city":"Estinnes",
    "sg:orig_category":"Installation de menuiserie en bois and plastique",
    "sg:phone":"+32 64 34 12 90",
    "sg:postcode":"7120",
    "sg:province":"Hainaut",
    "wof:name":"Rudi Bouhez",
    "wof:placetype":"venue"
},
  "geometry": {"coordinates":[4.1036081314,50.4045028687],"type":"Point"}
}