{
  "type": "Feature",
  "properties": {
    "iso:country":"BE",
    "sg:address":"Rue Des Fran\u00e7ais 17",
    "sg:city":"Aiseau-presles (roselies)",
    "sg:classifiers":[
        {
            "category":"Personal",
            "subcategory":"Beauty Salon",
            "type":"Services"
        }
    ],
    "sg:phone":"+32 71 76 09 39",
    "sg:postcode":"6250",
    "sg:province":"Hainaut",
    "sg:tags":[
        "lady",
        "-",
        "hairdressing"
    ],
    "wof:name":"Van Cauteren J.p.",
    "wof:placetype":"venue"
},
  "geometry": {"coordinates":[4.5749797821,50.4276313782],"type":"Point"}
}