{
  "type": "Feature",
  "properties": {
    "iso:country":"BE",
    "sg:address":"Parkstraat 6 Box 1",
    "sg:city":"Overpelt",
    "sg:classifiers":[
        {
            "category":"Health Services",
            "subcategory":"Dentist",
            "type":"Services"
        }
    ],
    "sg:phone":"+32 11 64 40 41",
    "sg:postcode":"3900",
    "sg:province":"Limburg",
    "wof:name":"Knevels Marc",
    "wof:placetype":"venue"
},
  "geometry": {"coordinates":[5.4235649109,51.2117614746],"type":"Point"}
}