{
  "type": "Feature",
  "properties": {
    "addr:full":"Bakestraat 146 Keerbergen Vlaams-Brabant 3140",
    "addr:housenumber":"146",
    "addr:postcode":"3140",
    "addr:street":"Bakestraat",
    "iso:country":"BE",
    "sg:address":"Bakestraat 146",
    "sg:city":"Keerbergen",
    "sg:orig_category":"V\u00e9los",
    "sg:phone":"+32 15 52 91 29",
    "sg:postcode":"3140",
    "sg:province":"Vlaams-Brabant",
    "wof:name":"Christiaens",
    "wof:placetype":"venue"
},
  "geometry": {"coordinates":[4.6467638016,51.0150527954],"type":"Point"}
}