{
  "type": "Feature",
  "properties": {
    "addr:full":"Rue Du Panorama 2 Verviers Li\u00e8ge 4801",
    "addr:housenumber":"2",
    "addr:postcode":"4801",
    "addr:street":"Rue Du Panorama",
    "iso:country":"BE",
    "sg:address":"Rue Du Panorama 2",
    "sg:city":"Verviers",
    "sg:orig_category":"Cr\u00e9dits divers",
    "sg:postcode":"4801",
    "sg:province":"Li\u00e8ge",
    "wof:name":"Bancontact-mister Cash",
    "wof:placetype":"venue"
},
  "geometry": {"coordinates":[5.8930549622,50.5922393799],"type":"Point"}
}