{
  "type": "Feature",
  "properties": {
    "iso:country":"BE",
    "sg:address":"Ketenstraat 95",
    "sg:city":"Moorslede (dadizele)",
    "sg:classifiers":[
        {
            "category":"Manufacturing",
            "subcategory":"Tools & Machinery",
            "type":"Manufacturing & Wholesale Goods"
        }
    ],
    "sg:phone":"+32 56 50 16 75",
    "sg:postcode":"8890",
    "sg:province":"West-Vlaanderen",
    "sg:tags":[
        "builder"
    ],
    "wof:name":"Demeulenaere H",
    "wof:placetype":"venue"
},
  "geometry": {"coordinates":[3.0922179222,50.8476104736],"type":"Point"}
}