{
  "type": "Feature",
  "properties": {
    "addr:full":"Oosterring 14 Genk Limburg 3600",
    "addr:housenumber":"14",
    "addr:postcode":"3600",
    "addr:street":"Oosterring",
    "iso:country":"BE",
    "sg:address":"Oosterring 14",
    "sg:city":"Genk",
    "sg:classifiers":[
        {
            "category":"Home & Garden",
            "subcategory":"Carpets & Floor Coverings",
            "type":"Retail Goods"
        }
    ],
    "sg:phone":"+32 89 62 01 00",
    "sg:postcode":"3600",
    "sg:province":"Limburg",
    "sg:tags":[
        "automobile",
        "-",
        "upholstering",
        "cover"
    ],
    "wof:name":"Rieter Automotive Belgium Nv",
    "wof:placetype":"venue"
},
  "geometry": {"coordinates":[5.5311479568,50.9225769043],"type":"Point"}
}