{
  "type": "Feature",
  "properties": {
    "iso:country":"BE",
    "sg:address":"Kolonel Picquartlaan 62",
    "sg:city":"Schaarbeek/schaerbeek",
    "sg:orig_category":"Binnenhuisarchitecten",
    "sg:phone":"+32 2 242 35 55",
    "sg:postcode":"1030",
    "sg:province":"Bruxelles-Capitale",
    "wof:name":"Raymond Leclercq",
    "wof:placetype":"venue"
},
  "geometry": {"coordinates":[4.3840241432,50.8776779175],"type":"Point"}
}