{
  "type": "Feature",
  "properties": {
    "addr:full":"Avenue Louise 181 Bruxelles (ixelles) Bruxelles-Capitale 1050",
    "addr:housenumber":"181",
    "addr:postcode":"1050",
    "addr:street":"Avenue Louise",
    "iso:country":"BE",
    "sg:address":"Avenue Louise 181",
    "sg:city":"Bruxelles (ixelles)",
    "sg:classifiers":[
        {
            "category":"Health Services",
            "subcategory":"Dentist",
            "type":"Services"
        }
    ],
    "sg:phone":"+32 2 647 22 11",
    "sg:postcode":"1050",
    "sg:province":"Bruxelles-Capitale",
    "wof:name":"Van De Voorde Omer",
    "wof:placetype":"venue"
},
  "geometry": {"coordinates":[4.3629221916,50.8276138306],"type":"Point"}
}