{
  "type": "Feature",
  "properties": {
    "addr:full":"Koningin Astridlaan 1 Bredene West-Vlaanderen 8450",
    "addr:housenumber":"1",
    "addr:postcode":"8450",
    "addr:street":"Koningin Astridlaan",
    "iso:country":"BE",
    "sg:address":"Koningin Astridlaan 1",
    "sg:city":"Bredene",
    "sg:classifiers":[
        {
            "category":"Recreation",
            "subcategory":"Campground",
            "type":"Entertainment"
        }
    ],
    "sg:phone":"+32 59 32 12 47",
    "sg:postcode":"8450",
    "sg:province":"West-Vlaanderen",
    "sg:tags":[
        "site",
        "camping"
    ],
    "wof:name":"Camping Astrid",
    "wof:placetype":"venue"
},
  "geometry": {"coordinates":[2.9688589573,51.249874115],"type":"Point"}
}