{
  "type": "Feature",
  "properties": {
    "addr:full":"Avenue Du Fort 280 Fl\u00e9malle Li\u00e8ge 4400",
    "addr:housenumber":"280",
    "addr:postcode":"4400",
    "addr:street":"Avenue Du Fort",
    "iso:country":"BE",
    "sg:address":"Avenue Du Fort 280",
    "sg:city":"Fl\u00e9malle",
    "sg:classifiers":[
        {
            "category":"Arena",
            "subcategory":"Sports Club",
            "type":"Entertainment"
        }
    ],
    "sg:phone":"+32 4 233 77 42",
    "sg:postcode":"4400",
    "sg:province":"Li\u00e8ge",
    "wof:name":"Centre Sportif De Tir Fl\u00e9malois",
    "wof:placetype":"venue"
},
  "geometry": {"coordinates":[5.4653730392,50.6132469177],"type":"Point"}
}