{
  "type": "Feature",
  "properties": {
    "iso:country":"BE",
    "sg:address":"Peraltastraat 20",
    "sg:city":"Brugge",
    "sg:classifiers":[
        {
            "category":"Food & Beverages",
            "subcategory":"Fruits & Vegetables",
            "type":"Retail Goods"
        }
    ],
    "sg:phone":"+32 50 32 37 77",
    "sg:postcode":"8000",
    "sg:province":"West-Vlaanderen",
    "sg:tags":[
        "dried"
    ],
    "wof:name":"Delidaele",
    "wof:placetype":"venue"
},
  "geometry": {"coordinates":[3.2122519016,51.241317749],"type":"Point"}
}