{
  "type": "Feature",
  "properties": {
    "addr:full":"Avenue Mon Plaisir 99 Brussel/bruxelles Bruxelles-Capitale 1030",
    "addr:housenumber":"99",
    "addr:postcode":"1030",
    "addr:street":"Avenue Mon Plaisir;/",
    "iso:country":"BE",
    "sg:address":"Avenue Mon Plaisir 99",
    "sg:city":"Brussel/bruxelles",
    "sg:classifiers":[
        {
            "category":"Travel",
            "subcategory":"Hotels & Motels",
            "type":"Entertainment"
        }
    ],
    "sg:phone":"+32 2 242 53 93",
    "sg:postcode":"1030",
    "sg:province":"Bruxelles-Capitale",
    "wof:name":"Studio 99",
    "wof:placetype":"venue"
},
  "geometry": {"coordinates":[4.3786587715,50.8771972656],"type":"Point"}
}