{
  "type": "Feature",
  "properties": {
    "iso:country":"BE",
    "sg:address":"Middelstraat 25",
    "sg:city":"Lo-reninge",
    "sg:orig_category":"Eleveurs and marchands de porcs. Eleveurs de bovins",
    "sg:phone":"+32 51 54 43 92",
    "sg:postcode":"8647",
    "sg:province":"West-Vlaanderen",
    "wof:name":"Henri Decaesteker",
    "wof:placetype":"venue"
},
  "geometry": {"coordinates":[2.8133900166,50.9482879639],"type":"Point"}
}