{
  "type": "Feature",
  "properties": {
    "addr:full":"G. Vanden Berghestraat 1 Anderlecht/anderlecht Bruxelles-Capitale 1070",
    "addr:housenumber":"1",
    "addr:postcode":"1070",
    "addr:street":"G. Vanden Berghestraat",
    "iso:country":"BE",
    "sg:address":"G. Vanden Berghestraat 1",
    "sg:city":"Anderlecht/anderlecht",
    "sg:orig_category":"Brood, gebak and snoepgoed",
    "sg:phone":"+32 2 521 80 84",
    "sg:postcode":"1070",
    "sg:province":"Bruxelles-Capitale",
    "wof:name":"P\u00c2tisserie St.anne",
    "wof:placetype":"venue"
},
  "geometry": {"coordinates":[4.3048510551,50.8370895386],"type":"Point"}
}