{
  "type": "Feature",
  "properties": {
    "addr:full":"Rue De Fosse Roulette 4 Vielsalm Luxembourg 6690",
    "addr:housenumber":"4",
    "addr:postcode":"6690",
    "addr:street":"Rue De Fosse Roulette",
    "iso:country":"BE",
    "sg:address":"Rue De Fosse Roulette 4",
    "sg:city":"Vielsalm",
    "sg:classifiers":[
        {
            "category":"Shopping",
            "subcategory":"Crafts & Fabrics",
            "type":"Retail Goods"
        }
    ],
    "sg:phone":"+32 80 21 61 14",
    "sg:postcode":"6690",
    "sg:province":"Luxembourg",
    "sg:tags":[
        "paints",
        "varnish",
        "-",
        "lacquers",
        "enamel"
    ],
    "wof:name":"Lallemand",
    "wof:placetype":"venue"
},
  "geometry": {"coordinates":[5.9109969139,50.2790908813],"type":"Point"}
}