{
  "type": "Feature",
  "properties": {
    "addr:full":"Rue Neuve 7 Huy Li\u00e8ge 4500",
    "addr:housenumber":"7",
    "addr:postcode":"4500",
    "addr:street":"Rue Neuve",
    "iso:country":"BE",
    "sg:address":"Rue Neuve 7",
    "sg:city":"Huy",
    "sg:classifiers":[
        {
            "category":"Utilities",
            "subcategory":"Telephone",
            "type":"Services"
        }
    ],
    "sg:phone":"+32 85 31 05 70",
    "sg:postcode":"4500",
    "sg:province":"Li\u00e8ge",
    "sg:tags":[
        "house",
        "phone",
        "telecommunicatieapparaten"
    ],
    "wof:name":"The Phone House",
    "wof:placetype":"venue"
},
  "geometry": {"coordinates":[5.2360229492,50.5205039978],"type":"Point"}
}