{
  "type": "Feature",
  "properties": {
    "addr:full":"Rue G\u00c9o Warz\u00c9e 6 Wanze Li\u00e8ge 4520",
    "addr:housenumber":"6",
    "addr:postcode":"4520",
    "addr:street":"Rue Ge\u0301O Warze\u0301E",
    "iso:country":"BE",
    "sg:address":"Rue G\u00c9o Warz\u00c9e 6",
    "sg:city":"Wanze",
    "sg:orig_category":"Installation de menuiserie en bois and plastique",
    "sg:phone":"+32 85 23 53 67",
    "sg:postcode":"4520",
    "sg:province":"Li\u00e8ge",
    "wof:name":"Menuiserie Destockay",
    "wof:placetype":"venue"
},
  "geometry": {"coordinates":[5.2215719223,50.5357513428],"type":"Point"}
}