{
  "type": "Feature",
  "properties": {
    "iso:country":"BE",
    "sg:address":"Gentse Heerweg 69",
    "sg:city":"Waregem",
    "sg:classifiers":[
        {
            "category":"Professional",
            "subcategory":"Art Services",
            "type":"Services"
        }
    ],
    "sg:phone":"+32 472 44 30 89",
    "sg:postcode":"8790",
    "sg:province":"West-Vlaanderen",
    "sg:tags":[
        "graphic",
        "designer"
    ],
    "wof:name":"A Yeah Right Design",
    "wof:placetype":"venue"
},
  "geometry": {"coordinates":[3.4503920078,50.8932113647],"type":"Point"}
}