{
  "type": "Feature",
  "properties": {
    "iso:country":"BE",
    "sg:address":"Melveren-centrum 27",
    "sg:city":"Sint-truiden",
    "sg:classifiers":[
        {
            "category":"Restaurant",
            "type":"Food & Drink"
        }
    ],
    "sg:phone":"+32 11 68 14 38",
    "sg:postcode":"3800",
    "sg:province":"Limburg",
    "sg:tags":[
        "caf\u00e9s"
    ],
    "wof:name":"Taverne Melveren",
    "wof:placetype":"venue"
},
  "geometry": {"coordinates":[5.2012419701,50.8305931091],"type":"Point"}
}