{
  "type": "Feature",
  "properties": {
    "iso:country":"BE",
    "sg:address":"Jan Van Ruusbroecstraat 22",
    "sg:city":"Roeselare",
    "sg:orig_category":"Paramedische behandelingen",
    "sg:phone":"+32 51 22 10 58",
    "sg:postcode":"8800",
    "sg:province":"West-Vlaanderen",
    "wof:name":"K. Verstraete",
    "wof:placetype":"venue"
},
  "geometry": {"coordinates":[3.1285839081,50.9637794495],"type":"Point"}
}