{
  "type": "Feature",
  "properties": {
    "addr:full":"Place De Ros\u00e9e 40a Florennes (ros\u00e9e) Namur 5620",
    "addr:housenumber":"40a",
    "addr:postcode":"5620",
    "addr:street":"Place De Rose\u0301E",
    "iso:country":"BE",
    "sg:address":"Place De Ros\u00e9e 40a",
    "sg:city":"Florennes (ros\u00e9e)",
    "sg:classifiers":[
        {
            "category":"Retail",
            "subcategory":"Auto Repair",
            "type":"Services"
        }
    ],
    "sg:phone":"+32 82 68 81 42",
    "sg:postcode":"5620",
    "sg:province":"Namur",
    "sg:tags":[
        "garage"
    ],
    "wof:name":"Garage Duchesse",
    "wof:placetype":"venue"
},
  "geometry": {"coordinates":[4.6046648026,50.2513809204],"type":"Point"}
}