{
  "type": "Feature",
  "properties": {
    "addr:full":"Dokter Persoonslaan 35 Willebroek Antwerpen 2830",
    "addr:housenumber":"35",
    "addr:postcode":"2830",
    "addr:street":"Dokter Persoonslaan",
    "iso:country":"BE",
    "sg:address":"Dokter Persoonslaan 35",
    "sg:city":"Willebroek",
    "sg:orig_category":"Boucheries",
    "sg:phone":"+32 3 886 66 44",
    "sg:postcode":"2830",
    "sg:province":"Antwerpen",
    "wof:name":"Emiel Verheyden",
    "wof:placetype":"venue"
},
  "geometry": {"coordinates":[4.3612570763,51.0597915649],"type":"Point"}
}