{
  "type": "Feature",
  "properties": {
    "iso:country":"BE",
    "sg:address":"Rue Hector Denis 51",
    "sg:city":"Charleroi (mont-sur-marchienne)",
    "sg:classifiers":[
        {
            "category":"Health Services",
            "subcategory":"Nursing And Care Facility",
            "type":"Services"
        }
    ],
    "sg:phone":"+32 71 36 94 15",
    "sg:postcode":"6032",
    "sg:province":"Hainaut",
    "sg:tags":[
        "home"
    ],
    "wof:name":"Renier M",
    "wof:placetype":"venue"
},
  "geometry": {"coordinates":[4.4066781998,50.3866844177],"type":"Point"}
}