{
  "type": "Feature",
  "properties": {
    "iso:country":"BE",
    "sg:address":"Avenue Des Pl\u00e9iades 35",
    "sg:city":"Wavre (limal)",
    "sg:classifiers":[
        {
            "category":"Government",
            "subcategory":"Office",
            "type":"Public Place"
        }
    ],
    "sg:phone":"+32 10 41 93 85",
    "sg:postcode":"1300",
    "sg:province":"Brabant Wallon",
    "sg:tags":[
        "-",
        "tourism",
        "federation"
    ],
    "wof:name":"Minnoy V",
    "wof:placetype":"venue"
},
  "geometry": {"coordinates":[4.5642142296,50.7108573914],"type":"Point"}
}