{
  "type": "Feature",
  "properties": {
    "iso:country":"BE",
    "sg:address":"Rue De Marchienne 203",
    "sg:city":"Montigny-le-tilleul",
    "sg:orig_category":"Boekenuitgeverijen Drukkerijen and copyshops Secretariaatsdiensten",
    "sg:phone":"+32 71 51 63 35",
    "sg:postcode":"6110",
    "sg:province":"Hainaut",
    "wof:name":"Scaillet",
    "wof:placetype":"venue"
},
  "geometry": {"coordinates":[4.3837809563,50.3875656128],"type":"Point"}
}