{
  "type": "Feature",
  "properties": {
    "iso:country":"BE",
    "sg:address":"Kerrebroekstraat 8",
    "sg:city":"Lochristi",
    "sg:orig_category":"Plantes and fleurs Gr",
    "sg:phone":"+32 9 367 54 04",
    "sg:postcode":"9080",
    "sg:province":"Oost-Vlaanderen",
    "wof:name":"Imschoot A",
    "wof:placetype":"venue"
},
  "geometry": {"coordinates":[3.9218819141,51.0766563416],"type":"Point"}
}