{
  "type": "Feature",
  "properties": {
    "addr:full":"Pannestraat 40 Veurne West-Vlaanderen 8630",
    "addr:housenumber":"40",
    "addr:postcode":"8630",
    "addr:street":"Pannestraat",
    "iso:country":"BE",
    "sg:address":"Pannestraat 40",
    "sg:city":"Veurne",
    "sg:classifiers":[
        {
            "category":"Home & Garden",
            "subcategory":"Household Appliances",
            "type":"Retail Goods"
        }
    ],
    "sg:phone":"+32 58 31 13 29",
    "sg:postcode":"8630",
    "sg:province":"West-Vlaanderen",
    "sg:tags":[
        "housewares",
        "-"
    ],
    "wof:name":"Callewaert Elektro Nv",
    "wof:placetype":"venue"
},
  "geometry": {"coordinates":[2.6594700813,51.0743141174],"type":"Point"}
}