{
  "type": "Feature",
  "properties": {
    "iso:country":"BE",
    "sg:address":"Bunderbeeklaan 19",
    "sg:city":"Kapellen",
    "sg:orig_category":"Krantenuitgeverijen Tijdschriftenuitgeverijen",
    "sg:phone":"+32 3 664 17 12",
    "sg:postcode":"2950",
    "sg:province":"Antwerpen",
    "wof:name":"Eurobesitas",
    "wof:placetype":"venue"
},
  "geometry": {"coordinates":[4.4407172203,51.309677124],"type":"Point"}
}