{
  "type": "Feature",
  "properties": {
    "iso:country":"BE",
    "sg:address":"Wijngaardveld 44",
    "sg:city":"Aalst",
    "sg:classifiers":[
        {
            "category":"Home & Garden",
            "subcategory":"Building Materials",
            "type":"Retail Goods"
        }
    ],
    "sg:phone":"+32 53 78 02 58",
    "sg:postcode":"9300",
    "sg:province":"Oost-Vlaanderen",
    "sg:tags":[
        "house"
    ],
    "wof:name":"Chalets Baka Bvba-sprl",
    "wof:placetype":"venue"
},
  "geometry": {"coordinates":[4.0628237724,50.940448761],"type":"Point"}
}