{
  "type": "Feature",
  "properties": {
    "iso:country":"BE",
    "sg:address":"Oudenweg 74",
    "sg:city":"Riemst",
    "sg:orig_category":"Location d'articles de sport, de sport nautique and de camping",
    "sg:phone":"+32 12 45 22 44",
    "sg:postcode":"3770",
    "sg:province":"Limburg",
    "wof:name":"De Tweewieler",
    "wof:placetype":"venue"
},
  "geometry": {"coordinates":[5.5969901085,50.8109016418],"type":"Point"}
}