{
  "type": "Feature",
  "properties": {
    "iso:country":"BE",
    "sg:address":"Vooruitgangstraat 44",
    "sg:city":"Liedekerke",
    "sg:classifiers":[
        {
            "category":"Health Services",
            "subcategory":"Health Practitioner",
            "type":"Services"
        }
    ],
    "sg:phone":"+32 53 66 17 50",
    "sg:postcode":"1770",
    "sg:province":"Vlaams-Brabant",
    "sg:tags":[
        "physiotherapist"
    ],
    "wof:name":"Vercammen S",
    "wof:placetype":"venue"
},
  "geometry": {"coordinates":[4.0848069191,50.8650054932],"type":"Point"}
}