{
  "type": "Feature",
  "properties": {
    "addr:full":"Gladiolenstraat 1 Sint-niklaas Oost-Vlaanderen 9100",
    "addr:housenumber":"1",
    "addr:postcode":"9100",
    "addr:street":"Gladiolenstraat",
    "iso:country":"BE",
    "sg:address":"Gladiolenstraat 1",
    "sg:city":"Sint-niklaas",
    "sg:classifiers":[
        {
            "category":"Bakery",
            "type":"Food & Drink"
        }
    ],
    "sg:phone":"+32 3 776 21 21",
    "sg:postcode":"9100",
    "sg:province":"Oost-Vlaanderen",
    "sg:tags":[
        "confectioner",
        "baker"
    ],
    "wof:name":"De Vaeren",
    "wof:placetype":"venue"
},
  "geometry": {"coordinates":[4.1573390961,51.161403656],"type":"Point"}
}