{
  "type": "Feature",
  "properties": {
    "iso:country":"BE",
    "sg:address":"Rue De La Chapelle 5",
    "sg:city":"Habay (habay-la-neuve)",
    "sg:classifiers":[
        {
            "category":"Shopping",
            "subcategory":"Books",
            "type":"Retail Goods"
        }
    ],
    "sg:phone":"+32 63 42 23 75",
    "sg:postcode":"6720",
    "sg:province":"Luxembourg",
    "sg:tags":[
        "bookseller"
    ],
    "wof:name":"Halbardier-librairie",
    "wof:placetype":"venue"
},
  "geometry": {"coordinates":[5.6468100548,49.7278633118],"type":"Point"}
}