{
  "type": "Feature",
  "properties": {
    "addr:full":"Oude Kantinestraat 13 Roeselare West-Vlaanderen 8800",
    "addr:housenumber":"13",
    "addr:postcode":"8800",
    "addr:street":"Oude Kantinestraat",
    "iso:country":"BE",
    "sg:address":"Oude Kantinestraat 13",
    "sg:city":"Roeselare",
    "sg:orig_category":"Installation de menuiserie en bois and plastique",
    "sg:phone":"+32 51 20 87 08",
    "sg:postcode":"8800",
    "sg:province":"West-Vlaanderen",
    "wof:name":"Cools",
    "wof:placetype":"venue"
},
  "geometry": {"coordinates":[3.1612598896,50.8919487],"type":"Point"}
}