{
  "type": "Feature",
  "properties": {
    "iso:country":"BE",
    "sg:address":"Cornelis Peetersstraat 4",
    "sg:city":"Machelen",
    "sg:orig_category":"Banken and kredietinstellingen",
    "sg:phone":"+32 2 251 63 97",
    "sg:postcode":"1830",
    "sg:province":"Vlaams-Brabant",
    "wof:name":"Bacob",
    "wof:placetype":"venue"
},
  "geometry": {"coordinates":[4.4349012375,50.912071228],"type":"Point"}
}