{
  "type": "Feature",
  "properties": {
    "addr:full":"Rijselstraat 63 Menen West-Vlaanderen 8930",
    "addr:housenumber":"63",
    "addr:postcode":"8930",
    "addr:street":"Rijselstraat",
    "iso:country":"BE",
    "sg:address":"Rijselstraat 63",
    "sg:city":"Menen",
    "sg:orig_category":"Baby- and kinderkleding Babyspullen",
    "sg:phone":"+32 56 51 23 13",
    "sg:postcode":"8930",
    "sg:province":"West-Vlaanderen",
    "wof:name":"Huis Delphine",
    "wof:placetype":"venue"
},
  "geometry": {"coordinates":[3.1225678921,50.7932434082],"type":"Point"}
}