{
  "type": "Feature",
  "properties": {
    "addr:full":"Nieuwelaan 1 Meise Vlaams-Brabant 1860",
    "addr:housenumber":"1",
    "addr:postcode":"1860",
    "addr:street":"Nieuwelaan",
    "iso:country":"BE",
    "sg:address":"Nieuwelaan 1",
    "sg:city":"Meise",
    "sg:orig_category":"Rusthuizen and serviceflats",
    "sg:phone":"+32 2 269 80 31",
    "sg:postcode":"1860",
    "sg:province":"Vlaams-Brabant",
    "wof:name":"Home Select",
    "wof:placetype":"venue"
},
  "geometry": {"coordinates":[4.3302731514,50.9353218079],"type":"Point"}
}