{
  "type": "Feature",
  "properties": {
    "iso:country":"BE",
    "sg:address":"Rue Du Moulin-\u00c0-vent 36",
    "sg:city":"Gembloux",
    "sg:orig_category":"Mus\u00e9es and patrimoine culturel. Caf\u00e9s",
    "sg:phone":"+32 81 64 02 78",
    "sg:postcode":"5031",
    "sg:province":"Namur",
    "wof:name":"Moulin Defrenne",
    "wof:placetype":"venue"
},
  "geometry": {"coordinates":[4.766228199,50.5746688843],"type":"Point"}
}