{
  "type": "Feature",
  "properties": {
    "iso:country":"BE",
    "sg:address":"Rue De L'abbaye 47b1",
    "sg:city":"Ans",
    "sg:orig_category":"Advocaten and juridische adviseurs",
    "sg:phone":"+32 4 239 07 07",
    "sg:postcode":"4432",
    "sg:province":"Li\u00e8ge",
    "wof:name":"B. Perin",
    "wof:placetype":"venue"
},
  "geometry": {"coordinates":[5.5242800713,50.6659317017],"type":"Point"}
}