{
  "type": "Feature",
  "properties": {
    "iso:country":"BE",
    "sg:address":"Winterperre 13",
    "sg:city":"Beersel",
    "sg:orig_category":"Diepvriesproducten Gh",
    "sg:phone":"+32 2 380 33 45",
    "sg:postcode":"1653",
    "sg:province":"Vlaams-Brabant",
    "wof:name":"Y & P Trade Europe",
    "wof:placetype":"venue"
},
  "geometry": {"coordinates":[4.2991251945,50.7301254272],"type":"Point"}
}