{
  "type": "Feature",
  "properties": {
    "addr:full":"Lendedreef 48 Anzegem (vichte) West-Vlaanderen 8570",
    "addr:housenumber":"48",
    "addr:postcode":"8570",
    "addr:street":"Lendedreef",
    "iso:country":"BE",
    "sg:address":"Lendedreef 48",
    "sg:city":"Anzegem (vichte)",
    "sg:classifiers":[
        {
            "category":"Food & Beverages",
            "subcategory":"Groceries & Convenience Stores",
            "type":"Retail Goods"
        }
    ],
    "sg:phone":"+32 56 77 61 58",
    "sg:postcode":"8570",
    "sg:province":"West-Vlaanderen",
    "sg:tags":[
        "grocer"
    ],
    "wof:name":"Marketje",
    "wof:placetype":"venue"
},
  "geometry": {"coordinates":[3.3885819912,50.8377113342],"type":"Point"}
}