{
  "type": "Feature",
  "properties": {
    "addr:full":"Rue De Chaudfontaine 18 Li\u00e8ge 1 (li\u00e8ge 2) Li\u00e8ge 4020",
    "addr:housenumber":"18;1;2",
    "addr:postcode":"4020",
    "addr:street":"Rue De Chaudfontaine",
    "iso:country":"BE",
    "sg:address":"Rue De Chaudfontaine 18",
    "sg:city":"Li\u00e8ge 1 (li\u00e8ge 2)",
    "sg:classifiers":[
        {
            "category":"Health Services",
            "subcategory":"Health Practitioner",
            "type":"Services"
        }
    ],
    "sg:phone":"+32 4 344 30 26",
    "sg:postcode":"4020",
    "sg:province":"Li\u00e8ge",
    "sg:tags":[
        "osteopath"
    ],
    "wof:name":"Leplat Bertrand",
    "wof:placetype":"venue"
},
  "geometry": {"coordinates":[5.5855770111,50.6217536926],"type":"Point"}
}