{
  "type": "Feature",
  "properties": {
    "addr:full":"Rue Du Ch\u00e2teau Saint-pierre 4 Le Roeulx (thieu) Hainaut 7070",
    "addr:housenumber":"4",
    "addr:postcode":"7070",
    "addr:street":"Rue Du Cha\u0302Teau Saint-Pierre",
    "iso:country":"BE",
    "sg:address":"Rue Du Ch\u00e2teau Saint-pierre 4",
    "sg:city":"Le Roeulx (thieu)",
    "sg:classifiers":[
        {
            "category":"Parking",
            "subcategory":"Garage",
            "type":"Transportation"
        }
    ],
    "sg:phone":"+32 64 66 51 94",
    "sg:postcode":"7070",
    "sg:province":"Hainaut",
    "sg:tags":[
        "truck",
        "-",
        "dump",
        "transport"
    ],
    "wof:name":"Leoncelli M",
    "wof:placetype":"venue"
},
  "geometry": {"coordinates":[4.1089110374,50.4947967529],"type":"Point"}
}