{
  "type": "Feature",
  "properties": {
    "addr:full":"Koning Leopold Iii-laan 113 Brugge (sint-andries) West-Vlaanderen 8200",
    "addr:housenumber":"113",
    "addr:postcode":"8200",
    "addr:street":"Koning Leopold Iii-Laan",
    "iso:country":"BE",
    "sg:address":"Koning Leopold Iii-laan 113",
    "sg:city":"Brugge (sint-andries)",
    "sg:classifiers":[
        {
            "category":"Building & Trades",
            "subcategory":"Landscaping Services",
            "type":"Services"
        }
    ],
    "sg:phone":"+32 50 35 46 77",
    "sg:postcode":"8200",
    "sg:province":"West-Vlaanderen",
    "sg:tags":[
        "-",
        "lopping",
        "work",
        "tree",
        "felling"
    ],
    "wof:name":"Clemmens H",
    "wof:placetype":"venue"
},
  "geometry": {"coordinates":[3.1880040169,51.189868927],"type":"Point"}
}