{
  "type": "Feature",
  "properties": {
    "iso:country":"BE",
    "sg:address":"Europark 2015",
    "sg:city":"Houthalen-helchteren",
    "sg:orig_category":"Installation de menuiserie en bois and plastique. Eclairage et \u00e9quipements du foyer. Mat\u00e9riaux de co",
    "sg:phone":"+32 11 52 42 64",
    "sg:postcode":"3530",
    "sg:province":"Limburg",
    "wof:name":"Belcopur",
    "wof:placetype":"venue"
},
  "geometry": {"coordinates":[5.3928050995,51.0387268066],"type":"Point"}
}