{
  "type": "Feature",
  "properties": {
    "addr:full":"Geneberg 10ba Ham Limburg 3945",
    "addr:housenumber":"10ba",
    "addr:postcode":"3945",
    "addr:street":"Geneberg",
    "iso:country":"BE",
    "sg:address":"Geneberg 10ba",
    "sg:city":"Ham",
    "sg:orig_category":"Natuursteenbewerking Speciaalzaken Vloer- and muurbekleding",
    "sg:phone":"+32 11 34 15 67",
    "sg:postcode":"3945",
    "sg:province":"Limburg",
    "wof:name":"Gebroeders Jannes",
    "wof:placetype":"venue"
},
  "geometry": {"coordinates":[5.1776199341,51.1046104431],"type":"Point"}
}