{
  "type": "Feature",
  "properties": {
    "iso:country":"BE",
    "sg:address":"Zilveren Helmenstraat 38",
    "sg:city":"Halen",
    "sg:classifiers":[
        {
            "category":"Home & Garden",
            "subcategory":"Home Furnishings",
            "type":"Retail Goods"
        }
    ],
    "sg:phone":"+32 13 44 28 49",
    "sg:postcode":"3545",
    "sg:province":"Limburg",
    "sg:tags":[
        "curtain",
        "-",
        "fixture"
    ],
    "wof:name":"Raymakers A",
    "wof:placetype":"venue"
},
  "geometry": {"coordinates":[5.0803427696,50.9373512268],"type":"Point"}
}