{
  "type": "Feature",
  "properties": {
    "addr:full":"Rue Du Trefle 50 Herve Li\u00e8ge 4650",
    "addr:housenumber":"50",
    "addr:postcode":"4650",
    "addr:street":"Rue Du Trefle",
    "iso:country":"BE",
    "sg:address":"Rue Du Trefle 50",
    "sg:city":"Herve",
    "sg:orig_category":"Entretien and r\u00e9parations de voitures. Pi\u00e8ces and accessoires de v\u00e9hicules automobiles Gr",
    "sg:phone":"+32 87 67 52 89",
    "sg:postcode":"4650",
    "sg:province":"Li\u00e8ge",
    "wof:name":"Malta",
    "wof:placetype":"venue"
},
  "geometry": {"coordinates":[5.8459858894,50.6298141479],"type":"Point"}
}