{
  "type": "Feature",
  "properties": {
    "iso:country":"BE",
    "sg:address":"Hasseltsesteenweg 166",
    "sg:city":"Beringen",
    "sg:classifiers":[
        {
            "category":"Personal",
            "subcategory":"Beauty Salon",
            "type":"Services"
        }
    ],
    "sg:phone":"+32 11 42 32 04",
    "sg:postcode":"3580",
    "sg:province":"Limburg",
    "sg:tags":[
        "de",
        "coiffure"
    ],
    "wof:name":"Coiffure Linda",
    "wof:placetype":"venue"
},
  "geometry": {"coordinates":[5.2349710464,51.0413398743],"type":"Point"}
}