{
  "type": "Feature",
  "properties": {
    "addr:full":"Rue De Droixhe 7bg Li\u00c8ge Li\u00e8ge 4020",
    "addr:postcode":"7bg;4020",
    "addr:street":"Rue De Droixhe",
    "iso:country":"BE",
    "sg:address":"Rue De Droixhe 7bg",
    "sg:city":"Li\u00c8ge",
    "sg:orig_category":"Slagers",
    "sg:phone":"+32 4 362 73 67",
    "sg:postcode":"4020",
    "sg:province":"Li\u00e8ge",
    "wof:name":"Les Cochonailles",
    "wof:placetype":"venue"
},
  "geometry": {"coordinates":[5.6107831001,50.6478004456],"type":"Point"}
}