{
  "type": "Feature",
  "properties": {
    "addr:full":"Avenue De La For\u00eat 117 Bruxelles Bruxelles-Capitale 1000",
    "addr:housenumber":"117",
    "addr:postcode":"1000",
    "addr:street":"Avenue De La Fore\u0302T",
    "iso:country":"BE",
    "sg:address":"Avenue De La For\u00eat 117",
    "sg:city":"Bruxelles",
    "sg:classifiers":[
        {
            "category":"Real Estate",
            "subcategory":"Architect",
            "type":"Services"
        }
    ],
    "sg:phone":"+32 2 673 32 02",
    "sg:postcode":"1000",
    "sg:province":"Bruxelles-Capitale",
    "wof:name":"Martel G",
    "wof:placetype":"venue"
},
  "geometry": {"coordinates":[4.3953948021,50.7984962463],"type":"Point"}
}