{
  "type": "Feature",
  "properties": {
    "addr:full":"Opstal 14 Beerse Antwerpen 2340",
    "addr:housenumber":"14",
    "addr:postcode":"2340",
    "addr:street":"Opstal",
    "iso:country":"BE",
    "sg:address":"Opstal 14",
    "sg:city":"Beerse",
    "sg:orig_category":"Installatie van metalen schrijnwerk Verlichting and huishoudartikelen",
    "sg:phone":"+32 14 61 54 88",
    "sg:postcode":"2340",
    "sg:province":"Antwerpen",
    "wof:name":"Haco",
    "wof:placetype":"venue"
},
  "geometry": {"coordinates":[4.8702778816,51.3279495239],"type":"Point"}
}