{
  "type": "Feature",
  "properties": {
    "addr:full":"Almeroth 6 Attert Luxembourg 6717",
    "addr:housenumber":"6",
    "addr:postcode":"6717",
    "addr:street":"Almeroth",
    "iso:country":"BE",
    "sg:address":"Almeroth 6",
    "sg:city":"Attert",
    "sg:classifiers":[
        {
            "category":"Sports & Exercise",
            "subcategory":"Sports Center",
            "type":"Entertainment"
        }
    ],
    "sg:phone":"+32 63 23 25 03",
    "sg:postcode":"6717",
    "sg:province":"Luxembourg",
    "sg:tags":[
        "terrain",
        "hors",
        "de",
        "installation",
        "sportifs"
    ],
    "wof:name":"Marie Fraipont",
    "wof:placetype":"venue"
},
  "geometry": {"coordinates":[5.7888741493,49.7506217957],"type":"Point"}
}