{
  "type": "Feature",
  "properties": {
    "iso:country":"BE",
    "sg:address":"Van Breestraat 27",
    "sg:city":"Antwerpen",
    "sg:classifiers":[
        {
            "category":"Professional",
            "subcategory":"Management & Consulting",
            "type":"Services"
        }
    ],
    "sg:phone":"+32 3 771 04 20",
    "sg:postcode":"2018",
    "sg:province":"Antwerpen",
    "sg:tags":[
        "consultant"
    ],
    "wof:name":"Deha En Partners",
    "wof:placetype":"venue"
},
  "geometry": {"coordinates":[4.4090690613,51.2100028992],"type":"Point"}
}