{
  "type": "Feature",
  "properties": {
    "iso:country":"BE",
    "sg:address":"Vis\u00e9steenweg 201",
    "sg:city":"Riemst (zichen-zussen-bolder)",
    "sg:classifiers":[
        {
            "category":"Health Services",
            "subcategory":"Dentist",
            "type":"Services"
        }
    ],
    "sg:phone":"+32 12 45 18 90",
    "sg:postcode":"3770",
    "sg:province":"Limburg",
    "wof:name":"Lambrechts Ester",
    "wof:placetype":"venue"
},
  "geometry": {"coordinates":[5.6054201126,50.8047485352],"type":"Point"}
}