{
  "type": "Feature",
  "properties": {
    "addr:full":"Rue Fernand Stilmant 13 Farciennes (pironchamps) Hainaut 6240",
    "addr:housenumber":"13",
    "addr:postcode":"6240",
    "addr:street":"Rue Fernand Stilmant",
    "iso:country":"BE",
    "sg:address":"Rue Fernand Stilmant 13",
    "sg:city":"Farciennes (pironchamps)",
    "sg:classifiers":[
        {
            "category":"Food & Beverages",
            "subcategory":"Groceries & Convenience Stores",
            "type":"Retail Goods"
        }
    ],
    "sg:phone":"+32 71 40 37 22",
    "sg:postcode":"6240",
    "sg:province":"Hainaut",
    "sg:tags":[
        "grocer"
    ],
    "wof:name":"Inter Alimentation Plus",
    "wof:placetype":"venue"
},
  "geometry": {"coordinates":[4.5326600075,50.4235191345],"type":"Point"}
}