{
  "type": "Feature",
  "properties": {
    "addr:full":"Route De Trazegnies 500 Charleroi Hainaut 6031",
    "addr:housenumber":"500",
    "addr:postcode":"6031",
    "addr:street":"Route De Trazegnies;Hainaut",
    "iso:country":"BE",
    "sg:address":"Route De Trazegnies 500",
    "sg:city":"Charleroi",
    "sg:orig_category":"Jardinage. Construction de rev\u00eatements routiers and sportifs",
    "sg:phone":"+32 71 70 18 50",
    "sg:postcode":"6031",
    "sg:province":"Hainaut",
    "wof:name":"T. Ed.",
    "wof:placetype":"venue"
},
  "geometry": {"coordinates":[4.38022995,50.4121742249],"type":"Point"}
}