{
  "type": "Feature",
  "properties": {
    "addr:full":"Nijvelsebaan 11 Overijse Vlaams-Brabant 3090",
    "addr:housenumber":"11",
    "addr:postcode":"3090",
    "addr:street":"Nijvelsebaan",
    "iso:country":"BE",
    "sg:address":"Nijvelsebaan 11",
    "sg:city":"Overijse",
    "sg:classifiers":[
        {
            "category":"Cafe",
            "type":"Food & Drink"
        }
    ],
    "sg:phone":"+32 2 687 67 38",
    "sg:postcode":"3090",
    "sg:province":"Vlaams-Brabant",
    "sg:tags":[
        "caf\u00e9s"
    ],
    "wof:name":"Xenophon Kaplanis",
    "wof:placetype":"venue"
},
  "geometry": {"coordinates":[4.5370159149,50.7600364685],"type":"Point"}
}