{
  "type": "Feature",
  "properties": {
    "addr:full":"Diestsesteenweg 34 Tielt-winge (tielt) Vlaams-Brabant 3390",
    "addr:housenumber":"34",
    "addr:postcode":"3390",
    "addr:street":"Diestsesteenweg",
    "iso:country":"BE",
    "sg:address":"Diestsesteenweg 34",
    "sg:city":"Tielt-winge (tielt)",
    "sg:classifiers":[
        {
            "category":"Fast Food",
            "type":"Food & Drink"
        }
    ],
    "sg:phone":"+32 16 63 15 13",
    "sg:postcode":"3390",
    "sg:province":"Vlaams-Brabant",
    "sg:tags":[
        "fried",
        "stand",
        "potato"
    ],
    "wof:name":"Oase",
    "wof:placetype":"venue"
},
  "geometry": {"coordinates":[4.9384198189,50.9336242676],"type":"Point"}
}