{
  "type": "Feature",
  "properties": {
    "iso:country":"BE",
    "sg:address":"Itali\u00cblei 48",
    "sg:city":"Antwerpen",
    "sg:orig_category":"D\u00e9corateurs d'int\u00e9rieur",
    "sg:phone":"+32 3 233 56 43",
    "sg:postcode":"2000",
    "sg:province":"Antwerpen",
    "wof:name":"Office Collection",
    "wof:placetype":"venue"
},
  "geometry": {"coordinates":[4.4148278236,51.2242240906],"type":"Point"}
}