{
  "type": "Feature",
  "properties": {
    "iso:country":"BE",
    "sg:address":"Jagerstraat 10",
    "sg:city":"Hamme",
    "sg:orig_category":"Centres de relaxation and bien-\u00eatre",
    "sg:phone":"+32 52 48 13 65",
    "sg:postcode":"9220",
    "sg:province":"Oost-Vlaanderen",
    "wof:name":"Sauna-fit",
    "wof:placetype":"venue"
},
  "geometry": {"coordinates":[4.1360478401,51.0987167358],"type":"Point"}
}