{
  "type": "Feature",
  "properties": {
    "iso:country":"BE",
    "sg:address":"Spoormakersstraat 57",
    "sg:city":"Brussel/bruxelles",
    "sg:classifiers":[
        {
            "category":"Restaurant",
            "type":"Food & Drink"
        }
    ],
    "sg:phone":"+32 2 512 11 11",
    "sg:postcode":"1000",
    "sg:province":"Bruxelles-Capitale",
    "wof:name":"Mystical Resto",
    "wof:placetype":"venue"
},
  "geometry": {"coordinates":[4.3531088829,50.8452796936],"type":"Point"}
}