{
  "type": "Feature",
  "properties": {
    "iso:country":"BE",
    "sg:address":"Vuurkruisenlaan 21",
    "sg:city":"Wijnegem",
    "sg:orig_category":"Sportclubs",
    "sg:phone":"+32 3 353 99 94",
    "sg:postcode":"2110",
    "sg:province":"Antwerpen",
    "wof:name":"B.c. St.job",
    "wof:placetype":"venue"
},
  "geometry": {"coordinates":[4.5105199814,51.2277030945],"type":"Point"}
}