{
  "type": "Feature",
  "properties": {
    "addr:full":"Surister 45 Jalhay Li\u00e8ge 4845",
    "addr:housenumber":"45",
    "addr:postcode":"4845",
    "addr:street":"Surister",
    "iso:country":"BE",
    "sg:address":"Surister 45",
    "sg:city":"Jalhay",
    "sg:orig_category":"Rundveehouders",
    "sg:phone":"+32 87 64 70 65",
    "sg:postcode":"4845",
    "sg:province":"Li\u00e8ge",
    "wof:name":"Jacques Kerf",
    "wof:placetype":"venue"
},
  "geometry": {"coordinates":[5.926030159,50.5511703491],"type":"Point"}
}