{
  "type": "Feature",
  "properties": {
    "addr:full":"August Van Landeghemstr. 40b Willebroek Antwerpen 2830",
    "addr:housenumber":"40b",
    "addr:postcode":"2830",
    "addr:street":"August;Landeghemstr.",
    "iso:country":"BE",
    "sg:address":"August Van Landeghemstr. 40b",
    "sg:city":"Willebroek",
    "sg:orig_category":"Kapsalons",
    "sg:phone":"+32 3 886 62 29",
    "sg:postcode":"2830",
    "sg:province":"Antwerpen",
    "wof:name":"Coiffure Beauty",
    "wof:placetype":"venue"
},
  "geometry": {"coordinates":[4.3602800369,51.060218811],"type":"Point"}
}