{
  "type": "Feature",
  "properties": {
    "addr:full":"Place Saint-aubain 5 Namur Namur 5000",
    "addr:housenumber":"5",
    "addr:postcode":"5000",
    "addr:street":"Place Saint-Aubain",
    "iso:country":"BE",
    "sg:address":"Place Saint-aubain 5",
    "sg:city":"Namur",
    "sg:orig_category":"Rechtbanken",
    "sg:phone":"+32 81 22 69 64",
    "sg:postcode":"5000",
    "sg:province":"Namur",
    "wof:name":"Tribunal De Police",
    "wof:placetype":"venue"
},
  "geometry": {"coordinates":[4.8605041504,50.4639358521],"type":"Point"}
}