{
  "type": "Feature",
  "properties": {
    "iso:country":"BE",
    "sg:address":"Sur La Carri\u00e8re 40",
    "sg:city":"Vis\u00e9 (richelle)",
    "sg:orig_category":"Non-Classified Establishments",
    "sg:phone":"+32 4 379 30 61",
    "sg:postcode":"4600",
    "sg:province":"Li\u00e8ge",
    "wof:name":"Onclin",
    "wof:placetype":"venue"
},
  "geometry": {"coordinates":[5.6947331429,50.7198944092],"type":"Point"}
}