{
  "type": "Feature",
  "properties": {
    "addr:full":"Hellebeemden 16 Hasselt Limburg 3500",
    "addr:housenumber":"16",
    "addr:postcode":"3500",
    "addr:street":"Hellebeemden",
    "iso:country":"BE",
    "sg:address":"Hellebeemden 16",
    "sg:city":"Hasselt",
    "sg:classifiers":[
        {
            "category":"Professional",
            "subcategory":"Advertising",
            "type":"Services"
        }
    ],
    "sg:phone":"+32 15 62 02 00",
    "sg:postcode":"3500",
    "sg:province":"Limburg",
    "sg:tags":[
        "illuminated"
    ],
    "wof:name":"Publilicht B.v.b.a.",
    "wof:placetype":"venue"
},
  "geometry": {"coordinates":[4.497713089,50.9840774536],"type":"Point"}
}