{
  "type": "Feature",
  "properties": {
    "iso:country":"BE",
    "sg:address":"Doornaardstraat 69",
    "sg:city":"Wommelgem",
    "sg:orig_category":"V\u00eatements pour Hommes",
    "sg:phone":"+32 3 353 91 90",
    "sg:postcode":"2160",
    "sg:province":"Antwerpen",
    "wof:name":"Huis Mister Dream",
    "wof:placetype":"venue"
},
  "geometry": {"coordinates":[4.5127301216,51.2134399414],"type":"Point"}
}