{
  "type": "Feature",
  "properties": {
    "iso:country":"BE",
    "sg:address":"Ervaert 10",
    "sg:city":"Borgloon",
    "sg:classifiers":[
        {
            "category":"Government",
            "subcategory":"Police Station",
            "type":"Public Place"
        }
    ],
    "sg:phone":"+32 12 74 14 16",
    "sg:postcode":"3840",
    "sg:province":"Limburg",
    "sg:tags":[
        "gendarmerie"
    ],
    "wof:name":"Federale Politie/police F\u00c9d\u00c9rale",
    "wof:placetype":"venue"
},
  "geometry": {"coordinates":[5.3444581032,50.8095359802],"type":"Point"}
}