{
  "type": "Feature",
  "properties": {
    "addr:full":"August Van Geertstraat 68 Gent Oost-Vlaanderen 9040",
    "addr:housenumber":"68",
    "addr:postcode":"9040",
    "addr:street":"August;Geertstraat;Oost-Vlaanderen",
    "iso:country":"BE",
    "sg:address":"August Van Geertstraat 68",
    "sg:city":"Gent",
    "sg:orig_category":"Artiesten and kunstenaars",
    "sg:phone":"+32 9 228 00 21",
    "sg:postcode":"9040",
    "sg:province":"Oost-Vlaanderen",
    "wof:name":"Anselme Deliaert",
    "wof:placetype":"venue"
},
  "geometry": {"coordinates":[3.7543599606,51.0673904419],"type":"Point"}
}