{
  "type": "Feature",
  "properties": {
    "addr:full":"Quai Des Charbonnages 36-38 Sint-jans-molenbeek/molenbeek- Bruxelles-Capitale 1080",
    "addr:housenumber":"36-38",
    "addr:postcode":"1080",
    "addr:street":"Quai Des Charbonnages",
    "iso:country":"BE",
    "sg:address":"Quai Des Charbonnages 36-38",
    "sg:city":"Sint-jans-molenbeek/molenbeek-",
    "sg:orig_category":"R\u00e9alisation de programmes and logiciels",
    "sg:phone":"+32 2 527 10 05",
    "sg:postcode":"1080",
    "sg:province":"Bruxelles-Capitale",
    "wof:name":"Meca Consult",
    "wof:placetype":"venue"
},
  "geometry": {"coordinates":[4.3423252106,50.8551521301],"type":"Point"}
}