{
  "type": "Feature",
  "properties": {
    "iso:country":"BE",
    "sg:address":"Rue Raymond No\u00cbl 153",
    "sg:city":"Profondeville",
    "sg:orig_category":"D\u00e9molition d\u00b4immeubles and terrassements. Construction de maisons",
    "sg:phone":"+32 81 43 36 57",
    "sg:postcode":"5170",
    "sg:province":"Namur",
    "wof:name":"Crasset M & Fils",
    "wof:placetype":"venue"
},
  "geometry": {"coordinates":[4.825674057,50.3973922729],"type":"Point"}
}