{
  "type": "Feature",
  "properties": {
    "iso:country":"BE",
    "sg:address":"Rue Des Tanneries 36",
    "sg:city":"Rochefort",
    "sg:classifiers":[
        {
            "category":"Health Services",
            "subcategory":"Dentist",
            "type":"Services"
        }
    ],
    "sg:phone":"+32 84 22 13 36",
    "sg:postcode":"5580",
    "sg:province":"Namur",
    "wof:name":"Dubois C",
    "wof:placetype":"venue"
},
  "geometry": {"coordinates":[5.2190899849,50.1612281799],"type":"Point"}
}