{
  "type": "Feature",
  "properties": {
    "iso:country":"BE",
    "sg:address":"Rue De Bruxelles 195",
    "sg:city":"Awans",
    "sg:classifiers":[
        {
            "category":"Professional",
            "subcategory":"Management & Consulting",
            "type":"Services"
        }
    ],
    "sg:phone":"+32 4 263 37 68",
    "sg:postcode":"4340",
    "sg:province":"Li\u00e8ge",
    "sg:tags":[
        "consultant"
    ],
    "wof:name":"Latinum Sa",
    "wof:placetype":"venue"
},
  "geometry": {"coordinates":[5.4880208969,50.6732711792],"type":"Point"}
}