{
  "type": "Feature",
  "properties": {
    "addr:full":"Rue De La D\u00c9portation 18 Binche Hainaut 7130",
    "addr:housenumber":"18",
    "addr:postcode":"7130",
    "addr:street":"Rue De La De\u0301Portation",
    "iso:country":"BE",
    "sg:address":"Rue De La D\u00c9portation 18",
    "sg:city":"Binche",
    "sg:orig_category":"Diverse grafische activiteiten",
    "sg:phone":"+32 64 37 02 69",
    "sg:postcode":"7130",
    "sg:province":"Hainaut",
    "wof:name":"Messier 111",
    "wof:placetype":"venue"
},
  "geometry": {"coordinates":[4.1720690727,50.4109420776],"type":"Point"}
}