{
  "type": "Feature",
  "properties": {
    "iso:country":"BE",
    "sg:address":"Avenue De L'arc-d'airain 15",
    "sg:city":"Gembloux",
    "sg:orig_category":"Installation \u00e9lectrique r\u00e9sidentielle",
    "sg:phone":"+32 81 61 10 56",
    "sg:postcode":"5030",
    "sg:province":"Namur",
    "wof:name":"T.i.m.a.c.",
    "wof:placetype":"venue"
},
  "geometry": {"coordinates":[4.6824841499,50.5666427612],"type":"Point"}
}