{
  "type": "Feature",
  "properties": {
    "iso:country":"BE",
    "sg:address":"Brugseweg 129",
    "sg:city":"Langemark-poelkapelle",
    "sg:orig_category":"Eleveurs de bovins",
    "sg:phone":"+32 57 48 80 64",
    "sg:postcode":"8920",
    "sg:province":"West-Vlaanderen",
    "wof:name":"Gerard Lampaert",
    "wof:placetype":"venue"
},
  "geometry": {"coordinates":[2.9379899502,50.8924789429],"type":"Point"}
}