{
  "type": "Feature",
  "properties": {
    "addr:full":"Koninginnelaan 151 Schaarbeek/schaerbeek Bruxelles-Capitale 1030",
    "addr:housenumber":"151",
    "addr:postcode":"1030",
    "addr:street":"Koninginnelaan",
    "iso:country":"BE",
    "sg:address":"Koninginnelaan 151",
    "sg:city":"Schaarbeek/schaerbeek",
    "sg:classifiers":[
        {
            "category":"Fast Food",
            "type":"Food & Drink"
        }
    ],
    "sg:phone":"+32 2 201 10 60",
    "sg:postcode":"1030",
    "sg:province":"Bruxelles-Capitale",
    "sg:tags":[
        "meeneem",
        "restaurant"
    ],
    "wof:name":"Friture Du Coin",
    "wof:placetype":"venue"
},
  "geometry": {"coordinates":[4.3626680374,50.8691635132],"type":"Point"}
}