{
  "type": "Feature",
  "properties": {
    "addr:full":"Rue Ernest Havaux 23 Bruxelles (etterbeek) Bruxelles-Capitale 1040",
    "addr:housenumber":"23",
    "addr:postcode":"1040",
    "addr:street":"Rue Ernest Havaux",
    "iso:country":"BE",
    "sg:address":"Rue Ernest Havaux 23",
    "sg:city":"Bruxelles (etterbeek)",
    "sg:classifiers":[
        {
            "category":"Wholesale",
            "subcategory":"Construction Materials",
            "type":"Manufacturing & Wholesale Goods"
        }
    ],
    "sg:phone":"+32 2 646 25 27",
    "sg:postcode":"1040",
    "sg:province":"Bruxelles-Capitale",
    "sg:tags":[
        "adhesive"
    ],
    "wof:name":"Protector",
    "wof:placetype":"venue"
},
  "geometry": {"coordinates":[4.383685112,50.8325004578],"type":"Point"}
}