{
  "type": "Feature",
  "properties": {
    "iso:country":"BE",
    "sg:address":"Rue Hullos 22",
    "sg:city":"Li\u00e8ge 1",
    "sg:classifiers":[
        {
            "category":"Health Services",
            "subcategory":"Dentist",
            "type":"Services"
        }
    ],
    "sg:phone":"+32 4 226 85 97",
    "sg:postcode":"4000",
    "sg:province":"Li\u00e8ge",
    "wof:name":"Remits M",
    "wof:placetype":"venue"
},
  "geometry": {"coordinates":[5.5596141815,50.6449661255],"type":"Point"}
}