{
  "type": "Feature",
  "properties": {
    "addr:full":"Boulevard Saint-michel 45 Bruxelles (etterbeek) Bruxelles-Capitale 1040",
    "addr:housenumber":"45",
    "addr:postcode":"1040",
    "addr:street":"Boulevard Saint-Michel",
    "iso:country":"BE",
    "sg:address":"Boulevard Saint-michel 45",
    "sg:city":"Bruxelles (etterbeek)",
    "sg:classifiers":[
        {
            "category":"Professional",
            "subcategory":"Lawyer & Legal Services",
            "type":"Services"
        }
    ],
    "sg:phone":"+32 2 736 59 44",
    "sg:postcode":"1040",
    "sg:province":"Bruxelles-Capitale",
    "wof:name":"Fontaneau Vandoren Fran\u00e7oise",
    "wof:placetype":"venue"
},
  "geometry": {"coordinates":[4.4057779312,50.8348274231],"type":"Point"}
}