{
  "type": "Feature",
  "properties": {
    "iso:country":"BE",
    "sg:address":"Zillebeke-dorp 20",
    "sg:city":"Ieper (zillebeke)",
    "sg:classifiers":[
        {
            "category":"Banks & Credit Unions",
            "subcategory":"Investment Brokerage",
            "type":"Services"
        }
    ],
    "sg:phone":"+32 57 20 19 26",
    "sg:postcode":"8902",
    "sg:province":"West-Vlaanderen",
    "sg:tags":[
        "printing",
        "-"
    ],
    "wof:name":"Hillewaere-radys",
    "wof:placetype":"venue"
},
  "geometry": {"coordinates":[2.9220030308,50.8353881836],"type":"Point"}
}