{
  "type": "Feature",
  "properties": {
    "iso:country":"BE",
    "sg:address":"Hasseltsebaan 134",
    "sg:city":"Hechtel-eksel",
    "sg:orig_category":"Metaalafval, schrootrecyclage and sloperijen Voertuigen",
    "sg:phone":"+32 11 73 34 67",
    "sg:postcode":"3940",
    "sg:province":"Limburg",
    "wof:name":"Patrick Coomans",
    "wof:placetype":"venue"
},
  "geometry": {"coordinates":[5.3746128082,51.0967674255],"type":"Point"}
}