{
  "type": "Feature",
  "properties": {
    "iso:country":"BE",
    "sg:address":"Hondsmertjesstraat 25b1",
    "sg:city":"Izegem",
    "sg:orig_category":"Diverse persoonlijke diensten",
    "sg:phone":"+32 51 30 87 36",
    "sg:postcode":"8870",
    "sg:province":"West-Vlaanderen",
    "wof:name":"Ben Vroman",
    "wof:placetype":"venue"
},
  "geometry": {"coordinates":[3.1984550953,50.9333648682],"type":"Point"}
}