{
  "type": "Feature",
  "properties": {
    "iso:country":"BE",
    "sg:address":"Kouterken 5",
    "sg:city":"Nevele",
    "sg:orig_category":"Elektrische installaties voor woningen Industri\u00eble elektrische installaties",
    "sg:phone":"+32 9 371 66 63",
    "sg:postcode":"9850",
    "sg:province":"Oost-Vlaanderen",
    "wof:name":"Edt-electriciteitswerken",
    "wof:placetype":"venue"
},
  "geometry": {"coordinates":[3.5329339504,51.0854225159],"type":"Point"}
}