{
  "type": "Feature",
  "properties": {
    "addr:full":"Dennenlaan 69 Antwerpen (wilrijk) Antwerpen 2610",
    "addr:housenumber":"69",
    "addr:postcode":"2610",
    "addr:street":"Dennenlaan;Antwerpen",
    "iso:country":"BE",
    "sg:address":"Dennenlaan 69",
    "sg:city":"Antwerpen (wilrijk)",
    "sg:classifiers":[
        {
            "category":"Health Services",
            "subcategory":"Dentist",
            "type":"Services"
        }
    ],
    "sg:phone":"+32 3 830 26 16",
    "sg:postcode":"2610",
    "sg:province":"Antwerpen",
    "wof:name":"Rogiers Ilse",
    "wof:placetype":"venue"
},
  "geometry": {"coordinates":[4.4068398476,51.1743049622],"type":"Point"}
}