{
  "type": "Feature",
  "properties": {
    "iso:country":"BE",
    "sg:address":"Prinses Clementinalaan 43",
    "sg:city":"Gent",
    "sg:classifiers":[
        {
            "category":"Food & Beverages",
            "subcategory":"Supermarket",
            "type":"Retail Goods"
        }
    ],
    "sg:phone":"+32 9 221 41 18",
    "sg:postcode":"9000",
    "sg:province":"Oost-Vlaanderen",
    "sg:tags":[
        "frozen",
        "-"
    ],
    "wof:name":"Miss Roomijs",
    "wof:placetype":"venue"
},
  "geometry": {"coordinates":[3.7153320312,51.0347976685],"type":"Point"}
}