{
  "type": "Feature",
  "properties": {
    "addr:full":"Bosbeek 6 Beveren Oost-Vlaanderen 9120",
    "addr:housenumber":"6",
    "addr:postcode":"9120",
    "addr:street":"Bosbeek",
    "iso:country":"BE",
    "sg:address":"Bosbeek 6",
    "sg:city":"Beveren",
    "sg:orig_category":"Spuittoestellen Fab",
    "sg:phone":"+32 3 775 74 21",
    "sg:postcode":"9120",
    "sg:province":"Oost-Vlaanderen",
    "wof:name":"Dimex",
    "wof:placetype":"venue"
},
  "geometry": {"coordinates":[4.2392168045,51.2026443481],"type":"Point"}
}