{
  "type": "Feature",
  "properties": {
    "addr:full":"Rue Forestiere 8 Elsene/ixelles Bruxelles-Capitale 1050",
    "addr:housenumber":"8",
    "addr:postcode":"1050",
    "addr:street":"Rue Forestiere",
    "iso:country":"BE",
    "sg:address":"Rue Forestiere 8",
    "sg:city":"Elsene/ixelles",
    "sg:orig_category":"M\u00e9decins and sp\u00e9cialistes",
    "sg:phone":"+32 2 648 82 65",
    "sg:postcode":"1050",
    "sg:province":"Bruxelles-Capitale",
    "wof:name":"Claudine Biefnot",
    "wof:placetype":"venue"
},
  "geometry": {"coordinates":[4.3653001785,50.8230247498],"type":"Point"}
}