{
  "type": "Feature",
  "properties": {
    "iso:country":"BE",
    "sg:address":"Rue Al'croix 15",
    "sg:city":"Aiseau-presles (presles)",
    "sg:classifiers":[
        {
            "category":"Home & Garden",
            "subcategory":"Household Appliances",
            "type":"Retail Goods"
        }
    ],
    "sg:phone":"+32 71 40 37 42",
    "sg:postcode":"6250",
    "sg:province":"Hainaut",
    "sg:tags":[
        "repair",
        "mainten",
        "-",
        "electric"
    ],
    "wof:name":"Giambona G",
    "wof:placetype":"venue"
},
  "geometry": {"coordinates":[4.5738801956,50.4026298523],"type":"Point"}
}