{
  "type": "Feature",
  "properties": {
    "addr:full":"Roger Vansteenbruggestraat 77 Waregem West-Vlaanderen 8790",
    "addr:housenumber":"77",
    "addr:postcode":"8790",
    "addr:street":"Vansteenbruggestraat",
    "iso:country":"BE",
    "sg:address":"Roger Vansteenbruggestraat 77",
    "sg:city":"Waregem",
    "sg:classifiers":[
        {
            "category":"Professional",
            "subcategory":"Management & Consulting",
            "type":"Services"
        }
    ],
    "sg:phone":"+32 56 60 19 62",
    "sg:postcode":"8790",
    "sg:province":"West-Vlaanderen",
    "sg:tags":[
        "consultant"
    ],
    "wof:name":"Creative Business Advice Bvba",
    "wof:placetype":"venue"
},
  "geometry": {"coordinates":[3.4190590382,50.8927459717],"type":"Point"}
}