{
  "type": "Feature",
  "properties": {
    "addr:full":"Zandstraat 8b1 Balen Antwerpen 2490",
    "addr:housenumber":"8b1",
    "addr:postcode":"2490",
    "addr:street":"Zandstraat",
    "iso:country":"BE",
    "sg:address":"Zandstraat 8b1",
    "sg:city":"Balen",
    "sg:orig_category":"Chaussures",
    "sg:phone":"+32 14 81 37 81",
    "sg:postcode":"2490",
    "sg:province":"Antwerpen",
    "wof:name":"Gaby Stessens",
    "wof:placetype":"venue"
},
  "geometry": {"coordinates":[5.165763855,51.1717147827],"type":"Point"}
}