{
  "type": "Feature",
  "properties": {
    "iso:country":"BE",
    "sg:address":"Neervelpsestraat 11",
    "sg:city":"Boutersem",
    "sg:orig_category":"Overheidsdiensten",
    "sg:phone":"+32 16 72 10 64",
    "sg:postcode":"3370",
    "sg:province":"Vlaams-Brabant",
    "wof:name":"Gemeentebestuur",
    "wof:placetype":"venue"
},
  "geometry": {"coordinates":[4.8211989403,50.8280296326],"type":"Point"}
}