{
  "type": "Feature",
  "properties": {
    "addr:full":"Kortedagsteeg 35 Gent Oost-Vlaanderen 9000",
    "addr:housenumber":"35",
    "addr:postcode":"9000",
    "addr:street":"Kortedagsteeg;Oost-Vlaanderen",
    "iso:country":"BE",
    "sg:address":"Kortedagsteeg 35",
    "sg:city":"Gent",
    "sg:classifiers":[
        {
            "category":"Shopping",
            "subcategory":"Clothing, Apparel, & Fashions",
            "type":"Retail Goods"
        }
    ],
    "sg:phone":"+32 9 225 78 60",
    "sg:postcode":"9000",
    "sg:province":"Oost-Vlaanderen",
    "sg:tags":[
        "lingerie",
        "sous-v\u00eatements"
    ],
    "wof:name":"Simonne",
    "wof:placetype":"venue"
},
  "geometry": {"coordinates":[3.7266390324,51.0499038696],"type":"Point"}
}