{
  "type": "Feature",
  "properties": {
    "iso:country":"BE",
    "sg:address":"Rue Emile Vandervelde 137",
    "sg:city":"Beyne-heusay",
    "sg:orig_category":"Kansspelen",
    "sg:phone":"+32 4 362 53 07",
    "sg:postcode":"4610",
    "sg:province":"Li\u00e8ge",
    "wof:name":"Tierc\u00c9 Franco Belge",
    "wof:placetype":"venue"
},
  "geometry": {"coordinates":[5.6768250465,50.6378936768],"type":"Point"}
}