{
  "type": "Feature",
  "properties": {
    "addr:full":"Boulevard Du Souverain 91 Oudergem/auderghem Bruxelles-Capitale 1160",
    "addr:housenumber":"91",
    "addr:postcode":"1160",
    "addr:street":"Boulevard Du Souverain;/",
    "iso:country":"BE",
    "sg:address":"Boulevard Du Souverain 91",
    "sg:city":"Oudergem/auderghem",
    "sg:classifiers":[
        {
            "category":"Autos & Motor Vehicles",
            "subcategory":"Fuel & Gas Station",
            "type":"Retail Goods"
        }
    ],
    "sg:phone":"+32 2 673 96 08",
    "sg:postcode":"1160",
    "sg:province":"Bruxelles-Capitale",
    "sg:tags":[
        "stations-service",
        "carburants"
    ],
    "wof:name":"Jet",
    "wof:placetype":"venue"
},
  "geometry": {"coordinates":[4.4271879196,50.8133201599],"type":"Point"}
}