{
  "type": "Feature",
  "properties": {
    "addr:full":"Gentstraat 33 Deinze Oost-Vlaanderen 9800",
    "addr:housenumber":"33",
    "addr:postcode":"9800",
    "addr:street":"Gentstraat",
    "iso:country":"BE",
    "sg:address":"Gentstraat 33",
    "sg:city":"Deinze",
    "sg:orig_category":"Brood, gebak and snoepgoed",
    "sg:phone":"+32 9 386 28 86",
    "sg:postcode":"9800",
    "sg:province":"Oost-Vlaanderen",
    "wof:name":"Hugo Claeys",
    "wof:placetype":"venue"
},
  "geometry": {"coordinates":[3.5330491066,50.9797477722],"type":"Point"}
}