{
  "type": "Feature",
  "properties": {
    "iso:country":"BE",
    "sg:address":"Goudvinkstraat 11",
    "sg:city":"Zemst",
    "sg:orig_category":"Elektrische installaties voor woningen",
    "sg:phone":"+32 15 62 13 89",
    "sg:postcode":"1980",
    "sg:province":"Vlaams-Brabant",
    "wof:name":"Dany Van Eeckhout",
    "wof:placetype":"venue"
},
  "geometry": {"coordinates":[4.4591579437,50.9678382874],"type":"Point"}
}