{
  "type": "Feature",
  "properties": {
    "addr:full":"Grand'route 145-147 Fl\u00e9malle Li\u00e8ge 4400",
    "addr:housenumber":"145-147",
    "addr:postcode":"4400",
    "addr:street":"Grand'Route",
    "iso:country":"BE",
    "sg:address":"Grand'route 145-147",
    "sg:city":"Fl\u00e9malle",
    "sg:classifiers":[
        {
            "category":"Professional",
            "subcategory":"Testing Lab",
            "type":"Services"
        }
    ],
    "sg:phone":"+32 4 233 67 67",
    "sg:postcode":"4400",
    "sg:province":"Li\u00e8ge",
    "sg:tags":[
        "chemist"
    ],
    "wof:name":"Gurn\u00e9 P",
    "wof:placetype":"venue"
},
  "geometry": {"coordinates":[5.4492239952,50.5986442566],"type":"Point"}
}