{
  "type": "Feature",
  "properties": {
    "iso:country":"BE",
    "sg:address":"Weverstraat 47",
    "sg:city":"Boechout",
    "sg:orig_category":"Traitements param\u00e9dicaux",
    "sg:phone":"+32 497 30 27 20",
    "sg:postcode":"2531",
    "sg:province":"Antwerpen",
    "wof:name":"E. Van Eynde",
    "wof:placetype":"venue"
},
  "geometry": {"coordinates":[4.5198659897,51.1764450073],"type":"Point"}
}