{
  "type": "Feature",
  "properties": {
    "iso:country":"BE",
    "sg:address":"Berkenhoekstraat 20",
    "sg:city":"Onze-lieve-vrouw-waver",
    "sg:classifiers":[
        {
            "category":"Banks & Credit Unions",
            "subcategory":"Investment Brokerage",
            "type":"Services"
        }
    ],
    "sg:phone":"+32 15 76 09 60",
    "sg:postcode":"2861",
    "sg:province":"Antwerpen",
    "sg:tags":[
        "packaging",
        "product",
        "candy"
    ],
    "wof:name":"Elite Biscuit Nv",
    "wof:placetype":"venue"
},
  "geometry": {"coordinates":[4.567440033,51.0541114807],"type":"Point"}
}