{
  "type": "Feature",
  "properties": {
    "addr:full":"Wingepark 41 Rotselaar Vlaams-Brabant 3110",
    "addr:housenumber":"41",
    "addr:postcode":"3110",
    "addr:street":"Wingepark",
    "iso:country":"BE",
    "sg:address":"Wingepark 41",
    "sg:city":"Rotselaar",
    "sg:orig_category":"Non-Classified Establishments",
    "sg:phone":"+32 16 44 38 40",
    "sg:postcode":"3110",
    "sg:province":"Vlaams-Brabant",
    "wof:name":"Tupperware-dehaes Bvba",
    "wof:placetype":"venue"
},
  "geometry": {"coordinates":[4.7472600937,50.9410591125],"type":"Point"}
}