{
  "type": "Feature",
  "properties": {
    "addr:full":"Stoppelweg 12 Poperinge West-Vlaanderen 8978",
    "addr:housenumber":"12",
    "addr:postcode":"8978",
    "addr:street":"Stoppelweg",
    "iso:country":"BE",
    "sg:address":"Stoppelweg 12",
    "sg:city":"Poperinge",
    "sg:orig_category":"Rundveehouders Varkenskwekers",
    "sg:phone":"+32 57 38 82 49",
    "sg:postcode":"8978",
    "sg:province":"West-Vlaanderen",
    "wof:name":"Jozef Delanote",
    "wof:placetype":"venue"
},
  "geometry": {"coordinates":[2.6619999409,50.8276939392],"type":"Point"}
}