{
  "type": "Feature",
  "properties": {
    "iso:country":"BE",
    "sg:address":"Rue Du Grand Foriest 5",
    "sg:city":"Genappe (vieux-genappe)",
    "sg:classifiers":[
        {
            "category":"Retail",
            "subcategory":"Event Space",
            "type":"Services"
        }
    ],
    "sg:phone":"+32 67 79 07 00",
    "sg:postcode":"1472",
    "sg:province":"Brabant Wallon",
    "sg:tags":[
        "rental",
        "-",
        "hall"
    ],
    "wof:name":"Domaine Du Grand Foriest",
    "wof:placetype":"venue"
},
  "geometry": {"coordinates":[4.3956799507,50.620426178],"type":"Point"}
}