{
  "type": "Feature",
  "properties": {
    "iso:country":"BE",
    "sg:address":"Vrekkemstraat 43",
    "sg:city":"Knesselare (ursel)",
    "sg:classifiers":[
        {
            "category":"Shopping",
            "subcategory":"Bicycles & Sporting Goods",
            "type":"Retail Goods"
        }
    ],
    "sg:phone":"+32 495 50 00 00",
    "sg:postcode":"9910",
    "sg:province":"Oost-Vlaanderen",
    "sg:tags":[
        "-"
    ],
    "wof:name":"Bel-'bent Ligfietsen",
    "wof:placetype":"venue"
},
  "geometry": {"coordinates":[3.4849300385,51.1268463135],"type":"Point"}
}