{
  "type": "Feature",
  "properties": {
    "addr:full":"Bezelarestraat Wervik West-Vlaanderen 8940",
    "addr:postcode":"8940",
    "addr:street":"Bezelarestraat",
    "iso:country":"BE",
    "sg:address":"Bezelarestraat",
    "sg:city":"Wervik",
    "sg:orig_category":"Gestion des d\u00e9charges and sites d\u00e9finitifs de stockage",
    "sg:phone":"+32 56 52 81 30",
    "sg:postcode":"8940",
    "sg:province":"West-Vlaanderen",
    "wof:name":"Containerpark Geluwe",
    "wof:placetype":"venue"
},
  "geometry": {"coordinates":[3.0498309135,50.8280754089],"type":"Point"}
}