{
  "type": "Feature",
  "properties": {
    "iso:country":"BE",
    "sg:address":"Chauss\u00e9e De Charleroi 100c",
    "sg:city":"Fosses-la-ville",
    "sg:classifiers":[
        {
            "category":"Building & Trades",
            "subcategory":"Construction",
            "type":"Services"
        }
    ],
    "sg:phone":"+32 71 71 10 20",
    "sg:postcode":"5070",
    "sg:province":"Namur",
    "sg:tags":[
        "fork",
        "lift",
        "truck"
    ],
    "wof:name":"Genin Agricole Sa",
    "wof:placetype":"venue"
},
  "geometry": {"coordinates":[4.6720352173,50.3934173584],"type":"Point"}
}