{
  "type": "Feature",
  "properties": {
    "iso:country":"BE",
    "sg:address":"Aarschotsesteenweg 302",
    "sg:city":"Koningshooikt",
    "sg:orig_category":"Herstellingen and onderhoud van auto's Voertuigen",
    "sg:phone":"+32 3 482 11 88",
    "sg:postcode":"2500",
    "sg:province":"Antwerpen",
    "wof:name":"Garage Van Parijs",
    "wof:placetype":"venue"
},
  "geometry": {"coordinates":[4.6344270706,51.088848114],"type":"Point"}
}