{
  "type": "Feature",
  "properties": {
    "iso:country":"BE",
    "sg:address":"Puursesteenweg 390a",
    "sg:city":"Bornem",
    "sg:orig_category":"Pre-press",
    "sg:phone":"+32 3 899 67 95",
    "sg:postcode":"2880",
    "sg:province":"Antwerpen",
    "wof:name":"Combo Bvba",
    "wof:placetype":"venue"
},
  "geometry": {"coordinates":[4.2628540993,51.0855941772],"type":"Point"}
}