{
  "type": "Feature",
  "properties": {
    "iso:country":"BE",
    "sg:address":"Rue De Lavaux 61",
    "sg:city":"Saint-hubert",
    "sg:orig_category":"Experts-comptables",
    "sg:phone":"+32 61 61 19 61",
    "sg:postcode":"6870",
    "sg:province":"Luxembourg",
    "wof:name":"Bouillon",
    "wof:placetype":"venue"
},
  "geometry": {"coordinates":[5.379556179,50.0265884399],"type":"Point"}
}