{
  "type": "Feature",
  "properties": {
    "iso:country":"BE",
    "sg:address":"Capucienenstraat 9-13",
    "sg:city":"Maaseik",
    "sg:classifiers":[
        {
            "category":"Retail",
            "subcategory":"Self-service Laundry",
            "type":"Services"
        }
    ],
    "sg:phone":"+32 89 56 42 94",
    "sg:postcode":"3680",
    "sg:province":"Limburg",
    "sg:tags":[
        "-",
        "outfit",
        "communion",
        "wear",
        "bridal",
        "rental",
        "formal"
    ],
    "wof:name":"Corstjens Mannenmode",
    "wof:placetype":"venue"
},
  "geometry": {"coordinates":[5.7919559479,51.0957641602],"type":"Point"}
}