{
  "type": "Feature",
  "properties": {
    "iso:country":"BE",
    "sg:address":"Roeselaarsestraat 75",
    "sg:city":"Izegem",
    "sg:orig_category":"Immobili\u00ebnkantoren",
    "sg:phone":"+32 51 30 20 19",
    "sg:postcode":"8870",
    "sg:province":"West-Vlaanderen",
    "wof:name":"Sofimo",
    "wof:placetype":"venue"
},
  "geometry": {"coordinates":[3.2089428902,50.9191627502],"type":"Point"}
}