{
  "type": "Feature",
  "properties": {
    "iso:country":"BE",
    "sg:address":"Avenue Newton 1",
    "sg:city":"Wavre",
    "sg:orig_category":"Diverse juridische dienstverlening",
    "sg:phone":"+32 10 24 25 88",
    "sg:postcode":"1300",
    "sg:province":"Brabant Wallon",
    "wof:name":"Maison Newton",
    "wof:placetype":"venue"
},
  "geometry": {"coordinates":[4.5881199837,50.7369499207],"type":"Point"}
}