{
  "type": "Feature",
  "properties": {
    "iso:country":"BE",
    "sg:address":"Centrum Zuid 2098",
    "sg:city":"Houthalen-helchteren (houthalen)",
    "sg:classifiers":[
        {
            "category":"Utilities",
            "subcategory":"Refuse",
            "type":"Services"
        }
    ],
    "sg:phone":"+32 11 52 08 10",
    "sg:postcode":"3530",
    "sg:province":"Limburg",
    "sg:tags":[
        "management",
        "waste"
    ],
    "wof:name":"Regionale Milieuorganisatie Cvba",
    "wof:placetype":"venue"
},
  "geometry": {"coordinates":[5.3571949005,51.0150527954],"type":"Point"}
}