{
  "type": "Feature",
  "properties": {
    "addr:full":"Place Reine-astrid 16 Dinant Namur 5500",
    "addr:housenumber":"16",
    "addr:postcode":"5500",
    "addr:street":"Place Reine-Astrid",
    "iso:country":"BE",
    "sg:address":"Place Reine-astrid 16",
    "sg:city":"Dinant",
    "sg:classifiers":[
        {
            "category":"Restaurant",
            "type":"Food & Drink"
        }
    ],
    "sg:phone":"+32 82 22 71 40",
    "sg:postcode":"5500",
    "sg:province":"Namur",
    "sg:tags":[
        "caf\u00e9s"
    ],
    "wof:name":"Bridge Pub",
    "wof:placetype":"venue"
},
  "geometry": {"coordinates":[4.9121999741,50.2605781555],"type":"Point"}
}