{
  "type": "Feature",
  "properties": {
    "iso:country":"BE",
    "sg:address":"Ledebergplein 27",
    "sg:city":"Gent (ledeberg)",
    "sg:classifiers":[
        {
            "category":"Cafe",
            "type":"Food & Drink"
        }
    ],
    "sg:phone":"+32 475 39 65 00",
    "sg:postcode":"9050",
    "sg:province":"Oost-Vlaanderen",
    "sg:tags":[
        "snack-bars"
    ],
    "wof:name":"Picolootje-van Hoorleghem F",
    "wof:placetype":"venue"
},
  "geometry": {"coordinates":[3.7420740128,51.0368156433],"type":"Point"}
}