{
  "type": "Feature",
  "properties": {
    "addr:full":"Vieux Chemin De Hal 4 Braine-le-chateau Brabant Wallon 1440",
    "addr:housenumber":"4",
    "addr:postcode":"1440",
    "addr:street":"Vieux Chemin De Hal;Brabant Wallon",
    "iso:country":"BE",
    "sg:address":"Vieux Chemin De Hal 4",
    "sg:city":"Braine-le-chateau",
    "sg:orig_category":"Experts-comptables",
    "sg:phone":"+32 2 366 11 17",
    "sg:postcode":"1440",
    "sg:province":"Brabant Wallon",
    "wof:name":"Didier De Meyer",
    "wof:placetype":"venue"
},
  "geometry": {"coordinates":[4.2713270187,50.6852645874],"type":"Point"}
}