{
  "type": "Feature",
  "properties": {
    "addr:full":"Stedestraat 16 Harelbeke West-Vlaanderen 8530",
    "addr:housenumber":"16",
    "addr:postcode":"8530",
    "addr:street":"Stedestraat",
    "iso:country":"BE",
    "sg:address":"Stedestraat 16",
    "sg:city":"Harelbeke",
    "sg:classifiers":[
        {
            "category":"Wholesale",
            "subcategory":"Beer",
            "type":"Manufacturing & Wholesale Goods"
        }
    ],
    "sg:phone":"+32 56 71 27 37",
    "sg:postcode":"8530",
    "sg:province":"West-Vlaanderen",
    "sg:tags":[
        "ale",
        "-"
    ],
    "wof:name":"Demaeght L",
    "wof:placetype":"venue"
},
  "geometry": {"coordinates":[3.3047399521,50.8586997986],"type":"Point"}
}