{
  "type": "Feature",
  "properties": {
    "addr:full":"Rue Du Plan Inclin\u00c9 0 Li\u00c8ge Li\u00e8ge 4000",
    "addr:housenumber":"0",
    "addr:postcode":"4000",
    "addr:street":"Rue Du Plan Incline\u0301",
    "iso:country":"BE",
    "sg:address":"Rue Du Plan Inclin\u00c9 0",
    "sg:city":"Li\u00c8ge",
    "sg:orig_category":"Services annexes des transports terrestres",
    "sg:phone":"+32 4 254 13 36",
    "sg:postcode":"4000",
    "sg:province":"Li\u00e8ge",
    "wof:name":"Parking S.n.c.b.",
    "wof:placetype":"venue"
},
  "geometry": {"coordinates":[5.5640468597,50.6289329529],"type":"Point"}
}