{
  "type": "Feature",
  "properties": {
    "addr:full":"Breedstraat 139 Sint-niklaas Oost-Vlaanderen 9100",
    "addr:housenumber":"139",
    "addr:postcode":"9100",
    "addr:street":"Breedstraat",
    "iso:country":"BE",
    "sg:address":"Breedstraat 139",
    "sg:city":"Sint-niklaas",
    "sg:orig_category":"Industri\u00eble wasserijen and droogkuis",
    "sg:phone":"+32 3 776 08 14",
    "sg:postcode":"9100",
    "sg:province":"Oost-Vlaanderen",
    "wof:name":"Wasserij Coucke",
    "wof:placetype":"venue"
},
  "geometry": {"coordinates":[4.1619019508,51.1667060852],"type":"Point"}
}