{
  "type": "Feature",
  "properties": {
    "addr:full":"De Fraulalaan 20 Ranst Antwerpen 2520",
    "addr:housenumber":"20",
    "addr:postcode":"2520",
    "addr:street":"De Fraulalaan",
    "iso:country":"BE",
    "sg:address":"De Fraulalaan 20",
    "sg:city":"Ranst",
    "sg:classifiers":[
        {
            "category":"Shopping",
            "subcategory":"Jewelry",
            "type":"Retail Goods"
        }
    ],
    "sg:phone":"+32 3 384 13 50",
    "sg:postcode":"2520",
    "sg:province":"Antwerpen",
    "sg:tags":[
        "fab",
        "bijou"
    ],
    "wof:name":"Luc Rumers",
    "wof:placetype":"venue"
},
  "geometry": {"coordinates":[4.5899958611,51.2160758972],"type":"Point"}
}