{
  "type": "Feature",
  "properties": {
    "addr:full":"Chauss\u00e9e Brunehault 512 Herstal (vottem) Li\u00e8ge 4041",
    "addr:housenumber":"512",
    "addr:postcode":"4041",
    "addr:street":"Chausse\u0301E Brunehault;Vottem",
    "iso:country":"BE",
    "sg:address":"Chauss\u00e9e Brunehault 512",
    "sg:city":"Herstal (vottem)",
    "sg:classifiers":[
        {
            "category":"Arts & Performance",
            "subcategory":"Music",
            "type":"Entertainment"
        }
    ],
    "sg:phone":"+32 475 87 15 93",
    "sg:postcode":"4041",
    "sg:province":"Li\u00e8ge",
    "sg:tags":[
        "disc-jockeys"
    ],
    "wof:name":"Temple Of The Sound",
    "wof:placetype":"venue"
},
  "geometry": {"coordinates":[5.5830597878,50.6788482666],"type":"Point"}
}