{
  "type": "Feature",
  "properties": {
    "addr:full":"Nederveldstraat 11 Aalst Oost-Vlaanderen 9300",
    "addr:housenumber":"11",
    "addr:postcode":"9300",
    "addr:street":"Nederveldstraat",
    "iso:country":"BE",
    "sg:address":"Nederveldstraat 11",
    "sg:city":"Aalst",
    "sg:orig_category":"Artistes ind\u00e9pendants",
    "sg:phone":"+32 53 70 09 81",
    "sg:postcode":"9300",
    "sg:province":"Oost-Vlaanderen",
    "wof:name":"De Vree",
    "wof:placetype":"venue"
},
  "geometry": {"coordinates":[4.0673570633,50.9379348755],"type":"Point"}
}