{
  "type": "Feature",
  "properties": {
    "iso:country":"BE",
    "sg:address":"Bruggestraat 11",
    "sg:city":"Wingene (zwevezele)",
    "sg:classifiers":[
        {
            "category":"Banks & Credit Unions",
            "subcategory":"Bank",
            "type":"Services"
        }
    ],
    "sg:phone":"+32 51 61 30 27",
    "sg:postcode":"8750",
    "sg:province":"West-Vlaanderen",
    "sg:tags":[
        "savings-banks"
    ],
    "wof:name":"Verhaeghe K",
    "wof:placetype":"venue"
},
  "geometry": {"coordinates":[3.3471519947,51.0833587646],"type":"Point"}
}