{
  "type": "Feature",
  "properties": {
    "addr:full":"Elzeboomlaan 91ba50 Ukkel/uccle Bruxelles-Capitale 1180",
    "addr:housenumber":"91ba50",
    "addr:postcode":"1180",
    "addr:street":"Elzeboomlaan;/",
    "iso:country":"BE",
    "sg:address":"Elzeboomlaan 91ba50",
    "sg:city":"Ukkel/uccle",
    "sg:classifiers":[
        {
            "category":"Insurance",
            "subcategory":"Insurance Agent",
            "type":"Services"
        }
    ],
    "sg:phone":"+32 2 376 42 96",
    "sg:postcode":"1180",
    "sg:province":"Bruxelles-Capitale",
    "sg:tags":[
        "verzekeringsmakelaars",
        "expert"
    ],
    "wof:name":"Bureau Expertises Dansart",
    "wof:placetype":"venue"
},
  "geometry": {"coordinates":[4.3306450844,50.8028335571],"type":"Point"}
}