{
  "type": "Feature",
  "properties": {
    "iso:country":"BE",
    "sg:address":"Werbosstraat 4",
    "sg:city":"Dessel",
    "sg:classifiers":[
        {
            "category":"Retail",
            "subcategory":"Animal Services",
            "type":"Services"
        }
    ],
    "sg:phone":"+32 14 37 31 70",
    "sg:postcode":"2480",
    "sg:province":"Antwerpen",
    "sg:tags":[
        "grooming",
        "-",
        "dog"
    ],
    "wof:name":"Plessers C",
    "wof:placetype":"venue"
},
  "geometry": {"coordinates":[5.1093511581,51.24559021],"type":"Point"}
}