{
  "type": "Feature",
  "properties": {
    "iso:country":"BE",
    "sg:address":"Pluimstraat 8",
    "sg:city":"Haaltert",
    "sg:orig_category":"Installation \u00e9lectrique r\u00e9sidentielle",
    "sg:phone":"+32 53 83 37 60",
    "sg:postcode":"9450",
    "sg:province":"Oost-Vlaanderen",
    "wof:name":"Geerts E",
    "wof:placetype":"venue"
},
  "geometry": {"coordinates":[4.0031871796,50.9030532837],"type":"Point"}
}