{
  "type": "Feature",
  "properties": {
    "addr:full":"Avenue Albert 1er 14 Genval Brabant Wallon 1332",
    "addr:housenumber":"14",
    "addr:postcode":"1332",
    "addr:street":"Avenue Albert 1Er",
    "iso:country":"BE",
    "sg:address":"Avenue Albert 1er 14",
    "sg:city":"Genval",
    "sg:orig_category":"Electrom\u00e9nager, t\u00e9l\u00e9visions and radios. Articles de jardin. Souvenirs and objets artisanaux",
    "sg:phone":"+32 2 654 06 29",
    "sg:postcode":"1332",
    "sg:province":"Brabant Wallon",
    "wof:name":"Home & Hobby",
    "wof:placetype":"venue"
},
  "geometry": {"coordinates":[4.4886770248,50.727268219],"type":"Point"}
}