{
  "type": "Feature",
  "properties": {
    "addr:full":"Guido Gezellelaan 85 Heusden Limburg 3550",
    "addr:housenumber":"85",
    "addr:postcode":"3550",
    "addr:street":"Guido Gezellelaan",
    "iso:country":"BE",
    "sg:address":"Guido Gezellelaan 85",
    "sg:city":"Heusden",
    "sg:orig_category":"Keukens and Keukenapparatuur MEUBELONTWERP AND -INSTALLATIE Meubelzaken, woning- and keukeninrichtin",
    "sg:phone":"+32 87 63 08 09",
    "sg:postcode":"3550",
    "sg:province":"Limburg",
    "wof:name":"Interieur Frank Eerdekens",
    "wof:placetype":"venue"
},
  "geometry": {"coordinates":[5.2749810219,51.0300178528],"type":"Point"}
}