{
  "type": "Feature",
  "properties": {
    "addr:full":"Hundelgemsesteenweg 1009 Merelbeke Oost-Vlaanderen 9820",
    "addr:postcode":"1009;9820",
    "addr:street":"Hundelgemsesteenweg",
    "iso:country":"BE",
    "sg:address":"Hundelgemsesteenweg 1009",
    "sg:city":"Merelbeke",
    "sg:classifiers":[
        {
            "category":"Building & Trades",
            "subcategory":"Plumbing",
            "type":"Services"
        }
    ],
    "sg:phone":"+32 9 362 63 72",
    "sg:postcode":"9820",
    "sg:province":"Oost-Vlaanderen",
    "sg:tags":[
        "tank"
    ],
    "wof:name":"Alplast",
    "wof:placetype":"venue"
},
  "geometry": {"coordinates":[3.7351210117,50.9524879456],"type":"Point"}
}