{
  "type": "Feature",
  "properties": {
    "addr:full":"Kreuzstrasse 126 Lontzen/lontzen Li\u00e8ge 4711",
    "addr:housenumber":"126",
    "addr:postcode":"4711",
    "addr:street":"Kreuzstrasse",
    "iso:country":"BE",
    "sg:address":"Kreuzstrasse 126",
    "sg:city":"Lontzen/lontzen",
    "sg:orig_category":"Rundveehouders",
    "sg:phone":"+32 87 88 12 13",
    "sg:postcode":"4711",
    "sg:province":"Li\u00e8ge",
    "wof:name":"Guillaume Hocks",
    "wof:placetype":"venue"
},
  "geometry": {"coordinates":[6.047369957,50.6752853394],"type":"Point"}
}