{
  "type": "Feature",
  "properties": {
    "iso:country":"BE",
    "sg:address":"Le Grand Enclos 14",
    "sg:city":"Libramont-chevigny (saint-pierre)",
    "sg:orig_category":"Fiduciairies",
    "sg:phone":"+32 61 22 37 19",
    "sg:postcode":"6800",
    "sg:province":"Luxembourg",
    "wof:name":"Roland D (cabinet)",
    "wof:placetype":"venue"
},
  "geometry": {"coordinates":[5.3761348724,49.9199943542],"type":"Point"}
}