{
  "type": "Feature",
  "properties": {
    "iso:country":"BE",
    "sg:address":"Sint-adriaanstraat 147",
    "sg:city":"Haacht",
    "sg:orig_category":"Kapsalons",
    "sg:phone":"+32 16 60 20 84",
    "sg:postcode":"3150",
    "sg:province":"Vlaams-Brabant",
    "wof:name":"Coiffure Christine",
    "wof:placetype":"venue"
},
  "geometry": {"coordinates":[4.6212120056,50.9836273193],"type":"Point"}
}