{
  "type": "Feature",
  "properties": {
    "iso:country":"BE",
    "sg:address":"22",
    "sg:city":"Esplanade Heysel 1020 Bruxelles",
    "sg:classifiers":[
        {
            "category":"Health Services",
            "subcategory":"Medical Lab",
            "type":"Services"
        }
    ],
    "sg:phone":"+32 2 479 78 78",
    "sg:postcode":"22",
    "sg:tags":[
        "chemical",
        "pharmaceutical",
        "pharmacy"
    ],
    "wof:name":"Eurogenerics Sa",
    "wof:placetype":"venue"
},
  "geometry": {"coordinates":[4.341627121,50.8912887573],"type":"Point"}
}