{
  "type": "Feature",
  "properties": {
    "iso:country":"BE",
    "sg:address":"Bergstraat 182",
    "sg:city":"Heist-op-den-berg",
    "sg:classifiers":[
        {
            "category":"Tea Room",
            "subcategory":"None",
            "type":"Food & Drink"
        }
    ],
    "sg:phone":"+32 15 24 67 67",
    "sg:postcode":"2220",
    "sg:province":"Antwerpen",
    "wof:name":"Rimini",
    "wof:placetype":"venue"
},
  "geometry": {"coordinates":[4.7166500092,51.0772895813],"type":"Point"}
}