{
  "type": "Feature",
  "properties": {
    "addr:full":"Ketelmakersstraat 24 Tienen Vlaams-Brabant 3300",
    "addr:housenumber":"24",
    "addr:postcode":"3300",
    "addr:street":"Ketelmakersstraat",
    "iso:country":"BE",
    "sg:address":"Ketelmakersstraat 24",
    "sg:city":"Tienen",
    "sg:orig_category":"Pharmaciens",
    "sg:phone":"+32 16 81 69 02",
    "sg:postcode":"3300",
    "sg:province":"Vlaams-Brabant",
    "wof:name":"Martine Rens",
    "wof:placetype":"venue"
},
  "geometry": {"coordinates":[4.9297018051,50.8101654053],"type":"Point"}
}