{
  "type": "Feature",
  "properties": {
    "iso:country":"BE",
    "sg:address":"Mispelaarstraat 9",
    "sg:city":"Genk",
    "sg:orig_category":"Drukkerijen and copyshops",
    "sg:phone":"+32 89 35 32 95",
    "sg:postcode":"3600",
    "sg:province":"Limburg",
    "wof:name":"De Drukpers",
    "wof:placetype":"venue"
},
  "geometry": {"coordinates":[5.5268912315,50.9767074585],"type":"Point"}
}