{
  "type": "Feature",
  "properties": {
    "addr:full":"16 Vismarkt 3000 Leuven 16",
    "addr:housenumber":"16;16",
    "addr:postcode":"3000",
    "addr:street":"Vismarkt",
    "iso:country":"BE",
    "sg:address":"16",
    "sg:city":"Vismarkt 3000 Leuven",
    "sg:classifiers":[
        {
            "category":"Travel",
            "subcategory":"Hotels & Motels",
            "type":"Entertainment"
        }
    ],
    "sg:phone":"+32 16 22 05 70",
    "sg:postcode":"16",
    "sg:tags":[
        "hotels",
        "business",
        "restaurant"
    ],
    "wof:name":"De Blauwe Schuit Bvba",
    "wof:placetype":"venue"
},
  "geometry": {"coordinates":[4.6998400688,50.8816833496],"type":"Point"}
}