{
  "type": "Feature",
  "properties": {
    "iso:country":"BE",
    "sg:address":"Dorpsstraat 17",
    "sg:city":"Middelkerke",
    "sg:orig_category":"Epiceries",
    "sg:phone":"+32 59 30 11 53",
    "sg:postcode":"8432",
    "sg:province":"West-Vlaanderen",
    "wof:name":"Patrick Bentein",
    "wof:placetype":"venue"
},
  "geometry": {"coordinates":[2.8768401146,51.1755104065],"type":"Point"}
}