{
  "type": "Feature",
  "properties": {
    "iso:country":"BE",
    "sg:address":"Heirbaan 242",
    "sg:city":"Hamme",
    "sg:classifiers":[
        {
            "category":"Home & Garden",
            "subcategory":"Carpets & Floor Coverings",
            "type":"Retail Goods"
        }
    ],
    "sg:phone":"+32 52 47 70 90",
    "sg:postcode":"9220",
    "sg:province":"Oost-Vlaanderen",
    "sg:tags":[
        "parquet"
    ],
    "wof:name":"Vercammen Steven Bvba",
    "wof:placetype":"venue"
},
  "geometry": {"coordinates":[4.0962471962,51.0717658997],"type":"Point"}
}