{
  "type": "Feature",
  "properties": {
    "addr:full":"Eikenbeekstraat 13 Bilzen (eigenbilzen) Limburg 3740",
    "addr:housenumber":"13",
    "addr:postcode":"3740",
    "addr:street":"Eikenbeekstraat",
    "iso:country":"BE",
    "sg:address":"Eikenbeekstraat 13",
    "sg:city":"Bilzen (eigenbilzen)",
    "sg:classifiers":[
        {
            "category":"Professional",
            "subcategory":"Accounting & Tax Preparation",
            "type":"Services"
        }
    ],
    "sg:phone":"+32 89 50 33 25",
    "sg:postcode":"3740",
    "sg:province":"Limburg",
    "sg:tags":[
        "accountant"
    ],
    "wof:name":"Lathouwers B",
    "wof:placetype":"venue"
},
  "geometry": {"coordinates":[5.5756511688,50.873588562],"type":"Point"}
}