{
  "type": "Feature",
  "properties": {
    "addr:full":"Onze-lieve-vrouwstraat 190 Heusden-zolder (zolder) Limburg 3550",
    "addr:housenumber":"190",
    "addr:postcode":"3550",
    "addr:street":"Onze-Lieve-Vrouwstraat",
    "iso:country":"BE",
    "sg:address":"Onze-lieve-vrouwstraat 190",
    "sg:city":"Heusden-zolder (zolder)",
    "sg:classifiers":[
        {
            "category":"Communications",
            "subcategory":"Television Station",
            "type":"Services"
        }
    ],
    "sg:phone":"+32 11 53 79 27",
    "sg:postcode":"3550",
    "sg:province":"Limburg",
    "sg:tags":[
        "report",
        "video"
    ],
    "wof:name":"Videoreportages Rafael",
    "wof:placetype":"venue"
},
  "geometry": {"coordinates":[5.2678179741,51.010093689],"type":"Point"}
}