{
  "type": "Feature",
  "properties": {
    "iso:country":"BE",
    "sg:address":"Beekstraat 17",
    "sg:city":"Haaltert",
    "sg:orig_category":"Enseignement maternel and primaire",
    "sg:phone":"+32 53 83 91 46",
    "sg:postcode":"9451",
    "sg:province":"Oost-Vlaanderen",
    "wof:name":"Vrije Basisschool",
    "wof:placetype":"venue"
},
  "geometry": {"coordinates":[3.9928600788,50.8869972229],"type":"Point"}
}