{
  "type": "Feature",
  "properties": {
    "addr:full":"Da Vinciln 1 Kortewijk Village Building 4 F Zaventem Vlaams-Brabant 1930",
    "addr:housenumber":"1;f",
    "addr:postcode":"1930",
    "addr:street":"Kortewijk Village",
    "iso:country":"BE",
    "sg:address":"Da Vinciln 1 Kortewijk Village Building 4 F",
    "sg:city":"Zaventem",
    "sg:classifiers":[
        {
            "category":"Wholesale",
            "subcategory":"Medical Equipment & Supplies",
            "type":"Manufacturing & Wholesale Goods"
        }
    ],
    "sg:phone":"+32 2 774 68 11",
    "sg:postcode":"1930",
    "sg:province":"Vlaams-Brabant",
    "sg:tags":[
        "instrument",
        "health",
        "-",
        "precision"
    ],
    "wof:name":"Pacesetter Netherlands Distribution Vbr",
    "wof:placetype":"venue"
},
  "geometry": {"coordinates":[4.4741148949,50.8835449219],"type":"Point"}
}