{
  "type": "Feature",
  "properties": {
    "addr:full":"Bd Adolphe Max 146-160 Bruxelles Bruxelles-Capitale 1000",
    "addr:postcode":"146-160;1000",
    "addr:street":"Bd Adolphe Max",
    "iso:country":"BE",
    "sg:address":"Bd Adolphe Max 146-160",
    "sg:city":"Bruxelles",
    "sg:classifiers":[
        {
            "category":"Travel",
            "subcategory":"Hotels & Motels",
            "type":"Entertainment"
        }
    ],
    "sg:phone":"+32 2 250 10 20",
    "sg:postcode":"1000",
    "sg:province":"Bruxelles-Capitale",
    "sg:tags":[
        "hotels",
        "business",
        "restaurant"
    ],
    "wof:name":"Hotel Maison Du Dragon",
    "wof:placetype":"venue"
},
  "geometry": {"coordinates":[4.3571147919,50.8550262451],"type":"Point"}
}