{
  "type": "Feature",
  "properties": {
    "iso:country":"BE",
    "sg:address":"Gippershovenstraat 15",
    "sg:city":"Sint-truiden (zepperen)",
    "sg:classifiers":[
        {
            "category":"Farming",
            "subcategory":"Crops",
            "type":"Manufacturing & Wholesale Goods"
        }
    ],
    "sg:phone":"+32 478 75 12 58",
    "sg:postcode":"3800",
    "sg:province":"Limburg",
    "sg:tags":[
        "vegetable",
        "fruit",
        "-",
        "grower"
    ],
    "wof:name":"Vandersmissen F",
    "wof:placetype":"venue"
},
  "geometry": {"coordinates":[5.2737469673,50.8343582153],"type":"Point"}
}