{
  "type": "Feature",
  "properties": {
    "addr:full":"Aarschotsesteenweg 28 Tienen Vlaams-Brabant 3300",
    "addr:housenumber":"28",
    "addr:postcode":"3300",
    "addr:street":"Aarschotsesteenweg",
    "iso:country":"BE",
    "sg:address":"Aarschotsesteenweg 28",
    "sg:city":"Tienen",
    "sg:classifiers":[
        {
            "category":"Personal",
            "subcategory":"Beauty Salon",
            "type":"Services"
        }
    ],
    "sg:phone":"+32 16 81 26 72",
    "sg:postcode":"3300",
    "sg:province":"Vlaams-Brabant",
    "sg:tags":[
        "lady",
        "-",
        "hairdressing"
    ],
    "wof:name":"Arlette",
    "wof:placetype":"venue"
},
  "geometry": {"coordinates":[4.9275841713,50.8132743835],"type":"Point"}
}