{
  "type": "Feature",
  "properties": {
    "iso:country":"BE",
    "sg:address":"Place Communale 11",
    "sg:city":"Silly",
    "sg:orig_category":"Boekhouders",
    "sg:phone":"+32 68 55 23 24",
    "sg:postcode":"7830",
    "sg:province":"Hainaut",
    "wof:name":"Jean-claude Coche",
    "wof:placetype":"venue"
},
  "geometry": {"coordinates":[3.9236860275,50.6487770081],"type":"Point"}
}