{
  "type": "Feature",
  "properties": {
    "addr:full":"Rue Du Travail 9 - Zoning Industriel Nivelles Brabant Wallon 1400",
    "addr:housenumber":"9",
    "addr:postcode":"1400",
    "addr:street":"Rue Du Travail;Zoning Industriel",
    "iso:country":"BE",
    "sg:address":"Rue Du Travail 9 - Zoning Industriel",
    "sg:city":"Nivelles",
    "sg:classifiers":[
        {
            "category":"Building & Trades",
            "subcategory":"Plumbing",
            "type":"Services"
        }
    ],
    "sg:phone":"+32 67 49 37 10",
    "sg:postcode":"1400",
    "sg:province":"Brabant Wallon",
    "sg:tags":[
        "jacket",
        "sealing",
        "anticorrosive"
    ],
    "wof:name":"Stoncor Europe Sa",
    "wof:placetype":"venue"
},
  "geometry": {"coordinates":[4.3595428467,50.5958404541],"type":"Point"}
}