{
  "type": "Feature",
  "properties": {
    "iso:country":"BE",
    "sg:address":"Groenstraat 24",
    "sg:city":"Oud-heverlee",
    "sg:classifiers":[
        {
            "category":"Professional",
            "subcategory":"Computer Services",
            "type":"Services"
        }
    ],
    "sg:phone":"+32 16 40 19 21",
    "sg:postcode":"3050",
    "sg:province":"Vlaams-Brabant",
    "sg:tags":[
        "network"
    ],
    "wof:name":"Netcon",
    "wof:placetype":"venue"
},
  "geometry": {"coordinates":[4.6606740952,50.8360137939],"type":"Point"}
}