{
  "type": "Feature",
  "properties": {
    "addr:full":"Rue De Li\u00e8ge 39 Juprelle (lantin) Li\u00e8ge 4450",
    "addr:housenumber":"39",
    "addr:postcode":"4450",
    "addr:street":"Rue De Lie\u0300Ge;Lantin",
    "iso:country":"BE",
    "sg:address":"Rue De Li\u00e8ge 39",
    "sg:city":"Juprelle (lantin)",
    "sg:classifiers":[
        {
            "category":"Food & Beverages",
            "subcategory":"Specialty",
            "type":"Retail Goods"
        }
    ],
    "sg:phone":"+32 4 263 58 01",
    "sg:postcode":"4450",
    "sg:province":"Li\u00e8ge",
    "sg:tags":[
        "health",
        "dietary",
        "-",
        "biological"
    ],
    "wof:name":"Ferme A L'arbre De Liege",
    "wof:placetype":"venue"
},
  "geometry": {"coordinates":[5.5250401497,50.6844902039],"type":"Point"}
}