{
  "type": "Feature",
  "properties": {
    "addr:full":"Geetsvondelstraat 7 Tremelo Vlaams-Brabant 3120",
    "addr:housenumber":"7",
    "addr:postcode":"3120",
    "addr:street":"Geetsvondelstraat",
    "iso:country":"BE",
    "sg:address":"Geetsvondelstraat 7",
    "sg:city":"Tremelo",
    "sg:orig_category":"Herstellingen motorfietsen Motorfietsen",
    "sg:phone":"+32 16 53 82 87",
    "sg:postcode":"3120",
    "sg:province":"Vlaams-Brabant",
    "wof:name":"Putolev",
    "wof:placetype":"venue"
},
  "geometry": {"coordinates":[4.7546720505,50.9837226868],"type":"Point"}
}