{
  "type": "Feature",
  "properties": {
    "addr:full":"Provinciestraat 320 Antwerpen Antwerpen 2018",
    "addr:housenumber":"320",
    "addr:postcode":"2018",
    "addr:street":"Provinciestraat",
    "iso:country":"BE",
    "sg:address":"Provinciestraat 320",
    "sg:city":"Antwerpen",
    "sg:classifiers":[
        {
            "category":"Building & Trades",
            "subcategory":"Equipment Rental",
            "type":"Services"
        }
    ],
    "sg:phone":"+32 3 288 67 14",
    "sg:postcode":"2018",
    "sg:province":"Antwerpen",
    "sg:tags":[
        "machine",
        "industrial",
        "dishwashing"
    ],
    "wof:name":"Bontech",
    "wof:placetype":"venue"
},
  "geometry": {"coordinates":[4.4244799614,51.208782196],"type":"Point"}
}