{
  "type": "Feature",
  "properties": {
    "addr:full":"Rue Elise 59 Bruxelles (ixelles) Bruxelles-Capitale 1050",
    "addr:housenumber":"59",
    "addr:postcode":"1050",
    "addr:street":"Rue Elise",
    "iso:country":"BE",
    "sg:address":"Rue Elise 59",
    "sg:city":"Bruxelles (ixelles)",
    "sg:classifiers":[
        {
            "category":"Building & Trades",
            "subcategory":"Cleaning & Sanitation",
            "type":"Services"
        }
    ],
    "sg:phone":"+32 2 647 79 01",
    "sg:postcode":"1050",
    "sg:province":"Bruxelles-Capitale",
    "sg:tags":[
        "sweep",
        "chimney"
    ],
    "wof:name":"Maison Trentels",
    "wof:placetype":"venue"
},
  "geometry": {"coordinates":[4.3839631081,50.8182487488],"type":"Point"}
}