{
  "type": "Feature",
  "properties": {
    "addr:full":"Turkooislaan 33 Sint-genesius-rode/rhode-saint-genese Vlaams-Brabant 1640",
    "addr:housenumber":"33",
    "addr:postcode":"1640",
    "addr:street":"Turkooislaan",
    "iso:country":"BE",
    "sg:address":"Turkooislaan 33",
    "sg:city":"Sint-genesius-rode/rhode-saint-genese",
    "sg:orig_category":"Dansscholen",
    "sg:phone":"+32 2 380 00 99",
    "sg:postcode":"1640",
    "sg:province":"Vlaams-Brabant",
    "wof:name":"E. Mine",
    "wof:placetype":"venue"
},
  "geometry": {"coordinates":[4.3361539841,50.7346000671],"type":"Point"}
}