{
  "type": "Feature",
  "properties": {
    "addr:full":"Molenstraat 1 Aalst Oost-Vlaanderen 9310",
    "addr:housenumber":"1",
    "addr:postcode":"9310",
    "addr:street":"Molenstraat",
    "iso:country":"BE",
    "sg:address":"Molenstraat 1",
    "sg:city":"Aalst",
    "sg:classifiers":[
        {
            "category":"Cafe",
            "type":"Food & Drink"
        }
    ],
    "sg:phone":"+32 53 70 13 43",
    "sg:postcode":"9310",
    "sg:province":"Oost-Vlaanderen",
    "sg:tags":[
        "caf\u00e9s"
    ],
    "wof:name":"Magda Buyl",
    "wof:placetype":"venue"
},
  "geometry": {"coordinates":[4.0236501694,50.9376106262],"type":"Point"}
}