{
  "type": "Feature",
  "properties": {
    "addr:full":"Kapelaniestraat 8 Wevelgem (moorsele) West-Vlaanderen 8560",
    "addr:housenumber":"8",
    "addr:postcode":"8560",
    "addr:street":"Kapelaniestraat",
    "iso:country":"BE",
    "sg:address":"Kapelaniestraat 8",
    "sg:city":"Wevelgem (moorsele)",
    "sg:classifiers":[
        {
            "category":"Real Estate",
            "subcategory":"Real Estate Services",
            "type":"Services"
        }
    ],
    "sg:phone":"+32 56 50 35 00",
    "sg:postcode":"8560",
    "sg:province":"West-Vlaanderen",
    "wof:name":"Orema",
    "wof:placetype":"venue"
},
  "geometry": {"coordinates":[3.139482975,50.8344841003],"type":"Point"}
}