{
  "type": "Feature",
  "properties": {
    "addr:full":"Brugsesteenweg 528 Roeselare West-Vlaanderen 8800",
    "addr:housenumber":"528",
    "addr:postcode":"8800",
    "addr:street":"Brugsesteenweg",
    "iso:country":"BE",
    "sg:address":"Brugsesteenweg 528",
    "sg:city":"Roeselare",
    "sg:orig_category":"Location de voitures. Machines and mat\u00e9riel agricoles Gr",
    "sg:phone":"+32 51 20 45 81",
    "sg:postcode":"8800",
    "sg:province":"West-Vlaanderen",
    "wof:name":"Cluyse Christian",
    "wof:placetype":"venue"
},
  "geometry": {"coordinates":[3.1191000938,50.9758415222],"type":"Point"}
}