{
  "type": "Feature",
  "properties": {
    "iso:country":"BE",
    "sg:address":"Rue De La Gare 96",
    "sg:city":"Plombieres/plombieres",
    "sg:orig_category":"Epiceries",
    "sg:phone":"+32 87 78 61 57",
    "sg:postcode":"4850",
    "sg:province":"Li\u00e8ge",
    "wof:name":"P. Hermans",
    "wof:placetype":"venue"
},
  "geometry": {"coordinates":[5.9575219154,50.721321106],"type":"Point"}
}