{
  "type": "Feature",
  "properties": {
    "iso:country":"BE",
    "sg:address":"Vanden Elschenstraat 14",
    "sg:city":"Sint-pieters-leeuw",
    "sg:classifiers":[
        {
            "category":"Personal",
            "subcategory":"Beauty Salon",
            "type":"Services"
        }
    ],
    "sg:phone":"+32 2 377 08 46",
    "sg:postcode":"1601",
    "sg:province":"Vlaams-Brabant",
    "sg:tags":[
        "de",
        "coiffure"
    ],
    "wof:name":"Michel Dobbelaere",
    "wof:placetype":"venue"
},
  "geometry": {"coordinates":[4.2881708145,50.7847633362],"type":"Point"}
}