{
  "type": "Feature",
  "properties": {
    "iso:country":"BE",
    "sg:address":"Rue De La Roer 34",
    "sg:city":"Waimes/waimes",
    "sg:classifiers":[
        {
            "category":"Professional",
            "type":"Services"
        }
    ],
    "sg:phone":"+32 80 44 71 13",
    "sg:postcode":"4950",
    "sg:province":"Li\u00e8ge",
    "sg:tags":[
        "aux",
        "diver",
        "personnes"
    ],
    "wof:name":"Arthur Genten",
    "wof:placetype":"venue"
},
  "geometry": {"coordinates":[6.1210021973,50.4864311218],"type":"Point"}
}