{
  "type": "Feature",
  "properties": {
    "addr:full":"Landrainstraat 46 Wezembeek-oppem Vlaams-Brabant 1970",
    "addr:housenumber":"46",
    "addr:postcode":"1970",
    "addr:street":"Landrainstraat",
    "iso:country":"BE",
    "sg:address":"Landrainstraat 46",
    "sg:city":"Wezembeek-oppem",
    "sg:orig_category":"Diverse bedrijfsbeheeradviesbureaus",
    "sg:phone":"+32 2 731 64 55",
    "sg:postcode":"1970",
    "sg:province":"Vlaams-Brabant",
    "wof:name":"Stervan",
    "wof:placetype":"venue"
},
  "geometry": {"coordinates":[4.4763450623,50.8472061157],"type":"Point"}
}