{
  "type": "Feature",
  "properties": {
    "iso:country":"BE",
    "sg:address":"T Appelgoedje 15",
    "sg:city":"Poperinge",
    "sg:orig_category":"Studios photographiques",
    "sg:phone":"+32 57 33 66 29",
    "sg:postcode":"8970",
    "sg:province":"West-Vlaanderen",
    "wof:name":"Michael Blanckaert",
    "wof:placetype":"venue"
},
  "geometry": {"coordinates":[2.7107100487,50.8531990051],"type":"Point"}
}