{
  "type": "Feature",
  "properties": {
    "iso:country":"BE",
    "sg:address":"Potegemstraat 17b6",
    "sg:city":"Waregem",
    "sg:orig_category":"Secr\u00e9tariats sociaux",
    "sg:phone":"+32 56 61 47 40",
    "sg:postcode":"8790",
    "sg:province":"West-Vlaanderen",
    "wof:name":"Sociaal Hulpbetoon",
    "wof:placetype":"venue"
},
  "geometry": {"coordinates":[3.4377110004,50.8818626404],"type":"Point"}
}