{
  "type": "Feature",
  "properties": {
    "iso:country":"BE",
    "sg:address":"Jan Van Rijswijcklaan 62",
    "sg:city":"Antwerpen",
    "sg:classifiers":[
        {
            "category":"Social Services",
            "subcategory":"Retirement Home",
            "type":"Services"
        }
    ],
    "sg:phone":"+32 3 260 25 11",
    "sg:postcode":"2018",
    "sg:province":"Antwerpen",
    "sg:tags":[
        "compagnies",
        "vie",
        "assurance",
        "habitation"
    ],
    "wof:name":"Verzekeringen G.b. Lex",
    "wof:placetype":"venue"
},
  "geometry": {"coordinates":[4.4067411423,51.1975402832],"type":"Point"}
}