{
  "type": "Feature",
  "properties": {
    "addr:full":"Rue Stevin 174 Bruxelles Bruxelles-Capitale 1000",
    "addr:housenumber":"174",
    "addr:postcode":"1000",
    "addr:street":"Rue Stevin",
    "iso:country":"BE",
    "sg:address":"Rue Stevin 174",
    "sg:city":"Bruxelles",
    "sg:classifiers":[
        {
            "category":"Government",
            "subcategory":"Embassy",
            "type":"Public Place"
        }
    ],
    "sg:phone":"+32 2 219 63 65",
    "sg:postcode":"1000",
    "sg:province":"Bruxelles-Capitale",
    "sg:tags":[
        "consulate"
    ],
    "wof:name":"Belgium Visa Service",
    "wof:placetype":"venue"
},
  "geometry": {"coordinates":[4.384185791,50.8441772461],"type":"Point"}
}