{
  "type": "Feature",
  "properties": {
    "iso:country":"BE",
    "sg:address":"Rue Du Mont Saint-alban 20",
    "sg:city":"Bruxelles",
    "sg:classifiers":[
        {
            "category":"Personal",
            "subcategory":"Psychics & Astrologers",
            "type":"Services"
        }
    ],
    "sg:phone":"+32 2 476 92 97",
    "sg:postcode":"1020",
    "sg:province":"Bruxelles-Capitale",
    "sg:tags":[
        "astrology"
    ],
    "wof:name":"Wagner L",
    "wof:placetype":"venue"
},
  "geometry": {"coordinates":[4.3471431732,50.8826751709],"type":"Point"}
}