{
  "type": "Feature",
  "properties": {
    "iso:country":"BE",
    "sg:address":"Rue Saint-laurent 189",
    "sg:city":"Li\u00c8ge",
    "sg:orig_category":"Artsen and specialisten",
    "sg:phone":"+32 4 252 83 70",
    "sg:postcode":"4000",
    "sg:province":"Li\u00e8ge",
    "wof:name":"Carla Zennaro",
    "wof:placetype":"venue"
},
  "geometry": {"coordinates":[5.5543460846,50.6370735168],"type":"Point"}
}