{
  "type": "Feature",
  "properties": {
    "addr:full":"Oudebaan 3 Antwerpen Antwerpen 2180",
    "addr:housenumber":"3",
    "addr:postcode":"2180",
    "addr:street":"Oudebaan",
    "iso:country":"BE",
    "sg:address":"Oudebaan 3",
    "sg:city":"Antwerpen",
    "sg:orig_category":"Brood, gebak and snoepgoed",
    "sg:phone":"+32 3 645 93 00",
    "sg:postcode":"2180",
    "sg:province":"Antwerpen",
    "wof:name":"Bakkerij Edelweiss",
    "wof:placetype":"venue"
},
  "geometry": {"coordinates":[4.4189357758,51.2249298096],"type":"Point"}
}