{
  "type": "Feature",
  "properties": {
    "iso:country":"BE",
    "sg:address":"All\u00e9e Des Alouettes 100",
    "sg:city":"Vis\u00e9",
    "sg:classifiers":[
        {
            "category":"Health Services",
            "subcategory":"Nursing And Care Facility",
            "type":"Services"
        }
    ],
    "sg:phone":"+32 4 374 91 91",
    "sg:postcode":"4600",
    "sg:province":"Li\u00e8ge",
    "sg:tags":[
        "home",
        "rest"
    ],
    "wof:name":"R\u00e9sidence & Polyclinique Les 3 Rois",
    "wof:placetype":"venue"
},
  "geometry": {"coordinates":[5.7082290649,50.7391700745],"type":"Point"}
}