{
  "type": "Feature",
  "properties": {
    "iso:country":"BE",
    "sg:address":"Rue Charles Simon 53",
    "sg:city":"Namur (bouge)",
    "sg:classifiers":[
        {
            "category":"Building & Trades",
            "subcategory":"Landscaping Services",
            "type":"Services"
        }
    ],
    "sg:postcode":"5004",
    "sg:province":"Namur",
    "sg:tags":[
        "-",
        "lopping",
        "work",
        "tree",
        "felling"
    ],
    "wof:name":"Rongvaux Fabrice",
    "wof:placetype":"venue"
},
  "geometry": {"coordinates":[4.8789200783,50.4729042053],"type":"Point"}
}