{
  "type": "Feature",
  "properties": {
    "addr:full":"Dorekensstraat 10 Galmaarden Vlaams-Brabant 1570",
    "addr:housenumber":"10",
    "addr:postcode":"1570",
    "addr:street":"Dorekensstraat",
    "iso:country":"BE",
    "sg:address":"Dorekensstraat 10",
    "sg:city":"Galmaarden",
    "sg:classifiers":[
        {
            "category":"Manufacturing",
            "subcategory":"Petroleum Products",
            "type":"Manufacturing & Wholesale Goods"
        }
    ],
    "sg:phone":"+32 54 34 11 20",
    "sg:postcode":"1570",
    "sg:province":"Vlaams-Brabant",
    "sg:tags":[
        "production",
        "combustible",
        "de",
        "distribution",
        "gaz"
    ],
    "wof:name":"Bruno Surkyn",
    "wof:placetype":"venue"
},
  "geometry": {"coordinates":[3.9606559277,50.7758293152],"type":"Point"}
}