{
  "type": "Feature",
  "properties": {
    "iso:country":"BE",
    "sg:address":"Chemin De Marquain 5",
    "sg:city":"Tournai",
    "sg:orig_category":"Kapsalons",
    "sg:phone":"+32 69 84 62 70",
    "sg:postcode":"7522",
    "sg:province":"Hainaut",
    "wof:name":"Coiffure New Style",
    "wof:placetype":"venue"
},
  "geometry": {"coordinates":[3.2966010571,50.6006278992],"type":"Point"}
}