{
  "type": "Feature",
  "properties": {
    "iso:country":"BE",
    "sg:address":"Rue Du Pont 2",
    "sg:city":"Theux",
    "sg:classifiers":[
        {
            "category":"Shopping",
            "subcategory":"Jewelry",
            "type":"Retail Goods"
        }
    ],
    "sg:postcode":"4910",
    "sg:province":"Li\u00e8ge",
    "sg:tags":[
        "jeweller",
        "-"
    ],
    "wof:name":"Demoulin Bijouterie",
    "wof:placetype":"venue"
},
  "geometry": {"coordinates":[5.8133020401,50.5364608765],"type":"Point"}
}