{
  "type": "Feature",
  "properties": {
    "iso:country":"BE",
    "sg:address":"Kampweg 123",
    "sg:city":"Wuustwezel",
    "sg:classifiers":[
        {
            "category":"Manufacturing",
            "subcategory":"Metals",
            "type":"Manufacturing & Wholesale Goods"
        }
    ],
    "sg:phone":"+32 3 690 02 40",
    "sg:postcode":"2990",
    "sg:province":"Antwerpen",
    "sg:tags":[
        "treatment",
        "surface"
    ],
    "wof:name":"Superior Products Nv",
    "wof:placetype":"venue"
},
  "geometry": {"coordinates":[4.5999178886,51.3885040283],"type":"Point"}
}