{
  "type": "Feature",
  "properties": {
    "addr:full":"Hoogveld 1a Haacht Vlaams-Brabant 3150",
    "addr:housenumber":"1a",
    "addr:postcode":"3150",
    "addr:street":"Hoogveld",
    "iso:country":"BE",
    "sg:address":"Hoogveld 1a",
    "sg:city":"Haacht",
    "sg:classifiers":[
        {
            "category":"Manufacturing",
            "subcategory":"Printing",
            "type":"Manufacturing & Wholesale Goods"
        }
    ],
    "sg:phone":"+32 16 60 42 96",
    "sg:postcode":"3150",
    "sg:province":"Vlaams-Brabant",
    "sg:tags":[
        "textile",
        "-"
    ],
    "wof:name":"Drukpunt Bvba",
    "wof:placetype":"venue"
},
  "geometry": {"coordinates":[4.6434350014,50.9736671448],"type":"Point"}
}