{
  "type": "Feature",
  "properties": {
    "iso:country":"BE",
    "sg:address":"Rammelstraat 7ba",
    "sg:city":"Lede",
    "sg:orig_category":"Diverse kredietdiensten",
    "sg:postcode":"9340",
    "sg:province":"Oost-Vlaanderen",
    "wof:name":"Bancontact-mister Cash",
    "wof:placetype":"venue"
},
  "geometry": {"coordinates":[3.9769198895,50.967250824],"type":"Point"}
}