{
  "type": "Feature",
  "properties": {
    "addr:full":"Hertogendreef 2 Watermaal-bosvoorde/watermael-boitsfort Bruxelles-Capitale 1170",
    "addr:housenumber":"2",
    "addr:postcode":"1170",
    "addr:street":"Hertogendreef",
    "iso:country":"BE",
    "sg:address":"Hertogendreef 2",
    "sg:city":"Watermaal-bosvoorde/watermael-boitsfort",
    "sg:orig_category":"Openbare veiligheid",
    "sg:phone":"+32 2 674 74 74",
    "sg:postcode":"1170",
    "sg:province":"Bruxelles-Capitale",
    "wof:name":"Police F\u00c9d\u00c9rale/federale Politie",
    "wof:placetype":"venue"
},
  "geometry": {"coordinates":[4.4163842201,50.7981758118],"type":"Point"}
}