{
  "type": "Feature",
  "properties": {
    "addr:full":"Leedsesteenweg 148 Erpe-mere (erpe) Oost-Vlaanderen 9420",
    "addr:housenumber":"148",
    "addr:postcode":"9420",
    "addr:street":"Leedsesteenweg",
    "iso:country":"BE",
    "sg:address":"Leedsesteenweg 148",
    "sg:city":"Erpe-mere (erpe)",
    "sg:classifiers":[
        {
            "category":"Personal",
            "subcategory":"Barber",
            "type":"Services"
        }
    ],
    "sg:phone":"+32 53 80 10 50",
    "sg:postcode":"9420",
    "sg:province":"Oost-Vlaanderen",
    "sg:tags":[
        "gentleman",
        "salon",
        "-",
        "hairdressing"
    ],
    "wof:name":"Martine",
    "wof:placetype":"venue"
},
  "geometry": {"coordinates":[3.9824910164,50.9522018433],"type":"Point"}
}