{
  "type": "Feature",
  "properties": {
    "iso:country":"BE",
    "sg:address":"Cit\u00c9 De Husquet 3",
    "sg:city":"Dison",
    "sg:orig_category":"Paramedische behandelingen",
    "sg:phone":"+32 87 31 32 71",
    "sg:postcode":"4820",
    "sg:province":"Li\u00e8ge",
    "wof:name":"D. Brandt",
    "wof:placetype":"venue"
},
  "geometry": {"coordinates":[5.8462162018,50.6084327698],"type":"Point"}
}