{
  "type": "Feature",
  "properties": {
    "iso:country":"BE",
    "sg:address":"Gasthuisstraat 3",
    "sg:city":"Kuurne",
    "sg:orig_category":"Diverse bouwafwerking and reiniging Gespecialiseerde residenti\u00eble bouw Woningbouw",
    "sg:phone":"+32 56 71 40 67",
    "sg:postcode":"8520",
    "sg:province":"West-Vlaanderen",
    "wof:name":"Freddy Vandekerckhove",
    "wof:placetype":"venue"
},
  "geometry": {"coordinates":[3.2847130299,50.850894928],"type":"Point"}
}