{
  "type": "Feature",
  "properties": {
    "iso:country":"BE",
    "sg:address":"Rue Des Anciennes Houblonni\u00e8res 2",
    "sg:city":"Li\u00e8ge",
    "sg:classifiers":[
        {
            "category":"Food Court",
            "type":"Food & Drink"
        }
    ],
    "sg:phone":"+32 4 345 82 11",
    "sg:postcode":"4020",
    "sg:province":"Li\u00e8ge",
    "sg:tags":[
        "product",
        "related"
    ],
    "wof:name":"Interbrew Sa",
    "wof:placetype":"venue"
},
  "geometry": {"coordinates":[5.5829439163,50.6254577637],"type":"Point"}
}