{
  "type": "Feature",
  "properties": {
    "addr:full":"Vijverstraat 10 Aalst (hofstade) Oost-Vlaanderen 9308",
    "addr:housenumber":"10",
    "addr:postcode":"9308",
    "addr:street":"Vijverstraat",
    "iso:country":"BE",
    "sg:address":"Vijverstraat 10",
    "sg:city":"Aalst (hofstade)",
    "sg:classifiers":[
        {
            "category":"Autos & Motor Vehicles",
            "subcategory":"Automobile Sales",
            "type":"Retail Goods"
        }
    ],
    "sg:phone":"+32 53 78 39 01",
    "sg:postcode":"9308",
    "sg:province":"Oost-Vlaanderen",
    "sg:tags":[
        "motorhomes",
        "accessory"
    ],
    "wof:name":"B-free",
    "wof:placetype":"venue"
},
  "geometry": {"coordinates":[4.0347590446,50.9603500366],"type":"Point"}
}