{
  "type": "Feature",
  "properties": {
    "addr:full":"Rue De La Pecherie 19 Antoing Hainaut 7640",
    "addr:housenumber":"19",
    "addr:postcode":"7640",
    "addr:street":"Rue De La Pecherie",
    "iso:country":"BE",
    "sg:address":"Rue De La Pecherie 19",
    "sg:city":"Antoing",
    "sg:orig_category":"M\u00e9decins and sp\u00e9cialistes",
    "sg:phone":"+32 69 44 31 31",
    "sg:postcode":"7640",
    "sg:province":"Hainaut",
    "wof:name":"S. Bonsignore",
    "wof:placetype":"venue"
},
  "geometry": {"coordinates":[3.4444589615,50.5664367676],"type":"Point"}
}