{
  "type": "Feature",
  "properties": {
    "addr:full":"Rue Hauvent 54 Fosses-la-ville Namur 5070",
    "addr:housenumber":"54",
    "addr:postcode":"5070",
    "addr:street":"Rue Hauvent",
    "iso:country":"BE",
    "sg:address":"Rue Hauvent 54",
    "sg:city":"Fosses-la-ville",
    "sg:classifiers":[
        {
            "category":"Health Services",
            "subcategory":"Health Practitioner",
            "type":"Services"
        }
    ],
    "sg:phone":"+32 71 35 74 77",
    "sg:postcode":"5070",
    "sg:province":"Namur",
    "sg:tags":[
        "physiotherapist"
    ],
    "wof:name":"De Coster Ch (mme)",
    "wof:placetype":"venue"
},
  "geometry": {"coordinates":[4.697933197,50.3955917358],"type":"Point"}
}