{
  "type": "Feature",
  "properties": {
    "addr:full":"Rue De Nimy 94 Mons Hainaut 7000",
    "addr:housenumber":"94",
    "addr:postcode":"7000",
    "addr:street":"Rue De Nimy;Hainaut",
    "iso:country":"BE",
    "sg:address":"Rue De Nimy 94",
    "sg:city":"Mons",
    "sg:orig_category":"Huwelijks- and Relatiebureaus",
    "sg:phone":"+32 65 84 48 66",
    "sg:postcode":"7000",
    "sg:province":"Hainaut",
    "wof:name":"Val\u00c9rie Dax",
    "wof:placetype":"venue"
},
  "geometry": {"coordinates":[3.9556529522,50.4580726624],"type":"Point"}
}