{
  "type": "Feature",
  "properties": {
    "addr:full":"Koning Albertstraat 82 Ravels Antwerpen 2381",
    "addr:housenumber":"82",
    "addr:postcode":"2381",
    "addr:street":"Koning Albertstraat",
    "iso:country":"BE",
    "sg:address":"Koning Albertstraat 82",
    "sg:city":"Ravels",
    "sg:orig_category":"Banques and organismes de cr\u00e9dit",
    "sg:phone":"+32 14 65 54 86",
    "sg:postcode":"2381",
    "sg:province":"Antwerpen",
    "wof:name":"Kbc",
    "wof:placetype":"venue"
},
  "geometry": {"coordinates":[5.0049109459,51.4118080139],"type":"Point"}
}