{
  "type": "Feature",
  "properties": {
    "addr:full":"Invaliedenplein 9 Diksmuide West-Vlaanderen 8600",
    "addr:housenumber":"9",
    "addr:postcode":"8600",
    "addr:street":"Invaliedenplein",
    "iso:country":"BE",
    "sg:address":"Invaliedenplein 9",
    "sg:city":"Diksmuide",
    "sg:classifiers":[
        {
            "category":"Retail",
            "subcategory":"Veterinary Services",
            "type":"Services"
        }
    ],
    "sg:phone":"+32 51 51 02 63",
    "sg:postcode":"8600",
    "sg:province":"West-Vlaanderen",
    "sg:tags":[
        "veterinarian"
    ],
    "wof:name":"Moerman J",
    "wof:placetype":"venue"
},
  "geometry": {"coordinates":[2.8663010597,51.0351676941],"type":"Point"}
}