{
  "type": "Feature",
  "properties": {
    "addr:full":"Sint-elisabethstraat 56 Antwerpen Antwerpen 2060",
    "addr:housenumber":"56",
    "addr:postcode":"2060",
    "addr:street":"Sint-Elisabethstraat",
    "iso:country":"BE",
    "sg:address":"Sint-elisabethstraat 56",
    "sg:city":"Antwerpen",
    "sg:classifiers":[
        {
            "category":"Personal",
            "subcategory":"Beauty Salon",
            "type":"Services"
        }
    ],
    "sg:phone":"+32 3 236 64 49",
    "sg:postcode":"2060",
    "sg:province":"Antwerpen",
    "sg:tags":[
        "de",
        "coiffure"
    ],
    "wof:name":"Haute Coiffure Lambeau",
    "wof:placetype":"venue"
},
  "geometry": {"coordinates":[4.425383091,51.222858429],"type":"Point"}
}