{
  "type": "Feature",
  "properties": {
    "addr:full":"Avenue R. De Grimberghe 34 Rixensart Brabant Wallon 1330",
    "addr:housenumber":"34",
    "addr:postcode":"1330",
    "addr:street":"Avenue R. De Grimberghe;Wallon",
    "iso:country":"BE",
    "sg:address":"Avenue R. De Grimberghe 34",
    "sg:city":"Rixensart",
    "sg:classifiers":[
        {
            "category":"Real Estate",
            "subcategory":"Real Estate Services",
            "type":"Services"
        }
    ],
    "sg:phone":"+32 2 652 35 77",
    "sg:postcode":"1330",
    "sg:province":"Brabant Wallon",
    "wof:name":"Huybrechts V",
    "wof:placetype":"venue"
},
  "geometry": {"coordinates":[4.5224947929,50.7150840759],"type":"Point"}
}