{
  "type": "Feature",
  "properties": {
    "iso:country":"BE",
    "sg:address":"Deken De Bostraat 94",
    "sg:city":"Waregem (beveren-leie)",
    "sg:classifiers":[
        {
            "category":"Health Services",
            "subcategory":"Health Practitioner",
            "type":"Services"
        }
    ],
    "sg:phone":"+32 56 70 61 73",
    "sg:postcode":"8791",
    "sg:province":"West-Vlaanderen",
    "sg:tags":[
        "therapist",
        "speech"
    ],
    "wof:name":"Pappens Nancy",
    "wof:placetype":"venue"
},
  "geometry": {"coordinates":[3.3421061039,50.8787651062],"type":"Point"}
}