{
  "type": "Feature",
  "properties": {
    "iso:country":"BE",
    "sg:address":"Johannes Hartmannlaan 4",
    "sg:city":"Gent",
    "sg:classifiers":[
        {
            "category":"Sports & Exercise",
            "subcategory":"Sports Center",
            "type":"Entertainment"
        }
    ],
    "sg:phone":"+32 9 238 10 35",
    "sg:postcode":"9000",
    "sg:province":"Oost-Vlaanderen",
    "sg:tags":[
        "de",
        "fitness"
    ],
    "wof:name":"Spartacus Gym",
    "wof:placetype":"venue"
},
  "geometry": {"coordinates":[3.701570034,51.0540122986],"type":"Point"}
}