{
  "type": "Feature",
  "properties": {
    "addr:full":"Rue Genly 131 Z Frameries Vlaams-Brabant 1570",
    "addr:housenumber":"131 z",
    "addr:postcode":"1570",
    "addr:street":"Rue Genly",
    "iso:country":"BE",
    "sg:address":"Rue Genly 131 Z",
    "sg:city":"Frameries",
    "sg:orig_category":"Treinen and spoorwegen",
    "sg:phone":"+32 65 67 25 94",
    "sg:postcode":"1570",
    "sg:province":"Vlaams-Brabant",
    "wof:name":"Gare De Frameries",
    "wof:placetype":"venue"
},
  "geometry": {"coordinates":[3.9187200069,50.3922691345],"type":"Point"}
}