{
  "type": "Feature",
  "properties": {
    "iso:country":"BE",
    "sg:address":"Rue Jardon 37",
    "sg:city":"Verviers",
    "sg:classifiers":[
        {
            "category":"Building & Trades",
            "subcategory":"Construction",
            "type":"Services"
        }
    ],
    "sg:phone":"+32 87 33 57 80",
    "sg:postcode":"4800",
    "sg:province":"Li\u00e8ge",
    "sg:tags":[
        "industrial",
        "design"
    ],
    "wof:name":"Blanchy J",
    "wof:placetype":"venue"
},
  "geometry": {"coordinates":[5.8575758934,50.5904502869],"type":"Point"}
}