{
  "type": "Feature",
  "properties": {
    "addr:full":"Elisabethlaan 49 Box 1 Ninove Oost-Vlaanderen 9400",
    "addr:housenumber":"49;1",
    "addr:postcode":"9400",
    "addr:street":"Elisabethlaan;Box",
    "iso:country":"BE",
    "sg:address":"Elisabethlaan 49 Box 1",
    "sg:city":"Ninove",
    "sg:classifiers":[
        {
            "category":"Building & Trades",
            "subcategory":"Construction",
            "type":"Services"
        }
    ],
    "sg:phone":"+32 54 30 00 91",
    "sg:postcode":"9400",
    "sg:province":"Oost-Vlaanderen",
    "sg:tags":[
        "fork",
        "lift",
        "truck"
    ],
    "wof:name":"Afs",
    "wof:placetype":"venue"
},
  "geometry": {"coordinates":[4.0073537827,50.8359107971],"type":"Point"}
}