{
  "type": "Feature",
  "properties": {
    "addr:full":"Regentiestraat 46 Sint-niklaas Oost-Vlaanderen 9100",
    "addr:housenumber":"46",
    "addr:postcode":"9100",
    "addr:street":"Regentiestraat",
    "iso:country":"BE",
    "sg:address":"Regentiestraat 46",
    "sg:city":"Sint-niklaas",
    "sg:classifiers":[
        {
            "category":"Shopping",
            "subcategory":"Beauty & Cosmetics",
            "type":"Retail Goods"
        }
    ],
    "sg:phone":"+32 3 776 71 42",
    "sg:postcode":"9100",
    "sg:province":"Oost-Vlaanderen",
    "sg:tags":[
        "-",
        "perfumery"
    ],
    "wof:name":"Groupage Jeunesse",
    "wof:placetype":"venue"
},
  "geometry": {"coordinates":[4.1472411156,51.168182373],"type":"Point"}
}