{
  "type": "Feature",
  "properties": {
    "addr:full":"Rue Du Bassin 57 Li\u00e8ge 1 (grivegn\u00e9e) Li\u00e8ge 4030",
    "addr:housenumber":"57;1",
    "addr:postcode":"4030",
    "addr:street":"Rue Du Bassin",
    "iso:country":"BE",
    "sg:address":"Rue Du Bassin 57",
    "sg:city":"Li\u00e8ge 1 (grivegn\u00e9e)",
    "sg:classifiers":[
        {
            "category":"Professional",
            "type":"Services"
        }
    ],
    "sg:phone":"+32 4 365 99 31",
    "sg:postcode":"4030",
    "sg:province":"Li\u00e8ge",
    "sg:tags":[
        "entertainer"
    ],
    "wof:name":"Roba V",
    "wof:placetype":"venue"
},
  "geometry": {"coordinates":[5.6131110191,50.6314201355],"type":"Point"}
}