{
  "type": "Feature",
  "properties": {
    "addr:full":"Slachthuisstraat 27-35 Brussel Bruxelles-Capitale 1000",
    "addr:postcode":"27-35;1000",
    "addr:street":"Slachthuisstraat",
    "iso:country":"BE",
    "sg:address":"Slachthuisstraat 27-35",
    "sg:city":"Brussel",
    "sg:classifiers":[
        {
            "category":"Professional",
            "subcategory":"Advertising",
            "type":"Services"
        }
    ],
    "sg:phone":"+32 2 513 82 95",
    "sg:postcode":"1000",
    "sg:province":"Bruxelles-Capitale",
    "sg:tags":[
        "matter",
        "printed",
        "matters"
    ],
    "wof:name":"Bouwkroniek Nv",
    "wof:placetype":"venue"
},
  "geometry": {"coordinates":[4.3386721611,50.8468475342],"type":"Point"}
}