{
  "type": "Feature",
  "properties": {
    "iso:country":"BE",
    "sg:address":"Rue Du Moulin 16",
    "sg:city":"Hannut",
    "sg:orig_category":"Varkenskwekers",
    "sg:phone":"+32 19 51 06 99",
    "sg:postcode":"4280",
    "sg:province":"Li\u00e8ge",
    "wof:name":"Andre Deneys",
    "wof:placetype":"venue"
},
  "geometry": {"coordinates":[5.0699567795,50.6764755249],"type":"Point"}
}