{
  "type": "Feature",
  "properties": {
    "iso:country":"BE",
    "sg:address":"Mechelsesteenweg 35",
    "sg:city":"Vilvoorde",
    "sg:orig_category":"Meubles D\u00e9taillants, Am\u00e9nagement de B\u00e2timents et de Cuisines",
    "sg:phone":"+32 2 253 32 35",
    "sg:postcode":"1800",
    "sg:province":"Vlaams-Brabant",
    "wof:name":"Kieffer Meubelen",
    "wof:placetype":"venue"
},
  "geometry": {"coordinates":[4.4250950813,50.933216095],"type":"Point"}
}