{
  "type": "Feature",
  "properties": {
    "iso:country":"BE",
    "sg:address":"Bellevaux 12",
    "sg:city":"Malmedy",
    "sg:orig_category":"Enseignement maternel and primaire",
    "sg:phone":"+32 80 33 94 15",
    "sg:postcode":"4960",
    "sg:province":"Li\u00e8ge",
    "wof:name":"Ecole Prim. Communale",
    "wof:placetype":"venue"
},
  "geometry": {"coordinates":[6.0252141953,50.421546936],"type":"Point"}
}