{
  "type": "Feature",
  "properties": {
    "addr:full":"Museumstraat 30 Bellem-aalter Oost-Vlaanderen 9880",
    "addr:housenumber":"30",
    "addr:postcode":"9880",
    "addr:street":"Museumstraat;Oost-Vlaanderen",
    "iso:country":"BE",
    "sg:address":"Museumstraat 30",
    "sg:city":"Bellem-aalter",
    "sg:orig_category":"Aanleg van opritten and terreinen bij woningen Afbraak- and draineerwerken Verhuur diverse uitrustin",
    "sg:phone":"+32 477 29 36 12",
    "sg:postcode":"9880",
    "sg:province":"Oost-Vlaanderen",
    "wof:name":"Geert De Baere Grondwerken",
    "wof:placetype":"venue"
},
  "geometry": {"coordinates":[3.4227600098,51.069480896],"type":"Point"}
}