{
  "type": "Feature",
  "properties": {
    "iso:country":"BE",
    "sg:address":"Oude Diestsestraat 8",
    "sg:city":"Glabbeek (bunsbeek)",
    "sg:classifiers":[
        {
            "category":"Personal",
            "subcategory":"Nail Salon",
            "type":"Services"
        }
    ],
    "sg:phone":"+32 16 82 33 68",
    "sg:postcode":"3380",
    "sg:province":"Vlaams-Brabant",
    "sg:tags":[
        "pedicure"
    ],
    "wof:name":"De Grande Sonja",
    "wof:placetype":"venue"
},
  "geometry": {"coordinates":[4.9547581673,50.8473625183],"type":"Point"}
}