{
  "type": "Feature",
  "properties": {
    "addr:full":"Steenbergstraat 42 Grobbendonk Antwerpen 2280",
    "addr:housenumber":"42",
    "addr:postcode":"2280",
    "addr:street":"Steenbergstraat",
    "iso:country":"BE",
    "sg:address":"Steenbergstraat 42",
    "sg:city":"Grobbendonk",
    "sg:orig_category":"Vertalers and tolken",
    "sg:phone":"+32 14 50 79 40",
    "sg:postcode":"2280",
    "sg:province":"Antwerpen",
    "wof:name":"Dhaxley Translations",
    "wof:placetype":"venue"
},
  "geometry": {"coordinates":[4.7411460876,51.1951446533],"type":"Point"}
}