{
  "type": "Feature",
  "properties": {
    "addr:full":"Rue De Ville 7 Bernissart (pommeroeul) Hainaut 7322",
    "addr:housenumber":"7",
    "addr:postcode":"7322",
    "addr:street":"Rue De Ville",
    "iso:country":"BE",
    "sg:address":"Rue De Ville 7",
    "sg:city":"Bernissart (pommeroeul)",
    "sg:classifiers":[
        {
            "category":"Professional",
            "subcategory":"Testing Lab",
            "type":"Services"
        }
    ],
    "sg:phone":"+32 65 62 04 12",
    "sg:postcode":"7322",
    "sg:province":"Hainaut",
    "sg:tags":[
        "chemist"
    ],
    "wof:name":"Crasset J C",
    "wof:placetype":"venue"
},
  "geometry": {"coordinates":[3.7141079903,50.4626350403],"type":"Point"}
}