{
  "type": "Feature",
  "properties": {
    "iso:country":"BE",
    "sg:address":"Chemin Des Dames 20",
    "sg:city":"Braine-le-comte",
    "sg:classifiers":[
        {
            "category":"Professional",
            "subcategory":"Accounting & Tax Preparation",
            "type":"Services"
        }
    ],
    "sg:phone":"+32 67 55 39 82",
    "sg:postcode":"7090",
    "sg:province":"Hainaut",
    "sg:tags":[
        "accountant"
    ],
    "wof:name":"Jan Roelant",
    "wof:placetype":"venue"
},
  "geometry": {"coordinates":[4.1551008224,50.6083488464],"type":"Point"}
}