{
  "type": "Feature",
  "properties": {
    "addr:full":"Heirweg 14 Kuurne West-Vlaanderen 8520",
    "addr:housenumber":"14",
    "addr:postcode":"8520",
    "addr:street":"Heirweg",
    "iso:country":"BE",
    "sg:address":"Heirweg 14",
    "sg:city":"Kuurne",
    "sg:classifiers":[
        {
            "category":"Parking",
            "subcategory":"Lot",
            "type":"Transportation"
        }
    ],
    "sg:phone":"+32 56 35 52 42",
    "sg:postcode":"8520",
    "sg:province":"West-Vlaanderen",
    "sg:tags":[
        "armoured",
        "door",
        "fireproof"
    ],
    "wof:name":"Halsberghe Fres",
    "wof:placetype":"venue"
},
  "geometry": {"coordinates":[3.2645390034,50.8541526794],"type":"Point"}
}