{
  "type": "Feature",
  "properties": {
    "iso:country":"BE",
    "sg:address":"Rue Bosquetville 16",
    "sg:city":"Charleroi",
    "sg:classifiers":[
        {
            "category":"Building & Trades",
            "subcategory":"Equipment Rental",
            "type":"Services"
        }
    ],
    "sg:phone":"+32 71 31 67 39",
    "sg:postcode":"6000",
    "sg:province":"Hainaut",
    "sg:tags":[
        "safety",
        "collective",
        "individual",
        "-"
    ],
    "wof:name":"New Ever Best Sprl",
    "wof:placetype":"venue"
},
  "geometry": {"coordinates":[4.44917202,50.405380249],"type":"Point"}
}