{
  "type": "Feature",
  "properties": {
    "iso:country":"BE",
    "sg:address":"Rue De Tyberchamps 8",
    "sg:city":"Manage",
    "sg:orig_category":"Non-Classified Establishments",
    "sg:phone":"+32 64 55 91 72",
    "sg:postcode":"7170",
    "sg:province":"Hainaut",
    "wof:name":"Mineur P",
    "wof:placetype":"venue"
},
  "geometry": {"coordinates":[4.2225899696,50.5196418762],"type":"Point"}
}