{
  "type": "Feature",
  "properties": {
    "addr:full":"Rue Bouillenne 63 Fl\u00e9ron Li\u00e8ge 4620",
    "addr:housenumber":"63",
    "addr:postcode":"4620",
    "addr:street":"Rue Bouillenne",
    "iso:country":"BE",
    "sg:address":"Rue Bouillenne 63",
    "sg:city":"Fl\u00e9ron",
    "sg:classifiers":[
        {
            "category":"Communications",
            "subcategory":"Film & Video Production",
            "type":"Services"
        }
    ],
    "sg:phone":"+32 4 358 04 34",
    "sg:postcode":"4620",
    "sg:province":"Li\u00e8ge",
    "sg:tags":[
        "realisation",
        "-"
    ],
    "wof:name":"Vete-video",
    "wof:placetype":"venue"
},
  "geometry": {"coordinates":[5.6812682152,50.616104126],"type":"Point"}
}