{
  "type": "Feature",
  "properties": {
    "addr:full":"Avenue De Stalingrad 13 Bruxelles Bruxelles-Capitale 1000",
    "addr:housenumber":"13",
    "addr:postcode":"1000",
    "addr:street":"Avenue De Stalingrad",
    "iso:country":"BE",
    "sg:address":"Avenue De Stalingrad 13",
    "sg:city":"Bruxelles",
    "sg:classifiers":[
        {
            "category":"Professional",
            "subcategory":"Testing Lab",
            "type":"Services"
        }
    ],
    "sg:phone":"+32 2 512 32 14",
    "sg:postcode":"1000",
    "sg:province":"Bruxelles-Capitale",
    "sg:tags":[
        "chemist"
    ],
    "wof:name":"Pharmacie De La Place Rouppe",
    "wof:placetype":"venue"
},
  "geometry": {"coordinates":[4.344976902,50.8424453735],"type":"Point"}
}