{
  "type": "Feature",
  "properties": {
    "iso:country":"BE",
    "sg:address":"Lange Leemstraat 103",
    "sg:city":"Antwerpen",
    "sg:orig_category":"Blanchisseries and teintureries",
    "sg:phone":"+32 3 231 80 11",
    "sg:postcode":"2018",
    "sg:province":"Antwerpen",
    "wof:name":"Speedy Center",
    "wof:placetype":"venue"
},
  "geometry": {"coordinates":[4.412967205,51.2081565857],"type":"Point"}
}