{
  "type": "Feature",
  "properties": {
    "addr:full":"Elizastraat 8 Elsene/ixelles Bruxelles-Capitale 1050",
    "addr:housenumber":"8",
    "addr:postcode":"1050",
    "addr:street":"Elizastraat",
    "iso:country":"BE",
    "sg:address":"Elizastraat 8",
    "sg:city":"Elsene/ixelles",
    "sg:orig_category":"Artsen and specialisten",
    "sg:phone":"+32 2 640 31 20",
    "sg:postcode":"1050",
    "sg:province":"Bruxelles-Capitale",
    "wof:name":"Marie-louise Teichmann",
    "wof:placetype":"venue"
},
  "geometry": {"coordinates":[4.3862547874,50.8191452026],"type":"Point"}
}