{
  "type": "Feature",
  "properties": {
    "addr:full":"Aarlenstraat 55 Bruxelles (etterbeek) Bruxelles-Capitale 1040",
    "addr:housenumber":"55",
    "addr:postcode":"1040",
    "addr:street":"Aarlenstraat",
    "iso:country":"BE",
    "sg:address":"Aarlenstraat 55",
    "sg:city":"Bruxelles (etterbeek)",
    "sg:classifiers":[
        {
            "category":"Organizations",
            "subcategory":"Professional Association",
            "type":"Services"
        }
    ],
    "sg:phone":"+32 2 234 10 11",
    "sg:postcode":"1040",
    "sg:province":"Bruxelles-Capitale",
    "sg:tags":[
        "trade-union",
        "federation"
    ],
    "wof:name":"Cembureau-association Europ\u00e9enne Du Ciment-the European Cement Association",
    "wof:placetype":"venue"
},
  "geometry": {"coordinates":[4.3738031387,50.8420677185],"type":"Point"}
}