{
  "type": "Feature",
  "properties": {
    "iso:country":"BE",
    "sg:address":"Sint-amandusstraat 3",
    "sg:city":"Wortegem-petegem",
    "sg:orig_category":"Producteurs de fruits",
    "sg:phone":"+32 9 383 85 75",
    "sg:postcode":"9790",
    "sg:province":"Oost-Vlaanderen",
    "wof:name":"Bart Moerman",
    "wof:placetype":"venue"
},
  "geometry": {"coordinates":[3.557049036,50.8671379089],"type":"Point"}
}