{
  "type": "Feature",
  "properties": {
    "addr:full":"Lange Nieuwstraat 30 Beveren Oost-Vlaanderen 9130",
    "addr:housenumber":"30",
    "addr:postcode":"9130",
    "addr:street":"Lange Nieuwstraat",
    "iso:country":"BE",
    "sg:address":"Lange Nieuwstraat 30",
    "sg:city":"Beveren",
    "sg:orig_category":"Sportclubs",
    "sg:phone":"+32 3 773 34 14",
    "sg:postcode":"9130",
    "sg:province":"Oost-Vlaanderen",
    "wof:name":"De Gouden Pluim",
    "wof:placetype":"venue"
},
  "geometry": {"coordinates":[4.1778030396,51.2796173096],"type":"Point"}
}