{
  "type": "Feature",
  "properties": {
    "iso:country":"BE",
    "sg:address":"Rue De Robiano 70",
    "sg:city":"Brussel/bruxelles",
    "sg:orig_category":"D\u00e9molition d\u00b4immeubles and terrassements",
    "sg:phone":"+32 2 267 33 97",
    "sg:postcode":"1030",
    "sg:province":"Bruxelles-Capitale",
    "wof:name":"Tison Fr\u00c8s",
    "wof:placetype":"venue"
},
  "geometry": {"coordinates":[4.3747019768,50.86095047],"type":"Point"}
}