{
  "type": "Feature",
  "properties": {
    "addr:full":"Negenendertigste Linielaan 8a Maldegem Oost-Vlaanderen 9990",
    "addr:housenumber":"8a",
    "addr:postcode":"9990",
    "addr:street":"Negenendertigste Linielaan",
    "iso:country":"BE",
    "sg:address":"Negenendertigste Linielaan 8a",
    "sg:city":"Maldegem",
    "sg:classifiers":[
        {
            "category":"Home & Garden",
            "subcategory":"Furniture",
            "type":"Retail Goods"
        }
    ],
    "sg:phone":"+32 50 71 10 44",
    "sg:postcode":"9990",
    "sg:province":"Oost-Vlaanderen",
    "sg:tags":[
        "-"
    ],
    "wof:name":"Semaburo Bvba",
    "wof:placetype":"venue"
},
  "geometry": {"coordinates":[3.4619629383,51.1861839294],"type":"Point"}
}