{
  "type": "Feature",
  "properties": {
    "iso:country":"BE",
    "sg:address":"Rue Du Bois D'hymi\u00e9e 23",
    "sg:city":"Gerpinnes",
    "sg:classifiers":[
        {
            "category":"Building & Trades",
            "subcategory":"Electrical",
            "type":"Services"
        }
    ],
    "sg:phone":"+32 71 50 12 71",
    "sg:postcode":"6280",
    "sg:province":"Hainaut",
    "sg:tags":[
        "electric",
        "-",
        "housewiring",
        "contractor"
    ],
    "wof:name":"D.e.t.s.",
    "wof:placetype":"venue"
},
  "geometry": {"coordinates":[4.5743741989,50.3304214478],"type":"Point"}
}