{
  "type": "Feature",
  "properties": {
    "iso:country":"BE",
    "sg:address":"Haachtsesteenweg 374",
    "sg:city":"Schaarbeek/schaerbeek",
    "sg:orig_category":"Industri\u00eble wasserijen and droogkuis",
    "sg:phone":"+32 2 245 63 38",
    "sg:postcode":"1030",
    "sg:province":"Bruxelles-Capitale",
    "wof:name":"Marine Wash",
    "wof:placetype":"venue"
},
  "geometry": {"coordinates":[4.3754267693,50.8662185669],"type":"Point"}
}