{
  "type": "Feature",
  "properties": {
    "addr:full":"Rue De La Digue 16 Charleroi Hainaut 6000",
    "addr:housenumber":"16",
    "addr:postcode":"6000",
    "addr:street":"Rue De La Digue;Hainaut",
    "iso:country":"BE",
    "sg:address":"Rue De La Digue 16",
    "sg:city":"Charleroi",
    "sg:classifiers":[
        {
            "category":"Building & Trades",
            "subcategory":"Landscaping Services",
            "type":"Services"
        }
    ],
    "sg:phone":"+32 71 32 89 45",
    "sg:postcode":"6000",
    "sg:province":"Hainaut",
    "sg:tags":[
        "architect",
        "landscape"
    ],
    "wof:name":"Empreinte-paysage",
    "wof:placetype":"venue"
},
  "geometry": {"coordinates":[4.4382500648,50.4104537964],"type":"Point"}
}