{
  "type": "Feature",
  "properties": {
    "addr:full":"Route De Liege 1 Somme-leuze Namur 5377",
    "addr:housenumber":"1",
    "addr:postcode":"5377",
    "addr:street":"Route De Liege",
    "iso:country":"BE",
    "sg:address":"Route De Liege 1",
    "sg:city":"Somme-leuze",
    "sg:classifiers":[
        {
            "category":"Restaurant",
            "type":"Food & Drink"
        }
    ],
    "sg:phone":"+32 86 32 30 15",
    "sg:postcode":"5377",
    "sg:province":"Namur",
    "wof:name":"Le Charolais",
    "wof:placetype":"venue"
},
  "geometry": {"coordinates":[5.3714461327,50.3451499939],"type":"Point"}
}