{
  "type": "Feature",
  "properties": {
    "iso:country":"BE",
    "sg:address":"Rue Bois D\u00b4esneux 79",
    "sg:city":"Namur",
    "sg:orig_category":"Woningbouw",
    "sg:phone":"+32 81 21 19 02",
    "sg:postcode":"5021",
    "sg:province":"Namur",
    "wof:name":"Trans\u00b4actif-spaac",
    "wof:placetype":"venue"
},
  "geometry": {"coordinates":[4.9379210472,50.5012893677],"type":"Point"}
}