{
  "type": "Feature",
  "properties": {
    "addr:full":"Avenue Louise 335 Brussels Bruxelles-Capitale 1050",
    "addr:housenumber":"335",
    "addr:postcode":"1050",
    "addr:street":"Avenue Louise",
    "iso:country":"BE",
    "sg:address":"Avenue Louise 335",
    "sg:city":"Brussels",
    "sg:orig_category":"Reisbureaus",
    "sg:phone":"+32 2 627 49 90",
    "sg:postcode":"1050",
    "sg:province":"Bruxelles-Capitale",
    "wof:name":"Havanatour Benelux / But",
    "wof:placetype":"venue"
},
  "geometry": {"coordinates":[4.3687877655,50.8221511841],"type":"Point"}
}