{
  "type": "Feature",
  "properties": {
    "addr:full":"Steentjemolenstraat 33 Ieper (elverdinge) West-Vlaanderen 8906",
    "addr:housenumber":"33",
    "addr:postcode":"8906",
    "addr:street":"Steentjemolenstraat",
    "iso:country":"BE",
    "sg:address":"Steentjemolenstraat 33",
    "sg:city":"Ieper (elverdinge)",
    "sg:classifiers":[
        {
            "category":"Travel",
            "subcategory":"Resort",
            "type":"Entertainment"
        }
    ],
    "sg:phone":"+32 57 42 23 15",
    "sg:postcode":"8906",
    "sg:province":"West-Vlaanderen",
    "sg:tags":[
        "rental",
        "accomodation",
        "holiday",
        "-"
    ],
    "wof:name":"De Abeeleboom",
    "wof:placetype":"venue"
},
  "geometry": {"coordinates":[2.7898199558,50.8838577271],"type":"Point"}
}