{
  "type": "Feature",
  "properties": {
    "iso:country":"BE",
    "sg:address":"Bochtlaan 27b1",
    "sg:city":"Genk",
    "sg:orig_category":"Tijdelijke werkgelegenheid and uitzendkantoren",
    "sg:phone":"+32 89 32 25 00",
    "sg:postcode":"3600",
    "sg:province":"Limburg",
    "wof:name":"T Interim",
    "wof:placetype":"venue"
},
  "geometry": {"coordinates":[5.5024819374,50.9683952332],"type":"Point"}
}