{
  "type": "Feature",
  "properties": {
    "iso:country":"BE",
    "sg:address":"Rue D'havr\u00c9 42",
    "sg:city":"Mons",
    "sg:orig_category":"Dameskledingzaken Lingerie and ondergoed",
    "sg:phone":"+32 65 34 77 83",
    "sg:postcode":"7000",
    "sg:province":"Hainaut",
    "wof:name":"Maison Camelia",
    "wof:placetype":"venue"
},
  "geometry": {"coordinates":[3.9542770386,50.4536056519],"type":"Point"}
}