{
  "type": "Feature",
  "properties": {
    "addr:full":"Rue Des Ecoles 1 Lincent Li\u00e8ge 4287",
    "addr:housenumber":"1",
    "addr:postcode":"4287",
    "addr:street":"Rue Des Ecoles",
    "iso:country":"BE",
    "sg:address":"Rue Des Ecoles 1",
    "sg:city":"Lincent",
    "sg:classifiers":[
        {
            "category":"Government",
            "subcategory":"Police Station",
            "type":"Public Place"
        }
    ],
    "sg:phone":"+32 19 63 47 47",
    "sg:postcode":"4287",
    "sg:province":"Li\u00e8ge",
    "sg:tags":[
        "gendarmerie"
    ],
    "wof:name":"Police F\u00c9d\u00c9rale",
    "wof:placetype":"venue"
},
  "geometry": {"coordinates":[5.0332341194,50.714641571],"type":"Point"}
}