{
  "type": "Feature",
  "properties": {
    "addr:full":"Koerweg 90a Genk Limburg 3600",
    "addr:housenumber":"90a",
    "addr:postcode":"3600",
    "addr:street":"Koerweg",
    "iso:country":"BE",
    "sg:address":"Koerweg 90a",
    "sg:city":"Genk",
    "sg:classifiers":[
        {
            "category":"Tea Room",
            "subcategory":"None",
            "type":"Food & Drink"
        }
    ],
    "sg:phone":"+32 89 24 34 36",
    "sg:postcode":"3600",
    "sg:province":"Limburg",
    "wof:name":"Mrs Rose",
    "wof:placetype":"venue"
},
  "geometry": {"coordinates":[5.4944047928,50.9914360046],"type":"Point"}
}