{
  "type": "Feature",
  "properties": {
    "addr:full":"Avenue Victor Gilsoul 53 Bruxelles (woluwe-saint-lambert) Bruxelles-Capitale 1200",
    "addr:housenumber":"53",
    "addr:postcode":"1200",
    "addr:street":"Avenue Victor Gilsoul",
    "iso:country":"BE",
    "sg:address":"Avenue Victor Gilsoul 53",
    "sg:city":"Bruxelles (woluwe-saint-lambert)",
    "sg:classifiers":[
        {
            "category":"Real Estate",
            "subcategory":"Real Estate Services",
            "type":"Services"
        }
    ],
    "sg:phone":"+32 2 772 00 97",
    "sg:postcode":"1200",
    "sg:province":"Bruxelles-Capitale",
    "wof:name":"Faregan Nv",
    "wof:placetype":"venue"
},
  "geometry": {"coordinates":[4.4171581268,50.8412284851],"type":"Point"}
}