{
  "type": "Feature",
  "properties": {
    "addr:full":"Avenue Van Overbeke 29 Box 12 Bruxelles (ganshoren) Bruxelles-Capitale 1083",
    "addr:housenumber":"29 box 12",
    "addr:postcode":"1083",
    "addr:street":"Avenue Van Overbeke",
    "iso:country":"BE",
    "sg:address":"Avenue Van Overbeke 29 Box 12",
    "sg:city":"Bruxelles (ganshoren)",
    "sg:classifiers":[
        {
            "category":"Cafe",
            "type":"Food & Drink"
        }
    ],
    "sg:phone":"+32 2 425 67 57",
    "sg:postcode":"1083",
    "sg:province":"Bruxelles-Capitale",
    "sg:tags":[
        "snack-bars"
    ],
    "wof:name":"Comme Chez Vous",
    "wof:placetype":"venue"
},
  "geometry": {"coordinates":[4.3154778481,50.8691749573],"type":"Point"}
}