{
  "type": "Feature",
  "properties": {
    "iso:country":"BE",
    "sg:address":"Louis Godeaustraat 7",
    "sg:city":"Halle",
    "sg:orig_category":"Installation \u00e9lectrique r\u00e9sidentielle",
    "sg:phone":"+32 2 360 33 89",
    "sg:postcode":"1501",
    "sg:province":"Vlaams-Brabant",
    "wof:name":"Raoul Nuyttens",
    "wof:placetype":"venue"
},
  "geometry": {"coordinates":[4.2591710091,50.7425346375],"type":"Point"}
}