{
  "type": "Feature",
  "properties": {
    "iso:country":"BE",
    "sg:address":"Rue Saint-urbain 18",
    "sg:city":"Paliseul",
    "sg:orig_category":"Eleveurs de bovins",
    "sg:phone":"+32 61 53 32 62",
    "sg:postcode":"6851",
    "sg:province":"Luxembourg",
    "wof:name":"Jean Toussaint",
    "wof:placetype":"venue"
},
  "geometry": {"coordinates":[5.1210517883,49.8729515076],"type":"Point"}
}