{
  "type": "Feature",
  "properties": {
    "addr:full":"Grand'route 376 Braine-l'alleud Brabant Wallon 1428",
    "addr:housenumber":"376",
    "addr:postcode":"1428",
    "addr:street":"Grand'Route",
    "iso:country":"BE",
    "sg:address":"Grand'route 376",
    "sg:city":"Braine-l'alleud",
    "sg:classifiers":[
        {
            "category":"Cafe",
            "type":"Food & Drink"
        }
    ],
    "sg:phone":"+32 2 387 09 37",
    "sg:postcode":"1428",
    "sg:province":"Brabant Wallon",
    "sg:tags":[
        "caf\u00e9s"
    ],
    "wof:name":"Linda Cobut",
    "wof:placetype":"venue"
},
  "geometry": {"coordinates":[-0.6584389806,47.4034957886],"type":"Point"}
}