{
  "type": "Feature",
  "properties": {
    "iso:country":"BE",
    "sg:address":"Avenue Reine Astrid 99ba",
    "sg:city":"Limbourg",
    "sg:orig_category":"Aardappelproducten Gh Groenten and fruit Gh",
    "sg:phone":"+32 87 76 32 71",
    "sg:postcode":"4831",
    "sg:province":"Li\u00e8ge",
    "wof:name":"Geron",
    "wof:placetype":"venue"
},
  "geometry": {"coordinates":[5.9324541092,50.6154823303],"type":"Point"}
}