{
  "type": "Feature",
  "properties": {
    "iso:country":"BE",
    "sg:address":"Aalterbaan 159",
    "sg:city":"Maldegem",
    "sg:orig_category":"Newspapers, magazines, periodicals - Distribution",
    "sg:phone":"+32 50 62 06 72",
    "sg:postcode":"9990",
    "sg:province":"Oost-Vlaanderen",
    "wof:name":"Nieuwsbron (de)",
    "wof:placetype":"venue"
},
  "geometry": {"coordinates":[3.4524419308,51.1992988586],"type":"Point"}
}