{
  "type": "Feature",
  "properties": {
    "addr:full":"Rue Du Coll\u00c8ge 68 Verviers Li\u00e8ge 4800",
    "addr:housenumber":"68",
    "addr:postcode":"4800",
    "addr:street":"Rue Du Colle\u0300Ge",
    "iso:country":"BE",
    "sg:address":"Rue Du Coll\u00c8ge 68",
    "sg:city":"Verviers",
    "sg:orig_category":"Imprimeries and copyshops. Cr\u00e9dits divers",
    "sg:phone":"+32 87 35 35 82",
    "sg:postcode":"4800",
    "sg:province":"Li\u00e8ge",
    "wof:name":"Verviers-copy",
    "wof:placetype":"venue"
},
  "geometry": {"coordinates":[5.8638381958,50.5944404602],"type":"Point"}
}