{
  "type": "Feature",
  "properties": {
    "addr:full":"Goethalslaan 2 Kortrijk (heule) West-Vlaanderen 8501",
    "addr:housenumber":"2",
    "addr:postcode":"8501",
    "addr:street":"Goethalslaan",
    "iso:country":"BE",
    "sg:address":"Goethalslaan 2",
    "sg:city":"Kortrijk (heule)",
    "sg:classifiers":[
        {
            "category":"Real Estate",
            "subcategory":"Architect",
            "type":"Services"
        }
    ],
    "sg:phone":"+32 56 35 54 02",
    "sg:postcode":"8501",
    "sg:province":"West-Vlaanderen",
    "wof:name":"Callewaert J",
    "wof:placetype":"venue"
},
  "geometry": {"coordinates":[3.228924036,50.8434295654],"type":"Point"}
}