{
  "type": "Feature",
  "properties": {
    "addr:full":"Rue Des Templiers 19bb Chimay Hainaut 6464",
    "addr:housenumber":"19bb",
    "addr:postcode":"6464",
    "addr:street":"Rue Des Templiers",
    "iso:country":"BE",
    "sg:address":"Rue Des Templiers 19bb",
    "sg:city":"Chimay",
    "sg:orig_category":"Pain, p\u00e2tisseries and confiseries",
    "sg:phone":"+32 60 21 47 21",
    "sg:postcode":"6464",
    "sg:province":"Hainaut",
    "wof:name":"Au Petit Prince",
    "wof:placetype":"venue"
},
  "geometry": {"coordinates":[4.3258328438,50.0274620056],"type":"Point"}
}