{
  "type": "Feature",
  "properties": {
    "addr:full":"Rue Emile Delva 38 Bruxelles Bruxelles-Capitale 1020",
    "addr:housenumber":"38",
    "addr:postcode":"1020",
    "addr:street":"Rue Emile Delva",
    "iso:country":"BE",
    "sg:address":"Rue Emile Delva 38",
    "sg:city":"Bruxelles",
    "sg:classifiers":[
        {
            "category":"Real Estate",
            "subcategory":"Architect",
            "type":"Services"
        }
    ],
    "sg:phone":"+32 2 426 87 77",
    "sg:postcode":"1020",
    "sg:province":"Bruxelles-Capitale",
    "wof:name":"Giacomini M",
    "wof:placetype":"venue"
},
  "geometry": {"coordinates":[4.3419418335,50.8775901794],"type":"Point"}
}