{
  "type": "Feature",
  "properties": {
    "addr:full":"Sentier Du Bois Moue 2 Rixensart Brabant Wallon 1330",
    "addr:housenumber":"2",
    "addr:postcode":"1330",
    "addr:street":"Sentier Du Bois Moue;Wallon",
    "iso:country":"BE",
    "sg:address":"Sentier Du Bois Moue 2",
    "sg:city":"Rixensart",
    "sg:orig_category":"D\u00e9corateurs d'int\u00e9rieur. Eclairage et \u00e9quipements du foyer",
    "sg:phone":"+32 2 653 23 82",
    "sg:postcode":"1330",
    "sg:province":"Brabant Wallon",
    "wof:name":"B\u00c9n\u00c9dicte Henry",
    "wof:placetype":"venue"
},
  "geometry": {"coordinates":[4.513944149,50.7016410828],"type":"Point"}
}