{
  "type": "Feature",
  "properties": {
    "iso:country":"BE",
    "sg:address":"Sint-guibertusplein 16",
    "sg:city":"Heist-op-den-berg",
    "sg:orig_category":"Banken and kredietinstellingen",
    "sg:phone":"+32 15 25 06 90",
    "sg:postcode":"2222",
    "sg:province":"Antwerpen",
    "wof:name":"Kbc",
    "wof:placetype":"venue"
},
  "geometry": {"coordinates":[4.7292189598,51.1026153564],"type":"Point"}
}