{
  "type": "Feature",
  "properties": {
    "iso:country":"BE",
    "sg:address":"Rue Du Bout 19",
    "sg:city":"Fosses-la-ville",
    "sg:orig_category":"Quincailleries. Constructions r\u00e9sidentielles sp\u00e9cifiques. Travaux de pl\u00e2trage. Travaux de finition a",
    "sg:phone":"+32 71 71 16 55",
    "sg:postcode":"5070",
    "sg:province":"Namur",
    "wof:name":"Wiame",
    "wof:placetype":"venue"
},
  "geometry": {"coordinates":[4.6622152328,50.3946342468],"type":"Point"}
}