{
  "type": "Feature",
  "properties": {
    "addr:full":"Hendrik Consciencestraat 27 Eeklo Oost-Vlaanderen 9900",
    "addr:housenumber":"27",
    "addr:postcode":"9900",
    "addr:street":"Hendrik Consciencestraat",
    "iso:country":"BE",
    "sg:address":"Hendrik Consciencestraat 27",
    "sg:city":"Eeklo",
    "sg:classifiers":[
        {
            "category":"Farming",
            "subcategory":"Fish & Marine Products",
            "type":"Manufacturing & Wholesale Goods"
        }
    ],
    "sg:phone":"+32 9 330 92 45",
    "sg:postcode":"9900",
    "sg:province":"Oost-Vlaanderen",
    "sg:tags":[
        "retail",
        "-",
        "shellfish"
    ],
    "wof:name":"Puttaert M",
    "wof:placetype":"venue"
},
  "geometry": {"coordinates":[3.572742939,51.1767883301],"type":"Point"}
}