{
  "type": "Feature",
  "properties": {
    "addr:full":"Stijfselstraat 3 Antwerpen Antwerpen 2000",
    "addr:housenumber":"3",
    "addr:postcode":"2000",
    "addr:street":"Stijfselstraat",
    "iso:country":"BE",
    "sg:address":"Stijfselstraat 3",
    "sg:city":"Antwerpen",
    "sg:classifiers":[
        {
            "category":"Banks & Credit Unions",
            "subcategory":"Investment Brokerage",
            "type":"Services"
        }
    ],
    "sg:phone":"+32 3 213 42 54",
    "sg:postcode":"2000",
    "sg:province":"Antwerpen",
    "sg:tags":[
        "printing",
        "-"
    ],
    "wof:name":"Drukkerij De Vroey Bvba",
    "wof:placetype":"venue"
},
  "geometry": {"coordinates":[4.4106459618,51.2258453369],"type":"Point"}
}