{
  "type": "Feature",
  "properties": {
    "iso:country":"BE",
    "sg:address":"Schoutstraat 5",
    "sg:city":"Gent (oostakker)",
    "sg:classifiers":[
        {
            "category":"Shopping",
            "subcategory":"Stationery & Office Supplies",
            "type":"Retail Goods"
        }
    ],
    "sg:phone":"+32 9 259 08 21",
    "sg:postcode":"9041",
    "sg:province":"Oost-Vlaanderen",
    "sg:tags":[
        "label"
    ],
    "wof:name":"4 Pm Marketing",
    "wof:placetype":"venue"
},
  "geometry": {"coordinates":[3.7797350883,51.0979118347],"type":"Point"}
}