{
  "type": "Feature",
  "properties": {
    "iso:country":"BE",
    "sg:address":"Essenhoutstraat 69",
    "sg:city":"Kapellen",
    "sg:orig_category":"Brandweer and civiele bescherming",
    "sg:phone":"+32 3 605 13 95",
    "sg:postcode":"2950",
    "sg:province":"Antwerpen",
    "wof:name":"Brandweerkazerne",
    "wof:placetype":"venue"
},
  "geometry": {"coordinates":[4.4246850014,51.3121566772],"type":"Point"}
}