{
  "type": "Feature",
  "properties": {
    "addr:full":"Visserij 203 Gent Oost-Vlaanderen 9000",
    "addr:housenumber":"203",
    "addr:postcode":"9000",
    "addr:street":"Visserij;Oost-Vlaanderen",
    "iso:country":"BE",
    "sg:address":"Visserij 203",
    "sg:city":"Gent",
    "sg:classifiers":[
        {
            "category":"Communications",
            "subcategory":"Radio Station",
            "type":"Services"
        }
    ],
    "sg:phone":"+32 9 265 97 30",
    "sg:postcode":"9000",
    "sg:province":"Oost-Vlaanderen",
    "sg:tags":[
        "diffusion",
        "production",
        "de",
        "programme"
    ],
    "wof:name":"Radio Go",
    "wof:placetype":"venue"
},
  "geometry": {"coordinates":[3.7399270535,51.0426902771],"type":"Point"}
}