{
  "type": "Feature",
  "properties": {
    "iso:country":"BE",
    "sg:address":"Rothstraat 170",
    "sg:city":"Diest",
    "sg:orig_category":"Paramedische behandelingen",
    "sg:phone":"+32 13 33 71 10",
    "sg:postcode":"3290",
    "sg:province":"Vlaams-Brabant",
    "wof:name":"V. Francis",
    "wof:placetype":"venue"
},
  "geometry": {"coordinates":[5.1370630264,51.0335121155],"type":"Point"}
}