{
  "type": "Feature",
  "properties": {
    "addr:full":"Rue Du Progr\u00c8s 48 Li\u00c8ge Li\u00e8ge 4032",
    "addr:housenumber":"48",
    "addr:postcode":"4032",
    "addr:street":"Rue Du Progre\u0300S",
    "iso:country":"BE",
    "sg:address":"Rue Du Progr\u00c8s 48",
    "sg:city":"Li\u00c8ge",
    "sg:orig_category":"Studios photographiques",
    "sg:phone":"+32 45720072",
    "sg:postcode":"4032",
    "sg:province":"Li\u00e8ge",
    "wof:name":"Studio Doppagne",
    "wof:placetype":"venue"
},
  "geometry": {"coordinates":[5.619579792,50.6117401123],"type":"Point"}
}