{
  "type": "Feature",
  "properties": {
    "iso:country":"BE",
    "sg:address":"Place Des Maieurs 2",
    "sg:city":"Sint-pieters-woluwe/woluwe-saint-pierre",
    "sg:orig_category":"Catering and organisation de f\u00eates. Alimentation sp\u00e9cialis\u00e9e. Restaurants",
    "sg:phone":"+32 2 763 32 61",
    "sg:postcode":"1150",
    "sg:province":"Bruxelles-Capitale",
    "wof:name":"Au Peche Gourmand",
    "wof:placetype":"venue"
},
  "geometry": {"coordinates":[4.4305300713,50.837020874],"type":"Point"}
}