{
  "type": "Feature",
  "properties": {
    "iso:country":"BE",
    "sg:address":"Rue Fra\u00ceche Chemin 3",
    "sg:city":"Pont-a-celles",
    "sg:classifiers":[
        {
            "category":"Personal",
            "subcategory":"Beauty Salon",
            "type":"Services"
        }
    ],
    "sg:phone":"+32 67 87 77 86",
    "sg:postcode":"6230",
    "sg:province":"Hainaut",
    "sg:tags":[
        "de",
        "coiffure"
    ],
    "wof:name":"Espace Coiffure(l')",
    "wof:placetype":"venue"
},
  "geometry": {"coordinates":[4.3234009743,50.5432357788],"type":"Point"}
}