{
  "type": "Feature",
  "properties": {
    "iso:country":"BE",
    "sg:address":"Rue Petit Jonckeu 5",
    "sg:city":"Theux (polleur)",
    "sg:classifiers":[
        {
            "category":"Health Services",
            "subcategory":"Health Practitioner",
            "type":"Services"
        }
    ],
    "sg:phone":"+32 87 22 13 78",
    "sg:postcode":"4910",
    "sg:province":"Li\u00e8ge",
    "sg:tags":[
        "therapist",
        "speech"
    ],
    "wof:name":"Goffard-fettweis F",
    "wof:placetype":"venue"
},
  "geometry": {"coordinates":[5.8758502007,50.5481452942],"type":"Point"}
}