{
  "type": "Feature",
  "properties": {
    "iso:country":"BE",
    "sg:address":"Radstraat 49",
    "sg:city":"Brussel/bruxelles",
    "sg:orig_category":"Herstellingen and onderhoud van auto's",
    "sg:phone":"+32 2 511 36 84",
    "sg:postcode":"1000",
    "sg:province":"Bruxelles-Capitale",
    "wof:name":"Dur",
    "wof:placetype":"venue"
},
  "geometry": {"coordinates":[4.3469390869,50.8413238525],"type":"Point"}
}