{
  "type": "Feature",
  "properties": {
    "addr:full":"Kortrijksepoortstraat 220 Gent Oost-Vlaanderen 9000",
    "addr:housenumber":"220",
    "addr:postcode":"9000",
    "addr:street":"Kortrijksepoortstraat;Oost-Vlaanderen",
    "iso:country":"BE",
    "sg:address":"Kortrijksepoortstraat 220",
    "sg:city":"Gent",
    "sg:orig_category":"Tweedehandsgoederen",
    "sg:phone":"+32 9 233 00 27",
    "sg:postcode":"9000",
    "sg:province":"Oost-Vlaanderen",
    "wof:name":"Huis Florence-maud",
    "wof:placetype":"venue"
},
  "geometry": {"coordinates":[3.7217741013,51.0444984436],"type":"Point"}
}