{
  "type": "Feature",
  "properties": {
    "iso:country":"BE",
    "sg:address":"Charles Ramaekersstraat 25",
    "sg:city":"Brussel/bruxelles",
    "sg:orig_category":"Woningbouw",
    "sg:phone":"+32 2 478 02 74",
    "sg:postcode":"1020",
    "sg:province":"Bruxelles-Capitale",
    "wof:name":"Edouard Eyckmans",
    "wof:placetype":"venue"
},
  "geometry": {"coordinates":[4.3447108269,50.8828315735],"type":"Point"}
}