{
  "type": "Feature",
  "properties": {
    "addr:full":"President Kennedypark 13b Kortrijk West-Vlaanderen 8500",
    "addr:housenumber":"13b",
    "addr:postcode":"8500",
    "addr:street":"President Kennedypark",
    "iso:country":"BE",
    "sg:address":"President Kennedypark 13b",
    "sg:city":"Kortrijk",
    "sg:classifiers":[
        {
            "category":"Professional",
            "subcategory":"Accounting & Tax Preparation",
            "type":"Services"
        }
    ],
    "sg:phone":"+32 56 25 75 63",
    "sg:postcode":"8500",
    "sg:province":"West-Vlaanderen",
    "sg:tags":[
        "accountant"
    ],
    "wof:name":"De Smidt J-p",
    "wof:placetype":"venue"
},
  "geometry": {"coordinates":[3.2746798992,50.8029289246],"type":"Point"}
}