{
  "type": "Feature",
  "properties": {
    "addr:full":"Sint-mildredaplein 0 Alveringem West-Vlaanderen 8691",
    "addr:housenumber":"0",
    "addr:postcode":"8691",
    "addr:street":"Sint-Mildredaplein",
    "iso:country":"BE",
    "sg:address":"Sint-mildredaplein 0",
    "sg:city":"Alveringem",
    "sg:orig_category":"Mus\u00e9es and patrimoine culturel",
    "sg:phone":"+32 58 29 80 90",
    "sg:postcode":"8691",
    "sg:province":"West-Vlaanderen",
    "wof:name":"Bachten De Kupe",
    "wof:placetype":"venue"
},
  "geometry": {"coordinates":[2.6546199322,50.9942588806],"type":"Point"}
}