{
  "type": "Feature",
  "properties": {
    "iso:country":"BE",
    "sg:address":"Rue Des Vieux Sarts 6",
    "sg:city":"Namur",
    "sg:orig_category":"Groententeelt",
    "sg:phone":"+32 81 40 02 13",
    "sg:postcode":"5101",
    "sg:province":"Namur",
    "wof:name":"Benoit Hastir",
    "wof:placetype":"venue"
},
  "geometry": {"coordinates":[4.904815197,50.4481887817],"type":"Point"}
}