{
  "type": "Feature",
  "properties": {
    "iso:country":"BE",
    "sg:address":"Leuvenselaan 221",
    "sg:city":"Tienen",
    "sg:orig_category":"Epiceries",
    "sg:phone":"+32 16 81 19 80",
    "sg:postcode":"3300",
    "sg:province":"Vlaams-Brabant",
    "wof:name":"Omer Jonckers",
    "wof:placetype":"venue"
},
  "geometry": {"coordinates":[4.9214100838,50.8125457764],"type":"Point"}
}