{
  "type": "Feature",
  "properties": {
    "addr:full":"Nijven 11 Sint-amands Antwerpen 2890",
    "addr:housenumber":"11",
    "addr:postcode":"2890",
    "addr:street":"Nijven",
    "iso:country":"BE",
    "sg:address":"Nijven 11",
    "sg:city":"Sint-amands",
    "sg:orig_category":"Instruments de musique",
    "sg:phone":"+32 3 889 99 21",
    "sg:postcode":"2890",
    "sg:province":"Antwerpen",
    "wof:name":"Patrick Van Gucht",
    "wof:placetype":"venue"
},
  "geometry": {"coordinates":[4.245429039,51.0579719543],"type":"Point"}
}