{
  "type": "Feature",
  "properties": {
    "iso:country":"BE",
    "sg:address":"Rue De La Fourchin\u00c9e 1",
    "sg:city":"Momignies",
    "sg:classifiers":[
        {
            "category":"Cafe",
            "type":"Food & Drink"
        }
    ],
    "sg:phone":"+32 60 51 15 21",
    "sg:postcode":"6596",
    "sg:province":"Hainaut",
    "sg:tags":[
        "caf\u00e9s"
    ],
    "wof:name":"Caf\u00c9 Tourond",
    "wof:placetype":"venue"
},
  "geometry": {"coordinates":[4.2614798546,50.0037612915],"type":"Point"}
}