{
  "type": "Feature",
  "properties": {
    "addr:full":"Scheepsdaleln 47 Brugge West-Vlaanderen 8000",
    "addr:housenumber":"47",
    "addr:postcode":"8000",
    "addr:street":"Scheepsdaleln",
    "iso:country":"BE",
    "sg:address":"Scheepsdaleln 47",
    "sg:city":"Brugge",
    "sg:classifiers":[
        {
            "category":"Autos & Motor Vehicles",
            "subcategory":"Automobile Sales",
            "type":"Retail Goods"
        }
    ],
    "sg:phone":"+32 50 32 02 17",
    "sg:postcode":"8000",
    "sg:province":"West-Vlaanderen",
    "sg:tags":[
        "equipment",
        "motor-cars",
        "transport"
    ],
    "wof:name":"Garage Descheemaeker Nv",
    "wof:placetype":"venue"
},
  "geometry": {"coordinates":[3.2109019756,51.2180747986],"type":"Point"}
}