{
  "type": "Feature",
  "properties": {
    "addr:full":"Stationsstraat 15 Houthalen-helchteren Limburg 3530",
    "addr:housenumber":"15",
    "addr:postcode":"3530",
    "addr:street":"Stationsstraat",
    "iso:country":"BE",
    "sg:address":"Stationsstraat 15",
    "sg:city":"Houthalen-helchteren",
    "sg:orig_category":"V\u00e9hicules automobiles",
    "sg:phone":"+32 11 52 45 32",
    "sg:postcode":"3530",
    "sg:province":"Limburg",
    "wof:name":"A.b.d.",
    "wof:placetype":"venue"
},
  "geometry": {"coordinates":[5.3692750931,51.0304718018],"type":"Point"}
}