{
  "type": "Feature",
  "properties": {
    "iso:country":"BE",
    "sg:address":"Hoogstraat 85",
    "sg:city":"Haaltert",
    "sg:classifiers":[
        {
            "category":"Sports & Exercise",
            "subcategory":"Gym",
            "type":"Entertainment"
        }
    ],
    "sg:phone":"+32 53 83 38 25",
    "sg:postcode":"9450",
    "sg:province":"Oost-Vlaanderen",
    "sg:tags":[
        "fitness"
    ],
    "wof:name":"Mfc De Keij",
    "wof:placetype":"venue"
},
  "geometry": {"coordinates":[4.0031971931,50.8977546692],"type":"Point"}
}