{
  "type": "Feature",
  "properties": {
    "iso:country":"BE",
    "sg:address":"Bleuksken 18",
    "sg:city":"Houthalen-helchteren",
    "sg:orig_category":"Rev\u00eatements pour sols and murs",
    "sg:phone":"+32 11 52 61 38",
    "sg:postcode":"3530",
    "sg:province":"Limburg",
    "wof:name":"Cappelletti",
    "wof:placetype":"venue"
},
  "geometry": {"coordinates":[5.3835229874,51.0300254822],"type":"Point"}
}