{
  "type": "Feature",
  "properties": {
    "addr:full":"Markt 33 Sint-katelijne-waver Antwerpen 2860",
    "addr:housenumber":"33",
    "addr:postcode":"2860",
    "addr:street":"Markt",
    "iso:country":"BE",
    "sg:address":"Markt 33",
    "sg:city":"Sint-katelijne-waver",
    "sg:orig_category":"Effectenmakelaars and vermogensbeheer Verzekeringsmakelaars and experts",
    "sg:phone":"+32 15 31 03 50",
    "sg:postcode":"2860",
    "sg:province":"Antwerpen",
    "wof:name":"Zakenkantoor Cools",
    "wof:placetype":"venue"
},
  "geometry": {"coordinates":[4.5325779915,51.0704040527],"type":"Point"}
}