{
  "type": "Feature",
  "properties": {
    "iso:country":"BE",
    "sg:address":"Rijksweg 354",
    "sg:city":"Maasmechelen",
    "sg:classifiers":[
        {
            "category":"Retail",
            "subcategory":"Veterinary Services",
            "type":"Services"
        }
    ],
    "sg:phone":"+32 89 76 45 83",
    "sg:postcode":"3630",
    "sg:province":"Limburg",
    "sg:tags":[
        "veterinarian"
    ],
    "wof:name":"Vynckier G Bvba",
    "wof:placetype":"venue"
},
  "geometry": {"coordinates":[5.6970071793,50.9685249329],"type":"Point"}
}