{
  "type": "Feature",
  "properties": {
    "addr:full":"Keirlandse Zillen 14 Mol Antwerpen 2400",
    "addr:housenumber":"14",
    "addr:postcode":"2400",
    "addr:street":"Keirlandse Zillen",
    "iso:country":"BE",
    "sg:address":"Keirlandse Zillen 14",
    "sg:city":"Mol",
    "sg:classifiers":[
        {
            "category":"Communications",
            "subcategory":"Radio Station",
            "type":"Services"
        }
    ],
    "sg:phone":"+32 14 31 85 71",
    "sg:postcode":"2400",
    "sg:province":"Antwerpen",
    "sg:tags":[
        "diffusion",
        "production",
        "de",
        "programme"
    ],
    "wof:name":"Radio Mol",
    "wof:placetype":"venue"
},
  "geometry": {"coordinates":[5.1117081642,51.1907539368],"type":"Point"}
}