{
  "type": "Feature",
  "properties": {
    "addr:full":"Dokter Spitaelslaan 218 Halle Vlaams-Brabant 1502",
    "addr:housenumber":"218;1502",
    "addr:street":"Dokter Spitaelslaan",
    "iso:country":"BE",
    "sg:address":"Dokter Spitaelslaan 218",
    "sg:city":"Halle",
    "sg:orig_category":"Enseignement maternel and primaire",
    "sg:phone":"+32 2 356 74 34",
    "sg:postcode":"1502",
    "sg:province":"Vlaams-Brabant",
    "wof:name":"Vrije Basisschool",
    "wof:placetype":"venue"
},
  "geometry": {"coordinates":[4.2419838905,50.708896637],"type":"Point"}
}