{
  "type": "Feature",
  "properties": {
    "addr:full":"Harentstraat 39 Bonheiden (rijmenam) Antwerpen 2820",
    "addr:housenumber":"39",
    "addr:postcode":"2820",
    "addr:street":"Harentstraat",
    "iso:country":"BE",
    "sg:address":"Harentstraat 39",
    "sg:city":"Bonheiden (rijmenam)",
    "sg:classifiers":[
        {
            "category":"Retail",
            "subcategory":"Auto Repair",
            "type":"Services"
        }
    ],
    "sg:phone":"+32 495 24 66 71",
    "sg:postcode":"2820",
    "sg:province":"Antwerpen",
    "sg:tags":[
        "garage"
    ],
    "wof:name":"Van Den Broeck P",
    "wof:placetype":"venue"
},
  "geometry": {"coordinates":[4.576002121,51.020160675],"type":"Point"}
}