{
  "type": "Feature",
  "properties": {
    "iso:country":"BE",
    "sg:address":"Sint-kwintensstraat 15",
    "sg:city":"Linter (wommersom)",
    "sg:classifiers":[
        {
            "category":"Health Services",
            "subcategory":"Dentist",
            "type":"Services"
        }
    ],
    "sg:phone":"+32 14 81 73 58",
    "sg:postcode":"3350",
    "sg:province":"Vlaams-Brabant",
    "wof:name":"Vandenputte Riet",
    "wof:placetype":"venue"
},
  "geometry": {"coordinates":[5.0183329582,50.8129310608],"type":"Point"}
}