{
  "type": "Feature",
  "properties": {
    "addr:full":"Bizory 3 Bastogne Luxembourg 6600",
    "addr:housenumber":"3",
    "addr:postcode":"6600",
    "addr:street":"Bizory",
    "iso:country":"BE",
    "sg:address":"Bizory 3",
    "sg:city":"Bastogne",
    "sg:orig_category":"Eleveurs de bovins",
    "sg:phone":"+32 61 21 12 51",
    "sg:postcode":"6600",
    "sg:province":"Luxembourg",
    "wof:name":"Louis Emile & Jean",
    "wof:placetype":"venue"
},
  "geometry": {"coordinates":[5.7401161194,50.0118751526],"type":"Point"}
}