{
  "type": "Feature",
  "properties": {
    "iso:country":"BE",
    "sg:address":"Rue De L'universit\u00e9 43",
    "sg:city":"Li\u00e8ge 1",
    "sg:classifiers":[
        {
            "category":"Government",
            "subcategory":"Post Office",
            "type":"Public Place"
        }
    ],
    "sg:phone":"+32 4 222 35 14",
    "sg:postcode":"4000",
    "sg:province":"Li\u00e8ge",
    "sg:tags":[
        "poster"
    ],
    "wof:name":"Print Copy",
    "wof:placetype":"venue"
},
  "geometry": {"coordinates":[5.5745329857,50.6413993835],"type":"Point"}
}