{
  "type": "Feature",
  "properties": {
    "addr:full":"Rue De Linthout 150 Bruxelles (etterbeek) Bruxelles-Capitale 1040",
    "addr:housenumber":"150",
    "addr:postcode":"1040",
    "addr:street":"Rue De Linthout",
    "iso:country":"BE",
    "sg:address":"Rue De Linthout 150",
    "sg:city":"Bruxelles (etterbeek)",
    "sg:classifiers":[
        {
            "category":"Health Services",
            "subcategory":"Hospital",
            "type":"Services"
        }
    ],
    "sg:phone":"+32 2 737 80 00",
    "sg:postcode":"1040",
    "sg:province":"Bruxelles-Capitale",
    "wof:name":"St-michielskliniek",
    "wof:placetype":"venue"
},
  "geometry": {"coordinates":[4.4002752304,50.8430862427],"type":"Point"}
}