{
  "type": "Feature",
  "properties": {
    "addr:full":"Plantin En Moretuslei 77 Antwerpen Antwerpen 2018",
    "addr:housenumber":"77",
    "addr:postcode":"2018",
    "addr:street":"Plantin En Moretuslei",
    "iso:country":"BE",
    "sg:address":"Plantin En Moretuslei 77",
    "sg:city":"Antwerpen",
    "sg:classifiers":[
        {
            "category":"Real Estate",
            "subcategory":"Architect",
            "type":"Services"
        }
    ],
    "sg:phone":"+32 496 87 20 86",
    "sg:postcode":"2018",
    "sg:province":"Antwerpen",
    "wof:name":"Loyaerts A",
    "wof:placetype":"venue"
},
  "geometry": {"coordinates":[4.4247531891,51.210773468],"type":"Point"}
}