{
  "type": "Feature",
  "properties": {
    "iso:country":"BE",
    "sg:address":"Laarsebeekdreef 4",
    "sg:city":"Schoten",
    "sg:orig_category":"Bloemen and planten Gh",
    "sg:phone":"+32 3 651 40 36",
    "sg:postcode":"2900",
    "sg:province":"Antwerpen",
    "wof:name":"Huis Akerne Orchids",
    "wof:placetype":"venue"
},
  "geometry": {"coordinates":[4.5059747696,51.2855949402],"type":"Point"}
}