{
  "type": "Feature",
  "properties": {
    "iso:country":"BE",
    "sg:address":"Aux-ch\u00c9ras 5bb",
    "sg:city":"Houffalize",
    "sg:orig_category":"V\u00e9hicules automobiles",
    "sg:phone":"+32 61 28 87 30",
    "sg:postcode":"6661",
    "sg:province":"Luxembourg",
    "wof:name":"D\u00c9pannage De Wallonie",
    "wof:placetype":"venue"
},
  "geometry": {"coordinates":[5.7848820686,50.1485481262],"type":"Point"}
}