{
  "type": "Feature",
  "properties": {
    "iso:country":"BE",
    "sg:address":"Delaeystraat 59",
    "sg:city":"Hooglede",
    "sg:orig_category":"Enseignement maternel and primaire",
    "sg:phone":"+32 51 70 23 95",
    "sg:postcode":"8830",
    "sg:province":"West-Vlaanderen",
    "wof:name":"Vrije Basisschool",
    "wof:placetype":"venue"
},
  "geometry": {"coordinates":[3.0359039307,51.0009155273],"type":"Point"}
}