{
  "type": "Feature",
  "properties": {
    "iso:country":"BE",
    "sg:address":"Alfred Amelotstraat 3",
    "sg:city":"Zingem",
    "sg:classifiers":[
        {
            "category":"Cafe",
            "type":"Food & Drink"
        }
    ],
    "sg:phone":"+32 9 384 42 62",
    "sg:postcode":"9750",
    "sg:province":"Oost-Vlaanderen",
    "sg:tags":[
        "caf\u00e9s"
    ],
    "wof:name":"Rita Van Malderghem",
    "wof:placetype":"venue"
},
  "geometry": {"coordinates":[3.6526229382,50.9019699097],"type":"Point"}
}