{
  "type": "Feature",
  "properties": {
    "iso:country":"BE",
    "sg:address":"Schupstraat 9b42",
    "sg:city":"Antwerpen",
    "sg:orig_category":"Diverse intermediaire producten Gh",
    "sg:phone":"+32 3 232 85 56",
    "sg:postcode":"2018",
    "sg:province":"Antwerpen",
    "wof:name":"Altman & Zn",
    "wof:placetype":"venue"
},
  "geometry": {"coordinates":[4.4183797836,51.2143249512],"type":"Point"}
}