{
  "type": "Feature",
  "properties": {
    "iso:country":"BE",
    "sg:address":"Hoogkouterbaan 36",
    "sg:city":"Haaltert",
    "sg:orig_category":"Woningbouw",
    "sg:phone":"+32 53 83 37 23",
    "sg:postcode":"9450",
    "sg:province":"Oost-Vlaanderen",
    "wof:name":"Willem Brusselman",
    "wof:placetype":"venue"
},
  "geometry": {"coordinates":[3.9845910072,50.9004898071],"type":"Point"}
}