{
  "type": "Feature",
  "properties": {
    "addr:full":"Tarwestraat 4 Diksmuide West-Vlaanderen 8600",
    "addr:housenumber":"4",
    "addr:postcode":"8600",
    "addr:street":"Tarwestraat",
    "iso:country":"BE",
    "sg:address":"Tarwestraat 4",
    "sg:city":"Diksmuide",
    "sg:orig_category":"Pleisterwerk",
    "sg:phone":"+32 51 51 06 69",
    "sg:postcode":"8600",
    "sg:province":"West-Vlaanderen",
    "wof:name":"Ivan Stroobant",
    "wof:placetype":"venue"
},
  "geometry": {"coordinates":[2.8726439476,51.0302734375],"type":"Point"}
}