{
  "type": "Feature",
  "properties": {
    "addr:full":"Rue De Housse 52 Vis\u00e9 (richelle) Li\u00e8ge 4600",
    "addr:housenumber":"52",
    "addr:postcode":"4600",
    "addr:street":"Rue De Housse",
    "iso:country":"BE",
    "sg:address":"Rue De Housse 52",
    "sg:city":"Vis\u00e9 (richelle)",
    "sg:classifiers":[
        {
            "category":"Manufacturing",
            "subcategory":"Metals",
            "type":"Manufacturing & Wholesale Goods"
        }
    ],
    "sg:phone":"+32 4 379 33 13",
    "sg:postcode":"4600",
    "sg:province":"Li\u00e8ge",
    "sg:tags":[
        "turning"
    ],
    "wof:name":"Atelier M\u00e9canique De Richelle",
    "wof:placetype":"venue"
},
  "geometry": {"coordinates":[5.7003960609,50.7123413086],"type":"Point"}
}