{
  "type": "Feature",
  "properties": {
    "iso:country":"BE",
    "sg:address":"Rozendreef 13",
    "sg:city":"Kalmthout",
    "sg:classifiers":[
        {
            "category":"Building & Trades",
            "subcategory":"Pest Control",
            "type":"Services"
        }
    ],
    "sg:phone":"+32 3 666 02 68",
    "sg:postcode":"2920",
    "sg:province":"Antwerpen",
    "sg:tags":[
        "painting",
        "contractor"
    ],
    "wof:name":"Philippo",
    "wof:placetype":"venue"
},
  "geometry": {"coordinates":[4.4567279816,51.3784828186],"type":"Point"}
}