{
  "type": "Feature",
  "properties": {
    "addr:full":"Kerkstraat 364 Blankenberge West-Vlaanderen 8370",
    "addr:housenumber":"364",
    "addr:postcode":"8370",
    "addr:street":"Kerkstraat",
    "iso:country":"BE",
    "sg:address":"Kerkstraat 364",
    "sg:city":"Blankenberge",
    "sg:classifiers":[
        {
            "category":"Retail",
            "subcategory":"Laundry & Dry Cleaning",
            "type":"Services"
        }
    ],
    "sg:phone":"+32 50 42 82 42",
    "sg:postcode":"8370",
    "sg:province":"West-Vlaanderen",
    "sg:tags":[
        "self",
        "-"
    ],
    "wof:name":"Eco-wash",
    "wof:placetype":"venue"
},
  "geometry": {"coordinates":[3.1405611038,51.3059158325],"type":"Point"}
}