{
  "type": "Feature",
  "properties": {
    "addr:full":"Nieuwe Beggaardenstraat 27 Mechelen Antwerpen 2800",
    "addr:housenumber":"27",
    "addr:postcode":"2800",
    "addr:street":"Nieuwe Beggaardenstraat",
    "iso:country":"BE",
    "sg:address":"Nieuwe Beggaardenstraat 27",
    "sg:city":"Mechelen",
    "sg:classifiers":[
        {
            "category":"Professional",
            "subcategory":"Printing & Photocopies",
            "type":"Services"
        }
    ],
    "sg:phone":"+32 15 20 29 14",
    "sg:postcode":"2800",
    "sg:province":"Antwerpen",
    "sg:tags":[
        "offset"
    ],
    "wof:name":"Sint-lucas Co\u00f6peratief C.v.",
    "wof:placetype":"venue"
},
  "geometry": {"coordinates":[4.4741220474,51.0300102234],"type":"Point"}
}