{
  "type": "Feature",
  "properties": {
    "addr:full":"Ferdinand Campionlei 5 Vilvoorde Vlaams-Brabant 1800",
    "addr:housenumber":"5",
    "addr:postcode":"1800",
    "addr:street":"Ferdinand Campionlei",
    "iso:country":"BE",
    "sg:address":"Ferdinand Campionlei 5",
    "sg:city":"Vilvoorde",
    "sg:classifiers":[
        {
            "category":"Health Services",
            "subcategory":"Doctor",
            "type":"Services"
        }
    ],
    "sg:phone":"+32 2 252 58 25",
    "sg:postcode":"1800",
    "sg:province":"Vlaams-Brabant",
    "sg:tags":[
        "psychotherapist",
        "psychoanalyst"
    ],
    "wof:name":"Healing Center Cv",
    "wof:placetype":"venue"
},
  "geometry": {"coordinates":[4.4315037727,50.9277572632],"type":"Point"}
}