{
  "type": "Feature",
  "properties": {
    "iso:country":"BE",
    "sg:address":"Bollewerkstraat 76",
    "sg:city":"Gent",
    "sg:orig_category":"Installatie van houten of kunststof schrijnwerk",
    "sg:phone":"+32 9 329 34 60",
    "sg:postcode":"9031",
    "sg:province":"Oost-Vlaanderen",
    "wof:name":"J & M",
    "wof:placetype":"venue"
},
  "geometry": {"coordinates":[3.6418309212,51.0498008728],"type":"Point"}
}