{
  "type": "Feature",
  "properties": {
    "iso:country":"BE",
    "sg:address":"Kerkstraat 6",
    "sg:city":"Lille",
    "sg:classifiers":[
        {
            "category":"Health Services",
            "subcategory":"Dentist",
            "type":"Services"
        }
    ],
    "sg:phone":"+32 14 88 01 48",
    "sg:postcode":"2275",
    "sg:province":"Antwerpen",
    "wof:name":"Rosiers J",
    "wof:placetype":"venue"
},
  "geometry": {"coordinates":[4.8239011765,51.2385406494],"type":"Point"}
}