{
  "type": "Feature",
  "properties": {
    "iso:country":"BE",
    "sg:address":"Rue De L'espinette 2",
    "sg:city":"Hotton",
    "sg:classifiers":[
        {
            "category":"Fast Food",
            "type":"Food & Drink"
        }
    ],
    "sg:phone":"+32 84 46 67 56",
    "sg:postcode":"6990",
    "sg:province":"Luxembourg",
    "sg:tags":[
        "restaurant",
        "\u00c0",
        "domicile",
        "emporter",
        "livraison",
        "restaurants"
    ],
    "wof:name":"Restaurant Au Fin Gourmet",
    "wof:placetype":"venue"
},
  "geometry": {"coordinates":[5.4814310074,50.2851715088],"type":"Point"}
}