{
  "type": "Feature",
  "properties": {
    "addr:full":"Pleinstraat 101 Alken Limburg 3570",
    "addr:housenumber":"101",
    "addr:postcode":"3570",
    "addr:street":"Pleinstraat",
    "iso:country":"BE",
    "sg:address":"Pleinstraat 101",
    "sg:city":"Alken",
    "sg:orig_category":"Dakwerken Installatie van houten of kunststof schrijnwerk Loodgieterij, verwarming and sanitaire ins",
    "sg:phone":"+32 11 31 38 75",
    "sg:postcode":"3570",
    "sg:province":"Limburg",
    "wof:name":"Dakwerken Uitdebroeks",
    "wof:placetype":"venue"
},
  "geometry": {"coordinates":[5.281689167,50.8614349365],"type":"Point"}
}