{
  "type": "Feature",
  "properties": {
    "iso:country":"BE",
    "sg:address":"Rue De Corsal 18",
    "sg:city":"Chastre",
    "sg:orig_category":"Artsen and specialisten",
    "sg:phone":"+32 81 60 04 32",
    "sg:postcode":"1450",
    "sg:province":"Brabant Wallon",
    "wof:name":"D. Vande Voorde",
    "wof:placetype":"venue"
},
  "geometry": {"coordinates":[4.636452198,50.6085243225],"type":"Point"}
}