{
  "type": "Feature",
  "properties": {
    "iso:country":"BE",
    "sg:address":"Chausste D'alsemberg 928",
    "sg:city":"Ukkel/uccle",
    "sg:orig_category":"Tabac. Journaux",
    "sg:phone":"+32 2 376 81 30",
    "sg:postcode":"1180",
    "sg:province":"Bruxelles-Capitale",
    "wof:name":"E.v.i.",
    "wof:placetype":"venue"
},
  "geometry": {"coordinates":[4.3343830109,50.7939796448],"type":"Point"}
}