{
  "type": "Feature",
  "properties": {
    "addr:full":"Mechelsebaan 28 Scherpenheuvel-zichem Vlaams-Brabant 3272",
    "addr:housenumber":"28",
    "addr:postcode":"3272",
    "addr:street":"Mechelsebaan",
    "iso:country":"BE",
    "sg:address":"Mechelsebaan 28",
    "sg:city":"Scherpenheuvel-zichem",
    "sg:orig_category":"Verhuur cateringmateriaal and evenementuitrusting Verhuur diversen Winkelinrichting and handelsuitru",
    "sg:phone":"+32 13 78 11 21",
    "sg:postcode":"3272",
    "sg:province":"Vlaams-Brabant",
    "wof:name":"Promorent",
    "wof:placetype":"venue"
},
  "geometry": {"coordinates":[4.9497590065,51.0245628357],"type":"Point"}
}