{
  "type": "Feature",
  "properties": {
    "iso:country":"BE",
    "sg:address":"Rue Du Onze Novembre 17",
    "sg:city":"Frameries",
    "sg:classifiers":[
        {
            "category":"Health Services",
            "subcategory":"Health Practitioner",
            "type":"Services"
        }
    ],
    "sg:phone":"+32 65 67 20 07",
    "sg:postcode":"7080",
    "sg:province":"Hainaut",
    "sg:tags":[
        "physiotherapist"
    ],
    "wof:name":"Bultot Chantal",
    "wof:placetype":"venue"
},
  "geometry": {"coordinates":[3.8910839558,50.4105758667],"type":"Point"}
}