{
  "type": "Feature",
  "properties": {
    "addr:full":"Rue Royale 45 Box A Fontaine-l'ev\u00eaque (forchies-la-marche) Hainaut 6141",
    "addr:housenumber":"45",
    "addr:postcode":"6141",
    "addr:street":"Rue Royale;A;Hainaut",
    "iso:country":"BE",
    "sg:address":"Rue Royale 45 Box A",
    "sg:city":"Fontaine-l'ev\u00eaque (forchies-la-marche)",
    "sg:classifiers":[
        {
            "category":"Wholesale",
            "subcategory":"Scrap",
            "type":"Manufacturing & Wholesale Goods"
        }
    ],
    "sg:phone":"+32 71 54 05 51",
    "sg:postcode":"6141",
    "sg:province":"Hainaut",
    "sg:tags":[
        "metal"
    ],
    "wof:name":"Jocker Fer",
    "wof:placetype":"venue"
},
  "geometry": {"coordinates":[-111.9644622803,46.2507972717],"type":"Point"}
}