{
  "type": "Feature",
  "properties": {
    "addr:full":"Cornet 6 Ellezelles (lahamaide) Hainaut 7890",
    "addr:housenumber":"6",
    "addr:postcode":"7890",
    "addr:street":"Cornet",
    "iso:country":"BE",
    "sg:address":"Cornet 6",
    "sg:city":"Ellezelles (lahamaide)",
    "sg:classifiers":[
        {
            "category":"Recreation",
            "subcategory":"Campground",
            "type":"Entertainment"
        }
    ],
    "sg:phone":"+32 68 64 59 33",
    "sg:postcode":"7890",
    "sg:province":"Hainaut",
    "sg:tags":[
        "site",
        "camping"
    ],
    "wof:name":"Collines (les)",
    "wof:placetype":"venue"
},
  "geometry": {"coordinates":[3.7190520763,50.6938056946],"type":"Point"}
}