{
  "type": "Feature",
  "properties": {
    "iso:country":"BE",
    "sg:address":"Kalverhagestraat 15",
    "sg:city":"Melle",
    "sg:classifiers":[
        {
            "category":"Insurance",
            "subcategory":"Insurance Agent",
            "type":"Services"
        }
    ],
    "sg:phone":"+32 9 252 19 51",
    "sg:postcode":"9090",
    "sg:province":"Oost-Vlaanderen",
    "sg:tags":[
        "verzekeringsmakelaars",
        "expert"
    ],
    "wof:name":"Assudender",
    "wof:placetype":"venue"
},
  "geometry": {"coordinates":[3.8136479855,50.9880027771],"type":"Point"}
}