{
  "type": "Feature",
  "properties": {
    "addr:full":"Heidelaan 65 Sint-genesius-rode/rhode-saint-gen\u00c8se Vlaams-Brabant 1640",
    "addr:housenumber":"65",
    "addr:postcode":"1640",
    "addr:street":"Heidelaan",
    "iso:country":"BE",
    "sg:address":"Heidelaan 65",
    "sg:city":"Sint-genesius-rode/rhode-saint-gen\u00c8se",
    "sg:orig_category":"Film-, tv- and videoproductie",
    "sg:phone":"+32 2 380 60 06",
    "sg:postcode":"1640",
    "sg:province":"Vlaams-Brabant",
    "wof:name":"Dominique Christoffel",
    "wof:placetype":"venue"
},
  "geometry": {"coordinates":[4.3225531578,50.7279281616],"type":"Point"}
}