{
  "type": "Feature",
  "properties": {
    "iso:country":"BE",
    "sg:address":"Koning Albertlaan 20",
    "sg:city":"Lommel",
    "sg:orig_category":"M\u00e9decins and sp\u00e9cialistes",
    "sg:phone":"+32 11 54 37 43",
    "sg:postcode":"3920",
    "sg:province":"Limburg",
    "wof:name":"Paul Legrand",
    "wof:placetype":"venue"
},
  "geometry": {"coordinates":[5.3169369698,51.2318534851],"type":"Point"}
}