{
  "type": "Feature",
  "properties": {
    "addr:full":"Eugeen Woutersstraat 53 Heist-op-den-berg Antwerpen 2220",
    "addr:housenumber":"53",
    "addr:postcode":"2220",
    "addr:street":"Eugeen Woutersstraat",
    "iso:country":"BE",
    "sg:address":"Eugeen Woutersstraat 53",
    "sg:city":"Heist-op-den-berg",
    "sg:orig_category":"Banken and kredietinstellingen",
    "sg:phone":"+32 15 24 64 66",
    "sg:postcode":"2220",
    "sg:province":"Antwerpen",
    "wof:name":"Beroepskrediet",
    "wof:placetype":"venue"
},
  "geometry": {"coordinates":[4.7246618271,51.077545166],"type":"Point"}
}