{
  "type": "Feature",
  "properties": {
    "addr:full":"Boulevard D'ypres 9 Bruxelles Bruxelles-Capitale 1000",
    "addr:housenumber":"9",
    "addr:postcode":"1000",
    "addr:street":"Boulevard D'Ypres",
    "iso:country":"BE",
    "sg:address":"Boulevard D'ypres 9",
    "sg:city":"Bruxelles",
    "sg:classifiers":[
        {
            "category":"Communications",
            "type":"Services"
        }
    ],
    "sg:phone":"+32 2 219 79 26",
    "sg:postcode":"1000",
    "sg:province":"Bruxelles-Capitale",
    "sg:tags":[
        "translator"
    ],
    "wof:name":"De Backer A",
    "wof:placetype":"venue"
},
  "geometry": {"coordinates":[4.3470449448,50.8560638428],"type":"Point"}
}