{
  "type": "Feature",
  "properties": {
    "addr:full":"Zwijnaardsesteenweg 399 Gent Oost-Vlaanderen 9000",
    "addr:housenumber":"399",
    "addr:postcode":"9000",
    "addr:street":"Zwijnaardsesteenweg;Oost-Vlaanderen",
    "iso:country":"BE",
    "sg:address":"Zwijnaardsesteenweg 399",
    "sg:city":"Gent",
    "sg:classifiers":[
        {
            "category":"Fast Food",
            "type":"Food & Drink"
        }
    ],
    "sg:phone":"+32 9 222 72 74",
    "sg:postcode":"9000",
    "sg:province":"Oost-Vlaanderen",
    "sg:tags":[
        "\u00c0",
        "restaurants",
        "emporter",
        "restaurant"
    ],
    "wof:name":"Jasmine Garden",
    "wof:placetype":"venue"
},
  "geometry": {"coordinates":[3.7223980427,51.0281143188],"type":"Point"}
}