{
  "type": "Feature",
  "properties": {
    "addr:full":"Hamoirlaan 73 Ukkel/uccle Bruxelles-Capitale 1180",
    "addr:housenumber":"73",
    "addr:postcode":"1180",
    "addr:street":"Hamoirlaan;/",
    "iso:country":"BE",
    "sg:address":"Hamoirlaan 73",
    "sg:city":"Ukkel/uccle",
    "sg:orig_category":"Dameskledingzaken",
    "sg:phone":"+32 2 374 14 08",
    "sg:postcode":"1180",
    "sg:province":"Bruxelles-Capitale",
    "wof:name":"Rochar Couture",
    "wof:placetype":"venue"
},
  "geometry": {"coordinates":[4.3627929688,50.8031005859],"type":"Point"}
}