{
  "type": "Feature",
  "properties": {
    "iso:country":"BE",
    "sg:address":"Avenue De L\u00b4europe 3",
    "sg:city":"Ath",
    "sg:orig_category":"Advocaten and juridische adviseurs",
    "sg:phone":"+32 68 28 69 69",
    "sg:postcode":"7800",
    "sg:province":"Hainaut",
    "wof:name":"L. Denayer",
    "wof:placetype":"venue"
},
  "geometry": {"coordinates":[3.7761061192,50.6211166382],"type":"Point"}
}