{
  "type": "Feature",
  "properties": {
    "addr:full":"Vlinderstraat 3 Westerlo Antwerpen 2260",
    "addr:housenumber":"3",
    "addr:postcode":"2260",
    "addr:street":"Vlinderstraat",
    "iso:country":"BE",
    "sg:address":"Vlinderstraat 3",
    "sg:city":"Westerlo",
    "sg:orig_category":"Brood, gebak and snoepgoed",
    "sg:phone":"+32 16 69 96 67",
    "sg:postcode":"2260",
    "sg:province":"Antwerpen",
    "wof:name":"Huis Marcella",
    "wof:placetype":"venue"
},
  "geometry": {"coordinates":[4.8457670212,51.0857009888],"type":"Point"}
}