{
  "type": "Feature",
  "properties": {
    "addr:full":"Hendekenstraat 8 Assenede Oost-Vlaanderen 9960",
    "addr:housenumber":"8",
    "addr:postcode":"9960",
    "addr:street":"Hendekenstraat",
    "iso:country":"BE",
    "sg:address":"Hendekenstraat 8",
    "sg:city":"Assenede",
    "sg:orig_category":"Landbouwmachines Gh",
    "sg:phone":"+32 9 343 07 79",
    "sg:postcode":"9960",
    "sg:province":"Oost-Vlaanderen",
    "wof:name":"Persyn En Wittoek",
    "wof:placetype":"venue"
},
  "geometry": {"coordinates":[3.7187430859,51.2154273987],"type":"Point"}
}