{
  "type": "Feature",
  "properties": {
    "addr:full":"Rue De La Mariette 130 Quaregnon Hainaut 7390",
    "addr:housenumber":"130",
    "addr:postcode":"7390",
    "addr:street":"Rue De La Mariette",
    "iso:country":"BE",
    "sg:address":"Rue De La Mariette 130",
    "sg:city":"Quaregnon",
    "sg:orig_category":"Plomberie, chauffage and installations sanitaires",
    "sg:phone":"+32 65 79 34 19",
    "sg:postcode":"7390",
    "sg:province":"Hainaut",
    "wof:name":"Chauffage Tropique",
    "wof:placetype":"venue"
},
  "geometry": {"coordinates":[3.8515400887,50.4467010498],"type":"Point"}
}