{
  "type": "Feature",
  "properties": {
    "addr:full":"Skaldenstraat 121 Gent (desteldonk) Oost-Vlaanderen 9042",
    "addr:housenumber":"121",
    "addr:postcode":"9042",
    "addr:street":"Skaldenstraat",
    "iso:country":"BE",
    "sg:address":"Skaldenstraat 121",
    "sg:city":"Gent (desteldonk)",
    "sg:classifiers":[
        {
            "category":"Shopping",
            "subcategory":"Bicycles & Sporting Goods",
            "type":"Retail Goods"
        }
    ],
    "sg:phone":"+32 9 255 53 53",
    "sg:postcode":"9042",
    "sg:province":"Oost-Vlaanderen",
    "sg:tags":[
        "tyre"
    ],
    "wof:name":"Michelin Benelux Nv",
    "wof:placetype":"venue"
},
  "geometry": {"coordinates":[3.7816700935,51.1223831177],"type":"Point"}
}