{
  "type": "Feature",
  "properties": {
    "addr:full":"Berendries 70 Brakel Oost-Vlaanderen 9660",
    "addr:housenumber":"70",
    "addr:postcode":"9660",
    "addr:street":"Berendries",
    "iso:country":"BE",
    "sg:address":"Berendries 70",
    "sg:city":"Brakel",
    "sg:orig_category":"Studios photographiques",
    "sg:phone":"+32 55 42 17 41",
    "sg:postcode":"9660",
    "sg:province":"Oost-Vlaanderen",
    "wof:name":"Frank Brusselman",
    "wof:placetype":"venue"
},
  "geometry": {"coordinates":[3.7809729576,50.8319625854],"type":"Point"}
}