{
  "type": "Feature",
  "properties": {
    "addr:full":"Place Verte 69 Spa Li\u00e8ge 4900",
    "addr:housenumber":"69",
    "addr:postcode":"4900",
    "addr:street":"Place Verte",
    "iso:country":"BE",
    "sg:address":"Place Verte 69",
    "sg:city":"Spa",
    "sg:classifiers":[
        {
            "category":"Shopping",
            "subcategory":"Clothing, Apparel, & Fashions",
            "type":"Retail Goods"
        }
    ],
    "sg:phone":"+32 87 77 40 91",
    "sg:postcode":"4900",
    "sg:province":"Li\u00e8ge",
    "sg:tags":[
        "boutique"
    ],
    "wof:name":"D\u00e9cision Boutique",
    "wof:placetype":"venue"
},
  "geometry": {"coordinates":[5.8636989594,50.4912872314],"type":"Point"}
}