{
  "type": "Feature",
  "properties": {
    "addr:full":"Sauvegardestraat 43 Puurs Antwerpen 2870",
    "addr:housenumber":"43",
    "addr:postcode":"2870",
    "addr:street":"Sauvegardestraat",
    "iso:country":"BE",
    "sg:address":"Sauvegardestraat 43",
    "sg:city":"Puurs",
    "sg:classifiers":[
        {
            "category":"Cafe",
            "type":"Food & Drink"
        }
    ],
    "sg:phone":"+32 3 886 96 44",
    "sg:postcode":"2870",
    "sg:province":"Antwerpen",
    "sg:tags":[
        "caf\u00e9s"
    ],
    "wof:name":"Caf\u00c9 Prado",
    "wof:placetype":"venue"
},
  "geometry": {"coordinates":[4.3249750137,51.0813369751],"type":"Point"}
}