{
  "type": "Feature",
  "properties": {
    "iso:country":"BE",
    "sg:address":"Eikendreef 17",
    "sg:city":"Houthalen-helchteren (helchteren)",
    "sg:classifiers":[
        {
            "category":"Professional",
            "subcategory":"Management & Consulting",
            "type":"Services"
        }
    ],
    "sg:phone":"+32 11 82 28 88",
    "sg:postcode":"3530",
    "sg:province":"Limburg",
    "sg:tags":[
        "consultant",
        "law"
    ],
    "wof:name":"Luys J",
    "wof:placetype":"venue"
},
  "geometry": {"coordinates":[5.3719201088,51.0310020447],"type":"Point"}
}