{
  "type": "Feature",
  "properties": {
    "iso:country":"BE",
    "sg:address":"Bisschopslaan 37",
    "sg:city":"Beerse",
    "sg:classifiers":[
        {
            "category":"Parking",
            "subcategory":"Bicycle",
            "type":"Transportation"
        }
    ],
    "sg:phone":"+32 14 61 53 37",
    "sg:postcode":"2340",
    "sg:province":"Antwerpen",
    "sg:tags":[
        "chiropodist"
    ],
    "wof:name":"Van Puyvelde M",
    "wof:placetype":"venue"
},
  "geometry": {"coordinates":[4.8564219475,51.3134040833],"type":"Point"}
}