{
  "type": "Feature",
  "properties": {
    "iso:country":"BE",
    "sg:address":"Kruishoutemsesteenweg 197",
    "sg:city":"Zingem",
    "sg:classifiers":[
        {
            "category":"Communications",
            "subcategory":"Radio Station",
            "type":"Services"
        }
    ],
    "sg:phone":"+32 9 384 11 47",
    "sg:postcode":"9750",
    "sg:province":"Oost-Vlaanderen",
    "sg:tags":[
        "local"
    ],
    "wof:name":"Vlaams Radiobedrijf Nv",
    "wof:placetype":"venue"
},
  "geometry": {"coordinates":[3.6351799965,50.9094581604],"type":"Point"}
}