{
  "type": "Feature",
  "properties": {
    "addr:full":"Place A. Nouille 8 Flobecq Hainaut 7880",
    "addr:housenumber":"8",
    "addr:postcode":"7880",
    "addr:street":"Place A. Nouille;Hainaut",
    "iso:country":"BE",
    "sg:address":"Place A. Nouille 8",
    "sg:city":"Flobecq",
    "sg:classifiers":[
        {
            "category":"Building & Trades",
            "subcategory":"Electrical",
            "type":"Services"
        }
    ],
    "sg:phone":"+32 68 44 71 94",
    "sg:postcode":"7880",
    "sg:province":"Hainaut",
    "sg:tags":[
        "electric",
        "-",
        "housewiring",
        "contractor"
    ],
    "wof:name":"Leleux J",
    "wof:placetype":"venue"
},
  "geometry": {"coordinates":[3.7400100231,50.7361412048],"type":"Point"}
}