{
  "type": "Feature",
  "properties": {
    "addr:full":"Arme-klarenstraat 28ba Roeselare West-Vlaanderen 8800",
    "addr:housenumber":"28ba",
    "addr:postcode":"8800",
    "addr:street":"Arme-Klarenstraat",
    "iso:country":"BE",
    "sg:address":"Arme-klarenstraat 28ba",
    "sg:city":"Roeselare",
    "sg:orig_category":"Herenkledingzaken",
    "sg:phone":"+32 51 24 60 64",
    "sg:postcode":"8800",
    "sg:province":"West-Vlaanderen",
    "wof:name":"Butch-tailors",
    "wof:placetype":"venue"
},
  "geometry": {"coordinates":[3.1204719543,50.9439582825],"type":"Point"}
}