{
  "type": "Feature",
  "properties": {
    "addr:full":"Rue Grande 102 Champlon Tenneville Luxembourg 6971",
    "addr:housenumber":"102",
    "addr:postcode":"6971",
    "addr:street":"Rue Grande",
    "iso:country":"BE",
    "sg:address":"Rue Grande 102 Champlon",
    "sg:city":"Tenneville",
    "sg:classifiers":[
        {
            "category":"Home & Garden",
            "subcategory":"Furniture",
            "type":"Retail Goods"
        }
    ],
    "sg:phone":"+32 84 45 53 71",
    "sg:postcode":"6971",
    "sg:province":"Luxembourg",
    "sg:tags":[
        "wood"
    ],
    "wof:name":"Ets Laurent Et Fils Scrl",
    "wof:placetype":"venue"
},
  "geometry": {"coordinates":[5.5017828941,50.1076087952],"type":"Point"}
}