{
  "type": "Feature",
  "properties": {
    "iso:country":"BE",
    "sg:address":"Rue Longue Vie 13a",
    "sg:city":"Elsene/ixelles",
    "sg:orig_category":"Artistes ind\u00e9pendants",
    "sg:phone":"+32 2 511 57 95",
    "sg:postcode":"1050",
    "sg:province":"Bruxelles-Capitale",
    "wof:name":"Marcel Dossogne",
    "wof:placetype":"venue"
},
  "geometry": {"coordinates":[4.3653759956,50.8363685608],"type":"Point"}
}