{
  "type": "Feature",
  "properties": {
    "addr:full":"Rue Cl\u00c9menceau 60 Colfontaine Hainaut 7340",
    "addr:housenumber":"60",
    "addr:postcode":"7340",
    "addr:street":"Rue Cle\u0301Menceau",
    "iso:country":"BE",
    "sg:address":"Rue Cl\u00c9menceau 60",
    "sg:city":"Colfontaine",
    "sg:orig_category":"Diverse opleidingen and onderwijs Volwassenenonderwijs",
    "sg:phone":"+32 65 67 26 88",
    "sg:postcode":"7340",
    "sg:province":"Hainaut",
    "wof:name":"Inst.enseign.prom.sociale",
    "wof:placetype":"venue"
},
  "geometry": {"coordinates":[3.8426148891,50.4165306091],"type":"Point"}
}