{
  "type": "Feature",
  "properties": {
    "addr:full":"Matenstraat 54 Niel Antwerpen 2845",
    "addr:housenumber":"54",
    "addr:postcode":"2845",
    "addr:street":"Matenstraat",
    "iso:country":"BE",
    "sg:address":"Matenstraat 54",
    "sg:city":"Niel",
    "sg:orig_category":"Brood, gebak and snoepgoed",
    "sg:phone":"+32 3 888 24 59",
    "sg:postcode":"2845",
    "sg:province":"Antwerpen",
    "wof:name":"Bart Kesteleyn",
    "wof:placetype":"venue"
},
  "geometry": {"coordinates":[4.3402099609,51.1119613647],"type":"Point"}
}