{
  "type": "Feature",
  "properties": {
    "addr:full":"Halewijnkouter 59 Gent (drongen) Oost-Vlaanderen 9031",
    "addr:housenumber":"59",
    "addr:postcode":"9031",
    "addr:street":"Halewijnkouter",
    "iso:country":"BE",
    "sg:address":"Halewijnkouter 59",
    "sg:city":"Gent (drongen)",
    "sg:classifiers":[
        {
            "category":"Social Services",
            "subcategory":"Job Training",
            "type":"Services"
        }
    ],
    "sg:phone":"+32 9 237 06 77",
    "sg:postcode":"9031",
    "sg:province":"Oost-Vlaanderen",
    "sg:tags":[
        "personnel"
    ],
    "wof:name":"Pantelco",
    "wof:placetype":"venue"
},
  "geometry": {"coordinates":[3.6217339039,51.0472602844],"type":"Point"}
}