{
  "type": "Feature",
  "properties": {
    "iso:country":"BE",
    "sg:address":"Rue Du Foss\u00c9 Aux Loups 32",
    "sg:city":"Bruxelles",
    "sg:classifiers":[
        {
            "category":"Restaurant",
            "type":"Food & Drink"
        }
    ],
    "sg:phone":"+32 2 217 21 87",
    "sg:postcode":"1000",
    "sg:province":"Bruxelles-Capitale",
    "wof:name":"Belga Queen",
    "wof:placetype":"venue"
},
  "geometry": {"coordinates":[4.3545708656,50.8504219055],"type":"Point"}
}