{
  "type": "Feature",
  "properties": {
    "iso:country":"BE",
    "sg:address":"Rue De France 20",
    "sg:city":"Ath",
    "sg:orig_category":"Taxi's Verhuisdiensten",
    "sg:phone":"+32 68 28 30 08",
    "sg:postcode":"7800",
    "sg:province":"Hainaut",
    "wof:name":"Taxis Jean",
    "wof:placetype":"venue"
},
  "geometry": {"coordinates":[3.7755279541,50.6320495605],"type":"Point"}
}