{
  "type": "Feature",
  "properties": {
    "iso:country":"BE",
    "sg:address":"Kapitein Cdt Vinckestr. 3",
    "sg:city":"Ooigem",
    "sg:classifiers":[
        {
            "category":"Manufacturing",
            "subcategory":"Paper Products",
            "type":"Manufacturing & Wholesale Goods"
        }
    ],
    "sg:phone":"+32 56 66 67 71",
    "sg:postcode":"8710",
    "sg:province":"West-Vlaanderen",
    "sg:tags":[
        "finished",
        "cardboard",
        "-"
    ],
    "wof:name":"Hellyn Michiel & Zoon Bvba",
    "wof:placetype":"venue"
},
  "geometry": {"coordinates":[3.3334209919,50.8923568726],"type":"Point"}
}