{
  "type": "Feature",
  "properties": {
    "addr:full":"Klinkaert 7 Halle Vlaams-Brabant 1500",
    "addr:housenumber":"7",
    "addr:postcode":"1500",
    "addr:street":"Klinkaert",
    "iso:country":"BE",
    "sg:address":"Klinkaert 7",
    "sg:city":"Halle",
    "sg:classifiers":[
        {
            "category":"Insurance",
            "subcategory":"Insurance Agent",
            "type":"Services"
        }
    ],
    "sg:phone":"+32 2 360 11 98",
    "sg:postcode":"1500",
    "sg:province":"Vlaams-Brabant",
    "sg:tags":[
        "verzekeringsmakelaars",
        "expert"
    ],
    "wof:name":"P&v",
    "wof:placetype":"venue"
},
  "geometry": {"coordinates":[4.2371811867,50.7370262146],"type":"Point"}
}