{
  "type": "Feature",
  "properties": {
    "iso:country":"BE",
    "sg:address":"Vredebaan 55",
    "sg:city":"Mortsel",
    "sg:classifiers":[
        {
            "category":"Shopping",
            "subcategory":"Computers & Home Electronics",
            "type":"Retail Goods"
        }
    ],
    "sg:phone":"+32 3 457 36 30",
    "sg:postcode":"2640",
    "sg:province":"Antwerpen",
    "sg:tags":[
        "personal",
        "-",
        "processing",
        "data"
    ],
    "wof:name":"Forcom Bvba",
    "wof:placetype":"venue"
},
  "geometry": {"coordinates":[4.439330101,51.1726150513],"type":"Point"}
}