{
  "type": "Feature",
  "properties": {
    "addr:full":"Heldenplein 7d Ham (oostham) Limburg 3945",
    "addr:housenumber":"7d",
    "addr:postcode":"oostham;3945",
    "addr:street":"Heldenplein",
    "iso:country":"BE",
    "sg:address":"Heldenplein 7d",
    "sg:city":"Ham (oostham)",
    "sg:classifiers":[
        {
            "category":"Personal",
            "subcategory":"Barber",
            "type":"Services"
        }
    ],
    "sg:phone":"+32 11 40 36 74",
    "sg:postcode":"3945",
    "sg:province":"Limburg",
    "sg:tags":[
        "gentleman",
        "salon",
        "-",
        "hairdressing"
    ],
    "wof:name":"Axcent",
    "wof:placetype":"venue"
},
  "geometry": {"coordinates":[5.1776199341,51.1046104431],"type":"Point"}
}