{
  "type": "Feature",
  "properties": {
    "addr:full":"Oostmalsesteenweg 11 Rijkevorsel Antwerpen 2310",
    "addr:housenumber":"11",
    "addr:postcode":"2310",
    "addr:street":"Oostmalsesteenweg",
    "iso:country":"BE",
    "sg:address":"Oostmalsesteenweg 11",
    "sg:city":"Rijkevorsel",
    "sg:classifiers":[
        {
            "category":"Banks & Credit Unions",
            "subcategory":"Investment Brokerage",
            "type":"Services"
        }
    ],
    "sg:phone":"+32 3 314 61 66",
    "sg:postcode":"2310",
    "sg:province":"Antwerpen",
    "sg:tags":[
        "repair",
        "-",
        "installation",
        "sanitary",
        "article"
    ],
    "wof:name":"Batens-kuylen Bvba",
    "wof:placetype":"venue"
},
  "geometry": {"coordinates":[4.7589488029,51.3462982178],"type":"Point"}
}