{
  "type": "Feature",
  "properties": {
    "iso:country":"BE",
    "sg:address":"Tuileboomstr 17",
    "sg:city":"Sint-eloois-winkel",
    "sg:classifiers":[
        {
            "category":"Professional",
            "subcategory":"Engineering",
            "type":"Services"
        }
    ],
    "sg:phone":"+32 56 50 25 31",
    "sg:postcode":"8880",
    "sg:province":"West-Vlaanderen",
    "sg:tags":[
        "machine",
        "-",
        "mechanical"
    ],
    "wof:name":"Frans Demuynck Nv",
    "wof:placetype":"venue"
},
  "geometry": {"coordinates":[3.1813399792,50.8670501709],"type":"Point"}
}