{
  "type": "Feature",
  "properties": {
    "iso:country":"BE",
    "sg:address":"R\u00c9sidence Des Agasses 73",
    "sg:city":"Mons",
    "sg:orig_category":"Loodgieterij, verwarming and sanitaire installaties",
    "sg:phone":"+32 65 88 43 17",
    "sg:postcode":"7012",
    "sg:province":"Hainaut",
    "wof:name":"S Plombizing",
    "wof:placetype":"venue"
},
  "geometry": {"coordinates":[3.8894600868,50.4481964111],"type":"Point"}
}