{
  "type": "Feature",
  "properties": {
    "addr:full":"Miksebaan 201 Brasschaat Antwerpen 2930",
    "addr:housenumber":"201",
    "addr:postcode":"2930",
    "addr:street":"Miksebaan",
    "iso:country":"BE",
    "sg:address":"Miksebaan 201",
    "sg:city":"Brasschaat",
    "sg:orig_category":"Gespecialiseerde residenti\u00eble bouw IJzerwaren, bouw- and verfmaterialen Speelgoed Tuinbenodigdheden",
    "sg:phone":"+32 3 651 62 00",
    "sg:postcode":"2930",
    "sg:province":"Antwerpen",
    "wof:name":"Ambo",
    "wof:placetype":"venue"
},
  "geometry": {"coordinates":[4.5088558197,51.2939033508],"type":"Point"}
}