{
  "type": "Feature",
  "properties": {
    "addr:full":"Stormastraat Waregem West-Vlaanderen 8790",
    "addr:postcode":"8790",
    "addr:street":"Stormastraat",
    "iso:country":"BE",
    "sg:address":"Stormastraat",
    "sg:city":"Waregem",
    "sg:orig_category":"Royal Canin. Articles de camping and de sport. Articles divers Fab. Armes and munitions",
    "sg:phone":"+32 56 60 10 63",
    "sg:postcode":"8790",
    "sg:province":"West-Vlaanderen",
    "wof:name":"Braeckman",
    "wof:placetype":"venue"
},
  "geometry": {"coordinates":[3.4256339073,50.883605957],"type":"Point"}
}