{
  "type": "Feature",
  "properties": {
    "iso:country":"BE",
    "sg:address":"Avenue Des Na\u00efades 8",
    "sg:city":"Bruxelles (watermael-boitsfort)",
    "sg:classifiers":[
        {
            "category":"Retail",
            "subcategory":"Auto Repair",
            "type":"Services"
        }
    ],
    "sg:phone":"+32 2 675 00 00",
    "sg:postcode":"1170",
    "sg:province":"Bruxelles-Capitale",
    "sg:tags":[
        "garage"
    ],
    "wof:name":"Promospeed",
    "wof:placetype":"venue"
},
  "geometry": {"coordinates":[4.412129879,50.80519104],"type":"Point"}
}