{
  "type": "Feature",
  "properties": {
    "iso:country":"BE",
    "sg:address":"Rue De La Bach\u00e9e 81",
    "sg:city":"Lasne (plancenoit)",
    "sg:classifiers":[
        {
            "category":"Building & Trades",
            "subcategory":"Construction",
            "type":"Services"
        }
    ],
    "sg:phone":"+32 2 633 16 29",
    "sg:postcode":"1380",
    "sg:province":"Brabant Wallon",
    "sg:tags":[
        "installation",
        "-",
        "central",
        "heating"
    ],
    "wof:name":"De Buyser J C",
    "wof:placetype":"venue"
},
  "geometry": {"coordinates":[4.4248871803,50.659954071],"type":"Point"}
}