{
  "type": "Feature",
  "properties": {
    "iso:country":"BE",
    "sg:address":"Rue Louis De Brouck\u00e8re 3",
    "sg:city":"Saint-nicolas (montegn\u00e9e)",
    "sg:classifiers":[
        {
            "category":"Insurance",
            "subcategory":"Insurance Agent",
            "type":"Services"
        }
    ],
    "sg:phone":"+32 4 263 11 54",
    "sg:postcode":"4420",
    "sg:province":"Li\u00e8ge",
    "sg:tags":[
        "broker"
    ],
    "wof:name":"Kinet M",
    "wof:placetype":"venue"
},
  "geometry": {"coordinates":[5.5222969055,50.6383552551],"type":"Point"}
}