{
  "type": "Feature",
  "properties": {
    "addr:full":"Invalidenlaan 40b1 Oudergem/auderghem Bruxelles-Capitale 1160",
    "addr:housenumber":"40b1",
    "addr:postcode":"1160",
    "addr:street":"Invalidenlaan;/",
    "iso:country":"BE",
    "sg:address":"Invalidenlaan 40b1",
    "sg:city":"Oudergem/auderghem",
    "sg:orig_category":"Reclamebureaus",
    "sg:phone":"+32 2 675 03 98",
    "sg:postcode":"1160",
    "sg:province":"Bruxelles-Capitale",
    "wof:name":"Dani\u00cblle Simonet",
    "wof:placetype":"venue"
},
  "geometry": {"coordinates":[4.4160509109,50.8160743713],"type":"Point"}
}