{
  "type": "Feature",
  "properties": {
    "addr:full":"Rue Du Casino 7 Jemeppe-sur-sambre (spy) Namur 5190",
    "addr:housenumber":"7",
    "addr:postcode":"5190",
    "addr:street":"Rue Du Casino",
    "iso:country":"BE",
    "sg:address":"Rue Du Casino 7",
    "sg:city":"Jemeppe-sur-sambre (spy)",
    "sg:classifiers":[
        {
            "category":"Building & Trades",
            "subcategory":"Electrical",
            "type":"Services"
        }
    ],
    "sg:phone":"+32 71 78 05 88",
    "sg:postcode":"5190",
    "sg:province":"Namur",
    "sg:tags":[
        "-",
        "electric",
        "contractor"
    ],
    "wof:name":"B.j.e. Sprl",
    "wof:placetype":"venue"
},
  "geometry": {"coordinates":[4.6885638237,50.4923706055],"type":"Point"}
}