{
  "type": "Feature",
  "properties": {
    "iso:country":"BE",
    "sg:address":"Hoornzeelstraat 6",
    "sg:city":"Tervuren",
    "sg:classifiers":[
        {
            "category":"Bakery",
            "type":"Food & Drink"
        }
    ],
    "sg:phone":"+32 2 767 05 00",
    "sg:postcode":"3080",
    "sg:province":"Vlaams-Brabant",
    "sg:tags":[
        "confectioner",
        "baker"
    ],
    "wof:name":"Raskin E",
    "wof:placetype":"venue"
},
  "geometry": {"coordinates":[4.5135731697,50.8225517273],"type":"Point"}
}