{
  "type": "Feature",
  "properties": {
    "iso:country":"BE",
    "sg:address":"Stationsstraat 20",
    "sg:city":"Gistel",
    "sg:orig_category":"Blanchisseries and teintureries",
    "sg:phone":"+32 59 27 85 98",
    "sg:postcode":"8470",
    "sg:province":"West-Vlaanderen",
    "wof:name":"Was-o-matic",
    "wof:placetype":"venue"
},
  "geometry": {"coordinates":[2.9655499458,51.1559371948],"type":"Point"}
}