{
  "type": "Feature",
  "properties": {
    "iso:country":"BE",
    "sg:address":"Rue Louis Biernaux 23",
    "sg:city":"Charleroi (jumet)",
    "sg:classifiers":[
        {
            "category":"Professional",
            "subcategory":"Computer Services",
            "type":"Services"
        }
    ],
    "sg:phone":"+32 475 87 10 03",
    "sg:postcode":"6040",
    "sg:province":"Hainaut",
    "sg:tags":[
        "repair",
        "processing",
        "-",
        "maintenance",
        "data"
    ],
    "wof:name":"Alan's Pc",
    "wof:placetype":"venue"
},
  "geometry": {"coordinates":[4.4266529083,50.4444236755],"type":"Point"}
}