{
  "type": "Feature",
  "properties": {
    "iso:country":"BE",
    "sg:address":"2b Steenstraat",
    "sg:city":"Lede",
    "sg:classifiers":[
        {
            "category":"Home & Garden",
            "subcategory":"Furniture",
            "type":"Retail Goods"
        }
    ],
    "sg:phone":"+32 53 80 96 77",
    "sg:postcode":"9340",
    "sg:province":"Oost-Vlaanderen",
    "sg:tags":[
        "household",
        "wood"
    ],
    "wof:name":"Keldor Bvba",
    "wof:placetype":"venue"
},
  "geometry": {"coordinates":[4.0103502274,50.9625663757],"type":"Point"}
}