{
  "type": "Feature",
  "properties": {
    "addr:full":"Grand-place 1 Ronse/renaix Oost-Vlaanderen 9600",
    "addr:housenumber":"1",
    "addr:postcode":"9600",
    "addr:street":"Grand-Place",
    "iso:country":"BE",
    "sg:address":"Grand-place 1",
    "sg:city":"Ronse/renaix",
    "sg:classifiers":[
        {
            "category":"Health Services",
            "subcategory":"Nursing And Care Facility",
            "type":"Services"
        }
    ],
    "sg:phone":"+32 55 23 27 11",
    "sg:postcode":"9600",
    "sg:province":"Oost-Vlaanderen",
    "sg:tags":[
        "public"
    ],
    "wof:name":"Stadsbestuur",
    "wof:placetype":"venue"
},
  "geometry": {"coordinates":[3.6014258862,50.7476196289],"type":"Point"}
}