{
  "type": "Feature",
  "properties": {
    "addr:full":"Domentveldstraat 32 Affligem (essene) Vlaams-Brabant 1790",
    "addr:housenumber":"32",
    "addr:postcode":"1790",
    "addr:street":"Domentveldstraat",
    "iso:country":"BE",
    "sg:address":"Domentveldstraat 32",
    "sg:city":"Affligem (essene)",
    "sg:classifiers":[
        {
            "category":"Farming",
            "subcategory":"Livestock Farm",
            "type":"Manufacturing & Wholesale Goods"
        }
    ],
    "sg:phone":"+32 2 452 45 04",
    "sg:postcode":"1790",
    "sg:province":"Vlaams-Brabant",
    "sg:tags":[
        "horse"
    ],
    "wof:name":"Doment Ranch",
    "wof:placetype":"venue"
},
  "geometry": {"coordinates":[4.1328239441,50.9164123535],"type":"Point"}
}