{
  "type": "Feature",
  "properties": {
    "addr:full":"Route De Dinant 27 Libramont-chevigny (saint-pierre) Luxembourg 6800",
    "addr:housenumber":"27",
    "addr:postcode":"6800",
    "addr:street":"Route De Dinant;Libramont-Chevigny Saint-Pierre",
    "iso:country":"BE",
    "sg:address":"Route De Dinant 27",
    "sg:city":"Libramont-chevigny (saint-pierre)",
    "sg:classifiers":[
        {
            "category":"Retail",
            "subcategory":"Auto Repair",
            "type":"Services"
        }
    ],
    "sg:phone":"+32 61 22 48 81",
    "sg:postcode":"6800",
    "sg:province":"Luxembourg",
    "sg:tags":[
        "garage"
    ],
    "wof:name":"Garage Lorent Sa",
    "wof:placetype":"venue"
},
  "geometry": {"coordinates":[5.3761348724,49.9199943542],"type":"Point"}
}