{
  "type": "Feature",
  "properties": {
    "addr:full":"Rue Contrepr\u00c9 15 Frasnes-lez-anvaing Hainaut 7911",
    "addr:housenumber":"15",
    "addr:postcode":"7911",
    "addr:street":"Rue Contrepre\u0301",
    "iso:country":"BE",
    "sg:address":"Rue Contrepr\u00c9 15",
    "sg:city":"Frasnes-lez-anvaing",
    "sg:orig_category":"Rundveehouders",
    "sg:phone":"+32 69 86 61 71",
    "sg:postcode":"7911",
    "sg:province":"Hainaut",
    "wof:name":"Albert Delpierre",
    "wof:placetype":"venue"
},
  "geometry": {"coordinates":[3.6408700943,50.6748886108],"type":"Point"}
}