{
  "type": "Feature",
  "properties": {
    "addr:full":"Rue Charles Rittw\u00c9ger 4 Theux Li\u00e8ge 4910",
    "addr:housenumber":"4",
    "addr:postcode":"4910",
    "addr:street":"Rue Charles Rittwe\u0301Ger",
    "iso:country":"BE",
    "sg:address":"Rue Charles Rittw\u00c9ger 4",
    "sg:city":"Theux",
    "sg:classifiers":[
        {
            "category":"Restaurant",
            "type":"Food & Drink"
        }
    ],
    "sg:phone":"+32 87 54 14 08",
    "sg:postcode":"4910",
    "sg:province":"Li\u00e8ge",
    "wof:name":"Nadine Caro",
    "wof:placetype":"venue"
},
  "geometry": {"coordinates":[5.8128099442,50.5392494202],"type":"Point"}
}