{
  "type": "Feature",
  "properties": {
    "addr:full":"Kraaikant 54 Holsbeek Vlaams-Brabant 3221",
    "addr:housenumber":"54",
    "addr:postcode":"3221",
    "addr:street":"Kraaikant",
    "iso:country":"BE",
    "sg:address":"Kraaikant 54",
    "sg:city":"Holsbeek",
    "sg:orig_category":"Fruitteelt",
    "sg:phone":"+32 16 56 13 71",
    "sg:postcode":"3221",
    "sg:province":"Vlaams-Brabant",
    "wof:name":"Frans Van Oosterwijck",
    "wof:placetype":"venue"
},
  "geometry": {"coordinates":[4.826488018,50.9529151917],"type":"Point"}
}