{
  "type": "Feature",
  "properties": {
    "iso:country":"BE",
    "sg:address":"Diegemstraat 61-63",
    "sg:city":"Zaventem",
    "sg:orig_category":"Cuisines and Equipements de Cuisines. Fabrication and montage de mobilier. Meubles D\u00e9taillants, Am\u00e9n",
    "sg:phone":"+32 2 720 02 12",
    "sg:postcode":"1930",
    "sg:province":"Vlaams-Brabant",
    "wof:name":"Ilwa - Dries Luxi Interieur",
    "wof:placetype":"venue"
},
  "geometry": {"coordinates":[4.4645700455,50.8886184692],"type":"Point"}
}