{
  "type": "Feature",
  "properties": {
    "addr:full":"Nijverheidszone 'begijnenmeers' 65 Liedekerke Vlaams-Brabant 1770",
    "addr:postcode":"1770",
    "addr:street":"Vlaams-Brabant",
    "iso:country":"BE",
    "sg:address":"Nijverheidszone 'begijnenmeers' 65",
    "sg:city":"Liedekerke",
    "sg:classifiers":[
        {
            "category":"Building & Trades",
            "subcategory":"Construction",
            "type":"Services"
        }
    ],
    "sg:phone":"+32 53 68 42 39",
    "sg:postcode":"1770",
    "sg:province":"Vlaams-Brabant",
    "sg:tags":[
        "stair"
    ],
    "wof:name":"Lippens Metaalwerken",
    "wof:placetype":"venue"
},
  "geometry": {"coordinates":[4.0872688293,50.8854942322],"type":"Point"}
}