{
  "type": "Feature",
  "properties": {
    "addr:full":"Wulfhoekstraat 1bb Hooglede West-Vlaanderen 8830",
    "addr:postcode":"8830",
    "addr:street":"Wulfhoekstraat",
    "iso:country":"BE",
    "sg:address":"Wulfhoekstraat 1bb",
    "sg:city":"Hooglede",
    "sg:orig_category":"Varkenskwekers",
    "sg:phone":"+32 51 70 01 11",
    "sg:postcode":"8830",
    "sg:province":"West-Vlaanderen",
    "wof:name":"Hendrik Dewagtere",
    "wof:placetype":"venue"
},
  "geometry": {"coordinates":[3.0544900894,50.9733772278],"type":"Point"}
}