{
  "type": "Feature",
  "properties": {
    "addr:full":"Poelstraat 31 Merelbeke Oost-Vlaanderen 9820",
    "addr:housenumber":"31",
    "addr:postcode":"9820",
    "addr:street":"Poelstraat",
    "iso:country":"BE",
    "sg:address":"Poelstraat 31",
    "sg:city":"Merelbeke",
    "sg:classifiers":[
        {
            "category":"Food & Beverages",
            "subcategory":"Fruits & Vegetables",
            "type":"Retail Goods"
        }
    ],
    "sg:phone":"+32 9 231 02 28",
    "sg:postcode":"9820",
    "sg:province":"Oost-Vlaanderen",
    "sg:tags":[
        "l\u00e9gumes"
    ],
    "wof:name":"Hermine Eliano",
    "wof:placetype":"venue"
},
  "geometry": {"coordinates":[3.7481610775,50.9891586304],"type":"Point"}
}