{
  "type": "Feature",
  "properties": {
    "iso:country":"BE",
    "sg:address":"Rue Du Bailli 2",
    "sg:city":"Braine-le-ch\u00e2teau",
    "sg:classifiers":[
        {
            "category":"Bars & Pubs",
            "type":"Food & Drink"
        }
    ],
    "sg:phone":"+32 476 20 05 85",
    "sg:postcode":"1440",
    "sg:province":"Brabant Wallon",
    "sg:tags":[
        "tavern"
    ],
    "wof:name":"Ferme Rose (taverne De La)",
    "wof:placetype":"venue"
},
  "geometry": {"coordinates":[4.2581338882,50.6819877625],"type":"Point"}
}