{
  "type": "Feature",
  "properties": {
    "addr:full":"Rue Docteur Colson 8 Rebecq (rebecq-rognon) Brabant Wallon 1430",
    "addr:housenumber":"8",
    "addr:postcode":"1430",
    "addr:street":"Rue Docteur Colson;Wallon",
    "iso:country":"BE",
    "sg:address":"Rue Docteur Colson 8",
    "sg:city":"Rebecq (rebecq-rognon)",
    "sg:classifiers":[
        {
            "category":"Government",
            "subcategory":"Office",
            "type":"Public Place"
        }
    ],
    "sg:phone":"+32 67 63 82 32",
    "sg:postcode":"1430",
    "sg:province":"Brabant Wallon",
    "sg:tags":[
        "-",
        "tourism",
        "federation"
    ],
    "wof:name":"Bureau De Tourisme",
    "wof:placetype":"venue"
},
  "geometry": {"coordinates":[4.1322331429,50.6636238098],"type":"Point"}
}