{
  "type": "Feature",
  "properties": {
    "addr:full":"Vilvoordsesteenweg 214 Brussel/bruxelles Bruxelles-Capitale 1120",
    "addr:housenumber":"214",
    "addr:postcode":"1120",
    "addr:street":"Vilvoordsesteenweg;/",
    "iso:country":"BE",
    "sg:address":"Vilvoordsesteenweg 214",
    "sg:city":"Brussel/bruxelles",
    "sg:orig_category":"HUISBRANDOLIE",
    "sg:phone":"+32 2 203 63 83",
    "sg:postcode":"1120",
    "sg:province":"Bruxelles-Capitale",
    "wof:name":"Fa. Verbergt",
    "wof:placetype":"venue"
},
  "geometry": {"coordinates":[4.4070258141,50.9046287537],"type":"Point"}
}