{
  "type": "Feature",
  "properties": {
    "iso:country":"BE",
    "sg:address":"Rue Defacqz 150",
    "sg:city":"Bruxelles (saint-gilles)",
    "sg:classifiers":[
        {
            "category":"Retail",
            "subcategory":"Self-service Laundry",
            "type":"Services"
        }
    ],
    "sg:phone":"+32 2 539 17 93",
    "sg:postcode":"1060",
    "sg:province":"Bruxelles-Capitale",
    "sg:tags":[
        "-",
        "outfit",
        "communion",
        "wear",
        "bridal",
        "rental",
        "formal"
    ],
    "wof:name":"Amandine",
    "wof:placetype":"venue"
},
  "geometry": {"coordinates":[4.3553061485,50.8257980347],"type":"Point"}
}