{
  "type": "Feature",
  "properties": {
    "iso:country":"BE",
    "sg:address":"Route De Limbourg 17",
    "sg:city":"Jalhay",
    "sg:orig_category":"M\u00e9decins and sp\u00e9cialistes",
    "sg:phone":"+32 87 47 41 05",
    "sg:postcode":"4845",
    "sg:province":"Li\u00e8ge",
    "wof:name":"Jean-marie Comeliau",
    "wof:placetype":"venue"
},
  "geometry": {"coordinates":[5.914896965,50.5204849243],"type":"Point"}
}