{
  "type": "Feature",
  "properties": {
    "addr:full":"Oude Diksmuidestraat 6 Diksmuide West-Vlaanderen 8600",
    "addr:housenumber":"6",
    "addr:postcode":"8600",
    "addr:street":"Oude Diksmuidestraat",
    "iso:country":"BE",
    "sg:address":"Oude Diksmuidestraat 6",
    "sg:city":"Diksmuide",
    "sg:orig_category":"D\u00e9molition d\u00b4immeubles and terrassements. Eleveurs de bovins. Eleveurs and marchands de porcs",
    "sg:phone":"+32 51 55 51 78",
    "sg:postcode":"8600",
    "sg:province":"West-Vlaanderen",
    "wof:name":"Jean-pierre Vandaele",
    "wof:placetype":"venue"
},
  "geometry": {"coordinates":[2.7964429855,51.0665283203],"type":"Point"}
}