{
  "type": "Feature",
  "properties": {
    "iso:country":"BE",
    "sg:address":"Rue Du Bois Jacquet 88",
    "sg:city":"Spiere-helkijn/espierres-helchin",
    "sg:orig_category":"Meubles D\u00e9taillants, Am\u00e9nagement de B\u00e2timents et de Cuisines",
    "sg:phone":"+32 56 45 65 33",
    "sg:postcode":"8587",
    "sg:province":"West-Vlaanderen",
    "wof:name":"Steven Storme",
    "wof:placetype":"venue"
},
  "geometry": {"coordinates":[3.3347630501,50.7285308838],"type":"Point"}
}