{
  "type": "Feature",
  "properties": {
    "addr:full":"Asterstraat 24 Knokke-heist (knokke) West-Vlaanderen 8300",
    "addr:housenumber":"24",
    "addr:postcode":"8300",
    "addr:street":"Asterstraat",
    "iso:country":"BE",
    "sg:address":"Asterstraat 24",
    "sg:city":"Knokke-heist (knokke)",
    "sg:classifiers":[
        {
            "category":"Real Estate",
            "subcategory":"Real Estate Services",
            "type":"Services"
        }
    ],
    "sg:phone":"+32 50 62 12 22",
    "sg:postcode":"8300",
    "sg:province":"West-Vlaanderen",
    "wof:name":"Agence Anseeuw Syndic-buro",
    "wof:placetype":"venue"
},
  "geometry": {"coordinates":[3.2732179165,51.3405532837],"type":"Point"}
}