{
  "type": "Feature",
  "properties": {
    "addr:full":"Koningsstraat 245 Sint-joost-ten-node/saint-joss Bruxelles-Capitale 1210",
    "addr:housenumber":"245",
    "addr:postcode":"1210",
    "addr:street":"Koningsstraat",
    "iso:country":"BE",
    "sg:address":"Koningsstraat 245",
    "sg:city":"Sint-joost-ten-node/saint-joss",
    "sg:orig_category":"Fournitures de bureau. Secr\u00e9tariats. Imprimeries and copyshops. Mat\u00e9riel de T\u00e9l\u00e9communication",
    "sg:phone":"+32 2 217 42 73",
    "sg:postcode":"1210",
    "sg:province":"Bruxelles-Capitale",
    "wof:name":"Dynaprint",
    "wof:placetype":"venue"
},
  "geometry": {"coordinates":[4.3679599762,50.8571395874],"type":"Point"}
}