{
  "type": "Feature",
  "properties": {
    "iso:country":"BE",
    "sg:address":"Rue De Jaunay Clan 70",
    "sg:city":"P\u00e9ruwelz",
    "sg:classifiers":[
        {
            "category":"Bakery",
            "type":"Food & Drink"
        }
    ],
    "sg:phone":"+32 69 77 16 70",
    "sg:postcode":"7600",
    "sg:province":"Hainaut",
    "sg:tags":[
        "confectioner",
        "baker"
    ],
    "wof:name":"Foucart J",
    "wof:placetype":"venue"
},
  "geometry": {"coordinates":[3.5852138996,50.5181770325],"type":"Point"}
}