{
  "type": "Feature",
  "properties": {
    "addr:full":"Meerhem 119 Gent Oost-Vlaanderen 9000",
    "addr:housenumber":"119",
    "addr:postcode":"9000",
    "addr:street":"Meerhem;Oost-Vlaanderen",
    "iso:country":"BE",
    "sg:address":"Meerhem 119",
    "sg:city":"Gent",
    "sg:classifiers":[
        {
            "category":"Food & Beverages",
            "subcategory":"Dairy",
            "type":"Retail Goods"
        }
    ],
    "sg:phone":"+32 9 225 65 76",
    "sg:postcode":"9000",
    "sg:province":"Oost-Vlaanderen",
    "sg:tags":[
        "product",
        "-"
    ],
    "wof:name":"De Craene A",
    "wof:placetype":"venue"
},
  "geometry": {"coordinates":[3.7283871174,51.0642242432],"type":"Point"}
}