{
  "type": "Feature",
  "properties": {
    "iso:country":"BE",
    "sg:address":"Begonialaan 1",
    "sg:city":"Meise",
    "sg:orig_category":"Artsen and specialisten",
    "sg:phone":"+32 2 270 05 95",
    "sg:postcode":"1860",
    "sg:province":"Vlaams-Brabant",
    "wof:name":"Stefaan Van De Velde",
    "wof:placetype":"venue"
},
  "geometry": {"coordinates":[4.3402490616,50.9589080811],"type":"Point"}
}