{
  "type": "Feature",
  "properties": {
    "iso:country":"BE",
    "sg:address":"Jos Janssenstraat 29",
    "sg:city":"Houthulst (klerken)",
    "sg:classifiers":[
        {
            "category":"Professional",
            "subcategory":"Computer Services",
            "type":"Services"
        }
    ],
    "sg:phone":"+32 51 50 43 32",
    "sg:postcode":"8650",
    "sg:province":"West-Vlaanderen",
    "sg:tags":[
        "repair",
        "processing",
        "-",
        "maintenance",
        "data"
    ],
    "wof:name":"Vdb Automation",
    "wof:placetype":"venue"
},
  "geometry": {"coordinates":[2.9119958878,50.9923820496],"type":"Point"}
}