{
  "type": "Feature",
  "properties": {
    "addr:full":"Romeinsesteenweg 743 Brussel/bruxelles Bruxelles-Capitale 1020",
    "addr:housenumber":"743",
    "addr:postcode":"1020",
    "addr:street":"Romeinsesteenweg;/",
    "iso:country":"BE",
    "sg:address":"Romeinsesteenweg 743",
    "sg:city":"Brussel/bruxelles",
    "sg:orig_category":"Rusthuizen and serviceflats",
    "sg:phone":"+32 2 478 01 01",
    "sg:postcode":"1020",
    "sg:province":"Bruxelles-Capitale",
    "wof:name":"R\u00c9sidence Romana",
    "wof:placetype":"venue"
},
  "geometry": {"coordinates":[4.3192110062,50.8946685791],"type":"Point"}
}