{
  "type": "Feature",
  "properties": {
    "addr:full":"Avenue Des Combattants 80 Gembloux Namur 5030",
    "addr:housenumber":"80",
    "addr:postcode":"5030",
    "addr:street":"Avenue Des Combattants;Namur",
    "iso:country":"BE",
    "sg:address":"Avenue Des Combattants 80",
    "sg:city":"Gembloux",
    "sg:orig_category":"Avocats and conseillers juridiques",
    "sg:phone":"+32 81 61 54 29",
    "sg:postcode":"5030",
    "sg:province":"Namur",
    "wof:name":"Jean-luc Navarre",
    "wof:placetype":"venue"
},
  "geometry": {"coordinates":[4.7020888329,50.5568809509],"type":"Point"}
}