{
  "type": "Feature",
  "properties": {
    "iso:country":"BE",
    "sg:address":"Begijnenstraat 19",
    "sg:city":"Mechelen",
    "sg:orig_category":"Salles de spectacles",
    "sg:phone":"+32 15 20 37 80",
    "sg:postcode":"2800",
    "sg:province":"Antwerpen",
    "wof:name":"Theater Teater",
    "wof:placetype":"venue"
},
  "geometry": {"coordinates":[4.4778442383,51.0277786255],"type":"Point"}
}