{
  "type": "Feature",
  "properties": {
    "addr:full":"Rue De Droixhe Li\u00e8ge 1 (li\u00e8ge 2) Li\u00e8ge 4020",
    "addr:housenumber":"1;2",
    "addr:postcode":"4020",
    "addr:street":"Rue De Droixhe Lie\u0300Ge",
    "iso:country":"BE",
    "sg:address":"Rue De Droixhe",
    "sg:city":"Li\u00e8ge 1 (li\u00e8ge 2)",
    "sg:classifiers":[
        {
            "category":"Wholesale",
            "subcategory":"Fruits & Vegetables",
            "type":"Manufacturing & Wholesale Goods"
        }
    ],
    "sg:phone":"+32 4 362 64 13",
    "sg:postcode":"4020",
    "sg:province":"Li\u00e8ge",
    "sg:tags":[
        "whol",
        "-"
    ],
    "wof:name":"Thonon",
    "wof:placetype":"venue"
},
  "geometry": {"coordinates":[5.5317320824,50.6319351196],"type":"Point"}
}