{
  "type": "Feature",
  "properties": {
    "iso:country":"BE",
    "sg:address":"Molenstraat 112",
    "sg:city":"Rumst (reet)",
    "sg:classifiers":[
        {
            "category":"Health Services",
            "subcategory":"Health Practitioner",
            "type":"Services"
        }
    ],
    "sg:phone":"+32 3 827 48 98",
    "sg:postcode":"2840",
    "sg:province":"Antwerpen",
    "sg:tags":[
        "physiotherapist"
    ],
    "wof:name":"Haazen Nathalie",
    "wof:placetype":"venue"
},
  "geometry": {"coordinates":[4.3992109299,51.1006164551],"type":"Point"}
}