{
  "type": "Feature",
  "properties": {
    "iso:country":"BE",
    "sg:address":"Hof Te Praat 13",
    "sg:city":"Maldegem",
    "sg:orig_category":"Plaatsen van vloer- and muurbekleding Schilders",
    "sg:phone":"+32 9 377 67 62",
    "sg:postcode":"9991",
    "sg:province":"Oost-Vlaanderen",
    "wof:name":"Marc Brusseel",
    "wof:placetype":"venue"
},
  "geometry": {"coordinates":[3.5077769756,51.2020645142],"type":"Point"}
}