{
  "type": "Feature",
  "properties": {
    "iso:country":"BE",
    "sg:address":"Balen Neetlaan 10",
    "sg:city":"Mol",
    "sg:classifiers":[
        {
            "category":"Health Services",
            "subcategory":"Health Practitioner",
            "type":"Services"
        }
    ],
    "sg:phone":"+32 14 81 40 36",
    "sg:postcode":"2400",
    "sg:province":"Antwerpen",
    "sg:tags":[
        "physiotherapist"
    ],
    "wof:name":"Geys J",
    "wof:placetype":"venue"
},
  "geometry": {"coordinates":[5.226952076,51.1921768188],"type":"Point"}
}