{
  "type": "Feature",
  "properties": {
    "addr:full":"Rue Madame 46 Beaumont Hainaut 6500",
    "addr:housenumber":"46",
    "addr:postcode":"6500",
    "addr:street":"Rue Madame;Hainaut",
    "iso:country":"BE",
    "sg:address":"Rue Madame 46",
    "sg:city":"Beaumont",
    "sg:classifiers":[
        {
            "category":"Health Services",
            "subcategory":"Dentist",
            "type":"Services"
        }
    ],
    "sg:phone":"+32 71 58 85 91",
    "sg:postcode":"6500",
    "sg:province":"Hainaut",
    "wof:name":"Dorignaux B",
    "wof:placetype":"venue"
},
  "geometry": {"coordinates":[4.2398171425,50.2371063232],"type":"Point"}
}