{
  "type": "Feature",
  "properties": {
    "addr:full":"Rue Principale 71 Raeren/raeren Li\u00e8ge 4730",
    "addr:housenumber":"71",
    "addr:postcode":"4730",
    "addr:street":"Rue Principale",
    "iso:country":"BE",
    "sg:address":"Rue Principale 71",
    "sg:city":"Raeren/raeren",
    "sg:orig_category":"Pharmaciens",
    "sg:phone":"+32 87 85 12 86",
    "sg:postcode":"4730",
    "sg:province":"Li\u00e8ge",
    "wof:name":"Pharmacie Populaire",
    "wof:placetype":"venue"
},
  "geometry": {"coordinates":[6.0901751518,50.7137184143],"type":"Point"}
}