{
  "type": "Feature",
  "properties": {
    "iso:country":"BE",
    "sg:address":"Av. Bourg. Jean Materne 47",
    "sg:city":"Namur",
    "sg:orig_category":"Slagers",
    "sg:phone":"+32 81 30 04 79",
    "sg:postcode":"5100",
    "sg:province":"Namur",
    "wof:name":"Fr\u00c9d\u00c9ric Struys",
    "wof:placetype":"venue"
},
  "geometry": {"coordinates":[4.8713750839,50.4566345215],"type":"Point"}
}