{
  "type": "Feature",
  "properties": {
    "addr:full":"Itterplein 19 Bree Limburg 3960",
    "addr:housenumber":"19",
    "addr:postcode":"3960",
    "addr:street":"Itterplein",
    "iso:country":"BE",
    "sg:address":"Itterplein 19",
    "sg:city":"Bree",
    "sg:classifiers":[
        {
            "category":"Wholesale",
            "subcategory":"Beer",
            "type":"Manufacturing & Wholesale Goods"
        }
    ],
    "sg:phone":"+32 89 86 47 11",
    "sg:postcode":"3960",
    "sg:province":"Limburg",
    "wof:name":"Brouwerij Sint - Jozef B.v.b.a.",
    "wof:placetype":"venue"
},
  "geometry": {"coordinates":[5.5944190025,51.1405677795],"type":"Point"}
}