{
  "type": "Feature",
  "properties": {
    "iso:country":"BE",
    "sg:address":"Petite Rue De La Gare 12",
    "sg:city":"Braine-l'alleud",
    "sg:orig_category":"Tuinen",
    "sg:phone":"+32 2 384 32 45",
    "sg:postcode":"1420",
    "sg:province":"Brabant Wallon",
    "wof:name":"Jacques Derycke",
    "wof:placetype":"venue"
},
  "geometry": {"coordinates":[-85.5393981934,36.1789016724],"type":"Point"}
}