{
  "type": "Feature",
  "properties": {
    "addr:full":"Molenhoekstraat 10 Brakel (nederbrakel) Oost-Vlaanderen 9660",
    "addr:housenumber":"10",
    "addr:postcode":"9660",
    "addr:street":"Molenhoekstraat",
    "iso:country":"BE",
    "sg:address":"Molenhoekstraat 10",
    "sg:city":"Brakel (nederbrakel)",
    "sg:classifiers":[
        {
            "category":"Shopping",
            "subcategory":"Pets & Pet Supplies",
            "type":"Retail Goods"
        }
    ],
    "sg:phone":"+32 55 42 44 49",
    "sg:postcode":"9660",
    "sg:province":"Oost-Vlaanderen",
    "sg:tags":[
        "aquarium",
        "accessory"
    ],
    "wof:name":"Van De Mergel Bvba",
    "wof:placetype":"venue"
},
  "geometry": {"coordinates":[3.7712678909,50.8111228943],"type":"Point"}
}