{
  "type": "Feature",
  "properties": {
    "iso:country":"BE",
    "sg:address":"Antwerpsesteenweg 232",
    "sg:city":"Malle",
    "sg:orig_category":"Pain, p\u00e2tisseries and confiseries",
    "sg:phone":"+32 3 309 91 38",
    "sg:postcode":"2390",
    "sg:province":"Antwerpen",
    "wof:name":"Rudy Cop",
    "wof:placetype":"venue"
},
  "geometry": {"coordinates":[4.7148151398,51.2992706299],"type":"Point"}
}