{
  "type": "Feature",
  "properties": {
    "iso:country":"BE",
    "sg:address":"Nachtegaalstraat 32",
    "sg:city":"Neerpelt",
    "sg:orig_category":"Plomberie, chauffage and installations sanitaires",
    "sg:phone":"+32 11 64 49 70",
    "sg:postcode":"3910",
    "sg:province":"Limburg",
    "wof:name":"Verdonck H.",
    "wof:placetype":"venue"
},
  "geometry": {"coordinates":[5.4481329918,51.2181243896],"type":"Point"}
}