{
  "type": "Feature",
  "properties": {
    "iso:country":"BE",
    "sg:address":"Avenue Fraiteur 26",
    "sg:city":"Elsene/ixelles",
    "sg:orig_category":"Benzinestations and brandstoffen",
    "sg:phone":"+32 2 640 04 38",
    "sg:postcode":"1050",
    "sg:province":"Bruxelles-Capitale",
    "wof:name":"Nasir",
    "wof:placetype":"venue"
},
  "geometry": {"coordinates":[4.3938779831,50.8174285889],"type":"Point"}
}