{
  "type": "Feature",
  "properties": {
    "iso:country":"BE",
    "sg:address":"C. Van Der Cruyssenstr. 26",
    "sg:city":"Nevele",
    "sg:orig_category":"Brood, gebak and snoepgoed",
    "sg:phone":"+32 9 371 63 35",
    "sg:postcode":"9850",
    "sg:province":"Oost-Vlaanderen",
    "wof:name":"Jacques De Reviere",
    "wof:placetype":"venue"
},
  "geometry": {"coordinates":[3.5496819019,51.0341262817],"type":"Point"}
}