{
  "type": "Feature",
  "properties": {
    "addr:full":"Jagersstraat 80 Brakel Oost-Vlaanderen 9660",
    "addr:housenumber":"80",
    "addr:postcode":"9660",
    "addr:street":"Jagersstraat",
    "iso:country":"BE",
    "sg:address":"Jagersstraat 80",
    "sg:city":"Brakel",
    "sg:classifiers":[
        {
            "category":"Cafe",
            "type":"Food & Drink"
        }
    ],
    "sg:phone":"+32 55 42 42 41",
    "sg:postcode":"9660",
    "sg:province":"Oost-Vlaanderen",
    "sg:tags":[
        "caf\u00e9s"
    ],
    "wof:name":"Caf\u00c9 Jagershoekje",
    "wof:placetype":"venue"
},
  "geometry": {"coordinates":[3.7553920746,50.8016738892],"type":"Point"}
}