{
  "type": "Feature",
  "properties": {
    "addr:full":"Beenhouwerstraat 25 Willebroek (heindonk) Antwerpen 2830",
    "addr:housenumber":"25",
    "addr:postcode":"2830",
    "addr:street":"Beenhouwerstraat",
    "iso:country":"BE",
    "sg:address":"Beenhouwerstraat 25",
    "sg:city":"Willebroek (heindonk)",
    "sg:classifiers":[
        {
            "category":"Personal",
            "type":"Services"
        }
    ],
    "sg:phone":"+32 3 886 59 88",
    "sg:postcode":"2830",
    "sg:province":"Antwerpen",
    "sg:tags":[
        "party",
        "planning"
    ],
    "wof:name":"Tafelhouder De Marmiet",
    "wof:placetype":"venue"
},
  "geometry": {"coordinates":[4.405769825,51.0632209778],"type":"Point"}
}