{
  "type": "Feature",
  "properties": {
    "addr:full":"Rue D'ham-sur-heure 0 Ham-sur-heure-nalinnes Hainaut 6120",
    "addr:housenumber":"0",
    "addr:postcode":"6120",
    "addr:street":"Rue D'Ham-Sur-Heure;Hainaut",
    "iso:country":"BE",
    "sg:address":"Rue D'ham-sur-heure 0",
    "sg:city":"Ham-sur-heure-nalinnes",
    "sg:orig_category":"Afbraak- and draineerwerken",
    "sg:phone":"+32 81 21 47 47",
    "sg:postcode":"6120",
    "sg:province":"Hainaut",
    "wof:name":"Van Ooteghem",
    "wof:placetype":"venue"
},
  "geometry": {"coordinates":[4.4452228546,50.3235931396],"type":"Point"}
}