{
  "type": "Feature",
  "properties": {
    "iso:country":"BE",
    "sg:address":"Groene Hofstraat 6",
    "sg:city":"Boom",
    "sg:classifiers":[
        {
            "category":"Professional",
            "subcategory":"Lawyer & Legal Services",
            "type":"Services"
        }
    ],
    "sg:phone":"+32 3 888 33 79",
    "sg:postcode":"2850",
    "sg:province":"Antwerpen",
    "wof:name":"De Wit Johan",
    "wof:placetype":"venue"
},
  "geometry": {"coordinates":[4.3655347824,51.0851097107],"type":"Point"}
}