{
  "type": "Feature",
  "properties": {
    "addr:full":"Avenue Du Roi Chevalier 65 Bruxelles (woluwe-saint-lambert) Bruxelles-Capitale 1200",
    "addr:housenumber":"65",
    "addr:postcode":"1200",
    "addr:street":"Avenue Du Roi Chevalier",
    "iso:country":"BE",
    "sg:address":"Avenue Du Roi Chevalier 65",
    "sg:city":"Bruxelles (woluwe-saint-lambert)",
    "sg:classifiers":[
        {
            "category":"Home & Garden",
            "subcategory":"Building Materials",
            "type":"Retail Goods"
        }
    ],
    "sg:phone":"+32 2 772 19 11",
    "sg:postcode":"1200",
    "sg:province":"Bruxelles-Capitale",
    "sg:tags":[
        "wall",
        "cupboard"
    ],
    "wof:name":"Plac'art Cr\u00e9ation Sprl",
    "wof:placetype":"venue"
},
  "geometry": {"coordinates":[4.417550087,50.8446807861],"type":"Point"}
}