{
  "type": "Feature",
  "properties": {
    "iso:country":"BE",
    "sg:address":"Rue Des Martyrs 80",
    "sg:city":"Anderlues",
    "sg:orig_category":"Sportclubs",
    "sg:phone":"+32 71 52 57 59",
    "sg:postcode":"6150",
    "sg:province":"Hainaut",
    "wof:name":"V.c. Anderlues",
    "wof:placetype":"venue"
},
  "geometry": {"coordinates":[4.290705204,50.3973121643],"type":"Point"}
}