{
  "type": "Feature",
  "properties": {
    "iso:country":"BE",
    "sg:address":"Rue Haas 77-81",
    "sg:city":"Eupen",
    "sg:classifiers":[
        {
            "category":"Travel",
            "subcategory":"Hotels & Motels",
            "type":"Entertainment"
        }
    ],
    "sg:phone":"+32 87 74 08 00",
    "sg:postcode":"4700",
    "sg:province":"Li\u00e8ge",
    "sg:tags":[
        "hotels",
        "business",
        "restaurant"
    ],
    "wof:name":"Bosten Hotel Ambassador Ag",
    "wof:placetype":"venue"
},
  "geometry": {"coordinates":[6.0395951271,50.6220474243],"type":"Point"}
}