{
  "type": "Feature",
  "properties": {
    "addr:full":"Kloosterpoort 30 Bree Limburg 3960",
    "addr:housenumber":"30",
    "addr:postcode":"3960",
    "addr:street":"Kloosterpoort",
    "iso:country":"BE",
    "sg:address":"Kloosterpoort 30",
    "sg:city":"Bree",
    "sg:orig_category":"Kapsalons",
    "sg:phone":"+32 89 46 66 68",
    "sg:postcode":"3960",
    "sg:province":"Limburg",
    "wof:name":"Haarstudio Nele",
    "wof:placetype":"venue"
},
  "geometry": {"coordinates":[5.5955147743,51.1390914917],"type":"Point"}
}