{
  "type": "Feature",
  "properties": {
    "iso:country":"BE",
    "sg:address":"Van Der Bekenlaan 4b1",
    "sg:city":"Oud-turnhout",
    "sg:orig_category":"Apotheken",
    "sg:phone":"+32 14 45 37 38",
    "sg:postcode":"2360",
    "sg:province":"Antwerpen",
    "wof:name":"Willy Sneyers",
    "wof:placetype":"venue"
},
  "geometry": {"coordinates":[4.9823842049,51.3182640076],"type":"Point"}
}