{
  "type": "Feature",
  "properties": {
    "addr:full":"Eksterdreef Schoten Antwerpen 2900",
    "addr:postcode":"2900",
    "addr:street":"Eksterdreef",
    "iso:country":"BE",
    "sg:address":"Eksterdreef",
    "sg:city":"Schoten",
    "sg:classifiers":[
        {
            "category":"Arena",
            "subcategory":"Sports Club",
            "type":"Entertainment"
        }
    ],
    "sg:phone":"+32 3 658 18 08",
    "sg:postcode":"2900",
    "sg:province":"Antwerpen",
    "wof:name":"Simikos Voetbalklub",
    "wof:placetype":"venue"
},
  "geometry": {"coordinates":[4.505095005,51.2643508911],"type":"Point"}
}