{
  "type": "Feature",
  "properties": {
    "addr:full":"Slaghoutstraat 7 Genk Limburg 3600",
    "addr:housenumber":"7",
    "addr:postcode":"3600",
    "addr:street":"Slaghoutstraat",
    "iso:country":"BE",
    "sg:address":"Slaghoutstraat 7",
    "sg:city":"Genk",
    "sg:classifiers":[
        {
            "category":"Wholesale",
            "subcategory":"Plants",
            "type":"Manufacturing & Wholesale Goods"
        }
    ],
    "sg:phone":"+32 89 36 76 90",
    "sg:postcode":"3600",
    "sg:province":"Limburg",
    "sg:tags":[
        "whol",
        "flower",
        "-",
        "grower"
    ],
    "wof:name":"Primaplant",
    "wof:placetype":"venue"
},
  "geometry": {"coordinates":[5.4837670326,50.9235115051],"type":"Point"}
}