{
  "type": "Feature",
  "properties": {
    "addr:full":"Rue Sabar\u00e9 152 Vis\u00e9 (cheratte) Li\u00e8ge 4602",
    "addr:housenumber":"152",
    "addr:postcode":"4602",
    "addr:street":"Rue Sabare\u0301;Cheratte",
    "iso:country":"BE",
    "sg:address":"Rue Sabar\u00e9 152",
    "sg:city":"Vis\u00e9 (cheratte)",
    "sg:classifiers":[
        {
            "category":"Sports & Exercise",
            "subcategory":"Stables",
            "type":"Entertainment"
        }
    ],
    "sg:phone":"+32 4 362 52 36",
    "sg:postcode":"4602",
    "sg:province":"Li\u00e8ge",
    "sg:tags":[
        "riding",
        "school"
    ],
    "wof:name":"Equili\u00e8ge Revue",
    "wof:placetype":"venue"
},
  "geometry": {"coordinates":[5.6827301979,50.6848487854],"type":"Point"}
}