{
  "type": "Feature",
  "properties": {
    "iso:country":"BE",
    "sg:address":"Katersberg 158",
    "sg:city":"Geel",
    "sg:orig_category":"Eleveurs and marchands de porcs",
    "sg:phone":"+32 14 58 86 78",
    "sg:postcode":"2440",
    "sg:province":"Antwerpen",
    "wof:name":"Tops",
    "wof:placetype":"venue"
},
  "geometry": {"coordinates":[5.0137548447,51.1804046631],"type":"Point"}
}