{
  "type": "Feature",
  "properties": {
    "addr:full":"Durmstraat 54 Zomergem Oost-Vlaanderen 9930",
    "addr:housenumber":"54",
    "addr:postcode":"9930",
    "addr:street":"Durmstraat",
    "iso:country":"BE",
    "sg:address":"Durmstraat 54",
    "sg:city":"Zomergem",
    "sg:orig_category":"Eleveurs de bovins. Eleveurs and marchands de porcs",
    "sg:phone":"+32 9 372 78 33",
    "sg:postcode":"9930",
    "sg:province":"Oost-Vlaanderen",
    "wof:name":"Willy Berth",
    "wof:placetype":"venue"
},
  "geometry": {"coordinates":[3.565500021,51.108921051],"type":"Point"}
}