{
  "type": "Feature",
  "properties": {
    "addr:full":"Braamstraat 17 Mol Antwerpen 2400",
    "addr:housenumber":"17",
    "addr:postcode":"2400",
    "addr:street":"Braamstraat",
    "iso:country":"BE",
    "sg:address":"Braamstraat 17",
    "sg:city":"Mol",
    "sg:classifiers":[
        {
            "category":"Real Estate",
            "subcategory":"Architect",
            "type":"Services"
        }
    ],
    "sg:phone":"+32 11 31 45 49",
    "sg:postcode":"2400",
    "sg:province":"Antwerpen",
    "wof:name":"Cuyvers S",
    "wof:placetype":"venue"
},
  "geometry": {"coordinates":[5.1416120529,51.1911392212],"type":"Point"}
}