{
  "type": "Feature",
  "properties": {
    "addr:full":"Chauss\u00c9e De Bruxelles 279 Waterloo Brabant Wallon 1410",
    "addr:housenumber":"279",
    "addr:postcode":"1410",
    "addr:street":"Chausse\u0301E De Bruxelles",
    "iso:country":"BE",
    "sg:address":"Chauss\u00c9e De Bruxelles 279",
    "sg:city":"Waterloo",
    "sg:orig_category":"Tijdelijke werkgelegenheid and uitzendkantoren",
    "sg:phone":"+32 2 357 54 10",
    "sg:postcode":"1410",
    "sg:province":"Brabant Wallon",
    "wof:name":"Vedior Interim",
    "wof:placetype":"venue"
},
  "geometry": {"coordinates":[4.4002828598,50.7128143311],"type":"Point"}
}