{
  "type": "Feature",
  "properties": {
    "iso:country":"BE",
    "sg:address":"Ijzeren Bareel 30",
    "sg:city":"Spiere-helkijn",
    "sg:orig_category":"D\u00e9corateurs d'int\u00e9rieur",
    "sg:phone":"+32 56 45 55 00",
    "sg:postcode":"8587",
    "sg:province":"West-Vlaanderen",
    "wof:name":"Vandecasteele Nv",
    "wof:placetype":"venue"
},
  "geometry": {"coordinates":[3.3308150768,50.7246360779],"type":"Point"}
}