{
  "type": "Feature",
  "properties": {
    "addr:full":"Blauwesteenstraat 122a Kontich Antwerpen 2550",
    "addr:housenumber":"122a",
    "addr:postcode":"2550",
    "addr:street":"Blauwesteenstraat",
    "iso:country":"BE",
    "sg:address":"Blauwesteenstraat 122a",
    "sg:city":"Kontich",
    "sg:orig_category":"Lacquer, Varnishes, Industrial Lacquer",
    "sg:phone":"+32 3 458 44 96",
    "sg:postcode":"2550",
    "sg:province":"Antwerpen",
    "wof:name":"Eco-colors Nv",
    "wof:placetype":"venue"
},
  "geometry": {"coordinates":[4.4542798996,51.1245994568],"type":"Point"}
}