{
  "type": "Feature",
  "properties": {
    "iso:country":"BE",
    "sg:address":"Chauss\u00e9e De Ghislenghien 8",
    "sg:city":"Silly",
    "sg:classifiers":[
        {
            "category":"Manufacturing",
            "subcategory":"Metals",
            "type":"Manufacturing & Wholesale Goods"
        }
    ],
    "sg:phone":"+32 68 56 82 41",
    "sg:postcode":"7830",
    "sg:province":"Hainaut",
    "sg:tags":[
        "ornamental",
        "work",
        "-"
    ],
    "wof:name":"Noppe D",
    "wof:placetype":"venue"
},
  "geometry": {"coordinates":[3.9171950817,50.6425628662],"type":"Point"}
}