{
  "type": "Feature",
  "properties": {
    "iso:country":"BE",
    "sg:address":"Fossebaan 133",
    "sg:city":"Ternat (wambeek)",
    "sg:orig_category":"Non-Classified Establishments",
    "sg:phone":"+32 2 582 53 52",
    "sg:postcode":"1741",
    "sg:province":"Vlaams-Brabant",
    "wof:name":"Amtico - Farco Bvba",
    "wof:placetype":"venue"
},
  "geometry": {"coordinates":[4.137901783,50.862487793],"type":"Point"}
}