{
  "type": "Feature",
  "properties": {
    "iso:country":"BE",
    "sg:address":"Rue De Saint-leger 154",
    "sg:city":"Moeskroen/mouscron",
    "sg:orig_category":"M\u00e9decins and sp\u00e9cialistes",
    "sg:phone":"+32 56 48 94 87",
    "sg:postcode":"7711",
    "sg:province":"Hainaut",
    "wof:name":"G. Hollaert",
    "wof:placetype":"venue"
},
  "geometry": {"coordinates":[3.3077180386,50.7221908569],"type":"Point"}
}