{
  "type": "Feature",
  "properties": {
    "addr:full":"Rue Des Quatre D'gins 35 Lobbes Hainaut 6540",
    "addr:housenumber":"35",
    "addr:postcode":"6540",
    "addr:street":"Rue Des Quatre D'Gins",
    "iso:country":"BE",
    "sg:address":"Rue Des Quatre D'gins 35",
    "sg:city":"Lobbes",
    "sg:classifiers":[
        {
            "category":"Insurance",
            "subcategory":"Insurance Agent",
            "type":"Services"
        }
    ],
    "sg:phone":"+32 71 59 18 94",
    "sg:postcode":"6540",
    "sg:province":"Hainaut",
    "sg:tags":[
        "-",
        "representative"
    ],
    "wof:name":"Dartevelle",
    "wof:placetype":"venue"
},
  "geometry": {"coordinates":[4.2780241966,50.3655319214],"type":"Point"}
}