{
  "type": "Feature",
  "properties": {
    "iso:country":"BE",
    "sg:address":"Chauss\u00c9e De Tongres 419",
    "sg:city":"Juprelle",
    "sg:classifiers":[
        {
            "category":"Food & Beverages",
            "subcategory":"Fruits & Vegetables",
            "type":"Retail Goods"
        }
    ],
    "sg:phone":"+32 4 278 46 29",
    "sg:postcode":"4450",
    "sg:province":"Li\u00e8ge",
    "sg:tags":[
        "groenten"
    ],
    "wof:name":"Le Maraicher",
    "wof:placetype":"venue"
},
  "geometry": {"coordinates":[5.5246930122,50.7085342407],"type":"Point"}
}