{
  "type": "Feature",
  "properties": {
    "addr:full":"Hoevenzavellaan 17 Genk Limburg 3600",
    "addr:housenumber":"17",
    "addr:postcode":"3600",
    "addr:street":"Hoevenzavellaan",
    "iso:country":"BE",
    "sg:address":"Hoevenzavellaan 17",
    "sg:city":"Genk",
    "sg:classifiers":[
        {
            "category":"Cafe",
            "type":"Food & Drink"
        }
    ],
    "sg:phone":"+32 89 38 03 50",
    "sg:postcode":"3600",
    "sg:province":"Limburg",
    "sg:tags":[
        "caf\u00e9s"
    ],
    "wof:name":"Dovris",
    "wof:placetype":"venue"
},
  "geometry": {"coordinates":[5.5062618256,50.9993972778],"type":"Point"}
}