{
  "type": "Feature",
  "properties": {
    "iso:country":"BE",
    "sg:address":"Rijkenhoekstraat 21",
    "sg:city":"Grimbergen",
    "sg:classifiers":[
        {
            "category":"Arena",
            "subcategory":"Sports Club",
            "type":"Entertainment"
        }
    ],
    "sg:phone":"+32 2 270 13 29",
    "sg:postcode":"1850",
    "sg:province":"Vlaams-Brabant",
    "sg:tags":[
        "de"
    ],
    "wof:name":"Shotokan",
    "wof:placetype":"venue"
},
  "geometry": {"coordinates":[4.3736658096,50.9357299805],"type":"Point"}
}