{
  "type": "Feature",
  "properties": {
    "addr:full":"Kleinestraat 5 Mechelen Antwerpen 2811",
    "addr:housenumber":"5",
    "addr:postcode":"2811",
    "addr:street":"Kleinestraat",
    "iso:country":"BE",
    "sg:address":"Kleinestraat 5",
    "sg:city":"Mechelen",
    "sg:orig_category":"Paardenfokkers Rundveehouders",
    "sg:phone":"+32 15 41 28 53",
    "sg:postcode":"2811",
    "sg:province":"Antwerpen",
    "wof:name":"Fa. De Beck G. & W.",
    "wof:placetype":"venue"
},
  "geometry": {"coordinates":[4.3983178139,51.0132331848],"type":"Point"}
}