{
  "type": "Feature",
  "properties": {
    "addr:full":"Lippenslaan 214 B7 Knokke-heist West-Vlaanderen 8300",
    "addr:housenumber":"214 b7",
    "addr:postcode":"8300",
    "addr:street":"Lippenslaan",
    "iso:country":"BE",
    "sg:address":"Lippenslaan 214 B7",
    "sg:city":"Knokke-heist",
    "sg:orig_category":"Agences d'exp\u00e9dition. Transports routiers de marchandises",
    "sg:phone":"+32 50 54 57 95",
    "sg:postcode":"8300",
    "sg:province":"West-Vlaanderen",
    "wof:name":"Transport Callant",
    "wof:placetype":"venue"
},
  "geometry": {"coordinates":[3.287694931,51.3467254639],"type":"Point"}
}