{
  "type": "Feature",
  "properties": {
    "iso:country":"BE",
    "sg:address":"Rue De La Gland\u00c9e 15",
    "sg:city":"Seraing",
    "sg:orig_category":"Artsen and specialisten",
    "sg:phone":"+32 4 336 41 44",
    "sg:postcode":"4100",
    "sg:province":"Li\u00e8ge",
    "wof:name":"Paul Mottet",
    "wof:placetype":"venue"
},
  "geometry": {"coordinates":[5.4950551987,50.582118988],"type":"Point"}
}