{
  "type": "Feature",
  "properties": {
    "addr:full":"Veurnevaartstraat 2 Koksijde West-Vlaanderen 8670",
    "addr:housenumber":"2",
    "addr:postcode":"8670",
    "addr:street":"Veurnevaartstraat",
    "iso:country":"BE",
    "sg:address":"Veurnevaartstraat 2",
    "sg:city":"Koksijde",
    "sg:orig_category":"Installation de menuiserie en bois and plastique. Construction industrielle and commerciale. Mat\u00e9ria",
    "sg:phone":"+32 58 23 32 86",
    "sg:postcode":"8670",
    "sg:province":"West-Vlaanderen",
    "wof:name":"Vanden Bussche",
    "wof:placetype":"venue"
},
  "geometry": {"coordinates":[2.7474799156,51.1230125427],"type":"Point"}
}