{
  "type": "Feature",
  "properties": {
    "iso:country":"BE",
    "sg:address":"Fabriekstraat 138",
    "sg:city":"Sint-pieters-leeuw",
    "sg:orig_category":"Slagers",
    "sg:phone":"+32 2 377 45 69",
    "sg:postcode":"1601",
    "sg:province":"Vlaams-Brabant",
    "wof:name":"Agneessens Rudi",
    "wof:placetype":"venue"
},
  "geometry": {"coordinates":[4.2923960686,50.7840156555],"type":"Point"}
}