{
  "type": "Feature",
  "properties": {
    "iso:country":"BE",
    "sg:address":"Rue De Roms\u00c9e 37b8",
    "sg:city":"Fleron",
    "sg:orig_category":"M\u00e9decins and sp\u00e9cialistes",
    "sg:phone":"+32 4 358 33 65",
    "sg:postcode":"4620",
    "sg:province":"Li\u00e8ge",
    "wof:name":"Hubert Leners",
    "wof:placetype":"venue"
},
  "geometry": {"coordinates":[5.6758699417,50.6135597229],"type":"Point"}
}