{
  "type": "Feature",
  "properties": {
    "iso:country":"BE",
    "sg:address":"Antoine Dansaertstraat 113b4",
    "sg:city":"Brussel/bruxelles",
    "sg:orig_category":"Architecten",
    "sg:phone":"+32 2 514 33 08",
    "sg:postcode":"1000",
    "sg:province":"Bruxelles-Capitale",
    "wof:name":"Jan Goots",
    "wof:placetype":"venue"
},
  "geometry": {"coordinates":[4.3445801735,50.8516998291],"type":"Point"}
}