{
  "type": "Feature",
  "properties": {
    "iso:country":"BE",
    "sg:address":"Langemunt 22",
    "sg:city":"Gent",
    "sg:classifiers":[
        {
            "category":"Banks & Credit Unions",
            "subcategory":"Investment Brokerage",
            "type":"Services"
        }
    ],
    "sg:phone":"+32 9 223 26 80",
    "sg:postcode":"9000",
    "sg:province":"Oost-Vlaanderen",
    "sg:tags":[
        "jean",
        "casual",
        "wear"
    ],
    "wof:name":"Traxx",
    "wof:placetype":"venue"
},
  "geometry": {"coordinates":[3.7232339382,51.0561141968],"type":"Point"}
}