{
  "type": "Feature",
  "properties": {
    "addr:full":"Rue Royale 82 Tournai Hainaut 7500",
    "addr:housenumber":"82",
    "addr:postcode":"7500",
    "addr:street":"Rue Royale",
    "iso:country":"BE",
    "sg:address":"Rue Royale 82",
    "sg:city":"Tournai",
    "sg:orig_category":"Maroquinerie and articles de voyage",
    "sg:phone":"+32 69 22 48 35",
    "sg:postcode":"7500",
    "sg:province":"Hainaut",
    "wof:name":"Tamara",
    "wof:placetype":"venue"
},
  "geometry": {"coordinates":[3.3945229053,50.6112670898],"type":"Point"}
}