{
  "type": "Feature",
  "properties": {
    "addr:full":"Leon Bekaertstraat 3 Ingelmunster West-Vlaanderen 8770",
    "addr:housenumber":"3",
    "addr:postcode":"8770",
    "addr:street":"Bekaertstraat",
    "iso:country":"BE",
    "sg:address":"Leon Bekaertstraat 3",
    "sg:city":"Ingelmunster",
    "sg:orig_category":"Loodgieterij, verwarming and sanitaire installaties Viessmann",
    "sg:phone":"+32 51 48 92 76",
    "sg:postcode":"8770",
    "sg:province":"West-Vlaanderen",
    "wof:name":"Waelkens Gaby",
    "wof:placetype":"venue"
},
  "geometry": {"coordinates":[3.2659780979,50.937286377],"type":"Point"}
}