{
  "type": "Feature",
  "properties": {
    "addr:full":"Albertdreef 4 Brecht (sint-job-in-'t Goor) Antwerpen 2960",
    "addr:housenumber":"4",
    "addr:postcode":"2960",
    "addr:street":"Albertdreef;' T Goor",
    "iso:country":"BE",
    "sg:address":"Albertdreef 4",
    "sg:city":"Brecht (sint-job-in-'t Goor)",
    "sg:classifiers":[
        {
            "category":"Professional",
            "subcategory":"Secretarial Services",
            "type":"Services"
        }
    ],
    "sg:phone":"+32 3 636 31 87",
    "sg:postcode":"2960",
    "sg:province":"Antwerpen",
    "sg:tags":[
        "firm"
    ],
    "wof:name":"Boone C",
    "wof:placetype":"venue"
},
  "geometry": {"coordinates":[4.5525598526,51.2908782959],"type":"Point"}
}