{
  "type": "Feature",
  "properties": {
    "iso:country":"BE",
    "sg:address":"Langeveld 17",
    "sg:city":"Holsbeek",
    "sg:orig_category":"Tuinen",
    "sg:phone":"+32 16 44 80 04",
    "sg:postcode":"3220",
    "sg:province":"Vlaams-Brabant",
    "wof:name":"Dirkx W Tuinen",
    "wof:placetype":"venue"
},
  "geometry": {"coordinates":[4.7484607697,50.9188499451],"type":"Point"}
}