{
  "type": "Feature",
  "properties": {
    "iso:country":"BE",
    "sg:address":"Fenffe 14",
    "sg:city":"Houyet",
    "sg:orig_category":"Landbouwmachines Gh",
    "sg:phone":"+32 84 37 71 84",
    "sg:postcode":"5560",
    "sg:province":"Namur",
    "wof:name":"Francois Roynet",
    "wof:placetype":"venue"
},
  "geometry": {"coordinates":[5.0879411697,50.1839103699],"type":"Point"}
}