{
  "type": "Feature",
  "properties": {
    "iso:country":"BE",
    "sg:address":"Rijselstraat 141",
    "sg:city":"Menen",
    "sg:orig_category":"Bagage and lederwaren",
    "sg:phone":"+32 56 52 01 58",
    "sg:postcode":"8930",
    "sg:province":"West-Vlaanderen",
    "wof:name":"Xavier Fournier",
    "wof:placetype":"venue"
},
  "geometry": {"coordinates":[3.1257600784,50.790019989],"type":"Point"}
}