{
  "type": "Feature",
  "properties": {
    "addr:full":"Mariakerkesteenweg 25 Gent Oost-Vlaanderen 9031",
    "addr:housenumber":"25",
    "addr:postcode":"9031",
    "addr:street":"Mariakerkesteenweg;Oost-Vlaanderen",
    "iso:country":"BE",
    "sg:address":"Mariakerkesteenweg 25",
    "sg:city":"Gent",
    "sg:orig_category":"Schilders",
    "sg:phone":"+32 9 226 40 72",
    "sg:postcode":"9031",
    "sg:province":"Oost-Vlaanderen",
    "wof:name":"Van Speybroeck",
    "wof:placetype":"venue"
},
  "geometry": {"coordinates":[3.6621580124,51.0520591736],"type":"Point"}
}