{
  "type": "Feature",
  "properties": {
    "iso:country":"BE",
    "sg:address":"M. Van Torhoutstraat 175",
    "sg:city":"Oudenaarde",
    "sg:orig_category":"Centres de relaxation and bien-\u00eatre. Instituts de beaut\u00e9",
    "sg:phone":"+32 55 30 98 77",
    "sg:postcode":"9700",
    "sg:province":"Oost-Vlaanderen",
    "wof:name":"Instituut Estetica",
    "wof:placetype":"venue"
},
  "geometry": {"coordinates":[3.6271059513,50.8516654968],"type":"Point"}
}