{
  "type": "Feature",
  "properties": {
    "iso:country":"BE",
    "sg:address":"Herkkantstraat 87",
    "sg:city":"Hasselt",
    "sg:orig_category":"Rundveehouders",
    "sg:phone":"+32 11 31 50 50",
    "sg:postcode":"3512",
    "sg:province":"Limburg",
    "wof:name":"Louis Demot",
    "wof:placetype":"venue"
},
  "geometry": {"coordinates":[5.234041214,50.9229621887],"type":"Point"}
}