{
  "type": "Feature",
  "properties": {
    "addr:full":"Kleine Steenweg 19 Erpe-mere (erpe) Oost-Vlaanderen 9420",
    "addr:housenumber":"19",
    "addr:postcode":"9420",
    "addr:street":"Kleine Steenweg",
    "iso:country":"BE",
    "sg:address":"Kleine Steenweg 19",
    "sg:city":"Erpe-mere (erpe)",
    "sg:classifiers":[
        {
            "category":"Autos & Motor Vehicles",
            "subcategory":"Automobile Sales",
            "type":"Retail Goods"
        }
    ],
    "sg:phone":"+32 53 80 87 25",
    "sg:postcode":"9420",
    "sg:province":"Oost-Vlaanderen",
    "sg:tags":[
        "electrical"
    ],
    "wof:name":"Vebar",
    "wof:placetype":"venue"
},
  "geometry": {"coordinates":[3.987019062,50.9459838867],"type":"Point"}
}