{
  "type": "Feature",
  "properties": {
    "iso:country":"BE",
    "sg:address":"Route D'ath 9a",
    "sg:city":"Frasnes-lez-anvaing",
    "sg:classifiers":[
        {
            "category":"Personal",
            "subcategory":"Beauty Salon",
            "type":"Services"
        }
    ],
    "sg:phone":"+32 69 86 75 82",
    "sg:postcode":"7911",
    "sg:province":"Hainaut",
    "sg:tags":[
        "de",
        "coiffure"
    ],
    "wof:name":"Id\u00c9e Coiffure",
    "wof:placetype":"venue"
},
  "geometry": {"coordinates":[3.6542100906,50.6607284546],"type":"Point"}
}