{
  "type": "Feature",
  "properties": {
    "iso:country":"BE",
    "sg:address":"Westkerkestraat 194",
    "sg:city":"Ichtegem",
    "sg:orig_category":"Quincailleries",
    "sg:phone":"+32 59 29 80 15",
    "sg:postcode":"8480",
    "sg:province":"West-Vlaanderen",
    "wof:name":"Garanta Keuken",
    "wof:placetype":"venue"
},
  "geometry": {"coordinates":[3.0260360241,51.1391563416],"type":"Point"}
}