{
  "type": "Feature",
  "properties": {
    "iso:country":"BE",
    "sg:address":"Marktstraat 38",
    "sg:city":"Opwijk",
    "sg:orig_category":"Apotheken",
    "sg:phone":"+32 52 35 70 69",
    "sg:postcode":"1745",
    "sg:province":"Vlaams-Brabant",
    "wof:name":"M.t. Moens",
    "wof:placetype":"venue"
},
  "geometry": {"coordinates":[4.1885938644,50.9702301025],"type":"Point"}
}