{
  "type": "Feature",
  "properties": {
    "iso:country":"BE",
    "sg:address":"Merksplassesteenweg 100",
    "sg:city":"Rijkevorsel",
    "sg:orig_category":"D\u00e9taillants en pi\u00e8ces and accessoires de voitures",
    "sg:phone":"+32 3 314 98 27",
    "sg:postcode":"2310",
    "sg:province":"Antwerpen",
    "wof:name":"Brezan Autoparts",
    "wof:placetype":"venue"
},
  "geometry": {"coordinates":[4.8039941788,51.3479614258],"type":"Point"}
}