{
  "type": "Feature",
  "properties": {
    "iso:country":"BE",
    "sg:address":"Rue De Bois-de-breux 353",
    "sg:city":"Li\u00e8ge 1 (jupille-sur-meuse)",
    "sg:classifiers":[
        {
            "category":"Banks & Credit Unions",
            "subcategory":"Investment Brokerage",
            "type":"Services"
        }
    ],
    "sg:phone":"+32 4 370 09 22",
    "sg:postcode":"4020",
    "sg:province":"Li\u00e8ge",
    "sg:tags":[
        "fence"
    ],
    "wof:name":"F.r.e.g.",
    "wof:placetype":"venue"
},
  "geometry": {"coordinates":[5.6210289001,50.6368904114],"type":"Point"}
}