{
  "type": "Feature",
  "properties": {
    "addr:full":"Smedenstraat 15 Brugge West-Vlaanderen 8000",
    "addr:housenumber":"15",
    "addr:postcode":"8000",
    "addr:street":"Smedenstraat",
    "iso:country":"BE",
    "sg:address":"Smedenstraat 15",
    "sg:city":"Brugge",
    "sg:orig_category":"Dameskledingzaken",
    "sg:phone":"+32 50 33 74 12",
    "sg:postcode":"8000",
    "sg:province":"West-Vlaanderen",
    "wof:name":"Huis Fanucci",
    "wof:placetype":"venue"
},
  "geometry": {"coordinates":[3.2158050537,51.2055358887],"type":"Point"}
}