{
  "type": "Feature",
  "properties": {
    "iso:country":"BE",
    "sg:address":"Rue Saint-fiacre 88",
    "sg:city":"Charleroi",
    "sg:orig_category":"Pi\u00e8ces and accessoires de v\u00e9hicules automobiles Gr",
    "sg:phone":"+32 71 32 22 00",
    "sg:postcode":"6031",
    "sg:province":"Hainaut",
    "wof:name":"Fernand Bairiot",
    "wof:placetype":"venue"
},
  "geometry": {"coordinates":[4.3905692101,50.4106178284],"type":"Point"}
}