{
  "type": "Feature",
  "properties": {
    "addr:full":"Rijksweg 191 Maasmechelen Limburg 3630",
    "addr:housenumber":"191",
    "addr:postcode":"3630",
    "addr:street":"Rijksweg",
    "iso:country":"BE",
    "sg:address":"Rijksweg 191",
    "sg:city":"Maasmechelen",
    "sg:orig_category":"Dameskledingzaken",
    "sg:phone":"+32 89 77 44 63",
    "sg:postcode":"3630",
    "sg:province":"Limburg",
    "wof:name":"Top Mode",
    "wof:placetype":"venue"
},
  "geometry": {"coordinates":[5.7006950378,50.9779205322],"type":"Point"}
}