{
  "type": "Feature",
  "properties": {
    "addr:full":"Windmeulen 1 Welkenraedt/welkenraedt Li\u00e8ge 4841",
    "addr:housenumber":"1",
    "addr:postcode":"4841",
    "addr:street":"Windmeulen",
    "iso:country":"BE",
    "sg:address":"Windmeulen 1",
    "sg:city":"Welkenraedt/welkenraedt",
    "sg:orig_category":"Restaurants Ruimtes voor conferenties, recepties and feesten",
    "sg:phone":"+32 87 44 69 20",
    "sg:postcode":"4841",
    "sg:province":"Li\u00e8ge",
    "wof:name":"Salons Le Charlemagne",
    "wof:placetype":"venue"
},
  "geometry": {"coordinates":[5.9256300926,50.6628990173],"type":"Point"}
}