{
  "type": "Feature",
  "properties": {
    "iso:country":"BE",
    "sg:address":"Rue Du Palais 34",
    "sg:city":"Nivelles",
    "sg:orig_category":"Informaticaconsulenten Software ontwikkeling and ontwerp",
    "sg:phone":"+32 67 84 47 74",
    "sg:postcode":"1402",
    "sg:province":"Brabant Wallon",
    "wof:name":"C.d.r.-c.r.d.",
    "wof:placetype":"venue"
},
  "geometry": {"coordinates":[4.3742380142,50.5972976685],"type":"Point"}
}