{
  "type": "Feature",
  "properties": {
    "addr:full":"Neringe 124ba Tielt-winge Vlaams-Brabant 3390",
    "addr:postcode":"3390",
    "addr:street":"Vlaams-Brabant",
    "iso:country":"BE",
    "sg:address":"Neringe 124ba",
    "sg:city":"Tielt-winge",
    "sg:orig_category":"Varkenskwekers",
    "sg:phone":"+32 16 50 11 92",
    "sg:postcode":"3390",
    "sg:province":"Vlaams-Brabant",
    "wof:name":"Gaston Vranken",
    "wof:placetype":"venue"
},
  "geometry": {"coordinates":[4.9038281441,50.9413642883],"type":"Point"}
}