{
  "type": "Feature",
  "properties": {
    "iso:country":"BE",
    "sg:address":"Goudsbloemstraat 11",
    "sg:city":"Leuven",
    "sg:classifiers":[
        {
            "category":"Restaurant",
            "type":"Food & Drink"
        }
    ],
    "sg:phone":"+32 16 23 82 34",
    "sg:postcode":"3000",
    "sg:province":"Vlaams-Brabant",
    "wof:name":"Geuren & Kleuren",
    "wof:placetype":"venue"
},
  "geometry": {"coordinates":[4.6897649765,50.8808174133],"type":"Point"}
}