{
  "type": "Feature",
  "properties": {
    "addr:full":"Kloosterstraat 64 Lommel Limburg 3920",
    "addr:housenumber":"64",
    "addr:postcode":"3920",
    "addr:street":"Kloosterstraat",
    "iso:country":"BE",
    "sg:address":"Kloosterstraat 64",
    "sg:city":"Lommel",
    "sg:orig_category":"Dakwerken",
    "sg:phone":"+32 11 54 40 40",
    "sg:postcode":"3920",
    "sg:province":"Limburg",
    "wof:name":"L Kuppens",
    "wof:placetype":"venue"
},
  "geometry": {"coordinates":[5.3169188499,51.2302093506],"type":"Point"}
}