{
  "type": "Feature",
  "properties": {
    "iso:country":"BE",
    "sg:address":"Dambruggestraat 102",
    "sg:city":"Antwerpen",
    "sg:orig_category":"Hout and afgeleiden Gh IJzerwaren, bouw- and verfmaterialen",
    "sg:phone":"+32 3 232 87 67",
    "sg:postcode":"2060",
    "sg:province":"Antwerpen",
    "wof:name":"Hubo",
    "wof:placetype":"venue"
},
  "geometry": {"coordinates":[4.42274189,51.2217521667],"type":"Point"}
}