{
  "type": "Feature",
  "properties": {
    "iso:country":"BE",
    "sg:address":"Rue Des Sept Blasons 42",
    "sg:city":"Soignies (neufvilles)",
    "sg:classifiers":[
        {
            "category":"Building & Trades",
            "subcategory":"Construction",
            "type":"Services"
        }
    ],
    "sg:phone":"+32 65 73 17 57",
    "sg:postcode":"7063",
    "sg:province":"Hainaut",
    "sg:tags":[
        "carpenter"
    ],
    "wof:name":"Tamigneau M",
    "wof:placetype":"venue"
},
  "geometry": {"coordinates":[4.0121188164,50.5432510376],"type":"Point"}
}