{
  "type": "Feature",
  "properties": {
    "addr:full":"Wolfgang D'urselstraat 16 Bornem Antwerpen 2880",
    "addr:housenumber":"16",
    "addr:postcode":"2880",
    "addr:street":"Wolfgang D'Urselstraat",
    "iso:country":"BE",
    "sg:address":"Wolfgang D'urselstraat 16",
    "sg:city":"Bornem",
    "sg:orig_category":"Epiceries",
    "sg:phone":"+32 3 889 21 59",
    "sg:postcode":"2880",
    "sg:province":"Antwerpen",
    "wof:name":"Spar",
    "wof:placetype":"venue"
},
  "geometry": {"coordinates":[4.2699790001,51.1031303406],"type":"Point"}
}