{
  "type": "Feature",
  "properties": {
    "iso:country":"BE",
    "sg:address":"Tussenbruggen 14",
    "sg:city":"Oudenaarde",
    "sg:orig_category":"Pain, p\u00e2tisseries and confiseries",
    "sg:phone":"+32 55 31 21 36",
    "sg:postcode":"9700",
    "sg:province":"Oost-Vlaanderen",
    "wof:name":"Gijselinck Luc",
    "wof:placetype":"venue"
},
  "geometry": {"coordinates":[3.6075179577,50.8433036804],"type":"Point"}
}