{
  "type": "Feature",
  "properties": {
    "iso:country":"BE",
    "sg:address":"1051",
    "sg:city":"Europark 3530 Houthalen-helchter",
    "sg:classifiers":[
        {
            "category":"Professional",
            "type":"Services"
        }
    ],
    "sg:phone":"+32 11 52 16 60",
    "sg:postcode":"1051",
    "sg:tags":[
        "transport",
        "road"
    ],
    "wof:name":"Transportbedrijf De Coster Bvba",
    "wof:placetype":"venue"
},
  "geometry": {"coordinates":[5.3719201088,51.0310020447],"type":"Point"}
}