{
  "type": "Feature",
  "properties": {
    "addr:full":"Langestraat 23ba Zomergem Oost-Vlaanderen 9931",
    "addr:housenumber":"23ba",
    "addr:postcode":"9931",
    "addr:street":"Langestraat",
    "iso:country":"BE",
    "sg:address":"Langestraat 23ba",
    "sg:city":"Zomergem",
    "sg:orig_category":"Producteurs de l\u00e9gumes",
    "sg:phone":"+32 9 377 73 75",
    "sg:postcode":"9931",
    "sg:province":"Oost-Vlaanderen",
    "wof:name":"Guido De Witte",
    "wof:placetype":"venue"
},
  "geometry": {"coordinates":[3.5360479355,51.1542510986],"type":"Point"}
}