{
  "type": "Feature",
  "properties": {
    "addr:full":"Vaartstraat 24 Ham Limburg 3945",
    "addr:housenumber":"24",
    "addr:postcode":"3945",
    "addr:street":"Vaartstraat",
    "iso:country":"BE",
    "sg:address":"Vaartstraat 24",
    "sg:city":"Ham",
    "sg:classifiers":[
        {
            "category":"Restaurant",
            "type":"Food & Drink"
        }
    ],
    "sg:phone":"+32 11 34 81 77",
    "sg:postcode":"3945",
    "sg:province":"Limburg",
    "wof:name":"Taverne Hamse Hofstee",
    "wof:placetype":"venue"
},
  "geometry": {"coordinates":[5.1776199341,51.1046104431],"type":"Point"}
}