{
  "type": "Feature",
  "properties": {
    "addr:full":"Rue De La Fraternit\u00c9 1 Binche Hainaut 7130",
    "addr:housenumber":"1",
    "addr:postcode":"7130",
    "addr:street":"Rue De La Fraternite\u0301",
    "iso:country":"BE",
    "sg:address":"Rue De La Fraternit\u00c9 1",
    "sg:city":"Binche",
    "sg:classifiers":[
        {
            "category":"Cafe",
            "type":"Food & Drink"
        }
    ],
    "sg:phone":"+32 64 33 35 46",
    "sg:postcode":"7130",
    "sg:province":"Hainaut",
    "sg:tags":[
        "caf\u00e9s"
    ],
    "wof:name":"Claude Gervais",
    "wof:placetype":"venue"
},
  "geometry": {"coordinates":[4.1660728455,50.412311554],"type":"Point"}
}