{
  "type": "Feature",
  "properties": {
    "addr:full":"Driftweg 69 Bredene West-Vlaanderen 8450",
    "addr:housenumber":"69",
    "addr:postcode":"8450",
    "addr:street":"Driftweg",
    "iso:country":"BE",
    "sg:address":"Driftweg 69",
    "sg:city":"Bredene",
    "sg:classifiers":[
        {
            "category":"Education",
            "subcategory":"Special Training",
            "type":"Public Place"
        }
    ],
    "sg:phone":"+32 59 32 03 13",
    "sg:postcode":"8450",
    "sg:province":"West-Vlaanderen",
    "sg:tags":[
        "school",
        "sailing"
    ],
    "wof:name":"Twins Surf School",
    "wof:placetype":"venue"
},
  "geometry": {"coordinates":[2.9505860806,51.2439193726],"type":"Point"}
}