{
  "type": "Feature",
  "properties": {
    "iso:country":"BE",
    "sg:address":"Nazarethstraat 45",
    "sg:city":"De Pinte",
    "sg:orig_category":"M\u00e9decins and sp\u00e9cialistes",
    "sg:phone":"+32 9 281 12 42",
    "sg:postcode":"9840",
    "sg:province":"Oost-Vlaanderen",
    "wof:name":"Hendrik-harko Van Egmond",
    "wof:placetype":"venue"
},
  "geometry": {"coordinates":[3.6384789944,50.9853668213],"type":"Point"}
}