{
  "type": "Feature",
  "properties": {
    "addr:full":"Vrijheidslaan 36 Peer Limburg 3990",
    "addr:housenumber":"36",
    "addr:postcode":"3990",
    "addr:street":"Vrijheidslaan",
    "iso:country":"BE",
    "sg:address":"Vrijheidslaan 36",
    "sg:city":"Peer",
    "sg:orig_category":"Installatie van metalen schrijnwerk Pleisterwerk",
    "sg:phone":"+32 11 63 42 92",
    "sg:postcode":"3990",
    "sg:province":"Limburg",
    "wof:name":"Robert Dreesen",
    "wof:placetype":"venue"
},
  "geometry": {"coordinates":[5.4613509178,51.1355438232],"type":"Point"}
}