{
  "type": "Feature",
  "properties": {
    "iso:country":"BE",
    "sg:address":"Rue Joseph Wauters 37",
    "sg:city":"Waremme",
    "sg:orig_category":"Textiel",
    "sg:phone":"+32 19 32 39 78",
    "sg:postcode":"4300",
    "sg:province":"Li\u00e8ge",
    "wof:name":"Maison Nuit Blanche",
    "wof:placetype":"venue"
},
  "geometry": {"coordinates":[5.2544331551,50.6970558167],"type":"Point"}
}