{
  "type": "Feature",
  "properties": {
    "addr:full":"Astridlaan 73 Brugge (assebroek) West-Vlaanderen 8310",
    "addr:housenumber":"73",
    "addr:postcode":"8310",
    "addr:street":"Astridlaan",
    "iso:country":"BE",
    "sg:address":"Astridlaan 73",
    "sg:city":"Brugge (assebroek)",
    "sg:classifiers":[
        {
            "category":"Personal",
            "subcategory":"Beauty Salon",
            "type":"Services"
        }
    ],
    "sg:phone":"+32 50 35 25 78",
    "sg:postcode":"8310",
    "sg:province":"West-Vlaanderen",
    "sg:tags":[
        "lady",
        "-",
        "hairdressing"
    ],
    "wof:name":"Caprice",
    "wof:placetype":"venue"
},
  "geometry": {"coordinates":[3.2503259182,51.1987838745],"type":"Point"}
}