{
  "type": "Feature",
  "properties": {
    "iso:country":"BE",
    "sg:address":"Minderbroedersrui 45",
    "sg:city":"Antwerpen",
    "sg:orig_category":"Fotografen and fotostudio's",
    "sg:phone":"+32 3 231 88 55",
    "sg:postcode":"2000",
    "sg:province":"Antwerpen",
    "wof:name":"Luc Willame",
    "wof:placetype":"venue"
},
  "geometry": {"coordinates":[4.4042701721,51.2225799561],"type":"Point"}
}