{
  "type": "Feature",
  "properties": {
    "addr:full":"Staatsbaan 96 Maldegem Oost-Vlaanderen 9991",
    "addr:housenumber":"96",
    "addr:postcode":"9991",
    "addr:street":"Staatsbaan",
    "iso:country":"BE",
    "sg:address":"Staatsbaan 96",
    "sg:city":"Maldegem",
    "sg:orig_category":"Postkantoren Verzekeringsmakelaars and experts",
    "sg:phone":"+32 50 71 14 07",
    "sg:postcode":"9991",
    "sg:province":"Oost-Vlaanderen",
    "wof:name":"De Post",
    "wof:placetype":"venue"
},
  "geometry": {"coordinates":[3.4900159836,51.2044143677],"type":"Point"}
}