{
  "type": "Feature",
  "properties": {
    "addr:full":"Laaglandstraat 12 Heusden-zolder Limburg 3550",
    "addr:housenumber":"12",
    "addr:postcode":"3550",
    "addr:street":"Laaglandstraat",
    "iso:country":"BE",
    "sg:address":"Laaglandstraat 12",
    "sg:city":"Heusden-zolder",
    "sg:orig_category":"Woningbouw",
    "sg:phone":"+32 11 43 36 27",
    "sg:postcode":"3550",
    "sg:province":"Limburg",
    "wof:name":"Yilmaz Oktay",
    "wof:placetype":"venue"
},
  "geometry": {"coordinates":[5.2522292137,50.9976577759],"type":"Point"}
}