{
  "type": "Feature",
  "properties": {
    "addr:full":"Rue Grand'm\u00e8re 19 La Bruy\u00e8re (emines) Namur 5080",
    "addr:housenumber":"19",
    "addr:postcode":"5080",
    "addr:street":"Rue Grand'Me \u0300Re;Bruye\u0300Re Emines",
    "iso:country":"BE",
    "sg:address":"Rue Grand'm\u00e8re 19",
    "sg:city":"La Bruy\u00e8re (emines)",
    "sg:classifiers":[
        {
            "category":"Retail",
            "subcategory":"Auto Repair",
            "type":"Services"
        }
    ],
    "sg:phone":"+32 81 21 30 75",
    "sg:postcode":"5080",
    "sg:province":"Namur",
    "sg:tags":[
        "automobile-body"
    ],
    "wof:name":"Morph\u00e9e E",
    "wof:placetype":"venue"
},
  "geometry": {"coordinates":[4.8422899246,50.5166702271],"type":"Point"}
}