{
  "type": "Feature",
  "properties": {
    "addr:full":"Roeselarestraat 213 Wevelgem West-Vlaanderen 8560",
    "addr:housenumber":"213",
    "addr:postcode":"8560",
    "addr:street":"Roeselarestraat",
    "iso:country":"BE",
    "sg:address":"Roeselarestraat 213",
    "sg:city":"Wevelgem",
    "sg:orig_category":"Reisbureaus",
    "sg:phone":"+32 56 42 16 57",
    "sg:postcode":"8560",
    "sg:province":"West-Vlaanderen",
    "wof:name":"Cyprus Travel Agency",
    "wof:placetype":"venue"
},
  "geometry": {"coordinates":[3.1786630154,50.8168869019],"type":"Point"}
}