{
  "type": "Feature",
  "properties": {
    "addr:full":"Driegaaienstraat 112 Box 5 Sint-niklaas Oost-Vlaanderen 9100",
    "addr:housenumber":"112;5",
    "addr:postcode":"9100",
    "addr:street":"Driegaaienstraat;Box",
    "iso:country":"BE",
    "sg:address":"Driegaaienstraat 112 Box 5",
    "sg:city":"Sint-niklaas",
    "sg:classifiers":[
        {
            "category":"Shopping",
            "subcategory":"Party Supplies",
            "type":"Retail Goods"
        }
    ],
    "sg:phone":"+32 3 766 26 26",
    "sg:postcode":"9100",
    "sg:province":"Oost-Vlaanderen",
    "sg:tags":[
        "machine",
        "shoemaker",
        "-"
    ],
    "wof:name":"Bink",
    "wof:placetype":"venue"
},
  "geometry": {"coordinates":[4.1339859962,51.154624939],"type":"Point"}
}