{
  "type": "Feature",
  "properties": {
    "iso:country":"BE",
    "sg:address":"Eeuwfeestwal 30 Box 1",
    "sg:city":"Tongeren",
    "sg:classifiers":[
        {
            "category":"Professional",
            "subcategory":"Accounting & Tax Preparation",
            "type":"Services"
        }
    ],
    "sg:phone":"+32 12 23 12 35",
    "sg:postcode":"3700",
    "sg:province":"Limburg",
    "sg:tags":[
        "accountant"
    ],
    "wof:name":"Accountantskantoor Liesens Nv",
    "wof:placetype":"venue"
},
  "geometry": {"coordinates":[5.4605259895,50.7804832458],"type":"Point"}
}