{
  "type": "Feature",
  "properties": {
    "addr:full":"Foyr 87 Jalhay Li\u00e8ge 4845",
    "addr:housenumber":"87",
    "addr:postcode":"4845",
    "addr:street":"Foyr",
    "iso:country":"BE",
    "sg:address":"Foyr 87",
    "sg:city":"Jalhay",
    "sg:orig_category":"Mat\u00e9riaux de construction Rev\u00eatements de sols and murs. Rev\u00eatements pour sols and murs",
    "sg:phone":"+32 87 64 77 08",
    "sg:postcode":"4845",
    "sg:province":"Li\u00e8ge",
    "wof:name":"Cerami Carrelages",
    "wof:placetype":"venue"
},
  "geometry": {"coordinates":[5.9364957809,50.5687675476],"type":"Point"}
}