{
  "type": "Feature",
  "properties": {
    "addr:full":"Armentierestraat 345 Komen-waasten/comines-warneton Hainaut 7783",
    "addr:housenumber":"345;7783",
    "addr:street":"Armentierestraat",
    "iso:country":"BE",
    "sg:address":"Armentierestraat 345",
    "sg:city":"Komen-waasten/comines-warneton",
    "sg:classifiers":[
        {
            "category":"Food & Beverages",
            "subcategory":"Meat & Fish",
            "type":"Retail Goods"
        }
    ],
    "sg:phone":"+32 56 58 82 81",
    "sg:postcode":"7783",
    "sg:province":"Hainaut",
    "sg:tags":[
        "vi",
        "zeevruchten"
    ],
    "wof:name":"Maison Bizet",
    "wof:placetype":"venue"
},
  "geometry": {"coordinates":[2.8828949928,50.7069244385],"type":"Point"}
}