{
  "type": "Feature",
  "properties": {
    "addr:full":"Aartrijksestraat 65 Zedelgem (aartrijke) West-Vlaanderen 8211",
    "addr:housenumber":"65",
    "addr:postcode":"8211",
    "addr:street":"Aartrijksestraat",
    "iso:country":"BE",
    "sg:address":"Aartrijksestraat 65",
    "sg:city":"Zedelgem (aartrijke)",
    "sg:classifiers":[
        {
            "category":"Arena",
            "subcategory":"Sports Club",
            "type":"Entertainment"
        }
    ],
    "sg:phone":"+32 50 20 88 73",
    "sg:postcode":"8211",
    "sg:province":"West-Vlaanderen",
    "wof:name":"Verbroedering Voetbalclub Aartrijke",
    "wof:placetype":"venue"
},
  "geometry": {"coordinates":[3.0889649391,51.1200408936],"type":"Point"}
}