{
  "type": "Feature",
  "properties": {
    "addr:full":"Immerzeeldreef 112 Aalst Oost-Vlaanderen 9300",
    "addr:housenumber":"112",
    "addr:postcode":"9300",
    "iso:country":"BE",
    "sg:address":"Immerzeeldreef 112",
    "sg:city":"Aalst",
    "sg:orig_category":"Enseignement maternel and primaire",
    "sg:phone":"+32 53 77 48 26",
    "sg:postcode":"9300",
    "sg:province":"Oost-Vlaanderen",
    "wof:name":"Vrije Basisschool",
    "wof:placetype":"venue"
},
  "geometry": {"coordinates":[4.0708618164,50.9302902222],"type":"Point"}
}