{
  "type": "Feature",
  "properties": {
    "iso:country":"BE",
    "sg:address":"Stationstraat 169-173",
    "sg:city":"Moorslede",
    "sg:classifiers":[
        {
            "category":"Retail",
            "subcategory":"Repair Shop",
            "type":"Services"
        }
    ],
    "sg:phone":"+32 51 77 81 05",
    "sg:postcode":"8890",
    "sg:province":"West-Vlaanderen",
    "sg:tags":[
        "radio",
        "television",
        "-",
        "maintenance"
    ],
    "wof:name":"Saelens T.c. Nv",
    "wof:placetype":"venue"
},
  "geometry": {"coordinates":[3.0405580997,50.8941307068],"type":"Point"}
}