{
  "type": "Feature",
  "properties": {
    "addr:full":"Maagdekensdelle 17 Tervuren (grand) Vlaams-Brabant 3080",
    "addr:housenumber":"17",
    "addr:postcode":"3080",
    "addr:street":"Maagdekensdelle",
    "iso:country":"BE",
    "sg:address":"Maagdekensdelle 17",
    "sg:city":"Tervuren (grand)",
    "sg:classifiers":[
        {
            "category":"Personal",
            "subcategory":"Beauty Salon",
            "type":"Services"
        }
    ],
    "sg:phone":"+32 2 767 50 99",
    "sg:postcode":"3080",
    "sg:province":"Vlaams-Brabant",
    "sg:tags":[
        "de",
        "coiffure"
    ],
    "wof:name":"Coiffure Arlette",
    "wof:placetype":"venue"
},
  "geometry": {"coordinates":[4.562526226,50.8325958252],"type":"Point"}
}