{
  "type": "Feature",
  "properties": {
    "addr:full":"La Brisedreef 6b2 Watermaal-bosvoorde/watermael-boitsfort Bruxelles-Capitale 1170",
    "addr:postcode":"1170",
    "iso:country":"BE",
    "sg:address":"La Brisedreef 6b2",
    "sg:city":"Watermaal-bosvoorde/watermael-boitsfort",
    "sg:orig_category":"Boekhouders",
    "sg:phone":"+32 2 673 73 92",
    "sg:postcode":"1170",
    "sg:province":"Bruxelles-Capitale",
    "wof:name":"B\u00c9atrice Bouchat",
    "wof:placetype":"venue"
},
  "geometry": {"coordinates":[4.4146208763,50.7995491028],"type":"Point"}
}