{
  "type": "Feature",
  "properties": {
    "iso:country":"BE",
    "sg:address":"Peter Benoitlaan 18",
    "sg:city":"Veurne",
    "sg:classifiers":[
        {
            "category":"Health Services",
            "subcategory":"Doctor",
            "type":"Services"
        }
    ],
    "sg:phone":"+32 58 31 15 25",
    "sg:postcode":"8630",
    "sg:province":"West-Vlaanderen",
    "sg:tags":[
        "medicinephysicians",
        "surgeon"
    ],
    "wof:name":"Joos Els",
    "wof:placetype":"venue"
},
  "geometry": {"coordinates":[2.6613240242,51.0693855286],"type":"Point"}
}