{
  "type": "Feature",
  "properties": {
    "iso:country":"BE",
    "sg:address":"Rue Massart 4ba",
    "sg:city":"Court-saint-etienne",
    "sg:classifiers":[
        {
            "category":"Building & Trades",
            "subcategory":"Equipment Rental",
            "type":"Services"
        }
    ],
    "sg:phone":"+32 10 61 77 57",
    "sg:postcode":"1490",
    "sg:province":"Brabant Wallon",
    "sg:tags":[
        "de",
        "\u00e9v\u00e9nements",
        "pour",
        "mat\u00e9riel",
        "location",
        "banquet"
    ],
    "wof:name":"Fe. Dubuis Chapiteaux",
    "wof:placetype":"venue"
},
  "geometry": {"coordinates":[4.557721138,50.6163787842],"type":"Point"}
}