{
  "type": "Feature",
  "properties": {
    "addr:full":"Avenue Herbofin 16b Libramont-chevigny (libramont) Luxembourg 6800",
    "addr:housenumber":"16b",
    "addr:postcode":"6800",
    "addr:street":"Avenue Herbofin",
    "iso:country":"BE",
    "sg:address":"Avenue Herbofin 16b",
    "sg:city":"Libramont-chevigny (libramont)",
    "sg:classifiers":[
        {
            "category":"Health Services",
            "subcategory":"Hospital",
            "type":"Services"
        }
    ],
    "sg:phone":"+32 61 22 59 17",
    "sg:postcode":"6800",
    "sg:province":"Luxembourg",
    "wof:name":"Arista",
    "wof:placetype":"venue"
},
  "geometry": {"coordinates":[5.3761348724,49.9199943542],"type":"Point"}
}