{
  "type": "Feature",
  "properties": {
    "addr:full":"Parijseweg 36 Kapellen Antwerpen 2950",
    "addr:housenumber":"36",
    "addr:postcode":"2950",
    "addr:street":"Parijseweg",
    "iso:country":"BE",
    "sg:address":"Parijseweg 36",
    "sg:city":"Kapellen",
    "sg:classifiers":[
        {
            "category":"Building & Trades",
            "subcategory":"Landscaping Services",
            "type":"Services"
        }
    ],
    "sg:phone":"+32 3 664 85 50",
    "sg:postcode":"2950",
    "sg:province":"Antwerpen",
    "sg:tags":[
        "gardening",
        "garden",
        "maintenance"
    ],
    "wof:name":"Cromheeke P",
    "wof:placetype":"venue"
},
  "geometry": {"coordinates":[4.4003520012,51.3221321106],"type":"Point"}
}