{
  "type": "Feature",
  "properties": {
    "iso:country":"BE",
    "sg:address":"Alberic Deleustraat 18",
    "sg:city":"Torhout",
    "sg:orig_category":"Slagers",
    "sg:phone":"+32 50 21 21 39",
    "sg:postcode":"8820",
    "sg:province":"West-Vlaanderen",
    "wof:name":"Rik Dekoninck",
    "wof:placetype":"venue"
},
  "geometry": {"coordinates":[3.0662379265,51.0918807983],"type":"Point"}
}