{
  "type": "Feature",
  "properties": {
    "iso:country":"BE",
    "sg:address":"Lage Kaart 185",
    "sg:city":"Brasschaat",
    "sg:orig_category":"Non-Classified Establishments",
    "sg:phone":"+32 3 651 58 20",
    "sg:postcode":"2930",
    "sg:province":"Antwerpen",
    "wof:name":"Vaessen Audio Design",
    "wof:placetype":"venue"
},
  "geometry": {"coordinates":[4.4773540497,51.2984085083],"type":"Point"}
}