{
  "type": "Feature",
  "properties": {
    "addr:full":"Oosteeklo-dorp 70 Assenede (oosteeklo) Oost-Vlaanderen 9968",
    "addr:housenumber":"70",
    "addr:postcode":"9968",
    "addr:street":"Oosteeklo-Dorp",
    "iso:country":"BE",
    "sg:address":"Oosteeklo-dorp 70",
    "sg:city":"Assenede (oosteeklo)",
    "sg:classifiers":[
        {
            "category":"Retail",
            "subcategory":"Repair Shop",
            "type":"Services"
        }
    ],
    "sg:phone":"+32 9 373 89 62",
    "sg:postcode":"9968",
    "sg:province":"Oost-Vlaanderen",
    "wof:name":"Mathieu L",
    "wof:placetype":"venue"
},
  "geometry": {"coordinates":[3.6859459877,51.1901245117],"type":"Point"}
}