{
  "type": "Feature",
  "properties": {
    "addr:full":"Rue Des Am\u00c9ricains 95 Mons Hainaut 7022",
    "addr:housenumber":"95",
    "addr:postcode":"7022",
    "addr:street":"Rue Des Ame\u0301Ricains;Hainaut",
    "iso:country":"BE",
    "sg:address":"Rue Des Am\u00c9ricains 95",
    "sg:city":"Mons",
    "sg:orig_category":"Installatie van houten of kunststof schrijnwerk",
    "sg:phone":"+32 65 36 25 67",
    "sg:postcode":"7022",
    "sg:province":"Hainaut",
    "wof:name":"Christophe Hoyois",
    "wof:placetype":"venue"
},
  "geometry": {"coordinates":[3.9613599777,50.4351081848],"type":"Point"}
}