{
  "type": "Feature",
  "properties": {
    "addr:full":"Rue De L'eglise 17 Berloz (corswarem) Li\u00e8ge 4257",
    "addr:housenumber":"17",
    "addr:postcode":"4257",
    "addr:street":"Rue De L'Eglise;Corswarem",
    "iso:country":"BE",
    "sg:address":"Rue De L'eglise 17",
    "sg:city":"Berloz (corswarem)",
    "sg:classifiers":[
        {
            "category":"Bakery",
            "type":"Food & Drink"
        }
    ],
    "sg:phone":"+32 19 32 28 39",
    "sg:postcode":"4257",
    "sg:province":"Li\u00e8ge",
    "sg:tags":[
        "confectioner",
        "baker"
    ],
    "wof:name":"Pierard G",
    "wof:placetype":"venue"
},
  "geometry": {"coordinates":[5.217523098,50.7086334229],"type":"Point"}
}