{
  "type": "Feature",
  "properties": {
    "addr:full":"Steenweg Weelde 68a Ravels (poppel) Antwerpen 2382",
    "addr:housenumber":"68a",
    "addr:postcode":"2382",
    "addr:street":"Steenweg Weelde",
    "iso:country":"BE",
    "sg:address":"Steenweg Weelde 68a",
    "sg:city":"Ravels (poppel)",
    "sg:classifiers":[
        {
            "category":"Retail",
            "subcategory":"Auto Repair",
            "type":"Services"
        }
    ],
    "sg:phone":"+32 14 65 51 94",
    "sg:postcode":"2382",
    "sg:province":"Antwerpen",
    "sg:tags":[
        "garage"
    ],
    "wof:name":"Jochems Garage Bvba",
    "wof:placetype":"venue"
},
  "geometry": {"coordinates":[5.041768074,51.4469108582],"type":"Point"}
}