{
  "type": "Feature",
  "properties": {
    "iso:country":"BE",
    "sg:address":"Rue Des Mog\u00c9s 2",
    "sg:city":"Neupre",
    "sg:orig_category":"SMEEDWERK, METAALBEWERKING AND POEDERMETALLURGIE",
    "sg:phone":"+32 4 371 24 18",
    "sg:postcode":"4120",
    "sg:province":"Li\u00e8ge",
    "wof:name":"Parent",
    "wof:placetype":"venue"
},
  "geometry": {"coordinates":[5.480410099,50.5349159241],"type":"Point"}
}