{
  "type": "Feature",
  "properties": {
    "iso:country":"BE",
    "sg:address":"Route De Marche 37",
    "sg:city":"Durbuy (barvaux-sur-ourthe)",
    "sg:classifiers":[
        {
            "category":"Banks & Credit Unions",
            "subcategory":"Financial Services",
            "type":"Services"
        }
    ],
    "sg:phone":"+32 86 21 19 44",
    "sg:postcode":"6940",
    "sg:province":"Luxembourg",
    "sg:tags":[
        "financing"
    ],
    "wof:name":"Kinet L",
    "wof:placetype":"venue"
},
  "geometry": {"coordinates":[5.4543361664,50.3515777588],"type":"Point"}
}