{
  "type": "Feature",
  "properties": {
    "addr:full":"Zilverstraat 28 Grimbergen Vlaams-Brabant 1850",
    "addr:housenumber":"28",
    "addr:postcode":"1850",
    "addr:street":"Zilverstraat",
    "iso:country":"BE",
    "sg:address":"Zilverstraat 28",
    "sg:city":"Grimbergen",
    "sg:classifiers":[
        {
            "category":"Banks & Credit Unions",
            "subcategory":"Bureau De Change",
            "type":"Services"
        }
    ],
    "sg:phone":"+32 2 270 98 53",
    "sg:postcode":"1850",
    "sg:province":"Vlaams-Brabant",
    "sg:tags":[
        "measuring",
        "control",
        "apparatus"
    ],
    "wof:name":"M E C Industries",
    "wof:placetype":"venue"
},
  "geometry": {"coordinates":[4.3694758415,50.923324585],"type":"Point"}
}