{
  "type": "Feature",
  "properties": {
    "iso:country":"BE",
    "sg:address":"Rue Des D\u00e9port\u00e9s 12a",
    "sg:city":"Rumes",
    "sg:classifiers":[
        {
            "category":"Arena",
            "subcategory":"Sports Club",
            "type":"Entertainment"
        }
    ],
    "sg:phone":"+32 69 64 00 01",
    "sg:postcode":"7610",
    "sg:province":"Hainaut",
    "wof:name":"Football Club Rumois",
    "wof:placetype":"venue"
},
  "geometry": {"coordinates":[3.305891037,50.5462608337],"type":"Point"}
}