{
  "type": "Feature",
  "properties": {
    "addr:full":"Rue Neufcour 49 Beyne-heusay Li\u00e8ge 4610",
    "addr:housenumber":"49",
    "addr:postcode":"4610",
    "addr:street":"Rue Neufcour",
    "iso:country":"BE",
    "sg:address":"Rue Neufcour 49",
    "sg:city":"Beyne-heusay",
    "sg:orig_category":"Binnenhuisarchitecten",
    "sg:phone":"+32 4 358 88 08",
    "sg:postcode":"4610",
    "sg:province":"Li\u00e8ge",
    "wof:name":"Industr. Design Marechal",
    "wof:placetype":"venue"
},
  "geometry": {"coordinates":[5.6503000259,50.6227989197],"type":"Point"}
}