{
  "type": "Feature",
  "properties": {
    "addr:full":"Beninksstraat 45 Rotselaar Vlaams-Brabant 3111",
    "addr:housenumber":"45",
    "addr:postcode":"3111",
    "addr:street":"Beninksstraat",
    "iso:country":"BE",
    "sg:address":"Beninksstraat 45",
    "sg:city":"Rotselaar",
    "sg:orig_category":"Producteurs de fruits. Producteurs de l\u00e9gumes",
    "sg:phone":"+32 16 58 02 51",
    "sg:postcode":"3111",
    "sg:province":"Vlaams-Brabant",
    "wof:name":"Georges Vandezande",
    "wof:placetype":"venue"
},
  "geometry": {"coordinates":[4.7733421326,50.9477424622],"type":"Point"}
}