{
  "type": "Feature",
  "properties": {
    "addr:full":"Rue Omer Houssi\u00c8re 38 La Louviere Hainaut 7110",
    "addr:housenumber":"38",
    "addr:postcode":"7110",
    "addr:street":"Rue Omer Houssie\u0300Re",
    "iso:country":"BE",
    "sg:address":"Rue Omer Houssi\u00c8re 38",
    "sg:city":"La Louviere",
    "sg:classifiers":[
        {
            "category":"Personal",
            "subcategory":"Beauty Salon",
            "type":"Services"
        }
    ],
    "sg:phone":"+32 64 67 55 28",
    "sg:postcode":"7110",
    "sg:province":"Hainaut",
    "sg:tags":[
        "de",
        "coiffure"
    ],
    "wof:name":"Coiffure Ideastyle",
    "wof:placetype":"venue"
},
  "geometry": {"coordinates":[4.1505050659,50.4826698303],"type":"Point"}
}