{
  "type": "Feature",
  "properties": {
    "addr:full":"Henri Horriestraat 33 Roeselare West-Vlaanderen 8800",
    "addr:housenumber":"33",
    "addr:postcode":"8800",
    "addr:street":"Henri Horriestraat",
    "iso:country":"BE",
    "sg:address":"Henri Horriestraat 33",
    "sg:city":"Roeselare",
    "sg:orig_category":"S\u00e9curit\u00e9 sociale",
    "sg:phone":"+32 51 22 05 13",
    "sg:postcode":"8800",
    "sg:province":"West-Vlaanderen",
    "wof:name":"Christ.mut.verb.roeselare",
    "wof:placetype":"venue"
},
  "geometry": {"coordinates":[3.1240539551,50.9477386475],"type":"Point"}
}