{
  "type": "Feature",
  "properties": {
    "addr:full":"Rue Lambotte 2 Colfontaine (wasmes) Hainaut 7340",
    "addr:housenumber":"2",
    "addr:postcode":"7340",
    "addr:street":"Rue Lambotte",
    "iso:country":"BE",
    "sg:address":"Rue Lambotte 2",
    "sg:city":"Colfontaine (wasmes)",
    "sg:classifiers":[
        {
            "category":"Shopping",
            "subcategory":"Crafts & Fabrics",
            "type":"Retail Goods"
        }
    ],
    "sg:phone":"+32 65 78 52 78",
    "sg:postcode":"7340",
    "sg:province":"Hainaut",
    "sg:tags":[
        "paints",
        "varnish",
        "-",
        "lacquers",
        "enamel"
    ],
    "wof:name":"Dragopaint",
    "wof:placetype":"venue"
},
  "geometry": {"coordinates":[3.8447840214,50.4241294861],"type":"Point"}
}