{
  "type": "Feature",
  "properties": {
    "addr:full":"Kontichsesteenweg 21 Aartselaar Antwerpen 2630",
    "addr:housenumber":"21",
    "addr:postcode":"2630",
    "addr:street":"Kontichsesteenweg",
    "iso:country":"BE",
    "sg:address":"Kontichsesteenweg 21",
    "sg:city":"Aartselaar",
    "sg:classifiers":[
        {
            "category":"Manufacturing",
            "subcategory":"Metals",
            "type":"Manufacturing & Wholesale Goods"
        }
    ],
    "sg:phone":"+32 3 887 53 36",
    "sg:postcode":"2630",
    "sg:province":"Antwerpen",
    "sg:tags":[
        "-",
        "machine",
        "equipment",
        "engineering",
        "machinery",
        "mechanical"
    ],
    "wof:name":"P Gillard Bvba",
    "wof:placetype":"venue"
},
  "geometry": {"coordinates":[4.3831658363,51.14295578],"type":"Point"}
}