{
  "type": "Feature",
  "properties": {
    "addr:full":"Montenegrostraat 60 Sint-gillis/saint-gilles Bruxelles-Capitale 1060",
    "addr:housenumber":"60",
    "addr:postcode":"1060",
    "addr:street":"Montenegrostraat",
    "iso:country":"BE",
    "sg:address":"Montenegrostraat 60",
    "sg:city":"Sint-gillis/saint-gilles",
    "sg:orig_category":"Slagers",
    "sg:phone":"+32 2 537 20 47",
    "sg:postcode":"1060",
    "sg:province":"Bruxelles-Capitale",
    "wof:name":"Abderrahman Atia",
    "wof:placetype":"venue"
},
  "geometry": {"coordinates":[4.3361148834,50.8270492554],"type":"Point"}
}