{
  "type": "Feature",
  "properties": {
    "iso:country":"BE",
    "sg:address":"Industriepark 57a",
    "sg:city":"Beernem",
    "sg:orig_category":"Installation de menuiserie en bois and plastique",
    "sg:phone":"+32 50 78 01 16",
    "sg:postcode":"8730",
    "sg:province":"West-Vlaanderen",
    "wof:name":"G. Pieyns",
    "wof:placetype":"venue"
},
  "geometry": {"coordinates":[3.3454170227,51.1249961853],"type":"Point"}
}