{
  "type": "Feature",
  "properties": {
    "iso:country":"BE",
    "sg:address":"Frankrijkstraat 51",
    "sg:city":"Gooik",
    "sg:orig_category":"Telecommunicatieapparaten",
    "sg:phone":"+32 475 61 78 99",
    "sg:postcode":"1755",
    "sg:province":"Vlaams-Brabant",
    "wof:name":"Kv Comp",
    "wof:placetype":"venue"
},
  "geometry": {"coordinates":[4.0699620247,50.7681655884],"type":"Point"}
}