{
  "type": "Feature",
  "properties": {
    "addr:full":"Antwerpsesteenweg 439 Malle Antwerpen 2390",
    "addr:housenumber":"439",
    "addr:postcode":"2390",
    "addr:street":"Antwerpsesteenweg",
    "iso:country":"BE",
    "sg:address":"Antwerpsesteenweg 439",
    "sg:city":"Malle",
    "sg:orig_category":"Restaurants Ruimtes voor conferenties, recepties and feesten",
    "sg:phone":"+32 3 312 51 11",
    "sg:postcode":"2390",
    "sg:province":"Antwerpen",
    "wof:name":"\u00b4t Geel Grilleke",
    "wof:placetype":"venue"
},
  "geometry": {"coordinates":[4.6737108231,51.2895317078],"type":"Point"}
}