{
  "type": "Feature",
  "properties": {
    "iso:country":"BE",
    "sg:address":"Kempenplein 2",
    "sg:city":"Neerpelt",
    "sg:classifiers":[
        {
            "category":"Shopping",
            "subcategory":"Clothing, Apparel, & Fashions",
            "type":"Retail Goods"
        }
    ],
    "sg:phone":"+32 11 66 24 96",
    "sg:postcode":"3910",
    "sg:province":"Limburg",
    "sg:tags":[
        "lingerie",
        "sous-v\u00eatements"
    ],
    "wof:name":"Di Novo Casa",
    "wof:placetype":"venue"
},
  "geometry": {"coordinates":[5.4333620071,51.2282981873],"type":"Point"}
}