{
  "type": "Feature",
  "properties": {
    "addr:full":"Rue Mon Plaisir 2 Ittre Brabant Wallon 1460",
    "addr:housenumber":"2;1460",
    "addr:street":"Rue Mon Plaisir",
    "iso:country":"BE",
    "sg:address":"Rue Mon Plaisir 2",
    "sg:city":"Ittre",
    "sg:orig_category":"Rundveehouders",
    "sg:phone":"+32 67 64 63 77",
    "sg:postcode":"1460",
    "sg:province":"Brabant Wallon",
    "wof:name":"Luc Godart",
    "wof:placetype":"venue"
},
  "geometry": {"coordinates":[4.2299661636,50.6321144104],"type":"Point"}
}