{
  "type": "Feature",
  "properties": {
    "iso:country":"BE",
    "sg:address":"Twee Huizenstraat 57a",
    "sg:city":"Brussel",
    "sg:classifiers":[
        {
            "category":"Manufacturing",
            "subcategory":"Paper Products",
            "type":"Manufacturing & Wholesale Goods"
        }
    ],
    "sg:phone":"+32 2 242 37 00",
    "sg:postcode":"1140",
    "sg:province":"Bruxelles-Capitale",
    "sg:tags":[
        "device",
        "binding",
        "systems"
    ],
    "wof:name":"Gmp Belgium-bibliofilm Nv",
    "wof:placetype":"venue"
},
  "geometry": {"coordinates":[4.4183878899,50.8604125977],"type":"Point"}
}