{
  "type": "Feature",
  "properties": {
    "addr:full":"Lichterstraat 39 Puurs Antwerpen 2870",
    "addr:housenumber":"39",
    "addr:postcode":"2870",
    "addr:street":"Lichterstraat",
    "iso:country":"BE",
    "sg:address":"Lichterstraat 39",
    "sg:city":"Puurs",
    "sg:classifiers":[
        {
            "category":"Military Area",
            "subcategory":"Air Force Base",
            "type":"Public Place"
        }
    ],
    "sg:phone":"+32 3 326 75 70",
    "sg:postcode":"2870",
    "sg:province":"Antwerpen",
    "sg:tags":[
        "window",
        "skylight",
        "dormer"
    ],
    "wof:name":"Plastiek Van Wauwe B.v.b.a.",
    "wof:placetype":"venue"
},
  "geometry": {"coordinates":[4.4695701599,51.2332038879],"type":"Point"}
}