{
  "type": "Feature",
  "properties": {
    "iso:country":"BE",
    "sg:address":"Place Du Vingt-ao\u00dbt 13",
    "sg:city":"Li\u00c8ge",
    "sg:orig_category":"Art and fournitures artistiques",
    "sg:phone":"+32 4 222 23 23",
    "sg:postcode":"4000",
    "sg:province":"Li\u00e8ge",
    "wof:name":"Affiche Ancienne",
    "wof:placetype":"venue"
},
  "geometry": {"coordinates":[5.5760521889,50.6399497986],"type":"Point"}
}