{
  "type": "Feature",
  "properties": {
    "addr:full":"Ondernemingenstraat 4 Veurne West-Vlaanderen 8630",
    "addr:housenumber":"4",
    "addr:postcode":"8630",
    "addr:street":"Ondernemingenstraat",
    "iso:country":"BE",
    "sg:address":"Ondernemingenstraat 4",
    "sg:city":"Veurne",
    "sg:classifiers":[
        {
            "category":"Banks & Credit Unions",
            "subcategory":"Investment Brokerage",
            "type":"Services"
        }
    ],
    "sg:phone":"+32 58 31 11 22",
    "sg:postcode":"8630",
    "sg:province":"West-Vlaanderen",
    "sg:tags":[
        "varnishing",
        "firms",
        "industrial"
    ],
    "wof:name":"Bonaventure J. B.v.b.a.",
    "wof:placetype":"venue"
},
  "geometry": {"coordinates":[2.677850008,51.0620689392],"type":"Point"}
}