{
  "type": "Feature",
  "properties": {
    "addr:full":"Venlosesteenweg 23 Kinrooi Limburg 3640",
    "addr:housenumber":"23",
    "addr:postcode":"3640",
    "addr:street":"Venlosesteenweg",
    "iso:country":"BE",
    "sg:address":"Venlosesteenweg 23",
    "sg:city":"Kinrooi",
    "sg:classifiers":[
        {
            "category":"Restaurant",
            "type":"Food & Drink"
        }
    ],
    "sg:phone":"+32 89 56 11 57",
    "sg:postcode":"3640",
    "sg:province":"Limburg",
    "wof:name":"Lunchroom De 7 Ambachten",
    "wof:placetype":"venue"
},
  "geometry": {"coordinates":[5.8008980751,51.1215934753],"type":"Point"}
}