{
  "type": "Feature",
  "properties": {
    "iso:country":"BE",
    "sg:address":"Bessemerstraat 165b1",
    "sg:city":"Lanaken",
    "sg:orig_category":"Boekhouders",
    "sg:phone":"+32 89 73 19 96",
    "sg:postcode":"3620",
    "sg:province":"Limburg",
    "wof:name":"Guido Stouten",
    "wof:placetype":"venue"
},
  "geometry": {"coordinates":[5.6463618279,50.8933868408],"type":"Point"}
}