{
  "type": "Feature",
  "properties": {
    "iso:country":"BE",
    "sg:address":"Potaardestraat 25",
    "sg:city":"Temse",
    "sg:orig_category":"Mat\u00e9riel m\u00e9dical and orthop\u00e9dique and proth\u00e8ses Fab",
    "sg:phone":"+32 3 771 12 54",
    "sg:postcode":"9140",
    "sg:province":"Oost-Vlaanderen",
    "wof:name":"Van Hecke",
    "wof:placetype":"venue"
},
  "geometry": {"coordinates":[4.2262349129,51.1339607239],"type":"Point"}
}