{
  "type": "Feature",
  "properties": {
    "addr:full":"Kleine Zavelheide 62 Leopoldsburg Limburg 3970",
    "addr:housenumber":"62",
    "addr:postcode":"3970",
    "addr:street":"Kleine Zavelheide",
    "iso:country":"BE",
    "sg:address":"Kleine Zavelheide 62",
    "sg:city":"Leopoldsburg",
    "sg:orig_category":"Animations diverses",
    "sg:phone":"+32 11 40 12 40",
    "sg:postcode":"3970",
    "sg:province":"Limburg",
    "wof:name":"Flash-back",
    "wof:placetype":"venue"
},
  "geometry": {"coordinates":[5.2500681877,51.1097831726],"type":"Point"}
}