{
  "type": "Feature",
  "properties": {
    "addr:full":"Place Du Grand Sablon 9b6 Bruxelles/ Bruxelles-Capitale 1000",
    "addr:housenumber":"9b6",
    "addr:postcode":"1000",
    "addr:street":"Place Du Grand Sablon",
    "iso:country":"BE",
    "sg:address":"Place Du Grand Sablon 9b6",
    "sg:city":"Bruxelles/",
    "sg:classifiers":[
        {
            "category":"Restaurant",
            "type":"Food & Drink"
        }
    ],
    "sg:phone":"+32 2 502 05 09",
    "sg:postcode":"1000",
    "sg:province":"Bruxelles-Capitale",
    "wof:name":"Rest. Au Duc D'arenberg",
    "wof:placetype":"venue"
},
  "geometry": {"coordinates":[4.354883194,50.8413047791],"type":"Point"}
}