{
  "type": "Feature",
  "properties": {
    "addr:full":"Rue L\u00e9on G\u00e9nie 5 Celles (viemme) Li\u00e8ge 4317",
    "addr:housenumber":"5",
    "addr:postcode":"4317",
    "addr:street":"Rue Le\u0301On Ge\u0301Nie",
    "iso:country":"BE",
    "sg:address":"Rue L\u00e9on G\u00e9nie 5",
    "sg:city":"Celles (viemme)",
    "sg:classifiers":[
        {
            "category":"Health Services",
            "subcategory":"Health Practitioner",
            "type":"Services"
        }
    ],
    "sg:phone":"+32 19 32 67 66",
    "sg:postcode":"4317",
    "sg:province":"Li\u00e8ge",
    "sg:tags":[
        "physiotherapist"
    ],
    "wof:name":"Radoux Anne-cath\u00e9rine",
    "wof:placetype":"venue"
},
  "geometry": {"coordinates":[5.2618951797,50.6657218933],"type":"Point"}
}