{
  "type": "Feature",
  "properties": {
    "iso:country":"BE",
    "sg:address":"Waaslandlaan 8",
    "sg:city":"Lokeren",
    "sg:classifiers":[
        {
            "category":"Banks & Credit Unions",
            "subcategory":"Investment Brokerage",
            "type":"Services"
        }
    ],
    "sg:phone":"+32 9 349 46 10",
    "sg:postcode":"9160",
    "sg:province":"Oost-Vlaanderen",
    "sg:tags":[
        "fence"
    ],
    "wof:name":"Metalux Hekwerk",
    "wof:placetype":"venue"
},
  "geometry": {"coordinates":[4.0108809471,51.1206588745],"type":"Point"}
}