{
  "type": "Feature",
  "properties": {
    "iso:country":"BE",
    "sg:address":"Grand Thumas 15",
    "sg:city":"Beaumont",
    "sg:orig_category":"Installation de menuiserie m\u00e9tallique",
    "sg:phone":"+32 60 31 33 65",
    "sg:postcode":"6500",
    "sg:province":"Hainaut",
    "wof:name":"Innover & Construire",
    "wof:placetype":"venue"
},
  "geometry": {"coordinates":[4.2299208641,50.1884422302],"type":"Point"}
}