{
  "type": "Feature",
  "properties": {
    "iso:country":"BE",
    "sg:address":"Zonnestraat 94",
    "sg:city":"Ronse",
    "sg:classifiers":[
        {
            "category":"Professional",
            "subcategory":"Printing & Photocopies",
            "type":"Services"
        }
    ],
    "sg:phone":"+32 3 236 27 51",
    "sg:postcode":"9600",
    "sg:province":"Oost-Vlaanderen",
    "sg:tags":[
        "dry",
        "offset"
    ],
    "wof:name":"Onzea Nv",
    "wof:placetype":"venue"
},
  "geometry": {"coordinates":[4.4385948181,51.2125320435],"type":"Point"}
}