{
  "type": "Feature",
  "properties": {
    "addr:full":"Sint-eloois Winkelstraat 103 Ledegem West-Vlaanderen 8880",
    "addr:housenumber":"103",
    "addr:postcode":"8880",
    "addr:street":"Winkelstraat",
    "iso:country":"BE",
    "sg:address":"Sint-eloois Winkelstraat 103",
    "sg:city":"Ledegem",
    "sg:classifiers":[
        {
            "category":"Building & Trades",
            "subcategory":"Landscaping Services",
            "type":"Services"
        }
    ],
    "sg:phone":"+32 56 50 00 47",
    "sg:postcode":"8880",
    "sg:province":"West-Vlaanderen",
    "sg:tags":[
        "slaughterer"
    ],
    "wof:name":"Oplinus M",
    "wof:placetype":"venue"
},
  "geometry": {"coordinates":[3.1378118992,50.8576011658],"type":"Point"}
}