{
  "type": "Feature",
  "properties": {
    "iso:country":"BE",
    "sg:address":"Avenue Du Spirou 23",
    "sg:city":"Fleurus",
    "sg:orig_category":"Boekbinderijen and afwerking",
    "sg:phone":"+32 71 81 01 01",
    "sg:postcode":"6220",
    "sg:province":"Hainaut",
    "wof:name":"Helio Charleroi",
    "wof:placetype":"venue"
},
  "geometry": {"coordinates":[4.537735939,50.4556541443],"type":"Point"}
}