{
  "type": "Feature",
  "properties": {
    "addr:full":"Heidelbergstraat 22 Zedelgem (loppem) West-Vlaanderen 8210",
    "addr:housenumber":"22",
    "addr:postcode":"8210",
    "addr:street":"Heidelbergstraat",
    "iso:country":"BE",
    "sg:address":"Heidelbergstraat 22",
    "sg:city":"Zedelgem (loppem)",
    "sg:classifiers":[
        {
            "category":"Home & Garden",
            "subcategory":"Building Materials",
            "type":"Retail Goods"
        }
    ],
    "sg:phone":"+32 50 82 29 06",
    "sg:postcode":"8210",
    "sg:province":"West-Vlaanderen",
    "sg:tags":[
        "article",
        "-",
        "do-it-yourself"
    ],
    "wof:name":"Clovan - Alltrading Nv",
    "wof:placetype":"venue"
},
  "geometry": {"coordinates":[3.1458399296,51.1376457214],"type":"Point"}
}