{
  "type": "Feature",
  "properties": {
    "iso:country":"BE",
    "sg:address":"Rode-rokstraat 132",
    "sg:city":"Hasselt",
    "sg:orig_category":"Eleveurs de bovins",
    "sg:phone":"+32 11 25 22 65",
    "sg:postcode":"3511",
    "sg:province":"Limburg",
    "wof:name":"Rene Gelders",
    "wof:placetype":"venue"
},
  "geometry": {"coordinates":[5.2955589294,50.9501152039],"type":"Point"}
}