{
  "type": "Feature",
  "properties": {
    "iso:country":"BE",
    "sg:address":"Merksplassebaan 80",
    "sg:city":"Malle (oostmalle)",
    "sg:classifiers":[
        {
            "category":"Building & Trades",
            "subcategory":"Pest Control",
            "type":"Services"
        }
    ],
    "sg:phone":"+32 3 312 49 06",
    "sg:postcode":"2390",
    "sg:province":"Antwerpen",
    "sg:tags":[
        "painting",
        "contractor"
    ],
    "wof:name":"Van Gestel F",
    "wof:placetype":"venue"
},
  "geometry": {"coordinates":[4.744820118,51.3089599609],"type":"Point"}
}