{
  "type": "Feature",
  "properties": {
    "iso:country":"BE",
    "sg:address":"Sint-pieterszuidstraat 39",
    "sg:city":"Brugge",
    "sg:orig_category":"Groenten and fruit Gh",
    "sg:phone":"+32 50 31 63 72",
    "sg:postcode":"8000",
    "sg:province":"West-Vlaanderen",
    "wof:name":"Denaeghel",
    "wof:placetype":"venue"
},
  "geometry": {"coordinates":[3.2059500217,51.252571106],"type":"Point"}
}