{
  "type": "Feature",
  "properties": {
    "iso:country":"BE",
    "sg:address":"Kortrijkseheerweg 20",
    "sg:city":"Nazareth",
    "sg:orig_category":"Eleveurs and marchands de porcs. Eleveurs de bovins",
    "sg:phone":"+32 9 385 40 68",
    "sg:postcode":"9810",
    "sg:province":"Oost-Vlaanderen",
    "wof:name":"R Cnockaert",
    "wof:placetype":"venue"
},
  "geometry": {"coordinates":[3.6061871052,50.9752960205],"type":"Point"}
}