{
  "type": "Feature",
  "properties": {
    "iso:country":"BE",
    "sg:address":"Jevoumont 43b",
    "sg:city":"Theux",
    "sg:orig_category":"Kampeerterreinen",
    "sg:phone":"+32 87 54 15 45",
    "sg:postcode":"4910",
    "sg:province":"Li\u00e8ge",
    "wof:name":"Camping Barri\u00c8res Bleues",
    "wof:placetype":"venue"
},
  "geometry": {"coordinates":[5.8069200516,50.5243186951],"type":"Point"}
}