{
  "type": "Feature",
  "properties": {
    "iso:country":"BE",
    "sg:address":"Rue De Luins 3",
    "sg:city":"Sy Station",
    "sg:orig_category":"H\u00f4tels",
    "sg:phone":"+32 86 38 80 46",
    "sg:postcode":"4190",
    "sg:province":"Li\u00e8ge",
    "wof:name":"Au Repos Du Cheval Blanc",
    "wof:placetype":"venue"
},
  "geometry": {"coordinates":[5.6052899361,50.4007606506],"type":"Point"}
}