{
  "type": "Feature",
  "properties": {
    "addr:full":"Rue De Neufchateau 112 Arlon Luxembourg 6700",
    "addr:housenumber":"112",
    "addr:postcode":"6700",
    "addr:street":"Rue De Neufchateau",
    "iso:country":"BE",
    "sg:address":"Rue De Neufchateau 112",
    "sg:city":"Arlon",
    "sg:orig_category":"Instituts de beaut\u00e9",
    "sg:phone":"+32 63 21 62 03",
    "sg:postcode":"6700",
    "sg:province":"Luxembourg",
    "wof:name":"Marie Hesse",
    "wof:placetype":"venue"
},
  "geometry": {"coordinates":[5.8029470444,49.6855354309],"type":"Point"}
}