{
  "type": "Feature",
  "properties": {
    "addr:full":"Rue Du Fond-des-naux 7 Florenville Luxembourg 6821",
    "addr:housenumber":"7",
    "addr:postcode":"6821",
    "addr:street":"Rue Du Fond-Des-Naux",
    "iso:country":"BE",
    "sg:address":"Rue Du Fond-des-naux 7",
    "sg:city":"Florenville",
    "sg:orig_category":"Catering and organisation de f\u00eates. H\u00f4tels. Restaurants fast food and \u00e0 emporter. Restaurants. Resta",
    "sg:phone":"+32 61 31 11 40",
    "sg:postcode":"6821",
    "sg:province":"Luxembourg",
    "wof:name":"Auberge De La Vall\u00c9e",
    "wof:placetype":"venue"
},
  "geometry": {"coordinates":[5.3185172081,49.7181854248],"type":"Point"}
}