{
  "type": "Feature",
  "properties": {
    "iso:country":"BE",
    "sg:address":"Rue Nationale 28",
    "sg:city":"Waremme (oleye)",
    "sg:classifiers":[
        {
            "category":"Banks & Credit Unions",
            "subcategory":"Financial Services",
            "type":"Services"
        }
    ],
    "sg:phone":"+32 19 32 30 09",
    "sg:postcode":"4300",
    "sg:province":"Li\u00e8ge",
    "sg:tags":[
        "loan",
        "mortgage"
    ],
    "wof:name":"Lambert A & Fils",
    "wof:placetype":"venue"
},
  "geometry": {"coordinates":[5.2795357704,50.7108421326],"type":"Point"}
}