{
  "type": "Feature",
  "properties": {
    "addr:full":"Tongersesteenweg 70 Sint-truiden Limburg 3800",
    "addr:housenumber":"70",
    "addr:postcode":"3800",
    "addr:street":"Tongersesteenweg",
    "iso:country":"BE",
    "sg:address":"Tongersesteenweg 70",
    "sg:city":"Sint-truiden",
    "sg:classifiers":[
        {
            "category":"Insurance",
            "subcategory":"Insurance Agent",
            "type":"Services"
        }
    ],
    "sg:phone":"+32 11 69 69 60",
    "sg:postcode":"3800",
    "sg:province":"Limburg",
    "sg:tags":[
        "verzekeringsmakelaars",
        "expert"
    ],
    "wof:name":"Verzekeringen Boonen",
    "wof:placetype":"venue"
},
  "geometry": {"coordinates":[5.1948218346,50.8120307922],"type":"Point"}
}