{
  "type": "Feature",
  "properties": {
    "iso:country":"BE",
    "sg:address":"Meysbrug 3",
    "sg:city":"Mechelen",
    "sg:classifiers":[
        {
            "category":"Professional",
            "subcategory":"Art Services",
            "type":"Services"
        }
    ],
    "sg:phone":"+32 15 20 37 66",
    "sg:postcode":"2800",
    "sg:province":"Antwerpen",
    "sg:tags":[
        "-",
        "painter",
        "artist"
    ],
    "wof:name":"Brouwers",
    "wof:placetype":"venue"
},
  "geometry": {"coordinates":[4.4850621223,51.0264091492],"type":"Point"}
}