{
  "type": "Feature",
  "properties": {
    "addr:full":"Kattestraat 59a Heist-op-den-berg Antwerpen 2220",
    "addr:housenumber":"59a",
    "addr:postcode":"2220",
    "addr:street":"Kattestraat",
    "iso:country":"BE",
    "sg:address":"Kattestraat 59a",
    "sg:city":"Heist-op-den-berg",
    "sg:orig_category":"Secretariaatsdiensten",
    "sg:phone":"+32 15 25 18 66",
    "sg:postcode":"2220",
    "sg:province":"Antwerpen",
    "wof:name":"Parisis",
    "wof:placetype":"venue"
},
  "geometry": {"coordinates":[4.7170791626,51.074306488],"type":"Point"}
}