{
  "type": "Feature",
  "properties": {
    "iso:country":"BE",
    "sg:address":"Tongersesteenweg 267",
    "sg:city":"Sint-truiden",
    "sg:orig_category":"Voertuigen",
    "sg:phone":"+32 11 68 31 39",
    "sg:postcode":"3800",
    "sg:province":"Limburg",
    "wof:name":"Garage Raepers",
    "wof:placetype":"venue"
},
  "geometry": {"coordinates":[5.2143378258,50.8103065491],"type":"Point"}
}