{
  "type": "Feature",
  "properties": {
    "addr:full":"Dorpsstraat 37 Brugge (sint-michiels) West-Vlaanderen 8200",
    "addr:housenumber":"37",
    "addr:postcode":"8200",
    "addr:street":"Dorpsstraat",
    "iso:country":"BE",
    "sg:address":"Dorpsstraat 37",
    "sg:city":"Brugge (sint-michiels)",
    "sg:classifiers":[
        {
            "category":"Shopping",
            "subcategory":"Florist",
            "type":"Retail Goods"
        }
    ],
    "sg:phone":"+32 50 30 03 37",
    "sg:postcode":"8200",
    "sg:province":"West-Vlaanderen",
    "wof:name":"Geurig En Fleurig",
    "wof:placetype":"venue"
},
  "geometry": {"coordinates":[3.2145910263,51.1876411438],"type":"Point"}
}