{
  "type": "Feature",
  "properties": {
    "addr:full":"Waverse Steenweg 98 Elsene/ixelles Bruxelles-Capitale 1050",
    "addr:housenumber":"98",
    "addr:postcode":"1050",
    "addr:street":"Waverse Steenweg",
    "iso:country":"BE",
    "sg:address":"Waverse Steenweg 98",
    "sg:city":"Elsene/ixelles",
    "sg:orig_category":"Fotogravure and zetwerk Herstelling aan huis van huishoudartikelen Herstelling leer and schoeisel He",
    "sg:phone":"+32 2 511 28 08",
    "sg:postcode":"1050",
    "sg:province":"Bruxelles-Capitale",
    "wof:name":"Brussels Key Services",
    "wof:placetype":"venue"
},
  "geometry": {"coordinates":[4.3667640686,50.8366851807],"type":"Point"}
}