{
  "type": "Feature",
  "properties": {
    "addr:full":"Rue Fernand Houget 3 Verviers Li\u00e8ge 4800",
    "addr:housenumber":"3",
    "addr:postcode":"4800",
    "addr:street":"Rue Fernand Houget",
    "iso:country":"BE",
    "sg:address":"Rue Fernand Houget 3",
    "sg:city":"Verviers",
    "sg:orig_category":"Speelgoed Sport- and kampeermateriaal Verlichting and huishoudartikelen",
    "sg:phone":"+32 87 31 75 04",
    "sg:postcode":"4800",
    "sg:province":"Li\u00e8ge",
    "wof:name":"Blokker",
    "wof:placetype":"venue"
},
  "geometry": {"coordinates":[5.8476219177,50.5891036987],"type":"Point"}
}