{
  "type": "Feature",
  "properties": {
    "addr:full":"Avenue Du Val D'or 1 Namur (w\u00e9pion) Namur 5100",
    "addr:housenumber":"1",
    "addr:postcode":"5100",
    "addr:street":"Avenue Du Val D'Or",
    "iso:country":"BE",
    "sg:address":"Avenue Du Val D'or 1",
    "sg:city":"Namur (w\u00e9pion)",
    "sg:classifiers":[
        {
            "category":"Professional",
            "subcategory":"Lawyer & Legal Services",
            "type":"Services"
        }
    ],
    "sg:phone":"+32 475 51 42 36",
    "sg:postcode":"5100",
    "sg:province":"Namur",
    "wof:name":"Sacr\u00e9 Jean-fran\u00e7ois",
    "wof:placetype":"venue"
},
  "geometry": {"coordinates":[4.8670258522,50.4702224731],"type":"Point"}
}