{
  "type": "Feature",
  "properties": {
    "iso:country":"BE",
    "sg:address":"Avenue Des D\u00e9port\u00e9s 32",
    "sg:city":"Fosses-la-ville",
    "sg:classifiers":[
        {
            "category":"Autos & Motor Vehicles",
            "subcategory":"Automobile Sales",
            "type":"Retail Goods"
        }
    ],
    "sg:phone":"+32 71 71 11 58",
    "sg:postcode":"5070",
    "sg:province":"Namur",
    "sg:tags":[
        "car",
        "used",
        "-"
    ],
    "wof:name":"Mazuin Fosses Sa",
    "wof:placetype":"venue"
},
  "geometry": {"coordinates":[4.6827969551,50.3939666748],"type":"Point"}
}