{
  "type": "Feature",
  "properties": {
    "iso:country":"BE",
    "sg:address":"Avenue Baron Louis Huart 91b",
    "sg:city":"Namur",
    "sg:classifiers":[
        {
            "category":"Organizations",
            "subcategory":"Community Association",
            "type":"Services"
        }
    ],
    "sg:phone":"+32 81 22 10 42",
    "sg:postcode":"5000",
    "sg:province":"Namur",
    "sg:tags":[
        "cultural"
    ],
    "wof:name":"Institut Destr\u00e9e",
    "wof:placetype":"venue"
},
  "geometry": {"coordinates":[4.8654499054,50.4590187073],"type":"Point"}
}