{
  "type": "Feature",
  "properties": {
    "addr:full":"Burgmolenstraat 39 Alveringem West-Vlaanderen 8690",
    "addr:housenumber":"39",
    "addr:postcode":"8690",
    "addr:street":"Burgmolenstraat",
    "iso:country":"BE",
    "sg:address":"Burgmolenstraat 39",
    "sg:city":"Alveringem",
    "sg:orig_category":"Rundveehouders Varkenskwekers",
    "sg:phone":"+32 58 28 83 01",
    "sg:postcode":"8690",
    "sg:province":"West-Vlaanderen",
    "wof:name":"Elie Boedts",
    "wof:placetype":"venue"
},
  "geometry": {"coordinates":[2.6989049911,50.9899673462],"type":"Point"}
}