{
  "type": "Feature",
  "properties": {
    "iso:country":"BE",
    "sg:address":"Melkerijstraat 1",
    "sg:city":"Gierle",
    "sg:classifiers":[
        {
            "category":"Food & Beverages",
            "subcategory":"Cheese",
            "type":"Retail Goods"
        }
    ],
    "sg:phone":"+32 14 55 88 88",
    "sg:postcode":"2275",
    "sg:province":"Antwerpen",
    "wof:name":"Kempico C.v.",
    "wof:placetype":"venue"
},
  "geometry": {"coordinates":[4.8664212227,51.2684402466],"type":"Point"}
}