{
  "type": "Feature",
  "properties": {
    "addr:full":"Weertersteenweg 135 Maaseik Limburg 3680",
    "addr:housenumber":"135",
    "addr:postcode":"3680",
    "addr:street":"Weertersteenweg",
    "iso:country":"BE",
    "sg:address":"Weertersteenweg 135",
    "sg:city":"Maaseik",
    "sg:classifiers":[
        {
            "category":"Education",
            "subcategory":"School",
            "type":"Public Place"
        }
    ],
    "sg:phone":"+32 89 56 49 83",
    "sg:postcode":"3680",
    "sg:province":"Limburg",
    "sg:tags":[
        "secondary"
    ],
    "wof:name":"B.u.s.o. St-jansberg",
    "wof:placetype":"venue"
},
  "geometry": {"coordinates":[5.7776060104,51.1065788269],"type":"Point"}
}