{
  "type": "Feature",
  "properties": {
    "iso:country":"BE",
    "sg:address":"Lange Slachterijstraat 91",
    "sg:city":"Antwerpen",
    "sg:classifiers":[
        {
            "category":"Food & Beverages",
            "subcategory":"Meat & Fish",
            "type":"Retail Goods"
        }
    ],
    "sg:phone":"+32 3 235 67 72",
    "sg:postcode":"2060",
    "sg:province":"Antwerpen",
    "wof:name":"Krieckemans-goormans Nv",
    "wof:placetype":"venue"
},
  "geometry": {"coordinates":[4.4306278229,51.2294807434],"type":"Point"}
}