{
  "type": "Feature",
  "properties": {
    "addr:full":"Rue Courtejoie 12b2 Ciney Namur 5590",
    "addr:housenumber":"12b2",
    "addr:postcode":"5590",
    "addr:street":"Rue Courtejoie",
    "iso:country":"BE",
    "sg:address":"Rue Courtejoie 12b2",
    "sg:city":"Ciney",
    "sg:orig_category":"Avocats and conseillers juridiques",
    "sg:phone":"+32 83 21 47 23",
    "sg:postcode":"5590",
    "sg:province":"Namur",
    "wof:name":"B. Legros",
    "wof:placetype":"venue"
},
  "geometry": {"coordinates":[5.1004447937,50.2949905396],"type":"Point"}
}