{
  "type": "Feature",
  "properties": {
    "iso:country":"BE",
    "sg:address":"Everaertsstraat 51",
    "sg:city":"Antwerpen",
    "sg:classifiers":[
        {
            "category":"Real Estate",
            "subcategory":"Architect",
            "type":"Services"
        }
    ],
    "sg:phone":"+32 3 295 05 82",
    "sg:postcode":"2060",
    "sg:province":"Antwerpen",
    "wof:name":"Gennotte W",
    "wof:placetype":"venue"
},
  "geometry": {"coordinates":[4.4247589111,51.2272148132],"type":"Point"}
}