{
  "type": "Feature",
  "properties": {
    "addr:full":"Rue De Frizet 153 Namur (saint-marc) Namur 5003",
    "addr:housenumber":"153",
    "addr:postcode":"5003",
    "addr:street":"Rue De Frizet",
    "iso:country":"BE",
    "sg:address":"Rue De Frizet 153",
    "sg:city":"Namur (saint-marc)",
    "sg:orig_category":"Non-Classified Establishments",
    "sg:phone":"+32 81 74 62 96",
    "sg:postcode":"5003",
    "sg:province":"Namur",
    "wof:name":"Galettes Namuroise",
    "wof:placetype":"venue"
},
  "geometry": {"coordinates":[4.8473348618,50.4915008545],"type":"Point"}
}