{
  "type": "Feature",
  "properties": {
    "addr:full":"Avenue De L' Astronomie 19 Brussel (brussel) Bruxelles-Capitale 1210",
    "addr:housenumber":"19",
    "addr:postcode":"1210",
    "addr:street":"Avenue De L ' Astronomie",
    "iso:country":"BE",
    "sg:address":"Avenue De L' Astronomie 19",
    "sg:city":"Brussel (brussel)",
    "sg:classifiers":[
        {
            "category":"Insurance",
            "subcategory":"Life Insurance",
            "type":"Services"
        }
    ],
    "sg:phone":"+32 2 227 98 11",
    "sg:postcode":"1210",
    "sg:province":"Bruxelles-Capitale",
    "sg:tags":[
        "assurance"
    ],
    "wof:name":"Smap",
    "wof:placetype":"venue"
},
  "geometry": {"coordinates":[4.3693947792,50.851348877],"type":"Point"}
}