{
  "type": "Feature",
  "properties": {
    "iso:country":"BE",
    "sg:address":"Rue Emile Vandervelde 74",
    "sg:city":"Sambreville",
    "sg:orig_category":"Installation de menuiserie en bois and plastique",
    "sg:phone":"+32 71 74 29 11",
    "sg:postcode":"5060",
    "sg:province":"Namur",
    "wof:name":"Olivier Boigelot",
    "wof:placetype":"venue"
},
  "geometry": {"coordinates":[4.5818610191,50.4411849976],"type":"Point"}
}