{
  "type": "Feature",
  "properties": {
    "iso:country":"BE",
    "sg:address":"Rijselstraat 139",
    "sg:city":"Torhout",
    "sg:orig_category":"Slagers",
    "sg:phone":"+32 50 21 21 65",
    "sg:postcode":"8820",
    "sg:province":"West-Vlaanderen",
    "wof:name":"Slagerij Denolf",
    "wof:placetype":"venue"
},
  "geometry": {"coordinates":[3.1033110619,51.056438446],"type":"Point"}
}