{
  "type": "Feature",
  "properties": {
    "addr:full":"Rue De Warnoumont 58 Sprimont Li\u00e8ge 4140",
    "addr:housenumber":"58",
    "addr:postcode":"4140",
    "addr:street":"Rue De Warnoumont",
    "iso:country":"BE",
    "sg:address":"Rue De Warnoumont 58",
    "sg:city":"Sprimont",
    "sg:orig_category":"Brood, gebak and snoepgoed",
    "sg:phone":"+32 4 382 15 97",
    "sg:postcode":"4140",
    "sg:province":"Li\u00e8ge",
    "wof:name":"Gregoire",
    "wof:placetype":"venue"
},
  "geometry": {"coordinates":[5.6597499847,50.5072059631],"type":"Point"}
}