{
  "type": "Feature",
  "properties": {
    "iso:country":"BE",
    "sg:address":"Rue Xhav\u00e9e 32-34",
    "sg:city":"Verviers",
    "sg:classifiers":[
        {
            "category":"Professional",
            "subcategory":"Employment Agencies",
            "type":"Services"
        }
    ],
    "sg:phone":"+32 87 32 11 90",
    "sg:postcode":"4800",
    "sg:province":"Li\u00e8ge",
    "sg:tags":[
        "temping",
        "-",
        "manual"
    ],
    "wof:name":"Manpower Horeca Verviers",
    "wof:placetype":"venue"
},
  "geometry": {"coordinates":[5.8588080406,50.5916213989],"type":"Point"}
}