{
  "type": "Feature",
  "properties": {
    "addr:full":"Daverlostraat 110 Brugge West-Vlaanderen 8310",
    "addr:housenumber":"110",
    "addr:postcode":"8310",
    "addr:street":"Daverlostraat",
    "iso:country":"BE",
    "sg:address":"Daverlostraat 110",
    "sg:city":"Brugge",
    "sg:orig_category":"Apotheken",
    "sg:phone":"+32 50 35 03 51",
    "sg:postcode":"8310",
    "sg:province":"West-Vlaanderen",
    "wof:name":"Medifarm",
    "wof:placetype":"venue"
},
  "geometry": {"coordinates":[3.2394061089,51.1997108459],"type":"Point"}
}