{
  "type": "Feature",
  "properties": {
    "addr:full":"Emile Duraylaan 66 Brussel/bruxelles Bruxelles-Capitale 1000",
    "addr:housenumber":"66",
    "addr:postcode":"1000",
    "addr:street":"Emile Duraylaan;/",
    "iso:country":"BE",
    "sg:address":"Emile Duraylaan 66",
    "sg:city":"Brussel/bruxelles",
    "sg:orig_category":"Artiesten and kunstenaars",
    "sg:phone":"+32 2 640 11 52",
    "sg:postcode":"1000",
    "sg:province":"Bruxelles-Capitale",
    "wof:name":"Fabienne Crommelynck",
    "wof:placetype":"venue"
},
  "geometry": {"coordinates":[4.3762469292,50.8165092468],"type":"Point"}
}