{
  "type": "Feature",
  "properties": {
    "addr:full":"Rue De La Rochette 88e Bi\u00e8vre (monceau-en-ardenne) Namur 5555",
    "addr:housenumber":"88e",
    "addr:postcode":"5555",
    "addr:street":"Rue De La Rochette",
    "iso:country":"BE",
    "sg:address":"Rue De La Rochette 88e",
    "sg:city":"Bi\u00e8vre (monceau-en-ardenne)",
    "sg:classifiers":[
        {
            "category":"Wholesale",
            "subcategory":"Plants",
            "type":"Manufacturing & Wholesale Goods"
        }
    ],
    "sg:phone":"+32 61 51 15 96",
    "sg:postcode":"5555",
    "sg:province":"Namur",
    "sg:tags":[
        "whol",
        "flower",
        "-",
        "grower"
    ],
    "wof:name":"Van Veen G",
    "wof:placetype":"venue"
},
  "geometry": {"coordinates":[4.9949531555,49.9080810547],"type":"Point"}
}