{
  "type": "Feature",
  "properties": {
    "addr:full":"Industrielaan 34 Kuurne West-Vlaanderen 8520",
    "addr:housenumber":"34",
    "addr:postcode":"8520",
    "addr:street":"Industrielaan",
    "iso:country":"BE",
    "sg:address":"Industrielaan 34",
    "sg:city":"Kuurne",
    "sg:classifiers":[
        {
            "category":"Manufacturing",
            "subcategory":"Chemicals & Compounds",
            "type":"Manufacturing & Wholesale Goods"
        }
    ],
    "sg:phone":"+32 56 35 42 12",
    "sg:postcode":"8520",
    "sg:province":"West-Vlaanderen",
    "sg:tags":[
        "synthetic",
        "fibre"
    ],
    "wof:name":"Fibral Nv",
    "wof:placetype":"venue"
},
  "geometry": {"coordinates":[3.2594399452,50.8567810059],"type":"Point"}
}