{
  "type": "Feature",
  "properties": {
    "addr:full":"Frankrijklaan 13-15 Poperinge West-Vlaanderen 8970",
    "addr:postcode":"13-15;8970",
    "addr:street":"Frankrijklaan",
    "iso:country":"BE",
    "sg:address":"Frankrijklaan 13-15",
    "sg:city":"Poperinge",
    "sg:orig_category":"Transports routiers de marchandises",
    "sg:phone":"+32 57 33 33 27",
    "sg:postcode":"8970",
    "sg:province":"West-Vlaanderen",
    "wof:name":"Deraedt",
    "wof:placetype":"venue"
},
  "geometry": {"coordinates":[2.7435390949,50.8479537964],"type":"Point"}
}