{
  "type": "Feature",
  "properties": {
    "addr:full":"Rue Adrien Materne 99 Grace-hollogne Li\u00e8ge 4460",
    "addr:housenumber":"99",
    "addr:postcode":"4460",
    "addr:street":"Rue Adrien Materne",
    "iso:country":"BE",
    "sg:address":"Rue Adrien Materne 99",
    "sg:city":"Grace-hollogne",
    "sg:orig_category":"Notarissen",
    "sg:phone":"+32 4 239 75 15",
    "sg:postcode":"4460",
    "sg:province":"Li\u00e8ge",
    "wof:name":"R. Mottard",
    "wof:placetype":"venue"
},
  "geometry": {"coordinates":[5.5067300797,50.644947052],"type":"Point"}
}