{
  "type": "Feature",
  "properties": {
    "addr:full":"Avenue Charles Deli\u00e8ge 73 Binche Hainaut 7130",
    "addr:housenumber":"73",
    "addr:postcode":"7130",
    "addr:street":"Avenue Charles Delie\u0300Ge",
    "iso:country":"BE",
    "sg:address":"Avenue Charles Deli\u00e8ge 73",
    "sg:city":"Binche",
    "sg:classifiers":[
        {
            "category":"Health Services",
            "subcategory":"Dentist",
            "type":"Services"
        }
    ],
    "sg:phone":"+32 64 26 75 85",
    "sg:postcode":"7130",
    "sg:province":"Hainaut",
    "wof:name":"Palenik Steve",
    "wof:placetype":"venue"
},
  "geometry": {"coordinates":[4.1669597626,50.4134254456],"type":"Point"}
}