{
  "type": "Feature",
  "properties": {
    "iso:country":"BE",
    "sg:address":"Avenue Du Centenaire 59",
    "sg:city":"Seraing",
    "sg:orig_category":"Sportclubs Sportterreinen and installaties behalve sportcentra",
    "sg:phone":"+32 4 336 00 64",
    "sg:postcode":"4102",
    "sg:province":"Li\u00e8ge",
    "wof:name":"T C Centenaire",
    "wof:placetype":"venue"
},
  "geometry": {"coordinates":[5.5394501686,50.5933303833],"type":"Point"}
}