{
  "type": "Feature",
  "properties": {
    "addr:full":"Tiensestraat 170 Leuven Vlaams-Brabant 3000",
    "addr:housenumber":"170",
    "addr:postcode":"3000",
    "addr:street":"Tiensestraat",
    "iso:country":"BE",
    "sg:address":"Tiensestraat 170",
    "sg:city":"Leuven",
    "sg:orig_category":"Drukkerijen and copyshops",
    "sg:phone":"+32 16 22 94 16",
    "sg:postcode":"3000",
    "sg:province":"Vlaams-Brabant",
    "wof:name":"Megacopy Ii",
    "wof:placetype":"venue"
},
  "geometry": {"coordinates":[4.7098751068,50.8749961853],"type":"Point"}
}