{
  "type": "Feature",
  "properties": {
    "addr:full":"Keiberg 2 Oosterzele Oost-Vlaanderen 9250",
    "addr:housenumber":"2",
    "addr:postcode":"9250",
    "addr:street":"Keiberg;Oost-Vlaanderen",
    "iso:country":"BE",
    "sg:address":"Keiberg 2",
    "sg:city":"Oosterzele",
    "sg:classifiers":[
        {
            "category":"Banks & Credit Unions",
            "subcategory":"Bank",
            "type":"Services"
        }
    ],
    "sg:phone":"+32 54 62 54 94",
    "sg:postcode":"9250",
    "sg:province":"Oost-Vlaanderen",
    "wof:name":"Banque Bruxelles Lambert Sa",
    "wof:placetype":"venue"
},
  "geometry": {"coordinates":[169.96351623539999,-46.1276092529],"type":"Point"}
}