{
  "type": "Feature",
  "properties": {
    "addr:full":"Brusselsesteenweg 8 Asse Vlaams-Brabant 1730",
    "addr:housenumber":"8",
    "addr:postcode":"1730",
    "addr:street":"Brusselsesteenweg",
    "iso:country":"BE",
    "sg:address":"Brusselsesteenweg 8",
    "sg:city":"Asse",
    "sg:classifiers":[
        {
            "category":"Health Services",
            "subcategory":"Health Practitioner",
            "type":"Services"
        }
    ],
    "sg:phone":"+32 2 452 62 86",
    "sg:postcode":"1730",
    "sg:province":"Vlaams-Brabant",
    "sg:tags":[
        "physiotherapist"
    ],
    "wof:name":"Coppens M",
    "wof:placetype":"venue"
},
  "geometry": {"coordinates":[4.2093110085,50.905128479],"type":"Point"}
}