{
  "type": "Feature",
  "properties": {
    "addr:full":"Voorstadstraat 66 Komen-waasten/comines-warneton Hainaut 7780",
    "addr:housenumber":"66;7780",
    "addr:street":"Voorstadstraat",
    "iso:country":"BE",
    "sg:address":"Voorstadstraat 66",
    "sg:city":"Komen-waasten/comines-warneton",
    "sg:orig_category":"Foto-uitrusting Geschenken and souvenirs Huishoudapparaten, televisies and radio's Speelgoed Sport- ",
    "sg:phone":"+32 56 55 78 73",
    "sg:postcode":"7780",
    "sg:province":"Hainaut",
    "wof:name":"Blokker",
    "wof:placetype":"venue"
},
  "geometry": {"coordinates":[2.9984300137,50.7863311768],"type":"Point"}
}