{
  "type": "Feature",
  "properties": {
    "iso:country":"BE",
    "sg:address":"Stormestraat 9",
    "sg:city":"Waregem",
    "sg:classifiers":[
        {
            "category":"Personal",
            "subcategory":"Beauty Salon",
            "type":"Services"
        }
    ],
    "sg:phone":"+32 56 60 62 94",
    "sg:postcode":"8790",
    "sg:province":"West-Vlaanderen",
    "sg:tags":[
        "de",
        "coiffure"
    ],
    "wof:name":"Hair Look Nico",
    "wof:placetype":"venue"
},
  "geometry": {"coordinates":[3.4312679768,50.8863716125],"type":"Point"}
}