{
  "type": "Feature",
  "properties": {
    "addr:full":"Aarschotsesteenweg 205 Herselt Antwerpen 2230",
    "addr:housenumber":"205",
    "addr:postcode":"2230",
    "addr:street":"Aarschotsesteenweg",
    "iso:country":"BE",
    "sg:address":"Aarschotsesteenweg 205",
    "sg:city":"Herselt",
    "sg:orig_category":"Eleveurs de bovins",
    "sg:phone":"+32 16 68 08 39",
    "sg:postcode":"2230",
    "sg:province":"Antwerpen",
    "wof:name":"Fa. Van Roosbroeck & Co",
    "wof:placetype":"venue"
},
  "geometry": {"coordinates":[4.847205162,51.0294837952],"type":"Point"}
}