{
  "type": "Feature",
  "properties": {
    "iso:country":"BE",
    "sg:address":"Venecoweg 25",
    "sg:city":"Nazareth",
    "sg:classifiers":[
        {
            "category":"Utilities",
            "subcategory":"Electric",
            "type":"Services"
        }
    ],
    "sg:phone":"+32 9 252 13 09",
    "sg:postcode":"9810",
    "sg:province":"Oost-Vlaanderen",
    "sg:tags":[
        "electricity",
        "electronic",
        "electrical",
        "equipment"
    ],
    "wof:name":"Werkhuizen Goedertier Bvba",
    "wof:placetype":"venue"
},
  "geometry": {"coordinates":[3.5542340279,50.953338623],"type":"Point"}
}