{
  "type": "Feature",
  "properties": {
    "addr:full":"Stationsstraat 38 Leopoldsburg Limburg 3970",
    "addr:housenumber":"38",
    "addr:postcode":"3970",
    "addr:street":"Stationsstraat",
    "iso:country":"BE",
    "sg:address":"Stationsstraat 38",
    "sg:city":"Leopoldsburg",
    "sg:classifiers":[
        {
            "category":"Shopping",
            "subcategory":"Clothing, Apparel, & Fashions",
            "type":"Retail Goods"
        }
    ],
    "sg:phone":"+32 11 40 17 10",
    "sg:postcode":"3970",
    "sg:province":"Limburg",
    "sg:tags":[
        "lingerie",
        "sous-v\u00eatements"
    ],
    "wof:name":"Huis Donna Pi\u00db",
    "wof:placetype":"venue"
},
  "geometry": {"coordinates":[5.2606258392,51.1175765991],"type":"Point"}
}