{
  "type": "Feature",
  "properties": {
    "iso:country":"BE",
    "sg:address":"Vlaanderenstraat 1",
    "sg:city":"Kortrijk (heule)",
    "sg:orig_category":"Domotics",
    "sg:phone":"+32 56 35 77 16",
    "sg:postcode":"8501",
    "sg:province":"West-Vlaanderen",
    "wof:name":"Domotech",
    "wof:placetype":"venue"
},
  "geometry": {"coordinates":[3.2538669109,50.8459014893],"type":"Point"}
}