{
  "type": "Feature",
  "properties": {
    "iso:country":"BE",
    "sg:address":"Sint-gillislaan 54 Box 3",
    "sg:city":"Dendermonde",
    "sg:classifiers":[
        {
            "category":"Health Services",
            "subcategory":"Nursing And Care Facility",
            "type":"Services"
        }
    ],
    "sg:phone":"+32 52 21 52 43",
    "sg:postcode":"9200",
    "sg:province":"Oost-Vlaanderen",
    "sg:tags":[
        "home"
    ],
    "wof:name":"Bleys K",
    "wof:placetype":"venue"
},
  "geometry": {"coordinates":[4.1096482277,51.020072937],"type":"Point"}
}