{
  "type": "Feature",
  "properties": {
    "addr:full":"Englebert Adanglaan 4 Box 7 Leopoldsburg Limburg 3970",
    "addr:housenumber":"4;7",
    "addr:postcode":"3970",
    "addr:street":"Adanglaan;Box",
    "iso:country":"BE",
    "sg:address":"Englebert Adanglaan 4 Box 7",
    "sg:city":"Leopoldsburg",
    "sg:classifiers":[
        {
            "category":"Building & Trades",
            "subcategory":"Construction",
            "type":"Services"
        }
    ],
    "sg:phone":"+32 11 34 08 40",
    "sg:postcode":"3970",
    "sg:province":"Limburg",
    "sg:tags":[
        "installation",
        "-",
        "central",
        "heating"
    ],
    "wof:name":"Matheco",
    "wof:placetype":"venue"
},
  "geometry": {"coordinates":[5.2640399933,51.1204414368],"type":"Point"}
}