{
  "type": "Feature",
  "properties": {
    "addr:full":"Hekkestraat 4 Aalst Oost-Vlaanderen 9308",
    "addr:housenumber":"4",
    "addr:postcode":"9308",
    "addr:street":"Hekkestraat",
    "iso:country":"BE",
    "sg:address":"Hekkestraat 4",
    "sg:city":"Aalst",
    "sg:classifiers":[
        {
            "category":"Insurance",
            "subcategory":"Insurance Agent",
            "type":"Services"
        }
    ],
    "sg:phone":"+32 53 77 61 08",
    "sg:postcode":"9308",
    "sg:province":"Oost-Vlaanderen",
    "sg:tags":[
        "verzekeringsmakelaars",
        "expert"
    ],
    "wof:name":"M. De Wolf",
    "wof:placetype":"venue"
},
  "geometry": {"coordinates":[4.0347590446,50.9603500366],"type":"Point"}
}