{
  "type": "Feature",
  "properties": {
    "addr:full":"Wingepark 5b Rotselaar Vlaams-Brabant 3110",
    "addr:housenumber":"5b",
    "addr:postcode":"3110",
    "addr:street":"Wingepark",
    "iso:country":"BE",
    "sg:address":"Wingepark 5b",
    "sg:city":"Rotselaar",
    "sg:orig_category":"Verhuur bouwmachines",
    "sg:phone":"+32 16 44 83 73",
    "sg:postcode":"3110",
    "sg:province":"Vlaams-Brabant",
    "wof:name":"Havico",
    "wof:placetype":"venue"
},
  "geometry": {"coordinates":[4.7439618111,50.9398460388],"type":"Point"}
}