{
  "type": "Feature",
  "properties": {
    "iso:country":"BE",
    "sg:address":"Chaus\u00c9e De Gand 126",
    "sg:city":"Brussel",
    "sg:orig_category":"Sportclubs Sportterreinen and installaties behalve sportcentra",
    "sg:phone":"+32 2 411 03 38",
    "sg:postcode":"1080",
    "sg:province":"Bruxelles-Capitale",
    "wof:name":"F.c. Atlas De Bruxelles",
    "wof:placetype":"venue"
},
  "geometry": {"coordinates":[4.335436821,50.8552856445],"type":"Point"}
}