{
  "type": "Feature",
  "properties": {
    "addr:full":"Hogedries 9 Peer Limburg 3990",
    "addr:housenumber":"9",
    "addr:postcode":"3990",
    "addr:street":"Hogedries",
    "iso:country":"BE",
    "sg:address":"Hogedries 9",
    "sg:city":"Peer",
    "sg:orig_category":"Dranken",
    "sg:phone":"+32 11 79 29 75",
    "sg:postcode":"3990",
    "sg:province":"Limburg",
    "wof:name":"Huis Vinas",
    "wof:placetype":"venue"
},
  "geometry": {"coordinates":[5.4371151924,51.094997406],"type":"Point"}
}