{
  "type": "Feature",
  "properties": {
    "addr:full":"Route Du Tonnelet 22 Spa Li\u00e8ge 4900",
    "addr:housenumber":"22",
    "addr:postcode":"4900",
    "addr:street":"Route Du Tonnelet",
    "iso:country":"BE",
    "sg:address":"Route Du Tonnelet 22",
    "sg:city":"Spa",
    "sg:orig_category":"V\u00e9t\u00e9rinaires",
    "sg:phone":"+32 87 77 59 44",
    "sg:postcode":"4900",
    "sg:province":"Li\u00e8ge",
    "wof:name":"Georges Fabry",
    "wof:placetype":"venue"
},
  "geometry": {"coordinates":[5.8777351379,50.4897041321],"type":"Point"}
}