{
  "type": "Feature",
  "properties": {
    "iso:country":"BE",
    "sg:address":"Place De Bossi\u00e8re 9",
    "sg:city":"Gembloux-sur-orneau (bossi\u00e8re)",
    "sg:classifiers":[
        {
            "category":"Shopping",
            "subcategory":"Antiques",
            "type":"Retail Goods"
        }
    ],
    "sg:phone":"+32 81 63 45 32",
    "sg:postcode":"5032",
    "sg:province":"Namur",
    "wof:name":"Devuyst Antiquit\u00e9s",
    "wof:placetype":"venue"
},
  "geometry": {"coordinates":[4.6972928047,50.5179634094],"type":"Point"}
}