{
  "type": "Feature",
  "properties": {
    "addr:full":"Rue De Roseli\u00c8res 8 Tournai Hainaut 7500",
    "addr:housenumber":"8",
    "addr:postcode":"7500",
    "addr:street":"Rue De Roselie\u0300Res",
    "iso:country":"BE",
    "sg:address":"Rue De Roseli\u00c8res 8",
    "sg:city":"Tournai",
    "sg:classifiers":[
        {
            "category":"Education",
            "subcategory":"University",
            "type":"Public Place"
        }
    ],
    "sg:phone":"+32 69 64 19 57",
    "sg:postcode":"7500",
    "sg:province":"Hainaut",
    "sg:tags":[
        "photo",
        "hall"
    ],
    "wof:name":"Photo Hall",
    "wof:placetype":"venue"
},
  "geometry": {"coordinates":[3.3867199421,50.606098175],"type":"Point"}
}