{
  "type": "Feature",
  "properties": {
    "addr:full":"Andries Pevernagestraat 81 Harelbeke West-Vlaanderen 8530",
    "addr:housenumber":"81",
    "addr:postcode":"8530",
    "addr:street":"Andries Pevernagestraat",
    "iso:country":"BE",
    "sg:address":"Andries Pevernagestraat 81",
    "sg:city":"Harelbeke",
    "sg:classifiers":[
        {
            "category":"Fast Food",
            "type":"Food & Drink"
        }
    ],
    "sg:phone":"+32 56 71 54 79",
    "sg:postcode":"8530",
    "sg:province":"West-Vlaanderen",
    "sg:tags":[
        "meeneem",
        "restaurant"
    ],
    "wof:name":"Jozef Velghe",
    "wof:placetype":"venue"
},
  "geometry": {"coordinates":[3.3088951111,50.852180481],"type":"Point"}
}