{
  "type": "Feature",
  "properties": {
    "addr:full":"Kortrijksesteenweg 630 Gent Oost-Vlaanderen 9000",
    "addr:housenumber":"630",
    "addr:postcode":"9000",
    "addr:street":"Kortrijksesteenweg;Oost-Vlaanderen",
    "iso:country":"BE",
    "sg:address":"Kortrijksesteenweg 630",
    "sg:city":"Gent",
    "sg:classifiers":[
        {
            "category":"Social Services",
            "subcategory":"Retirement Home",
            "type":"Services"
        }
    ],
    "sg:phone":"+32 9 221 90 41",
    "sg:postcode":"9000",
    "sg:province":"Oost-Vlaanderen",
    "sg:tags":[
        "residence"
    ],
    "wof:name":"Aline Home",
    "wof:placetype":"venue"
},
  "geometry": {"coordinates":[3.7128579617,51.0307884216],"type":"Point"}
}