{
  "type": "Feature",
  "properties": {
    "iso:country":"BE",
    "sg:address":"Rue De L'harmonie 9",
    "sg:city":"Verviers",
    "sg:orig_category":"Dameskledingzaken",
    "sg:phone":"+32 87 33 52 87",
    "sg:postcode":"4800",
    "sg:province":"Li\u00e8ge",
    "wof:name":"Collections",
    "wof:placetype":"venue"
},
  "geometry": {"coordinates":[5.8755340576,50.5953216553],"type":"Point"}
}