{
  "type": "Feature",
  "properties": {
    "iso:country":"BE",
    "sg:address":"Avenue Reine Astrid 258",
    "sg:city":"Verviers",
    "sg:orig_category":"Benzinestations and brandstoffen",
    "sg:phone":"+32 87 22 09 30",
    "sg:postcode":"4802",
    "sg:province":"Li\u00e8ge",
    "wof:name":"Collard-bovy",
    "wof:placetype":"venue"
},
  "geometry": {"coordinates":[5.8870787621,50.5832061768],"type":"Point"}
}