{
  "type": "Feature",
  "properties": {
    "iso:country":"BE",
    "sg:address":"Kraaienveld 18",
    "sg:city":"Waregem",
    "sg:classifiers":[
        {
            "category":"Arena",
            "subcategory":"Sports Club",
            "type":"Entertainment"
        }
    ],
    "sg:phone":"+32 56 60 27 76",
    "sg:postcode":"8790",
    "sg:province":"West-Vlaanderen",
    "sg:tags":[
        "de"
    ],
    "wof:name":"B.c. Waregem",
    "wof:placetype":"venue"
},
  "geometry": {"coordinates":[3.4509170055,50.8959503174],"type":"Point"}
}