{
  "type": "Feature",
  "properties": {
    "addr:full":"Leuvensesteenweg 282b2 Boortmeerbeek Vlaams-Brabant 3190",
    "addr:housenumber":"282b2",
    "addr:postcode":"3190",
    "addr:street":"Leuvensesteenweg",
    "iso:country":"BE",
    "sg:address":"Leuvensesteenweg 282b2",
    "sg:city":"Boortmeerbeek",
    "sg:orig_category":"Ordinateurs and \u00e9quipement informatique",
    "sg:phone":"+32 15 52 82 62",
    "sg:postcode":"3190",
    "sg:province":"Vlaams-Brabant",
    "wof:name":"Quadrox",
    "wof:placetype":"venue"
},
  "geometry": {"coordinates":[4.5686612129,50.9710350037],"type":"Point"}
}