{
  "type": "Feature",
  "properties": {
    "iso:country":"BE",
    "sg:address":"Boulevard De La Sauveni\u00c8re 134",
    "sg:city":"Li\u00c8ge",
    "sg:orig_category":"Agences d\u00b4interim and personnel temporaire",
    "sg:phone":"+32 4 222 40 52",
    "sg:postcode":"4000",
    "sg:province":"Li\u00e8ge",
    "wof:name":"Amis-arrow Interim",
    "wof:placetype":"venue"
},
  "geometry": {"coordinates":[5.566411972,50.6417388916],"type":"Point"}
}