{
  "type": "Feature",
  "properties": {
    "iso:country":"BE",
    "sg:address":"Keizerstraat 43",
    "sg:city":"Diepenbeek",
    "sg:orig_category":"Artsen and specialisten",
    "sg:phone":"+32 11 32 38 47",
    "sg:postcode":"3590",
    "sg:province":"Limburg",
    "wof:name":"Liesbeth Vandermeeren",
    "wof:placetype":"venue"
},
  "geometry": {"coordinates":[5.4110097885,50.9080619812],"type":"Point"}
}