{
  "type": "Feature",
  "properties": {
    "iso:country":"BE",
    "sg:address":"Herentalsstraat 59",
    "sg:city":"Turnhout",
    "sg:classifiers":[
        {
            "category":"Real Estate",
            "subcategory":"Architect",
            "type":"Services"
        }
    ],
    "sg:phone":"+32 14 72 47 64",
    "sg:postcode":"2300",
    "sg:province":"Antwerpen",
    "wof:name":"Seuntjens R",
    "wof:placetype":"venue"
},
  "geometry": {"coordinates":[4.9497199059,51.3202629089],"type":"Point"}
}