{
  "type": "Feature",
  "properties": {
    "iso:country":"BE",
    "sg:address":"Stationsstraat 115",
    "sg:city":"Ternat",
    "sg:classifiers":[
        {
            "category":"Restaurant",
            "type":"Food & Drink"
        }
    ],
    "sg:phone":"+32 2 582 70 40",
    "sg:postcode":"1740",
    "sg:province":"Vlaams-Brabant",
    "wof:name":"Luc Van Holsbeeck",
    "wof:placetype":"venue"
},
  "geometry": {"coordinates":[4.1649951935,50.8742828369],"type":"Point"}
}