{
  "type": "Feature",
  "properties": {
    "iso:country":"BE",
    "sg:address":"Sint-juliaanskerklaan 25",
    "sg:city":"Oudergem/auderghem",
    "sg:orig_category":"Installatie van houten of kunststof schrijnwerk",
    "sg:phone":"+32 2 660 71 42",
    "sg:postcode":"1160",
    "sg:province":"Bruxelles-Capitale",
    "wof:name":"Ets. N\u00c9lis J.",
    "wof:placetype":"venue"
},
  "geometry": {"coordinates":[4.4081630707,50.8199005127],"type":"Point"}
}