{
  "type": "Feature",
  "properties": {
    "addr:full":"Kunstlaan 11 Boom Antwerpen 2850",
    "addr:housenumber":"11",
    "addr:postcode":"2850",
    "addr:street":"Kunstlaan",
    "iso:country":"BE",
    "sg:address":"Kunstlaan 11",
    "sg:city":"Boom",
    "sg:orig_category":"Divers amusement Diverse zakelijke dienstverlening",
    "sg:phone":"+32 3 844 62 85",
    "sg:postcode":"2850",
    "sg:province":"Antwerpen",
    "wof:name":"Koko Pepe",
    "wof:placetype":"venue"
},
  "geometry": {"coordinates":[4.369571209,51.1018867493],"type":"Point"}
}