{
  "type": "Feature",
  "properties": {
    "addr:full":"Chauss\u00c9e De Tirlemont 60 Geldenaken Brabant Wallon 1370",
    "addr:housenumber":"60;1370",
    "addr:street":"Chausse\u0301E De Tirlemont;Brabant Wallon",
    "iso:country":"BE",
    "sg:address":"Chauss\u00c9e De Tirlemont 60",
    "sg:city":"Geldenaken",
    "sg:orig_category":"Sportclubs",
    "sg:phone":"+32 10 81 32 45",
    "sg:postcode":"1370",
    "sg:province":"Brabant Wallon",
    "wof:name":"Tennis Club Ermitage",
    "wof:placetype":"venue"
},
  "geometry": {"coordinates":[4.8746528625,50.7269973755],"type":"Point"}
}