{
  "type": "Feature",
  "properties": {
    "iso:country":"BE",
    "sg:address":"Chauss\u00c9e D\u00b4alsemberg 1210",
    "sg:city":"Brussel/bruxelles",
    "sg:orig_category":"Entretien et r\u00e9parations de v\u00e9hicules \u00e0 domicile. Entretien et r\u00e9parations de v\u00e9hicules \u00e0 domicile",
    "sg:phone":"+32 2 332 00 15",
    "sg:postcode":"1180",
    "sg:province":"Bruxelles-Capitale",
    "wof:name":"Omega-240",
    "wof:placetype":"venue"
},
  "geometry": {"coordinates":[4.3287920952,50.7851791382],"type":"Point"}
}