{
  "type": "Feature",
  "properties": {
    "addr:full":"Rue Spintay 24 Verviers Li\u00e8ge 4800",
    "addr:housenumber":"24",
    "addr:postcode":"4800",
    "addr:street":"Rue Spintay",
    "iso:country":"BE",
    "sg:address":"Rue Spintay 24",
    "sg:city":"Verviers",
    "sg:classifiers":[
        {
            "category":"Personal",
            "subcategory":"Piercing",
            "type":"Services"
        }
    ],
    "sg:phone":"+32 87 33 36 85",
    "sg:postcode":"4800",
    "sg:province":"Li\u00e8ge",
    "sg:tags":[
        "piercings",
        "tatouages"
    ],
    "wof:name":"Tatoo Studio",
    "wof:placetype":"venue"
},
  "geometry": {"coordinates":[5.8594508171,50.5917663574],"type":"Point"}
}