{
  "type": "Feature",
  "properties": {
    "addr:full":"Hoevelei 47 Aartselaar Antwerpen 2630",
    "addr:housenumber":"47",
    "addr:postcode":"2630",
    "addr:street":"Hoevelei",
    "iso:country":"BE",
    "sg:address":"Hoevelei 47",
    "sg:city":"Aartselaar",
    "sg:classifiers":[
        {
            "category":"Personal",
            "subcategory":"Beauty Salon",
            "type":"Services"
        }
    ],
    "sg:phone":"+32 3 887 72 97",
    "sg:postcode":"2630",
    "sg:province":"Antwerpen",
    "sg:tags":[
        "de",
        "coiffure"
    ],
    "wof:name":"Coiffure Queeny",
    "wof:placetype":"venue"
},
  "geometry": {"coordinates":[4.3863368034,51.1357841492],"type":"Point"}
}