{
  "type": "Feature",
  "properties": {
    "iso:country":"BE",
    "sg:address":"Marktplein 41",
    "sg:city":"Moeskroen/mouscron",
    "sg:orig_category":"Diverse kredietdiensten",
    "sg:postcode":"7700",
    "sg:province":"Hainaut",
    "wof:name":"Bancontact-mister Cash",
    "wof:placetype":"venue"
},
  "geometry": {"coordinates":[3.2323200703,50.7400932312],"type":"Point"}
}