{
  "type": "Feature",
  "properties": {
    "addr:full":"Rue Ri\u00e9ssonsart 85b Olne Li\u00e8ge 4877",
    "addr:housenumber":"85b",
    "addr:postcode":"4877",
    "addr:street":"Rue Rie\u0301Ssonsart",
    "iso:country":"BE",
    "sg:address":"Rue Ri\u00e9ssonsart 85b",
    "sg:city":"Olne",
    "sg:classifiers":[
        {
            "category":"Health Services",
            "subcategory":"Doctor",
            "type":"Services"
        }
    ],
    "sg:phone":"+32 4 358 76 16",
    "sg:postcode":"4877",
    "sg:province":"Li\u00e8ge",
    "sg:tags":[
        "medicinephysicians",
        "surgeon"
    ],
    "wof:name":"Defontaine Elisabeth",
    "wof:placetype":"venue"
},
  "geometry": {"coordinates":[5.7077112198,50.6094703674],"type":"Point"}
}