{
  "type": "Feature",
  "properties": {
    "iso:country":"BE",
    "sg:address":"Rue Du Planty 29",
    "sg:city":"Walcourt",
    "sg:orig_category":"Eleveurs de bovins",
    "sg:phone":"+32 71 53 31 83",
    "sg:postcode":"5650",
    "sg:province":"Namur",
    "wof:name":"Michel Quertain",
    "wof:placetype":"venue"
},
  "geometry": {"coordinates":[4.3211150169,50.2551422119],"type":"Point"}
}