{
  "type": "Feature",
  "properties": {
    "iso:country":"BE",
    "sg:address":"Bld De La Sauveni\u00c8re 85b42",
    "sg:city":"Li\u00c8ge",
    "sg:orig_category":"Advocaten and juridische adviseurs",
    "sg:phone":"+32 4 222 17 42",
    "sg:postcode":"4000",
    "sg:province":"Li\u00e8ge",
    "wof:name":"J. Hanssen",
    "wof:placetype":"venue"
},
  "geometry": {"coordinates":[5.5661458969,50.6429290771],"type":"Point"}
}