{
  "type": "Feature",
  "properties": {
    "addr:full":"Rue Delb\u00c8que 35ba Morlanwelz Hainaut 7140",
    "addr:housenumber":"35ba",
    "addr:postcode":"7140",
    "addr:street":"Rue Delbe\u0300Que",
    "iso:country":"BE",
    "sg:address":"Rue Delb\u00c8que 35ba",
    "sg:city":"Morlanwelz",
    "sg:orig_category":"M\u00e9decins and sp\u00e9cialistes",
    "sg:phone":"+32 64 44 66 17",
    "sg:postcode":"7140",
    "sg:province":"Hainaut",
    "wof:name":"Marie-paule Gustin",
    "wof:placetype":"venue"
},
  "geometry": {"coordinates":[4.2483000755,50.4520645142],"type":"Point"}
}