{
  "type": "Feature",
  "properties": {
    "addr:full":"Chauss\u00e9e De Bruxelles 72 Mons Hainaut 7000",
    "addr:housenumber":"72",
    "addr:postcode":"7000",
    "addr:street":"Chausse\u0301E De Bruxelles;Hainaut",
    "iso:country":"BE",
    "sg:address":"Chauss\u00e9e De Bruxelles 72",
    "sg:city":"Mons",
    "sg:classifiers":[
        {
            "category":"Real Estate",
            "subcategory":"Architect",
            "type":"Services"
        }
    ],
    "sg:phone":"+32 65 84 47 20",
    "sg:postcode":"7000",
    "sg:province":"Hainaut",
    "wof:name":"Delpire D",
    "wof:placetype":"venue"
},
  "geometry": {"coordinates":[3.9577059746,50.4665298462],"type":"Point"}
}