{
  "type": "Feature",
  "properties": {
    "iso:country":"BE",
    "sg:address":"Chemin Du Lefa 34",
    "sg:city":"Malm\u00c9dy",
    "sg:orig_category":"Installatie van houten of kunststof schrijnwerk",
    "sg:phone":"+32 80 33 05 32",
    "sg:postcode":"4960",
    "sg:province":"Li\u00e8ge",
    "wof:name":"Warland Ren\u00c9",
    "wof:placetype":"venue"
},
  "geometry": {"coordinates":[6.0585842133,50.4031066895],"type":"Point"}
}