{
  "type": "Feature",
  "properties": {
    "addr:full":"Dennenlaan 33 Zandhoven (pulle) Antwerpen 2243",
    "addr:housenumber":"33",
    "addr:postcode":"2243",
    "addr:street":"Dennenlaan",
    "iso:country":"BE",
    "sg:address":"Dennenlaan 33",
    "sg:city":"Zandhoven (pulle)",
    "sg:classifiers":[
        {
            "category":"Wholesale",
            "subcategory":"Construction Materials",
            "type":"Manufacturing & Wholesale Goods"
        }
    ],
    "sg:phone":"+32 3 464 17 31",
    "sg:postcode":"2243",
    "sg:province":"Antwerpen",
    "sg:tags":[
        "tubing",
        "industrial"
    ],
    "wof:name":"Ditec",
    "wof:placetype":"venue"
},
  "geometry": {"coordinates":[4.6938700676,51.1943092346],"type":"Point"}
}