{
  "type": "Feature",
  "properties": {
    "addr:full":"Aardeweg 26 Beringen (koersel) Limburg 3582",
    "addr:housenumber":"26",
    "addr:postcode":"3582",
    "addr:street":"Aardeweg",
    "iso:country":"BE",
    "sg:address":"Aardeweg 26",
    "sg:city":"Beringen (koersel)",
    "sg:classifiers":[
        {
            "category":"Farming",
            "subcategory":"Farm & Veterinary Services",
            "type":"Manufacturing & Wholesale Goods"
        }
    ],
    "sg:phone":"+32 11 42 48 41",
    "sg:postcode":"3582",
    "sg:province":"Limburg",
    "sg:tags":[
        "agricultural",
        "contractor"
    ],
    "wof:name":"Peeters",
    "wof:placetype":"venue"
},
  "geometry": {"coordinates":[5.2708749771,51.0595359802],"type":"Point"}
}