{
  "type": "Feature",
  "properties": {
    "iso:country":"BE",
    "sg:address":"Rue De La Poulie 2",
    "sg:city":"Bouillon",
    "sg:classifiers":[
        {
            "category":"Social Services",
            "subcategory":"Job Training",
            "type":"Services"
        }
    ],
    "sg:phone":"+32 61 46 61 36",
    "sg:postcode":"6830",
    "sg:province":"Luxembourg",
    "sg:tags":[
        "de",
        "terrain",
        "camping"
    ],
    "wof:name":"Robert Camion",
    "wof:placetype":"venue"
},
  "geometry": {"coordinates":[5.0659689903,49.7948760986],"type":"Point"}
}