{
  "type": "Feature",
  "properties": {
    "addr:full":"Rue Lucien Defays 27 Verviers Li\u00e8ge 4800",
    "addr:housenumber":"27",
    "addr:postcode":"4800",
    "addr:street":"Rue Lucien Defays",
    "iso:country":"BE",
    "sg:address":"Rue Lucien Defays 27",
    "sg:city":"Verviers",
    "sg:orig_category":"Quincailleries",
    "sg:phone":"+32 87 33 23 60",
    "sg:postcode":"4800",
    "sg:province":"Li\u00e8ge",
    "wof:name":"Clavir Et Fils",
    "wof:placetype":"venue"
},
  "geometry": {"coordinates":[5.8536949158,50.5920143127],"type":"Point"}
}