{
  "type": "Feature",
  "properties": {
    "iso:country":"BE",
    "sg:address":"Rue Des Fran\u00e7ais 5",
    "sg:city":"Les Bons Villers (frasnes-lez-gosselies)",
    "sg:classifiers":[
        {
            "category":"Retail",
            "subcategory":"Auto Repair",
            "type":"Services"
        }
    ],
    "sg:phone":"+32 71 85 01 35",
    "sg:postcode":"6210",
    "sg:province":"Hainaut",
    "sg:tags":[
        "lpg",
        "automobile",
        "-",
        "system"
    ],
    "wof:name":"Eurotechnic Sprl",
    "wof:placetype":"venue"
},
  "geometry": {"coordinates":[4.4511561394,50.5378227234],"type":"Point"}
}