{
  "type": "Feature",
  "properties": {
    "addr:full":"Cedronbeekstraat 60 Stekene Oost-Vlaanderen 9190",
    "addr:housenumber":"60",
    "addr:postcode":"9190",
    "addr:street":"Cedronbeekstraat",
    "iso:country":"BE",
    "sg:address":"Cedronbeekstraat 60",
    "sg:city":"Stekene",
    "sg:classifiers":[
        {
            "category":"Personal",
            "subcategory":"Nail Salon",
            "type":"Services"
        }
    ],
    "sg:phone":"+32 3 789 16 39",
    "sg:postcode":"9190",
    "sg:province":"Oost-Vlaanderen",
    "sg:tags":[
        "pedicure"
    ],
    "wof:name":"De Mulder K",
    "wof:placetype":"venue"
},
  "geometry": {"coordinates":[4.0467028618,51.2025909424],"type":"Point"}
}