{
  "type": "Feature",
  "properties": {
    "addr:full":"Rue De Namur 65a Liege Li\u00e8ge 4000",
    "addr:housenumber":"65a",
    "addr:postcode":"4000",
    "addr:street":"Rue De Namur",
    "iso:country":"BE",
    "sg:address":"Rue De Namur 65a",
    "sg:city":"Liege",
    "sg:orig_category":"V\u00eatements, chaussures and accessoires Imprimeries and copyshops",
    "sg:phone":"+32 4 229 35 55",
    "sg:postcode":"4000",
    "sg:province":"Li\u00e8ge",
    "wof:name":"Godart R",
    "wof:placetype":"venue"
},
  "geometry": {"coordinates":[5.5770978928,50.6197242737],"type":"Point"}
}