{
  "type": "Feature",
  "properties": {
    "addr:full":"Chauss\u00e9e De Mons 460 Bruxelles (anderlecht) Bruxelles-Capitale 1070",
    "addr:housenumber":"460",
    "addr:postcode":"1070",
    "addr:street":"Chausse\u0301E De Mons",
    "iso:country":"BE",
    "sg:address":"Chauss\u00e9e De Mons 460",
    "sg:city":"Bruxelles (anderlecht)",
    "sg:classifiers":[
        {
            "category":"Autos & Motor Vehicles",
            "subcategory":"Motorcycle Sales",
            "type":"Retail Goods"
        }
    ],
    "sg:phone":"+32 2 522 97 07",
    "sg:postcode":"1070",
    "sg:province":"Bruxelles-Capitale",
    "sg:tags":[
        "scooter",
        "-",
        "moped"
    ],
    "wof:name":"Recup Motos Fun Sprl",
    "wof:placetype":"venue"
},
  "geometry": {"coordinates":[4.3159427643,50.8348617554],"type":"Point"}
}