{
  "type": "Feature",
  "properties": {
    "addr:full":"Mechelsesteenweg 8 Heist-op-den-berg Antwerpen 2220",
    "addr:housenumber":"8",
    "addr:postcode":"2220",
    "addr:street":"Mechelsesteenweg",
    "iso:country":"BE",
    "sg:address":"Mechelsesteenweg 8",
    "sg:city":"Heist-op-den-berg",
    "sg:classifiers":[
        {
            "category":"Health Services",
            "subcategory":"Health Practitioner",
            "type":"Services"
        }
    ],
    "sg:phone":"+32 15 25 11 54",
    "sg:postcode":"2220",
    "sg:province":"Antwerpen",
    "sg:tags":[
        "physiotherapist"
    ],
    "wof:name":"Mee\u00fbs Katleen",
    "wof:placetype":"venue"
},
  "geometry": {"coordinates":[4.7071008682,51.0740814209],"type":"Point"}
}