{
  "type": "Feature",
  "properties": {
    "addr:full":"Place Yvon Paul 27 Momignies Hainaut 6591",
    "addr:housenumber":"27",
    "addr:postcode":"6591",
    "addr:street":"Place Yvon Paul;Hainaut",
    "iso:country":"BE",
    "sg:address":"Place Yvon Paul 27",
    "sg:city":"Momignies",
    "sg:orig_category":"Plaatsen van vloer- and muurbekleding Schilders",
    "sg:phone":"+32 60 51 23 86",
    "sg:postcode":"6591",
    "sg:province":"Hainaut",
    "wof:name":"Michel Dupuis",
    "wof:placetype":"venue"
},
  "geometry": {"coordinates":[4.2087621689,50.0521697998],"type":"Point"}
}