{
  "type": "Feature",
  "properties": {
    "addr:full":"Stationsstraat 13 Bertem Vlaams-Brabant 3060",
    "addr:housenumber":"13",
    "addr:postcode":"3060",
    "addr:street":"Stationsstraat",
    "iso:country":"BE",
    "sg:address":"Stationsstraat 13",
    "sg:city":"Bertem",
    "sg:orig_category":"Clubs de sport. Services divers aux entreprises. Location d'articles de sport, de sport nautique and",
    "sg:phone":"+32 16 47 04 80",
    "sg:postcode":"3060",
    "sg:province":"Vlaams-Brabant",
    "wof:name":"Escape Now",
    "wof:placetype":"venue"
},
  "geometry": {"coordinates":[4.6411590576,50.8392028809],"type":"Point"}
}