{
  "type": "Feature",
  "properties": {
    "addr:full":"Rue Armand Bury 150 Thuin Hainaut 6534",
    "addr:housenumber":"150",
    "addr:postcode":"6534",
    "addr:street":"Rue Armand Bury",
    "iso:country":"BE",
    "sg:address":"Rue Armand Bury 150",
    "sg:city":"Thuin",
    "sg:orig_category":"Pain, p\u00e2tisseries and confiseries",
    "sg:phone":"+32 71 51 54 70",
    "sg:postcode":"6534",
    "sg:province":"Hainaut",
    "wof:name":"Roland Maquet",
    "wof:placetype":"venue"
},
  "geometry": {"coordinates":[4.3577260971,50.3454933167],"type":"Point"}
}