{
  "type": "Feature",
  "properties": {
    "addr:full":"Basse Campagne 113-115 Herstal Li\u00e8ge 4040",
    "addr:postcode":"113-115;4040",
    "addr:street":"Basse Campagne",
    "iso:country":"BE",
    "sg:address":"Basse Campagne 113-115",
    "sg:city":"Herstal",
    "sg:orig_category":"Royal Canin",
    "sg:phone":"+32 4 240 15 86",
    "sg:postcode":"4040",
    "sg:province":"Li\u00e8ge",
    "wof:name":"Tom & Co",
    "wof:placetype":"venue"
},
  "geometry": {"coordinates":[5.6450171471,50.6878128052],"type":"Point"}
}