{
  "type": "Feature",
  "properties": {
    "addr:full":"Halve Maanstraat 3 Gistel West-Vlaanderen 8470",
    "addr:housenumber":"3",
    "addr:postcode":"8470",
    "addr:street":"Halve Maanstraat",
    "iso:country":"BE",
    "sg:address":"Halve Maanstraat 3",
    "sg:city":"Gistel",
    "sg:orig_category":"Verplichte sociale verzekeringen",
    "sg:phone":"+32 59 27 66 67",
    "sg:postcode":"8470",
    "sg:province":"West-Vlaanderen",
    "wof:name":"Westvl. Liberaal Ziekenf.",
    "wof:placetype":"venue"
},
  "geometry": {"coordinates":[2.964345932,51.1557731628],"type":"Point"}
}