{
  "type": "Feature",
  "properties": {
    "iso:country":"BE",
    "sg:address":"Rietmusweg 108",
    "sg:city":"Tongeren",
    "sg:classifiers":[
        {
            "category":"Health Services",
            "subcategory":"Nursing And Care Facility",
            "type":"Services"
        }
    ],
    "sg:phone":"+32 12 23 75 04",
    "sg:postcode":"3700",
    "sg:province":"Limburg",
    "sg:tags":[
        "access",
        "equipment",
        "hospital",
        "-"
    ],
    "wof:name":"Principle Business Intern Nv",
    "wof:placetype":"venue"
},
  "geometry": {"coordinates":[5.4761648178,50.7698020935],"type":"Point"}
}