{
  "type": "Feature",
  "properties": {
    "iso:country":"BE",
    "sg:address":"Cornet De Grezstraat 14",
    "sg:city":"Sint-joost-ten-node/saint-josse-ten-noode",
    "sg:orig_category":"Boekhouders",
    "sg:phone":"+32 2 218 45 35",
    "sg:postcode":"1210",
    "sg:province":"Bruxelles-Capitale",
    "wof:name":"Charly De Backer",
    "wof:placetype":"venue"
},
  "geometry": {"coordinates":[4.3688430786,50.8571891785],"type":"Point"}
}