{
  "type": "Feature",
  "properties": {
    "iso:country":"BE",
    "sg:address":"Konijnenboslaan 14",
    "sg:city":"Gistel",
    "sg:orig_category":"Bouwmaterialen Gh Dakwerken",
    "sg:phone":"+32 59 27 76 98",
    "sg:postcode":"8470",
    "sg:province":"West-Vlaanderen",
    "wof:name":"Atab",
    "wof:placetype":"venue"
},
  "geometry": {"coordinates":[2.9488461018,51.1498794556],"type":"Point"}
}