{
  "type": "Feature",
  "properties": {
    "addr:full":"Bollestraat 1 Hooglede West-Vlaanderen 8830",
    "addr:housenumber":"1",
    "addr:postcode":"8830",
    "addr:street":"Bollestraat",
    "iso:country":"BE",
    "sg:address":"Bollestraat 1",
    "sg:city":"Hooglede",
    "sg:orig_category":"Varkenskwekers",
    "sg:phone":"+32 51 72 51 18",
    "sg:postcode":"8830",
    "sg:province":"West-Vlaanderen",
    "wof:name":"Maria Stevens",
    "wof:placetype":"venue"
},
  "geometry": {"coordinates":[3.1236100197,51.0135307312],"type":"Point"}
}