{
  "type": "Feature",
  "properties": {
    "iso:country":"BE",
    "sg:address":"Predikherenlaan 18",
    "sg:city":"Lier",
    "sg:orig_category":"Technisch and beroeps secundair onderwijs",
    "sg:phone":"+32 3 480 27 07",
    "sg:postcode":"2500",
    "sg:province":"Antwerpen",
    "wof:name":"Koninklijk Atheneum",
    "wof:placetype":"venue"
},
  "geometry": {"coordinates":[4.5748858452,51.132270813],"type":"Point"}
}