{
  "type": "Feature",
  "properties": {
    "iso:country":"BE",
    "sg:address":"Aarschotsesteenweg 662",
    "sg:city":"Leuven (wilsele)",
    "sg:orig_category":"Newspapers, magazines, periodicals - Distribution",
    "sg:phone":"+32 16 44 54 55",
    "sg:postcode":"3012",
    "sg:province":"Vlaams-Brabant",
    "wof:name":"'t Schrijverke-wilsele Bvba",
    "wof:placetype":"venue"
},
  "geometry": {"coordinates":[4.7219882011,50.9252700806],"type":"Point"}
}