{
  "type": "Feature",
  "properties": {
    "iso:country":"BE",
    "sg:address":"Marktstraat 23",
    "sg:city":"Opwijk",
    "sg:orig_category":"Traitements param\u00e9dicaux",
    "sg:phone":"+32 52 35 69 96",
    "sg:postcode":"1745",
    "sg:province":"Vlaams-Brabant",
    "wof:name":"Mieke Ringoot",
    "wof:placetype":"venue"
},
  "geometry": {"coordinates":[4.1882109642,50.9708824158],"type":"Point"}
}