{
  "type": "Feature",
  "properties": {
    "addr:full":"Brusselsesteenweg 190 Zemst Vlaams-Brabant 1980",
    "addr:housenumber":"190",
    "addr:postcode":"1980",
    "addr:street":"Brusselsesteenweg;Vlaams-Brabant",
    "iso:country":"BE",
    "sg:address":"Brusselsesteenweg 190",
    "sg:city":"Zemst",
    "sg:classifiers":[
        {
            "category":"Bus Stop",
            "subcategory":"None",
            "type":"Transportation"
        }
    ],
    "sg:phone":"+32 15 61 32 20",
    "sg:postcode":"1980",
    "sg:province":"Vlaams-Brabant",
    "sg:tags":[
        "seal"
    ],
    "wof:name":"De Geest",
    "wof:placetype":"venue"
},
  "geometry": {"coordinates":[4.4587368965,50.9789428711],"type":"Point"}
}