{
  "type": "Feature",
  "properties": {
    "iso:country":"BE",
    "sg:address":"Sluisstraat 14",
    "sg:city":"Ham",
    "sg:orig_category":"Rundveehouders",
    "sg:phone":"+32 13 66 77 81",
    "sg:postcode":"3945",
    "sg:province":"Limburg",
    "wof:name":"Josephus Govaerts",
    "wof:placetype":"venue"
},
  "geometry": {"coordinates":[5.1776199341,51.1046104431],"type":"Point"}
}