{
  "type": "Feature",
  "properties": {
    "iso:country":"BE",
    "sg:address":"Rue Pr\u00c9vot 9",
    "sg:city":"Soignies",
    "sg:orig_category":"Avocats and conseillers juridiques",
    "sg:phone":"+32 67 33 02 40",
    "sg:postcode":"7060",
    "sg:province":"Hainaut",
    "wof:name":"B. Schoeps",
    "wof:placetype":"venue"
},
  "geometry": {"coordinates":[4.0662617683,50.5700874329],"type":"Point"}
}