{
  "type": "Feature",
  "properties": {
    "addr:full":"Rue De La Bourse 64 La Louvi\u00c8re Hainaut 7110",
    "addr:housenumber":"64",
    "addr:postcode":"7110",
    "addr:street":"Rue De La Bourse",
    "iso:country":"BE",
    "sg:address":"Rue De La Bourse 64",
    "sg:city":"La Louvi\u00c8re",
    "sg:orig_category":"Sportclubs",
    "sg:phone":"+32 64 66 57 47",
    "sg:postcode":"7110",
    "sg:province":"Hainaut",
    "wof:name":"Badminton Mutu Binche",
    "wof:placetype":"venue"
},
  "geometry": {"coordinates":[4.1505050659,50.4826698303],"type":"Point"}
}