{
  "type": "Feature",
  "properties": {
    "addr:full":"Peerderbaan 21 Bree Limburg 3960",
    "addr:housenumber":"21",
    "addr:postcode":"3960",
    "addr:street":"Peerderbaan",
    "iso:country":"BE",
    "sg:address":"Peerderbaan 21",
    "sg:city":"Bree",
    "sg:orig_category":"Assistances juridiques. Conseillers fiscaux",
    "sg:phone":"+32 89 46 07 60",
    "sg:postcode":"3960",
    "sg:province":"Limburg",
    "wof:name":"S.b.b.",
    "wof:placetype":"venue"
},
  "geometry": {"coordinates":[5.5944190025,51.1405677795],"type":"Point"}
}