{
  "type": "Feature",
  "properties": {
    "iso:country":"BE",
    "sg:address":"Zandvlietstraat 60",
    "sg:city":"Antwerpen",
    "sg:orig_category":"Artsen and specialisten",
    "sg:phone":"+32 3 237 77 98",
    "sg:postcode":"2020",
    "sg:province":"Antwerpen",
    "wof:name":"P. Prims",
    "wof:placetype":"venue"
},
  "geometry": {"coordinates":[4.3860359192,51.1860313416],"type":"Point"}
}