{
  "type": "Feature",
  "properties": {
    "iso:country":"BE",
    "sg:address":"Weg Naar As 168 Box 1",
    "sg:city":"Genk",
    "sg:classifiers":[
        {
            "category":"Food & Beverages",
            "subcategory":"Fruits & Vegetables",
            "type":"Retail Goods"
        }
    ],
    "sg:phone":"+32 89 30 39 37",
    "sg:postcode":"3600",
    "sg:province":"Limburg",
    "sg:tags":[
        "-"
    ],
    "wof:name":"Limoentje ('t)",
    "wof:placetype":"venue"
},
  "geometry": {"coordinates":[5.5167808533,50.9725761414],"type":"Point"}
}