{
  "type": "Feature",
  "properties": {
    "addr:full":"Ophemstraat 10 Ninove Oost-Vlaanderen 9400",
    "addr:housenumber":"10",
    "addr:postcode":"9400",
    "addr:street":"Ophemstraat",
    "iso:country":"BE",
    "sg:address":"Ophemstraat 10",
    "sg:city":"Ninove",
    "sg:orig_category":"Mat\u00e9riaux de construction Plomberie, chauffage and installations sanitaires. Mat\u00e9riel pour plomberie",
    "sg:phone":"+32 54 50 24 56",
    "sg:postcode":"9400",
    "sg:province":"Oost-Vlaanderen",
    "wof:name":"Van Belle",
    "wof:placetype":"venue"
},
  "geometry": {"coordinates":[4.0232000351,50.8349113464],"type":"Point"}
}