{
  "type": "Feature",
  "properties": {
    "iso:country":"BE",
    "sg:address":"Rue De Nazareth 19",
    "sg:city":"Ath",
    "sg:classifiers":[
        {
            "category":"Shopping",
            "subcategory":"Bridal",
            "type":"Retail Goods"
        }
    ],
    "sg:phone":"+32 68 46 68 73",
    "sg:postcode":"7800",
    "sg:province":"Hainaut",
    "sg:tags":[
        "list",
        "-",
        "present",
        "wedding"
    ],
    "wof:name":"Athuart Design",
    "wof:placetype":"venue"
},
  "geometry": {"coordinates":[3.7791469097,50.6301383972],"type":"Point"}
}