{
  "type": "Feature",
  "properties": {
    "addr:full":"Benedenstraat 4 Melle Oost-Vlaanderen 9090",
    "addr:housenumber":"4",
    "addr:postcode":"9090",
    "addr:street":"Benedenstraat",
    "iso:country":"BE",
    "sg:address":"Benedenstraat 4",
    "sg:city":"Melle",
    "sg:classifiers":[
        {
            "category":"Health Services",
            "subcategory":"Health Practitioner",
            "type":"Services"
        }
    ],
    "sg:phone":"+32 9 252 32 70",
    "sg:postcode":"9090",
    "sg:province":"Oost-Vlaanderen",
    "sg:tags":[
        "physiotherapist"
    ],
    "wof:name":"Tack R",
    "wof:placetype":"venue"
},
  "geometry": {"coordinates":[3.8277330399,50.9928894043],"type":"Point"}
}