{
  "type": "Feature",
  "properties": {
    "iso:country":"BE",
    "sg:address":"Statielei 34",
    "sg:city":"Mortsel",
    "sg:classifiers":[
        {
            "category":"Shopping",
            "subcategory":"Baby Store",
            "type":"Retail Goods"
        }
    ],
    "sg:phone":"+32 3 449 24 89",
    "sg:postcode":"2640",
    "sg:province":"Antwerpen",
    "sg:tags":[
        "-",
        "accessory"
    ],
    "wof:name":"Baby Home Bvba",
    "wof:placetype":"venue"
},
  "geometry": {"coordinates":[4.4525561333,51.1703262329],"type":"Point"}
}