{
  "type": "Feature",
  "properties": {
    "iso:country":"BE",
    "sg:address":"Rue De La Station 94",
    "sg:city":"Bi\u00e8vre (graide)",
    "sg:classifiers":[
        {
            "category":"Building & Trades",
            "subcategory":"Construction",
            "type":"Services"
        }
    ],
    "sg:phone":"+32 61 51 11 87",
    "sg:postcode":"5555",
    "sg:province":"Namur",
    "sg:tags":[
        "installation",
        "-",
        "central",
        "heating"
    ],
    "wof:name":"Dion F",
    "wof:placetype":"venue"
},
  "geometry": {"coordinates":[5.0630311966,49.9432563782],"type":"Point"}
}