{
  "type": "Feature",
  "properties": {
    "iso:country":"BE",
    "sg:address":"Industrielaan 2",
    "sg:city":"Overpelt",
    "sg:orig_category":"Fer and acier Fab",
    "sg:phone":"+32 11 80 08 00",
    "sg:postcode":"3900",
    "sg:province":"Limburg",
    "wof:name":"Metalim Staal",
    "wof:placetype":"venue"
},
  "geometry": {"coordinates":[5.3734021187,51.2165107727],"type":"Point"}
}