{
  "type": "Feature",
  "properties": {
    "addr:full":"Stasegemsestraat 150 Kortrijk West-Vlaanderen 8500",
    "addr:housenumber":"150",
    "addr:postcode":"8500",
    "addr:street":"Stasegemsestraat",
    "iso:country":"BE",
    "sg:address":"Stasegemsestraat 150",
    "sg:city":"Kortrijk",
    "sg:classifiers":[
        {
            "category":"Building & Trades",
            "subcategory":"Electrical",
            "type":"Services"
        }
    ],
    "sg:phone":"+32 56 22 11 53",
    "sg:postcode":"8500",
    "sg:province":"West-Vlaanderen",
    "sg:tags":[
        "industrial",
        "-",
        "electric",
        "contractor"
    ],
    "wof:name":"Vanden Berghe E",
    "wof:placetype":"venue"
},
  "geometry": {"coordinates":[3.2836699486,50.8311691284],"type":"Point"}
}