{
  "type": "Feature",
  "properties": {
    "addr:full":"Heirbaan 8 Deinze (gottem) Oost-Vlaanderen 9800",
    "addr:housenumber":"8",
    "addr:postcode":"9800",
    "addr:street":"Heirbaan",
    "iso:country":"BE",
    "sg:address":"Heirbaan 8",
    "sg:city":"Deinze (gottem)",
    "sg:classifiers":[
        {
            "category":"Travel",
            "subcategory":"Bed & Breakfast",
            "type":"Entertainment"
        }
    ],
    "sg:phone":"+32 51 63 40 71",
    "sg:postcode":"9800",
    "sg:province":"Oost-Vlaanderen",
    "sg:tags":[
        "ladder"
    ],
    "wof:name":"De Smet F",
    "wof:placetype":"venue"
},
  "geometry": {"coordinates":[3.4537959099,50.9614143372],"type":"Point"}
}