{
  "type": "Feature",
  "properties": {
    "iso:country":"BE",
    "sg:address":"Kanaaldijk 1",
    "sg:city":"Geel",
    "sg:orig_category":"Kinderopvang",
    "sg:phone":"+32 14 85 23 22",
    "sg:postcode":"2440",
    "sg:province":"Antwerpen",
    "wof:name":"Barbara Deseyn",
    "wof:placetype":"venue"
},
  "geometry": {"coordinates":[4.9826498032,51.2016296387],"type":"Point"}
}