{
  "type": "Feature",
  "properties": {
    "addr:full":"Deinsesteenweg 43 Kruishoutem Oost-Vlaanderen 9770",
    "addr:housenumber":"43",
    "addr:postcode":"9770",
    "addr:street":"Deinsesteenweg",
    "iso:country":"BE",
    "sg:address":"Deinsesteenweg 43",
    "sg:city":"Kruishoutem",
    "sg:orig_category":"Woningbouw",
    "sg:phone":"+32 9 383 53 55",
    "sg:postcode":"9770",
    "sg:province":"Oost-Vlaanderen",
    "wof:name":"Bouwonderneming Saveyn",
    "wof:placetype":"venue"
},
  "geometry": {"coordinates":[3.5305109024,50.9205284119],"type":"Point"}
}