{
  "type": "Feature",
  "properties": {
    "iso:country":"BE",
    "sg:address":"Rue Edouard Deknoop 43",
    "sg:city":"Evere/evere",
    "sg:orig_category":"M\u00e9decins and sp\u00e9cialistes",
    "sg:phone":"+32 2 215 08 16",
    "sg:postcode":"1140",
    "sg:province":"Bruxelles-Capitale",
    "wof:name":"A\u00cfda Le Beau De Hemricourt",
    "wof:placetype":"venue"
},
  "geometry": {"coordinates":[4.3980841637,50.8717384338],"type":"Point"}
}