{
  "type": "Feature",
  "properties": {
    "iso:country":"BE",
    "sg:address":"Hongerbeek 6",
    "sg:city":"Bree",
    "sg:classifiers":[
        {
            "category":"Personal",
            "subcategory":"Beauty Salon",
            "type":"Services"
        }
    ],
    "sg:phone":"+32 89 46 53 47",
    "sg:postcode":"3960",
    "sg:province":"Limburg",
    "wof:name":"Agna",
    "wof:placetype":"venue"
},
  "geometry": {"coordinates":[5.5944190025,51.1405677795],"type":"Point"}
}