{
  "type": "Feature",
  "properties": {
    "iso:country":"BE",
    "sg:address":"Peperkoren 9",
    "sg:city":"Beveren",
    "sg:orig_category":"Mat\u00e9riel m\u00e9dical and orthop\u00e9dique and proth\u00e8ses Fab",
    "sg:phone":"+32 3 775 32 00",
    "sg:postcode":"9120",
    "sg:province":"Oost-Vlaanderen",
    "wof:name":"Verbrugghe",
    "wof:placetype":"venue"
},
  "geometry": {"coordinates":[4.2623801231,51.2165985107],"type":"Point"}
}