{
  "type": "Feature",
  "properties": {
    "iso:country":"BE",
    "sg:address":"Kapelstraat 58",
    "sg:city":"Hove",
    "sg:orig_category":"Drukkerijen and copyshops",
    "sg:phone":"+32 3 455 49 36",
    "sg:postcode":"2540",
    "sg:province":"Antwerpen",
    "wof:name":"Drukkerij J Ouderits",
    "wof:placetype":"venue"
},
  "geometry": {"coordinates":[4.4671959877,51.1545829773],"type":"Point"}
}