{
  "type": "Feature",
  "properties": {
    "iso:country":"BE",
    "sg:address":"Avenue Lavoisier 15",
    "sg:city":"Wavre",
    "sg:orig_category":"Non-Classified Establishments",
    "sg:phone":"+32 10 24 24 44",
    "sg:postcode":"1300",
    "sg:province":"Brabant Wallon",
    "wof:name":"Habi",
    "wof:placetype":"venue"
},
  "geometry": {"coordinates":[4.5925321579,50.7353363037],"type":"Point"}
}