{
  "type": "Feature",
  "properties": {
    "iso:country":"BE",
    "sg:address":"Heikant 69",
    "sg:city":"Meerhout",
    "sg:classifiers":[
        {
            "category":"Real Estate",
            "subcategory":"Architect",
            "type":"Services"
        }
    ],
    "sg:phone":"+32 14 30 19 04",
    "sg:postcode":"2450",
    "sg:province":"Antwerpen",
    "wof:name":"Craps T",
    "wof:placetype":"venue"
},
  "geometry": {"coordinates":[5.0542712212,51.1422462463],"type":"Point"}
}