{
  "type": "Feature",
  "properties": {
    "iso:country":"BE",
    "sg:address":"Wouters Lefebvreplein 16a",
    "sg:city":"Willebroek (blaasveld)",
    "sg:classifiers":[
        {
            "category":"Shopping",
            "subcategory":"Florist",
            "type":"Retail Goods"
        }
    ],
    "sg:phone":"+32 474 45 41 25",
    "sg:postcode":"2830",
    "sg:province":"Antwerpen",
    "wof:name":"Orchideetje",
    "wof:placetype":"venue"
},
  "geometry": {"coordinates":[4.3732099533,51.0565757751],"type":"Point"}
}