{
  "type": "Feature",
  "properties": {
    "addr:full":"Chauss\u00e9e De Douai 25 Tournai (froidmont) Hainaut 7504",
    "addr:housenumber":"25",
    "addr:postcode":"7504",
    "addr:street":"Chausse\u0301E De Douai",
    "iso:country":"BE",
    "sg:address":"Chauss\u00e9e De Douai 25",
    "sg:city":"Tournai (froidmont)",
    "sg:classifiers":[
        {
            "category":"Home & Garden",
            "subcategory":"Garden Supply",
            "type":"Retail Goods"
        }
    ],
    "sg:phone":"+32 69 64 79 76",
    "sg:postcode":"7504",
    "sg:province":"Hainaut",
    "sg:tags":[
        "machine",
        "agricultural",
        "-"
    ],
    "wof:name":"Luyckx",
    "wof:placetype":"venue"
},
  "geometry": {"coordinates":[3.3778440952,50.5997581482],"type":"Point"}
}