{
  "type": "Feature",
  "properties": {
    "addr:full":"Lascheid 3 Burg-reuland/burg-reuland Li\u00e8ge 4790",
    "addr:housenumber":"3",
    "addr:postcode":"4790",
    "addr:street":"Lascheid",
    "iso:country":"BE",
    "sg:address":"Lascheid 3",
    "sg:city":"Burg-reuland/burg-reuland",
    "sg:orig_category":"Rundveehouders",
    "sg:phone":"+32 80 32 92 59",
    "sg:postcode":"4790",
    "sg:province":"Li\u00e8ge",
    "wof:name":"Alois Paquet",
    "wof:placetype":"venue"
},
  "geometry": {"coordinates":[6.1172151566,50.1876945496],"type":"Point"}
}