{
  "type": "Feature",
  "properties": {
    "addr:full":"Grote Baan 12 Zomergem Oost-Vlaanderen 9930",
    "addr:housenumber":"12",
    "addr:postcode":"9930",
    "addr:street":"Grote Baan",
    "iso:country":"BE",
    "sg:address":"Grote Baan 12",
    "sg:city":"Zomergem",
    "sg:orig_category":"H\u00f4tels. Caf\u00e9s",
    "sg:phone":"+32 9 372 86 55",
    "sg:postcode":"9930",
    "sg:province":"Oost-Vlaanderen",
    "wof:name":"Pan",
    "wof:placetype":"venue"
},
  "geometry": {"coordinates":[3.6100740433,51.1198234558],"type":"Point"}
}