{
  "type": "Feature",
  "properties": {
    "iso:country":"BE",
    "sg:address":"Rue J.-b. Loriaux 3bb",
    "sg:city":"Les Bons Villers",
    "sg:orig_category":"Rev\u00eatements pour sols and murs. Eclairage et \u00e9quipements du foyer. Peinture. Rev\u00eatements de sols and",
    "sg:phone":"+32 71 85 11 24",
    "sg:postcode":"6210",
    "sg:province":"Hainaut",
    "wof:name":"Peinture & Deco-melon J.",
    "wof:placetype":"venue"
},
  "geometry": {"coordinates":[4.4511561394,50.5378227234],"type":"Point"}
}