{
  "type": "Feature",
  "properties": {
    "addr:full":"Rue De Savoie 2 Binche Hainaut 7130",
    "addr:housenumber":"2",
    "addr:postcode":"7130",
    "addr:street":"Rue De Savoie",
    "iso:country":"BE",
    "sg:address":"Rue De Savoie 2",
    "sg:city":"Binche",
    "sg:orig_category":"Installation de menuiserie en bois and plastique. Quincailleries. Fabrication and montage de mobilie",
    "sg:phone":"+32 64 36 92 59",
    "sg:postcode":"7130",
    "sg:province":"Hainaut",
    "wof:name":"Frederic Porson",
    "wof:placetype":"venue"
},
  "geometry": {"coordinates":[4.1669921875,50.4134178162],"type":"Point"}
}