{
  "type": "Feature",
  "properties": {
    "addr:full":"Dorpstraas 70 Middelkerke West-Vlaanderen 8432",
    "addr:housenumber":"70",
    "addr:postcode":"8432",
    "addr:street":"Dorpstraas",
    "iso:country":"BE",
    "sg:address":"Dorpstraas 70",
    "sg:city":"Middelkerke",
    "sg:orig_category":"RESTAURANTS: CATERING AND ORGANISATION DE F\u00caTES. SALLES DE CONF\u00c9RENCES AND DE R\u00c9CEPTIONS",
    "sg:phone":"+32 59 30 01 38",
    "sg:postcode":"8432",
    "sg:province":"West-Vlaanderen",
    "wof:name":"Old Fisher",
    "wof:placetype":"venue"
},
  "geometry": {"coordinates":[2.8773488998,51.1767501831],"type":"Point"}
}