{
  "type": "Feature",
  "properties": {
    "addr:full":"Stationsstraat 99 Aalter Oost-Vlaanderen 9880",
    "addr:housenumber":"99",
    "addr:postcode":"9880",
    "addr:street":"Stationsstraat",
    "iso:country":"BE",
    "sg:address":"Stationsstraat 99",
    "sg:city":"Aalter",
    "sg:orig_category":"Assurances. Bureaux de poste",
    "sg:phone":"+32 9 374 12 14",
    "sg:postcode":"9880",
    "sg:province":"Oost-Vlaanderen",
    "wof:name":"De Post",
    "wof:placetype":"venue"
},
  "geometry": {"coordinates":[3.4473690987,51.089138031],"type":"Point"}
}