{
  "type": "Feature",
  "properties": {
    "iso:country":"BE",
    "sg:address":"Plantin En Moretuslei 41",
    "sg:city":"Antwerpen",
    "sg:orig_category":"Rookartikelen",
    "sg:phone":"+32 3 226 23 22",
    "sg:postcode":"2018",
    "sg:province":"Antwerpen",
    "wof:name":"Bela Grosz",
    "wof:placetype":"venue"
},
  "geometry": {"coordinates":[4.4207911491,51.2106361389],"type":"Point"}
}