{
  "type": "Feature",
  "properties": {
    "iso:country":"BE",
    "sg:address":"Wortegemseweg 51",
    "sg:city":"Waregem",
    "sg:classifiers":[
        {
            "category":"Restaurant",
            "type":"Food & Drink"
        }
    ],
    "sg:phone":"+32 56 61 69 54",
    "sg:postcode":"8790",
    "sg:province":"West-Vlaanderen",
    "wof:name":"Hobo",
    "wof:placetype":"venue"
},
  "geometry": {"coordinates":[3.4455521107,50.8756752014],"type":"Point"}
}