{
  "type": "Feature",
  "properties": {
    "iso:country":"BE",
    "sg:address":"Rue Du Bl\u00c9 81",
    "sg:city":"Charleroi",
    "sg:orig_category":"Meubelzaken, woning- and keukeninrichting",
    "sg:phone":"+32 71 70 13 96",
    "sg:postcode":"6031",
    "sg:province":"Hainaut",
    "wof:name":"Fabrigroup",
    "wof:placetype":"venue"
},
  "geometry": {"coordinates":[4.38022995,50.4121742249],"type":"Point"}
}