{
  "type": "Feature",
  "properties": {
    "addr:full":"Huibrechtstraat 1 Lier Antwerpen 2500",
    "addr:housenumber":"1",
    "addr:postcode":"2500",
    "addr:street":"Huibrechtstraat",
    "iso:country":"BE",
    "sg:address":"Huibrechtstraat 1",
    "sg:city":"Lier",
    "sg:orig_category":"Banques and organismes de cr\u00e9dit",
    "sg:phone":"+32 3 480 16 65",
    "sg:postcode":"2500",
    "sg:province":"Antwerpen",
    "wof:name":"Ippa",
    "wof:placetype":"venue"
},
  "geometry": {"coordinates":[4.5716781616,51.1333389282],"type":"Point"}
}