{
  "type": "Feature",
  "properties": {
    "addr:full":"Deinsesteenweg 53 Kruishoutem Oost-Vlaanderen 9770",
    "addr:housenumber":"53",
    "addr:postcode":"9770",
    "addr:street":"Deinsesteenweg",
    "iso:country":"BE",
    "sg:address":"Deinsesteenweg 53",
    "sg:city":"Kruishoutem",
    "sg:classifiers":[
        {
            "category":"Manufacturing",
            "subcategory":"Metals",
            "type":"Manufacturing & Wholesale Goods"
        }
    ],
    "sg:phone":"+32 9 383 72 58",
    "sg:postcode":"9770",
    "sg:province":"Oost-Vlaanderen",
    "sg:tags":[
        "working"
    ],
    "wof:name":"A.g.p. Bvba",
    "wof:placetype":"venue"
},
  "geometry": {"coordinates":[3.5307290554,50.921333313],"type":"Point"}
}