{
  "type": "Feature",
  "properties": {
    "iso:country":"BE",
    "sg:address":"Kloosterstraat 29",
    "sg:city":"Zwijndrecht",
    "sg:classifiers":[
        {
            "category":"Recreation",
            "type":"Entertainment"
        }
    ],
    "sg:phone":"+32 3 252 97 90",
    "sg:postcode":"2070",
    "sg:province":"Antwerpen",
    "sg:tags":[
        "diver",
        "amusement"
    ],
    "wof:name":"Oscar",
    "wof:placetype":"venue"
},
  "geometry": {"coordinates":[4.3486700058,51.2037391663],"type":"Point"}
}