{
  "type": "Feature",
  "properties": {
    "addr:full":"Rue A. Defrise 142 Mons Hainaut 7012",
    "addr:housenumber":"142",
    "addr:postcode":"7012",
    "addr:street":"Rue A. Defrise;Hainaut",
    "iso:country":"BE",
    "sg:address":"Rue A. Defrise 142",
    "sg:city":"Mons",
    "sg:classifiers":[
        {
            "category":"Professional",
            "subcategory":"Accounting & Tax Preparation",
            "type":"Services"
        }
    ],
    "sg:phone":"+32 65 88 49 23",
    "sg:postcode":"7012",
    "sg:province":"Hainaut",
    "sg:tags":[
        "accountant"
    ],
    "wof:name":"Gerard Wettterene",
    "wof:placetype":"venue"
},
  "geometry": {"coordinates":[3.8894600868,50.4481964111],"type":"Point"}
}