{
  "type": "Feature",
  "properties": {
    "iso:country":"BE",
    "sg:address":"Avenue Louis Goblet 220",
    "sg:city":"Saint-ghislain",
    "sg:orig_category":"M\u00e9decins and sp\u00e9cialistes",
    "sg:phone":"+32 65 64 27 13",
    "sg:postcode":"7331",
    "sg:province":"Hainaut",
    "wof:name":"J. Thonnard",
    "wof:placetype":"venue"
},
  "geometry": {"coordinates":[3.8317520618,50.4844169617],"type":"Point"}
}