{
  "type": "Feature",
  "properties": {
    "iso:country":"BE",
    "sg:address":"Warande 41",
    "sg:city":"Laarne",
    "sg:orig_category":"Voedingsspeciaalzaken",
    "sg:phone":"+32 9 368 14 71",
    "sg:postcode":"9270",
    "sg:province":"Oost-Vlaanderen",
    "wof:name":"Ludo Cobbaut",
    "wof:placetype":"venue"
},
  "geometry": {"coordinates":[3.8518280983,51.023525238],"type":"Point"}
}