{
  "type": "Feature",
  "properties": {
    "addr:full":"Grand Place 0 Aubange Luxembourg 6791",
    "addr:housenumber":"0",
    "addr:postcode":"6791",
    "addr:street":"Grand Place",
    "iso:country":"BE",
    "sg:address":"Grand Place 0",
    "sg:city":"Aubange",
    "sg:orig_category":"Diverse kredietdiensten",
    "sg:postcode":"6791",
    "sg:province":"Luxembourg",
    "wof:name":"Bancontact-mister Cash",
    "wof:placetype":"venue"
},
  "geometry": {"coordinates":[5.8368301392,49.5627288818],"type":"Point"}
}