{
  "type": "Feature",
  "properties": {
    "iso:country":"BE",
    "sg:address":"Rue De La Carpi\u00c8re 5",
    "sg:city":"Virton",
    "sg:orig_category":"M\u00e9decins and sp\u00e9cialistes",
    "sg:phone":"+32 63 57 76 96",
    "sg:postcode":"6760",
    "sg:province":"Luxembourg",
    "wof:name":"Claude Authelet",
    "wof:placetype":"venue"
},
  "geometry": {"coordinates":[5.5801692009,49.5786018372],"type":"Point"}
}