{
  "type": "Feature",
  "properties": {
    "addr:full":"Rue Du Beau-mur 54 Li\u00c8ge Li\u00e8ge 4030",
    "addr:housenumber":"54",
    "addr:postcode":"4030",
    "addr:street":"Rue Du Beau-Mur",
    "iso:country":"BE",
    "sg:address":"Rue Du Beau-mur 54",
    "sg:city":"Li\u00c8ge",
    "sg:orig_category":"Artistes ind\u00e9pendants",
    "sg:phone":"+32 4 343 56 17",
    "sg:postcode":"4030",
    "sg:province":"Li\u00e8ge",
    "wof:name":"Palate",
    "wof:placetype":"venue"
},
  "geometry": {"coordinates":[5.588329792,50.6293754578],"type":"Point"}
}