{
  "type": "Feature",
  "properties": {
    "addr:full":"Muizenhol 35 Sint-laureins Oost-Vlaanderen 9988",
    "addr:housenumber":"35",
    "addr:postcode":"9988",
    "addr:street":"Muizenhol",
    "iso:country":"BE",
    "sg:address":"Muizenhol 35",
    "sg:city":"Sint-laureins",
    "sg:classifiers":[
        {
            "category":"Food & Beverages",
            "subcategory":"Fruits & Vegetables",
            "type":"Retail Goods"
        }
    ],
    "sg:phone":"+32 9 379 86 27",
    "sg:postcode":"9988",
    "sg:province":"Oost-Vlaanderen",
    "sg:tags":[
        "l\u00e9gumes",
        "gr"
    ],
    "wof:name":"Etienne Van Der Schueren",
    "wof:placetype":"venue"
},
  "geometry": {"coordinates":[3.6611590385,51.268119812],"type":"Point"}
}