{
  "type": "Feature",
  "properties": {
    "addr:full":"Schuurveld 3 Londerzeel Vlaams-Brabant 1840",
    "addr:housenumber":"3",
    "addr:postcode":"1840",
    "addr:street":"Schuurveld",
    "iso:country":"BE",
    "sg:address":"Schuurveld 3",
    "sg:city":"Londerzeel",
    "sg:classifiers":[
        {
            "category":"Farming",
            "subcategory":"Crops",
            "type":"Manufacturing & Wholesale Goods"
        }
    ],
    "sg:phone":"+32 52 30 95 63",
    "sg:postcode":"1840",
    "sg:province":"Vlaams-Brabant",
    "sg:tags":[
        "vegetable",
        "fruit",
        "-",
        "grower"
    ],
    "wof:name":"Van Den Bergh A",
    "wof:placetype":"venue"
},
  "geometry": {"coordinates":[4.2996912003,50.9960670471],"type":"Point"}
}