{
  "type": "Feature",
  "properties": {
    "addr:full":"Rue De La Bourgogne 20 Juprelle Li\u00e8ge 4452",
    "addr:housenumber":"20",
    "addr:postcode":"4452",
    "addr:street":"Rue De La Bourgogne",
    "iso:country":"BE",
    "sg:address":"Rue De La Bourgogne 20",
    "sg:city":"Juprelle",
    "sg:orig_category":"Gespecialiseerde niet-residenti\u00eble bouw Installatie van metalen schrijnwerk",
    "sg:phone":"+32 4 278 55 12",
    "sg:postcode":"4452",
    "sg:province":"Li\u00e8ge",
    "wof:name":"Jomy",
    "wof:placetype":"venue"
},
  "geometry": {"coordinates":[5.5091848373,50.7263183594],"type":"Point"}
}