{
  "type": "Feature",
  "properties": {
    "iso:country":"BE",
    "sg:address":"Chemin De La Procession 80",
    "sg:city":"Mons",
    "sg:orig_category":"M\u00e9decins and sp\u00e9cialistes",
    "sg:phone":"+32 65 36 08 53",
    "sg:postcode":"7000",
    "sg:province":"Hainaut",
    "wof:name":"Bernard Mathy",
    "wof:placetype":"venue"
},
  "geometry": {"coordinates":[3.9621779919,50.4642868042],"type":"Point"}
}