{
  "type": "Feature",
  "properties": {
    "addr:full":"Markt 16 Ichtegem West-Vlaanderen 8480",
    "addr:housenumber":"16",
    "addr:postcode":"8480",
    "addr:street":"Markt",
    "iso:country":"BE",
    "sg:address":"Markt 16",
    "sg:city":"Ichtegem",
    "sg:classifiers":[
        {
            "category":"Real Estate",
            "subcategory":"Architect",
            "type":"Services"
        }
    ],
    "sg:phone":"+32 51 58 92 47",
    "sg:postcode":"8480",
    "sg:province":"West-Vlaanderen",
    "wof:name":"Sys A",
    "wof:placetype":"venue"
},
  "geometry": {"coordinates":[3.0103569031,51.0915298462],"type":"Point"}
}