{
  "type": "Feature",
  "properties": {
    "iso:country":"BE",
    "sg:address":"Torhoutstraat 49",
    "sg:city":"Hooglede",
    "sg:orig_category":"Producteurs de l\u00e9gumes",
    "sg:phone":"+32 51 72 28 27",
    "sg:postcode":"8830",
    "sg:province":"West-Vlaanderen",
    "wof:name":"Plovier Marcel & Maria",
    "wof:placetype":"venue"
},
  "geometry": {"coordinates":[3.0961060524,51.0055885315],"type":"Point"}
}