{
  "type": "Feature",
  "properties": {
    "iso:country":"BE",
    "sg:address":"Liersesteenweg 35",
    "sg:city":"Mechelen",
    "sg:orig_category":"Reliure and finition",
    "sg:phone":"+32 15 20 93 61",
    "sg:postcode":"2800",
    "sg:province":"Antwerpen",
    "wof:name":"Fa. Masui",
    "wof:placetype":"venue"
},
  "geometry": {"coordinates":[4.4824447632,51.0347976685],"type":"Point"}
}