{
  "type": "Feature",
  "properties": {
    "addr:full":"Rue Gallait 190 Bruxelles (schaerbeek) Bruxelles-Capitale 1030",
    "addr:housenumber":"190",
    "addr:postcode":"1030",
    "addr:street":"Rue Gallait",
    "iso:country":"BE",
    "sg:address":"Rue Gallait 190",
    "sg:city":"Bruxelles (schaerbeek)",
    "sg:classifiers":[
        {
            "category":"Utilities",
            "subcategory":"Telephone",
            "type":"Services"
        }
    ],
    "sg:phone":"+32 2 215 67 59",
    "sg:postcode":"1030",
    "sg:province":"Bruxelles-Capitale",
    "sg:tags":[
        "installation"
    ],
    "wof:name":"Univers Telecom",
    "wof:placetype":"venue"
},
  "geometry": {"coordinates":[4.3709578514,50.8694190979],"type":"Point"}
}