{
  "type": "Feature",
  "properties": {
    "iso:country":"BE",
    "sg:address":"Stefaniestraat 16",
    "sg:city":"Antwerpen",
    "sg:classifiers":[
        {
            "category":"Health Services",
            "subcategory":"Health Practitioner",
            "type":"Services"
        }
    ],
    "sg:phone":"+32 3 248 09 95",
    "sg:postcode":"2018",
    "sg:province":"Antwerpen",
    "sg:tags":[
        "psychologist"
    ],
    "wof:name":"Meeus M",
    "wof:placetype":"venue"
},
  "geometry": {"coordinates":[4.4030451775,51.2050552368],"type":"Point"}
}