{
  "type": "Feature",
  "properties": {
    "addr:full":"Euphrosina Beernaertstraat 56 Oostende West-Vlaanderen 8400",
    "addr:housenumber":"56",
    "addr:postcode":"8400",
    "addr:street":"Beernaertstraat",
    "iso:country":"BE",
    "sg:address":"Euphrosina Beernaertstraat 56",
    "sg:city":"Oostende",
    "sg:classifiers":[
        {
            "category":"Professional",
            "subcategory":"Lawyer & Legal Services",
            "type":"Services"
        }
    ],
    "sg:phone":"+32 59 80 86 81",
    "sg:postcode":"8400",
    "sg:province":"West-Vlaanderen",
    "wof:name":"Bonny V",
    "wof:placetype":"venue"
},
  "geometry": {"coordinates":[2.9147660732,51.2272567749],"type":"Point"}
}