{
  "type": "Feature",
  "properties": {
    "addr:full":"Rue Du Coll\u00c8ge 27 Namur Namur 5000",
    "addr:housenumber":"27",
    "addr:postcode":"5000",
    "addr:street":"Rue Du Colle\u0300Ge",
    "iso:country":"BE",
    "sg:address":"Rue Du Coll\u00c8ge 27",
    "sg:city":"Namur",
    "sg:classifiers":[
        {
            "category":"Restaurant",
            "type":"Food & Drink"
        }
    ],
    "sg:phone":"+32 81 22 71 46",
    "sg:postcode":"5000",
    "sg:province":"Namur",
    "wof:name":"Grand Caf\u00c9 Galer. St.loup",
    "wof:placetype":"venue"
},
  "geometry": {"coordinates":[4.8628749847,50.4636154175],"type":"Point"}
}