{
  "type": "Feature",
  "properties": {
    "iso:country":"BE",
    "sg:address":"Puttestraat 51",
    "sg:city":"Stabroek",
    "sg:orig_category":"Fietsen",
    "sg:phone":"+32 3 664 44 43",
    "sg:postcode":"2940",
    "sg:province":"Antwerpen",
    "wof:name":"Robert Jacqmain",
    "wof:placetype":"venue"
},
  "geometry": {"coordinates":[4.3964848518,51.3535118103],"type":"Point"}
}