{
  "type": "Feature",
  "properties": {
    "addr:full":"Brugsesteenweg 169 Roeselare West-Vlaanderen 8800",
    "addr:housenumber":"169",
    "addr:postcode":"8800",
    "addr:street":"Brugsesteenweg",
    "iso:country":"BE",
    "sg:address":"Brugsesteenweg 169",
    "sg:city":"Roeselare",
    "sg:classifiers":[
        {
            "category":"Home & Garden",
            "subcategory":"Home Furnishings",
            "type":"Retail Goods"
        }
    ],
    "sg:phone":"+32 51 22 80 91",
    "sg:postcode":"8800",
    "sg:province":"West-Vlaanderen",
    "sg:tags":[
        "interior",
        "decoration"
    ],
    "wof:name":"De Witte Duif Bvba",
    "wof:placetype":"venue"
},
  "geometry": {"coordinates":[3.1214718819,50.9557533264],"type":"Point"}
}