{
  "type": "Feature",
  "properties": {
    "addr:full":"Beverlodorp 23 Beringen Limburg 3581",
    "addr:housenumber":"23",
    "addr:postcode":"3581",
    "addr:street":"Beverlodorp",
    "iso:country":"BE",
    "sg:address":"Beverlodorp 23",
    "sg:city":"Beringen",
    "sg:classifiers":[
        {
            "category":"Shopping",
            "subcategory":"Clothing, Apparel, & Fashions",
            "type":"Retail Goods"
        }
    ],
    "sg:phone":"+32 11 34 22 49",
    "sg:postcode":"3581",
    "sg:province":"Limburg",
    "sg:tags":[
        "ondergoed",
        "lingerie"
    ],
    "wof:name":"Huis Wernique",
    "wof:placetype":"venue"
},
  "geometry": {"coordinates":[5.2208609581,51.0879325867],"type":"Point"}
}