{
  "type": "Feature",
  "properties": {
    "addr:full":"Molenstraat 68b1 Turnhout Antwerpen 2300",
    "addr:housenumber":"68b1",
    "addr:postcode":"2300",
    "addr:street":"Molenstraat",
    "iso:country":"BE",
    "sg:address":"Molenstraat 68b1",
    "sg:city":"Turnhout",
    "sg:orig_category":"Advocaten and juridische adviseurs",
    "sg:phone":"+32 14 41 28 74",
    "sg:postcode":"2300",
    "sg:province":"Antwerpen",
    "wof:name":"Ria Timmermans",
    "wof:placetype":"venue"
},
  "geometry": {"coordinates":[4.937584877,51.3212547302],"type":"Point"}
}