{
  "type": "Feature",
  "properties": {
    "iso:country":"BE",
    "sg:address":"Rue Saint-hilaire 31",
    "sg:city":"Huy",
    "sg:classifiers":[
        {
            "category":"Manufacturing",
            "subcategory":"Metals",
            "type":"Manufacturing & Wholesale Goods"
        }
    ],
    "sg:phone":"+32 85 25 10 00",
    "sg:postcode":"4500",
    "sg:province":"Li\u00e8ge",
    "sg:tags":[
        "foundry"
    ],
    "wof:name":"Fonderie Felon & Lange Sa",
    "wof:placetype":"venue"
},
  "geometry": {"coordinates":[5.2304058075,50.5190696716],"type":"Point"}
}