{
  "type": "Feature",
  "properties": {
    "addr:full":"Rue De La Grande Bruy\u00c8re 17ba Braine-le-chateau Brabant Wallon 1440",
    "addr:housenumber":"17ba",
    "addr:postcode":"1440",
    "addr:street":"Rue De La Grande Bruye\u0300Re;Brabant Wallon",
    "iso:country":"BE",
    "sg:address":"Rue De La Grande Bruy\u00c8re 17ba",
    "sg:city":"Braine-le-chateau",
    "sg:orig_category":"Experts-comptables",
    "sg:phone":"+32 2 366 97 55",
    "sg:postcode":"1440",
    "sg:province":"Brabant Wallon",
    "wof:name":"Jean-claude De Nockere",
    "wof:placetype":"venue"
},
  "geometry": {"coordinates":[4.2718000412,50.6715660095],"type":"Point"}
}