{
  "type": "Feature",
  "properties": {
    "addr:full":"Beekstraat 28 Sint-truiden Limburg 3800",
    "addr:housenumber":"28",
    "addr:postcode":"3800",
    "addr:street":"Beekstraat",
    "iso:country":"BE",
    "sg:address":"Beekstraat 28",
    "sg:city":"Sint-truiden",
    "sg:orig_category":"Pr\u00eats hypoth\u00e9caires and cr\u00e9dits immobiliers",
    "sg:phone":"+32 11 68 21 29",
    "sg:postcode":"3800",
    "sg:province":"Limburg",
    "wof:name":"Mijn Huis",
    "wof:placetype":"venue"
},
  "geometry": {"coordinates":[5.1847271919,50.8161201477],"type":"Point"}
}