{
  "type": "Feature",
  "properties": {
    "addr:full":"Legeweg 333 Brugge West-Vlaanderen 8200",
    "addr:housenumber":"333",
    "addr:postcode":"8200",
    "addr:street":"Legeweg",
    "iso:country":"BE",
    "sg:address":"Legeweg 333",
    "sg:city":"Brugge",
    "sg:orig_category":"Producteurs de l\u00e9gumes",
    "sg:phone":"+32 50 31 20 86",
    "sg:postcode":"8200",
    "sg:province":"West-Vlaanderen",
    "wof:name":"Guido Coudeville",
    "wof:placetype":"venue"
},
  "geometry": {"coordinates":[3.1957600117,51.2053184509],"type":"Point"}
}