{
  "type": "Feature",
  "properties": {
    "addr:full":"Ambachtslaan 3 Brecht Antwerpen 2960",
    "addr:housenumber":"3",
    "addr:postcode":"2960",
    "addr:street":"Ambachtslaan",
    "iso:country":"BE",
    "sg:address":"Ambachtslaan 3",
    "sg:city":"Brecht",
    "sg:orig_category":"Antiek Tweedehandsgoederen",
    "sg:phone":"+32 3 313 07 57",
    "sg:postcode":"2960",
    "sg:province":"Antwerpen",
    "wof:name":"Aank.verk. Centrum Kempen",
    "wof:placetype":"venue"
},
  "geometry": {"coordinates":[4.6345930099,51.3538970947],"type":"Point"}
}