{
  "type": "Feature",
  "properties": {
    "iso:country":"BE",
    "sg:address":"Spijker 86",
    "sg:city":"Essen",
    "sg:orig_category":"Articles textiles and tissus de d\u00e9coration Fab. Articles de f\u00eate, farces and attrapes",
    "sg:phone":"+32 3 667 29 73",
    "sg:postcode":"2910",
    "sg:province":"Antwerpen",
    "wof:name":"A A-textieldrukkerij",
    "wof:placetype":"venue"
},
  "geometry": {"coordinates":[4.4686121941,51.4676551819],"type":"Point"}
}