{
  "type": "Feature",
  "properties": {
    "addr:full":"Molenstraat 2 Bree (opitter) Limburg 3960",
    "addr:housenumber":"2",
    "addr:postcode":"3960",
    "addr:street":"Molenstraat",
    "iso:country":"BE",
    "sg:address":"Molenstraat 2",
    "sg:city":"Bree (opitter)",
    "sg:classifiers":[
        {
            "category":"Wholesale",
            "subcategory":"Plants",
            "type":"Manufacturing & Wholesale Goods"
        }
    ],
    "sg:phone":"+32 89 86 68 85",
    "sg:postcode":"3960",
    "sg:province":"Limburg",
    "sg:tags":[
        "whol",
        "flower",
        "-",
        "grower"
    ],
    "wof:name":"Schoolmeesters J",
    "wof:placetype":"venue"
},
  "geometry": {"coordinates":[5.604403019,51.1422729492],"type":"Point"}
}