{
  "type": "Feature",
  "properties": {
    "addr:full":"Nijvelsebaan 16a Huldenberg Vlaams-Brabant 3040",
    "addr:housenumber":"16a",
    "addr:postcode":"3040",
    "addr:street":"Nijvelsebaan",
    "iso:country":"BE",
    "sg:address":"Nijvelsebaan 16a",
    "sg:city":"Huldenberg",
    "sg:orig_category":"Dakwerken",
    "sg:phone":"+32 16 47 33 26",
    "sg:postcode":"3040",
    "sg:province":"Vlaams-Brabant",
    "wof:name":"Christiaan Jacobs",
    "wof:placetype":"venue"
},
  "geometry": {"coordinates":[4.598482132,50.7822380066],"type":"Point"}
}