{
  "type": "Feature",
  "properties": {
    "iso:country":"BE",
    "sg:address":"Rue Des D\u00c9port\u00c9s 82",
    "sg:city":"Arlon",
    "sg:orig_category":"M\u00e9decins and sp\u00e9cialistes",
    "sg:phone":"+32 63 23 03 83",
    "sg:postcode":"6700",
    "sg:province":"Luxembourg",
    "wof:name":"Bernard Vincken",
    "wof:placetype":"venue"
},
  "geometry": {"coordinates":[5.8208508492,49.6791954041],"type":"Point"}
}