{
  "type": "Feature",
  "properties": {
    "addr:full":"All\u00c9e Des Sorbiers 35 Neupre Li\u00e8ge 4120",
    "addr:housenumber":"35",
    "addr:postcode":"4120",
    "addr:street":"Alle\u0301E Des Sorbiers",
    "iso:country":"BE",
    "sg:address":"All\u00c9e Des Sorbiers 35",
    "sg:city":"Neupre",
    "sg:orig_category":"Gespecialiseerde residenti\u00eble bouw",
    "sg:phone":"+32 4 371 59 13",
    "sg:postcode":"4120",
    "sg:province":"Li\u00e8ge",
    "wof:name":"Batilogis",
    "wof:placetype":"venue"
},
  "geometry": {"coordinates":[5.4860100746,50.5402908325],"type":"Point"}
}