{
  "type": "Feature",
  "properties": {
    "addr:full":"Kanaalstraat 14 Zandhoven Antwerpen 2240",
    "addr:housenumber":"14",
    "addr:postcode":"2240",
    "addr:street":"Kanaalstraat",
    "iso:country":"BE",
    "sg:address":"Kanaalstraat 14",
    "sg:city":"Zandhoven",
    "sg:orig_category":"Sportterreinen and installaties behalve sportcentra",
    "sg:phone":"+32 3 485 60 20",
    "sg:postcode":"2240",
    "sg:province":"Antwerpen",
    "wof:name":"R.c. Massenhoven",
    "wof:placetype":"venue"
},
  "geometry": {"coordinates":[4.6362781525,51.1919975281],"type":"Point"}
}