{
  "type": "Feature",
  "properties": {
    "iso:country":"BE",
    "sg:address":"Eduard Arsenstraat 13",
    "sg:city":"Mortsel",
    "sg:orig_category":"Herstellingen and onderhoud van auto's",
    "sg:phone":"+32 3 449 02 34",
    "sg:postcode":"2640",
    "sg:province":"Antwerpen",
    "wof:name":"Popular Technics",
    "wof:placetype":"venue"
},
  "geometry": {"coordinates":[4.4456048012,51.1687736511],"type":"Point"}
}