{
  "type": "Feature",
  "properties": {
    "iso:country":"BE",
    "sg:address":"Chauss\u00e9e De Wavre 64a",
    "sg:city":"Perwez",
    "sg:classifiers":[
        {
            "category":"Wholesale",
            "subcategory":"Hardware",
            "type":"Manufacturing & Wholesale Goods"
        }
    ],
    "sg:phone":"+32 81 65 50 73",
    "sg:postcode":"1360",
    "sg:province":"Brabant Wallon",
    "sg:tags":[
        "lubricating",
        "compound"
    ],
    "wof:name":"Jacqmotte Scrl Ets",
    "wof:placetype":"venue"
},
  "geometry": {"coordinates":[4.8033800125,50.6295204163],"type":"Point"}
}