{
  "type": "Feature",
  "properties": {
    "addr:full":"Rue J.dulait 42 Charleroi Hainaut 6001",
    "addr:housenumber":"42",
    "addr:postcode":"6001",
    "addr:street":"Rue J.Dulait;Hainaut",
    "iso:country":"BE",
    "sg:address":"Rue J.dulait 42",
    "sg:city":"Charleroi",
    "sg:orig_category":"Magasins sp\u00e9cialis\u00e9s",
    "sg:phone":"+32 71 47 33 61",
    "sg:postcode":"6001",
    "sg:province":"Hainaut",
    "wof:name":"Trans Energie",
    "wof:placetype":"venue"
},
  "geometry": {"coordinates":[4.4448251724,50.3973655701],"type":"Point"}
}