{
  "type": "Feature",
  "properties": {
    "iso:country":"BE",
    "sg:address":"Chauss\u00c9e De Waterloo 825b",
    "sg:city":"Ukkel/uccle",
    "sg:orig_category":"Diverse producten Gh Dranken Voedingsspeciaalzaken",
    "sg:phone":"+32 2 374 16 63",
    "sg:postcode":"1180",
    "sg:province":"Bruxelles-Capitale",
    "wof:name":"Upignac Le Foie Gras",
    "wof:placetype":"venue"
},
  "geometry": {"coordinates":[4.3688788414,50.8103866577],"type":"Point"}
}