{
  "type": "Feature",
  "properties": {
    "addr:full":"Chauss\u00e9e D'alsemberg 243 Bruxelles (forest) Bruxelles-Capitale 1190",
    "addr:housenumber":"243",
    "addr:postcode":"1190",
    "addr:street":"Chausse\u0301E D'Alsemberg",
    "iso:country":"BE",
    "sg:address":"Chauss\u00e9e D'alsemberg 243",
    "sg:city":"Bruxelles (forest)",
    "sg:classifiers":[
        {
            "category":"Health Services",
            "subcategory":"Doctor",
            "type":"Services"
        }
    ],
    "sg:phone":"+32 495 10 69 02",
    "sg:postcode":"1190",
    "sg:province":"Bruxelles-Capitale",
    "sg:tags":[
        "psychotherapist",
        "psychoanalyst"
    ],
    "wof:name":"Bernard N",
    "wof:placetype":"venue"
},
  "geometry": {"coordinates":[4.3362002373,50.8246688843],"type":"Point"}
}