{
  "type": "Feature",
  "properties": {
    "iso:country":"BE",
    "sg:address":"Houtmarkt 2",
    "sg:city":"Aalst",
    "sg:orig_category":"M\u00e9decins and sp\u00e9cialistes",
    "sg:phone":"+32 53 21 42 88",
    "sg:postcode":"9300",
    "sg:province":"Oost-Vlaanderen",
    "wof:name":"Philippe Schockaert",
    "wof:placetype":"venue"
},
  "geometry": {"coordinates":[4.0442409515,50.934967041],"type":"Point"}
}