{
  "type": "Feature",
  "properties": {
    "iso:country":"BE",
    "sg:address":"Heistse Hoekstraat 7ba",
    "sg:city":"Heist-op-den-berg",
    "sg:orig_category":"Gespecialiseerde residenti\u00eble bouw",
    "sg:phone":"+32 15 24 52 36",
    "sg:postcode":"2220",
    "sg:province":"Antwerpen",
    "wof:name":"Pardon Service Bedrijf",
    "wof:placetype":"venue"
},
  "geometry": {"coordinates":[4.7064609528,51.057559967],"type":"Point"}
}