{
  "type": "Feature",
  "properties": {
    "addr:full":"Riemsterweg 427 Bilzen Limburg 3740",
    "addr:housenumber":"427",
    "addr:postcode":"3740",
    "iso:country":"BE",
    "sg:address":"Riemsterweg 427",
    "sg:city":"Bilzen",
    "sg:orig_category":"Banken and kredietinstellingen",
    "sg:phone":"+32 12 45 51 27",
    "sg:postcode":"3740",
    "sg:province":"Limburg",
    "wof:name":"Bacob",
    "wof:placetype":"venue"
},
  "geometry": {"coordinates":[5.5292901993,50.8601989746],"type":"Point"}
}