{
  "type": "Feature",
  "properties": {
    "addr:full":"Rue De Bosquetville 3 Charleroi Hainaut 6000",
    "addr:housenumber":"3",
    "addr:postcode":"6000",
    "addr:street":"Rue De Bosquetville;Hainaut",
    "iso:country":"BE",
    "sg:address":"Rue De Bosquetville 3",
    "sg:city":"Charleroi",
    "sg:orig_category":"Bouwmaterialen Gh Hout and afgeleiden Gh IJzerwaren, bouw- and verfmaterialen",
    "sg:phone":"+32 71 31 44 11",
    "sg:postcode":"6000",
    "sg:province":"Hainaut",
    "wof:name":"Negleman",
    "wof:placetype":"venue"
},
  "geometry": {"coordinates":[4.449534893,50.405216217],"type":"Point"}
}