{
  "type": "Feature",
  "properties": {
    "addr:full":"Veurnseweg 526 Ieper (elverdinge) West-Vlaanderen 8906",
    "addr:housenumber":"526",
    "addr:postcode":"8906",
    "addr:street":"Veurnseweg",
    "iso:country":"BE",
    "sg:address":"Veurnseweg 526",
    "sg:city":"Ieper (elverdinge)",
    "sg:classifiers":[
        {
            "category":"Shopping",
            "subcategory":"Antiques",
            "type":"Retail Goods"
        }
    ],
    "sg:phone":"+32 57 42 16 98",
    "sg:postcode":"8906",
    "sg:province":"West-Vlaanderen",
    "wof:name":"Brocanterie (de)",
    "wof:placetype":"venue"
},
  "geometry": {"coordinates":[2.8208749294,50.884677887],"type":"Point"}
}