{
  "type": "Feature",
  "properties": {
    "iso:country":"BE",
    "sg:address":"Heiderfeld 28",
    "sg:city":"Amel",
    "sg:classifiers":[
        {
            "category":"Manufacturing",
            "subcategory":"Lumber",
            "type":"Manufacturing & Wholesale Goods"
        }
    ],
    "sg:phone":"+32 80 34 04 69",
    "sg:postcode":"4770",
    "sg:province":"Li\u00e8ge",
    "sg:tags":[
        "sawdust",
        "shaving"
    ],
    "wof:name":"Fehring-weckmann Sprl",
    "wof:placetype":"venue"
},
  "geometry": {"coordinates":[6.1627559662,50.3523101807],"type":"Point"}
}