{
  "type": "Feature",
  "properties": {
    "addr:full":"Luikersteenweg 539 Lommel Limburg 3920",
    "addr:housenumber":"539",
    "addr:postcode":"3920",
    "addr:street":"Luikersteenweg",
    "iso:country":"BE",
    "sg:address":"Luikersteenweg 539",
    "sg:city":"Lommel",
    "sg:orig_category":"Installation \u00e9lectrique r\u00e9sidentielle",
    "sg:phone":"+32 11 64 26 75",
    "sg:postcode":"3920",
    "sg:province":"Limburg",
    "wof:name":"Adrianus Van Asten",
    "wof:placetype":"venue"
},
  "geometry": {"coordinates":[5.3755497932,51.2355194092],"type":"Point"}
}