{
  "type": "Feature",
  "properties": {
    "iso:country":"BE",
    "sg:address":"Turnhoutsebaan 159ba",
    "sg:city":"Malle",
    "sg:orig_category":"Fleurs and plantes. Jardinage",
    "sg:phone":"+32 3 309 27 48",
    "sg:postcode":"2390",
    "sg:province":"Antwerpen",
    "wof:name":"Fa. De Keyser-de Proost",
    "wof:placetype":"venue"
},
  "geometry": {"coordinates":[4.7636818886,51.3017158508],"type":"Point"}
}