{
  "type": "Feature",
  "properties": {
    "addr:full":"Kloosterlei 11 Sint-katelijne-waver (onze-lieve-vrouw-waver) Antwerpen 2861",
    "addr:housenumber":"11",
    "addr:postcode":"2861",
    "addr:street":"Kloosterlei",
    "iso:country":"BE",
    "sg:address":"Kloosterlei 11",
    "sg:city":"Sint-katelijne-waver (onze-lieve-vrouw-waver)",
    "sg:classifiers":[
        {
            "category":"Building & Trades",
            "subcategory":"Equipment Rental",
            "type":"Services"
        }
    ],
    "sg:phone":"+32 15 76 13 33",
    "sg:postcode":"2861",
    "sg:province":"Antwerpen",
    "sg:tags":[
        "sound",
        "-",
        "system"
    ],
    "wof:name":"Saelens D",
    "wof:placetype":"venue"
},
  "geometry": {"coordinates":[4.5768451691,51.0633010864],"type":"Point"}
}