{
  "type": "Feature",
  "properties": {
    "iso:country":"BE",
    "sg:address":"Weg Naar As 140 Box 1",
    "sg:city":"Genk",
    "sg:classifiers":[
        {
            "category":"Professional",
            "subcategory":"Lawyer & Legal Services",
            "type":"Services"
        }
    ],
    "sg:phone":"+32 89 32 91 91",
    "sg:postcode":"3600",
    "sg:province":"Limburg",
    "wof:name":"Keybeck Bart",
    "wof:placetype":"venue"
},
  "geometry": {"coordinates":[5.5149312019,50.9715690613],"type":"Point"}
}