{
  "type": "Feature",
  "properties": {
    "addr:full":"Hoogstraat 177 Lierde (sint-maria-lierde) Oost-Vlaanderen 9570",
    "addr:housenumber":"177",
    "addr:postcode":"9570",
    "addr:street":"Hoogstraat",
    "iso:country":"BE",
    "sg:address":"Hoogstraat 177",
    "sg:city":"Lierde (sint-maria-lierde)",
    "sg:classifiers":[
        {
            "category":"Shopping",
            "subcategory":"Bicycles & Sporting Goods",
            "type":"Retail Goods"
        }
    ],
    "sg:phone":"+32 55 42 28 60",
    "sg:postcode":"9570",
    "sg:province":"Oost-Vlaanderen",
    "sg:tags":[
        "-"
    ],
    "wof:name":"Meurrens F",
    "wof:placetype":"venue"
},
  "geometry": {"coordinates":[3.8090341091,50.8123779297],"type":"Point"}
}