{
  "type": "Feature",
  "properties": {
    "addr:full":"Avenue De La Chasse 65 Bruxelles (etterbeek) Bruxelles-Capitale 1040",
    "addr:housenumber":"65",
    "addr:postcode":"1040",
    "addr:street":"Avenue De La Chasse",
    "iso:country":"BE",
    "sg:address":"Avenue De La Chasse 65",
    "sg:city":"Bruxelles (etterbeek)",
    "sg:classifiers":[
        {
            "category":"Shopping",
            "subcategory":"Shoes",
            "type":"Retail Goods"
        }
    ],
    "sg:phone":"+32 2 647 44 92",
    "sg:postcode":"1040",
    "sg:province":"Bruxelles-Capitale",
    "sg:tags":[
        "slipper",
        "-"
    ],
    "wof:name":"Palais De La Pantoufle",
    "wof:placetype":"venue"
},
  "geometry": {"coordinates":[4.3916659355,50.8321228027],"type":"Point"}
}