{
  "type": "Feature",
  "properties": {
    "iso:country":"BE",
    "sg:address":"Iepersestraat 40",
    "sg:city":"Roeselare",
    "sg:orig_category":"V\u00eatements",
    "sg:phone":"+32 51 20 06 17",
    "sg:postcode":"8800",
    "sg:province":"West-Vlaanderen",
    "wof:name":"De Regenboog",
    "wof:placetype":"venue"
},
  "geometry": {"coordinates":[3.1223270893,50.9424743652],"type":"Point"}
}