{
  "type": "Feature",
  "properties": {
    "iso:country":"BE",
    "sg:address":"Oude Baan 360",
    "sg:city":"Maasmechelen (eisden)",
    "sg:classifiers":[
        {
            "category":"Bars & Pubs",
            "type":"Food & Drink"
        }
    ],
    "sg:phone":"+32 89 77 79 24",
    "sg:postcode":"3630",
    "sg:province":"Limburg",
    "wof:name":"Giostra (la)",
    "wof:placetype":"venue"
},
  "geometry": {"coordinates":[5.6836428642,50.970451355],"type":"Point"}
}