{
  "type": "Feature",
  "properties": {
    "addr:full":"Skaldenstraat 72 Gent Oost-Vlaanderen 9042",
    "addr:housenumber":"72",
    "addr:postcode":"9042",
    "addr:street":"Skaldenstraat;Oost-Vlaanderen",
    "iso:country":"BE",
    "sg:address":"Skaldenstraat 72",
    "sg:city":"Gent",
    "sg:classifiers":[
        {
            "category":"Government",
            "subcategory":"Department Of Motor Vehicles",
            "type":"Public Place"
        }
    ],
    "sg:phone":"+32 9 255 57 00",
    "sg:postcode":"9042",
    "sg:province":"Oost-Vlaanderen",
    "sg:tags":[
        "equipment",
        "industrial",
        "transport",
        "motor-cars"
    ],
    "wof:name":"Plastal Nv",
    "wof:placetype":"venue"
},
  "geometry": {"coordinates":[3.7816700935,51.1223831177],"type":"Point"}
}