{
  "type": "Feature",
  "properties": {
    "iso:country":"BE",
    "sg:address":"Dorp 35",
    "sg:city":"Lommel",
    "sg:classifiers":[
        {
            "category":"Bars & Pubs",
            "type":"Food & Drink"
        }
    ],
    "sg:phone":"+32 11 54 41 04",
    "sg:postcode":"3920",
    "sg:province":"Limburg",
    "wof:name":"Melchior",
    "wof:placetype":"venue"
},
  "geometry": {"coordinates":[5.3088569641,51.2304344177],"type":"Point"}
}