{
  "type": "Feature",
  "properties": {
    "addr:full":"Bonny 12 Nassogne Luxembourg 6951",
    "addr:housenumber":"12",
    "addr:postcode":"6951",
    "addr:street":"Bonny",
    "iso:country":"BE",
    "sg:address":"Bonny 12",
    "sg:city":"Nassogne",
    "sg:classifiers":[
        {
            "category":"Arena",
            "subcategory":"Sports Club",
            "type":"Entertainment"
        }
    ],
    "sg:phone":"+32 84 34 41 94",
    "sg:postcode":"6951",
    "sg:province":"Luxembourg",
    "sg:tags":[
        "de"
    ],
    "wof:name":"C.c. De Bande",
    "wof:placetype":"venue"
},
  "geometry": {"coordinates":[5.4198231697,50.1669082642],"type":"Point"}
}