{
  "type": "Feature",
  "properties": {
    "addr:full":"Kortrijkseweg 352 Waregem West-Vlaanderen 8791",
    "addr:housenumber":"352",
    "addr:postcode":"8791",
    "iso:country":"BE",
    "sg:address":"Kortrijkseweg 352",
    "sg:city":"Waregem",
    "sg:orig_category":"Antiquit\u00e9s. Installation de menuiserie en bois and plastique",
    "sg:phone":"+32 56 71 67 92",
    "sg:postcode":"8791",
    "sg:province":"West-Vlaanderen",
    "wof:name":"Johan Decavel",
    "wof:placetype":"venue"
},
  "geometry": {"coordinates":[3.358068943,50.8792114258],"type":"Point"}
}