{
  "type": "Feature",
  "properties": {
    "addr:full":"Leegstraat 89 Oostrozebeke West-Vlaanderen 8780",
    "addr:housenumber":"89",
    "addr:postcode":"8780",
    "addr:street":"Leegstraat",
    "iso:country":"BE",
    "sg:address":"Leegstraat 89",
    "sg:city":"Oostrozebeke",
    "sg:orig_category":"R\u00e9parations d'appareils \u00e9lectrom\u00e9nagers. Electrom\u00e9nager, t\u00e9l\u00e9visions and radios",
    "sg:phone":"+32 56 66 67 11",
    "sg:postcode":"8780",
    "sg:province":"West-Vlaanderen",
    "wof:name":"Huis Vorwerk",
    "wof:placetype":"venue"
},
  "geometry": {"coordinates":[3.3184769154,50.9175415039],"type":"Point"}
}