{
  "type": "Feature",
  "properties": {
    "addr:full":"Avenue De C\u00eeteaux 15 Ottignies-louvain-la-neuve (louvain-la-neuve) Brabant Wallon 1348",
    "addr:housenumber":"15",
    "addr:postcode":"1348",
    "addr:street":"Avenue De Ci\u0302Teaux",
    "iso:country":"BE",
    "sg:address":"Avenue De C\u00eeteaux 15",
    "sg:city":"Ottignies-louvain-la-neuve (louvain-la-neuve)",
    "sg:classifiers":[
        {
            "category":"Parking",
            "subcategory":"Bicycle",
            "type":"Transportation"
        }
    ],
    "sg:phone":"+32 10 41 53 46",
    "sg:postcode":"1348",
    "sg:province":"Brabant Wallon",
    "sg:tags":[
        "chiropodist"
    ],
    "wof:name":"Seghers Michette",
    "wof:placetype":"venue"
},
  "geometry": {"coordinates":[4.6195631027,50.6762428284],"type":"Point"}
}