{
  "type": "Feature",
  "properties": {
    "addr:full":"Cyriel Buyssestraat 14 Nazareth Oost-Vlaanderen 9810",
    "addr:housenumber":"14",
    "addr:postcode":"9810",
    "addr:street":"Cyriel Buyssestraat",
    "iso:country":"BE",
    "sg:address":"Cyriel Buyssestraat 14",
    "sg:city":"Nazareth",
    "sg:orig_category":"G\u00e9om\u00e8tres",
    "sg:phone":"+32 9 385 69 11",
    "sg:postcode":"9810",
    "sg:province":"Oost-Vlaanderen",
    "wof:name":"Willy Vander Donck",
    "wof:placetype":"venue"
},
  "geometry": {"coordinates":[3.6361689568,50.9599723816],"type":"Point"}
}