{
  "type": "Feature",
  "properties": {
    "addr:full":"Rue Dos Fanchon 20 Liege Li\u00e8ge 4020",
    "addr:housenumber":"20",
    "addr:postcode":"4020",
    "addr:street":"Rue Dos Fanchon",
    "iso:country":"BE",
    "sg:address":"Rue Dos Fanchon 20",
    "sg:city":"Liege",
    "sg:classifiers":[
        {
            "category":"Professional",
            "subcategory":"Business Services",
            "type":"Services"
        }
    ],
    "sg:phone":"+32 4 342 41 82",
    "sg:postcode":"4020",
    "sg:province":"Li\u00e8ge",
    "sg:tags":[
        "aux",
        "diver",
        "entreprises"
    ],
    "wof:name":"Agence A S I",
    "wof:placetype":"venue"
},
  "geometry": {"coordinates":[5.5889139175,50.6458206177],"type":"Point"}
}