{
  "type": "Feature",
  "properties": {
    "addr:full":"Hoogstraat 118b1 As Limburg 3668",
    "addr:housenumber":"118b1",
    "addr:postcode":"3668",
    "addr:street":"Hoogstraat",
    "iso:country":"BE",
    "sg:address":"Hoogstraat 118b1",
    "sg:city":"As",
    "sg:orig_category":"Banques and organismes de cr\u00e9dit",
    "sg:phone":"+32 89 65 81 25",
    "sg:postcode":"3668",
    "sg:province":"Limburg",
    "wof:name":"Kbc",
    "wof:placetype":"venue"
},
  "geometry": {"coordinates":[5.6011309624,51.01537323],"type":"Point"}
}