{
  "type": "Feature",
  "properties": {
    "addr:full":"Avenue Albert I 18a Rixensart Brabant Wallon 1332",
    "addr:housenumber":"18a",
    "addr:postcode":"1332",
    "addr:street":"Avenue Albert I;Wallon",
    "iso:country":"BE",
    "sg:address":"Avenue Albert I 18a",
    "sg:city":"Rixensart",
    "sg:classifiers":[
        {
            "category":"Personal",
            "subcategory":"Beauty Salon",
            "type":"Services"
        }
    ],
    "sg:phone":"+32 2 652 13 50",
    "sg:postcode":"1332",
    "sg:province":"Brabant Wallon",
    "sg:tags":[
        "de",
        "coiffure"
    ],
    "wof:name":"Touche",
    "wof:placetype":"venue"
},
  "geometry": {"coordinates":[4.4889521599,50.7272911072],"type":"Point"}
}