{
  "type": "Feature",
  "properties": {
    "addr:full":"Northlaan 15 Oostende West-Vlaanderen 8400",
    "addr:housenumber":"15",
    "addr:postcode":"8400",
    "addr:street":"Northlaan",
    "iso:country":"BE",
    "sg:address":"Northlaan 15",
    "sg:city":"Oostende",
    "sg:orig_category":"Jeux de hasard",
    "sg:phone":"+32 59 51 10 33",
    "sg:postcode":"8400",
    "sg:province":"West-Vlaanderen",
    "wof:name":"Agence Hippique Dumoulin",
    "wof:placetype":"venue"
},
  "geometry": {"coordinates":[2.8909819126,51.2168121338],"type":"Point"}
}