{
  "type": "Feature",
  "properties": {
    "iso:country":"BE",
    "sg:address":"Polderstraat 33",
    "sg:city":"Westerlo",
    "sg:classifiers":[
        {
            "category":"Banks & Credit Unions",
            "subcategory":"Investment Brokerage",
            "type":"Services"
        }
    ],
    "sg:phone":"+32 14 54 81 09",
    "sg:postcode":"2260",
    "sg:province":"Antwerpen",
    "sg:tags":[
        "jean",
        "casual",
        "wear"
    ],
    "wof:name":"Just In",
    "wof:placetype":"venue"
},
  "geometry": {"coordinates":[4.9156942368,51.0848197937],"type":"Point"}
}