{
  "type": "Feature",
  "properties": {
    "addr:full":"Rue Des D'joyeux Wallons 71 Seraing Li\u00e8ge 4100",
    "addr:housenumber":"71",
    "addr:postcode":"4100",
    "addr:street":"Rue Des D'Joyeux Wallons",
    "iso:country":"BE",
    "sg:address":"Rue Des D'joyeux Wallons 71",
    "sg:city":"Seraing",
    "sg:orig_category":"Schoonheidssalons",
    "sg:phone":"+32 4 330 91 55",
    "sg:postcode":"4100",
    "sg:province":"Li\u00e8ge",
    "wof:name":"Sandrine Giudici",
    "wof:placetype":"venue"
},
  "geometry": {"coordinates":[5.5510811806,50.562046051],"type":"Point"}
}