{
  "type": "Feature",
  "properties": {
    "addr:full":"Gr. De Smet De Naeyerln 79 Kortrijk West-Vlaanderen 8500",
    "addr:housenumber":"79",
    "addr:postcode":"8500",
    "addr:street":"Gr. De Smet De Naeyerln",
    "iso:country":"BE",
    "sg:address":"Gr. De Smet De Naeyerln 79",
    "sg:city":"Kortrijk",
    "sg:classifiers":[
        {
            "category":"Shopping Center",
            "type":"Public Place"
        }
    ],
    "sg:phone":"+32 56 35 50 08",
    "sg:postcode":"8500",
    "sg:province":"West-Vlaanderen",
    "sg:tags":[
        "enseignement",
        "formation"
    ],
    "wof:name":"All Language Services",
    "wof:placetype":"venue"
},
  "geometry": {"coordinates":[3.256581068,50.8346633911],"type":"Point"}
}