{
  "type": "Feature",
  "properties": {
    "addr:full":"Prinses Clementinalaan 1 Gent Oost-Vlaanderen 9000",
    "addr:housenumber":"1",
    "addr:postcode":"9000",
    "addr:street":"Prinses Clementinalaan;Oost-Vlaanderen",
    "iso:country":"BE",
    "sg:address":"Prinses Clementinalaan 1",
    "sg:city":"Gent",
    "sg:orig_category":"Installatie van houten of kunststof schrijnwerk Installatie van metalen schrijnwerk Verlichting and ",
    "sg:phone":"+32 9 222 38 08",
    "sg:postcode":"9000",
    "sg:province":"Oost-Vlaanderen",
    "wof:name":"Stor'shop",
    "wof:placetype":"venue"
},
  "geometry": {"coordinates":[3.715708971,51.0347862244],"type":"Point"}
}