{
  "type": "Feature",
  "properties": {
    "addr:full":"Elisabethlaan 289 Oostende West-Vlaanderen 8400",
    "addr:housenumber":"289",
    "addr:postcode":"8400",
    "addr:street":"Elisabethlaan",
    "iso:country":"BE",
    "sg:address":"Elisabethlaan 289",
    "sg:city":"Oostende",
    "sg:orig_category":"M\u00e9decins and sp\u00e9cialistes",
    "sg:phone":"+32 59 70 78 73",
    "sg:postcode":"8400",
    "sg:province":"West-Vlaanderen",
    "wof:name":"Roland Matton",
    "wof:placetype":"venue"
},
  "geometry": {"coordinates":[2.9041669369,51.2139472961],"type":"Point"}
}