{
  "type": "Feature",
  "properties": {
    "iso:country":"BE",
    "sg:address":"Kleine Molenstraat 4",
    "sg:city":"Lauwe",
    "sg:classifiers":[
        {
            "category":"Manufacturing",
            "subcategory":"Signs",
            "type":"Manufacturing & Wholesale Goods"
        }
    ],
    "sg:phone":"+32 56 40 15 13",
    "sg:postcode":"8930",
    "sg:province":"West-Vlaanderen",
    "sg:tags":[
        "car",
        "lettering"
    ],
    "wof:name":"Ingels I.c.z.",
    "wof:placetype":"venue"
},
  "geometry": {"coordinates":[3.1209149361,50.7961845398],"type":"Point"}
}