{
  "type": "Feature",
  "properties": {
    "addr:full":"Galerie De La Toison D'or 392 Bruxelles (ixelles) Bruxelles-Capitale 1050",
    "addr:housenumber":"392",
    "addr:postcode":"1050",
    "addr:street":"Galerie De La Toison D'Or",
    "iso:country":"BE",
    "sg:address":"Galerie De La Toison D'or 392",
    "sg:city":"Bruxelles (ixelles)",
    "sg:classifiers":[
        {
            "category":"Shopping",
            "subcategory":"Clothing, Apparel, & Fashions",
            "type":"Retail Goods"
        }
    ],
    "sg:phone":"+32 2 512 77 70",
    "sg:postcode":"1050",
    "sg:province":"Bruxelles-Capitale",
    "sg:tags":[
        "boutique"
    ],
    "wof:name":"Gazella",
    "wof:placetype":"venue"
},
  "geometry": {"coordinates":[4.3798799515,50.8206710815],"type":"Point"}
}