{
  "type": "Feature",
  "properties": {
    "addr:full":"Langveldstraat 50 Hasselt Limburg 3500",
    "addr:housenumber":"50",
    "addr:postcode":"3500",
    "addr:street":"Langveldstraat",
    "iso:country":"BE",
    "sg:address":"Langveldstraat 50",
    "sg:city":"Hasselt",
    "sg:orig_category":"Epuration des eaux",
    "sg:phone":"+32 11 27 01 12",
    "sg:postcode":"3500",
    "sg:province":"Limburg",
    "wof:name":"Cuvenet",
    "wof:placetype":"venue"
},
  "geometry": {"coordinates":[5.3540377617,50.9177360535],"type":"Point"}
}