{
  "type": "Feature",
  "properties": {
    "iso:country":"BE",
    "sg:address":"Hippokrateslaan 54",
    "sg:city":"Sint-lambrechts-woluwe/woluwe-saint-lambert",
    "sg:orig_category":"Artsen and specialisten",
    "sg:phone":"+32 2 764 54 74",
    "sg:postcode":"1200",
    "sg:province":"Bruxelles-Capitale",
    "wof:name":"Jean-claude Henquin",
    "wof:placetype":"venue"
},
  "geometry": {"coordinates":[4.4552679062,50.8524780273],"type":"Point"}
}