{
  "type": "Feature",
  "properties": {
    "addr:full":"Rue Miville 6 Seraing (jemeppe-sur-meuse) Li\u00e8ge 4101",
    "addr:housenumber":"6",
    "addr:postcode":"4101",
    "addr:street":"Rue Miville;Jemeppe-Sur-Meuse",
    "iso:country":"BE",
    "sg:address":"Rue Miville 6",
    "sg:city":"Seraing (jemeppe-sur-meuse)",
    "sg:classifiers":[
        {
            "category":"Professional",
            "subcategory":"Credit Reporting & Collection",
            "type":"Services"
        }
    ],
    "sg:phone":"+32 4 231 14 24",
    "sg:postcode":"4101",
    "sg:province":"Li\u00e8ge",
    "sg:tags":[
        "bailiff"
    ],
    "wof:name":"Sauvage F",
    "wof:placetype":"venue"
},
  "geometry": {"coordinates":[5.5040712357,50.6173782349],"type":"Point"}
}