{
  "type": "Feature",
  "properties": {
    "addr:full":"Latemdreef 50 Zwalm Oost-Vlaanderen 9630",
    "addr:housenumber":"50",
    "addr:postcode":"9630",
    "addr:street":"Latemdreef;Oost-Vlaanderen",
    "iso:country":"BE",
    "sg:address":"Latemdreef 50",
    "sg:city":"Zwalm",
    "sg:orig_category":"Studios photographiques",
    "sg:phone":"+32 55 49 96 16",
    "sg:postcode":"9630",
    "sg:province":"Oost-Vlaanderen",
    "wof:name":"Marc Blaton",
    "wof:placetype":"venue"
},
  "geometry": {"coordinates":[3.7047920227,50.8889656067],"type":"Point"}
}