{
  "type": "Feature",
  "properties": {
    "addr:full":"Montenau 52 Amel Li\u00e8ge 4770",
    "addr:housenumber":"52",
    "addr:postcode":"4770",
    "addr:street":"Montenau",
    "iso:country":"BE",
    "sg:address":"Montenau 52",
    "sg:city":"Amel",
    "sg:orig_category":"Voedingsspeciaalzaken",
    "sg:phone":"+32 80 34 06 39",
    "sg:postcode":"4770",
    "sg:province":"Li\u00e8ge",
    "wof:name":"Marc Pfeiffer",
    "wof:placetype":"venue"
},
  "geometry": {"coordinates":[6.1093120575,50.3788757324],"type":"Point"}
}