{
  "type": "Feature",
  "properties": {
    "addr:full":"Sint-tillostraat 7 Box 1 Izegem West-Vlaanderen 8870",
    "addr:housenumber":"7;1",
    "addr:postcode":"8870",
    "addr:street":"Sint-Tillostraat;Box",
    "iso:country":"BE",
    "sg:address":"Sint-tillostraat 7 Box 1",
    "sg:city":"Izegem",
    "sg:classifiers":[
        {
            "category":"Health Services",
            "subcategory":"Dentist",
            "type":"Services"
        }
    ],
    "sg:phone":"+32 51 30 69 44",
    "sg:postcode":"8870",
    "sg:province":"West-Vlaanderen",
    "wof:name":"Vanderstraeten Carla",
    "wof:placetype":"venue"
},
  "geometry": {"coordinates":[3.2130858898,50.9169235229],"type":"Point"}
}