{
  "type": "Feature",
  "properties": {
    "iso:country":"BE",
    "sg:address":"Route Des Chantoirs 17a",
    "sg:city":"Aywaille (sougn\u00e9-remouchamps)",
    "sg:classifiers":[
        {
            "category":"Home & Garden",
            "subcategory":"Building Materials",
            "type":"Retail Goods"
        }
    ],
    "sg:phone":"+32 4 360 89 30",
    "sg:postcode":"4920",
    "sg:province":"Li\u00e8ge",
    "sg:tags":[
        "granite",
        "stone",
        "natural",
        "marble"
    ],
    "wof:name":"Rox Belgium Sprl",
    "wof:placetype":"venue"
},
  "geometry": {"coordinates":[5.7175679207,50.4995155334],"type":"Point"}
}