{
  "type": "Feature",
  "properties": {
    "iso:country":"BE",
    "sg:address":"Molenstraat 80b2",
    "sg:city":"Merelbeke",
    "sg:orig_category":"Bloemen and planten Gh",
    "sg:phone":"+32 9 362 66 78",
    "sg:postcode":"9820",
    "sg:province":"Oost-Vlaanderen",
    "wof:name":"Vandersteene-favere",
    "wof:placetype":"venue"
},
  "geometry": {"coordinates":[3.7268979549,50.9694252014],"type":"Point"}
}