{
  "type": "Feature",
  "properties": {
    "iso:country":"BE",
    "sg:address":"Kleine Kerkstraat 50-52",
    "sg:city":"Gent (ledeberg)",
    "sg:classifiers":[
        {
            "category":"Shopping",
            "subcategory":"Antiques",
            "type":"Retail Goods"
        }
    ],
    "sg:phone":"+32 9 231 79 16",
    "sg:postcode":"9050",
    "sg:province":"Oost-Vlaanderen",
    "wof:name":"Vervondel H",
    "wof:placetype":"venue"
},
  "geometry": {"coordinates":[3.7565009594,51.0453224182],"type":"Point"}
}