{
  "type": "Feature",
  "properties": {
    "addr:full":"Zoning Industriel Verviers (stembert) Li\u00e8ge 4801",
    "addr:postcode":"4801",
    "addr:street":"Zoning Industriel",
    "iso:country":"BE",
    "sg:address":"Zoning Industriel",
    "sg:city":"Verviers (stembert)",
    "sg:classifiers":[
        {
            "category":"Communications",
            "subcategory":"Radio Station",
            "type":"Services"
        }
    ],
    "sg:phone":"+32 87 31 22 77",
    "sg:postcode":"4801",
    "sg:province":"Li\u00e8ge",
    "sg:tags":[
        "transmission"
    ],
    "wof:name":"Ateliers P Sauvage Sa",
    "wof:placetype":"venue"
},
  "geometry": {"coordinates":[5.8930549622,50.5922393799],"type":"Point"}
}