{
  "type": "Feature",
  "properties": {
    "addr:full":"Rue Ti\u00c8ge De Perwez 48 Orp-jauche Brabant Wallon 1350",
    "addr:housenumber":"48",
    "addr:postcode":"1350",
    "addr:street":"Rue Tie\u0300Ge De Perwez",
    "iso:country":"BE",
    "sg:address":"Rue Ti\u00c8ge De Perwez 48",
    "sg:city":"Orp-jauche",
    "sg:orig_category":"R\u00e9parations d'appareils \u00e9lectrom\u00e9nagers. Electrom\u00e9nager, t\u00e9l\u00e9visions and radios",
    "sg:phone":"+32 19 63 39 27",
    "sg:postcode":"1350",
    "sg:province":"Brabant Wallon",
    "wof:name":"Gilbert Van Den Dooren",
    "wof:placetype":"venue"
},
  "geometry": {"coordinates":[4.97920084,50.6738891602],"type":"Point"}
}