{
  "type": "Feature",
  "properties": {
    "iso:country":"BE",
    "sg:address":"Pieter Hauwaertssquare 29b5",
    "sg:city":"Evere",
    "sg:orig_category":"Sportclubs Sportterreinen and installaties behalve sportcentra",
    "sg:phone":"+32 2 215 81 61",
    "sg:postcode":"1140",
    "sg:province":"Bruxelles-Capitale",
    "wof:name":"R.f.c. Kituro Ovalie",
    "wof:placetype":"venue"
},
  "geometry": {"coordinates":[4.4019317627,50.875038147],"type":"Point"}
}