{
  "type": "Feature",
  "properties": {
    "addr:full":"Paleizenstr.over Bruggen 398 Brussel/bruxelles Bruxelles-Capitale 1020",
    "addr:housenumber":"398",
    "addr:postcode":"1020",
    "addr:street":"Bruggen;/",
    "iso:country":"BE",
    "sg:address":"Paleizenstr.over Bruggen 398",
    "sg:city":"Brussel/bruxelles",
    "sg:orig_category":"Loodgieterij and centrale verwarming Gh Loodgieterij, verwarming and sanitaire installaties",
    "sg:phone":"+32 2 426 45 44",
    "sg:postcode":"1020",
    "sg:province":"Bruxelles-Capitale",
    "wof:name":"Dupont W. & P.",
    "wof:placetype":"venue"
},
  "geometry": {"coordinates":[4.3599729538,50.8747138977],"type":"Point"}
}