{
  "type": "Feature",
  "properties": {
    "addr:full":"Stationsstraat 129 Geel Antwerpen 2440",
    "addr:housenumber":"129",
    "addr:postcode":"2440",
    "addr:street":"Stationsstraat",
    "iso:country":"BE",
    "sg:address":"Stationsstraat 129",
    "sg:city":"Geel",
    "sg:classifiers":[
        {
            "category":"Home & Garden",
            "subcategory":"Home Furnishings",
            "type":"Retail Goods"
        }
    ],
    "sg:phone":"+32 14 58 83 26",
    "sg:postcode":"2440",
    "sg:province":"Antwerpen",
    "sg:tags":[
        "-",
        "furniture"
    ],
    "wof:name":"Bartsen Nv",
    "wof:placetype":"venue"
},
  "geometry": {"coordinates":[4.989068985,51.1669578552],"type":"Point"}
}