{
  "type": "Feature",
  "properties": {
    "addr:full":"Bankstraat Wevelgem (gullegem) West-Vlaanderen 8560",
    "addr:postcode":"8560",
    "addr:street":"Bankstraat",
    "iso:country":"BE",
    "sg:address":"Bankstraat",
    "sg:city":"Wevelgem (gullegem)",
    "sg:classifiers":[
        {
            "category":"Fast Food",
            "type":"Food & Drink"
        }
    ],
    "sg:phone":"+32 475 58 41 68",
    "sg:postcode":"8560",
    "sg:province":"West-Vlaanderen",
    "sg:tags":[
        "fried",
        "stand",
        "potato"
    ],
    "wof:name":"Bankske ('t)",
    "wof:placetype":"venue"
},
  "geometry": {"coordinates":[3.1995849609,50.8447608948],"type":"Point"}
}