{
  "type": "Feature",
  "properties": {
    "addr:full":"Rue Rasson 91 Bruxelles (schaerbeek) Bruxelles-Capitale 1030",
    "addr:housenumber":"91",
    "addr:postcode":"1030",
    "addr:street":"Rue Rasson",
    "iso:country":"BE",
    "sg:address":"Rue Rasson 91",
    "sg:city":"Bruxelles (schaerbeek)",
    "sg:classifiers":[
        {
            "category":"Health Services",
            "subcategory":"Health Practitioner",
            "type":"Services"
        }
    ],
    "sg:phone":"+32 2 734 62 19",
    "sg:postcode":"1030",
    "sg:province":"Bruxelles-Capitale",
    "sg:tags":[
        "physiotherapist"
    ],
    "wof:name":"Dugot Nadine",
    "wof:placetype":"venue"
},
  "geometry": {"coordinates":[4.3942670822,50.8484382629],"type":"Point"}
}