{
  "type": "Feature",
  "properties": {
    "addr:full":"Otterstraat 127 Turnhout Antwerpen 2300",
    "addr:housenumber":"127",
    "addr:postcode":"2300",
    "addr:street":"Otterstraat",
    "iso:country":"BE",
    "sg:address":"Otterstraat 127",
    "sg:city":"Turnhout",
    "sg:classifiers":[
        {
            "category":"Health Services",
            "subcategory":"Doctor",
            "type":"Services"
        }
    ],
    "sg:phone":"+32 14 41 22 67",
    "sg:postcode":"2300",
    "sg:province":"Antwerpen",
    "sg:tags":[
        "medicinephysicians",
        "surgeon"
    ],
    "wof:name":"Cornil P",
    "wof:placetype":"venue"
},
  "geometry": {"coordinates":[4.9558601379,51.3216018677],"type":"Point"}
}