{
  "type": "Feature",
  "properties": {
    "iso:country":"BE",
    "sg:address":"Geraardsbergse Steenweg 56",
    "sg:city":"Oosterzele",
    "sg:classifiers":[
        {
            "category":"Retail",
            "subcategory":"Auto Repair",
            "type":"Services"
        }
    ],
    "sg:phone":"+32 495 89 50 36",
    "sg:postcode":"9860",
    "sg:province":"Oost-Vlaanderen",
    "sg:tags":[
        "automobile-body"
    ],
    "wof:name":"Houbracken A",
    "wof:placetype":"venue"
},
  "geometry": {"coordinates":[3.8098978996,50.9566307068],"type":"Point"}
}