{
  "type": "Feature",
  "properties": {
    "iso:country":"BE",
    "sg:address":"All\u00e9e Des Grands Ducs 8",
    "sg:city":"Philippeville (neuville)",
    "sg:classifiers":[
        {
            "category":"Retail",
            "subcategory":"Repair Shop",
            "type":"Services"
        }
    ],
    "sg:phone":"+32 60 31 31 05",
    "sg:postcode":"5600",
    "sg:province":"Namur",
    "sg:tags":[
        "machine",
        "sewing",
        "-"
    ],
    "wof:name":"Abc D\u00e9pannages",
    "wof:placetype":"venue"
},
  "geometry": {"coordinates":[4.4912781715,50.1346092224],"type":"Point"}
}