{
  "type": "Feature",
  "properties": {
    "iso:country":"BE",
    "sg:address":"Smedenlaan 8",
    "sg:city":"Hasselt",
    "sg:classifiers":[
        {
            "category":"Education",
            "subcategory":"Special Training",
            "type":"Public Place"
        }
    ],
    "sg:phone":"+32 11 27 23 70",
    "sg:postcode":"3500",
    "sg:province":"Limburg",
    "sg:tags":[
        "professional"
    ],
    "wof:name":"Meers H",
    "wof:placetype":"venue"
},
  "geometry": {"coordinates":[5.3233361244,50.9213829041],"type":"Point"}
}