{
  "type": "Feature",
  "properties": {
    "addr:full":"Sint-lambertusstraat 87 Landen Vlaams-Brabant 3400",
    "addr:housenumber":"87",
    "addr:postcode":"3400",
    "addr:street":"Sint-Lambertusstraat",
    "iso:country":"BE",
    "sg:address":"Sint-lambertusstraat 87",
    "sg:city":"Landen",
    "sg:classifiers":[
        {
            "category":"Utilities",
            "subcategory":"Telephone",
            "type":"Services"
        }
    ],
    "sg:phone":"+32 70 22 43 05",
    "sg:postcode":"3400",
    "sg:province":"Vlaams-Brabant",
    "sg:tags":[
        "-",
        "internet"
    ],
    "wof:name":"Dommel.com",
    "wof:placetype":"venue"
},
  "geometry": {"coordinates":[5.0770530701,50.7427139282],"type":"Point"}
}