{
  "type": "Feature",
  "properties": {
    "addr:full":"Rue De La Vierge Noire 32 Bruxelles Bruxelles-Capitale 1000",
    "addr:housenumber":"32",
    "addr:postcode":"1000",
    "addr:street":"Rue De La Vierge Noire",
    "iso:country":"BE",
    "sg:address":"Rue De La Vierge Noire 32",
    "sg:city":"Bruxelles",
    "sg:classifiers":[
        {
            "category":"Travel",
            "subcategory":"Hotels & Motels",
            "type":"Entertainment"
        }
    ],
    "sg:phone":"+32 2 505 50 50",
    "sg:postcode":"1000",
    "sg:province":"Bruxelles-Capitale",
    "wof:name":"Novotel Brussels Centre Tour Noire",
    "wof:placetype":"venue"
},
  "geometry": {"coordinates":[4.3497362137,50.8502845764],"type":"Point"}
}