{
  "type": "Feature",
  "properties": {
    "addr:full":"Chemin De Ville Du Bois 10b Vielsalm (petit-thier) Luxembourg 6692",
    "addr:housenumber":"10b",
    "addr:postcode":"6692",
    "addr:street":"Chemin De Ville Du Bois",
    "iso:country":"BE",
    "sg:address":"Chemin De Ville Du Bois 10b",
    "sg:city":"Vielsalm (petit-thier)",
    "sg:classifiers":[
        {
            "category":"Building & Trades",
            "subcategory":"Cleaning & Sanitation",
            "type":"Services"
        }
    ],
    "sg:phone":"+32 80 21 55 23",
    "sg:postcode":"6692",
    "sg:province":"Luxembourg",
    "sg:tags":[
        "sweep",
        "chimney"
    ],
    "wof:name":"Christophe J",
    "wof:placetype":"venue"
},
  "geometry": {"coordinates":[5.9619030952,50.305141449],"type":"Point"}
}