{
  "type": "Feature",
  "properties": {
    "addr:full":"Picardiestraat 43 Evere/evere Bruxelles-Capitale 1140",
    "addr:housenumber":"43",
    "addr:postcode":"1140",
    "addr:street":"Picardiestraat",
    "iso:country":"BE",
    "sg:address":"Picardiestraat 43",
    "sg:city":"Evere/evere",
    "sg:orig_category":"Technische and wetenschappelijke instrumenten Fab Telecommunicatiesystemen",
    "sg:phone":"+32 2 245 22 39",
    "sg:postcode":"1140",
    "sg:province":"Bruxelles-Capitale",
    "wof:name":"Nation. Control Syst.",
    "wof:placetype":"venue"
},
  "geometry": {"coordinates":[4.397277832,50.8781967163],"type":"Point"}
}