{
  "type": "Feature",
  "properties": {
    "iso:country":"BE",
    "sg:address":"L. Theodorstraat 122",
    "sg:city":"Jette",
    "sg:orig_category":"Blanchisserie, Nettoyage \u00e0 Sec and Salons-Lavoirs. Blanchisseries and teintureries",
    "sg:phone":"+32 52 37 26 82",
    "sg:postcode":"1090",
    "sg:province":"Bruxelles-Capitale",
    "wof:name":"Omnidaim",
    "wof:placetype":"venue"
},
  "geometry": {"coordinates":[4.3277220726,50.8764686584],"type":"Point"}
}