{
  "type": "Feature",
  "properties": {
    "addr:full":"Rue De La Fontaine 1 Fl\u00e9malle Li\u00e8ge 4400",
    "addr:housenumber":"1",
    "addr:postcode":"4400",
    "addr:street":"Rue De La Fontaine",
    "iso:country":"BE",
    "sg:address":"Rue De La Fontaine 1",
    "sg:city":"Fl\u00e9malle",
    "sg:classifiers":[
        {
            "category":"Bars & Pubs",
            "type":"Food & Drink"
        }
    ],
    "sg:phone":"+32 4 231 18 77",
    "sg:postcode":"4400",
    "sg:province":"Li\u00e8ge",
    "wof:name":"Horecages Scrl",
    "wof:placetype":"venue"
},
  "geometry": {"coordinates":[5.4785861969,50.6069564819],"type":"Point"}
}