{
  "type": "Feature",
  "properties": {
    "addr:full":"Grand-route 116 Verlaine Li\u00e8ge 4537",
    "addr:housenumber":"116",
    "addr:postcode":"4537",
    "addr:street":"Grand-Route",
    "iso:country":"BE",
    "sg:address":"Grand-route 116",
    "sg:city":"Verlaine",
    "sg:orig_category":"Bois Gr. Charpentes and couvertures",
    "sg:phone":"+32 4 259 67 06",
    "sg:postcode":"4537",
    "sg:province":"Li\u00e8ge",
    "wof:name":"Monfort-binet",
    "wof:placetype":"venue"
},
  "geometry": {"coordinates":[5.3151669502,50.6106147766],"type":"Point"}
}