{
  "type": "Feature",
  "properties": {
    "addr:full":"Oude Waalstraat 251 Zulte Oost-Vlaanderen 9870",
    "addr:housenumber":"251",
    "addr:postcode":"9870",
    "addr:street":"Oude Waalstraat",
    "iso:country":"BE",
    "sg:address":"Oude Waalstraat 251",
    "sg:city":"Zulte",
    "sg:classifiers":[
        {
            "category":"Shopping",
            "subcategory":"Crafts & Fabrics",
            "type":"Retail Goods"
        }
    ],
    "sg:phone":"+32 9 388 91 40",
    "sg:postcode":"9870",
    "sg:province":"Oost-Vlaanderen",
    "sg:tags":[
        "textile",
        "recycling"
    ],
    "wof:name":"Eurofrip Nv",
    "wof:placetype":"venue"
},
  "geometry": {"coordinates":[3.4667429924,50.9078178406],"type":"Point"}
}