{
  "type": "Feature",
  "properties": {
    "addr:full":"Rue De La Citadelle 135 Tournai Hainaut 7500",
    "addr:housenumber":"135",
    "addr:postcode":"7500",
    "addr:street":"Rue De La Citadelle",
    "iso:country":"BE",
    "sg:address":"Rue De La Citadelle 135",
    "sg:city":"Tournai",
    "sg:classifiers":[
        {
            "category":"Organizations",
            "subcategory":"Professional Association",
            "type":"Services"
        }
    ],
    "sg:phone":"+32 69 84 04 54",
    "sg:postcode":"7500",
    "sg:province":"Hainaut",
    "sg:tags":[
        "trade-union",
        "federation"
    ],
    "wof:name":"Citadelle Toxicomanie Asbl",
    "wof:placetype":"venue"
},
  "geometry": {"coordinates":[3.3887500763,50.5992088318],"type":"Point"}
}