{
  "type": "Feature",
  "properties": {
    "addr:full":"Sacramentsstraat 9 Sint-niklaas Oost-Vlaanderen 9100",
    "addr:housenumber":"9",
    "addr:postcode":"9100",
    "addr:street":"Sacramentsstraat",
    "iso:country":"BE",
    "sg:address":"Sacramentsstraat 9",
    "sg:city":"Sint-niklaas",
    "sg:classifiers":[
        {
            "category":"Bars & Pubs",
            "type":"Food & Drink"
        }
    ],
    "sg:phone":"+32 477 88 17 25",
    "sg:postcode":"9100",
    "sg:province":"Oost-Vlaanderen",
    "wof:name":"Club (the)",
    "wof:placetype":"venue"
},
  "geometry": {"coordinates":[4.1428208351,51.1642341614],"type":"Point"}
}