{
  "type": "Feature",
  "properties": {
    "addr:full":"Parklaan 36 Aalst Oost-Vlaanderen 9300",
    "addr:housenumber":"36",
    "addr:postcode":"9300",
    "addr:street":"Parklaan",
    "iso:country":"BE",
    "sg:address":"Parklaan 36",
    "sg:city":"Aalst",
    "sg:classifiers":[
        {
            "category":"Health Services",
            "subcategory":"Health Practitioner",
            "type":"Services"
        }
    ],
    "sg:phone":"+32 53 70 45 70",
    "sg:postcode":"9300",
    "sg:province":"Oost-Vlaanderen",
    "sg:tags":[
        "physiotherapist"
    ],
    "wof:name":"De Veylder Paul",
    "wof:placetype":"venue"
},
  "geometry": {"coordinates":[4.0376739502,50.9284629822],"type":"Point"}
}