{
  "type": "Feature",
  "properties": {
    "addr:full":"Rue Deburges 1 La Louvi\u00e8re (houdeng-goegnies) Hainaut 7110",
    "addr:housenumber":"1",
    "addr:postcode":"7110",
    "addr:street":"Rue Deburges",
    "iso:country":"BE",
    "sg:address":"Rue Deburges 1",
    "sg:city":"La Louvi\u00e8re (houdeng-goegnies)",
    "sg:classifiers":[
        {
            "category":"Health Services",
            "subcategory":"Health Practitioner",
            "type":"Services"
        }
    ],
    "sg:phone":"+32 64 22 41 43",
    "sg:postcode":"7110",
    "sg:province":"Hainaut",
    "sg:tags":[
        "psychologist"
    ],
    "wof:name":"Bauduin/a",
    "wof:placetype":"venue"
},
  "geometry": {"coordinates":[4.1505050659,50.4826698303],"type":"Point"}
}