{
  "type": "Feature",
  "properties": {
    "addr:full":"Oude Vismijn 1 Lokeren Oost-Vlaanderen 9160",
    "addr:housenumber":"1",
    "addr:postcode":"9160",
    "addr:street":"Oude Vismijn",
    "iso:country":"BE",
    "sg:address":"Oude Vismijn 1",
    "sg:city":"Lokeren",
    "sg:orig_category":"Caf\u00e9s. V\u00e9t\u00e9rinaires",
    "sg:phone":"+32 9 349 44 24",
    "sg:postcode":"9160",
    "sg:province":"Oost-Vlaanderen",
    "wof:name":"Caf\u00c9 Shooters",
    "wof:placetype":"venue"
},
  "geometry": {"coordinates":[3.9875299931,51.1040306091],"type":"Point"}
}