{
  "type": "Feature",
  "properties": {
    "addr:full":"Steenbakkersweg 52 Overijse Vlaams-Brabant 3090",
    "addr:housenumber":"52",
    "addr:postcode":"3090",
    "addr:street":"Steenbakkersweg",
    "iso:country":"BE",
    "sg:address":"Steenbakkersweg 52",
    "sg:city":"Overijse",
    "sg:orig_category":"Producteurs de fruits",
    "sg:phone":"+32 2 657 91 45",
    "sg:postcode":"3090",
    "sg:province":"Vlaams-Brabant",
    "wof:name":"Roger Boogaerts",
    "wof:placetype":"venue"
},
  "geometry": {"coordinates":[4.5061130524,50.7585945129],"type":"Point"}
}