{
  "type": "Feature",
  "properties": {
    "iso:country":"BE",
    "sg:address":"Nieuwdorp 37",
    "sg:city":"Stekene",
    "sg:orig_category":"Woningbouw",
    "sg:phone":"+32 3 779 94 61",
    "sg:postcode":"9190",
    "sg:province":"Oost-Vlaanderen",
    "wof:name":"Vercammen Dirk",
    "wof:placetype":"venue"
},
  "geometry": {"coordinates":[3.9997839928,51.223072052],"type":"Point"}
}