{
  "type": "Feature",
  "properties": {
    "addr:full":"Rue Du Long Ch\u00eane 83 Wezembeek-oppem Vlaams-Brabant 1970",
    "addr:housenumber":"83",
    "addr:postcode":"1970",
    "addr:street":"Rue Du Long Che\u0302Ne",
    "iso:country":"BE",
    "sg:address":"Rue Du Long Ch\u00eane 83",
    "sg:city":"Wezembeek-oppem",
    "sg:classifiers":[
        {
            "category":"Health Services",
            "subcategory":"Doctor",
            "type":"Services"
        }
    ],
    "sg:phone":"+32 2 731 96 92",
    "sg:postcode":"1970",
    "sg:province":"Vlaams-Brabant",
    "sg:tags":[
        "medicinephysicians",
        "surgeon"
    ],
    "wof:name":"Kotulla B",
    "wof:placetype":"venue"
},
  "geometry": {"coordinates":[4.4908900261,50.8522109985],"type":"Point"}
}