{
  "type": "Feature",
  "properties": {
    "addr:full":"Lavaux 1 Esneux Li\u00e8ge 4130",
    "addr:housenumber":"1",
    "addr:postcode":"4130",
    "addr:street":"Lavaux",
    "iso:country":"BE",
    "sg:address":"Lavaux 1",
    "sg:city":"Esneux",
    "sg:orig_category":"Artsen and specialisten",
    "sg:phone":"+32 4 349 49 99",
    "sg:postcode":"4130",
    "sg:province":"Li\u00e8ge",
    "wof:name":"Dominique Libert",
    "wof:placetype":"venue"
},
  "geometry": {"coordinates":[5.5647110939,50.5337982178],"type":"Point"}
}