{
  "type": "Feature",
  "properties": {
    "iso:country":"BE",
    "sg:address":"Stuivenbergstraat 47",
    "sg:city":"Evergem",
    "sg:orig_category":"Ordinateurs and \u00e9quipement informatique",
    "sg:phone":"+32 9 344 83 93",
    "sg:postcode":"9940",
    "sg:province":"Oost-Vlaanderen",
    "wof:name":"Comserve",
    "wof:placetype":"venue"
},
  "geometry": {"coordinates":[3.7296059132,51.1785850525],"type":"Point"}
}