{
  "type": "Feature",
  "properties": {
    "addr:full":"Au Ch\u00eane 148 Pepinster (soiron) Li\u00e8ge 4861",
    "addr:housenumber":"148",
    "addr:postcode":"4861",
    "addr:street":"Pepinster Soiron",
    "iso:country":"BE",
    "sg:address":"Au Ch\u00eane 148",
    "sg:city":"Pepinster (soiron)",
    "sg:classifiers":[
        {
            "category":"Retail",
            "subcategory":"Auto Repair",
            "type":"Services"
        }
    ],
    "sg:phone":"+32 87 46 02 96",
    "sg:postcode":"4861",
    "sg:province":"Li\u00e8ge",
    "sg:tags":[
        "automobile-body"
    ],
    "wof:name":"Remont L",
    "wof:placetype":"venue"
},
  "geometry": {"coordinates":[5.7885251045,50.58826828],"type":"Point"}
}