{
  "type": "Feature",
  "properties": {
    "addr:full":"Rue Marcel Thiry 8 Braine L'alleud (braine-l'alleud) Brabant Wallon 1420",
    "addr:housenumber":"8",
    "addr:postcode":"1420",
    "addr:street":"Rue Marcel Thiry",
    "iso:country":"BE",
    "sg:address":"Rue Marcel Thiry 8",
    "sg:city":"Braine L'alleud (braine-l'alleud)",
    "sg:classifiers":[
        {
            "category":"Shopping",
            "subcategory":"Optician",
            "type":"Retail Goods"
        }
    ],
    "sg:phone":"+32 2 384 99 32",
    "sg:postcode":"1420",
    "sg:province":"Brabant Wallon",
    "sg:tags":[
        "-"
    ],
    "wof:name":"Cation Sprl",
    "wof:placetype":"venue"
},
  "geometry": {"coordinates":[-75.60595703120001,37.7877616882],"type":"Point"}
}