{
  "type": "Feature",
  "properties": {
    "addr:full":"Nieuwstraat 21 De Haan West-Vlaanderen 8420",
    "addr:housenumber":"21",
    "addr:postcode":"8420",
    "addr:street":"Nieuwstraat",
    "iso:country":"BE",
    "sg:address":"Nieuwstraat 21",
    "sg:city":"De Haan",
    "sg:orig_category":"Quincailleries",
    "sg:phone":"+32 59 23 36 10",
    "sg:postcode":"8420",
    "sg:province":"West-Vlaanderen",
    "wof:name":"L'angelus",
    "wof:placetype":"venue"
},
  "geometry": {"coordinates":[3.0359430313,51.2720146179],"type":"Point"}
}