{
  "type": "Feature",
  "properties": {
    "addr:full":"Cit\u00c9 Bougard 90 Morlanwelz Hainaut 7141",
    "addr:housenumber":"90",
    "addr:postcode":"7141",
    "addr:street":"Cite\u0301 Bougard",
    "iso:country":"BE",
    "sg:address":"Cit\u00c9 Bougard 90",
    "sg:city":"Morlanwelz",
    "sg:classifiers":[
        {
            "category":"Personal",
            "subcategory":"Beauty Salon",
            "type":"Services"
        }
    ],
    "sg:phone":"+32 64 44 40 64",
    "sg:postcode":"7141",
    "sg:province":"Hainaut",
    "sg:tags":[
        "de",
        "coiffure"
    ],
    "wof:name":"Coiffure Josephine",
    "wof:placetype":"venue"
},
  "geometry": {"coordinates":[4.2536110878,50.4371261597],"type":"Point"}
}