{
  "type": "Feature",
  "properties": {
    "addr:full":"Droogte 37 Evergem Oost-Vlaanderen 9940",
    "addr:housenumber":"37",
    "addr:postcode":"9940",
    "addr:street":"Droogte;Oost-Vlaanderen",
    "iso:country":"BE",
    "sg:address":"Droogte 37",
    "sg:city":"Evergem",
    "sg:orig_category":"Biljart- and snookerzalen Caf\u00e9s Sportclubs",
    "sg:phone":"+32 9 253 64 32",
    "sg:postcode":"9940",
    "sg:province":"Oost-Vlaanderen",
    "wof:name":"Snookertaverne Fiesta",
    "wof:placetype":"venue"
},
  "geometry": {"coordinates":[3.7136309147,51.1164665222],"type":"Point"}
}