{
  "type": "Feature",
  "properties": {
    "iso:country":"BE",
    "sg:address":"Rue De L'egalit\u00c9 450",
    "sg:city":"Soumagne",
    "sg:classifiers":[
        {
            "category":"Personal",
            "subcategory":"Beauty Salon",
            "type":"Services"
        }
    ],
    "sg:phone":"+32 4 377 40 35",
    "sg:postcode":"4630",
    "sg:province":"Li\u00e8ge",
    "sg:tags":[
        "de",
        "coiffure"
    ],
    "wof:name":"Coiffure Nouv'elle Vague",
    "wof:placetype":"venue"
},
  "geometry": {"coordinates":[5.7472782135,50.6137237549],"type":"Point"}
}