{
  "type": "Feature",
  "properties": {
    "addr:full":"Avenue De La Salm 49 Vielsalm Luxembourg 6690",
    "addr:housenumber":"49",
    "addr:postcode":"6690",
    "addr:street":"Avenue De La Salm",
    "iso:country":"BE",
    "sg:address":"Avenue De La Salm 49",
    "sg:city":"Vielsalm",
    "sg:orig_category":"Slagers",
    "sg:phone":"+32 80 21 62 22",
    "sg:postcode":"6690",
    "sg:province":"Luxembourg",
    "wof:name":"J.p. Guillaume",
    "wof:placetype":"venue"
},
  "geometry": {"coordinates":[5.9115300179,50.2796516418],"type":"Point"}
}