{
  "type": "Feature",
  "properties": {
    "addr:full":"Lombardstraat 12 Tienen Vlaams-Brabant 3300",
    "addr:housenumber":"12",
    "addr:postcode":"3300",
    "addr:street":"Lombardstraat",
    "iso:country":"BE",
    "sg:address":"Lombardstraat 12",
    "sg:city":"Tienen",
    "sg:classifiers":[
        {
            "category":"Health Services",
            "subcategory":"Health Practitioner",
            "type":"Services"
        }
    ],
    "sg:phone":"+32 16 81 80 04",
    "sg:postcode":"3300",
    "sg:province":"Vlaams-Brabant",
    "sg:tags":[
        "physiotherapist"
    ],
    "wof:name":"Uyttebroek M",
    "wof:placetype":"venue"
},
  "geometry": {"coordinates":[4.9408240318,50.8041305542],"type":"Point"}
}