{
  "type": "Feature",
  "properties": {
    "addr:full":"Missestraat 50 Duffel Antwerpen 2570",
    "addr:housenumber":"50",
    "addr:postcode":"2570",
    "addr:street":"Missestraat",
    "iso:country":"BE",
    "sg:address":"Missestraat 50",
    "sg:city":"Duffel",
    "sg:orig_category":"Paramedische behandelingen",
    "sg:phone":"+32 15 31 20 79",
    "sg:postcode":"2570",
    "sg:province":"Antwerpen",
    "wof:name":"L. Jacobs",
    "wof:placetype":"venue"
},
  "geometry": {"coordinates":[4.5054497719,51.1133003235],"type":"Point"}
}