{
  "type": "Feature",
  "properties": {
    "iso:country":"BE",
    "sg:address":"Overleiestraat 69",
    "sg:city":"Kortrijk",
    "sg:orig_category":"Kruideniers Voedingsspeciaalzaken",
    "sg:phone":"+32 56 35 02 28",
    "sg:postcode":"8500",
    "sg:province":"West-Vlaanderen",
    "wof:name":"Thi",
    "wof:placetype":"venue"
},
  "geometry": {"coordinates":[3.2590789795,50.8332328796],"type":"Point"}
}