{
  "type": "Feature",
  "properties": {
    "iso:country":"BE",
    "sg:address":"Place Abb\u00e9 Renard 6",
    "sg:city":"Braine L'alleud (braine-l'alleud)",
    "sg:classifiers":[
        {
            "category":"Professional",
            "subcategory":"Lawyer & Legal Services",
            "type":"Services"
        }
    ],
    "sg:phone":"+32 2 389 18 68",
    "sg:postcode":"1420",
    "sg:province":"Brabant Wallon",
    "wof:name":"Deville M",
    "wof:placetype":"venue"
},
  "geometry": {"coordinates":[-0.7004899979,47.369140625],"type":"Point"}
}