{
  "type": "Feature",
  "properties": {
    "addr:full":"Manestraat 9 Oostende West-Vlaanderen 8400",
    "addr:housenumber":"9",
    "addr:postcode":"8400",
    "addr:street":"Manestraat",
    "iso:country":"BE",
    "sg:address":"Manestraat 9",
    "sg:city":"Oostende",
    "sg:orig_category":"Linge de maison Fab. Textiles",
    "sg:phone":"+32 59 80 22 12",
    "sg:postcode":"8400",
    "sg:province":"West-Vlaanderen",
    "wof:name":"Decorte - Makelberge",
    "wof:placetype":"venue"
},
  "geometry": {"coordinates":[2.9389901161,51.2162704468],"type":"Point"}
}