{
  "type": "Feature",
  "properties": {
    "addr:full":"Rue De La Fabrique 11 Lessines Hainaut 7860",
    "addr:housenumber":"11",
    "addr:postcode":"7860",
    "addr:street":"Rue De La Fabrique;Hainaut",
    "iso:country":"BE",
    "sg:address":"Rue De La Fabrique 11",
    "sg:city":"Lessines",
    "sg:orig_category":"Verre creux Fab",
    "sg:phone":"+32 68 33 20 60",
    "sg:postcode":"7860",
    "sg:province":"Hainaut",
    "wof:name":"Amphabel",
    "wof:placetype":"venue"
},
  "geometry": {"coordinates":[3.8328299522,50.7114181519],"type":"Point"}
}