{
  "type": "Feature",
  "properties": {
    "addr:full":"Avenue Louis Lepoutre 13 Bruxelles (ixelles) Bruxelles-Capitale 1050",
    "addr:housenumber":"13",
    "addr:postcode":"1050",
    "addr:street":"Avenue Louis Lepoutre",
    "iso:country":"BE",
    "sg:address":"Avenue Louis Lepoutre 13",
    "sg:city":"Bruxelles (ixelles)",
    "sg:classifiers":[
        {
            "category":"Real Estate",
            "subcategory":"Real Estate Services",
            "type":"Services"
        }
    ],
    "sg:phone":"+32 2 343 53 12",
    "sg:postcode":"1050",
    "sg:province":"Bruxelles-Capitale",
    "wof:name":"Communaut\u00e9s (immobili\u00e8re Des)",
    "wof:placetype":"venue"
},
  "geometry": {"coordinates":[4.3588352203,50.8199653625],"type":"Point"}
}