{
  "type": "Feature",
  "properties": {
    "addr:full":"Rue De Saint-ethon 78 Seneffe Hainaut 7181",
    "addr:housenumber":"78",
    "addr:postcode":"7181",
    "addr:street":"Rue De Saint-Ethon",
    "iso:country":"BE",
    "sg:address":"Rue De Saint-ethon 78",
    "sg:city":"Seneffe",
    "sg:orig_category":"Sportclubs",
    "sg:phone":"+32 67 87 74 76",
    "sg:postcode":"7181",
    "sg:province":"Hainaut",
    "wof:name":"Seneffe T.c.",
    "wof:placetype":"venue"
},
  "geometry": {"coordinates":[4.2554302216,50.5584106445],"type":"Point"}
}