{
  "type": "Feature",
  "properties": {
    "iso:country":"BE",
    "sg:address":"Avenue De L'epine Vinette 1",
    "sg:city":"Namur (wierde)",
    "sg:classifiers":[
        {
            "category":"Professional",
            "subcategory":"Accounting & Tax Preparation",
            "type":"Services"
        }
    ],
    "sg:phone":"+32 81 40 19 25",
    "sg:postcode":"5100",
    "sg:province":"Namur",
    "sg:tags":[
        "accountant"
    ],
    "wof:name":"Socofiges Sprl",
    "wof:placetype":"venue"
},
  "geometry": {"coordinates":[4.9298791885,50.4410400391],"type":"Point"}
}