{
  "type": "Feature",
  "properties": {
    "addr:full":"Rue De Maison-d\u00b4orbais 54 Gembloux Namur 5032",
    "addr:housenumber":"54",
    "addr:postcode":"5032",
    "addr:street":"Rue De Maison-D\u00b4Orbais;Namur",
    "iso:country":"BE",
    "sg:address":"Rue De Maison-d\u00b4orbais 54",
    "sg:city":"Gembloux",
    "sg:orig_category":"Salles de spectacles",
    "sg:phone":"+32 81 63 21 61",
    "sg:postcode":"5032",
    "sg:province":"Namur",
    "wof:name":"Trans\u00b4acte",
    "wof:placetype":"venue"
},
  "geometry": {"coordinates":[4.6621441841,50.5355110168],"type":"Point"}
}