{
  "type": "Feature",
  "properties": {
    "addr:full":"Jubelfeestlaan 119 Sint-jans-molenbeek/molenbeek-saint-jean Bruxelles-Capitale 1080",
    "addr:housenumber":"119;/",
    "addr:postcode":"1080",
    "addr:street":"Jubelfeestlaan;Sint-Jans-Molenbeek",
    "iso:country":"BE",
    "sg:address":"Jubelfeestlaan 119",
    "sg:city":"Sint-jans-molenbeek/molenbeek-saint-jean",
    "sg:orig_category":"Apotheken",
    "sg:phone":"+32 2 426 50 07",
    "sg:postcode":"1080",
    "sg:province":"Bruxelles-Capitale",
    "wof:name":"Tripharma",
    "wof:placetype":"venue"
},
  "geometry": {"coordinates":[4.3398537636,50.8661651611],"type":"Point"}
}