{
  "type": "Feature",
  "properties": {
    "iso:country":"BE",
    "sg:address":"Rue Du Dix Novembre 25",
    "sg:city":"Leuze-en-hainaut",
    "sg:orig_category":"Elektrische installaties voor woningen",
    "sg:phone":"+32 69 66 63 47",
    "sg:postcode":"7900",
    "sg:province":"Hainaut",
    "wof:name":"Thierry Boitte",
    "wof:placetype":"venue"
},
  "geometry": {"coordinates":[3.6270129681,50.5965003967],"type":"Point"}
}