{
  "type": "Feature",
  "properties": {
    "addr:full":"Zandvlietse Dorpstraat 178 Antwerpen Antwerpen 2040",
    "addr:housenumber":"178",
    "addr:postcode":"2040",
    "addr:street":"Zandvlietse Dorpstraat",
    "iso:country":"BE",
    "sg:address":"Zandvlietse Dorpstraat 178",
    "sg:city":"Antwerpen",
    "sg:orig_category":"Huwelijks- and Relatiebureaus",
    "sg:phone":"+32 475 69 08 25",
    "sg:postcode":"2040",
    "sg:province":"Antwerpen",
    "wof:name":"Van Hees",
    "wof:placetype":"venue"
},
  "geometry": {"coordinates":[4.3128800392,51.3499603271],"type":"Point"}
}