{
  "type": "Feature",
  "properties": {
    "iso:country":"BE",
    "sg:address":"Rue Frans Landrain 26",
    "sg:city":"Wezembeek-oppem",
    "sg:orig_category":"RESTAURANTS: CLUBS DE SPORT. SALLES DE CONF\u00c9RENCES AND DE R\u00c9CEPTIONS",
    "sg:phone":"+32 2 731 80 11",
    "sg:postcode":"1970",
    "sg:province":"Vlaams-Brabant",
    "wof:name":"Tennis Davis T.c.",
    "wof:placetype":"venue"
},
  "geometry": {"coordinates":[4.4763450623,50.8472061157],"type":"Point"}
}