{
  "type": "Feature",
  "properties": {
    "addr:full":"Rue Lucien Burnotte 2 Neufch\u00e2teau Luxembourg 6840",
    "addr:housenumber":"2",
    "addr:postcode":"6840",
    "addr:street":"Rue Lucien Burnotte",
    "iso:country":"BE",
    "sg:address":"Rue Lucien Burnotte 2",
    "sg:city":"Neufch\u00e2teau",
    "sg:classifiers":[
        {
            "category":"Shopping",
            "subcategory":"Clothing, Apparel, & Fashions",
            "type":"Retail Goods"
        }
    ],
    "sg:phone":"+32 61 29 28 87",
    "sg:postcode":"6840",
    "sg:province":"Luxembourg",
    "sg:tags":[
        "underwear",
        "lingerie",
        "-"
    ],
    "wof:name":"Autour D'elles",
    "wof:placetype":"venue"
},
  "geometry": {"coordinates":[5.4359030724,49.8407325745],"type":"Point"}
}