{
  "type": "Feature",
  "properties": {
    "iso:country":"BE",
    "sg:address":"Olekenbosstraat 31",
    "sg:city":"Anzegem (vichte)",
    "sg:classifiers":[
        {
            "category":"Military Area",
            "subcategory":"Air Force Base",
            "type":"Public Place"
        }
    ],
    "sg:phone":"+32 477 49 78 14",
    "sg:postcode":"8570",
    "sg:province":"West-Vlaanderen",
    "sg:tags":[
        "fire",
        "protection"
    ],
    "wof:name":"Maestro Technics",
    "wof:placetype":"venue"
},
  "geometry": {"coordinates":[3.384057045,50.8388671875],"type":"Point"}
}