{
  "type": "Feature",
  "properties": {
    "addr:full":"Eerdegemstraat 13 Aalst Oost-Vlaanderen 9310",
    "addr:housenumber":"13",
    "addr:postcode":"9310",
    "addr:street":"Eerdegemstraat",
    "iso:country":"BE",
    "sg:address":"Eerdegemstraat 13",
    "sg:city":"Aalst",
    "sg:orig_category":"Brood, gebak and snoepgoed",
    "sg:phone":"+32 52 35 85 43",
    "sg:postcode":"9310",
    "sg:province":"Oost-Vlaanderen",
    "wof:name":"Bakkerij Colson",
    "wof:placetype":"venue"
},
  "geometry": {"coordinates":[4.1295661926,50.9632720947],"type":"Point"}
}