{
  "type": "Feature",
  "properties": {
    "addr:full":"Mirfeld 99 Amel/ambleve Li\u00e8ge 4771",
    "addr:housenumber":"99",
    "addr:postcode":"4771",
    "addr:street":"Mirfeld",
    "iso:country":"BE",
    "sg:address":"Mirfeld 99",
    "sg:city":"Amel/ambleve",
    "sg:orig_category":"Meubelzaken, woning- and keukeninrichting",
    "sg:phone":"+32 80 34 93 74",
    "sg:postcode":"4771",
    "sg:province":"Li\u00e8ge",
    "wof:name":"Moebel Lentz",
    "wof:placetype":"venue"
},
  "geometry": {"coordinates":[6.2186770439,50.3613700867],"type":"Point"}
}