{
  "type": "Feature",
  "properties": {
    "addr:full":"Ring Shoppingcenter Kuurne West-Vlaanderen 8520",
    "addr:postcode":"8520",
    "addr:street":"Ring",
    "iso:country":"BE",
    "sg:address":"Ring Shoppingcenter",
    "sg:city":"Kuurne",
    "sg:orig_category":"V\u00eatements",
    "sg:phone":"+32 56 37 29 79",
    "sg:postcode":"8520",
    "sg:province":"West-Vlaanderen",
    "wof:name":"Huis Absolu",
    "wof:placetype":"venue"
},
  "geometry": {"coordinates":[3.2867200375,50.8503799438],"type":"Point"}
}