{
  "type": "Feature",
  "properties": {
    "addr:full":"Jonkershovestraat 71b Houthulst West-Vlaanderen 8650",
    "addr:housenumber":"71b",
    "addr:postcode":"8650",
    "addr:street":"Jonkershovestraat",
    "iso:country":"BE",
    "sg:address":"Jonkershovestraat 71b",
    "sg:city":"Houthulst",
    "sg:classifiers":[
        {
            "category":"Retail",
            "subcategory":"Auto Repair",
            "type":"Services"
        }
    ],
    "sg:phone":"+32 51 70 04 30",
    "sg:postcode":"8650",
    "sg:province":"West-Vlaanderen",
    "sg:tags":[
        "automobile",
        "-",
        "wrecking"
    ],
    "wof:name":"Staelens G",
    "wof:placetype":"venue"
},
  "geometry": {"coordinates":[2.9401450157,50.975112915],"type":"Point"}
}