{
  "type": "Feature",
  "properties": {
    "addr:full":"Kortrijksesteenweg 201 Sint-martens-latem Oost-Vlaanderen 9830",
    "addr:housenumber":"201",
    "addr:postcode":"9830",
    "addr:street":"Kortrijksesteenweg",
    "iso:country":"BE",
    "sg:address":"Kortrijksesteenweg 201",
    "sg:city":"Sint-martens-latem",
    "sg:classifiers":[
        {
            "category":"Bars & Pubs",
            "subcategory":"Nightclub",
            "type":"Food & Drink"
        }
    ],
    "sg:phone":"+32 9 282 70 40",
    "sg:postcode":"9830",
    "sg:province":"Oost-Vlaanderen",
    "wof:name":"Trigon",
    "wof:placetype":"venue"
},
  "geometry": {"coordinates":[3.6304860115,51.0075798035],"type":"Point"}
}