{
  "type": "Feature",
  "properties": {
    "addr:full":"Merellaan 6 Ravels (groot) Antwerpen 2382",
    "addr:housenumber":"6",
    "addr:postcode":"2382",
    "addr:street":"Merellaan;Groot Antwerpen",
    "iso:country":"BE",
    "sg:address":"Merellaan 6",
    "sg:city":"Ravels (groot)",
    "sg:orig_category":"Landmeters and schatters",
    "sg:phone":"+32 14 65 21 07",
    "sg:postcode":"2382",
    "sg:province":"Antwerpen",
    "wof:name":"Bouwservice Management",
    "wof:placetype":"venue"
},
  "geometry": {"coordinates":[5.041768074,51.4469108582],"type":"Point"}
}