{
  "type": "Feature",
  "properties": {
    "addr:full":"Chemin Du Champ De L'eglise 65 Rhode-saint-gen\u00e8se Vlaams-Brabant 1640",
    "addr:housenumber":"65",
    "addr:postcode":"1640",
    "addr:street":"Chemin Du Champ De L'Eglise",
    "iso:country":"BE",
    "sg:address":"Chemin Du Champ De L'eglise 65",
    "sg:city":"Rhode-saint-gen\u00e8se",
    "sg:classifiers":[
        {
            "category":"Professional",
            "subcategory":"Business Services",
            "type":"Services"
        }
    ],
    "sg:phone":"+32 2 380 37 09",
    "sg:postcode":"1640",
    "sg:province":"Vlaams-Brabant",
    "sg:tags":[
        "automobile",
        "-",
        "assessor"
    ],
    "wof:name":"Nagant De Deuxchaisnes J-c",
    "wof:placetype":"venue"
},
  "geometry": {"coordinates":[4.3291010857,50.7346229553],"type":"Point"}
}