{
  "type": "Feature",
  "properties": {
    "iso:country":"BE",
    "sg:address":"Rue De L'abbaye 28b",
    "sg:city":"Bruxelles (ixelles)",
    "sg:classifiers":[
        {
            "category":"Real Estate",
            "subcategory":"Architect",
            "type":"Services"
        }
    ],
    "sg:phone":"+32 2 649 89 89",
    "sg:postcode":"1050",
    "sg:province":"Bruxelles-Capitale",
    "wof:name":"Kirkpatrick Th",
    "wof:placetype":"venue"
},
  "geometry": {"coordinates":[4.3667941093,50.8187789917],"type":"Point"}
}