{
  "type": "Feature",
  "properties": {
    "addr:full":"Avenue Victor Gilsoul 82 Bruxelles (woluwe-saint-lambert) Bruxelles-Capitale 1200",
    "addr:housenumber":"82",
    "addr:postcode":"1200",
    "addr:street":"Avenue Victor Gilsoul",
    "iso:country":"BE",
    "sg:address":"Avenue Victor Gilsoul 82",
    "sg:city":"Bruxelles (woluwe-saint-lambert)",
    "sg:classifiers":[
        {
            "category":"Professional",
            "subcategory":"Management & Consulting",
            "type":"Services"
        }
    ],
    "sg:phone":"+32 2 772 13 36",
    "sg:postcode":"1200",
    "sg:province":"Bruxelles-Capitale",
    "sg:tags":[
        "consultant"
    ],
    "wof:name":"Remacle J P",
    "wof:placetype":"venue"
},
  "geometry": {"coordinates":[4.4162402153,50.8414802551],"type":"Point"}
}