{
  "type": "Feature",
  "properties": {
    "iso:country":"BE",
    "sg:address":"Donkerstraat 14",
    "sg:city":"Zulte",
    "sg:classifiers":[
        {
            "category":"Personal",
            "subcategory":"Beauty Salon",
            "type":"Services"
        }
    ],
    "sg:phone":"+32 9 387 00 11",
    "sg:postcode":"9870",
    "sg:province":"Oost-Vlaanderen",
    "sg:tags":[
        "de",
        "coiffure"
    ],
    "wof:name":"Coiffure Eveline",
    "wof:placetype":"venue"
},
  "geometry": {"coordinates":[3.492620945,50.9646224976],"type":"Point"}
}