{
  "type": "Feature",
  "properties": {
    "iso:country":"BE",
    "sg:address":"Zwartzustersvest 21",
    "sg:city":"Mechelen",
    "sg:classifiers":[
        {
            "category":"Social Services",
            "type":"Services"
        }
    ],
    "sg:phone":"+32 15 44 06 20",
    "sg:postcode":"2800",
    "sg:province":"Antwerpen",
    "wof:name":"Comit\u00e9 Voor Bijzondere Jeugdzorg Mechelen",
    "wof:placetype":"venue"
},
  "geometry": {"coordinates":[4.4851741791,51.0323295593],"type":"Point"}
}