{
  "type": "Feature",
  "properties": {
    "addr:full":"Molenstraat 32 Kluisbergen Oost-Vlaanderen 9690",
    "addr:housenumber":"32",
    "addr:postcode":"9690",
    "addr:street":"Molenstraat",
    "iso:country":"BE",
    "sg:address":"Molenstraat 32",
    "sg:city":"Kluisbergen",
    "sg:orig_category":"Avocats and conseillers juridiques",
    "sg:phone":"+32 55 38 82 57",
    "sg:postcode":"9690",
    "sg:province":"Oost-Vlaanderen",
    "wof:name":"V. Vandewalle",
    "wof:placetype":"venue"
},
  "geometry": {"coordinates":[3.5077090263,50.789604187],"type":"Point"}
}