{
  "type": "Feature",
  "properties": {
    "addr:full":"Petrus Bogaertslaan 45 Schilde Antwerpen 2970",
    "addr:housenumber":"45",
    "addr:postcode":"2970",
    "addr:street":"Petrus Bogaertslaan",
    "iso:country":"BE",
    "sg:address":"Petrus Bogaertslaan 45",
    "sg:city":"Schilde",
    "sg:orig_category":"Ice-cream parlours",
    "sg:phone":"+32 3 383 06 87",
    "sg:postcode":"2970",
    "sg:province":"Antwerpen",
    "wof:name":"Margriet",
    "wof:placetype":"venue"
},
  "geometry": {"coordinates":[4.5780010223,51.2351226807],"type":"Point"}
}