{
  "type": "Feature",
  "properties": {
    "iso:country":"BE",
    "sg:address":"Van Schoonbekeplein 3",
    "sg:city":"Antwerpen",
    "sg:classifiers":[
        {
            "category":"Bars & Pubs",
            "type":"Food & Drink"
        }
    ],
    "sg:phone":"+32 3 233 10 53",
    "sg:postcode":"2000",
    "sg:province":"Antwerpen",
    "wof:name":"Happy Castor (the)",
    "wof:placetype":"venue"
},
  "geometry": {"coordinates":[4.4055261612,51.2276725769],"type":"Point"}
}