{
  "type": "Feature",
  "properties": {
    "iso:country":"BE",
    "sg:address":"Nestor De Ti\u00c8restraat 135",
    "sg:city":"Oudenaarde",
    "sg:orig_category":"V\u00eatements pour Dames. V\u00eatements pour Hommes",
    "sg:phone":"+32 55 31 75 35",
    "sg:postcode":"9700",
    "sg:province":"Oost-Vlaanderen",
    "wof:name":"Klein Londen Fashion",
    "wof:placetype":"venue"
},
  "geometry": {"coordinates":[3.6187529564,50.8671798706],"type":"Point"}
}