{
  "type": "Feature",
  "properties": {
    "addr:full":"Grote Heibergstraat 31 Hulshout Antwerpen 2235",
    "addr:housenumber":"31",
    "addr:postcode":"2235",
    "addr:street":"Grote Heibergstraat",
    "iso:country":"BE",
    "sg:address":"Grote Heibergstraat 31",
    "sg:city":"Hulshout",
    "sg:classifiers":[
        {
            "category":"Retail",
            "subcategory":"Animal Services",
            "type":"Services"
        }
    ],
    "sg:phone":"+32 15 22 09 63",
    "sg:postcode":"2235",
    "sg:province":"Antwerpen",
    "sg:tags":[
        "grooming",
        "-",
        "dog"
    ],
    "wof:name":"Dierenvriend (de)",
    "wof:placetype":"venue"
},
  "geometry": {"coordinates":[4.807448864,51.0682678223],"type":"Point"}
}