{
  "type": "Feature",
  "properties": {
    "iso:country":"BE",
    "sg:address":"Alsembergse Steenweg 147",
    "sg:city":"Vorst/forest",
    "sg:orig_category":"Apotheken",
    "sg:phone":"+32 2 537 56 92",
    "sg:postcode":"1190",
    "sg:province":"Bruxelles-Capitale",
    "wof:name":"Michele Carlier",
    "wof:placetype":"venue"
},
  "geometry": {"coordinates":[4.3421649933,50.8220291138],"type":"Point"}
}