{
  "type": "Feature",
  "properties": {
    "iso:country":"BE",
    "sg:address":"Rue De L'egalit\u00e9 28",
    "sg:city":"Frameries (eugies)",
    "sg:classifiers":[
        {
            "category":"Real Estate",
            "subcategory":"Surveying",
            "type":"Services"
        }
    ],
    "sg:phone":"+32 65 67 49 94",
    "sg:postcode":"7080",
    "sg:province":"Hainaut",
    "sg:tags":[
        "lettering",
        "letter"
    ],
    "wof:name":"M P R Impressions Sprl",
    "wof:placetype":"venue"
},
  "geometry": {"coordinates":[3.8887228966,50.3925094604],"type":"Point"}
}