{
  "type": "Feature",
  "properties": {
    "iso:country":"BE",
    "sg:address":"Industriepark-zwijnaarde 7",
    "sg:city":"Zwijnaarde",
    "sg:classifiers":[
        {
            "category":"Food & Beverages",
            "subcategory":"Groceries & Convenience Stores",
            "type":"Retail Goods"
        }
    ],
    "sg:phone":"+32 9 241 07 11",
    "sg:postcode":"9052",
    "sg:province":"Oost-Vlaanderen",
    "sg:tags":[
        "product",
        "grain",
        "cereal",
        "related"
    ],
    "wof:name":"Innogenetics Belux Nv",
    "wof:placetype":"venue"
},
  "geometry": {"coordinates":[3.7222120762,51.0094032288],"type":"Point"}
}