{
  "type": "Feature",
  "properties": {
    "addr:full":"Hoogstraat 3 Zottegem Oost-Vlaanderen 9620",
    "addr:housenumber":"3",
    "addr:postcode":"9620",
    "addr:street":"Hoogstraat",
    "iso:country":"BE",
    "sg:address":"Hoogstraat 3",
    "sg:city":"Zottegem",
    "sg:orig_category":"Opticiens Pearle Opticiens",
    "sg:phone":"+32 9 361 18 13",
    "sg:postcode":"9620",
    "sg:province":"Oost-Vlaanderen",
    "wof:name":"Pearle Opticiens",
    "wof:placetype":"venue"
},
  "geometry": {"coordinates":[3.8100669384,50.869468689],"type":"Point"}
}