{
  "type": "Feature",
  "properties": {
    "addr:full":"Baasrodeveerstraat 2 Hamme Oost-Vlaanderen 9220",
    "addr:housenumber":"2",
    "addr:postcode":"9220",
    "addr:street":"Baasrodeveerstraat",
    "iso:country":"BE",
    "sg:address":"Baasrodeveerstraat 2",
    "sg:city":"Hamme",
    "sg:orig_category":"Verhuur cateringmateriaal and evenementuitrusting Winkelinrichting and handelsuitrusting Gh",
    "sg:phone":"+32 52 48 30 87",
    "sg:postcode":"9220",
    "sg:province":"Oost-Vlaanderen",
    "wof:name":"L. Verhelst",
    "wof:placetype":"venue"
},
  "geometry": {"coordinates":[4.16766119,51.0491409302],"type":"Point"}
}