{
  "type": "Feature",
  "properties": {
    "iso:country":"BE",
    "sg:address":"Rue D\u00b4aumale 81",
    "sg:city":"Anderlecht",
    "sg:orig_category":"Installatie van metalen schrijnwerk",
    "sg:phone":"+32 2 520 09 40",
    "sg:postcode":"1070",
    "sg:province":"Bruxelles-Capitale",
    "wof:name":"Intec",
    "wof:placetype":"venue"
},
  "geometry": {"coordinates":[4.3098812103,50.8381309509],"type":"Point"}
}