{
  "type": "Feature",
  "properties": {
    "addr:full":"Avenue Des Alouettes 38 Tubize Brabant Wallon 1480",
    "addr:housenumber":"38",
    "addr:postcode":"1480",
    "addr:street":"Avenue Des Alouettes;Wallon",
    "iso:country":"BE",
    "sg:address":"Avenue Des Alouettes 38",
    "sg:city":"Tubize",
    "sg:orig_category":"Dansscholen",
    "sg:phone":"+32 2 355 83 36",
    "sg:postcode":"1480",
    "sg:province":"Brabant Wallon",
    "wof:name":"Modern Jazz",
    "wof:placetype":"venue"
},
  "geometry": {"coordinates":[4.2364091873,50.6887931824],"type":"Point"}
}