{
  "type": "Feature",
  "properties": {
    "iso:country":"BE",
    "sg:address":"Avenue Henri De Brouck\u00c8re 48",
    "sg:city":"Oudergem/auderghem",
    "sg:orig_category":"Notaires",
    "sg:phone":"+32 2 672 40 00",
    "sg:postcode":"1160",
    "sg:province":"Bruxelles-Capitale",
    "wof:name":"Patrick Gustin",
    "wof:placetype":"venue"
},
  "geometry": {"coordinates":[4.4239377975,50.818321228],"type":"Point"}
}