{
  "type": "Feature",
  "properties": {
    "addr:full":"Kloosterberg 29 Herzele (steenhuize-wijnhuize) Oost-Vlaanderen 9550",
    "addr:housenumber":"29",
    "addr:postcode":"9550",
    "addr:street":"Kloosterberg;Steenhuize-Wijnhuize Oost-Vlaanderen",
    "iso:country":"BE",
    "sg:address":"Kloosterberg 29",
    "sg:city":"Herzele (steenhuize-wijnhuize)",
    "sg:classifiers":[
        {
            "category":"Freight",
            "type":"Transportation"
        }
    ],
    "sg:phone":"+32 475 70 04 72",
    "sg:postcode":"9550",
    "sg:province":"Oost-Vlaanderen",
    "sg:tags":[
        "-",
        "transport"
    ],
    "wof:name":"Jacob",
    "wof:placetype":"venue"
},
  "geometry": {"coordinates":[3.8891899586,50.8389091492],"type":"Point"}
}