{
  "type": "Feature",
  "properties": {
    "iso:country":"BE",
    "sg:address":"Lange Bergstraat 10ba",
    "sg:city":"Wetteren",
    "sg:orig_category":"Dameskledingzaken",
    "sg:phone":"+32 9 366 14 76",
    "sg:postcode":"9230",
    "sg:province":"Oost-Vlaanderen",
    "wof:name":"Trento Fashion",
    "wof:placetype":"venue"
},
  "geometry": {"coordinates":[3.8833229542,51.0052070618],"type":"Point"}
}