{
  "type": "Feature",
  "properties": {
    "iso:country":"BE",
    "sg:address":"Artesi\u00cbstraat 60",
    "sg:city":"Brussel/bruxelles",
    "sg:orig_category":"Artiesten and kunstenaars",
    "sg:phone":"+32 2 502 63 36",
    "sg:postcode":"1000",
    "sg:province":"Bruxelles-Capitale",
    "wof:name":"Marie-pierre Meinzel",
    "wof:placetype":"venue"
},
  "geometry": {"coordinates":[4.3406271935,50.8422355652],"type":"Point"}
}