{
  "type": "Feature",
  "properties": {
    "addr:full":"Rue Wiertz 50 Bruxelles (ixelles) Bruxelles-Capitale 1050",
    "addr:housenumber":"50",
    "addr:postcode":"1050",
    "addr:street":"Rue Wiertz",
    "iso:country":"BE",
    "sg:address":"Rue Wiertz 50",
    "sg:city":"Bruxelles (ixelles)",
    "sg:classifiers":[
        {
            "category":"Organizations",
            "subcategory":"Professional Association",
            "type":"Services"
        }
    ],
    "sg:phone":"+32 2 286 91 22",
    "sg:postcode":"1050",
    "sg:province":"Bruxelles-Capitale",
    "sg:tags":[
        "trade-union",
        "federation"
    ],
    "wof:name":"Egta",
    "wof:placetype":"venue"
},
  "geometry": {"coordinates":[4.3747739792,50.8378143311],"type":"Point"}
}