{
  "type": "Feature",
  "properties": {
    "iso:country":"BE",
    "sg:address":"Leenstraat 41",
    "sg:city":"Herne",
    "sg:orig_category":"Sportclubs",
    "sg:phone":"+32 54 56 85 03",
    "sg:postcode":"1540",
    "sg:province":"Vlaams-Brabant",
    "wof:name":"Shotokan",
    "wof:placetype":"venue"
},
  "geometry": {"coordinates":[4.0525970459,50.7465591431],"type":"Point"}
}