{
  "type": "Feature",
  "properties": {
    "iso:country":"BE",
    "sg:address":"Hulst 133",
    "sg:city":"Opwijk",
    "sg:orig_category":"Fabrication and montage de mobilier",
    "sg:phone":"+32 52 35 53 74",
    "sg:postcode":"1745",
    "sg:province":"Vlaams-Brabant",
    "wof:name":"Aelbrecht Jean-paul",
    "wof:placetype":"venue"
},
  "geometry": {"coordinates":[4.1855549812,50.9595947266],"type":"Point"}
}