{
  "type": "Feature",
  "properties": {
    "addr:full":"Rue Des Forges 18 Couvin Namur 5660",
    "addr:housenumber":"18",
    "addr:postcode":"5660",
    "addr:street":"Rue Des Forges",
    "iso:country":"BE",
    "sg:address":"Rue Des Forges 18",
    "sg:city":"Couvin",
    "sg:classifiers":[
        {
            "category":"Insurance",
            "subcategory":"Life Insurance",
            "type":"Services"
        }
    ],
    "sg:phone":"+32 60 34 60 11",
    "sg:postcode":"5660",
    "sg:province":"Namur",
    "sg:tags":[
        "assurance"
    ],
    "wof:name":"J.f. Valentin",
    "wof:placetype":"venue"
},
  "geometry": {"coordinates":[4.4253802299,50.0278091431],"type":"Point"}
}