{
  "type": "Feature",
  "properties": {
    "addr:full":"Vollezelestraat 148ba Gooik Vlaams-Brabant 1755",
    "addr:postcode":"1755",
    "addr:street":"Vollezelestraat;Vlaams-Brabant",
    "iso:country":"BE",
    "sg:address":"Vollezelestraat 148ba",
    "sg:city":"Gooik",
    "sg:orig_category":"Entretien and r\u00e9parations de voitures",
    "sg:phone":"+32 54 56 71 07",
    "sg:postcode":"1755",
    "sg:province":"Vlaams-Brabant",
    "wof:name":"Dirk Lemaire",
    "wof:placetype":"venue"
},
  "geometry": {"coordinates":[4.0427708626,50.7678604126],"type":"Point"}
}