{
  "type": "Feature",
  "properties": {
    "addr:full":"Koning Albertlaan 29a Lochristi Oost-Vlaanderen 9080",
    "addr:housenumber":"29a",
    "addr:postcode":"9080",
    "addr:street":"Koning Albertlaan",
    "iso:country":"BE",
    "sg:address":"Koning Albertlaan 29a",
    "sg:city":"Lochristi",
    "sg:classifiers":[
        {
            "category":"Health Services",
            "subcategory":"Doctor",
            "type":"Services"
        }
    ],
    "sg:phone":"+32 9 355 89 98",
    "sg:postcode":"9080",
    "sg:province":"Oost-Vlaanderen",
    "sg:tags":[
        "medicinephysicians",
        "surgeon"
    ],
    "wof:name":"De Laender F",
    "wof:placetype":"venue"
},
  "geometry": {"coordinates":[3.8303720951,51.0982551575],"type":"Point"}
}