{
  "type": "Feature",
  "properties": {
    "addr:full":"Avenue Joseph Lebeau 1 Huy Li\u00e8ge 4500",
    "addr:housenumber":"1",
    "addr:postcode":"4500",
    "addr:street":"Avenue Joseph Lebeau",
    "iso:country":"BE",
    "sg:address":"Avenue Joseph Lebeau 1",
    "sg:city":"Huy",
    "sg:orig_category":"Advocaten and juridische adviseurs",
    "sg:phone":"+32 85 21 58 95",
    "sg:postcode":"4500",
    "sg:province":"Li\u00e8ge",
    "wof:name":"Marielle Donne",
    "wof:placetype":"venue"
},
  "geometry": {"coordinates":[5.2420139313,50.5232124329],"type":"Point"}
}