{
  "type": "Feature",
  "properties": {
    "addr:full":"Oude Bruggestraat 53 Wingene West-Vlaanderen 8750",
    "addr:housenumber":"53",
    "addr:postcode":"8750",
    "addr:street":"Oude Bruggestraat",
    "iso:country":"BE",
    "sg:address":"Oude Bruggestraat 53",
    "sg:city":"Wingene",
    "sg:classifiers":[
        {
            "category":"Professional",
            "subcategory":"Art Services",
            "type":"Services"
        }
    ],
    "sg:phone":"+32 51 54 53 09",
    "sg:postcode":"8750",
    "sg:province":"West-Vlaanderen",
    "sg:tags":[
        "sculptor"
    ],
    "wof:name":"Van Zon M",
    "wof:placetype":"venue"
},
  "geometry": {"coordinates":[3.274627924,51.0584983826],"type":"Point"}
}