{
  "type": "Feature",
  "properties": {
    "iso:country":"BE",
    "sg:address":"Rue De La Source 43",
    "sg:city":"Sint-gillis/saint-gilles",
    "sg:orig_category":"Diverse informatica-activiteiten Diverse opleidingen and onderwijs Software ontwikkeling and ontwerp",
    "sg:phone":"+32 475 66 24 09",
    "sg:postcode":"1060",
    "sg:province":"Bruxelles-Capitale",
    "wof:name":"Web4pro",
    "wof:placetype":"venue"
},
  "geometry": {"coordinates":[4.3517990112,50.8312721252],"type":"Point"}
}