{
  "type": "Feature",
  "properties": {
    "addr:full":"Moorselbaan 31 Aalst Oost-Vlaanderen 9300",
    "addr:housenumber":"31",
    "addr:postcode":"9300",
    "addr:street":"Moorselbaan",
    "iso:country":"BE",
    "sg:address":"Moorselbaan 31",
    "sg:city":"Aalst",
    "sg:orig_category":"Opticiens",
    "sg:phone":"+32 53 21 59 24",
    "sg:postcode":"9300",
    "sg:province":"Oost-Vlaanderen",
    "wof:name":"Optiek Hilde",
    "wof:placetype":"venue"
},
  "geometry": {"coordinates":[4.0475931168,50.9413757324],"type":"Point"}
}