{
  "type": "Feature",
  "properties": {
    "iso:country":"BE",
    "sg:address":"Gentsesteenweg 412",
    "sg:city":"Aalst",
    "sg:orig_category":"Computers and computerapparatuur Onderhoud van kantoor- and computeruitrusting Software ontwikkeling",
    "sg:phone":"+32 53 21 13 52",
    "sg:postcode":"9300",
    "sg:province":"Oost-Vlaanderen",
    "wof:name":"Dataction",
    "wof:placetype":"venue"
},
  "geometry": {"coordinates":[4.0056171417,50.9409561157],"type":"Point"}
}