{
  "type": "Feature",
  "properties": {
    "addr:full":"Ooststraat 18 Roeselare West-Vlaanderen 8800",
    "addr:housenumber":"18",
    "addr:postcode":"8800",
    "addr:street":"Ooststraat",
    "iso:country":"BE",
    "sg:address":"Ooststraat 18",
    "sg:city":"Roeselare",
    "sg:orig_category":"Parfumeries",
    "sg:phone":"+32 51 24 45 17",
    "sg:postcode":"8800",
    "sg:province":"West-Vlaanderen",
    "wof:name":"Ici Paris Xl",
    "wof:placetype":"venue"
},
  "geometry": {"coordinates":[3.1248459816,50.9455680847],"type":"Point"}
}