{
  "type": "Feature",
  "properties": {
    "iso:country":"BE",
    "sg:address":"Val Du Prince 36",
    "sg:city":"Kraainem/kraainem",
    "sg:orig_category":"M\u00e9decins and sp\u00e9cialistes",
    "sg:phone":"+32 2 731 79 21",
    "sg:postcode":"1950",
    "sg:province":"Vlaams-Brabant",
    "wof:name":"B. Kreit",
    "wof:placetype":"venue"
},
  "geometry": {"coordinates":[4.4746928215,50.8352432251],"type":"Point"}
}