{
  "type": "Feature",
  "properties": {
    "addr:full":"Delacenseriestraat 23 De Haan (wenduine) West-Vlaanderen 8420",
    "addr:housenumber":"23",
    "addr:postcode":"8420",
    "addr:street":"Delacenseriestraat",
    "iso:country":"BE",
    "sg:address":"Delacenseriestraat 23",
    "sg:city":"De Haan (wenduine)",
    "sg:classifiers":[
        {
            "category":"Farming",
            "subcategory":"Fish & Marine Products",
            "type":"Manufacturing & Wholesale Goods"
        }
    ],
    "sg:phone":"+32 50 41 36 06",
    "sg:postcode":"8420",
    "sg:province":"West-Vlaanderen",
    "sg:tags":[
        "retail",
        "-",
        "shellfish"
    ],
    "wof:name":"De Tuimelaar",
    "wof:placetype":"venue"
},
  "geometry": {"coordinates":[3.0796570778,51.3002738953],"type":"Point"}
}