{
  "type": "Feature",
  "properties": {
    "addr:full":"Rue D'opprebais 1 Perwez Brabant Wallon 1360",
    "addr:housenumber":"1",
    "addr:postcode":"1360",
    "addr:street":"Rue D'Opprebais",
    "iso:country":"BE",
    "sg:address":"Rue D'opprebais 1",
    "sg:city":"Perwez",
    "sg:classifiers":[
        {
            "category":"Personal",
            "subcategory":"Beauty Salon",
            "type":"Services"
        }
    ],
    "sg:phone":"+32 10 88 82 83",
    "sg:postcode":"1360",
    "sg:province":"Brabant Wallon",
    "sg:tags":[
        "de",
        "coiffure"
    ],
    "wof:name":"L'atelier De Coiffure",
    "wof:placetype":"venue"
},
  "geometry": {"coordinates":[4.78358078,50.6588821411],"type":"Point"}
}