{
  "type": "Feature",
  "properties": {
    "iso:country":"BE",
    "sg:address":"Koolsveldlaan 159",
    "sg:city":"Wijnegem",
    "sg:orig_category":"Boucheries",
    "sg:phone":"+32 3 353 99 85",
    "sg:postcode":"2110",
    "sg:province":"Antwerpen",
    "wof:name":"Harry Dillewijns",
    "wof:placetype":"venue"
},
  "geometry": {"coordinates":[4.506840229,51.2213172913],"type":"Point"}
}