{
  "type": "Feature",
  "properties": {
    "addr:full":"Theo De Deckerlaan 2 Temse Oost-Vlaanderen 9140",
    "addr:housenumber":"2",
    "addr:postcode":"9140",
    "addr:street":"Theo;Deckerlaan",
    "iso:country":"BE",
    "sg:address":"Theo De Deckerlaan 2",
    "sg:city":"Temse",
    "sg:classifiers":[
        {
            "category":"Education",
            "subcategory":"School",
            "type":"Public Place"
        }
    ],
    "sg:phone":"+32 3 771 07 12",
    "sg:postcode":"9140",
    "sg:province":"Oost-Vlaanderen",
    "sg:tags":[
        "primary"
    ],
    "wof:name":"B.s.g.o. Temse",
    "wof:placetype":"venue"
},
  "geometry": {"coordinates":[4.2079992294,51.131023407],"type":"Point"}
}