{
  "type": "Feature",
  "properties": {
    "iso:country":"BE",
    "sg:address":"Langdorpsesteenweg 25",
    "sg:city":"Aarschot",
    "sg:orig_category":"Dierenartsen",
    "sg:phone":"+32 16 56 82 71",
    "sg:postcode":"3200",
    "sg:province":"Vlaams-Brabant",
    "wof:name":"Bart Debontridder",
    "wof:placetype":"venue"
},
  "geometry": {"coordinates":[4.8427200317,50.9921798706],"type":"Point"}
}