{
  "type": "Feature",
  "properties": {
    "addr:full":"Lentestraat 35 Diepenbeek Limburg 3590",
    "addr:housenumber":"35",
    "addr:postcode":"3590",
    "addr:street":"Lentestraat",
    "iso:country":"BE",
    "sg:address":"Lentestraat 35",
    "sg:city":"Diepenbeek",
    "sg:orig_category":"Diverse bouwafwerking and reiniging",
    "sg:phone":"+32 11 32 23 58",
    "sg:postcode":"3590",
    "sg:province":"Limburg",
    "wof:name":"Ferdinand Smeers",
    "wof:placetype":"venue"
},
  "geometry": {"coordinates":[5.4466137886,50.9329147339],"type":"Point"}
}