{
  "type": "Feature",
  "properties": {
    "addr:full":"Rue Sainte-agn\u00e8s 67 Charleroi (gilly) Hainaut 6060",
    "addr:housenumber":"67",
    "addr:postcode":"6060",
    "addr:street":"Rue Sainte-Agne\u0300S",
    "iso:country":"BE",
    "sg:address":"Rue Sainte-agn\u00e8s 67",
    "sg:city":"Charleroi (gilly)",
    "sg:classifiers":[
        {
            "category":"Professional",
            "subcategory":"Accounting & Tax Preparation",
            "type":"Services"
        }
    ],
    "sg:phone":"+32 71 41 90 14",
    "sg:postcode":"6060",
    "sg:province":"Hainaut",
    "sg:tags":[
        "pattern",
        "maker"
    ],
    "wof:name":"Deneure Y",
    "wof:placetype":"venue"
},
  "geometry": {"coordinates":[4.4880981445,50.4251937866],"type":"Point"}
}