{
  "type": "Feature",
  "properties": {
    "addr:full":"Rue Du Pont Du Christ 46b Wavre Brabant Wallon 1300",
    "addr:housenumber":"46b;1300",
    "addr:street":"Rue Du Pont Du Christ",
    "iso:country":"BE",
    "sg:address":"Rue Du Pont Du Christ 46b",
    "sg:city":"Wavre",
    "sg:orig_category":"V\u00eatements pour Hommes. V\u00eatements pour Dames. V\u00eatements pour b\u00e9b\u00e9s and enfants",
    "sg:phone":"+32 10 22 54 94",
    "sg:postcode":"1300",
    "sg:province":"Brabant Wallon",
    "wof:name":"Benetton",
    "wof:placetype":"venue"
},
  "geometry": {"coordinates":[4.6092939377,50.7159118652],"type":"Point"}
}