{
  "type": "Feature",
  "properties": {
    "addr:full":"Fond De Nanty 1 Florenville Luxembourg 6820",
    "addr:housenumber":"1",
    "addr:postcode":"6820",
    "iso:country":"BE",
    "sg:address":"Fond De Nanty 1",
    "sg:city":"Florenville",
    "sg:classifiers":[
        {
            "category":"Bars & Pubs",
            "type":"Food & Drink"
        }
    ],
    "sg:phone":"+32 61 31 59 45",
    "sg:postcode":"6820",
    "sg:province":"Luxembourg",
    "wof:name":"Fond De Nanty",
    "wof:placetype":"venue"
},
  "geometry": {"coordinates":[5.2845420837,49.6838188171],"type":"Point"}
}