{
  "type": "Feature",
  "properties": {
    "iso:country":"BE",
    "sg:address":"Rue De Birmingham 75",
    "sg:city":"Molenbeek-saint-jean",
    "sg:orig_category":"Produits chimiques Gr",
    "sg:phone":"+32 2 410 02 72",
    "sg:postcode":"1080",
    "sg:province":"Bruxelles-Capitale",
    "wof:name":"Van Malderen",
    "wof:placetype":"venue"
},
  "geometry": {"coordinates":[4.32538414,50.8472900391],"type":"Point"}
}