{
  "type": "Feature",
  "properties": {
    "addr:full":"Rue De Marchienne 5 Montigny-le-tilleul Hainaut 6110",
    "addr:housenumber":"5",
    "addr:postcode":"6110",
    "addr:street":"Rue De Marchienne",
    "iso:country":"BE",
    "sg:address":"Rue De Marchienne 5",
    "sg:city":"Montigny-le-tilleul",
    "sg:orig_category":"Overheidsdiensten",
    "sg:phone":"+32 71 51 88 10",
    "sg:postcode":"6110",
    "sg:province":"Hainaut",
    "wof:name":"Administration Communale",
    "wof:placetype":"venue"
},
  "geometry": {"coordinates":[4.3804421425,50.379863739],"type":"Point"}
}