{
  "type": "Feature",
  "properties": {
    "addr:full":"Vliegveldlaan 179 Sint-truiden Limburg 3800",
    "addr:housenumber":"179",
    "addr:postcode":"sint-truiden;3800",
    "addr:street":"Vliegveldlaan",
    "iso:country":"BE",
    "sg:address":"Vliegveldlaan 179",
    "sg:city":"Sint-truiden",
    "sg:classifiers":[
        {
            "category":"Restaurant",
            "type":"Food & Drink"
        }
    ],
    "sg:phone":"+32 11 69 15 37",
    "sg:postcode":"3800",
    "sg:province":"Limburg",
    "sg:tags":[
        "caf\u00e9s"
    ],
    "wof:name":"Taverne Bovary",
    "wof:placetype":"venue"
},
  "geometry": {"coordinates":[5.2262020111,50.8092803955],"type":"Point"}
}