{
  "type": "Feature",
  "properties": {
    "iso:country":"BE",
    "sg:address":"Teniersstraat 1b1",
    "sg:city":"Schaarbeek/schaerbeek",
    "sg:orig_category":"Persagentschappen",
    "sg:phone":"+32 2 216 16 42",
    "sg:postcode":"1030",
    "sg:province":"Bruxelles-Capitale",
    "wof:name":"Pascal De Gendt",
    "wof:placetype":"venue"
},
  "geometry": {"coordinates":[4.3774638176,50.8644638062],"type":"Point"}
}