{
  "type": "Feature",
  "properties": {
    "iso:country":"BE",
    "sg:address":"Jean Dubrucqlaan 84",
    "sg:city":"Sint-jans-molenbeek/molenbeek-saint-jean",
    "sg:orig_category":"Herstelling leer and schoeisel",
    "sg:phone":"+32 2 428 27 41",
    "sg:postcode":"1080",
    "sg:province":"Bruxelles-Capitale",
    "wof:name":"Francesco Gaudiuso",
    "wof:placetype":"venue"
},
  "geometry": {"coordinates":[4.3353900909,50.866065979],"type":"Point"}
}