{
  "type": "Feature",
  "properties": {
    "iso:country":"BE",
    "sg:address":"Kruisbaan 122",
    "sg:city":"Beringen",
    "sg:orig_category":"Sportclubs Sportterreinen and installaties behalve sportcentra",
    "sg:phone":"+32 11 42 66 23",
    "sg:postcode":"3580",
    "sg:province":"Limburg",
    "wof:name":"A.c. Tervant",
    "wof:placetype":"venue"
},
  "geometry": {"coordinates":[5.205988884,51.0642738342],"type":"Point"}
}