{
  "type": "Feature",
  "properties": {
    "iso:country":"BE",
    "sg:address":"Borgoumont 71",
    "sg:city":"Stoumont",
    "sg:orig_category":"Tuinen",
    "sg:phone":"+32 80 78 54 17",
    "sg:postcode":"4987",
    "sg:province":"Li\u00e8ge",
    "wof:name":"Behling",
    "wof:placetype":"venue"
},
  "geometry": {"coordinates":[5.8098897934,50.4056663513],"type":"Point"}
}