{
  "type": "Feature",
  "properties": {
    "addr:full":"Kronevoordestraat 55 Kortemark West-Vlaanderen 8610",
    "addr:housenumber":"55",
    "addr:postcode":"8610",
    "addr:street":"Kronevoordestraat",
    "iso:country":"BE",
    "sg:address":"Kronevoordestraat 55",
    "sg:city":"Kortemark",
    "sg:classifiers":[
        {
            "category":"Cafe",
            "type":"Food & Drink"
        }
    ],
    "sg:phone":"+32 51 56 95 85",
    "sg:postcode":"8610",
    "sg:province":"West-Vlaanderen",
    "sg:tags":[
        "caf\u00e9s"
    ],
    "wof:name":"Bart Beeckaert",
    "wof:placetype":"venue"
},
  "geometry": {"coordinates":[3.0052530766,51.02135849],"type":"Point"}
}