{
  "type": "Feature",
  "properties": {
    "iso:country":"BE",
    "sg:address":"Brusselsesteenweg 26",
    "sg:city":"Tervuren",
    "sg:orig_category":"Meubles D\u00e9taillants, Am\u00e9nagement de B\u00e2timents et de Cuisines",
    "sg:phone":"+32 2 767 31 88",
    "sg:postcode":"3080",
    "sg:province":"Vlaams-Brabant",
    "wof:name":"Jan Steenacker",
    "wof:placetype":"venue"
},
  "geometry": {"coordinates":[4.51060009,50.8243713379],"type":"Point"}
}