{
  "type": "Feature",
  "properties": {
    "iso:country":"BE",
    "sg:address":"Merksplassesteenweg 23",
    "sg:city":"Rijkevorsel",
    "sg:orig_category":"Eleveurs de bovins",
    "sg:phone":"+32 3 314 51 60",
    "sg:postcode":"2310",
    "sg:province":"Antwerpen",
    "wof:name":"Jozef Hermans",
    "wof:placetype":"venue"
},
  "geometry": {"coordinates":[4.7834200859,51.3465309143],"type":"Point"}
}