{
  "type": "Feature",
  "properties": {
    "iso:country":"BE",
    "sg:address":"Gullegemsestraat 94",
    "sg:city":"Kortrijk (heule)",
    "sg:orig_category":"Non-Classified Establishments",
    "sg:phone":"+32 56 35 63 91",
    "sg:postcode":"8501",
    "sg:province":"West-Vlaanderen",
    "wof:name":"Orfino",
    "wof:placetype":"venue"
},
  "geometry": {"coordinates":[3.2239630222,50.8441581726],"type":"Point"}
}