{
  "type": "Feature",
  "properties": {
    "addr:full":"Rue Eloi Fouarge 38 Saint-georges-sur-meuse Li\u00e8ge 4470",
    "addr:housenumber":"38",
    "addr:postcode":"4470",
    "addr:street":"Rue Eloi Fouarge",
    "iso:country":"BE",
    "sg:address":"Rue Eloi Fouarge 38",
    "sg:city":"Saint-georges-sur-meuse",
    "sg:classifiers":[
        {
            "category":"Personal",
            "subcategory":"Beauty Salon",
            "type":"Services"
        }
    ],
    "sg:phone":"+32 4 275 71 26",
    "sg:postcode":"4470",
    "sg:province":"Li\u00e8ge",
    "sg:tags":[
        "de",
        "coiffure"
    ],
    "wof:name":"Coiffure Olivier",
    "wof:placetype":"venue"
},
  "geometry": {"coordinates":[5.3606710434,50.58934021],"type":"Point"}
}