{
  "type": "Feature",
  "properties": {
    "iso:country":"BE",
    "sg:address":"Tweede Aardstraat 22",
    "sg:city":"Harelbeke (bavikhove)",
    "sg:classifiers":[
        {
            "category":"Building & Trades",
            "subcategory":"Construction",
            "type":"Services"
        }
    ],
    "sg:phone":"+32 56 71 67 76",
    "sg:postcode":"8531",
    "sg:province":"West-Vlaanderen",
    "sg:tags":[
        "carpenter"
    ],
    "wof:name":"Verheye P",
    "wof:placetype":"venue"
},
  "geometry": {"coordinates":[3.3206949234,50.8797492981],"type":"Point"}
}