{
  "type": "Feature",
  "properties": {
    "addr:full":"Rue De Taillis Pr\u00e9 71 Ch\u00e2telet (ch\u00e2telineau) Hainaut 6200",
    "addr:housenumber":"71",
    "addr:postcode":"6200",
    "addr:street":"Rue De Taillis Pre\u0301",
    "iso:country":"BE",
    "sg:address":"Rue De Taillis Pr\u00e9 71",
    "sg:city":"Ch\u00e2telet (ch\u00e2telineau)",
    "sg:classifiers":[
        {
            "category":"Manufacturing",
            "subcategory":"Textiles",
            "type":"Manufacturing & Wholesale Goods"
        }
    ],
    "sg:phone":"+32 71 38 90 52",
    "sg:postcode":"6200",
    "sg:province":"Hainaut",
    "sg:tags":[
        "retail",
        "-"
    ],
    "wof:name":"Ingotex",
    "wof:placetype":"venue"
},
  "geometry": {"coordinates":[4.5070271492,50.4336471558],"type":"Point"}
}