{
  "type": "Feature",
  "properties": {
    "iso:country":"BE",
    "sg:address":"Brusselsesteenweg 291",
    "sg:city":"Asse",
    "sg:orig_category":"Drogueries",
    "sg:phone":"+32 2 452 28 49",
    "sg:postcode":"1730",
    "sg:province":"Vlaams-Brabant",
    "wof:name":"Jozef De Donder",
    "wof:placetype":"venue"
},
  "geometry": {"coordinates":[4.2325439453,50.897605896],"type":"Point"}
}