{
  "type": "Feature",
  "properties": {
    "iso:country":"BE",
    "sg:address":"Chauss\u00c9e De Wervicq 343",
    "sg:city":"Komen-waasten/comines-warneton",
    "sg:classifiers":[
        {
            "category":"Cafe",
            "type":"Food & Drink"
        }
    ],
    "sg:phone":"+32 56 55 92 39",
    "sg:postcode":"7780",
    "sg:province":"Hainaut",
    "sg:tags":[
        "caf\u00e9s"
    ],
    "wof:name":"Liliane Herreman",
    "wof:placetype":"venue"
},
  "geometry": {"coordinates":[3.0177650452,50.7766265869],"type":"Point"}
}