{
  "type": "Feature",
  "properties": {
    "iso:country":"BE",
    "sg:address":"Korte Vianenstraat 4b39",
    "sg:city":"Turnhout",
    "sg:orig_category":"Artsen and specialisten",
    "sg:phone":"+32 14 43 52 72",
    "sg:postcode":"2300",
    "sg:province":"Antwerpen",
    "wof:name":"Otto M.j. Stammen",
    "wof:placetype":"venue"
},
  "geometry": {"coordinates":[4.9434270859,51.3194007874],"type":"Point"}
}