{
  "type": "Feature",
  "properties": {
    "addr:full":"Josaphatstraat 73 Schaarbeek/schaerbeek Bruxelles-Capitale 1030",
    "addr:housenumber":"73",
    "addr:postcode":"1030",
    "addr:street":"Josaphatstraat",
    "iso:country":"BE",
    "sg:address":"Josaphatstraat 73",
    "sg:city":"Schaarbeek/schaerbeek",
    "sg:orig_category":"Apotheken",
    "sg:phone":"+32 2 217 11 71",
    "sg:postcode":"1030",
    "sg:province":"Bruxelles-Capitale",
    "wof:name":"Alain Schmit",
    "wof:placetype":"venue"
},
  "geometry": {"coordinates":[4.3734898567,50.8579750061],"type":"Point"}
}