{
  "type": "Feature",
  "properties": {
    "iso:country":"BE",
    "sg:address":"Avenue Eiffel 8",
    "sg:city":"Wavre",
    "sg:classifiers":[
        {
            "category":"Banks & Credit Unions",
            "subcategory":"Bureau De Change",
            "type":"Services"
        }
    ],
    "sg:phone":"+32 10 24 36 66",
    "sg:postcode":"1300",
    "sg:province":"Brabant Wallon",
    "sg:tags":[
        "machine",
        "duplicating",
        "supply"
    ],
    "wof:name":"Meatec Sa",
    "wof:placetype":"venue"
},
  "geometry": {"coordinates":[4.5966749191,50.7376441956],"type":"Point"}
}