{
  "type": "Feature",
  "properties": {
    "iso:country":"BE",
    "sg:address":"Rue Du Vieux Monument 1",
    "sg:city":"Lasne (lasne-chapelle-saint-lambert)",
    "sg:classifiers":[
        {
            "category":"Real Estate",
            "subcategory":"Architect",
            "type":"Services"
        }
    ],
    "sg:phone":"+32 2 633 51 73",
    "sg:postcode":"1380",
    "sg:province":"Brabant Wallon",
    "wof:name":"Cl\u00e9ment G",
    "wof:placetype":"venue"
},
  "geometry": {"coordinates":[4.4795331955,50.6842346191],"type":"Point"}
}