{
  "type": "Feature",
  "properties": {
    "addr:full":"Rijksweg 146 Zulte (machelen) Oost-Vlaanderen 9870",
    "addr:housenumber":"146",
    "addr:postcode":"9870",
    "addr:street":"Rijksweg",
    "iso:country":"BE",
    "sg:address":"Rijksweg 146",
    "sg:city":"Zulte (machelen)",
    "sg:classifiers":[
        {
            "category":"Recreation",
            "subcategory":"Dance Hall",
            "type":"Entertainment"
        }
    ],
    "sg:phone":"+32 9 386 32 70",
    "sg:postcode":"9870",
    "sg:province":"Oost-Vlaanderen",
    "sg:tags":[
        "discotheque"
    ],
    "wof:name":"Montini",
    "wof:placetype":"venue"
},
  "geometry": {"coordinates":[3.4863829613,50.9505767822],"type":"Point"}
}