{
  "type": "Feature",
  "properties": {
    "iso:country":"BE",
    "sg:address":"Roeselaarsestraat 2",
    "sg:city":"Izegem",
    "sg:orig_category":"Opticiens",
    "sg:phone":"+32 51 31 90 90",
    "sg:postcode":"8870",
    "sg:province":"West-Vlaanderen",
    "wof:name":"Optiek Lambert",
    "wof:placetype":"venue"
},
  "geometry": {"coordinates":[3.2139699459,50.9178390503],"type":"Point"}
}