{
  "type": "Feature",
  "properties": {
    "iso:country":"BE",
    "sg:address":"'t Pleintje 13",
    "sg:city":"Sint-katelijne-waver (onze-lieve-vrouw-waver)",
    "sg:classifiers":[
        {
            "category":"Health Services",
            "subcategory":"Doctor",
            "type":"Services"
        }
    ],
    "sg:phone":"+32 15 75 76 37",
    "sg:postcode":"2861",
    "sg:province":"Antwerpen",
    "sg:tags":[
        "medicinephysicians",
        "surgeon"
    ],
    "wof:name":"Bruylants Stefan",
    "wof:placetype":"venue"
},
  "geometry": {"coordinates":[4.5798969269,51.0597648621],"type":"Point"}
}