{
  "type": "Feature",
  "properties": {
    "addr:full":"Lodewijk De Meesterstr. 3 Sint-niklaas Oost-Vlaanderen 9100",
    "addr:housenumber":"3",
    "addr:postcode":"9100",
    "addr:street":"Lodewijk De Meesterstr.",
    "iso:country":"BE",
    "sg:address":"Lodewijk De Meesterstr. 3",
    "sg:city":"Sint-niklaas",
    "sg:orig_category":"Overheidsdiensten",
    "sg:phone":"+32 3 760 78 88",
    "sg:postcode":"9100",
    "sg:province":"Oost-Vlaanderen",
    "wof:name":"O.c.m.w.",
    "wof:placetype":"venue"
},
  "geometry": {"coordinates":[4.1511101723,51.1633415222],"type":"Point"}
}