{
  "type": "Feature",
  "properties": {
    "addr:full":"Luikersteenweg 30 Sint-truiden Limburg 3800",
    "addr:housenumber":"30",
    "addr:postcode":"3800",
    "addr:street":"Luikersteenweg",
    "iso:country":"BE",
    "sg:address":"Luikersteenweg 30",
    "sg:city":"Sint-truiden",
    "sg:orig_category":"Supermarkten",
    "sg:phone":"+32 11 68 09 86",
    "sg:postcode":"3800",
    "sg:province":"Limburg",
    "wof:name":"Gb Contact",
    "wof:placetype":"venue"
},
  "geometry": {"coordinates":[5.1900439262,50.811794281],"type":"Point"}
}