{
  "type": "Feature",
  "properties": {
    "addr:full":"Van De Reydtlaan 26 Brecht Antwerpen 2960",
    "addr:housenumber":"26",
    "addr:postcode":"2960",
    "addr:street":"Van;Reydtlaan",
    "iso:country":"BE",
    "sg:address":"Van De Reydtlaan 26",
    "sg:city":"Brecht",
    "sg:classifiers":[
        {
            "category":"Park",
            "subcategory":"Provincial",
            "type":"Public Place"
        }
    ],
    "sg:phone":"+32 3 636 06 51",
    "sg:postcode":"2960",
    "sg:province":"Antwerpen",
    "sg:tags":[
        "closer",
        "door"
    ],
    "wof:name":"Dams J",
    "wof:placetype":"venue"
},
  "geometry": {"coordinates":[4.5928120613,51.3246879578],"type":"Point"}
}