{
  "type": "Feature",
  "properties": {
    "iso:country":"BE",
    "sg:address":"Levisstraat 2",
    "sg:city":"Villevorde",
    "sg:classifiers":[
        {
            "category":"Manufacturing",
            "subcategory":"Chemicals & Compounds",
            "type":"Manufacturing & Wholesale Goods"
        }
    ],
    "sg:phone":"+32 3 226 95 18",
    "sg:postcode":"1830",
    "sg:province":"Vlaams-Brabant",
    "sg:tags":[
        "pharmaceutical",
        "chemistry",
        "-",
        "by-product"
    ],
    "wof:name":"Tristar Industries Belgium Nv",
    "wof:placetype":"venue"
},
  "geometry": {"coordinates":[4.7310400009,51.4836540222],"type":"Point"}
}