{
  "type": "Feature",
  "properties": {
    "iso:country":"BE",
    "sg:address":"Avenue Des Combattants 122",
    "sg:city":"Rixensart",
    "sg:orig_category":"V\u00e9hicules automobiles",
    "sg:phone":"+32 2 653 75 15",
    "sg:postcode":"1332",
    "sg:province":"Brabant Wallon",
    "wof:name":"Garage Goffart",
    "wof:placetype":"venue"
},
  "geometry": {"coordinates":[4.506483078,50.7205238342],"type":"Point"}
}