{
  "type": "Feature",
  "properties": {
    "addr:full":"Rue Des Tongres 33 Etterbeek (brussel) Bruxelles-Capitale 1040",
    "addr:housenumber":"33",
    "addr:postcode":"1040",
    "addr:street":"Rue Des Tongres",
    "iso:country":"BE",
    "sg:address":"Rue Des Tongres 33",
    "sg:city":"Etterbeek (brussel)",
    "sg:orig_category":"Textiles. V\u00eatements",
    "sg:phone":"+32 2 735 45 35",
    "sg:postcode":"1040",
    "sg:province":"Bruxelles-Capitale",
    "wof:name":"Veritas",
    "wof:placetype":"venue"
},
  "geometry": {"coordinates":[4.4001131058,50.8397865295],"type":"Point"}
}