{
  "type": "Feature",
  "properties": {
    "addr:full":"Chauss\u00c9e De Huy 212 Chaumont-gistoux Brabant Wallon 1325",
    "addr:housenumber":"212",
    "addr:postcode":"1325",
    "addr:street":"Chausse\u0301E De Huy",
    "iso:country":"BE",
    "sg:address":"Chauss\u00c9e De Huy 212",
    "sg:city":"Chaumont-gistoux",
    "sg:orig_category":"Catering and organisation de f\u00eates. Alimentation sp\u00e9cialis\u00e9e",
    "sg:phone":"+32 10 68 89 88",
    "sg:postcode":"1325",
    "sg:province":"Brabant Wallon",
    "wof:name":"Traiteurs Dassonville",
    "wof:placetype":"venue"
},
  "geometry": {"coordinates":[4.6932210922,50.6852874756],"type":"Point"}
}