{
  "type": "Feature",
  "properties": {
    "addr:full":"Siemenslaan 17 Oostkamp West-Vlaanderen 8020",
    "addr:housenumber":"17",
    "addr:postcode":"8020",
    "addr:street":"Siemenslaan",
    "iso:country":"BE",
    "sg:address":"Siemenslaan 17",
    "sg:city":"Oostkamp",
    "sg:classifiers":[
        {
            "category":"Professional",
            "subcategory":"Printing & Photocopies",
            "type":"Services"
        }
    ],
    "sg:phone":"+32 50 83 38 83",
    "sg:postcode":"8020",
    "sg:province":"West-Vlaanderen",
    "sg:tags":[
        "industry",
        "publishing",
        "software"
    ],
    "wof:name":"Cerm Benelux Nv",
    "wof:placetype":"venue"
},
  "geometry": {"coordinates":[3.2374799252,51.1476554871],"type":"Point"}
}