{
  "type": "Feature",
  "properties": {
    "addr:full":"Noordlaan 50 Zwalm (munkzwalm) Oost-Vlaanderen 9630",
    "addr:housenumber":"50",
    "addr:postcode":"9630",
    "addr:street":"Noordlaan;Munkzwalm",
    "iso:country":"BE",
    "sg:address":"Noordlaan 50",
    "sg:city":"Zwalm (munkzwalm)",
    "sg:classifiers":[
        {
            "category":"Professional",
            "subcategory":"Lawyer & Legal Services",
            "type":"Services"
        }
    ],
    "sg:phone":"+32 55 49 90 70",
    "sg:postcode":"9630",
    "sg:province":"Oost-Vlaanderen",
    "sg:tags":[
        "notary"
    ],
    "wof:name":"Sobrie M",
    "wof:placetype":"venue"
},
  "geometry": {"coordinates":[3.7352049351,50.8888206482],"type":"Point"}
}