{
  "type": "Feature",
  "properties": {
    "addr:full":"Meetingstraat 15 Antwerpen Antwerpen 2060",
    "addr:housenumber":"15",
    "addr:postcode":"2060",
    "addr:street":"Meetingstraat",
    "iso:country":"BE",
    "sg:address":"Meetingstraat 15",
    "sg:city":"Antwerpen",
    "sg:orig_category":"M\u00e9decins and sp\u00e9cialistes",
    "sg:phone":"+32 3 236 30 88",
    "sg:postcode":"2060",
    "sg:province":"Antwerpen",
    "wof:name":"W. Dieben",
    "wof:placetype":"venue"
},
  "geometry": {"coordinates":[4.4325032234,51.2220878601],"type":"Point"}
}