{
  "type": "Feature",
  "properties": {
    "addr:full":"A. Coolsstraat 2 Antwerpen Antwerpen 2020",
    "addr:housenumber":"2",
    "addr:postcode":"2020",
    "addr:street":"A. Coolsstraat",
    "iso:country":"BE",
    "sg:address":"A. Coolsstraat 2",
    "sg:city":"Antwerpen",
    "sg:orig_category":"Fotogravure and zetwerk",
    "sg:phone":"+32 3 248 34 89",
    "sg:postcode":"2020",
    "sg:province":"Antwerpen",
    "wof:name":"Graph-x",
    "wof:placetype":"venue"
},
  "geometry": {"coordinates":[4.3932361603,51.1892929077],"type":"Point"}
}