{
  "type": "Feature",
  "properties": {
    "addr:full":"Bankstraat 54 Wevelgem West-Vlaanderen 8560",
    "addr:housenumber":"54",
    "addr:postcode":"8560",
    "addr:street":"Bankstraat",
    "iso:country":"BE",
    "sg:address":"Bankstraat 54",
    "sg:city":"Wevelgem",
    "sg:orig_category":"Graan, zaad and dierenvoeding Gh",
    "sg:phone":"+32 56 41 43 04",
    "sg:postcode":"8560",
    "sg:province":"West-Vlaanderen",
    "wof:name":"Devos H.",
    "wof:placetype":"venue"
},
  "geometry": {"coordinates":[3.2010099888,50.8447418213],"type":"Point"}
}