{
  "type": "Feature",
  "properties": {
    "iso:country":"BE",
    "sg:address":"Kortrijksestraat 42",
    "sg:city":"Moorslede",
    "sg:orig_category":"Woningbouw",
    "sg:phone":"+32 56 50 21 42",
    "sg:postcode":"8890",
    "sg:province":"West-Vlaanderen",
    "wof:name":"Sambouw",
    "wof:placetype":"venue"
},
  "geometry": {"coordinates":[3.1185779572,50.8498916626],"type":"Point"}
}