{
  "type": "Feature",
  "properties": {
    "iso:country":"BE",
    "sg:address":"Schoutetstraat 7",
    "sg:city":"Mechelen",
    "sg:classifiers":[
        {
            "category":"Building & Trades",
            "subcategory":"Construction",
            "type":"Services"
        }
    ],
    "sg:phone":"+32 15 20 29 05",
    "sg:postcode":"2800",
    "sg:province":"Antwerpen",
    "sg:tags":[
        "tapestry"
    ],
    "wof:name":"De Wit-koninklijke Manufactuur Van Wandtapijten",
    "wof:placetype":"venue"
},
  "geometry": {"coordinates":[4.4784460068,51.0313453674],"type":"Point"}
}