{
  "type": "Feature",
  "properties": {
    "addr:full":"Doorniksesteenweg 256 Avelgem West-Vlaanderen 8580",
    "addr:housenumber":"256",
    "addr:postcode":"8580",
    "addr:street":"Doorniksesteenweg",
    "iso:country":"BE",
    "sg:address":"Doorniksesteenweg 256",
    "sg:city":"Avelgem",
    "sg:classifiers":[
        {
            "category":"Food & Beverages",
            "subcategory":"Meat & Fish",
            "type":"Retail Goods"
        }
    ],
    "sg:phone":"+32 56 64 43 43",
    "sg:postcode":"8580",
    "sg:province":"West-Vlaanderen",
    "sg:tags":[
        "-",
        "livestock"
    ],
    "wof:name":"De Reytmolen Bvba",
    "wof:placetype":"venue"
},
  "geometry": {"coordinates":[3.4414858818,50.7653007507],"type":"Point"}
}