{
  "type": "Feature",
  "properties": {
    "addr:full":"Koningin Elisabethlaan 32 Brugge West-Vlaanderen 8000",
    "addr:housenumber":"32",
    "addr:postcode":"8000",
    "addr:street":"Koningin Elisabethlaan",
    "iso:country":"BE",
    "sg:address":"Koningin Elisabethlaan 32",
    "sg:city":"Brugge",
    "sg:classifiers":[
        {
            "category":"Fast Food",
            "type":"Food & Drink"
        }
    ],
    "sg:phone":"+32 50 34 37 24",
    "sg:postcode":"8000",
    "sg:province":"West-Vlaanderen",
    "sg:tags":[
        "fried",
        "stand",
        "potato"
    ],
    "wof:name":"Biezen (de)",
    "wof:placetype":"venue"
},
  "geometry": {"coordinates":[3.2174959183,51.2159385681],"type":"Point"}
}