{
  "type": "Feature",
  "properties": {
    "addr:full":"Rue Du Dries 6 Vorst/forest Bruxelles-Capitale 1190",
    "addr:housenumber":"6",
    "addr:postcode":"1190",
    "addr:street":"Rue Du Dries;/ Forest",
    "iso:country":"BE",
    "sg:address":"Rue Du Dries 6",
    "sg:city":"Vorst/forest",
    "sg:orig_category":"Lampes and appareils \u00e9lectriques Fab. Travaux d\u00b4installation divers",
    "sg:phone":"+32 2 376 22 69",
    "sg:postcode":"1190",
    "sg:province":"Bruxelles-Capitale",
    "wof:name":"Desimpel",
    "wof:placetype":"venue"
},
  "geometry": {"coordinates":[4.3151469231,50.8089103699],"type":"Point"}
}