{
  "type": "Feature",
  "properties": {
    "iso:country":"BE",
    "sg:address":"Klotbroek 71",
    "sg:city":"Genk",
    "sg:classifiers":[
        {
            "category":"Arena",
            "subcategory":"Sports Club",
            "type":"Entertainment"
        }
    ],
    "sg:phone":"+32 89 35 67 01",
    "sg:postcode":"3600",
    "sg:province":"Limburg",
    "sg:tags":[
        "de"
    ],
    "wof:name":"W.c. Heidebloem",
    "wof:placetype":"venue"
},
  "geometry": {"coordinates":[5.4411811829,50.9754066467],"type":"Point"}
}