{
  "type": "Feature",
  "properties": {
    "iso:country":"BE",
    "sg:address":"Rue Meyerbeer 157",
    "sg:city":"Bruxelles (uccle)",
    "sg:classifiers":[
        {
            "category":"Retail",
            "subcategory":"Auto Repair",
            "type":"Services"
        }
    ],
    "sg:phone":"+32 2 343 60 96",
    "sg:postcode":"1180",
    "sg:province":"Bruxelles-Capitale",
    "sg:tags":[
        "garage"
    ],
    "wof:name":"Claude",
    "wof:placetype":"venue"
},
  "geometry": {"coordinates":[4.340034008,50.8146591187],"type":"Point"}
}