{
  "type": "Feature",
  "properties": {
    "addr:full":"Champagne 103 Weismes Li\u00e8ge 4950",
    "addr:housenumber":"103",
    "addr:postcode":"4950",
    "addr:street":"Champagne",
    "iso:country":"BE",
    "sg:address":"Champagne 103",
    "sg:city":"Weismes",
    "sg:classifiers":[
        {
            "category":"Shopping",
            "subcategory":"Bicycles & Sporting Goods",
            "type":"Retail Goods"
        }
    ],
    "sg:phone":"+32 80 67 98 62",
    "sg:postcode":"4950",
    "sg:province":"Li\u00e8ge",
    "sg:tags":[
        "-"
    ],
    "wof:name":"Go Bike",
    "wof:placetype":"venue"
},
  "geometry": {"coordinates":[6.1385030746,50.4378395081],"type":"Point"}
}