{
  "type": "Feature",
  "properties": {
    "addr:full":"Hubesheide 5 Bree Limburg 3960",
    "addr:housenumber":"5",
    "addr:postcode":"3960",
    "addr:street":"Hubesheide",
    "iso:country":"BE",
    "sg:address":"Hubesheide 5",
    "sg:city":"Bree",
    "sg:classifiers":[
        {
            "category":"Insurance",
            "subcategory":"Life Insurance",
            "type":"Services"
        }
    ],
    "sg:phone":"+32 89 86 38 13",
    "sg:postcode":"3960",
    "sg:province":"Limburg",
    "sg:tags":[
        "assurance"
    ],
    "wof:name":"J. Bosmans",
    "wof:placetype":"venue"
},
  "geometry": {"coordinates":[5.6667699814,51.1229019165],"type":"Point"}
}