{
  "type": "Feature",
  "properties": {
    "addr:full":"Sur Les Roches 2 Malmedy Li\u00e8ge 4960",
    "addr:housenumber":"2",
    "addr:postcode":"4960",
    "addr:street":"Sur Les Roches",
    "iso:country":"BE",
    "sg:address":"Sur Les Roches 2",
    "sg:city":"Malmedy",
    "sg:orig_category":"Pain, p\u00e2tisseries and confiseries",
    "sg:phone":"+32 80 33 77 00",
    "sg:postcode":"4960",
    "sg:province":"Li\u00e8ge",
    "wof:name":"Daniel Jacob",
    "wof:placetype":"venue"
},
  "geometry": {"coordinates":[6.0353841782,50.4215087891],"type":"Point"}
}