{
  "type": "Feature",
  "properties": {
    "addr:full":"Avenue Joseph Abras 34 Namur (belgrade) Namur 5001",
    "addr:housenumber":"34",
    "addr:postcode":"5001",
    "addr:street":"Avenue Joseph Abras",
    "iso:country":"BE",
    "sg:address":"Avenue Joseph Abras 34",
    "sg:city":"Namur (belgrade)",
    "sg:classifiers":[
        {
            "category":"Personal",
            "subcategory":"Beauty Salon",
            "type":"Services"
        }
    ],
    "sg:phone":"+32 81 73 07 27",
    "sg:postcode":"5001",
    "sg:province":"Namur",
    "sg:tags":[
        "lady",
        "-",
        "hairdressing"
    ],
    "wof:name":"Elegance",
    "wof:placetype":"venue"
},
  "geometry": {"coordinates":[4.8257050514,50.4722557068],"type":"Point"}
}