{
  "type": "Feature",
  "properties": {
    "iso:country":"BE",
    "sg:address":"Rue Des Combattants 3",
    "sg:city":"Dalhem (warsage)",
    "sg:classifiers":[
        {
            "category":"Military Area",
            "subcategory":"Air Force Base",
            "type":"Public Place"
        }
    ],
    "sg:phone":"+32 4 376 76 27",
    "sg:postcode":"4608",
    "sg:province":"Li\u00e8ge",
    "sg:tags":[
        "herb",
        "-",
        "medicinal"
    ],
    "wof:name":"Walti S",
    "wof:placetype":"venue"
},
  "geometry": {"coordinates":[5.7650651932,50.7360877991],"type":"Point"}
}