{
  "type": "Feature",
  "properties": {
    "iso:country":"BE",
    "sg:address":"Rozenstraat 42",
    "sg:city":"Wevelgem (moorsele)",
    "sg:classifiers":[
        {
            "category":"Real Estate",
            "subcategory":"Architect",
            "type":"Services"
        }
    ],
    "sg:phone":"+32 56 41 48 31",
    "sg:postcode":"8560",
    "sg:province":"West-Vlaanderen",
    "wof:name":"Deleu L",
    "wof:placetype":"venue"
},
  "geometry": {"coordinates":[3.1671030521,50.8417663574],"type":"Point"}
}