{
  "type": "Feature",
  "properties": {
    "iso:country":"BE",
    "sg:address":"Rue Du Tombeu 38",
    "sg:city":"Awans",
    "sg:orig_category":"Landbouwmachines Gh",
    "sg:phone":"+32 4 257 55 34",
    "sg:postcode":"4342",
    "sg:province":"Li\u00e8ge",
    "wof:name":"Philippe Czichosz",
    "wof:placetype":"venue"
},
  "geometry": {"coordinates":[5.4498257637,50.6779747009],"type":"Point"}
}