{
  "type": "Feature",
  "properties": {
    "addr:full":"Adolf Baeyensstraat 21 Gent (sint-amandsberg) Oost-Vlaanderen 9040",
    "addr:housenumber":"21",
    "addr:postcode":"9040",
    "addr:street":"Baeyensstraat",
    "iso:country":"BE",
    "sg:address":"Adolf Baeyensstraat 21",
    "sg:city":"Gent (sint-amandsberg)",
    "sg:classifiers":[
        {
            "category":"Shopping",
            "subcategory":"Crafts & Fabrics",
            "type":"Retail Goods"
        }
    ],
    "sg:phone":"+32 9 228 57 79",
    "sg:postcode":"9040",
    "sg:province":"Oost-Vlaanderen",
    "sg:tags":[
        "plant",
        "flower",
        "artificial"
    ],
    "wof:name":"Kerkhove J",
    "wof:placetype":"venue"
},
  "geometry": {"coordinates":[3.7516961098,51.0567588806],"type":"Point"}
}