{
  "type": "Feature",
  "properties": {
    "iso:country":"BE",
    "sg:address":"Rue Vaudr\u00e9e 65",
    "sg:city":"Li\u00e8ge 1 (angleur)",
    "sg:classifiers":[
        {
            "category":"Professional",
            "subcategory":"Lawyer & Legal Services",
            "type":"Services"
        }
    ],
    "sg:phone":"+32 4 365 00 12",
    "sg:postcode":"4031",
    "sg:province":"Li\u00e8ge",
    "wof:name":"Jaumotte Pierre",
    "wof:placetype":"venue"
},
  "geometry": {"coordinates":[5.5964431763,50.6125221252],"type":"Point"}
}