{
  "type": "Feature",
  "properties": {
    "iso:country":"BE",
    "sg:address":"Kalvariestraat 67",
    "sg:city":"Kortrijk",
    "sg:orig_category":"Kapsalons",
    "sg:phone":"+32 56 20 39 26",
    "sg:postcode":"8510",
    "sg:province":"West-Vlaanderen",
    "wof:name":"Heidi",
    "wof:placetype":"venue"
},
  "geometry": {"coordinates":[3.234844923,50.8020095825],"type":"Point"}
}