{
  "type": "Feature",
  "properties": {
    "addr:full":"Heilige Geestmolenstraat 122 Lokeren Oost-Vlaanderen 9160",
    "addr:housenumber":"122",
    "addr:postcode":"9160",
    "addr:street":"Geestmolenstraat",
    "iso:country":"BE",
    "sg:address":"Heilige Geestmolenstraat 122",
    "sg:city":"Lokeren",
    "sg:classifiers":[
        {
            "category":"Home & Garden",
            "subcategory":"Building Materials",
            "type":"Retail Goods"
        }
    ],
    "sg:phone":"+32 9 349 24 05",
    "sg:postcode":"9160",
    "sg:province":"Oost-Vlaanderen",
    "sg:tags":[
        "window"
    ],
    "wof:name":"Thoen P",
    "wof:placetype":"venue"
},
  "geometry": {"coordinates":[3.9720709324,51.1186180115],"type":"Point"}
}