{
  "type": "Feature",
  "properties": {
    "iso:country":"BE",
    "sg:address":"Lanfraystraat 19",
    "sg:city":"Ixelles",
    "sg:orig_category":"Tuinen",
    "sg:phone":"+32 2 647 94 61",
    "sg:postcode":"1050",
    "sg:province":"Bruxelles-Capitale",
    "wof:name":"Greenexpress",
    "wof:placetype":"venue"
},
  "geometry": {"coordinates":[4.3738980293,50.8255844116],"type":"Point"}
}