{
  "type": "Feature",
  "properties": {
    "iso:country":"BE",
    "sg:address":"Avenue De La Porall\u00c9e 31",
    "sg:city":"Aywaille",
    "sg:orig_category":"Electrom\u00e9nager, t\u00e9l\u00e9visions and radios. Mat\u00e9riel de T\u00e9l\u00e9communication. R\u00e9parations d'appareils \u00e9lect",
    "sg:phone":"+32 4 384 60 30",
    "sg:postcode":"4920",
    "sg:province":"Li\u00e8ge",
    "wof:name":"Maison Leonard",
    "wof:placetype":"venue"
},
  "geometry": {"coordinates":[5.6782069206,50.4738540649],"type":"Point"}
}