{
  "type": "Feature",
  "properties": {
    "addr:full":"Sint-jobplaasts Ukkel Bruxelles-Capitale 1180",
    "addr:postcode":"1180",
    "iso:country":"BE",
    "sg:address":"Sint-jobplaasts",
    "sg:city":"Ukkel",
    "sg:orig_category":"Reisbureaus",
    "sg:phone":"+32 2 375 20 20",
    "sg:postcode":"1180",
    "sg:province":"Bruxelles-Capitale",
    "wof:name":"Nomades",
    "wof:placetype":"venue"
},
  "geometry": {"coordinates":[4.3668498993,50.7945098877],"type":"Point"}
}