{
  "type": "Feature",
  "properties": {
    "addr:full":"Kempenseweg 48 Zutendaal Limburg 3690",
    "addr:housenumber":"48",
    "addr:postcode":"3690",
    "addr:street":"Kempenseweg",
    "iso:country":"BE",
    "sg:address":"Kempenseweg 48",
    "sg:city":"Zutendaal",
    "sg:orig_category":"Dierenartsen",
    "sg:phone":"+32 89 61 20 89",
    "sg:postcode":"3690",
    "sg:province":"Limburg",
    "wof:name":"Clement Lambie",
    "wof:placetype":"venue"
},
  "geometry": {"coordinates":[5.5597629547,50.9456291199],"type":"Point"}
}