{
  "type": "Feature",
  "properties": {
    "iso:country":"BE",
    "sg:address":"Rue Malvoz 16",
    "sg:city":"Charleroi (marcinelle)",
    "sg:classifiers":[
        {
            "category":"Building & Trades",
            "subcategory":"Electrical",
            "type":"Services"
        }
    ],
    "sg:phone":"+32 477 24 46 62",
    "sg:postcode":"6001",
    "sg:province":"Hainaut",
    "sg:tags":[
        "electric",
        "-",
        "housewiring",
        "contractor"
    ],
    "wof:name":"Trovonelli Domenico",
    "wof:placetype":"venue"
},
  "geometry": {"coordinates":[4.4419198036,50.3719100952],"type":"Point"}
}