{
  "type": "Feature",
  "properties": {
    "iso:country":"BE",
    "sg:address":"Rue Henri Pochez 53",
    "sg:city":"Dour",
    "sg:classifiers":[
        {
            "category":"Organizations",
            "subcategory":"Community Association",
            "type":"Services"
        }
    ],
    "sg:phone":"+32 65 65 98 17",
    "sg:postcode":"7370",
    "sg:province":"Hainaut",
    "sg:tags":[
        "organisation"
    ],
    "wof:name":"Maison Des Jeunes M.j.t.",
    "wof:placetype":"venue"
},
  "geometry": {"coordinates":[3.7877941132,50.398021698],"type":"Point"}
}