{
  "type": "Feature",
  "properties": {
    "addr:full":"Meerestraat 40 Langdorp Vlaams-Brabant 3201",
    "addr:housenumber":"40",
    "addr:postcode":"3201",
    "addr:street":"Meerestraat",
    "iso:country":"BE",
    "sg:address":"Meerestraat 40",
    "sg:city":"Langdorp",
    "sg:classifiers":[
        {
            "category":"Building & Trades",
            "subcategory":"Construction",
            "type":"Services"
        }
    ],
    "sg:phone":"+32 16 56 99 35",
    "sg:postcode":"3201",
    "sg:province":"Vlaams-Brabant",
    "sg:tags":[
        "siemens",
        "fujitsu"
    ],
    "wof:name":"Gemic Nv",
    "wof:placetype":"venue"
},
  "geometry": {"coordinates":[4.8867540359,51.015045166],"type":"Point"}
}