{
  "type": "Feature",
  "properties": {
    "iso:country":"BE",
    "sg:address":"Rue Moulin Naveau 3bb",
    "sg:city":"Fleurus",
    "sg:orig_category":"M\u00e9decins and sp\u00e9cialistes",
    "sg:phone":"+32 71 81 50 55",
    "sg:postcode":"6220",
    "sg:province":"Hainaut",
    "wof:name":"C. Ribesse",
    "wof:placetype":"venue"
},
  "geometry": {"coordinates":[4.5562138557,50.4846153259],"type":"Point"}
}