{
  "type": "Feature",
  "properties": {
    "addr:full":"Zeelaan 168 Koksijde West-Vlaanderen 8670",
    "addr:housenumber":"168",
    "addr:postcode":"8670",
    "addr:street":"Zeelaan",
    "iso:country":"BE",
    "sg:address":"Zeelaan 168",
    "sg:city":"Koksijde",
    "sg:classifiers":[
        {
            "category":"Real Estate",
            "subcategory":"Architect",
            "type":"Services"
        }
    ],
    "sg:phone":"+32 58 52 43 10",
    "sg:postcode":"8670",
    "sg:province":"West-Vlaanderen",
    "wof:name":"Depla S",
    "wof:placetype":"venue"
},
  "geometry": {"coordinates":[2.6217749119,51.1159248352],"type":"Point"}
}