{
  "type": "Feature",
  "properties": {
    "iso:country":"BE",
    "sg:address":"Oude Nieuwpoortstraat 10",
    "sg:city":"Middelkerke",
    "sg:orig_category":"Enseignement maternel and primaire",
    "sg:phone":"+32 58 23 56 35",
    "sg:postcode":"8434",
    "sg:province":"West-Vlaanderen",
    "wof:name":"Vrije Basisschool",
    "wof:placetype":"venue"
},
  "geometry": {"coordinates":[2.7557349205,51.1476860046],"type":"Point"}
}