{
  "type": "Feature",
  "properties": {
    "addr:full":"Kalleputstraat 5 Ieper (voormezele) West-Vlaanderen 8902",
    "addr:housenumber":"5",
    "addr:postcode":"8902",
    "addr:street":"Kalleputstraat",
    "iso:country":"BE",
    "sg:address":"Kalleputstraat 5",
    "sg:city":"Ieper (voormezele)",
    "sg:classifiers":[
        {
            "category":"Shopping",
            "subcategory":"Discount & Variety Stores",
            "type":"Retail Goods"
        }
    ],
    "sg:phone":"+32 57 20 66 97",
    "sg:postcode":"8902",
    "sg:province":"West-Vlaanderen",
    "sg:tags":[
        "shop",
        "clearers",
        "curiosity",
        "furniture"
    ],
    "wof:name":"Belpaire P",
    "wof:placetype":"venue"
},
  "geometry": {"coordinates":[2.9219009876,50.8342857361],"type":"Point"}
}