{
  "type": "Feature",
  "properties": {
    "addr:full":"Rue Albert De Latour 71 Bruxelles (schaerbeek) Bruxelles-Capitale 1030",
    "addr:housenumber":"71",
    "addr:postcode":"1030",
    "addr:street":"Rue Albert De Latour",
    "iso:country":"BE",
    "sg:address":"Rue Albert De Latour 71",
    "sg:city":"Bruxelles (schaerbeek)",
    "sg:classifiers":[
        {
            "category":"Real Estate",
            "subcategory":"Architect",
            "type":"Services"
        }
    ],
    "sg:phone":"+32 2 243 07 15",
    "sg:postcode":"1030",
    "sg:province":"Bruxelles-Capitale",
    "wof:name":"Morineau S",
    "wof:placetype":"venue"
},
  "geometry": {"coordinates":[4.3819551468,50.8557128906],"type":"Point"}
}