{
  "type": "Feature",
  "properties": {
    "addr:full":"Kapittelstr 121 Ninove Oost-Vlaanderen 9400",
    "addr:housenumber":"121",
    "addr:postcode":"9400",
    "iso:country":"BE",
    "sg:address":"Kapittelstr 121",
    "sg:city":"Ninove",
    "sg:classifiers":[
        {
            "category":"Manufacturing",
            "subcategory":"Metals",
            "type":"Manufacturing & Wholesale Goods"
        }
    ],
    "sg:phone":"+32 54 33 41 15",
    "sg:postcode":"9400",
    "sg:province":"Oost-Vlaanderen",
    "sg:tags":[
        "metallurgy",
        "metalworking",
        "processing"
    ],
    "wof:name":"Eurocoating Nv",
    "wof:placetype":"venue"
},
  "geometry": {"coordinates":[4.0232000351,50.8349113464],"type":"Point"}
}