{
  "type": "Feature",
  "properties": {
    "addr:full":"Eekhoutstraat 13 Wortegem-petegem (petegem-aan-de-schelde) Oost-Vlaanderen 9790",
    "addr:housenumber":"13",
    "addr:postcode":"9790",
    "addr:street":"Eekhoutstraat;Petegem-Aan-De-Schelde",
    "iso:country":"BE",
    "sg:address":"Eekhoutstraat 13",
    "sg:city":"Wortegem-petegem (petegem-aan-de-schelde)",
    "sg:classifiers":[
        {
            "category":"Transit Center",
            "subcategory":"Freight",
            "type":"Transportation"
        }
    ],
    "sg:phone":"+32 55 30 07 54",
    "sg:postcode":"9790",
    "sg:province":"Oost-Vlaanderen",
    "sg:tags":[
        "import",
        "export",
        "-"
    ],
    "wof:name":"Van Praet",
    "wof:placetype":"venue"
},
  "geometry": {"coordinates":[3.5605399609,50.8405151367],"type":"Point"}
}