{
  "type": "Feature",
  "properties": {
    "addr:full":"Zuiderlaan 1 Asse (zellik) Vlaams-Brabant 1731",
    "addr:housenumber":"1",
    "addr:postcode":"1731",
    "addr:street":"Zuiderlaan",
    "iso:country":"BE",
    "sg:address":"Zuiderlaan 1",
    "sg:city":"Asse (zellik)",
    "sg:classifiers":[
        {
            "category":"Real Estate",
            "subcategory":"Real Estate Services",
            "type":"Services"
        }
    ],
    "sg:phone":"+32 2 466 11 09",
    "sg:postcode":"1731",
    "sg:province":"Vlaams-Brabant",
    "wof:name":"Immo Bea De Ruijter",
    "wof:placetype":"venue"
},
  "geometry": {"coordinates":[4.2822709084,50.878288269],"type":"Point"}
}