{
  "type": "Feature",
  "properties": {
    "addr:full":"Peulisbaan 130 Putte Antwerpen 2580",
    "addr:housenumber":"130",
    "addr:postcode":"2580",
    "addr:street":"Peulisbaan",
    "iso:country":"BE",
    "sg:address":"Peulisbaan 130",
    "sg:city":"Putte",
    "sg:classifiers":[
        {
            "category":"Health Services",
            "subcategory":"Health Practitioner",
            "type":"Services"
        }
    ],
    "sg:phone":"+32 15 75 66 60",
    "sg:postcode":"2580",
    "sg:province":"Antwerpen",
    "sg:tags":[
        "physiotherapist"
    ],
    "wof:name":"Frederickx B",
    "wof:placetype":"venue"
},
  "geometry": {"coordinates":[4.588657856,51.0361785889],"type":"Point"}
}