{
  "type": "Feature",
  "properties": {
    "addr:full":"August Nobelsstraat 7 Sint-niklaas Oost-Vlaanderen 9100",
    "addr:housenumber":"7",
    "addr:postcode":"9100",
    "addr:street":"Nobelsstraat",
    "iso:country":"BE",
    "sg:address":"August Nobelsstraat 7",
    "sg:city":"Sint-niklaas",
    "sg:classifiers":[
        {
            "category":"Professional",
            "subcategory":"Lawyer & Legal Services",
            "type":"Services"
        }
    ],
    "sg:phone":"+32 3 776 97 97",
    "sg:postcode":"9100",
    "sg:province":"Oost-Vlaanderen",
    "wof:name":"Verhofst\u00e9 Raf",
    "wof:placetype":"venue"
},
  "geometry": {"coordinates":[4.145468235,51.1609954834],"type":"Point"}
}