{
  "type": "Feature",
  "properties": {
    "iso:country":"BE",
    "sg:address":"Rue Du Soleil 6",
    "sg:city":"Ronse/renaix",
    "sg:orig_category":"Location de voitures",
    "sg:phone":"+32 55 20 91 41",
    "sg:postcode":"9600",
    "sg:province":"Oost-Vlaanderen",
    "wof:name":"Autolux - Luxauto",
    "wof:placetype":"venue"
},
  "geometry": {"coordinates":[3.5992999077,50.7470397949],"type":"Point"}
}