{
  "type": "Feature",
  "properties": {
    "iso:country":"BE",
    "sg:address":"Gistelsteenweg 90",
    "sg:city":"Jabbeke (varsenare)",
    "sg:orig_category":"Autombile concessionaires",
    "sg:phone":"+32 50 38 84 88",
    "sg:postcode":"8490",
    "sg:province":"West-Vlaanderen",
    "wof:name":"Gar Carr Deprez-claus Bvba",
    "wof:placetype":"venue"
},
  "geometry": {"coordinates":[3.1105320454,51.1793174744],"type":"Point"}
}