{
  "type": "Feature",
  "properties": {
    "addr:full":"Zeedijk 10bf Nieuwpoort West-Vlaanderen 8620",
    "addr:housenumber":"10bf",
    "addr:postcode":"8620",
    "addr:street":"Zeedijk",
    "iso:country":"BE",
    "sg:address":"Zeedijk 10bf",
    "sg:city":"Nieuwpoort",
    "sg:orig_category":"Watersport-, Sport- and Kampeerbenodigdheden Verhuur",
    "sg:phone":"+32 58 23 89 17",
    "sg:postcode":"8620",
    "sg:province":"West-Vlaanderen",
    "wof:name":"Huis Happy",
    "wof:placetype":"venue"
},
  "geometry": {"coordinates":[2.7191970348,51.1504592896],"type":"Point"}
}