{
  "type": "Feature",
  "properties": {
    "addr:full":"Avenue Des Alezans 2 Bruxelles (woluwe-saint-pierre) Bruxelles-Capitale 1150",
    "addr:housenumber":"2",
    "addr:postcode":"1150",
    "addr:street":"Avenue Des Alezans",
    "iso:country":"BE",
    "sg:address":"Avenue Des Alezans 2",
    "sg:city":"Bruxelles (woluwe-saint-pierre)",
    "sg:classifiers":[
        {
            "category":"Professional",
            "subcategory":"Lawyer & Legal Services",
            "type":"Services"
        }
    ],
    "sg:phone":"+32 2 770 81 94",
    "sg:postcode":"1150",
    "sg:province":"Bruxelles-Capitale",
    "wof:name":"Delhaye Agn\u00e8s",
    "wof:placetype":"venue"
},
  "geometry": {"coordinates":[4.4617609978,50.8355636597],"type":"Point"}
}