{
  "type": "Feature",
  "properties": {
    "iso:country":"BE",
    "sg:address":"Tuinstraat 5a",
    "sg:city":"Melle",
    "sg:orig_category":"Bloemen and planten Gh",
    "sg:phone":"+32 9 230 98 61",
    "sg:postcode":"9090",
    "sg:province":"Oost-Vlaanderen",
    "wof:name":"Schuerbeke R",
    "wof:placetype":"venue"
},
  "geometry": {"coordinates":[3.7786550522,51.0187339783],"type":"Point"}
}