{
  "type": "Feature",
  "properties": {
    "addr:full":"Berendrechtstraat 92 Antwerpen Antwerpen 2020",
    "addr:housenumber":"92",
    "addr:postcode":"2020",
    "addr:street":"Berendrechtstraat",
    "iso:country":"BE",
    "sg:address":"Berendrechtstraat 92",
    "sg:city":"Antwerpen",
    "sg:classifiers":[
        {
            "category":"Food & Beverages",
            "subcategory":"Groceries & Convenience Stores",
            "type":"Retail Goods"
        }
    ],
    "sg:phone":"+32 3 238 02 48",
    "sg:postcode":"2020",
    "sg:province":"Antwerpen",
    "sg:tags":[
        "grocer"
    ],
    "wof:name":"Ertexy Empex",
    "wof:placetype":"venue"
},
  "geometry": {"coordinates":[4.3848280907,51.1863059998],"type":"Point"}
}