{
  "type": "Feature",
  "properties": {
    "addr:full":"Hoogboomsteenweg 113 Kapellen Antwerpen 2950",
    "addr:housenumber":"113",
    "addr:postcode":"2950",
    "addr:street":"Hoogboomsteenweg",
    "iso:country":"BE",
    "sg:address":"Hoogboomsteenweg 113",
    "sg:city":"Kapellen",
    "sg:orig_category":"Enseignement maternel and primaire",
    "sg:phone":"+32 3 664 26 72",
    "sg:postcode":"2950",
    "sg:province":"Antwerpen",
    "wof:name":"Basisschool De Platanen",
    "wof:placetype":"venue"
},
  "geometry": {"coordinates":[4.4512667656,51.3118934631],"type":"Point"}
}