{
  "type": "Feature",
  "properties": {
    "addr:full":"Broesveldstraat 1ba Neerpelt Limburg 3910",
    "addr:postcode":"3910",
    "addr:street":"Broesveldstraat",
    "iso:country":"BE",
    "sg:address":"Broesveldstraat 1ba",
    "sg:city":"Neerpelt",
    "sg:orig_category":"Banques and organismes de cr\u00e9dit",
    "sg:phone":"+32 11 64 10 02",
    "sg:postcode":"3910",
    "sg:province":"Limburg",
    "wof:name":"Fortis",
    "wof:placetype":"venue"
},
  "geometry": {"coordinates":[5.4300260544,51.2289276123],"type":"Point"}
}