{
  "type": "Feature",
  "properties": {
    "addr:full":"Hendrik Deberghstraat 18 Vleteren (oostvleteren) West-Vlaanderen 8640",
    "addr:housenumber":"18",
    "addr:postcode":"8640",
    "addr:street":"Deberghstraat",
    "iso:country":"BE",
    "sg:address":"Hendrik Deberghstraat 18",
    "sg:city":"Vleteren (oostvleteren)",
    "sg:classifiers":[
        {
            "category":"Health Services",
            "subcategory":"Nursing And Care Facility",
            "type":"Services"
        }
    ],
    "sg:phone":"+32 57 40 12 00",
    "sg:postcode":"8640",
    "sg:province":"West-Vlaanderen",
    "sg:tags":[
        "home"
    ],
    "wof:name":"De Poorter Wim",
    "wof:placetype":"venue"
},
  "geometry": {"coordinates":[2.7396650314,50.9317703247],"type":"Point"}
}