{
  "type": "Feature",
  "properties": {
    "addr:full":"Avenue D\u00b4hyon 99 Mons Hainaut 7000",
    "addr:housenumber":"99",
    "addr:postcode":"7000",
    "addr:street":"Avenue D\u00b4Hyon;Hainaut",
    "iso:country":"BE",
    "sg:address":"Avenue D\u00b4hyon 99",
    "sg:city":"Mons",
    "sg:orig_category":"Medische apparatuur, orthopedische artikelen and prothesen Fab",
    "sg:phone":"+32 65 33 74 50",
    "sg:postcode":"7000",
    "sg:province":"Hainaut",
    "wof:name":"Jean-p. Duquesnoy",
    "wof:placetype":"venue"
},
  "geometry": {"coordinates":[3.9553558826,50.4447937012],"type":"Point"}
}