{
  "type": "Feature",
  "properties": {
    "iso:country":"BE",
    "sg:address":"Kapelaan Staslaan 5",
    "sg:city":"Wommelgem",
    "sg:orig_category":"Gestion de media publicitaires",
    "sg:phone":"+32 3 320 94 44",
    "sg:postcode":"2160",
    "sg:province":"Antwerpen",
    "wof:name":"Publibak",
    "wof:placetype":"venue"
},
  "geometry": {"coordinates":[4.5020918846,51.1971549988],"type":"Point"}
}