{
  "type": "Feature",
  "properties": {
    "addr:full":"Grasdreef 5 Sint-michiels-brugge West-Vlaanderen 8200",
    "addr:housenumber":"5",
    "addr:postcode":"8200",
    "addr:street":"Grasdreef;West-Vlaanderen",
    "iso:country":"BE",
    "sg:address":"Grasdreef 5",
    "sg:city":"Sint-michiels-brugge",
    "sg:orig_category":"Diverse juridische dienstverlening Royal Canin",
    "sg:phone":"+32 50 39 60 32",
    "sg:postcode":"8200",
    "sg:province":"West-Vlaanderen",
    "wof:name":"Bvba Stock Allemeersch",
    "wof:placetype":"venue"
},
  "geometry": {"coordinates":[3.197947979,51.1874885559],"type":"Point"}
}