{
  "type": "Feature",
  "properties": {
    "addr:full":"Karel Janssenslaan 9 Oostende West-Vlaanderen 8400",
    "addr:housenumber":"9",
    "addr:postcode":"8400",
    "addr:street":"Karel Janssenslaan",
    "iso:country":"BE",
    "sg:address":"Karel Janssenslaan 9",
    "sg:city":"Oostende",
    "sg:orig_category":"M\u00e9decins and sp\u00e9cialistes",
    "sg:phone":"+32 59 80 04 74",
    "sg:postcode":"8400",
    "sg:province":"West-Vlaanderen",
    "wof:name":"Kim Khuu",
    "wof:placetype":"venue"
},
  "geometry": {"coordinates":[2.9138379097,51.2295684814],"type":"Point"}
}