{
  "type": "Feature",
  "properties": {
    "addr:full":"Dorp 7 Nazareth Oost-Vlaanderen 9810",
    "addr:housenumber":"7",
    "addr:postcode":"9810",
    "addr:street":"Dorp",
    "iso:country":"BE",
    "sg:address":"Dorp 7",
    "sg:city":"Nazareth",
    "sg:orig_category":"Banken and kredietinstellingen",
    "sg:phone":"+32 9 385 31 40",
    "sg:postcode":"9810",
    "sg:province":"Oost-Vlaanderen",
    "wof:name":"Ippa",
    "wof:placetype":"venue"
},
  "geometry": {"coordinates":[3.5978860855,50.9594917297],"type":"Point"}
}