{
  "type": "Feature",
  "properties": {
    "iso:country":"BE",
    "sg:address":"Oudekapellestraat 7",
    "sg:city":"Diksmuide",
    "sg:orig_category":"Eleveurs de bovins",
    "sg:phone":"+32 51 50 02 99",
    "sg:postcode":"8600",
    "sg:province":"West-Vlaanderen",
    "wof:name":"Henri Crul",
    "wof:placetype":"venue"
},
  "geometry": {"coordinates":[2.8246901035,51.0308113098],"type":"Point"}
}