{
  "type": "Feature",
  "properties": {
    "addr:full":"Ellestraat 2 Herent Vlaams-Brabant 3020",
    "addr:housenumber":"2",
    "addr:postcode":"3020",
    "addr:street":"Ellestraat",
    "iso:country":"BE",
    "sg:address":"Ellestraat 2",
    "sg:city":"Herent",
    "sg:orig_category":"Groententeelt",
    "sg:phone":"+32 16 48 87 52",
    "sg:postcode":"3020",
    "sg:province":"Vlaams-Brabant",
    "wof:name":"Corneel Goossens",
    "wof:placetype":"venue"
},
  "geometry": {"coordinates":[4.6749200821,50.9079055786],"type":"Point"}
}