{
  "type": "Feature",
  "properties": {
    "addr:full":"Verbindingsstraat 11 Tongeren Limburg 3700",
    "addr:housenumber":"11",
    "addr:postcode":"3700",
    "addr:street":"Verbindingsstraat",
    "iso:country":"BE",
    "sg:address":"Verbindingsstraat 11",
    "sg:city":"Tongeren",
    "sg:orig_category":"Dansscholen Fitnesscentra Sportcentra Sportclubs",
    "sg:phone":"+32 12 26 14 02",
    "sg:postcode":"3700",
    "sg:province":"Limburg",
    "wof:name":"New Coast Club Bernard",
    "wof:placetype":"venue"
},
  "geometry": {"coordinates":[5.469233036,50.7867774963],"type":"Point"}
}