{
  "type": "Feature",
  "properties": {
    "addr:full":"A. Vandenpeereboomplein 35 Ieper West-Vlaanderen 8900",
    "addr:housenumber":"35",
    "addr:postcode":"8900",
    "addr:street":"Vandenpeereboomplein",
    "iso:country":"BE",
    "sg:address":"A. Vandenpeereboomplein 35",
    "sg:city":"Ieper",
    "sg:orig_category":"Kapsalons",
    "sg:phone":"+32 57 20 12 06",
    "sg:postcode":"8900",
    "sg:province":"West-Vlaanderen",
    "wof:name":"Severine",
    "wof:placetype":"venue"
},
  "geometry": {"coordinates":[2.8833959103,50.8518867493],"type":"Point"}
}