{
  "type": "Feature",
  "properties": {
    "iso:country":"BE",
    "sg:address":"Parc Scientifique",
    "sg:city":"Mons",
    "sg:classifiers":[
        {
            "category":"Professional",
            "subcategory":"Engineering",
            "type":"Services"
        }
    ],
    "sg:phone":"+32 65 34 60 00",
    "sg:postcode":"7000",
    "sg:province":"Hainaut",
    "sg:tags":[
        "civil",
        "offices-"
    ],
    "wof:name":"Geopro",
    "wof:placetype":"venue"
},
  "geometry": {"coordinates":[3.9522509575,50.4547271729],"type":"Point"}
}