{
  "type": "Feature",
  "properties": {
    "iso:country":"BE",
    "sg:address":"Pelikaanstraat 104",
    "sg:city":"Antwerpen",
    "sg:orig_category":"Bijoux Fab. Horloges, m\u00e9taux pr\u00e9cieux and bijoux Gr",
    "sg:phone":"+32 3 227 15 24",
    "sg:postcode":"2018",
    "sg:province":"Antwerpen",
    "wof:name":"Geri",
    "wof:placetype":"venue"
},
  "geometry": {"coordinates":[4.4205679893,51.2136116028],"type":"Point"}
}