{
  "type": "Feature",
  "properties": {
    "addr:full":"Rue Voie Des Vaux 149 Saint-nicolas (montegn\u00e9e) Li\u00e8ge 4420",
    "addr:housenumber":"149",
    "addr:postcode":"4420",
    "addr:street":"Rue Voie Des Vaux;Montegne\u0301E",
    "iso:country":"BE",
    "sg:address":"Rue Voie Des Vaux 149",
    "sg:city":"Saint-nicolas (montegn\u00e9e)",
    "sg:classifiers":[
        {
            "category":"Building & Trades",
            "subcategory":"Construction",
            "type":"Services"
        }
    ],
    "sg:phone":"+32 496 50 70 76",
    "sg:postcode":"4420",
    "sg:province":"Li\u00e8ge",
    "sg:tags":[
        "duct",
        "underground",
        "ducting"
    ],
    "wof:name":"Lns Gestions",
    "wof:placetype":"venue"
},
  "geometry": {"coordinates":[5.5119180679,50.635887146],"type":"Point"}
}