{
  "type": "Feature",
  "properties": {
    "addr:full":"Rue Laoureux 14 Verviers Li\u00e8ge 4800",
    "addr:housenumber":"14",
    "addr:postcode":"4800",
    "addr:street":"Rue Laoureux",
    "iso:country":"BE",
    "sg:address":"Rue Laoureux 14",
    "sg:city":"Verviers",
    "sg:orig_category":"V\u00e9t\u00e9rinaires",
    "sg:phone":"+32 87 33 29 60",
    "sg:postcode":"4800",
    "sg:province":"Li\u00e8ge",
    "wof:name":"Roger Micha",
    "wof:placetype":"venue"
},
  "geometry": {"coordinates":[5.8639340401,50.5922851562],"type":"Point"}
}