{
  "type": "Feature",
  "properties": {
    "addr:full":"Champs 772 Bertogne Luxembourg 6688",
    "addr:housenumber":"772",
    "addr:postcode":"6688",
    "iso:country":"BE",
    "sg:address":"Champs 772",
    "sg:city":"Bertogne",
    "sg:orig_category":"Eleveurs de bovins",
    "sg:phone":"+32 61 21 42 05",
    "sg:postcode":"6688",
    "sg:province":"Luxembourg",
    "wof:name":"Rene Lockman",
    "wof:placetype":"venue"
},
  "geometry": {"coordinates":[5.6690850258,50.0382194519],"type":"Point"}
}