{
  "type": "Feature",
  "properties": {
    "addr:full":"Boechoutsesteenweg 137b Hove Antwerpen 2540",
    "addr:housenumber":"137b",
    "addr:postcode":"2540",
    "addr:street":"Boechoutsesteenweg",
    "iso:country":"BE",
    "sg:address":"Boechoutsesteenweg 137b",
    "sg:city":"Hove",
    "sg:classifiers":[
        {
            "category":"Autos & Motor Vehicles",
            "subcategory":"Automobile Sales",
            "type":"Retail Goods"
        }
    ],
    "sg:phone":"+32 3 454 28 27",
    "sg:postcode":"2540",
    "sg:province":"Antwerpen",
    "sg:tags":[
        "car",
        "used",
        "-"
    ],
    "wof:name":"Projimmo Bvba",
    "wof:placetype":"venue"
},
  "geometry": {"coordinates":[4.4796800613,51.156162262],"type":"Point"}
}