{
  "type": "Feature",
  "properties": {
    "addr:full":"Avenue De L'universit\u00c9 8 Elsene/ixelles Bruxelles-Capitale 1050",
    "addr:housenumber":"8",
    "addr:postcode":"1050",
    "addr:street":"Avenue De L'Universite \u0301",
    "iso:country":"BE",
    "sg:address":"Avenue De L'universit\u00c9 8",
    "sg:city":"Elsene/ixelles",
    "sg:orig_category":"Blanchisseries and teintureries",
    "sg:phone":"+32 2 649 40 04",
    "sg:postcode":"1050",
    "sg:province":"Bruxelles-Capitale",
    "wof:name":"H.s. Dry Cleaning",
    "wof:placetype":"venue"
},
  "geometry": {"coordinates":[4.3893399239,50.8153381348],"type":"Point"}
}