{
  "type": "Feature",
  "properties": {
    "addr:full":"Juliaan Devriendtstraat 1 Overpelt Limburg 3900",
    "addr:housenumber":"1",
    "addr:postcode":"3900",
    "addr:street":"Devriendtstraat",
    "iso:country":"BE",
    "sg:address":"Juliaan Devriendtstraat 1",
    "sg:city":"Overpelt",
    "sg:orig_category":"Maatkleding Fab",
    "sg:phone":"+32 11 66 55 80",
    "sg:postcode":"3900",
    "sg:province":"Limburg",
    "wof:name":"Fa. Cari",
    "wof:placetype":"venue"
},
  "geometry": {"coordinates":[5.4245128632,51.2097358704],"type":"Point"}
}