{
  "type": "Feature",
  "properties": {
    "addr:full":"Rue Entre-deux-portes 41 Huy Li\u00e8ge 4500",
    "addr:housenumber":"41",
    "addr:postcode":"4500",
    "addr:street":"Rue Entre-Deux-Portes",
    "iso:country":"BE",
    "sg:address":"Rue Entre-deux-portes 41",
    "sg:city":"Huy",
    "sg:orig_category":"Immobili\u00ebnkantoren",
    "sg:phone":"+32 85 23 52 09",
    "sg:postcode":"4500",
    "sg:province":"Li\u00e8ge",
    "wof:name":"Innover Home",
    "wof:placetype":"venue"
},
  "geometry": {"coordinates":[5.2306399345,50.524974823],"type":"Point"}
}