{
  "type": "Feature",
  "properties": {
    "iso:country":"BE",
    "sg:address":"Stee 22",
    "sg:city":"Sint-laureins",
    "sg:orig_category":"Electrom\u00e9nager, t\u00e9l\u00e9visions and radios",
    "sg:phone":"+32 9 379 82 69",
    "sg:postcode":"9988",
    "sg:province":"Oost-Vlaanderen",
    "wof:name":"Cyriel De Vos",
    "wof:placetype":"venue"
},
  "geometry": {"coordinates":[3.6265199184,51.2763786316],"type":"Point"}
}