{
  "type": "Feature",
  "properties": {
    "iso:country":"BE",
    "sg:address":"Kerkeneinde 5",
    "sg:city":"Hemiksem",
    "sg:orig_category":"Artsen and specialisten",
    "sg:phone":"+32 3 887 32 77",
    "sg:postcode":"2620",
    "sg:province":"Antwerpen",
    "wof:name":"J. Van Boeckhout",
    "wof:placetype":"venue"
},
  "geometry": {"coordinates":[4.3545851707,51.1368980408],"type":"Point"}
}