{
  "type": "Feature",
  "properties": {
    "addr:full":"Kettingbrugweg 34 Box 1 Bocholt (kaulille) Limburg 3950",
    "addr:housenumber":"34;1",
    "addr:postcode":"3950",
    "addr:street":"Kettingbrugweg;Box",
    "iso:country":"BE",
    "sg:address":"Kettingbrugweg 34 Box 1",
    "sg:city":"Bocholt (kaulille)",
    "sg:classifiers":[
        {
            "category":"Wholesale",
            "subcategory":"Beer",
            "type":"Manufacturing & Wholesale Goods"
        }
    ],
    "sg:phone":"+32 11 61 18 00",
    "sg:postcode":"3950",
    "sg:province":"Limburg",
    "sg:tags":[
        "ale",
        "-"
    ],
    "wof:name":"Kempo Nv",
    "wof:placetype":"venue"
},
  "geometry": {"coordinates":[5.5217380524,51.2119522095],"type":"Point"}
}