{
  "type": "Feature",
  "properties": {
    "addr:full":"Hingenesteenweg 3 Bornem Antwerpen 2880",
    "addr:housenumber":"3",
    "addr:postcode":"2880",
    "addr:street":"Hingenesteenweg",
    "iso:country":"BE",
    "sg:address":"Hingenesteenweg 3",
    "sg:city":"Bornem",
    "sg:orig_category":"V\u00e9t\u00e9rinaires",
    "sg:phone":"+32 3 889 41 98",
    "sg:postcode":"2880",
    "sg:province":"Antwerpen",
    "wof:name":"Daniel Dhondt",
    "wof:placetype":"venue"
},
  "geometry": {"coordinates":[4.2411408424,51.0995674133],"type":"Point"}
}