{
  "type": "Feature",
  "properties": {
    "addr:full":"Square Des Combattants 17 Bruxelles Bruxelles-Capitale 1020",
    "addr:housenumber":"17",
    "addr:postcode":"1020",
    "addr:street":"Square Des Combattants",
    "iso:country":"BE",
    "sg:address":"Square Des Combattants 17",
    "sg:city":"Bruxelles",
    "sg:classifiers":[
        {
            "category":"Health Services",
            "subcategory":"Dentist",
            "type":"Services"
        }
    ],
    "sg:phone":"+32 2 428 34 55",
    "sg:postcode":"1020",
    "sg:province":"Bruxelles-Capitale",
    "wof:name":"Fran\u00e7ois Christine",
    "wof:placetype":"venue"
},
  "geometry": {"coordinates":[4.3485059738,50.8770866394],"type":"Point"}
}