{
  "type": "Feature",
  "properties": {
    "iso:country":"BE",
    "sg:address":"Avenue Chazal 194",
    "sg:city":"Bruxelles",
    "sg:orig_category":"Agences immobili\u00e8res. Construction de maisons",
    "sg:phone":"+32 2 241 71 02",
    "sg:postcode":"1030",
    "sg:province":"Bruxelles-Capitale",
    "wof:name":"Home & Away",
    "wof:placetype":"venue"
},
  "geometry": {"coordinates":[4.3908991814,50.8588142395],"type":"Point"}
}