{
  "type": "Feature",
  "properties": {
    "addr:full":"Rue Des Combattants 116 La Hulpe Brabant Wallon 1310",
    "addr:housenumber":"116",
    "addr:postcode":"1310",
    "addr:street":"Rue Des Combattants",
    "iso:country":"BE",
    "sg:address":"Rue Des Combattants 116",
    "sg:city":"La Hulpe",
    "sg:classifiers":[
        {
            "category":"Health Services",
            "subcategory":"Dentist",
            "type":"Services"
        }
    ],
    "sg:phone":"+32 2 654 05 42",
    "sg:postcode":"1310",
    "sg:province":"Brabant Wallon",
    "wof:name":"De Clerck P",
    "wof:placetype":"venue"
},
  "geometry": {"coordinates":[4.4848771095,50.730846405],"type":"Point"}
}