{
  "type": "Feature",
  "properties": {
    "iso:country":"BE",
    "sg:address":"Durmakker 6",
    "sg:city":"Evergem",
    "sg:orig_category":"Shingles, Wood Shingles, Roof Shingles, Wall Shingles",
    "sg:phone":"+32 9 258 07 00",
    "sg:postcode":"9940",
    "sg:province":"Oost-Vlaanderen",
    "wof:name":"Hanssens Spanten Nv",
    "wof:placetype":"venue"
},
  "geometry": {"coordinates":[3.6980860233,51.1030349731],"type":"Point"}
}