{
  "type": "Feature",
  "properties": {
    "addr:full":"Raubrandplein 3a Halen Limburg 3545",
    "addr:housenumber":"3a",
    "addr:postcode":"3545",
    "addr:street":"Raubrandplein",
    "iso:country":"BE",
    "sg:address":"Raubrandplein 3a",
    "sg:city":"Halen",
    "sg:orig_category":"Notaires",
    "sg:phone":"+32 13 44 10 94",
    "sg:postcode":"3545",
    "sg:province":"Limburg",
    "wof:name":"Baudouin Verelst",
    "wof:placetype":"venue"
},
  "geometry": {"coordinates":[5.1156220436,50.9471588135],"type":"Point"}
}