{
  "type": "Feature",
  "properties": {
    "addr:full":"Vervierser Stasse 109 Eupen Li\u00e8ge 4700",
    "addr:housenumber":"109",
    "addr:postcode":"4700",
    "addr:street":"Vervierser Stasse",
    "iso:country":"BE",
    "sg:address":"Vervierser Stasse 109",
    "sg:city":"Eupen",
    "sg:orig_category":"Loodgieterij, verwarming and sanitaire installaties",
    "sg:phone":"+32 87 55 37 76",
    "sg:postcode":"4700",
    "sg:province":"Li\u00e8ge",
    "wof:name":"Amg Belgium",
    "wof:placetype":"venue"
},
  "geometry": {"coordinates":[6.0155520439,50.6323051453],"type":"Point"}
}