{
  "type": "Feature",
  "properties": {
    "iso:country":"BE",
    "sg:address":"Markt 29",
    "sg:city":"Heuvelland (nieuwkerke)",
    "sg:classifiers":[
        {
            "category":"Shopping",
            "subcategory":"Shoes",
            "type":"Retail Goods"
        }
    ],
    "sg:phone":"+32 57 44 49 62",
    "sg:postcode":"8950",
    "sg:province":"West-Vlaanderen",
    "sg:tags":[
        "slipper",
        "-"
    ],
    "wof:name":"Goudeseune M",
    "wof:placetype":"venue"
},
  "geometry": {"coordinates":[2.8258678913,50.7464599609],"type":"Point"}
}