{
  "type": "Feature",
  "properties": {
    "iso:country":"BE",
    "sg:address":"Rue Frappe Cul 19",
    "sg:city":"Profondeville (lustin)",
    "sg:classifiers":[
        {
            "category":"Professional",
            "subcategory":"Lawyer & Legal Services",
            "type":"Services"
        }
    ],
    "sg:phone":"+32 81 41 32 82",
    "sg:postcode":"5170",
    "sg:province":"Namur",
    "wof:name":"Hubert Christophe",
    "wof:placetype":"venue"
},
  "geometry": {"coordinates":[4.8735861778,50.3632240295],"type":"Point"}
}