{
  "type": "Feature",
  "properties": {
    "addr:full":"Borchtstraat 32b2 Mechelen Antwerpen 2800",
    "addr:housenumber":"32b2",
    "addr:postcode":"2800",
    "addr:street":"Borchtstraat",
    "iso:country":"BE",
    "sg:address":"Borchtstraat 32b2",
    "sg:city":"Mechelen",
    "sg:orig_category":"Activit\u00e9s diverses d'imprimerie. D\u00e9corateurs d'int\u00e9rieur",
    "sg:phone":"+32 15 55 65 46",
    "sg:postcode":"2800",
    "sg:province":"Antwerpen",
    "wof:name":"Katleen Bosteels",
    "wof:placetype":"venue"
},
  "geometry": {"coordinates":[4.4941048622,51.0301513672],"type":"Point"}
}