{
  "type": "Feature",
  "properties": {
    "addr:full":"Excelsiorlaan 36-38 Zaventem Vlaams-Brabant 1930",
    "addr:housenumber":"36-38",
    "addr:postcode":"1930",
    "addr:street":"Excelsiorlaan",
    "iso:country":"BE",
    "sg:address":"Excelsiorlaan 36-38",
    "sg:city":"Zaventem",
    "sg:orig_category":"Diverse informatica-activiteiten Informaticaconsulenten Microsoft Software ontwikkeling and ontwerp",
    "sg:phone":"+32 2 720 21 45",
    "sg:postcode":"1930",
    "sg:province":"Vlaams-Brabant",
    "wof:name":"Smp",
    "wof:placetype":"venue"
},
  "geometry": {"coordinates":[4.4564762115,50.8838691711],"type":"Point"}
}