{
  "type": "Feature",
  "properties": {
    "addr:full":"Meersstraat 10-29l Kortrijk West-Vlaanderen 8500",
    "addr:housenumber":"10-29l",
    "addr:postcode":"8500",
    "addr:street":"Meersstraat",
    "iso:country":"BE",
    "sg:address":"Meersstraat 10-29l",
    "sg:city":"Kortrijk",
    "sg:classifiers":[
        {
            "category":"Social Services",
            "subcategory":"Retirement Home",
            "type":"Services"
        }
    ],
    "sg:phone":"+32 56 24 52 71",
    "sg:postcode":"8500",
    "sg:province":"West-Vlaanderen",
    "sg:tags":[
        "residence"
    ],
    "wof:name":"Guido Gezelle Serviceflats",
    "wof:placetype":"venue"
},
  "geometry": {"coordinates":[3.255975008,50.828338623],"type":"Point"}
}