{
  "type": "Feature",
  "properties": {
    "iso:country":"BE",
    "sg:address":"Chemin Du Chenois 32",
    "sg:city":"Rebecq (quenast)",
    "sg:classifiers":[
        {
            "category":"Personal",
            "subcategory":"Nail Salon",
            "type":"Services"
        }
    ],
    "sg:phone":"+32 67 67 03 25",
    "sg:postcode":"1430",
    "sg:province":"Brabant Wallon",
    "sg:tags":[
        "pedicure"
    ],
    "wof:name":"Brenard A",
    "wof:placetype":"venue"
},
  "geometry": {"coordinates":[4.1602721214,50.6740036011],"type":"Point"}
}