{
  "type": "Feature",
  "properties": {
    "iso:country":"BE",
    "sg:address":"Vindictivelaan 25",
    "sg:city":"Oostende",
    "sg:classifiers":[
        {
            "category":"Insurance",
            "subcategory":"Life Insurance",
            "type":"Services"
        }
    ],
    "sg:phone":"+32 59 70 05 30",
    "sg:postcode":"8400",
    "sg:province":"West-Vlaanderen",
    "sg:tags":[
        "assurance"
    ],
    "wof:name":"Ostend Assur",
    "wof:placetype":"venue"
},
  "geometry": {"coordinates":[2.9230101109,51.22864151],"type":"Point"}
}