{
  "type": "Feature",
  "properties": {
    "iso:country":"BE",
    "sg:address":"Rue Dethy 17bc",
    "sg:city":"Sint-gillis/saint-gilles",
    "sg:orig_category":"Boucheries",
    "sg:phone":"+32 2 537 84 91",
    "sg:postcode":"1060",
    "sg:province":"Bruxelles-Capitale",
    "wof:name":"Mostafa Touil",
    "wof:placetype":"venue"
},
  "geometry": {"coordinates":[4.3433279991,50.8290863037],"type":"Point"}
}