{
  "type": "Feature",
  "properties": {
    "addr:full":"Chauss\u00c9e De Wavre 225 Gembloux Namur 5030",
    "addr:housenumber":"225",
    "addr:postcode":"5030",
    "addr:street":"Chausse\u0301E De Wavre;Namur",
    "iso:country":"BE",
    "sg:address":"Chauss\u00c9e De Wavre 225",
    "sg:city":"Gembloux",
    "sg:orig_category":"Quincailleries. Meubles D\u00e9taillants, Am\u00e9nagement de B\u00e2timents et de Cuisines",
    "sg:phone":"+32 81 61 18 22",
    "sg:postcode":"5030",
    "sg:province":"Namur",
    "wof:name":"Meubles St.eloi",
    "wof:placetype":"venue"
},
  "geometry": {"coordinates":[4.6864800453,50.5800285339],"type":"Point"}
}