{
  "type": "Feature",
  "properties": {
    "addr:full":"Kachtemsestraat 330 Roeselare West-Vlaanderen 8800",
    "addr:housenumber":"330",
    "addr:postcode":"8800",
    "addr:street":"Kachtemsestraat",
    "iso:country":"BE",
    "sg:address":"Kachtemsestraat 330",
    "sg:city":"Roeselare",
    "sg:classifiers":[
        {
            "category":"Freight",
            "type":"Transportation"
        }
    ],
    "sg:phone":"+32 51 22 33 34",
    "sg:postcode":"8800",
    "sg:province":"West-Vlaanderen",
    "sg:tags":[
        "-",
        "transport"
    ],
    "wof:name":"Stercus",
    "wof:placetype":"venue"
},
  "geometry": {"coordinates":[3.1697609425,50.9448547363],"type":"Point"}
}