{
  "type": "Feature",
  "properties": {
    "iso:country":"BE",
    "sg:address":"Avenue Reine Astrid 175-177",
    "sg:city":"Wemmel",
    "sg:orig_category":"Autombile concessionaires",
    "sg:phone":"+32 2 721 11 89",
    "sg:postcode":"1780",
    "sg:province":"Vlaams-Brabant",
    "wof:name":"Lexus Brussels",
    "wof:placetype":"venue"
},
  "geometry": {"coordinates":[4.3168101311,50.8954849243],"type":"Point"}
}