{
  "type": "Feature",
  "properties": {
    "iso:country":"BE",
    "sg:address":"Morgenster 16",
    "sg:city":"Kuurne",
    "sg:orig_category":"Slagers",
    "sg:phone":"+32 56 37 03 16",
    "sg:postcode":"8520",
    "sg:province":"West-Vlaanderen",
    "wof:name":"C. Deylgat",
    "wof:placetype":"venue"
},
  "geometry": {"coordinates":[3.2664139271,50.8636512756],"type":"Point"}
}