{
  "type": "Feature",
  "properties": {
    "addr:full":"Aalststraat 4 Oudenaarde Oost-Vlaanderen 9700",
    "addr:housenumber":"4",
    "addr:postcode":"9700",
    "addr:street":"Aalststraat",
    "iso:country":"BE",
    "sg:address":"Aalststraat 4",
    "sg:city":"Oudenaarde",
    "sg:orig_category":"Mat\u00e9riel m\u00e9dical and orthop\u00e9dique and proth\u00e8ses Fab",
    "sg:phone":"+32 55 31 68 70",
    "sg:postcode":"9700",
    "sg:province":"Oost-Vlaanderen",
    "wof:name":"Firmin Drieghe",
    "wof:placetype":"venue"
},
  "geometry": {"coordinates":[3.610268116,50.8364372253],"type":"Point"}
}