{
  "type": "Feature",
  "properties": {
    "iso:country":"BE",
    "sg:address":"Karrenbergstraat 1",
    "sg:city":"Hoeilaart",
    "sg:orig_category":"Agences de publicit\u00e9",
    "sg:phone":"+32 2 657 59 58",
    "sg:postcode":"1560",
    "sg:province":"Vlaams-Brabant",
    "wof:name":"De Brabander Advertising",
    "wof:placetype":"venue"
},
  "geometry": {"coordinates":[4.4577651024,50.7685966492],"type":"Point"}
}