{
  "type": "Feature",
  "properties": {
    "iso:country":"BE",
    "sg:address":"Aalst-dorp 5-1",
    "sg:city":"Sint-truiden (aalst)",
    "sg:classifiers":[
        {
            "category":"Professional",
            "subcategory":"Art Services",
            "type":"Services"
        }
    ],
    "sg:phone":"+32 11 70 28 90",
    "sg:postcode":"3800",
    "sg:province":"Limburg",
    "sg:tags":[
        "graphic",
        "designer"
    ],
    "wof:name":"Ideart\u00e9",
    "wof:placetype":"venue"
},
  "geometry": {"coordinates":[5.1913280487,50.8091468811],"type":"Point"}
}