{
  "type": "Feature",
  "properties": {
    "addr:full":"Brugstraat 24 Ieper (boezinge) West-Vlaanderen 8904",
    "addr:housenumber":"24",
    "addr:postcode":"8904",
    "addr:street":"Brugstraat",
    "iso:country":"BE",
    "sg:address":"Brugstraat 24",
    "sg:city":"Ieper (boezinge)",
    "sg:classifiers":[
        {
            "category":"Personal",
            "subcategory":"Beauty Salon",
            "type":"Services"
        }
    ],
    "sg:phone":"+32 57 21 23 59",
    "sg:postcode":"8904",
    "sg:province":"West-Vlaanderen",
    "sg:tags":[
        "lady",
        "-",
        "hairdressing"
    ],
    "wof:name":"Charlotte",
    "wof:placetype":"venue"
},
  "geometry": {"coordinates":[2.8607261181,50.8945198059],"type":"Point"}
}