{
  "type": "Feature",
  "properties": {
    "addr:full":"Rue Ernest Solvay 352 Li\u00c8ge Li\u00e8ge 4000",
    "addr:housenumber":"352",
    "addr:postcode":"4000",
    "addr:street":"Rue Ernest Solvay",
    "iso:country":"BE",
    "sg:address":"Rue Ernest Solvay 352",
    "sg:city":"Li\u00c8ge",
    "sg:classifiers":[
        {
            "category":"Fast Food",
            "type":"Food & Drink"
        }
    ],
    "sg:phone":"+32 4 233 04 43",
    "sg:postcode":"4000",
    "sg:province":"Li\u00e8ge",
    "sg:tags":[
        "meeneem",
        "restaurant"
    ],
    "wof:name":"La Bonne Fourchette",
    "wof:placetype":"venue"
},
  "geometry": {"coordinates":[5.5379800797,50.6120300293],"type":"Point"}
}