{
  "type": "Feature",
  "properties": {
    "iso:country":"BE",
    "sg:address":"Chemin De Sandron 2",
    "sg:city":"Marchin",
    "sg:classifiers":[
        {
            "category":"Professional",
            "subcategory":"Lawyer & Legal Services",
            "type":"Services"
        }
    ],
    "sg:phone":"+32 85 21 10 60",
    "sg:postcode":"4570",
    "sg:province":"Li\u00e8ge",
    "sg:tags":[
        "notary"
    ],
    "wof:name":"Dapsens V",
    "wof:placetype":"venue"
},
  "geometry": {"coordinates":[5.2268528938,50.4815254211],"type":"Point"}
}