{
  "type": "Feature",
  "properties": {
    "addr:full":"Rue Des Fran\u00e7ais 94 Aiseau-presles (roselies) Hainaut 6250",
    "addr:housenumber":"94",
    "addr:postcode":"6250",
    "addr:street":"Rue Des Franc\u0327Ais",
    "iso:country":"BE",
    "sg:address":"Rue Des Fran\u00e7ais 94",
    "sg:city":"Aiseau-presles (roselies)",
    "sg:classifiers":[
        {
            "category":"Home & Garden",
            "subcategory":"Building Materials",
            "type":"Retail Goods"
        }
    ],
    "sg:phone":"+32 71 76 01 79",
    "sg:postcode":"6250",
    "sg:province":"Hainaut",
    "sg:tags":[
        "veranda"
    ],
    "wof:name":"Depuydt-sacrez",
    "wof:placetype":"venue"
},
  "geometry": {"coordinates":[4.5767660141,50.4263114929],"type":"Point"}
}