{
  "type": "Feature",
  "properties": {
    "iso:country":"BE",
    "sg:address":"Rue Jules Guesde 23",
    "sg:city":"Quaregnon",
    "sg:classifiers":[
        {
            "category":"Arena",
            "subcategory":"Sports Club",
            "type":"Entertainment"
        }
    ],
    "sg:phone":"+32 476 20 91 64",
    "sg:postcode":"7390",
    "sg:province":"Hainaut",
    "sg:tags":[
        "de"
    ],
    "wof:name":"T.c. De Quaregnon",
    "wof:placetype":"venue"
},
  "geometry": {"coordinates":[3.8607239723,50.432926178],"type":"Point"}
}