{
  "type": "Feature",
  "properties": {
    "addr:full":"Avenue Des Combattants 20 Jodoigne Brabant Wallon 1370",
    "addr:housenumber":"20",
    "addr:postcode":"1370",
    "addr:street":"Avenue Des Combattants",
    "iso:country":"BE",
    "sg:address":"Avenue Des Combattants 20",
    "sg:city":"Jodoigne",
    "sg:orig_category":"DIENSTEN VOOR TELECOMMUNICATIE Industri\u00eble elektrische installaties",
    "sg:phone":"+32 10 48 66 11",
    "sg:postcode":"1370",
    "sg:province":"Brabant Wallon",
    "wof:name":"Electrabel",
    "wof:placetype":"venue"
},
  "geometry": {"coordinates":[4.870018959,50.723865509],"type":"Point"}
}