{
  "type": "Feature",
  "properties": {
    "iso:country":"BE",
    "sg:address":"H. Speecqvest 62",
    "sg:city":"Mechelen",
    "sg:classifiers":[
        {
            "category":"Retail",
            "subcategory":"Car Wash",
            "type":"Services"
        }
    ],
    "sg:phone":"+32 15 43 60 22",
    "sg:postcode":"2800",
    "sg:province":"Antwerpen",
    "sg:tags":[
        "machine",
        "mat\u00e9riel",
        "de",
        "bureau",
        "fournitures"
    ],
    "wof:name":"Office Solutions",
    "wof:placetype":"venue"
},
  "geometry": {"coordinates":[4.4856610298,51.02110672],"type":"Point"}
}