{
  "type": "Feature",
  "properties": {
    "iso:country":"BE",
    "sg:address":"Keiberg 1",
    "sg:city":"Lierde",
    "sg:orig_category":"Eleveurs de bovins. Eleveurs and marchands de porcs",
    "sg:phone":"+32 54 41 86 97",
    "sg:postcode":"9572",
    "sg:province":"Oost-Vlaanderen",
    "wof:name":"Marc De Vos",
    "wof:placetype":"venue"
},
  "geometry": {"coordinates":[3.8429999352,50.8019866943],"type":"Point"}
}