{
  "type": "Feature",
  "properties": {
    "iso:country":"BE",
    "sg:address":"Bosstraat 54b10",
    "sg:city":"Maaseik",
    "sg:orig_category":"Artsen and specialisten",
    "sg:phone":"+32 89 56 34 52",
    "sg:postcode":"3680",
    "sg:province":"Limburg",
    "wof:name":"Valerie Christiaens",
    "wof:placetype":"venue"
},
  "geometry": {"coordinates":[5.7884697914,51.0953483582],"type":"Point"}
}