{
  "type": "Feature",
  "properties": {
    "iso:country":"BE",
    "sg:address":"Route Solre-saint-g\u00c9ry 1",
    "sg:city":"Beaumont",
    "sg:orig_category":"Zand and grindontginning",
    "sg:phone":"+32 71 58 86 89",
    "sg:postcode":"6500",
    "sg:province":"Hainaut",
    "wof:name":"Carri\u00c8res De Barben\u00c7on",
    "wof:placetype":"venue"
},
  "geometry": {"coordinates":[4.2681469917,50.2178115845],"type":"Point"}
}