{
  "type": "Feature",
  "properties": {
    "addr:full":"Vlaskapelstraat 8 Wevelgem (gullegem) West-Vlaanderen 8560",
    "addr:housenumber":"8",
    "addr:postcode":"8560",
    "addr:street":"Vlaskapelstraat",
    "iso:country":"BE",
    "sg:address":"Vlaskapelstraat 8",
    "sg:city":"Wevelgem (gullegem)",
    "sg:classifiers":[
        {
            "category":"Bars & Pubs",
            "subcategory":"Wine Bar",
            "type":"Food & Drink"
        }
    ],
    "sg:phone":"+32 56 41 96 74",
    "sg:postcode":"8560",
    "sg:province":"West-Vlaanderen",
    "sg:tags":[
        "cellar",
        "fixture"
    ],
    "wof:name":"Cottyn Marc Koeltechn. Bvba",
    "wof:placetype":"venue"
},
  "geometry": {"coordinates":[3.2085900307,50.8435401917],"type":"Point"}
}