{
  "type": "Feature",
  "properties": {
    "iso:country":"BE",
    "sg:address":"Krijgelstraat 57",
    "sg:city":"Wichelen",
    "sg:orig_category":"Bouwmaterialen Gh Woningbouw",
    "sg:phone":"+32 9 369 97 91",
    "sg:postcode":"9260",
    "sg:province":"Oost-Vlaanderen",
    "wof:name":"Bouwwerken De Cremer",
    "wof:placetype":"venue"
},
  "geometry": {"coordinates":[3.9551889896,50.9986724854],"type":"Point"}
}