{
  "type": "Feature",
  "properties": {
    "iso:country":"BE",
    "sg:address":"Opstaldries 42",
    "sg:city":"Lierde",
    "sg:orig_category":"Banques and organismes de cr\u00e9dit",
    "sg:phone":"+32 55 42 37 01",
    "sg:postcode":"9572",
    "sg:province":"Oost-Vlaanderen",
    "wof:name":"Dexia",
    "wof:placetype":"venue"
},
  "geometry": {"coordinates":[3.8281729221,50.7999000549],"type":"Point"}
}