{
  "type": "Feature",
  "properties": {
    "iso:country":"BE",
    "sg:address":"Ontmijnersstraat 11",
    "sg:city":"Blankenberge",
    "sg:classifiers":[
        {
            "category":"Bars & Pubs",
            "type":"Food & Drink"
        }
    ],
    "sg:phone":"+32 50 41 04 73",
    "sg:postcode":"8370",
    "sg:province":"West-Vlaanderen",
    "wof:name":"Swingcaf\u00e9 ('t)",
    "wof:placetype":"venue"
},
  "geometry": {"coordinates":[3.1315488815,51.3118095398],"type":"Point"}
}