{
  "type": "Feature",
  "properties": {
    "iso:country":"BE",
    "sg:address":"Place Wiertz 18",
    "sg:city":"Namur",
    "sg:classifiers":[
        {
            "category":"Wholesale",
            "subcategory":"Sporting Goods",
            "type":"Manufacturing & Wholesale Goods"
        }
    ],
    "sg:phone":"+32 81 74 82 50",
    "sg:postcode":"5000",
    "sg:province":"Namur",
    "sg:tags":[
        "sport-",
        "kampeermateriaal"
    ],
    "wof:name":"Tra\u00b4montagne",
    "wof:placetype":"venue"
},
  "geometry": {"coordinates":[4.84877491,50.4644813538],"type":"Point"}
}