{
  "type": "Feature",
  "properties": {
    "addr:full":"Chauss\u00e9e De Li\u00e8ge 39 Huy Li\u00e8ge 4500",
    "addr:housenumber":"39",
    "addr:postcode":"4500",
    "addr:street":"Chausse\u0301E De Lie\u0300Ge",
    "iso:country":"BE",
    "sg:address":"Chauss\u00e9e De Li\u00e8ge 39",
    "sg:city":"Huy",
    "sg:classifiers":[
        {
            "category":"Banks & Credit Unions",
            "subcategory":"Financial Services",
            "type":"Services"
        }
    ],
    "sg:phone":"+32 85 23 31 71",
    "sg:postcode":"4500",
    "sg:province":"Li\u00e8ge",
    "sg:tags":[
        "financing"
    ],
    "wof:name":"Ppt Du Pays De Huy",
    "wof:placetype":"venue"
},
  "geometry": {"coordinates":[5.2380871773,50.5258712769],"type":"Point"}
}