{
  "type": "Feature",
  "properties": {
    "iso:country":"BE",
    "sg:address":"Industrielaan 7b",
    "sg:city":"Eeklo",
    "sg:orig_category":"Transports routiers de marchandises",
    "sg:phone":"+32 9 376 76 76",
    "sg:postcode":"9900",
    "sg:province":"Oost-Vlaanderen",
    "wof:name":"Meetjesland",
    "wof:placetype":"venue"
},
  "geometry": {"coordinates":[3.5408809185,51.1820297241],"type":"Point"}
}