{
  "type": "Feature",
  "properties": {
    "addr:full":"Meusegemstraat 22 Meise Vlaams-Brabant 1861",
    "addr:housenumber":"22",
    "addr:postcode":"1861",
    "addr:street":"Meusegemstraat",
    "iso:country":"BE",
    "sg:address":"Meusegemstraat 22",
    "sg:city":"Meise",
    "sg:orig_category":"Verlichting and huishoudartikelen",
    "sg:phone":"+32 2 270 20 93",
    "sg:postcode":"1861",
    "sg:province":"Vlaams-Brabant",
    "wof:name":"Collyns",
    "wof:placetype":"venue"
},
  "geometry": {"coordinates":[4.2887501717,50.9566001892],"type":"Point"}
}