{
  "type": "Feature",
  "properties": {
    "iso:country":"BE",
    "sg:address":"Slangstraat 45",
    "sg:city":"Hamme",
    "sg:classifiers":[
        {
            "category":"Health Services",
            "subcategory":"Doctor",
            "type":"Services"
        }
    ],
    "sg:phone":"+32 52 48 14 61",
    "sg:postcode":"9220",
    "sg:province":"Oost-Vlaanderen",
    "sg:tags":[
        "medicinephysicians",
        "surgeon"
    ],
    "wof:name":"Koentges Didrik",
    "wof:placetype":"venue"
},
  "geometry": {"coordinates":[4.1360459328,51.0937347412],"type":"Point"}
}