{
  "type": "Feature",
  "properties": {
    "iso:country":"BE",
    "sg:address":"Avenue Des D\u00c9mineurs 18b1",
    "sg:city":"Stavelot",
    "sg:orig_category":"V\u00eatements pour Hommes. V\u00eatements pour Dames",
    "sg:phone":"+32 80 86 23 56",
    "sg:postcode":"4970",
    "sg:province":"Li\u00e8ge",
    "wof:name":"Close Boutique",
    "wof:placetype":"venue"
},
  "geometry": {"coordinates":[5.9352688789,50.3958816528],"type":"Point"}
}