{
  "type": "Feature",
  "properties": {
    "addr:full":"Dellestraat 33 Heusden-zolder Limburg 3550",
    "addr:housenumber":"33",
    "addr:postcode":"3550",
    "addr:street":"Dellestraat",
    "iso:country":"BE",
    "sg:address":"Dellestraat 33",
    "sg:city":"Heusden-zolder",
    "sg:orig_category":"Emballages en plastique Fab",
    "sg:phone":"+32 13 53 92 11",
    "sg:postcode":"3550",
    "sg:province":"Limburg",
    "wof:name":"Belfort International",
    "wof:placetype":"venue"
},
  "geometry": {"coordinates":[5.2434902191,50.9820556641],"type":"Point"}
}