{
  "type": "Feature",
  "properties": {
    "addr:full":"Hoogstraat 33 Putte (beerzel) Antwerpen 2580",
    "addr:housenumber":"33",
    "addr:postcode":"2580",
    "addr:street":"Hoogstraat",
    "iso:country":"BE",
    "sg:address":"Hoogstraat 33",
    "sg:city":"Putte (beerzel)",
    "sg:classifiers":[
        {
            "category":"Food & Beverages",
            "subcategory":"Fruits & Vegetables",
            "type":"Retail Goods"
        }
    ],
    "sg:phone":"+32 15 22 65 01",
    "sg:postcode":"2580",
    "sg:province":"Antwerpen",
    "sg:tags":[
        "-"
    ],
    "wof:name":"Wendy's Nieuwe Oogst",
    "wof:placetype":"venue"
},
  "geometry": {"coordinates":[4.6687102318,51.0575637817],"type":"Point"}
}