{
  "type": "Feature",
  "properties": {
    "addr:full":"Rue De Rixensart 33 Rixensart Brabant Wallon 1332",
    "addr:housenumber":"33",
    "addr:postcode":"1332",
    "addr:street":"Rue De Rixensart;Wallon",
    "iso:country":"BE",
    "sg:address":"Rue De Rixensart 33",
    "sg:city":"Rixensart",
    "sg:classifiers":[
        {
            "category":"Government",
            "subcategory":"Police Station",
            "type":"Public Place"
        }
    ],
    "sg:phone":"+32 2 653 62 63",
    "sg:postcode":"1332",
    "sg:province":"Brabant Wallon",
    "sg:tags":[
        "gendarmerie"
    ],
    "wof:name":"Police F\u00c9d\u00c9rale/federale Politie",
    "wof:placetype":"venue"
},
  "geometry": {"coordinates":[4.5142741203,50.7231521606],"type":"Point"}
}