{
  "type": "Feature",
  "properties": {
    "addr:full":"Steenweg Naar Alsemberg 994 Beersel (huizingen) Vlaams-Brabant 1654",
    "addr:housenumber":"994",
    "addr:postcode":"1654",
    "addr:street":"Steenweg Naar Alsemberg",
    "iso:country":"BE",
    "sg:address":"Steenweg Naar Alsemberg 994",
    "sg:city":"Beersel (huizingen)",
    "sg:classifiers":[
        {
            "category":"Professional",
            "subcategory":"Testing Lab",
            "type":"Services"
        }
    ],
    "sg:phone":"+32 2 356 77 40",
    "sg:postcode":"1654",
    "sg:province":"Vlaams-Brabant",
    "sg:tags":[
        "chemist"
    ],
    "wof:name":"Van Wilderode P Bvba",
    "wof:placetype":"venue"
},
  "geometry": {"coordinates":[4.2681760788,50.7452735901],"type":"Point"}
}