{
  "type": "Feature",
  "properties": {
    "iso:country":"BE",
    "sg:address":"Hamerstraat 58",
    "sg:city":"Stekene",
    "sg:orig_category":"Eleveurs and marchands de porcs. Eleveurs de bovins",
    "sg:phone":"+32 3 789 29 50",
    "sg:postcode":"9190",
    "sg:province":"Oost-Vlaanderen",
    "wof:name":"De Theye & Zoon",
    "wof:placetype":"venue"
},
  "geometry": {"coordinates":[4.0218281746,51.2098426819],"type":"Point"}
}