{
  "type": "Feature",
  "properties": {
    "iso:country":"BE",
    "sg:address":"Chauss\u00c9e De Namur 15",
    "sg:city":"Ramillies",
    "sg:orig_category":"Assistances juridiques",
    "sg:phone":"+32 81 87 72 17",
    "sg:postcode":"1367",
    "sg:province":"Brabant Wallon",
    "wof:name":"Lauris",
    "wof:placetype":"venue"
},
  "geometry": {"coordinates":[4.8448901176,50.6514205933],"type":"Point"}
}