{
  "type": "Feature",
  "properties": {
    "iso:country":"BE",
    "sg:address":"Heynholwegel",
    "sg:city":"Zwevegem (sint-denijs)",
    "sg:classifiers":[
        {
            "category":"Farming",
            "subcategory":"Livestock Farm",
            "type":"Manufacturing & Wholesale Goods"
        }
    ],
    "sg:phone":"+32 56 75 88 04",
    "sg:postcode":"8554",
    "sg:province":"West-Vlaanderen",
    "sg:tags":[
        "buyer"
    ],
    "wof:name":"Vandecasteele A",
    "wof:placetype":"venue"
},
  "geometry": {"coordinates":[3.3706920147,50.7496185303],"type":"Point"}
}