{
  "type": "Feature",
  "properties": {
    "addr:full":"Kortestraat 7 Zoersel Antwerpen 2980",
    "addr:housenumber":"7",
    "addr:postcode":"2980",
    "addr:street":"Kortestraat",
    "iso:country":"BE",
    "sg:address":"Kortestraat 7",
    "sg:city":"Zoersel",
    "sg:classifiers":[
        {
            "category":"Health Services",
            "subcategory":"Nursing And Care Facility",
            "type":"Services"
        }
    ],
    "sg:phone":"+32 3 312 19 15",
    "sg:postcode":"2980",
    "sg:province":"Antwerpen",
    "sg:tags":[
        "home"
    ],
    "wof:name":"Verryckt S",
    "wof:placetype":"venue"
},
  "geometry": {"coordinates":[4.7000069618,51.2692451477],"type":"Point"}
}