{
  "type": "Feature",
  "properties": {
    "iso:country":"BE",
    "sg:address":"Oefenpleinstraat 16",
    "sg:city":"Melle",
    "sg:classifiers":[
        {
            "category":"Banks & Credit Unions",
            "subcategory":"Investment Brokerage",
            "type":"Services"
        }
    ],
    "sg:phone":"+32 9 231 72 59",
    "sg:postcode":"9090",
    "sg:province":"Oost-Vlaanderen",
    "sg:tags":[
        "auditor"
    ],
    "wof:name":"Vermussche D",
    "wof:placetype":"venue"
},
  "geometry": {"coordinates":[3.7807099819,51.0236320496],"type":"Point"}
}