{
  "type": "Feature",
  "properties": {
    "iso:country":"BE",
    "sg:address":"Gullegemsestraat 152",
    "sg:city":"Ledegem",
    "sg:orig_category":"Pain, p\u00e2tisseries and confiseries. Cr\u00e9meries",
    "sg:phone":"+32 56 50 27 95",
    "sg:postcode":"8880",
    "sg:province":"West-Vlaanderen",
    "wof:name":"De Korenhalm",
    "wof:placetype":"venue"
},
  "geometry": {"coordinates":[3.1840751171,50.8666419983],"type":"Point"}
}