{
  "type": "Feature",
  "properties": {
    "addr:full":"Rue Jules Destr\u00e9e 47 Oupeye Li\u00e8ge 4680",
    "addr:housenumber":"47",
    "addr:postcode":"4680",
    "addr:street":"Rue Jules Destre\u0301E",
    "iso:country":"BE",
    "sg:address":"Rue Jules Destr\u00e9e 47",
    "sg:city":"Oupeye",
    "sg:classifiers":[
        {
            "category":"Retail",
            "subcategory":"Auto Repair",
            "type":"Services"
        }
    ],
    "sg:phone":"+32 4 248 25 81",
    "sg:postcode":"4680",
    "sg:province":"Li\u00e8ge",
    "sg:tags":[
        "automobile",
        "servic",
        "electrical",
        "-"
    ],
    "wof:name":"Fafra R",
    "wof:placetype":"venue"
},
  "geometry": {"coordinates":[5.6423311234,50.7062835693],"type":"Point"}
}