{
  "type": "Feature",
  "properties": {
    "addr:full":"Stippelberg 128 Westerlo Antwerpen 2260",
    "addr:housenumber":"128",
    "addr:postcode":"2260",
    "addr:street":"Stippelberg",
    "iso:country":"BE",
    "sg:address":"Stippelberg 128",
    "sg:city":"Westerlo",
    "sg:orig_category":"Woningbouw",
    "sg:phone":"+32 16 69 98 28",
    "sg:postcode":"2260",
    "sg:province":"Antwerpen",
    "wof:name":"Achilles Van Den Brande",
    "wof:placetype":"venue"
},
  "geometry": {"coordinates":[4.8574972153,51.0764274597],"type":"Point"}
}