{
  "type": "Feature",
  "properties": {
    "iso:country":"BE",
    "sg:address":"Place Albert I 1",
    "sg:city":"Malmedy",
    "sg:classifiers":[
        {
            "category":"Shopping",
            "subcategory":"Music",
            "type":"Retail Goods"
        }
    ],
    "sg:phone":"+32 80 33 73 13",
    "sg:postcode":"4960",
    "sg:province":"Li\u00e8ge",
    "sg:tags":[
        "-",
        "cd's",
        "recorded",
        "cassette"
    ],
    "wof:name":"Music 2000",
    "wof:placetype":"venue"
},
  "geometry": {"coordinates":[6.0306248665,50.4252433777],"type":"Point"}
}