{
  "type": "Feature",
  "properties": {
    "iso:country":"BE",
    "sg:address":"Rue Louis Snyers 24",
    "sg:city":"Hannut",
    "sg:orig_category":"Woningbouw",
    "sg:phone":"+32 19 51 19 27",
    "sg:postcode":"4280",
    "sg:province":"Li\u00e8ge",
    "wof:name":"Alain Lambert",
    "wof:placetype":"venue"
},
  "geometry": {"coordinates":[5.0851840973,50.6702461243],"type":"Point"}
}