{
  "type": "Feature",
  "properties": {
    "iso:country":"BE",
    "sg:address":"Calaignestraat 20",
    "sg:city":"Eksaarde",
    "sg:orig_category":"Huisdieren and benodigdheden Royal Canin",
    "sg:phone":"+32 9 348 41 03",
    "sg:postcode":"9160",
    "sg:province":"Oost-Vlaanderen",
    "wof:name":"Het Neerhof",
    "wof:placetype":"venue"
},
  "geometry": {"coordinates":[3.9271929264,51.1262359619],"type":"Point"}
}