{
  "type": "Feature",
  "properties": {
    "addr:full":"Maldersesteenweg 123b2 Londerzeel Vlaams-Brabant 1840",
    "addr:housenumber":"123b2",
    "addr:postcode":"1840",
    "addr:street":"Maldersesteenweg",
    "iso:country":"BE",
    "sg:address":"Maldersesteenweg 123b2",
    "sg:city":"Londerzeel",
    "sg:orig_category":"D\u00e9chets and d\u00e9bris Gr",
    "sg:phone":"+32 52 30 37 41",
    "sg:postcode":"1840",
    "sg:province":"Vlaams-Brabant",
    "wof:name":"Rudolf De Kinder",
    "wof:placetype":"venue"
},
  "geometry": {"coordinates":[4.2759900093,51.0269966125],"type":"Point"}
}