{
  "type": "Feature",
  "properties": {
    "iso:country":"BE",
    "sg:address":"Middelheimlaan 1",
    "sg:city":"Antwerpen",
    "sg:orig_category":"Enseignement sup\u00e9rieur",
    "sg:phone":"+32 3 218 05 37",
    "sg:postcode":"2020",
    "sg:province":"Antwerpen",
    "wof:name":"Ruca-fac.toeg.econ.wet.",
    "wof:placetype":"venue"
},
  "geometry": {"coordinates":[4.4161300659,51.1835403442],"type":"Point"}
}