{
  "type": "Feature",
  "properties": {
    "addr:full":"Bohemen 54 Wichelen Oost-Vlaanderen 9260",
    "addr:housenumber":"54",
    "addr:postcode":"9260",
    "addr:street":"Bohemen",
    "iso:country":"BE",
    "sg:address":"Bohemen 54",
    "sg:city":"Wichelen",
    "sg:classifiers":[
        {
            "category":"Bars & Pubs",
            "type":"Food & Drink"
        }
    ],
    "sg:phone":"+32 52 42 71 49",
    "sg:postcode":"9260",
    "sg:province":"Oost-Vlaanderen",
    "wof:name":"Giloma",
    "wof:placetype":"venue"
},
  "geometry": {"coordinates":[3.9811599255,51.0032806396],"type":"Point"}
}