{
  "type": "Feature",
  "properties": {
    "iso:country":"BE",
    "sg:address":"Grand'rue 160",
    "sg:city":"Jalhay (sart)",
    "sg:classifiers":[
        {
            "category":"Bakery",
            "type":"Food & Drink"
        }
    ],
    "sg:phone":"+32 87 47 46 02",
    "sg:postcode":"4845",
    "sg:province":"Li\u00e8ge",
    "sg:tags":[
        "confectioner",
        "baker"
    ],
    "wof:name":"La mitch.au Beurre",
    "wof:placetype":"venue"
},
  "geometry": {"coordinates":[5.9321532249,50.5156097412],"type":"Point"}
}