{
  "type": "Feature",
  "properties": {
    "addr:full":"Rue De Marchienne 19 Montigny-le-tilleul Hainaut 6110",
    "addr:housenumber":"19",
    "addr:postcode":"6110",
    "addr:street":"Rue De Marchienne",
    "iso:country":"BE",
    "sg:address":"Rue De Marchienne 19",
    "sg:city":"Montigny-le-tilleul",
    "sg:orig_category":"Avocats and conseillers juridiques",
    "sg:phone":"+32 71 51 91 91",
    "sg:postcode":"6110",
    "sg:province":"Hainaut",
    "wof:name":"A. Michiels",
    "wof:placetype":"venue"
},
  "geometry": {"coordinates":[4.3804798126,50.3801994324],"type":"Point"}
}