{
  "type": "Feature",
  "properties": {
    "iso:country":"BE",
    "sg:address":"Rue De La Marine 9",
    "sg:city":"Charleroi",
    "sg:orig_category":"Boekhouders",
    "sg:phone":"+32 71 35 02 00",
    "sg:postcode":"6040",
    "sg:province":"Hainaut",
    "wof:name":"Urbain Cornet",
    "wof:placetype":"venue"
},
  "geometry": {"coordinates":[4.4374041557,50.4341239929],"type":"Point"}
}