{
  "type": "Feature",
  "properties": {
    "addr:full":"Wiedauwkaai 51 Gent Oost-Vlaanderen 9000",
    "addr:housenumber":"51",
    "addr:postcode":"9000",
    "addr:street":"Wiedauwkaai;Oost-Vlaanderen",
    "iso:country":"BE",
    "sg:address":"Wiedauwkaai 51",
    "sg:city":"Gent",
    "sg:orig_category":"Jardinage",
    "sg:phone":"+32 9 258 01 46",
    "sg:postcode":"9000",
    "sg:province":"Oost-Vlaanderen",
    "wof:name":"Garden Styling",
    "wof:placetype":"venue"
},
  "geometry": {"coordinates":[3.7260890007,51.0745429993],"type":"Point"}
}