{
  "type": "Feature",
  "properties": {
    "addr:full":"Nederholbeekstraat 158 Maarkedal (etikhove) Oost-Vlaanderen 9680",
    "addr:housenumber":"158",
    "addr:postcode":"9680",
    "addr:street":"Nederholbeekstraat",
    "iso:country":"BE",
    "sg:address":"Nederholbeekstraat 158",
    "sg:city":"Maarkedal (etikhove)",
    "sg:classifiers":[
        {
            "category":"Health Services",
            "subcategory":"Doctor",
            "type":"Services"
        }
    ],
    "sg:phone":"+32 55 31 44 00",
    "sg:postcode":"9680",
    "sg:province":"Oost-Vlaanderen",
    "sg:tags":[
        "medicinephysicians",
        "surgeon"
    ],
    "wof:name":"Cooman F",
    "wof:placetype":"venue"
},
  "geometry": {"coordinates":[3.62165308,50.8020324707],"type":"Point"}
}