{
  "type": "Feature",
  "properties": {
    "iso:country":"BE",
    "sg:address":"Rue De La Bruy\u00c8re 20",
    "sg:city":"Tournai",
    "sg:orig_category":"Mat\u00e9riel m\u00e9dical and orthop\u00e9dique and proth\u00e8ses Fab",
    "sg:phone":"+32 69 23 34 81",
    "sg:postcode":"7540",
    "sg:province":"Hainaut",
    "wof:name":"Serge Ducobu",
    "wof:placetype":"venue"
},
  "geometry": {"coordinates":[3.3659830093,50.6491279602],"type":"Point"}
}