{
  "type": "Feature",
  "properties": {
    "iso:country":"BE",
    "sg:address":"Rue Des D\u00c9port\u00c9s 130",
    "sg:city":"Beloeil",
    "sg:orig_category":"Boucheries",
    "sg:phone":"+32 69 57 52 60",
    "sg:postcode":"7971",
    "sg:province":"Hainaut",
    "wof:name":"Freddy Thomas",
    "wof:placetype":"venue"
},
  "geometry": {"coordinates":[3.6421720982,50.5223693848],"type":"Point"}
}