{
  "type": "Feature",
  "properties": {
    "iso:country":"BE",
    "sg:address":"Rue Thim 38",
    "sg:city":"Kelmis",
    "sg:orig_category":"Bloemen and planten Fleurop Interflora",
    "sg:phone":"+32 87 65 92 19",
    "sg:postcode":"4720",
    "sg:province":"Li\u00e8ge",
    "wof:name":"Au Mimosa",
    "wof:placetype":"venue"
},
  "geometry": {"coordinates":[6.0109968185,50.7173728943],"type":"Point"}
}