{
  "type": "Feature",
  "properties": {
    "addr:full":"Turnhoutseweg 14a Baarle-hertog Antwerpen 2387",
    "addr:housenumber":"14a",
    "addr:postcode":"2387",
    "addr:street":"Turnhoutseweg",
    "iso:country":"BE",
    "sg:address":"Turnhoutseweg 14a",
    "sg:city":"Baarle-hertog",
    "sg:classifiers":[
        {
            "category":"Real Estate",
            "subcategory":"Real Estate Services",
            "type":"Services"
        }
    ],
    "sg:phone":"+31 13 507 8499",
    "sg:postcode":"2387",
    "sg:province":"Antwerpen",
    "wof:name":"Van Rooij A",
    "wof:placetype":"venue"
},
  "geometry": {"coordinates":[4.9311170578,51.4342346191],"type":"Point"}
}