{
  "type": "Feature",
  "properties": {
    "addr:full":"Lenniksebaan 1120 Sint-pieters-leeuw Vlaams-Brabant 1602",
    "addr:housenumber":"1120",
    "addr:postcode":"1602",
    "addr:street":"Lenniksebaan",
    "iso:country":"BE",
    "sg:address":"Lenniksebaan 1120",
    "sg:city":"Sint-pieters-leeuw",
    "sg:orig_category":"Installatie van houten of kunststof schrijnwerk",
    "sg:phone":"+32 2 569 28 77",
    "sg:postcode":"1602",
    "sg:province":"Vlaams-Brabant",
    "wof:name":"Marcel Boom",
    "wof:placetype":"venue"
},
  "geometry": {"coordinates":[4.2471308708,50.8173370361],"type":"Point"}
}