{
  "type": "Feature",
  "properties": {
    "iso:country":"BE",
    "sg:address":"Avenue Jacques Sermon 107/23",
    "sg:city":"Jette",
    "sg:orig_category":"Agences immobili\u00e8res. Administration d'immeubles",
    "sg:phone":"+32 2 420 11 55",
    "sg:postcode":"1090",
    "sg:province":"Bruxelles-Capitale",
    "wof:name":"Jet Immo",
    "wof:placetype":"venue"
},
  "geometry": {"coordinates":[4.3231258392,50.8706092834],"type":"Point"}
}