{
  "type": "Feature",
  "properties": {
    "iso:country":"BE",
    "sg:address":"Rue De L'ecluse 99",
    "sg:city":"Vise",
    "sg:orig_category":"Kapsalons",
    "sg:phone":"+32 4 379 68 80",
    "sg:postcode":"4600",
    "sg:province":"Li\u00e8ge",
    "wof:name":"Coiffure Benedicte",
    "wof:placetype":"venue"
},
  "geometry": {"coordinates":[5.6790289879,50.7476005554],"type":"Point"}
}