{
  "type": "Feature",
  "properties": {
    "iso:country":"BE",
    "sg:address":"Rue Du Labyrinthe 60",
    "sg:city":"Mouscron",
    "sg:orig_category":"Industri\u00eble wasserijen and droogkuis",
    "sg:phone":"+32 56 32 40 05",
    "sg:postcode":"7700",
    "sg:province":"Hainaut",
    "wof:name":"Lavoir Ipso-wash",
    "wof:placetype":"venue"
},
  "geometry": {"coordinates":[3.195360899,50.7468299866],"type":"Point"}
}