{
  "type": "Feature",
  "properties": {
    "iso:country":"BE",
    "sg:address":"Rue Emile Dury 142",
    "sg:city":"Waterloo",
    "sg:classifiers":[
        {
            "category":"Building & Trades",
            "subcategory":"Plumbing",
            "type":"Services"
        }
    ],
    "sg:phone":"+32 2 354 18 29",
    "sg:postcode":"1410",
    "sg:province":"Brabant Wallon",
    "sg:tags":[
        "contractor"
    ],
    "wof:name":"Van Hamme J",
    "wof:placetype":"venue"
},
  "geometry": {"coordinates":[4.3811430931,50.7092781067],"type":"Point"}
}