{
  "type": "Feature",
  "properties": {
    "iso:country":"BE",
    "sg:address":"Beukenbosstraat 6",
    "sg:city":"Mol",
    "sg:orig_category":"Plaatsen van vloer- and muurbekleding Schilders",
    "sg:phone":"+32 14 31 10 96",
    "sg:postcode":"2400",
    "sg:province":"Antwerpen",
    "wof:name":"Van De Kerkhof",
    "wof:placetype":"venue"
},
  "geometry": {"coordinates":[5.115131855,51.204914093],"type":"Point"}
}