{
  "type": "Feature",
  "properties": {
    "addr:full":"Place D'herchies 1 Jurbise (herchies) Hainaut 7050",
    "addr:housenumber":"1",
    "addr:postcode":"7050",
    "addr:street":"Place D'Herchies",
    "iso:country":"BE",
    "sg:address":"Place D'herchies 1",
    "sg:city":"Jurbise (herchies)",
    "sg:classifiers":[
        {
            "category":"Social Services",
            "type":"Services"
        }
    ],
    "sg:phone":"+32 65 22 80 70",
    "sg:postcode":"7050",
    "sg:province":"Hainaut",
    "wof:name":"C.p.a.s.",
    "wof:placetype":"venue"
},
  "geometry": {"coordinates":[3.8833971024,50.5061302185],"type":"Point"}
}