{
  "type": "Feature",
  "properties": {
    "iso:country":"BE",
    "sg:address":"Vaartdijk Noord 61",
    "sg:city":"Middelkerke",
    "sg:orig_category":"Sportclubs",
    "sg:phone":"+32 58 23 67 19",
    "sg:postcode":"8433",
    "sg:province":"West-Vlaanderen",
    "wof:name":"H.c. Thor Middelkerke",
    "wof:placetype":"venue"
},
  "geometry": {"coordinates":[2.8475210667,51.1547775269],"type":"Point"}
}