{
  "type": "Feature",
  "properties": {
    "iso:country":"BE",
    "sg:address":"Pladijsstraat 295",
    "sg:city":"Deerlijk",
    "sg:classifiers":[
        {
            "category":"Building & Trades",
            "subcategory":"Construction",
            "type":"Services"
        }
    ],
    "sg:phone":"+32 56 77 16 54",
    "sg:postcode":"8540",
    "sg:province":"West-Vlaanderen",
    "sg:tags":[
        "stucco",
        "contractor"
    ],
    "wof:name":"Petit Claude",
    "wof:placetype":"venue"
},
  "geometry": {"coordinates":[3.3756830692,50.8228225708],"type":"Point"}
}