{
  "type": "Feature",
  "properties": {
    "iso:country":"BE",
    "sg:address":"Burgemeester Gillonlaan 27",
    "sg:city":"Kortrijk",
    "sg:classifiers":[
        {
            "category":"Insurance",
            "subcategory":"Life Insurance",
            "type":"Services"
        }
    ],
    "sg:phone":"+32 56 22 18 67",
    "sg:postcode":"8500",
    "sg:province":"West-Vlaanderen",
    "sg:tags":[
        "assurance"
    ],
    "wof:name":"Willem Piette En Co",
    "wof:placetype":"venue"
},
  "geometry": {"coordinates":[3.2785880566,50.8203125],"type":"Point"}
}