{
  "type": "Feature",
  "properties": {
    "iso:country":"BE",
    "sg:address":"Oudezakstraat 28",
    "sg:city":"Beernem",
    "sg:orig_category":"Diverse organisaties and verenigingen",
    "sg:phone":"+32 50 78 01 04",
    "sg:postcode":"8730",
    "sg:province":"West-Vlaanderen",
    "wof:name":"J.a. Oranje Oedelem",
    "wof:placetype":"venue"
},
  "geometry": {"coordinates":[3.341547966,51.169128418],"type":"Point"}
}