{
  "type": "Feature",
  "properties": {
    "addr:full":"Otto Veniusstraat 28 Antwerpen Antwerpen 2000",
    "addr:housenumber":"28",
    "addr:postcode":"2000",
    "addr:street":"Otto Veniusstraat",
    "iso:country":"BE",
    "sg:address":"Otto Veniusstraat 28",
    "sg:city":"Antwerpen",
    "sg:classifiers":[
        {
            "category":"Real Estate",
            "subcategory":"Real Estate Services",
            "type":"Services"
        }
    ],
    "sg:phone":"+32 3 232 26 06",
    "sg:postcode":"2000",
    "sg:province":"Antwerpen",
    "wof:name":"Eigenaarsbond Vzw",
    "wof:placetype":"venue"
},
  "geometry": {"coordinates":[4.4122848511,51.2170639038],"type":"Point"}
}