{
  "type": "Feature",
  "properties": {
    "addr:full":"Rue Des Carri\u00c8res 2 Beauraing Namur 5570",
    "addr:housenumber":"2",
    "addr:postcode":"5570",
    "addr:street":"Rue Des Carrie\u0300Res",
    "iso:country":"BE",
    "sg:address":"Rue Des Carri\u00c8res 2",
    "sg:city":"Beauraing",
    "sg:orig_category":"M\u00e9decins and sp\u00e9cialistes",
    "sg:phone":"+32 82 71 34 12",
    "sg:postcode":"5570",
    "sg:province":"Namur",
    "wof:name":"Georges Thomas",
    "wof:placetype":"venue"
},
  "geometry": {"coordinates":[4.8927798271,50.0954093933],"type":"Point"}
}