{
  "type": "Feature",
  "properties": {
    "addr:full":"Ottergemsesteenweg-zuid 720 Gent Oost-Vlaanderen 9000",
    "addr:housenumber":"720",
    "addr:postcode":"9000",
    "addr:street":"Ottergemsesteenweg-Zuid;Oost-Vlaanderen",
    "iso:country":"BE",
    "sg:address":"Ottergemsesteenweg-zuid 720",
    "sg:city":"Gent",
    "sg:orig_category":"RESTAURANTS: SUPPLIES",
    "sg:phone":"+32 9 241 51 11",
    "sg:postcode":"9000",
    "sg:province":"Oost-Vlaanderen",
    "wof:name":"I.s.p.c. Nv",
    "wof:placetype":"venue"
},
  "geometry": {"coordinates":[3.7379009724,51.0172691345],"type":"Point"}
}