{
  "type": "Feature",
  "properties": {
    "addr:full":"Rue Reine Elisabeth 6 Mettet Namur 5640",
    "addr:housenumber":"6",
    "addr:postcode":"5640",
    "addr:street":"Rue Reine Elisabeth",
    "iso:country":"BE",
    "sg:address":"Rue Reine Elisabeth 6",
    "sg:city":"Mettet",
    "sg:orig_category":"Banken and kredietinstellingen",
    "sg:phone":"+32 71 72 98 89",
    "sg:postcode":"5640",
    "sg:province":"Namur",
    "wof:name":"Cbc",
    "wof:placetype":"venue"
},
  "geometry": {"coordinates":[4.6582369804,50.3200149536],"type":"Point"}
}