{
  "type": "Feature",
  "properties": {
    "iso:country":"BE",
    "sg:address":"Rue De Herm\u00e9e 216b",
    "sg:city":"Herstal",
    "sg:classifiers":[
        {
            "category":"Fast Food",
            "type":"Food & Drink"
        }
    ],
    "sg:phone":"+32 4 264 53 50",
    "sg:postcode":"4040",
    "sg:province":"Li\u00e8ge",
    "sg:tags":[
        "fried",
        "stand",
        "potato"
    ],
    "wof:name":"Le Rendez-vous",
    "wof:placetype":"venue"
},
  "geometry": {"coordinates":[5.6276311874,50.6946144104],"type":"Point"}
}