{
  "type": "Feature",
  "properties": {
    "iso:country":"BE",
    "sg:address":"Henri Brounsstraat 39",
    "sg:city":"Machelen",
    "sg:orig_category":"Artsen and specialisten",
    "sg:phone":"+32 2 251 17 70",
    "sg:postcode":"1830",
    "sg:province":"Vlaams-Brabant",
    "wof:name":"Rudi Bruyninckx",
    "wof:placetype":"venue"
},
  "geometry": {"coordinates":[4.432513237,50.9091682434],"type":"Point"}
}