{
  "type": "Feature",
  "properties": {
    "addr:full":"Vliegenstraat 5 Antwerpen Antwerpen 2060",
    "addr:housenumber":"5",
    "addr:postcode":"2060",
    "addr:street":"Vliegenstraat",
    "iso:country":"BE",
    "sg:address":"Vliegenstraat 5",
    "sg:city":"Antwerpen",
    "sg:classifiers":[
        {
            "category":"Personal",
            "subcategory":"Beauty Salon",
            "type":"Services"
        }
    ],
    "sg:phone":"+32 3 231 42 45",
    "sg:postcode":"2060",
    "sg:province":"Antwerpen",
    "sg:tags":[
        "lady",
        "-",
        "hairdressing"
    ],
    "wof:name":"M G I",
    "wof:placetype":"venue"
},
  "geometry": {"coordinates":[4.4205060005,51.2255973816],"type":"Point"}
}