{
  "type": "Feature",
  "properties": {
    "addr:full":"Binnenstraat 45 Veltem-beisem Vlaams-Brabant 3020",
    "addr:housenumber":"45",
    "addr:postcode":"3020",
    "addr:street":"Binnenstraat",
    "iso:country":"BE",
    "sg:address":"Binnenstraat 45",
    "sg:city":"Veltem-beisem",
    "sg:orig_category":"Transports terrestres de voyageurs",
    "sg:phone":"+32 16 48 84 13",
    "sg:postcode":"3020",
    "sg:province":"Vlaams-Brabant",
    "wof:name":"Mjb Coach",
    "wof:placetype":"venue"
},
  "geometry": {"coordinates":[4.6177887917,50.9049797058],"type":"Point"}
}