{
  "type": "Feature",
  "properties": {
    "iso:country":"BE",
    "sg:address":"Rue De La Terre \u00c0 Briques 29a",
    "sg:city":"Tournai",
    "sg:orig_category":"R\u00e9alisation de programmes and logiciels",
    "sg:phone":"+32 69 88 01 55",
    "sg:postcode":"7503",
    "sg:province":"Hainaut",
    "wof:name":"Ige-xao Benelux",
    "wof:placetype":"venue"
},
  "geometry": {"coordinates":[3.331154108,50.6171684265],"type":"Point"}
}