{
  "type": "Feature",
  "properties": {
    "addr:full":"Mechelbaan 13 Onze-lieve-vrouw-waver Antwerpen 2861",
    "addr:housenumber":"13",
    "addr:postcode":"2861",
    "addr:street":"Mechelbaan",
    "iso:country":"BE",
    "sg:address":"Mechelbaan 13",
    "sg:city":"Onze-lieve-vrouw-waver",
    "sg:orig_category":"Koerierbedrijven",
    "sg:phone":"+32 474 27 29 60",
    "sg:postcode":"2861",
    "sg:province":"Antwerpen",
    "wof:name":"Rodiwo",
    "wof:placetype":"venue"
},
  "geometry": {"coordinates":[4.5704889297,51.055015564],"type":"Point"}
}