{
  "type": "Feature",
  "properties": {
    "iso:country":"BE",
    "sg:address":"Schipstraat 30",
    "sg:city":"Puurs",
    "sg:classifiers":[
        {
            "category":"Organizations",
            "subcategory":"Labor Organization",
            "type":"Services"
        }
    ],
    "sg:phone":"+32 3 889 17 56",
    "sg:postcode":"2870",
    "sg:province":"Antwerpen",
    "sg:tags":[
        "woodworking",
        "machinery"
    ],
    "wof:name":"New Vertongen Nv",
    "wof:placetype":"venue"
},
  "geometry": {"coordinates":[4.2772698402,51.0763244629],"type":"Point"}
}