{
  "type": "Feature",
  "properties": {
    "addr:full":"Karreweg 7 Nazareth Oost-Vlaanderen 9810",
    "addr:housenumber":"7",
    "addr:postcode":"9810",
    "addr:street":"Karreweg",
    "iso:country":"BE",
    "sg:address":"Karreweg 7",
    "sg:city":"Nazareth",
    "sg:classifiers":[
        {
            "category":"Banks & Credit Unions",
            "subcategory":"Bureau De Change",
            "type":"Services"
        }
    ],
    "sg:phone":"+32 9 380 17 40",
    "sg:postcode":"9810",
    "sg:province":"Oost-Vlaanderen",
    "sg:tags":[
        "window",
        "display",
        "supply"
    ],
    "wof:name":"Motion Planet",
    "wof:placetype":"venue"
},
  "geometry": {"coordinates":[3.553745985,50.9603424072],"type":"Point"}
}