{
  "type": "Feature",
  "properties": {
    "addr:full":"Ter Borcht 6 Brasschaat Antwerpen 2930",
    "addr:housenumber":"6",
    "addr:postcode":"2930",
    "addr:street":"Borcht",
    "iso:country":"BE",
    "sg:address":"Ter Borcht 6",
    "sg:city":"Brasschaat",
    "sg:classifiers":[
        {
            "category":"Health Services",
            "subcategory":"Doctor",
            "type":"Services"
        }
    ],
    "sg:phone":"+32 3 651 47 22",
    "sg:postcode":"2930",
    "sg:province":"Antwerpen",
    "sg:tags":[
        "medicinephysicians",
        "surgeon"
    ],
    "wof:name":"De Loore I",
    "wof:placetype":"venue"
},
  "geometry": {"coordinates":[4.4719128609,51.2933731079],"type":"Point"}
}