{
  "type": "Feature",
  "properties": {
    "addr:full":"Bovenrij 84 Herentals Antwerpen 2200",
    "addr:housenumber":"84",
    "addr:postcode":"2200",
    "addr:street":"Bovenrij",
    "iso:country":"BE",
    "sg:address":"Bovenrij 84",
    "sg:city":"Herentals",
    "sg:classifiers":[
        {
            "category":"Health Services",
            "subcategory":"Dentist",
            "type":"Services"
        }
    ],
    "sg:phone":"+32 14 21 11 41",
    "sg:postcode":"2200",
    "sg:province":"Antwerpen",
    "wof:name":"Cardyn Veronique",
    "wof:placetype":"venue"
},
  "geometry": {"coordinates":[4.8370280266,51.1756591797],"type":"Point"}
}