{
  "type": "Feature",
  "properties": {
    "addr:full":"Avenue Des Franciscains 2 Sint-pieters-woluwe/woluwe-saint-pierre Bruxelles-Capitale 1150",
    "addr:housenumber":"2",
    "addr:postcode":"1150",
    "addr:street":"Avenue Des Franciscains;/",
    "iso:country":"BE",
    "sg:address":"Avenue Des Franciscains 2",
    "sg:city":"Sint-pieters-woluwe/woluwe-saint-pierre",
    "sg:orig_category":"Pain, p\u00e2tisseries and confiseries",
    "sg:phone":"+32 2 770 05 94",
    "sg:postcode":"1150",
    "sg:province":"Bruxelles-Capitale",
    "wof:name":"P\u00c2tisserie Le Gourmet",
    "wof:placetype":"venue"
},
  "geometry": {"coordinates":[4.4197878838,50.8272018433],"type":"Point"}
}