{
  "type": "Feature",
  "properties": {
    "addr:full":"Rue Emile Muselle 41 Berloz Li\u00e8ge 4257",
    "addr:housenumber":"41",
    "addr:postcode":"4257",
    "addr:street":"Rue Emile Muselle",
    "iso:country":"BE",
    "sg:address":"Rue Emile Muselle 41",
    "sg:city":"Berloz",
    "sg:classifiers":[
        {
            "category":"Cafe",
            "type":"Food & Drink"
        }
    ],
    "sg:phone":"+32 19 33 01 66",
    "sg:postcode":"4257",
    "sg:province":"Li\u00e8ge",
    "sg:tags":[
        "caf\u00e9s"
    ],
    "wof:name":"Caf\u00c9 Le Relais",
    "wof:placetype":"venue"
},
  "geometry": {"coordinates":[5.2108812332,50.7019042969],"type":"Point"}
}