{
  "type": "Feature",
  "properties": {
    "iso:country":"BE",
    "sg:address":"Leeuwerikstraat 6",
    "sg:city":"Staden",
    "sg:orig_category":"Passagiersvervoer over de weg",
    "sg:phone":"+32 51 24 08 23",
    "sg:postcode":"8840",
    "sg:province":"West-Vlaanderen",
    "wof:name":"Eva Cars",
    "wof:placetype":"venue"
},
  "geometry": {"coordinates":[3.0656569004,50.9395332336],"type":"Point"}
}