{
  "type": "Feature",
  "properties": {
    "iso:country":"BE",
    "sg:address":"Lange Akker 8",
    "sg:city":"Zele",
    "sg:classifiers":[
        {
            "category":"Food & Beverages",
            "subcategory":"Groceries & Convenience Stores",
            "type":"Retail Goods"
        }
    ],
    "sg:phone":"+32 52 45 40 03",
    "sg:postcode":"9240",
    "sg:province":"Oost-Vlaanderen",
    "sg:tags":[
        "grocer"
    ],
    "wof:name":"Can Market",
    "wof:placetype":"venue"
},
  "geometry": {"coordinates":[4.0294427872,51.0667190552],"type":"Point"}
}