{
  "type": "Feature",
  "properties": {
    "iso:country":"BE",
    "sg:address":"Rue Camille Moury 2",
    "sg:city":"Dour",
    "sg:orig_category":"M\u00e9decins and sp\u00e9cialistes",
    "sg:phone":"+32 65 65 92 29",
    "sg:postcode":"7370",
    "sg:province":"Hainaut",
    "wof:name":"Fr\u00c9d\u00c9ric Sapin",
    "wof:placetype":"venue"
},
  "geometry": {"coordinates":[3.7792859077,50.402179718],"type":"Point"}
}