{
  "type": "Feature",
  "properties": {
    "addr:full":"Nati\u00cbnlaan 72b Knokke West-Vlaanderen 8300",
    "addr:housenumber":"72b",
    "addr:postcode":"8300",
    "addr:street":"Natie\u0308Nlaan",
    "iso:country":"BE",
    "sg:address":"Nati\u00cbnlaan 72b",
    "sg:city":"Knokke",
    "sg:classifiers":[
        {
            "category":"Autos & Motor Vehicles",
            "subcategory":"Automobile Sales",
            "type":"Retail Goods"
        }
    ],
    "sg:phone":"+32 50 60 41 62",
    "sg:postcode":"8300",
    "sg:province":"West-Vlaanderen",
    "sg:tags":[
        "autos",
        "bmw",
        "v\u00e9hicules"
    ],
    "wof:name":"Auto's Cocquyt Knokke",
    "wof:placetype":"venue"
},
  "geometry": {"coordinates":[3.2885000706,51.336227417],"type":"Point"}
}