{
  "type": "Feature",
  "properties": {
    "addr:full":"All\u00e9e De N\u00e9ris 11 Namur (w\u00e9pion) Namur 5100",
    "addr:housenumber":"11",
    "addr:postcode":"5100",
    "addr:street":"Alle\u0301E De Ne\u0301Ris",
    "iso:country":"BE",
    "sg:address":"All\u00e9e De N\u00e9ris 11",
    "sg:city":"Namur (w\u00e9pion)",
    "sg:classifiers":[
        {
            "category":"Health Services",
            "subcategory":"Doctor",
            "type":"Services"
        }
    ],
    "sg:phone":"+32 81 46 16 23",
    "sg:postcode":"5100",
    "sg:province":"Namur",
    "sg:tags":[
        "medicinephysicians",
        "surgeon"
    ],
    "wof:name":"Goffioul Andr\u00e9",
    "wof:placetype":"venue"
},
  "geometry": {"coordinates":[4.8463921547,50.4222946167],"type":"Point"}
}