{
  "type": "Feature",
  "properties": {
    "iso:country":"BE",
    "sg:address":"Nieuwstraat 37",
    "sg:city":"Brussel/bruxelles",
    "sg:orig_category":"Bagage and lederwaren",
    "sg:phone":"+32 2 217 87 60",
    "sg:postcode":"1000",
    "sg:province":"Bruxelles-Capitale",
    "wof:name":"Maison Transit",
    "wof:placetype":"venue"
},
  "geometry": {"coordinates":[4.3548140526,50.8535308838],"type":"Point"}
}