{
  "type": "Feature",
  "properties": {
    "addr:full":"Grand'place 41 Saint-ghislain Hainaut 7330",
    "addr:housenumber":"41",
    "addr:postcode":"7330",
    "addr:street":"Grand'Place;Hainaut",
    "iso:country":"BE",
    "sg:address":"Grand'place 41",
    "sg:city":"Saint-ghislain",
    "sg:orig_category":"Postkantoren Verzekeringsmakelaars and experts",
    "sg:phone":"+32 65 78 43 05",
    "sg:postcode":"7330",
    "sg:province":"Hainaut",
    "wof:name":"La Poste",
    "wof:placetype":"venue"
},
  "geometry": {"coordinates":[3.8205890656,50.4484443665],"type":"Point"}
}