{
  "type": "Feature",
  "properties": {
    "iso:country":"BE",
    "sg:address":"Plockroy 55",
    "sg:city":"Meeuwen-gruitrode",
    "sg:orig_category":"Rundveehouders",
    "sg:phone":"+32 11 79 28 55",
    "sg:postcode":"3670",
    "sg:province":"Limburg",
    "wof:name":"Petrus Knevels",
    "wof:placetype":"venue"
},
  "geometry": {"coordinates":[5.5276851654,51.0825042725],"type":"Point"}
}