{
  "type": "Feature",
  "properties": {
    "addr:full":"Delfdries 6 Maarkedal Oost-Vlaanderen 9680",
    "addr:housenumber":"6",
    "addr:postcode":"9680",
    "addr:street":"Delfdries",
    "iso:country":"BE",
    "sg:address":"Delfdries 6",
    "sg:city":"Maarkedal",
    "sg:orig_category":"Instituts de beaut\u00e9",
    "sg:phone":"+32 55 30 33 53",
    "sg:postcode":"9680",
    "sg:province":"Oost-Vlaanderen",
    "wof:name":"A Vande Catsyne",
    "wof:placetype":"venue"
},
  "geometry": {"coordinates":[3.6442608833,50.7942047119],"type":"Point"}
}