{
  "type": "Feature",
  "properties": {
    "addr:full":"Kerkstraat 5 De Haan West-Vlaanderen 8420",
    "addr:housenumber":"5",
    "addr:postcode":"8420",
    "addr:street":"Kerkstraat",
    "iso:country":"BE",
    "sg:address":"Kerkstraat 5",
    "sg:city":"De Haan",
    "sg:classifiers":[
        {
            "category":"Restaurant",
            "type":"Food & Drink"
        }
    ],
    "sg:phone":"+32 50 41 17 74",
    "sg:postcode":"8420",
    "sg:province":"West-Vlaanderen",
    "wof:name":"Falstaff",
    "wof:placetype":"venue"
},
  "geometry": {"coordinates":[3.0791909695,51.3009033203],"type":"Point"}
}