{
  "type": "Feature",
  "properties": {
    "addr:full":"Rue De L\u00b4et\u00c9 214 Elsene/ixelles Bruxelles-Capitale 1050",
    "addr:housenumber":"214",
    "addr:postcode":"1050",
    "addr:street":"Rue De L\u00b4Ete\u0301",
    "iso:country":"BE",
    "sg:address":"Rue De L\u00b4et\u00c9 214",
    "sg:city":"Elsene/ixelles",
    "sg:orig_category":"Traitements param\u00e9dicaux",
    "sg:phone":"+32 2 644 30 00",
    "sg:postcode":"1050",
    "sg:province":"Bruxelles-Capitale",
    "wof:name":"F. Gradwohl",
    "wof:placetype":"venue"
},
  "geometry": {"coordinates":[4.3913578987,50.8168296814],"type":"Point"}
}