{
  "type": "Feature",
  "properties": {
    "addr:full":"Rue Du Beau-vallon 89 Namur Namur 5002",
    "addr:housenumber":"89",
    "addr:postcode":"5002",
    "addr:street":"Rue Du Beau-Vallon",
    "iso:country":"BE",
    "sg:address":"Rue Du Beau-vallon 89",
    "sg:city":"Namur",
    "sg:orig_category":"Plomberie, chauffage and installations sanitaires",
    "sg:phone":"+32 81 73 36 67",
    "sg:postcode":"5002",
    "sg:province":"Namur",
    "wof:name":"Alain Charrin",
    "wof:placetype":"venue"
},
  "geometry": {"coordinates":[4.8415927887,50.474029541],"type":"Point"}
}