{
  "type": "Feature",
  "properties": {
    "iso:country":"BE",
    "sg:address":"Rue De La Tayette 84",
    "sg:city":"Tintigny (saint-vincent)",
    "sg:classifiers":[
        {
            "category":"Farming",
            "subcategory":"Farm & Veterinary Services",
            "type":"Manufacturing & Wholesale Goods"
        }
    ],
    "sg:phone":"+32 63 44 44 54",
    "sg:postcode":"6730",
    "sg:province":"Luxembourg",
    "sg:tags":[
        "agricultural",
        "contractor"
    ],
    "wof:name":"Gillet Association",
    "wof:placetype":"venue"
},
  "geometry": {"coordinates":[5.4755330086,49.6779899597],"type":"Point"}
}