{
  "type": "Feature",
  "properties": {
    "iso:country":"BE",
    "sg:address":"Chauss\u00c9e De Valenciennes 309",
    "sg:city":"Ath",
    "sg:orig_category":"Entretien and r\u00e9parations de voitures. Stations-service and carburants",
    "sg:phone":"+32 68 28 67 67",
    "sg:postcode":"7802",
    "sg:province":"Hainaut",
    "wof:name":"Garage Fran\u00c7ois Etienne",
    "wof:placetype":"venue"
},
  "geometry": {"coordinates":[3.7527279854,50.5938110352],"type":"Point"}
}