{
  "type": "Feature",
  "properties": {
    "addr:full":"Chauss\u00e9e De Lodelinsart 44 Charleroi (gilly) Hainaut 6060",
    "addr:housenumber":"44",
    "addr:postcode":"6060",
    "addr:street":"Chausse\u0301E De Lodelinsart",
    "iso:country":"BE",
    "sg:address":"Chauss\u00e9e De Lodelinsart 44",
    "sg:city":"Charleroi (gilly)",
    "sg:classifiers":[
        {
            "category":"Food & Beverages",
            "subcategory":"Fruits & Vegetables",
            "type":"Retail Goods"
        }
    ],
    "sg:phone":"+32 71 41 52 14",
    "sg:postcode":"6060",
    "sg:province":"Hainaut",
    "sg:tags":[
        "-"
    ],
    "wof:name":"Fruital",
    "wof:placetype":"venue"
},
  "geometry": {"coordinates":[4.4880981445,50.4251937866],"type":"Point"}
}