{
  "type": "Feature",
  "properties": {
    "addr:full":"Kerkplaats 2 Tervuren Vlaams-Brabant 3080",
    "addr:housenumber":"2",
    "addr:postcode":"3080",
    "addr:street":"Kerkplaats",
    "iso:country":"BE",
    "sg:address":"Kerkplaats 2",
    "sg:city":"Tervuren",
    "sg:classifiers":[
        {
            "category":"Restaurant",
            "type":"Food & Drink"
        }
    ],
    "sg:phone":"+32 2 768 16 39",
    "sg:postcode":"3080",
    "sg:province":"Vlaams-Brabant",
    "wof:name":"De Quabrie",
    "wof:placetype":"venue"
},
  "geometry": {"coordinates":[4.5520710945,50.8168296814],"type":"Point"}
}