{
  "type": "Feature",
  "properties": {
    "addr:full":"Rue Du Radium 12 Bruxelles (schaerbeek) Bruxelles-Capitale 1030",
    "addr:housenumber":"12",
    "addr:postcode":"1030",
    "addr:street":"Rue Du Radium",
    "iso:country":"BE",
    "sg:address":"Rue Du Radium 12",
    "sg:city":"Bruxelles (schaerbeek)",
    "sg:classifiers":[
        {
            "category":"Professional",
            "subcategory":"Art Services",
            "type":"Services"
        }
    ],
    "sg:phone":"+32 2 733 30 03",
    "sg:postcode":"1030",
    "sg:province":"Bruxelles-Capitale",
    "sg:tags":[
        "graphic",
        "designer"
    ],
    "wof:name":"Marmelade Scrl",
    "wof:placetype":"venue"
},
  "geometry": {"coordinates":[4.3907060623,50.8524703979],"type":"Point"}
}