{
  "type": "Feature",
  "properties": {
    "iso:country":"BE",
    "sg:address":"Wakkensteenweg 13",
    "sg:city":"Wielsbeke",
    "sg:classifiers":[
        {
            "category":"Cafe",
            "type":"Food & Drink"
        }
    ],
    "sg:phone":"+32 56 61 39 23",
    "sg:postcode":"8710",
    "sg:province":"West-Vlaanderen",
    "sg:tags":[
        "caf\u00e9s"
    ],
    "wof:name":"Caf\u00c9 De Cadi",
    "wof:placetype":"venue"
},
  "geometry": {"coordinates":[3.3966341019,50.9117393494],"type":"Point"}
}