{
  "type": "Feature",
  "properties": {
    "iso:country":"BE",
    "sg:address":"Rue Joseph Wettinck 17",
    "sg:city":"Seraing",
    "sg:orig_category":"Bijouteries and horlogeries",
    "sg:phone":"+32 4 233 91 46",
    "sg:postcode":"4101",
    "sg:province":"Li\u00e8ge",
    "wof:name":"Henri Skrzypek",
    "wof:placetype":"venue"
},
  "geometry": {"coordinates":[5.5029010773,50.6156196594],"type":"Point"}
}