{
  "type": "Feature",
  "properties": {
    "addr:full":"Rue Albert I 114 Mettet Namur 5640",
    "addr:housenumber":"114",
    "addr:postcode":"5640",
    "addr:street":"Rue Albert I",
    "iso:country":"BE",
    "sg:address":"Rue Albert I 114",
    "sg:city":"Mettet",
    "sg:classifiers":[
        {
            "category":"Retail",
            "subcategory":"Auto Repair",
            "type":"Services"
        }
    ],
    "sg:phone":"+32 71 72 72 46",
    "sg:postcode":"5640",
    "sg:province":"Namur",
    "sg:tags":[
        "garage"
    ],
    "wof:name":"Hubert & Fils",
    "wof:placetype":"venue"
},
  "geometry": {"coordinates":[4.6558938026,50.3269386292],"type":"Point"}
}