{
  "type": "Feature",
  "properties": {
    "iso:country":"BE",
    "sg:address":"Regentiestraat 180",
    "sg:city":"Welle",
    "sg:orig_category":"Miscellaneous Products",
    "sg:phone":"+32 53 68 15 80",
    "sg:postcode":"9473",
    "sg:province":"Oost-Vlaanderen",
    "wof:name":"Chrisline Bvba",
    "wof:placetype":"venue"
},
  "geometry": {"coordinates":[4.0549378395,50.8989448547],"type":"Point"}
}