{
  "type": "Feature",
  "properties": {
    "iso:country":"BE",
    "sg:address":"Kronkelbeekstraat 34",
    "sg:city":"Schuiferskapelle",
    "sg:orig_category":"Loodgieterij, verwarming and sanitaire installaties",
    "sg:phone":"+32 51 40 71 38",
    "sg:postcode":"8700",
    "sg:province":"West-Vlaanderen",
    "wof:name":"Demeco",
    "wof:placetype":"venue"
},
  "geometry": {"coordinates":[3.340307951,51.0330238342],"type":"Point"}
}