{
  "type": "Feature",
  "properties": {
    "addr:full":"Eikenstraat 53 Rumst Antwerpen 2840",
    "addr:housenumber":"53",
    "addr:postcode":"2840",
    "addr:street":"Eikenstraat",
    "iso:country":"BE",
    "sg:address":"Eikenstraat 53",
    "sg:city":"Rumst",
    "sg:orig_category":"S\u00e9curit\u00e9 sociale",
    "sg:phone":"+32 3 888 74 56",
    "sg:postcode":"2840",
    "sg:province":"Antwerpen",
    "wof:name":"Christelijke Mutualiteit",
    "wof:placetype":"venue"
},
  "geometry": {"coordinates":[4.4115319252,51.1033058167],"type":"Point"}
}