{
  "type": "Feature",
  "properties": {
    "addr:full":"Rue De Pr\u00c9e 5ba Mettet Namur 5640",
    "addr:housenumber":"5ba",
    "addr:postcode":"5640",
    "addr:street":"Rue De Pre\u0301E",
    "iso:country":"BE",
    "sg:address":"Rue De Pr\u00c9e 5ba",
    "sg:city":"Mettet",
    "sg:orig_category":"D\u00e9molition d\u00b4immeubles and terrassements",
    "sg:phone":"+32 71 72 70 73",
    "sg:postcode":"5640",
    "sg:province":"Namur",
    "wof:name":"Deravet",
    "wof:placetype":"venue"
},
  "geometry": {"coordinates":[4.6049380302,50.3244781494],"type":"Point"}
}