{
  "type": "Feature",
  "properties": {
    "iso:country":"BE",
    "sg:address":"Jan Van Rijswijcklaan 154",
    "sg:city":"Antwerpen",
    "sg:classifiers":[
        {
            "category":"Professional",
            "subcategory":"Testing Lab",
            "type":"Services"
        }
    ],
    "sg:phone":"+32 3 238 28 58",
    "sg:postcode":"2018",
    "sg:province":"Antwerpen",
    "sg:tags":[
        "chemist"
    ],
    "wof:name":"De Singel",
    "wof:placetype":"venue"
},
  "geometry": {"coordinates":[4.4024348259,51.1945457458],"type":"Point"}
}