{
  "type": "Feature",
  "properties": {
    "addr:full":"Gentsesteenweg 116 Dendermonde Oost-Vlaanderen 9200",
    "addr:housenumber":"116",
    "addr:postcode":"9200",
    "addr:street":"Gentsesteenweg;Oost-Vlaanderen",
    "iso:country":"BE",
    "sg:address":"Gentsesteenweg 116",
    "sg:city":"Dendermonde",
    "sg:classifiers":[
        {
            "category":"Health Services",
            "subcategory":"Doctor",
            "type":"Services"
        }
    ],
    "sg:phone":"+32 52 21 33 01",
    "sg:postcode":"9200",
    "sg:province":"Oost-Vlaanderen",
    "sg:tags":[
        "medicinephysicians",
        "surgeon"
    ],
    "wof:name":"Lorr\u00e9 A",
    "wof:placetype":"venue"
},
  "geometry": {"coordinates":[4.0842399597,51.0324821472],"type":"Point"}
}