{
  "type": "Feature",
  "properties": {
    "iso:country":"BE",
    "sg:address":"Avenue Des Combattants 19",
    "sg:city":"Ottignies-louvain-la-neuve",
    "sg:orig_category":"V\u00e9t\u00e9rinaires",
    "sg:phone":"+32 10 40 17 71",
    "sg:postcode":"1340",
    "sg:province":"Brabant Wallon",
    "wof:name":"Jean-philippe Meunier",
    "wof:placetype":"venue"
},
  "geometry": {"coordinates":[4.565554142,50.6641044617],"type":"Point"}
}