{
  "type": "Feature",
  "properties": {
    "addr:full":"Langemunt 25-27 Gent Oost-Vlaanderen 9000",
    "addr:housenumber":"25-27",
    "addr:postcode":"9000",
    "addr:street":"Langemunt;Oost-Vlaanderen",
    "iso:country":"BE",
    "sg:address":"Langemunt 25-27",
    "sg:city":"Gent",
    "sg:orig_category":"Kleding Textiel",
    "sg:phone":"+32 9 223 88 80",
    "sg:postcode":"9000",
    "sg:province":"Oost-Vlaanderen",
    "wof:name":"Veritas",
    "wof:placetype":"venue"
},
  "geometry": {"coordinates":[3.7232201099,51.0564537048],"type":"Point"}
}