{
  "type": "Feature",
  "properties": {
    "iso:country":"BE",
    "sg:address":"Ossegemstraat 102",
    "sg:city":"Meise",
    "sg:orig_category":"Mat\u00e9riel m\u00e9dical and orthop\u00e9dique and proth\u00e8ses Fab",
    "sg:phone":"+32 2 269 65 52",
    "sg:postcode":"1861",
    "sg:province":"Vlaams-Brabant",
    "wof:name":"Labo De Ruyck",
    "wof:placetype":"venue"
},
  "geometry": {"coordinates":[4.3194279671,50.9650344849],"type":"Point"}
}