{
  "type": "Feature",
  "properties": {
    "iso:country":"BE",
    "sg:address":"Rue J Decarpentrie 11",
    "sg:city":"Brunehaut",
    "sg:orig_category":"Aanleg van wegen, sportterreinen and vliegvelden Afbraak- and draineerwerken",
    "sg:phone":"+32 69 34 66 87",
    "sg:postcode":"7620",
    "sg:province":"Hainaut",
    "wof:name":"Travaux Brunehaut",
    "wof:placetype":"venue"
},
  "geometry": {"coordinates":[3.4089579582,50.5127105713],"type":"Point"}
}