{
  "type": "Feature",
  "properties": {
    "addr:full":"Eksaardebaan 27 Lokeren Oost-Vlaanderen 9160",
    "addr:housenumber":"27",
    "addr:postcode":"9160",
    "addr:street":"Eksaardebaan",
    "iso:country":"BE",
    "sg:address":"Eksaardebaan 27",
    "sg:city":"Lokeren",
    "sg:orig_category":"Rundveehouders",
    "sg:phone":"+32 9 348 65 41",
    "sg:postcode":"9160",
    "sg:province":"Oost-Vlaanderen",
    "wof:name":"Guido De Waele",
    "wof:placetype":"venue"
},
  "geometry": {"coordinates":[3.9629690647,51.115196228],"type":"Point"}
}