{
  "type": "Feature",
  "properties": {
    "addr:full":"Avenue Champ De Bataille 531 Mons (jemappes) Hainaut 7012",
    "addr:housenumber":"531",
    "addr:postcode":"7012",
    "addr:street":"Avenue Champ De Bataille",
    "iso:country":"BE",
    "sg:address":"Avenue Champ De Bataille 531",
    "sg:city":"Mons (jemappes)",
    "sg:classifiers":[
        {
            "category":"Building & Trades",
            "subcategory":"Construction",
            "type":"Services"
        }
    ],
    "sg:phone":"+32 65 82 49 04",
    "sg:postcode":"7012",
    "sg:province":"Hainaut",
    "sg:tags":[
        "installation",
        "-",
        "central",
        "heating"
    ],
    "wof:name":"Entreprise F & F",
    "wof:placetype":"venue"
},
  "geometry": {"coordinates":[3.8894600868,50.4481964111],"type":"Point"}
}