{
  "type": "Feature",
  "properties": {
    "addr:full":"Retiesebaan 17 Kasterlee Antwerpen 2460",
    "addr:housenumber":"17",
    "addr:postcode":"2460",
    "addr:street":"Retiesebaan",
    "iso:country":"BE",
    "sg:address":"Retiesebaan 17",
    "sg:city":"Kasterlee",
    "sg:classifiers":[
        {
            "category":"Shopping",
            "subcategory":"Clothing, Apparel, & Fashions",
            "type":"Retail Goods"
        }
    ],
    "sg:phone":"+32 14 85 01 52",
    "sg:postcode":"2460",
    "sg:province":"Antwerpen",
    "sg:tags":[
        "-",
        "clothing",
        "child"
    ],
    "wof:name":"Marjolein",
    "wof:placetype":"venue"
},
  "geometry": {"coordinates":[4.9706439972,51.241355896],"type":"Point"}
}