{
  "type": "Feature",
  "properties": {
    "iso:country":"BE",
    "sg:address":"Lage Kaart 360",
    "sg:city":"Brasschaat",
    "sg:classifiers":[
        {
            "category":"Cafe",
            "type":"Food & Drink"
        }
    ],
    "sg:phone":"+32 3 651 95 79",
    "sg:postcode":"2930",
    "sg:province":"Antwerpen",
    "sg:tags":[
        "caf\u00e9s"
    ],
    "wof:name":"Caf\u00c9 Ivoren Bal",
    "wof:placetype":"venue"
},
  "geometry": {"coordinates":[4.4844441414,51.3035202026],"type":"Point"}
}