{
  "type": "Feature",
  "properties": {
    "iso:country":"BE",
    "sg:address":"Rue Franklin 66",
    "sg:city":"Brussel/bruxelles",
    "sg:classifiers":[
        {
            "category":"Fast Food",
            "type":"Food & Drink"
        }
    ],
    "sg:phone":"+32 2 734 71 31",
    "sg:postcode":"1000",
    "sg:province":"Bruxelles-Capitale",
    "sg:tags":[
        "\u00c0",
        "restaurants",
        "emporter",
        "restaurant"
    ],
    "wof:name":"Bambou Garden",
    "wof:placetype":"venue"
},
  "geometry": {"coordinates":[4.3871388435,50.8455200195],"type":"Point"}
}