{
  "type": "Feature",
  "properties": {
    "iso:country":"BE",
    "sg:address":"Zwarteindestraat 51",
    "sg:city":"Nieuwerkerken",
    "sg:orig_category":"Woningbouw",
    "sg:phone":"+32 11 31 40 59",
    "sg:postcode":"3850",
    "sg:province":"Limburg",
    "wof:name":"A.g.v. Bouwwerken",
    "wof:placetype":"venue"
},
  "geometry": {"coordinates":[5.2414541245,50.8884811401],"type":"Point"}
}