{
  "type": "Feature",
  "properties": {
    "addr:full":"Linterseweg 44a Zoutleeuw (budingen) Vlaams-Brabant 3440",
    "addr:housenumber":"44a",
    "addr:postcode":"3440",
    "addr:street":"Linterseweg",
    "iso:country":"BE",
    "sg:address":"Linterseweg 44a",
    "sg:city":"Zoutleeuw (budingen)",
    "sg:classifiers":[
        {
            "category":"Health Services",
            "subcategory":"Health Practitioner",
            "type":"Services"
        }
    ],
    "sg:phone":"+32 11 58 15 89",
    "sg:postcode":"3440",
    "sg:province":"Vlaams-Brabant",
    "sg:tags":[
        "physiotherapist"
    ],
    "wof:name":"Raskin C",
    "wof:placetype":"venue"
},
  "geometry": {"coordinates":[5.0867671967,50.8614730835],"type":"Point"}
}