{
  "type": "Feature",
  "properties": {
    "addr:full":"Berenhoek 18 Haaltert Oost-Vlaanderen 9450",
    "addr:housenumber":"18",
    "addr:postcode":"9450",
    "addr:street":"Berenhoek",
    "iso:country":"BE",
    "sg:address":"Berenhoek 18",
    "sg:city":"Haaltert",
    "sg:orig_category":"Eleveurs de bovins",
    "sg:phone":"+32 53 62 41 73",
    "sg:postcode":"9450",
    "sg:province":"Oost-Vlaanderen",
    "wof:name":"Dirk Blondeel",
    "wof:placetype":"venue"
},
  "geometry": {"coordinates":[3.9579250813,50.8742141724],"type":"Point"}
}