{
  "type": "Feature",
  "properties": {
    "iso:country":"BE",
    "sg:address":"Kruisbaan 12",
    "sg:city":"Grobbendonk",
    "sg:orig_category":"Gespecialiseerde residenti\u00eble bouw",
    "sg:phone":"+32 14 51 74 46",
    "sg:postcode":"2280",
    "sg:province":"Antwerpen",
    "wof:name":"Ruddie Moens",
    "wof:placetype":"venue"
},
  "geometry": {"coordinates":[4.7178168297,51.1983909607],"type":"Point"}
}