{
  "type": "Feature",
  "properties": {
    "addr:full":"Chauss\u00e9e De Waterloo 14 Bruxelles (saint-gilles) Bruxelles-Capitale 1060",
    "addr:housenumber":"14",
    "addr:postcode":"1060",
    "addr:street":"Chausse\u0301E De Waterloo",
    "iso:country":"BE",
    "sg:address":"Chauss\u00e9e De Waterloo 14",
    "sg:city":"Bruxelles (saint-gilles)",
    "sg:classifiers":[
        {
            "category":"Bars & Pubs",
            "type":"Food & Drink"
        }
    ],
    "sg:phone":"+32 2 534 75 11",
    "sg:postcode":"1060",
    "sg:province":"Bruxelles-Capitale",
    "wof:name":"New Europe",
    "wof:placetype":"venue"
},
  "geometry": {"coordinates":[4.3450479507,50.8321723938],"type":"Point"}
}