{
  "type": "Feature",
  "properties": {
    "addr:full":"Les Trois Bonniers 36 Namur Namur 5020",
    "addr:housenumber":"36",
    "addr:postcode":"5020",
    "iso:country":"BE",
    "sg:address":"Les Trois Bonniers 36",
    "sg:city":"Namur",
    "sg:classifiers":[
        {
            "category":"Personal",
            "subcategory":"Beauty Salon",
            "type":"Services"
        }
    ],
    "sg:phone":"+32 81 21 39 58",
    "sg:postcode":"5020",
    "sg:province":"Namur",
    "sg:tags":[
        "de",
        "coiffure"
    ],
    "wof:name":"Salvator Monteleone",
    "wof:placetype":"venue"
},
  "geometry": {"coordinates":[4.7952418327,50.4352035522],"type":"Point"}
}