{
  "type": "Feature",
  "properties": {
    "addr:full":"Chauss\u00c9e Paul Houtart 296 La Louvi\u00c8re Hainaut 7110",
    "addr:housenumber":"296",
    "addr:postcode":"7110",
    "addr:street":"Chausse\u0301E Paul Houtart",
    "iso:country":"BE",
    "sg:address":"Chauss\u00c9e Paul Houtart 296",
    "sg:city":"La Louvi\u00c8re",
    "sg:orig_category":"Boucheries",
    "sg:phone":"+32 64 22 80 32",
    "sg:postcode":"7110",
    "sg:province":"Hainaut",
    "wof:name":"Boucherie Du Parc",
    "wof:placetype":"venue"
},
  "geometry": {"coordinates":[4.1571221352,50.4869918823],"type":"Point"}
}