{
  "type": "Feature",
  "properties": {
    "iso:country":"BE",
    "sg:address":"Hoogweg 87",
    "sg:city":"Kluisbergen (ruien)",
    "sg:classifiers":[
        {
            "category":"Health Services",
            "subcategory":"Health Practitioner",
            "type":"Services"
        }
    ],
    "sg:phone":"+32 55 38 74 84",
    "sg:postcode":"9690",
    "sg:province":"Oost-Vlaanderen",
    "sg:tags":[
        "physiotherapist"
    ],
    "wof:name":"Allinckx Anouchka",
    "wof:placetype":"venue"
},
  "geometry": {"coordinates":[3.4889171124,50.7688865662],"type":"Point"}
}