{
  "type": "Feature",
  "properties": {
    "addr:full":"Roeselaarsestraat 626 Izegem West-Vlaanderen 8870",
    "addr:housenumber":"626",
    "addr:postcode":"8870",
    "addr:street":"Roeselaarsestraat",
    "iso:country":"BE",
    "sg:address":"Roeselaarsestraat 626",
    "sg:city":"Izegem",
    "sg:orig_category":"Drogueries",
    "sg:phone":"+32 51 30 30 31",
    "sg:postcode":"8870",
    "sg:province":"West-Vlaanderen",
    "wof:name":"Gabriel Delarue",
    "wof:placetype":"venue"
},
  "geometry": {"coordinates":[3.1837110519,50.9275360107],"type":"Point"}
}