{
  "type": "Feature",
  "properties": {
    "addr:full":"Molenstraat 174 Kaprijke Oost-Vlaanderen 9970",
    "addr:housenumber":"174",
    "addr:postcode":"9970",
    "addr:street":"Molenstraat",
    "iso:country":"BE",
    "sg:address":"Molenstraat 174",
    "sg:city":"Kaprijke",
    "sg:orig_category":"Dranken",
    "sg:phone":"+32 9 379 81 78",
    "sg:postcode":"9970",
    "sg:province":"Oost-Vlaanderen",
    "wof:name":"Goethals & Zoon",
    "wof:placetype":"venue"
},
  "geometry": {"coordinates":[3.5943319798,51.214931488],"type":"Point"}
}