{
  "type": "Feature",
  "properties": {
    "addr:full":"Rue De Forri\u00c8re 180 Courcelles Hainaut 6180",
    "addr:housenumber":"180",
    "addr:postcode":"6180",
    "addr:street":"Rue De Forrie\u0300Re",
    "iso:country":"BE",
    "sg:address":"Rue De Forri\u00c8re 180",
    "sg:city":"Courcelles",
    "sg:orig_category":"Artsen and specialisten",
    "sg:phone":"+32 71 45 00 41",
    "sg:postcode":"6180",
    "sg:province":"Hainaut",
    "wof:name":"Yves Despas",
    "wof:placetype":"venue"
},
  "geometry": {"coordinates":[4.3618969917,50.4466171265],"type":"Point"}
}