{
  "type": "Feature",
  "properties": {
    "iso:country":"BE",
    "sg:address":"Romershovenstraat 3",
    "sg:city":"Hoeselt",
    "sg:orig_category":"Fruits and l\u00e9gumes. Producteurs de fruits",
    "sg:phone":"+32 89 51 47 30",
    "sg:postcode":"3730",
    "sg:province":"Limburg",
    "wof:name":"Huis Raskin Gebrs",
    "wof:placetype":"venue"
},
  "geometry": {"coordinates":[5.4634389877,50.8505783081],"type":"Point"}
}