{
  "type": "Feature",
  "properties": {
    "addr:full":"Magdalenastraat 36 Kontich Antwerpen 2550",
    "addr:housenumber":"36",
    "addr:postcode":"2550",
    "addr:street":"Magdalenastraat",
    "iso:country":"BE",
    "sg:address":"Magdalenastraat 36",
    "sg:city":"Kontich",
    "sg:classifiers":[
        {
            "category":"Social Services",
            "subcategory":"Child Care",
            "type":"Services"
        }
    ],
    "sg:phone":"+32 3 457 39 69",
    "sg:postcode":"2550",
    "sg:province":"Antwerpen",
    "sg:tags":[
        "baby",
        "nursery",
        "day",
        "sitting"
    ],
    "wof:name":"Dienst Opvanggezinnen Dommeltje",
    "wof:placetype":"venue"
},
  "geometry": {"coordinates":[4.4473180771,51.1341590881],"type":"Point"}
}