{
  "type": "Feature",
  "properties": {
    "iso:country":"BE",
    "sg:address":"Rue De Ganshoren 25",
    "sg:city":"Koekelberg/koekelberg",
    "sg:orig_category":"Installation \u00e9lectrique r\u00e9sidentielle",
    "sg:phone":"+32 2 414 22 43",
    "sg:postcode":"1081",
    "sg:province":"Bruxelles-Capitale",
    "wof:name":"Ferdinand De Puydt",
    "wof:placetype":"venue"
},
  "geometry": {"coordinates":[4.3296041489,50.8596878052],"type":"Point"}
}