{
  "type": "Feature",
  "properties": {
    "iso:country":"BE",
    "sg:address":"Rue Croix Maron 110",
    "sg:city":"Philippeville (surice)",
    "sg:classifiers":[
        {
            "category":"Sports & Exercise",
            "subcategory":"Stables",
            "type":"Entertainment"
        }
    ],
    "sg:phone":"+32 82 67 83 98",
    "sg:postcode":"5600",
    "sg:province":"Namur",
    "sg:tags":[
        "riding",
        "school"
    ],
    "wof:name":"Le Fiacre",
    "wof:placetype":"venue"
},
  "geometry": {"coordinates":[4.6906299591,50.1826515198],"type":"Point"}
}