{
  "type": "Feature",
  "properties": {
    "iso:country":"BE",
    "sg:address":"Molstenstraat 20",
    "sg:city":"Oostrozebeke",
    "sg:orig_category":"Woningbouw",
    "sg:phone":"+32 56 66 85 46",
    "sg:postcode":"8780",
    "sg:province":"West-Vlaanderen",
    "wof:name":"Luc Tieberghien",
    "wof:placetype":"venue"
},
  "geometry": {"coordinates":[3.3488759995,50.9375915527],"type":"Point"}
}