{
  "type": "Feature",
  "properties": {
    "addr:full":"Rue St. Martin 119 Tournai Hainaut 7500",
    "addr:housenumber":"119",
    "addr:postcode":"7500",
    "addr:street":"Rue St. Martin",
    "iso:country":"BE",
    "sg:address":"Rue St. Martin 119",
    "sg:city":"Tournai",
    "sg:orig_category":"Krantenwinkels Rookartikelen",
    "sg:phone":"+32 69 23 42 08",
    "sg:postcode":"7500",
    "sg:province":"Hainaut",
    "wof:name":"Presse-shop",
    "wof:placetype":"venue"
},
  "geometry": {"coordinates":[3.3844931126,50.6028022766],"type":"Point"}
}