{
  "type": "Feature",
  "properties": {
    "addr:full":"Grand'rue 278 Charleroi Hainaut 6000",
    "addr:housenumber":"278",
    "addr:postcode":"6000",
    "addr:street":"Grand'Rue;Hainaut",
    "iso:country":"BE",
    "sg:address":"Grand'rue 278",
    "sg:city":"Charleroi",
    "sg:orig_category":"Drukkerijen and copyshops",
    "sg:phone":"+32 71 41 78 87",
    "sg:postcode":"6000",
    "sg:province":"Hainaut",
    "wof:name":"Christian Pinera-gonzalez",
    "wof:placetype":"venue"
},
  "geometry": {"coordinates":[4.4527988434,50.4181480408],"type":"Point"}
}