{
  "type": "Feature",
  "properties": {
    "iso:country":"BE",
    "sg:address":"Beckhofstraat 50",
    "sg:city":"Torhout",
    "sg:orig_category":"Boekhouders",
    "sg:postcode":"8820",
    "sg:province":"West-Vlaanderen",
    "wof:name":"Karel Defoirdt",
    "wof:placetype":"venue"
},
  "geometry": {"coordinates":[3.1018350124,51.0568580627],"type":"Point"}
}