{
  "type": "Feature",
  "properties": {
    "iso:country":"BE",
    "sg:address":"Gentsesteenweg 1311",
    "sg:city":"Sint-agatha-berchem/berchem-sainte-agathe",
    "sg:orig_category":"Juwelen and horloges",
    "sg:phone":"+32 2 465 47 34",
    "sg:postcode":"1082",
    "sg:province":"Bruxelles-Capitale",
    "wof:name":"Avd-diamonds Jewelry",
    "wof:placetype":"venue"
},
  "geometry": {"coordinates":[4.2922019958,50.8694229126],"type":"Point"}
}