{
  "type": "Feature",
  "properties": {
    "addr:full":"Brugstraat 24 Boutersem Vlaams-Brabant 3370",
    "addr:housenumber":"24",
    "addr:postcode":"3370",
    "addr:street":"Brugstraat",
    "iso:country":"BE",
    "sg:address":"Brugstraat 24",
    "sg:city":"Boutersem",
    "sg:orig_category":"Huwelijks- and Relatiebureaus",
    "sg:phone":"+32 16 72 01 90",
    "sg:postcode":"3370",
    "sg:province":"Vlaams-Brabant",
    "wof:name":"Happy People",
    "wof:placetype":"venue"
},
  "geometry": {"coordinates":[4.8315048218,50.8373641968],"type":"Point"}
}