{
  "type": "Feature",
  "properties": {
    "addr:full":"Rue Th\u00c9odore Verhaegen 121 Sint-gillis/saint-gilles Bruxelles-Capitale 1060",
    "addr:housenumber":"121",
    "addr:postcode":"1060",
    "addr:street":"Rue The\u0301Odore Verhaegen",
    "iso:country":"BE",
    "sg:address":"Rue Th\u00c9odore Verhaegen 121",
    "sg:city":"Sint-gillis/saint-gilles",
    "sg:orig_category":"Epiceries. Alimentation sp\u00e9cialis\u00e9e",
    "sg:phone":"+32 2 534 49 94",
    "sg:postcode":"1060",
    "sg:province":"Bruxelles-Capitale",
    "wof:name":"Maison Mercado Portugues",
    "wof:placetype":"venue"
},
  "geometry": {"coordinates":[4.3388719559,50.8295783997],"type":"Point"}
}