{
  "type": "Feature",
  "properties": {
    "addr:full":"Chauss\u00c9e Charlemagne 70 Thimister-clermont Li\u00e8ge 4890",
    "addr:housenumber":"70",
    "addr:postcode":"4890",
    "addr:street":"Chausse\u0301E Charlemagne",
    "iso:country":"BE",
    "sg:address":"Chauss\u00c9e Charlemagne 70",
    "sg:city":"Thimister-clermont",
    "sg:orig_category":"Rundveehouders",
    "sg:phone":"+32 87 44 50 84",
    "sg:postcode":"4890",
    "sg:province":"Li\u00e8ge",
    "wof:name":"Lucien Somja",
    "wof:placetype":"venue"
},
  "geometry": {"coordinates":[5.8640408516,50.6469573975],"type":"Point"}
}