{
  "type": "Feature",
  "properties": {
    "iso:country":"BE",
    "sg:address":"Rodenbachlaan 42",
    "sg:city":"Zoersel",
    "sg:orig_category":"Aanleg van opritten and terreinen bij woningen Industri\u00eble and commerci\u00eble bouw Plaatsen van vloer- ",
    "sg:phone":"+32 3 384 29 05",
    "sg:postcode":"2980",
    "sg:province":"Antwerpen",
    "wof:name":"De Pauw",
    "wof:placetype":"venue"
},
  "geometry": {"coordinates":[4.652572155,51.2621269226],"type":"Point"}
}