{
  "type": "Feature",
  "properties": {
    "addr:full":"Rue Haute 305 Bruxelles Bruxelles-Capitale 1000",
    "addr:housenumber":"305",
    "addr:postcode":"1000",
    "addr:street":"Rue Haute",
    "iso:country":"BE",
    "sg:address":"Rue Haute 305",
    "sg:city":"Bruxelles",
    "sg:classifiers":[
        {
            "category":"Bakery",
            "type":"Food & Drink"
        }
    ],
    "sg:phone":"+32 2 511 60 44",
    "sg:postcode":"1000",
    "sg:province":"Bruxelles-Capitale",
    "sg:tags":[
        "confectioner",
        "baker"
    ],
    "wof:name":"Didion A",
    "wof:placetype":"venue"
},
  "geometry": {"coordinates":[4.3469772339,50.835521698],"type":"Point"}
}