{
  "type": "Feature",
  "properties": {
    "addr:full":"R C\u00e9sar Franck 52 Bruxelles Bruxelles-Capitale 1050",
    "addr:housenumber":"52",
    "addr:postcode":"1050",
    "iso:country":"BE",
    "sg:address":"R C\u00e9sar Franck 52",
    "sg:city":"Bruxelles",
    "sg:classifiers":[
        {
            "category":"Professional",
            "type":"Services"
        }
    ],
    "sg:phone":"+32 2 648 50 36",
    "sg:postcode":"1050",
    "sg:province":"Bruxelles-Capitale",
    "sg:tags":[
        "transport",
        "road"
    ],
    "wof:name":"Droeven Jim Sprl",
    "wof:placetype":"venue"
},
  "geometry": {"coordinates":[4.3910150528,50.8184165955],"type":"Point"}
}