{
  "type": "Feature",
  "properties": {
    "iso:country":"BE",
    "sg:address":"Paul Wemaerestraat 24",
    "sg:city":"Sint-pieters-woluwe/woluwe-saint-pierre",
    "sg:orig_category":"Marktonderzoekbureaus",
    "sg:phone":"+32 2 770 35 38",
    "sg:postcode":"1150",
    "sg:province":"Bruxelles-Capitale",
    "wof:name":"Research Solution",
    "wof:placetype":"venue"
},
  "geometry": {"coordinates":[4.43024683,50.8350715637],"type":"Point"}
}