{
  "type": "Feature",
  "properties": {
    "addr:full":"Steenweg Op Turnhout 125 Oud-turnhout Antwerpen 2360",
    "addr:housenumber":"125",
    "addr:postcode":"2360",
    "addr:street":"Steenweg Op Turnhout",
    "iso:country":"BE",
    "sg:address":"Steenweg Op Turnhout 125",
    "sg:city":"Oud-turnhout",
    "sg:classifiers":[
        {
            "category":"Restaurant",
            "type":"Food & Drink"
        }
    ],
    "sg:phone":"+32 14 45 39 16",
    "sg:postcode":"2360",
    "sg:province":"Antwerpen",
    "wof:name":"\u00b4t Krokantje",
    "wof:placetype":"venue"
},
  "geometry": {"coordinates":[4.9697518349,51.3208656311],"type":"Point"}
}