{
  "type": "Feature",
  "properties": {
    "addr:full":"Rue D'angleterre 57 Sint-gillis/saint-gilles Bruxelles-Capitale 1060",
    "addr:housenumber":"57",
    "addr:postcode":"1060",
    "addr:street":"Rue D'Angleterre",
    "iso:country":"BE",
    "sg:address":"Rue D'angleterre 57",
    "sg:city":"Sint-gillis/saint-gilles",
    "sg:orig_category":"Mus\u00e9es and patrimoine culturel",
    "sg:phone":"+32 2 533 32 11",
    "sg:postcode":"1060",
    "sg:province":"Bruxelles-Capitale",
    "wof:name":"Musee Oiseaux Lig.braille",
    "wof:placetype":"venue"
},
  "geometry": {"coordinates":[4.3408021927,50.8347091675],"type":"Point"}
}