{
  "type": "Feature",
  "properties": {
    "iso:country":"BE",
    "sg:address":"Lodewijk De Raetstraat 13",
    "sg:city":"Gent",
    "sg:orig_category":"Sportclubs",
    "sg:phone":"+32 9 222 63 56",
    "sg:postcode":"9051",
    "sg:province":"Oost-Vlaanderen",
    "wof:name":"Flanders Motor Club",
    "wof:placetype":"venue"
},
  "geometry": {"coordinates":[3.6676499844,51.0275497437],"type":"Point"}
}