{
  "type": "Feature",
  "properties": {
    "addr:full":"K\u00f6nig-albert-all\u00e9e 30-32 Eupen Li\u00e8ge 4700",
    "addr:postcode":"30-32;4700",
    "iso:country":"BE",
    "sg:address":"K\u00f6nig-albert-all\u00e9e 30-32",
    "sg:city":"Eupen",
    "sg:classifiers":[
        {
            "category":"Professional",
            "subcategory":"Management & Consulting",
            "type":"Services"
        }
    ],
    "sg:phone":"+32 87 55 31 48",
    "sg:postcode":"4700",
    "sg:province":"Li\u00e8ge",
    "sg:tags":[
        "tax-consultants"
    ],
    "wof:name":"Hennen H",
    "wof:placetype":"venue"
},
  "geometry": {"coordinates":[6.02039814,50.6304855347],"type":"Point"}
}