{
  "type": "Feature",
  "properties": {
    "addr:full":"Rue Gilles-savoie 20 Brunehaut Hainaut 7622",
    "addr:housenumber":"20",
    "addr:postcode":"7622",
    "addr:street":"Rue Gilles-Savoie",
    "iso:country":"BE",
    "sg:address":"Rue Gilles-savoie 20",
    "sg:city":"Brunehaut",
    "sg:orig_category":"Producteurs de fruits",
    "sg:phone":"+32 69 34 53 23",
    "sg:postcode":"7622",
    "sg:province":"Hainaut",
    "wof:name":"Jean-loup Dumont",
    "wof:placetype":"venue"
},
  "geometry": {"coordinates":[3.4469599724,50.5208015442],"type":"Point"}
}