{
  "type": "Feature",
  "properties": {
    "iso:country":"BE",
    "sg:address":"Rue Montante 129ba",
    "sg:city":"Florennes",
    "sg:orig_category":"Pain, p\u00e2tisseries and confiseries",
    "sg:phone":"+32 82 68 81 77",
    "sg:postcode":"5620",
    "sg:province":"Namur",
    "wof:name":"Boulangerie Brihaye",
    "wof:placetype":"venue"
},
  "geometry": {"coordinates":[4.6866297722,50.2313308716],"type":"Point"}
}