{
  "type": "Feature",
  "properties": {
    "iso:country":"BE",
    "sg:address":"Bilzersteenweg 66",
    "sg:city":"Tongeren",
    "sg:orig_category":"Avocats and conseillers juridiques",
    "sg:phone":"+32 12 23 14 62",
    "sg:postcode":"3700",
    "sg:province":"Limburg",
    "wof:name":"Mark Moens",
    "wof:placetype":"venue"
},
  "geometry": {"coordinates":[5.4624891281,50.7856941223],"type":"Point"}
}