{
  "type": "Feature",
  "properties": {
    "addr:full":"Processieweg 11 Heusden-zolder (heusden) Limburg 3550",
    "addr:housenumber":"11",
    "addr:postcode":"3550",
    "addr:street":"Processieweg",
    "iso:country":"BE",
    "sg:address":"Processieweg 11",
    "sg:city":"Heusden-zolder (heusden)",
    "sg:classifiers":[
        {
            "category":"Personal",
            "subcategory":"Beauty Salon",
            "type":"Services"
        }
    ],
    "sg:phone":"+32 11 42 64 37",
    "sg:postcode":"3550",
    "sg:province":"Limburg",
    "sg:tags":[
        "lady",
        "-",
        "hairdressing"
    ],
    "wof:name":"Eerdekens A",
    "wof:placetype":"venue"
},
  "geometry": {"coordinates":[5.2762351036,51.029548645],"type":"Point"}
}