{
  "type": "Feature",
  "properties": {
    "addr:full":"Poelweg 10 Holsbeek (kortrijk-dutsel) Vlaams-Brabant 3220",
    "addr:housenumber":"10",
    "addr:postcode":"3220",
    "addr:street":"Poelweg",
    "iso:country":"BE",
    "sg:address":"Poelweg 10",
    "sg:city":"Holsbeek (kortrijk-dutsel)",
    "sg:classifiers":[
        {
            "category":"Communications",
            "type":"Services"
        }
    ],
    "sg:phone":"+32 16 62 90 66",
    "sg:postcode":"3220",
    "sg:province":"Vlaams-Brabant",
    "sg:tags":[
        "translator"
    ],
    "wof:name":"Hendrickx S",
    "wof:placetype":"venue"
},
  "geometry": {"coordinates":[4.8109002113,50.9254074097],"type":"Point"}
}