{
  "type": "Feature",
  "properties": {
    "addr:full":"Hoogstraat 122 Deerlijk West-Vlaanderen 8540",
    "addr:housenumber":"122",
    "addr:postcode":"8540",
    "addr:street":"Hoogstraat",
    "iso:country":"BE",
    "sg:address":"Hoogstraat 122",
    "sg:city":"Deerlijk",
    "sg:orig_category":"Biblioth\u00e8ques and archives publiques",
    "sg:phone":"+32 56 71 89 81",
    "sg:postcode":"8540",
    "sg:province":"West-Vlaanderen",
    "wof:name":"Openbare Bibliotheek",
    "wof:placetype":"venue"
},
  "geometry": {"coordinates":[3.3536269665,50.8542938232],"type":"Point"}
}