{
  "type": "Feature",
  "properties": {
    "addr:full":"Holt 136 Box 1 Bilzen Limburg 3740",
    "addr:housenumber":"136;1",
    "addr:postcode":"3740",
    "addr:street":"Box",
    "iso:country":"BE",
    "sg:address":"Holt 136 Box 1",
    "sg:city":"Bilzen",
    "sg:classifiers":[
        {
            "category":"Building & Trades",
            "subcategory":"Landscaping Services",
            "type":"Services"
        }
    ],
    "sg:phone":"+32 89 41 55 13",
    "sg:postcode":"3740",
    "sg:province":"Limburg",
    "sg:tags":[
        "-",
        "lopping",
        "work",
        "tree",
        "felling"
    ],
    "wof:name":"M.o.b. Service Bvba",
    "wof:placetype":"venue"
},
  "geometry": {"coordinates":[5.4750618935,50.8902168274],"type":"Point"}
}