{
  "type": "Feature",
  "properties": {
    "addr:full":"Rue Louvrex 105 Li\u00c8ge Li\u00e8ge 4000",
    "addr:housenumber":"105",
    "addr:postcode":"4000",
    "addr:street":"Rue Louvrex",
    "iso:country":"BE",
    "sg:address":"Rue Louvrex 105",
    "sg:city":"Li\u00c8ge",
    "sg:orig_category":"M\u00e9decins and sp\u00e9cialistes",
    "sg:phone":"+32 4 223 31 50",
    "sg:postcode":"4000",
    "sg:province":"Li\u00e8ge",
    "wof:name":"Andr\u00c9 Nossent",
    "wof:placetype":"venue"
},
  "geometry": {"coordinates":[5.5646262169,50.6333503723],"type":"Point"}
}