{
  "type": "Feature",
  "properties": {
    "addr:full":"Pontstraat 99 Deerlijk West-Vlaanderen 8540",
    "addr:housenumber":"99",
    "addr:postcode":"8540",
    "addr:street":"Pontstraat",
    "iso:country":"BE",
    "sg:address":"Pontstraat 99",
    "sg:city":"Deerlijk",
    "sg:orig_category":"Jardins botaniques, zoologiques, observatoires and r\u00e9serves naturelles",
    "sg:phone":"+32 56 77 79 29",
    "sg:postcode":"8540",
    "sg:province":"West-Vlaanderen",
    "wof:name":"Bokkeslot",
    "wof:placetype":"venue"
},
  "geometry": {"coordinates":[3.360656023,50.8494224548],"type":"Point"}
}