{
  "type": "Feature",
  "properties": {
    "addr:full":"Kartuizersvest 24 Lier Antwerpen 2500",
    "addr:housenumber":"24",
    "addr:postcode":"2500",
    "addr:street":"Kartuizersvest",
    "iso:country":"BE",
    "sg:address":"Kartuizersvest 24",
    "sg:city":"Lier",
    "sg:orig_category":"Epiceries",
    "sg:phone":"+32 3 488 48 81",
    "sg:postcode":"2500",
    "sg:province":"Antwerpen",
    "wof:name":"Den Dadel",
    "wof:placetype":"venue"
},
  "geometry": {"coordinates":[4.5685329437,51.1336402893],"type":"Point"}
}