{
  "type": "Feature",
  "properties": {
    "addr:full":"Klein Tegelrij 77 Nieuwerkerken Limburg 3850",
    "addr:housenumber":"77",
    "addr:postcode":"3850",
    "addr:street":"Klein Tegelrij",
    "iso:country":"BE",
    "sg:address":"Klein Tegelrij 77",
    "sg:city":"Nieuwerkerken",
    "sg:orig_category":"HERSTELLING ELEKTRISCHE HUISHOUDAPPARATEN Huishoudapparaten, televisies and radio's",
    "sg:phone":"+32 11 68 62 96",
    "sg:postcode":"3850",
    "sg:province":"Limburg",
    "wof:name":"Huis Kempeneers",
    "wof:placetype":"venue"
},
  "geometry": {"coordinates":[5.1885499954,50.8793716431],"type":"Point"}
}