{
  "type": "Feature",
  "properties": {
    "iso:country":"BE",
    "sg:address":"Roeterstraat 2",
    "sg:city":"Scherpenheuvel-zichem",
    "sg:orig_category":"Eleveurs de bovins",
    "sg:phone":"+32 13 33 35 17",
    "sg:postcode":"3270",
    "sg:province":"Vlaams-Brabant",
    "wof:name":"Kris Jannes",
    "wof:placetype":"venue"
},
  "geometry": {"coordinates":[4.9995059967,50.9696617126],"type":"Point"}
}