{
  "type": "Feature",
  "properties": {
    "iso:country":"BE",
    "sg:address":"Rue Auguste Baccus 35",
    "sg:city":"Orp-jauche",
    "sg:orig_category":"Jardins botaniques, zoologiques, observatoires and r\u00e9serves naturelles",
    "sg:phone":"+32 81 87 73 66",
    "sg:postcode":"1350",
    "sg:province":"Brabant Wallon",
    "wof:name":"Grottes De Folx-les-caves",
    "wof:placetype":"venue"
},
  "geometry": {"coordinates":[4.97920084,50.6738891602],"type":"Point"}
}