{
  "type": "Feature",
  "properties": {
    "iso:country":"BE",
    "sg:address":"Rue Warissaet 2",
    "sg:city":"Silly (bassilly)",
    "sg:classifiers":[
        {
            "category":"Building & Trades",
            "subcategory":"Construction",
            "type":"Services"
        }
    ],
    "sg:phone":"+32 68 56 83 56",
    "sg:postcode":"7830",
    "sg:province":"Hainaut",
    "sg:tags":[
        "carpenter"
    ],
    "wof:name":"Euromenuiserie Sprl",
    "wof:placetype":"venue"
},
  "geometry": {"coordinates":[3.9199800491,50.6881408691],"type":"Point"}
}