{
  "type": "Feature",
  "properties": {
    "iso:country":"BE",
    "sg:address":"Rue Vanderkindere 130",
    "sg:city":"Ukkel/uccle",
    "sg:orig_category":"Quincailleries. Drogueries. Parfumeries",
    "sg:phone":"+32 2 344 75 41",
    "sg:postcode":"1180",
    "sg:province":"Bruxelles-Capitale",
    "wof:name":"Termont Droguerie Conseil",
    "wof:placetype":"venue"
},
  "geometry": {"coordinates":[4.3445501328,50.8138885498],"type":"Point"}
}