{
  "type": "Feature",
  "properties": {
    "addr:full":"Rue Lesbroussart 36 Bruxelles (ixelles) Bruxelles-Capitale 1050",
    "addr:housenumber":"36",
    "addr:postcode":"1050",
    "addr:street":"Rue Lesbroussart",
    "iso:country":"BE",
    "sg:address":"Rue Lesbroussart 36",
    "sg:city":"Bruxelles (ixelles)",
    "sg:classifiers":[
        {
            "category":"Personal",
            "subcategory":"Beauty Salon",
            "type":"Services"
        }
    ],
    "sg:phone":"+32 2 649 27 03",
    "sg:postcode":"1050",
    "sg:province":"Bruxelles-Capitale",
    "sg:tags":[
        "lady",
        "-",
        "hairdressing"
    ],
    "wof:name":"De Haes Dany",
    "wof:placetype":"venue"
},
  "geometry": {"coordinates":[4.3694181442,50.8276252747],"type":"Point"}
}