{
  "type": "Feature",
  "properties": {
    "iso:country":"BE",
    "sg:address":"Leemstraat 88",
    "sg:city":"Lochristi (zaffelare)",
    "sg:classifiers":[
        {
            "category":"Professional",
            "subcategory":"Lawyer & Legal Services",
            "type":"Services"
        }
    ],
    "sg:phone":"+32 9 355 62 94",
    "sg:postcode":"9080",
    "sg:province":"Oost-Vlaanderen",
    "sg:tags":[
        "notary"
    ],
    "wof:name":"Van Duffel G",
    "wof:placetype":"venue"
},
  "geometry": {"coordinates":[3.8807449341,51.1281585693],"type":"Point"}
}