{
  "type": "Feature",
  "properties": {
    "iso:country":"BE",
    "sg:address":"Rue De La Rivi\u00e8re 19",
    "sg:city":"Bruxelles (saint-josse-ten-noode)",
    "sg:classifiers":[
        {
            "category":"Organizations",
            "subcategory":"Community Association",
            "type":"Services"
        }
    ],
    "sg:phone":"+32 2 217 01 54",
    "sg:postcode":"1210",
    "sg:province":"Bruxelles-Capitale",
    "sg:tags":[
        "cultural"
    ],
    "wof:name":"A.b.m.c.s. Asbl",
    "wof:placetype":"venue"
},
  "geometry": {"coordinates":[4.3625068665,50.8570327759],"type":"Point"}
}