{
  "type": "Feature",
  "properties": {
    "iso:country":"BE",
    "sg:address":"Nolet De Brauwerestraat 9",
    "sg:city":"Vilvoorde",
    "sg:classifiers":[
        {
            "category":"Real Estate",
            "subcategory":"Architect",
            "type":"Services"
        }
    ],
    "sg:phone":"+32 2 251 71 87",
    "sg:postcode":"1800",
    "sg:province":"Vlaams-Brabant",
    "wof:name":"Bollen P",
    "wof:placetype":"venue"
},
  "geometry": {"coordinates":[4.4227671623,50.9295082092],"type":"Point"}
}