{
  "type": "Feature",
  "properties": {
    "iso:country":"BE",
    "sg:address":"Rue Grande 13",
    "sg:city":"Dinant",
    "sg:orig_category":"Banques and organismes de cr\u00e9dit",
    "sg:phone":"+32 82 22 42 43",
    "sg:postcode":"5500",
    "sg:province":"Namur",
    "wof:name":"Cbc",
    "wof:placetype":"venue"
},
  "geometry": {"coordinates":[4.9160518646,50.2565574646],"type":"Point"}
}