{
  "type": "Feature",
  "properties": {
    "addr:full":"Rooiendamlaan 9 Essen Antwerpen 2910",
    "addr:housenumber":"9",
    "addr:postcode":"2910",
    "addr:street":"Rooiendamlaan",
    "iso:country":"BE",
    "sg:address":"Rooiendamlaan 9",
    "sg:city":"Essen",
    "sg:orig_category":"Plomberie, chauffage and installations sanitaires",
    "sg:phone":"+32 3 677 02 60",
    "sg:postcode":"2910",
    "sg:province":"Antwerpen",
    "wof:name":"Eric Kerstens",
    "wof:placetype":"venue"
},
  "geometry": {"coordinates":[4.4560389519,51.4273071289],"type":"Point"}
}