{
  "type": "Feature",
  "properties": {
    "addr:full":"Rue De La Tour 10a Mont-saint-guibert (corbais) Brabant Wallon 1435",
    "addr:housenumber":"10a",
    "addr:postcode":"1435",
    "addr:street":"Rue De La Tour;Wallon",
    "iso:country":"BE",
    "sg:address":"Rue De La Tour 10a",
    "sg:city":"Mont-saint-guibert (corbais)",
    "sg:classifiers":[
        {
            "category":"Building & Trades",
            "subcategory":"Construction",
            "type":"Services"
        }
    ],
    "sg:phone":"+32 10 68 90 33",
    "sg:postcode":"1435",
    "sg:province":"Brabant Wallon",
    "sg:tags":[
        "-",
        "door",
        "folding",
        "sliding"
    ],
    "wof:name":"Iconic",
    "wof:placetype":"venue"
},
  "geometry": {"coordinates":[4.6545128822,50.6466636658],"type":"Point"}
}