{
  "type": "Feature",
  "properties": {
    "addr:full":"Grote Baan 199 Ravels Antwerpen 2380",
    "addr:housenumber":"199",
    "addr:postcode":"2380",
    "addr:street":"Grote Baan",
    "iso:country":"BE",
    "sg:address":"Grote Baan 199",
    "sg:city":"Ravels",
    "sg:classifiers":[
        {
            "category":"Cafe",
            "type":"Food & Drink"
        }
    ],
    "sg:phone":"+32 14 65 15 38",
    "sg:postcode":"2380",
    "sg:province":"Antwerpen",
    "sg:tags":[
        "caf\u00e9s"
    ],
    "wof:name":"The Bridge",
    "wof:placetype":"venue"
},
  "geometry": {"coordinates":[4.9904880524,51.3625793457],"type":"Point"}
}