{
  "type": "Feature",
  "properties": {
    "iso:country":"BE",
    "sg:address":"Beversesteenweg 545",
    "sg:city":"Roeselare",
    "sg:classifiers":[
        {
            "category":"Insurance",
            "subcategory":"Insurance Agent",
            "type":"Services"
        }
    ],
    "sg:phone":"+32 51 20 65 71",
    "sg:postcode":"8800",
    "sg:province":"West-Vlaanderen",
    "sg:tags":[
        "broker"
    ],
    "wof:name":"Ysebaert",
    "wof:placetype":"venue"
},
  "geometry": {"coordinates":[3.1597049236,50.9739112854],"type":"Point"}
}