{
  "type": "Feature",
  "properties": {
    "addr:full":"Walbosdreef 19 Destelbergen Oost-Vlaanderen 9070",
    "addr:housenumber":"19",
    "addr:postcode":"9070",
    "addr:street":"Walbosdreef",
    "iso:country":"BE",
    "sg:address":"Walbosdreef 19",
    "sg:city":"Destelbergen",
    "sg:classifiers":[
        {
            "category":"Health Services",
            "subcategory":"Nursing And Care Facility",
            "type":"Services"
        }
    ],
    "sg:phone":"+32 9 238 24 79",
    "sg:postcode":"9070",
    "sg:province":"Oost-Vlaanderen",
    "sg:tags":[
        "home"
    ],
    "wof:name":"Galle K",
    "wof:placetype":"venue"
},
  "geometry": {"coordinates":[3.7946150303,51.0543212891],"type":"Point"}
}