{
  "type": "Feature",
  "properties": {
    "iso:country":"BE",
    "sg:address":"Hoogleedsesteenweg 256",
    "sg:city":"Roeselare",
    "sg:classifiers":[
        {
            "category":"Food & Beverages",
            "subcategory":"Fruits & Vegetables",
            "type":"Retail Goods"
        }
    ],
    "sg:phone":"+32 51 22 90 18",
    "sg:postcode":"8800",
    "sg:province":"West-Vlaanderen",
    "sg:tags":[
        "-"
    ],
    "wof:name":"Primeurke ('t)",
    "wof:placetype":"venue"
},
  "geometry": {"coordinates":[3.1089420319,50.9567070007],"type":"Point"}
}