{
  "type": "Feature",
  "properties": {
    "addr:full":"Plantijnlei 46b4 Schoten Antwerpen 2900",
    "addr:housenumber":"46b4",
    "addr:postcode":"2900",
    "addr:street":"Plantijnlei",
    "iso:country":"BE",
    "sg:address":"Plantijnlei 46b4",
    "sg:city":"Schoten",
    "sg:orig_category":"Industri\u00eble elektrische installaties",
    "sg:phone":"+32 3 645 24 89",
    "sg:postcode":"2900",
    "sg:province":"Antwerpen",
    "wof:name":"Liftronics",
    "wof:placetype":"venue"
},
  "geometry": {"coordinates":[4.4656438828,51.2475509644],"type":"Point"}
}