{
  "type": "Feature",
  "properties": {
    "addr:full":"Rue De La Goffe 21 Esneux Li\u00e8ge 4130",
    "addr:housenumber":"21",
    "addr:postcode":"4130",
    "addr:street":"Rue De La Goffe",
    "iso:country":"BE",
    "sg:address":"Rue De La Goffe 21",
    "sg:city":"Esneux",
    "sg:orig_category":"Travaux de finition and nettoyage de b\u00e2timents",
    "sg:phone":"+32 4 380 41 60",
    "sg:postcode":"4130",
    "sg:province":"Li\u00e8ge",
    "wof:name":"Jean-claude Bellem",
    "wof:placetype":"venue"
},
  "geometry": {"coordinates":[5.5839800835,50.5388641357],"type":"Point"}
}