{
  "type": "Feature",
  "properties": {
    "addr:full":"Rue De La Victoire 222 Bruxelles (saint-gilles) Bruxelles-Capitale 1060",
    "addr:housenumber":"222",
    "addr:postcode":"1060",
    "addr:street":"Rue De La Victoire",
    "iso:country":"BE",
    "sg:address":"Rue De La Victoire 222",
    "sg:city":"Bruxelles (saint-gilles)",
    "sg:classifiers":[
        {
            "category":"Real Estate",
            "subcategory":"Architect",
            "type":"Services"
        }
    ],
    "sg:phone":"+32 2 537 84 81",
    "sg:postcode":"1060",
    "sg:province":"Bruxelles-Capitale",
    "wof:name":"Zichy W",
    "wof:placetype":"venue"
},
  "geometry": {"coordinates":[4.3541889191,50.8261642456],"type":"Point"}
}