{
  "type": "Feature",
  "properties": {
    "iso:country":"BE",
    "sg:address":"Koningin Astridlaan 18",
    "sg:city":"Wetteren",
    "sg:orig_category":"Sportclubs",
    "sg:phone":"+32 9 369 83 74",
    "sg:postcode":"9230",
    "sg:province":"Oost-Vlaanderen",
    "wof:name":"W.s.v. Wetteren",
    "wof:placetype":"venue"
},
  "geometry": {"coordinates":[3.8798120022,51.0039482117],"type":"Point"}
}