{
  "type": "Feature",
  "properties": {
    "addr:full":"Angereelstr 8 Appelterre 9498",
    "addr:housenumber":"8",
    "addr:postcode":"9498",
    "addr:street":"Angereelstr",
    "iso:country":"BE",
    "sg:address":"Angereelstr 8",
    "sg:city":"Appelterre",
    "sg:classifiers":[
        {
            "category":"Banks & Credit Unions",
            "subcategory":"Bank",
            "type":"Services"
        }
    ],
    "sg:phone":"+32 54 33 57 95",
    "sg:postcode":"9498",
    "wof:name":"Kredietbank",
    "wof:placetype":"venue"
},
  "geometry": {"coordinates":[170.54762268069999,-44.600769043],"type":"Point"}
}