{
  "type": "Feature",
  "properties": {
    "addr:full":"Hardenvoort 5 Antwerpen Antwerpen 2060",
    "addr:housenumber":"5",
    "addr:postcode":"2060",
    "addr:street":"Hardenvoort",
    "iso:country":"BE",
    "sg:address":"Hardenvoort 5",
    "sg:city":"Antwerpen",
    "sg:orig_category":"Herstellingen and onderhoud van auto's Voertuigen",
    "sg:phone":"+32 3 233 92 29",
    "sg:postcode":"2060",
    "sg:province":"Antwerpen",
    "wof:name":"Carrosserie Marien",
    "wof:placetype":"venue"
},
  "geometry": {"coordinates":[4.4236860275,51.2320899963],"type":"Point"}
}