{
  "type": "Feature",
  "properties": {
    "iso:country":"BE",
    "sg:address":"Rue Hamoir 157",
    "sg:city":"La Louviere",
    "sg:orig_category":"Bloemen and planten",
    "sg:phone":"+32 64 22 13 44",
    "sg:postcode":"7100",
    "sg:province":"Hainaut",
    "wof:name":"Patrick Debauque",
    "wof:placetype":"venue"
},
  "geometry": {"coordinates":[4.1941599846,50.4749946594],"type":"Point"}
}