{
  "type": "Feature",
  "properties": {
    "addr:full":"Chauss\u00e9e De Jette 479-485 Bruxelles (jette) Bruxelles-Capitale 1090",
    "addr:postcode":"479-485;1090",
    "addr:street":"Chausse\u0301E De Jette",
    "iso:country":"BE",
    "sg:address":"Chauss\u00e9e De Jette 479-485",
    "sg:city":"Bruxelles (jette)",
    "sg:classifiers":[
        {
            "category":"Shopping",
            "subcategory":"Party Supplies",
            "type":"Retail Goods"
        }
    ],
    "sg:phone":"+32 2 425 96 80",
    "sg:postcode":"1090",
    "sg:province":"Bruxelles-Capitale",
    "sg:tags":[
        "ice-cream",
        "-",
        "parlour"
    ],
    "wof:name":"Liobel Biscuit",
    "wof:placetype":"venue"
},
  "geometry": {"coordinates":[4.3289189339,50.8685874939],"type":"Point"}
}