{
  "type": "Feature",
  "properties": {
    "iso:country":"BE",
    "sg:address":"Touwstr 29",
    "sg:city":"Antwerpen",
    "sg:classifiers":[
        {
            "category":"Manufacturing",
            "subcategory":"Wood Products",
            "type":"Manufacturing & Wholesale Goods"
        }
    ],
    "sg:phone":"+32 3 271 06 08",
    "sg:postcode":"2060",
    "sg:province":"Antwerpen",
    "sg:tags":[
        "fabric",
        "textile",
        "linen",
        "professional",
        "clothing",
        "furniture"
    ],
    "wof:name":"Decoratex Bvba",
    "wof:placetype":"venue"
},
  "geometry": {"coordinates":[4.4392771721,51.2247276306],"type":"Point"}
}