{
  "type": "Feature",
  "properties": {
    "iso:country":"BE",
    "sg:address":"Geraardsbergsestraat 90",
    "sg:city":"Aalst",
    "sg:orig_category":"Enseignement maternel and primaire",
    "sg:phone":"+32 53 77 70 49",
    "sg:postcode":"9300",
    "sg:province":"Oost-Vlaanderen",
    "wof:name":"Vrije Basisschool",
    "wof:placetype":"venue"
},
  "geometry": {"coordinates":[4.0365929604,50.9328765869],"type":"Point"}
}