{
  "type": "Feature",
  "properties": {
    "iso:country":"BE",
    "sg:address":"Heidestatiestraat 33",
    "sg:city":"Kalmthout",
    "sg:classifiers":[
        {
            "category":"Shopping",
            "subcategory":"Shoes",
            "type":"Retail Goods"
        }
    ],
    "sg:phone":"+32 3 666 87 47",
    "sg:postcode":"2920",
    "sg:province":"Antwerpen",
    "sg:tags":[
        "slipper",
        "-"
    ],
    "wof:name":"Bim-bim",
    "wof:placetype":"venue"
},
  "geometry": {"coordinates":[4.4648571014,51.3655357361],"type":"Point"}
}