{
  "type": "Feature",
  "properties": {
    "addr:full":"Avenue Emile Theys 13 Waterloo Brabant Wallon 1410",
    "addr:housenumber":"13",
    "addr:postcode":"1410",
    "addr:street":"Avenue Emile Theys",
    "iso:country":"BE",
    "sg:address":"Avenue Emile Theys 13",
    "sg:city":"Waterloo",
    "sg:orig_category":"M\u00e9decins and sp\u00e9cialistes",
    "sg:phone":"+32 2 354 44 03",
    "sg:postcode":"1410",
    "sg:province":"Brabant Wallon",
    "wof:name":"Consultation Nourissons",
    "wof:placetype":"venue"
},
  "geometry": {"coordinates":[4.3879499435,50.7172431946],"type":"Point"}
}