{
  "type": "Feature",
  "properties": {
    "addr:full":"Boulevard Maurice Lemonnier 87 Bruxelles Bruxelles-Capitale 1000",
    "addr:housenumber":"87",
    "addr:postcode":"1000",
    "addr:street":"Boulevard Maurice Lemonnier",
    "iso:country":"BE",
    "sg:address":"Boulevard Maurice Lemonnier 87",
    "sg:city":"Bruxelles",
    "sg:classifiers":[
        {
            "category":"Home & Garden",
            "subcategory":"Building Materials",
            "type":"Retail Goods"
        }
    ],
    "sg:phone":"+32 2 512 20 75",
    "sg:postcode":"1000",
    "sg:province":"Bruxelles-Capitale",
    "sg:tags":[
        "wall",
        "cupboard"
    ],
    "wof:name":"Generale Revetements",
    "wof:placetype":"venue"
},
  "geometry": {"coordinates":[4.3441181183,50.8432273865],"type":"Point"}
}