{
  "type": "Feature",
  "properties": {
    "addr:full":"Klein Veerle 1 Brecht (sint-lenaarts) Antwerpen 2960",
    "addr:housenumber":"1",
    "addr:postcode":"2960",
    "addr:street":"Klein Veerle",
    "iso:country":"BE",
    "sg:address":"Klein Veerle 1",
    "sg:city":"Brecht (sint-lenaarts)",
    "sg:classifiers":[
        {
            "category":"Building & Trades",
            "subcategory":"Construction",
            "type":"Services"
        }
    ],
    "sg:phone":"+32 3 313 97 35",
    "sg:postcode":"2960",
    "sg:province":"Antwerpen",
    "sg:tags":[
        "ceiling"
    ],
    "wof:name":"Roli-construct Bvba",
    "wof:placetype":"venue"
},
  "geometry": {"coordinates":[4.6744561195,51.3314399719],"type":"Point"}
}