{
  "type": "Feature",
  "properties": {
    "addr:full":"Dr\u00e8ve 14 Rhode-saint-gen\u00e8se Vlaams-Brabant 1640",
    "addr:housenumber":"14",
    "addr:postcode":"1640",
    "addr:street":"Dre\u0300Ve",
    "iso:country":"BE",
    "sg:address":"Dr\u00e8ve 14",
    "sg:city":"Rhode-saint-gen\u00e8se",
    "sg:classifiers":[
        {
            "category":"Retail",
            "subcategory":"Repair Shop",
            "type":"Services"
        }
    ],
    "sg:phone":"+32 2 380 78 17",
    "sg:postcode":"1640",
    "sg:province":"Vlaams-Brabant",
    "sg:tags":[
        "jobbing",
        "tailoring",
        "-"
    ],
    "wof:name":"Rodea",
    "wof:placetype":"venue"
},
  "geometry": {"coordinates":[4.3416209221,50.7436790466],"type":"Point"}
}