{
  "type": "Feature",
  "properties": {
    "iso:country":"BE",
    "sg:address":"Wolfshaegen 24",
    "sg:city":"Huldenberg",
    "sg:classifiers":[
        {
            "category":"Health Services",
            "subcategory":"Health Practitioner",
            "type":"Services"
        }
    ],
    "sg:phone":"+32 16 47 30 31",
    "sg:postcode":"3040",
    "sg:province":"Vlaams-Brabant",
    "sg:tags":[
        "physiotherapist"
    ],
    "wof:name":"Depre Herman",
    "wof:placetype":"venue"
},
  "geometry": {"coordinates":[4.6151561737,50.7772445679],"type":"Point"}
}