{
  "type": "Feature",
  "properties": {
    "addr:full":"Ouwegemstraat 8 Zingem Oost-Vlaanderen 9750",
    "addr:housenumber":"8",
    "addr:postcode":"9750",
    "addr:street":"Ouwegemstraat;Oost-Vlaanderen",
    "iso:country":"BE",
    "sg:address":"Ouwegemstraat 8",
    "sg:city":"Zingem",
    "sg:orig_category":"Etalage- and showroomontwerpers",
    "sg:phone":"+32 9 384 65 68",
    "sg:postcode":"9750",
    "sg:province":"Oost-Vlaanderen",
    "wof:name":"Inge Snoeck",
    "wof:placetype":"venue"
},
  "geometry": {"coordinates":[3.6135630608,50.9100761414],"type":"Point"}
}