{
  "type": "Feature",
  "properties": {
    "addr:full":"Leopold Ii Laan 7 Dendermonde Oost-Vlaanderen 9200",
    "addr:housenumber":"7",
    "addr:postcode":"9200",
    "addr:street":"Leopold Ii Laan;Oost-Vlaanderen",
    "iso:country":"BE",
    "sg:address":"Leopold Ii Laan 7",
    "sg:city":"Dendermonde",
    "sg:classifiers":[
        {
            "category":"Professional",
            "subcategory":"Computer Services",
            "type":"Services"
        }
    ],
    "sg:phone":"+32 52 22 67 07",
    "sg:postcode":"9200",
    "sg:province":"Oost-Vlaanderen",
    "sg:tags":[
        "network"
    ],
    "wof:name":"Nettech",
    "wof:placetype":"venue"
},
  "geometry": {"coordinates":[4.1019887924,51.0258674622],"type":"Point"}
}