{
  "type": "Feature",
  "properties": {
    "iso:country":"BE",
    "sg:address":"Rue Franche-taverne 21",
    "sg:city":"Fernelmont",
    "sg:orig_category":"Salons de coiffure. Centres de relaxation and bien-\u00eatre",
    "sg:phone":"+32 81 83 36 80",
    "sg:postcode":"5380",
    "sg:province":"Namur",
    "wof:name":"Liliane",
    "wof:placetype":"venue"
},
  "geometry": {"coordinates":[4.9861078262,50.5531463623],"type":"Point"}
}