{
  "type": "Feature",
  "properties": {
    "iso:country":"BE",
    "sg:address":"Braunlauf 2",
    "sg:city":"Burg-reuland/burg-reuland",
    "sg:orig_category":"Eleveurs de bovins",
    "sg:phone":"+32 80 22 75 38",
    "sg:postcode":"4791",
    "sg:province":"Li\u00e8ge",
    "wof:name":"Willy Holper",
    "wof:placetype":"venue"
},
  "geometry": {"coordinates":[6.0600709915,50.2418403625],"type":"Point"}
}