{
  "type": "Feature",
  "properties": {
    "iso:country":"BE",
    "sg:address":"Rue De La Sabliere 10",
    "sg:city":"Villers-le-bouillet",
    "sg:orig_category":"M\u00e9decines alternatives. M\u00e9decins and sp\u00e9cialistes",
    "sg:phone":"+32 85 21 45 50",
    "sg:postcode":"4530",
    "sg:province":"Li\u00e8ge",
    "wof:name":"Jacques Kersten",
    "wof:placetype":"venue"
},
  "geometry": {"coordinates":[5.2770237923,50.5738487244],"type":"Point"}
}