{
  "type": "Feature",
  "properties": {
    "addr:full":"Vijfstraten 50 Keerbergen Vlaams-Brabant 3140",
    "addr:housenumber":"50",
    "addr:postcode":"3140",
    "addr:street":"Vijfstraten",
    "iso:country":"BE",
    "sg:address":"Vijfstraten 50",
    "sg:city":"Keerbergen",
    "sg:orig_category":"Activit\u00e9s r\u00e9cr\u00e9atives diverses",
    "sg:phone":"+32 16 53 73 44",
    "sg:postcode":"3140",
    "sg:province":"Vlaams-Brabant",
    "wof:name":"Bridge Club",
    "wof:placetype":"venue"
},
  "geometry": {"coordinates":[4.6833848953,51.0005874634],"type":"Point"}
}