{
  "type": "Feature",
  "properties": {
    "addr:full":"Marktplein 7 Galmaarden Vlaams-Brabant 1570",
    "addr:housenumber":"7",
    "addr:postcode":"1570",
    "addr:street":"Marktplein",
    "iso:country":"BE",
    "sg:address":"Marktplein 7",
    "sg:city":"Galmaarden",
    "sg:orig_category":"Banques and organismes de cr\u00e9dit",
    "sg:phone":"+32 54 58 85 16",
    "sg:postcode":"1570",
    "sg:province":"Vlaams-Brabant",
    "wof:name":"Nagelmackers",
    "wof:placetype":"venue"
},
  "geometry": {"coordinates":[3.9712030888,50.7532653809],"type":"Point"}
}