{
  "type": "Feature",
  "properties": {
    "iso:country":"BE",
    "sg:address":"Boulevard De L'yser",
    "sg:city":"Charleroi",
    "sg:classifiers":[
        {
            "category":"Shopping",
            "subcategory":"Hobbies, Toys, & Games",
            "type":"Retail Goods"
        }
    ],
    "sg:phone":"+32 71 70 00 61",
    "sg:postcode":"6000",
    "sg:province":"Hainaut",
    "sg:tags":[
        "computer",
        "video"
    ],
    "wof:name":"Red Sector",
    "wof:placetype":"venue"
},
  "geometry": {"coordinates":[4.4426779747,50.4100341797],"type":"Point"}
}