{
  "type": "Feature",
  "properties": {
    "iso:country":"BE",
    "sg:address":"Ambachtsweg 32",
    "sg:city":"Merelbeke",
    "sg:classifiers":[
        {
            "category":"Sports & Exercise",
            "subcategory":"Ice Rink",
            "type":"Entertainment"
        }
    ],
    "sg:phone":"+32 9 272 72 52",
    "sg:postcode":"9820",
    "sg:province":"Oost-Vlaanderen",
    "sg:tags":[
        "machine",
        "making"
    ],
    "wof:name":"Incotech Bvba",
    "wof:placetype":"venue"
},
  "geometry": {"coordinates":[3.7622139454,50.9926223755],"type":"Point"}
}