{
  "type": "Feature",
  "properties": {
    "iso:country":"BE",
    "sg:address":"Oude Lillebaan 15",
    "sg:city":"Lille (gierle)",
    "sg:classifiers":[
        {
            "category":"Building & Trades",
            "subcategory":"Landscaping Services",
            "type":"Services"
        }
    ],
    "sg:phone":"+32 14 55 12 97",
    "sg:postcode":"2275",
    "sg:province":"Antwerpen",
    "sg:tags":[
        "gardening",
        "garden",
        "maintenance"
    ],
    "wof:name":"Delvaux Erik Bvba",
    "wof:placetype":"venue"
},
  "geometry": {"coordinates":[4.8543272018,51.2611846924],"type":"Point"}
}