{
  "type": "Feature",
  "properties": {
    "iso:country":"BE",
    "sg:address":"Verbiststraat 24",
    "sg:city":"Sint-joost-ten-node/saint-josse-ten-noode",
    "sg:classifiers":[
        {
            "category":"Cafe",
            "type":"Food & Drink"
        }
    ],
    "sg:phone":"+32 2 219 17 55",
    "sg:postcode":"1210",
    "sg:province":"Bruxelles-Capitale",
    "sg:tags":[
        "caf\u00e9s"
    ],
    "wof:name":"Caf\u00c9 Miami Beach",
    "wof:placetype":"venue"
},
  "geometry": {"coordinates":[4.3761367798,50.8503875732],"type":"Point"}
}