{
  "type": "Feature",
  "properties": {
    "addr:full":"Rue De La Gare 19 Rochefort Namur 5580",
    "addr:housenumber":"19",
    "addr:postcode":"5580",
    "addr:street":"Rue De La Gare",
    "iso:country":"BE",
    "sg:address":"Rue De La Gare 19",
    "sg:city":"Rochefort",
    "sg:orig_category":"Diverse organisaties and verenigingen",
    "sg:phone":"+32 84 21 40 48",
    "sg:postcode":"5580",
    "sg:province":"Namur",
    "wof:name":"Centre De Jeunes",
    "wof:placetype":"venue"
},
  "geometry": {"coordinates":[5.1637001038,50.1470108032],"type":"Point"}
}