{
  "type": "Feature",
  "properties": {
    "addr:full":"Dornernieuwstraat 26 Maaseik Limburg 3680",
    "addr:housenumber":"26",
    "addr:postcode":"3680",
    "addr:street":"Dornernieuwstraat",
    "iso:country":"BE",
    "sg:address":"Dornernieuwstraat 26",
    "sg:city":"Maaseik",
    "sg:classifiers":[
        {
            "category":"Insurance",
            "subcategory":"Life Insurance",
            "type":"Services"
        }
    ],
    "sg:phone":"+32 89 85 67 29",
    "sg:postcode":"3680",
    "sg:province":"Limburg",
    "sg:tags":[
        "assurance"
    ],
    "wof:name":"John Geelen",
    "wof:placetype":"venue"
},
  "geometry": {"coordinates":[5.791285038,51.0954208374],"type":"Point"}
}