{
  "type": "Feature",
  "properties": {
    "addr:full":"Rue Derri\u00c8re Les Murs 41 Malmedy/malmedy Li\u00e8ge 4960",
    "addr:housenumber":"41",
    "addr:postcode":"4960",
    "addr:street":"Rue Derrie\u0300Re Les Murs",
    "iso:country":"BE",
    "sg:address":"Rue Derri\u00c8re Les Murs 41",
    "sg:city":"Malmedy/malmedy",
    "sg:orig_category":"Diensten voor huisdieren",
    "sg:phone":"+32 80 77 14 70",
    "sg:postcode":"4960",
    "sg:province":"Li\u00e8ge",
    "wof:name":"Toilettage Canin",
    "wof:placetype":"venue"
},
  "geometry": {"coordinates":[6.0551772118,50.37657547],"type":"Point"}
}