{
  "type": "Feature",
  "properties": {
    "iso:country":"BE",
    "sg:address":"Rue Mar\u00e9chal Foch 37",
    "sg:city":"Charleroi (roux)",
    "sg:classifiers":[
        {
            "category":"Bars & Pubs",
            "type":"Food & Drink"
        }
    ],
    "sg:phone":"+32 71 45 14 50",
    "sg:postcode":"6044",
    "sg:province":"Hainaut",
    "sg:tags":[
        "tavern"
    ],
    "wof:name":"Madison (le)",
    "wof:placetype":"venue"
},
  "geometry": {"coordinates":[4.394534111,50.4425888062],"type":"Point"}
}