{
  "type": "Feature",
  "properties": {
    "iso:country":"BE",
    "sg:address":"Rue Du Cow\u00c2 205",
    "sg:city":"Flemalle",
    "sg:orig_category":"Dakwerken Gespecialiseerde residenti\u00eble bouw Woningbouw",
    "sg:phone":"+32 4 275 65 62",
    "sg:postcode":"4400",
    "sg:province":"Li\u00e8ge",
    "wof:name":"Guy Thiry",
    "wof:placetype":"venue"
},
  "geometry": {"coordinates":[5.4134559631,50.6158294678],"type":"Point"}
}