{
  "type": "Feature",
  "properties": {
    "iso:country":"BE",
    "sg:address":"Dorpstraat 80",
    "sg:city":"Jabbeke",
    "sg:orig_category":"Banken and kredietinstellingen",
    "sg:phone":"+32 50 81 43 34",
    "sg:postcode":"8490",
    "sg:province":"West-Vlaanderen",
    "wof:name":"Agf Assubel",
    "wof:placetype":"venue"
},
  "geometry": {"coordinates":[3.0883989334,51.1816673279],"type":"Point"}
}