{
  "type": "Feature",
  "properties": {
    "iso:country":"BE",
    "sg:address":"Dr. O. De Gruyterstr. 21",
    "sg:city":"Merelbeke",
    "sg:orig_category":"Belastingconsulenten Diverse juridische dienstverlening",
    "sg:phone":"+32 9 230 71 80",
    "sg:postcode":"9820",
    "sg:province":"Oost-Vlaanderen",
    "wof:name":"P. De Smet",
    "wof:placetype":"venue"
},
  "geometry": {"coordinates":[3.749341011,50.9921836853],"type":"Point"}
}