{
  "type": "Feature",
  "properties": {
    "addr:full":"Rue De La Scierie 11 Saint-hubert Luxembourg 6870",
    "addr:housenumber":"11",
    "addr:postcode":"6870",
    "addr:street":"Rue De La Scierie",
    "iso:country":"BE",
    "sg:address":"Rue De La Scierie 11",
    "sg:city":"Saint-hubert",
    "sg:orig_category":"Eleveurs de bovins",
    "sg:phone":"+32 61 61 25 14",
    "sg:postcode":"6870",
    "sg:province":"Luxembourg",
    "wof:name":"Guy Gabriel",
    "wof:placetype":"venue"
},
  "geometry": {"coordinates":[5.4033961296,50.0015602112],"type":"Point"}
}