{
  "type": "Feature",
  "properties": {
    "iso:country":"BE",
    "sg:address":"Rue De Nivelles 95",
    "sg:city":"Wavre",
    "sg:classifiers":[
        {
            "category":"Wholesale",
            "subcategory":"Medical Equipment & Supplies",
            "type":"Manufacturing & Wholesale Goods"
        }
    ],
    "sg:phone":"+32 10 24 54 88",
    "sg:postcode":"1300",
    "sg:province":"Brabant Wallon",
    "sg:tags":[
        "aid",
        "hearing"
    ],
    "wof:name":"Centre Auditif Tastenhoye Sprl",
    "wof:placetype":"venue"
},
  "geometry": {"coordinates":[4.6063771248,50.7139854431],"type":"Point"}
}