{
  "type": "Feature",
  "properties": {
    "addr:full":"Rue Ferdinand Nicolay 303 Saint-nicolas Li\u00e8ge 4420",
    "addr:housenumber":"303",
    "addr:postcode":"4420",
    "addr:street":"Rue Ferdinand Nicolay",
    "iso:country":"BE",
    "sg:address":"Rue Ferdinand Nicolay 303",
    "sg:city":"Saint-nicolas",
    "sg:orig_category":"D\u00e9taillants en pi\u00e8ces and accessoires de voitures",
    "sg:phone":"+32 4 234 33 32",
    "sg:postcode":"4420",
    "sg:province":"Li\u00e8ge",
    "wof:name":"Fe. Technic Design",
    "wof:placetype":"venue"
},
  "geometry": {"coordinates":[5.5333371162,50.6288948059],"type":"Point"}
}