{
  "type": "Feature",
  "properties": {
    "addr:full":"Rue Jacob Makoy 77 Li\u00e8ge 1 Li\u00e8ge 4000",
    "addr:housenumber":"77;1",
    "addr:postcode":"4000",
    "addr:street":"Rue Jacob Makoy",
    "iso:country":"BE",
    "sg:address":"Rue Jacob Makoy 77",
    "sg:city":"Li\u00e8ge 1",
    "sg:orig_category":"Non-Classified Establishments",
    "sg:phone":"+32 4 252 52 57",
    "sg:postcode":"4000",
    "sg:province":"Li\u00e8ge",
    "wof:name":"Andr\u00e0s Luminaires",
    "wof:placetype":"venue"
},
  "geometry": {"coordinates":[5.5594568253,50.6294403076],"type":"Point"}
}