{
  "type": "Feature",
  "properties": {
    "addr:full":"Amsterdamstraat 32 Hoogstraten Antwerpen 2321",
    "addr:housenumber":"32",
    "addr:postcode":"2321",
    "addr:street":"Amsterdamstraat",
    "iso:country":"BE",
    "sg:address":"Amsterdamstraat 32",
    "sg:city":"Hoogstraten",
    "sg:orig_category":"Banques and organismes de cr\u00e9dit",
    "sg:phone":"+32 3 317 04 00",
    "sg:postcode":"2321",
    "sg:province":"Antwerpen",
    "wof:name":"Kbc",
    "wof:placetype":"venue"
},
  "geometry": {"coordinates":[4.7366099358,51.442325592],"type":"Point"}
}