{
  "type": "Feature",
  "properties": {
    "addr:full":"De Smet Nayerlaan 94 Blankenberge West-Vlaanderen 8370",
    "addr:housenumber":"94",
    "addr:postcode":"8370",
    "addr:street":"De;Nayerlaan",
    "iso:country":"BE",
    "sg:address":"De Smet Nayerlaan 94",
    "sg:city":"Blankenberge",
    "sg:orig_category":"Opticiens",
    "sg:phone":"+32 50 41 90 09",
    "sg:postcode":"8370",
    "sg:province":"West-Vlaanderen",
    "wof:name":"Dirk Maertens",
    "wof:placetype":"venue"
},
  "geometry": {"coordinates":[3.1299750805,51.3118972778],"type":"Point"}
}