{
  "type": "Feature",
  "properties": {
    "iso:country":"BE",
    "sg:address":"Keizer Karellaan 93",
    "sg:city":"Ganshoren/ganshoren",
    "sg:orig_category":"Apotheken",
    "sg:phone":"+32 2 425 15 83",
    "sg:postcode":"1083",
    "sg:province":"Bruxelles-Capitale",
    "wof:name":"Jacques Schmitz",
    "wof:placetype":"venue"
},
  "geometry": {"coordinates":[4.3113999367,50.8685264587],"type":"Point"}
}