{
  "type": "Feature",
  "properties": {
    "addr:full":"Predikherenrei 15a Brugge West-Vlaanderen 8000",
    "addr:housenumber":"15a",
    "addr:postcode":"8000",
    "addr:street":"Predikherenrei",
    "iso:country":"BE",
    "sg:address":"Predikherenrei 15a",
    "sg:city":"Brugge",
    "sg:classifiers":[
        {
            "category":"Social Services",
            "type":"Services"
        }
    ],
    "sg:phone":"+32 50 34 30 17",
    "sg:postcode":"8000",
    "sg:province":"West-Vlaanderen",
    "wof:name":"Parochiaal Centrum Den Hooie",
    "wof:placetype":"venue"
},
  "geometry": {"coordinates":[3.2346599102,51.2076644897],"type":"Point"}
}