{
  "type": "Feature",
  "properties": {
    "addr:full":"Houba De Strooperlaan 12 Brussel/bruxelles Bruxelles-Capitale 1020",
    "addr:housenumber":"12",
    "addr:postcode":"1020",
    "addr:street":"Houba De Strooperlaan;/",
    "iso:country":"BE",
    "sg:address":"Houba De Strooperlaan 12",
    "sg:city":"Brussel/bruxelles",
    "sg:orig_category":"Postkantoren Verzekeringsmakelaars and experts",
    "sg:phone":"+32 2 476 12 22",
    "sg:postcode":"1020",
    "sg:province":"Bruxelles-Capitale",
    "wof:name":"De Post",
    "wof:placetype":"venue"
},
  "geometry": {"coordinates":[4.3424301147,50.8854980469],"type":"Point"}
}