{
  "type": "Feature",
  "properties": {
    "iso:country":"BE",
    "sg:address":"Keetberglaan 6",
    "sg:city":"Beveren (melsele)",
    "sg:classifiers":[
        {
            "category":"Wholesale",
            "subcategory":"Construction Materials",
            "type":"Manufacturing & Wholesale Goods"
        }
    ],
    "sg:phone":"+32 3 254 04 55",
    "sg:postcode":"9120",
    "sg:province":"Oost-Vlaanderen",
    "sg:tags":[
        "tubing",
        "industrial"
    ],
    "wof:name":"Weber Belgie Nv Engineering En Constructie",
    "wof:placetype":"venue"
},
  "geometry": {"coordinates":[4.2594051361,51.2448158264],"type":"Point"}
}