{
  "type": "Feature",
  "properties": {
    "addr:full":"Berchembosln 28 Berchem Antwerpen 2600",
    "addr:housenumber":"28",
    "addr:postcode":"2600",
    "addr:street":"Berchembosln;Antwerpen",
    "iso:country":"BE",
    "sg:address":"Berchembosln 28",
    "sg:city":"Berchem",
    "sg:classifiers":[
        {
            "category":"Banks & Credit Unions",
            "subcategory":"Bank",
            "type":"Services"
        }
    ],
    "sg:phone":"+32 3 449 06 77",
    "sg:postcode":"2600",
    "sg:province":"Antwerpen",
    "wof:name":"G\u00e9n\u00e9rale De Banque Sa",
    "wof:placetype":"venue"
},
  "geometry": {"coordinates":[4.4373211861,51.1825866699],"type":"Point"}
}