{
  "type": "Feature",
  "properties": {
    "iso:country":"BE",
    "sg:address":"Rijksweg 67a",
    "sg:city":"Puurs",
    "sg:orig_category":"Verlichting and huishoudartikelen",
    "sg:phone":"+32 3 886 81 38",
    "sg:postcode":"2870",
    "sg:province":"Antwerpen",
    "wof:name":"Euroline-verlichting",
    "wof:placetype":"venue"
},
  "geometry": {"coordinates":[4.2928609848,51.080078125],"type":"Point"}
}