{
  "type": "Feature",
  "properties": {
    "iso:country":"BE",
    "sg:address":"Chauss\u00e9e De Marche 552",
    "sg:city":"Namur (erpent)",
    "sg:classifiers":[
        {
            "category":"Government",
            "subcategory":"Fire Station",
            "type":"Public Place"
        }
    ],
    "sg:phone":"+32 81 30 19 96",
    "sg:postcode":"5101",
    "sg:province":"Namur",
    "sg:tags":[
        "installation",
        "-",
        "air conditioning"
    ],
    "wof:name":"Marichal J-p Ets",
    "wof:placetype":"venue"
},
  "geometry": {"coordinates":[4.9034090042,50.4428062439],"type":"Point"}
}