{
  "type": "Feature",
  "properties": {
    "iso:country":"BE",
    "sg:address":"Rue Albert Elisabeth 274",
    "sg:city":"Binche (p\u00e9ronnes-lez-binche)",
    "sg:classifiers":[
        {
            "category":"Health Services",
            "subcategory":"Doctor",
            "type":"Services"
        }
    ],
    "sg:phone":"+32 64 33 87 26",
    "sg:postcode":"7134",
    "sg:province":"Hainaut",
    "sg:tags":[
        "medicinephysicians",
        "surgeon"
    ],
    "wof:name":"Formato Vincent",
    "wof:placetype":"venue"
},
  "geometry": {"coordinates":[4.1929478645,50.4336700439],"type":"Point"}
}