{
  "type": "Feature",
  "properties": {
    "iso:country":"BE",
    "sg:address":"Kastanjelaan 2",
    "sg:city":"Heist-op-den-berg (itegem)",
    "sg:classifiers":[
        {
            "category":"Professional",
            "subcategory":"Management & Consulting",
            "type":"Services"
        }
    ],
    "sg:phone":"+32 15 24 88 88",
    "sg:postcode":"2222",
    "sg:province":"Antwerpen",
    "sg:tags":[
        "consultant"
    ],
    "wof:name":"K.r.c. Bvba",
    "wof:placetype":"venue"
},
  "geometry": {"coordinates":[4.6927652359,51.0679244995],"type":"Point"}
}