{
  "type": "Feature",
  "properties": {
    "addr:full":"Ieperseweg 54 Poperinge West-Vlaanderen 8970",
    "addr:housenumber":"54",
    "addr:postcode":"8970",
    "addr:street":"Ieperseweg",
    "iso:country":"BE",
    "sg:address":"Ieperseweg 54",
    "sg:city":"Poperinge",
    "sg:classifiers":[
        {
            "category":"Insurance",
            "subcategory":"Life Insurance",
            "type":"Services"
        }
    ],
    "sg:phone":"+32 57 33 57 35",
    "sg:postcode":"8970",
    "sg:province":"West-Vlaanderen",
    "sg:tags":[
        "assurance"
    ],
    "wof:name":"De Leeuw L.-boedts J.",
    "wof:placetype":"venue"
},
  "geometry": {"coordinates":[2.7605659962,50.8558311462],"type":"Point"}
}