{
  "type": "Feature",
  "properties": {
    "iso:country":"BE",
    "sg:address":"Chauss\u00e9e De Waterloo 1469",
    "sg:city":"Bruxelles (uccle)",
    "sg:classifiers":[
        {
            "category":"Shopping",
            "subcategory":"Pawn Shop",
            "type":"Retail Goods"
        }
    ],
    "sg:phone":"+32 2 373 38 64",
    "sg:postcode":"1180",
    "sg:province":"Bruxelles-Capitale",
    "sg:tags":[
        "tax",
        "free"
    ],
    "wof:name":"Diplomatic Cash & Carry",
    "wof:placetype":"venue"
},
  "geometry": {"coordinates":[4.378590107,50.7838058472],"type":"Point"}
}