{
  "type": "Feature",
  "properties": {
    "iso:country":"BE",
    "sg:address":"Rue Du Bois L\u00e0 Haut 1",
    "sg:city":"Mons",
    "sg:classifiers":[
        {
            "category":"Real Estate",
            "subcategory":"Architect",
            "type":"Services"
        }
    ],
    "sg:phone":"+32 65 31 18 55",
    "sg:postcode":"7000",
    "sg:province":"Hainaut",
    "wof:name":"Latour S",
    "wof:placetype":"venue"
},
  "geometry": {"coordinates":[3.9854500294,50.4428405762],"type":"Point"}
}