{
  "type": "Feature",
  "properties": {
    "iso:country":"BE",
    "sg:address":"Leliestraat 25",
    "sg:city":"Hamont-achel",
    "sg:orig_category":"Eleveurs and marchands de porcs",
    "sg:phone":"+32 11 64 48 60",
    "sg:postcode":"3930",
    "sg:province":"Limburg",
    "wof:name":"Van Rooi Import En Export",
    "wof:placetype":"venue"
},
  "geometry": {"coordinates":[5.4801959991,51.2593383789],"type":"Point"}
}