{
  "type": "Feature",
  "properties": {
    "iso:country":"BE",
    "sg:address":"Rue Victor Libert 9",
    "sg:city":"Marche-en-famenne",
    "sg:orig_category":"Rechtbanken",
    "sg:phone":"+32 84 31 11 07",
    "sg:postcode":"6900",
    "sg:province":"Luxembourg",
    "wof:name":"Justice De Paix",
    "wof:placetype":"venue"
},
  "geometry": {"coordinates":[5.3399391174,50.2280006409],"type":"Point"}
}