{
  "type": "Feature",
  "properties": {
    "iso:country":"BE",
    "sg:address":"Avenue Des Sept-bonniers 118",
    "sg:city":"Vorst/forest",
    "sg:orig_category":"Artistes ind\u00e9pendants",
    "sg:phone":"+32 2 344 29 18",
    "sg:postcode":"1190",
    "sg:province":"Bruxelles-Capitale",
    "wof:name":"L. Ganzo",
    "wof:placetype":"venue"
},
  "geometry": {"coordinates":[4.3344688416,50.8122940063],"type":"Point"}
}