{
  "type": "Feature",
  "properties": {
    "addr:full":"Bergstraat 9 Merelbeke Oost-Vlaanderen 9820",
    "addr:housenumber":"9",
    "addr:postcode":"9820",
    "addr:street":"Bergstraat",
    "iso:country":"BE",
    "sg:address":"Bergstraat 9",
    "sg:city":"Merelbeke",
    "sg:orig_category":"Etalage- and showroomontwerpers",
    "sg:phone":"+32 9 230 09 40",
    "sg:postcode":"9820",
    "sg:province":"Oost-Vlaanderen",
    "wof:name":"Lindsay De Croock",
    "wof:placetype":"venue"
},
  "geometry": {"coordinates":[3.7544651031,51.0139045715],"type":"Point"}
}