{
  "type": "Feature",
  "properties": {
    "iso:country":"BE",
    "sg:address":"Frans De L'arbrelaan 1",
    "sg:city":"Antwerpen",
    "sg:orig_category":"Brood, gebak and snoepgoed",
    "sg:phone":"+32 3 645 15 34",
    "sg:postcode":"2170",
    "sg:province":"Antwerpen",
    "wof:name":"Bakkerij Tanja",
    "wof:placetype":"venue"
},
  "geometry": {"coordinates":[4.4397630692,51.2411079407],"type":"Point"}
}