{
  "type": "Feature",
  "properties": {
    "iso:country":"BE",
    "sg:address":"Florali\u00cbnstraat 89b170",
    "sg:city":"Sint-lambrechts-woluwe/woluwe-saint-lambert",
    "sg:orig_category":"Artsen and specialisten",
    "sg:phone":"+32 2 763 20 82",
    "sg:postcode":"1200",
    "sg:province":"Bruxelles-Capitale",
    "wof:name":"Hassan Mir Mohammad Sadeghi",
    "wof:placetype":"venue"
},
  "geometry": {"coordinates":[4.4348378181,50.8453445435],"type":"Point"}
}