{
  "type": "Feature",
  "properties": {
    "iso:country":"BE",
    "sg:address":"De Limburg Stirumlaan 87",
    "sg:city":"Wemmel/wemmel",
    "sg:classifiers":[
        {
            "category":"Professional",
            "subcategory":"Accounting & Tax Preparation",
            "type":"Services"
        }
    ],
    "sg:phone":"+32 2 460 74 98",
    "sg:postcode":"1780",
    "sg:province":"Vlaams-Brabant",
    "sg:tags":[
        "accountant"
    ],
    "wof:name":"Th\u00c9r\u00c8se Geets/t. Geets",
    "wof:placetype":"venue"
},
  "geometry": {"coordinates":[4.3070898056,50.9067382812],"type":"Point"}
}