{
  "type": "Feature",
  "properties": {
    "addr:full":"Rue Du Cornet 127 Bruxelles (etterbeek) Bruxelles-Capitale 1040",
    "addr:housenumber":"127",
    "addr:postcode":"1040",
    "addr:street":"Rue Du Cornet",
    "iso:country":"BE",
    "sg:address":"Rue Du Cornet 127",
    "sg:city":"Bruxelles (etterbeek)",
    "sg:orig_category":"Scenery Stage-, film-, and television",
    "sg:phone":"+32 2 733 11 76",
    "sg:postcode":"1040",
    "sg:province":"Bruxelles-Capitale",
    "wof:name":"Waterkeyn O",
    "wof:placetype":"venue"
},
  "geometry": {"coordinates":[4.3888630867,50.8379516602],"type":"Point"}
}