{
  "type": "Feature",
  "properties": {
    "addr:full":"Kerkstraat 55 Laarne Oost-Vlaanderen 9270",
    "addr:housenumber":"55",
    "addr:postcode":"9270",
    "addr:street":"Kerkstraat",
    "iso:country":"BE",
    "sg:address":"Kerkstraat 55",
    "sg:city":"Laarne",
    "sg:orig_category":"Studios photographiques",
    "sg:phone":"+32 9 366 73 28",
    "sg:postcode":"9270",
    "sg:province":"Oost-Vlaanderen",
    "wof:name":"Studio Mediant",
    "wof:placetype":"venue"
},
  "geometry": {"coordinates":[3.8645000458,51.0385665894],"type":"Point"}
}