{
  "type": "Feature",
  "properties": {
    "iso:country":"BE",
    "sg:address":"Sleestraat 1",
    "sg:city":"Diksmuide",
    "sg:orig_category":"Eleveurs de bovins",
    "sg:phone":"+32 51 50 46 51",
    "sg:postcode":"8600",
    "sg:province":"West-Vlaanderen",
    "wof:name":"Willy Bossant",
    "wof:placetype":"venue"
},
  "geometry": {"coordinates":[2.8123118877,51.015007019],"type":"Point"}
}