{
  "type": "Feature",
  "properties": {
    "addr:full":"Paardskerkhofstraat 8 Neerpelt Limburg 3910",
    "addr:housenumber":"8",
    "addr:postcode":"3910",
    "addr:street":"Paardskerkhofstraat",
    "iso:country":"BE",
    "sg:address":"Paardskerkhofstraat 8",
    "sg:city":"Neerpelt",
    "sg:orig_category":"Benzinestations and brandstoffen",
    "sg:phone":"+32 11 64 86 05",
    "sg:postcode":"3910",
    "sg:province":"Limburg",
    "wof:name":"Laurens Damen",
    "wof:placetype":"venue"
},
  "geometry": {"coordinates":[5.4853949547,51.2304382324],"type":"Point"}
}