{
  "type": "Feature",
  "properties": {
    "addr:full":"Parc Du Peterbos 9 Bruxelles (anderlecht) Bruxelles-Capitale 1070",
    "addr:housenumber":"9",
    "addr:postcode":"1070",
    "addr:street":"Parc Du Peterbos",
    "iso:country":"BE",
    "sg:address":"Parc Du Peterbos 9",
    "sg:city":"Bruxelles (anderlecht)",
    "sg:classifiers":[
        {
            "category":"Professional",
            "subcategory":"Testing Lab",
            "type":"Services"
        }
    ],
    "sg:phone":"+32 2 524 04 75",
    "sg:postcode":"1070",
    "sg:province":"Bruxelles-Capitale",
    "sg:tags":[
        "chemist"
    ],
    "wof:name":"Peterbos (du)",
    "wof:placetype":"venue"
},
  "geometry": {"coordinates":[4.294588089,50.8417739868],"type":"Point"}
}