{
  "type": "Feature",
  "properties": {
    "iso:country":"BE",
    "sg:address":"Blauwstraat 17",
    "sg:city":"Boom",
    "sg:orig_category":"Baby- and kinderkleding Kleding",
    "sg:phone":"+32 3 888 13 46",
    "sg:postcode":"2850",
    "sg:province":"Antwerpen",
    "wof:name":"West-kids",
    "wof:placetype":"venue"
},
  "geometry": {"coordinates":[4.3669638634,51.0864486694],"type":"Point"}
}