{
  "type": "Feature",
  "properties": {
    "addr:full":"Smedenstraat 119 Knokke-heist West-Vlaanderen 8300",
    "addr:housenumber":"119",
    "addr:postcode":"8300",
    "addr:street":"Smedenstraat",
    "iso:country":"BE",
    "sg:address":"Smedenstraat 119",
    "sg:city":"Knokke-heist",
    "sg:classifiers":[
        {
            "category":"Cafe",
            "type":"Food & Drink"
        }
    ],
    "sg:phone":"+32 50 61 56 79",
    "sg:postcode":"8300",
    "sg:province":"West-Vlaanderen",
    "sg:tags":[
        "caf\u00e9s"
    ],
    "wof:name":"Carina Brams",
    "wof:placetype":"venue"
},
  "geometry": {"coordinates":[3.2939610481,51.3368911743],"type":"Point"}
}