{
  "type": "Feature",
  "properties": {
    "iso:country":"BE",
    "sg:address":"Kortrijksestraat 99",
    "sg:city":"Harelbeke",
    "sg:classifiers":[
        {
            "category":"Bars & Pubs",
            "type":"Food & Drink"
        }
    ],
    "sg:phone":"+32 56 70 21 78",
    "sg:postcode":"8530",
    "sg:province":"West-Vlaanderen",
    "wof:name":"Comix (the)",
    "wof:placetype":"venue"
},
  "geometry": {"coordinates":[3.3050301075,50.8520126343],"type":"Point"}
}