{
  "type": "Feature",
  "properties": {
    "iso:country":"BE",
    "sg:address":"Pittemstraat 56",
    "sg:city":"Meulebeke",
    "sg:classifiers":[
        {
            "category":"Structure",
            "subcategory":"Building",
            "type":"Public Place"
        }
    ],
    "sg:phone":"+32 51 48 91 71",
    "sg:postcode":"8760",
    "sg:province":"West-Vlaanderen",
    "sg:tags":[
        "apartment"
    ],
    "wof:name":"Vuylsteke Chris Nv",
    "wof:placetype":"venue"
},
  "geometry": {"coordinates":[3.2869460583,50.9534454346],"type":"Point"}
}