{
  "type": "Feature",
  "properties": {
    "addr:full":"Stationstraat 12 Haacht (groot) Vlaams-Brabant 3150",
    "addr:housenumber":"12",
    "addr:postcode":"3150",
    "addr:street":"Stationstraat;Groot Vlaams-Brabant",
    "iso:country":"BE",
    "sg:address":"Stationstraat 12",
    "sg:city":"Haacht (groot)",
    "sg:orig_category":"Banques and organismes de cr\u00e9dit",
    "sg:phone":"+32 16 60 28 82",
    "sg:postcode":"3150",
    "sg:province":"Vlaams-Brabant",
    "wof:name":"Dexia",
    "wof:placetype":"venue"
},
  "geometry": {"coordinates":[4.6346387863,50.9771080017],"type":"Point"}
}