{
  "type": "Feature",
  "properties": {
    "iso:country":"BE",
    "sg:address":"Sint-annastraat 18",
    "sg:city":"Oudenaarde",
    "sg:orig_category":"Travaux d'isolation",
    "sg:phone":"+32 55 30 15 07",
    "sg:postcode":"9700",
    "sg:province":"Oost-Vlaanderen",
    "wof:name":"Interieurbouw Dezutter",
    "wof:placetype":"venue"
},
  "geometry": {"coordinates":[3.6140019894,50.8637237549],"type":"Point"}
}