{
  "type": "Feature",
  "properties": {
    "iso:country":"BE",
    "sg:address":"Rue Saumont 21",
    "sg:city":"Marche-en-famenne (aye)",
    "sg:classifiers":[
        {
            "category":"Personal",
            "subcategory":"Barber",
            "type":"Services"
        }
    ],
    "sg:phone":"+32 84 32 15 93",
    "sg:postcode":"6900",
    "sg:province":"Luxembourg",
    "sg:tags":[
        "gentleman",
        "salon",
        "-",
        "hairdressing"
    ],
    "wof:name":"Lamoline I",
    "wof:placetype":"venue"
},
  "geometry": {"coordinates":[5.3000388145,50.2293586731],"type":"Point"}
}