{
  "type": "Feature",
  "properties": {
    "iso:country":"BE",
    "sg:address":"Kachtemsestraat 80",
    "sg:city":"Roeselare",
    "sg:orig_category":"D\u00e9taillants en pi\u00e8ces and accessoires de voitures. Entretien and r\u00e9parations de voitures",
    "sg:phone":"+32 51 22 52 63",
    "sg:postcode":"8800",
    "sg:province":"West-Vlaanderen",
    "wof:name":"Garage Vermote",
    "wof:placetype":"venue"
},
  "geometry": {"coordinates":[3.1512770653,50.9465827942],"type":"Point"}
}