{
  "type": "Feature",
  "properties": {
    "addr:full":"Weverstraat 54 Vremde Antwerpen 2531",
    "addr:housenumber":"54",
    "addr:postcode":"2531",
    "addr:street":"Weverstraat",
    "iso:country":"BE",
    "sg:address":"Weverstraat 54",
    "sg:city":"Vremde",
    "sg:classifiers":[
        {
            "category":"Professional",
            "subcategory":"Accounting & Tax Preparation",
            "type":"Services"
        }
    ],
    "sg:phone":"+32 3 455 00 78",
    "sg:postcode":"2531",
    "sg:province":"Antwerpen",
    "sg:tags":[
        "financial",
        "software"
    ],
    "wof:name":"Bumico B.v.b.a.",
    "wof:placetype":"venue"
},
  "geometry": {"coordinates":[4.5169849396,51.1770057678],"type":"Point"}
}