{
  "type": "Feature",
  "properties": {
    "addr:full":"Deken Bernardstraat 4 Maasmechelen Limburg 3630",
    "addr:housenumber":"4",
    "addr:postcode":"3630",
    "addr:street":"Deken Bernardstraat",
    "iso:country":"BE",
    "sg:address":"Deken Bernardstraat 4",
    "sg:city":"Maasmechelen",
    "sg:orig_category":"Non-Classified Establishments",
    "sg:phone":"+32 89 77 97 30",
    "sg:postcode":"3630",
    "sg:province":"Limburg",
    "wof:name":"Vrije Centra Voor Leerlingenbegeleiding Maasland Vzw",
    "wof:placetype":"venue"
},
  "geometry": {"coordinates":[5.697136879,50.962272644],"type":"Point"}
}