{
  "type": "Feature",
  "properties": {
    "iso:country":"BE",
    "sg:address":"Leuvensebaan 233",
    "sg:city":"Putte",
    "sg:orig_category":"Boucheries",
    "sg:phone":"+32 15 75 20 50",
    "sg:postcode":"2580",
    "sg:province":"Antwerpen",
    "wof:name":"Torino",
    "wof:placetype":"venue"
},
  "geometry": {"coordinates":[4.6369571686,51.0300827026],"type":"Point"}
}