{
  "type": "Feature",
  "properties": {
    "iso:country":"BE",
    "sg:address":"Fazantenlaan 36",
    "sg:city":"Zedelgem",
    "sg:orig_category":"Activit\u00e9s r\u00e9cr\u00e9atives diverses",
    "sg:phone":"+32 50 20 14 28",
    "sg:postcode":"8210",
    "sg:province":"West-Vlaanderen",
    "wof:name":"Bridge Club Chaver",
    "wof:placetype":"venue"
},
  "geometry": {"coordinates":[3.1461780071,51.1421585083],"type":"Point"}
}