{
  "type": "Feature",
  "properties": {
    "addr:full":"Heieinde 84 Oud-turnhout Antwerpen 2360",
    "addr:housenumber":"84",
    "addr:postcode":"2360",
    "addr:street":"Heieinde",
    "iso:country":"BE",
    "sg:address":"Heieinde 84",
    "sg:city":"Oud-turnhout",
    "sg:orig_category":"Fruitteelt",
    "sg:phone":"+32 14 41 47 68",
    "sg:postcode":"2360",
    "sg:province":"Antwerpen",
    "wof:name":"Pierre Marien",
    "wof:placetype":"venue"
},
  "geometry": {"coordinates":[4.9821138382,51.3401870728],"type":"Point"}
}