{
  "type": "Feature",
  "properties": {
    "iso:country":"BE",
    "sg:address":"Rue De La Kan 79",
    "sg:city":"Aubel",
    "sg:orig_category":"Overheidsdiensten",
    "sg:phone":"+32 87 68 72 14",
    "sg:postcode":"4880",
    "sg:province":"Li\u00e8ge",
    "wof:name":"C.p.a.s.",
    "wof:placetype":"venue"
},
  "geometry": {"coordinates":[5.8649258614,50.7060470581],"type":"Point"}
}