{
  "type": "Feature",
  "properties": {
    "addr:full":"Gal Du Centre 24 Bruxelles Bruxelles-Capitale 1000",
    "addr:housenumber":"24",
    "addr:postcode":"1000",
    "iso:country":"BE",
    "sg:address":"Gal Du Centre 24",
    "sg:city":"Bruxelles",
    "sg:classifiers":[
        {
            "category":"Personal",
            "subcategory":"Beauty Salon",
            "type":"Services"
        }
    ],
    "sg:phone":"+32 2 223 09 97",
    "sg:postcode":"1000",
    "sg:province":"Bruxelles-Capitale",
    "sg:tags":[
        "de",
        "coiffure"
    ],
    "wof:name":"Coiffure D'erive",
    "wof:placetype":"venue"
},
  "geometry": {"coordinates":[4.3527669907,50.848651886],"type":"Point"}
}