{
  "type": "Feature",
  "properties": {
    "addr:full":"Ch De Haecht 584 Bruxelles Bruxelles-Capitale 1030",
    "addr:housenumber":"584",
    "addr:postcode":"1030",
    "addr:street":"Ch De Haecht",
    "iso:country":"BE",
    "sg:address":"Ch De Haecht 584",
    "sg:city":"Bruxelles",
    "sg:classifiers":[
        {
            "category":"Manufacturing",
            "subcategory":"Chemicals & Compounds",
            "type":"Manufacturing & Wholesale Goods"
        }
    ],
    "sg:phone":"+32 2 241 73 88",
    "sg:postcode":"1030",
    "sg:province":"Bruxelles-Capitale",
    "sg:tags":[
        "pharmaceutical",
        "chemistry",
        "-",
        "by-product"
    ],
    "wof:name":"C Van Haecht",
    "wof:placetype":"venue"
},
  "geometry": {"coordinates":[4.3877887726,50.8693275452],"type":"Point"}
}