{
  "type": "Feature",
  "properties": {
    "addr:full":"Malgr\u00c9toutstraat 79 Kortrijk West-Vlaanderen 8511",
    "addr:housenumber":"79",
    "addr:postcode":"8511",
    "addr:street":"Malgre\u0301Toutstraat",
    "iso:country":"BE",
    "sg:address":"Malgr\u00c9toutstraat 79",
    "sg:city":"Kortrijk",
    "sg:orig_category":"Eleveurs de bovins",
    "sg:phone":"+32 56 41 41 85",
    "sg:postcode":"8511",
    "sg:province":"West-Vlaanderen",
    "wof:name":"Gaston Labis",
    "wof:placetype":"venue"
},
  "geometry": {"coordinates":[3.2284300327,50.7639694214],"type":"Point"}
}