{
  "type": "Feature",
  "properties": {
    "addr:full":"Rue Saivelette 78 Blegny Li\u00e8ge 4671",
    "addr:housenumber":"78",
    "addr:postcode":"4671",
    "addr:street":"Rue Saivelette",
    "iso:country":"BE",
    "sg:address":"Rue Saivelette 78",
    "sg:city":"Blegny",
    "sg:orig_category":"Experts-comptables",
    "sg:phone":"+32 4 362 49 09",
    "sg:postcode":"4671",
    "sg:province":"Li\u00e8ge",
    "wof:name":"Caroline Louis",
    "wof:placetype":"venue"
},
  "geometry": {"coordinates":[5.6820588112,50.6480712891],"type":"Point"}
}