{
  "type": "Feature",
  "properties": {
    "iso:country":"BE",
    "sg:address":"Rue De Ch\u00e8vremont 35",
    "sg:city":"Chaudfontaine (vaux-sous-ch\u00e8vremont)",
    "sg:classifiers":[
        {
            "category":"Retail",
            "subcategory":"Event Space",
            "type":"Services"
        }
    ],
    "sg:phone":"+32 4 367 03 32",
    "sg:postcode":"4051",
    "sg:province":"Li\u00e8ge",
    "sg:tags":[
        "rental",
        "-",
        "hall"
    ],
    "wof:name":"Grillons (les)",
    "wof:placetype":"venue"
},
  "geometry": {"coordinates":[5.6490168571,50.6013069153],"type":"Point"}
}