{
  "type": "Feature",
  "properties": {
    "addr:full":"Hennepstraat 19 Antwerpen Antwerpen 2170",
    "addr:housenumber":"19",
    "addr:postcode":"2170",
    "addr:street":"Hennepstraat",
    "iso:country":"BE",
    "sg:address":"Hennepstraat 19",
    "sg:city":"Antwerpen",
    "sg:orig_category":"Boekhouders",
    "sg:phone":"+32 3 646 77 90",
    "sg:postcode":"2170",
    "sg:province":"Antwerpen",
    "wof:name":"Tom Peeters",
    "wof:placetype":"venue"
},
  "geometry": {"coordinates":[4.4505147934,51.246723175],"type":"Point"}
}