{
  "type": "Feature",
  "properties": {
    "addr:full":"Koning Albertstraat 37 Lint Antwerpen 2547",
    "addr:housenumber":"37",
    "addr:postcode":"2547",
    "addr:street":"Koning Albertstraat",
    "iso:country":"BE",
    "sg:address":"Koning Albertstraat 37",
    "sg:city":"Lint",
    "sg:orig_category":"Foto-uitrusting",
    "sg:phone":"+32 3 488 26 94",
    "sg:postcode":"2547",
    "sg:province":"Antwerpen",
    "wof:name":"Huis Fotix",
    "wof:placetype":"venue"
},
  "geometry": {"coordinates":[4.4941749573,51.1277351379],"type":"Point"}
}