{
  "type": "Feature",
  "properties": {
    "iso:country":"BE",
    "sg:address":"Goelevenweg 2",
    "sg:city":"Waregem",
    "sg:orig_category":"Non-Classified Establishments",
    "sg:phone":"+32 56 60 11 32",
    "sg:postcode":"8790",
    "sg:province":"West-Vlaanderen",
    "wof:name":"Bulcaen Nv",
    "wof:placetype":"venue"
},
  "geometry": {"coordinates":[3.408780098,50.8612442017],"type":"Point"}
}