{
  "type": "Feature",
  "properties": {
    "iso:country":"BE",
    "sg:address":"Rue De La Place 51",
    "sg:city":"Ramillies",
    "sg:orig_category":"Artsen and specialisten",
    "sg:phone":"+32 81 87 72 45",
    "sg:postcode":"1367",
    "sg:province":"Brabant Wallon",
    "wof:name":"Jean-pierre Berchem",
    "wof:placetype":"venue"
},
  "geometry": {"coordinates":[4.920525074,50.6647949219],"type":"Point"}
}