{
  "type": "Feature",
  "properties": {
    "iso:country":"BE",
    "sg:address":"Diestsestraat 108",
    "sg:city":"Leuven",
    "sg:orig_category":"Schoenen Sport- and kampeermateriaal",
    "sg:phone":"+32 16 23 15 66",
    "sg:postcode":"3000",
    "sg:province":"Vlaams-Brabant",
    "wof:name":"All-sport",
    "wof:placetype":"venue"
},
  "geometry": {"coordinates":[4.7079181671,50.8807907104],"type":"Point"}
}