{
  "type": "Feature",
  "properties": {
    "addr:full":"Sprietstraat 4 Ardooie West-Vlaanderen 8850",
    "addr:housenumber":"4",
    "addr:postcode":"8850",
    "addr:street":"Sprietstraat",
    "iso:country":"BE",
    "sg:address":"Sprietstraat 4",
    "sg:city":"Ardooie",
    "sg:orig_category":"Installation de menuiserie en bois and plastique",
    "sg:phone":"+32 51 74 40 15",
    "sg:postcode":"8850",
    "sg:province":"West-Vlaanderen",
    "wof:name":"Guido Vanhaverbeke",
    "wof:placetype":"venue"
},
  "geometry": {"coordinates":[3.1901929379,50.9789009094],"type":"Point"}
}