{
  "type": "Feature",
  "properties": {
    "addr:full":"Rue Roc Saint-nicaise 5a Tournai Hainaut 7500",
    "addr:housenumber":"5a",
    "addr:postcode":"7500",
    "addr:street":"Rue Roc Saint-Nicaise",
    "iso:country":"BE",
    "sg:address":"Rue Roc Saint-nicaise 5a",
    "sg:city":"Tournai",
    "sg:classifiers":[
        {
            "category":"Health Services",
            "subcategory":"Health Practitioner",
            "type":"Services"
        }
    ],
    "sg:phone":"+32 69 84 12 18",
    "sg:postcode":"7500",
    "sg:province":"Hainaut",
    "sg:tags":[
        "physiotherapist"
    ],
    "wof:name":"Gerin A-f",
    "wof:placetype":"venue"
},
  "geometry": {"coordinates":[3.3832249641,50.6060066223],"type":"Point"}
}