{
  "type": "Feature",
  "properties": {
    "addr:full":"Rue Boniface 24 Anderlues Hainaut 6150",
    "addr:housenumber":"24",
    "addr:postcode":"6150",
    "addr:street":"Rue Boniface",
    "iso:country":"BE",
    "sg:address":"Rue Boniface 24",
    "sg:city":"Anderlues",
    "sg:orig_category":"Epiceries",
    "sg:phone":"+32 71 52 02 04",
    "sg:postcode":"6150",
    "sg:province":"Hainaut",
    "wof:name":"Chez Sylviane",
    "wof:placetype":"venue"
},
  "geometry": {"coordinates":[4.2805128098,50.3927574158],"type":"Point"}
}