{
  "type": "Feature",
  "properties": {
    "iso:country":"BE",
    "sg:address":"Steenhout 29",
    "sg:city":"Ninove (denderwindeke)",
    "sg:classifiers":[
        {
            "category":"Health Services",
            "subcategory":"Health Practitioner",
            "type":"Services"
        }
    ],
    "sg:phone":"+32 54 33 41 79",
    "sg:postcode":"9400",
    "sg:province":"Oost-Vlaanderen",
    "sg:tags":[
        "osteopath"
    ],
    "wof:name":"De Troy Kris",
    "wof:placetype":"venue"
},
  "geometry": {"coordinates":[4.0260901451,50.7854499817],"type":"Point"}
}