{
  "type": "Feature",
  "properties": {
    "iso:country":"BE",
    "sg:address":"Boulevard Industriel 109",
    "sg:city":"Anderlecht",
    "sg:orig_category":"Location de voitures",
    "sg:phone":"+32 2 526 10 70",
    "sg:postcode":"1070",
    "sg:province":"Bruxelles-Capitale",
    "wof:name":"C.w. Lease Belgium",
    "wof:placetype":"venue"
},
  "geometry": {"coordinates":[4.3081541061,50.8195953369],"type":"Point"}
}