{
  "type": "Feature",
  "properties": {
    "iso:country":"BE",
    "sg:address":"Lostraat 49",
    "sg:city":"Nevele",
    "sg:orig_category":"Maisons de vacances. Agences de voyages",
    "sg:phone":"+32 9 362 31 42",
    "sg:postcode":"9850",
    "sg:province":"Oost-Vlaanderen",
    "wof:name":"Cap",
    "wof:placetype":"venue"
},
  "geometry": {"coordinates":[3.5886249542,51.0877761841],"type":"Point"}
}