{
  "type": "Feature",
  "properties": {
    "iso:country":"BE",
    "sg:address":"Rue Emile-pirson 2",
    "sg:city":"Sombreffe",
    "sg:orig_category":"Eleveurs de bovins",
    "sg:phone":"+32 71 88 80 24",
    "sg:postcode":"5140",
    "sg:province":"Namur",
    "wof:name":"Emile Vigneron",
    "wof:placetype":"venue"
},
  "geometry": {"coordinates":[4.615363121,50.538860321],"type":"Point"}
}