{
  "type": "Feature",
  "properties": {
    "addr:full":"Mechelsesteenweg 7bb5 Rumst Antwerpen 2840",
    "addr:housenumber":"7bb5",
    "addr:postcode":"2840",
    "addr:street":"Mechelsesteenweg",
    "iso:country":"BE",
    "sg:address":"Mechelsesteenweg 7bb5",
    "sg:city":"Rumst",
    "sg:orig_category":"Artistes ind\u00e9pendants",
    "sg:phone":"+32 15 32 21 49",
    "sg:postcode":"2840",
    "sg:province":"Antwerpen",
    "wof:name":"Anke Helsen",
    "wof:placetype":"venue"
},
  "geometry": {"coordinates":[4.4523849487,51.0844421387],"type":"Point"}
}