{
  "type": "Feature",
  "properties": {
    "iso:country":"BE",
    "sg:address":"Aristide Briandlaan 9",
    "sg:city":"Anderlecht",
    "sg:orig_category":"Beautyfarms, relaxatie and lichamelijk welzijn",
    "sg:phone":"+32 2 521 19 18",
    "sg:postcode":"1070",
    "sg:province":"Bruxelles-Capitale",
    "wof:name":"Sunails",
    "wof:placetype":"venue"
},
  "geometry": {"coordinates":[4.303126812,50.8291015625],"type":"Point"}
}