{
  "type": "Feature",
  "properties": {
    "addr:full":"Rue Georges Mabile 91 Mons (havr\u00e9) Hainaut 7021",
    "addr:housenumber":"91",
    "addr:postcode":"7021",
    "addr:street":"Rue Georges Mabile",
    "iso:country":"BE",
    "sg:address":"Rue Georges Mabile 91",
    "sg:city":"Mons (havr\u00e9)",
    "sg:classifiers":[
        {
            "category":"Autos & Motor Vehicles",
            "subcategory":"Recreational Vehicle Sales",
            "type":"Retail Goods"
        }
    ],
    "sg:phone":"+32 65 87 15 05",
    "sg:postcode":"7021",
    "sg:province":"Hainaut",
    "sg:tags":[
        "saw"
    ],
    "wof:name":"Lesage M",
    "wof:placetype":"venue"
},
  "geometry": {"coordinates":[4.0456829071,50.4640655518],"type":"Point"}
}