{
  "type": "Feature",
  "properties": {
    "iso:country":"BE",
    "sg:address":"Avenue Hanlet 52",
    "sg:city":"Verviers",
    "sg:orig_category":"Advocaten and juridische adviseurs",
    "sg:phone":"+32 87 22 35 13",
    "sg:postcode":"4802",
    "sg:province":"Li\u00e8ge",
    "wof:name":"F. Chantraine",
    "wof:placetype":"venue"
},
  "geometry": {"coordinates":[5.8642840385,50.5820388794],"type":"Point"}
}