{
  "type": "Feature",
  "properties": {
    "iso:country":"BE",
    "sg:address":"Tervuursesteenweg 668",
    "sg:city":"Zemst (elewijt)",
    "sg:classifiers":[
        {
            "category":"Freight",
            "type":"Transportation"
        }
    ],
    "sg:phone":"+32 15 61 13 51",
    "sg:postcode":"1982",
    "sg:province":"Vlaams-Brabant",
    "sg:tags":[
        "-",
        "transport"
    ],
    "wof:name":"Transport De Laet Bvba",
    "wof:placetype":"venue"
},
  "geometry": {"coordinates":[4.4960379601,50.966796875],"type":"Point"}
}