{
  "type": "Feature",
  "properties": {
    "addr:full":"Oudestraat 14 Peer Limburg 3990",
    "addr:housenumber":"14",
    "addr:postcode":"3990",
    "addr:street":"Oudestraat",
    "iso:country":"BE",
    "sg:address":"Oudestraat 14",
    "sg:city":"Peer",
    "sg:orig_category":"Brood, gebak and snoepgoed",
    "sg:phone":"+32 11 63 20 40",
    "sg:postcode":"3990",
    "sg:province":"Limburg",
    "wof:name":"Huis 't Snuikerke",
    "wof:placetype":"venue"
},
  "geometry": {"coordinates":[5.4566650391,51.1311798096],"type":"Point"}
}