{
  "type": "Feature",
  "properties": {
    "addr:full":"Vluchtenboerstraat 59 Gavere Oost-Vlaanderen 9890",
    "addr:housenumber":"59",
    "addr:postcode":"9890",
    "addr:street":"Vluchtenboerstraat",
    "iso:country":"BE",
    "sg:address":"Vluchtenboerstraat 59",
    "sg:city":"Gavere",
    "sg:classifiers":[
        {
            "category":"Professional",
            "type":"Services"
        }
    ],
    "sg:phone":"+32 9 384 85 55",
    "sg:postcode":"9890",
    "sg:province":"Oost-Vlaanderen",
    "sg:tags":[
        "surveyor",
        "-",
        "valuer"
    ],
    "wof:name":"Goetgebuer-bottequin Bvba",
    "wof:placetype":"venue"
},
  "geometry": {"coordinates":[3.6731300354,50.9294433594],"type":"Point"}
}