{
  "type": "Feature",
  "properties": {
    "addr:full":"Rue Des Lattes 7ba Cerfontaine Namur 5630",
    "addr:housenumber":"7ba",
    "addr:postcode":"5630",
    "addr:street":"Rue Des Lattes",
    "iso:country":"BE",
    "sg:address":"Rue Des Lattes 7ba",
    "sg:city":"Cerfontaine",
    "sg:orig_category":"Dakwerken Installatie van houten of kunststof schrijnwerk Loodgieterij, verwarming and sanitaire ins",
    "sg:phone":"+32 71 61 13 70",
    "sg:postcode":"5630",
    "sg:province":"Namur",
    "wof:name":"Ren\u00c9 Robert -charles",
    "wof:placetype":"venue"
},
  "geometry": {"coordinates":[4.4580860138,50.2178382874],"type":"Point"}
}