{
  "type": "Feature",
  "properties": {
    "iso:country":"BE",
    "sg:address":"336",
    "sg:city":"Blankenbergse Steenweg 8000 Brugge",
    "sg:classifiers":[
        {
            "category":"Utilities",
            "subcategory":"Electric",
            "type":"Services"
        }
    ],
    "sg:phone":"+32 50 31 46 29",
    "sg:postcode":"336",
    "sg:tags":[
        "electricity",
        "electronic",
        "electrical",
        "equipment"
    ],
    "wof:name":"Busschaert Victor Cyriel M.",
    "wof:placetype":"venue"
},
  "geometry": {"coordinates":[3.1961491108,51.2412643433],"type":"Point"}
}