{
  "type": "Feature",
  "properties": {
    "iso:country":"BE",
    "sg:address":"Terhulpsesteenweg 171",
    "sg:city":"Watermaal-bosvoorde/watermael-boitsfort",
    "sg:orig_category":"Industri\u00eble and commerci\u00eble bouw",
    "sg:phone":"+32 2 663 60 00",
    "sg:postcode":"1170",
    "sg:province":"Bruxelles-Capitale",
    "wof:name":"B\u00c2timents & Ponts Constr.",
    "wof:placetype":"venue"
},
  "geometry": {"coordinates":[4.4016389847,50.7960395813],"type":"Point"}
}