{
  "type": "Feature",
  "properties": {
    "addr:full":"Lange Leemstraat 119 Antwerpen Antwerpen 2018",
    "addr:housenumber":"119",
    "addr:postcode":"2018",
    "addr:street":"Lange Leemstraat",
    "iso:country":"BE",
    "sg:address":"Lange Leemstraat 119",
    "sg:city":"Antwerpen",
    "sg:orig_category":"Herstelling leer and schoeisel",
    "sg:phone":"+32 3 218 62 66",
    "sg:postcode":"2018",
    "sg:province":"Antwerpen",
    "wof:name":"Schoenmakerij Schubert",
    "wof:placetype":"venue"
},
  "geometry": {"coordinates":[4.4132900238,51.2079124451],"type":"Point"}
}