{
  "type": "Feature",
  "properties": {
    "addr:full":"Rue Du Roteux 37 L\u00e9glise Luxembourg 6860",
    "addr:housenumber":"37",
    "addr:postcode":"6860",
    "addr:street":"Rue Du Roteux",
    "iso:country":"BE",
    "sg:address":"Rue Du Roteux 37",
    "sg:city":"L\u00e9glise",
    "sg:classifiers":[
        {
            "category":"Structure",
            "subcategory":"Office Building",
            "type":"Public Place"
        }
    ],
    "sg:phone":"+32 63 42 23 16",
    "sg:postcode":"6860",
    "sg:province":"Luxembourg",
    "sg:tags":[
        "roofing",
        "slate"
    ],
    "wof:name":"Didier Evrard",
    "wof:placetype":"venue"
},
  "geometry": {"coordinates":[5.6021199226,49.7828826904],"type":"Point"}
}