{
  "type": "Feature",
  "properties": {
    "iso:country":"BE",
    "sg:address":"Rue Eug\u00c8ne Smits 28",
    "sg:city":"Schaarbeek/schaerbeek",
    "sg:orig_category":"Plomberie, chauffage and installations sanitaires. Installation \u00e9lectrique industrielle. Installatio",
    "sg:phone":"+32 2 215 32 57",
    "sg:postcode":"1030",
    "sg:province":"Bruxelles-Capitale",
    "wof:name":"Meunier Ch. & Cie",
    "wof:placetype":"venue"
},
  "geometry": {"coordinates":[4.382144928,50.8577232361],"type":"Point"}
}