{
  "type": "Feature",
  "properties": {
    "iso:country":"BE",
    "sg:address":"Parkstraat 31",
    "sg:city":"Wevelgem",
    "sg:orig_category":"Installation de menuiserie m\u00e9tallique. Installation de menuiserie en bois and plastique",
    "sg:phone":"+32 56 40 15 27",
    "sg:postcode":"8560",
    "sg:province":"West-Vlaanderen",
    "wof:name":"Marcel Vereecke",
    "wof:placetype":"venue"
},
  "geometry": {"coordinates":[3.1728239059,50.8051528931],"type":"Point"}
}