{
  "type": "Feature",
  "properties": {
    "addr:full":"Leuvensesteenweg D50 Zaventem Vlaams-Brabant 1932",
    "addr:housenumber":"d50",
    "addr:postcode":"1932",
    "addr:street":"Leuvensesteenweg",
    "iso:country":"BE",
    "sg:address":"Leuvensesteenweg D50",
    "sg:city":"Zaventem",
    "sg:orig_category":"D\u00e9taillants en pi\u00e8ces and accessoires de voitures",
    "sg:phone":"+32 2 720 80 97",
    "sg:postcode":"1932",
    "sg:province":"Vlaams-Brabant",
    "wof:name":"Soregi",
    "wof:placetype":"venue"
},
  "geometry": {"coordinates":[4.4498548508,50.8691558838],"type":"Point"}
}