{
  "type": "Feature",
  "properties": {
    "iso:country":"BE",
    "sg:address":"Koornzakstraat 15",
    "sg:city":"Meulebeke",
    "sg:classifiers":[
        {
            "category":"Professional",
            "subcategory":"Lawyer & Legal Services",
            "type":"Services"
        }
    ],
    "sg:phone":"+32 51 48 94 33",
    "sg:postcode":"8760",
    "sg:province":"West-Vlaanderen",
    "wof:name":"Behaeghe Ingrid",
    "wof:placetype":"venue"
},
  "geometry": {"coordinates":[3.2957429886,50.9439811707],"type":"Point"}
}