{
  "type": "Feature",
  "properties": {
    "iso:country":"BE",
    "sg:address":"Vlasmarkt 45",
    "sg:city":"Dendermonde",
    "sg:orig_category":"RESTAURANTS: CAF\u00c9S",
    "sg:phone":"+32 52 22 43 44",
    "sg:postcode":"9200",
    "sg:province":"Oost-Vlaanderen",
    "wof:name":"Taverne De Vlasmarkt",
    "wof:placetype":"venue"
},
  "geometry": {"coordinates":[4.0989718437,51.0290603638],"type":"Point"}
}