{
  "type": "Feature",
  "properties": {
    "iso:country":"BE",
    "sg:address":"Rue Melsens 38",
    "sg:city":"Bruxelles",
    "sg:classifiers":[
        {
            "category":"Community Center",
            "subcategory":"Youth",
            "type":"Public Place"
        }
    ],
    "sg:phone":"+32 2 279 59 46",
    "sg:postcode":"1000",
    "sg:province":"Bruxelles-Capitale",
    "sg:tags":[
        "club"
    ],
    "wof:name":"St-catherine",
    "wof:placetype":"venue"
},
  "geometry": {"coordinates":[4.3485012054,50.8502960205],"type":"Point"}
}