{
  "type": "Feature",
  "properties": {
    "addr:full":"Zitteblokveld 73 Herent Vlaams-Brabant 3020",
    "addr:housenumber":"73",
    "addr:postcode":"3020",
    "addr:street":"Zitteblokveld",
    "iso:country":"BE",
    "sg:address":"Zitteblokveld 73",
    "sg:city":"Herent",
    "sg:classifiers":[
        {
            "category":"Building & Trades",
            "subcategory":"Pest Control",
            "type":"Services"
        }
    ],
    "sg:phone":"+32 16 20 57 62",
    "sg:postcode":"3020",
    "sg:province":"Vlaams-Brabant",
    "sg:tags":[
        "painting",
        "contractor"
    ],
    "wof:name":"Cuypers C Nv",
    "wof:placetype":"venue"
},
  "geometry": {"coordinates":[4.6644291878,50.9076271057],"type":"Point"}
}