{
  "type": "Feature",
  "properties": {
    "addr:full":"Chauss\u00e9e De Waterloo 1381 Bruxelles (uccle) Bruxelles-Capitale 1180",
    "addr:housenumber":"1381",
    "addr:postcode":"1180",
    "addr:street":"Chausse\u0301E De Waterloo",
    "iso:country":"BE",
    "sg:address":"Chauss\u00e9e De Waterloo 1381",
    "sg:city":"Bruxelles (uccle)",
    "sg:classifiers":[
        {
            "category":"Structure",
            "subcategory":"Office Building",
            "type":"Public Place"
        }
    ],
    "sg:phone":"+32 2 374 29 53",
    "sg:postcode":"1180",
    "sg:province":"Bruxelles-Capitale",
    "sg:tags":[
        "drawing"
    ],
    "wof:name":"Debarre A",
    "wof:placetype":"venue"
},
  "geometry": {"coordinates":[4.3755931854,50.7875900269],"type":"Point"}
}