{
  "type": "Feature",
  "properties": {
    "iso:country":"BE",
    "sg:address":"Avenue Franklin Roosevelt 27b",
    "sg:city":"Vis\u00e9",
    "sg:classifiers":[
        {
            "category":"Professional",
            "type":"Services"
        }
    ],
    "sg:phone":"+32 4 379 73 00",
    "sg:postcode":"4600",
    "sg:province":"Li\u00e8ge",
    "sg:tags":[
        "sharpening"
    ],
    "wof:name":"Affu-service",
    "wof:placetype":"venue"
},
  "geometry": {"coordinates":[5.6857948303,50.7373695374],"type":"Point"}
}