{
  "type": "Feature",
  "properties": {
    "iso:country":"BE",
    "sg:address":"Pennemansbaan 24a",
    "sg:city":"Laarne",
    "sg:orig_category":"HUISBRANDOLIE",
    "sg:phone":"+32 9 367 50 04",
    "sg:postcode":"9270",
    "sg:province":"Oost-Vlaanderen",
    "wof:name":"Kuys Andr\u00c9",
    "wof:placetype":"venue"
},
  "geometry": {"coordinates":[3.9230659008,51.0438919067],"type":"Point"}
}