{
  "type": "Feature",
  "properties": {
    "addr:full":"Antwerpsesteenweg 172 Malle Antwerpen 2390",
    "addr:housenumber":"172",
    "addr:postcode":"2390",
    "addr:street":"Antwerpsesteenweg",
    "iso:country":"BE",
    "sg:address":"Antwerpsesteenweg 172",
    "sg:city":"Malle",
    "sg:classifiers":[
        {
            "category":"Fast Food",
            "type":"Food & Drink"
        }
    ],
    "sg:phone":"+32 3 312 32 15",
    "sg:postcode":"2390",
    "sg:province":"Antwerpen",
    "sg:tags":[
        "\u00c0",
        "restaurants",
        "emporter",
        "restaurant"
    ],
    "wof:name":"Gouden Kroon",
    "wof:placetype":"venue"
},
  "geometry": {"coordinates":[4.6999797821,51.2974357605],"type":"Point"}
}