{
  "type": "Feature",
  "properties": {
    "addr:full":"Felicien Cauwelstraat 50 Geraardsbergen Oost-Vlaanderen 9500",
    "addr:housenumber":"50",
    "addr:postcode":"9500",
    "addr:street":"Cauwelstraat",
    "iso:country":"BE",
    "sg:address":"Felicien Cauwelstraat 50",
    "sg:city":"Geraardsbergen",
    "sg:orig_category":"WAPENS AND MUNITIE",
    "sg:phone":"+32 54 41 11 56",
    "sg:postcode":"9500",
    "sg:province":"Oost-Vlaanderen",
    "wof:name":"Wapens Pletinckx",
    "wof:placetype":"venue"
},
  "geometry": {"coordinates":[3.8668589592,50.7761535645],"type":"Point"}
}