{
  "type": "Feature",
  "properties": {
    "addr:full":"Ieperstraat 213 Wervik (geluwe) West-Vlaanderen 8940",
    "addr:housenumber":"213",
    "addr:postcode":"8940",
    "addr:street":"Ieperstraat",
    "iso:country":"BE",
    "sg:address":"Ieperstraat 213",
    "sg:city":"Wervik (geluwe)",
    "sg:classifiers":[
        {
            "category":"Wholesale",
            "subcategory":"Meat",
            "type":"Manufacturing & Wholesale Goods"
        }
    ],
    "sg:phone":"+32 56 51 12 27",
    "sg:postcode":"8940",
    "sg:province":"West-Vlaanderen",
    "sg:tags":[
        "whol",
        "-"
    ],
    "wof:name":"Westhoek Voeders Nv",
    "wof:placetype":"venue"
},
  "geometry": {"coordinates":[3.0410308838,50.8200645447],"type":"Point"}
}