{
  "type": "Feature",
  "properties": {
    "iso:country":"BE",
    "sg:address":"Rue Les Hauts Du Ry Ternel",
    "sg:city":"Ittre (haut-ittre)",
    "sg:classifiers":[
        {
            "category":"Education",
            "subcategory":"Dance Studio",
            "type":"Public Place"
        }
    ],
    "sg:phone":"+32 67 63 66 46",
    "sg:postcode":"1461",
    "sg:province":"Brabant Wallon",
    "sg:tags":[
        "school",
        "dancing"
    ],
    "wof:name":"Vandenberghe G",
    "wof:placetype":"venue"
},
  "geometry": {"coordinates":[4.296877861,50.6537132263],"type":"Point"}
}