{
  "type": "Feature",
  "properties": {
    "addr:full":"Boulevard De La Sauveni\u00e8re 141 Li\u00e8ge 1 Li\u00e8ge 4000",
    "addr:housenumber":"141;1",
    "addr:postcode":"4000",
    "addr:street":"Boulevard De La Sauvenie\u0300Re",
    "iso:country":"BE",
    "sg:address":"Boulevard De La Sauveni\u00e8re 141",
    "sg:city":"Li\u00e8ge 1",
    "sg:classifiers":[
        {
            "category":"Personal",
            "subcategory":"Beauty Salon",
            "type":"Services"
        }
    ],
    "sg:phone":"+32 497 64 49 85",
    "sg:postcode":"4000",
    "sg:province":"Li\u00e8ge",
    "sg:tags":[
        "lady",
        "-",
        "hairdressing"
    ],
    "wof:name":"Cap'tifs",
    "wof:placetype":"venue"
},
  "geometry": {"coordinates":[5.5685582161,50.6407241821],"type":"Point"}
}