{
  "type": "Feature",
  "properties": {
    "iso:country":"BE",
    "sg:address":"Frans Vekemansstraat 116a",
    "sg:city":"Brussel/bruxelles",
    "sg:orig_category":"Reisbureaus",
    "sg:phone":"+32 2 262 13 55",
    "sg:postcode":"1120",
    "sg:province":"Bruxelles-Capitale",
    "wof:name":"Travelsquare",
    "wof:placetype":"venue"
},
  "geometry": {"coordinates":[4.3873767853,50.8952407837],"type":"Point"}
}