{
  "type": "Feature",
  "properties": {
    "iso:country":"BE",
    "sg:address":"Guldendal 9",
    "sg:city":"Grimbergen",
    "sg:orig_category":"Artsen and specialisten",
    "sg:phone":"+32 2 269 01 87",
    "sg:postcode":"1850",
    "sg:province":"Vlaams-Brabant",
    "wof:name":"Carine Boonen",
    "wof:placetype":"venue"
},
  "geometry": {"coordinates":[4.3716812134,50.9264144897],"type":"Point"}
}