{
  "type": "Feature",
  "properties": {
    "iso:country":"BE",
    "sg:address":"Westelsebaan 59",
    "sg:city":"Scherpenheuvel-zichem (averbode)",
    "sg:classifiers":[
        {
            "category":"Health Services",
            "subcategory":"Doctor",
            "type":"Services"
        }
    ],
    "sg:phone":"+32 13 77 17 04",
    "sg:postcode":"3271",
    "sg:province":"Vlaams-Brabant",
    "sg:tags":[
        "medicinephysicians",
        "surgeon"
    ],
    "wof:name":"De Wijs J",
    "wof:placetype":"venue"
},
  "geometry": {"coordinates":[4.9859080315,51.0245056152],"type":"Point"}
}