{
  "type": "Feature",
  "properties": {
    "iso:country":"BE",
    "sg:address":"Rue Du Village 19",
    "sg:city":"Pont-a-celles",
    "sg:orig_category":"Boissons. Services divers aux personnes",
    "sg:phone":"+32 71 84 38 18",
    "sg:postcode":"6230",
    "sg:province":"Hainaut",
    "wof:name":"Gerard Redon",
    "wof:placetype":"venue"
},
  "geometry": {"coordinates":[4.3572440147,50.5271339417],"type":"Point"}
}