{
  "type": "Feature",
  "properties": {
    "addr:full":"Hennepstraat 37 Oostende West-Vlaanderen 8400",
    "addr:housenumber":"37",
    "addr:postcode":"8400",
    "addr:street":"Hennepstraat",
    "iso:country":"BE",
    "sg:address":"Hennepstraat 37",
    "sg:city":"Oostende",
    "sg:orig_category":"Artsen and specialisten",
    "sg:phone":"+32 59 80 20 58",
    "sg:postcode":"8400",
    "sg:province":"West-Vlaanderen",
    "wof:name":"Jacques De Groote",
    "wof:placetype":"venue"
},
  "geometry": {"coordinates":[2.9092431068,51.2189178467],"type":"Point"}
}