{
  "type": "Feature",
  "properties": {
    "addr:full":"Rue Henri De Dinant 8 Li\u00e8ge 1 (li\u00e8ge 2) Li\u00e8ge 4020",
    "addr:housenumber":"8;1;2",
    "addr:postcode":"4020",
    "addr:street":"Rue Henri De Dinant",
    "iso:country":"BE",
    "sg:address":"Rue Henri De Dinant 8",
    "sg:city":"Li\u00e8ge 1 (li\u00e8ge 2)",
    "sg:classifiers":[
        {
            "category":"Professional",
            "subcategory":"Art Services",
            "type":"Services"
        }
    ],
    "sg:phone":"+32 4 343 26 53",
    "sg:postcode":"4020",
    "sg:province":"Li\u00e8ge",
    "sg:tags":[
        "photographer"
    ],
    "wof:name":"Goulard P F",
    "wof:placetype":"venue"
},
  "geometry": {"coordinates":[5.5830368996,50.6413459778],"type":"Point"}
}