{
  "type": "Feature",
  "properties": {
    "addr:full":"Zandberg 7 Ruiselede West-Vlaanderen 8755",
    "addr:housenumber":"7",
    "addr:postcode":"8755",
    "addr:street":"Zandberg",
    "iso:country":"BE",
    "sg:address":"Zandberg 7",
    "sg:city":"Ruiselede",
    "sg:orig_category":"Herstellingen motorfietsen",
    "sg:phone":"+32 51 68 72 71",
    "sg:postcode":"8755",
    "sg:province":"West-Vlaanderen",
    "wof:name":"Marnix Boeckaert",
    "wof:placetype":"venue"
},
  "geometry": {"coordinates":[3.3907699585,51.0717697144],"type":"Point"}
}