{
  "type": "Feature",
  "properties": {
    "addr:full":"Heldenplein 43 Gent Oost-Vlaanderen 9000",
    "addr:housenumber":"43",
    "addr:postcode":"9000",
    "addr:street":"Heldenplein;Oost-Vlaanderen",
    "iso:country":"BE",
    "sg:address":"Heldenplein 43",
    "sg:city":"Gent",
    "sg:classifiers":[
        {
            "category":"Personal",
            "subcategory":"Beauty Salon",
            "type":"Services"
        }
    ],
    "sg:phone":"+32 9 226 88 73",
    "sg:postcode":"9000",
    "sg:province":"Oost-Vlaanderen",
    "sg:tags":[
        "de",
        "coiffure"
    ],
    "wof:name":"Coiffure Knapp",
    "wof:placetype":"venue"
},
  "geometry": {"coordinates":[3.694396019,51.0530319214],"type":"Point"}
}