{
  "type": "Feature",
  "properties": {
    "addr:full":"Rue C\u00c9lestin-hastir 60 Floreffe Namur 5150",
    "addr:housenumber":"60",
    "addr:postcode":"5150",
    "addr:street":"Rue Ce\u0301Lestin-Hastir",
    "iso:country":"BE",
    "sg:address":"Rue C\u00c9lestin-hastir 60",
    "sg:city":"Floreffe",
    "sg:orig_category":"Artsen and specialisten",
    "sg:phone":"+32 81 44 40 69",
    "sg:postcode":"5150",
    "sg:province":"Namur",
    "wof:name":"Francis Delcourt",
    "wof:placetype":"venue"
},
  "geometry": {"coordinates":[4.7622351646,50.4418373108],"type":"Point"}
}