{
  "type": "Feature",
  "properties": {
    "iso:country":"BE",
    "sg:address":"Verbrandebrugsesteenweg 58",
    "sg:city":"Grimbergen",
    "sg:orig_category":"Produits chimiques Gr",
    "sg:phone":"+32 2 255 94 30",
    "sg:postcode":"1850",
    "sg:province":"Vlaams-Brabant",
    "wof:name":"National Chemsearch",
    "wof:placetype":"venue"
},
  "geometry": {"coordinates":[4.4094090462,50.9446411133],"type":"Point"}
}