{
  "type": "Feature",
  "properties": {
    "iso:country":"BE",
    "sg:address":"Boulevard De Smet De Naeyer 320",
    "sg:city":"Bruxelles (jette)",
    "sg:classifiers":[
        {
            "category":"Shopping",
            "subcategory":"Florist",
            "type":"Retail Goods"
        }
    ],
    "sg:phone":"+32 2 426 41 32",
    "sg:postcode":"1090",
    "sg:province":"Bruxelles-Capitale",
    "wof:name":"Florence (fleurs De)",
    "wof:placetype":"venue"
},
  "geometry": {"coordinates":[4.3346939087,50.8795166016],"type":"Point"}
}