{
  "type": "Feature",
  "properties": {
    "addr:full":"Wayai 20 Jalhay Li\u00e8ge 4845",
    "addr:housenumber":"20",
    "addr:postcode":"4845",
    "addr:street":"Wayai",
    "iso:country":"BE",
    "sg:address":"Wayai 20",
    "sg:city":"Jalhay",
    "sg:orig_category":"Gespecialiseerde residenti\u00eble bouw",
    "sg:phone":"+32 87 47 47 23",
    "sg:postcode":"4845",
    "sg:province":"Li\u00e8ge",
    "wof:name":"Jean Pauls",
    "wof:placetype":"venue"
},
  "geometry": {"coordinates":[5.9532232285,50.502456665],"type":"Point"}
}