{
  "type": "Feature",
  "properties": {
    "iso:country":"BE",
    "sg:address":"Rue De Gages 28bb",
    "sg:city":"Lessines",
    "sg:orig_category":"Catering and organisation de f\u00eates",
    "sg:phone":"+32 68 33 95 84",
    "sg:postcode":"7866",
    "sg:province":"Hainaut",
    "wof:name":"Georges Bouillon",
    "wof:placetype":"venue"
},
  "geometry": {"coordinates":[3.8632760048,50.7075271606],"type":"Point"}
}