{
  "type": "Feature",
  "properties": {
    "iso:country":"BE",
    "sg:address":"Heringstraat 17",
    "sg:city":"Brakel",
    "sg:orig_category":"Dakwerken Loodgieterij, verwarming and sanitaire installaties Schoonmaakbedrijven and ongediertebest",
    "sg:phone":"+32 55 42 71 47",
    "sg:postcode":"9660",
    "sg:province":"Oost-Vlaanderen",
    "wof:name":"Mondial Dak & Bouw",
    "wof:placetype":"venue"
},
  "geometry": {"coordinates":[3.7642250061,50.8031082153],"type":"Point"}
}