{
  "type": "Feature",
  "properties": {
    "addr:full":"Place Saint-pholien 8 Li\u00e8ge 1 (li\u00e8ge 2) Li\u00e8ge 4020",
    "addr:housenumber":"8;1;2",
    "addr:postcode":"4020",
    "addr:street":"Place Saint-Pholien",
    "iso:country":"BE",
    "sg:address":"Place Saint-pholien 8",
    "sg:city":"Li\u00e8ge 1 (li\u00e8ge 2)",
    "sg:classifiers":[
        {
            "category":"Shopping",
            "subcategory":"Books",
            "type":"Retail Goods"
        }
    ],
    "sg:phone":"+32 4 343 39 01",
    "sg:postcode":"4020",
    "sg:province":"Li\u00e8ge",
    "sg:tags":[
        "bookseller"
    ],
    "wof:name":"Lejeune",
    "wof:placetype":"venue"
},
  "geometry": {"coordinates":[5.5804409981,50.6428718567],"type":"Point"}
}