{
  "type": "Feature",
  "properties": {
    "iso:country":"BE",
    "sg:address":"Chemin Chapelle Collard 8",
    "sg:city":"Tournay",
    "sg:orig_category":"Quincailleries",
    "sg:phone":"+32 61 27 90 15",
    "sg:postcode":"6840",
    "sg:province":"Luxembourg",
    "wof:name":"Po\u00calerie Ardennaise",
    "wof:placetype":"venue"
},
  "geometry": {"coordinates":[5.3960180283,49.8549041748],"type":"Point"}
}