{
  "type": "Feature",
  "properties": {
    "iso:country":"BE",
    "sg:address":"Tervuursesteenweg 42",
    "sg:city":"Leuven",
    "sg:orig_category":"Binnenhuisarchitecten",
    "sg:phone":"+32 16 20 36 33",
    "sg:postcode":"3001",
    "sg:province":"Vlaams-Brabant",
    "wof:name":"Philippe Van Der Velpen",
    "wof:placetype":"venue"
},
  "geometry": {"coordinates":[4.6808657646,50.8764076233],"type":"Point"}
}