{
  "type": "Feature",
  "properties": {
    "addr:full":"Dr\u00e8ve Du Bois Des Aulnes 13 Waterloo Brabant Wallon 1410",
    "addr:housenumber":"13",
    "addr:postcode":"1410",
    "addr:street":"Dre\u0300Ve Du Bois Des Aulnes",
    "iso:country":"BE",
    "sg:address":"Dr\u00e8ve Du Bois Des Aulnes 13",
    "sg:city":"Waterloo",
    "sg:classifiers":[
        {
            "category":"Home & Garden",
            "subcategory":"Furniture",
            "type":"Retail Goods"
        }
    ],
    "sg:phone":"+32 475 23 12 70",
    "sg:postcode":"1410",
    "sg:province":"Brabant Wallon",
    "sg:tags":[
        "-"
    ],
    "wof:name":"1 2 3 Jardin",
    "wof:placetype":"venue"
},
  "geometry": {"coordinates":[4.4155597687,50.7068405151],"type":"Point"}
}