{
  "type": "Feature",
  "properties": {
    "addr:full":"Prelaat Stalpaertslaan 16 Westerlo Antwerpen 2260",
    "addr:housenumber":"16",
    "addr:postcode":"2260",
    "addr:street":"Prelaat Stalpaertslaan",
    "iso:country":"BE",
    "sg:address":"Prelaat Stalpaertslaan 16",
    "sg:city":"Westerlo",
    "sg:orig_category":"Paramedische behandelingen",
    "sg:phone":"+32 14 23 48 31",
    "sg:postcode":"2260",
    "sg:province":"Antwerpen",
    "wof:name":"H. Seynave",
    "wof:placetype":"venue"
},
  "geometry": {"coordinates":[4.9015412331,51.1291007996],"type":"Point"}
}