{
  "type": "Feature",
  "properties": {
    "addr:full":"Rue De La Station 147 Mouscron Hainaut 7700",
    "addr:housenumber":"147",
    "addr:postcode":"7700",
    "addr:street":"Rue De La Station",
    "iso:country":"BE",
    "sg:address":"Rue De La Station 147",
    "sg:city":"Mouscron",
    "sg:classifiers":[
        {
            "category":"Health Services",
            "subcategory":"Doctor",
            "type":"Services"
        }
    ],
    "sg:phone":"+32 56 33 05 37",
    "sg:postcode":"7700",
    "sg:province":"Hainaut",
    "sg:tags":[
        "medicinephysicians",
        "surgeon"
    ],
    "wof:name":"Delbauve Jean-pierre",
    "wof:placetype":"venue"
},
  "geometry": {"coordinates":[3.2272698879,50.7427215576],"type":"Point"}
}