{
  "type": "Feature",
  "properties": {
    "addr:full":"Dr\u00c8ve Des Alli\u00c9s 108 Thuin Hainaut 6530",
    "addr:housenumber":"108",
    "addr:postcode":"6530",
    "addr:street":"Dre\u0300Ve Des Allie\u0301S",
    "iso:country":"BE",
    "sg:address":"Dr\u00c8ve Des Alli\u00c9s 108",
    "sg:city":"Thuin",
    "sg:orig_category":"Epiceries",
    "sg:phone":"+32 71 59 55 05",
    "sg:postcode":"6530",
    "sg:province":"Hainaut",
    "wof:name":"Battard",
    "wof:placetype":"venue"
},
  "geometry": {"coordinates":[4.3101568222,50.339302063],"type":"Point"}
}