{
  "type": "Feature",
  "properties": {
    "addr:full":"Kasteelstraat 10 Assenede Oost-Vlaanderen 9960",
    "addr:housenumber":"10",
    "addr:postcode":"9960",
    "addr:street":"Kasteelstraat",
    "iso:country":"BE",
    "sg:address":"Kasteelstraat 10",
    "sg:city":"Assenede",
    "sg:classifiers":[
        {
            "category":"Real Estate",
            "subcategory":"Architect",
            "type":"Services"
        }
    ],
    "sg:phone":"+32 9 344 52 81",
    "sg:postcode":"9960",
    "sg:province":"Oost-Vlaanderen",
    "wof:name":"Neyt G",
    "wof:placetype":"venue"
},
  "geometry": {"coordinates":[3.7531089783,51.2248687744],"type":"Point"}
}