{
  "type": "Feature",
  "properties": {
    "iso:country":"BE",
    "sg:address":"Smeetshoevenstraat 13",
    "sg:city":"Beringen (koersel)",
    "sg:classifiers":[
        {
            "category":"Manufacturing",
            "subcategory":"Metals",
            "type":"Manufacturing & Wholesale Goods"
        }
    ],
    "sg:phone":"+32 11 43 16 18",
    "sg:postcode":"3582",
    "sg:province":"Limburg",
    "sg:tags":[
        "working"
    ],
    "wof:name":"Ancia Nv",
    "wof:placetype":"venue"
},
  "geometry": {"coordinates":[5.2708749771,51.0595359802],"type":"Point"}
}