{
  "type": "Feature",
  "properties": {
    "iso:country":"BE",
    "sg:address":"Beaulieustraat 7",
    "sg:city":"Machelen",
    "sg:classifiers":[
        {
            "category":"Autos & Motor Vehicles",
            "subcategory":"Recreational Vehicle Sales",
            "type":"Retail Goods"
        }
    ],
    "sg:phone":"+32 2 252 45 20",
    "sg:postcode":"1830",
    "sg:province":"Vlaams-Brabant",
    "sg:tags":[
        "installation",
        "metal",
        "-",
        "surface",
        "machine",
        "treatment"
    ],
    "wof:name":"Euromat-gent",
    "wof:placetype":"venue"
},
  "geometry": {"coordinates":[4.4252710342,50.9071044922],"type":"Point"}
}