{
  "type": "Feature",
  "properties": {
    "addr:full":"Bogaardestraat 10-12 Antwerpen Antwerpen 2000",
    "addr:postcode":"10-12;2000",
    "addr:street":"Bogaardestraat",
    "iso:country":"BE",
    "sg:address":"Bogaardestraat 10-12",
    "sg:city":"Antwerpen",
    "sg:classifiers":[
        {
            "category":"Real Estate",
            "subcategory":"Architect",
            "type":"Services"
        }
    ],
    "sg:phone":"+32 3 232 48 49",
    "sg:postcode":"2000",
    "sg:province":"Antwerpen",
    "wof:name":"Cuypers G",
    "wof:placetype":"venue"
},
  "geometry": {"coordinates":[4.4003801346,51.2154197693],"type":"Point"}
}