{
  "type": "Feature",
  "properties": {
    "iso:country":"BE",
    "sg:address":"Knokkestraat 25",
    "sg:city":"Lokeren",
    "sg:classifiers":[
        {
            "category":"Home & Garden",
            "subcategory":"Household Appliances",
            "type":"Retail Goods"
        }
    ],
    "sg:phone":"+32 9 348 57 84",
    "sg:postcode":"9160",
    "sg:province":"Oost-Vlaanderen",
    "sg:tags":[
        "repair",
        "mainten",
        "-",
        "electric"
    ],
    "wof:name":"Reyniers-elektro-discount",
    "wof:placetype":"venue"
},
  "geometry": {"coordinates":[3.9952950478,51.1035575867],"type":"Point"}
}