{
  "type": "Feature",
  "properties": {
    "addr:full":"Rue Richard Vandevelde 58 Schaarbeek/schaerbeek Bruxelles-Capitale 1030",
    "addr:housenumber":"58",
    "addr:postcode":"1030",
    "addr:street":"Rue Richard Vandevelde",
    "iso:country":"BE",
    "sg:address":"Rue Richard Vandevelde 58",
    "sg:city":"Schaarbeek/schaerbeek",
    "sg:orig_category":"Boucheries",
    "sg:phone":"+32 2 215 77 21",
    "sg:postcode":"1030",
    "sg:province":"Bruxelles-Capitale",
    "wof:name":"Fe. Cosijns",
    "wof:placetype":"venue"
},
  "geometry": {"coordinates":[4.3890137672,50.872882843],"type":"Point"}
}