{
  "type": "Feature",
  "properties": {
    "iso:country":"BE",
    "sg:address":"Harmoniestraat 12",
    "sg:city":"Antwerpen",
    "sg:classifiers":[
        {
            "category":"Government",
            "subcategory":"Post Office",
            "type":"Public Place"
        }
    ],
    "sg:phone":"+32 3 216 22 08",
    "sg:postcode":"2018",
    "sg:province":"Antwerpen",
    "sg:tags":[
        "yoga"
    ],
    "wof:name":"Yoga Vedanta Vzw",
    "wof:placetype":"venue"
},
  "geometry": {"coordinates":[4.4092612267,51.2034912109],"type":"Point"}
}