{
  "type": "Feature",
  "properties": {
    "addr:full":"Rue De L'horloge 169 Cerfontaine (senzeille) Namur 5630",
    "addr:housenumber":"169",
    "addr:postcode":"5630",
    "addr:street":"Rue De L'Horloge",
    "iso:country":"BE",
    "sg:address":"Rue De L'horloge 169",
    "sg:city":"Cerfontaine (senzeille)",
    "sg:classifiers":[
        {
            "category":"Food & Beverages",
            "subcategory":"Groceries & Convenience Stores",
            "type":"Retail Goods"
        }
    ],
    "sg:phone":"+32 71 64 32 57",
    "sg:postcode":"5630",
    "sg:province":"Namur",
    "sg:tags":[
        "grocer"
    ],
    "wof:name":"Houbat M-t",
    "wof:placetype":"venue"
},
  "geometry": {"coordinates":[4.4649000168,50.1774330139],"type":"Point"}
}