{
  "type": "Feature",
  "properties": {
    "addr:full":"Kortrijkstraat 220-224 Menen West-Vlaanderen 8930",
    "addr:housenumber":"220-224",
    "addr:postcode":"8930",
    "addr:street":"Kortrijkstraat",
    "iso:country":"BE",
    "sg:address":"Kortrijkstraat 220-224",
    "sg:city":"Menen",
    "sg:classifiers":[
        {
            "category":"Health Services",
            "subcategory":"Nursing And Care Facility",
            "type":"Services"
        }
    ],
    "sg:phone":"+32 56 52 15 70",
    "sg:postcode":"8930",
    "sg:province":"West-Vlaanderen",
    "sg:tags":[
        "home",
        "rest"
    ],
    "wof:name":"Residentie Marie-astrid",
    "wof:placetype":"venue"
},
  "geometry": {"coordinates":[3.1297979355,50.7981758118],"type":"Point"}
}