{
  "type": "Feature",
  "properties": {
    "iso:country":"BE",
    "sg:address":"Doorniksestraat 52",
    "sg:city":"Kortrijk",
    "sg:orig_category":"Imprimeries and copyshops",
    "sg:phone":"+32 56 20 12 10",
    "sg:postcode":"8500",
    "sg:province":"West-Vlaanderen",
    "wof:name":"Missis Copy",
    "wof:placetype":"venue"
},
  "geometry": {"coordinates":[3.2675409317,50.8249130249],"type":"Point"}
}