{
  "type": "Feature",
  "properties": {
    "iso:country":"BE",
    "sg:address":"Route De Saint-vith 23",
    "sg:city":"Malmedy/malmedy",
    "sg:orig_category":"Openbare veiligheid",
    "sg:phone":"+32 80 33 08 83",
    "sg:postcode":"4960",
    "sg:province":"Li\u00e8ge",
    "wof:name":"Police F\u00c9d\u00c9rale",
    "wof:placetype":"venue"
},
  "geometry": {"coordinates":[6.0551772118,50.37657547],"type":"Point"}
}