{
  "type": "Feature",
  "properties": {
    "addr:full":"Kerselaarstraat 59 Dilbeek Vlaams-Brabant 1700",
    "addr:housenumber":"59",
    "addr:postcode":"1700",
    "addr:street":"Kerselaarstraat",
    "iso:country":"BE",
    "sg:address":"Kerselaarstraat 59",
    "sg:city":"Dilbeek",
    "sg:orig_category":"Schoonheidssalons",
    "sg:phone":"+32 2 466 25 06",
    "sg:postcode":"1700",
    "sg:province":"Vlaams-Brabant",
    "wof:name":"Krista De Ruddere",
    "wof:placetype":"venue"
},
  "geometry": {"coordinates":[4.2841439247,50.8568534851],"type":"Point"}
}