{
  "type": "Feature",
  "properties": {
    "iso:country":"BE",
    "sg:address":"Vijfwegenstraat 29",
    "sg:city":"Izegem",
    "sg:orig_category":"Artiesten and kunstenaars",
    "sg:phone":"+32 51 31 65 38",
    "sg:postcode":"8870",
    "sg:province":"West-Vlaanderen",
    "wof:name":"Johan Herman",
    "wof:placetype":"venue"
},
  "geometry": {"coordinates":[3.2156970501,50.9259109497],"type":"Point"}
}