{
  "type": "Feature",
  "properties": {
    "addr:full":"Baive 135 Assesse Namur 5330",
    "addr:housenumber":"135",
    "addr:postcode":"5330",
    "addr:street":"Baive",
    "iso:country":"BE",
    "sg:address":"Baive 135",
    "sg:city":"Assesse",
    "sg:orig_category":"Eleveurs de bovins",
    "sg:phone":"+32 83 65 61 91",
    "sg:postcode":"5330",
    "sg:province":"Namur",
    "wof:name":"Joannes De Prins",
    "wof:placetype":"venue"
},
  "geometry": {"coordinates":[4.9748620987,50.370880127],"type":"Point"}
}