{
  "type": "Feature",
  "properties": {
    "iso:country":"BE",
    "sg:address":"Weg Naar Zwartberg 17b1",
    "sg:city":"Opglabbeek",
    "sg:orig_category":"Alimentation sp\u00e9cialis\u00e9e",
    "sg:phone":"+32 89 81 11 45",
    "sg:postcode":"3660",
    "sg:province":"Limburg",
    "wof:name":"Huis Bi-jooke",
    "wof:placetype":"venue"
},
  "geometry": {"coordinates":[5.5818099976,51.0418968201],"type":"Point"}
}