{
  "type": "Feature",
  "properties": {
    "addr:full":"Schoolstraat 71 Harelbeke West-Vlaanderen 8530",
    "addr:housenumber":"71",
    "addr:postcode":"8530",
    "addr:street":"Schoolstraat",
    "iso:country":"BE",
    "sg:address":"Schoolstraat 71",
    "sg:city":"Harelbeke",
    "sg:orig_category":"Huishoudapparaten, televisies and radio's",
    "sg:phone":"+32 56 71 27 36",
    "sg:postcode":"8530",
    "sg:province":"West-Vlaanderen",
    "wof:name":"Henri Callant",
    "wof:placetype":"venue"
},
  "geometry": {"coordinates":[3.3151640892,50.851348877],"type":"Point"}
}