{
  "type": "Feature",
  "properties": {
    "iso:country":"BE",
    "sg:address":"Voisinage J. Malpas 36",
    "sg:city":"Seraing",
    "sg:orig_category":"Kapsalons",
    "sg:phone":"+32 4 336 46 26",
    "sg:postcode":"4102",
    "sg:province":"Li\u00e8ge",
    "wof:name":"Iris",
    "wof:placetype":"venue"
},
  "geometry": {"coordinates":[5.5343170166,50.5932617188],"type":"Point"}
}