{
  "type": "Feature",
  "properties": {
    "iso:country":"BE",
    "sg:address":"Koning Leopold Iii-plein 69",
    "sg:city":"Harelbeke",
    "sg:orig_category":"Enseignement maternel and primaire",
    "sg:phone":"+32 56 71 94 92",
    "sg:postcode":"8530",
    "sg:province":"West-Vlaanderen",
    "wof:name":"Vrije Basisschool",
    "wof:placetype":"venue"
},
  "geometry": {"coordinates":[3.3219139576,50.8567771912],"type":"Point"}
}