{
  "type": "Feature",
  "properties": {
    "addr:full":"Rue De Cambrai 31b14 Braine-l\u00b4alleud Brabant Wallon 1420",
    "addr:housenumber":"31b14",
    "addr:postcode":"1420",
    "addr:street":"Rue De Cambrai;Brabant Wallon",
    "iso:country":"BE",
    "sg:address":"Rue De Cambrai 31b14",
    "sg:city":"Braine-l\u00b4alleud",
    "sg:orig_category":"Production de films, t\u00e9l\u00e9films and vid\u00e9os",
    "sg:phone":"+32 475 29 05 69",
    "sg:postcode":"1420",
    "sg:province":"Brabant Wallon",
    "wof:name":"Fr\u00c9d\u00c9ric De Henau",
    "wof:placetype":"venue"
},
  "geometry": {"coordinates":[4.3790822029,50.6809272766],"type":"Point"}
}