{
  "type": "Feature",
  "properties": {
    "addr:full":"Rue Du Village 154 Quaregnon Hainaut 7390",
    "addr:housenumber":"154",
    "addr:postcode":"7390",
    "addr:street":"Rue Du Village",
    "iso:country":"BE",
    "sg:address":"Rue Du Village 154",
    "sg:city":"Quaregnon",
    "sg:orig_category":"Advocaten and juridische adviseurs",
    "sg:phone":"+32 65 78 02 78",
    "sg:postcode":"7390",
    "sg:province":"Hainaut",
    "wof:name":"Philippe Cauchies",
    "wof:placetype":"venue"
},
  "geometry": {"coordinates":[3.8656439781,50.4412994385],"type":"Point"}
}