{
  "type": "Feature",
  "properties": {
    "addr:full":"Rue De Percke 64 Bruxelles (uccle) Bruxelles-Capitale 1180",
    "addr:housenumber":"64",
    "addr:postcode":"1180",
    "addr:street":"Rue De Percke",
    "iso:country":"BE",
    "sg:address":"Rue De Percke 64",
    "sg:city":"Bruxelles (uccle)",
    "sg:classifiers":[
        {
            "category":"Health Services",
            "subcategory":"Doctor",
            "type":"Services"
        }
    ],
    "sg:phone":"+32 2 375 62 54",
    "sg:postcode":"1180",
    "sg:province":"Bruxelles-Capitale",
    "sg:tags":[
        "medicinephysicians",
        "surgeon"
    ],
    "wof:name":"Lescot J",
    "wof:placetype":"venue"
},
  "geometry": {"coordinates":[4.3672938347,50.7736930847],"type":"Point"}
}