{
  "type": "Feature",
  "properties": {
    "iso:country":"BE",
    "sg:address":"Schoolstraat 22b",
    "sg:city":"Opwijk",
    "sg:classifiers":[
        {
            "category":"Insurance",
            "subcategory":"Insurance Agent",
            "type":"Services"
        }
    ],
    "sg:phone":"+32 52 35 08 05",
    "sg:postcode":"1745",
    "sg:province":"Vlaams-Brabant",
    "sg:tags":[
        "broker"
    ],
    "wof:name":"Costers-rasschaert",
    "wof:placetype":"venue"
},
  "geometry": {"coordinates":[4.1858110428,50.9693489075],"type":"Point"}
}