{
  "type": "Feature",
  "properties": {
    "addr:full":"Stationsstraat 111bb Hamont-achel Limburg 3930",
    "addr:housenumber":"111bb",
    "addr:postcode":"3930",
    "addr:street":"Stationsstraat",
    "iso:country":"BE",
    "sg:address":"Stationsstraat 111bb",
    "sg:city":"Hamont-achel",
    "sg:orig_category":"Epiceries",
    "sg:phone":"+32 11 62 21 04",
    "sg:postcode":"3930",
    "sg:province":"Limburg",
    "wof:name":"Spar",
    "wof:placetype":"venue"
},
  "geometry": {"coordinates":[5.5450549126,51.2511863708],"type":"Point"}
}