{
  "type": "Feature",
  "properties": {
    "iso:country":"BE",
    "sg:address":"Rue Reine Astrid 21a",
    "sg:city":"Engis",
    "sg:orig_category":"Boekhouders",
    "sg:phone":"+32 4 275 16 34",
    "sg:postcode":"4480",
    "sg:province":"Li\u00e8ge",
    "wof:name":"Lurson Raymond",
    "wof:placetype":"venue"
},
  "geometry": {"coordinates":[5.4035701752,50.5833969116],"type":"Point"}
}