{
  "type": "Feature",
  "properties": {
    "iso:country":"BE",
    "sg:address":"Rue Baudouin 46",
    "sg:city":"Frameries (eugies)",
    "sg:classifiers":[
        {
            "category":"Organizations",
            "subcategory":"Labor Organization",
            "type":"Services"
        }
    ],
    "sg:phone":"+32 65 67 24 57",
    "sg:postcode":"7080",
    "sg:province":"Hainaut",
    "sg:tags":[
        "draining",
        "work"
    ],
    "wof:name":"Bagetra",
    "wof:placetype":"venue"
},
  "geometry": {"coordinates":[3.8703000546,50.3941116333],"type":"Point"}
}