{
  "type": "Feature",
  "properties": {
    "addr:full":"Boulevard De Waterloo 133b134 Brussel/bruxelles Bruxelles-Capitale 1000",
    "addr:housenumber":"133b134",
    "addr:postcode":"1000",
    "addr:street":"Boulevard De Waterloo;/",
    "iso:country":"BE",
    "sg:address":"Boulevard De Waterloo 133b134",
    "sg:city":"Brussel/bruxelles",
    "sg:classifiers":[
        {
            "category":"Restaurant",
            "type":"Food & Drink"
        }
    ],
    "sg:phone":"+32 2 538 56 17",
    "sg:postcode":"1000",
    "sg:province":"Bruxelles-Capitale",
    "wof:name":"Brasseries Saint-pierre",
    "wof:placetype":"venue"
},
  "geometry": {"coordinates":[4.3457398415,50.8333053589],"type":"Point"}
}