{
  "type": "Feature",
  "properties": {
    "addr:full":"Bissegemplaats 10 Kortrijk (bissegem) West-Vlaanderen 8501",
    "addr:housenumber":"10",
    "addr:postcode":"8501",
    "addr:street":"Bissegemplaats",
    "iso:country":"BE",
    "sg:address":"Bissegemplaats 10",
    "sg:city":"Kortrijk (bissegem)",
    "sg:classifiers":[
        {
            "category":"Real Estate",
            "subcategory":"Real Estate Services",
            "type":"Services"
        }
    ],
    "sg:phone":"+32 56 32 08 06",
    "sg:postcode":"8501",
    "sg:province":"West-Vlaanderen",
    "wof:name":"Animmo",
    "wof:placetype":"venue"
},
  "geometry": {"coordinates":[3.2266290188,50.8233604431],"type":"Point"}
}