{
  "type": "Feature",
  "properties": {
    "iso:country":"BE",
    "sg:address":"Belgi\u00cblaan 2bc",
    "sg:city":"Herentals",
    "sg:orig_category":"Recouvrement de factures and \u00e9valuation de solvabilit\u00e9",
    "sg:phone":"+32 14 21 54 18",
    "sg:postcode":"2200",
    "sg:province":"Antwerpen",
    "wof:name":"Belgisch Incasso Bureau",
    "wof:placetype":"venue"
},
  "geometry": {"coordinates":[4.834250927,51.1794128418],"type":"Point"}
}