{
  "type": "Feature",
  "properties": {
    "iso:country":"BE",
    "sg:address":"Sint-maartensplein 2",
    "sg:city":"Koekelare",
    "sg:classifiers":[
        {
            "category":"Bars & Pubs",
            "type":"Food & Drink"
        }
    ],
    "sg:phone":"+32 51 58 32 06",
    "sg:postcode":"8680",
    "sg:province":"West-Vlaanderen",
    "sg:tags":[
        "tavern"
    ],
    "wof:name":"De Kroon",
    "wof:placetype":"venue"
},
  "geometry": {"coordinates":[2.9788548946,51.0891609192],"type":"Point"}
}