{
  "type": "Feature",
  "properties": {
    "iso:country":"BE",
    "sg:address":"7700",
    "sg:city":"Moeskroen",
    "sg:orig_category":"Pharmaciens",
    "sg:phone":"+32 900 10 500",
    "sg:postcode":"7700",
    "sg:province":"Hainaut",
    "wof:name":"Pharmacies De Garde",
    "wof:placetype":"venue"
},
  "geometry": {"coordinates":[3.2271699905,50.7411499023],"type":"Point"}
}