{
  "type": "Feature",
  "properties": {
    "addr:full":"Rue Du Bois 3 Lessines (bois-de-lessines) Hainaut 7866",
    "addr:housenumber":"3",
    "addr:postcode":"7866",
    "addr:street":"Rue Du Bois",
    "iso:country":"BE",
    "sg:address":"Rue Du Bois 3",
    "sg:city":"Lessines (bois-de-lessines)",
    "sg:classifiers":[
        {
            "category":"Food & Beverages",
            "subcategory":"Groceries & Convenience Stores",
            "type":"Retail Goods"
        }
    ],
    "sg:phone":"+32 68 33 46 83",
    "sg:postcode":"7866",
    "sg:province":"Hainaut",
    "sg:tags":[
        "grocer"
    ],
    "wof:name":"Centra",
    "wof:placetype":"venue"
},
  "geometry": {"coordinates":[3.8898200989,50.6935081482],"type":"Point"}
}