{
  "type": "Feature",
  "properties": {
    "addr:full":"Rue De Corbeau 99 Courcelles Hainaut 6183",
    "addr:housenumber":"99",
    "addr:postcode":"6183",
    "addr:street":"Rue De Corbeau",
    "iso:country":"BE",
    "sg:address":"Rue De Corbeau 99",
    "sg:city":"Courcelles",
    "sg:orig_category":"Woningbouw",
    "sg:phone":"+32 71 45 45 81",
    "sg:postcode":"6183",
    "sg:province":"Hainaut",
    "wof:name":"Scillia",
    "wof:placetype":"venue"
},
  "geometry": {"coordinates":[4.3402848244,50.4712944031],"type":"Point"}
}