{
  "type": "Feature",
  "properties": {
    "iso:country":"BE",
    "sg:address":"Asschout 13",
    "sg:city":"Evergem",
    "sg:orig_category":"Travaux de pl\u00e2trage",
    "sg:phone":"+32 9 357 76 26",
    "sg:postcode":"9940",
    "sg:province":"Oost-Vlaanderen",
    "wof:name":"Etienne Bauwens",
    "wof:placetype":"venue"
},
  "geometry": {"coordinates":[3.6868178844,51.117565155],"type":"Point"}
}