{
  "type": "Feature",
  "properties": {
    "iso:country":"BE",
    "sg:address":"Hofkwartier 25",
    "sg:city":"Herentals",
    "sg:orig_category":"Brood, gebak and snoepgoed",
    "sg:phone":"+32 14 21 16 16",
    "sg:postcode":"2200",
    "sg:province":"Antwerpen",
    "wof:name":"Bakkerij Moons",
    "wof:placetype":"venue"
},
  "geometry": {"coordinates":[4.8353328705,51.1787757874],"type":"Point"}
}