{
  "type": "Feature",
  "properties": {
    "addr:full":"Rue De Barvaux 33 Hotton Luxembourg 6990",
    "addr:housenumber":"33",
    "addr:postcode":"6990",
    "addr:street":"Rue De Barvaux",
    "iso:country":"BE",
    "sg:address":"Rue De Barvaux 33",
    "sg:city":"Hotton",
    "sg:orig_category":"V\u00e9hicules automobiles. Entretien and r\u00e9parations de voitures",
    "sg:phone":"+32 84 46 67 90",
    "sg:postcode":"6990",
    "sg:province":"Luxembourg",
    "wof:name":"P. Moreau",
    "wof:placetype":"venue"
},
  "geometry": {"coordinates":[5.4598298073,50.2859687805],"type":"Point"}
}