{
  "type": "Feature",
  "properties": {
    "addr:full":"Avenue Reine Astrid 273 Seneffe Hainaut 7180",
    "addr:housenumber":"273",
    "addr:postcode":"7180",
    "addr:street":"Avenue Reine Astrid",
    "iso:country":"BE",
    "sg:address":"Avenue Reine Astrid 273",
    "sg:city":"Seneffe",
    "sg:orig_category":"Banken and kredietinstellingen",
    "sg:phone":"+32 64 54 81 55",
    "sg:postcode":"7180",
    "sg:province":"Hainaut",
    "wof:name":"Dexia",
    "wof:placetype":"venue"
},
  "geometry": {"coordinates":[4.2551789284,50.5290641785],"type":"Point"}
}