{
  "type": "Feature",
  "properties": {
    "iso:country":"BE",
    "sg:address":"Rue De La Plage 61",
    "sg:city":"Fosses-la-ville",
    "sg:classifiers":[
        {
            "category":"Professional",
            "subcategory":"Testing Lab",
            "type":"Services"
        }
    ],
    "sg:phone":"+32 71 71 15 97",
    "sg:postcode":"5070",
    "sg:province":"Namur",
    "sg:tags":[
        "laboratory",
        "-"
    ],
    "wof:name":"Agreau Lab",
    "wof:placetype":"venue"
},
  "geometry": {"coordinates":[4.6833028793,50.3779945374],"type":"Point"}
}