{
  "type": "Feature",
  "properties": {
    "iso:country":"BE",
    "sg:address":"Rue De Merbes 193",
    "sg:city":"Binche",
    "sg:orig_category":"Services de Nettoyage and de D\u00e9sinfection",
    "sg:phone":"+32 64 33 54 00",
    "sg:postcode":"7131",
    "sg:province":"Hainaut",
    "wof:name":"R.j.m. Ramonage",
    "wof:placetype":"venue"
},
  "geometry": {"coordinates":[4.1714229584,50.4031524658],"type":"Point"}
}