{
  "type": "Feature",
  "properties": {
    "iso:country":"BE",
    "sg:address":"Bavikhoofsestraat 9",
    "sg:city":"Wielsbeke (ooigem)",
    "sg:orig_category":"Newspapers, magazines, periodicals - Distribution",
    "sg:phone":"+32 56 66 86 73",
    "sg:postcode":"8710",
    "sg:province":"West-Vlaanderen",
    "wof:name":"Griffel (de)",
    "wof:placetype":"venue"
},
  "geometry": {"coordinates":[3.3355131149,50.8926582336],"type":"Point"}
}