{
  "type": "Feature",
  "properties": {
    "addr:full":"Place De La Libert\u00c9 29 Li\u00c8ge Li\u00e8ge 4030",
    "addr:housenumber":"29",
    "addr:postcode":"4030",
    "addr:street":"Place De La Liberte\u0301",
    "iso:country":"BE",
    "sg:address":"Place De La Libert\u00c9 29",
    "sg:city":"Li\u00c8ge",
    "sg:classifiers":[
        {
            "category":"Personal",
            "subcategory":"Beauty Salon",
            "type":"Services"
        }
    ],
    "sg:phone":"+32 4 343 61 79",
    "sg:postcode":"4030",
    "sg:province":"Li\u00e8ge",
    "sg:tags":[
        "de",
        "coiffure"
    ],
    "wof:name":"Coiffure Sophie",
    "wof:placetype":"venue"
},
  "geometry": {"coordinates":[5.5868082047,50.6397819519],"type":"Point"}
}