{
  "type": "Feature",
  "properties": {
    "iso:country":"BE",
    "sg:address":"Rue De La Bruy\u00c8re 30",
    "sg:city":"Lincent",
    "sg:orig_category":"Alternatieve geneeskunde",
    "sg:phone":"+32 19 63 37 07",
    "sg:postcode":"4287",
    "sg:province":"Li\u00e8ge",
    "wof:name":"A. Kempinaire",
    "wof:placetype":"venue"
},
  "geometry": {"coordinates":[5.0411148071,50.712802887],"type":"Point"}
}