{
  "type": "Feature",
  "properties": {
    "addr:full":"Place De Brogne 3 Mettet Namur 5640",
    "addr:housenumber":"3",
    "addr:postcode":"5640",
    "addr:street":"Place De Brogne",
    "iso:country":"BE",
    "sg:address":"Place De Brogne 3",
    "sg:city":"Mettet",
    "sg:classifiers":[
        {
            "category":"Restaurant",
            "type":"Food & Drink"
        }
    ],
    "sg:phone":"+32 71 79 70 71",
    "sg:postcode":"5640",
    "sg:province":"Namur",
    "wof:name":"Abbaye De Brogne",
    "wof:placetype":"venue"
},
  "geometry": {"coordinates":[4.7407212257,50.3457870483],"type":"Point"}
}