{
  "type": "Feature",
  "properties": {
    "iso:country":"BE",
    "sg:address":"Rue De La Paille 2-8",
    "sg:city":"Brussel/bruxelles",
    "sg:orig_category":"H\u00f4tels",
    "sg:phone":"+32 2 513 60 40",
    "sg:postcode":"1000",
    "sg:province":"Bruxelles-Capitale",
    "wof:name":"Hotel Alfa Sablon/h\u00d4tel Alfa Sablon",
    "wof:placetype":"venue"
},
  "geometry": {"coordinates":[4.3558239937,50.8423957825],"type":"Point"}
}