{
  "type": "Feature",
  "properties": {
    "iso:country":"BE",
    "sg:address":"Augustijnernonnenstraat 80",
    "sg:city":"Jette/jette",
    "sg:orig_category":"Plaatsen van vloer- and muurbekleding Schilders",
    "sg:phone":"+32 2 426 47 50",
    "sg:postcode":"1090",
    "sg:province":"Bruxelles-Capitale",
    "wof:name":"Cavallotto",
    "wof:placetype":"venue"
},
  "geometry": {"coordinates":[4.3345079422,50.8763847351],"type":"Point"}
}