{
  "type": "Feature",
  "properties": {
    "addr:full":"Kolonel Dusartplein 1a Hasselt Limburg 3500",
    "addr:housenumber":"1a",
    "addr:postcode":"3500",
    "addr:street":"Kolonel Dusartplein",
    "iso:country":"BE",
    "sg:address":"Kolonel Dusartplein 1a",
    "sg:city":"Hasselt",
    "sg:classifiers":[
        {
            "category":"Real Estate",
            "subcategory":"Surveying",
            "type":"Services"
        }
    ],
    "sg:phone":"+32 11 23 42 73",
    "sg:postcode":"3500",
    "sg:province":"Limburg",
    "sg:tags":[
        "lettering",
        "letter"
    ],
    "wof:name":"Ppa Lettering",
    "wof:placetype":"venue"
},
  "geometry": {"coordinates":[5.3446497917,50.9308891296],"type":"Point"}
}