{
  "type": "Feature",
  "properties": {
    "iso:country":"BE",
    "sg:address":"Endepoelstraat 22",
    "sg:city":"Lubbeek",
    "sg:orig_category":"Non-Classified Establishments",
    "sg:phone":"+32 16 62 18 88",
    "sg:postcode":"3210",
    "sg:province":"Vlaams-Brabant",
    "wof:name":"Bamed",
    "wof:placetype":"venue"
},
  "geometry": {"coordinates":[4.7949700356,50.8948898315],"type":"Point"}
}