{
  "type": "Feature",
  "properties": {
    "iso:country":"BE",
    "sg:address":"Kortrijksebaan 7",
    "sg:city":"Holsbeek",
    "sg:orig_category":"Viessmann. Plomberie, chauffage and installations sanitaires. Meubles D\u00e9taillants, Am\u00e9nagement de B\u00e2",
    "sg:phone":"+32 16 44 48 18",
    "sg:postcode":"3220",
    "sg:province":"Vlaams-Brabant",
    "wof:name":"Van Meensel Jonny",
    "wof:placetype":"venue"
},
  "geometry": {"coordinates":[4.7597899437,50.9200973511],"type":"Point"}
}