{
  "type": "Feature",
  "properties": {
    "iso:country":"BE",
    "sg:address":"Kerkstraat 108",
    "sg:city":"Blankenberge",
    "sg:orig_category":"Brood, gebak and snoepgoed",
    "sg:phone":"+32 50 41 15 00",
    "sg:postcode":"8370",
    "sg:province":"West-Vlaanderen",
    "wof:name":"Bakkerij Haers",
    "wof:placetype":"venue"
},
  "geometry": {"coordinates":[3.1315219402,51.3133392334],"type":"Point"}
}