{
  "type": "Feature",
  "properties": {
    "addr:full":"Avenue Seghers 54 Bruxelles (koekelberg) Bruxelles-Capitale 1081",
    "addr:housenumber":"54",
    "addr:postcode":"1081",
    "addr:street":"Avenue Seghers",
    "iso:country":"BE",
    "sg:address":"Avenue Seghers 54",
    "sg:city":"Bruxelles (koekelberg)",
    "sg:classifiers":[
        {
            "category":"Professional",
            "subcategory":"Testing Lab",
            "type":"Services"
        }
    ],
    "sg:phone":"+32 2 414 48 12",
    "sg:postcode":"1081",
    "sg:province":"Bruxelles-Capitale",
    "sg:tags":[
        "chemist"
    ],
    "wof:name":"Phardec",
    "wof:placetype":"venue"
},
  "geometry": {"coordinates":[4.3212518692,50.8629570007],"type":"Point"}
}