{
  "type": "Feature",
  "properties": {
    "addr:full":"Terhulpensesteenweg 498 Overijse Vlaams-Brabant 3090",
    "addr:housenumber":"498",
    "addr:postcode":"3090",
    "addr:street":"Terhulpensesteenweg",
    "iso:country":"BE",
    "sg:address":"Terhulpensesteenweg 498",
    "sg:city":"Overijse",
    "sg:orig_category":"Elektrische installaties voor woningen",
    "sg:phone":"+32 2 687 36 45",
    "sg:postcode":"3090",
    "sg:province":"Vlaams-Brabant",
    "wof:name":"Petrus Van Belle",
    "wof:placetype":"venue"
},
  "geometry": {"coordinates":[4.5301628113,50.7591209412],"type":"Point"}
}