{
  "type": "Feature",
  "properties": {
    "iso:country":"BE",
    "sg:address":"Quatre Chemins 2",
    "sg:city":"Ellezelles",
    "sg:orig_category":"V\u00e9t\u00e9rinaires",
    "sg:phone":"+32 68 44 71 91",
    "sg:postcode":"7890",
    "sg:province":"Hainaut",
    "wof:name":"Thierry Mercier",
    "wof:placetype":"venue"
},
  "geometry": {"coordinates":[3.7326900959,50.7237319946],"type":"Point"}
}