{
  "type": "Feature",
  "properties": {
    "iso:country":"BE",
    "sg:address":"Geraardsbergsestraat 7",
    "sg:city":"Aalst",
    "sg:orig_category":"Tabac. Journaux",
    "sg:phone":"+32 53 77 45 13",
    "sg:postcode":"9300",
    "sg:province":"Oost-Vlaanderen",
    "wof:name":"De Specht",
    "wof:placetype":"venue"
},
  "geometry": {"coordinates":[4.0371809006,50.9344520569],"type":"Point"}
}