{
  "type": "Feature",
  "properties": {
    "iso:country":"BE",
    "sg:address":"Chauss\u00e9e Romaine 178",
    "sg:city":"Waremme",
    "sg:classifiers":[
        {
            "category":"Community Center",
            "subcategory":"Youth",
            "type":"Public Place"
        }
    ],
    "sg:phone":"+32 19 33 87 77",
    "sg:postcode":"4300",
    "sg:province":"Li\u00e8ge",
    "sg:tags":[
        "workshop",
        "sheltered"
    ],
    "wof:name":"Entreprise De Travail Adapt\u00e9 De Waremme",
    "wof:placetype":"venue"
},
  "geometry": {"coordinates":[5.2690467834,50.6935424805],"type":"Point"}
}