{
  "type": "Feature",
  "properties": {
    "iso:country":"BE",
    "sg:address":"Reeboklaan 4",
    "sg:city":"Kapellen",
    "sg:orig_category":"Services de Nettoyage and de D\u00e9sinfection",
    "sg:phone":"+32 3 665 24 81",
    "sg:postcode":"2950",
    "sg:province":"Antwerpen",
    "wof:name":"A A S Splendid",
    "wof:placetype":"venue"
},
  "geometry": {"coordinates":[4.4402890205,51.3295783997],"type":"Point"}
}