{
  "type": "Feature",
  "properties": {
    "addr:full":"Steenweg Op Dendermonde 151 Aalst (hofstade) Oost-Vlaanderen 9308",
    "addr:housenumber":"151",
    "addr:postcode":"9308",
    "addr:street":"Steenweg Op Dendermonde",
    "iso:country":"BE",
    "sg:address":"Steenweg Op Dendermonde 151",
    "sg:city":"Aalst (hofstade)",
    "sg:classifiers":[
        {
            "category":"Building & Trades",
            "subcategory":"Electrical",
            "type":"Services"
        }
    ],
    "sg:phone":"+32 53 79 04 29",
    "sg:postcode":"9308",
    "sg:province":"Oost-Vlaanderen",
    "sg:tags":[
        "electric",
        "-",
        "housewiring",
        "contractor"
    ],
    "wof:name":"De Paepe G",
    "wof:placetype":"venue"
},
  "geometry": {"coordinates":[4.0347590446,50.9603500366],"type":"Point"}
}