{
  "type": "Feature",
  "properties": {
    "addr:full":"Kramerijkstraat 15 Galmaarden Vlaams-Brabant 1570",
    "addr:housenumber":"15",
    "addr:postcode":"1570",
    "addr:street":"Kramerijkstraat",
    "iso:country":"BE",
    "sg:address":"Kramerijkstraat 15",
    "sg:city":"Galmaarden",
    "sg:orig_category":"Industri\u00eble elektrische installaties Informaticaconsulenten",
    "sg:phone":"+32 54 58 75 85",
    "sg:postcode":"1570",
    "sg:province":"Vlaams-Brabant",
    "wof:name":"Van Belle Electro",
    "wof:placetype":"venue"
},
  "geometry": {"coordinates":[3.9908490181,50.734413147],"type":"Point"}
}