{
  "type": "Feature",
  "properties": {
    "addr:full":"Kattestraat 28 Geraardsbergen Oost-Vlaanderen 9500",
    "addr:housenumber":"28",
    "addr:postcode":"9500",
    "addr:street":"Kattestraat",
    "iso:country":"BE",
    "sg:address":"Kattestraat 28",
    "sg:city":"Geraardsbergen",
    "sg:classifiers":[
        {
            "category":"Personal",
            "subcategory":"Beauty Salon",
            "type":"Services"
        }
    ],
    "sg:phone":"+32 54 42 39 24",
    "sg:postcode":"9500",
    "sg:province":"Oost-Vlaanderen",
    "wof:name":"Cardoen K",
    "wof:placetype":"venue"
},
  "geometry": {"coordinates":[3.8788430691,50.7709617615],"type":"Point"}
}