{
  "type": "Feature",
  "properties": {
    "iso:country":"BE",
    "sg:address":"Rue De La Coop\u00c9ration 42",
    "sg:city":"Binche",
    "sg:orig_category":"Sportterreinen and installaties behalve sportcentra",
    "sg:phone":"+32 64 33 71 02",
    "sg:postcode":"7130",
    "sg:province":"Hainaut",
    "wof:name":"Idea",
    "wof:placetype":"venue"
},
  "geometry": {"coordinates":[4.1660728455,50.412311554],"type":"Point"}
}