{
  "type": "Feature",
  "properties": {
    "addr:full":"Rue De L'epideme 124 Tourcoing Cedex 59204",
    "addr:housenumber":"124",
    "addr:postcode":"59204",
    "addr:street":"Rue De L'Epideme",
    "iso:country":"BE",
    "sg:address":"Rue De L'epideme 124",
    "sg:city":"Tourcoing Cedex",
    "sg:classifiers":[
        {
            "category":"Manufacturing",
            "subcategory":"Lumber",
            "type":"Manufacturing & Wholesale Goods"
        }
    ],
    "sg:phone":"+33 3 20 26 07 08",
    "sg:postcode":"59204",
    "sg:tags":[
        "timber"
    ],
    "wof:name":"Senelar Ets",
    "wof:placetype":"venue"
},
  "geometry": {"coordinates":[3.1719930172,50.7166404724],"type":"Point"}
}