{
  "type": "Feature",
  "properties": {
    "iso:country":"BE",
    "sg:address":"Passtraat 332",
    "sg:city":"Sint-niklaas",
    "sg:classifiers":[
        {
            "category":"Professional",
            "subcategory":"Accounting & Tax Preparation",
            "type":"Services"
        }
    ],
    "sg:phone":"+32 3 777 90 10",
    "sg:postcode":"9100",
    "sg:province":"Oost-Vlaanderen",
    "sg:tags":[
        "accountant"
    ],
    "wof:name":"Patrick De Terwangne",
    "wof:placetype":"venue"
},
  "geometry": {"coordinates":[4.1802377701,51.1615600586],"type":"Point"}
}