{
  "type": "Feature",
  "properties": {
    "addr:full":"Eikelaarstraat 26 Genk Limburg 3600",
    "addr:housenumber":"26",
    "addr:postcode":"3600",
    "addr:street":"Eikelaarstraat",
    "iso:country":"BE",
    "sg:address":"Eikelaarstraat 26",
    "sg:city":"Genk",
    "sg:orig_category":"V\u00e9hicules automobiles",
    "sg:phone":"+32 89 36 41 22",
    "sg:postcode":"3600",
    "sg:province":"Limburg",
    "wof:name":"T.r.a.c.",
    "wof:placetype":"venue"
},
  "geometry": {"coordinates":[5.487057209,50.9304580688],"type":"Point"}
}