{
  "type": "Feature",
  "properties": {
    "addr:full":"Rue Jean-laurent 50b Musson Luxembourg 6750",
    "addr:housenumber":"50b",
    "addr:postcode":"6750",
    "addr:street":"Rue Jean-Laurent",
    "iso:country":"BE",
    "sg:address":"Rue Jean-laurent 50b",
    "sg:city":"Musson",
    "sg:classifiers":[
        {
            "category":"Insurance",
            "subcategory":"Life Insurance",
            "type":"Services"
        }
    ],
    "sg:phone":"+32 63 67 73 42",
    "sg:postcode":"6750",
    "sg:province":"Luxembourg",
    "sg:tags":[
        "assurance"
    ],
    "wof:name":"Assurances Goffinet",
    "wof:placetype":"venue"
},
  "geometry": {"coordinates":[5.698802948,49.5579681396],"type":"Point"}
}