{
  "type": "Feature",
  "properties": {
    "addr:full":"E 3 Laan 56-60 Deinze (petegem-aan-de-leie) Oost-Vlaanderen 9800",
    "addr:postcode":"9800",
    "addr:street":"E 3 Laan 56-60;Petegem-Aan-De-Leie Oost-Vlaanderen",
    "iso:country":"BE",
    "sg:address":"E 3 Laan 56-60",
    "sg:city":"Deinze (petegem-aan-de-leie)",
    "sg:orig_category":"Solar protection - Outside",
    "sg:phone":"+32 9 386 11 76",
    "sg:postcode":"9800",
    "sg:province":"Oost-Vlaanderen",
    "wof:name":"Torck Poorten",
    "wof:placetype":"venue"
},
  "geometry": {"coordinates":[3.5378699303,50.9576911926],"type":"Point"}
}