{
  "type": "Feature",
  "properties": {
    "addr:full":"Rue De Roux 7a Charleroi (gosselies) Hainaut 6041",
    "addr:housenumber":"7a",
    "addr:postcode":"6041",
    "addr:street":"Rue De Roux",
    "iso:country":"BE",
    "sg:address":"Rue De Roux 7a",
    "sg:city":"Charleroi (gosselies)",
    "sg:classifiers":[
        {
            "category":"Wholesale",
            "subcategory":"Scrap",
            "type":"Manufacturing & Wholesale Goods"
        }
    ],
    "sg:phone":"+32 71 35 43 23",
    "sg:postcode":"6041",
    "sg:province":"Hainaut",
    "sg:tags":[
        "metal"
    ],
    "wof:name":"Fonderie Jacquet Sprl",
    "wof:placetype":"venue"
},
  "geometry": {"coordinates":[4.4050102234,50.4261322021],"type":"Point"}
}