{
  "type": "Feature",
  "properties": {
    "addr:full":"Chauss\u00c9e De Tongres 672 Li\u00c8ge Li\u00e8ge 4000",
    "addr:housenumber":"672",
    "addr:postcode":"4000",
    "addr:street":"Chausse\u0301E De Tongres",
    "iso:country":"BE",
    "sg:address":"Chauss\u00c9e De Tongres 672",
    "sg:city":"Li\u00c8ge",
    "sg:classifiers":[
        {
            "category":"Food & Beverages",
            "subcategory":"Fruits & Vegetables",
            "type":"Retail Goods"
        }
    ],
    "sg:phone":"+32 4 239 06 84",
    "sg:postcode":"4000",
    "sg:province":"Li\u00e8ge",
    "sg:tags":[
        "l\u00e9gumes"
    ],
    "wof:name":"Jose Gonzales Carreno",
    "wof:placetype":"venue"
},
  "geometry": {"coordinates":[5.5616159439,50.66381073],"type":"Point"}
}