{
  "type": "Feature",
  "properties": {
    "addr:full":"Br\u00fcckberg 24 B\u00fctgenbach Li\u00e8ge 4750",
    "addr:housenumber":"24",
    "addr:postcode":"4750",
    "addr:street":"Brueckberg",
    "iso:country":"BE",
    "sg:address":"Br\u00fcckberg 24",
    "sg:city":"B\u00fctgenbach",
    "sg:classifiers":[
        {
            "category":"Professional",
            "subcategory":"Art Services",
            "type":"Services"
        }
    ],
    "sg:phone":"+32 80 44 50 68",
    "sg:postcode":"4750",
    "sg:province":"Li\u00e8ge",
    "sg:tags":[
        "-",
        "painter",
        "artist"
    ],
    "wof:name":"Boemer H",
    "wof:placetype":"venue"
},
  "geometry": {"coordinates":[6.1694321632,50.4447898865],"type":"Point"}
}