{
  "type": "Feature",
  "properties": {
    "addr:full":"Troonstraat 47b3 Oostende West-Vlaanderen 8400",
    "addr:housenumber":"47b3",
    "addr:postcode":"8400",
    "addr:street":"Troonstraat",
    "iso:country":"BE",
    "sg:address":"Troonstraat 47b3",
    "sg:city":"Oostende",
    "sg:classifiers":[
        {
            "category":"Cafe",
            "type":"Food & Drink"
        }
    ],
    "sg:phone":"+32 59 80 88 48",
    "sg:postcode":"8400",
    "sg:province":"West-Vlaanderen",
    "sg:tags":[
        "caf\u00e9s"
    ],
    "wof:name":"Jean De Loose",
    "wof:placetype":"venue"
},
  "geometry": {"coordinates":[2.8898561001,51.2206840515],"type":"Point"}
}