{
  "type": "Feature",
  "properties": {
    "iso:country":"BE",
    "sg:address":"Chauss\u00c9e De Jolimont 28",
    "sg:city":"La Louviere",
    "sg:orig_category":"Banken and kredietinstellingen",
    "sg:phone":"+32 64 21 30 09",
    "sg:postcode":"7100",
    "sg:province":"Hainaut",
    "wof:name":"Fortis",
    "wof:placetype":"venue"
},
  "geometry": {"coordinates":[4.2180700302,50.4738082886],"type":"Point"}
}