{
  "type": "Feature",
  "properties": {
    "addr:full":"Avenue De France 8 Paliseul (maissin) Luxembourg 6852",
    "addr:housenumber":"8",
    "addr:postcode":"6852",
    "addr:street":"Avenue De France",
    "iso:country":"BE",
    "sg:address":"Avenue De France 8",
    "sg:city":"Paliseul (maissin)",
    "sg:classifiers":[
        {
            "category":"Health Services",
            "subcategory":"Health Practitioner",
            "type":"Services"
        }
    ],
    "sg:phone":"+32 61 65 66 02",
    "sg:postcode":"6852",
    "sg:province":"Luxembourg",
    "sg:tags":[
        "physiotherapist"
    ],
    "wof:name":"Henrotin Anne-fran\u00e7oise",
    "wof:placetype":"venue"
},
  "geometry": {"coordinates":[5.1785240173,49.9646186829],"type":"Point"}
}