{
  "type": "Feature",
  "properties": {
    "addr:full":"Sint-martensplein 2a Aalst Oost-Vlaanderen 9300",
    "addr:housenumber":"2a",
    "addr:postcode":"9300",
    "addr:street":"Sint-Martensplein",
    "iso:country":"BE",
    "sg:address":"Sint-martensplein 2a",
    "sg:city":"Aalst",
    "sg:classifiers":[
        {
            "category":"Education",
            "subcategory":"School",
            "type":"Public Place"
        }
    ],
    "sg:phone":"+32 53 21 29 88",
    "sg:postcode":"9300",
    "sg:province":"Oost-Vlaanderen",
    "sg:tags":[
        "primary"
    ],
    "wof:name":"Dvm Basisschool",
    "wof:placetype":"venue"
},
  "geometry": {"coordinates":[4.0409259796,50.9382476807],"type":"Point"}
}