{
  "type": "Feature",
  "properties": {
    "addr:full":"Molenstraat 92 Waregem West-Vlaanderen 8790",
    "addr:housenumber":"92",
    "addr:postcode":"8790",
    "addr:street":"Molenstraat",
    "iso:country":"BE",
    "sg:address":"Molenstraat 92",
    "sg:city":"Waregem",
    "sg:classifiers":[
        {
            "category":"Retail",
            "subcategory":"Laundry & Dry Cleaning",
            "type":"Services"
        }
    ],
    "sg:phone":"+32 56 60 16 35",
    "sg:postcode":"8790",
    "sg:province":"West-Vlaanderen",
    "wof:name":"Rap En Rein",
    "wof:placetype":"venue"
},
  "geometry": {"coordinates":[3.4236400127,50.8885116577],"type":"Point"}
}