{
  "type": "Feature",
  "properties": {
    "addr:full":"8500 Kortrijk West-Vlaanderen 8500",
    "addr:postcode":"8500;8500",
    "iso:country":"BE",
    "sg:address":"8500",
    "sg:city":"Kortrijk",
    "sg:orig_category":"Erotische Etablissementen Erotische- and Escortediensten",
    "sg:phone":"+32 473 28 31 21",
    "sg:postcode":"8500",
    "sg:province":"West-Vlaanderen",
    "wof:name":"Priv\u00c9 Ontvangst",
    "wof:placetype":"venue"
},
  "geometry": {"coordinates":[3.2800600529,50.817741394],"type":"Point"}
}