{
  "type": "Feature",
  "properties": {
    "addr:full":"Avenue Cardinal Mercier 17 Namur Namur 5000",
    "addr:housenumber":"17",
    "addr:postcode":"5000",
    "addr:street":"Avenue Cardinal Mercier",
    "iso:country":"BE",
    "sg:address":"Avenue Cardinal Mercier 17",
    "sg:city":"Namur",
    "sg:orig_category":"M\u00e9decins and sp\u00e9cialistes",
    "sg:phone":"+32 81 74 26 37",
    "sg:postcode":"5000",
    "sg:province":"Namur",
    "wof:name":"Lucie Duchatel",
    "wof:placetype":"venue"
},
  "geometry": {"coordinates":[4.8522977829,50.4656982422],"type":"Point"}
}