{
  "type": "Feature",
  "properties": {
    "iso:country":"BE",
    "sg:address":"Dahliastraat 13",
    "sg:city":"Aarschot",
    "sg:classifiers":[
        {
            "category":"Professional",
            "subcategory":"Computer Services",
            "type":"Services"
        }
    ],
    "sg:phone":"+32 16 56 18 71",
    "sg:postcode":"3200",
    "sg:province":"Vlaams-Brabant",
    "sg:tags":[
        "-",
        "processing",
        "data",
        "software"
    ],
    "wof:name":"Softidev Bvba",
    "wof:placetype":"venue"
},
  "geometry": {"coordinates":[4.8381500244,50.9889831543],"type":"Point"}
}