{
  "type": "Feature",
  "properties": {
    "iso:country":"BE",
    "sg:address":"Kloosterstraat 26",
    "sg:city":"Zwalm",
    "sg:orig_category":"Boekhouders",
    "sg:phone":"+32 55 49 77 10",
    "sg:postcode":"9630",
    "sg:province":"Oost-Vlaanderen",
    "wof:name":"Robert Vandenhaesevelde",
    "wof:placetype":"venue"
},
  "geometry": {"coordinates":[3.7500801086,50.8637161255],"type":"Point"}
}