{
  "type": "Feature",
  "properties": {
    "addr:full":"Chemin Du Petit Champ 21 Chaumont-gistoux (corroy-le-grand) Brabant Wallon 1325",
    "addr:housenumber":"21",
    "addr:postcode":"1325",
    "addr:street":"Chemin Du Petit Champ",
    "iso:country":"BE",
    "sg:address":"Chemin Du Petit Champ 21",
    "sg:city":"Chaumont-gistoux (corroy-le-grand)",
    "sg:classifiers":[
        {
            "category":"Health Services",
            "subcategory":"Health Practitioner",
            "type":"Services"
        }
    ],
    "sg:phone":"+32 10 68 95 38",
    "sg:postcode":"1325",
    "sg:province":"Brabant Wallon",
    "sg:tags":[
        "therapist",
        "speech"
    ],
    "wof:name":"Cooreman D",
    "wof:placetype":"venue"
},
  "geometry": {"coordinates":[4.6349577904,50.6745414734],"type":"Point"}
}