{
  "type": "Feature",
  "properties": {
    "iso:country":"BE",
    "sg:address":"Hubert Heymansstraat 20",
    "sg:city":"Sint-agatha-berchem/berchem-sainte-agathe",
    "sg:orig_category":"Installatie van houten of kunststof schrijnwerk",
    "sg:phone":"+32 2 465 14 83",
    "sg:postcode":"1082",
    "sg:province":"Bruxelles-Capitale",
    "wof:name":"Maurice Amandt",
    "wof:placetype":"venue"
},
  "geometry": {"coordinates":[4.2993650436,50.8657455444],"type":"Point"}
}