{
  "type": "Feature",
  "properties": {
    "iso:country":"BE",
    "sg:address":"Stationstraat 134",
    "sg:city":"Nijlen",
    "sg:orig_category":"Fleurs and plantes. Souvenirs and objets artisanaux. Animaux domestiques and accessoires. Articles d",
    "sg:phone":"+32 3 480 15 47",
    "sg:postcode":"2560",
    "sg:province":"Antwerpen",
    "wof:name":"Pvba Welters-verelst",
    "wof:placetype":"venue"
},
  "geometry": {"coordinates":[4.6245059967,51.1445541382],"type":"Point"}
}