{
  "type": "Feature",
  "properties": {
    "addr:full":"Place De La Collegiale 8bb Vise Li\u00e8ge 4600",
    "addr:housenumber":"8bb",
    "addr:postcode":"4600",
    "addr:street":"Place De La Collegiale",
    "iso:country":"BE",
    "sg:address":"Place De La Collegiale 8bb",
    "sg:city":"Vise",
    "sg:orig_category":"Dierenartsen",
    "sg:phone":"+32 4 379 56 52",
    "sg:postcode":"4600",
    "sg:province":"Li\u00e8ge",
    "wof:name":"Jean Purnode",
    "wof:placetype":"venue"
},
  "geometry": {"coordinates":[5.6955251694,50.7335929871],"type":"Point"}
}