{
  "type": "Feature",
  "properties": {
    "iso:country":"BE",
    "sg:address":"Bevrijdingsplein 2",
    "sg:city":"Menen",
    "sg:classifiers":[
        {
            "category":"Cafe",
            "type":"Food & Drink"
        }
    ],
    "sg:phone":"+32 56 53 01 54",
    "sg:postcode":"8930",
    "sg:province":"West-Vlaanderen",
    "sg:tags":[
        "caf\u00e9s"
    ],
    "wof:name":"Schifano T. & Lameize Ph.",
    "wof:placetype":"venue"
},
  "geometry": {"coordinates":[3.1144270897,50.7990455627],"type":"Point"}
}