{
  "type": "Feature",
  "properties": {
    "iso:country":"BE",
    "sg:address":"Rue De La Gare 68",
    "sg:city":"Rochefort (eprave)",
    "sg:classifiers":[
        {
            "category":"Real Estate",
            "subcategory":"Architect",
            "type":"Services"
        }
    ],
    "sg:phone":"+32 84 37 70 18",
    "sg:postcode":"5580",
    "sg:province":"Namur",
    "wof:name":"Moreau J",
    "wof:placetype":"venue"
},
  "geometry": {"coordinates":[5.1661520004,50.1516723633],"type":"Point"}
}