{
  "type": "Feature",
  "properties": {
    "iso:country":"BE",
    "sg:address":"Industrielaan 130ba",
    "sg:city":"Anderlecht",
    "sg:orig_category":"Bouwmaterialen Gh Installatie van houten of kunststof schrijnwerk",
    "sg:phone":"+32 2 521 51 17",
    "sg:postcode":"1070",
    "sg:province":"Bruxelles-Capitale",
    "wof:name":"Bara Plastic",
    "wof:placetype":"venue"
},
  "geometry": {"coordinates":[4.3079910278,50.8162460327],"type":"Point"}
}