{
  "type": "Feature",
  "properties": {
    "iso:country":"BE",
    "sg:address":"Klein Veldeken 12ba",
    "sg:city":"Asse",
    "sg:orig_category":"Rusthuizen and serviceflats",
    "sg:phone":"+32 2 453 03 00",
    "sg:postcode":"1730",
    "sg:province":"Vlaams-Brabant",
    "wof:name":"S\u00c9niorie Mida",
    "wof:placetype":"venue"
},
  "geometry": {"coordinates":[4.1955990791,50.9176177979],"type":"Point"}
}