{
  "type": "Feature",
  "properties": {
    "addr:full":"Kesselsesteenweg 43 Nijlen Antwerpen 2560",
    "addr:housenumber":"43",
    "addr:postcode":"2560",
    "addr:street":"Kesselsesteenweg",
    "iso:country":"BE",
    "sg:address":"Kesselsesteenweg 43",
    "sg:city":"Nijlen",
    "sg:orig_category":"Woningbouw",
    "sg:phone":"+32 3 481 94 62",
    "sg:postcode":"2560",
    "sg:province":"Antwerpen",
    "wof:name":"Francois Dieltjens",
    "wof:placetype":"venue"
},
  "geometry": {"coordinates":[4.6616649628,51.1554679871],"type":"Point"}
}