{
  "type": "Feature",
  "properties": {
    "addr:full":"Herkenrodesingel 89 Hasselt Limburg 3500",
    "addr:housenumber":"89",
    "addr:postcode":"3500",
    "addr:street":"Herkenrodesingel",
    "iso:country":"BE",
    "sg:address":"Herkenrodesingel 89",
    "sg:city":"Hasselt",
    "sg:orig_category":"Non-Classified Establishments",
    "sg:phone":"+32 11 25 57 99",
    "sg:postcode":"3500",
    "sg:province":"Limburg",
    "wof:name":"Scholiers Koolzuur Bvba",
    "wof:placetype":"venue"
},
  "geometry": {"coordinates":[5.3328509331,50.9410743713],"type":"Point"}
}