{
  "type": "Feature",
  "properties": {
    "addr:full":"Kalkstraat 56a Anzegem West-Vlaanderen 8570",
    "addr:housenumber":"56a",
    "addr:postcode":"8570",
    "addr:street":"Kalkstraat",
    "iso:country":"BE",
    "sg:address":"Kalkstraat 56a",
    "sg:city":"Anzegem",
    "sg:orig_category":"Non-Classified Establishments",
    "sg:phone":"+32 56 68 81 55",
    "sg:postcode":"8570",
    "sg:province":"West-Vlaanderen",
    "wof:name":"Garotex",
    "wof:placetype":"venue"
},
  "geometry": {"coordinates":[3.4757950306,50.8400611877],"type":"Point"}
}