{
  "type": "Feature",
  "properties": {
    "iso:country":"BE",
    "sg:address":"Dr De La Grappe 12",
    "sg:city":"Forest (bruxelles)",
    "sg:orig_category":"Installation \u00e9lectrique r\u00e9sidentielle",
    "sg:phone":"+32 2 332 32 35",
    "sg:postcode":"1190",
    "sg:province":"Bruxelles-Capitale",
    "wof:name":"Van Leeuwen",
    "wof:placetype":"venue"
},
  "geometry": {"coordinates":[4.3239369392,50.8071861267],"type":"Point"}
}