{
  "type": "Feature",
  "properties": {
    "iso:country":"BE",
    "sg:address":"Posterijlaan 5",
    "sg:city":"Pittem",
    "sg:orig_category":"Graan, zaad and dierenvoeding Gh",
    "sg:phone":"+32 51 46 40 44",
    "sg:postcode":"8740",
    "sg:province":"West-Vlaanderen",
    "wof:name":"Grizo",
    "wof:placetype":"venue"
},
  "geometry": {"coordinates":[3.2561109066,50.9914054871],"type":"Point"}
}