{
  "type": "Feature",
  "properties": {
    "iso:country":"BE",
    "sg:address":"Rue D'eghez\u00e9e 45",
    "sg:city":"Fernelmont (forville)",
    "sg:classifiers":[
        {
            "category":"Banks & Credit Unions",
            "subcategory":"Financial Services",
            "type":"Services"
        }
    ],
    "sg:phone":"+32 81 83 43 00",
    "sg:postcode":"5380",
    "sg:province":"Namur",
    "sg:tags":[
        "financing"
    ],
    "wof:name":"Axa Banque",
    "wof:placetype":"venue"
},
  "geometry": {"coordinates":[5.0000309944,50.5738296509],"type":"Point"}
}