{
  "type": "Feature",
  "properties": {
    "iso:country":"BE",
    "sg:address":"Rue De Huy 30",
    "sg:city":"Waremme",
    "sg:orig_category":"Dakwerken",
    "sg:phone":"+32 19 32 49 48",
    "sg:postcode":"4300",
    "sg:province":"Li\u00e8ge",
    "wof:name":"S. Roultiaux",
    "wof:placetype":"venue"
},
  "geometry": {"coordinates":[5.2513017654,50.6932296753],"type":"Point"}
}