{
  "type": "Feature",
  "properties": {
    "addr:full":"Kortrijksesteenweg 95 Sint-martens-latem Oost-Vlaanderen 9830",
    "addr:housenumber":"95",
    "addr:postcode":"9830",
    "addr:street":"Kortrijksesteenweg",
    "iso:country":"BE",
    "sg:address":"Kortrijksesteenweg 95",
    "sg:city":"Sint-martens-latem",
    "sg:classifiers":[
        {
            "category":"Restaurant",
            "type":"Food & Drink"
        }
    ],
    "sg:phone":"+32 9 282 72 24",
    "sg:postcode":"9830",
    "sg:province":"Oost-Vlaanderen",
    "sg:tags":[
        "de",
        "organisation",
        "\u00c0",
        "fast",
        "catering",
        "emporter",
        "f\u00cates",
        "restaurants"
    ],
    "wof:name":"Restaurant La Chine",
    "wof:placetype":"venue"
},
  "geometry": {"coordinates":[3.6432070732,51.0125236511],"type":"Point"}
}