{
  "type": "Feature",
  "properties": {
    "iso:country":"BE",
    "sg:address":"Place De Jamblinne De Meux 30",
    "sg:city":"Bruxelles (schaerbeek)",
    "sg:classifiers":[
        {
            "category":"Education",
            "subcategory":"School",
            "type":"Public Place"
        }
    ],
    "sg:phone":"+32 2 743 45 20",
    "sg:postcode":"1030",
    "sg:province":"Bruxelles-Capitale",
    "sg:tags":[
        "-",
        "private"
    ],
    "wof:name":"Home Language Box Scrl",
    "wof:placetype":"venue"
},
  "geometry": {"coordinates":[4.3944621086,50.8476600647],"type":"Point"}
}