{
  "type": "Feature",
  "properties": {
    "iso:country":"BE",
    "sg:address":"Chemin Du Beau Vallon 38",
    "sg:city":"Namur",
    "sg:orig_category":"Medische apparatuur, orthopedische artikelen and prothesen Fab",
    "sg:phone":"+32 81 41 15 91",
    "sg:postcode":"5100",
    "sg:province":"Namur",
    "wof:name":"Christyn De Ribaucourt",
    "wof:placetype":"venue"
},
  "geometry": {"coordinates":[4.8759951591,50.3906517029],"type":"Point"}
}