{
  "type": "Feature",
  "properties": {
    "addr:full":"All\u00c9e Des Rosiers 1 Namur Namur 5101",
    "addr:housenumber":"1",
    "addr:postcode":"5101",
    "addr:street":"Alle\u0301E Des Rosiers",
    "iso:country":"BE",
    "sg:address":"All\u00c9e Des Rosiers 1",
    "sg:city":"Namur",
    "sg:orig_category":"Diverse bedrijfsbeheeradviesbureaus",
    "sg:phone":"+32 81 30 57 58",
    "sg:postcode":"5101",
    "sg:province":"Namur",
    "wof:name":"Ch.dusollier",
    "wof:placetype":"venue"
},
  "geometry": {"coordinates":[4.9061760902,50.4448471069],"type":"Point"}
}