{
  "type": "Feature",
  "properties": {
    "addr:full":"Bogaertstraat 26 Sint-martens-latem Oost-Vlaanderen 9830",
    "addr:housenumber":"26",
    "addr:postcode":"9830",
    "addr:street":"Bogaertstraat",
    "iso:country":"BE",
    "sg:address":"Bogaertstraat 26",
    "sg:city":"Sint-martens-latem",
    "sg:classifiers":[
        {
            "category":"Social Services",
            "subcategory":"Job Training",
            "type":"Services"
        }
    ],
    "sg:phone":"+32 9 282 65 78",
    "sg:postcode":"9830",
    "sg:province":"Oost-Vlaanderen",
    "sg:tags":[
        "personnel"
    ],
    "wof:name":"Delbecque B",
    "wof:placetype":"venue"
},
  "geometry": {"coordinates":[3.6129500866,51.0234184265],"type":"Point"}
}