{
  "type": "Feature",
  "properties": {
    "addr:full":"Rue Froide 10 Ham-sur-heure-nalinnes Hainaut 6120",
    "addr:housenumber":"10",
    "addr:postcode":"6120",
    "addr:street":"Rue Froide;Hainaut",
    "iso:country":"BE",
    "sg:address":"Rue Froide 10",
    "sg:city":"Ham-sur-heure-nalinnes",
    "sg:orig_category":"Slagers",
    "sg:phone":"+32 71 21 31 82",
    "sg:postcode":"6120",
    "sg:province":"Hainaut",
    "wof:name":"Etienne Lefevre",
    "wof:placetype":"venue"
},
  "geometry": {"coordinates":[4.3872900009,50.3219146729],"type":"Point"}
}