{
  "type": "Feature",
  "properties": {
    "iso:country":"BE",
    "sg:address":"Roeselarestraat 67",
    "sg:city":"Wevelgem",
    "sg:orig_category":"Herstellingen and onderhoud van auto's Voertuigen",
    "sg:phone":"+32 56 41 45 07",
    "sg:postcode":"8560",
    "sg:province":"West-Vlaanderen",
    "wof:name":"Gar. Debrouwere Verpoort",
    "wof:placetype":"venue"
},
  "geometry": {"coordinates":[3.1800160408,50.8126907349],"type":"Point"}
}