{
  "type": "Feature",
  "properties": {
    "addr:full":"Avenue Godin-parnajon 2 Huy Li\u00e8ge 4500",
    "addr:housenumber":"2",
    "addr:postcode":"4500",
    "addr:street":"Avenue Godin-Parnajon",
    "iso:country":"BE",
    "sg:address":"Avenue Godin-parnajon 2",
    "sg:city":"Huy",
    "sg:classifiers":[
        {
            "category":"Health Services",
            "subcategory":"Nursing And Care Facility",
            "type":"Services"
        }
    ],
    "sg:phone":"+32 85 21 49 31",
    "sg:postcode":"4500",
    "sg:province":"Li\u00e8ge",
    "sg:tags":[
        "public"
    ],
    "wof:name":"Admin. Contrib. Directes",
    "wof:placetype":"venue"
},
  "geometry": {"coordinates":[5.2424778938,50.5239181519],"type":"Point"}
}