{
  "type": "Feature",
  "properties": {
    "addr:full":"Rue Neuville 23 Olne Li\u00e8ge 4877",
    "addr:housenumber":"23",
    "addr:postcode":"4877",
    "addr:street":"Rue Neuville",
    "iso:country":"BE",
    "sg:address":"Rue Neuville 23",
    "sg:city":"Olne",
    "sg:classifiers":[
        {
            "category":"Banks & Credit Unions",
            "subcategory":"Investment Brokerage",
            "type":"Services"
        }
    ],
    "sg:phone":"+32 4 358 63 82",
    "sg:postcode":"4877",
    "sg:province":"Li\u00e8ge",
    "sg:tags":[
        "repair",
        "-",
        "installation",
        "sanitary",
        "article"
    ],
    "wof:name":"Meyers J Ets",
    "wof:placetype":"venue"
},
  "geometry": {"coordinates":[5.715113163,50.5929489136],"type":"Point"}
}