{
  "type": "Feature",
  "properties": {
    "iso:country":"BE",
    "sg:address":"F Wouterslaan 33",
    "sg:city":"Kampenhout",
    "sg:orig_category":"Installatie van houten of kunststof schrijnwerk",
    "sg:phone":"+32 16 65 55 63",
    "sg:postcode":"1910",
    "sg:province":"Vlaams-Brabant",
    "wof:name":"Renova Rama",
    "wof:placetype":"venue"
},
  "geometry": {"coordinates":[4.5518369675,50.9391326904],"type":"Point"}
}