{
  "type": "Feature",
  "properties": {
    "addr:full":"Damstraat 168 Moerbeke-waas Oost-Vlaanderen 9180",
    "addr:housenumber":"168",
    "addr:postcode":"9180",
    "addr:street":"Damstraat;Oost-Vlaanderen",
    "iso:country":"BE",
    "sg:address":"Damstraat 168",
    "sg:city":"Moerbeke-waas",
    "sg:orig_category":"HUISBRANDOLIE",
    "sg:phone":"+32 9 346 84 42",
    "sg:postcode":"9180",
    "sg:province":"Oost-Vlaanderen",
    "wof:name":"Dirk Clauwaert",
    "wof:placetype":"venue"
},
  "geometry": {"coordinates":[3.9502029419,51.1730003357],"type":"Point"}
}