{
  "type": "Feature",
  "properties": {
    "addr:full":"Winterweg 14 Ternat Vlaams-Brabant 1740",
    "addr:housenumber":"14",
    "addr:postcode":"1740",
    "addr:street":"Winterweg",
    "iso:country":"BE",
    "sg:address":"Winterweg 14",
    "sg:city":"Ternat",
    "sg:orig_category":"Overheidsdiensten",
    "sg:phone":"+32 2 582 12 63",
    "sg:postcode":"1740",
    "sg:province":"Vlaams-Brabant",
    "wof:name":"Admin. Directe Belast.",
    "wof:placetype":"venue"
},
  "geometry": {"coordinates":[4.1803641319,50.8708839417],"type":"Point"}
}