{
  "type": "Feature",
  "properties": {
    "addr:full":"Kortrijkstraat 241 Wevelgem West-Vlaanderen 8560",
    "addr:housenumber":"241",
    "addr:postcode":"8560",
    "addr:street":"Kortrijkstraat",
    "iso:country":"BE",
    "sg:address":"Kortrijkstraat 241",
    "sg:city":"Wevelgem",
    "sg:classifiers":[
        {
            "category":"Professional",
            "subcategory":"Computer Services",
            "type":"Services"
        }
    ],
    "sg:phone":"+32 56 41 88 00",
    "sg:postcode":"8560",
    "sg:province":"West-Vlaanderen",
    "sg:tags":[
        "-",
        "processing",
        "data",
        "software"
    ],
    "wof:name":"Craeynest Software Bvba",
    "wof:placetype":"venue"
},
  "geometry": {"coordinates":[3.1971149445,50.8129653931],"type":"Point"}
}