{
  "type": "Feature",
  "properties": {
    "iso:country":"BE",
    "sg:address":"Stationsplein 3",
    "sg:city":"Zottegem",
    "sg:classifiers":[
        {
            "category":"Cafe",
            "type":"Food & Drink"
        }
    ],
    "sg:phone":"+32 9 360 50 69",
    "sg:postcode":"9620",
    "sg:province":"Oost-Vlaanderen",
    "sg:tags":[
        "caf\u00e9s"
    ],
    "wof:name":"Gebroeders Van Geert",
    "wof:placetype":"venue"
},
  "geometry": {"coordinates":[3.8115520477,50.8692245483],"type":"Point"}
}