{
  "type": "Feature",
  "properties": {
    "addr:full":"Holakenstraat 3 Halen Limburg 3545",
    "addr:housenumber":"3",
    "addr:postcode":"3545",
    "addr:street":"Holakenstraat",
    "iso:country":"BE",
    "sg:address":"Holakenstraat 3",
    "sg:city":"Halen",
    "sg:orig_category":"Paramedische behandelingen",
    "sg:phone":"+32 13 44 29 00",
    "sg:postcode":"3545",
    "sg:province":"Limburg",
    "wof:name":"F. Arnauts",
    "wof:placetype":"venue"
},
  "geometry": {"coordinates":[5.1260480881,50.9340629578],"type":"Point"}
}