{
  "type": "Feature",
  "properties": {
    "addr:full":"Beverhoutplein 3 Gent Oost-Vlaanderen 9000",
    "addr:housenumber":"3",
    "addr:postcode":"9000",
    "addr:street":"Beverhoutplein;Oost-Vlaanderen",
    "iso:country":"BE",
    "sg:address":"Beverhoutplein 3",
    "sg:city":"Gent",
    "sg:orig_category":"Art and fournitures artistiques. Antiquit\u00e9s",
    "sg:phone":"+32 9 228 49 55",
    "sg:postcode":"9000",
    "sg:province":"Oost-Vlaanderen",
    "wof:name":"Rudolphe Bouvie",
    "wof:placetype":"venue"
},
  "geometry": {"coordinates":[3.7284491062,51.0570106506],"type":"Point"}
}