{
  "type": "Feature",
  "properties": {
    "addr:full":"Diestsevest 14 Leuven Vlaams-Brabant 3000",
    "addr:housenumber":"14",
    "addr:postcode":"3000",
    "addr:street":"Diestsevest",
    "iso:country":"BE",
    "sg:address":"Diestsevest 14",
    "sg:city":"Leuven",
    "sg:classifiers":[
        {
            "category":"Professional",
            "subcategory":"Management & Consulting",
            "type":"Services"
        }
    ],
    "sg:phone":"+32 2 474 01 09",
    "sg:postcode":"3000",
    "sg:province":"Vlaams-Brabant",
    "sg:tags":[
        "consultant",
        "-",
        "legislation",
        "social"
    ],
    "wof:name":"Acerta",
    "wof:placetype":"venue"
},
  "geometry": {"coordinates":[4.7140460014,50.8826942444],"type":"Point"}
}