{
  "type": "Feature",
  "properties": {
    "iso:country":"BE",
    "sg:address":"Boulevard Anspach 41",
    "sg:city":"Bruxelles",
    "sg:classifiers":[
        {
            "category":"Social Services",
            "type":"Services"
        }
    ],
    "sg:phone":"+32 2 219 66 73",
    "sg:postcode":"1000",
    "sg:province":"Bruxelles-Capitale",
    "wof:name":"Werk Voor Sociaal Wederaanpassing",
    "wof:placetype":"venue"
},
  "geometry": {"coordinates":[4.3505377769,50.8494491577],"type":"Point"}
}