{
  "type": "Feature",
  "properties": {
    "iso:country":"BE",
    "sg:address":"Borgtstraat 35",
    "sg:city":"Vilvoorde",
    "sg:classifiers":[
        {
            "category":"Autos & Motor Vehicles",
            "subcategory":"Motorcycle Sales",
            "type":"Retail Goods"
        }
    ],
    "sg:phone":"+32 2 251 72 18",
    "sg:postcode":"1800",
    "sg:province":"Vlaams-Brabant",
    "sg:tags":[
        "yamaha"
    ],
    "wof:name":"Van Heers Yves",
    "wof:placetype":"venue"
},
  "geometry": {"coordinates":[4.4151129723,50.9262504578],"type":"Point"}
}