{
  "type": "Feature",
  "properties": {
    "iso:country":"BE",
    "sg:address":"Rue Du Maris 2",
    "sg:city":"Brussels",
    "sg:classifiers":[
        {
            "category":"Banks & Credit Unions",
            "subcategory":"Bank",
            "type":"Services"
        }
    ],
    "sg:phone":"+32 15 20 26 62",
    "sg:postcode":"1000",
    "sg:province":"Bruxelles-Capitale",
    "wof:name":"Isep Sa (belgium)",
    "wof:placetype":"venue"
},
  "geometry": {"coordinates":[4.3575558662,50.8505554199],"type":"Point"}
}