{
  "type": "Feature",
  "properties": {
    "addr:full":"Nieuwpoortsestenweg 467 Oostende West-Vlaanderen 8400",
    "addr:housenumber":"467",
    "addr:postcode":"8400",
    "iso:country":"BE",
    "sg:address":"Nieuwpoortsestenweg 467",
    "sg:city":"Oostende",
    "sg:orig_category":"Reisbureaus",
    "sg:phone":"+32 59 80 10 77",
    "sg:postcode":"8400",
    "sg:province":"West-Vlaanderen",
    "wof:name":"Lotus Reizen",
    "wof:placetype":"venue"
},
  "geometry": {"coordinates":[2.8899390697,51.2159957886],"type":"Point"}
}