{
  "type": "Feature",
  "properties": {
    "addr:full":"Avenue Libre Acad\u00e9mie 56 Bruxelles (anderlecht) Bruxelles-Capitale 1070",
    "addr:housenumber":"56",
    "addr:postcode":"1070",
    "addr:street":"Avenue Libre Acade\u0301Mie",
    "iso:country":"BE",
    "sg:address":"Avenue Libre Acad\u00e9mie 56",
    "sg:city":"Bruxelles (anderlecht)",
    "sg:classifiers":[
        {
            "category":"Health Services",
            "subcategory":"Health Practitioner",
            "type":"Services"
        }
    ],
    "sg:phone":"+32 475 54 93 34",
    "sg:postcode":"1070",
    "sg:province":"Bruxelles-Capitale",
    "sg:tags":[
        "physiotherapist"
    ],
    "wof:name":"Kestemont Emmanuel",
    "wof:placetype":"venue"
},
  "geometry": {"coordinates":[4.2854499817,50.8304367065],"type":"Point"}
}