{
  "type": "Feature",
  "properties": {
    "addr:full":"Rue De La Neuville 56 Braine L'alleud (braine-l'alleud) Brabant Wallon 1420",
    "addr:housenumber":"56",
    "addr:postcode":"1420",
    "addr:street":"Rue De La Neuville",
    "iso:country":"BE",
    "sg:address":"Rue De La Neuville 56",
    "sg:city":"Braine L'alleud (braine-l'alleud)",
    "sg:classifiers":[
        {
            "category":"Health Services",
            "subcategory":"Health Practitioner",
            "type":"Services"
        }
    ],
    "sg:phone":"+32 2 384 36 48",
    "sg:postcode":"1420",
    "sg:province":"Brabant Wallon",
    "sg:tags":[
        "physiotherapist"
    ],
    "wof:name":"Wanty A",
    "wof:placetype":"venue"
},
  "geometry": {"coordinates":[1.4309049845,49.8882484436],"type":"Point"}
}