{
  "type": "Feature",
  "properties": {
    "addr:full":"Rue Bois L'ev\u00caque 4 Andenne Namur 5300",
    "addr:housenumber":"4",
    "addr:postcode":"5300",
    "addr:street":"Rue Bois L'Eve \u0302Que",
    "iso:country":"BE",
    "sg:address":"Rue Bois L'ev\u00caque 4",
    "sg:city":"Andenne",
    "sg:orig_category":"Goederenvervoer over de weg",
    "sg:phone":"+32 81 58 88 88",
    "sg:postcode":"5300",
    "sg:province":"Namur",
    "wof:name":"Sandri M",
    "wof:placetype":"venue"
},
  "geometry": {"coordinates":[4.9988970757,50.4720611572],"type":"Point"}
}