{
  "type": "Feature",
  "properties": {
    "iso:country":"BE",
    "sg:address":"Avenue De L'uruguay 7",
    "sg:city":"Bruxelles",
    "sg:classifiers":[
        {
            "category":"Real Estate",
            "subcategory":"Real Estate Services",
            "type":"Services"
        }
    ],
    "sg:phone":"+32 475 79 86 10",
    "sg:postcode":"1000",
    "sg:province":"Bruxelles-Capitale",
    "wof:name":"Consultance & Gestion Sprl",
    "wof:placetype":"venue"
},
  "geometry": {"coordinates":[4.393348217,50.799446106],"type":"Point"}
}