{
  "type": "Feature",
  "properties": {
    "iso:country":"BE",
    "sg:address":"Gentstraat 95",
    "sg:city":"Sint-niklaas",
    "sg:orig_category":"Eleveurs de bovins. Eleveurs and marchands de porcs",
    "sg:phone":"+32 3 766 19 97",
    "sg:postcode":"9111",
    "sg:province":"Oost-Vlaanderen",
    "wof:name":"Gilbert De Pauw",
    "wof:placetype":"venue"
},
  "geometry": {"coordinates":[4.0978980064,51.1703147888],"type":"Point"}
}