{
  "type": "Feature",
  "properties": {
    "iso:country":"BE",
    "sg:address":"Rempart Des Arquebusiers 31",
    "sg:city":"Vis\u00e9",
    "sg:classifiers":[
        {
            "category":"Personal",
            "subcategory":"Beauty Salon",
            "type":"Services"
        }
    ],
    "sg:phone":"+32 4 379 42 31",
    "sg:postcode":"4600",
    "sg:province":"Li\u00e8ge",
    "sg:tags":[
        "lady",
        "-",
        "hairdressing"
    ],
    "wof:name":"Gomina",
    "wof:placetype":"venue"
},
  "geometry": {"coordinates":[5.6968851089,50.7343864441],"type":"Point"}
}