{
  "type": "Feature",
  "properties": {
    "addr:full":"Toekomststraat 6 Vilvoorde Vlaams-Brabant 1800",
    "addr:housenumber":"6",
    "addr:postcode":"1800",
    "addr:street":"Toekomststraat",
    "iso:country":"BE",
    "sg:address":"Toekomststraat 6",
    "sg:city":"Vilvoorde",
    "sg:classifiers":[
        {
            "category":"Health Services",
            "subcategory":"Doctor",
            "type":"Services"
        }
    ],
    "sg:phone":"+32 2 251 53 23",
    "sg:postcode":"1800",
    "sg:province":"Vlaams-Brabant",
    "sg:tags":[
        "psychotherapist",
        "psychoanalyst"
    ],
    "wof:name":"Maes S",
    "wof:placetype":"venue"
},
  "geometry": {"coordinates":[4.4248809814,50.9293746948],"type":"Point"}
}