{
  "type": "Feature",
  "properties": {
    "addr:full":"Leuvensesteenweg 184 Diest Vlaams-Brabant 3290",
    "addr:housenumber":"184",
    "addr:postcode":"3290",
    "addr:street":"Leuvensesteenweg",
    "iso:country":"BE",
    "sg:address":"Leuvensesteenweg 184",
    "sg:city":"Diest",
    "sg:orig_category":"Voertuigen",
    "sg:phone":"+32 13 33 32 53",
    "sg:postcode":"3290",
    "sg:province":"Vlaams-Brabant",
    "wof:name":"Garage Thomas R.",
    "wof:placetype":"venue"
},
  "geometry": {"coordinates":[5.0362567902,50.9709701538],"type":"Point"}
}