{
  "type": "Feature",
  "properties": {
    "iso:country":"BE",
    "sg:address":"Rue Arthur Fran\u00c7ois 6",
    "sg:city":"Estaimpuis",
    "sg:orig_category":"Installatie van houten of kunststof schrijnwerk",
    "sg:phone":"+32 56 48 72 34",
    "sg:postcode":"7730",
    "sg:province":"Hainaut",
    "wof:name":"Bernard Willocq",
    "wof:placetype":"venue"
},
  "geometry": {"coordinates":[3.2675020695,50.6879997253],"type":"Point"}
}