{
  "type": "Feature",
  "properties": {
    "iso:country":"BE",
    "sg:address":"Helskensstraat 42",
    "sg:city":"Tremelo",
    "sg:classifiers":[
        {
            "category":"Health Services",
            "subcategory":"Nursing And Care Facility",
            "type":"Services"
        }
    ],
    "sg:phone":"+32 16 53 48 04",
    "sg:postcode":"3120",
    "sg:province":"Vlaams-Brabant",
    "sg:tags":[
        "home"
    ],
    "wof:name":"Busschodts P",
    "wof:placetype":"venue"
},
  "geometry": {"coordinates":[4.6891989708,50.9880027771],"type":"Point"}
}