{
  "type": "Feature",
  "properties": {
    "addr:full":"Chauss\u00c9e De Tirlemont 40 Wanze Li\u00e8ge 4520",
    "addr:housenumber":"40",
    "addr:postcode":"4520",
    "addr:street":"Chausse\u0301E De Tirlemont",
    "iso:country":"BE",
    "sg:address":"Chauss\u00c9e De Tirlemont 40",
    "sg:city":"Wanze",
    "sg:classifiers":[
        {
            "category":"Insurance",
            "subcategory":"Insurance Agent",
            "type":"Services"
        }
    ],
    "sg:phone":"+32 85 23 48 39",
    "sg:postcode":"4520",
    "sg:province":"Li\u00e8ge",
    "sg:tags":[
        "verzekeringsmakelaars",
        "expert"
    ],
    "wof:name":"J.d. Assurances",
    "wof:placetype":"venue"
},
  "geometry": {"coordinates":[5.2198619843,50.5349502563],"type":"Point"}
}