{
  "type": "Feature",
  "properties": {
    "addr:full":"Avenue Des Celtes 32 Bruxelles (etterbeek) Bruxelles-Capitale 1040",
    "addr:housenumber":"32",
    "addr:postcode":"1040",
    "addr:street":"Avenue Des Celtes",
    "iso:country":"BE",
    "sg:address":"Avenue Des Celtes 32",
    "sg:city":"Bruxelles (etterbeek)",
    "sg:classifiers":[
        {
            "category":"Professional",
            "type":"Services"
        }
    ],
    "sg:phone":"+32 2 734 38 81",
    "sg:postcode":"1040",
    "sg:province":"Bruxelles-Capitale",
    "sg:tags":[
        "entertainer"
    ],
    "wof:name":"Dejean D",
    "wof:placetype":"venue"
},
  "geometry": {"coordinates":[4.3977708817,50.8382720947],"type":"Point"}
}