{
  "type": "Feature",
  "properties": {
    "iso:country":"BE",
    "sg:address":"Route De Modave 4a",
    "sg:city":"Modave",
    "sg:orig_category":"Kapsalons",
    "sg:phone":"+32 85 41 29 18",
    "sg:postcode":"4577",
    "sg:province":"Li\u00e8ge",
    "wof:name":"Espace Beaut\u00c9 Imagin'hair",
    "wof:placetype":"venue"
},
  "geometry": {"coordinates":[5.2990298271,50.4409332275],"type":"Point"}
}