{
  "type": "Feature",
  "properties": {
    "addr:full":"Leuvensesteenweg 326 Brussel/bruxelles Bruxelles-Capitale 1000",
    "addr:housenumber":"326",
    "addr:postcode":"1000",
    "addr:street":"Leuvensesteenweg;/",
    "iso:country":"BE",
    "sg:address":"Leuvensesteenweg 326",
    "sg:city":"Brussel/bruxelles",
    "sg:orig_category":"Huishoudapparaten, televisies and radio's",
    "sg:phone":"+32 2 735 38 30",
    "sg:postcode":"1000",
    "sg:province":"Bruxelles-Capitale",
    "wof:name":"Maison Verheyden",
    "wof:placetype":"venue"
},
  "geometry": {"coordinates":[4.3838758469,50.8512153625],"type":"Point"}
}