{
  "type": "Feature",
  "properties": {
    "iso:country":"BE",
    "sg:address":"Onderstraat 1",
    "sg:city":"Lennik (gaasbeek)",
    "sg:classifiers":[
        {
            "category":"Wholesale",
            "subcategory":"Beer",
            "type":"Manufacturing & Wholesale Goods"
        }
    ],
    "sg:phone":"+32 2 532 31 75",
    "sg:postcode":"1750",
    "sg:province":"Vlaams-Brabant",
    "sg:tags":[
        "ale",
        "-"
    ],
    "wof:name":"Limbourg Bierhandel Drinks Bvba",
    "wof:placetype":"venue"
},
  "geometry": {"coordinates":[4.189953804,50.79920578],"type":"Point"}
}