{
  "type": "Feature",
  "properties": {
    "addr:full":"Heistraat 265 Sint-niklaas Oost-Vlaanderen 9100",
    "addr:housenumber":"265",
    "addr:postcode":"9100",
    "addr:street":"Heistraat",
    "iso:country":"BE",
    "sg:address":"Heistraat 265",
    "sg:city":"Sint-niklaas",
    "sg:orig_category":"Slagers",
    "sg:phone":"+32 3 777 71 30",
    "sg:postcode":"9100",
    "sg:province":"Oost-Vlaanderen",
    "wof:name":"Johan Quatacker",
    "wof:placetype":"venue"
},
  "geometry": {"coordinates":[4.1397948265,51.1759300232],"type":"Point"}
}