{
  "type": "Feature",
  "properties": {
    "addr:full":"Clemenceaustraat 211 Sint-katelijne-waver Antwerpen 2860",
    "addr:housenumber":"211",
    "addr:postcode":"2860",
    "addr:street":"Clemenceaustraat",
    "iso:country":"BE",
    "sg:address":"Clemenceaustraat 211",
    "sg:city":"Sint-katelijne-waver",
    "sg:orig_category":"Producteurs de l\u00e9gumes",
    "sg:phone":"+32 15 31 25 96",
    "sg:postcode":"2860",
    "sg:province":"Antwerpen",
    "wof:name":"Frans Van Den Eynde",
    "wof:placetype":"venue"
},
  "geometry": {"coordinates":[4.4943141937,51.0662269592],"type":"Point"}
}