{
  "type": "Feature",
  "properties": {
    "iso:country":"BE",
    "sg:address":"Rue Comte Cornet 17",
    "sg:city":"Mons",
    "sg:orig_category":"Avocats and conseillers juridiques",
    "sg:phone":"+32 65 84 05 15",
    "sg:postcode":"7020",
    "sg:province":"Hainaut",
    "wof:name":"Jean-paul Moerman",
    "wof:placetype":"venue"
},
  "geometry": {"coordinates":[3.9553449154,50.4761772156],"type":"Point"}
}