{
  "type": "Feature",
  "properties": {
    "addr:full":"Rue Z\u00e9nobe Gramme 75 Hannut Li\u00e8ge 4280",
    "addr:housenumber":"75",
    "addr:postcode":"4280",
    "addr:street":"Rue Ze\u0301Nobe Gramme",
    "iso:country":"BE",
    "sg:address":"Rue Z\u00e9nobe Gramme 75",
    "sg:city":"Hannut",
    "sg:classifiers":[
        {
            "category":"Shopping",
            "subcategory":"Crafts & Fabrics",
            "type":"Retail Goods"
        }
    ],
    "sg:phone":"+32 19 51 23 42",
    "sg:postcode":"4280",
    "sg:province":"Li\u00e8ge",
    "sg:tags":[
        "silk",
        "-"
    ],
    "wof:name":"Diolux",
    "wof:placetype":"venue"
},
  "geometry": {"coordinates":[5.0744299889,50.6704330444],"type":"Point"}
}