{
  "type": "Feature",
  "properties": {
    "addr:full":"Avenue Du Four \u00e0 Briques 1 Bruxelles (evere) Bruxelles-Capitale 1140",
    "addr:housenumber":"1",
    "addr:postcode":"1140",
    "addr:street":"Avenue Du Four A\u0300 Briques",
    "iso:country":"BE",
    "sg:address":"Avenue Du Four \u00e0 Briques 1",
    "sg:city":"Bruxelles (evere)",
    "sg:classifiers":[
        {
            "category":"Manufacturing",
            "subcategory":"Chemicals & Compounds",
            "type":"Manufacturing & Wholesale Goods"
        }
    ],
    "sg:phone":"+32 2 726 11 85",
    "sg:postcode":"1140",
    "sg:province":"Bruxelles-Capitale",
    "sg:tags":[
        "pharmaceutical",
        "product"
    ],
    "wof:name":"Melisana Nv",
    "wof:placetype":"venue"
},
  "geometry": {"coordinates":[4.4119529724,50.8647651672],"type":"Point"}
}