{
  "type": "Feature",
  "properties": {
    "iso:country":"BE",
    "sg:address":"Maarschalk Fochlaan 26",
    "sg:city":"Ieper",
    "sg:classifiers":[
        {
            "category":"Cafe",
            "type":"Food & Drink"
        }
    ],
    "sg:phone":"+32 57 20 78 80",
    "sg:postcode":"8900",
    "sg:province":"West-Vlaanderen",
    "sg:tags":[
        "caf\u00e9s"
    ],
    "wof:name":"Snackbar Den Ijzer",
    "wof:placetype":"venue"
},
  "geometry": {"coordinates":[2.876390934,50.8498306274],"type":"Point"}
}