{
  "type": "Feature",
  "properties": {
    "addr:full":"Lombardsijdelaan 215 Middelkerke (westende) West-Vlaanderen 8434",
    "addr:housenumber":"215",
    "addr:postcode":"8434",
    "addr:street":"Lombardsijdelaan",
    "iso:country":"BE",
    "sg:address":"Lombardsijdelaan 215",
    "sg:city":"Middelkerke (westende)",
    "sg:classifiers":[
        {
            "category":"Professional",
            "subcategory":"Testing Lab",
            "type":"Services"
        }
    ],
    "sg:phone":"+32 58 23 47 95",
    "sg:postcode":"8434",
    "sg:province":"West-Vlaanderen",
    "sg:tags":[
        "chemist"
    ],
    "wof:name":"Baeyaert F",
    "wof:placetype":"venue"
},
  "geometry": {"coordinates":[2.7591700554,51.150806427],"type":"Point"}
}