{
  "type": "Feature",
  "properties": {
    "addr:full":"Boomgaardstraat 24 Ieper West-Vlaanderen 8900",
    "addr:housenumber":"24",
    "addr:postcode":"8900",
    "addr:street":"Boomgaardstraat",
    "iso:country":"BE",
    "sg:address":"Boomgaardstraat 24",
    "sg:city":"Ieper",
    "sg:orig_category":"Fleurs and plantes",
    "sg:phone":"+32 57 20 11 44",
    "sg:postcode":"8900",
    "sg:province":"West-Vlaanderen",
    "wof:name":"Bloemen Flora",
    "wof:placetype":"venue"
},
  "geometry": {"coordinates":[2.8847060204,50.8497772217],"type":"Point"}
}