{
  "type": "Feature",
  "properties": {
    "addr:full":"Avenue Louise 363 Bruxelles (ixelles) Bruxelles-Capitale 1050",
    "addr:housenumber":"363",
    "addr:postcode":"1050",
    "addr:street":"Avenue Louise",
    "iso:country":"BE",
    "sg:address":"Avenue Louise 363",
    "sg:city":"Bruxelles (ixelles)",
    "sg:classifiers":[
        {
            "category":"Health Services",
            "subcategory":"Health Practitioner",
            "type":"Services"
        }
    ],
    "sg:phone":"+32 2 648 76 99",
    "sg:postcode":"1050",
    "sg:province":"Bruxelles-Capitale",
    "sg:tags":[
        "physiotherapist"
    ],
    "wof:name":"De Vos Annie",
    "wof:placetype":"venue"
},
  "geometry": {"coordinates":[4.3691887856,50.8212280273],"type":"Point"}
}