{
  "type": "Feature",
  "properties": {
    "addr:full":"Rue Notre-dame 76 Box 1 Namur Namur 5000",
    "addr:housenumber":"76;1",
    "addr:postcode":"5000",
    "addr:street":"Rue Notre-Dame;Box",
    "iso:country":"BE",
    "sg:address":"Rue Notre-dame 76 Box 1",
    "sg:city":"Namur",
    "sg:classifiers":[
        {
            "category":"Food & Beverages",
            "subcategory":"Groceries & Convenience Stores",
            "type":"Retail Goods"
        }
    ],
    "sg:phone":"+32 81 83 59 32",
    "sg:postcode":"5000",
    "sg:province":"Namur",
    "sg:tags":[
        "grocer"
    ],
    "wof:name":"Shop Services",
    "wof:placetype":"venue"
},
  "geometry": {"coordinates":[4.8657460213,50.4598121643],"type":"Point"}
}