{
  "type": "Feature",
  "properties": {
    "addr:full":"Everdijstraat 31 Antwerpen Antwerpen 2000",
    "addr:housenumber":"31",
    "addr:postcode":"2000",
    "addr:street":"Everdijstraat",
    "iso:country":"BE",
    "sg:address":"Everdijstraat 31",
    "sg:city":"Antwerpen",
    "sg:classifiers":[
        {
            "category":"Professional",
            "subcategory":"Management & Consulting",
            "type":"Services"
        }
    ],
    "sg:phone":"+32 3 213 04 44",
    "sg:postcode":"2000",
    "sg:province":"Antwerpen",
    "sg:tags":[
        "consultant",
        "law"
    ],
    "wof:name":"Juribel Partners Bvba",
    "wof:placetype":"venue"
},
  "geometry": {"coordinates":[4.403055191,51.2166671753],"type":"Point"}
}