{
  "type": "Feature",
  "properties": {
    "iso:country":"BE",
    "sg:address":"Rue Du Roi Albert 221",
    "sg:city":"Oupeye",
    "sg:orig_category":"Banques and organismes de cr\u00e9dit",
    "sg:phone":"+32 4 264 34 22",
    "sg:postcode":"4680",
    "sg:province":"Li\u00e8ge",
    "wof:name":"Bbl",
    "wof:placetype":"venue"
},
  "geometry": {"coordinates":[5.6446280479,50.709022522],"type":"Point"}
}