{
  "type": "Feature",
  "properties": {
    "addr:full":"Koning Albertlaan 2e Maldegem Oost-Vlaanderen 9990",
    "addr:housenumber":"2e",
    "addr:postcode":"9990",
    "addr:street":"Koning Albertlaan",
    "iso:country":"BE",
    "sg:address":"Koning Albertlaan 2e",
    "sg:city":"Maldegem",
    "sg:classifiers":[
        {
            "category":"Airport",
            "subcategory":"International",
            "type":"Transportation"
        }
    ],
    "sg:phone":"+32 50 71 67 94",
    "sg:postcode":"9990",
    "sg:province":"Oost-Vlaanderen",
    "sg:tags":[
        "-",
        "transport"
    ],
    "wof:name":"Daltrans",
    "wof:placetype":"venue"
},
  "geometry": {"coordinates":[3.4241960049,51.2088737488],"type":"Point"}
}