{
  "type": "Feature",
  "properties": {
    "addr:full":"Rue De L'enseignement 43 Li\u00c8ge Li\u00e8ge 4020",
    "addr:housenumber":"43",
    "addr:postcode":"4020",
    "addr:street":"Rue De L'Enseignement",
    "iso:country":"BE",
    "sg:address":"Rue De L'enseignement 43",
    "sg:city":"Li\u00c8ge",
    "sg:orig_category":"Rev\u00eatements pour sols and murs. D\u00e9corateurs d'int\u00e9rieur. Peinture",
    "sg:phone":"+32 4 344 34 60",
    "sg:postcode":"4020",
    "sg:province":"Li\u00e8ge",
    "wof:name":"Bureau D.t.l.",
    "wof:placetype":"venue"
},
  "geometry": {"coordinates":[5.5882949829,50.6405487061],"type":"Point"}
}