{
  "type": "Feature",
  "properties": {
    "addr:full":"Rue Salvador Allende 165 Binche Hainaut 7134",
    "addr:housenumber":"165",
    "addr:postcode":"7134",
    "addr:street":"Rue Salvador Allende",
    "iso:country":"BE",
    "sg:address":"Rue Salvador Allende 165",
    "sg:city":"Binche",
    "sg:orig_category":"Catering and organisatie van feesten",
    "sg:phone":"+32 64 34 25 55",
    "sg:postcode":"7134",
    "sg:province":"Hainaut",
    "wof:name":"Traiteur Lo Spuntino",
    "wof:placetype":"venue"
},
  "geometry": {"coordinates":[4.2220668793,50.4235343933],"type":"Point"}
}