{
  "type": "Feature",
  "properties": {
    "iso:country":"BE",
    "sg:address":"Avenue Du P\u00e9rou 25",
    "sg:city":"Bruxelles",
    "sg:classifiers":[
        {
            "category":"Retail",
            "subcategory":"Event Space",
            "type":"Services"
        }
    ],
    "sg:phone":"+32 476 60 32 96",
    "sg:postcode":"1000",
    "sg:province":"Bruxelles-Capitale",
    "sg:tags":[
        "organisation"
    ],
    "wof:name":"Ramdam Sprl",
    "wof:placetype":"venue"
},
  "geometry": {"coordinates":[4.3969678879,50.8007698059],"type":"Point"}
}