{
  "type": "Feature",
  "properties": {
    "addr:full":"Westkaai 8 Antwerpen (merksem) Antwerpen 2170",
    "addr:housenumber":"8",
    "addr:postcode":"2170",
    "addr:street":"Westkaai",
    "iso:country":"BE",
    "sg:address":"Westkaai 8",
    "sg:city":"Antwerpen (merksem)",
    "sg:classifiers":[
        {
            "category":"Home & Garden",
            "subcategory":"Garden Supply",
            "type":"Retail Goods"
        }
    ],
    "sg:phone":"+32 3 647 06 07",
    "sg:postcode":"2170",
    "sg:province":"Antwerpen",
    "sg:tags":[
        "seed",
        "-"
    ],
    "wof:name":"Hollandia Nv",
    "wof:placetype":"venue"
},
  "geometry": {"coordinates":[4.4062809944,51.2307472229],"type":"Point"}
}