{
  "type": "Feature",
  "properties": {
    "addr:full":"Rue Pierre-joseph Wery 32 Charleroi Hainaut 6040",
    "addr:housenumber":"32",
    "addr:postcode":"6040",
    "addr:street":"Rue Pierre-Joseph Wery;Hainaut",
    "iso:country":"BE",
    "sg:address":"Rue Pierre-joseph Wery 32",
    "sg:city":"Charleroi",
    "sg:orig_category":"Huishoudapparaten, televisies and radio's Loodgieterij, verwarming and sanitaire installaties Schoon",
    "sg:phone":"+32 71 34 55 63",
    "sg:postcode":"6040",
    "sg:province":"Hainaut",
    "wof:name":"Sicuro",
    "wof:placetype":"venue"
},
  "geometry": {"coordinates":[4.4120130539,50.4354133606],"type":"Point"}
}