{
  "type": "Feature",
  "properties": {
    "addr:full":"Vorstlaan 125 Oudergem/auderghem Bruxelles-Capitale 1160",
    "addr:housenumber":"125",
    "addr:postcode":"1160",
    "addr:street":"Vorstlaan;/",
    "iso:country":"BE",
    "sg:address":"Vorstlaan 125",
    "sg:city":"Oudergem/auderghem",
    "sg:classifiers":[
        {
            "category":"Insurance",
            "subcategory":"Insurance Agent",
            "type":"Services"
        }
    ],
    "sg:phone":"+32 2 672 99 46",
    "sg:postcode":"1160",
    "sg:province":"Bruxelles-Capitale",
    "sg:tags":[
        "verzekeringsmakelaars",
        "expert"
    ],
    "wof:name":"Huyberechts Et Cie",
    "wof:placetype":"venue"
},
  "geometry": {"coordinates":[4.4263901711,50.8147392273],"type":"Point"}
}