{
  "type": "Feature",
  "properties": {
    "addr:full":"Regentiestraat 172 Denderleeuw Oost-Vlaanderen 9473",
    "addr:housenumber":"172",
    "addr:postcode":"9473",
    "addr:street":"Regentiestraat",
    "iso:country":"BE",
    "sg:address":"Regentiestraat 172",
    "sg:city":"Denderleeuw",
    "sg:orig_category":"Banken and kredietinstellingen",
    "sg:phone":"+32 53 66 45 67",
    "sg:postcode":"9473",
    "sg:province":"Oost-Vlaanderen",
    "wof:name":"Ippa",
    "wof:placetype":"venue"
},
  "geometry": {"coordinates":[4.0546221733,50.8989906311],"type":"Point"}
}