{
  "type": "Feature",
  "properties": {
    "iso:country":"BE",
    "sg:address":"Eynestraat 77",
    "sg:city":"Sint-truiden (zepperen)",
    "sg:orig_category":"Newspapers, magazines, periodicals - Distribution",
    "sg:phone":"+32 11 68 48 82",
    "sg:postcode":"3800",
    "sg:province":"Limburg",
    "wof:name":"Leeshoekje('t)",
    "wof:placetype":"venue"
},
  "geometry": {"coordinates":[5.2589502335,50.8288574219],"type":"Point"}
}