{
  "type": "Feature",
  "properties": {
    "addr:full":"Industrielaan 29 Hoeselt Limburg 3730",
    "addr:housenumber":"29",
    "addr:postcode":"3730",
    "addr:street":"Industrielaan",
    "iso:country":"BE",
    "sg:address":"Industrielaan 29",
    "sg:city":"Hoeselt",
    "sg:classifiers":[
        {
            "category":"Home & Garden",
            "subcategory":"Kitchen Supply",
            "type":"Retail Goods"
        }
    ],
    "sg:phone":"+32 89 41 72 65",
    "sg:postcode":"3730",
    "sg:province":"Limburg",
    "sg:tags":[
        "installation"
    ],
    "wof:name":"Morias Interieur Bvba",
    "wof:placetype":"venue"
},
  "geometry": {"coordinates":[5.4860200882,50.8581008911],"type":"Point"}
}