{
  "type": "Feature",
  "properties": {
    "addr:full":"Molenstraat 84 Brecht Antwerpen 2960",
    "addr:housenumber":"84",
    "addr:postcode":"2960",
    "addr:street":"Molenstraat",
    "iso:country":"BE",
    "sg:address":"Molenstraat 84",
    "sg:city":"Brecht",
    "sg:orig_category":"Eleveurs d'\u00e9quid\u00e9s",
    "sg:phone":"+32 3 313 69 96",
    "sg:postcode":"2960",
    "sg:province":"Antwerpen",
    "wof:name":"Molenveld",
    "wof:placetype":"venue"
},
  "geometry": {"coordinates":[4.6228790283,51.3424034119],"type":"Point"}
}