{
  "type": "Feature",
  "properties": {
    "iso:country":"BE",
    "sg:address":"Nachtegaalstraat 3",
    "sg:city":"Kruishoutem",
    "sg:orig_category":"Tuinen",
    "sg:phone":"+32 9 383 83 47",
    "sg:postcode":"9770",
    "sg:province":"Oost-Vlaanderen",
    "wof:name":"Pol Van Parijs",
    "wof:placetype":"venue"
},
  "geometry": {"coordinates":[3.551115036,50.9069252014],"type":"Point"}
}