{
  "type": "Feature",
  "properties": {
    "iso:country":"BE",
    "sg:address":"135",
    "sg:city":"Oostendsesteenweg 8000 Brugge",
    "sg:classifiers":[
        {
            "category":"Shopping",
            "subcategory":"Computers & Home Electronics",
            "type":"Retail Goods"
        }
    ],
    "sg:phone":"+32 50 45 67 89",
    "sg:postcode":"135",
    "sg:tags":[
        "electronic",
        "electrical",
        "equipment"
    ],
    "wof:name":"Waitermate Nv",
    "wof:placetype":"venue"
},
  "geometry": {"coordinates":[3.168806076,51.2375602722],"type":"Point"}
}