{
  "type": "Feature",
  "properties": {
    "iso:country":"BE",
    "sg:address":"Gistelsesteenweg 105",
    "sg:city":"Oostende",
    "sg:orig_category":"Brood, gebak and snoepgoed",
    "sg:phone":"+32 59 80 00 73",
    "sg:postcode":"8400",
    "sg:province":"West-Vlaanderen",
    "wof:name":"Bakkerij St.aubertus",
    "wof:placetype":"venue"
},
  "geometry": {"coordinates":[2.9262011051,51.2159461975],"type":"Point"}
}