{
  "type": "Feature",
  "properties": {
    "iso:country":"BE",
    "sg:address":"Notarisstraat 23",
    "sg:city":"Gent",
    "sg:classifiers":[
        {
            "category":"Professional",
            "subcategory":"Lawyer & Legal Services",
            "type":"Services"
        }
    ],
    "sg:phone":"+32 9 223 88 99",
    "sg:postcode":"9000",
    "sg:province":"Oost-Vlaanderen",
    "wof:name":"Verhaegen Philippe",
    "wof:placetype":"venue"
},
  "geometry": {"coordinates":[3.7296071053,51.0511932373],"type":"Point"}
}