{
  "type": "Feature",
  "properties": {
    "addr:full":"Rue De Montigny 37 Fernelmont Namur 5380",
    "addr:housenumber":"37",
    "addr:postcode":"5380",
    "addr:street":"Rue De Montigny",
    "iso:country":"BE",
    "sg:address":"Rue De Montigny 37",
    "sg:city":"Fernelmont",
    "sg:orig_category":"Muziekinstrumenten",
    "sg:phone":"+32 81 83 33 11",
    "sg:postcode":"5380",
    "sg:province":"Namur",
    "wof:name":"Accord\u00c9on j",
    "wof:placetype":"venue"
},
  "geometry": {"coordinates":[4.9861078262,50.5531463623],"type":"Point"}
}