{
  "type": "Feature",
  "properties": {
    "iso:country":"BE",
    "sg:address":"Boerderijstraat 24",
    "sg:city":"Dentergem (wakken)",
    "sg:classifiers":[
        {
            "category":"Farming",
            "subcategory":"Livestock Farm",
            "type":"Manufacturing & Wholesale Goods"
        }
    ],
    "sg:phone":"+32 9 388 81 17",
    "sg:postcode":"8720",
    "sg:province":"West-Vlaanderen",
    "sg:tags":[
        "buyer"
    ],
    "wof:name":"Delombaerde U",
    "wof:placetype":"venue"
},
  "geometry": {"coordinates":[3.4168820381,50.9458198547],"type":"Point"}
}