{
  "type": "Feature",
  "properties": {
    "addr:full":"Groenstraat 18 Glabbeek Vlaams-Brabant 3381",
    "addr:housenumber":"18",
    "addr:postcode":"3381",
    "addr:street":"Groenstraat",
    "iso:country":"BE",
    "sg:address":"Groenstraat 18",
    "sg:city":"Glabbeek",
    "sg:orig_category":"Fruitteelt",
    "sg:phone":"+32 16 77 13 20",
    "sg:postcode":"3381",
    "sg:province":"Vlaams-Brabant",
    "wof:name":"Jan Guelinckx",
    "wof:placetype":"venue"
},
  "geometry": {"coordinates":[4.9628582001,50.8976135254],"type":"Point"}
}