{
  "type": "Feature",
  "properties": {
    "addr:full":"Kloosterstraat 4 Gooik Vlaams-Brabant 1755",
    "addr:housenumber":"4",
    "addr:postcode":"1755",
    "addr:street":"Kloosterstraat",
    "iso:country":"BE",
    "sg:address":"Kloosterstraat 4",
    "sg:city":"Gooik",
    "sg:orig_category":"Gespecialiseerde residenti\u00eble bouw",
    "sg:phone":"+32 54 56 84 58",
    "sg:postcode":"1755",
    "sg:province":"Vlaams-Brabant",
    "wof:name":"Vandevelde T.",
    "wof:placetype":"venue"
},
  "geometry": {"coordinates":[4.0627179146,50.7737045288],"type":"Point"}
}