{
  "type": "Feature",
  "properties": {
    "iso:country":"BE",
    "sg:address":"Rue De Laeken 42",
    "sg:city":"Brussel/bruxelles",
    "sg:orig_category":"Cr\u00e9meries",
    "sg:phone":"+32 2 218 20 90",
    "sg:postcode":"1000",
    "sg:province":"Bruxelles-Capitale",
    "wof:name":"La Ferme Normande",
    "wof:placetype":"venue"
},
  "geometry": {"coordinates":[4.3511829376,50.8525161743],"type":"Point"}
}