{
  "type": "Feature",
  "properties": {
    "iso:country":"BE",
    "sg:address":"Maldingen 6",
    "sg:city":"Burg-reuland (thommen)",
    "sg:classifiers":[
        {
            "category":"Building & Trades",
            "subcategory":"Construction",
            "type":"Services"
        }
    ],
    "sg:phone":"+32 80 22 88 02",
    "sg:postcode":"4791",
    "sg:province":"Li\u00e8ge",
    "sg:tags":[
        "installation",
        "-",
        "central",
        "heating"
    ],
    "wof:name":"Houscheid Sprl",
    "wof:placetype":"venue"
},
  "geometry": {"coordinates":[6.0944099426,50.2024497986],"type":"Point"}
}