{
  "type": "Feature",
  "properties": {
    "addr:full":"Sint-antoniusbaan 350 Zoersel Antwerpen 2980",
    "addr:housenumber":"350",
    "addr:postcode":"2980",
    "iso:country":"BE",
    "sg:address":"Sint-antoniusbaan 350",
    "sg:city":"Zoersel",
    "sg:classifiers":[
        {
            "category":"Manufacturing",
            "subcategory":"Tools & Machinery",
            "type":"Manufacturing & Wholesale Goods"
        }
    ],
    "sg:phone":"+32 3 383 17 19",
    "sg:postcode":"2980",
    "sg:province":"Antwerpen",
    "sg:tags":[
        "-"
    ],
    "wof:name":"Mac Tools",
    "wof:placetype":"venue"
},
  "geometry": {"coordinates":[4.6525840759,51.267124176],"type":"Point"}
}