{
  "type": "Feature",
  "properties": {
    "iso:country":"BE",
    "sg:address":"Konijnenweg 19",
    "sg:city":"Keerbergen",
    "sg:orig_category":"Epiceries. Alimentation sp\u00e9cialis\u00e9e",
    "sg:phone":"+32 15 51 35 32",
    "sg:postcode":"3140",
    "sg:province":"Vlaams-Brabant",
    "wof:name":"Marie-paule De Bell",
    "wof:placetype":"venue"
},
  "geometry": {"coordinates":[4.6040701866,50.9972915649],"type":"Point"}
}