{
  "type": "Feature",
  "properties": {
    "addr:full":"Rue De Bastogne 230 Arlon Luxembourg 6700",
    "addr:housenumber":"230",
    "addr:postcode":"6700",
    "addr:street":"Rue De Bastogne",
    "iso:country":"BE",
    "sg:address":"Rue De Bastogne 230",
    "sg:city":"Arlon",
    "sg:orig_category":"HERSTELLING ELEKTRISCHE HUISHOUDAPPARATEN Huishoudapparaten, televisies and radio's",
    "sg:phone":"+32 63 22 02 39",
    "sg:postcode":"6700",
    "sg:province":"Luxembourg",
    "wof:name":"Erga",
    "wof:placetype":"venue"
},
  "geometry": {"coordinates":[5.8100538254,49.6943778992],"type":"Point"}
}