{
  "type": "Feature",
  "properties": {
    "addr:full":"Avenue Roi Albert 135 Andenne Namur 5300",
    "addr:housenumber":"135",
    "addr:postcode":"5300",
    "addr:street":"Avenue Roi Albert",
    "iso:country":"BE",
    "sg:address":"Avenue Roi Albert 135",
    "sg:city":"Andenne",
    "sg:orig_category":"Produits surgel\u00e9s Gr",
    "sg:phone":"+32 85 84 40 24",
    "sg:postcode":"5300",
    "sg:province":"Namur",
    "wof:name":"Covee",
    "wof:placetype":"venue"
},
  "geometry": {"coordinates":[5.1067700386,50.493598938],"type":"Point"}
}