{
  "type": "Feature",
  "properties": {
    "addr:full":"Rue Sainte-walburge 478 Li\u00e8ge 1 Li\u00e8ge 4000",
    "addr:housenumber":"478;1",
    "addr:postcode":"4000",
    "addr:street":"Rue Sainte-Walburge",
    "iso:country":"BE",
    "sg:address":"Rue Sainte-walburge 478",
    "sg:city":"Li\u00e8ge 1",
    "sg:classifiers":[
        {
            "category":"Communications",
            "subcategory":"Television Station",
            "type":"Services"
        }
    ],
    "sg:phone":"+32 4 225 96 80",
    "sg:postcode":"4000",
    "sg:province":"Li\u00e8ge",
    "sg:tags":[
        "antenna"
    ],
    "wof:name":"Cashtronic",
    "wof:placetype":"venue"
},
  "geometry": {"coordinates":[5.5621600151,50.6637306213],"type":"Point"}
}