{
  "type": "Feature",
  "properties": {
    "iso:country":"BE",
    "sg:address":"Rue De La Converserie 1",
    "sg:city":"Saint-hubert",
    "sg:classifiers":[
        {
            "category":"Education",
            "subcategory":"School",
            "type":"Public Place"
        }
    ],
    "sg:phone":"+32 61 61 22 44",
    "sg:postcode":"6870",
    "sg:province":"Luxembourg",
    "sg:tags":[
        "secondary"
    ],
    "wof:name":"Acad\u00e9mie De Musique",
    "wof:placetype":"venue"
},
  "geometry": {"coordinates":[5.3761768341,50.0281143188],"type":"Point"}
}