{
  "type": "Feature",
  "properties": {
    "addr:full":"Rue Chanoine Scarmure 58 Soignies Hainaut 7060",
    "addr:housenumber":"58",
    "addr:postcode":"7060",
    "addr:street":"Rue Chanoine Scarmure",
    "iso:country":"BE",
    "sg:address":"Rue Chanoine Scarmure 58",
    "sg:city":"Soignies",
    "sg:classifiers":[
        {
            "category":"Health Services",
            "subcategory":"Health Practitioner",
            "type":"Services"
        }
    ],
    "sg:phone":"+32 67 33 99 03",
    "sg:postcode":"7060",
    "sg:province":"Hainaut",
    "sg:tags":[
        "psychologist"
    ],
    "wof:name":"Debongnie F",
    "wof:placetype":"venue"
},
  "geometry": {"coordinates":[4.0741209984,50.5800628662],"type":"Point"}
}