{
  "type": "Feature",
  "properties": {
    "addr:full":"Rue De L\u00b4eglise 57 Seraing Li\u00e8ge 4100",
    "addr:housenumber":"57",
    "addr:postcode":"4100",
    "addr:street":"Rue De L\u00b4Eglise",
    "iso:country":"BE",
    "sg:address":"Rue De L\u00b4eglise 57",
    "sg:city":"Seraing",
    "sg:classifiers":[
        {
            "category":"Autos & Motor Vehicles",
            "subcategory":"Fuel & Gas Station",
            "type":"Retail Goods"
        }
    ],
    "sg:phone":"+32 4 338 54 04",
    "sg:postcode":"4100",
    "sg:province":"Li\u00e8ge",
    "sg:tags":[
        "stations-service",
        "carburants"
    ],
    "wof:name":"Texaco",
    "wof:placetype":"venue"
},
  "geometry": {"coordinates":[5.5135030746,50.6105766296],"type":"Point"}
}