{
  "type": "Feature",
  "properties": {
    "addr:full":"Dorpsstraat 93 Lochristi Oost-Vlaanderen 9080",
    "addr:housenumber":"93",
    "addr:postcode":"9080",
    "addr:street":"Dorpsstraat",
    "iso:country":"BE",
    "sg:address":"Dorpsstraat 93",
    "sg:city":"Lochristi",
    "sg:classifiers":[
        {
            "category":"Personal",
            "subcategory":"Beauty Salon",
            "type":"Services"
        }
    ],
    "sg:phone":"+32 9 326 03 01",
    "sg:postcode":"9080",
    "sg:province":"Oost-Vlaanderen",
    "sg:tags":[
        "lady",
        "-",
        "hairdressing"
    ],
    "wof:name":"Haarstudio De Nieuwe Schaar",
    "wof:placetype":"venue"
},
  "geometry": {"coordinates":[3.834995985,51.1027565002],"type":"Point"}
}