{
  "type": "Feature",
  "properties": {
    "addr:full":"Cantecroylaan 32 Mortsel Antwerpen 2640",
    "addr:housenumber":"32",
    "addr:postcode":"2640",
    "addr:street":"Cantecroylaan",
    "iso:country":"BE",
    "sg:address":"Cantecroylaan 32",
    "sg:city":"Mortsel",
    "sg:classifiers":[
        {
            "category":"Autos & Motor Vehicles",
            "subcategory":"Automobile Sales",
            "type":"Retail Goods"
        }
    ],
    "sg:phone":"+32 3 440 80 70",
    "sg:postcode":"2640",
    "sg:province":"Antwerpen",
    "sg:tags":[
        "motorhomes",
        "accessory"
    ],
    "wof:name":"Freeman Nv",
    "wof:placetype":"venue"
},
  "geometry": {"coordinates":[4.4625511169,51.1760787964],"type":"Point"}
}