{
  "type": "Feature",
  "properties": {
    "iso:country":"BE",
    "sg:address":"Demosthenesstraat 203",
    "sg:city":"Anderlecht/anderlecht",
    "sg:orig_category":"Dierenartsen",
    "sg:phone":"+32 2 523 57 86",
    "sg:postcode":"1070",
    "sg:province":"Bruxelles-Capitale",
    "wof:name":"Philippe De Pauw",
    "wof:placetype":"venue"
},
  "geometry": {"coordinates":[4.3054270744,50.8404464722],"type":"Point"}
}