{
  "type": "Feature",
  "properties": {
    "iso:country":"BE",
    "sg:address":"Villalaan 12",
    "sg:city":"Halle",
    "sg:classifiers":[
        {
            "category":"Professional",
            "subcategory":"Computer Services",
            "type":"Services"
        }
    ],
    "sg:phone":"+32 2 305 37 18",
    "sg:postcode":"1500",
    "sg:province":"Vlaams-Brabant",
    "sg:tags":[
        "webdesign",
        "-",
        "internet"
    ],
    "wof:name":"Publish & Print",
    "wof:placetype":"venue"
},
  "geometry": {"coordinates":[4.2442097664,50.7320594788],"type":"Point"}
}