{
  "type": "Feature",
  "properties": {
    "addr:full":"Chemin Des Meuniers 16 Ramillies Brabant Wallon 1367",
    "addr:housenumber":"16",
    "addr:postcode":"1367",
    "addr:street":"Chemin Des Meuniers",
    "iso:country":"BE",
    "sg:address":"Chemin Des Meuniers 16",
    "sg:city":"Ramillies",
    "sg:orig_category":"Boekhouders",
    "sg:phone":"+32 81 87 71 87",
    "sg:postcode":"1367",
    "sg:province":"Brabant Wallon",
    "wof:name":"Marcel Willems",
    "wof:placetype":"venue"
},
  "geometry": {"coordinates":[4.9189448357,50.674533844],"type":"Point"}
}