{
  "type": "Feature",
  "properties": {
    "addr:full":"Rue Locquenghien 45 Brussel/bruxelles Bruxelles-Capitale 1000",
    "addr:housenumber":"45",
    "addr:postcode":"1000",
    "addr:street":"Rue Locquenghien;/",
    "iso:country":"BE",
    "sg:address":"Rue Locquenghien 45",
    "sg:city":"Brussel/bruxelles",
    "sg:orig_category":"Studios photographiques",
    "sg:phone":"+32 2 217 03 88",
    "sg:postcode":"1000",
    "sg:province":"Bruxelles-Capitale",
    "wof:name":"Marie-jose Burki",
    "wof:placetype":"venue"
},
  "geometry": {"coordinates":[4.3435821533,50.8541183472],"type":"Point"}
}