{
  "type": "Feature",
  "properties": {
    "iso:country":"BE",
    "sg:address":"Basiliekstraat 106",
    "sg:city":"Halle",
    "sg:orig_category":"Jeux de hasard",
    "sg:phone":"+32 2 360 17 74",
    "sg:postcode":"1500",
    "sg:province":"Vlaams-Brabant",
    "wof:name":"Ladbroke",
    "wof:placetype":"venue"
},
  "geometry": {"coordinates":[4.2363128662,50.7333106995],"type":"Point"}
}