{
  "type": "Feature",
  "properties": {
    "iso:country":"BE",
    "sg:address":"Martelarenlaan 19",
    "sg:city":"Gent",
    "sg:classifiers":[
        {
            "category":"Fast Food",
            "type":"Food & Drink"
        }
    ],
    "sg:phone":"+32 9 234 14 67",
    "sg:postcode":"9000",
    "sg:province":"Oost-Vlaanderen",
    "sg:tags":[
        "meeneem",
        "restaurant"
    ],
    "wof:name":"Mcdonald's",
    "wof:placetype":"venue"
},
  "geometry": {"coordinates":[3.7110629082,51.0467834473],"type":"Point"}
}