{
  "type": "Feature",
  "properties": {
    "addr:full":"Hector Van Wittenberghestraat 70 Gent Oost-Vlaanderen 9000",
    "addr:housenumber":"70",
    "addr:postcode":"9000",
    "addr:street":"Hector Van Wittenberghestraat;Oost-Vlaanderen",
    "iso:country":"BE",
    "sg:address":"Hector Van Wittenberghestraat 70",
    "sg:city":"Gent",
    "sg:classifiers":[
        {
            "category":"Wholesale",
            "subcategory":"Medical Equipment & Supplies",
            "type":"Manufacturing & Wholesale Goods"
        }
    ],
    "sg:phone":"+32 485 57 60 78",
    "sg:postcode":"9000",
    "sg:province":"Oost-Vlaanderen",
    "sg:tags":[
        "massage"
    ],
    "wof:name":"Chimate",
    "wof:placetype":"venue"
},
  "geometry": {"coordinates":[3.7133340836,51.0586891174],"type":"Point"}
}