{
  "type": "Feature",
  "properties": {
    "iso:country":"BE",
    "sg:address":"Hamveer 1",
    "sg:city":"Hamme",
    "sg:orig_category":"Bouwmaterialen Gh",
    "sg:phone":"+32 52 47 25 40",
    "sg:postcode":"9220",
    "sg:province":"Oost-Vlaanderen",
    "wof:name":"Boel",
    "wof:placetype":"venue"
},
  "geometry": {"coordinates":[4.1415200233,51.1001815796],"type":"Point"}
}