{
  "type": "Feature",
  "properties": {
    "addr:full":"Rue Pouplin 27 Li\u00e8ge 1 Li\u00e8ge 4000",
    "addr:housenumber":"27;1",
    "addr:postcode":"4000",
    "addr:street":"Rue Pouplin",
    "iso:country":"BE",
    "sg:address":"Rue Pouplin 27",
    "sg:city":"Li\u00e8ge 1",
    "sg:classifiers":[
        {
            "category":"Education",
            "subcategory":"University",
            "type":"Public Place"
        }
    ],
    "sg:phone":"+32 4 222 02 62",
    "sg:postcode":"4000",
    "sg:province":"Li\u00e8ge",
    "sg:tags":[
        "higher"
    ],
    "wof:name":"Institut De Travaux Publics",
    "wof:placetype":"venue"
},
  "geometry": {"coordinates":[5.5613250732,50.6394538879],"type":"Point"}
}