{
  "type": "Feature",
  "properties": {
    "addr:full":"Rue Du Grand Bru 27 Sprimont Li\u00e8ge 4140",
    "addr:housenumber":"27",
    "addr:postcode":"4140",
    "addr:street":"Rue Du Grand Bru",
    "iso:country":"BE",
    "sg:address":"Rue Du Grand Bru 27",
    "sg:city":"Sprimont",
    "sg:classifiers":[
        {
            "category":"Professional",
            "type":"Services"
        }
    ],
    "sg:phone":"+32 4 382 35 60",
    "sg:postcode":"4140",
    "sg:province":"Li\u00e8ge",
    "sg:tags":[
        "organisation",
        "de",
        "restaurants",
        "f\u00cates",
        "catering"
    ],
    "wof:name":"La Maison Des Saveurs",
    "wof:placetype":"venue"
},
  "geometry": {"coordinates":[5.6571211815,50.5227432251],"type":"Point"}
}