{
  "type": "Feature",
  "properties": {
    "iso:country":"BE",
    "sg:address":"149 Rue Colonel Bourg",
    "sg:city":"Brussels",
    "sg:classifiers":[
        {
            "category":"Industrial Area",
            "type":"Public Place"
        }
    ],
    "sg:phone":"+32 3 443 19 11",
    "sg:postcode":"1140",
    "sg:province":"Bruxelles-Capitale",
    "sg:tags":[
        "large",
        "private"
    ],
    "wof:name":"Punch International Nv",
    "wof:placetype":"venue"
},
  "geometry": {"coordinates":[4.5343470573,51.1530952454],"type":"Point"}
}