{
  "type": "Feature",
  "properties": {
    "addr:full":"Rue De Plainevaux 141 Seraing Li\u00e8ge 4100",
    "addr:housenumber":"141",
    "addr:postcode":"4100",
    "addr:street":"Rue De Plainevaux",
    "iso:country":"BE",
    "sg:address":"Rue De Plainevaux 141",
    "sg:city":"Seraing",
    "sg:orig_category":"Journaux. Tabac. Fournitures de bureau. Librairies",
    "sg:phone":"+32 4 338 38 29",
    "sg:postcode":"4100",
    "sg:province":"Li\u00e8ge",
    "wof:name":"Maison Neven-weymiens",
    "wof:placetype":"venue"
},
  "geometry": {"coordinates":[5.5069699287,50.5829086304],"type":"Point"}
}