{
  "type": "Feature",
  "properties": {
    "iso:country":"BE",
    "sg:address":"Rijkmakerlaan 7",
    "sg:city":"Essen",
    "sg:classifiers":[
        {
            "category":"Retail",
            "subcategory":"Car Wash",
            "type":"Services"
        }
    ],
    "sg:phone":"+32 3 272 22 20",
    "sg:postcode":"2910",
    "sg:province":"Antwerpen",
    "sg:tags":[
        "automobile",
        "-",
        "washing",
        "truck",
        "equipment"
    ],
    "wof:name":"Jack Carclean",
    "wof:placetype":"venue"
},
  "geometry": {"coordinates":[4.4988942146,51.4453125],"type":"Point"}
}