{
  "type": "Feature",
  "properties": {
    "addr:full":"Chauss\u00e9e De Tervuren 68 Waterloo Brabant Wallon 1410",
    "addr:housenumber":"68",
    "addr:postcode":"1410",
    "addr:street":"Chausse\u0301E De Tervuren",
    "iso:country":"BE",
    "sg:address":"Chauss\u00e9e De Tervuren 68",
    "sg:city":"Waterloo",
    "sg:classifiers":[
        {
            "category":"Building & Trades",
            "subcategory":"Pest Control",
            "type":"Services"
        }
    ],
    "sg:phone":"+32 2 353 12 89",
    "sg:postcode":"1410",
    "sg:province":"Brabant Wallon",
    "sg:tags":[
        "painting",
        "contractor"
    ],
    "wof:name":"Usuwiel F",
    "wof:placetype":"venue"
},
  "geometry": {"coordinates":[4.4038648605,50.7036819458],"type":"Point"}
}