{
  "type": "Feature",
  "properties": {
    "addr:full":"Sainte-marie 25a Libramont-chevigny Luxembourg 6800",
    "addr:housenumber":"25a",
    "addr:postcode":"6800",
    "addr:street":"Sainte-Marie",
    "iso:country":"BE",
    "sg:address":"Sainte-marie 25a",
    "sg:city":"Libramont-chevigny",
    "sg:orig_category":"V\u00e9hicules automobiles",
    "sg:phone":"+32 61 22 48 40",
    "sg:postcode":"6800",
    "sg:province":"Luxembourg",
    "wof:name":"Garage Pol Louis",
    "wof:placetype":"venue"
},
  "geometry": {"coordinates":[5.4573698044,49.9233283997],"type":"Point"}
}