{
  "type": "Feature",
  "properties": {
    "addr:full":"Bijvaerdeweg 12 Opglabbeek Limburg 3660",
    "addr:housenumber":"12",
    "addr:postcode":"3660",
    "addr:street":"Bijvaerdeweg",
    "iso:country":"BE",
    "sg:address":"Bijvaerdeweg 12",
    "sg:city":"Opglabbeek",
    "sg:orig_category":"Woningbouw",
    "sg:phone":"+32 89 85 23 70",
    "sg:postcode":"3660",
    "sg:province":"Limburg",
    "wof:name":"Gebroeders Maes",
    "wof:placetype":"venue"
},
  "geometry": {"coordinates":[5.5861377716,51.0326004028],"type":"Point"}
}