{
  "type": "Feature",
  "properties": {
    "addr:full":"Louis Thysstraat 52 Sint-pieters-woluwe/woluwe-saint-pierre Bruxelles-Capitale 1150",
    "addr:housenumber":"52",
    "addr:postcode":"1150",
    "addr:street":"Louis Thysstraat;/",
    "iso:country":"BE",
    "sg:address":"Louis Thysstraat 52",
    "sg:city":"Sint-pieters-woluwe/woluwe-saint-pierre",
    "sg:orig_category":"Advocaten and juridische adviseurs",
    "sg:phone":"+32 2 762 85 29",
    "sg:postcode":"1150",
    "sg:province":"Bruxelles-Capitale",
    "wof:name":"N. Verheyden",
    "wof:placetype":"venue"
},
  "geometry": {"coordinates":[4.4334321022,50.837600708],"type":"Point"}
}