{
  "type": "Feature",
  "properties": {
    "addr:full":"Visesteenweg 2 Riemst Limburg 3770",
    "addr:housenumber":"2",
    "addr:postcode":"3770",
    "addr:street":"Visesteenweg",
    "iso:country":"BE",
    "sg:address":"Visesteenweg 2",
    "sg:city":"Riemst",
    "sg:orig_category":"Verplichte sociale verzekeringen",
    "sg:phone":"+32 12 45 25 05",
    "sg:postcode":"3770",
    "sg:province":"Limburg",
    "wof:name":"Christelijke Mutualiteit",
    "wof:placetype":"venue"
},
  "geometry": {"coordinates":[5.5959200859,50.8112182617],"type":"Point"}
}