{
  "type": "Feature",
  "properties": {
    "addr:full":"Rue De Libois 137 Ohey Namur 5350",
    "addr:housenumber":"137",
    "addr:postcode":"5350",
    "addr:street":"Rue De Libois",
    "iso:country":"BE",
    "sg:address":"Rue De Libois 137",
    "sg:city":"Ohey",
    "sg:orig_category":"Poissonniers and \u00e9caillers",
    "sg:phone":"+32 85 61 20 16",
    "sg:postcode":"5350",
    "sg:province":"Namur",
    "wof:name":"Philippe Gerard",
    "wof:placetype":"venue"
},
  "geometry": {"coordinates":[5.1258101463,50.4296760559],"type":"Point"}
}