{
  "type": "Feature",
  "properties": {
    "iso:country":"BE",
    "sg:address":"Renier Sniedersstraat 23",
    "sg:city":"Turnhout",
    "sg:classifiers":[
        {
            "category":"Health Services",
            "subcategory":"Dentist",
            "type":"Services"
        }
    ],
    "sg:phone":"+32 14 42 92 09",
    "sg:postcode":"2300",
    "sg:province":"Antwerpen",
    "wof:name":"Kerstiens H",
    "wof:placetype":"venue"
},
  "geometry": {"coordinates":[4.9419388771,51.3230857849],"type":"Point"}
}