{
  "type": "Feature",
  "properties": {
    "addr:full":"Grande Rue Au Bois 57 Schaarbeek/schaerbeek Bruxelles-Capitale 1030",
    "addr:housenumber":"57",
    "addr:postcode":"1030",
    "addr:street":"Grande Rue Au Bois",
    "iso:country":"BE",
    "sg:address":"Grande Rue Au Bois 57",
    "sg:city":"Schaarbeek/schaerbeek",
    "sg:orig_category":"M\u00e9decins and sp\u00e9cialistes",
    "sg:phone":"+32 2 242 57 54",
    "sg:postcode":"1030",
    "sg:province":"Bruxelles-Capitale",
    "wof:name":"Consultations Nourrissons",
    "wof:placetype":"venue"
},
  "geometry": {"coordinates":[4.3855938911,50.856174469],"type":"Point"}
}