{
  "type": "Feature",
  "properties": {
    "addr:full":"Kasteleinsstraat 32 Ixelles Bruxelles-Capitale 1050",
    "addr:housenumber":"32",
    "addr:postcode":"1050",
    "addr:street":"Kasteleinsstraat",
    "iso:country":"BE",
    "sg:address":"Kasteleinsstraat 32",
    "sg:city":"Ixelles",
    "sg:orig_category":"Diverse bedrijfsbeheeradviesbureaus Werk and personeelsselectie",
    "sg:phone":"+32 2 627 19 03",
    "sg:postcode":"1050",
    "sg:province":"Bruxelles-Capitale",
    "wof:name":"Lison Michele",
    "wof:placetype":"venue"
},
  "geometry": {"coordinates":[4.3603777885,50.8242454529],"type":"Point"}
}