{
  "type": "Feature",
  "properties": {
    "addr:full":"Chauss\u00c9e De Namur 64 Nivelles Brabant Wallon 1400",
    "addr:housenumber":"64",
    "addr:postcode":"1400",
    "addr:street":"Chausse\u0301E De Namur",
    "iso:country":"BE",
    "sg:address":"Chauss\u00c9e De Namur 64",
    "sg:city":"Nivelles",
    "sg:orig_category":"Bouwwerktuigen Gh Diverse machines voor de nijverheid Gh Verhuur bouwmachines",
    "sg:phone":"+32 67 21 71 21",
    "sg:postcode":"1400",
    "sg:province":"Brabant Wallon",
    "wof:name":"Parmentier E.f.",
    "wof:placetype":"venue"
},
  "geometry": {"coordinates":[4.3647999763,50.5953292847],"type":"Point"}
}