{
  "type": "Feature",
  "properties": {
    "addr:full":"Chemin Goffin 5a Beauvechain (tourinnes-la-grosse) Brabant Wallon 1320",
    "addr:housenumber":"5a",
    "addr:postcode":"1320",
    "addr:street":"Chemin Goffin;Wallon",
    "iso:country":"BE",
    "sg:address":"Chemin Goffin 5a",
    "sg:city":"Beauvechain (tourinnes-la-grosse)",
    "sg:classifiers":[
        {
            "category":"Insurance",
            "subcategory":"Insurance Agent",
            "type":"Services"
        }
    ],
    "sg:phone":"+32 10 86 66 73",
    "sg:postcode":"1320",
    "sg:province":"Brabant Wallon",
    "sg:tags":[
        "broker"
    ],
    "wof:name":"Perspective Gestion & Promotion Sprl",
    "wof:placetype":"venue"
},
  "geometry": {"coordinates":[4.7535648346,50.7765235901],"type":"Point"}
}