{
  "type": "Feature",
  "properties": {
    "iso:country":"BE",
    "sg:address":"Rue Madame 1",
    "sg:city":"Beaumont",
    "sg:classifiers":[
        {
            "category":"Cafe",
            "type":"Food & Drink"
        }
    ],
    "sg:phone":"+32 71 58 71 58",
    "sg:postcode":"6500",
    "sg:province":"Hainaut",
    "sg:tags":[
        "caf\u00e9s"
    ],
    "wof:name":"Le Petit Marche - Tordeur",
    "wof:placetype":"venue"
},
  "geometry": {"coordinates":[4.2368459702,50.2367744446],"type":"Point"}
}