{
  "type": "Feature",
  "properties": {
    "iso:country":"BE",
    "sg:address":"Blokstraat 2",
    "sg:city":"Sint-gillis-waas",
    "sg:orig_category":"Maisons de repos and r\u00e9sidences",
    "sg:phone":"+32 3 707 01 56",
    "sg:postcode":"9170",
    "sg:province":"Oost-Vlaanderen",
    "wof:name":"Rusthuis De Kroon",
    "wof:placetype":"venue"
},
  "geometry": {"coordinates":[4.1242399216,51.2225265503],"type":"Point"}
}