{
  "type": "Feature",
  "properties": {
    "iso:country":"BE",
    "sg:address":"Rue De Caraute 101",
    "sg:city":"Waterloo",
    "sg:orig_category":"Alternatieve geneeskunde",
    "sg:phone":"+32 2 353 25 13",
    "sg:postcode":"1410",
    "sg:province":"Brabant Wallon",
    "wof:name":"Ch. Albert",
    "wof:placetype":"venue"
},
  "geometry": {"coordinates":[4.363448143,50.7132110596],"type":"Point"}
}