{
  "type": "Feature",
  "properties": {
    "addr:full":"Avenue De L'araucaria 57 Bruxelles Bruxelles-Capitale 1020",
    "addr:housenumber":"57",
    "addr:postcode":"1020",
    "addr:street":"Avenue De L'Araucaria",
    "iso:country":"BE",
    "sg:address":"Avenue De L'araucaria 57",
    "sg:city":"Bruxelles",
    "sg:classifiers":[
        {
            "category":"Retail",
            "subcategory":"Laundry & Dry Cleaning",
            "type":"Services"
        }
    ],
    "sg:phone":"+32 2 268 44 03",
    "sg:postcode":"1020",
    "sg:province":"Bruxelles-Capitale",
    "sg:tags":[
        "self",
        "-"
    ],
    "wof:name":"Self Wash",
    "wof:placetype":"venue"
},
  "geometry": {"coordinates":[4.363694191,50.8954658508],"type":"Point"}
}