{
  "type": "Feature",
  "properties": {
    "iso:country":"BE",
    "sg:address":"Avenue G\u00c9n\u00c9ral De Gaulle 91b Bte 20",
    "sg:city":"Mons",
    "sg:orig_category":"Rev\u00eatements de sols and murs. Rev\u00eatements pour sols and murs. Peinture",
    "sg:phone":"+32 65 31 69 12",
    "sg:postcode":"7000",
    "sg:province":"Hainaut",
    "wof:name":"Acr Martin D\u00c9co",
    "wof:placetype":"venue"
},
  "geometry": {"coordinates":[3.9471540451,50.4430351257],"type":"Point"}
}