{
  "type": "Feature",
  "properties": {
    "iso:country":"BE",
    "sg:address":"Rue Des P\u00eacheries 81",
    "sg:city":"Bruxelles",
    "sg:classifiers":[
        {
            "category":"Autos & Motor Vehicles",
            "subcategory":"Automobile Sales",
            "type":"Retail Goods"
        }
    ],
    "sg:phone":"+32 2 734 97 90",
    "sg:postcode":"1170",
    "sg:province":"Bruxelles-Capitale",
    "sg:tags":[
        "equipment",
        "motor-cars",
        "transport"
    ],
    "wof:name":"Cartrust Sprl",
    "wof:placetype":"venue"
},
  "geometry": {"coordinates":[4.4098467827,50.8124504089],"type":"Point"}
}