{
  "type": "Feature",
  "properties": {
    "addr:full":"Route D'yvoir 82 Ciney Namur 5590",
    "addr:housenumber":"82",
    "addr:postcode":"5590",
    "addr:street":"Route D'Yvoir",
    "iso:country":"BE",
    "sg:address":"Route D'yvoir 82",
    "sg:city":"Ciney",
    "sg:orig_category":"Charpentes and couvertures",
    "sg:phone":"+32 83 21 23 47",
    "sg:postcode":"5590",
    "sg:province":"Namur",
    "wof:name":"F G F Toitures",
    "wof:placetype":"venue"
},
  "geometry": {"coordinates":[5.1022500992,50.2970809937],"type":"Point"}
}