{
  "type": "Feature",
  "properties": {
    "addr:full":"Heuvenstraat 26 Zonhoven Limburg 3520",
    "addr:housenumber":"26",
    "addr:postcode":"3520",
    "addr:street":"Heuvenstraat",
    "iso:country":"BE",
    "sg:address":"Heuvenstraat 26",
    "sg:city":"Zonhoven",
    "sg:classifiers":[
        {
            "category":"Food & Beverages",
            "subcategory":"Cheese",
            "type":"Retail Goods"
        }
    ],
    "sg:phone":"+32 11 81 41 36",
    "sg:postcode":"3520",
    "sg:province":"Limburg",
    "sg:tags":[
        "-"
    ],
    "wof:name":"Kruidentuintje ('t)",
    "wof:placetype":"venue"
},
  "geometry": {"coordinates":[5.3671917915,50.9896011353],"type":"Point"}
}