{
  "type": "Feature",
  "properties": {
    "iso:country":"BE",
    "sg:address":"Avenue Albert I 183",
    "sg:city":"Rixensart (genval)",
    "sg:classifiers":[
        {
            "category":"Organizations",
            "subcategory":"Professional Association",
            "type":"Services"
        }
    ],
    "sg:phone":"+32 2 652 26 92",
    "sg:postcode":"1332",
    "sg:province":"Brabant Wallon",
    "sg:tags":[
        "trade-union",
        "federation"
    ],
    "wof:name":"Syndicaat Der Zelfstandigen & Kmo",
    "wof:placetype":"venue"
},
  "geometry": {"coordinates":[4.5042161942,50.7279052734],"type":"Point"}
}