{
  "type": "Feature",
  "properties": {
    "addr:full":"Watersportlaan 15 Zandhoven Antwerpen 2240",
    "addr:housenumber":"15",
    "addr:postcode":"2240",
    "addr:street":"Watersportlaan",
    "iso:country":"BE",
    "sg:address":"Watersportlaan 15",
    "sg:city":"Zandhoven",
    "sg:orig_category":"Eleveurs de bovins",
    "sg:phone":"+32 3 485 57 55",
    "sg:postcode":"2240",
    "sg:province":"Antwerpen",
    "wof:name":"Frans De Groof",
    "wof:placetype":"venue"
},
  "geometry": {"coordinates":[4.6572709084,51.1905937195],"type":"Point"}
}