{
  "type": "Feature",
  "properties": {
    "iso:country":"BE",
    "sg:address":"Potaardestraat 115",
    "sg:city":"Lebbeke",
    "sg:orig_category":"Sportclubs",
    "sg:phone":"+32 52 41 00 20",
    "sg:postcode":"9280",
    "sg:province":"Oost-Vlaanderen",
    "wof:name":"De Veldduif",
    "wof:placetype":"venue"
},
  "geometry": {"coordinates":[4.1613841057,51.0048141479],"type":"Point"}
}