{
  "type": "Feature",
  "properties": {
    "addr:full":"Veldkantstraat 150 Grimbergen Vlaams-Brabant 1850",
    "addr:housenumber":"150",
    "addr:postcode":"1850",
    "addr:street":"Veldkantstraat",
    "iso:country":"BE",
    "sg:address":"Veldkantstraat 150",
    "sg:city":"Grimbergen",
    "sg:classifiers":[
        {
            "category":"Arena",
            "subcategory":"Sports Club",
            "type":"Entertainment"
        }
    ],
    "sg:phone":"+32 2 269 73 07",
    "sg:postcode":"1850",
    "sg:province":"Vlaams-Brabant",
    "sg:tags":[
        "terrain",
        "hors",
        "de",
        "installation",
        "sportifs"
    ],
    "wof:name":"V.k. Veldkanteva's",
    "wof:placetype":"venue"
},
  "geometry": {"coordinates":[4.3854169846,50.9365730286],"type":"Point"}
}