{
  "type": "Feature",
  "properties": {
    "iso:country":"BE",
    "sg:address":"Rue Des Hott\u00c9es 6",
    "sg:city":"Virton",
    "sg:orig_category":"Instellingen voor mindervalide volwassenen",
    "sg:phone":"+32 63 57 74 69",
    "sg:postcode":"6760",
    "sg:province":"Luxembourg",
    "wof:name":"Fourneau David - Les Iris",
    "wof:placetype":"venue"
},
  "geometry": {"coordinates":[5.5320987701,49.5654907227],"type":"Point"}
}