{
  "type": "Feature",
  "properties": {
    "addr:full":"Rue Hamoir 49 La Louvi\u00e8re Hainaut 7100",
    "addr:housenumber":"49",
    "addr:postcode":"7100",
    "addr:street":"Rue Hamoir",
    "iso:country":"BE",
    "sg:address":"Rue Hamoir 49",
    "sg:city":"La Louvi\u00e8re",
    "sg:classifiers":[
        {
            "category":"Personal",
            "subcategory":"Beauty Salon",
            "type":"Services"
        }
    ],
    "sg:phone":"+32 64 26 59 59",
    "sg:postcode":"7100",
    "sg:province":"Hainaut",
    "sg:tags":[
        "lady",
        "-",
        "hairdressing"
    ],
    "wof:name":"Hair Fashion",
    "wof:placetype":"venue"
},
  "geometry": {"coordinates":[4.1890859604,50.4749488831],"type":"Point"}
}