{
  "type": "Feature",
  "properties": {
    "addr:full":"Rue Fleming 28 Seraing Li\u00e8ge 4100",
    "addr:housenumber":"28",
    "addr:postcode":"4100",
    "addr:street":"Rue Fleming",
    "iso:country":"BE",
    "sg:address":"Rue Fleming 28",
    "sg:city":"Seraing",
    "sg:orig_category":"Paramedische behandelingen",
    "sg:phone":"+32 4 336 71 36",
    "sg:postcode":"4100",
    "sg:province":"Li\u00e8ge",
    "wof:name":"Marie Chaineux",
    "wof:placetype":"venue"
},
  "geometry": {"coordinates":[5.4937419891,50.5779571533],"type":"Point"}
}