{
  "type": "Feature",
  "properties": {
    "addr:full":"Wandelingstraat 74 Kortrijk West-Vlaanderen 8500",
    "addr:housenumber":"74",
    "addr:postcode":"8500",
    "addr:street":"Wandelingstraat",
    "iso:country":"BE",
    "sg:address":"Wandelingstraat 74",
    "sg:city":"Kortrijk",
    "sg:orig_category":"Tabac. Journaux",
    "sg:phone":"+32 56 22 11 52",
    "sg:postcode":"8500",
    "sg:province":"West-Vlaanderen",
    "wof:name":"Rigolle",
    "wof:placetype":"venue"
},
  "geometry": {"coordinates":[3.276184082,50.8263282776],"type":"Point"}
}