{
  "type": "Feature",
  "properties": {
    "addr:full":"Av. O. Van Goidtsnoven 101 Vorst/forest Bruxelles-Capitale 1190",
    "addr:housenumber":"101",
    "addr:postcode":"1190",
    "addr:street":"Av. O. Van Goidtsnoven;/ Forest",
    "iso:country":"BE",
    "sg:address":"Av. O. Van Goidtsnoven 101",
    "sg:city":"Vorst/forest",
    "sg:orig_category":"Boucheries",
    "sg:phone":"+32 2 344 10 21",
    "sg:postcode":"1190",
    "sg:province":"Bruxelles-Capitale",
    "wof:name":"Boucherie Imp\u00c9riale",
    "wof:placetype":"venue"
},
  "geometry": {"coordinates":[4.3373827934,50.8160476685],"type":"Point"}
}