{
  "type": "Feature",
  "properties": {
    "iso:country":"BE",
    "sg:address":"Guido Gezellelaan 213",
    "sg:city":"Kortrijk",
    "sg:orig_category":"Woningbouw",
    "sg:phone":"+32 56 37 02 29",
    "sg:postcode":"8501",
    "sg:province":"West-Vlaanderen",
    "wof:name":"Geert Meersschaert",
    "wof:placetype":"venue"
},
  "geometry": {"coordinates":[3.2364449501,50.8362426758],"type":"Point"}
}