{
  "type": "Feature",
  "properties": {
    "iso:country":"BE",
    "sg:address":"Ubbelstraat 170",
    "sg:city":"Heusden-zolder (zolder)",
    "sg:classifiers":[
        {
            "category":"Professional",
            "subcategory":"Management & Consulting",
            "type":"Services"
        }
    ],
    "sg:phone":"+32 11 53 87 80",
    "sg:postcode":"3550",
    "sg:province":"Limburg",
    "sg:tags":[
        "consultant",
        "agency",
        "advertising"
    ],
    "wof:name":"1 N 2 Bvba",
    "wof:placetype":"venue"
},
  "geometry": {"coordinates":[5.2724890709,51.0084533691],"type":"Point"}
}