{
  "type": "Feature",
  "properties": {
    "iso:country":"BE",
    "sg:address":"Kaai 26",
    "sg:city":"Nieuwpoort",
    "sg:orig_category":"Epiceries",
    "sg:phone":"+32 58 23 47 24",
    "sg:postcode":"8620",
    "sg:province":"West-Vlaanderen",
    "wof:name":"Valcke",
    "wof:placetype":"venue"
},
  "geometry": {"coordinates":[2.7502820492,51.133190155],"type":"Point"}
}