{
  "type": "Feature",
  "properties": {
    "addr:full":"Steenhouwersvest 15 Antwerpen Antwerpen 2000",
    "addr:housenumber":"15",
    "addr:postcode":"2000",
    "addr:street":"Steenhouwersvest",
    "iso:country":"BE",
    "sg:address":"Steenhouwersvest 15",
    "sg:city":"Antwerpen",
    "sg:classifiers":[
        {
            "category":"Home & Garden",
            "subcategory":"Home Furnishings",
            "type":"Retail Goods"
        }
    ],
    "sg:phone":"+32 3 233 95 85",
    "sg:postcode":"2000",
    "sg:province":"Antwerpen",
    "sg:tags":[
        "interior",
        "decoration"
    ],
    "wof:name":"Decoration Guild-bailleux",
    "wof:placetype":"venue"
},
  "geometry": {"coordinates":[4.397726059,51.2182273865],"type":"Point"}
}