{
  "type": "Feature",
  "properties": {
    "addr:full":"Rue Arthur Warocqu\u00e9 2 La Louvi\u00e8re Hainaut 7100",
    "addr:housenumber":"2",
    "addr:postcode":"7100",
    "addr:street":"Rue Arthur Warocque\u0301",
    "iso:country":"BE",
    "sg:address":"Rue Arthur Warocqu\u00e9 2",
    "sg:city":"La Louvi\u00e8re",
    "sg:classifiers":[
        {
            "category":"Community Center",
            "type":"Public Place"
        }
    ],
    "sg:phone":"+32 64 22 81 62",
    "sg:postcode":"7100",
    "sg:province":"Hainaut",
    "sg:tags":[
        "medical"
    ],
    "wof:name":"Centre De Gyn\u00e9cologie",
    "wof:placetype":"venue"
},
  "geometry": {"coordinates":[4.1901049614,50.4777755737],"type":"Point"}
}