{
  "type": "Feature",
  "properties": {
    "addr:full":"Hulststraat 41 Tervuren Vlaams-Brabant 3080",
    "addr:housenumber":"41",
    "addr:postcode":"3080",
    "addr:street":"Hulststraat",
    "iso:country":"BE",
    "sg:address":"Hulststraat 41",
    "sg:city":"Tervuren",
    "sg:orig_category":"Voertuigen",
    "sg:phone":"+32 2 767 20 13",
    "sg:postcode":"3080",
    "sg:province":"Vlaams-Brabant",
    "wof:name":"Garage Stenny",
    "wof:placetype":"venue"
},
  "geometry": {"coordinates":[4.5463399887,50.8076286316],"type":"Point"}
}