{
  "type": "Feature",
  "properties": {
    "iso:country":"BE",
    "sg:address":"Kortemarkstraat 154",
    "sg:city":"Torhout",
    "sg:classifiers":[
        {
            "category":"Farming",
            "subcategory":"Livestock Farm",
            "type":"Manufacturing & Wholesale Goods"
        }
    ],
    "sg:phone":"+32 50 21 22 61",
    "sg:postcode":"8820",
    "sg:province":"West-Vlaanderen",
    "sg:tags":[
        "buyer"
    ],
    "wof:name":"Tanghe A",
    "wof:placetype":"venue"
},
  "geometry": {"coordinates":[3.0885078907,51.0578918457],"type":"Point"}
}