{
  "type": "Feature",
  "properties": {
    "iso:country":"BE",
    "sg:address":"Molenstraat 1",
    "sg:city":"Maasmechelen (leut)",
    "sg:classifiers":[
        {
            "category":"Building & Trades",
            "subcategory":"Construction",
            "type":"Services"
        }
    ],
    "sg:phone":"+32 89 75 79 68",
    "sg:postcode":"3630",
    "sg:province":"Limburg",
    "sg:tags":[
        "industrial",
        "design"
    ],
    "wof:name":"Art & Design",
    "wof:placetype":"venue"
},
  "geometry": {"coordinates":[5.7290620804,51.0020484924],"type":"Point"}
}