{
  "type": "Feature",
  "properties": {
    "addr:full":"Leynseelstraat 114 Avelgem West-Vlaanderen 8580",
    "addr:housenumber":"114",
    "addr:postcode":"8580",
    "addr:street":"Leynseelstraat",
    "iso:country":"BE",
    "sg:address":"Leynseelstraat 114",
    "sg:city":"Avelgem",
    "sg:classifiers":[
        {
            "category":"Shopping",
            "type":"Retail Goods"
        }
    ],
    "sg:phone":"+32 56 64 52 01",
    "sg:postcode":"8580",
    "sg:province":"West-Vlaanderen",
    "sg:tags":[
        "product",
        "cleaning",
        "maintenance"
    ],
    "wof:name":"Denca",
    "wof:placetype":"venue"
},
  "geometry": {"coordinates":[3.428000927,50.7771453857],"type":"Point"}
}