{
  "type": "Feature",
  "properties": {
    "iso:country":"BE",
    "sg:address":"Bergstraat 41",
    "sg:city":"Waregem",
    "sg:classifiers":[
        {
            "category":"Travel",
            "subcategory":"Hotels & Motels",
            "type":"Entertainment"
        }
    ],
    "sg:phone":"+32 56 60 97 36",
    "sg:postcode":"8790",
    "sg:province":"West-Vlaanderen",
    "wof:name":"Happy Golf Hotel & Business Center",
    "wof:placetype":"venue"
},
  "geometry": {"coordinates":[3.4661910534,50.8821182251],"type":"Point"}
}