{
  "type": "Feature",
  "properties": {
    "iso:country":"BE",
    "sg:address":"Ossenberg 9",
    "sg:city":"Balen",
    "sg:orig_category":"Rundveehouders",
    "sg:phone":"+32 14 30 04 67",
    "sg:postcode":"2490",
    "sg:province":"Antwerpen",
    "wof:name":"Gerardus Mols",
    "wof:placetype":"venue"
},
  "geometry": {"coordinates":[5.1273531914,51.1512107849],"type":"Point"}
}