{
  "type": "Feature",
  "properties": {
    "addr:full":"Rue Du Longtry 62 Charleroi (mont-sur-marchienne) Hainaut 6032",
    "addr:housenumber":"62",
    "addr:postcode":"6032",
    "addr:street":"Rue Du Longtry",
    "iso:country":"BE",
    "sg:address":"Rue Du Longtry 62",
    "sg:city":"Charleroi (mont-sur-marchienne)",
    "sg:classifiers":[
        {
            "category":"Organizations",
            "subcategory":"Political Organization",
            "type":"Services"
        }
    ],
    "sg:phone":"+32 71 32 86 66",
    "sg:postcode":"6032",
    "sg:province":"Hainaut",
    "sg:tags":[
        "charitable",
        "organisation"
    ],
    "wof:name":"Emmaus Quart-monde Asbl",
    "wof:placetype":"venue"
},
  "geometry": {"coordinates":[4.4072360992,50.3730812073],"type":"Point"}
}