{
  "type": "Feature",
  "properties": {
    "iso:country":"BE",
    "sg:address":"Avenue Bat.-thomas-braun 17",
    "sg:city":"Paliseul",
    "sg:orig_category":"Woningbouw",
    "sg:phone":"+32 61 65 63 09",
    "sg:postcode":"6852",
    "sg:province":"Luxembourg",
    "wof:name":"M. Paquin",
    "wof:placetype":"venue"
},
  "geometry": {"coordinates":[5.1859130859,49.9735221863],"type":"Point"}
}