{
  "type": "Feature",
  "properties": {
    "addr:full":"Rue De Mazy 53 Gembloux Namur 5030",
    "addr:housenumber":"53",
    "addr:postcode":"5030",
    "addr:street":"Rue De Mazy;Namur",
    "iso:country":"BE",
    "sg:address":"Rue De Mazy 53",
    "sg:city":"Gembloux",
    "sg:orig_category":"Artsen and specialisten",
    "sg:phone":"+32 81 61 23 12",
    "sg:postcode":"5030",
    "sg:province":"Namur",
    "wof:name":"G. Delfosse",
    "wof:placetype":"venue"
},
  "geometry": {"coordinates":[4.6968069077,50.5544204712],"type":"Point"}
}