{
  "type": "Feature",
  "properties": {
    "iso:country":"BE",
    "sg:address":"Oude Brugsepoort 92",
    "sg:city":"Deinze",
    "sg:orig_category":"Brood, gebak and snoepgoed",
    "sg:phone":"+32 9 386 27 41",
    "sg:postcode":"9800",
    "sg:province":"Oost-Vlaanderen",
    "wof:name":"Bakkerij Colpaert",
    "wof:placetype":"venue"
},
  "geometry": {"coordinates":[3.5173261166,50.9906387329],"type":"Point"}
}