{
  "type": "Feature",
  "properties": {
    "iso:country":"BE",
    "sg:address":"Dorpsplein 6",
    "sg:city":"Zonhoven",
    "sg:orig_category":"Kapsalons",
    "sg:phone":"+32 11 81 37 30",
    "sg:postcode":"3520",
    "sg:province":"Limburg",
    "wof:name":"Coiffure Jacqueline",
    "wof:placetype":"venue"
},
  "geometry": {"coordinates":[5.3673768044,50.9943161011],"type":"Point"}
}