{
  "type": "Feature",
  "properties": {
    "addr:full":"Beertsestraat 37 Halle Vlaams-Brabant 1500",
    "addr:housenumber":"37",
    "addr:postcode":"1500",
    "addr:street":"Beertsestraat",
    "iso:country":"BE",
    "sg:address":"Beertsestraat 37",
    "sg:city":"Halle",
    "sg:classifiers":[
        {
            "category":"Insurance",
            "subcategory":"Insurance Agent",
            "type":"Services"
        }
    ],
    "sg:phone":"+32 2 360 18 58",
    "sg:postcode":"1500",
    "sg:province":"Vlaams-Brabant",
    "sg:tags":[
        "broker"
    ],
    "wof:name":"Van Cauter Marc Zakenkantoor",
    "wof:placetype":"venue"
},
  "geometry": {"coordinates":[4.2293930054,50.7322158813],"type":"Point"}
}