{
  "type": "Feature",
  "properties": {
    "addr:full":"Rue Houzeau De Lehaie 41 Sint-jans-molenbeek/molenbeek-saint-jean Bruxelles-Capitale 1080",
    "addr:housenumber":"41",
    "addr:postcode":"1080",
    "addr:street":"Rue Houzeau De Lehaie",
    "iso:country":"BE",
    "sg:address":"Rue Houzeau De Lehaie 41",
    "sg:city":"Sint-jans-molenbeek/molenbeek-saint-jean",
    "sg:orig_category":"Epiceries",
    "sg:phone":"+32 2 411 90 27",
    "sg:postcode":"1080",
    "sg:province":"Bruxelles-Capitale",
    "wof:name":"Gultas Recep",
    "wof:placetype":"venue"
},
  "geometry": {"coordinates":[4.3366007805,50.8603973389],"type":"Point"}
}