{
  "type": "Feature",
  "properties": {
    "addr:full":"Gemeenteplein 9 Meise Vlaams-Brabant 1861",
    "addr:housenumber":"9",
    "addr:postcode":"1861",
    "addr:street":"Gemeenteplein",
    "iso:country":"BE",
    "sg:address":"Gemeenteplein 9",
    "sg:city":"Meise",
    "sg:orig_category":"R\u00e9parations de chaussures and articles en cuir",
    "sg:phone":"+32 2 269 56 56",
    "sg:postcode":"1861",
    "sg:province":"Vlaams-Brabant",
    "wof:name":"Schoenmakerij Romain",
    "wof:placetype":"venue"
},
  "geometry": {"coordinates":[4.3088359833,50.9508323669],"type":"Point"}
}