{
  "type": "Feature",
  "properties": {
    "addr:full":"Centre Hospitalier Soignies Hainaut 7060",
    "addr:postcode":"7060",
    "iso:country":"BE",
    "sg:address":"Centre Hospitalier",
    "sg:city":"Soignies",
    "sg:classifiers":[
        {
            "category":"Health Services",
            "subcategory":"Doctor",
            "type":"Services"
        }
    ],
    "sg:phone":"+32 67 34 85 22",
    "sg:postcode":"7060",
    "sg:province":"Hainaut",
    "sg:tags":[
        "medicinephysicians",
        "surgeon"
    ],
    "wof:name":"Dr Annie Kruszewski",
    "wof:placetype":"venue"
},
  "geometry": {"coordinates":[4.0724000931,50.5779037476],"type":"Point"}
}