{
  "type": "Feature",
  "properties": {
    "iso:country":"BE",
    "sg:address":"Parc Artisanal De Cornemont 7",
    "sg:city":"Sprimont (louveign\u00e9)",
    "sg:classifiers":[
        {
            "category":"Building & Trades",
            "subcategory":"Landscaping Services",
            "type":"Services"
        }
    ],
    "sg:phone":"+32 4 360 92 86",
    "sg:postcode":"4141",
    "sg:province":"Li\u00e8ge",
    "sg:tags":[
        "gardening",
        "garden",
        "maintenance"
    ],
    "wof:name":"Thoumsin Jardins Sa",
    "wof:placetype":"venue"
},
  "geometry": {"coordinates":[5.7102560997,50.5312538147],"type":"Point"}
}