{
  "type": "Feature",
  "properties": {
    "iso:country":"BE",
    "sg:address":"Av. Des Quatre Saisons 27",
    "sg:city":"Waterloo",
    "sg:classifiers":[
        {
            "category":"Professional",
            "subcategory":"Accounting & Tax Preparation",
            "type":"Services"
        }
    ],
    "sg:phone":"+32 2 354 46 25",
    "sg:postcode":"1410",
    "sg:province":"Brabant Wallon",
    "sg:tags":[
        "accountant"
    ],
    "wof:name":"Julien Vanlaethem",
    "wof:placetype":"venue"
},
  "geometry": {"coordinates":[4.3923959732,50.7048873901],"type":"Point"}
}