{
  "type": "Feature",
  "properties": {
    "addr:full":"Plein 85 Kaprijke Oost-Vlaanderen 9970",
    "addr:housenumber":"85",
    "addr:postcode":"9970",
    "addr:street":"Plein",
    "iso:country":"BE",
    "sg:address":"Plein 85",
    "sg:city":"Kaprijke",
    "sg:orig_category":"Agences de presse",
    "sg:phone":"+32 9 373 57 61",
    "sg:postcode":"9970",
    "sg:province":"Oost-Vlaanderen",
    "wof:name":"K. Boute",
    "wof:placetype":"venue"
},
  "geometry": {"coordinates":[3.6209139824,51.2166862488],"type":"Point"}
}