{
  "type": "Feature",
  "properties": {
    "addr:full":"Lodewijk De Raetlaan 10 Overpelt Limburg 3900",
    "addr:housenumber":"10",
    "addr:postcode":"3900",
    "addr:street":"Lodewijk De Raetlaan",
    "iso:country":"BE",
    "sg:address":"Lodewijk De Raetlaan 10",
    "sg:city":"Overpelt",
    "sg:classifiers":[
        {
            "category":"Professional",
            "subcategory":"Management & Consulting",
            "type":"Services"
        }
    ],
    "sg:phone":"+32 11 80 88 08",
    "sg:postcode":"3900",
    "sg:province":"Limburg",
    "sg:tags":[
        "consultant",
        "agency",
        "advertising"
    ],
    "wof:name":"Big Media Group",
    "wof:placetype":"venue"
},
  "geometry": {"coordinates":[5.3762750626,51.2236976624],"type":"Point"}
}