{
  "type": "Feature",
  "properties": {
    "addr:full":"Place J. Thiry 6 Aywaille Li\u00e8ge 4920",
    "addr:housenumber":"6",
    "addr:postcode":"4920",
    "addr:street":"Place J. Thiry",
    "iso:country":"BE",
    "sg:address":"Place J. Thiry 6",
    "sg:city":"Aywaille",
    "sg:orig_category":"Baby- and kinderkleding",
    "sg:phone":"+32 4 384 59 92",
    "sg:postcode":"4920",
    "sg:province":"Li\u00e8ge",
    "wof:name":"Pierre Et Le Loup",
    "wof:placetype":"venue"
},
  "geometry": {"coordinates":[5.6753058434,50.4738006592],"type":"Point"}
}