{
  "type": "Feature",
  "properties": {
    "iso:country":"BE",
    "sg:address":"Pastorijstraat 46",
    "sg:city":"Bilzen (grote-spouwen)",
    "sg:classifiers":[
        {
            "category":"Health Services",
            "subcategory":"Health Practitioner",
            "type":"Services"
        }
    ],
    "sg:phone":"+32 12 45 16 66",
    "sg:postcode":"3740",
    "sg:province":"Limburg",
    "sg:tags":[
        "physiotherapist"
    ],
    "wof:name":"Benats Ren\u00e9-willy",
    "wof:placetype":"venue"
},
  "geometry": {"coordinates":[5.5537528992,50.8353767395],"type":"Point"}
}