{
  "type": "Feature",
  "properties": {
    "addr:full":"Beversesteenweg 568 Roeselare West-Vlaanderen 8800",
    "addr:housenumber":"568",
    "addr:postcode":"8800",
    "addr:street":"Beversesteenweg",
    "iso:country":"BE",
    "sg:address":"Beversesteenweg 568",
    "sg:city":"Roeselare",
    "sg:classifiers":[
        {
            "category":"Autos & Motor Vehicles",
            "subcategory":"Automobile Sales",
            "type":"Retail Goods"
        }
    ],
    "sg:phone":"+32 51 22 82 38",
    "sg:postcode":"8800",
    "sg:province":"West-Vlaanderen",
    "sg:tags":[
        "-",
        "truck"
    ],
    "wof:name":"Garage N Callant",
    "wof:placetype":"venue"
},
  "geometry": {"coordinates":[3.1587059498,50.9731063843],"type":"Point"}
}