{
  "type": "Feature",
  "properties": {
    "iso:country":"BE",
    "sg:address":"Bosbeek 37",
    "sg:city":"Beveren",
    "sg:orig_category":"Sportclubs",
    "sg:phone":"+32 3 775 14 63",
    "sg:postcode":"9120",
    "sg:province":"Oost-Vlaanderen",
    "wof:name":"Bbc Turuka \u00b490 Willebroek",
    "wof:placetype":"venue"
},
  "geometry": {"coordinates":[4.2381548882,51.2028160095],"type":"Point"}
}