{
  "type": "Feature",
  "properties": {
    "addr:full":"Thier Pirka 8 Villers-le-bouillet (warnant-dreye) Li\u00e8ge 4530",
    "addr:housenumber":"8",
    "addr:postcode":"4530",
    "addr:street":"Thier Pirka;Warnant-Dreye",
    "iso:country":"BE",
    "sg:address":"Thier Pirka 8",
    "sg:city":"Villers-le-bouillet (warnant-dreye)",
    "sg:classifiers":[
        {
            "category":"Utilities",
            "subcategory":"Recycling",
            "type":"Services"
        }
    ],
    "sg:phone":"+32 19 51 26 38",
    "sg:postcode":"4530",
    "sg:province":"Li\u00e8ge",
    "sg:tags":[
        "rubbish",
        "removal"
    ],
    "wof:name":"Legros J-m",
    "wof:placetype":"venue"
},
  "geometry": {"coordinates":[5.2342758179,50.5962219238],"type":"Point"}
}