{
  "type": "Feature",
  "properties": {
    "iso:country":"BE",
    "sg:address":"Chemin Des Pr\u00c9elles 0",
    "sg:city":"Mons",
    "sg:orig_category":"Sportcentra Sportclubs Sportterreinen and installaties behalve sportcentra",
    "sg:phone":"+32 65 31 23 92",
    "sg:postcode":"7000",
    "sg:province":"Hainaut",
    "wof:name":"Salle Omnisports Enseign.",
    "wof:placetype":"venue"
},
  "geometry": {"coordinates":[3.9639599323,50.4503288269],"type":"Point"}
}