{
  "type": "Feature",
  "properties": {
    "iso:country":"BE",
    "sg:address":"Blokstraat 14",
    "sg:city":"Sint-gillis-waas",
    "sg:classifiers":[
        {
            "category":"Insurance",
            "subcategory":"Life Insurance",
            "type":"Services"
        }
    ],
    "sg:phone":"+32 3 770 77 30",
    "sg:postcode":"9170",
    "sg:province":"Oost-Vlaanderen",
    "sg:tags":[
        "assurance"
    ],
    "wof:name":"Vero",
    "wof:placetype":"venue"
},
  "geometry": {"coordinates":[4.1267371178,51.2228851318],"type":"Point"}
}