{
  "type": "Feature",
  "properties": {
    "iso:country":"BE",
    "sg:address":"George Lacroixstraat 18",
    "sg:city":"Machelen",
    "sg:classifiers":[
        {
            "category":"Real Estate",
            "subcategory":"Architect",
            "type":"Services"
        }
    ],
    "sg:phone":"+32 2 251 58 34",
    "sg:postcode":"1830",
    "sg:province":"Vlaams-Brabant",
    "wof:name":"Beyls J-p",
    "wof:placetype":"venue"
},
  "geometry": {"coordinates":[4.4298419952,50.9048271179],"type":"Point"}
}