{
  "type": "Feature",
  "properties": {
    "addr:full":"Waterpasstraat 38 Sint-jans-molenbeek/molenbeek-saint-jean Bruxelles-Capitale 1080",
    "addr:housenumber":"38",
    "addr:postcode":"1080",
    "addr:street":"Waterpasstraat",
    "iso:country":"BE",
    "sg:address":"Waterpasstraat 38",
    "sg:city":"Sint-jans-molenbeek/molenbeek-saint-jean",
    "sg:classifiers":[
        {
            "category":"Cafe",
            "type":"Food & Drink"
        }
    ],
    "sg:phone":"+32 2 410 86 42",
    "sg:postcode":"1080",
    "sg:province":"Bruxelles-Capitale",
    "sg:tags":[
        "caf\u00e9s"
    ],
    "wof:name":"Le Vieux Niveau",
    "wof:placetype":"venue"
},
  "geometry": {"coordinates":[4.337916851,50.8553237915],"type":"Point"}
}