{
  "type": "Feature",
  "properties": {
    "iso:country":"BE",
    "sg:address":"Noordlaan 23",
    "sg:city":"Torhout",
    "sg:classifiers":[
        {
            "category":"Structure",
            "subcategory":"Office Building",
            "type":"Public Place"
        }
    ],
    "sg:phone":"+32 50 21 26 16",
    "sg:postcode":"8820",
    "sg:province":"West-Vlaanderen",
    "sg:tags":[
        "-",
        "type",
        "door",
        "sliding",
        "overhead"
    ],
    "wof:name":"Ve-tor Poorten Bvba",
    "wof:placetype":"venue"
},
  "geometry": {"coordinates":[3.0916979313,51.0692481995],"type":"Point"}
}