{
  "type": "Feature",
  "properties": {
    "iso:country":"BE",
    "sg:address":"Lotissement Du Gros Termpe 3",
    "sg:city":"Tintigny",
    "sg:classifiers":[
        {
            "category":"Personal",
            "subcategory":"Beauty Salon",
            "type":"Services"
        }
    ],
    "sg:phone":"+32 63 44 45 87",
    "sg:postcode":"6730",
    "sg:province":"Luxembourg",
    "sg:tags":[
        "de",
        "coiffure"
    ],
    "wof:name":"Carlo Zanini",
    "wof:placetype":"venue"
},
  "geometry": {"coordinates":[5.5174751282,49.6808395386],"type":"Point"}
}