{
  "type": "Feature",
  "properties": {
    "iso:country":"BE",
    "sg:address":"Boechoutlaan 55",
    "sg:city":"Grimbergen (strombeek-bever)",
    "sg:classifiers":[
        {
            "category":"Wholesale",
            "subcategory":"Medical Equipment & Supplies",
            "type":"Manufacturing & Wholesale Goods"
        }
    ],
    "sg:phone":"+32 70 22 44 70",
    "sg:postcode":"1853",
    "sg:province":"Vlaams-Brabant",
    "sg:tags":[
        "instrument",
        "apparatus"
    ],
    "wof:name":"Sofamor",
    "wof:placetype":"venue"
},
  "geometry": {"coordinates":[4.3446741104,50.9036521912],"type":"Point"}
}