{
  "type": "Feature",
  "properties": {
    "addr:full":"Rue C\u00c9sar De Paepe 5 Soumagne Li\u00e8ge 4630",
    "addr:housenumber":"5",
    "addr:postcode":"4630",
    "addr:street":"Rue Ce\u0301Sar De Paepe",
    "iso:country":"BE",
    "sg:address":"Rue C\u00c9sar De Paepe 5",
    "sg:city":"Soumagne",
    "sg:orig_category":"Equipement photographique. Studios photographiques",
    "sg:phone":"+32 4 377 09 96",
    "sg:postcode":"4630",
    "sg:province":"Li\u00e8ge",
    "wof:name":"Studio Prometh\u00c9e",
    "wof:placetype":"venue"
},
  "geometry": {"coordinates":[5.735517025,50.6313934326],"type":"Point"}
}