{
  "type": "Feature",
  "properties": {
    "iso:country":"BE",
    "sg:address":"Veurnesteenweg 2",
    "sg:city":"Lo-reninge",
    "sg:orig_category":"Eleveurs and marchands de porcs",
    "sg:phone":"+32 58 28 87 14",
    "sg:postcode":"8647",
    "sg:province":"West-Vlaanderen",
    "wof:name":"Freddy Vermeersch",
    "wof:placetype":"venue"
},
  "geometry": {"coordinates":[2.7186539173,50.9515609741],"type":"Point"}
}