{
  "type": "Feature",
  "properties": {
    "iso:country":"BE",
    "sg:address":"Solhofdreef 8",
    "sg:city":"Aartselaar",
    "sg:classifiers":[
        {
            "category":"Building & Trades",
            "subcategory":"Electrical",
            "type":"Services"
        }
    ],
    "sg:phone":"+32 3 887 01 80",
    "sg:postcode":"2630",
    "sg:province":"Antwerpen",
    "sg:tags":[
        "electric",
        "-",
        "housewiring",
        "contractor"
    ],
    "wof:name":"Aerts",
    "wof:placetype":"venue"
},
  "geometry": {"coordinates":[4.3930330276,51.1367225647],"type":"Point"}
}