{
  "type": "Feature",
  "properties": {
    "addr:full":"Einhoven 38 Zoersel Antwerpen 2980",
    "addr:housenumber":"38",
    "addr:postcode":"2980",
    "addr:street":"Einhoven",
    "iso:country":"BE",
    "sg:address":"Einhoven 38",
    "sg:city":"Zoersel",
    "sg:orig_category":"Eleveurs de bovins",
    "sg:phone":"+32 3 312 35 63",
    "sg:postcode":"2980",
    "sg:province":"Antwerpen",
    "wof:name":"Louis Van De Vloet",
    "wof:placetype":"venue"
},
  "geometry": {"coordinates":[4.7275691032,51.2581977844],"type":"Point"}
}