{
  "type": "Feature",
  "properties": {
    "iso:country":"BE",
    "sg:address":"Rue De La R\u00e9sistance 7",
    "sg:city":"Saint-nicolas (montegn\u00e9e)",
    "sg:classifiers":[
        {
            "category":"Shopping",
            "subcategory":"Florist",
            "type":"Retail Goods"
        }
    ],
    "sg:phone":"+32 4 263 44 06",
    "sg:postcode":"4420",
    "sg:province":"Li\u00e8ge",
    "wof:name":"Wathieu",
    "wof:placetype":"venue"
},
  "geometry": {"coordinates":[5.5207748413,50.6411514282],"type":"Point"}
}