{
  "type": "Feature",
  "properties": {
    "addr:full":"Otterstraat 106 Dendermonde (sint-gillis-bij-dendermonde) Oost-Vlaanderen 9200",
    "addr:housenumber":"106",
    "addr:postcode":"9200",
    "addr:street":"Otterstraat",
    "iso:country":"BE",
    "sg:address":"Otterstraat 106",
    "sg:city":"Dendermonde (sint-gillis-bij-dendermonde)",
    "sg:classifiers":[
        {
            "category":"Real Estate",
            "subcategory":"Architect",
            "type":"Services"
        }
    ],
    "sg:phone":"+32 52 20 25 84",
    "sg:postcode":"9200",
    "sg:province":"Oost-Vlaanderen",
    "wof:name":"De Grom A",
    "wof:placetype":"venue"
},
  "geometry": {"coordinates":[4.1110978127,51.021774292],"type":"Point"}
}