{
  "type": "Feature",
  "properties": {
    "addr:full":"Rue Du Ch\u00c2teau D'eau 34 Hamois Namur 5360",
    "addr:housenumber":"34",
    "addr:postcode":"5360",
    "addr:street":"Rue Du Cha\u0302Teau D'Eau",
    "iso:country":"BE",
    "sg:address":"Rue Du Ch\u00c2teau D'eau 34",
    "sg:city":"Hamois",
    "sg:orig_category":"Apotheken",
    "sg:phone":"+32 83 21 23 40",
    "sg:postcode":"5360",
    "sg:province":"Namur",
    "wof:name":"Fran\u00c7oise Maitrejean",
    "wof:placetype":"venue"
},
  "geometry": {"coordinates":[5.0555000305,50.3376235962],"type":"Point"}
}