{
  "type": "Feature",
  "properties": {
    "addr:full":"Hagenbroeksesteenweg 182 Lier Antwerpen 2500",
    "addr:housenumber":"182",
    "addr:postcode":"2500",
    "addr:street":"Hagenbroeksesteenweg",
    "iso:country":"BE",
    "sg:address":"Hagenbroeksesteenweg 182",
    "sg:city":"Lier",
    "sg:orig_category":"Instituts de beaut\u00e9",
    "sg:phone":"+32 3 488 49 77",
    "sg:postcode":"2500",
    "sg:province":"Antwerpen",
    "wof:name":"P. Van Immerseel",
    "wof:placetype":"venue"
},
  "geometry": {"coordinates":[4.5662617683,51.1490287781],"type":"Point"}
}