{
  "type": "Feature",
  "properties": {
    "iso:country":"BE",
    "sg:address":"Rue De La Falize 20",
    "sg:city":"Rhisnes",
    "sg:classifiers":[
        {
            "category":"Building & Trades",
            "subcategory":"Construction",
            "type":"Services"
        }
    ],
    "sg:phone":"+32 81 56 02 55",
    "sg:postcode":"5080",
    "sg:province":"Namur",
    "sg:tags":[
        "la",
        "de",
        "\u00e9quipement",
        "pour",
        "machine",
        "location"
    ],
    "wof:name":"Fobeltran",
    "wof:placetype":"venue"
},
  "geometry": {"coordinates":[4.8074917793,50.4998893738],"type":"Point"}
}