{
  "type": "Feature",
  "properties": {
    "iso:country":"BE",
    "sg:address":"Place De P\u00e2turages 26",
    "sg:city":"Colfontaine (p\u00e2turages)",
    "sg:classifiers":[
        {
            "category":"Real Estate",
            "subcategory":"Architect",
            "type":"Services"
        }
    ],
    "sg:phone":"+32 65 67 56 61",
    "sg:postcode":"7340",
    "sg:province":"Hainaut",
    "wof:name":"Carzedda A",
    "wof:placetype":"venue"
},
  "geometry": {"coordinates":[3.8630409241,50.4134407043],"type":"Point"}
}