{
  "type": "Feature",
  "properties": {
    "addr:full":"Zonnestraat 15 Ronse/renaix Oost-Vlaanderen 9600",
    "addr:housenumber":"15",
    "addr:postcode":"9600",
    "addr:street":"Zonnestraat",
    "iso:country":"BE",
    "sg:address":"Zonnestraat 15",
    "sg:city":"Ronse/renaix",
    "sg:orig_category":"Artsen and specialisten",
    "sg:phone":"+32 55 21 99 29",
    "sg:postcode":"9600",
    "sg:province":"Oost-Vlaanderen",
    "wof:name":"M. Derijcke",
    "wof:placetype":"venue"
},
  "geometry": {"coordinates":[3.5947010517,50.749786377],"type":"Point"}
}