{
  "type": "Feature",
  "properties": {
    "iso:country":"BE",
    "sg:address":"Perstraat 57",
    "sg:city":"Beveren",
    "sg:orig_category":"Plaatsen van vloer- and muurbekleding Schilders Verlichting and huishoudartikelen",
    "sg:phone":"+32 3 775 65 72",
    "sg:postcode":"9120",
    "sg:province":"Oost-Vlaanderen",
    "wof:name":"Decoran",
    "wof:placetype":"venue"
},
  "geometry": {"coordinates":[4.2504920959,51.1725997925],"type":"Point"}
}