{
  "type": "Feature",
  "properties": {
    "addr:full":"Hekkestraat 74 Sint-amands Antwerpen 2890",
    "addr:housenumber":"74",
    "addr:postcode":"2890",
    "addr:street":"Hekkestraat",
    "iso:country":"BE",
    "sg:address":"Hekkestraat 74",
    "sg:city":"Sint-amands",
    "sg:orig_category":"Artsen and specialisten",
    "sg:phone":"+32 52 33 23 13",
    "sg:postcode":"2890",
    "sg:province":"Antwerpen",
    "wof:name":"Jozef T.o. Van Der Veken",
    "wof:placetype":"venue"
},
  "geometry": {"coordinates":[4.2012400627,51.051361084],"type":"Point"}
}