{
  "type": "Feature",
  "properties": {
    "iso:country":"BE",
    "sg:address":"Wintertuinstraat 21",
    "sg:city":"Gent",
    "sg:orig_category":"Activit\u00e9s diverses d'imprimerie",
    "sg:phone":"+32 9 233 67 37",
    "sg:postcode":"9000",
    "sg:province":"Oost-Vlaanderen",
    "wof:name":"B. Koning",
    "wof:placetype":"venue"
},
  "geometry": {"coordinates":[3.7048959732,51.0521469116],"type":"Point"}
}