{
  "type": "Feature",
  "properties": {
    "addr:full":"Oude Molenstraat 26 Assenede Oost-Vlaanderen 9960",
    "addr:housenumber":"26",
    "addr:postcode":"9960",
    "addr:street":"Oude Molenstraat",
    "iso:country":"BE",
    "sg:address":"Oude Molenstraat 26",
    "sg:city":"Assenede",
    "sg:classifiers":[
        {
            "category":"Personal",
            "subcategory":"Beauty Salon",
            "type":"Services"
        }
    ],
    "sg:phone":"+32 9 344 55 39",
    "sg:postcode":"9960",
    "sg:province":"Oost-Vlaanderen",
    "sg:tags":[
        "lady",
        "-",
        "hairdressing"
    ],
    "wof:name":"Persyn M",
    "wof:placetype":"venue"
},
  "geometry": {"coordinates":[3.7495748997,51.2256546021],"type":"Point"}
}