{
  "type": "Feature",
  "properties": {
    "addr:full":"Heer Halewijnlaan 9 Izegem West-Vlaanderen 8870",
    "addr:housenumber":"9",
    "addr:postcode":"8870",
    "addr:street":"Heer Halewijnlaan",
    "iso:country":"BE",
    "sg:address":"Heer Halewijnlaan 9",
    "sg:city":"Izegem",
    "sg:orig_category":"Cr\u00e9meries",
    "sg:phone":"+32 51 30 84 57",
    "sg:postcode":"8870",
    "sg:province":"West-Vlaanderen",
    "wof:name":"Geert Claerhout",
    "wof:placetype":"venue"
},
  "geometry": {"coordinates":[3.224378109,50.9070129395],"type":"Point"}
}