{
  "type": "Feature",
  "properties": {
    "iso:country":"BE",
    "sg:address":"Verrewinkelstraat 93",
    "sg:city":"Ukkel/uccle",
    "sg:orig_category":"Film-, tv- and videoproductie",
    "sg:phone":"+32 2 373 99 40",
    "sg:postcode":"1180",
    "sg:province":"Bruxelles-Capitale",
    "wof:name":"S.b.d.c.",
    "wof:placetype":"venue"
},
  "geometry": {"coordinates":[4.3453621864,50.7872238159],"type":"Point"}
}