{
  "type": "Feature",
  "properties": {
    "iso:country":"BE",
    "sg:address":"Bilzersteenweg 64",
    "sg:city":"Riemst",
    "sg:orig_category":"Entretien and r\u00e9parations de voitures",
    "sg:phone":"+32 12 45 79 90",
    "sg:postcode":"3770",
    "sg:province":"Limburg",
    "wof:name":"Gerd Thijs",
    "wof:placetype":"venue"
},
  "geometry": {"coordinates":[5.5921740532,50.8163108826],"type":"Point"}
}