{
  "type": "Feature",
  "properties": {
    "iso:country":"BE",
    "sg:address":"Van Hemelrijcklei 1",
    "sg:city":"Brasschaat",
    "sg:orig_category":"Meubelzaken, woning- and keukeninrichting",
    "sg:phone":"+32 3 653 00 50",
    "sg:postcode":"2930",
    "sg:province":"Antwerpen",
    "wof:name":"Matrassenreus",
    "wof:placetype":"venue"
},
  "geometry": {"coordinates":[4.4944839478,51.2928962708],"type":"Point"}
}