{
  "type": "Feature",
  "properties": {
    "addr:full":"Leistraat 91 Kasterlee (lichtaart) Antwerpen 2460",
    "addr:housenumber":"91",
    "addr:postcode":"2460",
    "addr:street":"Leistraat",
    "iso:country":"BE",
    "sg:address":"Leistraat 91",
    "sg:city":"Kasterlee (lichtaart)",
    "sg:classifiers":[
        {
            "category":"Insurance",
            "subcategory":"Insurance Agent",
            "type":"Services"
        }
    ],
    "sg:phone":"+32 14 55 22 81",
    "sg:postcode":"2460",
    "sg:province":"Antwerpen",
    "sg:tags":[
        "broker"
    ],
    "wof:name":"Driesen G",
    "wof:placetype":"venue"
},
  "geometry": {"coordinates":[4.9138450623,51.2238922119],"type":"Point"}
}