{
  "type": "Feature",
  "properties": {
    "iso:country":"BE",
    "sg:address":"Zomerstraat-oost 33",
    "sg:city":"Damme (sijsele)",
    "sg:classifiers":[
        {
            "category":"Retail",
            "subcategory":"Veterinary Services",
            "type":"Services"
        }
    ],
    "sg:phone":"+32 50 79 09 19",
    "sg:postcode":"8340",
    "sg:province":"West-Vlaanderen",
    "sg:tags":[
        "veterinarian"
    ],
    "wof:name":"Mattart J",
    "wof:placetype":"venue"
},
  "geometry": {"coordinates":[3.2815999985,51.2513160706],"type":"Point"}
}