{
  "type": "Feature",
  "properties": {
    "iso:country":"BE",
    "sg:address":"Quai Du Commerce 40 Box 6",
    "sg:city":"Bruxelles",
    "sg:classifiers":[
        {
            "category":"Home & Garden",
            "subcategory":"Home Furnishings",
            "type":"Retail Goods"
        }
    ],
    "sg:phone":"+32 2 219 95 29",
    "sg:postcode":"1000",
    "sg:province":"Bruxelles-Capitale",
    "sg:tags":[
        "curtain",
        "-",
        "fixture"
    ],
    "wof:name":"Pour Le Plaisir Des Yeux",
    "wof:placetype":"venue"
},
  "geometry": {"coordinates":[4.3480758667,50.8570861816],"type":"Point"}
}