{
  "type": "Feature",
  "properties": {
    "iso:country":"BE",
    "sg:address":"Vollezelestraat 41",
    "sg:city":"Galmaarden (tollembeek)",
    "sg:classifiers":[
        {
            "category":"Communications",
            "type":"Services"
        }
    ],
    "sg:phone":"+32 54 58 64 02",
    "sg:postcode":"1570",
    "sg:province":"Vlaams-Brabant",
    "sg:tags":[
        "translator"
    ],
    "wof:name":"Langenakens",
    "wof:placetype":"venue"
},
  "geometry": {"coordinates":[4.0124988556,50.7449607849],"type":"Point"}
}