{
  "type": "Feature",
  "properties": {
    "addr:full":"Grand-place 16 Herbeumont Luxembourg 6887",
    "addr:housenumber":"16",
    "addr:postcode":"6887",
    "addr:street":"Grand-Place",
    "iso:country":"BE",
    "sg:address":"Grand-place 16",
    "sg:city":"Herbeumont",
    "sg:classifiers":[
        {
            "category":"Cafe",
            "type":"Food & Drink"
        }
    ],
    "sg:phone":"+32 61 41 19 36",
    "sg:postcode":"6887",
    "sg:province":"Luxembourg",
    "sg:tags":[
        "caf\u00e9s"
    ],
    "wof:name":"Caf\u00c9 Au Bon Coin",
    "wof:placetype":"venue"
},
  "geometry": {"coordinates":[5.2371988297,49.7805290222],"type":"Point"}
}