{
  "type": "Feature",
  "properties": {
    "addr:full":"Rue Octave De Falleur 1 Charleroi Hainaut 6040",
    "addr:housenumber":"1",
    "addr:postcode":"6040",
    "addr:street":"Rue Octave De Falleur;Hainaut",
    "iso:country":"BE",
    "sg:address":"Rue Octave De Falleur 1",
    "sg:city":"Charleroi",
    "sg:orig_category":"Belastingconsulenten Diverse juridische dienstverlening Landmeters and schatters Verzekeringsmakelaa",
    "sg:phone":"+32 71 37 37 26",
    "sg:postcode":"6040",
    "sg:province":"Hainaut",
    "wof:name":"Jacques Semal",
    "wof:placetype":"venue"
},
  "geometry": {"coordinates":[4.439412117,50.4430656433],"type":"Point"}
}