{
  "type": "Feature",
  "properties": {
    "iso:country":"BE",
    "sg:address":"Gustave De Stuersstraat 2",
    "sg:city":"Ieper",
    "sg:orig_category":"Apotheken",
    "sg:phone":"+32 57 20 08 55",
    "sg:postcode":"8900",
    "sg:province":"West-Vlaanderen",
    "wof:name":"Luc Delbeke",
    "wof:placetype":"venue"
},
  "geometry": {"coordinates":[2.8815720081,50.8502235413],"type":"Point"}
}