{
  "type": "Feature",
  "properties": {
    "iso:country":"BE",
    "sg:address":"Heimolenstraat 125",
    "sg:city":"Sint-niklaas",
    "sg:orig_category":"Architecten",
    "sg:phone":"+32 3 776 34 43",
    "sg:postcode":"9100",
    "sg:province":"Oost-Vlaanderen",
    "wof:name":"Cauberghe C.",
    "wof:placetype":"venue"
},
  "geometry": {"coordinates":[4.133849144,51.1386222839],"type":"Point"}
}