{
  "type": "Feature",
  "properties": {
    "iso:country":"BE",
    "sg:address":"Hoveniersstraat 12",
    "sg:city":"Antwerpen",
    "sg:orig_category":"Beveiligingsdiensten and bewakingsbedrijven",
    "sg:phone":"+32 3 225 04 05",
    "sg:postcode":"2018",
    "sg:province":"Antwerpen",
    "wof:name":"Monstrey Worldwide Services",
    "wof:placetype":"venue"
},
  "geometry": {"coordinates":[4.418487072,51.2155227661],"type":"Point"}
}