{
  "type": "Feature",
  "properties": {
    "addr:full":"Bachstrasse 3 Kelmis/la Calamine Li\u00e8ge 4720",
    "addr:housenumber":"3",
    "addr:postcode":"4720",
    "addr:street":"Bachstrasse",
    "iso:country":"BE",
    "sg:address":"Bachstrasse 3",
    "sg:city":"Kelmis/la Calamine",
    "sg:classifiers":[
        {
            "category":"Fast Food",
            "type":"Food & Drink"
        }
    ],
    "sg:phone":"+32 87 63 04 22",
    "sg:postcode":"4720",
    "sg:province":"Li\u00e8ge",
    "sg:tags":[
        "meeneem",
        "restaurant"
    ],
    "wof:name":"Chez Alice",
    "wof:placetype":"venue"
},
  "geometry": {"coordinates":[6.0070748329,50.7164077759],"type":"Point"}
}