{
  "type": "Feature",
  "properties": {
    "iso:country":"BE",
    "sg:address":"Rue De Cugnon 3",
    "sg:city":"Florenville",
    "sg:orig_category":"Artsen and specialisten",
    "sg:phone":"+32 61 31 21 76",
    "sg:postcode":"6820",
    "sg:province":"Luxembourg",
    "wof:name":"Pierre Robinet",
    "wof:placetype":"venue"
},
  "geometry": {"coordinates":[5.1751499176,49.7168083191],"type":"Point"}
}