{
  "type": "Feature",
  "properties": {
    "iso:country":"BE",
    "sg:address":"Rue De Taillis Pr\u00e9 301",
    "sg:city":"Ch\u00e2telet (ch\u00e2telineau)",
    "sg:classifiers":[
        {
            "category":"Building & Trades",
            "subcategory":"Landscaping Services",
            "type":"Services"
        }
    ],
    "sg:phone":"+32 71 39 23 37",
    "sg:postcode":"6200",
    "sg:province":"Hainaut",
    "sg:tags":[
        "gardening",
        "garden",
        "maintenance"
    ],
    "wof:name":"Simon Luc",
    "wof:placetype":"venue"
},
  "geometry": {"coordinates":[4.5119948387,50.4390487671],"type":"Point"}
}