{
  "type": "Feature",
  "properties": {
    "iso:country":"BE",
    "sg:address":"Bijvoordestraat 21",
    "sg:city":"Boutersem",
    "sg:orig_category":"Rundveehouders",
    "sg:phone":"+32 16 73 36 63",
    "sg:postcode":"3370",
    "sg:province":"Vlaams-Brabant",
    "wof:name":"Joannes Mottie",
    "wof:placetype":"venue"
},
  "geometry": {"coordinates":[4.8858299255,50.8484611511],"type":"Point"}
}