{
  "type": "Feature",
  "properties": {
    "addr:full":"Rue De Brabant 185 Bruxelles (schaerbeek) Bruxelles-Capitale 1030",
    "addr:housenumber":"185",
    "addr:postcode":"1030",
    "addr:street":"Rue De Brabant",
    "iso:country":"BE",
    "sg:address":"Rue De Brabant 185",
    "sg:city":"Bruxelles (schaerbeek)",
    "sg:classifiers":[
        {
            "category":"Shopping",
            "subcategory":"Gifts & Souvenirs",
            "type":"Retail Goods"
        }
    ],
    "sg:phone":"+32 2 215 75 26",
    "sg:postcode":"1030",
    "sg:province":"Bruxelles-Capitale",
    "sg:tags":[
        "-"
    ],
    "wof:name":"Diodati Export",
    "wof:placetype":"venue"
},
  "geometry": {"coordinates":[4.3657531738,50.8634262085],"type":"Point"}
}