{
  "type": "Feature",
  "properties": {
    "iso:country":"BE",
    "sg:address":"All\u00c9e Du Nondeux 7",
    "sg:city":"Beauraing",
    "sg:orig_category":"Bouwmaterialen Gh Installatie van metalen schrijnwerk Vloer- and muurbekleding",
    "sg:phone":"+32 82 71 40 60",
    "sg:postcode":"5570",
    "sg:province":"Namur",
    "wof:name":"Construmat",
    "wof:placetype":"venue"
},
  "geometry": {"coordinates":[4.955163002,50.1097068787],"type":"Point"}
}