{
  "type": "Feature",
  "properties": {
    "addr:full":"Rue De Stassart 54 Box 3 Bruxelles (ixelles) Bruxelles-Capitale 1050",
    "addr:housenumber":"54;3",
    "addr:postcode":"1050",
    "addr:street":"Rue De Stassart;Box",
    "iso:country":"BE",
    "sg:address":"Rue De Stassart 54 Box 3",
    "sg:city":"Bruxelles (ixelles)",
    "sg:classifiers":[
        {
            "category":"Building & Trades",
            "subcategory":"Landscaping Services",
            "type":"Services"
        }
    ],
    "sg:phone":"+32 2 514 20 99",
    "sg:postcode":"1050",
    "sg:province":"Bruxelles-Capitale",
    "sg:tags":[
        "architect",
        "landscape"
    ],
    "wof:name":"Tonglet A",
    "wof:placetype":"venue"
},
  "geometry": {"coordinates":[4.3607859612,50.8362808228],"type":"Point"}
}