{
  "type": "Feature",
  "properties": {
    "addr:full":"Rue Du Gonhy 35 Seraing Li\u00e8ge 4100",
    "addr:housenumber":"35",
    "addr:postcode":"4100",
    "addr:street":"Rue Du Gonhy",
    "iso:country":"BE",
    "sg:address":"Rue Du Gonhy 35",
    "sg:city":"Seraing",
    "sg:orig_category":"M\u00e9decins and sp\u00e9cialistes",
    "sg:phone":"+32 4 338 29 87",
    "sg:postcode":"4100",
    "sg:province":"Li\u00e8ge",
    "wof:name":"Agn\u00c8s Riviere",
    "wof:placetype":"venue"
},
  "geometry": {"coordinates":[5.5473937988,50.5641517639],"type":"Point"}
}