{
  "type": "Feature",
  "properties": {
    "iso:country":"BE",
    "sg:address":"Grote Baan 33",
    "sg:city":"Lummen",
    "sg:orig_category":"Bloemen and planten Tuinbenodigdheden Tuinen",
    "sg:phone":"+32 13 31 28 19",
    "sg:postcode":"3560",
    "sg:province":"Limburg",
    "wof:name":"Lieten-lieten",
    "wof:placetype":"venue"
},
  "geometry": {"coordinates":[5.1242499352,51.0128517151],"type":"Point"}
}