{
  "type": "Feature",
  "properties": {
    "addr:full":"Vaartkant Links 36 Brecht Antwerpen 2960",
    "addr:housenumber":"36",
    "addr:postcode":"2960",
    "addr:street":"Vaartkant Links",
    "iso:country":"BE",
    "sg:address":"Vaartkant Links 36",
    "sg:city":"Brecht",
    "sg:orig_category":"Quincailleries",
    "sg:phone":"+32 3 313 02 09",
    "sg:postcode":"2960",
    "sg:province":"Antwerpen",
    "wof:name":"Bastiaansen",
    "wof:placetype":"venue"
},
  "geometry": {"coordinates":[4.6415200233,51.3512115479],"type":"Point"}
}