{
  "type": "Feature",
  "properties": {
    "iso:country":"BE",
    "sg:address":"Kleine Monnikenwerve 16",
    "sg:city":"Brugge",
    "sg:orig_category":"Zuivelproducten",
    "sg:phone":"+32 50 31 92 91",
    "sg:postcode":"8000",
    "sg:province":"West-Vlaanderen",
    "wof:name":"Gardin",
    "wof:placetype":"venue"
},
  "geometry": {"coordinates":[3.1980309486,51.2479362488],"type":"Point"}
}