{
  "type": "Feature",
  "properties": {
    "addr:full":"Avenue Des Alli\u00e9s 29 Charleroi Hainaut 6000",
    "addr:housenumber":"29",
    "addr:postcode":"6000",
    "addr:street":"Avenue Des Allie\u0301S;Hainaut",
    "iso:country":"BE",
    "sg:address":"Avenue Des Alli\u00e9s 29",
    "sg:city":"Charleroi",
    "sg:classifiers":[
        {
            "category":"Banks & Credit Unions",
            "subcategory":"Financial Services",
            "type":"Services"
        }
    ],
    "sg:phone":"+32 71 53 57 96",
    "sg:postcode":"6000",
    "sg:province":"Hainaut",
    "sg:tags":[
        "loan",
        "mortgage"
    ],
    "wof:name":"Immogesta Prets +",
    "wof:placetype":"venue"
},
  "geometry": {"coordinates":[4.4392762184,50.4112014771],"type":"Point"}
}