{
  "type": "Feature",
  "properties": {
    "addr:full":"Roodkruisstraat 18bc Hamme Oost-Vlaanderen 9220",
    "addr:housenumber":"18bc",
    "addr:postcode":"9220",
    "addr:street":"Roodkruisstraat",
    "iso:country":"BE",
    "sg:address":"Roodkruisstraat 18bc",
    "sg:city":"Hamme",
    "sg:orig_category":"Installation \u00e9lectrique r\u00e9sidentielle",
    "sg:phone":"+32 52 47 72 30",
    "sg:postcode":"9220",
    "sg:province":"Oost-Vlaanderen",
    "wof:name":"Maurits De Pillecijn",
    "wof:placetype":"venue"
},
  "geometry": {"coordinates":[4.1425647736,51.1005363464],"type":"Point"}
}