{
  "type": "Feature",
  "properties": {
    "addr:full":"Beernemsteenweg 49 Wingene West-Vlaanderen 8750",
    "addr:housenumber":"49",
    "addr:postcode":"8750",
    "addr:street":"Beernemsteenweg",
    "iso:country":"BE",
    "sg:address":"Beernemsteenweg 49",
    "sg:city":"Wingene",
    "sg:classifiers":[
        {
            "category":"Professional",
            "subcategory":"Testing Lab",
            "type":"Services"
        }
    ],
    "sg:phone":"+32 51 65 62 97",
    "sg:postcode":"8750",
    "sg:province":"West-Vlaanderen",
    "sg:tags":[
        "laboratory",
        "-"
    ],
    "wof:name":"Ascor Envirocontrol Bvba",
    "wof:placetype":"venue"
},
  "geometry": {"coordinates":[3.2986629009,51.0783424377],"type":"Point"}
}