{
  "type": "Feature",
  "properties": {
    "iso:country":"BE",
    "sg:address":"Luingnesteenweg 2",
    "sg:city":"Moeskroen/mouscron",
    "sg:orig_category":"Banken and kredietinstellingen",
    "sg:phone":"+32 56 33 17 59",
    "sg:postcode":"7712",
    "sg:province":"Hainaut",
    "wof:name":"Fortis",
    "wof:placetype":"venue"
},
  "geometry": {"coordinates":[3.2535879612,50.714931488],"type":"Point"}
}