{
  "type": "Feature",
  "properties": {
    "addr:full":"Veltjensstraat 39 Geel Antwerpen 2440",
    "addr:housenumber":"39",
    "addr:postcode":"2440",
    "addr:street":"Veltjensstraat",
    "iso:country":"BE",
    "sg:address":"Veltjensstraat 39",
    "sg:city":"Geel",
    "sg:classifiers":[
        {
            "category":"Cafe",
            "type":"Food & Drink"
        }
    ],
    "sg:phone":"+32 14 31 78 35",
    "sg:postcode":"2440",
    "sg:province":"Antwerpen",
    "sg:tags":[
        "caf\u00e9s"
    ],
    "wof:name":"Caf\u00c9 't Belshof",
    "wof:placetype":"venue"
},
  "geometry": {"coordinates":[5.0705599785,51.1684455872],"type":"Point"}
}