{
  "type": "Feature",
  "properties": {
    "addr:full":"Roeselarestraat 73 Staden (oostnieuwkerke) West-Vlaanderen 8840",
    "addr:housenumber":"73",
    "addr:postcode":"8840",
    "addr:street":"Roeselarestraat",
    "iso:country":"BE",
    "sg:address":"Roeselarestraat 73",
    "sg:city":"Staden (oostnieuwkerke)",
    "sg:classifiers":[
        {
            "category":"Shopping",
            "subcategory":"Bicycles & Sporting Goods",
            "type":"Retail Goods"
        }
    ],
    "sg:phone":"+32 51 20 38 88",
    "sg:postcode":"8840",
    "sg:province":"West-Vlaanderen",
    "sg:tags":[
        "-"
    ],
    "wof:name":"Vandewalle F",
    "wof:placetype":"venue"
},
  "geometry": {"coordinates":[3.0655179024,50.9421234131],"type":"Point"}
}