{
  "type": "Feature",
  "properties": {
    "iso:country":"BE",
    "sg:address":"Koning Boudewijnstraat 148",
    "sg:city":"Kuurne",
    "sg:orig_category":"Non-Classified Establishments",
    "sg:phone":"+32 56 72 52 26",
    "sg:postcode":"8520",
    "sg:province":"West-Vlaanderen",
    "wof:name":"T.b.o. Bvba",
    "wof:placetype":"venue"
},
  "geometry": {"coordinates":[3.2796730995,50.8625831604],"type":"Point"}
}