{
  "type": "Feature",
  "properties": {
    "iso:country":"BE",
    "sg:address":"Avenue Brugmann 520",
    "sg:city":"Bruxelles (uccle)",
    "sg:orig_category":"Non-Classified Establishments",
    "sg:phone":"+32 2 347 50 33",
    "sg:postcode":"1180",
    "sg:province":"Bruxelles-Capitale",
    "wof:name":"Sharmila Production",
    "wof:placetype":"venue"
},
  "geometry": {"coordinates":[4.3383588791,50.8009986877],"type":"Point"}
}