{
  "type": "Feature",
  "properties": {
    "iso:country":"BE",
    "sg:address":"Oostakkerdorp 20",
    "sg:city":"Gent (oostakker)",
    "sg:classifiers":[
        {
            "category":"Fast Food",
            "type":"Food & Drink"
        }
    ],
    "sg:phone":"+32 9 259 08 29",
    "sg:postcode":"9041",
    "sg:province":"Oost-Vlaanderen",
    "sg:tags":[
        "fried",
        "stand",
        "potato"
    ],
    "wof:name":"Everzwijn ('t)",
    "wof:placetype":"venue"
},
  "geometry": {"coordinates":[3.7629740238,51.1009216309],"type":"Point"}
}