{
  "type": "Feature",
  "properties": {
    "addr:full":"Chauss\u00c9e De Charleroi 71b4 Gembloux Namur 5030",
    "addr:housenumber":"71b4",
    "addr:postcode":"5030",
    "addr:street":"Chausse\u0301E De Charleroi;Namur",
    "iso:country":"BE",
    "sg:address":"Chauss\u00c9e De Charleroi 71b4",
    "sg:city":"Gembloux",
    "sg:orig_category":"Artsen and specialisten",
    "sg:phone":"+32 81 60 01 66",
    "sg:postcode":"5030",
    "sg:province":"Namur",
    "wof:name":"Raoul Nassar",
    "wof:placetype":"venue"
},
  "geometry": {"coordinates":[4.6867499352,50.5636482239],"type":"Point"}
}