{
  "type": "Feature",
  "properties": {
    "addr:full":"Duiveketestraat 7 De Haan West-Vlaanderen 8420",
    "addr:housenumber":"7",
    "addr:postcode":"8420",
    "addr:street":"Duiveketestraat",
    "iso:country":"BE",
    "sg:address":"Duiveketestraat 7",
    "sg:city":"De Haan",
    "sg:orig_category":"Installation \u00e9lectrique r\u00e9sidentielle",
    "sg:phone":"+32 59 23 40 33",
    "sg:postcode":"8420",
    "sg:province":"West-Vlaanderen",
    "wof:name":"Peter Zwaenepoel",
    "wof:placetype":"venue"
},
  "geometry": {"coordinates":[3.0331459045,51.2727775574],"type":"Point"}
}