{
  "type": "Feature",
  "properties": {
    "iso:country":"BE",
    "sg:address":"Place Docteur Schweitzer 8-10 Box 13",
    "sg:city":"Bruxelles (berchem-sainte-agathe)",
    "sg:classifiers":[
        {
            "category":"Communications",
            "subcategory":"Film & Video Production",
            "type":"Services"
        }
    ],
    "sg:phone":"+32 2 465 03 33",
    "sg:postcode":"1082",
    "sg:province":"Bruxelles-Capitale",
    "sg:tags":[
        "multimedia",
        "-",
        "system"
    ],
    "wof:name":"Omnicomm Productions",
    "wof:placetype":"venue"
},
  "geometry": {"coordinates":[4.2982487679,50.8644790649],"type":"Point"}
}