{
  "type": "Feature",
  "properties": {
    "addr:full":"Route D'andenne 29 Gesves (faulx-les-tombes) Namur 5340",
    "addr:housenumber":"29",
    "addr:postcode":"5340",
    "addr:street":"Route D'Andenne",
    "iso:country":"BE",
    "sg:address":"Route D'andenne 29",
    "sg:city":"Gesves (faulx-les-tombes)",
    "sg:classifiers":[
        {
            "category":"Building & Trades",
            "subcategory":"Electrical",
            "type":"Services"
        }
    ],
    "sg:phone":"+32 81 57 09 56",
    "sg:postcode":"5340",
    "sg:province":"Namur",
    "sg:tags":[
        "electric",
        "-",
        "housewiring",
        "contractor"
    ],
    "wof:name":"Franquinet",
    "wof:placetype":"venue"
},
  "geometry": {"coordinates":[5.0273208618,50.4268913269],"type":"Point"}
}