{
  "type": "Feature",
  "properties": {
    "addr:full":"Zwevegemsestraat 103 Kortrijk West-Vlaanderen 8500",
    "addr:housenumber":"103",
    "addr:postcode":"8500",
    "addr:street":"Zwevegemsestraat",
    "iso:country":"BE",
    "sg:address":"Zwevegemsestraat 103",
    "sg:city":"Kortrijk",
    "sg:orig_category":"Boekenuitgeverijen Divers amusement Muziekinstrumenten",
    "sg:phone":"+32 56 21 66 72",
    "sg:postcode":"8500",
    "sg:province":"West-Vlaanderen",
    "wof:name":"Uitgeverij Coccioli",
    "wof:placetype":"venue"
},
  "geometry": {"coordinates":[3.2756969929,50.8234214783],"type":"Point"}
}