{
  "type": "Feature",
  "properties": {
    "iso:country":"BE",
    "sg:address":"Rue Pont-\u00c0-la-faulx 31",
    "sg:city":"Peruwelz",
    "sg:classifiers":[
        {
            "category":"Wholesale",
            "subcategory":"Sporting Goods",
            "type":"Manufacturing & Wholesale Goods"
        }
    ],
    "sg:phone":"+32 69 77 20 01",
    "sg:postcode":"7600",
    "sg:province":"Hainaut",
    "sg:tags":[
        "sport-",
        "kampeermateriaal"
    ],
    "wof:name":"Luc Sports",
    "wof:placetype":"venue"
},
  "geometry": {"coordinates":[3.5950570107,50.5109939575],"type":"Point"}
}