{
  "type": "Feature",
  "properties": {
    "addr:full":"Ambiorixstraat 38 Tongeren Limburg 3700",
    "addr:housenumber":"38",
    "addr:postcode":"3700",
    "addr:street":"Ambiorixstraat",
    "iso:country":"BE",
    "sg:address":"Ambiorixstraat 38",
    "sg:city":"Tongeren",
    "sg:orig_category":"Installation de menuiserie m\u00e9tallique",
    "sg:phone":"+32 12 23 27 41",
    "sg:postcode":"3700",
    "sg:province":"Limburg",
    "wof:name":"Krieken",
    "wof:placetype":"venue"
},
  "geometry": {"coordinates":[5.4769678116,50.7872390747],"type":"Point"}
}