{
  "type": "Feature",
  "properties": {
    "iso:country":"BE",
    "sg:address":"Rue Des Papillards 177",
    "sg:city":"Li\u00e8ge 1 (jupille-sur-meuse)",
    "sg:classifiers":[
        {
            "category":"Communications",
            "subcategory":"Television Station",
            "type":"Services"
        }
    ],
    "sg:phone":"+32 4 370 61 66",
    "sg:postcode":"4020",
    "sg:province":"Li\u00e8ge",
    "sg:tags":[
        "report",
        "video"
    ],
    "wof:name":"Dal'bo N",
    "wof:placetype":"venue"
},
  "geometry": {"coordinates":[5.656908989,50.6379623413],"type":"Point"}
}