{
  "type": "Feature",
  "properties": {
    "addr:full":"Einderpad 33 Lommel Limburg 3920",
    "addr:housenumber":"33",
    "addr:postcode":"3920",
    "addr:street":"Einderpad",
    "iso:country":"BE",
    "sg:address":"Einderpad 33",
    "sg:city":"Lommel",
    "sg:classifiers":[
        {
            "category":"Insurance",
            "subcategory":"Life Insurance",
            "type":"Services"
        }
    ],
    "sg:phone":"+32 11 55 04 45",
    "sg:postcode":"3920",
    "sg:province":"Limburg",
    "sg:tags":[
        "assurance"
    ],
    "wof:name":"M. Swinnen",
    "wof:placetype":"venue"
},
  "geometry": {"coordinates":[5.3102898598,51.229183197],"type":"Point"}
}