{
  "type": "Feature",
  "properties": {
    "addr:full":"Avenue Fernand Charlot 5ba Jodoigne Brabant Wallon 1370",
    "addr:postcode":"5ba;1370",
    "addr:street":"Avenue Fernand Charlot",
    "iso:country":"BE",
    "sg:address":"Avenue Fernand Charlot 5ba",
    "sg:city":"Jodoigne",
    "sg:classifiers":[
        {
            "category":"Insurance",
            "subcategory":"Life Insurance",
            "type":"Services"
        }
    ],
    "sg:phone":"+32 10 81 06 94",
    "sg:postcode":"1370",
    "sg:province":"Brabant Wallon",
    "sg:tags":[
        "assurance"
    ],
    "wof:name":"Ibis 4",
    "wof:placetype":"venue"
},
  "geometry": {"coordinates":[4.8708720207,50.7231330872],"type":"Point"}
}