{
  "type": "Feature",
  "properties": {
    "iso:country":"BE",
    "sg:address":"Rue Du Sart 26",
    "sg:city":"Ans",
    "sg:orig_category":"Voertuigen",
    "sg:phone":"+32 4 247 17 47",
    "sg:postcode":"4432",
    "sg:province":"Li\u00e8ge",
    "wof:name":"Wash One",
    "wof:placetype":"venue"
},
  "geometry": {"coordinates":[5.5100851059,50.6676864624],"type":"Point"}
}