{
  "type": "Feature",
  "properties": {
    "iso:country":"BE",
    "sg:address":"Grand'route De Mons 107",
    "sg:city":"Saint-ghislain",
    "sg:orig_category":"Pain, p\u00e2tisseries and confiseries",
    "sg:phone":"+32 65 62 03 27",
    "sg:postcode":"7334",
    "sg:province":"Hainaut",
    "wof:name":"Lebrun",
    "wof:placetype":"venue"
},
  "geometry": {"coordinates":[3.7649760246,50.4797706604],"type":"Point"}
}