{
  "type": "Feature",
  "properties": {
    "addr:full":"Bisschop Ruttenstraat 17 Kinrooi Limburg 3640",
    "addr:housenumber":"17",
    "addr:postcode":"3640",
    "addr:street":"Bisschop Ruttenstraat",
    "iso:country":"BE",
    "sg:address":"Bisschop Ruttenstraat 17",
    "sg:city":"Kinrooi",
    "sg:classifiers":[
        {
            "category":"Utilities",
            "subcategory":"Fuel Oil & Lpg",
            "type":"Services"
        }
    ],
    "sg:phone":"+32 50 54 76 20",
    "sg:postcode":"3640",
    "sg:province":"Limburg",
    "sg:tags":[
        "cleaning",
        "agent",
        "contamination"
    ],
    "wof:name":"A.i.c.b.",
    "wof:placetype":"venue"
},
  "geometry": {"coordinates":[3.2070729733,51.3352279663],"type":"Point"}
}