{
  "type": "Feature",
  "properties": {
    "addr:full":"Route De L'etat 35 Merbes-le-ch\u00c2teau Hainaut 6567",
    "addr:housenumber":"35",
    "addr:postcode":"6567",
    "addr:street":"Route De L'Etat",
    "iso:country":"BE",
    "sg:address":"Route De L'etat 35",
    "sg:city":"Merbes-le-ch\u00c2teau",
    "sg:orig_category":"Eleveurs de bovins",
    "sg:phone":"+32 64 77 11 94",
    "sg:postcode":"6567",
    "sg:province":"Hainaut",
    "wof:name":"Nadine Becquet",
    "wof:placetype":"venue"
},
  "geometry": {"coordinates":[4.1666707993,50.3561553955],"type":"Point"}
}