{
  "type": "Feature",
  "properties": {
    "iso:country":"BE",
    "sg:address":"Stationsstraat 23",
    "sg:city":"Puurs",
    "sg:orig_category":"Fietsen",
    "sg:phone":"+32 3 889 40 02",
    "sg:postcode":"2870",
    "sg:province":"Antwerpen",
    "wof:name":"Thomas Sport",
    "wof:placetype":"venue"
},
  "geometry": {"coordinates":[4.2808389664,51.0770149231],"type":"Point"}
}