{
  "type": "Feature",
  "properties": {
    "iso:country":"BE",
    "sg:address":"Peter Benoitlaan 31a",
    "sg:city":"Kontich",
    "sg:classifiers":[
        {
            "category":"Professional",
            "subcategory":"Art Services",
            "type":"Services"
        }
    ],
    "sg:phone":"+32 3 457 72 04",
    "sg:postcode":"2550",
    "sg:province":"Antwerpen",
    "sg:tags":[
        "graphic",
        "designer"
    ],
    "wof:name":"Cesart Bvba",
    "wof:placetype":"venue"
},
  "geometry": {"coordinates":[4.4441800117,51.1386299133],"type":"Point"}
}