{
  "type": "Feature",
  "properties": {
    "addr:full":"Hasseltsesteenweg 279 Tongeren Limburg 3700",
    "addr:housenumber":"279",
    "addr:postcode":"3700",
    "addr:street":"Hasseltsesteenweg",
    "iso:country":"BE",
    "sg:address":"Hasseltsesteenweg 279",
    "sg:city":"Tongeren",
    "sg:orig_category":"Epiceries",
    "sg:phone":"+32 12 23 26 06",
    "sg:postcode":"3700",
    "sg:province":"Limburg",
    "wof:name":"W. Veugen",
    "wof:placetype":"venue"
},
  "geometry": {"coordinates":[5.4514307976,50.7897415161],"type":"Point"}
}