{
  "type": "Feature",
  "properties": {
    "iso:country":"BE",
    "sg:address":"Rue De La Fontaine 65",
    "sg:city":"Fl\u00e9malle",
    "sg:classifiers":[
        {
            "category":"Parking",
            "subcategory":"Bicycle",
            "type":"Transportation"
        }
    ],
    "sg:phone":"+32 4 231 16 73",
    "sg:postcode":"4400",
    "sg:province":"Li\u00e8ge",
    "sg:tags":[
        "chiropodist"
    ],
    "wof:name":"Van Laer M",
    "wof:placetype":"venue"
},
  "geometry": {"coordinates":[5.4771680832,50.6085205078],"type":"Point"}
}