{
  "type": "Feature",
  "properties": {
    "iso:country":"BE",
    "sg:address":"Posterijstraat 26",
    "sg:city":"Waregem",
    "sg:orig_category":"Jardinage",
    "sg:phone":"+32 56 60 56 97",
    "sg:postcode":"8793",
    "sg:province":"West-Vlaanderen",
    "wof:name":"De Blanck J",
    "wof:placetype":"venue"
},
  "geometry": {"coordinates":[3.4051470757,50.9050712585],"type":"Point"}
}