{
  "type": "Feature",
  "properties": {
    "addr:full":"Bissegemstraat 6 Wevelgem West-Vlaanderen 8560",
    "addr:housenumber":"6",
    "addr:postcode":"8560",
    "addr:street":"Bissegemstraat",
    "iso:country":"BE",
    "sg:address":"Bissegemstraat 6",
    "sg:city":"Wevelgem",
    "sg:orig_category":"Dameskledingzaken Herenkledingzaken",
    "sg:phone":"+32 56 40 29 05",
    "sg:postcode":"8560",
    "sg:province":"West-Vlaanderen",
    "wof:name":"M-mode",
    "wof:placetype":"venue"
},
  "geometry": {"coordinates":[3.2048289776,50.8428840637],"type":"Point"}
}