{
  "type": "Feature",
  "properties": {
    "iso:country":"BE",
    "sg:address":"Gulden Sporenstraat 6",
    "sg:city":"Roeselare",
    "sg:classifiers":[
        {
            "category":"Professional",
            "subcategory":"Business Services",
            "type":"Services"
        }
    ],
    "sg:phone":"+32 51 25 00 19",
    "sg:postcode":"8800",
    "sg:province":"West-Vlaanderen",
    "sg:tags":[
        "aux",
        "diver",
        "entreprises"
    ],
    "wof:name":"Event Idee",
    "wof:placetype":"venue"
},
  "geometry": {"coordinates":[3.1337120533,50.9369049072],"type":"Point"}
}