{
  "type": "Feature",
  "properties": {
    "addr:full":"Molendries 26 Aalst Oost-Vlaanderen 9300",
    "addr:housenumber":"26",
    "addr:postcode":"9300",
    "addr:street":"Molendries",
    "iso:country":"BE",
    "sg:address":"Molendries 26",
    "sg:city":"Aalst",
    "sg:orig_category":"Rookartikelen",
    "sg:phone":"+32 53 70 25 32",
    "sg:postcode":"9300",
    "sg:province":"Oost-Vlaanderen",
    "wof:name":"Huis Decock",
    "wof:placetype":"venue"
},
  "geometry": {"coordinates":[4.0443100929,50.9417190552],"type":"Point"}
}