{
  "type": "Feature",
  "properties": {
    "iso:country":"BE",
    "sg:address":"Zavelstraat 75",
    "sg:city":"Herzele",
    "sg:orig_category":"Belastingconsulenten Boekhouders Diverse juridische dienstverlening",
    "sg:phone":"+32 54 50 37 99",
    "sg:postcode":"9550",
    "sg:province":"Oost-Vlaanderen",
    "wof:name":"Karel Detremerie",
    "wof:placetype":"venue"
},
  "geometry": {"coordinates":[3.9126238823,50.8459968567],"type":"Point"}
}