{
  "type": "Feature",
  "properties": {
    "addr:full":"Kapellestraat 18 Oostende West-Vlaanderen 8400",
    "addr:housenumber":"18",
    "addr:postcode":"8400",
    "addr:street":"Kapellestraat",
    "iso:country":"BE",
    "sg:address":"Kapellestraat 18",
    "sg:city":"Oostende",
    "sg:orig_category":"Extrazone and HVH Speelgoed",
    "sg:phone":"+32 59 51 19 07",
    "sg:postcode":"8400",
    "sg:province":"West-Vlaanderen",
    "wof:name":"Extrazone Oostende",
    "wof:placetype":"venue"
},
  "geometry": {"coordinates":[2.9182980061,51.2310447693],"type":"Point"}
}