{
  "type": "Feature",
  "properties": {
    "iso:country":"BE",
    "sg:address":"Rue Du Tilleul 20",
    "sg:city":"Hamoir",
    "sg:orig_category":"Verhuur cateringmateriaal and evenementuitrusting Verhuur televisie- and audiovisuele apparatuur",
    "sg:phone":"+32 86 38 77 02",
    "sg:postcode":"4180",
    "sg:province":"Li\u00e8ge",
    "wof:name":"Productions Events",
    "wof:placetype":"venue"
},
  "geometry": {"coordinates":[5.5428791046,50.4448242188],"type":"Point"}
}