{
  "type": "Feature",
  "properties": {
    "iso:country":"BE",
    "sg:address":"Lieven Bauwensstraat 29",
    "sg:city":"Brugge",
    "sg:orig_category":"D\u00e9corateurs d'int\u00e9rieur",
    "sg:phone":"+32 50 45 66 77",
    "sg:postcode":"8200",
    "sg:province":"West-Vlaanderen",
    "wof:name":"Archimed",
    "wof:placetype":"venue"
},
  "geometry": {"coordinates":[3.1960539818,51.2144622803],"type":"Point"}
}