{
  "type": "Feature",
  "properties": {
    "iso:country":"BE",
    "sg:address":"Blekersdijk 13",
    "sg:city":"Gent",
    "sg:classifiers":[
        {
            "category":"Health Services",
            "subcategory":"Doctor",
            "type":"Services"
        }
    ],
    "sg:phone":"+32 9 223 07 97",
    "sg:postcode":"9000",
    "sg:province":"Oost-Vlaanderen",
    "sg:tags":[
        "psychotherapist",
        "psychoanalyst"
    ],
    "wof:name":"Vrijgeleide (het)",
    "wof:placetype":"venue"
},
  "geometry": {"coordinates":[3.7306270599,51.0598754883],"type":"Point"}
}