{
  "type": "Feature",
  "properties": {
    "addr:full":"Ringvaartstraat 25 Merelbeke Oost-Vlaanderen 9820",
    "addr:housenumber":"25",
    "addr:postcode":"9820",
    "addr:street":"Ringvaartstraat",
    "iso:country":"BE",
    "sg:address":"Ringvaartstraat 25",
    "sg:city":"Merelbeke",
    "sg:classifiers":[
        {
            "category":"Professional",
            "subcategory":"Management & Consulting",
            "type":"Services"
        }
    ],
    "sg:phone":"+32 9 252 66 37",
    "sg:postcode":"9820",
    "sg:province":"Oost-Vlaanderen",
    "sg:tags":[
        "marketing",
        "-",
        "consultant"
    ],
    "wof:name":"Carnac Bvba",
    "wof:placetype":"venue"
},
  "geometry": {"coordinates":[3.7524929047,51.0102272034],"type":"Point"}
}