{
  "type": "Feature",
  "properties": {
    "addr:full":"Moerplas 113 Puurs Antwerpen 2870",
    "addr:housenumber":"113",
    "addr:postcode":"2870",
    "addr:street":"Moerplas",
    "iso:country":"BE",
    "sg:address":"Moerplas 113",
    "sg:city":"Puurs",
    "sg:classifiers":[
        {
            "category":"Shopping",
            "subcategory":"Pets & Pet Supplies",
            "type":"Retail Goods"
        }
    ],
    "sg:phone":"+32 3 886 56 34",
    "sg:postcode":"2870",
    "sg:province":"Antwerpen",
    "sg:tags":[
        "shop",
        "-"
    ],
    "wof:name":"Claes J",
    "wof:placetype":"venue"
},
  "geometry": {"coordinates":[4.3169541359,51.0817718506],"type":"Point"}
}