{
  "type": "Feature",
  "properties": {
    "addr:full":"Rue D'ormont 46 Tournai (kain) Hainaut 7540",
    "addr:housenumber":"46",
    "addr:postcode":"7540",
    "addr:street":"Rue D'Ormont",
    "iso:country":"BE",
    "sg:address":"Rue D'ormont 46",
    "sg:city":"Tournai (kain)",
    "sg:classifiers":[
        {
            "category":"Insurance",
            "subcategory":"Insurance Agent",
            "type":"Services"
        }
    ],
    "sg:phone":"+32 69 21 38 70",
    "sg:postcode":"7540",
    "sg:province":"Hainaut",
    "sg:tags":[
        "broker"
    ],
    "wof:name":"Balthasar Ch",
    "wof:placetype":"venue"
},
  "geometry": {"coordinates":[3.3700749874,50.6374588013],"type":"Point"}
}