{
  "type": "Feature",
  "properties": {
    "iso:country":"BE",
    "sg:address":"Anjelierstraat 25",
    "sg:city":"Gent",
    "sg:orig_category":"Elektrische installaties voor woningen",
    "sg:phone":"+32 9 227 26 02",
    "sg:postcode":"9000",
    "sg:province":"Oost-Vlaanderen",
    "wof:name":"Fa. A.a.a. Servelek",
    "wof:placetype":"venue"
},
  "geometry": {"coordinates":[3.7125110626,51.0729217529],"type":"Point"}
}