{
  "type": "Feature",
  "properties": {
    "iso:country":"BE",
    "sg:address":"Lammerdries 12",
    "sg:city":"Geel",
    "sg:orig_category":"Imprimeries and copyshops",
    "sg:phone":"+32 14 23 71 14",
    "sg:postcode":"2440",
    "sg:province":"Antwerpen",
    "wof:name":"Goedhart Repro",
    "wof:placetype":"venue"
},
  "geometry": {"coordinates":[4.9223408699,51.1459121704],"type":"Point"}
}