{
  "type": "Feature",
  "properties": {
    "addr:full":"Avenue Houba De Strooper 66 Brussel/bruxelles Bruxelles-Capitale 1020",
    "addr:housenumber":"66",
    "addr:postcode":"1020",
    "addr:street":"Avenue Houba De Strooper;/",
    "iso:country":"BE",
    "sg:address":"Avenue Houba De Strooper 66",
    "sg:city":"Brussel/bruxelles",
    "sg:orig_category":"D\u00e9corateurs d'int\u00e9rieur",
    "sg:phone":"+32 2 479 25 53",
    "sg:postcode":"1020",
    "sg:province":"Bruxelles-Capitale",
    "wof:name":"Bureau Fiscart & Cie",
    "wof:placetype":"venue"
},
  "geometry": {"coordinates":[4.3401942253,50.8872451782],"type":"Point"}
}