{
  "type": "Feature",
  "properties": {
    "addr:full":"Alsembergse Steenweg 626 Ukkel/uccle Bruxelles-Capitale 1180",
    "addr:housenumber":"626",
    "addr:postcode":"1180",
    "addr:street":"Alsembergse Steenweg;/",
    "iso:country":"BE",
    "sg:address":"Alsembergse Steenweg 626",
    "sg:city":"Ukkel/uccle",
    "sg:orig_category":"Boekhouders",
    "sg:phone":"+32 2 343 30 24",
    "sg:postcode":"1180",
    "sg:province":"Bruxelles-Capitale",
    "wof:name":"Myriam Delporte",
    "wof:placetype":"venue"
},
  "geometry": {"coordinates":[4.336991787,50.8045654297],"type":"Point"}
}