{
  "type": "Feature",
  "properties": {
    "addr:full":"Rue Gillot 119 Charleroi Hainaut 6061",
    "addr:housenumber":"119",
    "addr:postcode":"6061",
    "addr:street":"Rue Gillot;Hainaut",
    "iso:country":"BE",
    "sg:address":"Rue Gillot 119",
    "sg:city":"Charleroi",
    "sg:orig_category":"Produits chimiques Gr",
    "sg:phone":"+32 71 30 16 66",
    "sg:postcode":"6061",
    "sg:province":"Hainaut",
    "wof:name":"Jec Chimie",
    "wof:placetype":"venue"
},
  "geometry": {"coordinates":[4.4720702171,50.4008216858],"type":"Point"}
}