{
  "type": "Feature",
  "properties": {
    "addr:full":"Steenweg Op Bergen 570 Anderlecht Bruxelles-Capitale 1070",
    "addr:housenumber":"570",
    "addr:postcode":"1070",
    "addr:street":"Steenweg Op Bergen",
    "iso:country":"BE",
    "sg:address":"Steenweg Op Bergen 570",
    "sg:city":"Anderlecht",
    "sg:orig_category":"Slagers",
    "sg:phone":"+32 2 520 86 04",
    "sg:postcode":"1070",
    "sg:province":"Bruxelles-Capitale",
    "wof:name":"Renmans",
    "wof:placetype":"venue"
},
  "geometry": {"coordinates":[4.312125206,50.8324508667],"type":"Point"}
}