{
  "type": "Feature",
  "properties": {
    "iso:country":"BE",
    "sg:address":"Chauss\u00c9e De Bruxelles 12",
    "sg:city":"Vorst/forest",
    "sg:orig_category":"Boucheries",
    "sg:phone":"+32 2 332 33 24",
    "sg:postcode":"1190",
    "sg:province":"Bruxelles-Capitale",
    "wof:name":"El Kheir",
    "wof:placetype":"venue"
},
  "geometry": {"coordinates":[4.3176999092,50.8106117249],"type":"Point"}
}