{
  "type": "Feature",
  "properties": {
    "addr:full":"Provincieweg 259 Herzele (hillegem) Oost-Vlaanderen 9550",
    "addr:housenumber":"259",
    "addr:postcode":"9550",
    "addr:street":"Provincieweg",
    "iso:country":"BE",
    "sg:address":"Provincieweg 259",
    "sg:city":"Herzele (hillegem)",
    "sg:classifiers":[
        {
            "category":"Home & Garden",
            "subcategory":"Building Materials",
            "type":"Retail Goods"
        }
    ],
    "sg:phone":"+32 53 62 90 72",
    "sg:postcode":"9550",
    "sg:province":"Oost-Vlaanderen",
    "sg:tags":[
        "granite",
        "stone",
        "natural",
        "marble"
    ],
    "wof:name":"Verhelst G",
    "wof:placetype":"venue"
},
  "geometry": {"coordinates":[3.8787400723,50.8998908997],"type":"Point"}
}