{
  "type": "Feature",
  "properties": {
    "iso:country":"BE",
    "sg:address":"Zonnebloemstraat 18",
    "sg:city":"Geraardsbergen",
    "sg:orig_category":"Herstellingen and onderhoud van auto's Voertuigen",
    "sg:phone":"+32 54 41 12 03",
    "sg:postcode":"9500",
    "sg:province":"Oost-Vlaanderen",
    "wof:name":"Autobedrijf Condijts",
    "wof:placetype":"venue"
},
  "geometry": {"coordinates":[3.888739109,50.7772712708],"type":"Point"}
}