{
  "type": "Feature",
  "properties": {
    "iso:country":"BE",
    "sg:address":"Lettenburgstraat 15",
    "sg:city":"Diksmuide",
    "sg:classifiers":[
        {
            "category":"Restaurant",
            "type":"Food & Drink"
        }
    ],
    "sg:phone":"+32 51 55 57 83",
    "sg:postcode":"8600",
    "sg:province":"West-Vlaanderen",
    "wof:name":"Lettenburg Gasthof",
    "wof:placetype":"venue"
},
  "geometry": {"coordinates":[2.8109099865,51.0471687317],"type":"Point"}
}