{
  "type": "Feature",
  "properties": {
    "addr:full":"Gistelstraat 106 Ingelmunster West-Vlaanderen 8770",
    "addr:housenumber":"106",
    "addr:postcode":"8770",
    "addr:street":"Gistelstraat",
    "iso:country":"BE",
    "sg:address":"Gistelstraat 106",
    "sg:city":"Ingelmunster",
    "sg:classifiers":[
        {
            "category":"Banks & Credit Unions",
            "subcategory":"Investment Brokerage",
            "type":"Services"
        }
    ],
    "sg:phone":"+32 51 30 51 91",
    "sg:postcode":"8770",
    "sg:province":"West-Vlaanderen",
    "sg:tags":[
        "repair",
        "-",
        "installation",
        "sanitary",
        "article"
    ],
    "wof:name":"Delbeke R",
    "wof:placetype":"venue"
},
  "geometry": {"coordinates":[3.2374010086,50.9305381775],"type":"Point"}
}