{
  "type": "Feature",
  "properties": {
    "addr:full":"Sint-andreasstraat 8 Lommel Limburg 3920",
    "addr:housenumber":"8",
    "addr:postcode":"3920",
    "addr:street":"Sint-Andreasstraat",
    "iso:country":"BE",
    "sg:address":"Sint-andreasstraat 8",
    "sg:city":"Lommel",
    "sg:orig_category":"Elektrische installaties voor woningen",
    "sg:phone":"+32 11 64 41 76",
    "sg:postcode":"3920",
    "sg:province":"Limburg",
    "wof:name":"Stefan Geerits",
    "wof:placetype":"venue"
},
  "geometry": {"coordinates":[5.3829469681,51.2509422302],"type":"Point"}
}