{
  "type": "Feature",
  "properties": {
    "iso:country":"BE",
    "sg:address":"Chauss\u00c9e Reine Atrid 39",
    "sg:city":"Braine-l`alleud",
    "sg:orig_category":"Artsen and specialisten",
    "sg:phone":"+32 2 384 14 66",
    "sg:postcode":"1420",
    "sg:province":"Brabant Wallon",
    "wof:name":"Stinglhamber R.",
    "wof:placetype":"venue"
},
  "geometry": {"coordinates":[5.8036999702,45.9799995422],"type":"Point"}
}