{
  "type": "Feature",
  "properties": {
    "iso:country":"BE",
    "sg:address":"Statiestraat 44",
    "sg:city":"Mol",
    "sg:orig_category":"Kapsalons",
    "sg:phone":"+32 14 31 68 78",
    "sg:postcode":"2400",
    "sg:province":"Antwerpen",
    "wof:name":"Buzzi & Ko Casual",
    "wof:placetype":"venue"
},
  "geometry": {"coordinates":[5.1182022095,51.1898498535],"type":"Point"}
}