{
  "type": "Feature",
  "properties": {
    "addr:full":"Dorp 130 Assenede (bassevelde) Oost-Vlaanderen 9968",
    "addr:housenumber":"130",
    "addr:postcode":"9968",
    "addr:street":"Dorp",
    "iso:country":"BE",
    "sg:address":"Dorp 130",
    "sg:city":"Assenede (bassevelde)",
    "sg:classifiers":[
        {
            "category":"Real Estate",
            "subcategory":"Architect",
            "type":"Services"
        }
    ],
    "sg:phone":"+32 9 373 61 29",
    "sg:postcode":"9968",
    "sg:province":"Oost-Vlaanderen",
    "wof:name":"De Pape M",
    "wof:placetype":"venue"
},
  "geometry": {"coordinates":[3.6887938976,51.1923027039],"type":"Point"}
}