{
  "type": "Feature",
  "properties": {
    "addr:full":"Chauss\u00c9e De Dinant 143 Anhee Namur 5537",
    "addr:housenumber":"143",
    "addr:postcode":"5537",
    "addr:street":"Chausse\u0301E De Dinant;Namur",
    "iso:country":"BE",
    "sg:address":"Chauss\u00c9e De Dinant 143",
    "sg:city":"Anhee",
    "sg:orig_category":"Bloemen and planten Boomkwekerijen Geschenken and souvenirs Tuinbenodigdheden Tuinen",
    "sg:phone":"+32 82 61 45 62",
    "sg:postcode":"5537",
    "sg:province":"Namur",
    "wof:name":"Verts Espaces",
    "wof:placetype":"venue"
},
  "geometry": {"coordinates":[4.8936080933,50.2961120605],"type":"Point"}
}