{
  "type": "Feature",
  "properties": {
    "addr:full":"Oude Koornmarkt 36 Antwerpen Antwerpen 2000",
    "addr:housenumber":"36",
    "addr:postcode":"2000",
    "addr:street":"Oude Koornmarkt",
    "iso:country":"BE",
    "sg:address":"Oude Koornmarkt 36",
    "sg:city":"Antwerpen",
    "sg:classifiers":[
        {
            "category":"Building & Trades",
            "subcategory":"Cleaning & Sanitation",
            "type":"Services"
        }
    ],
    "sg:phone":"+32 3 213 32 67",
    "sg:postcode":"2000",
    "sg:province":"Antwerpen",
    "sg:tags":[
        "fa\u00e7ade",
        "maintenance"
    ],
    "wof:name":"A.s.a. Aannemersbedrijf",
    "wof:placetype":"venue"
},
  "geometry": {"coordinates":[4.3999471664,51.2198982239],"type":"Point"}
}