{
  "type": "Feature",
  "properties": {
    "addr:full":"Avenue Des Rogations 37 Bruxelles (woluwe-saint-lambert) Bruxelles-Capitale 1200",
    "addr:housenumber":"37",
    "addr:postcode":"1200",
    "addr:street":"Avenue Des Rogations",
    "iso:country":"BE",
    "sg:address":"Avenue Des Rogations 37",
    "sg:city":"Bruxelles (woluwe-saint-lambert)",
    "sg:classifiers":[
        {
            "category":"Retail",
            "subcategory":"Veterinary Services",
            "type":"Services"
        }
    ],
    "sg:phone":"+32 2 736 14 14",
    "sg:postcode":"1200",
    "sg:province":"Bruxelles-Capitale",
    "sg:tags":[
        "veterinarian"
    ],
    "wof:name":"Devaux E",
    "wof:placetype":"venue"
},
  "geometry": {"coordinates":[4.4040617943,50.8425559998],"type":"Point"}
}