{
  "type": "Feature",
  "properties": {
    "iso:country":"BE",
    "sg:address":"Rue Jean Servais 24",
    "sg:city":"Fl\u00e9malle (awirs)",
    "sg:classifiers":[
        {
            "category":"Professional",
            "subcategory":"Engineering",
            "type":"Services"
        }
    ],
    "sg:phone":"+32 4 275 39 05",
    "sg:postcode":"4400",
    "sg:province":"Li\u00e8ge",
    "sg:tags":[
        "industrial",
        "-",
        "automation"
    ],
    "wof:name":"Malau Service",
    "wof:placetype":"venue"
},
  "geometry": {"coordinates":[5.4178109169,50.5994262695],"type":"Point"}
}