{
  "type": "Feature",
  "properties": {
    "addr:full":"Hoogstraat 11 Haaltert Oost-Vlaanderen 9450",
    "addr:housenumber":"11",
    "addr:postcode":"9450",
    "addr:street":"Hoogstraat",
    "iso:country":"BE",
    "sg:address":"Hoogstraat 11",
    "sg:city":"Haaltert",
    "sg:orig_category":"Boucheries",
    "sg:phone":"+32 53 83 84 70",
    "sg:postcode":"9450",
    "sg:province":"Oost-Vlaanderen",
    "wof:name":"Patricia Wellekens",
    "wof:placetype":"venue"
},
  "geometry": {"coordinates":[4.004720211,50.9002914429],"type":"Point"}
}