{
  "type": "Feature",
  "properties": {
    "iso:country":"BE",
    "sg:address":"Boulevard De La Sauveni\u00e8re 30",
    "sg:city":"Li\u00e8ge 1",
    "sg:classifiers":[
        {
            "category":"Social Services",
            "type":"Services"
        }
    ],
    "sg:phone":"+32 4 222 91 20",
    "sg:postcode":"4000",
    "sg:province":"Li\u00e8ge",
    "wof:name":"Service Droit Des Jeunes De Li\u00e8ge Asbl",
    "wof:placetype":"venue"
},
  "geometry": {"coordinates":[5.5688009262,50.6443862915],"type":"Point"}
}