{
  "type": "Feature",
  "properties": {
    "iso:country":"BE",
    "sg:address":"Beekstraat 20",
    "sg:city":"Sint-truiden",
    "sg:classifiers":[
        {
            "category":"Professional",
            "subcategory":"Management & Consulting",
            "type":"Services"
        }
    ],
    "sg:phone":"+32 11 69 45 67",
    "sg:postcode":"3800",
    "sg:province":"Limburg",
    "sg:tags":[
        "consultant",
        "law"
    ],
    "wof:name":"Govaerts Geert",
    "wof:placetype":"venue"
},
  "geometry": {"coordinates":[5.1841788292,50.815536499],"type":"Point"}
}