{
  "type": "Feature",
  "properties": {
    "iso:country":"BE",
    "sg:address":"Hazendreef 51",
    "sg:city":"Hoeilaart",
    "sg:classifiers":[
        {
            "category":"Cafe",
            "type":"Food & Drink"
        }
    ],
    "sg:phone":"+32 2 657 53 81",
    "sg:postcode":"1560",
    "sg:province":"Vlaams-Brabant",
    "sg:tags":[
        "caf\u00e9s"
    ],
    "wof:name":"Willy Bergiers",
    "wof:placetype":"venue"
},
  "geometry": {"coordinates":[4.4727129936,50.7538337708],"type":"Point"}
}