{
  "type": "Feature",
  "properties": {
    "addr:full":"Rue Des Coteaux 138 Bruxelles (schaerbeek) Bruxelles-Capitale 1030",
    "addr:housenumber":"138",
    "addr:postcode":"1030",
    "addr:street":"Rue Des Coteaux",
    "iso:country":"BE",
    "sg:address":"Rue Des Coteaux 138",
    "sg:city":"Bruxelles (schaerbeek)",
    "sg:classifiers":[
        {
            "category":"Manufacturing",
            "subcategory":"Textiles",
            "type":"Manufacturing & Wholesale Goods"
        }
    ],
    "sg:phone":"+32 2 215 52 32",
    "sg:postcode":"1030",
    "sg:province":"Bruxelles-Capitale",
    "sg:tags":[
        "retail",
        "-"
    ],
    "wof:name":"Rahana",
    "wof:placetype":"venue"
},
  "geometry": {"coordinates":[4.3766851425,50.8582000732],"type":"Point"}
}