{
  "type": "Feature",
  "properties": {
    "iso:country":"BE",
    "sg:address":"Nachtegaalstraat 77",
    "sg:city":"Zulte",
    "sg:orig_category":"Cad/Cam systems",
    "sg:phone":"+32 9 388 94 89",
    "sg:postcode":"9870",
    "sg:province":"Oost-Vlaanderen",
    "wof:name":"V I A Bvba",
    "wof:placetype":"venue"
},
  "geometry": {"coordinates":[3.4554729462,50.9222106934],"type":"Point"}
}