{
  "type": "Feature",
  "properties": {
    "addr:full":"Bilzersteenweg 11 Hoeselt Limburg 3730",
    "addr:housenumber":"11",
    "addr:postcode":"3730",
    "addr:street":"Bilzersteenweg",
    "iso:country":"BE",
    "sg:address":"Bilzersteenweg 11",
    "sg:city":"Hoeselt",
    "sg:orig_category":"V\u00e9t\u00e9rinaires",
    "sg:phone":"+32 89 41 54 53",
    "sg:postcode":"3730",
    "sg:province":"Limburg",
    "wof:name":"David Voes",
    "wof:placetype":"venue"
},
  "geometry": {"coordinates":[5.4922380447,50.8509521484],"type":"Point"}
}