{
  "type": "Feature",
  "properties": {
    "iso:country":"BE",
    "sg:address":"Diestsesteenweg 201b",
    "sg:city":"Lubbeek (linden)",
    "sg:classifiers":[
        {
            "category":"Retail",
            "subcategory":"Car Wash",
            "type":"Services"
        }
    ],
    "sg:phone":"+32 16 62 36 41",
    "sg:postcode":"3210",
    "sg:province":"Vlaams-Brabant",
    "sg:tags":[
        "automobile",
        "washing",
        "-",
        "truck"
    ],
    "wof:name":"Mr Shine",
    "wof:placetype":"venue"
},
  "geometry": {"coordinates":[4.8095397949,50.8933792114],"type":"Point"}
}