{
  "type": "Feature",
  "properties": {
    "iso:country":"BE",
    "sg:address":"Kikkerstraat 32",
    "sg:city":"Lommel",
    "sg:orig_category":"Eleveurs de bovins",
    "sg:phone":"+32 11 54 12 18",
    "sg:postcode":"3920",
    "sg:province":"Limburg",
    "wof:name":"Henricus Jansen",
    "wof:placetype":"venue"
},
  "geometry": {"coordinates":[5.3218121529,51.2182769775],"type":"Point"}
}