{
  "type": "Feature",
  "properties": {
    "addr:full":"Dorp 24 Zoersel Antwerpen 2980",
    "addr:housenumber":"24",
    "addr:postcode":"2980",
    "addr:street":"Dorp",
    "iso:country":"BE",
    "sg:address":"Dorp 24",
    "sg:city":"Zoersel",
    "sg:orig_category":"S\u00e9curit\u00e9 sociale",
    "sg:phone":"+32 3 309 12 06",
    "sg:postcode":"2980",
    "sg:province":"Antwerpen",
    "wof:name":"Socialist. Mutualiteit",
    "wof:placetype":"venue"
},
  "geometry": {"coordinates":[4.7129092216,51.2684173584],"type":"Point"}
}