{
  "type": "Feature",
  "properties": {
    "addr:full":"Avenue Pieter Goedefroy 1 Ganshoren/ganshoren Bruxelles-Capitale 1083",
    "addr:housenumber":"1",
    "addr:postcode":"1083",
    "addr:street":"Avenue Pieter Goedefroy",
    "iso:country":"BE",
    "sg:address":"Avenue Pieter Goedefroy 1",
    "sg:city":"Ganshoren/ganshoren",
    "sg:orig_category":"Banques and organismes de cr\u00e9dit",
    "sg:phone":"+32 2 426 94 94",
    "sg:postcode":"1083",
    "sg:province":"Bruxelles-Capitale",
    "wof:name":"Cbc",
    "wof:placetype":"venue"
},
  "geometry": {"coordinates":[4.3146858215,50.8729667664],"type":"Point"}
}