{
  "type": "Feature",
  "properties": {
    "iso:country":"BE",
    "sg:address":"Rue Chambrie 1",
    "sg:city":"Remicourt (pousset)",
    "sg:classifiers":[
        {
            "category":"Building & Trades",
            "subcategory":"Plumbing",
            "type":"Services"
        }
    ],
    "sg:phone":"+32 19 69 77 01",
    "sg:postcode":"4350",
    "sg:province":"Li\u00e8ge",
    "sg:tags":[
        "repair",
        "mainten",
        "-",
        "central",
        "heating"
    ],
    "wof:name":"Lardinois D",
    "wof:placetype":"venue"
},
  "geometry": {"coordinates":[5.329395771,50.6783905029],"type":"Point"}
}