{
  "type": "Feature",
  "properties": {
    "iso:country":"BE",
    "sg:address":"Rue Fran\u00c7ois Vekemans 99",
    "sg:city":"Brussel/bruxelles",
    "sg:orig_category":"Boucheries",
    "sg:phone":"+32 2 262 01 33",
    "sg:postcode":"1120",
    "sg:province":"Bruxelles-Capitale",
    "wof:name":"Boucherie Brabant",
    "wof:placetype":"venue"
},
  "geometry": {"coordinates":[4.3877248764,50.8950271606],"type":"Point"}
}