{
  "type": "Feature",
  "properties": {
    "iso:country":"BE",
    "sg:address":"Molderbeemdendijk 23",
    "sg:city":"Geel",
    "sg:orig_category":"Jardinage. Fleurs and plantes",
    "sg:phone":"+32 14 58 75 91",
    "sg:postcode":"2440",
    "sg:province":"Antwerpen",
    "wof:name":"Frans Vervoort",
    "wof:placetype":"venue"
},
  "geometry": {"coordinates":[4.9816069603,51.1839408875],"type":"Point"}
}