{
  "type": "Feature",
  "properties": {
    "addr:full":"Rue Gaston Gailliez 4 Estinnes Hainaut 7120",
    "addr:housenumber":"4",
    "addr:postcode":"7120",
    "addr:street":"Rue Gaston Gailliez",
    "iso:country":"BE",
    "sg:address":"Rue Gaston Gailliez 4",
    "sg:city":"Estinnes",
    "sg:orig_category":"Eleveurs de bovins. Combustibles",
    "sg:phone":"+32 65 58 68 90",
    "sg:postcode":"7120",
    "sg:province":"Hainaut",
    "wof:name":"Maurice Durigneux",
    "wof:placetype":"venue"
},
  "geometry": {"coordinates":[4.0588569641,50.4019966125],"type":"Point"}
}