{
  "type": "Feature",
  "properties": {
    "addr:full":"Drongenplein 25 Gent (drongen) Oost-Vlaanderen 9031",
    "addr:housenumber":"25",
    "addr:postcode":"9031",
    "addr:street":"Drongenplein",
    "iso:country":"BE",
    "sg:address":"Drongenplein 25",
    "sg:city":"Gent (drongen)",
    "sg:classifiers":[
        {
            "category":"Bars & Pubs",
            "type":"Food & Drink"
        }
    ],
    "sg:phone":"+32 9 227 79 91",
    "sg:postcode":"9031",
    "sg:province":"Oost-Vlaanderen",
    "wof:name":"Gouden Leeuw (de)",
    "wof:placetype":"venue"
},
  "geometry": {"coordinates":[3.6627590656,51.0503349304],"type":"Point"}
}