{
  "type": "Feature",
  "properties": {
    "iso:country":"BE",
    "sg:address":"Rue De L\u00b4eglise 11",
    "sg:city":"Seraing",
    "sg:orig_category":"Pharmaciens",
    "sg:phone":"+32 4 336 11 26",
    "sg:postcode":"4100",
    "sg:province":"Li\u00e8ge",
    "wof:name":"Pharmacie R. Walnier",
    "wof:placetype":"venue"
},
  "geometry": {"coordinates":[5.5135030746,50.6105766296],"type":"Point"}
}