{
  "type": "Feature",
  "properties": {
    "addr:full":"Kerkstraat 16 Bredene West-Vlaanderen 8450",
    "addr:housenumber":"16",
    "addr:postcode":"8450",
    "addr:street":"Kerkstraat",
    "iso:country":"BE",
    "sg:address":"Kerkstraat 16",
    "sg:city":"Bredene",
    "sg:orig_category":"M\u00e9decins and sp\u00e9cialistes",
    "sg:phone":"+32 59 32 04 77",
    "sg:postcode":"8450",
    "sg:province":"West-Vlaanderen",
    "wof:name":"Consultatiebur.jonge Kind",
    "wof:placetype":"venue"
},
  "geometry": {"coordinates":[2.9507439137,51.2228622437],"type":"Point"}
}