{
  "type": "Feature",
  "properties": {
    "addr:full":"Albertlaan 19 Aarschot Vlaams-Brabant 3200",
    "addr:housenumber":"19",
    "addr:postcode":"3200",
    "addr:street":"Albertlaan",
    "iso:country":"BE",
    "sg:address":"Albertlaan 19",
    "sg:city":"Aarschot",
    "sg:orig_category":"Binnenhuisarchitecten",
    "sg:phone":"+32 16 56 07 10",
    "sg:postcode":"3200",
    "sg:province":"Vlaams-Brabant",
    "wof:name":"Katrin Serneels",
    "wof:placetype":"venue"
},
  "geometry": {"coordinates":[4.8281788826,50.9842453003],"type":"Point"}
}