{
  "type": "Feature",
  "properties": {
    "iso:country":"BE",
    "sg:address":"Rue Du Tige 23",
    "sg:city":"Gembloux-sur-orneau (gembloux)",
    "sg:classifiers":[
        {
            "category":"Building & Trades",
            "subcategory":"Cleaning & Sanitation",
            "type":"Services"
        }
    ],
    "sg:phone":"+32 10 84 33 56",
    "sg:postcode":"5030",
    "sg:province":"Namur",
    "sg:tags":[
        "cleaner",
        "window"
    ],
    "wof:name":"Net & Coo Sprl",
    "wof:placetype":"venue"
},
  "geometry": {"coordinates":[4.7284960747,50.5915145874],"type":"Point"}
}