{
  "type": "Feature",
  "properties": {
    "addr:full":"Brouwerijstraat 34 Hulshout Antwerpen 2235",
    "addr:housenumber":"34",
    "addr:postcode":"2235",
    "addr:street":"Brouwerijstraat",
    "iso:country":"BE",
    "sg:address":"Brouwerijstraat 34",
    "sg:city":"Hulshout",
    "sg:orig_category":"Fitnesscentra",
    "sg:phone":"+32 15 22 01 70",
    "sg:postcode":"2235",
    "sg:province":"Antwerpen",
    "wof:name":"Indoor Fitness",
    "wof:placetype":"venue"
},
  "geometry": {"coordinates":[4.784828186,51.0777511597],"type":"Point"}
}