{
  "type": "Feature",
  "properties": {
    "addr:full":"Kloosterstraat 72a Merelbeke Oost-Vlaanderen 9820",
    "addr:housenumber":"72a",
    "addr:postcode":"9820",
    "addr:street":"Kloosterstraat",
    "iso:country":"BE",
    "sg:address":"Kloosterstraat 72a",
    "sg:city":"Merelbeke",
    "sg:classifiers":[
        {
            "category":"Insurance",
            "subcategory":"Insurance Agent",
            "type":"Services"
        }
    ],
    "sg:phone":"+32 9 232 02 00",
    "sg:postcode":"9820",
    "sg:province":"Oost-Vlaanderen",
    "sg:tags":[
        "broker"
    ],
    "wof:name":"Parmentier P",
    "wof:placetype":"venue"
},
  "geometry": {"coordinates":[3.7537128925,50.9897346497],"type":"Point"}
}