{
  "type": "Feature",
  "properties": {
    "iso:country":"BE",
    "sg:address":"Rotelenberg 20",
    "sg:city":"Oudenaarde",
    "sg:orig_category":"Zuivelproducten",
    "sg:phone":"+32 55 31 16 93",
    "sg:postcode":"9700",
    "sg:province":"Oost-Vlaanderen",
    "wof:name":"Jean-pierre Dekeyser",
    "wof:placetype":"venue"
},
  "geometry": {"coordinates":[3.5727620125,50.8105278015],"type":"Point"}
}