{
  "type": "Feature",
  "properties": {
    "addr:full":"Verschansingstraat 63 Antwerpen Antwerpen 2000",
    "addr:housenumber":"63",
    "addr:postcode":"2000",
    "addr:street":"Verschansingstraat",
    "iso:country":"BE",
    "sg:address":"Verschansingstraat 63",
    "sg:city":"Antwerpen",
    "sg:classifiers":[
        {
            "category":"Cafe",
            "type":"Food & Drink"
        }
    ],
    "sg:phone":"+32 3 216 36 65",
    "sg:postcode":"2000",
    "sg:province":"Antwerpen",
    "sg:tags":[
        "caf\u00e9s"
    ],
    "wof:name":"De Muziekdoos",
    "wof:placetype":"venue"
},
  "geometry": {"coordinates":[4.3894348145,51.2080574036],"type":"Point"}
}