{
  "type": "Feature",
  "properties": {
    "addr:full":"Mandellaan 590 Roeselare West-Vlaanderen 8800",
    "addr:housenumber":"590",
    "addr:postcode":"8800",
    "addr:street":"Mandellaan",
    "iso:country":"BE",
    "sg:address":"Mandellaan 590",
    "sg:city":"Roeselare",
    "sg:classifiers":[
        {
            "category":"Professional",
            "subcategory":"Art Services",
            "type":"Services"
        }
    ],
    "sg:phone":"+32 51 24 43 36",
    "sg:postcode":"8800",
    "sg:province":"West-Vlaanderen",
    "sg:tags":[
        "graphic",
        "designer"
    ],
    "wof:name":"G.l.e.",
    "wof:placetype":"venue"
},
  "geometry": {"coordinates":[3.1526479721,50.9375305176],"type":"Point"}
}