{
  "type": "Feature",
  "properties": {
    "addr:full":"All\u00c9e Du Ch\u00c2teau 8 Morlanwelz Hainaut 7140",
    "addr:housenumber":"8",
    "addr:postcode":"7140",
    "addr:street":"Alle\u0301E Du Cha\u0302Teau",
    "iso:country":"BE",
    "sg:address":"All\u00c9e Du Ch\u00c2teau 8",
    "sg:city":"Morlanwelz",
    "sg:orig_category":"Boekhouders",
    "sg:phone":"+32 64 22 02 02",
    "sg:postcode":"7140",
    "sg:province":"Hainaut",
    "wof:name":"Michel Dominique",
    "wof:placetype":"venue"
},
  "geometry": {"coordinates":[4.2256798744,50.4653396606],"type":"Point"}
}