{
  "type": "Feature",
  "properties": {
    "iso:country":"BE",
    "sg:address":"Vrijheidslaan 2",
    "sg:city":"Sint-truiden",
    "sg:classifiers":[
        {
            "category":"Arena",
            "subcategory":"Sports Club",
            "type":"Entertainment"
        }
    ],
    "sg:phone":"+32 11 68 31 12",
    "sg:postcode":"3803",
    "sg:province":"Limburg",
    "sg:tags":[
        "de"
    ],
    "wof:name":"Wtc Beringen Vzw",
    "wof:placetype":"venue"
},
  "geometry": {"coordinates":[5.14351511,50.8200912476],"type":"Point"}
}