{
  "type": "Feature",
  "properties": {
    "addr:full":"Maastrichterstraat 39 Tongeren Limburg 3700",
    "addr:housenumber":"39",
    "addr:postcode":"3700",
    "addr:street":"Maastrichterstraat",
    "iso:country":"BE",
    "sg:address":"Maastrichterstraat 39",
    "sg:city":"Tongeren",
    "sg:classifiers":[
        {
            "category":"Manufacturing",
            "subcategory":"Textiles",
            "type":"Manufacturing & Wholesale Goods"
        }
    ],
    "sg:phone":"+32 12 23 39 41",
    "sg:postcode":"3700",
    "sg:province":"Limburg",
    "sg:tags":[
        "retail",
        "-"
    ],
    "wof:name":"Raepers Textiel",
    "wof:placetype":"venue"
},
  "geometry": {"coordinates":[5.4655680656,50.7818870544],"type":"Point"}
}