{
  "type": "Feature",
  "properties": {
    "addr:full":"Rue Haute 17 Soumagne (melen) Li\u00e8ge 4633",
    "addr:housenumber":"17",
    "addr:postcode":"4633",
    "addr:street":"Rue Haute;Melen",
    "iso:country":"BE",
    "sg:address":"Rue Haute 17",
    "sg:city":"Soumagne (melen)",
    "sg:classifiers":[
        {
            "category":"Retail",
            "subcategory":"Auto Repair",
            "type":"Services"
        }
    ],
    "sg:phone":"+32 4 377 55 76",
    "sg:postcode":"4633",
    "sg:province":"Li\u00e8ge",
    "sg:tags":[
        "automobile-body"
    ],
    "wof:name":"Lonneux A",
    "wof:placetype":"venue"
},
  "geometry": {"coordinates":[5.7406311035,50.6487426758],"type":"Point"}
}