{
  "type": "Feature",
  "properties": {
    "iso:country":"BE",
    "sg:address":"Twee Leeuwenstraat 8",
    "sg:city":"Kortenberg",
    "sg:orig_category":"Emballages en plastique Fab",
    "sg:phone":"+32 2 759 49 42",
    "sg:postcode":"3078",
    "sg:province":"Vlaams-Brabant",
    "wof:name":"Europack",
    "wof:placetype":"venue"
},
  "geometry": {"coordinates":[4.5717639923,50.8784484863],"type":"Point"}
}