{
  "type": "Feature",
  "properties": {
    "addr:full":"25-27-29 Rue De L'h\u00f4pital Bruxelles Bruxelles-Capitale 1000",
    "addr:housenumber":"25-27-29",
    "addr:postcode":"1000",
    "addr:street":"Rue De L'Ho \u0302Pital",
    "iso:country":"BE",
    "sg:address":"25-27-29 Rue De L'h\u00f4pital",
    "sg:city":"Bruxelles",
    "sg:classifiers":[
        {
            "category":"Home & Garden",
            "subcategory":"Furniture",
            "type":"Retail Goods"
        }
    ],
    "sg:phone":"+32 2 513 58 92",
    "sg:postcode":"1000",
    "sg:province":"Bruxelles-Capitale",
    "sg:tags":[
        "household",
        "wood"
    ],
    "wof:name":"Emery & Cie",
    "wof:placetype":"venue"
},
  "geometry": {"coordinates":[4.3537898064,50.8437995911],"type":"Point"}
}