{
  "type": "Feature",
  "properties": {
    "addr:full":"Hundelgemsesteenweg 929 Merelbeke Oost-Vlaanderen 9820",
    "addr:housenumber":"929",
    "addr:postcode":"9820",
    "addr:street":"Hundelgemsesteenweg",
    "iso:country":"BE",
    "sg:address":"Hundelgemsesteenweg 929",
    "sg:city":"Merelbeke",
    "sg:classifiers":[
        {
            "category":"Personal",
            "subcategory":"Beauty Salon",
            "type":"Services"
        }
    ],
    "sg:phone":"+32 9 362 88 41",
    "sg:postcode":"9820",
    "sg:province":"Oost-Vlaanderen",
    "sg:tags":[
        "de",
        "coiffure"
    ],
    "wof:name":"Coiffure Gwenny",
    "wof:placetype":"venue"
},
  "geometry": {"coordinates":[3.7398979664,50.96301651],"type":"Point"}
}