{
  "type": "Feature",
  "properties": {
    "iso:country":"BE",
    "sg:address":"Smalle Heerweg 160",
    "sg:city":"Lochristi",
    "sg:orig_category":"Varkenskwekers",
    "sg:phone":"+32 9 355 27 31",
    "sg:postcode":"9080",
    "sg:province":"Oost-Vlaanderen",
    "wof:name":"Mouton",
    "wof:placetype":"venue"
},
  "geometry": {"coordinates":[3.7996389866,51.0923423767],"type":"Point"}
}