{
  "type": "Feature",
  "properties": {
    "iso:country":"BE",
    "sg:address":"Rue Alphonse Thomas 6",
    "sg:city":"Berloz",
    "sg:orig_category":"Artsen and specialisten",
    "sg:phone":"+32 19 32 39 64",
    "sg:postcode":"4257",
    "sg:province":"Li\u00e8ge",
    "wof:name":"Jacques Missotten",
    "wof:placetype":"venue"
},
  "geometry": {"coordinates":[5.2113800049,50.7093887329],"type":"Point"}
}