{
  "type": "Feature",
  "properties": {
    "addr:full":"Westkerkestraat 5 Ichtegem (eernegem) West-Vlaanderen 8480",
    "addr:housenumber":"5",
    "addr:postcode":"8480",
    "addr:street":"Westkerkestraat",
    "iso:country":"BE",
    "sg:address":"Westkerkestraat 5",
    "sg:city":"Ichtegem (eernegem)",
    "sg:classifiers":[
        {
            "category":"Health Services",
            "subcategory":"Doctor",
            "type":"Services"
        }
    ],
    "sg:phone":"+32 59 29 92 64",
    "sg:postcode":"8480",
    "sg:province":"West-Vlaanderen",
    "sg:tags":[
        "medicinephysicians",
        "surgeon"
    ],
    "wof:name":"Lievens Koen",
    "wof:placetype":"venue"
},
  "geometry": {"coordinates":[3.0273110867,51.130657196],"type":"Point"}
}