{
  "type": "Feature",
  "properties": {
    "addr:full":"Maria-hendrikastraat 54 Elsene/ixelles Bruxelles-Capitale 1050",
    "addr:housenumber":"54",
    "addr:postcode":"1050",
    "addr:street":"Maria-Hendrikastraat",
    "iso:country":"BE",
    "sg:address":"Maria-hendrikastraat 54",
    "sg:city":"Elsene/ixelles",
    "sg:orig_category":"Artsen and specialisten",
    "sg:phone":"+32 2 647 76 34",
    "sg:postcode":"1050",
    "sg:province":"Bruxelles-Capitale",
    "wof:name":"Gabriel Liberale",
    "wof:placetype":"venue"
},
  "geometry": {"coordinates":[4.3748950958,50.8298149109],"type":"Point"}
}