{
  "type": "Feature",
  "properties": {
    "addr:full":"Begijneweidestraat 17 Wetteren Oost-Vlaanderen 9230",
    "addr:housenumber":"17",
    "addr:postcode":"9230",
    "addr:street":"Begijneweidestraat",
    "iso:country":"BE",
    "sg:address":"Begijneweidestraat 17",
    "sg:city":"Wetteren",
    "sg:orig_category":"Avocats and conseillers juridiques",
    "sg:phone":"+32 9 369 33 60",
    "sg:postcode":"9230",
    "sg:province":"Oost-Vlaanderen",
    "wof:name":"Wim Rasschaert",
    "wof:placetype":"venue"
},
  "geometry": {"coordinates":[3.8743629456,51.0046615601],"type":"Point"}
}