{
  "type": "Feature",
  "properties": {
    "iso:country":"BE",
    "sg:address":"Tongerlodorp 8",
    "sg:city":"Westerlo",
    "sg:classifiers":[
        {
            "category":"Restaurant",
            "type":"Food & Drink"
        }
    ],
    "sg:phone":"+32 14 54 92 40",
    "sg:postcode":"2260",
    "sg:province":"Antwerpen",
    "sg:tags":[
        "caf\u00e9s"
    ],
    "wof:name":"Taverne 't Abdijke",
    "wof:placetype":"venue"
},
  "geometry": {"coordinates":[4.9156341553,51.1066017151],"type":"Point"}
}