{
  "type": "Feature",
  "properties": {
    "iso:country":"BE",
    "sg:address":"Kerkstraat 3",
    "sg:city":"Koekelare",
    "sg:classifiers":[
        {
            "category":"Health Services",
            "subcategory":"Dentist",
            "type":"Services"
        }
    ],
    "sg:phone":"+32 51 58 03 49",
    "sg:postcode":"8680",
    "sg:province":"West-Vlaanderen",
    "wof:name":"Verfaillie M",
    "wof:placetype":"venue"
},
  "geometry": {"coordinates":[2.979516983,51.0904884338],"type":"Point"}
}