{
  "type": "Feature",
  "properties": {
    "addr:full":"Rue Georges-simenon 30 Li\u00e8ge 1 (li\u00e8ge 2) Li\u00e8ge 4020",
    "addr:housenumber":"30;1;2",
    "addr:postcode":"4020",
    "addr:street":"Rue Georges-Simenon",
    "iso:country":"BE",
    "sg:address":"Rue Georges-simenon 30",
    "sg:city":"Li\u00e8ge 1 (li\u00e8ge 2)",
    "sg:classifiers":[
        {
            "category":"Health Services",
            "subcategory":"Doctor",
            "type":"Services"
        }
    ],
    "sg:phone":"+32 4 343 30 87",
    "sg:postcode":"4020",
    "sg:province":"Li\u00e8ge",
    "sg:tags":[
        "medicinephysicians",
        "surgeon"
    ],
    "wof:name":"Demonceau D",
    "wof:placetype":"venue"
},
  "geometry": {"coordinates":[5.5867390633,50.641872406],"type":"Point"}
}