{
  "type": "Feature",
  "properties": {
    "addr:full":"Godveerdegemstraat 173 Zottegem Oost-Vlaanderen 9620",
    "addr:housenumber":"173",
    "addr:postcode":"9620",
    "addr:street":"Godveerdegemstraat",
    "iso:country":"BE",
    "sg:address":"Godveerdegemstraat 173",
    "sg:city":"Zottegem",
    "sg:classifiers":[
        {
            "category":"Wholesale",
            "subcategory":"Beer",
            "type":"Manufacturing & Wholesale Goods"
        }
    ],
    "sg:phone":"+32 9 360 87 90",
    "sg:postcode":"9620",
    "sg:province":"Oost-Vlaanderen",
    "sg:tags":[
        "ale",
        "-"
    ],
    "wof:name":"Porrez Drinks",
    "wof:placetype":"venue"
},
  "geometry": {"coordinates":[3.8242900372,50.8640327454],"type":"Point"}
}