{
  "type": "Feature",
  "properties": {
    "addr:full":"Rue Des Saules 100 Huy Li\u00e8ge 4500",
    "addr:housenumber":"100",
    "addr:postcode":"4500",
    "addr:street":"Rue Des Saules",
    "iso:country":"BE",
    "sg:address":"Rue Des Saules 100",
    "sg:city":"Huy",
    "sg:classifiers":[
        {
            "category":"Arena",
            "subcategory":"Sports Club",
            "type":"Entertainment"
        }
    ],
    "sg:phone":"+32 85 23 69 82",
    "sg:postcode":"4500",
    "sg:province":"Li\u00e8ge",
    "sg:tags":[
        "de"
    ],
    "wof:name":"B.c. Marchin",
    "wof:placetype":"venue"
},
  "geometry": {"coordinates":[5.2565331459,50.5316925049],"type":"Point"}
}