{
  "type": "Feature",
  "properties": {
    "iso:country":"BE",
    "sg:address":"Rue De Pintamont 4",
    "sg:city":"Ath",
    "sg:classifiers":[
        {
            "category":"Retail",
            "subcategory":"Laundry & Dry Cleaning",
            "type":"Services"
        }
    ],
    "sg:phone":"+32 68 28 36 53",
    "sg:postcode":"7800",
    "sg:province":"Hainaut",
    "sg:tags":[
        "dyer",
        "cleaner"
    ],
    "wof:name":"Pressing Saint-julien",
    "wof:placetype":"venue"
},
  "geometry": {"coordinates":[3.7749400139,50.6290817261],"type":"Point"}
}