{
  "type": "Feature",
  "properties": {
    "addr:full":"Chauss\u00e9e D'alsemberg 486 Braine L'alleud (braine-l'alleud) Brabant Wallon 1420",
    "addr:housenumber":"486",
    "addr:postcode":"1420",
    "addr:street":"Chausse\u0301E D'Alsemberg",
    "iso:country":"BE",
    "sg:address":"Chauss\u00e9e D'alsemberg 486",
    "sg:city":"Braine L'alleud (braine-l'alleud)",
    "sg:classifiers":[
        {
            "category":"Shopping",
            "subcategory":"Bicycles & Sporting Goods",
            "type":"Retail Goods"
        }
    ],
    "sg:phone":"+32 2 384 47 38",
    "sg:postcode":"1420",
    "sg:province":"Brabant Wallon",
    "sg:tags":[
        "tyre"
    ],
    "wof:name":"De Greef-van Den Bulcke Sprl",
    "wof:placetype":"venue"
},
  "geometry": {"coordinates":[-0.7711730003,47.3931159973],"type":"Point"}
}