{
  "type": "Feature",
  "properties": {
    "addr:full":"Pand 251-253 Waregem West-Vlaanderen 8790",
    "addr:postcode":"251-253;8790",
    "iso:country":"BE",
    "sg:address":"Pand 251-253",
    "sg:city":"Waregem",
    "sg:classifiers":[
        {
            "category":"Shopping",
            "subcategory":"Clothing, Apparel, & Fashions",
            "type":"Retail Goods"
        }
    ],
    "sg:phone":"+32 56 32 95 49",
    "sg:postcode":"8790",
    "sg:province":"West-Vlaanderen",
    "sg:tags":[
        "lady",
        "clothing",
        "-"
    ],
    "wof:name":"Laguna Fashion Bvba",
    "wof:placetype":"venue"
},
  "geometry": {"coordinates":[3.4312019348,50.8861961365],"type":"Point"}
}