{
  "type": "Feature",
  "properties": {
    "iso:country":"BE",
    "sg:address":"Rue Walth\u00e8re Jamar 77",
    "sg:city":"Ans",
    "sg:classifiers":[
        {
            "category":"Professional",
            "subcategory":"Lawyer & Legal Services",
            "type":"Services"
        }
    ],
    "sg:phone":"+32 4 224 00 30",
    "sg:postcode":"4430",
    "sg:province":"Li\u00e8ge",
    "wof:name":"Talha Abdennacer",
    "wof:placetype":"venue"
},
  "geometry": {"coordinates":[5.5431032181,50.6513977051],"type":"Point"}
}