{
  "type": "Feature",
  "properties": {
    "addr:full":"Noordlaan 77 Box 1 Roeselare West-Vlaanderen 8800",
    "addr:housenumber":"77;1",
    "addr:postcode":"8800",
    "addr:street":"Noordlaan;Box",
    "iso:country":"BE",
    "sg:address":"Noordlaan 77 Box 1",
    "sg:city":"Roeselare",
    "sg:classifiers":[
        {
            "category":"Shopping",
            "subcategory":"Computers & Home Electronics",
            "type":"Retail Goods"
        }
    ],
    "sg:phone":"+32 51 20 00 25",
    "sg:postcode":"8800",
    "sg:province":"West-Vlaanderen",
    "sg:tags":[
        "-",
        "television",
        "radio"
    ],
    "wof:name":"Lebon Robert Nv",
    "wof:placetype":"venue"
},
  "geometry": {"coordinates":[3.1159369946,50.9549102783],"type":"Point"}
}