{
  "type": "Feature",
  "properties": {
    "addr:full":"Rotenstraat 13 Genk Limburg 3600",
    "addr:housenumber":"13",
    "addr:postcode":"3600",
    "addr:street":"Rotenstraat",
    "iso:country":"BE",
    "sg:address":"Rotenstraat 13",
    "sg:city":"Genk",
    "sg:classifiers":[
        {
            "category":"Personal",
            "subcategory":"Beauty Salon",
            "type":"Services"
        }
    ],
    "sg:phone":"+32 89 36 38 35",
    "sg:postcode":"3600",
    "sg:province":"Limburg",
    "sg:tags":[
        "de",
        "coiffure"
    ],
    "wof:name":"Riggio Enzo",
    "wof:placetype":"venue"
},
  "geometry": {"coordinates":[5.5028338432,50.9652481079],"type":"Point"}
}