{
  "type": "Feature",
  "properties": {
    "iso:country":"BE",
    "sg:address":"Rue Des Saules 105",
    "sg:city":"Huy",
    "sg:orig_category":"V\u00e9hicules automobiles",
    "sg:phone":"+32 85 21 53 93",
    "sg:postcode":"4500",
    "sg:province":"Li\u00e8ge",
    "wof:name":"Garage Michel",
    "wof:placetype":"venue"
},
  "geometry": {"coordinates":[5.2511930466,50.5325660706],"type":"Point"}
}