{
  "type": "Feature",
  "properties": {
    "iso:country":"BE",
    "sg:address":"Haverheidelaan 9",
    "sg:city":"Temse",
    "sg:classifiers":[
        {
            "category":"Personal",
            "subcategory":"Skin Care",
            "type":"Services"
        }
    ],
    "sg:phone":"+32 3 710 96 50",
    "sg:postcode":"9140",
    "sg:province":"Oost-Vlaanderen",
    "sg:tags":[
        "product"
    ],
    "wof:name":"Louis Widmer Nv",
    "wof:placetype":"venue"
},
  "geometry": {"coordinates":[4.1982541084,51.1383552551],"type":"Point"}
}