{
  "type": "Feature",
  "properties": {
    "addr:full":"Chauss\u00c9e De Namur 72 Hamois Namur 5360",
    "addr:housenumber":"72",
    "addr:postcode":"5360",
    "addr:street":"Chausse\u0301E De Namur",
    "iso:country":"BE",
    "sg:address":"Chauss\u00c9e De Namur 72",
    "sg:city":"Hamois",
    "sg:orig_category":"Woningbouw",
    "sg:phone":"+32 83 21 13 04",
    "sg:postcode":"5360",
    "sg:province":"Namur",
    "wof:name":"Raoul Radu Et Fils",
    "wof:placetype":"venue"
},
  "geometry": {"coordinates":[5.052749157,50.346950531],"type":"Point"}
}