{
  "type": "Feature",
  "properties": {
    "iso:country":"BE",
    "sg:address":"Moeremaaistraat 21",
    "sg:city":"Wervik",
    "sg:orig_category":"Eleveurs and marchands de porcs",
    "sg:phone":"+32 56 51 31 20",
    "sg:postcode":"8940",
    "sg:province":"West-Vlaanderen",
    "wof:name":"Ivan Bonne",
    "wof:placetype":"venue"
},
  "geometry": {"coordinates":[3.0569620132,50.8325767517],"type":"Point"}
}