{
  "type": "Feature",
  "properties": {
    "iso:country":"BE",
    "sg:address":"Hoogzand 8",
    "sg:city":"Hulshout (westmeerbeek)",
    "sg:classifiers":[
        {
            "category":"Shopping",
            "subcategory":"Clothing, Apparel, & Fashions",
            "type":"Retail Goods"
        }
    ],
    "sg:phone":"+32 16 69 87 82",
    "sg:postcode":"2235",
    "sg:province":"Antwerpen",
    "sg:tags":[
        "boutique"
    ],
    "wof:name":"Marjel Boetiek",
    "wof:placetype":"venue"
},
  "geometry": {"coordinates":[4.8360409737,51.0604705811],"type":"Point"}
}