{
  "type": "Feature",
  "properties": {
    "addr:full":"Onze Lieve Vrouwstraat Bilzen Limburg 3740",
    "addr:postcode":"3740",
    "addr:street":"Onze Lieve Vrouwstraat",
    "iso:country":"BE",
    "sg:address":"Onze Lieve Vrouwstraat",
    "sg:city":"Bilzen",
    "sg:orig_category":"Schoenen",
    "sg:phone":"+32 89 41 24 30",
    "sg:postcode":"3740",
    "sg:province":"Limburg",
    "wof:name":"Shoes In The Box",
    "wof:placetype":"venue"
},
  "geometry": {"coordinates":[5.5160250664,50.8706245422],"type":"Point"}
}