{
  "type": "Feature",
  "properties": {
    "iso:country":"BE",
    "sg:address":"Rue Xhav\u00c9e 4",
    "sg:city":"Verviers",
    "sg:orig_category":"Agences d\u00b4interim and personnel temporaire",
    "sg:phone":"+32 87 31 56 46",
    "sg:postcode":"4800",
    "sg:province":"Li\u00e8ge",
    "wof:name":"Bik Interim",
    "wof:placetype":"venue"
},
  "geometry": {"coordinates":[5.8599338531,50.5921287537],"type":"Point"}
}