{
  "type": "Feature",
  "properties": {
    "addr:full":"Veerstraat 186 Zandhoven Antwerpen 2240",
    "addr:housenumber":"186",
    "addr:postcode":"2240",
    "addr:street":"Veerstraat",
    "iso:country":"BE",
    "sg:address":"Veerstraat 186",
    "sg:city":"Zandhoven",
    "sg:orig_category":"Installatie van houten of kunststof schrijnwerk",
    "sg:phone":"+32 3 485 82 45",
    "sg:postcode":"2240",
    "sg:province":"Antwerpen",
    "wof:name":"Andre Moulaert",
    "wof:placetype":"venue"
},
  "geometry": {"coordinates":[4.6357588768,51.1815643311],"type":"Point"}
}