{
  "type": "Feature",
  "properties": {
    "iso:country":"BE",
    "sg:address":"Marktstraat 16",
    "sg:city":"Opwijk",
    "sg:classifiers":[
        {
            "category":"Real Estate",
            "subcategory":"Architect",
            "type":"Services"
        }
    ],
    "sg:phone":"+32 52 35 63 96",
    "sg:postcode":"1745",
    "sg:province":"Vlaams-Brabant",
    "wof:name":"Van Lembergen E",
    "wof:placetype":"venue"
},
  "geometry": {"coordinates":[4.1878938675,50.9707756042],"type":"Point"}
}