{
  "type": "Feature",
  "properties": {
    "addr:full":"Groenstraat 112 Aalst Oost-Vlaanderen 9300",
    "addr:housenumber":"112",
    "addr:postcode":"9300",
    "addr:street":"Groenstraat",
    "iso:country":"BE",
    "sg:address":"Groenstraat 112",
    "sg:city":"Aalst",
    "sg:orig_category":"Herstelling and restauratie van meubelen Meubelzaken, woning- and keukeninrichting",
    "sg:phone":"+32 53 21 61 68",
    "sg:postcode":"9300",
    "sg:province":"Oost-Vlaanderen",
    "wof:name":"Norbert De Cock",
    "wof:placetype":"venue"
},
  "geometry": {"coordinates":[4.051967144,50.9440956116],"type":"Point"}
}