{
  "type": "Feature",
  "properties": {
    "addr:full":"Rue Des Minimes 24 Brussel/bruxelles Bruxelles-Capitale 1000",
    "addr:housenumber":"24",
    "addr:postcode":"1000",
    "addr:street":"Rue Des Minimes;/",
    "iso:country":"BE",
    "sg:address":"Rue Des Minimes 24",
    "sg:city":"Brussel/bruxelles",
    "sg:orig_category":"Antiquit\u00e9s",
    "sg:phone":"+32 2 503 24 94",
    "sg:postcode":"1000",
    "sg:province":"Bruxelles-Capitale",
    "wof:name":"Boon Gallery",
    "wof:placetype":"venue"
},
  "geometry": {"coordinates":[4.3537669182,50.8407249451],"type":"Point"}
}