{
  "type": "Feature",
  "properties": {
    "iso:country":"BE",
    "sg:address":"Place Verdi 1",
    "sg:city":"Bruxelles (anderlecht)",
    "sg:classifiers":[
        {
            "category":"Bars & Pubs",
            "type":"Food & Drink"
        }
    ],
    "sg:phone":"+32 2 522 11 15",
    "sg:postcode":"1070",
    "sg:province":"Bruxelles-Capitale",
    "wof:name":"Verdi (le)",
    "wof:placetype":"venue"
},
  "geometry": {"coordinates":[4.3005270958,50.8288650513],"type":"Point"}
}