{
  "type": "Feature",
  "properties": {
    "addr:full":"Kerkplein 12 Izegem West-Vlaanderen 8870",
    "addr:housenumber":"12",
    "addr:postcode":"8870",
    "addr:street":"Kerkplein",
    "iso:country":"BE",
    "sg:address":"Kerkplein 12",
    "sg:city":"Izegem",
    "sg:classifiers":[
        {
            "category":"Shopping",
            "subcategory":"Shoes",
            "type":"Retail Goods"
        }
    ],
    "sg:phone":"+32 51 30 02 29",
    "sg:postcode":"8870",
    "sg:province":"West-Vlaanderen",
    "sg:tags":[
        "slipper",
        "-"
    ],
    "wof:name":"Denys (huis)",
    "wof:placetype":"venue"
},
  "geometry": {"coordinates":[3.2138829231,50.9166908264],"type":"Point"}
}