{
  "type": "Feature",
  "properties": {
    "addr:full":"Aarseleweg 4 Deinze Oost-Vlaanderen 9800",
    "addr:housenumber":"4",
    "addr:postcode":"9800",
    "addr:street":"Aarseleweg",
    "iso:country":"BE",
    "sg:address":"Aarseleweg 4",
    "sg:city":"Deinze",
    "sg:orig_category":"Pain, p\u00e2tisseries and confiseries",
    "sg:phone":"+32 9 386 12 61",
    "sg:postcode":"9800",
    "sg:province":"Oost-Vlaanderen",
    "wof:name":"Christiaan Van Simaeys",
    "wof:placetype":"venue"
},
  "geometry": {"coordinates":[3.4781939983,51.007976532],"type":"Point"}
}