{
  "type": "Feature",
  "properties": {
    "addr:full":"Rue Champs Des Oiseaux 14 Saint-georges-sur-meuse Li\u00e8ge 4470",
    "addr:housenumber":"14",
    "addr:postcode":"4470",
    "addr:street":"Rue Champs Des Oiseaux",
    "iso:country":"BE",
    "sg:address":"Rue Champs Des Oiseaux 14",
    "sg:city":"Saint-georges-sur-meuse",
    "sg:orig_category":"Eleveurs de bovins",
    "sg:phone":"+32 4 259 53 63",
    "sg:postcode":"4470",
    "sg:province":"Li\u00e8ge",
    "wof:name":"Leon Piraprez",
    "wof:placetype":"venue"
},
  "geometry": {"coordinates":[5.3413500786,50.5818023682],"type":"Point"}
}