{
  "type": "Feature",
  "properties": {
    "iso:country":"BE",
    "sg:address":"Rue Middelbourg 130",
    "sg:city":"Watermaal-bosvoorde/watermael-boitsfort",
    "sg:classifiers":[
        {
            "category":"Restaurant",
            "type":"Food & Drink"
        }
    ],
    "sg:phone":"+32 2 660 06 77",
    "sg:postcode":"1170",
    "sg:province":"Bruxelles-Capitale",
    "sg:tags":[
        "caf\u00e9s",
        "\u00e0",
        "emporter",
        "fast"
    ],
    "wof:name":"Chez Arnaud",
    "wof:placetype":"venue"
},
  "geometry": {"coordinates":[4.4186000824,50.7939796448],"type":"Point"}
}