{
  "type": "Feature",
  "properties": {
    "iso:country":"BE",
    "sg:address":"Rue Mitoyenne 322",
    "sg:city":"Lontzen/lontzen",
    "sg:orig_category":"Travaux de pl\u00e2trage",
    "sg:phone":"+32 87 89 03 17",
    "sg:postcode":"4710",
    "sg:province":"Li\u00e8ge",
    "wof:name":"Jean-pierre Houben",
    "wof:placetype":"venue"
},
  "geometry": {"coordinates":[5.9695281982,50.6734428406],"type":"Point"}
}