{
  "type": "Feature",
  "properties": {
    "addr:full":"Rue Eloi Bouvier 1a Genappe (ways) Brabant Wallon 1474",
    "addr:housenumber":"1a",
    "addr:postcode":"1474",
    "addr:street":"Rue Eloi Bouvier;Ways",
    "iso:country":"BE",
    "sg:address":"Rue Eloi Bouvier 1a",
    "sg:city":"Genappe (ways)",
    "sg:classifiers":[
        {
            "category":"Building & Trades",
            "subcategory":"Pest Control",
            "type":"Services"
        }
    ],
    "sg:phone":"+32 2 633 54 70",
    "sg:postcode":"1474",
    "sg:province":"Brabant Wallon",
    "sg:tags":[
        "painting",
        "contractor"
    ],
    "wof:name":"Dumont J-m",
    "wof:placetype":"venue"
},
  "geometry": {"coordinates":[4.4630827904,50.6126594543],"type":"Point"}
}