{
  "type": "Feature",
  "properties": {
    "iso:country":"BE",
    "sg:address":"Garebaan 16",
    "sg:city":"Sint-pieters-leeuw",
    "sg:orig_category":"Agences de presse",
    "sg:phone":"+32 2 331 23 13",
    "sg:postcode":"1600",
    "sg:province":"Vlaams-Brabant",
    "wof:name":"Frank Abbeloos",
    "wof:placetype":"venue"
},
  "geometry": {"coordinates":[4.239508152,50.7763404846],"type":"Point"}
}