{
  "type": "Feature",
  "properties": {
    "addr:full":"Rue D'astenet 54 Lontzen/lontzen Li\u00e8ge 4711",
    "addr:housenumber":"54",
    "addr:postcode":"4711",
    "addr:street":"Rue D'Astenet",
    "iso:country":"BE",
    "sg:address":"Rue D'astenet 54",
    "sg:city":"Lontzen/lontzen",
    "sg:orig_category":"Auto-\u00e9coles",
    "sg:phone":"+32 87 65 87 04",
    "sg:postcode":"4711",
    "sg:province":"Li\u00e8ge",
    "wof:name":"Auto-ecole Central",
    "wof:placetype":"venue"
},
  "geometry": {"coordinates":[6.0368680954,50.6825485229],"type":"Point"}
}