{
  "type": "Feature",
  "properties": {
    "addr:full":"Rue Du Bois Des R\u00caves 61 Ottignies-louvain-la-neuve Brabant Wallon 1341",
    "addr:housenumber":"61",
    "addr:postcode":"1341",
    "addr:street":"Rue Du Bois Des Re\u0302Ves",
    "iso:country":"BE",
    "sg:address":"Rue Du Bois Des R\u00caves 61",
    "sg:city":"Ottignies-louvain-la-neuve",
    "sg:orig_category":"Avocats and conseillers juridiques",
    "sg:phone":"+32 475 42 29 87",
    "sg:postcode":"1341",
    "sg:province":"Brabant Wallon",
    "wof:name":"W. Wallyn",
    "wof:placetype":"venue"
},
  "geometry": {"coordinates":[4.5627598763,50.6583099365],"type":"Point"}
}