{
  "type": "Feature",
  "properties": {
    "iso:country":"BE",
    "sg:address":"Kortrijkstraat 133",
    "sg:city":"Tielt",
    "sg:orig_category":"Agences immobili\u00e8res",
    "sg:phone":"+32 51 40 52 53",
    "sg:postcode":"8780",
    "sg:province":"West-Vlaanderen",
    "wof:name":"Immo Cova",
    "wof:placetype":"venue"
},
  "geometry": {"coordinates":[3.3254320621,50.9948272705],"type":"Point"}
}