{
  "type": "Feature",
  "properties": {
    "iso:country":"BE",
    "sg:address":"Rue De Biesme 107",
    "sg:city":"Thuin (biesme-sous-thuin)",
    "sg:classifiers":[
        {
            "category":"Recreation",
            "subcategory":"Campground",
            "type":"Entertainment"
        }
    ],
    "sg:phone":"+32 71 59 09 62",
    "sg:postcode":"6531",
    "sg:province":"Hainaut",
    "sg:tags":[
        "site",
        "camping"
    ],
    "wof:name":"Camping Le Seurus",
    "wof:placetype":"venue"
},
  "geometry": {"coordinates":[4.3195710182,50.3147583008],"type":"Point"}
}