{
  "type": "Feature",
  "properties": {
    "iso:country":"BE",
    "sg:address":"Rue Sur Les Roches 22",
    "sg:city":"Saint-georges-sur-meuse",
    "sg:classifiers":[
        {
            "category":"Communications",
            "subcategory":"Radio Station",
            "type":"Services"
        }
    ],
    "sg:phone":"+32 4 275 45 82",
    "sg:postcode":"4470",
    "sg:province":"Li\u00e8ge",
    "sg:tags":[
        "local"
    ],
    "wof:name":"Radio Plein Sud",
    "wof:placetype":"venue"
},
  "geometry": {"coordinates":[5.3655729294,50.5746116638],"type":"Point"}
}