{
  "type": "Feature",
  "properties": {
    "addr:full":"Toekomststraat 9 Lommel Limburg 3920",
    "addr:housenumber":"9",
    "addr:postcode":"3920",
    "addr:street":"Toekomststraat",
    "iso:country":"BE",
    "sg:address":"Toekomststraat 9",
    "sg:city":"Lommel",
    "sg:orig_category":"Woningbouw",
    "sg:phone":"+32 11 34 75 81",
    "sg:postcode":"3920",
    "sg:province":"Limburg",
    "wof:name":"Maurizio Malavolta",
    "wof:placetype":"venue"
},
  "geometry": {"coordinates":[5.2693891525,51.1655197144],"type":"Point"}
}