{
  "type": "Feature",
  "properties": {
    "addr:full":"Uitweg 3 Tielt West-Vlaanderen 8700",
    "addr:housenumber":"3",
    "addr:postcode":"8700",
    "addr:street":"Uitweg",
    "iso:country":"BE",
    "sg:address":"Uitweg 3",
    "sg:city":"Tielt",
    "sg:orig_category":"Rundveehouders",
    "sg:phone":"+32 51 40 05 29",
    "sg:postcode":"8700",
    "sg:province":"West-Vlaanderen",
    "wof:name":"Broeierij David",
    "wof:placetype":"venue"
},
  "geometry": {"coordinates":[3.328150034,51.0330848694],"type":"Point"}
}