{
  "type": "Feature",
  "properties": {
    "addr:full":"Zoning De Cuesmes Mons (cuesmes) Hainaut 7033",
    "addr:postcode":"7033",
    "addr:street":"Zoning De Cuesmes",
    "iso:country":"BE",
    "sg:address":"Zoning De Cuesmes",
    "sg:city":"Mons (cuesmes)",
    "sg:classifiers":[
        {
            "category":"Home & Garden",
            "subcategory":"Carpets & Floor Coverings",
            "type":"Retail Goods"
        }
    ],
    "sg:phone":"+32 65 31 20 87",
    "sg:postcode":"7033",
    "sg:province":"Hainaut",
    "sg:tags":[
        "layer",
        "mosaicists"
    ],
    "wof:name":"Caropose",
    "wof:placetype":"venue"
},
  "geometry": {"coordinates":[3.9402499199,50.4501838684],"type":"Point"}
}