{
  "type": "Feature",
  "properties": {
    "addr:full":"Rue De La Foulerie 37-1 Couvin Namur 5660",
    "addr:housenumber":"37-1",
    "addr:postcode":"5660",
    "addr:street":"Rue De La Foulerie",
    "iso:country":"BE",
    "sg:address":"Rue De La Foulerie 37-1",
    "sg:city":"Couvin",
    "sg:classifiers":[
        {
            "category":"Retail",
            "subcategory":"Auto Repair",
            "type":"Services"
        }
    ],
    "sg:phone":"+32 60 39 04 58",
    "sg:postcode":"5660",
    "sg:province":"Namur",
    "sg:tags":[
        "automobile-body"
    ],
    "wof:name":"Carro Couvin",
    "wof:placetype":"venue"
},
  "geometry": {"coordinates":[4.5000810623,50.0446968079],"type":"Point"}
}