{
  "type": "Feature",
  "properties": {
    "iso:country":"BE",
    "sg:address":"Clos Des Spinettes 7",
    "sg:city":"Namur",
    "sg:orig_category":"Artsen and specialisten",
    "sg:phone":"+32 81 46 17 61",
    "sg:postcode":"5100",
    "sg:province":"Namur",
    "wof:name":"Yves Laroche",
    "wof:placetype":"venue"
},
  "geometry": {"coordinates":[4.858479023,50.4300918579],"type":"Point"}
}