{
  "type": "Feature",
  "properties": {
    "addr:full":"Rue Des Cl\u00e9matites 10 Neupr\u00e9 (neuville-en-condroz) Li\u00e8ge 4121",
    "addr:housenumber":"10",
    "addr:postcode":"4121",
    "addr:street":"Rue Des Cle\u0301Matites",
    "iso:country":"BE",
    "sg:address":"Rue Des Cl\u00e9matites 10",
    "sg:city":"Neupr\u00e9 (neuville-en-condroz)",
    "sg:classifiers":[
        {
            "category":"Home & Garden",
            "subcategory":"Building Materials",
            "type":"Retail Goods"
        }
    ],
    "sg:phone":"+32 4 371 28 65",
    "sg:postcode":"4121",
    "sg:province":"Li\u00e8ge",
    "sg:tags":[
        "shutter"
    ],
    "wof:name":"Christofel",
    "wof:placetype":"venue"
},
  "geometry": {"coordinates":[5.4843139648,50.547000885],"type":"Point"}
}