{
  "type": "Feature",
  "properties": {
    "addr:full":"Gerststraat 10 Balen Antwerpen 2490",
    "addr:housenumber":"10",
    "addr:postcode":"2490",
    "addr:street":"Gerststraat",
    "iso:country":"BE",
    "sg:address":"Gerststraat 10",
    "sg:city":"Balen",
    "sg:orig_category":"Gereedschapswerktuigen Gh",
    "sg:phone":"+32 14 31 97 56",
    "sg:postcode":"2490",
    "sg:province":"Antwerpen",
    "wof:name":"Pipe Consultants Belgium",
    "wof:placetype":"venue"
},
  "geometry": {"coordinates":[5.1268310547,51.171131134],"type":"Point"}
}