{
  "type": "Feature",
  "properties": {
    "addr:full":"Rue Grande 88 Boussu Hainaut 7301",
    "addr:housenumber":"88",
    "addr:postcode":"7301",
    "addr:street":"Rue Grande",
    "iso:country":"BE",
    "sg:address":"Rue Grande 88",
    "sg:city":"Boussu",
    "sg:orig_category":"Cabinets d\u00b4huissiers",
    "sg:phone":"+32 65 79 15 47",
    "sg:postcode":"7301",
    "sg:province":"Hainaut",
    "wof:name":"M. Tonneau",
    "wof:placetype":"venue"
},
  "geometry": {"coordinates":[3.8257451057,50.4362258911],"type":"Point"}
}