{
  "type": "Feature",
  "properties": {
    "iso:country":"BE",
    "sg:address":"Rue Saint-gervais 49",
    "sg:city":"Brugelette (m\u00e9vergnies-lez-lens)",
    "sg:classifiers":[
        {
            "category":"Autos & Motor Vehicles",
            "subcategory":"Automobile Sales",
            "type":"Retail Goods"
        }
    ],
    "sg:phone":"+32 68 45 40 94",
    "sg:postcode":"7942",
    "sg:province":"Hainaut",
    "sg:tags":[
        "car",
        "used",
        "-"
    ],
    "wof:name":"Leleux Daniel Ets",
    "wof:placetype":"venue"
},
  "geometry": {"coordinates":[3.8516390324,50.6059455872],"type":"Point"}
}