{
  "type": "Feature",
  "properties": {
    "iso:country":"BE",
    "sg:address":"Sint-albaansbergstraat 59b",
    "sg:city":"Brussel",
    "sg:orig_category":"Diverse bedrijfsbeheeradviesbureaus",
    "sg:phone":"+32 2 476 00 98",
    "sg:postcode":"1020",
    "sg:province":"Bruxelles-Capitale",
    "wof:name":"Alisca",
    "wof:placetype":"venue"
},
  "geometry": {"coordinates":[4.3454289436,50.8839530945],"type":"Point"}
}