{
  "type": "Feature",
  "properties": {
    "iso:country":"BE",
    "sg:address":"Rue Louvrex 55",
    "sg:city":"Li\u00c8ge",
    "sg:orig_category":"Avocats and conseillers juridiques",
    "sg:phone":"+32 4 220 03 03",
    "sg:postcode":"4000",
    "sg:province":"Li\u00e8ge",
    "wof:name":"J.l. Brandenberg",
    "wof:placetype":"venue"
},
  "geometry": {"coordinates":[5.5638151169,50.635635376],"type":"Point"}
}