{
  "type": "Feature",
  "properties": {
    "iso:country":"BE",
    "sg:address":"Hanselaarstraat 25",
    "sg:city":"Lochristi",
    "sg:orig_category":"Rundveehouders",
    "sg:phone":"+32 9 355 70 39",
    "sg:postcode":"9080",
    "sg:province":"Oost-Vlaanderen",
    "wof:name":"Sylvain Standaert",
    "wof:placetype":"venue"
},
  "geometry": {"coordinates":[3.9012789726,51.0762443542],"type":"Point"}
}