{
  "type": "Feature",
  "properties": {
    "addr:full":"Gasthuisstraat 68 Brecht Antwerpen 2960",
    "addr:housenumber":"68",
    "addr:postcode":"2960",
    "addr:street":"Gasthuisstraat",
    "iso:country":"BE",
    "sg:address":"Gasthuisstraat 68",
    "sg:city":"Brecht",
    "sg:classifiers":[
        {
            "category":"Health Services",
            "subcategory":"Doctor",
            "type":"Services"
        }
    ],
    "sg:phone":"+32 3 313 93 53",
    "sg:postcode":"2960",
    "sg:province":"Antwerpen",
    "sg:tags":[
        "medicinephysicians",
        "surgeon"
    ],
    "wof:name":"Deckers Willem",
    "wof:placetype":"venue"
},
  "geometry": {"coordinates":[4.6351099014,51.347076416],"type":"Point"}
}