{
  "type": "Feature",
  "properties": {
    "addr:full":"Rue De Herve 787 Beyne-heusay Li\u00e8ge 4610",
    "addr:housenumber":"787",
    "addr:postcode":"4610",
    "addr:street":"Rue De Herve",
    "iso:country":"BE",
    "sg:address":"Rue De Herve 787",
    "sg:city":"Beyne-heusay",
    "sg:classifiers":[
        {
            "category":"Restaurant",
            "type":"Food & Drink"
        }
    ],
    "sg:phone":"+32 4 366 00 84",
    "sg:postcode":"4610",
    "sg:province":"Li\u00e8ge",
    "wof:name":"Chez Grand-p\u00c8re",
    "wof:placetype":"venue"
},
  "geometry": {"coordinates":[5.6397857666,50.6259880066],"type":"Point"}
}