{
  "type": "Feature",
  "properties": {
    "addr:full":"Rue Tombeux 41 Donceel (haneffe) Li\u00e8ge 4357",
    "addr:housenumber":"41",
    "addr:postcode":"4357",
    "addr:street":"Rue Tombeux;Haneffe",
    "iso:country":"BE",
    "sg:address":"Rue Tombeux 41",
    "sg:city":"Donceel (haneffe)",
    "sg:classifiers":[
        {
            "category":"Health Services",
            "subcategory":"Health Practitioner",
            "type":"Services"
        }
    ],
    "sg:phone":"+32 4 259 59 66",
    "sg:postcode":"4357",
    "sg:province":"Li\u00e8ge",
    "sg:tags":[
        "physiotherapist"
    ],
    "wof:name":"Guisset Anne-sophie",
    "wof:placetype":"venue"
},
  "geometry": {"coordinates":[5.3258938789,50.638710022],"type":"Point"}
}