{
  "type": "Feature",
  "properties": {
    "iso:country":"BE",
    "sg:address":"Jachtstraat 10",
    "sg:city":"Berlare",
    "sg:orig_category":"Installatie van houten of kunststof schrijnwerk",
    "sg:phone":"+32 9 367 69 58",
    "sg:postcode":"9290",
    "sg:province":"Oost-Vlaanderen",
    "wof:name":"Dirk Buyst",
    "wof:placetype":"venue"
},
  "geometry": {"coordinates":[3.9835500717,51.045173645],"type":"Point"}
}