{
  "type": "Feature",
  "properties": {
    "addr:full":"Konijnenhoekstraat 5 Oud-heverlee (haasrode) Vlaams-Brabant 3053",
    "addr:housenumber":"5",
    "addr:postcode":"3053",
    "addr:street":"Konijnenhoekstraat",
    "iso:country":"BE",
    "sg:address":"Konijnenhoekstraat 5",
    "sg:city":"Oud-heverlee (haasrode)",
    "sg:classifiers":[
        {
            "category":"Personal",
            "subcategory":"Beauty Salon",
            "type":"Services"
        }
    ],
    "sg:phone":"+32 16 40 14 36",
    "sg:postcode":"3053",
    "sg:province":"Vlaams-Brabant",
    "sg:tags":[
        "equipment",
        "hairdressing",
        "-",
        "supply"
    ],
    "wof:name":"Vanderlinden",
    "wof:placetype":"venue"
},
  "geometry": {"coordinates":[4.7206730843,50.8348655701],"type":"Point"}
}