{
  "type": "Feature",
  "properties": {
    "iso:country":"BE",
    "sg:address":"Leopoldlaan 45",
    "sg:city":"Overpelt",
    "sg:orig_category":"Kinderopvang",
    "sg:phone":"+32 11 80 17 92",
    "sg:postcode":"3900",
    "sg:province":"Limburg",
    "wof:name":"\u00b4t Ravotterke",
    "wof:placetype":"venue"
},
  "geometry": {"coordinates":[5.4267239571,51.219291687],"type":"Point"}
}