{
  "type": "Feature",
  "properties": {
    "addr:full":"Leon Bekaertlaan 16 Aalter Oost-Vlaanderen 9880",
    "addr:housenumber":"16",
    "addr:postcode":"9880",
    "addr:street":"Leon Bekaertlaan",
    "iso:country":"BE",
    "sg:address":"Leon Bekaertlaan 16",
    "sg:city":"Aalter",
    "sg:classifiers":[
        {
            "category":"Building & Trades",
            "subcategory":"Construction",
            "type":"Services"
        }
    ],
    "sg:phone":"+32 9 374 69 22",
    "sg:postcode":"9880",
    "sg:province":"Oost-Vlaanderen",
    "sg:tags":[
        "carpenter"
    ],
    "wof:name":"Hoste Bvba",
    "wof:placetype":"venue"
},
  "geometry": {"coordinates":[3.4493610859,51.1012649536],"type":"Point"}
}