{
  "type": "Feature",
  "properties": {
    "addr:full":"Schuttershofstraat 9 Merksplas Antwerpen 2330",
    "addr:housenumber":"9",
    "addr:postcode":"2330",
    "addr:street":"Schuttershofstraat",
    "iso:country":"BE",
    "sg:address":"Schuttershofstraat 9",
    "sg:city":"Merksplas",
    "sg:orig_category":"Pharmaciens",
    "sg:phone":"+32 14 63 33 83",
    "sg:postcode":"2330",
    "sg:province":"Antwerpen",
    "wof:name":"Biopharm",
    "wof:placetype":"venue"
},
  "geometry": {"coordinates":[4.8625898361,51.3582115173],"type":"Point"}
}