{
  "type": "Feature",
  "properties": {
    "addr:full":"Avenue De Gu\u00c9m\u00c9n\u00c9e 42 Braine-l'alleud Brabant Wallon 1420",
    "addr:housenumber":"42",
    "addr:postcode":"1420",
    "addr:street":"Avenue De Gue\u0301Me\u0301Ne\u0301E",
    "iso:country":"BE",
    "sg:address":"Avenue De Gu\u00c9m\u00c9n\u00c9e 42",
    "sg:city":"Braine-l'alleud",
    "sg:orig_category":"Woningbouw",
    "sg:phone":"+32 2 387 17 10",
    "sg:postcode":"1420",
    "sg:province":"Brabant Wallon",
    "wof:name":"Comp. G\u00c9n. Construction",
    "wof:placetype":"venue"
},
  "geometry": {"coordinates":[-0.7004899979,47.369140625],"type":"Point"}
}