{
  "type": "Feature",
  "properties": {
    "addr:full":"Markt 30 Herk-de-stad Limburg 3540",
    "addr:housenumber":"30",
    "addr:postcode":"3540",
    "addr:street":"Markt",
    "iso:country":"BE",
    "sg:address":"Markt 30",
    "sg:city":"Herk-de-stad",
    "sg:orig_category":"Banques and organismes de cr\u00e9dit",
    "sg:phone":"+32 13 55 02 30",
    "sg:postcode":"3540",
    "sg:province":"Limburg",
    "wof:name":"Dexia",
    "wof:placetype":"venue"
},
  "geometry": {"coordinates":[5.1659698486,50.9407691956],"type":"Point"}
}