{
  "type": "Feature",
  "properties": {
    "iso:country":"BE",
    "sg:address":"Rue Albert Bodson 34",
    "sg:city":"Gerpinnes",
    "sg:orig_category":"HUISBRANDOLIE",
    "sg:phone":"+32 71 50 27 67",
    "sg:postcode":"6280",
    "sg:province":"Hainaut",
    "wof:name":"Rose Et Barbier",
    "wof:placetype":"venue"
},
  "geometry": {"coordinates":[4.5155520439,50.3359451294],"type":"Point"}
}