{
  "type": "Feature",
  "properties": {
    "addr:full":"Rue De La Jonction 16 Bertrix Luxembourg 6880",
    "addr:housenumber":"16",
    "addr:postcode":"6880",
    "addr:street":"Rue De La Jonction",
    "iso:country":"BE",
    "sg:address":"Rue De La Jonction 16",
    "sg:city":"Bertrix",
    "sg:classifiers":[
        {
            "category":"Health Services",
            "subcategory":"Dentist",
            "type":"Services"
        }
    ],
    "sg:phone":"+32 61 41 18 09",
    "sg:postcode":"6880",
    "sg:province":"Luxembourg",
    "wof:name":"Georges D",
    "wof:placetype":"venue"
},
  "geometry": {"coordinates":[5.2552928925,49.8555641174],"type":"Point"}
}