{
  "type": "Feature",
  "properties": {
    "iso:country":"BE",
    "sg:address":"Keizerstraat 48",
    "sg:city":"Mechelen",
    "sg:classifiers":[
        {
            "category":"Shopping",
            "subcategory":"Bicycles & Sporting Goods",
            "type":"Retail Goods"
        }
    ],
    "sg:phone":"+32 15 20 49 39",
    "sg:postcode":"2800",
    "sg:province":"Antwerpen",
    "sg:tags":[
        "-"
    ],
    "wof:name":"Robot Bvba",
    "wof:placetype":"venue"
},
  "geometry": {"coordinates":[4.4875731468,51.0288734436],"type":"Point"}
}