{
  "type": "Feature",
  "properties": {
    "addr:full":"Oude Molenstraat 52 Dendermonde (grembergen) Oost-Vlaanderen 9200",
    "addr:housenumber":"52",
    "addr:postcode":"9200",
    "addr:street":"Oude Molenstraat",
    "iso:country":"BE",
    "sg:address":"Oude Molenstraat 52",
    "sg:city":"Dendermonde (grembergen)",
    "sg:classifiers":[
        {
            "category":"Real Estate",
            "subcategory":"Architect",
            "type":"Services"
        }
    ],
    "sg:phone":"+32 52 52 01 70",
    "sg:postcode":"9200",
    "sg:province":"Oost-Vlaanderen",
    "wof:name":"Cuypers K",
    "wof:placetype":"venue"
},
  "geometry": {"coordinates":[4.0981760025,51.0262031555],"type":"Point"}
}