{
  "type": "Feature",
  "properties": {
    "addr:full":"Karel Van Hulthemstraat 9 Gent Oost-Vlaanderen 9000",
    "addr:housenumber":"9",
    "addr:postcode":"9000",
    "addr:street":"Karel Van Hulthemstraat;Oost-Vlaanderen",
    "iso:country":"BE",
    "sg:address":"Karel Van Hulthemstraat 9",
    "sg:city":"Gent",
    "sg:orig_category":"Avocats and conseillers juridiques",
    "sg:phone":"+32 9 224 06 88",
    "sg:postcode":"9000",
    "sg:province":"Oost-Vlaanderen",
    "wof:name":"J. Verschaffel",
    "wof:placetype":"venue"
},
  "geometry": {"coordinates":[3.7234370708,51.04454422],"type":"Point"}
}