{
  "type": "Feature",
  "properties": {
    "iso:country":"BE",
    "sg:address":"Rue Du Pan 2",
    "sg:city":"Bernissart (blaton)",
    "sg:classifiers":[
        {
            "category":"Building & Trades",
            "subcategory":"Construction",
            "type":"Services"
        }
    ],
    "sg:phone":"+32 69 58 08 91",
    "sg:postcode":"7321",
    "sg:province":"Hainaut",
    "sg:tags":[
        "carpenter"
    ],
    "wof:name":"I . M . A . Sprl",
    "wof:placetype":"venue"
},
  "geometry": {"coordinates":[3.6615700722,50.4914016724],"type":"Point"}
}