{
  "type": "Feature",
  "properties": {
    "iso:country":"BE",
    "sg:address":"Rue Du Parc 19",
    "sg:city":"Mons",
    "sg:orig_category":"Verplichte sociale verzekeringen",
    "sg:phone":"+32 65 35 22 57",
    "sg:postcode":"7000",
    "sg:province":"Hainaut",
    "wof:name":"Mut. Metallurg.dessidents",
    "wof:placetype":"venue"
},
  "geometry": {"coordinates":[3.9519879818,50.458694458],"type":"Point"}
}