{
  "type": "Feature",
  "properties": {
    "addr:full":"Eynderweg 25 Houthalen-helchteren (helchteren) Limburg 3530",
    "addr:housenumber":"25",
    "addr:postcode":"3530",
    "addr:street":"Eynderweg",
    "iso:country":"BE",
    "sg:address":"Eynderweg 25",
    "sg:city":"Houthalen-helchteren (helchteren)",
    "sg:classifiers":[
        {
            "category":"Home & Garden",
            "subcategory":"Kitchen Supply",
            "type":"Retail Goods"
        }
    ],
    "sg:phone":"+32 11 52 12 30",
    "sg:postcode":"3530",
    "sg:province":"Limburg",
    "sg:tags":[
        "-",
        "industrial",
        "installation",
        "equipment"
    ],
    "wof:name":"Timmers Jean",
    "wof:placetype":"venue"
},
  "geometry": {"coordinates":[5.3719201088,51.0310020447],"type":"Point"}
}