{
  "type": "Feature",
  "properties": {
    "addr:full":"Stokrooieweg 26 Hasselt Limburg 3511",
    "addr:housenumber":"26",
    "addr:postcode":"3511",
    "addr:street":"Stokrooieweg",
    "iso:country":"BE",
    "sg:address":"Stokrooieweg 26",
    "sg:city":"Hasselt",
    "sg:classifiers":[
        {
            "category":"Insurance",
            "subcategory":"Insurance Agent",
            "type":"Services"
        }
    ],
    "sg:phone":"+32 11 25 35 71",
    "sg:postcode":"3511",
    "sg:province":"Limburg",
    "sg:tags":[
        "verzekeringsmakelaars",
        "expert"
    ],
    "wof:name":"Bureau Celis V.",
    "wof:placetype":"venue"
},
  "geometry": {"coordinates":[5.282643795,50.9741897583],"type":"Point"}
}