{
  "type": "Feature",
  "properties": {
    "addr:full":"Buksboomstraat 12 Watermaal-bosvoorde/watermael- Bruxelles-Capitale 1170",
    "addr:housenumber":"12",
    "addr:postcode":"1170",
    "addr:street":"Buksboomstraat",
    "iso:country":"BE",
    "sg:address":"Buksboomstraat 12",
    "sg:city":"Watermaal-bosvoorde/watermael-",
    "sg:orig_category":"Databanken",
    "sg:phone":"+32 2 673 79 07",
    "sg:postcode":"1170",
    "sg:province":"Bruxelles-Capitale",
    "wof:name":"Infotraffic",
    "wof:placetype":"venue"
},
  "geometry": {"coordinates":[4.4210600853,50.7934455872],"type":"Point"}
}