{
  "type": "Feature",
  "properties": {
    "iso:country":"BE",
    "sg:address":"Sint-andriessteenweg 55",
    "sg:city":"Zottegem (strijpen)",
    "sg:classifiers":[
        {
            "category":"Health Services",
            "subcategory":"Health Practitioner",
            "type":"Services"
        }
    ],
    "sg:phone":"+32 9 361 14 67",
    "sg:postcode":"9620",
    "sg:province":"Oost-Vlaanderen",
    "sg:tags":[
        "physiotherapist"
    ],
    "wof:name":"Vekeman Nico",
    "wof:placetype":"venue"
},
  "geometry": {"coordinates":[3.7978260517,50.8679771423],"type":"Point"}
}