{
  "type": "Feature",
  "properties": {
    "addr:full":"Kerkstraat 129 Grimbergen (humbeek) Vlaams-Brabant 1851",
    "addr:housenumber":"129",
    "addr:postcode":"1851",
    "addr:street":"Kerkstraat",
    "iso:country":"BE",
    "sg:address":"Kerkstraat 129",
    "sg:city":"Grimbergen (humbeek)",
    "sg:classifiers":[
        {
            "category":"Professional",
            "subcategory":"Testing Lab",
            "type":"Services"
        }
    ],
    "sg:phone":"+32 2 270 10 25",
    "sg:postcode":"1851",
    "sg:province":"Vlaams-Brabant",
    "sg:tags":[
        "chemist"
    ],
    "wof:name":"De Preter P",
    "wof:placetype":"venue"
},
  "geometry": {"coordinates":[4.3855810165,50.9731369019],"type":"Point"}
}