{
  "type": "Feature",
  "properties": {
    "iso:country":"BE",
    "sg:address":"R. Notre-dame De La Paix 1",
    "sg:city":"Chimay",
    "sg:orig_category":"Belastingconsulenten Diverse juridische dienstverlening",
    "sg:phone":"+32 60 21 25 79",
    "sg:postcode":"6460",
    "sg:province":"Hainaut",
    "wof:name":"Joel Gilot",
    "wof:placetype":"venue"
},
  "geometry": {"coordinates":[4.308909893,50.0493049622],"type":"Point"}
}