{
  "type": "Feature",
  "properties": {
    "iso:country":"BE",
    "sg:address":"Rue D\u00b4aerschot 262",
    "sg:city":"Schaarbeek/schaerbeek",
    "sg:orig_category":"Vitrage",
    "sg:phone":"+32 477 42 01 86",
    "sg:postcode":"1030",
    "sg:province":"Bruxelles-Capitale",
    "wof:name":"Artisan Assistance",
    "wof:placetype":"venue"
},
  "geometry": {"coordinates":[4.3656711578,50.8667755127],"type":"Point"}
}