{
  "type": "Feature",
  "properties": {
    "iso:country":"BE",
    "sg:address":"Chauss\u00c9e De Beaumont 80",
    "sg:city":"Froidchapelle",
    "sg:orig_category":"Entretien and r\u00e9parations de voitures",
    "sg:phone":"+32 71 63 33 46",
    "sg:postcode":"6440",
    "sg:province":"Hainaut",
    "wof:name":"Garage Victor",
    "wof:placetype":"venue"
},
  "geometry": {"coordinates":[4.3275232315,50.1511878967],"type":"Point"}
}