{
  "type": "Feature",
  "properties": {
    "iso:country":"BE",
    "sg:address":"Klein Lafeltstraat 2",
    "sg:city":"Riemst",
    "sg:orig_category":"Enseignement maternel and primaire",
    "sg:phone":"+32 12 45 28 42",
    "sg:postcode":"3770",
    "sg:province":"Limburg",
    "wof:name":"Gemeentel. Lagere School",
    "wof:placetype":"venue"
},
  "geometry": {"coordinates":[5.600689888,50.8100891113],"type":"Point"}
}