{
  "type": "Feature",
  "properties": {
    "addr:full":"Antwerpselaan 15 Brussel/bruxelles Bruxelles-Capitale 1000",
    "addr:housenumber":"15",
    "addr:postcode":"1000",
    "addr:street":"Antwerpselaan;/",
    "iso:country":"BE",
    "sg:address":"Antwerpselaan 15",
    "sg:city":"Brussel/bruxelles",
    "sg:classifiers":[
        {
            "category":"Fast Food",
            "type":"Food & Drink"
        }
    ],
    "sg:phone":"+32 2 217 71 82",
    "sg:postcode":"1000",
    "sg:province":"Bruxelles-Capitale",
    "sg:tags":[
        "meeneem",
        "restaurant"
    ],
    "wof:name":"Restaurant Paros",
    "wof:placetype":"venue"
},
  "geometry": {"coordinates":[4.3538498878,50.8562316895],"type":"Point"}
}