{
  "type": "Feature",
  "properties": {
    "addr:full":"Europark-noord 32 Sint-niklaas Oost-Vlaanderen 9100",
    "addr:housenumber":"32",
    "addr:postcode":"9100",
    "addr:street":"Europark-Noord",
    "iso:country":"BE",
    "sg:address":"Europark-noord 32",
    "sg:city":"Sint-niklaas",
    "sg:orig_category":"Studios photographiques. Traitement and rev\u00eatement des m\u00e9taux",
    "sg:phone":"+32 3 777 49 59",
    "sg:postcode":"9100",
    "sg:province":"Oost-Vlaanderen",
    "wof:name":"Reprometal",
    "wof:placetype":"venue"
},
  "geometry": {"coordinates":[4.1662569046,51.1686325073],"type":"Point"}
}