{
  "type": "Feature",
  "properties": {
    "iso:country":"BE",
    "sg:address":"Lotse Steenweg 71",
    "sg:city":"Beersel",
    "sg:classifiers":[
        {
            "category":"Communications",
            "subcategory":"Film & Video Production",
            "type":"Services"
        }
    ],
    "sg:phone":"+32 2 380 08 17",
    "sg:postcode":"1653",
    "sg:province":"Vlaams-Brabant",
    "sg:tags":[
        "commerce",
        "electrom\u00e9nager",
        "t\u00e9l\u00e9visions",
        "equipement",
        "pour",
        "radio",
        "diver"
    ],
    "wof:name":"Paternot J",
    "wof:placetype":"venue"
},
  "geometry": {"coordinates":[4.2991251945,50.7301254272],"type":"Point"}
}