{
  "type": "Feature",
  "properties": {
    "iso:country":"BE",
    "sg:address":"Rue Des Vennes 89",
    "sg:city":"Li\u00c8ge",
    "sg:orig_category":"Epiceries",
    "sg:phone":"+32 4 343 46 53",
    "sg:postcode":"4020",
    "sg:province":"Li\u00e8ge",
    "wof:name":"Anna Levenstond",
    "wof:placetype":"venue"
},
  "geometry": {"coordinates":[5.5858402252,50.6264038086],"type":"Point"}
}