{
  "type": "Feature",
  "properties": {
    "addr:full":"Rue Jean Lambert Sauveur 47 Herstal Li\u00e8ge 4040",
    "addr:housenumber":"47",
    "addr:postcode":"4040",
    "addr:street":"Rue Jean Lambert Sauveur",
    "iso:country":"BE",
    "sg:address":"Rue Jean Lambert Sauveur 47",
    "sg:city":"Herstal",
    "sg:orig_category":"Eclairage et \u00e9quipements du foyer. Librairies. Fournitures de bureau. Tabac. Journaux",
    "sg:phone":"+32 4 264 07 73",
    "sg:postcode":"4040",
    "sg:province":"Li\u00e8ge",
    "wof:name":"Librairie Balhan",
    "wof:placetype":"venue"
},
  "geometry": {"coordinates":[5.629983902,50.6736679077],"type":"Point"}
}