{
  "type": "Feature",
  "properties": {
    "iso:country":"BE",
    "sg:address":"Brugsesteenweg 18",
    "sg:city":"De Haan (wenduine)",
    "sg:classifiers":[
        {
            "category":"Shopping",
            "subcategory":"Florist",
            "type":"Retail Goods"
        }
    ],
    "sg:phone":"+32 50 41 23 44",
    "sg:postcode":"8420",
    "sg:province":"West-Vlaanderen",
    "wof:name":"Ameel",
    "wof:placetype":"venue"
},
  "geometry": {"coordinates":[3.0841710567,51.2965354919],"type":"Point"}
}