{
  "type": "Feature",
  "properties": {
    "iso:country":"BE",
    "sg:address":"Chemin De Renval 1",
    "sg:city":"Bastogne",
    "sg:orig_category":"Alternatieve geneeskunde",
    "sg:phone":"+32 61 21 41 53",
    "sg:postcode":"6600",
    "sg:province":"Luxembourg",
    "wof:name":"Inst.kin\u00c9siologie Luxemb.",
    "wof:placetype":"venue"
},
  "geometry": {"coordinates":[5.6987748146,50.0044898987],"type":"Point"}
}