{
  "type": "Feature",
  "properties": {
    "addr:full":"Patersstraat 174 Turnhout Antwerpen 2300",
    "addr:housenumber":"174",
    "addr:postcode":"2300",
    "addr:street":"Patersstraat",
    "iso:country":"BE",
    "sg:address":"Patersstraat 174",
    "sg:city":"Turnhout",
    "sg:orig_category":"Brood, gebak and snoepgoed",
    "sg:phone":"+32 14 41 18 44",
    "sg:postcode":"2300",
    "sg:province":"Antwerpen",
    "wof:name":"Bakk. Sips-van Der Veken",
    "wof:placetype":"venue"
},
  "geometry": {"coordinates":[4.9496498108,51.3277893066],"type":"Point"}
}