{
  "type": "Feature",
  "properties": {
    "addr:full":"Kleine Sint-amandsstraat 2 Brugge West-Vlaanderen 8000",
    "addr:housenumber":"2",
    "addr:postcode":"8000",
    "addr:street":"Kleine Sint-Amandsstraat",
    "iso:country":"BE",
    "sg:address":"Kleine Sint-amandsstraat 2",
    "sg:city":"Brugge",
    "sg:classifiers":[
        {
            "category":"Restaurant",
            "type":"Food & Drink"
        }
    ],
    "sg:phone":"+32 50 33 23 26",
    "sg:postcode":"8000",
    "sg:province":"West-Vlaanderen",
    "wof:name":"Le Due Venezie",
    "wof:placetype":"venue"
},
  "geometry": {"coordinates":[3.2225489616,51.2083587646],"type":"Point"}
}