{
  "type": "Feature",
  "properties": {
    "addr:full":"Meersstraat 5 Waregem West-Vlaanderen 8790",
    "addr:housenumber":"5",
    "addr:postcode":"8790",
    "addr:street":"Meersstraat",
    "iso:country":"BE",
    "sg:address":"Meersstraat 5",
    "sg:city":"Waregem",
    "sg:orig_category":"Sportcentra",
    "sg:phone":"+32 56 60 07 44",
    "sg:postcode":"8790",
    "sg:province":"West-Vlaanderen",
    "wof:name":"Gemeentelijke Sporthal",
    "wof:placetype":"venue"
},
  "geometry": {"coordinates":[3.4294810295,50.8848190308],"type":"Point"}
}