{
  "type": "Feature",
  "properties": {
    "iso:country":"BE",
    "sg:address":"Halvemaanstraat 59",
    "sg:city":"Gent (sint-amandsberg)",
    "sg:classifiers":[
        {
            "category":"Farming",
            "subcategory":"Farm & Veterinary Services",
            "type":"Manufacturing & Wholesale Goods"
        }
    ],
    "sg:phone":"+32 9 229 14 47",
    "sg:postcode":"9040",
    "sg:province":"Oost-Vlaanderen",
    "sg:tags":[
        "agricultural",
        "contractor"
    ],
    "wof:name":"Tulpen",
    "wof:placetype":"venue"
},
  "geometry": {"coordinates":[3.7464311123,51.0626487732],"type":"Point"}
}