{
  "type": "Feature",
  "properties": {
    "addr:full":"Melkstraat 126 Machelen Vlaams-Brabant 1830",
    "addr:housenumber":"126",
    "addr:postcode":"1830",
    "addr:street":"Melkstraat",
    "iso:country":"BE",
    "sg:address":"Melkstraat 126",
    "sg:city":"Machelen",
    "sg:classifiers":[
        {
            "category":"Wholesale",
            "subcategory":"Beer",
            "type":"Manufacturing & Wholesale Goods"
        }
    ],
    "sg:phone":"+32 2 251 81 94",
    "sg:postcode":"1830",
    "sg:province":"Vlaams-Brabant",
    "sg:tags":[
        "ale",
        "-"
    ],
    "wof:name":"Vander Schelde W",
    "wof:placetype":"venue"
},
  "geometry": {"coordinates":[4.4385647774,50.9051055908],"type":"Point"}
}