{
  "type": "Feature",
  "properties": {
    "iso:country":"BE",
    "sg:address":"Chauss\u00c9e De Louvain 420",
    "sg:city":"Namur",
    "sg:orig_category":"Dierenartsen",
    "sg:phone":"+32 81 21 32 93",
    "sg:postcode":"5004",
    "sg:province":"Namur",
    "wof:name":"Fran\u00c7oise Lessire",
    "wof:placetype":"venue"
},
  "geometry": {"coordinates":[4.8852128983,50.4823532104],"type":"Point"}
}