{
  "type": "Feature",
  "properties": {
    "iso:country":"BE",
    "sg:address":"Noville 14",
    "sg:city":"Bastogne (noville)",
    "sg:classifiers":[
        {
            "category":"Building & Trades",
            "subcategory":"Electrical",
            "type":"Services"
        }
    ],
    "sg:phone":"+32 61 21 28 12",
    "sg:postcode":"6600",
    "sg:province":"Luxembourg",
    "sg:tags":[
        "heating"
    ],
    "wof:name":"Thermilux Ets",
    "wof:placetype":"venue"
},
  "geometry": {"coordinates":[5.7148199081,50.0007820129],"type":"Point"}
}