{
  "type": "Feature",
  "properties": {
    "iso:country":"BE",
    "sg:address":"Rue De Wasseiges 26",
    "sg:city":"Hannut",
    "sg:orig_category":"Eleveurs de bovins",
    "sg:phone":"+32 19 51 38 64",
    "sg:postcode":"4280",
    "sg:province":"Li\u00e8ge",
    "wof:name":"Jean Lhonnay",
    "wof:placetype":"venue"
},
  "geometry": {"coordinates":[5.0624871254,50.6581687927],"type":"Point"}
}