{
  "type": "Feature",
  "properties": {
    "addr:full":"Moerstraat 5 Zele Oost-Vlaanderen 9240",
    "addr:housenumber":"5",
    "addr:postcode":"9240",
    "addr:street":"Moerstraat",
    "iso:country":"BE",
    "sg:address":"Moerstraat 5",
    "sg:city":"Zele",
    "sg:classifiers":[
        {
            "category":"Manufacturing",
            "subcategory":"Tools & Machinery",
            "type":"Manufacturing & Wholesale Goods"
        }
    ],
    "sg:phone":"+32 52 44 81 19",
    "sg:postcode":"9240",
    "sg:province":"Oost-Vlaanderen",
    "sg:tags":[
        "builder"
    ],
    "wof:name":"P.m.a. Industrial",
    "wof:placetype":"venue"
},
  "geometry": {"coordinates":[4.0410971642,51.0718307495],"type":"Point"}
}