{
  "type": "Feature",
  "properties": {
    "iso:country":"BE",
    "sg:address":"Stationsstraat 20",
    "sg:city":"Kortemark",
    "sg:orig_category":"Quincailleries. Plomberie, chauffage and installations sanitaires",
    "sg:phone":"+32 51 56 74 97",
    "sg:postcode":"8610",
    "sg:province":"West-Vlaanderen",
    "wof:name":"Guido Lagae",
    "wof:placetype":"venue"
},
  "geometry": {"coordinates":[3.0420498848,51.0253181458],"type":"Point"}
}