{
  "type": "Feature",
  "properties": {
    "addr:full":"Rue De La Laderie 21 La Bruy\u00c8re Namur 5080",
    "addr:housenumber":"21",
    "addr:postcode":"5080",
    "addr:street":"Rue De La Laderie",
    "iso:country":"BE",
    "sg:address":"Rue De La Laderie 21",
    "sg:city":"La Bruy\u00c8re",
    "sg:orig_category":"Elektrische installaties voor woningen",
    "sg:phone":"+32 81 21 33 51",
    "sg:postcode":"5080",
    "sg:province":"Namur",
    "wof:name":"Leclercq Jacques",
    "wof:placetype":"venue"
},
  "geometry": {"coordinates":[4.8354701996,50.5233688354],"type":"Point"}
}