{
  "type": "Feature",
  "properties": {
    "addr:full":"Square Des Conduites D' Eau 13-14 Liege Li\u00e8ge 4020",
    "addr:housenumber":"13-14",
    "addr:postcode":"4020",
    "addr:street":"Square Des Conduites D ' Eau",
    "iso:country":"BE",
    "sg:address":"Square Des Conduites D' Eau 13-14",
    "sg:city":"Liege",
    "sg:orig_category":"Sociale secretariaten Verplichte sociale verzekeringen",
    "sg:phone":"+32 4 349 25 00",
    "sg:postcode":"4020",
    "sg:province":"Li\u00e8ge",
    "wof:name":"Partena",
    "wof:placetype":"venue"
},
  "geometry": {"coordinates":[5.5892472267,50.638874054],"type":"Point"}
}