{
  "type": "Feature",
  "properties": {
    "iso:country":"BE",
    "sg:address":"Markweg 2",
    "sg:city":"Hoogstraten",
    "sg:orig_category":"Fruitteelt",
    "sg:phone":"+32 3 315 80 14",
    "sg:postcode":"2328",
    "sg:province":"Antwerpen",
    "wof:name":"Frans Van Dun",
    "wof:placetype":"venue"
},
  "geometry": {"coordinates":[4.7920198441,51.4978485107],"type":"Point"}
}