{
  "type": "Feature",
  "properties": {
    "iso:country":"BE",
    "sg:address":"Chauss\u00c9e De March\u00c9 601bc",
    "sg:city":"Namur",
    "sg:orig_category":"Onderhoud van kantoor- and computeruitrusting",
    "sg:phone":"+32 81 32 04 50",
    "sg:postcode":"5101",
    "sg:province":"Namur",
    "wof:name":"Getronics Service",
    "wof:placetype":"venue"
},
  "geometry": {"coordinates":[4.9087619781,50.4395065308],"type":"Point"}
}