{
  "type": "Feature",
  "properties": {
    "addr:full":"Rue C\u00e9sar Despretz 62 Lessines Hainaut 7860",
    "addr:housenumber":"62",
    "addr:postcode":"7860",
    "addr:street":"Rue Ce\u0301Sar Despretz;Hainaut",
    "iso:country":"BE",
    "sg:address":"Rue C\u00e9sar Despretz 62",
    "sg:city":"Lessines",
    "sg:classifiers":[
        {
            "category":"Shopping",
            "subcategory":"Computers & Home Electronics",
            "type":"Retail Goods"
        }
    ],
    "sg:phone":"+32 68 33 65 66",
    "sg:postcode":"7860",
    "sg:province":"Hainaut",
    "sg:tags":[
        "tool",
        "-"
    ],
    "wof:name":"Equiptronic Sprl",
    "wof:placetype":"venue"
},
  "geometry": {"coordinates":[3.828263998,50.7104682922],"type":"Point"}
}