{
  "type": "Feature",
  "properties": {
    "addr:full":"Rue Royale 74 Tournai Hainaut 7500",
    "addr:housenumber":"74",
    "addr:postcode":"7500",
    "addr:street":"Rue Royale",
    "iso:country":"BE",
    "sg:address":"Rue Royale 74",
    "sg:city":"Tournai",
    "sg:classifiers":[
        {
            "category":"Professional",
            "subcategory":"Testing Lab",
            "type":"Services"
        }
    ],
    "sg:phone":"+32 69 84 33 83",
    "sg:postcode":"7500",
    "sg:province":"Hainaut",
    "sg:tags":[
        "laboratory",
        "photographic",
        "film"
    ],
    "wof:name":"Photo Royale-kodak Express",
    "wof:placetype":"venue"
},
  "geometry": {"coordinates":[3.3945229053,50.6112670898],"type":"Point"}
}