{
  "type": "Feature",
  "properties": {
    "addr:full":"Christinastraat 20 Oostende West-Vlaanderen 8400",
    "addr:housenumber":"20",
    "addr:postcode":"8400",
    "addr:street":"Christinastraat",
    "iso:country":"BE",
    "sg:address":"Christinastraat 20",
    "sg:city":"Oostende",
    "sg:classifiers":[
        {
            "category":"Restaurant",
            "type":"Food & Drink"
        }
    ],
    "sg:phone":"+32 59 80 99 69",
    "sg:postcode":"8400",
    "sg:province":"West-Vlaanderen",
    "wof:name":"Wiener Caffee",
    "wof:placetype":"venue"
},
  "geometry": {"coordinates":[2.9155619144,51.2323074341],"type":"Point"}
}