{
  "type": "Feature",
  "properties": {
    "addr:full":"Brusselsesteenweg 504 Mechelen Antwerpen 2800",
    "addr:housenumber":"504",
    "addr:postcode":"2800",
    "addr:street":"Brusselsesteenweg",
    "iso:country":"BE",
    "sg:address":"Brusselsesteenweg 504",
    "sg:city":"Mechelen",
    "sg:classifiers":[
        {
            "category":"Communications",
            "subcategory":"Radio Station",
            "type":"Services"
        }
    ],
    "sg:phone":"+32 15 41 49 53",
    "sg:postcode":"2800",
    "sg:province":"Antwerpen",
    "sg:tags":[
        "telephony"
    ],
    "wof:name":"Pep Engineering Bvba",
    "wof:placetype":"venue"
},
  "geometry": {"coordinates":[4.4737458229,50.9997596741],"type":"Point"}
}