{
  "type": "Feature",
  "properties": {
    "addr:full":"Veeweidestraat 11 Huldenberg Vlaams-Brabant 3040",
    "addr:housenumber":"11",
    "addr:postcode":"3040",
    "addr:street":"Veeweidestraat",
    "iso:country":"BE",
    "sg:address":"Veeweidestraat 11",
    "sg:city":"Huldenberg",
    "sg:orig_category":"Boekhouders",
    "sg:phone":"+32 16 47 13 86",
    "sg:postcode":"3040",
    "sg:province":"Vlaams-Brabant",
    "wof:name":"Van Bockstael Luc",
    "wof:placetype":"venue"
},
  "geometry": {"coordinates":[4.5709900856,50.8141784668],"type":"Point"}
}