{
  "type": "Feature",
  "properties": {
    "iso:country":"BE",
    "sg:address":"Magnolialaan 3",
    "sg:city":"Kapellen",
    "sg:orig_category":"Agences d'exp\u00e9dition",
    "sg:phone":"+32 3 605 00 24",
    "sg:postcode":"2950",
    "sg:province":"Antwerpen",
    "wof:name":"Intermarine",
    "wof:placetype":"venue"
},
  "geometry": {"coordinates":[4.4250478745,51.3293571472],"type":"Point"}
}