{
  "type": "Feature",
  "properties": {
    "iso:country":"BE",
    "sg:address":"Rue De La Croix Jurlet 176",
    "sg:city":"Herstal",
    "sg:classifiers":[
        {
            "category":"Arena",
            "subcategory":"Sports Club",
            "type":"Entertainment"
        }
    ],
    "sg:phone":"+32 4 264 09 12",
    "sg:postcode":"4040",
    "sg:province":"Li\u00e8ge",
    "sg:tags":[
        "de"
    ],
    "wof:name":"B.b.c. Inter Herstal",
    "wof:placetype":"venue"
},
  "geometry": {"coordinates":[5.6318697929,50.6730194092],"type":"Point"}
}