{
  "type": "Feature",
  "properties": {
    "addr:full":"Nieuwstraat 17 Steenokkerzeel Vlaams-Brabant 1820",
    "addr:housenumber":"17",
    "addr:postcode":"1820",
    "addr:street":"Nieuwstraat",
    "iso:country":"BE",
    "sg:address":"Nieuwstraat 17",
    "sg:city":"Steenokkerzeel",
    "sg:classifiers":[
        {
            "category":"Arena",
            "subcategory":"Sports Club",
            "type":"Entertainment"
        }
    ],
    "sg:phone":"+32 2 305 75 89",
    "sg:postcode":"1820",
    "sg:province":"Vlaams-Brabant",
    "wof:name":"Atletiek-club-kortenberg-overijse",
    "wof:placetype":"venue"
},
  "geometry": {"coordinates":[4.5084738731,50.9153060913],"type":"Point"}
}