{
  "type": "Feature",
  "properties": {
    "iso:country":"BE",
    "sg:address":"Lierselei 181",
    "sg:city":"Malle (oostmalle)",
    "sg:orig_category":"Non-Classified Establishments",
    "sg:phone":"+32 3 312 45 11",
    "sg:postcode":"2390",
    "sg:province":"Antwerpen",
    "wof:name":"Van Der Plaetsen Nv",
    "wof:placetype":"venue"
},
  "geometry": {"coordinates":[4.7237110138,51.2841720581],"type":"Point"}
}