{
  "type": "Feature",
  "properties": {
    "addr:full":"Rue De La D\u00e9portation 47 Tubize Brabant Wallon 1480",
    "addr:housenumber":"47",
    "addr:postcode":"1480",
    "addr:street":"Rue De La De\u0301Portation;Wallon",
    "iso:country":"BE",
    "sg:address":"Rue De La D\u00e9portation 47",
    "sg:city":"Tubize",
    "sg:classifiers":[
        {
            "category":"Banks & Credit Unions",
            "subcategory":"Financial Services",
            "type":"Services"
        }
    ],
    "sg:phone":"+32 2 355 62 37",
    "sg:postcode":"1480",
    "sg:province":"Brabant Wallon",
    "sg:tags":[
        "banking",
        "finance",
        "insurance"
    ],
    "wof:name":"Beltex Sa",
    "wof:placetype":"venue"
},
  "geometry": {"coordinates":[4.2079348564,50.6922836304],"type":"Point"}
}