{
  "type": "Feature",
  "properties": {
    "addr:full":"Chauss\u00c9e De Bruxelles 145 Wemmel Vlaams-Brabant 1780",
    "addr:housenumber":"145",
    "addr:postcode":"1780",
    "addr:street":"Chausse\u0301E De Bruxelles;Vlaams-Brabant",
    "iso:country":"BE",
    "sg:address":"Chauss\u00c9e De Bruxelles 145",
    "sg:city":"Wemmel",
    "sg:orig_category":"Bloemen and planten Fleurop Interflora",
    "sg:phone":"+32 2 461 04 14",
    "sg:postcode":"1780",
    "sg:province":"Vlaams-Brabant",
    "wof:name":"Fleurs Goossens",
    "wof:placetype":"venue"
},
  "geometry": {"coordinates":[4.3059768677,50.9031906128],"type":"Point"}
}