{
  "type": "Feature",
  "properties": {
    "iso:country":"BE",
    "sg:address":"Rue Henri L\u00c9onard 43",
    "sg:city":"Manage",
    "sg:orig_category":"Traitements param\u00e9dicaux",
    "sg:phone":"+32 64 21 18 00",
    "sg:postcode":"7170",
    "sg:province":"Hainaut",
    "wof:name":"Monachino Giuseppina",
    "wof:placetype":"venue"
},
  "geometry": {"coordinates":[4.2398138046,50.4764518738],"type":"Point"}
}