{
  "type": "Feature",
  "properties": {
    "iso:country":"BE",
    "sg:address":"Oosteeklodorp 22",
    "sg:city":"Assenede",
    "sg:orig_category":"Journaux. Fournitures de bureau",
    "sg:phone":"+32 9 373 53 07",
    "sg:postcode":"9968",
    "sg:province":"Oost-Vlaanderen",
    "wof:name":"Arsene Reyniers",
    "wof:placetype":"venue"
},
  "geometry": {"coordinates":[3.688352108,51.1921653748],"type":"Point"}
}