{
  "type": "Feature",
  "properties": {
    "iso:country":"BE",
    "sg:address":"Rue Des Corbeaux 19",
    "sg:city":"Grez-doiceau (bossut-gottechain)",
    "sg:classifiers":[
        {
            "category":"Brewery",
            "type":"Food & Drink"
        }
    ],
    "sg:phone":"+32 10 84 51 35",
    "sg:postcode":"1390",
    "sg:province":"Brabant Wallon",
    "wof:name":"Drakson",
    "wof:placetype":"venue"
},
  "geometry": {"coordinates":[4.6916828156,50.7582969666],"type":"Point"}
}