{
  "type": "Feature",
  "properties": {
    "iso:country":"BE",
    "sg:address":"Kuiermansstraat 1",
    "sg:city":"Kapelle-op-den-bos",
    "sg:classifiers":[
        {
            "category":"Government",
            "subcategory":"Fire Station",
            "type":"Public Place"
        }
    ],
    "sg:phone":"+32 15 71 33 51",
    "sg:postcode":"1880",
    "sg:province":"Vlaams-Brabant",
    "sg:tags":[
        "bricks",
        "acid",
        "proof"
    ],
    "wof:name":"Promat Nv",
    "wof:placetype":"venue"
},
  "geometry": {"coordinates":[4.3609890938,51.0101623535],"type":"Point"}
}