{
  "type": "Feature",
  "properties": {
    "addr:full":"Kortrijkstraat 31 Oudenaarde Oost-Vlaanderen 9700",
    "addr:housenumber":"31",
    "addr:postcode":"9700",
    "addr:street":"Kortrijkstraat",
    "iso:country":"BE",
    "sg:address":"Kortrijkstraat 31",
    "sg:city":"Oudenaarde",
    "sg:orig_category":"Quincailleries. Bois Gr",
    "sg:phone":"+32 55 31 14 87",
    "sg:postcode":"9700",
    "sg:province":"Oost-Vlaanderen",
    "wof:name":"Dirk Van De Weghe",
    "wof:placetype":"venue"
},
  "geometry": {"coordinates":[3.5926389694,50.8502464294],"type":"Point"}
}