{
  "type": "Feature",
  "properties": {
    "iso:country":"BE",
    "sg:address":"Rue Du Try Martin 4",
    "sg:city":"Louvain-la-neuve",
    "sg:classifiers":[
        {
            "category":"Shopping",
            "subcategory":"Computers & Home Electronics",
            "type":"Retail Goods"
        }
    ],
    "sg:phone":"+32 10 23 21 53",
    "sg:postcode":"1348",
    "sg:province":"Brabant Wallon",
    "sg:tags":[
        "computerapparatuur",
        "microsoft"
    ],
    "wof:name":"Tdh Computers",
    "wof:placetype":"venue"
},
  "geometry": {"coordinates":[4.6087927818,50.6727142334],"type":"Point"}
}