{
  "type": "Feature",
  "properties": {
    "iso:country":"BE",
    "sg:address":"Ambachtsstraat 50",
    "sg:city":"Malle",
    "sg:orig_category":"Installatie van houten of kunststof schrijnwerk",
    "sg:phone":"+32 3 312 14 85",
    "sg:postcode":"2390",
    "sg:province":"Antwerpen",
    "wof:name":"De Houwer H.",
    "wof:placetype":"venue"
},
  "geometry": {"coordinates":[4.7081971169,51.2912902832],"type":"Point"}
}