{
  "type": "Feature",
  "properties": {
    "addr:full":"Rue Du Ch\u00e2telain 24 Bruxelles (ixelles) Bruxelles-Capitale 1050",
    "addr:housenumber":"24",
    "addr:postcode":"1050",
    "addr:street":"Rue Du Cha\u0302Telain",
    "iso:country":"BE",
    "sg:address":"Rue Du Ch\u00e2telain 24",
    "sg:city":"Bruxelles (ixelles)",
    "sg:classifiers":[
        {
            "category":"Real Estate",
            "subcategory":"Surveying",
            "type":"Services"
        }
    ],
    "sg:phone":"+32 2 647 06 55",
    "sg:postcode":"1050",
    "sg:province":"Bruxelles-Capitale",
    "sg:tags":[
        "surveyor",
        "land"
    ],
    "wof:name":"Delhaye J",
    "wof:placetype":"venue"
},
  "geometry": {"coordinates":[4.3624968529,50.825553894],"type":"Point"}
}