{
  "type": "Feature",
  "properties": {
    "addr:full":"Rue Lafayette 73 Rochefort Namur 5580",
    "addr:housenumber":"73",
    "addr:postcode":"5580",
    "addr:street":"Rue Lafayette",
    "iso:country":"BE",
    "sg:address":"Rue Lafayette 73",
    "sg:city":"Rochefort",
    "sg:orig_category":"Traitements param\u00e9dicaux",
    "sg:phone":"+32 84 21 10 89",
    "sg:postcode":"5580",
    "sg:province":"Namur",
    "wof:name":"Fe. Renard-imbreckx",
    "wof:placetype":"venue"
},
  "geometry": {"coordinates":[5.2244210243,50.151802063],"type":"Point"}
}