{
  "type": "Feature",
  "properties": {
    "iso:country":"BE",
    "sg:address":"Klein Boom 9",
    "sg:city":"Putte",
    "sg:classifiers":[
        {
            "category":"Shopping",
            "subcategory":"Discount & Variety Stores",
            "type":"Retail Goods"
        }
    ],
    "sg:phone":"+32 15 76 76 60",
    "sg:postcode":"2580",
    "sg:province":"Antwerpen",
    "sg:tags":[
        "warehouse",
        "-",
        "merchandise"
    ],
    "wof:name":"Van Loock Warehousing Bvba",
    "wof:placetype":"venue"
},
  "geometry": {"coordinates":[4.6099758148,51.050163269],"type":"Point"}
}