{
  "type": "Feature",
  "properties": {
    "addr:full":"Wissenboslaan 12 Antwerpen (hoboken) Antwerpen 2660",
    "addr:housenumber":"12",
    "addr:postcode":"2660",
    "addr:street":"Wissenboslaan",
    "iso:country":"BE",
    "sg:address":"Wissenboslaan 12",
    "sg:city":"Antwerpen (hoboken)",
    "sg:classifiers":[
        {
            "category":"Utilities",
            "subcategory":"Telephone",
            "type":"Services"
        }
    ],
    "sg:phone":"+32 3 288 58 07",
    "sg:postcode":"2660",
    "sg:province":"Antwerpen",
    "sg:tags":[
        "-",
        "internet"
    ],
    "wof:name":"Desonet",
    "wof:placetype":"venue"
},
  "geometry": {"coordinates":[4.3364138603,51.1850852966],"type":"Point"}
}