{
  "type": "Feature",
  "properties": {
    "addr:full":"Korte Zavelstraat 27 Antwerpen Antwerpen 2060",
    "addr:housenumber":"27",
    "addr:postcode":"2060",
    "addr:street":"Korte Zavelstraat",
    "iso:country":"BE",
    "sg:address":"Korte Zavelstraat 27",
    "sg:city":"Antwerpen",
    "sg:orig_category":"Pain, p\u00e2tisseries and confiseries",
    "sg:phone":"+32 3 232 92 45",
    "sg:postcode":"2060",
    "sg:province":"Antwerpen",
    "wof:name":"Luc Smet",
    "wof:placetype":"venue"
},
  "geometry": {"coordinates":[4.4266700745,51.2232551575],"type":"Point"}
}