{
  "type": "Feature",
  "properties": {
    "addr:full":"Avenue Chazal 168 Bruxelles (schaerbeek) Bruxelles-Capitale 1030",
    "addr:housenumber":"168",
    "addr:postcode":"1030",
    "addr:street":"Avenue Chazal",
    "iso:country":"BE",
    "sg:address":"Avenue Chazal 168",
    "sg:city":"Bruxelles (schaerbeek)",
    "sg:classifiers":[
        {
            "category":"Health Services",
            "subcategory":"Dentist",
            "type":"Services"
        }
    ],
    "sg:phone":"+32 2 216 70 73",
    "sg:postcode":"1030",
    "sg:province":"Bruxelles-Capitale",
    "wof:name":"Tanghe Martine",
    "wof:placetype":"venue"
},
  "geometry": {"coordinates":[4.3905777931,50.8582382202],"type":"Point"}
}