{
  "type": "Feature",
  "properties": {
    "addr:full":"Rue Victor Forthomme 44 Sprimont Li\u00e8ge 4140",
    "addr:housenumber":"44",
    "addr:postcode":"4140",
    "addr:street":"Rue Victor Forthomme",
    "iso:country":"BE",
    "sg:address":"Rue Victor Forthomme 44",
    "sg:city":"Sprimont",
    "sg:classifiers":[
        {
            "category":"Arena",
            "subcategory":"Sports Club",
            "type":"Entertainment"
        }
    ],
    "sg:phone":"+32 4 382 42 40",
    "sg:postcode":"4140",
    "sg:province":"Li\u00e8ge",
    "sg:tags":[
        "de"
    ],
    "wof:name":"V.b. Sprimont",
    "wof:placetype":"venue"
},
  "geometry": {"coordinates":[5.6597499847,50.5072059631],"type":"Point"}
}