{
  "type": "Feature",
  "properties": {
    "addr:full":"Diestsestraat 192 Leuven Vlaams-Brabant 3000",
    "addr:housenumber":"192",
    "addr:postcode":"3000",
    "addr:street":"Diestsestraat",
    "iso:country":"BE",
    "sg:address":"Diestsestraat 192",
    "sg:city":"Leuven",
    "sg:orig_category":"Articles de sport, camping and jouets V\u00e9los",
    "sg:phone":"+32 16 22 39 16",
    "sg:postcode":"3000",
    "sg:province":"Vlaams-Brabant",
    "wof:name":"Rijwielen Hugo Jacobs",
    "wof:placetype":"venue"
},
  "geometry": {"coordinates":[4.7108469009,50.8816108704],"type":"Point"}
}