{
  "type": "Feature",
  "properties": {
    "addr:full":"Kouterstraat 32 Herzele Oost-Vlaanderen 9550",
    "addr:housenumber":"32",
    "addr:postcode":"9550",
    "addr:street":"Kouterstraat;Oost-Vlaanderen",
    "iso:country":"BE",
    "sg:address":"Kouterstraat 32",
    "sg:city":"Herzele",
    "sg:classifiers":[
        {
            "category":"Health Services",
            "subcategory":"Health Practitioner",
            "type":"Services"
        }
    ],
    "sg:phone":"+32 53 62 70 74",
    "sg:postcode":"9550",
    "sg:province":"Oost-Vlaanderen",
    "sg:tags":[
        "physiotherapist"
    ],
    "wof:name":"De Doncker H",
    "wof:placetype":"venue"
},
  "geometry": {"coordinates":[3.8839459419,50.8899536133],"type":"Point"}
}