{
  "type": "Feature",
  "properties": {
    "iso:country":"BE",
    "sg:address":"Bredabaan 271",
    "sg:city":"Brasschaat",
    "sg:orig_category":"Textiel",
    "sg:phone":"+32 3 652 03 40",
    "sg:postcode":"2930",
    "sg:province":"Antwerpen",
    "wof:name":"Butler Huishoudtextiel",
    "wof:placetype":"venue"
},
  "geometry": {"coordinates":[4.4875421524,51.2879638672],"type":"Point"}
}