{
  "type": "Feature",
  "properties": {
    "iso:country":"BE",
    "sg:address":"Cardijnstraat 12b1",
    "sg:city":"Zemst",
    "sg:classifiers":[
        {
            "category":"Restaurant",
            "type":"Food & Drink"
        }
    ],
    "sg:phone":"+32 15 62 13 46",
    "sg:postcode":"1980",
    "sg:province":"Vlaams-Brabant",
    "sg:tags":[
        "caf\u00e9s"
    ],
    "wof:name":"Taverne Aubergine",
    "wof:placetype":"venue"
},
  "geometry": {"coordinates":[4.4556188583,50.9617042542],"type":"Point"}
}