{
  "type": "Feature",
  "properties": {
    "iso:country":"BE",
    "sg:address":"Venlosesteenweg 95",
    "sg:city":"Kinrooi",
    "sg:orig_category":"Imprimeries and copyshops. Tabac. Fournitures de bureau. Journaux. Equipement photographique",
    "sg:phone":"+32 89 56 23 81",
    "sg:postcode":"3640",
    "sg:province":"Limburg",
    "wof:name":"Kwaspen",
    "wof:placetype":"venue"
},
  "geometry": {"coordinates":[5.8021359444,51.1262664795],"type":"Point"}
}