{
  "type": "Feature",
  "properties": {
    "iso:country":"BE",
    "sg:address":"2 Route De Baudour",
    "sg:city":"Ghlin",
    "sg:classifiers":[
        {
            "category":"Manufacturing",
            "subcategory":"Glass & Minerals",
            "type":"Manufacturing & Wholesale Goods"
        }
    ],
    "sg:phone":"+32 65 39 52 50",
    "sg:postcode":"7011",
    "sg:province":"Hainaut",
    "sg:tags":[
        "building",
        "material"
    ],
    "wof:name":"La Manufacture Du Verre",
    "wof:placetype":"venue"
},
  "geometry": {"coordinates":[3.8931069374,50.47473526],"type":"Point"}
}