{
  "type": "Feature",
  "properties": {
    "iso:country":"BE",
    "sg:address":"Grote Baan 150",
    "sg:city":"Lovendegem",
    "sg:orig_category":"Benzinestations and brandstoffen Herstellingen and onderhoud van auto's Voertuigen",
    "sg:phone":"+32 9 372 96 17",
    "sg:postcode":"9920",
    "sg:province":"Oost-Vlaanderen",
    "wof:name":"Maeyens W",
    "wof:placetype":"venue"
},
  "geometry": {"coordinates":[3.63180089,51.102230072],"type":"Point"}
}