{
  "type": "Feature",
  "properties": {
    "iso:country":"BE",
    "sg:address":"Generaal De Wittelaan 17 Box 3",
    "sg:city":"Mechelen",
    "sg:classifiers":[
        {
            "category":"Shopping",
            "subcategory":"Computers & Home Electronics",
            "type":"Retail Goods"
        }
    ],
    "sg:phone":"+32 15 28 08 00",
    "sg:postcode":"2800",
    "sg:province":"Antwerpen",
    "sg:tags":[
        "personal",
        "-",
        "processing",
        "data"
    ],
    "wof:name":"Info'products Belgi\u00eb",
    "wof:placetype":"venue"
},
  "geometry": {"coordinates":[4.4549531937,51.053237915],"type":"Point"}
}