{
  "type": "Feature",
  "properties": {
    "iso:country":"BE",
    "sg:address":"Najadenlaan 15",
    "sg:city":"Watermaal-bosvoorde/watermael-boitsfort",
    "sg:orig_category":"Architecten",
    "sg:phone":"+32 2 673 55 70",
    "sg:postcode":"1170",
    "sg:province":"Bruxelles-Capitale",
    "wof:name":"Paul Hertsens",
    "wof:placetype":"venue"
},
  "geometry": {"coordinates":[4.4113969803,50.8042564392],"type":"Point"}
}