{
  "type": "Feature",
  "properties": {
    "addr:full":"Avenue Michel Ange 54 Bruxelles Bruxelles-Capitale 1000",
    "addr:housenumber":"54",
    "addr:postcode":"1000",
    "addr:street":"Avenue Michel Ange",
    "iso:country":"BE",
    "sg:address":"Avenue Michel Ange 54",
    "sg:city":"Bruxelles",
    "sg:classifiers":[
        {
            "category":"Health Services",
            "subcategory":"Nursing And Care Facility",
            "type":"Services"
        }
    ],
    "sg:phone":"+32 2 734 95 18",
    "sg:postcode":"1000",
    "sg:province":"Bruxelles-Capitale",
    "sg:tags":[
        "home",
        "rest"
    ],
    "wof:name":"Alverna",
    "wof:placetype":"venue"
},
  "geometry": {"coordinates":[4.3861470222,50.844871521],"type":"Point"}
}