{
  "type": "Feature",
  "properties": {
    "iso:country":"BE",
    "sg:address":"Galerie De La Porte Louise 43",
    "sg:city":"Bruxelles-ixelles",
    "sg:classifiers":[
        {
            "category":"Utilities",
            "subcategory":"Telephone",
            "type":"Services"
        }
    ],
    "sg:phone":"+32 2 213 14 40",
    "sg:postcode":"1050",
    "sg:province":"Bruxelles-Capitale",
    "sg:tags":[
        "phone",
        "telecommunicatiesystemen",
        "house"
    ],
    "wof:name":"The Phone House",
    "wof:placetype":"venue"
},
  "geometry": {"coordinates":[4.3567042351,50.835231781],"type":"Point"}
}