{
  "type": "Feature",
  "properties": {
    "iso:country":"BE",
    "sg:address":"Tieltsesteenweg 51",
    "sg:city":"Oostrozebeke",
    "sg:orig_category":"Bloemen and planten",
    "sg:phone":"+32 56 66 49 61",
    "sg:postcode":"8780",
    "sg:province":"West-Vlaanderen",
    "wof:name":"Van Der Cruyssen",
    "wof:placetype":"venue"
},
  "geometry": {"coordinates":[3.3351449966,50.9201011658],"type":"Point"}
}