{
  "type": "Feature",
  "properties": {
    "addr:full":"Rue Blanc Try 4 Wavre Brabant Wallon 1301",
    "addr:housenumber":"4;1301",
    "addr:street":"Rue Blanc Try",
    "iso:country":"BE",
    "sg:address":"Rue Blanc Try 4",
    "sg:city":"Wavre",
    "sg:orig_category":"Woningbouw",
    "sg:phone":"+32 10 41 37 06",
    "sg:postcode":"1301",
    "sg:province":"Brabant Wallon",
    "wof:name":"Moisse",
    "wof:placetype":"venue"
},
  "geometry": {"coordinates":[4.5770459175,50.7114677429],"type":"Point"}
}