{
  "type": "Feature",
  "properties": {
    "addr:full":"Lindestraat 32 Gooik Vlaams-Brabant 1755",
    "addr:housenumber":"32",
    "addr:postcode":"1755",
    "addr:street":"Lindestraat",
    "iso:country":"BE",
    "sg:address":"Lindestraat 32",
    "sg:city":"Gooik",
    "sg:orig_category":"Belastingconsulenten Diverse juridische dienstverlening",
    "sg:phone":"+32 54 56 82 77",
    "sg:postcode":"1755",
    "sg:province":"Vlaams-Brabant",
    "wof:name":"Accountantskantoor Caro",
    "wof:placetype":"venue"
},
  "geometry": {"coordinates":[4.1037478447,50.7965774536],"type":"Point"}
}