{
  "type": "Feature",
  "properties": {
    "addr:full":"Klein Heiken 42 Kapellen Antwerpen 2950",
    "addr:housenumber":"42",
    "addr:postcode":"2950",
    "addr:street":"Klein Heiken",
    "iso:country":"BE",
    "sg:address":"Klein Heiken 42",
    "sg:city":"Kapellen",
    "sg:orig_category":"Kapsalons",
    "sg:phone":"+32 3 664 47 89",
    "sg:postcode":"2950",
    "sg:province":"Antwerpen",
    "wof:name":"Coiffure Glenn",
    "wof:placetype":"venue"
},
  "geometry": {"coordinates":[4.432393074,51.304561615],"type":"Point"}
}