{
  "type": "Feature",
  "properties": {
    "iso:country":"BE",
    "sg:address":"Simarstrasse 5",
    "sg:city":"Eupen",
    "sg:classifiers":[
        {
            "category":"Health Services",
            "subcategory":"Dentist",
            "type":"Services"
        }
    ],
    "sg:phone":"+32 87 74 32 52",
    "sg:postcode":"4700",
    "sg:province":"Li\u00e8ge",
    "wof:name":"Bosch Myriam",
    "wof:placetype":"venue"
},
  "geometry": {"coordinates":[6.0306081772,50.6325111389],"type":"Point"}
}