{
  "type": "Feature",
  "properties": {
    "addr:full":"Hellestraat 19 Box 163 Wevelgem West-Vlaanderen 8560",
    "addr:housenumber":"19",
    "addr:postcode":"8560",
    "addr:street":"Hellestraat;Box 163",
    "iso:country":"BE",
    "sg:address":"Hellestraat 19 Box 163",
    "sg:city":"Wevelgem",
    "sg:classifiers":[
        {
            "category":"Professional",
            "subcategory":"Engineering",
            "type":"Services"
        }
    ],
    "sg:phone":"+32 56 40 38 48",
    "sg:postcode":"8560",
    "sg:province":"West-Vlaanderen",
    "sg:tags":[
        "technical",
        "industrial",
        "-",
        "subcontracting"
    ],
    "wof:name":"Standard Industrie",
    "wof:placetype":"venue"
},
  "geometry": {"coordinates":[3.2138168812,50.8163566589],"type":"Point"}
}