{
  "type": "Feature",
  "properties": {
    "iso:country":"BE",
    "sg:address":"Gaverstraat 35",
    "sg:city":"Geraardsbergen",
    "sg:classifiers":[
        {
            "category":"Professional",
            "subcategory":"Business Services",
            "type":"Services"
        }
    ],
    "sg:phone":"+32 54 42 14 95",
    "sg:postcode":"9500",
    "sg:province":"Oost-Vlaanderen",
    "sg:tags":[
        "industrial",
        "laundry"
    ],
    "wof:name":"Wasserij-werkkledij Moderna B.v.b.a.",
    "wof:placetype":"venue"
},
  "geometry": {"coordinates":[3.8796401024,50.7635993958],"type":"Point"}
}