{
  "type": "Feature",
  "properties": {
    "iso:country":"BE",
    "sg:address":"Heusdenbaan 55",
    "sg:city":"Melle",
    "sg:classifiers":[
        {
            "category":"Cafe",
            "type":"Food & Drink"
        }
    ],
    "sg:phone":"+32 9 230 65 40",
    "sg:postcode":"9090",
    "sg:province":"Oost-Vlaanderen",
    "sg:tags":[
        "caf\u00e9s"
    ],
    "wof:name":"Rudy Haegens",
    "wof:placetype":"venue"
},
  "geometry": {"coordinates":[3.7730131149,51.0250205994],"type":"Point"}
}