{
  "type": "Feature",
  "properties": {
    "iso:country":"BE",
    "sg:address":"Resedastraat 7",
    "sg:city":"Liedekerke",
    "sg:orig_category":"Installation de menuiserie en bois and plastique. Installation de menuiserie m\u00e9tallique",
    "sg:phone":"+32 53 66 35 47",
    "sg:postcode":"1770",
    "sg:province":"Vlaams-Brabant",
    "wof:name":"Willy Ghysels",
    "wof:placetype":"venue"
},
  "geometry": {"coordinates":[4.0997300148,50.8772201538],"type":"Point"}
}