{
  "type": "Feature",
  "properties": {
    "addr:full":"Stationstraat 58 Ternat Vlaams-Brabant 1740",
    "addr:housenumber":"58",
    "addr:postcode":"1740",
    "addr:street":"Stationstraat",
    "iso:country":"BE",
    "sg:address":"Stationstraat 58",
    "sg:city":"Ternat",
    "sg:classifiers":[
        {
            "category":"Shopping",
            "subcategory":"Florist",
            "type":"Retail Goods"
        }
    ],
    "sg:phone":"+32 2 582 15 63",
    "sg:postcode":"1740",
    "sg:province":"Vlaams-Brabant",
    "wof:name":"Bloemenkorf ( In De )",
    "wof:placetype":"venue"
},
  "geometry": {"coordinates":[4.1723098755,50.8718833923],"type":"Point"}
}