{
  "type": "Feature",
  "properties": {
    "iso:country":"BE",
    "sg:address":"Cours De Cramignon 2a",
    "sg:city":"Ottignies-louvain-la-neuve",
    "sg:orig_category":"Informaticaconsulenten",
    "sg:phone":"+32 10 45 40 39",
    "sg:postcode":"1348",
    "sg:province":"Brabant Wallon",
    "wof:name":"Coherence",
    "wof:placetype":"venue"
},
  "geometry": {"coordinates":[4.6118950844,50.6737213135],"type":"Point"}
}