{
  "type": "Feature",
  "properties": {
    "addr:full":"Brabantsebaan 356 Sint-pieters-leeuw Vlaams-Brabant 1600",
    "addr:housenumber":"356",
    "addr:postcode":"1600",
    "addr:street":"Brabantsebaan",
    "iso:country":"BE",
    "sg:address":"Brabantsebaan 356",
    "sg:city":"Sint-pieters-leeuw",
    "sg:classifiers":[
        {
            "category":"Parking",
            "subcategory":"Lot",
            "type":"Transportation"
        }
    ],
    "sg:phone":"+32 2 532 57 12",
    "sg:postcode":"1600",
    "sg:province":"Vlaams-Brabant",
    "sg:tags":[
        "parking-places",
        "laying-out"
    ],
    "wof:name":"Desmet Ph & Zn",
    "wof:placetype":"venue"
},
  "geometry": {"coordinates":[4.2107582092,50.7823982239],"type":"Point"}
}