{
  "type": "Feature",
  "properties": {
    "iso:country":"BE",
    "sg:address":"Elsense Steenweg 185",
    "sg:city":"Ixelles",
    "sg:orig_category":"Belastingconsulenten Diverse juridische dienstverlening",
    "sg:phone":"+32 2 514 34 63",
    "sg:postcode":"1050",
    "sg:province":"Bruxelles-Capitale",
    "wof:name":"Gail Martiri",
    "wof:placetype":"venue"
},
  "geometry": {"coordinates":[4.3668479919,50.8322181702],"type":"Point"}
}