{
  "type": "Feature",
  "properties": {
    "iso:country":"BE",
    "sg:address":"Nijvelsebaan 63",
    "sg:city":"Huldenberg",
    "sg:classifiers":[
        {
            "category":"Social Services",
            "subcategory":"Child Care",
            "type":"Services"
        }
    ],
    "sg:phone":"+32 16 47 34 94",
    "sg:postcode":"3040",
    "sg:province":"Vlaams-Brabant",
    "sg:tags":[
        "baby",
        "nursery",
        "day",
        "sitting"
    ],
    "wof:name":"Tante Yvette (bij)",
    "wof:placetype":"venue"
},
  "geometry": {"coordinates":[4.5998702049,50.7837104797],"type":"Point"}
}