{
  "type": "Feature",
  "properties": {
    "iso:country":"BE",
    "sg:address":"Hoogland 4",
    "sg:city":"Wervik",
    "sg:orig_category":"Epiceries",
    "sg:phone":"+32 56 31 01 95",
    "sg:postcode":"8940",
    "sg:province":"West-Vlaanderen",
    "wof:name":"Christiane Callewaert",
    "wof:placetype":"venue"
},
  "geometry": {"coordinates":[3.01907897,50.8166236877],"type":"Point"}
}