{
  "type": "Feature",
  "properties": {
    "iso:country":"BE",
    "sg:address":"Ouwegemsesteenweg 123",
    "sg:city":"Zingem (ouwegem)",
    "sg:classifiers":[
        {
            "category":"Bars & Pubs",
            "type":"Food & Drink"
        }
    ],
    "sg:phone":"+32 9 384 28 58",
    "sg:postcode":"9750",
    "sg:province":"Oost-Vlaanderen",
    "wof:name":"Welkom (de)",
    "wof:placetype":"venue"
},
  "geometry": {"coordinates":[3.6115300655,50.9101982117],"type":"Point"}
}