{
  "type": "Feature",
  "properties": {
    "iso:country":"BE",
    "sg:address":"Place De Sainte-adresse 12",
    "sg:city":"Bruxelles (anderlecht)",
    "sg:classifiers":[
        {
            "category":"Professional",
            "subcategory":"Employment Agencies",
            "type":"Services"
        }
    ],
    "sg:phone":"+32 2 527 51 31",
    "sg:postcode":"1070",
    "sg:province":"Bruxelles-Capitale",
    "sg:tags":[
        "-",
        "processing",
        "data"
    ],
    "wof:name":"Infodidac",
    "wof:placetype":"venue"
},
  "geometry": {"coordinates":[4.3052830696,50.8382339478],"type":"Point"}
}