{
  "type": "Feature",
  "properties": {
    "addr:full":"Wielmakerstraat 3 Tielt West-Vlaanderen 8700",
    "addr:housenumber":"3",
    "addr:postcode":"8700",
    "addr:street":"Wielmakerstraat",
    "iso:country":"BE",
    "sg:address":"Wielmakerstraat 3",
    "sg:city":"Tielt",
    "sg:orig_category":"Eleveurs de bovins",
    "sg:phone":"+32 51 40 17 63",
    "sg:postcode":"8700",
    "sg:province":"West-Vlaanderen",
    "wof:name":"Vandeweghe",
    "wof:placetype":"venue"
},
  "geometry": {"coordinates":[3.3539779186,50.9934196472],"type":"Point"}
}