{
  "type": "Feature",
  "properties": {
    "addr:full":"Kapellestraat 28 Lierde Oost-Vlaanderen 9570",
    "addr:housenumber":"28",
    "addr:postcode":"9570",
    "addr:street":"Kapellestraat",
    "iso:country":"BE",
    "sg:address":"Kapellestraat 28",
    "sg:city":"Lierde",
    "sg:orig_category":"Aanleg van opritten and terreinen bij woningen Plaatsen van vloer- and muurbekleding",
    "sg:phone":"+32 55 42 59 25",
    "sg:postcode":"9570",
    "sg:province":"Oost-Vlaanderen",
    "wof:name":"De Turck",
    "wof:placetype":"venue"
},
  "geometry": {"coordinates":[3.85648489,50.8239631653],"type":"Point"}
}