{
  "type": "Feature",
  "properties": {
    "iso:country":"BE",
    "sg:address":"Mechelbaan 545",
    "sg:city":"Putte",
    "sg:classifiers":[
        {
            "category":"Personal",
            "subcategory":"Beauty Salon",
            "type":"Services"
        }
    ],
    "sg:phone":"+32 15 75 53 43",
    "sg:postcode":"2580",
    "sg:province":"Antwerpen",
    "sg:tags":[
        "lady",
        "-",
        "hairdressing"
    ],
    "wof:name":"Mady",
    "wof:placetype":"venue"
},
  "geometry": {"coordinates":[4.6265568733,51.0535430908],"type":"Point"}
}