{
  "type": "Feature",
  "properties": {
    "addr:full":"Zirkstraat 17 Antwerpen Antwerpen 2000",
    "addr:housenumber":"17",
    "addr:postcode":"2000",
    "addr:street":"Zirkstraat",
    "iso:country":"BE",
    "sg:address":"Zirkstraat 17",
    "sg:city":"Antwerpen",
    "sg:classifiers":[
        {
            "category":"Restaurant",
            "type":"Food & Drink"
        }
    ],
    "sg:phone":"+32 3 226 92 20",
    "sg:postcode":"2000",
    "sg:province":"Antwerpen",
    "wof:name":"De Zoute Zoen",
    "wof:placetype":"venue"
},
  "geometry": {"coordinates":[4.4007239342,51.2231826782],"type":"Point"}
}