{
  "type": "Feature",
  "properties": {
    "addr:full":"Place Aux Foires 18 Durbuy Luxembourg 6940",
    "addr:housenumber":"18",
    "addr:postcode":"6940",
    "addr:street":"Place Aux Foires",
    "iso:country":"BE",
    "sg:address":"Place Aux Foires 18",
    "sg:city":"Durbuy",
    "sg:classifiers":[
        {
            "category":"Fast Food",
            "type":"Food & Drink"
        }
    ],
    "sg:phone":"+32 86 21 25 92",
    "sg:postcode":"6940",
    "sg:province":"Luxembourg",
    "sg:tags":[
        "\u00c0",
        "restaurants",
        "emporter",
        "restaurant"
    ],
    "wof:name":"Le Saint Amour",
    "wof:placetype":"venue"
},
  "geometry": {"coordinates":[5.4569339752,50.3516120911],"type":"Point"}
}