{
  "type": "Feature",
  "properties": {
    "iso:country":"BE",
    "sg:address":"Opstal 34",
    "sg:city":"Kasterlee",
    "sg:orig_category":"Producteurs de fruits. Producteurs de l\u00e9gumes",
    "sg:phone":"+32 14 55 67 14",
    "sg:postcode":"2460",
    "sg:province":"Antwerpen",
    "wof:name":"Albert Eykens",
    "wof:placetype":"venue"
},
  "geometry": {"coordinates":[4.9048428535,51.2444381714],"type":"Point"}
}