{
  "type": "Feature",
  "properties": {
    "iso:country":"BE",
    "sg:address":"Rue Artan 118",
    "sg:city":"Schaarbeek/schaerbeek",
    "sg:orig_category":"Installation de menuiserie en bois and plastique",
    "sg:phone":"+32 2 732 86 53",
    "sg:postcode":"1030",
    "sg:province":"Bruxelles-Capitale",
    "wof:name":"Fe. Leclercqz",
    "wof:placetype":"venue"
},
  "geometry": {"coordinates":[4.3836350441,50.8533172607],"type":"Point"}
}