{
  "type": "Feature",
  "properties": {
    "addr:full":"Eikstraat 56 Pepingen Vlaams-Brabant 1673",
    "addr:housenumber":"56",
    "addr:postcode":"1673",
    "addr:street":"Eikstraat",
    "iso:country":"BE",
    "sg:address":"Eikstraat 56",
    "sg:city":"Pepingen",
    "sg:orig_category":"Rundveehouders",
    "sg:phone":"+32 2 356 11 42",
    "sg:postcode":"1673",
    "sg:province":"Vlaams-Brabant",
    "wof:name":"Andre Deeren",
    "wof:placetype":"venue"
},
  "geometry": {"coordinates":[4.1825051308,50.7473678589],"type":"Point"}
}