{
  "type": "Feature",
  "properties": {
    "iso:country":"BE",
    "sg:address":"Rue Des Ecaussinnes 100",
    "sg:city":"Le Roeulx",
    "sg:orig_category":"Eleveurs de bovins",
    "sg:phone":"+32 64 66 28 89",
    "sg:postcode":"7070",
    "sg:province":"Hainaut",
    "wof:name":"Herbaut",
    "wof:placetype":"venue"
},
  "geometry": {"coordinates":[4.1123590469,50.5258674622],"type":"Point"}
}