{
  "type": "Feature",
  "properties": {
    "addr:full":"Boulevard Sylvain Dupuis 73 Bruxelles (anderlecht) Bruxelles-Capitale 1070",
    "addr:housenumber":"73",
    "addr:postcode":"1070",
    "addr:street":"Boulevard Sylvain Dupuis",
    "iso:country":"BE",
    "sg:address":"Boulevard Sylvain Dupuis 73",
    "sg:city":"Bruxelles (anderlecht)",
    "sg:orig_category":"Non-Classified Establishments",
    "sg:phone":"+32 2 521 42 03",
    "sg:postcode":"1070",
    "sg:province":"Bruxelles-Capitale",
    "wof:name":"Gastronomie Service Sprl",
    "wof:placetype":"venue"
},
  "geometry": {"coordinates":[4.3023161888,50.8375167847],"type":"Point"}
}