{
  "type": "Feature",
  "properties": {
    "iso:country":"BE",
    "sg:address":"Rue Van Lint 25",
    "sg:city":"Bruxelles (anderlecht)",
    "sg:orig_category":"Non-Classified Establishments",
    "sg:phone":"+32 2 522 34 55",
    "sg:postcode":"1070",
    "sg:province":"Bruxelles-Capitale",
    "wof:name":"Garitex",
    "wof:placetype":"venue"
},
  "geometry": {"coordinates":[4.3280181885,50.8396072388],"type":"Point"}
}