{
  "type": "Feature",
  "properties": {
    "iso:country":"BE",
    "sg:address":"Weibroekdreef 41",
    "sg:city":"Aalter",
    "sg:orig_category":"Plaatsen van vloer- and muurbekleding Schilders",
    "sg:phone":"+32 9 374 28 09",
    "sg:postcode":"9880",
    "sg:province":"Oost-Vlaanderen",
    "wof:name":"Joris De Muynck",
    "wof:placetype":"venue"
},
  "geometry": {"coordinates":[3.4553060532,51.0895500183],"type":"Point"}
}