{
  "type": "Feature",
  "properties": {
    "iso:country":"BE",
    "sg:address":"Schaapsdries 24",
    "sg:city":"Genk",
    "sg:orig_category":"M\u00e9decins and sp\u00e9cialistes",
    "sg:phone":"+32 89 30 84 60",
    "sg:postcode":"3600",
    "sg:province":"Limburg",
    "wof:name":"Christel Ivens",
    "wof:placetype":"venue"
},
  "geometry": {"coordinates":[5.5195198059,50.9691314697],"type":"Point"}
}