{
  "type": "Feature",
  "properties": {
    "iso:country":"BE",
    "sg:address":"Rue De La Station 125",
    "sg:city":"Jemeppe-sur-sambre",
    "sg:orig_category":"Banken and kredietinstellingen",
    "sg:phone":"+32 71 78 70 90",
    "sg:postcode":"5190",
    "sg:province":"Namur",
    "wof:name":"Dexia",
    "wof:placetype":"venue"
},
  "geometry": {"coordinates":[4.6950750351,50.4561233521],"type":"Point"}
}