{
  "type": "Feature",
  "properties": {
    "addr:full":"Turnhoutsebaan 459 Schilde Antwerpen 2970",
    "addr:housenumber":"459",
    "addr:postcode":"2970",
    "addr:street":"Turnhoutsebaan",
    "iso:country":"BE",
    "sg:address":"Turnhoutsebaan 459",
    "sg:city":"Schilde",
    "sg:classifiers":[
        {
            "category":"Professional",
            "subcategory":"Testing Lab",
            "type":"Services"
        }
    ],
    "sg:phone":"+32 3 385 91 46",
    "sg:postcode":"2970",
    "sg:province":"Antwerpen",
    "sg:tags":[
        "chemist"
    ],
    "wof:name":"De Lathauwer M",
    "wof:placetype":"venue"
},
  "geometry": {"coordinates":[4.613866806,51.2530288696],"type":"Point"}
}