{
  "type": "Feature",
  "properties": {
    "iso:country":"BE",
    "sg:address":"Rue Fran\u00c7ois Gilon 2",
    "sg:city":"Crisnee",
    "sg:orig_category":"Epiceries",
    "sg:phone":"+32 19 67 73 30",
    "sg:postcode":"4367",
    "sg:province":"Li\u00e8ge",
    "wof:name":"Maison Dewallef",
    "wof:placetype":"venue"
},
  "geometry": {"coordinates":[5.3981471062,50.7176437378],"type":"Point"}
}