{
  "type": "Feature",
  "properties": {
    "addr:full":"Kasteelstraat 5b101 De Panne West-Vlaanderen 8660",
    "addr:housenumber":"5b101",
    "addr:postcode":"8660",
    "addr:street":"Kasteelstraat",
    "iso:country":"BE",
    "sg:address":"Kasteelstraat 5b101",
    "sg:city":"De Panne",
    "sg:classifiers":[
        {
            "category":"Food & Beverages",
            "subcategory":"Fruits & Vegetables",
            "type":"Retail Goods"
        }
    ],
    "sg:phone":"+32 58 41 16 19",
    "sg:postcode":"8660",
    "sg:province":"West-Vlaanderen",
    "sg:tags":[
        "l\u00e9gumes"
    ],
    "wof:name":"Luc Debeir",
    "wof:placetype":"venue"
},
  "geometry": {"coordinates":[2.5921308994,51.0982208252],"type":"Point"}
}