{
  "type": "Feature",
  "properties": {
    "addr:full":"Chauss\u00c9e De Mons 333 La Louviere Hainaut 7100",
    "addr:housenumber":"333",
    "addr:postcode":"7100",
    "addr:street":"Chausse\u0301E De Mons",
    "iso:country":"BE",
    "sg:address":"Chauss\u00c9e De Mons 333",
    "sg:city":"La Louviere",
    "sg:orig_category":"HERSTELLING ELEKTRISCHE HUISHOUDAPPARATEN Huishoudapparaten, televisies and radio's",
    "sg:phone":"+32 64 26 09 32",
    "sg:postcode":"7100",
    "sg:province":"Hainaut",
    "wof:name":"T.v. Lab Service",
    "wof:placetype":"venue"
},
  "geometry": {"coordinates":[4.1995410919,50.4645805359],"type":"Point"}
}