{
  "type": "Feature",
  "properties": {
    "addr:full":"Rue Du Bois De Buis 89 Walhain (walhain-saint-paul) Brabant Wallon 1457",
    "addr:housenumber":"89",
    "addr:postcode":"1457",
    "addr:street":"Rue Du Bois De Buis;Wallon",
    "iso:country":"BE",
    "sg:address":"Rue Du Bois De Buis 89",
    "sg:city":"Walhain (walhain-saint-paul)",
    "sg:classifiers":[
        {
            "category":"Health Services",
            "subcategory":"Health Practitioner",
            "type":"Services"
        }
    ],
    "sg:phone":"+32 10 65 09 60",
    "sg:postcode":"1457",
    "sg:province":"Brabant Wallon",
    "sg:tags":[
        "physiotherapist"
    ],
    "wof:name":"Evrard Philippe",
    "wof:placetype":"venue"
},
  "geometry": {"coordinates":[4.7194800377,50.6136627197],"type":"Point"}
}