{
  "type": "Feature",
  "properties": {
    "addr:full":"Waregemstraat 110 Zulte Oost-Vlaanderen 9870",
    "addr:housenumber":"110",
    "addr:postcode":"9870",
    "addr:street":"Waregemstraat",
    "iso:country":"BE",
    "sg:address":"Waregemstraat 110",
    "sg:city":"Zulte",
    "sg:orig_category":"Eleveurs de bovins. Eleveurs and marchands de porcs",
    "sg:phone":"+32 56 61 48 06",
    "sg:postcode":"9870",
    "sg:province":"Oost-Vlaanderen",
    "wof:name":"Robert De Blancq",
    "wof:placetype":"venue"
},
  "geometry": {"coordinates":[3.450510025,50.9086303711],"type":"Point"}
}