{
  "type": "Feature",
  "properties": {
    "addr:full":"Grand Monchaut 17 Ellezelles Hainaut 7890",
    "addr:housenumber":"17",
    "addr:postcode":"7890",
    "iso:country":"BE",
    "sg:address":"Grand Monchaut 17",
    "sg:city":"Ellezelles",
    "sg:classifiers":[
        {
            "category":"Structure",
            "subcategory":"Office Building",
            "type":"Public Place"
        }
    ],
    "sg:phone":"+32 68 54 29 77",
    "sg:postcode":"7890",
    "sg:province":"Hainaut",
    "sg:tags":[
        "drawing"
    ],
    "wof:name":"Huysman P",
    "wof:placetype":"venue"
},
  "geometry": {"coordinates":[3.6795580387,50.7065849304],"type":"Point"}
}