{
  "type": "Feature",
  "properties": {
    "addr:full":"Meibloemstraat 18 Gent Oost-Vlaanderen 9000",
    "addr:housenumber":"18",
    "addr:postcode":"9000",
    "addr:street":"Meibloemstraat;Oost-Vlaanderen",
    "iso:country":"BE",
    "sg:address":"Meibloemstraat 18",
    "sg:city":"Gent",
    "sg:classifiers":[
        {
            "category":"Sports & Exercise",
            "subcategory":"Sports Center",
            "type":"Entertainment"
        }
    ],
    "sg:phone":"+32 9 227 27 72",
    "sg:postcode":"9000",
    "sg:province":"Oost-Vlaanderen",
    "sg:tags":[
        "terrain",
        "hors",
        "de",
        "installation",
        "sportifs"
    ],
    "wof:name":"Bowling De Meibloem",
    "wof:placetype":"venue"
},
  "geometry": {"coordinates":[3.6985340118,51.0585479736],"type":"Point"}
}