{
  "type": "Feature",
  "properties": {
    "iso:country":"BE",
    "sg:address":"Wijnheuvelenstraat 227",
    "sg:city":"Schaarbeek/schaerbeek",
    "sg:orig_category":"Advocaten and juridische adviseurs",
    "sg:phone":"+32 2 242 69 32",
    "sg:postcode":"1030",
    "sg:province":"Bruxelles-Capitale",
    "wof:name":"Laure Demez",
    "wof:placetype":"venue"
},
  "geometry": {"coordinates":[4.3776669502,50.8601570129],"type":"Point"}
}