{
  "type": "Feature",
  "properties": {
    "addr:full":"Industrielaan 3 Lichtervelde West-Vlaanderen 8810",
    "addr:housenumber":"3",
    "addr:postcode":"8810",
    "addr:street":"Industrielaan",
    "iso:country":"BE",
    "sg:address":"Industrielaan 3",
    "sg:city":"Lichtervelde",
    "sg:orig_category":"Chemicali\u00ebn Gh",
    "sg:phone":"+32 51 72 65 76",
    "sg:postcode":"8810",
    "sg:province":"West-Vlaanderen",
    "wof:name":"Chem-lab",
    "wof:placetype":"venue"
},
  "geometry": {"coordinates":[3.1138560772,51.0301589966],"type":"Point"}
}