{
  "type": "Feature",
  "properties": {
    "iso:country":"BE",
    "sg:address":"Affligemdreef 89",
    "sg:city":"Aalst",
    "sg:orig_category":"Bars Divers amusement Ruimtes voor conferenties, recepties and feesten",
    "sg:phone":"+32 53 77 17 78",
    "sg:postcode":"9300",
    "sg:province":"Oost-Vlaanderen",
    "wof:name":"Troffaes",
    "wof:placetype":"venue"
},
  "geometry": {"coordinates":[4.0664758682,50.9349365234],"type":"Point"}
}