{
  "type": "Feature",
  "properties": {
    "addr:full":"Karreweg 22 Zulte Oost-Vlaanderen 9870",
    "addr:housenumber":"22",
    "addr:postcode":"9870",
    "addr:street":"Karreweg",
    "iso:country":"BE",
    "sg:address":"Karreweg 22",
    "sg:city":"Zulte",
    "sg:classifiers":[
        {
            "category":"Food & Beverages",
            "subcategory":"Groceries & Convenience Stores",
            "type":"Retail Goods"
        }
    ],
    "sg:phone":"+32 9 388 91 81",
    "sg:postcode":"9870",
    "sg:province":"Oost-Vlaanderen",
    "sg:tags":[
        "product",
        "related"
    ],
    "wof:name":"Flandria Foods Nv",
    "wof:placetype":"venue"
},
  "geometry": {"coordinates":[3.4671199322,50.9050216675],"type":"Point"}
}