{
  "type": "Feature",
  "properties": {
    "iso:country":"BE",
    "sg:address":"Terluchtestraat 42",
    "sg:city":"Ruddervoorde",
    "sg:classifiers":[
        {
            "category":"Insurance",
            "subcategory":"Life Insurance",
            "type":"Services"
        }
    ],
    "sg:phone":"+32 50 28 06 86",
    "sg:postcode":"8020",
    "sg:province":"West-Vlaanderen",
    "sg:tags":[
        "clock",
        "grandfather"
    ],
    "wof:name":"M.c.s. Furniture B.v.b.a.",
    "wof:placetype":"venue"
},
  "geometry": {"coordinates":[3.2350599766,51.1533241272],"type":"Point"}
}