{
  "type": "Feature",
  "properties": {
    "iso:country":"BE",
    "sg:address":"Westeindestraat 45",
    "sg:city":"Maldegem",
    "sg:orig_category":"Slagers",
    "sg:phone":"+32 50 71 15 51",
    "sg:postcode":"9990",
    "sg:province":"Oost-Vlaanderen",
    "wof:name":"Jean Van Landschoot",
    "wof:placetype":"venue"
},
  "geometry": {"coordinates":[3.441380024,51.2089233398],"type":"Point"}
}