{
  "type": "Feature",
  "properties": {
    "iso:country":"BE",
    "sg:address":"Waregemsestraat 46",
    "sg:city":"Desselgem",
    "sg:orig_category":"Rev\u00eatements de sols and murs",
    "sg:phone":"+32 56 72 09 36",
    "sg:postcode":"8792",
    "sg:province":"West-Vlaanderen",
    "wof:name":"Parket Center",
    "wof:placetype":"venue"
},
  "geometry": {"coordinates":[3.3657178879,50.8811912537],"type":"Point"}
}