{
  "type": "Feature",
  "properties": {
    "iso:country":"BE",
    "sg:address":"Lijsterbesstraat 8",
    "sg:city":"Eeklo",
    "sg:classifiers":[
        {
            "category":"Professional",
            "subcategory":"Computer Services",
            "type":"Services"
        }
    ],
    "sg:phone":"+32 9 378 35 19",
    "sg:postcode":"9900",
    "sg:province":"Oost-Vlaanderen",
    "sg:tags":[
        "-",
        "processing",
        "data",
        "software"
    ],
    "wof:name":"Cooman Consulting Bvba",
    "wof:placetype":"venue"
},
  "geometry": {"coordinates":[3.557518959,51.1915855408],"type":"Point"}
}