{
  "type": "Feature",
  "properties": {
    "addr:full":"Rue D'izel 20 Florenville Luxembourg 6820",
    "addr:housenumber":"20",
    "addr:postcode":"6820",
    "addr:street":"Rue D'Izel",
    "iso:country":"BE",
    "sg:address":"Rue D'izel 20",
    "sg:city":"Florenville",
    "sg:classifiers":[
        {
            "category":"Building & Trades",
            "subcategory":"Electrical",
            "type":"Services"
        }
    ],
    "sg:phone":"+32 61 31 37 14",
    "sg:postcode":"6820",
    "sg:province":"Luxembourg",
    "sg:tags":[
        "electric",
        "-",
        "housewiring",
        "contractor"
    ],
    "wof:name":"Batiflor",
    "wof:placetype":"venue"
},
  "geometry": {"coordinates":[5.3256039619,49.6986999512],"type":"Point"}
}