{
  "type": "Feature",
  "properties": {
    "addr:full":"Driehoeksstraat 6 Kalmthout Antwerpen 2920",
    "addr:housenumber":"6",
    "addr:postcode":"2920",
    "addr:street":"Driehoeksstraat",
    "iso:country":"BE",
    "sg:address":"Driehoeksstraat 6",
    "sg:city":"Kalmthout",
    "sg:orig_category":"Gespecialiseerde residenti\u00eble bouw Installatie van houten of kunststof schrijnwerk",
    "sg:phone":"+32 3 666 85 38",
    "sg:postcode":"2920",
    "sg:province":"Antwerpen",
    "wof:name":"Van Oevelen",
    "wof:placetype":"venue"
},
  "geometry": {"coordinates":[4.4754948616,51.381313324],"type":"Point"}
}