{
  "type": "Feature",
  "properties": {
    "addr:full":"Avenue Des Traquets 35-37 Bruxelles (auderghem) Bruxelles-Capitale 1160",
    "addr:housenumber":"35-37",
    "addr:postcode":"1160",
    "addr:street":"Avenue Des Traquets",
    "iso:country":"BE",
    "sg:address":"Avenue Des Traquets 35-37",
    "sg:city":"Bruxelles (auderghem)",
    "sg:classifiers":[
        {
            "category":"Health Services",
            "subcategory":"Nursing And Care Facility",
            "type":"Services"
        }
    ],
    "sg:phone":"+32 2 673 17 76",
    "sg:postcode":"1160",
    "sg:province":"Bruxelles-Capitale",
    "sg:tags":[
        "home",
        "rest"
    ],
    "wof:name":"Seigneurie Chant D'oiseau",
    "wof:placetype":"venue"
},
  "geometry": {"coordinates":[4.4156451225,50.8206253052],"type":"Point"}
}