{
  "type": "Feature",
  "properties": {
    "iso:country":"BE",
    "sg:address":"Chazallaan 11",
    "sg:city":"Schaarbeek/schaerbeek",
    "sg:orig_category":"Artsen and specialisten",
    "sg:phone":"+32 2 736 31 06",
    "sg:postcode":"1030",
    "sg:province":"Bruxelles-Capitale",
    "wof:name":"Jean-marie Kaninda Mulengi",
    "wof:placetype":"venue"
},
  "geometry": {"coordinates":[4.3882741928,50.8531570435],"type":"Point"}
}