{
  "type": "Feature",
  "properties": {
    "iso:country":"BE",
    "sg:address":"Kl Waregemsestraat 13",
    "sg:city":"Harelbeke",
    "sg:classifiers":[
        {
            "category":"Shopping",
            "subcategory":"Computers & Home Electronics",
            "type":"Retail Goods"
        }
    ],
    "sg:phone":"+32 56 70 24 86",
    "sg:postcode":"8530",
    "sg:province":"West-Vlaanderen",
    "sg:tags":[
        "equipment",
        "household",
        "electrical",
        "appliance",
        "electronic"
    ],
    "wof:name":"Perfecta Belgi\u00cb Bvba",
    "wof:placetype":"venue"
},
  "geometry": {"coordinates":[3.3336200714,50.8593788147],"type":"Point"}
}