{
  "type": "Feature",
  "properties": {
    "addr:full":"Rue Paul Henri Spaak 10 Peruwelz Hainaut 7608",
    "addr:housenumber":"10",
    "addr:postcode":"7608",
    "addr:street":"Rue Paul Henri Spaak;Hainaut",
    "iso:country":"BE",
    "sg:address":"Rue Paul Henri Spaak 10",
    "sg:city":"Peruwelz",
    "sg:orig_category":"Loodgieterij, verwarming and sanitaire installaties",
    "sg:phone":"+32 69 77 25 71",
    "sg:postcode":"7608",
    "sg:province":"Hainaut",
    "wof:name":"Gaston Delvaux",
    "wof:placetype":"venue"
},
  "geometry": {"coordinates":[3.5358870029,50.5051994324],"type":"Point"}
}