{
  "type": "Feature",
  "properties": {
    "addr:full":"Boulevard Emile Bockstael 17 Bruxelles Bruxelles-Capitale 1020",
    "addr:housenumber":"17",
    "addr:postcode":"1020",
    "addr:street":"Boulevard Emile Bockstael",
    "iso:country":"BE",
    "sg:address":"Boulevard Emile Bockstael 17",
    "sg:city":"Bruxelles",
    "sg:classifiers":[
        {
            "category":"Health Services",
            "subcategory":"Dentist",
            "type":"Services"
        }
    ],
    "sg:phone":"+32 2 426 06 89",
    "sg:postcode":"1020",
    "sg:province":"Bruxelles-Capitale",
    "wof:name":"Thirion Rolande",
    "wof:placetype":"venue"
},
  "geometry": {"coordinates":[4.343817234,50.8705215454],"type":"Point"}
}