{
  "type": "Feature",
  "properties": {
    "addr:full":"Chauss\u00e9e De Wavre 200 Wanze Li\u00e8ge 4520",
    "addr:housenumber":"200",
    "addr:postcode":"4520",
    "addr:street":"Chausse\u0301E De Wavre",
    "iso:country":"BE",
    "sg:address":"Chauss\u00e9e De Wavre 200",
    "sg:city":"Wanze",
    "sg:classifiers":[
        {
            "category":"Building & Trades",
            "subcategory":"Electrical",
            "type":"Services"
        }
    ],
    "sg:phone":"+32 475 62 68 93",
    "sg:postcode":"4520",
    "sg:province":"Li\u00e8ge",
    "sg:tags":[
        "electric",
        "-",
        "housewiring",
        "contractor"
    ],
    "wof:name":"Vigin X",
    "wof:placetype":"venue"
},
  "geometry": {"coordinates":[5.1979198456,50.5379486084],"type":"Point"}
}