{
  "type": "Feature",
  "properties": {
    "iso:country":"BE",
    "sg:address":"Brusselsesteenweg 539",
    "sg:city":"Asse (zellik)",
    "sg:classifiers":[
        {
            "category":"Bars & Pubs",
            "type":"Food & Drink"
        }
    ],
    "sg:phone":"+32 2 466 41 09",
    "sg:postcode":"1731",
    "sg:province":"Vlaams-Brabant",
    "wof:name":"Zwaan (in De)",
    "wof:placetype":"venue"
},
  "geometry": {"coordinates":[4.2757210732,50.8834266663],"type":"Point"}
}