{
  "type": "Feature",
  "properties": {
    "addr:full":"Rue De La Grippelotte 16 Chaumont-gistoux Brabant Wallon 1325",
    "addr:housenumber":"16",
    "addr:postcode":"1325",
    "addr:street":"Rue De La Grippelotte",
    "iso:country":"BE",
    "sg:address":"Rue De La Grippelotte 16",
    "sg:city":"Chaumont-gistoux",
    "sg:orig_category":"Production de films, t\u00e9l\u00e9films and vid\u00e9os. Studios photographiques",
    "sg:phone":"+32 10 68 97 93",
    "sg:postcode":"1325",
    "sg:province":"Brabant Wallon",
    "wof:name":"Danielle Levita",
    "wof:placetype":"venue"
},
  "geometry": {"coordinates":[4.6649308205,50.6913986206],"type":"Point"}
}