{
  "type": "Feature",
  "properties": {
    "addr:full":"Hoogboome Steenweg 6 Kapellen Antwerpen 2950",
    "addr:housenumber":"6",
    "addr:postcode":"2950",
    "addr:street":"Steenweg",
    "iso:country":"BE",
    "sg:address":"Hoogboome Steenweg 6",
    "sg:city":"Kapellen",
    "sg:orig_category":"Alternatieve geneeskunde Artsen and specialisten",
    "sg:phone":"+32 3 664 11 22",
    "sg:postcode":"2950",
    "sg:province":"Antwerpen",
    "wof:name":"Dokter Boermeester Walter",
    "wof:placetype":"venue"
},
  "geometry": {"coordinates":[4.4377279282,51.3037834167],"type":"Point"}
}