{
  "type": "Feature",
  "properties": {
    "addr:full":"Rue Haute 266 Fourons (fouron-le-comte) Limburg 3798",
    "addr:housenumber":"266",
    "addr:postcode":"3798",
    "addr:street":"Rue Haute",
    "iso:country":"BE",
    "sg:address":"Rue Haute 266",
    "sg:city":"Fourons (fouron-le-comte)",
    "sg:classifiers":[
        {
            "category":"Freight",
            "type":"Transportation"
        }
    ],
    "sg:phone":"+32 4 381 13 83",
    "sg:postcode":"3798",
    "sg:province":"Limburg",
    "sg:tags":[
        "-",
        "transport"
    ],
    "wof:name":"Pinckers Eric Bvba",
    "wof:placetype":"venue"
},
  "geometry": {"coordinates":[5.7674999237,50.7582321167],"type":"Point"}
}