{
  "type": "Feature",
  "properties": {
    "addr:full":"27 Jules De Troozlaan 1150 St-pieters-woluwe 27",
    "addr:housenumber":"27;1150;27",
    "addr:street":"Jules De Troozlaan;St-Pieters-Woluwe",
    "iso:country":"BE",
    "sg:address":"27",
    "sg:city":"Jules De Troozlaan 1150 St-pieters-woluwe",
    "sg:classifiers":[
        {
            "category":"Wholesale",
            "subcategory":"Medical Equipment & Supplies",
            "type":"Manufacturing & Wholesale Goods"
        }
    ],
    "sg:phone":"+32 2 770 34 09",
    "sg:postcode":"27",
    "sg:tags":[
        "instrument",
        "health",
        "-",
        "precision"
    ],
    "wof:name":"Orthopedie Lucas Nv",
    "wof:placetype":"venue"
},
  "geometry": {"coordinates":[4.4295201302,50.8370780945],"type":"Point"}
}