{
  "type": "Feature",
  "properties": {
    "iso:country":"BE",
    "sg:address":"Coupure Rechts 864",
    "sg:city":"Gent",
    "sg:orig_category":"Advocaten and juridische adviseurs Balie van Gent",
    "sg:phone":"+32 9 233 28 10",
    "sg:postcode":"9000",
    "sg:province":"Oost-Vlaanderen",
    "wof:name":"Bello",
    "wof:placetype":"venue"
},
  "geometry": {"coordinates":[3.7093551159,51.0558013916],"type":"Point"}
}