{
  "type": "Feature",
  "properties": {
    "iso:country":"BE",
    "sg:address":"Rue Des Glaieuls 16",
    "sg:city":"Aubange",
    "sg:classifiers":[
        {
            "category":"Arena",
            "subcategory":"Sports Club",
            "type":"Entertainment"
        }
    ],
    "sg:phone":"+32 63 38 61 43",
    "sg:postcode":"6791",
    "sg:province":"Luxembourg",
    "sg:tags":[
        "de"
    ],
    "wof:name":"Les M\u00c9tallos De La Chiers",
    "wof:placetype":"venue"
},
  "geometry": {"coordinates":[5.8422031403,49.5694313049],"type":"Point"}
}