{
  "type": "Feature",
  "properties": {
    "iso:country":"BE",
    "sg:address":"Rue Adolphe Renson 23",
    "sg:city":"Saint-nicolas",
    "sg:orig_category":"Services fun\u00e9raires",
    "sg:phone":"+32 4 226 57 53",
    "sg:postcode":"4420",
    "sg:province":"Li\u00e8ge",
    "wof:name":"Lambert Mestre",
    "wof:placetype":"venue"
},
  "geometry": {"coordinates":[5.5332260132,50.6400680542],"type":"Point"}
}