{
  "type": "Feature",
  "properties": {
    "iso:country":"BE",
    "sg:address":"Bodegemstraat 257",
    "sg:city":"Dilbeek",
    "sg:orig_category":"Transports terrestres de voyageurs",
    "sg:phone":"+32 2 567 17 00",
    "sg:postcode":"1700",
    "sg:province":"Vlaams-Brabant",
    "wof:name":"Fun Cars",
    "wof:placetype":"venue"
},
  "geometry": {"coordinates":[4.2320098877,50.8499984741],"type":"Point"}
}