{
  "type": "Feature",
  "properties": {
    "addr:full":"13 Ring 2200 Herentals 13",
    "addr:housenumber":"13;13",
    "addr:postcode":"2200",
    "addr:street":"Ring",
    "iso:country":"BE",
    "sg:address":"13",
    "sg:city":"Ring 2200 Herentals",
    "sg:classifiers":[
        {
            "category":"Bakery",
            "type":"Food & Drink"
        }
    ],
    "sg:phone":"+32 14 26 25 46",
    "sg:postcode":"13",
    "sg:tags":[
        "cake",
        "product",
        "related",
        "bread"
    ],
    "wof:name":"Brood-en Banket Bak De Ceulaer Bvba",
    "wof:placetype":"venue"
},
  "geometry": {"coordinates":[4.8472828865,51.1718826294],"type":"Point"}
}