{
  "type": "Feature",
  "properties": {
    "addr:full":"Rue De Falisolle 46ba Sambreville Namur 5060",
    "addr:housenumber":"46ba",
    "addr:postcode":"5060",
    "addr:street":"Rue De Falisolle",
    "iso:country":"BE",
    "sg:address":"Rue De Falisolle 46ba",
    "sg:city":"Sambreville",
    "sg:orig_category":"Kinderopvang",
    "sg:phone":"+32 71 77 36 80",
    "sg:postcode":"5060",
    "sg:province":"Namur",
    "wof:name":"Intercom. Acc. Jeun. Enf.",
    "wof:placetype":"venue"
},
  "geometry": {"coordinates":[4.6285200119,50.4448738098],"type":"Point"}
}