{
  "type": "Feature",
  "properties": {
    "addr:full":"Grand-place 1 Neufchateau Luxembourg 6840",
    "addr:housenumber":"1",
    "addr:postcode":"6840",
    "addr:street":"Grand-Place",
    "iso:country":"BE",
    "sg:address":"Grand-place 1",
    "sg:city":"Neufchateau",
    "sg:orig_category":"Enseignement maternel and primaire",
    "sg:phone":"+32 61 27 90 42",
    "sg:postcode":"6840",
    "sg:province":"Luxembourg",
    "wof:name":"Ecole Fondamentale",
    "wof:placetype":"venue"
},
  "geometry": {"coordinates":[5.4355101585,49.8402252197],"type":"Point"}
}