{
  "type": "Feature",
  "properties": {
    "addr:full":"Weg Naar Opoeteren 105 Opglabbeek Limburg 3660",
    "addr:housenumber":"105",
    "addr:postcode":"3660",
    "addr:street":"Weg Naar Opoeteren",
    "iso:country":"BE",
    "sg:address":"Weg Naar Opoeteren 105",
    "sg:city":"Opglabbeek",
    "sg:orig_category":"Bijouteries and horlogeries. R\u00e9parations d'horloges, montres and bijoux",
    "sg:phone":"+32 89 85 60 91",
    "sg:postcode":"3660",
    "sg:province":"Limburg",
    "wof:name":"Golden Jewels",
    "wof:placetype":"venue"
},
  "geometry": {"coordinates":[5.5979781151,51.049030304],"type":"Point"}
}