{
  "type": "Feature",
  "properties": {
    "addr:full":"Gentsesteenweg 316 Zele Oost-Vlaanderen 9240",
    "addr:housenumber":"316",
    "addr:postcode":"9240",
    "addr:street":"Gentsesteenweg",
    "iso:country":"BE",
    "sg:address":"Gentsesteenweg 316",
    "sg:city":"Zele",
    "sg:classifiers":[
        {
            "category":"Structure",
            "subcategory":"Building",
            "type":"Public Place"
        }
    ],
    "sg:phone":"+32 9 367 07 71",
    "sg:postcode":"9240",
    "sg:province":"Oost-Vlaanderen",
    "sg:tags":[
        "door"
    ],
    "wof:name":"Aldepa Bvba",
    "wof:placetype":"venue"
},
  "geometry": {"coordinates":[3.994343996,51.0553398132],"type":"Point"}
}