{
  "type": "Feature",
  "properties": {
    "addr:full":"Stuivekenskerkestraat 13 Antwerpen (borgerhout) Antwerpen 2140",
    "addr:housenumber":"13",
    "addr:postcode":"2140",
    "addr:street":"Stuivekenskerkestraat",
    "iso:country":"BE",
    "sg:address":"Stuivekenskerkestraat 13",
    "sg:city":"Antwerpen (borgerhout)",
    "sg:classifiers":[
        {
            "category":"Retail",
            "subcategory":"Event Space",
            "type":"Services"
        }
    ],
    "sg:phone":"+32 3 322 14 46",
    "sg:postcode":"2140",
    "sg:province":"Antwerpen",
    "sg:tags":[
        "organisation"
    ],
    "wof:name":"Van B.",
    "wof:placetype":"venue"
},
  "geometry": {"coordinates":[4.4332199097,51.2137565613],"type":"Point"}
}