{
  "type": "Feature",
  "properties": {
    "addr:full":"Boulevard Lambermont 422 Bruxelles (schaerbeek) Bruxelles-Capitale 1030",
    "addr:housenumber":"422",
    "addr:postcode":"1030",
    "addr:street":"Boulevard Lambermont",
    "iso:country":"BE",
    "sg:address":"Boulevard Lambermont 422",
    "sg:city":"Bruxelles (schaerbeek)",
    "sg:classifiers":[
        {
            "category":"Professional",
            "subcategory":"Computer Services",
            "type":"Services"
        }
    ],
    "sg:phone":"+32 2 245 84 65",
    "sg:postcode":"1030",
    "sg:province":"Bruxelles-Capitale",
    "sg:tags":[
        "network"
    ],
    "wof:name":"Soft Power Sprl",
    "wof:placetype":"venue"
},
  "geometry": {"coordinates":[4.3882780075,50.8622817993],"type":"Point"}
}