{
  "type": "Feature",
  "properties": {
    "addr:full":"Dronkaertstraat 677 Menen (lauwe) West-Vlaanderen 8930",
    "addr:housenumber":"677",
    "addr:postcode":"8930",
    "addr:street":"Dronkaertstraat",
    "iso:country":"BE",
    "sg:address":"Dronkaertstraat 677",
    "sg:city":"Menen (lauwe)",
    "sg:classifiers":[
        {
            "category":"Farming",
            "subcategory":"Livestock Farm",
            "type":"Manufacturing & Wholesale Goods"
        }
    ],
    "sg:phone":"+32 56 41 24 83",
    "sg:postcode":"8930",
    "sg:province":"West-Vlaanderen",
    "sg:tags":[
        "poultry",
        "rabbit"
    ],
    "wof:name":"Delto Poultry Nv",
    "wof:placetype":"venue"
},
  "geometry": {"coordinates":[3.1636819839,50.7693557739],"type":"Point"}
}