{
  "type": "Feature",
  "properties": {
    "addr:full":"Zuid Australi\u00eblaan 32 Lier Antwerpen 2500",
    "addr:housenumber":"32",
    "addr:postcode":"2500",
    "addr:street":"Australie\u0308Laan",
    "iso:country":"BE",
    "sg:address":"Zuid Australi\u00eblaan 32",
    "sg:city":"Lier",
    "sg:classifiers":[
        {
            "category":"Health Services",
            "subcategory":"Health Practitioner",
            "type":"Services"
        }
    ],
    "sg:phone":"+32 3 480 35 68",
    "sg:postcode":"2500",
    "sg:province":"Antwerpen",
    "sg:tags":[
        "therapist",
        "speech"
    ],
    "wof:name":"Spoelders D",
    "wof:placetype":"venue"
},
  "geometry": {"coordinates":[4.5561909676,51.1373023987],"type":"Point"}
}