{
  "type": "Feature",
  "properties": {
    "addr:full":"Ninoofsesteenweg 41 Haaltert Oost-Vlaanderen 9450",
    "addr:housenumber":"41",
    "addr:postcode":"9450",
    "addr:street":"Ninoofsesteenweg",
    "iso:country":"BE",
    "sg:address":"Ninoofsesteenweg 41",
    "sg:city":"Haaltert",
    "sg:orig_category":"Woningbouw",
    "sg:phone":"+32 54 33 09 25",
    "sg:postcode":"9450",
    "sg:province":"Oost-Vlaanderen",
    "wof:name":"Scheerlinck E",
    "wof:placetype":"venue"
},
  "geometry": {"coordinates":[4.0215539932,50.8596763611],"type":"Point"}
}