{
  "type": "Feature",
  "properties": {
    "addr:full":"Roeselaarsestraat 63 Kortrijk West-Vlaanderen 8501",
    "addr:housenumber":"63",
    "addr:postcode":"8501",
    "addr:street":"Roeselaarsestraat",
    "iso:country":"BE",
    "sg:address":"Roeselaarsestraat 63",
    "sg:city":"Kortrijk",
    "sg:orig_category":"Papierwaren and schoolbenodigdheden Gh",
    "sg:phone":"+32 56 35 00 38",
    "sg:postcode":"8501",
    "sg:province":"West-Vlaanderen",
    "wof:name":"Adhesive Industires",
    "wof:placetype":"venue"
},
  "geometry": {"coordinates":[3.2215240002,50.8477973938],"type":"Point"}
}