{
  "type": "Feature",
  "properties": {
    "addr:full":"Willekenslaan 101 Begijnendijk (betekom) Vlaams-Brabant 3130",
    "addr:housenumber":"101",
    "addr:postcode":"3130",
    "addr:street":"Willekenslaan",
    "iso:country":"BE",
    "sg:address":"Willekenslaan 101",
    "sg:city":"Begijnendijk (betekom)",
    "sg:classifiers":[
        {
            "category":"Bars & Pubs",
            "type":"Food & Drink"
        }
    ],
    "sg:phone":"+32 16 53 03 31",
    "sg:postcode":"3130",
    "sg:province":"Vlaams-Brabant",
    "wof:name":"Kwetterhof (het)",
    "wof:placetype":"venue"
},
  "geometry": {"coordinates":[4.7792930603,51.0009269714],"type":"Point"}
}