{
  "type": "Feature",
  "properties": {
    "iso:country":"BE",
    "sg:address":"Oudstrijdersstraat 149",
    "sg:city":"Ranst (oelegem)",
    "sg:classifiers":[
        {
            "category":"Personal",
            "subcategory":"Beauty Salon",
            "type":"Services"
        }
    ],
    "sg:phone":"+32 3 385 11 28",
    "sg:postcode":"2520",
    "sg:province":"Antwerpen",
    "sg:tags":[
        "equipment",
        "hairdressing",
        "-",
        "supply"
    ],
    "wof:name":"Lugore",
    "wof:placetype":"venue"
},
  "geometry": {"coordinates":[4.5827231407,51.2131156921],"type":"Point"}
}