{
  "type": "Feature",
  "properties": {
    "iso:country":"BE",
    "sg:address":"Bormansstraat 41",
    "sg:city":"Landen",
    "sg:orig_category":"Slagers",
    "sg:phone":"+32 11 83 21 86",
    "sg:postcode":"3401",
    "sg:province":"Vlaams-Brabant",
    "wof:name":"Marc Dormaal",
    "wof:placetype":"venue"
},
  "geometry": {"coordinates":[5.0876088142,50.7202377319],"type":"Point"}
}