{
  "type": "Feature",
  "properties": {
    "iso:country":"BE",
    "sg:address":"Retiebaan 5",
    "sg:city":"Kasterlee",
    "sg:orig_category":"V\u00eatements",
    "sg:phone":"+32 14 85 03 41",
    "sg:postcode":"2460",
    "sg:province":"Antwerpen",
    "wof:name":"Charlatan",
    "wof:placetype":"venue"
},
  "geometry": {"coordinates":[5.0140829086,51.2486839294],"type":"Point"}
}