{
  "type": "Feature",
  "properties": {
    "addr:full":"Molenberg 46 Meerhout Antwerpen 2450",
    "addr:housenumber":"46",
    "addr:postcode":"2450",
    "addr:street":"Molenberg",
    "iso:country":"BE",
    "sg:address":"Molenberg 46",
    "sg:city":"Meerhout",
    "sg:orig_category":"Gespecialiseerde residenti\u00eble bouw",
    "sg:phone":"+32 14 30 85 30",
    "sg:postcode":"2450",
    "sg:province":"Antwerpen",
    "wof:name":"Karel Vangeel",
    "wof:placetype":"venue"
},
  "geometry": {"coordinates":[5.0734620094,51.1329498291],"type":"Point"}
}