{
  "type": "Feature",
  "properties": {
    "addr:full":"Abdijstraat 3 Affligem Vlaams-Brabant 1790",
    "addr:housenumber":"3",
    "addr:postcode":"1790",
    "addr:street":"Abdijstraat",
    "iso:country":"BE",
    "sg:address":"Abdijstraat 3",
    "sg:city":"Affligem",
    "sg:orig_category":"Avocats and conseillers juridiques",
    "sg:phone":"+32 53 68 27 52",
    "sg:postcode":"1790",
    "sg:province":"Vlaams-Brabant",
    "wof:name":"Inge Van Hove",
    "wof:placetype":"venue"
},
  "geometry": {"coordinates":[4.1126561165,50.9233398438],"type":"Point"}
}