{
  "type": "Feature",
  "properties": {
    "addr:full":"Nachtegaalstraat 64 Stekene Oost-Vlaanderen 9190",
    "addr:housenumber":"64",
    "addr:postcode":"9190",
    "addr:street":"Nachtegaalstraat",
    "iso:country":"BE",
    "sg:address":"Nachtegaalstraat 64",
    "sg:city":"Stekene",
    "sg:classifiers":[
        {
            "category":"Fast Food",
            "type":"Food & Drink"
        }
    ],
    "sg:phone":"+32 3 779 52 08",
    "sg:postcode":"9190",
    "sg:province":"Oost-Vlaanderen",
    "sg:tags":[
        "fried",
        "stand",
        "potato"
    ],
    "wof:name":"Frituur Express",
    "wof:placetype":"venue"
},
  "geometry": {"coordinates":[4.0329332352,51.2206916809],"type":"Point"}
}