{
  "type": "Feature",
  "properties": {
    "addr:full":"Dr. J. Casselaan 4 Middelkerke West-Vlaanderen 8430",
    "addr:housenumber":"4",
    "addr:postcode":"8430",
    "addr:street":"Dr.;Casselaan",
    "iso:country":"BE",
    "sg:address":"Dr. J. Casselaan 4",
    "sg:city":"Middelkerke",
    "sg:orig_category":"Offices du tourisme",
    "sg:phone":"+32 59 30 03 68",
    "sg:postcode":"8430",
    "sg:province":"West-Vlaanderen",
    "wof:name":"Middelkerke Toerisme",
    "wof:placetype":"venue"
},
  "geometry": {"coordinates":[2.8183009624,51.1888046265],"type":"Point"}
}