{
  "type": "Feature",
  "properties": {
    "iso:country":"BE",
    "sg:address":"Breendonkstraat 94",
    "sg:city":"Londerzeel",
    "sg:classifiers":[
        {
            "category":"Cafe",
            "type":"Food & Drink"
        }
    ],
    "sg:phone":"+32 52 30 11 97",
    "sg:postcode":"1840",
    "sg:province":"Vlaams-Brabant",
    "sg:tags":[
        "caf\u00e9s"
    ],
    "wof:name":"Grens Caf\u00c9",
    "wof:placetype":"venue"
},
  "geometry": {"coordinates":[4.3036818504,51.0275917053],"type":"Point"}
}