{
  "type": "Feature",
  "properties": {
    "iso:country":"BE",
    "sg:address":"Avenue Du Saphir 2",
    "sg:city":"Braine-l\u00b4alleud",
    "sg:orig_category":"D\u00e9corateurs d'int\u00e9rieur",
    "sg:phone":"+32 2 354 64 74",
    "sg:postcode":"1420",
    "sg:province":"Brabant Wallon",
    "wof:name":"Ancre De Chine",
    "wof:placetype":"venue"
},
  "geometry": {"coordinates":[4.3347678185,50.7332038879],"type":"Point"}
}