{
  "type": "Feature",
  "properties": {
    "iso:country":"BE",
    "sg:address":"Rue De La Pacification 44",
    "sg:city":"Bruxelles",
    "sg:classifiers":[
        {
            "category":"Building & Trades",
            "subcategory":"Construction",
            "type":"Services"
        }
    ],
    "sg:phone":"+32 2 230 33 66",
    "sg:postcode":"1000",
    "sg:province":"Bruxelles-Capitale",
    "sg:tags":[
        "insulation",
        "thermical",
        "work",
        "acoustical"
    ],
    "wof:name":"Aka Sprl",
    "wof:placetype":"venue"
},
  "geometry": {"coordinates":[4.3762512207,50.8483543396],"type":"Point"}
}