{
  "type": "Feature",
  "properties": {
    "addr:full":"Hundelgemsesteenweg 35 Gavere (baaigem) Oost-Vlaanderen 9890",
    "addr:housenumber":"35",
    "addr:postcode":"9890",
    "addr:street":"Hundelgemsesteenweg",
    "iso:country":"BE",
    "sg:address":"Hundelgemsesteenweg 35",
    "sg:city":"Gavere (baaigem)",
    "sg:classifiers":[
        {
            "category":"Building & Trades",
            "subcategory":"Plumbing",
            "type":"Services"
        }
    ],
    "sg:phone":"+32 9 362 45 91",
    "sg:postcode":"9890",
    "sg:province":"Oost-Vlaanderen",
    "sg:tags":[
        "tank"
    ],
    "wof:name":"V D E Metaalkonstrukties Bvba",
    "wof:placetype":"venue"
},
  "geometry": {"coordinates":[3.6588599682,50.9283752441],"type":"Point"}
}