{
  "type": "Feature",
  "properties": {
    "iso:country":"BE",
    "sg:address":"Diestersteenweg 100",
    "sg:city":"Maaseik",
    "sg:classifiers":[
        {
            "category":"Autos & Motor Vehicles",
            "subcategory":"Automobile Sales",
            "type":"Retail Goods"
        }
    ],
    "sg:phone":"+32 89 86 48 78",
    "sg:postcode":"3680",
    "sg:province":"Limburg",
    "sg:tags":[
        "car",
        "used",
        "-"
    ],
    "wof:name":"Heussen Garage",
    "wof:placetype":"venue"
},
  "geometry": {"coordinates":[5.7717900276,51.0992393494],"type":"Point"}
}