{
  "type": "Feature",
  "properties": {
    "iso:country":"BE",
    "sg:address":"Esdoorndreef 12",
    "sg:city":"Puurs (liezele)",
    "sg:classifiers":[
        {
            "category":"Building & Trades",
            "subcategory":"Equipment Rental",
            "type":"Services"
        }
    ],
    "sg:phone":"+32 3 889 96 81",
    "sg:postcode":"2870",
    "sg:province":"Antwerpen",
    "sg:tags":[
        "sound",
        "-",
        "system"
    ],
    "wof:name":"D & L Events",
    "wof:placetype":"venue"
},
  "geometry": {"coordinates":[4.2718439102,51.059627533],"type":"Point"}
}