{
  "type": "Feature",
  "properties": {
    "addr:full":"Waverse Steenweg 1297b8 Oudergem/auderghem Bruxelles-Capitale 1160",
    "addr:housenumber":"1297b8",
    "addr:postcode":"1160",
    "addr:street":"Waverse Steenweg;/",
    "iso:country":"BE",
    "sg:address":"Waverse Steenweg 1297b8",
    "sg:city":"Oudergem/auderghem",
    "sg:orig_category":"Boekhouders",
    "sg:phone":"+32 2 675 25 34",
    "sg:postcode":"1160",
    "sg:province":"Bruxelles-Capitale",
    "wof:name":"Philippe Carlton",
    "wof:placetype":"venue"
},
  "geometry": {"coordinates":[4.4082832336,50.8208351135],"type":"Point"}
}