{
  "type": "Feature",
  "properties": {
    "iso:country":"BE",
    "sg:address":"Stadspoortstraat 12",
    "sg:city":"Herentals",
    "sg:classifiers":[
        {
            "category":"Bars & Pubs",
            "type":"Food & Drink"
        }
    ],
    "sg:phone":"+32 14 22 49 55",
    "sg:postcode":"2200",
    "sg:province":"Antwerpen",
    "sg:tags":[
        "tavern"
    ],
    "wof:name":"Stadspoort",
    "wof:placetype":"venue"
},
  "geometry": {"coordinates":[4.8393130302,51.1733779907],"type":"Point"}
}