{
  "type": "Feature",
  "properties": {
    "addr:full":"Kleindokkaai 10 Gent Oost-Vlaanderen 9000",
    "addr:housenumber":"10",
    "addr:postcode":"9000",
    "addr:street":"Kleindokkaai;Oost-Vlaanderen",
    "iso:country":"BE",
    "sg:address":"Kleindokkaai 10",
    "sg:city":"Gent",
    "sg:orig_category":"Onderdelen and accessoires voor auto's Onderdelen and accessoires voor voertuigen and motoren Fab",
    "sg:phone":"+32 9 225 37 42",
    "sg:postcode":"9000",
    "sg:province":"Oost-Vlaanderen",
    "wof:name":"Kwik-fit",
    "wof:placetype":"venue"
},
  "geometry": {"coordinates":[3.7386829853,51.0590171814],"type":"Point"}
}