{
  "type": "Feature",
  "properties": {
    "addr:full":"Zandberg 8 Westerlo Antwerpen 2260",
    "addr:housenumber":"8",
    "addr:postcode":"2260",
    "addr:street":"Zandberg",
    "iso:country":"BE",
    "sg:address":"Zandberg 8",
    "sg:city":"Westerlo",
    "sg:orig_category":"RESTAURANTS: CAF\u00c9S",
    "sg:phone":"+32 14 54 74 00",
    "sg:postcode":"2260",
    "sg:province":"Antwerpen",
    "wof:name":"Taverne De Zandberg",
    "wof:placetype":"venue"
},
  "geometry": {"coordinates":[4.9318480492,51.0934257507],"type":"Point"}
}