{
  "type": "Feature",
  "properties": {
    "iso:country":"BE",
    "sg:address":"Botermelkstraat 104",
    "sg:city":"Erpe-mere",
    "sg:orig_category":"Woningbouw",
    "sg:phone":"+32 53 78 54 29",
    "sg:postcode":"9420",
    "sg:province":"Oost-Vlaanderen",
    "wof:name":"De Swaef-d S",
    "wof:placetype":"venue"
},
  "geometry": {"coordinates":[3.9837589264,50.9399452209],"type":"Point"}
}