{
  "type": "Feature",
  "properties": {
    "iso:country":"BE",
    "sg:address":"Rue E. Dinot 20",
    "sg:city":"Ciney",
    "sg:orig_category":"Bioscopen",
    "sg:phone":"+32 83 21 67 83",
    "sg:postcode":"5590",
    "sg:province":"Namur",
    "wof:name":"Ciney Chapline",
    "wof:placetype":"venue"
},
  "geometry": {"coordinates":[5.1002421379,50.2934303284],"type":"Point"}
}