{
  "type": "Feature",
  "properties": {
    "addr:full":"Sint - Anna 25 Kortrijk West-Vlaanderen 8500",
    "addr:housenumber":"25",
    "addr:postcode":"8500",
    "addr:street":"Sint Anna",
    "iso:country":"BE",
    "sg:address":"Sint - Anna 25",
    "sg:city":"Kortrijk",
    "sg:orig_category":"Gespecialiseerde residenti\u00eble bouw Tuinen",
    "sg:phone":"+32 56 22 20 87",
    "sg:postcode":"8500",
    "sg:province":"West-Vlaanderen",
    "wof:name":"De Groene Golf",
    "wof:placetype":"venue"
},
  "geometry": {"coordinates":[3.2495799065,50.7928962708],"type":"Point"}
}