{
  "type": "Feature",
  "properties": {
    "addr:full":"Rue Du Marquat 18 Hannut Li\u00e8ge 4280",
    "addr:housenumber":"18",
    "addr:postcode":"4280",
    "addr:street":"Rue Du Marquat",
    "iso:country":"BE",
    "sg:address":"Rue Du Marquat 18",
    "sg:city":"Hannut",
    "sg:orig_category":"Rundveehouders",
    "sg:phone":"+32 81 85 54 65",
    "sg:postcode":"4280",
    "sg:province":"Li\u00e8ge",
    "wof:name":"Roger Mahaux",
    "wof:placetype":"venue"
},
  "geometry": {"coordinates":[4.9973750114,50.6476745605],"type":"Point"}
}