{
  "type": "Feature",
  "properties": {
    "addr:full":"Kranenburgstraat 82 Scherpenheuvel-zichem Vlaams-Brabant 3271",
    "addr:housenumber":"82",
    "addr:postcode":"3271",
    "addr:street":"Kranenburgstraat",
    "iso:country":"BE",
    "sg:address":"Kranenburgstraat 82",
    "sg:city":"Scherpenheuvel-zichem",
    "sg:orig_category":"Brood, gebak and snoepgoed",
    "sg:phone":"+32 13 77 25 28",
    "sg:postcode":"3271",
    "sg:province":"Vlaams-Brabant",
    "wof:name":"Lucien Maes",
    "wof:placetype":"venue"
},
  "geometry": {"coordinates":[4.9887399673,50.9997673035],"type":"Point"}
}