{
  "type": "Feature",
  "properties": {
    "iso:country":"BE",
    "sg:address":"3 Priester Daensstraat",
    "sg:city":"Lommel",
    "sg:classifiers":[
        {
            "category":"Autos & Motor Vehicles",
            "subcategory":"Automobile Sales",
            "type":"Retail Goods"
        }
    ],
    "sg:phone":"+32 11 55 48 31",
    "sg:postcode":"3920",
    "sg:province":"Limburg",
    "sg:tags":[
        "equipment",
        "transport"
    ],
    "wof:name":"Glg Bvba",
    "wof:placetype":"venue"
},
  "geometry": {"coordinates":[5.270758152,51.2169723511],"type":"Point"}
}