{
  "type": "Feature",
  "properties": {
    "addr:full":"Rue Du Comptoir 85 Oupeye Li\u00e8ge 4680",
    "addr:housenumber":"85",
    "addr:postcode":"4680",
    "addr:street":"Rue Du Comptoir",
    "iso:country":"BE",
    "sg:address":"Rue Du Comptoir 85",
    "sg:city":"Oupeye",
    "sg:orig_category":"Tuinen",
    "sg:phone":"+32 4 278 00 68",
    "sg:postcode":"4680",
    "sg:province":"Li\u00e8ge",
    "wof:name":"Close",
    "wof:placetype":"venue"
},
  "geometry": {"coordinates":[5.6444120407,50.7089729309],"type":"Point"}
}