{
  "type": "Feature",
  "properties": {
    "iso:country":"BE",
    "sg:address":"Gillegomstraat 45",
    "sg:city":"Boechout",
    "sg:orig_category":"M\u00e9decins and sp\u00e9cialistes",
    "sg:phone":"+32 3 455 83 43",
    "sg:postcode":"2530",
    "sg:province":"Antwerpen",
    "wof:name":"Anne Teulingkx",
    "wof:placetype":"venue"
},
  "geometry": {"coordinates":[4.4997801781,51.166934967],"type":"Point"}
}