{
  "type": "Feature",
  "properties": {
    "iso:country":"BE",
    "sg:address":"Rue Emile Vandervelde 23a",
    "sg:city":"Charleroi",
    "sg:orig_category":"Kapsalons",
    "sg:phone":"+32 71 32 65 59",
    "sg:postcode":"6030",
    "sg:province":"Hainaut",
    "wof:name":"Coiffure Franco",
    "wof:placetype":"venue"
},
  "geometry": {"coordinates":[4.3947510719,50.40883255],"type":"Point"}
}