{
  "type": "Feature",
  "properties": {
    "iso:country":"BE",
    "sg:address":"Dendermondse Steenweg 244",
    "sg:city":"Aalst",
    "sg:orig_category":"Tabac. Journaux",
    "sg:phone":"+32 53 21 33 54",
    "sg:postcode":"9300",
    "sg:province":"Oost-Vlaanderen",
    "wof:name":"Cooman",
    "wof:placetype":"venue"
},
  "geometry": {"coordinates":[4.0305762291,50.9503059387],"type":"Point"}
}