{
  "type": "Feature",
  "properties": {
    "iso:country":"BE",
    "sg:address":"Dukkeldamstraat 38",
    "sg:city":"Gent",
    "sg:classifiers":[
        {
            "category":"Professional",
            "subcategory":"Advertising",
            "type":"Services"
        }
    ],
    "sg:phone":"+32 475 64 96 45",
    "sg:postcode":"9000",
    "sg:province":"Oost-Vlaanderen",
    "sg:tags":[
        "photography"
    ],
    "wof:name":"De Cock B",
    "wof:placetype":"venue"
},
  "geometry": {"coordinates":[3.7317180634,51.0776443481],"type":"Point"}
}