{
  "type": "Feature",
  "properties": {
    "iso:country":"BE",
    "sg:address":"Stenenmolenstraat 98",
    "sg:city":"Mechelen",
    "sg:classifiers":[
        {
            "category":"Communications",
            "subcategory":"Film & Video Production",
            "type":"Services"
        }
    ],
    "sg:phone":"+32 15 43 63 63",
    "sg:postcode":"2800",
    "sg:province":"Antwerpen",
    "sg:tags":[
        "sound",
        "recording",
        "studio"
    ],
    "wof:name":"De Saedeleer D Nv",
    "wof:placetype":"venue"
},
  "geometry": {"coordinates":[4.4794311523,51.0097808838],"type":"Point"}
}