{
  "type": "Feature",
  "properties": {
    "addr:full":"Kannegatstraat 63 Maasmechelen (boorsem) Limburg 3631",
    "addr:housenumber":"63",
    "addr:postcode":"3631",
    "addr:street":"Kannegatstraat",
    "iso:country":"BE",
    "sg:address":"Kannegatstraat 63",
    "sg:city":"Maasmechelen (boorsem)",
    "sg:orig_category":"Non-Classified Establishments",
    "sg:phone":"+32 89 77 25 72",
    "sg:postcode":"3631",
    "sg:province":"Limburg",
    "wof:name":"Van Wijngaerden",
    "wof:placetype":"venue"
},
  "geometry": {"coordinates":[5.7239232063,50.9423713684],"type":"Point"}
}