{
  "type": "Feature",
  "properties": {
    "addr:full":"Beukenlei 4 Brecht Antwerpen 2960",
    "addr:housenumber":"4",
    "addr:postcode":"2960",
    "addr:street":"Beukenlei",
    "iso:country":"BE",
    "sg:address":"Beukenlei 4",
    "sg:city":"Brecht",
    "sg:orig_category":"Opticiens",
    "sg:phone":"+32 3 636 41 78",
    "sg:postcode":"2960",
    "sg:province":"Antwerpen",
    "wof:name":"Optiek Mark Steegmans",
    "wof:placetype":"venue"
},
  "geometry": {"coordinates":[4.5674262047,51.3046188354],"type":"Point"}
}