{
  "type": "Feature",
  "properties": {
    "addr:full":"Rue Belliard 177 Bruxelles (etterbeek) Bruxelles-Capitale 1040",
    "addr:housenumber":"177",
    "addr:postcode":"1040",
    "addr:street":"Rue Belliard",
    "iso:country":"BE",
    "sg:address":"Rue Belliard 177",
    "sg:city":"Bruxelles (etterbeek)",
    "sg:classifiers":[
        {
            "category":"Education",
            "subcategory":"School",
            "type":"Public Place"
        }
    ],
    "sg:phone":"+32 2 230 69 12",
    "sg:postcode":"1040",
    "sg:province":"Bruxelles-Capitale",
    "sg:tags":[
        "supply"
    ],
    "wof:name":"Papeterie Du Parc L\u00e9opold Sprl",
    "wof:placetype":"venue"
},
  "geometry": {"coordinates":[4.3825697899,50.8397827148],"type":"Point"}
}