{
  "type": "Feature",
  "properties": {
    "iso:country":"BE",
    "sg:address":"Prinses Elisabethlaan 23",
    "sg:city":"Bredene",
    "sg:orig_category":"Artiesten and kunstenaars",
    "sg:phone":"+32 59 33 17 94",
    "sg:postcode":"8450",
    "sg:province":"West-Vlaanderen",
    "wof:name":"Jean-christian Blommaerts",
    "wof:placetype":"venue"
},
  "geometry": {"coordinates":[2.948143959,51.2230987549],"type":"Point"}
}