{
  "type": "Feature",
  "properties": {
    "iso:country":"BE",
    "sg:address":"Hogedries 8",
    "sg:city":"Peer",
    "sg:orig_category":"Industri\u00eble and commerci\u00eble bouw",
    "sg:phone":"+32 11 79 15 61",
    "sg:postcode":"3990",
    "sg:province":"Limburg",
    "wof:name":"Azet",
    "wof:placetype":"venue"
},
  "geometry": {"coordinates":[5.4378008842,51.0948066711],"type":"Point"}
}