{
  "type": "Feature",
  "properties": {
    "addr:full":"Hemelingenstraat 24 Tongeren Limburg 3700",
    "addr:housenumber":"24",
    "addr:postcode":"3700",
    "addr:street":"Hemelingenstraat",
    "iso:country":"BE",
    "sg:address":"Hemelingenstraat 24",
    "sg:city":"Tongeren",
    "sg:classifiers":[
        {
            "category":"Shopping",
            "subcategory":"Jewelry",
            "type":"Retail Goods"
        }
    ],
    "sg:phone":"+32 12 23 13 15",
    "sg:postcode":"3700",
    "sg:province":"Limburg",
    "sg:tags":[
        "jeweller",
        "-"
    ],
    "wof:name":"Rogister & Zn",
    "wof:placetype":"venue"
},
  "geometry": {"coordinates":[5.4625301361,50.781414032],"type":"Point"}
}