{
  "type": "Feature",
  "properties": {
    "iso:country":"BE",
    "sg:address":"Rue Sainte-anne 59",
    "sg:city":"Waterloo",
    "sg:orig_category":"H\u00f4tels",
    "sg:phone":"+32 2 353 18 18",
    "sg:postcode":"1410",
    "sg:province":"Brabant Wallon",
    "wof:name":"H\u00d4tel Le Joli-bois",
    "wof:placetype":"venue"
},
  "geometry": {"coordinates":[4.4089717865,50.6958961487],"type":"Point"}
}