{
  "type": "Feature",
  "properties": {
    "addr:full":"Korte Beenhouwersstraat 33 Brussel/bruxelles Bruxelles-Capitale 1000",
    "addr:housenumber":"33",
    "addr:postcode":"1000",
    "addr:street":"Korte Beenhouwersstraat;/",
    "iso:country":"BE",
    "sg:address":"Korte Beenhouwersstraat 33",
    "sg:city":"Brussel/bruxelles",
    "sg:classifiers":[
        {
            "category":"Restaurant",
            "type":"Food & Drink"
        }
    ],
    "sg:phone":"+32 2 513 15 62",
    "sg:postcode":"1000",
    "sg:province":"Bruxelles-Capitale",
    "wof:name":"Restaurant Le Calalou",
    "wof:placetype":"venue"
},
  "geometry": {"coordinates":[4.3545060158,50.8478088379],"type":"Point"}
}