{
  "type": "Feature",
  "properties": {
    "iso:country":"BE",
    "sg:address":"Sint-truiderstraat 41",
    "sg:city":"Tongeren",
    "sg:orig_category":"V\u00eatements. V\u00eatements pour Dames",
    "sg:phone":"+32 12 26 18 13",
    "sg:postcode":"3700",
    "sg:province":"Limburg",
    "wof:name":"Agnes Studio",
    "wof:placetype":"venue"
},
  "geometry": {"coordinates":[5.4608211517,50.7802391052],"type":"Point"}
}