{
  "type": "Feature",
  "properties": {
    "addr:full":"Rodepoortstraat 3 Ardooie West-Vlaanderen 8850",
    "addr:housenumber":"3",
    "addr:postcode":"8850",
    "addr:street":"Rodepoortstraat",
    "iso:country":"BE",
    "sg:address":"Rodepoortstraat 3",
    "sg:city":"Ardooie",
    "sg:orig_category":"Producteurs de l\u00e9gumes",
    "sg:phone":"+32 51 74 65 47",
    "sg:postcode":"8850",
    "sg:province":"West-Vlaanderen",
    "wof:name":"Rafael Devroe",
    "wof:placetype":"venue"
},
  "geometry": {"coordinates":[3.1832849979,50.9580802917],"type":"Point"}
}