{
  "type": "Feature",
  "properties": {
    "iso:country":"BE",
    "sg:address":"Nieuwstraat 15",
    "sg:city":"Tienen",
    "sg:classifiers":[
        {
            "category":"Shopping",
            "subcategory":"Shoes",
            "type":"Retail Goods"
        }
    ],
    "sg:phone":"+32 16 81 28 90",
    "sg:postcode":"3300",
    "sg:province":"Vlaams-Brabant",
    "sg:tags":[
        "slipper",
        "-"
    ],
    "wof:name":"Steels",
    "wof:placetype":"venue"
},
  "geometry": {"coordinates":[4.9387688637,50.8067207336],"type":"Point"}
}