{
  "type": "Feature",
  "properties": {
    "addr:full":"Prins Filiplaan 34 Knokke-heist (knokke) West-Vlaanderen 8300",
    "addr:housenumber":"34",
    "addr:postcode":"8300",
    "addr:street":"Prins Filiplaan",
    "iso:country":"BE",
    "sg:address":"Prins Filiplaan 34",
    "sg:city":"Knokke-heist (knokke)",
    "sg:classifiers":[
        {
            "category":"Real Estate",
            "subcategory":"Real Estate Services",
            "type":"Services"
        }
    ],
    "sg:phone":"+32 50 60 24 53",
    "sg:postcode":"8300",
    "sg:province":"West-Vlaanderen",
    "wof:name":"Rocke Intl Europe",
    "wof:placetype":"venue"
},
  "geometry": {"coordinates":[3.287694931,51.3467254639],"type":"Point"}
}