{
  "type": "Feature",
  "properties": {
    "addr:full":"Grand Place Mons Hainaut 7000",
    "addr:postcode":"7000",
    "addr:street":"Grand Place;Hainaut",
    "iso:country":"BE",
    "sg:address":"Grand Place",
    "sg:city":"Mons",
    "sg:classifiers":[
        {
            "category":"Arts & Performance",
            "subcategory":"Theater",
            "type":"Entertainment"
        }
    ],
    "sg:phone":"+32 65 39 59 39",
    "sg:postcode":"7000",
    "sg:province":"Hainaut",
    "sg:tags":[
        "concert-halls",
        "theatre"
    ],
    "wof:name":"Centre Culturel De La R\u00e9gion De Mons",
    "wof:placetype":"venue"
},
  "geometry": {"coordinates":[3.9522190094,50.4539833069],"type":"Point"}
}