{
  "type": "Feature",
  "properties": {
    "iso:country":"BE",
    "sg:address":"Herstalstraat 27",
    "sg:city":"Wellen",
    "sg:orig_category":"Eleveurs de bovins",
    "sg:phone":"+32 11 37 66 11",
    "sg:postcode":"3830",
    "sg:province":"Limburg",
    "wof:name":"Jans",
    "wof:placetype":"venue"
},
  "geometry": {"coordinates":[5.3534860611,50.8478622437],"type":"Point"}
}