{
  "type": "Feature",
  "properties": {
    "addr:full":"Tipstraat 74 Bilzen Limburg 3740",
    "addr:housenumber":"74",
    "addr:postcode":"3740",
    "addr:street":"Tipstraat",
    "iso:country":"BE",
    "sg:address":"Tipstraat 74",
    "sg:city":"Bilzen",
    "sg:orig_category":"Brood, gebak and snoepgoed",
    "sg:phone":"+32 89 41 35 86",
    "sg:postcode":"3740",
    "sg:province":"Limburg",
    "wof:name":"Anne-marie Bielen",
    "wof:placetype":"venue"
},
  "geometry": {"coordinates":[5.4593000412,50.8968200684],"type":"Point"}
}