{
  "type": "Feature",
  "properties": {
    "addr:full":"Dreefstraat 8 Leuven (heverlee) Vlaams-Brabant 3001",
    "addr:housenumber":"8",
    "addr:postcode":"3001",
    "addr:street":"Dreefstraat",
    "iso:country":"BE",
    "sg:address":"Dreefstraat 8",
    "sg:city":"Leuven (heverlee)",
    "sg:classifiers":[
        {
            "category":"Real Estate",
            "subcategory":"Real Estate Services",
            "type":"Services"
        }
    ],
    "sg:phone":"+32 16 23 78 64",
    "sg:postcode":"3001",
    "sg:province":"Vlaams-Brabant",
    "wof:name":"Aes",
    "wof:placetype":"venue"
},
  "geometry": {"coordinates":[4.6954770088,50.8663291931],"type":"Point"}
}