{
  "type": "Feature",
  "properties": {
    "addr:full":"Place Albert I 23 Froidchapelle Hainaut 6440",
    "addr:housenumber":"23",
    "addr:postcode":"6440",
    "addr:street":"Place Albert I",
    "iso:country":"BE",
    "sg:address":"Place Albert I 23",
    "sg:city":"Froidchapelle",
    "sg:classifiers":[
        {
            "category":"Shopping",
            "subcategory":"Bicycles & Sporting Goods",
            "type":"Retail Goods"
        }
    ],
    "sg:phone":"+32 60 41 10 62",
    "sg:postcode":"6440",
    "sg:province":"Hainaut",
    "sg:tags":[
        "sport",
        "-"
    ],
    "wof:name":"Ats Bobo",
    "wof:placetype":"venue"
},
  "geometry": {"coordinates":[4.3282771111,50.1507911682],"type":"Point"}
}