{
  "type": "Feature",
  "properties": {
    "addr:full":"Frankrijklei 54 Antwerpen Antwerpen 2000",
    "addr:housenumber":"54",
    "addr:postcode":"2000",
    "addr:street":"Frankrijklei",
    "iso:country":"BE",
    "sg:address":"Frankrijklei 54",
    "sg:city":"Antwerpen",
    "sg:classifiers":[
        {
            "category":"Shopping",
            "subcategory":"Clothing, Apparel, & Fashions",
            "type":"Retail Goods"
        }
    ],
    "sg:phone":"+32 3 231 56 01",
    "sg:postcode":"2000",
    "sg:province":"Antwerpen",
    "sg:tags":[
        "boutique"
    ],
    "wof:name":"Graffity",
    "wof:placetype":"venue"
},
  "geometry": {"coordinates":[4.4143061638,51.2172584534],"type":"Point"}
}