{
  "type": "Feature",
  "properties": {
    "addr:full":"Alfons Pieterslaan 84 Oostende West-Vlaanderen 8400",
    "addr:housenumber":"84",
    "addr:postcode":"8400",
    "addr:street":"Alfons Pieterslaan",
    "iso:country":"BE",
    "sg:address":"Alfons Pieterslaan 84",
    "sg:city":"Oostende",
    "sg:classifiers":[
        {
            "category":"Shopping",
            "subcategory":"Jewelry",
            "type":"Retail Goods"
        }
    ],
    "sg:phone":"+32 59 70 88 41",
    "sg:postcode":"8400",
    "sg:province":"West-Vlaanderen",
    "sg:tags":[
        "jeweller",
        "-"
    ],
    "wof:name":"M & D Juwels Bvba",
    "wof:placetype":"venue"
},
  "geometry": {"coordinates":[2.9114880562,51.2252044678],"type":"Point"}
}