{
  "type": "Feature",
  "properties": {
    "addr:full":"Sweversveld 49 Kinrooi Limburg 3640",
    "addr:housenumber":"49",
    "addr:postcode":"3640",
    "addr:street":"Sweversveld",
    "iso:country":"BE",
    "sg:address":"Sweversveld 49",
    "sg:city":"Kinrooi",
    "sg:orig_category":"Catering and organisation de f\u00eates",
    "sg:phone":"+32 89 56 84 80",
    "sg:postcode":"3640",
    "sg:province":"Limburg",
    "wof:name":"Marc Houben",
    "wof:placetype":"venue"
},
  "geometry": {"coordinates":[5.7422151566,51.1452484131],"type":"Point"}
}