{
  "type": "Feature",
  "properties": {
    "iso:country":"BE",
    "sg:address":"Plein 6",
    "sg:city":"Laakdal",
    "sg:orig_category":"Charpentes and couvertures",
    "sg:phone":"+32 14 86 66 53",
    "sg:postcode":"2430",
    "sg:province":"Antwerpen",
    "wof:name":"Fa. Den Hondt & Zoon",
    "wof:placetype":"venue"
},
  "geometry": {"coordinates":[4.9952521324,51.097076416],"type":"Point"}
}