{
  "type": "Feature",
  "properties": {
    "iso:country":"BE",
    "sg:address":"Rue De Goz\u00c9e 625",
    "sg:city":"Montigny-le-tilleul",
    "sg:orig_category":"Kantoormateriaal Krantenwinkels Rookartikelen",
    "sg:phone":"+32 71 51 61 87",
    "sg:postcode":"6110",
    "sg:province":"Hainaut",
    "wof:name":"Aux Lecteurs Du Bois",
    "wof:placetype":"venue"
},
  "geometry": {"coordinates":[4.3637719154,50.3663635254],"type":"Point"}
}