{
  "type": "Feature",
  "properties": {
    "iso:country":"BE",
    "sg:address":"Rue De Saint-donat",
    "sg:city":"Mettet",
    "sg:classifiers":[
        {
            "category":"Home & Garden",
            "subcategory":"Building Materials",
            "type":"Retail Goods"
        }
    ],
    "sg:phone":"+32 71 72 68 01",
    "sg:postcode":"5640",
    "sg:province":"Namur",
    "sg:tags":[
        "window"
    ],
    "wof:name":"Chassis Fd",
    "wof:placetype":"venue"
},
  "geometry": {"coordinates":[4.6500148773,50.3025360107],"type":"Point"}
}