{
  "type": "Feature",
  "properties": {
    "addr:full":"Rue De Grand Bigard 8 Bruxelles (berchem-sainte-agathe) Bruxelles-Capitale 1082",
    "addr:housenumber":"8",
    "addr:postcode":"1082",
    "addr:street":"Rue De Grand Bigard",
    "iso:country":"BE",
    "sg:address":"Rue De Grand Bigard 8",
    "sg:city":"Bruxelles (berchem-sainte-agathe)",
    "sg:classifiers":[
        {
            "category":"Building & Trades",
            "subcategory":"Electrical",
            "type":"Services"
        }
    ],
    "sg:phone":"+32 2 469 16 79",
    "sg:postcode":"1082",
    "sg:province":"Bruxelles-Capitale",
    "sg:tags":[
        "electric",
        "-",
        "housewiring",
        "contractor"
    ],
    "wof:name":"Caussin B",
    "wof:placetype":"venue"
},
  "geometry": {"coordinates":[4.2947697639,50.8605384827],"type":"Point"}
}