{
  "type": "Feature",
  "properties": {
    "addr:full":"Boulevard D'herbatte 219 Namur Namur 5000",
    "addr:housenumber":"219",
    "addr:postcode":"5000",
    "addr:street":"Boulevard D'Herbatte",
    "iso:country":"BE",
    "sg:address":"Boulevard D'herbatte 219",
    "sg:city":"Namur",
    "sg:classifiers":[
        {
            "category":"Autos & Motor Vehicles",
            "subcategory":"Automobile Sales",
            "type":"Retail Goods"
        }
    ],
    "sg:phone":"+32 81 23 01 99",
    "sg:postcode":"5000",
    "sg:province":"Namur",
    "sg:tags":[
        "car",
        "used",
        "-"
    ],
    "wof:name":"Firepower 6 Sprl",
    "wof:placetype":"venue"
},
  "geometry": {"coordinates":[4.8793621063,50.4685440063],"type":"Point"}
}