{
  "type": "Feature",
  "properties": {
    "iso:country":"BE",
    "sg:address":"Brouwersstraat 2",
    "sg:city":"Beringen",
    "sg:orig_category":"Advocaten and juridische adviseurs",
    "sg:phone":"+32 11 42 18 32",
    "sg:postcode":"3580",
    "sg:province":"Limburg",
    "wof:name":"Bert Vandenreyt",
    "wof:placetype":"venue"
},
  "geometry": {"coordinates":[5.2231721878,51.0478858948],"type":"Point"}
}