{
  "type": "Feature",
  "properties": {
    "iso:country":"BE",
    "sg:address":"Route De Ramecroix 18",
    "sg:city":"Antoing",
    "sg:classifiers":[
        {
            "category":"Manufacturing",
            "subcategory":"Rubber & Plastics",
            "type":"Manufacturing & Wholesale Goods"
        }
    ],
    "sg:phone":"+32 69 44 26 07",
    "sg:postcode":"7640",
    "sg:province":"Hainaut",
    "sg:tags":[
        "industrial",
        "-"
    ],
    "wof:name":"Varina",
    "wof:placetype":"venue"
},
  "geometry": {"coordinates":[3.4538590908,50.5722427368],"type":"Point"}
}