{
  "type": "Feature",
  "properties": {
    "iso:country":"BE",
    "sg:address":"Rue Lambert Daxhelet 9",
    "sg:city":"Burdinne",
    "sg:orig_category":"Elektrische installaties voor woningen",
    "sg:phone":"+32 85 71 35 31",
    "sg:postcode":"4210",
    "sg:province":"Li\u00e8ge",
    "wof:name":"J.m.s. Electricit\u00c9",
    "wof:placetype":"venue"
},
  "geometry": {"coordinates":[5.1447467804,50.5808677673],"type":"Point"}
}