{
  "type": "Feature",
  "properties": {
    "addr:full":"Torhoutsesteenweg Oostende West-Vlaanderen 8400",
    "addr:postcode":"8400",
    "addr:street":"Torhoutsesteenweg",
    "iso:country":"BE",
    "sg:address":"Torhoutsesteenweg",
    "sg:city":"Oostende",
    "sg:classifiers":[
        {
            "category":"Shopping",
            "subcategory":"Shoes",
            "type":"Retail Goods"
        }
    ],
    "sg:phone":"+32 59 80 86 01",
    "sg:postcode":"8400",
    "sg:province":"West-Vlaanderen",
    "sg:tags":[
        "slipper",
        "-"
    ],
    "wof:name":"Tip-toe",
    "wof:placetype":"venue"
},
  "geometry": {"coordinates":[2.9056351185,51.2112197876],"type":"Point"}
}