{
  "type": "Feature",
  "properties": {
    "addr:full":"Burg. Callewaertlaan 49 Lichtervelde West-Vlaanderen 8810",
    "addr:housenumber":"49",
    "addr:postcode":"8810",
    "addr:street":"Burg. Callewaertlaan",
    "iso:country":"BE",
    "sg:address":"Burg. Callewaertlaan 49",
    "sg:city":"Lichtervelde",
    "sg:orig_category":"Notaires",
    "sg:phone":"+32 51 72 20 64",
    "sg:postcode":"8810",
    "sg:province":"West-Vlaanderen",
    "wof:name":"Marc Wa\u00dbters",
    "wof:placetype":"venue"
},
  "geometry": {"coordinates":[3.1338660717,51.0266838074],"type":"Point"}
}