{
  "type": "Feature",
  "properties": {
    "addr:full":"Rue De Falisolle 330 Sambreville (auvelais) Namur 5060",
    "addr:housenumber":"330",
    "addr:postcode":"5060",
    "addr:street":"Rue De Falisolle",
    "iso:country":"BE",
    "sg:address":"Rue De Falisolle 330",
    "sg:city":"Sambreville (auvelais)",
    "sg:classifiers":[
        {
            "category":"Autos & Motor Vehicles",
            "subcategory":"Boat Sales",
            "type":"Retail Goods"
        }
    ],
    "sg:phone":"+32 71 77 85 65",
    "sg:postcode":"5060",
    "sg:province":"Namur",
    "sg:tags":[
        "balloon"
    ],
    "wof:name":"Decoration Ballons",
    "wof:placetype":"venue"
},
  "geometry": {"coordinates":[4.6285200119,50.4448738098],"type":"Point"}
}