{
  "type": "Feature",
  "properties": {
    "iso:country":"BE",
    "sg:address":"Chauss\u00c9e De Tongres 146",
    "sg:city":"Juprelle",
    "sg:orig_category":"Meubelzaken, woning- and keukeninrichting",
    "sg:phone":"+32 4 263 56 98",
    "sg:postcode":"4450",
    "sg:province":"Li\u00e8ge",
    "wof:name":"Meubles Juniorama",
    "wof:placetype":"venue"
},
  "geometry": {"coordinates":[5.5315198898,50.698299408],"type":"Point"}
}