{
  "type": "Feature",
  "properties": {
    "addr:full":"Hundelgemsesteenweg 19 Merelbeke Oost-Vlaanderen 9820",
    "addr:housenumber":"19",
    "addr:postcode":"9820",
    "addr:street":"Hundelgemsesteenweg",
    "iso:country":"BE",
    "sg:address":"Hundelgemsesteenweg 19",
    "sg:city":"Merelbeke",
    "sg:orig_category":"Dansscholen",
    "sg:phone":"+32 9 230 04 71",
    "sg:postcode":"9820",
    "sg:province":"Oost-Vlaanderen",
    "wof:name":"Dansclub Nike",
    "wof:placetype":"venue"
},
  "geometry": {"coordinates":[3.7534201145,51.0174484253],"type":"Point"}
}