{
  "type": "Feature",
  "properties": {
    "addr:full":"Rue Des Augustins 44 Huy Li\u00e8ge 4500",
    "addr:housenumber":"44",
    "addr:postcode":"4500",
    "addr:street":"Rue Des Augustins",
    "iso:country":"BE",
    "sg:address":"Rue Des Augustins 44",
    "sg:city":"Huy",
    "sg:orig_category":"Non-Classified Establishments",
    "sg:phone":"+32 85 21 29 14",
    "sg:postcode":"4500",
    "sg:province":"Li\u00e8ge",
    "wof:name":"Centre Pms Libre 1&2",
    "wof:placetype":"venue"
},
  "geometry": {"coordinates":[5.2433719635,50.5221061707],"type":"Point"}
}