{
  "type": "Feature",
  "properties": {
    "addr:full":"Poperingseweg 28bb-c Ieper West-Vlaanderen 8900",
    "addr:housenumber":"28bb-c",
    "addr:postcode":"8900",
    "addr:street":"Poperingseweg",
    "iso:country":"BE",
    "sg:address":"Poperingseweg 28bb-c",
    "sg:city":"Ieper",
    "sg:orig_category":"Instellingen voor mindervalide volwassenen",
    "sg:phone":"+32 57 20 60 59",
    "sg:postcode":"8900",
    "sg:province":"West-Vlaanderen",
    "wof:name":"Den Ommeloop",
    "wof:placetype":"venue"
},
  "geometry": {"coordinates":[2.8878269196,50.8513641357],"type":"Point"}
}