{
  "type": "Feature",
  "properties": {
    "addr:full":"Edingseweg 365 Moerbeke Oost-Vlaanderen 9500",
    "addr:housenumber":"365",
    "addr:postcode":"9500",
    "addr:street":"Edingseweg",
    "iso:country":"BE",
    "sg:address":"Edingseweg 365",
    "sg:city":"Moerbeke",
    "sg:orig_category":"Bloemen and planten Royal Canin Tuinbenodigdheden",
    "sg:phone":"+32 54 41 34 59",
    "sg:postcode":"9500",
    "sg:province":"Oost-Vlaanderen",
    "wof:name":"Flora Tuincentrum",
    "wof:placetype":"venue"
},
  "geometry": {"coordinates":[3.9207799435,50.7468605042],"type":"Point"}
}