{
  "type": "Feature",
  "properties": {
    "iso:country":"BE",
    "sg:address":"Diestsestraat 204",
    "sg:city":"Leuven",
    "sg:orig_category":"Entretien and r\u00e9parations de machines de bureau and ordinateurs",
    "sg:phone":"+32 16 20 55 63",
    "sg:postcode":"3000",
    "sg:province":"Vlaams-Brabant",
    "wof:name":"Neta Com",
    "wof:placetype":"venue"
},
  "geometry": {"coordinates":[4.7124137878,50.8817863464],"type":"Point"}
}