{
  "type": "Feature",
  "properties": {
    "addr:full":"Avenue De La R\u00e9sistance 2 Leuze-en-hainaut Hainaut 7900",
    "addr:housenumber":"2",
    "addr:postcode":"7900",
    "addr:street":"Avenue De La Re\u0301Sistance",
    "iso:country":"BE",
    "sg:address":"Avenue De La R\u00e9sistance 2",
    "sg:city":"Leuze-en-hainaut",
    "sg:classifiers":[
        {
            "category":"Banks & Credit Unions",
            "subcategory":"Investment Brokerage",
            "type":"Services"
        }
    ],
    "sg:phone":"+32 69 67 24 10",
    "sg:postcode":"7900",
    "sg:province":"Hainaut",
    "sg:tags":[
        "repair",
        "-",
        "installation",
        "sanitary",
        "article"
    ],
    "wof:name":"Di Silvestro Et Fils Sprl",
    "wof:placetype":"venue"
},
  "geometry": {"coordinates":[3.6208269596,50.6009902954],"type":"Point"}
}