{
  "type": "Feature",
  "properties": {
    "iso:country":"BE",
    "sg:address":"Lusweg 9",
    "sg:city":"Grimbergen",
    "sg:classifiers":[
        {
            "category":"Arena",
            "subcategory":"Sports Club",
            "type":"Entertainment"
        }
    ],
    "sg:phone":"+32 2 269 35 92",
    "sg:postcode":"1851",
    "sg:province":"Vlaams-Brabant",
    "sg:tags":[
        "de"
    ],
    "wof:name":"R.w.k. De Morgenstond",
    "wof:placetype":"venue"
},
  "geometry": {"coordinates":[4.3875150681,50.9734077454],"type":"Point"}
}