{
  "type": "Feature",
  "properties": {
    "iso:country":"BE",
    "sg:address":"Adegemdorp 1",
    "sg:city":"Maldegem",
    "sg:orig_category":"IJzerwaren, bouw- and verfmaterialen Verlichting and huishoudartikelen",
    "sg:phone":"+32 50 71 21 67",
    "sg:postcode":"9991",
    "sg:province":"Oost-Vlaanderen",
    "wof:name":"Simona Ginneberge",
    "wof:placetype":"venue"
},
  "geometry": {"coordinates":[3.4868040085,51.204284668],"type":"Point"}
}