{
  "type": "Feature",
  "properties": {
    "addr:full":"Beringen 2 Pepingen Vlaams-Brabant 1670",
    "addr:housenumber":"2",
    "addr:postcode":"1670",
    "addr:street":"Beringen",
    "iso:country":"BE",
    "sg:address":"Beringen 2",
    "sg:city":"Pepingen",
    "sg:orig_category":"Rundveehouders Varkenskwekers",
    "sg:phone":"+32 2 356 14 89",
    "sg:postcode":"1670",
    "sg:province":"Vlaams-Brabant",
    "wof:name":"Jean Borremans",
    "wof:placetype":"venue"
},
  "geometry": {"coordinates":[4.1583251953,50.7593231201],"type":"Point"}
}