{
  "type": "Feature",
  "properties": {
    "addr:full":"Michel Theysstraat 60 Diest Vlaams-Brabant 3290",
    "addr:housenumber":"60",
    "addr:postcode":"3290",
    "addr:street":"Theysstraat",
    "iso:country":"BE",
    "sg:address":"Michel Theysstraat 60",
    "sg:city":"Diest",
    "sg:classifiers":[
        {
            "category":"Government",
            "subcategory":"Police Station",
            "type":"Public Place"
        }
    ],
    "sg:phone":"+32 13 31 21 22",
    "sg:postcode":"3290",
    "sg:province":"Vlaams-Brabant",
    "sg:tags":[
        "gendarmerie"
    ],
    "wof:name":"Federale Politie",
    "wof:placetype":"venue"
},
  "geometry": {"coordinates":[5.054336071,50.9878692627],"type":"Point"}
}