{
  "type": "Feature",
  "properties": {
    "iso:country":"BE",
    "sg:address":"Rue Paul D'andrimont 9",
    "sg:city":"Soumagne",
    "sg:orig_category":"Verplichte sociale verzekeringen",
    "sg:phone":"+32 4 358 37 58",
    "sg:postcode":"4630",
    "sg:province":"Li\u00e8ge",
    "wof:name":"Mutualit\u00c9 Profes. & Libre",
    "wof:placetype":"venue"
},
  "geometry": {"coordinates":[5.7121348381,50.6247215271],"type":"Point"}
}