{
  "type": "Feature",
  "properties": {
    "iso:country":"BE",
    "sg:address":"Aarschotsebaan 15",
    "sg:city":"Boortmeerbeek",
    "sg:orig_category":"Rev\u00eatements de sols and murs. Rev\u00eatements pour sols and murs",
    "sg:phone":"+32 15 61 00 75",
    "sg:postcode":"3191",
    "sg:province":"Vlaams-Brabant",
    "wof:name":"Floridor",
    "wof:placetype":"venue"
},
  "geometry": {"coordinates":[4.5420560837,50.969291687],"type":"Point"}
}