{
  "type": "Feature",
  "properties": {
    "addr:full":"Fraikinstraat 12 Herentals Antwerpen 2200",
    "addr:housenumber":"12",
    "addr:postcode":"2200",
    "addr:street":"Fraikinstraat",
    "iso:country":"BE",
    "sg:address":"Fraikinstraat 12",
    "sg:city":"Herentals",
    "sg:classifiers":[
        {
            "category":"Shopping",
            "subcategory":"Computers & Home Electronics",
            "type":"Retail Goods"
        }
    ],
    "sg:phone":"+32 14 28 66 66",
    "sg:postcode":"2200",
    "sg:province":"Antwerpen",
    "sg:tags":[
        "-",
        "typewriter"
    ],
    "wof:name":"Maes Nv",
    "wof:placetype":"venue"
},
  "geometry": {"coordinates":[4.8350701332,51.17993927],"type":"Point"}
}