{
  "type": "Feature",
  "properties": {
    "iso:country":"BE",
    "sg:address":"Maastrichtersteenweg 6",
    "sg:city":"Maaseik",
    "sg:orig_category":"Slagers",
    "sg:phone":"+32 89 56 72 43",
    "sg:postcode":"3680",
    "sg:province":"Limburg",
    "wof:name":"Budgetslager",
    "wof:placetype":"venue"
},
  "geometry": {"coordinates":[5.7855172157,51.0959739685],"type":"Point"}
}