{
  "type": "Feature",
  "properties": {
    "addr:full":"R Massart 16a Fernelmont Namur 5380",
    "addr:housenumber":"16a",
    "addr:postcode":"5380",
    "addr:street":"Massart",
    "iso:country":"BE",
    "sg:address":"R Massart 16a",
    "sg:city":"Fernelmont",
    "sg:classifiers":[
        {
            "category":"Real Estate",
            "subcategory":"Real Estate Services",
            "type":"Services"
        }
    ],
    "sg:phone":"+32 81 83 51 99",
    "sg:postcode":"5380",
    "sg:province":"Namur",
    "wof:name":"Jp Partners",
    "wof:placetype":"venue"
},
  "geometry": {"coordinates":[4.9861078262,50.5531463623],"type":"Point"}
}