{
  "type": "Feature",
  "properties": {
    "iso:country":"BE",
    "sg:address":"Boulevard Belgica 58",
    "sg:city":"Sint-jans-molenbeek/molenbeek-saint-jean",
    "sg:orig_category":"Epiceries",
    "sg:phone":"+32 2 427 60 13",
    "sg:postcode":"1080",
    "sg:province":"Bruxelles-Capitale",
    "wof:name":"Atmanex",
    "wof:placetype":"venue"
},
  "geometry": {"coordinates":[4.3361778259,50.8671150208],"type":"Point"}
}