{
  "type": "Feature",
  "properties": {
    "addr:full":"Scheldestraat 23 Zwalm Oost-Vlaanderen 9636",
    "addr:housenumber":"23",
    "addr:postcode":"9636",
    "addr:street":"Scheldestraat;Oost-Vlaanderen",
    "iso:country":"BE",
    "sg:address":"Scheldestraat 23",
    "sg:city":"Zwalm",
    "sg:orig_category":"Woningbouw",
    "sg:phone":"+32 55 49 87 86",
    "sg:postcode":"9636",
    "sg:province":"Oost-Vlaanderen",
    "wof:name":"Marlex",
    "wof:placetype":"venue"
},
  "geometry": {"coordinates":[3.6837511063,50.8923606873],"type":"Point"}
}