{
  "type": "Feature",
  "properties": {
    "iso:country":"BE",
    "sg:address":"Avenue Des P\u00c2querettes 16",
    "sg:city":"Rixensart",
    "sg:orig_category":"Jardinage",
    "sg:phone":"+32 2 653 07 64",
    "sg:postcode":"1330",
    "sg:province":"Brabant Wallon",
    "wof:name":"Stassin",
    "wof:placetype":"venue"
},
  "geometry": {"coordinates":[4.5248208046,50.7128639221],"type":"Point"}
}