{
  "type": "Feature",
  "properties": {
    "iso:country":"BE",
    "sg:address":"Rue De La Vicomt\u00c9 4",
    "sg:city":"Ferrieres",
    "sg:orig_category":"Installatie van houten of kunststof schrijnwerk",
    "sg:phone":"+32 864005",
    "sg:postcode":"4190",
    "sg:province":"Li\u00e8ge",
    "wof:name":"Cuisine Monde",
    "wof:placetype":"venue"
},
  "geometry": {"coordinates":[5.6183948517,50.4026527405],"type":"Point"}
}