{
  "type": "Feature",
  "properties": {
    "addr:full":"Place De La Grande P\u00eacherie 18 Mons Hainaut 7000",
    "addr:housenumber":"18",
    "addr:postcode":"7000",
    "addr:street":"Place De La Grande Pe\u0302Cherie;Hainaut",
    "iso:country":"BE",
    "sg:address":"Place De La Grande P\u00eacherie 18",
    "sg:city":"Mons",
    "sg:classifiers":[
        {
            "category":"Real Estate",
            "subcategory":"Architect",
            "type":"Services"
        }
    ],
    "sg:phone":"+32 65 35 42 51",
    "sg:postcode":"7000",
    "sg:province":"Hainaut",
    "wof:name":"Poulain M",
    "wof:placetype":"venue"
},
  "geometry": {"coordinates":[3.9517519474,50.451587677],"type":"Point"}
}