{
  "type": "Feature",
  "properties": {
    "iso:country":"BE",
    "sg:address":"Rue De La Gare 9",
    "sg:city":"Comines-warneton",
    "sg:orig_category":"Mat\u00e9riel de T\u00e9l\u00e9communication. Equipement photographique",
    "sg:phone":"+32 56 55 54 91",
    "sg:postcode":"7780",
    "sg:province":"Hainaut",
    "wof:name":"La Maison De La Photo",
    "wof:placetype":"venue"
},
  "geometry": {"coordinates":[2.9971749783,50.7715950012],"type":"Point"}
}