{
  "type": "Feature",
  "properties": {
    "iso:country":"BE",
    "sg:address":"Kielsbroek 56",
    "sg:city":"Antwerpen",
    "sg:classifiers":[
        {
            "category":"Wholesale",
            "subcategory":"Fruits & Vegetables",
            "type":"Manufacturing & Wholesale Goods"
        }
    ],
    "sg:phone":"+32 3 237 59 73",
    "sg:postcode":"2020",
    "sg:province":"Antwerpen",
    "sg:tags":[
        "whol",
        "-"
    ],
    "wof:name":"Euro Gijbels Nv",
    "wof:placetype":"venue"
},
  "geometry": {"coordinates":[4.3715372086,51.1985931396],"type":"Point"}
}