{
  "type": "Feature",
  "properties": {
    "iso:country":"BE",
    "sg:address":"Route Des Moulins 77",
    "sg:city":"Anthisnes (tavier)",
    "sg:classifiers":[
        {
            "category":"Farming",
            "subcategory":"Fish & Marine Products",
            "type":"Manufacturing & Wholesale Goods"
        }
    ],
    "sg:phone":"+32 4 383 66 57",
    "sg:postcode":"4163",
    "sg:province":"Li\u00e8ge",
    "sg:tags":[
        "breeding"
    ],
    "wof:name":"Pisciculture Du Condroz",
    "wof:placetype":"venue"
},
  "geometry": {"coordinates":[5.4595918655,50.4836044312],"type":"Point"}
}