{
  "type": "Feature",
  "properties": {
    "iso:country":"BE",
    "sg:address":"Verastenstraat 2",
    "sg:city":"Aalst",
    "sg:classifiers":[
        {
            "category":"Real Estate",
            "subcategory":"Architect",
            "type":"Services"
        }
    ],
    "sg:phone":"+32 53 41 49 80",
    "sg:postcode":"9300",
    "sg:province":"Oost-Vlaanderen",
    "wof:name":"Sterck H",
    "wof:placetype":"venue"
},
  "geometry": {"coordinates":[4.026693821,50.9391403198],"type":"Point"}
}