{
  "type": "Feature",
  "properties": {
    "addr:full":"Houtstraat 54 Zulte Oost-Vlaanderen 9870",
    "addr:housenumber":"54",
    "addr:postcode":"9870",
    "addr:street":"Houtstraat",
    "iso:country":"BE",
    "sg:address":"Houtstraat 54",
    "sg:city":"Zulte",
    "sg:classifiers":[
        {
            "category":"Restaurant",
            "type":"Food & Drink"
        }
    ],
    "sg:phone":"+32 9 388 33 03",
    "sg:postcode":"9870",
    "sg:province":"Oost-Vlaanderen",
    "wof:name":"St-christophe",
    "wof:placetype":"venue"
},
  "geometry": {"coordinates":[3.4666550159,50.9252052307],"type":"Point"}
}