{
  "type": "Feature",
  "properties": {
    "addr:full":"Chauss\u00c9e De Bruxelles 113 Soignies Hainaut 7061",
    "addr:housenumber":"113",
    "addr:postcode":"7061",
    "addr:street":"Chausse\u0301E De Bruxelles",
    "iso:country":"BE",
    "sg:address":"Chauss\u00c9e De Bruxelles 113",
    "sg:city":"Soignies",
    "sg:orig_category":"Artsen and specialisten",
    "sg:phone":"+32 65 73 03 99",
    "sg:postcode":"7061",
    "sg:province":"Hainaut",
    "wof:name":"Mich\u00c8le Johnson",
    "wof:placetype":"venue"
},
  "geometry": {"coordinates":[4.0133500099,50.5159416199],"type":"Point"}
}