{
  "type": "Feature",
  "properties": {
    "addr:full":"Ten-brielenstraat 46 Komen-waasten/comines-warneton Hainaut 7780",
    "addr:housenumber":"46;7780",
    "addr:street":"Ten-Brielenstraat",
    "iso:country":"BE",
    "sg:address":"Ten-brielenstraat 46",
    "sg:city":"Komen-waasten/comines-warneton",
    "sg:orig_category":"Kapsalons",
    "sg:phone":"+32 56 55 64 88",
    "sg:postcode":"7780",
    "sg:province":"Hainaut",
    "wof:name":"Jean-luc Hairdressing",
    "wof:placetype":"venue"
},
  "geometry": {"coordinates":[2.9984300137,50.7863311768],"type":"Point"}
}