{
  "type": "Feature",
  "properties": {
    "iso:country":"BE",
    "sg:address":"Provinciale Steenweg 371",
    "sg:city":"Schelle",
    "sg:classifiers":[
        {
            "category":"Cafe",
            "type":"Food & Drink"
        }
    ],
    "sg:phone":"+32 3 887 74 57",
    "sg:postcode":"2627",
    "sg:province":"Antwerpen",
    "sg:tags":[
        "caf\u00e9s"
    ],
    "wof:name":"Caf\u00c9 't Moleken",
    "wof:placetype":"venue"
},
  "geometry": {"coordinates":[4.3350391388,51.1189002991],"type":"Point"}
}