{
  "type": "Feature",
  "properties": {
    "iso:country":"BE",
    "sg:address":"Cauwerburg 50",
    "sg:city":"Temse",
    "sg:classifiers":[
        {
            "category":"Building & Trades",
            "subcategory":"Pest Control",
            "type":"Services"
        }
    ],
    "sg:phone":"+32 3 711 07 05",
    "sg:postcode":"9140",
    "sg:province":"Oost-Vlaanderen",
    "sg:tags":[
        "painting",
        "contractor"
    ],
    "wof:name":"Verbeke M",
    "wof:placetype":"venue"
},
  "geometry": {"coordinates":[4.2019281387,51.1249656677],"type":"Point"}
}