{
  "type": "Feature",
  "properties": {
    "addr:full":"Torredreef 12 Maldegem Oost-Vlaanderen 9990",
    "addr:housenumber":"12",
    "addr:postcode":"9990",
    "addr:street":"Torredreef",
    "iso:country":"BE",
    "sg:address":"Torredreef 12",
    "sg:city":"Maldegem",
    "sg:orig_category":"Eleveurs and marchands de porcs. Eleveurs de bovins",
    "sg:phone":"+32 50 71 32 49",
    "sg:postcode":"9990",
    "sg:province":"Oost-Vlaanderen",
    "wof:name":"Luc Dhaenens",
    "wof:placetype":"venue"
},
  "geometry": {"coordinates":[3.4347751141,51.168006897],"type":"Point"}
}