{
  "type": "Feature",
  "properties": {
    "addr:full":"Oud-hoflaan 18 Kruibeke (bazel) Oost-Vlaanderen 9150",
    "addr:housenumber":"18",
    "addr:postcode":"9150",
    "addr:street":"Oud-Hoflaan",
    "iso:country":"BE",
    "sg:address":"Oud-hoflaan 18",
    "sg:city":"Kruibeke (bazel)",
    "sg:classifiers":[
        {
            "category":"Manufacturing",
            "subcategory":"Textiles",
            "type":"Manufacturing & Wholesale Goods"
        }
    ],
    "sg:phone":"+32 3 774 49 64",
    "sg:postcode":"9150",
    "sg:province":"Oost-Vlaanderen",
    "sg:tags":[
        "raw",
        "material",
        "-"
    ],
    "wof:name":"Nefil",
    "wof:placetype":"venue"
},
  "geometry": {"coordinates":[4.3080840111,51.1758880615],"type":"Point"}
}