{
  "type": "Feature",
  "properties": {
    "addr:full":"Wingepark 10 Rotselaar Vlaams-Brabant 3110",
    "addr:housenumber":"10",
    "addr:postcode":"3110",
    "addr:street":"Wingepark",
    "iso:country":"BE",
    "sg:address":"Wingepark 10",
    "sg:city":"Rotselaar",
    "sg:classifiers":[
        {
            "category":"Restaurant",
            "type":"Food & Drink"
        }
    ],
    "sg:phone":"+32 16 58 99 00",
    "sg:postcode":"3110",
    "sg:province":"Vlaams-Brabant",
    "sg:tags":[
        "industrial",
        "kitchen",
        "catering"
    ],
    "wof:name":"Java",
    "wof:placetype":"venue"
},
  "geometry": {"coordinates":[4.7463560104,50.9398727417],"type":"Point"}
}