{
  "type": "Feature",
  "properties": {
    "iso:country":"BE",
    "sg:address":"Stokstraat 14",
    "sg:city":"Kruishoutem",
    "sg:classifiers":[
        {
            "category":"Home & Garden",
            "subcategory":"Carpets & Floor Coverings",
            "type":"Retail Goods"
        }
    ],
    "sg:phone":"+32 9 388 33 15",
    "sg:postcode":"9770",
    "sg:province":"Oost-Vlaanderen",
    "sg:tags":[
        "prefab",
        "element"
    ],
    "wof:name":"De Sloovere Kruisbeton Nv",
    "wof:placetype":"venue"
},
  "geometry": {"coordinates":[3.4859530926,50.9089393616],"type":"Point"}
}