{
  "type": "Feature",
  "properties": {
    "iso:country":"BE",
    "sg:address":"Rue De Bouny 46",
    "sg:city":"Fl\u00e9ron (roms\u00e9e)",
    "sg:classifiers":[
        {
            "category":"Health Services",
            "subcategory":"Doctor",
            "type":"Services"
        }
    ],
    "sg:phone":"+32 4 358 93 73",
    "sg:postcode":"4624",
    "sg:province":"Li\u00e8ge",
    "sg:tags":[
        "medicinephysicians",
        "surgeon"
    ],
    "wof:name":"Lissens C",
    "wof:placetype":"venue"
},
  "geometry": {"coordinates":[5.6644630432,50.6101989746],"type":"Point"}
}