{
  "type": "Feature",
  "properties": {
    "addr:full":"Kortrijksestraat 23 Harelbeke West-Vlaanderen 8530",
    "addr:housenumber":"23",
    "addr:postcode":"8530",
    "addr:street":"Kortrijksestraat",
    "iso:country":"BE",
    "sg:address":"Kortrijksestraat 23",
    "sg:city":"Harelbeke",
    "sg:orig_category":"Pain, p\u00e2tisseries and confiseries",
    "sg:phone":"+32 56 71 29 57",
    "sg:postcode":"8530",
    "sg:province":"West-Vlaanderen",
    "wof:name":"G. Meyfroot",
    "wof:placetype":"venue"
},
  "geometry": {"coordinates":[3.3068039417,50.8532829285],"type":"Point"}
}