{
  "type": "Feature",
  "properties": {
    "addr:full":"Grote Markt 43 Turnhout Antwerpen 2300",
    "addr:housenumber":"43",
    "addr:postcode":"2300",
    "addr:street":"Grote Markt",
    "iso:country":"BE",
    "sg:address":"Grote Markt 43",
    "sg:city":"Turnhout",
    "sg:classifiers":[
        {
            "category":"Travel",
            "subcategory":"Travel Agent",
            "type":"Entertainment"
        }
    ],
    "sg:phone":"+32 14 43 88 81",
    "sg:postcode":"2300",
    "sg:province":"Antwerpen",
    "sg:tags":[
        "holiday",
        "flash",
        "plus",
        "reisbureaus"
    ],
    "wof:name":"Boschmans Reizen",
    "wof:placetype":"venue"
},
  "geometry": {"coordinates":[4.9478597641,51.3229217529],"type":"Point"}
}