{
  "type": "Feature",
  "properties": {
    "iso:country":"BE",
    "sg:address":"Rue Samiette 170",
    "sg:city":"Nivelles",
    "sg:orig_category":"M\u00e9decins and sp\u00e9cialistes",
    "sg:phone":"+32 67 21 08 45",
    "sg:postcode":"1400",
    "sg:province":"Brabant Wallon",
    "wof:name":"T. Bertrand",
    "wof:placetype":"venue"
},
  "geometry": {"coordinates":[4.3066730499,50.5964622498],"type":"Point"}
}