{
  "type": "Feature",
  "properties": {
    "addr:full":"Zuidlaan 55 Blankenberge West-Vlaanderen 8370",
    "addr:housenumber":"55",
    "addr:postcode":"8370",
    "addr:street":"Zuidlaan",
    "iso:country":"BE",
    "sg:address":"Zuidlaan 55",
    "sg:city":"Blankenberge",
    "sg:classifiers":[
        {
            "category":"Health Services",
            "subcategory":"Health Practitioner",
            "type":"Services"
        }
    ],
    "sg:phone":"+32 50 41 37 64",
    "sg:postcode":"8370",
    "sg:province":"West-Vlaanderen",
    "sg:tags":[
        "physiotherapist"
    ],
    "wof:name":"Rivi\u00e8re Thierry",
    "wof:placetype":"venue"
},
  "geometry": {"coordinates":[3.1326389313,51.3094177246],"type":"Point"}
}