{
  "type": "Feature",
  "properties": {
    "iso:country":"BE",
    "sg:address":"Rue Des Brasseries 13",
    "sg:city":"Wavre",
    "sg:orig_category":"Voertuigen",
    "sg:phone":"+32 10 22 79 42",
    "sg:postcode":"1300",
    "sg:province":"Brabant Wallon",
    "wof:name":"Castro",
    "wof:placetype":"venue"
},
  "geometry": {"coordinates":[4.6113581657,50.7154388428],"type":"Point"}
}