{
  "type": "Feature",
  "properties": {
    "addr:full":"Rue De Saint-l\u00e9ger 154 Mouscron (dottignies) Hainaut 7711",
    "addr:housenumber":"154",
    "addr:postcode":"7711",
    "addr:street":"Rue De Saint-Le\u0301Ger",
    "iso:country":"BE",
    "sg:address":"Rue De Saint-l\u00e9ger 154",
    "sg:city":"Mouscron (dottignies)",
    "sg:classifiers":[
        {
            "category":"Health Services",
            "subcategory":"Doctor",
            "type":"Services"
        }
    ],
    "sg:phone":"+32 56 48 94 87",
    "sg:postcode":"7711",
    "sg:province":"Hainaut",
    "sg:tags":[
        "medicinephysicians",
        "surgeon"
    ],
    "wof:name":"Hollaert G",
    "wof:placetype":"venue"
},
  "geometry": {"coordinates":[3.3077180386,50.7221908569],"type":"Point"}
}