{
  "type": "Feature",
  "properties": {
    "iso:country":"BE",
    "sg:address":"Boulevard Landrieu 36",
    "sg:city":"Beloeil (bas\u00e8cles)",
    "sg:classifiers":[
        {
            "category":"Banks & Credit Unions",
            "subcategory":"Financial Services",
            "type":"Services"
        }
    ],
    "sg:phone":"+32 69 57 71 19",
    "sg:postcode":"7971",
    "sg:province":"Hainaut",
    "sg:tags":[
        "loan",
        "mortgage"
    ],
    "wof:name":"Dath-hennebert Assurances",
    "wof:placetype":"venue"
},
  "geometry": {"coordinates":[3.6535658836,50.5254631042],"type":"Point"}
}