{
  "type": "Feature",
  "properties": {
    "iso:country":"BE",
    "sg:address":"Hoekskensstraat 13",
    "sg:city":"Lochristi",
    "sg:orig_category":"Rundveehouders",
    "sg:phone":"+32 9 355 81 41",
    "sg:postcode":"9080",
    "sg:province":"Oost-Vlaanderen",
    "wof:name":"Filips Rogiers",
    "wof:placetype":"venue"
},
  "geometry": {"coordinates":[3.8436219692,51.1000366211],"type":"Point"}
}