{
  "type": "Feature",
  "properties": {
    "addr:full":"Moutstraat 5 Gent Oost-Vlaanderen 9000",
    "addr:housenumber":"5",
    "addr:postcode":"9000",
    "addr:street":"Moutstraat;Oost-Vlaanderen",
    "iso:country":"BE",
    "sg:address":"Moutstraat 5",
    "sg:city":"Gent",
    "sg:classifiers":[
        {
            "category":"Retail",
            "subcategory":"Animal Services",
            "type":"Services"
        }
    ],
    "sg:phone":"+32 9 220 76 34",
    "sg:postcode":"9000",
    "sg:province":"Oost-Vlaanderen",
    "sg:tags":[
        "grooming",
        "-",
        "dog"
    ],
    "wof:name":"Bora",
    "wof:placetype":"venue"
},
  "geometry": {"coordinates":[3.7329208851,51.0293540955],"type":"Point"}
}