{
  "type": "Feature",
  "properties": {
    "iso:country":"BE",
    "sg:address":"Gounodlaan 80",
    "sg:city":"Anderlecht/anderlecht",
    "sg:orig_category":"Brood, gebak and snoepgoed",
    "sg:phone":"+32 2 521 52 01",
    "sg:postcode":"1070",
    "sg:province":"Bruxelles-Capitale",
    "wof:name":"Josephus Melotte/j. Melotte",
    "wof:placetype":"venue"
},
  "geometry": {"coordinates":[4.3009409904,50.8296775818],"type":"Point"}
}