{
  "type": "Feature",
  "properties": {
    "addr:full":"Raverschootstraat 184 Eeklo Oost-Vlaanderen 9900",
    "addr:housenumber":"184",
    "addr:postcode":"9900",
    "addr:street":"Raverschootstraat",
    "iso:country":"BE",
    "sg:address":"Raverschootstraat 184",
    "sg:city":"Eeklo",
    "sg:classifiers":[
        {
            "category":"Building & Trades",
            "subcategory":"Construction",
            "type":"Services"
        }
    ],
    "sg:phone":"+32 9 377 17 95",
    "sg:postcode":"9900",
    "sg:province":"Oost-Vlaanderen",
    "sg:tags":[
        "installation",
        "-",
        "central",
        "heating"
    ],
    "wof:name":"Vanderschaeghe D",
    "wof:placetype":"venue"
},
  "geometry": {"coordinates":[3.5465760231,51.188117981],"type":"Point"}
}