{
  "type": "Feature",
  "properties": {
    "iso:country":"BE",
    "sg:address":"Molenstraat 7",
    "sg:city":"Aarschot (rillaar)",
    "sg:classifiers":[
        {
            "category":"Shopping",
            "subcategory":"Party Supplies",
            "type":"Retail Goods"
        }
    ],
    "sg:phone":"+32 16 50 32 17",
    "sg:postcode":"3202",
    "sg:province":"Vlaams-Brabant",
    "sg:tags":[
        "-",
        "pedicure"
    ],
    "wof:name":"Kindex Bvba",
    "wof:placetype":"venue"
},
  "geometry": {"coordinates":[4.8924388885,50.9736862183],"type":"Point"}
}