{
  "type": "Feature",
  "properties": {
    "addr:full":"Land Van Waaslaan 1213kaai Beveren (verrebroek) Oost-Vlaanderen 9130",
    "addr:postcode":"1213kaai;9130",
    "addr:street":"Land Van Waaslaan",
    "iso:country":"BE",
    "sg:address":"Land Van Waaslaan 1213kaai",
    "sg:city":"Beveren (verrebroek)",
    "sg:classifiers":[
        {
            "category":"Government",
            "subcategory":"Embassy",
            "type":"Public Place"
        }
    ],
    "sg:phone":"+32 3 570 95 45",
    "sg:postcode":"9130",
    "sg:province":"Oost-Vlaanderen",
    "sg:tags":[
        "consulate"
    ],
    "wof:name":"Finland (consulaat Generaal)",
    "wof:placetype":"venue"
},
  "geometry": {"coordinates":[4.2433748245,51.2561531067],"type":"Point"}
}