{
  "type": "Feature",
  "properties": {
    "iso:country":"BE",
    "sg:address":"Rue D\u00b4havre 53/2",
    "sg:city":"Binche",
    "sg:classifiers":[
        {
            "category":"Insurance",
            "subcategory":"Life Insurance",
            "type":"Services"
        }
    ],
    "sg:phone":"+32 64 33 81 39",
    "sg:postcode":"7130",
    "sg:province":"Hainaut",
    "sg:tags":[
        "assurance"
    ],
    "wof:name":"De Braye Bureau Financier",
    "wof:placetype":"venue"
},
  "geometry": {"coordinates":[4.1660728455,50.412311554],"type":"Point"}
}