{
  "type": "Feature",
  "properties": {
    "iso:country":"BE",
    "sg:address":"Rue Schmitz 12",
    "sg:city":"Koekelberg",
    "sg:orig_category":"Kansspelen",
    "sg:phone":"+32 2 411 77 62",
    "sg:postcode":"1081",
    "sg:province":"Bruxelles-Capitale",
    "wof:name":"Le Derby-ladbroke",
    "wof:placetype":"venue"
},
  "geometry": {"coordinates":[4.332157135,50.8574638367],"type":"Point"}
}