{
  "type": "Feature",
  "properties": {
    "addr:full":"Marktplein 10 Nieuwpoort West-Vlaanderen 8620",
    "addr:housenumber":"10",
    "addr:postcode":"8620",
    "addr:street":"Marktplein",
    "iso:country":"BE",
    "sg:address":"Marktplein 10",
    "sg:city":"Nieuwpoort",
    "sg:orig_category":"Banken and kredietinstellingen",
    "sg:phone":"+32 58 23 50 76",
    "sg:postcode":"8620",
    "sg:province":"West-Vlaanderen",
    "wof:name":"Kbc",
    "wof:placetype":"venue"
},
  "geometry": {"coordinates":[2.7508380413,51.1295051575],"type":"Point"}
}