{
  "type": "Feature",
  "properties": {
    "addr:full":"Dr\u00c8ve Richelle 161 Waterloo Brabant Wallon 1410",
    "addr:housenumber":"161",
    "addr:postcode":"1410",
    "addr:street":"Dre\u0300Ve Richelle",
    "iso:country":"BE",
    "sg:address":"Dr\u00c8ve Richelle 161",
    "sg:city":"Waterloo",
    "sg:orig_category":"Agences d'exp\u00e9dition",
    "sg:phone":"+32 2 352 87 08",
    "sg:postcode":"1410",
    "sg:province":"Brabant Wallon",
    "wof:name":"Eurotin",
    "wof:placetype":"venue"
},
  "geometry": {"coordinates":[4.4104981422,50.7075843811],"type":"Point"}
}