{
  "type": "Feature",
  "properties": {
    "iso:country":"BE",
    "sg:address":"Vindictivelaan 31",
    "sg:city":"Oostende",
    "sg:classifiers":[
        {
            "category":"Travel",
            "subcategory":"Hotels & Motels",
            "type":"Entertainment"
        }
    ],
    "sg:phone":"+32 59 70 51 58",
    "sg:postcode":"8400",
    "sg:province":"West-Vlaanderen",
    "wof:name":"'t Zeegat",
    "wof:placetype":"venue"
},
  "geometry": {"coordinates":[2.92334795,51.228969574],"type":"Point"}
}