{
  "type": "Feature",
  "properties": {
    "iso:country":"BE",
    "sg:address":"Av Des M\u00e9sanges 11",
    "sg:city":"Bruxelles",
    "sg:orig_category":"Miscellaneous Products",
    "sg:phone":"+32 2 673 33 58",
    "sg:postcode":"1160",
    "sg:province":"Bruxelles-Capitale",
    "wof:name":"Huygens Sa",
    "wof:placetype":"venue"
},
  "geometry": {"coordinates":[4.424861908,50.8215332031],"type":"Point"}
}