{
  "type": "Feature",
  "properties": {
    "iso:country":"BE",
    "sg:address":"Boulevard G\u00e9n\u00e9ral Wahis 20 Box 41",
    "sg:city":"Bruxelles (schaerbeek)",
    "sg:classifiers":[
        {
            "category":"Manufacturing",
            "subcategory":"Chemicals & Compounds",
            "type":"Manufacturing & Wholesale Goods"
        }
    ],
    "sg:phone":"+32 2 726 00 44",
    "sg:postcode":"1030",
    "sg:province":"Bruxelles-Capitale",
    "sg:tags":[
        "pharmaceutical",
        "product"
    ],
    "wof:name":"Prochiphar Sa",
    "wof:placetype":"venue"
},
  "geometry": {"coordinates":[4.3954620361,50.8595237732],"type":"Point"}
}