{
  "type": "Feature",
  "properties": {
    "addr:full":"Verkortingstraat 53 Gent (sint-amandsberg) Oost-Vlaanderen 9040",
    "addr:housenumber":"53",
    "addr:postcode":"9040",
    "addr:street":"Verkortingstraat",
    "iso:country":"BE",
    "sg:address":"Verkortingstraat 53",
    "sg:city":"Gent (sint-amandsberg)",
    "sg:classifiers":[
        {
            "category":"Building & Trades",
            "subcategory":"Construction",
            "type":"Services"
        }
    ],
    "sg:phone":"+32 9 219 09 60",
    "sg:postcode":"9040",
    "sg:province":"Oost-Vlaanderen",
    "sg:tags":[
        "ecological"
    ],
    "wof:name":"Tintelijn Cvba",
    "wof:placetype":"venue"
},
  "geometry": {"coordinates":[3.7521839142,51.0648460388],"type":"Point"}
}