{
  "type": "Feature",
  "properties": {
    "addr:full":"Herkenrodesingel 2 Hasselt Limburg 3500",
    "addr:housenumber":"2",
    "addr:postcode":"3500",
    "addr:street":"Herkenrodesingel",
    "iso:country":"BE",
    "sg:address":"Herkenrodesingel 2",
    "sg:city":"Hasselt",
    "sg:classifiers":[
        {
            "category":"Shopping",
            "subcategory":"Optician",
            "type":"Retail Goods"
        }
    ],
    "sg:phone":"+32 11 25 14 50",
    "sg:postcode":"3500",
    "sg:province":"Limburg",
    "sg:tags":[
        "-"
    ],
    "wof:name":"Pearle Vision Center",
    "wof:placetype":"venue"
},
  "geometry": {"coordinates":[5.3173890114,50.937412262],"type":"Point"}
}