{
  "type": "Feature",
  "properties": {
    "addr:full":"Daalheideweg 70 Zonhoven Limburg 3520",
    "addr:housenumber":"70",
    "addr:postcode":"3520",
    "addr:street":"Daalheideweg",
    "iso:country":"BE",
    "sg:address":"Daalheideweg 70",
    "sg:city":"Zonhoven",
    "sg:orig_category":"Installatie van houten of kunststof schrijnwerk Woningbouw",
    "sg:phone":"+32 11 82 35 38",
    "sg:postcode":"3520",
    "sg:province":"Limburg",
    "wof:name":"Bielen",
    "wof:placetype":"venue"
},
  "geometry": {"coordinates":[5.404255867,50.9756469727],"type":"Point"}
}