{
  "type": "Feature",
  "properties": {
    "addr:full":"58 Kunstlaan Brussel Bruxelles-Capitale 1000",
    "addr:housenumber":"58",
    "addr:postcode":"1000",
    "addr:street":"Kunstlaan Brussel",
    "iso:country":"BE",
    "sg:address":"58 Kunstlaan",
    "sg:city":"Brussel",
    "sg:classifiers":[
        {
            "category":"Banks & Credit Unions",
            "subcategory":"Financial Services",
            "type":"Services"
        }
    ],
    "sg:phone":"+32 2 551 50 00",
    "sg:postcode":"1000",
    "sg:province":"Bruxelles-Capitale",
    "sg:tags":[
        "banking",
        "finance",
        "insurance"
    ],
    "wof:name":"Sumitomo Bank",
    "wof:placetype":"venue"
},
  "geometry": {"coordinates":[4.3670859337,50.8421707153],"type":"Point"}
}