{
  "type": "Feature",
  "properties": {
    "iso:country":"BE",
    "sg:address":"Molenakkerlaan 2",
    "sg:city":"Brecht",
    "sg:orig_category":"Editeurs de livres. Librairies",
    "sg:phone":"+32 3 290 80 35",
    "sg:postcode":"2960",
    "sg:province":"Antwerpen",
    "wof:name":"Koenraad Elst",
    "wof:placetype":"venue"
},
  "geometry": {"coordinates":[4.6331868172,51.3468055725],"type":"Point"}
}