{
  "type": "Feature",
  "properties": {
    "iso:country":"BE",
    "sg:address":"Vredestraat 157",
    "sg:city":"Hove",
    "sg:orig_category":"Avocats and conseillers juridiques",
    "sg:phone":"+32 3 457 71 56",
    "sg:postcode":"2540",
    "sg:province":"Antwerpen",
    "wof:name":"Johan Gruijthuijsen",
    "wof:placetype":"venue"
},
  "geometry": {"coordinates":[4.4644699097,51.1464004517],"type":"Point"}
}