{
  "type": "Feature",
  "properties": {
    "addr:full":"Rue Des Briquetteries 9 Wadelincourt Hainaut 7971",
    "addr:housenumber":"9",
    "addr:postcode":"7971",
    "addr:street":"Rue Des Briquetteries;Hainaut",
    "iso:country":"BE",
    "sg:address":"Rue Des Briquetteries 9",
    "sg:city":"Wadelincourt",
    "sg:classifiers":[
        {
            "category":"Farming",
            "subcategory":"Livestock Farm",
            "type":"Manufacturing & Wholesale Goods"
        }
    ],
    "sg:phone":"+32 69 57 50 73",
    "sg:postcode":"7971",
    "sg:province":"Hainaut",
    "sg:tags":[
        "breeding",
        "agriculture",
        "animal"
    ],
    "wof:name":"Claude Picron Et Fils Sa",
    "wof:placetype":"venue"
},
  "geometry": {"coordinates":[3.6504189968,50.5386199951],"type":"Point"}
}