{
  "type": "Feature",
  "properties": {
    "iso:country":"BE",
    "sg:address":"Steynstr 181",
    "sg:city":"Antwerpen",
    "sg:classifiers":[
        {
            "category":"Wholesale",
            "subcategory":"Medical Equipment & Supplies",
            "type":"Manufacturing & Wholesale Goods"
        }
    ],
    "sg:phone":"+32 3 828 56 90",
    "sg:postcode":"2660",
    "sg:province":"Antwerpen",
    "sg:tags":[
        "instrument",
        "health",
        "-",
        "precision"
    ],
    "wof:name":"Aldent Bvba",
    "wof:placetype":"venue"
},
  "geometry": {"coordinates":[4.3397898674,51.1732788086],"type":"Point"}
}