{
  "type": "Feature",
  "properties": {
    "addr:full":"Pastoriestraat 50 Brugge St Andries West-Vlaanderen 8200",
    "addr:housenumber":"50",
    "addr:postcode":"8200",
    "addr:street":"Pastoriestraat;St",
    "iso:country":"BE",
    "sg:address":"Pastoriestraat 50",
    "sg:city":"Brugge St Andries",
    "sg:orig_category":"Services pour animaux domestiques",
    "sg:phone":"+32 496 17 84 36",
    "sg:postcode":"8200",
    "sg:province":"West-Vlaanderen",
    "wof:name":"Trim Art",
    "wof:placetype":"venue"
},
  "geometry": {"coordinates":[3.2112550735,51.1885986328],"type":"Point"}
}