{
  "type": "Feature",
  "properties": {
    "addr:full":"Place Saint-denis 9 Bruxelles (forest) Bruxelles-Capitale 1190",
    "addr:housenumber":"9",
    "addr:postcode":"1190",
    "addr:street":"Place Saint-Denis",
    "iso:country":"BE",
    "sg:address":"Place Saint-denis 9",
    "sg:city":"Bruxelles (forest)",
    "sg:classifiers":[
        {
            "category":"Retail",
            "subcategory":"Event Space",
            "type":"Services"
        }
    ],
    "sg:phone":"+32 2 375 92 07",
    "sg:postcode":"1190",
    "sg:province":"Bruxelles-Capitale",
    "sg:tags":[
        "organisation"
    ],
    "wof:name":"A.b.i. Events",
    "wof:placetype":"venue"
},
  "geometry": {"coordinates":[4.3191409111,50.8122901917],"type":"Point"}
}