{
  "type": "Feature",
  "properties": {
    "iso:country":"BE",
    "sg:address":"D\u00dcrerlaan 1",
    "sg:city":"De Haan",
    "sg:classifiers":[
        {
            "category":"Travel",
            "subcategory":"Hotels & Motels",
            "type":"Entertainment"
        }
    ],
    "sg:phone":"+32 59 23 40 11",
    "sg:postcode":"8420",
    "sg:province":"West-Vlaanderen",
    "wof:name":"Hildekind",
    "wof:placetype":"venue"
},
  "geometry": {"coordinates":[3.0281889439,51.2761764526],"type":"Point"}
}