{
  "type": "Feature",
  "properties": {
    "addr:full":"Aalterseweg 10 Knesselare Oost-Vlaanderen 9890",
    "addr:housenumber":"10",
    "addr:postcode":"9890",
    "addr:street":"Aalterseweg;Oost-Vlaanderen",
    "iso:country":"BE",
    "sg:address":"Aalterseweg 10",
    "sg:city":"Knesselare",
    "sg:classifiers":[
        {
            "category":"Banks & Credit Unions",
            "subcategory":"Bank",
            "type":"Services"
        }
    ],
    "sg:phone":"+32 55 74 18 48",
    "sg:postcode":"9890",
    "sg:province":"Oost-Vlaanderen",
    "wof:name":"Gemeentekrediet",
    "wof:placetype":"venue"
},
  "geometry": {"coordinates":[3.4159669876,51.1353225708],"type":"Point"}
}