{
  "type": "Feature",
  "properties": {
    "addr:full":"Liersesteenweg 294 Begijnendijk Vlaams-Brabant 3130",
    "addr:housenumber":"294",
    "addr:postcode":"3130",
    "addr:street":"Liersesteenweg",
    "iso:country":"BE",
    "sg:address":"Liersesteenweg 294",
    "sg:city":"Begijnendijk",
    "sg:orig_category":"Boomkwekerijen",
    "sg:phone":"+32 16 56 14 27",
    "sg:postcode":"3130",
    "sg:province":"Vlaams-Brabant",
    "wof:name":"De Bruyn",
    "wof:placetype":"venue"
},
  "geometry": {"coordinates":[4.8056249619,51.0143203735],"type":"Point"}
}