{
  "type": "Feature",
  "properties": {
    "addr:full":"Rue Vanderkindere 73 Sint-jans-molenbeek/molenbeek- Bruxelles-Capitale 1080",
    "addr:housenumber":"73",
    "addr:postcode":"1080",
    "addr:street":"Rue Vanderkindere;Molenbeek",
    "iso:country":"BE",
    "sg:address":"Rue Vanderkindere 73",
    "sg:city":"Sint-jans-molenbeek/molenbeek-",
    "sg:orig_category":"Blanchisseries and teintureries",
    "sg:postcode":"1080",
    "sg:province":"Bruxelles-Capitale",
    "wof:name":"Ipsomat",
    "wof:placetype":"venue"
},
  "geometry": {"coordinates":[4.3390049934,50.8550453186],"type":"Point"}
}