{
  "type": "Feature",
  "properties": {
    "iso:country":"BE",
    "sg:address":"Koningin Astridlaan 39",
    "sg:city":"Kapellen",
    "sg:orig_category":"Non-Classified Establishments",
    "sg:phone":"+32 3 605 13 69",
    "sg:postcode":"2950",
    "sg:province":"Antwerpen",
    "wof:name":"I M S/polyvine Nv",
    "wof:placetype":"venue"
},
  "geometry": {"coordinates":[4.4412441254,51.3128509521],"type":"Point"}
}