{
  "type": "Feature",
  "properties": {
    "addr:full":"Hoogstraat 13 Zaventem Vlaams-Brabant 1930",
    "addr:housenumber":"13",
    "addr:postcode":"1930",
    "addr:street":"Hoogstraat",
    "iso:country":"BE",
    "sg:address":"Hoogstraat 13",
    "sg:city":"Zaventem",
    "sg:classifiers":[
        {
            "category":"Health Services",
            "subcategory":"Doctor",
            "type":"Services"
        }
    ],
    "sg:phone":"+32 2 721 70 00",
    "sg:postcode":"1930",
    "sg:province":"Vlaams-Brabant",
    "sg:tags":[
        "medicinephysicians",
        "surgeon"
    ],
    "wof:name":"Debyser An",
    "wof:placetype":"venue"
},
  "geometry": {"coordinates":[4.4756650925,50.8824882507],"type":"Point"}
}