{
  "type": "Feature",
  "properties": {
    "addr:full":"Goudregenlaan 24 Brecht Antwerpen 2960",
    "addr:housenumber":"24",
    "addr:postcode":"2960",
    "addr:street":"Goudregenlaan",
    "iso:country":"BE",
    "sg:address":"Goudregenlaan 24",
    "sg:city":"Brecht",
    "sg:classifiers":[
        {
            "category":"Building & Trades",
            "subcategory":"Plumbing",
            "type":"Services"
        }
    ],
    "sg:phone":"+32 3 636 23 52",
    "sg:postcode":"2960",
    "sg:province":"Antwerpen",
    "sg:tags":[
        "diver",
        "commerce",
        "gr",
        "pour",
        "equipement"
    ],
    "wof:name":"Robomat",
    "wof:placetype":"venue"
},
  "geometry": {"coordinates":[4.5724291801,51.3058242798],"type":"Point"}
}