{
  "type": "Feature",
  "properties": {
    "iso:country":"BE",
    "sg:address":"Ijzerstraat 37",
    "sg:city":"Edingen/enghien",
    "sg:classifiers":[
        {
            "category":"Restaurant",
            "type":"Food & Drink"
        }
    ],
    "sg:phone":"+32 2 395 35 80",
    "sg:postcode":"7850",
    "sg:province":"Hainaut",
    "wof:name":"Glacier Mauricette",
    "wof:placetype":"venue"
},
  "geometry": {"coordinates":[4.0366930962,50.6960144043],"type":"Point"}
}