{
  "type": "Feature",
  "properties": {
    "iso:country":"BE",
    "sg:address":"Boulevard Des Combattants 27",
    "sg:city":"Saint-georges-sur-meuse",
    "sg:classifiers":[
        {
            "category":"Professional",
            "subcategory":"Management & Consulting",
            "type":"Services"
        }
    ],
    "sg:phone":"+32 4 275 55 53",
    "sg:postcode":"4470",
    "sg:province":"Li\u00e8ge",
    "sg:tags":[
        "consultant",
        "hygiene",
        "industrial",
        "safety"
    ],
    "wof:name":"Britte R",
    "wof:placetype":"venue"
},
  "geometry": {"coordinates":[5.3626770973,50.5860481262],"type":"Point"}
}