{
  "type": "Feature",
  "properties": {
    "iso:country":"BE",
    "sg:address":"Boulevard Piercot 52",
    "sg:city":"Li\u00e8ge 1",
    "sg:classifiers":[
        {
            "category":"Utilities",
            "subcategory":"Water",
            "type":"Services"
        }
    ],
    "sg:phone":"+32 4 220 52 30",
    "sg:postcode":"4000",
    "sg:province":"Li\u00e8ge",
    "sg:tags":[
        "purification"
    ],
    "wof:name":"Epuration Des Eaux",
    "wof:placetype":"venue"
},
  "geometry": {"coordinates":[5.5690999031,50.635723114],"type":"Point"}
}