{
  "type": "Feature",
  "properties": {
    "iso:country":"BE",
    "sg:address":"Route De Bruxelles 27",
    "sg:city":"Rebecq",
    "sg:orig_category":"Benzinestations and brandstoffen Herstellingen and onderhoud van auto's Voertuigen",
    "sg:phone":"+32 67 63 62 17",
    "sg:postcode":"1430",
    "sg:province":"Brabant Wallon",
    "wof:name":"Garage Descamps J. & Fils",
    "wof:placetype":"venue"
},
  "geometry": {"coordinates":[4.1596632004,50.6494483948],"type":"Point"}
}