{
  "type": "Feature",
  "properties": {
    "iso:country":"BE",
    "sg:address":"Ruiseleedsesteenweg 67",
    "sg:city":"Tielt",
    "sg:classifiers":[
        {
            "category":"Retail",
            "subcategory":"Animal Services",
            "type":"Services"
        }
    ],
    "sg:phone":"+32 51 40 60 46",
    "sg:postcode":"8700",
    "sg:province":"West-Vlaanderen",
    "sg:tags":[
        "breeding",
        "selling",
        "-",
        "dog"
    ],
    "wof:name":"Kennel De Prayhoeve",
    "wof:placetype":"venue"
},
  "geometry": {"coordinates":[3.3656508923,51.0143699646],"type":"Point"}
}