{
  "type": "Feature",
  "properties": {
    "iso:country":"BE",
    "sg:address":"Kloosterstraat 48",
    "sg:city":"Antwerpen",
    "sg:orig_category":"Antiek Tweedehandsgoederen",
    "sg:phone":"+32 3 237 94 66",
    "sg:postcode":"2000",
    "sg:province":"Antwerpen",
    "wof:name":"Erik Tonen",
    "wof:placetype":"venue"
},
  "geometry": {"coordinates":[4.3947911263,51.2160263062],"type":"Point"}
}