{
  "type": "Feature",
  "properties": {
    "iso:country":"BE",
    "sg:address":"Dorpsstraat 45-47",
    "sg:city":"Kalmthout",
    "sg:classifiers":[
        {
            "category":"Retail",
            "subcategory":"Auto Repair",
            "type":"Services"
        }
    ],
    "sg:phone":"+32 3 666 75 35",
    "sg:postcode":"2920",
    "sg:province":"Antwerpen",
    "sg:tags":[
        "automobile-body"
    ],
    "wof:name":"Garage Koen De Kort Nv",
    "wof:placetype":"venue"
},
  "geometry": {"coordinates":[4.4736428261,51.3958930969],"type":"Point"}
}