{
  "type": "Feature",
  "properties": {
    "addr:full":"Avenue De Vis\u00e9 97 Bruxelles (watermael-boitsfort) Bruxelles-Capitale 1170",
    "addr:housenumber":"97",
    "addr:postcode":"1170",
    "addr:street":"Avenue De Vise\u0301",
    "iso:country":"BE",
    "sg:address":"Avenue De Vis\u00e9 97",
    "sg:city":"Bruxelles (watermael-boitsfort)",
    "sg:classifiers":[
        {
            "category":"Professional",
            "subcategory":"Testing Lab",
            "type":"Services"
        }
    ],
    "sg:phone":"+32 2 672 50 10",
    "sg:postcode":"1170",
    "sg:province":"Bruxelles-Capitale",
    "sg:tags":[
        "chemist"
    ],
    "wof:name":"Alaerts B",
    "wof:placetype":"venue"
},
  "geometry": {"coordinates":[4.3938159943,50.8116874695],"type":"Point"}
}