{
  "type": "Feature",
  "properties": {
    "addr:full":"Sint-jorispoort 37 Antwerpen Antwerpen 2000",
    "addr:housenumber":"37",
    "addr:postcode":"2000",
    "addr:street":"Sint-Jorispoort",
    "iso:country":"BE",
    "sg:address":"Sint-jorispoort 37",
    "sg:city":"Antwerpen",
    "sg:classifiers":[
        {
            "category":"Professional",
            "subcategory":"Art Services",
            "type":"Services"
        }
    ],
    "sg:phone":"+32 498 26 48 33",
    "sg:postcode":"2000",
    "sg:province":"Antwerpen",
    "sg:tags":[
        "interior",
        "designer"
    ],
    "wof:name":"Maes G",
    "wof:placetype":"venue"
},
  "geometry": {"coordinates":[4.4070239067,51.2125473022],"type":"Point"}
}