{
  "type": "Feature",
  "properties": {
    "addr:full":"Stationsstraat 13 Sint-truiden (groot) Limburg 3800",
    "addr:housenumber":"13",
    "addr:postcode":"3800",
    "addr:street":"Stationsstraat;Groot Limburg",
    "iso:country":"BE",
    "sg:address":"Stationsstraat 13",
    "sg:city":"Sint-truiden (groot)",
    "sg:orig_category":"Sociale secretariaten Verplichte sociale verzekeringen",
    "sg:phone":"+32 11 68 84 17",
    "sg:postcode":"3800",
    "sg:province":"Limburg",
    "wof:name":"Partena",
    "wof:placetype":"venue"
},
  "geometry": {"coordinates":[5.1796240807,50.8160743713],"type":"Point"}
}