{
  "type": "Feature",
  "properties": {
    "addr:full":"Avenue De La Coop\u00c9ration 14 Soumagne Li\u00e8ge 4630",
    "addr:housenumber":"14",
    "addr:postcode":"4630",
    "addr:street":"Avenue De La Coope\u0301Ration",
    "iso:country":"BE",
    "sg:address":"Avenue De La Coop\u00c9ration 14",
    "sg:city":"Soumagne",
    "sg:classifiers":[
        {
            "category":"Insurance",
            "subcategory":"Life Insurance",
            "type":"Services"
        }
    ],
    "sg:phone":"+32 4 377 91 11",
    "sg:postcode":"4630",
    "sg:province":"Li\u00e8ge",
    "sg:tags":[
        "assurance"
    ],
    "wof:name":"P&v",
    "wof:placetype":"venue"
},
  "geometry": {"coordinates":[5.7472958565,50.6121063232],"type":"Point"}
}