{
  "type": "Feature",
  "properties": {
    "iso:country":"BE",
    "sg:address":"Rue Jean Jaur\u00e8s 17",
    "sg:city":"Gr\u00e2ce-hollogne (gr\u00e2ce-berleur)",
    "sg:classifiers":[
        {
            "category":"Bars & Pubs",
            "type":"Food & Drink"
        }
    ],
    "sg:phone":"+32 4 246 01 73",
    "sg:postcode":"4460",
    "sg:province":"Li\u00e8ge",
    "wof:name":"Boule Rouge (la)",
    "wof:placetype":"venue"
},
  "geometry": {"coordinates":[5.5050530434,50.643951416],"type":"Point"}
}