{
  "type": "Feature",
  "properties": {
    "iso:country":"BE",
    "sg:address":"Streepstraat 13b2",
    "sg:city":"Herentals",
    "sg:orig_category":"Peinture. Rev\u00eatements pour sols and murs",
    "sg:phone":"+32 14 26 35 61",
    "sg:postcode":"2200",
    "sg:province":"Antwerpen",
    "wof:name":"Rafa\u00cbl Roodhooft",
    "wof:placetype":"venue"
},
  "geometry": {"coordinates":[4.8247947693,51.1209259033],"type":"Point"}
}