{
  "type": "Feature",
  "properties": {
    "addr:full":"Avenue Albert Drossart 4 Orp-jauche Brabant Wallon 1350",
    "addr:housenumber":"4",
    "addr:postcode":"1350",
    "addr:street":"Avenue Albert Drossart",
    "iso:country":"BE",
    "sg:address":"Avenue Albert Drossart 4",
    "sg:city":"Orp-jauche",
    "sg:classifiers":[
        {
            "category":"Restaurant",
            "type":"Food & Drink"
        }
    ],
    "sg:phone":"+32 19 63 36 27",
    "sg:postcode":"1350",
    "sg:province":"Brabant Wallon",
    "sg:tags":[
        "caf\u00e9s"
    ],
    "wof:name":"Taverne La Canardi\u00c8re",
    "wof:placetype":"venue"
},
  "geometry": {"coordinates":[4.97920084,50.6738891602],"type":"Point"}
}