{
  "type": "Feature",
  "properties": {
    "iso:country":"BE",
    "sg:address":"Rue De La Lib\u00e9ration 20",
    "sg:city":"Rochefort",
    "sg:orig_category":"Autombile concessionaires",
    "sg:phone":"+32 84 22 16 80",
    "sg:postcode":"5580",
    "sg:province":"Namur",
    "wof:name":"Gar Jacquemin-dubois Sprl",
    "wof:placetype":"venue"
},
  "geometry": {"coordinates":[5.2174072266,50.1630592346],"type":"Point"}
}