{
  "type": "Feature",
  "properties": {
    "addr:full":"Grote Steenweg 50 Geel Antwerpen 2440",
    "addr:housenumber":"50",
    "addr:postcode":"2440",
    "addr:street":"Grote Steenweg",
    "iso:country":"BE",
    "sg:address":"Grote Steenweg 50",
    "sg:city":"Geel",
    "sg:classifiers":[
        {
            "category":"Shopping",
            "subcategory":"Stationery & Office Supplies",
            "type":"Retail Goods"
        }
    ],
    "sg:phone":"+32 14 54 59 91",
    "sg:postcode":"2440",
    "sg:province":"Antwerpen",
    "sg:tags":[
        "partition"
    ],
    "wof:name":"Beva",
    "wof:placetype":"venue"
},
  "geometry": {"coordinates":[4.9446201324,51.0975112915],"type":"Point"}
}