{
  "type": "Feature",
  "properties": {
    "addr:full":"Lange Kroonstraat 1 Boechout Antwerpen 2530",
    "addr:housenumber":"1",
    "addr:postcode":"2530",
    "addr:street":"Lange Kroonstraat",
    "iso:country":"BE",
    "sg:address":"Lange Kroonstraat 1",
    "sg:city":"Boechout",
    "sg:orig_category":"Enseignement maternel and primaire",
    "sg:phone":"+32 3 455 67 05",
    "sg:postcode":"2530",
    "sg:province":"Antwerpen",
    "wof:name":"Vrije Basisschool",
    "wof:placetype":"venue"
},
  "geometry": {"coordinates":[4.4903049469,51.1608200073],"type":"Point"}
}