{
  "type": "Feature",
  "properties": {
    "iso:country":"BE",
    "sg:address":"Nachtegaalweg 33",
    "sg:city":"Koksijde",
    "sg:orig_category":"Architecten",
    "sg:phone":"+32 58 24 07 01",
    "sg:postcode":"8670",
    "sg:province":"West-Vlaanderen",
    "wof:name":"Kathy Decoene",
    "wof:placetype":"venue"
},
  "geometry": {"coordinates":[2.7035579681,51.1400794983],"type":"Point"}
}