{
  "type": "Feature",
  "properties": {
    "iso:country":"BE",
    "sg:address":"Metro Louise 1",
    "sg:city":"Bruxelles",
    "sg:classifiers":[
        {
            "category":"Cafe",
            "type":"Food & Drink"
        }
    ],
    "sg:phone":"+32 2 503 47 43",
    "sg:postcode":"1000",
    "sg:province":"Bruxelles-Capitale",
    "sg:tags":[
        "snack-bars"
    ],
    "wof:name":"Croissanterie-snack Europe",
    "wof:placetype":"venue"
},
  "geometry": {"coordinates":[4.3573999405,50.8332901001],"type":"Point"}
}