{
  "type": "Feature",
  "properties": {
    "addr:full":"Landjuwelenstraat 20 Brugge West-Vlaanderen 8000",
    "addr:housenumber":"20",
    "addr:postcode":"8000",
    "addr:street":"Landjuwelenstraat",
    "iso:country":"BE",
    "sg:address":"Landjuwelenstraat 20",
    "sg:city":"Brugge",
    "sg:classifiers":[
        {
            "category":"Shopping",
            "subcategory":"Discount & Variety Stores",
            "type":"Retail Goods"
        }
    ],
    "sg:phone":"+32 50 34 21 84",
    "sg:postcode":"8000",
    "sg:province":"West-Vlaanderen",
    "sg:tags":[
        "shop",
        "clearers",
        "curiosity",
        "furniture"
    ],
    "wof:name":"Brocante-antiek-bij Jul",
    "wof:placetype":"venue"
},
  "geometry": {"coordinates":[3.2304840088,51.2297286987],"type":"Point"}
}