{
  "type": "Feature",
  "properties": {
    "iso:country":"BE",
    "sg:address":"Diamantlaan 29",
    "sg:city":"Nijlen",
    "sg:orig_category":"Jeux and jouets",
    "sg:phone":"+32 3 481 70 90",
    "sg:postcode":"2560",
    "sg:province":"Antwerpen",
    "wof:name":"Kmc Distrishop",
    "wof:placetype":"venue"
},
  "geometry": {"coordinates":[4.6587958336,51.1630821228],"type":"Point"}
}