{
  "type": "Feature",
  "properties": {
    "addr:full":"Av. O. Van Goidtsnoven 97 Vorst/forest Bruxelles-Capitale 1190",
    "addr:housenumber":"97",
    "addr:postcode":"1190",
    "addr:street":"Av. O. Van Goidtsnoven;/ Forest",
    "iso:country":"BE",
    "sg:address":"Av. O. Van Goidtsnoven 97",
    "sg:city":"Vorst/forest",
    "sg:orig_category":"Avocats and conseillers juridiques",
    "sg:phone":"+32 2 345 90 43",
    "sg:postcode":"1190",
    "sg:province":"Bruxelles-Capitale",
    "wof:name":"J.p. Dumont",
    "wof:placetype":"venue"
},
  "geometry": {"coordinates":[4.3374409676,50.8159675598],"type":"Point"}
}