{
  "type": "Feature",
  "properties": {
    "addr:full":"Rue De Ch\u00c2telet 208 Gerpinnes Hainaut 6280",
    "addr:housenumber":"208",
    "addr:postcode":"6280",
    "addr:street":"Rue De Cha\u0302Telet;Hainaut",
    "iso:country":"BE",
    "sg:address":"Rue De Ch\u00c2telet 208",
    "sg:city":"Gerpinnes",
    "sg:orig_category":"Entretien and r\u00e9parations de machines de bureau and ordinateurs",
    "sg:phone":"+32 71 50 26 63",
    "sg:postcode":"6280",
    "sg:province":"Hainaut",
    "wof:name":"Damien Forret",
    "wof:placetype":"venue"
},
  "geometry": {"coordinates":[4.5509290695,50.3637504578],"type":"Point"}
}