{
  "type": "Feature",
  "properties": {
    "iso:country":"BE",
    "sg:address":"All\u00c9e Ambiorix 13",
    "sg:city":"Chaudfontaine",
    "sg:classifiers":[
        {
            "category":"Arena",
            "subcategory":"Sports Club",
            "type":"Entertainment"
        }
    ],
    "sg:phone":"+32 4 367 40 83",
    "sg:postcode":"4053",
    "sg:province":"Li\u00e8ge",
    "sg:tags":[
        "de"
    ],
    "wof:name":"V.b. Embourg",
    "wof:placetype":"venue"
},
  "geometry": {"coordinates":[5.6063070297,50.5889282227],"type":"Point"}
}