{
  "type": "Feature",
  "properties": {
    "iso:country":"BE",
    "sg:address":"Brugsesteenweg 404",
    "sg:city":"Gent",
    "sg:orig_category":"Installation de menuiserie en bois and plastique",
    "sg:phone":"+32 9 226 16 32",
    "sg:postcode":"9030",
    "sg:province":"Oost-Vlaanderen",
    "wof:name":"Marcel Beyst",
    "wof:placetype":"venue"
},
  "geometry": {"coordinates":[3.6841769218,51.069103241],"type":"Point"}
}