{
  "type": "Feature",
  "properties": {
    "iso:country":"BE",
    "sg:address":"Eindeken 13",
    "sg:city":"Evergem",
    "sg:classifiers":[
        {
            "category":"Personal",
            "subcategory":"Beauty Salon",
            "type":"Services"
        }
    ],
    "sg:phone":"+32 9 253 95 31",
    "sg:postcode":"9940",
    "sg:province":"Oost-Vlaanderen",
    "sg:tags":[
        "de",
        "coiffure"
    ],
    "wof:name":"Kapsalon De Vos",
    "wof:placetype":"venue"
},
  "geometry": {"coordinates":[3.7087299824,51.1082382202],"type":"Point"}
}