{
  "type": "Feature",
  "properties": {
    "addr:full":"Steenweg 158a Alken Limburg 3570",
    "addr:housenumber":"158a",
    "addr:postcode":"3570",
    "addr:street":"Steenweg",
    "iso:country":"BE",
    "sg:address":"Steenweg 158a",
    "sg:city":"Alken",
    "sg:orig_category":"Werk- and beschermkleding Fab",
    "sg:phone":"+32 11 31 47 44",
    "sg:postcode":"3570",
    "sg:province":"Limburg",
    "wof:name":"Helco",
    "wof:placetype":"venue"
},
  "geometry": {"coordinates":[5.2835078239,50.885684967],"type":"Point"}
}