{
  "type": "Feature",
  "properties": {
    "iso:country":"BE",
    "sg:address":"Rue De Fagnolle 4",
    "sg:city":"Philippeville",
    "sg:orig_category":"M\u00e9decins and sp\u00e9cialistes",
    "sg:phone":"+32 60 31 27 22",
    "sg:postcode":"5600",
    "sg:province":"Namur",
    "wof:name":"M. Payfa",
    "wof:placetype":"venue"
},
  "geometry": {"coordinates":[4.5704488754,50.1053886414],"type":"Point"}
}