{
  "type": "Feature",
  "properties": {
    "iso:country":"BE",
    "sg:address":"Kleine Kerkhofstraat 60",
    "sg:city":"Brugge (assebroek)",
    "sg:classifiers":[
        {
            "category":"Building & Trades",
            "subcategory":"Construction",
            "type":"Services"
        }
    ],
    "sg:phone":"+32 50 36 39 75",
    "sg:postcode":"8310",
    "sg:province":"West-Vlaanderen",
    "sg:tags":[
        "installation",
        "-",
        "central",
        "heating"
    ],
    "wof:name":"Aqua Team",
    "wof:placetype":"venue"
},
  "geometry": {"coordinates":[3.2359530926,51.1930923462],"type":"Point"}
}