{
  "type": "Feature",
  "properties": {
    "addr:full":"Droogte 24 Evergem Oost-Vlaanderen 9940",
    "addr:housenumber":"24",
    "addr:postcode":"9940",
    "addr:street":"Droogte;Oost-Vlaanderen",
    "iso:country":"BE",
    "sg:address":"Droogte 24",
    "sg:city":"Evergem",
    "sg:classifiers":[
        {
            "category":"Shopping",
            "subcategory":"Florist",
            "type":"Retail Goods"
        }
    ],
    "sg:phone":"+32 9 253 57 79",
    "sg:postcode":"9940",
    "sg:province":"Oost-Vlaanderen",
    "wof:name":"Florist Michel Cv",
    "wof:placetype":"venue"
},
  "geometry": {"coordinates":[3.714507103,51.1169433594],"type":"Point"}
}