{
  "type": "Feature",
  "properties": {
    "addr:full":"Rue Abb\u00c9-michel-renard 15 Nivelles Brabant Wallon 1400",
    "addr:housenumber":"15",
    "addr:postcode":"1400",
    "addr:street":"Rue Abbe\u0301-Michel-Renard",
    "iso:country":"BE",
    "sg:address":"Rue Abb\u00c9-michel-renard 15",
    "sg:city":"Nivelles",
    "sg:orig_category":"Imprimeries and copyshops. Editeurs de journaux. Editeurs de revues and p\u00e9riodiques",
    "sg:phone":"+32 67 21 61 64",
    "sg:postcode":"1400",
    "sg:province":"Brabant Wallon",
    "wof:name":"Editions Moto 80",
    "wof:placetype":"venue"
},
  "geometry": {"coordinates":[4.3374490738,50.6026878357],"type":"Point"}
}