{
  "type": "Feature",
  "properties": {
    "iso:country":"BE",
    "sg:address":"Rue Wazon 91",
    "sg:city":"Li\u00e8ge 1",
    "sg:classifiers":[
        {
            "category":"Professional",
            "subcategory":"Employment Agencies",
            "type":"Services"
        }
    ],
    "sg:phone":"+32 4 222 30 76",
    "sg:postcode":"4000",
    "sg:province":"Li\u00e8ge",
    "sg:tags":[
        "market",
        "research"
    ],
    "wof:name":"Market Knowledge Sprl",
    "wof:placetype":"venue"
},
  "geometry": {"coordinates":[5.5585608482,50.6398582458],"type":"Point"}
}