{
  "type": "Feature",
  "properties": {
    "addr:full":"Nieuwstraat 1 Hechtel-eksel Limburg 3941",
    "addr:housenumber":"1",
    "addr:postcode":"3941",
    "addr:street":"Nieuwstraat",
    "iso:country":"BE",
    "sg:address":"Nieuwstraat 1",
    "sg:city":"Hechtel-eksel",
    "sg:orig_category":"Journaux. Tabac",
    "sg:phone":"+32 11 73 52 28",
    "sg:postcode":"3941",
    "sg:province":"Limburg",
    "wof:name":"De Gazet",
    "wof:placetype":"venue"
},
  "geometry": {"coordinates":[5.3897681236,51.1511611938],"type":"Point"}
}