{
  "type": "Feature",
  "properties": {
    "addr:full":"Wallemeers 2 Roeselare West-Vlaanderen 8800",
    "addr:housenumber":"2",
    "addr:postcode":"8800",
    "addr:street":"Wallemeers",
    "iso:country":"BE",
    "sg:address":"Wallemeers 2",
    "sg:city":"Roeselare",
    "sg:classifiers":[
        {
            "category":"Real Estate",
            "subcategory":"Architect",
            "type":"Services"
        }
    ],
    "sg:phone":"+32 51 22 88 22",
    "sg:postcode":"8800",
    "sg:province":"West-Vlaanderen",
    "wof:name":"Berkein Architectenburo",
    "wof:placetype":"venue"
},
  "geometry": {"coordinates":[3.1259400845,50.9364738464],"type":"Point"}
}