{
  "type": "Feature",
  "properties": {
    "addr:full":"Turnhoutsebaan 540 Wijnegem Antwerpen 2110",
    "addr:housenumber":"540",
    "addr:postcode":"2110",
    "addr:street":"Turnhoutsebaan",
    "iso:country":"BE",
    "sg:address":"Turnhoutsebaan 540",
    "sg:city":"Wijnegem",
    "sg:orig_category":"Diverse intermediaire producten Gh",
    "sg:phone":"+32 3 353 86 26",
    "sg:postcode":"2110",
    "sg:province":"Antwerpen",
    "wof:name":"Aim\u00c9 Bellen",
    "wof:placetype":"venue"
},
  "geometry": {"coordinates":[4.5388479233,51.2282981873],"type":"Point"}
}