{
  "type": "Feature",
  "properties": {
    "iso:country":"BE",
    "sg:address":"Rue Vieille Haine 12",
    "sg:city":"Mons",
    "sg:orig_category":"Afval and schroot Gh Huisvuilophaling and -verwerking Metaalvrije afvalrecyclage",
    "sg:phone":"+32 65 82 21 46",
    "sg:postcode":"7012",
    "sg:province":"Hainaut",
    "wof:name":"Alfred Alvin & Cie",
    "wof:placetype":"venue"
},
  "geometry": {"coordinates":[3.8894600868,50.4481964111],"type":"Point"}
}