{
  "type": "Feature",
  "properties": {
    "addr:full":"Rue Des Alli\u00e9s 34 Bruxelles (forest) Bruxelles-Capitale 1190",
    "addr:housenumber":"34",
    "addr:postcode":"1190",
    "addr:street":"Rue Des Allie\u0301S",
    "iso:country":"BE",
    "sg:address":"Rue Des Alli\u00e9s 34",
    "sg:city":"Bruxelles (forest)",
    "sg:classifiers":[
        {
            "category":"Home & Garden",
            "subcategory":"Household Appliances",
            "type":"Retail Goods"
        }
    ],
    "sg:phone":"+32 2 343 97 64",
    "sg:postcode":"1190",
    "sg:province":"Bruxelles-Capitale",
    "sg:tags":[
        "thermostat"
    ],
    "wof:name":"Deomatic",
    "wof:placetype":"venue"
},
  "geometry": {"coordinates":[4.3263940811,50.8157501221],"type":"Point"}
}