{
  "type": "Feature",
  "properties": {
    "addr:full":"Acht-meilaan 50 Knokke-heist (heist-aan-zee) West-Vlaanderen 8301",
    "addr:housenumber":"50",
    "addr:postcode":"8301",
    "addr:street":"Acht-Meilaan",
    "iso:country":"BE",
    "sg:address":"Acht-meilaan 50",
    "sg:city":"Knokke-heist (heist-aan-zee)",
    "sg:classifiers":[
        {
            "category":"Professional",
            "subcategory":"Accounting & Tax Preparation",
            "type":"Services"
        }
    ],
    "sg:phone":"+32 50 51 35 72",
    "sg:postcode":"8301",
    "sg:province":"West-Vlaanderen",
    "sg:tags":[
        "bookkeeper"
    ],
    "wof:name":"De Kust Bvba",
    "wof:placetype":"venue"
},
  "geometry": {"coordinates":[3.2639000416,51.3396911621],"type":"Point"}
}