{
  "type": "Feature",
  "properties": {
    "addr:full":"Rue De Rixensart 31 Rixensart Brabant Wallon 1330",
    "addr:housenumber":"31",
    "addr:postcode":"1330",
    "addr:street":"Rue De Rixensart;Wallon",
    "iso:country":"BE",
    "sg:address":"Rue De Rixensart 31",
    "sg:city":"Rixensart",
    "sg:orig_category":"Diverse kredietdiensten",
    "sg:postcode":"1330",
    "sg:province":"Brabant Wallon",
    "wof:name":"Postomat Rixensart",
    "wof:placetype":"venue"
},
  "geometry": {"coordinates":[4.5160498619,50.7219085693],"type":"Point"}
}