{
  "type": "Feature",
  "properties": {
    "addr:full":"Kloosterstraat 4 Heers Limburg 3870",
    "addr:housenumber":"4",
    "addr:postcode":"3870",
    "addr:street":"Kloosterstraat",
    "iso:country":"BE",
    "sg:address":"Kloosterstraat 4",
    "sg:city":"Heers",
    "sg:orig_category":"Enseignement maternel and primaire",
    "sg:phone":"+32 11 48 48 88",
    "sg:postcode":"3870",
    "sg:province":"Limburg",
    "wof:name":"Vrije Basisschool",
    "wof:placetype":"venue"
},
  "geometry": {"coordinates":[5.3017759323,50.752746582],"type":"Point"}
}