{
  "type": "Feature",
  "properties": {
    "iso:country":"BE",
    "sg:address":"190",
    "sg:city":"Beversesteenweg 8800 Roeselare",
    "sg:classifiers":[
        {
            "category":"Bakery",
            "type":"Food & Drink"
        }
    ],
    "sg:phone":"+32 51 24 92 44",
    "sg:postcode":"190",
    "sg:tags":[
        "cake",
        "product",
        "related",
        "bread"
    ],
    "wof:name":"Ignace Bvba",
    "wof:placetype":"venue"
},
  "geometry": {"coordinates":[3.16968894,50.9771080017],"type":"Point"}
}