{
  "type": "Feature",
  "properties": {
    "addr:full":"Rue Des Thuyas 26 Bruxelles (watermael-boitsfort) Bruxelles-Capitale 1170",
    "addr:housenumber":"26",
    "addr:postcode":"1170",
    "addr:street":"Rue Des Thuyas",
    "iso:country":"BE",
    "sg:address":"Rue Des Thuyas 26",
    "sg:city":"Bruxelles (watermael-boitsfort)",
    "sg:classifiers":[
        {
            "category":"Health Services",
            "subcategory":"Doctor",
            "type":"Services"
        }
    ],
    "sg:phone":"+32 2 673 08 01",
    "sg:postcode":"1170",
    "sg:province":"Bruxelles-Capitale",
    "sg:tags":[
        "medicinephysicians",
        "surgeon"
    ],
    "wof:name":"Delatte Ph",
    "wof:placetype":"venue"
},
  "geometry": {"coordinates":[4.404542923,50.8090171814],"type":"Point"}
}