{
  "type": "Feature",
  "properties": {
    "addr:full":"Jules Vanlaerstraat 8 Bertem Vlaams-Brabant 3060",
    "addr:housenumber":"8",
    "addr:postcode":"3060",
    "addr:street":"Vanlaerstraat",
    "iso:country":"BE",
    "sg:address":"Jules Vanlaerstraat 8",
    "sg:city":"Bertem",
    "sg:classifiers":[
        {
            "category":"Social Services",
            "subcategory":"Child Care",
            "type":"Services"
        }
    ],
    "sg:phone":"+32 16 46 49 90",
    "sg:postcode":"3060",
    "sg:province":"Vlaams-Brabant",
    "sg:tags":[
        "baby",
        "nursery",
        "day",
        "sitting"
    ],
    "wof:name":"Inimini",
    "wof:placetype":"venue"
},
  "geometry": {"coordinates":[4.6422100067,50.8689498901],"type":"Point"}
}