{
  "type": "Feature",
  "properties": {
    "addr:full":"Rue Du Monument 9 Pecq Hainaut 7740",
    "addr:housenumber":"9",
    "addr:postcode":"7740",
    "addr:street":"Rue Du Monument",
    "iso:country":"BE",
    "sg:address":"Rue Du Monument 9",
    "sg:city":"Pecq",
    "sg:orig_category":"Traitements param\u00e9dicaux",
    "sg:phone":"+32 69 55 88 14",
    "sg:postcode":"7740",
    "sg:province":"Hainaut",
    "wof:name":"M.c. Staessens",
    "wof:placetype":"venue"
},
  "geometry": {"coordinates":[3.3436429501,50.7030563354],"type":"Point"}
}