{
  "type": "Feature",
  "properties": {
    "addr:full":"Amerikalei 128 Antwerpen Antwerpen 2000",
    "addr:housenumber":"128",
    "addr:postcode":"2000",
    "addr:street":"Amerikalei",
    "iso:country":"BE",
    "sg:address":"Amerikalei 128",
    "sg:city":"Antwerpen",
    "sg:orig_category":"Avocats and conseillers juridiques",
    "sg:phone":"+32 3 237 45 27",
    "sg:postcode":"2000",
    "sg:province":"Antwerpen",
    "wof:name":"C. Verfaillie",
    "wof:placetype":"venue"
},
  "geometry": {"coordinates":[4.394449234,51.2066307068],"type":"Point"}
}