{
  "type": "Feature",
  "properties": {
    "addr:full":"Nieuwstraat 7 De Pinte Oost-Vlaanderen 9840",
    "addr:housenumber":"7",
    "addr:postcode":"9840",
    "addr:street":"Nieuwstraat",
    "iso:country":"BE",
    "sg:address":"Nieuwstraat 7",
    "sg:city":"De Pinte",
    "sg:orig_category":"DIVERSE RECREATIEVE ACTIVITEITEN",
    "sg:phone":"+32 9 282 34 77",
    "sg:postcode":"9840",
    "sg:province":"Oost-Vlaanderen",
    "wof:name":"Bridge Club Athena",
    "wof:placetype":"venue"
},
  "geometry": {"coordinates":[3.6453669071,50.9834938049],"type":"Point"}
}