{
  "type": "Feature",
  "properties": {
    "addr:full":"Dumortierlaan 20 Knokke-heist West-Vlaanderen 8300",
    "addr:housenumber":"20",
    "addr:postcode":"8300",
    "addr:street":"Dumortierlaan",
    "iso:country":"BE",
    "sg:address":"Dumortierlaan 20",
    "sg:city":"Knokke-heist",
    "sg:orig_category":"M\u00e9decins and sp\u00e9cialistes",
    "sg:phone":"+32 50 61 34 34",
    "sg:postcode":"8300",
    "sg:province":"West-Vlaanderen",
    "wof:name":"Sabine Maene",
    "wof:placetype":"venue"
},
  "geometry": {"coordinates":[3.287694931,51.3467254639],"type":"Point"}
}