{
  "type": "Feature",
  "properties": {
    "iso:country":"BE",
    "sg:address":"Rue Bonne Esp\u00c9rance 50",
    "sg:city":"Mettet",
    "sg:orig_category":"Messageries",
    "sg:phone":"+32 71 74 31 89",
    "sg:postcode":"5640",
    "sg:province":"Namur",
    "wof:name":"Trans Dm",
    "wof:placetype":"venue"
},
  "geometry": {"coordinates":[4.6709299088,50.3236083984],"type":"Point"}
}