{
  "type": "Feature",
  "properties": {
    "addr:full":"Motedreef 3 Moorslede West-Vlaanderen 8890",
    "addr:housenumber":"3",
    "addr:postcode":"8890",
    "addr:street":"Motedreef",
    "iso:country":"BE",
    "sg:address":"Motedreef 3",
    "sg:city":"Moorslede",
    "sg:orig_category":"Varkenskwekers",
    "sg:phone":"+32 51 77 84 35",
    "sg:postcode":"8890",
    "sg:province":"West-Vlaanderen",
    "wof:name":"Daniel Deryckere",
    "wof:placetype":"venue"
},
  "geometry": {"coordinates":[3.0947079659,50.8942680359],"type":"Point"}
}