{
  "type": "Feature",
  "properties": {
    "iso:country":"BE",
    "sg:address":"Rue Crocq 37",
    "sg:city":"Bruxelles",
    "sg:orig_category":"Sportclubs",
    "sg:phone":"+32 2 762 75 18",
    "sg:postcode":"1200",
    "sg:province":"Bruxelles-Capitale",
    "wof:name":"Amicale De Volley",
    "wof:placetype":"venue"
},
  "geometry": {"coordinates":[4.4224247932,50.8463516235],"type":"Point"}
}