{
  "type": "Feature",
  "properties": {
    "iso:country":"BE",
    "sg:address":"Rue Fran\u00e7ois Hanon 71",
    "sg:city":"Awans (fooz)",
    "sg:classifiers":[
        {
            "category":"Professional",
            "subcategory":"Computer Services",
            "type":"Services"
        }
    ],
    "sg:phone":"+32 4 250 44 08",
    "sg:postcode":"4340",
    "sg:province":"Li\u00e8ge",
    "sg:tags":[
        "-",
        "processing",
        "data",
        "software"
    ],
    "wof:name":"Devline Sprl",
    "wof:placetype":"venue"
},
  "geometry": {"coordinates":[5.4699959755,50.6692352295],"type":"Point"}
}