{
  "type": "Feature",
  "properties": {
    "iso:country":"BE",
    "sg:address":"Kasteelstraat 53",
    "sg:city":"Temse",
    "sg:orig_category":"Catering and organisatie van feesten Vis and zeevruchten Voedingsspeciaalzaken",
    "sg:phone":"+32 3 711 08 45",
    "sg:postcode":"9140",
    "sg:province":"Oost-Vlaanderen",
    "wof:name":"Traiteur Sails",
    "wof:placetype":"venue"
},
  "geometry": {"coordinates":[4.2172241211,51.1242485046],"type":"Point"}
}