{
  "type": "Feature",
  "properties": {
    "addr:full":"Rue Du Palais 31 Verviers Li\u00e8ge 4800",
    "addr:housenumber":"31",
    "addr:postcode":"4800",
    "addr:street":"Rue Du Palais",
    "iso:country":"BE",
    "sg:address":"Rue Du Palais 31",
    "sg:city":"Verviers",
    "sg:classifiers":[
        {
            "category":"Health Services",
            "subcategory":"Health Practitioner",
            "type":"Services"
        }
    ],
    "sg:phone":"+32 87 22 40 53",
    "sg:postcode":"4800",
    "sg:province":"Li\u00e8ge",
    "sg:tags":[
        "therapist",
        "speech"
    ],
    "wof:name":"Centre Du Langage",
    "wof:placetype":"venue"
},
  "geometry": {"coordinates":[5.8635540009,50.590259552],"type":"Point"}
}