{
  "type": "Feature",
  "properties": {
    "addr:full":"Dijkstraat 64 Mechelen Antwerpen 2800",
    "addr:housenumber":"64",
    "addr:postcode":"2800",
    "addr:street":"Dijkstraat",
    "iso:country":"BE",
    "sg:address":"Dijkstraat 64",
    "sg:city":"Mechelen",
    "sg:orig_category":"Pain, p\u00e2tisseries and confiseries",
    "sg:phone":"+32 15 41 49 97",
    "sg:postcode":"2800",
    "sg:province":"Antwerpen",
    "wof:name":"Berlindis Beterams",
    "wof:placetype":"venue"
},
  "geometry": {"coordinates":[4.4749507904,51.0165634155],"type":"Point"}
}