{
  "type": "Feature",
  "properties": {
    "addr:full":"Boulevard Baudouin Ier 4 Ottignies-louvain-la-neuve Brabant Wallon 1348",
    "addr:housenumber":"4",
    "addr:postcode":"1348",
    "addr:street":"Boulevard Baudouin Ier",
    "iso:country":"BE",
    "sg:address":"Boulevard Baudouin Ier 4",
    "sg:city":"Ottignies-louvain-la-neuve",
    "sg:orig_category":"Installation \u00e9lectrique r\u00e9sidentielle",
    "sg:phone":"+32 10 45 22 71",
    "sg:postcode":"1348",
    "sg:province":"Brabant Wallon",
    "wof:name":"Roland Storder",
    "wof:placetype":"venue"
},
  "geometry": {"coordinates":[4.567553997,50.6661262512],"type":"Point"}
}