{
  "type": "Feature",
  "properties": {
    "iso:country":"BE",
    "sg:address":"Avenue Louise 413",
    "sg:city":"Bruxelles",
    "sg:orig_category":"Huishoudapparaten, televisies and radio's",
    "sg:phone":"+32 2 644 68 28",
    "sg:postcode":"1050",
    "sg:province":"Bruxelles-Capitale",
    "wof:name":"Planet Audio",
    "wof:placetype":"venue"
},
  "geometry": {"coordinates":[4.370639801,50.8191146851],"type":"Point"}
}