{
  "type": "Feature",
  "properties": {
    "iso:country":"BE",
    "sg:address":"Paalstraat 122",
    "sg:city":"Schoten",
    "sg:classifiers":[
        {
            "category":"Professional",
            "subcategory":"Testing Lab",
            "type":"Services"
        }
    ],
    "sg:phone":"+32 3 658 66 12",
    "sg:postcode":"2900",
    "sg:province":"Antwerpen",
    "sg:tags":[
        "chemist"
    ],
    "wof:name":"Tessens L",
    "wof:placetype":"venue"
},
  "geometry": {"coordinates":[4.5029010773,51.2536010742],"type":"Point"}
}