{
  "type": "Feature",
  "properties": {
    "addr:full":"Avenue Reine Astrid 15b2 La Hulpe Brabant Wallon 1310",
    "addr:housenumber":"15b2",
    "addr:postcode":"1310",
    "addr:street":"Avenue Reine Astrid",
    "iso:country":"BE",
    "sg:address":"Avenue Reine Astrid 15b2",
    "sg:city":"La Hulpe",
    "sg:orig_category":"Artsen and specialisten",
    "sg:phone":"+32 2 653 11 92",
    "sg:postcode":"1310",
    "sg:province":"Brabant Wallon",
    "wof:name":"Fortun\u00c9e Cohen",
    "wof:placetype":"venue"
},
  "geometry": {"coordinates":[4.4810791016,50.7300338745],"type":"Point"}
}