{
  "type": "Feature",
  "properties": {
    "addr:full":"Rue De La Gare 59 Bertrix Luxembourg 6800",
    "addr:housenumber":"59",
    "addr:postcode":"6800",
    "addr:street":"Rue De La Gare",
    "iso:country":"BE",
    "sg:address":"Rue De La Gare 59",
    "sg:city":"Bertrix",
    "sg:classifiers":[
        {
            "category":"Banks & Credit Unions",
            "subcategory":"Bank",
            "type":"Services"
        }
    ],
    "sg:phone":"+32 61 41 18 91",
    "sg:postcode":"6800",
    "sg:province":"Luxembourg",
    "wof:name":"Aslk-cger Bank",
    "wof:placetype":"venue"
},
  "geometry": {"coordinates":[5.3761348724,49.9199943542],"type":"Point"}
}