{
  "type": "Feature",
  "properties": {
    "addr:full":"Mechelsesteenweg 30 Kampenhout Vlaams-Brabant 1910",
    "addr:housenumber":"30",
    "addr:postcode":"1910",
    "addr:street":"Mechelsesteenweg",
    "iso:country":"BE",
    "sg:address":"Mechelsesteenweg 30",
    "sg:city":"Kampenhout",
    "sg:orig_category":"Diepvriesproducten Gh",
    "sg:phone":"+32 16 61 96 96",
    "sg:postcode":"1910",
    "sg:province":"Vlaams-Brabant",
    "wof:name":"Covee",
    "wof:placetype":"venue"
},
  "geometry": {"coordinates":[4.588283062,50.9589996338],"type":"Point"}
}