{
  "type": "Feature",
  "properties": {
    "addr:full":"Rue De Qui\u00e9vrain 110 Boussu Hainaut 7300",
    "addr:housenumber":"110",
    "addr:postcode":"7300",
    "addr:street":"Rue De Quie\u0301Vrain",
    "iso:country":"BE",
    "sg:address":"Rue De Qui\u00e9vrain 110",
    "sg:city":"Boussu",
    "sg:classifiers":[
        {
            "category":"Health Services",
            "subcategory":"Nursing And Care Facility",
            "type":"Services"
        }
    ],
    "sg:postcode":"7300",
    "sg:province":"Hainaut",
    "sg:tags":[
        "home"
    ],
    "wof:name":"Coulon Gilberte",
    "wof:placetype":"venue"
},
  "geometry": {"coordinates":[3.7833809853,50.4275283813],"type":"Point"}
}