{
  "type": "Feature",
  "properties": {
    "iso:country":"BE",
    "sg:address":"Rue Des Arondes 21",
    "sg:city":"Courcelles",
    "sg:orig_category":"Epiceries",
    "sg:phone":"+32 71 45 72 19",
    "sg:postcode":"6180",
    "sg:province":"Hainaut",
    "wof:name":"Bernard Esmanne",
    "wof:placetype":"venue"
},
  "geometry": {"coordinates":[4.3887381554,50.4570960999],"type":"Point"}
}