{
  "type": "Feature",
  "properties": {
    "iso:country":"BE",
    "sg:address":"Coupure 526",
    "sg:city":"Gent",
    "sg:classifiers":[
        {
            "category":"Health Services",
            "subcategory":"Health Practitioner",
            "type":"Services"
        }
    ],
    "sg:phone":"+32 9 223 33 27",
    "sg:postcode":"9000",
    "sg:province":"Oost-Vlaanderen",
    "sg:tags":[
        "psychologist"
    ],
    "wof:name":"Vande Casteele L",
    "wof:placetype":"venue"
},
  "geometry": {"coordinates":[3.7098228931,51.054397583],"type":"Point"}
}