{
  "type": "Feature",
  "properties": {
    "iso:country":"BE",
    "sg:address":"Voorhoventerweg 36",
    "sg:city":"Maaseik (grand)",
    "sg:orig_category":"D\u00e9molition d\u00b4immeubles and terrassements. Collecte and \u00e9puration des eaux us\u00e9es",
    "sg:phone":"+32 89 86 57 08",
    "sg:postcode":"3680",
    "sg:province":"Limburg",
    "wof:name":"Algrozo",
    "wof:placetype":"venue"
},
  "geometry": {"coordinates":[5.791285038,51.0954208374],"type":"Point"}
}