{
  "type": "Feature",
  "properties": {
    "iso:country":"BE",
    "sg:address":"Rue Du Mont 30",
    "sg:city":"Anh\u00e9e (bioul)",
    "sg:classifiers":[
        {
            "category":"Arts & Performance",
            "subcategory":"Theater",
            "type":"Entertainment"
        }
    ],
    "sg:phone":"+32 71 79 89 07",
    "sg:postcode":"5537",
    "sg:province":"Namur",
    "sg:tags":[
        "theatrical",
        "agency"
    ],
    "wof:name":"Caravane Production",
    "wof:placetype":"venue"
},
  "geometry": {"coordinates":[4.7976732254,50.3291435242],"type":"Point"}
}