{
  "type": "Feature",
  "properties": {
    "iso:country":"BE",
    "sg:address":"Rue De La Fagne 34",
    "sg:city":"Assesse",
    "sg:classifiers":[
        {
            "category":"Home & Garden",
            "subcategory":"Home Furnishings",
            "type":"Retail Goods"
        }
    ],
    "sg:phone":"+32 83 65 52 15",
    "sg:postcode":"5330",
    "sg:province":"Namur",
    "sg:tags":[
        "interior",
        "decoration"
    ],
    "wof:name":"Melvil Decoration",
    "wof:placetype":"venue"
},
  "geometry": {"coordinates":[5.0410680771,50.368473053],"type":"Point"}
}