{
  "type": "Feature",
  "properties": {
    "addr:full":"Parmastraat 41 Beveren (melsele) Oost-Vlaanderen 9120",
    "addr:housenumber":"41",
    "addr:postcode":"9120",
    "addr:street":"Parmastraat",
    "iso:country":"BE",
    "sg:address":"Parmastraat 41",
    "sg:city":"Beveren (melsele)",
    "sg:classifiers":[
        {
            "category":"Professional",
            "subcategory":"Art Services",
            "type":"Services"
        }
    ],
    "sg:phone":"+32 476 98 47 90",
    "sg:postcode":"9120",
    "sg:province":"Oost-Vlaanderen",
    "sg:tags":[
        "designer",
        "display"
    ],
    "wof:name":"De Munck V",
    "wof:placetype":"venue"
},
  "geometry": {"coordinates":[4.2984189987,51.2086143494],"type":"Point"}
}