{
  "type": "Feature",
  "properties": {
    "addr:full":"Galerij De Ware Vrienden Hasselt Limburg 3500",
    "addr:postcode":"3500",
    "addr:street":"Galerij",
    "iso:country":"BE",
    "sg:address":"Galerij De Ware Vrienden",
    "sg:city":"Hasselt",
    "sg:classifiers":[
        {
            "category":"Shopping",
            "subcategory":"Optician",
            "type":"Retail Goods"
        }
    ],
    "sg:phone":"+32 11 22 11 90",
    "sg:postcode":"3500",
    "sg:province":"Limburg",
    "sg:tags":[
        "-"
    ],
    "wof:name":"Bruninx",
    "wof:placetype":"venue"
},
  "geometry": {"coordinates":[5.3359251022,50.9270362854],"type":"Point"}
}