{
  "type": "Feature",
  "properties": {
    "iso:country":"BE",
    "sg:address":"Mortelputstraat 27",
    "sg:city":"Sint-martens-latem",
    "sg:orig_category":"Herstellingen and onderhoud van auto's",
    "sg:phone":"+32 9 282 51 39",
    "sg:postcode":"9830",
    "sg:province":"Oost-Vlaanderen",
    "wof:name":"Garage Poppe",
    "wof:placetype":"venue"
},
  "geometry": {"coordinates":[3.6449050903,51.0209274292],"type":"Point"}
}