{
  "type": "Feature",
  "properties": {
    "addr:full":"Rue Saint-jacques 14 Dinant Namur 5500",
    "addr:housenumber":"14",
    "addr:postcode":"5500",
    "addr:street":"Rue Saint-Jacques",
    "iso:country":"BE",
    "sg:address":"Rue Saint-jacques 14",
    "sg:city":"Dinant",
    "sg:orig_category":"Chaussures",
    "sg:phone":"+32 82 22 65 18",
    "sg:postcode":"5500",
    "sg:province":"Namur",
    "wof:name":"Brantano",
    "wof:placetype":"venue"
},
  "geometry": {"coordinates":[4.911441803,50.2630157471],"type":"Point"}
}