{
  "type": "Feature",
  "properties": {
    "iso:country":"BE",
    "sg:address":"Industrieweg 1086",
    "sg:city":"Herk-de-stad",
    "sg:classifiers":[
        {
            "category":"Manufacturing",
            "subcategory":"Tools & Machinery",
            "type":"Manufacturing & Wholesale Goods"
        }
    ],
    "sg:phone":"+32 13 31 57 36",
    "sg:postcode":"3540",
    "sg:province":"Limburg",
    "sg:tags":[
        "builder"
    ],
    "wof:name":"Labor Aiding Systems Europe Nv",
    "wof:placetype":"venue"
},
  "geometry": {"coordinates":[5.1713671684,50.9452209473],"type":"Point"}
}