{
  "type": "Feature",
  "properties": {
    "iso:country":"BE",
    "sg:address":"Blakmeers 103",
    "sg:city":"Affligem",
    "sg:orig_category":"Erotische Etablissementen",
    "sg:phone":"+32 53 66 03 03",
    "sg:postcode":"1790",
    "sg:province":"Vlaams-Brabant",
    "wof:name":"Happy-week-end",
    "wof:placetype":"venue"
},
  "geometry": {"coordinates":[4.1194081306,50.9041290283],"type":"Point"}
}