{
  "type": "Feature",
  "properties": {
    "addr:full":"Rue L\u00c9opold 71 Dison Li\u00e8ge 4820",
    "addr:housenumber":"71",
    "addr:postcode":"4820",
    "addr:street":"Rue Le\u0301Opold",
    "iso:country":"BE",
    "sg:address":"Rue L\u00c9opold 71",
    "sg:city":"Dison",
    "sg:classifiers":[
        {
            "category":"Personal",
            "subcategory":"Beauty Salon",
            "type":"Services"
        }
    ],
    "sg:phone":"+32 87 33 56 03",
    "sg:postcode":"4820",
    "sg:province":"Li\u00e8ge",
    "sg:tags":[
        "de",
        "coiffure"
    ],
    "wof:name":"Coiff. Danielle Et Marcel",
    "wof:placetype":"venue"
},
  "geometry": {"coordinates":[5.8508491516,50.6107063293],"type":"Point"}
}