{
  "type": "Feature",
  "properties": {
    "addr:full":"Eug\u00c8ne Keymplein 58b12 Watermaal-bosvoorde/watermael-boitsfort Bruxelles-Capitale 1170",
    "addr:housenumber":"58b12",
    "addr:postcode":"1170",
    "addr:street":"Euge\u0300Ne Keymplein",
    "iso:country":"BE",
    "sg:address":"Eug\u00c8ne Keymplein 58b12",
    "sg:city":"Watermaal-bosvoorde/watermael-boitsfort",
    "sg:orig_category":"Brood, gebak and snoepgoed Restaurants",
    "sg:phone":"+32 2 660 43 88",
    "sg:postcode":"1170",
    "sg:province":"Bruxelles-Capitale",
    "wof:name":"La Brioche",
    "wof:placetype":"venue"
},
  "geometry": {"coordinates":[4.403181076,50.8091392517],"type":"Point"}
}