{
  "type": "Feature",
  "properties": {
    "iso:country":"BE",
    "sg:address":"Rue Neuve 36",
    "sg:city":"Herve",
    "sg:classifiers":[
        {
            "category":"Shopping",
            "subcategory":"Shoes",
            "type":"Retail Goods"
        }
    ],
    "sg:phone":"+32 87 67 84 36",
    "sg:postcode":"4650",
    "sg:province":"Li\u00e8ge",
    "sg:tags":[
        "slipper",
        "-"
    ],
    "wof:name":"Malo\u00efc",
    "wof:placetype":"venue"
},
  "geometry": {"coordinates":[5.7913379669,50.6387863159],"type":"Point"}
}