{
  "type": "Feature",
  "properties": {
    "iso:country":"BE",
    "sg:address":"Poelstraat 100a",
    "sg:city":"Merelbeke",
    "sg:classifiers":[
        {
            "category":"Home & Garden",
            "subcategory":"Building Materials",
            "type":"Retail Goods"
        }
    ],
    "sg:phone":"+32 9 231 08 23",
    "sg:postcode":"9820",
    "sg:province":"Oost-Vlaanderen",
    "sg:tags":[
        "aluminium",
        "construction",
        "-"
    ],
    "wof:name":"De Keyser Bvba",
    "wof:placetype":"venue"
},
  "geometry": {"coordinates":[3.752024889,50.9865608215],"type":"Point"}
}