{
  "type": "Feature",
  "properties": {
    "iso:country":"BE",
    "sg:address":"Grand'rue 157",
    "sg:city":"Charleroi",
    "sg:orig_category":"Artsen and specialisten",
    "sg:phone":"+32 71 42 07 25",
    "sg:postcode":"6000",
    "sg:province":"Hainaut",
    "wof:name":"Ph. Paquay",
    "wof:placetype":"venue"
},
  "geometry": {"coordinates":[4.4527988434,50.4181480408],"type":"Point"}
}