{
  "type": "Feature",
  "properties": {
    "iso:country":"BE",
    "sg:address":"Nachtegaallaan 62",
    "sg:city":"Asse",
    "sg:classifiers":[
        {
            "category":"Arena",
            "subcategory":"Sports Club",
            "type":"Entertainment"
        }
    ],
    "sg:phone":"+32 2 463 03 15",
    "sg:postcode":"1731",
    "sg:province":"Vlaams-Brabant",
    "sg:tags":[
        "de"
    ],
    "wof:name":"T.r.c. Groot-bijgaarden",
    "wof:placetype":"venue"
},
  "geometry": {"coordinates":[4.2796998024,50.8843612671],"type":"Point"}
}