{
  "type": "Feature",
  "properties": {
    "addr:full":"Europalaan 60 Tielt West-Vlaanderen 8700",
    "addr:housenumber":"60",
    "addr:postcode":"8700",
    "addr:street":"Europalaan",
    "iso:country":"BE",
    "sg:address":"Europalaan 60",
    "sg:city":"Tielt",
    "sg:classifiers":[
        {
            "category":"Cafe",
            "type":"Food & Drink"
        }
    ],
    "sg:phone":"+32 51 40 71 59",
    "sg:postcode":"8700",
    "sg:province":"West-Vlaanderen",
    "sg:tags":[
        "caf\u00e9s"
    ],
    "wof:name":"Yolande Lefebre",
    "wof:placetype":"venue"
},
  "geometry": {"coordinates":[3.3343200684,50.9989089966],"type":"Point"}
}