{
  "type": "Feature",
  "properties": {
    "addr:full":"Sparrebosstraat 1 Hoeilaart Vlaams-Brabant 1560",
    "addr:housenumber":"1",
    "addr:postcode":"1560",
    "addr:street":"Sparrebosstraat",
    "iso:country":"BE",
    "sg:address":"Sparrebosstraat 1",
    "sg:city":"Hoeilaart",
    "sg:orig_category":"Pain, p\u00e2tisseries and confiseries",
    "sg:phone":"+32 2 657 10 64",
    "sg:postcode":"1560",
    "sg:province":"Vlaams-Brabant",
    "wof:name":"Fa. Vandervaeren",
    "wof:placetype":"venue"
},
  "geometry": {"coordinates":[4.4598731995,50.7730903625],"type":"Point"}
}