{
  "type": "Feature",
  "properties": {
    "addr:full":"Route De Mesch 5bd Voeren/fourons Limburg 3798",
    "addr:housenumber":"5bd",
    "addr:postcode":"3798",
    "addr:street":"Route De Mesch",
    "iso:country":"BE",
    "sg:address":"Route De Mesch 5bd",
    "sg:city":"Voeren/fourons",
    "sg:classifiers":[
        {
            "category":"Arena",
            "subcategory":"Sports Club",
            "type":"Entertainment"
        }
    ],
    "sg:phone":"+32 4 381 06 78",
    "sg:postcode":"3798",
    "sg:province":"Limburg",
    "sg:tags":[
        "de"
    ],
    "wof:name":"Berg- En Boswandeling",
    "wof:placetype":"venue"
},
  "geometry": {"coordinates":[5.7698001862,50.761089325],"type":"Point"}
}