{
  "type": "Feature",
  "properties": {
    "addr:full":"Goteringenstraat 43 Gooik (kester) Vlaams-Brabant 1755",
    "addr:housenumber":"43;1755",
    "addr:street":"Goteringenstraat",
    "iso:country":"BE",
    "sg:address":"Goteringenstraat 43",
    "sg:city":"Gooik (kester)",
    "sg:classifiers":[
        {
            "category":"Banks & Credit Unions",
            "subcategory":"Investment Brokerage",
            "type":"Services"
        }
    ],
    "sg:phone":"+32 54 56 82 34",
    "sg:postcode":"1755",
    "sg:province":"Vlaams-Brabant",
    "sg:tags":[
        "aid",
        "rehabiliation",
        "apparatus"
    ],
    "wof:name":"Berchmans L",
    "wof:placetype":"venue"
},
  "geometry": {"coordinates":[4.0872311592,50.7636184692],"type":"Point"}
}