{
  "type": "Feature",
  "properties": {
    "addr:full":"Rumoldusstraat 62 Dilbeek Vlaams-Brabant 1703",
    "addr:housenumber":"62",
    "addr:postcode":"1703",
    "addr:street":"Rumoldusstraat",
    "iso:country":"BE",
    "sg:address":"Rumoldusstraat 62",
    "sg:city":"Dilbeek",
    "sg:orig_category":"Kapsalons",
    "sg:phone":"+32 2 569 79 00",
    "sg:postcode":"1703",
    "sg:province":"Vlaams-Brabant",
    "wof:name":"Coiffure Ingrid",
    "wof:placetype":"venue"
},
  "geometry": {"coordinates":[4.1972007751,50.8401145935],"type":"Point"}
}