{
  "type": "Feature",
  "properties": {
    "iso:country":"BE",
    "sg:address":"En Faurieux 72",
    "sg:city":"Herstal",
    "sg:orig_category":"Entretien and r\u00e9parations de voitures",
    "sg:phone":"+32 4 248 18 41",
    "sg:postcode":"4040",
    "sg:province":"Li\u00e8ge",
    "wof:name":"Garage Stepcar",
    "wof:placetype":"venue"
},
  "geometry": {"coordinates":[5.6269497871,50.6658287048],"type":"Point"}
}