{
  "type": "Feature",
  "properties": {
    "iso:country":"BE",
    "sg:address":"Achel Statie 91",
    "sg:city":"Hamont-achel",
    "sg:classifiers":[
        {
            "category":"Banks & Credit Unions",
            "subcategory":"Investment Brokerage",
            "type":"Services"
        }
    ],
    "sg:phone":"+32 11 80 27 98",
    "sg:postcode":"3930",
    "sg:province":"Limburg",
    "sg:tags":[
        "shutter",
        "roller"
    ],
    "wof:name":"Rubo - Rol B.v.b.a.",
    "wof:placetype":"venue"
},
  "geometry": {"coordinates":[5.4693341255,51.2734642029],"type":"Point"}
}