{
  "type": "Feature",
  "properties": {
    "addr:full":"Sint-denijslaan 335 Gent Oost-Vlaanderen 9000",
    "addr:housenumber":"335",
    "addr:postcode":"9000",
    "addr:street":"Oost-Vlaanderen",
    "iso:country":"BE",
    "sg:address":"Sint-denijslaan 335",
    "sg:city":"Gent",
    "sg:orig_category":"Alternatieve geneeskunde",
    "sg:phone":"+32 9 245 15 00",
    "sg:postcode":"9000",
    "sg:province":"Oost-Vlaanderen",
    "wof:name":"D. Verstraete",
    "wof:placetype":"venue"
},
  "geometry": {"coordinates":[3.6996030807,51.0364990234],"type":"Point"}
}