{
  "type": "Feature",
  "properties": {
    "iso:country":"BE",
    "sg:address":"Rue De Treignes 23",
    "sg:city":"Viroinval (maz\u00e9e)",
    "sg:classifiers":[
        {
            "category":"Farming",
            "subcategory":"Livestock Farm",
            "type":"Manufacturing & Wholesale Goods"
        }
    ],
    "sg:phone":"+32 60 39 92 22",
    "sg:postcode":"5670",
    "sg:province":"Namur",
    "sg:tags":[
        "breeding"
    ],
    "wof:name":"Plasschaert J-m",
    "wof:placetype":"venue"
},
  "geometry": {"coordinates":[4.6875247955,50.0988388062],"type":"Point"}
}