{
  "type": "Feature",
  "properties": {
    "addr:full":"Rue Royale Sainte-marie 84 Schaarbeek/schaerbeek Bruxelles-Capitale 1030",
    "addr:housenumber":"84",
    "addr:postcode":"1030",
    "addr:street":"Rue Royale Sainte-Marie",
    "iso:country":"BE",
    "sg:address":"Rue Royale Sainte-marie 84",
    "sg:city":"Schaarbeek/schaerbeek",
    "sg:orig_category":"Agences de presse",
    "sg:phone":"+32 2 242 60 20",
    "sg:postcode":"1030",
    "sg:province":"Bruxelles-Capitale",
    "wof:name":"Solange Villes",
    "wof:placetype":"venue"
},
  "geometry": {"coordinates":[4.3708610535,50.8623580933],"type":"Point"}
}