{
  "type": "Feature",
  "properties": {
    "iso:country":"BE",
    "sg:address":"Jules Lowetlaan 17",
    "sg:city":"Hoegaarden",
    "sg:classifiers":[
        {
            "category":"Home & Garden",
            "subcategory":"Garden Supply",
            "type":"Retail Goods"
        }
    ],
    "sg:phone":"+32 16 76 51 83",
    "sg:postcode":"3320",
    "sg:province":"Vlaams-Brabant",
    "sg:tags":[
        "lawn",
        "mower"
    ],
    "wof:name":"Lenaerts H",
    "wof:placetype":"venue"
},
  "geometry": {"coordinates":[4.9063892365,50.7727622986],"type":"Point"}
}