{
  "type": "Feature",
  "properties": {
    "iso:country":"BE",
    "sg:address":"Kesselsesteenweg 112",
    "sg:city":"Lier",
    "sg:orig_category":"D\u00e9taillants en pi\u00e8ces and accessoires de voitures. Entretien and r\u00e9parations de voitures",
    "sg:phone":"+32 3 480 26 47",
    "sg:postcode":"2500",
    "sg:province":"Antwerpen",
    "wof:name":"Garage Marvex",
    "wof:placetype":"venue"
},
  "geometry": {"coordinates":[4.5935549736,51.1363639832],"type":"Point"}
}