{
  "type": "Feature",
  "properties": {
    "addr:full":"Hoogstraat 23 Zottegem Oost-Vlaanderen 9620",
    "addr:housenumber":"23",
    "addr:postcode":"9620",
    "addr:street":"Hoogstraat",
    "iso:country":"BE",
    "sg:address":"Hoogstraat 23",
    "sg:city":"Zottegem",
    "sg:classifiers":[
        {
            "category":"Personal",
            "subcategory":"Beauty Salon",
            "type":"Services"
        }
    ],
    "sg:phone":"+32 9 360 64 40",
    "sg:postcode":"9620",
    "sg:province":"Oost-Vlaanderen",
    "sg:tags":[
        "lady",
        "-",
        "hairdressing"
    ],
    "wof:name":"Image",
    "wof:placetype":"venue"
},
  "geometry": {"coordinates":[3.8097600937,50.8691368103],"type":"Point"}
}