{
  "type": "Feature",
  "properties": {
    "addr:full":"Veurnelaan 15 Koksijde West-Vlaanderen 8670",
    "addr:housenumber":"15",
    "addr:postcode":"8670",
    "addr:street":"Veurnelaan",
    "iso:country":"BE",
    "sg:address":"Veurnelaan 15",
    "sg:city":"Koksijde",
    "sg:classifiers":[
        {
            "category":"Cafe",
            "type":"Food & Drink"
        }
    ],
    "sg:phone":"+32 58 51 12 05",
    "sg:postcode":"8670",
    "sg:province":"West-Vlaanderen",
    "sg:tags":[
        "caf\u00e9s"
    ],
    "wof:name":"Noel Duprez",
    "wof:placetype":"venue"
},
  "geometry": {"coordinates":[2.6285541058,51.1004867554],"type":"Point"}
}