{
  "type": "Feature",
  "properties": {
    "addr:full":"Bouquetstraat 115 Diepenbeek Limburg 3590",
    "addr:housenumber":"115",
    "addr:postcode":"3590",
    "addr:street":"Bouquetstraat",
    "iso:country":"BE",
    "sg:address":"Bouquetstraat 115",
    "sg:city":"Diepenbeek",
    "sg:orig_category":"Loodgieterij, verwarming and sanitaire installaties",
    "sg:phone":"+32 11 32 11 64",
    "sg:postcode":"3590",
    "sg:province":"Limburg",
    "wof:name":"Yvan Smolders",
    "wof:placetype":"venue"
},
  "geometry": {"coordinates":[5.3894820213,50.9001312256],"type":"Point"}
}