{
  "type": "Feature",
  "properties": {
    "iso:country":"BE",
    "sg:address":"Wervikstraat 350",
    "sg:city":"Menen",
    "sg:orig_category":"Installatie van metalen schrijnwerk",
    "sg:phone":"+32 56 51 42 51",
    "sg:postcode":"8930",
    "sg:province":"West-Vlaanderen",
    "wof:name":"Holvrieka",
    "wof:placetype":"venue"
},
  "geometry": {"coordinates":[3.1036949158,50.7870178223],"type":"Point"}
}