{
  "type": "Feature",
  "properties": {
    "addr:full":"Bredabaan 1303 Schoten Antwerpen 2900",
    "addr:housenumber":"1303",
    "addr:postcode":"2900",
    "addr:street":"Bredabaan",
    "iso:country":"BE",
    "sg:address":"Bredabaan 1303",
    "sg:city":"Schoten",
    "sg:orig_category":"Meubelzaken, woning- and keukeninrichting",
    "sg:phone":"+32 3 644 07 01",
    "sg:postcode":"2900",
    "sg:province":"Antwerpen",
    "wof:name":"Trendhopper",
    "wof:placetype":"venue"
},
  "geometry": {"coordinates":[4.4647989273,51.2688179016],"type":"Point"}
}