{
  "type": "Feature",
  "properties": {
    "iso:country":"BE",
    "sg:address":".",
    "sg:city":"Bonheiden (groot)",
    "sg:orig_category":"Apotheken",
    "sg:phone":"+32 900 10 500",
    "sg:postcode":"2820",
    "sg:province":"Antwerpen",
    "wof:name":"Apothekers Van Wacht",
    "wof:placetype":"venue"
},
  "geometry": {"coordinates":[4.5496602058,51.0218009949],"type":"Point"}
}