{
  "type": "Feature",
  "properties": {
    "iso:country":"BE",
    "sg:address":"Rue Albert I 51",
    "sg:city":"Hannut",
    "sg:classifiers":[
        {
            "category":"Retail",
            "subcategory":"Event Space",
            "type":"Services"
        }
    ],
    "sg:phone":"+32 19 51 35 50",
    "sg:postcode":"4280",
    "sg:province":"Li\u00e8ge",
    "sg:tags":[
        "organisation"
    ],
    "wof:name":"Yocotess",
    "wof:placetype":"venue"
},
  "geometry": {"coordinates":[5.0832848549,50.6693344116],"type":"Point"}
}