{
  "type": "Feature",
  "properties": {
    "iso:country":"BE",
    "sg:address":"Rue De La Marli\u00e8re 197",
    "sg:city":"Mouscron",
    "sg:classifiers":[
        {
            "category":"Bars & Pubs",
            "type":"Food & Drink"
        }
    ],
    "sg:phone":"+32 56 84 75 74",
    "sg:postcode":"7700",
    "sg:province":"Hainaut",
    "sg:tags":[
        "tavern"
    ],
    "wof:name":"Provence (la)",
    "wof:placetype":"venue"
},
  "geometry": {"coordinates":[3.1991970539,50.7393531799],"type":"Point"}
}