{
  "type": "Feature",
  "properties": {
    "iso:country":"BE",
    "sg:address":"Samr\u00e9e 9",
    "sg:city":"La Roche-en-ardenne (samr\u00e9e)",
    "sg:classifiers":[
        {
            "category":"Personal",
            "subcategory":"Beauty Salon",
            "type":"Services"
        }
    ],
    "sg:phone":"+32 84 44 46 65",
    "sg:postcode":"6982",
    "sg:province":"Luxembourg",
    "sg:tags":[
        "lady",
        "-",
        "hairdressing"
    ],
    "wof:name":"G\u00e9n\u00e9ration Coiffure",
    "wof:placetype":"venue"
},
  "geometry": {"coordinates":[5.638133049,50.2120666504],"type":"Point"}
}