{
  "type": "Feature",
  "properties": {
    "iso:country":"BE",
    "sg:address":"Oostjachtpark 10",
    "sg:city":"Sint-niklaas",
    "sg:orig_category":"V\u00eatements",
    "sg:phone":"+32 3 766 61 77",
    "sg:postcode":"9100",
    "sg:province":"Oost-Vlaanderen",
    "wof:name":"Jeanswinkel",
    "wof:placetype":"venue"
},
  "geometry": {"coordinates":[4.1711678505,51.1425552368],"type":"Point"}
}