{
  "type": "Feature",
  "properties": {
    "addr:full":"Assenedesteenweg 37 Zelzate Oost-Vlaanderen 9060",
    "addr:housenumber":"37",
    "addr:postcode":"9060",
    "addr:street":"Assenedesteenweg",
    "iso:country":"BE",
    "sg:address":"Assenedesteenweg 37",
    "sg:city":"Zelzate",
    "sg:orig_category":"Entretien and r\u00e9parations de voitures. V\u00e9hicules automobiles",
    "sg:phone":"+32 9 344 51 58",
    "sg:postcode":"9060",
    "sg:province":"Oost-Vlaanderen",
    "wof:name":"De Vrieze",
    "wof:placetype":"venue"
},
  "geometry": {"coordinates":[3.797287941,51.1973457336],"type":"Point"}
}