{
  "type": "Feature",
  "properties": {
    "iso:country":"BE",
    "sg:address":"Heerlijkheidstraat 46",
    "sg:city":"Dendermonde (schoonaarde)",
    "sg:classifiers":[
        {
            "category":"Building & Trades",
            "subcategory":"Equipment Rental",
            "type":"Services"
        }
    ],
    "sg:phone":"+32 52 42 22 06",
    "sg:postcode":"9200",
    "sg:province":"Oost-Vlaanderen",
    "sg:tags":[
        "use",
        "apparatus",
        "tool",
        "-",
        "professional",
        "machines"
    ],
    "wof:name":"Isatrans Bvba",
    "wof:placetype":"venue"
},
  "geometry": {"coordinates":[4.0225358009,51.0064125061],"type":"Point"}
}