{
  "type": "Feature",
  "properties": {
    "iso:country":"BE",
    "sg:address":"Chauss\u00c9e Charlemagne 150",
    "sg:city":"Thimister-clermont",
    "sg:orig_category":"Installation \u00e9lectrique r\u00e9sidentielle",
    "sg:phone":"+32 87 44 50 02",
    "sg:postcode":"4890",
    "sg:province":"Li\u00e8ge",
    "wof:name":"Albert Schyns",
    "wof:placetype":"venue"
},
  "geometry": {"coordinates":[5.8860259056,50.6544532776],"type":"Point"}
}