{
  "type": "Feature",
  "properties": {
    "iso:country":"BE",
    "sg:address":"Rue Du Pressoir 43",
    "sg:city":"Libramont",
    "sg:orig_category":"Installatie van houten of kunststof schrijnwerk",
    "sg:phone":"+32 61 22 50 45",
    "sg:postcode":"6800",
    "sg:province":"Luxembourg",
    "wof:name":"Philippe Paul",
    "wof:placetype":"venue"
},
  "geometry": {"coordinates":[5.3910617828,49.9173774719],"type":"Point"}
}