{
  "type": "Feature",
  "properties": {
    "addr:full":"Bosstraat 10 Buggenhout Oost-Vlaanderen 9255",
    "addr:housenumber":"10",
    "addr:postcode":"9255",
    "addr:street":"Bosstraat",
    "iso:country":"BE",
    "sg:address":"Bosstraat 10",
    "sg:city":"Buggenhout",
    "sg:orig_category":"M\u00e9decins and sp\u00e9cialistes",
    "sg:phone":"+32 52 33 76 20",
    "sg:postcode":"9255",
    "sg:province":"Oost-Vlaanderen",
    "wof:name":"J. Tilley",
    "wof:placetype":"venue"
},
  "geometry": {"coordinates":[4.2070178986,51.0126457214],"type":"Point"}
}