{
  "type": "Feature",
  "properties": {
    "addr:full":"Daillylaan 12 Schaarbeek/schaerbeek Bruxelles-Capitale 1030",
    "addr:housenumber":"12",
    "addr:postcode":"1030",
    "addr:street":"Daillylaan",
    "iso:country":"BE",
    "sg:address":"Daillylaan 12",
    "sg:city":"Schaarbeek/schaerbeek",
    "sg:orig_category":"Kapsalons",
    "sg:phone":"+32 2 241 14 56",
    "sg:postcode":"1030",
    "sg:province":"Bruxelles-Capitale",
    "wof:name":"Coiffure Mary",
    "wof:placetype":"venue"
},
  "geometry": {"coordinates":[4.3810720444,50.8583679199],"type":"Point"}
}