{
  "type": "Feature",
  "properties": {
    "addr:full":"Avenue Des Alouettes 3 Braine-l'alleud Brabant Wallon 1428",
    "addr:housenumber":"3",
    "addr:postcode":"1428",
    "addr:street":"Avenue Des Alouettes",
    "iso:country":"BE",
    "sg:address":"Avenue Des Alouettes 3",
    "sg:city":"Braine-l'alleud",
    "sg:orig_category":"M\u00e9decins and sp\u00e9cialistes",
    "sg:phone":"+32 2 384 30 62",
    "sg:postcode":"1428",
    "sg:province":"Brabant Wallon",
    "wof:name":"Michel Nyst",
    "wof:placetype":"venue"
},
  "geometry": {"coordinates":[-0.6952610016,47.3734397888],"type":"Point"}
}