{
  "type": "Feature",
  "properties": {
    "addr:full":"Rue De L'abbaye 47 Box 1 Ans (alleur) Li\u00e8ge 4432",
    "addr:housenumber":"47",
    "addr:postcode":"4432",
    "addr:street":"Rue De L'Abbaye;Box 1",
    "iso:country":"BE",
    "sg:address":"Rue De L'abbaye 47 Box 1",
    "sg:city":"Ans (alleur)",
    "sg:classifiers":[
        {
            "category":"Professional",
            "subcategory":"Lawyer & Legal Services",
            "type":"Services"
        }
    ],
    "sg:phone":"+32 4 239 07 07",
    "sg:postcode":"4432",
    "sg:province":"Li\u00e8ge",
    "wof:name":"Perin B",
    "wof:placetype":"venue"
},
  "geometry": {"coordinates":[5.5242800713,50.6659317017],"type":"Point"}
}