{
  "type": "Feature",
  "properties": {
    "addr:full":"Chauss\u00c9e De Namur 52 Nivelles Brabant Wallon 1400",
    "addr:housenumber":"52",
    "addr:postcode":"1400",
    "addr:street":"Chausse\u0301E De Namur",
    "iso:country":"BE",
    "sg:address":"Chauss\u00c9e De Namur 52",
    "sg:city":"Nivelles",
    "sg:orig_category":"V\u00e9hicules automobiles. Entretien and r\u00e9parations de voitures",
    "sg:phone":"+32 67 84 31 30",
    "sg:postcode":"1400",
    "sg:province":"Brabant Wallon",
    "wof:name":"Garage Crymoco",
    "wof:placetype":"venue"
},
  "geometry": {"coordinates":[4.3570609093,50.5974235535],"type":"Point"}
}