{
  "type": "Feature",
  "properties": {
    "iso:country":"BE",
    "sg:address":"Rue Sax 74",
    "sg:city":"Dinant",
    "sg:orig_category":"Fleurop Interflora. Fleurs and plantes",
    "sg:phone":"+32 82 22 45 39",
    "sg:postcode":"5500",
    "sg:province":"Namur",
    "wof:name":"La Roseraie",
    "wof:placetype":"venue"
},
  "geometry": {"coordinates":[4.9119329453,50.2604866028],"type":"Point"}
}