{
  "type": "Feature",
  "properties": {
    "addr:full":"Rue Baronne-lemonnier 56 Rochefort Namur 5580",
    "addr:housenumber":"56",
    "addr:postcode":"5580",
    "addr:street":"Rue Baronne-Lemonnier",
    "iso:country":"BE",
    "sg:address":"Rue Baronne-lemonnier 56",
    "sg:city":"Rochefort",
    "sg:orig_category":"Plomberie, chauffage and installations sanitaires",
    "sg:phone":"+32 84 38 94 17",
    "sg:postcode":"5580",
    "sg:province":"Namur",
    "wof:name":"Walter Meskens",
    "wof:placetype":"venue"
},
  "geometry": {"coordinates":[5.0984020233,50.1151428223],"type":"Point"}
}