{
  "type": "Feature",
  "properties": {
    "addr:full":"Open Luchtlaan 43 Sint-genesius-rode/rhode-saint-gen\u00c8se Vlaams-Brabant 1640",
    "addr:housenumber":"43",
    "addr:postcode":"1640",
    "addr:street":"Luchtlaan",
    "iso:country":"BE",
    "sg:address":"Open Luchtlaan 43",
    "sg:city":"Sint-genesius-rode/rhode-saint-gen\u00c8se",
    "sg:orig_category":"Binnenhuisarchitecten",
    "sg:phone":"+32 2 358 45 74",
    "sg:postcode":"1640",
    "sg:province":"Vlaams-Brabant",
    "wof:name":"Pierre Vandeperre",
    "wof:placetype":"venue"
},
  "geometry": {"coordinates":[4.3662791252,50.7595214844],"type":"Point"}
}