{
  "type": "Feature",
  "properties": {
    "iso:country":"BE",
    "sg:address":"Schollenberg 45",
    "sg:city":"Bertem",
    "sg:orig_category":"Sportclubs",
    "sg:phone":"+32 2 767 13 91",
    "sg:postcode":"3061",
    "sg:province":"Vlaams-Brabant",
    "wof:name":"W.k. De Wringers",
    "wof:placetype":"venue"
},
  "geometry": {"coordinates":[4.5852799416,50.8514518738],"type":"Point"}
}