{
  "type": "Feature",
  "properties": {
    "iso:country":"BE",
    "sg:address":"Meulevijverstraat 3ba",
    "sg:city":"Stekene",
    "sg:orig_category":"Paramedische behandelingen",
    "sg:phone":"+32 3 789 00 62",
    "sg:postcode":"9190",
    "sg:province":"Oost-Vlaanderen",
    "wof:name":"Mertens C.",
    "wof:placetype":"venue"
},
  "geometry": {"coordinates":[4.0144171715,51.1854057312],"type":"Point"}
}