{
  "type": "Feature",
  "properties": {
    "iso:country":"BE",
    "sg:address":"Avenue Orban 231",
    "sg:city":"Sint-pieters-woluwe/woluwe-sai",
    "sg:classifiers":[
        {
            "category":"Restaurant",
            "type":"Food & Drink"
        }
    ],
    "sg:phone":"+32 2 770 12 34",
    "sg:postcode":"1150",
    "sg:province":"Bruxelles-Capitale",
    "sg:tags":[
        "\u00c0",
        "domicile",
        "fast",
        "emporter",
        "livraison",
        "restaurants"
    ],
    "wof:name":"Domino\u00b4s Pizza",
    "wof:placetype":"venue"
},
  "geometry": {"coordinates":[4.4645061493,50.8389701843],"type":"Point"}
}