{
  "type": "Feature",
  "properties": {
    "addr:full":"Bonaerde 6 Kuurne West-Vlaanderen 8520",
    "addr:housenumber":"6",
    "addr:postcode":"8520",
    "addr:street":"Bonaerde",
    "iso:country":"BE",
    "sg:address":"Bonaerde 6",
    "sg:city":"Kuurne",
    "sg:orig_category":"G\u00e9om\u00e8tres",
    "sg:phone":"+32 56 37 29 23",
    "sg:postcode":"8520",
    "sg:province":"West-Vlaanderen",
    "wof:name":"Peter Van Kerkhove",
    "wof:placetype":"venue"
},
  "geometry": {"coordinates":[3.2787079811,50.8425865173],"type":"Point"}
}