{
  "type": "Feature",
  "properties": {
    "addr:full":"Rue C. Mercier 5 La Louvi\u00e8re (houdeng-goegnies) Hainaut 7110",
    "addr:housenumber":"5",
    "addr:postcode":"7110",
    "addr:street":"Rue C. Mercier",
    "iso:country":"BE",
    "sg:address":"Rue C. Mercier 5",
    "sg:city":"La Louvi\u00e8re (houdeng-goegnies)",
    "sg:classifiers":[
        {
            "category":"Wholesale",
            "subcategory":"Construction Materials",
            "type":"Manufacturing & Wholesale Goods"
        }
    ],
    "sg:phone":"+32 64 28 02 37",
    "sg:postcode":"7110",
    "sg:province":"Hainaut",
    "sg:tags":[
        "tubing",
        "industrial"
    ],
    "wof:name":"Delta Tube Sa",
    "wof:placetype":"venue"
},
  "geometry": {"coordinates":[4.1505050659,50.4826698303],"type":"Point"}
}