{
  "type": "Feature",
  "properties": {
    "iso:country":"BE",
    "sg:address":"Bostraat 139",
    "sg:city":"Hamont",
    "sg:orig_category":"Voedings- and genotsmiddelen Gh",
    "sg:phone":"+32 11 44 55 42",
    "sg:postcode":"3930",
    "sg:province":"Limburg",
    "wof:name":"Van Hout Horeca",
    "wof:placetype":"venue"
},
  "geometry": {"coordinates":[5.5187940598,51.2479438782],"type":"Point"}
}