{
  "type": "Feature",
  "properties": {
    "addr:full":"Valkenstraat 29 Brakel (nederbrakel) Oost-Vlaanderen 9660",
    "addr:housenumber":"29",
    "addr:postcode":"9660",
    "addr:street":"Valkenstraat",
    "iso:country":"BE",
    "sg:address":"Valkenstraat 29",
    "sg:city":"Brakel (nederbrakel)",
    "sg:orig_category":"Non-Classified Establishments",
    "sg:phone":"+32 55 42 83 20",
    "sg:postcode":"9660",
    "sg:province":"Oost-Vlaanderen",
    "wof:name":"Gildewerk",
    "wof:placetype":"venue"
},
  "geometry": {"coordinates":[3.7570240498,50.8153762817],"type":"Point"}
}