{
  "type": "Feature",
  "properties": {
    "addr:full":"Almaplein 3 Box 2 Bruxelles (woluwe-saint-lambert) Bruxelles-Capitale 1200",
    "addr:housenumber":"3;2",
    "addr:postcode":"1200",
    "addr:street":"Almaplein;Box",
    "iso:country":"BE",
    "sg:address":"Almaplein 3 Box 2",
    "sg:city":"Bruxelles (woluwe-saint-lambert)",
    "sg:classifiers":[
        {
            "category":"Organizations",
            "subcategory":"Professional Association",
            "type":"Services"
        }
    ],
    "sg:phone":"+32 2 779 41 74",
    "sg:postcode":"1200",
    "sg:province":"Bruxelles-Capitale",
    "sg:tags":[
        "trade-union",
        "federation"
    ],
    "wof:name":"Bvf/ifpi",
    "wof:placetype":"venue"
},
  "geometry": {"coordinates":[4.4531497955,50.8495864868],"type":"Point"}
}