{
  "type": "Feature",
  "properties": {
    "addr:full":"Industrieterrein Kanaal-noord 1-113 Bree Limburg 3960",
    "addr:housenumber":"1-113",
    "addr:postcode":"3960",
    "addr:street":"Industrieterrein Kanaal-Noord",
    "iso:country":"BE",
    "sg:address":"Industrieterrein Kanaal-noord 1-113",
    "sg:city":"Bree",
    "sg:classifiers":[
        {
            "category":"Professional",
            "subcategory":"Engineering",
            "type":"Services"
        }
    ],
    "sg:phone":"+32 89 47 11 28",
    "sg:postcode":"3960",
    "sg:province":"Limburg",
    "sg:tags":[
        "workshop"
    ],
    "wof:name":"Tancer Construct",
    "wof:placetype":"venue"
},
  "geometry": {"coordinates":[5.6246738434,51.1431350708],"type":"Point"}
}