{
  "type": "Feature",
  "properties": {
    "addr:full":"Torhoutse Steenweg 214 Brugge (sint-andries) West-Vlaanderen 8200",
    "addr:housenumber":"214",
    "addr:postcode":"8200",
    "addr:street":"Torhoutse Steenweg",
    "iso:country":"BE",
    "sg:address":"Torhoutse Steenweg 214",
    "sg:city":"Brugge (sint-andries)",
    "sg:classifiers":[
        {
            "category":"Insurance",
            "subcategory":"Insurance Agent",
            "type":"Services"
        }
    ],
    "sg:phone":"+32 50 39 16 15",
    "sg:postcode":"8200",
    "sg:province":"West-Vlaanderen",
    "sg:tags":[
        "broker"
    ],
    "wof:name":"D D M Makelaars",
    "wof:placetype":"venue"
},
  "geometry": {"coordinates":[3.1999549866,51.1961364746],"type":"Point"}
}