{
  "type": "Feature",
  "properties": {
    "iso:country":"BE",
    "sg:address":"Rue De La N\u00c9then 1",
    "sg:city":"Beauvechain",
    "sg:classifiers":[
        {
            "category":"Government",
            "subcategory":"Police Station",
            "type":"Public Place"
        }
    ],
    "sg:phone":"+32 10 86 63 56",
    "sg:postcode":"1320",
    "sg:province":"Brabant Wallon",
    "sg:tags":[
        "gendarmerie"
    ],
    "wof:name":"Police F\u00c9d\u00c9rale/federale Politie",
    "wof:placetype":"venue"
},
  "geometry": {"coordinates":[4.7673377991,50.7780532837],"type":"Point"}
}