{
  "type": "Feature",
  "properties": {
    "iso:country":"BE",
    "sg:address":"Hoogstraat 7",
    "sg:city":"Zaventem",
    "sg:orig_category":"Supermarkten",
    "sg:postcode":"1930",
    "sg:province":"Vlaams-Brabant",
    "wof:name":"Aldi",
    "wof:placetype":"venue"
},
  "geometry": {"coordinates":[4.4769701958,50.8827285767],"type":"Point"}
}