{
  "type": "Feature",
  "properties": {
    "iso:country":"BE",
    "sg:address":"Chauss\u00c9e De Mons 251",
    "sg:city":"Tubize",
    "sg:orig_category":"Installation de serres, double vitrage and fen\u00eatres",
    "sg:phone":"+32 2 355 95 25",
    "sg:postcode":"1480",
    "sg:province":"Brabant Wallon",
    "wof:name":"Lucien Vervoort",
    "wof:placetype":"venue"
},
  "geometry": {"coordinates":[4.1950521469,50.6843109131],"type":"Point"}
}