{
  "type": "Feature",
  "properties": {
    "addr:full":"Trapstraat 3 Antwerpen Antwerpen 2060",
    "addr:housenumber":"3",
    "addr:postcode":"2060",
    "addr:street":"Trapstraat",
    "iso:country":"BE",
    "sg:address":"Trapstraat 3",
    "sg:city":"Antwerpen",
    "sg:classifiers":[
        {
            "category":"Organizations",
            "subcategory":"Community Association",
            "type":"Services"
        }
    ],
    "sg:phone":"+32 3 226 25 38",
    "sg:postcode":"2060",
    "sg:province":"Antwerpen",
    "sg:tags":[
        "cultural"
    ],
    "wof:name":"Islamitische Culturele Vereniging",
    "wof:placetype":"venue"
},
  "geometry": {"coordinates":[4.4224429131,51.2277145386],"type":"Point"}
}