{
  "type": "Feature",
  "properties": {
    "iso:country":"BE",
    "sg:address":"Rue Osseghem 126",
    "sg:city":"Sint-jans-molenbeek/molenbeek-saint-jean",
    "sg:orig_category":"S\u00e9curit\u00e9 sociale",
    "sg:phone":"+32 2 410 54 97",
    "sg:postcode":"1080",
    "sg:province":"Bruxelles-Capitale",
    "wof:name":"Mutualit\u00c9 Socialiste",
    "wof:placetype":"venue"
},
  "geometry": {"coordinates":[4.3174629211,50.8540153503],"type":"Point"}
}