{
  "type": "Feature",
  "properties": {
    "addr:full":"Rue De Fleurus 95 Sambreville Namur 5060",
    "addr:housenumber":"95",
    "addr:postcode":"5060",
    "addr:street":"Rue De Fleurus",
    "iso:country":"BE",
    "sg:address":"Rue De Fleurus 95",
    "sg:city":"Sambreville",
    "sg:orig_category":"Apotheken",
    "sg:phone":"+32 71 77 15 92",
    "sg:postcode":"5060",
    "sg:province":"Namur",
    "wof:name":"Pharm. Concorde De Namur",
    "wof:placetype":"venue"
},
  "geometry": {"coordinates":[4.5876498222,50.4433708191],"type":"Point"}
}