{
  "type": "Feature",
  "properties": {
    "iso:country":"BE",
    "sg:address":"Rue Du Village 130",
    "sg:city":"Quaregnon",
    "sg:orig_category":"Banken and kredietinstellingen",
    "sg:phone":"+32 65 78 76 64",
    "sg:postcode":"7390",
    "sg:province":"Hainaut",
    "wof:name":"Bbl",
    "wof:placetype":"venue"
},
  "geometry": {"coordinates":[3.8651740551,50.4417953491],"type":"Point"}
}