{
  "type": "Feature",
  "properties": {
    "addr:full":"Toekomststraat 28 Bredene West-Vlaanderen 8450",
    "addr:housenumber":"28",
    "addr:postcode":"8450",
    "addr:street":"Toekomststraat",
    "iso:country":"BE",
    "sg:address":"Toekomststraat 28",
    "sg:city":"Bredene",
    "sg:orig_category":"Epiceries",
    "sg:phone":"+32 59 32 54 14",
    "sg:postcode":"8450",
    "sg:province":"West-Vlaanderen",
    "wof:name":"Marianne Dewulf",
    "wof:placetype":"venue"
},
  "geometry": {"coordinates":[2.9635679722,51.2282028198],"type":"Point"}
}