{
  "type": "Feature",
  "properties": {
    "addr:full":"Ouburg 37 Dendermonde Oost-Vlaanderen 9200",
    "addr:housenumber":"37",
    "addr:postcode":"9200",
    "addr:street":"Ouburg;Oost-Vlaanderen",
    "iso:country":"BE",
    "sg:address":"Ouburg 37",
    "sg:city":"Dendermonde",
    "sg:orig_category":"Woningbouw",
    "sg:phone":"+32 52 21 25 29",
    "sg:postcode":"9200",
    "sg:province":"Oost-Vlaanderen",
    "wof:name":"Hubert Smetrijns",
    "wof:placetype":"venue"
},
  "geometry": {"coordinates":[4.1006288528,51.0288200378],"type":"Point"}
}