{
  "type": "Feature",
  "properties": {
    "addr:full":"Dorpsstraat 50 Deinze (astene) Oost-Vlaanderen 9800",
    "addr:housenumber":"50",
    "addr:postcode":"9800",
    "addr:street":"Dorpsstraat",
    "iso:country":"BE",
    "sg:address":"Dorpsstraat 50",
    "sg:city":"Deinze (astene)",
    "sg:classifiers":[
        {
            "category":"Professional",
            "subcategory":"Accounting & Tax Preparation",
            "type":"Services"
        }
    ],
    "sg:phone":"+32 9 386 65 86",
    "sg:postcode":"9800",
    "sg:province":"Oost-Vlaanderen",
    "sg:tags":[
        "bookkeeper"
    ],
    "wof:name":"De Groeve F",
    "wof:placetype":"venue"
},
  "geometry": {"coordinates":[3.530174017,50.9863166809],"type":"Point"}
}