{
  "type": "Feature",
  "properties": {
    "addr:full":"Rue De La Loi 37 La Louvi\u00c8re Hainaut 7100",
    "addr:housenumber":"37",
    "addr:postcode":"7100",
    "addr:street":"Rue De La Loi",
    "iso:country":"BE",
    "sg:address":"Rue De La Loi 37",
    "sg:city":"La Louvi\u00c8re",
    "sg:orig_category":"Machines pour les industries du textile, de l\u00b4habillement and du cuir Fab. Machines \u00e0 coudre and tri",
    "sg:phone":"+32 64 84 89 30",
    "sg:postcode":"7100",
    "sg:province":"Hainaut",
    "wof:name":"Etablissements Parisi",
    "wof:placetype":"venue"
},
  "geometry": {"coordinates":[4.1862869263,50.4769706726],"type":"Point"}
}