{
  "type": "Feature",
  "properties": {
    "iso:country":"BE",
    "sg:address":"Rue De Marchovelette 9",
    "sg:city":"Namur",
    "sg:classifiers":[
        {
            "category":"Shopping",
            "subcategory":"Clothing, Apparel, & Fashions",
            "type":"Retail Goods"
        }
    ],
    "sg:phone":"+32 81 22 56 19",
    "sg:postcode":"5000",
    "sg:province":"Namur",
    "sg:tags":[
        "lady",
        "clothing",
        "-"
    ],
    "wof:name":"Devernois (boutique)",
    "wof:placetype":"venue"
},
  "geometry": {"coordinates":[4.8671278954,50.4627037048],"type":"Point"}
}