{
  "type": "Feature",
  "properties": {
    "addr:full":"Mechelsesteenweg 446 Zaventem Vlaams-Brabant 1930",
    "addr:housenumber":"446",
    "addr:postcode":"1930",
    "addr:street":"Mechelsesteenweg",
    "iso:country":"BE",
    "sg:address":"Mechelsesteenweg 446",
    "sg:city":"Zaventem",
    "sg:orig_category":"Installatie van houten of kunststof schrijnwerk Installatie van metalen schrijnwerk",
    "sg:phone":"+32 2 757 25 40",
    "sg:postcode":"1930",
    "sg:province":"Vlaams-Brabant",
    "wof:name":"Frank Haesaerts",
    "wof:placetype":"venue"
},
  "geometry": {"coordinates":[4.5075740814,50.8768959045],"type":"Point"}
}