{
  "type": "Feature",
  "properties": {
    "addr:full":"Koning Albert I Laan 98 Roeselare West-Vlaanderen 8800",
    "addr:housenumber":"98",
    "addr:postcode":"8800",
    "addr:street":"Koning Albert I Laan",
    "iso:country":"BE",
    "sg:address":"Koning Albert I Laan 98",
    "sg:city":"Roeselare",
    "sg:classifiers":[
        {
            "category":"Professional",
            "subcategory":"Printing & Photocopies",
            "type":"Services"
        }
    ],
    "sg:phone":"+32 51 24 75 75",
    "sg:postcode":"8800",
    "sg:province":"West-Vlaanderen",
    "sg:tags":[
        "-",
        "plan",
        "reproduction"
    ],
    "wof:name":"Dokuplan",
    "wof:placetype":"venue"
},
  "geometry": {"coordinates":[3.1272580624,50.9395332336],"type":"Point"}
}