{
  "type": "Feature",
  "properties": {
    "iso:country":"BE",
    "sg:address":"Rue Pierre-joseph Wery 1",
    "sg:city":"Charleroi",
    "sg:orig_category":"Entretien and r\u00e9parations de voitures",
    "sg:phone":"+32 71 35 66 06",
    "sg:postcode":"6040",
    "sg:province":"Hainaut",
    "wof:name":"Garage D'angelo",
    "wof:placetype":"venue"
},
  "geometry": {"coordinates":[4.4134321213,50.4351081848],"type":"Point"}
}