{
  "type": "Feature",
  "properties": {
    "iso:country":"BE",
    "sg:address":"Chauss\u00e9e D'ypres 41",
    "sg:city":"Comines-warneton (warneton)",
    "sg:classifiers":[
        {
            "category":"Building & Trades",
            "subcategory":"Landscaping Services",
            "type":"Services"
        }
    ],
    "sg:phone":"+32 56 55 75 09",
    "sg:postcode":"7784",
    "sg:province":"Hainaut",
    "sg:tags":[
        "nurseryman"
    ],
    "wof:name":"L'etre Vert",
    "wof:placetype":"venue"
},
  "geometry": {"coordinates":[2.9479990005,50.7544555664],"type":"Point"}
}