{
  "type": "Feature",
  "properties": {
    "iso:country":"BE",
    "sg:address":"Avenue Adolphe Lacombl\u00e9 52 Box 7",
    "sg:city":"Bruxelles (schaerbeek)",
    "sg:classifiers":[
        {
            "category":"Health Services",
            "subcategory":"Hospital",
            "type":"Services"
        }
    ],
    "sg:phone":"+32 2 738 75 37",
    "sg:postcode":"1030",
    "sg:province":"Bruxelles-Capitale",
    "wof:name":"Cbmt",
    "wof:placetype":"venue"
},
  "geometry": {"coordinates":[4.399160862,50.8490905762],"type":"Point"}
}