{
  "type": "Feature",
  "properties": {
    "addr:full":"Piet Stautstraat 52 Beveren (beveren-waas) Oost-Vlaanderen 9120",
    "addr:housenumber":"52",
    "addr:postcode":"9120",
    "addr:street":"Stautstraat;Oost-Vlaanderen",
    "iso:country":"BE",
    "sg:address":"Piet Stautstraat 52",
    "sg:city":"Beveren (beveren-waas)",
    "sg:classifiers":[
        {
            "category":"Landmark",
            "subcategory":"Memorial",
            "type":"Public Place"
        }
    ],
    "sg:phone":"+32 3 775 77 93",
    "sg:postcode":"9120",
    "sg:province":"Oost-Vlaanderen",
    "sg:tags":[
        "-",
        "monument"
    ],
    "wof:name":"Van Ombergen Gebr",
    "wof:placetype":"venue"
},
  "geometry": {"coordinates":[4.2591118813,51.2047805786],"type":"Point"}
}