{
  "type": "Feature",
  "properties": {
    "addr:full":"Sint-michielsweg 33 Kuurne West-Vlaanderen 8520",
    "addr:housenumber":"33",
    "addr:postcode":"8520",
    "addr:street":"Sint-Michielsweg",
    "iso:country":"BE",
    "sg:address":"Sint-michielsweg 33",
    "sg:city":"Kuurne",
    "sg:orig_category":"Epiceries",
    "sg:phone":"+32 56 71 80 13",
    "sg:postcode":"8520",
    "sg:province":"West-Vlaanderen",
    "wof:name":"Huis De Molenaar",
    "wof:placetype":"venue"
},
  "geometry": {"coordinates":[3.2714850903,50.8642807007],"type":"Point"}
}