{
  "type": "Feature",
  "properties": {
    "iso:country":"BE",
    "sg:address":"Rue Fontaine-au-biez 57",
    "sg:city":"Verviers (heusy)",
    "sg:classifiers":[
        {
            "category":"Retail",
            "subcategory":"Animal Services",
            "type":"Services"
        }
    ],
    "sg:phone":"+32 87 22 70 41",
    "sg:postcode":"4802",
    "sg:province":"Li\u00e8ge",
    "sg:tags":[
        "breeding",
        "selling",
        "-",
        "dog"
    ],
    "wof:name":"De Chandaril",
    "wof:placetype":"venue"
},
  "geometry": {"coordinates":[5.8888411522,50.5790519714],"type":"Point"}
}