{
  "type": "Feature",
  "properties": {
    "iso:country":"BE",
    "sg:address":"Rue Joseph Martin 35",
    "sg:city":"Juprelle (lantin)",
    "sg:classifiers":[
        {
            "category":"Home & Garden",
            "subcategory":"Kitchen Supply",
            "type":"Retail Goods"
        }
    ],
    "sg:phone":"+32 4 263 96 05",
    "sg:postcode":"4450",
    "sg:province":"Li\u00e8ge",
    "sg:tags":[
        "installation"
    ],
    "wof:name":"A.b.c. Cuisine-martin",
    "wof:placetype":"venue"
},
  "geometry": {"coordinates":[5.527659893,50.7088737488],"type":"Point"}
}