{
  "type": "Feature",
  "properties": {
    "iso:country":"BE",
    "sg:address":"Mispelaar 19",
    "sg:city":"Brugge (assebroek)",
    "sg:classifiers":[
        {
            "category":"Professional",
            "subcategory":"Management & Consulting",
            "type":"Services"
        }
    ],
    "sg:phone":"+32 50 35 39 35",
    "sg:postcode":"8310",
    "sg:province":"West-Vlaanderen",
    "sg:tags":[
        "consultant",
        "agency",
        "advertising"
    ],
    "wof:name":"C.c.r.-reclamemakers",
    "wof:placetype":"venue"
},
  "geometry": {"coordinates":[3.2573440075,51.2042236328],"type":"Point"}
}