{
  "type": "Feature",
  "properties": {
    "iso:country":"BE",
    "sg:address":"Rue De La Dendre 9",
    "sg:city":"Brugelette",
    "sg:orig_category":"Rundveehouders",
    "sg:phone":"+32 68 45 45 78",
    "sg:postcode":"7940",
    "sg:province":"Hainaut",
    "wof:name":"Norbert Clement",
    "wof:placetype":"venue"
},
  "geometry": {"coordinates":[3.8544900417,50.5980796814],"type":"Point"}
}