{
  "type": "Feature",
  "properties": {
    "addr:full":"Kortrijksestraat 330 Kortrijk West-Vlaanderen 8501",
    "addr:housenumber":"330",
    "addr:postcode":"8501",
    "addr:street":"Kortrijksestraat",
    "iso:country":"BE",
    "sg:address":"Kortrijksestraat 330",
    "sg:city":"Kortrijk",
    "sg:orig_category":"Banken and kredietinstellingen",
    "sg:phone":"+32 56 37 27 72",
    "sg:postcode":"8501",
    "sg:province":"West-Vlaanderen",
    "wof:name":"Groep Argenta",
    "wof:placetype":"venue"
},
  "geometry": {"coordinates":[3.2476799488,50.835521698],"type":"Point"}
}