{
  "type": "Feature",
  "properties": {
    "addr:full":"Rue Des Tanneurs 116 Bruxelles Bruxelles-Capitale 1000",
    "addr:housenumber":"116",
    "addr:postcode":"1000",
    "addr:street":"Rue Des Tanneurs",
    "iso:country":"BE",
    "sg:address":"Rue Des Tanneurs 116",
    "sg:city":"Bruxelles",
    "sg:classifiers":[
        {
            "category":"Building & Trades",
            "subcategory":"Electrical",
            "type":"Services"
        }
    ],
    "sg:phone":"+32 2 510 09 20",
    "sg:postcode":"1000",
    "sg:province":"Bruxelles-Capitale",
    "sg:tags":[
        "tool",
        "electric"
    ],
    "wof:name":"Bosch-huyghe",
    "wof:placetype":"venue"
},
  "geometry": {"coordinates":[4.3453512192,50.8381462097],"type":"Point"}
}