{
  "type": "Feature",
  "properties": {
    "iso:country":"BE",
    "sg:address":"Schelfheidestraat 18ba",
    "sg:city":"Nieuwerkerken",
    "sg:orig_category":"Fruitteelt",
    "sg:phone":"+32 11 68 59 24",
    "sg:postcode":"3850",
    "sg:province":"Limburg",
    "wof:name":"Jozef Jacobs",
    "wof:placetype":"venue"
},
  "geometry": {"coordinates":[5.1829881668,50.875125885],"type":"Point"}
}