{
  "type": "Feature",
  "properties": {
    "addr:full":"Ledebergstraat 109 Gent (ledeberg) Oost-Vlaanderen 9050",
    "addr:housenumber":"109",
    "addr:postcode":"9050",
    "addr:street":"Ledebergstraat",
    "iso:country":"BE",
    "sg:address":"Ledebergstraat 109",
    "sg:city":"Gent (ledeberg)",
    "sg:classifiers":[
        {
            "category":"Health Services",
            "subcategory":"Doctor",
            "type":"Services"
        }
    ],
    "sg:phone":"+32 9 232 32 33",
    "sg:postcode":"9050",
    "sg:province":"Oost-Vlaanderen",
    "sg:tags":[
        "medicinephysicians",
        "surgeon"
    ],
    "wof:name":"Derese Anselm",
    "wof:placetype":"venue"
},
  "geometry": {"coordinates":[3.7418029308,51.0340156555],"type":"Point"}
}