{
  "type": "Feature",
  "properties": {
    "addr:full":"Korte Meer 31 Gent Oost-Vlaanderen 9000",
    "addr:housenumber":"31",
    "addr:postcode":"9000",
    "addr:street":"Korte Meer;Oost-Vlaanderen",
    "iso:country":"BE",
    "sg:address":"Korte Meer 31",
    "sg:city":"Gent",
    "sg:classifiers":[
        {
            "category":"Organizations",
            "subcategory":"Community Association",
            "type":"Services"
        }
    ],
    "sg:phone":"+32 9 330 51 48",
    "sg:postcode":"9000",
    "sg:province":"Oost-Vlaanderen",
    "sg:tags":[
        "cultural"
    ],
    "wof:name":"Vzw La Concorde",
    "wof:placetype":"venue"
},
  "geometry": {"coordinates":[3.7161390781,51.0407676697],"type":"Point"}
}