{
  "type": "Feature",
  "properties": {
    "iso:country":"BE",
    "sg:address":"Lange Steenstraat 6",
    "sg:city":"Kortrijk",
    "sg:classifiers":[
        {
            "category":"Shopping",
            "subcategory":"Clothing, Apparel, & Fashions",
            "type":"Retail Goods"
        }
    ],
    "sg:phone":"+32 56 20 50 60",
    "sg:postcode":"8500",
    "sg:province":"West-Vlaanderen",
    "sg:tags":[
        "v\u00eatements",
        "pour",
        "dame"
    ],
    "wof:name":"We Women",
    "wof:placetype":"venue"
},
  "geometry": {"coordinates":[3.2675259113,50.826133728],"type":"Point"}
}