{
  "type": "Feature",
  "properties": {
    "addr:full":"B\u00c9rismenil 6 La Roche-en-ardenne Luxembourg 6982",
    "addr:housenumber":"6",
    "addr:postcode":"6982",
    "addr:street":"Be\u0301Rismenil",
    "iso:country":"BE",
    "sg:address":"B\u00c9rismenil 6",
    "sg:city":"La Roche-en-ardenne",
    "sg:classifiers":[
        {
            "category":"Restaurant",
            "type":"Food & Drink"
        }
    ],
    "sg:phone":"+32 84 44 45 97",
    "sg:postcode":"6982",
    "sg:province":"Luxembourg",
    "wof:name":"Bon App\u00c9tit",
    "wof:placetype":"venue"
},
  "geometry": {"coordinates":[5.638133049,50.2120666504],"type":"Point"}
}