{
  "type": "Feature",
  "properties": {
    "iso:country":"BE",
    "sg:address":"Chauss\u00c9e De Tongres 447",
    "sg:city":"Li\u00c8ge",
    "sg:orig_category":"Bois Gr. Quincailleries. Mat\u00e9riaux de construction Gr",
    "sg:phone":"+32 4 263 48 31",
    "sg:postcode":"4000",
    "sg:province":"Li\u00e8ge",
    "wof:name":"Guerin",
    "wof:placetype":"venue"
},
  "geometry": {"coordinates":[5.5443148613,50.6772842407],"type":"Point"}
}