{
  "type": "Feature",
  "properties": {
    "addr:full":"Rue Joseph Ii 164 Bruxelles Bruxelles-Capitale 1000",
    "addr:housenumber":"164",
    "addr:postcode":"1000",
    "addr:street":"Rue Joseph Ii",
    "iso:country":"BE",
    "sg:address":"Rue Joseph Ii 164",
    "sg:city":"Bruxelles",
    "sg:classifiers":[
        {
            "category":"Travel",
            "subcategory":"Hotels & Motels",
            "type":"Entertainment"
        }
    ],
    "sg:phone":"+32 2 280 15 49",
    "sg:postcode":"1000",
    "sg:province":"Bruxelles-Capitale",
    "wof:name":"Ambassador R\u00e9sidences",
    "wof:placetype":"venue"
},
  "geometry": {"coordinates":[4.3805179596,50.8441009521],"type":"Point"}
}