{
  "type": "Feature",
  "properties": {
    "addr:full":"Tientjesstraat 5 Kortrijk (bissegem) West-Vlaanderen 8501",
    "addr:housenumber":"5",
    "addr:postcode":"8501",
    "addr:street":"Tientjesstraat",
    "iso:country":"BE",
    "sg:address":"Tientjesstraat 5",
    "sg:city":"Kortrijk (bissegem)",
    "sg:classifiers":[
        {
            "category":"Health Services",
            "subcategory":"Health Practitioner",
            "type":"Services"
        }
    ],
    "sg:phone":"+32 56 35 82 11",
    "sg:postcode":"8501",
    "sg:province":"West-Vlaanderen",
    "sg:tags":[
        "physiotherapist"
    ],
    "wof:name":"Slembrouck Donaat",
    "wof:placetype":"venue"
},
  "geometry": {"coordinates":[3.2278881073,50.8286323547],"type":"Point"}
}