{
  "type": "Feature",
  "properties": {
    "addr:full":"Grote Kouterstraat 21 Berlare Oost-Vlaanderen 9290",
    "addr:housenumber":"21",
    "addr:postcode":"9290",
    "addr:street":"Grote Kouterstraat",
    "iso:country":"BE",
    "sg:address":"Grote Kouterstraat 21",
    "sg:city":"Berlare",
    "sg:orig_category":"Bloemen and planten Bloemen and planten Gh Boomkwekerijen",
    "sg:phone":"+32 9 367 53 36",
    "sg:postcode":"9290",
    "sg:province":"Oost-Vlaanderen",
    "wof:name":"Nieuwdonk",
    "wof:placetype":"venue"
},
  "geometry": {"coordinates":[3.956444025,51.0161933899],"type":"Point"}
}