{
  "type": "Feature",
  "properties": {
    "iso:country":"BE",
    "sg:address":"Stapelstraat 2",
    "sg:city":"Sint-truiden",
    "sg:classifiers":[
        {
            "category":"Food & Beverages",
            "subcategory":"Chocolate",
            "type":"Retail Goods"
        }
    ],
    "sg:phone":"+32 11 58 22 60",
    "sg:postcode":"3800",
    "sg:province":"Limburg",
    "sg:tags":[
        "confectionery",
        "-"
    ],
    "wof:name":"Galler",
    "wof:placetype":"venue"
},
  "geometry": {"coordinates":[5.1835999489,50.8150405884],"type":"Point"}
}