{
  "type": "Feature",
  "properties": {
    "iso:country":"BE",
    "sg:address":"Engelbamp 29",
    "sg:city":"Sint-truiden",
    "sg:orig_category":"Producteurs de fruits",
    "sg:phone":"+32 11 67 13 58",
    "sg:postcode":"3800",
    "sg:province":"Limburg",
    "wof:name":"Stanislas De Biolley",
    "wof:placetype":"venue"
},
  "geometry": {"coordinates":[5.2054181099,50.8437690735],"type":"Point"}
}