{
  "type": "Feature",
  "properties": {
    "iso:country":"BE",
    "sg:address":"Kolonel Begaultlaan 9",
    "sg:city":"Leuven",
    "sg:orig_category":"Meubelzaken, woning- and keukeninrichting Tweedehandsgoederen",
    "sg:phone":"+32 16 23 64 14",
    "sg:postcode":"3012",
    "sg:province":"Vlaams-Brabant",
    "wof:name":"Eco Shop",
    "wof:placetype":"venue"
},
  "geometry": {"coordinates":[4.705947876,50.8910255432],"type":"Point"}
}