{
  "type": "Feature",
  "properties": {
    "addr:full":"Oever 29 Lier Antwerpen 2500",
    "addr:housenumber":"29",
    "addr:postcode":"2500",
    "addr:street":"Oever",
    "iso:country":"BE",
    "sg:address":"Oever 29",
    "sg:city":"Lier",
    "sg:classifiers":[
        {
            "category":"Professional",
            "subcategory":"Management & Consulting",
            "type":"Services"
        }
    ],
    "sg:phone":"+32 3 488 64 92",
    "sg:postcode":"2500",
    "sg:province":"Antwerpen",
    "sg:tags":[
        "tax-consultants"
    ],
    "wof:name":"Meeusen K",
    "wof:placetype":"venue"
},
  "geometry": {"coordinates":[4.5769767761,51.1332206726],"type":"Point"}
}