{
  "type": "Feature",
  "properties": {
    "iso:country":"BE",
    "sg:address":"Rue Jules Delhaize 45-47",
    "sg:city":"Sint-jans-molenbeek/molenbeek-",
    "sg:orig_category":"Travaux d\u00b4installation divers. Lampes and appareils \u00e9lectriques Fab",
    "sg:phone":"+32 2 410 75 44",
    "sg:postcode":"1080",
    "sg:province":"Bruxelles-Capitale",
    "wof:name":"Eclairbel",
    "wof:placetype":"venue"
},
  "geometry": {"coordinates":[4.3220620155,50.8561553955],"type":"Point"}
}