{
  "type": "Feature",
  "properties": {
    "addr:full":"Rue Du Marais \u00c0 Criquelions 8 Mons (grand) Hainaut 7011",
    "addr:housenumber":"8",
    "addr:postcode":"7011",
    "addr:street":"Rue Du Marais A\u0300 Criquelions",
    "iso:country":"BE",
    "sg:address":"Rue Du Marais \u00c0 Criquelions 8",
    "sg:city":"Mons (grand)",
    "sg:orig_category":"S\u00e9curit\u00e9 sociale. Secr\u00e9tariats sociaux",
    "sg:phone":"+32 65 33 68 88",
    "sg:postcode":"7011",
    "sg:province":"Hainaut",
    "wof:name":"Partena",
    "wof:placetype":"venue"
},
  "geometry": {"coordinates":[3.912539959,50.4712982178],"type":"Point"}
}