{
  "type": "Feature",
  "properties": {
    "addr:full":"Wallerode 6a Sankt Vith (wallerode) Li\u00e8ge 4780",
    "addr:housenumber":"6a",
    "addr:postcode":"4780",
    "addr:street":"Wallerode",
    "iso:country":"BE",
    "sg:address":"Wallerode 6a",
    "sg:city":"Sankt Vith (wallerode)",
    "sg:classifiers":[
        {
            "category":"Sports & Exercise",
            "subcategory":"Gym",
            "type":"Entertainment"
        }
    ],
    "sg:phone":"+32 80 22 18 45",
    "sg:postcode":"4780",
    "sg:province":"Li\u00e8ge",
    "sg:tags":[
        "fitness"
    ],
    "wof:name":"Sana Relax",
    "wof:placetype":"venue"
},
  "geometry": {"coordinates":[6.1365971565,50.2856025696],"type":"Point"}
}