{
  "type": "Feature",
  "properties": {
    "iso:country":"BE",
    "sg:address":"Industriepark Bosduin",
    "sg:city":"Kalmthout",
    "sg:classifiers":[
        {
            "category":"Building & Trades",
            "subcategory":"Construction",
            "type":"Services"
        }
    ],
    "sg:phone":"+32 3 666 52 92",
    "sg:postcode":"2920",
    "sg:province":"Antwerpen",
    "sg:tags":[
        "carpenter"
    ],
    "wof:name":"Krijnen Bvba",
    "wof:placetype":"venue"
},
  "geometry": {"coordinates":[4.4750452042,51.3837051392],"type":"Point"}
}