{
  "type": "Feature",
  "properties": {
    "addr:full":"Luxemburglaan 23 Tielt West-Vlaanderen 8700",
    "addr:housenumber":"23",
    "addr:postcode":"8700",
    "addr:street":"Luxemburglaan",
    "iso:country":"BE",
    "sg:address":"Luxemburglaan 23",
    "sg:city":"Tielt",
    "sg:orig_category":"Charpentes and couvertures",
    "sg:phone":"+32 51 40 83 91",
    "sg:postcode":"8700",
    "sg:province":"West-Vlaanderen",
    "wof:name":"Nico Lievrouw",
    "wof:placetype":"venue"
},
  "geometry": {"coordinates":[3.3377130032,51.0020294189],"type":"Point"}
}