{
  "type": "Feature",
  "properties": {
    "iso:country":"BE",
    "sg:address":"Rue De La Grande Bruy\u00c8re 31",
    "sg:city":"Rixensart",
    "sg:classifiers":[
        {
            "category":"Landmark",
            "subcategory":"Marketplace",
            "type":"Public Place"
        }
    ],
    "sg:phone":"+32 2 653 01 63",
    "sg:postcode":"1330",
    "sg:province":"Brabant Wallon",
    "sg:tags":[
        "commerce",
        "gr",
        "equipement",
        "de",
        "pour",
        "divers",
        "biens",
        "location",
        "diver"
    ],
    "wof:name":"Claeys L",
    "wof:placetype":"venue"
},
  "geometry": {"coordinates":[4.5145688057,50.7157897949],"type":"Point"}
}