{
  "type": "Feature",
  "properties": {
    "addr:full":"Rue Muller-tesch 27 Messancy Luxembourg 6780",
    "addr:housenumber":"27",
    "addr:postcode":"6780",
    "addr:street":"Rue Muller-Tesch",
    "iso:country":"BE",
    "sg:address":"Rue Muller-tesch 27",
    "sg:city":"Messancy",
    "sg:orig_category":"Assistances juridiques. Comptables. Conseillers fiscaux",
    "sg:phone":"+32 63 38 67 30",
    "sg:postcode":"6780",
    "sg:province":"Luxembourg",
    "wof:name":"Francy Friob",
    "wof:placetype":"venue"
},
  "geometry": {"coordinates":[5.8102087975,49.595199585],"type":"Point"}
}