{
  "type": "Feature",
  "properties": {
    "addr:full":"Loveldlaan 15 Aalter Oost-Vlaanderen 9880",
    "addr:housenumber":"15",
    "addr:postcode":"9880",
    "addr:street":"Loveldlaan",
    "iso:country":"BE",
    "sg:address":"Loveldlaan 15",
    "sg:city":"Aalter",
    "sg:classifiers":[
        {
            "category":"Health Services",
            "subcategory":"Health Practitioner",
            "type":"Services"
        }
    ],
    "sg:phone":"+32 9 374 34 34",
    "sg:postcode":"9880",
    "sg:province":"Oost-Vlaanderen",
    "sg:tags":[
        "physiotherapist"
    ],
    "wof:name":"Baeckelandt N",
    "wof:placetype":"venue"
},
  "geometry": {"coordinates":[3.4565019608,51.0811347961],"type":"Point"}
}