{
  "type": "Feature",
  "properties": {
    "addr:full":"Nijverheidstraat 112 Oostende West-Vlaanderen 8400",
    "addr:housenumber":"112",
    "addr:postcode":"8400",
    "addr:street":"Nijverheidstraat",
    "iso:country":"BE",
    "sg:address":"Nijverheidstraat 112",
    "sg:city":"Oostende",
    "sg:classifiers":[
        {
            "category":"Personal",
            "subcategory":"Beauty Salon",
            "type":"Services"
        }
    ],
    "sg:phone":"+32 59 50 67 60",
    "sg:postcode":"8400",
    "sg:province":"West-Vlaanderen",
    "sg:tags":[
        "lady",
        "-",
        "hairdressing"
    ],
    "wof:name":"Ch\u00e9rif Betina",
    "wof:placetype":"venue"
},
  "geometry": {"coordinates":[2.9061849117,51.2178192139],"type":"Point"}
}