{
  "type": "Feature",
  "properties": {
    "iso:country":"BE",
    "sg:address":"Rue De Givet 7",
    "sg:city":"Durbuy (grandhan)",
    "sg:classifiers":[
        {
            "category":"Insurance",
            "subcategory":"Insurance Agent",
            "type":"Services"
        }
    ],
    "sg:phone":"+32 86 21 24 96",
    "sg:postcode":"6940",
    "sg:province":"Luxembourg",
    "sg:tags":[
        "broker"
    ],
    "wof:name":"Joris (bureau D'assurances)",
    "wof:placetype":"venue"
},
  "geometry": {"coordinates":[5.4376068115,50.3369369507],"type":"Point"}
}