{
  "type": "Feature",
  "properties": {
    "iso:country":"BE",
    "sg:address":"Stationsstraat 15",
    "sg:city":"Erpe-mere",
    "sg:orig_category":"Boekhouders",
    "sg:phone":"+32 53 63 19 67",
    "sg:postcode":"9420",
    "sg:province":"Oost-Vlaanderen",
    "wof:name":"Patrick Kestemont",
    "wof:placetype":"venue"
},
  "geometry": {"coordinates":[3.9225049019,50.9061088562],"type":"Point"}
}