{
  "type": "Feature",
  "properties": {
    "addr:full":"Rue De N\u00c9chin 30 Tournai Hainaut 7520",
    "addr:housenumber":"30",
    "addr:postcode":"7520",
    "addr:street":"Rue De Ne\u0301Chin",
    "iso:country":"BE",
    "sg:address":"Rue De N\u00c9chin 30",
    "sg:city":"Tournai",
    "sg:orig_category":"Architectes",
    "sg:phone":"+32 69 35 35 15",
    "sg:postcode":"7520",
    "sg:province":"Hainaut",
    "wof:name":"Vandeveugle Eric",
    "wof:placetype":"venue"
},
  "geometry": {"coordinates":[3.281443119,50.6461029053],"type":"Point"}
}