{
  "type": "Feature",
  "properties": {
    "iso:country":"BE",
    "sg:address":"Warandestraat 24",
    "sg:city":"Torhout",
    "sg:classifiers":[
        {
            "category":"Health Services",
            "subcategory":"Doctor",
            "type":"Services"
        }
    ],
    "sg:phone":"+32 50 21 27 33",
    "sg:postcode":"8820",
    "sg:province":"West-Vlaanderen",
    "sg:tags":[
        "medicinephysicians",
        "surgeon"
    ],
    "wof:name":"Hulsbosch J",
    "wof:placetype":"venue"
},
  "geometry": {"coordinates":[3.0900840759,51.0779495239],"type":"Point"}
}