{
  "type": "Feature",
  "properties": {
    "iso:country":"BE",
    "sg:address":"Kuurnsestraat 6",
    "sg:city":"Harelbeke (hulste)",
    "sg:classifiers":[
        {
            "category":"Autos & Motor Vehicles",
            "subcategory":"Motorcycle Sales",
            "type":"Retail Goods"
        }
    ],
    "sg:phone":"+32 56 71 81 41",
    "sg:postcode":"8531",
    "sg:province":"West-Vlaanderen",
    "sg:tags":[
        "scooter",
        "-",
        "moped"
    ],
    "wof:name":"Ampe",
    "wof:placetype":"venue"
},
  "geometry": {"coordinates":[3.298899889,50.8812561035],"type":"Point"}
}