{
  "type": "Feature",
  "properties": {
    "addr:full":"Rue D'amercoeur 55 Li\u00e8ge 1 (li\u00e8ge 2) Li\u00e8ge 4020",
    "addr:housenumber":"55;1;2",
    "addr:postcode":"4020",
    "addr:street":"Rue D'Amercoeur",
    "iso:country":"BE",
    "sg:address":"Rue D'amercoeur 55",
    "sg:city":"Li\u00e8ge 1 (li\u00e8ge 2)",
    "sg:classifiers":[
        {
            "category":"Social Services",
            "subcategory":"Child Care",
            "type":"Services"
        }
    ],
    "sg:phone":"+32 4 349 84 83",
    "sg:postcode":"4020",
    "sg:province":"Li\u00e8ge",
    "sg:tags":[
        "baby",
        "nursery",
        "day",
        "sitting"
    ],
    "wof:name":"Garderie Des Tous Petits Asbl",
    "wof:placetype":"venue"
},
  "geometry": {"coordinates":[5.5902299881,50.6367492676],"type":"Point"}
}