{
  "type": "Feature",
  "properties": {
    "addr:full":"Rue De L'ancienne Gare 25 Libramont-chevigny (libramont) Luxembourg 6800",
    "addr:housenumber":"25",
    "addr:postcode":"6800",
    "addr:street":"Rue De L'Ancienne Gare",
    "iso:country":"BE",
    "sg:address":"Rue De L'ancienne Gare 25",
    "sg:city":"Libramont-chevigny (libramont)",
    "sg:classifiers":[
        {
            "category":"Shopping",
            "subcategory":"Crafts & Fabrics",
            "type":"Retail Goods"
        }
    ],
    "sg:phone":"+32 61 22 37 63",
    "sg:postcode":"6800",
    "sg:province":"Luxembourg",
    "sg:tags":[
        "-",
        "wool",
        "knitting",
        "yarn"
    ],
    "wof:name":"Annell",
    "wof:placetype":"venue"
},
  "geometry": {"coordinates":[5.3766350746,49.9189453125],"type":"Point"}
}