{
  "type": "Feature",
  "properties": {
    "iso:country":"BE",
    "sg:address":"Korenstraat 26",
    "sg:city":"Bilzen",
    "sg:orig_category":"Kapsalons",
    "sg:phone":"+32 89 41 28 68",
    "sg:postcode":"3740",
    "sg:province":"Limburg",
    "wof:name":"Coiffure Liane",
    "wof:placetype":"venue"
},
  "geometry": {"coordinates":[5.5140480995,50.8701400757],"type":"Point"}
}