{
  "type": "Feature",
  "properties": {
    "iso:country":"BE",
    "sg:address":"Moederhoefstraat 188",
    "sg:city":"Lint",
    "sg:orig_category":"D\u00e9m\u00e9nagements",
    "sg:phone":"+32 3 455 49 99",
    "sg:postcode":"2547",
    "sg:province":"Antwerpen",
    "wof:name":"Faes Logistics",
    "wof:placetype":"venue"
},
  "geometry": {"coordinates":[4.4845118523,51.1255302429],"type":"Point"}
}