{
  "type": "Feature",
  "properties": {
    "addr:full":"Rue Du Cornet 75 Bruxelles (etterbeek) Bruxelles-Capitale 1040",
    "addr:housenumber":"75",
    "addr:postcode":"1040",
    "addr:street":"Rue Du Cornet",
    "iso:country":"BE",
    "sg:address":"Rue Du Cornet 75",
    "sg:city":"Bruxelles (etterbeek)",
    "sg:classifiers":[
        {
            "category":"Organizations",
            "subcategory":"Professional Association",
            "type":"Services"
        }
    ],
    "sg:phone":"+32 2 230 69 34",
    "sg:postcode":"1040",
    "sg:province":"Bruxelles-Capitale",
    "sg:tags":[
        "trade-union",
        "federation"
    ],
    "wof:name":"The Association Of Danish Shipbuilders",
    "wof:placetype":"venue"
},
  "geometry": {"coordinates":[4.3855628967,50.8376350403],"type":"Point"}
}