{
  "type": "Feature",
  "properties": {
    "addr:full":"Terlindenhofstraat 110 Antwerpen Antwerpen 2170",
    "addr:housenumber":"110",
    "addr:postcode":"2170",
    "addr:street":"Terlindenhofstraat",
    "iso:country":"BE",
    "sg:address":"Terlindenhofstraat 110",
    "sg:city":"Antwerpen",
    "sg:orig_category":"M\u00e9decins and sp\u00e9cialistes",
    "sg:phone":"+32 3 644 69 73",
    "sg:postcode":"2170",
    "sg:province":"Antwerpen",
    "wof:name":"Consultatiebur.jonge Kind",
    "wof:placetype":"venue"
},
  "geometry": {"coordinates":[4.4505147934,51.246723175],"type":"Point"}
}