{
  "type": "Feature",
  "properties": {
    "iso:country":"BE",
    "sg:address":"Grimaldilaan 97",
    "sg:city":"Stabroek",
    "sg:orig_category":"Experts-comptables. Assistances juridiques. Conseillers fiscaux",
    "sg:phone":"+32 3 568 72 22",
    "sg:postcode":"2940",
    "sg:province":"Antwerpen",
    "wof:name":"R. Verhaeren",
    "wof:placetype":"venue"
},
  "geometry": {"coordinates":[4.3809971809,51.3309288025],"type":"Point"}
}