{
  "type": "Feature",
  "properties": {
    "addr:full":"Maatsheikensstraat 2 Ravels Antwerpen 2381",
    "addr:housenumber":"2",
    "addr:postcode":"2381",
    "addr:street":"Maatsheikensstraat",
    "iso:country":"BE",
    "sg:address":"Maatsheikensstraat 2",
    "sg:city":"Ravels",
    "sg:orig_category":"Producteurs de l\u00e9gumes",
    "sg:phone":"+32 14 65 88 47",
    "sg:postcode":"2381",
    "sg:province":"Antwerpen",
    "wof:name":"Eddie Verstraelen",
    "wof:placetype":"venue"
},
  "geometry": {"coordinates":[5.006374836,51.4099845886],"type":"Point"}
}