{
  "type": "Feature",
  "properties": {
    "iso:country":"BE",
    "sg:address":"Kruipuit 34",
    "sg:city":"Maldegem",
    "sg:orig_category":"Fietsen",
    "sg:phone":"+32 9 377 28 44",
    "sg:postcode":"9991",
    "sg:province":"Oost-Vlaanderen",
    "wof:name":"Luciaan Fore",
    "wof:placetype":"venue"
},
  "geometry": {"coordinates":[3.5161540508,51.1575202942],"type":"Point"}
}