{
  "type": "Feature",
  "properties": {
    "addr:full":"Heikant 113 Zele Oost-Vlaanderen 9240",
    "addr:housenumber":"113",
    "addr:postcode":"9240",
    "addr:street":"Heikant",
    "iso:country":"BE",
    "sg:address":"Heikant 113",
    "sg:city":"Zele",
    "sg:orig_category":"Rundveehouders",
    "sg:phone":"+32 52 44 91 24",
    "sg:postcode":"9240",
    "sg:province":"Oost-Vlaanderen",
    "wof:name":"Dhooghe Leo & Alois",
    "wof:placetype":"venue"
},
  "geometry": {"coordinates":[4.0004029274,51.0623970032],"type":"Point"}
}