{
  "type": "Feature",
  "properties": {
    "iso:country":"BE",
    "sg:address":"Grotstraat 8",
    "sg:city":"Kapelle-op-den-bos",
    "sg:orig_category":"Enseignement maternel and primaire",
    "sg:phone":"+32 15 71 31 78",
    "sg:postcode":"1880",
    "sg:province":"Vlaams-Brabant",
    "wof:name":"Vrije Basisschool",
    "wof:placetype":"venue"
},
  "geometry": {"coordinates":[4.3341989517,51.0134124756],"type":"Point"}
}